{
  "type": "Feature",
  "properties": {
    "addr:full":"15 W Water St Wakefield MA 01880",
    "addr:housenumber":"15",
    "addr:postcode":"01880",
    "addr:street":"W Water St",
    "iso:country":"US",
    "sg:address":"15 W Water St",
    "sg:city":"Wakefield",
    "sg:classifiers":[
        {
            "category":"Health Services",
            "subcategory":"Doctor",
            "type":"Services"
        }
    ],
    "sg:phone":"+1 781 245 4400",
    "sg:postcode":"01880",
    "sg:province":"MA",
    "sg:tags":[
        "dentist"
    ],
    "wof:name":"Joseph P Russo DDS",
    "wof:placetype":"venue"
},
  "geometry": {"coordinates":[-71.074265,42.501215],"type":"Point"}
}