{
  "type": "Feature",
  "properties": {
    "iso:country":"US",
    "sg:address":"157 Seaport Boulevard",
    "sg:city":"Boston",
    "sg:classifiers":[
        {
            "category":"Professional",
            "type":"Services"
        }
    ],
    "sg:phone":"+1 617 563 8334",
    "sg:postcode":"02210",
    "sg:province":"MA",
    "sg:tags":[
        "caterer"
    ],
    "sg:website":"www.sebastians.com/",
    "wof:name":"Sebastian's Catering",
    "wof:placetype":"venue"
},
  "geometry": {"coordinates":[-71.043215,42.350664],"type":"Point"}
}