{
  "type": "Feature",
  "properties": {
    "addr:full": "133 Boston St Salem MA 01970",
    "addr:housenumber": "133",
    "addr:postcode": "01970",
    "addr:street": "Boston St",
    "iso:country": "US",
    "sg:address": "133 Boston St",
    "sg:city": "Salem",
    "sg:classifiers": [
      {
        "category": "Professional",
        "subcategory": "Computer Services",
        "type": "Services"
      }
    ],
    "sg:phone": "+1 978 744 8448",
    "sg:postcode": "01970",
    "sg:province": "MA",
    "sg:tags": [
      "repair"
    ],
    "wof:name": "Computer Service Sales",
    "wof:placetype": "venue"
  },
  "geometry": {"coordinates":[-70.913973,42.521138],"type":"Point"}
}
