{
  "type": "Feature",
  "properties": {
    "addr:full":"19 Foster St Littleton MA 01460",
    "addr:housenumber":"19",
    "addr:postcode":"01460",
    "addr:street":"Foster St",
    "iso:country":"US",
    "sg:address":"19 Foster St",
    "sg:city":"Littleton",
    "sg:classifiers":[
        {
            "category":"Organizations",
            "subcategory":"Religious Organization",
            "type":"Services"
        }
    ],
    "sg:phone":"+1 978 486 3044",
    "sg:postcode":"01460",
    "sg:province":"MA",
    "sg:tags":[
        "place",
        "worship",
        "church"
    ],
    "sg:website":"www.fculittle.org",
    "wof:name":"First Church Unitarian Of Littleton",
    "wof:placetype":"venue"
},
  "geometry": {"coordinates":[-71.484283,42.53788],"type":"Point"}
}