{
  "type": "Feature",
  "properties": {
    "addr:full": "619 Central St Framingham MA 01701",
    "addr:housenumber": "619",
    "addr:postcode": "01701",
    "addr:street": "Central St",
    "iso:country": "US",
    "sg:address": "619 Central St",
    "sg:city": "Framingham",
    "sg:classifiers": [
      {
        "category": "Building \u0026 Trades",
        "subcategory": "Landscaping Services",
        "type": "Services"
      }
    ],
    "sg:phone": "+1 508 405 2244",
    "sg:postcode": "01701",
    "sg:province": "MA",
    "sg:tags": [
      "tree"
    ],
    "wof:name": "Landscape Central Tree",
    "wof:placetype": "venue"
  },
  "geometry": {"coordinates":[-71.4204,42.31152],"type":"Point"}
}
