{
  "type": "Feature",
  "properties": {
    "addr:full": "199 E Bay Rd Osterville MA 02655",
    "addr:housenumber": "199",
    "addr:postcode": "02655",
    "addr:street": "E Bay Rd",
    "iso:country": "US",
    "sg:address": "199 E Bay Rd",
    "sg:city": "Osterville",
    "sg:classifiers": [
      {
        "category": "Home \u0026 Garden",
        "subcategory": "Furniture",
        "type": "Retail Goods"
      }
    ],
    "sg:phone": "+1 508 420 1170",
    "sg:postcode": "02655",
    "sg:province": "MA",
    "sg:tags": [
      "equipment",
      "kitchen",
      "cabinet"
    ],
    "wof:name": "Edward Grant Co",
    "wof:placetype": "venue"
  },
  "geometry": {"coordinates":[-70.37523,41.624559],"type":"Point"}
}
