{
  "type": "Feature",
  "properties": {
    "iso:country":"US",
    "sg:address":"59 Olympic Village Dr",
    "sg:city":"Methuen",
    "sg:classifiers":[
        {
            "category":"Building & Trades",
            "subcategory":"Pest Control",
            "type":"Services"
        }
    ],
    "sg:phone":"+1   ",
    "sg:postcode":"01844",
    "sg:province":"MA",
    "wof:name":"Defense Pest Control",
    "wof:placetype":"venue"
},
  "geometry": {"coordinates":[-71.151793,42.755226],"type":"Point"}
}