{
  "type": "Feature",
  "properties": {
    "iso:country":"US",
    "sg:address":"120 Forest St",
    "sg:city":"Stoneham",
    "sg:classifiers":[
        {
            "category":"Building & Trades",
            "subcategory":"Electrical",
            "type":"Services"
        }
    ],
    "sg:phone":"+1 781 438 1841",
    "sg:postcode":"02180",
    "sg:province":"MA",
    "sg:tags":[
        "electric",
        "contractor"
    ],
    "wof:name":"Frank Cefaioli",
    "wof:placetype":"venue"
},
  "geometry": {"coordinates":[-71.115712,42.490675],"type":"Point"}
}