{
  "type": "Feature",
  "properties": {
    "addr:full": "69 Cummings Park Woburn MA 01801",
    "addr:housenumber": "69",
    "addr:postcode": "01801",
    "addr:street": "Cummings Park",
    "iso:country": "US",
    "sg:address": "69 Cummings Park",
    "sg:city": "Woburn",
    "sg:classifiers": [
      {
        "category": "Organizations",
        "subcategory": "Religious Organization",
        "type": "Services"
      }
    ],
    "sg:phone": "+1 339 298 4355",
    "sg:postcode": "01801",
    "sg:province": "MA",
    "wof:name": "World Revival Church",
    "wof:placetype": "venue"
  },
  "geometry": {"coordinates":[-71.124102,42.497612],"type":"Point"}
}
