{
  "type": "Feature",
  "properties": {
    "iso:country":"US",
    "sg:address":"69 Cummings Park",
    "sg:city":"Woburn",
    "sg:classifiers":[
        {
            "category":"Organizations",
            "subcategory":"Religious Organization",
            "type":"Services"
        }
    ],
    "sg:phone":"+1 339 298 4355",
    "sg:postcode":"01801",
    "sg:province":"MA",
    "wof:name":"World Revival Church",
    "wof:placetype":"venue"
},
  "geometry": {"coordinates":[-71.12410199999999,42.497612],"type":"Point"}
}