{
  "type": "Feature",
  "properties": {
    "addr:full":"1 Trowbridge Rd Buzzards Bay MA 02532",
    "addr:housenumber":"1",
    "addr:postcode":"02532",
    "addr:street":"Trowbridge Rd",
    "iso:country":"US",
    "sg:address":"1 Trowbridge Rd",
    "sg:city":"Buzzards Bay",
    "sg:classifiers":[
        {
            "category":"Health Services",
            "subcategory":"Doctor",
            "type":"Services"
        }
    ],
    "sg:phone":"+1 508 743 0770",
    "sg:postcode":"02532",
    "sg:province":"MA",
    "sg:tags":[
        "medicine",
        "internal"
    ],
    "wof:name":"Nouaime Georgina",
    "wof:placetype":"venue"
},
  "geometry": {"coordinates":[-70.598546,41.740751],"type":"Point"}
}