{
  "type": "Feature",
  "properties": {
    "addr:full": "18 Walker Rd Beverly MA 01915",
    "addr:housenumber": "18",
    "addr:postcode": "01915",
    "addr:street": "Walker Rd",
    "iso:country": "US",
    "sg:address": "18 Walker Rd",
    "sg:city": "Beverly",
    "sg:classifiers": [
      {
        "category": "Professional",
        "subcategory": "Management \u0026 Consulting",
        "type": "Services"
      }
    ],
    "sg:phone": "+1   ",
    "sg:postcode": "01915",
    "sg:province": "MA",
    "wof:name": "Morris Associates",
    "wof:placetype": "venue"
  },
  "geometry": {"coordinates":[-70.847476,42.581997],"type":"Point"}
}
