{
  "type": "Feature",
  "properties": {
    "addr:full":"14 Jonathan Dr Ayer MA 01432",
    "addr:housenumber":"14",
    "addr:postcode":"01432",
    "addr:street":"Jonathan Dr",
    "iso:country":"US",
    "sg:address":"14 Jonathan Dr",
    "sg:city":"Ayer",
    "sg:classifiers":[
        {
            "category":"Shopping",
            "subcategory":"Clothing, Apparel, & Fashions",
            "type":"Retail Goods"
        }
    ],
    "sg:phone":"+1 978 391 4265",
    "sg:postcode":"01432",
    "sg:province":"MA",
    "sg:tags":[
        "shirts-custom",
        "made",
        "alterations-clothing"
    ],
    "wof:name":"American Domani",
    "wof:placetype":"venue"
},
  "geometry": {"coordinates":[-71.586467,42.572026],"type":"Point"}
}