{
  "type": "Feature",
  "properties": {
    "addr:full": "26 Webster St Malden MA 02148",
    "addr:housenumber": "26",
    "addr:postcode": "02148",
    "addr:street": "Webster St",
    "iso:country": "US",
    "sg:address": "26 Webster St",
    "sg:city": "Malden",
    "sg:classifiers": [
      {
        "category": "Retail",
        "subcategory": "Repair Shop",
        "type": "Services"
      }
    ],
    "sg:phone": "+1 781 322 6125",
    "sg:postcode": "02148",
    "sg:province": "MA",
    "sg:tags": [
      "equipment",
      "photographic"
    ],
    "wof:name": "Cellux Electronic Co",
    "wof:placetype": "venue"
  },
  "geometry": {"coordinates":[-71.047611,42.431719],"type":"Point"}
}
