{
  "type": "Feature",
  "properties": {
    "iso:country":"US",
    "sg:address":"35 School St",
    "sg:city":"Acton",
    "sg:classifiers":[
        {
            "category":"Organizations",
            "subcategory":"Religious Organization",
            "type":"Services"
        }
    ],
    "sg:phone":"+1 978 263 2332",
    "sg:postcode":"01720",
    "sg:province":"MA",
    "sg:tags":[
        "church"
    ],
    "sg:website":"www.southactoncc.org",
    "wof:name":"South Acton Congregational Chr",
    "wof:placetype":"venue"
},
  "geometry": {"coordinates":[-71.453962,42.460371],"type":"Point"}
}