{
  "type": "Feature",
  "properties": {
    "iso:country":"US",
    "sg:address":"232 Stockbridge Rd",
    "sg:city":"Great Barrington",
    "sg:classifiers":[
        {
            "category":"Shopping",
            "subcategory":"Crafts & Fabrics",
            "type":"Retail Goods"
        }
    ],
    "sg:phone":"+1 413 528 2473",
    "sg:postcode":"01230",
    "sg:province":"MA",
    "sg:tags":[
        "yarn"
    ],
    "sg:website":"www.wonderful-things.com",
    "wof:name":"Wonderful Things",
    "wof:placetype":"venue"
},
  "geometry": {"coordinates":[-73.346625,42.205101],"type":"Point"}
}