{
  "type": "Feature",
  "properties": {
    "addr:full": "250 Boylston St Boston MA 02116",
    "addr:housenumber": "250",
    "addr:postcode": "02116",
    "addr:street": "Boylston St",
    "iso:country": "US",
    "sg:address": "250 Boylston St",
    "sg:city": "Boston",
    "sg:classifiers": [
      {
        "category": "Shopping",
        "subcategory": "Clothing, Apparel, \u0026 Fashions",
        "type": "Retail Goods"
      }
    ],
    "sg:phone": "+1 617 423 5709",
    "sg:postcode": "02116",
    "sg:province": "MA",
    "sg:tags": [
      "lingerie"
    ],
    "wof:name": "La Perla",
    "wof:placetype": "venue"
  },
  "geometry": {"coordinates":[-71.069236,42.351894],"type":"Point"}
}
