{
  "type": "Feature",
  "properties": {
    "iso:country":"US",
    "sg:address":"813 Berkshire Ave",
    "sg:city":"Indian Orchard",
    "sg:classifiers":[
        {
            "category":"Autos & Motor Vehicles",
            "subcategory":"Automobile Sales",
            "type":"Retail Goods"
        }
    ],
    "sg:phone":"+1 413 543 5071",
    "sg:postcode":"01151",
    "sg:province":"MA",
    "sg:tags":[
        "car",
        "dealer"
    ],
    "wof:name":"Flynn's Auto Sales",
    "wof:placetype":"venue"
},
  "geometry": {"coordinates":[-72.524214,42.140436],"type":"Point"}
}