{
  "type": "Feature",
  "properties": {
    "addr:full": "521 Mount Auburn St Ste 103 Watertown MA 02472",
    "addr:housenumber": "521",
    "addr:postcode": "02472",
    "addr:street": "Mount Auburn St Ste 103",
    "iso:country": "US",
    "sg:address": "521 Mount Auburn St Ste 103",
    "sg:city": "Watertown",
    "sg:classifiers": [
      {
        "category": "Health Services",
        "subcategory": "Doctor",
        "type": "Services"
      }
    ],
    "sg:phone": "+1 617 926 2414",
    "sg:postcode": "02472",
    "sg:province": "MA",
    "wof:name": "Mount Auburn Practice for Women",
    "wof:placetype": "venue"
  },
  "geometry": {"coordinates":[-71.161829,42.370527],"type":"Point"}
}
