{
  "type": "Feature",
  "properties": {
    "iso:country":"US",
    "sg:address":"325 Southfield Dr",
    "sg:city":"Brockton",
    "sg:classifiers":[
        {
            "category":"Building & Trades",
            "subcategory":"Construction",
            "type":"Services"
        }
    ],
    "sg:phone":"+1 781 341 0233",
    "sg:postcode":"02302",
    "sg:province":"MA",
    "sg:tags":[
        "roofing",
        "contractor"
    ],
    "wof:name":"Joe's Home Improvement",
    "wof:placetype":"venue"
},
  "geometry": {"coordinates":[-70.988337,42.065466],"type":"Point"}
}