{
  "type": "Feature",
  "properties": {
    "addr:full": "325 Southfield Dr Brockton MA 02302",
    "addr:housenumber": "325",
    "addr:postcode": "02302",
    "addr:street": "Southfield Dr",
    "iso:country": "US",
    "sg:address": "325 Southfield Dr",
    "sg:city": "Brockton",
    "sg:classifiers": [
      {
        "category": "Building \u0026 Trades",
        "subcategory": "Construction",
        "type": "Services"
      }
    ],
    "sg:phone": "+1 781 341 0233",
    "sg:postcode": "02302",
    "sg:province": "MA",
    "sg:tags": [
      "roofing",
      "contractor"
    ],
    "wof:name": "Joe's Home Improvement",
    "wof:placetype": "venue"
  },
  "geometry": {"coordinates":[-70.988337,42.065466],"type":"Point"}
}
