{
  "type": "Feature",
  "properties": {
    "iso:country":"US",
    "sg:address":"9 Cordaville Rd",
    "sg:city":"Southborough",
    "sg:classifiers":[
        {
            "category":"Organizations",
            "subcategory":"Religious Organization",
            "type":"Services"
        }
    ],
    "sg:phone":"+1 508 624 4006",
    "sg:postcode":"01772",
    "sg:province":"MA",
    "sg:tags":[
        "church"
    ],
    "sg:website":"www.chapelofthecross.com",
    "wof:name":"Chapel Of The Cross",
    "wof:placetype":"venue"
},
  "geometry": {"coordinates":[-71.52945,42.305807],"type":"Point"}
}