{
  "type": "Feature",
  "properties": {
    "addr:full":"144 Turnpike Rd Southborough MA 01772",
    "addr:housenumber":"144",
    "addr:postcode":"01772",
    "addr:street":"Turnpike Rd",
    "iso:country":"US",
    "sg:address":"144 Turnpike Rd",
    "sg:city":"Southborough",
    "sg:classifiers":[
        {
            "category":"Insurance",
            "subcategory":"Insurance Agent",
            "type":"Services"
        }
    ],
    "sg:phone":"+1 508 229 4700",
    "sg:postcode":"01772",
    "sg:province":"MA",
    "wof:name":"Keating Insurance",
    "wof:placetype":"venue"
},
  "geometry": {"coordinates":[-71.517326,42.29263],"type":"Point"}
}