{
  "type": "Feature",
  "properties": {
    "iso:country":"US",
    "sg:address":"7 Sandy Ln",
    "sg:city":"Buzzards Bay",
    "sg:classifiers":[
        {
            "category":"Autos & Motor Vehicles",
            "subcategory":"Fuel & Gas Station",
            "type":"Retail Goods"
        }
    ],
    "sg:phone":"+1 508 759 6890",
    "sg:postcode":"02532",
    "sg:province":"MA",
    "sg:tags":[
        "oil"
    ],
    "wof:name":"Cape Cod Gas",
    "wof:placetype":"venue"
},
  "geometry": {"coordinates":[-70.58785899999999,41.740519],"type":"Point"}
}