{
  "type": "Feature",
  "properties": {
    "addr:full": "7 Sandy Ln Buzzards Bay MA 02532",
    "addr:housenumber": "7",
    "addr:postcode": "02532",
    "addr:street": "Sandy Ln",
    "iso:country": "US",
    "sg:address": "7 Sandy Ln",
    "sg:city": "Buzzards Bay",
    "sg:classifiers": [
      {
        "category": "Autos \u0026 Motor Vehicles",
        "subcategory": "Fuel \u0026 Gas Station",
        "type": "Retail Goods"
      }
    ],
    "sg:phone": "+1 508 759 6890",
    "sg:postcode": "02532",
    "sg:province": "MA",
    "sg:tags": [
      "oil"
    ],
    "wof:name": "Cape Cod Gas",
    "wof:placetype": "venue"
  },
  "geometry": {"coordinates":[-70.587859,41.740519],"type":"Point"}
}
