{
  "type": "Feature",
  "properties": {
    "iso:country":"US",
    "sg:address":"10 Oyster Watcha Rd",
    "sg:city":"Edgartown",
    "sg:classifiers":[
        {
            "category":"Retail",
            "subcategory":"Veterinary Services",
            "type":"Services"
        }
    ],
    "sg:phone":"+1 508 627 3623",
    "sg:postcode":"02539",
    "sg:province":"MA",
    "sg:tags":[
        "veterinarian"
    ],
    "wof:name":"Sea Breeze Veterinary Svc",
    "wof:placetype":"venue"
},
  "geometry": {"coordinates":[-70.605366,41.356626],"type":"Point"}
}