{
  "type": "Feature",
  "properties": {
    "addr:full": "28 Maddigan Way Apt C Middleboro MA 02346",
    "addr:housenumber": "28",
    "addr:postcode": "02346",
    "addr:street": "Maddigan Way Apt C",
    "iso:country": "US",
    "sg:address": "28 Maddigan Way Apt C",
    "sg:city": "Middleboro",
    "sg:classifiers": [
      {
        "category": "Professional",
        "subcategory": "Lawyer \u0026 Legal Services",
        "type": "Services"
      }
    ],
    "sg:phone": "+1 508 264 1012",
    "sg:postcode": "02346",
    "sg:province": "MA",
    "sg:tags": [
      "attorney"
    ],
    "wof:name": "Robert Murphy",
    "wof:placetype": "venue"
  },
  "geometry": {"coordinates":[-70.915793,41.8987],"type":"Point"}
}
