{
  "type": "Feature",
  "properties": {
    "iso:country":"US",
    "sg:address":"28 Maddigan Way Apt C",
    "sg:city":"Middleboro",
    "sg:classifiers":[
        {
            "category":"Professional",
            "subcategory":"Lawyer & Legal Services",
            "type":"Services"
        }
    ],
    "sg:phone":"+1 508 264 1012",
    "sg:postcode":"02346",
    "sg:province":"MA",
    "sg:tags":[
        "attorney"
    ],
    "wof:name":"Robert Murphy",
    "wof:placetype":"venue"
},
  "geometry": {"coordinates":[-70.91579299999999,41.8987],"type":"Point"}
}