{
  "type": "Feature",
  "properties": {
    "addr:full":"1 Boston Pl Ste 1210 Boston MA 02108",
    "addr:housenumber":"1",
    "addr:postcode":"02108",
    "addr:street":"Boston Pl Ste 1210",
    "iso:country":"US",
    "sg:address":"1 Boston Pl Ste 1210",
    "sg:city":"Boston",
    "sg:classifiers":[
        {
            "category":"Professional",
            "subcategory":"Lawyer & Legal Services",
            "type":"Services"
        }
    ],
    "sg:phone":"+1 617 722 9310",
    "sg:postcode":"02108",
    "sg:province":"MA",
    "sg:tags":[
        "attorney",
        "practice"
    ],
    "wof:name":"Law Office Of Robert E Daidione",
    "wof:placetype":"venue"
},
  "geometry": {"coordinates":[-71.058044,42.358955],"type":"Point"}
}