{
  "type": "Feature",
  "properties": {
    "addr:full": "74 Summit Ave Quincy MA 02170",
    "addr:housenumber": "74",
    "addr:postcode": "02170",
    "addr:street": "Summit Ave",
    "iso:country": "US",
    "sg:address": "74 Summit Ave",
    "sg:city": "Quincy",
    "sg:classifiers": [
      {
        "category": "Recreation",
        "type": "Entertainment"
      },
      {
        "category": "Building \u0026 Trades",
        "subcategory": "Landscaping Services",
        "type": "Services"
      }
    ],
    "sg:phone": "+1 617 479 1264",
    "sg:postcode": "02170",
    "sg:province": "MA",
    "sg:tags": [
      "course",
      "lawn",
      "golf",
      "maintenance",
      "grounds"
    ],
    "wof:name": "Furnace Brook Golf Club Proshp",
    "wof:placetype": "venue"
  },
  "geometry": {"coordinates":[-71.025916,42.258805],"type":"Point"}
}
