{
  "type": "Feature",
  "properties": {
    "iso:country":"US",
    "sg:address":"426 Main St",
    "sg:city":"Stoneham",
    "sg:classifiers":[
        {
            "category":"Insurance",
            "subcategory":"Hazard Insurance",
            "type":"Services"
        }
    ],
    "sg:phone":"+1 781 438 1375",
    "sg:postcode":"02180",
    "sg:province":"MA",
    "sg:website":"www.lopriore.com",
    "wof:name":"Lopriore Insurance Agency",
    "wof:placetype":"venue"
},
  "geometry": {"coordinates":[-71.107872,42.404634],"type":"Point"}
}