{
  "type": "Feature",
  "properties": {
    "addr:full":"183 Main St Groveland MA 01834",
    "addr:housenumber":"183",
    "addr:postcode":"01834",
    "addr:street":"Main St",
    "iso:country":"US",
    "sg:address":"183 Main St",
    "sg:city":"Groveland",
    "sg:classifiers":[
        {
            "category":"Government",
            "subcategory":"Office",
            "type":"Public Place"
        }
    ],
    "sg:phone":"+1 978 372 3942",
    "sg:postcode":"01834",
    "sg:province":"MA",
    "sg:tags":[
        "village"
    ],
    "wof:name":"Health Board",
    "wof:placetype":"venue"
},
  "geometry": {"coordinates":[-71.02356899999999,42.767858],"type":"Point"}
}