{
  "type": "Feature",
  "properties": {
    "addr:full":"356 Chestnut Hill Ave Brighton MA 02135",
    "addr:housenumber":"356",
    "addr:postcode":"02135",
    "addr:street":"Chestnut Hill Ave",
    "iso:country":"US",
    "sg:address":"356 Chestnut Hill Ave",
    "sg:city":"Brighton",
    "sg:classifiers":[
        {
            "category":"Restaurant",
            "type":"Food & Drink"
        }
    ],
    "sg:menulink":"http://www.allmenus.com/ma/boston/1140-roggies-brew--grille/menu/",
    "sg:phone":"+1 617 713 0555",
    "sg:postcode":"02135",
    "sg:province":"MA",
    "sg:tags":[
        "sandwich",
        "mexican",
        "salad",
        "food",
        "pub",
        "soup",
        "american",
        "wrap",
        "pizza"
    ],
    "wof:name":"Roggie's Brew & Grille",
    "wof:placetype":"venue"
},
  "geometry": {"coordinates":[-71.151653,42.336727],"type":"Point"}
}