{
  "type": "Feature",
  "properties": {
    "addr:full":"233 State St Belchertown MA 01007",
    "addr:housenumber":"233",
    "addr:postcode":"01007",
    "addr:street":"State St",
    "iso:country":"US",
    "sg:address":"233 State St",
    "sg:city":"Belchertown",
    "sg:classifiers":[
        {
            "category":"Building & Trades",
            "subcategory":"Construction",
            "type":"Services"
        }
    ],
    "sg:phone":"+1   ",
    "sg:postcode":"01007",
    "sg:province":"MA",
    "sg:tags":[
        "house"
    ],
    "wof:name":"Thackeray Builders",
    "wof:placetype":"venue"
},
  "geometry": {"coordinates":[-72.428515,42.268717],"type":"Point"}
}