{
  "type": "Feature",
  "properties": {
    "addr:full": "52 Spring St Williamstown MA 01267",
    "addr:housenumber": "52",
    "addr:postcode": "01267",
    "addr:street": "Spring St",
    "iso:country": "US",
    "sg:address": "52 Spring St",
    "sg:city": "Williamstown",
    "sg:classifiers": [
      {
        "category": "Food \u0026 Beverages",
        "subcategory": "Liquor \u0026 Beverages",
        "type": "Retail Goods"
      }
    ],
    "sg:phone": "+1 413 458 5948",
    "sg:postcode": "01267",
    "sg:province": "MA",
    "wof:name": "West's Wine \u0026 Sprits",
    "wof:placetype": "venue"
  },
  "geometry": {"coordinates":[-73.204066,42.71065],"type":"Point"}
}
