{
  "type": "Feature",
  "properties": {
    "iso:country":"US",
    "sg:address":"52 Spring St",
    "sg:city":"Williamstown",
    "sg:classifiers":[
        {
            "category":"Food & Beverages",
            "subcategory":"Liquor & Beverages",
            "type":"Retail Goods"
        }
    ],
    "sg:phone":"+1 413 458 5948",
    "sg:postcode":"01267",
    "sg:province":"MA",
    "wof:name":"West's Wine & Sprits",
    "wof:placetype":"venue"
},
  "geometry": {"coordinates":[-73.204066,42.71065],"type":"Point"}
}