{
  "type": "Feature",
  "properties": {
    "addr:full": "31 Clinton St Mansfield MA 02048",
    "addr:housenumber": "31",
    "addr:postcode": "02048",
    "addr:street": "Clinton St",
    "iso:country": "US",
    "sg:address": "31 Clinton St",
    "sg:city": "Mansfield",
    "sg:classifiers": [
      {
        "category": "Professional",
        "subcategory": "Art Services",
        "type": "Services"
      }
    ],
    "sg:phone": "+1   ",
    "sg:postcode": "02048",
    "sg:province": "MA",
    "sg:tags": [
      "commercial",
      "design"
    ],
    "wof:name": "Jean Kara Graphic Design",
    "wof:placetype": "venue"
  },
  "geometry": {"coordinates":[-71.213364,42.032653],"type":"Point"}
}
