{
  "type": "Feature",
  "properties": {
    "addr:full": "500 Elm St Kingston MA 02364",
    "addr:housenumber": "500",
    "addr:postcode": "02364",
    "addr:street": "Elm St",
    "iso:country": "US",
    "sg:address": "500 Elm St",
    "sg:city": "Kingston",
    "sg:classifiers": [
      {
        "category": "Building \u0026 Trades",
        "subcategory": "Construction",
        "type": "Services"
      }
    ],
    "sg:phone": "+1   ",
    "sg:postcode": "02364",
    "sg:province": "MA",
    "sg:tags": [
      "residential"
    ],
    "wof:name": "Dr \u0026 Son Construction Co",
    "wof:placetype": "venue"
  },
  "geometry": {"coordinates":[-70.761407,41.970577],"type":"Point"}
}
