{
  "type": "Feature",
  "properties": {
    "iso:country":"US",
    "sg:address":"410 Broadway",
    "sg:city":"Lynnfield",
    "sg:classifiers":[
        {
            "category":"Real Estate",
            "subcategory":"Architect",
            "type":"Services"
        }
    ],
    "sg:phone":"+1 781 596 2781",
    "sg:postcode":"01940",
    "sg:province":"MA",
    "sg:tags":[
        "architectural"
    ],
    "wof:name":"Gmg Group Incnst Corp",
    "wof:placetype":"venue"
},
  "geometry": {"coordinates":[-71.005518,42.513275],"type":"Point"}
}