{
  "type": "Feature",
  "properties": {
    "addr:full": "85 Mansfield Ave Norton MA 02766",
    "addr:housenumber": "85",
    "addr:postcode": "02766",
    "addr:street": "Mansfield Ave",
    "iso:country": "US",
    "sg:address": "85 Mansfield Ave",
    "sg:city": "Norton",
    "sg:classifiers": [
      {
        "category": "Real Estate",
        "subcategory": "Real Estate Services",
        "type": "Services"
      },
      {
        "category": "Real Estate",
        "subcategory": "Real Estate Agent",
        "type": "Services"
      }
    ],
    "sg:phone": "+1 508 285 2900",
    "sg:postcode": "02766",
    "sg:province": "MA",
    "sg:tags": [
      "buyer",
      "broker"
    ],
    "wof:name": "Mcc Realty Inc",
    "wof:placetype": "venue"
  },
  "geometry": {"coordinates":[-71.197032,41.975317],"type":"Point"}
}
