{
  "type": "Feature",
  "properties": {
    "addr:full": "1112 Blue Hill Avenue Dorchester Center MA 02124",
    "addr:housenumber": "1112",
    "addr:postcode": "02124",
    "addr:street": "Blue Hill Avenue",
    "iso:country": "US",
    "sg:address": "1112 Blue Hill Avenue",
    "sg:city": "Dorchester Center",
    "sg:classifiers": [
      {
        "category": "Personal",
        "subcategory": "Barber",
        "type": "Services"
      }
    ],
    "sg:phone": "+1 617 436 9119",
    "sg:postcode": "02124",
    "sg:province": "MA",
    "wof:name": "Mattapan's Finest Barber",
    "wof:placetype": "venue"
  },
  "geometry": {"coordinates":[-71.090806,42.286332],"type":"Point"}
}
