{
  "type": "Feature",
  "properties": {
    "iso:country":"US",
    "sg:address":"44 Belchertown Rd",
    "sg:city":"Amherst",
    "sg:classifiers":[
        {
            "category":"Shopping",
            "subcategory":"Computers & Home Electronics",
            "type":"Retail Goods"
        }
    ],
    "sg:phone":"+1 413 253 7430",
    "sg:postcode":"01002",
    "sg:province":"MA",
    "sg:tags":[
        "software"
    ],
    "sg:website":"www.chiliad.com",
    "wof:name":"Chiliad Publishing",
    "wof:placetype":"venue"
},
  "geometry": {"coordinates":[-72.49877600000001,42.371715],"type":"Point"}
}