{
  "type": "Feature",
  "properties": {
    "addr:full": "44 Belchertown Rd Amherst MA 01002",
    "addr:housenumber": "44",
    "addr:postcode": "01002",
    "addr:street": "Belchertown Rd",
    "iso:country": "US",
    "sg:address": "44 Belchertown Rd",
    "sg:city": "Amherst",
    "sg:classifiers": [
      {
        "category": "Shopping",
        "subcategory": "Computers \u0026 Home Electronics",
        "type": "Retail Goods"
      }
    ],
    "sg:phone": "+1 413 253 7430",
    "sg:postcode": "01002",
    "sg:province": "MA",
    "sg:tags": [
      "software"
    ],
    "sg:website": "www.chiliad.com",
    "wof:name": "Chiliad Publishing",
    "wof:placetype": "venue"
  },
  "geometry": {"coordinates":[-72.498776,42.371715],"type":"Point"}
}
