{
  "type": "Feature",
  "properties": {
    "addr:full":"31 Shady Hill Rd Newton MA 02461",
    "addr:housenumber":"31",
    "addr:postcode":"02461",
    "addr:street":"Shady Hill Rd",
    "iso:country":"US",
    "sg:address":"31 Shady Hill Rd",
    "sg:city":"Newton",
    "sg:classifiers":[
        {
            "category":"Professional",
            "subcategory":"Business Services",
            "type":"Services"
        }
    ],
    "sg:phone":"+1 617 969 9099",
    "sg:postcode":"02461",
    "sg:province":"MA",
    "sg:tags":[
        "interior",
        "consultant",
        "design",
        "decorator"
    ],
    "wof:name":"Sandler-Dick Assoc",
    "wof:placetype":"venue"
},
  "geometry": {"coordinates":[-71.203678,42.316945],"type":"Point"}
}