{
  "type": "Feature",
  "properties": {
    "addr:full":"5 Babcock Street Brookline MA 02446",
    "addr:housenumber":"5",
    "addr:postcode":"02446",
    "addr:street":"Babcock Street",
    "iso:country":"US",
    "sg:address":"5 Babcock Street",
    "sg:city":"Brookline",
    "sg:classifiers":[
        {
            "category":"Personal",
            "subcategory":"Nail Salon",
            "type":"Services"
        }
    ],
    "sg:phone":"+1 617 264 9383",
    "sg:postcode":"02446",
    "sg:province":"MA",
    "wof:name":"Nouveau Nails",
    "wof:placetype":"venue"
},
  "geometry": {"coordinates":[-71.12316199999999,42.343705],"type":"Point"}
}