{
  "type": "Feature",
  "properties": {
    "iso:country":"US",
    "sg:address":"1 Walcott Rd",
    "sg:city":"Danvers",
    "sg:classifiers":[
        {
            "category":"Building & Trades",
            "subcategory":"Plumbing",
            "type":"Services"
        }
    ],
    "sg:phone":"+1 978 532 0206",
    "sg:postcode":"01923",
    "sg:province":"MA",
    "sg:tags":[
        "conditioning",
        "air",
        "system",
        "contractor"
    ],
    "wof:name":"Environmental Temp Control",
    "wof:placetype":"venue"
},
  "geometry": {"coordinates":[-70.94464499999999,42.549133],"type":"Point"}
}