{
  "type": "Feature",
  "properties": {
    "iso:country":"US",
    "sg:address":"17 Beecher St",
    "sg:city":"East Weymouth",
    "sg:classifiers":[
        {
            "category":"Professional",
            "type":"Services"
        }
    ],
    "sg:phone":"+1   ",
    "sg:postcode":"02189",
    "sg:province":"MA",
    "wof:name":"Dropo Sculpture",
    "wof:placetype":"venue"
},
  "geometry": {"coordinates":[-70.941881,42.20216],"type":"Point"}
}