{
  "type": "Feature",
  "properties": {
    "addr:full":"151 Merrimac St Ste 600 Boston MA 02114",
    "addr:housenumber":"151",
    "addr:postcode":"02114",
    "addr:street":"Merrimac St Ste 600",
    "iso:country":"US",
    "sg:address":"151 Merrimac St Ste 600",
    "sg:city":"Boston",
    "sg:classifiers":[
        {
            "category":"Education",
            "subcategory":"University",
            "type":"Public Place"
        }
    ],
    "sg:phone":"+1 617 367 4871",
    "sg:postcode":"02114",
    "sg:province":"MA",
    "sg:tags":[
        "college"
    ],
    "wof:name":"Tufts University",
    "wof:placetype":"venue"
},
  "geometry": {"coordinates":[-71.062698,42.363899],"type":"Point"}
}