{
  "type": "Feature",
  "properties": {
    "addr:full":"20 College Ave Somerville MA 02144",
    "addr:housenumber":"20",
    "addr:postcode":"02144",
    "addr:street":"College Ave",
    "iso:country":"US",
    "sg:address":"20 College Ave",
    "sg:city":"Somerville",
    "sg:classifiers":[
        {
            "category":"Deli",
            "type":"Food & Drink"
        }
    ],
    "sg:phone":"+1 617 629 4444",
    "sg:postcode":"02144",
    "sg:province":"MA",
    "wof:name":"Deli-icious",
    "wof:placetype":"venue"
},
  "geometry": {"coordinates":[-71.121948,42.397144],"type":"Point"}
}