{
  "type": "Feature",
  "properties": {
    "addr:full":"34 Walden St Concord MA 01742",
    "addr:housenumber":"34",
    "addr:postcode":"01742",
    "addr:street":"Walden St",
    "iso:country":"US",
    "sg:address":"34 Walden St",
    "sg:city":"Concord",
    "sg:classifiers":[
        {
            "category":"Government",
            "subcategory":"Post Office",
            "type":"Public Place"
        }
    ],
    "sg:phone":"+1 978 000 1111",
    "sg:postcode":"01742",
    "sg:province":"MA",
    "wof:name":"US Post Office",
    "wof:placetype":"venue"
},
  "geometry": {"coordinates":[-71.35033799999999,42.45986],"type":"Point"}
}