{
  "type": "Feature",
  "properties": {
    "addr:full": "459 Broadway Cambridge MA 02138",
    "addr:housenumber": "459",
    "addr:postcode": "02138",
    "addr:street": "Broadway",
    "iso:country": "US",
    "sg:address": "459 Broadway",
    "sg:city": "Cambridge",
    "sg:classifiers": [
      {
        "category": "Education",
        "subcategory": "Library",
        "type": "Public Place"
      }
    ],
    "sg:phone": "+1 617 349 6778",
    "sg:postcode": "02138",
    "sg:province": "MA",
    "sg:tags": [
      "special",
      "interest"
    ],
    "wof:name": "Cambridge Teachers Resrce Ctr",
    "wof:placetype": "venue"
  },
  "geometry": {"coordinates":[-71.112777,42.373968],"type":"Point"}
}
