{
  "type": "Feature",
  "properties": {
    "iso:country":"US",
    "sg:address":"800 Massachusetts Avenue",
    "sg:city":"Arlington",
    "sg:classifiers":[
        {
            "category":"Health Services",
            "subcategory":"Dentist",
            "type":"Services"
        }
    ],
    "sg:phone":"+1 781 648 9200",
    "sg:postcode":"02476",
    "sg:province":"MA",
    "sg:tags":[
        "orthodontist"
    ],
    "sg:website":"www.varalloortho.com",
    "wof:name":"Varallo Orthodontics",
    "wof:placetype":"venue"
},
  "geometry": {"coordinates":[-71.159133,42.41659],"type":"Point"}
}