{
  "type": "Feature",
  "properties": {
    "addr:full":"1902 Massachusetts Avenue Cambridge MA 02140",
    "addr:housenumber":"1902",
    "addr:postcode":"02140",
    "addr:street":"Massachusetts Avenue",
    "iso:country":"US",
    "sg:address":"1902 Massachusetts Avenue",
    "sg:city":"Cambridge",
    "sg:classifiers":[
        {
            "category":"Shopping",
            "subcategory":"Hobbies, Toys, & Games",
            "type":"Retail Goods"
        },
        {
            "category":"Personal",
            "type":"Services"
        }
    ],
    "sg:phone":"+1 617 661 5899",
    "sg:postcode":"02140",
    "sg:province":"MA",
    "sg:tags":[
        "shop",
        "hobby",
        "planning",
        "wedding"
    ],
    "wof:name":"The Atholl Brose",
    "wof:placetype":"venue"
},
  "geometry": {"coordinates":[-71.119587,42.388919],"type":"Point"}
}