{
  "type": "Feature",
  "properties": {
    "addr:full": "250 Colonel Bell Dr Brockton MA 02301",
    "addr:housenumber": "250",
    "addr:postcode": "02301",
    "addr:street": "Colonel Bell Dr",
    "iso:country": "US",
    "sg:address": "250 Colonel Bell Dr",
    "sg:city": "Brockton",
    "sg:classifiers": [
      {
        "category": "Real Estate",
        "subcategory": "Real Estate Operator",
        "type": "Services"
      }
    ],
    "sg:phone": "+1 508 583 5513",
    "sg:postcode": "02301",
    "sg:province": "MA",
    "sg:tags": [
      "condominium"
    ],
    "wof:name": "Fieldside Gardens Condominiums",
    "wof:placetype": "venue"
  },
  "geometry": {"coordinates":[-71.03975,42.098409],"type":"Point"}
}
