{
  "type": "Feature",
  "properties": {
    "addr:full": "73 Main St Charlestown MA 02129",
    "addr:housenumber": "73",
    "addr:postcode": "02129",
    "addr:street": "Main St",
    "iso:country": "US",
    "ovtr:label": "Tangierino, 83 Main St Charlestown MA US",
    "ovtr:similarity": 2.4576098918914795,
    "sg:address": "73 Main St",
    "sg:city": "Charlestown",
    "sg:classifiers": [
      {
        "category": "Bars \u0026 Pubs",
        "subcategory": "Hookah Bar",
        "type": "Food \u0026 Drink"
      },
      {
        "category": "Restaurant",
        "type": "Food \u0026 Drink"
      },
      {
        "category": "Retail",
        "subcategory": "Event Space",
        "type": "Services"
      }
    ],
    "sg:phone": "+1 617 242 6009",
    "sg:postcode": "02129",
    "sg:province": "MA",
    "sg:tags": [
      "venue",
      "moroccan"
    ],
    "sg:website": "www.tangierino.com",
    "wof:name": "Tangierino",
    "wof:placetype": "venue"
  },
  "geometry": {"coordinates":[-71.06262,42.373864],"type":"Point"}
}
