{
  "type": "Feature",
  "properties": {
    "iso:country":"US",
    "sg:address":"73 Main St",
    "sg:city":"Charlestown",
    "sg:classifiers":[
        {
            "category":"Bars & Pubs",
            "subcategory":"Hookah Bar",
            "type":"Food & Drink"
        },
        {
            "category":"Restaurant",
            "type":"Food & Drink"
        },
        {
            "category":"Retail",
            "subcategory":"Event Space",
            "type":"Services"
        }
    ],
    "sg:phone":"+1 617 242 6009",
    "sg:postcode":"02129",
    "sg:province":"MA",
    "sg:tags":[
        "venue",
        "moroccan"
    ],
    "sg:website":"www.tangierino.com",
    "wof:name":"Tangierino",
    "wof:placetype":"venue"
},
  "geometry": {"coordinates":[-71.06262,42.373864],"type":"Point"}
}