{
  "type": "Feature",
  "properties": {
    "addr:full": "436 Pleasant St Brockton MA 02301",
    "addr:housenumber": "436",
    "addr:postcode": "02301",
    "addr:street": "Pleasant St",
    "iso:country": "US",
    "sg:address": "436 Pleasant St",
    "sg:city": "Brockton",
    "sg:classifiers": [
      {
        "category": "Real Estate",
        "subcategory": "Real Estate Agent",
        "type": "Services"
      }
    ],
    "sg:phone": "+1 508 559 9300",
    "sg:postcode": "02301",
    "sg:province": "MA",
    "wof:name": "Prime Rentals",
    "wof:placetype": "venue"
  },
  "geometry": {"coordinates":[-71.036832,42.088655],"type":"Point"}
}
