{
  "type": "Feature",
  "properties": {
    "iso:country":"US",
    "sg:address":"5 Ballard St",
    "sg:city":"Randolph",
    "sg:classifiers":[
        {
            "category":"Building & Trades",
            "subcategory":"Plumbing",
            "type":"Services"
        }
    ],
    "sg:phone":"+1 781 986 8801",
    "sg:postcode":"02368",
    "sg:province":"MA",
    "sg:tags":[
        "contractor"
    ],
    "wof:name":"O'neill Kevin W Plumbing",
    "wof:placetype":"venue"
},
  "geometry": {"coordinates":[-71.06109600000001,42.1991],"type":"Point"}
}