{
  "type": "Feature",
  "properties": {
    "addr:full":"9 Bonazzoli Ave Hudson MA 01749",
    "addr:housenumber":"9",
    "addr:postcode":"01749",
    "addr:street":"Bonazzoli Ave",
    "iso:country":"US",
    "sg:address":"9 Bonazzoli Ave",
    "sg:city":"Hudson",
    "sg:classifiers":[
        {
            "category":"Building & Trades",
            "subcategory":"Cleaning & Sanitation",
            "type":"Services"
        }
    ],
    "sg:phone":"+1 978 568 0393",
    "sg:postcode":"01749",
    "sg:province":"MA",
    "sg:tags":[
        "janitor"
    ],
    "wof:name":"Cleantech",
    "wof:placetype":"venue"
},
  "geometry": {"coordinates":[-71.548632,42.391861],"type":"Point"}
}