{
  "type": "Feature",
  "properties": {
    "addr:full": "158 Colony Place Rd Plymouth MA 02360",
    "addr:housenumber": "158",
    "addr:postcode": "02360",
    "addr:street": "Colony Place Rd",
    "iso:country": "US",
    "ovtr:label": "Cold Stone Creamery, 158 Colony Place Rd Plymouth MA US",
    "ovtr:similarity": 2.1996569633483887,
    "sg:address": "158 Colony Place Rd",
    "sg:city": "Plymouth",
    "sg:classifiers": [
      {
        "category": "Ice Cream",
        "type": "Food \u0026 Drink"
      }
    ],
    "sg:phone": "+1 508 746 7737",
    "sg:postcode": "02360",
    "sg:province": "MA",
    "sg:tags": [
      "frozen",
      "yogurt"
    ],
    "sg:website": "www.coldstonecreamery.com",
    "wof:name": "Cold Stone Creamery",
    "wof:placetype": "venue"
  },
  "geometry": {"coordinates":[-70.71261,41.954966],"type":"Point"}
}
