{
  "type": "Feature",
  "properties": {
    "iso:country":"US",
    "sg:address":"158 Colony Place Rd",
    "sg:city":"Plymouth",
    "sg:classifiers":[
        {
            "category":"Ice Cream",
            "type":"Food & Drink"
        }
    ],
    "sg:phone":"+1 508 746 7737",
    "sg:postcode":"02360",
    "sg:province":"MA",
    "sg:tags":[
        "frozen",
        "yogurt"
    ],
    "sg:website":"www.coldstonecreamery.com",
    "wof:name":"Cold Stone Creamery",
    "wof:placetype":"venue"
},
  "geometry": {"coordinates":[-70.71261,41.954966],"type":"Point"}
}