{
  "type": "Feature",
  "properties": {
    "iso:country":"US",
    "sg:address":"75 Lanewood Ave",
    "sg:city":"Framingham",
    "sg:classifiers":[
        {
            "category":"Retail",
            "subcategory":"Photofinishing",
            "type":"Services"
        }
    ],
    "sg:phone":"+1 508 875 4880",
    "sg:postcode":"01701",
    "sg:province":"MA",
    "sg:tags":[
        "photo",
        "restoration",
        "retouching",
        "laboratory"
    ],
    "wof:name":"Quick Photo",
    "wof:placetype":"venue"
},
  "geometry": {"coordinates":[-71.482321,42.32178],"type":"Point"}
}