{
  "type": "Feature",
  "properties": {
    "addr:full": "102 Broad St. Boston MA 02110",
    "addr:housenumber": "102",
    "addr:postcode": "02110",
    "addr:street": "Broad St.",
    "iso:country": "US",
    "sg:address": "102 Broad St.",
    "sg:city": "Boston",
    "sg:classifiers": [
      {
        "category": "Bars \u0026 Pubs",
        "type": "Food \u0026 Drink"
      },
      {
        "category": "Restaurant",
        "type": "Food \u0026 Drink"
      }
    ],
    "sg:phone": "+1 617 542 8469",
    "sg:postcode": "02110",
    "sg:province": "MA",
    "sg:tags": [
      "grill",
      "brew",
      "tavern"
    ],
    "wof:name": "The Littlest Bar",
    "wof:placetype": "venue"
  },
  "geometry": {"coordinates":[-71.052228,42.357316],"type":"Point"}
}
