{
  "type": "Feature",
  "properties": {
    "iso:country":"US",
    "sg:address":"102 Broad St.",
    "sg:city":"Boston",
    "sg:classifiers":[
        {
            "category":"Bars & Pubs",
            "type":"Food & Drink"
        },
        {
            "category":"Restaurant",
            "type":"Food & Drink"
        }
    ],
    "sg:phone":"+1 617 542 8469",
    "sg:postcode":"02110",
    "sg:province":"MA",
    "sg:tags":[
        "grill",
        "brew",
        "tavern"
    ],
    "wof:name":"The Littlest Bar",
    "wof:placetype":"venue"
},
  "geometry": {"coordinates":[-71.052228,42.357316],"type":"Point"}
}