{
  "type": "Feature",
  "properties": {
    "addr:full": "165 Chandler St Worcester MA 01609",
    "addr:housenumber": "165",
    "addr:postcode": "01609",
    "addr:street": "Chandler St",
    "iso:country": "US",
    "sg:address": "165 Chandler St",
    "sg:city": "Worcester",
    "sg:classifiers": [
      {
        "category": "Shopping",
        "subcategory": "Bicycles \u0026 Sporting Goods",
        "type": "Retail Goods"
      }
    ],
    "sg:phone": "+1 508 757 3754",
    "sg:postcode": "01609",
    "sg:province": "MA",
    "wof:name": "Barney's Bicycle",
    "wof:placetype": "venue"
  },
  "geometry": {"coordinates":[-71.814196,42.260655],"type":"Point"}
}
