{
  "type": "Feature",
  "properties": {
    "iso:country":"US",
    "sg:address":"165 Chandler St",
    "sg:city":"Worcester",
    "sg:classifiers":[
        {
            "category":"Shopping",
            "subcategory":"Bicycles & Sporting Goods",
            "type":"Retail Goods"
        }
    ],
    "sg:phone":"+1 508 757 3754",
    "sg:postcode":"01609",
    "sg:province":"MA",
    "wof:name":"Barney's Bicycle",
    "wof:placetype":"venue"
},
  "geometry": {"coordinates":[-71.814196,42.260655],"type":"Point"}
}