{
  "type": "Feature",
  "properties": {
    "iso:country":"US",
    "sg:address":"44 Old Powder House Rd",
    "sg:city":"Lakeville",
    "sg:classifiers":[
        {
            "category":"Manufacturing",
            "subcategory":"Tools & Machinery",
            "type":"Manufacturing & Wholesale Goods"
        }
    ],
    "sg:phone":"+1 508 947 8704",
    "sg:postcode":"02347",
    "sg:province":"MA",
    "sg:tags":[
        "equipment",
        "electric",
        "heating"
    ],
    "wof:name":"Radiant Heat Products Inc",
    "wof:placetype":"venue"
},
  "geometry": {"coordinates":[-70.94704,41.837249],"type":"Point"}
}