{
  "type": "Feature",
  "properties": {
    "addr:full": "44 Old Powder House Rd Lakeville MA 02347",
    "addr:housenumber": "44",
    "addr:postcode": "02347",
    "addr:street": "Old Powder House Rd",
    "iso:country": "US",
    "sg:address": "44 Old Powder House Rd",
    "sg:city": "Lakeville",
    "sg:classifiers": [
      {
        "category": "Manufacturing",
        "subcategory": "Tools \u0026 Machinery",
        "type": "Manufacturing \u0026 Wholesale Goods"
      }
    ],
    "sg:phone": "+1 508 947 8704",
    "sg:postcode": "02347",
    "sg:province": "MA",
    "sg:tags": [
      "equipment",
      "electric",
      "heating"
    ],
    "wof:name": "Radiant Heat Products Inc",
    "wof:placetype": "venue"
  },
  "geometry": {"coordinates":[-70.94704,41.837249],"type":"Point"}
}
