{
  "type": "Feature",
  "properties": {
    "iso:country":"US",
    "sg:address":"4100 State Hwy",
    "sg:city":"Eastham",
    "sg:classifiers":[
        {
            "category":"Restaurant",
            "type":"Food & Drink"
        }
    ],
    "sg:phone":"+1 508 255 2650",
    "sg:postcode":"02642",
    "sg:province":"MA",
    "sg:tags":[
        "seafood",
        "pan",
        "american",
        "chinese",
        "asian"
    ],
    "wof:name":"Sea Dog Restaurant & Saloon",
    "wof:placetype":"venue"
},
  "geometry": {"coordinates":[-69.987584,41.849254],"type":"Point"}
}