{
  "type": "Feature",
  "properties": {
    "addr:full":"21 Highland Ave Ste 16 Newburyport MA 01950",
    "addr:housenumber":"21",
    "addr:postcode":"01950",
    "addr:street":"Highland Ave Ste 16",
    "iso:country":"US",
    "sg:address":"21 Highland Ave Ste 16",
    "sg:city":"Newburyport",
    "sg:classifiers":[
        {
            "category":"Health Services",
            "subcategory":"Doctor",
            "type":"Services"
        }
    ],
    "sg:phone":"+1 978 462 7555",
    "sg:postcode":"01950",
    "sg:province":"MA",
    "sg:tags":[
        "physician",
        "surgeons",
        "orthopedics",
        "medicine",
        "surgeon",
        "sport"
    ],
    "wof:name":"Ford, James J, Md - Seacoast Orthopedic Assoc",
    "wof:placetype":"venue"
},
  "geometry": {"coordinates":[-70.890266,42.81464],"type":"Point"}
}