{
  "type": "Feature",
  "properties": {
    "iso:country":"US",
    "sg:address":"66 Laurel Dr",
    "sg:city":"Needham",
    "sg:classifiers":[
        {
            "category":"Freight",
            "type":"Transportation"
        }
    ],
    "sg:phone":"+1 781 449 4339",
    "sg:postcode":"02492",
    "sg:province":"MA",
    "sg:tags":[
        "mover"
    ],
    "wof:name":"S C Merola",
    "wof:placetype":"venue"
},
  "geometry": {"coordinates":[-71.232085,42.271793],"type":"Point"}
}