{
  "type": "Feature",
  "properties": {
    "iso:country":"US",
    "sg:address":"15 Mary Moore Beatty Cir",
    "sg:city":"Mattapan",
    "sg:classifiers":[
        {
            "category":"Real Estate",
            "subcategory":"Real Estate Agent",
            "type":"Services"
        }
    ],
    "sg:phone":"+1 617 988 5119",
    "sg:postcode":"02126",
    "sg:province":"MA",
    "sg:tags":[
        "authorities",
        "housing"
    ],
    "wof:name":"Boston Housing Authority",
    "wof:placetype":"venue"
},
  "geometry": {"coordinates":[-71.07893799999999,42.271863],"type":"Point"}
}