{
  "type": "Feature",
  "properties": {
    "addr:full":"1 International Place Boston MA 02110",
    "addr:housenumber":"1",
    "addr:postcode":"02110",
    "addr:street":"International Place",
    "iso:country":"US",
    "sg:address":"1 International Place",
    "sg:city":"Boston",
    "sg:classifiers":[
        {
            "category":"Professional",
            "subcategory":"Lawyer & Legal Services",
            "type":"Services"
        }
    ],
    "sg:phone":"+1 617 951 7180",
    "sg:postcode":"02110",
    "sg:province":"MA",
    "wof:name":"Roberts Keith A Lwyr",
    "wof:placetype":"venue"
},
  "geometry": {"coordinates":[-71.05258000000001,42.35628],"type":"Point"}
}