{
  "type": "Feature",
  "properties": {
    "addr:full": "44 Garden St Everett MA 02149",
    "addr:housenumber": "44",
    "addr:postcode": "02149",
    "addr:street": "Garden St",
    "iso:country": "US",
    "sg:address": "44 Garden St",
    "sg:city": "Everett",
    "sg:classifiers": [
      {
        "category": "Real Estate",
        "subcategory": "Real Estate Services",
        "type": "Services"
      },
      {
        "category": "Real Estate",
        "subcategory": "Real Estate Agent",
        "type": "Services"
      }
    ],
    "sg:phone": "+1 617 381 9461",
    "sg:postcode": "02149",
    "sg:province": "MA",
    "sg:tags": [
      "buyer",
      "broker"
    ],
    "wof:name": "Garden Street Realty Trust",
    "wof:placetype": "venue"
  },
  "geometry": {"coordinates":[-71.048588,42.401149],"type":"Point"}
}
