{
  "type": "Feature",
  "properties": {
    "addr:full": "1191 River St Hyde Park MA 02136",
    "addr:housenumber": "1191",
    "addr:postcode": "02136",
    "addr:street": "River St",
    "iso:country": "US",
    "sg:address": "1191 River St",
    "sg:city": "Hyde Park",
    "sg:classifiers": [
      {
        "category": "Manufacturing",
        "subcategory": "Printing",
        "type": "Manufacturing \u0026 Wholesale Goods"
      }
    ],
    "sg:phone": "+1 617 364 2398",
    "sg:postcode": "02136",
    "sg:province": "MA",
    "sg:tags": [
      "commercial"
    ],
    "wof:name": "PDM Assoc",
    "wof:placetype": "venue"
  },
  "geometry": {"coordinates":[-71.122034,42.256104],"type":"Point"}
}
