{
  "type": "Feature",
  "properties": {
    "iso:country":"US",
    "sg:address":"100 Sterling St",
    "sg:city":"Clinton",
    "sg:classifiers":[
        {
            "category":"Wholesale",
            "subcategory":"Machinery & Supplies",
            "type":"Manufacturing & Wholesale Goods"
        }
    ],
    "sg:phone":"+1 978 365 4544",
    "sg:postcode":"01510",
    "sg:province":"MA",
    "sg:tags":[
        "abrasive"
    ],
    "sg:website":"www.darmann.com",
    "wof:name":"Darmann Abrasive Products",
    "wof:placetype":"venue"
},
  "geometry": {"coordinates":[-71.690776,42.421625],"type":"Point"}
}