{
  "type": "Feature",
  "properties": {
    "addr:full": "3359 Washington St Jamaica Plain MA 02130",
    "addr:housenumber": "3359",
    "addr:postcode": "02130",
    "addr:street": "Washington St",
    "iso:country": "US",
    "sg:address": "3359 Washington St",
    "sg:city": "Jamaica Plain",
    "sg:classifiers": [
      {
        "category": "Building \u0026 Trades",
        "subcategory": "Construction",
        "type": "Services"
      }
    ],
    "sg:phone": "+1 617 524 5463",
    "sg:postcode": "02130",
    "sg:province": "MA",
    "sg:tags": [
      "carpentry",
      "contractor"
    ],
    "wof:name": "Finishing Unlimited",
    "wof:placetype": "venue"
  },
  "geometry": {"coordinates":[-71.10614,42.307976],"type":"Point"}
}
