{
  "type": "Feature",
  "properties": {
    "iso:country":"US",
    "sg:address":"3359 Washington St",
    "sg:city":"Jamaica Plain",
    "sg:classifiers":[
        {
            "category":"Building & Trades",
            "subcategory":"Construction",
            "type":"Services"
        }
    ],
    "sg:phone":"+1 617 524 5463",
    "sg:postcode":"02130",
    "sg:province":"MA",
    "sg:tags":[
        "carpentry",
        "contractor"
    ],
    "wof:name":"Finishing Unlimited",
    "wof:placetype":"venue"
},
  "geometry": {"coordinates":[-71.10614,42.307976],"type":"Point"}
}