{
  "type": "Feature",
  "properties": {
    "addr:full":"15 Connecticut Ave Boston MA 02108",
    "addr:housenumber":"15",
    "addr:postcode":"02108",
    "addr:street":"Connecticut Ave",
    "iso:country":"US",
    "sg:address":"15 Connecticut Ave",
    "sg:city":"Boston",
    "sg:classifiers":[
        {
            "category":"Professional",
            "subcategory":"Lawyer & Legal Services",
            "type":"Services"
        }
    ],
    "sg:phone":"+1 617 523 3622",
    "sg:postcode":"02108",
    "sg:province":"MA",
    "wof:name":"Tangusso John S Atty",
    "wof:placetype":"venue"
},
  "geometry": {"coordinates":[-71.065102,42.3577],"type":"Point"}
}