{
  "type": "Feature",
  "properties": {
    "iso:country":"US",
    "sg:address":"750 Concord St",
    "sg:city":"Holliston",
    "sg:classifiers":[
        {
            "category":"Recreation",
            "type":"Entertainment"
        }
    ],
    "sg:phone":"+1   ",
    "sg:postcode":"01746",
    "sg:province":"MA",
    "sg:tags":[
        "miniature",
        "golf"
    ],
    "wof:name":"Water Hazard",
    "wof:placetype":"venue"
},
  "geometry": {"coordinates":[-71.431073,42.234091],"type":"Point"}
}