{
  "type": "Feature",
  "properties": {
    "iso:country":"US",
    "sg:address":"289 York St",
    "sg:city":"Canton",
    "sg:classifiers":[
        {
            "category":"Professional",
            "subcategory":"Lawyer & Legal Services",
            "type":"Services"
        }
    ],
    "sg:phone":"+1 781 828 2331",
    "sg:postcode":"02021",
    "sg:province":"MA",
    "wof:name":"Drake Harold M Jr Lwyr",
    "wof:placetype":"venue"
},
  "geometry": {"coordinates":[-71.09075300000001,42.171637],"type":"Point"}
}