{
  "type": "Feature",
  "properties": {
    "addr:full": "289 York St Canton MA 02021",
    "addr:housenumber": "289",
    "addr:postcode": "02021",
    "addr:street": "York St",
    "iso:country": "US",
    "sg:address": "289 York St",
    "sg:city": "Canton",
    "sg:classifiers": [
      {
        "category": "Professional",
        "subcategory": "Lawyer \u0026 Legal Services",
        "type": "Services"
      }
    ],
    "sg:phone": "+1 781 828 2331",
    "sg:postcode": "02021",
    "sg:province": "MA",
    "wof:name": "Drake Harold M Jr Lwyr",
    "wof:placetype": "venue"
  },
  "geometry": {"coordinates":[-71.090753,42.171637],"type":"Point"}
}
