{
  "type": "Feature",
  "properties": {
    "addr:full": "32 Leslie O Johnson Rd Gloucester MA 01930",
    "addr:housenumber": "32",
    "addr:postcode": "01930",
    "addr:street": "Leslie O Johnson Rd",
    "iso:country": "US",
    "ovtr:label": "Gloucester High School, 32 Leslie O Johnson Rd Gloucester MA US",
    "ovtr:similarity": 3.2406489849090576,
    "sg:address": "32 Leslie O Johnson Rd",
    "sg:city": "Gloucester",
    "sg:classifiers": [
      {
        "category": "Education",
        "subcategory": "School",
        "type": "Public Place"
      }
    ],
    "sg:phone": "+1 978 281 9870",
    "sg:postcode": "01930",
    "sg:province": "MA",
    "wof:name": "Gloucester High School",
    "wof:placetype": "venue"
  },
  "geometry": {"coordinates":[-70.675871,42.613181],"type":"Point"}
}
