{
  "type": "Feature",
  "properties": {
    "iso:country":"US",
    "sg:address":"46 Crystal Ct",
    "sg:city":"Haverhill",
    "sg:classifiers":[
        {
            "category":"Professional",
            "subcategory":"Computer Services",
            "type":"Services"
        }
    ],
    "sg:phone":"+1 978 469 9191",
    "sg:postcode":"01832",
    "sg:province":"MA",
    "sg:tags":[
        "website",
        "design"
    ],
    "wof:name":"O'Connell Designs",
    "wof:placetype":"venue"
},
  "geometry": {"coordinates":[-71.171926,42.789779],"type":"Point"}
}