{
  "type": "Feature",
  "properties": {
    "addr:full": "44 Glendower Rd Roslindale MA 02131",
    "addr:housenumber": "44",
    "addr:postcode": "02131",
    "addr:street": "Glendower Rd",
    "iso:country": "US",
    "sg:address": "44 Glendower Rd",
    "sg:city": "Roslindale",
    "sg:classifiers": [
      {
        "category": "Manufacturing",
        "subcategory": "Food",
        "type": "Manufacturing \u0026 Wholesale Goods"
      }
    ],
    "sg:phone": "+1 617 323 7362",
    "sg:postcode": "02131",
    "sg:province": "MA",
    "sg:tags": [
      "wine",
      "mfg"
    ],
    "wof:name": "Solera",
    "wof:placetype": "venue"
  },
  "geometry": {"coordinates":[-71.129004,42.274088],"type":"Point"}
}
