{
  "type": "Feature",
  "properties": {
    "iso:country":"US",
    "sg:address":"40 Emerson Ave",
    "sg:city":"Brockton",
    "sg:classifiers":[
        {
            "category":"Organizations",
            "subcategory":"Community Association",
            "type":"Services"
        }
    ],
    "sg:phone":"+1 508 583 9539",
    "sg:postcode":"02301",
    "sg:province":"MA",
    "sg:tags":[
        "workers'",
        "placement",
        "volunteer"
    ],
    "wof:name":"Polish White Eagle",
    "wof:placetype":"venue"
},
  "geometry": {"coordinates":[-71.02188,42.103994],"type":"Point"}
}