{
  "type": "Feature",
  "properties": {
    "iso:country":"US",
    "sg:address":"196 Harvard Avenue",
    "sg:city":"Allston",
    "sg:classifiers":[
        {
            "category":"Education",
            "subcategory":"Special Training",
            "type":"Public Place"
        }
    ],
    "sg:phone":"+1 617 787 5401",
    "sg:postcode":"02134",
    "sg:province":"MA",
    "sg:tags":[
        "school",
        "language"
    ],
    "wof:name":"Approach International Student Centers",
    "wof:placetype":"venue"
},
  "geometry": {"coordinates":[-71.13099699999999,42.350489],"type":"Point"}
}