{
  "type": "Feature",
  "properties": {
    "addr:full": "196 Harvard Avenue Allston MA 02134",
    "addr:housenumber": "196",
    "addr:postcode": "02134",
    "addr:street": "Harvard Avenue",
    "iso:country": "US",
    "ovtr:label": "Approach International Student Center, 196 Harvard Ave Allston MA US",
    "ovtr:similarity": 3.1300270557403564,
    "sg:address": "196 Harvard Avenue",
    "sg:city": "Allston",
    "sg:classifiers": [
      {
        "category": "Education",
        "subcategory": "Special Training",
        "type": "Public Place"
      }
    ],
    "sg:phone": "+1 617 787 5401",
    "sg:postcode": "02134",
    "sg:province": "MA",
    "sg:tags": [
      "school",
      "language"
    ],
    "wof:name": "Approach International Student Centers",
    "wof:placetype": "venue"
  },
  "geometry": {"coordinates":[-71.130997,42.350489],"type":"Point"}
}
