{
  "type": "Feature",
  "properties": {
    "addr:full": "580 Washington St Newton MA 02458",
    "addr:housenumber": "580",
    "addr:postcode": "02458",
    "addr:street": "Washington St",
    "iso:country": "US",
    "sg:address": "580 Washington St",
    "sg:city": "Newton",
    "sg:classifiers": [
      {
        "category": "Organizations",
        "subcategory": "Religious Organization",
        "type": "Services"
      }
    ],
    "sg:phone": "+1 617 965 4343",
    "sg:postcode": "02458",
    "sg:province": "MA",
    "wof:name": "National Catholic Groups Purch",
    "wof:placetype": "venue"
  },
  "geometry": {"coordinates":[-71.197667,42.354386],"type":"Point"}
}
