{
  "type": "Feature",
  "properties": {
    "addr:full":"4 Russell Rd Lexington MA 02420",
    "addr:housenumber":"4",
    "addr:postcode":"02420",
    "addr:street":"Russell Rd",
    "iso:country":"US",
    "sg:address":"4 Russell Rd",
    "sg:city":"Lexington",
    "sg:classifiers":[
        {
            "category":"Professional",
            "subcategory":"Computer Services",
            "type":"Services"
        }
    ],
    "sg:phone":"+1   ",
    "sg:postcode":"02420",
    "sg:province":"MA",
    "sg:tags":[
        "related"
    ],
    "wof:name":"Mesosoft Corp",
    "wof:placetype":"venue"
},
  "geometry": {"coordinates":[-71.184383,42.444233],"type":"Point"}
}