{
  "type": "Feature",
  "properties": {
    "addr:full":"4 N Main St Sharon MA 02067",
    "addr:housenumber":"4",
    "addr:postcode":"02067",
    "addr:street":"N Main St",
    "iso:country":"US",
    "sg:address":"4 N Main St",
    "sg:city":"Sharon",
    "sg:classifiers":[
        {
            "category":"Organizations",
            "subcategory":"Religious Organization",
            "type":"Services"
        }
    ],
    "sg:phone":"+1 781 784 3652",
    "sg:postcode":"02067",
    "sg:province":"MA",
    "sg:tags":[
        "church"
    ],
    "wof:name":"Unitarian Church Of Sharon",
    "wof:placetype":"venue"
},
  "geometry": {"coordinates":[-71.17848499999999,42.12446],"type":"Point"}
}