{
  "type": "Feature",
  "properties": {
    "iso:country":"US",
    "sg:address":"445 Osterville West Barnstable Rd",
    "sg:city":"Osterville",
    "sg:classifiers":[
        {
            "category":"Building & Trades",
            "subcategory":"Landscaping Services",
            "type":"Services"
        }
    ],
    "sg:phone":"+1 508 419 7377",
    "sg:postcode":"02655",
    "sg:province":"MA",
    "sg:tags":[
        "tree"
    ],
    "wof:name":"Dc Tree Service",
    "wof:placetype":"venue"
},
  "geometry": {"coordinates":[-70.392197,41.653728],"type":"Point"}
}