{
  "type": "Feature",
  "properties": {
    "iso:country":"US",
    "sg:address":"17 Bridge St",
    "sg:city":"Billerica",
    "sg:classifiers":[
        {
            "category":"Real Estate",
            "subcategory":"Real Estate Services",
            "type":"Services"
        }
    ],
    "sg:phone":"+1 978 667 0045",
    "sg:postcode":"01821",
    "sg:province":"MA",
    "sg:tags":[
        "management",
        "property"
    ],
    "wof:name":"Clock Tower Place",
    "wof:placetype":"venue"
},
  "geometry": {"coordinates":[-71.283124,42.574165],"type":"Point"}
}