{
  "type": "Feature",
  "properties": {
    "iso:country":"US",
    "sg:address":"236 Blossom St",
    "sg:city":"Fitchburg",
    "sg:classifiers":[
        {
            "category":"Arts & Performance",
            "subcategory":"Theater",
            "type":"Entertainment"
        }
    ],
    "sg:phone":"+1   ",
    "sg:postcode":"01420",
    "sg:province":"MA",
    "sg:tags":[
        "group"
    ],
    "wof:name":"Randy J Fairas",
    "wof:placetype":"venue"
},
  "geometry": {"coordinates":[-71.794448,42.588593],"type":"Point"}
}