{
  "type": "Feature",
  "properties": {
    "addr:full":"582 Dorchester Avenue Boston MA 02127",
    "addr:housenumber":"582",
    "addr:postcode":"02127",
    "addr:street":"Dorchester Avenue",
    "iso:country":"US",
    "sg:address":"582 Dorchester Avenue",
    "sg:city":"Boston",
    "sg:classifiers":[
        {
            "category":"Restaurant",
            "type":"Food & Drink"
        }
    ],
    "sg:phone":"+1 617 464 3663",
    "sg:postcode":"02127",
    "sg:province":"MA",
    "sg:tags":[
        "pizza"
    ],
    "wof:name":"Alex's Pizza",
    "wof:placetype":"venue"
},
  "geometry": {"coordinates":[-71.057095,42.329786],"type":"Point"}
}