{
  "type": "Feature",
  "properties": {
    "iso:country":"US",
    "sg:address":"67 Pleasant St",
    "sg:city":"Brockton",
    "sg:classifiers":[
        {
            "category":"Real Estate",
            "subcategory":"Real Estate Agent",
            "type":"Services"
        }
    ],
    "sg:phone":"+1 508 588 4663",
    "sg:postcode":"02301",
    "sg:province":"MA",
    "wof:name":"Berlus Realty",
    "wof:placetype":"venue"
},
  "geometry": {"coordinates":[-71.01993,42.085557],"type":"Point"}
}