{
  "type": "Feature",
  "properties": {
    "addr:full":"142 Main St Sturbridge MA 01566",
    "addr:housenumber":"142",
    "addr:postcode":"01566",
    "addr:street":"Main St",
    "iso:country":"US",
    "sg:address":"142 Main St",
    "sg:city":"Sturbridge",
    "sg:classifiers":[
        {
            "category":"Travel",
            "subcategory":"Hotels & Motels",
            "type":"Entertainment"
        }
    ],
    "sg:phone":"+1 508 347 9514",
    "sg:postcode":"01566",
    "sg:province":"MA",
    "sg:website":"www.bookroomsnow.com",
    "wof:name":"Scottish Inns",
    "wof:placetype":"venue"
},
  "geometry": {"coordinates":[-72.0681,42.0942],"type":"Point"}
}