{
  "type": "Feature",
  "properties": {
    "addr:full": "1148 Beacon St Newton MA 02461",
    "addr:housenumber": "1148",
    "addr:postcode": "02461",
    "addr:street": "Beacon St",
    "iso:country": "US",
    "sg:address": "1148 Beacon St",
    "sg:city": "Newton",
    "sg:classifiers": [
      {
        "category": "Food \u0026 Beverages",
        "subcategory": "Bakery",
        "type": "Retail Goods"
      }
    ],
    "sg:phone": "+1 617 964 6892",
    "sg:postcode": "02461",
    "sg:province": "MA",
    "sg:tags": [
      "doughnut"
    ],
    "wof:name": "Dunkin Donuts",
    "wof:placetype": "venue"
  },
  "geometry": {"coordinates":[-71.208412,42.330833],"type":"Point"}
}
