{
  "type": "Feature",
  "properties": {
    "addr:full":"89 Church St Lowell MA 01852",
    "addr:housenumber":"89",
    "addr:postcode":"01852",
    "addr:street":"Church St",
    "iso:country":"US",
    "sg:address":"89 Church St",
    "sg:city":"Lowell",
    "sg:classifiers":[
        {
            "category":"Shopping",
            "subcategory":"Clothing, Apparel, & Fashions",
            "type":"Retail Goods"
        }
    ],
    "sg:phone":"+1 978 458 3406",
    "sg:postcode":"01852",
    "sg:province":"MA",
    "wof:name":"J Silver Clothing Inc",
    "wof:placetype":"venue"
},
  "geometry": {"coordinates":[-71.30801200000001,42.641246],"type":"Point"}
}