{
  "type": "Feature",
  "properties": {
    "iso:country":"US",
    "sg:address":"50 Finnell Dr",
    "sg:city":"Weymouth",
    "sg:classifiers":[
        {
            "category":"Manufacturing",
            "subcategory":"Tools & Machinery",
            "type":"Manufacturing & Wholesale Goods"
        }
    ],
    "sg:phone":"+1 781 331 7877",
    "sg:postcode":"02188",
    "sg:province":"MA",
    "sg:tags":[
        "physician",
        "surgeon"
    ],
    "wof:name":"Ultra Clenz",
    "wof:placetype":"venue"
},
  "geometry": {"coordinates":[-70.968129,42.188847],"type":"Point"}
}