{
  "type": "Feature",
  "properties": {
    "addr:full": "25 Bay State Rd Ste 2 Boston MA 02215",
    "addr:housenumber": "25",
    "addr:postcode": "02215",
    "addr:street": "Bay State Rd Ste 2",
    "iso:country": "US",
    "sg:address": "25 Bay State Rd Ste 2",
    "sg:city": "Boston",
    "sg:classifiers": [
      {
        "category": "Professional",
        "subcategory": "Lawyer \u0026 Legal Services",
        "type": "Services"
      }
    ],
    "sg:phone": "+1 617 437 0330",
    "sg:postcode": "02215",
    "sg:province": "MA",
    "wof:name": "Angelone Elaine M Atty",
    "wof:placetype": "venue"
  },
  "geometry": {"coordinates":[-71.094101,42.349899],"type":"Point"}
}
