{
  "type": "Feature",
  "properties": {
    "iso:country":"US",
    "sg:address":"32 Parker St",
    "sg:city":"Indian Orchard",
    "sg:classifiers":[
        {
            "category":"Shopping",
            "subcategory":"Jewelry",
            "type":"Retail Goods"
        }
    ],
    "sg:phone":"+1 413 543 1677",
    "sg:postcode":"01151",
    "sg:province":"MA",
    "sg:tags":[
        "jeweler"
    ],
    "wof:name":"Rita C Jewelry & Display's",
    "wof:placetype":"venue"
},
  "geometry": {"coordinates":[-72.48747299999999,42.155482],"type":"Point"}
}