{
  "type": "Feature",
  "properties": {
    "iso:country":"US",
    "sg:address":"42 Gifford Ave",
    "sg:city":"Westfield",
    "sg:classifiers":[
        {
            "category":"Building & Trades",
            "subcategory":"Construction",
            "type":"Services"
        }
    ],
    "sg:phone":"+1   ",
    "sg:postcode":"01085",
    "sg:province":"MA",
    "sg:tags":[
        "contractor"
    ],
    "wof:name":"Ricks Framing & Siding",
    "wof:placetype":"venue"
},
  "geometry": {"coordinates":[-72.763257,42.144396],"type":"Point"}
}