{
  "type": "Feature",
  "properties": {
    "addr:full":"1001 Beacon St Brookline MA 02446",
    "addr:housenumber":"1001",
    "addr:postcode":"02446",
    "addr:street":"Beacon St",
    "iso:country":"US",
    "sg:address":"1001 Beacon St",
    "sg:city":"Brookline",
    "sg:classifiers":[
        {
            "category":"Manufacturing",
            "subcategory":"Food",
            "type":"Manufacturing & Wholesale Goods"
        }
    ],
    "sg:phone":"+1 617 731 5500",
    "sg:postcode":"02446",
    "sg:province":"MA",
    "sg:tags":[
        "winery"
    ],
    "wof:name":"Domain Select Wine Estates",
    "wof:placetype":"venue"
},
  "geometry": {"coordinates":[-71.10906,42.34538],"type":"Point"}
}