{
  "type": "Feature",
  "properties": {
    "addr:full":"931 Massachusetts Ave Cambridge MA 02139",
    "addr:housenumber":"931",
    "addr:postcode":"02139",
    "addr:street":"Massachusetts Ave",
    "iso:country":"US",
    "sg:address":"931 Massachusetts Ave",
    "sg:city":"Cambridge",
    "sg:classifiers":[
        {
            "category":"Real Estate",
            "subcategory":"Real Estate Operator",
            "type":"Services"
        }
    ],
    "sg:phone":"+1 617 576 6639",
    "sg:postcode":"02139",
    "sg:province":"MA",
    "sg:tags":[
        "condominium"
    ],
    "wof:name":"931 Massachusetts Ave Assoc",
    "wof:placetype":"venue"
},
  "geometry": {"coordinates":[-71.110152,42.369029],"type":"Point"}
}