{
  "type": "Feature",
  "properties": {
    "addr:full": "107 Highland St Worcester MA 01609",
    "addr:housenumber": "107",
    "addr:postcode": "01609",
    "addr:street": "Highland St",
    "iso:country": "US",
    "sg:address": "107 Highland St",
    "sg:city": "Worcester",
    "sg:phone": "+1 508 756 7267",
    "sg:postcode": "01609",
    "sg:province": "MA",
    "sg:website": "http://www.tortillasams.com",
    "wof:name": "Tortilla Sams",
    "wof:placetype": "venue"
  },
  "geometry": {"coordinates":[-71.806709,42.27108],"type":"Point"}
}
