{
  "type": "Feature",
  "properties": {
    "addr:full": "56 E Main St Westborough MA 01581",
    "addr:housenumber": "56",
    "addr:postcode": "01581",
    "addr:street": "E Main St",
    "iso:country": "US",
    "sg:address": "56 E Main St",
    "sg:city": "Westborough",
    "sg:classifiers": [
      {
        "category": "Restaurant",
        "type": "Food \u0026 Drink"
      }
    ],
    "sg:phone": "+1 508 366 2288",
    "sg:postcode": "01581",
    "sg:province": "MA",
    "wof:name": "Mandarin Westboro Inc",
    "wof:placetype": "venue"
  },
  "geometry": {"coordinates":[-71.610844,42.273244],"type":"Point"}
}
