{
  "type": "Feature",
  "properties": {
    "addr:full": "27 Union St Manchester MA 01944",
    "addr:housenumber": "27",
    "addr:postcode": "01944",
    "addr:street": "Union St",
    "iso:country": "US",
    "ovtr:label": "Manchester By the Book, 27 Union St Manchester MA US",
    "ovtr:similarity": 2.768695116043091,
    "sg:address": "27 Union St",
    "sg:city": "Manchester",
    "sg:classifiers": [
      {
        "category": "Shopping",
        "subcategory": "Used Merchandise",
        "type": "Retail Goods"
      }
    ],
    "sg:phone": "+1 978 525 2929",
    "sg:postcode": "01944",
    "sg:province": "MA",
    "sg:tags": [
      "shop",
      "book",
      "rare",
      "gift"
    ],
    "wof:name": "Manchester By The Book",
    "wof:placetype": "venue"
  },
  "geometry": {"coordinates":[-70.770148,42.575098],"type":"Point"}
}
