{
  "type": "Feature",
  "properties": {
    "iso:country":"US",
    "sg:address":"27 Union St",
    "sg:city":"Manchester",
    "sg:classifiers":[
        {
            "category":"Shopping",
            "subcategory":"Used Merchandise",
            "type":"Retail Goods"
        }
    ],
    "sg:phone":"+1 978 525 2929",
    "sg:postcode":"01944",
    "sg:province":"MA",
    "sg:tags":[
        "shop",
        "book",
        "rare",
        "gift"
    ],
    "wof:name":"Manchester By The Book",
    "wof:placetype":"venue"
},
  "geometry": {"coordinates":[-70.77014800000001,42.575098],"type":"Point"}
}