{
  "type": "Feature",
  "properties": {
    "iso:country":"US",
    "sg:address":"1111 Southampton Rd",
    "sg:city":"Westfield",
    "sg:classifiers":[
        {
            "category":"Professional",
            "subcategory":"Management & Consulting",
            "type":"Services"
        }
    ],
    "sg:phone":"+1 413 568 1909",
    "sg:postcode":"01085",
    "sg:province":"MA",
    "sg:tags":[
        "development",
        "industrial"
    ],
    "wof:name":"Westfield Development Assoc",
    "wof:placetype":"venue"
},
  "geometry": {"coordinates":[-72.726889,42.177977],"type":"Point"}
}