{
  "type": "Feature",
  "properties": {
    "addr:full":"107 W Main St Norton MA 02766",
    "addr:housenumber":"107",
    "addr:postcode":"02766",
    "addr:street":"W Main St",
    "iso:country":"US",
    "sg:address":"107 W Main St",
    "sg:city":"Norton",
    "sg:classifiers":[
        {
            "category":"Retail",
            "subcategory":"Auto Repair",
            "type":"Services"
        }
    ],
    "sg:phone":"+1 508 285 7973",
    "sg:postcode":"02766",
    "sg:province":"MA",
    "sg:tags":[
        "muffler",
        "exhaust",
        "system",
        "general"
    ],
    "wof:name":"Arnolds Muffler and Brake Shop",
    "wof:placetype":"venue"
},
  "geometry": {"coordinates":[-71.199702,41.961191],"type":"Point"}
}