{
  "type": "Feature",
  "properties": {
    "iso:country":"US",
    "sg:address":"462 Washington St",
    "sg:city":"Brighton",
    "sg:classifiers":[
        {
            "category":"Utilities",
            "subcategory":"Mobile Phone",
            "type":"Services"
        }
    ],
    "sg:phone":"+1 617 787 4836",
    "sg:postcode":"02135",
    "sg:province":"MA",
    "sg:tags":[
        "telephone",
        "cellular"
    ],
    "wof:name":"Nextel Administration",
    "wof:placetype":"venue"
},
  "geometry": {"coordinates":[-71.158205,42.349111],"type":"Point"}
}