{
  "type": "Feature",
  "properties": {
    "iso:country":"US",
    "sg:address":"8 Alton Place",
    "sg:city":"Brookline",
    "sg:classifiers":[
        {
            "category":"Personal",
            "subcategory":"Massage",
            "type":"Services"
        }
    ],
    "sg:phone":"+1 617 739 2599",
    "sg:postcode":"02446",
    "sg:province":"MA",
    "wof:name":"Jacobson Thomas Lmt",
    "wof:placetype":"venue"
},
  "geometry": {"coordinates":[-71.12082100000001,42.33916],"type":"Point"}
}