{
  "type": "Feature",
  "properties": {
    "iso:country":"US",
    "sg:address":"4 Library Plz",
    "sg:city":"Marshfield",
    "sg:classifiers":[
        {
            "category":"Retail",
            "subcategory":"Veterinary Services",
            "type":"Services"
        },
        {
            "category":"Retail",
            "subcategory":"Animal Services",
            "type":"Services"
        }
    ],
    "sg:phone":"+1 781 566 0178",
    "sg:postcode":"02050",
    "sg:province":"MA",
    "sg:tags":[
        "pet",
        "hospital",
        "veterinarian",
        "clinic"
    ],
    "sg:website":"http://ad.doubleclick.net/clk;226007916;49913701;g?http://www.vcahospitals.com/main/offer?utm_source=iyp&utm_medium=iyp&utm_campaign=yellowpages",
    "wof:name":"VCA Animal Care Center of Marshfield",
    "wof:placetype":"venue"
},
  "geometry": {"coordinates":[-70.702518,42.092179],"type":"Point"}
}