{
  "type": "Feature",
  "properties": {
    "addr:full": "264 Huntington Avenue Boston MA 02115",
    "addr:housenumber": "264",
    "addr:postcode": "02115",
    "addr:street": "Huntington Avenue",
    "iso:country": "US",
    "sg:address": "264 Huntington Avenue",
    "sg:city": "Boston",
    "sg:classifiers": [
      {
        "category": "Arts \u0026 Performance",
        "subcategory": "Arts Center",
        "type": "Entertainment"
      }
    ],
    "sg:phone": "+1 617 933 8600",
    "sg:postcode": "02115",
    "sg:province": "MA",
    "sg:tags": [
      "performing"
    ],
    "sg:website": "www.bu.edu/cfa/bcap",
    "wof:name": "Boston Center for American Performance",
    "wof:placetype": "venue"
  },
  "geometry": {"coordinates":[-71.0856,42.3417],"type":"Point"}
}
