{
  "type": "Feature",
  "properties": {
    "addr:full":"100 Stephanie Ln Bridgewater MA 02324",
    "addr:housenumber":"100",
    "addr:postcode":"02324",
    "addr:street":"Stephanie Ln",
    "iso:country":"US",
    "sg:address":"100 Stephanie Ln",
    "sg:city":"Bridgewater",
    "sg:classifiers":[
        {
            "category":"Building & Trades",
            "subcategory":"Construction",
            "type":"Services"
        }
    ],
    "sg:phone":"+1 508 697 2727",
    "sg:postcode":"02324",
    "sg:province":"MA",
    "sg:tags":[
        "general",
        "contractor"
    ],
    "wof:name":"Walsh Construction",
    "wof:placetype":"venue"
},
  "geometry": {"coordinates":[-70.984773,41.967106],"type":"Point"}
}