{
  "type": "Feature",
  "properties": {
    "iso:country":"US",
    "sg:address":"75 Forbes Blvd",
    "sg:city":"Mansfield",
    "sg:classifiers":[
        {
            "category":"Professional",
            "subcategory":"Management & Consulting",
            "type":"Services"
        }
    ],
    "sg:phone":"+1 508 339 0800",
    "sg:postcode":"02048",
    "sg:province":"MA",
    "sg:tags":[
        "consultant",
        "motel",
        "hotel"
    ],
    "wof:name":"Lee-Cox, Inc.",
    "wof:placetype":"venue"
},
  "geometry": {"coordinates":[-71.237792,42.032291],"type":"Point"}
}