{
  "type": "Feature",
  "properties": {
    "addr:full": "21 N Beacon St Watertown MA 02472",
    "addr:housenumber": "21",
    "addr:postcode": "02472",
    "addr:street": "N Beacon St",
    "iso:country": "US",
    "ovtr:label": "Sullivan Tire \u0026 Auto Service, 21 N Beacon St Watertown MA US",
    "ovtr:similarity": 2.0453269481658936,
    "sg:address": "21 N Beacon St",
    "sg:city": "Watertown",
    "sg:phone": "+1 617 926 5070",
    "sg:postcode": "02472",
    "sg:province": "MA",
    "sg:website": "http://www.goodyeartires.com/",
    "wof:name": "Sullivan Tire \u0026 Auto Service",
    "wof:placetype": "venue"
  },
  "geometry": {"coordinates":[-71.182953,42.364979],"type":"Point"}
}
