{
  "type": "Feature",
  "properties": {
    "iso:country":"US",
    "sg:address":"21 N Beacon St",
    "sg:city":"Watertown",
    "sg:phone":"+1 617 926 5070",
    "sg:postcode":"02472",
    "sg:province":"MA",
    "sg:website":"http://www.goodyeartires.com/",
    "wof:name":"Sullivan Tire & Auto Service",
    "wof:placetype":"venue"
},
  "geometry": {"coordinates":[-71.182953,42.364979],"type":"Point"}
}