{
  "type": "Feature",
  "properties": {
    "iso:country":"US",
    "sg:address":"120 Waverly St",
    "sg:city":"Framingham",
    "sg:classifiers":[
        {
            "category":"Wholesale",
            "subcategory":"Scrap",
            "type":"Manufacturing & Wholesale Goods"
        }
    ],
    "sg:phone":"+1 508 872 4393",
    "sg:postcode":"01702",
    "sg:province":"MA",
    "sg:tags":[
        "metal",
        "iron"
    ],
    "wof:name":"Framingham Salvage Co",
    "wof:placetype":"venue"
},
  "geometry": {"coordinates":[-71.404213,42.279429],"type":"Point"}
}