{
  "type": "Feature",
  "properties": {
    "addr:full": "120 Waverly St Framingham MA 01702",
    "addr:housenumber": "120",
    "addr:postcode": "01702",
    "addr:street": "Waverly St",
    "iso:country": "US",
    "sg:address": "120 Waverly St",
    "sg:city": "Framingham",
    "sg:classifiers": [
      {
        "category": "Wholesale",
        "subcategory": "Scrap",
        "type": "Manufacturing \u0026 Wholesale Goods"
      }
    ],
    "sg:phone": "+1 508 872 4393",
    "sg:postcode": "01702",
    "sg:province": "MA",
    "sg:tags": [
      "metal",
      "iron"
    ],
    "wof:name": "Framingham Salvage Co",
    "wof:placetype": "venue"
  },
  "geometry": {"coordinates":[-71.404213,42.279429],"type":"Point"}
}
