{
  "type": "Feature",
  "properties": {
    "addr:full":"53 Center St Granby MA 01033",
    "addr:housenumber":"53",
    "addr:postcode":"01033",
    "addr:street":"Center St",
    "iso:country":"US",
    "sg:address":"53 Center St",
    "sg:city":"Granby",
    "sg:classifiers":[
        {
            "category":"Recreation",
            "type":"Entertainment"
        }
    ],
    "sg:phone":"+1 413 467 2215",
    "sg:postcode":"01033",
    "sg:province":"MA",
    "sg:tags":[
        "stable"
    ],
    "wof:name":"Y-Knot Equine Ctr",
    "wof:placetype":"venue"
},
  "geometry": {"coordinates":[-72.51572299999999,42.252674],"type":"Point"}
}