{
  "type": "Feature",
  "properties": {
    "iso:country":"US",
    "sg:address":"400 Research Dr",
    "sg:city":"Wilmington",
    "sg:classifiers":[
        {
            "category":"Shopping",
            "subcategory":"Computers & Home Electronics",
            "type":"Retail Goods"
        }
    ],
    "sg:phone":"+1 978 658 3456",
    "sg:postcode":"01887",
    "sg:province":"MA",
    "sg:tags":[
        "equipment",
        "dealer"
    ],
    "wof:name":"Central Computer",
    "wof:placetype":"venue"
},
  "geometry": {"coordinates":[-71.15241,42.607541],"type":"Point"}
}