{
  "type": "Feature",
  "properties": {
    "iso:country":"US",
    "sg:address":"87 Elm St",
    "sg:city":"Pepperell",
    "sg:classifiers":[
        {
            "category":"Restaurant",
            "type":"Food & Drink"
        }
    ],
    "sg:phone":"+1 978 433 2758",
    "sg:postcode":"01463",
    "sg:province":"MA",
    "wof:name":"Scotch Pine Farm",
    "wof:placetype":"venue"
},
  "geometry": {"coordinates":[-71.59705200000001,42.652321],"type":"Point"}
}