{
  "type": "Feature",
  "properties": {
    "addr:full":"34 E Springfield St Boston MA 02118",
    "addr:housenumber":"34",
    "addr:postcode":"02118",
    "addr:street":"E Springfield St",
    "iso:country":"US",
    "sg:address":"34 E Springfield St",
    "sg:city":"Boston",
    "sg:classifiers":[
        {
            "category":"Education",
            "subcategory":"School",
            "type":"Public Place"
        }
    ],
    "sg:phone":"+1   ",
    "sg:postcode":"02118",
    "sg:province":"MA",
    "wof:name":"Internet School of Hip Hop",
    "wof:placetype":"venue"
},
  "geometry": {"coordinates":[-71.074549,42.335586],"type":"Point"}
}