{
  "type": "Feature",
  "properties": {
    "addr:full": "181 Canal St Lawrence MA 01840",
    "addr:housenumber": "181",
    "addr:postcode": "01840",
    "addr:street": "Canal St",
    "iso:country": "US",
    "sg:address": "181 Canal St",
    "sg:city": "Lawrence",
    "sg:classifiers": [
      {
        "category": "Home \u0026 Garden",
        "subcategory": "Household Appliances",
        "type": "Retail Goods"
      }
    ],
    "sg:phone": "+1 978 681 9069",
    "sg:postcode": "01840",
    "sg:province": "MA",
    "sg:tags": [
      "machine",
      "sewing"
    ],
    "wof:name": "Flying Geese Sewing Arts",
    "wof:placetype": "venue"
  },
  "geometry": {"coordinates":[-71.154697,42.70655],"type":"Point"}
}
