{
  "type": "Feature",
  "properties": {
    "addr:full": "35 Medford St Somerville MA 02143",
    "addr:housenumber": "35",
    "addr:postcode": "02143",
    "addr:street": "Medford St",
    "iso:country": "US",
    "sg:address": "35 Medford St",
    "sg:city": "Somerville",
    "sg:classifiers": [
      {
        "category": "Real Estate",
        "subcategory": "Architect",
        "type": "Services"
      }
    ],
    "sg:phone": "+1 617 628 8100",
    "sg:postcode": "02143",
    "sg:province": "MA",
    "wof:name": "Sutphin Architects",
    "wof:placetype": "venue"
  },
  "geometry": {"coordinates":[-71.087752,42.373879],"type":"Point"}
}
