{
  "type": "Feature",
  "properties": {
    "iso:country":"US",
    "sg:address":"27 Humboldt Ave",
    "sg:city":"Burlington",
    "sg:classifiers":[
        {
            "category":"Retail",
            "subcategory":"Laundry & Dry Cleaning",
            "type":"Services"
        },
        {
            "category":"Building & Trades",
            "subcategory":"Cleaning & Sanitation",
            "type":"Services"
        }
    ],
    "sg:phone":"+1 781 365 1089",
    "sg:postcode":"01803",
    "sg:province":"MA",
    "sg:tags":[
        "cleaner",
        "house"
    ],
    "wof:name":"Star Cleaning Service",
    "wof:placetype":"venue"
},
  "geometry": {"coordinates":[-71.212677,42.50061],"type":"Point"}
}