{
  "type": "Feature",
  "properties": {
    "addr:full": "27 Humboldt Ave Burlington MA 01803",
    "addr:housenumber": "27",
    "addr:postcode": "01803",
    "addr:street": "Humboldt Ave",
    "iso:country": "US",
    "sg:address": "27 Humboldt Ave",
    "sg:city": "Burlington",
    "sg:classifiers": [
      {
        "category": "Retail",
        "subcategory": "Laundry \u0026 Dry Cleaning",
        "type": "Services"
      },
      {
        "category": "Building \u0026 Trades",
        "subcategory": "Cleaning \u0026 Sanitation",
        "type": "Services"
      }
    ],
    "sg:phone": "+1 781 365 1089",
    "sg:postcode": "01803",
    "sg:province": "MA",
    "sg:tags": [
      "cleaner",
      "house"
    ],
    "wof:name": "Star Cleaning Service",
    "wof:placetype": "venue"
  },
  "geometry": {"coordinates":[-71.212677,42.50061],"type":"Point"}
}
