{
  "type": "Feature",
  "properties": {
    "addr:full": "308 Massachusetts Ave Lunenburg MA 01462",
    "addr:housenumber": "308",
    "addr:postcode": "01462",
    "addr:street": "Massachusetts Ave",
    "iso:country": "US",
    "sg:address": "308 Massachusetts Ave",
    "sg:city": "Lunenburg",
    "sg:classifiers": [
      {
        "category": "Restaurant",
        "type": "Food \u0026 Drink"
      }
    ],
    "sg:phone": "+1 978 582 9701",
    "sg:postcode": "01462",
    "sg:province": "MA",
    "sg:website": "http://www.ixtapacantina.com",
    "wof:name": "Ixtapa Cantina Mexican Rstrnt",
    "wof:placetype": "venue"
  },
  "geometry": {"coordinates":[-71.758476,42.592371],"type":"Point"}
}
