{
  "type": "Feature",
  "properties": {
    "addr:full":"319 Brookfield Rd Fiskdale MA 01518",
    "addr:housenumber":"319",
    "addr:postcode":"01518",
    "addr:street":"Brookfield Rd",
    "iso:country":"US",
    "sg:address":"319 Brookfield Rd",
    "sg:city":"Fiskdale",
    "sg:classifiers":[
        {
            "category":"Education",
            "subcategory":"School",
            "type":"Public Place"
        }
    ],
    "sg:phone":"+1 508 347 9301",
    "sg:postcode":"01518",
    "sg:province":"MA",
    "sg:website":"www.tantasqua.org",
    "wof:name":"Tantasqua Regional High School",
    "wof:placetype":"venue"
},
  "geometry": {"coordinates":[-72.129226,42.157768],"type":"Point"}
}