{
  "type": "Feature",
  "properties": {
    "addr:full":"804 E 7th Street Boston MA 02127",
    "addr:housenumber":"804",
    "addr:postcode":"02127",
    "addr:street":"E 7Th Street",
    "iso:country":"US",
    "sg:address":"804 E 7th Street",
    "sg:city":"Boston",
    "sg:classifiers":[
        {
            "category":"Sports & Exercise",
            "subcategory":"Gym",
            "type":"Entertainment"
        }
    ],
    "sg:phone":"+1 617 268 8968",
    "sg:postcode":"02127",
    "sg:province":"MA",
    "sg:tags":[
        "trainer"
    ],
    "wof:name":"Harborlights South Boston Nursing",
    "wof:placetype":"venue"
},
  "geometry": {"coordinates":[-71.029239,42.332288],"type":"Point"}
}