{
  "type": "Feature",
  "properties": {
    "addr:full":"83 Canal St Boston MA 02114",
    "addr:housenumber":"83",
    "addr:postcode":"02114",
    "addr:street":"Canal St",
    "iso:country":"US",
    "sg:address":"83 Canal St",
    "sg:city":"Boston",
    "sg:classifiers":[
        {
            "category":"Recreation",
            "type":"Entertainment"
        }
    ],
    "sg:phone":"+1 617 523 1082",
    "sg:postcode":"02114",
    "sg:province":"MA",
    "sg:tags":[
        "ticket",
        "event",
        "sale"
    ],
    "wof:name":"Ringside Ticket Agency",
    "wof:placetype":"venue"
},
  "geometry": {"coordinates":[-71.059867,42.36434],"type":"Point"}
}