{
  "type": "Feature",
  "properties": {
    "addr:full": "333 Washington St Ste 519 Boston MA 02108",
    "addr:housenumber": "333",
    "addr:postcode": "02108",
    "addr:street": "Washington St Ste 519",
    "iso:country": "US",
    "sg:address": "333 Washington St Ste 519",
    "sg:city": "Boston",
    "sg:classifiers": [
      {
        "category": "Shopping",
        "subcategory": "Jewelry",
        "type": "Retail Goods"
      },
      {
        "category": "Manufacturing",
        "subcategory": "Jewelry",
        "type": "Manufacturing \u0026 Wholesale Goods"
      }
    ],
    "sg:phone": "+1 617 227 4291",
    "sg:postcode": "02108",
    "sg:province": "MA",
    "sg:tags": [
      "manufacturer",
      "designer",
      "watch",
      "jewelers-wholesale",
      "jeweler"
    ],
    "wof:name": "Roupen's Setting",
    "wof:placetype": "venue"
  },
  "geometry": {"coordinates":[-71.059012,42.356777],"type":"Point"}
}
