{
  "type": "Feature",
  "properties": {
    "addr:full": "180 Massachusetts Ave Arlington MA 02474",
    "addr:housenumber": "180",
    "addr:postcode": "02474",
    "addr:street": "Massachusetts Ave",
    "iso:country": "US",
    "sg:address": "180 Massachusetts Ave",
    "sg:city": "Arlington",
    "sg:classifiers": [
      {
        "category": "Health Services",
        "subcategory": "Health Practitioner",
        "type": "Services"
      }
    ],
    "sg:phone": "+1 617 970 5721",
    "sg:postcode": "02474",
    "sg:province": "MA",
    "sg:tags": [
      "acupuncture"
    ],
    "wof:name": "Bubbling Brook Acupuncture",
    "wof:placetype": "venue"
  },
  "geometry": {"coordinates":[-71.141737,42.405076],"type":"Point"}
}
