{
  "type": "Feature",
  "properties": {
    "iso:country":"US",
    "sg:address":"87 Washington St",
    "sg:city":"Salem",
    "sg:classifiers":[
        {
            "category":"Shopping",
            "subcategory":"Stationery & Office Supplies",
            "type":"Retail Goods"
        }
    ],
    "sg:phone":"+1 978 744 1051",
    "sg:postcode":"01970",
    "sg:province":"MA",
    "sg:tags":[
        "rubber",
        "stamp",
        "plastic"
    ],
    "sg:website":"www.corpconnect.com",
    "wof:name":"Corporate Connection",
    "wof:placetype":"venue"
},
  "geometry": {"coordinates":[-70.895712,42.522205],"type":"Point"}
}