{
  "type": "Feature",
  "properties": {
    "iso:country":"US",
    "sg:address":"136 Lost Lake Dr",
    "sg:city":"Groton",
    "sg:classifiers":[
        {
            "category":"Building & Trades",
            "subcategory":"Construction",
            "type":"Services"
        }
    ],
    "sg:phone":"+1 978 448 6639",
    "sg:postcode":"01450",
    "sg:province":"MA",
    "sg:tags":[
        "carpenter"
    ],
    "wof:name":"Webster Building Assoc",
    "wof:placetype":"venue"
},
  "geometry": {"coordinates":[-71.527472,42.605212],"type":"Point"}
}