{
  "type": "Feature",
  "properties": {
    "iso:country":"US",
    "sg:address":"Corner of Franklin and Washington",
    "sg:city":"Boston",
    "sg:classifiers":[
        {
            "category":"Restaurant",
            "type":"Food & Drink"
        },
        {
            "category":"Food Court",
            "type":"Food & Drink"
        }
    ],
    "sg:postcode":"02108",
    "sg:province":"MA",
    "sg:tags":[
        "middle",
        "stand",
        "eastern"
    ],
    "wof:name":"South End Pita",
    "wof:placetype":"venue"
},
  "geometry": {"coordinates":[-71.05945699999999,42.356375],"type":"Point"}
}