{
  "type": "Feature",
  "properties": {
    "addr:full": "160 Belmont St Watertown MA 02472",
    "addr:housenumber": "160",
    "addr:postcode": "02472",
    "addr:street": "Belmont St",
    "iso:country": "US",
    "sg:address": "160 Belmont St",
    "sg:city": "Watertown",
    "sg:classifiers": [
      {
        "category": "Professional",
        "subcategory": "Computer Services",
        "type": "Services"
      }
    ],
    "sg:phone": "+1 617 393 1617",
    "sg:postcode": "02472",
    "sg:province": "MA",
    "sg:tags": [
      "repair"
    ],
    "wof:name": "Computer Express",
    "wof:placetype": "venue"
  },
  "geometry": {"coordinates":[-71.15747,42.37589],"type":"Point"}
}
