{
  "type": "Feature",
  "properties": {
    "iso:country":"US",
    "sg:address":"160 Belmont St",
    "sg:city":"Watertown",
    "sg:classifiers":[
        {
            "category":"Professional",
            "subcategory":"Computer Services",
            "type":"Services"
        }
    ],
    "sg:phone":"+1 617 393 1617",
    "sg:postcode":"02472",
    "sg:province":"MA",
    "sg:tags":[
        "repair"
    ],
    "wof:name":"Computer Express",
    "wof:placetype":"venue"
},
  "geometry": {"coordinates":[-71.15747,42.37589],"type":"Point"}
}