{
  "type": "Feature",
  "properties": {
    "iso:country":"US",
    "sg:address":"45 Christy Pl",
    "sg:city":"Brockton",
    "sg:classifiers":[
        {
            "category":"Social Services",
            "subcategory":"Adult Care",
            "type":"Services"
        }
    ],
    "sg:phone":"+1 508 427 6099",
    "sg:postcode":"02301",
    "sg:province":"MA",
    "sg:tags":[
        "home",
        "residential"
    ],
    "sg:website":"www.thehearth.org",
    "wof:name":"Hearthstone At Heights Xing",
    "wof:placetype":"venue"
},
  "geometry": {"coordinates":[-71.054666,42.091087],"type":"Point"}
}