{
  "type": "Feature",
  "properties": {
    "iso:country":"US",
    "sg:address":"175 Central St",
    "sg:city":"Lowell",
    "sg:classifiers":[
        {
            "category":"Professional",
            "subcategory":"Credit Reporting & Collection",
            "type":"Services"
        }
    ],
    "sg:phone":"+1 978 970 1400",
    "sg:postcode":"01852",
    "sg:province":"MA",
    "sg:tags":[
        "agency"
    ],
    "wof:name":"K Bolduc Enterprises",
    "wof:placetype":"venue"
},
  "geometry": {"coordinates":[-71.308587,42.643195],"type":"Point"}
}