{
  "type": "Feature",
  "properties": {
    "addr:full":"141 Lafayette Sq Haverhill MA 01832",
    "addr:housenumber":"141",
    "addr:postcode":"01832",
    "addr:street":"Lafayette Sq",
    "iso:country":"US",
    "sg:address":"141 Lafayette Sq",
    "sg:city":"Haverhill",
    "sg:classifiers":[
        {
            "category":"Retail",
            "subcategory":"Auto Repair",
            "type":"Services"
        }
    ],
    "sg:phone":"+1 978 372 4165",
    "sg:postcode":"01832",
    "sg:province":"MA",
    "sg:tags":[
        "road"
    ],
    "wof:name":"L & R Svc",
    "wof:placetype":"venue"
},
  "geometry": {"coordinates":[-71.09021,42.778176],"type":"Point"}
}