{
  "type": "Feature",
  "properties": {
    "addr:full": "J. W. McCormack Building 5 Post Office Square, 3rd Floor Boston MA 02109",
    "addr:housenumber": "3rd floor",
    "addr:postcode": "02109",
    "addr:street": "J. W.;Post Office Square",
    "iso:country": "US",
    "sg:address": "J. W. McCormack Building 5 Post Office Square, 3rd Floor",
    "sg:city": "Boston",
    "sg:classifiers": [
      {
        "category": "Restaurant",
        "type": "Food \u0026 Drink"
      }
    ],
    "sg:phone": "+1 617 292 4646",
    "sg:postcode": "02109",
    "sg:province": "MA",
    "sg:website": "mckcafe.com",
    "wof:name": "McCormack Cafe",
    "wof:placetype": "venue"
  },
  "geometry": {"coordinates":[-71.0569,42.3572],"type":"Point"}
}
