{
  "type": "Feature",
  "properties": {
    "addr:full": "82 Monmouth Street Brookline MA 02446",
    "addr:housenumber": "82",
    "addr:postcode": "02446",
    "addr:street": "Monmouth Street",
    "iso:country": "US",
    "sg:address": "82 Monmouth Street",
    "sg:city": "Brookline",
    "sg:classifiers": [
      {
        "category": "Building \u0026 Trades",
        "subcategory": "Construction",
        "type": "Services"
      }
    ],
    "sg:phone": "+1 617 734 9822",
    "sg:postcode": "02446",
    "sg:province": "MA",
    "sg:tags": [
      "interior",
      "design"
    ],
    "wof:name": "Interior Impressions",
    "wof:placetype": "venue"
  },
  "geometry": {"coordinates":[-71.106359,42.345099],"type":"Point"}
}
