{
  "type": "Feature",
  "properties": {
    "iso:country":"US",
    "sg:address":"46 Amesbury St",
    "sg:city":"Lawrence",
    "sg:classifiers":[
        {
            "category":"Building & Trades",
            "subcategory":"Construction",
            "type":"Services"
        }
    ],
    "sg:phone":"+1 978 794 8338",
    "sg:postcode":"01840",
    "sg:province":"MA",
    "sg:tags":[
        "general",
        "contractor"
    ],
    "wof:name":"ASAP Construction Solutions",
    "wof:placetype":"venue"
},
  "geometry": {"coordinates":[-71.163132,42.70724],"type":"Point"}
}