{
  "type": "Feature",
  "properties": {
    "addr:full": "8 Cohannet Ct Taunton MA 02780",
    "addr:housenumber": "8",
    "addr:postcode": "02780",
    "addr:street": "Cohannet Ct",
    "iso:country": "US",
    "sg:address": "8 Cohannet Ct",
    "sg:city": "Taunton",
    "sg:classifiers": [
      {
        "category": "Manufacturing",
        "subcategory": "Tools \u0026 Machinery",
        "type": "Manufacturing \u0026 Wholesale Goods"
      }
    ],
    "sg:phone": "+1 508 880 9820",
    "sg:postcode": "02780",
    "sg:province": "MA",
    "sg:tags": [
      "machine",
      "shop"
    ],
    "wof:name": "Pike Machine",
    "wof:placetype": "venue"
  },
  "geometry": {"coordinates":[-71.095125,41.900842],"type":"Point"}
}
