{
  "type": "Feature",
  "properties": {
    "addr:full":"634 N Falmouth Hwy North Falmouth MA 02556",
    "addr:housenumber":"634",
    "addr:postcode":"02556",
    "addr:street":"N Falmouth Hwy North",
    "iso:country":"US",
    "sg:address":"634 N Falmouth Hwy",
    "sg:city":"North Falmouth",
    "sg:classifiers":[
        {
            "category":"Real Estate",
            "subcategory":"Real Estate Agent",
            "type":"Services"
        }
    ],
    "sg:phone":"+1 508 563 5100",
    "sg:postcode":"02556",
    "sg:province":"MA",
    "wof:name":"Falmouth Realty Assoc LTD",
    "wof:placetype":"venue"
},
  "geometry": {"coordinates":[-70.61223200000001,41.649374],"type":"Point"}
}