{
  "type": "Feature",
  "properties": {
    "addr:full":"510 Riverside Ave Medford MA 02155",
    "addr:housenumber":"510",
    "addr:postcode":"02155",
    "addr:street":"Riverside Ave",
    "iso:country":"US",
    "sg:address":"510 Riverside Ave",
    "sg:city":"Medford",
    "sg:classifiers":[
        {
            "category":"Building & Trades",
            "subcategory":"Construction",
            "type":"Services"
        }
    ],
    "sg:phone":"+1 781 393 0880",
    "sg:postcode":"02155",
    "sg:province":"MA",
    "sg:tags":[
        "roofing",
        "contractor"
    ],
    "wof:name":"Landmark Construction Group",
    "wof:placetype":"venue"
},
  "geometry": {"coordinates":[-71.084414,42.409748],"type":"Point"}
}