{
  "type": "Feature",
  "properties": {
    "iso:country":"US",
    "sg:address":"49 Main St",
    "sg:city":"Kingston",
    "sg:classifiers":[
        {
            "category":"Professional",
            "subcategory":"Computer Services",
            "type":"Services"
        }
    ],
    "sg:phone":"+1 781 585 1341",
    "sg:postcode":"02364",
    "sg:province":"MA",
    "sg:tags":[
        "consultant",
        "product",
        "designer",
        "internet"
    ],
    "wof:name":"24 7 Network Svc",
    "wof:placetype":"venue"
},
  "geometry": {"coordinates":[-70.702169,41.984307],"type":"Point"}
}