{
  "type": "Feature",
  "properties": {
    "iso:country":"US",
    "sg:address":"165 Front St",
    "sg:city":"Chicopee",
    "sg:classifiers":[
        {
            "category":"Manufacturing",
            "subcategory":"Glass & Minerals",
            "type":"Manufacturing & Wholesale Goods"
        }
    ],
    "sg:phone":"+1 413 598 8300",
    "sg:postcode":"01013",
    "sg:province":"MA",
    "sg:tags":[
        "tile"
    ],
    "wof:name":"Equipment Of Culture",
    "wof:placetype":"venue"
},
  "geometry": {"coordinates":[-72.611739,42.148052],"type":"Point"}
}