{
  "type": "Feature",
  "properties": {
    "addr:full": "154 Seekonk St Norfolk MA 02056",
    "addr:housenumber": "154",
    "addr:postcode": "02056",
    "addr:street": "Seekonk St",
    "iso:country": "US",
    "sg:address": "154 Seekonk St",
    "sg:city": "Norfolk",
    "sg:classifiers": [
      {
        "category": "Building \u0026 Trades",
        "subcategory": "Plumbing",
        "type": "Services"
      }
    ],
    "sg:phone": "+1 508 528 6969",
    "sg:postcode": "02056",
    "sg:province": "MA",
    "sg:tags": [
      "plumbing",
      "contractor"
    ],
    "wof:name": "Javco Plumbing \u0026 Heating",
    "wof:placetype": "venue"
  },
  "geometry": {"coordinates":[-71.3122,42.14096],"type":"Point"}
}
