{
  "type": "Feature",
  "properties": {
    "iso:country":"US",
    "sg:address":"55 Ferncroft Rd",
    "sg:city":"Danvers",
    "sg:classifiers":[
        {
            "category":"Professional",
            "subcategory":"Lawyer & Legal Services",
            "type":"Services"
        }
    ],
    "sg:phone":"+1 978 774 7123",
    "sg:postcode":"01923",
    "sg:province":"MA",
    "sg:tags":[
        "attorney"
    ],
    "wof:name":"Mac Lean Holloway Doherty",
    "wof:placetype":"venue"
},
  "geometry": {"coordinates":[-70.969255,42.595606],"type":"Point"}
}