{
  "type": "Feature",
  "properties": {
    "iso:country":"US",
    "sg:address":"169 Nashua Rd",
    "sg:city":"Pepperell",
    "sg:classifiers":[
        {
            "category":"Manufacturing",
            "subcategory":"Printing",
            "type":"Manufacturing & Wholesale Goods"
        }
    ],
    "sg:phone":"+1 978 433 5331",
    "sg:postcode":"01463",
    "sg:province":"MA",
    "sg:tags":[
        "lithographic",
        "commercial",
        "photocopying"
    ],
    "wof:name":"Shattuck Printing",
    "wof:placetype":"venue"
},
  "geometry": {"coordinates":[-71.55462,42.697013],"type":"Point"}
}