{
  "type": "Feature",
  "properties": {
    "addr:full":"69 Taylor Rd Ashby MA 01431",
    "addr:housenumber":"69",
    "addr:postcode":"01431",
    "addr:street":"Taylor Rd",
    "iso:country":"US",
    "sg:address":"69 Taylor Rd",
    "sg:city":"Ashby",
    "sg:classifiers":[
        {
            "category":"Retail",
            "subcategory":"Auto Repair",
            "type":"Services"
        }
    ],
    "sg:phone":"+1 978 342 5540",
    "sg:postcode":"01431",
    "sg:province":"MA",
    "sg:tags":[
        "automobile",
        "restoration",
        "classic"
    ],
    "wof:name":"Twins Auto Body",
    "wof:placetype":"venue"
},
  "geometry": {"coordinates":[-71.78376,42.63743],"type":"Point"}
}