{
  "type": "Feature",
  "properties": {
    "iso:country":"US",
    "sg:address":"732 Washington Ave",
    "sg:city":"Revere",
    "sg:classifiers":[
        {
            "category":"Recreation",
            "type":"Entertainment"
        }
    ],
    "sg:phone":"+1 781 289 8322",
    "sg:postcode":"02151",
    "sg:province":"MA",
    "sg:tags":[
        "instruction",
        "yoga"
    ],
    "wof:name":"Bikrams Yoga Of Woburn Inc",
    "wof:placetype":"venue"
},
  "geometry": {"coordinates":[-71.022451,42.42964],"type":"Point"}
}