{
  "type": "Feature",
  "properties": {
    "addr:full":"20 Maple St Belchertown MA 01007",
    "addr:housenumber":"20",
    "addr:postcode":"01007",
    "addr:street":"Maple St",
    "iso:country":"US",
    "sg:address":"20 Maple St",
    "sg:city":"Belchertown",
    "sg:classifiers":[
        {
            "category":"Museum",
            "type":"Entertainment"
        }
    ],
    "sg:phone":"+1 413 323 6573",
    "sg:postcode":"01007",
    "sg:province":"MA",
    "wof:name":"Belchertown Historical Museum",
    "wof:placetype":"venue"
},
  "geometry": {"coordinates":[-72.40367999999999,42.275628],"type":"Point"}
}