{
  "type": "Feature",
  "properties": {
    "addr:full":"432 Columbia St Cambridge MA 02141",
    "addr:housenumber":"432",
    "addr:postcode":"02141",
    "addr:street":"Columbia St",
    "iso:country":"US",
    "sg:address":"432 Columbia St",
    "sg:city":"Cambridge",
    "sg:classifiers":[
        {
            "category":"Professional",
            "subcategory":"Management & Consulting",
            "type":"Services"
        }
    ],
    "sg:phone":"+1 617 252 9955",
    "sg:postcode":"02141",
    "sg:province":"MA",
    "sg:tags":[
        "communications",
        "consultant"
    ],
    "wof:name":"K T Communications",
    "wof:placetype":"venue"
},
  "geometry": {"coordinates":[-71.093878,42.373808],"type":"Point"}
}