{
  "type": "Feature",
  "properties": {
    "addr:full": "1875 Main St Tewksbury MA 01876",
    "addr:housenumber": "1875",
    "addr:postcode": "01876",
    "addr:street": "Main St",
    "iso:country": "US",
    "sg:address": "1875 Main St",
    "sg:city": "Tewksbury",
    "sg:classifiers": [
      {
        "category": "Home \u0026 Garden",
        "subcategory": "Building Materials",
        "type": "Retail Goods"
      }
    ],
    "sg:phone": "+1 978 851 2285",
    "sg:postcode": "01876",
    "sg:province": "MA",
    "sg:tags": [
      "glass",
      "window",
      "plate"
    ],
    "wof:name": "Glass East \u0026 Mirror Co",
    "wof:placetype": "venue"
  },
  "geometry": {"coordinates":[-71.202622,42.589388],"type":"Point"}
}
