{
  "type": "Feature",
  "properties": {
    "addr:full": "10 Tracy Dr Avon MA 02322",
    "addr:housenumber": "10",
    "addr:postcode": "02322",
    "addr:street": "Tracy Dr",
    "iso:country": "US",
    "sg:address": "10 Tracy Dr",
    "sg:city": "Avon",
    "sg:classifiers": [
      {
        "category": "Manufacturing",
        "subcategory": "Apparel",
        "type": "Manufacturing \u0026 Wholesale Goods"
      }
    ],
    "sg:phone": "+1 508 559 5177",
    "sg:postcode": "02322",
    "sg:province": "MA",
    "sg:tags": [
      "mfg"
    ],
    "wof:name": "Finely Done",
    "wof:placetype": "venue"
  },
  "geometry": {"coordinates":[-71.052058,42.125352],"type":"Point"}
}
