{
  "type": "Feature",
  "properties": {
    "iso:country":"US",
    "sg:address":"10 Tracy Dr",
    "sg:city":"Avon",
    "sg:classifiers":[
        {
            "category":"Manufacturing",
            "subcategory":"Apparel",
            "type":"Manufacturing & Wholesale Goods"
        }
    ],
    "sg:phone":"+1 508 559 5177",
    "sg:postcode":"02322",
    "sg:province":"MA",
    "sg:tags":[
        "mfg"
    ],
    "wof:name":"Finely Done",
    "wof:placetype":"venue"
},
  "geometry": {"coordinates":[-71.052058,42.125352],"type":"Point"}
}