{
  "type": "Feature",
  "properties": {
    "iso:country":"US",
    "sg:address":"8 Main St",
    "sg:city":"Rockport",
    "sg:classifiers":[
        {
            "category":"Shopping",
            "type":"Retail Goods"
        }
    ],
    "sg:phone":"+1 978 546 2654",
    "sg:postcode":"01966",
    "sg:province":"MA",
    "sg:tags":[
        "art",
        "gallery",
        "dealer"
    ],
    "wof:name":"Ivan N Kamalic Gallery",
    "wof:placetype":"venue"
},
  "geometry": {"coordinates":[-70.61850200000001,42.658233],"type":"Point"}
}