{
  "type": "Feature",
  "properties": {
    "addr:full": "26 Water St Newburyport MA 01950",
    "addr:housenumber": "26",
    "addr:postcode": "01950",
    "addr:street": "Water St",
    "iso:country": "US",
    "sg:address": "26 Water St",
    "sg:city": "Newburyport",
    "sg:classifiers": [
      {
        "category": "Retail",
        "subcategory": "Laundry \u0026 Dry Cleaning",
        "type": "Services"
      }
    ],
    "sg:phone": "+1 978 465 9048",
    "sg:postcode": "01950",
    "sg:province": "MA",
    "wof:name": "Village Wash Tub Laundromat",
    "wof:placetype": "venue"
  },
  "geometry": {"coordinates":[-70.86925,42.811665],"type":"Point"}
}
