{
  "type": "Feature",
  "properties": {
    "iso:country":"US",
    "sg:address":"22 Quincy St",
    "sg:city":"Ludlow",
    "sg:classifiers":[
        {
            "category":"Real Estate",
            "subcategory":"Real Estate Operator",
            "type":"Services"
        }
    ],
    "sg:phone":"+1 413 583 2029",
    "sg:postcode":"01056",
    "sg:province":"MA",
    "sg:tags":[
        "apartment"
    ],
    "wof:name":"Roland Lavoie Apartments",
    "wof:placetype":"venue"
},
  "geometry": {"coordinates":[-72.478033,42.174602],"type":"Point"}
}