{
  "type": "Feature",
  "properties": {
    "addr:full": "639 Granite St Braintree MA 02184",
    "addr:housenumber": "639",
    "addr:postcode": "02184",
    "addr:street": "Granite St",
    "iso:country": "US",
    "sg:address": "639 Granite St",
    "sg:city": "Braintree",
    "sg:classifiers": [
      {
        "category": "Social Services",
        "type": "Services"
      },
      {
        "category": "Health Services",
        "subcategory": "Doctor",
        "type": "Services"
      },
      {
        "category": "Personal",
        "type": "Services"
      },
      {
        "category": "Health Services",
        "subcategory": "Clinic",
        "type": "Services"
      }
    ],
    "sg:phone": "+1 781 848 7745",
    "sg:postcode": "02184",
    "sg:province": "MA",
    "sg:tags": [
      "individual",
      "mental",
      "family",
      "psychologist",
      "therapist",
      "marriage",
      "child",
      "counseling",
      "counselor"
    ],
    "sg:website": "http://www.relationshipresources.biz",
    "wof:name": "Relationship Resources",
    "wof:placetype": "venue"
  },
  "geometry": {"coordinates":[-71.021128,42.208398],"type":"Point"}
}
