{
  "type": "Feature",
  "properties": {
    "iso:country":"US",
    "sg:address":"20 Linden Street",
    "sg:city":"Allston",
    "sg:classifiers":[
        {
            "category":"Communications",
            "subcategory":"Radio Station",
            "type":"Services"
        }
    ],
    "sg:phone":"+1 617 787 5900",
    "sg:postcode":"02134",
    "sg:province":"MA",
    "sg:tags":[
        "equipment"
    ],
    "wof:name":"Russian Radio Network",
    "wof:placetype":"venue"
},
  "geometry": {"coordinates":[-71.13072099999999,42.355148],"type":"Point"}
}