{
  "type": "Feature",
  "properties": {
    "iso:country":"US",
    "sg:address":"660 Main St",
    "sg:city":"Woburn",
    "sg:classifiers":[
        {
            "category":"Professional",
            "subcategory":"Research",
            "type":"Services"
        }
    ],
    "sg:phone":"+1 781 933 5653",
    "sg:postcode":"01801",
    "sg:province":"MA",
    "wof:name":"Advanced Vision Research",
    "wof:placetype":"venue"
},
  "geometry": {"coordinates":[-71.153994,42.491333],"type":"Point"}
}