{
  "type": "Feature",
  "properties": {
    "iso:country":"US",
    "sg:address":"875 Massachusetts Ave",
    "sg:city":"Cambridge",
    "sg:classifiers":[
        {
            "category":"Health Services",
            "subcategory":"Health Practitioner",
            "type":"Services"
        }
    ],
    "sg:phone":"+1 617 868 1814",
    "sg:postcode":"02139",
    "sg:province":"MA",
    "sg:tags":[
        "psychotherapist"
    ],
    "wof:name":"Sharon Roberts",
    "wof:placetype":"venue"
},
  "geometry": {"coordinates":[-71.10701400000001,42.367427],"type":"Point"}
}