{
  "type": "Feature",
  "properties": {
    "iso:country":"US",
    "sg:address":"52 Accord Park Dr",
    "sg:city":"Norwell",
    "sg:classifiers":[
        {
            "category":"Professional",
            "subcategory":"Computer Services",
            "type":"Services"
        }
    ],
    "sg:phone":"+1   ",
    "sg:postcode":"02061",
    "sg:province":"MA",
    "sg:tags":[
        "prepackaged",
        "software"
    ],
    "wof:name":"Microsoft Corporation",
    "wof:placetype":"venue"
},
  "geometry": {"coordinates":[-70.886448,42.165794],"type":"Point"}
}