{
  "type": "Feature",
  "properties": {
    "addr:full": "63 Jefferson Street Winthrop MA 02152",
    "addr:housenumber": "63",
    "addr:postcode": "02152",
    "addr:street": "Jefferson Street",
    "iso:country": "US",
    "sg:address": "63 Jefferson Street",
    "sg:city": "Winthrop",
    "sg:classifiers": [
      {
        "category": "Arts \u0026 Performance",
        "subcategory": "Art Gallery",
        "type": "Entertainment"
      }
    ],
    "sg:phone": "+1 617 846 0376",
    "sg:postcode": "02152",
    "sg:province": "MA",
    "wof:name": "Classic Art Galleries",
    "wof:placetype": "venue"
  },
  "geometry": {"coordinates":[-70.985246,42.375061],"type":"Point"}
}
