{
  "type": "Feature",
  "properties": {
    "iso:country":"US",
    "sg:address":"36 Exchange St",
    "sg:city":"Holliston",
    "sg:classifiers":[
        {
            "category":"Professional",
            "subcategory":"Engineering",
            "type":"Services"
        }
    ],
    "sg:phone":"+1 508 429 8201",
    "sg:postcode":"01746",
    "sg:province":"MA",
    "sg:tags":[
        "engineer"
    ],
    "wof:name":"Ernie Dennison Assoc Inc",
    "wof:placetype":"venue"
},
  "geometry": {"coordinates":[-71.428213,42.198914],"type":"Point"}
}