{
  "type": "Feature",
  "properties": {
    "iso:country":"US",
    "sg:address":"22 Clifton St",
    "sg:city":"Somerville",
    "sg:classifiers":[
        {
            "category":"Manufacturing",
            "subcategory":"Building Materials",
            "type":"Manufacturing & Wholesale Goods"
        }
    ],
    "sg:phone":"+1 617 628 3000",
    "sg:postcode":"02144",
    "sg:province":"MA",
    "wof:name":"J P Moriarty Millwork",
    "wof:placetype":"venue"
},
  "geometry": {"coordinates":[-71.11766299999999,42.396063],"type":"Point"}
}