{
  "type": "Feature",
  "properties": {
    "addr:full":"71 West St Medfield MA 02052",
    "addr:housenumber":"71",
    "addr:postcode":"02052",
    "addr:street":"West St",
    "iso:country":"US",
    "sg:address":"71 West St",
    "sg:city":"Medfield",
    "sg:classifiers":[
        {
            "category":"Manufacturing",
            "subcategory":"Printing",
            "type":"Manufacturing & Wholesale Goods"
        }
    ],
    "sg:phone":"+1 508 359 2786",
    "sg:postcode":"02052",
    "sg:province":"MA",
    "sg:tags":[
        "screen"
    ],
    "sg:website":"www.milarasmt.com",
    "wof:name":"MILARA Inc",
    "wof:placetype":"venue"
},
  "geometry": {"coordinates":[-71.325059,42.191526],"type":"Point"}
}