{
  "type": "Feature",
  "properties": {
    "addr:full": "800 Middle Rd Acushnet MA 02743",
    "addr:housenumber": "800",
    "addr:postcode": "02743",
    "addr:street": "Middle Rd",
    "iso:country": "US",
    "ovtr:label": "Acushnet Elementary School, 800 Middle Rd Acushnet MA US",
    "ovtr:similarity": 3.933471918106079,
    "sg:address": "800 Middle Rd",
    "sg:city": "Acushnet",
    "sg:classifiers": [
      {
        "category": "Education",
        "subcategory": "School",
        "type": "Public Place"
      }
    ],
    "sg:phone": "+1 508 998 0255",
    "sg:postcode": "02743",
    "sg:province": "MA",
    "wof:name": "Acushnet Elementary School",
    "wof:placetype": "venue"
  },
  "geometry": {"coordinates":[-70.911087,41.731708],"type":"Point"}
}
