{
  "type": "Feature",
  "properties": {
    "addr:full": "114 Essex Rd Ipswich MA 01938",
    "addr:housenumber": "114",
    "addr:postcode": "01938",
    "addr:street": "Essex Rd",
    "iso:country": "US",
    "sg:address": "114 Essex Rd",
    "sg:city": "Ipswich",
    "sg:classifiers": [
      {
        "category": "Organizations",
        "subcategory": "Community Association",
        "type": "Services"
      }
    ],
    "sg:phone": "+1 978 356 0216",
    "sg:postcode": "01938",
    "sg:province": "MA",
    "sg:tags": [
      "environmental",
      "org"
    ],
    "wof:name": "North American Wolf Foundation",
    "wof:placetype": "venue"
  },
  "geometry": {"coordinates":[-70.81423,42.655598],"type":"Point"}
}
