{
  "type": "Feature",
  "properties": {
    "addr:full": "578 Columbia Road Dorchester MA 02125",
    "addr:housenumber": "578",
    "addr:postcode": "02125",
    "addr:street": "Columbia Road",
    "iso:country": "US",
    "sg:address": "578 Columbia Road",
    "sg:city": "Dorchester",
    "sg:classifiers": [
      {
        "category": "Building \u0026 Trades",
        "subcategory": "Construction",
        "type": "Services"
      }
    ],
    "sg:phone": "+1 617 825 9339",
    "sg:postcode": "02125",
    "sg:province": "MA",
    "sg:tags": [
      "contractor"
    ],
    "wof:name": "Technical Construction Services",
    "wof:placetype": "venue"
  },
  "geometry": {"coordinates":[-71.065517,42.316673],"type":"Point"}
}
