{
  "type": "Feature",
  "properties": {
    "addr:full":"93 Cordaville Rd Ashland MA 01721",
    "addr:housenumber":"93",
    "addr:postcode":"01721",
    "addr:street":"Cordaville Rd",
    "iso:country":"US",
    "sg:address":"93 Cordaville Rd",
    "sg:city":"Ashland",
    "sg:classifiers":[
        {
            "category":"Home & Garden",
            "subcategory":"Carpets & Floor Coverings",
            "type":"Retail Goods"
        }
    ],
    "sg:phone":"+1 508 881 8876",
    "sg:postcode":"01721",
    "sg:province":"MA",
    "sg:tags":[
        "dealer",
        "rug"
    ],
    "wof:name":"Carpet Showroom T & R Carpets",
    "wof:placetype":"venue"
},
  "geometry": {"coordinates":[-71.485871,42.265404],"type":"Point"}
}