{
  "type": "Feature",
  "properties": {
    "iso:country":"US",
    "sg:address":"22 Waverly St",
    "sg:city":"Ashland",
    "sg:classifiers":[
        {
            "category":"Autos & Motor Vehicles",
            "subcategory":"Fuel & Gas Station",
            "type":"Retail Goods"
        }
    ],
    "sg:phone":"+1 508 875 4280",
    "sg:postcode":"01721",
    "sg:province":"MA",
    "sg:tags":[
        "oil"
    ],
    "wof:name":"Framingham Mobil",
    "wof:placetype":"venue"
},
  "geometry": {"coordinates":[-71.446736,42.265411],"type":"Point"}
}