{
  "type": "Feature",
  "properties": {
    "addr:full": "12 Highland Ave Arlington MA 02476",
    "addr:housenumber": "12",
    "addr:postcode": "02476",
    "addr:street": "Highland Ave",
    "iso:country": "US",
    "sg:address": "12 Highland Ave",
    "sg:city": "Arlington",
    "sg:classifiers": [
      {
        "category": "Professional",
        "subcategory": "Computer Services",
        "type": "Services"
      }
    ],
    "sg:phone": "+1 781 316 1999",
    "sg:postcode": "02476",
    "sg:province": "MA",
    "sg:tags": [
      "website",
      "design"
    ],
    "sg:website": "www.bowmandesign.com",
    "wof:name": "Bowman Design",
    "wof:placetype": "venue"
  },
  "geometry": {"coordinates":[-71.165305,42.417656],"type":"Point"}
}
