{
  "type": "Feature",
  "properties": {
    "iso:country":"US",
    "sg:address":"45 Union Sq",
    "sg:city":"Somerville",
    "sg:classifiers":[
        {
            "category":"Food & Beverages",
            "subcategory":"Groceries & Convenience Stores",
            "type":"Retail Goods"
        }
    ],
    "sg:phone":"+1 617 623 9620",
    "sg:postcode":"02143",
    "sg:province":"MA",
    "sg:tags":[
        "market"
    ],
    "wof:name":"Reliable Meat Mkt",
    "wof:placetype":"venue"
},
  "geometry": {"coordinates":[-71.096502,42.379876],"type":"Point"}
}