{
  "type": "Feature",
  "properties": {
    "iso:country":"US",
    "sg:address":"25 Toby Garden St",
    "sg:city":"Duxbury",
    "sg:classifiers":[
        {
            "category":"Wholesale",
            "subcategory":"Stationery",
            "type":"Manufacturing & Wholesale Goods"
        }
    ],
    "sg:phone":"+1 781 934 5885",
    "sg:postcode":"02332",
    "sg:province":"MA",
    "sg:tags":[
        "supply"
    ],
    "wof:name":"Punkins Papers",
    "wof:placetype":"venue"
},
  "geometry": {"coordinates":[-70.701336,42.025964],"type":"Point"}
}