{
  "type": "Feature",
  "properties": {
    "addr:full": "25 Toby Garden St Duxbury MA 02332",
    "addr:housenumber": "25",
    "addr:postcode": "02332",
    "addr:street": "Toby Garden St",
    "iso:country": "US",
    "sg:address": "25 Toby Garden St",
    "sg:city": "Duxbury",
    "sg:classifiers": [
      {
        "category": "Wholesale",
        "subcategory": "Stationery",
        "type": "Manufacturing \u0026 Wholesale Goods"
      }
    ],
    "sg:phone": "+1 781 934 5885",
    "sg:postcode": "02332",
    "sg:province": "MA",
    "sg:tags": [
      "supply"
    ],
    "wof:name": "Punkins Papers",
    "wof:placetype": "venue"
  },
  "geometry": {"coordinates":[-70.701336,42.025964],"type":"Point"}
}
