{
  "type": "Feature",
  "properties": {
    "addr:full": "656 Laurel St Longmeadow MA 01106",
    "addr:housenumber": "656",
    "addr:postcode": "01106",
    "addr:street": "Laurel St",
    "iso:country": "US",
    "sg:address": "656 Laurel St",
    "sg:city": "Longmeadow",
    "sg:classifiers": [
      {
        "category": "Banks \u0026 Credit Unions",
        "subcategory": "Financial Services",
        "type": "Services"
      }
    ],
    "sg:phone": "+1   ",
    "sg:postcode": "01106",
    "sg:province": "MA",
    "sg:tags": [
      "investment",
      "closed"
    ],
    "wof:name": "Ajay Ltd Partneship",
    "wof:placetype": "venue"
  },
  "geometry": {"coordinates":[-72.573139,42.051521],"type":"Point"}
}
