{
  "type": "Feature",
  "properties": {
    "iso:country":"US",
    "sg:address":"656 Laurel St",
    "sg:city":"Longmeadow",
    "sg:classifiers":[
        {
            "category":"Banks & Credit Unions",
            "subcategory":"Financial Services",
            "type":"Services"
        }
    ],
    "sg:phone":"+1   ",
    "sg:postcode":"01106",
    "sg:province":"MA",
    "sg:tags":[
        "investment",
        "closed"
    ],
    "wof:name":"Ajay Ltd Partneship",
    "wof:placetype":"venue"
},
  "geometry": {"coordinates":[-72.573139,42.051521],"type":"Point"}
}