{
  "type": "Feature",
  "properties": {
    "addr:full": "81 Alma St Lowell MA 01854",
    "addr:housenumber": "81",
    "addr:postcode": "01854",
    "addr:street": "Alma St",
    "iso:country": "US",
    "sg:address": "81 Alma St",
    "sg:city": "Lowell",
    "sg:classifiers": [
      {
        "category": "Building \u0026 Trades",
        "subcategory": "Electrical",
        "type": "Services"
      }
    ],
    "sg:phone": "+1 978 453 2338",
    "sg:postcode": "01854",
    "sg:province": "MA",
    "sg:tags": [
      "electric",
      "contractor"
    ],
    "wof:name": "Berube Electric Svc",
    "wof:placetype": "venue"
  },
  "geometry": {"coordinates":[-71.324501,42.65901],"type":"Point"}
}
