{
  "type": "Feature",
  "properties": {
    "addr:full": "2 Seaport Ln Boston MA 02210",
    "addr:housenumber": "2",
    "addr:postcode": "02210",
    "addr:street": "Seaport Ln",
    "iso:country": "US",
    "sg:address": "2 Seaport Ln",
    "sg:city": "Boston",
    "sg:classifiers": [
      {
        "category": "Structure",
        "subcategory": "Office Building",
        "type": "Public Place"
      }
    ],
    "sg:phone": "+1 617 261 9541",
    "sg:postcode": "02210",
    "sg:province": "MA",
    "sg:tags": [
      "park"
    ],
    "wof:name": "A-799 Ninth Street",
    "wof:placetype": "venue"
  },
  "geometry": {"coordinates":[-71.040802,42.349621],"type":"Point"}
}
