{
  "type": "Feature",
  "properties": {
    "addr:full":"25 Depot Rd Harvard MA 01451",
    "addr:housenumber":"25",
    "addr:postcode":"01451",
    "addr:street":"Depot Rd",
    "iso:country":"US",
    "sg:address":"25 Depot Rd",
    "sg:city":"Harvard",
    "sg:phone":"+1 978 456 9110",
    "sg:postcode":"01451",
    "sg:province":"MA",
    "sg:tags":[
        "oil"
    ],
    "wof:name":"West Heating Oil Inc",
    "wof:placetype":"venue"
},
  "geometry": {"coordinates":[-71.589237,42.508646],"type":"Point"}
}