{
  "type": "Feature",
  "properties": {
    "addr:full":"110 Commonwealth Ave Concord MA 01742",
    "addr:housenumber":"110",
    "addr:postcode":"01742",
    "addr:street":"Commonwealth Ave",
    "iso:country":"US",
    "sg:address":"110 Commonwealth Ave",
    "sg:city":"Concord",
    "sg:classifiers":[
        {
            "category":"Shopping",
            "subcategory":"Gifts & Souvenirs",
            "type":"Retail Goods"
        }
    ],
    "sg:phone":"+1 978 369 0252",
    "sg:postcode":"01742",
    "sg:province":"MA",
    "sg:tags":[
        "shop"
    ],
    "wof:name":"Gatehouse",
    "wof:placetype":"venue"
},
  "geometry": {"coordinates":[-71.39577800000001,42.457343],"type":"Point"}
}