{
  "type": "Feature",
  "properties": {
    "iso:country":"US",
    "sg:address":"550 Chicopee St",
    "sg:city":"Chicopee",
    "sg:classifiers":[
        {
            "category":"Coffee & Tea",
            "type":"Food & Drink"
        },
        {
            "category":"Restaurant",
            "type":"Food & Drink"
        }
    ],
    "sg:phone":"+1 413 536 1935",
    "sg:postcode":"01013",
    "sg:province":"MA",
    "sg:tags":[
        "espresso"
    ],
    "wof:name":"Colonial Cafe",
    "wof:placetype":"venue"
},
  "geometry": {"coordinates":[-72.61531100000001,42.181591],"type":"Point"}
}