{
  "type": "Feature",
  "properties": {
    "addr:full": "550 Chicopee St Chicopee MA 01013",
    "addr:housenumber": "550",
    "addr:postcode": "01013",
    "addr:street": "Chicopee St",
    "iso:country": "US",
    "ovtr:label": "Colonial Cafe, 550 Chicopee St Chicopee MA US",
    "ovtr:similarity": 2.3796029090881348,
    "sg:address": "550 Chicopee St",
    "sg:city": "Chicopee",
    "sg:classifiers": [
      {
        "category": "Coffee \u0026 Tea",
        "type": "Food \u0026 Drink"
      },
      {
        "category": "Restaurant",
        "type": "Food \u0026 Drink"
      }
    ],
    "sg:phone": "+1 413 536 1935",
    "sg:postcode": "01013",
    "sg:province": "MA",
    "sg:tags": [
      "espresso"
    ],
    "wof:name": "Colonial Cafe",
    "wof:placetype": "venue"
  },
  "geometry": {"coordinates":[-72.615311,42.181591],"type":"Point"}
}
