{
  "type": "Feature",
  "properties": {
    "addr:full": "95 Post Office Park Wilbraham MA 01095",
    "addr:housenumber": "95",
    "addr:postcode": "01095",
    "addr:street": "Post Office Park",
    "iso:country": "US",
    "sg:address": "95 Post Office Park",
    "sg:city": "Wilbraham",
    "sg:classifiers": [
      {
        "category": "Banks \u0026 Credit Unions",
        "subcategory": "Investment Brokerage",
        "type": "Services"
      }
    ],
    "sg:phone": "+1 413 596 6300",
    "sg:postcode": "01095",
    "sg:province": "MA",
    "sg:tags": [
      "consultant",
      "planning",
      "financial"
    ],
    "wof:name": "Joseph Carr Assoc",
    "wof:placetype": "venue"
  },
  "geometry": {"coordinates":[-72.443657,42.149193],"type":"Point"}
}
