{
  "type": "Feature",
  "properties": {
    "iso:country":"US",
    "sg:address":"82 Central St",
    "sg:city":"Ipswich",
    "sg:classifiers":[
        {
            "category":"Personal",
            "type":"Services"
        }
    ],
    "sg:phone":"+1   ",
    "sg:postcode":"01938",
    "sg:province":"MA",
    "wof:name":"Handyman Services",
    "wof:placetype":"venue"
},
  "geometry": {"coordinates":[-70.84046499999999,42.681782],"type":"Point"}
}