{
  "type": "Feature",
  "properties": {
    "addr:full": "168 Main St Stoneham MA 02180",
    "addr:housenumber": "168",
    "addr:postcode": "02180",
    "addr:street": "Main St",
    "iso:country": "US",
    "sg:address": "168 Main St",
    "sg:city": "Stoneham",
    "sg:classifiers": [
      {
        "category": "Real Estate",
        "subcategory": "Real Estate Agent",
        "type": "Services"
      }
    ],
    "sg:phone": "+1   ",
    "sg:postcode": "02180",
    "sg:province": "MA",
    "wof:name": "E R Andrew Schmid Inc",
    "wof:placetype": "venue"
  },
  "geometry": {"coordinates":[-71.100145,42.489975],"type":"Point"}
}
