{
  "type": "Feature",
  "properties": {
    "addr:full":"570 Mill St Worcester MA 01602",
    "addr:housenumber":"570",
    "addr:postcode":"01602",
    "addr:street":"Mill St",
    "iso:country":"US",
    "sg:address":"570 Mill St",
    "sg:city":"Worcester",
    "sg:classifiers":[
        {
            "category":"Organizations",
            "subcategory":"Community Association",
            "type":"Services"
        }
    ],
    "sg:phone":"+1 508 799 4054",
    "sg:postcode":"01602",
    "sg:province":"MA",
    "sg:tags":[
        "club"
    ],
    "wof:name":"Tatnuck Post 288",
    "wof:placetype":"venue"
},
  "geometry": {"coordinates":[-71.854156,42.274622],"type":"Point"}
}