{
  "type": "Feature",
  "properties": {
    "addr:full":"89 Locke Rd Chelmsford MA 01824",
    "addr:housenumber":"89",
    "addr:postcode":"01824",
    "addr:street":"Locke Rd",
    "iso:country":"US",
    "sg:address":"89 Locke Rd",
    "sg:city":"Chelmsford",
    "sg:classifiers":[
        {
            "category":"Building & Trades",
            "subcategory":"Construction",
            "type":"Services"
        }
    ],
    "sg:phone":"+1 978 857 0780",
    "sg:postcode":"01824",
    "sg:province":"MA",
    "sg:tags":[
        "carpenter"
    ],
    "wof:name":"The Complete Carpenter",
    "wof:placetype":"venue"
},
  "geometry": {"coordinates":[-71.37469400000001,42.607612],"type":"Point"}
}