{
  "type": "Feature",
  "properties": {
    "iso:country":"US",
    "sg:address":"424 Main St",
    "sg:city":"Woburn",
    "sg:classifiers":[
        {
            "category":"Personal",
            "subcategory":"Nail Salon",
            "type":"Services"
        }
    ],
    "sg:phone":"+1 781 935 4694",
    "sg:postcode":"01801",
    "sg:province":"MA",
    "wof:name":"California Nail by Pro - CLOSED",
    "wof:placetype":"venue"
},
  "geometry": {"coordinates":[-71.1511,42.483398],"type":"Point"}
}