{
  "type": "Feature",
  "properties": {
    "iso:country":"US",
    "sg:address":"1553 Osterville-West Barnstable Rd",
    "sg:city":"West Barnstable",
    "sg:classifiers":[
        {
            "category":"Autos & Motor Vehicles",
            "subcategory":"Automobile Sales",
            "type":"Retail Goods"
        }
    ],
    "sg:phone":"+1   ",
    "sg:postcode":"02668",
    "sg:province":"MA",
    "sg:tags":[
        "used"
    ],
    "wof:name":"No Look Motors Inc",
    "wof:placetype":"venue"
},
  "geometry": {"coordinates":[-70.388059,41.683604],"type":"Point"}
}