{
  "type": "Feature",
  "properties": {
    "iso:country":"US",
    "sg:address":"475 Hancock St Ste 4",
    "sg:city":"Quincy",
    "sg:classifiers":[
        {
            "category":"Shopping",
            "subcategory":"Clothing, Apparel, & Fashions",
            "type":"Retail Goods"
        },
        {
            "category":"Sports & Exercise",
            "subcategory":"Swimming Pool",
            "type":"Entertainment"
        }
    ],
    "sg:phone":"+1 617 847 6193",
    "sg:postcode":"02171",
    "sg:province":"MA",
    "sg:tags":[
        "hosiery",
        "swimwear",
        "accessory",
        "apparel",
        "lingerie",
        "handbag",
        "girls'",
        "women's",
        "clothing",
        "store"
    ],
    "sg:website":"http://www.fashionbug.com",
    "wof:name":"Fashion Bug",
    "wof:placetype":"venue"
},
  "geometry": {"coordinates":[-71.022982,42.271844],"type":"Point"}
}