{
  "type": "Feature",
  "properties": {
    "iso:country":"US",
    "sg:address":"86 Pilgrim Rd",
    "sg:city":"Boston",
    "sg:classifiers":[
        {
            "category":"Personal",
            "subcategory":"Tanning Parlor",
            "type":"Services"
        }
    ],
    "sg:phone":"+1 617 738 2631",
    "sg:postcode":"02215",
    "sg:province":"MA",
    "sg:tags":[
        "salon"
    ],
    "wof:name":"Tanning Plar",
    "wof:placetype":"venue"
},
  "geometry": {"coordinates":[-71.10663099999999,42.341096],"type":"Point"}
}