{
  "type": "Feature",
  "properties": {
    "addr:full": "86 Pilgrim Rd Boston MA 02215",
    "addr:housenumber": "86",
    "addr:postcode": "02215",
    "addr:street": "Pilgrim Rd",
    "iso:country": "US",
    "sg:address": "86 Pilgrim Rd",
    "sg:city": "Boston",
    "sg:classifiers": [
      {
        "category": "Personal",
        "subcategory": "Tanning Parlor",
        "type": "Services"
      }
    ],
    "sg:phone": "+1 617 738 2631",
    "sg:postcode": "02215",
    "sg:province": "MA",
    "sg:tags": [
      "salon"
    ],
    "wof:name": "Tanning Plar",
    "wof:placetype": "venue"
  },
  "geometry": {"coordinates":[-71.106631,42.341096],"type":"Point"}
}
