{
  "type": "Feature",
  "properties": {
    "iso:country":"US",
    "sg:address":"564 E 1st St",
    "sg:city":"Boston",
    "sg:classifiers":[
        {
            "category":"Manufacturing",
            "subcategory":"Building Materials",
            "type":"Manufacturing & Wholesale Goods"
        }
    ],
    "sg:phone":"+1 617 269 1921",
    "sg:postcode":"02127",
    "sg:province":"MA",
    "sg:tags":[
        "mfg",
        "household",
        "cabinet",
        "wood",
        "kitchen",
        "furniture"
    ],
    "wof:name":"Richmond Furniture Mfg Co",
    "wof:placetype":"venue"
},
  "geometry": {"coordinates":[-71.037537,42.338169],"type":"Point"}
}