{
  "type": "Feature",
  "properties": {
    "addr:full":"123 Macarthur Dr New Bedford MA 02740",
    "addr:housenumber":"123",
    "addr:postcode":"02740",
    "addr:street":"Macarthur Dr",
    "iso:country":"US",
    "sg:address":"123 Macarthur Dr",
    "sg:city":"New Bedford",
    "sg:classifiers":[
        {
            "category":"Restaurant",
            "type":"Food & Drink"
        }
    ],
    "sg:phone":"+1 508 991 3336",
    "sg:postcode":"02740",
    "sg:province":"MA",
    "wof:name":"Royal Restaurant II",
    "wof:placetype":"venue"
},
  "geometry": {"coordinates":[-70.92109600000001,41.627624],"type":"Point"}
}