{
  "type": "Feature",
  "properties": {
    "addr:full": "1889 Memorial Dr Chicopee MA 01020",
    "addr:housenumber": "1889",
    "addr:postcode": "01020",
    "addr:street": "Memorial Dr",
    "iso:country": "US",
    "sg:address": "1889 Memorial Dr",
    "sg:city": "Chicopee",
    "sg:classifiers": [
      {
        "category": "Shopping",
        "type": "Retail Goods"
      }
    ],
    "sg:phone": "+1 413 534 1255",
    "sg:postcode": "01020",
    "sg:province": "MA",
    "sg:tags": [
      "pet",
      "shop"
    ],
    "wof:name": "Pet-O-Rama",
    "wof:placetype": "venue"
  },
  "geometry": {"coordinates":[-72.571188,42.208724],"type":"Point"}
}
