{
  "type": "Feature",
  "properties": {
    "addr:full": "15 Townsend Rd Lynnfield MA 01940",
    "addr:housenumber": "15",
    "addr:postcode": "01940",
    "addr:street": "Townsend Rd",
    "iso:country": "US",
    "sg:address": "15 Townsend Rd",
    "sg:city": "Lynnfield",
    "sg:classifiers": [
      {
        "category": "Shopping",
        "subcategory": "Used Merchandise",
        "type": "Retail Goods"
      }
    ],
    "sg:phone": "+1   ",
    "sg:postcode": "01940",
    "sg:province": "MA",
    "wof:name": "Christmas Country",
    "wof:placetype": "venue"
  },
  "geometry": {"coordinates":[-71.058466,42.546796],"type":"Point"}
}
