{
  "type": "Feature",
  "properties": {
    "addr:full": "14 Main St Upton MA 01568",
    "addr:housenumber": "14",
    "addr:postcode": "01568",
    "addr:street": "Main St",
    "iso:country": "US",
    "sg:address": "14 Main St",
    "sg:city": "Upton",
    "sg:classifiers": [
      {
        "category": "Retail",
        "subcategory": "Car Wash",
        "type": "Services"
      }
    ],
    "sg:phone": "+1 508 529 4285",
    "sg:postcode": "01568",
    "sg:province": "MA",
    "sg:tags": [
      "automobile",
      "detailing"
    ],
    "wof:name": "Bill's Detailing",
    "wof:placetype": "venue"
  },
  "geometry": {"coordinates":[-71.604692,42.171154],"type":"Point"}
}
