{
  "type": "Feature",
  "properties": {
    "addr:full":"301 Commercial St Provincetown MA 02657",
    "addr:housenumber":"301",
    "addr:postcode":"02657",
    "addr:street":"Commercial St",
    "iso:country":"US",
    "sg:address":"301 Commercial St",
    "sg:city":"Provincetown",
    "sg:classifiers":[
        {
            "category":"Shopping",
            "subcategory":"Gifts & Souvenirs",
            "type":"Retail Goods"
        }
    ],
    "sg:phone":"+1 508 487 1136",
    "sg:postcode":"02657",
    "sg:province":"MA",
    "sg:tags":[
        "shop"
    ],
    "sg:website":"www.friendsofheart.com",
    "wof:name":"Friends Of Heart",
    "wof:placetype":"venue"
},
  "geometry": {"coordinates":[-70.185677,42.051866],"type":"Point"}
}