{
  "type": "Feature",
  "properties": {
    "addr:full": "235 Viscoloid Ave Leominster MA 01453",
    "addr:housenumber": "235",
    "addr:postcode": "01453",
    "addr:street": "Viscoloid Ave",
    "iso:country": "US",
    "sg:address": "235 Viscoloid Ave",
    "sg:city": "Leominster",
    "sg:classifiers": [
      {
        "category": "Real Estate",
        "subcategory": "Developer",
        "type": "Services"
      }
    ],
    "sg:phone": "+1 978 537 1700",
    "sg:postcode": "01453",
    "sg:province": "MA",
    "wof:name": "Crossroads Office Park",
    "wof:placetype": "venue"
  },
  "geometry": {"coordinates":[-71.741997,42.514389],"type":"Point"}
}
