{
  "type": "Feature",
  "properties": {
    "iso:country":"US",
    "sg:address":"36 Mechanic St",
    "sg:city":"Foxboro",
    "sg:classifiers":[
        {
            "category":"Wholesale",
            "subcategory":"Toys & Hobbies",
            "type":"Manufacturing & Wholesale Goods"
        }
    ],
    "sg:phone":"+1 508 543 1084",
    "sg:postcode":"02035",
    "sg:province":"MA",
    "sg:tags":[
        "wholesaler"
    ],
    "wof:name":"National City Wholesale",
    "wof:placetype":"venue"
},
  "geometry": {"coordinates":[-71.244106,42.068192],"type":"Point"}
}