{
  "type": "Feature",
  "properties": {
    "iso:country":"US",
    "sg:address":"718 Main St",
    "sg:city":"Fitchburg",
    "sg:classifiers":[
        {
            "category":"Government",
            "subcategory":"Office",
            "type":"Public Place"
        }
    ],
    "sg:phone":"+1 978 345 9576",
    "sg:postcode":"01420",
    "sg:province":"MA",
    "sg:tags":[
        "village"
    ],
    "wof:name":"Fitchburg Purchasing Dept",
    "wof:placetype":"venue"
},
  "geometry": {"coordinates":[-71.803597,42.584146],"type":"Point"}
}