{
  "type": "Feature",
  "properties": {
    "addr:full":"80 Harrison Ave Woburn MA 01801",
    "addr:housenumber":"80",
    "addr:postcode":"01801",
    "addr:street":"Harrison Ave",
    "iso:country":"US",
    "sg:address":"80 Harrison Ave",
    "sg:city":"Woburn",
    "sg:classifiers":[
        {
            "category":"Professional",
            "subcategory":"Management & Consulting",
            "type":"Services"
        }
    ],
    "sg:phone":"+1   ",
    "sg:postcode":"01801",
    "sg:province":"MA",
    "sg:tags":[
        "business"
    ],
    "wof:name":"Laura Anamateros",
    "wof:placetype":"venue"
},
  "geometry": {"coordinates":[-71.162023,42.480028],"type":"Point"}
}