{
  "type": "Feature",
  "properties": {
    "iso:country":"US",
    "sg:address":"151 Park Ave",
    "sg:city":"Dalton",
    "sg:classifiers":[
        {
            "category":"Arts & Performance",
            "subcategory":"Theater",
            "type":"Entertainment"
        }
    ],
    "sg:phone":"+1 413 684 4441",
    "sg:postcode":"01226",
    "sg:province":"MA",
    "sg:tags":[
        "television",
        "program",
        "producer"
    ],
    "wof:name":"Dalton Community Cable Assoc",
    "wof:placetype":"venue"
},
  "geometry": {"coordinates":[-73.175168,42.4766],"type":"Point"}
}