{
  "type": "Feature",
  "properties": {
    "addr:full": "151 Park Ave Dalton MA 01226",
    "addr:housenumber": "151",
    "addr:postcode": "01226",
    "addr:street": "Park Ave",
    "iso:country": "US",
    "sg:address": "151 Park Ave",
    "sg:city": "Dalton",
    "sg:classifiers": [
      {
        "category": "Arts \u0026 Performance",
        "subcategory": "Theater",
        "type": "Entertainment"
      }
    ],
    "sg:phone": "+1 413 684 4441",
    "sg:postcode": "01226",
    "sg:province": "MA",
    "sg:tags": [
      "television",
      "program",
      "producer"
    ],
    "wof:name": "Dalton Community Cable Assoc",
    "wof:placetype": "venue"
  },
  "geometry": {"coordinates":[-73.175168,42.4766],"type":"Point"}
}
