{
  "type": "Feature",
  "properties": {
    "addr:full":"312 E Main St Norton MA 02766",
    "addr:housenumber":"312",
    "addr:postcode":"02766",
    "addr:street":"E Main St",
    "iso:country":"US",
    "sg:address":"312 E Main St",
    "sg:city":"Norton",
    "sg:classifiers":[
        {
            "category":"Professional",
            "subcategory":"Advertising",
            "type":"Services"
        }
    ],
    "sg:phone":"+1 508 285 2800",
    "sg:postcode":"02766",
    "sg:province":"MA",
    "sg:tags":[
        "mailing",
        "shipping"
    ],
    "sg:website":"www.cfsmail.com",
    "wof:name":"Corporate Fulfillment Systems",
    "wof:placetype":"venue"
},
  "geometry": {"coordinates":[-71.151906,41.99593],"type":"Point"}
}