{
  "type": "Feature",
  "properties": {
    "addr:full":"2 Brattle Sq Cambridge MA 02138",
    "addr:housenumber":"2",
    "addr:postcode":"02138",
    "addr:street":"Brattle Sq",
    "iso:country":"US",
    "sg:address":"2 Brattle Sq",
    "sg:city":"Cambridge",
    "sg:classifiers":[
        {
            "category":"Organizations",
            "subcategory":"Non-profit Organization",
            "type":"Services"
        }
    ],
    "sg:phone":"+1 617 349 0040",
    "sg:postcode":"02138",
    "sg:province":"MA",
    "wof:name":"Ibis Reproductive Health",
    "wof:placetype":"venue"
},
  "geometry": {"coordinates":[-71.120779,42.373186],"type":"Point"}
}