{
  "type": "Feature",
  "properties": {
    "iso:country":"US",
    "sg:address":"30 Mohawk St",
    "sg:city":"Danvers",
    "sg:classifiers":[
        {
            "category":"Professional",
            "subcategory":"Advertising",
            "type":"Services"
        }
    ],
    "sg:phone":"+1   ",
    "sg:postcode":"01923",
    "sg:province":"MA",
    "sg:tags":[
        "agency"
    ],
    "wof:name":"Higgins Advertising",
    "wof:placetype":"venue"
},
  "geometry": {"coordinates":[-70.94580499999999,42.589969],"type":"Point"}
}