{
  "type": "Feature",
  "properties": {
    "iso:country":"US",
    "sg:address":"44 Hastings Rd",
    "sg:city":"Ashburnham",
    "sg:classifiers":[
        {
            "category":"Building & Trades",
            "subcategory":"Equipment Rental",
            "type":"Services"
        }
    ],
    "sg:phone":"+1 617 527 6213",
    "sg:postcode":"01430",
    "sg:province":"MA",
    "sg:tags":[
        "yard",
        "leasing",
        "store"
    ],
    "wof:name":"Northmeadow Leasing Corp",
    "wof:placetype":"venue"
},
  "geometry": {"coordinates":[-71.91670999999999,42.643959],"type":"Point"}
}