{
  "type": "Feature",
  "properties": {
    "addr:full": "126 Chandler St Worcester MA 01609",
    "addr:housenumber": "126",
    "addr:postcode": "01609",
    "addr:street": "Chandler St",
    "iso:country": "US",
    "sg:address": "126 Chandler St",
    "sg:city": "Worcester",
    "sg:classifiers": [
      {
        "category": "Wholesale",
        "subcategory": "Medical Equipment \u0026 Supplies",
        "type": "Manufacturing \u0026 Wholesale Goods"
      }
    ],
    "sg:phone": "+1 508 757 3853",
    "sg:postcode": "01609",
    "sg:province": "MA",
    "sg:tags": [
      "hospital"
    ],
    "wof:name": "P L Rider Co",
    "wof:placetype": "venue"
  },
  "geometry": {"coordinates":[-71.811957,42.260541],"type":"Point"}
}
