{
  "type": "Feature",
  "properties": {
    "iso:country":"US",
    "sg:address":"126 Chandler St",
    "sg:city":"Worcester",
    "sg:classifiers":[
        {
            "category":"Wholesale",
            "subcategory":"Medical Equipment & Supplies",
            "type":"Manufacturing & Wholesale Goods"
        }
    ],
    "sg:phone":"+1 508 757 3853",
    "sg:postcode":"01609",
    "sg:province":"MA",
    "sg:tags":[
        "hospital"
    ],
    "wof:name":"P L Rider Co",
    "wof:placetype":"venue"
},
  "geometry": {"coordinates":[-71.81195700000001,42.260541],"type":"Point"}
}