{
  "type": "Feature",
  "properties": {
    "iso:country":"US",
    "sg:address":"5 Babson Ct",
    "sg:city":"Gloucester",
    "sg:classifiers":[
        {
            "category":"Insurance",
            "subcategory":"Insurance Agent",
            "type":"Services"
        }
    ],
    "sg:phone":"+1 978 283 5131",
    "sg:postcode":"01930",
    "sg:province":"MA",
    "wof:name":"G Everett Mahony Insurance Inc",
    "wof:placetype":"venue"
},
  "geometry": {"coordinates":[-70.670267,42.610809],"type":"Point"}
}