{
  "type": "Feature",
  "properties": {
    "iso:country":"US",
    "sg:address":"601 Brayton Ave",
    "sg:city":"Fall River",
    "sg:classifiers":[
        {
            "category":"Bus Charters",
            "type":"Transportation"
        }
    ],
    "sg:phone":"+1 508 672 6071",
    "sg:postcode":"02721",
    "sg:province":"MA",
    "sg:tags":[
        "rental"
    ],
    "wof:name":"Southeastern Regional Transit",
    "wof:placetype":"venue"
},
  "geometry": {"coordinates":[-71.14761799999999,41.682828],"type":"Point"}
}