{
  "type": "Feature",
  "properties": {
    "iso:country":"US",
    "sg:address":"89 Canal Rd",
    "sg:city":"Sagamore Beach",
    "sg:phone":"+1 508 888 0137",
    "sg:postcode":"02562",
    "sg:province":"MA",
    "sg:tags":[
        "oil"
    ],
    "wof:name":"Sorenti Petroleum Inc",
    "wof:placetype":"venue"
},
  "geometry": {"coordinates":[-70.53386999999999,41.776968],"type":"Point"}
}