{
  "type": "Feature",
  "properties": {
    "addr:full": "663 Plain St Marshfield MA 02050",
    "addr:housenumber": "663",
    "addr:postcode": "02050",
    "addr:street": "Plain St",
    "iso:country": "US",
    "sg:address": "663 Plain St",
    "sg:city": "Marshfield",
    "sg:classifiers": [
      {
        "category": "Personal",
        "subcategory": "Beauty Salon",
        "type": "Services"
      }
    ],
    "sg:phone": "+1 781 834 8525",
    "sg:postcode": "02050",
    "sg:province": "MA",
    "wof:name": "LA Mirage",
    "wof:placetype": "venue"
  },
  "geometry": {"coordinates":[-70.735154,42.104476],"type":"Point"}
}
