{
  "type": "Feature",
  "properties": {
    "addr:full": "123 Dartmouth St New Bedford MA 02740",
    "addr:housenumber": "123",
    "addr:postcode": "02740",
    "addr:street": "Dartmouth St",
    "iso:country": "US",
    "sg:address": "123 Dartmouth St",
    "sg:city": "New Bedford",
    "sg:classifiers": [
      {
        "category": "Retail",
        "subcategory": "Repair Shop",
        "type": "Services"
      }
    ],
    "sg:phone": "+1 508 996 0300",
    "sg:postcode": "02740",
    "sg:province": "MA",
    "sg:tags": [
      "television",
      "radio"
    ],
    "wof:name": "Audio Metrics",
    "wof:placetype": "venue"
  },
  "geometry": {"coordinates":[-70.933275,41.623535],"type":"Point"}
}
