{
  "type": "Feature",
  "properties": {
    "iso:country":"US",
    "sg:address":"123 Dartmouth St",
    "sg:city":"New Bedford",
    "sg:classifiers":[
        {
            "category":"Retail",
            "subcategory":"Repair Shop",
            "type":"Services"
        }
    ],
    "sg:phone":"+1 508 996 0300",
    "sg:postcode":"02740",
    "sg:province":"MA",
    "sg:tags":[
        "television",
        "radio"
    ],
    "wof:name":"Audio Metrics",
    "wof:placetype":"venue"
},
  "geometry": {"coordinates":[-70.93327499999999,41.623535],"type":"Point"}
}