{
  "type": "Feature",
  "properties": {
    "addr:full":"29 Rattle Hill Rd Southampton MA 01073",
    "addr:housenumber":"29",
    "addr:postcode":"01073",
    "addr:street":"Rattle Hill Rd",
    "iso:country":"US",
    "sg:address":"29 Rattle Hill Rd",
    "sg:city":"Southampton",
    "sg:classifiers":[
        {
            "category":"Building & Trades",
            "subcategory":"Plumbing",
            "type":"Services"
        }
    ],
    "sg:phone":"+1 413 527 5812",
    "sg:postcode":"01073",
    "sg:province":"MA",
    "sg:tags":[
        "conditioning",
        "air",
        "system",
        "contractor"
    ],
    "wof:name":"Orchard Valley Htg & Cooling",
    "wof:placetype":"venue"
},
  "geometry": {"coordinates":[-72.73078599999999,42.24821],"type":"Point"}
}