{
  "type": "Feature",
  "properties": {
    "iso:country":"US",
    "sg:address":"9 Stockbridge St",
    "sg:city":"Springfield",
    "sg:classifiers":[
        {
            "category":"Real Estate",
            "subcategory":"Surveying",
            "type":"Services"
        }
    ],
    "sg:phone":"+1 413 787 6480",
    "sg:postcode":"01103",
    "sg:province":"MA",
    "sg:tags":[
        "surveyor"
    ],
    "wof:name":"Dispute Resolution Svc Inc",
    "wof:placetype":"venue"
},
  "geometry": {"coordinates":[-72.585793,42.101205],"type":"Point"}
}