{
  "type": "Feature",
  "properties": {
    "addr:full":"1842 Beacon Street Brookline MA 02445",
    "addr:housenumber":"1842",
    "addr:postcode":"02445",
    "addr:street":"Beacon Street",
    "iso:country":"US",
    "sg:address":"1842 Beacon Street",
    "sg:city":"Brookline",
    "sg:classifiers":[
        {
            "category":"Insurance",
            "subcategory":"Hazard Insurance",
            "type":"Services"
        },
        {
            "category":"Travel",
            "subcategory":"Travel Agent",
            "type":"Entertainment"
        }
    ],
    "sg:phone":"+1 617 232 9290",
    "sg:postcode":"02445",
    "sg:province":"MA",
    "sg:tags":[
        "commercial",
        "agency",
        "services-commercial",
        "business"
    ],
    "wof:name":"Citywide Insurance Agency",
    "wof:placetype":"venue"
},
  "geometry": {"coordinates":[-71.145315,42.337225],"type":"Point"}
}