{
  "type": "Feature",
  "properties": {
    "addr:full":"67 State Rd Great Barrington MA 01230",
    "addr:housenumber":"67",
    "addr:postcode":"01230",
    "addr:street":"State Rd",
    "iso:country":"US",
    "sg:address":"67 State Rd",
    "sg:city":"Great Barrington",
    "sg:classifiers":[
        {
            "category":"Wholesale",
            "subcategory":"Machinery & Supplies",
            "type":"Manufacturing & Wholesale Goods"
        }
    ],
    "sg:phone":"+1 413 528 4009",
    "sg:postcode":"01230",
    "sg:province":"MA",
    "sg:tags":[
        "salon",
        "beauty"
    ],
    "wof:name":"Instyle Hair Design",
    "wof:placetype":"venue"
},
  "geometry": {"coordinates":[-73.357519,42.201487],"type":"Point"}
}