{
  "type": "Feature",
  "properties": {
    "addr:full": "170 Centre St Milton MA 02186",
    "addr:housenumber": "170",
    "addr:postcode": "02186",
    "addr:street": "Centre St",
    "iso:country": "US",
    "sg:address": "170 Centre St",
    "sg:city": "Milton",
    "sg:classifiers": [
      {
        "category": "Professional",
        "type": "Services"
      }
    ],
    "sg:phone": "+1 617 898 1758",
    "sg:postcode": "02186",
    "sg:province": "MA",
    "sg:tags": [
      "establishment"
    ],
    "wof:name": "Tom \u0026 Liz Gagnon",
    "wof:placetype": "venue"
  },
  "geometry": {"coordinates":[-71.069427,42.256494],"type":"Point"}
}
