{
  "type": "Feature",
  "properties": {
    "iso:country":"US",
    "sg:address":"170 Centre St",
    "sg:city":"Milton",
    "sg:classifiers":[
        {
            "category":"Professional",
            "type":"Services"
        }
    ],
    "sg:phone":"+1 617 898 1758",
    "sg:postcode":"02186",
    "sg:province":"MA",
    "sg:tags":[
        "establishment"
    ],
    "wof:name":"Tom & Liz Gagnon",
    "wof:placetype":"venue"
},
  "geometry": {"coordinates":[-71.069427,42.256494],"type":"Point"}
}