{
  "type": "Feature",
  "properties": {
    "addr:full":"682 Bedford St Whitman MA 02382",
    "addr:housenumber":"682",
    "addr:postcode":"02382",
    "addr:street":"Bedford St",
    "iso:country":"US",
    "sg:address":"682 Bedford St",
    "sg:city":"Whitman",
    "sg:classifiers":[
        {
            "category":"Bars & Pubs",
            "type":"Food & Drink"
        },
        {
            "category":"Restaurant",
            "type":"Food & Drink"
        }
    ],
    "sg:phone":"+1 781 447 3680",
    "sg:postcode":"02382",
    "sg:province":"MA",
    "sg:tags":[
        "brew",
        "asian",
        "chinese",
        "pan"
    ],
    "wof:name":"Waikiki House",
    "wof:placetype":"venue"
},
  "geometry": {"coordinates":[-70.94694800000001,42.079614],"type":"Point"}
}