{
  "type": "Feature",
  "properties": {
    "iso:country":"US",
    "sg:address":"1 Faneuil Hall Mrkt Pl",
    "sg:city":"Boston",
    "sg:classifiers":[
        {
            "category":"Shopping",
            "subcategory":"Hobbies, Toys, & Games",
            "type":"Retail Goods"
        }
    ],
    "sg:phone":"+1 617 227 6266",
    "sg:postcode":"02109",
    "sg:province":"MA",
    "sg:tags":[
        "shop",
        "hobby",
        "toy",
        "store"
    ],
    "sg:website":"www.zoinkstoys.com/",
    "wof:name":"Zoinks! Toys",
    "wof:placetype":"venue"
},
  "geometry": {"coordinates":[-71.053596,42.359798],"type":"Point"}
}