{
  "type": "Feature",
  "properties": {
    "iso:country":"US",
    "sg:address":"275 Tremont St",
    "sg:city":"Boston",
    "sg:classifiers":[
        {
            "category":"Bars & Pubs",
            "type":"Food & Drink"
        }
    ],
    "sg:phone":"+1 617 542 4077",
    "sg:postcode":"02116",
    "sg:province":"MA",
    "sg:tags":[
        "dance",
        "club",
        "night"
    ],
    "wof:name":"Matrix",
    "wof:placetype":"venue"
},
  "geometry": {"coordinates":[-71.065201,42.349899],"type":"Point"}
}