{
  "type": "Feature",
  "properties": {
    "addr:full": "275 Tremont St Boston MA 02116",
    "addr:housenumber": "275",
    "addr:postcode": "02116",
    "addr:street": "Tremont St",
    "iso:country": "US",
    "sg:address": "275 Tremont St",
    "sg:city": "Boston",
    "sg:classifiers": [
      {
        "category": "Bars \u0026 Pubs",
        "type": "Food \u0026 Drink"
      }
    ],
    "sg:phone": "+1 617 542 4077",
    "sg:postcode": "02116",
    "sg:province": "MA",
    "sg:tags": [
      "dance",
      "club",
      "night"
    ],
    "wof:name": "Matrix",
    "wof:placetype": "venue"
  },
  "geometry": {"coordinates":[-71.065201,42.349899],"type":"Point"}
}
