{
  "type": "Feature",
  "properties": {
    "addr:full": "153 Ruthven Street Dorchester MA 02121",
    "addr:housenumber": "153",
    "addr:postcode": "02121",
    "addr:street": "Ruthven Street",
    "iso:country": "US",
    "sg:address": "153 Ruthven Street",
    "sg:city": "Dorchester",
    "sg:classifiers": [
      {
        "category": "Autos \u0026 Motor Vehicles",
        "subcategory": "Automobile Sales",
        "type": "Retail Goods"
      }
    ],
    "sg:phone": "+1 617 427 0913",
    "sg:postcode": "02121",
    "sg:province": "MA",
    "sg:tags": [
      "limo"
    ],
    "sg:website": "www.dalyarrival.com",
    "wof:name": "Daly Arrival",
    "wof:placetype": "venue"
  },
  "geometry": {"coordinates":[-71.088352,42.31209],"type":"Point"}
}
