{
  "type": "Feature",
  "properties": {
    "addr:full": "35 Davis St Tyngsboro MA 01879",
    "addr:housenumber": "35",
    "addr:postcode": "01879",
    "addr:street": "Davis St",
    "iso:country": "US",
    "sg:address": "35 Davis St",
    "sg:city": "Tyngsboro",
    "sg:classifiers": [
      {
        "category": "Travel",
        "subcategory": "Campground",
        "type": "Entertainment"
      }
    ],
    "sg:phone": "+1 978 649 3141",
    "sg:postcode": "01879",
    "sg:province": "MA",
    "wof:name": "Barry's Grove Campground Inc",
    "wof:placetype": "venue"
  },
  "geometry": {"coordinates":[-71.39669,42.680622],"type":"Point"}
}
