{
  "type": "Feature",
  "properties": {
    "addr:full": "1387 Fall River Ave Seekonk MA 02771",
    "addr:housenumber": "1387",
    "addr:postcode": "02771",
    "addr:street": "Fall River Ave",
    "iso:country": "US",
    "sg:address": "1387 Fall River Ave",
    "sg:city": "Seekonk",
    "sg:classifiers": [
      {
        "category": "Shopping",
        "subcategory": "Gifts \u0026 Souvenirs",
        "type": "Retail Goods"
      }
    ],
    "sg:phone": "+1 508 336 6012",
    "sg:postcode": "02771",
    "sg:province": "MA",
    "sg:tags": [
      "collectible"
    ],
    "wof:name": "Wee Luv Collectibles",
    "wof:placetype": "venue"
  },
  "geometry": {"coordinates":[-71.319969,41.788493],"type":"Point"}
}
