{
  "type": "Feature",
  "properties": {
    "addr:full": "175 Haven St Reading MA 01867",
    "addr:housenumber": "175",
    "addr:postcode": "01867",
    "addr:street": "Haven St",
    "iso:country": "US",
    "sg:address": "175 Haven St",
    "sg:city": "Reading",
    "sg:classifiers": [
      {
        "category": "Professional",
        "subcategory": "Accounting \u0026 Tax Preparation",
        "type": "Services"
      }
    ],
    "sg:phone": "+1 781 944 2321",
    "sg:postcode": "01867",
    "sg:province": "MA",
    "sg:tags": [
      "accountant"
    ],
    "sg:website": "www.jbcrosby.com",
    "wof:name": "J \u0026 B Crosby \u0026 Co",
    "wof:placetype": "venue"
  },
  "geometry": {"coordinates":[-71.103817,42.523514],"type":"Point"}
}
