{
  "type": "Feature",
  "properties": {
    "iso:country":"US",
    "sg:address":"175 Haven St",
    "sg:city":"Reading",
    "sg:classifiers":[
        {
            "category":"Professional",
            "subcategory":"Accounting & Tax Preparation",
            "type":"Services"
        }
    ],
    "sg:phone":"+1 781 944 2321",
    "sg:postcode":"01867",
    "sg:province":"MA",
    "sg:tags":[
        "accountant"
    ],
    "sg:website":"www.jbcrosby.com",
    "wof:name":"J & B Crosby & Co",
    "wof:placetype":"venue"
},
  "geometry": {"coordinates":[-71.10381700000001,42.523514],"type":"Point"}
}