{
  "type": "Feature",
  "properties": {
    "iso:country":"US",
    "sg:address":"282 Beacon St",
    "sg:city":"Boston",
    "sg:classifiers":[
        {
            "category":"Professional",
            "subcategory":"Management & Consulting",
            "type":"Services"
        }
    ],
    "sg:phone":"+1 617 859 3065",
    "sg:postcode":"02116",
    "sg:province":"MA",
    "sg:tags":[
        "consultant"
    ],
    "wof:name":"Oyster International",
    "wof:placetype":"venue"
},
  "geometry": {"coordinates":[-71.081284,42.353062],"type":"Point"}
}