{
  "type": "Feature",
  "properties": {
    "addr:full": "709 W Roxbury Pkwy West Roxbury MA 02132",
    "addr:housenumber": "709",
    "addr:postcode": "02132",
    "addr:street": "W Roxbury Pkwy",
    "iso:country": "US",
    "sg:address": "709 W Roxbury Pkwy",
    "sg:city": "West Roxbury",
    "sg:classifiers": [
      {
        "category": "Retail",
        "subcategory": "Laundry \u0026 Dry Cleaning",
        "type": "Services"
      }
    ],
    "sg:phone": "+1 617 325 1990",
    "sg:postcode": "02132",
    "sg:province": "MA",
    "sg:tags": [
      "cleaners"
    ],
    "wof:name": "KCP Realty",
    "wof:placetype": "venue"
  },
  "geometry": {"coordinates":[-71.143788,42.280254],"type":"Point"}
}
