{
  "type": "Feature",
  "properties": {
    "addr:full": "30 River St Winchester MA 01890",
    "addr:housenumber": "30",
    "addr:postcode": "01890",
    "addr:street": "River St",
    "iso:country": "US",
    "sg:address": "30 River St",
    "sg:city": "Winchester",
    "sg:classifiers": [
      {
        "category": "Organizations",
        "subcategory": "Community Association",
        "type": "Services"
      }
    ],
    "sg:phone": "+1 781 729 9888",
    "sg:postcode": "01890",
    "sg:province": "MA",
    "sg:tags": [
      "club"
    ],
    "wof:name": "Veterans Of Foreign Wars",
    "wof:placetype": "venue"
  },
  "geometry": {"coordinates":[-71.136343,42.464678],"type":"Point"}
}
