{
  "type": "Feature",
  "properties": {
    "addr:full":"184 Main St Wareham MA 02571",
    "addr:housenumber":"184",
    "addr:postcode":"02571",
    "addr:street":"Main St",
    "iso:country":"US",
    "sg:address":"184 Main St",
    "sg:city":"Wareham",
    "sg:classifiers":[
        {
            "category":"Professional",
            "subcategory":"Lawyer & Legal Services",
            "type":"Services"
        }
    ],
    "sg:phone":"+1 508 295 2522",
    "sg:postcode":"02571",
    "sg:province":"MA",
    "wof:name":"Bello Leonard A Atty",
    "wof:placetype":"venue"
},
  "geometry": {"coordinates":[-70.716599,41.7593],"type":"Point"}
}