{
  "type": "Feature",
  "properties": {
    "iso:country":"US",
    "sg:address":"366 Washington St",
    "sg:city":"Brookline",
    "sg:classifiers":[
        {
            "category":"Organizations",
            "subcategory":"Religious Organization",
            "type":"Services"
        }
    ],
    "sg:phone":"+1 617 277 6266",
    "sg:postcode":"02445",
    "sg:province":"MA",
    "sg:tags":[
        "church"
    ],
    "wof:name":"Christian Community Church",
    "wof:placetype":"venue"
},
  "geometry": {"coordinates":[-71.12132099999999,42.333838],"type":"Point"}
}