{
  "type": "Feature",
  "properties": {
    "addr:full": "366 Washington St Brookline MA 02445",
    "addr:housenumber": "366",
    "addr:postcode": "02445",
    "addr:street": "Washington St",
    "iso:country": "US",
    "sg:address": "366 Washington St",
    "sg:city": "Brookline",
    "sg:classifiers": [
      {
        "category": "Organizations",
        "subcategory": "Religious Organization",
        "type": "Services"
      }
    ],
    "sg:phone": "+1 617 277 6266",
    "sg:postcode": "02445",
    "sg:province": "MA",
    "sg:tags": [
      "church"
    ],
    "wof:name": "Christian Community Church",
    "wof:placetype": "venue"
  },
  "geometry": {"coordinates":[-71.121321,42.333838],"type":"Point"}
}
