{
  "type": "Feature",
  "properties": {
    "iso:country":"US",
    "sg:address":"25 Clinton St",
    "sg:city":"Framingham",
    "sg:classifiers":[
        {
            "category":"Education",
            "subcategory":"School",
            "type":"Public Place"
        }
    ],
    "sg:phone":"+1 508 879 9000",
    "sg:postcode":"01702",
    "sg:province":"MA",
    "wof:name":"Framingham Community Charter",
    "wof:placetype":"venue"
},
  "geometry": {"coordinates":[-71.41431300000001,42.280898],"type":"Point"}
}