{
  "type": "Feature",
  "properties": {
    "addr:full":"16 Colt Rd Pittsfield MA 01201",
    "addr:housenumber":"16",
    "addr:postcode":"01201",
    "addr:street":"Colt Rd",
    "iso:country":"US",
    "sg:address":"16 Colt Rd",
    "sg:city":"Pittsfield",
    "sg:classifiers":[
        {
            "category":"Restaurant",
            "type":"Food & Drink"
        }
    ],
    "sg:phone":"+1 413 442 2200",
    "sg:postcode":"01201",
    "sg:province":"MA",
    "sg:tags":[
        "lunch",
        "brunch",
        "breakfast"
    ],
    "wof:name":"Jewish Federation Lunch Program",
    "wof:placetype":"venue"
},
  "geometry": {"coordinates":[-73.255286,42.440448],"type":"Point"}
}