{
  "type": "Feature",
  "properties": {
    "addr:full": "311 Main St Worcester MA 01608",
    "addr:housenumber": "311",
    "addr:postcode": "01608",
    "addr:street": "Main St",
    "iso:country": "US",
    "sg:address": "311 Main St",
    "sg:city": "Worcester",
    "sg:classifiers": [
      {
        "category": "Manufacturing",
        "subcategory": "Food",
        "type": "Manufacturing \u0026 Wholesale Goods"
      },
      {
        "category": "Wholesale",
        "subcategory": "Groceries",
        "type": "Manufacturing \u0026 Wholesale Goods"
      },
      {
        "category": "Food \u0026 Beverages",
        "subcategory": "Groceries \u0026 Convenience Stores",
        "type": "Retail Goods"
      }
    ],
    "sg:phone": "+1 508 869 1000",
    "sg:postcode": "01608",
    "sg:province": "MA",
    "sg:tags": [
      "product",
      "processing",
      "products-wholesale",
      "chip",
      "potato"
    ],
    "sg:website": "http://www.fritolay.com",
    "wof:name": "Frito Lay Incorporated",
    "wof:placetype": "venue"
  },
  "geometry": {"coordinates":[-71.801186,42.265819],"type":"Point"}
}
