{
  "type": "Feature",
  "properties": {
    "iso:country":"US",
    "sg:address":"171 Chester St",
    "sg:city":"North Falmouth",
    "sg:classifiers":[
        {
            "category":"Building & Trades",
            "subcategory":"Construction",
            "type":"Services"
        }
    ],
    "sg:phone":"+1 508 563 1858",
    "sg:postcode":"02556",
    "sg:province":"MA",
    "sg:tags":[
        "contractor"
    ],
    "sg:website":"www.goodbuildersinc.com",
    "wof:name":"Good Builders Inc",
    "wof:placetype":"venue"
},
  "geometry": {"coordinates":[-70.627019,41.646921],"type":"Point"}
}