{
  "type": "Feature",
  "properties": {
    "addr:full":"310 Trapelo Rd Belmont MA 02478",
    "addr:housenumber":"310",
    "addr:postcode":"02478",
    "addr:street":"Trapelo Rd",
    "iso:country":"US",
    "sg:address":"310 Trapelo Rd",
    "sg:city":"Belmont",
    "sg:classifiers":[
        {
            "category":"Organizations",
            "subcategory":"Community Association",
            "type":"Services"
        }
    ],
    "sg:phone":"+1   ",
    "sg:postcode":"02478",
    "sg:province":"MA",
    "wof:name":"Veterans Foreign Wars 1272",
    "wof:placetype":"venue"
},
  "geometry": {"coordinates":[-71.181557,42.383705],"type":"Point"}
}