{
  "type": "Feature",
  "properties": {
    "addr:full": "32 S Main St Attleboro MA 02703",
    "addr:housenumber": "32",
    "addr:postcode": "02703",
    "addr:street": "S Main St",
    "iso:country": "US",
    "sg:address": "32 S Main St",
    "sg:city": "Attleboro",
    "sg:classifiers": [
      {
        "category": "Home \u0026 Garden",
        "subcategory": "Furniture",
        "type": "Retail Goods"
      }
    ],
    "sg:phone": "+1 508 222 0520",
    "sg:postcode": "02703",
    "sg:province": "MA",
    "sg:tags": [
      "store"
    ],
    "wof:name": "Berard's Home Furnishings - CLOSED",
    "wof:placetype": "venue"
  },
  "geometry": {"coordinates":[-71.2845,41.943001],"type":"Point"}
}
