{
  "type": "Feature",
  "properties": {
    "iso:country":"US",
    "sg:address":"32 S Main St",
    "sg:city":"Attleboro",
    "sg:classifiers":[
        {
            "category":"Home & Garden",
            "subcategory":"Furniture",
            "type":"Retail Goods"
        }
    ],
    "sg:phone":"+1 508 222 0520",
    "sg:postcode":"02703",
    "sg:province":"MA",
    "sg:tags":[
        "store"
    ],
    "wof:name":"Berard's Home Furnishings - CLOSED",
    "wof:placetype":"venue"
},
  "geometry": {"coordinates":[-71.28449999999999,41.943001],"type":"Point"}
}