{
  "type": "Feature",
  "properties": {
    "addr:full": "3 River Rd South Deerfield MA 01373",
    "addr:housenumber": "3",
    "addr:postcode": "01373",
    "addr:street": "River Rd",
    "iso:country": "US",
    "sg:address": "3 River Rd",
    "sg:city": "South Deerfield",
    "sg:classifiers": [
      {
        "category": "Home \u0026 Garden",
        "subcategory": "Garden Supply",
        "type": "Retail Goods"
      }
    ],
    "sg:phone": "+1 413 665 4318",
    "sg:postcode": "01373",
    "sg:province": "MA",
    "sg:tags": [
      "lawn",
      "mower"
    ],
    "wof:name": "C \u0026 A Repair \u0026 Equipment",
    "wof:placetype": "venue"
  },
  "geometry": {"coordinates":[-72.589547,42.423287],"type":"Point"}
}
