{
  "type": "Feature",
  "properties": {
    "addr:full":"179 Sidney St Cambridge MA 02139",
    "addr:housenumber":"179",
    "addr:postcode":"02139",
    "addr:street":"Sidney St",
    "iso:country":"US",
    "sg:address":"179 Sidney St",
    "sg:city":"Cambridge",
    "sg:classifiers":[
        {
            "category":"Shopping",
            "subcategory":"Computers & Home Electronics",
            "type":"Retail Goods"
        }
    ],
    "sg:phone":"+1 617 218 0100",
    "sg:postcode":"02139",
    "sg:province":"MA",
    "sg:tags":[
        "software"
    ],
    "wof:name":"Component Software Inc",
    "wof:placetype":"venue"
},
  "geometry": {"coordinates":[-71.10542,42.357957],"type":"Point"}
}