{
  "type": "Feature",
  "properties": {
    "addr:full":"27 Tesla St Mattapan MA 02126",
    "addr:housenumber":"27",
    "addr:postcode":"02126",
    "addr:street":"Tesla St",
    "iso:country":"US",
    "sg:address":"27 Tesla St",
    "sg:city":"Mattapan",
    "sg:classifiers":[
        {
            "category":"Retail",
            "subcategory":"Repair Shop",
            "type":"Services"
        }
    ],
    "sg:phone":"+1 617 296 2346",
    "sg:postcode":"02126",
    "sg:province":"MA",
    "sg:tags":[
        "ironwork"
    ],
    "wof:name":"Top Mechanical",
    "wof:placetype":"venue"
},
  "geometry": {"coordinates":[-71.09630900000001,42.265843],"type":"Point"}
}