{
  "type": "Feature",
  "properties": {
    "addr:full":"38 Sandy Ridge Rd Stoughton MA 02072",
    "addr:housenumber":"38",
    "addr:postcode":"02072",
    "addr:street":"Sandy Ridge Rd",
    "iso:country":"US",
    "sg:address":"38 Sandy Ridge Rd",
    "sg:city":"Stoughton",
    "sg:classifiers":[
        {
            "category":"Professional",
            "subcategory":"Research",
            "type":"Services"
        }
    ],
    "sg:phone":"+1 781 762 2447",
    "sg:postcode":"02072",
    "sg:province":"MA",
    "wof:name":"Computational Physics",
    "wof:placetype":"venue"
},
  "geometry": {"coordinates":[-71.115253,42.12355],"type":"Point"}
}