{
  "type": "Feature",
  "properties": {
    "addr:full": "123 Boston Street Dorchester MA 02125",
    "addr:housenumber": "123",
    "addr:postcode": "02125",
    "addr:street": "Boston Street",
    "iso:country": "US",
    "sg:address": "123 Boston Street",
    "sg:city": "Dorchester",
    "sg:classifiers": [
      {
        "category": "Professional",
        "subcategory": "Lawyer \u0026 Legal Services",
        "type": "Services"
      }
    ],
    "sg:phone": "+1 617 740 7340",
    "sg:postcode": "02125",
    "sg:province": "MA",
    "wof:name": "Russo \u0026 Minchoff Attorney At Law",
    "wof:placetype": "venue"
  },
  "geometry": {"coordinates":[-71.05894,42.325352],"type":"Point"}
}
