{
  "type": "Feature",
  "properties": {
    "addr:full": "290 Main St North Reading MA 01864",
    "addr:housenumber": "290",
    "addr:postcode": "01864",
    "addr:street": "Main St",
    "iso:country": "US",
    "sg:address": "290 Main St",
    "sg:city": "North Reading",
    "sg:phone": "+1 978 664 2446",
    "sg:postcode": "01864",
    "sg:province": "MA",
    "sg:tags": [
      "oil"
    ],
    "wof:name": "Commonwealth Oil Inc",
    "wof:placetype": "venue"
  },
  "geometry": {"coordinates":[-71.119102,42.59418],"type":"Point"}
}
