{
  "type": "Feature",
  "properties": {
    "iso:country":"US",
    "sg:address":"174 Main St",
    "sg:city":"Wareham",
    "sg:classifiers":[
        {
            "category":"Manufacturing",
            "subcategory":"Printing",
            "type":"Manufacturing & Wholesale Goods"
        }
    ],
    "sg:phone":"+1 508 295 0505",
    "sg:postcode":"02571",
    "sg:province":"MA",
    "sg:tags":[
        "printer"
    ],
    "wof:name":"Gateway Printing",
    "wof:placetype":"venue"
},
  "geometry": {"coordinates":[-70.714456,41.757498],"type":"Point"}
}