{
  "type": "Feature",
  "properties": {
    "addr:full": "174 Main St Wareham MA 02571",
    "addr:housenumber": "174",
    "addr:postcode": "02571",
    "addr:street": "Main St",
    "iso:country": "US",
    "ovtr:label": "Gateway Printing, 174 Main St Wareham MA US",
    "ovtr:similarity": 1.6851589679718018,
    "sg:address": "174 Main St",
    "sg:city": "Wareham",
    "sg:classifiers": [
      {
        "category": "Manufacturing",
        "subcategory": "Printing",
        "type": "Manufacturing \u0026 Wholesale Goods"
      }
    ],
    "sg:phone": "+1 508 295 0505",
    "sg:postcode": "02571",
    "sg:province": "MA",
    "sg:tags": [
      "printer"
    ],
    "wof:name": "Gateway Printing",
    "wof:placetype": "venue"
  },
  "geometry": {"coordinates":[-70.714456,41.757498],"type":"Point"}
}
