{
  "type": "Feature",
  "properties": {
    "addr:full":"46 Walnut Ave Andover MA 01810",
    "addr:housenumber":"46",
    "addr:postcode":"01810",
    "addr:street":"Walnut Ave",
    "iso:country":"US",
    "sg:address":"46 Walnut Ave",
    "sg:city":"Andover",
    "sg:classifiers":[
        {
            "category":"Professional",
            "subcategory":"Business Services",
            "type":"Services"
        }
    ],
    "sg:phone":"+1   ",
    "sg:postcode":"01810",
    "sg:province":"MA",
    "wof:name":"Wheelkick Inc",
    "wof:placetype":"venue"
},
  "geometry": {"coordinates":[-71.139076,42.663036],"type":"Point"}
}