{
  "type": "Feature",
  "properties": {
    "addr:full": "85 Columbian St Weymouth MA 02190",
    "addr:housenumber": "85",
    "addr:postcode": "02190",
    "addr:street": "Columbian St",
    "iso:country": "US",
    "sg:address": "85 Columbian St",
    "sg:city": "Weymouth",
    "sg:classifiers": [
      {
        "category": "Health Services",
        "subcategory": "Hospital",
        "type": "Services"
      }
    ],
    "sg:phone": "+1 781 340 1653",
    "sg:postcode": "02190",
    "sg:province": "MA",
    "wof:name": "South Shore Hospital",
    "wof:placetype": "venue"
  },
  "geometry": {"coordinates":[-70.951628,42.174887],"type":"Point"}
}
