{
  "type": "Feature",
  "properties": {
    "addr:full":"2 Westside Dr Acton MA 01720",
    "addr:housenumber":"2",
    "addr:postcode":"01720",
    "addr:street":"Westside Dr",
    "iso:country":"US",
    "sg:address":"2 Westside Dr",
    "sg:city":"Acton",
    "sg:classifiers":[
        {
            "category":"Building & Trades",
            "subcategory":"Construction",
            "type":"Services"
        }
    ],
    "sg:phone":"+1 978 461 0220",
    "sg:postcode":"01720",
    "sg:province":"MA",
    "sg:tags":[
        "plastering",
        "contractor"
    ],
    "wof:name":"David Zawodny Plastering",
    "wof:placetype":"venue"
},
  "geometry": {"coordinates":[-71.431776,42.438137],"type":"Point"}
}