{
  "type": "Feature",
  "properties": {
    "iso:country":"US",
    "sg:address":"925 Main St",
    "sg:city":"Athol",
    "sg:classifiers":[
        {
            "category":"Recreation",
            "type":"Entertainment"
        }
    ],
    "sg:phone":"+1 978 249 7690",
    "sg:postcode":"01331",
    "sg:province":"MA",
    "sg:tags":[
        "hall",
        "auditorium"
    ],
    "wof:name":"Our Lady Immaculate Church",
    "wof:placetype":"venue"
},
  "geometry": {"coordinates":[-72.22218700000001,42.59486],"type":"Point"}
}