{
  "type": "Feature",
  "properties": {
    "addr:full":"240 Concord Ave Cambridge MA 02138",
    "addr:housenumber":"240",
    "addr:postcode":"02138",
    "addr:street":"Concord Ave",
    "iso:country":"US",
    "sg:address":"240 Concord Ave",
    "sg:city":"Cambridge",
    "sg:classifiers":[
        {
            "category":"Health Services",
            "subcategory":"Doctor",
            "type":"Services"
        }
    ],
    "sg:phone":"+1 617 864 0868",
    "sg:postcode":"02138",
    "sg:province":"MA",
    "sg:tags":[
        "physician",
        "surgeon"
    ],
    "wof:name":"Patti Levin MD",
    "wof:placetype":"venue"
},
  "geometry": {"coordinates":[-71.13285399999999,42.383275],"type":"Point"}
}