{
  "type": "Feature",
  "properties": {
    "addr:full":"191 Thomas E Burgin Pkwy Quincy MA 02169",
    "addr:housenumber":"191",
    "addr:postcode":"02169",
    "addr:street":"Thomas E Burgin Pkwy",
    "iso:country":"US",
    "sg:address":"191 Thomas E Burgin Pkwy",
    "sg:city":"Quincy",
    "sg:classifiers":[
        {
            "category":"Organizations",
            "subcategory":"Non-profit Organization",
            "type":"Services"
        }
    ],
    "sg:phone":"+1 617 786 9687",
    "sg:postcode":"02169",
    "sg:province":"MA",
    "wof:name":"Quincy Veteran's House",
    "wof:placetype":"venue"
},
  "geometry": {"coordinates":[-71.00608099999999,42.237086],"type":"Point"}
}