{
  "type": "Feature",
  "properties": {
    "addr:full":"139 Billerica Rd Chelmsford MA 01824",
    "addr:housenumber":"139",
    "addr:postcode":"01824",
    "addr:street":"Billerica Rd",
    "iso:country":"US",
    "sg:address":"139 Billerica Rd",
    "sg:city":"Chelmsford",
    "sg:classifiers":[
        {
            "category":"Professional",
            "subcategory":"Lawyer & Legal Services",
            "type":"Services"
        }
    ],
    "sg:phone":"+1 978 256 2660",
    "sg:postcode":"01824",
    "sg:province":"MA",
    "sg:tags":[
        "divorce",
        "law",
        "family"
    ],
    "wof:name":"Kurland & Grossman PC",
    "wof:placetype":"venue"
},
  "geometry": {"coordinates":[-71.34050000000001,42.5994],"type":"Point"}
}