{
  "type": "Feature",
  "properties": {
    "addr:full":"97 Main St Blackstone MA 01504",
    "addr:housenumber":"97",
    "addr:postcode":"01504",
    "addr:street":"Main St",
    "iso:country":"US",
    "sg:address":"97 Main St",
    "sg:city":"Blackstone",
    "sg:classifiers":[
        {
            "category":"Restaurant",
            "type":"Food & Drink"
        }
    ],
    "sg:phone":"+1 508 984 1214",
    "sg:postcode":"01504",
    "sg:province":"MA",
    "sg:tags":[
        "pizza"
    ],
    "wof:name":"Athens Pizzeria",
    "wof:placetype":"venue"
},
  "geometry": {"coordinates":[-71.536413,42.018881],"type":"Point"}
}