{
  "type": "Feature",
  "properties": {
    "addr:full": "30 Glennie St Worcester MA 01605",
    "addr:housenumber": "30",
    "addr:postcode": "01605",
    "addr:street": "Glennie St",
    "iso:country": "US",
    "sg:address": "30 Glennie St",
    "sg:city": "Worcester",
    "sg:classifiers": [
      {
        "category": "Wholesale",
        "subcategory": "Electrical",
        "type": "Manufacturing \u0026 Wholesale Goods"
      }
    ],
    "sg:phone": "+1 508 757 3807",
    "sg:postcode": "01605",
    "sg:province": "MA",
    "sg:tags": [
      "equipment",
      "electric",
      "supply"
    ],
    "wof:name": "Nesco/Benjamin Electric Supply",
    "wof:placetype": "venue"
  },
  "geometry": {"coordinates":[-71.805036,42.286476],"type":"Point"}
}
