{
  "type": "Feature",
  "properties": {
    "iso:country":"US",
    "sg:address":"2500 Main St",
    "sg:city":"Tewksbury",
    "sg:classifiers":[
        {
            "category":"Professional",
            "subcategory":"Lawyer & Legal Services",
            "type":"Services"
        }
    ],
    "sg:phone":"+1 978 658 0733",
    "sg:postcode":"01876",
    "sg:province":"MA",
    "sg:tags":[
        "attorney"
    ],
    "wof:name":"Michae J Larkin Jr Law Offices",
    "wof:placetype":"venue"
},
  "geometry": {"coordinates":[-71.193691,42.579601],"type":"Point"}
}