{
  "type": "Feature",
  "properties": {
    "addr:full":"22 Gilbert Rd Southampton MA 01073",
    "addr:housenumber":"22",
    "addr:postcode":"01073",
    "addr:street":"Gilbert Rd",
    "iso:country":"US",
    "sg:address":"22 Gilbert Rd",
    "sg:city":"Southampton",
    "sg:classifiers":[
        {
            "category":"Building & Trades",
            "subcategory":"Construction",
            "type":"Services"
        }
    ],
    "sg:phone":"+1   ",
    "sg:postcode":"01073",
    "sg:province":"MA",
    "sg:tags":[
        "contractor"
    ],
    "wof:name":"Denis J Duga Construction",
    "wof:placetype":"venue"
},
  "geometry": {"coordinates":[-72.74618599999999,42.218969],"type":"Point"}
}