{
  "type": "Feature",
  "properties": {
    "iso:country":"US",
    "sg:address":"204 Village St",
    "sg:city":"Medway",
    "sg:classifiers":[
        {
            "category":"Food & Beverages",
            "subcategory":"Bakery",
            "type":"Retail Goods"
        }
    ],
    "sg:phone":"+1 508 533 5643",
    "sg:postcode":"02053",
    "sg:province":"MA",
    "sg:tags":[
        "cookie",
        "cracker"
    ],
    "wof:name":"Cookies To Go",
    "wof:placetype":"venue"
},
  "geometry": {"coordinates":[-71.39905899999999,42.14051],"type":"Point"}
}