{
  "type": "Feature",
  "properties": {
    "addr:full": "204 Village St Medway MA 02053",
    "addr:housenumber": "204",
    "addr:postcode": "02053",
    "addr:street": "Village St",
    "iso:country": "US",
    "sg:address": "204 Village St",
    "sg:city": "Medway",
    "sg:classifiers": [
      {
        "category": "Food \u0026 Beverages",
        "subcategory": "Bakery",
        "type": "Retail Goods"
      }
    ],
    "sg:phone": "+1 508 533 5643",
    "sg:postcode": "02053",
    "sg:province": "MA",
    "sg:tags": [
      "cookie",
      "cracker"
    ],
    "wof:name": "Cookies To Go",
    "wof:placetype": "venue"
  },
  "geometry": {"coordinates":[-71.399059,42.14051],"type":"Point"}
}
