{
  "type": "Feature",
  "properties": {
    "iso:country":"US",
    "sg:address":"13 Buckboard Pass",
    "sg:city":"Brookfield",
    "sg:classifiers":[
        {
            "category":"Real Estate",
            "subcategory":"Real Estate Operator",
            "type":"Services"
        }
    ],
    "sg:phone":"+1 508 867 7111",
    "sg:postcode":"01506",
    "sg:province":"MA",
    "sg:tags":[
        "mobile",
        "home",
        "community"
    ],
    "wof:name":"Wagon Wheel Mobile Home Park",
    "wof:placetype":"venue"
},
  "geometry": {"coordinates":[-72.09270600000001,42.189279],"type":"Point"}
}