{
  "type": "Feature",
  "properties": {
    "iso:country":"US",
    "sg:address":"1 Saint Clare Rd",
    "sg:city":"Medford",
    "sg:classifiers":[
        {
            "category":"Building & Trades",
            "subcategory":"Locksmith",
            "type":"Services"
        }
    ],
    "sg:phone":"+1 781 658 3103",
    "sg:postcode":"02155",
    "sg:province":"MA",
    "sg:tags":[
        "key"
    ],
    "wof:name":"Real Time Locksmith",
    "wof:placetype":"venue"
},
  "geometry": {"coordinates":[-71.100854,42.426337],"type":"Point"}
}