{
  "type": "Feature",
  "properties": {
    "addr:full": "254 Bodwell St Avon MA 02322",
    "addr:housenumber": "254",
    "addr:postcode": "02322",
    "addr:street": "Bodwell St",
    "iso:country": "US",
    "sg:address": "254 Bodwell St",
    "sg:city": "Avon",
    "sg:classifiers": [
      {
        "category": "Professional",
        "subcategory": "Computer Services",
        "type": "Services"
      }
    ],
    "sg:phone": "+1 508 427 6181",
    "sg:postcode": "02322",
    "sg:province": "MA",
    "sg:tags": [
      "repair"
    ],
    "wof:name": "First Resource Computer Svc - CLOSED",
    "wof:placetype": "venue"
  },
  "geometry": {"coordinates":[-71.059998,42.135799],"type":"Point"}
}
