{
  "type": "Feature",
  "properties": {
    "addr:full":"4 Alpine Ln Chelmsford MA 01824",
    "addr:housenumber":"4",
    "addr:postcode":"01824",
    "addr:street":"Alpine Ln",
    "iso:country":"US",
    "sg:address":"4 Alpine Ln",
    "sg:city":"Chelmsford",
    "sg:classifiers":[
        {
            "category":"Banks & Credit Unions",
            "subcategory":"Financial Services",
            "type":"Services"
        }
    ],
    "sg:phone":"+1 978 256 2968",
    "sg:postcode":"01824",
    "sg:province":"MA",
    "sg:tags":[
        "broker",
        "mortgage"
    ],
    "sg:website":"www.citifinancial.com",
    "wof:name":"Citifinancial",
    "wof:placetype":"venue"
},
  "geometry": {"coordinates":[-71.346497,42.602501],"type":"Point"}
}