{
  "type": "Feature",
  "properties": {
    "addr:full": "31 Maple St Bellingham MA 02019",
    "addr:housenumber": "31",
    "addr:postcode": "02019",
    "addr:street": "Maple St",
    "iso:country": "US",
    "sg:address": "31 Maple St",
    "sg:city": "Bellingham",
    "sg:classifiers": [
      {
        "category": "Utilities",
        "subcategory": "Cable",
        "type": "Services"
      }
    ],
    "sg:phone": "+1 508 966 0633",
    "sg:postcode": "02019",
    "sg:province": "MA",
    "sg:tags": [
      "satellite",
      "carrier"
    ],
    "wof:name": "U S Communications",
    "wof:placetype": "venue"
  },
  "geometry": {"coordinates":[-71.453871,42.119981],"type":"Point"}
}
