{
  "type": "Feature",
  "properties": {
    "addr:full": "34 Smith St Rehoboth MA 02769",
    "addr:housenumber": "34",
    "addr:postcode": "02769",
    "addr:street": "Smith St",
    "iso:country": "US",
    "sg:address": "34 Smith St",
    "sg:city": "Rehoboth",
    "sg:classifiers": [
      {
        "category": "Building \u0026 Trades",
        "subcategory": "Landscaping Services",
        "type": "Services"
      }
    ],
    "sg:phone": "+1 508 222 7883",
    "sg:postcode": "02769",
    "sg:province": "MA",
    "sg:tags": [
      "landscape",
      "contractor"
    ],
    "wof:name": "Lawnscapes Professional",
    "wof:placetype": "venue"
  },
  "geometry": {"coordinates":[-71.239768,41.908049],"type":"Point"}
}
