{
  "type": "Feature",
  "properties": {
    "addr:full": "390 Main St Worcester MA 01608",
    "addr:housenumber": "390",
    "addr:postcode": "01608",
    "addr:street": "Main St",
    "iso:country": "US",
    "sg:address": "390 Main St",
    "sg:city": "Worcester",
    "sg:classifiers": [
      {
        "category": "Wholesale",
        "subcategory": "Groceries",
        "type": "Manufacturing \u0026 Wholesale Goods"
      }
    ],
    "sg:phone": "+1   ",
    "sg:postcode": "01608",
    "sg:province": "MA",
    "sg:tags": [
      "water",
      "bottled"
    ],
    "wof:name": "Mount Grylock Ntral Spring Wtr",
    "wof:placetype": "venue"
  },
  "geometry": {"coordinates":[-71.801693,42.264819],"type":"Point"}
}
