{
  "type": "Feature",
  "properties": {
    "addr:full": "8 Heritage Rd Shrewsbury MA 01545",
    "addr:housenumber": "8",
    "addr:postcode": "01545",
    "addr:street": "Heritage Rd",
    "iso:country": "US",
    "sg:address": "8 Heritage Rd",
    "sg:city": "Shrewsbury",
    "sg:classifiers": [
      {
        "category": "Education",
        "subcategory": "Vocational School",
        "type": "Public Place"
      }
    ],
    "sg:phone": "+1   ",
    "sg:postcode": "01545",
    "sg:province": "MA",
    "sg:tags": [
      "development",
      "training",
      "software"
    ],
    "wof:name": "Meg Vootukuru Madhavi",
    "wof:placetype": "venue"
  },
  "geometry": {"coordinates":[-71.723317,42.279022],"type":"Point"}
}
