{
  "type": "Feature",
  "properties": {
    "addr:full":"1 Natsue Way Middleton MA 01949",
    "addr:housenumber":"1",
    "addr:postcode":"01949",
    "addr:street":"Natsue Way",
    "iso:country":"US",
    "sg:address":"1 Natsue Way",
    "sg:city":"Middleton",
    "sg:classifiers":[
        {
            "category":"Manufacturing",
            "subcategory":"Tools & Machinery",
            "type":"Manufacturing & Wholesale Goods"
        },
        {
            "category":"Freight",
            "type":"Transportation"
        },
        {
            "category":"Building & Trades",
            "subcategory":"Construction",
            "type":"Services"
        },
        {
            "category":"Home & Garden",
            "subcategory":"Carpets & Floor Coverings",
            "type":"Retail Goods"
        }
    ],
    "sg:phone":"+1 978 774 7415",
    "sg:postcode":"01949",
    "sg:province":"MA",
    "sg:tags":[
        "aerial",
        "scaffolding",
        "lift",
        "rigger",
        "trucking",
        "erectors",
        "mover",
        "local"
    ],
    "wof:name":"Quinn, D L Co Moving & Storage",
    "wof:placetype":"venue"
},
  "geometry": {"coordinates":[-71.00578299999999,42.571468],"type":"Point"}
}