{
  "type": "Feature",
  "properties": {
    "addr:full": "1 Natsue Way Middleton MA 01949",
    "addr:housenumber": "1",
    "addr:postcode": "01949",
    "addr:street": "Natsue Way",
    "iso:country": "US",
    "sg:address": "1 Natsue Way",
    "sg:city": "Middleton",
    "sg:classifiers": [
      {
        "category": "Manufacturing",
        "subcategory": "Tools \u0026 Machinery",
        "type": "Manufacturing \u0026 Wholesale Goods"
      },
      {
        "category": "Freight",
        "type": "Transportation"
      },
      {
        "category": "Building \u0026 Trades",
        "subcategory": "Construction",
        "type": "Services"
      },
      {
        "category": "Home \u0026 Garden",
        "subcategory": "Carpets \u0026 Floor Coverings",
        "type": "Retail Goods"
      }
    ],
    "sg:phone": "+1 978 774 7415",
    "sg:postcode": "01949",
    "sg:province": "MA",
    "sg:tags": [
      "aerial",
      "scaffolding",
      "lift",
      "rigger",
      "trucking",
      "erectors",
      "mover",
      "local"
    ],
    "wof:name": "Quinn, D L Co Moving \u0026 Storage",
    "wof:placetype": "venue"
  },
  "geometry": {"coordinates":[-71.005783,42.571468],"type":"Point"}
}
