{
  "type": "Feature",
  "properties": {
    "addr:full":"1058 Pleasant St Palmer MA 01069",
    "addr:housenumber":"1058",
    "addr:postcode":"01069",
    "addr:street":"Pleasant St",
    "iso:country":"US",
    "sg:address":"1058 Pleasant St",
    "sg:city":"Palmer",
    "sg:classifiers":[
        {
            "category":"Real Estate",
            "subcategory":"Real Estate Agent",
            "type":"Services"
        }
    ],
    "sg:phone":"+1 413 283 4242",
    "sg:postcode":"01069",
    "sg:province":"MA",
    "sg:tags":[
        "appraiser"
    ],
    "wof:name":"Yankee Properties",
    "wof:placetype":"venue"
},
  "geometry": {"coordinates":[-72.326239,42.156203],"type":"Point"}
}