{
  "type": "Feature",
  "properties": {
    "iso:country":"US",
    "sg:address":"7 Hill St",
    "sg:city":"Norwood",
    "sg:classifiers":[
        {
            "category":"Building & Trades",
            "subcategory":"Locksmith",
            "type":"Services"
        }
    ],
    "sg:phone":"+1 781 501 4471",
    "sg:postcode":"02062",
    "sg:province":"MA",
    "sg:tags":[
        "key"
    ],
    "wof:name":"Locksmith Service On Hill All Week 24 Emergency",
    "wof:placetype":"venue"
},
  "geometry": {"coordinates":[-71.19657599999999,42.195908],"type":"Point"}
}