{
  "type": "Feature",
  "properties": {
    "addr:full":"17 North St Ware MA 01082",
    "addr:housenumber":"17",
    "addr:postcode":"01082",
    "addr:street":"North St",
    "iso:country":"US",
    "sg:address":"17 North St",
    "sg:city":"Ware",
    "sg:classifiers":[
        {
            "category":"Organizations",
            "subcategory":"Religious Organization",
            "type":"Services"
        }
    ],
    "sg:phone":"+1 413 967 4963",
    "sg:postcode":"01082",
    "sg:province":"MA",
    "sg:tags":[
        "church"
    ],
    "wof:name":"All Saints Rectory",
    "wof:placetype":"venue"
},
  "geometry": {"coordinates":[-72.24138600000001,42.260873],"type":"Point"}
}