{
  "type": "Feature",
  "properties": {
    "iso:country":"US",
    "sg:address":"40 Main St",
    "sg:city":"Florence",
    "sg:classifiers":[
        {
            "category":"Museum",
            "type":"Entertainment"
        }
    ],
    "sg:phone":"+1 413 585 5968",
    "sg:postcode":"01062",
    "sg:province":"MA",
    "sg:tags":[
        "organization",
        "arts",
        "information"
    ],
    "wof:name":"Fund For Women Artists",
    "wof:placetype":"venue"
},
  "geometry": {"coordinates":[-72.66965399999999,42.335088],"type":"Point"}
}