{
  "type": "Feature",
  "properties": {
    "iso:country":"US",
    "sg:address":"127 Main St",
    "sg:city":"Buzzards Bay",
    "sg:classifiers":[
        {
            "category":"Real Estate",
            "subcategory":"Real Estate Agent",
            "type":"Services"
        }
    ],
    "sg:phone":"+1 508 759 6262",
    "sg:postcode":"02532",
    "sg:province":"MA",
    "sg:website":"www.bridgewayre.com",
    "wof:name":"Bridgeway Realtors Inc",
    "wof:placetype":"venue"
},
  "geometry": {"coordinates":[-70.614914,41.745218],"type":"Point"}
}