{
  "type": "Feature",
  "properties": {
    "addr:full":"16 Prospect St Cambridge MA 02139",
    "addr:housenumber":"16",
    "addr:postcode":"02139",
    "addr:street":"Prospect St",
    "iso:country":"US",
    "sg:address":"16 Prospect St",
    "sg:city":"Cambridge",
    "sg:classifiers":[
        {
            "category":"Personal",
            "subcategory":"Barber",
            "type":"Services"
        }
    ],
    "sg:phone":"+1 617 492 2962",
    "sg:postcode":"02139",
    "sg:province":"MA",
    "wof:name":"John's Barber Shop",
    "wof:placetype":"venue"
},
  "geometry": {"coordinates":[-71.1035,42.365898],"type":"Point"}
}