{
  "type": "Feature",
  "properties": {
    "iso:country":"US",
    "sg:address":"59 Washington St",
    "sg:city":"Weymouth",
    "sg:classifiers":[
        {
            "category":"Real Estate",
            "subcategory":"Real Estate Agent",
            "type":"Services"
        }
    ],
    "sg:phone":"+1 781 335 2230",
    "sg:postcode":"02188",
    "sg:province":"MA",
    "wof:name":"Brava Real Estate Inc",
    "wof:placetype":"venue"
},
  "geometry": {"coordinates":[-70.967602,42.21923],"type":"Point"}
}