{
  "type": "Feature",
  "properties": {
    "iso:country":"US",
    "sg:address":"1692 Massachusetts Avenue",
    "sg:city":"Cambridge",
    "sg:classifiers":[
        {
            "category":"Health Services",
            "subcategory":"Dentist",
            "type":"Services"
        }
    ],
    "sg:phone":"+1 617 492 3616",
    "sg:postcode":"02138",
    "sg:province":"MA",
    "sg:tags":[
        "endodontist"
    ],
    "wof:name":"Howard A Levine DMD",
    "wof:placetype":"venue"
},
  "geometry": {"coordinates":[-71.119562,42.382525],"type":"Point"}
}