{
  "type": "Feature",
  "properties": {
    "addr:full":"301 W Main St Chartley MA 02766",
    "addr:housenumber":"301",
    "addr:postcode":"02766",
    "addr:street":"W Main St",
    "iso:country":"US",
    "sg:address":"301 W Main St",
    "sg:city":"Chartley",
    "sg:classifiers":[
        {
            "category":"Manufacturing",
            "subcategory":"Tools & Machinery",
            "type":"Manufacturing & Wholesale Goods"
        }
    ],
    "sg:phone":"+1 508 222 7126",
    "sg:postcode":"02766",
    "sg:province":"MA",
    "wof:name":"Triad Inc",
    "wof:placetype":"venue"
},
  "geometry": {"coordinates":[-71.22349699999999,41.952063],"type":"Point"}
}