{
  "type": "Feature",
  "properties": {
    "addr:full":"140 Tremont St Boston MA 02111",
    "addr:housenumber":"140",
    "addr:postcode":"02111",
    "addr:street":"Tremont St",
    "iso:country":"US",
    "sg:address":"140 Tremont St",
    "sg:city":"Boston",
    "sg:classifiers":[
        {
            "category":"Deli",
            "type":"Food & Drink"
        },
        {
            "category":"Restaurant",
            "type":"Food & Drink"
        },
        {
            "category":"Wholesale",
            "subcategory":"Fruits & Vegetables",
            "type":"Manufacturing & Wholesale Goods"
        },
        {
            "category":"Food & Beverages",
            "subcategory":"Groceries & Convenience Stores",
            "type":"Retail Goods"
        }
    ],
    "sg:phone":"+1 617 338 6500",
    "sg:postcode":"02111",
    "sg:province":"MA",
    "sg:tags":[
        "delicatessen",
        "veggie"
    ],
    "sg:website":"www.lambertsofboston.com",
    "wof:name":"Lambert's Marketplace",
    "wof:placetype":"venue"
},
  "geometry": {"coordinates":[-71.062893,42.355648],"type":"Point"}
}