{
  "type": "Feature",
  "properties": {
    "iso:country":"US",
    "sg:address":"222b E Main St",
    "sg:city":"Marlborough",
    "sg:classifiers":[
        {
            "category":"Restaurant",
            "type":"Food & Drink"
        }
    ],
    "sg:menulink":"http://www.allmenus.com/ma/marlborough/43716-sals-pizza/menu/",
    "sg:phone":"+1 508 624 7257",
    "sg:postcode":"01752",
    "sg:province":"MA",
    "sg:tags":[
        "american",
        "pizza"
    ],
    "wof:name":"Sal's Pizza",
    "wof:placetype":"venue"
},
  "geometry": {"coordinates":[-71.534789,42.351087],"type":"Point"}
}