{
  "type": "Feature",
  "properties": {
    "addr:full": "8 Landing Ln Hopedale MA 01747",
    "addr:housenumber": "8",
    "addr:postcode": "01747",
    "addr:street": "Landing Ln",
    "iso:country": "US",
    "sg:address": "8 Landing Ln",
    "sg:city": "Hopedale",
    "sg:classifiers": [
      {
        "category": "Professional",
        "type": "Services"
      }
    ],
    "sg:phone": "+1 508 478 3881",
    "sg:postcode": "01747",
    "sg:province": "MA",
    "sg:tags": [
      "establishment"
    ],
    "wof:name": "Sjm Soft",
    "wof:placetype": "venue"
  },
  "geometry": {"coordinates":[-71.511325,42.103398],"type":"Point"}
}
