{
  "type": "Feature",
  "properties": {
    "addr:full": "635 Main St Great Barrington MA 01230",
    "addr:housenumber": "635",
    "addr:postcode": "01230",
    "addr:street": "Main St",
    "iso:country": "US",
    "sg:address": "635 Main St",
    "sg:city": "Great Barrington",
    "sg:classifiers": [
      {
        "category": "Shopping",
        "subcategory": "Florist",
        "type": "Retail Goods"
      }
    ],
    "sg:phone": "+1 413 528 0245",
    "sg:postcode": "01230",
    "sg:province": "MA",
    "wof:name": "Farmhouse LLC",
    "wof:placetype": "venue"
  },
  "geometry": {"coordinates":[-73.364496,42.182359],"type":"Point"}
}
