{
  "type": "Feature",
  "properties": {
    "iso:country":"US",
    "sg:address":"230 S Main St",
    "sg:city":"Middleton",
    "sg:classifiers":[
        {
            "category":"Banks & Credit Unions",
            "subcategory":"Bank",
            "type":"Services"
        }
    ],
    "sg:phone":"+1 978 774 4345",
    "sg:postcode":"01949",
    "sg:province":"MA",
    "wof:name":"Banknorth",
    "wof:placetype":"venue"
},
  "geometry": {"coordinates":[-71.00121900000001,42.580235],"type":"Point"}
}