{
  "type": "Feature",
  "properties": {
    "addr:full":"26 Townsend Rd Shirley MA 01464",
    "addr:housenumber":"26",
    "addr:postcode":"01464",
    "addr:street":"Townsend Rd",
    "iso:country":"US",
    "sg:address":"26 Townsend Rd",
    "sg:city":"Shirley",
    "sg:classifiers":[
        {
            "category":"Building & Trades",
            "subcategory":"Construction",
            "type":"Services"
        }
    ],
    "sg:phone":"+1 978 425 9751",
    "sg:postcode":"01464",
    "sg:province":"MA",
    "sg:tags":[
        "excavating",
        "contractor"
    ],
    "wof:name":"G J Caruso Paveway Corp",
    "wof:placetype":"venue"
},
  "geometry": {"coordinates":[-71.650909,42.588964],"type":"Point"}
}