{
  "type": "Feature",
  "properties": {
    "addr:full":"5 Anthony Rd Tewksbury MA 01876",
    "addr:housenumber":"5",
    "addr:postcode":"01876",
    "addr:street":"Anthony Rd",
    "iso:country":"US",
    "sg:address":"5 Anthony Rd",
    "sg:city":"Tewksbury",
    "sg:classifiers":[
        {
            "category":"Professional",
            "subcategory":"Accounting & Tax Preparation",
            "type":"Services"
        }
    ],
    "sg:phone":"+1 978 851 3984",
    "sg:postcode":"01876",
    "sg:province":"MA",
    "sg:tags":[
        "return",
        "filing"
    ],
    "wof:name":"James M Batten",
    "wof:placetype":"venue"
},
  "geometry": {"coordinates":[-71.18912899999999,42.608216],"type":"Point"}
}