{
  "type": "Feature",
  "properties": {
    "addr:full":"82 Parkman St Boston MA 02114",
    "addr:housenumber":"82",
    "addr:postcode":"02114",
    "addr:street":"Parkman St",
    "iso:country":"US",
    "sg:address":"82 Parkman St",
    "sg:city":"Boston",
    "sg:classifiers":[
        {
            "category":"Building & Trades",
            "subcategory":"Locksmith",
            "type":"Services"
        }
    ],
    "sg:phone":"+1 617 704 9186",
    "sg:postcode":"02114",
    "sg:province":"MA",
    "sg:tags":[
        "key"
    ],
    "wof:name":"Emergency Locksmith Available 24 7",
    "wof:placetype":"venue"
},
  "geometry": {"coordinates":[-71.068422,42.362026],"type":"Point"}
}