{
  "type": "Feature",
  "properties": {
    "addr:full":"298 Washington St Fl 1 Gloucester MA 01930",
    "addr:housenumber":"298;1",
    "addr:postcode":"01930",
    "addr:street":"Washington St",
    "iso:country":"US",
    "sg:address":"298 Washington St Fl 1",
    "sg:city":"Gloucester",
    "sg:classifiers":[
        {
            "category":"Organizations",
            "subcategory":"Membership Organization",
            "type":"Services"
        }
    ],
    "sg:phone":"+1 978 282 0676",
    "sg:postcode":"01930",
    "sg:province":"MA",
    "sg:tags":[
        "military",
        "veteran"
    ],
    "wof:name":"Gloucester Outpatient Clinic",
    "wof:placetype":"venue"
},
  "geometry": {"coordinates":[-70.679192,42.625359],"type":"Point"}
}