{
  "type": "Feature",
  "properties": {
    "iso:country":"US",
    "sg:address":"29 Commonwealth Avenue Ste 901",
    "sg:city":"Boston",
    "sg:classifiers":[
        {
            "category":"Professional",
            "subcategory":"Advertising",
            "type":"Services"
        }
    ],
    "sg:phone":"+1 617 412 4050",
    "sg:postcode":"02116",
    "sg:province":"MA",
    "sg:tags":[
        "marketing"
    ],
    "sg:website":"www.trinity1.com",
    "wof:name":"TrinityOne Inc",
    "wof:placetype":"venue"
},
  "geometry": {"coordinates":[-71.07429999999999,42.3534],"type":"Point"}
}