{
  "type": "Feature",
  "properties": {
    "iso:country":"US",
    "sg:address":"451 D St",
    "sg:city":"Boston",
    "sg:classifiers":[
        {
            "category":"Banks & Credit Unions",
            "subcategory":"Investment Brokerage",
            "type":"Services"
        }
    ],
    "sg:phone":"+1 617 261 4646",
    "sg:postcode":"02210",
    "sg:province":"MA",
    "sg:tags":[
        "investing",
        "advisory",
        "financial"
    ],
    "sg:website":"www.michelltd.com",
    "wof:name":"Michel Associates",
    "wof:placetype":"venue"
},
  "geometry": {"coordinates":[-71.04299899999999,42.345501],"type":"Point"}
}