{
  "type": "Feature",
  "properties": {
    "addr:full": "451 D St Boston MA 02210",
    "addr:housenumber": "451",
    "addr:postcode": "02210",
    "addr:street": "D St",
    "iso:country": "US",
    "sg:address": "451 D St",
    "sg:city": "Boston",
    "sg:classifiers": [
      {
        "category": "Banks \u0026 Credit Unions",
        "subcategory": "Investment Brokerage",
        "type": "Services"
      }
    ],
    "sg:phone": "+1 617 261 4646",
    "sg:postcode": "02210",
    "sg:province": "MA",
    "sg:tags": [
      "investing",
      "advisory",
      "financial"
    ],
    "sg:website": "www.michelltd.com",
    "wof:name": "Michel Associates",
    "wof:placetype": "venue"
  },
  "geometry": {"coordinates":[-71.042999,42.345501],"type":"Point"}
}
