{
  "type": "Feature",
  "properties": {
    "addr:full":"111 Devonshire St Boston MA 02109",
    "addr:housenumber":"111",
    "addr:postcode":"02109",
    "addr:street":"Devonshire St",
    "iso:country":"US",
    "sg:address":"111 Devonshire St",
    "sg:city":"Boston",
    "sg:classifiers":[
        {
            "category":"Professional",
            "subcategory":"Lawyer & Legal Services",
            "type":"Services"
        }
    ],
    "sg:phone":"+1 617 654 8208",
    "sg:postcode":"02109",
    "sg:province":"MA",
    "wof:name":"Gilman Pamela Slater",
    "wof:placetype":"venue"
},
  "geometry": {"coordinates":[-71.05729700000001,42.3577],"type":"Point"}
}