{
  "type": "Feature",
  "properties": {
    "iso:country":"US",
    "sg:address":"22 Mill Street",
    "sg:city":"Arlington",
    "sg:classifiers":[
        {
            "category":"Health Services",
            "subcategory":"Doctor",
            "type":"Services"
        },
        {
            "category":"Sports & Exercise",
            "subcategory":"Gym",
            "type":"Entertainment"
        }
    ],
    "sg:phone":"+1 781 646 4345",
    "sg:postcode":"02476",
    "sg:province":"MA",
    "sg:tags":[
        "trainer"
    ],
    "wof:name":"Morvai Ann MD",
    "wof:placetype":"venue"
},
  "geometry": {"coordinates":[-71.157782,42.417424],"type":"Point"}
}