{
  "type": "Feature",
  "properties": {
    "addr:full":"110 Andover St North Andover MA 01845",
    "addr:housenumber":"110",
    "addr:postcode":"01845",
    "addr:street":"Andover St",
    "iso:country":"US",
    "sg:address":"110 Andover St",
    "sg:city":"North Andover",
    "sg:classifiers":[
        {
            "category":"Shopping",
            "subcategory":"Bicycles & Sporting Goods",
            "type":"Retail Goods"
        }
    ],
    "sg:phone":"+1 978 688 4292",
    "sg:postcode":"01845",
    "sg:province":"MA",
    "sg:tags":[
        "equipment",
        "hockey"
    ],
    "wof:name":"Madeline A Sweeney Foundation",
    "wof:placetype":"venue"
},
  "geometry": {"coordinates":[-71.117023,42.681924],"type":"Point"}
}