{
  "type": "Feature",
  "properties": {
    "addr:full": "1070 Osgood St North Andover MA 01845",
    "addr:housenumber": "1070",
    "addr:postcode": "01845",
    "addr:street": "Osgood St",
    "iso:country": "US",
    "sg:address": "1070 Osgood St",
    "sg:city": "North Andover",
    "sg:classifiers": [
      {
        "category": "Restaurant",
        "type": "Food \u0026 Drink"
      }
    ],
    "sg:phone": "+1 978 685 7979",
    "sg:postcode": "01845",
    "sg:province": "MA",
    "wof:name": "Chai Restaurant",
    "wof:placetype": "venue"
  },
  "geometry": {"coordinates":[-71.115721,42.715149],"type":"Point"}
}
