{
  "type": "Feature",
  "properties": {
    "iso:country":"US",
    "sg:address":"2 Braunecker Rd",
    "sg:city":"Plymouth",
    "sg:classifiers":[
        {
            "category":"Professional",
            "subcategory":"Accounting & Tax Preparation",
            "type":"Services"
        }
    ],
    "sg:phone":"+1   ",
    "sg:postcode":"02360",
    "sg:province":"MA",
    "wof:name":"Dunham Rh Tax Services",
    "wof:placetype":"venue"
},
  "geometry": {"coordinates":[-70.682667,41.963704],"type":"Point"}
}