{
  "type": "Feature",
  "properties": {
    "addr:full":"508 River St Mattapan MA 02126",
    "addr:housenumber":"508",
    "addr:postcode":"02126",
    "addr:street":"River St",
    "iso:country":"US",
    "sg:address":"508 River St",
    "sg:city":"Mattapan",
    "sg:classifiers":[
        {
            "category":"Banks & Credit Unions",
            "subcategory":"Bank",
            "type":"Services"
        }
    ],
    "sg:phone":"+1 617 298 9366",
    "sg:postcode":"02126",
    "sg:province":"MA",
    "sg:tags":[
        "money",
        "order"
    ],
    "wof:name":"Boby Express Co",
    "wof:placetype":"venue"
},
  "geometry": {"coordinates":[-71.09338,42.267786],"type":"Point"}
}