{
  "type": "Feature",
  "properties": {
    "iso:country":"US",
    "sg:address":"1831 Bedford St",
    "sg:city":"Fall River",
    "sg:classifiers":[
        {
            "category":"Government",
            "subcategory":"Office",
            "type":"Public Place"
        }
    ],
    "sg:phone":"+1 508 324 2725",
    "sg:postcode":"02723",
    "sg:province":"MA",
    "sg:tags":[
        "village"
    ],
    "wof:name":"Fall River Water Filtration",
    "wof:placetype":"venue"
},
  "geometry": {"coordinates":[-71.123865,41.696094],"type":"Point"}
}