{
  "type": "Feature",
  "properties": {
    "addr:full":"14 Chestnut St Gloucester MA 01930",
    "addr:housenumber":"14",
    "addr:postcode":"01930",
    "addr:street":"Chestnut St",
    "iso:country":"US",
    "sg:address":"14 Chestnut St",
    "sg:city":"Gloucester",
    "sg:classifiers":[
        {
            "category":"Personal",
            "subcategory":"Beauty Salon",
            "type":"Services"
        }
    ],
    "sg:phone":"+1 978 281 3688",
    "sg:postcode":"01930",
    "sg:province":"MA",
    "wof:name":"Kerry's Salon",
    "wof:placetype":"venue"
},
  "geometry": {"coordinates":[-70.660089,42.613801],"type":"Point"}
}