{
  "type": "Feature",
  "properties": {
    "iso:country":"US",
    "sg:address":"65 Boyd St",
    "sg:city":"Watertown",
    "sg:classifiers":[
        {
            "category":"Freight",
            "type":"Transportation"
        }
    ],
    "sg:phone":"+1   ",
    "sg:postcode":"02472",
    "sg:province":"MA",
    "sg:tags":[
        "operator",
        "local",
        "trucking"
    ],
    "wof:name":"Aristocrat Movers Inc",
    "wof:placetype":"venue"
},
  "geometry": {"coordinates":[-71.190136,42.360424],"type":"Point"}
}