{
  "type": "Feature",
  "properties": {
    "addr:full":"131 Park Dr Apt G1 Boston MA 02215",
    "addr:housenumber":"131",
    "addr:postcode":"02215",
    "addr:street":"Park Dr Apt G1",
    "iso:country":"US",
    "sg:address":"131 Park Dr Apt G1",
    "sg:city":"Boston",
    "sg:classifiers":[
        {
            "category":"Real Estate",
            "subcategory":"Real Estate Services",
            "type":"Services"
        }
    ],
    "sg:phone":"+1 617 236 6977",
    "sg:postcode":"02215",
    "sg:province":"MA",
    "sg:tags":[
        "management",
        "property"
    ],
    "wof:name":"Modica Associate",
    "wof:placetype":"venue"
},
  "geometry": {"coordinates":[-71.097702,42.341599],"type":"Point"}
}