{
  "type": "Feature",
  "properties": {
    "iso:country":"US",
    "sg:address":"171 Amory St",
    "sg:city":"Brookline",
    "sg:classifiers":[
        {
            "category":"Travel",
            "subcategory":"Travel Agent",
            "type":"Entertainment"
        }
    ],
    "sg:phone":"+1 617 232 1708",
    "sg:postcode":"02446",
    "sg:province":"MA",
    "sg:tags":[
        "agency",
        "bureau"
    ],
    "wof:name":"Universe Travel Inc",
    "wof:placetype":"venue"
},
  "geometry": {"coordinates":[-71.113748,42.350521],"type":"Point"}
}