{
  "type": "Feature",
  "properties": {
    "addr:full": "515 Washington St Canton MA 02021",
    "addr:housenumber": "515",
    "addr:postcode": "02021",
    "addr:street": "Washington St",
    "iso:country": "US",
    "sg:address": "515 Washington St",
    "sg:city": "Canton",
    "sg:classifiers": [
      {
        "category": "Retail",
        "subcategory": "Auto Repair",
        "type": "Services"
      }
    ],
    "sg:phone": "+1 781 575 0066",
    "sg:postcode": "02021",
    "sg:province": "MA",
    "sg:tags": [
      "wrecker"
    ],
    "wof:name": "White's Towing",
    "wof:placetype": "venue"
  },
  "geometry": {"coordinates":[-71.148214,42.15213],"type":"Point"}
}
