{
  "type": "Feature",
  "properties": {
    "addr:full":"41 Elm St Marblehead MA 01945",
    "addr:housenumber":"41",
    "addr:postcode":"01945",
    "addr:street":"Elm St",
    "iso:country":"US",
    "sg:address":"41 Elm St",
    "sg:city":"Marblehead",
    "sg:classifiers":[
        {
            "category":"Arena",
            "subcategory":"Sports Club",
            "type":"Entertainment"
        }
    ],
    "sg:phone":"+1   ",
    "sg:postcode":"01945",
    "sg:province":"MA",
    "wof:name":"Premier Racing Inc",
    "wof:placetype":"venue"
},
  "geometry": {"coordinates":[-70.84908299999999,42.507583],"type":"Point"}
}