{
  "type": "Feature",
  "properties": {
    "addr:full":"42 Adams St Foxboro MA 02035",
    "addr:housenumber":"42",
    "addr:postcode":"02035",
    "addr:street":"Adams St",
    "iso:country":"US",
    "sg:address":"42 Adams St",
    "sg:city":"Foxboro",
    "sg:classifiers":[
        {
            "category":"Professional",
            "subcategory":"Management & Consulting",
            "type":"Services"
        }
    ],
    "sg:phone":"+1 508 543 7778",
    "sg:postcode":"02035",
    "sg:province":"MA",
    "sg:tags":[
        "consultant",
        "educational"
    ],
    "wof:name":"Educational Sales Assoc",
    "wof:placetype":"venue"
},
  "geometry": {"coordinates":[-71.21025,42.060849],"type":"Point"}
}