{
  "type": "Feature",
  "properties": {
    "addr:full":"1 New St Cambridge MA 02138",
    "addr:housenumber":"1",
    "addr:postcode":"02138",
    "addr:street":"New St",
    "iso:country":"US",
    "sg:address":"1 New St",
    "sg:city":"Cambridge",
    "sg:classifiers":[
        {
            "category":"Health Services",
            "subcategory":"Health Practitioner",
            "type":"Services"
        }
    ],
    "sg:phone":"+1 617 441 5550",
    "sg:postcode":"02138",
    "sg:province":"MA",
    "sg:tags":[
        "midwife"
    ],
    "wof:name":"Valerie Hodenius CNM",
    "wof:placetype":"venue"
},
  "geometry": {"coordinates":[-71.138944,42.389963],"type":"Point"}
}