{
  "type": "Feature",
  "properties": {
    "addr:full": "364 N Main St Sharon MA 02067",
    "addr:housenumber": "364",
    "addr:postcode": "02067",
    "addr:street": "N Main St",
    "iso:country": "US",
    "sg:address": "364 N Main St",
    "sg:city": "Sharon",
    "sg:classifiers": [
      {
        "category": "Professional",
        "type": "Services"
      }
    ],
    "sg:phone": "+1 781 784 6200",
    "sg:postcode": "02067",
    "sg:province": "MA",
    "wof:name": "Lincour Inc",
    "wof:placetype": "venue"
  },
  "geometry": {"coordinates":[-71.157816,42.136758],"type":"Point"}
}
