{
  "type": "Feature",
  "properties": {
    "iso:country":"US",
    "sg:address":"14 Alton Ct",
    "sg:city":"Brookline",
    "sg:classifiers":[
        {
            "category":"Professional",
            "subcategory":"Management & Consulting",
            "type":"Services"
        }
    ],
    "sg:phone":"+1 617 232 5400",
    "sg:postcode":"02446",
    "sg:province":"MA",
    "sg:tags":[
        "export"
    ],
    "wof:name":"Glynn International Inc",
    "wof:placetype":"venue"
},
  "geometry": {"coordinates":[-71.119471,42.338038],"type":"Point"}
}