{
  "type": "Feature",
  "properties": {
    "addr:full":"77 Franklin St Lbby Boston MA 02110",
    "addr:housenumber":"77",
    "addr:postcode":"02110",
    "addr:street":"Franklin St",
    "iso:country":"US",
    "sg:address":"77 Franklin St Lbby",
    "sg:city":"Boston",
    "sg:classifiers":[
        {
            "category":"Professional",
            "subcategory":"Lawyer & Legal Services",
            "type":"Services"
        }
    ],
    "sg:phone":"+1 617 933 3838",
    "sg:postcode":"02110",
    "sg:province":"MA",
    "sg:tags":[
        "attorney",
        "practice",
        "worker",
        "benefit",
        "labor",
        "compensation",
        "employee",
        "law",
        "employment"
    ],
    "wof:name":"Davis & Davis",
    "wof:placetype":"venue"
},
  "geometry": {"coordinates":[-71.058037,42.355412],"type":"Point"}
}