{
  "type": "Feature",
  "properties": {
    "iso:country":"US",
    "sg:address":"56 Sparrow Rd",
    "sg:city":"Stoughton",
    "sg:classifiers":[
        {
            "category":"Education",
            "subcategory":"School",
            "type":"Public Place"
        }
    ],
    "sg:phone":"+1   ",
    "sg:postcode":"02072",
    "sg:province":"MA",
    "wof:name":"London Sports Academy Inc",
    "wof:placetype":"venue"
},
  "geometry": {"coordinates":[-71.133257,42.120029],"type":"Point"}
}