{
  "type": "Feature",
  "properties": {
    "iso:country":"US",
    "sg:address":"34 Farnsworth St Fl 2",
    "sg:city":"Boston",
    "sg:classifiers":[
        {
            "category":"Communications",
            "subcategory":"Radio Station",
            "type":"Services"
        },
        {
            "category":"Professional",
            "subcategory":"Business Services",
            "type":"Services"
        }
    ],
    "sg:phone":"+1 617 502 8400",
    "sg:postcode":"02210",
    "sg:province":"MA",
    "sg:tags":[
        "medium",
        "publicity",
        "broker"
    ],
    "sg:website":"http://www.pgrmedia.com",
    "wof:name":"Pgr Media",
    "wof:placetype":"venue"
},
  "geometry": {"coordinates":[-71.04864999999999,42.351303],"type":"Point"}
}