{
  "type": "Feature",
  "properties": {
    "iso:country":"US",
    "sg:address":"205 Highland Ave",
    "sg:city":"Salem",
    "sg:classifiers":[
        {
            "category":"Real Estate",
            "subcategory":"Real Estate Operator",
            "type":"Services"
        }
    ],
    "sg:phone":"+1 978 825 0030",
    "sg:postcode":"01970",
    "sg:province":"MA",
    "sg:tags":[
        "apartment"
    ],
    "wof:name":"Hawthorne Commons",
    "wof:placetype":"venue"
},
  "geometry": {"coordinates":[-70.919978,42.50511],"type":"Point"}
}