{
  "type": "Feature",
  "properties": {
    "addr:full":"1 Buttonwood Ln Scituate MA 02066",
    "addr:housenumber":"1",
    "addr:postcode":"02066",
    "addr:street":"Buttonwood Ln",
    "iso:country":"US",
    "sg:address":"1 Buttonwood Ln",
    "sg:city":"Scituate",
    "sg:classifiers":[
        {
            "category":"Building & Trades",
            "subcategory":"Plumbing",
            "type":"Services"
        }
    ],
    "sg:phone":"+1 781 545 6874",
    "sg:postcode":"02066",
    "sg:province":"MA",
    "sg:tags":[
        "plumber",
        "contractor"
    ],
    "wof:name":"A P Cassidy Co Inc",
    "wof:placetype":"venue"
},
  "geometry": {"coordinates":[-70.76458,42.23864],"type":"Point"}
}