{
  "type": "Feature",
  "properties": {
    "iso:country":"US",
    "sg:address":"1274 Broadway",
    "sg:city":"Somerville",
    "sg:classifiers":[
        {
            "category":"Real Estate",
            "subcategory":"Real Estate Agent",
            "type":"Services"
        }
    ],
    "sg:phone":"+1 617 623 5566",
    "sg:postcode":"02144",
    "sg:province":"MA",
    "wof:name":"Everest Realty",
    "wof:placetype":"venue"
},
  "geometry": {"coordinates":[-71.130675,42.405376],"type":"Point"}
}