{
  "type": "Feature",
  "properties": {
    "iso:country":"US",
    "sg:address":"85 Millbury St",
    "sg:city":"Worcester",
    "sg:classifiers":[
        {
            "category":"Retail",
            "subcategory":"Self-service Laundry",
            "type":"Services"
        }
    ],
    "sg:phone":"+1 508 752 9443",
    "sg:postcode":"01610",
    "sg:province":"MA",
    "wof:name":"Oscar's Coin-Op",
    "wof:placetype":"venue"
},
  "geometry": {"coordinates":[-71.79897800000001,42.252848],"type":"Point"}
}