{
  "type": "Feature",
  "properties": {
    "addr:full": "85 Millbury St Worcester MA 01610",
    "addr:housenumber": "85",
    "addr:postcode": "01610",
    "addr:street": "Millbury St",
    "iso:country": "US",
    "sg:address": "85 Millbury St",
    "sg:city": "Worcester",
    "sg:classifiers": [
      {
        "category": "Retail",
        "subcategory": "Self-service Laundry",
        "type": "Services"
      }
    ],
    "sg:phone": "+1 508 752 9443",
    "sg:postcode": "01610",
    "sg:province": "MA",
    "wof:name": "Oscar's Coin-Op",
    "wof:placetype": "venue"
  },
  "geometry": {"coordinates":[-71.798978,42.252848],"type":"Point"}
}
