{
  "type": "Feature",
  "properties": {
    "addr:full": "156 Hayden Rowe St Hopkinton MA 01748",
    "addr:housenumber": "156",
    "addr:postcode": "01748",
    "addr:street": "Hayden Rowe St",
    "iso:country": "US",
    "sg:address": "156 Hayden Rowe St",
    "sg:city": "Hopkinton",
    "sg:classifiers": [
      {
        "category": "Manufacturing",
        "subcategory": "Tools \u0026 Machinery",
        "type": "Manufacturing \u0026 Wholesale Goods"
      }
    ],
    "sg:phone": "+1 508 435 5350",
    "sg:postcode": "01748",
    "sg:province": "MA",
    "sg:tags": [
      "measuring",
      "instrument",
      "electrical",
      "mfg"
    ],
    "sg:website": "www.measurepoint.com",
    "wof:name": "Measurepoint Corp",
    "wof:placetype": "venue"
  },
  "geometry": {"coordinates":[-71.514013,42.211699],"type":"Point"}
}
