{
  "type": "Feature",
  "properties": {
    "iso:country":"US",
    "sg:address":"16 Central St",
    "sg:city":"Arlington",
    "sg:classifiers":[
        {
            "category":"Building & Trades",
            "subcategory":"Construction",
            "type":"Services"
        }
    ],
    "sg:phone":"+1 781 648 4201",
    "sg:postcode":"02476",
    "sg:province":"MA",
    "sg:tags":[
        "handyman"
    ],
    "wof:name":"Dennis Piechota",
    "wof:placetype":"venue"
},
  "geometry": {"coordinates":[-71.156441,42.41687],"type":"Point"}
}