{
  "type": "Feature",
  "properties": {
    "iso:country":"US",
    "sg:address":"466 Washington Ave",
    "sg:city":"Chelsea",
    "sg:classifiers":[
        {
            "category":"Professional",
            "subcategory":"Accounting & Tax Preparation",
            "type":"Services"
        }
    ],
    "sg:phone":"+1   ",
    "sg:postcode":"02150",
    "sg:province":"MA",
    "sg:tags":[
        "return"
    ],
    "wof:name":"Bruce E Searleman",
    "wof:placetype":"venue"
},
  "geometry": {"coordinates":[-71.032229,42.406659],"type":"Point"}
}