{
  "type": "Feature",
  "properties": {
    "addr:full":"505 Washington St Norwell MA 02061",
    "addr:housenumber":"505",
    "addr:postcode":"02061",
    "addr:street":"Washington St",
    "iso:country":"US",
    "sg:address":"505 Washington St",
    "sg:city":"Norwell",
    "sg:classifiers":[
        {
            "category":"Personal",
            "subcategory":"Beauty Salon",
            "type":"Services"
        },
        {
            "category":"Personal",
            "subcategory":"Nail Salon",
            "type":"Services"
        }
    ],
    "sg:phone":"+1 781 659 2957",
    "sg:postcode":"02061",
    "sg:province":"MA",
    "wof:name":"Perfect Nails",
    "wof:placetype":"venue"
},
  "geometry": {"coordinates":[-70.853329,42.15927],"type":"Point"}
}