{
  "type": "Feature",
  "properties": {
    "addr:full":"59 Brightwood St Chicopee MA 01020",
    "addr:housenumber":"59",
    "addr:postcode":"01020",
    "addr:street":"Brightwood St",
    "iso:country":"US",
    "sg:address":"59 Brightwood St",
    "sg:city":"Chicopee",
    "sg:classifiers":[
        {
            "category":"Building & Trades",
            "subcategory":"Plumbing",
            "type":"Services"
        }
    ],
    "sg:phone":"+1   ",
    "sg:postcode":"01020",
    "sg:province":"MA",
    "sg:tags":[
        "contractor"
    ],
    "wof:name":"Mark C Gadoury Plumbing",
    "wof:placetype":"venue"
},
  "geometry": {"coordinates":[-72.589388,42.166507],"type":"Point"}
}