{
  "type": "Feature",
  "properties": {
    "addr:full":"312 Burrage St Lunenburg MA 01462",
    "addr:housenumber":"312",
    "addr:postcode":"01462",
    "addr:street":"Burrage St",
    "iso:country":"US",
    "sg:address":"312 Burrage St",
    "sg:city":"Lunenburg",
    "sg:classifiers":[
        {
            "category":"Professional",
            "subcategory":"Business Services",
            "type":"Services"
        }
    ],
    "sg:phone":"+1 978 582 4331",
    "sg:postcode":"01462",
    "sg:province":"MA",
    "sg:tags":[
        "drafting"
    ],
    "wof:name":"Beyond Basics",
    "wof:placetype":"venue"
},
  "geometry": {"coordinates":[-71.685976,42.572696],"type":"Point"}
}