{
  "type": "Feature",
  "properties": {
    "addr:full": "149 North St Salem MA 01970",
    "addr:housenumber": "149",
    "addr:postcode": "01970",
    "addr:street": "North St",
    "iso:country": "US",
    "sg:address": "149 North St",
    "sg:city": "Salem",
    "sg:classifiers": [
      {
        "category": "Shopping",
        "subcategory": "Jewelry",
        "type": "Retail Goods"
      }
    ],
    "sg:phone": "+1 978 744 2646",
    "sg:postcode": "01970",
    "sg:province": "MA",
    "sg:tags": [
      "jeweler"
    ],
    "wof:name": "Salem Coin \u0026 Jewelry",
    "wof:placetype": "venue"
  },
  "geometry": {"coordinates":[-70.904247,42.528948],"type":"Point"}
}
