{
  "type": "Feature",
  "properties": {
    "iso:country":"US",
    "sg:address":"1550 Worcester Rd",
    "sg:city":"Framingham",
    "sg:classifiers":[
        {
            "category":"Manufacturing",
            "subcategory":"Printing",
            "type":"Manufacturing & Wholesale Goods"
        }
    ],
    "sg:phone":"+1 508 370 9915",
    "sg:postcode":"01702",
    "sg:province":"MA",
    "sg:tags":[
        "publisher",
        "software"
    ],
    "sg:website":"www.curapath.com",
    "wof:name":"Cura Path Systems Inc",
    "wof:placetype":"venue"
},
  "geometry": {"coordinates":[-71.4633,42.293874],"type":"Point"}
}