{
  "type": "Feature",
  "properties": {
    "addr:full": "232 Centre St Dorchester Ctr MA 02124",
    "addr:housenumber": "232",
    "addr:postcode": "02124",
    "addr:street": "Centre St",
    "iso:country": "US",
    "sg:address": "232 Centre St",
    "sg:city": "Dorchester Ctr",
    "sg:classifiers": [
      {
        "category": "Social Services",
        "subcategory": "Child Care",
        "type": "Services"
      }
    ],
    "sg:phone": "+1 617 474 1223",
    "sg:postcode": "02124",
    "sg:province": "MA",
    "wof:name": "Bartholomew Family Daycare",
    "wof:placetype": "venue"
  },
  "geometry": {"coordinates":[-71.062533,42.293563],"type":"Point"}
}
