{
  "type": "Feature",
  "properties": {
    "iso:country":"US",
    "sg:address":"232 Centre St",
    "sg:city":"Dorchester Ctr",
    "sg:classifiers":[
        {
            "category":"Social Services",
            "subcategory":"Child Care",
            "type":"Services"
        }
    ],
    "sg:phone":"+1 617 474 1223",
    "sg:postcode":"02124",
    "sg:province":"MA",
    "wof:name":"Bartholomew Family Daycare",
    "wof:placetype":"venue"
},
  "geometry": {"coordinates":[-71.062533,42.293563],"type":"Point"}
}