{
  "type": "Feature",
  "properties": {
    "addr:full":"45 Harvard St Brookline MA 02445",
    "addr:housenumber":"45",
    "addr:postcode":"02445",
    "addr:street":"Harvard St",
    "iso:country":"US",
    "sg:address":"45 Harvard St",
    "sg:city":"Brookline",
    "sg:classifiers":[
        {
            "category":"Retail",
            "subcategory":"Repair Shop",
            "type":"Services"
        }
    ],
    "sg:phone":"+1 617 232 8167",
    "sg:postcode":"02445",
    "sg:province":"MA",
    "sg:tags":[
        "television",
        "radio"
    ],
    "wof:name":"Beacon TV Sales & Svc Inc",
    "wof:placetype":"venue"
},
  "geometry": {"coordinates":[-71.11908,42.33439],"type":"Point"}
}