{
  "type": "Feature",
  "properties": {
    "addr:full": "30 Kevill Rd Lynn MA 01904",
    "addr:housenumber": "30",
    "addr:postcode": "01904",
    "addr:street": "Kevill Rd",
    "iso:country": "US",
    "sg:address": "30 Kevill Rd",
    "sg:city": "Lynn",
    "sg:classifiers": [
      {
        "category": "Freight",
        "type": "Transportation"
      }
    ],
    "sg:phone": "+1 781 598 1120",
    "sg:postcode": "01904",
    "sg:province": "MA",
    "sg:tags": [
      "courier"
    ],
    "wof:name": "Custom Delivery Svc",
    "wof:placetype": "venue"
  },
  "geometry": {"coordinates":[-70.9419,42.488014],"type":"Point"}
}
