{
  "type": "Feature",
  "properties": {
    "addr:full": "43 Pleasant St Westfield MA 01085",
    "addr:housenumber": "43",
    "addr:postcode": "01085",
    "addr:street": "Pleasant St",
    "iso:country": "US",
    "sg:address": "43 Pleasant St",
    "sg:city": "Westfield",
    "sg:classifiers": [
      {
        "category": "Manufacturing",
        "subcategory": "Buildings",
        "type": "Manufacturing \u0026 Wholesale Goods"
      },
      {
        "category": "Building \u0026 Trades",
        "subcategory": "Construction",
        "type": "Services"
      }
    ],
    "sg:phone": "+1 413 427 3494",
    "sg:postcode": "01085",
    "sg:province": "MA",
    "sg:tags": [
      "home",
      "builder",
      "contractor"
    ],
    "wof:name": "Home Improvements Unlimited",
    "wof:placetype": "venue"
  },
  "geometry": {"coordinates":[-72.752388,42.116161],"type":"Point"}
}
