{
  "type": "Feature",
  "properties": {
    "iso:country":"US",
    "sg:address":"43 Pleasant St",
    "sg:city":"Westfield",
    "sg:classifiers":[
        {
            "category":"Manufacturing",
            "subcategory":"Buildings",
            "type":"Manufacturing & Wholesale Goods"
        },
        {
            "category":"Building & Trades",
            "subcategory":"Construction",
            "type":"Services"
        }
    ],
    "sg:phone":"+1 413 427 3494",
    "sg:postcode":"01085",
    "sg:province":"MA",
    "sg:tags":[
        "home",
        "builder",
        "contractor"
    ],
    "wof:name":"Home Improvements Unlimited",
    "wof:placetype":"venue"
},
  "geometry": {"coordinates":[-72.752388,42.116161],"type":"Point"}
}