{
  "type": "Feature",
  "properties": {
    "iso:country":"US",
    "sg:address":"1 Fox Hill Rd",
    "sg:city":"Burlington",
    "sg:classifiers":[
        {
            "category":"Building & Trades",
            "subcategory":"Locksmith",
            "type":"Services"
        }
    ],
    "sg:phone":"+1 781 313 8002",
    "sg:postcode":"01803",
    "sg:province":"MA",
    "sg:tags":[
        "key"
    ],
    "wof:name":"Google Locksmith",
    "wof:placetype":"venue"
},
  "geometry": {"coordinates":[-71.19676200000001,42.517463],"type":"Point"}
}