{
  "type": "Feature",
  "properties": {
    "addr:full":"55 Cambridge Pkwy Cambridge MA 02142",
    "addr:housenumber":"55",
    "addr:postcode":"02142",
    "addr:street":"Cambridge Pkwy",
    "iso:country":"US",
    "sg:address":"55 Cambridge Pkwy",
    "sg:city":"Cambridge",
    "sg:classifiers":[
        {
            "category":"Professional",
            "subcategory":"Lawyer & Legal Services",
            "type":"Services"
        }
    ],
    "sg:phone":"+1 617 452 1600",
    "sg:postcode":"02142",
    "sg:province":"MA",
    "sg:website":"www.finnegan.com",
    "wof:name":"Finnegan Henderson",
    "wof:placetype":"venue"
},
  "geometry": {"coordinates":[-71.074898,42.366402],"type":"Point"}
}