{
  "type": "Feature",
  "properties": {
    "iso:country":"US",
    "sg:address":"26 Cummins Hwy Ste 1",
    "sg:city":"Roslindale",
    "sg:classifiers":[
        {
            "category":"Health Services",
            "subcategory":"Clinic",
            "type":"Services"
        }
    ],
    "sg:phone":"+1 617 469 8288",
    "sg:postcode":"02131",
    "sg:province":"MA",
    "sg:tags":[
        "medical"
    ],
    "sg:website":"www.thehealingwaysite.com",
    "wof:name":"The Healing Way",
    "wof:placetype":"venue"
},
  "geometry": {"coordinates":[-71.127037,42.285954],"type":"Point"}
}