{
  "type": "Feature",
  "properties": {
    "addr:full":"470 Wildwood Ave Ste 7 Woburn MA 01801",
    "addr:housenumber":"470",
    "addr:postcode":"01801",
    "addr:street":"Wildwood Ave Ste 7",
    "iso:country":"US",
    "sg:address":"470 Wildwood Ave Ste 7",
    "sg:city":"Woburn",
    "sg:classifiers":[
        {
            "category":"Personal",
            "type":"Services"
        }
    ],
    "sg:phone":"+1 781 939 5867",
    "sg:postcode":"01801",
    "sg:province":"MA",
    "sg:tags":[
        "party",
        "planning",
        "event"
    ],
    "wof:name":"Jump On In",
    "wof:placetype":"venue"
},
  "geometry": {"coordinates":[-71.140263,42.496604],"type":"Point"}
}