{
  "type": "Feature",
  "properties": {
    "iso:country":"US",
    "sg:address":"45 Main St",
    "sg:city":"Florence",
    "sg:classifiers":[
        {
            "category":"Health Services",
            "subcategory":"Chiropractor",
            "type":"Services"
        }
    ],
    "sg:phone":"+1 413 584 6226",
    "sg:postcode":"01062",
    "sg:province":"MA",
    "wof:name":"Wood Family Chiropractic",
    "wof:placetype":"venue"
},
  "geometry": {"coordinates":[-72.669448,42.335116],"type":"Point"}
}