{
  "type": "Feature",
  "properties": {
    "addr:full":"42 Kelton St Allston MA 02134",
    "addr:housenumber":"42",
    "addr:postcode":"02134",
    "addr:street":"Kelton St",
    "iso:country":"US",
    "sg:address":"42 Kelton St",
    "sg:city":"Allston",
    "sg:classifiers":[
        {
            "category":"Building & Trades",
            "subcategory":"Locksmith",
            "type":"Services"
        }
    ],
    "sg:phone":"+1 617 714 1229",
    "sg:postcode":"02134",
    "sg:province":"MA",
    "sg:tags":[
        "key"
    ],
    "wof:name":"Atlas Locksmith",
    "wof:placetype":"venue"
},
  "geometry": {"coordinates":[-71.139937,42.348626],"type":"Point"}
}