{
  "type": "Feature",
  "properties": {
    "iso:country":"US",
    "sg:address":"10 Lockwood Rd",
    "sg:city":"Wilmington",
    "sg:classifiers":[
        {
            "category":"Personal",
            "type":"Services"
        }
    ],
    "sg:phone":"+1 978 658 7053",
    "sg:postcode":"01887",
    "sg:province":"MA",
    "sg:tags":[
        "association"
    ],
    "wof:name":"TOPS",
    "wof:placetype":"venue"
},
  "geometry": {"coordinates":[-71.156386,42.580195],"type":"Point"}
}