{
  "type": "Feature",
  "properties": {
    "addr:full":"48 Maverick St East Boston MA 02128",
    "addr:housenumber":"48",
    "addr:postcode":"02128",
    "addr:street":"Maverick St",
    "iso:country":"US",
    "sg:address":"48 Maverick St",
    "sg:city":"East Boston",
    "sg:classifiers":[
        {
            "category":"Building & Trades",
            "subcategory":"Cleaning & Sanitation",
            "type":"Services"
        }
    ],
    "sg:phone":"+1 617 569 0592",
    "sg:postcode":"02128",
    "sg:province":"MA",
    "sg:tags":[
        "janitor"
    ],
    "wof:name":"Northeast Cleaning Svc",
    "wof:placetype":"venue"
},
  "geometry": {"coordinates":[-71.040949,42.371104],"type":"Point"}
}