{
  "type": "Feature",
  "properties": {
    "addr:full":"992 Bay St Springfield ME 01109",
    "addr:housenumber":"992",
    "addr:postcode":"01109",
    "addr:street":"Bay St",
    "iso:country":"US",
    "sg:address":"992 Bay St",
    "sg:city":"Springfield",
    "sg:classifiers":[
        {
            "category":"Retail",
            "subcategory":"Repair Shop",
            "type":"Services"
        }
    ],
    "sg:phone":"+1 413 736 3682",
    "sg:postcode":"01109",
    "sg:province":"ME",
    "sg:tags":[
        "valve"
    ],
    "sg:website":"www.ivicorp.net",
    "wof:name":"International Valve",
    "wof:placetype":"venue"
},
  "geometry": {"coordinates":[-72.550498,42.131548],"type":"Point"}
}