{
  "type": "Feature",
  "properties": {
    "addr:full":"615 School St Mansfield MA 02048",
    "addr:housenumber":"615",
    "addr:postcode":"02048",
    "addr:street":"School St",
    "iso:country":"US",
    "sg:address":"615 School St",
    "sg:city":"Mansfield",
    "sg:classifiers":[
        {
            "category":"Real Estate",
            "subcategory":"Real Estate Agent",
            "type":"Services"
        }
    ],
    "sg:phone":"+1 508 238 0003",
    "sg:postcode":"02048",
    "sg:province":"MA",
    "sg:tags":[
        "management"
    ],
    "wof:name":"Southeastern Property Mgmt Inc",
    "wof:placetype":"venue"
},
  "geometry": {"coordinates":[-71.237906,42.00951],"type":"Point"}
}