{
  "type": "Feature",
  "properties": {
    "iso:country":"US",
    "sg:address":"2 Magnolia Ave",
    "sg:city":"Gloucester",
    "sg:classifiers":[
        {
            "category":"Health Services",
            "subcategory":"Health Practitioner",
            "type":"Services"
        }
    ],
    "sg:phone":"+1 978 525 2255",
    "sg:postcode":"01930",
    "sg:province":"MA",
    "sg:website":"www.atlanticacupuncture.com",
    "wof:name":"Eli Jacobe Acupuncture",
    "wof:placetype":"venue"
},
  "geometry": {"coordinates":[-70.714868,42.577144],"type":"Point"}
}