{
  "type": "Feature",
  "properties": {
    "iso:country":"US",
    "sg:address":"5 Causeway St",
    "sg:city":"Medfield",
    "sg:classifiers":[
        {
            "category":"Wholesale",
            "subcategory":"Stationery",
            "type":"Manufacturing & Wholesale Goods"
        }
    ],
    "sg:phone":"+1 508 359 1999",
    "sg:postcode":"02052",
    "sg:province":"MA",
    "sg:tags":[
        "product",
        "paper"
    ],
    "wof:name":"Paper Moon",
    "wof:placetype":"venue"
},
  "geometry": {"coordinates":[-71.312083,42.184415],"type":"Point"}
}