{
  "type": "Feature",
  "properties": {
    "addr:full": "5 Causeway St Medfield MA 02052",
    "addr:housenumber": "5",
    "addr:postcode": "02052",
    "addr:street": "Causeway St",
    "iso:country": "US",
    "sg:address": "5 Causeway St",
    "sg:city": "Medfield",
    "sg:classifiers": [
      {
        "category": "Wholesale",
        "subcategory": "Stationery",
        "type": "Manufacturing \u0026 Wholesale Goods"
      }
    ],
    "sg:phone": "+1 508 359 1999",
    "sg:postcode": "02052",
    "sg:province": "MA",
    "sg:tags": [
      "product",
      "paper"
    ],
    "wof:name": "Paper Moon",
    "wof:placetype": "venue"
  },
  "geometry": {"coordinates":[-71.312083,42.184415],"type":"Point"}
}
