{
  "type": "Feature",
  "properties": {
    "iso:country":"US",
    "sg:address":"950 Watertown St",
    "sg:city":"West Newton",
    "sg:classifiers":[
        {
            "category":"Wholesale",
            "subcategory":"Groceries",
            "type":"Manufacturing & Wholesale Goods"
        }
    ],
    "sg:phone":"+1 617 559 0018",
    "sg:postcode":"02465",
    "sg:province":"MA",
    "sg:tags":[
        "food",
        "product"
    ],
    "wof:name":"Olam Foods",
    "wof:placetype":"venue"
},
  "geometry": {"coordinates":[-71.224097,42.350218],"type":"Point"}
}