{
  "type": "Feature",
  "properties": {
    "addr:full":"270 Water St Quincy MA 02169",
    "addr:housenumber":"270",
    "addr:postcode":"02169",
    "addr:street":"Water St",
    "iso:country":"US",
    "sg:address":"270 Water St",
    "sg:city":"Quincy",
    "sg:classifiers":[
        {
            "category":"Personal",
            "subcategory":"Beauty Salon",
            "type":"Services"
        }
    ],
    "sg:phone":"+1 617 773 1220",
    "sg:postcode":"02169",
    "sg:province":"MA",
    "sg:tags":[
        "hair",
        "stylist"
    ],
    "wof:name":"Hair Sense",
    "wof:placetype":"venue"
},
  "geometry": {"coordinates":[-71.008869,42.240897],"type":"Point"}
}