{
  "type": "Feature",
  "properties": {
    "addr:full":"11 Stoughton St Dorchester MA 02125",
    "addr:housenumber":"11",
    "addr:postcode":"02125",
    "addr:street":"Stoughton St",
    "iso:country":"US",
    "sg:address":"11 Stoughton St",
    "sg:city":"Dorchester",
    "sg:classifiers":[
        {
            "category":"Wholesale",
            "subcategory":"Painting Supplies",
            "type":"Manufacturing & Wholesale Goods"
        },
        {
            "category":"Building & Trades",
            "subcategory":"Construction",
            "type":"Services"
        }
    ],
    "sg:phone":"+1 617 282 1845",
    "sg:postcode":"02125",
    "sg:province":"MA",
    "sg:tags":[
        "altering",
        "paint",
        "remodeling",
        "contractor"
    ],
    "wof:name":"New Looks Paint Service",
    "wof:placetype":"venue"
},
  "geometry": {"coordinates":[-71.064657,42.316841],"type":"Point"}
}