{
  "type": "Feature",
  "properties": {
    "addr:full": "230 Cotuit Rd Marstons Mills MA 02648",
    "addr:housenumber": "230",
    "addr:postcode": "02648",
    "addr:street": "Cotuit Rd",
    "iso:country": "US",
    "sg:address": "230 Cotuit Rd",
    "sg:city": "Marstons Mills",
    "sg:classifiers": [
      {
        "category": "Social Services",
        "type": "Services"
      }
    ],
    "sg:phone": "+1 508 428 9800",
    "sg:postcode": "02648",
    "sg:province": "MA",
    "sg:tags": [
      "worker"
    ],
    "wof:name": "Carol G Fortune Licsw",
    "wof:placetype": "venue"
  },
  "geometry": {"coordinates":[-70.411361,41.656851],"type":"Point"}
}
