{
  "type": "Feature",
  "properties": {
    "addr:full":"303 Beale St Quincy MA 02170",
    "addr:housenumber":"303",
    "addr:postcode":"02170",
    "addr:street":"Beale St",
    "iso:country":"US",
    "sg:address":"303 Beale St",
    "sg:city":"Quincy",
    "sg:classifiers":[
        {
            "category":"Professional",
            "type":"Services"
        }
    ],
    "sg:phone":"+1   ",
    "sg:postcode":"02170",
    "sg:province":"MA",
    "wof:name":"McMillen Marine Service",
    "wof:placetype":"venue"
},
  "geometry": {"coordinates":[-71.02786999999999,42.26068],"type":"Point"}
}