{
  "type": "Feature",
  "properties": {
    "iso:country":"US",
    "sg:address":"14 Arrow Rd",
    "sg:city":"Norton",
    "sg:classifiers":[
        {
            "category":"Place Of Worship",
            "type":"Public Place"
        }
    ],
    "sg:phone":"+1 508 285 2454",
    "sg:postcode":"02766",
    "sg:province":"MA",
    "sg:tags":[
        "church"
    ],
    "wof:name":"Berlo Dma & Chr",
    "wof:placetype":"venue"
},
  "geometry": {"coordinates":[-71.18716000000001,41.983436],"type":"Point"}
}