{
  "type": "Feature",
  "properties": {
    "addr:full":"140 Malden St Malden MA 02148",
    "addr:housenumber":"140",
    "addr:postcode":"02148",
    "addr:street":"Malden St",
    "iso:country":"US",
    "sg:address":"140 Malden St",
    "sg:city":"Malden",
    "sg:classifiers":[
        {
            "category":"Retail",
            "subcategory":"Animal Services",
            "type":"Services"
        }
    ],
    "sg:phone":"+1 781 321 5784",
    "sg:postcode":"02148",
    "sg:province":"MA",
    "sg:tags":[
        "pet",
        "grooming",
        "washing"
    ],
    "wof:name":"Happy Paws Pet Sitting",
    "wof:placetype":"venue"
},
  "geometry": {"coordinates":[-71.084388,42.419463],"type":"Point"}
}