{
  "type": "Feature",
  "properties": {
    "addr:full": "75 West St Medfield MA 02052",
    "addr:housenumber": "75",
    "addr:postcode": "02052",
    "addr:street": "West St",
    "iso:country": "US",
    "ovtr:label": "Wills Hardware, 75 West St Medfield MA US",
    "ovtr:similarity": 3.9680540561676025,
    "sg:address": "75 West St",
    "sg:city": "Medfield",
    "sg:classifiers": [
      {
        "category": "Home \u0026 Garden",
        "subcategory": "Building Materials",
        "type": "Retail Goods"
      }
    ],
    "sg:phone": "+1 508 359 4433",
    "sg:postcode": "02052",
    "sg:province": "MA",
    "sg:tags": [
      "paint"
    ],
    "wof:name": "Wills Hardware Inc",
    "wof:placetype": "venue"
  },
  "geometry": {"coordinates":[-71.323929,42.192299],"type":"Point"}
}
