{
  "type": "Feature",
  "properties": {
    "addr:full":"75 West St Medfield MA 02052",
    "addr:housenumber":"75",
    "addr:postcode":"02052",
    "addr:street":"West St",
    "iso:country":"US",
    "sg:address":"75 West St",
    "sg:city":"Medfield",
    "sg:classifiers":[
        {
            "category":"Home & Garden",
            "subcategory":"Building Materials",
            "type":"Retail Goods"
        }
    ],
    "sg:phone":"+1 508 359 4433",
    "sg:postcode":"02052",
    "sg:province":"MA",
    "sg:tags":[
        "paint"
    ],
    "wof:name":"Wills Hardware Inc",
    "wof:placetype":"venue"
},
  "geometry": {"coordinates":[-71.32392900000001,42.192299],"type":"Point"}
}