{
  "type": "Feature",
  "properties": {
    "iso:country":"US",
    "sg:address":"56 Havre St",
    "sg:city":"Boston",
    "sg:classifiers":[
        {
            "category":"Animal Shelter",
            "type":"Public Place"
        }
    ],
    "sg:phone":"+1 617 567 5926",
    "sg:postcode":"02128",
    "sg:province":"MA",
    "wof:name":"The Most Holy Redeemer Church",
    "wof:placetype":"venue"
},
  "geometry": {"coordinates":[-71.03998199999999,42.371087],"type":"Point"}
}