{
  "type": "Feature",
  "properties": {
    "addr:full":"24 Hartwell Ave Lexington MA 02421",
    "addr:housenumber":"24",
    "addr:postcode":"02421",
    "addr:street":"Hartwell Ave",
    "iso:country":"US",
    "sg:address":"24 Hartwell Ave",
    "sg:city":"Lexington",
    "sg:classifiers":[
        {
            "category":"Professional",
            "subcategory":"Management & Consulting",
            "type":"Services"
        }
    ],
    "sg:phone":"+1 781 676 6900",
    "sg:postcode":"02421",
    "sg:province":"MA",
    "sg:tags":[
        "consultant",
        "business"
    ],
    "sg:website":"www.workingnights.com",
    "wof:name":"Circadian Technologies Inc",
    "wof:placetype":"venue"
},
  "geometry": {"coordinates":[-71.25433099999999,42.474488],"type":"Point"}
}