{
  "type": "Feature",
  "properties": {
    "iso:country":"US",
    "sg:address":"231 Geneva Avenue",
    "sg:city":"Dorchester",
    "sg:classifiers":[
        {
            "category":"Real Estate",
            "subcategory":"Real Estate Operator",
            "type":"Services"
        }
    ],
    "sg:phone":"+1 617 282 8461",
    "sg:postcode":"02121",
    "sg:province":"MA",
    "sg:tags":[
        "apartment"
    ],
    "wof:name":"Geneva Apartments",
    "wof:placetype":"venue"
},
  "geometry": {"coordinates":[-71.07332100000001,42.3047],"type":"Point"}
}