{
  "type": "Feature",
  "properties": {
    "addr:full": "4 Goelette Dr Plymouth MA 02360",
    "addr:housenumber": "4",
    "addr:postcode": "02360",
    "addr:street": "Goelette Dr",
    "iso:country": "US",
    "sg:address": "4 Goelette Dr",
    "sg:city": "Plymouth",
    "sg:classifiers": [
      {
        "category": "Professional",
        "subcategory": "Advertising",
        "type": "Services"
      }
    ],
    "sg:phone": "+1 508 747 5822",
    "sg:postcode": "02360",
    "sg:province": "MA",
    "sg:website": "www.myprintit.com",
    "wof:name": "MYPRINTIT.COM",
    "wof:placetype": "venue"
  },
  "geometry": {"coordinates":[-70.535344,41.879684],"type":"Point"}
}
