{
  "type": "Feature",
  "properties": {
    "iso:country":"US",
    "sg:address":"15 Park Ave",
    "sg:city":"Hull",
    "sg:classifiers":[
        {
            "category":"Real Estate",
            "subcategory":"Real Estate Agent",
            "type":"Services"
        }
    ],
    "sg:phone":"+1 781 925 5063",
    "sg:postcode":"02045",
    "sg:province":"MA",
    "wof:name":"Paragon Park Realty",
    "wof:placetype":"venue"
},
  "geometry": {"coordinates":[-70.853297,42.267674],"type":"Point"}
}