{
  "type": "Feature",
  "properties": {
    "iso:country":"US",
    "sg:address":"11 Russell St",
    "sg:city":"Plymouth",
    "sg:classifiers":[
        {
            "category":"Professional",
            "subcategory":"Lawyer & Legal Services",
            "type":"Services"
        }
    ],
    "sg:phone":"+1 508 747 7333",
    "sg:postcode":"02360",
    "sg:province":"MA",
    "wof:name":"Sheehan Lisa M Atty",
    "wof:placetype":"venue"
},
  "geometry": {"coordinates":[-70.66680100000001,41.957298],"type":"Point"}
}