{
  "type": "Feature",
  "properties": {
    "iso:country":"US",
    "sg:address":"1470 Main St",
    "sg:city":"Chatham",
    "sg:classifiers":[
        {
            "category":"Travel",
            "subcategory":"Hotels & Motels",
            "type":"Entertainment"
        }
    ],
    "sg:phone":"+1 508 945 1976",
    "sg:postcode":"02633",
    "sg:province":"MA",
    "sg:tags":[
        "cottage",
        "cabin"
    ],
    "wof:name":"Eider Duck Cottages",
    "wof:placetype":"venue"
},
  "geometry": {"coordinates":[-69.988193,41.683017],"type":"Point"}
}