{
  "type": "Feature",
  "properties": {
    "addr:full": "90 Lyndhurst St Dorchester Ctr MA 02124",
    "addr:housenumber": "90",
    "addr:postcode": "02124",
    "addr:street": "Lyndhurst St",
    "iso:country": "US",
    "sg:address": "90 Lyndhurst St",
    "sg:city": "Dorchester Ctr",
    "sg:classifiers": [
      {
        "category": "Banks \u0026 Credit Unions",
        "subcategory": "Investment Brokerage",
        "type": "Services"
      }
    ],
    "sg:phone": "+1 617 282 5053",
    "sg:postcode": "02124",
    "sg:province": "MA",
    "sg:tags": [
      "security"
    ],
    "wof:name": "Global Investment Strategies",
    "wof:placetype": "venue"
  },
  "geometry": {"coordinates":[-71.071372,42.292408],"type":"Point"}
}
