{
  "type": "Feature",
  "properties": {
    "iso:country":"US",
    "sg:address":"90 Lyndhurst St",
    "sg:city":"Dorchester Ctr",
    "sg:classifiers":[
        {
            "category":"Banks & Credit Unions",
            "subcategory":"Investment Brokerage",
            "type":"Services"
        }
    ],
    "sg:phone":"+1 617 282 5053",
    "sg:postcode":"02124",
    "sg:province":"MA",
    "sg:tags":[
        "security"
    ],
    "wof:name":"Global Investment Strategies",
    "wof:placetype":"venue"
},
  "geometry": {"coordinates":[-71.071372,42.292408],"type":"Point"}
}