{
  "type": "Feature",
  "properties": {
    "iso:country":"US",
    "sg:address":"36 Roanoke Ave",
    "sg:city":"West Springfield",
    "sg:classifiers":[
        {
            "category":"Manufacturing",
            "subcategory":"Metals",
            "type":"Manufacturing & Wholesale Goods"
        }
    ],
    "sg:phone":"+1 413 737 8808",
    "sg:postcode":"01089",
    "sg:province":"MA",
    "sg:tags":[
        "production",
        "grinding"
    ],
    "wof:name":"Sharp Precision Grinding Co",
    "wof:placetype":"venue"
},
  "geometry": {"coordinates":[-72.62754700000001,42.094732],"type":"Point"}
}