{
  "type": "Feature",
  "properties": {
    "iso:country":"US",
    "sg:address":"1 Alton Dr",
    "sg:city":"Dudley",
    "sg:classifiers":[
        {
            "category":"Home & Garden",
            "subcategory":"Household Appliances",
            "type":"Retail Goods"
        }
    ],
    "sg:phone":"+1   ",
    "sg:postcode":"01571",
    "sg:province":"MA",
    "wof:name":"Dudley Sewing & Music",
    "wof:placetype":"venue"
},
  "geometry": {"coordinates":[-71.911863,42.041126],"type":"Point"}
}