{
  "type": "Feature",
  "properties": {
    "addr:full": "1 Alton Dr Dudley MA 01571",
    "addr:housenumber": "1",
    "addr:postcode": "01571",
    "addr:street": "Alton Dr",
    "iso:country": "US",
    "sg:address": "1 Alton Dr",
    "sg:city": "Dudley",
    "sg:classifiers": [
      {
        "category": "Home \u0026 Garden",
        "subcategory": "Household Appliances",
        "type": "Retail Goods"
      }
    ],
    "sg:phone": "+1   ",
    "sg:postcode": "01571",
    "sg:province": "MA",
    "wof:name": "Dudley Sewing \u0026 Music",
    "wof:placetype": "venue"
  },
  "geometry": {"coordinates":[-71.911863,42.041126],"type":"Point"}
}
