{
  "type": "Feature",
  "properties": {
    "iso:country":"US",
    "sg:address":"158 E Union St",
    "sg:city":"Ashland",
    "sg:classifiers":[
        {
            "category":"Building & Trades",
            "subcategory":"Landscaping Services",
            "type":"Services"
        }
    ],
    "sg:phone":"+1 508 881 3187",
    "sg:postcode":"01721",
    "sg:province":"MA",
    "sg:tags":[
        "landscape",
        "contractor"
    ],
    "wof:name":"Landscape Design",
    "wof:placetype":"venue"
},
  "geometry": {"coordinates":[-71.43592599999999,42.261111],"type":"Point"}
}