{
  "type": "Feature",
  "properties": {
    "addr:full":"10 Seaboard Lane Hyannis MA 02601",
    "addr:housenumber":"10",
    "addr:postcode":"02601",
    "addr:street":"Seaboard Lane",
    "iso:country":"US",
    "sg:address":"10 Seaboard Lane",
    "sg:city":"Hyannis",
    "sg:classifiers":[
        {
            "category":"Fast Food",
            "type":"Food & Drink"
        },
        {
            "category":"Food & Beverages",
            "subcategory":"Bakery",
            "type":"Retail Goods"
        },
        {
            "category":"Restaurant",
            "type":"Food & Drink"
        }
    ],
    "sg:phone":"+1 508 771 3330",
    "sg:postcode":"02601",
    "sg:province":"MA",
    "sg:tags":[
        "burger",
        "sandwich",
        "pizza"
    ],
    "sg:website":"bnbpizza.com",
    "wof:name":"B & B Pizza",
    "wof:placetype":"venue"
},
  "geometry": {"coordinates":[-70.31659999999999,41.6521],"type":"Point"}
}