{
  "type": "Feature",
  "properties": {
    "addr:full": "10 Seaboard Lane Hyannis MA 02601",
    "addr:housenumber": "10",
    "addr:postcode": "02601",
    "addr:street": "Seaboard Lane",
    "iso:country": "US",
    "ovtr:label": "B \u0026 B Pizza, 10 Seaboard Ln Hyannis MA US",
    "ovtr:similarity": 3.4055991172790527,
    "sg:address": "10 Seaboard Lane",
    "sg:city": "Hyannis",
    "sg:classifiers": [
      {
        "category": "Fast Food",
        "type": "Food \u0026 Drink"
      },
      {
        "category": "Food \u0026 Beverages",
        "subcategory": "Bakery",
        "type": "Retail Goods"
      },
      {
        "category": "Restaurant",
        "type": "Food \u0026 Drink"
      }
    ],
    "sg:phone": "+1 508 771 3330",
    "sg:postcode": "02601",
    "sg:province": "MA",
    "sg:tags": [
      "burger",
      "sandwich",
      "pizza"
    ],
    "sg:website": "bnbpizza.com",
    "wof:name": "B \u0026 B Pizza",
    "wof:placetype": "venue"
  },
  "geometry": {"coordinates":[-70.3166,41.6521],"type":"Point"}
}
