{
  "type": "Feature",
  "properties": {
    "addr:full": "209 N Main St Andover MA 01810",
    "addr:housenumber": "209",
    "addr:postcode": "01810",
    "addr:street": "N Main St",
    "iso:country": "US",
    "sg:address": "209 N Main St",
    "sg:city": "Andover",
    "sg:classifiers": [
      {
        "category": "Utilities",
        "subcategory": "Mobile Phone",
        "type": "Services"
      },
      {
        "category": "Shopping",
        "subcategory": "Mobile Phones",
        "type": "Retail Goods"
      },
      {
        "category": "Utilities",
        "subcategory": "Telephone",
        "type": "Services"
      },
      {
        "category": "Professional",
        "subcategory": "Computer Services",
        "type": "Services"
      }
    ],
    "sg:phone": "+1 978 475 4911",
    "sg:postcode": "01810",
    "sg:province": "MA",
    "sg:tags": [
      "telecommunication",
      "supply",
      "communication",
      "system",
      "wireless",
      "equipment",
      "cellular"
    ],
    "sg:website": "http://clickserve.dartsearch.net/link/click?lid=43000000308049899",
    "wof:name": "T-Mobile",
    "wof:placetype": "venue"
  },
  "geometry": {"coordinates":[-71.145447,42.663887],"type":"Point"}
}
