{
  "type": "Feature",
  "properties": {
    "addr:full": "10 Walden St Concord MA 01742",
    "addr:housenumber": "10",
    "addr:postcode": "01742",
    "addr:street": "Walden St",
    "iso:country": "US",
    "sg:address": "10 Walden St",
    "sg:city": "Concord",
    "sg:classifiers": [
      {
        "category": "Arts \u0026 Performance",
        "subcategory": "Art Gallery",
        "type": "Entertainment"
      }
    ],
    "sg:phone": "+1 978 287 4800",
    "sg:postcode": "01742",
    "sg:province": "MA",
    "sg:tags": [
      "consultant",
      "galleries"
    ],
    "sg:website": "http://www.concordmousetrap.com",
    "wof:name": "The Concord Mouse Trap",
    "wof:placetype": "venue"
  },
  "geometry": {"coordinates":[-71.350152,42.459693],"type":"Point"}
}
