{
  "type": "Feature",
  "properties": {
    "addr:full": "23 Oregon Rd Ludlow MA 01056",
    "addr:housenumber": "23",
    "addr:postcode": "01056",
    "addr:street": "Oregon Rd",
    "iso:country": "US",
    "sg:address": "23 Oregon Rd",
    "sg:city": "Ludlow",
    "sg:classifiers": [
      {
        "category": "Building \u0026 Trades",
        "subcategory": "Plumbing",
        "type": "Services"
      }
    ],
    "sg:phone": "+1 413 547 2970",
    "sg:postcode": "01056",
    "sg:province": "MA",
    "sg:tags": [
      "plumbing",
      "contractor"
    ],
    "wof:name": "Biermann Plumbing \u0026 Heating",
    "wof:placetype": "venue"
  },
  "geometry": {"coordinates":[-72.518347,42.20211],"type":"Point"}
}
