{
  "type": "Feature",
  "properties": {
    "iso:country":"US",
    "sg:address":"23 Oregon Rd",
    "sg:city":"Ludlow",
    "sg:classifiers":[
        {
            "category":"Building & Trades",
            "subcategory":"Plumbing",
            "type":"Services"
        }
    ],
    "sg:phone":"+1 413 547 2970",
    "sg:postcode":"01056",
    "sg:province":"MA",
    "sg:tags":[
        "plumbing",
        "contractor"
    ],
    "wof:name":"Biermann Plumbing & Heating",
    "wof:placetype":"venue"
},
  "geometry": {"coordinates":[-72.51834700000001,42.20211],"type":"Point"}
}