{
  "type": "Feature",
  "properties": {
    "addr:full": "341 June St Worcester MA 01602",
    "addr:housenumber": "341",
    "addr:postcode": "01602",
    "addr:street": "June St",
    "iso:country": "US",
    "sg:address": "341 June St",
    "sg:city": "Worcester",
    "sg:classifiers": [
      {
        "category": "Organizations",
        "subcategory": "Religious Organization",
        "type": "Services"
      }
    ],
    "sg:phone": "+1 508 799 4031",
    "sg:postcode": "01602",
    "sg:province": "MA",
    "sg:tags": [
      "church"
    ],
    "wof:name": "St Charles Borromeo Rectory",
    "wof:placetype": "venue"
  },
  "geometry": {"coordinates":[-71.845942,42.260484],"type":"Point"}
}
