{
  "type": "Feature",
  "properties": {
    "iso:country":"US",
    "sg:address":"31 Hastings St",
    "sg:city":"Mendon",
    "sg:classifiers":[
        {
            "category":"Utilities",
            "subcategory":"Telephone",
            "type":"Services"
        }
    ],
    "sg:phone":"+1 508 478 1416",
    "sg:postcode":"01756",
    "sg:province":"MA",
    "sg:tags":[
        "telecommunication"
    ],
    "wof:name":"Interconnx Inc",
    "wof:placetype":"venue"
},
  "geometry": {"coordinates":[-71.55734,42.104555],"type":"Point"}
}