{
  "type": "Feature",
  "properties": {
    "addr:full": "458 S Main St Webster MA 01570",
    "addr:housenumber": "458",
    "addr:postcode": "01570",
    "addr:street": "S Main St",
    "iso:country": "US",
    "sg:address": "458 S Main St",
    "sg:city": "Webster",
    "sg:classifiers": [
      {
        "category": "Shopping",
        "subcategory": "Used Merchandise",
        "type": "Retail Goods"
      }
    ],
    "sg:phone": "+1 508 943 2320",
    "sg:postcode": "01570",
    "sg:province": "MA",
    "sg:tags": [
      "shop",
      "thrift"
    ],
    "wof:name": "Closet Classics",
    "wof:placetype": "venue"
  },
  "geometry": {"coordinates":[-71.879827,42.050329],"type":"Point"}
}
