{
  "type": "Feature",
  "properties": {
    "addr:full":"1 Bowdoin St Boston MA 02114",
    "addr:housenumber":"1",
    "addr:postcode":"02114",
    "addr:street":"Bowdoin St",
    "iso:country":"US",
    "sg:address":"1 Bowdoin St",
    "sg:city":"Boston",
    "sg:classifiers":[
        {
            "category":"Professional",
            "subcategory":"Lawyer & Legal Services",
            "type":"Services"
        }
    ],
    "sg:phone":"+1 617 747 7550",
    "sg:postcode":"02114",
    "sg:province":"MA",
    "sg:tags":[
        "attorney"
    ],
    "wof:name":"Reece & Assoc",
    "wof:placetype":"venue"
},
  "geometry": {"coordinates":[-71.06287399999999,42.359483],"type":"Point"}
}