{
  "type": "Feature",
  "properties": {
    "iso:country":"US",
    "sg:address":"546 E Broadway 1st Floor",
    "sg:city":"Boston",
    "sg:classifiers":[
        {
            "category":"Shopping",
            "subcategory":"Computers & Home Electronics",
            "type":"Retail Goods"
        }
    ],
    "sg:phone":"+1 617 268 0002",
    "sg:postcode":"02127",
    "sg:province":"MA",
    "sg:tags":[
        "installation",
        "theatre"
    ],
    "sg:website":"www.blackdiamondllc.com",
    "wof:name":"Black Diamond, LLC",
    "wof:placetype":"venue"
},
  "geometry": {"coordinates":[-71.0424,42.3359],"type":"Point"}
}