{
  "type": "Feature",
  "properties": {
    "addr:full": "546 E Broadway 1st Floor Boston MA 02127",
    "addr:housenumber": "546;1st floor",
    "addr:postcode": "02127",
    "addr:street": "E Broadway",
    "iso:country": "US",
    "sg:address": "546 E Broadway 1st Floor",
    "sg:city": "Boston",
    "sg:classifiers": [
      {
        "category": "Shopping",
        "subcategory": "Computers \u0026 Home Electronics",
        "type": "Retail Goods"
      }
    ],
    "sg:phone": "+1 617 268 0002",
    "sg:postcode": "02127",
    "sg:province": "MA",
    "sg:tags": [
      "installation",
      "theatre"
    ],
    "sg:website": "www.blackdiamondllc.com",
    "wof:name": "Black Diamond, LLC",
    "wof:placetype": "venue"
  },
  "geometry": {"coordinates":[-71.0424,42.3359],"type":"Point"}
}
