{
  "type": "Feature",
  "properties": {
    "addr:full":"25 Market St Swansea MA 02777",
    "addr:housenumber":"25",
    "addr:postcode":"02777",
    "addr:street":"Market St",
    "iso:country":"US",
    "sg:address":"25 Market St",
    "sg:city":"Swansea",
    "sg:classifiers":[
        {
            "category":"Restaurant",
            "type":"Food & Drink"
        }
    ],
    "sg:menulink":"http://www.allmenus.com/ma/swansea/84582-dominos-pizza/menu/",
    "sg:phone":"+1 508 379 0200",
    "sg:postcode":"02777",
    "sg:province":"MA",
    "sg:tags":[
        "american",
        "wing",
        "pizza"
    ],
    "wof:name":"Domino's Pizza",
    "wof:placetype":"venue"
},
  "geometry": {"coordinates":[-71.265775,41.768938],"type":"Point"}
}