{
  "type": "Feature",
  "properties": {
    "addr:full": "125 Canal St Ste 7 Salem MA 01970",
    "addr:housenumber": "125",
    "addr:postcode": "01970",
    "addr:street": "Canal St Ste 7",
    "iso:country": "US",
    "sg:address": "125 Canal St Ste 7",
    "sg:city": "Salem",
    "sg:classifiers": [
      {
        "category": "Banks \u0026 Credit Unions",
        "subcategory": "Bank",
        "type": "Services"
      }
    ],
    "sg:phone": "+1 978 740 6634",
    "sg:postcode": "01970",
    "sg:province": "MA",
    "wof:name": "Danversbank",
    "wof:placetype": "venue"
  },
  "geometry": {"coordinates":[-70.896056,42.509268],"type":"Point"}
}
