{
  "type": "Feature",
  "properties": {
    "iso:country":"US",
    "sg:address":"2440 Boston Rd",
    "sg:city":"Wilbraham",
    "sg:classifiers":[
        {
            "category":"Banks & Credit Unions",
            "subcategory":"Investment Brokerage",
            "type":"Services"
        }
    ],
    "sg:phone":"+1 413 596 8803",
    "sg:postcode":"01095",
    "sg:province":"MA",
    "sg:tags":[
        "consultant",
        "planning",
        "financial"
    ],
    "wof:name":"Havican Wealth Strategies",
    "wof:placetype":"venue"
},
  "geometry": {"coordinates":[-72.44537,42.148976],"type":"Point"}
}