{
  "type": "Feature",
  "properties": {
    "addr:full": "161 Johnson St Somerset MA 02726",
    "addr:housenumber": "161",
    "addr:postcode": "02726",
    "addr:street": "Johnson St",
    "iso:country": "US",
    "sg:address": "161 Johnson St",
    "sg:city": "Somerset",
    "sg:classifiers": [
      {
        "category": "Health Services",
        "subcategory": "Doctor",
        "type": "Services"
      }
    ],
    "sg:phone": "+1 508 679 3825",
    "sg:postcode": "02726",
    "sg:province": "MA",
    "sg:tags": [
      "physician",
      "surgeon"
    ],
    "wof:name": "Ruth M Miller MD",
    "wof:placetype": "venue"
  },
  "geometry": {"coordinates":[-71.145264,41.73994],"type":"Point"}
}
