{
  "type": "Feature",
  "properties": {
    "iso:country":"US",
    "sg:address":"10 Mudge Way",
    "sg:city":"Bedford",
    "sg:classifiers":[
        {
            "category":"Government",
            "subcategory":"Office",
            "type":"Public Place"
        }
    ],
    "sg:phone":"+1 781 275 0046",
    "sg:postcode":"01730",
    "sg:province":"MA",
    "sg:tags":[
        "city",
        "taxation"
    ],
    "wof:name":"Bedford Town Assessor",
    "wof:placetype":"venue"
},
  "geometry": {"coordinates":[-71.281622,42.49204],"type":"Point"}
}