{
  "type": "Feature",
  "properties": {
    "addr:full": "190 State Rd Westport MA 02790",
    "addr:housenumber": "190",
    "addr:postcode": "02790",
    "addr:street": "State Rd",
    "iso:country": "US",
    "sg:address": "190 State Rd",
    "sg:city": "Westport",
    "sg:classifiers": [
      {
        "category": "Utilities",
        "subcategory": "Refuse",
        "type": "Services"
      },
      {
        "category": "Utilities",
        "type": "Services"
      }
    ],
    "sg:phone": "+1 508 673 0521",
    "sg:postcode": "02790",
    "sg:province": "MA",
    "sg:tags": [
      "collection",
      "garbage"
    ],
    "wof:name": "Cleanway Disposal \u0026 Recycling",
    "wof:placetype": "venue"
  },
  "geometry": {"coordinates":[-71.107572,41.674787],"type":"Point"}
}
