{
  "type": "Feature",
  "properties": {
    "iso:country":"US",
    "sg:address":"115 Southworth St",
    "sg:city":"West Springfield",
    "sg:classifiers":[
        {
            "category":"Education",
            "subcategory":"School",
            "type":"Public Place"
        }
    ],
    "sg:phone":"+1 413 263 3318",
    "sg:postcode":"01089",
    "sg:province":"MA",
    "wof:name":"Coburn Elementary School",
    "wof:placetype":"venue"
},
  "geometry": {"coordinates":[-72.622676,42.107886],"type":"Point"}
}