{
  "type": "Feature",
  "properties": {
    "addr:full": "115 Southworth St West Springfield MA 01089",
    "addr:housenumber": "115",
    "addr:postcode": "01089",
    "addr:street": "Southworth St",
    "iso:country": "US",
    "ovtr:label": "Coburn Elementary School, 115 Southworth St West Springfield MA US",
    "ovtr:similarity": 2.6138899326324463,
    "sg:address": "115 Southworth St",
    "sg:city": "West Springfield",
    "sg:classifiers": [
      {
        "category": "Education",
        "subcategory": "School",
        "type": "Public Place"
      }
    ],
    "sg:phone": "+1 413 263 3318",
    "sg:postcode": "01089",
    "sg:province": "MA",
    "wof:name": "Coburn Elementary School",
    "wof:placetype": "venue"
  },
  "geometry": {"coordinates":[-72.622676,42.107886],"type":"Point"}
}
