{
  "type": "Feature",
  "properties": {
    "iso:country":"US",
    "sg:address":"256 Commercial St",
    "sg:city":"Provincetown",
    "sg:classifiers":[
        {
            "category":"Shopping",
            "subcategory":"Gifts & Souvenirs",
            "type":"Retail Goods"
        }
    ],
    "sg:phone":"+1 508 487 6323",
    "sg:postcode":"02657",
    "sg:province":"MA",
    "wof:name":"Eclectiques",
    "wof:placetype":"venue"
},
  "geometry": {"coordinates":[-70.187164,42.051139],"type":"Point"}
}