{
  "type": "Feature",
  "properties": {
    "iso:country":"US",
    "sg:address":"220 Broadway Fl 1",
    "sg:city":"Methuen",
    "sg:classifiers":[
        {
            "category":"Personal",
            "subcategory":"Beauty Salon",
            "type":"Services"
        }
    ],
    "sg:phone":"+1 978 685 7997",
    "sg:postcode":"01844",
    "sg:province":"MA",
    "wof:name":"Nelly's Place Beauty Salon",
    "wof:placetype":"venue"
},
  "geometry": {"coordinates":[-71.184479,42.724791],"type":"Point"}
}