{
  "type": "Feature",
  "properties": {
    "addr:full": "220 Broadway Fl 1 Methuen MA 01844",
    "addr:housenumber": "220",
    "addr:postcode": "1;01844",
    "addr:street": "Broadway",
    "iso:country": "US",
    "sg:address": "220 Broadway Fl 1",
    "sg:city": "Methuen",
    "sg:classifiers": [
      {
        "category": "Personal",
        "subcategory": "Beauty Salon",
        "type": "Services"
      }
    ],
    "sg:phone": "+1 978 685 7997",
    "sg:postcode": "01844",
    "sg:province": "MA",
    "wof:name": "Nelly's Place Beauty Salon",
    "wof:placetype": "venue"
  },
  "geometry": {"coordinates":[-71.184479,42.724791],"type":"Point"}
}
