{
  "type": "Feature",
  "properties": {
    "addr:full":"15 Greenwood Ave Woburn MA 01801",
    "addr:housenumber":"15",
    "addr:postcode":"01801",
    "addr:street":"Greenwood Ave",
    "iso:country":"US",
    "sg:address":"15 Greenwood Ave",
    "sg:city":"Woburn",
    "sg:classifiers":[
        {
            "category":"Building & Trades",
            "subcategory":"Electrical",
            "type":"Services"
        }
    ],
    "sg:phone":"+1 781 933 7388",
    "sg:postcode":"01801",
    "sg:province":"MA",
    "sg:tags":[
        "electrician",
        "electric",
        "contractor"
    ],
    "sg:website":"www.faganelectricalservice.com",
    "wof:name":"Fagan Electrical Service",
    "wof:placetype":"venue"
},
  "geometry": {"coordinates":[-71.148003,42.4795],"type":"Point"}
}