{
  "type": "Feature",
  "properties": {
    "iso:country":"US",
    "sg:address":"2 Van Norden St",
    "sg:city":"Cambridge",
    "sg:classifiers":[
        {
            "category":"Real Estate",
            "subcategory":"Real Estate Agent",
            "type":"Services"
        }
    ],
    "sg:phone":"+1   ",
    "sg:postcode":"02140",
    "sg:province":"MA",
    "wof:name":"Mr Norman R Boucher",
    "wof:placetype":"venue"
},
  "geometry": {"coordinates":[-71.12918999999999,42.391234],"type":"Point"}
}