{
  "type": "Feature",
  "properties": {
    "iso:country":"US",
    "sg:address":"214 N Main St",
    "sg:city":"Natick",
    "sg:classifiers":[
        {
            "category":"Professional",
            "subcategory":"Management & Consulting",
            "type":"Services"
        }
    ],
    "sg:phone":"+1 508 651 1338",
    "sg:postcode":"01760",
    "sg:province":"MA",
    "sg:tags":[
        "consultant",
        "business"
    ],
    "wof:name":"RJH Management",
    "wof:placetype":"venue"
},
  "geometry": {"coordinates":[-71.360804,42.301565],"type":"Point"}
}