{
  "type": "Feature",
  "properties": {
    "addr:full": "76 Sagamore Ave Winthrop MA 02152",
    "addr:housenumber": "76",
    "addr:postcode": "02152",
    "addr:street": "Sagamore Ave",
    "iso:country": "US",
    "sg:address": "76 Sagamore Ave",
    "sg:city": "Winthrop",
    "sg:classifiers": [
      {
        "category": "Retail",
        "subcategory": "Auto Rental",
        "type": "Services"
      }
    ],
    "sg:phone": "+1 617 539 0243",
    "sg:postcode": "02152",
    "sg:province": "MA",
    "sg:tags": [
      "car"
    ],
    "wof:name": "All Purpose Car Rental Inc",
    "wof:placetype": "venue"
  },
  "geometry": {"coordinates":[-70.977222,42.385102],"type":"Point"}
}
