{
  "type": "Feature",
  "properties": {
    "iso:country":"US",
    "sg:address":"40 Weir St",
    "sg:city":"Taunton",
    "sg:classifiers":[
        {
            "category":"Professional",
            "subcategory":"Computer Services",
            "type":"Services"
        }
    ],
    "sg:phone":"+1   ",
    "sg:postcode":"02780",
    "sg:province":"MA",
    "sg:tags":[
        "design",
        "system"
    ],
    "wof:name":"Bay State Cad",
    "wof:placetype":"venue"
},
  "geometry": {"coordinates":[-71.092476,41.901195],"type":"Point"}
}