{
  "type": "Feature",
  "properties": {
    "addr:full": "131 Hartwell Avenue Lexington MA 02421",
    "addr:housenumber": "131",
    "addr:postcode": "02421",
    "addr:street": "Hartwell Avenue",
    "iso:country": "US",
    "sg:address": "131 Hartwell Avenue",
    "sg:city": "Lexington",
    "sg:classifiers": [
      {
        "category": "Professional",
        "subcategory": "Computer Services",
        "type": "Services"
      }
    ],
    "sg:phone": "+1 781 652 7000",
    "sg:postcode": "02421",
    "sg:province": "MA",
    "sg:website": "http://www.makanasolutions.com/",
    "wof:name": "Makana Solutions",
    "wof:placetype": "venue"
  },
  "geometry": {"coordinates":[-71.262394,42.466216],"type":"Point"}
}
