{
  "type": "Feature",
  "properties": {
    "addr:full":"149 Bellevue Ave Adams MA 01220",
    "addr:housenumber":"149",
    "addr:postcode":"01220",
    "addr:street":"Bellevue Ave",
    "iso:country":"US",
    "sg:address":"149 Bellevue Ave",
    "sg:city":"Adams",
    "sg:classifiers":[
        {
            "category":"Government",
            "subcategory":"Office",
            "type":"Public Place"
        }
    ],
    "sg:phone":"+1 413 743 8399",
    "sg:postcode":"01220",
    "sg:province":"MA",
    "sg:tags":[
        "village"
    ],
    "wof:name":"Bellevue Cemetery",
    "wof:placetype":"venue"
},
  "geometry": {"coordinates":[-73.1246,42.605328],"type":"Point"}
}