{
  "type": "Feature",
  "properties": {
    "iso:country":"US",
    "sg:address":"455 Bullard St",
    "sg:city":"Holden",
    "sg:classifiers":[
        {
            "category":"Building & Trades",
            "subcategory":"Plumbing",
            "type":"Services"
        }
    ],
    "sg:phone":"+1   ",
    "sg:postcode":"01520",
    "sg:province":"MA",
    "sg:tags":[
        "air",
        "heating",
        "conditioning",
        "contractor"
    ],
    "wof:name":"J L Demarco",
    "wof:placetype":"venue"
},
  "geometry": {"coordinates":[-71.82814500000001,42.356792],"type":"Point"}
}