{
  "type": "Feature",
  "properties": {
    "addr:full": "455 Bullard St Holden MA 01520",
    "addr:housenumber": "455",
    "addr:postcode": "01520",
    "addr:street": "Bullard St",
    "iso:country": "US",
    "sg:address": "455 Bullard St",
    "sg:city": "Holden",
    "sg:classifiers": [
      {
        "category": "Building \u0026 Trades",
        "subcategory": "Plumbing",
        "type": "Services"
      }
    ],
    "sg:phone": "+1   ",
    "sg:postcode": "01520",
    "sg:province": "MA",
    "sg:tags": [
      "air",
      "heating",
      "conditioning",
      "contractor"
    ],
    "wof:name": "J L Demarco",
    "wof:placetype": "venue"
  },
  "geometry": {"coordinates":[-71.828145,42.356792],"type":"Point"}
}
