{
  "type": "Feature",
  "properties": {
    "iso:country":"US",
    "sg:address":"580 Harrison Ave Ste 400",
    "sg:city":"Boston",
    "sg:classifiers":[
        {
            "category":"Professional",
            "subcategory":"Business Services",
            "type":"Services"
        }
    ],
    "sg:phone":"+1 617 670 0158",
    "sg:postcode":"02118",
    "sg:province":"MA",
    "sg:tags":[
        "development",
        "plan"
    ],
    "wof:name":"Trace Resource Group",
    "wof:placetype":"venue"
},
  "geometry": {"coordinates":[-71.067983,42.340603],"type":"Point"}
}