{
  "type": "Feature",
  "properties": {
    "addr:full": "91 Newbury St Boston MA 02116",
    "addr:housenumber": "91",
    "addr:postcode": "02116",
    "addr:street": "Newbury St",
    "iso:country": "US",
    "sg:address": "91 Newbury St",
    "sg:city": "Boston",
    "sg:classifiers": [
      {
        "category": "Banks \u0026 Credit Unions",
        "subcategory": "Financial Services",
        "type": "Services"
      }
    ],
    "sg:phone": "+1 617 424 7669",
    "sg:postcode": "02116",
    "sg:province": "MA",
    "sg:tags": [
      "trust"
    ],
    "wof:name": "Willow Trust",
    "wof:placetype": "venue"
  },
  "geometry": {"coordinates":[-71.074488,42.351954],"type":"Point"}
}
