{
  "type": "Feature",
  "properties": {
    "iso:country":"US",
    "sg:address":"91 Newbury St",
    "sg:city":"Boston",
    "sg:classifiers":[
        {
            "category":"Banks & Credit Unions",
            "subcategory":"Financial Services",
            "type":"Services"
        }
    ],
    "sg:phone":"+1 617 424 7669",
    "sg:postcode":"02116",
    "sg:province":"MA",
    "sg:tags":[
        "trust"
    ],
    "wof:name":"Willow Trust",
    "wof:placetype":"venue"
},
  "geometry": {"coordinates":[-71.074488,42.351954],"type":"Point"}
}