{
  "type": "Feature",
  "properties": {
    "iso:country":"US",
    "sg:address":"2 Summerhill Ave",
    "sg:city":"Worcester",
    "sg:classifiers":[
        {
            "category":"Building & Trades",
            "subcategory":"Construction",
            "type":"Services"
        }
    ],
    "sg:phone":"+1 508 852 1268",
    "sg:postcode":"01606",
    "sg:province":"MA",
    "sg:tags":[
        "home",
        "improvement"
    ],
    "wof:name":"Salum Home Improvements",
    "wof:placetype":"venue"
},
  "geometry": {"coordinates":[-71.797016,42.305354],"type":"Point"}
}