{
  "type": "Feature",
  "properties": {
    "iso:country":"US",
    "sg:address":"362 Main St",
    "sg:city":"Sturbridge",
    "sg:classifiers":[
        {
            "category":"Shopping",
            "subcategory":"Antiques",
            "type":"Retail Goods"
        }
    ],
    "sg:phone":"+1 508 347 3926",
    "sg:postcode":"01566",
    "sg:province":"MA",
    "wof:name":"Fairgrounds Antique Center the",
    "wof:placetype":"venue"
},
  "geometry": {"coordinates":[-72.064301,42.0882],"type":"Point"}
}