{
  "type": "Feature",
  "properties": {
    "addr:full": "430 Osgood St North Andover MA 01845",
    "addr:housenumber": "430",
    "addr:postcode": "01845",
    "addr:street": "Osgood St",
    "iso:country": "US",
    "sg:address": "430 Osgood St",
    "sg:city": "North Andover",
    "sg:classifiers": [
      {
        "category": "Education",
        "subcategory": "School",
        "type": "Public Place"
      }
    ],
    "sg:phone": "+1 978 794 8051",
    "sg:postcode": "01845",
    "sg:province": "MA",
    "wof:name": "North Andover HS Pathway Prog",
    "wof:placetype": "venue"
  },
  "geometry": {"coordinates":[-71.112299,42.698547],"type":"Point"}
}
