{
  "type": "Feature",
  "properties": {
    "addr:full": "1475 Massachusetts Ave Lexington MA 02420",
    "addr:housenumber": "1475",
    "addr:postcode": "02420",
    "addr:street": "Massachusetts Ave",
    "iso:country": "US",
    "sg:address": "1475 Massachusetts Ave",
    "sg:city": "Lexington",
    "sg:classifiers": [
      {
        "category": "Government",
        "subcategory": "Office",
        "type": "Public Place"
      }
    ],
    "sg:phone": "+1 781 861 2742",
    "sg:postcode": "02420",
    "sg:province": "MA",
    "sg:tags": [
      "city",
      "resource",
      "human"
    ],
    "wof:name": "Lexington Human Svc-Veterans",
    "wof:placetype": "venue"
  },
  "geometry": {"coordinates":[-71.221429,42.445274],"type":"Point"}
}
