{
  "type": "Feature",
  "properties": {
    "iso:country":"US",
    "sg:address":"1475 Massachusetts Ave",
    "sg:city":"Lexington",
    "sg:classifiers":[
        {
            "category":"Government",
            "subcategory":"Office",
            "type":"Public Place"
        }
    ],
    "sg:phone":"+1 781 861 2742",
    "sg:postcode":"02420",
    "sg:province":"MA",
    "sg:tags":[
        "city",
        "resource",
        "human"
    ],
    "wof:name":"Lexington Human Svc-Veterans",
    "wof:placetype":"venue"
},
  "geometry": {"coordinates":[-71.221429,42.445274],"type":"Point"}
}