{
  "type": "Feature",
  "properties": {
    "addr:full":"53 Waltham St Boston MA 02118",
    "addr:housenumber":"53",
    "addr:postcode":"02118",
    "addr:street":"Waltham St",
    "iso:country":"US",
    "sg:address":"53 Waltham St",
    "sg:city":"Boston",
    "sg:classifiers":[
        {
            "category":"Building & Trades",
            "subcategory":"Locksmith",
            "type":"Services"
        }
    ],
    "sg:phone":"+1 617 449 0086",
    "sg:postcode":"02118",
    "sg:province":"MA",
    "sg:tags":[
        "key"
    ],
    "wof:name":"Aaron Locksmith Service",
    "wof:placetype":"venue"
},
  "geometry": {"coordinates":[-71.069503,42.342447],"type":"Point"}
}