{
  "type": "Feature",
  "properties": {
    "addr:full": "30 Rantoul St Ste 2 Beverly MA 01915",
    "addr:housenumber": "30",
    "addr:postcode": "01915",
    "addr:street": "Rantoul St Ste 2",
    "iso:country": "US",
    "sg:address": "30 Rantoul St Ste 2",
    "sg:city": "Beverly",
    "sg:classifiers": [
      {
        "category": "Social Services",
        "subcategory": "Child Care",
        "type": "Services"
      }
    ],
    "sg:phone": "+1 978 921 1735",
    "sg:postcode": "01915",
    "sg:province": "MA",
    "sg:tags": [
      "baby",
      "sitter"
    ],
    "sg:website": "http://www.sidebandsys.com",
    "wof:name": "In Search Of Nanny Inc",
    "wof:placetype": "venue"
  },
  "geometry": {"coordinates":[-70.884985,42.542344],"type":"Point"}
}
