{
  "type": "Feature",
  "properties": {
    "iso:country":"US",
    "sg:address":"88 School St",
    "sg:city":"Mansfield",
    "sg:classifiers":[
        {
            "category":"Retail",
            "subcategory":"Funeral Services",
            "type":"Services"
        }
    ],
    "sg:phone":"+1 508 339 6830",
    "sg:postcode":"02048",
    "sg:province":"MA",
    "sg:tags":[
        "cemetery"
    ],
    "wof:name":"Springbrook Cemetery",
    "wof:placetype":"venue"
},
  "geometry": {"coordinates":[-71.22450000000001,42.0202],"type":"Point"}
}