{
  "type": "Feature",
  "properties": {
    "addr:full": "88 School St Mansfield MA 02048",
    "addr:housenumber": "88",
    "addr:postcode": "02048",
    "addr:street": "School St",
    "iso:country": "US",
    "sg:address": "88 School St",
    "sg:city": "Mansfield",
    "sg:classifiers": [
      {
        "category": "Retail",
        "subcategory": "Funeral Services",
        "type": "Services"
      }
    ],
    "sg:phone": "+1 508 339 6830",
    "sg:postcode": "02048",
    "sg:province": "MA",
    "sg:tags": [
      "cemetery"
    ],
    "wof:name": "Springbrook Cemetery",
    "wof:placetype": "venue"
  },
  "geometry": {"coordinates":[-71.2245,42.0202],"type":"Point"}
}
