{
  "type": "Feature",
  "properties": {
    "iso:country":"US",
    "sg:address":"606 N Main St",
    "sg:city":"Raynham Center",
    "sg:classifiers":[
        {
            "category":"Health Services",
            "subcategory":"Doctor",
            "type":"Services"
        }
    ],
    "sg:phone":"+1 508 824 8900",
    "sg:postcode":"02743",
    "sg:province":"MA",
    "sg:tags":[
        "dentist"
    ],
    "wof:name":"Robert G Paquette DDS",
    "wof:placetype":"venue"
},
  "geometry": {"coordinates":[-70.887792,41.709015],"type":"Point"}
}