{
  "type": "Feature",
  "properties": {
    "addr:full": "10 Park Plz Ste 5450 Boston MA 02116",
    "addr:housenumber": "10",
    "addr:postcode": "02116",
    "addr:street": "Park Plz Ste 5450",
    "iso:country": "US",
    "sg:address": "10 Park Plz Ste 5450",
    "sg:city": "Boston",
    "sg:classifiers": [
      {
        "category": "Autos \u0026 Motor Vehicles",
        "subcategory": "Automobile Sales",
        "type": "Retail Goods"
      }
    ],
    "sg:phone": "+1 617 351 9977",
    "sg:postcode": "02116",
    "sg:province": "MA",
    "sg:tags": [
      "new",
      "used",
      "car"
    ],
    "wof:name": "Comm Of Mass Motor Vehicl",
    "wof:placetype": "venue"
  },
  "geometry": {"coordinates":[-71.067261,42.35186],"type":"Point"}
}
