{
  "type": "Feature",
  "properties": {
    "iso:country":"US",
    "sg:address":"10 Park Plz Ste 5450",
    "sg:city":"Boston",
    "sg:classifiers":[
        {
            "category":"Autos & Motor Vehicles",
            "subcategory":"Automobile Sales",
            "type":"Retail Goods"
        }
    ],
    "sg:phone":"+1 617 351 9977",
    "sg:postcode":"02116",
    "sg:province":"MA",
    "sg:tags":[
        "new",
        "used",
        "car"
    ],
    "wof:name":"Comm Of Mass Motor Vehicl",
    "wof:placetype":"venue"
},
  "geometry": {"coordinates":[-71.067261,42.35186],"type":"Point"}
}