{
  "type": "Feature",
  "properties": {
    "iso:country":"US",
    "sg:address":"168 Robinson St",
    "sg:city":"Hanson",
    "sg:classifiers":[
        {
            "category":"Farming",
            "subcategory":"Farm",
            "type":"Manufacturing & Wholesale Goods"
        }
    ],
    "sg:phone":"+1 781 294 8500",
    "sg:postcode":"02341",
    "sg:province":"MA",
    "wof:name":"Country Farm Cranberry Assoc",
    "wof:placetype":"venue"
},
  "geometry": {"coordinates":[-70.870335,42.040389],"type":"Point"}
}