{
  "type": "Feature",
  "properties": {
    "iso:country":"US",
    "sg:address":"6 Firehouse Ln",
    "sg:city":"Oak Bluffs",
    "sg:classifiers":[
        {
            "category":"Government",
            "subcategory":"Office",
            "type":"Public Place"
        }
    ],
    "sg:phone":"+1 508 693 5380",
    "sg:postcode":"02557",
    "sg:province":"MA",
    "sg:tags":[
        "village"
    ],
    "wof:name":"Oak Bluffs Ambulance Dept",
    "wof:placetype":"venue"
},
  "geometry": {"coordinates":[-70.574066,41.447676],"type":"Point"}
}