{
  "type": "Feature",
  "properties": {
    "addr:full": "37 Locust Rd Orleans MA 02653",
    "addr:housenumber": "37",
    "addr:postcode": "02653",
    "addr:street": "Locust Rd",
    "iso:country": "US",
    "sg:address": "37 Locust Rd",
    "sg:city": "Orleans",
    "sg:classifiers": [
      {
        "category": "Building \u0026 Trades",
        "subcategory": "Construction",
        "type": "Services"
      }
    ],
    "sg:phone": "+1   ",
    "sg:postcode": "02653",
    "sg:province": "MA",
    "sg:tags": [
      "hanging",
      "contractor"
    ],
    "wof:name": "Jayco Painting Inc",
    "wof:placetype": "venue"
  },
  "geometry": {"coordinates":[-69.989023,41.79432],"type":"Point"}
}
