{
  "type": "Feature",
  "properties": {
    "iso:country":"US",
    "sg:address":"15 Drury Rd",
    "sg:city":"Hyde Park",
    "sg:classifiers":[
        {
            "category":"Retail",
            "subcategory":"Photofinishing",
            "type":"Services"
        }
    ],
    "sg:phone":"+1   ",
    "sg:postcode":"02136",
    "sg:province":"MA",
    "sg:tags":[
        "photo",
        "finishing"
    ],
    "wof:name":"McDonnell Photo",
    "wof:placetype":"venue"
},
  "geometry": {"coordinates":[-71.13403700000001,42.251213],"type":"Point"}
}