{
  "type": "Feature",
  "properties": {
    "addr:full":"14 Temi Rd Chelmsford MA 01824",
    "addr:housenumber":"14",
    "addr:postcode":"01824",
    "addr:street":"Temi Rd",
    "iso:country":"US",
    "sg:address":"14 Temi Rd",
    "sg:city":"Chelmsford",
    "sg:classifiers":[
        {
            "category":"Airline",
            "type":"Transportation"
        },
        {
            "category":"Professional",
            "subcategory":"Business Services",
            "type":"Services"
        }
    ],
    "sg:phone":"+1 978 256 3566",
    "sg:postcode":"01824",
    "sg:province":"MA",
    "sg:tags":[
        "delivery",
        "shuttle",
        "airport",
        "courier"
    ],
    "wof:name":"Alert Delivery Service - CLOSED",
    "wof:placetype":"venue"
},
  "geometry": {"coordinates":[-71.34200300000001,42.573898],"type":"Point"}
}