{
  "type": "Feature",
  "properties": {
    "addr:full": "26 George St Brockton MA 02302",
    "addr:housenumber": "26",
    "addr:postcode": "02302",
    "addr:street": "George St",
    "iso:country": "US",
    "sg:address": "26 George St",
    "sg:city": "Brockton",
    "sg:classifiers": [
      {
        "category": "Retail",
        "subcategory": "Auto Repair",
        "type": "Services"
      }
    ],
    "sg:phone": "+1 508 586 5195",
    "sg:postcode": "02302",
    "sg:province": "MA",
    "sg:tags": [
      "wrecker"
    ],
    "wof:name": "Manoli Towing \u0026 Svc",
    "wof:placetype": "venue"
  },
  "geometry": {"coordinates":[-70.996433,42.076511],"type":"Point"}
}
