{
  "type": "Feature",
  "properties": {
    "iso:country":"US",
    "sg:address":"26 George St",
    "sg:city":"Brockton",
    "sg:classifiers":[
        {
            "category":"Retail",
            "subcategory":"Auto Repair",
            "type":"Services"
        }
    ],
    "sg:phone":"+1 508 586 5195",
    "sg:postcode":"02302",
    "sg:province":"MA",
    "sg:tags":[
        "wrecker"
    ],
    "wof:name":"Manoli Towing & Svc",
    "wof:placetype":"venue"
},
  "geometry": {"coordinates":[-70.996433,42.076511],"type":"Point"}
}