{
  "type": "Feature",
  "properties": {
    "iso:country":"US",
    "sg:address":"29 Prospect St",
    "sg:city":"Kingston",
    "sg:classifiers":[
        {
            "category":"Professional",
            "subcategory":"Art Services",
            "type":"Services"
        }
    ],
    "sg:phone":"+1   ",
    "sg:postcode":"02364",
    "sg:province":"MA",
    "sg:tags":[
        "commercial",
        "design"
    ],
    "wof:name":"Fine Design Graphic Web Sites",
    "wof:placetype":"venue"
},
  "geometry": {"coordinates":[-70.71136799999999,41.98267],"type":"Point"}
}