{
  "type": "Feature",
  "properties": {
    "addr:full":"17 Hampden St Springfield MA 01103",
    "addr:housenumber":"17",
    "addr:postcode":"01103",
    "addr:street":"Hampden St",
    "iso:country":"US",
    "sg:address":"17 Hampden St",
    "sg:city":"Springfield",
    "sg:classifiers":[
        {
            "category":"Real Estate",
            "subcategory":"Architect",
            "type":"Services"
        }
    ],
    "sg:phone":"+1 413 733 6798",
    "sg:postcode":"01103",
    "sg:province":"MA",
    "sg:website":"www.dietzarch.com",
    "wof:name":"Dietz & Co Architects",
    "wof:placetype":"venue"
},
  "geometry": {"coordinates":[-72.594971,42.103281],"type":"Point"}
}