{
  "type": "Feature",
  "properties": {
    "iso:country":"US",
    "sg:address":"8 Windham Rd",
    "sg:city":"Hyde Park",
    "sg:classifiers":[
        {
            "category":"Building & Trades",
            "subcategory":"Landscaping Services",
            "type":"Services"
        }
    ],
    "sg:phone":"+1   ",
    "sg:postcode":"02136",
    "sg:province":"MA",
    "wof:name":"Forever Green Landscaping",
    "wof:placetype":"venue"
},
  "geometry": {"coordinates":[-71.124764,42.27227],"type":"Point"}
}