{
  "type": "Feature",
  "properties": {
    "addr:full": "8 Windham Rd Hyde Park MA 02136",
    "addr:housenumber": "8",
    "addr:postcode": "02136",
    "addr:street": "Windham Rd",
    "iso:country": "US",
    "sg:address": "8 Windham Rd",
    "sg:city": "Hyde Park",
    "sg:classifiers": [
      {
        "category": "Building \u0026 Trades",
        "subcategory": "Landscaping Services",
        "type": "Services"
      }
    ],
    "sg:phone": "+1   ",
    "sg:postcode": "02136",
    "sg:province": "MA",
    "wof:name": "Forever Green Landscaping",
    "wof:placetype": "venue"
  },
  "geometry": {"coordinates":[-71.124764,42.27227],"type":"Point"}
}
