{
  "type": "Feature",
  "properties": {
    "iso:country":"US",
    "sg:address":"13 Leavitt St",
    "sg:city":"Hingham",
    "sg:classifiers":[
        {
            "category":"Real Estate",
            "subcategory":"Real Estate Agent",
            "type":"Services"
        }
    ],
    "sg:phone":"+1 781 749 3650",
    "sg:postcode":"02043",
    "sg:province":"MA",
    "wof:name":"Hingham Centre LTD Realtors",
    "wof:placetype":"venue"
},
  "geometry": {"coordinates":[-70.878282,42.234178],"type":"Point"}
}