{
  "type": "Feature",
  "properties": {
    "iso:country":"US",
    "sg:address":"69 Westech Dr",
    "sg:city":"Tyngsboro",
    "sg:classifiers":[
        {
            "category":"Building & Trades",
            "subcategory":"Construction",
            "type":"Services"
        }
    ],
    "sg:phone":"+1 978 649 0601",
    "sg:postcode":"01879",
    "sg:province":"MA",
    "sg:tags":[
        "maker",
        "cabinet"
    ],
    "sg:website":"www.pmhcw.com",
    "wof:name":"PMH Custom Woodworking",
    "wof:placetype":"venue"
},
  "geometry": {"coordinates":[-71.425438,42.659993],"type":"Point"}
}