{
  "type": "Feature",
  "properties": {
    "addr:full":"468 Chestnut St Lynn MA 01902",
    "addr:housenumber":"468",
    "addr:postcode":"01902",
    "addr:street":"Chestnut St",
    "iso:country":"US",
    "sg:address":"468 Chestnut St",
    "sg:city":"Lynn",
    "sg:classifiers":[
        {
            "category":"Restaurant",
            "type":"Food & Drink"
        }
    ],
    "sg:phone":"+1 781 593 3733",
    "sg:postcode":"01902",
    "sg:province":"MA",
    "wof:name":"Ozo Roast Beef",
    "wof:placetype":"venue"
},
  "geometry": {"coordinates":[-70.947676,42.476541],"type":"Point"}
}