{
  "type": "Feature",
  "properties": {
    "addr:full": "555 Main St Wilmington MA 01887",
    "addr:housenumber": "555",
    "addr:postcode": "01887",
    "addr:street": "Main St",
    "iso:country": "US",
    "sg:address": "555 Main St",
    "sg:city": "Wilmington",
    "sg:classifiers": [
      {
        "category": "Retail",
        "subcategory": "Auto Repair",
        "type": "Services"
      }
    ],
    "sg:phone": "+1 978 988 0763",
    "sg:postcode": "01887",
    "sg:province": "MA",
    "sg:tags": [
      "repairing",
      "automobile"
    ],
    "wof:name": "South Street Automotive",
    "wof:placetype": "venue"
  },
  "geometry": {"coordinates":[-71.170428,42.543644],"type":"Point"}
}
