{
  "type": "Feature",
  "properties": {
    "addr:full":"Chappel Rock Park, Squantum Quincy MA 02171",
    "addr:postcode":"02171",
    "iso:country":"US",
    "sg:address":"Chappel Rock Park, Squantum",
    "sg:city":"Quincy",
    "sg:classifiers":[
        {
            "category":"Recreation",
            "subcategory":"Dog Park",
            "type":"Entertainment"
        },
        {
            "category":"Recreation",
            "subcategory":"Water Park",
            "type":"Entertainment"
        }
    ],
    "sg:postcode":"02171",
    "sg:province":"MA",
    "sg:tags":[
        "beach"
    ],
    "wof:name":"Nickerson Beach",
    "wof:placetype":"venue"
},
  "geometry": {"coordinates":[-71.011518,42.30363],"type":"Point"}
}