{
  "type": "Feature",
  "properties": {
    "iso:country":"US",
    "sg:address":"25 Staniford St Ste 2E",
    "sg:city":"Boston",
    "sg:classifiers":[
        {
            "category":"Health Services",
            "subcategory":"Clinic",
            "type":"Services"
        }
    ],
    "sg:phone":"+1 617 523 1529",
    "sg:postcode":"02114",
    "sg:province":"MA",
    "sg:tags":[
        "information",
        "mental"
    ],
    "sg:website":"http://www.northsuffolk.org",
    "wof:name":"Boston Emrgncy Svcs Team Best",
    "wof:placetype":"venue"
},
  "geometry": {"coordinates":[-71.06385,42.36216],"type":"Point"}
}