{
  "type": "Feature",
  "properties": {
    "addr:full": "64 Middlesex Tpke Burlington MA 01803",
    "addr:housenumber": "64",
    "addr:postcode": "01803",
    "addr:street": "Middlesex Tpke",
    "iso:country": "US",
    "sg:address": "64 Middlesex Tpke",
    "sg:city": "Burlington",
    "sg:classifiers": [
      {
        "category": "Shopping",
        "subcategory": "Mobile Phones",
        "type": "Retail Goods"
      }
    ],
    "sg:phone": "+1 781 221 7222",
    "sg:postcode": "01803",
    "sg:province": "MA",
    "wof:name": "Grand Wireless",
    "wof:placetype": "venue"
  },
  "geometry": {"coordinates":[-71.217003,42.4809],"type":"Point"}
}
