{
  "type": "Feature",
  "properties": {
    "addr:full":"71 Main St Vineyard Haven MA 02568",
    "addr:housenumber":"71",
    "addr:postcode":"02568",
    "addr:street":"Main St",
    "iso:country":"US",
    "sg:address":"71 Main St",
    "sg:city":"Vineyard Haven",
    "sg:classifiers":[
        {
            "category":"Professional",
            "subcategory":"Advertising",
            "type":"Services"
        }
    ],
    "sg:phone":"+1 508 693 5807",
    "sg:postcode":"02568",
    "sg:province":"MA",
    "sg:tags":[
        "counselor"
    ],
    "wof:name":"Kolodny & Rentschler Advertise",
    "wof:placetype":"venue"
},
  "geometry": {"coordinates":[-70.602835,41.454844],"type":"Point"}
}