{
  "type": "Feature",
  "properties": {
    "addr:full":"345 Centre St Jamaica Plain MA 02130",
    "addr:housenumber":"345",
    "addr:postcode":"02130",
    "addr:street":"Centre St",
    "iso:country":"US",
    "sg:address":"345 Centre St",
    "sg:city":"Jamaica Plain",
    "sg:classifiers":[
        {
            "category":"Professional",
            "subcategory":"Business Services",
            "type":"Services"
        }
    ],
    "sg:phone":"+1 617 524 7100",
    "sg:postcode":"02130",
    "sg:province":"MA",
    "sg:tags":[
        "paging",
        "signaling"
    ],
    "wof:name":"99 Cents Store",
    "wof:placetype":"venue"
},
  "geometry": {"coordinates":[-71.10621500000001,42.322684],"type":"Point"}
}