{
  "type": "Feature",
  "properties": {
    "iso:country":"US",
    "sg:address":"32 Hemeon Dr",
    "sg:city":"West Yarmouth",
    "sg:classifiers":[
        {
            "category":"Building & Trades",
            "subcategory":"Plumbing",
            "type":"Services"
        },
        {
            "category":"Home & Garden",
            "subcategory":"Garden Supply",
            "type":"Retail Goods"
        }
    ],
    "sg:phone":"+1 508 775 2404",
    "sg:postcode":"02673",
    "sg:province":"MA",
    "sg:tags":[
        "sprinkler",
        "contractor"
    ],
    "wof:name":"Crahan's Lawn Sprinkler Svc",
    "wof:placetype":"venue"
},
  "geometry": {"coordinates":[-70.246407,41.652541],"type":"Point"}
}