{
  "type": "Feature",
  "properties": {
    "addr:full": "62 Ledgelawn Ave Lexington MA 02420",
    "addr:housenumber": "62",
    "addr:postcode": "02420",
    "addr:street": "Ledgelawn Ave",
    "iso:country": "US",
    "sg:address": "62 Ledgelawn Ave",
    "sg:city": "Lexington",
    "sg:classifiers": [
      {
        "category": "Health Services",
        "subcategory": "Doctor",
        "type": "Services"
      }
    ],
    "sg:phone": "+1   ",
    "sg:postcode": "02420",
    "sg:province": "MA",
    "sg:tags": [
      "medical"
    ],
    "wof:name": "Randy Zioto",
    "wof:placetype": "venue"
  },
  "geometry": {"coordinates":[-71.233185,42.461394],"type":"Point"}
}
