{
  "type": "Feature",
  "properties": {
    "iso:country":"US",
    "sg:address":"62 Ledgelawn Ave",
    "sg:city":"Lexington",
    "sg:classifiers":[
        {
            "category":"Health Services",
            "subcategory":"Doctor",
            "type":"Services"
        }
    ],
    "sg:phone":"+1   ",
    "sg:postcode":"02420",
    "sg:province":"MA",
    "sg:tags":[
        "medical"
    ],
    "wof:name":"Randy Zioto",
    "wof:placetype":"venue"
},
  "geometry": {"coordinates":[-71.23318500000001,42.461394],"type":"Point"}
}