{
  "type": "Feature",
  "properties": {
    "addr:full": "4 Whitridge Rd Natick MA 01760",
    "addr:housenumber": "4",
    "addr:postcode": "01760",
    "addr:street": "Whitridge Rd",
    "iso:country": "US",
    "sg:address": "4 Whitridge Rd",
    "sg:city": "Natick",
    "sg:classifiers": [
      {
        "category": "Professional",
        "subcategory": "Business Services",
        "type": "Services"
      }
    ],
    "sg:phone": "+1 508 651 8330",
    "sg:postcode": "01760",
    "sg:province": "MA",
    "wof:name": "Laurie Gorelick Interiors",
    "wof:placetype": "venue"
  },
  "geometry": {"coordinates":[-71.339818,42.261933],"type":"Point"}
}
