{
  "type": "Feature",
  "properties": {
    "iso:country":"US",
    "sg:address":"4 Whitridge Rd",
    "sg:city":"Natick",
    "sg:classifiers":[
        {
            "category":"Professional",
            "subcategory":"Business Services",
            "type":"Services"
        }
    ],
    "sg:phone":"+1 508 651 8330",
    "sg:postcode":"01760",
    "sg:province":"MA",
    "wof:name":"Laurie Gorelick Interiors",
    "wof:placetype":"venue"
},
  "geometry": {"coordinates":[-71.33981799999999,42.261933],"type":"Point"}
}