{
  "type": "Feature",
  "properties": {
    "addr:full":"31 Cabot Rd Woburn MA 01801",
    "addr:housenumber":"31",
    "addr:postcode":"01801",
    "addr:street":"Cabot Rd",
    "iso:country":"US",
    "sg:address":"31 Cabot Rd",
    "sg:city":"Woburn",
    "sg:classifiers":[
        {
            "category":"Wholesale",
            "subcategory":"Machinery & Supplies",
            "type":"Manufacturing & Wholesale Goods"
        }
    ],
    "sg:phone":"+1 781 935 8808",
    "sg:postcode":"01801",
    "sg:province":"MA",
    "sg:tags":[
        "equipment",
        "industrial"
    ],
    "sg:website":"www.grainger.com",
    "wof:name":"Grainger Inc",
    "wof:placetype":"venue"
},
  "geometry": {"coordinates":[-71.135328,42.506245],"type":"Point"}
}