{
  "type": "Feature",
  "properties": {
    "iso:country":"US",
    "sg:address":"109 Wapping Rd",
    "sg:city":"Kingston",
    "sg:classifiers":[
        {
            "category":"Building & Trades",
            "subcategory":"Construction",
            "type":"Services"
        }
    ],
    "sg:phone":"+1 781 585 7844",
    "sg:postcode":"02364",
    "sg:province":"MA",
    "sg:tags":[
        "floor",
        "laying",
        "contractor"
    ],
    "wof:name":"Maddock Flooring",
    "wof:placetype":"venue"
},
  "geometry": {"coordinates":[-70.779494,41.989658],"type":"Point"}
}