{
  "type": "Feature",
  "properties": {
    "addr:full":"1440 US Hwy 44 Raynham MA 02767",
    "addr:housenumber":"1440",
    "addr:postcode":"02767",
    "addr:street":"Us Hwy 44",
    "iso:country":"US",
    "sg:address":"1440 US Hwy 44",
    "sg:city":"Raynham",
    "sg:classifiers":[
        {
            "category":"Autos & Motor Vehicles",
            "subcategory":"Automobile Sales",
            "type":"Retail Goods"
        }
    ],
    "sg:phone":"+1 508 880 0000",
    "sg:postcode":"02767",
    "sg:province":"MA",
    "sg:tags":[
        "car",
        "dealer"
    ],
    "wof:name":"Rodman Ford Lincoln Mercury",
    "wof:placetype":"venue"
},
  "geometry": {"coordinates":[-71.014849,41.904451],"type":"Point"}
}