{
  "type": "Feature",
  "properties": {
    "addr:full": "617 Columbia Rd Dorchester MA 02125",
    "addr:housenumber": "617",
    "addr:postcode": "02125",
    "addr:street": "Columbia Rd",
    "iso:country": "US",
    "sg:address": "617 Columbia Rd",
    "sg:city": "Dorchester",
    "sg:classifiers": [
      {
        "category": "Wholesale",
        "subcategory": "Machinery \u0026 Supplies",
        "type": "Manufacturing \u0026 Wholesale Goods"
      }
    ],
    "sg:phone": "+1 617 825 0456",
    "sg:postcode": "02125",
    "sg:province": "MA",
    "sg:tags": [
      "janitor"
    ],
    "wof:name": "Atco Supply Co Inc",
    "wof:placetype": "venue"
  },
  "geometry": {"coordinates":[-71.0652,42.317071],"type":"Point"}
}
