{
  "type": "Feature",
  "properties": {
    "addr:full": "10 Anthony Rd Hopedale MA 01747",
    "addr:housenumber": "10",
    "addr:postcode": "01747",
    "addr:street": "Anthony Rd",
    "iso:country": "US",
    "sg:address": "10 Anthony Rd",
    "sg:city": "Hopedale",
    "sg:classifiers": [
      {
        "category": "Professional",
        "subcategory": "Advertising",
        "type": "Services"
      }
    ],
    "sg:phone": "+1 508 478 4243",
    "sg:postcode": "01747",
    "sg:province": "MA",
    "sg:tags": [
      "agency",
      "specialty"
    ],
    "wof:name": "Michael \u0026 Betty Maguire",
    "wof:placetype": "venue"
  },
  "geometry": {"coordinates":[-71.519691,42.101479],"type":"Point"}
}
