{
  "type": "Feature",
  "properties": {
    "iso:country":"US",
    "sg:address":"53 Langley Rd",
    "sg:city":"Newton",
    "sg:classifiers":[
        {
            "category":"Health Services",
            "subcategory":"Health Practitioner",
            "type":"Services"
        }
    ],
    "sg:phone":"+1 617 780 9773",
    "sg:postcode":"02459",
    "sg:province":"MA",
    "sg:tags":[
        "psychologist"
    ],
    "wof:name":"Lillian Sober-Ain PHD",
    "wof:placetype":"venue"
},
  "geometry": {"coordinates":[-71.191726,42.330167],"type":"Point"}
}