{
  "type": "Feature",
  "properties": {
    "addr:full": "259 McGrath Hwy Somerville MA 02145",
    "addr:housenumber": "259",
    "addr:postcode": "02145",
    "addr:street": "Mcgrath Hwy",
    "iso:country": "US",
    "sg:address": "259 McGrath Hwy",
    "sg:city": "Somerville",
    "sg:classifiers": [
      {
        "category": "Autos \u0026 Motor Vehicles",
        "subcategory": "Automobile Sales",
        "type": "Retail Goods"
      }
    ],
    "sg:phone": "+1 617 666 4100",
    "sg:postcode": "02145",
    "sg:province": "MA",
    "sg:tags": [
      "car"
    ],
    "sg:website": "www.herbchambers.com",
    "wof:name": "Chambers Motorcars of Boston",
    "wof:placetype": "venue"
  },
  "geometry": {"coordinates":[-71.08852,42.377231],"type":"Point"}
}
