{
  "type": "Feature",
  "properties": {
    "iso:country":"US",
    "sg:address":"945 Concord St",
    "sg:city":"Framingham",
    "sg:classifiers":[
        {
            "category":"Professional",
            "subcategory":"Business Services",
            "type":"Services"
        }
    ],
    "sg:phone":"+1 508 405 1087",
    "sg:postcode":"01701",
    "sg:province":"MA",
    "sg:tags":[
        "organizing",
        "services-household"
    ],
    "wof:name":"Cobblestone Career Management",
    "wof:placetype":"venue"
},
  "geometry": {"coordinates":[-71.403954,42.30479],"type":"Point"}
}