{
  "type": "Feature",
  "properties": {
    "addr:full":"1460 Main St Springfield MA 01103",
    "addr:housenumber":"1460",
    "addr:postcode":"01103",
    "addr:street":"Main St",
    "iso:country":"US",
    "sg:address":"1460 Main St",
    "sg:city":"Springfield",
    "sg:classifiers":[
        {
            "category":"Professional",
            "subcategory":"Lawyer & Legal Services",
            "type":"Services"
        }
    ],
    "sg:phone":"+1 413 747 7700",
    "sg:postcode":"01103",
    "sg:province":"MA",
    "sg:tags":[
        "attorney"
    ],
    "wof:name":"Gold & Vanaria",
    "wof:placetype":"venue"
},
  "geometry": {"coordinates":[-72.590774,42.102648],"type":"Point"}
}