{
  "type": "Feature",
  "properties": {
    "iso:country":"US",
    "sg:address":"65 Hancock Street",
    "sg:city":"Everett",
    "sg:classifiers":[
        {
            "category":"Shopping",
            "subcategory":"Pets & Pet Supplies",
            "type":"Retail Goods"
        }
    ],
    "sg:phone":"+1 617 389 7258",
    "sg:postcode":"02149",
    "sg:province":"MA",
    "sg:tags":[
        "store"
    ],
    "wof:name":"Exotic Marine Fish Company",
    "wof:placetype":"venue"
},
  "geometry": {"coordinates":[-71.05459,42.412483],"type":"Point"}
}