{
  "type": "Feature",
  "properties": {
    "addr:full":"515 Saratoga St Boston MA 02128",
    "addr:housenumber":"515",
    "addr:postcode":"02128",
    "addr:street":"Saratoga St",
    "iso:country":"US",
    "sg:address":"515 Saratoga St",
    "sg:city":"Boston",
    "sg:classifiers":[
        {
            "category":"Building & Trades",
            "subcategory":"Electrical",
            "type":"Services"
        }
    ],
    "sg:phone":"+1 617 561 9844",
    "sg:postcode":"02128",
    "sg:province":"MA",
    "sg:tags":[
        "electric",
        "industrial",
        "contractors-commercial",
        "contractor"
    ],
    "wof:name":"Patricelli Electrical Contractors",
    "wof:placetype":"venue"
},
  "geometry": {"coordinates":[-71.025854,42.380538],"type":"Point"}
}