{
  "type": "Feature",
  "properties": {
    "iso:country":"US",
    "sg:address":"9 Green St",
    "sg:city":"Holliston",
    "sg:classifiers":[
        {
            "category":"Building & Trades",
            "subcategory":"Construction",
            "type":"Services"
        }
    ],
    "sg:phone":"+1 508 429 7789",
    "sg:postcode":"01746",
    "sg:province":"MA",
    "sg:tags":[
        "carpenter"
    ],
    "sg:website":"www.jmconstructionco.com",
    "wof:name":"J M Construction",
    "wof:placetype":"venue"
},
  "geometry": {"coordinates":[-71.432451,42.19999],"type":"Point"}
}