{
  "type": "Feature",
  "properties": {
    "iso:country":"US",
    "sg:address":"1410 Boston Provdnce Tpke Ste 308",
    "sg:city":"Norwood",
    "sg:classifiers":[
        {
            "category":"Professional",
            "subcategory":"Employment Agencies",
            "type":"Services"
        }
    ],
    "sg:phone":"+1 781 769 8350",
    "sg:postcode":"02062",
    "sg:province":"MA",
    "wof:name":"Davidson Robt H Assocs Inc - CLOSED",
    "wof:placetype":"venue"
},
  "geometry": {"coordinates":[-71.197304,42.168201],"type":"Point"}
}