{
  "type": "Feature",
  "properties": {
    "addr:full":"133 Federal St Lower Level Boston MA 02110",
    "addr:housenumber":"133",
    "addr:postcode":"02110",
    "addr:street":"Federal St;Level",
    "iso:country":"US",
    "sg:address":"133 Federal St Lower Level",
    "sg:city":"Boston",
    "sg:classifiers":[
        {
            "category":"Sports & Exercise",
            "subcategory":"Gym",
            "type":"Entertainment"
        },
        {
            "category":"Arena",
            "subcategory":"Sports Club",
            "type":"Entertainment"
        }
    ],
    "sg:phone":"+1 617 426 1009",
    "sg:postcode":"02110",
    "sg:province":"MA",
    "sg:tags":[
        "health",
        "gymnasium"
    ],
    "sg:website":"www.fedsthealth.com/",
    "wof:name":"Federal Street Health & Fitness",
    "wof:placetype":"venue"
},
  "geometry": {"coordinates":[-71.056381,42.354318],"type":"Point"}
}