{
  "type": "Feature",
  "properties": {
    "addr:full":"8 Burke Street Boston MA 02127",
    "addr:housenumber":"8",
    "addr:postcode":"02127",
    "addr:street":"Burke Street",
    "iso:country":"US",
    "sg:address":"8 Burke Street",
    "sg:city":"Boston",
    "sg:classifiers":[
        {
            "category":"Sports & Exercise",
            "subcategory":"Gym",
            "type":"Entertainment"
        }
    ],
    "sg:phone":"+1 617 269 8054",
    "sg:postcode":"02127",
    "sg:province":"MA",
    "sg:tags":[
        "trainer"
    ],
    "wof:name":"Intensive Outpatient Program",
    "wof:placetype":"venue"
},
  "geometry": {"coordinates":[-71.051372,42.330129],"type":"Point"}
}