{
  "type": "Feature",
  "properties": {
    "addr:full":"370 Main St South Dennis MA 02660",
    "addr:housenumber":"370",
    "addr:postcode":"02660",
    "addr:street":"Main St",
    "iso:country":"US",
    "sg:address":"370 Main St",
    "sg:city":"South Dennis",
    "sg:classifiers":[
        {
            "category":"Travel",
            "subcategory":"Hotels & Motels",
            "type":"Entertainment"
        }
    ],
    "sg:phone":"+1 508 394 7474",
    "sg:postcode":"02660",
    "sg:province":"MA",
    "sg:tags":[
        "breakfast",
        "accommodation",
        "bed"
    ],
    "wof:name":"Shady Hollow Inn",
    "wof:placetype":"venue"
},
  "geometry": {"coordinates":[-70.155473,41.682706],"type":"Point"}
}