{
  "type": "Feature",
  "properties": {
    "addr:full": "307 Boylston St Brookline MA 02445",
    "addr:housenumber": "307",
    "addr:postcode": "02445",
    "addr:street": "Boylston St",
    "iso:country": "US",
    "sg:address": "307 Boylston St",
    "sg:city": "Brookline",
    "sg:classifiers": [
      {
        "category": "Professional",
        "type": "Services"
      }
    ],
    "sg:phone": "+1 617 566 9305",
    "sg:postcode": "02445",
    "sg:province": "MA",
    "sg:tags": [
      "establishment"
    ],
    "wof:name": "Bob Sullivan's Jenney Station",
    "wof:placetype": "venue"
  },
  "geometry": {"coordinates":[-71.124972,42.330374],"type":"Point"}
}
