{
  "type": "Feature",
  "properties": {
    "addr:full":"197 Centre St Dorchester Ctr MA 02124",
    "addr:housenumber":"197",
    "addr:postcode":"02124",
    "addr:street":"Centre St",
    "iso:country":"US",
    "sg:address":"197 Centre St",
    "sg:city":"Dorchester Ctr",
    "sg:classifiers":[
        {
            "category":"Education",
            "subcategory":"School",
            "type":"Public Place"
        }
    ],
    "sg:phone":"+1 617 825 0703",
    "sg:postcode":"02124",
    "sg:province":"MA",
    "wof:name":"Neighborhood House Charter",
    "wof:placetype":"venue"
},
  "geometry": {"coordinates":[-71.064401,42.292294],"type":"Point"}
}