{
  "type": "Feature",
  "properties": {
    "addr:full": "49 Hancock Street Cambridge MA 02139",
    "addr:housenumber": "49",
    "addr:postcode": "02139",
    "addr:street": "Hancock Street",
    "iso:country": "US",
    "sg:address": "49 Hancock Street",
    "sg:city": "Cambridge",
    "sg:classifiers": [
      {
        "category": "Health Services",
        "subcategory": "Doctor",
        "type": "Services"
      },
      {
        "category": "Sports \u0026 Exercise",
        "subcategory": "Gym",
        "type": "Entertainment"
      }
    ],
    "sg:phone": "+1 617 576 6199",
    "sg:postcode": "02139",
    "sg:province": "MA",
    "sg:tags": [
      "trainer"
    ],
    "wof:name": "Bennett William Ira MD",
    "wof:placetype": "venue"
  },
  "geometry": {"coordinates":[-71.109122,42.368094],"type":"Point"}
}
