{
  "type": "Feature",
  "properties": {
    "iso:country":"US",
    "sg:address":"136 Cranberry Hwy",
    "sg:city":"Orleans",
    "sg:classifiers":[
        {
            "category":"Personal",
            "subcategory":"Beauty Salon",
            "type":"Services"
        }
    ],
    "sg:phone":"+1 508 255 1760",
    "sg:postcode":"02653",
    "sg:province":"MA",
    "wof:name":"Tom's Hairstyling",
    "wof:placetype":"venue"
},
  "geometry": {"coordinates":[-69.993833,41.785122],"type":"Point"}
}