{
  "type": "Feature",
  "properties": {
    "addr:full": "110 Francis St Boston MA 02215",
    "addr:housenumber": "110",
    "addr:postcode": "02215",
    "addr:street": "Francis St",
    "iso:country": "US",
    "sg:address": "110 Francis St",
    "sg:city": "Boston",
    "sg:classifiers": [
      {
        "category": "Health Services",
        "subcategory": "Doctor",
        "type": "Services"
      }
    ],
    "sg:phone": "+1 617 632 8990",
    "sg:postcode": "02215",
    "sg:province": "MA",
    "wof:name": "Cady Blake MD",
    "wof:placetype": "venue"
  },
  "geometry": {"coordinates":[-71.109398,42.337002],"type":"Point"}
}
