{
  "type": "Feature",
  "properties": {
    "addr:full": "12 Furness Cir Wakefield MA 01880",
    "addr:housenumber": "12",
    "addr:postcode": "01880",
    "addr:street": "Furness Cir",
    "iso:country": "US",
    "sg:address": "12 Furness Cir",
    "sg:city": "Wakefield",
    "sg:classifiers": [
      {
        "category": "Arts \u0026 Performance",
        "subcategory": "Theater",
        "type": "Entertainment"
      }
    ],
    "sg:phone": "+1   ",
    "sg:postcode": "01880",
    "sg:province": "MA",
    "sg:tags": [
      "group"
    ],
    "wof:name": "Sound Sensation",
    "wof:placetype": "venue"
  },
  "geometry": {"coordinates":[-71.059802,42.481831],"type":"Point"}
}
