{
  "type": "Feature",
  "properties": {
    "addr:full":"1895 River St Hyde Park MA 02136",
    "addr:housenumber":"1895",
    "addr:postcode":"02136",
    "addr:street":"River St",
    "iso:country":"US",
    "sg:address":"1895 River St",
    "sg:city":"Hyde Park",
    "sg:classifiers":[
        {
            "category":"Wholesale",
            "subcategory":"Metals & Minerals",
            "type":"Manufacturing & Wholesale Goods"
        }
    ],
    "sg:phone":"+1 617 333 9621",
    "sg:postcode":"02136",
    "sg:province":"MA",
    "sg:tags":[
        "pipe"
    ],
    "sg:website":"www.advancedpipe.com",
    "wof:name":"Advanced Pipe Inspection",
    "wof:placetype":"venue"
},
  "geometry": {"coordinates":[-71.14150100000001,42.243259],"type":"Point"}
}