{
  "type": "Feature",
  "properties": {
    "iso:country":"US",
    "sg:address":"850 Millbury St",
    "sg:city":"Worcester",
    "sg:classifiers":[
        {
            "category":"Retail",
            "subcategory":"Repair Shop",
            "type":"Services"
        }
    ],
    "sg:phone":"+1 508 756 0180",
    "sg:postcode":"01607",
    "sg:province":"MA",
    "sg:tags":[
        "lock",
        "locksmith"
    ],
    "wof:name":"Village Locksmith",
    "wof:placetype":"venue"
},
  "geometry": {"coordinates":[-71.794922,42.232948],"type":"Point"}
}