{
  "type": "Feature",
  "properties": {
    "addr:full":"109 Bullock St New Bedford MA 02740",
    "addr:housenumber":"109",
    "addr:postcode":"02740",
    "addr:street":"Bullock St",
    "iso:country":"US",
    "sg:address":"109 Bullock St",
    "sg:city":"New Bedford",
    "sg:classifiers":[
        {
            "category":"Home & Garden",
            "subcategory":"Building Materials",
            "type":"Retail Goods"
        }
    ],
    "sg:phone":"+1 508 993 7610",
    "sg:postcode":"02740",
    "sg:province":"MA",
    "sg:tags":[
        "door"
    ],
    "wof:name":"B & M Garage Doors",
    "wof:placetype":"venue"
},
  "geometry": {"coordinates":[-70.940341,41.651029],"type":"Point"}
}