{
  "type": "Feature",
  "properties": {
    "iso:country":"US",
    "sg:address":"1322 Main St",
    "sg:city":"Concord",
    "sg:classifiers":[
        {
            "category":"Government",
            "subcategory":"Office",
            "type":"Public Place"
        }
    ],
    "sg:phone":"+1 978 318 0906",
    "sg:postcode":"01742",
    "sg:province":"MA",
    "sg:tags":[
        "village"
    ],
    "wof:name":"Town Of Concord",
    "wof:placetype":"venue"
},
  "geometry": {"coordinates":[-71.395478,42.4548],"type":"Point"}
}