{
  "type": "Feature",
  "properties": {
    "addr:full": "20 Braintree Hill Park Braintree MA 02184",
    "addr:housenumber": "20",
    "addr:postcode": "02184",
    "addr:street": "Braintree Hill Park",
    "iso:country": "US",
    "sg:address": "20 Braintree Hill Park",
    "sg:city": "Braintree",
    "sg:classifiers": [
      {
        "category": "Building \u0026 Trades",
        "subcategory": "Construction",
        "type": "Services"
      }
    ],
    "sg:phone": "+1 781 843 6790",
    "sg:postcode": "02184",
    "sg:province": "MA",
    "sg:tags": [
      "contractor"
    ],
    "wof:name": "Preformance Building Co Inc",
    "wof:placetype": "venue"
  },
  "geometry": {"coordinates":[-71.026928,42.226407],"type":"Point"}
}
