{
  "type": "Feature",
  "properties": {
    "addr:full": "373 Whitney Ave Holyoke MA 01040",
    "addr:housenumber": "373",
    "addr:postcode": "01040",
    "addr:street": "Whitney Ave",
    "iso:country": "US",
    "sg:address": "373 Whitney Ave",
    "sg:city": "Holyoke",
    "sg:classifiers": [
      {
        "category": "Manufacturing",
        "subcategory": "Tools \u0026 Machinery",
        "type": "Manufacturing \u0026 Wholesale Goods"
      }
    ],
    "sg:phone": "+1 413 536 1300",
    "sg:postcode": "01040",
    "sg:province": "MA",
    "sg:tags": [
      "machine",
      "shop"
    ],
    "sg:website": "www.marox.com",
    "wof:name": "Marox Corp",
    "wof:placetype": "venue"
  },
  "geometry": {"coordinates":[-72.646266,42.168421],"type":"Point"}
}
