{
  "type": "Feature",
  "properties": {
    "addr:full":"47 Gibson St Boston MA 02122",
    "addr:housenumber":"47",
    "addr:postcode":"02122",
    "addr:street":"Gibson St",
    "iso:country":"US",
    "sg:address":"47 Gibson St",
    "sg:city":"Boston",
    "sg:classifiers":[
        {
            "category":"Building & Trades",
            "subcategory":"Construction",
            "type":"Services"
        }
    ],
    "sg:phone":"+1   ",
    "sg:postcode":"02122",
    "sg:province":"MA",
    "sg:tags":[
        "hanging",
        "contractor"
    ],
    "wof:name":"Ql Painting Co",
    "wof:placetype":"venue"
},
  "geometry": {"coordinates":[-71.057069,42.298151],"type":"Point"}
}