{
  "type": "Feature",
  "properties": {
    "iso:country":"US",
    "sg:address":"280 Elm St",
    "sg:city":"East Longmeadow",
    "sg:classifiers":[
        {
            "category":"Home & Garden",
            "subcategory":"Garden Supply",
            "type":"Retail Goods"
        }
    ],
    "sg:phone":"+1 413 525 6137",
    "sg:postcode":"01028",
    "sg:province":"MA",
    "sg:tags":[
        "center"
    ],
    "wof:name":"Graziano Gardens",
    "wof:placetype":"venue"
},
  "geometry": {"coordinates":[-72.508028,42.079706],"type":"Point"}
}