{
  "type": "Feature",
  "properties": {
    "addr:full": "280 Elm St East Longmeadow MA 01028",
    "addr:housenumber": "280",
    "addr:postcode": "01028",
    "addr:street": "Elm St",
    "iso:country": "US",
    "ovtr:label": "Graziano Gardens, 280 Elm St East Longmeadow MA US",
    "ovtr:similarity": 2.6580440998077393,
    "sg:address": "280 Elm St",
    "sg:city": "East Longmeadow",
    "sg:classifiers": [
      {
        "category": "Home \u0026 Garden",
        "subcategory": "Garden Supply",
        "type": "Retail Goods"
      }
    ],
    "sg:phone": "+1 413 525 6137",
    "sg:postcode": "01028",
    "sg:province": "MA",
    "sg:tags": [
      "center"
    ],
    "wof:name": "Graziano Gardens",
    "wof:placetype": "venue"
  },
  "geometry": {"coordinates":[-72.508028,42.079706],"type":"Point"}
}
