{
  "type": "Feature",
  "properties": {
    "addr:full":"43 Main St Edgartown MA 02539",
    "addr:housenumber":"43",
    "addr:postcode":"02539",
    "addr:street":"Main St",
    "iso:country":"US",
    "sg:address":"43 Main St",
    "sg:city":"Edgartown",
    "sg:classifiers":[
        {
            "category":"Professional",
            "type":"Services"
        }
    ],
    "sg:phone":"+1 508 627 9439",
    "sg:postcode":"02539",
    "sg:province":"MA",
    "sg:tags":[
        "arts",
        "artist"
    ],
    "wof:name":"Edgartown Scrimshaw Co",
    "wof:placetype":"venue"
},
  "geometry": {"coordinates":[-70.513637,41.389708],"type":"Point"}
}