{
  "type": "Feature",
  "properties": {
    "iso:country":"US",
    "sg:address":"33 Gould Rd",
    "sg:city":"Bedford",
    "sg:classifiers":[
        {
            "category":"Real Estate",
            "subcategory":"Real Estate Operator",
            "type":"Services"
        }
    ],
    "sg:phone":"+1   ",
    "sg:postcode":"01730",
    "sg:province":"MA",
    "sg:tags":[
        "owner"
    ],
    "wof:name":"Joseph R Demartino",
    "wof:placetype":"venue"
},
  "geometry": {"coordinates":[-71.27028900000001,42.513257],"type":"Point"}
}