{
  "type": "Feature",
  "properties": {
    "addr:full": "11 Enterprise Rd Hyannis MA 02601",
    "addr:housenumber": "11",
    "addr:postcode": "02601",
    "addr:street": "Enterprise Rd",
    "iso:country": "US",
    "ovtr:label": "Regency Police Supply, 11 Enterprise Rd Hyannis MA US",
    "ovtr:similarity": 2.077728033065796,
    "sg:address": "11 Enterprise Rd",
    "sg:city": "Hyannis",
    "sg:classifiers": [
      {
        "category": "Shopping",
        "subcategory": "Clothing, Apparel, \u0026 Fashions",
        "type": "Retail Goods"
      }
    ],
    "sg:phone": "+1 508 790 4141",
    "sg:postcode": "02601",
    "sg:province": "MA",
    "sg:tags": [
      "uniform"
    ],
    "wof:name": "Regency Police Supply",
    "wof:placetype": "venue"
  },
  "geometry": {"coordinates":[-70.30263,41.666873],"type":"Point"}
}
