{
  "type": "Feature",
  "properties": {
    "addr:full":"505 Washington Street Boston MA 02111",
    "addr:housenumber":"505",
    "addr:postcode":"02111",
    "addr:street":"Washington Street",
    "iso:country":"US",
    "sg:address":"505 Washington Street",
    "sg:city":"Boston",
    "sg:classifiers":[
        {
            "category":"Shopping",
            "type":"Retail Goods"
        }
    ],
    "sg:postcode":"02111",
    "sg:province":"MA",
    "sg:website":"www.bostonhandmade.org",
    "wof:name":"Boston Handmade DOWNTOWN",
    "wof:placetype":"venue"
},
  "geometry": {"coordinates":[-71.061655,42.354433],"type":"Point"}
}