{
  "type": "Feature",
  "properties": {
    "addr:full": "214 Ed Clark Rd Colrain MA 01340",
    "addr:housenumber": "214",
    "addr:postcode": "01340",
    "addr:street": "Ed Clark Rd",
    "iso:country": "US",
    "sg:address": "214 Ed Clark Rd",
    "sg:city": "Colrain",
    "sg:classifiers": [
      {
        "category": "Building \u0026 Trades",
        "subcategory": "Construction",
        "type": "Services"
      }
    ],
    "sg:phone": "+1   ",
    "sg:postcode": "01340",
    "sg:province": "MA",
    "sg:tags": [
      "floor",
      "laying",
      "contractor"
    ],
    "wof:name": "Als Carpet Flooring",
    "wof:placetype": "venue"
  },
  "geometry": {"coordinates":[-72.763878,42.717144],"type":"Point"}
}
