{
  "type": "Feature",
  "properties": {
    "iso:country":"US",
    "sg:address":"300 W Yarmouth Rd",
    "sg:city":"West Yarmouth",
    "sg:classifiers":[
        {
            "category":"Professional",
            "subcategory":"Management & Consulting",
            "type":"Services"
        }
    ],
    "sg:phone":"+1 508 771 5260",
    "sg:postcode":"02673",
    "sg:province":"MA",
    "sg:tags":[
        "consultant",
        "educational"
    ],
    "wof:name":"Aucello Assoc Inc",
    "wof:placetype":"venue"
},
  "geometry": {"coordinates":[-70.229574,41.665195],"type":"Point"}
}