{
  "type": "Feature",
  "properties": {
    "addr:full": "3723 N Main St Fall River MA 02720",
    "addr:housenumber": "3723",
    "addr:postcode": "02720",
    "addr:street": "N Main St",
    "iso:country": "US",
    "sg:address": "3723 N Main St",
    "sg:city": "Fall River",
    "sg:classifiers": [
      {
        "category": "Education",
        "subcategory": "Special Training",
        "type": "Public Place"
      }
    ],
    "sg:phone": "+1 508 675 4573",
    "sg:postcode": "02720",
    "sg:province": "MA",
    "sg:tags": [
      "school",
      "language"
    ],
    "wof:name": "Inbuserv Japanese Svc",
    "wof:placetype": "venue"
  },
  "geometry": {"coordinates":[-71.124008,41.749121],"type":"Point"}
}
