{
  "type": "Feature",
  "properties": {
    "iso:country":"US",
    "sg:address":"28 South St",
    "sg:city":"Hingham",
    "sg:classifiers":[
        {
            "category":"Professional",
            "subcategory":"Computer Services",
            "type":"Services"
        }
    ],
    "sg:phone":"+1 781 740 8680",
    "sg:postcode":"02043",
    "sg:province":"MA",
    "sg:tags":[
        "consultant",
        "designer"
    ],
    "wof:name":"Rick Allen",
    "wof:placetype":"venue"
},
  "geometry": {"coordinates":[-70.889167,42.242084],"type":"Point"}
}