{
  "type": "Feature",
  "properties": {
    "iso:country":"US",
    "sg:address":"308 Central St",
    "sg:city":"Acton",
    "sg:classifiers":[
        {
            "category":"Insurance",
            "subcategory":"Hazard Insurance",
            "type":"Services"
        }
    ],
    "sg:phone":"+1 978 263 1468",
    "sg:postcode":"01720",
    "sg:province":"MA",
    "sg:tags":[
        "commercial",
        "business"
    ],
    "wof:name":"Bettinson Insrnce Agncy",
    "wof:placetype":"venue"
},
  "geometry": {"coordinates":[-71.47533,42.479057],"type":"Point"}
}