{
  "type": "Feature",
  "properties": {
    "addr:full": "1655 Boston Rd Ste B15 Springfield MA 01129",
    "addr:housenumber": "1655",
    "addr:postcode": "01129",
    "addr:street": "Boston Rd Ste B15",
    "iso:country": "US",
    "sg:address": "1655 Boston Rd Ste B15",
    "sg:city": "Springfield",
    "sg:classifiers": [
      {
        "category": "Shopping",
        "subcategory": "Jewelry",
        "type": "Retail Goods"
      },
      {
        "category": "Manufacturing",
        "subcategory": "Jewelry",
        "type": "Manufacturing \u0026 Wholesale Goods"
      }
    ],
    "sg:phone": "+1 413 543 5225",
    "sg:postcode": "01129",
    "sg:province": "MA",
    "sg:tags": [
      "stone",
      "designer",
      "watch",
      "jeweler",
      "precious",
      "semi-precious"
    ],
    "sg:website": "http://www.kay.com",
    "wof:name": "Kay Jewelers",
    "wof:placetype": "venue"
  },
  "geometry": {"coordinates":[-72.488167,42.14331],"type":"Point"}
}
