{
  "type": "Feature",
  "properties": {
    "addr:full":"537 State Hwy 28 Harwich Port MA 02646",
    "addr:housenumber":"537",
    "addr:postcode":"02646",
    "addr:street":"State Hwy 28",
    "iso:country":"US",
    "sg:address":"537 State Hwy 28",
    "sg:city":"Harwich Port",
    "sg:classifiers":[
        {
            "category":"Health Services",
            "subcategory":"Health Practitioner",
            "type":"Services"
        }
    ],
    "sg:phone":"+1 508 430 8672",
    "sg:postcode":"02646",
    "sg:province":"MA",
    "sg:tags":[
        "psychologist"
    ],
    "wof:name":"Mary Beth Lean",
    "wof:placetype":"venue"
},
  "geometry": {"coordinates":[-70.07771099999999,41.667646],"type":"Point"}
}