{
  "type": "Feature",
  "properties": {
    "iso:country":"US",
    "sg:address":"14 N Dartmouth Mall",
    "sg:city":"North Dartmouth",
    "sg:classifiers":[
        {
            "category":"Home & Garden",
            "subcategory":"Furniture",
            "type":"Retail Goods"
        }
    ],
    "sg:phone":"+1   ",
    "sg:postcode":"02747",
    "sg:province":"MA",
    "wof:name":"Saxons Furniture Co",
    "wof:placetype":"venue"
},
  "geometry": {"coordinates":[-70.99415500000001,41.641403],"type":"Point"}
}