{
  "type": "Feature",
  "properties": {
    "iso:country":"US",
    "sg:address":"30 Lynnbrook Rd",
    "sg:city":"Lynnfield",
    "sg:classifiers":[
        {
            "category":"Professional",
            "subcategory":"Research",
            "type":"Services"
        }
    ],
    "sg:phone":"+1 781 592 9700",
    "sg:postcode":"01940",
    "sg:province":"MA",
    "sg:tags":[
        "market",
        "analysis"
    ],
    "wof:name":"Boston Reader Board",
    "wof:placetype":"venue"
},
  "geometry": {"coordinates":[-70.995009,42.512088],"type":"Point"}
}