{
  "type": "Feature",
  "properties": {
    "addr:full":"888 Hancock Rd Williamstown MA 01267",
    "addr:housenumber":"888",
    "addr:postcode":"01267",
    "addr:street":"Hancock Rd",
    "iso:country":"US",
    "sg:address":"888 Hancock Rd",
    "sg:city":"Williamstown",
    "sg:classifiers":[
        {
            "category":"Wholesale",
            "subcategory":"Durable Goods & Equipment",
            "type":"Manufacturing & Wholesale Goods"
        }
    ],
    "sg:phone":"+1 413 458 7900",
    "sg:postcode":"01267",
    "sg:province":"MA",
    "sg:tags":[
        "exporter"
    ],
    "wof:name":"Exports Of Africa Inc",
    "wof:placetype":"venue"
},
  "geometry": {"coordinates":[-73.266925,42.647968],"type":"Point"}
}