{
  "type": "Feature",
  "properties": {
    "iso:country":"US",
    "sg:address":"5 Federal St",
    "sg:city":"Nantucket",
    "sg:classifiers":[
        {
            "category":"Government",
            "subcategory":"Post Office",
            "type":"Public Place"
        }
    ],
    "sg:phone":"+1 508 228 1067",
    "sg:postcode":"02554",
    "sg:province":"MA",
    "wof:name":"US Post Office",
    "wof:placetype":"venue"
},
  "geometry": {"coordinates":[-70.098983,41.283943],"type":"Point"}
}