{
  "type": "Feature",
  "properties": {
    "addr:full": "257 Hokum Rock Rd Dennis MA 02660",
    "addr:housenumber": "257",
    "addr:postcode": "02660",
    "addr:street": "Hokum Rock Rd",
    "iso:country": "US",
    "sg:address": "257 Hokum Rock Rd",
    "sg:city": "Dennis",
    "sg:classifiers": [
      {
        "category": "Professional",
        "subcategory": "Business Services",
        "type": "Services"
      }
    ],
    "sg:phone": "+1   ",
    "sg:postcode": "02660",
    "sg:province": "MA",
    "sg:tags": [
      "appraiser"
    ],
    "wof:name": "Agagails Knieriem Movers",
    "wof:placetype": "venue"
  },
  "geometry": {"coordinates":[-70.163011,41.730482],"type":"Point"}
}
