{
  "type": "Feature",
  "properties": {
    "iso:country":"US",
    "sg:address":"40 Harrison Ave Unit 3B",
    "sg:city":"Boston",
    "sg:classifiers":[
        {
            "category":"Banks & Credit Unions",
            "subcategory":"Financial Services",
            "type":"Services"
        }
    ],
    "sg:phone":"+1 617 426 3331",
    "sg:postcode":"02111",
    "sg:province":"MA",
    "sg:tags":[
        "broker",
        "mortgage"
    ],
    "wof:name":"US Financial Corp",
    "wof:placetype":"venue"
},
  "geometry": {"coordinates":[-71.061172,42.351586],"type":"Point"}
}