{
  "type": "Feature",
  "properties": {
    "iso:country":"US",
    "sg:address":"1035 Saratoga St",
    "sg:city":"Boston",
    "sg:classifiers":[
        {
            "category":"Food & Beverages",
            "subcategory":"Liquor & Beverages",
            "type":"Retail Goods"
        }
    ],
    "sg:phone":"+1   ",
    "sg:postcode":"02128",
    "sg:province":"MA",
    "sg:tags":[
        "alcoholic"
    ],
    "wof:name":"Woodys Inc",
    "wof:placetype":"venue"
},
  "geometry": {"coordinates":[-71.00535000000001,42.386119],"type":"Point"}
}