{
  "type": "Feature",
  "properties": {
    "addr:full":"95 Washington St Canton MA 02021",
    "addr:housenumber":"95",
    "addr:postcode":"02021",
    "addr:street":"Washington St",
    "iso:country":"US",
    "sg:address":"95 Washington St",
    "sg:city":"Canton",
    "sg:classifiers":[
        {
            "category":"Professional",
            "subcategory":"Lawyer & Legal Services",
            "type":"Services"
        }
    ],
    "sg:phone":"+1 781 575 0037",
    "sg:postcode":"02021",
    "sg:province":"MA",
    "wof:name":"Levine Roger L Attorney At Law",
    "wof:placetype":"venue"
},
  "geometry": {"coordinates":[-71.14859800000001,42.1408],"type":"Point"}
}