{
  "type": "Feature",
  "properties": {
    "iso:country":"US",
    "sg:address":"168 Great Rd",
    "sg:city":"Bedford",
    "sg:classifiers":[
        {
            "category":"Building & Trades",
            "subcategory":"Locksmith",
            "type":"Services"
        }
    ],
    "sg:phone":"+1 781 301 6031",
    "sg:postcode":"01730",
    "sg:province":"MA",
    "sg:tags":[
        "key"
    ],
    "wof:name":"Great Rd Emerency Locksmith",
    "wof:placetype":"venue"
},
  "geometry": {"coordinates":[-71.274687,42.490216],"type":"Point"}
}