{
  "type": "Feature",
  "properties": {
    "addr:full": "168 Great Rd Bedford MA 01730",
    "addr:housenumber": "168",
    "addr:postcode": "01730",
    "addr:street": "Great Rd",
    "iso:country": "US",
    "sg:address": "168 Great Rd",
    "sg:city": "Bedford",
    "sg:classifiers": [
      {
        "category": "Building \u0026 Trades",
        "subcategory": "Locksmith",
        "type": "Services"
      }
    ],
    "sg:phone": "+1 781 301 6031",
    "sg:postcode": "01730",
    "sg:province": "MA",
    "sg:tags": [
      "key"
    ],
    "wof:name": "Great Rd Emerency Locksmith",
    "wof:placetype": "venue"
  },
  "geometry": {"coordinates":[-71.274687,42.490216],"type":"Point"}
}
