{
  "type": "Feature",
  "properties": {
    "addr:full":"31 Sunrise Ave Plymouth MA 02360",
    "addr:housenumber":"31",
    "addr:postcode":"02360",
    "addr:street":"Sunrise Ave",
    "iso:country":"US",
    "sg:address":"31 Sunrise Ave",
    "sg:city":"Plymouth",
    "sg:classifiers":[
        {
            "category":"Building & Trades",
            "subcategory":"Construction",
            "type":"Services"
        }
    ],
    "sg:phone":"+1   ",
    "sg:postcode":"02360",
    "sg:province":"MA",
    "sg:tags":[
        "floor",
        "laying",
        "contractor"
    ],
    "wof:name":"John Ricardo Hardwood Floors",
    "wof:placetype":"venue"
},
  "geometry": {"coordinates":[-70.63538699999999,41.940144],"type":"Point"}
}