{
  "type": "Feature",
  "properties": {
    "addr:full": "45 N Main St Falmouth MA 02540",
    "addr:housenumber": "45",
    "addr:postcode": "02540",
    "addr:street": "N Main St",
    "iso:country": "US",
    "sg:address": "45 N Main St",
    "sg:city": "Falmouth",
    "sg:classifiers": [
      {
        "category": "Building \u0026 Trades",
        "subcategory": "Construction",
        "type": "Services"
      }
    ],
    "sg:phone": "+1 508 495 3888",
    "sg:postcode": "02540",
    "sg:province": "MA",
    "sg:tags": [
      "home",
      "builder"
    ],
    "wof:name": "Oolala Home",
    "wof:placetype": "venue"
  },
  "geometry": {"coordinates":[-70.621473,41.556053],"type":"Point"}
}
