{
  "type": "Feature",
  "properties": {
    "iso:country":"US",
    "sg:address":"45 N Main St",
    "sg:city":"Falmouth",
    "sg:classifiers":[
        {
            "category":"Building & Trades",
            "subcategory":"Construction",
            "type":"Services"
        }
    ],
    "sg:phone":"+1 508 495 3888",
    "sg:postcode":"02540",
    "sg:province":"MA",
    "sg:tags":[
        "home",
        "builder"
    ],
    "wof:name":"Oolala Home",
    "wof:placetype":"venue"
},
  "geometry": {"coordinates":[-70.62147299999999,41.556053],"type":"Point"}
}