{
  "type": "Feature",
  "properties": {
    "addr:full":"250 Beacon St Boston MA 02116",
    "addr:housenumber":"250",
    "addr:postcode":"02116",
    "addr:street":"Beacon St",
    "iso:country":"US",
    "sg:address":"250 Beacon St",
    "sg:city":"Boston",
    "sg:classifiers":[
        {
            "category":"Professional",
            "subcategory":"Research",
            "type":"Services"
        }
    ],
    "sg:phone":"+1 617 267 9029",
    "sg:postcode":"02116",
    "sg:province":"MA",
    "sg:tags":[
        "information",
        "medical"
    ],
    "wof:name":"Jane C Weeks",
    "wof:placetype":"venue"
},
  "geometry": {"coordinates":[-71.079806,42.353449],"type":"Point"}
}