{
  "type": "Feature",
  "properties": {
    "addr:full": "20 Crystal St Melrose MA 02176",
    "addr:housenumber": "20",
    "addr:postcode": "02176",
    "addr:street": "Crystal St",
    "iso:country": "US",
    "sg:address": "20 Crystal St",
    "sg:city": "Melrose",
    "sg:classifiers": [
      {
        "category": "Wholesale",
        "subcategory": "Computers",
        "type": "Manufacturing \u0026 Wholesale Goods"
      }
    ],
    "sg:phone": "+1 781 665 5205",
    "sg:postcode": "02176",
    "sg:province": "MA",
    "sg:tags": [
      "computer-wholesale",
      "manufacturer"
    ],
    "wof:name": "Microsystems",
    "wof:placetype": "venue"
  },
  "geometry": {"coordinates":[-71.062946,42.461757],"type":"Point"}
}
