{
  "type": "Feature",
  "properties": {
    "iso:country":"US",
    "sg:address":"1504 Providence Hwy",
    "sg:city":"Norwood",
    "sg:classifiers":[
        {
            "category":"Wholesale",
            "subcategory":"Durable Goods & Equipment",
            "type":"Manufacturing & Wholesale Goods"
        }
    ],
    "sg:phone":"+1 781 769 9988",
    "sg:postcode":"02062",
    "sg:province":"MA",
    "sg:tags":[
        "representative",
        "manufacturer"
    ],
    "wof:name":"Serpa Corp",
    "wof:placetype":"venue"
},
  "geometry": {"coordinates":[-71.200271,42.160322],"type":"Point"}
}