{
  "type": "Feature",
  "properties": {
    "iso:country":"US",
    "sg:address":"150 Grossman Dr",
    "sg:city":"Braintree",
    "sg:classifiers":[
        {
            "category":"Professional",
            "subcategory":"Employment Agencies",
            "type":"Services"
        }
    ],
    "sg:phone":"+1 781 380 0989",
    "sg:postcode":"02184",
    "sg:province":"MA",
    "sg:tags":[
        "opportunity"
    ],
    "wof:name":"Manpower Inc",
    "wof:placetype":"venue"
},
  "geometry": {"coordinates":[-70.999447,42.210707],"type":"Point"}
}