{
  "type": "Feature",
  "properties": {
    "addr:full":"580 Mount Auburn St Watertown MA 02472",
    "addr:housenumber":"580",
    "addr:postcode":"02472",
    "addr:street":"Mount Auburn St",
    "iso:country":"US",
    "sg:address":"580 Mount Auburn St",
    "sg:city":"Watertown",
    "sg:classifiers":[
        {
            "category":"Restaurant",
            "type":"Food & Drink"
        }
    ],
    "sg:menulink":"http://www.allmenus.com/ma/watertown/292250-jasmine/menu/",
    "sg:phone":"+1 617 923 3999",
    "sg:postcode":"02472",
    "sg:province":"MA",
    "sg:tags":[
        "middle",
        "eastern"
    ],
    "wof:name":"Jasmine",
    "wof:placetype":"venue"
},
  "geometry": {"coordinates":[-71.14488,42.375192],"type":"Point"}
}