{
  "type": "Feature",
  "properties": {
    "iso:country":"US",
    "sg:address":"13 Pond Rd",
    "sg:city":"Gloucester",
    "sg:classifiers":[
        {
            "category":"Real Estate",
            "subcategory":"Real Estate Services",
            "type":"Services"
        },
        {
            "category":"Real Estate",
            "subcategory":"Real Estate Agent",
            "type":"Services"
        }
    ],
    "sg:phone":"+1 978 281 1111",
    "sg:postcode":"01930",
    "sg:province":"MA",
    "sg:tags":[
        "management"
    ],
    "wof:name":"Vadala Real State Appraisals",
    "wof:placetype":"venue"
},
  "geometry": {"coordinates":[-70.6395,42.629003],"type":"Point"}
}