{
  "type": "Feature",
  "properties": {
    "addr:full":"108 Greenpoint Cir Chicopee MA 01020",
    "addr:housenumber":"108",
    "addr:postcode":"01020",
    "addr:street":"Greenpoint Cir",
    "iso:country":"US",
    "sg:address":"108 Greenpoint Cir",
    "sg:city":"Chicopee",
    "sg:classifiers":[
        {
            "category":"Professional",
            "subcategory":"Lawyer & Legal Services",
            "type":"Services"
        }
    ],
    "sg:phone":"+1 413 536 6445",
    "sg:postcode":"01020",
    "sg:province":"MA",
    "sg:tags":[
        "attorney",
        "practice"
    ],
    "sg:website":"http://www.invention-patent.com",
    "wof:name":"Collier, Stan Law Office Of",
    "wof:placetype":"venue"
},
  "geometry": {"coordinates":[-72.567719,42.199039],"type":"Point"}
}