{
  "type": "Feature",
  "properties": {
    "addr:full": "15 Auburn Ct Watertown MA 02472",
    "addr:housenumber": "15",
    "addr:postcode": "02472",
    "addr:street": "Auburn Ct",
    "iso:country": "US",
    "sg:address": "15 Auburn Ct",
    "sg:city": "Watertown",
    "sg:classifiers": [
      {
        "category": "Professional",
        "subcategory": "Accounting \u0026 Tax Preparation",
        "type": "Services"
      }
    ],
    "sg:phone": "+1 617 923 6258",
    "sg:postcode": "02472",
    "sg:province": "MA",
    "sg:tags": [
      "bookkeeping",
      "billing"
    ],
    "wof:name": "Auburn Bookkeeping",
    "wof:placetype": "venue"
  },
  "geometry": {"coordinates":[-71.180543,42.366955],"type":"Point"}
}
