{
  "type": "Feature",
  "properties": {
    "addr:full":"127 W Central St Natick MA 01760",
    "addr:housenumber":"127",
    "addr:postcode":"01760",
    "addr:street":"W Central St",
    "iso:country":"US",
    "sg:address":"127 W Central St",
    "sg:city":"Natick",
    "sg:classifiers":[
        {
            "category":"Personal",
            "subcategory":"Beauty Salon",
            "type":"Services"
        }
    ],
    "sg:phone":"+1 508 653 7230",
    "sg:postcode":"01760",
    "sg:province":"MA",
    "wof:name":"Total Image",
    "wof:placetype":"venue"
},
  "geometry": {"coordinates":[-71.370206,42.283527],"type":"Point"}
}