{
  "type": "Feature",
  "properties": {
    "addr:full": "280 W Broadway Boston MA 02127",
    "addr:housenumber": "280",
    "addr:postcode": "02127",
    "addr:street": "W Broadway",
    "iso:country": "US",
    "sg:address": "280 W Broadway",
    "sg:city": "Boston",
    "sg:classifiers": [
      {
        "category": "Building \u0026 Trades",
        "subcategory": "Locksmith",
        "type": "Services"
      }
    ],
    "sg:phone": "+1 617 272 4331",
    "sg:postcode": "02127",
    "sg:province": "MA",
    "sg:tags": [
      "key"
    ],
    "wof:name": "Locksmith Services",
    "wof:placetype": "venue"
  },
  "geometry": {"coordinates":[-71.051127,42.339185],"type":"Point"}
}
