{
  "type": "Feature",
  "properties": {
    "addr:full": "1126 Main St Brockton MA 02301",
    "addr:housenumber": "1126",
    "addr:postcode": "02301",
    "addr:street": "Main St",
    "iso:country": "US",
    "sg:address": "1126 Main St",
    "sg:city": "Brockton",
    "sg:classifiers": [
      {
        "category": "Utilities",
        "subcategory": "Mobile Phone",
        "type": "Services"
      }
    ],
    "sg:phone": "+1   ",
    "sg:postcode": "02301",
    "sg:province": "MA",
    "sg:tags": [
      "communication",
      "radiotelephone"
    ],
    "wof:name": "Cabo Connection",
    "wof:placetype": "venue"
  },
  "geometry": {"coordinates":[-71.015224,42.06321],"type":"Point"}
}
