{
  "type": "Feature",
  "properties": {
    "addr:full": "213 Powell Rd Cummington MA 01026",
    "addr:housenumber": "213",
    "addr:postcode": "01026",
    "addr:street": "Powell Rd",
    "iso:country": "US",
    "sg:address": "213 Powell Rd",
    "sg:city": "Cummington",
    "sg:classifiers": [
      {
        "category": "Food \u0026 Beverages",
        "subcategory": "Bakery",
        "type": "Retail Goods"
      }
    ],
    "sg:phone": "+1 413 634 2201",
    "sg:postcode": "01026",
    "sg:province": "MA",
    "sg:tags": [
      "baker"
    ],
    "wof:name": "Bread Euphoria",
    "wof:placetype": "venue"
  },
  "geometry": {"coordinates":[-72.949099,42.459578],"type":"Point"}
}
