{
  "type": "Feature",
  "properties": {
    "iso:country":"US",
    "sg:address":"84 Free St",
    "sg:city":"Hingham",
    "sg:classifiers":[
        {
            "category":"Building & Trades",
            "subcategory":"Construction",
            "type":"Services"
        }
    ],
    "sg:phone":"+1 781 749 5571",
    "sg:postcode":"02043",
    "sg:province":"MA",
    "sg:tags":[
        "general",
        "contractor"
    ],
    "wof:name":"Ewell Construction",
    "wof:placetype":"venue"
},
  "geometry": {"coordinates":[-70.878012,42.217137],"type":"Point"}
}