{
  "type": "Feature",
  "properties": {
    "iso:country":"US",
    "sg:address":"111 Huntington Ave",
    "sg:city":"Boston",
    "sg:classifiers":[
        {
            "category":"Professional",
            "subcategory":"Lawyer & Legal Services",
            "type":"Services"
        }
    ],
    "sg:phone":"+1 617 239 0389",
    "sg:postcode":"02115",
    "sg:province":"MA",
    "sg:tags":[
        "attorney"
    ],
    "wof:name":"Walter St Onge III",
    "wof:placetype":"venue"
},
  "geometry": {"coordinates":[-71.081382,42.345837],"type":"Point"}
}