{
  "type": "Feature",
  "properties": {
    "addr:full": "11 John Rd Sutton MA 01590",
    "addr:housenumber": "11",
    "addr:postcode": "01590",
    "addr:street": "John Rd",
    "iso:country": "US",
    "sg:address": "11 John Rd",
    "sg:city": "Sutton",
    "sg:classifiers": [
      {
        "category": "Professional",
        "subcategory": "Research",
        "type": "Services"
      }
    ],
    "sg:phone": "+1 508 581 9880",
    "sg:postcode": "01590",
    "sg:province": "MA",
    "sg:tags": [
      "environmental",
      "ecological"
    ],
    "wof:name": "Zebra Environmental Corp",
    "wof:placetype": "venue"
  },
  "geometry": {"coordinates":[-71.759889,42.175321],"type":"Point"}
}
