{
  "type": "Feature",
  "properties": {
    "addr:full":"52 Haven St Dover MA 02030",
    "addr:housenumber":"52",
    "addr:postcode":"02030",
    "addr:street":"Haven St",
    "iso:country":"US",
    "sg:address":"52 Haven St",
    "sg:city":"Dover",
    "sg:classifiers":[
        {
            "category":"Professional",
            "subcategory":"Management & Consulting",
            "type":"Services"
        },
        {
            "category":"Professional",
            "subcategory":"Advertising",
            "type":"Services"
        }
    ],
    "sg:phone":"+1 508 785 2938",
    "sg:postcode":"02030",
    "sg:province":"MA",
    "sg:tags":[
        "marketing",
        "program",
        "consultant"
    ],
    "sg:website":"http://www.tfmconsultants.com",
    "wof:name":"Technology Finance Mktg Cons",
    "wof:placetype":"venue"
},
  "geometry": {"coordinates":[-71.284599,42.25045],"type":"Point"}
}