{
  "type": "Feature",
  "properties": {
    "addr:full": "121 Ball St Northborough MA 01532",
    "addr:housenumber": "121",
    "addr:postcode": "01532",
    "addr:street": "Ball St",
    "iso:country": "US",
    "sg:address": "121 Ball St",
    "sg:city": "Northborough",
    "sg:classifiers": [
      {
        "category": "Farming",
        "subcategory": "Farm",
        "type": "Manufacturing \u0026 Wholesale Goods"
      }
    ],
    "sg:phone": "+1   ",
    "sg:postcode": "01532",
    "sg:province": "MA",
    "wof:name": "Appleway Farm",
    "wof:placetype": "venue"
  },
  "geometry": {"coordinates":[-71.67771,42.337508],"type":"Point"}
}
