{
  "type": "Feature",
  "properties": {
    "addr:full":"93 N Main St Fl 1 Andover MA 01810",
    "addr:housenumber":"93;1",
    "addr:postcode":"01810",
    "addr:street":"N Main St",
    "iso:country":"US",
    "sg:address":"93 N Main St Fl 1",
    "sg:city":"Andover",
    "sg:classifiers":[
        {
            "category":"Personal",
            "subcategory":"Beauty Salon",
            "type":"Services"
        },
        {
            "category":"Personal",
            "subcategory":"Nail Salon",
            "type":"Services"
        }
    ],
    "sg:phone":"+1 978 475 0745",
    "sg:postcode":"01810",
    "sg:province":"MA",
    "sg:website":"http://www.starnail.com",
    "wof:name":"Star Nails Beauty Salon",
    "wof:placetype":"venue"
},
  "geometry": {"coordinates":[-71.14270399999999,42.659104],"type":"Point"}
}