{
  "type": "Feature",
  "properties": {
    "iso:country":"US",
    "sg:address":"323 Turnpike St",
    "sg:city":"Canton",
    "sg:classifiers":[
        {
            "category":"Education",
            "subcategory":"Dance Studio",
            "type":"Public Place"
        }
    ],
    "sg:phone":"+1 781 575 1775",
    "sg:postcode":"02021",
    "sg:province":"MA",
    "wof:name":"Studio Of Performing Arts",
    "wof:placetype":"venue"
},
  "geometry": {"coordinates":[-71.11205099999999,42.17467],"type":"Point"}
}