{
  "type": "Feature",
  "properties": {
    "iso:country":"US",
    "sg:address":"104 Russell St",
    "sg:city":"Hadley",
    "sg:classifiers":[
        {
            "category":"Education",
            "subcategory":"Special Training",
            "type":"Public Place"
        }
    ],
    "sg:phone":"+1 413 582 0193",
    "sg:postcode":"01035",
    "sg:province":"MA",
    "sg:tags":[
        "educational"
    ],
    "wof:name":"North Star",
    "wof:placetype":"venue"
},
  "geometry": {"coordinates":[-72.59445700000001,42.342092],"type":"Point"}
}