{
  "type": "Feature",
  "properties": {
    "iso:country":"US",
    "sg:address":"13 Crompton St",
    "sg:city":"Acushnet",
    "sg:classifiers":[
        {
            "category":"Professional",
            "subcategory":"Business Services",
            "type":"Services"
        }
    ],
    "sg:phone":"+1   ",
    "sg:postcode":"02743",
    "sg:province":"MA",
    "wof:name":"Acushnet Realty Group",
    "wof:placetype":"venue"
},
  "geometry": {"coordinates":[-70.91013599999999,41.683641],"type":"Point"}
}