{
  "type": "Feature",
  "properties": {
    "addr:full": "13 Crompton St Acushnet MA 02743",
    "addr:housenumber": "13",
    "addr:postcode": "02743",
    "addr:street": "Crompton St",
    "iso:country": "US",
    "sg:address": "13 Crompton St",
    "sg:city": "Acushnet",
    "sg:classifiers": [
      {
        "category": "Professional",
        "subcategory": "Business Services",
        "type": "Services"
      }
    ],
    "sg:phone": "+1   ",
    "sg:postcode": "02743",
    "sg:province": "MA",
    "wof:name": "Acushnet Realty Group",
    "wof:placetype": "venue"
  },
  "geometry": {"coordinates":[-70.910136,41.683641],"type":"Point"}
}
