{
  "type": "Feature",
  "properties": {
    "addr:full": "81 Glenmore St Springfield MA 01129",
    "addr:housenumber": "81",
    "addr:postcode": "01129",
    "addr:street": "Glenmore St",
    "iso:country": "US",
    "sg:address": "81 Glenmore St",
    "sg:city": "Springfield",
    "sg:classifiers": [
      {
        "category": "Shopping",
        "type": "Retail Goods"
      }
    ],
    "sg:phone": "+1 413 543 1328",
    "sg:postcode": "01129",
    "sg:province": "MA",
    "sg:tags": [
      "cosmetic",
      "perfume"
    ],
    "wof:name": "Win-Win Enterprise",
    "wof:placetype": "venue"
  },
  "geometry": {"coordinates":[-72.497884,42.14539],"type":"Point"}
}
