{
  "type": "Feature",
  "properties": {
    "addr:full": "41 Winter Street Suite 55 Boston MA 02108",
    "addr:housenumber": "41;55",
    "addr:postcode": "02108",
    "addr:street": "Winter Street Suite",
    "iso:country": "US",
    "sg:address": "41 Winter Street Suite 55",
    "sg:city": "Boston",
    "sg:classifiers": [
      {
        "category": "Education",
        "subcategory": "School",
        "type": "Public Place"
      }
    ],
    "sg:phone": "+1 617 292 7777",
    "sg:postcode": "02108",
    "sg:province": "MA",
    "wof:name": "Drink Master Bartending School",
    "wof:placetype": "venue"
  },
  "geometry": {"coordinates":[-71.061794,42.356044],"type":"Point"}
}
