{
  "type": "Feature",
  "properties": {
    "iso:country":"US",
    "sg:address":"9 Pebblebrook Way",
    "sg:city":"Lakeville",
    "sg:classifiers":[
        {
            "category":"Building & Trades",
            "subcategory":"Construction",
            "type":"Services"
        }
    ],
    "sg:phone":"+1 508 947 8003",
    "sg:postcode":"02347",
    "sg:province":"MA",
    "sg:tags":[
        "carpenter"
    ],
    "wof:name":"RSBH Construction",
    "wof:placetype":"venue"
},
  "geometry": {"coordinates":[-70.971734,41.801898],"type":"Point"}
}