{
  "type": "Feature",
  "properties": {
    "iso:country":"US",
    "sg:address":"134 Cashman Rd",
    "sg:city":"Brockton",
    "sg:classifiers":[
        {
            "category":"Utilities",
            "subcategory":"Telephone",
            "type":"Services"
        }
    ],
    "sg:phone":"+1 508 583 0676",
    "sg:postcode":"02301",
    "sg:province":"MA",
    "sg:tags":[
        "telecommunication"
    ],
    "wof:name":"Global Enterprises",
    "wof:placetype":"venue"
},
  "geometry": {"coordinates":[-71.06382000000001,42.091847],"type":"Point"}
}