{
  "type": "Feature",
  "properties": {
    "addr:full": "28 Smith St Newburyport MA 01950",
    "addr:housenumber": "28",
    "addr:postcode": "01950",
    "addr:street": "Smith St",
    "iso:country": "US",
    "sg:address": "28 Smith St",
    "sg:city": "Newburyport",
    "sg:classifiers": [
      {
        "category": "Wholesale",
        "subcategory": "Computers",
        "type": "Manufacturing \u0026 Wholesale Goods"
      }
    ],
    "sg:phone": "+1 978 465 3895",
    "sg:postcode": "01950",
    "sg:province": "MA",
    "wof:name": "US Robotics Palm Computing",
    "wof:placetype": "venue"
  },
  "geometry": {"coordinates":[-70.864799,42.8083],"type":"Point"}
}
