{
  "type": "Feature",
  "properties": {
    "iso:country":"US",
    "sg:address":"35 Highland Ave",
    "sg:city":"Seekonk",
    "sg:classifiers":[
        {
            "category":"Building & Trades",
            "subcategory":"Construction",
            "type":"Services"
        }
    ],
    "sg:phone":"+1 508 336 9211",
    "sg:postcode":"02771",
    "sg:province":"MA",
    "sg:tags":[
        "general",
        "contractor"
    ],
    "wof:name":"Poulin Construction",
    "wof:placetype":"venue"
},
  "geometry": {"coordinates":[-71.331017,41.796377],"type":"Point"}
}