{
  "type": "Feature",
  "properties": {
    "iso:country":"US",
    "sg:address":"486 Common St",
    "sg:city":"Belmont",
    "sg:classifiers":[
        {
            "category":"Real Estate",
            "subcategory":"Real Estate Agent",
            "type":"Services"
        }
    ],
    "sg:phone":"+1 617 924 6900",
    "sg:postcode":"02478",
    "sg:province":"MA",
    "sg:website":"http://www.century21.com",
    "wof:name":"Century 21 Adams",
    "wof:placetype":"venue"
},
  "geometry": {"coordinates":[-71.17493399999999,42.379958],"type":"Point"}
}