{
  "type": "Feature",
  "properties": {
    "addr:full":"14 Francine Rd Acton MA 01720",
    "addr:housenumber":"14",
    "addr:postcode":"01720",
    "addr:street":"Francine Rd",
    "iso:country":"US",
    "sg:address":"14 Francine Rd",
    "sg:city":"Acton",
    "sg:classifiers":[
        {
            "category":"Education",
            "subcategory":"Special Training",
            "type":"Public Place"
        }
    ],
    "sg:phone":"+1   ",
    "sg:postcode":"01720",
    "sg:province":"MA",
    "wof:name":"Learning Success Helpline Inc",
    "wof:placetype":"venue"
},
  "geometry": {"coordinates":[-71.45086999999999,42.470938],"type":"Point"}
}