{
  "type": "Feature",
  "properties": {
    "iso:country":"US",
    "sg:address":"140 Balcom St",
    "sg:city":"Mansfield",
    "sg:classifiers":[
        {
            "category":"Food & Beverages",
            "subcategory":"Bakery",
            "type":"Retail Goods"
        }
    ],
    "sg:phone":"+1 508 543 1880",
    "sg:postcode":"02048",
    "sg:province":"MA",
    "sg:tags":[
        "baker"
    ],
    "wof:name":"Fran's Apple Pies",
    "wof:placetype":"venue"
},
  "geometry": {"coordinates":[-71.252207,41.999615],"type":"Point"}
}