{
  "type": "Feature",
  "properties": {
    "addr:full":"612 Center St Jamaica Plain MA 02130",
    "addr:housenumber":"612",
    "addr:postcode":"02130",
    "addr:street":"Center St",
    "iso:country":"US",
    "sg:address":"612 Center St",
    "sg:city":"Jamaica Plain",
    "sg:classifiers":[
        {
            "category":"Health Services",
            "subcategory":"Dentist",
            "type":"Services"
        }
    ],
    "sg:phone":"+1 617 524 4400",
    "sg:postcode":"02130",
    "sg:province":"MA",
    "sg:website":"www.gentledental.com",
    "wof:name":"Gentle Dental",
    "wof:placetype":"venue"
},
  "geometry": {"coordinates":[-71.114006,42.314294],"type":"Point"}
}