{
  "type": "Feature",
  "properties": {
    "iso:country":"US",
    "sg:address":"145 Lincoln Rd",
    "sg:city":"Lincoln",
    "sg:classifiers":[
        {
            "category":"Shopping",
            "subcategory":"Gifts & Souvenirs",
            "type":"Retail Goods"
        }
    ],
    "sg:phone":"+1 781 259 0544",
    "sg:postcode":"01773",
    "sg:province":"MA",
    "sg:tags":[
        "shop"
    ],
    "wof:name":"Something Special",
    "wof:placetype":"venue"
},
  "geometry": {"coordinates":[-71.325636,42.414203],"type":"Point"}
}