{
  "type": "Feature",
  "properties": {
    "addr:full": "145 Lincoln Rd Lincoln MA 01773",
    "addr:housenumber": "145",
    "addr:postcode": "01773",
    "addr:street": "Lincoln Rd",
    "iso:country": "US",
    "ovtr:label": "Something Special, 145 Lincoln Rd Lincoln MA US",
    "ovtr:similarity": 3.774967908859253,
    "sg:address": "145 Lincoln Rd",
    "sg:city": "Lincoln",
    "sg:classifiers": [
      {
        "category": "Shopping",
        "subcategory": "Gifts \u0026 Souvenirs",
        "type": "Retail Goods"
      }
    ],
    "sg:phone": "+1 781 259 0544",
    "sg:postcode": "01773",
    "sg:province": "MA",
    "sg:tags": [
      "shop"
    ],
    "wof:name": "Something Special",
    "wof:placetype": "venue"
  },
  "geometry": {"coordinates":[-71.325636,42.414203],"type":"Point"}
}
