{
  "type": "Feature",
  "properties": {
    "addr:full":"187 Sanborn Ln Reading MA 01867",
    "addr:housenumber":"187",
    "addr:postcode":"01867",
    "addr:street":"Sanborn Ln",
    "iso:country":"US",
    "sg:address":"187 Sanborn Ln",
    "sg:city":"Reading",
    "sg:classifiers":[
        {
            "category":"Professional",
            "subcategory":"Research",
            "type":"Services"
        }
    ],
    "sg:phone":"+1 781 942 0689",
    "sg:postcode":"01867",
    "sg:province":"MA",
    "sg:tags":[
        "environmental",
        "ecological"
    ],
    "wof:name":"RSP Assoc",
    "wof:placetype":"venue"
},
  "geometry": {"coordinates":[-71.117411,42.558078],"type":"Point"}
}