{
  "type": "Feature",
  "properties": {
    "addr:full": "489 Merrimack St Lowell MA 01854",
    "addr:housenumber": "489",
    "addr:postcode": "01854",
    "addr:street": "Merrimack St",
    "iso:country": "US",
    "sg:address": "489 Merrimack St",
    "sg:city": "Lowell",
    "sg:classifiers": [
      {
        "category": "Banks \u0026 Credit Unions",
        "subcategory": "Bank",
        "type": "Services"
      }
    ],
    "sg:phone": "+1 978 000 1111",
    "sg:postcode": "01854",
    "sg:province": "MA",
    "wof:name": "Sovereign Bank",
    "wof:placetype": "venue"
  },
  "geometry": {"coordinates":[-71.316271,42.646909],"type":"Point"}
}
