{
  "type": "Feature",
  "properties": {
    "iso:country":"US",
    "sg:address":"550 Broad St",
    "sg:city":"Weymouth",
    "sg:classifiers":[
        {
            "category":"Restaurant",
            "type":"Food & Drink"
        }
    ],
    "sg:phone":"+1 781 335 9796",
    "sg:postcode":"02189",
    "sg:province":"MA",
    "wof:name":"Jim Bo's Cafe & Take Out",
    "wof:placetype":"venue"
},
  "geometry": {"coordinates":[-70.938367,42.217655],"type":"Point"}
}