{
  "type": "Feature",
  "properties": {
    "iso:country":"US",
    "sg:address":"165 Front St",
    "sg:city":"Chicopee",
    "sg:classifiers":[
        {
            "category":"Professional",
            "type":"Services"
        }
    ],
    "sg:phone":"+1 413 594 5105",
    "sg:postcode":"01013",
    "sg:province":"MA",
    "sg:tags":[
        "establishment"
    ],
    "wof:name":"Off-Beat Records",
    "wof:placetype":"venue"
},
  "geometry": {"coordinates":[-72.611739,42.148052],"type":"Point"}
}