{
  "type": "Feature",
  "properties": {
    "addr:full": "150 Granite St Braintree MA 02184",
    "addr:housenumber": "150",
    "addr:postcode": "02184",
    "addr:street": "Granite St",
    "iso:country": "US",
    "sg:address": "150 Granite St",
    "sg:city": "Braintree",
    "sg:classifiers": [
      {
        "category": "Shopping",
        "subcategory": "Gifts \u0026 Souvenirs",
        "type": "Retail Goods"
      }
    ],
    "sg:phone": "+1 781 380 3655",
    "sg:postcode": "02184",
    "sg:province": "MA",
    "sg:tags": [
      "shop"
    ],
    "sg:website": "http://store-locator.barnesandnoble.com/store/1989",
    "wof:name": "Barnes \u0026 Noble Booksellers",
    "wof:placetype": "venue"
  },
  "geometry": {"coordinates":[-71.031418,42.223919],"type":"Point"}
}
