{
  "type": "Feature",
  "properties": {
    "addr:full": "26 Center St Nantucket MA 02554",
    "addr:housenumber": "26",
    "addr:postcode": "02554",
    "addr:street": "Center St",
    "iso:country": "US",
    "sg:address": "26 Center St",
    "sg:city": "Nantucket",
    "sg:classifiers": [
      {
        "category": "Wholesale",
        "subcategory": "Groceries",
        "type": "Manufacturing \u0026 Wholesale Goods"
      }
    ],
    "sg:phone": "+1 508 228 5814",
    "sg:postcode": "02554",
    "sg:province": "MA",
    "sg:tags": [
      "cocoa",
      "chocolate"
    ],
    "sg:website": "www.nantucketchocolate.com",
    "wof:name": "Sweet Inspiration Of Nantucket",
    "wof:placetype": "venue"
  },
  "geometry": {"coordinates":[-70.099832,41.283547],"type":"Point"}
}
