{
  "type": "Feature",
  "properties": {
    "addr:full": "174 Mendell Rd Rochester MA 02770",
    "addr:housenumber": "174",
    "addr:postcode": "02770",
    "addr:street": "Mendell Rd",
    "iso:country": "US",
    "sg:address": "174 Mendell Rd",
    "sg:city": "Rochester",
    "sg:classifiers": [
      {
        "category": "Real Estate",
        "subcategory": "Architect",
        "type": "Services"
      }
    ],
    "sg:phone": "+1 508 763 3441",
    "sg:postcode": "02770",
    "sg:province": "MA",
    "wof:name": "Miquelle Architecture",
    "wof:placetype": "venue"
  },
  "geometry": {"coordinates":[-70.82842,41.746444],"type":"Point"}
}
