{
  "type": "Feature",
  "properties": {
    "addr:full": "269 Somerville Avenue Somerville MA 02143",
    "addr:housenumber": "269",
    "addr:postcode": "02143",
    "addr:street": "Somerville Avenue",
    "iso:country": "US",
    "ovtr:label": "Fred M Susan Auto Body, 269 Somerville Ave Somerville MA US",
    "ovtr:similarity": 2.4060020446777344,
    "sg:address": "269 Somerville Avenue",
    "sg:city": "Somerville",
    "sg:classifiers": [
      {
        "category": "Retail",
        "subcategory": "Auto Repair",
        "type": "Services"
      }
    ],
    "sg:phone": "+1 617 776 1570",
    "sg:postcode": "02143",
    "sg:province": "MA",
    "wof:name": "Fred M Susan Auto Body",
    "wof:placetype": "venue"
  },
  "geometry": {"coordinates":[-71.093771,42.378823],"type":"Point"}
}
