{
  "type": "Feature",
  "properties": {
    "iso:country":"US",
    "sg:address":"269 Somerville Avenue",
    "sg:city":"Somerville",
    "sg:classifiers":[
        {
            "category":"Retail",
            "subcategory":"Auto Repair",
            "type":"Services"
        }
    ],
    "sg:phone":"+1 617 776 1570",
    "sg:postcode":"02143",
    "sg:province":"MA",
    "wof:name":"Fred M Susan Auto Body",
    "wof:placetype":"venue"
},
  "geometry": {"coordinates":[-71.093771,42.378823],"type":"Point"}
}