{
  "type": "Feature",
  "properties": {
    "iso:country":"US",
    "sg:address":"50 Corinth St",
    "sg:city":"Roslindale",
    "sg:classifiers":[
        {
            "category":"Building & Trades",
            "subcategory":"Locksmith",
            "type":"Services"
        }
    ],
    "sg:phone":"+1 617 272 4344",
    "sg:postcode":"02131",
    "sg:province":"MA",
    "sg:tags":[
        "key"
    ],
    "wof:name":"Locksmith 24 Hours",
    "wof:placetype":"venue"
},
  "geometry": {"coordinates":[-71.129363,42.286109],"type":"Point"}
}