{
  "type": "Feature",
  "properties": {
    "addr:full": "50 Corinth St Roslindale MA 02131",
    "addr:housenumber": "50",
    "addr:postcode": "02131",
    "addr:street": "Corinth St",
    "iso:country": "US",
    "sg:address": "50 Corinth St",
    "sg:city": "Roslindale",
    "sg:classifiers": [
      {
        "category": "Building \u0026 Trades",
        "subcategory": "Locksmith",
        "type": "Services"
      }
    ],
    "sg:phone": "+1 617 272 4344",
    "sg:postcode": "02131",
    "sg:province": "MA",
    "sg:tags": [
      "key"
    ],
    "wof:name": "Locksmith 24 Hours",
    "wof:placetype": "venue"
  },
  "geometry": {"coordinates":[-71.129363,42.286109],"type":"Point"}
}
