{
  "type": "Feature",
  "properties": {
    "iso:country":"US",
    "sg:address":"45 Kings Hwy",
    "sg:city":"West Wareham",
    "sg:classifiers":[
        {
            "category":"Manufacturing",
            "subcategory":"Metals",
            "type":"Manufacturing & Wholesale Goods"
        }
    ],
    "sg:phone":"+1 508 291 7150",
    "sg:postcode":"02576",
    "sg:province":"MA",
    "sg:tags":[
        "steel"
    ],
    "sg:website":"www.harrisrebar.com",
    "wof:name":"Harris Rebar Boston Inc",
    "wof:placetype":"venue"
},
  "geometry": {"coordinates":[-70.776659,41.797655],"type":"Point"}
}