{
  "type": "Feature",
  "properties": {
    "iso:country":"US",
    "sg:address":"552 Massachusetts Ave",
    "sg:city":"Cambridge",
    "sg:classifiers":[
        {
            "category":"Real Estate",
            "subcategory":"Real Estate Operator",
            "type":"Services"
        }
    ],
    "sg:phone":"+1 617 492 4700",
    "sg:postcode":"02139",
    "sg:province":"MA",
    "sg:tags":[
        "apartment"
    ],
    "wof:name":"Corporate Housing Options",
    "wof:placetype":"venue"
},
  "geometry": {"coordinates":[-71.102362,42.36452],"type":"Point"}
}