{
  "type": "Feature",
  "properties": {
    "iso:country":"US",
    "sg:address":"105 Main St",
    "sg:city":"Great Barrington",
    "sg:classifiers":[
        {
            "category":"Health Services",
            "subcategory":"Health Practitioner",
            "type":"Services"
        }
    ],
    "sg:phone":"+1 413 528 3514",
    "sg:postcode":"01230",
    "sg:province":"MA",
    "sg:tags":[
        "acupuncture"
    ],
    "wof:name":"Centre For Acupuncture",
    "wof:placetype":"venue"
},
  "geometry": {"coordinates":[-73.359683,42.199581],"type":"Point"}
}