{
  "type": "Feature",
  "properties": {
    "iso:country":"US",
    "sg:address":"64 Main St",
    "sg:city":"Winchendon",
    "sg:classifiers":[
        {
            "category":"Wholesale",
            "subcategory":"Scrap",
            "type":"Manufacturing & Wholesale Goods"
        }
    ],
    "sg:phone":"+1 978 297 2050",
    "sg:postcode":"01475",
    "sg:province":"MA",
    "sg:tags":[
        "material",
        "metal",
        "iron"
    ],
    "wof:name":"Ed's Scrap Metal",
    "wof:placetype":"venue"
},
  "geometry": {"coordinates":[-72.069582,42.674067],"type":"Point"}
}