{
  "type": "Feature",
  "properties": {
    "iso:country":"US",
    "sg:address":"5 East Blvd",
    "sg:city":"Onset",
    "sg:classifiers":[
        {
            "category":"Professional",
            "subcategory":"Engineering",
            "type":"Services"
        }
    ],
    "sg:phone":"+1 508 295 9009",
    "sg:postcode":"02558",
    "sg:province":"MA",
    "sg:tags":[
        "engineer"
    ],
    "wof:name":"Wetlands & Coastal Consultants",
    "wof:placetype":"venue"
},
  "geometry": {"coordinates":[-70.65628599999999,41.744406],"type":"Point"}
}