{
  "type": "Feature",
  "properties": {
    "addr:full": "5 East Blvd Onset MA 02558",
    "addr:housenumber": "5",
    "addr:postcode": "02558",
    "addr:street": "East Blvd",
    "iso:country": "US",
    "sg:address": "5 East Blvd",
    "sg:city": "Onset",
    "sg:classifiers": [
      {
        "category": "Professional",
        "subcategory": "Engineering",
        "type": "Services"
      }
    ],
    "sg:phone": "+1 508 295 9009",
    "sg:postcode": "02558",
    "sg:province": "MA",
    "sg:tags": [
      "engineer"
    ],
    "wof:name": "Wetlands \u0026 Coastal Consultants",
    "wof:placetype": "venue"
  },
  "geometry": {"coordinates":[-70.656286,41.744406],"type":"Point"}
}
