{
  "type": "Feature",
  "properties": {
    "iso:country":"US",
    "sg:address":"761 Washington St",
    "sg:city":"Stoughton",
    "sg:classifiers":[
        {
            "category":"Shopping",
            "type":"Retail Goods"
        }
    ],
    "sg:phone":"+1 781 297 5220",
    "sg:postcode":"02072",
    "sg:province":"MA",
    "sg:tags":[
        "art",
        "gallery"
    ],
    "wof:name":"Henson Jackson Art Gallery and Framery",
    "wof:placetype":"venue"
},
  "geometry": {"coordinates":[-71.102097,42.125198],"type":"Point"}
}