{
  "type": "Feature",
  "properties": {
    "iso:country":"US",
    "sg:address":"179 Massachusetts Ave",
    "sg:city":"Arlington",
    "sg:classifiers":[
        {
            "category":"Personal",
            "subcategory":"Beauty Salon",
            "type":"Services"
        }
    ],
    "sg:phone":"+1 781 648 1880",
    "sg:postcode":"02474",
    "sg:province":"MA",
    "sg:tags":[
        "hair"
    ],
    "sg:website":"www.mamihairsalon.com",
    "wof:name":"Mami Hair Salon",
    "wof:placetype":"venue"
},
  "geometry": {"coordinates":[-71.141971,42.405543],"type":"Point"}
}