{
  "type": "Feature",
  "properties": {
    "addr:full": "179 Massachusetts Ave Arlington MA 02474",
    "addr:housenumber": "179",
    "addr:postcode": "02474",
    "addr:street": "Massachusetts Ave",
    "iso:country": "US",
    "sg:address": "179 Massachusetts Ave",
    "sg:city": "Arlington",
    "sg:classifiers": [
      {
        "category": "Personal",
        "subcategory": "Beauty Salon",
        "type": "Services"
      }
    ],
    "sg:phone": "+1 781 648 1880",
    "sg:postcode": "02474",
    "sg:province": "MA",
    "sg:tags": [
      "hair"
    ],
    "sg:website": "www.mamihairsalon.com",
    "wof:name": "Mami Hair Salon",
    "wof:placetype": "venue"
  },
  "geometry": {"coordinates":[-71.141971,42.405543],"type":"Point"}
}
