{
  "type": "Feature",
  "properties": {
    "addr:full": "196 Ocean St Lynn MA 01902",
    "addr:housenumber": "196",
    "addr:postcode": "01902",
    "addr:street": "Ocean St",
    "iso:country": "US",
    "sg:address": "196 Ocean St",
    "sg:city": "Lynn",
    "sg:classifiers": [
      {
        "category": "Education",
        "subcategory": "Special Training",
        "type": "Public Place"
      }
    ],
    "sg:phone": "+1 781 595 9592",
    "sg:postcode": "01902",
    "sg:province": "MA",
    "sg:tags": [
      "educational"
    ],
    "wof:name": "Child Life Education \u0026 Dev Inc",
    "wof:placetype": "venue"
  },
  "geometry": {"coordinates":[-70.931903,42.462292],"type":"Point"}
}
