{
  "type": "Feature",
  "properties": {
    "iso:country":"US",
    "sg:address":"196 Ocean St",
    "sg:city":"Lynn",
    "sg:classifiers":[
        {
            "category":"Education",
            "subcategory":"Special Training",
            "type":"Public Place"
        }
    ],
    "sg:phone":"+1 781 595 9592",
    "sg:postcode":"01902",
    "sg:province":"MA",
    "sg:tags":[
        "educational"
    ],
    "wof:name":"Child Life Education & Dev Inc",
    "wof:placetype":"venue"
},
  "geometry": {"coordinates":[-70.93190300000001,42.462292],"type":"Point"}
}