{
  "type": "Feature",
  "properties": {
    "iso:country":"US",
    "sg:address":"200 Oxford St N",
    "sg:city":"Auburn",
    "sg:classifiers":[
        {
            "category":"Real Estate",
            "subcategory":"Real Estate Agent",
            "type":"Services"
        }
    ],
    "sg:phone":"+1 508 832 3852",
    "sg:postcode":"01501",
    "sg:province":"MA",
    "sg:tags":[
        "authorities",
        "housing"
    ],
    "wof:name":"Auburn Housing Authority",
    "wof:placetype":"venue"
},
  "geometry": {"coordinates":[-71.84612199999999,42.214447],"type":"Point"}
}