{
  "type": "Feature",
  "properties": {
    "iso:country":"US",
    "sg:address":"66 Union Sq",
    "sg:city":"Somerville",
    "sg:classifiers":[
        {
            "category":"Building & Trades",
            "subcategory":"Construction",
            "type":"Services"
        }
    ],
    "sg:phone":"+1 617 623 1122",
    "sg:postcode":"02143",
    "sg:province":"MA",
    "sg:tags":[
        "interior",
        "design"
    ],
    "wof:name":"Wellesley Design Consultants - closed",
    "wof:placetype":"venue"
},
  "geometry": {"coordinates":[-71.078087,42.388062],"type":"Point"}
}