{
  "type": "Feature",
  "properties": {
    "iso:country":"US",
    "sg:address":"301 Pleasant St",
    "sg:city":"Worcester",
    "sg:classifiers":[
        {
            "category":"Social Services",
            "type":"Services"
        }
    ],
    "sg:phone":"+1 508 754 7793",
    "sg:postcode":"01609",
    "sg:province":"MA",
    "sg:tags":[
        "organization",
        "welfare"
    ],
    "wof:name":"Pleasant Street Neighborhood",
    "wof:placetype":"venue"
},
  "geometry": {"coordinates":[-71.813407,42.263987],"type":"Point"}
}