{
  "type": "Feature",
  "properties": {
    "iso:country":"US",
    "sg:address":"17 W Water St",
    "sg:city":"Wakefield",
    "sg:classifiers":[
        {
            "category":"Personal",
            "subcategory":"Beauty Salon",
            "type":"Services"
        }
    ],
    "sg:phone":"+1 781 245 2827",
    "sg:postcode":"01880",
    "sg:province":"MA",
    "sg:tags":[
        "shop"
    ],
    "wof:name":"Rita's Beauty Salon",
    "wof:placetype":"venue"
},
  "geometry": {"coordinates":[-71.074116,42.50127],"type":"Point"}
}