{
  "type": "Feature",
  "properties": {
    "iso:country":"US",
    "sg:address":"695 Truman Hwy",
    "sg:city":"Hyde Park",
    "sg:classifiers":[
        {
            "category":"Social Services",
            "type":"Services"
        }
    ],
    "sg:phone":"+1 617 364 4453",
    "sg:postcode":"02136",
    "sg:province":"MA",
    "sg:tags":[
        "organization",
        "welfare"
    ],
    "wof:name":"Harvard Street Health Ctr Wic",
    "wof:placetype":"venue"
},
  "geometry": {"coordinates":[-71.11961599999999,42.251722],"type":"Point"}
}