{
  "type": "Feature",
  "properties": {
    "iso:country":"US",
    "sg:address":"210 Winter St Ste 303",
    "sg:city":"Weymouth",
    "sg:classifiers":[
        {
            "category":"Health Services",
            "subcategory":"Clinic",
            "type":"Services"
        },
        {
            "category":"Health Services",
            "subcategory":"Health Practitioner",
            "type":"Services"
        }
    ],
    "sg:phone":"+1 781 337 4499",
    "sg:postcode":"02188",
    "sg:province":"MA",
    "sg:tags":[
        "therapist",
        "therapy",
        "physical"
    ],
    "wof:name":"Relax & Renew",
    "wof:placetype":"venue"
},
  "geometry": {"coordinates":[-70.94837099999999,42.200736],"type":"Point"}
}