{
  "type": "Feature",
  "properties": {
    "addr:full": "85 Academy Hill Rd Brighton MA 02135",
    "addr:housenumber": "85",
    "addr:postcode": "02135",
    "addr:street": "Academy Hill Rd",
    "iso:country": "US",
    "sg:address": "85 Academy Hill Rd",
    "sg:city": "Brighton",
    "sg:classifiers": [
      {
        "category": "Building \u0026 Trades",
        "subcategory": "Construction",
        "type": "Services"
      }
    ],
    "sg:phone": "+1 617 254 2626",
    "sg:postcode": "02135",
    "sg:province": "MA",
    "sg:tags": [
      "painter"
    ],
    "wof:name": "Central Painting Co",
    "wof:placetype": "venue"
  },
  "geometry": {"coordinates":[-71.154558,42.346267],"type":"Point"}
}
