{
  "type": "Feature",
  "properties": {
    "addr:full":"31 Elm St Tyngsboro MA 01879",
    "addr:housenumber":"31",
    "addr:postcode":"01879",
    "addr:street":"Elm St",
    "iso:country":"US",
    "sg:address":"31 Elm St",
    "sg:city":"Tyngsboro",
    "sg:classifiers":[
        {
            "category":"Real Estate",
            "subcategory":"Real Estate Services",
            "type":"Services"
        },
        {
            "category":"Real Estate",
            "subcategory":"Real Estate Agent",
            "type":"Services"
        }
    ],
    "sg:phone":"+1 978 649 6719",
    "sg:postcode":"01879",
    "sg:province":"MA",
    "sg:tags":[
        "buyer",
        "broker"
    ],
    "wof:name":"Polo Realty Group",
    "wof:placetype":"venue"
},
  "geometry": {"coordinates":[-71.376222,42.690709],"type":"Point"}
}