{
  "type": "Feature",
  "properties": {
    "iso:country":"US",
    "sg:address":"2 Union Sq",
    "sg:city":"Somerville",
    "sg:classifiers":[
        {
            "category":"Retail",
            "subcategory":"Driving School",
            "type":"Services"
        },
        {
            "category":"Autos & Motor Vehicles",
            "subcategory":"Boat Sales",
            "type":"Retail Goods"
        },
        {
            "category":"Autos & Motor Vehicles",
            "subcategory":"Motorcycle Sales",
            "type":"Retail Goods"
        },
        {
            "category":"Retail",
            "subcategory":"Auto Repair",
            "type":"Services"
        },
        {
            "category":"Personal",
            "subcategory":"Piercing",
            "type":"Services"
        }
    ],
    "sg:phone":"+1 617 628 6400",
    "sg:postcode":"02143",
    "sg:province":"MA",
    "sg:tags":[
        "scooters-repairing",
        "watercraft",
        "instruction"
    ],
    "sg:website":"www.riversidemoto.com",
    "wof:name":"Riverside Motorsports",
    "wof:placetype":"venue"
},
  "geometry": {"coordinates":[-71.09516000000001,42.37908],"type":"Point"}
}