{
  "type": "Feature",
  "properties": {
    "iso:country":"US",
    "sg:address":"161 Mount Auburn St",
    "sg:city":"Watertown",
    "sg:classifiers":[
        {
            "category":"Real Estate",
            "subcategory":"Real Estate Agent",
            "type":"Services"
        }
    ],
    "sg:phone":"+1 617 926 5280",
    "sg:postcode":"02472",
    "sg:province":"MA",
    "sg:website":"www.century21west.com",
    "wof:name":"Century 21 West Realty",
    "wof:placetype":"venue"
},
  "geometry": {"coordinates":[-71.17695999999999,42.368352],"type":"Point"}
}