{
  "type": "Feature",
  "properties": {
    "addr:full":"40 Mall Rd Burlington MA 01803",
    "addr:housenumber":"40",
    "addr:postcode":"01803",
    "addr:street":"Mall Rd",
    "iso:country":"US",
    "sg:address":"40 Mall Rd",
    "sg:city":"Burlington",
    "sg:classifiers":[
        {
            "category":"Professional",
            "subcategory":"Lawyer & Legal Services",
            "type":"Services"
        }
    ],
    "sg:phone":"+1 781 270 4707",
    "sg:postcode":"01803",
    "sg:province":"MA",
    "wof:name":"Impemba Joseph A",
    "wof:placetype":"venue"
},
  "geometry": {"coordinates":[-71.204796,42.487226],"type":"Point"}
}