{
  "type": "Feature",
  "properties": {
    "iso:country":"US",
    "sg:address":"706 Brook Rd",
    "sg:city":"Milton",
    "sg:classifiers":[
        {
            "category":"Health Services",
            "subcategory":"Doctor",
            "type":"Services"
        }
    ],
    "sg:phone":"+1 617 696 0952",
    "sg:postcode":"02186",
    "sg:province":"MA",
    "sg:tags":[
        "medicine",
        "physician",
        "practice",
        "surgeons",
        "family"
    ],
    "wof:name":"S P Ganguly Md Pc",
    "wof:placetype":"venue"
},
  "geometry": {"coordinates":[-71.070589,42.25993],"type":"Point"}
}