{
  "type": "Feature",
  "properties": {
    "addr:full":"1394 Beacon St Brookline MA 02446",
    "addr:housenumber":"1394",
    "addr:postcode":"02446",
    "addr:street":"Beacon St",
    "iso:country":"US",
    "sg:address":"1394 Beacon St",
    "sg:city":"Brookline",
    "sg:classifiers":[
        {
            "category":"Professional",
            "type":"Services"
        }
    ],
    "sg:phone":"+1 617 975 0005",
    "sg:postcode":"02446",
    "sg:province":"MA",
    "sg:tags":[
        "establishment"
    ],
    "wof:name":"Consigning Women",
    "wof:placetype":"venue"
},
  "geometry": {"coordinates":[-71.125469,42.341309],"type":"Point"}
}