{
  "type": "Feature",
  "properties": {
    "addr:full": "45 Fernwood Ave Haverhill MA 01835",
    "addr:housenumber": "45",
    "addr:postcode": "01835",
    "addr:street": "Fernwood Ave",
    "iso:country": "US",
    "sg:address": "45 Fernwood Ave",
    "sg:city": "Haverhill",
    "sg:classifiers": [
      {
        "category": "Building \u0026 Trades",
        "subcategory": "Landscaping Services",
        "type": "Services"
      }
    ],
    "sg:phone": "+1 978 374 1739",
    "sg:postcode": "01835",
    "sg:province": "MA",
    "sg:tags": [
      "landscape",
      "contractor"
    ],
    "wof:name": "Clark Landscaping",
    "wof:placetype": "venue"
  },
  "geometry": {"coordinates":[-71.083832,42.75935],"type":"Point"}
}
