{
  "type": "Feature",
  "properties": {
    "iso:country":"US",
    "sg:address":"143 W Main St",
    "sg:city":"West Brookfield",
    "sg:classifiers":[
        {
            "category":"Food & Beverages",
            "subcategory":"Liquor & Beverages",
            "type":"Retail Goods"
        }
    ],
    "sg:phone":"+1 508 867 5844",
    "sg:postcode":"01585",
    "sg:province":"MA",
    "wof:name":"Spirit Shoppe",
    "wof:placetype":"venue"
},
  "geometry": {"coordinates":[-72.156057,42.233755],"type":"Point"}
}