{
  "type": "Feature",
  "properties": {
    "addr:full": "143 W Main St West Brookfield MA 01585",
    "addr:housenumber": "143",
    "addr:postcode": "01585",
    "addr:street": "W Main St West",
    "iso:country": "US",
    "ovtr:label": "The Spirit Shoppe, 143 W Main St West Brookfield MA US",
    "ovtr:similarity": 3.156873941421509,
    "sg:address": "143 W Main St",
    "sg:city": "West Brookfield",
    "sg:classifiers": [
      {
        "category": "Food \u0026 Beverages",
        "subcategory": "Liquor \u0026 Beverages",
        "type": "Retail Goods"
      }
    ],
    "sg:phone": "+1 508 867 5844",
    "sg:postcode": "01585",
    "sg:province": "MA",
    "wof:name": "Spirit Shoppe",
    "wof:placetype": "venue"
  },
  "geometry": {"coordinates":[-72.156057,42.233755],"type":"Point"}
}
