{
  "type": "Feature",
  "properties": {
    "addr:full": "15 Boylston Pl Brookline MA 02445",
    "addr:housenumber": "15",
    "addr:postcode": "02445",
    "addr:street": "Boylston Pl",
    "iso:country": "US",
    "sg:address": "15 Boylston Pl",
    "sg:city": "Brookline",
    "sg:classifiers": [
      {
        "category": "Professional",
        "subcategory": "Accounting \u0026 Tax Preparation",
        "type": "Services"
      }
    ],
    "sg:phone": "+1 617 738 8982",
    "sg:postcode": "02445",
    "sg:province": "MA",
    "sg:tags": [
      "bookkeeping",
      "general"
    ],
    "wof:name": "Ted Kalogeropoulos",
    "wof:placetype": "venue"
  },
  "geometry": {"coordinates":[-71.125314,42.330469],"type":"Point"}
}
