{
  "type": "Feature",
  "properties": {
    "addr:full":"25 Bodwell St Avon MA 02322",
    "addr:housenumber":"25",
    "addr:postcode":"02322",
    "addr:street":"Bodwell St",
    "iso:country":"US",
    "sg:address":"25 Bodwell St",
    "sg:city":"Avon",
    "sg:classifiers":[
        {
            "category":"Building & Trades",
            "subcategory":"Equipment Rental",
            "type":"Services"
        }
    ],
    "sg:phone":"+1 508 586 0900",
    "sg:postcode":"02322",
    "sg:province":"MA",
    "sg:tags":[
        "camping"
    ],
    "sg:website":"www.bctent.com",
    "wof:name":"B C Tent & Awning Co",
    "wof:placetype":"venue"
},
  "geometry": {"coordinates":[-71.05459999999999,42.12697],"type":"Point"}
}