{
  "type": "Feature",
  "properties": {
    "iso:country":"US",
    "sg:address":"24 Crystal Pond Rd",
    "sg:city":"Franklin",
    "sg:classifiers":[
        {
            "category":"Building & Trades",
            "subcategory":"Cleaning & Sanitation",
            "type":"Services"
        }
    ],
    "sg:phone":"+1 508 541 1440",
    "sg:postcode":"02038",
    "sg:province":"MA",
    "sg:tags":[
        "janitor"
    ],
    "wof:name":"All In One Cleaning Svc",
    "wof:placetype":"venue"
},
  "geometry": {"coordinates":[-71.431771,42.115876],"type":"Point"}
}