{
  "type": "Feature",
  "properties": {
    "addr:full": "24 Crystal Pond Rd Franklin MA 02038",
    "addr:housenumber": "24",
    "addr:postcode": "02038",
    "addr:street": "Crystal Pond Rd",
    "iso:country": "US",
    "sg:address": "24 Crystal Pond Rd",
    "sg:city": "Franklin",
    "sg:classifiers": [
      {
        "category": "Building \u0026 Trades",
        "subcategory": "Cleaning \u0026 Sanitation",
        "type": "Services"
      }
    ],
    "sg:phone": "+1 508 541 1440",
    "sg:postcode": "02038",
    "sg:province": "MA",
    "sg:tags": [
      "janitor"
    ],
    "wof:name": "All In One Cleaning Svc",
    "wof:placetype": "venue"
  },
  "geometry": {"coordinates":[-71.431771,42.115876],"type":"Point"}
}
