{
  "type": "Feature",
  "properties": {
    "iso:country":"US",
    "sg:address":"1160 Boylston Street",
    "sg:city":"Chestnut Hill",
    "sg:classifiers":[
        {
            "category":"Shopping",
            "subcategory":"Jewelry",
            "type":"Retail Goods"
        }
    ],
    "sg:phone":"+1 617 739 8584",
    "sg:postcode":"02467",
    "sg:province":"MA",
    "wof:name":"Kosmima Fine Jewelry",
    "wof:placetype":"venue"
},
  "geometry": {"coordinates":[-71.163296,42.323689],"type":"Point"}
}