{
  "type": "Feature",
  "properties": {
    "addr:full": "1160 Boylston Street Chestnut Hill MA 02467",
    "addr:housenumber": "1160",
    "addr:postcode": "02467",
    "addr:street": "Boylston Street",
    "iso:country": "US",
    "ovtr:label": "Kosmima Fine Jewelry, 1160 Boylston St Chestnut Hill MA US",
    "ovtr:similarity": 1.8625849485397339,
    "sg:address": "1160 Boylston Street",
    "sg:city": "Chestnut Hill",
    "sg:classifiers": [
      {
        "category": "Shopping",
        "subcategory": "Jewelry",
        "type": "Retail Goods"
      }
    ],
    "sg:phone": "+1 617 739 8584",
    "sg:postcode": "02467",
    "sg:province": "MA",
    "wof:name": "Kosmima Fine Jewelry",
    "wof:placetype": "venue"
  },
  "geometry": {"coordinates":[-71.163296,42.323689],"type":"Point"}
}
