{
  "type": "Feature",
  "properties": {
    "addr:full": "181 W Boylston St West Boylston MA 01583",
    "addr:housenumber": "181",
    "addr:postcode": "01583",
    "addr:street": "W Boylston St",
    "iso:country": "US",
    "sg:address": "181 W Boylston St",
    "sg:city": "West Boylston",
    "sg:classifiers": [
      {
        "category": "Travel",
        "subcategory": "Hotels \u0026 Motels",
        "type": "Entertainment"
      }
    ],
    "sg:phone": "+1 508 835 4456",
    "sg:postcode": "01583",
    "sg:province": "MA",
    "wof:name": "Classic Suites \u0026 Inns",
    "wof:placetype": "venue"
  },
  "geometry": {"coordinates":[-71.784554,42.355238],"type":"Point"}
}
