{
  "type": "Feature",
  "properties": {
    "addr:full":"152 King St Cohasset MA 02025",
    "addr:housenumber":"152",
    "addr:postcode":"02025",
    "addr:street":"King St",
    "iso:country":"US",
    "sg:address":"152 King St",
    "sg:city":"Cohasset",
    "sg:classifiers":[
        {
            "category":"Professional",
            "subcategory":"Accounting & Tax Preparation",
            "type":"Services"
        }
    ],
    "sg:phone":"+1 781 383 6070",
    "sg:postcode":"02025",
    "sg:province":"MA",
    "sg:tags":[
        "accountant"
    ],
    "wof:name":"James F Kearney & Co",
    "wof:placetype":"venue"
},
  "geometry": {"coordinates":[-70.828765,42.241191],"type":"Point"}
}