{
  "type": "Feature",
  "properties": {
    "addr:full": "345 Rocus St Springfield MA 01104",
    "addr:housenumber": "345",
    "addr:postcode": "01104",
    "addr:street": "Rocus St",
    "iso:country": "US",
    "sg:address": "345 Rocus St",
    "sg:city": "Springfield",
    "sg:classifiers": [
      {
        "category": "Freight",
        "type": "Transportation"
      }
    ],
    "sg:phone": "+1 413 733 9820",
    "sg:postcode": "01104",
    "sg:province": "MA",
    "sg:tags": [
      "trucking"
    ],
    "sg:website": "www.mylandair.com",
    "wof:name": "Land Air Express New England",
    "wof:placetype": "venue"
  },
  "geometry": {"coordinates":[-72.537775,42.147146],"type":"Point"}
}
