{
  "type": "Feature",
  "properties": {
    "addr:full": "917 High St Westwood MA 02090",
    "addr:housenumber": "917",
    "addr:postcode": "02090",
    "addr:street": "High St",
    "iso:country": "US",
    "sg:address": "917 High St",
    "sg:city": "Westwood",
    "sg:classifiers": [
      {
        "category": "Health Services",
        "subcategory": "Health Practitioner",
        "type": "Services"
      }
    ],
    "sg:phone": "+1 781 320 0066",
    "sg:postcode": "02090",
    "sg:province": "MA",
    "sg:tags": [
      "nutritionist"
    ],
    "wof:name": "Fitness Transformations",
    "wof:placetype": "venue"
  },
  "geometry": {"coordinates":[-71.223389,42.219226],"type":"Point"}
}
