{
  "type": "Feature",
  "properties": {
    "addr:full":"1 Faneuil Hall Market Pl Boston MA 02109",
    "addr:housenumber":"1",
    "addr:postcode":"02109",
    "addr:street":"Faneuil Hall Market Pl",
    "iso:country":"US",
    "sg:address":"1 Faneuil Hall Market Pl",
    "sg:city":"Boston",
    "sg:classifiers":[
        {
            "category":"Coffee & Tea",
            "type":"Food & Drink"
        }
    ],
    "sg:phone":"+1 617 367 8390",
    "sg:postcode":"02109",
    "sg:province":"MA",
    "sg:website":"www.redbarncoffee.com/",
    "wof:name":"Red Barn Coffee Roasters",
    "wof:placetype":"venue"
},
  "geometry": {"coordinates":[-71.05589999999999,42.3597],"type":"Point"}
}