{
  "type": "Feature",
  "properties": {
    "iso:country":"US",
    "sg:address":"14 Kalamat Farms Cir",
    "sg:city":"Shrewsbury",
    "sg:classifiers":[
        {
            "category":"Manufacturing",
            "subcategory":"Jewelry",
            "type":"Manufacturing & Wholesale Goods"
        }
    ],
    "sg:phone":"+1   ",
    "sg:postcode":"01545",
    "sg:province":"MA",
    "sg:tags":[
        "precious",
        "metal",
        "mfg"
    ],
    "wof:name":"Viacolorcom",
    "wof:placetype":"venue"
},
  "geometry": {"coordinates":[-71.69533,42.30789],"type":"Point"}
}