{
  "type": "Feature",
  "properties": {
    "addr:full": "920 Main St Holyoke MA 01040",
    "addr:housenumber": "920",
    "addr:postcode": "01040",
    "addr:street": "Main St",
    "iso:country": "US",
    "sg:address": "920 Main St",
    "sg:city": "Holyoke",
    "sg:classifiers": [
      {
        "category": "Bars \u0026 Pubs",
        "type": "Food \u0026 Drink"
      }
    ],
    "sg:phone": "+1 413 532 2292",
    "sg:postcode": "01040",
    "sg:province": "MA",
    "sg:tags": [
      "club",
      "night"
    ],
    "wof:name": "Waterfront Tavern \u0026 Restaurant",
    "wof:placetype": "venue"
  },
  "geometry": {"coordinates":[-72.625614,42.185541],"type":"Point"}
}
