{
  "type": "Feature",
  "properties": {
    "iso:country":"US",
    "sg:address":"920 Main St",
    "sg:city":"Holyoke",
    "sg:classifiers":[
        {
            "category":"Bars & Pubs",
            "type":"Food & Drink"
        }
    ],
    "sg:phone":"+1 413 532 2292",
    "sg:postcode":"01040",
    "sg:province":"MA",
    "sg:tags":[
        "club",
        "night"
    ],
    "wof:name":"Waterfront Tavern & Restaurant",
    "wof:placetype":"venue"
},
  "geometry": {"coordinates":[-72.625614,42.185541],"type":"Point"}
}