{
  "type": "Feature",
  "properties": {
    "addr:full":"251 W Main St Dudley MA 01571",
    "addr:housenumber":"251",
    "addr:postcode":"01571",
    "addr:street":"W Main St",
    "iso:country":"US",
    "sg:address":"251 W Main St",
    "sg:city":"Dudley",
    "sg:classifiers":[
        {
            "category":"Food & Beverages",
            "subcategory":"Groceries & Convenience Stores",
            "type":"Retail Goods"
        }
    ],
    "sg:phone":"+1 508 943 0877",
    "sg:postcode":"01571",
    "sg:province":"MA",
    "wof:name":"Xtra Mart",
    "wof:placetype":"venue"
},
  "geometry": {"coordinates":[-71.91943000000001,42.036604],"type":"Point"}
}