{
  "type": "Feature",
  "properties": {
    "iso:country":"US",
    "sg:address":"262 Beacon St",
    "sg:city":"Boston",
    "sg:classifiers":[
        {
            "category":"Banks & Credit Unions",
            "subcategory":"Investment Brokerage",
            "type":"Services"
        }
    ],
    "sg:phone":"+1 617 536 2040",
    "sg:postcode":"02116",
    "sg:province":"MA",
    "sg:tags":[
        "investing"
    ],
    "wof:name":"Cornerstone Wealth Management",
    "wof:placetype":"venue"
},
  "geometry": {"coordinates":[-71.08041299999999,42.353435],"type":"Point"}
}