{
  "type": "Feature",
  "properties": {
    "addr:full": "262 Beacon St Boston MA 02116",
    "addr:housenumber": "262",
    "addr:postcode": "02116",
    "addr:street": "Beacon St",
    "iso:country": "US",
    "sg:address": "262 Beacon St",
    "sg:city": "Boston",
    "sg:classifiers": [
      {
        "category": "Banks \u0026 Credit Unions",
        "subcategory": "Investment Brokerage",
        "type": "Services"
      }
    ],
    "sg:phone": "+1 617 536 2040",
    "sg:postcode": "02116",
    "sg:province": "MA",
    "sg:tags": [
      "investing"
    ],
    "wof:name": "Cornerstone Wealth Management",
    "wof:placetype": "venue"
  },
  "geometry": {"coordinates":[-71.080413,42.353435],"type":"Point"}
}
