{
  "type": "Feature",
  "properties": {
    "addr:full": "660 Harrison Ave Boston MA 02118",
    "addr:housenumber": "660",
    "addr:postcode": "02118",
    "addr:street": "Harrison Ave",
    "iso:country": "US",
    "sg:address": "660 Harrison Ave",
    "sg:city": "Boston",
    "sg:classifiers": [
      {
        "category": "Health Services",
        "subcategory": "Clinic",
        "type": "Services"
      },
      {
        "category": "Health Services",
        "subcategory": "Hospital",
        "type": "Services"
      }
    ],
    "sg:phone": "+1 617 859 7000",
    "sg:postcode": "02118",
    "sg:province": "MA",
    "sg:tags": [
      "medical",
      "dialysis"
    ],
    "sg:website": "http://www.noorrahman.com",
    "wof:name": "Da Vita Inc",
    "wof:placetype": "venue"
  },
  "geometry": {"coordinates":[-71.070023,42.339039],"type":"Point"}
}
