{
  "type": "Feature",
  "properties": {
    "iso:country":"US",
    "sg:address":"660 Harrison Ave",
    "sg:city":"Boston",
    "sg:classifiers":[
        {
            "category":"Health Services",
            "subcategory":"Clinic",
            "type":"Services"
        },
        {
            "category":"Health Services",
            "subcategory":"Hospital",
            "type":"Services"
        }
    ],
    "sg:phone":"+1 617 859 7000",
    "sg:postcode":"02118",
    "sg:province":"MA",
    "sg:tags":[
        "medical",
        "dialysis"
    ],
    "sg:website":"http://www.noorrahman.com",
    "wof:name":"Da Vita Inc",
    "wof:placetype":"venue"
},
  "geometry": {"coordinates":[-71.07002300000001,42.339039],"type":"Point"}
}