{
  "type": "Feature",
  "properties": {
    "addr:full":"1450 Plymouth Ave Fall River MA 02721",
    "addr:housenumber":"1450",
    "addr:postcode":"02721",
    "addr:street":"Plymouth Ave",
    "iso:country":"US",
    "sg:address":"1450 Plymouth Ave",
    "sg:city":"Fall River",
    "sg:classifiers":[
        {
            "category":"Banks & Credit Unions",
            "subcategory":"Bank",
            "type":"Services"
        }
    ],
    "sg:phone":"+1 508 679 8484",
    "sg:postcode":"02721",
    "sg:province":"MA",
    "wof:name":"Webster Bank",
    "wof:placetype":"venue"
},
  "geometry": {"coordinates":[-71.163793,41.683608],"type":"Point"}
}