{
  "type": "Feature",
  "properties": {
    "addr:full": "74 Fairmont Ave Cambridge MA 02139",
    "addr:housenumber": "74",
    "addr:postcode": "02139",
    "addr:street": "Fairmont Ave",
    "iso:country": "US",
    "sg:address": "74 Fairmont Ave",
    "sg:city": "Cambridge",
    "sg:classifiers": [
      {
        "category": "Professional",
        "subcategory": "Management \u0026 Consulting",
        "type": "Services"
      }
    ],
    "sg:phone": "+1 617 864 3333",
    "sg:postcode": "02139",
    "sg:province": "MA",
    "sg:tags": [
      "consultant",
      "business"
    ],
    "wof:name": "Burruss Consulting Svc",
    "wof:placetype": "venue"
  },
  "geometry": {"coordinates":[-71.112178,42.362035],"type":"Point"}
}
