{
  "type": "Feature",
  "properties": {
    "addr:full": "29 Ox Bow Ln Randolph MA 02368",
    "addr:housenumber": "29",
    "addr:postcode": "02368",
    "addr:street": "Ox Bow Ln",
    "iso:country": "US",
    "sg:address": "29 Ox Bow Ln",
    "sg:city": "Randolph",
    "sg:classifiers": [
      {
        "category": "Wholesale",
        "subcategory": "Stationery",
        "type": "Manufacturing \u0026 Wholesale Goods"
      }
    ],
    "sg:phone": "+1   ",
    "sg:postcode": "02368",
    "sg:province": "MA",
    "sg:tags": [
      "supply"
    ],
    "wof:name": "Gallant Inteprises",
    "wof:placetype": "venue"
  },
  "geometry": {"coordinates":[-71.064614,42.188569],"type":"Point"}
}
