{
  "type": "Feature",
  "properties": {
    "iso:country":"US",
    "sg:address":"29 Ox Bow Ln",
    "sg:city":"Randolph",
    "sg:classifiers":[
        {
            "category":"Wholesale",
            "subcategory":"Stationery",
            "type":"Manufacturing & Wholesale Goods"
        }
    ],
    "sg:phone":"+1   ",
    "sg:postcode":"02368",
    "sg:province":"MA",
    "sg:tags":[
        "supply"
    ],
    "wof:name":"Gallant Inteprises",
    "wof:placetype":"venue"
},
  "geometry": {"coordinates":[-71.06461400000001,42.188569],"type":"Point"}
}