{
  "type": "Feature",
  "properties": {
    "addr:full":"210 Washington St Boston MA 02121",
    "addr:housenumber":"210",
    "addr:postcode":"02121",
    "addr:street":"Washington St",
    "iso:country":"US",
    "sg:address":"210 Washington St",
    "sg:city":"Boston",
    "sg:classifiers":[
        {
            "category":"Retail",
            "subcategory":"Auto Repair",
            "type":"Services"
        }
    ],
    "sg:phone":"+1 617 436 5573",
    "sg:postcode":"02121",
    "sg:province":"MA",
    "sg:tags":[
        "body",
        "automobile",
        "painting",
        "general"
    ],
    "wof:name":"Sandman Auto Body",
    "wof:placetype":"venue"
},
  "geometry": {"coordinates":[-71.078007,42.302807],"type":"Point"}
}