{
  "type": "Feature",
  "properties": {
    "addr:full":"22 Sunset Dr Westfield MA 01085",
    "addr:housenumber":"22",
    "addr:postcode":"01085",
    "addr:street":"Sunset Dr",
    "iso:country":"US",
    "sg:address":"22 Sunset Dr",
    "sg:city":"Westfield",
    "sg:classifiers":[
        {
            "category":"Building & Trades",
            "subcategory":"Landscaping Services",
            "type":"Services"
        }
    ],
    "sg:phone":"+1   ",
    "sg:postcode":"01085",
    "sg:province":"MA",
    "sg:tags":[
        "landscape"
    ],
    "wof:name":"Western Mass Ldscpg Indus Svcs",
    "wof:placetype":"venue"
},
  "geometry": {"coordinates":[-72.734278,42.148826],"type":"Point"}
}