{
  "type": "Feature",
  "properties": {
    "addr:full": "105 Chauncy Street Boston MA 02111",
    "addr:housenumber": "105",
    "addr:postcode": "02111",
    "addr:street": "Chauncy Street",
    "iso:country": "US",
    "sg:address": "105 Chauncy Street",
    "sg:city": "Boston",
    "sg:classifiers": [
      {
        "category": "Social Services",
        "subcategory": "Child Care",
        "type": "Services"
      }
    ],
    "sg:phone": "+1 617 542 5437",
    "sg:postcode": "02111",
    "sg:province": "MA",
    "sg:tags": [
      "day"
    ],
    "wof:name": "Child Care Choices of Boston",
    "wof:placetype": "venue"
  },
  "geometry": {"coordinates":[-71.060709,42.353104],"type":"Point"}
}
