{
  "type": "Feature",
  "properties": {
    "addr:full": "257 Palmer Ave Falmouth MA 02540",
    "addr:housenumber": "257",
    "addr:postcode": "02540",
    "addr:street": "Palmer Ave",
    "iso:country": "US",
    "sg:address": "257 Palmer Ave",
    "sg:city": "Falmouth",
    "sg:classifiers": [
      {
        "category": "Utilities",
        "subcategory": "Refuse",
        "type": "Services"
      }
    ],
    "sg:phone": "+1 508 495 4501",
    "sg:postcode": "02540",
    "sg:province": "MA",
    "sg:tags": [
      "garbage",
      "collection"
    ],
    "wof:name": "Cavossa Disposal",
    "wof:placetype": "venue"
  },
  "geometry": {"coordinates":[-70.619049,41.559653],"type":"Point"}
}
