{
  "type": "Feature",
  "properties": {
    "addr:full": "229 E Main St Milford MA 01757",
    "addr:housenumber": "229",
    "addr:postcode": "01757",
    "addr:street": "E Main St",
    "iso:country": "US",
    "sg:address": "229 E Main St",
    "sg:city": "Milford",
    "sg:classifiers": [
      {
        "category": "Bars \u0026 Pubs",
        "type": "Food \u0026 Drink"
      }
    ],
    "sg:menulink": "http://www.allmenus.com/ma/milford/49284-prezzo-grill--bar/menu/",
    "sg:phone": "+1 508 634 0101",
    "sg:postcode": "01757",
    "sg:province": "MA",
    "sg:tags": [
      "italian"
    ],
    "wof:name": "Prezzo Grill \u0026 Bar",
    "wof:placetype": "venue"
  },
  "geometry": {"coordinates":[-71.500031,42.150793],"type":"Point"}
}
