{
  "type": "Feature",
  "properties": {
    "iso:country":"US",
    "sg:address":"229 E Main St",
    "sg:city":"Milford",
    "sg:classifiers":[
        {
            "category":"Bars & Pubs",
            "type":"Food & Drink"
        }
    ],
    "sg:menulink":"http://www.allmenus.com/ma/milford/49284-prezzo-grill--bar/menu/",
    "sg:phone":"+1 508 634 0101",
    "sg:postcode":"01757",
    "sg:province":"MA",
    "sg:tags":[
        "italian"
    ],
    "wof:name":"Prezzo Grill & Bar",
    "wof:placetype":"venue"
},
  "geometry": {"coordinates":[-71.50003100000001,42.150793],"type":"Point"}
}