{
  "type": "Feature",
  "properties": {
    "iso:country":"US",
    "sg:address":"84 Main St",
    "sg:city":"Harwich",
    "sg:classifiers":[
        {
            "category":"Personal",
            "subcategory":"Beauty Salon",
            "type":"Services"
        }
    ],
    "sg:phone":"+1 508 432 8844",
    "sg:postcode":"02645",
    "sg:province":"MA",
    "wof:name":"Doreen's",
    "wof:placetype":"venue"
},
  "geometry": {"coordinates":[-70.127841,41.699368],"type":"Point"}
}