{
  "type": "Feature",
  "properties": {
    "iso:country":"US",
    "sg:address":"22 Cherry St",
    "sg:city":"Westfield",
    "sg:classifiers":[
        {
            "category":"Freight",
            "type":"Transportation"
        }
    ],
    "sg:phone":"+1 413 568 0982",
    "sg:postcode":"01085",
    "sg:province":"MA",
    "sg:tags":[
        "commercial",
        "storage"
    ],
    "wof:name":"Cherry St Storage",
    "wof:placetype":"venue"
},
  "geometry": {"coordinates":[-72.74476300000001,42.12063],"type":"Point"}
}