{
  "type": "Feature",
  "properties": {
    "addr:full": "22 Cherry St Westfield MA 01085",
    "addr:housenumber": "22",
    "addr:postcode": "01085",
    "addr:street": "Cherry St",
    "iso:country": "US",
    "sg:address": "22 Cherry St",
    "sg:city": "Westfield",
    "sg:classifiers": [
      {
        "category": "Freight",
        "type": "Transportation"
      }
    ],
    "sg:phone": "+1 413 568 0982",
    "sg:postcode": "01085",
    "sg:province": "MA",
    "sg:tags": [
      "commercial",
      "storage"
    ],
    "wof:name": "Cherry St Storage",
    "wof:placetype": "venue"
  },
  "geometry": {"coordinates":[-72.744763,42.12063],"type":"Point"}
}
