{
  "type": "Feature",
  "properties": {
    "iso:country":"US",
    "sg:address":"96 N Pleasant St",
    "sg:city":"Amherst",
    "sg:classifiers":[
        {
            "category":"Restaurant",
            "type":"Food & Drink"
        }
    ],
    "sg:menulink":"http://www.allmenus.com/ma/amherst/31526-souperbowl/menu/",
    "sg:phone":"+1 413 253 1855",
    "sg:postcode":"01002",
    "sg:province":"MA",
    "sg:tags":[
        "soup",
        "american",
        "salad"
    ],
    "wof:name":"SouperBowl",
    "wof:placetype":"venue"
},
  "geometry": {"coordinates":[-72.519902,42.377714],"type":"Point"}
}