{
  "type": "Feature",
  "properties": {
    "addr:full":"53 Main St Fairhaven MA 02719",
    "addr:housenumber":"53",
    "addr:postcode":"02719",
    "addr:street":"Main St",
    "iso:country":"US",
    "sg:address":"53 Main St",
    "sg:city":"Fairhaven",
    "sg:classifiers":[
        {
            "category":"Home & Garden",
            "subcategory":"Furniture",
            "type":"Retail Goods"
        },
        {
            "category":"Home & Garden",
            "subcategory":"Home Furnishings",
            "type":"Retail Goods"
        }
    ],
    "sg:phone":"+1 508 990 8444",
    "sg:postcode":"02719",
    "sg:province":"MA",
    "wof:name":"Enchanted Treasures Inc",
    "wof:placetype":"venue"
},
  "geometry": {"coordinates":[-70.90490699999999,41.636521],"type":"Point"}
}