{
  "type": "Feature",
  "properties": {
    "addr:full": "62 West St Leominster MA 01453",
    "addr:housenumber": "62",
    "addr:postcode": "01453",
    "addr:street": "West St",
    "iso:country": "US",
    "sg:address": "62 West St",
    "sg:city": "Leominster",
    "sg:classifiers": [
      {
        "category": "Social Services",
        "type": "Services"
      }
    ],
    "sg:phone": "+1 978 840 2727",
    "sg:postcode": "01453",
    "sg:province": "MA",
    "sg:tags": [
      "organization",
      "welfare"
    ],
    "wof:name": "Beacon Of Hope",
    "wof:placetype": "venue"
  },
  "geometry": {"coordinates":[-71.763149,42.527279],"type":"Point"}
}
