{
  "type": "Feature",
  "properties": {
    "addr:full": "19 Grant St Ludlow MA 01056",
    "addr:housenumber": "19",
    "addr:postcode": "01056",
    "addr:street": "Grant St",
    "iso:country": "US",
    "sg:address": "19 Grant St",
    "sg:city": "Ludlow",
    "sg:classifiers": [
      {
        "category": "Professional",
        "type": "Services"
      }
    ],
    "sg:phone": "+1   ",
    "sg:postcode": "01056",
    "sg:province": "MA",
    "wof:name": "Gwenn Paliki",
    "wof:placetype": "venue"
  },
  "geometry": {"coordinates":[-72.49653,42.167282],"type":"Point"}
}
