{
  "type": "Feature",
  "properties": {
    "addr:full":"22 Abbott St Worcester MA 01602",
    "addr:housenumber":"22",
    "addr:postcode":"01602",
    "addr:street":"Abbott St",
    "iso:country":"US",
    "sg:address":"22 Abbott St",
    "sg:city":"Worcester",
    "sg:classifiers":[
        {
            "category":"Building & Trades",
            "subcategory":"Landscaping Services",
            "type":"Services"
        }
    ],
    "sg:phone":"+1   ",
    "sg:postcode":"01602",
    "sg:province":"MA",
    "sg:tags":[
        "landscape"
    ],
    "wof:name":"Eaton Jon Land",
    "wof:placetype":"venue"
},
  "geometry": {"coordinates":[-71.821617,42.261887],"type":"Point"}
}