{
  "type": "Feature",
  "properties": {
    "addr:full":"30 Harding St Milford MA 01757",
    "addr:housenumber":"30",
    "addr:postcode":"01757",
    "addr:street":"Harding St",
    "iso:country":"US",
    "sg:address":"30 Harding St",
    "sg:city":"Milford",
    "sg:classifiers":[
        {
            "category":"Utilities",
            "subcategory":"Mobile Phone",
            "type":"Services"
        }
    ],
    "sg:phone":"+1 508 473 3145",
    "sg:postcode":"01757",
    "sg:province":"MA",
    "sg:tags":[
        "telephone",
        "cellular"
    ],
    "wof:name":"Karma Wireless Inc",
    "wof:placetype":"venue"
},
  "geometry": {"coordinates":[-71.54209899999999,42.14896],"type":"Point"}
}