{
  "type": "Feature",
  "properties": {
    "addr:full":"50 Judge St Fall River MA 02721",
    "addr:housenumber":"50",
    "addr:postcode":"02721",
    "addr:street":"Judge St",
    "iso:country":"US",
    "sg:address":"50 Judge St",
    "sg:city":"Fall River",
    "sg:classifiers":[
        {
            "category":"Health Services",
            "subcategory":"Clinic",
            "type":"Services"
        }
    ],
    "sg:phone":"+1 508 672 3651",
    "sg:postcode":"02721",
    "sg:province":"MA",
    "wof:name":"Specialized Health Care Svc",
    "wof:placetype":"venue"
},
  "geometry": {"coordinates":[-71.13201100000001,41.649147],"type":"Point"}
}