{
  "type": "Feature",
  "properties": {
    "iso:country":"US",
    "sg:address":"408 Atlantic Ave",
    "sg:city":"Boston",
    "sg:classifiers":[
        {
            "category":"Recreation",
            "type":"Entertainment"
        }
    ],
    "sg:phone":"+1 617 223 8672",
    "sg:postcode":"02110",
    "sg:province":"MA",
    "sg:tags":[
        "parks"
    ],
    "wof:name":"Boston Harbor Islands Park",
    "wof:placetype":"venue"
},
  "geometry": {"coordinates":[-71.050971,42.355161],"type":"Point"}
}