{
  "type": "Feature",
  "properties": {
    "addr:full":"16 Orono St Milton MA 02186",
    "addr:housenumber":"16",
    "addr:postcode":"02186",
    "addr:street":"Orono St",
    "iso:country":"US",
    "sg:address":"16 Orono St",
    "sg:city":"Milton",
    "sg:classifiers":[
        {
            "category":"Professional",
            "subcategory":"Computer Services",
            "type":"Services"
        }
    ],
    "sg:phone":"+1   ",
    "sg:postcode":"02186",
    "sg:province":"MA",
    "sg:tags":[
        "design",
        "system"
    ],
    "wof:name":"Eileen Callahan Design",
    "wof:placetype":"venue"
},
  "geometry": {"coordinates":[-71.08792,42.259853],"type":"Point"}
}