{
  "type": "Feature",
  "properties": {
    "addr:full":"1531 Massachusetts Ave Arlington MA 02476",
    "addr:housenumber":"1531",
    "addr:postcode":"02476",
    "addr:street":"Massachusetts Ave",
    "iso:country":"US",
    "sg:address":"1531 Massachusetts Ave",
    "sg:city":"Arlington",
    "sg:phone":"+1 781 648 3100",
    "sg:postcode":"02476",
    "sg:province":"MA",
    "sg:website":"http://www.chisholmandsons.com",
    "wof:name":"Chisholm And Sons Glass",
    "wof:placetype":"venue"
},
  "geometry": {"coordinates":[-71.191188,42.425401],"type":"Point"}
}