{
  "type": "Feature",
  "properties": {
    "addr:full":"23 Hawthorne Dr Franklin MA 02038",
    "addr:housenumber":"23",
    "addr:postcode":"02038",
    "addr:street":"Hawthorne Dr",
    "iso:country":"US",
    "sg:address":"23 Hawthorne Dr",
    "sg:city":"Franklin",
    "sg:classifiers":[
        {
            "category":"Shopping",
            "subcategory":"Computers & Home Electronics",
            "type":"Retail Goods"
        }
    ],
    "sg:phone":"+1 508 533 5005",
    "sg:postcode":"02038",
    "sg:province":"MA",
    "sg:tags":[
        "software"
    ],
    "wof:name":"Hotel Data Systems",
    "wof:placetype":"venue"
},
  "geometry": {"coordinates":[-71.39259,42.106422],"type":"Point"}
}