{
  "type": "Feature",
  "properties": {
    "iso:country":"US",
    "sg:address":"8 Abigail Dr",
    "sg:city":"Hudson",
    "sg:classifiers":[
        {
            "category":"Retail",
            "subcategory":"Photofinishing",
            "type":"Services"
        }
    ],
    "sg:phone":"+1   ",
    "sg:postcode":"01749",
    "sg:province":"MA",
    "sg:tags":[
        "laboratory"
    ],
    "wof:name":"Vals Digital Darkroom",
    "wof:placetype":"venue"
},
  "geometry": {"coordinates":[-71.528469,42.379803],"type":"Point"}
}