{
  "type": "Feature",
  "properties": {
    "addr:full": "58 Long Pond Rd Plymouth MA 02360",
    "addr:housenumber": "58",
    "addr:postcode": "02360",
    "addr:street": "Long Pond Rd",
    "iso:country": "US",
    "sg:address": "58 Long Pond Rd",
    "sg:city": "Plymouth",
    "sg:classifiers": [
      {
        "category": "Building \u0026 Trades",
        "subcategory": "Construction",
        "type": "Services"
      }
    ],
    "sg:phone": "+1   ",
    "sg:postcode": "02360",
    "sg:province": "MA",
    "sg:tags": [
      "residential"
    ],
    "wof:name": "Torrey Co",
    "wof:placetype": "venue"
  },
  "geometry": {"coordinates":[-70.657274,41.928986],"type":"Point"}
}
