{
  "type": "Feature",
  "properties": {
    "iso:country":"US",
    "sg:address":"58 Long Pond Rd",
    "sg:city":"Plymouth",
    "sg:classifiers":[
        {
            "category":"Building & Trades",
            "subcategory":"Construction",
            "type":"Services"
        }
    ],
    "sg:phone":"+1   ",
    "sg:postcode":"02360",
    "sg:province":"MA",
    "sg:tags":[
        "residential"
    ],
    "wof:name":"Torrey Co",
    "wof:placetype":"venue"
},
  "geometry": {"coordinates":[-70.657274,41.928986],"type":"Point"}
}