{
  "type": "Feature",
  "properties": {
    "iso:country":"US",
    "sg:address":"485 Riverside Rd",
    "sg:city":"Springfield",
    "sg:classifiers":[
        {
            "category":"Building & Trades",
            "subcategory":"Construction",
            "type":"Services"
        }
    ],
    "sg:phone":"+1   ",
    "sg:postcode":"01107",
    "sg:province":"MA",
    "sg:tags":[
        "hanging",
        "contractor"
    ],
    "wof:name":"Colons Repairs & Painting",
    "wof:placetype":"venue"
},
  "geometry": {"coordinates":[-72.61925100000001,42.121816],"type":"Point"}
}