{
  "type": "Feature",
  "properties": {
    "addr:full": "485 Riverside Rd Springfield MA 01107",
    "addr:housenumber": "485",
    "addr:postcode": "01107",
    "addr:street": "Riverside Rd",
    "iso:country": "US",
    "sg:address": "485 Riverside Rd",
    "sg:city": "Springfield",
    "sg:classifiers": [
      {
        "category": "Building \u0026 Trades",
        "subcategory": "Construction",
        "type": "Services"
      }
    ],
    "sg:phone": "+1   ",
    "sg:postcode": "01107",
    "sg:province": "MA",
    "sg:tags": [
      "hanging",
      "contractor"
    ],
    "wof:name": "Colons Repairs \u0026 Painting",
    "wof:placetype": "venue"
  },
  "geometry": {"coordinates":[-72.619251,42.121816],"type":"Point"}
}
