{
  "type": "Feature",
  "properties": {
    "addr:full":"916 Dorchester Ave Dorchester MA 02125",
    "addr:housenumber":"916",
    "addr:postcode":"02125",
    "addr:street":"Dorchester Ave",
    "iso:country":"US",
    "sg:address":"916 Dorchester Ave",
    "sg:city":"Dorchester",
    "sg:classifiers":[
        {
            "category":"Health Services",
            "subcategory":"Chiropractor",
            "type":"Services"
        }
    ],
    "sg:phone":"+1 617 282 2828",
    "sg:postcode":"02125",
    "sg:province":"MA",
    "wof:name":"First Spine & Rehab",
    "wof:placetype":"venue"
},
  "geometry": {"coordinates":[-71.0565,42.3197],"type":"Point"}
}