{
  "type": "Feature",
  "properties": {
    "iso:country":"US",
    "sg:address":"42 Pikes Hill Rd",
    "sg:city":"Sterling",
    "sg:classifiers":[
        {
            "category":"Professional",
            "subcategory":"Management & Consulting",
            "type":"Services"
        }
    ],
    "sg:phone":"+1 978 422 9740",
    "sg:postcode":"01564",
    "sg:province":"MA",
    "sg:tags":[
        "science",
        "consultant",
        "academic"
    ],
    "wof:name":"Parker Environmental Corp",
    "wof:placetype":"venue"
},
  "geometry": {"coordinates":[-71.82547700000001,42.42837],"type":"Point"}
}