{
  "type": "Feature",
  "properties": {
    "addr:full":"287 Lowell St Reading MA 01867",
    "addr:housenumber":"287",
    "addr:postcode":"01867",
    "addr:street":"Lowell St",
    "iso:country":"US",
    "sg:address":"287 Lowell St",
    "sg:city":"Reading",
    "sg:classifiers":[
        {
            "category":"Food & Beverages",
            "subcategory":"Groceries & Convenience Stores",
            "type":"Retail Goods"
        }
    ],
    "sg:phone":"+1 781 944 3524",
    "sg:postcode":"01867",
    "sg:province":"MA",
    "wof:name":"P & S Convenient",
    "wof:placetype":"venue"
},
  "geometry": {"coordinates":[-71.118599,42.531601],"type":"Point"}
}