{
  "type": "Feature",
  "properties": {
    "addr:full": "40 Dimock St Roxbury MA 02119",
    "addr:housenumber": "40",
    "addr:postcode": "02119",
    "addr:street": "Dimock St",
    "iso:country": "US",
    "sg:address": "40 Dimock St",
    "sg:city": "Roxbury",
    "sg:classifiers": [
      {
        "category": "Professional",
        "subcategory": "Employment Agencies",
        "type": "Services"
      }
    ],
    "sg:phone": "+1 617 427 1545",
    "sg:postcode": "02119",
    "sg:province": "MA",
    "sg:tags": [
      "teachers'"
    ],
    "wof:name": "Metropolitan Council For Educa",
    "wof:placetype": "venue"
  },
  "geometry": {"coordinates":[-71.097504,42.319511],"type":"Point"}
}
