{
  "type": "Feature",
  "properties": {
    "iso:country":"US",
    "sg:address":"1265 Whipple Rd",
    "sg:city":"Tewksbury",
    "sg:classifiers":[
        {
            "category":"Home & Garden",
            "subcategory":"Garden Supply",
            "type":"Retail Goods"
        }
    ],
    "sg:phone":"+1 978 863 1991",
    "sg:postcode":"01876",
    "sg:province":"MA",
    "sg:tags":[
        "lawn",
        "mower"
    ],
    "wof:name":"Small Engine Shop Inc",
    "wof:placetype":"venue"
},
  "geometry": {"coordinates":[-71.23531,42.586687],"type":"Point"}
}