{
  "type": "Feature",
  "properties": {
    "addr:full": "150 Main St Peabody MA 01960",
    "addr:housenumber": "150",
    "addr:postcode": "01960",
    "addr:street": "Main St",
    "iso:country": "US",
    "sg:address": "150 Main St",
    "sg:city": "Peabody",
    "sg:classifiers": [
      {
        "category": "Restaurant",
        "type": "Food \u0026 Drink"
      }
    ],
    "sg:phone": "+1 978 532 1530",
    "sg:postcode": "01960",
    "sg:province": "MA",
    "wof:name": "Bernardo's Pizza",
    "wof:placetype": "venue"
  },
  "geometry": {"coordinates":[-70.920391,42.523121],"type":"Point"}
}
