{
  "type": "Feature",
  "properties": {
    "addr:full": "16 Pondview Pl Tyngsboro MA 01879",
    "addr:housenumber": "16",
    "addr:postcode": "01879",
    "addr:street": "Pondview Pl",
    "iso:country": "US",
    "sg:address": "16 Pondview Pl",
    "sg:city": "Tyngsboro",
    "sg:classifiers": [
      {
        "category": "Shopping",
        "type": "Retail Goods"
      }
    ],
    "sg:phone": "+1 978 649 7228",
    "sg:postcode": "01879",
    "sg:province": "MA",
    "sg:tags": [
      "limb",
      "artificial"
    ],
    "wof:name": "New England Hair Illusions",
    "wof:placetype": "venue"
  },
  "geometry": {"coordinates":[-71.434371,42.68722],"type":"Point"}
}
