{
  "type": "Feature",
  "properties": {
    "iso:country":"US",
    "sg:address":"39 Delorenzo Dr",
    "sg:city":"Duxbury",
    "sg:classifiers":[
        {
            "category":"Professional",
            "subcategory":"Employment Agencies",
            "type":"Services"
        }
    ],
    "sg:phone":"+1 781 582 2535",
    "sg:postcode":"02332",
    "sg:province":"MA",
    "sg:tags":[
        "consultant",
        "search",
        "executive"
    ],
    "wof:name":"Mountain Hire",
    "wof:placetype":"venue"
},
  "geometry": {"coordinates":[-70.749863,42.046537],"type":"Point"}
}