{
  "type": "Feature",
  "properties": {
    "iso:country":"US",
    "sg:address":"1148 Washington St",
    "sg:city":"Norwood",
    "sg:classifiers":[
        {
            "category":"Banks & Credit Unions",
            "subcategory":"Bank",
            "type":"Services"
        }
    ],
    "sg:phone":"+1 781 769 5169",
    "sg:postcode":"02062",
    "sg:province":"MA",
    "wof:name":"Norwood Town Employees Federal Credit Union",
    "wof:placetype":"venue"
},
  "geometry": {"coordinates":[-71.2062,42.177898],"type":"Point"}
}