{
  "type": "Feature",
  "properties": {
    "addr:full": "76 Elm St Westfield MA 01085",
    "addr:housenumber": "76",
    "addr:postcode": "01085",
    "addr:street": "Elm St",
    "iso:country": "US",
    "sg:address": "76 Elm St",
    "sg:city": "Westfield",
    "sg:classifiers": [
      {
        "category": "Banks \u0026 Credit Unions",
        "subcategory": "Investment Brokerage",
        "type": "Services"
      }
    ],
    "sg:phone": "+1 413 568 3377",
    "sg:postcode": "01085",
    "sg:province": "MA",
    "sg:tags": [
      "consultant",
      "planning",
      "financial"
    ],
    "wof:name": "Peter Gould Financial Svc",
    "wof:placetype": "venue"
  },
  "geometry": {"coordinates":[-72.748768,42.122023],"type":"Point"}
}
