{
  "type": "Feature",
  "properties": {
    "iso:country":"US",
    "sg:address":"210 N Main St",
    "sg:city":"Sharon",
    "sg:classifiers":[
        {
            "category":"Professional",
            "subcategory":"Lawyer & Legal Services",
            "type":"Services"
        }
    ],
    "sg:phone":"+1 781 784 0600",
    "sg:postcode":"02067",
    "sg:province":"MA",
    "wof:name":"Fine Elliott & Associates",
    "wof:placetype":"venue"
},
  "geometry": {"coordinates":[-71.171117,42.134628],"type":"Point"}
}