{
  "type": "Feature",
  "properties": {
    "addr:full": "210 N Main St Sharon MA 02067",
    "addr:housenumber": "210",
    "addr:postcode": "02067",
    "addr:street": "N Main St",
    "iso:country": "US",
    "sg:address": "210 N Main St",
    "sg:city": "Sharon",
    "sg:classifiers": [
      {
        "category": "Professional",
        "subcategory": "Lawyer \u0026 Legal Services",
        "type": "Services"
      }
    ],
    "sg:phone": "+1 781 784 0600",
    "sg:postcode": "02067",
    "sg:province": "MA",
    "wof:name": "Fine Elliott \u0026 Associates",
    "wof:placetype": "venue"
  },
  "geometry": {"coordinates":[-71.171117,42.134628],"type":"Point"}
}
