{
  "type": "Feature",
  "properties": {
    "addr:full":"968 Bedford St Abington MA 02351",
    "addr:housenumber":"968",
    "addr:postcode":"02351",
    "addr:street":"Bedford St",
    "iso:country":"US",
    "sg:address":"968 Bedford St",
    "sg:city":"Abington",
    "sg:classifiers":[
        {
            "category":"Food & Beverages",
            "subcategory":"Groceries & Convenience Stores",
            "type":"Retail Goods"
        }
    ],
    "sg:phone":"+1 781 878 2633",
    "sg:postcode":"02351",
    "sg:province":"MA",
    "wof:name":"Tedeschi Food Shops",
    "wof:placetype":"venue"
},
  "geometry": {"coordinates":[-70.95013400000001,42.130893],"type":"Point"}
}