{
  "type": "Feature",
  "properties": {
    "addr:full": "1 Court St Plymouth MA 02360",
    "addr:housenumber": "1",
    "addr:postcode": "02360",
    "addr:street": "Court St",
    "iso:country": "US",
    "sg:address": "1 Court St",
    "sg:city": "Plymouth",
    "sg:classifiers": [
      {
        "category": "Museum",
        "type": "Entertainment"
      }
    ],
    "sg:phone": "+1 508 746 0616",
    "sg:postcode": "02360",
    "sg:province": "MA",
    "wof:name": "Museum Surplus Ltd",
    "wof:placetype": "venue"
  },
  "geometry": {"coordinates":[-70.664001,41.955799],"type":"Point"}
}
