{
  "type": "Feature",
  "properties": {
    "addr:full": "698 Eastern Ave Malden MA 02148",
    "addr:housenumber": "698",
    "addr:postcode": "02148",
    "addr:street": "Eastern Ave",
    "iso:country": "US",
    "sg:address": "698 Eastern Ave",
    "sg:city": "Malden",
    "sg:classifiers": [
      {
        "category": "Utilities",
        "subcategory": "Mobile Phone",
        "type": "Services"
      },
      {
        "category": "Shopping",
        "subcategory": "Mobile Phones",
        "type": "Retail Goods"
      }
    ],
    "sg:phone": "+1 781 321 1187",
    "sg:postcode": "02148",
    "sg:province": "MA",
    "sg:tags": [
      "equipment",
      "telephone",
      "cellular",
      "supply"
    ],
    "wof:name": "Cellco Partnership",
    "wof:placetype": "venue"
  },
  "geometry": {"coordinates":[-71.049778,42.429606],"type":"Point"}
}
