{
  "type": "Feature",
  "properties": {
    "addr:full": "75 Technology Dr Lowell MA 01851",
    "addr:housenumber": "75",
    "addr:postcode": "01851",
    "addr:street": "Technology Dr",
    "iso:country": "US",
    "sg:address": "75 Technology Dr",
    "sg:city": "Lowell",
    "sg:classifiers": [
      {
        "category": "Home \u0026 Garden",
        "subcategory": "Hardware",
        "type": "Retail Goods"
      }
    ],
    "sg:phone": "+1 978 453 3083",
    "sg:postcode": "01851",
    "sg:province": "MA",
    "sg:tags": [
      "filters-liquid"
    ],
    "wof:name": "United States Filter Corporation Proj",
    "wof:placetype": "venue"
  },
  "geometry": {"coordinates":[-71.359413,42.628021],"type":"Point"}
}
