{
  "type": "Feature",
  "properties": {
    "iso:country":"US",
    "sg:address":"29 Winn St",
    "sg:city":"Burlington",
    "sg:classifiers":[
        {
            "category":"Building & Trades",
            "subcategory":"Locksmith",
            "type":"Services"
        }
    ],
    "sg:phone":"+1 781 912 0485",
    "sg:postcode":"01803",
    "sg:province":"MA",
    "sg:tags":[
        "key"
    ],
    "wof:name":"0 1 24 Hour Emergency A Locksmith",
    "wof:placetype":"venue"
},
  "geometry": {"coordinates":[-71.17362900000001,42.490599],"type":"Point"}
}