{
  "type": "Feature",
  "properties": {
    "iso:country":"US",
    "sg:address":"34 Bates St",
    "sg:city":"Mashpee",
    "sg:classifiers":[
        {
            "category":"Health Services",
            "subcategory":"Doctor",
            "type":"Services"
        }
    ],
    "sg:phone":"+1 508 539 3353",
    "sg:postcode":"02655",
    "sg:province":"MA",
    "sg:tags":[
        "physician",
        "surgeon"
    ],
    "wof:name":"Cape Cod Family Practice",
    "wof:placetype":"venue"
},
  "geometry": {"coordinates":[-70.380422,41.62527],"type":"Point"}
}