{
  "type": "Feature",
  "properties": {
    "addr:full": "61 N Falmouth Hwy North Falmouth MA 02556",
    "addr:housenumber": "61",
    "addr:postcode": "02556",
    "addr:street": "N Falmouth Hwy North",
    "iso:country": "US",
    "sg:address": "61 N Falmouth Hwy",
    "sg:city": "North Falmouth",
    "sg:classifiers": [
      {
        "category": "Building \u0026 Trades",
        "subcategory": "Construction",
        "type": "Services"
      }
    ],
    "sg:phone": "+1 508 563 7584",
    "sg:postcode": "02556",
    "sg:province": "MA",
    "sg:tags": [
      "masonry",
      "contractor"
    ],
    "wof:name": "Robert Andrade Masonry",
    "wof:placetype": "venue"
  },
  "geometry": {"coordinates":[-70.622755,41.619217],"type":"Point"}
}
