{
  "type": "Feature",
  "properties": {
    "addr:full": "724 Main St Winchester MA 01890",
    "addr:housenumber": "724",
    "addr:postcode": "01890",
    "addr:street": "Main St",
    "iso:country": "US",
    "sg:address": "724 Main St",
    "sg:city": "Winchester",
    "sg:classifiers": [
      {
        "category": "Professional",
        "type": "Services"
      }
    ],
    "sg:phone": "+1 781 721 0003",
    "sg:postcode": "01890",
    "sg:province": "MA",
    "sg:tags": [
      "contractor"
    ],
    "wof:name": "Sarcon Corp",
    "wof:placetype": "venue"
  },
  "geometry": {"coordinates":[-71.138298,42.4571],"type":"Point"}
}
