{
  "type": "Feature",
  "properties": {
    "addr:full": "256 Herman Melville Blvd New Bedford MA 02740",
    "addr:housenumber": "256",
    "addr:postcode": "02740",
    "addr:street": "Herman Melville Blvd",
    "iso:country": "US",
    "ovtr:label": "Marine Hydraulics, 256 Herman Melville Blvd New Bedford MA US",
    "ovtr:similarity": 1.6448090076446533,
    "sg:address": "256 Herman Melville Blvd",
    "sg:city": "New Bedford",
    "sg:classifiers": [
      {
        "category": "Manufacturing",
        "subcategory": "Tools \u0026 Machinery",
        "type": "Manufacturing \u0026 Wholesale Goods"
      }
    ],
    "sg:phone": "+1 508 990 2866",
    "sg:postcode": "02740",
    "sg:province": "MA",
    "wof:name": "Marine Hydraulics",
    "wof:placetype": "venue"
  },
  "geometry": {"coordinates":[-70.924043,41.644852],"type":"Point"}
}
