{
  "type": "Feature",
  "properties": {
    "iso:country":"US",
    "sg:address":"322 Lincoln St",
    "sg:city":"Hingham",
    "sg:classifiers":[
        {
            "category":"Shopping",
            "subcategory":"Hobbies, Toys, & Games",
            "type":"Retail Goods"
        },
        {
            "category":"Recreation",
            "subcategory":"Gun Range",
            "type":"Entertainment"
        }
    ],
    "sg:phone":"+1 781 749 1303",
    "sg:postcode":"02043",
    "sg:province":"MA",
    "sg:tags":[
        "ammunition",
        "gunsmith"
    ],
    "wof:name":"Fb Krause & Sons",
    "wof:placetype":"venue"
},
  "geometry": {"coordinates":[-70.917992,42.249359],"type":"Point"}
}