{
  "type": "Feature",
  "properties": {
    "iso:country":"US",
    "sg:address":"25 S Spring St",
    "sg:city":"Haverhill",
    "sg:classifiers":[
        {
            "category":"Education",
            "subcategory":"School",
            "type":"Public Place"
        }
    ],
    "sg:phone":"+1 978 374 3467",
    "sg:postcode":"01835",
    "sg:province":"MA",
    "sg:tags":[
        "elementary"
    ],
    "sg:website":"http://www.haverhillwater.com",
    "wof:name":"R L Wood Elementary School",
    "wof:placetype":"venue"
},
  "geometry": {"coordinates":[-71.08863599999999,42.763932],"type":"Point"}
}