{
  "type": "Feature",
  "properties": {
    "addr:full":"374 Beulah St Whitman MA 02382",
    "addr:housenumber":"374",
    "addr:postcode":"02382",
    "addr:street":"Beulah St",
    "iso:country":"US",
    "sg:address":"374 Beulah St",
    "sg:city":"Whitman",
    "sg:classifiers":[
        {
            "category":"Building & Trades",
            "subcategory":"Electrical",
            "type":"Services"
        }
    ],
    "sg:phone":"+1   ",
    "sg:postcode":"02382",
    "sg:province":"MA",
    "sg:tags":[
        "electrical",
        "contractor"
    ],
    "wof:name":"Morrill Electric & Alarm Co",
    "wof:placetype":"venue"
},
  "geometry": {"coordinates":[-70.943018,42.08592],"type":"Point"}
}