{
  "type": "Feature",
  "properties": {
    "iso:country":"US",
    "sg:address":"27 Howley St",
    "sg:city":"Peabody",
    "sg:classifiers":[
        {
            "category":"Manufacturing",
            "subcategory":"Apparel",
            "type":"Manufacturing & Wholesale Goods"
        }
    ],
    "sg:phone":"+1 978 531 9021",
    "sg:postcode":"01960",
    "sg:province":"MA",
    "sg:tags":[
        "canvas",
        "product",
        "related"
    ],
    "sg:website":"www.allensautotrim.com",
    "wof:name":"Allen's Auto Trim Inc",
    "wof:placetype":"venue"
},
  "geometry": {"coordinates":[-70.91860200000001,42.52451],"type":"Point"}
}