{
  "type": "Feature",
  "properties": {
    "iso:country":"US",
    "sg:address":"329 W Main St",
    "sg:city":"Northborough",
    "sg:classifiers":[
        {
            "category":"Utilities",
            "subcategory":"Telephone",
            "type":"Services"
        }
    ],
    "sg:phone":"+1 508 393 0176",
    "sg:postcode":"01532",
    "sg:province":"MA",
    "sg:tags":[
        "telecommunication"
    ],
    "wof:name":"Mediafonx Corp",
    "wof:placetype":"venue"
},
  "geometry": {"coordinates":[-71.65915200000001,42.306789],"type":"Point"}
}