{
  "type": "Feature",
  "properties": {
    "addr:full": "27 Depot St East Wareham MA 02538",
    "addr:housenumber": "27",
    "addr:postcode": "02538",
    "addr:street": "Depot St",
    "iso:country": "US",
    "sg:address": "27 Depot St",
    "sg:city": "East Wareham",
    "sg:classifiers": [
      {
        "category": "Education",
        "subcategory": "School",
        "type": "Public Place"
      }
    ],
    "sg:phone": "+1 508 291 3586",
    "sg:postcode": "02538",
    "sg:province": "MA",
    "sg:tags": [
      "high",
      "middle",
      "elementary"
    ],
    "wof:name": "Wareham Town of",
    "wof:placetype": "venue"
  },
  "geometry": {"coordinates":[-70.675977,41.758519],"type":"Point"}
}
