{
  "type": "Feature",
  "properties": {
    "addr:full": "245 Summer St Boston MA 02210",
    "addr:housenumber": "245",
    "addr:postcode": "02210",
    "addr:street": "Summer St",
    "iso:country": "US",
    "sg:address": "245 Summer St",
    "sg:city": "Boston",
    "sg:classifiers": [
      {
        "category": "Building \u0026 Trades",
        "subcategory": "Locksmith",
        "type": "Services"
      }
    ],
    "sg:phone": "+1 617 671 0882",
    "sg:postcode": "02210",
    "sg:province": "MA",
    "sg:tags": [
      "key"
    ],
    "wof:name": "20 24 Hours Locksmith",
    "wof:placetype": "venue"
  },
  "geometry": {"coordinates":[-71.053268,42.351352],"type":"Point"}
}
