{
  "type": "Feature",
  "properties": {
    "addr:full":"42 Jerome Ave Newton MA 02465",
    "addr:housenumber":"42",
    "addr:postcode":"02465",
    "addr:street":"Jerome Ave",
    "iso:country":"US",
    "sg:address":"42 Jerome Ave",
    "sg:city":"Newton",
    "sg:classifiers":[
        {
            "category":"Professional",
            "subcategory":"Business Services",
            "type":"Services"
        }
    ],
    "sg:phone":"+1   ",
    "sg:postcode":"02465",
    "sg:province":"MA",
    "sg:tags":[
        "rubber",
        "stamp",
        "pen",
        "sales"
    ],
    "wof:name":"Stamp Rite Pens",
    "wof:placetype":"venue"
},
  "geometry": {"coordinates":[-71.22905299999999,42.35968],"type":"Point"}
}