{
  "type": "Feature",
  "properties": {
    "iso:country":"US",
    "sg:address":"100 Cambridgeside Pl",
    "sg:city":"Cambridge",
    "sg:classifiers":[
        {
            "category":"Shopping",
            "subcategory":"Clothing, Apparel, & Fashions",
            "type":"Retail Goods"
        }
    ],
    "sg:phone":"+1 617 494 9386",
    "sg:postcode":"02141",
    "sg:province":"MA",
    "sg:tags":[
        "children's",
        "girls'",
        "clothing"
    ],
    "sg:website":"www.gap.com",
    "wof:name":"Gap",
    "wof:placetype":"venue"
},
  "geometry": {"coordinates":[-71.076014,42.367035],"type":"Point"}
}