{
  "type": "Feature",
  "properties": {
    "iso:country":"US",
    "sg:address":"137 Hillside Ave",
    "sg:city":"Rehoboth",
    "sg:classifiers":[
        {
            "category":"Building & Trades",
            "subcategory":"Construction",
            "type":"Services"
        }
    ],
    "sg:phone":"+1   ",
    "sg:postcode":"02769",
    "sg:province":"MA",
    "sg:tags":[
        "house"
    ],
    "wof:name":"Richard G Dias Const",
    "wof:placetype":"venue"
},
  "geometry": {"coordinates":[-71.273228,41.84735],"type":"Point"}
}