{
  "type": "Feature",
  "properties": {
    "addr:full": "137 Hillside Ave Rehoboth MA 02769",
    "addr:housenumber": "137",
    "addr:postcode": "02769",
    "addr:street": "Hillside Ave",
    "iso:country": "US",
    "sg:address": "137 Hillside Ave",
    "sg:city": "Rehoboth",
    "sg:classifiers": [
      {
        "category": "Building \u0026 Trades",
        "subcategory": "Construction",
        "type": "Services"
      }
    ],
    "sg:phone": "+1   ",
    "sg:postcode": "02769",
    "sg:province": "MA",
    "sg:tags": [
      "house"
    ],
    "wof:name": "Richard G Dias Const",
    "wof:placetype": "venue"
  },
  "geometry": {"coordinates":[-71.273228,41.84735],"type":"Point"}
}
