{
  "type": "Feature",
  "properties": {
    "iso:country":"US",
    "sg:address":"10 Stevens Rd",
    "sg:city":"Fitchburg",
    "sg:classifiers":[
        {
            "category":"Shopping",
            "subcategory":"Gifts & Souvenirs",
            "type":"Retail Goods"
        }
    ],
    "sg:phone":"+1 978 342 1414",
    "sg:postcode":"01420",
    "sg:province":"MA",
    "sg:tags":[
        "collectible"
    ],
    "sg:website":"www.conversationconcepts.com",
    "wof:name":"Conversation Concepts",
    "wof:placetype":"venue"
},
  "geometry": {"coordinates":[-71.853641,42.56391],"type":"Point"}
}