{
  "type": "Feature",
  "properties": {
    "iso:country":"US",
    "sg:address":"12 Heather Hill Rd",
    "sg:city":"Sandwich",
    "sg:classifiers":[
        {
            "category":"Building & Trades",
            "subcategory":"Plumbing",
            "type":"Services"
        }
    ],
    "sg:phone":"+1 508 420 3916",
    "sg:postcode":"02563",
    "sg:province":"MA",
    "sg:tags":[
        "plumbing",
        "contractor"
    ],
    "wof:name":"Stewart Plumbing & Heating",
    "wof:placetype":"venue"
},
  "geometry": {"coordinates":[-70.47174200000001,41.682041],"type":"Point"}
}