{
  "type": "Feature",
  "properties": {
    "addr:full": "12 Heather Hill Rd Sandwich MA 02563",
    "addr:housenumber": "12",
    "addr:postcode": "02563",
    "addr:street": "Heather Hill Rd",
    "iso:country": "US",
    "sg:address": "12 Heather Hill Rd",
    "sg:city": "Sandwich",
    "sg:classifiers": [
      {
        "category": "Building \u0026 Trades",
        "subcategory": "Plumbing",
        "type": "Services"
      }
    ],
    "sg:phone": "+1 508 420 3916",
    "sg:postcode": "02563",
    "sg:province": "MA",
    "sg:tags": [
      "plumbing",
      "contractor"
    ],
    "wof:name": "Stewart Plumbing \u0026 Heating",
    "wof:placetype": "venue"
  },
  "geometry": {"coordinates":[-70.471742,41.682041],"type":"Point"}
}
