{
  "type": "Feature",
  "properties": {
    "addr:full":"125 Burlington St Lexington MA 02420",
    "addr:housenumber":"125",
    "addr:postcode":"02420",
    "addr:street":"Burlington St",
    "iso:country":"US",
    "sg:address":"125 Burlington St",
    "sg:city":"Lexington",
    "sg:classifiers":[
        {
            "category":"Professional",
            "type":"Services"
        }
    ],
    "sg:phone":"+1   ",
    "sg:postcode":"02420",
    "sg:province":"MA",
    "wof:name":"Bentley/Jnh Ltd Partnersh",
    "wof:placetype":"venue"
},
  "geometry": {"coordinates":[-71.226568,42.470369],"type":"Point"}
}