{
  "type": "Feature",
  "properties": {
    "addr:full":"89 Newbury St Ste 200 Danvers MA 01923",
    "addr:housenumber":"89",
    "addr:postcode":"01923",
    "addr:street":"Newbury St Ste 200",
    "iso:country":"US",
    "sg:address":"89 Newbury St Ste 200",
    "sg:city":"Danvers",
    "sg:classifiers":[
        {
            "category":"Professional",
            "subcategory":"Management & Consulting",
            "type":"Services"
        },
        {
            "category":"Banks & Credit Unions",
            "subcategory":"Financial Services",
            "type":"Services"
        }
    ],
    "sg:phone":"+1 978 750 0450",
    "sg:postcode":"01923",
    "sg:province":"MA",
    "sg:tags":[
        "consultant",
        "financing",
        "planning"
    ],
    "wof:name":"Atlantic Wealth Strategies",
    "wof:placetype":"venue"
},
  "geometry": {"coordinates":[-70.97587300000001,42.564111],"type":"Point"}
}