{
  "type": "Feature",
  "properties": {
    "addr:full":"29 Robken Rd Roslindale MA 02131",
    "addr:housenumber":"29",
    "addr:postcode":"02131",
    "addr:street":"Robken Rd",
    "iso:country":"US",
    "sg:address":"29 Robken Rd",
    "sg:city":"Roslindale",
    "sg:classifiers":[
        {
            "category":"Professional",
            "subcategory":"Computer Services",
            "type":"Services"
        },
        {
            "category":"Wholesale",
            "subcategory":"Computers",
            "type":"Manufacturing & Wholesale Goods"
        }
    ],
    "sg:phone":"+1 617 325 2574",
    "sg:postcode":"02131",
    "sg:province":"MA",
    "sg:tags":[
        "equipment",
        "software"
    ],
    "wof:name":"Compu Fact Inc",
    "wof:placetype":"venue"
},
  "geometry": {"coordinates":[-71.134344,42.293571],"type":"Point"}
}