{
  "type": "Feature",
  "properties": {
    "iso:country":"US",
    "sg:address":"1275 Fall River Ave",
    "sg:city":"Seekonk",
    "sg:classifiers":[
        {
            "category":"Building & Trades",
            "subcategory":"Plumbing",
            "type":"Services"
        }
    ],
    "sg:phone":"+1 508 336 3502",
    "sg:postcode":"02771",
    "sg:province":"MA",
    "sg:tags":[
        "conditioning",
        "air",
        "system",
        "contractor"
    ],
    "wof:name":"Acu Temp Hvac",
    "wof:placetype":"venue"
},
  "geometry": {"coordinates":[-71.323024,41.791174],"type":"Point"}
}