{
  "type": "Feature",
  "properties": {
    "iso:country":"US",
    "sg:address":"482 Boston Rd",
    "sg:city":"Billerica",
    "sg:classifiers":[
        {
            "category":"Banks & Credit Unions",
            "subcategory":"Bank",
            "type":"Services"
        }
    ],
    "sg:phone":"+1 978 667 4107",
    "sg:postcode":"01821",
    "sg:province":"MA",
    "sg:website":"www.nbtc.com",
    "wof:name":"Northern Bank & Trust Company",
    "wof:placetype":"venue"
},
  "geometry": {"coordinates":[-71.264503,42.5532],"type":"Point"}
}