{
  "type": "Feature",
  "properties": {
    "addr:full": "482 Boston Rd Billerica MA 01821",
    "addr:housenumber": "482",
    "addr:postcode": "01821",
    "addr:street": "Boston Rd",
    "iso:country": "US",
    "sg:address": "482 Boston Rd",
    "sg:city": "Billerica",
    "sg:classifiers": [
      {
        "category": "Banks \u0026 Credit Unions",
        "subcategory": "Bank",
        "type": "Services"
      }
    ],
    "sg:phone": "+1 978 667 4107",
    "sg:postcode": "01821",
    "sg:province": "MA",
    "sg:website": "www.nbtc.com",
    "wof:name": "Northern Bank \u0026 Trust Company",
    "wof:placetype": "venue"
  },
  "geometry": {"coordinates":[-71.264503,42.5532],"type":"Point"}
}
