{
  "type": "Feature",
  "properties": {
    "addr:full": "22 Mohawk Rd Marblehead MA 01945",
    "addr:housenumber": "22",
    "addr:postcode": "01945",
    "addr:street": "Mohawk Rd",
    "iso:country": "US",
    "sg:address": "22 Mohawk Rd",
    "sg:city": "Marblehead",
    "sg:classifiers": [
      {
        "category": "Wholesale",
        "subcategory": "Medical Equipment \u0026 Supplies",
        "type": "Manufacturing \u0026 Wholesale Goods"
      }
    ],
    "sg:phone": "+1 781 631 8629",
    "sg:postcode": "01945",
    "sg:province": "MA",
    "sg:tags": [
      "physician",
      "surgeon"
    ],
    "wof:name": "Stephen Nikonchuk",
    "wof:placetype": "venue"
  },
  "geometry": {"coordinates":[-70.868399,42.497486],"type":"Point"}
}
