{
  "type": "Feature",
  "properties": {
    "addr:full":"34 Arbor St Wenham MA 01984",
    "addr:housenumber":"34",
    "addr:postcode":"01984",
    "addr:street":"Arbor St",
    "iso:country":"US",
    "sg:address":"34 Arbor St",
    "sg:city":"Wenham",
    "sg:classifiers":[
        {
            "category":"Autos & Motor Vehicles",
            "subcategory":"Automobile Sales",
            "type":"Retail Goods"
        }
    ],
    "sg:phone":"+1 978 468 2757",
    "sg:postcode":"01984",
    "sg:province":"MA",
    "sg:tags":[
        "car",
        "dealer"
    ],
    "wof:name":"Freeman's Garage",
    "wof:placetype":"venue"
},
  "geometry": {"coordinates":[-70.887066,42.608683],"type":"Point"}
}