{
  "type": "Feature",
  "properties": {
    "addr:full":"300 US Hwy 44 Raynham MA 02767",
    "addr:housenumber":"300",
    "addr:postcode":"02767",
    "addr:street":"Us Hwy 44",
    "iso:country":"US",
    "sg:address":"300 US Hwy 44",
    "sg:city":"Raynham",
    "sg:classifiers":[
        {
            "category":"Shopping",
            "subcategory":"Crafts & Fabrics",
            "type":"Retail Goods"
        }
    ],
    "sg:phone":"+1 508 823 8110",
    "sg:postcode":"02767",
    "sg:province":"MA",
    "sg:tags":[
        "shop"
    ],
    "sg:website":"www.joann.com",
    "wof:name":"Jo-Ann Fabrics & Crafts",
    "wof:placetype":"venue"
},
  "geometry": {"coordinates":[-71.052547,41.905885],"type":"Point"}
}