{
  "type": "Feature",
  "properties": {
    "addr:full":"172 Cambridge Cir Longmeadow MA 01106",
    "addr:housenumber":"172",
    "addr:postcode":"01106",
    "addr:street":"Cambridge Cir",
    "iso:country":"US",
    "sg:address":"172 Cambridge Cir",
    "sg:city":"Longmeadow",
    "sg:classifiers":[
        {
            "category":"Professional",
            "subcategory":"Lawyer & Legal Services",
            "type":"Services"
        }
    ],
    "sg:phone":"+1   ",
    "sg:postcode":"01106",
    "sg:province":"MA",
    "wof:name":"Steven D Ostrowsky Atty",
    "wof:placetype":"venue"
},
  "geometry": {"coordinates":[-72.54892599999999,42.042762],"type":"Point"}
}