{
  "type": "Feature",
  "properties": {
    "iso:country":"US",
    "sg:address":"91 Fox Hill Rd",
    "sg:city":"Nahant",
    "sg:classifiers":[
        {
            "category":"Building & Trades",
            "subcategory":"Pest Control",
            "type":"Services"
        }
    ],
    "sg:phone":"+1 781 233 4644",
    "sg:postcode":"01908",
    "sg:province":"MA",
    "sg:tags":[
        "mothproofing"
    ],
    "wof:name":"B & B Pest Control Company",
    "wof:placetype":"venue"
},
  "geometry": {"coordinates":[-70.93347799999999,42.426298],"type":"Point"}
}