{
  "type": "Feature",
  "properties": {
    "addr:full": "91 Fox Hill Rd Nahant MA 01908",
    "addr:housenumber": "91",
    "addr:postcode": "01908",
    "addr:street": "Fox Hill Rd",
    "iso:country": "US",
    "sg:address": "91 Fox Hill Rd",
    "sg:city": "Nahant",
    "sg:classifiers": [
      {
        "category": "Building \u0026 Trades",
        "subcategory": "Pest Control",
        "type": "Services"
      }
    ],
    "sg:phone": "+1 781 233 4644",
    "sg:postcode": "01908",
    "sg:province": "MA",
    "sg:tags": [
      "mothproofing"
    ],
    "wof:name": "B \u0026 B Pest Control Company",
    "wof:placetype": "venue"
  },
  "geometry": {"coordinates":[-70.933478,42.426298],"type":"Point"}
}
