{
  "type": "Feature",
  "properties": {
    "iso:country":"US",
    "sg:address":"568 Bumps River Rd",
    "sg:city":"Osterville",
    "sg:classifiers":[
        {
            "category":"Banks & Credit Unions",
            "subcategory":"Financial Services",
            "type":"Services"
        }
    ],
    "sg:phone":"+1   ",
    "sg:postcode":"02655",
    "sg:province":"MA",
    "sg:tags":[
        "management",
        "open",
        "investment"
    ],
    "wof:name":"Nexum Corp",
    "wof:placetype":"venue"
},
  "geometry": {"coordinates":[-70.373063,41.643583],"type":"Point"}
}