{
  "type": "Feature",
  "properties": {
    "addr:full":"7 Bulfinch Place Boston MA 02114",
    "addr:housenumber":"7",
    "addr:postcode":"02114",
    "addr:street":"Bulfinch Place",
    "iso:country":"US",
    "sg:address":"7 Bulfinch Place",
    "sg:city":"Boston",
    "sg:classifiers":[
        {
            "category":"Communications",
            "subcategory":"Television Station",
            "type":"Services"
        }
    ],
    "sg:phone":"+1 617 725 0777",
    "sg:postcode":"02114",
    "sg:province":"MA",
    "wof:name":"Channel 7",
    "wof:placetype":"venue"
},
  "geometry": {"coordinates":[-71.061189,42.361306],"type":"Point"}
}