{
  "type": "Feature",
  "properties": {
    "iso:country":"US",
    "sg:address":"127 Mount Auburn St",
    "sg:city":"Cambridge",
    "sg:classifiers":[
        {
            "category":"Health Services",
            "subcategory":"Clinic",
            "type":"Services"
        }
    ],
    "sg:phone":"+1 617 354 6770",
    "sg:postcode":"02138",
    "sg:province":"MA",
    "sg:tags":[
        "counseling",
        "mental"
    ],
    "wof:name":"Vervaet Gay R Socl Workr",
    "wof:placetype":"venue"
},
  "geometry": {"coordinates":[-71.12339799999999,42.373501],"type":"Point"}
}