{
  "type": "Feature",
  "properties": {
    "iso:country":"US",
    "sg:address":"102 Ford Rd",
    "sg:city":"Sudbury",
    "sg:classifiers":[
        {
            "category":"Utilities",
            "subcategory":"Telephone",
            "type":"Services"
        }
    ],
    "sg:phone":"+1   ",
    "sg:postcode":"01776",
    "sg:province":"MA",
    "sg:tags":[
        "communications",
        "broker"
    ],
    "wof:name":"Access International",
    "wof:placetype":"venue"
},
  "geometry": {"coordinates":[-71.434776,42.417389],"type":"Point"}
}