{
  "type": "Feature",
  "properties": {
    "addr:full": "102 Ford Rd Sudbury MA 01776",
    "addr:housenumber": "102",
    "addr:postcode": "01776",
    "addr:street": "Ford Rd",
    "iso:country": "US",
    "sg:address": "102 Ford Rd",
    "sg:city": "Sudbury",
    "sg:classifiers": [
      {
        "category": "Utilities",
        "subcategory": "Telephone",
        "type": "Services"
      }
    ],
    "sg:phone": "+1   ",
    "sg:postcode": "01776",
    "sg:province": "MA",
    "sg:tags": [
      "communications",
      "broker"
    ],
    "wof:name": "Access International",
    "wof:placetype": "venue"
  },
  "geometry": {"coordinates":[-71.434776,42.417389],"type":"Point"}
}
