{
  "type": "Feature",
  "properties": {
    "addr:full":"15 Centre St Quincy MA 02169",
    "addr:housenumber":"15",
    "addr:postcode":"02169",
    "addr:street":"Centre St",
    "iso:country":"US",
    "sg:address":"15 Centre St",
    "sg:city":"Quincy",
    "sg:classifiers":[
        {
            "category":"Mining & Drilling",
            "type":"Manufacturing & Wholesale Goods"
        }
    ],
    "sg:phone":"+1 617 773 3025",
    "sg:postcode":"02169",
    "sg:province":"MA",
    "sg:tags":[
        "oil",
        "gas",
        "producer"
    ],
    "wof:name":"E & J Oil Co",
    "wof:placetype":"venue"
},
  "geometry": {"coordinates":[-71.02219599999999,42.242774],"type":"Point"}
}