{
  "type": "Feature",
  "properties": {
    "iso:country":"US",
    "sg:address":"65 Hopedale St",
    "sg:city":"Hopedale",
    "sg:classifiers":[
        {
            "category":"Organizations",
            "subcategory":"Religious Organization",
            "type":"Services"
        }
    ],
    "sg:phone":"+1 508 473 0745",
    "sg:postcode":"01747",
    "sg:province":"MA",
    "sg:tags":[
        "place",
        "worship",
        "church"
    ],
    "wof:name":"Hopedale Unitarian Parish",
    "wof:placetype":"venue"
},
  "geometry": {"coordinates":[-71.54014599999999,42.129506],"type":"Point"}
}