{
  "type": "Feature",
  "properties": {
    "addr:full": "65 Hopedale St Hopedale MA 01747",
    "addr:housenumber": "65",
    "addr:postcode": "01747",
    "addr:street": "Hopedale St",
    "iso:country": "US",
    "ovtr:label": "Hopedale Unitarian Parish, 65 Hopedale St Hopedale MA US",
    "ovtr:similarity": 3.712207078933716,
    "sg:address": "65 Hopedale St",
    "sg:city": "Hopedale",
    "sg:classifiers": [
      {
        "category": "Organizations",
        "subcategory": "Religious Organization",
        "type": "Services"
      }
    ],
    "sg:phone": "+1 508 473 0745",
    "sg:postcode": "01747",
    "sg:province": "MA",
    "sg:tags": [
      "place",
      "worship",
      "church"
    ],
    "wof:name": "Hopedale Unitarian Parish",
    "wof:placetype": "venue"
  },
  "geometry": {"coordinates":[-71.540146,42.129506],"type":"Point"}
}
