{
  "type": "Feature",
  "properties": {
    "addr:full":"28 Mugford St Marblehead MA 01945",
    "addr:housenumber":"28",
    "addr:postcode":"01945",
    "addr:street":"Mugford St",
    "iso:country":"US",
    "sg:address":"28 Mugford St",
    "sg:city":"Marblehead",
    "sg:classifiers":[
        {
            "category":"Organizations",
            "subcategory":"Community Association",
            "type":"Services"
        }
    ],
    "sg:phone":"+1 781 631 8987",
    "sg:postcode":"01945",
    "sg:province":"MA",
    "sg:tags":[
        "club"
    ],
    "wof:name":"Me & Thee Coffee House",
    "wof:placetype":"venue"
},
  "geometry": {"coordinates":[-70.85111499999999,42.505907],"type":"Point"}
}