{
  "type": "Feature",
  "properties": {
    "addr:full": "249 North St Danvers MA 01923",
    "addr:housenumber": "249",
    "addr:postcode": "01923",
    "addr:street": "North St",
    "iso:country": "US",
    "sg:address": "249 North St",
    "sg:city": "Danvers",
    "sg:classifiers": [
      {
        "category": "Freight",
        "type": "Transportation"
      }
    ],
    "sg:phone": "+1 978 539 3333",
    "sg:postcode": "01923",
    "sg:province": "MA",
    "sg:tags": [
      "mover"
    ],
    "wof:name": "Allied Van Lines",
    "wof:placetype": "venue"
  },
  "geometry": {"coordinates":[-70.962941,42.60046],"type":"Point"}
}
