{
  "type": "Feature",
  "properties": {
    "iso:country":"US",
    "sg:address":"101 Mystic Ave",
    "sg:city":"Medford",
    "sg:classifiers":[
        {
            "category":"Wholesale",
            "subcategory":"Jewelry",
            "type":"Manufacturing & Wholesale Goods"
        },
        {
            "category":"Shopping",
            "subcategory":"Jewelry",
            "type":"Retail Goods"
        },
        {
            "category":"Manufacturing",
            "subcategory":"Jewelry",
            "type":"Manufacturing & Wholesale Goods"
        }
    ],
    "sg:phone":"+1 781 393 8665",
    "sg:postcode":"02155",
    "sg:province":"MA",
    "sg:tags":[
        "supply",
        "jeweler",
        "finding",
        "jewelers'",
        "supplies-wholesale",
        "manufacturer"
    ],
    "sg:website":"www.nationaljewelerssupplies.com",
    "wof:name":"National Jewelers Supplies",
    "wof:placetype":"venue"
},
  "geometry": {"coordinates":[-71.106661,42.411106],"type":"Point"}
}