{
  "type": "Feature",
  "properties": {
    "iso:country":"US",
    "sg:address":"158 Meadowview Dr",
    "sg:city":"Pittsfield",
    "sg:classifiers":[
        {
            "category":"Arts & Performance",
            "subcategory":"Theater",
            "type":"Entertainment"
        }
    ],
    "sg:phone":"+1 413 499 6327",
    "sg:postcode":"01201",
    "sg:province":"MA",
    "sg:tags":[
        "live",
        "music"
    ],
    "wof:name":"Sound Trax",
    "wof:placetype":"venue"
},
  "geometry": {"coordinates":[-73.20039199999999,42.473767],"type":"Point"}
}