{
  "type": "Feature",
  "properties": {
    "addr:full": "158 Meadowview Dr Pittsfield MA 01201",
    "addr:housenumber": "158",
    "addr:postcode": "01201",
    "addr:street": "Meadowview Dr",
    "iso:country": "US",
    "sg:address": "158 Meadowview Dr",
    "sg:city": "Pittsfield",
    "sg:classifiers": [
      {
        "category": "Arts \u0026 Performance",
        "subcategory": "Theater",
        "type": "Entertainment"
      }
    ],
    "sg:phone": "+1 413 499 6327",
    "sg:postcode": "01201",
    "sg:province": "MA",
    "sg:tags": [
      "live",
      "music"
    ],
    "wof:name": "Sound Trax",
    "wof:placetype": "venue"
  },
  "geometry": {"coordinates":[-73.200392,42.473767],"type":"Point"}
}
