{
  "type": "Feature",
  "properties": {
    "addr:full": "25 Fair Oaks St Cambridge MA 02140",
    "addr:housenumber": "25",
    "addr:postcode": "02140",
    "addr:street": "Fair Oaks St",
    "iso:country": "US",
    "sg:address": "25 Fair Oaks St",
    "sg:city": "Cambridge",
    "sg:classifiers": [
      {
        "category": "Building \u0026 Trades",
        "subcategory": "Plumbing",
        "type": "Services"
      }
    ],
    "sg:phone": "+1 617 876 6020",
    "sg:postcode": "02140",
    "sg:province": "MA",
    "sg:tags": [
      "gas",
      "burner"
    ],
    "wof:name": "Combustion Service Co",
    "wof:placetype": "venue"
  },
  "geometry": {"coordinates":[-71.130131,42.398365],"type":"Point"}
}
