{
  "type": "Feature",
  "properties": {
    "iso:country":"US",
    "sg:address":"1342 Belmont St",
    "sg:city":"Brockton",
    "sg:classifiers":[
        {
            "category":"Health Services",
            "subcategory":"Health Practitioner",
            "type":"Services"
        }
    ],
    "sg:phone":"+1 508 427 6911",
    "sg:postcode":"02301",
    "sg:province":"MA",
    "sg:tags":[
        "psychologist"
    ],
    "wof:name":"Behavioral Medicine Assocs",
    "wof:placetype":"venue"
},
  "geometry": {"coordinates":[-71.068831,42.057978],"type":"Point"}
}