{
  "type": "Feature",
  "properties": {
    "iso:country":"US",
    "sg:address":"1200 Converse St",
    "sg:city":"Longmeadow",
    "sg:classifiers":[
        {
            "category":"Social Services",
            "type":"Services"
        }
    ],
    "sg:phone":"+1 413 565 5121",
    "sg:postcode":"01106",
    "sg:province":"MA",
    "sg:tags":[
        "counseling"
    ],
    "wof:name":"Beacon Counseling Svc",
    "wof:placetype":"venue"
},
  "geometry": {"coordinates":[-72.539351,42.059718],"type":"Point"}
}