{
  "type": "Feature",
  "properties": {
    "addr:full":"326 Watertown St Newton MA 02458",
    "addr:housenumber":"326",
    "addr:postcode":"02458",
    "addr:street":"Watertown St",
    "iso:country":"US",
    "sg:address":"326 Watertown St",
    "sg:city":"Newton",
    "sg:classifiers":[
        {
            "category":"Government",
            "subcategory":"Post Office",
            "type":"Public Place"
        }
    ],
    "sg:phone":"+1 617 244 1073",
    "sg:postcode":"02458",
    "sg:province":"MA",
    "wof:name":"US Post Office",
    "wof:placetype":"venue"
},
  "geometry": {"coordinates":[-71.19972300000001,42.360887],"type":"Point"}
}