{
  "type": "Feature",
  "properties": {
    "iso:country":"US",
    "sg:address":"40 Hooker Ave",
    "sg:city":"Somerville",
    "sg:classifiers":[
        {
            "category":"Professional",
            "subcategory":"Art Services",
            "type":"Services"
        }
    ],
    "sg:phone":"+1 203 247 1145",
    "sg:postcode":"02144",
    "sg:province":"MA",
    "sg:tags":[
        "photographer"
    ],
    "sg:website":"kristenschueler.com/",
    "wof:name":"Kristen Schueler Photography",
    "wof:placetype":"venue"
},
  "geometry": {"coordinates":[-71.131709,42.402367],"type":"Point"}
}