{
  "type": "Feature",
  "properties": {
    "addr:full": "33 Prospect St Baldwinville MA 01436",
    "addr:housenumber": "33",
    "addr:postcode": "01436",
    "addr:street": "Prospect St",
    "iso:country": "US",
    "sg:address": "33 Prospect St",
    "sg:city": "Baldwinville",
    "sg:classifiers": [
      {
        "category": "Building \u0026 Trades",
        "subcategory": "Construction",
        "type": "Services"
      }
    ],
    "sg:phone": "+1 508 294 3648",
    "sg:postcode": "01436",
    "sg:province": "MA",
    "sg:tags": [
      "repairing",
      "remodeling",
      "contractor"
    ],
    "wof:name": "JPR Remodeling",
    "wof:placetype": "venue"
  },
  "geometry": {"coordinates":[-72.081048,42.604809],"type":"Point"}
}
