{
  "type": "Feature",
  "properties": {
    "iso:country":"US",
    "sg:address":"33 Prospect St",
    "sg:city":"Baldwinville",
    "sg:classifiers":[
        {
            "category":"Building & Trades",
            "subcategory":"Construction",
            "type":"Services"
        }
    ],
    "sg:phone":"+1 508 294 3648",
    "sg:postcode":"01436",
    "sg:province":"MA",
    "sg:tags":[
        "repairing",
        "remodeling",
        "contractor"
    ],
    "wof:name":"JPR Remodeling",
    "wof:placetype":"venue"
},
  "geometry": {"coordinates":[-72.081048,42.604809],"type":"Point"}
}