{
  "type": "Feature",
  "properties": {
    "addr:full":"97 Chestnut St Pepperell MA 01463",
    "addr:housenumber":"97",
    "addr:postcode":"01463",
    "addr:street":"Chestnut St",
    "iso:country":"US",
    "sg:address":"97 Chestnut St",
    "sg:city":"Pepperell",
    "sg:classifiers":[
        {
            "category":"Building & Trades",
            "subcategory":"Plumbing",
            "type":"Services"
        }
    ],
    "sg:phone":"+1 978 433 6859",
    "sg:postcode":"01463",
    "sg:province":"MA",
    "sg:tags":[
        "plumbing",
        "contractor"
    ],
    "wof:name":"Eugene B Douglas Plumbing",
    "wof:placetype":"venue"
},
  "geometry": {"coordinates":[-71.641633,42.682512],"type":"Point"}
}