{
  "type": "Feature",
  "properties": {
    "addr:full": "831 Main St Waltham MA 02451",
    "addr:housenumber": "831",
    "addr:postcode": "02451",
    "addr:street": "Main St",
    "iso:country": "US",
    "sg:address": "831 Main St",
    "sg:city": "Waltham",
    "sg:classifiers": [
      {
        "category": "Shopping",
        "subcategory": "Discount \u0026 Variety Stores",
        "type": "Retail Goods"
      }
    ],
    "sg:phone": "+1 781 647 7529",
    "sg:postcode": "02451",
    "sg:province": "MA",
    "wof:name": "Tony D's",
    "wof:placetype": "venue"
  },
  "geometry": {"coordinates":[-71.244764,42.376326],"type":"Point"}
}
