{
  "type": "Feature",
  "properties": {
    "iso:country":"US",
    "sg:address":"109 Edge Hill Rd",
    "sg:city":"Braintree",
    "sg:classifiers":[
        {
            "category":"Wholesale",
            "subcategory":"Construction Materials",
            "type":"Manufacturing & Wholesale Goods"
        }
    ],
    "sg:phone":"+1 781 843 5061",
    "sg:postcode":"02184",
    "sg:province":"MA",
    "sg:tags":[
        "fence"
    ],
    "wof:name":"Massachusetts Fence Co",
    "wof:placetype":"venue"
},
  "geometry": {"coordinates":[-70.96262,42.228802],"type":"Point"}
}