{
  "type": "Feature",
  "properties": {
    "addr:full":"749 S Washington St North Attleboro MA 02760",
    "addr:housenumber":"749",
    "addr:postcode":"02760",
    "addr:street":"S Washington St",
    "iso:country":"US",
    "sg:address":"749 S Washington St",
    "sg:city":"North Attleboro",
    "sg:classifiers":[
        {
            "category":"Sports & Exercise",
            "subcategory":"Gym",
            "type":"Entertainment"
        }
    ],
    "sg:phone":"+1 508 695 9924",
    "sg:postcode":"02760",
    "sg:province":"MA",
    "sg:website":"www.fitnessplus1.com",
    "wof:name":"Fitness Plus",
    "wof:placetype":"venue"
},
  "geometry": {"coordinates":[-71.342697,41.956699],"type":"Point"}
}