{
  "type": "Feature",
  "properties": {
    "addr:full":"70 Brimmer St Boston MA 02108",
    "addr:housenumber":"70",
    "addr:postcode":"02108",
    "addr:street":"Brimmer St",
    "iso:country":"US",
    "sg:address":"70 Brimmer St",
    "sg:city":"Boston",
    "sg:classifiers":[
        {
            "category":"Utilities",
            "subcategory":"Mobile Phone",
            "type":"Services"
        }
    ],
    "sg:phone":"+1 617 722 9279",
    "sg:postcode":"02108",
    "sg:province":"MA",
    "sg:tags":[
        "telephone",
        "cellular"
    ],
    "wof:name":"Cellular One",
    "wof:placetype":"venue"
},
  "geometry": {"coordinates":[-71.071455,42.356117],"type":"Point"}
}