{
  "type": "Feature",
  "properties": {
    "addr:full":"41 Walnut Plain Rd Rochester MA 02770",
    "addr:housenumber":"41",
    "addr:postcode":"02770",
    "addr:street":"Walnut Plain Rd",
    "iso:country":"US",
    "sg:address":"41 Walnut Plain Rd",
    "sg:city":"Rochester",
    "sg:classifiers":[
        {
            "category":"Building & Trades",
            "subcategory":"Plumbing",
            "type":"Services"
        }
    ],
    "sg:phone":"+1   ",
    "sg:postcode":"02770",
    "sg:province":"MA",
    "sg:tags":[
        "contractor"
    ],
    "wof:name":"Bolduc Roger N Plbg Htg Remod",
    "wof:placetype":"venue"
},
  "geometry": {"coordinates":[-70.810956,41.738455],"type":"Point"}
}