{
  "type": "Feature",
  "properties": {
    "iso:country":"US",
    "sg:address":"2840 Acushnet Ave",
    "sg:city":"New Bedford",
    "sg:classifiers":[
        {
            "category":"Restaurant",
            "type":"Food & Drink"
        }
    ],
    "sg:phone":"+1 508 998 9994",
    "sg:postcode":"02745",
    "sg:province":"MA",
    "wof:name":"Latin Grill",
    "wof:placetype":"venue"
},
  "geometry": {"coordinates":[-70.934453,41.697228],"type":"Point"}
}