{
  "type": "Feature",
  "properties": {
    "iso:country":"US",
    "sg:address":"2 Park Row",
    "sg:city":"Mansfield",
    "sg:classifiers":[
        {
            "category":"Education",
            "subcategory":"School",
            "type":"Public Place"
        }
    ],
    "sg:phone":"+1 508 261 7505",
    "sg:postcode":"02048",
    "sg:province":"MA",
    "sg:website":"www.mansfieldschools.com",
    "wof:name":"Mansfield School Supt Office",
    "wof:placetype":"venue"
},
  "geometry": {"coordinates":[-71.21589299999999,42.023734],"type":"Point"}
}