{
  "type": "Feature",
  "properties": {
    "addr:full":"535 Worcester Rd Framingham MA 01701",
    "addr:housenumber":"535",
    "addr:postcode":"01701",
    "addr:street":"Worcester Rd",
    "iso:country":"US",
    "sg:address":"535 Worcester Rd",
    "sg:city":"Framingham",
    "sg:classifiers":[
        {
            "category":"Health Services",
            "subcategory":"Chiropractor",
            "type":"Services"
        }
    ],
    "sg:phone":"+1 508 872 2555",
    "sg:postcode":"01701",
    "sg:province":"MA",
    "sg:tags":[
        "chiropractic"
    ],
    "wof:name":"Slone Bonnie",
    "wof:placetype":"venue"
},
  "geometry": {"coordinates":[-71.417862,42.297829],"type":"Point"}
}