{
  "type": "Feature",
  "properties": {
    "iso:country":"US",
    "sg:address":"2 Prospect Hill Rd",
    "sg:city":"Stockbridge",
    "sg:classifiers":[
        {
            "category":"Shopping",
            "subcategory":"Gifts & Souvenirs",
            "type":"Retail Goods"
        }
    ],
    "sg:phone":"+1 413 298 1112",
    "sg:postcode":"01262",
    "sg:province":"MA",
    "sg:tags":[
        "shop"
    ],
    "wof:name":"National Shrine/Devine Mercy",
    "wof:placetype":"venue"
},
  "geometry": {"coordinates":[-73.316468,42.30086],"type":"Point"}
}