{
  "type": "Feature",
  "properties": {
    "addr:full": "2 Prospect Hill Rd Stockbridge MA 01262",
    "addr:housenumber": "2",
    "addr:postcode": "01262",
    "addr:street": "Prospect Hill Rd",
    "iso:country": "US",
    "sg:address": "2 Prospect Hill Rd",
    "sg:city": "Stockbridge",
    "sg:classifiers": [
      {
        "category": "Shopping",
        "subcategory": "Gifts \u0026 Souvenirs",
        "type": "Retail Goods"
      }
    ],
    "sg:phone": "+1 413 298 1112",
    "sg:postcode": "01262",
    "sg:province": "MA",
    "sg:tags": [
      "shop"
    ],
    "wof:name": "National Shrine/Devine Mercy",
    "wof:placetype": "venue"
  },
  "geometry": {"coordinates":[-73.316468,42.30086],"type":"Point"}
}
