{
  "type": "Feature",
  "properties": {
    "addr:full":"12 Lake St Chatham MA 02633",
    "addr:housenumber":"12",
    "addr:postcode":"02633",
    "addr:street":"Lake St",
    "iso:country":"US",
    "sg:address":"12 Lake St",
    "sg:city":"Chatham",
    "sg:classifiers":[
        {
            "category":"Building & Trades",
            "subcategory":"Construction",
            "type":"Services"
        }
    ],
    "sg:phone":"+1 508 945 0701",
    "sg:postcode":"02633",
    "sg:province":"MA",
    "sg:tags":[
        "contractor"
    ],
    "wof:name":"Community Builders",
    "wof:placetype":"venue"
},
  "geometry": {"coordinates":[-69.965891,41.69228],"type":"Point"}
}