{
  "type": "Feature",
  "properties": {
    "addr:full": "259 North St Hingham MA 02043",
    "addr:housenumber": "259",
    "addr:postcode": "02043",
    "addr:street": "North St",
    "iso:country": "US",
    "sg:address": "259 North St",
    "sg:city": "Hingham",
    "sg:classifiers": [
      {
        "category": "Education",
        "subcategory": "Vocational School",
        "type": "Public Place"
      }
    ],
    "sg:phone": "+1   ",
    "sg:postcode": "02043",
    "sg:province": "MA",
    "sg:tags": [
      "computer"
    ],
    "wof:name": "Macintosh Solutions",
    "wof:placetype": "venue"
  },
  "geometry": {"coordinates":[-70.897671,42.241283],"type":"Point"}
}
