{
  "type": "Feature",
  "properties": {
    "addr:full": "168 South St Jamaica Plain MA 02130",
    "addr:housenumber": "168",
    "addr:postcode": "02130",
    "addr:street": "South St",
    "iso:country": "US",
    "sg:address": "168 South St",
    "sg:city": "Jamaica Plain",
    "sg:classifiers": [
      {
        "category": "Building \u0026 Trades",
        "subcategory": "Locksmith",
        "type": "Services"
      }
    ],
    "sg:phone": "+1 617 942 4024",
    "sg:postcode": "02130",
    "sg:province": "MA",
    "sg:tags": [
      "key"
    ],
    "wof:name": "Available Locksmith 24 7",
    "wof:placetype": "venue"
  },
  "geometry": {"coordinates":[-71.114501,42.304111],"type":"Point"}
}
