{
  "type": "Feature",
  "properties": {
    "addr:full": "128 York Ave Randolph MA 02368",
    "addr:housenumber": "128",
    "addr:postcode": "02368",
    "addr:street": "York Ave",
    "iso:country": "US",
    "sg:address": "128 York Ave",
    "sg:city": "Randolph",
    "sg:classifiers": [
      {
        "category": "Personal",
        "type": "Services"
      }
    ],
    "sg:phone": "+1 781 986 7676",
    "sg:postcode": "02368",
    "sg:province": "MA",
    "sg:tags": [
      "mover"
    ],
    "wof:name": "Burgess Transportation Services Inc",
    "wof:placetype": "venue"
  },
  "geometry": {"coordinates":[-71.071999,42.181499],"type":"Point"}
}
