{
  "type": "Feature",
  "properties": {
    "iso:country":"US",
    "sg:address":"128 York Ave",
    "sg:city":"Randolph",
    "sg:classifiers":[
        {
            "category":"Personal",
            "type":"Services"
        }
    ],
    "sg:phone":"+1 781 986 7676",
    "sg:postcode":"02368",
    "sg:province":"MA",
    "sg:tags":[
        "mover"
    ],
    "wof:name":"Burgess Transportation Services Inc",
    "wof:placetype":"venue"
},
  "geometry": {"coordinates":[-71.07199900000001,42.181499],"type":"Point"}
}