{
  "type": "Feature",
  "properties": {
    "addr:full": "125 Pearl St Braintree MA 02184",
    "addr:housenumber": "125",
    "addr:postcode": "02184",
    "addr:street": "Pearl St",
    "iso:country": "US",
    "sg:address": "125 Pearl St",
    "sg:city": "Braintree",
    "sg:classifiers": [
      {
        "category": "Utilities",
        "subcategory": "Mobile Phone",
        "type": "Services"
      }
    ],
    "sg:phone": "+1 781 356 2103",
    "sg:postcode": "02184",
    "sg:province": "MA",
    "sg:tags": [
      "telephone",
      "cellular"
    ],
    "wof:name": "ATS Mobile",
    "wof:placetype": "venue"
  },
  "geometry": {"coordinates":[-71.001501,42.20249],"type":"Point"}
}
