{
  "type": "Feature",
  "properties": {
    "addr:full":"PO Box 556 Sturbridge MA 01566",
    "addr:housenumber":"po",
    "addr:postcode":"01566",
    "addr:street":"Box 556",
    "iso:country":"US",
    "sg:address":"PO Box 556",
    "sg:city":"Sturbridge",
    "sg:classifiers":[
        {
            "category":"Travel",
            "subcategory":"Hotels & Motels",
            "type":"Entertainment"
        }
    ],
    "sg:phone":"+1 508 347 7700",
    "sg:postcode":"01566",
    "sg:province":"MA",
    "wof:name":"Travel Nest - CLOSED",
    "wof:placetype":"venue"
},
  "geometry": {"coordinates":[-72.0802,42.110401],"type":"Point"}
}