{
  "type": "Feature",
  "properties": {
    "iso:country":"US",
    "sg:address":"160 Providence Hwy",
    "sg:city":"Norwood",
    "sg:classifiers":[
        {
            "category":"Retail",
            "subcategory":"Animal Services",
            "type":"Services"
        }
    ],
    "sg:phone":"+1   ",
    "sg:postcode":"02062",
    "sg:province":"MA",
    "sg:tags":[
        "dog",
        "officer"
    ],
    "wof:name":"Norwood Dog Officer",
    "wof:placetype":"venue"
},
  "geometry": {"coordinates":[-71.18529700000001,42.206922],"type":"Point"}
}