{
  "type": "Feature",
  "properties": {
    "addr:full":"148 Sidney Street Cambridge MA 02139",
    "addr:housenumber":"148",
    "addr:postcode":"02139",
    "addr:street":"Sidney Street",
    "iso:country":"US",
    "sg:address":"148 Sidney Street",
    "sg:city":"Cambridge",
    "sg:classifiers":[
        {
            "category":"Professional",
            "subcategory":"Research",
            "type":"Services"
        }
    ],
    "sg:phone":"+1 617 621 7700",
    "sg:postcode":"02139",
    "sg:province":"MA",
    "sg:website":"http://www.archemix.com",
    "wof:name":"Archemix",
    "wof:placetype":"venue"
},
  "geometry": {"coordinates":[-71.103949,42.359108],"type":"Point"}
}