{
  "type": "Feature",
  "properties": {
    "iso:country":"US",
    "sg:address":"3 Bow Street",
    "sg:city":"Cambridge",
    "sg:classifiers":[
        {
            "category":"Health Services",
            "subcategory":"Clinic",
            "type":"Services"
        }
    ],
    "sg:phone":"+1 617 547 2255",
    "sg:postcode":"02138",
    "sg:province":"MA",
    "sg:tags":[
        "counseling",
        "mental"
    ],
    "sg:website":"www.eatingdisordercenter.org/",
    "wof:name":"Cambridge Eating Disorder Center",
    "wof:placetype":"venue"
},
  "geometry": {"coordinates":[-71.115527,42.372115],"type":"Point"}
}