{
  "type": "Feature",
  "properties": {
    "addr:full":"10 Guild Rd Forestdale MA 02644",
    "addr:housenumber":"10",
    "addr:postcode":"02644",
    "addr:street":"Guild Rd",
    "iso:country":"US",
    "sg:address":"10 Guild Rd",
    "sg:city":"Forestdale",
    "sg:classifiers":[
        {
            "category":"Building & Trades",
            "subcategory":"Construction",
            "type":"Services"
        }
    ],
    "sg:phone":"+1 508 888 6781",
    "sg:postcode":"02644",
    "sg:province":"MA",
    "sg:tags":[
        "painter"
    ],
    "wof:name":"Barefoot Painint",
    "wof:placetype":"venue"
},
  "geometry": {"coordinates":[-70.50238299999999,41.674633],"type":"Point"}
}