{
  "type": "Feature",
  "properties": {
    "addr:full":"20 S Deerfield Byp South Deerfield MA 01373",
    "addr:housenumber":"20",
    "addr:postcode":"01373",
    "addr:street":"S Deerfield Byp",
    "iso:country":"US",
    "sg:address":"20 S Deerfield Byp",
    "sg:city":"South Deerfield",
    "sg:classifiers":[
        {
            "category":"Freight",
            "type":"Transportation"
        }
    ],
    "sg:phone":"+1 413 665 2136",
    "sg:postcode":"01373",
    "sg:province":"MA",
    "sg:tags":[
        "trucking"
    ],
    "sg:website":"www.nbexpress.com",
    "wof:name":"N & B Express Inc",
    "wof:placetype":"venue"
},
  "geometry": {"coordinates":[-72.614052,42.47462],"type":"Point"}
}