{
  "type": "Feature",
  "properties": {
    "iso:country":"US",
    "sg:address":"247 Chestnut Hill Ave",
    "sg:city":"Brighton",
    "sg:classifiers":[
        {
            "category":"Communications",
            "subcategory":"Film & Video Production",
            "type":"Services"
        }
    ],
    "sg:phone":"+1 617 782 0666",
    "sg:postcode":"02135",
    "sg:province":"MA",
    "sg:tags":[
        "taping"
    ],
    "wof:name":"Phoenix Productions",
    "wof:placetype":"venue"
},
  "geometry": {"coordinates":[-71.15361,42.338352],"type":"Point"}
}