{
  "type": "Feature",
  "properties": {
    "iso:country":"US",
    "sg:address":"204 Lafayette St",
    "sg:city":"Salem",
    "sg:classifiers":[
        {
            "category":"Professional",
            "subcategory":"Research",
            "type":"Services"
        }
    ],
    "sg:phone":"+1 978 745 6618",
    "sg:postcode":"01970",
    "sg:province":"MA",
    "sg:tags":[
        "environmental",
        "ecological"
    ],
    "wof:name":"Gulf Of Maine Research Ctr",
    "wof:placetype":"venue"
},
  "geometry": {"coordinates":[-70.892359,42.513423],"type":"Point"}
}