{
  "type": "Feature",
  "properties": {
    "iso:country":"US",
    "sg:address":"25 Chestnut St",
    "sg:city":"Marblehead",
    "sg:classifiers":[
        {
            "category":"Building & Trades",
            "subcategory":"Construction",
            "type":"Services"
        }
    ],
    "sg:phone":"+1 781 639 2640",
    "sg:postcode":"01945",
    "sg:province":"MA",
    "sg:tags":[
        "contractor"
    ],
    "wof:name":"Essex Building Co",
    "wof:placetype":"venue"
},
  "geometry": {"coordinates":[-70.85619699999999,42.496717],"type":"Point"}
}