{
  "type": "Feature",
  "properties": {
    "addr:full": "25 Chestnut St Marblehead MA 01945",
    "addr:housenumber": "25",
    "addr:postcode": "01945",
    "addr:street": "Chestnut St",
    "iso:country": "US",
    "sg:address": "25 Chestnut St",
    "sg:city": "Marblehead",
    "sg:classifiers": [
      {
        "category": "Building \u0026 Trades",
        "subcategory": "Construction",
        "type": "Services"
      }
    ],
    "sg:phone": "+1 781 639 2640",
    "sg:postcode": "01945",
    "sg:province": "MA",
    "sg:tags": [
      "contractor"
    ],
    "wof:name": "Essex Building Co",
    "wof:placetype": "venue"
  },
  "geometry": {"coordinates":[-70.856197,42.496717],"type":"Point"}
}
