{
  "type": "Feature",
  "properties": {
    "iso:country":"US",
    "sg:address":"115 Broad Street",
    "sg:city":"Boston",
    "sg:classifiers":[
        {
            "category":"Professional",
            "subcategory":"Lawyer & Legal Services",
            "type":"Services"
        }
    ],
    "sg:phone":"+1 617 535 3268",
    "sg:postcode":"02110",
    "sg:province":"MA",
    "wof:name":"Law Practice Consultants",
    "wof:placetype":"venue"
},
  "geometry": {"coordinates":[-71.052209,42.357285],"type":"Point"}
}