{
  "type": "Feature",
  "properties": {
    "iso:country":"US",
    "sg:address":"29 Upwey Rd",
    "sg:city":"Wellesley",
    "sg:classifiers":[
        {
            "category":"Professional",
            "subcategory":"Accounting & Tax Preparation",
            "type":"Services"
        }
    ],
    "sg:phone":"+1 781 237 2515",
    "sg:postcode":"02481",
    "sg:province":"MA",
    "sg:tags":[
        "consultant"
    ],
    "wof:name":"Stephen B Daunis Consultant",
    "wof:placetype":"venue"
},
  "geometry": {"coordinates":[-71.285156,42.307687],"type":"Point"}
}