{
  "type": "Feature",
  "properties": {
    "iso:country":"US",
    "sg:address":"115 Newbury St",
    "sg:city":"Boston",
    "sg:classifiers":[
        {
            "category":"Health Services",
            "subcategory":"Health Practitioner",
            "type":"Services"
        }
    ],
    "sg:phone":"+1 781 598 6751",
    "sg:postcode":"02116",
    "sg:province":"MA",
    "sg:tags":[
        "psychotherapist"
    ],
    "wof:name":"Life Counseling Assoc",
    "wof:placetype":"venue"
},
  "geometry": {"coordinates":[-71.077465,42.351076],"type":"Point"}
}