{
  "type": "Feature",
  "properties": {
    "addr:full": "543 State Hwy 6 Alt Dennis MA 02638",
    "addr:housenumber": "543",
    "addr:postcode": "02638",
    "addr:street": "State Hwy 6",
    "iso:country": "US",
    "sg:address": "543 State Hwy 6 Alt",
    "sg:city": "Dennis",
    "sg:classifiers": [
      {
        "category": "Professional",
        "subcategory": "Lawyer \u0026 Legal Services",
        "type": "Services"
      }
    ],
    "sg:phone": "+1 508 385 4844",
    "sg:postcode": "02638",
    "sg:province": "MA",
    "sg:tags": [
      "attorney"
    ],
    "wof:name": "Lumsden \u0026 Inge",
    "wof:placetype": "venue"
  },
  "geometry": {"coordinates":[-70.194583,41.733744],"type":"Point"}
}
