{
  "type": "Feature",
  "properties": {
    "addr:full": "374 Boston Post Rd Weston MA 02493",
    "addr:housenumber": "374",
    "addr:postcode": "02493",
    "addr:street": "Boston Post Rd",
    "iso:country": "US",
    "sg:address": "374 Boston Post Rd",
    "sg:city": "Weston",
    "sg:classifiers": [
      {
        "category": "Organizations",
        "subcategory": "Religious Organization",
        "type": "Services"
      }
    ],
    "sg:phone": "+1 781 899 2677",
    "sg:postcode": "02493",
    "sg:province": "MA",
    "sg:tags": [
      "church"
    ],
    "wof:name": "St Julia's Church \u0026 Rectory",
    "wof:placetype": "venue"
  },
  "geometry": {"coordinates":[-71.299836,42.367532],"type":"Point"}
}
