{
  "type": "Feature",
  "properties": {
    "iso:country":"US",
    "sg:address":"9 Warren St",
    "sg:city":"Randolph",
    "sg:classifiers":[
        {
            "category":"Shopping",
            "subcategory":"Optical Goods",
            "type":"Retail Goods"
        },
        {
            "category":"Health Services",
            "subcategory":"Optometrist",
            "type":"Services"
        },
        {
            "category":"Shopping",
            "subcategory":"Optician",
            "type":"Retail Goods"
        }
    ],
    "sg:phone":"+1 781 963 8448",
    "sg:postcode":"02368",
    "sg:province":"MA",
    "sg:tags":[
        "lens",
        "eyeglass",
        "contact",
        "eyewear"
    ],
    "wof:name":"Eyecare Etc",
    "wof:placetype":"venue"
},
  "geometry": {"coordinates":[-71.043739,42.165598],"type":"Point"}
}