{
  "type": "Feature",
  "properties": {
    "addr:full": "9 Warren St Randolph MA 02368",
    "addr:housenumber": "9",
    "addr:postcode": "02368",
    "addr:street": "Warren St",
    "iso:country": "US",
    "ovtr:label": "Eyecare Etc, 9 Warren St Randolph MA US",
    "ovtr:similarity": 2.2415239810943604,
    "sg:address": "9 Warren St",
    "sg:city": "Randolph",
    "sg:classifiers": [
      {
        "category": "Shopping",
        "subcategory": "Optical Goods",
        "type": "Retail Goods"
      },
      {
        "category": "Health Services",
        "subcategory": "Optometrist",
        "type": "Services"
      },
      {
        "category": "Shopping",
        "subcategory": "Optician",
        "type": "Retail Goods"
      }
    ],
    "sg:phone": "+1 781 963 8448",
    "sg:postcode": "02368",
    "sg:province": "MA",
    "sg:tags": [
      "lens",
      "eyeglass",
      "contact",
      "eyewear"
    ],
    "wof:name": "Eyecare Etc",
    "wof:placetype": "venue"
  },
  "geometry": {"coordinates":[-71.043739,42.165598],"type":"Point"}
}
