{
  "type": "Feature",
  "properties": {
    "addr:full":"56 Bridge St Chelmsford MA 01824",
    "addr:housenumber":"56",
    "addr:postcode":"01824",
    "addr:street":"Bridge St",
    "iso:country":"US",
    "sg:address":"56 Bridge St",
    "sg:city":"Chelmsford",
    "sg:classifiers":[
        {
            "category":"Professional",
            "subcategory":"Business Services",
            "type":"Services"
        }
    ],
    "sg:phone":"+1 978 256 3777",
    "sg:postcode":"01824",
    "sg:province":"MA",
    "sg:website":"www.eaglefiresafety.com",
    "wof:name":"Eagle Fire Safety",
    "wof:placetype":"venue"
},
  "geometry": {"coordinates":[-71.356222,42.597299],"type":"Point"}
}