{
  "type": "Feature",
  "properties": {
    "addr:full":"1 Bowdoin Sq Boston MA 02114",
    "addr:housenumber":"1",
    "addr:postcode":"02114",
    "addr:street":"Bowdoin Sq",
    "iso:country":"US",
    "sg:address":"1 Bowdoin Sq",
    "sg:city":"Boston",
    "sg:classifiers":[
        {
            "category":"Professional",
            "subcategory":"Lawyer & Legal Services",
            "type":"Services"
        }
    ],
    "sg:phone":"+1 617 720 2027",
    "sg:postcode":"02114",
    "sg:province":"MA",
    "wof:name":"Brooks Robert E Lwyr",
    "wof:placetype":"venue"
},
  "geometry": {"coordinates":[-71.06021800000001,42.362047],"type":"Point"}
}