{
  "type": "Feature",
  "properties": {
    "iso:country":"US",
    "sg:address":"197 Harvard St",
    "sg:city":"Brookline",
    "sg:classifiers":[
        {
            "category":"Personal",
            "subcategory":"Massage",
            "type":"Services"
        },
        {
            "category":"Personal",
            "subcategory":"Day Spa",
            "type":"Services"
        }
    ],
    "sg:phone":"+1 617 739 8989",
    "sg:postcode":"02446",
    "sg:province":"MA",
    "sg:website":"relaxatorchid.com",
    "wof:name":"Orchid Spa & Massage",
    "wof:placetype":"venue"
},
  "geometry": {"coordinates":[-71.12099600000001,42.339483],"type":"Point"}
}