{
  "type": "Feature",
  "properties": {
    "iso:country":"US",
    "sg:address":"71 Maple St",
    "sg:city":"Norwood",
    "sg:classifiers":[
        {
            "category":"Building & Trades",
            "subcategory":"Locksmith",
            "type":"Services"
        }
    ],
    "sg:phone":"+1 781 501 4468",
    "sg:postcode":"02062",
    "sg:province":"MA",
    "sg:tags":[
        "key"
    ],
    "wof:name":"Locksmith On Maple ABC 24 A Day Emergency",
    "wof:placetype":"venue"
},
  "geometry": {"coordinates":[-71.20426,42.194093],"type":"Point"}
}