{
  "type": "Feature",
  "properties": {
    "addr:full": "211 Vaughn Hill Rd Bolton MA 01740",
    "addr:housenumber": "211",
    "addr:postcode": "01740",
    "addr:street": "Vaughn Hill Rd",
    "iso:country": "US",
    "sg:address": "211 Vaughn Hill Rd",
    "sg:city": "Bolton",
    "sg:classifiers": [
      {
        "category": "Education",
        "subcategory": "Vocational School",
        "type": "Public Place"
      }
    ],
    "sg:phone": "+1 508 651 1400",
    "sg:postcode": "01740",
    "sg:province": "MA",
    "sg:tags": [
      "training",
      "computer"
    ],
    "sg:website": "www.esitechnology.com",
    "wof:name": "Esi Technology Corp",
    "wof:placetype": "venue"
  },
  "geometry": {"coordinates":[-71.625488,42.465797],"type":"Point"}
}
