{
  "type": "Feature",
  "properties": {
    "addr:full": "80 Washington St Ste E12 Norwell MA 02061",
    "addr:housenumber": "80",
    "addr:postcode": "02061",
    "addr:street": "Washington St Ste E12",
    "iso:country": "US",
    "sg:address": "80 Washington St Ste E12",
    "sg:city": "Norwell",
    "sg:classifiers": [
      {
        "category": "Professional",
        "subcategory": "Lawyer \u0026 Legal Services",
        "type": "Services"
      }
    ],
    "sg:phone": "+1 781 871 8855",
    "sg:postcode": "02061",
    "sg:province": "MA",
    "sg:tags": [
      "attorney",
      "practice"
    ],
    "sg:website": "http://www.glazierking.com",
    "wof:name": "Glazier \u0026 King",
    "wof:placetype": "venue"
  },
  "geometry": {"coordinates":[-70.879211,42.17234],"type":"Point"}
}
