{
  "type": "Feature",
  "properties": {
    "addr:full": "102 Conserve Ave Westport MA 02790",
    "addr:housenumber": "102",
    "addr:postcode": "02790",
    "addr:street": "Conserve Ave",
    "iso:country": "US",
    "sg:address": "102 Conserve Ave",
    "sg:city": "Westport",
    "sg:classifiers": [
      {
        "category": "Utilities",
        "subcategory": "Refuse",
        "type": "Services"
      }
    ],
    "sg:phone": "+1 508 672 2844",
    "sg:postcode": "02790",
    "sg:province": "MA",
    "sg:tags": [
      "collection",
      "garbage"
    ],
    "wof:name": "Gill \u0026 Cherryl Girard",
    "wof:placetype": "venue"
  },
  "geometry": {"coordinates":[-71.106,41.664929],"type":"Point"}
}
