{
  "type": "Feature",
  "properties": {
    "iso:country":"US",
    "sg:address":"102 Conserve Ave",
    "sg:city":"Westport",
    "sg:classifiers":[
        {
            "category":"Utilities",
            "subcategory":"Refuse",
            "type":"Services"
        }
    ],
    "sg:phone":"+1 508 672 2844",
    "sg:postcode":"02790",
    "sg:province":"MA",
    "sg:tags":[
        "collection",
        "garbage"
    ],
    "wof:name":"Gill & Cherryl Girard",
    "wof:placetype":"venue"
},
  "geometry": {"coordinates":[-71.10599999999999,41.664929],"type":"Point"}
}