{
  "type": "Feature",
  "properties": {
    "addr:full": "47 Gould St Stoneham MA 02180",
    "addr:housenumber": "47",
    "addr:postcode": "02180",
    "addr:street": "Gould St",
    "iso:country": "US",
    "sg:address": "47 Gould St",
    "sg:city": "Stoneham",
    "sg:classifiers": [
      {
        "category": "Manufacturing",
        "subcategory": "Petroleum Products",
        "type": "Manufacturing \u0026 Wholesale Goods"
      }
    ],
    "sg:phone": "+1 781 438 1146",
    "sg:postcode": "02180",
    "sg:province": "MA",
    "sg:tags": [
      "candles-wholesale",
      "manufacturer"
    ],
    "wof:name": "Kaylee's Candles And Event Planning",
    "wof:placetype": "venue"
  },
  "geometry": {"coordinates":[-71.091174,42.480223],"type":"Point"}
}
