{
  "type": "Feature",
  "properties": {
    "addr:full":"11 Enterprise Rd Hyannis MA 02601",
    "addr:housenumber":"11",
    "addr:postcode":"02601",
    "addr:street":"Enterprise Rd",
    "iso:country":"US",
    "sg:address":"11 Enterprise Rd",
    "sg:city":"Hyannis",
    "sg:classifiers":[
        {
            "category":"Recreation",
            "type":"Entertainment"
        }
    ],
    "sg:phone":"+1 508 771 0111",
    "sg:postcode":"02601",
    "sg:province":"MA",
    "sg:tags":[
        "martial art",
        "instruction"
    ],
    "sg:website":"www.shaolinamericankempo.com",
    "wof:name":"Self Defense Centers USA",
    "wof:placetype":"venue"
},
  "geometry": {"coordinates":[-70.302696,41.666801],"type":"Point"}
}