{
  "type": "Feature",
  "properties": {
    "iso:country":"US",
    "sg:address":"51 Quimby St",
    "sg:city":"Watertown",
    "sg:classifiers":[
        {
            "category":"Arts & Performance",
            "subcategory":"Theater",
            "type":"Entertainment"
        }
    ],
    "sg:phone":"+1   ",
    "sg:postcode":"02472",
    "sg:province":"MA",
    "sg:tags":[
        "group"
    ],
    "wof:name":"The Drive",
    "wof:placetype":"venue"
},
  "geometry": {"coordinates":[-71.160978,42.36751],"type":"Point"}
}