{
  "type": "Feature",
  "properties": {
    "addr:full": "51 Quimby St Watertown MA 02472",
    "addr:housenumber": "51",
    "addr:postcode": "02472",
    "addr:street": "Quimby St",
    "iso:country": "US",
    "sg:address": "51 Quimby St",
    "sg:city": "Watertown",
    "sg:classifiers": [
      {
        "category": "Arts \u0026 Performance",
        "subcategory": "Theater",
        "type": "Entertainment"
      }
    ],
    "sg:phone": "+1   ",
    "sg:postcode": "02472",
    "sg:province": "MA",
    "sg:tags": [
      "group"
    ],
    "wof:name": "The Drive",
    "wof:placetype": "venue"
  },
  "geometry": {"coordinates":[-71.160978,42.36751],"type":"Point"}
}
