{
  "type": "Feature",
  "properties": {
    "addr:full":"498 Main St Dalton MA 01226",
    "addr:housenumber":"498",
    "addr:postcode":"01226",
    "addr:street":"Main St",
    "iso:country":"US",
    "sg:address":"498 Main St",
    "sg:city":"Dalton",
    "sg:classifiers":[
        {
            "category":"Health Services",
            "subcategory":"Doctor",
            "type":"Services"
        }
    ],
    "sg:phone":"+1 413 684 0615",
    "sg:postcode":"01226",
    "sg:province":"MA",
    "sg:tags":[
        "dentist"
    ],
    "wof:name":"J Patrick Carsell DDS",
    "wof:placetype":"venue"
},
  "geometry": {"coordinates":[-73.169523,42.473237],"type":"Point"}
}