{
  "type": "Feature",
  "properties": {
    "addr:full": "5 Washington St Sherborn MA 01770",
    "addr:housenumber": "5",
    "addr:postcode": "01770",
    "addr:street": "Washington St",
    "iso:country": "US",
    "sg:address": "5 Washington St",
    "sg:city": "Sherborn",
    "sg:classifiers": [
      {
        "category": "Banks \u0026 Credit Unions",
        "subcategory": "Investment Brokerage",
        "type": "Services"
      }
    ],
    "sg:phone": "+1 508 647 0625",
    "sg:postcode": "01770",
    "sg:province": "MA",
    "sg:tags": [
      "advisory",
      "financial"
    ],
    "wof:name": "Atlantic Capital Management",
    "wof:placetype": "venue"
  },
  "geometry": {"coordinates":[-71.370321,42.242365],"type":"Point"}
}
