{
  "type": "Feature",
  "properties": {
    "addr:full": "174 Squire Rd Revere MA 02151",
    "addr:housenumber": "174",
    "addr:postcode": "02151",
    "addr:street": "Squire Rd",
    "iso:country": "US",
    "sg:address": "174 Squire Rd",
    "sg:city": "Revere",
    "sg:classifiers": [
      {
        "category": "Autos \u0026 Motor Vehicles",
        "subcategory": "Fuel \u0026 Gas Station",
        "type": "Retail Goods"
      }
    ],
    "sg:phone": "+1 781 289 6070",
    "sg:postcode": "02151",
    "sg:province": "MA",
    "wof:name": "Squire Road Service",
    "wof:placetype": "venue"
  },
  "geometry": {"coordinates":[-71.010383,42.423961],"type":"Point"}
}
