{
  "type": "Feature",
  "properties": {
    "iso:country":"US",
    "sg:address":"174 Squire Rd",
    "sg:city":"Revere",
    "sg:classifiers":[
        {
            "category":"Autos & Motor Vehicles",
            "subcategory":"Fuel & Gas Station",
            "type":"Retail Goods"
        }
    ],
    "sg:phone":"+1 781 289 6070",
    "sg:postcode":"02151",
    "sg:province":"MA",
    "wof:name":"Squire Road Service",
    "wof:placetype":"venue"
},
  "geometry": {"coordinates":[-71.010383,42.423961],"type":"Point"}
}