{
  "type": "Feature",
  "properties": {
    "iso:country":"US",
    "sg:address":"657 Middlesex St",
    "sg:city":"Lowell",
    "sg:classifiers":[
        {
            "category":"Government",
            "subcategory":"Police Station",
            "type":"Public Place"
        }
    ],
    "sg:phone":"+1   ",
    "sg:postcode":"01851",
    "sg:province":"MA",
    "sg:tags":[
        "protection"
    ],
    "wof:name":"Police Dept- West Sector",
    "wof:placetype":"venue"
},
  "geometry": {"coordinates":[-71.318865,42.638685],"type":"Point"}
}