{
  "type": "Feature",
  "properties": {
    "addr:full":"121 Marion Rd Wareham MA 02571",
    "addr:housenumber":"121",
    "addr:postcode":"02571",
    "addr:street":"Marion Rd",
    "iso:country":"US",
    "sg:address":"121 Marion Rd",
    "sg:city":"Wareham",
    "sg:classifiers":[
        {
            "category":"Food & Beverages",
            "subcategory":"Groceries & Convenience Stores",
            "type":"Retail Goods"
        }
    ],
    "sg:phone":"+1 508 295 4887",
    "sg:postcode":"02571",
    "sg:province":"MA",
    "sg:tags":[
        "grocer"
    ],
    "wof:name":"Iga Foodliner",
    "wof:placetype":"venue"
},
  "geometry": {"coordinates":[-70.727892,41.758705],"type":"Point"}
}