{
  "type": "Feature",
  "properties": {
    "iso:country":"US",
    "sg:address":"105 Saint Paul St",
    "sg:city":"Brookline",
    "sg:classifiers":[
        {
            "category":"Place Of Worship",
            "type":"Public Place"
        },
        {
            "category":"Organizations",
            "subcategory":"Religious Organization",
            "type":"Services"
        }
    ],
    "sg:phone":"+1 617 888 3202",
    "sg:postcode":"02446",
    "sg:province":"MA",
    "sg:tags":[
        "church"
    ],
    "wof:name":"Chabad Center Of Brookline",
    "wof:placetype":"venue"
},
  "geometry": {"coordinates":[-71.11760099999999,42.340448],"type":"Point"}
}