{
  "type": "Feature",
  "properties": {
    "iso:country":"US",
    "sg:address":"657 Cambridge St",
    "sg:city":"Cambridge",
    "sg:classifiers":[
        {
            "category":"Insurance",
            "subcategory":"Insurance Agent",
            "type":"Services"
        }
    ],
    "sg:phone":"+1 617 492 4150",
    "sg:postcode":"02141",
    "sg:province":"MA",
    "sg:website":"www.velmed.com",
    "wof:name":"Vellucci Insurance Inc",
    "wof:placetype":"venue"
},
  "geometry": {"coordinates":[-71.087175,42.372028],"type":"Point"}
}