{
  "type": "Feature",
  "properties": {
    "addr:full":"480 Washington St Ste 102 Brighton MA 02135",
    "addr:housenumber":"480",
    "addr:postcode":"02135",
    "addr:street":"Washington St Ste 102",
    "iso:country":"US",
    "sg:address":"480 Washington St Ste 102",
    "sg:city":"Brighton",
    "sg:classifiers":[
        {
            "category":"Health Services",
            "subcategory":"Health Practitioner",
            "type":"Services"
        }
    ],
    "sg:phone":"+1 617 254 0492",
    "sg:postcode":"02135",
    "sg:province":"MA",
    "sg:tags":[
        "nutritionist"
    ],
    "wof:name":"Brighton Wic Program",
    "wof:placetype":"venue"
},
  "geometry": {"coordinates":[-71.160281,42.348752],"type":"Point"}
}