{
  "type": "Feature",
  "properties": {
    "iso:country":"US",
    "sg:address":"710 Saratoga St",
    "sg:city":"Boston",
    "sg:classifiers":[
        {
            "category":"Building & Trades",
            "subcategory":"Locksmith",
            "type":"Services"
        }
    ],
    "sg:phone":"+1 617 418 6161",
    "sg:postcode":"02128",
    "sg:province":"MA",
    "sg:tags":[
        "key"
    ],
    "wof:name":"Rc Locksmith",
    "wof:placetype":"venue"
},
  "geometry": {"coordinates":[-71.018914,42.383267],"type":"Point"}
}