{
  "type": "Feature",
  "properties": {
    "addr:full": "1 Faneuil Hall Sq Boston MA 02109",
    "addr:housenumber": "1",
    "addr:postcode": "02109",
    "addr:street": "Faneuil Hall Sq",
    "iso:country": "US",
    "sg:address": "1 Faneuil Hall Sq",
    "sg:city": "Boston",
    "sg:classifiers": [
      {
        "category": "Professional",
        "subcategory": "Management \u0026 Consulting",
        "type": "Services"
      },
      {
        "category": "Professional",
        "subcategory": "Advertising",
        "type": "Services"
      }
    ],
    "sg:phone": "+1 617 426 8200",
    "sg:postcode": "02109",
    "sg:province": "MA",
    "sg:tags": [
      "marketing",
      "program",
      "agency",
      "specialty",
      "consultant"
    ],
    "wof:name": "Blacksheep Marketing",
    "wof:placetype": "venue"
  },
  "geometry": {"coordinates":[-71.055794,42.359959],"type":"Point"}
}
