{
  "type": "Feature",
  "properties": {
    "addr:full": "3 Ray Ave Burlington MA 01803",
    "addr:housenumber": "3",
    "addr:postcode": "01803",
    "addr:street": "Ray Ave",
    "iso:country": "US",
    "sg:address": "3 Ray Ave",
    "sg:city": "Burlington",
    "sg:classifiers": [
      {
        "category": "Real Estate",
        "subcategory": "Architect",
        "type": "Services"
      }
    ],
    "sg:phone": "+1 781 221 7406",
    "sg:postcode": "01803",
    "sg:province": "MA",
    "sg:tags": [
      "architectural"
    ],
    "wof:name": "Huygens Rw Architects Inc",
    "wof:placetype": "venue"
  },
  "geometry": {"coordinates":[-71.186065,42.482088],"type":"Point"}
}
