{
  "type": "Feature",
  "properties": {
    "iso:country":"US",
    "sg:address":"160 Main Rd",
    "sg:city":"Westfield",
    "sg:classifiers":[
        {
            "category":"Education",
            "subcategory":"Library",
            "type":"Public Place"
        }
    ],
    "sg:phone":"+1   ",
    "sg:postcode":"01085",
    "sg:province":"MA",
    "wof:name":"Grace Hall Memorial Library",
    "wof:placetype":"venue"
},
  "geometry": {"coordinates":[-72.812393,42.21008],"type":"Point"}
}