{
  "type": "Feature",
  "properties": {
    "addr:full": "24 High St Medway MA 02053",
    "addr:housenumber": "24",
    "addr:postcode": "02053",
    "addr:street": "High St",
    "iso:country": "US",
    "sg:address": "24 High St",
    "sg:city": "Medway",
    "sg:classifiers": [
      {
        "category": "Building \u0026 Trades",
        "subcategory": "Construction",
        "type": "Services"
      }
    ],
    "sg:phone": "+1 508 533 1558",
    "sg:postcode": "02053",
    "sg:province": "MA",
    "sg:tags": [
      "house"
    ],
    "wof:name": "Brian Kasparian Woodworking",
    "wof:placetype": "venue"
  },
  "geometry": {"coordinates":[-71.43016,42.143606],"type":"Point"}
}
