{
  "type": "Feature",
  "properties": {
    "iso:country":"US",
    "sg:address":"5 Woodvue Cir",
    "sg:city":"Forestdale",
    "sg:classifiers":[
        {
            "category":"Government",
            "subcategory":"Court House",
            "type":"Public Place"
        }
    ],
    "sg:phone":"+1 508 477 1150",
    "sg:postcode":"02644",
    "sg:province":"MA",
    "sg:tags":[
        "justice",
        "peace"
    ],
    "wof:name":"Jeanette A Jones",
    "wof:placetype":"venue"
},
  "geometry": {"coordinates":[-70.497564,41.700847],"type":"Point"}
}