{
  "type": "Feature",
  "properties": {
    "iso:country":"US",
    "sg:address":"61 Homestead St",
    "sg:city":"Waban",
    "sg:classifiers":[
        {
            "category":"Education",
            "subcategory":"School",
            "type":"Public Place"
        }
    ],
    "sg:phone":"+1   ",
    "sg:postcode":"02468",
    "sg:province":"MA",
    "wof:name":"Literature & Professions",
    "wof:placetype":"venue"
},
  "geometry": {"coordinates":[-71.225024,42.325652],"type":"Point"}
}