{
  "type": "Feature",
  "properties": {
    "addr:full":"46 Barnum St Taunton MA 02780",
    "addr:housenumber":"46",
    "addr:postcode":"02780",
    "addr:street":"Barnum St",
    "iso:country":"US",
    "sg:address":"46 Barnum St",
    "sg:city":"Taunton",
    "sg:classifiers":[
        {
            "category":"Building & Trades",
            "subcategory":"Construction",
            "type":"Services"
        }
    ],
    "sg:phone":"+1   ",
    "sg:postcode":"02780",
    "sg:province":"MA",
    "sg:tags":[
        "house"
    ],
    "wof:name":"Christopher P Martin Cnstr",
    "wof:placetype":"venue"
},
  "geometry": {"coordinates":[-71.09718100000001,41.894174],"type":"Point"}
}