{
  "type": "Feature",
  "properties": {
    "addr:full": "229 Berkeley St Ste 201 Boston MA 02116",
    "addr:housenumber": "229",
    "addr:postcode": "02116",
    "addr:street": "Berkeley St Ste 201",
    "iso:country": "US",
    "sg:address": "229 Berkeley St Ste 201",
    "sg:city": "Boston",
    "sg:classifiers": [
      {
        "category": "Real Estate",
        "subcategory": "Real Estate Services",
        "type": "Services"
      },
      {
        "category": "Real Estate",
        "subcategory": "Real Estate Agent",
        "type": "Services"
      }
    ],
    "sg:phone": "+1 617 419 0027",
    "sg:postcode": "02116",
    "sg:province": "MA",
    "sg:website": "www.rossboston.com",
    "wof:name": "ROSSBOSTON",
    "wof:placetype": "venue"
  },
  "geometry": {"coordinates":[-71.07317,42.351665],"type":"Point"}
}
