{
  "type": "Feature",
  "properties": {
    "iso:country":"US",
    "sg:address":"53 Pequossette Rd",
    "sg:city":"Belmont",
    "sg:classifiers":[
        {
            "category":"Recreation",
            "type":"Entertainment"
        }
    ],
    "sg:phone":"+1   ",
    "sg:postcode":"02478",
    "sg:province":"MA",
    "wof:name":"Wilmington Precision Figure",
    "wof:placetype":"venue"
},
  "geometry": {"coordinates":[-71.168243,42.378916],"type":"Point"}
}