{
  "type": "Feature",
  "properties": {
    "iso:country":"US",
    "sg:address":"250 Main St",
    "sg:city":"Webster",
    "sg:classifiers":[
        {
            "category":"Home & Garden",
            "subcategory":"Carpets & Floor Coverings",
            "type":"Retail Goods"
        }
    ],
    "sg:phone":"+1 508 987 6467",
    "sg:postcode":"01570",
    "sg:province":"MA",
    "sg:tags":[
        "material"
    ],
    "wof:name":"Carpet Barn",
    "wof:placetype":"venue"
},
  "geometry": {"coordinates":[-71.88256,42.049258],"type":"Point"}
}