{
  "type": "Feature",
  "properties": {
    "addr:full": "37 Harlow St North Easton MA 02356",
    "addr:housenumber": "37",
    "addr:postcode": "02356",
    "addr:street": "Harlow St",
    "iso:country": "US",
    "sg:address": "37 Harlow St",
    "sg:city": "North Easton",
    "sg:classifiers": [
      {
        "category": "Professional",
        "subcategory": "Management \u0026 Consulting",
        "type": "Services"
      }
    ],
    "sg:phone": "+1 508 238 1881",
    "sg:postcode": "02356",
    "sg:province": "MA",
    "sg:tags": [
      "consultant",
      "training"
    ],
    "wof:name": "On-Site Resource",
    "wof:placetype": "venue"
  },
  "geometry": {"coordinates":[-71.105868,42.079553],"type":"Point"}
}
