{
  "type": "Feature",
  "properties": {
    "iso:country":"US",
    "sg:address":"37 Harlow St",
    "sg:city":"North Easton",
    "sg:classifiers":[
        {
            "category":"Professional",
            "subcategory":"Management & Consulting",
            "type":"Services"
        }
    ],
    "sg:phone":"+1 508 238 1881",
    "sg:postcode":"02356",
    "sg:province":"MA",
    "sg:tags":[
        "consultant",
        "training"
    ],
    "wof:name":"On-Site Resource",
    "wof:placetype":"venue"
},
  "geometry": {"coordinates":[-71.105868,42.079553],"type":"Point"}
}