{
  "type": "Feature",
  "properties": {
    "addr:full": "62 Brown St Ste 420 Haverhill MA 01830",
    "addr:housenumber": "62",
    "addr:postcode": "01830",
    "addr:street": "Brown St Ste 420",
    "iso:country": "US",
    "sg:address": "62 Brown St Ste 420",
    "sg:city": "Haverhill",
    "sg:classifiers": [
      {
        "category": "Wholesale",
        "subcategory": "Medical Equipment \u0026 Supplies",
        "type": "Manufacturing \u0026 Wholesale Goods"
      },
      {
        "category": "Health Services",
        "subcategory": "Health Practitioner",
        "type": "Services"
      }
    ],
    "sg:phone": "+1 978 372 1939",
    "sg:postcode": "01830",
    "sg:province": "MA",
    "sg:tags": [
      "assistive",
      "device",
      "audiologists",
      "aid",
      "hearing"
    ],
    "wof:name": "North Shore Hearing Center",
    "wof:placetype": "venue"
  },
  "geometry": {"coordinates":[-71.047112,42.76487],"type":"Point"}
}
