{
  "type": "Feature",
  "properties": {
    "iso:country":"US",
    "sg:address":"62 Brown St Ste 420",
    "sg:city":"Haverhill",
    "sg:classifiers":[
        {
            "category":"Wholesale",
            "subcategory":"Medical Equipment & Supplies",
            "type":"Manufacturing & Wholesale Goods"
        },
        {
            "category":"Health Services",
            "subcategory":"Health Practitioner",
            "type":"Services"
        }
    ],
    "sg:phone":"+1 978 372 1939",
    "sg:postcode":"01830",
    "sg:province":"MA",
    "sg:tags":[
        "assistive",
        "device",
        "audiologists",
        "aid",
        "hearing"
    ],
    "wof:name":"North Shore Hearing Center",
    "wof:placetype":"venue"
},
  "geometry": {"coordinates":[-71.047112,42.76487],"type":"Point"}
}