{
  "type": "Feature",
  "properties": {
    "iso:country":"US",
    "sg:address":"1044 Chicopee St",
    "sg:city":"Chicopee",
    "sg:classifiers":[
        {
            "category":"Home & Garden",
            "subcategory":"Carpets & Floor Coverings",
            "type":"Retail Goods"
        }
    ],
    "sg:phone":"+1 413 538 5239",
    "sg:postcode":"01013",
    "sg:province":"MA",
    "sg:tags":[
        "dealer",
        "rug"
    ],
    "sg:website":"www.desrosiersfloorcovering.com",
    "wof:name":"Desrosier's Floor Covering",
    "wof:placetype":"venue"
},
  "geometry": {"coordinates":[-72.60061899999999,42.191905],"type":"Point"}
}