{
  "type": "Feature",
  "properties": {
    "addr:full": "1044 Chicopee St Chicopee MA 01013",
    "addr:housenumber": "1044",
    "addr:postcode": "01013",
    "addr:street": "Chicopee St",
    "iso:country": "US",
    "sg:address": "1044 Chicopee St",
    "sg:city": "Chicopee",
    "sg:classifiers": [
      {
        "category": "Home \u0026 Garden",
        "subcategory": "Carpets \u0026 Floor Coverings",
        "type": "Retail Goods"
      }
    ],
    "sg:phone": "+1 413 538 5239",
    "sg:postcode": "01013",
    "sg:province": "MA",
    "sg:tags": [
      "dealer",
      "rug"
    ],
    "sg:website": "www.desrosiersfloorcovering.com",
    "wof:name": "Desrosier's Floor Covering",
    "wof:placetype": "venue"
  },
  "geometry": {"coordinates":[-72.600619,42.191905],"type":"Point"}
}
