{
  "type": "Feature",
  "properties": {
    "iso:country":"US",
    "sg:address":"1 Post Office Sq",
    "sg:city":"Acton",
    "sg:classifiers":[
        {
            "category":"Professional",
            "subcategory":"Business Services",
            "type":"Services"
        }
    ],
    "sg:phone":"+1 978 264 4450",
    "sg:postcode":"01720",
    "sg:province":"MA",
    "sg:tags":[
        "development",
        "product",
        "designers-industrial",
        "marketing",
        "commercial",
        "design"
    ],
    "wof:name":"Product Insight Inc",
    "wof:placetype":"venue"
},
  "geometry": {"coordinates":[-71.426964,42.49057],"type":"Point"}
}