{
  "type": "Feature",
  "properties": {
    "iso:country":"US",
    "sg:address":"6 Ford Ln",
    "sg:city":"Framingham",
    "sg:classifiers":[
        {
            "category":"Professional",
            "type":"Services"
        }
    ],
    "sg:phone":"+1   ",
    "sg:postcode":"01701",
    "sg:province":"MA",
    "wof:name":"Viasolutions",
    "wof:placetype":"venue"
},
  "geometry": {"coordinates":[-71.46586000000001,42.302996],"type":"Point"}
}