{
  "type": "Feature",
  "properties": {
    "iso:country":"US",
    "sg:address":"470 Atlantic Ave",
    "sg:city":"Boston",
    "sg:classifiers":[
        {
            "category":"Insurance",
            "subcategory":"Insurance Agent",
            "type":"Services"
        }
    ],
    "sg:phone":"+1 617 261 6700",
    "sg:postcode":"02210",
    "sg:province":"MA",
    "sg:website":"www.wgains.com",
    "wof:name":"William Gallagher Assoc",
    "wof:placetype":"venue"
},
  "geometry": {"coordinates":[-71.053386,42.353784],"type":"Point"}
}