{
  "type": "Feature",
  "properties": {
    "addr:full":"637 Lowell St Peabody MA 01960",
    "addr:housenumber":"637",
    "addr:postcode":"01960",
    "addr:street":"Lowell St",
    "iso:country":"US",
    "sg:address":"637 Lowell St",
    "sg:city":"Peabody",
    "sg:classifiers":[
        {
            "category":"Government",
            "subcategory":"Post Office",
            "type":"Public Place"
        }
    ],
    "sg:phone":"+1 978 000 1111",
    "sg:postcode":"01960",
    "sg:province":"MA",
    "wof:name":"US Post Office",
    "wof:placetype":"venue"
},
  "geometry": {"coordinates":[-70.999078,42.550323],"type":"Point"}
}