{
  "type": "Feature",
  "properties": {
    "addr:full": "50 Border St Scituate MA 02066",
    "addr:housenumber": "50",
    "addr:postcode": "02066",
    "addr:street": "Border St",
    "iso:country": "US",
    "sg:address": "50 Border St",
    "sg:city": "Scituate",
    "sg:classifiers": [
      {
        "category": "Travel",
        "subcategory": "Travel Agent",
        "type": "Entertainment"
      }
    ],
    "sg:phone": "+1 781 545 2007",
    "sg:postcode": "02066",
    "sg:province": "MA",
    "sg:tags": [
      "agency",
      "bureau"
    ],
    "wof:name": "Madelene Travel",
    "wof:placetype": "venue"
  },
  "geometry": {"coordinates":[-70.777912,42.227574],"type":"Point"}
}
