{
  "type": "Feature",
  "properties": {
    "addr:full": "9 Plaza Ln Buzzards Bay MA 02532",
    "addr:postcode": "02532",
    "addr:street": "Plaza Ln",
    "iso:country": "US",
    "sg:address": "9 Plaza Ln",
    "sg:city": "Buzzards Bay",
    "sg:classifiers": [
      {
        "category": "Retail",
        "subcategory": "Repair Shop",
        "type": "Services"
      }
    ],
    "sg:phone": "+1 508 759 6224",
    "sg:postcode": "02532",
    "sg:province": "MA",
    "wof:name": "Studio Renee",
    "wof:placetype": "venue"
  },
  "geometry": {"coordinates":[-70.619972,41.743994],"type":"Point"}
}
