{
  "type": "Feature",
  "properties": {
    "addr:full":"45 Teed Dr Randolph MA 02368",
    "addr:housenumber":"45",
    "addr:postcode":"02368",
    "addr:street":"Teed Dr",
    "iso:country":"US",
    "sg:address":"45 Teed Dr",
    "sg:city":"Randolph",
    "sg:classifiers":[
        {
            "category":"Professional",
            "subcategory":"Advertising",
            "type":"Services"
        }
    ],
    "sg:phone":"+1   ",
    "sg:postcode":"02368",
    "sg:province":"MA",
    "sg:tags":[
        "outdoor"
    ],
    "wof:name":"T D I",
    "wof:placetype":"venue"
},
  "geometry": {"coordinates":[-71.02603999999999,42.177231],"type":"Point"}
}