{
  "type": "Feature",
  "properties": {
    "addr:full": "19 Franklin Ct Dorchester MA 02125",
    "addr:housenumber": "19",
    "addr:postcode": "02125",
    "addr:street": "Franklin Ct",
    "iso:country": "US",
    "sg:address": "19 Franklin Ct",
    "sg:city": "Dorchester",
    "sg:classifiers": [
      {
        "category": "Building \u0026 Trades",
        "subcategory": "Construction",
        "type": "Services"
      }
    ],
    "sg:phone": "+1 617 442 5588",
    "sg:postcode": "02125",
    "sg:province": "MA",
    "sg:tags": [
      "contractor"
    ],
    "wof:name": "Nova Restorations Inc",
    "wof:placetype": "venue"
  },
  "geometry": {"coordinates":[-71.0657,42.3222],"type":"Point"}
}
