{
  "type": "Feature",
  "properties": {
    "addr:full":"19 Rindge Ave Cambridge MA 02140",
    "addr:housenumber":"19",
    "addr:postcode":"02140",
    "addr:street":"Rindge Ave",
    "iso:country":"US",
    "sg:address":"19 Rindge Ave",
    "sg:city":"Cambridge",
    "sg:classifiers":[
        {
            "category":"Social Services",
            "subcategory":"Child Care",
            "type":"Services"
        }
    ],
    "sg:phone":"+1   ",
    "sg:postcode":"02140",
    "sg:province":"MA",
    "sg:tags":[
        "day"
    ],
    "wof:name":"Zachary Bear Food Program Inc",
    "wof:placetype":"venue"
},
  "geometry": {"coordinates":[-71.12501399999999,42.392649],"type":"Point"}
}