{
  "type": "Feature",
  "properties": {
    "addr:full": "811 Boylston St 3rd Fl Boston MA 02116",
    "addr:housenumber": "811;3rd fl",
    "addr:postcode": "02116",
    "addr:street": "Boylston St",
    "iso:country": "US",
    "sg:address": "811 Boylston St 3rd Fl",
    "sg:city": "Boston",
    "sg:classifiers": [
      {
        "category": "Health Services",
        "subcategory": "Dentist",
        "type": "Services"
      }
    ],
    "sg:phone": "+1 617 267 3993",
    "sg:postcode": "02116",
    "sg:province": "MA",
    "sg:website": "www.kurbanfereidouni.com",
    "wof:name": "Kurban \u0026 Fereidouni",
    "wof:placetype": "venue"
  },
  "geometry": {"coordinates":[-71.082207,42.348803],"type":"Point"}
}
