{
  "type": "Feature",
  "properties": {
    "addr:full": "27 Elm St Andover MA 01810",
    "addr:housenumber": "27",
    "addr:postcode": "01810",
    "addr:street": "Elm St",
    "iso:country": "US",
    "sg:address": "27 Elm St",
    "sg:city": "Andover",
    "sg:classifiers": [
      {
        "category": "Building \u0026 Trades",
        "subcategory": "Construction",
        "type": "Services"
      }
    ],
    "sg:phone": "+1 978 921 1213",
    "sg:postcode": "01810",
    "sg:province": "MA",
    "sg:tags": [
      "painter"
    ],
    "wof:name": "Clark House Painting",
    "wof:placetype": "venue"
  },
  "geometry": {"coordinates":[-71.140202,42.657558],"type":"Point"}
}
