{
  "type": "Feature",
  "properties": {
    "addr:full":"41 Mall Rd Burlington MA 01803",
    "addr:housenumber":"41",
    "addr:postcode":"01803",
    "addr:street":"Mall Rd",
    "iso:country":"US",
    "sg:address":"41 Mall Rd",
    "sg:city":"Burlington",
    "sg:classifiers":[
        {
            "category":"Health Services",
            "subcategory":"Doctor",
            "type":"Services"
        }
    ],
    "sg:phone":"+1 781 273 8635",
    "sg:postcode":"01803",
    "sg:province":"MA",
    "wof:name":"Lessell Irma M MD",
    "wof:placetype":"venue"
},
  "geometry": {"coordinates":[-71.198402,42.490398],"type":"Point"}
}