{
  "type": "Feature",
  "properties": {
    "addr:full": "32 Forestdale Dr Halifax MA 02338",
    "addr:housenumber": "32",
    "addr:postcode": "02338",
    "addr:street": "Forestdale Dr",
    "iso:country": "US",
    "sg:address": "32 Forestdale Dr",
    "sg:city": "Halifax",
    "sg:classifiers": [
      {
        "category": "Retail",
        "subcategory": "Auto Repair",
        "type": "Services"
      }
    ],
    "sg:phone": "+1   ",
    "sg:postcode": "02338",
    "sg:province": "MA",
    "sg:tags": [
      "body",
      "special",
      "mfg"
    ],
    "wof:name": "Brooks Sign",
    "wof:placetype": "venue"
  },
  "geometry": {"coordinates":[-70.827756,41.993368],"type":"Point"}
}
