{
  "type": "Feature",
  "properties": {
    "addr:full":"1400 Middlesex St Lowell MA 01851",
    "addr:housenumber":"1400",
    "addr:postcode":"01851",
    "addr:street":"Middlesex St",
    "iso:country":"US",
    "sg:address":"1400 Middlesex St",
    "sg:city":"Lowell",
    "sg:classifiers":[
        {
            "category":"Manufacturing",
            "subcategory":"Textiles",
            "type":"Manufacturing & Wholesale Goods"
        }
    ],
    "sg:phone":"+1 978 458 6833",
    "sg:postcode":"01851",
    "sg:province":"MA",
    "sg:tags":[
        "rubberized",
        "coated",
        "fabric"
    ],
    "wof:name":"Ideal Tape Co",
    "wof:placetype":"venue"
},
  "geometry": {"coordinates":[-71.34125299999999,42.638301],"type":"Point"}
}