{
  "type": "Feature",
  "properties": {
    "addr:full": "9 Park Dr Westford MA 01886",
    "addr:housenumber": "9",
    "addr:postcode": "01886",
    "addr:street": "Park Dr",
    "iso:country": "US",
    "sg:address": "9 Park Dr",
    "sg:city": "Westford",
    "sg:classifiers": [
      {
        "category": "Home \u0026 Garden",
        "subcategory": "Carpets \u0026 Floor Coverings",
        "type": "Retail Goods"
      }
    ],
    "sg:phone": "+1   ",
    "sg:postcode": "01886",
    "sg:province": "MA",
    "wof:name": "Westford Custom Floors",
    "wof:placetype": "venue"
  },
  "geometry": {"coordinates":[-71.435472,42.557333],"type":"Point"}
}
