{
  "type": "Feature",
  "properties": {
    "addr:full": "2 Mount Royal Ave Marlborough MA 01752",
    "addr:housenumber": "2",
    "addr:postcode": "01752",
    "addr:street": "Mount Royal Ave",
    "iso:country": "US",
    "sg:address": "2 Mount Royal Ave",
    "sg:city": "Marlborough",
    "sg:classifiers": [
      {
        "category": "Professional",
        "subcategory": "Management \u0026 Consulting",
        "type": "Services"
      }
    ],
    "sg:phone": "+1 508 460 9600",
    "sg:postcode": "01752",
    "sg:province": "MA",
    "sg:tags": [
      "consultant"
    ],
    "wof:name": "Clark Consulting",
    "wof:placetype": "venue"
  },
  "geometry": {"coordinates":[-71.581054,42.340315],"type":"Point"}
}
