{
  "type": "Feature",
  "properties": {
    "addr:full":"118 Merrimack St Haverhill MA 01830",
    "addr:housenumber":"118",
    "addr:postcode":"01830",
    "addr:street":"Merrimack St",
    "iso:country":"US",
    "sg:address":"118 Merrimack St",
    "sg:city":"Haverhill",
    "sg:classifiers":[
        {
            "category":"Health Services",
            "subcategory":"Doctor",
            "type":"Services"
        }
    ],
    "sg:phone":"+1 978 373 4150",
    "sg:postcode":"01830",
    "sg:province":"MA",
    "sg:tags":[
        "dentist"
    ],
    "wof:name":"Stephen C Chadwick DDS",
    "wof:placetype":"venue"
},
  "geometry": {"coordinates":[-71.079629,42.774298],"type":"Point"}
}