{
  "type": "Feature",
  "properties": {
    "addr:full": "151 Queen Anne Rd Harwich MA 02645",
    "addr:housenumber": "151",
    "addr:postcode": "02645",
    "addr:street": "Queen Anne Rd",
    "iso:country": "US",
    "sg:address": "151 Queen Anne Rd",
    "sg:city": "Harwich",
    "sg:classifiers": [
      {
        "category": "Retail",
        "subcategory": "Repair Shop",
        "type": "Services"
      }
    ],
    "sg:phone": "+1 508 430 7486",
    "sg:postcode": "02645",
    "sg:province": "MA",
    "sg:tags": [
      "upholsterer"
    ],
    "wof:name": "Upholstery Design \u0026 Canvas",
    "wof:placetype": "venue"
  },
  "geometry": {"coordinates":[-70.100165,41.697984],"type":"Point"}
}
