{
  "type": "Feature",
  "properties": {
    "iso:country":"US",
    "sg:address":"151 Queen Anne Rd",
    "sg:city":"Harwich",
    "sg:classifiers":[
        {
            "category":"Retail",
            "subcategory":"Repair Shop",
            "type":"Services"
        }
    ],
    "sg:phone":"+1 508 430 7486",
    "sg:postcode":"02645",
    "sg:province":"MA",
    "sg:tags":[
        "upholsterer"
    ],
    "wof:name":"Upholstery Design & Canvas",
    "wof:placetype":"venue"
},
  "geometry": {"coordinates":[-70.100165,41.697984],"type":"Point"}
}