{
  "type": "Feature",
  "properties": {
    "addr:full":"275 Beacon St Somerville MA 02143",
    "addr:housenumber":"275",
    "addr:postcode":"02143",
    "addr:street":"Beacon St",
    "iso:country":"US",
    "sg:address":"275 Beacon St",
    "sg:city":"Somerville",
    "sg:classifiers":[
        {
            "category":"Food & Beverages",
            "subcategory":"Groceries & Convenience Stores",
            "type":"Retail Goods"
        }
    ],
    "sg:phone":"+1 617 354 7023",
    "sg:postcode":"02143",
    "sg:province":"MA",
    "sg:tags":[
        "grocer"
    ],
    "wof:name":"Star Market",
    "wof:placetype":"venue"
},
  "geometry": {"coordinates":[-71.111752,42.383484],"type":"Point"}
}