{
  "type": "Feature",
  "properties": {
    "iso:country":"US",
    "sg:address":"68 Bay State Rd",
    "sg:city":"Weston",
    "sg:classifiers":[
        {
            "category":"Professional",
            "subcategory":"Management & Consulting",
            "type":"Services"
        }
    ],
    "sg:phone":"+1   ",
    "sg:postcode":"02493",
    "sg:province":"MA",
    "wof:name":"Allen Michel & Assoc Inc",
    "wof:placetype":"venue"
},
  "geometry": {"coordinates":[-71.282866,42.395233],"type":"Point"}
}