{
  "type": "Feature",
  "properties": {
    "addr:full": "68 Bay State Rd Weston MA 02493",
    "addr:housenumber": "68",
    "addr:postcode": "02493",
    "addr:street": "Bay State Rd",
    "iso:country": "US",
    "sg:address": "68 Bay State Rd",
    "sg:city": "Weston",
    "sg:classifiers": [
      {
        "category": "Professional",
        "subcategory": "Management \u0026 Consulting",
        "type": "Services"
      }
    ],
    "sg:phone": "+1   ",
    "sg:postcode": "02493",
    "sg:province": "MA",
    "wof:name": "Allen Michel \u0026 Assoc Inc",
    "wof:placetype": "venue"
  },
  "geometry": {"coordinates":[-71.282866,42.395233],"type":"Point"}
}
