{
  "type": "Feature",
  "properties": {
    "iso:country":"US",
    "sg:address":"233 Carew St",
    "sg:city":"Springfield",
    "sg:classifiers":[
        {
            "category":"Health Services",
            "subcategory":"Hospital",
            "type":"Services"
        }
    ],
    "sg:phone":"+1 413 748 6800",
    "sg:postcode":"01104",
    "sg:province":"MA",
    "sg:website":"www.mercycares.com",
    "wof:name":"Weldon Rehabilitation Hospital",
    "wof:placetype":"venue"
},
  "geometry": {"coordinates":[-72.595372,42.116104],"type":"Point"}
}