{
  "type": "Feature",
  "properties": {
    "iso:country":"US",
    "sg:address":"6 Stanton St",
    "sg:city":"Saugus",
    "sg:classifiers":[
        {
            "category":"Retail",
            "subcategory":"Repair Shop",
            "type":"Services"
        }
    ],
    "sg:phone":"+1   ",
    "sg:postcode":"01906",
    "sg:province":"MA",
    "sg:tags":[
        "electrical"
    ],
    "wof:name":"Mf Electric",
    "wof:placetype":"venue"
},
  "geometry": {"coordinates":[-70.99943399999999,42.46017],"type":"Point"}
}