{
  "type": "Feature",
  "properties": {
    "addr:full": "6 Stanton St Saugus MA 01906",
    "addr:housenumber": "6",
    "addr:postcode": "01906",
    "addr:street": "Stanton St",
    "iso:country": "US",
    "sg:address": "6 Stanton St",
    "sg:city": "Saugus",
    "sg:classifiers": [
      {
        "category": "Retail",
        "subcategory": "Repair Shop",
        "type": "Services"
      }
    ],
    "sg:phone": "+1   ",
    "sg:postcode": "01906",
    "sg:province": "MA",
    "sg:tags": [
      "electrical"
    ],
    "wof:name": "Mf Electric",
    "wof:placetype": "venue"
  },
  "geometry": {"coordinates":[-70.999434,42.46017],"type":"Point"}
}
