{
  "type": "Feature",
  "properties": {
    "addr:full": "1045 University Ave Norwood MA 02062",
    "addr:housenumber": "1045",
    "addr:postcode": "02062",
    "addr:street": "University Ave",
    "iso:country": "US",
    "sg:address": "1045 University Ave",
    "sg:city": "Norwood",
    "sg:classifiers": [
      {
        "category": "Freight",
        "type": "Transportation"
      }
    ],
    "sg:postcode": "02062",
    "sg:province": "MA",
    "sg:tags": [
      "shipping"
    ],
    "wof:name": "UPS",
    "wof:placetype": "venue"
  },
  "geometry": {"coordinates":[-71.178921,42.206831],"type":"Point"}
}
