{
  "type": "Feature",
  "properties": {
    "iso:country":"US",
    "sg:address":"139 Coolidge Rd",
    "sg:city":"Worcester",
    "sg:classifiers":[
        {
            "category":"Insurance",
            "subcategory":"Insurance Agent",
            "type":"Services"
        }
    ],
    "sg:phone":"+1 508 753 3366",
    "sg:postcode":"01602",
    "sg:province":"MA",
    "wof:name":"Brunell Group",
    "wof:placetype":"venue"
},
  "geometry": {"coordinates":[-71.82488499999999,42.265687],"type":"Point"}
}