{
  "type": "Feature",
  "properties": {
    "addr:full":"625 Main St Hampden MA 01036",
    "addr:housenumber":"625",
    "addr:postcode":"01036",
    "addr:street":"Main St",
    "iso:country":"US",
    "sg:address":"625 Main St",
    "sg:city":"Hampden",
    "sg:classifiers":[
        {
            "category":"Recreation",
            "type":"Entertainment"
        }
    ],
    "sg:phone":"+1 413 566 2204",
    "sg:postcode":"01036",
    "sg:province":"MA",
    "sg:tags":[
        "parks"
    ],
    "wof:name":"Parks Dept",
    "wof:placetype":"venue"
},
  "geometry": {"coordinates":[-72.414541,42.063966],"type":"Point"}
}