{
  "type": "Feature",
  "properties": {
    "iso:country":"US",
    "sg:address":"100 Grove St",
    "sg:city":"Worcester",
    "sg:classifiers":[
        {
            "category":"Social Services",
            "type":"Services"
        }
    ],
    "sg:phone":"+1 508 793 0059",
    "sg:postcode":"01605",
    "sg:province":"MA",
    "sg:tags":[
        "organization",
        "welfare"
    ],
    "wof:name":"Centro Presente",
    "wof:placetype":"venue"
},
  "geometry": {"coordinates":[-71.80070499999999,42.275338],"type":"Point"}
}