{
  "type": "Feature",
  "properties": {
    "addr:full": "10 Commercial Wharf Boston MA 02110",
    "addr:housenumber": "10",
    "addr:postcode": "02110",
    "addr:street": "Commercial Wharf",
    "iso:country": "US",
    "sg:address": "10 Commercial Wharf",
    "sg:city": "Boston",
    "sg:classifiers": [
      {
        "category": "Professional",
        "subcategory": "Secretarial Services",
        "type": "Services"
      }
    ],
    "sg:phone": "+1 617 723 0640",
    "sg:postcode": "02110",
    "sg:province": "MA",
    "sg:tags": [
      "convention",
      "court",
      "reporter"
    ],
    "wof:name": "Catuogno Court Reporting",
    "wof:placetype": "venue"
  },
  "geometry": {"coordinates":[-71.051177,42.362452],"type":"Point"}
}
