{
  "type": "Feature",
  "properties": {
    "iso:country":"US",
    "sg:address":"888 Broadway",
    "sg:city":"Everett",
    "sg:classifiers":[
        {
            "category":"Education",
            "subcategory":"School",
            "type":"Public Place"
        }
    ],
    "sg:phone":"+1 617 389 0240",
    "sg:postcode":"02149",
    "sg:province":"MA",
    "wof:name":"Pope John 23rd High School",
    "wof:placetype":"venue"
},
  "geometry": {"coordinates":[-71.04392,42.420342],"type":"Point"}
}