{
  "type": "Feature",
  "properties": {
    "addr:full": "32 Homeward Ln Walpole MA 02081",
    "addr:housenumber": "32",
    "addr:postcode": "02081",
    "addr:street": "Homeward Ln",
    "iso:country": "US",
    "sg:address": "32 Homeward Ln",
    "sg:city": "Walpole",
    "sg:classifiers": [
      {
        "category": "Banks \u0026 Credit Unions",
        "subcategory": "Investment Brokerage",
        "type": "Services"
      }
    ],
    "sg:phone": "+1 508 850 9808",
    "sg:postcode": "02081",
    "sg:province": "MA",
    "sg:tags": [
      "advisory",
      "financial"
    ],
    "wof:name": "J \u0026 P Assoc LTD",
    "wof:placetype": "venue"
  },
  "geometry": {"coordinates":[-71.261048,42.176595],"type":"Point"}
}
