{
  "type": "Feature",
  "properties": {
    "iso:country":"US",
    "sg:address":"32 Homeward Ln",
    "sg:city":"Walpole",
    "sg:classifiers":[
        {
            "category":"Banks & Credit Unions",
            "subcategory":"Investment Brokerage",
            "type":"Services"
        }
    ],
    "sg:phone":"+1 508 850 9808",
    "sg:postcode":"02081",
    "sg:province":"MA",
    "sg:tags":[
        "advisory",
        "financial"
    ],
    "wof:name":"J & P Assoc LTD",
    "wof:placetype":"venue"
},
  "geometry": {"coordinates":[-71.261048,42.176595],"type":"Point"}
}