{
  "type": "Feature",
  "properties": {
    "iso:country":"US",
    "sg:address":"558 Clark Rd",
    "sg:city":"Tewksbury",
    "sg:classifiers":[
        {
            "category":"Wholesale",
            "subcategory":"Beer",
            "type":"Manufacturing & Wholesale Goods"
        }
    ],
    "sg:phone":"+1 978 654 6307",
    "sg:postcode":"01876",
    "sg:province":"MA",
    "sg:tags":[
        "ale"
    ],
    "wof:name":"D J Reardon Co",
    "wof:placetype":"venue"
},
  "geometry": {"coordinates":[-71.269631,42.630466],"type":"Point"}
}