{
  "type": "Feature",
  "properties": {
    "iso:country":"US",
    "sg:address":"48 Woerd Ave",
    "sg:city":"Waltham",
    "sg:classifiers":[
        {
            "category":"Professional",
            "type":"Services"
        }
    ],
    "sg:phone":"+1 781 419 3900",
    "sg:postcode":"02453",
    "sg:province":"MA",
    "sg:tags":[
        "establishment"
    ],
    "wof:name":"R D Tech",
    "wof:placetype":"venue"
},
  "geometry": {"coordinates":[-71.24398600000001,42.363363],"type":"Point"}
}