{
  "type": "Feature",
  "properties": {
    "iso:country":"US",
    "sg:address":"130 Canal St",
    "sg:city":"Salem",
    "sg:classifiers":[
        {
            "category":"Shopping",
            "subcategory":"Gifts & Souvenirs",
            "type":"Retail Goods"
        }
    ],
    "sg:phone":"+1 978 745 6967",
    "sg:postcode":"01970",
    "sg:province":"MA",
    "sg:tags":[
        "basket",
        "fruit"
    ],
    "wof:name":"North Shore Fruit Basket Co",
    "wof:placetype":"venue"
},
  "geometry": {"coordinates":[-70.89649799999999,42.51076],"type":"Point"}
}