{
  "type": "Feature",
  "properties": {
    "addr:full":"27 Katrina Rd Chelmsford MA 01824",
    "addr:housenumber":"27",
    "addr:postcode":"01824",
    "addr:street":"Katrina Rd",
    "iso:country":"US",
    "sg:address":"27 Katrina Rd",
    "sg:city":"Chelmsford",
    "sg:classifiers":[
        {
            "category":"Freight",
            "type":"Transportation"
        }
    ],
    "sg:phone":"+1 978 433 2515",
    "sg:postcode":"01824",
    "sg:province":"MA",
    "sg:tags":[
        "mover"
    ],
    "sg:website":"www.northmiddlesexmoving.com",
    "wof:name":"North Middlesex Moving Systems",
    "wof:placetype":"venue"
},
  "geometry": {"coordinates":[-71.331841,42.609698],"type":"Point"}
}