{
  "type": "Feature",
  "properties": {
    "iso:country":"US",
    "sg:address":"5 Douglas St",
    "sg:city":"Uxbridge",
    "sg:classifiers":[
        {
            "category":"Food & Beverages",
            "subcategory":"Bakery",
            "type":"Retail Goods"
        }
    ],
    "sg:phone":"+1 508 278 9977",
    "sg:postcode":"01569",
    "sg:province":"MA",
    "sg:tags":[
        "shop",
        "donut",
        "doughnut"
    ],
    "wof:name":"Jumbo Donuts",
    "wof:placetype":"venue"
},
  "geometry": {"coordinates":[-71.630371,42.076981],"type":"Point"}
}