{
  "type": "Feature",
  "properties": {
    "iso:country":"US",
    "sg:address":"210 Commercial St",
    "sg:city":"Boston",
    "sg:classifiers":[
        {
            "category":"Building & Trades",
            "subcategory":"Locksmith",
            "type":"Services"
        }
    ],
    "sg:phone":"+1 617 531 0878",
    "sg:postcode":"02109",
    "sg:province":"MA",
    "sg:tags":[
        "key"
    ],
    "wof:name":"24 Emergency Locksmith",
    "wof:placetype":"venue"
},
  "geometry": {"coordinates":[-71.05173600000001,42.363234],"type":"Point"}
}