{
  "type": "Feature",
  "properties": {
    "addr:full": "210 Commercial St Boston MA 02109",
    "addr:housenumber": "210",
    "addr:postcode": "02109",
    "addr:street": "Commercial St",
    "iso:country": "US",
    "sg:address": "210 Commercial St",
    "sg:city": "Boston",
    "sg:classifiers": [
      {
        "category": "Building \u0026 Trades",
        "subcategory": "Locksmith",
        "type": "Services"
      }
    ],
    "sg:phone": "+1 617 531 0878",
    "sg:postcode": "02109",
    "sg:province": "MA",
    "sg:tags": [
      "key"
    ],
    "wof:name": "24 Emergency Locksmith",
    "wof:placetype": "venue"
  },
  "geometry": {"coordinates":[-71.051736,42.363234],"type":"Point"}
}
