{
  "type": "Feature",
  "properties": {
    "iso:country":"US",
    "sg:address":"260 Wood St",
    "sg:city":"Middleboro",
    "sg:classifiers":[
        {
            "category":"Professional",
            "type":"Services"
        },
        {
            "category":"Shopping",
            "subcategory":"Party Supplies",
            "type":"Retail Goods"
        },
        {
            "category":"Restaurant",
            "type":"Food & Drink"
        }
    ],
    "sg:phone":"+1 508 947 0668",
    "sg:postcode":"02346",
    "sg:province":"MA",
    "sg:tags":[
        "caterer",
        "buffet",
        "wedding"
    ],
    "sg:website":"http://www.cateringbywarren.com",
    "wof:name":"Catering By Warren",
    "wof:placetype":"venue"
},
  "geometry": {"coordinates":[-70.87975900000001,41.891303],"type":"Point"}
}