{
  "type": "Feature",
  "properties": {
    "iso:country":"US",
    "sg:address":"5 High Rock Rd",
    "sg:city":"Stoneham",
    "sg:classifiers":[
        {
            "category":"Wholesale",
            "subcategory":"Non-durable Goods",
            "type":"Manufacturing & Wholesale Goods"
        }
    ],
    "sg:phone":"+1   ",
    "sg:postcode":"02180",
    "sg:province":"MA",
    "sg:tags":[
        "who",
        "advertising",
        "specialty"
    ],
    "wof:name":"Legendary Promotions",
    "wof:placetype":"venue"
},
  "geometry": {"coordinates":[-71.098297,42.46975],"type":"Point"}
}