{
  "type": "Feature",
  "properties": {
    "iso:country":"US",
    "sg:address":"290 Washington St",
    "sg:city":"Brighton",
    "sg:classifiers":[
        {
            "category":"Food & Beverages",
            "subcategory":"Bakery",
            "type":"Retail Goods"
        },
        {
            "category":"Food & Beverages",
            "subcategory":"Groceries & Convenience Stores",
            "type":"Retail Goods"
        }
    ],
    "sg:phone":"+1 617 254 9486",
    "sg:postcode":"02135",
    "sg:province":"MA",
    "sg:tags":[
        "sandwich"
    ],
    "wof:name":"Winship Spa",
    "wof:placetype":"venue"
},
  "geometry": {"coordinates":[-71.15239699999999,42.349201],"type":"Point"}
}