{
  "type": "Feature",
  "properties": {
    "addr:full": "290 Washington St Brighton MA 02135",
    "addr:housenumber": "290",
    "addr:postcode": "02135",
    "addr:street": "Washington St",
    "iso:country": "US",
    "sg:address": "290 Washington St",
    "sg:city": "Brighton",
    "sg:classifiers": [
      {
        "category": "Food \u0026 Beverages",
        "subcategory": "Bakery",
        "type": "Retail Goods"
      },
      {
        "category": "Food \u0026 Beverages",
        "subcategory": "Groceries \u0026 Convenience Stores",
        "type": "Retail Goods"
      }
    ],
    "sg:phone": "+1 617 254 9486",
    "sg:postcode": "02135",
    "sg:province": "MA",
    "sg:tags": [
      "sandwich"
    ],
    "wof:name": "Winship Spa",
    "wof:placetype": "venue"
  },
  "geometry": {"coordinates":[-71.152397,42.349201],"type":"Point"}
}
