{
  "type": "Feature",
  "properties": {
    "addr:full":"240 Fortune Blvd Milford MA 01757",
    "addr:housenumber":"240",
    "addr:postcode":"01757",
    "addr:street":"Fortune Blvd",
    "iso:country":"US",
    "sg:address":"240 Fortune Blvd",
    "sg:city":"Milford",
    "sg:classifiers":[
        {
            "category":"Restaurant",
            "type":"Food & Drink"
        }
    ],
    "sg:menulink":"http://www.allmenus.com/ma/milford/75633-tgi-fridays/menu/",
    "sg:phone":"+1 508 634 3018",
    "sg:postcode":"01757",
    "sg:province":"MA",
    "sg:tags":[
        "american"
    ],
    "wof:name":"T.G.I. Friday's",
    "wof:placetype":"venue"
},
  "geometry": {"coordinates":[-71.50060000000001,42.159613],"type":"Point"}
}