{
  "type": "Feature",
  "properties": {
    "iso:country":"US",
    "sg:address":"26 Tremont St",
    "sg:city":"Lynn",
    "sg:classifiers":[
        {
            "category":"Communications",
            "type":"Services"
        }
    ],
    "sg:phone":"+1 781 596 9641",
    "sg:postcode":"01902",
    "sg:province":"MA",
    "wof:name":"Lynn Community Access & Media",
    "wof:placetype":"venue"
},
  "geometry": {"coordinates":[-70.950467,42.462683],"type":"Point"}
}