{
  "type": "Feature",
  "properties": {
    "iso:country":"US",
    "sg:address":"396 Main St",
    "sg:city":"Hyannis",
    "sg:classifiers":[
        {
            "category":"Manufacturing",
            "subcategory":"Watercraft",
            "type":"Manufacturing & Wholesale Goods"
        }
    ],
    "sg:phone":"+1 508 771 8911",
    "sg:postcode":"02601",
    "sg:province":"MA",
    "sg:tags":[
        "boat"
    ],
    "sg:website":"www.cookyacht.com",
    "wof:name":"Cook Yacht Design",
    "wof:placetype":"venue"
},
  "geometry": {"coordinates":[-70.284423,41.652599],"type":"Point"}
}