{
  "type": "Feature",
  "properties": {
    "addr:full": "396 Main St Hyannis MA 02601",
    "addr:housenumber": "396",
    "addr:postcode": "02601",
    "addr:street": "Main St",
    "iso:country": "US",
    "sg:address": "396 Main St",
    "sg:city": "Hyannis",
    "sg:classifiers": [
      {
        "category": "Manufacturing",
        "subcategory": "Watercraft",
        "type": "Manufacturing \u0026 Wholesale Goods"
      }
    ],
    "sg:phone": "+1 508 771 8911",
    "sg:postcode": "02601",
    "sg:province": "MA",
    "sg:tags": [
      "boat"
    ],
    "sg:website": "www.cookyacht.com",
    "wof:name": "Cook Yacht Design",
    "wof:placetype": "venue"
  },
  "geometry": {"coordinates":[-70.284423,41.652599],"type":"Point"}
}
