{
  "type": "Feature",
  "properties": {
    "iso:country":"US",
    "sg:address":"510 King St",
    "sg:city":"Littleton",
    "sg:classifiers":[
        {
            "category":"Insurance",
            "subcategory":"Insurance Agent",
            "type":"Services"
        }
    ],
    "sg:phone":"+1 978 486 3575",
    "sg:postcode":"01460",
    "sg:province":"MA",
    "wof:name":"Farm Family Insurance Co",
    "wof:placetype":"venue"
},
  "geometry": {"coordinates":[-71.471915,42.546974],"type":"Point"}
}