{
  "type": "Feature",
  "properties": {
    "addr:full":"128 Wheeler Rd Burlington MA 01803",
    "addr:housenumber":"128",
    "addr:postcode":"01803",
    "addr:street":"Wheeler Rd",
    "iso:country":"US",
    "sg:address":"128 Wheeler Rd",
    "sg:city":"Burlington",
    "sg:classifiers":[
        {
            "category":"Health Services",
            "subcategory":"Health Practitioner",
            "type":"Services"
        }
    ],
    "sg:phone":"+1 781 273 3244",
    "sg:postcode":"01803",
    "sg:province":"MA",
    "sg:tags":[
        "nurse",
        "registry"
    ],
    "wof:name":"D B Healthcare",
    "wof:placetype":"venue"
},
  "geometry": {"coordinates":[-71.21506100000001,42.476508],"type":"Point"}
}