{
  "type": "Feature",
  "properties": {
    "addr:full": "1400 Hancock St Quincy MA 02169",
    "addr:housenumber": "1400",
    "addr:postcode": "02169",
    "addr:street": "Hancock St",
    "iso:country": "US",
    "sg:address": "1400 Hancock St",
    "sg:city": "Quincy",
    "sg:classifiers": [
      {
        "category": "Organizations",
        "subcategory": "Professional Association",
        "type": "Services"
      }
    ],
    "sg:phone": "+1 617 479 0220",
    "sg:postcode": "02169",
    "sg:province": "MA",
    "sg:website": "www.btea.net",
    "wof:name": "Building Trade Employers Assn",
    "wof:placetype": "venue"
  },
  "geometry": {"coordinates":[-71.002459,42.249603],"type":"Point"}
}
