{
  "type": "Feature",
  "properties": {
    "addr:full":"100 Cambridgeside Pl Cambridge MA 02141",
    "addr:housenumber":"100",
    "addr:postcode":"02141",
    "addr:street":"Cambridgeside Pl",
    "iso:country":"US",
    "sg:address":"100 Cambridgeside Pl",
    "sg:city":"Cambridge",
    "sg:classifiers":[
        {
            "category":"Shopping",
            "subcategory":"Gifts & Souvenirs",
            "type":"Retail Goods"
        },
        {
            "category":"Health Services",
            "subcategory":"Nursing And Care Facility",
            "type":"Services"
        }
    ],
    "sg:phone":"+1 617 621 6959",
    "sg:postcode":"02141",
    "sg:province":"MA",
    "sg:tags":[
        "shop",
        "equipment",
        "massage",
        "supply"
    ],
    "sg:website":"http://www.brookstone.com",
    "wof:name":"Brookstone",
    "wof:placetype":"venue"
},
  "geometry": {"coordinates":[-71.07567,42.36694],"type":"Point"}
}