{
  "type": "Feature",
  "properties": {
    "addr:full": "36 Norfolk Ave Roxbury MA 02119",
    "addr:housenumber": "36",
    "addr:postcode": "02119",
    "addr:street": "Norfolk Ave",
    "iso:country": "US",
    "sg:address": "36 Norfolk Ave",
    "sg:city": "Roxbury",
    "sg:classifiers": [
      {
        "category": "Building \u0026 Trades",
        "subcategory": "Construction",
        "type": "Services"
      }
    ],
    "sg:phone": "+1 617 427 2921",
    "sg:postcode": "02119",
    "sg:province": "MA",
    "sg:tags": [
      "painter"
    ],
    "wof:name": "Gazzola Painting Co Inc",
    "wof:placetype": "venue"
  },
  "geometry": {"coordinates":[-71.074699,42.328701],"type":"Point"}
}
