{
  "type": "Feature",
  "properties": {
    "iso:country":"US",
    "sg:address":"36 Norfolk Ave",
    "sg:city":"Roxbury",
    "sg:classifiers":[
        {
            "category":"Building & Trades",
            "subcategory":"Construction",
            "type":"Services"
        }
    ],
    "sg:phone":"+1 617 427 2921",
    "sg:postcode":"02119",
    "sg:province":"MA",
    "sg:tags":[
        "painter"
    ],
    "wof:name":"Gazzola Painting Co Inc",
    "wof:placetype":"venue"
},
  "geometry": {"coordinates":[-71.074699,42.328701],"type":"Point"}
}