{
  "type": "Feature",
  "properties": {
    "addr:full":"340 Front St Marion MA 02738",
    "addr:housenumber":"340",
    "addr:postcode":"02738",
    "addr:street":"Front St",
    "iso:country":"US",
    "sg:address":"340 Front St",
    "sg:city":"Marion",
    "sg:classifiers":[
        {
            "category":"Professional",
            "subcategory":"Computer Services",
            "type":"Services"
        }
    ],
    "sg:phone":"+1 508 748 6611",
    "sg:postcode":"02738",
    "sg:province":"MA",
    "sg:tags":[
        "website",
        "design"
    ],
    "sg:website":"www.katewood.com",
    "wof:name":"Katewood Group",
    "wof:placetype":"venue"
},
  "geometry": {"coordinates":[-70.769627,41.715117],"type":"Point"}
}