{
  "type": "Feature",
  "properties": {
    "addr:full": "627 Main St Wakefield MA 01880",
    "addr:housenumber": "627",
    "addr:postcode": "01880",
    "addr:street": "Main St",
    "iso:country": "US",
    "ovtr:label": "Animal Kingdom, 627 Main St Wakefield MA US",
    "ovtr:similarity": 1.968561053276062,
    "sg:address": "627 Main St",
    "sg:city": "Wakefield",
    "sg:classifiers": [
      {
        "category": "Retail",
        "subcategory": "Veterinary Services",
        "type": "Services"
      }
    ],
    "sg:phone": "+1 781 246 3313",
    "sg:postcode": "01880",
    "sg:province": "MA",
    "wof:name": "Animal Kingdom",
    "wof:placetype": "venue"
  },
  "geometry": {"coordinates":[-71.069312,42.496477],"type":"Point"}
}
