{
  "type": "Feature",
  "properties": {
    "iso:country":"US",
    "sg:address":"44 Front St",
    "sg:city":"Worcester",
    "sg:classifiers":[
        {
            "category":"Professional",
            "subcategory":"Management & Consulting",
            "type":"Services"
        }
    ],
    "sg:phone":"+1 508 459 7500",
    "sg:postcode":"01608",
    "sg:province":"MA",
    "sg:tags":[
        "consultant",
        "business"
    ],
    "wof:name":"APG Management",
    "wof:placetype":"venue"
},
  "geometry": {"coordinates":[-71.80168399999999,42.263288],"type":"Point"}
}