{
  "type": "Feature",
  "properties": {
    "iso:country":"US",
    "sg:address":"110 Washington St",
    "sg:city":"Cambridge",
    "sg:classifiers":[
        {
            "category":"Professional",
            "type":"Services"
        }
    ],
    "sg:phone":"+1 617 737 2442",
    "sg:postcode":"02139",
    "sg:province":"MA",
    "sg:tags":[
        "establishment"
    ],
    "wof:name":"Continental Village Water Dist",
    "wof:placetype":"venue"
},
  "geometry": {"coordinates":[-71.09712,42.365048],"type":"Point"}
}