{
  "type": "Feature",
  "properties": {
    "iso:country":"US",
    "sg:address":"45 Felton St",
    "sg:city":"Waltham",
    "sg:classifiers":[
        {
            "category":"Retail",
            "subcategory":"Auto Repair",
            "type":"Services"
        }
    ],
    "sg:phone":"+1 781 893 9217",
    "sg:postcode":"02453",
    "sg:province":"MA",
    "sg:tags":[
        "body",
        "automobile",
        "painting"
    ],
    "wof:name":"Luchey's Auto Body",
    "wof:placetype":"venue"
},
  "geometry": {"coordinates":[-71.238271,42.374321],"type":"Point"}
}