{
  "type": "Feature",
  "properties": {
    "iso:country":"US",
    "sg:address":"46 Middle St",
    "sg:city":"Braintree",
    "sg:classifiers":[
        {
            "category":"Building & Trades",
            "subcategory":"Construction",
            "type":"Services"
        }
    ],
    "sg:phone":"+1 781 848 9877",
    "sg:postcode":"02184",
    "sg:province":"MA",
    "sg:tags":[
        "general",
        "contractor"
    ],
    "wof:name":"T C Healy Equipment Corp",
    "wof:placetype":"venue"
},
  "geometry": {"coordinates":[-70.995778,42.222587],"type":"Point"}
}