{
  "type": "Feature",
  "properties": {
    "addr:full":"467 Union Ave Framingham MA 01702",
    "addr:housenumber":"467",
    "addr:postcode":"01702",
    "addr:street":"Union Ave",
    "iso:country":"US",
    "sg:address":"467 Union Ave",
    "sg:city":"Framingham",
    "sg:classifiers":[
        {
            "category":"Professional",
            "subcategory":"Printing & Photocopies",
            "type":"Services"
        }
    ],
    "sg:phone":"+1 508 879 2499",
    "sg:postcode":"01702",
    "sg:province":"MA",
    "sg:tags":[
        "duplicating",
        "copying"
    ],
    "wof:name":"Briston Copy & Printing Inc",
    "wof:placetype":"venue"
},
  "geometry": {"coordinates":[-71.42684300000001,42.292035],"type":"Point"}
}