{
  "type": "Feature",
  "properties": {
    "addr:full": "44 Sacramento St Cambridge MA 02138",
    "addr:housenumber": "44",
    "addr:postcode": "02138",
    "addr:street": "Sacramento St",
    "iso:country": "US",
    "sg:address": "44 Sacramento St",
    "sg:city": "Cambridge",
    "sg:classifiers": [
      {
        "category": "Communications",
        "subcategory": "Film \u0026 Video Production",
        "type": "Services"
      }
    ],
    "sg:phone": "+1 617 876 9430",
    "sg:postcode": "02138",
    "sg:province": "MA",
    "sg:tags": [
      "motion",
      "taping"
    ],
    "wof:name": "Seven Generations Video",
    "wof:placetype": "venue"
  },
  "geometry": {"coordinates":[-71.114453,42.382471],"type":"Point"}
}
