{
  "type": "Feature",
  "properties": {
    "addr:full": "800 Pleasant St Rochdale MA 01542",
    "addr:housenumber": "800",
    "addr:postcode": "01542",
    "addr:street": "Pleasant St",
    "iso:country": "US",
    "sg:address": "800 Pleasant St",
    "sg:city": "Rochdale",
    "sg:classifiers": [
      {
        "category": "Farming",
        "subcategory": "Farm",
        "type": "Manufacturing \u0026 Wholesale Goods"
      }
    ],
    "sg:phone": "+1 508 892 8884",
    "sg:postcode": "01542",
    "sg:province": "MA",
    "wof:name": "Mary C Owen",
    "wof:placetype": "venue"
  },
  "geometry": {"coordinates":[-71.9125,42.198067],"type":"Point"}
}
