{
  "type": "Feature",
  "properties": {
    "addr:full": "1109 Montello St Brockton MA 02301",
    "addr:housenumber": "1109",
    "addr:postcode": "02301",
    "addr:street": "Montello St",
    "iso:country": "US",
    "sg:address": "1109 Montello St",
    "sg:city": "Brockton",
    "sg:classifiers": [
      {
        "category": "Freight",
        "type": "Transportation"
      }
    ],
    "sg:phone": "+1 508 586 9426",
    "sg:postcode": "02301",
    "sg:province": "MA",
    "sg:tags": [
      "mover"
    ],
    "wof:name": "Triple M Movers \u0026 Storage",
    "wof:placetype": "venue"
  },
  "geometry": {"coordinates":[-71.013924,42.06341],"type":"Point"}
}
