{
  "type": "Feature",
  "properties": {
    "addr:full": "254 W Newton St Boston MA 02108",
    "addr:housenumber": "254",
    "addr:postcode": "02108",
    "addr:street": "W Newton St",
    "iso:country": "US",
    "sg:address": "254 W Newton St",
    "sg:city": "Boston",
    "sg:classifiers": [
      {
        "category": "Professional",
        "type": "Services"
      }
    ],
    "sg:phone": "+1 617 267 8000",
    "sg:postcode": "02108",
    "sg:province": "MA",
    "sg:tags": [
      "management",
      "property"
    ],
    "sg:website": "www.clarendoncompanies.com",
    "wof:name": "Clarendon Companies",
    "wof:placetype": "venue"
  },
  "geometry": {"coordinates":[-71.08096,42.344823],"type":"Point"}
}
