{
  "type": "Feature",
  "properties": {
    "iso:country":"US",
    "sg:address":"29 Butternut Cir",
    "sg:city":"Cotuit",
    "sg:classifiers":[
        {
            "category":"Personal",
            "subcategory":"Barber",
            "type":"Services"
        }
    ],
    "sg:phone":"+1 508 428 7498",
    "sg:postcode":"02635",
    "sg:province":"MA",
    "wof:name":"Star Barber Shop",
    "wof:placetype":"venue"
},
  "geometry": {"coordinates":[-70.434226,41.646558],"type":"Point"}
}