{
  "type": "Feature",
  "properties": {
    "addr:full": "25 Birch St Ste C302 Milford MA 01757",
    "addr:housenumber": "25",
    "addr:postcode": "01757",
    "addr:street": "Birch St Ste C302",
    "iso:country": "US",
    "sg:address": "25 Birch St Ste C302",
    "sg:city": "Milford",
    "sg:classifiers": [
      {
        "category": "Professional",
        "subcategory": "Accounting \u0026 Tax Preparation",
        "type": "Services"
      }
    ],
    "sg:phone": "+1 508 377 9888",
    "sg:postcode": "01757",
    "sg:province": "MA",
    "sg:tags": [
      "payroll"
    ],
    "sg:website": "http://www.compupay.com",
    "wof:name": "CompuPay",
    "wof:placetype": "venue"
  },
  "geometry": {"coordinates":[-71.491594,42.14342],"type":"Point"}
}
