{
  "type": "Feature",
  "properties": {
    "iso:country":"US",
    "sg:address":"25 Birch St Ste C302",
    "sg:city":"Milford",
    "sg:classifiers":[
        {
            "category":"Professional",
            "subcategory":"Accounting & Tax Preparation",
            "type":"Services"
        }
    ],
    "sg:phone":"+1 508 377 9888",
    "sg:postcode":"01757",
    "sg:province":"MA",
    "sg:tags":[
        "payroll"
    ],
    "sg:website":"http://www.compupay.com",
    "wof:name":"CompuPay",
    "wof:placetype":"venue"
},
  "geometry": {"coordinates":[-71.49159400000001,42.14342],"type":"Point"}
}