{
  "type": "Feature",
  "properties": {
    "addr:full": "49 Dalton Ave Pittsfield MA 01201",
    "addr:housenumber": "49",
    "addr:postcode": "01201",
    "addr:street": "Dalton Ave",
    "iso:country": "US",
    "sg:address": "49 Dalton Ave",
    "sg:city": "Pittsfield",
    "sg:classifiers": [
      {
        "category": "Retail",
        "subcategory": "Self-service Laundry",
        "type": "Services"
      }
    ],
    "sg:phone": "+1 413 442 8003",
    "sg:postcode": "01201",
    "sg:province": "MA",
    "wof:name": "Sudds Mill E-Z Wash",
    "wof:placetype": "venue"
  },
  "geometry": {"coordinates":[-73.230765,42.457202],"type":"Point"}
}
