{
  "type": "Feature",
  "properties": {
    "iso:country":"US",
    "sg:address":"835 Memorial Ave",
    "sg:city":"West Springfield",
    "sg:classifiers":[
        {
            "category":"Home & Garden",
            "subcategory":"Building Materials",
            "type":"Retail Goods"
        }
    ],
    "sg:phone":"+1 413 731 0195",
    "sg:postcode":"01089",
    "sg:province":"MA",
    "sg:tags":[
        "paint"
    ],
    "wof:name":"Sherwin-Williams Paints",
    "wof:placetype":"venue"
},
  "geometry": {"coordinates":[-72.61221399999999,42.095107],"type":"Point"}
}