{
  "type": "Feature",
  "properties": {
    "addr:full": "137 Teaticket Hwy Teaticket MA 02536",
    "addr:housenumber": "137",
    "addr:postcode": "02536",
    "addr:street": "Teaticket Hwy",
    "iso:country": "US",
    "sg:address": "137 Teaticket Hwy",
    "sg:city": "Teaticket",
    "sg:classifiers": [
      {
        "category": "Shopping",
        "subcategory": "Jewelry",
        "type": "Retail Goods"
      }
    ],
    "sg:phone": "+1 508 548 9107",
    "sg:postcode": "02536",
    "sg:province": "MA",
    "sg:tags": [
      "jeweler"
    ],
    "wof:name": "Hannoush Jewelers",
    "wof:placetype": "venue"
  },
  "geometry": {"coordinates":[-70.5961,41.564189],"type":"Point"}
}
