{
  "type": "Feature",
  "properties": {
    "iso:country":"US",
    "sg:address":"10 Marjorie St",
    "sg:city":"Attleboro",
    "sg:classifiers":[
        {
            "category":"Building & Trades",
            "subcategory":"Construction",
            "type":"Services"
        }
    ],
    "sg:phone":"+1 508 369 4039",
    "sg:postcode":"02703",
    "sg:province":"MA",
    "sg:tags":[
        "painting",
        "painter",
        "contractor"
    ],
    "wof:name":"A H Painting",
    "wof:placetype":"venue"
},
  "geometry": {"coordinates":[-71.285447,41.932502],"type":"Point"}
}