{
  "type": "Feature",
  "properties": {
    "iso:country":"US",
    "sg:address":"518 Main St",
    "sg:city":"Holyoke",
    "sg:classifiers":[
        {
            "category":"Home & Garden",
            "subcategory":"Carpets & Floor Coverings",
            "type":"Retail Goods"
        }
    ],
    "sg:phone":"+1 413 536 2400",
    "sg:postcode":"01040",
    "sg:province":"MA",
    "sg:tags":[
        "dealer",
        "rug"
    ],
    "wof:name":"Holyoke Millwork",
    "wof:placetype":"venue"
},
  "geometry": {"coordinates":[-72.60960799999999,42.197618],"type":"Point"}
}