{
  "type": "Feature",
  "properties": {
    "addr:full": "518 Main St Holyoke MA 01040",
    "addr:housenumber": "518",
    "addr:postcode": "01040",
    "addr:street": "Main St",
    "iso:country": "US",
    "ovtr:label": "Holyoke Millwork, 518 Main St Holyoke MA US",
    "ovtr:similarity": 2.8138720989227295,
    "sg:address": "518 Main St",
    "sg:city": "Holyoke",
    "sg:classifiers": [
      {
        "category": "Home \u0026 Garden",
        "subcategory": "Carpets \u0026 Floor Coverings",
        "type": "Retail Goods"
      }
    ],
    "sg:phone": "+1 413 536 2400",
    "sg:postcode": "01040",
    "sg:province": "MA",
    "sg:tags": [
      "dealer",
      "rug"
    ],
    "wof:name": "Holyoke Millwork",
    "wof:placetype": "venue"
  },
  "geometry": {"coordinates":[-72.609608,42.197618],"type":"Point"}
}
