{
  "type": "Feature",
  "properties": {
    "addr:full": "143 Longwood Ave Apt 1 Brookline MA 02446",
    "addr:housenumber": "143;1",
    "addr:postcode": "02446",
    "addr:street": "Longwood Ave Apt",
    "iso:country": "US",
    "sg:address": "143 Longwood Ave Apt 1",
    "sg:city": "Brookline",
    "sg:classifiers": [
      {
        "category": "Travel",
        "subcategory": "Hotels \u0026 Motels",
        "type": "Entertainment"
      },
      {
        "category": "Personal",
        "type": "Services"
      }
    ],
    "sg:phone": "+1 805 459 7796",
    "sg:postcode": "02446",
    "sg:province": "MA",
    "sg:tags": [
      "assistant",
      "concierge"
    ],
    "wof:name": "Kathryn Ganpman",
    "wof:placetype": "venue"
  },
  "geometry": {"coordinates":[-71.113909,42.340573],"type":"Point"}
}
