{
  "type": "Feature",
  "properties": {
    "iso:country":"US",
    "sg:address":"143 Longwood Ave Apt 1",
    "sg:city":"Brookline",
    "sg:classifiers":[
        {
            "category":"Travel",
            "subcategory":"Hotels & Motels",
            "type":"Entertainment"
        },
        {
            "category":"Personal",
            "type":"Services"
        }
    ],
    "sg:phone":"+1 805 459 7796",
    "sg:postcode":"02446",
    "sg:province":"MA",
    "sg:tags":[
        "assistant",
        "concierge"
    ],
    "wof:name":"Kathryn Ganpman",
    "wof:placetype":"venue"
},
  "geometry": {"coordinates":[-71.11390900000001,42.340573],"type":"Point"}
}