{
  "type": "Feature",
  "properties": {
    "addr:full": "15 Canal Rd Orleans MA 02653",
    "addr:housenumber": "15",
    "addr:postcode": "02653",
    "addr:street": "Canal Rd",
    "iso:country": "US",
    "ovtr:label": "Wendy's, 15 Canal Rd Orleans MA US",
    "ovtr:similarity": 2.874385118484497,
    "sg:address": "15 Canal Rd",
    "sg:city": "Orleans",
    "sg:classifiers": [
      {
        "category": "Restaurant",
        "type": "Food \u0026 Drink"
      }
    ],
    "sg:menulink": "http://www.allmenus.com/ma/orleans/173325-wendys/menu/",
    "sg:phone": "+1 508 255 4523",
    "sg:postcode": "02653",
    "sg:province": "MA",
    "sg:tags": [
      "burger",
      "american",
      "soup"
    ],
    "wof:name": "Wendy's",
    "wof:placetype": "venue"
  },
  "geometry": {"coordinates":[-69.984941,41.796998],"type":"Point"}
}
