{
  "type": "Feature",
  "properties": {
    "addr:full":"15 Canal Rd Orleans MA 02653",
    "addr:housenumber":"15",
    "addr:postcode":"02653",
    "addr:street":"Canal Rd",
    "iso:country":"US",
    "sg:address":"15 Canal Rd",
    "sg:city":"Orleans",
    "sg:classifiers":[
        {
            "category":"Restaurant",
            "type":"Food & Drink"
        }
    ],
    "sg:menulink":"http://www.allmenus.com/ma/orleans/173325-wendys/menu/",
    "sg:phone":"+1 508 255 4523",
    "sg:postcode":"02653",
    "sg:province":"MA",
    "sg:tags":[
        "burger",
        "american",
        "soup"
    ],
    "wof:name":"Wendy's",
    "wof:placetype":"venue"
},
  "geometry": {"coordinates":[-69.98494100000001,41.796998],"type":"Point"}
}