{
  "type": "Feature",
  "properties": {
    "addr:full": "649 Massachusetts Ave Cambridge MA 02139",
    "addr:housenumber": "649",
    "addr:postcode": "02139",
    "addr:street": "Massachusetts Ave",
    "iso:country": "US",
    "sg:address": "649 Massachusetts Ave",
    "sg:city": "Cambridge",
    "sg:classifiers": [
      {
        "category": "Professional",
        "subcategory": "Lawyer \u0026 Legal Services",
        "type": "Services"
      }
    ],
    "sg:phone": "+1 617 354 1711",
    "sg:postcode": "02139",
    "sg:province": "MA",
    "wof:name": "MacDonald Bruce T Atty",
    "wof:placetype": "venue"
  },
  "geometry": {"coordinates":[-71.104053,42.365624],"type":"Point"}
}
