{
  "type": "Feature",
  "properties": {
    "iso:country":"US",
    "sg:address":"649 Massachusetts Ave",
    "sg:city":"Cambridge",
    "sg:classifiers":[
        {
            "category":"Professional",
            "subcategory":"Lawyer & Legal Services",
            "type":"Services"
        }
    ],
    "sg:phone":"+1 617 354 1711",
    "sg:postcode":"02139",
    "sg:province":"MA",
    "wof:name":"MacDonald Bruce T Atty",
    "wof:placetype":"venue"
},
  "geometry": {"coordinates":[-71.10405299999999,42.365624],"type":"Point"}
}