{
  "type": "Feature",
  "properties": {
    "addr:full": "282 Providence Hwy Westwood MA 02090",
    "addr:housenumber": "282",
    "addr:postcode": "02090",
    "addr:street": "Providence Hwy",
    "iso:country": "US",
    "sg:address": "282 Providence Hwy",
    "sg:city": "Westwood",
    "sg:classifiers": [
      {
        "category": "Shopping",
        "subcategory": "Jewelry",
        "type": "Retail Goods"
      },
      {
        "category": "Manufacturing",
        "subcategory": "Jewelry",
        "type": "Manufacturing \u0026 Wholesale Goods"
      }
    ],
    "sg:phone": "+1 781 329 1111",
    "sg:postcode": "02090",
    "sg:province": "MA",
    "sg:tags": [
      "diamond",
      "watch",
      "designer",
      "jeweler"
    ],
    "sg:website": "http://www.dolabanyjewelers.net",
    "wof:name": "Dolabany Jewelry",
    "wof:placetype": "venue"
  },
  "geometry": {"coordinates":[-71.180435,42.219384],"type":"Point"}
}
