{
  "type": "Feature",
  "properties": {
    "addr:full": "328 Main St Southbridge MA 01550",
    "addr:housenumber": "328",
    "addr:postcode": "01550",
    "addr:street": "Main St",
    "iso:country": "US",
    "sg:address": "328 Main St",
    "sg:city": "Southbridge",
    "sg:classifiers": [
      {
        "category": "Banks \u0026 Credit Unions",
        "subcategory": "Bank",
        "type": "Services"
      }
    ],
    "sg:phone": "+1 508 764 8923",
    "sg:postcode": "01550",
    "sg:province": "MA",
    "wof:name": "Saver's Bank",
    "wof:placetype": "venue"
  },
  "geometry": {"coordinates":[-72.03477,42.075831],"type":"Point"}
}
