{
  "type": "Feature",
  "properties": {
    "addr:full": "671 High St Dedham MA 02026",
    "addr:housenumber": "671",
    "addr:postcode": "02026",
    "addr:street": "High St",
    "iso:country": "US",
    "sg:address": "671 High St",
    "sg:city": "Dedham",
    "sg:classifiers": [
      {
        "category": "Professional",
        "subcategory": "Accounting \u0026 Tax Preparation",
        "type": "Services"
      }
    ],
    "sg:phone": "+1 781 326 2699",
    "sg:postcode": "02026",
    "sg:province": "MA",
    "sg:tags": [
      "bookkeeping",
      "general"
    ],
    "wof:name": "By The Book",
    "wof:placetype": "venue"
  },
  "geometry": {"coordinates":[-71.177497,42.24937],"type":"Point"}
}
