{
  "type": "Feature",
  "properties": {
    "addr:full": "24 Chestnut St Waltham MA 02453",
    "addr:housenumber": "24",
    "addr:postcode": "02453",
    "addr:street": "Chestnut St",
    "iso:country": "US",
    "sg:address": "24 Chestnut St",
    "sg:city": "Waltham",
    "sg:classifiers": [
      {
        "category": "Real Estate",
        "subcategory": "Real Estate Agent",
        "type": "Services"
      }
    ],
    "sg:phone": "+1 781 647 9794",
    "sg:postcode": "02453",
    "sg:province": "MA",
    "wof:name": "S \u0026 P Holmes Realty",
    "wof:placetype": "venue"
  },
  "geometry": {"coordinates":[-71.241006,42.369297],"type":"Point"}
}
