{
  "type": "Feature",
  "properties": {
    "iso:country":"US",
    "sg:address":"32 Long Pond Rd",
    "sg:city":"Plymouth",
    "sg:classifiers":[
        {
            "category":"Banks & Credit Unions",
            "subcategory":"Bank",
            "type":"Services"
        }
    ],
    "sg:phone":"+1 508 747 4650",
    "sg:postcode":"02360",
    "sg:province":"MA",
    "wof:name":"Rockland Trust Co",
    "wof:placetype":"venue"
},
  "geometry": {"coordinates":[-70.657725,41.929404],"type":"Point"}
}