{
  "type": "Feature",
  "properties": {
    "addr:full":"1 Mystic St Methuen MA 01844",
    "addr:housenumber":"1",
    "addr:postcode":"01844",
    "addr:street":"Mystic St",
    "iso:country":"US",
    "sg:address":"1 Mystic St",
    "sg:city":"Methuen",
    "sg:classifiers":[
        {
            "category":"Social Services",
            "type":"Services"
        }
    ],
    "sg:phone":"+1 978 794 8668",
    "sg:postcode":"01844",
    "sg:province":"MA",
    "sg:tags":[
        "organization",
        "welfare"
    ],
    "wof:name":"Key Program Inc",
    "wof:placetype":"venue"
},
  "geometry": {"coordinates":[-71.195702,42.725442],"type":"Point"}
}