{
  "type": "Feature",
  "properties": {
    "addr:full":"43 Riverside Ave Medford MA 02155",
    "addr:housenumber":"43",
    "addr:postcode":"02155",
    "addr:street":"Riverside Ave",
    "iso:country":"US",
    "sg:address":"43 Riverside Ave",
    "sg:city":"Medford",
    "sg:classifiers":[
        {
            "category":"Professional",
            "subcategory":"Computer Services",
            "type":"Services"
        }
    ],
    "sg:phone":"+1 781 324 0055",
    "sg:postcode":"02155",
    "sg:province":"MA",
    "sg:tags":[
        "repair"
    ],
    "wof:name":"Tech Solutions",
    "wof:placetype":"venue"
},
  "geometry": {"coordinates":[-71.10763300000001,42.417571],"type":"Point"}
}