{
  "type": "Feature",
  "properties": {
    "addr:full": "1170 Main St Manomet MA 02339",
    "addr:housenumber": "1170",
    "addr:postcode": "02339",
    "addr:street": "Main St",
    "iso:country": "US",
    "sg:address": "1170 Main St",
    "sg:city": "Manomet",
    "sg:phone": "+1 508 224 2255",
    "sg:postcode": "02339",
    "sg:province": "MA",
    "sg:tags": [
      "oil"
    ],
    "wof:name": "New Colony Home Heating Oil",
    "wof:placetype": "venue"
  },
  "geometry": {"coordinates":[-70.86931,42.151141],"type":"Point"}
}
