{
  "type": "Feature",
  "properties": {
    "addr:full": "10 Orlando Ave Winthrop MA 02152",
    "addr:housenumber": "10",
    "addr:postcode": "02152",
    "addr:street": "Orlando Ave",
    "iso:country": "US",
    "sg:address": "10 Orlando Ave",
    "sg:city": "Winthrop",
    "sg:classifiers": [
      {
        "category": "Building \u0026 Trades",
        "subcategory": "Landscaping Services",
        "type": "Services"
      }
    ],
    "sg:phone": "+1 617 539 4909",
    "sg:postcode": "02152",
    "sg:province": "MA",
    "wof:name": "Madd Grass Irrigation Inc",
    "wof:placetype": "venue"
  },
  "geometry": {"coordinates":[-70.987119,42.369177],"type":"Point"}
}
