{
  "type": "Feature",
  "properties": {
    "iso:country":"US",
    "sg:address":"10 Orlando Ave",
    "sg:city":"Winthrop",
    "sg:classifiers":[
        {
            "category":"Building & Trades",
            "subcategory":"Landscaping Services",
            "type":"Services"
        }
    ],
    "sg:phone":"+1 617 539 4909",
    "sg:postcode":"02152",
    "sg:province":"MA",
    "wof:name":"Madd Grass Irrigation Inc",
    "wof:placetype":"venue"
},
  "geometry": {"coordinates":[-70.98711900000001,42.369177],"type":"Point"}
}