{
  "type": "Feature",
  "properties": {
    "addr:full": "286 Southbridge St Auburn MA 01501",
    "addr:housenumber": "286",
    "addr:postcode": "01501",
    "addr:street": "Southbridge St",
    "iso:country": "US",
    "ovtr:label": "Coffee Mug, 286 Southbridge St Auburn MA US",
    "ovtr:similarity": 2.5406620502471924,
    "sg:address": "286 Southbridge St",
    "sg:city": "Auburn",
    "sg:classifiers": [
      {
        "category": "Coffee \u0026 Tea",
        "type": "Food \u0026 Drink"
      },
      {
        "category": "Restaurant",
        "type": "Food \u0026 Drink"
      }
    ],
    "sg:phone": "+1 508 832 3616",
    "sg:postcode": "01501",
    "sg:province": "MA",
    "sg:tags": [
      "shop",
      "espresso"
    ],
    "wof:name": "Coffee Mug",
    "wof:placetype": "venue"
  },
  "geometry": {"coordinates":[-71.829302,42.210601],"type":"Point"}
}
