{
  "type": "Feature",
  "properties": {
    "iso:country":"US",
    "sg:address":"286 Southbridge St",
    "sg:city":"Auburn",
    "sg:classifiers":[
        {
            "category":"Coffee & Tea",
            "type":"Food & Drink"
        },
        {
            "category":"Restaurant",
            "type":"Food & Drink"
        }
    ],
    "sg:phone":"+1 508 832 3616",
    "sg:postcode":"01501",
    "sg:province":"MA",
    "sg:tags":[
        "shop",
        "espresso"
    ],
    "wof:name":"Coffee Mug",
    "wof:placetype":"venue"
},
  "geometry": {"coordinates":[-71.829302,42.210601],"type":"Point"}
}