{
  "type": "Feature",
  "properties": {
    "iso:country":"US",
    "sg:address":"222 Arsenal St",
    "sg:city":"Watertown",
    "sg:classifiers":[
        {
            "category":"Restaurant",
            "type":"Food & Drink"
        }
    ],
    "sg:phone":"+1 617 923 7676",
    "sg:postcode":"02472",
    "sg:province":"MA",
    "wof:name":"Low Fat Know Fat",
    "wof:placetype":"venue"
},
  "geometry": {"coordinates":[-71.174008,42.364551],"type":"Point"}
}