{
  "type": "Feature",
  "properties": {
    "iso:country":"US",
    "sg:address":"108 Moulton St",
    "sg:city":"Springfield",
    "sg:classifiers":[
        {
            "category":"Manufacturing",
            "subcategory":"Printing",
            "type":"Manufacturing & Wholesale Goods"
        }
    ],
    "sg:phone":"+1 413 796 7600",
    "sg:postcode":"01118",
    "sg:province":"MA",
    "sg:tags":[
        "publisher",
        "software"
    ],
    "wof:name":"Phoenix Computer Systems",
    "wof:placetype":"venue"
},
  "geometry": {"coordinates":[-72.533855,42.082282],"type":"Point"}
}