{
  "type": "Feature",
  "properties": {
    "addr:full": "334 Main St Hyannis MA 02601",
    "addr:housenumber": "334",
    "addr:postcode": "02601",
    "addr:street": "Main St",
    "iso:country": "US",
    "sg:address": "334 Main St",
    "sg:city": "Hyannis",
    "sg:classifiers": [
      {
        "category": "Bars \u0026 Pubs",
        "type": "Food \u0026 Drink"
      },
      {
        "category": "Restaurant",
        "type": "Food \u0026 Drink"
      }
    ],
    "sg:phone": "+1 508 862 9430",
    "sg:postcode": "02601",
    "sg:province": "MA",
    "sg:tags": [
      "irish"
    ],
    "sg:website": "tommydoyles.com",
    "wof:name": "Tommy Doyle's Irish Pub \u0026 Restaurant",
    "wof:placetype": "venue"
  },
  "geometry": {"coordinates":[-70.28169,41.653789],"type":"Point"}
}
