{
  "type": "Feature",
  "properties": {
    "iso:country":"US",
    "sg:address":"334 Main St",
    "sg:city":"Hyannis",
    "sg:classifiers":[
        {
            "category":"Bars & Pubs",
            "type":"Food & Drink"
        },
        {
            "category":"Restaurant",
            "type":"Food & Drink"
        }
    ],
    "sg:phone":"+1 508 862 9430",
    "sg:postcode":"02601",
    "sg:province":"MA",
    "sg:tags":[
        "irish"
    ],
    "sg:website":"tommydoyles.com",
    "wof:name":"Tommy Doyle's Irish Pub & Restaurant",
    "wof:placetype":"venue"
},
  "geometry": {"coordinates":[-70.28169,41.653789],"type":"Point"}
}