{
  "type": "Feature",
  "properties": {
    "iso:country":"US",
    "sg:address":"466 Main St",
    "sg:city":"Chatham",
    "sg:classifiers":[
        {
            "category":"Shopping",
            "subcategory":"Gifts & Souvenirs",
            "type":"Retail Goods"
        }
    ],
    "sg:phone":"+1 508 945 3593",
    "sg:postcode":"02633",
    "sg:province":"MA",
    "sg:tags":[
        "jewelry"
    ],
    "wof:name":"Dolli Llama",
    "wof:placetype":"venue"
},
  "geometry": {"coordinates":[-69.956176,41.679482],"type":"Point"}
}