{
  "type": "Feature",
  "properties": {
    "addr:full":"300 Main St Northborough MA 01532",
    "addr:housenumber":"300",
    "addr:postcode":"01532",
    "addr:street":"Main St",
    "iso:country":"US",
    "sg:address":"300 Main St",
    "sg:city":"Northborough",
    "sg:classifiers":[
        {
            "category":"Health Services",
            "subcategory":"Health Practitioner",
            "type":"Services"
        }
    ],
    "sg:phone":"+1 508 393 1821",
    "sg:postcode":"01532",
    "sg:province":"MA",
    "sg:tags":[
        "psychologist"
    ],
    "wof:name":"Strategy Works",
    "wof:placetype":"venue"
},
  "geometry": {"coordinates":[-71.621549,42.327743],"type":"Point"}
}