{
  "type": "Feature",
  "properties": {
    "iso:country":"US",
    "sg:address":"39 W Main St",
    "sg:city":"Northborough",
    "sg:classifiers":[
        {
            "category":"Personal",
            "subcategory":"Beauty Salon",
            "type":"Services"
        }
    ],
    "sg:phone":"+1 508 351 9966",
    "sg:postcode":"01532",
    "sg:province":"MA",
    "wof:name":"Hair Divine",
    "wof:placetype":"venue"
},
  "geometry": {"coordinates":[-71.64412,42.31983],"type":"Point"}
}