{
  "type": "Feature",
  "properties": {
    "iso:country":"US",
    "sg:address":"44 Sewall St",
    "sg:city":"Ludlow",
    "sg:classifiers":[
        {
            "category":"Professional",
            "subcategory":"Business Services",
            "type":"Services"
        }
    ],
    "sg:phone":"+1 413 547 8030",
    "sg:postcode":"01056",
    "sg:province":"MA",
    "sg:tags":[
        "equipment",
        "microfilming"
    ],
    "wof:name":"King Information Systems Inc",
    "wof:placetype":"venue"
},
  "geometry": {"coordinates":[-72.480811,42.157737],"type":"Point"}
}