{
  "type": "Feature",
  "properties": {
    "iso:country":"US",
    "sg:address":"207 Glenrose Ave",
    "sg:city":"Braintree",
    "sg:classifiers":[
        {
            "category":"Building & Trades",
            "subcategory":"Construction",
            "type":"Services"
        }
    ],
    "sg:phone":"+1   ",
    "sg:postcode":"02184",
    "sg:province":"MA",
    "sg:tags":[
        "house"
    ],
    "wof:name":"Foley Cnstruction",
    "wof:placetype":"venue"
},
  "geometry": {"coordinates":[-70.963498,42.233767],"type":"Point"}
}