{
  "type": "Feature",
  "properties": {
    "addr:full":"50 White Pl Brookline MA 02445",
    "addr:housenumber":"50",
    "addr:postcode":"02445",
    "addr:street":"White Pl",
    "iso:country":"US",
    "sg:address":"50 White Pl",
    "sg:city":"Brookline",
    "sg:classifiers":[
        {
            "category":"Shopping",
            "subcategory":"Catalog Store",
            "type":"Retail Goods"
        }
    ],
    "sg:phone":"+1   ",
    "sg:postcode":"02445",
    "sg:province":"MA",
    "sg:tags":[
        "mail",
        "house"
    ],
    "wof:name":"Icons of Design",
    "wof:placetype":"venue"
},
  "geometry": {"coordinates":[-71.119455,42.331897],"type":"Point"}
}