{
  "type": "Feature",
  "properties": {
    "addr:full": "85 Mill St Brockton MA 02301",
    "addr:housenumber": "85",
    "addr:postcode": "02301",
    "addr:street": "Mill St",
    "iso:country": "US",
    "sg:address": "85 Mill St",
    "sg:city": "Brockton",
    "sg:classifiers": [
      {
        "category": "Health Services",
        "subcategory": "Health Practitioner",
        "type": "Services"
      }
    ],
    "sg:phone": "+1 508 583 4884",
    "sg:postcode": "02301",
    "sg:province": "MA",
    "sg:tags": [
      "therapist",
      "physical"
    ],
    "wof:name": "Mill Street Physical Therapy",
    "wof:placetype": "venue"
  },
  "geometry": {"coordinates":[-71.063822,42.058802],"type":"Point"}
}
