{
  "type": "Feature",
  "properties": {
    "addr:full":"180 Shirley Ave Revere MA 02151",
    "addr:housenumber":"180",
    "addr:postcode":"02151",
    "addr:street":"Shirley Ave",
    "iso:country":"US",
    "sg:address":"180 Shirley Ave",
    "sg:city":"Revere",
    "sg:classifiers":[
        {
            "category":"Health Services",
            "subcategory":"Podiatrist",
            "type":"Services"
        }
    ],
    "sg:phone":"+1 781 284 5954",
    "sg:postcode":"02151",
    "sg:province":"MA",
    "wof:name":"Feffery R Coen Gentle Footcare",
    "wof:placetype":"venue"
},
  "geometry": {"coordinates":[-70.994343,42.407738],"type":"Point"}
}