{
  "type": "Feature",
  "properties": {
    "addr:full": "2 Amesbury St Lawrence MA 01840",
    "addr:housenumber": "2",
    "addr:postcode": "01840",
    "addr:street": "Amesbury St",
    "iso:country": "US",
    "sg:address": "2 Amesbury St",
    "sg:city": "Lawrence",
    "sg:classifiers": [
      {
        "category": "Restaurant",
        "type": "Food \u0026 Drink"
      }
    ],
    "sg:phone": "+1 978 681 8444",
    "sg:postcode": "01840",
    "sg:province": "MA",
    "sg:tags": [
      "eating"
    ],
    "wof:name": "LA Parrilla",
    "wof:placetype": "venue"
  },
  "geometry": {"coordinates":[-71.162388,42.70659],"type":"Point"}
}
