{
  "type": "Feature",
  "properties": {
    "iso:country":"US",
    "sg:address":"2 Amesbury St",
    "sg:city":"Lawrence",
    "sg:classifiers":[
        {
            "category":"Restaurant",
            "type":"Food & Drink"
        }
    ],
    "sg:phone":"+1 978 681 8444",
    "sg:postcode":"01840",
    "sg:province":"MA",
    "sg:tags":[
        "eating"
    ],
    "wof:name":"LA Parrilla",
    "wof:placetype":"venue"
},
  "geometry": {"coordinates":[-71.16238800000001,42.70659],"type":"Point"}
}