{
  "type": "Feature",
  "properties": {
    "addr:full": "1236 Main St Springfield MA 01103",
    "addr:housenumber": "1236",
    "addr:postcode": "01103",
    "addr:street": "Main St",
    "iso:country": "US",
    "sg:address": "1236 Main St",
    "sg:city": "Springfield",
    "sg:classifiers": [
      {
        "category": "Restaurant",
        "type": "Food \u0026 Drink"
      }
    ],
    "sg:phone": "+1 413 737 1217",
    "sg:postcode": "01103",
    "sg:province": "MA",
    "sg:tags": [
      "mexican"
    ],
    "wof:name": "Sol Karib Restaurant",
    "wof:placetype": "venue"
  },
  "geometry": {"coordinates":[-72.587664,42.101254],"type":"Point"}
}
