{
  "type": "Feature",
  "properties": {
    "iso:country":"US",
    "sg:address":"22 Harris St",
    "sg:city":"Dedham",
    "sg:classifiers":[
        {
            "category":"Shopping",
            "subcategory":"Antiques",
            "type":"Retail Goods"
        },
        {
            "category":"Professional",
            "subcategory":"Business Services",
            "type":"Services"
        }
    ],
    "sg:phone":"+1 781 461 9530",
    "sg:postcode":"02026",
    "sg:province":"MA",
    "sg:tags":[
        "auction",
        "appraiser",
        "auctioneer"
    ],
    "sg:website":"http://www.groganco.com",
    "wof:name":"Grogan and Company",
    "wof:placetype":"venue"
},
  "geometry": {"coordinates":[-71.171335,42.248998],"type":"Point"}
}