{
  "type": "Feature",
  "properties": {
    "addr:full":"250 Granite St Braintree MA 02184",
    "addr:housenumber":"250",
    "addr:postcode":"02184",
    "addr:street":"Granite St",
    "iso:country":"US",
    "sg:address":"250 Granite St",
    "sg:city":"Braintree",
    "sg:classifiers":[
        {
            "category":"Health Services",
            "subcategory":"Doctor",
            "type":"Services"
        },
        {
            "category":"Personal",
            "subcategory":"Hair Removal",
            "type":"Services"
        },
        {
            "category":"Personal",
            "subcategory":"Skin Care",
            "type":"Services"
        }
    ],
    "sg:phone":"+1 617 934 6703",
    "sg:postcode":"02184",
    "sg:province":"MA",
    "sg:tags":[
        "physician",
        "reconstructive",
        "surgeons",
        "cosmetic",
        "plastic",
        "surgery",
        "surgeon"
    ],
    "sg:website":"http://boston.citysearch.com/profile/external/45207426/braintree_ma/sleek_medspa.html?publisher=yellowpages&reference_id=1&placement=ypwebsitemip",
    "wof:name":"Sleek MedSpa",
    "wof:placetype":"venue"
},
  "geometry": {"coordinates":[-71.028069,42.220501],"type":"Point"}
}