{
  "type": "Feature",
  "properties": {
    "addr:full":"80 Cliff Ave Winthrop MA 02152",
    "addr:housenumber":"80",
    "addr:postcode":"02152",
    "addr:street":"Cliff Ave",
    "iso:country":"US",
    "sg:address":"80 Cliff Ave",
    "sg:city":"Winthrop",
    "sg:classifiers":[
        {
            "category":"Professional",
            "subcategory":"Art Services",
            "type":"Services"
        }
    ],
    "sg:phone":"+1 617 846 6231",
    "sg:postcode":"02152",
    "sg:province":"MA",
    "sg:tags":[
        "picture",
        "frame"
    ],
    "wof:name":"Cambridge Art & Frame",
    "wof:placetype":"venue"
},
  "geometry": {"coordinates":[-70.97381,42.387879],"type":"Point"}
}