{
  "type": "Feature",
  "properties": {
    "iso:country":"US",
    "sg:address":"1287 Main St",
    "sg:city":"Lynnfield",
    "sg:classifiers":[
        {
            "category":"Shopping",
            "subcategory":"Bicycles & Sporting Goods",
            "type":"Retail Goods"
        },
        {
            "category":"Sports & Exercise",
            "subcategory":"Golf",
            "type":"Entertainment"
        }
    ],
    "sg:phone":"+1 781 334 3151",
    "sg:postcode":"01940",
    "sg:province":"MA",
    "sg:tags":[
        "course",
        "practice",
        "equipment",
        "range",
        "supply"
    ],
    "sg:website":"http://www.sagamoregolf.com",
    "wof:name":"Sagamore Spring Golf Club Inc",
    "wof:placetype":"venue"
},
  "geometry": {"coordinates":[-71.04060699999999,42.559262],"type":"Point"}
}