{
  "type": "Feature",
  "properties": {
    "addr:full": "1287 Main St Lynnfield MA 01940",
    "addr:housenumber": "1287",
    "addr:postcode": "01940",
    "addr:street": "Main St",
    "iso:country": "US",
    "ovtr:label": "Sagamore Spring Golf Club, 1287 Main St Lynnfield MA US",
    "ovtr:similarity": 3.341085910797119,
    "sg:address": "1287 Main St",
    "sg:city": "Lynnfield",
    "sg:classifiers": [
      {
        "category": "Shopping",
        "subcategory": "Bicycles \u0026 Sporting Goods",
        "type": "Retail Goods"
      },
      {
        "category": "Sports \u0026 Exercise",
        "subcategory": "Golf",
        "type": "Entertainment"
      }
    ],
    "sg:phone": "+1 781 334 3151",
    "sg:postcode": "01940",
    "sg:province": "MA",
    "sg:tags": [
      "course",
      "practice",
      "equipment",
      "range",
      "supply"
    ],
    "sg:website": "http://www.sagamoregolf.com",
    "wof:name": "Sagamore Spring Golf Club Inc",
    "wof:placetype": "venue"
  },
  "geometry": {"coordinates":[-71.040607,42.559262],"type":"Point"}
}
