{
  "type": "Feature",
  "properties": {
    "addr:full":"25 Chestnut St Salem MA 01970",
    "addr:housenumber":"25",
    "addr:postcode":"01970",
    "addr:street":"Chestnut St",
    "iso:country":"US",
    "sg:address":"25 Chestnut St",
    "sg:city":"Salem",
    "sg:classifiers":[
        {
            "category":"Real Estate",
            "subcategory":"Real Estate Agent",
            "type":"Services"
        }
    ],
    "sg:phone":"+1 978 745 7174",
    "sg:postcode":"01970",
    "sg:province":"MA",
    "wof:name":"Newport Commercial Moorings W2",
    "wof:placetype":"venue"
},
  "geometry": {"coordinates":[-70.901196,42.519379],"type":"Point"}
}