{
  "type": "Feature",
  "properties": {
    "iso:country":"US",
    "sg:address":"220 Sumner St",
    "sg:city":"Boston",
    "sg:classifiers":[
        {
            "category":"Government",
            "subcategory":"City Hall",
            "type":"Public Place"
        }
    ],
    "sg:phone":"+1 617 222 3200",
    "sg:postcode":"02128",
    "sg:province":"MA",
    "sg:website":"www.mbta.com/schedules_and_maps/...",
    "wof:name":"Maverick Station",
    "wof:placetype":"venue"
},
  "geometry": {"coordinates":[-71.03985,42.368944],"type":"Point"}
}