{
  "type": "Feature",
  "properties": {
    "addr:city": "Manchester",
    "addr:full": "10 Union St Manchester, Ma 01944-1553",
    "addr:house_number": "10",
    "addr:housenumber": "10",
    "addr:phone": "+1 978-526-7230",
    "addr:postcode": "01944-1553",
    "addr:road": "Union St",
    "addr:state": "MA",
    "addr:street": "Union St",
    "ilms:label": "MANCHESTER HISTORICAL SOCIETY, 10 UNION ST MANCHESTER MA 01944-1553",
    "ilms:similarity": 1.3432949781417847,
    "iso:country": "US",
    "sg:address": "10 Union St",
    "sg:city": "Manchester",
    "sg:classifiers": [
      {
        "category": "Recreation",
        "type": "Entertainment"
      }
    ],
    "sg:phone": "+1 978 526 7230",
    "sg:postcode": "01944",
    "sg:province": "MA",
    "sg:tags": [
      "historical"
    ],
    "sg:website": "www.manchesterhistorical.org",
    "wof:airports": [
      102527605
    ],
    "wof:name": "Manchester Historical Society",
    "wof:placetype": "venue"
  },
  "geometry": {"coordinates":[-70.77026,42.57524],"type":"Point"}
}
