{
  "type": "Feature",
  "properties": {
    "addr:full":"10 Union St Manchester MA 01944",
    "addr:housenumber":"10",
    "addr:postcode":"01944",
    "addr:street":"Union St",
    "iso:country":"US",
    "sg:address":"10 Union St",
    "sg:city":"Manchester",
    "sg:classifiers":[
        {
            "category":"Recreation",
            "type":"Entertainment"
        }
    ],
    "sg:phone":"+1 978 526 7230",
    "sg:postcode":"01944",
    "sg:province":"MA",
    "sg:tags":[
        "historical"
    ],
    "sg:website":"www.manchesterhistorical.org",
    "wof:name":"Manchester Historical Society",
    "wof:placetype":"venue"
},
  "geometry": {"coordinates":[-70.77131199999999,42.57532],"type":"Point"}
}