{
  "type": "Feature",
  "properties": {
    "iso:country":"US",
    "sg:address":"87 Essex St",
    "sg:city":"Swampscott",
    "sg:classifiers":[
        {
            "category":"Retail",
            "subcategory":"Repair Shop",
            "type":"Services"
        }
    ],
    "sg:phone":"+1   ",
    "sg:postcode":"01907",
    "sg:province":"MA",
    "wof:name":"North Shore Organ Service",
    "wof:placetype":"venue"
},
  "geometry": {"coordinates":[-70.92234999999999,42.475565],"type":"Point"}
}