{
  "type": "Feature",
  "properties": {
    "addr:full": "87 Essex St Swampscott MA 01907",
    "addr:housenumber": "87",
    "addr:postcode": "01907",
    "addr:street": "Essex St",
    "iso:country": "US",
    "sg:address": "87 Essex St",
    "sg:city": "Swampscott",
    "sg:classifiers": [
      {
        "category": "Retail",
        "subcategory": "Repair Shop",
        "type": "Services"
      }
    ],
    "sg:phone": "+1   ",
    "sg:postcode": "01907",
    "sg:province": "MA",
    "wof:name": "North Shore Organ Service",
    "wof:placetype": "venue"
  },
  "geometry": {"coordinates":[-70.92235,42.475565],"type":"Point"}
}
