{
  "type": "Feature",
  "properties": {
    "addr:full":"1842 Beacon Street Brookline MA 02445",
    "addr:housenumber":"1842",
    "addr:postcode":"02445",
    "addr:street":"Beacon Street",
    "iso:country":"US",
    "sg:address":"1842 Beacon Street",
    "sg:city":"Brookline",
    "sg:classifiers":[
        {
            "category":"Health Services",
            "subcategory":"Doctor",
            "type":"Services"
        }
    ],
    "sg:phone":"+1   ",
    "sg:postcode":"02445",
    "sg:province":"MA",
    "sg:tags":[
        "medical"
    ],
    "wof:name":"Hsing Wu MD",
    "wof:placetype":"venue"
},
  "geometry": {"coordinates":[-71.14519300000001,42.337301],"type":"Point"}
}