{
  "type": "Feature",
  "properties": {
    "addr:full":"736 Worcester St Southbridge MA 01550",
    "addr:housenumber":"736",
    "addr:postcode":"01550",
    "addr:street":"Worcester St",
    "iso:country":"US",
    "sg:address":"736 Worcester St",
    "sg:city":"Southbridge",
    "sg:classifiers":[
        {
            "category":"Donuts",
            "subcategory":"None",
            "type":"Food & Drink"
        }
    ],
    "sg:phone":"+1 508 764 2150",
    "sg:postcode":"01550",
    "sg:province":"MA",
    "sg:website":"www.dunkindonuts.com",
    "wof:name":"Dunkin Donuts",
    "wof:placetype":"venue"
},
  "geometry": {"coordinates":[-72.019773,42.097464],"type":"Point"}
}