{
  "type": "Feature",
  "properties": {
    "addr:full": "38 Green St Milford MA 01747",
    "addr:housenumber": "38",
    "addr:postcode": "01747",
    "addr:street": "Green St",
    "iso:country": "US",
    "sg:address": "38 Green St",
    "sg:city": "Milford",
    "sg:classifiers": [
      {
        "category": "Building \u0026 Trades",
        "subcategory": "Pest Control",
        "type": "Services"
      }
    ],
    "sg:phone": "+1 508 366 1820",
    "sg:postcode": "01747",
    "sg:province": "MA",
    "wof:name": "Westboro Pest Control",
    "wof:placetype": "venue"
  },
  "geometry": {"coordinates":[-71.525553,42.12882],"type":"Point"}
}
