{
  "type": "Feature",
  "properties": {
    "iso:country":"US",
    "sg:address":"372 Commercial St",
    "sg:city":"Provincetown",
    "sg:classifiers":[
        {
            "category":"Personal",
            "subcategory":"Beauty Salon",
            "type":"Services"
        }
    ],
    "sg:phone":"+1 508 487 5506",
    "sg:postcode":"02657",
    "sg:province":"MA",
    "sg:tags":[
        "spa",
        "day"
    ],
    "wof:name":"Blue Day Spa",
    "wof:placetype":"venue"
},
  "geometry": {"coordinates":[-70.183387,42.053884],"type":"Point"}
}