{
  "type": "Feature",
  "properties": {
    "addr:full": "660 South St Wrentham MA 02093",
    "addr:housenumber": "660",
    "addr:postcode": "02093",
    "addr:street": "South St",
    "iso:country": "US",
    "ovtr:label": "Wampum Corner Wines and Liquors, 660 South St Wrentham MA US",
    "ovtr:similarity": 2.4923670291900635,
    "sg:address": "660 South St",
    "sg:city": "Wrentham",
    "sg:classifiers": [
      {
        "category": "Food \u0026 Beverages",
        "subcategory": "Liquor \u0026 Beverages",
        "type": "Retail Goods"
      }
    ],
    "sg:phone": "+1 508 384 8412",
    "sg:postcode": "02093",
    "sg:province": "MA",
    "sg:tags": [
      "wine"
    ],
    "wof:name": "Wampum Corner Wine \u0026 Liquors",
    "wof:placetype": "venue"
  },
  "geometry": {"coordinates":[-71.34591,42.0507],"type":"Point"}
}
