{
  "type": "Feature",
  "properties": {
    "iso:country":"US",
    "sg:address":"660 South St",
    "sg:city":"Wrentham",
    "sg:classifiers":[
        {
            "category":"Food & Beverages",
            "subcategory":"Liquor & Beverages",
            "type":"Retail Goods"
        }
    ],
    "sg:phone":"+1 508 384 8412",
    "sg:postcode":"02093",
    "sg:province":"MA",
    "sg:tags":[
        "wine"
    ],
    "wof:name":"Wampum Corner Wine & Liquors",
    "wof:placetype":"venue"
},
  "geometry": {"coordinates":[-71.34591,42.0507],"type":"Point"}
}