{
  "type": "Feature",
  "properties": {
    "addr:full": "165 Bow St Everett MA 02149",
    "addr:housenumber": "165",
    "addr:postcode": "02149",
    "addr:street": "Bow St",
    "iso:country": "US",
    "sg:address": "165 Bow St",
    "sg:city": "Everett",
    "sg:classifiers": [
      {
        "category": "Home \u0026 Garden",
        "subcategory": "Building Materials",
        "type": "Retail Goods"
      }
    ],
    "sg:phone": "+1 617 387 8713",
    "sg:postcode": "02149",
    "sg:province": "MA",
    "sg:tags": [
      "windows-repair",
      "window",
      "installation",
      "replacement"
    ],
    "wof:name": "Greene Installation Co",
    "wof:placetype": "venue"
  },
  "geometry": {"coordinates":[-71.061737,42.398949],"type":"Point"}
}
