{
  "type": "Feature",
  "properties": {
    "iso:country":"US",
    "sg:address":"165 Bow St",
    "sg:city":"Everett",
    "sg:classifiers":[
        {
            "category":"Home & Garden",
            "subcategory":"Building Materials",
            "type":"Retail Goods"
        }
    ],
    "sg:phone":"+1 617 387 8713",
    "sg:postcode":"02149",
    "sg:province":"MA",
    "sg:tags":[
        "windows-repair",
        "window",
        "installation",
        "replacement"
    ],
    "wof:name":"Greene Installation Co",
    "wof:placetype":"venue"
},
  "geometry": {"coordinates":[-71.06173699999999,42.398949],"type":"Point"}
}