{
  "type": "Feature",
  "properties": {
    "addr:full": "323 Main St North Reading MA 01864",
    "addr:housenumber": "323",
    "addr:postcode": "01864",
    "addr:street": "Main St",
    "iso:country": "US",
    "ovtr:label": "Mass 1 Auto Body, 323 Main St North Reading MA US",
    "ovtr:similarity": 1.9937859773635864,
    "sg:address": "323 Main St",
    "sg:city": "North Reading",
    "sg:classifiers": [
      {
        "category": "Retail",
        "subcategory": "Auto Repair",
        "type": "Services"
      }
    ],
    "sg:phone": "+1 978 664 0040",
    "sg:postcode": "01864",
    "sg:province": "MA",
    "sg:tags": [
      "body",
      "automobile",
      "painting"
    ],
    "wof:name": "Mass 1 Auto Body",
    "wof:placetype": "venue"
  },
  "geometry": {"coordinates":[-71.120252,42.597007],"type":"Point"}
}
