{
  "type": "Feature",
  "properties": {
    "iso:country":"US",
    "sg:address":"323 Main St",
    "sg:city":"North Reading",
    "sg:classifiers":[
        {
            "category":"Retail",
            "subcategory":"Auto Repair",
            "type":"Services"
        }
    ],
    "sg:phone":"+1 978 664 0040",
    "sg:postcode":"01864",
    "sg:province":"MA",
    "sg:tags":[
        "body",
        "automobile",
        "painting"
    ],
    "wof:name":"Mass 1 Auto Body",
    "wof:placetype":"venue"
},
  "geometry": {"coordinates":[-71.12025199999999,42.597007],"type":"Point"}
}