{
  "type": "Feature",
  "properties": {
    "addr:full":"23 Temple St Whitman MA 02382",
    "addr:housenumber":"23",
    "addr:postcode":"02382",
    "addr:street":"Temple St",
    "iso:country":"US",
    "sg:address":"23 Temple St",
    "sg:city":"Whitman",
    "sg:classifiers":[
        {
            "category":"Personal",
            "subcategory":"Beauty Salon",
            "type":"Services"
        }
    ],
    "sg:phone":"+1 781 447 6418",
    "sg:postcode":"02382",
    "sg:province":"MA",
    "sg:tags":[
        "hair",
        "stylist"
    ],
    "wof:name":"Eugene's Hair Design",
    "wof:placetype":"venue"
},
  "geometry": {"coordinates":[-70.93792000000001,42.080341],"type":"Point"}
}