{
  "type": "Feature",
  "properties": {
    "iso:country":"US",
    "sg:address":"44 Diauto Dr",
    "sg:city":"Randolph",
    "sg:classifiers":[
        {
            "category":"Taxi",
            "type":"Transportation"
        }
    ],
    "sg:phone":"+1 781 963 2200",
    "sg:postcode":"02368",
    "sg:province":"MA",
    "sg:tags":[
        "taxicab"
    ],
    "wof:name":"South Shore Cab & Courier Inc",
    "wof:placetype":"venue"
},
  "geometry": {"coordinates":[-71.04545,42.164196],"type":"Point"}
}