{
  "type": "Feature",
  "properties": {
    "addr:full": "891 Hyde Park Ave Hyde Park MA 02136",
    "addr:housenumber": "891",
    "addr:postcode": "02136",
    "addr:street": "Hyde Park Ave",
    "iso:country": "US",
    "sg:address": "891 Hyde Park Ave",
    "sg:city": "Hyde Park",
    "sg:classifiers": [
      {
        "category": "Health Services",
        "subcategory": "Chiropractor",
        "type": "Services"
      }
    ],
    "sg:phone": "+1 617 364 5656",
    "sg:postcode": "02136",
    "sg:province": "MA",
    "wof:name": "Hyde Park Chiropractic",
    "wof:placetype": "venue"
  },
  "geometry": {"coordinates":[-71.120955,42.26884],"type":"Point"}
}
