{
  "type": "Feature",
  "properties": {
    "addr:full":"1890 Columbus Ave Roxbury MA 02119",
    "addr:housenumber":"1890",
    "addr:postcode":"02119",
    "addr:street":"Columbus Ave",
    "iso:country":"US",
    "sg:address":"1890 Columbus Ave",
    "sg:city":"Roxbury",
    "sg:classifiers":[
        {
            "category":"Professional",
            "subcategory":"Lawyer & Legal Services",
            "type":"Services"
        }
    ],
    "sg:phone":"+1 800 427 0504",
    "sg:postcode":"02119",
    "sg:province":"MA",
    "sg:tags":[
        "attorney"
    ],
    "wof:name":"John B Shorton Atty",
    "wof:placetype":"venue"
},
  "geometry": {"coordinates":[-71.09804200000001,42.317623],"type":"Point"}
}