{
  "type": "Feature",
  "properties": {
    "addr:full": "993 Hyde Park Ave Hyde Park MA 02136",
    "addr:housenumber": "993",
    "addr:postcode": "02136",
    "addr:street": "Hyde Park Ave",
    "iso:country": "US",
    "sg:address": "993 Hyde Park Ave",
    "sg:city": "Hyde Park",
    "sg:classifiers": [
      {
        "category": "Personal",
        "subcategory": "Barber",
        "type": "Services"
      }
    ],
    "sg:phone": "+1 617 364 8510",
    "sg:postcode": "02136",
    "sg:province": "MA",
    "wof:name": "Fleetwood Barbershop",
    "wof:placetype": "venue"
  },
  "geometry": {"coordinates":[-71.121257,42.265341],"type":"Point"}
}
