{
  "type": "Feature",
  "properties": {
    "iso:country":"US",
    "sg:address":"608 Page Blvd",
    "sg:city":"Springfield",
    "sg:classifiers":[
        {
            "category":"Restaurant",
            "type":"Food & Drink"
        }
    ],
    "sg:phone":"+1   ",
    "sg:postcode":"01104",
    "sg:province":"MA",
    "sg:tags":[
        "eating"
    ],
    "wof:name":"Han Inc",
    "wof:placetype":"venue"
},
  "geometry": {"coordinates":[-72.558589,42.140645],"type":"Point"}
}