{
  "type": "Feature",
  "properties": {
    "addr:full":"365 Hudson Rd Sudbury MA 01776",
    "addr:housenumber":"365",
    "addr:postcode":"01776",
    "addr:street":"Hudson Rd",
    "iso:country":"US",
    "sg:address":"365 Hudson Rd",
    "sg:city":"Sudbury",
    "sg:classifiers":[
        {
            "category":"Wholesale",
            "subcategory":"Groceries",
            "type":"Manufacturing & Wholesale Goods"
        }
    ],
    "sg:phone":"+1 978 443 4606",
    "sg:postcode":"01776",
    "sg:province":"MA",
    "sg:tags":[
        "food",
        "broker",
        "general"
    ],
    "wof:name":"Fincher Food Assoicates",
    "wof:placetype":"venue"
},
  "geometry": {"coordinates":[-71.44358,42.39174],"type":"Point"}
}