{
  "type": "Feature",
  "properties": {
    "addr:full": "225 Armory St Springfield MA 01104",
    "addr:housenumber": "225",
    "addr:postcode": "01104",
    "addr:street": "Armory St",
    "iso:country": "US",
    "sg:address": "225 Armory St",
    "sg:city": "Springfield",
    "sg:classifiers": [
      {
        "category": "Wholesale",
        "subcategory": "Electrical",
        "type": "Manufacturing \u0026 Wholesale Goods"
      }
    ],
    "sg:phone": "+1 413 739 2271",
    "sg:postcode": "01104",
    "sg:province": "MA",
    "sg:tags": [
      "alarm",
      "burglar",
      "system"
    ],
    "wof:name": "IBS Electronics \u0026 Security",
    "wof:placetype": "venue"
  },
  "geometry": {"coordinates":[-72.582236,42.116034],"type":"Point"}
}
