{
  "type": "Feature",
  "properties": {
    "iso:country":"US",
    "sg:address":"225 Armory St",
    "sg:city":"Springfield",
    "sg:classifiers":[
        {
            "category":"Wholesale",
            "subcategory":"Electrical",
            "type":"Manufacturing & Wholesale Goods"
        }
    ],
    "sg:phone":"+1 413 739 2271",
    "sg:postcode":"01104",
    "sg:province":"MA",
    "sg:tags":[
        "alarm",
        "burglar",
        "system"
    ],
    "wof:name":"IBS Electronics & Security",
    "wof:placetype":"venue"
},
  "geometry": {"coordinates":[-72.58223599999999,42.116034],"type":"Point"}
}