{
  "type": "Feature",
  "properties": {
    "iso:country":"US",
    "sg:address":"75 Middlesex Ave",
    "sg:city":"Natick",
    "sg:classifiers":[
        {
            "category":"Professional",
            "type":"Services"
        }
    ],
    "sg:phone":"+1 508 655 9171",
    "sg:postcode":"01760",
    "sg:province":"MA",
    "sg:tags":[
        "establishment"
    ],
    "sg:website":"www.schallercorp.com",
    "wof:name":"Schaller Corp",
    "wof:placetype":"venue"
},
  "geometry": {"coordinates":[-71.35162,42.28471],"type":"Point"}
}