{
  "type": "Feature",
  "properties": {
    "iso:country":"US",
    "sg:address":"444 E Falmouth Hwy",
    "sg:city":"East Falmouth",
    "sg:classifiers":[
        {
            "category":"Banks & Credit Unions",
            "subcategory":"Bank",
            "type":"Services"
        }
    ],
    "sg:phone":"+1 508 540 2241",
    "sg:postcode":"02536",
    "sg:province":"MA",
    "sg:tags":[
        "loan",
        "real estate"
    ],
    "wof:name":"Epic Mortgage Dan Co",
    "wof:placetype":"venue"
},
  "geometry": {"coordinates":[-70.557574,41.578475],"type":"Point"}
}