{
  "type": "Feature",
  "properties": {
    "addr:full": "99 Bridge St Medfield MA 02052",
    "addr:housenumber": "99",
    "addr:postcode": "02052",
    "addr:street": "Bridge St",
    "iso:country": "US",
    "sg:address": "99 Bridge St",
    "sg:city": "Medfield",
    "sg:classifiers": [
      {
        "category": "Government",
        "subcategory": "Office",
        "type": "Public Place"
      }
    ],
    "sg:phone": "+1 508 359 4533",
    "sg:postcode": "02052",
    "sg:province": "MA",
    "sg:tags": [
      "village"
    ],
    "wof:name": "Medfield Waste Water Plant",
    "wof:placetype": "venue"
  },
  "geometry": {"coordinates":[-71.327284,42.18904],"type":"Point"}
}
