{
  "type": "Feature",
  "properties": {
    "addr:full": "85 Main St Peabody MA 01960",
    "addr:housenumber": "85",
    "addr:postcode": "01960",
    "addr:street": "Main St",
    "iso:country": "US",
    "sg:address": "85 Main St",
    "sg:city": "Peabody",
    "sg:classifiers": [
      {
        "category": "Food \u0026 Beverages",
        "subcategory": "Groceries \u0026 Convenience Stores",
        "type": "Retail Goods"
      },
      {
        "category": "Food \u0026 Beverages",
        "subcategory": "Specialty",
        "type": "Retail Goods"
      }
    ],
    "sg:phone": "+1 978 977 0403",
    "sg:postcode": "01960",
    "sg:province": "MA",
    "sg:tags": [
      "market"
    ],
    "wof:name": "Michelle's Market",
    "wof:placetype": "venue"
  },
  "geometry": {"coordinates":[-70.923674,42.524329],"type":"Point"}
}
