{
  "type": "Feature",
  "properties": {
    "addr:full":"95 Main St Reading MA 01867",
    "addr:housenumber":"95",
    "addr:postcode":"01867",
    "addr:street":"Main St",
    "iso:country":"US",
    "sg:address":"95 Main St",
    "sg:city":"Reading",
    "sg:classifiers":[
        {
            "category":"Building & Trades",
            "subcategory":"Plumbing",
            "type":"Services"
        }
    ],
    "sg:phone":"+1 617 332 9989",
    "sg:postcode":"01867",
    "sg:province":"MA",
    "sg:tags":[
        "heating",
        "contractor"
    ],
    "wof:name":"Heat Maker Heating",
    "wof:placetype":"venue"
},
  "geometry": {"coordinates":[-71.103634,42.506391],"type":"Point"}
}