{
  "type": "Feature",
  "properties": {
    "iso:country":"US",
    "sg:address":"242 Mystic Avenue",
    "sg:city":"Medford",
    "sg:classifiers":[
        {
            "category":"Retail",
            "subcategory":"Auto Rental",
            "type":"Services"
        }
    ],
    "sg:phone":"+1 781 306 0610",
    "sg:postcode":"02155",
    "sg:province":"MA",
    "sg:tags":[
        "car"
    ],
    "wof:name":"Hertz Local Edition",
    "wof:placetype":"venue"
},
  "geometry": {"coordinates":[-71.102873,42.406903],"type":"Point"}
}