{
  "type": "Feature",
  "properties": {
    "addr:full":"26 Lakeview Dr Raynham MA 02767",
    "addr:housenumber":"26",
    "addr:postcode":"02767",
    "addr:street":"Lakeview Dr",
    "iso:country":"US",
    "sg:address":"26 Lakeview Dr",
    "sg:city":"Raynham",
    "sg:classifiers":[
        {
            "category":"Retail",
            "subcategory":"Portrait Studio",
            "type":"Services"
        }
    ],
    "sg:phone":"+1 508 824 1569",
    "sg:postcode":"02767",
    "sg:province":"MA",
    "sg:tags":[
        "photography"
    ],
    "wof:name":"J Mac Causland Photo",
    "wof:placetype":"venue"
},
  "geometry": {"coordinates":[-71.05847199999999,41.936431],"type":"Point"}
}