{
  "type": "Feature",
  "properties": {
    "iso:country":"US",
    "sg:address":"247 Northampton St Ste 11",
    "sg:city":"Easthampton",
    "sg:classifiers":[
        {
            "category":"Health Services",
            "subcategory":"Doctor",
            "type":"Services"
        },
        {
            "category":"Health Services",
            "subcategory":"Health Practitioner",
            "type":"Services"
        }
    ],
    "sg:phone":"+1 413 529 7188",
    "sg:postcode":"01027",
    "sg:province":"MA",
    "sg:tags":[
        "psychotherapist",
        "psychologist"
    ],
    "wof:name":"Hannah S Berenson Psychot",
    "wof:placetype":"venue"
},
  "geometry": {"coordinates":[-72.661607,42.288508],"type":"Point"}
}