{
  "type": "Feature",
  "properties": {
    "addr:full": "21 N Main St Avon MA 02322",
    "addr:housenumber": "21",
    "addr:postcode": "02322",
    "addr:street": "N Main St",
    "iso:country": "US",
    "sg:address": "21 N Main St",
    "sg:city": "Avon",
    "sg:classifiers": [
      {
        "category": "Retail",
        "subcategory": "Animal Services",
        "type": "Services"
      }
    ],
    "sg:phone": "+1   ",
    "sg:postcode": "02322",
    "sg:province": "MA",
    "sg:tags": [
      "grooming"
    ],
    "wof:name": "Cats Cats Cats",
    "wof:placetype": "venue"
  },
  "geometry": {"coordinates":[-71.039846,42.134883],"type":"Point"}
}
