{
  "type": "Feature",
  "properties": {
    "iso:country":"US",
    "sg:address":"105 State Hwy 137",
    "sg:city":"Harwich",
    "sg:classifiers":[
        {
            "category":"Home & Garden",
            "subcategory":"Furniture",
            "type":"Retail Goods"
        }
    ],
    "sg:phone":"+1 508 430 4610",
    "sg:postcode":"02645",
    "sg:province":"MA",
    "wof:name":"Rose Cottage Shop",
    "wof:placetype":"venue"
},
  "geometry": {"coordinates":[-70.020955,41.705891],"type":"Point"}
}