{
  "type": "Feature",
  "properties": {
    "iso:country":"US",
    "sg:address":"4 Edgewood Rd",
    "sg:city":"Westborough",
    "sg:classifiers":[
        {
            "category":"Restaurant",
            "type":"Food & Drink"
        }
    ],
    "sg:phone":"+1 508 898 3926",
    "sg:postcode":"01581",
    "sg:province":"MA",
    "sg:tags":[
        "pizza"
    ],
    "wof:name":"Pizza Dom & Carol",
    "wof:placetype":"venue"
},
  "geometry": {"coordinates":[-71.61944,42.243457],"type":"Point"}
}