{
  "type": "Feature",
  "properties": {
    "addr:full": "4 Edgewood Rd Westborough MA 01581",
    "addr:housenumber": "4",
    "addr:postcode": "01581",
    "addr:street": "Edgewood Rd",
    "iso:country": "US",
    "sg:address": "4 Edgewood Rd",
    "sg:city": "Westborough",
    "sg:classifiers": [
      {
        "category": "Restaurant",
        "type": "Food \u0026 Drink"
      }
    ],
    "sg:phone": "+1 508 898 3926",
    "sg:postcode": "01581",
    "sg:province": "MA",
    "sg:tags": [
      "pizza"
    ],
    "wof:name": "Pizza Dom \u0026 Carol",
    "wof:placetype": "venue"
  },
  "geometry": {"coordinates":[-71.61944,42.243457],"type":"Point"}
}
