{
  "type": "Feature",
  "properties": {
    "addr:full": "24 Ray Ave Burlington MA 01803",
    "addr:housenumber": "24",
    "addr:postcode": "01803",
    "addr:street": "Ray Ave",
    "iso:country": "US",
    "sg:address": "24 Ray Ave",
    "sg:city": "Burlington",
    "sg:classifiers": [
      {
        "category": "Wholesale",
        "subcategory": "Drugs",
        "type": "Manufacturing \u0026 Wholesale Goods"
      }
    ],
    "sg:phone": "+1 781 221 1666",
    "sg:postcode": "01803",
    "sg:province": "MA",
    "sg:tags": [
      "cosmetic"
    ],
    "wof:name": "Platinum Enterprises",
    "wof:placetype": "venue"
  },
  "geometry": {"coordinates":[-71.185333,42.482276],"type":"Point"}
}
