{
  "type": "Feature",
  "properties": {
    "addr:full": "200 N Beacon St Brighton MA 02135",
    "addr:housenumber": "200",
    "addr:postcode": "02135",
    "addr:street": "N Beacon St",
    "iso:country": "US",
    "sg:address": "200 N Beacon St",
    "sg:city": "Brighton",
    "sg:classifiers": [
      {
        "category": "Retail",
        "subcategory": "Laundry \u0026 Dry Cleaning",
        "type": "Services"
      }
    ],
    "sg:phone": "+1 617 746 9990",
    "sg:postcode": "02135",
    "sg:province": "MA",
    "sg:tags": [
      "cleaners",
      "rug",
      "carpet"
    ],
    "wof:name": "Magic Carpet Cleaning",
    "wof:placetype": "venue"
  },
  "geometry": {"coordinates":[-71.147536,42.355748],"type":"Point"}
}
