{
  "type": "Feature",
  "properties": {
    "addr:full":"24 Berry St Danvers MA 01923",
    "addr:housenumber":"24",
    "addr:postcode":"01923",
    "addr:street":"Berry St",
    "iso:country":"US",
    "sg:address":"24 Berry St",
    "sg:city":"Danvers",
    "sg:classifiers":[
        {
            "category":"Professional",
            "subcategory":"Engineering",
            "type":"Services"
        }
    ],
    "sg:phone":"+1   ",
    "sg:postcode":"01923",
    "sg:province":"MA",
    "wof:name":"R B Whalen Co",
    "wof:placetype":"venue"
},
  "geometry": {"coordinates":[-70.933221,42.565498],"type":"Point"}
}