{
  "type": "Feature",
  "properties": {
    "iso:country":"US",
    "sg:address":"13 Lanewood Ave",
    "sg:city":"Framingham",
    "sg:classifiers":[
        {
            "category":"Health Services",
            "subcategory":"Optometrist",
            "type":"Services"
        },
        {
            "category":"Shopping",
            "subcategory":"Optical Goods",
            "type":"Retail Goods"
        }
    ],
    "sg:phone":"+1 508 620 1040",
    "sg:postcode":"01701",
    "sg:province":"MA",
    "sg:tags":[
        "lens",
        "contact"
    ],
    "wof:name":"Arthur N Rosen",
    "wof:placetype":"venue"
},
  "geometry": {"coordinates":[-71.481853,42.311076],"type":"Point"}
}