{
  "type": "Feature",
  "properties": {
    "iso:country":"US",
    "sg:address":"14 Essex St",
    "sg:city":"Charlestown",
    "sg:classifiers":[
        {
            "category":"Banks & Credit Unions",
            "subcategory":"Financial Services",
            "type":"Services"
        }
    ],
    "sg:phone":"+1   ",
    "sg:postcode":"02129",
    "sg:province":"MA",
    "sg:tags":[
        "trust",
        "nonprofit",
        "management"
    ],
    "wof:name":"Charlestown Poors Fund Trust",
    "wof:placetype":"venue"
},
  "geometry": {"coordinates":[-71.06901999999999,42.378893],"type":"Point"}
}