{
  "type": "Feature",
  "properties": {
    "addr:full": "69 Russell Ln Abington MA 02351",
    "addr:housenumber": "69",
    "addr:postcode": "02351",
    "addr:street": "Russell Ln",
    "iso:country": "US",
    "sg:address": "69 Russell Ln",
    "sg:city": "Abington",
    "sg:classifiers": [
      {
        "category": "Professional",
        "subcategory": "Computer Services",
        "type": "Services"
      }
    ],
    "sg:phone": "+1 781 878 3800",
    "sg:postcode": "02351",
    "sg:province": "MA",
    "sg:tags": [
      "processing",
      "datum"
    ],
    "wof:name": "Abington Data Processing Ctr",
    "wof:placetype": "venue"
  },
  "geometry": {"coordinates":[-70.963506,42.131346],"type":"Point"}
}
