{
  "type": "Feature",
  "properties": {
    "addr:full":"260 Haverhill St Lawrence MA 01840",
    "addr:housenumber":"260",
    "addr:postcode":"01840",
    "addr:street":"Haverhill St",
    "iso:country":"US",
    "sg:address":"260 Haverhill St",
    "sg:city":"Lawrence",
    "sg:classifiers":[
        {
            "category":"Real Estate",
            "subcategory":"Real Estate Operator",
            "type":"Services"
        }
    ],
    "sg:phone":"+1 978 682 9898",
    "sg:postcode":"01840",
    "sg:province":"MA",
    "sg:tags":[
        "apartment"
    ],
    "wof:name":"Parkside Apartments West 21",
    "wof:placetype":"venue"
},
  "geometry": {"coordinates":[-71.165572,42.710014],"type":"Point"}
}