{
  "type": "Feature",
  "properties": {
    "addr:full":"15 W Bay Rd Osterville MA 02655",
    "addr:housenumber":"15",
    "addr:postcode":"02655",
    "addr:street":"W Bay Rd",
    "iso:country":"US",
    "sg:address":"15 W Bay Rd",
    "sg:city":"Osterville",
    "sg:classifiers":[
        {
            "category":"Personal",
            "subcategory":"Massage",
            "type":"Services"
        }
    ],
    "sg:phone":"+1 508 428 5436",
    "sg:postcode":"02655",
    "sg:province":"MA",
    "wof:name":"Osterville Therapeutic Massage & Healing Center",
    "wof:placetype":"venue"
},
  "geometry": {"coordinates":[-70.38310199999999,41.6278],"type":"Point"}
}