{
  "type": "Feature",
  "properties": {
    "addr:full": "159 Mill Cir Winchendon Spgs MA 01475",
    "addr:housenumber": "159",
    "addr:postcode": "01475",
    "addr:street": "Mill Cir",
    "iso:country": "US",
    "sg:address": "159 Mill Cir",
    "sg:city": "Winchendon Spgs",
    "sg:classifiers": [
      {
        "category": "Government",
        "subcategory": "Post Office",
        "type": "Public Place"
      }
    ],
    "sg:phone": "+1 978 000 1111",
    "sg:postcode": "01475",
    "sg:province": "MA",
    "wof:name": "US Post Office",
    "wof:placetype": "venue"
  },
  "geometry": {"coordinates":[-72.011843,42.695405],"type":"Point"}
}
