{
  "type": "Feature",
  "properties": {
    "iso:country":"US",
    "sg:address":"177 Adams St",
    "sg:city":"Braintree",
    "sg:phone":"+1 781 843 5749",
    "sg:postcode":"02184",
    "sg:province":"MA",
    "sg:tags":[
        "oil"
    ],
    "wof:name":"Brow Oil",
    "wof:placetype":"venue"
},
  "geometry": {"coordinates":[-70.98664599999999,42.224116],"type":"Point"}
}