{
  "type": "Feature",
  "properties": {
    "iso:country":"US",
    "sg:address":"17 Maverick Sq",
    "sg:city":"East Boston",
    "sg:classifiers":[
        {
            "category":"Organizations",
            "subcategory":"Religious Organization",
            "type":"Services"
        }
    ],
    "sg:phone":"+1 617 567 3883",
    "sg:postcode":"02128",
    "sg:province":"MA",
    "sg:tags":[
        "monastery",
        "convent"
    ],
    "wof:name":"Sisters Of Norte Dame",
    "wof:placetype":"venue"
},
  "geometry": {"coordinates":[-71.03958799999999,42.369319],"type":"Point"}
}