{
  "type": "Feature",
  "properties": {
    "iso:country":"US",
    "sg:address":"9 Middle St",
    "sg:city":"South Dartmouth",
    "sg:classifiers":[
        {
            "category":"Building & Trades",
            "subcategory":"Construction",
            "type":"Services"
        }
    ],
    "sg:phone":"+1 508 979 8984",
    "sg:postcode":"02748",
    "sg:province":"MA",
    "sg:tags":[
        "siding",
        "contractor"
    ],
    "wof:name":"Marshall Building Products Co",
    "wof:placetype":"venue"
},
  "geometry": {"coordinates":[-70.93995099999999,41.587959],"type":"Point"}
}