{
  "type": "Feature",
  "properties": {
    "addr:full": "3 Brookside Rd Somerset MA 02726",
    "addr:housenumber": "3",
    "addr:postcode": "02726",
    "addr:street": "Brookside Rd",
    "iso:country": "US",
    "sg:address": "3 Brookside Rd",
    "sg:city": "Somerset",
    "sg:classifiers": [
      {
        "category": "Shopping",
        "subcategory": "Computers \u0026 Home Electronics",
        "type": "Retail Goods"
      }
    ],
    "sg:phone": "+1   ",
    "sg:postcode": "02726",
    "sg:province": "MA",
    "sg:tags": [
      "paper"
    ],
    "wof:name": "P C R Supply",
    "wof:placetype": "venue"
  },
  "geometry": {"coordinates":[-71.148596,41.760406],"type":"Point"}
}
