{
  "type": "Feature",
  "properties": {
    "addr:full":"710 Marrett Rd Lexington MA 02421",
    "addr:housenumber":"710",
    "addr:postcode":"02421",
    "addr:street":"Marrett Rd",
    "iso:country":"US",
    "sg:address":"710 Marrett Rd",
    "sg:city":"Lexington",
    "sg:classifiers":[
        {
            "category":"Building & Trades",
            "subcategory":"Construction",
            "type":"Services"
        }
    ],
    "sg:phone":"+1 781 274 1288",
    "sg:postcode":"02421",
    "sg:province":"MA",
    "sg:tags":[
        "general",
        "contractor"
    ],
    "wof:name":"D & R General Contracting Inc",
    "wof:placetype":"venue"
},
  "geometry": {"coordinates":[-71.25703799999999,42.442957],"type":"Point"}
}