{
  "type": "Feature",
  "properties": {
    "iso:country":"US",
    "sg:address":"725 Lexington St",
    "sg:city":"Waltham",
    "sg:classifiers":[
        {
            "category":"Social Services",
            "subcategory":"Child Care",
            "type":"Services"
        }
    ],
    "sg:phone":"+1 781 894 5295",
    "sg:postcode":"02452",
    "sg:province":"MA",
    "wof:name":"YMCA",
    "wof:placetype":"venue"
},
  "geometry": {"coordinates":[-71.23401,42.401008],"type":"Point"}
}