{
  "type": "Feature",
  "properties": {
    "addr:full": "55 Walton Ave Methuen MA 01844",
    "addr:housenumber": "55",
    "addr:postcode": "01844",
    "addr:street": "Walton Ave",
    "iso:country": "US",
    "sg:address": "55 Walton Ave",
    "sg:city": "Methuen",
    "sg:classifiers": [
      {
        "category": "Autos \u0026 Motor Vehicles",
        "subcategory": "Motorcycle Sales",
        "type": "Retail Goods"
      }
    ],
    "sg:phone": "+1   ",
    "sg:postcode": "01844",
    "sg:province": "MA",
    "sg:tags": [
      "parts",
      "accessory"
    ],
    "wof:name": "Master Cycles",
    "wof:placetype": "venue"
  },
  "geometry": {"coordinates":[-71.129457,42.739149],"type":"Point"}
}
