{
  "type": "Feature",
  "properties": {
    "addr:full":"1440 Russell Rd Westfield MA 01085",
    "addr:housenumber":"1440",
    "addr:postcode":"01085",
    "addr:street":"Russell Rd",
    "iso:country":"US",
    "sg:address":"1440 Russell Rd",
    "sg:city":"Westfield",
    "sg:classifiers":[
        {
            "category":"Professional",
            "subcategory":"Accounting & Tax Preparation",
            "type":"Services"
        }
    ],
    "sg:phone":"+1 413 568 3101",
    "sg:postcode":"01085",
    "sg:province":"MA",
    "sg:tags":[
        "accountant"
    ],
    "sg:website":"http://www.morinoshea.com",
    "wof:name":"Morin & O'shea PC",
    "wof:placetype":"venue"
},
  "geometry": {"coordinates":[-72.813912,42.153155],"type":"Point"}
}