{
  "type": "Feature",
  "properties": {
    "addr:full": "20 Academy St Ste G11 Arlington MA 02476",
    "addr:housenumber": "20",
    "addr:postcode": "02476",
    "addr:street": "Academy St Ste G11",
    "iso:country": "US",
    "sg:address": "20 Academy St Ste G11",
    "sg:city": "Arlington",
    "sg:classifiers": [
      {
        "category": "Real Estate",
        "subcategory": "Real Estate Services",
        "type": "Services"
      }
    ],
    "sg:phone": "+1 781 316 3429",
    "sg:postcode": "02476",
    "sg:province": "MA",
    "sg:website": "www.housingcorparlington.org",
    "wof:name": "Housing Corporation of Arlington",
    "wof:placetype": "venue"
  },
  "geometry": {"coordinates":[-71.157334,42.415075],"type":"Point"}
}
