{
  "type": "Feature",
  "properties": {
    "iso:country":"US",
    "sg:address":"9 Main St",
    "sg:city":"South Grafton",
    "sg:classifiers":[
        {
            "category":"Restaurant",
            "type":"Food & Drink"
        }
    ],
    "sg:phone":"+1 508 839 6488",
    "sg:postcode":"01560",
    "sg:province":"MA",
    "sg:tags":[
        "pizza"
    ],
    "wof:name":"Fancy Pizza",
    "wof:placetype":"venue"
},
  "geometry": {"coordinates":[-71.68045499999999,42.176439],"type":"Point"}
}