{
  "type": "Feature",
  "properties": {
    "addr:full": "369 Harvard St Cambridge MA 02138",
    "addr:housenumber": "369",
    "addr:postcode": "02138",
    "addr:street": "Harvard St",
    "iso:country": "US",
    "sg:address": "369 Harvard St",
    "sg:city": "Cambridge",
    "sg:classifiers": [
      {
        "category": "Professional",
        "subcategory": "Lawyer \u0026 Legal Services",
        "type": "Services"
      }
    ],
    "sg:phone": "+1 617 492 7203",
    "sg:postcode": "02138",
    "sg:province": "MA",
    "wof:name": "Lawson James W Atty",
    "wof:placetype": "venue"
  },
  "geometry": {"coordinates":[-71.112099,42.371498],"type":"Point"}
}
