{
  "type": "Feature",
  "properties": {
    "iso:country":"US",
    "sg:address":"150 Aldrich St",
    "sg:city":"Roslindale",
    "sg:classifiers":[
        {
            "category":"Professional",
            "subcategory":"Computer Services",
            "type":"Services"
        }
    ],
    "sg:phone":"+1 617 325 1606",
    "sg:postcode":"02131",
    "sg:province":"MA",
    "sg:tags":[
        "home",
        "consulting",
        "page",
        "dev",
        "internet"
    ],
    "sg:website":"www.sorcerersolutions.com",
    "wof:name":"Warren Frank Group Inc",
    "wof:placetype":"venue"
},
  "geometry": {"coordinates":[-71.144375,42.281728],"type":"Point"}
}