{
  "type": "Feature",
  "properties": {
    "addr:full": "915 Main St Millis MA 02054",
    "addr:housenumber": "915",
    "addr:postcode": "02054",
    "addr:street": "Main St",
    "iso:country": "US",
    "ovtr:label": "Millis House of Pizza, 915 Main St Millis MA US",
    "ovtr:similarity": 2.5042359828948975,
    "sg:address": "915 Main St",
    "sg:city": "Millis",
    "sg:classifiers": [
      {
        "category": "Restaurant",
        "type": "Food \u0026 Drink"
      }
    ],
    "sg:phone": "+1 508 376 8500",
    "sg:postcode": "02054",
    "sg:province": "MA",
    "sg:tags": [
      "pizza"
    ],
    "wof:name": "Millis House Of Pizza",
    "wof:placetype": "venue"
  },
  "geometry": {"coordinates":[-71.359638,42.166507],"type":"Point"}
}
