{
  "type": "Feature",
  "properties": {
    "addr:full": "320 Riverside Dr Florence MA 01062",
    "addr:housenumber": "320",
    "addr:postcode": "01062",
    "addr:street": "Riverside Dr",
    "iso:country": "US",
    "sg:address": "320 Riverside Dr",
    "sg:city": "Florence",
    "sg:classifiers": [
      {
        "category": "Restaurant",
        "type": "Food \u0026 Drink"
      }
    ],
    "sg:phone": "+1 413 587 3567",
    "sg:postcode": "01062",
    "sg:province": "MA",
    "wof:name": "Flo's Pies",
    "wof:placetype": "venue"
  },
  "geometry": {"coordinates":[-72.664525,42.320599],"type":"Point"}
}
