{
  "type": "Feature",
  "properties": {
    "addr:full":"449 Washington St Boston MA 02111",
    "addr:housenumber":"449",
    "addr:postcode":"02111",
    "addr:street":"Washington St",
    "iso:country":"US",
    "sg:address":"449 Washington St",
    "sg:city":"Boston",
    "sg:classifiers":[
        {
            "category":"Banks & Credit Unions",
            "subcategory":"Bank",
            "type":"Services"
        }
    ],
    "sg:phone":"+1 617 426 0751",
    "sg:postcode":"02111",
    "sg:province":"MA",
    "sg:tags":[
        "machine",
        "teller",
        "automated"
    ],
    "wof:name":"Fast Atm",
    "wof:placetype":"venue"
},
  "geometry": {"coordinates":[-71.06121400000001,42.35494],"type":"Point"}
}