{
  "type": "Feature",
  "properties": {
    "iso:country":"US",
    "sg:address":"288 Northfield Rd",
    "sg:city":"Bernardston",
    "sg:classifiers":[
        {
            "category":"Building & Trades",
            "subcategory":"Construction",
            "type":"Services"
        }
    ],
    "sg:phone":"+1 413 648 9507",
    "sg:postcode":"01337",
    "sg:province":"MA",
    "sg:tags":[
        "general",
        "contractor"
    ],
    "wof:name":"Charles R Deane Excavating",
    "wof:placetype":"venue"
},
  "geometry": {"coordinates":[-72.522111,42.669462],"type":"Point"}
}