{
  "type": "Feature",
  "properties": {
    "addr:full": "1655 Fall River Ave Seekonk MA 02771",
    "addr:housenumber": "1655",
    "addr:postcode": "02771",
    "addr:street": "Fall River Ave",
    "iso:country": "US",
    "sg:address": "1655 Fall River Ave",
    "sg:city": "Seekonk",
    "sg:classifiers": [
      {
        "category": "Building \u0026 Trades",
        "subcategory": "Construction",
        "type": "Services"
      }
    ],
    "sg:phone": "+1   ",
    "sg:postcode": "02771",
    "sg:province": "MA",
    "sg:tags": [
      "house"
    ],
    "wof:name": "Jdi Construction Inc",
    "wof:placetype": "venue"
  },
  "geometry": {"coordinates":[-71.30922,41.784342],"type":"Point"}
}
