{
  "type": "Feature",
  "properties": {
    "addr:full":"68 Park St Andover MA 01810",
    "addr:housenumber":"68",
    "addr:postcode":"01810",
    "addr:street":"Park St",
    "iso:country":"US",
    "sg:address":"68 Park St",
    "sg:city":"Andover",
    "sg:classifiers":[
        {
            "category":"Manufacturing",
            "subcategory":"Electronics",
            "type":"Manufacturing & Wholesale Goods"
        }
    ],
    "sg:phone":"+1 978 470 3400",
    "sg:postcode":"01810",
    "sg:province":"MA",
    "sg:tags":[
        "semiconductor",
        "devices"
    ],
    "wof:name":"Spindrift Technology",
    "wof:placetype":"venue"
},
  "geometry": {"coordinates":[-71.136995,42.657425],"type":"Point"}
}