{
  "type": "Feature",
  "properties": {
    "iso:country":"US",
    "sg:address":"56 Bissell Rd",
    "sg:city":"Goshen",
    "sg:classifiers":[
        {
            "category":"Education",
            "subcategory":"Vocational School",
            "type":"Public Place"
        }
    ],
    "sg:phone":"+1   ",
    "sg:postcode":"01096",
    "sg:province":"MA",
    "wof:name":"Careerformation Inc",
    "wof:placetype":"venue"
},
  "geometry": {"coordinates":[-72.81092700000001,42.418588],"type":"Point"}
}