{
  "type": "Feature",
  "properties": {
    "iso:country":"US",
    "sg:address":"153 Belcher Dr",
    "sg:city":"Sudbury",
    "sg:classifiers":[
        {
            "category":"Professional",
            "subcategory":"Computer Services",
            "type":"Services"
        }
    ],
    "sg:phone":"+1   ",
    "sg:postcode":"01776",
    "sg:province":"MA",
    "sg:tags":[
        "related"
    ],
    "wof:name":"Excel Systems Development",
    "wof:placetype":"venue"
},
  "geometry": {"coordinates":[-71.43702500000001,42.416512],"type":"Point"}
}