{
  "type": "Feature",
  "properties": {
    "iso:country":"US",
    "sg:address":"100 W Boylston St",
    "sg:city":"West Boylston",
    "sg:classifiers":[
        {
            "category":"Education",
            "subcategory":"School",
            "type":"Public Place"
        }
    ],
    "sg:phone":"+1 508 835 1112",
    "sg:postcode":"01583",
    "sg:province":"MA",
    "wof:name":"Developmental Learning Ctr",
    "wof:placetype":"venue"
},
  "geometry": {"coordinates":[-71.784627,42.356283],"type":"Point"}
}