{
  "type": "Feature",
  "properties": {
    "iso:country":"US",
    "sg:address":"14 Liberty Ave",
    "sg:city":"Burlington",
    "sg:classifiers":[
        {
            "category":"Building & Trades",
            "subcategory":"Landscaping Services",
            "type":"Services"
        }
    ],
    "sg:phone":"+1 781 229 2389",
    "sg:postcode":"01803",
    "sg:province":"MA",
    "sg:tags":[
        "landscape",
        "contractor"
    ],
    "wof:name":"Duncan Brothers Landscaping",
    "wof:placetype":"venue"
},
  "geometry": {"coordinates":[-71.22460599999999,42.504511],"type":"Point"}
}