{
  "type": "Feature",
  "properties": {
    "addr:full": "12 Rose Ln Stoneham MA 02180",
    "addr:housenumber": "12",
    "addr:postcode": "02180",
    "addr:street": "Rose Ln",
    "iso:country": "US",
    "sg:address": "12 Rose Ln",
    "sg:city": "Stoneham",
    "sg:classifiers": [
      {
        "category": "Building \u0026 Trades",
        "subcategory": "Plumbing",
        "type": "Services"
      }
    ],
    "sg:phone": "+1 978 663 0737",
    "sg:postcode": "02180",
    "sg:province": "MA",
    "sg:tags": [
      "plumbing",
      "contractor"
    ],
    "wof:name": "Superior Mechanical Plumbing",
    "wof:placetype": "venue"
  },
  "geometry": {"coordinates":[-71.113182,42.49633],"type":"Point"}
}
