{
  "type": "Feature",
  "properties": {
    "addr:full":"491 Fairway Dr Somerset MA 02726",
    "addr:housenumber":"491",
    "addr:postcode":"02726",
    "addr:street":"Fairway Dr",
    "iso:country":"US",
    "sg:address":"491 Fairway Dr",
    "sg:city":"Somerset",
    "sg:classifiers":[
        {
            "category":"Building & Trades",
            "subcategory":"Cleaning & Sanitation",
            "type":"Services"
        }
    ],
    "sg:phone":"+1 508 677 4703",
    "sg:postcode":"02726",
    "sg:province":"MA",
    "wof:name":"Goodson Enterprises",
    "wof:placetype":"venue"
},
  "geometry": {"coordinates":[-71.14833900000001,41.779937],"type":"Point"}
}