{
  "type": "Feature",
  "properties": {
    "addr:full": "106 Addison St Chelsea MA 02150",
    "addr:housenumber": "106",
    "addr:postcode": "02150",
    "addr:street": "Addison St",
    "iso:country": "US",
    "sg:address": "106 Addison St",
    "sg:city": "Chelsea",
    "sg:classifiers": [
      {
        "category": "Restaurant",
        "type": "Food \u0026 Drink"
      }
    ],
    "sg:phone": "+1   ",
    "sg:postcode": "02150",
    "sg:province": "MA",
    "sg:tags": [
      "eating"
    ],
    "wof:name": "Wing Fat Inc",
    "wof:placetype": "venue"
  },
  "geometry": {"coordinates":[-71.035575,42.399245],"type":"Point"}
}
