{
  "type": "Feature",
  "properties": {
    "addr:full":"33 Hartwell Rd Bedford MA 01730",
    "addr:housenumber":"33",
    "addr:postcode":"01730",
    "addr:street":"Hartwell Rd",
    "iso:country":"US",
    "sg:address":"33 Hartwell Rd",
    "sg:city":"Bedford",
    "sg:classifiers":[
        {
            "category":"Wholesale",
            "subcategory":"Electrical",
            "type":"Manufacturing & Wholesale Goods"
        },
        {
            "category":"Shopping",
            "subcategory":"Computers & Home Electronics",
            "type":"Retail Goods"
        }
    ],
    "sg:phone":"+1 781 275 8171",
    "sg:postcode":"01730",
    "sg:province":"MA",
    "sg:tags":[
        "communication",
        "radio",
        "system",
        "repair"
    ],
    "wof:name":"Ed's Radio Communications",
    "wof:placetype":"venue"
},
  "geometry": {"coordinates":[-71.277895,42.483054],"type":"Point"}
}