{
  "type": "Feature",
  "properties": {
    "addr:full": "204 Main St Worcester MA 01608",
    "addr:housenumber": "204",
    "addr:postcode": "01608",
    "addr:street": "Main St",
    "iso:country": "US",
    "sg:address": "204 Main St",
    "sg:city": "Worcester",
    "sg:classifiers": [
      {
        "category": "Shopping",
        "type": "Retail Goods"
      }
    ],
    "sg:phone": "+1 508 754 3293",
    "sg:postcode": "01608",
    "sg:province": "MA",
    "sg:tags": [
      "trophy",
      "medal",
      "award"
    ],
    "wof:name": "Olympic Trophy Mfg Co",
    "wof:placetype": "venue"
  },
  "geometry": {"coordinates":[-71.800841,42.267466],"type":"Point"}
}
