{
  "type": "Feature",
  "properties": {
    "addr:full":"3 Windy Hill Ln Wayland MA 01778",
    "addr:housenumber":"3",
    "addr:postcode":"01778",
    "addr:street":"Windy Hill Ln",
    "iso:country":"US",
    "sg:address":"3 Windy Hill Ln",
    "sg:city":"Wayland",
    "sg:classifiers":[
        {
            "category":"Professional",
            "subcategory":"Management & Consulting",
            "type":"Services"
        }
    ],
    "sg:phone":"+1 508 358 4274",
    "sg:postcode":"01778",
    "sg:province":"MA",
    "sg:tags":[
        "consultant",
        "business"
    ],
    "sg:website":"www.mstweb.com",
    "wof:name":"Management Support Technology",
    "wof:placetype":"venue"
},
  "geometry": {"coordinates":[-71.35491500000001,42.353023],"type":"Point"}
}