{
  "type": "Feature",
  "properties": {
    "iso:country":"US",
    "sg:address":"226 Lowell St",
    "sg:city":"Wilmington",
    "sg:classifiers":[
        {
            "category":"Building & Trades",
            "subcategory":"Construction",
            "type":"Services"
        }
    ],
    "sg:phone":"+1 978 658 0302",
    "sg:postcode":"01887",
    "sg:province":"MA",
    "sg:tags":[
        "contractor"
    ],
    "wof:name":"C J M Builders Inc",
    "wof:placetype":"venue"
},
  "geometry": {"coordinates":[-71.14919999999999,42.539501],"type":"Point"}
}