{
  "type": "Feature",
  "properties": {
    "addr:full": "26 Mount Auburn St Watertown MA 02472",
    "addr:housenumber": "26",
    "addr:postcode": "02472",
    "addr:street": "Mount Auburn St",
    "iso:country": "US",
    "sg:address": "26 Mount Auburn St",
    "sg:city": "Watertown",
    "sg:classifiers": [
      {
        "category": "Personal",
        "subcategory": "Beauty Salon",
        "type": "Services"
      }
    ],
    "sg:phone": "+1 617 924 6567",
    "sg:postcode": "02472",
    "sg:province": "MA",
    "sg:tags": [
      "manicuring"
    ],
    "wof:name": "Diamond Nail Salon",
    "wof:placetype": "venue"
  },
  "geometry": {"coordinates":[-71.183832,42.365524],"type":"Point"}
}
