{
  "type": "Feature",
  "properties": {
    "iso:country":"US",
    "sg:address":"10 Central St",
    "sg:city":"Norwood",
    "sg:classifiers":[
        {
            "category":"Building & Trades",
            "subcategory":"Locksmith",
            "type":"Services"
        }
    ],
    "sg:phone":"+1 781 269 7081",
    "sg:postcode":"02062",
    "sg:province":"MA",
    "sg:tags":[
        "key"
    ],
    "wof:name":"A 1 Emergency Locksmith",
    "wof:placetype":"venue"
},
  "geometry": {"coordinates":[-71.20223799999999,42.190576],"type":"Point"}
}