{
  "type": "Feature",
  "properties": {
    "addr:full": "342 Main St Great Barrington MA 01230",
    "addr:housenumber": "342",
    "addr:postcode": "01230",
    "addr:street": "Main St",
    "iso:country": "US",
    "sg:address": "342 Main St",
    "sg:city": "Great Barrington",
    "sg:classifiers": [
      {
        "category": "Professional",
        "subcategory": "Lawyer \u0026 Legal Services",
        "type": "Services"
      }
    ],
    "sg:phone": "+1 413 528 4800",
    "sg:postcode": "01230",
    "sg:province": "MA",
    "sg:tags": [
      "attorney"
    ],
    "wof:name": "Hellman \u0026 Shearn",
    "wof:placetype": "venue"
  },
  "geometry": {"coordinates":[-73.363447,42.193189],"type":"Point"}
}
