{
  "type": "Feature",
  "properties": {
    "iso:country":"US",
    "sg:address":"588 Mt Auburn St",
    "sg:city":"Watertown",
    "sg:classifiers":[
        {
            "category":"Personal",
            "subcategory":"Beauty Salon",
            "type":"Services"
        },
        {
            "category":"Personal",
            "subcategory":"Barber",
            "type":"Services"
        }
    ],
    "sg:phone":"+1 617 923 1988",
    "sg:postcode":"02472",
    "sg:province":"MA",
    "sg:tags":[
        "hair"
    ],
    "wof:name":"The Barbershop & The Salon",
    "wof:placetype":"venue"
},
  "geometry": {"coordinates":[-71.158709,42.370754],"type":"Point"}
}