{
  "type": "Feature",
  "properties": {
    "addr:full":"966 Park St, Unit B7 Stoughton MA 02072",
    "addr:housenumber":"966",
    "addr:postcode":"02072",
    "addr:street":"Park St;B7",
    "iso:country":"US",
    "sg:address":"966 Park St, Unit B7",
    "sg:city":"Stoughton",
    "sg:classifiers":[
        {
            "category":"Community Center",
            "type":"Public Place"
        }
    ],
    "sg:phone":"+1 800 639 6773",
    "sg:postcode":"02072",
    "sg:province":"MA",
    "sg:tags":[
        "medical"
    ],
    "sg:website":"www.localstdtesting.com/15",
    "wof:name":"Local STD Testing",
    "wof:placetype":"venue"
},
  "geometry": {"coordinates":[-71.07255000000001,42.11166],"type":"Point"}
}