{
  "type": "Feature",
  "properties": {
    "addr:full": "871 Webster St Marshfield MA 02050",
    "addr:housenumber": "871",
    "addr:postcode": "02050",
    "addr:street": "Webster St",
    "iso:country": "US",
    "sg:address": "871 Webster St",
    "sg:city": "Marshfield",
    "sg:classifiers": [
      {
        "category": "Professional",
        "subcategory": "Computer Services",
        "type": "Services"
      }
    ],
    "sg:phone": "+1 781 834 9400",
    "sg:postcode": "02050",
    "sg:province": "MA",
    "sg:tags": [
      "website",
      "design"
    ],
    "wof:name": "Mcd Studios",
    "wof:placetype": "venue"
  },
  "geometry": {"coordinates":[-70.702233,42.088884],"type":"Point"}
}
