{
  "type": "Feature",
  "properties": {
    "addr:full":"1 Elm St Lee MA 01262",
    "addr:housenumber":"1",
    "addr:postcode":"01262",
    "addr:street":"Elm St",
    "iso:country":"US",
    "sg:address":"1 Elm St",
    "sg:city":"Lee",
    "sg:classifiers":[
        {
            "category":"Travel",
            "subcategory":"Hotels & Motels",
            "type":"Entertainment"
        }
    ],
    "sg:phone":"+1 413 243 2221",
    "sg:postcode":"01262",
    "sg:province":"MA",
    "sg:tags":[
        "breakfast",
        "accommodation",
        "bed"
    ],
    "sg:website":"www.berkshireinns.com",
    "wof:name":"Chambery Inn",
    "wof:placetype":"venue"
},
  "geometry": {"coordinates":[-73.309956,42.281814],"type":"Point"}
}