{
  "type": "Feature",
  "properties": {
    "iso:country":"US",
    "sg:address":"443 Washington St",
    "sg:city":"Dorchester Ctr",
    "sg:classifiers":[
        {
            "category":"Retail",
            "subcategory":"Laundry & Dry Cleaning",
            "type":"Services"
        }
    ],
    "sg:phone":"+1 617 288 1330",
    "sg:postcode":"02124",
    "sg:province":"MA",
    "sg:tags":[
        "cleaners"
    ],
    "wof:name":"Vin's Cleaners",
    "wof:placetype":"venue"
},
  "geometry": {"coordinates":[-71.07229,42.296404],"type":"Point"}
}