{
  "type": "Feature",
  "properties": {
    "addr:full": "443 Washington St Dorchester Ctr MA 02124",
    "addr:housenumber": "443",
    "addr:postcode": "02124",
    "addr:street": "Washington St",
    "iso:country": "US",
    "sg:address": "443 Washington St",
    "sg:city": "Dorchester Ctr",
    "sg:classifiers": [
      {
        "category": "Retail",
        "subcategory": "Laundry \u0026 Dry Cleaning",
        "type": "Services"
      }
    ],
    "sg:phone": "+1 617 288 1330",
    "sg:postcode": "02124",
    "sg:province": "MA",
    "sg:tags": [
      "cleaners"
    ],
    "wof:name": "Vin's Cleaners",
    "wof:placetype": "venue"
  },
  "geometry": {"coordinates":[-71.07229,42.296404],"type":"Point"}
}
