{
  "type": "Feature",
  "properties": {
    "addr:full":"510-520 Providence Highway Dedham MA 02026",
    "addr:housenumber":"510-520",
    "addr:postcode":"02026",
    "addr:street":"Providence Highway",
    "iso:country":"US",
    "sg:address":"510-520 Providence Highway",
    "sg:city":"Dedham",
    "sg:classifiers":[
        {
            "category":"Home & Garden",
            "subcategory":"Carpets & Floor Coverings",
            "type":"Retail Goods"
        }
    ],
    "sg:phone":"+1 781 326 0919",
    "sg:postcode":"02026",
    "sg:province":"MA",
    "sg:tags":[
        "mattress"
    ],
    "sg:website":"www.sleepys.com/",
    "wof:name":"Sleepy's, The Mattress Professionals",
    "wof:placetype":"venue"
},
  "geometry": {"coordinates":[-71.183548,42.193447],"type":"Point"}
}