{
  "type": "Feature",
  "properties": {
    "addr:full": "1753 Broadway Saugus MA 01906",
    "addr:housenumber": "1753",
    "addr:postcode": "01906",
    "addr:street": "Broadway",
    "iso:country": "US",
    "sg:address": "1753 Broadway",
    "sg:city": "Saugus",
    "sg:classifiers": [
      {
        "category": "Travel",
        "subcategory": "Hotels \u0026 Motels",
        "type": "Entertainment"
      }
    ],
    "sg:phone": "+1 781 233 6700",
    "sg:postcode": "01906",
    "sg:province": "MA",
    "wof:name": "Colonial Traveler Motor Court",
    "wof:placetype": "venue"
  },
  "geometry": {"coordinates":[-71.027298,42.447102],"type":"Point"}
}
