{
  "type": "Feature",
  "properties": {
    "iso:country":"US",
    "sg:address":"194 Towne St",
    "sg:city":"North Attleboro",
    "sg:classifiers":[
        {
            "category":"Building & Trades",
            "subcategory":"Cleaning & Sanitation",
            "type":"Services"
        }
    ],
    "sg:phone":"+1 508 695 5253",
    "sg:postcode":"02760",
    "sg:province":"MA",
    "sg:tags":[
        "carpet"
    ],
    "wof:name":"Nempro Rug Cleaning",
    "wof:placetype":"venue"
},
  "geometry": {"coordinates":[-71.313193,41.970866],"type":"Point"}
}