{
  "type": "Feature",
  "properties": {
    "addr:full": "194 Towne St North Attleboro MA 02760",
    "addr:housenumber": "194",
    "addr:postcode": "02760",
    "addr:street": "Towne St",
    "iso:country": "US",
    "sg:address": "194 Towne St",
    "sg:city": "North Attleboro",
    "sg:classifiers": [
      {
        "category": "Building \u0026 Trades",
        "subcategory": "Cleaning \u0026 Sanitation",
        "type": "Services"
      }
    ],
    "sg:phone": "+1 508 695 5253",
    "sg:postcode": "02760",
    "sg:province": "MA",
    "sg:tags": [
      "carpet"
    ],
    "wof:name": "Nempro Rug Cleaning",
    "wof:placetype": "venue"
  },
  "geometry": {"coordinates":[-71.313193,41.970866],"type":"Point"}
}
