{
  "type": "Feature",
  "properties": {
    "iso:country":"US",
    "sg:address":"54 Leonard St",
    "sg:city":"Norton",
    "sg:classifiers":[
        {
            "category":"Farming",
            "subcategory":"Fish & Marine Products",
            "type":"Manufacturing & Wholesale Goods"
        }
    ],
    "sg:phone":"+1 508 285 5111",
    "sg:postcode":"02766",
    "sg:province":"MA",
    "sg:tags":[
        "relocation",
        "rescue",
        "animal",
        "transporting"
    ],
    "wof:name":"C & B Pest Control",
    "wof:placetype":"venue"
},
  "geometry": {"coordinates":[-71.14936,41.983857],"type":"Point"}
}