{
  "type": "Feature",
  "properties": {
    "addr:full":"20 Concord St Gloucester MA 01930",
    "addr:housenumber":"20",
    "addr:postcode":"01930",
    "addr:street":"Concord St",
    "iso:country":"US",
    "sg:address":"20 Concord St",
    "sg:city":"Gloucester",
    "sg:classifiers":[
        {
            "category":"Social Services",
            "subcategory":"Child Care",
            "type":"Services"
        }
    ],
    "sg:phone":"+1 978 281 2860",
    "sg:postcode":"01930",
    "sg:province":"MA",
    "wof:name":"Kids Kottage Family Child Care",
    "wof:placetype":"venue"
},
  "geometry": {"coordinates":[-70.709642,42.622601],"type":"Point"}
}