{
  "type": "Feature",
  "properties": {
    "iso:country":"US",
    "sg:address":"309 Front St",
    "sg:city":"Chicopee",
    "sg:classifiers":[
        {
            "category":"Personal",
            "subcategory":"Beauty Salon",
            "type":"Services"
        }
    ],
    "sg:phone":"+1 413 592 3800",
    "sg:postcode":"01013",
    "sg:province":"MA",
    "wof:name":"Paulo's Family Hair & Nail",
    "wof:placetype":"venue"
},
  "geometry": {"coordinates":[-72.60443100000001,42.148433],"type":"Point"}
}