{
  "type": "Feature",
  "properties": {
    "addr:full": "309 Front St Chicopee MA 01013",
    "addr:housenumber": "309",
    "addr:postcode": "01013",
    "addr:street": "Front St",
    "iso:country": "US",
    "sg:address": "309 Front St",
    "sg:city": "Chicopee",
    "sg:classifiers": [
      {
        "category": "Personal",
        "subcategory": "Beauty Salon",
        "type": "Services"
      }
    ],
    "sg:phone": "+1 413 592 3800",
    "sg:postcode": "01013",
    "sg:province": "MA",
    "wof:name": "Paulo's Family Hair \u0026 Nail",
    "wof:placetype": "venue"
  },
  "geometry": {"coordinates":[-72.604431,42.148433],"type":"Point"}
}
