{
  "type": "Feature",
  "properties": {
    "addr:full":"27 Enfield Rd Pelham MA 01002",
    "addr:housenumber":"27",
    "addr:postcode":"01002",
    "addr:street":"Enfield Rd",
    "iso:country":"US",
    "sg:address":"27 Enfield Rd",
    "sg:city":"Pelham",
    "sg:classifiers":[
        {
            "category":"Wholesale",
            "subcategory":"Poultry",
            "type":"Manufacturing & Wholesale Goods"
        }
    ],
    "sg:phone":"+1 413 253 2123",
    "sg:postcode":"01002",
    "sg:province":"MA",
    "sg:tags":[
        "eggs"
    ],
    "wof:name":"Hall Poultry",
    "wof:placetype":"venue"
},
  "geometry": {"coordinates":[-72.446229,42.371228],"type":"Point"}
}