{
  "type": "Feature",
  "properties": {
    "addr:full":"107 North St Danvers MA 01923",
    "addr:housenumber":"107",
    "addr:postcode":"01923",
    "addr:street":"North St",
    "iso:country":"US",
    "sg:address":"107 North St",
    "sg:city":"Danvers",
    "sg:classifiers":[
        {
            "category":"Building & Trades",
            "subcategory":"Electrical",
            "type":"Services"
        }
    ],
    "sg:phone":"+1   ",
    "sg:postcode":"01923",
    "sg:province":"MA",
    "sg:tags":[
        "electrical",
        "contractor"
    ],
    "wof:name":"Paul J Fasciano",
    "wof:placetype":"venue"
},
  "geometry": {"coordinates":[-70.952078,42.59351],"type":"Point"}
}