{
  "type": "Feature",
  "properties": {
    "addr:full": "265 Pine St Leicester MA 01524",
    "addr:housenumber": "265",
    "addr:postcode": "01524",
    "addr:street": "Pine St",
    "iso:country": "US",
    "sg:address": "265 Pine St",
    "sg:city": "Leicester",
    "sg:classifiers": [
      {
        "category": "Building \u0026 Trades",
        "subcategory": "Construction",
        "type": "Services"
      }
    ],
    "sg:phone": "+1   ",
    "sg:postcode": "01524",
    "sg:province": "MA",
    "sg:tags": [
      "excavation",
      "contractor"
    ],
    "wof:name": "Airbourne Excavating",
    "wof:placetype": "venue"
  },
  "geometry": {"coordinates":[-71.924757,42.22319],"type":"Point"}
}
