{
  "type": "Feature",
  "properties": {
    "addr:full": "29 Pleasant St Gardner MA 01440",
    "addr:housenumber": "29",
    "addr:postcode": "01440",
    "addr:street": "Pleasant St",
    "iso:country": "US",
    "sg:address": "29 Pleasant St",
    "sg:city": "Gardner",
    "sg:classifiers": [
      {
        "category": "Recreation",
        "type": "Entertainment"
      }
    ],
    "sg:phone": "+1 978 632 9201",
    "sg:postcode": "01440",
    "sg:province": "MA",
    "sg:tags": [
      "parlor",
      "billiard"
    ],
    "wof:name": "Shooter's Billiards \u0026 Supplies",
    "wof:placetype": "venue"
  },
  "geometry": {"coordinates":[-71.99526,42.575581],"type":"Point"}
}
