{
  "type": "Feature",
  "properties": {
    "iso:country":"US",
    "sg:address":"280 Main St",
    "sg:city":"Medford",
    "sg:classifiers":[
        {
            "category":"Personal",
            "subcategory":"Beauty Salon",
            "type":"Services"
        }
    ],
    "sg:phone":"+1 781 395 5451",
    "sg:postcode":"02155",
    "sg:province":"MA",
    "wof:name":"Debra's Hair Designs",
    "wof:placetype":"venue"
},
  "geometry": {"coordinates":[-71.10933300000001,42.408687],"type":"Point"}
}