{
  "type": "Feature",
  "properties": {
    "iso:country":"US",
    "sg:address":"13 Ashdale Rd",
    "sg:city":"North Billerica",
    "sg:classifiers":[
        {
            "category":"Professional",
            "subcategory":"Secretarial Services",
            "type":"Services"
        }
    ],
    "sg:phone":"+1   ",
    "sg:postcode":"01862",
    "sg:province":"MA",
    "sg:tags":[
        "reporting"
    ],
    "wof:name":"After Six Secretarial Sevices",
    "wof:placetype":"venue"
},
  "geometry": {"coordinates":[-71.262789,42.590283],"type":"Point"}
}