{
  "type": "Feature",
  "properties": {
    "addr:full":"88 Main St Acushnet MA 02743",
    "addr:housenumber":"88",
    "addr:postcode":"02743",
    "addr:street":"Main St",
    "iso:country":"US",
    "sg:address":"88 Main St",
    "sg:city":"Acushnet",
    "sg:classifiers":[
        {
            "category":"Education",
            "subcategory":"Library",
            "type":"Public Place"
        }
    ],
    "sg:phone":"+1 508 998 0270",
    "sg:postcode":"02743",
    "sg:province":"MA",
    "wof:name":"Acushnet Public Library",
    "wof:placetype":"venue"
},
  "geometry": {"coordinates":[-70.912295,41.682822],"type":"Point"}
}