{
  "type": "Feature",
  "properties": {
    "iso:country":"US",
    "sg:address":"541 Main St",
    "sg:city":"Medfield",
    "sg:classifiers":[
        {
            "category":"Professional",
            "subcategory":"Engineering",
            "type":"Services"
        }
    ],
    "sg:phone":"+1 508 359 8945",
    "sg:postcode":"02052",
    "sg:province":"MA",
    "sg:tags":[
        "engineer"
    ],
    "sg:website":"www.childseng.com",
    "wof:name":"Childs Engineering Corp",
    "wof:placetype":"venue"
},
  "geometry": {"coordinates":[-71.307999,42.185858],"type":"Point"}
}