{
  "type": "Feature",
  "properties": {
    "iso:country":"US",
    "sg:address":"80 High Rock Ter",
    "sg:city":"Chestnut Hill",
    "sg:classifiers":[
        {
            "category":"Professional",
            "subcategory":"Management & Consulting",
            "type":"Services"
        }
    ],
    "sg:phone":"+1   ",
    "sg:postcode":"02467",
    "sg:province":"MA",
    "sg:tags":[
        "business"
    ],
    "wof:name":"Ripples Ripples Group",
    "wof:placetype":"venue"
},
  "geometry": {"coordinates":[-71.173012,42.307429],"type":"Point"}
}