{
  "type": "Feature",
  "properties": {
    "iso:country":"US",
    "sg:address":"19 Amesbury St",
    "sg:city":"Lawrence",
    "sg:classifiers":[
        {
            "category":"Personal",
            "subcategory":"Barber",
            "type":"Services"
        }
    ],
    "sg:phone":"+1 978 975 0782",
    "sg:postcode":"01840",
    "sg:province":"MA",
    "wof:name":"Jose Luis Barber Shop",
    "wof:placetype":"venue"
},
  "geometry": {"coordinates":[-71.161958,42.706047],"type":"Point"}
}