{
  "type": "Feature",
  "properties": {
    "iso:country":"US",
    "sg:address":"13 Sycamore St",
    "sg:city":"Chelmsford",
    "sg:classifiers":[
        {
            "category":"Local Transit",
            "type":"Transportation"
        }
    ],
    "sg:phone":"+1 978 458 9400",
    "sg:postcode":"01824",
    "sg:province":"MA",
    "sg:tags":[
        "limousine"
    ],
    "wof:name":"Chelmsford Limousine Svc",
    "wof:placetype":"venue"
},
  "geometry": {"coordinates":[-71.381067,42.606393],"type":"Point"}
}