{
  "type": "Feature",
  "properties": {
    "addr:full": "200 Heard St Worcester MA 01603",
    "addr:housenumber": "200",
    "addr:postcode": "01603",
    "addr:street": "Heard St",
    "iso:country": "US",
    "sg:address": "200 Heard St",
    "sg:city": "Worcester",
    "sg:classifiers": [
      {
        "category": "Education",
        "subcategory": "School",
        "type": "Public Place"
      }
    ],
    "sg:phone": "+1 508 799 3525",
    "sg:postcode": "01603",
    "sg:province": "MA",
    "sg:tags": [
      "elementary"
    ],
    "sg:website": "http://www.wpsweb.com",
    "wof:name": "Heard Street Elementary School",
    "wof:placetype": "venue"
  },
  "geometry": {"coordinates":[-71.842529,42.231869],"type":"Point"}
}
