{
  "type": "Feature",
  "properties": {
    "addr:full": "11 Newbury St Quincy MA 02171",
    "addr:housenumber": "11",
    "addr:postcode": "02171",
    "addr:street": "Newbury St",
    "iso:country": "US",
    "sg:address": "11 Newbury St",
    "sg:city": "Quincy",
    "sg:classifiers": [
      {
        "category": "Professional",
        "type": "Services"
      }
    ],
    "sg:phone": "+1 617 328 1920",
    "sg:postcode": "02171",
    "sg:province": "MA",
    "sg:tags": [
      "establishment"
    ],
    "wof:name": "Mwm Co Inc",
    "wof:placetype": "venue"
  },
  "geometry": {"coordinates":[-71.037183,42.2817],"type":"Point"}
}
