{
  "type": "Feature",
  "properties": {
    "addr:full":"16 Park St Ayer MA 01432",
    "addr:housenumber":"16",
    "addr:postcode":"01432",
    "addr:street":"Park St",
    "iso:country":"US",
    "sg:address":"16 Park St",
    "sg:city":"Ayer",
    "sg:classifiers":[
        {
            "category":"Bagels",
            "type":"Food & Drink"
        },
        {
            "category":"Coffee & Tea",
            "type":"Food & Drink"
        },
        {
            "category":"Food & Beverages",
            "subcategory":"Bakery",
            "type":"Retail Goods"
        },
        {
            "category":"Bakery",
            "type":"Food & Drink"
        },
        {
            "category":"Donuts",
            "type":"Food & Drink"
        }
    ],
    "sg:menulink":"http://www.allmenus.com/ma/ayer/142675-dunkin-donuts/menu/",
    "sg:phone":"+1 978 772 7553",
    "sg:postcode":"01432",
    "sg:province":"MA",
    "sg:tags":[
        "coffee",
        "diner",
        "tea",
        "bakery",
        "bagel",
        "american",
        "pastry"
    ],
    "wof:name":"Dunkin' Donuts",
    "wof:placetype":"venue"
},
  "geometry": {"coordinates":[-71.591005,42.561763],"type":"Point"}
}