{
  "type": "Feature",
  "properties": {
    "addr:full":"171 Pleasant St East Bridgewater MA 02333",
    "addr:housenumber":"171",
    "addr:postcode":"02333",
    "addr:street":"Pleasant St",
    "iso:country":"US",
    "sg:address":"171 Pleasant St",
    "sg:city":"East Bridgewater",
    "sg:classifiers":[
        {
            "category":"Professional",
            "subcategory":"Secretarial Services",
            "type":"Services"
        }
    ],
    "sg:phone":"+1   ",
    "sg:postcode":"02333",
    "sg:province":"MA",
    "sg:tags":[
        "reporting"
    ],
    "wof:name":"Conant Reporting Services",
    "wof:placetype":"venue"
},
  "geometry": {"coordinates":[-70.977268,42.035363],"type":"Point"}
}