{
  "type": "Feature",
  "properties": {
    "addr:full": "14 Colonial Dr Shrewsbury MA 01545",
    "addr:housenumber": "14",
    "addr:postcode": "01545",
    "addr:street": "Colonial Dr",
    "iso:country": "US",
    "sg:address": "14 Colonial Dr",
    "sg:city": "Shrewsbury",
    "sg:classifiers": [
      {
        "category": "Professional",
        "subcategory": "Business Services",
        "type": "Services"
      }
    ],
    "sg:phone": "+1 508 870 2939",
    "sg:postcode": "01545",
    "sg:province": "MA",
    "sg:tags": [
      "transcribing",
      "disc"
    ],
    "wof:name": "Professional Transcription Svc",
    "wof:placetype": "venue"
  },
  "geometry": {"coordinates":[-71.718079,42.3248],"type":"Point"}
}
