{
  "type": "Feature",
  "properties": {
    "iso:country":"US",
    "sg:address":"347 Congress St",
    "sg:city":"Boston",
    "sg:classifiers":[
        {
            "category":"Professional",
            "type":"Services"
        }
    ],
    "sg:phone":"+1 617 790 3900",
    "sg:postcode":"02210",
    "sg:province":"MA",
    "sg:tags":[
        "establishment"
    ],
    "wof:name":"Kensington Investment Co",
    "wof:placetype":"venue"
},
  "geometry": {"coordinates":[-71.04876400000001,42.35052],"type":"Point"}
}