{
  "type": "Feature",
  "properties": {
    "iso:country":"US",
    "sg:address":"132 Shore Rd",
    "sg:city":"North Truro",
    "sg:classifiers":[
        {
            "category":"Travel",
            "subcategory":"Hotels & Motels",
            "type":"Entertainment"
        }
    ],
    "sg:phone":"+1 508 487 2207",
    "sg:postcode":"02652",
    "sg:province":"MA",
    "wof:name":"Braemar Resort",
    "wof:placetype":"venue"
},
  "geometry": {"coordinates":[-70.10075399999999,42.043337],"type":"Point"}
}