{
  "type": "Feature",
  "properties": {
    "addr:full": "529 Main St Winchester MA 01890",
    "addr:housenumber": "529",
    "addr:postcode": "01890",
    "addr:street": "Main St",
    "iso:country": "US",
    "sg:address": "529 Main St",
    "sg:city": "Winchester",
    "sg:classifiers": [
      {
        "category": "Deli",
        "type": "Food \u0026 Drink"
      }
    ],
    "sg:phone": "+1 781 729 7481",
    "sg:postcode": "01890",
    "sg:province": "MA",
    "wof:name": "J \u0026 A Food Store - CLOSED",
    "wof:placetype": "venue"
  },
  "geometry": {"coordinates":[-71.136597,42.4519],"type":"Point"}
}
