{
  "type": "Feature",
  "properties": {
    "iso:country":"US",
    "sg:address":"341 State Rd",
    "sg:city":"North Dartmouth",
    "sg:classifiers":[
        {
            "category":"Shopping",
            "subcategory":"Optical Goods",
            "type":"Retail Goods"
        }
    ],
    "sg:phone":"+1 508 997 6591",
    "sg:postcode":"02747",
    "sg:province":"MA",
    "wof:name":"Pearle Vision",
    "wof:placetype":"venue"
},
  "geometry": {"coordinates":[-70.985831,41.639371],"type":"Point"}
}