{
  "type": "Feature",
  "properties": {
    "addr:full":"36 White St Cambridge MA 02238",
    "addr:housenumber":"36",
    "addr:postcode":"02238",
    "addr:street":"White St",
    "iso:country":"US",
    "sg:address":"36 White St",
    "sg:city":"Cambridge",
    "sg:classifiers":[
        {
            "category":"Shopping",
            "subcategory":"Pharmacy",
            "type":"Retail Goods"
        }
    ],
    "sg:phone":"+1 617 876 5519",
    "sg:postcode":"02238",
    "sg:province":"MA",
    "sg:tags":[
        "drugstore"
    ],
    "wof:name":"CVS Pharmacy",
    "wof:placetype":"venue"
},
  "geometry": {"coordinates":[-71.117831,42.389192],"type":"Point"}
}