{
  "type": "Feature",
  "properties": {
    "iso:country":"US",
    "sg:address":"1200 Providence Hwy",
    "sg:city":"Walpole",
    "sg:classifiers":[
        {
            "category":"Home & Garden",
            "subcategory":"Building Materials",
            "type":"Retail Goods"
        }
    ],
    "sg:phone":"+1 781 762 8080",
    "sg:postcode":"02081",
    "sg:province":"MA",
    "sg:tags":[
        "supply"
    ],
    "wof:name":"General Builders Supply Co",
    "wof:placetype":"venue"
},
  "geometry": {"coordinates":[-71.246002,42.111401],"type":"Point"}
}