{
  "type": "Feature",
  "properties": {
    "addr:full": "1200 Providence Hwy Walpole MA 02081",
    "addr:housenumber": "1200",
    "addr:postcode": "02081",
    "addr:street": "Providence Hwy",
    "iso:country": "US",
    "sg:address": "1200 Providence Hwy",
    "sg:city": "Walpole",
    "sg:classifiers": [
      {
        "category": "Home \u0026 Garden",
        "subcategory": "Building Materials",
        "type": "Retail Goods"
      }
    ],
    "sg:phone": "+1 781 762 8080",
    "sg:postcode": "02081",
    "sg:province": "MA",
    "sg:tags": [
      "supply"
    ],
    "wof:name": "General Builders Supply Co",
    "wof:placetype": "venue"
  },
  "geometry": {"coordinates":[-71.246002,42.111401],"type":"Point"}
}
