{
  "type": "Feature",
  "properties": {
    "addr:full":"59 High Ridge Rd Boxford MA 01921",
    "addr:housenumber":"59",
    "addr:postcode":"01921",
    "addr:street":"High Ridge Rd",
    "iso:country":"US",
    "sg:address":"59 High Ridge Rd",
    "sg:city":"Boxford",
    "sg:classifiers":[
        {
            "category":"Building & Trades",
            "subcategory":"Plumbing",
            "type":"Services"
        }
    ],
    "sg:phone":"+1   ",
    "sg:postcode":"01921",
    "sg:province":"MA",
    "sg:tags":[
        "plumber"
    ],
    "wof:name":"Francis T Valeriani",
    "wof:placetype":"venue"
},
  "geometry": {"coordinates":[-71.007887,42.68304],"type":"Point"}
}