{
  "type": "Feature",
  "properties": {
    "addr:full":"29 Kirkwood Rd Brighton MA 02135",
    "addr:housenumber":"29",
    "addr:postcode":"02135",
    "addr:street":"Kirkwood Rd",
    "iso:country":"US",
    "sg:address":"29 Kirkwood Rd",
    "sg:city":"Brighton",
    "sg:classifiers":[
        {
            "category":"Building & Trades",
            "subcategory":"Locksmith",
            "type":"Services"
        }
    ],
    "sg:phone":"+1 617 415 9150",
    "sg:postcode":"02135",
    "sg:province":"MA",
    "sg:tags":[
        "key"
    ],
    "wof:name":"Emergency Locksmith Service Brig 24 A Day All Week",
    "wof:placetype":"venue"
},
  "geometry": {"coordinates":[-71.157124,42.341078],"type":"Point"}
}