{
  "type": "Feature",
  "properties": {
    "addr:full": "1191 Greendale Ave Needham MA 02492",
    "addr:housenumber": "1191",
    "addr:postcode": "02492",
    "addr:street": "Greendale Ave",
    "iso:country": "US",
    "ovtr:label": "St. Sebastian's School, 1191 Greendale Ave Needham MA US",
    "ovtr:similarity": 3.7265779972076416,
    "sg:address": "1191 Greendale Ave",
    "sg:city": "Needham",
    "sg:classifiers": [
      {
        "category": "Social Services",
        "subcategory": "Child Care",
        "type": "Services"
      },
      {
        "category": "Education",
        "subcategory": "School",
        "type": "Public Place"
      }
    ],
    "sg:phone": "+1 781 449 5200",
    "sg:postcode": "02492",
    "sg:province": "MA",
    "sg:tags": [
      "nursery",
      "private",
      "k-",
      "day"
    ],
    "sg:website": "http://www.stsebs.org",
    "wof:name": "St. Sebastian's School, Inc.",
    "wof:placetype": "venue"
  },
  "geometry": {"coordinates":[-71.205513,42.269202],"type":"Point"}
}
