{
  "type": "Feature",
  "properties": {
    "iso:country":"US",
    "sg:address":"1191 Greendale Ave",
    "sg:city":"Needham",
    "sg:classifiers":[
        {
            "category":"Social Services",
            "subcategory":"Child Care",
            "type":"Services"
        },
        {
            "category":"Education",
            "subcategory":"School",
            "type":"Public Place"
        }
    ],
    "sg:phone":"+1 781 449 5200",
    "sg:postcode":"02492",
    "sg:province":"MA",
    "sg:tags":[
        "nursery",
        "private",
        "k-",
        "day"
    ],
    "sg:website":"http://www.stsebs.org",
    "wof:name":"St. Sebastian's School, Inc.",
    "wof:placetype":"venue"
},
  "geometry": {"coordinates":[-71.205513,42.269202],"type":"Point"}
}