{
  "type": "Feature",
  "properties": {
    "iso:country":"US",
    "sg:address":"75 Wells Ave",
    "sg:city":"Newton",
    "sg:classifiers":[
        {
            "category":"Insurance",
            "subcategory":"Insurance Agent",
            "type":"Services"
        }
    ],
    "sg:phone":"+1 617 964 5416",
    "sg:postcode":"02459",
    "sg:province":"MA",
    "wof:name":"Farrelly Hammer & Smith",
    "wof:placetype":"venue"
},
  "geometry": {"coordinates":[-71.19874900000001,42.292278],"type":"Point"}
}