{
  "type": "Feature",
  "properties": {
    "iso:country":"US",
    "sg:address":"1 Beacon St",
    "sg:city":"Boston",
    "sg:classifiers":[
        {
            "category":"Sports & Exercise",
            "subcategory":"Gym",
            "type":"Entertainment"
        }
    ],
    "sg:phone":"+1 617 248 9797",
    "sg:postcode":"02108",
    "sg:province":"MA",
    "sg:tags":[
        "trainer"
    ],
    "sg:website":"www.fitcorp.com",
    "wof:name":"Fitcorp",
    "wof:placetype":"venue"
},
  "geometry": {"coordinates":[-71.060835,42.358449],"type":"Point"}
}