{
  "type": "Feature",
  "properties": {
    "addr:full": "94 Lessey St Amherst MA 01002",
    "addr:housenumber": "94",
    "addr:postcode": "01002",
    "addr:street": "Lessey St",
    "iso:country": "US",
    "sg:address": "94 Lessey St",
    "sg:city": "Amherst",
    "sg:classifiers": [
      {
        "category": "Education",
        "subcategory": "School",
        "type": "Public Place"
      }
    ],
    "sg:phone": "+1 413 253 2595",
    "sg:postcode": "01002",
    "sg:province": "MA",
    "wof:name": "Alexander Technique Schl Neng",
    "wof:placetype": "venue"
  },
  "geometry": {"coordinates":[-72.513469,42.377142],"type":"Point"}
}
