{
  "type": "Feature",
  "properties": {
    "addr:full": "54A Union Sq Somerville MA 02143",
    "addr:housenumber": "54a",
    "addr:postcode": "02143",
    "addr:street": "Union Sq",
    "iso:country": "US",
    "ovtr:label": "Union Square Smoke Shop, 54 Union Sq Somerville MA US",
    "ovtr:similarity": 2.8781230449676514,
    "sg:address": "54A Union Sq",
    "sg:city": "Somerville",
    "sg:classifiers": [
      {
        "category": "Shopping",
        "subcategory": "Tobacco",
        "type": "Retail Goods"
      }
    ],
    "sg:phone": "+1 617 776 6463",
    "sg:postcode": "02143",
    "sg:province": "MA",
    "sg:tags": [
      "shop"
    ],
    "wof:name": "Union Square Smoke Shop",
    "wof:placetype": "venue"
  },
  "geometry": {"coordinates":[-71.096389,42.379641],"type":"Point"}
}
