{
  "type": "Feature",
  "properties": {
    "iso:country":"US",
    "sg:address":"54A Union Sq",
    "sg:city":"Somerville",
    "sg:classifiers":[
        {
            "category":"Shopping",
            "subcategory":"Tobacco",
            "type":"Retail Goods"
        }
    ],
    "sg:phone":"+1 617 776 6463",
    "sg:postcode":"02143",
    "sg:province":"MA",
    "sg:tags":[
        "shop"
    ],
    "wof:name":"Union Square Smoke Shop",
    "wof:placetype":"venue"
},
  "geometry": {"coordinates":[-71.096389,42.379641],"type":"Point"}
}