{
  "type": "Feature",
  "properties": {
    "iso:country":"US",
    "sg:address":"58 Summer St",
    "sg:city":"Malden",
    "sg:classifiers":[
        {
            "category":"Personal",
            "subcategory":"Beauty Salon",
            "type":"Services"
        }
    ],
    "sg:phone":"+1 781 324 9771",
    "sg:postcode":"02148",
    "sg:province":"MA",
    "sg:tags":[
        "shop"
    ],
    "wof:name":"Shear Attention",
    "wof:placetype":"venue"
},
  "geometry": {"coordinates":[-71.07410900000001,42.429017],"type":"Point"}
}