{
  "type": "Feature",
  "properties": {
    "addr:full": "263 Cotuit Rd Sandwich MA 02563",
    "addr:housenumber": "263",
    "addr:postcode": "02563",
    "addr:street": "Cotuit Rd",
    "iso:country": "US",
    "sg:address": "263 Cotuit Rd",
    "sg:city": "Sandwich",
    "sg:classifiers": [
      {
        "category": "Restaurant",
        "type": "Food \u0026 Drink"
      }
    ],
    "sg:phone": "+1 508 477 4192",
    "sg:postcode": "02563",
    "sg:province": "MA",
    "wof:name": "Meetinghouse Package",
    "wof:placetype": "venue"
  },
  "geometry": {"coordinates":[-70.485541,41.705707],"type":"Point"}
}
