{
  "type": "Feature",
  "properties": {
    "iso:country":"US",
    "sg:address":"263 Cotuit Rd",
    "sg:city":"Sandwich",
    "sg:classifiers":[
        {
            "category":"Restaurant",
            "type":"Food & Drink"
        }
    ],
    "sg:phone":"+1 508 477 4192",
    "sg:postcode":"02563",
    "sg:province":"MA",
    "wof:name":"Meetinghouse Package",
    "wof:placetype":"venue"
},
  "geometry": {"coordinates":[-70.485541,41.705707],"type":"Point"}
}