{
  "type": "Feature",
  "properties": {
    "addr:full":"413 Boston Post Rd Weston MA 02493",
    "addr:housenumber":"413",
    "addr:postcode":"02493",
    "addr:street":"Boston Post Rd",
    "iso:country":"US",
    "sg:address":"413 Boston Post Rd",
    "sg:city":"Weston",
    "sg:classifiers":[
        {
            "category":"Professional",
            "subcategory":"Management & Consulting",
            "type":"Services"
        }
    ],
    "sg:phone":"+1 781 891 5342",
    "sg:postcode":"02493",
    "sg:province":"MA",
    "sg:tags":[
        "consultant",
        "business"
    ],
    "wof:name":"Andrea Bullard & Co",
    "wof:placetype":"venue"
},
  "geometry": {"coordinates":[-71.300468,42.367451],"type":"Point"}
}