{
  "type": "Feature",
  "properties": {
    "addr:full": "1250 Washington St Boston MA 02118",
    "addr:housenumber": "1250",
    "addr:postcode": "02118",
    "addr:street": "Washington St",
    "iso:country": "US",
    "sg:address": "1250 Washington St",
    "sg:city": "Boston",
    "sg:classifiers": [
      {
        "category": "Education",
        "subcategory": "Special Training",
        "type": "Public Place"
      }
    ],
    "sg:phone": "+1 617 988 6288",
    "sg:postcode": "02118",
    "sg:province": "MA",
    "sg:tags": [
      "instruction",
      "driving"
    ],
    "wof:name": "City Auto School",
    "wof:placetype": "venue"
  },
  "geometry": {"coordinates":[-71.067263,42.342604],"type":"Point"}
}
