{
  "type": "Feature",
  "properties": {
    "iso:country":"US",
    "sg:address":"29 Brooklawn Rd",
    "sg:city":"Wilbraham",
    "sg:classifiers":[
        {
            "category":"Building & Trades",
            "subcategory":"Electrical",
            "type":"Services"
        }
    ],
    "sg:phone":"+1 413 599 0110",
    "sg:postcode":"01095",
    "sg:province":"MA",
    "sg:tags":[
        "electric",
        "contractor"
    ],
    "wof:name":"Norman LA Chance Electric",
    "wof:placetype":"venue"
},
  "geometry": {"coordinates":[-72.47350900000001,42.122789],"type":"Point"}
}