{
  "type": "Feature",
  "properties": {
    "addr:full": "43 Forest Ave Everett MA 02149",
    "addr:housenumber": "43",
    "addr:postcode": "02149",
    "addr:street": "Forest Ave",
    "iso:country": "US",
    "sg:address": "43 Forest Ave",
    "sg:city": "Everett",
    "sg:classifiers": [
      {
        "category": "Building \u0026 Trades",
        "subcategory": "Electrical",
        "type": "Services"
      }
    ],
    "sg:phone": "+1   ",
    "sg:postcode": "02149",
    "sg:province": "MA",
    "sg:tags": [
      "electrical",
      "contractor"
    ],
    "wof:name": "Desario Electric",
    "wof:placetype": "venue"
  },
  "geometry": {"coordinates":[-71.060929,42.407893],"type":"Point"}
}
