{
  "type": "Feature",
  "properties": {
    "addr:full":"8 N Hoosac St Adams MA 01220",
    "addr:housenumber":"8",
    "addr:postcode":"01220",
    "addr:street":"N Hoosac St",
    "iso:country":"US",
    "sg:address":"8 N Hoosac St",
    "sg:city":"Adams",
    "sg:classifiers":[
        {
            "category":"Manufacturing",
            "subcategory":"Metals",
            "type":"Manufacturing & Wholesale Goods"
        },
        {
            "category":"Building & Trades",
            "subcategory":"Construction",
            "type":"Services"
        },
        {
            "category":"Manufacturing",
            "subcategory":"Building Materials",
            "type":"Manufacturing & Wholesale Goods"
        }
    ],
    "sg:phone":"+1 413 743 3282",
    "sg:postcode":"01220",
    "sg:province":"MA",
    "sg:tags":[
        "roofing",
        "industrial",
        "sheet",
        "work",
        "contractor",
        "contractors-commercial",
        "work-manufacturers",
        "fabricator"
    ],
    "wof:name":"David Kittler",
    "wof:placetype":"venue"
},
  "geometry": {"coordinates":[-73.114413,42.625106],"type":"Point"}
}