{
  "type": "Feature",
  "properties": {
    "addr:full":"126 Royalston Rd Templeton MA 01436",
    "addr:housenumber":"126",
    "addr:postcode":"01436",
    "addr:street":"Royalston Rd",
    "iso:country":"US",
    "sg:address":"126 Royalston Rd",
    "sg:city":"Templeton",
    "sg:classifiers":[
        {
            "category":"Organizations",
            "subcategory":"Labor Organization",
            "type":"Services"
        }
    ],
    "sg:phone":"+1 978 939 2019",
    "sg:postcode":"01436",
    "sg:province":"MA",
    "wof:name":"AFSCME 554",
    "wof:placetype":"venue"
},
  "geometry": {"coordinates":[-72.096872,42.604061],"type":"Point"}
}