{
  "type": "Feature",
  "properties": {
    "iso:country":"US",
    "sg:address":"110 K St Ste 3",
    "sg:city":"Boston",
    "sg:classifiers":[
        {
            "category":"Building & Trades",
            "subcategory":"Electrical",
            "type":"Services"
        }
    ],
    "sg:phone":"+1 617 269 2242",
    "sg:postcode":"02127",
    "sg:province":"MA",
    "sg:tags":[
        "electrician"
    ],
    "wof:name":"Mgm Electric Co., Inc.",
    "wof:placetype":"venue"
},
  "geometry": {"coordinates":[-71.03759700000001,42.338517],"type":"Point"}
}