{
  "type": "Feature",
  "properties": {
    "iso:country":"US",
    "sg:address":"443 Webster St",
    "sg:city":"Rockland",
    "sg:classifiers":[
        {
            "category":"Manufacturing",
            "subcategory":"Apparel",
            "type":"Manufacturing & Wholesale Goods"
        }
    ],
    "sg:phone":"+1 781 871 3133",
    "sg:postcode":"02370",
    "sg:province":"MA",
    "sg:tags":[
        "flag",
        "banner"
    ],
    "wof:name":"America's Flag Co",
    "wof:placetype":"venue"
},
  "geometry": {"coordinates":[-70.901629,42.136666],"type":"Point"}
}