{
  "type": "Feature",
  "properties": {
    "addr:full": "443 Webster St Rockland MA 02370",
    "addr:housenumber": "443",
    "addr:postcode": "02370",
    "addr:street": "Webster St",
    "iso:country": "US",
    "sg:address": "443 Webster St",
    "sg:city": "Rockland",
    "sg:classifiers": [
      {
        "category": "Manufacturing",
        "subcategory": "Apparel",
        "type": "Manufacturing \u0026 Wholesale Goods"
      }
    ],
    "sg:phone": "+1 781 871 3133",
    "sg:postcode": "02370",
    "sg:province": "MA",
    "sg:tags": [
      "flag",
      "banner"
    ],
    "wof:name": "America's Flag Co",
    "wof:placetype": "venue"
  },
  "geometry": {"coordinates":[-70.901629,42.136666],"type":"Point"}
}
