{
  "type": "Feature",
  "properties": {
    "addr:full":"295 Bullard St Walpole MA 02081",
    "addr:housenumber":"295",
    "addr:postcode":"02081",
    "addr:street":"Bullard St",
    "iso:country":"US",
    "sg:address":"295 Bullard St",
    "sg:city":"Walpole",
    "sg:classifiers":[
        {
            "category":"Professional",
            "subcategory":"Business Services",
            "type":"Services"
        }
    ],
    "sg:phone":"+1   ",
    "sg:postcode":"02081",
    "sg:province":"MA",
    "wof:name":"Affordable Business MGT Svcs",
    "wof:placetype":"venue"
},
  "geometry": {"coordinates":[-71.230836,42.17614],"type":"Point"}
}