{
  "type": "Feature",
  "properties": {
    "addr:full": "270 Communication Way Hyannis MA 02601",
    "addr:housenumber": "270",
    "addr:postcode": "02601",
    "addr:street": "Communication Way",
    "iso:country": "US",
    "sg:address": "270 Communication Way",
    "sg:city": "Hyannis",
    "sg:classifiers": [
      {
        "category": "Government",
        "subcategory": "Office",
        "type": "Public Place"
      }
    ],
    "sg:phone": "+1 508 771 2595",
    "sg:postcode": "02601",
    "sg:province": "MA",
    "sg:tags": [
      "state",
      "program",
      "health"
    ],
    "wof:name": "Mental Retardation Dept",
    "wof:placetype": "venue"
  },
  "geometry": {"coordinates":[-70.293595,41.683189],"type":"Point"}
}
