{
  "type": "Feature",
  "properties": {
    "addr:full":"540 Shore Rd Truro MA 02652",
    "addr:housenumber":"540",
    "addr:postcode":"02652",
    "addr:street":"Shore Rd",
    "iso:country":"US",
    "sg:address":"540 Shore Rd",
    "sg:city":"Truro",
    "sg:classifiers":[
        {
            "category":"Travel",
            "subcategory":"Hotels & Motels",
            "type":"Entertainment"
        }
    ],
    "sg:phone":"+1 508 487 2122",
    "sg:postcode":"02652",
    "sg:province":"MA",
    "sg:tags":[
        "cottage",
        "cabin"
    ],
    "wof:name":"Ebb Tide On The Bay",
    "wof:placetype":"venue"
},
  "geometry": {"coordinates":[-70.141229,42.05999],"type":"Point"}
}