{
  "type": "Feature",
  "properties": {
    "iso:country":"US",
    "sg:address":"59 Federal St",
    "sg:city":"Salem",
    "sg:classifiers":[
        {
            "category":"Professional",
            "subcategory":"Lawyer & Legal Services",
            "type":"Services"
        }
    ],
    "sg:phone":"+1 978 745 7456",
    "sg:postcode":"01970",
    "sg:province":"MA",
    "sg:tags":[
        "attorney"
    ],
    "wof:name":"Michael J Eschelbacher",
    "wof:placetype":"venue"
},
  "geometry": {"coordinates":[-70.897655,42.522928],"type":"Point"}
}