{
  "type": "Feature",
  "properties": {
    "iso:country":"US",
    "sg:address":"139 Mechanic St",
    "sg:city":"Bellingham",
    "sg:classifiers":[
        {
            "category":"Professional",
            "subcategory":"Business Services",
            "type":"Services"
        }
    ],
    "sg:phone":"+1 508 966 4101",
    "sg:postcode":"02019",
    "sg:province":"MA",
    "sg:tags":[
        "paralegal"
    ],
    "wof:name":"Badzmierowski Services",
    "wof:placetype":"venue"
},
  "geometry": {"coordinates":[-71.464298,42.08158],"type":"Point"}
}