{
  "type": "Feature",
  "properties": {
    "addr:full":"49 Hemlock Rd Sudbury MA 01776",
    "addr:housenumber":"49",
    "addr:postcode":"01776",
    "addr:street":"Hemlock Rd",
    "iso:country":"US",
    "sg:address":"49 Hemlock Rd",
    "sg:city":"Sudbury",
    "sg:classifiers":[
        {
            "category":"Organizations",
            "subcategory":"Community Association",
            "type":"Services"
        }
    ],
    "sg:phone":"+1 978 443 8787",
    "sg:postcode":"01776",
    "sg:province":"MA",
    "sg:tags":[
        "club"
    ],
    "wof:name":"Sudbury Swim Tennis Club",
    "wof:placetype":"venue"
},
  "geometry": {"coordinates":[-71.447394,42.378148],"type":"Point"}
}