{
  "type": "Feature",
  "properties": {
    "addr:full":"209 Page Blvd Springfield MA 01104",
    "addr:housenumber":"209",
    "addr:postcode":"01104",
    "addr:street":"Page Blvd",
    "iso:country":"US",
    "sg:address":"209 Page Blvd",
    "sg:city":"Springfield",
    "sg:classifiers":[
        {
            "category":"Manufacturing",
            "subcategory":"Metals",
            "type":"Manufacturing & Wholesale Goods"
        }
    ],
    "sg:phone":"+1 413 733 2121",
    "sg:postcode":"01104",
    "sg:province":"MA",
    "sg:tags":[
        "steel",
        "processing"
    ],
    "wof:name":"Charles C Lewis Co",
    "wof:placetype":"venue"
},
  "geometry": {"coordinates":[-72.563288,42.130829],"type":"Point"}
}