{
  "type": "Feature",
  "properties": {
    "addr:full":"23 Auburn St Waltham MA 02453",
    "addr:housenumber":"23",
    "addr:postcode":"02453",
    "addr:street":"Auburn St",
    "iso:country":"US",
    "sg:address":"23 Auburn St",
    "sg:city":"Waltham",
    "sg:classifiers":[
        {
            "category":"Wholesale",
            "subcategory":"Construction Materials",
            "type":"Manufacturing & Wholesale Goods"
        }
    ],
    "sg:phone":"+1 781 899 6475",
    "sg:postcode":"02453",
    "sg:province":"MA",
    "sg:tags":[
        "fence"
    ],
    "wof:name":"Custom Made Fences",
    "wof:placetype":"venue"
},
  "geometry": {"coordinates":[-71.25106700000001,42.374273],"type":"Point"}
}