{
  "type": "Feature",
  "properties": {
    "addr:full": "235 Hanover St Ste 1 Hanover MA 02339",
    "addr:housenumber": "235",
    "addr:postcode": "02339",
    "addr:street": "Hanover St Ste 1",
    "iso:country": "US",
    "sg:address": "235 Hanover St Ste 1",
    "sg:city": "Hanover",
    "sg:classifiers": [
      {
        "category": "Professional",
        "subcategory": "Testing Lab",
        "type": "Services"
      },
      {
        "category": "Health Services",
        "subcategory": "Medical Lab",
        "type": "Services"
      }
    ],
    "sg:phone": "+1 781 826 7321",
    "sg:postcode": "02339",
    "sg:province": "MA",
    "sg:tags": [
      "laboratory",
      "dental"
    ],
    "wof:name": "Sun Dental Lab",
    "wof:placetype": "venue"
  },
  "geometry": {"coordinates":[-70.830258,42.114655],"type":"Point"}
}
