{
  "type": "Feature",
  "properties": {
    "iso:country":"US",
    "sg:address":"647 Boylston St # 2",
    "sg:city":"Boston",
    "sg:classifiers":[
        {
            "category":"Education",
            "subcategory":"Special Training",
            "type":"Public Place"
        }
    ],
    "sg:phone":"+1 617 262 2949",
    "sg:postcode":"02116",
    "sg:province":"MA",
    "sg:tags":[
        "school",
        "art"
    ],
    "wof:name":"The Cloud Foundation",
    "wof:placetype":"venue"
},
  "geometry": {"coordinates":[-71.07759900000001,42.349899],"type":"Point"}
}