{
  "type": "Feature",
  "properties": {
    "addr:full":"150 Worcester Rd Framingham MA 01702",
    "addr:housenumber":"150",
    "addr:postcode":"01702",
    "addr:street":"Worcester Rd",
    "iso:country":"US",
    "sg:address":"150 Worcester Rd",
    "sg:city":"Framingham",
    "sg:classifiers":[
        {
            "category":"Utilities",
            "subcategory":"Mobile Phone",
            "type":"Services"
        }
    ],
    "sg:phone":"+1 508 879 7477",
    "sg:postcode":"01702",
    "sg:province":"MA",
    "sg:tags":[
        "telephone",
        "cellular"
    ],
    "wof:name":"T-Mobile",
    "wof:placetype":"venue"
},
  "geometry": {"coordinates":[-71.403503,42.298412],"type":"Point"}
}