{
  "type": "Feature",
  "properties": {
    "iso:country":"US",
    "sg:address":"3 Kimball Ln",
    "sg:city":"Northborough",
    "sg:classifiers":[
        {
            "category":"Professional",
            "subcategory":"Secretarial Services",
            "type":"Services"
        }
    ],
    "sg:phone":"+1 508 393 3877",
    "sg:postcode":"01532",
    "sg:province":"MA",
    "sg:tags":[
        "reporting"
    ],
    "wof:name":"Word Processing Etc",
    "wof:placetype":"venue"
},
  "geometry": {"coordinates":[-71.623454,42.303037],"type":"Point"}
}