{
  "type": "Feature",
  "properties": {
    "iso:country":"US",
    "sg:address":"16 Waterhouse Rd",
    "sg:city":"Buzzards Bay",
    "sg:classifiers":[
        {
            "category":"Real Estate",
            "subcategory":"Real Estate Agent",
            "type":"Services"
        }
    ],
    "sg:phone":"+1 508 759 1188",
    "sg:postcode":"02532",
    "sg:province":"MA",
    "wof:name":"Cheli Properties",
    "wof:placetype":"venue"
},
  "geometry": {"coordinates":[-70.597656,41.739951],"type":"Point"}
}