{
  "type": "Feature",
  "properties": {
    "iso:country":"US",
    "sg:address":"61 Cheshire Rd",
    "sg:city":"Pittsfield",
    "sg:classifiers":[
        {
            "category":"Restaurant",
            "type":"Food & Drink"
        }
    ],
    "sg:menulink":"http://www.allmenus.com/ma/pittsfield/185292-mcdonalds/menu/",
    "sg:phone":"+1 413 442 4602",
    "sg:postcode":"01201",
    "sg:province":"MA",
    "sg:tags":[
        "burger",
        "american"
    ],
    "wof:name":"McDonald's",
    "wof:placetype":"venue"
},
  "geometry": {"coordinates":[-73.20386499999999,42.470485],"type":"Point"}
}