{
  "type": "Feature",
  "properties": {
    "iso:country":"US",
    "sg:address":"59 Depot Ave",
    "sg:city":"Falmouth",
    "sg:classifiers":[
        {
            "category":"Local Transit",
            "type":"Transportation"
        }
    ],
    "sg:phone":"+1 508 548 7588",
    "sg:postcode":"02540",
    "sg:province":"MA",
    "sg:tags":[
        "bus",
        "line"
    ],
    "wof:name":"Bonanza Bus Lines Inc",
    "wof:placetype":"venue"
},
  "geometry": {"coordinates":[-70.62333700000001,41.556458],"type":"Point"}
}