{
  "type": "Feature",
  "properties": {
    "iso:country":"US",
    "sg:address":"24 Newbury St",
    "sg:city":"Danvers",
    "sg:classifiers":[
        {
            "category":"Professional",
            "subcategory":"Business Services",
            "type":"Services"
        }
    ],
    "sg:phone":"+1   ",
    "sg:postcode":"01923",
    "sg:province":"MA",
    "wof:name":"Pool Masters Inc",
    "wof:placetype":"venue"
},
  "geometry": {"coordinates":[-70.97856899999999,42.557548],"type":"Point"}
}