{
  "type": "Feature",
  "properties": {
    "addr:full":"49 Millbury St Worcester MA 01610",
    "addr:housenumber":"49",
    "addr:postcode":"01610",
    "addr:street":"Millbury St",
    "iso:country":"US",
    "sg:address":"49 Millbury St",
    "sg:city":"Worcester",
    "sg:classifiers":[
        {
            "category":"Restaurant",
            "type":"Food & Drink"
        }
    ],
    "sg:phone":"+1 508 792 3830",
    "sg:postcode":"01610",
    "sg:province":"MA",
    "wof:name":"Emerald Isle",
    "wof:placetype":"venue"
},
  "geometry": {"coordinates":[-71.798625,42.253393],"type":"Point"}
}