{
  "type": "Feature",
  "properties": {
    "addr:full":"11 Freeport Dr Burlington MA 01803",
    "addr:housenumber":"11",
    "addr:postcode":"01803",
    "addr:street":"Freeport Dr",
    "iso:country":"US",
    "sg:address":"11 Freeport Dr",
    "sg:city":"Burlington",
    "sg:classifiers":[
        {
            "category":"Professional",
            "subcategory":"Business Services",
            "type":"Services"
        }
    ],
    "sg:phone":"+1   ",
    "sg:postcode":"01803",
    "sg:province":"MA",
    "sg:tags":[
        "construction",
        "b",
        "sales",
        "package"
    ],
    "wof:name":"MJB-Eagles Nest Homes Inc",
    "wof:placetype":"venue"
},
  "geometry": {"coordinates":[-71.18724400000001,42.522234],"type":"Point"}
}