{
  "type": "Feature",
  "properties": {
    "iso:country":"US",
    "sg:address":"324 Waverly St",
    "sg:city":"Framingham",
    "sg:classifiers":[
        {
            "category":"Autos & Motor Vehicles",
            "subcategory":"Fuel & Gas Station",
            "type":"Retail Goods"
        }
    ],
    "sg:phone":"+1 508 875 3562",
    "sg:postcode":"01702",
    "sg:province":"MA",
    "sg:tags":[
        "oil"
    ],
    "wof:name":"K & P Svc Inc",
    "wof:placetype":"venue"
},
  "geometry": {"coordinates":[-71.41566899999999,42.276976],"type":"Point"}
}