{
  "type": "Feature",
  "properties": {
    "iso:country":"US",
    "sg:address":"42 Arcadia Ave",
    "sg:city":"Waltham",
    "sg:classifiers":[
        {
            "category":"Building & Trades",
            "subcategory":"Construction",
            "type":"Services"
        }
    ],
    "sg:phone":"+1   ",
    "sg:postcode":"02452",
    "sg:province":"MA",
    "sg:tags":[
        "house"
    ],
    "wof:name":"Center Line Construction",
    "wof:placetype":"venue"
},
  "geometry": {"coordinates":[-71.20381,42.396989],"type":"Point"}
}