{
  "type": "Feature",
  "properties": {
    "iso:country":"US",
    "sg:address":"2409 Massachusetts Avenue",
    "sg:city":"Cambridge",
    "sg:classifiers":[
        {
            "category":"Professional",
            "subcategory":"Lawyer & Legal Services",
            "type":"Services"
        }
    ],
    "sg:phone":"+1 617 354 7200",
    "sg:postcode":"02140",
    "sg:province":"MA",
    "wof:name":"Paratore Fitzgerald & Favorat PC",
    "wof:placetype":"venue"
},
  "geometry": {"coordinates":[-71.130465,42.397486],"type":"Point"}
}