{
  "type": "Feature",
  "properties": {
    "addr:full": "47 Meadowlark Ln Springfield MA 01119",
    "addr:housenumber": "47",
    "addr:postcode": "01119",
    "addr:street": "Meadowlark Ln",
    "iso:country": "US",
    "sg:address": "47 Meadowlark Ln",
    "sg:city": "Springfield",
    "sg:classifiers": [
      {
        "category": "Building \u0026 Trades",
        "subcategory": "Plumbing",
        "type": "Services"
      }
    ],
    "sg:phone": "+1 413 783 9344",
    "sg:postcode": "01119",
    "sg:province": "MA",
    "sg:tags": [
      "plumbing",
      "contractor"
    ],
    "wof:name": "Bob Stevens Plumbing \u0026 Heating",
    "wof:placetype": "venue"
  },
  "geometry": {"coordinates":[-72.512465,42.123466],"type":"Point"}
}
