{
  "type": "Feature",
  "properties": {
    "iso:country":"US",
    "sg:address":"13 Taunton St",
    "sg:city":"Plainville",
    "sg:classifiers":[
        {
            "category":"Restaurant",
            "type":"Food & Drink"
        }
    ],
    "sg:menulink":"http://www.allmenus.com/ma/plainville/131748-subway/menu/",
    "sg:phone":"+1 508 699 0998",
    "sg:postcode":"02762",
    "sg:province":"MA",
    "sg:tags":[
        "american",
        "sandwich"
    ],
    "wof:name":"Subway",
    "wof:placetype":"venue"
},
  "geometry": {"coordinates":[-71.305971,42.011151],"type":"Point"}
}