{
  "type": "Feature",
  "properties": {
    "addr:full": "13 Taunton St Plainville MA 02762",
    "addr:housenumber": "13",
    "addr:postcode": "02762",
    "addr:street": "Taunton St",
    "iso:country": "US",
    "sg:address": "13 Taunton St",
    "sg:city": "Plainville",
    "sg:classifiers": [
      {
        "category": "Restaurant",
        "type": "Food \u0026 Drink"
      }
    ],
    "sg:menulink": "http://www.allmenus.com/ma/plainville/131748-subway/menu/",
    "sg:phone": "+1 508 699 0998",
    "sg:postcode": "02762",
    "sg:province": "MA",
    "sg:tags": [
      "american",
      "sandwich"
    ],
    "wof:name": "Subway",
    "wof:placetype": "venue"
  },
  "geometry": {"coordinates":[-71.305971,42.011151],"type":"Point"}
}
