{
  "type": "Feature",
  "properties": {
    "addr:full":"5 Phillips Cir Westford MA 01886",
    "addr:housenumber":"5",
    "addr:postcode":"01886",
    "addr:street":"Phillips Cir",
    "iso:country":"US",
    "sg:address":"5 Phillips Cir",
    "sg:city":"Westford",
    "sg:classifiers":[
        {
            "category":"Building & Trades",
            "subcategory":"Plumbing",
            "type":"Services"
        }
    ],
    "sg:phone":"+1 978 692 4023",
    "sg:postcode":"01886",
    "sg:province":"MA",
    "sg:tags":[
        "contractor"
    ],
    "wof:name":"Joseph W Regan Plumbing & Htg",
    "wof:placetype":"venue"
},
  "geometry": {"coordinates":[-71.452645,42.56047],"type":"Point"}
}