{
  "type": "Feature",
  "properties": {
    "addr:full":"1542 N Main St Fall River MA 02720",
    "addr:housenumber":"1542",
    "addr:postcode":"02720",
    "addr:street":"N Main St",
    "iso:country":"US",
    "sg:address":"1542 N Main St",
    "sg:city":"Fall River",
    "sg:classifiers":[
        {
            "category":"Personal",
            "subcategory":"Barber",
            "type":"Services"
        }
    ],
    "sg:phone":"+1 508 673 0073",
    "sg:postcode":"02720",
    "sg:province":"MA",
    "wof:name":"Trendsetters Barber",
    "wof:placetype":"venue"
},
  "geometry": {"coordinates":[-71.146113,41.720784],"type":"Point"}
}