{
  "type": "Feature",
  "properties": {
    "iso:country":"US",
    "sg:address":"466 Main St",
    "sg:city":"Stoneham",
    "sg:classifiers":[
        {
            "category":"Retail",
            "subcategory":"Animal Services",
            "type":"Services"
        }
    ],
    "sg:phone":"+1 781 279 4762",
    "sg:postcode":"02180",
    "sg:province":"MA",
    "wof:name":"Clipper Corner",
    "wof:placetype":"venue"
},
  "geometry": {"coordinates":[-71.100497,42.476156],"type":"Point"}
}