{
  "type": "Feature",
  "properties": {
    "iso:country":"US",
    "sg:address":"108 Newburyport Tpke",
    "sg:city":"Rowley",
    "sg:classifiers":[
        {
            "category":"Retail",
            "subcategory":"Animal Services",
            "type":"Services"
        }
    ],
    "sg:phone":"+1 978 948 5353",
    "sg:postcode":"01969",
    "sg:province":"MA",
    "sg:tags":[
        "pet",
        "training"
    ],
    "wof:name":"Canine Consulting Training Ctr",
    "wof:placetype":"venue"
},
  "geometry": {"coordinates":[-70.911102,42.700285],"type":"Point"}
}