{
  "type": "Feature",
  "properties": {
    "iso:country":"US",
    "sg:address":"206 White St",
    "sg:city":"Lowell",
    "sg:classifiers":[
        {
            "category":"Personal",
            "subcategory":"Beauty Salon",
            "type":"Services"
        }
    ],
    "sg:phone":"+1   ",
    "sg:postcode":"01854",
    "sg:province":"MA",
    "sg:tags":[
        "shop"
    ],
    "wof:name":"Chantels Hair Styling",
    "wof:placetype":"venue"
},
  "geometry": {"coordinates":[-71.32847700000001,42.656241],"type":"Point"}
}