{
  "type": "Feature",
  "properties": {
    "iso:country":"US",
    "sg:address":"420 Cooley St",
    "sg:city":"Springfield",
    "sg:classifiers":[
        {
            "category":"Shopping",
            "subcategory":"Department Store",
            "type":"Retail Goods"
        }
    ],
    "sg:phone":"+1 413 782 7300",
    "sg:postcode":"01128",
    "sg:province":"MA",
    "sg:tags":[
        "shop"
    ],
    "wof:name":"Big Lots",
    "wof:placetype":"venue"
},
  "geometry": {"coordinates":[-72.499099,42.093874],"type":"Point"}
}