{
  "type": "Feature",
  "properties": {
    "addr:full": "420 Cooley St Springfield MA 01128",
    "addr:housenumber": "420",
    "addr:postcode": "01128",
    "addr:street": "Cooley St",
    "iso:country": "US",
    "ovtr:label": "Big Lots, 390 Cooley St Springfield MA US",
    "ovtr:similarity": 3.5711119174957275,
    "sg:address": "420 Cooley St",
    "sg:city": "Springfield",
    "sg:classifiers": [
      {
        "category": "Shopping",
        "subcategory": "Department Store",
        "type": "Retail Goods"
      }
    ],
    "sg:phone": "+1 413 782 7300",
    "sg:postcode": "01128",
    "sg:province": "MA",
    "sg:tags": [
      "shop"
    ],
    "wof:name": "Big Lots",
    "wof:placetype": "venue"
  },
  "geometry": {"coordinates":[-72.499099,42.093874],"type":"Point"}
}
