{
  "type": "Feature",
  "properties": {
    "iso:country":"US",
    "sg:address":"904 Meadow St",
    "sg:city":"Chicopee",
    "sg:classifiers":[
        {
            "category":"Wholesale",
            "subcategory":"Electrical",
            "type":"Manufacturing & Wholesale Goods"
        }
    ],
    "sg:phone":"+1 413 592 4554",
    "sg:postcode":"01013",
    "sg:province":"MA",
    "sg:tags":[
        "communication",
        "radio",
        "system"
    ],
    "wof:name":"Tower Communications Co",
    "wof:placetype":"venue"
},
  "geometry": {"coordinates":[-72.61387499999999,42.162061],"type":"Point"}
}