{
  "type": "Feature",
  "properties": {
    "iso:country":"US",
    "sg:address":"10 Railroad St",
    "sg:city":"Abington",
    "sg:classifiers":[
        {
            "category":"Shopping",
            "subcategory":"Gifts & Souvenirs",
            "type":"Retail Goods"
        }
    ],
    "sg:phone":"+1 781 878 5151",
    "sg:postcode":"02351",
    "sg:province":"MA",
    "sg:tags":[
        "greeting",
        "card"
    ],
    "wof:name":"New England Art Store",
    "wof:placetype":"venue"
},
  "geometry": {"coordinates":[-70.94102700000001,42.126522],"type":"Point"}
}