{
  "type": "Feature",
  "properties": {
    "addr:full": "25 Belmont Ave Stoughton MA 02072",
    "addr:housenumber": "25",
    "addr:postcode": "02072",
    "addr:street": "Belmont Ave",
    "iso:country": "US",
    "sg:address": "25 Belmont Ave",
    "sg:city": "Stoughton",
    "sg:classifiers": [
      {
        "category": "Building \u0026 Trades",
        "subcategory": "Construction",
        "type": "Services"
      }
    ],
    "sg:phone": "+1 781 341 1886",
    "sg:postcode": "02072",
    "sg:province": "MA",
    "sg:tags": [
      "wallcoverings-installation",
      "wallpaper",
      "painting",
      "contractor"
    ],
    "wof:name": "Visser Painting Inc.",
    "wof:placetype": "venue"
  },
  "geometry": {"coordinates":[-71.088934,42.118971],"type":"Point"}
}
