{
  "type": "Feature",
  "properties": {
    "iso:country":"US",
    "sg:address":"861 Ashley Blvd",
    "sg:city":"New Bedford",
    "sg:classifiers":[
        {
            "category":"Shopping",
            "subcategory":"Florist",
            "type":"Retail Goods"
        }
    ],
    "sg:phone":"+1 508 998 5252",
    "sg:postcode":"02745",
    "sg:province":"MA",
    "wof:name":"Potting Bench",
    "wof:placetype":"venue"
},
  "geometry": {"coordinates":[-70.934229,41.683718],"type":"Point"}
}