{
  "type": "Feature",
  "properties": {
    "addr:full":"161 Granite Ave Dorchester Ctr MA 02124",
    "addr:housenumber":"161",
    "addr:postcode":"02124",
    "addr:street":"Granite Ave Dorchester Ctr",
    "iso:country":"US",
    "sg:address":"161 Granite Ave",
    "sg:city":"Dorchester Ctr",
    "sg:classifiers":[
        {
            "category":"Professional",
            "subcategory":"Lawyer & Legal Services",
            "type":"Services"
        }
    ],
    "sg:phone":"+1 617 740 9898",
    "sg:postcode":"02124",
    "sg:province":"MA",
    "sg:tags":[
        "attorney"
    ],
    "wof:name":"Thomas E Finnerty Jr Attorney",
    "wof:placetype":"venue"
},
  "geometry": {"coordinates":[-71.054107,42.278629],"type":"Point"}
}