{
  "type": "Feature",
  "properties": {
    "addr:full":"1600 Providence Hwy Walpole MA 02081",
    "addr:housenumber":"1600",
    "addr:postcode":"02081",
    "addr:street":"Providence Hwy",
    "iso:country":"US",
    "sg:address":"1600 Providence Hwy",
    "sg:city":"Walpole",
    "sg:classifiers":[
        {
            "category":"Shopping",
            "subcategory":"Photographic Equipment",
            "type":"Retail Goods"
        }
    ],
    "sg:phone":"+1   ",
    "sg:postcode":"02081",
    "sg:province":"MA",
    "sg:tags":[
        "camera",
        "technology",
        "infrared"
    ],
    "wof:name":"Ir Cameras Northeast Inc",
    "wof:placetype":"venue"
},
  "geometry": {"coordinates":[-71.237831,42.116063],"type":"Point"}
}