{
  "type": "Feature",
  "properties": {
    "addr:full":"281 Middleton Rd Boxford MA 01921",
    "addr:housenumber":"281",
    "addr:postcode":"01921",
    "addr:street":"Middleton Rd",
    "iso:country":"US",
    "sg:address":"281 Middleton Rd",
    "sg:city":"Boxford",
    "sg:classifiers":[
        {
            "category":"Shopping",
            "subcategory":"Bicycles & Sporting Goods",
            "type":"Retail Goods"
        }
    ],
    "sg:phone":"+1 978 887 1313",
    "sg:postcode":"01921",
    "sg:province":"MA",
    "sg:website":"www.mclub.com",
    "wof:name":"Master Club",
    "wof:placetype":"venue"
},
  "geometry": {"coordinates":[-70.979465,42.634622],"type":"Point"}
}