{
  "type": "Feature",
  "properties": {
    "iso:country":"US",
    "sg:address":"130 Horse Pond Rd",
    "sg:city":"Sudbury",
    "sg:classifiers":[
        {
            "category":"Building & Trades",
            "subcategory":"Plumbing",
            "type":"Services"
        }
    ],
    "sg:phone":"+1 978 440 8181",
    "sg:postcode":"01776",
    "sg:province":"MA",
    "sg:tags":[
        "plumbing",
        "contractor"
    ],
    "wof:name":"A & L Plumbing & Heating",
    "wof:placetype":"venue"
},
  "geometry": {"coordinates":[-71.437116,42.370334],"type":"Point"}
}