{
  "type": "Feature",
  "properties": {
    "addr:full": "130 Horse Pond Rd Sudbury MA 01776",
    "addr:housenumber": "130",
    "addr:postcode": "01776",
    "addr:street": "Horse Pond Rd",
    "iso:country": "US",
    "sg:address": "130 Horse Pond Rd",
    "sg:city": "Sudbury",
    "sg:classifiers": [
      {
        "category": "Building \u0026 Trades",
        "subcategory": "Plumbing",
        "type": "Services"
      }
    ],
    "sg:phone": "+1 978 440 8181",
    "sg:postcode": "01776",
    "sg:province": "MA",
    "sg:tags": [
      "plumbing",
      "contractor"
    ],
    "wof:name": "A \u0026 L Plumbing \u0026 Heating",
    "wof:placetype": "venue"
  },
  "geometry": {"coordinates":[-71.437116,42.370334],"type":"Point"}
}
