{
  "type": "Feature",
  "properties": {
    "addr:full": "1124 Pleasant St 26 Worcester MA 01602",
    "addr:housenumber": "1124;26",
    "addr:postcode": "01602",
    "addr:street": "Pleasant St",
    "iso:country": "US",
    "sg:address": "1124 Pleasant St 26",
    "sg:city": "Worcester",
    "sg:classifiers": [
      {
        "category": "Home \u0026 Garden",
        "subcategory": "Hardware",
        "type": "Retail Goods"
      }
    ],
    "sg:phone": "+1 508 721 9519",
    "sg:postcode": "01602",
    "sg:province": "MA",
    "sg:tags": [
      "store"
    ],
    "wof:name": "Alan-Barry Servi Star",
    "wof:placetype": "venue"
  },
  "geometry": {"coordinates":[-71.853592,42.27829],"type":"Point"}
}
