{
  "type": "Feature",
  "properties": {
    "iso:country":"US",
    "sg:address":"1124 Pleasant St 26",
    "sg:city":"Worcester",
    "sg:classifiers":[
        {
            "category":"Home & Garden",
            "subcategory":"Hardware",
            "type":"Retail Goods"
        }
    ],
    "sg:phone":"+1 508 721 9519",
    "sg:postcode":"01602",
    "sg:province":"MA",
    "sg:tags":[
        "store"
    ],
    "wof:name":"Alan-Barry Servi Star",
    "wof:placetype":"venue"
},
  "geometry": {"coordinates":[-71.85359200000001,42.27829],"type":"Point"}
}