{
  "type": "Feature",
  "properties": {
    "addr:full": "8 Pearl St Provincetown MA 02657",
    "addr:housenumber": "8",
    "addr:postcode": "02657",
    "addr:street": "Pearl St",
    "iso:country": "US",
    "sg:address": "8 Pearl St",
    "sg:city": "Provincetown",
    "sg:classifiers": [
      {
        "category": "Shopping",
        "type": "Retail Goods"
      }
    ],
    "sg:phone": "+1 508 487 7281",
    "sg:postcode": "02657",
    "sg:province": "MA",
    "sg:tags": [
      "art",
      "gallery",
      "dealer"
    ],
    "wof:name": "Outer Cape Art Auctions",
    "wof:placetype": "venue"
  },
  "geometry": {"coordinates":[-70.18359,42.054183],"type":"Point"}
}
