{
  "type": "Feature",
  "properties": {
    "addr:full": "55 Marshall St Leominster MA 01453",
    "addr:housenumber": "55",
    "addr:postcode": "01453",
    "addr:street": "Marshall St",
    "iso:country": "US",
    "sg:address": "55 Marshall St",
    "sg:city": "Leominster",
    "sg:classifiers": [
      {
        "category": "Manufacturing",
        "subcategory": "Tools \u0026 Machinery",
        "type": "Manufacturing \u0026 Wholesale Goods"
      }
    ],
    "sg:phone": "+1 978 534 8305",
    "sg:postcode": "01453",
    "sg:province": "MA",
    "sg:tags": [
      "mold"
    ],
    "sg:website": "www.mar-leecompanies.com",
    "wof:name": "Mar Lee Molds",
    "wof:placetype": "venue"
  },
  "geometry": {"coordinates":[-71.740608,42.542399],"type":"Point"}
}
