{
  "type": "Feature",
  "properties": {
    "iso:country":"US",
    "sg:address":"72 Sandwich Rd",
    "sg:city":"Wareham",
    "sg:classifiers":[
        {
            "category":"Government",
            "subcategory":"Office",
            "type":"Public Place"
        }
    ],
    "sg:phone":"+1 508 295 6725",
    "sg:postcode":"02571",
    "sg:province":"MA",
    "sg:tags":[
        "village"
    ],
    "wof:name":"Wareham Emergency Medical Svc",
    "wof:placetype":"venue"
},
  "geometry": {"coordinates":[-70.69856900000001,41.760348],"type":"Point"}
}