{
  "type": "Feature",
  "properties": {
    "addr:full": "72 Sandwich Rd Wareham MA 02571",
    "addr:housenumber": "72",
    "addr:postcode": "02571",
    "addr:street": "Sandwich Rd",
    "iso:country": "US",
    "sg:address": "72 Sandwich Rd",
    "sg:city": "Wareham",
    "sg:classifiers": [
      {
        "category": "Government",
        "subcategory": "Office",
        "type": "Public Place"
      }
    ],
    "sg:phone": "+1 508 295 6725",
    "sg:postcode": "02571",
    "sg:province": "MA",
    "sg:tags": [
      "village"
    ],
    "wof:name": "Wareham Emergency Medical Svc",
    "wof:placetype": "venue"
  },
  "geometry": {"coordinates":[-70.698569,41.760348],"type":"Point"}
}
