{
  "type": "Feature",
  "properties": {
    "addr:full": "25 B St Burlington MA 01803",
    "addr:housenumber": "25",
    "addr:postcode": "01803",
    "addr:street": "B St",
    "iso:country": "US",
    "sg:address": "25 B St",
    "sg:city": "Burlington",
    "sg:classifiers": [
      {
        "category": "Shopping",
        "subcategory": "Computers \u0026 Home Electronics",
        "type": "Retail Goods"
      }
    ],
    "sg:phone": "+1 781 270 4881",
    "sg:postcode": "01803",
    "sg:province": "MA",
    "sg:tags": [
      "software"
    ],
    "wof:name": "Site Plan Web Solutions",
    "wof:placetype": "venue"
  },
  "geometry": {"coordinates":[-71.222951,42.498479],"type":"Point"}
}
