{
  "type": "Feature",
  "properties": {
    "iso:country":"US",
    "sg:address":"25 B St",
    "sg:city":"Burlington",
    "sg:classifiers":[
        {
            "category":"Shopping",
            "subcategory":"Computers & Home Electronics",
            "type":"Retail Goods"
        }
    ],
    "sg:phone":"+1 781 270 4881",
    "sg:postcode":"01803",
    "sg:province":"MA",
    "sg:tags":[
        "software"
    ],
    "wof:name":"Site Plan Web Solutions",
    "wof:placetype":"venue"
},
  "geometry": {"coordinates":[-71.22295099999999,42.498479],"type":"Point"}
}