{
  "type": "Feature",
  "properties": {
    "addr:full": "885 Main St Tewksbury MA 01876",
    "addr:housenumber": "885",
    "addr:postcode": "01876",
    "addr:street": "Main St",
    "iso:country": "US",
    "sg:address": "885 Main St",
    "sg:city": "Tewksbury",
    "sg:classifiers": [
      {
        "category": "Education",
        "subcategory": "Special Training",
        "type": "Public Place"
      }
    ],
    "sg:phone": "+1   ",
    "sg:postcode": "01876",
    "sg:province": "MA",
    "wof:name": "Professnal Brtnders Schl of Ne",
    "wof:placetype": "venue"
  },
  "geometry": {"coordinates":[-71.237672,42.61369],"type":"Point"}
}
