{
  "type": "Feature",
  "properties": {
    "addr:full": "275 Centre St Indian Orchard MA 01151",
    "addr:housenumber": "275",
    "addr:postcode": "01151",
    "addr:street": "Centre St",
    "iso:country": "US",
    "sg:address": "275 Centre St",
    "sg:city": "Indian Orchard",
    "sg:classifiers": [
      {
        "category": "Building \u0026 Trades",
        "subcategory": "Landscaping Services",
        "type": "Services"
      }
    ],
    "sg:phone": "+1   ",
    "sg:postcode": "01151",
    "sg:province": "MA",
    "wof:name": "Gils Landscaping \u0026 Cnstr",
    "wof:placetype": "venue"
  },
  "geometry": {"coordinates":[-72.497263,42.159583],"type":"Point"}
}
