{
  "type": "Feature",
  "properties": {
    "iso:country":"US",
    "sg:address":"275 Centre St",
    "sg:city":"Indian Orchard",
    "sg:classifiers":[
        {
            "category":"Building & Trades",
            "subcategory":"Landscaping Services",
            "type":"Services"
        }
    ],
    "sg:phone":"+1   ",
    "sg:postcode":"01151",
    "sg:province":"MA",
    "wof:name":"Gils Landscaping & Cnstr",
    "wof:placetype":"venue"
},
  "geometry": {"coordinates":[-72.497263,42.159583],"type":"Point"}
}