{
  "type": "Feature",
  "properties": {
    "iso:country":"US",
    "sg:address":"38 Cameron Ave Ste 100",
    "sg:city":"Cambridge",
    "sg:classifiers":[
        {
            "category":"Arts & Performance",
            "subcategory":"Art Gallery",
            "type":"Entertainment"
        }
    ],
    "sg:phone":"+1 617 492 4091",
    "sg:postcode":"02140",
    "sg:province":"MA",
    "sg:website":"www.38cameron.com",
    "wof:name":"38 Cameron",
    "wof:placetype":"venue"
},
  "geometry": {"coordinates":[-71.12921299999999,42.398115],"type":"Point"}
}