{
  "type": "Feature",
  "properties": {
    "addr:full": "22 Denmark Ln Needham MA 02492",
    "addr:housenumber": "22",
    "addr:postcode": "02492",
    "addr:street": "Denmark Ln",
    "iso:country": "US",
    "sg:address": "22 Denmark Ln",
    "sg:city": "Needham",
    "sg:classifiers": [
      {
        "category": "Professional",
        "subcategory": "Business Services",
        "type": "Services"
      }
    ],
    "sg:phone": "+1   ",
    "sg:postcode": "02492",
    "sg:province": "MA",
    "wof:name": "Mpulse Group",
    "wof:placetype": "venue"
  },
  "geometry": {"coordinates":[-71.23837,42.279381],"type":"Point"}
}
