{
  "type": "Feature",
  "properties": {
    "iso:country":"US",
    "sg:address":"1637 Worcester Rd Framingham",
    "sg:city":"Framingham",
    "sg:classifiers":[
        {
            "category":"Travel",
            "subcategory":"Hotels & Motels",
            "type":"Entertainment"
        },
        {
            "category":"Travel",
            "subcategory":"Resort",
            "type":"Entertainment"
        },
        {
            "category":"Sports & Exercise",
            "subcategory":"Ski Resort",
            "type":"Entertainment"
        }
    ],
    "sg:phone":"+1 888 625 5144",
    "sg:postcode":"01701",
    "sg:province":"MA",
    "sg:tags":[
        "corporate",
        "lodging"
    ],
    "sg:website":"http://clk.atdmt.com/NYC/go/249187165/direct/01/",
    "wof:name":"Sheraton Framingham",
    "wof:placetype":"venue"
},
  "geometry": {"coordinates":[-71.479298,42.296911],"type":"Point"}
}