{
  "type": "Feature",
  "properties": {
    "addr:full":"260 Jackson St Lawrence MA 01841",
    "addr:housenumber":"260",
    "addr:postcode":"01841",
    "addr:street":"Jackson St",
    "iso:country":"US",
    "sg:address":"260 Jackson St",
    "sg:city":"Lawrence",
    "sg:classifiers":[
        {
            "category":"Food & Beverages",
            "subcategory":"Liquor & Beverages",
            "type":"Retail Goods"
        }
    ],
    "sg:phone":"+1 978 686 6842",
    "sg:postcode":"01841",
    "sg:province":"MA",
    "wof:name":"Garcia's Liquors Inc",
    "wof:placetype":"venue"
},
  "geometry": {"coordinates":[-71.157957,42.717302],"type":"Point"}
}