{
  "type": "Feature",
  "properties": {
    "iso:country":"US",
    "sg:address":"47 Oak St Ext",
    "sg:city":"Brockton",
    "sg:classifiers":[
        {
            "category":"Personal",
            "subcategory":"Beauty Salon",
            "type":"Services"
        }
    ],
    "sg:phone":"+1 508 897 0666",
    "sg:postcode":"02301",
    "sg:province":"MA",
    "sg:tags":[
        "hair",
        "stylist"
    ],
    "wof:name":"Good Cuts",
    "wof:placetype":"venue"
},
  "geometry": {"coordinates":[-71.065426,42.09987],"type":"Point"}
}