{
  "type": "Feature",
  "properties": {
    "iso:country":"US",
    "sg:address":"74 Warren St",
    "sg:city":"Boston",
    "sg:classifiers":[
        {
            "category":"Professional",
            "subcategory":"Computer Services",
            "type":"Services"
        }
    ],
    "sg:phone":"+1 617 445 4335",
    "sg:postcode":"02119",
    "sg:province":"MA",
    "sg:tags":[
        "repair"
    ],
    "sg:website":"www.geekznthehood.com/",
    "wof:name":"Geekz n The Hood",
    "wof:placetype":"venue"
},
  "geometry": {"coordinates":[-71.083011,42.327875],"type":"Point"}
}