{
  "type": "Feature",
  "properties": {
    "addr:full": "957A Broadway Everett MA 02149",
    "addr:housenumber": "957a",
    "addr:postcode": "02149",
    "addr:street": "Broadway",
    "iso:country": "US",
    "sg:address": "957A Broadway",
    "sg:city": "Everett",
    "sg:classifiers": [
      {
        "category": "Autos \u0026 Motor Vehicles",
        "subcategory": "Auto Supplies",
        "type": "Retail Goods"
      }
    ],
    "sg:phone": "+1 617 381 9009",
    "sg:postcode": "02149",
    "sg:province": "MA",
    "sg:tags": [
      "part"
    ],
    "sg:website": "www.artieshubcaps.com",
    "wof:name": "Artie's Used Hubcaps",
    "wof:placetype": "venue"
  },
  "geometry": {"coordinates":[-71.043217,42.422217],"type":"Point"}
}
