{
  "type": "Feature",
  "properties": {
    "iso:country":"US",
    "sg:address":"957A Broadway",
    "sg:city":"Everett",
    "sg:classifiers":[
        {
            "category":"Autos & Motor Vehicles",
            "subcategory":"Auto Supplies",
            "type":"Retail Goods"
        }
    ],
    "sg:phone":"+1 617 381 9009",
    "sg:postcode":"02149",
    "sg:province":"MA",
    "sg:tags":[
        "part"
    ],
    "sg:website":"www.artieshubcaps.com",
    "wof:name":"Artie's Used Hubcaps",
    "wof:placetype":"venue"
},
  "geometry": {"coordinates":[-71.043217,42.422217],"type":"Point"}
}