{
  "type": "Feature",
  "properties": {
    "addr:full": "865 Turnpike St North Andover MA 01845",
    "addr:housenumber": "865",
    "addr:postcode": "01845",
    "addr:street": "Turnpike St",
    "iso:country": "US",
    "sg:address": "865 Turnpike St",
    "sg:city": "North Andover",
    "sg:classifiers": [
      {
        "category": "Building \u0026 Trades",
        "subcategory": "Construction",
        "type": "Services"
      }
    ],
    "sg:phone": "+1 978 688 8895",
    "sg:postcode": "01845",
    "sg:province": "MA",
    "sg:tags": [
      "general",
      "contractor"
    ],
    "wof:name": "Grasso Construction Co",
    "wof:placetype": "venue"
  },
  "geometry": {"coordinates":[-71.104399,42.65756],"type":"Point"}
}
