{
  "type": "Feature",
  "properties": {
    "iso:country":"US",
    "sg:address":"157 Agawam Ave",
    "sg:city":"West Springfield",
    "sg:classifiers":[
        {
            "category":"Wholesale",
            "subcategory":"Auto Parts",
            "type":"Manufacturing & Wholesale Goods"
        }
    ],
    "sg:phone":"+1 413 733 6948",
    "sg:postcode":"01089",
    "sg:province":"MA",
    "sg:tags":[
        "automobile",
        "rebuilt"
    ],
    "wof:name":"Auto Salvage-West Springfield",
    "wof:placetype":"venue"
},
  "geometry": {"coordinates":[-72.59936,42.09324],"type":"Point"}
}