{
  "type": "Feature",
  "properties": {
    "addr:full":"2 E Main St Merrimac MA 01860",
    "addr:housenumber":"2",
    "addr:postcode":"01860",
    "addr:street":"E Main St",
    "iso:country":"US",
    "sg:address":"2 E Main St",
    "sg:city":"Merrimac",
    "sg:classifiers":[
        {
            "category":"Building & Trades",
            "subcategory":"Construction",
            "type":"Services"
        }
    ],
    "sg:phone":"+1 978 346 4496",
    "sg:postcode":"01860",
    "sg:province":"MA",
    "sg:tags":[
        "woodworker"
    ],
    "wof:name":"Enduring Wood Products",
    "wof:placetype":"venue"
},
  "geometry": {"coordinates":[-71.001098,42.834136],"type":"Point"}
}