{
  "type": "Feature",
  "properties": {
    "iso:country":"US",
    "sg:address":"30 Dearborn St",
    "sg:city":"Salem",
    "sg:classifiers":[
        {
            "category":"Real Estate",
            "subcategory":"Architect",
            "type":"Services"
        }
    ],
    "sg:phone":"+1   ",
    "sg:postcode":"01970",
    "sg:province":"MA",
    "sg:tags":[
        "architectural"
    ],
    "wof:name":"McDermet Staley Associates",
    "wof:placetype":"venue"
},
  "geometry": {"coordinates":[-70.899523,42.530212],"type":"Point"}
}