{
  "type": "Feature",
  "properties": {
    "iso:country":"US",
    "sg:address":"200 Foxboro Blvd # 500",
    "sg:city":"Foxboro",
    "sg:classifiers":[
        {
            "category":"Real Estate",
            "subcategory":"Real Estate Services",
            "type":"Services"
        },
        {
            "category":"Banks & Credit Unions",
            "subcategory":"Financial Services",
            "type":"Services"
        }
    ],
    "sg:phone":"+1 508 543 2085",
    "sg:postcode":"02035",
    "sg:province":"MA",
    "sg:tags":[
        "loan",
        "processing",
        "mortgage"
    ],
    "wof:name":"Sand Canyon Corporation",
    "wof:placetype":"venue"
},
  "geometry": {"coordinates":[-71.235916,42.042381],"type":"Point"}
}