{
  "type": "Feature",
  "properties": {
    "addr:full": "14 West St Granby MA 01033",
    "addr:housenumber": "14",
    "addr:postcode": "01033",
    "addr:street": "West St",
    "iso:country": "US",
    "sg:address": "14 West St",
    "sg:city": "Granby",
    "sg:classifiers": [
      {
        "category": "Education",
        "subcategory": "School",
        "type": "Public Place"
      }
    ],
    "sg:phone": "+1 413 467 9235",
    "sg:postcode": "01033",
    "sg:province": "MA",
    "wof:name": "West Street Elementary School",
    "wof:placetype": "venue"
  },
  "geometry": {"coordinates":[-72.521796,42.257705],"type":"Point"}
}
