{
  "type": "Feature",
  "properties": {
    "addr:full":"672 Broadway Malden MA 02148",
    "addr:housenumber":"672",
    "addr:postcode":"02148",
    "addr:street":"Broadway",
    "iso:country":"US",
    "sg:address":"672 Broadway",
    "sg:city":"Malden",
    "sg:classifiers":[
        {
            "category":"Retail",
            "subcategory":"Auto Repair",
            "type":"Services"
        }
    ],
    "sg:phone":"+1 781 397 1625",
    "sg:postcode":"02148",
    "sg:province":"MA",
    "wof:name":"Richards Collisions Center",
    "wof:placetype":"venue"
},
  "geometry": {"coordinates":[-71.027438,42.446631],"type":"Point"}
}