{
  "type": "Feature",
  "properties": {
    "addr:full": "300 Stafford St Springfield MA 01104",
    "addr:housenumber": "300",
    "addr:postcode": "01104",
    "addr:street": "Stafford St",
    "iso:country": "US",
    "sg:address": "300 Stafford St",
    "sg:city": "Springfield",
    "sg:classifiers": [
      {
        "category": "Health Services",
        "subcategory": "Health Practitioner",
        "type": "Services"
      }
    ],
    "sg:phone": "+1 413 734 8440",
    "sg:postcode": "01104",
    "sg:province": "MA",
    "sg:tags": [
      "therapist",
      "physical"
    ],
    "wof:name": "MVA Ctr For Rehabilitation",
    "wof:placetype": "venue"
  },
  "geometry": {"coordinates":[-72.595486,42.111689],"type":"Point"}
}
