{
  "type": "Feature",
  "properties": {
    "addr:full": "837 Suffield St Agawam MA 01001",
    "addr:housenumber": "837",
    "addr:postcode": "01001",
    "addr:street": "Suffield St",
    "iso:country": "US",
    "sg:address": "837 Suffield St",
    "sg:city": "Agawam",
    "sg:classifiers": [
      {
        "category": "Utilities",
        "subcategory": "Mobile Phone",
        "type": "Services"
      }
    ],
    "sg:phone": "+1 413 821 0055",
    "sg:postcode": "01001",
    "sg:province": "MA",
    "sg:tags": [
      "telephone",
      "cellular"
    ],
    "wof:name": "Totally Cellular",
    "wof:placetype": "venue"
  },
  "geometry": {"coordinates":[-72.632186,42.060959],"type":"Point"}
}
