{
  "type": "Feature",
  "properties": {
    "addr:full":"165 Mechanic St Leominster MA 01453",
    "addr:housenumber":"165",
    "addr:postcode":"01453",
    "addr:street":"Mechanic St",
    "iso:country":"US",
    "sg:address":"165 Mechanic St",
    "sg:city":"Leominster",
    "sg:classifiers":[
        {
            "category":"Professional",
            "subcategory":"Lawyer & Legal Services",
            "type":"Services"
        }
    ],
    "sg:phone":"+1 978 466 1300",
    "sg:postcode":"01453",
    "sg:province":"MA",
    "sg:tags":[
        "attorney"
    ],
    "wof:name":"William A Comeau Esq",
    "wof:placetype":"venue"
},
  "geometry": {"coordinates":[-71.75156200000001,42.523619],"type":"Point"}
}