{
  "type": "Feature",
  "properties": {
    "addr:full":"9 Hanson Rd North Reading MA 01864",
    "addr:housenumber":"9",
    "addr:postcode":"01864",
    "addr:street":"Hanson Rd",
    "iso:country":"US",
    "sg:address":"9 Hanson Rd",
    "sg:city":"North Reading",
    "sg:classifiers":[
        {
            "category":"Retail",
            "subcategory":"Repair Shop",
            "type":"Services"
        },
        {
            "category":"Building & Trades",
            "subcategory":"Plumbing",
            "type":"Services"
        }
    ],
    "sg:phone":"+1 978 664 1115",
    "sg:postcode":"01864",
    "sg:province":"MA",
    "sg:tags":[
        "septic"
    ],
    "wof:name":"New England Septic Service Co",
    "wof:placetype":"venue"
},
  "geometry": {"coordinates":[-71.13214600000001,42.595785],"type":"Point"}
}