{
  "type": "Feature",
  "properties": {
    "addr:full":"1 West St Pittsfield MA 01201",
    "addr:housenumber":"1",
    "addr:postcode":"01201",
    "addr:street":"West St",
    "iso:country":"US",
    "sg:address":"1 West St",
    "sg:city":"Pittsfield",
    "sg:classifiers":[
        {
            "category":"Travel",
            "subcategory":"Hotels & Motels",
            "type":"Entertainment"
        }
    ],
    "sg:phone":"+1 413 499 2000",
    "sg:postcode":"01201",
    "sg:province":"MA",
    "wof:name":"Crowne Plaza Pittsfld-Berkshrs",
    "wof:placetype":"venue"
},
  "geometry": {"coordinates":[-73.255026,42.448567],"type":"Point"}
}