{
  "type": "Feature",
  "properties": {
    "iso:country":"US",
    "sg:address":"104 Munn Rd",
    "sg:city":"Monson",
    "sg:classifiers":[
        {
            "category":"Manufacturing",
            "subcategory":"Lumber",
            "type":"Manufacturing & Wholesale Goods"
        }
    ],
    "sg:phone":"+1 413 267 3827",
    "sg:postcode":"01057",
    "sg:province":"MA",
    "sg:tags":[
        "logging"
    ],
    "wof:name":"R T Smart Logging Fire Woo",
    "wof:placetype":"venue"
},
  "geometry": {"coordinates":[-72.289198,42.088459],"type":"Point"}
}