{
  "type": "Feature",
  "properties": {
    "iso:country":"US",
    "sg:address":"340 River St",
    "sg:city":"West Newton",
    "sg:classifiers":[
        {
            "category":"Restaurant",
            "type":"Food & Drink"
        }
    ],
    "sg:phone":"+1 617 964 2985",
    "sg:postcode":"02465",
    "sg:province":"MA",
    "sg:tags":[
        "cafe"
    ],
    "wof:name":"Namaste Cafe",
    "wof:placetype":"venue"
},
  "geometry": {"coordinates":[-71.23934199999999,42.35756],"type":"Point"}
}