{
  "type": "Feature",
  "properties": {
    "addr:full": "340 River St West Newton MA 02465",
    "addr:housenumber": "340",
    "addr:postcode": "02465",
    "addr:street": "River St",
    "iso:country": "US",
    "sg:address": "340 River St",
    "sg:city": "West Newton",
    "sg:classifiers": [
      {
        "category": "Restaurant",
        "type": "Food \u0026 Drink"
      }
    ],
    "sg:phone": "+1 617 964 2985",
    "sg:postcode": "02465",
    "sg:province": "MA",
    "sg:tags": [
      "cafe"
    ],
    "wof:name": "Namaste Cafe",
    "wof:placetype": "venue"
  },
  "geometry": {"coordinates":[-71.239342,42.35756],"type":"Point"}
}
