{
  "type": "Feature",
  "properties": {
    "addr:full": "2 Boylston St Boston MA 02116",
    "addr:housenumber": "2",
    "addr:postcode": "02116",
    "addr:street": "Boylston St",
    "iso:country": "US",
    "sg:address": "2 Boylston St",
    "sg:city": "Boston",
    "sg:classifiers": [
      {
        "category": "Landmark",
        "subcategory": "Historic",
        "type": "Public Place"
      }
    ],
    "sg:phone": "+1 617 338 4339",
    "sg:postcode": "02116",
    "sg:province": "MA",
    "sg:tags": [
      "building",
      "historical"
    ],
    "wof:name": "Chinese Historical Society of New England",
    "wof:placetype": "venue"
  },
  "geometry": {"coordinates":[-71.062599,42.352501],"type":"Point"}
}
