{
  "type": "Feature",
  "properties": {
    "addr:full": "22 Main St Sturbridge MA 01566",
    "addr:housenumber": "22",
    "addr:postcode": "01566",
    "addr:street": "Main St",
    "iso:country": "US",
    "sg:address": "22 Main St",
    "sg:city": "Sturbridge",
    "sg:classifiers": [
      {
        "category": "Health Services",
        "subcategory": "Doctor",
        "type": "Services"
      }
    ],
    "sg:phone": "+1 508 347 7171",
    "sg:postcode": "01566",
    "sg:province": "MA",
    "sg:tags": [
      "dentist"
    ],
    "wof:name": "Robert H Audet DDS",
    "wof:placetype": "venue"
  },
  "geometry": {"coordinates":[-72.056615,42.085149],"type":"Point"}
}
