{
  "type": "Feature",
  "properties": {
    "iso:country":"US",
    "sg:address":"22 Main St",
    "sg:city":"Sturbridge",
    "sg:classifiers":[
        {
            "category":"Health Services",
            "subcategory":"Doctor",
            "type":"Services"
        }
    ],
    "sg:phone":"+1 508 347 7171",
    "sg:postcode":"01566",
    "sg:province":"MA",
    "sg:tags":[
        "dentist"
    ],
    "wof:name":"Robert H Audet DDS",
    "wof:placetype":"venue"
},
  "geometry": {"coordinates":[-72.05661499999999,42.085149],"type":"Point"}
}