{
  "type": "Feature",
  "properties": {
    "addr:full": "800 Spring St Winchendon MA 01475",
    "addr:housenumber": "800",
    "addr:postcode": "01475",
    "addr:street": "Spring St",
    "iso:country": "US",
    "sg:address": "800 Spring St",
    "sg:city": "Winchendon",
    "sg:classifiers": [
      {
        "category": "Wholesale",
        "subcategory": "Auto Parts",
        "type": "Manufacturing \u0026 Wholesale Goods"
      }
    ],
    "sg:phone": "+1 978 297 0350",
    "sg:postcode": "01475",
    "sg:province": "MA",
    "sg:tags": [
      "automobile",
      "rebuilt"
    ],
    "sg:website": "www.toytownauto.com",
    "wof:name": "Always A Deal At Toy Town Auto",
    "wof:placetype": "venue"
  },
  "geometry": {"coordinates":[-71.994203,42.657448],"type":"Point"}
}
