{
  "type": "Feature",
  "properties": {
    "addr:full": "99 Broadway Somerville MA 02145",
    "addr:housenumber": "99",
    "addr:postcode": "02145",
    "addr:street": "Broadway",
    "iso:country": "US",
    "sg:address": "99 Broadway",
    "sg:city": "Somerville",
    "sg:classifiers": [
      {
        "category": "Food \u0026 Beverages",
        "subcategory": "Bakery",
        "type": "Retail Goods"
      }
    ],
    "sg:phone": "+1 617 776 0138",
    "sg:postcode": "02145",
    "sg:province": "MA",
    "sg:tags": [
      "baker"
    ],
    "wof:name": "Vicentino's Bakery",
    "wof:placetype": "venue"
  },
  "geometry": {"coordinates":[-71.08308,42.387486],"type":"Point"}
}
