{
  "type": "Feature",
  "properties": {
    "addr:full": "85 Parker St Newburyport MA 01950",
    "addr:housenumber": "85",
    "addr:postcode": "01950",
    "addr:street": "Parker St",
    "iso:country": "US",
    "sg:address": "85 Parker St",
    "sg:city": "Newburyport",
    "sg:classifiers": [
      {
        "category": "Manufacturing",
        "subcategory": "Rubber \u0026 Plastics",
        "type": "Manufacturing \u0026 Wholesale Goods"
      }
    ],
    "sg:phone": "+1 978 462 8101",
    "sg:postcode": "01950",
    "sg:province": "MA",
    "sg:tags": [
      "seal"
    ],
    "wof:name": "Electronic Products Inc",
    "wof:placetype": "venue"
  },
  "geometry": {"coordinates":[-70.880277,42.80021],"type":"Point"}
}
