{
  "type": "Feature",
  "properties": {
    "addr:full":"85 Parker St Newburyport MA 01950",
    "addr:housenumber":"85",
    "addr:postcode":"01950",
    "addr:street":"Parker St",
    "iso:country":"US",
    "sg:address":"85 Parker St",
    "sg:city":"Newburyport",
    "sg:classifiers":[
        {
            "category":"Manufacturing",
            "subcategory":"Rubber & Plastics",
            "type":"Manufacturing & Wholesale Goods"
        }
    ],
    "sg:phone":"+1 978 462 8101",
    "sg:postcode":"01950",
    "sg:province":"MA",
    "sg:tags":[
        "seal"
    ],
    "wof:name":"Electronic Products Inc",
    "wof:placetype":"venue"
},
  "geometry": {"coordinates":[-70.88027700000001,42.80021],"type":"Point"}
}