{
  "type": "Feature",
  "properties": {
    "addr:full":"34 Valentine St Cambridge MA 02139",
    "addr:housenumber":"34",
    "addr:postcode":"02139",
    "addr:street":"Valentine St",
    "iso:country":"US",
    "sg:address":"34 Valentine St",
    "sg:city":"Cambridge",
    "sg:classifiers":[
        {
            "category":"Professional",
            "subcategory":"Computer Services",
            "type":"Services"
        }
    ],
    "sg:phone":"+1   ",
    "sg:postcode":"02139",
    "sg:province":"MA",
    "sg:tags":[
        "programing",
        "custom"
    ],
    "wof:name":"Digidogs",
    "wof:placetype":"venue"
},
  "geometry": {"coordinates":[-71.106476,42.360504],"type":"Point"}
}