{
  "type": "Feature",
  "properties": {
    "addr:full":"37 Broadway Arlington MA 02474",
    "addr:housenumber":"37",
    "addr:postcode":"02474",
    "addr:street":"Broadway",
    "iso:country":"US",
    "sg:address":"37 Broadway",
    "sg:city":"Arlington",
    "sg:classifiers":[
        {
            "category":"Personal",
            "type":"Services"
        },
        {
            "category":"Sports & Exercise",
            "subcategory":"Gym",
            "type":"Entertainment"
        }
    ],
    "sg:phone":"+1 781 316 8500",
    "sg:postcode":"02474",
    "sg:province":"MA",
    "sg:tags":[
        "trainer",
        "consultant",
        "program",
        "health",
        "fitness"
    ],
    "sg:website":"http://www.fitnesstogether.com",
    "wof:name":"Fitness Together",
    "wof:placetype":"venue"
},
  "geometry": {"coordinates":[-71.136059,42.408056],"type":"Point"}
}