{
  "type": "Feature",
  "properties": {
    "iso:country":"US",
    "sg:address":"10 Central St",
    "sg:city":"Foxboro",
    "sg:classifiers":[
        {
            "category":"Personal",
            "subcategory":"Beauty Salon",
            "type":"Services"
        }
    ],
    "sg:phone":"+1 508 543 1046",
    "sg:postcode":"02035",
    "sg:province":"MA",
    "sg:tags":[
        "manicuring"
    ],
    "wof:name":"Elegant Touch",
    "wof:placetype":"venue"
},
  "geometry": {"coordinates":[-71.249556,42.064042],"type":"Point"}
}