{
  "type": "Feature",
  "properties": {
    "iso:country":"US",
    "sg:address":"58 Union Ave",
    "sg:city":"Framingham",
    "sg:classifiers":[
        {
            "category":"Personal",
            "subcategory":"Beauty Salon",
            "type":"Services"
        }
    ],
    "sg:phone":"+1 508 820 9933",
    "sg:postcode":"01702",
    "sg:province":"MA",
    "wof:name":"Lana's Beauty Salon",
    "wof:placetype":"venue"
},
  "geometry": {"coordinates":[-71.41698,42.279163],"type":"Point"}
}