{
  "type": "Feature",
  "properties": {
    "addr:full":"154 Worcester St Natick MA 01760",
    "addr:housenumber":"154",
    "addr:postcode":"01760",
    "addr:street":"Worcester St",
    "iso:country":"US",
    "sg:address":"154 Worcester St",
    "sg:city":"Natick",
    "sg:classifiers":[
        {
            "category":"Banks & Credit Unions",
            "subcategory":"Bank",
            "type":"Services"
        }
    ],
    "sg:phone":"+1 508 650 5142",
    "sg:postcode":"01760",
    "sg:province":"MA",
    "wof:name":"Banknorth",
    "wof:placetype":"venue"
},
  "geometry": {"coordinates":[-71.333164,42.303245],"type":"Point"}
}