{
  "type": "Feature",
  "properties": {
    "iso:country":"US",
    "sg:address":"6 Springfield St",
    "sg:city":"Springfield",
    "sg:classifiers":[
        {
            "category":"Professional",
            "type":"Services"
        }
    ],
    "sg:phone":"+1 973 467 1155",
    "sg:postcode":"01107",
    "sg:province":"MA",
    "sg:tags":[
        "establishment"
    ],
    "wof:name":"Mr Water Heater Inc",
    "wof:placetype":"venue"
},
  "geometry": {"coordinates":[-72.60481900000001,42.122096],"type":"Point"}
}