{
  "type": "Feature",
  "properties": {
    "addr:full":"228 Maverick St Boston MA 02128",
    "addr:housenumber":"228",
    "addr:postcode":"02128",
    "addr:street":"Maverick St",
    "iso:country":"US",
    "sg:address":"228 Maverick St",
    "sg:city":"Boston",
    "sg:classifiers":[
        {
            "category":"Building & Trades",
            "subcategory":"Electrical",
            "type":"Services"
        }
    ],
    "sg:phone":"+1 617 561 6682",
    "sg:postcode":"02128",
    "sg:province":"MA",
    "sg:tags":[
        "industrial",
        "electrician",
        "contractors-commercial",
        "electric"
    ],
    "wof:name":"Cora Electrical Services",
    "wof:placetype":"venue"
},
  "geometry": {"coordinates":[-71.035301,42.368401],"type":"Point"}
}