{
  "type": "Feature",
  "properties": {
    "iso:country":"US",
    "sg:address":"170 Dunns Pond Rd",
    "sg:city":"Hyannis",
    "sg:classifiers":[
        {
            "category":"Wholesale",
            "subcategory":"Books, Periodicals, & Newspapers",
            "type":"Manufacturing & Wholesale Goods"
        }
    ],
    "sg:phone":"+1 508 771 3238",
    "sg:postcode":"02601",
    "sg:province":"MA",
    "sg:tags":[
        "publisher",
        "book"
    ],
    "wof:name":"Glencoe Mc Graw Hill",
    "wof:placetype":"venue"
},
  "geometry": {"coordinates":[-70.316478,41.65511],"type":"Point"}
}