{
  "type": "Feature",
  "properties": {
    "addr:full": "170 Dunns Pond Rd Hyannis MA 02601",
    "addr:housenumber": "170",
    "addr:postcode": "02601",
    "addr:street": "Dunns Pond Rd",
    "iso:country": "US",
    "sg:address": "170 Dunns Pond Rd",
    "sg:city": "Hyannis",
    "sg:classifiers": [
      {
        "category": "Wholesale",
        "subcategory": "Books, Periodicals, \u0026 Newspapers",
        "type": "Manufacturing \u0026 Wholesale Goods"
      }
    ],
    "sg:phone": "+1 508 771 3238",
    "sg:postcode": "02601",
    "sg:province": "MA",
    "sg:tags": [
      "publisher",
      "book"
    ],
    "wof:name": "Glencoe Mc Graw Hill",
    "wof:placetype": "venue"
  },
  "geometry": {"coordinates":[-70.316478,41.65511],"type":"Point"}
}
