{
  "type": "Feature",
  "properties": {
    "iso:country":"US",
    "sg:address":"688 Broadway St",
    "sg:city":"Lowell",
    "sg:classifiers":[
        {
            "category":"Retail",
            "subcategory":"Auto Repair",
            "type":"Services"
        }
    ],
    "sg:phone":"+1 978 452 0265",
    "sg:postcode":"01854",
    "sg:province":"MA",
    "sg:tags":[
        "wrecker"
    ],
    "wof:name":"Kazanjian's Towing",
    "wof:placetype":"venue"
},
  "geometry": {"coordinates":[-71.328631,42.642763],"type":"Point"}
}