{
  "type": "Feature",
  "properties": {
    "addr:full": "120 Cross St Winchester MA 01890",
    "addr:housenumber": "120",
    "addr:postcode": "01890",
    "addr:street": "Cross St",
    "iso:country": "US",
    "sg:address": "120 Cross St",
    "sg:city": "Winchester",
    "sg:classifiers": [
      {
        "category": "Retail",
        "subcategory": "Repair Shop",
        "type": "Services"
      }
    ],
    "sg:phone": "+1 781 729 6920",
    "sg:postcode": "01890",
    "sg:province": "MA",
    "sg:tags": [
      "equipment",
      "telephone",
      "system"
    ],
    "wof:name": "Lighthouse Business Commun",
    "wof:placetype": "venue"
  },
  "geometry": {"coordinates":[-71.1312,42.467367],"type":"Point"}
}
