{
  "type": "Feature",
  "properties": {
    "iso:country":"US",
    "sg:address":"6 Ashley St",
    "sg:city":"Jamaica Plain",
    "sg:classifiers":[
        {
            "category":"Freight",
            "type":"Transportation"
        }
    ],
    "sg:phone":"+1   ",
    "sg:postcode":"02130",
    "sg:province":"MA",
    "sg:tags":[
        "operator",
        "local",
        "trucking"
    ],
    "wof:name":"Tfj Management Svcs",
    "wof:placetype":"venue"
},
  "geometry": {"coordinates":[-71.104034,42.321206],"type":"Point"}
}