{
  "type": "Feature",
  "properties": {
    "iso:country":"US",
    "sg:address":"26 Cabot St",
    "sg:city":"Beverly",
    "sg:classifiers":[
        {
            "category":"Autos & Motor Vehicles",
            "subcategory":"Automobile Sales",
            "type":"Retail Goods"
        }
    ],
    "sg:phone":"+1 978 921 9219",
    "sg:postcode":"01915",
    "sg:province":"MA",
    "sg:tags":[
        "classic"
    ],
    "wof:name":"European Legends",
    "wof:placetype":"venue"
},
  "geometry": {"coordinates":[-70.885188,42.541678],"type":"Point"}
}