{
  "type": "Feature",
  "properties": {
    "addr:full":"1167 E Columbus Ave Springfield MA 01105",
    "addr:housenumber":"1167",
    "addr:postcode":"01105",
    "addr:street":"E Columbus Ave",
    "iso:country":"US",
    "sg:address":"1167 E Columbus Ave",
    "sg:city":"Springfield",
    "sg:classifiers":[
        {
            "category":"Food & Beverages",
            "subcategory":"Groceries & Convenience Stores",
            "type":"Retail Goods"
        }
    ],
    "sg:phone":"+1 413 733 6358",
    "sg:postcode":"01105",
    "sg:province":"MA",
    "wof:name":"Albano Grocery Store",
    "wof:placetype":"venue"
},
  "geometry": {"coordinates":[-72.585956,42.096504],"type":"Point"}
}