{
  "type": "Feature",
  "properties": {
    "iso:country":"US",
    "sg:address":"33 Old Farm Rd",
    "sg:city":"Randolph",
    "sg:classifiers":[
        {
            "category":"Professional",
            "subcategory":"Accounting & Tax Preparation",
            "type":"Services"
        }
    ],
    "sg:phone":"+1 781 961 4818",
    "sg:postcode":"02368",
    "sg:province":"MA",
    "sg:tags":[
        "bookkeeping",
        "general"
    ],
    "wof:name":"Evergreen Accounting Svc",
    "wof:placetype":"venue"
},
  "geometry": {"coordinates":[-71.062833,42.187541],"type":"Point"}
}