{
  "type": "Feature",
  "properties": {
    "iso:country":"US",
    "sg:address":"17 Coffin St",
    "sg:city":"West Newbury",
    "sg:classifiers":[
        {
            "category":"Wholesale",
            "subcategory":"Durable Goods & Equipment",
            "type":"Manufacturing & Wholesale Goods"
        }
    ],
    "sg:phone":"+1 978 363 5323",
    "sg:postcode":"01985",
    "sg:province":"MA",
    "sg:tags":[
        "representative",
        "manufacturer"
    ],
    "sg:website":"www.dwyernet.com",
    "wof:name":"Dwyer Associates",
    "wof:placetype":"venue"
},
  "geometry": {"coordinates":[-70.969589,42.816799],"type":"Point"}
}