{
  "type": "Feature",
  "properties": {
    "iso:country":"US",
    "sg:address":"12 Washington St",
    "sg:city":"Millbury",
    "sg:classifiers":[
        {
            "category":"Wholesale",
            "subcategory":"Books, Periodicals, & Newspapers",
            "type":"Manufacturing & Wholesale Goods"
        }
    ],
    "sg:phone":"+1 617 752 1641",
    "sg:postcode":"01527",
    "sg:province":"MA",
    "sg:tags":[
        "publisher",
        "book"
    ],
    "wof:name":"Purple Ink Press",
    "wof:placetype":"venue"
},
  "geometry": {"coordinates":[-71.767218,42.184865],"type":"Point"}
}