{
  "type": "Feature",
  "properties": {
    "addr:full": "12 Washington St Millbury MA 01527",
    "addr:housenumber": "12",
    "addr:postcode": "01527",
    "addr:street": "Washington St",
    "iso:country": "US",
    "sg:address": "12 Washington St",
    "sg:city": "Millbury",
    "sg:classifiers": [
      {
        "category": "Wholesale",
        "subcategory": "Books, Periodicals, \u0026 Newspapers",
        "type": "Manufacturing \u0026 Wholesale Goods"
      }
    ],
    "sg:phone": "+1 617 752 1641",
    "sg:postcode": "01527",
    "sg:province": "MA",
    "sg:tags": [
      "publisher",
      "book"
    ],
    "wof:name": "Purple Ink Press",
    "wof:placetype": "venue"
  },
  "geometry": {"coordinates":[-71.767218,42.184865],"type":"Point"}
}
