{
  "type": "Feature",
  "properties": {
    "addr:full":"383 S Main St Cohasset MA 02025",
    "addr:housenumber":"383",
    "addr:postcode":"02025",
    "addr:street":"S Main St",
    "iso:country":"US",
    "sg:address":"383 S Main St",
    "sg:city":"Cohasset",
    "sg:classifiers":[
        {
            "category":"Food & Beverages",
            "subcategory":"Meat & Fish",
            "type":"Retail Goods"
        }
    ],
    "sg:phone":"+1 781 383 0901",
    "sg:postcode":"02025",
    "sg:province":"MA",
    "sg:tags":[
        "seafood-wholesale"
    ],
    "wof:name":"Fishing Vessel Ida Jean",
    "wof:placetype":"venue"
},
  "geometry": {"coordinates":[-70.792446,42.226079],"type":"Point"}
}