{
  "type": "Feature",
  "properties": {
    "addr:full": "74 American Legion Dr North Adams MA 01247",
    "addr:housenumber": "74",
    "addr:postcode": "01247",
    "addr:street": "American Legion Dr",
    "iso:country": "US",
    "ovtr:label": "Burger King, 74 American Legion Dr North Adams MA US",
    "ovtr:similarity": 3.08854603767395,
    "sg:address": "74 American Legion Dr",
    "sg:city": "North Adams",
    "sg:classifiers": [
      {
        "category": "Restaurant",
        "type": "Food \u0026 Drink"
      }
    ],
    "sg:menulink": "http://www.allmenus.com/ma/north-adams/197584-burger-king/menu/",
    "sg:phone": "+1 413 664 4779",
    "sg:postcode": "01247",
    "sg:province": "MA",
    "sg:tags": [
      "burger",
      "american"
    ],
    "wof:name": "Burger King",
    "wof:placetype": "venue"
  },
  "geometry": {"coordinates":[-73.113245,42.697462],"type":"Point"}
}
