{
  "type": "Feature",
  "properties": {
    "iso:country":"US",
    "sg:address":"74 American Legion Dr",
    "sg:city":"North Adams",
    "sg:classifiers":[
        {
            "category":"Restaurant",
            "type":"Food & Drink"
        }
    ],
    "sg:menulink":"http://www.allmenus.com/ma/north-adams/197584-burger-king/menu/",
    "sg:phone":"+1 413 664 4779",
    "sg:postcode":"01247",
    "sg:province":"MA",
    "sg:tags":[
        "burger",
        "american"
    ],
    "wof:name":"Burger King",
    "wof:placetype":"venue"
},
  "geometry": {"coordinates":[-73.11324500000001,42.697462],"type":"Point"}
}