{
  "type": "Feature",
  "properties": {
    "iso:country":"US",
    "sg:address":"943 Millbury St",
    "sg:city":"Worcester",
    "sg:classifiers":[
        {
            "category":"Freight",
            "type":"Transportation"
        }
    ],
    "sg:phone":"+1 508 757 5362",
    "sg:postcode":"01607",
    "sg:province":"MA",
    "sg:tags":[
        "trucking"
    ],
    "wof:name":"Frank Belsito Trucking",
    "wof:placetype":"venue"
},
  "geometry": {"coordinates":[-71.79138399999999,42.230323],"type":"Point"}
}