{
  "type": "Feature",
  "properties": {
    "iso:country":"US",
    "sg:address":"75 Newbury St",
    "sg:city":"Boston",
    "sg:classifiers":[
        {
            "category":"Personal",
            "subcategory":"Beauty Salon",
            "type":"Services"
        },
        {
            "category":"Shopping",
            "subcategory":"Beauty & Cosmetics",
            "type":"Retail Goods"
        }
    ],
    "sg:phone":"+1 617 247 0770",
    "sg:postcode":"02116",
    "sg:province":"MA",
    "sg:tags":[
        "hair",
        "braiding",
        "stylist",
        "perfume"
    ],
    "sg:website":"http://www.innerbeautyconcepts.com",
    "wof:name":"Umi Salon",
    "wof:placetype":"venue"
},
  "geometry": {"coordinates":[-71.074437,42.351954],"type":"Point"}
}