{
  "type": "Feature",
  "properties": {
    "iso:country":"US",
    "sg:address":"111 South St Ste 1",
    "sg:city":"Somerville",
    "sg:classifiers":[
        {
            "category":"Banks & Credit Unions",
            "subcategory":"Bank",
            "type":"Services"
        }
    ],
    "sg:phone":"+1 617 628 3366",
    "sg:postcode":"02143",
    "sg:province":"MA",
    "sg:website":"www.memberspluscu.org",
    "wof:name":"Members Plus Credit Union",
    "wof:placetype":"venue"
},
  "geometry": {"coordinates":[-71.0903,42.374483],"type":"Point"}
}