{
  "type": "Feature",
  "properties": {
    "iso:country":"US",
    "sg:address":"241 Salem St",
    "sg:city":"Malden",
    "sg:classifiers":[
        {
            "category":"Freight",
            "type":"Transportation"
        }
    ],
    "sg:phone":"+1 978 618 6116",
    "sg:postcode":"02148",
    "sg:province":"MA",
    "wof:name":"B K Transportation LTD",
    "wof:placetype":"venue"
},
  "geometry": {"coordinates":[-71.058571,42.430576],"type":"Point"}
}