{
  "type": "Feature",
  "properties": {
    "addr:full":"181 Main St Hudson MA 01749",
    "addr:housenumber":"181",
    "addr:postcode":"01749",
    "addr:street":"Main St",
    "iso:country":"US",
    "sg:address":"181 Main St",
    "sg:city":"Hudson",
    "sg:classifiers":[
        {
            "category":"Autos & Motor Vehicles",
            "subcategory":"Fuel & Gas Station",
            "type":"Retail Goods"
        }
    ],
    "sg:phone":"+1 978 562 6712",
    "sg:postcode":"01749",
    "sg:province":"MA",
    "sg:tags":[
        "oil"
    ],
    "wof:name":"Necds Hudson Shell",
    "wof:placetype":"venue"
},
  "geometry": {"coordinates":[-71.56272,42.391661],"type":"Point"}
}