{
  "type": "Feature",
  "properties": {
    "iso:country":"US",
    "sg:address":"4 Veterans Way",
    "sg:city":"Webster",
    "sg:classifiers":[
        {
            "category":"Organizations",
            "subcategory":"Membership Organization",
            "type":"Services"
        }
    ],
    "sg:phone":"+1 508 949 3855",
    "sg:postcode":"01570",
    "sg:province":"MA",
    "sg:tags":[
        "military",
        "veteran"
    ],
    "wof:name":"Webster Veterans Service Dept",
    "wof:placetype":"venue"
},
  "geometry": {"coordinates":[-71.87867900000001,42.049264],"type":"Point"}
}