{
  "type": "Feature",
  "properties": {
    "iso:country":"US",
    "sg:address":"18 Exchange St",
    "sg:city":"Milford",
    "sg:classifiers":[
        {
            "category":"Personal",
            "subcategory":"Beauty Salon",
            "type":"Services"
        }
    ],
    "sg:phone":"+1 508 634 5228",
    "sg:postcode":"01757",
    "sg:province":"MA",
    "wof:name":"Mery's Beauty Salon",
    "wof:placetype":"venue"
},
  "geometry": {"coordinates":[-71.52064799999999,42.140163],"type":"Point"}
}