{
  "type": "Feature",
  "properties": {
    "iso:country":"US",
    "sg:address":"1160 Blue Hill Ave",
    "sg:city":"Dorchester Ctr",
    "sg:classifiers":[
        {
            "category":"Restaurant",
            "type":"Food & Drink"
        }
    ],
    "sg:phone":"+1 617 265 9027",
    "sg:postcode":"02124",
    "sg:province":"MA",
    "wof:name":"KFC",
    "wof:placetype":"venue"
},
  "geometry": {"coordinates":[-71.091165,42.284813],"type":"Point"}
}