{
  "type": "Feature",
  "properties": {
    "addr:full":"340 Shrewsbury St Worcester MA 01604",
    "addr:housenumber":"340",
    "addr:postcode":"01604",
    "addr:street":"Shrewsbury St",
    "iso:country":"US",
    "sg:address":"340 Shrewsbury St",
    "sg:city":"Worcester",
    "sg:classifiers":[
        {
            "category":"Manufacturing",
            "subcategory":"Printing",
            "type":"Manufacturing & Wholesale Goods"
        }
    ],
    "sg:phone":"+1 508 797 4788",
    "sg:postcode":"01604",
    "sg:province":"MA",
    "sg:tags":[
        "printer"
    ],
    "sg:website":"www.quickstopprinting.com",
    "wof:name":"Quick Stop",
    "wof:placetype":"venue"
},
  "geometry": {"coordinates":[-71.77818499999999,42.269765],"type":"Point"}
}