{
  "type": "Feature",
  "properties": {
    "addr:full":"95 Nancy Ave Dracut MA 01826",
    "addr:housenumber":"95",
    "addr:postcode":"01826",
    "addr:street":"Nancy Ave",
    "iso:country":"US",
    "sg:address":"95 Nancy Ave",
    "sg:city":"Dracut",
    "sg:classifiers":[
        {
            "category":"Professional",
            "subcategory":"Management & Consulting",
            "type":"Services"
        }
    ],
    "sg:phone":"+1 978 957 6603",
    "sg:postcode":"01826",
    "sg:province":"MA",
    "sg:tags":[
        "consultant",
        "printing"
    ],
    "wof:name":"Prepress Strategies",
    "wof:placetype":"venue"
},
  "geometry": {"coordinates":[-71.340175,42.682701],"type":"Point"}
}