{
  "type": "Feature",
  "properties": {
    "iso:country":"US",
    "sg:address":"96 S Main St",
    "sg:city":"Fall River",
    "sg:classifiers":[
        {
            "category":"Shopping",
            "subcategory":"Catalog Store",
            "type":"Retail Goods"
        }
    ],
    "sg:phone":"+1   ",
    "sg:postcode":"02721",
    "sg:province":"MA",
    "sg:tags":[
        "house",
        "mail"
    ],
    "wof:name":"Avon",
    "wof:placetype":"venue"
},
  "geometry": {"coordinates":[-71.15579099999999,41.700664],"type":"Point"}
}