{
  "type": "Feature",
  "properties": {
    "iso:country":"US",
    "sg:address":"57 Main St",
    "sg:city":"Swansea",
    "sg:classifiers":[
        {
            "category":"Organizations",
            "subcategory":"Religious Organization",
            "type":"Services"
        }
    ],
    "sg:phone":"+1 508 678 0923",
    "sg:postcode":"02777",
    "sg:province":"MA",
    "sg:tags":[
        "church"
    ],
    "sg:website":"www.christchurchswansea.org",
    "wof:name":"Christ Church",
    "wof:placetype":"venue"
},
  "geometry": {"coordinates":[-71.191311,41.749231],"type":"Point"}
}