{
  "type": "Feature",
  "properties": {
    "addr:full": "57 Main St Swansea MA 02777",
    "addr:housenumber": "57",
    "addr:postcode": "02777",
    "addr:street": "Main St",
    "iso:country": "US",
    "sg:address": "57 Main St",
    "sg:city": "Swansea",
    "sg:classifiers": [
      {
        "category": "Organizations",
        "subcategory": "Religious Organization",
        "type": "Services"
      }
    ],
    "sg:phone": "+1 508 678 0923",
    "sg:postcode": "02777",
    "sg:province": "MA",
    "sg:tags": [
      "church"
    ],
    "sg:website": "www.christchurchswansea.org",
    "wof:name": "Christ Church",
    "wof:placetype": "venue"
  },
  "geometry": {"coordinates":[-71.191311,41.749231],"type":"Point"}
}
