{
  "type": "Feature",
  "properties": {
    "addr:full": "23 E Main St Ware MA 01082",
    "addr:housenumber": "23",
    "addr:postcode": "01082",
    "addr:street": "E Main St",
    "iso:country": "US",
    "sg:address": "23 E Main St",
    "sg:city": "Ware",
    "sg:classifiers": [
      {
        "category": "Home \u0026 Garden",
        "subcategory": "Household Appliances",
        "type": "Retail Goods"
      }
    ],
    "sg:phone": "+1 413 967 6871",
    "sg:postcode": "01082",
    "sg:province": "MA",
    "wof:name": "Cluett Appliances",
    "wof:placetype": "venue"
  },
  "geometry": {"coordinates":[-72.235824,42.260431],"type":"Point"}
}
