{
  "type": "Feature",
  "properties": {
    "iso:country":"US",
    "sg:address":"23 E Main St",
    "sg:city":"Ware",
    "sg:classifiers":[
        {
            "category":"Home & Garden",
            "subcategory":"Household Appliances",
            "type":"Retail Goods"
        }
    ],
    "sg:phone":"+1 413 967 6871",
    "sg:postcode":"01082",
    "sg:province":"MA",
    "wof:name":"Cluett Appliances",
    "wof:placetype":"venue"
},
  "geometry": {"coordinates":[-72.23582399999999,42.260431],"type":"Point"}
}