{
  "type": "Feature",
  "properties": {
    "iso:country":"US",
    "sg:address":"94 W Cedar Street",
    "sg:city":"Boston",
    "sg:classifiers":[
        {
            "category":"Building & Trades",
            "subcategory":"Locksmith",
            "type":"Services"
        }
    ],
    "sg:phone":"+1 617 208 1167",
    "sg:postcode":"02114",
    "sg:province":"MA",
    "sg:tags":[
        "key"
    ],
    "wof:name":"1 24 Hour Emergency Locksmith",
    "wof:placetype":"venue"
},
  "geometry": {"coordinates":[-71.069861,42.361001],"type":"Point"}
}