{
  "type": "Feature",
  "properties": {
    "addr:full": "1 Harvard St Brookline MA 02445",
    "addr:housenumber": "1",
    "addr:postcode": "02445",
    "addr:street": "Harvard St",
    "iso:country": "US",
    "sg:address": "1 Harvard St",
    "sg:city": "Brookline",
    "sg:classifiers": [
      {
        "category": "Professional",
        "subcategory": "Management \u0026 Consulting",
        "type": "Services"
      }
    ],
    "sg:phone": "+1 617 713 3800",
    "sg:postcode": "02445",
    "sg:province": "MA",
    "sg:tags": [
      "marketing",
      "consultant"
    ],
    "wof:name": "Big Fish Communications",
    "wof:placetype": "venue"
  },
  "geometry": {"coordinates":[-71.11886,42.33376],"type":"Point"}
}
