{
  "type": "Feature",
  "properties": {
    "addr:full":"3 Witherbee Ln Southborough MA 01772",
    "addr:housenumber":"3",
    "addr:postcode":"01772",
    "addr:street":"Witherbee Ln",
    "iso:country":"US",
    "sg:address":"3 Witherbee Ln",
    "sg:city":"Southborough",
    "sg:classifiers":[
        {
            "category":"Professional",
            "subcategory":"Management & Consulting",
            "type":"Services"
        }
    ],
    "sg:phone":"+1 508 875 1670",
    "sg:postcode":"01772",
    "sg:province":"MA",
    "sg:tags":[
        "consultant"
    ],
    "wof:name":"J Biz Ltd",
    "wof:placetype":"venue"
},
  "geometry": {"coordinates":[-71.491854,42.31552],"type":"Point"}
}