{
  "type": "Feature",
  "properties": {
    "addr:full":"547 Boston Post Rd E Marlborough MA 01752",
    "addr:housenumber":"547",
    "addr:postcode":"01752",
    "addr:street":"Boston Post Rd E",
    "iso:country":"US",
    "sg:address":"547 Boston Post Rd E",
    "sg:city":"Marlborough",
    "sg:classifiers":[
        {
            "category":"Real Estate",
            "subcategory":"Real Estate Agent",
            "type":"Services"
        }
    ],
    "sg:phone":"+1 508 485 9895",
    "sg:postcode":"01752",
    "sg:province":"MA",
    "wof:name":"Suacasa Inc",
    "wof:placetype":"venue"
},
  "geometry": {"coordinates":[-71.508067,42.347744],"type":"Point"}
}