{
  "type": "Feature",
  "properties": {
    "iso:country":"US",
    "sg:address":"299 Everett Avenue",
    "sg:city":"Chelsea",
    "sg:classifiers":[
        {
            "category":"Education",
            "subcategory":"School",
            "type":"Public Place"
        }
    ],
    "sg:phone":"+1 617 889 8449",
    "sg:postcode":"02150",
    "sg:province":"MA",
    "sg:tags":[
        "high",
        "middle",
        "elementary"
    ],
    "wof:name":"Mgh Chelsea Healthcare Center",
    "wof:placetype":"venue"
},
  "geometry": {"coordinates":[-71.04148499999999,42.401066],"type":"Point"}
}