{
  "type": "Feature",
  "properties": {
    "iso:country":"US",
    "sg:address":"885 Boylston St",
    "sg:city":"Boston",
    "sg:classifiers":[
        {
            "category":"Restaurant",
            "type":"Food & Drink"
        }
    ],
    "sg:phone":"+1   ",
    "sg:postcode":"02116",
    "sg:province":"MA",
    "sg:tags":[
        "drinking",
        "eating"
    ],
    "wof:name":"Wiskeys Smoke House",
    "wof:placetype":"venue"
},
  "geometry": {"coordinates":[-71.082027,42.348936],"type":"Point"}
}