{
  "type": "Feature",
  "properties": {
    "addr:full":"11 Sherwood Rd Norfolk MA 02056",
    "addr:housenumber":"11",
    "addr:postcode":"02056",
    "addr:street":"Sherwood Rd",
    "iso:country":"US",
    "sg:address":"11 Sherwood Rd",
    "sg:city":"Norfolk",
    "sg:classifiers":[
        {
            "category":"Building & Trades",
            "subcategory":"Plumbing",
            "type":"Services"
        }
    ],
    "sg:phone":"+1 508 384 8850",
    "sg:postcode":"02056",
    "sg:province":"MA",
    "sg:tags":[
        "septic"
    ],
    "wof:name":"J Hockman Inc Septic Svc",
    "wof:placetype":"venue"
},
  "geometry": {"coordinates":[-71.30234,42.093767],"type":"Point"}
}