{
  "type": "Feature",
  "properties": {
    "iso:country":"US",
    "sg:address":"159 Torrey St",
    "sg:city":"Brockton",
    "sg:classifiers":[
        {
            "category":"Recreation",
            "type":"Entertainment"
        }
    ],
    "sg:phone":"+1 508 586 2171",
    "sg:postcode":"02301",
    "sg:province":"MA",
    "sg:tags":[
        "course",
        "golf"
    ],
    "wof:name":"Thorny Lea Golf Club",
    "wof:placetype":"venue"
},
  "geometry": {"coordinates":[-71.049536,42.073205],"type":"Point"}
}