{
  "type": "Feature",
  "properties": {
    "iso:country":"US",
    "sg:address":"27 King St",
    "sg:city":"Westfield",
    "sg:classifiers":[
        {
            "category":"Building & Trades",
            "subcategory":"Construction",
            "type":"Services"
        }
    ],
    "sg:phone":"+1 413 572 4663",
    "sg:postcode":"01085",
    "sg:province":"MA",
    "sg:tags":[
        "project"
    ],
    "wof:name":"D R Berndt Inc",
    "wof:placetype":"venue"
},
  "geometry": {"coordinates":[-72.75664999999999,42.122009],"type":"Point"}
}