{
  "type": "Feature",
  "properties": {
    "addr:full":"120 Charles St Boston MA 02114",
    "addr:housenumber":"120",
    "addr:postcode":"02114",
    "addr:street":"Charles St",
    "iso:country":"US",
    "sg:address":"120 Charles St",
    "sg:city":"Boston",
    "sg:classifiers":[
        {
            "category":"Real Estate",
            "subcategory":"Real Estate Agent",
            "type":"Services"
        }
    ],
    "sg:phone":"+1 617 523 2399",
    "sg:postcode":"02114",
    "sg:province":"MA",
    "sg:website":"www.beaconhillapartments.com",
    "wof:name":"Capitol Realty Group",
    "wof:placetype":"venue"
},
  "geometry": {"coordinates":[-71.070832,42.359004],"type":"Point"}
}