{
  "type": "Feature",
  "properties": {
    "iso:country":"US",
    "sg:address":"1545 Tremont St",
    "sg:city":"Roxbury Crossing",
    "sg:classifiers":[
        {
            "category":"Organizations",
            "subcategory":"Religious Organization",
            "type":"Services"
        }
    ],
    "sg:phone":"+1 617 442 3938",
    "sg:postcode":"02120",
    "sg:province":"MA",
    "sg:tags":[
        "church"
    ],
    "wof:name":"Healing & Restoration Prayer Line",
    "wof:placetype":"venue"
},
  "geometry": {"coordinates":[-71.10030399999999,42.332699],"type":"Point"}
}