{
  "type": "Feature",
  "properties": {
    "addr:full": "1545 Tremont St Roxbury Crossing MA 02120",
    "addr:housenumber": "1545",
    "addr:postcode": "02120",
    "addr:street": "Tremont St",
    "iso:country": "US",
    "sg:address": "1545 Tremont St",
    "sg:city": "Roxbury Crossing",
    "sg:classifiers": [
      {
        "category": "Organizations",
        "subcategory": "Religious Organization",
        "type": "Services"
      }
    ],
    "sg:phone": "+1 617 442 3938",
    "sg:postcode": "02120",
    "sg:province": "MA",
    "sg:tags": [
      "church"
    ],
    "wof:name": "Healing \u0026 Restoration Prayer Line",
    "wof:placetype": "venue"
  },
  "geometry": {"coordinates":[-71.100304,42.332699],"type":"Point"}
}
