{
  "type": "Feature",
  "properties": {
    "addr:full":"214 Commercial St Malden MA 02148",
    "addr:housenumber":"214",
    "addr:postcode":"02148",
    "addr:street":"Commercial St",
    "iso:country":"US",
    "sg:address":"214 Commercial St",
    "sg:city":"Malden",
    "sg:classifiers":[
        {
            "category":"Building & Trades",
            "subcategory":"Electrical",
            "type":"Services"
        }
    ],
    "sg:phone":"+1 781 321 6366",
    "sg:postcode":"02148",
    "sg:province":"MA",
    "sg:tags":[
        "electric",
        "contractor"
    ],
    "wof:name":"Ace's Electrical Corp",
    "wof:placetype":"venue"
},
  "geometry": {"coordinates":[-71.07542100000001,42.420906],"type":"Point"}
}