{
  "type": "Feature",
  "properties": {
    "addr:full": "23 Bowditch Rd Jamaica Plain MA 02130",
    "addr:housenumber": "23",
    "addr:postcode": "02130",
    "addr:street": "Bowditch Rd",
    "iso:country": "US",
    "sg:address": "23 Bowditch Rd",
    "sg:city": "Jamaica Plain",
    "sg:classifiers": [
      {
        "category": "Health Services",
        "subcategory": "Dentist",
        "type": "Services"
      }
    ],
    "sg:phone": "+1 617 524 1199",
    "sg:postcode": "02130",
    "sg:province": "MA",
    "wof:name": "Morgan Vincent J DMD",
    "wof:placetype": "venue"
  },
  "geometry": {"coordinates":[-71.125438,42.310805],"type":"Point"}
}
