{
  "type": "Feature",
  "properties": {
    "iso:country":"US",
    "sg:address":"661 State Hwy 2",
    "sg:city":"Arlington",
    "sg:classifiers":[
        {
            "category":"Professional",
            "subcategory":"Management & Consulting",
            "type":"Services"
        }
    ],
    "sg:phone":"+1   ",
    "sg:postcode":"02476",
    "sg:province":"MA",
    "sg:tags":[
        "business"
    ],
    "wof:name":"Heeltoe Consulting",
    "wof:placetype":"venue"
},
  "geometry": {"coordinates":[-71.170092,42.407824],"type":"Point"}
}