{
  "type": "Feature",
  "properties": {
    "iso:country":"US",
    "sg:address":"544 Boston Post Rd",
    "sg:city":"Weston",
    "sg:classifiers":[
        {
            "category":"Personal",
            "subcategory":"Beauty Salon",
            "type":"Services"
        }
    ],
    "sg:phone":"+1 781 899 5588",
    "sg:postcode":"02493",
    "sg:province":"MA",
    "wof:name":"Masterworx Of Hair Design",
    "wof:placetype":"venue"
},
  "geometry": {"coordinates":[-71.301412,42.36718],"type":"Point"}
}