{
  "type": "Feature",
  "properties": {
    "addr:full": "130 Sconticut Neck Rd Fairhaven MA 02719",
    "addr:housenumber": "130",
    "addr:postcode": "02719",
    "addr:street": "Sconticut Neck Rd",
    "iso:country": "US",
    "ovtr:label": "Sivalai Thai Cuisine, 130 Sconticut Neck Rd Fairhaven MA US",
    "ovtr:similarity": 2.160170078277588,
    "sg:address": "130 Sconticut Neck Rd",
    "sg:city": "Fairhaven",
    "sg:phone": "+1 508 999 2527",
    "sg:postcode": "02719",
    "sg:province": "MA",
    "wof:name": "Sivalai Thai Cuisine",
    "wof:placetype": "venue"
  },
  "geometry": {"coordinates":[-70.875969,41.633137],"type":"Point"}
}
