{
  "type": "Feature",
  "properties": {
    "iso:country":"US",
    "sg:address":"130 Sconticut Neck Rd",
    "sg:city":"Fairhaven",
    "sg:phone":"+1 508 999 2527",
    "sg:postcode":"02719",
    "sg:province":"MA",
    "wof:name":"Sivalai Thai Cuisine",
    "wof:placetype":"venue"
},
  "geometry": {"coordinates":[-70.875969,41.633137],"type":"Point"}
}