{
  "type": "Feature",
  "properties": {
    "addr:full":"3 Water St Newburyport MA 01950",
    "addr:housenumber":"3",
    "addr:postcode":"01950",
    "addr:street":"Water St",
    "iso:country":"US",
    "sg:address":"3 Water St",
    "sg:city":"Newburyport",
    "sg:classifiers":[
        {
            "category":"Real Estate",
            "subcategory":"Real Estate Operator",
            "type":"Services"
        }
    ],
    "sg:phone":"+1 978 465 9371",
    "sg:postcode":"01950",
    "sg:province":"MA",
    "sg:tags":[
        "apartment"
    ],
    "sg:website":"www.karelisrealty.com",
    "wof:name":"Karelis Realty & Management",
    "wof:placetype":"venue"
},
  "geometry": {"coordinates":[-70.86930099999999,42.811798],"type":"Point"}
}