{
  "type": "Feature",
  "properties": {
    "addr:full": "192 Merrimack St Haverhill MA 01830",
    "addr:housenumber": "192",
    "addr:postcode": "01830",
    "addr:street": "Merrimack St",
    "iso:country": "US",
    "sg:address": "192 Merrimack St",
    "sg:city": "Haverhill",
    "sg:classifiers": [
      {
        "category": "Shopping",
        "subcategory": "Discount \u0026 Variety Stores",
        "type": "Retail Goods"
      }
    ],
    "sg:phone": "+1 978 521 6552",
    "sg:postcode": "01830",
    "sg:province": "MA",
    "sg:tags": [
      "merchandise",
      "general"
    ],
    "wof:name": "Garand's Discount",
    "wof:placetype": "venue"
  },
  "geometry": {"coordinates":[-71.081107,42.773965],"type":"Point"}
}
