{
  "type": "Feature",
  "properties": {
    "addr:full":"18 Congress Ave Chelsea MA 02150",
    "addr:housenumber":"18",
    "addr:postcode":"02150",
    "addr:street":"Congress Ave",
    "iso:country":"US",
    "sg:address":"18 Congress Ave",
    "sg:city":"Chelsea",
    "sg:classifiers":[
        {
            "category":"Building & Trades",
            "subcategory":"Locksmith",
            "type":"Services"
        }
    ],
    "sg:phone":"+1 617 819 3415",
    "sg:postcode":"02150",
    "sg:province":"MA",
    "sg:tags":[
        "key"
    ],
    "wof:name":"Locksmith Chelsea 123 24 A Day Emergency",
    "wof:placetype":"venue"
},
  "geometry": {"coordinates":[-71.036969,42.390467],"type":"Point"}
}