{
  "type": "Feature",
  "properties": {
    "addr:full": "57 Slab Bridge Rd Assonet MA 02702",
    "addr:housenumber": "57",
    "addr:postcode": "02702",
    "addr:street": "Slab Bridge Rd",
    "iso:country": "US",
    "sg:address": "57 Slab Bridge Rd",
    "sg:city": "Assonet",
    "sg:classifiers": [
      {
        "category": "Wholesale",
        "subcategory": "Electrical",
        "type": "Manufacturing \u0026 Wholesale Goods"
      }
    ],
    "sg:phone": "+1   ",
    "sg:postcode": "02702",
    "sg:province": "MA",
    "sg:tags": [
      "electronic"
    ],
    "wof:name": "East Coast Electronics",
    "wof:placetype": "venue"
  },
  "geometry": {"coordinates":[-71.030404,41.773053],"type":"Point"}
}
