{
  "type": "Feature",
  "properties": {
    "iso:country":"US",
    "sg:address":"100 Ontario St",
    "sg:city":"Lynn",
    "sg:classifiers":[
        {
            "category":"Building & Trades",
            "subcategory":"Landscaping Services",
            "type":"Services"
        }
    ],
    "sg:phone":"+1 781 477 0101",
    "sg:postcode":"01904",
    "sg:province":"MA",
    "sg:tags":[
        "lawn",
        "gardener"
    ],
    "wof:name":"J & J Landscaping",
    "wof:placetype":"venue"
},
  "geometry": {"coordinates":[-70.965976,42.474782],"type":"Point"}
}