{
  "type": "Feature",
  "properties": {
    "addr:full": "40 River St Boston MA 02108",
    "addr:housenumber": "40",
    "addr:postcode": "02108",
    "addr:street": "River St",
    "iso:country": "US",
    "sg:address": "40 River St",
    "sg:city": "Boston",
    "sg:classifiers": [
      {
        "category": "Shopping",
        "subcategory": "Used Merchandise",
        "type": "Retail Goods"
      }
    ],
    "sg:phone": "+1 617 227 9261",
    "sg:postcode": "02108",
    "sg:province": "MA",
    "sg:tags": [
      "antique"
    ],
    "wof:name": "Forty River Street Antiques",
    "wof:placetype": "venue"
  },
  "geometry": {"coordinates":[-71.070297,42.357201],"type":"Point"}
}
