{
  "type": "Feature",
  "properties": {
    "addr:full": "800 Washington Avenue Revere MA 02151",
    "addr:housenumber": "800",
    "addr:postcode": "02151",
    "addr:street": "Washington Avenue",
    "iso:country": "US",
    "sg:address": "800 Washington Avenue",
    "sg:city": "Revere",
    "sg:classifiers": [
      {
        "category": "Retail",
        "subcategory": "Auto Repair",
        "type": "Services"
      }
    ],
    "sg:phone": "+1 781 322 2565",
    "sg:postcode": "02151",
    "sg:province": "MA",
    "wof:name": "Advanced Custom Cycles",
    "wof:placetype": "venue"
  },
  "geometry": {"coordinates":[-71.023482,42.43094],"type":"Point"}
}
