{
  "type": "Feature",
  "properties": {
    "iso:country":"US",
    "sg:address":"425 Brookline Ave",
    "sg:city":"Boston",
    "sg:classifiers":[
        {
            "category":"Building & Trades",
            "subcategory":"Locksmith",
            "type":"Services"
        }
    ],
    "sg:phone":"+1 617 303 2708",
    "sg:postcode":"02215",
    "sg:province":"MA",
    "sg:tags":[
        "key"
    ],
    "wof:name":"Smouth Locksmith",
    "wof:placetype":"venue"
},
  "geometry": {"coordinates":[-71.107895,42.338522],"type":"Point"}
}