{
  "type": "Feature",
  "properties": {
    "iso:country":"US",
    "sg:address":"110 State Rd",
    "sg:city":"Buzzards Bay",
    "sg:classifiers":[
        {
            "category":"Building & Trades",
            "subcategory":"Construction",
            "type":"Services"
        }
    ],
    "sg:phone":"+1 508 833 0800",
    "sg:postcode":"02532",
    "sg:province":"MA",
    "sg:tags":[
        "contractor"
    ],
    "wof:name":"Bay Colony Builders Inc - CLOSED",
    "wof:placetype":"venue"
},
  "geometry": {"coordinates":[-70.597702,41.749901],"type":"Point"}
}