{
  "type": "Feature",
  "properties": {
    "addr:full":"185 Plain St Rockland MA 02370",
    "addr:housenumber":"185",
    "addr:postcode":"02370",
    "addr:street":"Plain St",
    "iso:country":"US",
    "sg:address":"185 Plain St",
    "sg:city":"Rockland",
    "sg:classifiers":[
        {
            "category":"Professional",
            "type":"Services"
        }
    ],
    "sg:phone":"+1 781 982 3170",
    "sg:postcode":"02370",
    "sg:province":"MA",
    "sg:tags":[
        "arts",
        "artist"
    ],
    "wof:name":"Sandy Cove Gallery",
    "wof:placetype":"venue"
},
  "geometry": {"coordinates":[-70.920929,42.124631],"type":"Point"}
}