{
  "type": "Feature",
  "properties": {
    "addr:full": "1020 Riverdale St West Springfield MA 01089",
    "addr:housenumber": "1020",
    "addr:postcode": "01089",
    "addr:street": "Riverdale St",
    "iso:country": "US",
    "sg:address": "1020 Riverdale St",
    "sg:city": "West Springfield",
    "sg:classifiers": [
      {
        "category": "Home \u0026 Garden",
        "subcategory": "Furniture",
        "type": "Retail Goods"
      }
    ],
    "sg:phone": "+1 413 746 5230",
    "sg:postcode": "01089",
    "sg:province": "MA",
    "wof:name": "Hopbrook Products",
    "wof:placetype": "venue"
  },
  "geometry": {"coordinates":[-72.626112,42.132453],"type":"Point"}
}
