{
  "type": "Feature",
  "properties": {
    "addr:full": "110 North St Ware MA 01082",
    "addr:housenumber": "110",
    "addr:postcode": "01082",
    "addr:street": "North St",
    "iso:country": "US",
    "sg:address": "110 North St",
    "sg:city": "Ware",
    "sg:classifiers": [
      {
        "category": "Building \u0026 Trades",
        "subcategory": "Electrical",
        "type": "Services"
      }
    ],
    "sg:phone": "+1 413 277 9993",
    "sg:postcode": "01082",
    "sg:province": "MA",
    "sg:tags": [
      "electric",
      "contractor"
    ],
    "wof:name": "Vadnais Electric",
    "wof:placetype": "venue"
  },
  "geometry": {"coordinates":[-72.239921,42.265365],"type":"Point"}
}
