{
  "type": "Feature",
  "properties": {
    "iso:country":"US",
    "sg:address":"31 2nd Street",
    "sg:city":"Chelsea",
    "sg:classifiers":[
        {
            "category":"Autos & Motor Vehicles",
            "subcategory":"Fuel & Gas Station",
            "type":"Retail Goods"
        }
    ],
    "sg:phone":"+1 617 884 9492",
    "sg:postcode":"02150",
    "sg:province":"MA",
    "wof:name":"Reggie's Service",
    "wof:placetype":"venue"
},
  "geometry": {"coordinates":[-71.039917,42.390376],"type":"Point"}
}