{
  "type": "Feature",
  "properties": {
    "iso:country":"US",
    "sg:address":"170 Milk St Ste 3",
    "sg:city":"Boston",
    "sg:classifiers":[
        {
            "category":"Professional",
            "subcategory":"Lawyer & Legal Services",
            "type":"Services"
        }
    ],
    "sg:phone":"+1 617 728 7227",
    "sg:postcode":"02109",
    "sg:province":"MA",
    "sg:tags":[
        "personal",
        "injury"
    ],
    "wof:name":"Garrity Donald P Atty",
    "wof:placetype":"venue"
},
  "geometry": {"coordinates":[-71.052471,42.358636],"type":"Point"}
}