{
  "type": "Feature",
  "properties": {
    "iso:country":"US",
    "sg:address":"23 Hawthorn St",
    "sg:city":"Cambridge",
    "sg:classifiers":[
        {
            "category":"Health Services",
            "subcategory":"Doctor",
            "type":"Services"
        }
    ],
    "sg:phone":"+1   ",
    "sg:postcode":"02138",
    "sg:province":"MA",
    "sg:tags":[
        "medical"
    ],
    "wof:name":"Brazelton T Berry MD",
    "wof:placetype":"venue"
},
  "geometry": {"coordinates":[-71.125646,42.37623],"type":"Point"}
}