{
  "type": "Feature",
  "properties": {
    "addr:full":"732 Harrison Avenue Boston MA 02118",
    "addr:housenumber":"732",
    "addr:postcode":"02118",
    "addr:street":"Harrison Avenue",
    "iso:country":"US",
    "sg:address":"732 Harrison Avenue",
    "sg:city":"Boston",
    "sg:classifiers":[
        {
            "category":"Sports & Exercise",
            "subcategory":"Gym",
            "type":"Entertainment"
        }
    ],
    "sg:phone":"+1 617 638 7460",
    "sg:postcode":"02118",
    "sg:province":"MA",
    "sg:tags":[
        "trainer"
    ],
    "wof:name":"Boston University Medical Group",
    "wof:placetype":"venue"
},
  "geometry": {"coordinates":[-71.07166100000001,42.337906],"type":"Point"}
}