{
  "type": "Feature",
  "properties": {
    "addr:full":"42 Quanapoag Rd East Freetown MA 02717",
    "addr:housenumber":"42",
    "addr:postcode":"02717",
    "addr:street":"Quanapoag Rd",
    "iso:country":"US",
    "sg:address":"42 Quanapoag Rd",
    "sg:city":"East Freetown",
    "sg:classifiers":[
        {
            "category":"Autos & Motor Vehicles",
            "subcategory":"Automobile Sales",
            "type":"Retail Goods"
        }
    ],
    "sg:phone":"+1 508 763 5927",
    "sg:postcode":"02717",
    "sg:province":"MA",
    "sg:tags":[
        "truck"
    ],
    "wof:name":"Big Wheel",
    "wof:placetype":"venue"
},
  "geometry": {"coordinates":[-70.975291,41.72965],"type":"Point"}
}