{
  "type": "Feature",
  "properties": {
    "iso:country":"US",
    "sg:address":"105 Harnden Ave",
    "sg:city":"Watertown",
    "sg:classifiers":[
        {
            "category":"Building & Trades",
            "subcategory":"Construction",
            "type":"Services"
        }
    ],
    "sg:phone":"+1 617 923 2820",
    "sg:postcode":"02472",
    "sg:province":"MA",
    "sg:tags":[
        "contractor"
    ],
    "wof:name":"Accurate Building",
    "wof:placetype":"venue"
},
  "geometry": {"coordinates":[-71.184864,42.378858],"type":"Point"}
}