{
  "type": "Feature",
  "properties": {
    "addr:full": "80 Main St Pepperell MA 01463",
    "addr:housenumber": "80",
    "addr:postcode": "01463",
    "addr:street": "Main St",
    "iso:country": "US",
    "sg:address": "80 Main St",
    "sg:city": "Pepperell",
    "sg:classifiers": [
      {
        "category": "Banks \u0026 Credit Unions",
        "subcategory": "Bank",
        "type": "Services"
      }
    ],
    "sg:phone": "+1 978 433 2552",
    "sg:postcode": "01463",
    "sg:province": "MA",
    "sg:website": "www.nmsb.com",
    "wof:name": "North Middlesex Savings Bank",
    "wof:placetype": "venue"
  },
  "geometry": {"coordinates":[-71.581242,42.665422],"type":"Point"}
}
