{
  "type": "Feature",
  "properties": {
    "iso:country":"US",
    "sg:address":"10 Taunton St",
    "sg:city":"Plainville",
    "sg:classifiers":[
        {
            "category":"Autos & Motor Vehicles",
            "subcategory":"Fuel & Gas Station",
            "type":"Retail Goods"
        }
    ],
    "sg:phone":"+1 508 699 7827",
    "sg:postcode":"02762",
    "sg:province":"MA",
    "sg:tags":[
        "oil"
    ],
    "wof:name":"Plainville Shell",
    "wof:placetype":"venue"
},
  "geometry": {"coordinates":[-71.30428999999999,42.00917],"type":"Point"}
}