{
  "type": "Feature",
  "properties": {
    "addr:full": "10 Taunton St Plainville MA 02762",
    "addr:housenumber": "10",
    "addr:postcode": "02762",
    "addr:street": "Taunton St",
    "iso:country": "US",
    "ovtr:label": "Shell Plainville, 10 Taunton St Plainville MA US",
    "ovtr:similarity": 3.463685989379883,
    "sg:address": "10 Taunton St",
    "sg:city": "Plainville",
    "sg:classifiers": [
      {
        "category": "Autos \u0026 Motor Vehicles",
        "subcategory": "Fuel \u0026 Gas Station",
        "type": "Retail Goods"
      }
    ],
    "sg:phone": "+1 508 699 7827",
    "sg:postcode": "02762",
    "sg:province": "MA",
    "sg:tags": [
      "oil"
    ],
    "wof:name": "Plainville Shell",
    "wof:placetype": "venue"
  },
  "geometry": {"coordinates":[-71.30429,42.00917],"type":"Point"}
}
