{
  "type": "Feature",
  "properties": {
    "addr:full": "89 Appleton St Lowell MA 01852",
    "addr:housenumber": "89",
    "addr:postcode": "01852",
    "addr:street": "Appleton St",
    "iso:country": "US",
    "sg:address": "89 Appleton St",
    "sg:city": "Lowell",
    "sg:classifiers": [
      {
        "category": "Government",
        "subcategory": "Jail",
        "type": "Public Place"
      }
    ],
    "sg:phone": "+1 978 441 3160",
    "sg:postcode": "01852",
    "sg:province": "MA",
    "sg:tags": [
      "govt",
      "state",
      "institution"
    ],
    "wof:name": "Juvenile Court Probation Ofc",
    "wof:placetype": "venue"
  },
  "geometry": {"coordinates":[-71.308752,42.641054],"type":"Point"}
}
