{
  "type": "Feature",
  "properties": {
    "iso:country":"US",
    "sg:address":"49 Eutaw Ave",
    "sg:city":"Lynn",
    "sg:classifiers":[
        {
            "category":"Wholesale",
            "subcategory":"Vending Machines",
            "type":"Manufacturing & Wholesale Goods"
        }
    ],
    "sg:phone":"+1   ",
    "sg:postcode":"01902",
    "sg:province":"MA",
    "sg:tags":[
        "operator"
    ],
    "wof:name":"Crompton & Sonsa Vending",
    "wof:placetype":"venue"
},
  "geometry": {"coordinates":[-70.940099,42.476959],"type":"Point"}
}