{
  "type": "Feature",
  "properties": {
    "addr:full": "49 Eutaw Ave Lynn MA 01902",
    "addr:housenumber": "49",
    "addr:postcode": "01902",
    "addr:street": "Eutaw Ave",
    "iso:country": "US",
    "sg:address": "49 Eutaw Ave",
    "sg:city": "Lynn",
    "sg:classifiers": [
      {
        "category": "Wholesale",
        "subcategory": "Vending Machines",
        "type": "Manufacturing \u0026 Wholesale Goods"
      }
    ],
    "sg:phone": "+1   ",
    "sg:postcode": "01902",
    "sg:province": "MA",
    "sg:tags": [
      "operator"
    ],
    "wof:name": "Crompton \u0026 Sonsa Vending",
    "wof:placetype": "venue"
  },
  "geometry": {"coordinates":[-70.940099,42.476959],"type":"Point"}
}
