{
  "type": "Feature",
  "properties": {
    "addr:full": "314 Gifford St Falmouth MA 02540",
    "addr:housenumber": "314",
    "addr:postcode": "02540",
    "addr:street": "Gifford St",
    "iso:country": "US",
    "sg:address": "314 Gifford St",
    "sg:city": "Falmouth",
    "sg:classifiers": [
      {
        "category": "Professional",
        "subcategory": "Lawyer \u0026 Legal Services",
        "type": "Services"
      }
    ],
    "sg:phone": "+1 508 495 4454",
    "sg:postcode": "02540",
    "sg:province": "MA",
    "sg:tags": [
      "attorney"
    ],
    "wof:name": "D'Oliveira \u0026 Morgan",
    "wof:placetype": "venue"
  },
  "geometry": {"coordinates":[-70.610336,41.56079],"type":"Point"}
}
