{
  "type": "Feature",
  "properties": {
    "iso:country":"US",
    "sg:address":"314 Gifford St",
    "sg:city":"Falmouth",
    "sg:classifiers":[
        {
            "category":"Professional",
            "subcategory":"Lawyer & Legal Services",
            "type":"Services"
        }
    ],
    "sg:phone":"+1 508 495 4454",
    "sg:postcode":"02540",
    "sg:province":"MA",
    "sg:tags":[
        "attorney"
    ],
    "wof:name":"D'Oliveira & Morgan",
    "wof:placetype":"venue"
},
  "geometry": {"coordinates":[-70.610336,41.56079],"type":"Point"}
}