{
  "type": "Feature",
  "properties": {
    "iso:country":"US",
    "sg:address":"25 Burncoat St",
    "sg:city":"Worcester",
    "sg:classifiers":[
        {
            "category":"Education",
            "subcategory":"Special Training",
            "type":"Public Place"
        }
    ],
    "sg:phone":"+1 508 852 7875",
    "sg:postcode":"01605",
    "sg:province":"MA",
    "sg:tags":[
        "tutoring"
    ],
    "wof:name":"Nancy K Lea",
    "wof:placetype":"venue"
},
  "geometry": {"coordinates":[-71.790695,42.288206],"type":"Point"}
}