{
  "type": "Feature",
  "properties": {
    "iso:country":"US",
    "sg:address":"186 S Main St",
    "sg:city":"Fall River",
    "sg:classifiers":[
        {
            "category":"Professional",
            "subcategory":"Management & Consulting",
            "type":"Services"
        }
    ],
    "sg:phone":"+1 508 674 6003",
    "sg:postcode":"02721",
    "sg:province":"MA",
    "sg:tags":[
        "consultant"
    ],
    "wof:name":"Peter's Sleeper Assoc",
    "wof:placetype":"venue"
},
  "geometry": {"coordinates":[-71.157023,41.699764],"type":"Point"}
}