{
  "type": "Feature",
  "properties": {
    "addr:full": "52 Beacon Street Somerville MA 02143",
    "addr:housenumber": "52",
    "addr:postcode": "02143",
    "addr:street": "Beacon Street",
    "iso:country": "US",
    "sg:address": "52 Beacon Street",
    "sg:city": "Somerville",
    "sg:classifiers": [
      {
        "category": "Real Estate",
        "subcategory": "Real Estate Services",
        "type": "Services"
      }
    ],
    "sg:phone": "+1 617 354 4900",
    "sg:postcode": "02143",
    "sg:province": "MA",
    "sg:tags": [
      "management",
      "property"
    ],
    "wof:name": "Elliot Management",
    "wof:placetype": "venue"
  },
  "geometry": {"coordinates":[-71.103232,42.375862],"type":"Point"}
}
