{
  "type": "Feature",
  "properties": {
    "addr:full": "8 Cedar St Woburn MA 01801",
    "addr:housenumber": "8",
    "addr:postcode": "01801",
    "addr:street": "Cedar St",
    "iso:country": "US",
    "sg:address": "8 Cedar St",
    "sg:city": "Woburn",
    "sg:classifiers": [
      {
        "category": "Professional",
        "subcategory": "Lawyer \u0026 Legal Services",
        "type": "Services"
      }
    ],
    "sg:phone": "+1 781 933 0940",
    "sg:postcode": "01801",
    "sg:province": "MA",
    "wof:name": "Curtis Geoffrey A Atty",
    "wof:placetype": "venue"
  },
  "geometry": {"coordinates":[-71.126297,42.493698],"type":"Point"}
}
