{
  "type": "Feature",
  "properties": {
    "iso:country":"US",
    "sg:address":"719 Main St",
    "sg:city":"Osterville",
    "sg:classifiers":[
        {
            "category":"Health Services",
            "subcategory":"Health Practitioner",
            "type":"Services"
        }
    ],
    "sg:phone":"+1 508 428 0300",
    "sg:postcode":"02655",
    "sg:province":"MA",
    "sg:tags":[
        "therapy",
        "physical"
    ],
    "sg:website":"www.physical-therapy-centers.com",
    "wof:name":"Physical Therapy Center the",
    "wof:placetype":"venue"
},
  "geometry": {"coordinates":[-70.383301,41.627899],"type":"Point"}
}