{
  "type": "Feature",
  "properties": {
    "addr:full":"2 Shaker Rd Shirley MA 01464",
    "addr:housenumber":"2",
    "addr:postcode":"01464",
    "addr:street":"Shaker Rd",
    "iso:country":"US",
    "sg:address":"2 Shaker Rd",
    "sg:city":"Shirley",
    "sg:classifiers":[
        {
            "category":"Manufacturing",
            "subcategory":"Printing",
            "type":"Manufacturing & Wholesale Goods"
        }
    ],
    "sg:phone":"+1 978 425 2455",
    "sg:postcode":"01464",
    "sg:province":"MA",
    "sg:tags":[
        "commercial",
        "lithographic"
    ],
    "wof:name":"Len Art Press",
    "wof:placetype":"venue"
},
  "geometry": {"coordinates":[-71.64772000000001,42.541711],"type":"Point"}
}