{
  "type": "Feature",
  "properties": {
    "addr:full": "363 N Main St Mansfield MA 02048",
    "addr:housenumber": "363",
    "addr:postcode": "02048",
    "addr:street": "N Main St",
    "iso:country": "US",
    "ovtr:label": "Grogan Marciano Sporting Goods, 363 N Main St Mansfield MA US",
    "ovtr:similarity": 1.584190011024475,
    "sg:address": "363 N Main St",
    "sg:city": "Mansfield",
    "sg:classifiers": [
      {
        "category": "Shopping",
        "subcategory": "Bicycles \u0026 Sporting Goods",
        "type": "Retail Goods"
      }
    ],
    "sg:phone": "+1 508 339 2945",
    "sg:postcode": "02048",
    "sg:province": "MA",
    "wof:name": "Grogan Marciano Sporting Goods",
    "wof:placetype": "venue"
  },
  "geometry": {"coordinates":[-71.218634,42.032428],"type":"Point"}
}
