{
  "type": "Feature",
  "properties": {
    "addr:full":"363 N Main St Mansfield MA 02048",
    "addr:housenumber":"363",
    "addr:postcode":"02048",
    "addr:street":"N Main St",
    "iso:country":"US",
    "sg:address":"363 N Main St",
    "sg:city":"Mansfield",
    "sg:classifiers":[
        {
            "category":"Shopping",
            "subcategory":"Bicycles & Sporting Goods",
            "type":"Retail Goods"
        }
    ],
    "sg:phone":"+1 508 339 2945",
    "sg:postcode":"02048",
    "sg:province":"MA",
    "wof:name":"Grogan Marciano Sporting Goods",
    "wof:placetype":"venue"
},
  "geometry": {"coordinates":[-71.21863399999999,42.032428],"type":"Point"}
}