{
  "type": "Feature",
  "properties": {
    "iso:country":"US",
    "sg:address":"104 Alden Rd",
    "sg:city":"Fairhaven",
    "sg:classifiers":[
        {
            "category":"Restaurant",
            "type":"Food & Drink"
        }
    ],
    "sg:phone":"+1 508 990 7786",
    "sg:postcode":"02719",
    "sg:province":"MA",
    "wof:name":"Jake's Diner",
    "wof:placetype":"venue"
},
  "geometry": {"coordinates":[-70.88686800000001,41.646382],"type":"Point"}
}