{
  "type": "Feature",
  "properties": {
    "addr:full": "15 Union Ave Sudbury MA 01776",
    "addr:housenumber": "15",
    "addr:postcode": "01776",
    "addr:street": "Union Ave",
    "iso:country": "US",
    "ovtr:label": "Sudbury Coffee Works, 15 Union Ave Sudbury MA US",
    "ovtr:similarity": 2.850393056869507,
    "sg:address": "15 Union Ave",
    "sg:city": "Sudbury",
    "sg:classifiers": [
      {
        "category": "Food \u0026 Beverages",
        "subcategory": "Specialty",
        "type": "Retail Goods"
      }
    ],
    "sg:phone": "+1 978 440 9752",
    "sg:postcode": "01776",
    "sg:province": "MA",
    "sg:tags": [
      "tea",
      "coffee"
    ],
    "wof:name": "Sudbury Coffee Works",
    "wof:placetype": "venue"
  },
  "geometry": {"coordinates":[-71.422291,42.361674],"type":"Point"}
}
