{
  "type": "Feature",
  "properties": {
    "iso:country":"US",
    "sg:address":"15 Union Ave",
    "sg:city":"Sudbury",
    "sg:classifiers":[
        {
            "category":"Food & Beverages",
            "subcategory":"Specialty",
            "type":"Retail Goods"
        }
    ],
    "sg:phone":"+1 978 440 9752",
    "sg:postcode":"01776",
    "sg:province":"MA",
    "sg:tags":[
        "tea",
        "coffee"
    ],
    "wof:name":"Sudbury Coffee Works",
    "wof:placetype":"venue"
},
  "geometry": {"coordinates":[-71.422291,42.361674],"type":"Point"}
}