{
  "type": "Feature",
  "properties": {
    "iso:country":"US",
    "sg:address":"453 Main St",
    "sg:city":"Winthrop",
    "sg:classifiers":[
        {
            "category":"Organizations",
            "subcategory":"Community Association",
            "type":"Services"
        }
    ],
    "sg:phone":"+1 617 846 9775",
    "sg:postcode":"02152",
    "sg:province":"MA",
    "sg:tags":[
        "club",
        "course",
        "golf"
    ],
    "sg:website":"http://www.winthropgolf.com",
    "wof:name":"Winthrop Golf Club",
    "wof:placetype":"venue"
},
  "geometry": {"coordinates":[-70.97958199999999,42.379801],"type":"Point"}
}