{
  "type": "Feature",
  "properties": {
    "addr:full":"210 Whalon St Fitchburg MA 01420",
    "addr:housenumber":"210",
    "addr:postcode":"01420",
    "addr:street":"Whalon St",
    "iso:country":"US",
    "sg:address":"210 Whalon St",
    "sg:city":"Fitchburg",
    "sg:classifiers":[
        {
            "category":"Personal",
            "subcategory":"Beauty Salon",
            "type":"Services"
        },
        {
            "category":"Personal",
            "subcategory":"Barber",
            "type":"Services"
        },
        {
            "category":"Shopping",
            "subcategory":"Beauty & Cosmetics",
            "type":"Retail Goods"
        }
    ],
    "sg:phone":"+1 978 343 9223",
    "sg:postcode":"01420",
    "sg:province":"MA",
    "sg:tags":[
        "equipment",
        "salons-equipment",
        "supply"
    ],
    "sg:website":"http://www.acebeautysupply.com",
    "wof:name":"Ace Beauty Supply Inc",
    "wof:placetype":"venue"
},
  "geometry": {"coordinates":[-71.783827,42.553079],"type":"Point"}
}