{
  "type": "Feature",
  "properties": {
    "iso:country":"US",
    "sg:address":"62 Elmwood St",
    "sg:city":"Auburn",
    "sg:classifiers":[
        {
            "category":"Professional",
            "subcategory":"Computer Services",
            "type":"Services"
        }
    ],
    "sg:phone":"+1 508 757 3365",
    "sg:postcode":"01501",
    "sg:province":"MA",
    "sg:tags":[
        "repair"
    ],
    "wof:name":"P C Solutions",
    "wof:placetype":"venue"
},
  "geometry": {"coordinates":[-71.821276,42.225403],"type":"Point"}
}