{
  "type": "Feature",
  "properties": {
    "iso:country":"US",
    "sg:address":"14 Mill St",
    "sg:city":"Natick",
    "sg:classifiers":[
        {
            "category":"Retail",
            "subcategory":"Storage",
            "type":"Services"
        }
    ],
    "sg:phone":"+1 508 921 0943",
    "sg:postcode":"01760",
    "sg:province":"MA",
    "sg:tags":[
        "automobile",
        "self",
        "commercial",
        "household"
    ],
    "sg:website":"http://boston.citysearch.com/profile/external/604187922/natick_ma/all_american_natick.html?publisher=yellowpages&reference_id=1&placement=ypwebsitemip",
    "wof:name":"All American - Natick",
    "wof:placetype":"venue"
},
  "geometry": {"coordinates":[-71.377379,42.278706],"type":"Point"}
}