{
  "type": "Feature",
  "properties": {
    "addr:full": "70 Howard St Reading MA 01867",
    "addr:housenumber": "70",
    "addr:postcode": "01867",
    "addr:street": "Howard St",
    "iso:country": "US",
    "sg:address": "70 Howard St",
    "sg:city": "Reading",
    "sg:classifiers": [
      {
        "category": "Professional",
        "subcategory": "Management \u0026 Consulting",
        "type": "Services"
      },
      {
        "category": "Professional",
        "subcategory": "Engineering",
        "type": "Services"
      }
    ],
    "sg:phone": "+1 781 942 2879",
    "sg:postcode": "01867",
    "sg:province": "MA",
    "sg:tags": [
      "environmental",
      "ecological",
      "engineer",
      "consultant"
    ],
    "wof:name": "Accurate Enviromental Inspection Inc",
    "wof:placetype": "venue"
  },
  "geometry": {"coordinates":[-71.118145,42.51593],"type":"Point"}
}
