{
  "type": "Feature",
  "properties": {
    "addr:full":"15 Court Sq Boston MA 02108",
    "addr:housenumber":"15",
    "addr:postcode":"02108",
    "addr:street":"Court Sq",
    "iso:country":"US",
    "sg:address":"15 Court Sq",
    "sg:city":"Boston",
    "sg:classifiers":[
        {
            "category":"Health Services",
            "subcategory":"Health Practitioner",
            "type":"Services"
        }
    ],
    "sg:phone":"+1 617 723 7651",
    "sg:postcode":"02108",
    "sg:province":"MA",
    "sg:tags":[
        "consultant",
        "medical",
        "practice",
        "psychotherapist"
    ],
    "wof:name":"Michael S Parson Psychtherpst",
    "wof:placetype":"venue"
},
  "geometry": {"coordinates":[-71.058228,42.358817],"type":"Point"}
}