{
  "type": "Feature",
  "properties": {
    "iso:country":"US",
    "sg:address":"733 Turnpike Street # 297",
    "sg:city":"North Andover",
    "sg:classifiers":[
        {
            "category":"Professional",
            "subcategory":"Computer Services",
            "type":"Services"
        }
    ],
    "sg:postcode":"01845",
    "sg:province":"MA",
    "sg:tags":[
        "products-and-services",
        "advertisement",
        "brand-awareness",
        "demobeat",
        "demo-09"
    ],
    "sg:website":"http://www.ham-it.com",
    "wof:name":"HAM-IT",
    "wof:placetype":"venue"
},
  "geometry": {"coordinates":[-71.10659800000001,42.659105],"type":"Point"}
}