{
  "type": "Feature",
  "properties": {
    "addr:full": "22 Lowell St Pepperell MA 01463",
    "addr:housenumber": "22",
    "addr:postcode": "01463",
    "addr:street": "Lowell St",
    "iso:country": "US",
    "sg:address": "22 Lowell St",
    "sg:city": "Pepperell",
    "sg:classifiers": [
      {
        "category": "Personal",
        "subcategory": "Beauty Salon",
        "type": "Services"
      }
    ],
    "sg:phone": "+1 978 433 2133",
    "sg:postcode": "01463",
    "sg:province": "MA",
    "sg:website": "www.pepperell.com",
    "wof:name": "Pepperell Braiding Co",
    "wof:placetype": "venue"
  },
  "geometry": {"coordinates":[-71.569201,42.668334],"type":"Point"}
}
