{
  "type": "Feature",
  "properties": {
    "addr:full":"377 Nantasket Ave Hull MA 02045",
    "addr:housenumber":"377",
    "addr:postcode":"02045",
    "addr:street":"Nantasket Ave",
    "iso:country":"US",
    "sg:address":"377 Nantasket Ave",
    "sg:city":"Hull",
    "sg:classifiers":[
        {
            "category":"Building & Trades",
            "subcategory":"Construction",
            "type":"Services"
        }
    ],
    "sg:phone":"+1 781 925 9052",
    "sg:postcode":"02045",
    "sg:province":"MA",
    "sg:tags":[
        "asbestos",
        "detection",
        "removal"
    ],
    "wof:name":"Abc",
    "wof:placetype":"venue"
},
  "geometry": {"coordinates":[-70.86703900000001,42.27863],"type":"Point"}
}