{
  "type": "Feature",
  "properties": {
    "addr:full": "2 Commerce Blvd Middleboro MA 02346",
    "addr:housenumber": "2",
    "addr:postcode": "02346",
    "addr:street": "Commerce Blvd",
    "iso:country": "US",
    "sg:address": "2 Commerce Blvd",
    "sg:city": "Middleboro",
    "sg:classifiers": [
      {
        "category": "Shopping",
        "subcategory": "Computers \u0026 Home Electronics",
        "type": "Retail Goods"
      }
    ],
    "sg:phone": "+1 508 946 5100",
    "sg:postcode": "02346",
    "sg:province": "MA",
    "sg:tags": [
      "parts",
      "supply"
    ],
    "sg:website": "www.computerboards.com",
    "wof:name": "Computer Boards Inc",
    "wof:placetype": "venue"
  },
  "geometry": {"coordinates":[-70.955929,41.905918],"type":"Point"}
}
