{
  "type": "Feature",
  "properties": {
    "iso:country":"US",
    "sg:address":"120 Washington St Ste 202",
    "sg:city":"Salem",
    "sg:classifiers":[
        {
            "category":"Professional",
            "subcategory":"Engineering",
            "type":"Services"
        }
    ],
    "sg:phone":"+1 978 741 7401",
    "sg:postcode":"01970",
    "sg:province":"MA",
    "sg:tags":[
        "civil",
        "consulting",
        "engineer"
    ],
    "wof:name":"New England Civil Engineering",
    "wof:placetype":"venue"
},
  "geometry": {"coordinates":[-70.895574,42.521025],"type":"Point"}
}