{
  "type": "Feature",
  "properties": {
    "iso:country":"US",
    "sg:address":"62 Brown St Ste 202",
    "sg:city":"Haverhill",
    "sg:classifiers":[
        {
            "category":"Health Services",
            "subcategory":"Doctor",
            "type":"Services"
        }
    ],
    "sg:phone":"+1 978 556 0555",
    "sg:postcode":"01830",
    "sg:province":"MA",
    "sg:tags":[
        "dermatologist"
    ],
    "wof:name":"Dr. Yuliya Mandel, MD PC",
    "wof:placetype":"venue"
},
  "geometry": {"coordinates":[-71.04750900000001,42.764948],"type":"Point"}
}