{
  "type": "Feature",
  "properties": {
    "iso:country":"US",
    "sg:address":"495 Springfield St",
    "sg:city":"Wilbraham",
    "sg:classifiers":[
        {
            "category":"Building & Trades",
            "subcategory":"Construction",
            "type":"Services"
        }
    ],
    "sg:phone":"+1   ",
    "sg:postcode":"01095",
    "sg:province":"MA",
    "sg:tags":[
        "home",
        "family",
        "contractor"
    ],
    "wof:name":"Brain Bagnall Construction Co",
    "wof:placetype":"venue"
},
  "geometry": {"coordinates":[-72.46566199999999,42.118783],"type":"Point"}
}