{
  "type": "Feature",
  "properties": {
    "addr:full": "447 Massasoit Rd Worcester MA 01604",
    "addr:housenumber": "447",
    "addr:postcode": "01604",
    "addr:street": "Massasoit Rd",
    "iso:country": "US",
    "sg:address": "447 Massasoit Rd",
    "sg:city": "Worcester",
    "sg:classifiers": [
      {
        "category": "Building \u0026 Trades",
        "subcategory": "Construction",
        "type": "Services"
      }
    ],
    "sg:phone": "+1 508 753 9039",
    "sg:postcode": "01604",
    "sg:province": "MA",
    "sg:tags": [
      "concrete",
      "contractor"
    ],
    "wof:name": "L J Morello Concrete Contr Inc",
    "wof:placetype": "venue"
  },
  "geometry": {"coordinates":[-71.763254,42.232262],"type":"Point"}
}
