{
  "type": "Feature",
  "properties": {
    "iso:country":"US",
    "sg:address":"2378 Boston Rd",
    "sg:city":"Wilbraham",
    "sg:classifiers":[
        {
            "category":"Autos & Motor Vehicles",
            "subcategory":"Motorcycle Sales",
            "type":"Retail Goods"
        }
    ],
    "sg:phone":"+1 413 596 9978",
    "sg:postcode":"01095",
    "sg:province":"MA",
    "sg:tags":[
        "scooter"
    ],
    "sg:website":"www.cycleaccessories.com",
    "wof:name":"Cycle Accessories & More",
    "wof:placetype":"venue"
},
  "geometry": {"coordinates":[-72.446282,42.149055],"type":"Point"}
}