{
  "type": "Feature",
  "properties": {
    "addr:full": "67 S Bedford St Burlington MA 01803",
    "addr:housenumber": "67",
    "addr:postcode": "01803",
    "addr:street": "S Bedford St",
    "iso:country": "US",
    "sg:address": "67 S Bedford St",
    "sg:city": "Burlington",
    "sg:classifiers": [
      {
        "category": "Food \u0026 Beverages",
        "subcategory": "Groceries \u0026 Convenience Stores",
        "type": "Retail Goods"
      }
    ],
    "sg:phone": "+1 781 229 5862",
    "sg:postcode": "01803",
    "sg:province": "MA",
    "sg:tags": [
      "product"
    ],
    "wof:name": "Food Analysis \u0026 Distribution",
    "wof:placetype": "venue"
  },
  "geometry": {"coordinates":[-71.19742,42.486022],"type":"Point"}
}
