{
  "type": "Feature",
  "properties": {
    "iso:country":"US",
    "sg:address":"41 Beaver Dam Rd",
    "sg:city":"Scituate",
    "sg:classifiers":[
        {
            "category":"Retail",
            "subcategory":"Repair Shop",
            "type":"Services"
        }
    ],
    "sg:phone":"+1 781 545 5451",
    "sg:postcode":"02066",
    "sg:province":"MA",
    "sg:tags":[
        "plumbing",
        "drain",
        "cleaning",
        "sewer"
    ],
    "wof:name":"Accu Drain",
    "wof:placetype":"venue"
},
  "geometry": {"coordinates":[-70.72882799999999,42.197873],"type":"Point"}
}