{
  "type": "Feature",
  "properties": {
    "addr:full": "PO Box 367 Bedford MA 01730",
    "addr:housenumber": "po",
    "addr:postcode": "01730",
    "addr:street": "Box 367",
    "iso:country": "US",
    "sg:address": "PO Box 367",
    "sg:city": "Bedford",
    "sg:classifiers": [
      {
        "category": "Building \u0026 Trades",
        "subcategory": "Construction",
        "type": "Services"
      }
    ],
    "sg:phone": "+1 781 275 6691",
    "sg:postcode": "01730",
    "sg:province": "MA",
    "sg:tags": [
      "contractor"
    ],
    "wof:name": "Scotsman Contracting Inc - CLOSED",
    "wof:placetype": "venue"
  },
  "geometry": {"coordinates":[-71.278999,42.4949],"type":"Point"}
}
