{
  "type": "Feature",
  "properties": {
    "iso:country":"US",
    "sg:address":"1070 Iyannough Rd",
    "sg:city":"Hyannis",
    "sg:classifiers":[
        {
            "category":"Food & Beverages",
            "subcategory":"Supermarket",
            "type":"Retail Goods"
        },
        {
            "category":"Shopping",
            "subcategory":"Pharmacy",
            "type":"Retail Goods"
        },
        {
            "category":"Food & Beverages",
            "subcategory":"Groceries & Convenience Stores",
            "type":"Retail Goods"
        }
    ],
    "sg:phone":"+1 508 775 7611",
    "sg:postcode":"02601",
    "sg:province":"MA",
    "sg:tags":[
        "super"
    ],
    "sg:website":"http://www.shaws.com/",
    "wof:name":"Shaw's Supermarkets",
    "wof:placetype":"venue"
},
  "geometry": {"coordinates":[-70.304187,41.672665],"type":"Point"}
}