{
  "type": "Feature",
  "properties": {
    "addr:full": "1070 Iyannough Rd Hyannis MA 02601",
    "addr:housenumber": "1070",
    "addr:postcode": "02601",
    "addr:street": "Iyannough Rd",
    "iso:country": "US",
    "ovtr:label": "Shaw's Supermarket, 1070 Iyannough Rd Hyannis MA US",
    "ovtr:similarity": 2.8438029289245605,
    "sg:address": "1070 Iyannough Rd",
    "sg:city": "Hyannis",
    "sg:classifiers": [
      {
        "category": "Food \u0026 Beverages",
        "subcategory": "Supermarket",
        "type": "Retail Goods"
      },
      {
        "category": "Shopping",
        "subcategory": "Pharmacy",
        "type": "Retail Goods"
      },
      {
        "category": "Food \u0026 Beverages",
        "subcategory": "Groceries \u0026 Convenience Stores",
        "type": "Retail Goods"
      }
    ],
    "sg:phone": "+1 508 775 7611",
    "sg:postcode": "02601",
    "sg:province": "MA",
    "sg:tags": [
      "super"
    ],
    "sg:website": "http://www.shaws.com/",
    "wof:name": "Shaw's Supermarkets",
    "wof:placetype": "venue"
  },
  "geometry": {"coordinates":[-70.304187,41.672665],"type":"Point"}
}
