{
  "type": "Feature",
  "properties": {
    "iso:country":"US",
    "sg:address":"870 N Main St",
    "sg:city":"Fall River",
    "sg:classifiers":[
        {
            "category":"Retail",
            "subcategory":"Photofinishing",
            "type":"Services"
        }
    ],
    "sg:phone":"+1 508 672 9257",
    "sg:postcode":"02720",
    "sg:province":"MA",
    "sg:tags":[
        "laboratory"
    ],
    "wof:name":"Brooks Pharmacy",
    "wof:placetype":"venue"
},
  "geometry": {"coordinates":[-71.15297099999999,41.713688],"type":"Point"}
}