{
  "type": "Feature",
  "properties": {
    "iso:country":"US",
    "sg:address":"27 Holyoke St",
    "sg:city":"Holyoke",
    "sg:classifiers":[
        {
            "category":"Shopping",
            "subcategory":"Computers & Home Electronics",
            "type":"Retail Goods"
        }
    ],
    "sg:phone":"+1 413 532 0400",
    "sg:postcode":"01040",
    "sg:province":"MA",
    "sg:website":"www.tweeter.com",
    "wof:name":"Tweeter",
    "wof:placetype":"venue"
},
  "geometry": {"coordinates":[-72.640508,42.173322],"type":"Point"}
}