{
  "type": "Feature",
  "properties": {
    "addr:full": "27 Holyoke St Holyoke MA 01040",
    "addr:housenumber": "27",
    "addr:postcode": "01040",
    "addr:street": "Holyoke St",
    "iso:country": "US",
    "sg:address": "27 Holyoke St",
    "sg:city": "Holyoke",
    "sg:classifiers": [
      {
        "category": "Shopping",
        "subcategory": "Computers \u0026 Home Electronics",
        "type": "Retail Goods"
      }
    ],
    "sg:phone": "+1 413 532 0400",
    "sg:postcode": "01040",
    "sg:province": "MA",
    "sg:website": "www.tweeter.com",
    "wof:name": "Tweeter",
    "wof:placetype": "venue"
  },
  "geometry": {"coordinates":[-72.640508,42.173322],"type":"Point"}
}
