{
  "type": "Feature",
  "properties": {
    "addr:full": "66 Beacon Street Boston MA 02108",
    "addr:housenumber": "66",
    "addr:postcode": "02108",
    "addr:street": "Beacon Street",
    "iso:country": "US",
    "sg:address": "66 Beacon Street",
    "sg:city": "Boston",
    "sg:classifiers": [
      {
        "category": "Real Estate",
        "subcategory": "Architect",
        "type": "Services"
      }
    ],
    "sg:phone": "+1 617 367 3655",
    "sg:postcode": "02108",
    "sg:province": "MA",
    "wof:name": "McNeely \u0026 Pauli Architects",
    "wof:placetype": "venue"
  },
  "geometry": {"coordinates":[-71.069439,42.356326],"type":"Point"}
}
