{
  "type": "Feature",
  "properties": {
    "addr:full":"826 Boylston St Brookline MA 02445",
    "addr:housenumber":"826",
    "addr:postcode":"02445",
    "addr:street":"Boylston St",
    "iso:country":"US",
    "sg:address":"826 Boylston St",
    "sg:city":"Brookline",
    "sg:classifiers":[
        {
            "category":"Real Estate",
            "subcategory":"Real Estate Services",
            "type":"Services"
        },
        {
            "category":"Real Estate",
            "subcategory":"Real Estate Agent",
            "type":"Services"
        }
    ],
    "sg:phone":"+1 617 782 8333",
    "sg:postcode":"02445",
    "sg:province":"MA",
    "sg:website":"www.tedduncan.com",
    "wof:name":"Ted Duncan - Hammond Residential Real Estate",
    "wof:placetype":"venue"
},
  "geometry": {"coordinates":[-71.1442,42.326326],"type":"Point"}
}