{
  "type": "Feature",
  "properties": {
    "addr:full": "181 Cambridge Street Boston MA 02134",
    "addr:housenumber": "181",
    "addr:postcode": "02134",
    "addr:street": "Cambridge Street",
    "iso:country": "US",
    "sg:address": "181 Cambridge Street",
    "sg:city": "Boston",
    "sg:classifiers": [
      {
        "category": "Shopping",
        "subcategory": "Florist",
        "type": "Retail Goods"
      }
    ],
    "sg:phone": "+1 617 723 0004",
    "sg:postcode": "02134",
    "sg:province": "MA",
    "wof:name": "Wholefoods Market - Flower Shop",
    "wof:placetype": "venue"
  },
  "geometry": {"coordinates":[-71.124877,42.358498],"type":"Point"}
}
