{
  "type": "Feature",
  "properties": {
    "iso:country":"US",
    "sg:address":"181 Cambridge Street",
    "sg:city":"Boston",
    "sg:classifiers":[
        {
            "category":"Shopping",
            "subcategory":"Florist",
            "type":"Retail Goods"
        }
    ],
    "sg:phone":"+1 617 723 0004",
    "sg:postcode":"02134",
    "sg:province":"MA",
    "wof:name":"Wholefoods Market - Flower Shop",
    "wof:placetype":"venue"
},
  "geometry": {"coordinates":[-71.124877,42.358498],"type":"Point"}
}