{
  "type": "Feature",
  "properties": {
    "addr:full":"597 Main St Holden MA 01520",
    "addr:housenumber":"597",
    "addr:postcode":"01520",
    "addr:street":"Main St",
    "iso:country":"US",
    "sg:address":"597 Main St",
    "sg:city":"Holden",
    "sg:classifiers":[
        {
            "category":"Restaurant",
            "type":"Food & Drink"
        }
    ],
    "sg:phone":"+1 508 829 5406",
    "sg:postcode":"01520",
    "sg:province":"MA",
    "sg:tags":[
        "pizza"
    ],
    "wof:name":"Holden Pizza",
    "wof:placetype":"venue"
},
  "geometry": {"coordinates":[-71.84003300000001,42.340867],"type":"Point"}
}