{
  "type": "Feature",
  "properties": {
    "addr:full": "597 Main St Holden MA 01520",
    "addr:housenumber": "597",
    "addr:postcode": "01520",
    "addr:street": "Main St",
    "iso:country": "US",
    "ovtr:label": "Holden Pizza, 597 Main St Holden MA US",
    "ovtr:similarity": 3.4074649810791016,
    "sg:address": "597 Main St",
    "sg:city": "Holden",
    "sg:classifiers": [
      {
        "category": "Restaurant",
        "type": "Food \u0026 Drink"
      }
    ],
    "sg:phone": "+1 508 829 5406",
    "sg:postcode": "01520",
    "sg:province": "MA",
    "sg:tags": [
      "pizza"
    ],
    "wof:name": "Holden Pizza",
    "wof:placetype": "venue"
  },
  "geometry": {"coordinates":[-71.840033,42.340867],"type":"Point"}
}
