{
  "type": "Feature",
  "properties": {
    "addr:full": "4 Davidson Ave Dorchester MA 02125",
    "addr:housenumber": "4",
    "addr:postcode": "02125",
    "addr:street": "Davidson Ave",
    "iso:country": "US",
    "sg:address": "4 Davidson Ave",
    "sg:city": "Dorchester",
    "sg:classifiers": [
      {
        "category": "Arts \u0026 Performance",
        "subcategory": "Theater",
        "type": "Entertainment"
      }
    ],
    "sg:phone": "+1 617 265 4166",
    "sg:postcode": "02125",
    "sg:province": "MA",
    "sg:tags": [
      "bureau"
    ],
    "wof:name": "Triiiple Threat Entertainment",
    "wof:placetype": "venue"
  },
  "geometry": {"coordinates":[-71.070865,42.30617],"type":"Point"}
}
