{
  "type": "Feature",
  "properties": {
    "addr:full":"71 Francis St Waltham MA 02451",
    "addr:housenumber":"71",
    "addr:postcode":"02451",
    "addr:street":"Francis St",
    "iso:country":"US",
    "sg:address":"71 Francis St",
    "sg:city":"Waltham",
    "sg:classifiers":[
        {
            "category":"Building & Trades",
            "subcategory":"Construction",
            "type":"Services"
        }
    ],
    "sg:phone":"+1 781 647 0061",
    "sg:postcode":"02451",
    "sg:province":"MA",
    "sg:tags":[
        "coping",
        "plastering",
        "tiling",
        "pool",
        "swimming"
    ],
    "wof:name":"Fap Swimming Pool Repair",
    "wof:placetype":"venue"
},
  "geometry": {"coordinates":[-71.245606,42.379739],"type":"Point"}
}