{
  "type": "Feature",
  "properties": {
    "iso:country":"US",
    "sg:address":"104 Conz St",
    "sg:city":"Northampton",
    "sg:classifiers":[
        {
            "category":"Food & Beverages",
            "subcategory":"Liquor & Beverages",
            "type":"Retail Goods"
        }
    ],
    "sg:phone":"+1 413 586 7050",
    "sg:postcode":"01060",
    "sg:province":"MA",
    "sg:tags":[
        "alcoholic"
    ],
    "wof:name":"Northampton Liquors & Wine",
    "wof:placetype":"venue"
},
  "geometry": {"coordinates":[-72.62612300000001,42.312941],"type":"Point"}
}