{
  "type": "Feature",
  "properties": {
    "addr:full": "104 Conz St Northampton MA 01060",
    "addr:housenumber": "104",
    "addr:postcode": "01060",
    "addr:street": "Conz St",
    "iso:country": "US",
    "ovtr:label": "Northampton Liquors \u0026 Wine, 104 Conz St Northampton MA US",
    "ovtr:similarity": 2.487617015838623,
    "sg:address": "104 Conz St",
    "sg:city": "Northampton",
    "sg:classifiers": [
      {
        "category": "Food \u0026 Beverages",
        "subcategory": "Liquor \u0026 Beverages",
        "type": "Retail Goods"
      }
    ],
    "sg:phone": "+1 413 586 7050",
    "sg:postcode": "01060",
    "sg:province": "MA",
    "sg:tags": [
      "alcoholic"
    ],
    "wof:name": "Northampton Liquors \u0026 Wine",
    "wof:placetype": "venue"
  },
  "geometry": {"coordinates":[-72.626123,42.312941],"type":"Point"}
}
