{
  "type": "Feature",
  "properties": {
    "addr:full": "56 Foster St Peabody MA 01960",
    "addr:housenumber": "56",
    "addr:postcode": "01960",
    "addr:street": "Foster St",
    "iso:country": "US",
    "ovtr:label": "A \u0026 L Liquors, 56 Foster St Peabody MA US",
    "ovtr:similarity": 2.2686638832092285,
    "sg:address": "56 Foster St",
    "sg:city": "Peabody",
    "sg:classifiers": [
      {
        "category": "Food \u0026 Beverages",
        "subcategory": "Liquor \u0026 Beverages",
        "type": "Retail Goods"
      }
    ],
    "sg:phone": "+1 978 532 3460",
    "sg:postcode": "01960",
    "sg:province": "MA",
    "wof:name": "A \u0026 L Liquors",
    "wof:placetype": "venue"
  },
  "geometry": {"coordinates":[-70.929209,42.523696],"type":"Point"}
}
