{
  "type": "Feature",
  "properties": {
    "addr:full":"2 Circle Ave Lynn MA 01905",
    "addr:housenumber":"2",
    "addr:postcode":"01905",
    "addr:street":"Circle Ave",
    "iso:country":"US",
    "sg:address":"2 Circle Ave",
    "sg:city":"Lynn",
    "sg:classifiers":[
        {
            "category":"Professional",
            "subcategory":"Business Services",
            "type":"Services"
        }
    ],
    "sg:phone":"+1 781 592 7048",
    "sg:postcode":"01905",
    "sg:province":"MA",
    "sg:tags":[
        "water",
        "treatment"
    ],
    "sg:website":"www.usfilter.com",
    "wof:name":"US Filter",
    "wof:placetype":"venue"
},
  "geometry": {"coordinates":[-70.95671299999999,42.453678],"type":"Point"}
}