{
  "type": "Feature",
  "properties": {
    "iso:country":"US",
    "sg:address":"651 Vfw Parkway",
    "sg:city":"Chestnut Hill",
    "sg:classifiers":[
        {
            "category":"Retail",
            "subcategory":"Laundry & Dry Cleaning",
            "type":"Services"
        }
    ],
    "sg:phone":"+1 617 327 3024",
    "sg:postcode":"02467",
    "sg:province":"MA",
    "wof:name":"Prime Clnrs",
    "wof:placetype":"venue"
},
  "geometry": {"coordinates":[-71.15989999999999,42.294678],"type":"Point"}
}