{
  "type": "Feature",
  "properties": {
    "addr:full": "216 Main St Harwich MA 02645",
    "addr:housenumber": "216",
    "addr:postcode": "02645",
    "addr:street": "Main St",
    "iso:country": "US",
    "sg:address": "216 Main St",
    "sg:city": "Harwich",
    "sg:classifiers": [
      {
        "category": "Real Estate",
        "subcategory": "Real Estate Agent",
        "type": "Services"
      }
    ],
    "sg:phone": "+1 508 432 0033",
    "sg:postcode": "02645",
    "sg:province": "MA",
    "wof:name": "Real Estate-Unlimited",
    "wof:placetype": "venue"
  },
  "geometry": {"coordinates":[-70.114991,41.695215],"type":"Point"}
}
