{
  "type": "Feature",
  "properties": {
    "iso:country":"US",
    "sg:address":"155 Webster St Ste F",
    "sg:city":"Hanover",
    "sg:classifiers":[
        {
            "category":"Autos & Motor Vehicles",
            "subcategory":"Auto Supplies",
            "type":"Retail Goods"
        }
    ],
    "sg:phone":"+1 781 982 1433",
    "sg:postcode":"02339",
    "sg:province":"MA",
    "sg:tags":[
        "automobile",
        "parts",
        "accessory",
        "part",
        "accessories-wholesale",
        "manufacturer"
    ],
    "wof:name":"International Car Parts Imports, Ltd.",
    "wof:placetype":"venue"
},
  "geometry": {"coordinates":[-70.85365299999999,42.155418],"type":"Point"}
}