{
  "type": "Feature",
  "properties": {
    "addr:full": "29 Glennie St Worcester MA 01605",
    "addr:housenumber": "29",
    "addr:postcode": "01605",
    "addr:street": "Glennie St",
    "iso:country": "US",
    "sg:address": "29 Glennie St",
    "sg:city": "Worcester",
    "sg:classifiers": [
      {
        "category": "Retail",
        "subcategory": "Auto Repair",
        "type": "Services"
      }
    ],
    "sg:phone": "+1 508 595 3291",
    "sg:postcode": "01605",
    "sg:province": "MA",
    "sg:tags": [
      "body",
      "repairing",
      "painting",
      "automobile"
    ],
    "sg:website": "http://www.harrautobody.com",
    "wof:name": "Harr Auto Body",
    "wof:placetype": "venue"
  },
  "geometry": {"coordinates":[-71.804787,42.2869],"type":"Point"}
}
