{
  "type": "Feature",
  "properties": {
    "addr:full":"137 Pond St Osterville MA 02655",
    "addr:housenumber":"137",
    "addr:postcode":"02655",
    "addr:street":"Pond St",
    "iso:country":"US",
    "sg:address":"137 Pond St",
    "sg:city":"Osterville",
    "sg:classifiers":[
        {
            "category":"Building & Trades",
            "subcategory":"Construction",
            "type":"Services"
        }
    ],
    "sg:phone":"+1 508 420 0900",
    "sg:postcode":"02655",
    "sg:province":"MA",
    "sg:tags":[
        "designer",
        "marine",
        "contractor"
    ],
    "wof:name":"Island Barge Inc",
    "wof:placetype":"venue"
},
  "geometry": {"coordinates":[-70.38757699999999,41.63481],"type":"Point"}
}