{
  "type": "Feature",
  "properties": {
    "addr:full": "15 Olympia Ave Woburn MA 01801",
    "addr:housenumber": "15",
    "addr:postcode": "01801",
    "addr:street": "Olympia Ave",
    "iso:country": "US",
    "ovtr:label": "Extra Space Storage, 15 Olympia Ave Woburn MA US",
    "ovtr:similarity": 1.974537968635559,
    "sg:address": "15 Olympia Ave",
    "sg:city": "Woburn",
    "sg:classifiers": [
      {
        "category": "Freight",
        "type": "Transportation"
      }
    ],
    "sg:phone": "+1 781 938 1093",
    "sg:postcode": "01801",
    "sg:province": "MA",
    "sg:tags": [
      "storage",
      "self",
      "commercial"
    ],
    "sg:website": "www.extraspace.com",
    "wof:name": "Extra Space Storage",
    "wof:placetype": "venue"
  },
  "geometry": {"coordinates":[-71.127799,42.500077],"type":"Point"}
}
