{
  "type": "Feature",
  "properties": {
    "addr:full": "162 Commercial St Provincetown MA 02657",
    "addr:housenumber": "162",
    "addr:postcode": "02657",
    "addr:street": "Commercial St",
    "iso:country": "US",
    "sg:address": "162 Commercial St",
    "sg:city": "Provincetown",
    "sg:classifiers": [
      {
        "category": "Real Estate",
        "subcategory": "Real Estate Agent",
        "type": "Services"
      }
    ],
    "sg:phone": "+1 508 487 4005",
    "sg:postcode": "02657",
    "sg:province": "MA",
    "sg:website": "www.harborside-realty.com",
    "wof:name": "Harborside Realty",
    "wof:placetype": "venue"
  },
  "geometry": {"coordinates":[-70.190673,42.046886],"type":"Point"}
}
