{
  "type": "Feature",
  "properties": {
    "iso:country":"US",
    "sg:address":"304 Brooksby Village Dr U",
    "sg:city":"Peabody",
    "sg:classifiers":[
        {
            "category":"Professional",
            "subcategory":"Detective & Security Services",
            "type":"Services"
        }
    ],
    "sg:phone":"+1 978 535 0063",
    "sg:postcode":"01960",
    "sg:province":"MA",
    "sg:tags":[
        "private",
        "investigator"
    ],
    "wof:name":"John S Donohoe",
    "wof:placetype":"venue"
},
  "geometry": {"coordinates":[-70.967629,42.552109],"type":"Point"}
}