{
  "type": "Feature",
  "properties": {
    "addr:full":"194 Gorham St Lowell MA 01852",
    "addr:housenumber":"194",
    "addr:postcode":"01852",
    "addr:street":"Gorham St",
    "iso:country":"US",
    "sg:address":"194 Gorham St",
    "sg:city":"Lowell",
    "sg:classifiers":[
        {
            "category":"Restaurant",
            "type":"Food & Drink"
        }
    ],
    "sg:phone":"+1 978 452 8186",
    "sg:postcode":"01852",
    "sg:province":"MA",
    "sg:tags":[
        "sandwich"
    ],
    "wof:name":"Santoro's Sub Shop",
    "wof:placetype":"venue"
},
  "geometry": {"coordinates":[-71.308781,42.639153],"type":"Point"}
}