{
  "type": "Feature",
  "properties": {
    "addr:full": "44 Old Billerica Rd Bedford MA 01730",
    "addr:housenumber": "44",
    "addr:postcode": "01730",
    "addr:street": "Old Billerica Rd",
    "iso:country": "US",
    "sg:address": "44 Old Billerica Rd",
    "sg:city": "Bedford",
    "sg:classifiers": [
      {
        "category": "Retail",
        "subcategory": "Repair Shop",
        "type": "Services"
      },
      {
        "category": "Wholesale",
        "subcategory": "Machinery \u0026 Supplies",
        "type": "Manufacturing \u0026 Wholesale Goods"
      }
    ],
    "sg:phone": "+1 781 275 6232",
    "sg:postcode": "01730",
    "sg:province": "MA",
    "sg:tags": [
      "compressor",
      "compressors-repair"
    ],
    "wof:name": "Allen H Soper Co",
    "wof:placetype": "venue"
  },
  "geometry": {"coordinates":[-71.257895,42.495656],"type":"Point"}
}
