{
  "type": "Feature",
  "properties": {
    "addr:full": "1 Olde North Rd Chelmsford MA 01824",
    "addr:housenumber": "1",
    "addr:postcode": "01824",
    "addr:street": "Olde North Rd",
    "iso:country": "US",
    "sg:address": "1 Olde North Rd",
    "sg:city": "Chelmsford",
    "sg:classifiers": [
      {
        "category": "Professional",
        "subcategory": "Engineering",
        "type": "Services"
      }
    ],
    "sg:phone": "+1 978 250 8173",
    "sg:postcode": "01824",
    "sg:province": "MA",
    "sg:tags": [
      "engineer"
    ],
    "wof:name": "TAJ Engineering",
    "wof:placetype": "venue"
  },
  "geometry": {"coordinates":[-71.366491,42.620014],"type":"Point"}
}
