{
  "type": "Feature",
  "properties": {
    "iso:country":"US",
    "sg:address":"71 Pond St",
    "sg:city":"Leominster",
    "sg:classifiers":[
        {
            "category":"Real Estate",
            "subcategory":"Real Estate Operator",
            "type":"Services"
        }
    ],
    "sg:phone":"+1 978 534 6866",
    "sg:postcode":"01453",
    "sg:province":"MA",
    "sg:tags":[
        "building",
        "apartment"
    ],
    "wof:name":"R & M Realty",
    "wof:placetype":"venue"
},
  "geometry": {"coordinates":[-71.767213,42.526159],"type":"Point"}
}