{
  "type": "Feature",
  "properties": {
    "addr:full":"1 Williams St Williamsburg MA 01096",
    "addr:housenumber":"1",
    "addr:postcode":"01096",
    "addr:street":"Williams St",
    "iso:country":"US",
    "sg:address":"1 Williams St",
    "sg:city":"Williamsburg",
    "sg:classifiers":[
        {
            "category":"Government",
            "subcategory":"Post Office",
            "type":"Public Place"
        }
    ],
    "sg:phone":"+1 413 268 7274",
    "sg:postcode":"01096",
    "sg:province":"MA",
    "wof:name":"US Post Office",
    "wof:placetype":"venue"
},
  "geometry": {"coordinates":[-72.732884,42.393359],"type":"Point"}
}