{
  "type": "Feature",
  "properties": {
    "addr:full":"83 Cambridge St Burlington MA 01803",
    "addr:housenumber":"83",
    "addr:postcode":"01803",
    "addr:street":"Cambridge St",
    "iso:country":"US",
    "sg:address":"83 Cambridge St",
    "sg:city":"Burlington",
    "sg:classifiers":[
        {
            "category":"Professional",
            "type":"Services"
        }
    ],
    "sg:phone":"+1 781 272 7413",
    "sg:postcode":"01803",
    "sg:province":"MA",
    "sg:tags":[
        "establishment"
    ],
    "wof:name":"Centra Technology Inc",
    "wof:placetype":"venue"
},
  "geometry": {"coordinates":[-71.194283,42.493732],"type":"Point"}
}