{
  "type": "Feature",
  "properties": {
    "addr:full":"116 North St Salem MA 01970",
    "addr:housenumber":"116",
    "addr:postcode":"01970",
    "addr:street":"North St",
    "iso:country":"US",
    "sg:address":"116 North St",
    "sg:city":"Salem",
    "sg:classifiers":[
        {
            "category":"Personal",
            "subcategory":"Beauty Salon",
            "type":"Services"
        }
    ],
    "sg:phone":"+1 978 744 5132",
    "sg:postcode":"01970",
    "sg:province":"MA",
    "wof:name":"New Heads On The Block",
    "wof:placetype":"venue"
},
  "geometry": {"coordinates":[-70.901233,42.526821],"type":"Point"}
}