{
  "type": "Feature",
  "properties": {
    "addr:full":"39 Dodge St Beverly MA 01915",
    "addr:housenumber":"39",
    "addr:postcode":"01915",
    "addr:street":"Dodge St",
    "iso:country":"US",
    "sg:address":"39 Dodge St",
    "sg:city":"Beverly",
    "sg:classifiers":[
        {
            "category":"Professional",
            "subcategory":"Advertising",
            "type":"Services"
        }
    ],
    "sg:phone":"+1 978 468 4339",
    "sg:postcode":"01915",
    "sg:province":"MA",
    "sg:tags":[
        "counselor"
    ],
    "wof:name":"Direct Impact",
    "wof:placetype":"venue"
},
  "geometry": {"coordinates":[-70.89197,42.575036],"type":"Point"}
}