{
  "type": "Feature",
  "properties": {
    "iso:country":"US",
    "sg:address":"76 Weir St",
    "sg:city":"Taunton",
    "sg:classifiers":[
        {
            "category":"Restaurant",
            "type":"Food & Drink"
        }
    ],
    "sg:phone":"+1 508 822 0391",
    "sg:postcode":"02780",
    "sg:province":"MA",
    "sg:tags":[
        "lounge",
        "cocktail"
    ],
    "wof:name":"Pub 76",
    "wof:placetype":"venue"
},
  "geometry": {"coordinates":[-71.09226200000001,41.899921],"type":"Point"}
}