{
  "type": "Feature",
  "properties": {
    "iso:country":"US",
    "sg:address":"16 Garfield Ave",
    "sg:city":"Beverly",
    "sg:classifiers":[
        {
            "category":"Professional",
            "type":"Services"
        }
    ],
    "sg:phone":"+1 978 927 0882",
    "sg:postcode":"01915",
    "sg:province":"MA",
    "sg:tags":[
        "establishment"
    ],
    "wof:name":"Abate Fredk",
    "wof:placetype":"venue"
},
  "geometry": {"coordinates":[-70.908777,42.55054],"type":"Point"}
}