{
  "type": "Feature",
  "properties": {
    "iso:country":"US",
    "sg:address":"16 Marlene Ave",
    "sg:city":"Brockton",
    "sg:classifiers":[
        {
            "category":"Building & Trades",
            "subcategory":"Construction",
            "type":"Services"
        },
        {
            "category":"Real Estate",
            "subcategory":"Architect",
            "type":"Services"
        }
    ],
    "sg:phone":"+1 508 586 1155",
    "sg:postcode":"02301",
    "sg:province":"MA",
    "sg:tags":[
        "interior",
        "design"
    ],
    "wof:name":"Tsokanis Architects",
    "wof:placetype":"venue"
},
  "geometry": {"coordinates":[-71.043098,42.086102],"type":"Point"}
}