{
  "type": "Feature",
  "properties": {
    "addr:full": "90 7th St Turners Falls MA 01376",
    "addr:housenumber": "90",
    "addr:postcode": "01376",
    "addr:street": "7Th St",
    "iso:country": "US",
    "sg:address": "90 7th St",
    "sg:city": "Turners Falls",
    "sg:classifiers": [
      {
        "category": "Organizations",
        "subcategory": "Religious Organization",
        "type": "Services"
      }
    ],
    "sg:phone": "+1 413 772 6377",
    "sg:postcode": "01376",
    "sg:province": "MA",
    "sg:tags": [
      "church"
    ],
    "wof:name": "Sacred Heart Catholic Church",
    "wof:placetype": "venue"
  },
  "geometry": {"coordinates":[-72.557898,42.604526],"type":"Point"}
}
