{
  "type": "Feature",
  "properties": {
    "iso:country":"US",
    "sg:address":"45 newbury street #208",
    "sg:city":"Boston",
    "sg:classifiers":[
        {
            "category":"Real Estate",
            "subcategory":"Real Estate Agent",
            "type":"Services"
        }
    ],
    "sg:phone":"+1 617 450 9898",
    "sg:postcode":"02116",
    "sg:province":"MA",
    "wof:name":"Back Bay Residential Properties",
    "wof:placetype":"venue"
},
  "geometry": {"coordinates":[-71.073291,42.352102],"type":"Point"}
}