{
  "type": "Feature",
  "properties": {
    "addr:full": "448 Main St Hyannis MA 02601",
    "addr:housenumber": "448",
    "addr:postcode": "02601",
    "addr:street": "Main St",
    "iso:country": "US",
    "sg:address": "448 Main St",
    "sg:city": "Hyannis",
    "sg:classifiers": [
      {
        "category": "Restaurant",
        "type": "Food \u0026 Drink"
      }
    ],
    "sg:phone": "+1 508 775 7678",
    "sg:postcode": "02601",
    "sg:province": "MA",
    "wof:name": "Pizza Port",
    "wof:placetype": "venue"
  },
  "geometry": {"coordinates":[-70.286059,41.65179],"type":"Point"}
}
