{
  "type": "Feature",
  "properties": {
    "addr:full": "918 Belmont St Watertown MA 02472",
    "addr:housenumber": "918",
    "addr:postcode": "02472",
    "addr:street": "Belmont St",
    "iso:country": "US",
    "sg:address": "918 Belmont St",
    "sg:city": "Watertown",
    "sg:classifiers": [
      {
        "category": "Professional",
        "subcategory": "Advertising",
        "type": "Services"
      }
    ],
    "sg:phone": "+1 617 924 7675",
    "sg:postcode": "02472",
    "sg:province": "MA",
    "sg:tags": [
      "counselor"
    ],
    "wof:name": "KMP LTD",
    "wof:placetype": "venue"
  },
  "geometry": {"coordinates":[-71.19143,42.38069],"type":"Point"}
}
