{
  "type": "Feature",
  "properties": {
    "addr:full":"148 Fire Rd 15 Lunenburg MA 01462",
    "addr:housenumber":"148;15",
    "addr:postcode":"01462",
    "addr:street":"Fire Rd",
    "iso:country":"US",
    "sg:address":"148 Fire Rd 15",
    "sg:city":"Lunenburg",
    "sg:classifiers":[
        {
            "category":"Building & Trades",
            "subcategory":"Plumbing",
            "type":"Services"
        }
    ],
    "sg:phone":"+1 978 343 4342",
    "sg:postcode":"01462",
    "sg:province":"MA",
    "sg:tags":[
        "refrigeration",
        "contractor"
    ],
    "wof:name":"Fiandaca Refrigeration",
    "wof:placetype":"venue"
},
  "geometry": {"coordinates":[-71.67992599999999,42.548394],"type":"Point"}
}