{
  "type": "Feature",
  "properties": {
    "iso:country":"US",
    "sg:address":"6 Roxbury St",
    "sg:city":"Roxbury",
    "sg:classifiers":[
        {
            "category":"Personal",
            "subcategory":"Beauty Salon",
            "type":"Services"
        }
    ],
    "sg:phone":"+1 617 427 5055",
    "sg:postcode":"02119",
    "sg:province":"MA",
    "wof:name":"Tammy's Higher Level Hair Std",
    "wof:placetype":"venue"
},
  "geometry": {"coordinates":[-71.08591300000001,42.329278],"type":"Point"}
}