{
  "type": "Feature",
  "properties": {
    "addr:full": "290 Baker Ave Concord MA 01742",
    "addr:housenumber": "290",
    "addr:postcode": "01742",
    "addr:street": "Baker Ave",
    "iso:country": "US",
    "sg:address": "290 Baker Ave",
    "sg:city": "Concord",
    "sg:classifiers": [
      {
        "category": "Health Services",
        "subcategory": "Clinic",
        "type": "Services"
      }
    ],
    "sg:phone": "+1 978 369 0932",
    "sg:postcode": "01742",
    "sg:province": "MA",
    "wof:name": "Pediatric \u0026 Adolescent Health",
    "wof:placetype": "venue"
  },
  "geometry": {"coordinates":[-71.386906,42.458264],"type":"Point"}
}
