{
  "type": "Feature",
  "properties": {
    "iso:country":"US",
    "sg:address":"333 Washington Street",
    "sg:city":"Boston",
    "sg:classifiers":[
        {
            "category":"Sports & Exercise",
            "subcategory":"Gym",
            "type":"Entertainment"
        }
    ],
    "sg:phone":"+1 617 557 4534",
    "sg:postcode":"02108",
    "sg:province":"MA",
    "sg:tags":[
        "trainer"
    ],
    "wof:name":"Favorite Nurses",
    "wof:placetype":"venue"
},
  "geometry": {"coordinates":[-71.06511399999999,42.357724],"type":"Point"}
}