{
  "type": "Feature",
  "properties": {
    "addr:full":"45 Fairfield Street Boston MA 02116",
    "addr:housenumber":"45",
    "addr:postcode":"02116",
    "addr:street":"Fairfield Street",
    "iso:country":"US",
    "sg:address":"45 Fairfield Street",
    "sg:city":"Boston",
    "sg:classifiers":[
        {
            "category":"Banks & Credit Unions",
            "subcategory":"Investment Brokerage",
            "type":"Services"
        }
    ],
    "sg:phone":"+1 617 239 9000",
    "sg:postcode":"02116",
    "sg:province":"MA",
    "sg:tags":[
        "investing"
    ],
    "sg:website":"www.neocarta.com",
    "wof:name":"Neocarta Ventures",
    "wof:placetype":"venue"
},
  "geometry": {"coordinates":[-71.082032,42.349278],"type":"Point"}
}