{
  "type": "Feature",
  "properties": {
    "iso:country":"US",
    "sg:address":"116 Long Pond Rd",
    "sg:city":"Plymouth",
    "sg:classifiers":[
        {
            "category":"Professional",
            "subcategory":"Business Services",
            "type":"Services"
        }
    ],
    "sg:phone":"+1 508 747 5583",
    "sg:postcode":"02360",
    "sg:province":"MA",
    "sg:tags":[
        "interior",
        "consultant",
        "design",
        "decorator"
    ],
    "wof:name":"Designed Interiors",
    "wof:placetype":"venue"
},
  "geometry": {"coordinates":[-70.65655099999999,41.924971],"type":"Point"}
}