{
  "type": "Feature",
  "properties": {
    "iso:country":"US",
    "sg:address":"304 Main St",
    "sg:city":"North Reading",
    "sg:classifiers":[
        {
            "category":"Retail",
            "subcategory":"Animal Services",
            "type":"Services"
        }
    ],
    "sg:phone":"+1 978 664 9298",
    "sg:postcode":"01864",
    "sg:province":"MA",
    "sg:tags":[
        "pet",
        "training"
    ],
    "sg:website":"www.k-9performance.com",
    "wof:name":"K-9 Performance",
    "wof:placetype":"venue"
},
  "geometry": {"coordinates":[-71.119519,42.59505],"type":"Point"}
}