{
  "type": "Feature",
  "properties": {
    "addr:full": "11 Freedom Trl Norfolk MA 02056",
    "addr:housenumber": "11",
    "addr:postcode": "02056",
    "addr:street": "Freedom Trl",
    "iso:country": "US",
    "sg:address": "11 Freedom Trl",
    "sg:city": "Norfolk",
    "sg:classifiers": [
      {
        "category": "Building \u0026 Trades",
        "subcategory": "Cleaning \u0026 Sanitation",
        "type": "Services"
      }
    ],
    "sg:phone": "+1 508 384 6424",
    "sg:postcode": "02056",
    "sg:province": "MA",
    "sg:tags": [
      "janitor"
    ],
    "wof:name": "Sanitrol Building Maintenance",
    "wof:placetype": "venue"
  },
  "geometry": {"coordinates":[-71.282285,42.089991],"type":"Point"}
}
