{
  "type": "Feature",
  "properties": {
    "iso:country":"US",
    "sg:address":"5 Michael Way",
    "sg:city":"West Townsend",
    "sg:classifiers":[
        {
            "category":"Autos & Motor Vehicles",
            "subcategory":"Automobile Sales",
            "type":"Retail Goods"
        }
    ],
    "sg:phone":"+1   ",
    "sg:postcode":"01474",
    "sg:province":"MA",
    "sg:tags":[
        "used"
    ],
    "wof:name":"Automobilia",
    "wof:placetype":"venue"
},
  "geometry": {"coordinates":[-71.753066,42.704538],"type":"Point"}
}