{
  "type": "Feature",
  "properties": {
    "iso:country":"US",
    "sg:address":"800 W Main St",
    "sg:city":"Avon",
    "sg:classifiers":[
        {
            "category":"Insurance",
            "subcategory":"Insurance Agent",
            "type":"Services"
        }
    ],
    "sg:phone":"+1 508 586 2973",
    "sg:postcode":"02322",
    "sg:province":"MA",
    "sg:website":"www.mccormickinsurance.com",
    "wof:name":"Mc Cormick Insurance",
    "wof:placetype":"venue"
},
  "geometry": {"coordinates":[-71.03470900000001,42.114731],"type":"Point"}
}