{
  "type": "Feature",
  "properties": {
    "iso:country":"US",
    "sg:address":"59 Chester Ave",
    "sg:city":"Chelsea",
    "sg:classifiers":[
        {
            "category":"Building & Trades",
            "subcategory":"Locksmith",
            "type":"Services"
        }
    ],
    "sg:phone":"+1 617 409 8026",
    "sg:postcode":"02150",
    "sg:province":"MA",
    "sg:tags":[
        "key"
    ],
    "wof:name":"Mobil Locksmith",
    "wof:placetype":"venue"
},
  "geometry": {"coordinates":[-71.032286,42.390795],"type":"Point"}
}