{
  "type": "Feature",
  "properties": {
    "iso:country":"US",
    "sg:address":"29 Washington St",
    "sg:city":"Canton",
    "sg:phone":"+1 781 830 9900",
    "sg:postcode":"02021",
    "sg:province":"MA",
    "wof:name":"Life's A Bagel",
    "wof:placetype":"venue"
},
  "geometry": {"coordinates":[-71.14866499999999,42.139783],"type":"Point"}
}