{
  "type": "Feature",
  "properties": {
    "addr:full": "45 Lovering St Medway MA 02053",
    "addr:housenumber": "45",
    "addr:postcode": "02053",
    "addr:street": "Lovering St",
    "iso:country": "US",
    "sg:address": "45 Lovering St",
    "sg:city": "Medway",
    "sg:classifiers": [
      {
        "category": "Professional",
        "subcategory": "Accounting \u0026 Tax Preparation",
        "type": "Services"
      }
    ],
    "sg:phone": "+1 508 533 8195",
    "sg:postcode": "02053",
    "sg:province": "MA",
    "sg:tags": [
      "return",
      "filing"
    ],
    "wof:name": "H \u0026 R Oil Co",
    "wof:placetype": "venue"
  },
  "geometry": {"coordinates":[-71.419859,42.156973],"type":"Point"}
}
