{
  "type": "Feature",
  "properties": {
    "addr:full": "38 Montvale Ave Stoneham MA 02180",
    "addr:housenumber": "38",
    "addr:postcode": "02180",
    "addr:street": "Montvale Ave",
    "iso:country": "US",
    "sg:address": "38 Montvale Ave",
    "sg:city": "Stoneham",
    "sg:classifiers": [
      {
        "category": "Wholesale",
        "subcategory": "Apparel",
        "type": "Manufacturing \u0026 Wholesale Goods"
      }
    ],
    "sg:phone": "+1 781 438 9631",
    "sg:postcode": "02180",
    "sg:province": "MA",
    "sg:tags": [
      "piece",
      "needlework"
    ],
    "wof:name": "Design Source",
    "wof:placetype": "venue"
  },
  "geometry": {"coordinates":[-71.103747,42.482102],"type":"Point"}
}
