{
  "type": "Feature",
  "properties": {
    "iso:country":"US",
    "sg:address":"25 Iyannough Rd",
    "sg:city":"Hyannis",
    "sg:classifiers":[
        {
            "category":"Building & Trades",
            "subcategory":"Construction",
            "type":"Services"
        }
    ],
    "sg:phone":"+1 508 771 3919",
    "sg:postcode":"02601",
    "sg:province":"MA",
    "sg:tags":[
        "contractor"
    ],
    "sg:website":"www.hamiltonhomes.net",
    "wof:name":"Hamilton Homes Inc",
    "wof:placetype":"venue"
},
  "geometry": {"coordinates":[-70.27160000000001,41.6579],"type":"Point"}
}