{
  "type": "Feature",
  "properties": {
    "iso:country":"US",
    "sg:address":"360 Newbury St",
    "sg:city":"Boston",
    "sg:classifiers":[
        {
            "category":"Professional",
            "subcategory":"Advertising",
            "type":"Services"
        }
    ],
    "sg:phone":"+1 617 449 4100",
    "sg:postcode":"02116",
    "sg:province":"MA",
    "sg:tags":[
        "counselor"
    ],
    "sg:website":"www.carat.com",
    "wof:name":"Carat Interactive",
    "wof:placetype":"venue"
},
  "geometry": {"coordinates":[-71.085649,42.348766],"type":"Point"}
}