{
  "type": "Feature",
  "properties": {
    "iso:country":"US",
    "sg:address":"40 Bow Ridge Rd",
    "sg:city":"Lynn",
    "sg:classifiers":[
        {
            "category":"Building & Trades",
            "subcategory":"Landscaping Services",
            "type":"Services"
        }
    ],
    "sg:phone":"+1 781 592 7900",
    "sg:postcode":"01904",
    "sg:province":"MA",
    "sg:tags":[
        "landscape",
        "contractor"
    ],
    "wof:name":"John A Peters Landscaping",
    "wof:placetype":"venue"
},
  "geometry": {"coordinates":[-70.99090099999999,42.506847],"type":"Point"}
}