{
  "type": "Feature",
  "properties": {
    "iso:country":"US",
    "sg:address":"4 Brookside Glen",
    "sg:city":"Huntington",
    "sg:classifiers":[
        {
            "category":"Wholesale",
            "subcategory":"Machinery & Supplies",
            "type":"Manufacturing & Wholesale Goods"
        }
    ],
    "sg:phone":"+1 413 667 3125",
    "sg:postcode":"01050",
    "sg:province":"MA",
    "sg:tags":[
        "truck"
    ],
    "wof:name":"Precision Industrial Svc",
    "wof:placetype":"venue"
},
  "geometry": {"coordinates":[-72.868242,42.288422],"type":"Point"}
}