{
  "type": "Feature",
  "properties": {
    "addr:full": "4 Brookside Glen Huntington MA 01050",
    "addr:housenumber": "4",
    "addr:postcode": "01050",
    "iso:country": "US",
    "sg:address": "4 Brookside Glen",
    "sg:city": "Huntington",
    "sg:classifiers": [
      {
        "category": "Wholesale",
        "subcategory": "Machinery \u0026 Supplies",
        "type": "Manufacturing \u0026 Wholesale Goods"
      }
    ],
    "sg:phone": "+1 413 667 3125",
    "sg:postcode": "01050",
    "sg:province": "MA",
    "sg:tags": [
      "truck"
    ],
    "wof:name": "Precision Industrial Svc",
    "wof:placetype": "venue"
  },
  "geometry": {"coordinates":[-72.868242,42.288422],"type":"Point"}
}
