{
  "type": "Feature",
  "properties": {
    "addr:full": "25 Highland Avenue Newburyport MA 01950",
    "addr:housenumber": "25",
    "addr:postcode": "01950",
    "addr:street": "Highland Avenue",
    "iso:country": "US",
    "sg:address": "25 Highland Avenue",
    "sg:city": "Newburyport",
    "sg:classifiers": [
      {
        "category": "Health Services",
        "subcategory": "Doctor",
        "type": "Services"
      }
    ],
    "sg:phone": "+1 978 556 0100",
    "sg:postcode": "01950",
    "sg:province": "MA",
    "sg:tags": [
      "gynecology",
      "physician",
      "surgeons",
      "obstetrics"
    ],
    "sg:website": "http://www.ajh.org",
    "wof:name": "Women?s Health Care at Anna Jaques Hospital",
    "wof:placetype": "venue"
  },
  "geometry": {"coordinates":[-70.890587,42.81488],"type":"Point"}
}
