{
  "type": "Feature",
  "properties": {
    "iso:country":"US",
    "sg:address":"11 Sewell Rd",
    "sg:city":"Wilmington",
    "sg:classifiers":[
        {
            "category":"Government",
            "subcategory":"Office",
            "type":"Public Place"
        }
    ],
    "sg:phone":"+1 978 657 4841",
    "sg:postcode":"01887",
    "sg:province":"MA",
    "sg:tags":[
        "govt",
        "city"
    ],
    "wof:name":"Wilmington Water Dept",
    "wof:placetype":"venue"
},
  "geometry": {"coordinates":[-71.145021,42.576598],"type":"Point"}
}