{
  "type": "Feature",
  "properties": {
    "addr:full":"121 Mill Valley Rd Hadley MA 01035",
    "addr:housenumber":"121",
    "addr:postcode":"01035",
    "addr:street":"Mill Valley Rd",
    "iso:country":"US",
    "sg:address":"121 Mill Valley Rd",
    "sg:city":"Hadley",
    "sg:classifiers":[
        {
            "category":"Professional",
            "type":"Services"
        }
    ],
    "sg:phone":"+1 413 585 1609",
    "sg:postcode":"01035",
    "sg:province":"MA",
    "sg:tags":[
        "establishment"
    ],
    "wof:name":"Parsons EM & Sons Inc",
    "wof:placetype":"venue"
},
  "geometry": {"coordinates":[-72.54963499999999,42.349334],"type":"Point"}
}