{
  "type": "Feature",
  "properties": {
    "addr:full":"11 Shady Ln Marion MA 02738",
    "addr:housenumber":"11",
    "addr:postcode":"02738",
    "addr:street":"Shady Ln",
    "iso:country":"US",
    "sg:address":"11 Shady Ln",
    "sg:city":"Marion",
    "sg:classifiers":[
        {
            "category":"Retail",
            "subcategory":"Portrait Studio",
            "type":"Services"
        }
    ],
    "sg:phone":"+1   ",
    "sg:postcode":"02738",
    "sg:province":"MA",
    "sg:tags":[
        "photo"
    ],
    "wof:name":"ESA Resources Service",
    "wof:placetype":"venue"
},
  "geometry": {"coordinates":[-70.73504200000001,41.725032],"type":"Point"}
}