{
  "type": "Feature",
  "properties": {
    "addr:full":"76 Everett Skinner Rd Plainville MA 02762",
    "addr:housenumber":"76",
    "addr:postcode":"02762",
    "addr:street":"Everett Skinner Rd",
    "iso:country":"US",
    "sg:address":"76 Everett Skinner Rd",
    "sg:city":"Plainville",
    "sg:classifiers":[
        {
            "category":"Professional",
            "type":"Services"
        }
    ],
    "sg:phone":"+1   ",
    "sg:postcode":"02762",
    "sg:province":"MA",
    "wof:name":"Crystal Spring Center Ecology",
    "wof:placetype":"venue"
},
  "geometry": {"coordinates":[-71.327822,42.021587],"type":"Point"}
}