{
  "type": "Feature",
  "properties": {
    "iso:country":"US",
    "sg:address":"40 Mechanic St",
    "sg:city":"Foxboro",
    "sg:classifiers":[
        {
            "category":"Health Services",
            "subcategory":"Podiatrist",
            "type":"Services"
        }
    ],
    "sg:phone":"+1 508 543 0094",
    "sg:postcode":"02035",
    "sg:province":"MA",
    "wof:name":"Attleboro/Foxoboro Foot Specs",
    "wof:placetype":"venue"
},
  "geometry": {"coordinates":[-71.244443,42.067924],"type":"Point"}
}