{
  "type": "Feature",
  "properties": {
    "iso:country":"US",
    "sg:address":"19 Main St",
    "sg:city":"Acushnet",
    "sg:classifiers":[
        {
            "category":"Manufacturing",
            "subcategory":"Tools & Machinery",
            "type":"Manufacturing & Wholesale Goods"
        }
    ],
    "sg:phone":"+1   ",
    "sg:postcode":"02743",
    "sg:province":"MA",
    "sg:tags":[
        "mfg"
    ],
    "wof:name":"Braley Tool & Die Co",
    "wof:placetype":"venue"
},
  "geometry": {"coordinates":[-70.917754,41.682193],"type":"Point"}
}