{
  "type": "Feature",
  "properties": {
    "addr:full": "19 Main St Acushnet MA 02743",
    "addr:housenumber": "19",
    "addr:postcode": "02743",
    "addr:street": "Main St",
    "iso:country": "US",
    "sg:address": "19 Main St",
    "sg:city": "Acushnet",
    "sg:classifiers": [
      {
        "category": "Manufacturing",
        "subcategory": "Tools \u0026 Machinery",
        "type": "Manufacturing \u0026 Wholesale Goods"
      }
    ],
    "sg:phone": "+1   ",
    "sg:postcode": "02743",
    "sg:province": "MA",
    "sg:tags": [
      "mfg"
    ],
    "wof:name": "Braley Tool \u0026 Die Co",
    "wof:placetype": "venue"
  },
  "geometry": {"coordinates":[-70.917754,41.682193],"type":"Point"}
}
