{
  "type": "Feature",
  "properties": {
    "addr:full": "422 Lyon St Ludlow MA 01056",
    "addr:housenumber": "422",
    "addr:postcode": "01056",
    "addr:street": "Lyon St",
    "iso:country": "US",
    "sg:address": "422 Lyon St",
    "sg:city": "Ludlow",
    "sg:classifiers": [
      {
        "category": "Building \u0026 Trades",
        "subcategory": "Plumbing",
        "type": "Services"
      }
    ],
    "sg:phone": "+1 413 583 2397",
    "sg:postcode": "01056",
    "sg:province": "MA",
    "sg:tags": [
      "heating",
      "contractor"
    ],
    "wof:name": "Scott's Plumbing \u0026 Heating",
    "wof:placetype": "venue"
  },
  "geometry": {"coordinates":[-72.465234,42.20144],"type":"Point"}
}
