{
  "type": "Feature",
  "properties": {
    "iso:country":"US",
    "sg:address":"320 Ferry Street",
    "sg:city":"Malden",
    "sg:classifiers":[
        {
            "category":"Sports & Exercise",
            "subcategory":"Gym",
            "type":"Entertainment"
        },
        {
            "category":"Health Services",
            "subcategory":"Dentist",
            "type":"Services"
        }
    ],
    "sg:phone":"+1 781 322 2980",
    "sg:postcode":"02148",
    "sg:province":"MA",
    "sg:tags":[
        "trainer"
    ],
    "wof:name":"Berman Robt L Dent",
    "wof:placetype":"venue"
},
  "geometry": {"coordinates":[-71.060624,42.422607],"type":"Point"}
}