{
  "type": "Feature",
  "properties": {
    "addr:full": "10 B St Burlington MA 01803",
    "addr:housenumber": "10",
    "addr:postcode": "01803",
    "addr:street": "B St",
    "iso:country": "US",
    "sg:address": "10 B St",
    "sg:city": "Burlington",
    "sg:classifiers": [
      {
        "category": "Manufacturing",
        "subcategory": "Tools \u0026 Machinery",
        "type": "Manufacturing \u0026 Wholesale Goods"
      }
    ],
    "sg:phone": "+1 781 273 5656",
    "sg:postcode": "01803",
    "sg:province": "MA",
    "sg:tags": [
      "diamond"
    ],
    "sg:website": "www.neuberdiamond.com",
    "wof:name": "Neuber Industrial Diamond Inc",
    "wof:placetype": "venue"
  },
  "geometry": {"coordinates":[-71.222577,42.498379],"type":"Point"}
}
