{
  "type": "Feature",
  "properties": {
    "iso:country":"US",
    "sg:address":"50 Spring Bars Rd",
    "sg:city":"Falmouth",
    "sg:classifiers":[
        {
            "category":"Autos & Motor Vehicles",
            "subcategory":"Automobile Sales",
            "type":"Retail Goods"
        },
        {
            "category":"Retail",
            "subcategory":"Auto Repair",
            "type":"Services"
        }
    ],
    "sg:phone":"+1 508 457 9300",
    "sg:postcode":"02540",
    "sg:province":"MA",
    "sg:tags":[
        "car",
        "used",
        "truck",
        "new"
    ],
    "wof:name":"O'hara Jeep Dodge Chrysler",
    "wof:placetype":"venue"
},
  "geometry": {"coordinates":[-70.59648199999999,41.55806],"type":"Point"}
}