{
  "type": "Feature",
  "properties": {
    "addr:full": "696 Lakeview Ave Lowell MA 01850",
    "addr:housenumber": "696",
    "addr:postcode": "01850",
    "addr:street": "Lakeview Ave",
    "iso:country": "US",
    "sg:address": "696 Lakeview Ave",
    "sg:city": "Lowell",
    "sg:classifiers": [
      {
        "category": "Shopping",
        "type": "Retail Goods"
      }
    ],
    "sg:phone": "+1 978 970 2996",
    "sg:postcode": "01850",
    "sg:province": "MA",
    "sg:tags": [
      "telephone",
      "cellular"
    ],
    "wof:name": "Cellular Corner",
    "wof:placetype": "venue"
  },
  "geometry": {"coordinates":[-71.312163,42.654421],"type":"Point"}
}
