{
  "type": "Feature",
  "properties": {
    "iso:country":"US",
    "sg:address":"399 River Rd",
    "sg:city":"Hudson",
    "sg:classifiers":[
        {
            "category":"Professional",
            "type":"Services"
        }
    ],
    "sg:phone":"+1 978 568 9901",
    "sg:postcode":"01749",
    "sg:province":"MA",
    "sg:tags":[
        "establishment"
    ],
    "wof:name":"Konnext Inc",
    "wof:placetype":"venue"
},
  "geometry": {"coordinates":[-71.595613,42.372063],"type":"Point"}
}