{
  "type": "Feature",
  "properties": {
    "iso:country":"US",
    "sg:address":"36 Tremont St",
    "sg:city":"Melrose",
    "sg:classifiers":[
        {
            "category":"Wholesale",
            "subcategory":"Electrical",
            "type":"Manufacturing & Wholesale Goods"
        }
    ],
    "sg:phone":"+1 781 662 1997",
    "sg:postcode":"02176",
    "sg:province":"MA",
    "sg:tags":[
        "telephone"
    ],
    "sg:website":"www.physicalayers.com",
    "wof:name":"Physicalayers",
    "wof:placetype":"venue"
},
  "geometry": {"coordinates":[-71.069734,42.462178],"type":"Point"}
}