{
  "type": "Feature",
  "properties": {
    "addr:full": "9 Appletree Ln Bedford MA 01730",
    "addr:housenumber": "9",
    "addr:postcode": "01730",
    "addr:street": "Appletree Ln",
    "iso:country": "US",
    "sg:address": "9 Appletree Ln",
    "sg:city": "Bedford",
    "sg:classifiers": [
      {
        "category": "Building \u0026 Trades",
        "subcategory": "Construction",
        "type": "Services"
      }
    ],
    "sg:phone": "+1 781 275 1144",
    "sg:postcode": "01730",
    "sg:province": "MA",
    "sg:tags": [
      "equipment",
      "station"
    ],
    "wof:name": "Kel-Scot Corp",
    "wof:placetype": "venue"
  },
  "geometry": {"coordinates":[-71.288653,42.519237],"type":"Point"}
}
