{
  "type": "Feature",
  "properties": {
    "addr:full":"955 Massachusetts Ave #231 Cambridge MA 02139",
    "addr:housenumber":"955",
    "addr:postcode":"02139",
    "addr:street":"Massachusetts Ave # 231",
    "iso:country":"US",
    "sg:address":"955 Massachusetts Ave #231",
    "sg:city":"Cambridge",
    "sg:classifiers":[
        {
            "category":"Communications",
            "type":"Services"
        }
    ],
    "sg:phone":"+1 617 818 3110",
    "sg:postcode":"02139",
    "sg:province":"MA",
    "sg:tags":[
        "web",
        "design"
    ],
    "wof:name":"Diverture",
    "wof:placetype":"venue"
},
  "geometry": {"coordinates":[-71.110276,42.369007],"type":"Point"}
}