{
  "type": "Feature",
  "properties": {
    "addr:full": "10 Pillings Pond Rd Lynnfield MA 01940",
    "addr:housenumber": "10",
    "addr:postcode": "01940",
    "addr:street": "Pillings Pond Rd",
    "iso:country": "US",
    "sg:address": "10 Pillings Pond Rd",
    "sg:city": "Lynnfield",
    "sg:classifiers": [
      {
        "category": "Real Estate",
        "subcategory": "Real Estate Operator",
        "type": "Services"
      }
    ],
    "sg:phone": "+1 781 334 4156",
    "sg:postcode": "01940",
    "sg:province": "MA",
    "sg:tags": [
      "apartment"
    ],
    "wof:name": "Aero Realty Inc",
    "wof:placetype": "venue"
  },
  "geometry": {"coordinates":[-71.02743,42.537619],"type":"Point"}
}
