{
  "type": "Feature",
  "properties": {
    "addr:full":"15 Jan Sebastian Dr Sandwich MA 02563",
    "addr:housenumber":"15",
    "addr:postcode":"02563",
    "addr:street":"Jan Sebastian Dr",
    "iso:country":"US",
    "sg:address":"15 Jan Sebastian Dr",
    "sg:city":"Sandwich",
    "sg:classifiers":[
        {
            "category":"Education",
            "subcategory":"Special Training",
            "type":"Public Place"
        }
    ],
    "sg:phone":"+1 508 888 7969",
    "sg:postcode":"02563",
    "sg:province":"MA",
    "sg:tags":[
        "instruction",
        "music"
    ],
    "sg:website":"www.scoremusicstudios.com",
    "wof:name":"Score Music Studios",
    "wof:placetype":"venue"
},
  "geometry": {"coordinates":[-70.48438299999999,41.71827],"type":"Point"}
}