{
  "type": "Feature",
  "properties": {
    "addr:full": "257 Providence St Worcester MA 01607",
    "addr:housenumber": "257",
    "addr:postcode": "01607",
    "addr:street": "Providence St",
    "iso:country": "US",
    "sg:address": "257 Providence St",
    "sg:city": "Worcester",
    "sg:classifiers": [
      {
        "category": "Bagels",
        "type": "Food \u0026 Drink"
      },
      {
        "category": "Coffee \u0026 Tea",
        "type": "Food \u0026 Drink"
      },
      {
        "category": "Food \u0026 Beverages",
        "subcategory": "Bakery",
        "type": "Retail Goods"
      },
      {
        "category": "Bakery",
        "type": "Food \u0026 Drink"
      },
      {
        "category": "Donuts",
        "type": "Food \u0026 Drink"
      }
    ],
    "sg:menulink": "http://www.allmenus.com/ma/worcester/143570-dunkin-donuts/menu/",
    "sg:phone": "+1 508 792 0080",
    "sg:postcode": "01607",
    "sg:province": "MA",
    "sg:tags": [
      "coffee",
      "diner",
      "tea",
      "bakery",
      "bagel",
      "american",
      "pastry"
    ],
    "wof:name": "Dunkin' Donuts",
    "wof:placetype": "venue"
  },
  "geometry": {"coordinates":[-71.792008,42.238749],"type":"Point"}
}
