{
  "type": "Feature",
  "properties": {
    "iso:country":"US",
    "sg:address":"1 Parker St",
    "sg:city":"Chelsea",
    "sg:classifiers":[
        {
            "category":"Local Transit",
            "type":"Transportation"
        }
    ],
    "sg:phone":"+1 617 285 9131",
    "sg:postcode":"02150",
    "sg:province":"MA",
    "sg:tags":[
        "passenger",
        "limousine"
    ],
    "wof:name":"Abebe Coach Service",
    "wof:placetype":"venue"
},
  "geometry": {"coordinates":[-71.029808,42.399639],"type":"Point"}
}