{
  "type": "Feature",
  "properties": {
    "addr:full": "17 Kellogg Ave Amherst MA 01002",
    "addr:housenumber": "17",
    "addr:postcode": "01002",
    "addr:street": "Kellogg Ave",
    "iso:country": "US",
    "sg:address": "17 Kellogg Ave",
    "sg:city": "Amherst",
    "sg:classifiers": [
      {
        "category": "Personal",
        "subcategory": "Beauty Salon",
        "type": "Services"
      }
    ],
    "sg:phone": "+1 413 253 9879",
    "sg:postcode": "01002",
    "sg:province": "MA",
    "wof:name": "Aesthetics Skin \u0026 Body Care",
    "wof:placetype": "venue"
  },
  "geometry": {"coordinates":[-72.519312,42.377481],"type":"Point"}
}
