{
  "type": "Feature",
  "properties": {
    "iso:country":"US",
    "sg:address":"728 Salem End Rd",
    "sg:city":"Framingham",
    "sg:classifiers":[
        {
            "category":"Organizations",
            "subcategory":"Religious Organization",
            "type":"Services"
        }
    ],
    "sg:phone":"+1 508 628 1511",
    "sg:postcode":"01702",
    "sg:province":"MA",
    "sg:tags":[
        "church"
    ],
    "wof:name":"Metro West Bridge Christian",
    "wof:placetype":"venue"
},
  "geometry": {"coordinates":[-71.466567,42.285053],"type":"Point"}
}