{
  "type": "Feature",
  "properties": {
    "addr:full":"427 2nd St Fall River MA 02721",
    "addr:housenumber":"427",
    "addr:postcode":"02721",
    "addr:street":"2Nd St",
    "iso:country":"US",
    "sg:address":"427 2nd St",
    "sg:city":"Fall River",
    "sg:classifiers":[
        {
            "category":"Building & Trades",
            "subcategory":"Construction",
            "type":"Services"
        }
    ],
    "sg:phone":"+1 508 673 2333",
    "sg:postcode":"02721",
    "sg:province":"MA",
    "sg:tags":[
        "lettering",
        "painting",
        "boat"
    ],
    "wof:name":"Gary's Signs",
    "wof:placetype":"venue"
},
  "geometry": {"coordinates":[-71.158016,41.697136],"type":"Point"}
}