{
  "type": "Feature",
  "properties": {
    "iso:country":"US",
    "sg:address":"199 Mystic Ave",
    "sg:city":"Medford",
    "sg:classifiers":[
        {
            "category":"Building & Trades",
            "subcategory":"Locksmith",
            "type":"Services"
        }
    ],
    "sg:phone":"+1 781 658 3134",
    "sg:postcode":"02155",
    "sg:province":"MA",
    "sg:tags":[
        "key"
    ],
    "wof:name":"1 24 Hour Emergency Locksmith",
    "wof:placetype":"venue"
},
  "geometry": {"coordinates":[-71.104043,42.408087],"type":"Point"}
}