{
  "type": "Feature",
  "properties": {
    "addr:full":"111R Salem St Woburn MA 01801",
    "addr:housenumber":"111r",
    "addr:postcode":"01801",
    "addr:street":"Salem St",
    "iso:country":"US",
    "sg:address":"111R Salem St",
    "sg:city":"Woburn",
    "sg:classifiers":[
        {
            "category":"Retail",
            "subcategory":"Auto Repair",
            "type":"Services"
        }
    ],
    "sg:phone":"+1 781 933 2574",
    "sg:postcode":"01801",
    "sg:province":"MA",
    "wof:name":"Salem Street Automotive",
    "wof:placetype":"venue"
},
  "geometry": {"coordinates":[-71.14360000000001,42.4869],"type":"Point"}
}