{
  "type": "Feature",
  "properties": {
    "iso:country":"US",
    "sg:address":"152 Maplewood Ave",
    "sg:city":"Gloucester",
    "sg:classifiers":[
        {
            "category":"Building & Trades",
            "subcategory":"Plumbing",
            "type":"Services"
        }
    ],
    "sg:phone":"+1 978 283 2258",
    "sg:postcode":"01930",
    "sg:province":"MA",
    "sg:tags":[
        "plumbing",
        "contractor"
    ],
    "wof:name":"Michael Burke Plumbing & Htg",
    "wof:placetype":"venue"
},
  "geometry": {"coordinates":[-70.669483,42.623177],"type":"Point"}
}