{
  "type": "Feature",
  "properties": {
    "addr:full":"851 Washington St Holliston MA 01746",
    "addr:housenumber":"851",
    "addr:postcode":"01746",
    "addr:street":"Washington St",
    "iso:country":"US",
    "sg:address":"851 Washington St",
    "sg:city":"Holliston",
    "sg:classifiers":[
        {
            "category":"Professional",
            "subcategory":"Management & Consulting",
            "type":"Services"
        }
    ],
    "sg:phone":"+1 508 893 6999",
    "sg:postcode":"01746",
    "sg:province":"MA",
    "wof:name":"Beacon Benefits Consulting",
    "wof:placetype":"venue"
},
  "geometry": {"coordinates":[-71.430685,42.198775],"type":"Point"}
}