{
  "type": "Feature",
  "properties": {
    "iso:country":"US",
    "sg:address":"210 Beacham St",
    "sg:city":"Everett",
    "sg:classifiers":[
        {
            "category":"Food & Beverages",
            "subcategory":"Meat & Fish",
            "type":"Retail Goods"
        }
    ],
    "sg:phone":"+1 617 389 3117",
    "sg:postcode":"02149",
    "sg:province":"MA",
    "sg:tags":[
        "shop"
    ],
    "wof:name":"Jet Provisions",
    "wof:placetype":"venue"
},
  "geometry": {"coordinates":[-71.055251,42.394468],"type":"Point"}
}