{
  "type": "Feature",
  "properties": {
    "addr:full": "35 Jacobs St 2 Peabody MA 01960",
    "addr:housenumber": "35;2",
    "addr:postcode": "01960",
    "addr:street": "Jacobs St",
    "iso:country": "US",
    "sg:address": "35 Jacobs St 2",
    "sg:city": "Peabody",
    "sg:classifiers": [
      {
        "category": "Personal",
        "subcategory": "Nail Salon",
        "type": "Services"
      }
    ],
    "sg:phone": "+1 978 532 4815",
    "sg:postcode": "01960",
    "sg:province": "MA",
    "wof:name": "Lisa Pantapas",
    "wof:placetype": "venue"
  },
  "geometry": {"coordinates":[-70.929613,42.529289],"type":"Point"}
}
