{
  "type": "Feature",
  "properties": {
    "addr:full": "12 Whites Path South Yarmouth MA 02664",
    "addr:housenumber": "12",
    "addr:postcode": "02664",
    "addr:street": "Whites Path",
    "iso:country": "US",
    "sg:address": "12 Whites Path",
    "sg:city": "South Yarmouth",
    "sg:classifiers": [
      {
        "category": "Manufacturing",
        "subcategory": "Signs",
        "type": "Manufacturing \u0026 Wholesale Goods"
      }
    ],
    "sg:phone": "+1 508 398 9100",
    "sg:postcode": "02664",
    "sg:province": "MA",
    "wof:name": "Sign-A-Rama",
    "wof:placetype": "venue"
  },
  "geometry": {"coordinates":[-70.210625,41.688102],"type":"Point"}
}
