{
  "type": "Feature",
  "properties": {
    "iso:country":"US",
    "sg:address":"12 Whites Path",
    "sg:city":"South Yarmouth",
    "sg:classifiers":[
        {
            "category":"Manufacturing",
            "subcategory":"Signs",
            "type":"Manufacturing & Wholesale Goods"
        }
    ],
    "sg:phone":"+1 508 398 9100",
    "sg:postcode":"02664",
    "sg:province":"MA",
    "wof:name":"Sign-A-Rama",
    "wof:placetype":"venue"
},
  "geometry": {"coordinates":[-70.21062499999999,41.688102],"type":"Point"}
}