{
  "type": "Feature",
  "properties": {
    "iso:country":"US",
    "sg:address":"132 S Union St",
    "sg:city":"Lawrence",
    "sg:classifiers":[
        {
            "category":"Shopping",
            "subcategory":"Music",
            "type":"Retail Goods"
        }
    ],
    "sg:phone":"+1 978 682 5193",
    "sg:postcode":"01843",
    "sg:province":"MA",
    "sg:tags":[
        "compact",
        "record",
        "disc",
        "tape"
    ],
    "wof:name":"Union Cd",
    "wof:placetype":"venue"
},
  "geometry": {"coordinates":[-71.153328,42.697558],"type":"Point"}
}