{
  "type": "Feature",
  "properties": {
    "iso:country":"US",
    "sg:address":"10 James Ave",
    "sg:city":"Boston",
    "sg:classifiers":[
        {
            "category":"Professional",
            "subcategory":"Lawyer & Legal Services",
            "type":"Services"
        }
    ],
    "sg:phone":"+1 617 523 2700",
    "sg:postcode":"02152",
    "sg:province":"MA",
    "sg:tags":[
        "attorney"
    ],
    "wof:name":"Holland & Knight",
    "wof:placetype":"venue"
},
  "geometry": {"coordinates":[-70.98156899999999,42.374565],"type":"Point"}
}