{
  "type": "Feature",
  "properties": {
    "iso:country":"US",
    "sg:address":"15 Court Sq",
    "sg:city":"Boston",
    "sg:classifiers":[
        {
            "category":"Shopping",
            "type":"Retail Goods"
        }
    ],
    "sg:phone":"+1 617 720 3434",
    "sg:postcode":"02108",
    "sg:province":"MA",
    "sg:tags":[
        "miscellaneous",
        "store"
    ],
    "wof:name":"Massachusetts Workforce Board",
    "wof:placetype":"venue"
},
  "geometry": {"coordinates":[-71.05866899999999,42.358718],"type":"Point"}
}