{
  "type": "Feature",
  "properties": {
    "iso:country":"US",
    "sg:address":"59 Waters Avenue",
    "sg:city":"Everett",
    "sg:classifiers":[
        {
            "category":"Personal",
            "type":"Services"
        }
    ],
    "sg:phone":"+1 781 324 5880",
    "sg:postcode":"02149",
    "sg:province":"MA",
    "sg:tags":[
        "mover"
    ],
    "wof:name":"A Town & Country Moving & Storage",
    "wof:placetype":"venue"
},
  "geometry": {"coordinates":[-71.048604,42.4103],"type":"Point"}
}