{
  "type": "Feature",
  "properties": {
    "addr:full":"94 Royal St Chicopee MA 01020",
    "addr:housenumber":"94",
    "addr:postcode":"01020",
    "addr:street":"Royal St",
    "iso:country":"US",
    "sg:address":"94 Royal St",
    "sg:city":"Chicopee",
    "sg:classifiers":[
        {
            "category":"Social Services",
            "subcategory":"Adult Care",
            "type":"Services"
        }
    ],
    "sg:phone":"+1   ",
    "sg:postcode":"01020",
    "sg:province":"MA",
    "sg:tags":[
        "residential"
    ],
    "wof:name":"Comuninity Service Program",
    "wof:placetype":"venue"
},
  "geometry": {"coordinates":[-72.56823799999999,42.20969],"type":"Point"}
}