{
  "type": "Feature",
  "properties": {
    "iso:country":"US",
    "sg:address":"47 High St",
    "sg:city":"Mansfield",
    "sg:classifiers":[
        {
            "category":"Organizations",
            "subcategory":"Religious Organization",
            "type":"Services"
        }
    ],
    "sg:phone":"+1 508 339 7484",
    "sg:postcode":"02048",
    "sg:province":"MA",
    "sg:tags":[
        "church"
    ],
    "wof:name":"St John's Episcopal Church",
    "wof:placetype":"venue"
},
  "geometry": {"coordinates":[-71.21987300000001,42.028646],"type":"Point"}
}