{
  "type": "Feature",
  "properties": {
    "addr:full":"52 Chauncy St Boston MA 02111",
    "addr:housenumber":"52",
    "addr:postcode":"02111",
    "addr:street":"Chauncy St",
    "iso:country":"US",
    "sg:address":"52 Chauncy St",
    "sg:city":"Boston",
    "sg:classifiers":[
        {
            "category":"Real Estate",
            "subcategory":"Real Estate Agent",
            "type":"Services"
        }
    ],
    "sg:phone":"+1 617 988 3441",
    "sg:postcode":"02111",
    "sg:province":"MA",
    "sg:tags":[
        "authorities",
        "housing"
    ],
    "sg:website":"www.bostonhousing.org",
    "wof:name":"Boston Housing Authority",
    "wof:placetype":"venue"
},
  "geometry": {"coordinates":[-71.060014,42.35374],"type":"Point"}
}