{
  "type": "Feature",
  "properties": {
    "iso:country":"US",
    "sg:address":"84 Highland Ave Ste 311",
    "sg:city":"Salem",
    "sg:classifiers":[
        {
            "category":"Health Services",
            "subcategory":"Doctor",
            "type":"Services"
        }
    ],
    "sg:phone":"+1 978 744 1550",
    "sg:postcode":"01970",
    "sg:province":"MA",
    "sg:tags":[
        "psychiatry",
        "physician",
        "surgeon",
        "surgeons"
    ],
    "wof:name":"Richard L Pohl",
    "wof:placetype":"venue"
},
  "geometry": {"coordinates":[-70.908722,42.511871],"type":"Point"}
}