{
  "type": "Feature",
  "properties": {
    "addr:full":"9 Lenway Rd Byfield MA 01922",
    "addr:housenumber":"9",
    "addr:postcode":"01922",
    "addr:street":"Lenway Rd",
    "iso:country":"US",
    "sg:address":"9 Lenway Rd",
    "sg:city":"Byfield",
    "sg:classifiers":[
        {
            "category":"Professional",
            "subcategory":"Management & Consulting",
            "type":"Services"
        }
    ],
    "sg:phone":"+1 978 465 7033",
    "sg:postcode":"01922",
    "sg:province":"MA",
    "sg:tags":[
        "marketing",
        "consultant"
    ],
    "wof:name":"Marketalk",
    "wof:placetype":"venue"
},
  "geometry": {"coordinates":[-70.942397,42.760312],"type":"Point"}
}