{
  "type": "Feature",
  "properties": {
    "iso:country":"US",
    "sg:address":"85 Copeland Dr",
    "sg:city":"Mansfield",
    "sg:classifiers":[
        {
            "category":"Professional",
            "subcategory":"Engineering",
            "type":"Services"
        }
    ],
    "sg:phone":"+1 508 337 3030",
    "sg:postcode":"02048",
    "sg:province":"MA",
    "sg:tags":[
        "engineer"
    ],
    "wof:name":"A I Engineers Inc",
    "wof:placetype":"venue"
},
  "geometry": {"coordinates":[-71.228573,42.029566],"type":"Point"}
}