{
  "type": "Feature",
  "properties": {
    "iso:country":"US",
    "sg:address":"42 Batterymarch St.",
    "sg:city":"Boston",
    "sg:classifiers":[
        {
            "category":"Personal",
            "subcategory":"Massage",
            "type":"Services"
        }
    ],
    "sg:phone":"+1 617 338 9999",
    "sg:postcode":"02110",
    "sg:province":"MA",
    "wof:name":"The Bamboo Valley Spa & Massage",
    "wof:placetype":"venue"
},
  "geometry": {"coordinates":[-71.053827,42.357566],"type":"Point"}
}