{
  "type": "Feature",
  "properties": {
    "addr:full":"496 Boston Post Rd E Marlborough MA 01752",
    "addr:housenumber":"496",
    "addr:postcode":"01752",
    "addr:street":"Boston Post Rd E",
    "iso:country":"US",
    "sg:address":"496 Boston Post Rd E",
    "sg:city":"Marlborough",
    "sg:classifiers":[
        {
            "category":"Social Services",
            "subcategory":"Child Care",
            "type":"Services"
        }
    ],
    "sg:phone":"+1 508 229 4415",
    "sg:postcode":"01752",
    "sg:province":"MA",
    "wof:name":"Kinder Care Learning Ctr",
    "wof:placetype":"venue"
},
  "geometry": {"coordinates":[-71.510814,42.347566],"type":"Point"}
}