{
  "type": "Feature",
  "properties": {
    "addr:full":"104 Hill Street Stoneham MA 02180",
    "addr:housenumber":"104",
    "addr:postcode":"02180",
    "addr:street":"Hill Street",
    "iso:country":"US",
    "sg:address":"104 Hill Street",
    "sg:city":"Stoneham",
    "sg:classifiers":[
        {
            "category":"Real Estate",
            "subcategory":"Real Estate Operator",
            "type":"Services"
        }
    ],
    "sg:phone":"+1 781 438 6049",
    "sg:postcode":"02180",
    "sg:province":"MA",
    "sg:tags":[
        "apartment"
    ],
    "wof:name":"Hillside Gardens Guard House",
    "wof:placetype":"venue"
},
  "geometry": {"coordinates":[-71.10991199999999,42.474099],"type":"Point"}
}