{
  "type": "Feature",
  "properties": {
    "addr:full": "125 Warren Ave Boston MA 02116",
    "addr:housenumber": "125",
    "addr:postcode": "02116",
    "addr:street": "Warren Ave",
    "iso:country": "US",
    "sg:address": "125 Warren Ave",
    "sg:city": "Boston",
    "sg:classifiers": [
      {
        "category": "Professional",
        "subcategory": "Research",
        "type": "Services"
      }
    ],
    "sg:phone": "+1 617 266 3620",
    "sg:postcode": "02116",
    "sg:province": "MA",
    "sg:tags": [
      "market",
      "analysis"
    ],
    "wof:name": "TNS",
    "wof:placetype": "venue"
  },
  "geometry": {"coordinates":[-71.073223,42.344842],"type":"Point"}
}
