{
  "type": "Feature",
  "properties": {
    "addr:full":"39 Robin Ln Rockland MA 02370",
    "addr:housenumber":"39",
    "addr:postcode":"02370",
    "addr:street":"Robin Ln",
    "iso:country":"US",
    "sg:address":"39 Robin Ln",
    "sg:city":"Rockland",
    "sg:classifiers":[
        {
            "category":"Professional",
            "subcategory":"Management & Consulting",
            "type":"Services"
        }
    ],
    "sg:phone":"+1 781 792 0990",
    "sg:postcode":"02370",
    "sg:province":"MA",
    "sg:tags":[
        "consultant",
        "business"
    ],
    "wof:name":"Linden Resources",
    "wof:placetype":"venue"
},
  "geometry": {"coordinates":[-70.91865799999999,42.106942],"type":"Point"}
}