{
  "type": "Feature",
  "properties": {
    "addr:full":"119 Route 137 Harwich MA 02645",
    "addr:housenumber":"119",
    "addr:postcode":"02645",
    "addr:street":"Route 137",
    "iso:country":"US",
    "sg:address":"119 Route 137",
    "sg:city":"Harwich",
    "sg:classifiers":[
        {
            "category":"Health Services",
            "subcategory":"Dentist",
            "type":"Services"
        }
    ],
    "sg:phone":"+1 508 432 8686",
    "sg:postcode":"02645",
    "sg:province":"MA",
    "wof:name":"Campagna Gary DMD",
    "wof:placetype":"venue"
},
  "geometry": {"coordinates":[-70.018501,41.710899],"type":"Point"}
}