{
  "type": "Feature",
  "properties": {
    "iso:country":"US",
    "sg:address":"206 Main St",
    "sg:city":"Haydenville",
    "sg:classifiers":[
        {
            "category":"Bakery",
            "type":"Food & Drink"
        }
    ],
    "sg:phone":"+1 413 268 7757",
    "sg:postcode":"01039",
    "sg:province":"MA",
    "wof:name":"Bread Euphoria",
    "wof:placetype":"venue"
},
  "geometry": {"coordinates":[-72.693986,42.369439],"type":"Point"}
}