{
  "type": "Feature",
  "properties": {
    "iso:country":"US",
    "sg:address":"3 Main St",
    "sg:city":"Lunenburg",
    "sg:classifiers":[
        {
            "category":"Retail",
            "subcategory":"Portrait Studio",
            "type":"Services"
        }
    ],
    "sg:phone":"+1 978 582 4060",
    "sg:postcode":"01462",
    "sg:province":"MA",
    "sg:tags":[
        "photographer"
    ],
    "wof:name":"Belliveau Photography",
    "wof:placetype":"venue"
},
  "geometry": {"coordinates":[-71.725123,42.595014],"type":"Point"}
}