{
  "type": "Feature",
  "properties": {
    "addr:full": "6 Baxter St Dennis Port MA 02639",
    "addr:housenumber": "6",
    "addr:postcode": "02639",
    "addr:street": "Baxter St",
    "iso:country": "US",
    "sg:address": "6 Baxter St",
    "sg:city": "Dennis Port",
    "sg:classifiers": [
      {
        "category": "Personal",
        "subcategory": "Beauty Salon",
        "type": "Services"
      }
    ],
    "sg:phone": "+1 508 394 8555",
    "sg:postcode": "02639",
    "sg:province": "MA",
    "sg:tags": [
      "spa",
      "day"
    ],
    "wof:name": "Spa 28",
    "wof:placetype": "venue"
  },
  "geometry": {"coordinates":[-70.147116,41.667435],"type":"Point"}
}
