{
  "type": "Feature",
  "properties": {
    "addr:full": "3067 Cranberry Hwy East Wareham MA 02538",
    "addr:housenumber": "3067",
    "addr:postcode": "02538",
    "addr:street": "Cranberry Hwy",
    "iso:country": "US",
    "sg:address": "3067 Cranberry Hwy",
    "sg:city": "East Wareham",
    "sg:classifiers": [
      {
        "category": "Autos \u0026 Motor Vehicles",
        "subcategory": "Fuel \u0026 Gas Station",
        "type": "Retail Goods"
      }
    ],
    "sg:phone": "+1 508 291 1357",
    "sg:postcode": "02538",
    "sg:province": "MA",
    "sg:tags": [
      "oil"
    ],
    "wof:name": "Pro-Team Quick Oil Change",
    "wof:placetype": "venue"
  },
  "geometry": {"coordinates":[-70.654345,41.756897],"type":"Point"}
}
