{
  "type": "Feature",
  "properties": {
    "iso:country":"US",
    "sg:address":"3067 Cranberry Hwy",
    "sg:city":"East Wareham",
    "sg:classifiers":[
        {
            "category":"Autos & Motor Vehicles",
            "subcategory":"Fuel & Gas Station",
            "type":"Retail Goods"
        }
    ],
    "sg:phone":"+1 508 291 1357",
    "sg:postcode":"02538",
    "sg:province":"MA",
    "sg:tags":[
        "oil"
    ],
    "wof:name":"Pro-Team Quick Oil Change",
    "wof:placetype":"venue"
},
  "geometry": {"coordinates":[-70.65434500000001,41.756897],"type":"Point"}
}