{
  "type": "Feature",
  "properties": {
    "iso:country":"US",
    "sg:address":"14 Milk St",
    "sg:city":"Newburyport",
    "sg:classifiers":[
        {
            "category":"Social Services",
            "type":"Services"
        }
    ],
    "sg:phone":"+1 978 462 8692",
    "sg:postcode":"01950",
    "sg:province":"MA",
    "wof:name":"Lakota Sioux Indian Outre",
    "wof:placetype":"venue"
},
  "geometry": {"coordinates":[-70.866117,42.807153],"type":"Point"}
}