{
  "type": "Feature",
  "properties": {
    "addr:full": "323 Barnstable Rd Hyannis MA 02601",
    "addr:housenumber": "323",
    "addr:postcode": "02601",
    "addr:street": "Barnstable Rd",
    "iso:country": "US",
    "ovtr:label": "Bike Zone, 323 Barnstable Rd Hyannis MA US",
    "ovtr:similarity": 1.8475090265274048,
    "sg:address": "323 Barnstable Rd",
    "sg:city": "Hyannis",
    "sg:classifiers": [
      {
        "category": "Sports \u0026 Exercise",
        "subcategory": "Bicycle Rental",
        "type": "Entertainment"
      }
    ],
    "sg:phone": "+1 508 775 3299",
    "sg:postcode": "02601",
    "sg:province": "MA",
    "sg:tags": [
      "bike"
    ],
    "wof:name": "Bike Zone",
    "wof:placetype": "venue"
  },
  "geometry": {"coordinates":[-70.286201,41.6628],"type":"Point"}
}
