{
  "type": "Feature",
  "properties": {
    "iso:country":"US",
    "sg:address":"323 Barnstable Rd",
    "sg:city":"Hyannis",
    "sg:classifiers":[
        {
            "category":"Sports & Exercise",
            "subcategory":"Bicycle Rental",
            "type":"Entertainment"
        }
    ],
    "sg:phone":"+1 508 775 3299",
    "sg:postcode":"02601",
    "sg:province":"MA",
    "sg:tags":[
        "bike"
    ],
    "wof:name":"Bike Zone",
    "wof:placetype":"venue"
},
  "geometry": {"coordinates":[-70.28620100000001,41.6628],"type":"Point"}
}