{
  "type": "Feature",
  "properties": {
    "iso:country":"US",
    "sg:address":"33 N Main St",
    "sg:city":"Sherborn",
    "sg:classifiers":[
        {
            "category":"Restaurant",
            "type":"Food & Drink"
        }
    ],
    "sg:phone":"+1 508 655 9521",
    "sg:postcode":"01770",
    "sg:province":"MA",
    "sg:tags":[
        "caterer"
    ],
    "sg:website":"www.sherborninn.com",
    "wof:name":"Sherborn Inn",
    "wof:placetype":"venue"
},
  "geometry": {"coordinates":[-71.369041,42.246776],"type":"Point"}
}