{
  "type": "Feature",
  "properties": {
    "addr:full": "33 N Main St Sherborn MA 01770",
    "addr:housenumber": "33",
    "addr:postcode": "01770",
    "addr:street": "N Main St",
    "iso:country": "US",
    "sg:address": "33 N Main St",
    "sg:city": "Sherborn",
    "sg:classifiers": [
      {
        "category": "Restaurant",
        "type": "Food \u0026 Drink"
      }
    ],
    "sg:phone": "+1 508 655 9521",
    "sg:postcode": "01770",
    "sg:province": "MA",
    "sg:tags": [
      "caterer"
    ],
    "sg:website": "www.sherborninn.com",
    "wof:name": "Sherborn Inn",
    "wof:placetype": "venue"
  },
  "geometry": {"coordinates":[-71.369041,42.246776],"type":"Point"}
}
