{
  "type": "Feature",
  "properties": {
    "iso:country":"US",
    "sg:address":"17 Pope St",
    "sg:city":"Hudson",
    "sg:classifiers":[
        {
            "category":"Wholesale",
            "subcategory":"Office Equipment",
            "type":"Manufacturing & Wholesale Goods"
        }
    ],
    "sg:phone":"+1 617 666 4899",
    "sg:postcode":"01749",
    "sg:province":"MA",
    "sg:tags":[
        "machine",
        "duplicating",
        "copying"
    ],
    "wof:name":"Digitron",
    "wof:placetype":"venue"
},
  "geometry": {"coordinates":[-71.567879,42.393264],"type":"Point"}
}