{
  "type": "Feature",
  "properties": {
    "iso:country":"US",
    "sg:address":"103 Vanderbilt Ave",
    "sg:city":"Norwood",
    "sg:classifiers":[
        {
            "category":"Retail",
            "subcategory":"Repair Shop",
            "type":"Services"
        }
    ],
    "sg:phone":"+1   ",
    "sg:postcode":"02062",
    "sg:province":"MA",
    "sg:tags":[
        "household",
        "appliance"
    ],
    "wof:name":"Sears Product Service 8103",
    "wof:placetype":"venue"
},
  "geometry": {"coordinates":[-71.19001299999999,42.17221],"type":"Point"}
}