{
  "type": "Feature",
  "properties": {
    "addr:full": "43 Beacham St Everett MA 02149",
    "addr:housenumber": "43",
    "addr:postcode": "02149",
    "addr:street": "Beacham St",
    "iso:country": "US",
    "sg:address": "43 Beacham St",
    "sg:city": "Everett",
    "sg:phone": "+1 617 389 9173",
    "sg:postcode": "02149",
    "sg:province": "MA",
    "sg:tags": [
      "oil"
    ],
    "wof:name": "Sprague Energy",
    "wof:placetype": "venue"
  },
  "geometry": {"coordinates":[-71.055722,42.394358],"type":"Point"}
}
