{
  "type": "Feature",
  "properties": {
    "addr:full":"20 Mill Ln Braintree MA 02184",
    "addr:housenumber":"20",
    "addr:postcode":"02184",
    "addr:street":"Mill Ln",
    "iso:country":"US",
    "sg:address":"20 Mill Ln",
    "sg:city":"Braintree",
    "sg:classifiers":[
        {
            "category":"Retail",
            "subcategory":"Auto Repair",
            "type":"Services"
        }
    ],
    "sg:phone":"+1 781 356 6365",
    "sg:postcode":"02184",
    "sg:province":"MA",
    "sg:tags":[
        "repairing",
        "automobile"
    ],
    "wof:name":"Craig's Auto Body",
    "wof:placetype":"venue"
},
  "geometry": {"coordinates":[-70.97475,42.220859],"type":"Point"}
}