{
  "type": "Feature",
  "properties": {
    "iso:country":"US",
    "sg:address":"61 Water St",
    "sg:city":"Rehoboth",
    "sg:classifiers":[
        {
            "category":"Banks & Credit Unions",
            "subcategory":"Investment Brokerage",
            "type":"Services"
        },
        {
            "category":"Banks & Credit Unions",
            "subcategory":"Financial Services",
            "type":"Services"
        }
    ],
    "sg:phone":"+1 508 336 4663",
    "sg:postcode":"02769",
    "sg:province":"MA",
    "sg:tags":[
        "advisory",
        "planner"
    ],
    "wof:name":"M & K Home Investment Inc",
    "wof:placetype":"venue"
},
  "geometry": {"coordinates":[-71.277451,41.812031],"type":"Point"}
}