{
  "type": "Feature",
  "properties": {
    "addr:full": "61 Water St Rehoboth MA 02769",
    "addr:housenumber": "61",
    "addr:postcode": "02769",
    "addr:street": "Water St",
    "iso:country": "US",
    "sg:address": "61 Water St",
    "sg:city": "Rehoboth",
    "sg:classifiers": [
      {
        "category": "Banks \u0026 Credit Unions",
        "subcategory": "Investment Brokerage",
        "type": "Services"
      },
      {
        "category": "Banks \u0026 Credit Unions",
        "subcategory": "Financial Services",
        "type": "Services"
      }
    ],
    "sg:phone": "+1 508 336 4663",
    "sg:postcode": "02769",
    "sg:province": "MA",
    "sg:tags": [
      "advisory",
      "planner"
    ],
    "wof:name": "M \u0026 K Home Investment Inc",
    "wof:placetype": "venue"
  },
  "geometry": {"coordinates":[-71.277451,41.812031],"type":"Point"}
}
