{
  "type": "Feature",
  "properties": {
    "addr:full": "1945 Washington St Stoughton MA 02072",
    "addr:housenumber": "1945",
    "addr:postcode": "02072",
    "addr:street": "Washington St",
    "iso:country": "US",
    "sg:address": "1945 Washington St",
    "sg:city": "Stoughton",
    "sg:classifiers": [
      {
        "category": "Retail",
        "subcategory": "Auto Repair",
        "type": "Services"
      }
    ],
    "sg:phone": "+1 781 341 0201",
    "sg:postcode": "02072",
    "sg:province": "MA",
    "sg:tags": [
      "automobile",
      "customizing"
    ],
    "wof:name": "Custom Reproductions Inc",
    "wof:placetype": "venue"
  },
  "geometry": {"coordinates":[-71.094315,42.093113],"type":"Point"}
}
