{
  "type": "Feature",
  "properties": {
    "addr:full": "57 Main St Webster MA 01570",
    "addr:housenumber": "57",
    "addr:postcode": "01570",
    "addr:street": "Main St",
    "iso:country": "US",
    "sg:address": "57 Main St",
    "sg:city": "Webster",
    "sg:classifiers": [
      {
        "category": "Food \u0026 Beverages",
        "subcategory": "Liquor \u0026 Beverages",
        "type": "Retail Goods"
      }
    ],
    "sg:phone": "+1 508 943 4088",
    "sg:postcode": "01570",
    "sg:province": "MA",
    "wof:name": "Webster Wine \u0026 Liquors Inc",
    "wof:placetype": "venue"
  },
  "geometry": {"coordinates":[-71.886267,42.049324],"type":"Point"}
}
