{
  "type": "Feature",
  "properties": {
    "addr:full":"153 Foundry St Wakefield MA 01880",
    "addr:housenumber":"153",
    "addr:postcode":"01880",
    "addr:street":"Foundry St",
    "iso:country":"US",
    "sg:address":"153 Foundry St",
    "sg:city":"Wakefield",
    "sg:classifiers":[
        {
            "category":"Retail",
            "subcategory":"Auto Repair",
            "type":"Services"
        }
    ],
    "sg:phone":"+1 781 245 0649",
    "sg:postcode":"01880",
    "sg:province":"MA",
    "sg:tags":[
        "general"
    ],
    "wof:name":"Foundry Street Garage",
    "wof:placetype":"venue"
},
  "geometry": {"coordinates":[-71.074603,42.499759],"type":"Point"}
}