{
  "type": "Feature",
  "properties": {
    "addr:full":"7-13 Mortimer Pl Ste 7 Somerville MA 02145",
    "addr:housenumber":"7-13",
    "addr:postcode":"02145",
    "addr:street":"Mortimer Pl Ste 7",
    "iso:country":"US",
    "sg:address":"7-13 Mortimer Pl Ste 7",
    "sg:city":"Somerville",
    "sg:classifiers":[
        {
            "category":"Personal",
            "type":"Services"
        }
    ],
    "sg:phone":"+1 508 878 0657",
    "sg:postcode":"02145",
    "sg:province":"MA",
    "sg:tags":[
        "shopping"
    ],
    "sg:website":"www.upolished.com",
    "wof:name":"U, Polished! Image Consulting",
    "wof:placetype":"venue"
},
  "geometry": {"coordinates":[-71.093788,42.390396],"type":"Point"}
}