{
  "type": "Feature",
  "properties": {
    "addr:full":"1503 Pleasant St Fall River MA 02723",
    "addr:housenumber":"1503",
    "addr:postcode":"02723",
    "addr:street":"Pleasant St",
    "iso:country":"US",
    "sg:address":"1503 Pleasant St",
    "sg:city":"Fall River",
    "sg:classifiers":[
        {
            "category":"Shopping",
            "subcategory":"Jewelry",
            "type":"Retail Goods"
        }
    ],
    "sg:phone":"+1 508 672 7311",
    "sg:postcode":"02723",
    "sg:province":"MA",
    "sg:tags":[
        "jeweler"
    ],
    "wof:name":"Angelini Jewelers",
    "wof:placetype":"venue"
},
  "geometry": {"coordinates":[-71.13334999999999,41.689852],"type":"Point"}
}