{
  "type": "Feature",
  "properties": {
    "iso:country":"US",
    "sg:address":"39 Dodge St",
    "sg:city":"Beverly",
    "sg:classifiers":[
        {
            "category":"Shopping",
            "subcategory":"Computers & Home Electronics",
            "type":"Retail Goods"
        }
    ],
    "sg:phone":"+1 978 921 6320",
    "sg:postcode":"01915",
    "sg:province":"MA",
    "sg:tags":[
        "equipment",
        "dealer"
    ],
    "wof:name":"Peabody Computer Sales",
    "wof:placetype":"venue"
},
  "geometry": {"coordinates":[-70.89197,42.575036],"type":"Point"}
}