{
  "type": "Feature",
  "properties": {
    "addr:full": "238 Bridge St Northampton MA 01060",
    "addr:housenumber": "238",
    "addr:postcode": "01060",
    "addr:street": "Bridge St",
    "iso:country": "US",
    "sg:address": "238 Bridge St",
    "sg:city": "Northampton",
    "sg:classifiers": [
      {
        "category": "Personal",
        "subcategory": "Tanning Parlor",
        "type": "Services"
      }
    ],
    "sg:phone": "+1 413 584 2230",
    "sg:postcode": "01060",
    "sg:province": "MA",
    "sg:tags": [
      "salon"
    ],
    "wof:name": "Tan Quick",
    "wof:placetype": "venue"
  },
  "geometry": {"coordinates":[-72.624839,42.327789],"type":"Point"}
}
