{
  "type": "Feature",
  "properties": {
    "addr:full":"1 1st St Boston MA 02148",
    "addr:housenumber":"1",
    "addr:postcode":"02148",
    "addr:street":"1St St",
    "iso:country":"US",
    "sg:address":"1 1st St",
    "sg:city":"Boston",
    "sg:classifiers":[
        {
            "category":"Government",
            "subcategory":"Office",
            "type":"Public Place"
        }
    ],
    "sg:phone":"+1 617 956 1500",
    "sg:postcode":"02148",
    "sg:province":"MA",
    "sg:tags":[
        "state",
        "inspection"
    ],
    "wof:name":"Banks Division",
    "wof:placetype":"venue"
},
  "geometry": {"coordinates":[-71.032956,42.441002],"type":"Point"}
}