{
  "type": "Feature",
  "properties": {
    "addr:full":"4 Masconomet Rd Ipswich MA 01938",
    "addr:housenumber":"4",
    "addr:postcode":"01938",
    "addr:street":"Masconomet Rd",
    "iso:country":"US",
    "sg:address":"4 Masconomet Rd",
    "sg:city":"Ipswich",
    "sg:classifiers":[
        {
            "category":"Building & Trades",
            "subcategory":"Construction",
            "type":"Services"
        }
    ],
    "sg:phone":"+1   ",
    "sg:postcode":"01938",
    "sg:province":"MA",
    "sg:tags":[
        "house"
    ],
    "wof:name":"Charles D Hatch",
    "wof:placetype":"venue"
},
  "geometry": {"coordinates":[-70.842341,42.667316],"type":"Point"}
}