{
  "type": "Feature",
  "properties": {
    "iso:country":"US",
    "sg:address":"597 Centre St",
    "sg:city":"Jamaica Plain",
    "sg:classifiers":[
        {
            "category":"Restaurant",
            "type":"Food & Drink"
        }
    ],
    "sg:menulink":"http://www.allmenus.com/ma/boston/1356-ten-tables/menu/",
    "sg:phone":"+1 617 524 8810",
    "sg:postcode":"02130",
    "sg:province":"MA",
    "sg:tags":[
        "american"
    ],
    "wof:name":"Ten Tables",
    "wof:placetype":"venue"
},
  "geometry": {"coordinates":[-71.114098,42.314989],"type":"Point"}
}