{
  "type": "Feature",
  "properties": {
    "iso:country":"US",
    "sg:address":"43 Elm St",
    "sg:city":"Foxboro",
    "sg:classifiers":[
        {
            "category":"Building & Trades",
            "subcategory":"Electrical",
            "type":"Services"
        }
    ],
    "sg:phone":"+1 508 543 3085",
    "sg:postcode":"02035",
    "sg:province":"MA",
    "sg:tags":[
        "electric",
        "contractor"
    ],
    "wof:name":"Mc Carthy Electric",
    "wof:placetype":"venue"
},
  "geometry": {"coordinates":[-71.23560500000001,42.058457],"type":"Point"}
}