{
  "type": "Feature",
  "properties": {
    "addr:full":"120 Highland Ave Seekonk MA 02771",
    "addr:housenumber":"120",
    "addr:postcode":"02771",
    "addr:street":"Highland Ave",
    "iso:country":"US",
    "sg:address":"120 Highland Ave",
    "sg:city":"Seekonk",
    "sg:classifiers":[
        {
            "category":"Shopping",
            "subcategory":"Shoes",
            "type":"Retail Goods"
        }
    ],
    "sg:phone":"+1 508 336 6354",
    "sg:postcode":"02771",
    "sg:province":"MA",
    "wof:name":"Red Wing Shoe Store",
    "wof:placetype":"venue"
},
  "geometry": {"coordinates":[-71.332543,41.79788],"type":"Point"}
}