{
  "type": "Feature",
  "properties": {
    "addr:full":"9 Westminster Ave Arlington MA 02474",
    "addr:housenumber":"9",
    "addr:postcode":"02474",
    "addr:street":"Westminster Ave",
    "iso:country":"US",
    "sg:address":"9 Westminster Ave",
    "sg:city":"Arlington",
    "sg:classifiers":[
        {
            "category":"Place Of Worship",
            "subcategory":"Church",
            "type":"Public Place"
        },
        {
            "category":"Place Of Worship",
            "type":"Public Place"
        }
    ],
    "sg:phone":"+1 781 643 5511",
    "sg:postcode":"02474",
    "sg:province":"MA",
    "sg:tags":[
        "churches-evangelical",
        "churches-covenant",
        "covenant",
        "churches-non-denominational"
    ],
    "wof:name":"Covenant Church",
    "wof:placetype":"venue"
},
  "geometry": {"coordinates":[-71.181977,42.4261],"type":"Point"}
}