{
  "type": "Feature",
  "properties": {
    "iso:country":"US",
    "sg:address":"168 Washington St",
    "sg:city":"Stoughton",
    "sg:classifiers":[
        {
            "category":"Home & Garden",
            "subcategory":"Garden Supply",
            "type":"Retail Goods"
        }
    ],
    "sg:phone":"+1 781 344 0300",
    "sg:postcode":"02072",
    "sg:province":"MA",
    "sg:tags":[
        "nursery",
        "gardening"
    ],
    "wof:name":"AA Will Landscape Supply & Stone Center",
    "wof:placetype":"venue"
},
  "geometry": {"coordinates":[-71.102699,42.139099],"type":"Point"}
}