{
  "type": "Feature",
  "properties": {
    "addr:full": "248 Worcester Rd Princeton MA 01541",
    "addr:housenumber": "248",
    "addr:postcode": "01541",
    "addr:street": "Worcester Rd",
    "iso:country": "US",
    "sg:address": "248 Worcester Rd",
    "sg:city": "Princeton",
    "sg:classifiers": [
      {
        "category": "Building \u0026 Trades",
        "subcategory": "Landscaping Services",
        "type": "Services"
      }
    ],
    "sg:phone": "+1 978 464 0177",
    "sg:postcode": "01541",
    "sg:province": "MA",
    "sg:tags": [
      "tree"
    ],
    "wof:name": "Calcia Tree Svc",
    "wof:placetype": "venue"
  },
  "geometry": {"coordinates":[-71.877242,42.417154],"type":"Point"}
}
