{
  "type": "Feature",
  "properties": {
    "addr:full": "167 East St Methuen MA 01844",
    "addr:housenumber": "167",
    "addr:postcode": "01844",
    "addr:street": "East St",
    "iso:country": "US",
    "sg:address": "167 East St",
    "sg:city": "Methuen",
    "sg:classifiers": [
      {
        "category": "Shopping",
        "subcategory": "Gifts \u0026 Souvenirs",
        "type": "Retail Goods"
      }
    ],
    "sg:phone": "+1 978 688 8117",
    "sg:postcode": "01844",
    "sg:province": "MA",
    "sg:tags": [
      "basket",
      "parcel"
    ],
    "wof:name": "Edible Arrangements",
    "wof:placetype": "venue"
  },
  "geometry": {"coordinates":[-71.150752,42.726403],"type":"Point"}
}
