{
  "type": "Feature",
  "properties": {
    "addr:full":"105 Rosemont Rd Westwood MA 02090",
    "addr:housenumber":"105",
    "addr:postcode":"02090",
    "addr:street":"Rosemont Rd",
    "iso:country":"US",
    "sg:address":"105 Rosemont Rd",
    "sg:city":"Westwood",
    "sg:classifiers":[
        {
            "category":"Insurance",
            "subcategory":"Hazard Insurance",
            "type":"Services"
        }
    ],
    "sg:phone":"+1 781 302 6186",
    "sg:postcode":"02090",
    "sg:province":"MA",
    "sg:tags":[
        "commercial",
        "business"
    ],
    "wof:name":"J&J Employee Benefit Association Trust For Union",
    "wof:placetype":"venue"
},
  "geometry": {"coordinates":[-71.155843,42.208491],"type":"Point"}
}