{
  "type": "Feature",
  "properties": {
    "addr:full":"12 Clarendon St Boston MA 02116",
    "addr:housenumber":"12",
    "addr:postcode":"02116",
    "addr:street":"Clarendon St",
    "iso:country":"US",
    "sg:address":"12 Clarendon St",
    "sg:city":"Boston",
    "sg:classifiers":[
        {
            "category":"Health Services",
            "subcategory":"Health Practitioner",
            "type":"Services"
        }
    ],
    "sg:phone":"+1 617 733 6284",
    "sg:postcode":"02116",
    "sg:province":"MA",
    "sg:tags":[
        "acupuncture"
    ],
    "sg:website":"www.truebalanceacupuncture.com",
    "wof:name":"True Balance Acupuncture",
    "wof:placetype":"venue"
},
  "geometry": {"coordinates":[-71.07235,42.344679],"type":"Point"}
}