{
  "type": "Feature",
  "properties": {
    "iso:country":"US",
    "sg:address":"201 Center St",
    "sg:city":"Groveland",
    "sg:classifiers":[
        {
            "category":"Building & Trades",
            "subcategory":"Landscaping Services",
            "type":"Services"
        }
    ],
    "sg:phone":"+1 978 373 0079",
    "sg:postcode":"01834",
    "sg:province":"MA",
    "sg:tags":[
        "lawn",
        "maintenance",
        "grounds"
    ],
    "wof:name":"Maguire Landscaping",
    "wof:placetype":"venue"
},
  "geometry": {"coordinates":[-71.019525,42.74662],"type":"Point"}
}