{
  "type": "Feature",
  "properties": {
    "addr:full":"11 Vinal Street Revere MA 02151",
    "addr:housenumber":"11",
    "addr:postcode":"02151",
    "addr:street":"Vinal Street",
    "iso:country":"US",
    "sg:address":"11 Vinal Street",
    "sg:city":"Revere",
    "sg:classifiers":[
        {
            "category":"Sports & Exercise",
            "subcategory":"Gym",
            "type":"Entertainment"
        },
        {
            "category":"Health Services",
            "subcategory":"Dentist",
            "type":"Services"
        }
    ],
    "sg:phone":"+1 781 284 3113",
    "sg:postcode":"02151",
    "sg:province":"MA",
    "sg:tags":[
        "trainer",
        "dentists-pediatric",
        "dentistry"
    ],
    "wof:name":"Corey Leo P DDS",
    "wof:placetype":"venue"
},
  "geometry": {"coordinates":[-71.015309,42.405537],"type":"Point"}
}