{
  "type": "Feature",
  "properties": {
    "addr:full": "432 Columbia St Cambridge MA 02141",
    "addr:housenumber": "432",
    "addr:postcode": "02141",
    "addr:street": "Columbia St",
    "iso:country": "US",
    "sg:address": "432 Columbia St",
    "sg:city": "Cambridge",
    "sg:classifiers": [
      {
        "category": "Professional",
        "subcategory": "Printing \u0026 Photocopies",
        "type": "Services"
      }
    ],
    "sg:phone": "+1 617 621 0450",
    "sg:postcode": "02141",
    "sg:province": "MA",
    "sg:tags": [
      "duplicating",
      "copying"
    ],
    "sg:website": "www.quickphone.com",
    "wof:name": "Quickphone",
    "wof:placetype": "venue"
  },
  "geometry": {"coordinates":[-71.093878,42.373808],"type":"Point"}
}
