{
  "type": "Feature",
  "properties": {
    "iso:country":"US",
    "sg:address":"151 Coolidge Ave Apt 107",
    "sg:city":"Watertown",
    "sg:phone":"+1 617 924 5352",
    "sg:postcode":"02472",
    "sg:province":"MA",
    "wof:name":"Crystal Visions",
    "wof:placetype":"venue"
},
  "geometry": {"coordinates":[-71.147916,42.365425],"type":"Point"}
}