{
  "type": "Feature",
  "properties": {
    "iso:country":"US",
    "sg:address":"20 Aegean Dr",
    "sg:city":"Methuen",
    "sg:classifiers":[
        {
            "category":"Wholesale",
            "subcategory":"Apparel",
            "type":"Manufacturing & Wholesale Goods"
        }
    ],
    "sg:phone":"+1 978 687 3900",
    "sg:postcode":"01844",
    "sg:province":"MA",
    "sg:tags":[
        "embroidery"
    ],
    "wof:name":"Mainline Embroidery Works",
    "wof:placetype":"venue"
},
  "geometry": {"coordinates":[-71.214258,42.732106],"type":"Point"}
}