{
  "type": "Feature",
  "properties": {
    "iso:country":"US",
    "sg:address":"166 Forbes Rd",
    "sg:city":"Braintree",
    "sg:classifiers":[
        {
            "category":"Insurance",
            "subcategory":"Insurance Agent",
            "type":"Services"
        }
    ],
    "sg:phone":"+1 781 848 1257",
    "sg:postcode":"02184",
    "sg:province":"MA",
    "wof:name":"Wolpert Insurance Agency Inc",
    "wof:placetype":"venue"
},
  "geometry": {"coordinates":[-71.03300299999999,42.220671],"type":"Point"}
}