{
  "type": "Feature",
  "properties": {
    "addr:full":"50 Commercial St Adams MA 01220",
    "addr:housenumber":"50",
    "addr:postcode":"01220",
    "addr:street":"Commercial St",
    "iso:country":"US",
    "sg:address":"50 Commercial St",
    "sg:city":"Adams",
    "sg:classifiers":[
        {
            "category":"Retail",
            "subcategory":"Auto Repair",
            "type":"Services"
        }
    ],
    "sg:phone":"+1 413 743 2225",
    "sg:postcode":"01220",
    "sg:province":"MA",
    "sg:tags":[
        "body"
    ],
    "wof:name":"Duteau Collision",
    "wof:placetype":"venue"
},
  "geometry": {"coordinates":[-73.122497,42.616589],"type":"Point"}
}