{
  "type": "Feature",
  "properties": {
    "addr:full": "380 Union St West Springfield MA 01089",
    "addr:housenumber": "380",
    "addr:postcode": "01089",
    "addr:street": "Union St",
    "iso:country": "US",
    "sg:address": "380 Union St",
    "sg:city": "West Springfield",
    "sg:classifiers": [
      {
        "category": "Building \u0026 Trades",
        "subcategory": "Construction",
        "type": "Services"
      }
    ],
    "sg:phone": "+1 413 785 5333",
    "sg:postcode": "01089",
    "sg:province": "MA",
    "sg:tags": [
      "roofing",
      "contractor"
    ],
    "wof:name": "Martin Roofing Co",
    "wof:placetype": "venue"
  },
  "geometry": {"coordinates":[-72.61546,42.101684],"type":"Point"}
}
