{
  "type": "Feature",
  "properties": {
    "addr:full": "40 School St Westfield MA 01085",
    "addr:housenumber": "40",
    "addr:postcode": "01085",
    "addr:street": "School St",
    "iso:country": "US",
    "sg:address": "40 School St",
    "sg:city": "Westfield",
    "sg:classifiers": [
      {
        "category": "Professional",
        "subcategory": "Engineering",
        "type": "Services"
      }
    ],
    "sg:phone": "+1 413 562 7566",
    "sg:postcode": "01085",
    "sg:province": "MA",
    "sg:tags": [
      "engineer"
    ],
    "wof:name": "D L Bean Inc",
    "wof:placetype": "venue"
  },
  "geometry": {"coordinates":[-72.752045,42.12185],"type":"Point"}
}
