{
  "type": "Feature",
  "properties": {
    "addr:full": "95 E Cottage St Dorchester MA 02125",
    "addr:housenumber": "95 e",
    "addr:postcode": "02125",
    "addr:street": "Cottage St",
    "iso:country": "US",
    "sg:address": "95 E Cottage St",
    "sg:city": "Dorchester",
    "sg:classifiers": [
      {
        "category": "Wholesale",
        "subcategory": "Groceries",
        "type": "Manufacturing \u0026 Wholesale Goods"
      }
    ],
    "sg:phone": "+1 617 287 9696",
    "sg:postcode": "02125",
    "sg:province": "MA",
    "sg:tags": [
      "grocer"
    ],
    "wof:name": "United Foods Inc",
    "wof:placetype": "venue"
  },
  "geometry": {"coordinates":[-71.065558,42.321207],"type":"Point"}
}
