{
  "type": "Feature",
  "properties": {
    "addr:full": "35 Squire Rd Revere MA 02151",
    "addr:housenumber": "35",
    "addr:postcode": "02151",
    "addr:street": "Squire Rd",
    "iso:country": "US",
    "sg:address": "35 Squire Rd",
    "sg:city": "Revere",
    "sg:classifiers": [
      {
        "category": "Building \u0026 Trades",
        "subcategory": "Locksmith",
        "type": "Services"
      }
    ],
    "sg:phone": "+1 617 517 0686",
    "sg:postcode": "02151",
    "sg:province": "MA",
    "sg:tags": [
      "key"
    ],
    "wof:name": "A 24 Locksmith",
    "wof:placetype": "venue"
  },
  "geometry": {"coordinates":[-71.005996,42.422026],"type":"Point"}
}
