{
  "type": "Feature",
  "properties": {
    "iso:country":"US",
    "sg:address":"618 Lincoln St",
    "sg:city":"Worcester",
    "sg:classifiers":[
        {
            "category":"Retail",
            "subcategory":"Auto Repair",
            "type":"Services"
        }
    ],
    "sg:phone":"+1 508 853 9900",
    "sg:postcode":"01605",
    "sg:province":"MA",
    "sg:tags":[
        "repairing",
        "automobile"
    ],
    "wof:name":"Clearview Auto",
    "wof:placetype":"venue"
},
  "geometry": {"coordinates":[-71.76977599999999,42.296275],"type":"Point"}
}