{
  "type": "Feature",
  "properties": {
    "addr:full": "618 Lincoln St Worcester MA 01605",
    "addr:housenumber": "618",
    "addr:postcode": "01605",
    "addr:street": "Lincoln St",
    "iso:country": "US",
    "ovtr:label": "Clearview Auto, 618 Lincoln St Worcester MA US",
    "ovtr:similarity": 2.2707090377807617,
    "sg:address": "618 Lincoln St",
    "sg:city": "Worcester",
    "sg:classifiers": [
      {
        "category": "Retail",
        "subcategory": "Auto Repair",
        "type": "Services"
      }
    ],
    "sg:phone": "+1 508 853 9900",
    "sg:postcode": "01605",
    "sg:province": "MA",
    "sg:tags": [
      "repairing",
      "automobile"
    ],
    "wof:name": "Clearview Auto",
    "wof:placetype": "venue"
  },
  "geometry": {"coordinates":[-71.769776,42.296275],"type":"Point"}
}
