{
  "type": "Feature",
  "properties": {
    "addr:full":"170 Revere Beach Pkwy Chelsea MA 02150",
    "addr:housenumber":"170",
    "addr:postcode":"02150",
    "addr:street":"Revere Beach Pkwy",
    "iso:country":"US",
    "sg:address":"170 Revere Beach Pkwy",
    "sg:city":"Chelsea",
    "sg:classifiers":[
        {
            "category":"Building & Trades",
            "subcategory":"Locksmith",
            "type":"Services"
        }
    ],
    "sg:phone":"+1 617 517 9032",
    "sg:postcode":"02150",
    "sg:province":"MA",
    "sg:tags":[
        "key"
    ],
    "wof:name":"Emergency A Locksmith",
    "wof:placetype":"venue"
},
  "geometry": {"coordinates":[-71.035894,42.403996],"type":"Point"}
}