{
  "type": "Feature",
  "properties": {
    "addr:full": "629 Beach Street Revere MA 02151",
    "addr:housenumber": "629",
    "addr:postcode": "02151",
    "addr:street": "Beach Street",
    "iso:country": "US",
    "sg:address": "629 Beach Street",
    "sg:city": "Revere",
    "sg:classifiers": [
      {
        "category": "Personal",
        "subcategory": "Barber",
        "type": "Services"
      }
    ],
    "sg:phone": "+1 781 286 9135",
    "sg:postcode": "02151",
    "sg:province": "MA",
    "wof:name": "Nelphy's Haircuts",
    "wof:placetype": "venue"
  },
  "geometry": {"coordinates":[-70.994694,42.408776],"type":"Point"}
}
