{
  "type": "Feature",
  "properties": {
    "addr:full":"17 Athol St Acushnet MA 02743",
    "addr:housenumber":"17",
    "addr:postcode":"02743",
    "addr:street":"Athol St",
    "iso:country":"US",
    "sg:address":"17 Athol St",
    "sg:city":"Acushnet",
    "sg:classifiers":[
        {
            "category":"Farming",
            "subcategory":"Farm",
            "type":"Manufacturing & Wholesale Goods"
        }
    ],
    "sg:phone":"+1 508 763 5178",
    "sg:postcode":"02743",
    "sg:province":"MA",
    "wof:name":"Rounsevell Curtis",
    "wof:placetype":"venue"
},
  "geometry": {"coordinates":[-70.91082299999999,41.740674],"type":"Point"}
}