{
  "type": "Feature",
  "properties": {
    "iso:country":"US",
    "sg:address":"179 William St",
    "sg:city":"New Bedford",
    "sg:classifiers":[
        {
            "category":"Professional",
            "subcategory":"Lawyer & Legal Services",
            "type":"Services"
        }
    ],
    "sg:phone":"+1 508 999 2930",
    "sg:postcode":"02740",
    "sg:province":"MA",
    "sg:tags":[
        "attorney"
    ],
    "wof:name":"Barry Hodge",
    "wof:placetype":"venue"
},
  "geometry": {"coordinates":[-70.92833,41.63522],"type":"Point"}
}