{
  "type": "Feature",
  "properties": {
    "addr:full": "8 Sunnyside Ave Everett MA 02149",
    "addr:housenumber": "8",
    "addr:postcode": "02149",
    "addr:street": "Sunnyside Ave",
    "iso:country": "US",
    "sg:address": "8 Sunnyside Ave",
    "sg:city": "Everett",
    "sg:classifiers": [
      {
        "category": "Building \u0026 Trades",
        "subcategory": "Construction",
        "type": "Services"
      }
    ],
    "sg:phone": "+1   ",
    "sg:postcode": "02149",
    "sg:province": "MA",
    "sg:tags": [
      "house"
    ],
    "wof:name": "Gd Construction Co",
    "wof:placetype": "venue"
  },
  "geometry": {"coordinates":[-71.042214,42.40828],"type":"Point"}
}
