{
  "type": "Feature",
  "properties": {
    "addr:full": "59 Center St Brockton MA 02367",
    "addr:housenumber": "59",
    "addr:postcode": "02367",
    "addr:street": "Center St",
    "iso:country": "US",
    "sg:address": "59 Center St",
    "sg:city": "Brockton",
    "sg:classifiers": [
      {
        "category": "Home \u0026 Garden",
        "subcategory": "Furniture",
        "type": "Retail Goods"
      }
    ],
    "sg:phone": "+1 508 586 3434",
    "sg:postcode": "02367",
    "sg:province": "MA",
    "sg:website": "www.wbmason.com",
    "wof:name": "W B Mason Co",
    "wof:placetype": "venue"
  },
  "geometry": {"coordinates":[-70.820439,41.963163],"type":"Point"}
}
