{
  "type": "Feature",
  "properties": {
    "iso:country":"US",
    "sg:address":"59 Center St",
    "sg:city":"Brockton",
    "sg:classifiers":[
        {
            "category":"Home & Garden",
            "subcategory":"Furniture",
            "type":"Retail Goods"
        }
    ],
    "sg:phone":"+1 508 586 3434",
    "sg:postcode":"02367",
    "sg:province":"MA",
    "sg:website":"www.wbmason.com",
    "wof:name":"W B Mason Co",
    "wof:placetype":"venue"
},
  "geometry": {"coordinates":[-70.82043899999999,41.963163],"type":"Point"}
}