{
  "type": "Feature",
  "properties": {
    "iso:country":"US",
    "sg:address":"10 Old Mine Rock Way",
    "sg:city":"Hingham",
    "sg:classifiers":[
        {
            "category":"Manufacturing",
            "subcategory":"Tools & Machinery",
            "type":"Manufacturing & Wholesale Goods"
        }
    ],
    "sg:phone":"+1 781 829 9228",
    "sg:postcode":"02043",
    "sg:province":"MA",
    "sg:tags":[
        "control"
    ],
    "sg:website":"www.acsmotion.com",
    "wof:name":"Advanced Control Systems",
    "wof:placetype":"venue"
},
  "geometry": {"coordinates":[-70.91889500000001,42.174023],"type":"Point"}
}