{
  "type": "Feature",
  "properties": {
    "iso:country":"US",
    "sg:address":"144 River Rd",
    "sg:city":"New Bedford",
    "sg:classifiers":[
        {
            "category":"Manufacturing",
            "subcategory":"Tools & Machinery",
            "type":"Manufacturing & Wholesale Goods"
        }
    ],
    "sg:phone":"+1 508 998 3417",
    "sg:postcode":"02745",
    "sg:province":"MA",
    "sg:tags":[
        "machine",
        "shop"
    ],
    "wof:name":"S K Machine Co Inc",
    "wof:placetype":"venue"
},
  "geometry": {"coordinates":[-70.917998,41.677593],"type":"Point"}
}