{
  "type": "Feature",
  "properties": {
    "addr:full": "144 River Rd New Bedford MA 02745",
    "addr:housenumber": "144",
    "addr:postcode": "02745",
    "addr:street": "River Rd",
    "iso:country": "US",
    "sg:address": "144 River Rd",
    "sg:city": "New Bedford",
    "sg:classifiers": [
      {
        "category": "Manufacturing",
        "subcategory": "Tools \u0026 Machinery",
        "type": "Manufacturing \u0026 Wholesale Goods"
      }
    ],
    "sg:phone": "+1 508 998 3417",
    "sg:postcode": "02745",
    "sg:province": "MA",
    "sg:tags": [
      "machine",
      "shop"
    ],
    "wof:name": "S K Machine Co Inc",
    "wof:placetype": "venue"
  },
  "geometry": {"coordinates":[-70.917998,41.677593],"type":"Point"}
}
