{
  "type": "Feature",
  "properties": {
    "iso:country":"US",
    "sg:address":"195 Hamilton Ave",
    "sg:city":"Lynn",
    "sg:classifiers":[
        {
            "category":"Retail",
            "subcategory":"Repair Shop",
            "type":"Services"
        }
    ],
    "sg:phone":"+1 978 744 7979",
    "sg:postcode":"01902",
    "sg:province":"MA",
    "sg:tags":[
        "typewriter"
    ],
    "wof:name":"One Call Office Machine Svc",
    "wof:placetype":"venue"
},
  "geometry": {"coordinates":[-70.94662,42.47206],"type":"Point"}
}