{
  "type": "Feature",
  "properties": {
    "addr:full": "44 Allen Cir Milton MA 02186",
    "addr:housenumber": "44",
    "addr:postcode": "02186",
    "addr:street": "Allen Cir",
    "iso:country": "US",
    "sg:address": "44 Allen Cir",
    "sg:city": "Milton",
    "sg:classifiers": [
      {
        "category": "Professional",
        "type": "Services"
      }
    ],
    "sg:phone": "+1   ",
    "sg:postcode": "02186",
    "sg:province": "MA",
    "wof:name": "Suzanne Saskel",
    "wof:placetype": "venue"
  },
  "geometry": {"coordinates":[-71.08488,42.26704],"type":"Point"}
}
