{
  "type": "Feature",
  "properties": {
    "addr:full": "262 Main St Hingham MA 02043",
    "addr:housenumber": "262",
    "addr:postcode": "02043",
    "addr:street": "Main St",
    "iso:country": "US",
    "sg:address": "262 Main St",
    "sg:city": "Hingham",
    "sg:classifiers": [
      {
        "category": "Real Estate",
        "subcategory": "Real Estate Services",
        "type": "Services"
      }
    ],
    "sg:phone": "+1 781 749 0151",
    "sg:postcode": "02043",
    "sg:province": "MA",
    "sg:tags": [
      "buyer",
      "broker"
    ],
    "wof:name": "Meadow View Partners",
    "wof:placetype": "venue"
  },
  "geometry": {"coordinates":[-70.881114,42.234133],"type":"Point"}
}
