{
  "type": "Feature",
  "properties": {
    "iso:country":"US",
    "sg:address":"262 Main St",
    "sg:city":"Hingham",
    "sg:classifiers":[
        {
            "category":"Real Estate",
            "subcategory":"Real Estate Services",
            "type":"Services"
        }
    ],
    "sg:phone":"+1 781 749 0151",
    "sg:postcode":"02043",
    "sg:province":"MA",
    "sg:tags":[
        "buyer",
        "broker"
    ],
    "wof:name":"Meadow View Partners",
    "wof:placetype":"venue"
},
  "geometry": {"coordinates":[-70.881114,42.234133],"type":"Point"}
}