{
  "type": "Feature",
  "properties": {
    "addr:full":"129 Knower Rd Westminster MA 01473",
    "addr:housenumber":"129",
    "addr:postcode":"01473",
    "addr:street":"Knower Rd",
    "iso:country":"US",
    "sg:address":"129 Knower Rd",
    "sg:city":"Westminster",
    "sg:classifiers":[
        {
            "category":"Manufacturing",
            "subcategory":"Building Materials",
            "type":"Manufacturing & Wholesale Goods"
        }
    ],
    "sg:phone":"+1 978 874 0810",
    "sg:postcode":"01473",
    "sg:province":"MA",
    "wof:name":"P Young Woodworking Co",
    "wof:placetype":"venue"
},
  "geometry": {"coordinates":[-71.927289,42.536015],"type":"Point"}
}