{
  "type": "Feature",
  "properties": {
    "addr:full":"92 Main St Florence MA 01062",
    "addr:housenumber":"92",
    "addr:postcode":"01062",
    "addr:street":"Main St",
    "iso:country":"US",
    "sg:address":"92 Main St",
    "sg:city":"Florence",
    "sg:classifiers":[
        {
            "category":"Real Estate",
            "subcategory":"Real Estate Agent",
            "type":"Services"
        }
    ],
    "sg:phone":"+1 413 586 8355",
    "sg:postcode":"01062",
    "sg:province":"MA",
    "sg:website":"www.upton-massamont.com",
    "wof:name":"Upton Massamont Realtors",
    "wof:placetype":"venue"
},
  "geometry": {"coordinates":[-72.67194600000001,42.335439],"type":"Point"}
}