{
  "type": "Feature",
  "properties": {
    "addr:full": "1041 Cascade St Pittsfield MA 01201",
    "addr:housenumber": "1041",
    "addr:postcode": "01201",
    "addr:street": "Cascade St",
    "iso:country": "US",
    "sg:address": "1041 Cascade St",
    "sg:city": "Pittsfield",
    "sg:classifiers": [
      {
        "category": "Government",
        "subcategory": "Office",
        "type": "Public Place"
      }
    ],
    "sg:phone": "+1 413 442 8992",
    "sg:postcode": "01201",
    "sg:province": "MA",
    "sg:tags": [
      "state",
      "forest"
    ],
    "wof:name": "Pittsfield State Forest",
    "wof:placetype": "venue"
  },
  "geometry": {"coordinates":[-73.295262,42.479836],"type":"Point"}
}
