{
  "type": "Feature",
  "properties": {
    "addr:full":"145 Meridian Street Boston MA 02128",
    "addr:housenumber":"145",
    "addr:postcode":"02128",
    "addr:street":"Meridian Street",
    "iso:country":"US",
    "sg:address":"145 Meridian Street",
    "sg:city":"Boston",
    "sg:classifiers":[
        {
            "category":"Food & Beverages",
            "subcategory":"Groceries & Convenience Stores",
            "type":"Retail Goods"
        }
    ],
    "sg:phone":"+1 617 567 8529",
    "sg:postcode":"02128",
    "sg:province":"MA",
    "wof:name":"Beni S Restaurant",
    "wof:placetype":"venue"
},
  "geometry": {"coordinates":[-71.03921099999999,42.373517],"type":"Point"}
}