{
  "type": "Feature",
  "properties": {
    "addr:full": "19 Belmont Street Cambridge MA 02138",
    "addr:housenumber": "19",
    "addr:postcode": "02138",
    "addr:street": "Belmont Street",
    "iso:country": "US",
    "sg:address": "19 Belmont Street",
    "sg:city": "Cambridge",
    "sg:classifiers": [
      {
        "category": "Sports \u0026 Exercise",
        "subcategory": "Gym",
        "type": "Entertainment"
      },
      {
        "category": "Health Services",
        "subcategory": "Health Practitioner",
        "type": "Services"
      }
    ],
    "sg:phone": "+1 617 868 3257",
    "sg:postcode": "02138",
    "sg:province": "MA",
    "sg:tags": [
      "acupuncture",
      "trainer"
    ],
    "wof:name": "Jackowicz Oriental Medical Therapy Associates",
    "wof:placetype": "venue"
  },
  "geometry": {"coordinates":[-71.150839,42.374691],"type":"Point"}
}
