{
  "type": "Feature",
  "properties": {
    "addr:full":"374 Chelmsford St Lowell MA 01851",
    "addr:housenumber":"374",
    "addr:postcode":"01851",
    "addr:street":"Chelmsford St",
    "iso:country":"US",
    "sg:address":"374 Chelmsford St",
    "sg:city":"Lowell",
    "sg:classifiers":[
        {
            "category":"Restaurant",
            "type":"Food & Drink"
        }
    ],
    "sg:menulink":"http://www.allmenus.com/ma/lowell/84529-dominos-pizza/menu/",
    "sg:phone":"+1 978 441 1000",
    "sg:postcode":"01851",
    "sg:province":"MA",
    "sg:tags":[
        "american",
        "wing",
        "pizza"
    ],
    "wof:name":"Domino's Pizza",
    "wof:placetype":"venue"
},
  "geometry": {"coordinates":[-71.321372,42.629864],"type":"Point"}
}