{
  "type": "Feature",
  "properties": {
    "addr:full":"282 Winthrop St Medford MA 02155",
    "addr:housenumber":"282",
    "addr:postcode":"02155",
    "addr:street":"Winthrop St",
    "iso:country":"US",
    "sg:address":"282 Winthrop St",
    "sg:city":"Medford",
    "sg:classifiers":[
        {
            "category":"Health Services",
            "subcategory":"Doctor",
            "type":"Services"
        }
    ],
    "sg:phone":"+1 781 396 3770",
    "sg:postcode":"02155",
    "sg:province":"MA",
    "sg:tags":[
        "dermatologist"
    ],
    "wof:name":"Brown Richard K Dr",
    "wof:placetype":"venue"
},
  "geometry": {"coordinates":[-71.118129,42.420595],"type":"Point"}
}