{
  "type": "Feature",
  "properties": {
    "iso:country":"US",
    "sg:address":"524 State Hwy 6 Alt",
    "sg:city":"Dennis",
    "sg:classifiers":[
        {
            "category":"Manufacturing",
            "subcategory":"Printing",
            "type":"Manufacturing & Wholesale Goods"
        }
    ],
    "sg:phone":"+1 508 385 3434",
    "sg:postcode":"02638",
    "sg:province":"MA",
    "sg:tags":[
        "screen"
    ],
    "wof:name":"David Grose Studio",
    "wof:placetype":"venue"
},
  "geometry": {"coordinates":[-70.194705,41.73256],"type":"Point"}
}