{
  "type": "Feature",
  "properties": {
    "addr:full": "524 State Hwy 6 Alt Dennis MA 02638",
    "addr:housenumber": "524",
    "addr:postcode": "02638",
    "addr:street": "State Hwy 6",
    "iso:country": "US",
    "sg:address": "524 State Hwy 6 Alt",
    "sg:city": "Dennis",
    "sg:classifiers": [
      {
        "category": "Manufacturing",
        "subcategory": "Printing",
        "type": "Manufacturing \u0026 Wholesale Goods"
      }
    ],
    "sg:phone": "+1 508 385 3434",
    "sg:postcode": "02638",
    "sg:province": "MA",
    "sg:tags": [
      "screen"
    ],
    "wof:name": "David Grose Studio",
    "wof:placetype": "venue"
  },
  "geometry": {"coordinates":[-70.194705,41.73256],"type":"Point"}
}
