{
  "type": "Feature",
  "properties": {
    "iso:country":"US",
    "sg:address":"102 Oakdale Rd",
    "sg:city":"Newton",
    "sg:classifiers":[
        {
            "category":"Professional",
            "subcategory":"Management & Consulting",
            "type":"Services"
        }
    ],
    "sg:phone":"+1 617 964 6464",
    "sg:postcode":"02461",
    "sg:province":"MA",
    "sg:tags":[
        "marketing",
        "program"
    ],
    "wof:name":"Graphics Marketing Svc",
    "wof:placetype":"venue"
},
  "geometry": {"coordinates":[-71.197282,42.318278],"type":"Point"}
}