{
  "type": "Feature",
  "properties": {
    "iso:country":"US",
    "sg:address":"66 Allen St",
    "sg:city":"Pittsfield",
    "sg:classifiers":[
        {
            "category":"Banks & Credit Unions",
            "subcategory":"Bank",
            "type":"Services"
        }
    ],
    "sg:phone":"+1 413 236 3290",
    "sg:postcode":"01201",
    "sg:province":"MA",
    "sg:website":"www.berkshirebank.com",
    "wof:name":"Berkshire Bank",
    "wof:placetype":"venue"
},
  "geometry": {"coordinates":[-73.25223699999999,42.45],"type":"Point"}
}