{
  "type": "Feature",
  "properties": {
    "addr:full": "66 Allen St Pittsfield MA 01201",
    "addr:housenumber": "66",
    "addr:postcode": "01201",
    "addr:street": "Allen St",
    "iso:country": "US",
    "sg:address": "66 Allen St",
    "sg:city": "Pittsfield",
    "sg:classifiers": [
      {
        "category": "Banks \u0026 Credit Unions",
        "subcategory": "Bank",
        "type": "Services"
      }
    ],
    "sg:phone": "+1 413 236 3290",
    "sg:postcode": "01201",
    "sg:province": "MA",
    "sg:website": "www.berkshirebank.com",
    "wof:name": "Berkshire Bank",
    "wof:placetype": "venue"
  },
  "geometry": {"coordinates":[-73.252237,42.45],"type":"Point"}
}
