{
  "type": "Feature",
  "properties": {
    "addr:full":"210 Boston Rd Billerica MA 01821",
    "addr:housenumber":"210",
    "addr:postcode":"01821",
    "addr:street":"Boston Rd",
    "iso:country":"US",
    "sg:address":"210 Boston Rd",
    "sg:city":"Billerica",
    "sg:classifiers":[
        {
            "category":"Shopping",
            "subcategory":"Pharmacy",
            "type":"Retail Goods"
        }
    ],
    "sg:phone":"+1 978 663 6616",
    "sg:postcode":"01821",
    "sg:province":"MA",
    "sg:tags":[
        "drugstore"
    ],
    "wof:name":"Cvs Pharmacy",
    "wof:placetype":"venue"
},
  "geometry": {"coordinates":[-71.252197,42.551701],"type":"Point"}
}