{
  "type": "Feature",
  "properties": {
    "addr:full": "10 Central St Topsfield MA 01983",
    "addr:housenumber": "10",
    "addr:postcode": "01983",
    "addr:street": "Central St",
    "iso:country": "US",
    "sg:address": "10 Central St",
    "sg:city": "Topsfield",
    "sg:classifiers": [
      {
        "category": "Real Estate",
        "subcategory": "Architect",
        "type": "Services"
      }
    ],
    "sg:phone": "+1 978 887 5544",
    "sg:postcode": "01983",
    "sg:province": "MA",
    "sg:tags": [
      "designer",
      "architectural"
    ],
    "wof:name": "Ippolito Design Associates",
    "wof:placetype": "venue"
  },
  "geometry": {"coordinates":[-70.950415,42.638475],"type":"Point"}
}
