{
  "type": "Feature",
  "properties": {
    "iso:country":"US",
    "sg:address":"10 Central St",
    "sg:city":"Topsfield",
    "sg:classifiers":[
        {
            "category":"Real Estate",
            "subcategory":"Architect",
            "type":"Services"
        }
    ],
    "sg:phone":"+1 978 887 5544",
    "sg:postcode":"01983",
    "sg:province":"MA",
    "sg:tags":[
        "designer",
        "architectural"
    ],
    "wof:name":"Ippolito Design Associates",
    "wof:placetype":"venue"
},
  "geometry": {"coordinates":[-70.95041500000001,42.638475],"type":"Point"}
}