{
  "type": "Feature",
  "properties": {
    "addr:full": "23 Wayside Rd Westborough MA 01581",
    "addr:housenumber": "23",
    "addr:postcode": "01581",
    "addr:street": "Wayside Rd",
    "iso:country": "US",
    "sg:address": "23 Wayside Rd",
    "sg:city": "Westborough",
    "sg:classifiers": [
      {
        "category": "Banks \u0026 Credit Unions",
        "subcategory": "Bank",
        "type": "Services"
      }
    ],
    "sg:phone": "+1   ",
    "sg:postcode": "01581",
    "sg:province": "MA",
    "sg:tags": [
      "food",
      "mortgage"
    ],
    "wof:name": "All Pro Solutions",
    "wof:placetype": "venue"
  },
  "geometry": {"coordinates":[-71.623934,42.243516],"type":"Point"}
}
