{
  "type": "Feature",
  "properties": {
    "iso:country":"US",
    "sg:address":"23 Wayside Rd",
    "sg:city":"Westborough",
    "sg:classifiers":[
        {
            "category":"Banks & Credit Unions",
            "subcategory":"Bank",
            "type":"Services"
        }
    ],
    "sg:phone":"+1   ",
    "sg:postcode":"01581",
    "sg:province":"MA",
    "sg:tags":[
        "food",
        "mortgage"
    ],
    "wof:name":"All Pro Solutions",
    "wof:placetype":"venue"
},
  "geometry": {"coordinates":[-71.62393400000001,42.243516],"type":"Point"}
}