{
  "type": "Feature",
  "properties": {
    "addr:full":"27 Frederick St Belmont MA 02478",
    "addr:housenumber":"27",
    "addr:postcode":"02478",
    "addr:street":"Frederick St",
    "iso:country":"US",
    "sg:address":"27 Frederick St",
    "sg:city":"Belmont",
    "sg:classifiers":[
        {
            "category":"Building & Trades",
            "subcategory":"Construction",
            "type":"Services"
        }
    ],
    "sg:phone":"+1   ",
    "sg:postcode":"02478",
    "sg:province":"MA",
    "sg:tags":[
        "contractor"
    ],
    "wof:name":"Daman Building & Contg LLC",
    "wof:placetype":"venue"
},
  "geometry": {"coordinates":[-71.18444,42.380828],"type":"Point"}
}