{
  "type": "Feature",
  "properties": {
    "addr:full": "39 Felton St Waltham MA 02453",
    "addr:housenumber": "39",
    "addr:postcode": "02453",
    "addr:street": "Felton St",
    "iso:country": "US",
    "sg:address": "39 Felton St",
    "sg:city": "Waltham",
    "sg:classifiers": [
      {
        "category": "Retail",
        "subcategory": "Auto Repair",
        "type": "Services"
      }
    ],
    "sg:phone": "+1 781 647 3279",
    "sg:postcode": "02453",
    "sg:province": "MA",
    "sg:tags": [
      "repairing",
      "automobile"
    ],
    "wof:name": "JMH Automotive Repair",
    "wof:placetype": "venue"
  },
  "geometry": {"coordinates":[-71.238617,42.374245],"type":"Point"}
}
