{
  "type": "Feature",
  "properties": {
    "iso:country":"US",
    "sg:address":"39 Felton St",
    "sg:city":"Waltham",
    "sg:classifiers":[
        {
            "category":"Retail",
            "subcategory":"Auto Repair",
            "type":"Services"
        }
    ],
    "sg:phone":"+1 781 647 3279",
    "sg:postcode":"02453",
    "sg:province":"MA",
    "sg:tags":[
        "repairing",
        "automobile"
    ],
    "wof:name":"JMH Automotive Repair",
    "wof:placetype":"venue"
},
  "geometry": {"coordinates":[-71.238617,42.374245],"type":"Point"}
}