{
  "type": "Feature",
  "properties": {
    "addr:full": "222 Third St. Suite 0350 Cambridge MA 02142",
    "addr:housenumber": "222",
    "addr:postcode": "02142",
    "addr:street": "Third St. Suite 0350",
    "iso:country": "US",
    "sg:address": "222 Third St. Suite 0350",
    "sg:city": "Cambridge",
    "sg:classifiers": [
      {
        "category": "Professional",
        "subcategory": "Employment Agencies",
        "type": "Services"
      }
    ],
    "sg:phone": "+1 617 252 0606",
    "sg:postcode": "02142",
    "sg:province": "MA",
    "sg:website": "www.hireminds.com",
    "wof:name": "HireMinds, LLC",
    "wof:placetype": "venue"
  },
  "geometry": {"coordinates":[-71.081447,42.367287],"type":"Point"}
}
