{
  "type": "Feature",
  "properties": {
    "iso:country":"US",
    "sg:address":"222 Third St. Suite 0350",
    "sg:city":"Cambridge",
    "sg:classifiers":[
        {
            "category":"Professional",
            "subcategory":"Employment Agencies",
            "type":"Services"
        }
    ],
    "sg:phone":"+1 617 252 0606",
    "sg:postcode":"02142",
    "sg:province":"MA",
    "sg:website":"www.hireminds.com",
    "wof:name":"HireMinds, LLC",
    "wof:placetype":"venue"
},
  "geometry": {"coordinates":[-71.081447,42.367287],"type":"Point"}
}