{
  "type": "Feature",
  "properties": {
    "addr:full": "189 Upland Rd Cambridge MA 02140",
    "addr:housenumber": "189",
    "addr:postcode": "02140",
    "addr:street": "Upland Rd",
    "iso:country": "US",
    "sg:address": "189 Upland Rd",
    "sg:city": "Cambridge",
    "sg:classifiers": [
      {
        "category": "Professional",
        "subcategory": "Engineering",
        "type": "Services"
      }
    ],
    "sg:phone": "+1 617 661 6110",
    "sg:postcode": "02140",
    "sg:province": "MA",
    "sg:tags": [
      "engineer"
    ],
    "wof:name": "Ariano Technologies Inc",
    "wof:placetype": "venue"
  },
  "geometry": {"coordinates":[-71.12665,42.386566],"type":"Point"}
}
