{
  "type": "Feature",
  "properties": {
    "addr:full": "90 Summer St Franklin MA 02038",
    "addr:housenumber": "90",
    "addr:postcode": "02038",
    "addr:street": "Summer St",
    "iso:country": "US",
    "sg:address": "90 Summer St",
    "sg:city": "Franklin",
    "sg:classifiers": [
      {
        "category": "Building \u0026 Trades",
        "subcategory": "Construction",
        "type": "Services"
      }
    ],
    "sg:phone": "+1 508 528 1741",
    "sg:postcode": "02038",
    "sg:province": "MA",
    "sg:tags": [
      "boring",
      "drilling",
      "contractor"
    ],
    "wof:name": "W S Wyllie",
    "wof:placetype": "venue"
  },
  "geometry": {"coordinates":[-71.394275,42.080009],"type":"Point"}
}
