{
  "type": "Feature",
  "properties": {
    "iso:country":"US",
    "sg:address":"90 Summer St",
    "sg:city":"Franklin",
    "sg:classifiers":[
        {
            "category":"Building & Trades",
            "subcategory":"Construction",
            "type":"Services"
        }
    ],
    "sg:phone":"+1 508 528 1741",
    "sg:postcode":"02038",
    "sg:province":"MA",
    "sg:tags":[
        "boring",
        "drilling",
        "contractor"
    ],
    "wof:name":"W S Wyllie",
    "wof:placetype":"venue"
},
  "geometry": {"coordinates":[-71.39427499999999,42.080009],"type":"Point"}
}