{
  "type": "Feature",
  "properties": {
    "addr:full": "100 Terminal St Boston MA 02129",
    "addr:housenumber": "100",
    "addr:postcode": "02129",
    "addr:street": "Terminal St",
    "iso:country": "US",
    "sg:address": "100 Terminal St",
    "sg:city": "Boston",
    "sg:classifiers": [
      {
        "category": "Freight",
        "type": "Transportation"
      }
    ],
    "sg:phone": "+1 617 569 3733",
    "sg:postcode": "02129",
    "sg:province": "MA",
    "wof:name": "Air Service Corp",
    "wof:placetype": "venue"
  },
  "geometry": {"coordinates":[-71.055325,42.381628],"type":"Point"}
}
