{
  "type": "Feature",
  "properties": {
    "addr:full": "134 Bliss St West Springfield MA 01089",
    "addr:housenumber": "134",
    "addr:postcode": "01089",
    "addr:street": "Bliss St",
    "iso:country": "US",
    "sg:address": "134 Bliss St",
    "sg:city": "West Springfield",
    "sg:classifiers": [
      {
        "category": "Wholesale",
        "subcategory": "Medical Equipment \u0026 Supplies",
        "type": "Manufacturing \u0026 Wholesale Goods"
      }
    ],
    "sg:phone": "+1 413 737 5466",
    "sg:postcode": "01089",
    "sg:province": "MA",
    "sg:tags": [
      "hospital"
    ],
    "wof:name": "Medequip Inc",
    "wof:placetype": "venue"
  },
  "geometry": {"coordinates":[-72.618391,42.103391],"type":"Point"}
}
