{
  "type": "Feature",
  "properties": {
    "iso:country":"US",
    "sg:address":"358 N Warren Ave",
    "sg:city":"Brockton",
    "sg:phone":"+1 508 586 1962",
    "sg:postcode":"02301",
    "sg:province":"MA",
    "sg:tags":[
        "oil"
    ],
    "wof:name":"Mass Fuel Assoc Inc",
    "wof:placetype":"venue"
},
  "geometry": {"coordinates":[-71.026614,42.094046],"type":"Point"}
}