{
  "type": "Feature",
  "properties": {
    "addr:full":"896 N Hoosac Rd Williamstown MA 01267",
    "addr:housenumber":"896",
    "addr:postcode":"01267",
    "addr:street":"N Hoosac Rd",
    "iso:country":"US",
    "sg:address":"896 N Hoosac Rd",
    "sg:city":"Williamstown",
    "sg:classifiers":[
        {
            "category":"Professional",
            "type":"Services"
        }
    ],
    "sg:phone":"+1 413 458 3403",
    "sg:postcode":"01267",
    "sg:province":"MA",
    "sg:tags":[
        "establishment"
    ],
    "wof:name":"Ejm Enterprises",
    "wof:placetype":"venue"
},
  "geometry": {"coordinates":[-73.193198,42.725725],"type":"Point"}
}