{
  "type": "Feature",
  "properties": {
    "addr:full": "291 American Legion Hwy Westport MA 02790",
    "addr:housenumber": "291",
    "addr:postcode": "02790",
    "addr:street": "American Legion Hwy",
    "iso:country": "US",
    "sg:address": "291 American Legion Hwy",
    "sg:city": "Westport",
    "sg:classifiers": [
      {
        "category": "Shopping",
        "subcategory": "Discount \u0026 Variety Stores",
        "type": "Retail Goods"
      }
    ],
    "sg:phone": "+1 508 636 5252",
    "sg:postcode": "02790",
    "sg:province": "MA",
    "wof:name": "Westport Market",
    "wof:placetype": "venue"
  },
  "geometry": {"coordinates":[-71.112585,41.626781],"type":"Point"}
}
