{
  "type": "Feature",
  "properties": {
    "iso:country":"US",
    "sg:address":"291 American Legion Hwy",
    "sg:city":"Westport",
    "sg:classifiers":[
        {
            "category":"Shopping",
            "subcategory":"Discount & Variety Stores",
            "type":"Retail Goods"
        }
    ],
    "sg:phone":"+1 508 636 5252",
    "sg:postcode":"02790",
    "sg:province":"MA",
    "wof:name":"Westport Market",
    "wof:placetype":"venue"
},
  "geometry": {"coordinates":[-71.112585,41.626781],"type":"Point"}
}