{
  "type": "Feature",
  "properties": {
    "addr:full": "1151 Washington St Braintree MA 02184",
    "addr:housenumber": "1151",
    "addr:postcode": "02184",
    "addr:street": "Washington St",
    "iso:country": "US",
    "sg:address": "1151 Washington St",
    "sg:city": "Braintree",
    "sg:classifiers": [
      {
        "category": "Retail",
        "subcategory": "Laundry \u0026 Dry Cleaning",
        "type": "Services"
      }
    ],
    "sg:phone": "+1 781 843 8883",
    "sg:postcode": "02184",
    "sg:province": "MA",
    "wof:name": "Alterations By Stephanie",
    "wof:placetype": "venue"
  },
  "geometry": {"coordinates":[-71.00645,42.19824],"type":"Point"}
}
