{
  "type": "Feature",
  "properties": {
    "addr:full": "47 Dunboy St Brighton MA 02135",
    "addr:housenumber": "47",
    "addr:postcode": "02135",
    "addr:street": "Dunboy St",
    "iso:country": "US",
    "sg:address": "47 Dunboy St",
    "sg:city": "Brighton",
    "sg:classifiers": [
      {
        "category": "Building \u0026 Trades",
        "subcategory": "Construction",
        "type": "Services"
      }
    ],
    "sg:phone": "+1 617 254 6130",
    "sg:postcode": "02135",
    "sg:province": "MA",
    "sg:tags": [
      "contractor"
    ],
    "wof:name": "Liam Byrne Contracting",
    "wof:placetype": "venue"
  },
  "geometry": {"coordinates":[-71.164687,42.352288],"type":"Point"}
}
