{
  "type": "Feature",
  "properties": {
    "iso:country":"US",
    "sg:address":"96 Mainline Dr",
    "sg:city":"Westfield",
    "sg:classifiers":[
        {
            "category":"Government",
            "subcategory":"Fire Station",
            "type":"Public Place"
        }
    ],
    "sg:phone":"+1 413 789 2398",
    "sg:postcode":"01085",
    "sg:province":"MA",
    "sg:tags":[
        "extinguisher",
        "supply",
        "consultant",
        "equipment",
        "protection",
        "servicing",
        "equipment-repairing"
    ],
    "sg:website":"http://www.firecontrolsystems.com",
    "wof:name":"Fire Control Systems Inc",
    "wof:placetype":"venue"
},
  "geometry": {"coordinates":[-72.73155,42.112531],"type":"Point"}
}