{
  "type": "Feature",
  "properties": {
    "addr:full":"38 Quincy St Holbrook MA 02343",
    "addr:housenumber":"38",
    "addr:postcode":"02343",
    "addr:street":"Quincy St",
    "iso:country":"US",
    "sg:address":"38 Quincy St",
    "sg:city":"Holbrook",
    "sg:classifiers":[
        {
            "category":"Building & Trades",
            "subcategory":"Plumbing",
            "type":"Services"
        }
    ],
    "sg:phone":"+1 781 767 3714",
    "sg:postcode":"02343",
    "sg:province":"MA",
    "sg:tags":[
        "septic"
    ],
    "wof:name":"Blakemore Co",
    "wof:placetype":"venue"
},
  "geometry": {"coordinates":[-71.005861,42.134098],"type":"Point"}
}