{
  "type": "Feature",
  "properties": {
    "addr:full":"5 Milestone Xing Nantucket MA 02554",
    "addr:housenumber":"5",
    "addr:postcode":"02554",
    "addr:street":"Milestone Xing",
    "iso:country":"US",
    "sg:address":"5 Milestone Xing",
    "sg:city":"Nantucket",
    "sg:classifiers":[
        {
            "category":"Professional",
            "subcategory":"Business Services",
            "type":"Services"
        }
    ],
    "sg:phone":"+1 508 228 0552",
    "sg:postcode":"02554",
    "sg:province":"MA",
    "sg:tags":[
        "consultant",
        "coach"
    ],
    "wof:name":"Nantucket Knotworks",
    "wof:placetype":"venue"
},
  "geometry": {"coordinates":[-70.066435,41.269953],"type":"Point"}
}