{
  "type": "Feature",
  "properties": {
    "addr:full":"109 E Emerson Rd Lexington MA 02420",
    "addr:housenumber":"109",
    "addr:postcode":"02420",
    "addr:street":"E Emerson Rd",
    "iso:country":"US",
    "sg:address":"109 E Emerson Rd",
    "sg:city":"Lexington",
    "sg:classifiers":[
        {
            "category":"Professional",
            "type":"Services"
        }
    ],
    "sg:phone":"+1   ",
    "sg:postcode":"02420",
    "sg:province":"MA",
    "wof:name":"Charles Brenner",
    "wof:placetype":"venue"
},
  "geometry": {"coordinates":[-71.207268,42.455399],"type":"Point"}
}