{
  "type": "Feature",
  "properties": {
    "iso:country":"US",
    "sg:address":"6 Fort Hill St",
    "sg:city":"Hingham",
    "sg:classifiers":[
        {
            "category":"Organizations",
            "subcategory":"Membership Organization",
            "type":"Services"
        }
    ],
    "sg:phone":"+1 781 749 1003",
    "sg:postcode":"02043",
    "sg:province":"MA",
    "sg:tags":[
        "club",
        "private"
    ],
    "wof:name":"South Shore Country Club Maint",
    "wof:placetype":"venue"
},
  "geometry": {"coordinates":[-70.902873,42.23711],"type":"Point"}
}