{
  "type": "Feature",
  "properties": {
    "addr:full": "William J. Day Boulevard at Farragut Road Boston MA 02127",
    "addr:postcode": "02127",
    "addr:street": "Boulevard At Farragut Road",
    "iso:country": "US",
    "sg:address": "William J. Day Boulevard at Farragut Road",
    "sg:city": "Boston",
    "sg:classifiers": [
      {
        "category": "Park",
        "type": "Public Place"
      },
      {
        "category": "Recreation",
        "subcategory": "Playground",
        "type": "Entertainment"
      }
    ],
    "sg:postcode": "02127",
    "sg:province": "MA",
    "wof:name": "Fort Independence Park",
    "wof:placetype": "venue"
  },
  "geometry": {"coordinates":[-71.024902,42.333],"type":"Point"}
}
