{
  "type": "Feature",
  "properties": {
    "iso:country":"US",
    "sg:address":"87 Kemble St",
    "sg:city":"Roxbury",
    "sg:classifiers":[
        {
            "category":"Wholesale",
            "subcategory":"Fruits & Vegetables",
            "type":"Manufacturing & Wholesale Goods"
        }
    ],
    "sg:phone":"+1 617 427 5500",
    "sg:postcode":"02119",
    "sg:province":"MA",
    "sg:tags":[
        "vegetables-wholesale"
    ],
    "wof:name":"Sea Best Express",
    "wof:placetype":"venue"
},
  "geometry": {"coordinates":[-71.07135,42.32766],"type":"Point"}
}