{
  "type": "Feature",
  "properties": {
    "addr:full":"62 Melha Ave Springfield MA 01104",
    "addr:housenumber":"62",
    "addr:postcode":"01104",
    "addr:street":"Melha Ave",
    "iso:country":"US",
    "sg:address":"62 Melha Ave",
    "sg:city":"Springfield",
    "sg:classifiers":[
        {
            "category":"Building & Trades",
            "subcategory":"Cleaning & Sanitation",
            "type":"Services"
        }
    ],
    "sg:phone":"+1   ",
    "sg:postcode":"01104",
    "sg:province":"MA",
    "sg:tags":[
        "maintenance"
    ],
    "wof:name":"Immaculate Homecleaning",
    "wof:placetype":"venue"
},
  "geometry": {"coordinates":[-72.594734,42.121835],"type":"Point"}
}