{
  "type": "Feature",
  "properties": {
    "iso:country":"US",
    "sg:address":"756 Dighton Ave",
    "sg:city":"Taunton",
    "sg:classifiers":[
        {
            "category":"Autos & Motor Vehicles",
            "subcategory":"Motorcycle Sales",
            "type":"Retail Goods"
        }
    ],
    "sg:phone":"+1 508 822 5639",
    "sg:postcode":"02780",
    "sg:province":"MA",
    "sg:tags":[
        "scooter"
    ],
    "wof:name":"Butch's Cycle Works",
    "wof:placetype":"venue"
},
  "geometry": {"coordinates":[-71.120682,41.867001],"type":"Point"}
}