{
  "type": "Feature",
  "properties": {
    "addr:full": "756 Dighton Ave Taunton MA 02780",
    "addr:housenumber": "756",
    "addr:postcode": "02780",
    "addr:street": "Dighton Ave",
    "iso:country": "US",
    "ovtr:label": "Butch's Cycle Works, 756 Dighton Ave Taunton MA US",
    "ovtr:similarity": 2.62903094291687,
    "sg:address": "756 Dighton Ave",
    "sg:city": "Taunton",
    "sg:classifiers": [
      {
        "category": "Autos \u0026 Motor Vehicles",
        "subcategory": "Motorcycle Sales",
        "type": "Retail Goods"
      }
    ],
    "sg:phone": "+1 508 822 5639",
    "sg:postcode": "02780",
    "sg:province": "MA",
    "sg:tags": [
      "scooter"
    ],
    "wof:name": "Butch's Cycle Works",
    "wof:placetype": "venue"
  },
  "geometry": {"coordinates":[-71.120682,41.867001],"type":"Point"}
}
