{
  "type": "Feature",
  "properties": {
    "addr:full": "151 State Hwy 1 Alt East Boston MA 02128",
    "addr:housenumber": "151",
    "addr:postcode": "02128",
    "addr:street": "State Hwy 1",
    "iso:country": "US",
    "sg:address": "151 State Hwy 1 Alt",
    "sg:city": "East Boston",
    "sg:classifiers": [
      {
        "category": "Airline",
        "type": "Transportation"
      }
    ],
    "sg:phone": "+1 617 567 2760",
    "sg:postcode": "02128",
    "sg:province": "MA",
    "sg:tags": [
      "cargo",
      "air"
    ],
    "sg:website": "www.agi.com",
    "wof:name": "Air General Inc",
    "wof:placetype": "venue"
  },
  "geometry": {"coordinates":[-71.020378,42.38451],"type":"Point"}
}
