{
  "type": "Feature",
  "properties": {
    "iso:country":"US",
    "sg:address":"140 Shurtleff St",
    "sg:city":"Chelsea",
    "sg:classifiers":[
        {
            "category":"Organizations",
            "subcategory":"Religious Organization",
            "type":"Services"
        }
    ],
    "sg:phone":"+1 617 887 9737",
    "sg:postcode":"02150",
    "sg:province":"MA",
    "sg:tags":[
        "churches-pentecostal",
        "church"
    ],
    "wof:name":"Iglesia Pentecostal Unida",
    "wof:placetype":"venue"
},
  "geometry": {"coordinates":[-71.034077,42.390929],"type":"Point"}
}