{
  "type": "Feature",
  "properties": {
    "addr:full":"17 Hudson Ave Oak Bluffs MA 02557",
    "addr:housenumber":"17",
    "addr:postcode":"02557",
    "addr:street":"Hudson Ave",
    "iso:country":"US",
    "sg:address":"17 Hudson Ave",
    "sg:city":"Oak Bluffs",
    "sg:classifiers":[
        {
            "category":"Retail",
            "subcategory":"Repair Shop",
            "type":"Services"
        }
    ],
    "sg:phone":"+1 508 693 4547",
    "sg:postcode":"02557",
    "sg:province":"MA",
    "sg:tags":[
        "lock",
        "locksmith"
    ],
    "wof:name":"Buzz's Key & Lock",
    "wof:placetype":"venue"
},
  "geometry": {"coordinates":[-70.576139,41.444153],"type":"Point"}
}