{
  "type": "Feature",
  "properties": {
    "addr:full": "113 Garden Street Cambridge MA 02138",
    "addr:housenumber": "113",
    "addr:postcode": "02138",
    "addr:street": "Garden Street",
    "iso:country": "US",
    "sg:address": "113 Garden Street",
    "sg:city": "Cambridge",
    "sg:classifiers": [
      {
        "category": "Banks \u0026 Credit Unions",
        "subcategory": "Bank",
        "type": "Services"
      }
    ],
    "sg:phone": "+1 617 864 2298",
    "sg:postcode": "02138",
    "sg:province": "MA",
    "wof:name": "Cambridge Firemen's Fedl Credit Union",
    "wof:placetype": "venue"
  },
  "geometry": {"coordinates":[-71.129786,42.383917],"type":"Point"}
}
