{
  "type": "Feature",
  "properties": {
    "iso:country":"US",
    "sg:address":"135 Bartlett Ave",
    "sg:city":"Pittsfield",
    "sg:classifiers":[
        {
            "category":"Professional",
            "subcategory":"Management & Consulting",
            "type":"Services"
        }
    ],
    "sg:phone":"+1   ",
    "sg:postcode":"01201",
    "sg:province":"MA",
    "sg:tags":[
        "business"
    ],
    "wof:name":"Ballen Consulting",
    "wof:placetype":"venue"
},
  "geometry": {"coordinates":[-73.252173,42.442761],"type":"Point"}
}