{
  "type": "Feature",
  "properties": {
    "addr:full":"240 Canal St Salem MA 01970",
    "addr:housenumber":"240",
    "addr:postcode":"01970",
    "addr:street":"Canal St",
    "iso:country":"US",
    "sg:address":"240 Canal St",
    "sg:city":"Salem",
    "sg:classifiers":[
        {
            "category":"Building & Trades",
            "subcategory":"Construction",
            "type":"Services"
        }
    ],
    "sg:phone":"+1 978 745 2890",
    "sg:postcode":"01970",
    "sg:province":"MA",
    "sg:tags":[
        "paving",
        "contractor"
    ],
    "wof:name":"Atlantic Paving Inc",
    "wof:placetype":"venue"
},
  "geometry": {"coordinates":[-70.89614400000001,42.506013],"type":"Point"}
}