{
  "type": "Feature",
  "properties": {
    "addr:full":"221 Pine St Florence MA 01062",
    "addr:housenumber":"221",
    "addr:postcode":"01062",
    "addr:street":"Pine St",
    "iso:country":"US",
    "sg:address":"221 Pine St",
    "sg:city":"Florence",
    "sg:classifiers":[
        {
            "category":"Professional",
            "subcategory":"Art Services",
            "type":"Services"
        }
    ],
    "sg:phone":"+1 413 586 0223",
    "sg:postcode":"01062",
    "sg:province":"MA",
    "sg:tags":[
        "artist"
    ],
    "wof:name":"Hilary Price Phymes W/Orange",
    "wof:placetype":"venue"
},
  "geometry": {"coordinates":[-72.68008,42.330622],"type":"Point"}
}