{
  "type": "Feature",
  "properties": {
    "iso:country":"US",
    "sg:address":"49 Nash Hill Rd",
    "sg:city":"Williamsburg",
    "sg:classifiers":[
        {
            "category":"Professional",
            "subcategory":"Computer Services",
            "type":"Services"
        }
    ],
    "sg:phone":"+1 413 268 3170",
    "sg:postcode":"01096",
    "sg:province":"MA",
    "sg:tags":[
        "consultant",
        "designer"
    ],
    "wof:name":"Proman Atlantic",
    "wof:placetype":"venue"
},
  "geometry": {"coordinates":[-72.727914,42.40233],"type":"Point"}
}