{
  "type": "Feature",
  "properties": {
    "addr:full":"49 Ketchum Ln South Weymouth MA 02190",
    "addr:housenumber":"49",
    "addr:postcode":"02190",
    "addr:street":"Ketchum Ln",
    "iso:country":"US",
    "sg:address":"49 Ketchum Ln",
    "sg:city":"South Weymouth",
    "sg:classifiers":[
        {
            "category":"Home & Garden",
            "subcategory":"Furniture",
            "type":"Retail Goods"
        }
    ],
    "sg:phone":"+1   ",
    "sg:postcode":"02190",
    "sg:province":"MA",
    "wof:name":"Russell J H Co",
    "wof:placetype":"venue"
},
  "geometry": {"coordinates":[-70.92683,42.172963],"type":"Point"}
}