{
  "type": "Feature",
  "properties": {
    "addr:full":"30 Martin Rd East Falmouth MA 02536",
    "addr:housenumber":"30",
    "addr:postcode":"02536",
    "addr:street":"Martin Rd",
    "iso:country":"US",
    "sg:address":"30 Martin Rd",
    "sg:city":"East Falmouth",
    "sg:classifiers":[
        {
            "category":"Building & Trades",
            "subcategory":"Electrical",
            "type":"Services"
        }
    ],
    "sg:phone":"+1 508 548 6916",
    "sg:postcode":"02536",
    "sg:province":"MA",
    "sg:tags":[
        "electric",
        "contractor"
    ],
    "wof:name":"Neil Meuller Electrician",
    "wof:placetype":"venue"
},
  "geometry": {"coordinates":[-70.50915000000001,41.591529],"type":"Point"}
}