{
  "type": "Feature",
  "properties": {
    "addr:full": "12 Dare Way Chicopee MA 01022",
    "addr:housenumber": "12",
    "addr:postcode": "01022",
    "addr:street": "Dare Way",
    "iso:country": "US",
    "sg:address": "12 Dare Way",
    "sg:city": "Chicopee",
    "sg:classifiers": [
      {
        "category": "Education",
        "subcategory": "School",
        "type": "Public Place"
      }
    ],
    "sg:phone": "+1 413 594 3449",
    "sg:postcode": "01022",
    "sg:province": "MA",
    "wof:name": "Selser School",
    "wof:placetype": "venue"
  },
  "geometry": {"coordinates":[-72.558603,42.198472],"type":"Point"}
}
