{
  "type": "Feature",
  "properties": {
    "addr:full":"150 Mechanic St Foxboro MA 02035",
    "addr:housenumber":"150",
    "addr:postcode":"02035",
    "addr:street":"Mechanic St",
    "iso:country":"US",
    "sg:address":"150 Mechanic St",
    "sg:city":"Foxboro",
    "sg:classifiers":[
        {
            "category":"Retail",
            "subcategory":"Repair Shop",
            "type":"Services"
        }
    ],
    "sg:phone":"+1   ",
    "sg:postcode":"02035",
    "sg:province":"MA",
    "wof:name":"Custom Design",
    "wof:placetype":"venue"
},
  "geometry": {"coordinates":[-71.23260000000001,42.079609],"type":"Point"}
}