{
  "type": "Feature",
  "properties": {
    "addr:full":"761 Beacon St Newton MA 02459",
    "addr:housenumber":"761",
    "addr:postcode":"02459",
    "addr:street":"Beacon St",
    "iso:country":"US",
    "sg:address":"761 Beacon St",
    "sg:city":"Newton",
    "sg:classifiers":[
        {
            "category":"Restaurant",
            "type":"Food & Drink"
        }
    ],
    "sg:menulink":"http://www.allmenus.com/ma/newton/260793-appetito/menu/",
    "sg:phone":"+1 617 244 9881",
    "sg:postcode":"02459",
    "sg:province":"MA",
    "sg:tags":[
        "italian"
    ],
    "wof:name":"Appetito",
    "wof:placetype":"venue"
},
  "geometry": {"coordinates":[-71.191851,42.330669],"type":"Point"}
}