{
  "type": "Feature",
  "properties": {
    "addr:full": "99A Blanchard Road Cambridge MA 02138",
    "addr:housenumber": "99a",
    "addr:postcode": "02138",
    "addr:street": "Blanchard Road",
    "iso:country": "US",
    "sg:address": "99A Blanchard Road",
    "sg:city": "Cambridge",
    "sg:classifiers": [
      {
        "category": "Real Estate",
        "subcategory": "Real Estate Operator",
        "type": "Services"
      }
    ],
    "sg:phone": "+1 617 491 4890",
    "sg:postcode": "02138",
    "sg:province": "MA",
    "sg:tags": [
      "apartment"
    ],
    "wof:name": "Blair Pond Estates",
    "wof:placetype": "venue"
  },
  "geometry": {"coordinates":[-71.158216,42.393566],"type":"Point"}
}
