{
  "type": "Feature",
  "properties": {
    "iso:country":"US",
    "sg:address":"190 Broadway",
    "sg:city":"North Attleboro",
    "sg:classifiers":[
        {
            "category":"Retail",
            "subcategory":"Repair Shop",
            "type":"Services"
        },
        {
            "category":"Home & Garden",
            "subcategory":"Garden Supply",
            "type":"Retail Goods"
        }
    ],
    "sg:phone":"+1 508 643 2072",
    "sg:postcode":"02760",
    "sg:province":"MA",
    "sg:tags":[
        "engine"
    ],
    "wof:name":"Bliek John Small Engine Svc",
    "wof:placetype":"venue"
},
  "geometry": {"coordinates":[-71.338427,41.978946],"type":"Point"}
}