{
  "type": "Feature",
  "properties": {
    "iso:country":"US",
    "sg:address":"10 N Pearl St",
    "sg:city":"Brockton",
    "sg:classifiers":[
        {
            "category":"Shopping",
            "subcategory":"Optical Goods",
            "type":"Retail Goods"
        }
    ],
    "sg:phone":"+1 508 583 6675",
    "sg:postcode":"02301",
    "sg:province":"MA",
    "sg:tags":[
        "optician"
    ],
    "wof:name":"Eye Health",
    "wof:placetype":"venue"
},
  "geometry": {"coordinates":[-71.06436600000001,42.090252],"type":"Point"}
}