{
  "type": "Feature",
  "properties": {
    "addr:full":"51 Walnut Park Boston MA 02119",
    "addr:housenumber":"51",
    "addr:postcode":"02119",
    "addr:street":"Walnut Park",
    "iso:country":"US",
    "sg:address":"51 Walnut Park",
    "sg:city":"Boston",
    "sg:classifiers":[
        {
            "category":"Real Estate",
            "subcategory":"Real Estate Agent",
            "type":"Services"
        }
    ],
    "sg:phone":"+1   ",
    "sg:postcode":"02119",
    "sg:province":"MA",
    "sg:tags":[
        "manager"
    ],
    "wof:name":"Lorenzo Pitts Inc",
    "wof:placetype":"venue"
},
  "geometry": {"coordinates":[-71.096069,42.315263],"type":"Point"}
}