{
  "type": "Feature",
  "properties": {
    "addr:full": "205 Central St South Weymouth MA 02190",
    "addr:housenumber": "205",
    "addr:postcode": "02190",
    "addr:street": "Central St",
    "iso:country": "US",
    "sg:address": "205 Central St",
    "sg:city": "South Weymouth",
    "sg:classifiers": [
      {
        "category": "Building \u0026 Trades",
        "subcategory": "Construction",
        "type": "Services"
      }
    ],
    "sg:phone": "+1 781 340 0200",
    "sg:postcode": "02190",
    "sg:province": "MA",
    "sg:tags": [
      "general",
      "contractor"
    ],
    "wof:name": "J C Milch Construction",
    "wof:placetype": "venue"
  },
  "geometry": {"coordinates":[-70.944806,42.169385],"type":"Point"}
}
