{
  "type": "Feature",
  "properties": {
    "addr:full":"15 Lexington Ave Ste 5 Gloucester MA 01930",
    "addr:housenumber":"15",
    "addr:postcode":"01930",
    "addr:street":"Lexington Ave Ste 5",
    "iso:country":"US",
    "sg:address":"15 Lexington Ave Ste 5",
    "sg:city":"Gloucester",
    "sg:classifiers":[
        {
            "category":"Personal",
            "subcategory":"Beauty Salon",
            "type":"Services"
        }
    ],
    "sg:phone":"+1 978 525 3960",
    "sg:postcode":"01930",
    "sg:province":"MA",
    "sg:tags":[
        "wig",
        "hair",
        "piece"
    ],
    "wof:name":"Shear Madness",
    "wof:placetype":"venue"
},
  "geometry": {"coordinates":[-70.712118,42.57659],"type":"Point"}
}