{
  "type": "Feature",
  "properties": {
    "iso:country":"US",
    "sg:address":"3 Electronics Ave",
    "sg:city":"Danvers",
    "sg:classifiers":[
        {
            "category":"Wholesale",
            "subcategory":"Drugs",
            "type":"Manufacturing & Wholesale Goods"
        }
    ],
    "sg:phone":"+1 978 774 3956",
    "sg:postcode":"01923",
    "sg:province":"MA",
    "sg:tags":[
        "pharmaceutical",
        "product"
    ],
    "sg:website":"www.biochemics.com",
    "wof:name":"Biochemics Inc",
    "wof:placetype":"venue"
},
  "geometry": {"coordinates":[-70.972342,42.575883],"type":"Point"}
}