{
  "type": "Feature",
  "properties": {
    "iso:country":"US",
    "sg:address":"100 Palmer Ave",
    "sg:city":"Falmouth",
    "sg:classifiers":[
        {
            "category":"Manufacturing",
            "subcategory":"Apparel",
            "type":"Manufacturing & Wholesale Goods"
        }
    ],
    "sg:phone":"+1 508 548 5260",
    "sg:postcode":"02540",
    "sg:province":"MA",
    "sg:tags":[
        "clothing",
        "mfg"
    ],
    "sg:website":"www.realbodies.com",
    "wof:name":"Real Bodies Clothing From Bali",
    "wof:placetype":"venue"
},
  "geometry": {"coordinates":[-70.620307,41.555522],"type":"Point"}
}