{
  "type": "Feature",
  "properties": {
    "addr:full":"34 Blynman Ave Gloucester MA 01930",
    "addr:housenumber":"34",
    "addr:postcode":"01930",
    "addr:street":"Blynman Ave",
    "iso:country":"US",
    "sg:address":"34 Blynman Ave",
    "sg:city":"Gloucester",
    "sg:classifiers":[
        {
            "category":"Freight",
            "type":"Transportation"
        }
    ],
    "sg:phone":"+1 978 281 1527",
    "sg:postcode":"01930",
    "sg:province":"MA",
    "sg:tags":[
        "delivery"
    ],
    "wof:name":"Double M Delivery",
    "wof:placetype":"venue"
},
  "geometry": {"coordinates":[-70.674448,42.613431],"type":"Point"}
}