{
  "type": "Feature",
  "properties": {
    "addr:full":"219 Lexington St Waltham MA 02452",
    "addr:housenumber":"219",
    "addr:postcode":"02452",
    "addr:street":"Lexington St",
    "iso:country":"US",
    "sg:address":"219 Lexington St",
    "sg:city":"Waltham",
    "sg:classifiers":[
        {
            "category":"Retail",
            "subcategory":"Auto Rental",
            "type":"Services"
        }
    ],
    "sg:phone":"+1 781 899 0667",
    "sg:postcode":"02452",
    "sg:province":"MA",
    "sg:tags":[
        "equipment",
        "moving",
        "supply"
    ],
    "wof:name":"A Boxes",
    "wof:placetype":"venue"
},
  "geometry": {"coordinates":[-71.23689400000001,42.38325],"type":"Point"}
}