{
  "type": "Feature",
  "properties": {
    "iso:country":"US",
    "sg:address":"190 Everett Ave.",
    "sg:city":"Chelsea",
    "sg:classifiers":[
        {
            "category":"Professional",
            "subcategory":"Research",
            "type":"Services"
        }
    ],
    "sg:postcode":"02150",
    "sg:province":"MA",
    "sg:website":"http://www.civitastherapeutics.com/",
    "wof:name":"Civitas Therapeutics",
    "wof:placetype":"venue"
},
  "geometry": {"coordinates":[-71.040719,42.398841],"type":"Point"}
}