{
  "type": "Feature",
  "properties": {
    "addr:full":"147 W 4th St South Boston MA 02127",
    "addr:housenumber":"147",
    "addr:postcode":"02127",
    "addr:street":"W 4Th St",
    "iso:country":"US",
    "sg:address":"147 W 4th St",
    "sg:city":"South Boston",
    "sg:classifiers":[
        {
            "category":"Building & Trades",
            "subcategory":"Locksmith",
            "type":"Services"
        }
    ],
    "sg:phone":"+1 617 315 9018",
    "sg:postcode":"02127",
    "sg:province":"MA",
    "sg:tags":[
        "key"
    ],
    "wof:name":"AAA Locksmith",
    "wof:placetype":"venue"
},
  "geometry": {"coordinates":[-71.055809,42.340594],"type":"Point"}
}