{
  "type": "Feature",
  "properties": {
    "addr:full":"10 Clever Ln Tewksbury MA 01876",
    "addr:housenumber":"10",
    "addr:postcode":"01876",
    "addr:street":"Clever Ln",
    "iso:country":"US",
    "sg:address":"10 Clever Ln",
    "sg:city":"Tewksbury",
    "sg:classifiers":[
        {
            "category":"Professional",
            "type":"Services"
        }
    ],
    "sg:phone":"+1 978 455 3383",
    "sg:postcode":"01876",
    "sg:province":"MA",
    "sg:tags":[
        "establishment"
    ],
    "sg:website":"www.ultsol.com",
    "wof:name":"Ultimate Solutions Inc",
    "wof:placetype":"venue"
},
  "geometry": {"coordinates":[-71.188202,42.610611],"type":"Point"}
}