{
  "type": "Feature",
  "properties": {
    "addr:full":"1813 Main St Agawam MA 01001",
    "addr:housenumber":"1813",
    "addr:postcode":"01001",
    "addr:street":"Main St",
    "iso:country":"US",
    "sg:address":"1813 Main St",
    "sg:city":"Agawam",
    "sg:classifiers":[
        {
            "category":"Bars & Pubs",
            "type":"Food & Drink"
        }
    ],
    "sg:phone":"+1 413 789 0058",
    "sg:postcode":"01001",
    "sg:province":"MA",
    "sg:tags":[
        "tavern"
    ],
    "wof:name":"Still",
    "wof:placetype":"venue"
},
  "geometry": {"coordinates":[-72.616882,42.031689],"type":"Point"}
}