{
  "type": "Feature",
  "properties": {
    "addr:full":"321 Centre Street Boston MA 02121",
    "addr:housenumber":"321",
    "addr:postcode":"02121",
    "addr:street":"Centre Street",
    "iso:country":"US",
    "sg:address":"321 Centre Street",
    "sg:city":"Boston",
    "sg:classifiers":[
        {
            "category":"Sports & Exercise",
            "subcategory":"Gym",
            "type":"Entertainment"
        }
    ],
    "sg:phone":"+1 617 825 6320",
    "sg:postcode":"02121",
    "sg:province":"MA",
    "sg:tags":[
        "trainer"
    ],
    "wof:name":"St Joseph Home",
    "wof:placetype":"venue"
},
  "geometry": {"coordinates":[-71.080997,42.309681],"type":"Point"}
}