{
  "type": "Feature",
  "properties": {
    "iso:country":"US",
    "sg:address":"720 Washington St",
    "sg:city":"Hanover",
    "sg:classifiers":[
        {
            "category":"Professional",
            "subcategory":"Engineering",
            "type":"Services"
        }
    ],
    "sg:phone":"+1 781 826 4550",
    "sg:postcode":"02339",
    "sg:province":"MA",
    "sg:tags":[
        "engineer"
    ],
    "wof:name":"DEC Inc",
    "wof:placetype":"venue"
},
  "geometry": {"coordinates":[-70.827479,42.125768],"type":"Point"}
}