{
  "type": "Feature",
  "properties": {
    "iso:country":"US",
    "sg:address":"300 Longwood Ave",
    "sg:city":"Boston",
    "sg:classifiers":[
        {
            "category":"Health Services",
            "subcategory":"Doctor",
            "type":"Services"
        },
        {
            "category":"Health Services",
            "subcategory":"Hospital",
            "type":"Services"
        }
    ],
    "sg:phone":"+1 617 355 7800",
    "sg:postcode":"02115",
    "sg:province":"MA",
    "wof:name":"Weldon Christopher MD PHD",
    "wof:placetype":"venue"
},
  "geometry": {"coordinates":[-71.103454,42.336981],"type":"Point"}
}