{
  "type": "Feature",
  "properties": {
    "addr:full":"104 Dahlia Dr Wayland MA 01778",
    "addr:housenumber":"104",
    "addr:postcode":"01778",
    "addr:street":"Dahlia Dr",
    "iso:country":"US",
    "sg:address":"104 Dahlia Dr",
    "sg:city":"Wayland",
    "sg:classifiers":[
        {
            "category":"Professional",
            "subcategory":"Business Services",
            "type":"Services"
        }
    ],
    "sg:phone":"+1   ",
    "sg:postcode":"01778",
    "sg:province":"MA",
    "wof:name":"William A Hawthorne Associates",
    "wof:placetype":"venue"
},
  "geometry": {"coordinates":[-71.336454,42.343603],"type":"Point"}
}