{
  "type": "Feature",
  "properties": {
    "iso:country":"US",
    "sg:address":"30 Monument Sq",
    "sg:city":"Concord",
    "sg:classifiers":[
        {
            "category":"Professional",
            "type":"Services"
        }
    ],
    "sg:phone":"+1 978 318 0650",
    "sg:postcode":"01742",
    "sg:province":"MA",
    "sg:tags":[
        "establishment"
    ],
    "sg:website":"www.pathfinderinnovation.com",
    "wof:name":"Pathfinder Innovations",
    "wof:placetype":"venue"
},
  "geometry": {"coordinates":[-71.349115,42.461264],"type":"Point"}
}