{
  "type": "Feature",
  "properties": {
    "iso:country":"US",
    "sg:address":"15 Perham St",
    "sg:city":"Wakefield",
    "sg:classifiers":[
        {
            "category":"Retail",
            "subcategory":"Auto Repair",
            "type":"Services"
        }
    ],
    "sg:phone":"+1 781 245 9811",
    "sg:postcode":"01880",
    "sg:province":"MA",
    "sg:tags":[
        "body",
        "automobile",
        "painting"
    ],
    "wof:name":"Body Craft Automotive",
    "wof:placetype":"venue"
},
  "geometry": {"coordinates":[-71.058125,42.504581],"type":"Point"}
}