{
  "type": "Feature",
  "properties": {
    "iso:country":"US",
    "sg:address":"14 Bigelow Ave",
    "sg:city":"Winchester",
    "sg:classifiers":[
        {
            "category":"Building & Trades",
            "subcategory":"Construction",
            "type":"Services"
        }
    ],
    "sg:phone":"+1 781 729 6233",
    "sg:postcode":"01890",
    "sg:province":"MA",
    "sg:tags":[
        "contractor"
    ],
    "wof:name":"Carlson Werner A Bldr",
    "wof:placetype":"venue"
},
  "geometry": {"coordinates":[-71.167503,42.449799],"type":"Point"}
}