{
  "type": "Feature",
  "properties": {
    "iso:country":"US",
    "sg:address":"104 Forest Ave",
    "sg:city":"Hudson",
    "sg:classifiers":[
        {
            "category":"Manufacturing",
            "subcategory":"Electronics",
            "type":"Manufacturing & Wholesale Goods"
        }
    ],
    "sg:phone":"+1 978 562 1751",
    "sg:postcode":"01749",
    "sg:province":"MA",
    "sg:tags":[
        "semiconductor",
        "devices"
    ],
    "wof:name":"Asml",
    "wof:placetype":"venue"
},
  "geometry": {"coordinates":[-71.549671,42.38789],"type":"Point"}
}