{
  "type": "Feature",
  "properties": {
    "addr:full":"62 Worcester St Taunton MA 02780",
    "addr:housenumber":"62",
    "addr:postcode":"02780",
    "addr:street":"Worcester St",
    "iso:country":"US",
    "sg:address":"62 Worcester St",
    "sg:city":"Taunton",
    "sg:classifiers":[
        {
            "category":"Personal",
            "subcategory":"Beauty Salon",
            "type":"Services"
        }
    ],
    "sg:phone":"+1 508 823 4352",
    "sg:postcode":"02780",
    "sg:province":"MA",
    "sg:tags":[
        "shop",
        "business"
    ],
    "wof:name":"Salon Mystique",
    "wof:placetype":"venue"
},
  "geometry": {"coordinates":[-71.155451,41.921996],"type":"Point"}
}