{
  "type": "Feature",
  "properties": {
    "addr:full":"106 State Rd North Dartmouth MA 02747",
    "addr:housenumber":"106",
    "addr:postcode":"02747",
    "addr:street":"State Rd",
    "iso:country":"US",
    "sg:address":"106 State Rd",
    "sg:city":"North Dartmouth",
    "sg:classifiers":[
        {
            "category":"Real Estate",
            "subcategory":"Real Estate Agent",
            "type":"Services"
        }
    ],
    "sg:phone":"+1 508 993 8045",
    "sg:postcode":"02747",
    "sg:province":"MA",
    "sg:website":"www.ronnieglassman.com",
    "wof:name":"Ronnie Glassman Real Estate",
    "wof:placetype":"venue"
},
  "geometry": {"coordinates":[-70.969585,41.638128],"type":"Point"}
}