{
  "type": "Feature",
  "properties": {
    "iso:country":"US",
    "sg:address":"17 Columbia St",
    "sg:city":"Swampscott",
    "sg:classifiers":[
        {
            "category":"Manufacturing",
            "subcategory":"Electronics",
            "type":"Manufacturing & Wholesale Goods"
        }
    ],
    "sg:phone":"+1 781 592 4600",
    "sg:postcode":"01907",
    "sg:province":"MA",
    "sg:tags":[
        "semiconductor",
        "devices"
    ],
    "wof:name":"Market Place Investors",
    "wof:placetype":"venue"
},
  "geometry": {"coordinates":[-70.924575,42.473052],"type":"Point"}
}