{
  "type": "Feature",
  "properties": {
    "iso:country":"US",
    "sg:address":"97 State St",
    "sg:city":"Shelburne Falls",
    "sg:classifiers":[
        {
            "category":"Building & Trades",
            "subcategory":"Cleaning & Sanitation",
            "type":"Services"
        }
    ],
    "sg:phone":"+1 413 625 2862",
    "sg:postcode":"01370",
    "sg:province":"MA",
    "wof:name":"Mohawk Commercial Cleaning",
    "wof:placetype":"venue"
},
  "geometry": {"coordinates":[-72.741012,42.605014],"type":"Point"}
}