{
  "type": "Feature",
  "properties": {
    "iso:country":"US",
    "sg:address":"580 MacArthur Blvd",
    "sg:city":"Buzzards Bay",
    "sg:classifiers":[
        {
            "category":"Health Services",
            "subcategory":"Dentist",
            "type":"Services"
        }
    ],
    "sg:phone":"+1 508 563 5549",
    "sg:postcode":"02532",
    "sg:province":"MA",
    "wof:name":"Pocasset Dental",
    "wof:placetype":"venue"
},
  "geometry": {"coordinates":[-70.583603,41.706501],"type":"Point"}
}