{
  "type": "Feature",
  "properties": {
    "addr:full": "20 Lydia St Springfield MA 01109",
    "addr:housenumber": "20",
    "addr:postcode": "01109",
    "addr:street": "Lydia St",
    "iso:country": "US",
    "ovtr:label": "Hiram L. Dorman Elementary, 20 Lydia St Springfield MA US",
    "ovtr:similarity": 3.2840631008148193,
    "sg:address": "20 Lydia St",
    "sg:city": "Springfield",
    "sg:classifiers": [
      {
        "category": "Education",
        "subcategory": "School",
        "type": "Public Place"
      }
    ],
    "sg:phone": "+1 413 787 7554",
    "sg:postcode": "01109",
    "sg:province": "MA",
    "sg:tags": [
      "elementary"
    ],
    "sg:website": "http://www.springfieldschoolvolunteers.org",
    "wof:name": "Hiram L Dorman Elementary School",
    "wof:placetype": "venue"
  },
  "geometry": {"coordinates":[-72.539088,42.127751],"type":"Point"}
}
