{
  "type": "Feature",
  "properties": {
    "addr:full":"20 Lydia St Springfield MA 01109",
    "addr:housenumber":"20",
    "addr:postcode":"01109",
    "addr:street":"Lydia St",
    "iso:country":"US",
    "sg:address":"20 Lydia St",
    "sg:city":"Springfield",
    "sg:classifiers":[
        {
            "category":"Education",
            "subcategory":"School",
            "type":"Public Place"
        }
    ],
    "sg:phone":"+1 413 787 7554",
    "sg:postcode":"01109",
    "sg:province":"MA",
    "sg:tags":[
        "elementary"
    ],
    "sg:website":"http://www.springfieldschoolvolunteers.org",
    "wof:name":"Hiram L Dorman Elementary School",
    "wof:placetype":"venue"
},
  "geometry": {"coordinates":[-72.53908800000001,42.127751],"type":"Point"}
}