{
  "type": "Feature",
  "properties": {
    "addr:full": "35 Central St Stoneham MA 02180",
    "addr:housenumber": "35",
    "addr:postcode": "02180",
    "addr:street": "Central St",
    "iso:country": "US",
    "sg:address": "35 Central St",
    "sg:city": "Stoneham",
    "sg:classifiers": [
      {
        "category": "Government",
        "subcategory": "Office",
        "type": "Public Place"
      }
    ],
    "sg:phone": "+1 781 279 2660",
    "sg:postcode": "02180",
    "sg:province": "MA",
    "sg:tags": [
      "city",
      "taxation"
    ],
    "wof:name": "City Tax Collection Ofc",
    "wof:placetype": "venue"
  },
  "geometry": {"coordinates":[-71.098884,42.480663],"type":"Point"}
}
