{
  "type": "Feature",
  "properties": {
    "iso:country":"US",
    "sg:address":"73 Main St",
    "sg:city":"Taunton",
    "sg:classifiers":[
        {
            "category":"Restaurant",
            "type":"Food & Drink"
        }
    ],
    "sg:phone":"+1 508 824 9207",
    "sg:postcode":"02780",
    "sg:province":"MA",
    "sg:tags":[
        "eating"
    ],
    "wof:name":"Main Street Grille & Coffee",
    "wof:placetype":"venue"
},
  "geometry": {"coordinates":[-71.09065200000001,41.901581],"type":"Point"}
}