{
  "type": "Feature",
  "properties": {
    "addr:full": "73 Main St Taunton MA 02780",
    "addr:housenumber": "73",
    "addr:postcode": "02780",
    "addr:street": "Main St",
    "iso:country": "US",
    "sg:address": "73 Main St",
    "sg:city": "Taunton",
    "sg:classifiers": [
      {
        "category": "Restaurant",
        "type": "Food \u0026 Drink"
      }
    ],
    "sg:phone": "+1 508 824 9207",
    "sg:postcode": "02780",
    "sg:province": "MA",
    "sg:tags": [
      "eating"
    ],
    "wof:name": "Main Street Grille \u0026 Coffee",
    "wof:placetype": "venue"
  },
  "geometry": {"coordinates":[-71.090652,41.901581],"type":"Point"}
}
