{
  "type": "Feature",
  "properties": {
    "addr:full":"Faneuil Hall 1 S Market St Boston MA 02109",
    "addr:housenumber":"1",
    "addr:postcode":"02109",
    "addr:street":"S Market St",
    "iso:country":"US",
    "sg:address":"Faneuil Hall 1 S Market St",
    "sg:city":"Boston",
    "sg:classifiers":[
        {
            "category":"Shopping",
            "subcategory":"Clothing, Apparel, & Fashions",
            "type":"Retail Goods"
        }
    ],
    "sg:phone":"+1 617 742 0031",
    "sg:postcode":"02109",
    "sg:province":"MA",
    "sg:tags":[
        "clothing",
        "women's"
    ],
    "sg:website":"www.anntaylor.com",
    "wof:name":"Ann Taylor",
    "wof:placetype":"venue"
},
  "geometry": {"coordinates":[-71.14765300000001,42.358683],"type":"Point"}
}