{
  "type": "Feature",
  "properties": {
    "addr:full":"28 Fowler Ave Revere MA 02151",
    "addr:housenumber":"28",
    "addr:postcode":"02151",
    "addr:street":"Fowler Ave",
    "iso:country":"US",
    "sg:address":"28 Fowler Ave",
    "sg:city":"Revere",
    "sg:classifiers":[
        {
            "category":"Home & Garden",
            "subcategory":"Carpets & Floor Coverings",
            "type":"Retail Goods"
        }
    ],
    "sg:phone":"+1 617 567 9545",
    "sg:postcode":"02151",
    "sg:province":"MA",
    "sg:tags":[
        "installation",
        "rug",
        "dealer"
    ],
    "wof:name":"Butler Flooring Co",
    "wof:placetype":"venue"
},
  "geometry": {"coordinates":[-70.96331000000001,42.440161],"type":"Point"}
}