{
  "type": "Feature",
  "properties": {
    "iso:country":"US",
    "sg:address":"320 Adams St",
    "sg:city":"Dorchester",
    "sg:classifiers":[
        {
            "category":"Professional",
            "subcategory":"Business Services",
            "type":"Services"
        }
    ],
    "sg:phone":"+1 617 436 1800",
    "sg:postcode":"02122",
    "sg:province":"MA",
    "sg:tags":[
        "appraiser"
    ],
    "wof:name":"Luther & Luther Enterprises",
    "wof:placetype":"venue"
},
  "geometry": {"coordinates":[-71.057177,42.298575],"type":"Point"}
}