{
  "type": "Feature",
  "properties": {
    "addr:full": "320 Adams St Dorchester MA 02122",
    "addr:housenumber": "320",
    "addr:postcode": "02122",
    "addr:street": "Adams St",
    "iso:country": "US",
    "sg:address": "320 Adams St",
    "sg:city": "Dorchester",
    "sg:classifiers": [
      {
        "category": "Professional",
        "subcategory": "Business Services",
        "type": "Services"
      }
    ],
    "sg:phone": "+1 617 436 1800",
    "sg:postcode": "02122",
    "sg:province": "MA",
    "sg:tags": [
      "appraiser"
    ],
    "wof:name": "Luther \u0026 Luther Enterprises",
    "wof:placetype": "venue"
  },
  "geometry": {"coordinates":[-71.057177,42.298575],"type":"Point"}
}
