{
  "type": "Feature",
  "properties": {
    "addr:full": "13 Meridian Street Boston MA 02128",
    "addr:housenumber": "13",
    "addr:postcode": "02128",
    "addr:street": "Meridian Street",
    "iso:country": "US",
    "ovtr:label": "Los Arrieros, 13 Meridian St Boston MA US",
    "ovtr:similarity": 2.9288740158081055,
    "sg:address": "13 Meridian Street",
    "sg:city": "Boston",
    "sg:classifiers": [
      {
        "category": "Restaurant",
        "type": "Food \u0026 Drink"
      }
    ],
    "sg:phone": "+1 617 569 1666",
    "sg:postcode": "02128",
    "sg:province": "MA",
    "wof:name": "Los Arrieros",
    "wof:placetype": "venue"
  },
  "geometry": {"coordinates":[-71.039115,42.370468],"type":"Point"}
}
