{
  "type": "Feature",
  "properties": {
    "addr:full": "14 Woods Ln Ipswich MA 01938",
    "addr:housenumber": "14",
    "addr:postcode": "01938",
    "addr:street": "Woods Ln",
    "iso:country": "US",
    "sg:address": "14 Woods Ln",
    "sg:city": "Ipswich",
    "sg:classifiers": [
      {
        "category": "Utilities",
        "subcategory": "Telephone",
        "type": "Services"
      }
    ],
    "sg:phone": "+1   ",
    "sg:postcode": "01938",
    "sg:province": "MA",
    "sg:tags": [
      "communications"
    ],
    "wof:name": "Freemarkets Inc",
    "wof:placetype": "venue"
  },
  "geometry": {"coordinates":[-70.831118,42.677454],"type":"Point"}
}
