{
  "type": "Feature",
  "properties": {
    "addr:full": "26 Gorham Rd Belmont MA 02478",
    "addr:housenumber": "26",
    "addr:postcode": "02478",
    "addr:street": "Gorham Rd",
    "iso:country": "US",
    "sg:address": "26 Gorham Rd",
    "sg:city": "Belmont",
    "sg:classifiers": [
      {
        "category": "Real Estate",
        "subcategory": "Real Estate Services",
        "type": "Services"
      },
      {
        "category": "Real Estate",
        "subcategory": "Real Estate Agent",
        "type": "Services"
      }
    ],
    "sg:phone": "+1 617 489 2980",
    "sg:postcode": "02478",
    "sg:province": "MA",
    "sg:tags": [
      "buyer",
      "broker"
    ],
    "wof:name": "J2 Realty Limited Partnership",
    "wof:placetype": "venue"
  },
  "geometry": {"coordinates":[-71.177261,42.382462],"type":"Point"}
}
