{
  "type": "Feature",
  "properties": {
    "addr:full": "496 Shawmut Ave Boston MA 02118",
    "addr:housenumber": "496",
    "addr:postcode": "02118",
    "addr:street": "Shawmut Ave",
    "iso:country": "US",
    "sg:address": "496 Shawmut Ave",
    "sg:city": "Boston",
    "sg:classifiers": [
      {
        "category": "Building \u0026 Trades",
        "subcategory": "Locksmith",
        "type": "Services"
      }
    ],
    "sg:phone": "+1 617 303 2830",
    "sg:postcode": "02118",
    "sg:province": "MA",
    "sg:tags": [
      "key"
    ],
    "wof:name": "Walnut Locksmith",
    "wof:placetype": "venue"
  },
  "geometry": {"coordinates":[-71.076717,42.338049],"type":"Point"}
}
