{
  "type": "Feature",
  "properties": {
    "iso:country":"US",
    "sg:address":"207 Main St",
    "sg:city":"Kingston",
    "sg:classifiers":[
        {
            "category":"Organizations",
            "subcategory":"Religious Organization",
            "type":"Services"
        }
    ],
    "sg:phone":"+1 781 585 3167",
    "sg:postcode":"02364",
    "sg:province":"MA",
    "sg:tags":[
        "church"
    ],
    "sg:website":"www.mayflowercongregationalchurch.org",
    "wof:name":"Mayflower Congregational Chr",
    "wof:placetype":"venue"
},
  "geometry": {"coordinates":[-70.72778099999999,41.992983],"type":"Point"}
}