{
  "type": "Feature",
  "properties": {
    "addr:full":"1 Intercontinental Way Peabody MA 01960",
    "addr:housenumber":"1",
    "addr:postcode":"01960",
    "addr:street":"Intercontinental Way",
    "iso:country":"US",
    "sg:address":"1 Intercontinental Way",
    "sg:city":"Peabody",
    "sg:classifiers":[
        {
            "category":"Building & Trades",
            "subcategory":"Construction",
            "type":"Services"
        }
    ],
    "sg:phone":"+1 978 536 4370",
    "sg:postcode":"01960",
    "sg:province":"MA",
    "sg:tags":[
        "home",
        "builder"
    ],
    "sg:website":"www.ohcdev.com",
    "wof:name":"OHC Corportation",
    "wof:placetype":"venue"
},
  "geometry": {"coordinates":[-70.98971299999999,42.525071],"type":"Point"}
}