{
  "type": "Feature",
  "properties": {
    "addr:full": "82 Marion Rd Rochester MA 02770",
    "addr:housenumber": "82",
    "addr:postcode": "02770",
    "addr:street": "Marion Rd",
    "iso:country": "US",
    "sg:address": "82 Marion Rd",
    "sg:city": "Rochester",
    "sg:classifiers": [
      {
        "category": "Building \u0026 Trades",
        "subcategory": "Construction",
        "type": "Services"
      }
    ],
    "sg:phone": "+1 508 763 3490",
    "sg:postcode": "02770",
    "sg:province": "MA",
    "sg:tags": [
      "masonry",
      "contractor"
    ],
    "wof:name": "Raymond Noble Mason Contractor",
    "wof:placetype": "venue"
  },
  "geometry": {"coordinates":[-70.80807,41.733388],"type":"Point"}
}
