{
  "type": "Feature",
  "properties": {
    "iso:country":"US",
    "sg:address":"82 Marion Rd",
    "sg:city":"Rochester",
    "sg:classifiers":[
        {
            "category":"Building & Trades",
            "subcategory":"Construction",
            "type":"Services"
        }
    ],
    "sg:phone":"+1 508 763 3490",
    "sg:postcode":"02770",
    "sg:province":"MA",
    "sg:tags":[
        "masonry",
        "contractor"
    ],
    "wof:name":"Raymond Noble Mason Contractor",
    "wof:placetype":"venue"
},
  "geometry": {"coordinates":[-70.80807,41.733388],"type":"Point"}
}