{
  "type": "Feature",
  "properties": {
    "addr:full":"208 Winter St Saugus MA 01906",
    "addr:housenumber":"208",
    "addr:postcode":"01906",
    "addr:street":"Winter St",
    "iso:country":"US",
    "sg:address":"208 Winter St",
    "sg:city":"Saugus",
    "sg:classifiers":[
        {
            "category":"Retail",
            "subcategory":"Auto Repair",
            "type":"Services"
        }
    ],
    "sg:phone":"+1 781 231 3010",
    "sg:postcode":"01906",
    "sg:province":"MA",
    "sg:tags":[
        "body",
        "automobile",
        "painting"
    ],
    "wof:name":"Northeast Autobody",
    "wof:placetype":"venue"
},
  "geometry": {"coordinates":[-71.00831700000001,42.460732],"type":"Point"}
}