{
  "type": "Feature",
  "properties": {
    "addr:full": "448 Great Rd Acton MA 01720",
    "addr:housenumber": "448",
    "addr:postcode": "01720",
    "addr:street": "Great Rd",
    "iso:country": "US",
    "sg:address": "448 Great Rd",
    "sg:city": "Acton",
    "sg:classifiers": [
      {
        "category": "Autos \u0026 Motor Vehicles",
        "subcategory": "Automobile Sales",
        "type": "Retail Goods"
      }
    ],
    "sg:phone": "+1 978 881 0071",
    "sg:postcode": "01720",
    "sg:province": "MA",
    "sg:tags": [
      "car",
      "dealer"
    ],
    "wof:name": "Acton Toyota Used Car Annex",
    "wof:placetype": "venue"
  },
  "geometry": {"coordinates":[-71.424603,42.513236],"type":"Point"}
}
