{
  "type": "Feature",
  "properties": {
    "addr:full":"116 School St Webster MA 01570",
    "addr:housenumber":"116",
    "addr:postcode":"01570",
    "addr:street":"School St",
    "iso:country":"US",
    "sg:address":"116 School St",
    "sg:city":"Webster",
    "sg:classifiers":[
        {
            "category":"Government",
            "subcategory":"Office",
            "type":"Public Place"
        }
    ],
    "sg:phone":"+1 508 949 3845",
    "sg:postcode":"01570",
    "sg:province":"MA",
    "sg:tags":[
        "village"
    ],
    "wof:name":"Webster Senior Ctr",
    "wof:placetype":"venue"
},
  "geometry": {"coordinates":[-71.884259,42.048359],"type":"Point"}
}