{
  "type": "Feature",
  "properties": {
    "addr:full":"3 Myrtle Ave Westford MA 01886",
    "addr:housenumber":"3",
    "addr:postcode":"01886",
    "addr:street":"Myrtle Ave",
    "iso:country":"US",
    "sg:address":"3 Myrtle Ave",
    "sg:city":"Westford",
    "sg:classifiers":[
        {
            "category":"Building & Trades",
            "subcategory":"Electrical",
            "type":"Services"
        }
    ],
    "sg:phone":"+1   ",
    "sg:postcode":"01886",
    "sg:province":"MA",
    "sg:tags":[
        "electrical",
        "contractor"
    ],
    "wof:name":"Hartery Electric",
    "wof:placetype":"venue"
},
  "geometry": {"coordinates":[-71.414661,42.614396],"type":"Point"}
}