{
  "type": "Feature",
  "properties": {
    "iso:country":"US",
    "sg:address":"46 Barrows St",
    "sg:city":"Norton",
    "sg:classifiers":[
        {
            "category":"Building & Trades",
            "subcategory":"Construction",
            "type":"Services"
        }
    ],
    "sg:phone":"+1 508 285 5005",
    "sg:postcode":"02766",
    "sg:province":"MA",
    "sg:tags":[
        "contractor"
    ],
    "wof:name":"Tmg Carpentry - CLOSED",
    "wof:placetype":"venue"
},
  "geometry": {"coordinates":[-71.189598,41.955898],"type":"Point"}
}