{
  "type": "Feature",
  "properties": {
    "iso:country":"US",
    "sg:address":"100 Pond St",
    "sg:city":"Seekonk",
    "sg:classifiers":[
        {
            "category":"Building & Trades",
            "subcategory":"Landscaping Services",
            "type":"Services"
        }
    ],
    "sg:phone":"+1 508 761 6229",
    "sg:postcode":"02771",
    "sg:province":"MA",
    "sg:tags":[
        "tree"
    ],
    "wof:name":"Douglas Tree Svc",
    "wof:placetype":"venue"
},
  "geometry": {"coordinates":[-71.32861200000001,41.897934],"type":"Point"}
}