{
  "type": "Feature",
  "properties": {
    "addr:full": "100 Pond St Seekonk MA 02771",
    "addr:housenumber": "100",
    "addr:postcode": "02771",
    "addr:street": "Pond St",
    "iso:country": "US",
    "sg:address": "100 Pond St",
    "sg:city": "Seekonk",
    "sg:classifiers": [
      {
        "category": "Building \u0026 Trades",
        "subcategory": "Landscaping Services",
        "type": "Services"
      }
    ],
    "sg:phone": "+1 508 761 6229",
    "sg:postcode": "02771",
    "sg:province": "MA",
    "sg:tags": [
      "tree"
    ],
    "wof:name": "Douglas Tree Svc",
    "wof:placetype": "venue"
  },
  "geometry": {"coordinates":[-71.328612,41.897934],"type":"Point"}
}
