{
  "type": "Feature",
  "properties": {
    "addr:full":"1475 Highland St Holliston MA 01746",
    "addr:housenumber":"1475",
    "addr:postcode":"01746",
    "addr:street":"Highland St",
    "iso:country":"US",
    "sg:address":"1475 Highland St",
    "sg:city":"Holliston",
    "sg:classifiers":[
        {
            "category":"Professional",
            "subcategory":"Advertising",
            "type":"Services"
        }
    ],
    "sg:phone":"+1 508 893 6940",
    "sg:postcode":"01746",
    "sg:province":"MA",
    "sg:tags":[
        "counselor"
    ],
    "wof:name":"Industrial Advertising",
    "wof:placetype":"venue"
},
  "geometry": {"coordinates":[-71.43346200000001,42.186397],"type":"Point"}
}