{
  "type": "Feature",
  "properties": {
    "iso:country":"US",
    "sg:address":"7 Elm St",
    "sg:city":"Baldwinville",
    "sg:classifiers":[
        {
            "category":"Food & Beverages",
            "subcategory":"Groceries & Convenience Stores",
            "type":"Retail Goods"
        }
    ],
    "sg:phone":"+1 978 939 2112",
    "sg:postcode":"01436",
    "sg:province":"MA",
    "wof:name":"Elm Street Liquor Corp",
    "wof:placetype":"venue"
},
  "geometry": {"coordinates":[-72.074956,42.608407],"type":"Point"}
}