{
  "type": "Feature",
  "properties": {
    "iso:country":"US",
    "sg:address":"1027 Great Plain Ave",
    "sg:city":"Needham",
    "sg:classifiers":[
        {
            "category":"Restaurant",
            "type":"Food & Drink"
        }
    ],
    "sg:menulink":"http://www.allmenus.com/ma/needham/247499-fava/menu/",
    "sg:phone":"+1 781 455 8668",
    "sg:postcode":"02492",
    "sg:province":"MA",
    "sg:tags":[
        "new",
        "american"
    ],
    "wof:name":"Fava",
    "wof:placetype":"venue"
},
  "geometry": {"coordinates":[-71.23732,42.28024],"type":"Point"}
}