{
  "type": "Feature",
  "properties": {
    "addr:full":"42 High Street Medford MA 02155",
    "addr:housenumber":"42",
    "addr:postcode":"02155",
    "addr:street":"High Street",
    "iso:country":"US",
    "sg:address":"42 High Street",
    "sg:city":"Medford",
    "sg:classifiers":[
        {
            "category":"Professional",
            "subcategory":"Lawyer & Legal Services",
            "type":"Services"
        }
    ],
    "sg:phone":"+1 781 396 6603",
    "sg:postcode":"02155",
    "sg:province":"MA",
    "wof:name":"Kenny Paul Atty",
    "wof:placetype":"venue"
},
  "geometry": {"coordinates":[-71.11084700000001,42.418526],"type":"Point"}
}