{
  "type": "Feature",
  "properties": {
    "iso:country":"US",
    "sg:address":"135 Brooks St",
    "sg:city":"Worcester",
    "sg:classifiers":[
        {
            "category":"Recreation",
            "subcategory":"Amusement Park",
            "type":"Entertainment"
        }
    ],
    "sg:phone":"+1 508 852 2944",
    "sg:postcode":"01606",
    "sg:province":"MA",
    "sg:website":"www.nationalamusements.com",
    "wof:name":"National Amusements Inc",
    "wof:placetype":"venue"
},
  "geometry": {"coordinates":[-71.80193199999999,42.312504],"type":"Point"}
}