{
  "type": "Feature",
  "properties": {
    "addr:full":"386 Walnut Street Ext Agawam MA 01001",
    "addr:housenumber":"386",
    "addr:postcode":"01001",
    "addr:street":"Walnut Street Ext",
    "iso:country":"US",
    "sg:address":"386 Walnut Street Ext",
    "sg:city":"Agawam",
    "sg:classifiers":[
        {
            "category":"Bars & Pubs",
            "type":"Food & Drink"
        },
        {
            "category":"Coffee & Tea",
            "type":"Food & Drink"
        },
        {
            "category":"Restaurant",
            "type":"Food & Drink"
        },
        {
            "category":"Bars & Pubs",
            "subcategory":"Lounge",
            "type":"Food & Drink"
        }
    ],
    "sg:phone":"+1 413 786 0967",
    "sg:postcode":"01001",
    "sg:province":"MA",
    "sg:tags":[
        "grill",
        "espresso",
        "brew",
        "cocktail"
    ],
    "wof:name":"Elbow Cafe",
    "wof:placetype":"venue"
},
  "geometry": {"coordinates":[-72.628563,42.086938],"type":"Point"}
}