{
  "type": "Feature",
  "properties": {
    "iso:country":"US",
    "sg:address":"1769 Riverdale St",
    "sg:city":"West Springfield",
    "sg:classifiers":[
        {
            "category":"Real Estate",
            "subcategory":"Real Estate Operator",
            "type":"Services"
        }
    ],
    "sg:phone":"+1 413 214 7992",
    "sg:postcode":"01089",
    "sg:province":"MA",
    "sg:tags":[
        "building",
        "parks"
    ],
    "wof:name":"Sky View Barns",
    "wof:placetype":"venue"
},
  "geometry": {"coordinates":[-72.63049700000001,42.150229],"type":"Point"}
}