{
  "type": "Feature",
  "properties": {
    "addr:full":"49 Hassey St New Bedford MA 02740",
    "addr:housenumber":"49",
    "addr:postcode":"02740",
    "addr:street":"Hassey St",
    "iso:country":"US",
    "sg:address":"49 Hassey St",
    "sg:city":"New Bedford",
    "sg:classifiers":[
        {
            "category":"Manufacturing",
            "subcategory":"Food",
            "type":"Manufacturing & Wholesale Goods"
        }
    ],
    "sg:phone":"+1 508 996 0242",
    "sg:postcode":"02740",
    "sg:province":"MA",
    "sg:tags":[
        "packer",
        "fish"
    ],
    "wof:name":"Buzzards Bay Trading Co Inc",
    "wof:placetype":"venue"
},
  "geometry": {"coordinates":[-70.916572,41.626448],"type":"Point"}
}