{
  "type": "Feature",
  "properties": {
    "iso:country":"US",
    "sg:address":"303 E Falmouth Hwy",
    "sg:city":"East Falmouth",
    "sg:classifiers":[
        {
            "category":"Building & Trades",
            "subcategory":"Construction",
            "type":"Services"
        }
    ],
    "sg:phone":"+1 508 457 0030",
    "sg:postcode":"02536",
    "sg:province":"MA",
    "sg:tags":[
        "paving",
        "contractor"
    ],
    "wof:name":"Rapoza's Sealcoating",
    "wof:placetype":"venue"
},
  "geometry": {"coordinates":[-70.562819,41.578776],"type":"Point"}
}