{
  "type": "Feature",
  "properties": {
    "addr:full": "3 Centre Pl Boston MA 02124",
    "addr:housenumber": "3",
    "addr:postcode": "02124",
    "addr:street": "Centre Pl",
    "iso:country": "US",
    "sg:address": "3 Centre Pl",
    "sg:city": "Boston",
    "sg:classifiers": [
      {
        "category": "Government",
        "subcategory": "Office",
        "type": "Public Place"
      }
    ],
    "sg:phone": "+1 617 788 6867",
    "sg:postcode": "02124",
    "sg:province": "MA",
    "wof:name": "Sentencing Commission",
    "wof:placetype": "venue"
  },
  "geometry": {"coordinates":[-71.064032,42.293592],"type":"Point"}
}
