{
  "type": "Feature",
  "properties": {
    "addr:full": "600 Charlton St Southbridge MA 01550",
    "addr:housenumber": "600",
    "addr:postcode": "01550",
    "addr:street": "Charlton St",
    "iso:country": "US",
    "sg:address": "600 Charlton St",
    "sg:city": "Southbridge",
    "sg:classifiers": [
      {
        "category": "Professional",
        "subcategory": "Engineering",
        "type": "Services"
      }
    ],
    "sg:phone": "+1 508 765 7755",
    "sg:postcode": "01550",
    "sg:province": "MA",
    "sg:tags": [
      "engineer"
    ],
    "wof:name": "Faist Engineering",
    "wof:placetype": "venue"
  },
  "geometry": {"coordinates":[-72.017499,42.095558],"type":"Point"}
}
