{
  "type": "Feature",
  "properties": {
    "addr:full":"22 Olney St Seekonk MA 02771",
    "addr:housenumber":"22",
    "addr:postcode":"02771",
    "addr:street":"Olney St",
    "iso:country":"US",
    "sg:address":"22 Olney St",
    "sg:city":"Seekonk",
    "sg:classifiers":[
        {
            "category":"Food & Beverages",
            "subcategory":"Meat & Fish",
            "type":"Retail Goods"
        }
    ],
    "sg:phone":"+1 508 336 6671",
    "sg:postcode":"02771",
    "sg:province":"MA",
    "sg:tags":[
        "shop"
    ],
    "wof:name":"Parker's Meat Market",
    "wof:placetype":"venue"
},
  "geometry": {"coordinates":[-71.31880200000001,41.813999],"type":"Point"}
}