{
  "type": "Feature",
  "properties": {
    "addr:full": "687 Highland Ave Needham MA 02494",
    "addr:housenumber": "687",
    "addr:postcode": "02494",
    "addr:street": "Highland Ave",
    "iso:country": "US",
    "sg:address": "687 Highland Ave",
    "sg:city": "Needham",
    "sg:classifiers": [
      {
        "category": "Insurance",
        "subcategory": "Insurance Agent",
        "type": "Services"
      }
    ],
    "sg:phone": "+1 781 449 9393",
    "sg:postcode": "02494",
    "sg:province": "MA",
    "wof:name": "Alan J Ross Insurance",
    "wof:placetype": "venue"
  },
  "geometry": {"coordinates":[-71.231971,42.298811],"type":"Point"}
}
