{
  "type": "Feature",
  "properties": {
    "iso:country":"US",
    "sg:address":"10 Preston Ct",
    "sg:city":"Swampscott",
    "sg:classifiers":[
        {
            "category":"Recreation",
            "type":"Entertainment"
        }
    ],
    "sg:phone":"+1 781 592 3284",
    "sg:postcode":"01907",
    "sg:province":"MA",
    "sg:tags":[
        "tours",
        "sightseeing"
    ],
    "sg:website":"www.dalemyerowassociates.com",
    "wof:name":"Dale Myerow Assoc",
    "wof:placetype":"venue"
},
  "geometry": {"coordinates":[-70.88199299999999,42.477324],"type":"Point"}
}