{
  "type": "Feature",
  "properties": {
    "addr:full": "500 Kendall St Cambridge MA 02142",
    "addr:housenumber": "500",
    "addr:postcode": "02142",
    "addr:street": "Kendall St",
    "iso:country": "US",
    "sg:address": "500 Kendall St",
    "sg:city": "Cambridge",
    "sg:classifiers": [
      {
        "category": "Manufacturing",
        "subcategory": "Chemicals \u0026 Compounds",
        "type": "Manufacturing \u0026 Wholesale Goods"
      },
      {
        "category": "Wholesale",
        "subcategory": "Medical Equipment \u0026 Supplies",
        "type": "Manufacturing \u0026 Wholesale Goods"
      }
    ],
    "sg:phone": "+1 617 252 7500",
    "sg:postcode": "02142",
    "sg:province": "MA",
    "sg:tags": [
      "pharmaceutical",
      "product",
      "products-wholesale",
      "manufacturer"
    ],
    "sg:website": "http://www.genzymediagnostics.com",
    "wof:name": "Genzyme Therapeutics Division",
    "wof:placetype": "venue"
  },
  "geometry": {"coordinates":[-71.081925,42.36371],"type":"Point"}
}
