{
  "type": "Feature",
  "properties": {
    "iso:country":"US",
    "sg:address":"900 Cummings Ctr Ste 109U",
    "sg:city":"Beverly",
    "sg:classifiers":[
        {
            "category":"Health Services",
            "subcategory":"Podiatrist",
            "type":"Services"
        }
    ],
    "sg:phone":"+1 978 927 1911",
    "sg:postcode":"01915",
    "sg:province":"MA",
    "sg:tags":[
        "physician",
        "surgeons"
    ],
    "wof:name":"Beverly Podiatry",
    "wof:placetype":"venue"
},
  "geometry": {"coordinates":[-70.88696,42.560454],"type":"Point"}
}