{
  "type": "Feature",
  "properties": {
    "addr:full":"76 Nashoba Rd Littleton MA 01460",
    "addr:housenumber":"76",
    "addr:postcode":"01460",
    "addr:street":"Nashoba Rd",
    "iso:country":"US",
    "sg:address":"76 Nashoba Rd",
    "sg:city":"Littleton",
    "sg:classifiers":[
        {
            "category":"Wholesale",
            "subcategory":"Office Equipment",
            "type":"Manufacturing & Wholesale Goods"
        }
    ],
    "sg:phone":"+1 617 367 8556",
    "sg:postcode":"01460",
    "sg:province":"MA",
    "sg:tags":[
        "refinish",
        "equipment-repair",
        "furniture"
    ],
    "wof:name":"New England Business Machine",
    "wof:placetype":"venue"
},
  "geometry": {"coordinates":[-71.44618199999999,42.519039],"type":"Point"}
}