{
  "type": "Feature",
  "properties": {
    "iso:country":"US",
    "sg:address":"313 Eastern Ave",
    "sg:city":"Springfield",
    "sg:classifiers":[
        {
            "category":"Building & Trades",
            "subcategory":"Construction",
            "type":"Services"
        }
    ],
    "sg:phone":"+1 413 732 0039",
    "sg:postcode":"01109",
    "sg:province":"MA",
    "sg:tags":[
        "general",
        "contractor"
    ],
    "wof:name":"H & L Construction",
    "wof:placetype":"venue"
},
  "geometry": {"coordinates":[-72.56211399999999,42.102206],"type":"Point"}
}