{
  "type": "Feature",
  "properties": {
    "addr:full": "313 Eastern Ave Springfield MA 01109",
    "addr:housenumber": "313",
    "addr:postcode": "01109",
    "addr:street": "Eastern Ave",
    "iso:country": "US",
    "sg:address": "313 Eastern Ave",
    "sg:city": "Springfield",
    "sg:classifiers": [
      {
        "category": "Building \u0026 Trades",
        "subcategory": "Construction",
        "type": "Services"
      }
    ],
    "sg:phone": "+1 413 732 0039",
    "sg:postcode": "01109",
    "sg:province": "MA",
    "sg:tags": [
      "general",
      "contractor"
    ],
    "wof:name": "H \u0026 L Construction",
    "wof:placetype": "venue"
  },
  "geometry": {"coordinates":[-72.562114,42.102206],"type":"Point"}
}
