{
  "type": "Feature",
  "properties": {
    "iso:country":"US",
    "sg:address":"158 Main St",
    "sg:city":"Norfolk",
    "sg:classifiers":[
        {
            "category":"Personal",
            "type":"Services"
        }
    ],
    "sg:phone":"+1 508 528 2888",
    "sg:postcode":"02056",
    "sg:province":"MA",
    "sg:tags":[
        "therapist",
        "massage"
    ],
    "wof:name":"American Skin Care",
    "wof:placetype":"venue"
},
  "geometry": {"coordinates":[-71.32702999999999,42.119323],"type":"Point"}
}