{
  "type": "Feature",
  "properties": {
    "addr:full":"1 James St Peabody MA 01960",
    "addr:housenumber":"1",
    "addr:postcode":"01960",
    "addr:street":"James St",
    "iso:country":"US",
    "sg:address":"1 James St",
    "sg:city":"Peabody",
    "sg:classifiers":[
        {
            "category":"Social Services",
            "type":"Services"
        }
    ],
    "sg:phone":"+1 978 532 5127",
    "sg:postcode":"01960",
    "sg:province":"MA",
    "sg:tags":[
        "youth",
        "organization",
        "center"
    ],
    "wof:name":"Peabody Little League",
    "wof:placetype":"venue"
},
  "geometry": {"coordinates":[-70.938609,42.527453],"type":"Point"}
}