{
  "type": "Feature",
  "properties": {
    "iso:country":"US",
    "sg:address":"12 Station St",
    "sg:city":"Charlton",
    "sg:classifiers":[
        {
            "category":"Restaurant",
            "type":"Food & Drink"
        }
    ],
    "sg:phone":"+1 508 248 9771",
    "sg:postcode":"01568",
    "sg:province":"MA",
    "wof:name":"Nana Eleanors",
    "wof:placetype":"venue"
},
  "geometry": {"coordinates":[-71.602386,42.167872],"type":"Point"}
}