{
  "type": "Feature",
  "properties": {
    "iso:country":"US",
    "sg:address":"1198 State Hwy 28",
    "sg:city":"South Yarmouth",
    "sg:classifiers":[
        {
            "category":"Personal",
            "subcategory":"Beauty Salon",
            "type":"Services"
        }
    ],
    "sg:phone":"+1 508 760 5959",
    "sg:postcode":"02664",
    "sg:province":"MA",
    "sg:tags":[
        "manicuring"
    ],
    "wof:name":"Best Nails",
    "wof:placetype":"venue"
},
  "geometry": {"coordinates":[-70.193978,41.665367],"type":"Point"}
}