{
  "type": "Feature",
  "properties": {
    "addr:full":"8 State St Haverhill MA 01832",
    "addr:housenumber":"8",
    "addr:postcode":"01832",
    "addr:street":"State St",
    "iso:country":"US",
    "sg:address":"8 State St",
    "sg:city":"Haverhill",
    "sg:classifiers":[
        {
            "category":"Building & Trades",
            "subcategory":"Construction",
            "type":"Services"
        }
    ],
    "sg:phone":"+1   ",
    "sg:postcode":"01832",
    "sg:province":"MA",
    "sg:tags":[
        "house"
    ],
    "wof:name":"Ashworth Const",
    "wof:placetype":"venue"
},
  "geometry": {"coordinates":[-71.12441200000001,42.774792],"type":"Point"}
}