{
  "type": "Feature",
  "properties": {
    "iso:country":"US",
    "sg:address":"714 W Falmouth Hwy",
    "sg:city":"Falmouth",
    "sg:classifiers":[
        {
            "category":"Autos & Motor Vehicles",
            "subcategory":"Fuel & Gas Station",
            "type":"Retail Goods"
        }
    ],
    "sg:phone":"+1 508 548 9797",
    "sg:postcode":"02540",
    "sg:province":"MA",
    "wof:name":"West Falmouth Getty",
    "wof:placetype":"venue"
},
  "geometry": {"coordinates":[-70.630501,41.608898],"type":"Point"}
}