{
  "type": "Feature",
  "properties": {
    "addr:full": "2145 Iyannough Rd West Barnstable MA 02668",
    "addr:housenumber": "2145",
    "addr:postcode": "02668",
    "addr:street": "Iyannough Rd",
    "iso:country": "US",
    "sg:address": "2145 Iyannough Rd",
    "sg:city": "West Barnstable",
    "sg:classifiers": [
      {
        "category": "Restaurant",
        "type": "Food \u0026 Drink"
      }
    ],
    "sg:menulink": "http://www.allmenus.com/ma/barnstable-town/131810-subway/menu/",
    "sg:phone": "+1 508 362 3700",
    "sg:postcode": "02668",
    "sg:province": "MA",
    "sg:tags": [
      "american",
      "sandwich"
    ],
    "wof:name": "Subway",
    "wof:placetype": "venue"
  },
  "geometry": {"coordinates":[-70.338106,41.689052],"type":"Point"}
}
