{
  "type": "Feature",
  "properties": {
    "addr:full":"51 Huntington Rd Worthington MA 01098",
    "addr:housenumber":"51",
    "addr:postcode":"01098",
    "addr:street":"Huntington Rd",
    "iso:country":"US",
    "sg:address":"51 Huntington Rd",
    "sg:city":"Worthington",
    "sg:classifiers":[
        {
            "category":"Government",
            "subcategory":"Fire Station",
            "type":"Public Place"
        }
    ],
    "sg:phone":"+1 413 238 4445",
    "sg:postcode":"01098",
    "sg:province":"MA",
    "sg:tags":[
        "department"
    ],
    "wof:name":"Worthington Fire Dept",
    "wof:placetype":"venue"
},
  "geometry": {"coordinates":[-72.938216,42.40405],"type":"Point"}
}