{
  "type": "Feature",
  "properties": {
    "addr:full": "1800 W Park Dr Westborough MA 01581",
    "addr:housenumber": "1800",
    "addr:postcode": "01581",
    "addr:street": "W Park Dr",
    "iso:country": "US",
    "sg:address": "1800 W Park Dr",
    "sg:city": "Westborough",
    "sg:classifiers": [
      {
        "category": "Museum",
        "type": "Entertainment"
      }
    ],
    "sg:phone": "+1 508 366 6175",
    "sg:postcode": "01581",
    "sg:province": "MA",
    "wof:name": "Turn On Media",
    "wof:placetype": "venue"
  },
  "geometry": {"coordinates":[-71.573841,42.287025],"type":"Point"}
}
