{
  "type": "Feature",
  "properties": {
    "addr:full": "45 School St Fl 5 Boston MA 02108",
    "addr:housenumber": "45;5",
    "addr:postcode": "02108",
    "addr:street": "School St",
    "iso:country": "US",
    "sg:address": "45 School St Fl 5",
    "sg:city": "Boston",
    "sg:classifiers": [
      {
        "category": "Organizations",
        "subcategory": "Non-profit Organization",
        "type": "Services"
      }
    ],
    "sg:phone": "+1 617 523 1635",
    "sg:postcode": "02108",
    "sg:province": "MA",
    "sg:tags": [
      "charity",
      "foundations-educational",
      "philanthropic",
      "research"
    ],
    "wof:name": "Wesley Weyman 755211000",
    "wof:placetype": "venue"
  },
  "geometry": {"coordinates":[-71.059464,42.357712],"type":"Point"}
}
