{
  "type": "Feature",
  "properties": {
    "iso:country":"US",
    "sg:address":"220 Bridge Rd",
    "sg:city":"Eastham",
    "sg:classifiers":[
        {
            "category":"Travel",
            "subcategory":"Hotels & Motels",
            "type":"Entertainment"
        }
    ],
    "sg:phone":"+1 508 255 0617",
    "sg:postcode":"02642",
    "sg:province":"MA",
    "sg:tags":[
        "breakfast",
        "accommodation",
        "bed"
    ],
    "sg:website":"www.whalewalkinn.com",
    "wof:name":"Whalewalk Inn",
    "wof:placetype":"venue"
},
  "geometry": {"coordinates":[-69.992547,41.801233],"type":"Point"}
}