{
  "type": "Feature",
  "properties": {
    "addr:full": "220 Bridge Rd Eastham MA 02642",
    "addr:housenumber": "220",
    "addr:postcode": "02642",
    "addr:street": "Bridge Rd",
    "iso:country": "US",
    "sg:address": "220 Bridge Rd",
    "sg:city": "Eastham",
    "sg:classifiers": [
      {
        "category": "Travel",
        "subcategory": "Hotels \u0026 Motels",
        "type": "Entertainment"
      }
    ],
    "sg:phone": "+1 508 255 0617",
    "sg:postcode": "02642",
    "sg:province": "MA",
    "sg:tags": [
      "breakfast",
      "accommodation",
      "bed"
    ],
    "sg:website": "www.whalewalkinn.com",
    "wof:name": "Whalewalk Inn",
    "wof:placetype": "venue"
  },
  "geometry": {"coordinates":[-69.992547,41.801233],"type":"Point"}
}
