{
  "type": "Feature",
  "properties": {
    "addr:full": "18 Dundee Park Dr Andover MA 01810",
    "addr:housenumber": "18",
    "addr:postcode": "01810",
    "addr:street": "Dundee Park Dr",
    "iso:country": "US",
    "sg:address": "18 Dundee Park Dr",
    "sg:city": "Andover",
    "sg:classifiers": [
      {
        "category": "Organizations",
        "subcategory": "Non-profit Organization",
        "type": "Services"
      }
    ],
    "sg:phone": "+1 978 470 2405",
    "sg:postcode": "01810",
    "sg:province": "MA",
    "wof:name": "Neighbors In Need",
    "wof:placetype": "venue"
  },
  "geometry": {"coordinates":[-71.14567,42.655421],"type":"Point"}
}
