{
  "type": "Feature",
  "properties": {
    "addr:full": "96 Central St Holliston MA 01746",
    "addr:housenumber": "96",
    "addr:postcode": "01746",
    "addr:street": "Central St",
    "iso:country": "US",
    "sg:address": "96 Central St",
    "sg:city": "Holliston",
    "sg:classifiers": [
      {
        "category": "Shopping",
        "subcategory": "Stationery \u0026 Office Supplies",
        "type": "Retail Goods"
      }
    ],
    "sg:phone": "+1 508 429 2299",
    "sg:postcode": "01746",
    "sg:province": "MA",
    "sg:tags": [
      "stationer"
    ],
    "wof:name": "Village Stationery \u0026 Gift Shop",
    "wof:placetype": "venue"
  },
  "geometry": {"coordinates":[-71.425852,42.200115],"type":"Point"}
}
