{
  "type": "Feature",
  "properties": {
    "iso:country":"US",
    "sg:address":"96 Central St",
    "sg:city":"Holliston",
    "sg:classifiers":[
        {
            "category":"Shopping",
            "subcategory":"Stationery & Office Supplies",
            "type":"Retail Goods"
        }
    ],
    "sg:phone":"+1 508 429 2299",
    "sg:postcode":"01746",
    "sg:province":"MA",
    "sg:tags":[
        "stationer"
    ],
    "wof:name":"Village Stationery & Gift Shop",
    "wof:placetype":"venue"
},
  "geometry": {"coordinates":[-71.42585200000001,42.200115],"type":"Point"}
}