{
  "type": "Feature",
  "properties": {
    "addr:full": "760 Chief Justice Cushing Hwy Cohasset MA 02025",
    "addr:housenumber": "760",
    "addr:postcode": "02025",
    "addr:street": "Chief Justice Cushing Hwy",
    "iso:country": "US",
    "sg:address": "760 Chief Justice Cushing Hwy",
    "sg:city": "Cohasset",
    "sg:classifiers": [
      {
        "category": "Insurance",
        "subcategory": "Insurance Agent",
        "type": "Services"
      }
    ],
    "sg:phone": "+1 781 383 1844",
    "sg:postcode": "02025",
    "sg:province": "MA",
    "wof:name": "Hanson Insurance",
    "wof:placetype": "venue"
  },
  "geometry": {"coordinates":[-70.804068,42.223248],"type":"Point"}
}
