{
  "type": "Feature",
  "properties": {
    "iso:country":"US",
    "sg:address":"490 Main St",
    "sg:city":"Wilmington",
    "sg:classifiers":[
        {
            "category":"Autos & Motor Vehicles",
            "subcategory":"Fuel & Gas Station",
            "type":"Retail Goods"
        }
    ],
    "sg:phone":"+1 978 988 9225",
    "sg:postcode":"01887",
    "sg:province":"MA",
    "sg:tags":[
        "oil"
    ],
    "wof:name":"Sabi's Gas Station",
    "wof:placetype":"venue"
},
  "geometry": {"coordinates":[-71.172202,42.545113],"type":"Point"}
}