{
  "type": "Feature",
  "properties": {
    "iso:country":"US",
    "sg:address":"47 Main St",
    "sg:city":"Orleans",
    "sg:classifiers":[
        {
            "category":"Shopping",
            "subcategory":"Clothing, Apparel, & Fashions",
            "type":"Retail Goods"
        }
    ],
    "sg:phone":"+1 508 255 2972",
    "sg:postcode":"02653",
    "sg:province":"MA",
    "wof:name":"Scott/Norman Realty Trust",
    "wof:placetype":"venue"
},
  "geometry": {"coordinates":[-69.990247,41.786764],"type":"Point"}
}