{
  "type": "Feature",
  "properties": {
    "addr:full": "3 Industrial Way Wilmington MA 01887",
    "addr:housenumber": "3",
    "addr:postcode": "01887",
    "addr:street": "Industrial Way",
    "iso:country": "US",
    "sg:address": "3 Industrial Way",
    "sg:city": "Wilmington",
    "sg:classifiers": [
      {
        "category": "Manufacturing",
        "subcategory": "Printing",
        "type": "Manufacturing \u0026 Wholesale Goods"
      }
    ],
    "sg:phone": "+1 781 935 8154",
    "sg:postcode": "01887",
    "sg:province": "MA",
    "sg:tags": [
      "publisher"
    ],
    "wof:name": "Zbr Publications",
    "wof:placetype": "venue"
  },
  "geometry": {"coordinates":[-71.141529,42.529591],"type":"Point"}
}
