{
  "type": "Feature",
  "properties": {
    "addr:full":"3 Industrial Way Wilmington MA 01887",
    "addr:housenumber":"3",
    "addr:postcode":"01887",
    "addr:street":"Industrial Way",
    "iso:country":"US",
    "sg:address":"3 Industrial Way",
    "sg:city":"Wilmington",
    "sg:classifiers":[
        {
            "category":"Manufacturing",
            "subcategory":"Printing",
            "type":"Manufacturing & Wholesale Goods"
        }
    ],
    "sg:phone":"+1 781 935 8154",
    "sg:postcode":"01887",
    "sg:province":"MA",
    "sg:tags":[
        "publisher"
    ],
    "wof:name":"Zbr Publications",
    "wof:placetype":"venue"
},
  "geometry": {"coordinates":[-71.14152900000001,42.529591],"type":"Point"}
}