{
  "type": "Feature",
  "properties": {
    "addr:full": "204 Aspinwall Avenue #2 Brookline MA 02446",
    "addr:housenumber": "204",
    "addr:postcode": "02446",
    "addr:street": "Aspinwall Avenue # 2",
    "iso:country": "US",
    "sg:address": "204 Aspinwall Avenue #2",
    "sg:city": "Brookline",
    "sg:classifiers": [
      {
        "category": "Education",
        "subcategory": "Music School",
        "type": "Public Place"
      }
    ],
    "sg:phone": "+1 617 596 2183",
    "sg:postcode": "02446",
    "sg:province": "MA",
    "sg:tags": [
      "instrument",
      "teacher",
      "musical"
    ],
    "wof:name": "Montse Mias",
    "wof:placetype": "venue"
  },
  "geometry": {"coordinates":[-71.11461,42.336412],"type":"Point"}
}
