{
  "type": "Feature",
  "properties": {
    "iso:country":"US",
    "sg:address":"1157 Grafton St",
    "sg:city":"Worcester",
    "sg:classifiers":[
        {
            "category":"Retail",
            "subcategory":"Repair Shop",
            "type":"Services"
        }
    ],
    "sg:phone":"+1   ",
    "sg:postcode":"01604",
    "sg:province":"MA",
    "sg:tags":[
        "refrigeration"
    ],
    "wof:name":"Campanales Refrigertation",
    "wof:placetype":"venue"
},
  "geometry": {"coordinates":[-71.75356600000001,42.240356],"type":"Point"}
}