{
  "type": "Feature",
  "properties": {
    "addr:full":"1266 Furnace Brook Pkwy Quincy MA 02169",
    "addr:housenumber":"1266",
    "addr:postcode":"02169",
    "addr:street":"Furnace Brook Pkwy",
    "iso:country":"US",
    "sg:address":"1266 Furnace Brook Pkwy",
    "sg:city":"Quincy",
    "sg:classifiers":[
        {
            "category":"Insurance",
            "subcategory":"Insurance Agent",
            "type":"Services"
        }
    ],
    "sg:phone":"+1 617 479 7621",
    "sg:postcode":"02169",
    "sg:province":"MA",
    "wof:name":"Kelleher & Mackey Insurance",
    "wof:placetype":"venue"
},
  "geometry": {"coordinates":[-71.025014,42.244209],"type":"Point"}
}