{
  "type": "Feature",
  "properties": {
    "iso:country":"US",
    "sg:address":"32 Elm St",
    "sg:city":"Worcester",
    "sg:classifiers":[
        {
            "category":"Professional",
            "subcategory":"Lawyer & Legal Services",
            "type":"Services"
        }
    ],
    "sg:phone":"+1 508 792 3360",
    "sg:postcode":"01609",
    "sg:province":"MA",
    "sg:tags":[
        "attorney"
    ],
    "wof:name":"Philip Soloperto Law Offices",
    "wof:placetype":"venue"
},
  "geometry": {"coordinates":[-71.80556300000001,42.265128],"type":"Point"}
}