{
  "type": "Feature",
  "properties": {
    "iso:country":"US",
    "sg:address":"21 Crystal Dr",
    "sg:city":"Stoneham",
    "sg:classifiers":[
        {
            "category":"Real Estate",
            "subcategory":"Real Estate Services",
            "type":"Services"
        },
        {
            "category":"Real Estate",
            "subcategory":"Real Estate Agent",
            "type":"Services"
        }
    ],
    "sg:phone":"+1 781 438 7623",
    "sg:postcode":"02180",
    "sg:province":"MA",
    "sg:tags":[
        "buyer",
        "broker"
    ],
    "wof:name":"Paicopolos Realty",
    "wof:placetype":"venue"
},
  "geometry": {"coordinates":[-71.07674799999999,42.485098],"type":"Point"}
}