{
  "type": "Feature",
  "properties": {
    "addr:full": "419 Neponset St Canton MA 02021",
    "addr:housenumber": "419",
    "addr:postcode": "02021",
    "addr:street": "Neponset St",
    "iso:country": "US",
    "sg:address": "419 Neponset St",
    "sg:city": "Canton",
    "sg:classifiers": [
      {
        "category": "Shopping",
        "type": "Retail Goods"
      }
    ],
    "sg:phone": "+1 781 828 8897",
    "sg:postcode": "02021",
    "sg:province": "MA",
    "sg:tags": [
      "trophy",
      "medal",
      "award"
    ],
    "wof:name": "Canton Trophies \u0026 Awards",
    "wof:placetype": "venue"
  },
  "geometry": {"coordinates":[-71.157021,42.161185],"type":"Point"}
}
