{
  "type": "Feature",
  "properties": {
    "iso:country":"US",
    "sg:address":"606 Washington St",
    "sg:city":"South Easton",
    "sg:classifiers":[
        {
            "category":"Banks & Credit Unions",
            "subcategory":"Bank",
            "type":"Services"
        }
    ],
    "sg:phone":"+1 508 205 6001",
    "sg:postcode":"02375",
    "sg:province":"MA",
    "sg:tags":[
        "loan",
        "real estate"
    ],
    "wof:name":"Summit Mortgage",
    "wof:placetype":"venue"
},
  "geometry": {"coordinates":[-71.08039599999999,42.04624],"type":"Point"}
}