{
  "type": "Feature",
  "properties": {
    "addr:full": "606 Washington St South Easton MA 02375",
    "addr:housenumber": "606",
    "addr:postcode": "02375",
    "addr:street": "Washington St",
    "iso:country": "US",
    "sg:address": "606 Washington St",
    "sg:city": "South Easton",
    "sg:classifiers": [
      {
        "category": "Banks \u0026 Credit Unions",
        "subcategory": "Bank",
        "type": "Services"
      }
    ],
    "sg:phone": "+1 508 205 6001",
    "sg:postcode": "02375",
    "sg:province": "MA",
    "sg:tags": [
      "loan",
      "real estate"
    ],
    "wof:name": "Summit Mortgage",
    "wof:placetype": "venue"
  },
  "geometry": {"coordinates":[-71.080396,42.04624],"type":"Point"}
}
