{
  "type": "Feature",
  "properties": {
    "iso:country":"US",
    "sg:address":"1277 Liberty St",
    "sg:city":"Springfield",
    "sg:classifiers":[
        {
            "category":"Banks & Credit Unions",
            "subcategory":"Bank",
            "type":"Services"
        }
    ],
    "sg:phone":"+1 413 788 0074",
    "sg:postcode":"01104",
    "sg:province":"MA",
    "wof:name":"Citizens Bank",
    "wof:placetype":"venue"
},
  "geometry": {"coordinates":[-72.583468,42.136962],"type":"Point"}
}