{
  "type": "Feature",
  "properties": {
    "addr:full": "346 Newbury St Boston MA 02115",
    "addr:housenumber": "346",
    "addr:postcode": "02115",
    "addr:street": "Newbury St",
    "iso:country": "US",
    "ovtr:label": "Patagonia, 346 Newbury St Boston MA US",
    "ovtr:similarity": 2.3740720748901367,
    "sg:address": "346 Newbury St",
    "sg:city": "Boston",
    "sg:classifiers": [
      {
        "category": "Shopping",
        "subcategory": "Clothing, Apparel, \u0026 Fashions",
        "type": "Retail Goods"
      },
      {
        "category": "Sports \u0026 Exercise",
        "subcategory": "Bicycle Rental",
        "type": "Entertainment"
      },
      {
        "category": "Shopping",
        "subcategory": "Bicycles \u0026 Sporting Goods",
        "type": "Retail Goods"
      }
    ],
    "sg:phone": "+1 617 424 1776",
    "sg:postcode": "02115",
    "sg:province": "MA",
    "sg:tags": [
      "outdoor",
      "gear",
      "sportswear",
      "accessory",
      "wear",
      "apparel",
      "women's",
      "clothing",
      "store"
    ],
    "sg:website": "www.patagonia.com",
    "wof:name": "Patagonia",
    "wof:placetype": "venue"
  },
  "geometry": {"coordinates":[-71.087799,42.348301],"type":"Point"}
}
