{
  "type": "Feature",
  "properties": {
    "addr:full":"87 Lake St Arlington MA 02474",
    "addr:housenumber":"87",
    "addr:postcode":"02474",
    "addr:street":"Lake St",
    "iso:country":"US",
    "sg:address":"87 Lake St",
    "sg:city":"Arlington",
    "sg:classifiers":[
        {
            "category":"Shopping",
            "subcategory":"Computers & Home Electronics",
            "type":"Retail Goods"
        }
    ],
    "sg:phone":"+1   ",
    "sg:postcode":"02474",
    "sg:province":"MA",
    "wof:name":"Advanced Mobile Audio",
    "wof:placetype":"venue"
},
  "geometry": {"coordinates":[-71.148354,42.404199],"type":"Point"}
}