{
  "type": "Feature",
  "properties": {
    "iso:country":"US",
    "sg:address":"47 Parker St",
    "sg:city":"Gloucester",
    "sg:classifiers":[
        {
            "category":"Recreation",
            "type":"Entertainment"
        }
    ],
    "sg:phone":"+1 978 283 9555",
    "sg:postcode":"01930",
    "sg:province":"MA",
    "sg:tags":[
        "charter",
        "boat"
    ],
    "wof:name":"Lattudes",
    "wof:placetype":"venue"
},
  "geometry": {"coordinates":[-70.65037599999999,42.615403],"type":"Point"}
}