{
  "type": "Feature",
  "properties": {
    "addr:full": "2 Birch Dr Harwich MA 02645",
    "addr:housenumber": "2",
    "addr:postcode": "02645",
    "addr:street": "Birch Dr",
    "iso:country": "US",
    "ovtr:label": "Pleasant Lake Farm, 2 Birch Dr Harwich MA US",
    "ovtr:similarity": 2.5991129875183105,
    "sg:address": "2 Birch Dr",
    "sg:city": "Harwich",
    "sg:classifiers": [
      {
        "category": "Farming",
        "subcategory": "Farm",
        "type": "Manufacturing \u0026 Wholesale Goods"
      }
    ],
    "sg:phone": "+1 508 432 3557",
    "sg:postcode": "02645",
    "sg:province": "MA",
    "wof:name": "Pleasant Lake Farm",
    "wof:placetype": "venue"
  },
  "geometry": {"coordinates":[-70.101341,41.709881],"type":"Point"}
}
