{
  "type": "Feature",
  "properties": {
    "iso:country":"US",
    "sg:address":"120 Prescott St",
    "sg:city":"Worcester",
    "sg:classifiers":[
        {
            "category":"Manufacturing",
            "subcategory":"Building Materials",
            "type":"Manufacturing & Wholesale Goods"
        }
    ],
    "sg:phone":"+1 508 753 2943",
    "sg:postcode":"01605",
    "sg:province":"MA",
    "sg:tags":[
        "equipment",
        "supply",
        "roofing"
    ],
    "wof:name":"Beacon Sales Acquisition, Inc.",
    "wof:placetype":"venue"
},
  "geometry": {"coordinates":[-71.79962500000001,42.278207],"type":"Point"}
}