{
  "type": "Feature",
  "properties": {
    "iso:country":"US",
    "sg:address":"362A Yarmouth Rd",
    "sg:city":"Hyannis",
    "sg:classifiers":[
        {
            "category":"Autos & Motor Vehicles",
            "subcategory":"Motorcycle Sales",
            "type":"Retail Goods"
        }
    ],
    "sg:phone":"+1 508 771 5252",
    "sg:postcode":"02601",
    "sg:province":"MA",
    "wof:name":"Scott's Cycle",
    "wof:placetype":"venue"
},
  "geometry": {"coordinates":[-70.273071,41.664157],"type":"Point"}
}