{
  "type": "Feature",
  "properties": {
    "iso:country":"US",
    "sg:address":"250 E Main St",
    "sg:city":"Norton",
    "sg:classifiers":[
        {
            "category":"Real Estate",
            "subcategory":"Real Estate Services",
            "type":"Services"
        },
        {
            "category":"Banks & Credit Unions",
            "subcategory":"Financial Services",
            "type":"Services"
        }
    ],
    "sg:phone":"+1 800 794 3434",
    "sg:postcode":"02766",
    "sg:province":"MA",
    "sg:tags":[
        "loan",
        "mortgage"
    ],
    "wof:name":"Equitable Funding Corp Toll Free-Dial '1' & Then",
    "wof:placetype":"venue"
},
  "geometry": {"coordinates":[-71.21790300000001,41.954529],"type":"Point"}
}