{
  "type": "Feature",
  "properties": {
    "addr:full": "250 E Main St Norton MA 02766",
    "addr:housenumber": "250",
    "addr:postcode": "02766",
    "addr:street": "E Main St",
    "iso:country": "US",
    "sg:address": "250 E Main St",
    "sg:city": "Norton",
    "sg:classifiers": [
      {
        "category": "Real Estate",
        "subcategory": "Real Estate Services",
        "type": "Services"
      },
      {
        "category": "Banks \u0026 Credit Unions",
        "subcategory": "Financial Services",
        "type": "Services"
      }
    ],
    "sg:phone": "+1 800 794 3434",
    "sg:postcode": "02766",
    "sg:province": "MA",
    "sg:tags": [
      "loan",
      "mortgage"
    ],
    "wof:name": "Equitable Funding Corp Toll Free-Dial '1' \u0026 Then",
    "wof:placetype": "venue"
  },
  "geometry": {"coordinates":[-71.217903,41.954529],"type":"Point"}
}
