{
  "type": "Feature",
  "properties": {
    "addr:full":"172 Green St Stoneham MA 02180",
    "addr:housenumber":"172",
    "addr:postcode":"02180",
    "addr:street":"Green St",
    "iso:country":"US",
    "sg:address":"172 Green St",
    "sg:city":"Stoneham",
    "sg:classifiers":[
        {
            "category":"Real Estate",
            "subcategory":"Real Estate Services",
            "type":"Services"
        },
        {
            "category":"Building & Trades",
            "subcategory":"Cleaning & Sanitation",
            "type":"Services"
        }
    ],
    "sg:phone":"+1 781 438 8851",
    "sg:postcode":"02180",
    "sg:province":"MA",
    "sg:tags":[
        "maintenance",
        "cleaners-interior"
    ],
    "wof:name":"Xcel Cleaning & Maintenance",
    "wof:placetype":"venue"
},
  "geometry": {"coordinates":[-71.08628400000001,42.487168],"type":"Point"}
}