{
  "type": "Feature",
  "properties": {
    "addr:full":"29 Shaume Rd North Falmouth MA 02556",
    "addr:housenumber":"29",
    "addr:postcode":"02556",
    "addr:street":"Shaume Rd",
    "iso:country":"US",
    "sg:address":"29 Shaume Rd",
    "sg:city":"North Falmouth",
    "sg:classifiers":[
        {
            "category":"Building & Trades",
            "subcategory":"Electrical",
            "type":"Services"
        }
    ],
    "sg:phone":"+1 508 540 6557",
    "sg:postcode":"02556",
    "sg:province":"MA",
    "sg:tags":[
        "telecommunication",
        "contractor"
    ],
    "wof:name":"Corriveau & Assoc Inc",
    "wof:placetype":"venue"
},
  "geometry": {"coordinates":[-70.633276,41.625621],"type":"Point"}
}