{
  "type": "Feature",
  "properties": {
    "addr:full":"163 Gore Street Cambridge MA 02141",
    "addr:housenumber":"163",
    "addr:postcode":"02141",
    "addr:street":"Gore Street",
    "iso:country":"US",
    "sg:address":"163 Gore Street",
    "sg:city":"Cambridge",
    "sg:classifiers":[
        {
            "category":"Health Services",
            "subcategory":"Doctor",
            "type":"Services"
        },
        {
            "category":"Health Services",
            "subcategory":"Hospital",
            "type":"Services"
        }
    ],
    "sg:phone":"+1 617 665 3000",
    "sg:postcode":"02141",
    "sg:province":"MA",
    "sg:tags":[
        "practice",
        "family"
    ],
    "wof:name":"Cambridge Health Alliance",
    "wof:placetype":"venue"
},
  "geometry": {"coordinates":[-71.085252,42.372596],"type":"Point"}
}