{
  "type": "Feature",
  "properties": {
    "iso:country":"US",
    "sg:address":"21 Clark Rd",
    "sg:city":"Pittsfield",
    "sg:classifiers":[
        {
            "category":"Professional",
            "subcategory":"Accounting & Tax Preparation",
            "type":"Services"
        }
    ],
    "sg:phone":"+1 413 443 1799",
    "sg:postcode":"01201",
    "sg:province":"MA",
    "sg:tags":[
        "bookkeeping",
        "general"
    ],
    "wof:name":"Carttney's Bookkeeping",
    "wof:placetype":"venue"
},
  "geometry": {"coordinates":[-73.23448399999999,42.476006],"type":"Point"}
}