{
  "type": "Feature",
  "properties": {
    "addr:full": "54 Bernice Ave Leominster MA 01453",
    "addr:housenumber": "54",
    "addr:postcode": "01453",
    "addr:street": "Bernice Ave",
    "iso:country": "US",
    "sg:address": "54 Bernice Ave",
    "sg:city": "Leominster",
    "sg:classifiers": [
      {
        "category": "Freight",
        "type": "Transportation"
      }
    ],
    "sg:phone": "+1   ",
    "sg:postcode": "01453",
    "sg:province": "MA",
    "sg:tags": [
      "operator",
      "local",
      "trucking"
    ],
    "wof:name": "Robert J Bashaw Trucking Inc",
    "wof:placetype": "venue"
  },
  "geometry": {"coordinates":[-71.74459,42.558886],"type":"Point"}
}
