{
  "type": "Feature",
  "properties": {
    "iso:country":"US",
    "sg:address":"196 Riverneck Rd",
    "sg:city":"Chelmsford",
    "sg:classifiers":[
        {
            "category":"Professional",
            "subcategory":"Engineering",
            "type":"Services"
        },
        {
            "category":"Manufacturing",
            "subcategory":"Electronics",
            "type":"Manufacturing & Wholesale Goods"
        },
        {
            "category":"Building & Trades",
            "subcategory":"Electrical",
            "type":"Services"
        }
    ],
    "sg:phone":"+1 978 244 1200",
    "sg:postcode":"01824",
    "sg:province":"MA",
    "sg:tags":[
        "control",
        "consulting",
        "system",
        "controls",
        "regulator",
        "regulators-control",
        "engineer",
        "panel"
    ],
    "wof:name":"DEI Dodge Engineering & Controls",
    "wof:placetype":"venue"
},
  "geometry": {"coordinates":[-71.32779600000001,42.603866],"type":"Point"}
}