{
  "type": "Feature",
  "properties": {
    "addr:full": "196 Riverneck Rd Chelmsford MA 01824",
    "addr:housenumber": "196",
    "addr:postcode": "01824",
    "addr:street": "Riverneck Rd",
    "iso:country": "US",
    "sg:address": "196 Riverneck Rd",
    "sg:city": "Chelmsford",
    "sg:classifiers": [
      {
        "category": "Professional",
        "subcategory": "Engineering",
        "type": "Services"
      },
      {
        "category": "Manufacturing",
        "subcategory": "Electronics",
        "type": "Manufacturing \u0026 Wholesale Goods"
      },
      {
        "category": "Building \u0026 Trades",
        "subcategory": "Electrical",
        "type": "Services"
      }
    ],
    "sg:phone": "+1 978 244 1200",
    "sg:postcode": "01824",
    "sg:province": "MA",
    "sg:tags": [
      "control",
      "consulting",
      "system",
      "controls",
      "regulator",
      "regulators-control",
      "engineer",
      "panel"
    ],
    "wof:name": "DEI Dodge Engineering \u0026 Controls",
    "wof:placetype": "venue"
  },
  "geometry": {"coordinates":[-71.327796,42.603866],"type":"Point"}
}
