{
  "type": "Feature",
  "properties": {
    "iso:country":"US",
    "sg:address":"1434 Centre St",
    "sg:city":"Roslindale",
    "sg:classifiers":[
        {
            "category":"Building & Trades",
            "subcategory":"Locksmith",
            "type":"Services"
        }
    ],
    "sg:phone":"+1 617 390 9009",
    "sg:postcode":"02131",
    "sg:province":"MA",
    "sg:tags":[
        "key"
    ],
    "wof:name":"Services Anytime Locksmith and Lock",
    "wof:placetype":"venue"
},
  "geometry": {"coordinates":[-71.13701,42.293343],"type":"Point"}
}