{
  "type": "Feature",
  "properties": {
    "iso:country":"US",
    "sg:address":"845 Burnett Rd",
    "sg:city":"Chicopee",
    "sg:classifiers":[
        {
            "category":"Utilities",
            "subcategory":"Refuse",
            "type":"Services"
        }
    ],
    "sg:phone":"+1 413 592 2196",
    "sg:postcode":"01020",
    "sg:province":"MA",
    "sg:tags":[
        "disposal",
        "waste"
    ],
    "wof:name":"BBFI",
    "wof:placetype":"venue"
},
  "geometry": {"coordinates":[-72.53297999999999,42.175041],"type":"Point"}
}