{
  "type": "Feature",
  "properties": {
    "iso:country":"US",
    "sg:address":"586 Bay Rd",
    "sg:city":"Stoughton",
    "sg:classifiers":[
        {
            "category":"Education",
            "subcategory":"Special Training",
            "type":"Public Place"
        }
    ],
    "sg:phone":"+1 781 341 1396",
    "sg:postcode":"02072",
    "sg:province":"MA",
    "sg:tags":[
        "instruction",
        "music"
    ],
    "wof:name":"J D Drum Studio",
    "wof:placetype":"venue"
},
  "geometry": {"coordinates":[-71.145197,42.124881],"type":"Point"}
}