{
  "type": "Feature",
  "properties": {
    "addr:full":"52 Circuit Ave Oak Bluffs MA 02557",
    "addr:housenumber":"52",
    "addr:postcode":"02557",
    "addr:street":"Circuit Ave",
    "iso:country":"US",
    "sg:address":"52 Circuit Ave",
    "sg:city":"Oak Bluffs",
    "sg:classifiers":[
        {
            "category":"Shopping",
            "subcategory":"Clothing, Apparel, & Fashions",
            "type":"Retail Goods"
        }
    ],
    "sg:phone":"+1 508 693 5550",
    "sg:postcode":"02557",
    "sg:province":"MA",
    "wof:name":"Third World Trading Co",
    "wof:placetype":"venue"
},
  "geometry": {"coordinates":[-70.558361,41.455406],"type":"Point"}
}