{
  "type": "Feature",
  "properties": {
    "addr:full": "6 Harrison St Stoneham MA 02180",
    "addr:housenumber": "6",
    "addr:postcode": "02180",
    "addr:street": "Harrison St",
    "iso:country": "US",
    "sg:address": "6 Harrison St",
    "sg:city": "Stoneham",
    "sg:classifiers": [
      {
        "category": "Building \u0026 Trades",
        "subcategory": "Plumbing",
        "type": "Services"
      }
    ],
    "sg:phone": "+1 781 662 7600",
    "sg:postcode": "02180",
    "sg:province": "MA",
    "sg:tags": [
      "plumbing",
      "contractor"
    ],
    "wof:name": "Theriault LLC",
    "wof:placetype": "venue"
  },
  "geometry": {"coordinates":[-71.078726,42.470306],"type":"Point"}
}
