{
  "type": "Feature",
  "properties": {
    "iso:country":"US",
    "sg:address":"6 Harrison St",
    "sg:city":"Stoneham",
    "sg:classifiers":[
        {
            "category":"Building & Trades",
            "subcategory":"Plumbing",
            "type":"Services"
        }
    ],
    "sg:phone":"+1 781 662 7600",
    "sg:postcode":"02180",
    "sg:province":"MA",
    "sg:tags":[
        "plumbing",
        "contractor"
    ],
    "wof:name":"Theriault LLC",
    "wof:placetype":"venue"
},
  "geometry": {"coordinates":[-71.078726,42.470306],"type":"Point"}
}