{
  "type": "Feature",
  "properties": {
    "addr:full":"110 Front St Worcester MA 01608",
    "addr:housenumber":"110",
    "addr:postcode":"01608",
    "addr:street":"Front St",
    "iso:country":"US",
    "sg:address":"110 Front St",
    "sg:city":"Worcester",
    "sg:classifiers":[
        {
            "category":"Restaurant",
            "type":"Food & Drink"
        }
    ],
    "sg:phone":"+1 508 770 0839",
    "sg:postcode":"01608",
    "sg:province":"MA",
    "wof:name":"Panda Pearls",
    "wof:placetype":"venue"
},
  "geometry": {"coordinates":[-71.799896,42.261788],"type":"Point"}
}