{
  "type": "Feature",
  "properties": {
    "iso:country":"US",
    "sg:address":"92 N Main St",
    "sg:city":"Raynham",
    "sg:classifiers":[
        {
            "category":"Real Estate",
            "subcategory":"Real Estate Agent",
            "type":"Services"
        }
    ],
    "sg:phone":"+1 508 823 9100",
    "sg:postcode":"02767",
    "sg:province":"MA",
    "wof:name":"Century 21",
    "wof:placetype":"venue"
},
  "geometry": {"coordinates":[-71.05302500000001,41.926738],"type":"Point"}
}