{
  "type": "Feature",
  "properties": {
    "addr:full": "39 N Bennet St Boston MA 02113",
    "addr:housenumber": "39",
    "addr:postcode": "02113",
    "addr:street": "N Bennet St",
    "iso:country": "US",
    "sg:address": "39 N Bennet St",
    "sg:city": "Boston",
    "sg:classifiers": [
      {
        "category": "Shopping",
        "subcategory": "Musical Instruments",
        "type": "Retail Goods"
      },
      {
        "category": "Education",
        "subcategory": "Junior College",
        "type": "Public Place"
      }
    ],
    "sg:phone": "+1 617 227 0155",
    "sg:postcode": "02113",
    "sg:province": "MA",
    "sg:tags": [
      "technical",
      "institute",
      "piano",
      "adult"
    ],
    "sg:website": "www.nbss.org",
    "wof:name": "North Bennet Street School",
    "wof:placetype": "venue"
  },
  "geometry": {"coordinates":[-71.054779,42.365886],"type":"Point"}
}
