{
  "type": "Feature",
  "properties": {
    "addr:full":"15 Oak St Beverly MA 01915",
    "addr:housenumber":"15",
    "addr:postcode":"01915",
    "addr:street":"Oak St",
    "iso:country":"US",
    "sg:address":"15 Oak St",
    "sg:city":"Beverly",
    "sg:classifiers":[
        {
            "category":"Personal",
            "subcategory":"Beauty Salon",
            "type":"Services"
        }
    ],
    "sg:phone":"+1 978 922 1272",
    "sg:postcode":"01915",
    "sg:province":"MA",
    "sg:tags":[
        "spa",
        "day"
    ],
    "wof:name":"Sea Spa",
    "wof:placetype":"venue"
},
  "geometry": {"coordinates":[-70.81175,42.561882],"type":"Point"}
}