{
  "type": "Feature",
  "properties": {
    "addr:full":"204 Mill St Haverhill MA 01830",
    "addr:housenumber":"204",
    "addr:postcode":"01830",
    "addr:street":"Mill St",
    "iso:country":"US",
    "sg:address":"204 Mill St",
    "sg:city":"Haverhill",
    "sg:classifiers":[
        {
            "category":"Real Estate",
            "subcategory":"Architect",
            "type":"Services"
        }
    ],
    "sg:phone":"+1 978 372 5445",
    "sg:postcode":"01830",
    "sg:province":"MA",
    "wof:name":"Building Dreams On Paper",
    "wof:placetype":"venue"
},
  "geometry": {"coordinates":[-71.069654,42.781596],"type":"Point"}
}