{
  "type": "Feature",
  "properties": {
    "addr:full": "1130 Dorchester Ave Dorchester MA 02125",
    "addr:housenumber": "1130",
    "addr:postcode": "02125",
    "addr:street": "Dorchester Ave",
    "iso:country": "US",
    "sg:address": "1130 Dorchester Ave",
    "sg:city": "Dorchester",
    "sg:classifiers": [
      {
        "category": "Building \u0026 Trades",
        "subcategory": "Construction",
        "type": "Services"
      }
    ],
    "sg:phone": "+1 617 825 5800",
    "sg:postcode": "02125",
    "sg:province": "MA",
    "sg:tags": [
      "utility",
      "contractor"
    ],
    "wof:name": "M \u0026 X Utility Co Inc",
    "wof:placetype": "venue"
  },
  "geometry": {"coordinates":[-71.057585,42.311355],"type":"Point"}
}
