{
  "type": "Feature",
  "properties": {
    "iso:country":"US",
    "sg:address":"140 Nauset St",
    "sg:city":"New Bedford",
    "sg:classifiers":[
        {
            "category":"Health Services",
            "subcategory":"Doctor",
            "type":"Services"
        }
    ],
    "sg:phone":"+1 508 990 8260",
    "sg:postcode":"02746",
    "sg:province":"MA",
    "sg:tags":[
        "clinic"
    ],
    "wof:name":"Tru-Med Walk-In Clinic",
    "wof:placetype":"venue"
},
  "geometry": {"coordinates":[-70.942948,41.661708],"type":"Point"}
}