{
  "type": "Feature",
  "properties": {
    "addr:full": "140 Nauset St New Bedford MA 02746",
    "addr:housenumber": "140",
    "addr:postcode": "02746",
    "addr:street": "Nauset St",
    "iso:country": "US",
    "sg:address": "140 Nauset St",
    "sg:city": "New Bedford",
    "sg:classifiers": [
      {
        "category": "Health Services",
        "subcategory": "Doctor",
        "type": "Services"
      }
    ],
    "sg:phone": "+1 508 990 8260",
    "sg:postcode": "02746",
    "sg:province": "MA",
    "sg:tags": [
      "clinic"
    ],
    "wof:name": "Tru-Med Walk-In Clinic",
    "wof:placetype": "venue"
  },
  "geometry": {"coordinates":[-70.942948,41.661708],"type":"Point"}
}
