{
  "type": "Feature",
  "properties": {
    "addr:full": "1134 American Legion Hwy Westport MA 02790",
    "addr:housenumber": "1134",
    "addr:postcode": "02790",
    "addr:street": "American Legion Hwy",
    "iso:country": "US",
    "ovtr:label": "Salon Salon Limousine, 1134 American Legion Hwy Westport MA US",
    "ovtr:similarity": 1.7806990146636963,
    "sg:address": "1134 American Legion Hwy",
    "sg:city": "Westport",
    "sg:classifiers": [
      {
        "category": "Personal",
        "subcategory": "Beauty Salon",
        "type": "Services"
      }
    ],
    "sg:phone": "+1 508 636 6688",
    "sg:postcode": "02790",
    "sg:province": "MA",
    "wof:name": "Salon Salon Limousine",
    "wof:placetype": "venue"
  },
  "geometry": {"coordinates":[-71.055386,41.634945],"type":"Point"}
}
