{
  "type": "Feature",
  "properties": {
    "iso:country":"US",
    "sg:address":"1134 American Legion Hwy",
    "sg:city":"Westport",
    "sg:classifiers":[
        {
            "category":"Personal",
            "subcategory":"Beauty Salon",
            "type":"Services"
        }
    ],
    "sg:phone":"+1 508 636 6688",
    "sg:postcode":"02790",
    "sg:province":"MA",
    "wof:name":"Salon Salon Limousine",
    "wof:placetype":"venue"
},
  "geometry": {"coordinates":[-71.055386,41.634945],"type":"Point"}
}