{
  "type": "Feature",
  "properties": {
    "iso:country":"US",
    "sg:address":"30 School St",
    "sg:city":"Cotuit",
    "sg:classifiers":[
        {
            "category":"Insurance",
            "subcategory":"Insurance Agent",
            "type":"Services"
        }
    ],
    "sg:phone":"+1 508 428 3511",
    "sg:postcode":"02635",
    "sg:province":"MA",
    "wof:name":"Mycock Insurance",
    "wof:placetype":"venue"
},
  "geometry": {"coordinates":[-70.4359,41.617557],"type":"Point"}
}