{
  "type": "Feature",
  "properties": {
    "addr:full": "30 School St Cotuit MA 02635",
    "addr:housenumber": "30",
    "addr:postcode": "02635",
    "addr:street": "School St",
    "iso:country": "US",
    "ovtr:label": "Mycock Insurance, 20 School St Cotuit MA US",
    "ovtr:similarity": 2.9581620693206787,
    "sg:address": "30 School St",
    "sg:city": "Cotuit",
    "sg:classifiers": [
      {
        "category": "Insurance",
        "subcategory": "Insurance Agent",
        "type": "Services"
      }
    ],
    "sg:phone": "+1 508 428 3511",
    "sg:postcode": "02635",
    "sg:province": "MA",
    "wof:name": "Mycock Insurance",
    "wof:placetype": "venue"
  },
  "geometry": {"coordinates":[-70.4359,41.617557],"type":"Point"}
}
