{
  "type": "Feature",
  "properties": {
    "addr:full":"153 Calvary St Waltham MA 02453",
    "addr:housenumber":"153",
    "addr:postcode":"02453",
    "addr:street":"Calvary St",
    "iso:country":"US",
    "sg:address":"153 Calvary St",
    "sg:city":"Waltham",
    "sg:classifiers":[
        {
            "category":"Building & Trades",
            "subcategory":"Landscaping Services",
            "type":"Services"
        }
    ],
    "sg:phone":"+1 781 647 5111",
    "sg:postcode":"02453",
    "sg:province":"MA",
    "sg:tags":[
        "landscape",
        "contractor"
    ],
    "wof:name":"Frank Fragale & Sons Landscpg",
    "wof:placetype":"venue"
},
  "geometry": {"coordinates":[-71.223941,42.367833],"type":"Point"}
}