{
  "type": "Feature",
  "properties": {
    "iso:country":"US",
    "sg:address":"245 Union St",
    "sg:city":"Braintree",
    "sg:classifiers":[
        {
            "category":"Building & Trades",
            "subcategory":"Construction",
            "type":"Services"
        }
    ],
    "sg:phone":"+1 781 843 0332",
    "sg:postcode":"02184",
    "sg:province":"MA",
    "sg:tags":[
        "marking",
        "maintenance",
        "parking"
    ],
    "wof:name":"Braintree Highway Dept",
    "wof:placetype":"venue"
},
  "geometry": {"coordinates":[-70.993606,42.211201],"type":"Point"}
}