{
  "type": "Feature",
  "properties": {
    "iso:country":"US",
    "sg:address":"30 Lyman St",
    "sg:city":"Westborough",
    "sg:classifiers":[
        {
            "category":"Wholesale",
            "subcategory":"Electrical",
            "type":"Manufacturing & Wholesale Goods"
        }
    ],
    "sg:phone":"+1 508 836 3300",
    "sg:postcode":"01581",
    "sg:province":"MA",
    "sg:tags":[
        "television",
        "radio"
    ],
    "wof:name":"Thomson Consumer Electronics",
    "wof:placetype":"venue"
},
  "geometry": {"coordinates":[-71.60709799999999,42.282356],"type":"Point"}
}