{
  "type": "Feature",
  "properties": {
    "addr:full": "600 Governors Dr Winthrop MA 02152",
    "addr:housenumber": "600",
    "addr:postcode": "02152",
    "addr:street": "Governors Dr",
    "iso:country": "US",
    "sg:address": "600 Governors Dr",
    "sg:city": "Winthrop",
    "sg:classifiers": [
      {
        "category": "Building \u0026 Trades",
        "subcategory": "Cleaning \u0026 Sanitation",
        "type": "Services"
      }
    ],
    "sg:phone": "+1 617 539 9099",
    "sg:postcode": "02152",
    "sg:province": "MA",
    "wof:name": "Boston Cleaning Svc",
    "wof:placetype": "venue"
  },
  "geometry": {"coordinates":[-70.981215,42.383129],"type":"Point"}
}
