{
  "type": "Feature",
  "properties": {
    "addr:full":"1233 Bennington St Boston MA 02128",
    "addr:housenumber":"1233",
    "addr:postcode":"02128",
    "addr:street":"Bennington St",
    "iso:country":"US",
    "sg:address":"1233 Bennington St",
    "sg:city":"Boston",
    "sg:classifiers":[
        {
            "category":"Restaurant",
            "type":"Food & Drink"
        }
    ],
    "sg:phone":"+1 617 567 4454",
    "sg:postcode":"02128",
    "sg:province":"MA",
    "wof:name":"Jimmy Magg's",
    "wof:placetype":"venue"
},
  "geometry": {"coordinates":[-70.996735,42.389897],"type":"Point"}
}