{
  "type": "Feature",
  "properties": {
    "addr:full": "141 Grove St Worcester MA 01605",
    "addr:housenumber": "141",
    "addr:postcode": "01605",
    "addr:street": "Grove St",
    "iso:country": "US",
    "sg:address": "141 Grove St",
    "sg:city": "Worcester",
    "sg:classifiers": [
      {
        "category": "Government",
        "subcategory": "Fire Station",
        "type": "Public Place"
      }
    ],
    "sg:phone": "+1 508 799 1822",
    "sg:postcode": "01605",
    "sg:province": "MA",
    "sg:tags": [
      "department"
    ],
    "sg:website": "www.fireprevention.com",
    "wof:name": "Fire Prevention",
    "wof:placetype": "venue"
  },
  "geometry": {"coordinates":[-71.803089,42.277712],"type":"Point"}
}
