{
  "type": "Feature",
  "properties": {
    "addr:full": "500 Yarmouth Rd Hyannis MA 02601",
    "addr:housenumber": "500",
    "addr:postcode": "02601",
    "addr:street": "Yarmouth Rd",
    "iso:country": "US",
    "sg:address": "500 Yarmouth Rd",
    "sg:city": "Hyannis",
    "sg:classifiers": [
      {
        "category": "Autos \u0026 Motor Vehicles",
        "subcategory": "Automobile Sales",
        "type": "Retail Goods"
      }
    ],
    "sg:phone": "+1 508 778 8888",
    "sg:postcode": "02601",
    "sg:province": "MA",
    "sg:tags": [
      "car",
      "dealer"
    ],
    "wof:name": "MBM Auto Sales",
    "wof:placetype": "venue"
  },
  "geometry": {"coordinates":[-70.270532,41.667362],"type":"Point"}
}
