{
  "type": "Feature",
  "properties": {
    "iso:country":"US",
    "sg:address":"75 Sherman St",
    "sg:city":"Revere",
    "sg:classifiers":[
        {
            "category":"Building & Trades",
            "subcategory":"Locksmith",
            "type":"Services"
        }
    ],
    "sg:phone":"+1 781 922 9080",
    "sg:postcode":"02151",
    "sg:province":"MA",
    "sg:tags":[
        "key"
    ],
    "wof:name":"Shermans Street 24 7 Locksmith Service",
    "wof:placetype":"venue"
},
  "geometry": {"coordinates":[-71.025012,42.429597],"type":"Point"}
}