{
  "type": "Feature",
  "properties": {
    "addr:full":"17 Station St Brookline MA 02445",
    "addr:housenumber":"17",
    "addr:postcode":"02445",
    "addr:street":"Station St",
    "iso:country":"US",
    "sg:address":"17 Station St",
    "sg:city":"Brookline",
    "sg:classifiers":[
        {
            "category":"Professional",
            "subcategory":"Management & Consulting",
            "type":"Services"
        }
    ],
    "sg:phone":"+1 617 232 4622",
    "sg:postcode":"02445",
    "sg:province":"MA",
    "wof:name":"Tracy Fleming",
    "wof:placetype":"venue"
},
  "geometry": {"coordinates":[-71.117633,42.33252],"type":"Point"}
}