{
  "type": "Feature",
  "properties": {
    "iso:country":"US",
    "sg:address":"883 Main St",
    "sg:city":"Wilmington",
    "sg:classifiers":[
        {
            "category":"Freight",
            "type":"Transportation"
        }
    ],
    "sg:phone":"+1   ",
    "sg:postcode":"01887",
    "sg:province":"MA",
    "sg:tags":[
        "operator",
        "local",
        "trucking"
    ],
    "wof:name":"TS Trucking",
    "wof:placetype":"venue"
},
  "geometry": {"coordinates":[-71.159869,42.523973],"type":"Point"}
}