{
  "type": "Feature",
  "properties": {
    "iso:country":"US",
    "sg:address":"200 Great Rd Ste 6A",
    "sg:city":"Bedford",
    "sg:classifiers":[
        {
            "category":"Health Services",
            "subcategory":"Optometrist",
            "type":"Services"
        }
    ],
    "sg:phone":"+1 781 275 0054",
    "sg:postcode":"01730",
    "sg:province":"MA",
    "wof:name":"Bedford Vision Center",
    "wof:placetype":"venue"
},
  "geometry": {"coordinates":[-71.2724,42.489399],"type":"Point"}
}