{
  "type": "Feature",
  "properties": {
    "iso:country":"US",
    "sg:address":"296 Chelmsford St",
    "sg:city":"Chelmsford",
    "sg:classifiers":[
        {
            "category":"Real Estate",
            "subcategory":"Real Estate Agent",
            "type":"Services"
        }
    ],
    "sg:phone":"+1   ",
    "sg:postcode":"01824",
    "sg:province":"MA",
    "wof:name":"N&H Realty Corp",
    "wof:placetype":"venue"
},
  "geometry": {"coordinates":[-71.328986,42.61331],"type":"Point"}
}