{
  "type": "Feature",
  "properties": {
    "iso:country":"US",
    "sg:address":"21 Main St",
    "sg:city":"Newbury",
    "sg:classifiers":[
        {
            "category":"Professional",
            "subcategory":"Computer Services",
            "type":"Services"
        }
    ],
    "sg:phone":"+1 978 462 9538",
    "sg:postcode":"01969",
    "sg:province":"MA",
    "sg:tags":[
        "consultant",
        "designer"
    ],
    "wof:name":"Strategic Data Group",
    "wof:placetype":"venue"
},
  "geometry": {"coordinates":[-70.881288,42.70738],"type":"Point"}
}