{
  "type": "Feature",
  "properties": {
    "addr:full":"282 Cottage St Franklin MA 02038",
    "addr:housenumber":"282",
    "addr:postcode":"02038",
    "addr:street":"Cottage St",
    "iso:country":"US",
    "sg:address":"282 Cottage St",
    "sg:city":"Franklin",
    "sg:classifiers":[
        {
            "category":"Shopping",
            "subcategory":"Bicycles & Sporting Goods",
            "type":"Retail Goods"
        }
    ],
    "sg:phone":"+1 508 528 1010",
    "sg:postcode":"02038",
    "sg:province":"MA",
    "sg:tags":[
        "repair",
        "book"
    ],
    "wof:name":"Crossing Cycle",
    "wof:placetype":"venue"
},
  "geometry": {"coordinates":[-71.405458,42.076133],"type":"Point"}
}