{
  "type": "Feature",
  "properties": {
    "addr:full":"426 River St Fitchburg MA 01420",
    "addr:housenumber":"426",
    "addr:postcode":"01420",
    "addr:street":"River St",
    "iso:country":"US",
    "sg:address":"426 River St",
    "sg:city":"Fitchburg",
    "sg:classifiers":[
        {
            "category":"Retail",
            "subcategory":"Auto Repair",
            "type":"Services"
        }
    ],
    "sg:phone":"+1 978 343 8613",
    "sg:postcode":"01420",
    "sg:province":"MA",
    "sg:tags":[
        "repairing",
        "automobile"
    ],
    "wof:name":"Mel's Service & Repair",
    "wof:placetype":"venue"
},
  "geometry": {"coordinates":[-71.821146,42.581859],"type":"Point"}
}