{
  "type": "Feature",
  "properties": {
    "iso:country":"US",
    "sg:address":"236 1st St",
    "sg:city":"Pittsfield",
    "sg:classifiers":[
        {
            "category":"Personal",
            "subcategory":"Beauty Salon",
            "type":"Services"
        }
    ],
    "sg:phone":"+1 413 499 4644",
    "sg:postcode":"01201",
    "sg:province":"MA",
    "sg:tags":[
        "shop"
    ],
    "wof:name":"Studio 100 Hair Designers",
    "wof:placetype":"venue"
},
  "geometry": {"coordinates":[-73.248975,42.455594],"type":"Point"}
}