{
  "type": "Feature",
  "properties": {
    "iso:country":"US",
    "sg:address":"92 Merrimac St",
    "sg:city":"Newburyport",
    "sg:classifiers":[
        {
            "category":"Personal",
            "subcategory":"Beauty Salon",
            "type":"Services"
        }
    ],
    "sg:phone":"+1 978 499 2938",
    "sg:postcode":"01950",
    "sg:province":"MA",
    "sg:tags":[
        "manicuring"
    ],
    "wof:name":"Vicki's Nails",
    "wof:placetype":"venue"
},
  "geometry": {"coordinates":[-70.87396699999999,42.812238],"type":"Point"}
}