{
  "type": "Feature",
  "properties": {
    "iso:country":"US",
    "sg:address":"98 Whittier Pl",
    "sg:city":"Boston",
    "sg:classifiers":[
        {
            "category":"Building & Trades",
            "subcategory":"Locksmith",
            "type":"Services"
        }
    ],
    "sg:phone":"+1 617 531 0569",
    "sg:postcode":"02114",
    "sg:province":"MA",
    "sg:tags":[
        "key"
    ],
    "wof:name":"24 7 Emergency Locksmith Service",
    "wof:placetype":"venue"
},
  "geometry": {"coordinates":[-71.067457,42.366259],"type":"Point"}
}