{
  "type": "Feature",
  "properties": {
    "addr:full": "98 Whittier Pl Boston MA 02114",
    "addr:housenumber": "98",
    "addr:postcode": "02114",
    "addr:street": "Whittier Pl",
    "iso:country": "US",
    "sg:address": "98 Whittier Pl",
    "sg:city": "Boston",
    "sg:classifiers": [
      {
        "category": "Building \u0026 Trades",
        "subcategory": "Locksmith",
        "type": "Services"
      }
    ],
    "sg:phone": "+1 617 531 0569",
    "sg:postcode": "02114",
    "sg:province": "MA",
    "sg:tags": [
      "key"
    ],
    "wof:name": "24 7 Emergency Locksmith Service",
    "wof:placetype": "venue"
  },
  "geometry": {"coordinates":[-71.067457,42.366259],"type":"Point"}
}
