{
  "type": "Feature",
  "properties": {
    "iso:country":"US",
    "sg:address":"8 Whittier Pl Ste 1E",
    "sg:city":"Boston",
    "sg:classifiers":[
        {
            "category":"Education",
            "subcategory":"Special Training",
            "type":"Public Place"
        },
        {
            "category":"Education",
            "subcategory":"Preschool",
            "type":"Public Place"
        }
    ],
    "sg:phone":"+1 617 367 9945",
    "sg:postcode":"02114",
    "sg:province":"MA",
    "sg:tags":[
        "kindergarten",
        "school",
        "nursery",
        "educational"
    ],
    "wof:name":"Boston Children's School",
    "wof:placetype":"venue"
},
  "geometry": {"coordinates":[-71.066924,42.365813],"type":"Point"}
}