{
  "type": "Feature",
  "properties": {
    "iso:country":"US",
    "sg:address":"117 Central St",
    "sg:city":"Gardner",
    "sg:classifiers":[
        {
            "category":"Health Services",
            "subcategory":"Doctor",
            "type":"Services"
        }
    ],
    "sg:phone":"+1 978 632 0267",
    "sg:postcode":"01440",
    "sg:province":"MA",
    "sg:tags":[
        "dentist"
    ],
    "wof:name":"Timothy J Dymek DDS",
    "wof:placetype":"venue"
},
  "geometry": {"coordinates":[-71.990134,42.578697],"type":"Point"}
}