{
  "type": "Feature",
  "properties": {
    "addr:full":"147 High St Medford MA 02155",
    "addr:housenumber":"147",
    "addr:postcode":"02155",
    "addr:street":"High St",
    "iso:country":"US",
    "sg:address":"147 High St",
    "sg:city":"Medford",
    "sg:classifiers":[
        {
            "category":"Place Of Worship",
            "subcategory":"Church",
            "type":"Public Place"
        }
    ],
    "sg:phone":"+1 781 396 4549",
    "sg:postcode":"02155",
    "sg:province":"MA",
    "wof:name":"Unitarian Universalist Church of Medford & Somerville",
    "wof:placetype":"venue"
},
  "geometry": {"coordinates":[-71.115345,42.420355],"type":"Point"}
}