{
  "type": "Feature",
  "properties": {
    "iso:country":"US",
    "sg:address":"15 Court Sq Ste 600",
    "sg:city":"Boston",
    "sg:classifiers":[
        {
            "category":"Professional",
            "subcategory":"Employment Agencies",
            "type":"Services"
        },
        {
            "category":"Organizations",
            "subcategory":"Professional Association",
            "type":"Services"
        }
    ],
    "sg:phone":"+1 617 426 0303",
    "sg:postcode":"02108",
    "sg:province":"MA",
    "sg:tags":[
        "employer",
        "business",
        "trade"
    ],
    "wof:name":"Massachusetts Association Of Community Development Corp.",
    "wof:placetype":"venue"
},
  "geometry": {"coordinates":[-71.058228,42.358817],"type":"Point"}
}