{
  "type": "Feature",
  "properties": {
    "iso:country":"US",
    "sg:address":"60 Main St",
    "sg:city":"Wenham",
    "sg:classifiers":[
        {
            "category":"Sports & Exercise",
            "subcategory":"Golf",
            "type":"Entertainment"
        }
    ],
    "sg:phone":"+1 978 468 9584",
    "sg:postcode":"01984",
    "sg:province":"MA",
    "sg:tags":[
        "course"
    ],
    "wof:name":"Lakeview Golf Club",
    "wof:placetype":"venue"
},
  "geometry": {"coordinates":[-70.88760499999999,42.597314],"type":"Point"}
}