{
  "type": "Feature",
  "properties": {
    "addr:full": "60 Main St Wenham MA 01984",
    "addr:housenumber": "60",
    "addr:postcode": "01984",
    "addr:street": "Main St",
    "iso:country": "US",
    "sg:address": "60 Main St",
    "sg:city": "Wenham",
    "sg:classifiers": [
      {
        "category": "Sports \u0026 Exercise",
        "subcategory": "Golf",
        "type": "Entertainment"
      }
    ],
    "sg:phone": "+1 978 468 9584",
    "sg:postcode": "01984",
    "sg:province": "MA",
    "sg:tags": [
      "course"
    ],
    "wof:name": "Lakeview Golf Club",
    "wof:placetype": "venue"
  },
  "geometry": {"coordinates":[-70.887605,42.597314],"type":"Point"}
}
