{
  "type": "Feature",
  "properties": {
    "iso:country":"US",
    "sg:address":"2136 Washington St",
    "sg:city":"Roxbury",
    "sg:classifiers":[
        {
            "category":"Personal",
            "subcategory":"Beauty Salon",
            "type":"Services"
        }
    ],
    "sg:phone":"+1 617 427 7200",
    "sg:postcode":"02119",
    "sg:province":"MA",
    "wof:name":"Hair Action",
    "wof:placetype":"venue"
},
  "geometry": {"coordinates":[-71.082223,42.331442],"type":"Point"}
}