{
  "type": "Feature",
  "properties": {
    "iso:country":"US",
    "sg:address":"1 Research Dr",
    "sg:city":"Westborough",
    "sg:classifiers":[
        {
            "category":"Health Services",
            "subcategory":"Clinic",
            "type":"Services"
        }
    ],
    "sg:phone":"+1 508 616 9390",
    "sg:postcode":"01581",
    "sg:province":"MA",
    "wof:name":"Status One Health Systems Inc",
    "wof:placetype":"venue"
},
  "geometry": {"coordinates":[-71.585719,42.287521],"type":"Point"}
}