{
  "type": "Feature",
  "properties": {
    "iso:country":"US",
    "sg:address":"195 Water St",
    "sg:city":"Lee",
    "sg:classifiers":[
        {
            "category":"Manufacturing",
            "subcategory":"Printing",
            "type":"Manufacturing & Wholesale Goods"
        }
    ],
    "sg:phone":"+1 413 243 2621",
    "sg:postcode":"01238",
    "sg:province":"MA",
    "sg:tags":[
        "commercial"
    ],
    "wof:name":"Appalachian Press",
    "wof:placetype":"venue"
},
  "geometry": {"coordinates":[-73.229699,42.295034],"type":"Point"}
}