{
  "type": "Feature",
  "properties": {
    "addr:full":"4 Channing Cir Cambridge MA 02138",
    "addr:housenumber":"4",
    "addr:postcode":"02138",
    "addr:street":"Channing Cir",
    "iso:country":"US",
    "sg:address":"4 Channing Cir",
    "sg:city":"Cambridge",
    "sg:classifiers":[
        {
            "category":"Shopping",
            "subcategory":"Jewelry",
            "type":"Retail Goods"
        }
    ],
    "sg:phone":"+1 617 354 0522",
    "sg:postcode":"02138",
    "sg:province":"MA",
    "sg:tags":[
        "pearl"
    ],
    "wof:name":"Pearl Street Development",
    "wof:placetype":"venue"
},
  "geometry": {"coordinates":[-71.135482,42.375722],"type":"Point"}
}