{
  "type": "Feature",
  "properties": {
    "iso:country":"US",
    "sg:address":"Medford Meadow Gln",
    "sg:city":"Medford",
    "sg:classifiers":[
        {
            "category":"Shopping",
            "subcategory":"Mobile Phones",
            "type":"Retail Goods"
        }
    ],
    "sg:phone":"+1 781 391 2578",
    "sg:postcode":"02155",
    "sg:province":"MA",
    "wof:name":"Radioshack-A Division of Tandy Corp",
    "wof:placetype":"venue"
},
  "geometry": {"coordinates":[-71.105598,42.416901],"type":"Point"}
}