{
  "type": "Feature",
  "properties": {
    "iso:country":"US",
    "sg:address":"654 Sudbury St",
    "sg:city":"Marlborough",
    "sg:classifiers":[
        {
            "category":"Professional",
            "subcategory":"Management & Consulting",
            "type":"Services"
        }
    ],
    "sg:phone":"+1 508 460 6465",
    "sg:postcode":"01752",
    "sg:province":"MA",
    "sg:tags":[
        "marketing",
        "consultant"
    ],
    "wof:name":"Habits & Habitats",
    "wof:placetype":"venue"
},
  "geometry": {"coordinates":[-71.49736799999999,42.37264],"type":"Point"}
}