{
  "type": "Feature",
  "properties": {
    "addr:full": "654 Sudbury St Marlborough MA 01752",
    "addr:housenumber": "654",
    "addr:postcode": "01752",
    "addr:street": "Sudbury St",
    "iso:country": "US",
    "sg:address": "654 Sudbury St",
    "sg:city": "Marlborough",
    "sg:classifiers": [
      {
        "category": "Professional",
        "subcategory": "Management \u0026 Consulting",
        "type": "Services"
      }
    ],
    "sg:phone": "+1 508 460 6465",
    "sg:postcode": "01752",
    "sg:province": "MA",
    "sg:tags": [
      "marketing",
      "consultant"
    ],
    "wof:name": "Habits \u0026 Habitats",
    "wof:placetype": "venue"
  },
  "geometry": {"coordinates":[-71.497368,42.37264],"type":"Point"}
}
