{
  "type": "Feature",
  "properties": {
    "addr:full":"175 Portland St Boston MA 02114",
    "addr:housenumber":"175",
    "addr:postcode":"02114",
    "addr:street":"Portland St",
    "iso:country":"US",
    "sg:address":"175 Portland St",
    "sg:city":"Boston",
    "sg:classifiers":[
        {
            "category":"Professional",
            "subcategory":"Employment Agencies",
            "type":"Services"
        }
    ],
    "sg:phone":"+1 617 557 3000",
    "sg:postcode":"02114",
    "sg:province":"MA",
    "sg:tags":[
        "opportunity"
    ],
    "sg:website":"www.printworkers.com",
    "wof:name":"Printstaff Inc",
    "wof:placetype":"venue"
},
  "geometry": {"coordinates":[-71.062029,42.36469],"type":"Point"}
}