{
  "type": "Feature",
  "properties": {
    "addr:full":"107 Union St East Walpole MA 02032",
    "addr:housenumber":"107",
    "addr:postcode":"02032",
    "addr:street":"Union St",
    "iso:country":"US",
    "sg:address":"107 Union St",
    "sg:city":"East Walpole",
    "sg:classifiers":[
        {
            "category":"Social Services",
            "type":"Services"
        }
    ],
    "sg:phone":"+1 508 668 5634",
    "sg:postcode":"02032",
    "sg:province":"MA",
    "sg:tags":[
        "youth",
        "organization",
        "center"
    ],
    "wof:name":"Youth Sports News",
    "wof:placetype":"venue"
},
  "geometry": {"coordinates":[-71.21003899999999,42.16148],"type":"Point"}
}