{
  "type": "Feature",
  "properties": {
    "iso:country":"US",
    "sg:address":"487 E Broadway",
    "sg:city":"Boston",
    "sg:classifiers":[
        {
            "category":"Building & Trades",
            "subcategory":"Locksmith",
            "type":"Services"
        }
    ],
    "sg:phone":"+1 617 315 9001",
    "sg:postcode":"02127",
    "sg:province":"MA",
    "sg:tags":[
        "key"
    ],
    "wof:name":"AAA Anytime Locksmith",
    "wof:placetype":"venue"
},
  "geometry": {"coordinates":[-71.04531799999999,42.335323],"type":"Point"}
}