{
  "type": "Feature",
  "properties": {
    "addr:full":"300 Summer St Apt 14B Boston MA 02210",
    "addr:housenumber":"300;14b",
    "addr:postcode":"02210",
    "addr:street":"Summer St Apt",
    "iso:country":"US",
    "sg:address":"300 Summer St Apt 14B",
    "sg:city":"Boston",
    "sg:classifiers":[
        {
            "category":"Real Estate",
            "subcategory":"Architect",
            "type":"Services"
        }
    ],
    "sg:phone":"+1 617 423 1343",
    "sg:postcode":"02210",
    "sg:province":"MA",
    "wof:name":"Buck Smith & McAvoy",
    "wof:placetype":"venue"
},
  "geometry": {"coordinates":[-71.049334,42.349928],"type":"Point"}
}