{
  "type": "Feature",
  "properties": {
    "iso:country":"US",
    "sg:address":"2 Virginia Hill Rd",
    "sg:city":"Holden",
    "sg:classifiers":[
        {
            "category":"Manufacturing",
            "subcategory":"Glass & Minerals",
            "type":"Manufacturing & Wholesale Goods"
        }
    ],
    "sg:phone":"+1 508 829 1766",
    "sg:postcode":"01520",
    "sg:province":"MA",
    "sg:tags":[
        "concrete",
        "brick",
        "prod",
        "block"
    ],
    "wof:name":"CTI Of Central Ma",
    "wof:placetype":"venue"
},
  "geometry": {"coordinates":[-71.852942,42.346016],"type":"Point"}
}