{
  "type": "Feature",
  "properties": {
    "addr:full": "150 Newton Rd Springfield MA 01118",
    "addr:housenumber": "150",
    "addr:postcode": "01118",
    "addr:street": "Newton Rd",
    "iso:country": "US",
    "sg:address": "150 Newton Rd",
    "sg:city": "Springfield",
    "sg:classifiers": [
      {
        "category": "Professional",
        "type": "Services"
      }
    ],
    "sg:phone": "+1   ",
    "sg:postcode": "01118",
    "sg:province": "MA",
    "wof:name": "Hearts and Roses Stained",
    "wof:placetype": "venue"
  },
  "geometry": {"coordinates":[-72.520503,42.101683],"type":"Point"}
}
