{
  "type": "Feature",
  "properties": {
    "iso:country":"US",
    "sg:address":"150 Newton Rd",
    "sg:city":"Springfield",
    "sg:classifiers":[
        {
            "category":"Professional",
            "type":"Services"
        }
    ],
    "sg:phone":"+1   ",
    "sg:postcode":"01118",
    "sg:province":"MA",
    "wof:name":"Hearts and Roses Stained",
    "wof:placetype":"venue"
},
  "geometry": {"coordinates":[-72.52050300000001,42.101683],"type":"Point"}
}