{
  "type": "Feature",
  "properties": {
    "iso:country":"US",
    "sg:address":"105 Central St",
    "sg:city":"Byfield",
    "sg:classifiers":[
        {
            "category":"Retail",
            "subcategory":"Portrait Studio",
            "type":"Services"
        },
        {
            "category":"Professional",
            "subcategory":"Art Services",
            "type":"Services"
        }
    ],
    "sg:phone":"+1 978 463 8100",
    "sg:postcode":"01922",
    "sg:province":"MA",
    "sg:tags":[
        "photographer",
        "photo"
    ],
    "wof:name":"Bill L Fransons Photography",
    "wof:placetype":"venue"
},
  "geometry": {"coordinates":[-70.927605,42.742932],"type":"Point"}
}