{
  "type": "Feature",
  "properties": {
    "iso:country":"US",
    "sg:address":"20 Vineyard St",
    "sg:city":"Danvers",
    "sg:classifiers":[
        {
            "category":"Professional",
            "subcategory":"Business Services",
            "type":"Services"
        }
    ],
    "sg:phone":"+1   ",
    "sg:postcode":"01923",
    "sg:province":"MA",
    "wof:name":"Wheeler Appraisal Service",
    "wof:placetype":"venue"
},
  "geometry": {"coordinates":[-70.950159,42.570647],"type":"Point"}
}