{
  "type": "Feature",
  "properties": {
    "iso:country":"US",
    "sg:address":"85 Cummins Hwy",
    "sg:city":"Roslindale",
    "sg:classifiers":[
        {
            "category":"Organizations",
            "subcategory":"Religious Organization",
            "type":"Services"
        }
    ],
    "sg:phone":"+1 508 586 8401",
    "sg:postcode":"02131",
    "sg:province":"MA",
    "sg:tags":[
        "church"
    ],
    "wof:name":"Apostolic Church Jesus Christ",
    "wof:placetype":"venue"
},
  "geometry": {"coordinates":[-71.125366,42.284479],"type":"Point"}
}