{
  "type": "Feature",
  "properties": {
    "addr:full": "350 Massachusetts Ave Arlington MA 02474",
    "addr:housenumber": "350",
    "addr:postcode": "02474",
    "addr:street": "Massachusetts Ave",
    "iso:country": "US",
    "sg:address": "350 Massachusetts Ave",
    "sg:city": "Arlington",
    "sg:classifiers": [
      {
        "category": "Professional",
        "subcategory": "Computer Services",
        "type": "Services"
      }
    ],
    "sg:phone": "+1   ",
    "sg:postcode": "02474",
    "sg:province": "MA",
    "wof:name": "Electronic Imaging \u0026 Comm",
    "wof:placetype": "venue"
  },
  "geometry": {"coordinates":[-71.148288,42.4114],"type":"Point"}
}
