{
  "type": "Feature",
  "properties": {
    "iso:country":"US",
    "sg:address":"350 Massachusetts Ave",
    "sg:city":"Arlington",
    "sg:classifiers":[
        {
            "category":"Professional",
            "subcategory":"Computer Services",
            "type":"Services"
        }
    ],
    "sg:phone":"+1   ",
    "sg:postcode":"02474",
    "sg:province":"MA",
    "wof:name":"Electronic Imaging & Comm",
    "wof:placetype":"venue"
},
  "geometry": {"coordinates":[-71.14828799999999,42.4114],"type":"Point"}
}