{
  "type": "Feature",
  "properties": {
    "addr:full": "263 Summer St Boston MA 02210",
    "addr:housenumber": "263",
    "addr:postcode": "02210",
    "addr:street": "Summer St",
    "iso:country": "US",
    "sg:address": "263 Summer St",
    "sg:city": "Boston",
    "sg:classifiers": [
      {
        "category": "Health Services",
        "subcategory": "Clinic",
        "type": "Services"
      }
    ],
    "sg:phone": "+1 617 735 9834",
    "sg:postcode": "02210",
    "sg:province": "MA",
    "sg:tags": [
      "welfare"
    ],
    "wof:name": "New England Hlth Racket Spp",
    "wof:placetype": "venue"
  },
  "geometry": {"coordinates":[-71.050783,42.350535],"type":"Point"}
}
