{
  "type": "Feature",
  "properties": {
    "iso:country":"US",
    "sg:address":"263 Summer St",
    "sg:city":"Boston",
    "sg:classifiers":[
        {
            "category":"Health Services",
            "subcategory":"Clinic",
            "type":"Services"
        }
    ],
    "sg:phone":"+1 617 735 9834",
    "sg:postcode":"02210",
    "sg:province":"MA",
    "sg:tags":[
        "welfare"
    ],
    "wof:name":"New England Hlth Racket Spp",
    "wof:placetype":"venue"
},
  "geometry": {"coordinates":[-71.050783,42.350535],"type":"Point"}
}