{
  "type": "Feature",
  "properties": {
    "iso:country":"US",
    "sg:address":"45 Walnut Rd",
    "sg:city":"Swampscott",
    "sg:classifiers":[
        {
            "category":"Building & Trades",
            "subcategory":"Construction",
            "type":"Services"
        }
    ],
    "sg:phone":"+1 781 842 3997",
    "sg:postcode":"01907",
    "sg:province":"MA",
    "sg:tags":[
        "painter"
    ],
    "wof:name":"Ford Painting & Wallpapering C",
    "wof:placetype":"venue"
},
  "geometry": {"coordinates":[-70.903897,42.471816],"type":"Point"}
}