{
  "type": "Feature",
  "properties": {
    "iso:country":"US",
    "sg:address":"297 Billerica Rd",
    "sg:city":"Chelmsford",
    "sg:classifiers":[
        {
            "category":"Manufacturing",
            "subcategory":"Tools & Machinery",
            "type":"Manufacturing & Wholesale Goods"
        }
    ],
    "sg:phone":"+1 978 250 9800",
    "sg:postcode":"01824",
    "sg:province":"MA",
    "sg:tags":[
        "recorder",
        "system",
        "time"
    ],
    "sg:website":"www.kronos.com",
    "wof:name":"Kronos Inc",
    "wof:placetype":"venue"
},
  "geometry": {"coordinates":[-71.319095,42.5932],"type":"Point"}
}