{
  "type": "Feature",
  "properties": {
    "addr:full": "297 Billerica Rd Chelmsford MA 01824",
    "addr:housenumber": "297",
    "addr:postcode": "01824",
    "addr:street": "Billerica Rd",
    "iso:country": "US",
    "sg:address": "297 Billerica Rd",
    "sg:city": "Chelmsford",
    "sg:classifiers": [
      {
        "category": "Manufacturing",
        "subcategory": "Tools \u0026 Machinery",
        "type": "Manufacturing \u0026 Wholesale Goods"
      }
    ],
    "sg:phone": "+1 978 250 9800",
    "sg:postcode": "01824",
    "sg:province": "MA",
    "sg:tags": [
      "recorder",
      "system",
      "time"
    ],
    "sg:website": "www.kronos.com",
    "wof:name": "Kronos Inc",
    "wof:placetype": "venue"
  },
  "geometry": {"coordinates":[-71.319095,42.5932],"type":"Point"}
}
