{
  "type": "Feature",
  "properties": {
    "addr:full":"63 Marathon St Arlington MA 02474",
    "addr:housenumber":"63",
    "addr:postcode":"02474",
    "addr:street":"Marathon St",
    "iso:country":"US",
    "sg:address":"63 Marathon St",
    "sg:city":"Arlington",
    "sg:classifiers":[
        {
            "category":"Wholesale",
            "subcategory":"Durable Goods & Equipment",
            "type":"Manufacturing & Wholesale Goods"
        }
    ],
    "sg:phone":"+1 781 648 7300",
    "sg:postcode":"02474",
    "sg:province":"MA",
    "sg:tags":[
        "representative",
        "manufacturer"
    ],
    "wof:name":"Hamilton Association Inc",
    "wof:placetype":"venue"
},
  "geometry": {"coordinates":[-71.136819,42.408065],"type":"Point"}
}