{
  "type": "Feature",
  "properties": {
    "addr:full":"390 Old Falmouth Rd Marstons Mills MA 02648",
    "addr:housenumber":"390",
    "addr:postcode":"02648",
    "addr:street":"Old Falmouth Rd",
    "iso:country":"US",
    "sg:address":"390 Old Falmouth Rd",
    "sg:city":"Marstons Mills",
    "sg:classifiers":[
        {
            "category":"Building & Trades",
            "subcategory":"Landscaping Services",
            "type":"Services"
        }
    ],
    "sg:phone":"+1 508 428 9336",
    "sg:postcode":"02648",
    "sg:province":"MA",
    "sg:tags":[
        "designer",
        "landscape"
    ],
    "wof:name":"James Aalto Landscape Constr",
    "wof:placetype":"venue"
},
  "geometry": {"coordinates":[-70.39707300000001,41.662193],"type":"Point"}
}