{
  "type": "Feature",
  "properties": {
    "addr:full":"411 Providence Hwy Westwood MA 02090",
    "addr:housenumber":"411",
    "addr:postcode":"02090",
    "addr:street":"Providence Hwy",
    "iso:country":"US",
    "sg:address":"411 Providence Hwy",
    "sg:city":"Westwood",
    "sg:classifiers":[
        {
            "category":"Shopping",
            "subcategory":"Clothing, Apparel, & Fashions",
            "type":"Retail Goods"
        }
    ],
    "sg:phone":"+1 781 461 8770",
    "sg:postcode":"02090",
    "sg:province":"MA",
    "sg:tags":[
        "furnishing"
    ],
    "wof:name":"K & G Fashion Superstore",
    "wof:placetype":"venue"
},
  "geometry": {"coordinates":[-71.18217,42.213949],"type":"Point"}
}