{
  "type": "Feature",
  "properties": {
    "addr:full":"1212 Washington St Gloucester MA 01930",
    "addr:housenumber":"1212",
    "addr:postcode":"01930",
    "addr:street":"Washington St",
    "iso:country":"US",
    "sg:address":"1212 Washington St",
    "sg:city":"Gloucester",
    "sg:classifiers":[
        {
            "category":"Manufacturing",
            "subcategory":"Building Materials",
            "type":"Manufacturing & Wholesale Goods"
        }
    ],
    "sg:phone":"+1 978 282 3100",
    "sg:postcode":"01930",
    "sg:province":"MA",
    "wof:name":"Tri Mountain Corp",
    "wof:placetype":"venue"
},
  "geometry": {"coordinates":[-70.644167,42.683288],"type":"Point"}
}