{
  "type": "Feature",
  "properties": {
    "addr:full":"25 Big Chief Hill Wellfleet MA 02667",
    "addr:housenumber":"25",
    "addr:postcode":"02667",
    "addr:street":"Big Chief Hill",
    "iso:country":"US",
    "sg:address":"25 Big Chief Hill",
    "sg:city":"Wellfleet",
    "sg:classifiers":[
        {
            "category":"Building & Trades",
            "subcategory":"Construction",
            "type":"Services"
        }
    ],
    "sg:phone":"+1 508 349 3012",
    "sg:postcode":"02667",
    "sg:province":"MA",
    "sg:tags":[
        "concrete",
        "contractor"
    ],
    "wof:name":"Oliver Design Kitchen Counter",
    "wof:placetype":"venue"
},
  "geometry": {"coordinates":[-70.013796,41.925795],"type":"Point"}
}