{
  "type": "Feature",
  "properties": {
    "iso:country":"US",
    "sg:address":"274 Broadway",
    "sg:city":"Taunton",
    "sg:classifiers":[
        {
            "category":"Banks & Credit Unions",
            "subcategory":"Investment Brokerage",
            "type":"Services"
        }
    ],
    "sg:phone":"+1 508 822 1143",
    "sg:postcode":"02780",
    "sg:province":"MA",
    "sg:tags":[
        "advisory"
    ],
    "wof:name":"Baron Investments",
    "wof:placetype":"venue"
},
  "geometry": {"coordinates":[-71.090309,41.925049],"type":"Point"}
}