{
  "type": "Feature",
  "properties": {
    "addr:full":"26 Longfellow Dr Florence MA 01062",
    "addr:housenumber":"26",
    "addr:postcode":"01062",
    "addr:street":"Longfellow Dr",
    "iso:country":"US",
    "sg:address":"26 Longfellow Dr",
    "sg:city":"Florence",
    "sg:classifiers":[
        {
            "category":"Professional",
            "type":"Services"
        }
    ],
    "sg:phone":"+1   ",
    "sg:postcode":"01062",
    "sg:province":"MA",
    "wof:name":"George W Keefe",
    "wof:placetype":"venue"
},
  "geometry": {"coordinates":[-72.684478,42.297487],"type":"Point"}
}