{
  "type": "Feature",
  "properties": {
    "iso:country":"US",
    "sg:address":"19 Belmont St",
    "sg:city":"South Easton",
    "sg:classifiers":[
        {
            "category":"Shopping",
            "subcategory":"Florist",
            "type":"Retail Goods"
        }
    ],
    "sg:phone":"+1 508 238 0129",
    "sg:postcode":"02375",
    "sg:province":"MA",
    "wof:name":"Purple Statice Inc",
    "wof:placetype":"venue"
},
  "geometry": {"coordinates":[-71.082932,42.049875],"type":"Point"}
}