{
  "type": "Feature",
  "properties": {
    "addr:full":"192 Old Webster Rd Oxford MA 01540",
    "addr:housenumber":"192",
    "addr:postcode":"01540",
    "addr:street":"Old Webster Rd",
    "iso:country":"US",
    "sg:address":"192 Old Webster Rd",
    "sg:city":"Oxford",
    "sg:classifiers":[
        {
            "category":"Retail",
            "subcategory":"Repair Shop",
            "type":"Services"
        }
    ],
    "sg:phone":"+1 508 987 9200",
    "sg:postcode":"01540",
    "sg:province":"MA",
    "sg:tags":[
        "related"
    ],
    "wof:name":"Zeke Equipment Repairs",
    "wof:placetype":"venue"
},
  "geometry": {"coordinates":[-71.89193,42.109839],"type":"Point"}
}