{
  "type": "Feature",
  "properties": {
    "iso:country":"US",
    "sg:address":"46 Griggs Rd",
    "sg:city":"Brookline",
    "sg:classifiers":[
        {
            "category":"Professional",
            "type":"Services"
        }
    ],
    "sg:phone":"+1 617 734 6299",
    "sg:postcode":"02446",
    "sg:province":"MA",
    "sg:tags":[
        "establishment"
    ],
    "wof:name":"Via Boston",
    "wof:placetype":"venue"
},
  "geometry": {"coordinates":[-71.12655599999999,42.338019],"type":"Point"}
}