{
  "type": "Feature",
  "properties": {
    "addr:full": "161 Harvard St New Bedford MA 02746",
    "addr:housenumber": "161",
    "addr:postcode": "02746",
    "addr:street": "Harvard St",
    "iso:country": "US",
    "sg:address": "161 Harvard St",
    "sg:city": "New Bedford",
    "sg:classifiers": [
      {
        "category": "Building \u0026 Trades",
        "subcategory": "Cleaning \u0026 Sanitation",
        "type": "Services"
      }
    ],
    "sg:phone": "+1 508 994 3229",
    "sg:postcode": "02746",
    "sg:province": "MA",
    "sg:tags": [
      "janitor"
    ],
    "wof:name": "JLR Professional Svc",
    "wof:placetype": "venue"
  },
  "geometry": {"coordinates":[-70.944335,41.656646],"type":"Point"}
}
