{
  "type": "Feature",
  "properties": {
    "addr:full":"25 South St Hudson MA 01749",
    "addr:housenumber":"25",
    "addr:postcode":"01749",
    "addr:street":"South St",
    "iso:country":"US",
    "sg:address":"25 South St",
    "sg:city":"Hudson",
    "sg:classifiers":[
        {
            "category":"Personal",
            "subcategory":"Beauty Salon",
            "type":"Services"
        }
    ],
    "sg:phone":"+1 978 567 5990",
    "sg:postcode":"01749",
    "sg:province":"MA",
    "wof:name":"Divina's Hair Design",
    "wof:placetype":"venue"
},
  "geometry": {"coordinates":[-71.56911599999999,42.390483],"type":"Point"}
}