{
  "type": "Feature",
  "properties": {
    "iso:country":"US",
    "sg:address":"1 Ballard Way",
    "sg:city":"Lawrence",
    "sg:classifiers":[
        {
            "category":"Shopping",
            "subcategory":"Computers & Home Electronics",
            "type":"Retail Goods"
        }
    ],
    "sg:phone":"+1 978 794 0885",
    "sg:postcode":"01843",
    "sg:province":"MA",
    "sg:tags":[
        "software"
    ],
    "wof:name":"Bldg Intercom",
    "wof:placetype":"venue"
},
  "geometry": {"coordinates":[-71.185935,42.683008],"type":"Point"}
}