{
  "type": "Feature",
  "properties": {
    "addr:full": "235 Great Rd Littleton MA 01460",
    "addr:housenumber": "235",
    "addr:postcode": "01460",
    "addr:street": "Great Rd",
    "iso:country": "US",
    "sg:address": "235 Great Rd",
    "sg:city": "Littleton",
    "sg:classifiers": [
      {
        "category": "Shopping",
        "subcategory": "Computers \u0026 Home Electronics",
        "type": "Retail Goods"
      }
    ],
    "sg:phone": "+1 978 952 6434",
    "sg:postcode": "01460",
    "sg:province": "MA",
    "sg:tags": [
      "equipment",
      "dealer"
    ],
    "sg:website": "www.computersurp.com",
    "wof:name": "Computer Surplus Solutions",
    "wof:placetype": "venue"
  },
  "geometry": {"coordinates":[-71.47064,42.545477],"type":"Point"}
}
