{
  "type": "Feature",
  "properties": {
    "iso:country":"US",
    "sg:address":"22 Gilbert St",
    "sg:city":"North Brookfield",
    "sg:classifiers":[
        {
            "category":"Health Services",
            "subcategory":"Doctor",
            "type":"Services"
        }
    ],
    "sg:phone":"+1 508 867 3708",
    "sg:postcode":"01535",
    "sg:province":"MA",
    "sg:tags":[
        "dentist"
    ],
    "wof:name":"Thomas J Sullivan PC",
    "wof:placetype":"venue"
},
  "geometry": {"coordinates":[-72.08440299999999,42.265177],"type":"Point"}
}