{
  "type": "Feature",
  "properties": {
    "iso:country":"US",
    "sg:address":"48 Juniper St",
    "sg:city":"Roxbury",
    "sg:classifiers":[
        {
            "category":"Education",
            "subcategory":"Special Training",
            "type":"Public Place"
        },
        {
            "category":"Professional",
            "subcategory":"Business Services",
            "type":"Services"
        }
    ],
    "sg:phone":"+1 617 541 4100",
    "sg:postcode":"02119",
    "sg:province":"MA",
    "sg:tags":[
        "consultant",
        "educational",
        "coach"
    ],
    "wof:name":"Visions Inc",
    "wof:placetype":"venue"
},
  "geometry": {"coordinates":[-71.088757,42.325569],"type":"Point"}
}