{
  "type": "Feature",
  "properties": {
    "addr:full": "3 Garden Ct Boston MA 02113",
    "addr:housenumber": "3",
    "addr:postcode": "02113",
    "addr:street": "Garden Ct",
    "iso:country": "US",
    "sg:address": "3 Garden Ct",
    "sg:city": "Boston",
    "sg:classifiers": [
      {
        "category": "Manufacturing",
        "subcategory": "Leather Goods",
        "type": "Manufacturing \u0026 Wholesale Goods"
      },
      {
        "category": "Shopping",
        "subcategory": "Luggage \u0026 Leather Goods",
        "type": "Retail Goods"
      },
      {
        "category": "Utilities",
        "type": "Services"
      }
    ],
    "sg:phone": "+1 617 227 0436",
    "sg:postcode": "02113",
    "sg:province": "MA",
    "sg:tags": [
      "repair"
    ],
    "wof:name": "Logan Luggage",
    "wof:placetype": "venue"
  },
  "geometry": {"coordinates":[-71.053476,42.364072],"type":"Point"}
}
