{
  "type": "Feature",
  "properties": {
    "iso:country":"US",
    "sg:address":"3 Garden Ct",
    "sg:city":"Boston",
    "sg:classifiers":[
        {
            "category":"Manufacturing",
            "subcategory":"Leather Goods",
            "type":"Manufacturing & Wholesale Goods"
        },
        {
            "category":"Shopping",
            "subcategory":"Luggage & Leather Goods",
            "type":"Retail Goods"
        },
        {
            "category":"Utilities",
            "type":"Services"
        }
    ],
    "sg:phone":"+1 617 227 0436",
    "sg:postcode":"02113",
    "sg:province":"MA",
    "sg:tags":[
        "repair"
    ],
    "wof:name":"Logan Luggage",
    "wof:placetype":"venue"
},
  "geometry": {"coordinates":[-71.053476,42.364072],"type":"Point"}
}