{
  "type": "Feature",
  "properties": {
    "addr:full":"20 Stockbridge Rd Great Barrington MA 01230",
    "addr:housenumber":"20",
    "addr:postcode":"01230",
    "addr:street":"Stockbridge Rd",
    "iso:country":"US",
    "sg:address":"20 Stockbridge Rd",
    "sg:city":"Great Barrington",
    "sg:classifiers":[
        {
            "category":"Real Estate",
            "subcategory":"Real Estate Agent",
            "type":"Services"
        }
    ],
    "sg:phone":"+1 413 528 8820",
    "sg:postcode":"01230",
    "sg:province":"MA",
    "wof:name":"Hebert Realty Inc",
    "wof:placetype":"venue"
},
  "geometry": {"coordinates":[-73.347267,42.202261],"type":"Point"}
}