{
  "type": "Feature",
  "properties": {
    "addr:full": "1026 Commonwealth Ave Newton Center MA 02459",
    "addr:housenumber": "1026",
    "addr:postcode": "02459",
    "addr:street": "Commonwealth Ave Newton Center",
    "iso:country": "US",
    "sg:address": "1026 Commonwealth Ave",
    "sg:city": "Newton Center",
    "sg:classifiers": [
      {
        "category": "Retail",
        "subcategory": "Repair Shop",
        "type": "Services"
      }
    ],
    "sg:phone": "+1 617 477 0270",
    "sg:postcode": "02459",
    "sg:province": "MA",
    "sg:tags": [
      "lock",
      "locksmith"
    ],
    "wof:name": "24 Hour Emergency Locksmith",
    "wof:placetype": "venue"
  },
  "geometry": {"coordinates":[-71.211573,42.33802],"type":"Point"}
}
