{
  "type": "Feature",
  "properties": {
    "addr:full": "12 Kendrick Rd Wareham MA 02571",
    "addr:housenumber": "12",
    "addr:postcode": "02571",
    "addr:street": "Kendrick Rd",
    "iso:country": "US",
    "ovtr:label": "Prism Powder Coating, 12 Kendrick Rd Wareham MA US",
    "ovtr:similarity": 1.9805539846420288,
    "sg:address": "12 Kendrick Rd",
    "sg:city": "Wareham",
    "sg:classifiers": [
      {
        "category": "Manufacturing",
        "subcategory": "Metals",
        "type": "Manufacturing \u0026 Wholesale Goods"
      }
    ],
    "sg:phone": "+1 508 295 5601",
    "sg:postcode": "02571",
    "sg:province": "MA",
    "sg:tags": [
      "finisher"
    ],
    "wof:name": "Prism Powder Coating",
    "wof:placetype": "venue"
  },
  "geometry": {"coordinates":[-70.739134,41.782429],"type":"Point"}
}
