{
  "type": "Feature",
  "properties": {
    "addr:full":"214 Harvard St Ste 1 Dorchester Center MA 02124",
    "addr:housenumber":"214",
    "addr:postcode":"02124",
    "addr:street":"Harvard St Ste 1 Dorchester Center",
    "iso:country":"US",
    "sg:address":"214 Harvard St Ste 1",
    "sg:city":"Dorchester Center",
    "sg:classifiers":[
        {
            "category":"Organizations",
            "subcategory":"Non-profit Organization",
            "type":"Services"
        }
    ],
    "sg:phone":"+1 617 436 0394",
    "sg:postcode":"02124",
    "sg:province":"MA",
    "sg:tags":[
        "service/non-profit",
        "community"
    ],
    "wof:name":"Boston Aging Concerns You",
    "wof:placetype":"venue"
},
  "geometry": {"coordinates":[-71.0853,42.2953],"type":"Point"}
}