{
  "type": "Feature",
  "properties": {
    "iso:country":"US",
    "sg:address":"2 Judith Rd",
    "sg:city":"Natick",
    "sg:classifiers":[
        {
            "category":"Building & Trades",
            "subcategory":"Construction",
            "type":"Services"
        }
    ],
    "sg:phone":"+1   ",
    "sg:postcode":"01760",
    "sg:province":"MA",
    "sg:tags":[
        "house"
    ],
    "wof:name":"Gino D Antonio Co",
    "wof:placetype":"venue"
},
  "geometry": {"coordinates":[-71.36499499999999,42.294717],"type":"Point"}
}