{
  "type": "Feature",
  "properties": {
    "addr:full": "2 Judith Rd Natick MA 01760",
    "addr:housenumber": "2",
    "addr:postcode": "01760",
    "addr:street": "Judith Rd",
    "iso:country": "US",
    "sg:address": "2 Judith Rd",
    "sg:city": "Natick",
    "sg:classifiers": [
      {
        "category": "Building \u0026 Trades",
        "subcategory": "Construction",
        "type": "Services"
      }
    ],
    "sg:phone": "+1   ",
    "sg:postcode": "01760",
    "sg:province": "MA",
    "sg:tags": [
      "house"
    ],
    "wof:name": "Gino D Antonio Co",
    "wof:placetype": "venue"
  },
  "geometry": {"coordinates":[-71.364995,42.294717],"type":"Point"}
}
