{
  "type": "Feature",
  "properties": {
    "addr:full": "30 Cedar St Wakefield MA 01880",
    "addr:housenumber": "30",
    "addr:postcode": "01880",
    "addr:street": "Cedar St",
    "iso:country": "US",
    "sg:address": "30 Cedar St",
    "sg:city": "Wakefield",
    "sg:classifiers": [
      {
        "category": "Social Services",
        "subcategory": "Adult Care",
        "type": "Services"
      }
    ],
    "sg:phone": "+1 781 245 5983",
    "sg:postcode": "01880",
    "sg:province": "MA",
    "sg:tags": [
      "home",
      "residential"
    ],
    "wof:name": "Cedar Street",
    "wof:placetype": "venue"
  },
  "geometry": {"coordinates":[-71.079904,42.503352],"type":"Point"}
}
