{
  "type": "Feature",
  "properties": {
    "addr:full":"84 Woodrow Ave Haverhill MA 01830",
    "addr:housenumber":"84",
    "addr:postcode":"01830",
    "addr:street":"Woodrow Ave",
    "iso:country":"US",
    "sg:address":"84 Woodrow Ave",
    "sg:city":"Haverhill",
    "sg:classifiers":[
        {
            "category":"Professional",
            "subcategory":"Business Services",
            "type":"Services"
        }
    ],
    "sg:phone":"+1   ",
    "sg:postcode":"01830",
    "sg:province":"MA",
    "sg:tags":[
        "finishing",
        "furniture"
    ],
    "wof:name":"Custom Finishing",
    "wof:placetype":"venue"
},
  "geometry": {"coordinates":[-71.099346,42.809366],"type":"Point"}
}