{
  "type": "Feature",
  "properties": {
    "addr:full":"150 Alford St Charlestown MA 02129",
    "addr:housenumber":"150",
    "addr:postcode":"02129",
    "addr:street":"Alford St",
    "iso:country":"US",
    "sg:address":"150 Alford St",
    "sg:city":"Charlestown",
    "sg:classifiers":[
        {
            "category":"Retail",
            "subcategory":"Car Wash",
            "type":"Services"
        }
    ],
    "sg:phone":"+1 617 387 1770",
    "sg:postcode":"02129",
    "sg:province":"MA",
    "sg:website":"www.rideandshinecarwash.com",
    "wof:name":"Ride & Shine Car Wash",
    "wof:placetype":"venue"
},
  "geometry": {"coordinates":[-71.07244,42.387749],"type":"Point"}
}