{
  "type": "Feature",
  "properties": {
    "addr:full":"1299 Main St Hanson MA 02341",
    "addr:housenumber":"1299",
    "addr:postcode":"02341",
    "addr:street":"Main St",
    "iso:country":"US",
    "sg:address":"1299 Main St",
    "sg:city":"Hanson",
    "sg:classifiers":[
        {
            "category":"Manufacturing",
            "subcategory":"Metals",
            "type":"Manufacturing & Wholesale Goods"
        }
    ],
    "sg:phone":"+1 781 293 0382",
    "sg:postcode":"02341",
    "sg:province":"MA",
    "sg:tags":[
        "tube",
        "fabricating"
    ],
    "wof:name":"R C Tube Design",
    "wof:placetype":"venue"
},
  "geometry": {"coordinates":[-70.88330499999999,42.043292],"type":"Point"}
}