{
  "type": "Feature",
  "properties": {
    "iso:country":"US",
    "sg:address":"450 N Main St",
    "sg:city":"Sharon",
    "sg:classifiers":[
        {
            "category":"Health Services",
            "subcategory":"Dentist",
            "type":"Services"
        }
    ],
    "sg:phone":"+1 781 784 3330",
    "sg:postcode":"02067",
    "sg:province":"MA",
    "wof:name":"Goodman Lawrence DMD",
    "wof:placetype":"venue"
},
  "geometry": {"coordinates":[-71.1521,42.137699],"type":"Point"}
}