{
  "type": "Feature",
  "properties": {
    "iso:country":"US",
    "sg:address":"181 Pearl St",
    "sg:city":"Somerville",
    "sg:classifiers":[
        {
            "category":"Home & Garden",
            "subcategory":"Home Furnishings",
            "type":"Retail Goods"
        }
    ],
    "sg:phone":"+1 617 623 9191",
    "sg:postcode":"02145",
    "sg:province":"MA",
    "sg:tags":[
        "pottery",
        "school",
        "art"
    ],
    "sg:website":"www.nanhamilton.com/mudville/mud...",
    "wof:name":"Mudville",
    "wof:placetype":"venue"
},
  "geometry": {"coordinates":[-71.09087599999999,42.386641],"type":"Point"}
}