{
  "type": "Feature",
  "properties": {
    "iso:country":"US",
    "sg:address":"24 Prospect St",
    "sg:city":"Maynard",
    "sg:classifiers":[
        {
            "category":"Restaurant",
            "type":"Food & Drink"
        }
    ],
    "sg:phone":"+1 978 897 4655",
    "sg:postcode":"01754",
    "sg:province":"MA",
    "wof:name":"Beef And Ale Restaurant",
    "wof:placetype":"venue"
},
  "geometry": {"coordinates":[-71.449753,42.436371],"type":"Point"}
}