{
  "type": "Feature",
  "properties": {
    "addr:full": "24 Prospect St Maynard MA 01754",
    "addr:housenumber": "24",
    "addr:postcode": "01754",
    "addr:street": "Prospect St",
    "iso:country": "US",
    "sg:address": "24 Prospect St",
    "sg:city": "Maynard",
    "sg:classifiers": [
      {
        "category": "Restaurant",
        "type": "Food \u0026 Drink"
      }
    ],
    "sg:phone": "+1 978 897 4655",
    "sg:postcode": "01754",
    "sg:province": "MA",
    "wof:name": "Beef And Ale Restaurant",
    "wof:placetype": "venue"
  },
  "geometry": {"coordinates":[-71.449753,42.436371],"type":"Point"}
}
