{
  "type": "Feature",
  "properties": {
    "addr:full": "183 Babcock St Brookline MA 02446",
    "addr:housenumber": "183",
    "addr:postcode": "02446",
    "addr:street": "Babcock St",
    "iso:country": "US",
    "sg:address": "183 Babcock St",
    "sg:city": "Brookline",
    "sg:classifiers": [
      {
        "category": "Cinema",
        "subcategory": "Movie Rental",
        "type": "Entertainment"
      }
    ],
    "sg:phone": "+1 617 739 6164",
    "sg:postcode": "02446",
    "sg:province": "MA",
    "sg:tags": [
      "picture",
      "exchange",
      "motion",
      "distributor",
      "film"
    ],
    "wof:name": "Steadman Productions, Inc.",
    "wof:placetype": "venue"
  },
  "geometry": {"coordinates":[-71.121307,42.349491],"type":"Point"}
}
