{
  "type": "Feature",
  "properties": {
    "iso:country":"US",
    "sg:address":"76 Bedford St Ste 19",
    "sg:city":"Lexington",
    "sg:classifiers":[
        {
            "category":"Health Services",
            "subcategory":"Doctor",
            "type":"Services"
        },
        {
            "category":"Health Services",
            "subcategory":"Clinic",
            "type":"Services"
        }
    ],
    "sg:phone":"+1 781 863 5600",
    "sg:postcode":"02420",
    "sg:province":"MA",
    "sg:tags":[
        "psychological",
        "psychologist"
    ],
    "wof:name":"Janice Levine",
    "wof:placetype":"venue"
},
  "geometry": {"coordinates":[-71.233559,42.454319],"type":"Point"}
}