{
  "type": "Feature",
  "properties": {
    "addr:full": "504 Quincy Ave Braintree MA 02184",
    "addr:housenumber": "504",
    "addr:postcode": "02184",
    "addr:street": "Quincy Ave",
    "iso:country": "US",
    "sg:address": "504 Quincy Ave",
    "sg:city": "Braintree",
    "sg:classifiers": [
      {
        "category": "Retail",
        "subcategory": "Auto Repair",
        "type": "Services"
      }
    ],
    "sg:phone": "+1 781 843 0110",
    "sg:postcode": "02184",
    "sg:province": "MA",
    "sg:tags": [
      "automobile",
      "lubrication"
    ],
    "sg:website": "www.jiffylube.com",
    "wof:name": "Jiffy Lube",
    "wof:placetype": "venue"
  },
  "geometry": {"coordinates":[-70.97795,42.23467],"type":"Point"}
}
