{
  "type": "Feature",
  "properties": {
    "iso:country":"US",
    "sg:address":"77 Warren St Building 2",
    "sg:city":"Brighton",
    "sg:classifiers":[
        {
            "category":"Health Services",
            "subcategory":"Clinic",
            "type":"Services"
        }
    ],
    "sg:phone":"+1 617 787 1901",
    "sg:postcode":"02135",
    "sg:province":"MA",
    "sg:tags":[
        "counseling",
        "mental"
    ],
    "wof:name":"Brighton Allston Mental Health Association",
    "wof:placetype":"venue"
},
  "geometry": {"coordinates":[-71.142329,42.349401],"type":"Point"}
}