{
  "type": "Feature",
  "properties": {
    "iso:country":"US",
    "sg:address":"423 Highland Ave",
    "sg:city":"Fall River",
    "sg:classifiers":[
        {
            "category":"Education",
            "subcategory":"School",
            "type":"Public Place"
        }
    ],
    "sg:phone":"+1 508 678 2828",
    "sg:postcode":"02720",
    "sg:province":"MA",
    "wof:name":"Catholic Education Ctr",
    "wof:placetype":"venue"
},
  "geometry": {"coordinates":[-71.14542,41.711815],"type":"Point"}
}