{
  "type": "Feature",
  "properties": {
    "iso:country":"US",
    "sg:address":"9 Meriam Street Suite 28",
    "sg:city":"Lexington",
    "sg:classifiers":[
        {
            "category":"Sports & Exercise",
            "subcategory":"Gym",
            "type":"Entertainment"
        }
    ],
    "sg:phone":"+1 781 863 1166",
    "sg:postcode":"02420",
    "sg:province":"MA",
    "sg:tags":[
        "trainer"
    ],
    "wof:name":"Cooperative Elder Services",
    "wof:placetype":"venue"
},
  "geometry": {"coordinates":[-71.228831,42.448908],"type":"Point"}
}