{
  "type": "Feature",
  "properties": {
    "addr:full":"73 Barrington Rd Longmeadow MA 01106",
    "addr:housenumber":"73",
    "addr:postcode":"01106",
    "addr:street":"Barrington Rd",
    "iso:country":"US",
    "sg:address":"73 Barrington Rd",
    "sg:city":"Longmeadow",
    "sg:classifiers":[
        {
            "category":"Professional",
            "subcategory":"Research",
            "type":"Services"
        }
    ],
    "sg:phone":"+1   ",
    "sg:postcode":"01106",
    "sg:province":"MA",
    "sg:tags":[
        "nonphysical",
        "commercial"
    ],
    "wof:name":"Independent Contractor",
    "wof:placetype":"venue"
},
  "geometry": {"coordinates":[-72.584801,42.029391],"type":"Point"}
}