{
  "type": "Feature",
  "properties": {
    "iso:country":"US",
    "sg:address":"285 Fellsway W",
    "sg:city":"Medford",
    "sg:classifiers":[
        {
            "category":"Autos & Motor Vehicles",
            "subcategory":"Fuel & Gas Station",
            "type":"Retail Goods"
        }
    ],
    "sg:phone":"+1 781 395 9841",
    "sg:postcode":"02155",
    "sg:province":"MA",
    "sg:tags":[
        "gasoline"
    ],
    "wof:name":"Foley's Fellsway Service",
    "wof:placetype":"venue"
},
  "geometry": {"coordinates":[-71.097037,42.425456],"type":"Point"}
}