{
  "type": "Feature",
  "properties": {
    "addr:full":"235 Wyman St Waltham MA 02451",
    "addr:housenumber":"235",
    "addr:postcode":"02451",
    "addr:street":"Wyman St",
    "iso:country":"US",
    "sg:address":"235 Wyman St",
    "sg:city":"Waltham",
    "sg:classifiers":[
        {
            "category":"Professional",
            "subcategory":"Research",
            "type":"Services"
        }
    ],
    "sg:phone":"+1 781 890 5544",
    "sg:postcode":"02451",
    "sg:province":"MA",
    "sg:tags":[
        "laboratory"
    ],
    "wof:name":"Health Assessment Lab",
    "wof:placetype":"venue"
},
  "geometry": {"coordinates":[-71.25883899999999,42.402218],"type":"Point"}
}