{
  "type": "Feature",
  "properties": {
    "addr:full": "53 Austin St Leominster MA 01453",
    "addr:housenumber": "53",
    "addr:postcode": "01453",
    "addr:street": "Austin St",
    "iso:country": "US",
    "sg:address": "53 Austin St",
    "sg:city": "Leominster",
    "sg:classifiers": [
      {
        "category": "Professional",
        "subcategory": "Research",
        "type": "Services"
      }
    ],
    "sg:phone": "+1   ",
    "sg:postcode": "01453",
    "sg:province": "MA",
    "sg:tags": [
      "nonphysical",
      "commercial"
    ],
    "wof:name": "Jim Moran",
    "wof:placetype": "venue"
  },
  "geometry": {"coordinates":[-71.774396,42.543048],"type":"Point"}
}
