{
  "type": "Feature",
  "properties": {
    "iso:country":"US",
    "sg:address":"36 Francis St",
    "sg:city":"Belmont",
    "sg:classifiers":[
        {
            "category":"Freight",
            "type":"Transportation"
        }
    ],
    "sg:phone":"+1   ",
    "sg:postcode":"02478",
    "sg:province":"MA",
    "sg:tags":[
        "operator",
        "local",
        "trucking"
    ],
    "wof:name":"Am Truck",
    "wof:placetype":"venue"
},
  "geometry": {"coordinates":[-71.181738,42.386754],"type":"Point"}
}