{
  "type": "Feature",
  "properties": {
    "iso:country":"US",
    "sg:address":"360 Eastern Ave",
    "sg:city":"Malden",
    "sg:classifiers":[
        {
            "category":"Manufacturing",
            "subcategory":"Printing",
            "type":"Manufacturing & Wholesale Goods"
        }
    ],
    "sg:phone":"+1 781 388 3636",
    "sg:postcode":"02148",
    "sg:province":"MA",
    "sg:tags":[
        "newspaper"
    ],
    "wof:name":"Diario Do Brasil",
    "wof:placetype":"venue"
},
  "geometry": {"coordinates":[-71.057039,42.428119],"type":"Point"}
}