{
  "type": "Feature",
  "properties": {
    "addr:full": "6 May Rd Westford MA 01886",
    "addr:housenumber": "6",
    "addr:postcode": "01886",
    "addr:street": "May Rd",
    "iso:country": "US",
    "sg:address": "6 May Rd",
    "sg:city": "Westford",
    "sg:classifiers": [
      {
        "category": "Food \u0026 Beverages",
        "subcategory": "Specialty",
        "type": "Retail Goods"
      }
    ],
    "sg:phone": "+1 978 692 3207",
    "sg:postcode": "01886",
    "sg:province": "MA",
    "sg:tags": [
      "product",
      "health",
      "diet"
    ],
    "wof:name": "Roca Nutrition Inc",
    "wof:placetype": "venue"
  },
  "geometry": {"coordinates":[-71.45127,42.557325],"type":"Point"}
}
