{
  "type": "Feature",
  "properties": {
    "iso:country":"US",
    "sg:address":"400 Border St",
    "sg:city":"East Boston",
    "sg:classifiers":[
        {
            "category":"Retail",
            "subcategory":"Repair Shop",
            "type":"Services"
        }
    ],
    "sg:phone":"+1 617 567 2302",
    "sg:postcode":"02128",
    "sg:province":"MA",
    "sg:tags":[
        "equipment",
        "hydraulic"
    ],
    "wof:name":"R J Hydraulics",
    "wof:placetype":"venue"
},
  "geometry": {"coordinates":[-71.04033200000001,42.381217],"type":"Point"}
}