{
  "type": "Feature",
  "properties": {
    "addr:full": "38 State St Marblehead MA 01945",
    "addr:housenumber": "38",
    "addr:postcode": "01945",
    "addr:street": "State St",
    "iso:country": "US",
    "sg:address": "38 State St",
    "sg:city": "Marblehead",
    "sg:classifiers": [
      {
        "category": "Shopping",
        "subcategory": "Used Merchandise",
        "type": "Retail Goods"
      }
    ],
    "sg:phone": "+1 781 631 0770",
    "sg:postcode": "01945",
    "sg:province": "MA",
    "sg:tags": [
      "antique"
    ],
    "wof:name": "Sacks Antiques",
    "wof:placetype": "venue"
  },
  "geometry": {"coordinates":[-70.847264,42.504413],"type":"Point"}
}
