{
  "type": "Feature",
  "properties": {
    "addr:full": "18 Union St Beverly MA 01915",
    "addr:housenumber": "18",
    "addr:postcode": "01915",
    "addr:street": "Union St",
    "iso:country": "US",
    "sg:address": "18 Union St",
    "sg:city": "Beverly",
    "sg:classifiers": [
      {
        "category": "Real Estate",
        "subcategory": "Surveying",
        "type": "Services"
      }
    ],
    "sg:phone": "+1 978 927 4048",
    "sg:postcode": "01915",
    "sg:province": "MA",
    "wof:name": "Bartram Land Survey",
    "wof:placetype": "venue"
  },
  "geometry": {"coordinates":[-70.881904,42.543409],"type":"Point"}
}
