{
  "type": "Feature",
  "properties": {
    "addr:full":"1704 Beacon St Brookline MA 02445",
    "addr:housenumber":"1704",
    "addr:postcode":"02445",
    "addr:street":"Beacon St",
    "iso:country":"US",
    "sg:address":"1704 Beacon St",
    "sg:city":"Brookline",
    "sg:classifiers":[
        {
            "category":"Restaurant",
            "type":"Food & Drink"
        }
    ],
    "sg:phone":"+1 617 879 9100",
    "sg:postcode":"02445",
    "sg:province":"MA",
    "sg:tags":[
        "fusion",
        "asian"
    ],
    "sg:website":"umamiboston.com/",
    "wof:name":"Umami",
    "wof:placetype":"venue"
},
  "geometry": {"coordinates":[-71.138908,42.338616],"type":"Point"}
}