{
  "type": "Feature",
  "properties": {
    "addr:full":"69 Rogers St Gloucester MA 01930",
    "addr:housenumber":"69",
    "addr:postcode":"01930",
    "addr:street":"Rogers St",
    "iso:country":"US",
    "sg:address":"69 Rogers St",
    "sg:city":"Gloucester",
    "sg:classifiers":[
        {
            "category":"Wholesale",
            "subcategory":"Seafood",
            "type":"Manufacturing & Wholesale Goods"
        }
    ],
    "sg:phone":"+1 978 283 7422",
    "sg:postcode":"01930",
    "sg:province":"MA",
    "wof:name":"Yeomen Seafoods Inc",
    "wof:placetype":"venue"
},
  "geometry": {"coordinates":[-70.66270400000001,42.611907],"type":"Point"}
}