{
  "type": "Feature",
  "properties": {
    "iso:country":"US",
    "sg:address":"257 Ambrose St",
    "sg:city":"Springfield",
    "sg:classifiers":[
        {
            "category":"Professional",
            "subcategory":"Business Services",
            "type":"Services"
        },
        {
            "category":"Professional",
            "subcategory":"Computer Services",
            "type":"Services"
        }
    ],
    "sg:phone":"+1 413 783 5900",
    "sg:postcode":"01109",
    "sg:province":"MA",
    "sg:tags":[
        "consultant",
        "coach",
        "design",
        "network",
        "system"
    ],
    "wof:name":"Dreamscrying Online",
    "wof:placetype":"venue"
},
  "geometry": {"coordinates":[-72.535017,42.118024],"type":"Point"}
}