{
  "type": "Feature",
  "properties": {
    "addr:full":"46 Gammons Rd Cohasset MA 02025",
    "addr:housenumber":"46",
    "addr:postcode":"02025",
    "addr:street":"Gammons Rd",
    "iso:country":"US",
    "sg:address":"46 Gammons Rd",
    "sg:city":"Cohasset",
    "sg:classifiers":[
        {
            "category":"Professional",
            "subcategory":"Management & Consulting",
            "type":"Services"
        }
    ],
    "sg:phone":"+1   ",
    "sg:postcode":"02025",
    "sg:province":"MA",
    "wof:name":"Stoneworks Strgc Consulting",
    "wof:placetype":"venue"
},
  "geometry": {"coordinates":[-70.80714999999999,42.25078],"type":"Point"}
}