{
  "type": "Feature",
  "properties": {
    "addr:full": "3 Hadley St South Hadley MA 01075",
    "addr:housenumber": "3",
    "addr:postcode": "01075",
    "addr:street": "Hadley St",
    "iso:country": "US",
    "sg:address": "3 Hadley St",
    "sg:city": "South Hadley",
    "sg:classifiers": [
      {
        "category": "Real Estate",
        "subcategory": "Real Estate Agent",
        "type": "Services"
      }
    ],
    "sg:phone": "+1 413 534 0198",
    "sg:postcode": "01075",
    "sg:province": "MA",
    "wof:name": "Chestnut Hill Real Estate",
    "wof:placetype": "venue"
  },
  "geometry": {"coordinates":[-72.574606,42.259296],"type":"Point"}
}
