{
  "type": "Feature",
  "properties": {
    "iso:country":"US",
    "sg:address":"1101 Beacon St",
    "sg:city":"Brookline",
    "sg:classifiers":[
        {
            "category":"Health Services",
            "subcategory":"Doctor",
            "type":"Services"
        }
    ],
    "sg:phone":"+1 617 487 4636",
    "sg:postcode":"02446",
    "sg:province":"MA",
    "sg:tags":[
        "physician",
        "reconstructive",
        "surgeons",
        "cosmetic",
        "plastic",
        "surgery"
    ],
    "sg:website":"http://bostoneyegroup.reachlocal.com/?scid=1917392",
    "wof:name":"Wrinkle Reduction & More",
    "wof:placetype":"venue"
},
  "geometry": {"coordinates":[-71.11084700000001,42.344872],"type":"Point"}
}