{
  "type": "Feature",
  "properties": {
    "addr:full": "1392 Main St Holden MA 01520",
    "addr:housenumber": "1392",
    "addr:postcode": "01520",
    "addr:street": "Main St",
    "iso:country": "US",
    "sg:address": "1392 Main St",
    "sg:city": "Holden",
    "sg:classifiers": [
      {
        "category": "Restaurant",
        "type": "Food \u0026 Drink"
      }
    ],
    "sg:phone": "+1 508 829 4006",
    "sg:postcode": "01520",
    "sg:province": "MA",
    "wof:name": "K P's Breakfast \u0026 Lunch",
    "wof:placetype": "venue"
  },
  "geometry": {"coordinates":[-71.871576,42.353305],"type":"Point"}
}
