{
  "type": "Feature",
  "properties": {
    "addr:full": "546 E Broadway Boston MA 02127",
    "addr:housenumber": "546",
    "addr:postcode": "02127",
    "addr:street": "E Broadway",
    "iso:country": "US",
    "sg:address": "546 E Broadway",
    "sg:city": "Boston",
    "sg:classifiers": [
      {
        "category": "Professional",
        "subcategory": "Lawyer \u0026 Legal Services",
        "type": "Services"
      }
    ],
    "sg:phone": "+1 617 323 5526",
    "sg:postcode": "02127",
    "sg:province": "MA",
    "wof:name": "Anderson \u0026 Moynihan Atty",
    "wof:placetype": "venue"
  },
  "geometry": {"coordinates":[-71.042397,42.3354],"type":"Point"}
}
