{
  "type": "Feature",
  "properties": {
    "addr:full": "25 Tyler St Boston MA 02111",
    "addr:housenumber": "25",
    "addr:postcode": "02111",
    "addr:street": "Tyler St",
    "iso:country": "US",
    "sg:address": "25 Tyler St",
    "sg:city": "Boston",
    "sg:classifiers": [
      {
        "category": "Utilities",
        "subcategory": "Mobile Phone",
        "type": "Services"
      }
    ],
    "sg:phone": "+1 617 292 3088",
    "sg:postcode": "02111",
    "sg:province": "MA",
    "sg:tags": [
      "telephone",
      "cellular"
    ],
    "wof:name": "Fusion Wireless",
    "wof:placetype": "venue"
  },
  "geometry": {"coordinates":[-71.060652,42.351324],"type":"Point"}
}
