{
  "type": "Feature",
  "properties": {
    "iso:country":"US",
    "sg:address":"20 Circuit St",
    "sg:city":"Medford",
    "sg:classifiers":[
        {
            "category":"Professional",
            "subcategory":"Employment Agencies",
            "type":"Services"
        },
        {
            "category":"Professional",
            "subcategory":"Lawyer & Legal Services",
            "type":"Services"
        }
    ],
    "sg:phone":"+1 781 777 2423",
    "sg:postcode":"02155",
    "sg:province":"MA",
    "sg:tags":[
        "convention",
        "secretarial",
        "reporters-court"
    ],
    "wof:name":"Jennifer Hunter",
    "wof:placetype":"venue"
},
  "geometry": {"coordinates":[-71.13070500000001,42.419293],"type":"Point"}
}