{
  "type": "Feature",
  "properties": {
    "addr:full": "420 Broadway Malden MA 02148",
    "addr:housenumber": "420",
    "addr:postcode": "02148",
    "addr:street": "Broadway",
    "iso:country": "US",
    "sg:address": "420 Broadway",
    "sg:city": "Malden",
    "sg:classifiers": [
      {
        "category": "Health Services",
        "subcategory": "Optometrist",
        "type": "Services"
      }
    ],
    "sg:phone": "+1   ",
    "sg:postcode": "02148",
    "sg:province": "MA",
    "sg:tags": [
      "optical",
      "good"
    ],
    "wof:name": "Steven M Liberfarb",
    "wof:placetype": "venue"
  },
  "geometry": {"coordinates":[-71.03693,42.436934],"type":"Point"}
}
