{
  "type": "Feature",
  "properties": {
    "iso:country":"US",
    "sg:address":"434 Chelsea St",
    "sg:city":"Boston",
    "sg:classifiers":[
        {
            "category":"Professional",
            "subcategory":"Detective & Security Services",
            "type":"Services"
        }
    ],
    "sg:phone":"+1 617 569 4588",
    "sg:postcode":"02128",
    "sg:province":"MA",
    "sg:tags":[
        "constable"
    ],
    "wof:name":"Jackson & Phoenix",
    "wof:placetype":"venue"
},
  "geometry": {"coordinates":[-71.026032,42.380843],"type":"Point"}
}