{
  "type": "Feature",
  "properties": {
    "addr:full":"481 Boston Rd Billerica MA 01821",
    "addr:housenumber":"481",
    "addr:postcode":"01821",
    "addr:street":"Boston Rd",
    "iso:country":"US",
    "sg:address":"481 Boston Rd",
    "sg:city":"Billerica",
    "sg:classifiers":[
        {
            "category":"Restaurant",
            "type":"Food & Drink"
        }
    ],
    "sg:phone":"+1 978 663 7737",
    "sg:postcode":"01821",
    "sg:province":"MA",
    "sg:tags":[
        "italian",
        "pizza"
    ],
    "sg:website":"www.strombolisexpressma.com",
    "wof:name":"Stromboli's",
    "wof:placetype":"venue"
},
  "geometry": {"coordinates":[-71.264397,42.553299],"type":"Point"}
}