{
  "type": "Feature",
  "properties": {
    "addr:full":"39 Court St Groton MA 01450",
    "addr:housenumber":"39",
    "addr:postcode":"01450",
    "addr:street":"Court St",
    "iso:country":"US",
    "sg:address":"39 Court St",
    "sg:city":"Groton",
    "sg:classifiers":[
        {
            "category":"Professional",
            "subcategory":"Computer Services",
            "type":"Services"
        }
    ],
    "sg:phone":"+1 978 448 9340",
    "sg:postcode":"01450",
    "sg:province":"MA",
    "sg:tags":[
        "consultant",
        "designer"
    ],
    "sg:website":"www.etcbin.com",
    "wof:name":"EBS",
    "wof:placetype":"venue"
},
  "geometry": {"coordinates":[-71.573497,42.608305],"type":"Point"}
}