{
  "type": "Feature",
  "properties": {
    "addr:full":"65 Sears Rd Wayland MA 01778",
    "addr:housenumber":"65",
    "addr:postcode":"01778",
    "addr:street":"Sears Rd",
    "iso:country":"US",
    "sg:address":"65 Sears Rd",
    "sg:city":"Wayland",
    "sg:classifiers":[
        {
            "category":"Wholesale",
            "subcategory":"Durable Goods & Equipment",
            "type":"Manufacturing & Wholesale Goods"
        }
    ],
    "sg:phone":"+1 508 358 5161",
    "sg:postcode":"01778",
    "sg:province":"MA",
    "sg:tags":[
        "representative",
        "manufacturer"
    ],
    "wof:name":"Centennial Sales Co",
    "wof:placetype":"venue"
},
  "geometry": {"coordinates":[-71.342186,42.377507],"type":"Point"}
}