{
  "type": "Feature",
  "properties": {
    "addr:full": "156 Cambridge St Burlington MA 01803",
    "addr:housenumber": "156",
    "addr:postcode": "01803",
    "addr:street": "Cambridge St",
    "iso:country": "US",
    "sg:address": "156 Cambridge St",
    "sg:city": "Burlington",
    "sg:classifiers": [
      {
        "category": "Shopping",
        "subcategory": "Department Store",
        "type": "Retail Goods"
      },
      {
        "category": "Home \u0026 Garden",
        "subcategory": "Carpets \u0026 Floor Coverings",
        "type": "Retail Goods"
      }
    ],
    "sg:phone": "+1 781 272 1919",
    "sg:postcode": "01803",
    "sg:province": "MA",
    "sg:tags": [
      "carpeting",
      "mattress"
    ],
    "wof:name": "Building 19-1 2 Sales Co",
    "wof:placetype": "venue"
  },
  "geometry": {"coordinates":[-71.196503,42.5075],"type":"Point"}
}
