{
  "type": "Feature",
  "properties": {
    "iso:country":"US",
    "sg:address":"139 North St",
    "sg:city":"Mattapoisett",
    "sg:classifiers":[
        {
            "category":"Marine",
            "type":"Transportation"
        }
    ],
    "sg:phone":"+1 508 758 9409",
    "sg:postcode":"02739",
    "sg:province":"MA",
    "sg:tags":[
        "transporting",
        "boat"
    ],
    "wof:name":"Maritime Boat Transport",
    "wof:placetype":"venue"
},
  "geometry": {"coordinates":[-70.831559,41.685725],"type":"Point"}
}