{
  "type": "Feature",
  "properties": {
    "addr:full": "208 Fitchburg Tpke Concord MA 01742",
    "addr:housenumber": "208",
    "addr:postcode": "01742",
    "addr:street": "Fitchburg Tpke",
    "iso:country": "US",
    "sg:address": "208 Fitchburg Tpke",
    "sg:city": "Concord",
    "sg:classifiers": [
      {
        "category": "Restaurant",
        "type": "Food \u0026 Drink"
      }
    ],
    "sg:phone": "+1 978 635 9040",
    "sg:postcode": "01742",
    "sg:province": "MA",
    "wof:name": "Rossini Pizzeria \u0026 Rest",
    "wof:placetype": "venue"
  },
  "geometry": {"coordinates":[-71.373366,42.42112],"type":"Point"}
}
