{
  "type": "Feature",
  "properties": {
    "iso:country":"US",
    "sg:address":"208 Fitchburg Tpke",
    "sg:city":"Concord",
    "sg:classifiers":[
        {
            "category":"Restaurant",
            "type":"Food & Drink"
        }
    ],
    "sg:phone":"+1 978 635 9040",
    "sg:postcode":"01742",
    "sg:province":"MA",
    "wof:name":"Rossini Pizzeria & Rest",
    "wof:placetype":"venue"
},
  "geometry": {"coordinates":[-71.373366,42.42112],"type":"Point"}
}