{
  "type": "Feature",
  "properties": {
    "iso:country":"US",
    "sg:address":"19 Varnum St",
    "sg:city":"Lowell",
    "sg:classifiers":[
        {
            "category":"Health Services",
            "subcategory":"Nursing And Care Facility",
            "type":"Services"
        }
    ],
    "sg:phone":"+1 978 454 5644",
    "sg:postcode":"01850",
    "sg:province":"MA",
    "sg:tags":[
        "home",
        "convalescent"
    ],
    "wof:name":"Lowell Healthcare Ctr",
    "wof:placetype":"venue"
},
  "geometry": {"coordinates":[-71.300326,42.652084],"type":"Point"}
}