{
  "type": "Feature",
  "properties": {
    "addr:full": "1 Condito Rd Hingham MA 02043",
    "addr:housenumber": "1",
    "addr:postcode": "02043",
    "addr:street": "Condito Rd",
    "iso:country": "US",
    "sg:address": "1 Condito Rd",
    "sg:city": "Hingham",
    "sg:classifiers": [
      {
        "category": "Professional",
        "subcategory": "Lawyer \u0026 Legal Services",
        "type": "Services"
      }
    ],
    "sg:phone": "+1 781 749 8708",
    "sg:postcode": "02043",
    "sg:province": "MA",
    "sg:tags": [
      "attorney"
    ],
    "wof:name": "Clarke Law Pc",
    "wof:placetype": "venue"
  },
  "geometry": {"coordinates":[-70.904259,42.251209],"type":"Point"}
}
