{
  "type": "Feature",
  "properties": {
    "addr:full": "48 Cove Cir Marion MA 02738",
    "addr:housenumber": "48",
    "addr:postcode": "02738",
    "addr:street": "Cove Cir",
    "iso:country": "US",
    "sg:address": "48 Cove Cir",
    "sg:city": "Marion",
    "sg:classifiers": [
      {
        "category": "Farming",
        "subcategory": "Berry Farm",
        "type": "Manufacturing \u0026 Wholesale Goods"
      }
    ],
    "sg:phone": "+1   ",
    "sg:postcode": "02738",
    "sg:province": "MA",
    "sg:tags": [
      "crop"
    ],
    "wof:name": "Phoenix Cranberry",
    "wof:placetype": "venue"
  },
  "geometry": {"coordinates":[-70.726248,41.695893],"type":"Point"}
}
