{
  "type": "Feature",
  "properties": {
    "iso:country":"US",
    "sg:address":"48 Cove Cir",
    "sg:city":"Marion",
    "sg:classifiers":[
        {
            "category":"Farming",
            "subcategory":"Berry Farm",
            "type":"Manufacturing & Wholesale Goods"
        }
    ],
    "sg:phone":"+1   ",
    "sg:postcode":"02738",
    "sg:province":"MA",
    "sg:tags":[
        "crop"
    ],
    "wof:name":"Phoenix Cranberry",
    "wof:placetype":"venue"
},
  "geometry": {"coordinates":[-70.726248,41.695893],"type":"Point"}
}