{
  "type": "Feature",
  "properties": {
    "iso:country":"US",
    "sg:address":"1 Wayside Ave",
    "sg:city":"Byfield",
    "sg:classifiers":[
        {
            "category":"Building & Trades",
            "subcategory":"Construction",
            "type":"Services"
        }
    ],
    "sg:phone":"+1 978 465 3649",
    "sg:postcode":"01922",
    "sg:province":"MA",
    "sg:tags":[
        "contractor"
    ],
    "wof:name":"Pearson's Septic Service - CLOSED",
    "wof:placetype":"venue"
},
  "geometry": {"coordinates":[-70.938698,42.759602],"type":"Point"}
}