{
  "type": "Feature",
  "properties": {
    "iso:country":"US",
    "sg:address":"358 Pleasant St",
    "sg:city":"Belmont",
    "sg:classifiers":[
        {
            "category":"Retail",
            "subcategory":"Auto Repair",
            "type":"Services"
        }
    ],
    "sg:phone":"+1 617 489 6548",
    "sg:postcode":"02478",
    "sg:province":"MA",
    "sg:tags":[
        "repairing",
        "automobile"
    ],
    "wof:name":"Benz Den",
    "wof:placetype":"venue"
},
  "geometry": {"coordinates":[-71.167187,42.403515],"type":"Point"}
}