{
  "type": "Feature",
  "properties": {
    "iso:country":"US",
    "sg:address":"14 de Marco Ter",
    "sg:city":"Worcester",
    "sg:classifiers":[
        {
            "category":"Retail",
            "subcategory":"Auto Repair",
            "type":"Services"
        }
    ],
    "sg:phone":"+1 508 754 0625",
    "sg:postcode":"01604",
    "sg:province":"MA",
    "sg:tags":[
        "general"
    ],
    "wof:name":"Bay State Auto",
    "wof:placetype":"venue"
},
  "geometry": {"coordinates":[-71.78507,42.26489],"type":"Point"}
}