{
  "type": "Feature",
  "properties": {
    "addr:full": "192 North Ave Attleboro MA 02703",
    "addr:housenumber": "192",
    "addr:postcode": "02703",
    "addr:street": "North Ave",
    "iso:country": "US",
    "sg:address": "192 North Ave",
    "sg:city": "Attleboro",
    "sg:classifiers": [
      {
        "category": "Professional",
        "subcategory": "Secretarial Services",
        "type": "Services"
      }
    ],
    "sg:phone": "+1   ",
    "sg:postcode": "02703",
    "sg:province": "MA",
    "sg:tags": [
      "support"
    ],
    "wof:name": "Administrative Support Svcs",
    "wof:placetype": "venue"
  },
  "geometry": {"coordinates":[-71.301409,41.964393],"type":"Point"}
}
