{
  "type": "Feature",
  "properties": {
    "iso:country":"US",
    "sg:address":"21 Woodward Ave",
    "sg:city":"Boston",
    "sg:classifiers":[
        {
            "category":"Professional",
            "subcategory":"Business Services",
            "type":"Services"
        }
    ],
    "sg:phone":"+1   ",
    "sg:postcode":"02119",
    "sg:province":"MA",
    "wof:name":"Wynlyn Enterprises LLC",
    "wof:placetype":"venue"
},
  "geometry": {"coordinates":[-71.072637,42.325251],"type":"Point"}
}