{
  "type": "Feature",
  "properties": {
    "iso:country":"US",
    "sg:address":"1783A Centre Street",
    "sg:city":"West Roxbury",
    "sg:classifiers":[
        {
            "category":"Personal",
            "subcategory":"Beauty Salon",
            "type":"Services"
        }
    ],
    "sg:phone":"+1 617 325 8467",
    "sg:postcode":"02132",
    "sg:province":"MA",
    "sg:tags":[
        "hair"
    ],
    "wof:name":"The Cutting Edge",
    "wof:placetype":"venue"
},
  "geometry": {"coordinates":[-71.151253,42.287322],"type":"Point"}
}