{
  "type": "Feature",
  "properties": {
    "addr:full": "200 Walnut St Dedham MA 02026",
    "addr:housenumber": "200",
    "addr:postcode": "02026",
    "addr:street": "Walnut St",
    "iso:country": "US",
    "sg:address": "200 Walnut St",
    "sg:city": "Dedham",
    "sg:classifiers": [
      {
        "category": "Professional",
        "subcategory": "Business Services",
        "type": "Services"
      }
    ],
    "sg:phone": "+1   ",
    "sg:postcode": "02026",
    "sg:province": "MA",
    "wof:name": "Kevin Maher",
    "wof:placetype": "venue"
  },
  "geometry": {"coordinates":[-71.15886,42.242242],"type":"Point"}
}
