{
  "type": "Feature",
  "properties": {
    "addr:full":"240 Branch St Mansfield MA 02048",
    "addr:housenumber":"240",
    "addr:postcode":"02048",
    "addr:street":"Branch St",
    "iso:country":"US",
    "sg:address":"240 Branch St",
    "sg:city":"Mansfield",
    "sg:classifiers":[
        {
            "category":"Wholesale",
            "subcategory":"Chemicals & Plastics",
            "type":"Manufacturing & Wholesale Goods"
        }
    ],
    "sg:phone":"+1 508 339 2781",
    "sg:postcode":"02048",
    "sg:province":"MA",
    "wof:name":"Compo Chemical Co Inc",
    "wof:placetype":"venue"
},
  "geometry": {"coordinates":[-71.203311,42.017373],"type":"Point"}
}