{
  "type": "Feature",
  "properties": {
    "addr:full":"44 Taylor St Saugus MA 01906",
    "addr:housenumber":"44",
    "addr:postcode":"01906",
    "addr:street":"Taylor St",
    "iso:country":"US",
    "sg:address":"44 Taylor St",
    "sg:city":"Saugus",
    "sg:classifiers":[
        {
            "category":"Organizations",
            "subcategory":"Community Association",
            "type":"Services"
        }
    ],
    "sg:phone":"+1 781 233 9706",
    "sg:postcode":"01906",
    "sg:province":"MA",
    "sg:tags":[
        "military"
    ],
    "wof:name":"American Legion",
    "wof:placetype":"venue"
},
  "geometry": {"coordinates":[-71.012066,42.46541],"type":"Point"}
}