{
  "type": "Feature",
  "properties": {
    "addr:full": "276 Main St Townsend MA 01469",
    "addr:housenumber": "276",
    "addr:postcode": "01469",
    "addr:street": "Main St",
    "iso:country": "US",
    "sg:address": "276 Main St",
    "sg:city": "Townsend",
    "sg:classifiers": [
      {
        "category": "Education",
        "subcategory": "Library",
        "type": "Public Place"
      }
    ],
    "sg:phone": "+1 978 597 1714",
    "sg:postcode": "01469",
    "sg:province": "MA",
    "sg:website": "www.townsendlibrary.com",
    "wof:name": "Townsend Town Library",
    "wof:placetype": "venue"
  },
  "geometry": {"coordinates":[-71.707318,42.667648],"type":"Point"}
}
