{
  "type": "Feature",
  "properties": {
    "iso:country":"US",
    "sg:address":"276 Main St",
    "sg:city":"Townsend",
    "sg:classifiers":[
        {
            "category":"Education",
            "subcategory":"Library",
            "type":"Public Place"
        }
    ],
    "sg:phone":"+1 978 597 1714",
    "sg:postcode":"01469",
    "sg:province":"MA",
    "sg:website":"www.townsendlibrary.com",
    "wof:name":"Townsend Town Library",
    "wof:placetype":"venue"
},
  "geometry": {"coordinates":[-71.707318,42.667648],"type":"Point"}
}