{
  "type": "Feature",
  "properties": {
    "addr:full": "247 Parkerville Rd Southborough MA 01772",
    "addr:housenumber": "247",
    "addr:postcode": "01772",
    "addr:street": "Parkerville Rd",
    "iso:country": "US",
    "sg:address": "247 Parkerville Rd",
    "sg:city": "Southborough",
    "sg:classifiers": [
      {
        "category": "Building \u0026 Trades",
        "subcategory": "Construction",
        "type": "Services"
      }
    ],
    "sg:phone": "+1 508 485 8851",
    "sg:postcode": "01772",
    "sg:province": "MA",
    "sg:tags": [
      "painter"
    ],
    "wof:name": "Daniel's Painting",
    "wof:placetype": "venue"
  },
  "geometry": {"coordinates":[-71.536626,42.267691],"type":"Point"}
}
