{
  "type": "Feature",
  "properties": {
    "iso:country":"US",
    "sg:address":"138 Main St",
    "sg:city":"Wenham",
    "sg:classifiers":[
        {
            "category":"Government",
            "subcategory":"Office",
            "type":"Public Place"
        }
    ],
    "sg:phone":"+1 978 468 5526",
    "sg:postcode":"01984",
    "sg:province":"MA",
    "sg:tags":[
        "department",
        "commission",
        "conservation",
        "city"
    ],
    "wof:name":"Wenham Conservation Commission",
    "wof:placetype":"venue"
},
  "geometry": {"coordinates":[-70.88755399999999,42.604304],"type":"Point"}
}