{
  "type": "Feature",
  "properties": {
    "iso:country":"US",
    "sg:address":"1322 Worcester St",
    "sg:city":"Natick",
    "sg:classifiers":[
        {
            "category":"Utilities",
            "subcategory":"Mobile Phone",
            "type":"Services"
        }
    ],
    "sg:phone":"+1 508 651 3000",
    "sg:postcode":"01760",
    "sg:province":"MA",
    "sg:tags":[
        "telephone",
        "cellular"
    ],
    "wof:name":"Verizon Wireless",
    "wof:placetype":"venue"
},
  "geometry": {"coordinates":[-71.384078,42.299076],"type":"Point"}
}