{
  "type": "Feature",
  "properties": {
    "addr:full": "643 Main St Springfield MA 01105",
    "addr:housenumber": "643",
    "addr:postcode": "01105",
    "addr:street": "Main St",
    "iso:country": "US",
    "sg:address": "643 Main St",
    "sg:city": "Springfield",
    "sg:classifiers": [
      {
        "category": "Wholesale",
        "subcategory": "Scrap",
        "type": "Manufacturing \u0026 Wholesale Goods"
      }
    ],
    "sg:phone": "+1 413 827 8178",
    "sg:postcode": "01105",
    "sg:province": "MA",
    "sg:tags": [
      "recycling",
      "center"
    ],
    "wof:name": "South End Bottle \u0026 Can Return",
    "wof:placetype": "venue"
  },
  "geometry": {"coordinates":[-72.581386,42.095428],"type":"Point"}
}
