{
  "type": "Feature",
  "properties": {
    "addr:full": "68 Highland Ave Malden MA 02148",
    "addr:housenumber": "68",
    "addr:postcode": "02148",
    "addr:street": "Highland Ave",
    "iso:country": "US",
    "sg:address": "68 Highland Ave",
    "sg:city": "Malden",
    "sg:classifiers": [
      {
        "category": "Shopping",
        "subcategory": "Discount \u0026 Variety Stores",
        "type": "Retail Goods"
      }
    ],
    "sg:phone": "+1 781 322 5294",
    "sg:postcode": "02148",
    "sg:province": "MA",
    "sg:tags": [
      "merchandise"
    ],
    "wof:name": "Klm Industrial Supply Co",
    "wof:placetype": "venue"
  },
  "geometry": {"coordinates":[-71.079788,42.41703],"type":"Point"}
}
