{
  "type": "Feature",
  "properties": {
    "iso:country":"US",
    "sg:address":"68 Highland Ave",
    "sg:city":"Malden",
    "sg:classifiers":[
        {
            "category":"Shopping",
            "subcategory":"Discount & Variety Stores",
            "type":"Retail Goods"
        }
    ],
    "sg:phone":"+1 781 322 5294",
    "sg:postcode":"02148",
    "sg:province":"MA",
    "sg:tags":[
        "merchandise"
    ],
    "wof:name":"Klm Industrial Supply Co",
    "wof:placetype":"venue"
},
  "geometry": {"coordinates":[-71.07978799999999,42.41703],"type":"Point"}
}