{
  "type": "Feature",
  "properties": {
    "iso:country":"US",
    "sg:address":"1355 Washington Street",
    "sg:city":"Roxbury",
    "sg:classifiers":[
        {
            "category":"Banks & Credit Unions",
            "subcategory":"Bank",
            "type":"Services"
        }
    ],
    "sg:phone":"+1 617 422 8240",
    "sg:postcode":"02118",
    "sg:province":"MA",
    "sg:website":"www.citizensbank.com",
    "wof:name":"Citizens Bank",
    "wof:placetype":"venue"
},
  "geometry": {"coordinates":[-71.069377,42.341326],"type":"Point"}
}