{
  "type": "Feature",
  "properties": {
    "iso:country":"US",
    "sg:address":"62 Long Pond Rd",
    "sg:city":"Plymouth",
    "sg:classifiers":[
        {
            "category":"Freight",
            "type":"Transportation"
        }
    ],
    "sg:phone":"+1   ",
    "sg:postcode":"02360",
    "sg:province":"MA",
    "sg:tags":[
        "operator",
        "local",
        "trucking"
    ],
    "wof:name":"Taylor Transport",
    "wof:placetype":"venue"
},
  "geometry": {"coordinates":[-70.65730000000001,41.929033],"type":"Point"}
}