{
  "type": "Feature",
  "properties": {
    "addr:full": "2 Gleason Rd Northampton MA 01060",
    "addr:housenumber": "2",
    "addr:postcode": "01060",
    "addr:street": "Gleason Rd",
    "iso:country": "US",
    "sg:address": "2 Gleason Rd",
    "sg:city": "Northampton",
    "sg:classifiers": [
      {
        "category": "Real Estate",
        "subcategory": "Real Estate Agent",
        "type": "Services"
      }
    ],
    "sg:phone": "+1 413 586 5401",
    "sg:postcode": "01060",
    "sg:province": "MA",
    "wof:name": "Pioneer Valley Assoc",
    "wof:placetype": "venue"
  },
  "geometry": {"coordinates":[-72.646626,42.33753],"type":"Point"}
}
