{
  "type": "Feature",
  "properties": {
    "addr:full": "52 Negus St Webster MA 01570",
    "addr:housenumber": "52",
    "addr:postcode": "01570",
    "addr:street": "Negus St",
    "iso:country": "US",
    "sg:address": "52 Negus St",
    "sg:city": "Webster",
    "sg:classifiers": [
      {
        "category": "Education",
        "subcategory": "School",
        "type": "Public Place"
      }
    ],
    "sg:phone": "+1 508 943 0817",
    "sg:postcode": "01570",
    "sg:province": "MA",
    "sg:tags": [
      "elementary"
    ],
    "wof:name": "St Louis Elementary School",
    "wof:placetype": "venue"
  },
  "geometry": {"coordinates":[-71.877872,42.049469],"type":"Point"}
}
