{
  "type": "Feature",
  "properties": {
    "iso:country":"US",
    "sg:address":"131 Weymouth St",
    "sg:city":"Rockland",
    "sg:classifiers":[
        {
            "category":"Farming",
            "subcategory":"Dairy Farm",
            "type":"Manufacturing & Wholesale Goods"
        }
    ],
    "sg:phone":"+1 781 871 1373",
    "sg:postcode":"02370",
    "sg:province":"MA",
    "wof:name":"Provender Dairy Kitchen",
    "wof:placetype":"venue"
},
  "geometry": {"coordinates":[-70.907517,42.158175],"type":"Point"}
}