{
  "type": "Feature",
  "properties": {
    "addr:full": "24 Hamilton St Southbridge MA 01550",
    "addr:housenumber": "24",
    "addr:postcode": "01550",
    "addr:street": "Hamilton St",
    "iso:country": "US",
    "sg:address": "24 Hamilton St",
    "sg:city": "Southbridge",
    "sg:classifiers": [
      {
        "category": "Utilities",
        "subcategory": "Mobile Phone",
        "type": "Services"
      }
    ],
    "sg:phone": "+1 508 764 8080",
    "sg:postcode": "01550",
    "sg:province": "MA",
    "sg:tags": [
      "telephone",
      "cellular"
    ],
    "wof:name": "J G Communications",
    "wof:placetype": "venue"
  },
  "geometry": {"coordinates":[-72.034841,42.076135],"type":"Point"}
}
