{
  "type": "Feature",
  "properties": {
    "iso:country":"US",
    "sg:address":"24 Hamilton St",
    "sg:city":"Southbridge",
    "sg:classifiers":[
        {
            "category":"Utilities",
            "subcategory":"Mobile Phone",
            "type":"Services"
        }
    ],
    "sg:phone":"+1 508 764 8080",
    "sg:postcode":"01550",
    "sg:province":"MA",
    "sg:tags":[
        "telephone",
        "cellular"
    ],
    "wof:name":"J G Communications",
    "wof:placetype":"venue"
},
  "geometry": {"coordinates":[-72.034841,42.076135],"type":"Point"}
}