{
  "type": "Feature",
  "properties": {
    "addr:full":"6 Hillside Meadow Dr Southampton MA 01073",
    "addr:postcode":"01073",
    "addr:street":"Hillside Meadow Dr",
    "iso:country":"US",
    "sg:address":"6 Hillside Meadow Dr",
    "sg:city":"Southampton",
    "sg:classifiers":[
        {
            "category":"Professional",
            "subcategory":"Business Services",
            "type":"Services"
        }
    ],
    "sg:phone":"+1   ",
    "sg:postcode":"01073",
    "sg:province":"MA",
    "wof:name":"Abbott & Children Group Inc",
    "wof:placetype":"venue"
},
  "geometry": {"coordinates":[-72.714631,42.24399],"type":"Point"}
}