{
  "type": "Feature",
  "properties": {
    "iso:country":"US",
    "sg:address":"250 Boston Rd",
    "sg:city":"Chelmsford",
    "sg:classifiers":[
        {
            "category":"Education",
            "subcategory":"School",
            "type":"Public Place"
        }
    ],
    "sg:phone":"+1 978 251 5177",
    "sg:postcode":"01824",
    "sg:province":"MA",
    "sg:tags":[
        "elementary"
    ],
    "sg:website":"http://www.chelmsford.k12.ma.us",
    "wof:name":"South Row Elementary School",
    "wof:placetype":"venue"
},
  "geometry": {"coordinates":[-71.335312,42.57592],"type":"Point"}
}