{
  "type": "Feature",
  "properties": {
    "iso:country":"US",
    "sg:address":"536 High Plain St",
    "sg:city":"Walpole",
    "sg:classifiers":[
        {
            "category":"Retail",
            "subcategory":"Car Wash",
            "type":"Services"
        }
    ],
    "sg:phone":"+1 508 660 5400",
    "sg:postcode":"02081",
    "sg:province":"MA",
    "sg:tags":[
        "automobile",
        "detail",
        "clean"
    ],
    "wof:name":"Dr Detail Car Wash & Express",
    "wof:placetype":"venue"
},
  "geometry": {"coordinates":[-71.218188,42.140287],"type":"Point"}
}