{
  "type": "Feature",
  "properties": {
    "addr:full": "536 High Plain St Walpole MA 02081",
    "addr:housenumber": "536",
    "addr:postcode": "02081",
    "addr:street": "High Plain St",
    "iso:country": "US",
    "ovtr:label": "Dr Detail Car Wash \u0026 Express, 536 High Plain St Walpole MA US",
    "ovtr:similarity": 1.982895016670227,
    "sg:address": "536 High Plain St",
    "sg:city": "Walpole",
    "sg:classifiers": [
      {
        "category": "Retail",
        "subcategory": "Car Wash",
        "type": "Services"
      }
    ],
    "sg:phone": "+1 508 660 5400",
    "sg:postcode": "02081",
    "sg:province": "MA",
    "sg:tags": [
      "automobile",
      "detail",
      "clean"
    ],
    "wof:name": "Dr Detail Car Wash \u0026 Express",
    "wof:placetype": "venue"
  },
  "geometry": {"coordinates":[-71.218188,42.140287],"type":"Point"}
}
