{
  "type": "Feature",
  "properties": {
    "iso:country":"US",
    "sg:address":"535 Plymouth St",
    "sg:city":"Whitman",
    "sg:classifiers":[
        {
            "category":"Home & Garden",
            "subcategory":"Garden Supply",
            "type":"Retail Goods"
        }
    ],
    "sg:phone":"+1 781 447 6268",
    "sg:postcode":"02382",
    "sg:province":"MA",
    "sg:tags":[
        "center"
    ],
    "wof:name":"Lotus Greenhouses & Garden Ctr",
    "wof:placetype":"venue"
},
  "geometry": {"coordinates":[-70.92201,42.092063],"type":"Point"}
}