{
  "type": "Feature",
  "properties": {
    "addr:full": "81 Town Farm Rd Winchendon MA 01475",
    "addr:housenumber": "81",
    "addr:postcode": "01475",
    "addr:street": "Town Farm Rd",
    "iso:country": "US",
    "sg:address": "81 Town Farm Rd",
    "sg:city": "Winchendon",
    "sg:classifiers": [
      {
        "category": "Retail",
        "subcategory": "Auto Repair",
        "type": "Services"
      }
    ],
    "sg:phone": "+1 978 297 1401",
    "sg:postcode": "01475",
    "sg:province": "MA",
    "sg:tags": [
      "automobile",
      "restoration-antique",
      "classic"
    ],
    "wof:name": "Rbc Repair",
    "wof:placetype": "venue"
  },
  "geometry": {"coordinates":[-72.039119,42.637178],"type":"Point"}
}
