{
  "type": "Feature",
  "properties": {
    "addr:full":"25 State St Newburyport MA 01950",
    "addr:housenumber":"25",
    "addr:postcode":"01950",
    "addr:street":"State St",
    "iso:country":"US",
    "sg:address":"25 State St",
    "sg:city":"Newburyport",
    "sg:classifiers":[
        {
            "category":"Health Services",
            "subcategory":"Clinic",
            "type":"Services"
        }
    ],
    "sg:phone":"+1 978 462 3756",
    "sg:postcode":"01950",
    "sg:province":"MA",
    "sg:tags":[
        "counseling",
        "mental"
    ],
    "wof:name":"Licsw Mark Spivak - CLOSED",
    "wof:placetype":"venue"
},
  "geometry": {"coordinates":[-70.86990400000001,42.8106],"type":"Point"}
}