{
  "type": "Feature",
  "properties": {
    "addr:full":"321 Centre St Dorchester MA 02122",
    "addr:housenumber":"321",
    "addr:postcode":"02122",
    "addr:street":"Centre St",
    "iso:country":"US",
    "sg:address":"321 Centre St",
    "sg:city":"Dorchester",
    "sg:classifiers":[
        {
            "category":"Health Services",
            "subcategory":"Nursing And Care Facility",
            "type":"Services"
        }
    ],
    "sg:phone":"+1 617 825 6320",
    "sg:postcode":"02122",
    "sg:province":"MA",
    "sg:tags":[
        "home",
        "convalescent"
    ],
    "wof:name":"St Joseph Home",
    "wof:placetype":"venue"
},
  "geometry": {"coordinates":[-71.060152,42.29414],"type":"Point"}
}