{
  "type": "Feature",
  "properties": {
    "iso:country":"US",
    "sg:address":"3 Centennial Dr",
    "sg:city":"Peabody",
    "sg:classifiers":[
        {
            "category":"Professional",
            "subcategory":"Computer Services",
            "type":"Services"
        }
    ],
    "sg:phone":"+1 978 538 0044",
    "sg:postcode":"01960",
    "sg:province":"MA",
    "sg:tags":[
        "internet"
    ],
    "wof:name":"Hickory Hill Advisors",
    "wof:placetype":"venue"
},
  "geometry": {"coordinates":[-70.972111,42.520625],"type":"Point"}
}