{
  "type": "Feature",
  "properties": {
    "addr:full": "171 Marlborough St Boston MA 02116",
    "addr:housenumber": "171",
    "addr:postcode": "02116",
    "addr:street": "Marlborough St",
    "iso:country": "US",
    "sg:address": "171 Marlborough St",
    "sg:city": "Boston",
    "sg:classifiers": [
      {
        "category": "Real Estate",
        "subcategory": "Architect",
        "type": "Services"
      }
    ],
    "sg:phone": "+1 617 424 7654",
    "sg:postcode": "02116",
    "sg:province": "MA",
    "wof:name": "Peter A Nottonson",
    "wof:placetype": "venue"
  },
  "geometry": {"coordinates":[-71.080227,42.352573],"type":"Point"}
}
