{
  "type": "Feature",
  "properties": {
    "addr:full": "9 Sylvan St Peabody MA 01960",
    "addr:housenumber": "9",
    "addr:postcode": "01960",
    "addr:street": "Sylvan St",
    "iso:country": "US",
    "sg:address": "9 Sylvan St",
    "sg:city": "Peabody",
    "sg:classifiers": [
      {
        "category": "Wholesale",
        "subcategory": "Machinery \u0026 Supplies",
        "type": "Manufacturing \u0026 Wholesale Goods"
      }
    ],
    "sg:phone": "+1 978 326 9000",
    "sg:postcode": "01960",
    "sg:province": "MA",
    "sg:tags": [
      "salon",
      "beauty"
    ],
    "wof:name": "Salon Concepts",
    "wof:placetype": "venue"
  },
  "geometry": {"coordinates":[-70.944928,42.545937],"type":"Point"}
}
