{
  "type": "Feature",
  "properties": {
    "iso:country":"US",
    "sg:address":"9 Sylvan St",
    "sg:city":"Peabody",
    "sg:classifiers":[
        {
            "category":"Wholesale",
            "subcategory":"Machinery & Supplies",
            "type":"Manufacturing & Wholesale Goods"
        }
    ],
    "sg:phone":"+1 978 326 9000",
    "sg:postcode":"01960",
    "sg:province":"MA",
    "sg:tags":[
        "salon",
        "beauty"
    ],
    "wof:name":"Salon Concepts",
    "wof:placetype":"venue"
},
  "geometry": {"coordinates":[-70.944928,42.545937],"type":"Point"}
}