{
  "type": "Feature",
  "properties": {
    "addr:full":"621 Western Ave Lynn MA 01905",
    "addr:housenumber":"621",
    "addr:postcode":"01905",
    "addr:street":"Western Ave",
    "iso:country":"US",
    "sg:address":"621 Western Ave",
    "sg:city":"Lynn",
    "sg:classifiers":[
        {
            "category":"Food & Beverages",
            "subcategory":"Groceries & Convenience Stores",
            "type":"Retail Goods"
        }
    ],
    "sg:phone":"+1 781 593 1600",
    "sg:postcode":"01905",
    "sg:province":"MA",
    "wof:name":"Quick Mart",
    "wof:placetype":"venue"
},
  "geometry": {"coordinates":[-70.96231899999999,42.465292],"type":"Point"}
}