{
  "type": "Feature",
  "properties": {
    "addr:full": "21 Bowker St Boston MA 02114",
    "addr:housenumber": "21",
    "addr:postcode": "02114",
    "addr:street": "Bowker St",
    "iso:country": "US",
    "sg:address": "21 Bowker St",
    "sg:city": "Boston",
    "sg:classifiers": [
      {
        "category": "Building \u0026 Trades",
        "subcategory": "Locksmith",
        "type": "Services"
      }
    ],
    "sg:phone": "+1 617 449 7603",
    "sg:postcode": "02114",
    "sg:province": "MA",
    "sg:tags": [
      "key"
    ],
    "wof:name": "Locksmith On Bowker 1 Call Emergency 24 Hour",
    "wof:placetype": "venue"
  },
  "geometry": {"coordinates":[-71.060196,42.362382],"type":"Point"}
}
