{
  "type": "Feature",
  "properties": {
    "addr:full":"62 Harvard St Brookline MA 02445",
    "addr:housenumber":"62",
    "addr:postcode":"02445",
    "addr:street":"Harvard St",
    "iso:country":"US",
    "sg:address":"62 Harvard St",
    "sg:city":"Brookline",
    "sg:classifiers":[
        {
            "category":"Sports & Exercise",
            "subcategory":"Gym",
            "type":"Entertainment"
        }
    ],
    "sg:phone":"+1 617 232 7440",
    "sg:postcode":"02445",
    "sg:province":"MA",
    "sg:tags":[
        "club",
        "health",
        "studio",
        "gymnasium"
    ],
    "sg:website":"www.fitnessunlimited.com",
    "wof:name":"Fitness Unlimited",
    "wof:placetype":"venue"
},
  "geometry": {"coordinates":[-71.119601,42.335094],"type":"Point"}
}