{
  "type": "Feature",
  "properties": {
    "addr:full": "415 Concord Ave Belmont MA 02478",
    "addr:housenumber": "415",
    "addr:postcode": "02478",
    "addr:street": "Concord Ave",
    "iso:country": "US",
    "sg:address": "415 Concord Ave",
    "sg:city": "Belmont",
    "sg:classifiers": [
      {
        "category": "Professional",
        "subcategory": "Lawyer \u0026 Legal Services",
        "type": "Services"
      }
    ],
    "sg:phone": "+1 617 489 1030",
    "sg:postcode": "02478",
    "sg:province": "MA",
    "sg:tags": [
      "attorney"
    ],
    "wof:name": "Charles L Gaffney",
    "wof:placetype": "venue"
  },
  "geometry": {"coordinates":[-71.171867,42.39485],"type":"Point"}
}
