{
  "type": "Feature",
  "properties": {
    "iso:country":"US",
    "sg:address":"33 Winn St 2nd Fl",
    "sg:city":"Burlington",
    "sg:classifiers":[
        {
            "category":"Education",
            "subcategory":"Dance Studio",
            "type":"Public Place"
        }
    ],
    "sg:phone":"+1 781 273 2623",
    "sg:postcode":"01803",
    "sg:province":"MA",
    "sg:website":"www.kadanse.com",
    "wof:name":"Kadanse Ballroom & Latin Dance Studio",
    "wof:placetype":"venue"
},
  "geometry": {"coordinates":[-71.17119599999999,42.489362],"type":"Point"}
}