{
  "type": "Feature",
  "properties": {
    "iso:country":"US",
    "sg:address":"450 Main St",
    "sg:city":"West Newbury",
    "sg:classifiers":[
        {
            "category":"Personal",
            "subcategory":"Beauty Salon",
            "type":"Services"
        }
    ],
    "sg:phone":"+1 978 363 2901",
    "sg:postcode":"01985",
    "sg:province":"MA",
    "sg:tags":[
        "shop"
    ],
    "wof:name":"Olde Combe Shoppe",
    "wof:placetype":"venue"
},
  "geometry": {"coordinates":[-70.98234600000001,42.8042],"type":"Point"}
}