{
  "type": "Feature",
  "properties": {
    "addr:full":"509A High St Medford MA 02155",
    "addr:housenumber":"509a",
    "addr:postcode":"02155",
    "addr:street":"High St",
    "iso:country":"US",
    "sg:address":"509A High St",
    "sg:city":"Medford",
    "sg:classifiers":[
        {
            "category":"Restaurant",
            "type":"Food & Drink"
        },
        {
            "category":"Food & Beverages",
            "subcategory":"Bakery",
            "type":"Retail Goods"
        }
    ],
    "sg:phone":"+1 781 488 8020",
    "sg:postcode":"02155",
    "sg:province":"MA",
    "sg:tags":[
        "greek",
        "sandwich",
        "pizza"
    ],
    "wof:name":"Jimmy's Pizza & Subs",
    "wof:placetype":"venue"
},
  "geometry": {"coordinates":[-71.133878,42.42139],"type":"Point"}
}