{
  "type": "Feature",
  "properties": {
    "addr:full": "439 Park Ave Worcester MA 01610",
    "addr:housenumber": "439",
    "addr:postcode": "01610",
    "addr:street": "Park Ave",
    "iso:country": "US",
    "sg:address": "439 Park Ave",
    "sg:city": "Worcester",
    "sg:classifiers": [
      {
        "category": "Restaurant",
        "type": "Food \u0026 Drink"
      },
      {
        "category": "Food \u0026 Beverages",
        "subcategory": "Ethnic Foods",
        "type": "Retail Goods"
      }
    ],
    "sg:phone": "+1 508 752 1330",
    "sg:postcode": "01610",
    "sg:province": "MA",
    "sg:tags": [
      "style",
      "pan",
      "asian",
      "family",
      "vietnamese"
    ],
    "wof:name": "Anh Thu Vietnamese Restaurant",
    "wof:placetype": "venue"
  },
  "geometry": {"coordinates":[-71.824448,42.255839],"type":"Point"}
}
