{
  "type": "Feature",
  "properties": {
    "iso:country":"US",
    "sg:address":"457 Pleasant St",
    "sg:city":"Brockton",
    "sg:classifiers":[
        {
            "category":"Insurance",
            "subcategory":"Insurance Agent",
            "type":"Services"
        }
    ],
    "sg:phone":"+1 508 587 7500",
    "sg:postcode":"02301",
    "sg:province":"MA",
    "wof:name":"Boufides Insurance",
    "wof:placetype":"venue"
},
  "geometry": {"coordinates":[-71.038394,42.089112],"type":"Point"}
}