{
  "type": "Feature",
  "properties": {
    "addr:full": "8 Mount Pleasant St Milford MA 01757",
    "addr:housenumber": "8",
    "addr:postcode": "01757",
    "addr:street": "Mount Pleasant St",
    "iso:country": "US",
    "sg:address": "8 Mount Pleasant St",
    "sg:city": "Milford",
    "sg:classifiers": [
      {
        "category": "Social Services",
        "subcategory": "Child Care",
        "type": "Services"
      }
    ],
    "sg:phone": "+1 508 473 5060",
    "sg:postcode": "01757",
    "sg:province": "MA",
    "sg:tags": [
      "kindergarten",
      "academic",
      "school"
    ],
    "wof:name": "Little Angels Preschool",
    "wof:placetype": "venue"
  },
  "geometry": {"coordinates":[-71.510645,42.142493],"type":"Point"}
}
