{
  "type": "Feature",
  "properties": {
    "iso:country":"US",
    "sg:address":"87 Smith Rd",
    "sg:city":"Charlton",
    "sg:classifiers":[
        {
            "category":"Building & Trades",
            "subcategory":"Landscaping Services",
            "type":"Services"
        }
    ],
    "sg:phone":"+1 508 832 4181",
    "sg:postcode":"01507",
    "sg:province":"MA",
    "sg:tags":[
        "landscape",
        "contractor"
    ],
    "wof:name":"Gardner Landscape Maintenance",
    "wof:placetype":"venue"
},
  "geometry": {"coordinates":[-71.928054,42.18701],"type":"Point"}
}