{
  "type": "Feature",
  "properties": {
    "addr:full":"25 Holway St Chatham MA 02633",
    "addr:housenumber":"25",
    "addr:postcode":"02633",
    "addr:street":"Holway St",
    "iso:country":"US",
    "sg:address":"25 Holway St",
    "sg:city":"Chatham",
    "sg:classifiers":[
        {
            "category":"Travel",
            "subcategory":"Hotels & Motels",
            "type":"Entertainment"
        }
    ],
    "sg:phone":"+1 508 945 9757",
    "sg:postcode":"02633",
    "sg:province":"MA",
    "wof:name":"Surfside Motor Inn",
    "wof:placetype":"venue"
},
  "geometry": {"coordinates":[-69.947155,41.676264],"type":"Point"}
}