{
  "type": "Feature",
  "properties": {
    "addr:full":"85 Liberty St Brockton MA 02301",
    "addr:housenumber":"85",
    "addr:postcode":"02301",
    "addr:street":"Liberty St",
    "iso:country":"US",
    "sg:address":"85 Liberty St",
    "sg:city":"Brockton",
    "sg:classifiers":[
        {
            "category":"Professional",
            "subcategory":"Business Services",
            "type":"Services"
        }
    ],
    "sg:phone":"+1 508 588 5443",
    "sg:postcode":"02301",
    "sg:province":"MA",
    "sg:tags":[
        "fund",
        "promotion",
        "raising"
    ],
    "wof:name":"Metro South Promotions",
    "wof:placetype":"venue"
},
  "geometry": {"coordinates":[-71.062186,42.056183],"type":"Point"}
}