{
  "type": "Feature",
  "properties": {
    "iso:country":"US",
    "sg:address":"1000 Lexington St",
    "sg:city":"Waltham",
    "sg:classifiers":[
        {
            "category":"Building & Trades",
            "subcategory":"Construction",
            "type":"Services"
        }
    ],
    "sg:phone":"+1   ",
    "sg:postcode":"02452",
    "sg:province":"MA",
    "sg:tags":[
        "carpentry",
        "contractor"
    ],
    "wof:name":"Woodframers Company",
    "wof:placetype":"venue"
},
  "geometry": {"coordinates":[-71.23436599999999,42.407708],"type":"Point"}
}