{
  "type": "Feature",
  "properties": {
    "addr:full": "1000 Lexington St Waltham MA 02452",
    "addr:housenumber": "1000",
    "addr:postcode": "02452",
    "addr:street": "Lexington St",
    "iso:country": "US",
    "sg:address": "1000 Lexington St",
    "sg:city": "Waltham",
    "sg:classifiers": [
      {
        "category": "Building \u0026 Trades",
        "subcategory": "Construction",
        "type": "Services"
      }
    ],
    "sg:phone": "+1   ",
    "sg:postcode": "02452",
    "sg:province": "MA",
    "sg:tags": [
      "carpentry",
      "contractor"
    ],
    "wof:name": "Woodframers Company",
    "wof:placetype": "venue"
  },
  "geometry": {"coordinates":[-71.234366,42.407708],"type":"Point"}
}
