{
  "type": "Feature",
  "properties": {
    "addr:full":"59 Howland Rd Assonet MA 02702",
    "addr:housenumber":"59",
    "addr:postcode":"02702",
    "addr:street":"Howland Rd",
    "iso:country":"US",
    "sg:address":"59 Howland Rd",
    "sg:city":"Assonet",
    "sg:classifiers":[
        {
            "category":"Social Services",
            "subcategory":"Child Care",
            "type":"Services"
        }
    ],
    "sg:phone":"+1 508 644 5221",
    "sg:postcode":"02702",
    "sg:province":"MA",
    "wof:name":"Emmanuel Day Care & Learning",
    "wof:placetype":"venue"
},
  "geometry": {"coordinates":[-71.039693,41.7979],"type":"Point"}
}