{
  "type": "Feature",
  "properties": {
    "addr:full":"1250 Hancock St Quincy MA 02169",
    "addr:housenumber":"1250",
    "addr:postcode":"02169",
    "addr:street":"Hancock St",
    "iso:country":"US",
    "sg:address":"1250 Hancock St",
    "sg:city":"Quincy",
    "sg:classifiers":[
        {
            "category":"Food & Beverages",
            "subcategory":"Groceries & Convenience Stores",
            "type":"Retail Goods"
        }
    ],
    "sg:phone":"+1 617 328 5532",
    "sg:postcode":"02169",
    "sg:province":"MA",
    "wof:name":"Tedeschi Food Shops",
    "wof:placetype":"venue"
},
  "geometry": {"coordinates":[-71.004164,42.252468],"type":"Point"}
}