{
  "type": "Feature",
  "properties": {
    "iso:country":"US",
    "sg:address":"278 Worcester St",
    "sg:city":"Southbridge",
    "sg:classifiers":[
        {
            "category":"Shopping",
            "subcategory":"Florist",
            "type":"Retail Goods"
        }
    ],
    "sg:phone":"+1 508 764 3733",
    "sg:postcode":"01550",
    "sg:province":"MA",
    "wof:name":"Parc Industries Inc - CLOSED",
    "wof:placetype":"venue"
},
  "geometry": {"coordinates":[-72.02359800000001,42.0886],"type":"Point"}
}