{
  "type": "Feature",
  "properties": {
    "iso:country":"US",
    "sg:address":"64 Inman St",
    "sg:city":"Cambridge",
    "sg:classifiers":[
        {
            "category":"Real Estate",
            "subcategory":"Architect",
            "type":"Services"
        }
    ],
    "sg:phone":"+1 617 354 4266",
    "sg:postcode":"02139",
    "sg:province":"MA",
    "wof:name":"Building & Design Resources Inc",
    "wof:placetype":"venue"
},
  "geometry": {"coordinates":[-71.102501,42.370399],"type":"Point"}
}