{
  "type": "Feature",
  "properties": {
    "addr:full":"8 Triangle Cir Edgartown MA 02563",
    "addr:housenumber":"8",
    "addr:postcode":"02563",
    "addr:street":"Triangle Cir",
    "iso:country":"US",
    "sg:address":"8 Triangle Cir",
    "sg:city":"Edgartown",
    "sg:classifiers":[
        {
            "category":"Shopping",
            "subcategory":"Music",
            "type":"Retail Goods"
        }
    ],
    "sg:phone":"+1 508 627 4678",
    "sg:postcode":"02563",
    "sg:province":"MA",
    "sg:tags":[
        "compact",
        "record",
        "disc",
        "tape"
    ],
    "wof:name":"Above Ground Records",
    "wof:placetype":"venue"
},
  "geometry": {"coordinates":[-70.483442,41.707011],"type":"Point"}
}