{
  "type": "Feature",
  "properties": {
    "iso:country":"US",
    "sg:address":"264 W Housatonic St",
    "sg:city":"Pittsfield",
    "sg:classifiers":[
        {
            "category":"Personal",
            "subcategory":"Tanning Parlor",
            "type":"Services"
        }
    ],
    "sg:phone":"+1 413 447 9400",
    "sg:postcode":"01201",
    "sg:province":"MA",
    "sg:tags":[
        "salon"
    ],
    "wof:name":"Bellatan II",
    "wof:placetype":"venue"
},
  "geometry": {"coordinates":[-73.267882,42.443188],"type":"Point"}
}