{
  "type": "Feature",
  "properties": {
    "addr:full": "832 Commonwealth Ave Boston MA 02215",
    "addr:housenumber": "832",
    "addr:postcode": "02215",
    "addr:street": "Commonwealth Ave",
    "iso:country": "US",
    "sg:address": "832 Commonwealth Ave",
    "sg:city": "Boston",
    "sg:classifiers": [
      {
        "category": "Personal",
        "subcategory": "Beauty Salon",
        "type": "Services"
      }
    ],
    "sg:phone": "+1 617 566 7280",
    "sg:postcode": "02215",
    "sg:province": "MA",
    "sg:tags": [
      "treatment",
      "skin"
    ],
    "wof:name": "A Total Skin Care",
    "wof:placetype": "venue"
  },
  "geometry": {"coordinates":[-71.111113,42.350466],"type":"Point"}
}
