{
  "type": "Feature",
  "properties": {
    "iso:country":"US",
    "sg:address":"25 Cross St",
    "sg:city":"Medfield",
    "sg:classifiers":[
        {
            "category":"Building & Trades",
            "subcategory":"Construction",
            "type":"Services"
        }
    ],
    "sg:phone":"+1 508 359 5274",
    "sg:postcode":"02052",
    "sg:province":"MA",
    "sg:tags":[
        "siding",
        "contractor"
    ],
    "wof:name":"J Foster Co Inc",
    "wof:placetype":"venue"
},
  "geometry": {"coordinates":[-71.292745,42.176057],"type":"Point"}
}