{
  "type": "Feature",
  "properties": {
    "addr:full": "69 Baldwin Rd Billerica MA 01821",
    "addr:housenumber": "69",
    "addr:postcode": "01821",
    "addr:street": "Baldwin Rd",
    "iso:country": "US",
    "sg:address": "69 Baldwin Rd",
    "sg:city": "Billerica",
    "sg:classifiers": [
      {
        "category": "Shopping",
        "type": "Retail Goods"
      }
    ],
    "sg:phone": "+1   ",
    "sg:postcode": "01821",
    "sg:province": "MA",
    "sg:tags": [
      "merchandise"
    ],
    "wof:name": "Wolforth John",
    "wof:placetype": "venue"
  },
  "geometry": {"coordinates":[-71.236587,42.555802],"type":"Point"}
}
