{
  "type": "Feature",
  "properties": {
    "addr:full": "2857 Acushnet Ave New Bedford MA 02745",
    "addr:housenumber": "2857",
    "addr:postcode": "02745",
    "addr:street": "Acushnet Ave",
    "iso:country": "US",
    "sg:address": "2857 Acushnet Ave",
    "sg:city": "New Bedford",
    "sg:classifiers": [
      {
        "category": "Restaurant",
        "type": "Food \u0026 Drink"
      }
    ],
    "sg:phone": "+1 508 995 7711",
    "sg:postcode": "02745",
    "sg:province": "MA",
    "sg:tags": [
      "pizza"
    ],
    "wof:name": "Pa Raffa's Italian Restaurant",
    "wof:placetype": "venue"
  },
  "geometry": {"coordinates":[-70.934786,41.697417],"type":"Point"}
}
