{
  "type": "Feature",
  "properties": {
    "iso:country":"US",
    "sg:address":"37 Brook Rd",
    "sg:city":"Sharon",
    "sg:classifiers":[
        {
            "category":"Professional",
            "subcategory":"Management & Consulting",
            "type":"Services"
        }
    ],
    "sg:phone":"+1 781 784 2900",
    "sg:postcode":"02067",
    "sg:province":"MA",
    "sg:tags":[
        "public",
        "relations"
    ],
    "wof:name":"Smith & Suita Communications",
    "wof:placetype":"venue"
},
  "geometry": {"coordinates":[-71.17521000000001,42.1272],"type":"Point"}
}