{
  "type": "Feature",
  "properties": {
    "addr:full": "37 Brook Rd Sharon MA 02067",
    "addr:housenumber": "37",
    "addr:postcode": "02067",
    "addr:street": "Brook Rd",
    "iso:country": "US",
    "sg:address": "37 Brook Rd",
    "sg:city": "Sharon",
    "sg:classifiers": [
      {
        "category": "Professional",
        "subcategory": "Management \u0026 Consulting",
        "type": "Services"
      }
    ],
    "sg:phone": "+1 781 784 2900",
    "sg:postcode": "02067",
    "sg:province": "MA",
    "sg:tags": [
      "public",
      "relations"
    ],
    "wof:name": "Smith \u0026 Suita Communications",
    "wof:placetype": "venue"
  },
  "geometry": {"coordinates":[-71.17521,42.1272],"type":"Point"}
}
