{
  "type": "Feature",
  "properties": {
    "addr:full":"10 Fawcett St Cambridge MA 02138",
    "addr:housenumber":"10",
    "addr:postcode":"02138",
    "addr:street":"Fawcett St",
    "iso:country":"US",
    "sg:address":"10 Fawcett St",
    "sg:city":"Cambridge",
    "sg:classifiers":[
        {
            "category":"Real Estate",
            "subcategory":"Real Estate Agent",
            "type":"Services"
        }
    ],
    "sg:phone":"+1 617 876 8700",
    "sg:postcode":"02138",
    "sg:province":"MA",
    "sg:tags":[
        "consultant"
    ],
    "wof:name":"Corporate Facilities Group",
    "wof:placetype":"venue"
},
  "geometry": {"coordinates":[-71.147487,42.393148],"type":"Point"}
}