{
  "type": "Feature",
  "properties": {
    "addr:full":"3 Apple Orchard Dr Billerica MA 01821",
    "addr:housenumber":"3",
    "addr:postcode":"01821",
    "addr:street":"Apple Orchard Dr",
    "iso:country":"US",
    "sg:address":"3 Apple Orchard Dr",
    "sg:city":"Billerica",
    "sg:classifiers":[
        {
            "category":"Professional",
            "subcategory":"Employment Agencies",
            "type":"Services"
        }
    ],
    "sg:phone":"+1 978 670 0055",
    "sg:postcode":"01821",
    "sg:province":"MA",
    "wof:name":"Signature Recruiting Inc",
    "wof:placetype":"venue"
},
  "geometry": {"coordinates":[-71.257442,42.539443],"type":"Point"}
}