{
  "type": "Feature",
  "properties": {
    "addr:full": "70 East St Ludlow MA 01056",
    "addr:housenumber": "70",
    "addr:postcode": "01056",
    "addr:street": "East St",
    "iso:country": "US",
    "ovtr:label": "Pizza Corner, 70 East St Ludlow MA US",
    "ovtr:similarity": 2.472311019897461,
    "sg:address": "70 East St",
    "sg:city": "Ludlow",
    "sg:classifiers": [
      {
        "category": "Restaurant",
        "type": "Food \u0026 Drink"
      }
    ],
    "sg:phone": "+1 413 583 3088",
    "sg:postcode": "01056",
    "sg:province": "MA",
    "sg:tags": [
      "pizza"
    ],
    "wof:name": "Pizza Corner",
    "wof:placetype": "venue"
  },
  "geometry": {"coordinates":[-72.479863,42.156923],"type":"Point"}
}
