{
  "type": "Feature",
  "properties": {
    "iso:country":"US",
    "sg:address":"70 East St",
    "sg:city":"Ludlow",
    "sg:classifiers":[
        {
            "category":"Restaurant",
            "type":"Food & Drink"
        }
    ],
    "sg:phone":"+1 413 583 3088",
    "sg:postcode":"01056",
    "sg:province":"MA",
    "sg:tags":[
        "pizza"
    ],
    "wof:name":"Pizza Corner",
    "wof:placetype":"venue"
},
  "geometry": {"coordinates":[-72.47986299999999,42.156923],"type":"Point"}
}