{
  "type": "Feature",
  "properties": {
    "iso:country":"US",
    "sg:address":"208 Main St",
    "sg:city":"Weymouth",
    "sg:classifiers":[
        {
            "category":"Utilities",
            "subcategory":"Mobile Phone",
            "type":"Services"
        }
    ],
    "sg:phone":"+1 781 335 5544",
    "sg:postcode":"02188",
    "sg:province":"MA",
    "sg:tags":[
        "telephone",
        "cellular"
    ],
    "wof:name":"Ats Mobile Electronics",
    "wof:placetype":"venue"
},
  "geometry": {"coordinates":[-70.95575700000001,42.19983],"type":"Point"}
}