{
  "type": "Feature",
  "properties": {
    "iso:country":"US",
    "sg:address":"472 High St",
    "sg:city":"Clinton",
    "sg:classifiers":[
        {
            "category":"Manufacturing",
            "subcategory":"Printing",
            "type":"Manufacturing & Wholesale Goods"
        }
    ],
    "sg:phone":"+1 978 365 4396",
    "sg:postcode":"01510",
    "sg:province":"MA",
    "sg:tags":[
        "commercial"
    ],
    "wof:name":"Clinton Offset Printers",
    "wof:placetype":"venue"
},
  "geometry": {"coordinates":[-71.68312,42.424312],"type":"Point"}
}