{
  "type": "Feature",
  "properties": {
    "iso:country":"US",
    "sg:address":"380 Burncoat St",
    "sg:city":"Worcester",
    "sg:classifiers":[
        {
            "category":"Insurance",
            "subcategory":"Insurance Agent",
            "type":"Services"
        }
    ],
    "sg:phone":"+1 508 853 1101",
    "sg:postcode":"01606",
    "sg:province":"MA",
    "wof:name":"Pervier Insurance Assoc",
    "wof:placetype":"venue"
},
  "geometry": {"coordinates":[-71.789215,42.312101],"type":"Point"}
}