{
  "type": "Feature",
  "properties": {
    "addr:full": "186 Woods Hole Rd Falmouth MA 02540",
    "addr:housenumber": "186",
    "addr:postcode": "02540",
    "addr:street": "Woods Hole Rd",
    "iso:country": "US",
    "sg:address": "186 Woods Hole Rd",
    "sg:city": "Falmouth",
    "sg:classifiers": [
      {
        "category": "Travel",
        "subcategory": "Hotels \u0026 Motels",
        "type": "Entertainment"
      }
    ],
    "sg:phone": "+1   ",
    "sg:postcode": "02540",
    "sg:province": "MA",
    "sg:tags": [
      "operation"
    ],
    "wof:name": "Woods Hole Pssage Bed Brakfast",
    "wof:placetype": "venue"
  },
  "geometry": {"coordinates":[-70.645874,41.547016],"type":"Point"}
}
