{
  "type": "Feature",
  "properties": {
    "iso:country":"US",
    "sg:address":"26 Ericsson St Port Norfolk",
    "sg:city":"Boston",
    "sg:classifiers":[
        {
            "category":"Winery",
            "type":"Food & Drink"
        }
    ],
    "sg:phone":"+1 617 265 9463",
    "sg:postcode":"02122",
    "sg:province":"MA",
    "sg:website":"bostonwinery.net/",
    "wof:name":"Boston Winery",
    "wof:placetype":"venue"
},
  "geometry": {"coordinates":[-71.039975,42.292829],"type":"Point"}
}