{
  "type": "Feature",
  "properties": {
    "addr:full": "7 Hilldale Rd Ashland MA 01721",
    "addr:housenumber": "7",
    "addr:postcode": "01721",
    "addr:street": "Hilldale Rd",
    "iso:country": "US",
    "sg:address": "7 Hilldale Rd",
    "sg:city": "Ashland",
    "sg:classifiers": [
      {
        "category": "Professional",
        "type": "Services"
      }
    ],
    "sg:phone": "+1   ",
    "sg:postcode": "01721",
    "sg:province": "MA",
    "wof:name": "Boston Nut Roasters",
    "wof:placetype": "venue"
  },
  "geometry": {"coordinates":[-71.452376,42.269273],"type":"Point"}
}
