{
  "type": "Feature",
  "properties": {
    "iso:country":"US",
    "sg:address":"96 E Water St",
    "sg:city":"Rockland",
    "sg:classifiers":[
        {
            "category":"Utilities",
            "subcategory":"Water",
            "type":"Services"
        }
    ],
    "sg:phone":"+1 781 982 2128",
    "sg:postcode":"02370",
    "sg:province":"MA",
    "sg:tags":[
        "company",
        "sewage"
    ],
    "wof:name":"Abington Water Dept",
    "wof:placetype":"venue"
},
  "geometry": {"coordinates":[-70.91166,42.128962],"type":"Point"}
}