{
  "type": "Feature",
  "properties": {
    "addr:full":"44 Mountain Ave Fitchburg MA 01420",
    "addr:housenumber":"44",
    "addr:postcode":"01420",
    "addr:street":"Mountain Ave",
    "iso:country":"US",
    "sg:address":"44 Mountain Ave",
    "sg:city":"Fitchburg",
    "sg:classifiers":[
        {
            "category":"Health Services",
            "subcategory":"Doctor",
            "type":"Services"
        }
    ],
    "sg:phone":"+1 978 345 0124",
    "sg:postcode":"01420",
    "sg:province":"MA",
    "sg:tags":[
        "physician",
        "surgeon"
    ],
    "wof:name":"John Fitch Radiology Inc",
    "wof:placetype":"venue"
},
  "geometry": {"coordinates":[-71.797692,42.574653],"type":"Point"}
}