{
  "type": "Feature",
  "properties": {
    "addr:full": "28 Comet Rd Methuen MA 01844",
    "addr:housenumber": "28",
    "addr:postcode": "01844",
    "addr:street": "Comet Rd",
    "iso:country": "US",
    "sg:address": "28 Comet Rd",
    "sg:city": "Methuen",
    "sg:classifiers": [
      {
        "category": "Social Services",
        "subcategory": "Child Care",
        "type": "Services"
      }
    ],
    "sg:phone": "+1   ",
    "sg:postcode": "01844",
    "sg:province": "MA",
    "sg:tags": [
      "day"
    ],
    "wof:name": "Cub House Daycare",
    "wof:placetype": "venue"
  },
  "geometry": {"coordinates":[-71.13843,42.736889],"type":"Point"}
}
