{
  "type": "Feature",
  "properties": {
    "addr:full":"208 Main St Kingston MA 02364",
    "addr:housenumber":"208",
    "addr:postcode":"02364",
    "addr:street":"Main St",
    "iso:country":"US",
    "sg:address":"208 Main St",
    "sg:city":"Kingston",
    "sg:classifiers":[
        {
            "category":"Professional",
            "subcategory":"Computer Services",
            "type":"Services"
        }
    ],
    "sg:phone":"+1   ",
    "sg:postcode":"02364",
    "sg:province":"MA",
    "sg:tags":[
        "related"
    ],
    "wof:name":"Kit Soft",
    "wof:placetype":"venue"
},
  "geometry": {"coordinates":[-70.72788799999999,41.992848],"type":"Point"}
}