{
  "type": "Feature",
  "properties": {
    "iso:country":"US",
    "sg:address":"132 Jackman St",
    "sg:city":"Georgetown",
    "sg:classifiers":[
        {
            "category":"Organizations",
            "subcategory":"Religious Organization",
            "type":"Services"
        }
    ],
    "sg:phone":"+1 978 352 6800",
    "sg:postcode":"01833",
    "sg:province":"MA",
    "wof:name":"Pastor Referral Network",
    "wof:placetype":"venue"
},
  "geometry": {"coordinates":[-70.932748,42.738571],"type":"Point"}
}