{
  "type": "Feature",
  "properties": {
    "addr:full": "19 West Rd Orleans MA 02653",
    "addr:housenumber": "19",
    "addr:postcode": "02653",
    "addr:street": "West Rd",
    "iso:country": "US",
    "sg:address": "19 West Rd",
    "sg:city": "Orleans",
    "sg:classifiers": [
      {
        "category": "Banks \u0026 Credit Unions",
        "subcategory": "Bank",
        "type": "Services"
      }
    ],
    "sg:phone": "+1 508 240 0555",
    "sg:postcode": "02653",
    "sg:province": "MA",
    "sg:website": "www.capecodfive.com",
    "wof:name": "Cape Cod Five Cents Svngs Bnk",
    "wof:placetype": "venue"
  },
  "geometry": {"coordinates":[-70.000836,41.781437],"type":"Point"}
}
