{
  "type": "Feature",
  "properties": {
    "iso:country":"US",
    "sg:address":"19 West Rd",
    "sg:city":"Orleans",
    "sg:classifiers":[
        {
            "category":"Banks & Credit Unions",
            "subcategory":"Bank",
            "type":"Services"
        }
    ],
    "sg:phone":"+1 508 240 0555",
    "sg:postcode":"02653",
    "sg:province":"MA",
    "sg:website":"www.capecodfive.com",
    "wof:name":"Cape Cod Five Cents Svngs Bnk",
    "wof:placetype":"venue"
},
  "geometry": {"coordinates":[-70.00083600000001,41.781437],"type":"Point"}
}