{
  "type": "Feature",
  "properties": {
    "addr:full":"389 Cambridge St Cambridge MA 02141",
    "addr:housenumber":"389",
    "addr:postcode":"02141",
    "addr:street":"Cambridge St",
    "iso:country":"US",
    "sg:address":"389 Cambridge St",
    "sg:city":"Cambridge",
    "sg:classifiers":[
        {
            "category":"Personal",
            "subcategory":"Beauty Salon",
            "type":"Services"
        }
    ],
    "sg:phone":"+1 617 354 7754",
    "sg:postcode":"02141",
    "sg:province":"MA",
    "sg:tags":[
        "shop"
    ],
    "wof:name":"Cambridge Hair Design",
    "wof:placetype":"venue"
},
  "geometry": {"coordinates":[-71.08233199999999,42.371376],"type":"Point"}
}