{
  "type": "Feature",
  "properties": {
    "addr:full": "260 Boston Post Rd Wayland MA 01778",
    "addr:housenumber": "260",
    "addr:postcode": "01778",
    "addr:street": "Boston Post Rd",
    "iso:country": "US",
    "sg:address": "260 Boston Post Rd",
    "sg:city": "Wayland",
    "sg:classifiers": [
      {
        "category": "Professional",
        "subcategory": "Lawyer \u0026 Legal Services",
        "type": "Services"
      }
    ],
    "sg:phone": "+1   ",
    "sg:postcode": "01778",
    "sg:province": "MA",
    "wof:name": "Linda Brownstein",
    "wof:placetype": "venue"
  },
  "geometry": {"coordinates":[-71.367784,42.363249],"type":"Point"}
}
