{
  "type": "Feature",
  "properties": {
    "addr:full": "331 Concord Ave Lexington MA 02421",
    "addr:housenumber": "331",
    "addr:postcode": "02421",
    "addr:street": "Concord Ave",
    "iso:country": "US",
    "sg:address": "331 Concord Ave",
    "sg:city": "Lexington",
    "sg:classifiers": [
      {
        "category": "Home \u0026 Garden",
        "subcategory": "Garden Supply",
        "type": "Retail Goods"
      }
    ],
    "sg:phone": "+1 781 863 0050",
    "sg:postcode": "02421",
    "sg:province": "MA",
    "sg:tags": [
      "mulch"
    ],
    "wof:name": "Cannizzo Brothers",
    "wof:placetype": "venue"
  },
  "geometry": {"coordinates":[-71.226991,42.417626],"type":"Point"}
}
