{
  "type": "Feature",
  "properties": {
    "iso:country":"US",
    "sg:address":"331 Concord Ave",
    "sg:city":"Lexington",
    "sg:classifiers":[
        {
            "category":"Home & Garden",
            "subcategory":"Garden Supply",
            "type":"Retail Goods"
        }
    ],
    "sg:phone":"+1 781 863 0050",
    "sg:postcode":"02421",
    "sg:province":"MA",
    "sg:tags":[
        "mulch"
    ],
    "wof:name":"Cannizzo Brothers",
    "wof:placetype":"venue"
},
  "geometry": {"coordinates":[-71.226991,42.417626],"type":"Point"}
}