{
  "type": "Feature",
  "properties": {
    "addr:full": "82 Academy Hill Rd Brighton MA 02135",
    "addr:housenumber": "82",
    "addr:postcode": "02135",
    "addr:street": "Academy Hill Rd",
    "iso:country": "US",
    "sg:address": "82 Academy Hill Rd",
    "sg:city": "Brighton",
    "sg:classifiers": [
      {
        "category": "Personal",
        "type": "Services"
      }
    ],
    "sg:phone": "+1   ",
    "sg:postcode": "02135",
    "sg:province": "MA",
    "wof:name": "Holly B Parent",
    "wof:placetype": "venue"
  },
  "geometry": {"coordinates":[-71.154741,42.345819],"type":"Point"}
}
