{
  "type": "Feature",
  "properties": {
    "iso:country":"US",
    "sg:address":"82 Academy Hill Rd",
    "sg:city":"Brighton",
    "sg:classifiers":[
        {
            "category":"Personal",
            "type":"Services"
        }
    ],
    "sg:phone":"+1   ",
    "sg:postcode":"02135",
    "sg:province":"MA",
    "wof:name":"Holly B Parent",
    "wof:placetype":"venue"
},
  "geometry": {"coordinates":[-71.154741,42.345819],"type":"Point"}
}