{
  "type": "Feature",
  "properties": {
    "addr:full":"20 Moore Ln Eastham MA 02642",
    "addr:housenumber":"20",
    "addr:postcode":"02642",
    "addr:street":"Moore Ln",
    "iso:country":"US",
    "sg:address":"20 Moore Ln",
    "sg:city":"Eastham",
    "sg:classifiers":[
        {
            "category":"Train Station",
            "subcategory":"Rail",
            "type":"Transportation"
        }
    ],
    "sg:phone":"+1 508 240 0326",
    "sg:postcode":"02642",
    "sg:province":"MA",
    "sg:tags":[
        "lobster"
    ],
    "wof:name":"Norsewind Fisheries",
    "wof:placetype":"venue"
},
  "geometry": {"coordinates":[-69.978754,41.835216],"type":"Point"}
}