{
  "type": "Feature",
  "properties": {
    "addr:full": "414 County St New Bedford MA 02740",
    "addr:housenumber": "414",
    "addr:postcode": "02740",
    "addr:street": "County St",
    "iso:country": "US",
    "sg:address": "414 County St",
    "sg:city": "New Bedford",
    "sg:classifiers": [
      {
        "category": "Professional",
        "subcategory": "Lawyer \u0026 Legal Services",
        "type": "Services"
      }
    ],
    "sg:phone": "+1 508 994 9696",
    "sg:postcode": "02740",
    "sg:province": "MA",
    "sg:tags": [
      "attorney"
    ],
    "wof:name": "Cabral \u0026 Cabral",
    "wof:placetype": "venue"
  },
  "geometry": {"coordinates":[-70.929671,41.632369],"type":"Point"}
}
