{
  "type": "Feature",
  "properties": {
    "addr:full": "280 Blanchard Road Belmont MA 02478",
    "addr:housenumber": "280",
    "addr:postcode": "02478",
    "addr:street": "Blanchard Road",
    "iso:country": "US",
    "sg:address": "280 Blanchard Road",
    "sg:city": "Belmont",
    "sg:classifiers": [
      {
        "category": "Home \u0026 Garden",
        "subcategory": "Hardware",
        "type": "Retail Goods"
      }
    ],
    "sg:phone": "+1 617 489 0250",
    "sg:postcode": "02478",
    "sg:province": "MA",
    "sg:tags": [
      "store"
    ],
    "wof:name": "Hillside Garden \u0026 True Value",
    "wof:placetype": "venue"
  },
  "geometry": {"coordinates":[-71.158163,42.394353],"type":"Point"}
}
