{
  "type": "Feature",
  "properties": {
    "addr:full": "970 Fellsway Medford MA 02155",
    "addr:housenumber": "970",
    "addr:postcode": "02155",
    "addr:street": "Fellsway",
    "iso:country": "US",
    "sg:address": "970 Fellsway",
    "sg:city": "Medford",
    "sg:classifiers": [
      {
        "category": "Freight",
        "type": "Transportation"
      }
    ],
    "sg:phone": "+1 781 391 0117",
    "sg:postcode": "02155",
    "sg:province": "MA",
    "sg:tags": [
      "commercial",
      "storage"
    ],
    "wof:name": "Planet Self Storage",
    "wof:placetype": "venue"
  },
  "geometry": {"coordinates":[-71.084364,42.415647],"type":"Point"}
}
