{
  "type": "Feature",
  "properties": {
    "addr:full":"1 Faneuil Hall Market Pl # 301 Boston MA 02109",
    "addr:housenumber":"1;301",
    "addr:postcode":"02109",
    "addr:street":"Faneuil Hall Market Pl #",
    "iso:country":"US",
    "sg:address":"1 Faneuil Hall Market Pl # 301",
    "sg:city":"Boston",
    "sg:classifiers":[
        {
            "category":"Professional",
            "subcategory":"Accounting & Tax Preparation",
            "type":"Services"
        }
    ],
    "sg:phone":"+1 617 523 3188",
    "sg:postcode":"02109",
    "sg:province":"MA",
    "sg:tags":[
        "public",
        "accountants-certified"
    ],
    "wof:name":"Paul Sapienza Pc",
    "wof:placetype":"venue"
},
  "geometry": {"coordinates":[-71.05579400000001,42.359959],"type":"Point"}
}