{
  "type": "Feature",
  "properties": {
    "iso:country":"US",
    "sg:address":"25 Kingston St",
    "sg:city":"Boston",
    "sg:classifiers":[
        {
            "category":"Professional",
            "subcategory":"Management & Consulting",
            "type":"Services"
        }
    ],
    "sg:phone":"+1 617 399 5000",
    "sg:postcode":"02111",
    "sg:province":"MA",
    "sg:tags":[
        "marketing",
        "program"
    ],
    "wof:name":"Dotomi LTD",
    "wof:placetype":"venue"
},
  "geometry": {"coordinates":[-71.059405,42.353402],"type":"Point"}
}