{
  "type": "Feature",
  "properties": {
    "iso:country":"US",
    "sg:address":"521 Main St",
    "sg:city":"Harwich",
    "sg:classifiers":[
        {
            "category":"Home & Garden",
            "subcategory":"Furniture",
            "type":"Retail Goods"
        }
    ],
    "sg:phone":"+1 508 432 6881",
    "sg:postcode":"02645",
    "sg:province":"MA",
    "sg:tags":[
        "top",
        "counter"
    ],
    "wof:name":"Kitchen Lady & Co",
    "wof:placetype":"venue"
},
  "geometry": {"coordinates":[-70.09133199999999,41.688924],"type":"Point"}
}