{
  "type": "Feature",
  "properties": {
    "addr:full":"13 Welch Rd South Easton MA 02375",
    "addr:housenumber":"13",
    "addr:postcode":"02375",
    "addr:street":"Welch Rd",
    "iso:country":"US",
    "sg:address":"13 Welch Rd",
    "sg:city":"South Easton",
    "sg:classifiers":[
        {
            "category":"Real Estate",
            "subcategory":"Real Estate Agent",
            "type":"Services"
        }
    ],
    "sg:phone":"+1 508 230 3746",
    "sg:postcode":"02375",
    "sg:province":"MA",
    "sg:tags":[
        "management"
    ],
    "wof:name":"A 1 Property Management",
    "wof:placetype":"venue"
},
  "geometry": {"coordinates":[-71.07901200000001,42.044278],"type":"Point"}
}