{
  "type": "Feature",
  "properties": {
    "iso:country":"US",
    "sg:address":"87 Maple St",
    "sg:city":"West Boylston",
    "sg:classifiers":[
        {
            "category":"Real Estate",
            "subcategory":"Real Estate Agent",
            "type":"Services"
        }
    ],
    "sg:phone":"+1 508 835 6060",
    "sg:postcode":"01583",
    "sg:province":"MA",
    "sg:tags":[
        "authorities",
        "housing"
    ],
    "wof:name":"West Boylston Housing Auth",
    "wof:placetype":"venue"
},
  "geometry": {"coordinates":[-71.778791,42.357263],"type":"Point"}
}