{
  "type": "Feature",
  "properties": {
    "iso:country":"US",
    "sg:address":"1180 Beacon Street Suite 1",
    "sg:city":"Brookline",
    "sg:classifiers":[
        {
            "category":"Sports & Exercise",
            "subcategory":"Gym",
            "type":"Entertainment"
        }
    ],
    "sg:phone":"+1 617 731 0060",
    "sg:postcode":"02446",
    "sg:province":"MA",
    "sg:tags":[
        "trainer"
    ],
    "wof:name":"Abortion-Abortion Care by Repro Associates",
    "wof:placetype":"venue"
},
  "geometry": {"coordinates":[-71.11447800000001,42.34415],"type":"Point"}
}