{
  "type": "Feature",
  "properties": {
    "addr:full": "1180 Beacon Street Suite 1 Brookline MA 02446",
    "addr:housenumber": "1180",
    "addr:postcode": "02446",
    "addr:street": "Beacon Street Suite 1",
    "iso:country": "US",
    "sg:address": "1180 Beacon Street Suite 1",
    "sg:city": "Brookline",
    "sg:classifiers": [
      {
        "category": "Sports \u0026 Exercise",
        "subcategory": "Gym",
        "type": "Entertainment"
      }
    ],
    "sg:phone": "+1 617 731 0060",
    "sg:postcode": "02446",
    "sg:province": "MA",
    "sg:tags": [
      "trainer"
    ],
    "wof:name": "Abortion-Abortion Care by Repro Associates",
    "wof:placetype": "venue"
  },
  "geometry": {"coordinates":[-71.114478,42.34415],"type":"Point"}
}
