{
  "type": "Feature",
  "properties": {
    "iso:country":"US",
    "sg:address":"99 School St",
    "sg:city":"Weston",
    "sg:classifiers":[
        {
            "category":"Education",
            "subcategory":"School",
            "type":"Public Place"
        }
    ],
    "sg:phone":"+1 781 891 8029",
    "sg:postcode":"02493",
    "sg:province":"MA",
    "wof:name":"Children's Center Of Weston",
    "wof:placetype":"venue"
},
  "geometry": {"coordinates":[-71.293756,42.361647],"type":"Point"}
}