{
  "type": "Feature",
  "properties": {
    "iso:country":"US",
    "sg:address":"148 Brookline Ave",
    "sg:city":"Boston",
    "sg:classifiers":[
        {
            "category":"Real Estate",
            "subcategory":"Developer",
            "type":"Services"
        }
    ],
    "sg:phone":"+1 617 236 0889",
    "sg:postcode":"02215",
    "sg:province":"MA",
    "wof:name":"Fenway Ventures",
    "wof:placetype":"venue"
},
  "geometry": {"coordinates":[-71.100892,42.344871],"type":"Point"}
}