{
  "type": "Feature",
  "properties": {
    "iso:country":"US",
    "sg:address":"579 Main St",
    "sg:city":"Chatham",
    "sg:classifiers":[
        {
            "category":"Shopping",
            "type":"Retail Goods"
        }
    ],
    "sg:phone":"+1 508 945 4711",
    "sg:postcode":"02633",
    "sg:province":"MA",
    "sg:tags":[
        "picture",
        "manufacturer",
        "art",
        "frames-wholesale",
        "gallery"
    ],
    "wof:name":"Kennedy Studios",
    "wof:placetype":"venue"
},
  "geometry": {"coordinates":[-69.958946,41.68145],"type":"Point"}
}