{
  "type": "Feature",
  "properties": {
    "iso:country":"US",
    "sg:address":"95 Ronald Rd",
    "sg:city":"Arlington",
    "sg:classifiers":[
        {
            "category":"Building & Trades",
            "subcategory":"Landscaping Services",
            "type":"Services"
        }
    ],
    "sg:phone":"+1 781 641 0750",
    "sg:postcode":"02474",
    "sg:province":"MA",
    "sg:tags":[
        "designer",
        "landscape"
    ],
    "wof:name":"Leonard Design Assoc",
    "wof:placetype":"venue"
},
  "geometry": {"coordinates":[-71.16883,42.428957],"type":"Point"}
}