{
  "type": "Feature",
  "properties": {
    "iso:country":"US",
    "sg:address":"50 Beach Plum Ln",
    "sg:city":"Menemsha",
    "sg:classifiers":[
        {
            "category":"Travel",
            "subcategory":"Hotels & Motels",
            "type":"Entertainment"
        }
    ],
    "sg:phone":"+1 508 645 9454",
    "sg:postcode":"02571",
    "sg:province":"MA",
    "sg:website":"www.beachpluminn.com",
    "wof:name":"Beach Plum Inn & Restaurant",
    "wof:placetype":"venue"
},
  "geometry": {"coordinates":[-70.67254,41.725901],"type":"Point"}
}