{
  "type": "Feature",
  "properties": {
    "addr:full": "50 Beach Plum Ln Menemsha MA 02571",
    "addr:housenumber": "50",
    "addr:postcode": "02571",
    "addr:street": "Beach Plum Ln",
    "iso:country": "US",
    "sg:address": "50 Beach Plum Ln",
    "sg:city": "Menemsha",
    "sg:classifiers": [
      {
        "category": "Travel",
        "subcategory": "Hotels \u0026 Motels",
        "type": "Entertainment"
      }
    ],
    "sg:phone": "+1 508 645 9454",
    "sg:postcode": "02571",
    "sg:province": "MA",
    "sg:website": "www.beachpluminn.com",
    "wof:name": "Beach Plum Inn \u0026 Restaurant",
    "wof:placetype": "venue"
  },
  "geometry": {"coordinates":[-70.67254,41.725901],"type":"Point"}
}
