{
  "type": "Feature",
  "properties": {
    "iso:country":"US",
    "sg:address":"90 Spencer Ave",
    "sg:city":"Chelsea",
    "sg:classifiers":[
        {
            "category":"Building & Trades",
            "subcategory":"Electrical",
            "type":"Services"
        }
    ],
    "sg:phone":"+1 617 884 2525",
    "sg:postcode":"02150",
    "sg:province":"MA",
    "sg:tags":[
        "industrial",
        "electrician",
        "contractors-commercial",
        "electric"
    ],
    "sg:website":"http://www.chappycorp.com",
    "wof:name":"The Chappy Corporation",
    "wof:placetype":"venue"
},
  "geometry": {"coordinates":[-71.02471199999999,42.397209],"type":"Point"}
}