{
  "type": "Feature",
  "properties": {
    "addr:full":"20 Maple St Lancaster MA 01562",
    "addr:housenumber":"20",
    "addr:postcode":"01562",
    "addr:street":"Maple St",
    "iso:country":"US",
    "sg:address":"20 Maple St",
    "sg:city":"Lancaster",
    "sg:classifiers":[
        {
            "category":"Professional",
            "subcategory":"Research",
            "type":"Services"
        }
    ],
    "sg:phone":"+1 978 368 3477",
    "sg:postcode":"01562",
    "sg:province":"MA",
    "sg:tags":[
        "medical"
    ],
    "sg:website":"www.davincibiomed.com",
    "wof:name":"Da Vinci Biomedical Research",
    "wof:placetype":"venue"
},
  "geometry": {"coordinates":[-71.99242099999999,42.244068],"type":"Point"}
}