{
  "type": "Feature",
  "properties": {
    "addr:full":"920 Meadow St Chicopee MA 01013",
    "addr:housenumber":"920",
    "addr:postcode":"01013",
    "addr:street":"Meadow St",
    "iso:country":"US",
    "sg:address":"920 Meadow St",
    "sg:city":"Chicopee",
    "sg:classifiers":[
        {
            "category":"Organizations",
            "subcategory":"Religious Organization",
            "type":"Services"
        }
    ],
    "sg:phone":"+1 413 598 0921",
    "sg:postcode":"01013",
    "sg:province":"MA",
    "sg:tags":[
        "church"
    ],
    "wof:name":"Victory Chapel",
    "wof:placetype":"venue"
},
  "geometry": {"coordinates":[-72.613889,42.162291],"type":"Point"}
}