{
  "type": "Feature",
  "properties": {
    "addr:full":"64 Kings Ct Yarmouth Port MA 02649",
    "addr:housenumber":"64",
    "addr:postcode":"02649",
    "addr:street":"Kings Ct",
    "iso:country":"US",
    "sg:address":"64 Kings Ct",
    "sg:city":"Yarmouth Port",
    "sg:classifiers":[
        {
            "category":"Sports & Exercise",
            "subcategory":"Golf",
            "type":"Entertainment"
        }
    ],
    "sg:phone":"+1 508 362 8870",
    "sg:postcode":"02649",
    "sg:province":"MA",
    "sg:tags":[
        "course"
    ],
    "sg:website":"www.kingswaygolf.com",
    "wof:name":"Kings Way Golf Club",
    "wof:placetype":"venue"
},
  "geometry": {"coordinates":[-70.494726,41.60133],"type":"Point"}
}