{
  "type": "Feature",
  "properties": {
    "addr:full":"323 Merrimac St Newburyport MA 01950",
    "addr:housenumber":"323",
    "addr:postcode":"01950",
    "addr:street":"Merrimac St",
    "iso:country":"US",
    "sg:address":"323 Merrimac St",
    "sg:city":"Newburyport",
    "sg:classifiers":[
        {
            "category":"Building & Trades",
            "subcategory":"Construction",
            "type":"Services"
        }
    ],
    "sg:phone":"+1   ",
    "sg:postcode":"01950",
    "sg:province":"MA",
    "sg:tags":[
        "residential"
    ],
    "wof:name":"Keith R Dodge General Contr",
    "wof:placetype":"venue"
},
  "geometry": {"coordinates":[-70.886263,42.82185],"type":"Point"}
}