{
  "type": "Feature",
  "properties": {
    "addr:full":"15 Raymond Rd Salem MA 01970",
    "addr:housenumber":"15",
    "addr:postcode":"01970",
    "addr:street":"Raymond Rd",
    "iso:country":"US",
    "sg:address":"15 Raymond Rd",
    "sg:city":"Salem",
    "sg:classifiers":[
        {
            "category":"Home & Garden",
            "subcategory":"Home Furnishings",
            "type":"Retail Goods"
        }
    ],
    "sg:phone":"+1 978 744 7435",
    "sg:postcode":"01970",
    "sg:province":"MA",
    "sg:tags":[
        "cover",
        "enclosure",
        "radiator"
    ],
    "wof:name":"N E Woodworks",
    "wof:placetype":"venue"
},
  "geometry": {"coordinates":[-70.893742,42.501572],"type":"Point"}
}