{
  "type": "Feature",
  "properties": {
    "iso:country":"US",
    "sg:address":"30 Hartford St",
    "sg:city":"Medfield",
    "sg:classifiers":[
        {
            "category":"Professional",
            "type":"Services"
        }
    ],
    "sg:phone":"+1   ",
    "sg:postcode":"02052",
    "sg:province":"MA",
    "wof:name":"Aj Lurie Inc",
    "wof:placetype":"venue"
},
  "geometry": {"coordinates":[-71.275496,42.207057],"type":"Point"}
}