{
  "type": "Feature",
  "properties": {
    "iso:country":"US",
    "sg:address":"48 Pine Hill Rd",
    "sg:city":"Russell",
    "sg:classifiers":[
        {
            "category":"Shopping",
            "subcategory":"Bicycles & Sporting Goods",
            "type":"Retail Goods"
        }
    ],
    "sg:phone":"+1 413 862 4525",
    "sg:postcode":"01071",
    "sg:province":"MA",
    "wof:name":"J C Golfworks",
    "wof:placetype":"venue"
},
  "geometry": {"coordinates":[-72.86005900000001,42.191267],"type":"Point"}
}