{
  "type": "Feature",
  "properties": {
    "addr:full": "48 Pine Hill Rd Russell MA 01071",
    "addr:housenumber": "48",
    "addr:postcode": "01071",
    "addr:street": "Pine Hill Rd",
    "iso:country": "US",
    "sg:address": "48 Pine Hill Rd",
    "sg:city": "Russell",
    "sg:classifiers": [
      {
        "category": "Shopping",
        "subcategory": "Bicycles \u0026 Sporting Goods",
        "type": "Retail Goods"
      }
    ],
    "sg:phone": "+1 413 862 4525",
    "sg:postcode": "01071",
    "sg:province": "MA",
    "wof:name": "J C Golfworks",
    "wof:placetype": "venue"
  },
  "geometry": {"coordinates":[-72.860059,42.191267],"type":"Point"}
}
