{
  "type": "Feature",
  "properties": {
    "addr:full":"119 Main St Townsend MA 01469",
    "addr:housenumber":"119",
    "addr:postcode":"01469",
    "addr:street":"Main St",
    "iso:country":"US",
    "sg:address":"119 Main St",
    "sg:city":"Townsend",
    "sg:classifiers":[
        {
            "category":"Organizations",
            "subcategory":"Community Association",
            "type":"Services"
        }
    ],
    "sg:phone":"+1 978 597 8761",
    "sg:postcode":"01469",
    "sg:province":"MA",
    "sg:tags":[
        "military"
    ],
    "wof:name":"American Legion",
    "wof:placetype":"venue"
},
  "geometry": {"coordinates":[-71.682131,42.655591],"type":"Point"}
}