{
  "type": "Feature",
  "properties": {
    "addr:full": "45 Winchester St Boston MA 02116",
    "addr:housenumber": "45",
    "addr:postcode": "02116",
    "addr:street": "Winchester St",
    "iso:country": "US",
    "sg:address": "45 Winchester St",
    "sg:city": "Boston",
    "sg:classifiers": [
      {
        "category": "Organizations",
        "subcategory": "Labor Organization",
        "type": "Services"
      }
    ],
    "sg:phone": "+1 617 426 1540",
    "sg:postcode": "02116",
    "sg:province": "MA",
    "wof:name": "Moving Picture Operators Union",
    "wof:placetype": "venue"
  },
  "geometry": {"coordinates":[-71.06959,42.349437],"type":"Point"}
}
