{
  "type": "Feature",
  "properties": {
    "addr:full": "11 Kearney Sq Lowell MA 01852",
    "addr:housenumber": "11",
    "addr:postcode": "01852",
    "addr:street": "Kearney Sq",
    "iso:country": "US",
    "sg:address": "11 Kearney Sq",
    "sg:city": "Lowell",
    "sg:classifiers": [
      {
        "category": "Banks \u0026 Credit Unions",
        "subcategory": "Bank",
        "type": "Services"
      }
    ],
    "sg:phone": "+1 978 459 9899",
    "sg:postcode": "01852",
    "sg:province": "MA",
    "sg:tags": [
      "loan"
    ],
    "wof:name": "Lowell Development \u0026 Financial",
    "wof:placetype": "venue"
  },
  "geometry": {"coordinates":[-71.307162,42.645283],"type":"Point"}
}
