{
  "type": "Feature",
  "properties": {
    "addr:full":"131 Linden St Waltham MA 02452",
    "addr:housenumber":"131",
    "addr:postcode":"02452",
    "addr:street":"Linden St",
    "iso:country":"US",
    "sg:address":"131 Linden St",
    "sg:city":"Waltham",
    "sg:classifiers":[
        {
            "category":"Retail",
            "subcategory":"Auto Repair",
            "type":"Services"
        }
    ],
    "sg:phone":"+1 781 788 4993",
    "sg:postcode":"02452",
    "sg:province":"MA",
    "sg:tags":[
        "repairing",
        "automobile"
    ],
    "wof:name":"Diaz Auto Repair",
    "wof:placetype":"venue"
},
  "geometry": {"coordinates":[-71.220917,42.380045],"type":"Point"}
}