{
  "type": "Feature",
  "properties": {
    "addr:full":"59 Cottage St Sharon MA 02067",
    "addr:housenumber":"59",
    "addr:postcode":"02067",
    "addr:street":"Cottage St",
    "iso:country":"US",
    "sg:address":"59 Cottage St",
    "sg:city":"Sharon",
    "sg:classifiers":[
        {
            "category":"Organizations",
            "subcategory":"Religious Organization",
            "type":"Services"
        }
    ],
    "sg:phone":"+1 781 784 2265",
    "sg:postcode":"02067",
    "sg:province":"MA",
    "sg:tags":[
        "church"
    ],
    "sg:website":"www.ourladyofsorrows.net",
    "wof:name":"Our Lady Of Sorrows Hall",
    "wof:placetype":"venue"
},
  "geometry": {"coordinates":[-71.172701,42.117053],"type":"Point"}
}