{
  "type": "Feature",
  "properties": {
    "addr:full":"125 Pleasant St Ashland MA 01721",
    "addr:housenumber":"125",
    "addr:postcode":"01721",
    "addr:street":"Pleasant St",
    "iso:country":"US",
    "sg:address":"125 Pleasant St",
    "sg:city":"Ashland",
    "sg:classifiers":[
        {
            "category":"Building & Trades",
            "subcategory":"Construction",
            "type":"Services"
        }
    ],
    "sg:phone":"+1   ",
    "sg:postcode":"01721",
    "sg:province":"MA",
    "sg:tags":[
        "hanging",
        "contractor"
    ],
    "wof:name":"Mouras Painting",
    "wof:placetype":"venue"
},
  "geometry": {"coordinates":[-71.471768,42.26201],"type":"Point"}
}