{
  "type": "Feature",
  "properties": {
    "addr:full": "30 N Main St Leominster MA 01453",
    "addr:housenumber": "30",
    "addr:postcode": "01453",
    "addr:street": "N Main St",
    "iso:country": "US",
    "sg:address": "30 N Main St",
    "sg:city": "Leominster",
    "sg:classifiers": [
      {
        "category": "Autos \u0026 Motor Vehicles",
        "subcategory": "Auto Supplies",
        "type": "Retail Goods"
      }
    ],
    "sg:phone": "+1 978 537 4011",
    "sg:postcode": "01453",
    "sg:province": "MA",
    "sg:tags": [
      "automobile",
      "parts"
    ],
    "wof:name": "Central Auto Parts",
    "wof:placetype": "venue"
  },
  "geometry": {"coordinates":[-71.756212,42.531891],"type":"Point"}
}
