{
  "type": "Feature",
  "properties": {
    "addr:full": "10 Cove St Chelmsford MA 01824",
    "addr:housenumber": "10",
    "addr:postcode": "01824",
    "addr:street": "Cove St",
    "iso:country": "US",
    "sg:address": "10 Cove St",
    "sg:city": "Chelmsford",
    "sg:classifiers": [
      {
        "category": "Banks \u0026 Credit Unions",
        "subcategory": "Bank",
        "type": "Services"
      }
    ],
    "sg:phone": "+1 978 256 6214",
    "sg:postcode": "01824",
    "sg:province": "MA",
    "sg:tags": [
      "loan",
      "real estate"
    ],
    "wof:name": "Global Mortgages",
    "wof:placetype": "venue"
  },
  "geometry": {"coordinates":[-71.339222,42.603058],"type":"Point"}
}
