{
  "type": "Feature",
  "properties": {
    "iso:country":"US",
    "sg:address":"125 Jericho Rd",
    "sg:city":"Weston",
    "sg:classifiers":[
        {
            "category":"Professional",
            "subcategory":"Lawyer & Legal Services",
            "type":"Services"
        }
    ],
    "sg:phone":"+1 781 647 3500",
    "sg:postcode":"02493",
    "sg:province":"MA",
    "sg:tags":[
        "attorney"
    ],
    "wof:name":"John W Costello",
    "wof:placetype":"venue"
},
  "geometry": {"coordinates":[-71.308538,42.369676],"type":"Point"}
}