{
  "type": "Feature",
  "properties": {
    "addr:full": "8 Chelmsford St Chelmsford MA 01824",
    "addr:housenumber": "8",
    "addr:postcode": "01824",
    "addr:street": "Chelmsford St",
    "iso:country": "US",
    "sg:address": "8 Chelmsford St",
    "sg:city": "Chelmsford",
    "sg:classifiers": [
      {
        "category": "Insurance",
        "subcategory": "Hazard Insurance",
        "type": "Services"
      }
    ],
    "sg:phone": "+1 978 256 0900",
    "sg:postcode": "01824",
    "sg:province": "MA",
    "sg:website": "www.CMInsuranceAgency.com/",
    "wof:name": "Christopoulos Muldoon Insurance Agency, Inc.",
    "wof:placetype": "venue"
  },
  "geometry": {"coordinates":[-71.351159,42.597214],"type":"Point"}
}
