{
  "type": "Feature",
  "properties": {
    "addr:full": "101 Tremont St Ste 401 Boston MA 02108",
    "addr:housenumber": "101",
    "addr:postcode": "02108",
    "addr:street": "Tremont St Ste 401",
    "iso:country": "US",
    "sg:address": "101 Tremont St Ste 401",
    "sg:city": "Boston",
    "sg:classifiers": [
      {
        "category": "Professional",
        "subcategory": "Business Services",
        "type": "Services"
      },
      {
        "category": "Organizations",
        "subcategory": "Membership Organization",
        "type": "Services"
      }
    ],
    "sg:phone": "+1 617 742 0054",
    "sg:postcode": "02108",
    "sg:province": "MA",
    "sg:tags": [
      "environmental",
      "product",
      "conservation",
      "ecological"
    ],
    "wof:name": "Environment Northeast",
    "wof:placetype": "venue"
  },
  "geometry": {"coordinates":[-71.061249,42.357159],"type":"Point"}
}
