{
  "type": "Feature",
  "properties": {
    "addr:full": "24 Spice St Ste 2 Charlestown MA 02129",
    "addr:housenumber": "24",
    "addr:postcode": "02129",
    "addr:street": "Spice St Ste 2",
    "iso:country": "US",
    "sg:address": "24 Spice St Ste 2",
    "sg:city": "Charlestown",
    "sg:classifiers": [
      {
        "category": "Utilities",
        "subcategory": "Electric",
        "type": "Services"
      }
    ],
    "sg:phone": "+1 617 241 0292",
    "sg:postcode": "02129",
    "sg:province": "MA",
    "sg:tags": [
      "electronic",
      "power",
      "supply"
    ],
    "wof:name": "Atw Electronics Inc",
    "wof:placetype": "venue"
  },
  "geometry": {"coordinates":[-71.075129,42.383349],"type":"Point"}
}
