{
  "type": "Feature",
  "properties": {
    "iso:country":"US",
    "sg:address":"345 Washington St",
    "sg:city":"Pembroke",
    "sg:classifiers":[
        {
            "category":"Home & Garden",
            "subcategory":"Carpets & Floor Coverings",
            "type":"Retail Goods"
        }
    ],
    "sg:phone":"+1 781 829 6952",
    "sg:postcode":"02359",
    "sg:province":"MA",
    "wof:name":"Durable Athletic Systems Inc",
    "wof:placetype":"venue"
},
  "geometry": {"coordinates":[-70.79227899999999,42.091215],"type":"Point"}
}