{
  "type": "Feature",
  "properties": {
    "addr:full": "345 Washington St Pembroke MA 02359",
    "addr:housenumber": "345",
    "addr:postcode": "02359",
    "addr:street": "Washington St",
    "iso:country": "US",
    "sg:address": "345 Washington St",
    "sg:city": "Pembroke",
    "sg:classifiers": [
      {
        "category": "Home \u0026 Garden",
        "subcategory": "Carpets \u0026 Floor Coverings",
        "type": "Retail Goods"
      }
    ],
    "sg:phone": "+1 781 829 6952",
    "sg:postcode": "02359",
    "sg:province": "MA",
    "wof:name": "Durable Athletic Systems Inc",
    "wof:placetype": "venue"
  },
  "geometry": {"coordinates":[-70.792279,42.091215],"type":"Point"}
}
