{
  "type": "Feature",
  "properties": {
    "addr:full": "655 Atlantic Ave Boston MA 02111",
    "addr:housenumber": "655",
    "addr:postcode": "02111",
    "addr:street": "Atlantic Ave",
    "iso:country": "US",
    "sg:address": "655 Atlantic Ave",
    "sg:city": "Boston",
    "sg:classifiers": [
      {
        "category": "Professional",
        "subcategory": "Lawyer \u0026 Legal Services",
        "type": "Services"
      }
    ],
    "sg:phone": "+1 617 426 5973",
    "sg:postcode": "02111",
    "sg:province": "MA",
    "wof:name": "Pepe \u0026 Hazard",
    "wof:placetype": "venue"
  },
  "geometry": {"coordinates":[-71.055701,42.352458],"type":"Point"}
}
