{
  "type": "Feature",
  "properties": {
    "iso:country":"US",
    "sg:address":"60 MacArthur Blvd",
    "sg:city":"Buzzards Bay",
    "sg:classifiers":[
        {
            "category":"Autos & Motor Vehicles",
            "subcategory":"Automobile Sales",
            "type":"Retail Goods"
        },
        {
            "category":"Retail",
            "subcategory":"Auto Repair",
            "type":"Services"
        }
    ],
    "sg:phone":"+1 877 280 0080",
    "sg:postcode":"02532",
    "sg:province":"MA",
    "sg:tags":[
        "car"
    ],
    "wof:name":"Finance Authority",
    "wof:placetype":"venue"
},
  "geometry": {"coordinates":[-70.58560199999999,41.738701],"type":"Point"}
}