{
  "type": "Feature",
  "properties": {
    "iso:country":"US",
    "sg:address":"61 Phillips Brooks Rd",
    "sg:city":"Westwood",
    "sg:classifiers":[
        {
            "category":"Professional",
            "type":"Services"
        }
    ],
    "sg:phone":"+1 781 326 9964",
    "sg:postcode":"02090",
    "sg:province":"MA",
    "sg:tags":[
        "establishment"
    ],
    "wof:name":"Substitute Caller Coordinator",
    "wof:placetype":"venue"
},
  "geometry": {"coordinates":[-71.17259799999999,42.215493],"type":"Point"}
}