{
  "type": "Feature",
  "properties": {
    "iso:country":"US",
    "sg:address":"78 Holten St",
    "sg:city":"Danvers",
    "sg:classifiers":[
        {
            "category":"Recreation",
            "type":"Entertainment"
        }
    ],
    "sg:phone":"+1 978 774 4779",
    "sg:postcode":"01923",
    "sg:province":"MA",
    "sg:tags":[
        "instruction",
        "gymnastic"
    ],
    "wof:name":"Yellow Jackets Gymnastics Too",
    "wof:placetype":"venue"
},
  "geometry": {"coordinates":[-70.947845,42.560877],"type":"Point"}
}