{
  "type": "Feature",
  "properties": {
    "addr:full": "64 Scranton Ave Falmouth MA 02540",
    "addr:housenumber": "64",
    "addr:postcode": "02540",
    "addr:street": "Scranton Ave",
    "iso:country": "US",
    "sg:address": "64 Scranton Ave",
    "sg:city": "Falmouth",
    "sg:classifiers": [
      {
        "category": "Real Estate",
        "subcategory": "Real Estate Agent",
        "type": "Services"
      }
    ],
    "sg:phone": "+1 508 540 7500",
    "sg:postcode": "02540",
    "sg:province": "MA",
    "wof:name": "Premier Properties Real Estate",
    "wof:placetype": "venue"
  },
  "geometry": {"coordinates":[-70.602531,41.551971],"type":"Point"}
}
