{
  "type": "Feature",
  "properties": {
    "addr:full":"449 Boston Post Rd E Marlborough MA 01752",
    "addr:housenumber":"449",
    "addr:postcode":"01752",
    "addr:street":"Boston Post Rd E",
    "iso:country":"US",
    "sg:address":"449 Boston Post Rd E",
    "sg:city":"Marlborough",
    "sg:classifiers":[
        {
            "category":"Real Estate",
            "subcategory":"Real Estate Agent",
            "type":"Services"
        }
    ],
    "sg:phone":"+1 508 485 1850",
    "sg:postcode":"01752",
    "sg:province":"MA",
    "wof:name":"Real Estate Discounters",
    "wof:placetype":"venue"
},
  "geometry": {"coordinates":[-71.51531199999999,42.348115],"type":"Point"}
}