{
  "type": "Feature",
  "properties": {
    "addr:full": "130 Maynard Rd Framingham MA 01701",
    "addr:housenumber": "130",
    "addr:postcode": "01701",
    "addr:street": "Maynard Rd",
    "iso:country": "US",
    "sg:address": "130 Maynard Rd",
    "sg:city": "Framingham",
    "sg:classifiers": [
      {
        "category": "Health Services",
        "subcategory": "Doctor",
        "type": "Services"
      }
    ],
    "sg:phone": "+1 508 879 8250",
    "sg:postcode": "01701",
    "sg:province": "MA",
    "sg:tags": [
      "dentist"
    ],
    "wof:name": "Spinale Dental Group",
    "wof:placetype": "venue"
  },
  "geometry": {"coordinates":[-71.441127,42.299631],"type":"Point"}
}
