{
  "type": "Feature",
  "properties": {
    "iso:country":"US",
    "sg:address":"130 Maynard Rd",
    "sg:city":"Framingham",
    "sg:classifiers":[
        {
            "category":"Health Services",
            "subcategory":"Doctor",
            "type":"Services"
        }
    ],
    "sg:phone":"+1 508 879 8250",
    "sg:postcode":"01701",
    "sg:province":"MA",
    "sg:tags":[
        "dentist"
    ],
    "wof:name":"Spinale Dental Group",
    "wof:placetype":"venue"
},
  "geometry": {"coordinates":[-71.44112699999999,42.299631],"type":"Point"}
}