{
  "type": "Feature",
  "properties": {
    "iso:country":"US",
    "sg:address":"46 Washington St",
    "sg:city":"Attleboro",
    "sg:classifiers":[
        {
            "category":"Travel",
            "subcategory":"Hotels & Motels",
            "type":"Entertainment"
        }
    ],
    "sg:phone":"+1 508 399 7380",
    "sg:postcode":"02703",
    "sg:province":"MA",
    "wof:name":"Hollywood",
    "wof:placetype":"venue"
},
  "geometry": {"coordinates":[-71.35430100000001,41.928398],"type":"Point"}
}