{
  "type": "Feature",
  "properties": {
    "addr:full": "46 Washington St Attleboro MA 02703",
    "addr:housenumber": "46",
    "addr:postcode": "02703",
    "addr:street": "Washington St",
    "iso:country": "US",
    "sg:address": "46 Washington St",
    "sg:city": "Attleboro",
    "sg:classifiers": [
      {
        "category": "Travel",
        "subcategory": "Hotels \u0026 Motels",
        "type": "Entertainment"
      }
    ],
    "sg:phone": "+1 508 399 7380",
    "sg:postcode": "02703",
    "sg:province": "MA",
    "wof:name": "Hollywood",
    "wof:placetype": "venue"
  },
  "geometry": {"coordinates":[-71.354301,41.928398],"type":"Point"}
}
