{
  "type": "Feature",
  "properties": {
    "addr:full": "86 Cambridge St Winchester MA 01890",
    "addr:housenumber": "86",
    "addr:postcode": "01890",
    "addr:street": "Cambridge St",
    "iso:country": "US",
    "sg:address": "86 Cambridge St",
    "sg:city": "Winchester",
    "sg:classifiers": [
      {
        "category": "Education",
        "subcategory": "Preschool",
        "type": "Public Place"
      }
    ],
    "sg:phone": "+1 781 368 7198",
    "sg:postcode": "01890",
    "sg:province": "MA",
    "sg:website": "PreschoolSocial.com",
    "wof:name": "Preschool Social Academy",
    "wof:placetype": "venue"
  },
  "geometry": {"coordinates":[-71.152083,42.444179],"type":"Point"}
}
