{
  "type": "Feature",
  "properties": {
    "addr:full": "6 Jones Ave Pittsfield MA 01201",
    "addr:housenumber": "6",
    "addr:postcode": "01201",
    "addr:street": "Jones Ave",
    "iso:country": "US",
    "sg:address": "6 Jones Ave",
    "sg:city": "Pittsfield",
    "sg:classifiers": [
      {
        "category": "Building \u0026 Trades",
        "subcategory": "Electrical",
        "type": "Services"
      }
    ],
    "sg:phone": "+1 413 443 3348",
    "sg:postcode": "01201",
    "sg:province": "MA",
    "sg:tags": [
      "electric",
      "contractor"
    ],
    "wof:name": "Willliam R Stodden Elec Contra",
    "wof:placetype": "venue"
  },
  "geometry": {"coordinates":[-73.309214,42.434956],"type":"Point"}
}
