{
  "type": "Feature",
  "properties": {
    "addr:full": "3 Metacomet Way Southborough MA 01776",
    "addr:housenumber": "3",
    "addr:postcode": "01776",
    "addr:street": "Metacomet Way",
    "iso:country": "US",
    "sg:address": "3 Metacomet Way",
    "sg:city": "Southborough",
    "sg:classifiers": [
      {
        "category": "Building \u0026 Trades",
        "subcategory": "Construction",
        "type": "Services"
      }
    ],
    "sg:phone": "+1 508 485 4470",
    "sg:postcode": "01776",
    "sg:province": "MA",
    "sg:tags": [
      "contractor"
    ],
    "wof:name": "Construction Rosewood",
    "wof:placetype": "venue"
  },
  "geometry": {"coordinates":[-71.40696,42.365469],"type":"Point"}
}
