{
  "type": "Feature",
  "properties": {
    "addr:full":"32 Linden St New Bedford MA 02740",
    "addr:housenumber":"32",
    "addr:postcode":"02740",
    "addr:street":"Linden St",
    "iso:country":"US",
    "sg:address":"32 Linden St",
    "sg:city":"New Bedford",
    "sg:classifiers":[
        {
            "category":"Retail",
            "subcategory":"Auto Repair",
            "type":"Services"
        }
    ],
    "sg:phone":"+1 508 994 3448",
    "sg:postcode":"02740",
    "sg:province":"MA",
    "sg:tags":[
        "truck",
        "general"
    ],
    "wof:name":"J G Truck & Trailer Repair",
    "wof:placetype":"venue"
},
  "geometry": {"coordinates":[-70.930488,41.649936],"type":"Point"}
}