{
  "type": "Feature",
  "properties": {
    "addr:full":"259 Linebrook Rd Ipswich MA 01938",
    "addr:housenumber":"259",
    "addr:postcode":"01938",
    "addr:street":"Linebrook Rd",
    "iso:country":"US",
    "sg:address":"259 Linebrook Rd",
    "sg:city":"Ipswich",
    "sg:classifiers":[
        {
            "category":"Restaurant",
            "type":"Food & Drink"
        },
        {
            "category":"Wholesale",
            "subcategory":"Fruits & Vegetables",
            "type":"Manufacturing & Wholesale Goods"
        }
    ],
    "sg:phone":"+1 978 356 0430",
    "sg:postcode":"01938",
    "sg:province":"MA",
    "sg:tags":[
        "veggie"
    ],
    "sg:website":"www.marinifarm.com",
    "wof:name":"Marini's Farm Stand",
    "wof:placetype":"venue"
},
  "geometry": {"coordinates":[-70.893649,42.68548],"type":"Point"}
}