{
  "type": "Feature",
  "properties": {
    "addr:full":"399 W Broadway South Boston MA 02127",
    "addr:housenumber":"399",
    "addr:postcode":"02127",
    "addr:street":"W Broadway",
    "iso:country":"US",
    "sg:address":"399 W Broadway",
    "sg:city":"South Boston",
    "sg:classifiers":[
        {
            "category":"Food & Beverages",
            "subcategory":"Liquor & Beverages",
            "type":"Retail Goods"
        }
    ],
    "sg:phone":"+1 617 464 3100",
    "sg:postcode":"02127",
    "sg:province":"MA",
    "sg:tags":[
        "beer",
        "spirit",
        "wine"
    ],
    "wof:name":"Soughie Liquor Store",
    "wof:placetype":"venue"
},
  "geometry": {"coordinates":[-71.04843,42.337078],"type":"Point"}
}