{
  "type": "Feature",
  "properties": {
    "iso:country":"US",
    "sg:address":"345 Carver Rd",
    "sg:city":"Plymouth",
    "sg:classifiers":[
        {
            "category":"Shopping",
            "subcategory":"Stationery & Office Supplies",
            "type":"Retail Goods"
        }
    ],
    "sg:phone":"+1 508 747 5004",
    "sg:postcode":"02360",
    "sg:province":"MA",
    "sg:tags":[
        "equipment"
    ],
    "sg:website":"www.wristwriter.com",
    "wof:name":"Wrist Writer",
    "wof:placetype":"venue"
},
  "geometry": {"coordinates":[-70.748402,41.927429],"type":"Point"}
}