{
  "type": "Feature",
  "properties": {
    "addr:full": "345 Carver Rd Plymouth MA 02360",
    "addr:housenumber": "345",
    "addr:postcode": "02360",
    "addr:street": "Carver Rd",
    "iso:country": "US",
    "sg:address": "345 Carver Rd",
    "sg:city": "Plymouth",
    "sg:classifiers": [
      {
        "category": "Shopping",
        "subcategory": "Stationery \u0026 Office Supplies",
        "type": "Retail Goods"
      }
    ],
    "sg:phone": "+1 508 747 5004",
    "sg:postcode": "02360",
    "sg:province": "MA",
    "sg:tags": [
      "equipment"
    ],
    "sg:website": "www.wristwriter.com",
    "wof:name": "Wrist Writer",
    "wof:placetype": "venue"
  },
  "geometry": {"coordinates":[-70.748402,41.927429],"type":"Point"}
}
