{
  "type": "Feature",
  "properties": {
    "addr:full":"40 Ronaele Rd Medford MA 02155",
    "addr:housenumber":"40",
    "addr:postcode":"02155",
    "addr:street":"Ronaele Rd",
    "iso:country":"US",
    "sg:address":"40 Ronaele Rd",
    "sg:city":"Medford",
    "sg:classifiers":[
        {
            "category":"Building & Trades",
            "subcategory":"Electrical",
            "type":"Services"
        }
    ],
    "sg:phone":"+1 781 391 7822",
    "sg:postcode":"02155",
    "sg:province":"MA",
    "sg:tags":[
        "electric",
        "contractor"
    ],
    "wof:name":"Hensen Electrical & Comms Svc",
    "wof:placetype":"venue"
},
  "geometry": {"coordinates":[-71.130303,42.43147],"type":"Point"}
}