{
  "type": "Feature",
  "properties": {
    "iso:country":"US",
    "sg:address":"3229 Cranberry Hwy",
    "sg:city":"Buzzards Bay",
    "sg:classifiers":[
        {
            "category":"Banks & Credit Unions",
            "subcategory":"Bank",
            "type":"Services"
        }
    ],
    "sg:phone":"+1 508 759 1919",
    "sg:postcode":"02532",
    "sg:province":"MA",
    "sg:tags":[
        "loan",
        "real estate"
    ],
    "sg:website":"www.30yearfixedrate.com",
    "wof:name":"Arrow Mortgage Corp",
    "wof:placetype":"venue"
},
  "geometry": {"coordinates":[-70.624062,41.748231],"type":"Point"}
}