{
  "type": "Feature",
  "properties": {
    "iso:country":"US",
    "sg:address":"59 Worcester Ave",
    "sg:city":"Springfield",
    "sg:classifiers":[
        {
            "category":"Building & Trades",
            "subcategory":"Landscaping Services",
            "type":"Services"
        }
    ],
    "sg:phone":"+1 413 736 2306",
    "sg:postcode":"01107",
    "sg:province":"MA",
    "sg:tags":[
        "lawn",
        "designer",
        "consultant",
        "contractor",
        "maintenance",
        "landscape"
    ],
    "wof:name":"Best Landscaping",
    "wof:placetype":"venue"
},
  "geometry": {"coordinates":[-72.614559,42.121966],"type":"Point"}
}