{
  "type": "Feature",
  "properties": {
    "addr:full": "33 Railroad Ave Duxbury MA 02332",
    "addr:housenumber": "33",
    "addr:postcode": "02332",
    "addr:street": "Railroad Ave",
    "iso:country": "US",
    "sg:address": "33 Railroad Ave",
    "sg:city": "Duxbury",
    "sg:classifiers": [
      {
        "category": "Organizations",
        "subcategory": "Non-profit Organization",
        "type": "Services"
      }
    ],
    "sg:phone": "+1 781 934 8905",
    "sg:postcode": "02332",
    "sg:province": "MA",
    "wof:name": "National Audubon Society",
    "wof:placetype": "venue"
  },
  "geometry": {"coordinates":[-70.685897,42.047031],"type":"Point"}
}
