{
  "type": "Feature",
  "properties": {
    "addr:full": "64 Vale St Fall River MA 02724",
    "addr:housenumber": "64",
    "addr:postcode": "02724",
    "addr:street": "Vale St",
    "iso:country": "US",
    "sg:address": "64 Vale St",
    "sg:city": "Fall River",
    "sg:classifiers": [
      {
        "category": "Food \u0026 Beverages",
        "subcategory": "Bakery",
        "type": "Retail Goods"
      }
    ],
    "sg:phone": "+1 508 672 9205",
    "sg:postcode": "02724",
    "sg:province": "MA",
    "sg:tags": [
      "doughnut"
    ],
    "wof:name": "Dunkin Donuts",
    "wof:placetype": "venue"
  },
  "geometry": {"coordinates":[-71.164457,41.687699],"type":"Point"}
}
