{
  "type": "Feature",
  "properties": {
    "iso:country":"US",
    "sg:address":"85 E Concord St",
    "sg:city":"Boston",
    "sg:classifiers":[
        {
            "category":"Professional",
            "subcategory":"Business Services",
            "type":"Services"
        }
    ],
    "sg:phone":"+1 617 414 4946",
    "sg:postcode":"02118",
    "sg:province":"MA",
    "sg:tags":[
        "medical",
        "administration"
    ],
    "wof:name":"Nursing Administration",
    "wof:placetype":"venue"
},
  "geometry": {"coordinates":[-71.07229599999999,42.335706],"type":"Point"}
}