{
  "type": "Feature",
  "properties": {
    "addr:full": "409 E Main St Southbridge MA 01550",
    "addr:housenumber": "409",
    "addr:postcode": "01550",
    "addr:street": "E Main St",
    "iso:country": "US",
    "sg:address": "409 E Main St",
    "sg:city": "Southbridge",
    "sg:classifiers": [
      {
        "category": "Personal",
        "subcategory": "Beauty Salon",
        "type": "Services"
      }
    ],
    "sg:phone": "+1 508 764 8155",
    "sg:postcode": "01550",
    "sg:province": "MA",
    "wof:name": "Salon East",
    "wof:placetype": "venue"
  },
  "geometry": {"coordinates":[-72.015042,42.071138],"type":"Point"}
}
