{
  "type": "Feature",
  "properties": {
    "addr:full": "26 Water St Williamstown MA 01267",
    "addr:housenumber": "26",
    "addr:postcode": "01267",
    "addr:street": "Water St",
    "iso:country": "US",
    "sg:address": "26 Water St",
    "sg:city": "Williamstown",
    "sg:classifiers": [
      {
        "category": "Shopping",
        "subcategory": "Books",
        "type": "Retail Goods"
      }
    ],
    "sg:phone": "+1 413 458 8071",
    "sg:postcode": "01267",
    "sg:province": "MA",
    "sg:tags": [
      "dealer"
    ],
    "wof:name": "Water Street Books",
    "wof:placetype": "venue"
  },
  "geometry": {"coordinates":[-73.199739,42.710509],"type":"Point"}
}
