{
  "type": "Feature",
  "properties": {
    "addr:full":"190 Main St Leicester MA 01524",
    "addr:housenumber":"190",
    "addr:postcode":"01524",
    "addr:street":"Main St",
    "iso:country":"US",
    "sg:address":"190 Main St",
    "sg:city":"Leicester",
    "sg:classifiers":[
        {
            "category":"Fast Food",
            "type":"Food & Drink"
        },
        {
            "category":"Restaurant",
            "type":"Food & Drink"
        }
    ],
    "sg:phone":"+1 508 892 3925",
    "sg:postcode":"01524",
    "sg:province":"MA",
    "sg:tags":[
        "traditional",
        "burger",
        "american",
        "brunch",
        "breakfast"
    ],
    "sg:website":"ellersrestaurant.com/",
    "wof:name":"Eller's Restaurant",
    "wof:placetype":"venue"
},
  "geometry": {"coordinates":[-71.899835,42.245301],"type":"Point"}
}