{
  "type": "Feature",
  "properties": {
    "addr:full":"33 Barbara Rd Sudbury MA 01776",
    "addr:housenumber":"33",
    "addr:postcode":"01776",
    "addr:street":"Barbara Rd",
    "iso:country":"US",
    "sg:address":"33 Barbara Rd",
    "sg:city":"Sudbury",
    "sg:classifiers":[
        {
            "category":"Bakery",
            "type":"Food & Drink"
        }
    ],
    "sg:phone":"+1 978 443 8007",
    "sg:postcode":"01776",
    "sg:province":"MA",
    "wof:name":"Pauline's Bakery Inc",
    "wof:placetype":"venue"
},
  "geometry": {"coordinates":[-71.459684,42.390699],"type":"Point"}
}