{
  "type": "Feature",
  "properties": {
    "addr:full":"45 Tyler Ave Medford MA 02155",
    "addr:housenumber":"45",
    "addr:postcode":"02155",
    "addr:street":"Tyler Ave",
    "iso:country":"US",
    "sg:address":"45 Tyler Ave",
    "sg:city":"Medford",
    "sg:classifiers":[
        {
            "category":"Home & Garden",
            "subcategory":"Building Materials",
            "type":"Retail Goods"
        }
    ],
    "sg:phone":"+1 781 391 6357",
    "sg:postcode":"02155",
    "sg:province":"MA",
    "sg:tags":[
        "windows"
    ],
    "wof:name":"Medford Vinyl",
    "wof:placetype":"venue"
},
  "geometry": {"coordinates":[-71.13644499999999,42.423468],"type":"Point"}
}