{
  "type": "Feature",
  "properties": {
    "addr:full":"532 Pond St South Weymouth MA 02190",
    "addr:housenumber":"532",
    "addr:postcode":"02190",
    "addr:street":"Pond St",
    "iso:country":"US",
    "sg:address":"532 Pond St",
    "sg:city":"South Weymouth",
    "sg:classifiers":[
        {
            "category":"Restaurant",
            "type":"Food & Drink"
        }
    ],
    "sg:menulink":"http://www.allmenus.com/ma/weymouth/69957-papa-ginos/menu/",
    "sg:phone":"+1 781 331 2266",
    "sg:postcode":"02190",
    "sg:province":"MA",
    "sg:tags":[
        "american",
        "pizza"
    ],
    "wof:name":"Papa Gino's",
    "wof:placetype":"venue"
},
  "geometry": {"coordinates":[-70.95389900000001,42.152202],"type":"Point"}
}