{
  "type": "Feature",
  "properties": {
    "iso:country":"US",
    "sg:address":"22 Castle St",
    "sg:city":"Worcester",
    "sg:classifiers":[
        {
            "category":"Real Estate",
            "subcategory":"Real Estate Operator",
            "type":"Services"
        }
    ],
    "sg:phone":"+1   ",
    "sg:postcode":"01610",
    "sg:province":"MA",
    "sg:tags":[
        "apartment",
        "complex"
    ],
    "wof:name":"Emma B Gates House",
    "wof:placetype":"venue"
},
  "geometry": {"coordinates":[-71.813338,42.257911],"type":"Point"}
}