{
  "type": "Feature",
  "properties": {
    "addr:full": "297 Torrey St Brockton MA 02301",
    "addr:housenumber": "297",
    "addr:postcode": "02301",
    "addr:street": "Torrey St",
    "iso:country": "US",
    "sg:address": "297 Torrey St",
    "sg:city": "Brockton",
    "sg:classifiers": [
      {
        "category": "Freight",
        "type": "Transportation"
      }
    ],
    "sg:phone": "+1 508 586 4685",
    "sg:postcode": "02301",
    "sg:province": "MA",
    "sg:tags": [
      "mover"
    ],
    "wof:name": "Triple M Movers \u0026 Storage",
    "wof:placetype": "venue"
  },
  "geometry": {"coordinates":[-71.05676,42.072082],"type":"Point"}
}
