{
  "type": "Feature",
  "properties": {
    "addr:full":"603 Riverdale St West Springfield MA 01089",
    "addr:housenumber":"603",
    "addr:postcode":"01089",
    "addr:street":"Riverdale St",
    "iso:country":"US",
    "sg:address":"603 Riverdale St",
    "sg:city":"West Springfield",
    "sg:classifiers":[
        {
            "category":"Autos & Motor Vehicles",
            "subcategory":"Automobile Sales",
            "type":"Retail Goods"
        }
    ],
    "sg:phone":"+1 413 733 5102",
    "sg:postcode":"01089",
    "sg:province":"MA",
    "sg:tags":[
        "car",
        "dealer"
    ],
    "sg:website":"www.lewbarimports.com",
    "wof:name":"Lewbar Imports Inc",
    "wof:placetype":"venue"
},
  "geometry": {"coordinates":[-72.625874,42.12475],"type":"Point"}
}