{
  "type": "Feature",
  "properties": {
    "addr:full": "201 N Common St Lynn MA 01905",
    "addr:housenumber": "201",
    "addr:postcode": "01905",
    "addr:street": "N Common St",
    "iso:country": "US",
    "sg:address": "201 N Common St",
    "sg:city": "Lynn",
    "sg:classifiers": [
      {
        "category": "Cinema",
        "subcategory": "Movie Rental",
        "type": "Entertainment"
      }
    ],
    "sg:phone": "+1 781 595 5300",
    "sg:postcode": "01905",
    "sg:province": "MA",
    "sg:tags": [
      "leasing",
      "video",
      "disc",
      "tape"
    ],
    "wof:name": "Video Craze",
    "wof:placetype": "venue"
  },
  "geometry": {"coordinates":[-70.964027,42.462897],"type":"Point"}
}
