{
  "type": "Feature",
  "properties": {
    "addr:full":"32 Wood St Middleboro MA 02346",
    "addr:housenumber":"32",
    "addr:postcode":"02346",
    "addr:street":"Wood St",
    "iso:country":"US",
    "sg:address":"32 Wood St",
    "sg:city":"Middleboro",
    "sg:classifiers":[
        {
            "category":"Building & Trades",
            "subcategory":"Electrical",
            "type":"Services"
        }
    ],
    "sg:phone":"+1   ",
    "sg:postcode":"02346",
    "sg:province":"MA",
    "sg:tags":[
        "electrical",
        "contractor"
    ],
    "wof:name":"Freitas & Sons Elec Inc",
    "wof:placetype":"venue"
},
  "geometry": {"coordinates":[-70.905794,41.856939],"type":"Point"}
}