{
  "type": "Feature",
  "properties": {
    "addr:full":"1847 Broadway St Raynham MA 02767",
    "addr:housenumber":"1847",
    "addr:postcode":"02767",
    "addr:street":"Broadway St",
    "iso:country":"US",
    "sg:address":"1847 Broadway St",
    "sg:city":"Raynham",
    "sg:classifiers":[
        {
            "category":"Manufacturing",
            "subcategory":"Furniture",
            "type":"Manufacturing & Wholesale Goods"
        },
        {
            "category":"Building & Trades",
            "subcategory":"Construction",
            "type":"Services"
        }
    ],
    "sg:phone":"+1 508 824 0439",
    "sg:postcode":"02767",
    "sg:province":"MA",
    "sg:tags":[
        "wooden",
        "shop",
        "cabinet",
        "woodworker"
    ],
    "wof:name":"Gerald Lagace Woodworking",
    "wof:placetype":"venue"
},
  "geometry": {"coordinates":[-71.069586,41.980629],"type":"Point"}
}