{
  "type": "Feature",
  "properties": {
    "iso:country":"US",
    "sg:address":"548 W Roxbury Pkwy",
    "sg:city":"West Roxbury",
    "sg:classifiers":[
        {
            "category":"Building & Trades",
            "subcategory":"Construction",
            "type":"Services"
        }
    ],
    "sg:phone":"+1 617 469 2899",
    "sg:postcode":"02132",
    "sg:province":"MA",
    "sg:tags":[
        "contractor"
    ],
    "wof:name":"Bonomo Tile Inc",
    "wof:placetype":"venue"
},
  "geometry": {"coordinates":[-71.14767500000001,42.286605],"type":"Point"}
}