{
  "type": "Feature",
  "properties": {
    "addr:full": "548 W Roxbury Pkwy West Roxbury MA 02132",
    "addr:housenumber": "548",
    "addr:postcode": "02132",
    "addr:street": "W Roxbury Pkwy",
    "iso:country": "US",
    "sg:address": "548 W Roxbury Pkwy",
    "sg:city": "West Roxbury",
    "sg:classifiers": [
      {
        "category": "Building \u0026 Trades",
        "subcategory": "Construction",
        "type": "Services"
      }
    ],
    "sg:phone": "+1 617 469 2899",
    "sg:postcode": "02132",
    "sg:province": "MA",
    "sg:tags": [
      "contractor"
    ],
    "wof:name": "Bonomo Tile Inc",
    "wof:placetype": "venue"
  },
  "geometry": {"coordinates":[-71.147675,42.286605],"type":"Point"}
}
