{
  "type": "Feature",
  "properties": {
    "iso:country":"US",
    "sg:address":"56 Hopedale St",
    "sg:city":"Hopedale",
    "sg:classifiers":[
        {
            "category":"Personal",
            "subcategory":"Beauty Salon",
            "type":"Services"
        }
    ],
    "sg:phone":"+1 508 473 5775",
    "sg:postcode":"01747",
    "sg:province":"MA",
    "wof:name":"Community Cuts",
    "wof:placetype":"venue"
},
  "geometry": {"coordinates":[-71.540177,42.129498],"type":"Point"}
}