{
  "type": "Feature",
  "properties": {
    "iso:country":"US",
    "sg:address":"Museum of Fine Arts, West Wing 465 Huntington Ave",
    "sg:city":"Boston",
    "sg:classifiers":[
        {
            "category":"Arts & Performance",
            "subcategory":"Arts Center",
            "type":"Entertainment"
        }
    ],
    "sg:phone":"+1 617 369 3300",
    "sg:postcode":"02115",
    "sg:province":"MA",
    "sg:tags":[
        "performing"
    ],
    "sg:website":"www.mfa.org",
    "wof:name":"Remis Auditorium",
    "wof:placetype":"venue"
},
  "geometry": {"coordinates":[-71.09404000000001,42.338413],"type":"Point"}
}