{
  "type": "Feature",
  "properties": {
    "iso:country":"US",
    "sg:address":"78 Cherry St",
    "sg:city":"Hudson",
    "sg:classifiers":[
        {
            "category":"Manufacturing",
            "subcategory":"Tools & Machinery",
            "type":"Manufacturing & Wholesale Goods"
        }
    ],
    "sg:phone":"+1 978 562 4775",
    "sg:postcode":"01749",
    "sg:province":"MA",
    "sg:tags":[
        "machine",
        "shop"
    ],
    "wof:name":"J T Precision Machining",
    "wof:placetype":"venue"
},
  "geometry": {"coordinates":[-71.559528,42.391389],"type":"Point"}
}