{
  "type": "Feature",
  "properties": {
    "addr:full": "78 Cherry St Hudson MA 01749",
    "addr:housenumber": "78",
    "addr:postcode": "01749",
    "addr:street": "Cherry St",
    "iso:country": "US",
    "sg:address": "78 Cherry St",
    "sg:city": "Hudson",
    "sg:classifiers": [
      {
        "category": "Manufacturing",
        "subcategory": "Tools \u0026 Machinery",
        "type": "Manufacturing \u0026 Wholesale Goods"
      }
    ],
    "sg:phone": "+1 978 562 4775",
    "sg:postcode": "01749",
    "sg:province": "MA",
    "sg:tags": [
      "machine",
      "shop"
    ],
    "wof:name": "J T Precision Machining",
    "wof:placetype": "venue"
  },
  "geometry": {"coordinates":[-71.559528,42.391389],"type":"Point"}
}
