{
  "type": "Feature",
  "properties": {
    "addr:full":"68 Cushing St Stoughton MA 02072",
    "addr:housenumber":"68",
    "addr:postcode":"02072",
    "addr:street":"Cushing St",
    "iso:country":"US",
    "sg:address":"68 Cushing St",
    "sg:city":"Stoughton",
    "sg:classifiers":[
        {
            "category":"Retail",
            "subcategory":"Auto Repair",
            "type":"Services"
        }
    ],
    "sg:phone":"+1 781 297 0008",
    "sg:postcode":"02072",
    "sg:province":"MA",
    "wof:name":"Randolph Associates",
    "wof:placetype":"venue"
},
  "geometry": {"coordinates":[-71.10749800000001,42.126999],"type":"Point"}
}