{
  "type": "Feature",
  "properties": {
    "addr:full": "25 S Point Dr Dorchester MA 02125",
    "addr:housenumber": "25",
    "addr:postcode": "02125",
    "addr:street": "S Point Dr",
    "iso:country": "US",
    "sg:address": "25 S Point Dr",
    "sg:city": "Dorchester",
    "sg:classifiers": [
      {
        "category": "Real Estate",
        "subcategory": "Real Estate Operator",
        "type": "Services"
      }
    ],
    "sg:phone": "+1 617 822 3880",
    "sg:postcode": "02125",
    "sg:province": "MA",
    "sg:tags": [
      "apartment"
    ],
    "wof:name": "Harbor Point Apartments",
    "wof:placetype": "venue"
  },
  "geometry": {"coordinates":[-71.040205,42.318205],"type":"Point"}
}
