{
  "type": "Feature",
  "properties": {
    "iso:country":"US",
    "sg:address":"82 Pembroke St",
    "sg:city":"Boston",
    "sg:classifiers":[
        {
            "category":"Museum",
            "type":"Entertainment"
        }
    ],
    "sg:phone":"+1 617 542 7464",
    "sg:postcode":"02118",
    "sg:province":"MA",
    "sg:tags":[
        "organization",
        "arts",
        "information"
    ],
    "wof:name":"Boston Gay Mens Chorus",
    "wof:placetype":"venue"
},
  "geometry": {"coordinates":[-71.077467,42.343082],"type":"Point"}
}