{
  "type": "Feature",
  "properties": {
    "addr:full":"186 South St Boston MA 02111",
    "addr:housenumber":"186",
    "addr:postcode":"02111",
    "addr:street":"South St",
    "iso:country":"US",
    "sg:address":"186 South St",
    "sg:city":"Boston",
    "sg:classifiers":[
        {
            "category":"Professional",
            "subcategory":"Computer Services",
            "type":"Services"
        }
    ],
    "sg:phone":"+1 617 357 6888",
    "sg:postcode":"02111",
    "sg:province":"MA",
    "sg:tags":[
        "repair"
    ],
    "wof:name":"Firstadvantage",
    "wof:placetype":"venue"
},
  "geometry": {"coordinates":[-71.057355,42.350254],"type":"Point"}
}