{
  "type": "Feature",
  "properties": {
    "addr:full": "38 Yorkshire Ter Shrewsbury MA 01545",
    "addr:housenumber": "38",
    "addr:postcode": "01545",
    "addr:street": "Yorkshire Ter",
    "iso:country": "US",
    "sg:address": "38 Yorkshire Ter",
    "sg:city": "Shrewsbury",
    "sg:classifiers": [
      {
        "category": "Building \u0026 Trades",
        "subcategory": "Cleaning \u0026 Sanitation",
        "type": "Services"
      }
    ],
    "sg:phone": "+1 508 845 1178",
    "sg:postcode": "01545",
    "sg:province": "MA",
    "sg:tags": [
      "janitor"
    ],
    "wof:name": "Elizabeth Cleaning Svc",
    "wof:placetype": "venue"
  },
  "geometry": {"coordinates":[-71.697944,42.276698],"type":"Point"}
}
