{
  "type": "Feature",
  "properties": {
    "iso:country":"US",
    "sg:address":"38 Yorkshire Ter",
    "sg:city":"Shrewsbury",
    "sg:classifiers":[
        {
            "category":"Building & Trades",
            "subcategory":"Cleaning & Sanitation",
            "type":"Services"
        }
    ],
    "sg:phone":"+1 508 845 1178",
    "sg:postcode":"01545",
    "sg:province":"MA",
    "sg:tags":[
        "janitor"
    ],
    "wof:name":"Elizabeth Cleaning Svc",
    "wof:placetype":"venue"
},
  "geometry": {"coordinates":[-71.69794400000001,42.276698],"type":"Point"}
}