{
  "type": "Feature",
  "properties": {
    "addr:full":"35 South St Barre MA 01005",
    "addr:housenumber":"35",
    "addr:postcode":"01005",
    "addr:street":"South St",
    "iso:country":"US",
    "sg:address":"35 South St",
    "sg:city":"Barre",
    "sg:classifiers":[
        {
            "category":"Professional",
            "subcategory":"Management & Consulting",
            "type":"Services"
        }
    ],
    "sg:phone":"+1   ",
    "sg:postcode":"01005",
    "sg:province":"MA",
    "wof:name":"Berry Integrated Center",
    "wof:placetype":"venue"
},
  "geometry": {"coordinates":[-72.10486299999999,42.421813],"type":"Point"}
}