{
  "type": "Feature",
  "properties": {
    "iso:country":"US",
    "sg:address":"87 Broadway",
    "sg:city":"Everett",
    "sg:classifiers":[
        {
            "category":"Retail",
            "subcategory":"Auto Repair",
            "type":"Services"
        }
    ],
    "sg:phone":"+1 617 389 3030",
    "sg:postcode":"02149",
    "sg:province":"MA",
    "sg:tags":[
        "body",
        "automobile",
        "painting"
    ],
    "wof:name":"Malden Auto Body",
    "wof:placetype":"venue"
},
  "geometry": {"coordinates":[-71.06394899999999,42.39784],"type":"Point"}
}