{
  "type": "Feature",
  "properties": {
    "iso:country":"US",
    "sg:address":"623 Essex St",
    "sg:city":"Lawrence",
    "sg:classifiers":[
        {
            "category":"Retail",
            "subcategory":"Car Wash",
            "type":"Services"
        }
    ],
    "sg:phone":"+1 978 685 2025",
    "sg:postcode":"01841",
    "sg:province":"MA",
    "sg:tags":[
        "automobile",
        "detail",
        "clean"
    ],
    "wof:name":"Abba Detail & Alarm",
    "wof:placetype":"venue"
},
  "geometry": {"coordinates":[-71.168938,42.70445],"type":"Point"}
}