{
  "type": "Feature",
  "properties": {
    "addr:full": "623 Essex St Lawrence MA 01841",
    "addr:housenumber": "623",
    "addr:postcode": "01841",
    "addr:street": "Essex St",
    "iso:country": "US",
    "sg:address": "623 Essex St",
    "sg:city": "Lawrence",
    "sg:classifiers": [
      {
        "category": "Retail",
        "subcategory": "Car Wash",
        "type": "Services"
      }
    ],
    "sg:phone": "+1 978 685 2025",
    "sg:postcode": "01841",
    "sg:province": "MA",
    "sg:tags": [
      "automobile",
      "detail",
      "clean"
    ],
    "wof:name": "Abba Detail \u0026 Alarm",
    "wof:placetype": "venue"
  },
  "geometry": {"coordinates":[-71.168938,42.70445],"type":"Point"}
}
