{
  "type": "Feature",
  "properties": {
    "iso:country":"US",
    "sg:address":"51 Park Ave",
    "sg:city":"Webster",
    "sg:classifiers":[
        {
            "category":"Building & Trades",
            "subcategory":"Plumbing",
            "type":"Services"
        }
    ],
    "sg:phone":"+1 508 520 2939",
    "sg:postcode":"01570",
    "sg:province":"MA",
    "sg:tags":[
        "plumber"
    ],
    "wof:name":"Steve Brown Plumbing & Heating LLc",
    "wof:placetype":"venue"
},
  "geometry": {"coordinates":[-71.866916,42.054179],"type":"Point"}
}