{
  "type": "Feature",
  "properties": {
    "addr:full": "390 Main St Worcester MA 01608",
    "addr:housenumber": "390",
    "addr:postcode": "01608",
    "addr:street": "Main St",
    "iso:country": "US",
    "sg:address": "390 Main St",
    "sg:city": "Worcester",
    "sg:classifiers": [
      {
        "category": "Professional",
        "subcategory": "Lawyer \u0026 Legal Services",
        "type": "Services"
      }
    ],
    "sg:phone": "+1 508 795 7550",
    "sg:postcode": "01608",
    "sg:province": "MA",
    "sg:tags": [
      "attorney"
    ],
    "wof:name": "Robert J Hennigan Law Office",
    "wof:placetype": "venue"
  },
  "geometry": {"coordinates":[-71.801693,42.264819],"type":"Point"}
}
