{
  "type": "Feature",
  "properties": {
    "addr:full":"297 Shad Hole Rd Dennis Port MA 02639",
    "addr:housenumber":"297",
    "addr:postcode":"02639",
    "addr:street":"Shad Hole Rd",
    "iso:country":"US",
    "sg:address":"297 Shad Hole Rd",
    "sg:city":"Dennis Port",
    "sg:classifiers":[
        {
            "category":"Travel",
            "subcategory":"Hotels & Motels",
            "type":"Entertainment"
        }
    ],
    "sg:phone":"+1 508 398 5921",
    "sg:postcode":"02639",
    "sg:province":"MA",
    "wof:name":"Old Landing Inn",
    "wof:placetype":"venue"
},
  "geometry": {"coordinates":[-70.133555,41.653447],"type":"Point"}
}