{
  "type": "Feature",
  "properties": {
    "iso:country":"US",
    "sg:address":"112 Captain Eames Cir",
    "sg:city":"Ashland",
    "sg:classifiers":[
        {
            "category":"Building & Trades",
            "subcategory":"Electrical",
            "type":"Services"
        }
    ],
    "sg:phone":"+1 508 881 7614",
    "sg:postcode":"01721",
    "sg:province":"MA",
    "sg:tags":[
        "electrician"
    ],
    "wof:name":"Courtade Electric",
    "wof:placetype":"venue"
},
  "geometry": {"coordinates":[-71.436632,42.247911],"type":"Point"}
}