{
  "type": "Feature",
  "properties": {
    "iso:country":"US",
    "sg:address":"9 Bussey St",
    "sg:city":"Dedham",
    "sg:classifiers":[
        {
            "category":"Manufacturing",
            "subcategory":"Printing",
            "type":"Manufacturing & Wholesale Goods"
        }
    ],
    "sg:phone":"+1 781 329 1815",
    "sg:postcode":"02026",
    "sg:province":"MA",
    "sg:tags":[
        "commercial"
    ],
    "wof:name":"Grant's Printing Svc",
    "wof:placetype":"venue"
},
  "geometry": {"coordinates":[-71.15597099999999,42.256232],"type":"Point"}
}