{
  "type": "Feature",
  "properties": {
    "addr:full": "149 Exchange St Chicopee MA 01013",
    "addr:housenumber": "149",
    "addr:postcode": "01013",
    "addr:street": "Exchange St",
    "iso:country": "US",
    "sg:address": "149 Exchange St",
    "sg:city": "Chicopee",
    "sg:classifiers": [
      {
        "category": "Sports \u0026 Exercise",
        "subcategory": "Sports Center",
        "type": "Entertainment"
      }
    ],
    "sg:phone": "+1 413 592 9293",
    "sg:postcode": "01013",
    "sg:province": "MA",
    "wof:name": "Chicopee Portuguese American Club Incorporated",
    "wof:placetype": "venue"
  },
  "geometry": {"coordinates":[-72.610779,42.147339],"type":"Point"}
}
