{
  "type": "Feature",
  "properties": {
    "addr:full": "1 Centre St Wakefield MA 01880",
    "addr:housenumber": "1",
    "addr:postcode": "01880",
    "addr:street": "Centre St",
    "iso:country": "US",
    "sg:address": "1 Centre St",
    "sg:city": "Wakefield",
    "sg:classifiers": [
      {
        "category": "Building \u0026 Trades",
        "subcategory": "Electrical",
        "type": "Services"
      }
    ],
    "sg:phone": "+1 781 246 3110",
    "sg:postcode": "01880",
    "sg:province": "MA",
    "sg:tags": [
      "electric",
      "contractor"
    ],
    "wof:name": "Haggerty Electrical Svc Inc",
    "wof:placetype": "venue"
  },
  "geometry": {"coordinates":[-71.070847,42.50401],"type":"Point"}
}
