{
  "type": "Feature",
  "properties": {
    "addr:full":"66 Providence St Mendon MA 01756",
    "addr:housenumber":"66",
    "addr:postcode":"01756",
    "addr:street":"Providence St",
    "iso:country":"US",
    "sg:address":"66 Providence St",
    "sg:city":"Mendon",
    "sg:classifiers":[
        {
            "category":"Building & Trades",
            "subcategory":"Construction",
            "type":"Services"
        }
    ],
    "sg:phone":"+1 508 473 0737",
    "sg:postcode":"01756",
    "sg:province":"MA",
    "sg:tags":[
        "marking",
        "maintenance",
        "parking"
    ],
    "wof:name":"Mendon Highway Dept",
    "wof:placetype":"venue"
},
  "geometry": {"coordinates":[-71.53861499999999,42.095966],"type":"Point"}
}