{
  "type": "Feature",
  "properties": {
    "addr:full":"672 Millville Rd Uxbridge MA 01569",
    "addr:housenumber":"672",
    "addr:postcode":"01569",
    "addr:street":"Millville Rd",
    "iso:country":"US",
    "sg:address":"672 Millville Rd",
    "sg:city":"Uxbridge",
    "sg:classifiers":[
        {
            "category":"Building & Trades",
            "subcategory":"Construction",
            "type":"Services"
        }
    ],
    "sg:phone":"+1 508 234 9340",
    "sg:postcode":"01569",
    "sg:province":"MA",
    "sg:tags":[
        "excavating",
        "contractor"
    ],
    "wof:name":"D J Salmon Lawn & Landscape",
    "wof:placetype":"venue"
},
  "geometry": {"coordinates":[-71.59927999999999,42.036315],"type":"Point"}
}