{
  "type": "Feature",
  "properties": {
    "iso:country":"US",
    "sg:address":"436 Marrett Rd",
    "sg:city":"Lexington",
    "sg:classifiers":[
        {
            "category":"Autos & Motor Vehicles",
            "subcategory":"Auto Supplies",
            "type":"Retail Goods"
        },
        {
            "category":"Retail",
            "subcategory":"Auto Repair",
            "type":"Services"
        }
    ],
    "sg:phone":"+1 781 676 7700",
    "sg:postcode":"02421",
    "sg:province":"MA",
    "sg:tags":[
        "tire"
    ],
    "sg:website":"AutoEngineering.com",
    "wof:name":"Auto Engineering of Lexington",
    "wof:placetype":"venue"
},
  "geometry": {"coordinates":[-71.24291599999999,42.434156],"type":"Point"}
}