{
  "type": "Feature",
  "properties": {
    "addr:full": "15 Carleton Cir Belmont MA 02478",
    "addr:housenumber": "15",
    "addr:postcode": "02478",
    "addr:street": "Carleton Cir",
    "iso:country": "US",
    "sg:address": "15 Carleton Cir",
    "sg:city": "Belmont",
    "sg:classifiers": [
      {
        "category": "Home \u0026 Garden",
        "subcategory": "Home Furnishings",
        "type": "Retail Goods"
      }
    ],
    "sg:phone": "+1 617 489 5988",
    "sg:postcode": "02478",
    "sg:province": "MA",
    "sg:tags": [
      "linen"
    ],
    "wof:name": "Coromandel",
    "wof:placetype": "venue"
  },
  "geometry": {"coordinates":[-71.173255,42.386568],"type":"Point"}
}
