{
  "type": "Feature",
  "properties": {
    "iso:country":"US",
    "sg:address":"15 Carleton Cir",
    "sg:city":"Belmont",
    "sg:classifiers":[
        {
            "category":"Home & Garden",
            "subcategory":"Home Furnishings",
            "type":"Retail Goods"
        }
    ],
    "sg:phone":"+1 617 489 5988",
    "sg:postcode":"02478",
    "sg:province":"MA",
    "sg:tags":[
        "linen"
    ],
    "wof:name":"Coromandel",
    "wof:placetype":"venue"
},
  "geometry": {"coordinates":[-71.173255,42.386568],"type":"Point"}
}