{
  "type": "Feature",
  "properties": {
    "iso:country":"US",
    "sg:address":"555 Broadway",
    "sg:city":"Lawrence",
    "sg:classifiers":[
        {
            "category":"Banks & Credit Unions",
            "subcategory":"Bank",
            "type":"Services"
        }
    ],
    "sg:phone":"+1 978 000 1111",
    "sg:postcode":"01841",
    "sg:province":"MA",
    "wof:name":"Sovereign Bank",
    "wof:placetype":"venue"
},
  "geometry": {"coordinates":[-71.17688800000001,42.71553],"type":"Point"}
}