{
  "type": "Feature",
  "properties": {
    "addr:full": "555 Broadway Lawrence MA 01841",
    "addr:housenumber": "555",
    "addr:postcode": "01841",
    "addr:street": "Broadway",
    "iso:country": "US",
    "sg:address": "555 Broadway",
    "sg:city": "Lawrence",
    "sg:classifiers": [
      {
        "category": "Banks \u0026 Credit Unions",
        "subcategory": "Bank",
        "type": "Services"
      }
    ],
    "sg:phone": "+1 978 000 1111",
    "sg:postcode": "01841",
    "sg:province": "MA",
    "wof:name": "Sovereign Bank",
    "wof:placetype": "venue"
  },
  "geometry": {"coordinates":[-71.176888,42.71553],"type":"Point"}
}
