{
  "type": "Feature",
  "properties": {
    "addr:full": "240 Western Ave Lynn MA 01904",
    "addr:housenumber": "240",
    "addr:postcode": "01904",
    "addr:street": "Western Ave",
    "iso:country": "US",
    "sg:address": "240 Western Ave",
    "sg:city": "Lynn",
    "sg:classifiers": [
      {
        "category": "Retail",
        "subcategory": "Auto Repair",
        "type": "Services"
      }
    ],
    "sg:phone": "+1 781 592 6669",
    "sg:postcode": "01904",
    "sg:province": "MA",
    "sg:tags": [
      "repairing",
      "automobile"
    ],
    "wof:name": "Gulf Auto Svc",
    "wof:placetype": "venue"
  },
  "geometry": {"coordinates":[-70.948657,42.477465],"type":"Point"}
}
