{
  "type": "Feature",
  "properties": {
    "addr:full":"58 Fairhaven Rd Mattapoisett MA 02739",
    "addr:housenumber":"58",
    "addr:postcode":"02739",
    "addr:street":"Fairhaven Rd",
    "iso:country":"US",
    "sg:address":"58 Fairhaven Rd",
    "sg:city":"Mattapoisett",
    "sg:classifiers":[
        {
            "category":"Professional",
            "subcategory":"Business Services",
            "type":"Services"
        }
    ],
    "sg:phone":"+1 508 758 2775",
    "sg:postcode":"02739",
    "sg:province":"MA",
    "sg:tags":[
        "embroidery"
    ],
    "wof:name":"Artistry Presentations",
    "wof:placetype":"venue"
},
  "geometry": {"coordinates":[-70.828642,41.658638],"type":"Point"}
}