{
  "type": "Feature",
  "properties": {
    "addr:full": "23 Town Hall Sq Falmouth MA 02540",
    "addr:housenumber": "23",
    "addr:postcode": "02540",
    "addr:street": "Town Hall Sq",
    "iso:country": "US",
    "sg:address": "23 Town Hall Sq",
    "sg:city": "Falmouth",
    "sg:classifiers": [
      {
        "category": "Sports \u0026 Exercise",
        "subcategory": "Bowling",
        "type": "Entertainment"
      }
    ],
    "sg:phone": "+1 508 540 4877",
    "sg:postcode": "02540",
    "sg:province": "MA",
    "sg:tags": [
      "center"
    ],
    "wof:name": "Leary Family Amusement Ctr",
    "wof:placetype": "venue"
  },
  "geometry": {"coordinates":[-70.617728,41.552092],"type":"Point"}
}
