{
  "type": "Feature",
  "properties": {
    "iso:country":"US",
    "sg:address":"170 E Bacon St",
    "sg:city":"Plainville",
    "sg:classifiers":[
        {
            "category":"Building & Trades",
            "subcategory":"Plumbing",
            "type":"Services"
        }
    ],
    "sg:phone":"+1 508 695 2274",
    "sg:postcode":"02762",
    "sg:province":"MA",
    "sg:tags":[
        "contractor"
    ],
    "wof:name":"P J C Plumbing & Heating",
    "wof:placetype":"venue"
},
  "geometry": {"coordinates":[-71.31245699999999,42.008823],"type":"Point"}
}