{
  "type": "Feature",
  "properties": {
    "addr:full": "170 E Bacon St Plainville MA 02762",
    "addr:housenumber": "170",
    "addr:postcode": "02762",
    "addr:street": "E Bacon St",
    "iso:country": "US",
    "sg:address": "170 E Bacon St",
    "sg:city": "Plainville",
    "sg:classifiers": [
      {
        "category": "Building \u0026 Trades",
        "subcategory": "Plumbing",
        "type": "Services"
      }
    ],
    "sg:phone": "+1 508 695 2274",
    "sg:postcode": "02762",
    "sg:province": "MA",
    "sg:tags": [
      "contractor"
    ],
    "wof:name": "P J C Plumbing \u0026 Heating",
    "wof:placetype": "venue"
  },
  "geometry": {"coordinates":[-71.312457,42.008823],"type":"Point"}
}
