{
  "type": "Feature",
  "properties": {
    "iso:country":"US",
    "sg:address":"9 East St Ste 2",
    "sg:city":"Boston",
    "sg:classifiers":[
        {
            "category":"Real Estate",
            "subcategory":"Architect",
            "type":"Services"
        }
    ],
    "sg:phone":"+1 617 482 4543",
    "sg:postcode":"02111",
    "sg:province":"MA",
    "wof:name":"Botticelli & Pohl",
    "wof:placetype":"venue"
},
  "geometry": {"coordinates":[-71.058753,42.307597],"type":"Point"}
}