{
  "type": "Feature",
  "properties": {
    "addr:full": "599 S Union St Lawrence MA 01843",
    "addr:housenumber": "599",
    "addr:postcode": "01843",
    "addr:street": "S Union St",
    "iso:country": "US",
    "sg:address": "599 S Union St",
    "sg:city": "Lawrence",
    "sg:classifiers": [
      {
        "category": "Government",
        "subcategory": "Office",
        "type": "Public Place"
      }
    ],
    "sg:phone": "+1   ",
    "sg:postcode": "01843",
    "sg:province": "MA",
    "sg:tags": [
      "licensing",
      "motor",
      "vehicle"
    ],
    "wof:name": "Motor Vehicles Mass Registry",
    "wof:placetype": "venue"
  },
  "geometry": {"coordinates":[-71.152834,42.686878],"type":"Point"}
}
