{
  "type": "Feature",
  "properties": {
    "addr:full": "282 Montvale Ave Woburn MA 01801",
    "addr:housenumber": "282",
    "addr:postcode": "01801",
    "addr:street": "Montvale Ave",
    "iso:country": "US",
    "sg:address": "282 Montvale Ave",
    "sg:city": "Woburn",
    "sg:classifiers": [
      {
        "category": "Wholesale",
        "subcategory": "Home Furnishings",
        "type": "Manufacturing \u0026 Wholesale Goods"
      }
    ],
    "sg:phone": "+1 781 935 1133",
    "sg:postcode": "01801",
    "sg:province": "MA",
    "sg:tags": [
      "rug",
      "carpet"
    ],
    "wof:name": "Preservation Intl Inc",
    "wof:placetype": "venue"
  },
  "geometry": {"coordinates":[-71.121829,42.479771],"type":"Point"}
}
