{
  "type": "Feature",
  "properties": {
    "iso:country":"US",
    "sg:address":"282 Montvale Ave",
    "sg:city":"Woburn",
    "sg:classifiers":[
        {
            "category":"Wholesale",
            "subcategory":"Home Furnishings",
            "type":"Manufacturing & Wholesale Goods"
        }
    ],
    "sg:phone":"+1 781 935 1133",
    "sg:postcode":"01801",
    "sg:province":"MA",
    "sg:tags":[
        "rug",
        "carpet"
    ],
    "wof:name":"Preservation Intl Inc",
    "wof:placetype":"venue"
},
  "geometry": {"coordinates":[-71.12182900000001,42.479771],"type":"Point"}
}