{
  "type": "Feature",
  "properties": {
    "iso:country":"US",
    "sg:address":"51 W Main St",
    "sg:city":"Georgetown",
    "sg:classifiers":[
        {
            "category":"Shopping",
            "subcategory":"Antiques",
            "type":"Retail Goods"
        },
        {
            "category":"Home & Garden",
            "subcategory":"Furniture",
            "type":"Retail Goods"
        }
    ],
    "sg:phone":"+1 978 352 8282",
    "sg:postcode":"01833",
    "sg:province":"MA",
    "sg:tags":[
        "store"
    ],
    "sg:website":"sedlersvillage.bizland.com/store...",
    "wof:name":"Sedler's Antique Village",
    "wof:placetype":"venue"
},
  "geometry": {"coordinates":[-70.9944,42.726501],"type":"Point"}
}