{
  "type": "Feature",
  "properties": {
    "iso:country":"US",
    "sg:address":"380 Arsenal St",
    "sg:city":"Watertown",
    "sg:classifiers":[
        {
            "category":"Home & Garden",
            "subcategory":"Furniture",
            "type":"Retail Goods"
        }
    ],
    "sg:phone":"+1 617 924 0770",
    "sg:postcode":"02472",
    "sg:province":"MA",
    "sg:tags":[
        "store"
    ],
    "wof:name":"Zaouin's Furniture",
    "wof:placetype":"venue"
},
  "geometry": {"coordinates":[-71.164484,42.363732],"type":"Point"}
}