{
  "type": "Feature",
  "properties": {
    "iso:country":"US",
    "sg:address":"222 Union St",
    "sg:city":"New Bedford",
    "sg:classifiers":[
        {
            "category":"Professional",
            "subcategory":"Lawyer & Legal Services",
            "type":"Services"
        }
    ],
    "sg:phone":"+1 508 748 2793",
    "sg:postcode":"02740",
    "sg:province":"MA",
    "sg:tags":[
        "attorney"
    ],
    "wof:name":"Hawley Bigelow",
    "wof:placetype":"venue"
},
  "geometry": {"coordinates":[-70.927533,41.633992],"type":"Point"}
}