{
  "type": "Feature",
  "properties": {
    "iso:country":"US",
    "sg:address":"2447 Massachusetts Ave",
    "sg:city":"Cambridge",
    "sg:classifiers":[
        {
            "category":"Restaurant",
            "type":"Food & Drink"
        }
    ],
    "sg:menulink":"http://www.allmenus.com/ma/cambridge/836-maria-bonita/menu/",
    "sg:phone":"+1 617 868 1160",
    "sg:postcode":"02140",
    "sg:province":"MA",
    "sg:tags":[
        "mexican"
    ],
    "wof:name":"Maria Bonita",
    "wof:placetype":"venue"
},
  "geometry": {"coordinates":[-71.130831,42.397989],"type":"Point"}
}