{
  "type": "Feature",
  "properties": {
    "addr:full": "2447 Massachusetts Ave Cambridge MA 02140",
    "addr:housenumber": "2447",
    "addr:postcode": "02140",
    "addr:street": "Massachusetts Ave",
    "iso:country": "US",
    "sg:address": "2447 Massachusetts Ave",
    "sg:city": "Cambridge",
    "sg:classifiers": [
      {
        "category": "Restaurant",
        "type": "Food \u0026 Drink"
      }
    ],
    "sg:menulink": "http://www.allmenus.com/ma/cambridge/836-maria-bonita/menu/",
    "sg:phone": "+1 617 868 1160",
    "sg:postcode": "02140",
    "sg:province": "MA",
    "sg:tags": [
      "mexican"
    ],
    "wof:name": "Maria Bonita",
    "wof:placetype": "venue"
  },
  "geometry": {"coordinates":[-71.130831,42.397989],"type":"Point"}
}
