{
  "type": "Feature",
  "properties": {
    "iso:country":"US",
    "sg:address":"50 N Franklin St",
    "sg:city":"Holbrook",
    "sg:classifiers":[
        {
            "category":"Building & Trades",
            "subcategory":"Construction",
            "type":"Services"
        }
    ],
    "sg:phone":"+1 781 767 1800",
    "sg:postcode":"02343",
    "sg:province":"MA",
    "sg:tags":[
        "marking",
        "maintenance",
        "parking"
    ],
    "wof:name":"Public Works Dept",
    "wof:placetype":"venue"
},
  "geometry": {"coordinates":[-71.00855,42.15479],"type":"Point"}
}