{
  "type": "Feature",
  "properties": {
    "addr:full": "14 Summer St Saugus MA 01906",
    "addr:housenumber": "14",
    "addr:postcode": "01906",
    "addr:street": "Summer St",
    "iso:country": "US",
    "ovtr:label": "Blessed Sacrament Church, 14 Summer St Saugus MA US",
    "ovtr:similarity": 3.400130033493042,
    "sg:address": "14 Summer St",
    "sg:city": "Saugus",
    "sg:classifiers": [
      {
        "category": "Organizations",
        "subcategory": "Religious Organization",
        "type": "Services"
      }
    ],
    "sg:phone": "+1 781 233 2497",
    "sg:postcode": "01906",
    "sg:province": "MA",
    "sg:tags": [
      "church"
    ],
    "sg:website": "www.blessedsacramentparish.org",
    "wof:name": "Blessed Sacrament Church",
    "wof:placetype": "venue"
  },
  "geometry": {"coordinates":[-71.012732,42.466145],"type":"Point"}
}
