{
  "type": "Feature",
  "properties": {
    "addr:full": "7 Millard Ave Lynn MA 01904",
    "addr:housenumber": "7",
    "addr:postcode": "01904",
    "addr:street": "Millard Ave",
    "iso:country": "US",
    "sg:address": "7 Millard Ave",
    "sg:city": "Lynn",
    "sg:classifiers": [
      {
        "category": "Building \u0026 Trades",
        "subcategory": "Construction",
        "type": "Services"
      }
    ],
    "sg:phone": "+1   ",
    "sg:postcode": "01904",
    "sg:province": "MA",
    "sg:tags": [
      "house"
    ],
    "wof:name": "Andrews Construction",
    "wof:placetype": "venue"
  },
  "geometry": {"coordinates":[-70.969153,42.495905],"type":"Point"}
}
