{
  "type": "Feature",
  "properties": {
    "addr:full": "88 Maybie St Arlington MA 02474",
    "addr:housenumber": "88",
    "addr:postcode": "02474",
    "addr:street": "Maybie St",
    "iso:country": "US",
    "sg:address": "88 Maybie St",
    "sg:city": "Arlington",
    "sg:classifiers": [
      {
        "category": "Building \u0026 Trades",
        "subcategory": "Locksmith",
        "type": "Services"
      }
    ],
    "sg:phone": "+1 781 443 7231",
    "sg:postcode": "02474",
    "sg:province": "MA",
    "sg:tags": [
      "key"
    ],
    "wof:name": "24 7 Call Emergency Locksmith On Maybi",
    "wof:placetype": "venue"
  },
  "geometry": {"coordinates":[-71.172701,42.43252],"type":"Point"}
}
