{
  "type": "Feature",
  "properties": {
    "addr:full": "1253 Great Plain Ave Needham MA 02492",
    "addr:housenumber": "1253",
    "addr:postcode": "02492",
    "addr:street": "Great Plain Ave",
    "iso:country": "US",
    "sg:address": "1253 Great Plain Ave",
    "sg:city": "Needham",
    "sg:classifiers": [
      {
        "category": "Health Services",
        "subcategory": "Health Practitioner",
        "type": "Services"
      }
    ],
    "sg:phone": "+1 781 449 0087",
    "sg:postcode": "02492",
    "sg:province": "MA",
    "sg:tags": [
      "psychologist"
    ],
    "wof:name": "Bradford B Bedar",
    "wof:placetype": "venue"
  },
  "geometry": {"coordinates":[-71.246087,42.280518],"type":"Point"}
}
