{
  "type": "Feature",
  "properties": {
    "iso:country":"US",
    "sg:address":"1071 N Main St",
    "sg:city":"Brockton",
    "sg:classifiers":[
        {
            "category":"Retail",
            "subcategory":"Laundry & Dry Cleaning",
            "type":"Services"
        }
    ],
    "sg:phone":"+1 508 586 2610",
    "sg:postcode":"02301",
    "sg:province":"MA",
    "wof:name":"Flake White Laundromat",
    "wof:placetype":"venue"
},
  "geometry": {"coordinates":[-71.032467,42.111072],"type":"Point"}
}