{
  "type": "Feature",
  "properties": {
    "iso:country":"US",
    "sg:address":"4 Boylston Pl",
    "sg:city":"Boston",
    "sg:classifiers":[
        {
            "category":"Organizations",
            "subcategory":"Community Association",
            "type":"Services"
        }
    ],
    "sg:phone":"+1 617 338 9682",
    "sg:postcode":"02116",
    "sg:province":"MA",
    "sg:tags":[
        "tavern",
        "club",
        "nightlife"
    ],
    "wof:name":"Tavern Club",
    "wof:placetype":"venue"
},
  "geometry": {"coordinates":[-71.065804,42.351898],"type":"Point"}
}