{
  "type": "Feature",
  "properties": {
    "iso:country":"US",
    "sg:address":"844 Blue Hill Ave",
    "sg:city":"Dorchester Ctr",
    "sg:classifiers":[
        {
            "category":"Professional",
            "subcategory":"Lawyer & Legal Services",
            "type":"Services"
        }
    ],
    "sg:phone":"+1 617 288 6600",
    "sg:postcode":"02124",
    "sg:province":"MA",
    "sg:tags":[
        "attorney"
    ],
    "wof:name":"Eric Chalif Esq",
    "wof:placetype":"venue"
},
  "geometry": {"coordinates":[-71.08741999999999,42.295939],"type":"Point"}
}