{
  "type": "Feature",
  "properties": {
    "addr:full": "844 Blue Hill Ave Dorchester Ctr MA 02124",
    "addr:housenumber": "844",
    "addr:postcode": "02124",
    "addr:street": "Blue Hill Ave Dorchester Ctr",
    "iso:country": "US",
    "sg:address": "844 Blue Hill Ave",
    "sg:city": "Dorchester Ctr",
    "sg:classifiers": [
      {
        "category": "Professional",
        "subcategory": "Lawyer \u0026 Legal Services",
        "type": "Services"
      }
    ],
    "sg:phone": "+1 617 288 6600",
    "sg:postcode": "02124",
    "sg:province": "MA",
    "sg:tags": [
      "attorney"
    ],
    "wof:name": "Eric Chalif Esq",
    "wof:placetype": "venue"
  },
  "geometry": {"coordinates":[-71.08742,42.295939],"type":"Point"}
}
