{
  "type": "Feature",
  "properties": {
    "addr:full": "875 Washington St Braintree MA 02184",
    "addr:housenumber": "875",
    "addr:postcode": "02184",
    "addr:street": "Washington St",
    "iso:country": "US",
    "sg:address": "875 Washington St",
    "sg:city": "Braintree",
    "sg:classifiers": [
      {
        "category": "Organizations",
        "subcategory": "Community Association",
        "type": "Services"
      }
    ],
    "sg:phone": "+1 781 843 9898",
    "sg:postcode": "02184",
    "sg:province": "MA",
    "sg:tags": [
      "fraternal"
    ],
    "wof:name": "Knights Of Columbus",
    "wof:placetype": "venue"
  },
  "geometry": {"coordinates":[-71.005167,42.20373],"type":"Point"}
}
