{
  "type": "Feature",
  "properties": {
    "iso:country":"US",
    "sg:address":"36 Commerce Way",
    "sg:city":"Woburn",
    "sg:classifiers":[
        {
            "category":"Professional",
            "subcategory":"Lawyer & Legal Services",
            "type":"Services"
        }
    ],
    "sg:phone":"+1 781 938 7878",
    "sg:postcode":"01801",
    "sg:province":"MA",
    "wof:name":"Pinta Howard",
    "wof:placetype":"venue"
},
  "geometry": {"coordinates":[-71.130898,42.505699],"type":"Point"}
}