{
  "type": "Feature",
  "properties": {
    "addr:full":"742 Main St North Oxford MA 01537",
    "addr:housenumber":"742",
    "addr:postcode":"01537",
    "addr:street":"Main St",
    "iso:country":"US",
    "sg:address":"742 Main St",
    "sg:city":"North Oxford",
    "sg:classifiers":[
        {
            "category":"Professional",
            "subcategory":"Accounting & Tax Preparation",
            "type":"Services"
        }
    ],
    "sg:phone":"+1 508 987 2372",
    "sg:postcode":"01537",
    "sg:province":"MA",
    "sg:tags":[
        "return",
        "filing"
    ],
    "wof:name":"H & R Block Tax Svc",
    "wof:placetype":"venue"
},
  "geometry": {"coordinates":[-71.88086199999999,42.171008],"type":"Point"}
}