{
  "type": "Feature",
  "properties": {
    "addr:full": "181 Beaver Dam Rd Scituate MA 02066",
    "addr:housenumber": "181",
    "addr:postcode": "02066",
    "addr:street": "Beaver Dam Rd",
    "iso:country": "US",
    "sg:address": "181 Beaver Dam Rd",
    "sg:city": "Scituate",
    "sg:classifiers": [
      {
        "category": "Restaurant",
        "type": "Food \u0026 Drink"
      }
    ],
    "sg:phone": "+1 781 545 7887",
    "sg:postcode": "02066",
    "sg:province": "MA",
    "sg:tags": [
      "eating"
    ],
    "wof:name": "P Desrosiers Lobster Co",
    "wof:placetype": "venue"
  },
  "geometry": {"coordinates":[-70.743984,42.198989],"type":"Point"}
}
