{
  "type": "Feature",
  "properties": {
    "iso:country":"US",
    "sg:address":"30 Weatherly Dr",
    "sg:city":"Salem",
    "sg:classifiers":[
        {
            "category":"Organizations",
            "subcategory":"Labor Organization",
            "type":"Services"
        }
    ],
    "sg:phone":"+1   ",
    "sg:postcode":"01970",
    "sg:province":"MA",
    "wof:name":"Local 126",
    "wof:placetype":"venue"
},
  "geometry": {"coordinates":[-70.90966899999999,42.486336],"type":"Point"}
}