{
  "type": "Feature",
  "properties": {
    "iso:country":"US",
    "sg:address":"100 John L Dietsch Blvd",
    "sg:city":"North Attleboro",
    "sg:classifiers":[
        {
            "category":"Professional",
            "type":"Services"
        }
    ],
    "sg:phone":"+1 508 643 4443",
    "sg:postcode":"02763",
    "sg:province":"MA",
    "sg:tags":[
        "establishment"
    ],
    "wof:name":"Time Planners",
    "wof:placetype":"venue"
},
  "geometry": {"coordinates":[-71.300912,41.977139],"type":"Point"}
}