{
  "type": "Feature",
  "properties": {
    "iso:country":"US",
    "sg:address":"50 Rowes Wharf",
    "sg:city":"Boston",
    "sg:classifiers":[
        {
            "category":"Professional",
            "subcategory":"Lawyer & Legal Services",
            "type":"Services"
        }
    ],
    "sg:phone":"+1 617 330 7151",
    "sg:postcode":"02110",
    "sg:province":"MA",
    "wof:name":"Peters Mark ESQ",
    "wof:placetype":"venue"
},
  "geometry": {"coordinates":[-71.050003,42.356201],"type":"Point"}
}