{
  "type": "Feature",
  "properties": {
    "iso:country":"US",
    "sg:address":"117 Concord St",
    "sg:city":"Framingham",
    "sg:classifiers":[
        {
            "category":"Organizations",
            "subcategory":"Religious Organization",
            "type":"Services"
        }
    ],
    "sg:phone":"+1   ",
    "sg:postcode":"01702",
    "sg:province":"MA",
    "wof:name":"Baptist Church Garden Oliver",
    "wof:placetype":"venue"
},
  "geometry": {"coordinates":[-71.41667200000001,42.278974],"type":"Point"}
}