{
  "type": "Feature",
  "properties": {
    "addr:full": "117 Concord St Framingham MA 01702",
    "addr:housenumber": "117",
    "addr:postcode": "01702",
    "addr:street": "Concord St",
    "iso:country": "US",
    "sg:address": "117 Concord St",
    "sg:city": "Framingham",
    "sg:classifiers": [
      {
        "category": "Organizations",
        "subcategory": "Religious Organization",
        "type": "Services"
      }
    ],
    "sg:phone": "+1   ",
    "sg:postcode": "01702",
    "sg:province": "MA",
    "wof:name": "Baptist Church Garden Oliver",
    "wof:placetype": "venue"
  },
  "geometry": {"coordinates":[-71.416672,42.278974],"type":"Point"}
}
