{
  "type": "Feature",
  "properties": {
    "addr:full":"218 Canton St Stoughton MA 02072",
    "addr:housenumber":"218",
    "addr:postcode":"02072",
    "addr:street":"Canton St",
    "iso:country":"US",
    "sg:address":"218 Canton St",
    "sg:city":"Stoughton",
    "sg:classifiers":[
        {
            "category":"Wholesale",
            "subcategory":"Scrap",
            "type":"Manufacturing & Wholesale Goods"
        }
    ],
    "sg:phone":"+1 781 341 6080",
    "sg:postcode":"02072",
    "sg:province":"MA",
    "sg:tags":[
        "recycling",
        "center"
    ],
    "sg:website":"www.grtonline.com",
    "wof:name":"Onyx Electronic Recycling",
    "wof:placetype":"venue"
},
  "geometry": {"coordinates":[-71.112077,42.126674],"type":"Point"}
}