{
  "type": "Feature",
  "properties": {
    "addr:full": "10 Timothy Ln Plymouth MA 02360",
    "addr:housenumber": "10",
    "addr:postcode": "02360",
    "addr:street": "Timothy Ln",
    "iso:country": "US",
    "sg:address": "10 Timothy Ln",
    "sg:city": "Plymouth",
    "sg:classifiers": [
      {
        "category": "Freight",
        "type": "Transportation"
      }
    ],
    "sg:phone": "+1   ",
    "sg:postcode": "02360",
    "sg:province": "MA",
    "sg:tags": [
      "operator",
      "local",
      "trucking"
    ],
    "wof:name": "Cotti and Son Trucking",
    "wof:placetype": "venue"
  },
  "geometry": {"coordinates":[-70.645,41.946414],"type":"Point"}
}
