{
  "type": "Feature",
  "properties": {
    "iso:country":"US",
    "sg:address":"324 Springfield St",
    "sg:city":"Agawam",
    "sg:classifiers":[
        {
            "category":"Personal",
            "type":"Services"
        }
    ],
    "sg:phone":"+1   ",
    "sg:postcode":"01001",
    "sg:province":"MA",
    "wof:name":"New England Thrapeutic Massage",
    "wof:placetype":"venue"
},
  "geometry": {"coordinates":[-72.639707,42.088255],"type":"Point"}
}