{
  "type": "Feature",
  "properties": {
    "iso:country":"US",
    "sg:address":"131 Tremont St Fl 8",
    "sg:city":"Boston",
    "sg:classifiers":[
        {
            "category":"Government",
            "subcategory":"Court House",
            "type":"Public Place"
        }
    ],
    "sg:phone":"+1 617 727 2200",
    "sg:postcode":"02111",
    "sg:province":"MA",
    "sg:tags":[
        "justice"
    ],
    "wof:name":"Medicaid Fraud Control",
    "wof:placetype":"venue"
},
  "geometry": {"coordinates":[-71.062254,42.356186],"type":"Point"}
}