{
  "type": "Feature",
  "properties": {
    "iso:country":"US",
    "sg:address":"26 Cook St",
    "sg:city":"Billerica",
    "sg:classifiers":[
        {
            "category":"Manufacturing",
            "subcategory":"Food",
            "type":"Manufacturing & Wholesale Goods"
        }
    ],
    "sg:phone":"+1 978 663 5400",
    "sg:postcode":"01821",
    "sg:province":"MA",
    "sg:tags":[
        "nut",
        "seed",
        "salted",
        "roasted"
    ],
    "wof:name":"Nutcracker Brands Inc",
    "wof:placetype":"venue"
},
  "geometry": {"coordinates":[-71.22876100000001,42.53577],"type":"Point"}
}