{
  "type": "Feature",
  "properties": {
    "addr:full": "4321 Washington St Roslindale MA 02131",
    "addr:housenumber": "4321",
    "addr:postcode": "02131",
    "addr:street": "Washington St",
    "iso:country": "US",
    "sg:address": "4321 Washington St",
    "sg:city": "Roslindale",
    "sg:classifiers": [
      {
        "category": "Personal",
        "type": "Services"
      },
      {
        "category": "Building \u0026 Trades",
        "subcategory": "Construction",
        "type": "Services"
      }
    ],
    "sg:phone": "+1 617 293 8015",
    "sg:postcode": "02131",
    "sg:province": "MA",
    "sg:tags": [
      "local",
      "painter"
    ],
    "wof:name": "CRK Painting",
    "wof:placetype": "venue"
  },
  "geometry": {"coordinates":[-71.131,42.2842],"type":"Point"}
}
