{
  "type": "Feature",
  "properties": {
    "iso:country":"US",
    "sg:address":"4321 Washington St",
    "sg:city":"Roslindale",
    "sg:classifiers":[
        {
            "category":"Personal",
            "type":"Services"
        },
        {
            "category":"Building & Trades",
            "subcategory":"Construction",
            "type":"Services"
        }
    ],
    "sg:phone":"+1 617 293 8015",
    "sg:postcode":"02131",
    "sg:province":"MA",
    "sg:tags":[
        "local",
        "painter"
    ],
    "wof:name":"CRK Painting",
    "wof:placetype":"venue"
},
  "geometry": {"coordinates":[-71.131,42.2842],"type":"Point"}
}