{
  "type": "Feature",
  "properties": {
    "addr:full": "190 W Main St Marlborough MA 01752",
    "addr:housenumber": "190",
    "addr:postcode": "01752",
    "addr:street": "W Main St",
    "iso:country": "US",
    "sg:address": "190 W Main St",
    "sg:city": "Marlborough",
    "sg:classifiers": [
      {
        "category": "Health Services",
        "subcategory": "Health Practitioner",
        "type": "Services"
      }
    ],
    "sg:phone": "+1   ",
    "sg:postcode": "01752",
    "sg:province": "MA",
    "wof:name": "Heaven To Earth Healing Center",
    "wof:placetype": "venue"
  },
  "geometry": {"coordinates":[-71.559514,42.342425],"type":"Point"}
}
