{
  "type": "Feature",
  "properties": {
    "iso:country":"US",
    "sg:address":"190 W Main St",
    "sg:city":"Marlborough",
    "sg:classifiers":[
        {
            "category":"Health Services",
            "subcategory":"Health Practitioner",
            "type":"Services"
        }
    ],
    "sg:phone":"+1   ",
    "sg:postcode":"01752",
    "sg:province":"MA",
    "wof:name":"Heaven To Earth Healing Center",
    "wof:placetype":"venue"
},
  "geometry": {"coordinates":[-71.55951399999999,42.342425],"type":"Point"}
}