{
  "type": "Feature",
  "properties": {
    "iso:country":"US",
    "sg:address":"225 Ware St",
    "sg:city":"Palmer",
    "sg:classifiers":[
        {
            "category":"Manufacturing",
            "subcategory":"Food",
            "type":"Manufacturing & Wholesale Goods"
        }
    ],
    "sg:phone":"+1 413 283 3740",
    "sg:postcode":"01069",
    "sg:province":"MA",
    "sg:tags":[
        "frozen",
        "dessert",
        "ice",
        "cream"
    ],
    "wof:name":"Gourmay Ice Cream Co",
    "wof:placetype":"venue"
},
  "geometry": {"coordinates":[-72.314696,42.183755],"type":"Point"}
}