{
  "type": "Feature",
  "properties": {
    "iso:country":"US",
    "sg:address":"149 Pike St",
    "sg:city":"Tewksbury",
    "sg:classifiers":[
        {
            "category":"Building & Trades",
            "subcategory":"Construction",
            "type":"Services"
        }
    ],
    "sg:phone":"+1 978 851 7269",
    "sg:postcode":"01876",
    "sg:province":"MA",
    "sg:tags":[
        "painting",
        "contractor"
    ],
    "wof:name":"David P Mattuchio",
    "wof:placetype":"venue"
},
  "geometry": {"coordinates":[-71.261002,42.61563],"type":"Point"}
}