{
  "type": "Feature",
  "properties": {
    "addr:full":"13 Kylene Cir Southampton MA 01073",
    "addr:housenumber":"13",
    "addr:postcode":"01073",
    "addr:street":"Kylene Cir",
    "iso:country":"US",
    "sg:address":"13 Kylene Cir",
    "sg:city":"Southampton",
    "sg:classifiers":[
        {
            "category":"Building & Trades",
            "subcategory":"Electrical",
            "type":"Services"
        }
    ],
    "sg:phone":"+1 413 527 2712",
    "sg:postcode":"01073",
    "sg:province":"MA",
    "sg:tags":[
        "electrician"
    ],
    "wof:name":"Bridgeman Electric",
    "wof:placetype":"venue"
},
  "geometry": {"coordinates":[-72.719688,42.248409],"type":"Point"}
}