{
  "type": "Feature",
  "properties": {
    "addr:full": "29 Worcester Rd Webster MA 01570",
    "addr:housenumber": "29",
    "addr:postcode": "01570",
    "addr:street": "Worcester Rd",
    "iso:country": "US",
    "sg:address": "29 Worcester Rd",
    "sg:city": "Webster",
    "sg:classifiers": [
      {
        "category": "Autos \u0026 Motor Vehicles",
        "subcategory": "Automobile Sales",
        "type": "Retail Goods"
      }
    ],
    "sg:phone": "+1 508 943 6333",
    "sg:postcode": "01570",
    "sg:province": "MA",
    "sg:tags": [
      "car",
      "dealer"
    ],
    "wof:name": "Lee Automotive",
    "wof:placetype": "venue"
  },
  "geometry": {"coordinates":[-71.863783,42.061661],"type":"Point"}
}
