{
  "type": "Feature",
  "properties": {
    "iso:country":"US",
    "sg:address":"448 King St",
    "sg:city":"Littleton",
    "sg:classifiers":[
        {
            "category":"Manufacturing",
            "subcategory":"Signs",
            "type":"Manufacturing & Wholesale Goods"
        }
    ],
    "sg:phone":"+1 978 772 3203",
    "sg:postcode":"01460",
    "sg:province":"MA",
    "wof:name":"Custom Signs & Neon",
    "wof:placetype":"venue"
},
  "geometry": {"coordinates":[-71.475359,42.545462],"type":"Point"}
}