{
  "type": "Feature",
  "properties": {
    "addr:full": "448 King St Littleton MA 01460",
    "addr:housenumber": "448",
    "addr:postcode": "01460",
    "addr:street": "King St",
    "iso:country": "US",
    "sg:address": "448 King St",
    "sg:city": "Littleton",
    "sg:classifiers": [
      {
        "category": "Manufacturing",
        "subcategory": "Signs",
        "type": "Manufacturing \u0026 Wholesale Goods"
      }
    ],
    "sg:phone": "+1 978 772 3203",
    "sg:postcode": "01460",
    "sg:province": "MA",
    "wof:name": "Custom Signs \u0026 Neon",
    "wof:placetype": "venue"
  },
  "geometry": {"coordinates":[-71.475359,42.545462],"type":"Point"}
}
