{
  "type": "Feature",
  "properties": {
    "addr:full": "729 Main St Falmouth MA 02540",
    "addr:housenumber": "729",
    "addr:postcode": "02540",
    "addr:street": "Main St",
    "iso:country": "US",
    "ovtr:label": "John's Liquor Store, 729 Main St Falmouth MA US",
    "ovtr:similarity": 2.0781071186065674,
    "sg:address": "729 Main St",
    "sg:city": "Falmouth",
    "sg:classifiers": [
      {
        "category": "Bars \u0026 Pubs",
        "subcategory": "Lounge",
        "type": "Food \u0026 Drink"
      },
      {
        "category": "Food \u0026 Beverages",
        "subcategory": "Liquor \u0026 Beverages",
        "type": "Retail Goods"
      },
      {
        "category": "Wholesale",
        "subcategory": "Wine \u0026 Distilled Alcoholic Beverages",
        "type": "Manufacturing \u0026 Wholesale Goods"
      }
    ],
    "sg:phone": "+1 508 548 2287",
    "sg:postcode": "02540",
    "sg:province": "MA",
    "sg:tags": [
      "store",
      "broker",
      "cocktail"
    ],
    "sg:website": "http://Johnsliquors.Com",
    "wof:name": "John's Liquor Store",
    "wof:placetype": "venue"
  },
  "geometry": {"coordinates":[-70.60365,41.553105],"type":"Point"}
}
