{
  "type": "Feature",
  "properties": {
    "iso:country":"US",
    "sg:address":"729 Main St",
    "sg:city":"Falmouth",
    "sg:classifiers":[
        {
            "category":"Bars & Pubs",
            "subcategory":"Lounge",
            "type":"Food & Drink"
        },
        {
            "category":"Food & Beverages",
            "subcategory":"Liquor & Beverages",
            "type":"Retail Goods"
        },
        {
            "category":"Wholesale",
            "subcategory":"Wine & Distilled Alcoholic Beverages",
            "type":"Manufacturing & Wholesale Goods"
        }
    ],
    "sg:phone":"+1 508 548 2287",
    "sg:postcode":"02540",
    "sg:province":"MA",
    "sg:tags":[
        "store",
        "broker",
        "cocktail"
    ],
    "sg:website":"http://Johnsliquors.Com",
    "wof:name":"John's Liquor Store",
    "wof:placetype":"venue"
},
  "geometry": {"coordinates":[-70.60365,41.553105],"type":"Point"}
}