{
  "type": "Feature",
  "properties": {
    "iso:country":"US",
    "sg:address":"12 Park St",
    "sg:city":"Natick",
    "sg:classifiers":[
        {
            "category":"Building & Trades",
            "subcategory":"Construction",
            "type":"Services"
        }
    ],
    "sg:phone":"+1 508 647 0515",
    "sg:postcode":"01760",
    "sg:province":"MA",
    "sg:tags":[
        "handyman"
    ],
    "wof:name":"Handyman Services LLC",
    "wof:placetype":"venue"
},
  "geometry": {"coordinates":[-71.346124,42.283021],"type":"Point"}
}