{
  "type": "Feature",
  "properties": {
    "iso:country":"US",
    "sg:address":"109 Sandwich St",
    "sg:city":"Plymouth",
    "sg:classifiers":[
        {
            "category":"Retail",
            "subcategory":"Auto Repair",
            "type":"Services"
        }
    ],
    "sg:phone":"+1 508 747 9818",
    "sg:postcode":"02360",
    "sg:province":"MA",
    "sg:tags":[
        "body",
        "automobile",
        "painting"
    ],
    "wof:name":"Micro Blend",
    "wof:placetype":"venue"
},
  "geometry": {"coordinates":[-70.658068,41.952328],"type":"Point"}
}