{
  "type": "Feature",
  "properties": {
    "addr:full": "387 Page St Stoughton MA 02072",
    "addr:housenumber": "387",
    "addr:postcode": "02072",
    "addr:street": "Page St",
    "iso:country": "US",
    "sg:address": "387 Page St",
    "sg:city": "Stoughton",
    "sg:classifiers": [
      {
        "category": "Home \u0026 Garden",
        "subcategory": "Furniture",
        "type": "Retail Goods"
      }
    ],
    "sg:phone": "+1 781 341 2244",
    "sg:postcode": "02072",
    "sg:province": "MA",
    "sg:tags": [
      "equipment",
      "kitchen",
      "cabinet"
    ],
    "wof:name": "Old Colony Cabinets",
    "wof:placetype": "venue"
  },
  "geometry": {"coordinates":[-71.07423,42.1515],"type":"Point"}
}
