{
  "type": "Feature",
  "properties": {
    "addr:full":"25 Mount Auburn St Ste 203 Cambridge MA 02138",
    "addr:housenumber":"25",
    "addr:postcode":"02138",
    "addr:street":"Mount Auburn St Ste 203",
    "iso:country":"US",
    "sg:address":"25 Mount Auburn St Ste 203",
    "sg:city":"Cambridge",
    "sg:classifiers":[
        {
            "category":"Organizations",
            "subcategory":"Non-profit Organization",
            "type":"Services"
        }
    ],
    "sg:phone":"+1 617 441 6300",
    "sg:postcode":"02138",
    "sg:province":"MA",
    "sg:tags":[
        "service/non-profit",
        "community"
    ],
    "wof:name":"Ecologic Development Fund",
    "wof:placetype":"venue"
},
  "geometry": {"coordinates":[-71.1151,42.3709],"type":"Point"}
}