{
  "type": "Feature",
  "properties": {
    "iso:country":"US",
    "sg:address":"13 Industrial Dr",
    "sg:city":"Southwick",
    "sg:classifiers":[
        {
            "category":"Building & Trades",
            "subcategory":"Construction",
            "type":"Services"
        }
    ],
    "sg:phone":"+1 413 569 3777",
    "sg:postcode":"01028",
    "sg:province":"MA",
    "sg:tags":[
        "contractor"
    ],
    "wof:name":"Shepherd Corp",
    "wof:placetype":"venue"
},
  "geometry": {"coordinates":[-72.521378,42.048347],"type":"Point"}
}