{
  "type": "Feature",
  "properties": {
    "iso:country":"US",
    "sg:address":"1080 Hixville Rd",
    "sg:city":"North Dartmouth",
    "sg:classifiers":[
        {
            "category":"Manufacturing",
            "subcategory":"Electronics",
            "type":"Manufacturing & Wholesale Goods"
        }
    ],
    "sg:phone":"+1   ",
    "sg:postcode":"02747",
    "sg:province":"MA",
    "sg:tags":[
        "electronic",
        "component",
        "mfg"
    ],
    "wof:name":"Environmental Electronics",
    "wof:placetype":"venue"
},
  "geometry": {"coordinates":[-71.029864,41.677501],"type":"Point"}
}