{
  "type": "Feature",
  "properties": {
    "addr:full": "121 E Berkeley St Boston MA 02228",
    "addr:housenumber": "121",
    "addr:postcode": "02228",
    "addr:street": "E Berkeley St",
    "iso:country": "US",
    "sg:address": "121 E Berkeley St",
    "sg:city": "Boston",
    "sg:classifiers": [
      {
        "category": "Sports \u0026 Exercise",
        "subcategory": "Gym",
        "type": "Entertainment"
      }
    ],
    "sg:phone": "+1 617 532 0691",
    "sg:postcode": "02228",
    "sg:province": "MA",
    "sg:tags": [
      "yoga"
    ],
    "sg:website": "www.o2yoga.com",
    "wof:name": "O2 Yoga",
    "wof:placetype": "venue"
  },
  "geometry": {"coordinates":[-71.065591,42.343843],"type":"Point"}
}
