{
  "type": "Feature",
  "properties": {
    "addr:full": "241 Beacon St Boston MA 02116",
    "addr:housenumber": "241",
    "addr:postcode": "02116",
    "addr:street": "Beacon St",
    "iso:country": "US",
    "sg:address": "241 Beacon St",
    "sg:city": "Boston",
    "sg:classifiers": [
      {
        "category": "Professional",
        "subcategory": "Management \u0026 Consulting",
        "type": "Services"
      },
      {
        "category": "Education",
        "subcategory": "School",
        "type": "Public Place"
      }
    ],
    "sg:phone": "+1 617 227 2220",
    "sg:postcode": "02116",
    "sg:province": "MA",
    "wof:name": "Protocol Advisors Inc",
    "wof:placetype": "venue"
  },
  "geometry": {"coordinates":[-71.077645,42.354021],"type":"Point"}
}
