{
  "type": "Feature",
  "properties": {
    "addr:full": "4 Vose Ln East Walpole MA 02032",
    "addr:housenumber": "4",
    "addr:postcode": "02032",
    "addr:street": "Vose Ln",
    "iso:country": "US",
    "sg:address": "4 Vose Ln",
    "sg:city": "East Walpole",
    "sg:classifiers": [
      {
        "category": "Wholesale",
        "subcategory": "Electrical",
        "type": "Manufacturing \u0026 Wholesale Goods"
      }
    ],
    "sg:phone": "+1   ",
    "sg:postcode": "02032",
    "sg:province": "MA",
    "sg:tags": [
      "equipment"
    ],
    "wof:name": "Access Plus Corp",
    "wof:placetype": "venue"
  },
  "geometry": {"coordinates":[-71.211761,42.153158],"type":"Point"}
}
