{
  "type": "Feature",
  "properties": {
    "addr:full": "59 Pioneer Knolls Florence MA 01062",
    "addr:housenumber": "59",
    "addr:postcode": "01062",
    "addr:street": "Pioneer Knolls",
    "iso:country": "US",
    "sg:address": "59 Pioneer Knolls",
    "sg:city": "Florence",
    "sg:classifiers": [
      {
        "category": "Professional",
        "subcategory": "Management \u0026 Consulting",
        "type": "Services"
      }
    ],
    "sg:phone": "+1   ",
    "sg:postcode": "01062",
    "sg:province": "MA",
    "sg:tags": [
      "software"
    ],
    "wof:name": "John E Kapitzky",
    "wof:placetype": "venue"
  },
  "geometry": {"coordinates":[-72.686233,42.321417],"type":"Point"}
}
