{
  "type": "Feature",
  "properties": {
    "iso:country":"US",
    "sg:address":"59 Pioneer Knolls",
    "sg:city":"Florence",
    "sg:classifiers":[
        {
            "category":"Professional",
            "subcategory":"Management & Consulting",
            "type":"Services"
        }
    ],
    "sg:phone":"+1   ",
    "sg:postcode":"01062",
    "sg:province":"MA",
    "sg:tags":[
        "software"
    ],
    "wof:name":"John E Kapitzky",
    "wof:placetype":"venue"
},
  "geometry": {"coordinates":[-72.686233,42.321417],"type":"Point"}
}