{
  "type": "Feature",
  "properties": {
    "iso:country":"US",
    "sg:address":"125 Granite St",
    "sg:city":"Quincy",
    "sg:classifiers":[
        {
            "category":"Organizations",
            "subcategory":"Religious Organization",
            "type":"Services"
        }
    ],
    "sg:phone":"+1   ",
    "sg:postcode":"02169",
    "sg:province":"MA",
    "wof:name":"Apostolic Witness Station",
    "wof:placetype":"venue"
},
  "geometry": {"coordinates":[-71.00555,42.246829],"type":"Point"}
}