{
  "type": "Feature",
  "properties": {
    "addr:full": "8 Johnson St Springfield MA 01108",
    "addr:housenumber": "8",
    "addr:postcode": "01108",
    "addr:street": "Johnson St",
    "iso:country": "US",
    "sg:address": "8 Johnson St",
    "sg:city": "Springfield",
    "sg:classifiers": [
      {
        "category": "Retail",
        "subcategory": "Repair Shop",
        "type": "Services"
      }
    ],
    "sg:phone": "+1 413 289 1987",
    "sg:postcode": "01108",
    "sg:province": "MA",
    "sg:tags": [
      "lock",
      "locksmith"
    ],
    "wof:name": "Norm's Locksmiths",
    "wof:placetype": "venue"
  },
  "geometry": {"coordinates":[-72.55958,42.090218],"type":"Point"}
}
