{
  "type": "Feature",
  "properties": {
    "iso:country":"US",
    "sg:address":"1 Jacintho St",
    "sg:city":"New Bedford",
    "sg:classifiers":[
        {
            "category":"Building & Trades",
            "subcategory":"Electrical",
            "type":"Services"
        }
    ],
    "sg:phone":"+1 508 996 6211",
    "sg:postcode":"02740",
    "sg:province":"MA",
    "sg:tags":[
        "electric",
        "contractor"
    ],
    "wof:name":"David H Lee Electric",
    "wof:placetype":"venue"
},
  "geometry": {"coordinates":[-70.948999,41.622955],"type":"Point"}
}