{
  "type": "Feature",
  "properties": {
    "addr:full": "10 Walnut Hill Park Woburn MA 01801",
    "addr:housenumber": "10",
    "addr:postcode": "01801",
    "addr:street": "Walnut Hill Park",
    "iso:country": "US",
    "sg:address": "10 Walnut Hill Park",
    "sg:city": "Woburn",
    "sg:classifiers": [
      {
        "category": "Professional",
        "subcategory": "Research",
        "type": "Services"
      }
    ],
    "sg:phone": "+1 781 932 3100",
    "sg:postcode": "01801",
    "sg:province": "MA",
    "sg:tags": [
      "market",
      "analysis"
    ],
    "sg:website": "www.primarypoint.com",
    "wof:name": "Primary Point Inc",
    "wof:placetype": "venue"
  },
  "geometry": {"coordinates":[-71.130488,42.48645],"type":"Point"}
}
