{
  "type": "Feature",
  "properties": {
    "addr:full": "199 Common St Belmont MA 02478",
    "addr:housenumber": "199",
    "addr:postcode": "02478",
    "addr:street": "Common St",
    "iso:country": "US",
    "sg:address": "199 Common St",
    "sg:city": "Belmont",
    "sg:classifiers": [
      {
        "category": "Organizations",
        "subcategory": "Religious Organization",
        "type": "Services"
      }
    ],
    "sg:phone": "+1 617 484 3963",
    "sg:postcode": "02478",
    "sg:province": "MA",
    "sg:tags": [
      "science",
      "churches-religious",
      "church"
    ],
    "wof:name": "Christian Science Churches",
    "wof:placetype": "venue"
  },
  "geometry": {"coordinates":[-71.173843,42.389462],"type":"Point"}
}
