{
  "type": "Feature",
  "properties": {
    "addr:full":"12 Maritime Dr Wareham MA 02571",
    "addr:housenumber":"12",
    "addr:postcode":"02571",
    "addr:street":"Maritime Dr",
    "iso:country":"US",
    "sg:address":"12 Maritime Dr",
    "sg:city":"Wareham",
    "sg:classifiers":[
        {
            "category":"Education",
            "subcategory":"Special Training",
            "type":"Public Place"
        }
    ],
    "sg:phone":"+1   ",
    "sg:postcode":"02571",
    "sg:province":"MA",
    "wof:name":"Massachusetts Home Lrng Assn",
    "wof:placetype":"venue"
},
  "geometry": {"coordinates":[-70.67784399999999,41.737724],"type":"Point"}
}