{
  "type": "Feature",
  "properties": {
    "addr:full":"360 Timpany Blvd Gardner MA 01440",
    "addr:housenumber":"360",
    "addr:postcode":"01440",
    "addr:street":"Timpany Blvd",
    "iso:country":"US",
    "sg:address":"360 Timpany Blvd",
    "sg:city":"Gardner",
    "sg:classifiers":[
        {
            "category":"Restaurant",
            "type":"Food & Drink"
        }
    ],
    "sg:phone":"+1 978 632 3888",
    "sg:postcode":"01440",
    "sg:province":"MA",
    "wof:name":"Szechuan Restaurant",
    "wof:placetype":"venue"
},
  "geometry": {"coordinates":[-71.992344,42.557236],"type":"Point"}
}