{
  "type": "Feature",
  "properties": {
    "addr:full": "803 Summer St Fl 1 Boston MA 02127",
    "addr:housenumber": "803;1",
    "addr:postcode": "02127",
    "addr:street": "Summer St",
    "iso:country": "US",
    "sg:address": "803 Summer St Fl 1",
    "sg:city": "Boston",
    "sg:classifiers": [
      {
        "category": "Building \u0026 Trades",
        "subcategory": "Construction",
        "type": "Services"
      }
    ],
    "sg:phone": "+1 857 524 1475",
    "sg:postcode": "02127",
    "sg:province": "MA",
    "sg:tags": [
      "industrial",
      "contractors-commercial",
      "contractor"
    ],
    "wof:name": "City Point Partners",
    "wof:placetype": "venue"
  },
  "geometry": {"coordinates":[-71.035507,42.33987],"type":"Point"}
}
