{
  "type": "Feature",
  "properties": {
    "iso:country":"US",
    "sg:address":"803 Summer St Fl 1",
    "sg:city":"Boston",
    "sg:classifiers":[
        {
            "category":"Building & Trades",
            "subcategory":"Construction",
            "type":"Services"
        }
    ],
    "sg:phone":"+1 857 524 1475",
    "sg:postcode":"02127",
    "sg:province":"MA",
    "sg:tags":[
        "industrial",
        "contractors-commercial",
        "contractor"
    ],
    "wof:name":"City Point Partners",
    "wof:placetype":"venue"
},
  "geometry": {"coordinates":[-71.035507,42.33987],"type":"Point"}
}