{
  "type": "Feature",
  "properties": {
    "addr:full":"601 Silver St Agawam MA 01001",
    "addr:housenumber":"601",
    "addr:postcode":"01001",
    "addr:street":"Silver St",
    "iso:country":"US",
    "sg:address":"601 Silver St",
    "sg:city":"Agawam",
    "sg:classifiers":[
        {
            "category":"Building & Trades",
            "subcategory":"Landscaping Services",
            "type":"Services"
        }
    ],
    "sg:phone":"+1 413 821 9498",
    "sg:postcode":"01001",
    "sg:province":"MA",
    "sg:tags":[
        "landscape",
        "contractor"
    ],
    "wof:name":"CRW Landscapes Inc",
    "wof:placetype":"venue"
},
  "geometry": {"coordinates":[-72.650999,42.055194],"type":"Point"}
}