{
  "type": "Feature",
  "properties": {
    "addr:full": "76 S Walnut St Quincy MA 02169",
    "addr:housenumber": "76",
    "addr:postcode": "02169",
    "addr:street": "S Walnut St",
    "iso:country": "US",
    "sg:address": "76 S Walnut St",
    "sg:city": "Quincy",
    "sg:classifiers": [
      {
        "category": "Health Services",
        "subcategory": "Clinic",
        "type": "Services"
      }
    ],
    "sg:phone": "+1 617 479 8984",
    "sg:postcode": "02169",
    "sg:province": "MA",
    "wof:name": "Erin's Own Healthcare Agency",
    "wof:placetype": "venue"
  },
  "geometry": {"coordinates":[-70.99247,42.2463],"type":"Point"}
}
