{
  "type": "Feature",
  "properties": {
    "addr:full": "273 Queen Anne Rd Harwich MA 02645",
    "addr:housenumber": "273",
    "addr:postcode": "02645",
    "addr:street": "Queen Anne Rd",
    "iso:country": "US",
    "sg:address": "273 Queen Anne Rd",
    "sg:city": "Harwich",
    "sg:classifiers": [
      {
        "category": "Government",
        "subcategory": "Office",
        "type": "Public Place"
      }
    ],
    "sg:phone": "+1 508 430 7555",
    "sg:postcode": "02645",
    "sg:province": "MA",
    "sg:tags": [
      "village"
    ],
    "wof:name": "Highway \u0026 Maintenance Dept",
    "wof:placetype": "venue"
  },
  "geometry": {"coordinates":[-70.095022,41.698464],"type":"Point"}
}
