{
  "type": "Feature",
  "properties": {
    "iso:country":"US",
    "sg:address":"273 Queen Anne Rd",
    "sg:city":"Harwich",
    "sg:classifiers":[
        {
            "category":"Government",
            "subcategory":"Office",
            "type":"Public Place"
        }
    ],
    "sg:phone":"+1 508 430 7555",
    "sg:postcode":"02645",
    "sg:province":"MA",
    "sg:tags":[
        "village"
    ],
    "wof:name":"Highway & Maintenance Dept",
    "wof:placetype":"venue"
},
  "geometry": {"coordinates":[-70.095022,41.698464],"type":"Point"}
}