{
  "type": "Feature",
  "properties": {
    "addr:full":"Barn Hill Ln West Chatham MA 02669",
    "addr:postcode":"02669",
    "addr:street":"Hill Ln West",
    "iso:country":"US",
    "sg:address":"Barn Hill Ln",
    "sg:city":"West Chatham",
    "sg:classifiers":[
        {
            "category":"Building & Trades",
            "subcategory":"Construction",
            "type":"Services"
        }
    ],
    "sg:phone":"+1 508 945 5544",
    "sg:postcode":"02669",
    "sg:province":"MA",
    "sg:tags":[
        "contractor"
    ],
    "wof:name":"Chatfield Company Inc",
    "wof:placetype":"venue"
},
  "geometry": {"coordinates":[-70.002403,41.685101],"type":"Point"}
}