{
  "type": "Feature",
  "properties": {
    "iso:country":"US",
    "sg:address":"428 Lowell Rd",
    "sg:city":"Concord",
    "sg:classifiers":[
        {
            "category":"Professional",
            "subcategory":"Management & Consulting",
            "type":"Services"
        }
    ],
    "sg:phone":"+1   ",
    "sg:postcode":"01742",
    "sg:province":"MA",
    "wof:name":"Concord Hlthcare Strtegies LLC",
    "wof:placetype":"venue"
},
  "geometry": {"coordinates":[-71.36143300000001,42.470463],"type":"Point"}
}