{
  "type": "Feature",
  "properties": {
    "addr:full": "428 Lowell Rd Concord MA 01742",
    "addr:housenumber": "428",
    "addr:postcode": "01742",
    "addr:street": "Lowell Rd",
    "iso:country": "US",
    "sg:address": "428 Lowell Rd",
    "sg:city": "Concord",
    "sg:classifiers": [
      {
        "category": "Professional",
        "subcategory": "Management \u0026 Consulting",
        "type": "Services"
      }
    ],
    "sg:phone": "+1   ",
    "sg:postcode": "01742",
    "sg:province": "MA",
    "wof:name": "Concord Hlthcare Strtegies LLC",
    "wof:placetype": "venue"
  },
  "geometry": {"coordinates":[-71.361433,42.470463],"type":"Point"}
}
