{
  "type": "Feature",
  "properties": {
    "iso:country":"US",
    "sg:address":"126 Inman Street",
    "sg:city":"Cambridge",
    "sg:classifiers":[
        {
            "category":"Sports & Exercise",
            "subcategory":"Gym",
            "type":"Entertainment"
        }
    ],
    "sg:phone":"+1 617 864 5434",
    "sg:postcode":"02139",
    "sg:province":"MA",
    "sg:tags":[
        "trainer"
    ],
    "wof:name":"New Directions For Men",
    "wof:placetype":"venue"
},
  "geometry": {"coordinates":[-71.100472,42.373354],"type":"Point"}
}