{
  "type": "Feature",
  "properties": {
    "addr:full": "812 Washington St Hanover MA 02339",
    "addr:housenumber": "812",
    "addr:postcode": "02339",
    "addr:street": "Washington St",
    "iso:country": "US",
    "sg:address": "812 Washington St",
    "sg:city": "Hanover",
    "sg:classifiers": [
      {
        "category": "Restaurant",
        "type": "Food \u0026 Drink"
      }
    ],
    "sg:phone": "+1 781 826 2465",
    "sg:postcode": "02339",
    "sg:province": "MA",
    "sg:tags": [
      "parlor",
      "ice",
      "cream"
    ],
    "wof:name": "J C's Dairy",
    "wof:placetype": "venue"
  },
  "geometry": {"coordinates":[-70.830514,42.127748],"type":"Point"}
}
