{
  "type": "Feature",
  "properties": {
    "iso:country":"US",
    "sg:address":"812 Washington St",
    "sg:city":"Hanover",
    "sg:classifiers":[
        {
            "category":"Restaurant",
            "type":"Food & Drink"
        }
    ],
    "sg:phone":"+1 781 826 2465",
    "sg:postcode":"02339",
    "sg:province":"MA",
    "sg:tags":[
        "parlor",
        "ice",
        "cream"
    ],
    "wof:name":"J C's Dairy",
    "wof:placetype":"venue"
},
  "geometry": {"coordinates":[-70.83051399999999,42.127748],"type":"Point"}
}