{
  "type": "Feature",
  "properties": {
    "iso:country":"US",
    "sg:address":"296 Broadway",
    "sg:city":"Lawrence",
    "sg:classifiers":[
        {
            "category":"Retail",
            "subcategory":"Auto Repair",
            "type":"Services"
        }
    ],
    "sg:phone":"+1 978 291 0027",
    "sg:postcode":"01841",
    "sg:province":"MA",
    "sg:tags":[
        "body",
        "repairing",
        "painting",
        "automobile"
    ],
    "wof:name":"Uris Auto Body",
    "wof:placetype":"venue"
},
  "geometry": {"coordinates":[-71.171953,42.709476],"type":"Point"}
}