{
  "type": "Feature",
  "properties": {
    "addr:full":"104 Walker St Seekonk MA 02771",
    "addr:housenumber":"104",
    "addr:postcode":"02771",
    "addr:street":"Walker St",
    "iso:country":"US",
    "sg:address":"104 Walker St",
    "sg:city":"Seekonk",
    "sg:classifiers":[
        {
            "category":"Home & Garden",
            "subcategory":"Hardware",
            "type":"Retail Goods"
        }
    ],
    "sg:phone":"+1   ",
    "sg:postcode":"02771",
    "sg:province":"MA",
    "wof:name":"Value Added Assoc Inc",
    "wof:placetype":"venue"
},
  "geometry": {"coordinates":[-71.325346,41.855251],"type":"Point"}
}