{
  "type": "Feature",
  "properties": {
    "addr:full": "300 Ledgewood Pl Ste 200 Rockland MA 02370",
    "addr:housenumber": "300",
    "addr:postcode": "02370",
    "addr:street": "Ledgewood Pl Ste 200",
    "iso:country": "US",
    "sg:address": "300 Ledgewood Pl Ste 200",
    "sg:city": "Rockland",
    "sg:classifiers": [
      {
        "category": "Banks \u0026 Credit Unions",
        "subcategory": "Financial Services",
        "type": "Services"
      }
    ],
    "sg:phone": "+1 781 871 1200",
    "sg:postcode": "02370",
    "sg:province": "MA",
    "sg:tags": [
      "loan"
    ],
    "sg:website": "http://www.kokofitness.com",
    "wof:name": "Koko Fitness, Inc.",
    "wof:placetype": "venue"
  },
  "geometry": {"coordinates":[-70.906939,42.160312],"type":"Point"}
}
