{
  "type": "Feature",
  "properties": {
    "iso:country":"US",
    "sg:address":"329 W Main St",
    "sg:city":"Northborough",
    "sg:classifiers":[
        {
            "category":"Education",
            "subcategory":"Dance Studio",
            "type":"Public Place"
        }
    ],
    "sg:phone":"+1 508 393 9697",
    "sg:postcode":"01532",
    "sg:province":"MA",
    "sg:tags":[
        "instruction",
        "dancing"
    ],
    "wof:name":"Diane Cournoyer Dance Center",
    "wof:placetype":"venue"
},
  "geometry": {"coordinates":[-71.65915200000001,42.306789],"type":"Point"}
}