{
  "type": "Feature",
  "properties": {
    "addr:full": "329 W Main St Northborough MA 01532",
    "addr:housenumber": "329",
    "addr:postcode": "01532",
    "addr:street": "W Main St",
    "iso:country": "US",
    "ovtr:label": "Diane Cournoyer Dance Center, 386 W Main St Northborough MA US",
    "ovtr:similarity": 2.928662061691284,
    "sg:address": "329 W Main St",
    "sg:city": "Northborough",
    "sg:classifiers": [
      {
        "category": "Education",
        "subcategory": "Dance Studio",
        "type": "Public Place"
      }
    ],
    "sg:phone": "+1 508 393 9697",
    "sg:postcode": "01532",
    "sg:province": "MA",
    "sg:tags": [
      "instruction",
      "dancing"
    ],
    "wof:name": "Diane Cournoyer Dance Center",
    "wof:placetype": "venue"
  },
  "geometry": {"coordinates":[-71.659152,42.306789],"type":"Point"}
}
