{
  "type": "Feature",
  "properties": {
    "addr:full":"425 Watertown St Newton MA 02458",
    "addr:housenumber":"425",
    "addr:postcode":"02458",
    "addr:street":"Watertown St",
    "iso:country":"US",
    "sg:address":"425 Watertown St",
    "sg:city":"Newton",
    "sg:classifiers":[
        {
            "category":"Travel",
            "subcategory":"Campground",
            "type":"Entertainment"
        }
    ],
    "sg:phone":"+1 617 969 2200",
    "sg:postcode":"02458",
    "sg:province":"MA",
    "sg:tags":[
        "camp"
    ],
    "sg:website":"www.academynewton.com",
    "wof:name":"Academy Of Physical & Social",
    "wof:placetype":"venue"
},
  "geometry": {"coordinates":[-71.202764,42.359915],"type":"Point"}
}