{
  "type": "Feature",
  "properties": {
    "iso:country":"US",
    "sg:address":"200 Concord Ave",
    "sg:city":"Cambridge",
    "sg:classifiers":[
        {
            "category":"Food & Beverages",
            "subcategory":"Groceries & Convenience Stores",
            "type":"Retail Goods"
        }
    ],
    "sg:phone":"+1 617 876 5999",
    "sg:postcode":"02138",
    "sg:province":"MA",
    "sg:website":"www.sarahscambridge.com",
    "wof:name":"Sarah's Market & Cafe",
    "wof:placetype":"venue"
},
  "geometry": {"coordinates":[-71.131023,42.382154],"type":"Point"}
}