{
  "type": "Feature",
  "properties": {
    "addr:full": "200 Concord Ave Cambridge MA 02138",
    "addr:housenumber": "200",
    "addr:postcode": "02138",
    "addr:street": "Concord Ave",
    "iso:country": "US",
    "sg:address": "200 Concord Ave",
    "sg:city": "Cambridge",
    "sg:classifiers": [
      {
        "category": "Food \u0026 Beverages",
        "subcategory": "Groceries \u0026 Convenience Stores",
        "type": "Retail Goods"
      }
    ],
    "sg:phone": "+1 617 876 5999",
    "sg:postcode": "02138",
    "sg:province": "MA",
    "sg:website": "www.sarahscambridge.com",
    "wof:name": "Sarah's Market \u0026 Cafe",
    "wof:placetype": "venue"
  },
  "geometry": {"coordinates":[-71.131023,42.382154],"type":"Point"}
}
