{
  "type": "Feature",
  "properties": {
    "iso:country":"US",
    "sg:address":"80 Tobey Ln",
    "sg:city":"North Dartmouth",
    "sg:classifiers":[
        {
            "category":"Wholesale",
            "subcategory":"Durable Goods & Equipment",
            "type":"Manufacturing & Wholesale Goods"
        }
    ],
    "sg:phone":"+1 508 991 2438",
    "sg:postcode":"02747",
    "sg:province":"MA",
    "sg:tags":[
        "importer"
    ],
    "wof:name":"JMI Intl",
    "wof:placetype":"venue"
},
  "geometry": {"coordinates":[-70.977231,41.623995],"type":"Point"}
}