{
  "type": "Feature",
  "properties": {
    "addr:full": "80 Tobey Ln North Dartmouth MA 02747",
    "addr:housenumber": "80",
    "addr:postcode": "02747",
    "addr:street": "Tobey Ln",
    "iso:country": "US",
    "sg:address": "80 Tobey Ln",
    "sg:city": "North Dartmouth",
    "sg:classifiers": [
      {
        "category": "Wholesale",
        "subcategory": "Durable Goods \u0026 Equipment",
        "type": "Manufacturing \u0026 Wholesale Goods"
      }
    ],
    "sg:phone": "+1 508 991 2438",
    "sg:postcode": "02747",
    "sg:province": "MA",
    "sg:tags": [
      "importer"
    ],
    "wof:name": "JMI Intl",
    "wof:placetype": "venue"
  },
  "geometry": {"coordinates":[-70.977231,41.623995],"type":"Point"}
}
