{
  "type": "Feature",
  "properties": {
    "addr:full": "167 Washington St Norwell MA 02061",
    "addr:housenumber": "167",
    "addr:postcode": "02061",
    "addr:street": "Washington St",
    "iso:country": "US",
    "sg:address": "167 Washington St",
    "sg:city": "Norwell",
    "sg:classifiers": [
      {
        "category": "Banks \u0026 Credit Unions",
        "subcategory": "Investment Brokerage",
        "type": "Services"
      }
    ],
    "sg:phone": "+1 781 261 9931",
    "sg:postcode": "02061",
    "sg:province": "MA",
    "sg:tags": [
      "advisory",
      "financial"
    ],
    "wof:name": "Brookstreet Securities Corp",
    "wof:placetype": "venue"
  },
  "geometry": {"coordinates":[-70.874551,42.168367],"type":"Point"}
}
