{
  "type": "Feature",
  "properties": {
    "iso:country":"US",
    "sg:address":"4 Pinecrest Rd",
    "sg:city":"Framingham",
    "sg:classifiers":[
        {
            "category":"Building & Trades",
            "subcategory":"Construction",
            "type":"Services"
        }
    ],
    "sg:phone":"+1 508 877 7330",
    "sg:postcode":"01701",
    "sg:province":"MA",
    "sg:tags":[
        "roofing",
        "contractor"
    ],
    "wof:name":"J C Roofing",
    "wof:placetype":"venue"
},
  "geometry": {"coordinates":[-71.390276,42.319875],"type":"Point"}
}