{
  "type": "Feature",
  "properties": {
    "addr:full": "64 Church Street Cambridge MA 02138",
    "addr:housenumber": "64",
    "addr:postcode": "02138",
    "addr:street": "Church Street",
    "iso:country": "US",
    "sg:address": "64 Church Street",
    "sg:city": "Cambridge",
    "sg:classifiers": [
      {
        "category": "Health Services",
        "subcategory": "Doctor",
        "type": "Services"
      }
    ],
    "sg:phone": "+1 617 441 7502",
    "sg:postcode": "02138",
    "sg:province": "MA",
    "sg:tags": [
      "practice",
      "family"
    ],
    "wof:name": "Shay Joseph PHD",
    "wof:placetype": "venue"
  },
  "geometry": {"coordinates":[-71.120772,42.374363],"type":"Point"}
}
