{
  "type": "Feature",
  "properties": {
    "iso:country":"US",
    "sg:address":"40 Salem St Ste 2-2",
    "sg:city":"Lynnfield",
    "sg:classifiers":[
        {
            "category":"Professional",
            "subcategory":"Computer Services",
            "type":"Services"
        }
    ],
    "sg:phone":"+1 781 463 6006",
    "sg:postcode":"01940",
    "sg:province":"MA",
    "sg:tags":[
        "designer",
        "technical",
        "consultant",
        "assistance",
        "system",
        "support"
    ],
    "wof:name":"Kyndl Corporation",
    "wof:placetype":"venue"
},
  "geometry": {"coordinates":[-71.032678,42.511322],"type":"Point"}
}