{
  "type": "Feature",
  "properties": {
    "iso:country":"US",
    "sg:address":"56 Roland St",
    "sg:city":"Charlestown",
    "sg:classifiers":[
        {
            "category":"Professional",
            "subcategory":"Computer Services",
            "type":"Services"
        }
    ],
    "sg:phone":"+1 617 776 5800",
    "sg:postcode":"02129",
    "sg:province":"MA",
    "sg:tags":[
        "website",
        "design"
    ],
    "sg:website":"www.beyourown.net",
    "wof:name":"BEYOUROWN.NET",
    "wof:placetype":"venue"
},
  "geometry": {"coordinates":[-71.079382,42.381653],"type":"Point"}
}