{
  "type": "Feature",
  "properties": {
    "iso:country":"US",
    "sg:address":"124 Washington St",
    "sg:city":"Dorchester",
    "sg:classifiers":[
        {
            "category":"Building & Trades",
            "subcategory":"Locksmith",
            "type":"Services"
        }
    ],
    "sg:phone":"+1 617 514 1503",
    "sg:postcode":"02121",
    "sg:province":"MA",
    "sg:tags":[
        "key"
    ],
    "wof:name":"AAA Anytime Locksmith",
    "wof:placetype":"venue"
},
  "geometry": {"coordinates":[-71.079825,42.305033],"type":"Point"}
}