{
  "type": "Feature",
  "properties": {
    "addr:full":"21 Chauncy St Apt 35 Cambridge MA 02138",
    "addr:housenumber":"21;35",
    "addr:postcode":"02138",
    "addr:street":"Chauncy St Apt",
    "iso:country":"US",
    "sg:address":"21 Chauncy St Apt 35",
    "sg:city":"Cambridge",
    "sg:classifiers":[
        {
            "category":"Communications",
            "subcategory":"Film & Video Production",
            "type":"Services"
        }
    ],
    "sg:phone":"+1 617 497 4579",
    "sg:postcode":"02138",
    "sg:province":"MA",
    "sg:tags":[
        "tv",
        "radio",
        "services-commercial",
        "companies-film"
    ],
    "wof:name":"Mcd Productions",
    "wof:placetype":"venue"
},
  "geometry": {"coordinates":[-71.123124,42.379375],"type":"Point"}
}