{
  "type": "Feature",
  "properties": {
    "addr:full":"1360 Allen St Springfield MA 01118",
    "addr:housenumber":"1360",
    "addr:postcode":"01118",
    "addr:street":"Allen St",
    "iso:country":"US",
    "sg:address":"1360 Allen St",
    "sg:city":"Springfield",
    "sg:classifiers":[
        {
            "category":"Shopping",
            "subcategory":"Jewelry",
            "type":"Retail Goods"
        }
    ],
    "sg:phone":"+1 413 783 5600",
    "sg:postcode":"01118",
    "sg:province":"MA",
    "sg:tags":[
        "jeweler"
    ],
    "wof:name":"Stephen Allen Jewelers",
    "wof:placetype":"venue"
},
  "geometry": {"coordinates":[-72.514073,42.094642],"type":"Point"}
}