{
  "type": "Feature",
  "properties": {
    "addr:full":"800 Boylston Street Boston MA 02199",
    "addr:housenumber":"800",
    "addr:postcode":"02199",
    "addr:street":"Boylston Street",
    "iso:country":"US",
    "sg:address":"800 Boylston Street",
    "sg:city":"Boston",
    "sg:classifiers":[
        {
            "category":"Communications",
            "subcategory":"Radio Station",
            "type":"Services"
        }
    ],
    "sg:phone":"+1 617 267 0123",
    "sg:postcode":"02199",
    "sg:province":"MA",
    "wof:name":"Wzlx-Fm Classic Rock",
    "wof:placetype":"venue"
},
  "geometry": {"coordinates":[-71.08181500000001,42.348976],"type":"Point"}
}