{
  "type": "Feature",
  "properties": {
    "iso:country":"US",
    "sg:address":"815 Main St",
    "sg:city":"Leominster",
    "sg:classifiers":[
        {
            "category":"Utilities",
            "subcategory":"Mobile Phone",
            "type":"Services"
        }
    ],
    "sg:phone":"+1 978 466 6464",
    "sg:postcode":"01453",
    "sg:province":"MA",
    "sg:tags":[
        "telephone",
        "cellular"
    ],
    "wof:name":"Directcom Nextel Sales & Svc",
    "wof:placetype":"venue"
},
  "geometry": {"coordinates":[-71.740112,42.550256],"type":"Point"}
}