{
  "type": "Feature",
  "properties": {
    "addr:full":"1010 Chestnut St Newton MA 02464",
    "addr:housenumber":"1010",
    "addr:postcode":"02464",
    "addr:street":"Chestnut St",
    "iso:country":"US",
    "sg:address":"1010 Chestnut St",
    "sg:city":"Newton",
    "sg:classifiers":[
        {
            "category":"Autos & Motor Vehicles",
            "subcategory":"Fuel & Gas Station",
            "type":"Retail Goods"
        }
    ],
    "sg:phone":"+1 617 527 7281",
    "sg:postcode":"02464",
    "sg:province":"MA",
    "sg:tags":[
        "oil"
    ],
    "wof:name":"Echo Bridge Svc Station",
    "wof:placetype":"venue"
},
  "geometry": {"coordinates":[-71.225572,42.315548],"type":"Point"}
}