{
  "type": "Feature",
  "properties": {
    "addr:full": "37 Chappaquiddick Rd Edgartown MA 02539",
    "addr:housenumber": "37",
    "addr:postcode": "02539",
    "addr:street": "Chappaquiddick Rd",
    "iso:country": "US",
    "sg:address": "37 Chappaquiddick Rd",
    "sg:city": "Edgartown",
    "sg:classifiers": [
      {
        "category": "Recreation",
        "type": "Entertainment"
      },
      {
        "category": "Organizations",
        "subcategory": "Community Association",
        "type": "Services"
      }
    ],
    "sg:phone": "+1 508 627 8221",
    "sg:postcode": "02539",
    "sg:province": "MA",
    "sg:tags": [
      "club",
      "beach",
      "membership",
      "bar"
    ],
    "wof:name": "Chappaquiddick Beach Club Inc",
    "wof:placetype": "venue"
  },
  "geometry": {"coordinates":[-70.508305,41.388657],"type":"Point"}
}
