{
  "type": "Feature",
  "properties": {
    "iso:country":"US",
    "sg:address":"85 Conomo Pt Ln",
    "sg:city":"Essex",
    "sg:classifiers":[
        {
            "category":"Professional",
            "subcategory":"Computer Services",
            "type":"Services"
        }
    ],
    "sg:phone":"+1 978 768 7399",
    "sg:postcode":"01929",
    "sg:province":"MA",
    "wof:name":"Jay Rowe Computing",
    "wof:placetype":"venue"
},
  "geometry": {"coordinates":[-70.744225,42.649579],"type":"Point"}
}