{
  "type": "Feature",
  "properties": {
    "addr:full": "589 Bay Rd South Hamilton MA 01982",
    "addr:housenumber": "589",
    "addr:postcode": "01982",
    "addr:street": "Bay Rd South",
    "iso:country": "US",
    "sg:address": "589 Bay Rd",
    "sg:city": "South Hamilton",
    "sg:classifiers": [
      {
        "category": "Government",
        "subcategory": "Post Office",
        "type": "Public Place"
      }
    ],
    "sg:phone": "+1 978 000 1111",
    "sg:postcode": "01982",
    "sg:province": "MA",
    "wof:name": "US Post Office",
    "wof:placetype": "venue"
  },
  "geometry": {"coordinates":[-70.854313,42.621979],"type":"Point"}
}
