{
  "type": "Feature",
  "properties": {
    "addr:full":"320 Underpass Rd Brewster MA 02631",
    "addr:housenumber":"320",
    "addr:postcode":"02631",
    "addr:street":"Underpass Rd",
    "iso:country":"US",
    "sg:address":"320 Underpass Rd",
    "sg:city":"Brewster",
    "sg:classifiers":[
        {
            "category":"Home & Garden",
            "subcategory":"Home Furnishings",
            "type":"Retail Goods"
        }
    ],
    "sg:phone":"+1 508 896 6505",
    "sg:postcode":"02631",
    "sg:province":"MA",
    "sg:tags":[
        "equipment",
        "fireplace"
    ],
    "wof:name":"Rose Forge Inc",
    "wof:placetype":"venue"
},
  "geometry": {"coordinates":[-70.06744500000001,41.755448],"type":"Point"}
}