{
  "type": "Feature",
  "properties": {
    "addr:full": "278 E Falmouth Hwy East Falmouth MA 02536",
    "addr:housenumber": "278",
    "addr:postcode": "02536",
    "addr:street": "E Falmouth Hwy",
    "iso:country": "US",
    "sg:address": "278 E Falmouth Hwy",
    "sg:city": "East Falmouth",
    "sg:classifiers": [
      {
        "category": "Education",
        "subcategory": "School",
        "type": "Public Place"
      }
    ],
    "sg:phone": "+1   ",
    "sg:postcode": "02536",
    "sg:province": "MA",
    "sg:tags": [
      "seminar"
    ],
    "wof:name": "Tim Verslycke",
    "wof:placetype": "venue"
  },
  "geometry": {"coordinates":[-70.564272,41.578841],"type":"Point"}
}
