{
  "type": "Feature",
  "properties": {
    "addr:full":"133 Elm St Salisbury MA 01952",
    "addr:housenumber":"133",
    "addr:postcode":"01952",
    "addr:street":"Elm St",
    "iso:country":"US",
    "sg:address":"133 Elm St",
    "sg:city":"Salisbury",
    "sg:classifiers":[
        {
            "category":"Building & Trades",
            "subcategory":"Landscaping Services",
            "type":"Services"
        }
    ],
    "sg:phone":"+1 978 499 2114",
    "sg:postcode":"01952",
    "sg:province":"MA",
    "sg:tags":[
        "tree"
    ],
    "wof:name":"A 1 Tree & Landscape",
    "wof:placetype":"venue"
},
  "geometry": {"coordinates":[-70.883297,42.844347],"type":"Point"}
}