{
  "type": "Feature",
  "properties": {
    "iso:country":"US",
    "sg:address":"28 Washington St",
    "sg:city":"Wellesley",
    "sg:classifiers":[
        {
            "category":"Health Services",
            "subcategory":"Nursing And Care Facility",
            "type":"Services"
        }
    ],
    "sg:phone":"+1 781 235 0203",
    "sg:postcode":"02481",
    "sg:province":"MA",
    "sg:tags":[
        "hospice"
    ],
    "wof:name":"Beverly Enterprises",
    "wof:placetype":"venue"
},
  "geometry": {"coordinates":[-71.26023000000001,42.32513],"type":"Point"}
}