{
  "type": "Feature",
  "properties": {
    "addr:full": "16 Bay Rd South Hamilton MA 01982",
    "addr:housenumber": "16",
    "addr:postcode": "01982",
    "addr:street": "Bay Rd South",
    "iso:country": "US",
    "sg:address": "16 Bay Rd",
    "sg:city": "South Hamilton",
    "sg:classifiers": [
      {
        "category": "Professional",
        "subcategory": "Business Services",
        "type": "Services"
      }
    ],
    "sg:phone": "+1 978 468 4949",
    "sg:postcode": "01982",
    "sg:province": "MA",
    "sg:tags": [
      "interior",
      "consultant",
      "design",
      "decorator"
    ],
    "wof:name": "Erika Leone Interiors",
    "wof:placetype": "venue"
  },
  "geometry": {"coordinates":[-70.875064,42.610198],"type":"Point"}
}
