{
  "type": "Feature",
  "properties": {
    "iso:country":"US",
    "sg:address":"16 Bay Rd",
    "sg:city":"South Hamilton",
    "sg:classifiers":[
        {
            "category":"Professional",
            "subcategory":"Business Services",
            "type":"Services"
        }
    ],
    "sg:phone":"+1 978 468 4949",
    "sg:postcode":"01982",
    "sg:province":"MA",
    "sg:tags":[
        "interior",
        "consultant",
        "design",
        "decorator"
    ],
    "wof:name":"Erika Leone Interiors",
    "wof:placetype":"venue"
},
  "geometry": {"coordinates":[-70.87506399999999,42.610198],"type":"Point"}
}