{
  "type": "Feature",
  "properties": {
    "addr:full": "605 N King St Northampton MA 01060",
    "addr:housenumber": "605",
    "addr:postcode": "01060",
    "addr:street": "N King St",
    "iso:country": "US",
    "sg:address": "605 N King St",
    "sg:city": "Northampton",
    "sg:classifiers": [
      {
        "category": "Autos \u0026 Motor Vehicles",
        "subcategory": "Automobile Sales",
        "type": "Retail Goods"
      }
    ],
    "sg:phone": "+1 413 586 9777",
    "sg:postcode": "01060",
    "sg:province": "MA",
    "sg:tags": [
      "car",
      "dealer"
    ],
    "wof:name": "J B Auto",
    "wof:placetype": "venue"
  },
  "geometry": {"coordinates":[-72.638969,42.356602],"type":"Point"}
}
