{
  "type": "Feature",
  "properties": {
    "addr:full":"119 Boston Rd Springfield MA 01109",
    "addr:housenumber":"119",
    "addr:postcode":"01109",
    "addr:street":"Boston Rd",
    "iso:country":"US",
    "sg:address":"119 Boston Rd",
    "sg:city":"Springfield",
    "sg:classifiers":[
        {
            "category":"Bakery",
            "type":"Food & Drink"
        },
        {
            "category":"Coffee & Tea",
            "type":"Food & Drink"
        },
        {
            "category":"Bagels",
            "type":"Food & Drink"
        },
        {
            "category":"Donuts",
            "type":"Food & Drink"
        }
    ],
    "sg:menulink":"http://www.allmenus.com/ma/springfield/143401-dunkin-donuts/menu/",
    "sg:phone":"+1 413 796 8251",
    "sg:postcode":"01109",
    "sg:province":"MA",
    "sg:tags":[
        "american",
        "diner",
        "pastry"
    ],
    "wof:name":"Dunkin' Donuts",
    "wof:placetype":"venue"
},
  "geometry": {"coordinates":[-72.53605,42.125074],"type":"Point"}
}