{
  "type": "Feature",
  "properties": {
    "addr:full":"18 Commerce Way Ste 2850 Woburn MA 01801",
    "addr:housenumber":"18",
    "addr:postcode":"2850;01801",
    "addr:street":"Commerce Way Ste",
    "iso:country":"US",
    "sg:address":"18 Commerce Way Ste 2850",
    "sg:city":"Woburn",
    "sg:classifiers":[
        {
            "category":"Wholesale",
            "subcategory":"Computers",
            "type":"Manufacturing & Wholesale Goods"
        }
    ],
    "sg:phone":"+1 781 932 6730",
    "sg:postcode":"01801",
    "sg:province":"MA",
    "wof:name":"Alliance Marketing Group",
    "wof:placetype":"venue"
},
  "geometry": {"coordinates":[-71.130898,42.5051],"type":"Point"}
}