{
  "type": "Feature",
  "properties": {
    "addr:full": "752 Washington St Pembroke MA 02359",
    "addr:housenumber": "752",
    "addr:postcode": "02359",
    "addr:street": "Washington St",
    "iso:country": "US",
    "sg:address": "752 Washington St",
    "sg:city": "Pembroke",
    "sg:classifiers": [
      {
        "category": "Professional",
        "subcategory": "Management \u0026 Consulting",
        "type": "Services"
      }
    ],
    "sg:phone": "+1 781 826 9142",
    "sg:postcode": "02359",
    "sg:province": "MA",
    "sg:tags": [
      "medical",
      "administration",
      "business"
    ],
    "wof:name": "Lake Shore Medical Designs",
    "wof:placetype": "venue"
  },
  "geometry": {"coordinates":[-70.777056,42.068951],"type":"Point"}
}
