{
  "type": "Feature",
  "properties": {
    "iso:country":"US",
    "sg:address":"752 Washington St",
    "sg:city":"Pembroke",
    "sg:classifiers":[
        {
            "category":"Professional",
            "subcategory":"Management & Consulting",
            "type":"Services"
        }
    ],
    "sg:phone":"+1 781 826 9142",
    "sg:postcode":"02359",
    "sg:province":"MA",
    "sg:tags":[
        "medical",
        "administration",
        "business"
    ],
    "wof:name":"Lake Shore Medical Designs",
    "wof:placetype":"venue"
},
  "geometry": {"coordinates":[-70.777056,42.068951],"type":"Point"}
}