{
  "type": "Feature",
  "properties": {
    "iso:country":"US",
    "sg:address":"47 Church St",
    "sg:city":"Wellesley",
    "sg:classifiers":[
        {
            "category":"Professional",
            "subcategory":"Lawyer & Legal Services",
            "type":"Services"
        }
    ],
    "sg:phone":"+1 781 237 2120",
    "sg:postcode":"02482",
    "sg:province":"MA",
    "sg:tags":[
        "attorney"
    ],
    "wof:name":"Edward C Donlon",
    "wof:placetype":"venue"
},
  "geometry": {"coordinates":[-71.295267,42.295749],"type":"Point"}
}