{
  "type": "Feature",
  "properties": {
    "addr:full": "7 Dudley St Haverhill MA 01830",
    "addr:housenumber": "7",
    "addr:postcode": "01830",
    "addr:street": "Dudley St",
    "iso:country": "US",
    "sg:address": "7 Dudley St",
    "sg:city": "Haverhill",
    "sg:classifiers": [
      {
        "category": "Retail",
        "subcategory": "Laundry \u0026 Dry Cleaning",
        "type": "Services"
      }
    ],
    "sg:phone": "+1 978 521 7653",
    "sg:postcode": "01830",
    "sg:province": "MA",
    "wof:name": "Garden Island Laundry",
    "wof:placetype": "venue"
  },
  "geometry": {"coordinates":[-71.076476,42.785691],"type":"Point"}
}
