{
  "type": "Feature",
  "properties": {
    "iso:country":"US",
    "sg:address":"68 Union St",
    "sg:city":"Easthampton",
    "sg:classifiers":[
        {
            "category":"Food & Beverages",
            "subcategory":"Liquor & Beverages",
            "type":"Retail Goods"
        }
    ],
    "sg:phone":"+1 413 527 8335",
    "sg:postcode":"01027",
    "sg:province":"MA",
    "wof:name":"Union Package Store",
    "wof:placetype":"venue"
},
  "geometry": {"coordinates":[-72.670326,42.267433],"type":"Point"}
}