{
  "type": "Feature",
  "properties": {
    "addr:full": "51 Main St Peabody MA 01960",
    "addr:housenumber": "51",
    "addr:postcode": "01960",
    "addr:street": "Main St",
    "iso:country": "US",
    "ovtr:label": "Roseanne Hair Salon, 51 Main St Peabody MA US",
    "ovtr:similarity": 2.570120096206665,
    "sg:address": "51 Main St",
    "sg:city": "Peabody",
    "sg:classifiers": [
      {
        "category": "Personal",
        "subcategory": "Beauty Salon",
        "type": "Services"
      }
    ],
    "sg:phone": "+1 978 532 4300",
    "sg:postcode": "01960",
    "sg:province": "MA",
    "wof:name": "Roseanne Hair Salon",
    "wof:placetype": "venue"
  },
  "geometry": {"coordinates":[-70.925034,42.52485],"type":"Point"}
}
