{
  "type": "Feature",
  "properties": {
    "iso:country":"US",
    "sg:address":"440 Forbes Blvd",
    "sg:city":"Mansfield",
    "sg:classifiers":[
        {
            "category":"Travel",
            "subcategory":"Travel Agent",
            "type":"Entertainment"
        }
    ],
    "sg:phone":"+1   ",
    "sg:postcode":"02048",
    "sg:province":"MA",
    "wof:name":"American Express",
    "wof:placetype":"venue"
},
  "geometry": {"coordinates":[-71.239209,42.017738],"type":"Point"}
}