{
  "type": "Feature",
  "properties": {
    "addr:full": "315 New Boston St Woburn MA 01801",
    "addr:housenumber": "315",
    "addr:postcode": "01801",
    "addr:street": "New Boston St",
    "iso:country": "US",
    "sg:address": "315 New Boston St",
    "sg:city": "Woburn",
    "sg:classifiers": [
      {
        "category": "Manufacturing",
        "subcategory": "Tools \u0026 Machinery",
        "type": "Manufacturing \u0026 Wholesale Goods"
      }
    ],
    "sg:phone": "+1 781 938 3884",
    "sg:postcode": "01801",
    "sg:province": "MA",
    "sg:tags": [
      "machine",
      "shop"
    ],
    "wof:name": "Cambridge Machine Co",
    "wof:placetype": "venue"
  },
  "geometry": {"coordinates":[-71.146842,42.520707],"type":"Point"}
}
