{
  "type": "Feature",
  "properties": {
    "iso:country":"US",
    "sg:address":"315 New Boston St",
    "sg:city":"Woburn",
    "sg:classifiers":[
        {
            "category":"Manufacturing",
            "subcategory":"Tools & Machinery",
            "type":"Manufacturing & Wholesale Goods"
        }
    ],
    "sg:phone":"+1 781 938 3884",
    "sg:postcode":"01801",
    "sg:province":"MA",
    "sg:tags":[
        "machine",
        "shop"
    ],
    "wof:name":"Cambridge Machine Co",
    "wof:placetype":"venue"
},
  "geometry": {"coordinates":[-71.14684200000001,42.520707],"type":"Point"}
}