{
  "type": "Feature",
  "properties": {
    "iso:country":"US",
    "sg:address":"26 High St",
    "sg:city":"Milton",
    "sg:classifiers":[
        {
            "category":"Manufacturing",
            "subcategory":"Printing",
            "type":"Manufacturing & Wholesale Goods"
        }
    ],
    "sg:phone":"+1 617 698 6563",
    "sg:postcode":"02186",
    "sg:province":"MA",
    "sg:tags":[
        "newspaper"
    ],
    "wof:name":"Milton Record Transcript",
    "wof:placetype":"venue"
},
  "geometry": {"coordinates":[-71.06787300000001,42.269004],"type":"Point"}
}