{
  "type": "Feature",
  "properties": {
    "addr:full": "26 High St Milton MA 02186",
    "addr:housenumber": "26",
    "addr:postcode": "02186",
    "addr:street": "High St",
    "iso:country": "US",
    "sg:address": "26 High St",
    "sg:city": "Milton",
    "sg:classifiers": [
      {
        "category": "Manufacturing",
        "subcategory": "Printing",
        "type": "Manufacturing \u0026 Wholesale Goods"
      }
    ],
    "sg:phone": "+1 617 698 6563",
    "sg:postcode": "02186",
    "sg:province": "MA",
    "sg:tags": [
      "newspaper"
    ],
    "wof:name": "Milton Record Transcript",
    "wof:placetype": "venue"
  },
  "geometry": {"coordinates":[-71.067873,42.269004],"type":"Point"}
}
