{
  "type": "Feature",
  "properties": {
    "iso:country":"US",
    "sg:address":"817 Colrain Rd",
    "sg:city":"Greenfield",
    "sg:classifiers":[
        {
            "category":"Travel",
            "subcategory":"Hotels & Motels",
            "type":"Entertainment"
        }
    ],
    "sg:phone":"+1 413 772 0474",
    "sg:postcode":"01301",
    "sg:province":"MA",
    "sg:tags":[
        "cottage",
        "cabin"
    ],
    "wof:name":"Old Tavern Farm",
    "wof:placetype":"venue"
},
  "geometry": {"coordinates":[-72.635565,42.621686],"type":"Point"}
}