{
  "type": "Feature",
  "properties": {
    "addr:full":"148 Marlborough St Boston MA 02116",
    "addr:housenumber":"148",
    "addr:postcode":"02116",
    "addr:street":"Marlborough St",
    "iso:country":"US",
    "sg:address":"148 Marlborough St",
    "sg:city":"Boston",
    "sg:classifiers":[
        {
            "category":"Real Estate",
            "subcategory":"Real Estate Agent",
            "type":"Services"
        }
    ],
    "sg:phone":"+1   ",
    "sg:postcode":"02116",
    "sg:province":"MA",
    "wof:name":"Chatham Trust",
    "wof:placetype":"venue"
},
  "geometry": {"coordinates":[-71.076888,42.353331],"type":"Point"}
}