{
  "type": "Feature",
  "properties": {
    "addr:full":"438 Common St Belmont MA 02478",
    "addr:housenumber":"438",
    "addr:postcode":"02478",
    "addr:street":"Common St",
    "iso:country":"US",
    "sg:address":"438 Common St",
    "sg:city":"Belmont",
    "sg:classifiers":[
        {
            "category":"Real Estate",
            "subcategory":"Architect",
            "type":"Services"
        }
    ],
    "sg:phone":"+1 617 489 8585",
    "sg:postcode":"02478",
    "sg:province":"MA",
    "wof:name":"Equus Design Group Inc",
    "wof:placetype":"venue"
},
  "geometry": {"coordinates":[-71.174593,42.380509],"type":"Point"}
}