{
  "type": "Feature",
  "properties": {
    "addr:full": "77 Locust St Assonet MA 02702",
    "addr:housenumber": "77",
    "addr:postcode": "02702",
    "addr:street": "Locust St",
    "iso:country": "US",
    "sg:address": "77 Locust St",
    "sg:city": "Assonet",
    "sg:classifiers": [
      {
        "category": "Wholesale",
        "subcategory": "Office Equipment",
        "type": "Manufacturing \u0026 Wholesale Goods"
      }
    ],
    "sg:phone": "+1 508 822 8880",
    "sg:postcode": "02702",
    "sg:province": "MA",
    "sg:tags": [
      "machine",
      "duplicating",
      "copying"
    ],
    "wof:name": "Dunn Business Equipment",
    "wof:placetype": "venue"
  },
  "geometry": {"coordinates":[-71.060404,41.8142],"type":"Point"}
}
