{
  "type": "Feature",
  "properties": {
    "iso:country":"US",
    "sg:address":"77 Locust St",
    "sg:city":"Assonet",
    "sg:classifiers":[
        {
            "category":"Wholesale",
            "subcategory":"Office Equipment",
            "type":"Manufacturing & Wholesale Goods"
        }
    ],
    "sg:phone":"+1 508 822 8880",
    "sg:postcode":"02702",
    "sg:province":"MA",
    "sg:tags":[
        "machine",
        "duplicating",
        "copying"
    ],
    "wof:name":"Dunn Business Equipment",
    "wof:placetype":"venue"
},
  "geometry": {"coordinates":[-71.06040400000001,41.8142],"type":"Point"}
}