{
  "type": "Feature",
  "properties": {
    "iso:country":"US",
    "sg:address":"10 Washington St",
    "sg:city":"Manchester",
    "sg:classifiers":[
        {
            "category":"Marine",
            "type":"Transportation"
        }
    ],
    "sg:phone":"+1 978 526 1894",
    "sg:postcode":"01944",
    "sg:province":"MA",
    "sg:tags":[
        "surveyor"
    ],
    "wof:name":"Ocean Technical Svc",
    "wof:placetype":"venue"
},
  "geometry": {"coordinates":[-70.767871,42.575558],"type":"Point"}
}