{
  "type": "Feature",
  "properties": {
    "addr:full":"119 Vale St Tewksbury MA 01876",
    "addr:housenumber":"119",
    "addr:postcode":"01876",
    "addr:street":"Vale St",
    "iso:country":"US",
    "sg:address":"119 Vale St",
    "sg:city":"Tewksbury",
    "sg:classifiers":[
        {
            "category":"Building & Trades",
            "subcategory":"Construction",
            "type":"Services"
        }
    ],
    "sg:phone":"+1 978 640 1159",
    "sg:postcode":"01876",
    "sg:province":"MA",
    "sg:tags":[
        "coping",
        "plastering",
        "tiling",
        "pool",
        "swimming"
    ],
    "wof:name":"Ideal Pools",
    "wof:placetype":"venue"
},
  "geometry": {"coordinates":[-71.18055,42.616116],"type":"Point"}
}