{
  "type": "Feature",
  "properties": {
    "addr:full": "1855 Dorchester Ave Dorchester Ctr MA 02124",
    "addr:housenumber": "1855",
    "addr:postcode": "02124",
    "addr:street": "Dorchester Ave Dorchester Ctr",
    "iso:country": "US",
    "sg:address": "1855 Dorchester Ave",
    "sg:city": "Dorchester Ctr",
    "sg:classifiers": [
      {
        "category": "Professional",
        "type": "Services"
      }
    ],
    "sg:phone": "+1 617 929 1037",
    "sg:postcode": "02124",
    "sg:province": "MA",
    "sg:tags": [
      "establishment"
    ],
    "wof:name": "Healthy Futures",
    "wof:placetype": "venue"
  },
  "geometry": {"coordinates":[-71.063839,42.287676],"type":"Point"}
}
