{
  "type": "Feature",
  "properties": {
    "iso:country":"US",
    "sg:address":"200 Linden St",
    "sg:city":"Wellesley",
    "sg:classifiers":[
        {
            "category":"Shopping",
            "subcategory":"Clothing, Apparel, & Fashions",
            "type":"Retail Goods"
        }
    ],
    "sg:phone":"+1 781 237 5526",
    "sg:postcode":"02482",
    "sg:province":"MA",
    "sg:tags":[
        "dancing",
        "supply"
    ],
    "sg:website":"www.capeziodance.com",
    "wof:name":"Capezio",
    "wof:placetype":"venue"
},
  "geometry": {"coordinates":[-71.293195,42.299525],"type":"Point"}
}