{
  "type": "Feature",
  "properties": {
    "iso:country":"US",
    "sg:address":"145 Botolph St",
    "sg:city":"Boston",
    "sg:classifiers":[
        {
            "category":"Professional",
            "subcategory":"Business Services",
            "type":"Services"
        }
    ],
    "sg:phone":"+1   ",
    "sg:postcode":"02171",
    "sg:province":"MA",
    "wof:name":"Russell Nl Assoc",
    "wof:placetype":"venue"
},
  "geometry": {"coordinates":[-71.02577599999999,42.280605],"type":"Point"}
}