{
  "type": "Feature",
  "properties": {
    "addr:full":"45 River Rd Rutland MA 01543",
    "addr:housenumber":"45",
    "addr:postcode":"01543",
    "addr:street":"River Rd",
    "iso:country":"US",
    "sg:address":"45 River Rd",
    "sg:city":"Rutland",
    "sg:classifiers":[
        {
            "category":"Building & Trades",
            "subcategory":"Construction",
            "type":"Services"
        }
    ],
    "sg:phone":"+1 508 886 4736",
    "sg:postcode":"01543",
    "sg:province":"MA",
    "sg:tags":[
        "product",
        "asphalt"
    ],
    "wof:name":"Caruso Paving",
    "wof:placetype":"venue"
},
  "geometry": {"coordinates":[-71.97553499999999,42.430173],"type":"Point"}
}