{
  "type": "Feature",
  "properties": {
    "iso:country":"US",
    "sg:address":"3198 Cranberry Hwy",
    "sg:city":"East Wareham",
    "sg:classifiers":[
        {
            "category":"Restaurant",
            "type":"Food & Drink"
        }
    ],
    "sg:phone":"+1 508 980 1005",
    "sg:postcode":"02538",
    "sg:province":"MA",
    "sg:tags":[
        "breakfast",
        "brunch"
    ],
    "sg:website":"www.persysplace.com",
    "wof:name":"Persy's Place",
    "wof:placetype":"venue"
},
  "geometry": {"coordinates":[-70.64241699999999,41.756034],"type":"Point"}
}