{
  "type": "Feature",
  "properties": {
    "addr:full": "3198 Cranberry Hwy East Wareham MA 02538",
    "addr:housenumber": "3198",
    "addr:postcode": "02538",
    "addr:street": "Cranberry Hwy",
    "iso:country": "US",
    "ovtr:label": "Persy's Place, 3198 Cranberry Hwy East Wareham MA US",
    "ovtr:similarity": 2.367990016937256,
    "sg:address": "3198 Cranberry Hwy",
    "sg:city": "East Wareham",
    "sg:classifiers": [
      {
        "category": "Restaurant",
        "type": "Food \u0026 Drink"
      }
    ],
    "sg:phone": "+1 508 980 1005",
    "sg:postcode": "02538",
    "sg:province": "MA",
    "sg:tags": [
      "breakfast",
      "brunch"
    ],
    "sg:website": "www.persysplace.com",
    "wof:name": "Persy's Place",
    "wof:placetype": "venue"
  },
  "geometry": {"coordinates":[-70.642417,41.756034],"type":"Point"}
}
