{
  "type": "Feature",
  "properties": {
    "iso:country":"US",
    "sg:address":"37 Old Bolton Rd",
    "sg:city":"Hudson",
    "sg:classifiers":[
        {
            "category":"Personal",
            "type":"Services"
        }
    ],
    "sg:phone":"+1   ",
    "sg:postcode":"01749",
    "sg:province":"MA",
    "wof:name":"Jami Attaway",
    "wof:placetype":"venue"
},
  "geometry": {"coordinates":[-71.55642899999999,42.409417],"type":"Point"}
}