{
  "type": "Feature",
  "properties": {
    "addr:full": "35 Gartland St Jamaica Plain MA 02130",
    "addr:housenumber": "35",
    "addr:postcode": "02130",
    "addr:street": "Gartland St",
    "iso:country": "US",
    "sg:address": "35 Gartland St",
    "sg:city": "Jamaica Plain",
    "sg:classifiers": [
      {
        "category": "Organizations",
        "subcategory": "Non-profit Organization",
        "type": "Services"
      }
    ],
    "sg:phone": "+1 617 522 2400",
    "sg:postcode": "02130",
    "sg:province": "MA",
    "sg:tags": [
      "charitable",
      "institution"
    ],
    "wof:name": "Boston Live Charity Fund",
    "wof:placetype": "venue"
  },
  "geometry": {"coordinates":[-71.10559,42.305694],"type":"Point"}
}
