{
  "type": "Feature",
  "properties": {
    "addr:full":"142 Lake Ave Fall River MA 02721",
    "addr:housenumber":"142",
    "addr:postcode":"02721",
    "addr:street":"Lake Ave",
    "iso:country":"US",
    "sg:address":"142 Lake Ave",
    "sg:city":"Fall River",
    "sg:classifiers":[
        {
            "category":"Building & Trades",
            "subcategory":"Cleaning & Sanitation",
            "type":"Services"
        }
    ],
    "sg:phone":"+1   ",
    "sg:postcode":"02721",
    "sg:province":"MA",
    "sg:tags":[
        "maintenance"
    ],
    "wof:name":"Colonial Window Cleaning Inc",
    "wof:placetype":"venue"
},
  "geometry": {"coordinates":[-71.132583,41.659613],"type":"Point"}
}