{
  "type": "Feature",
  "properties": {
    "addr:full":"44 Chatham Rd Newton MA 02461",
    "addr:housenumber":"44",
    "addr:postcode":"02461",
    "addr:street":"Chatham Rd",
    "iso:country":"US",
    "sg:address":"44 Chatham Rd",
    "sg:city":"Newton",
    "sg:classifiers":[
        {
            "category":"Health Services",
            "subcategory":"Doctor",
            "type":"Services"
        }
    ],
    "sg:phone":"+1   ",
    "sg:postcode":"02461",
    "sg:province":"MA",
    "sg:tags":[
        "specialist"
    ],
    "wof:name":"Richard S Beaser MD",
    "wof:placetype":"venue"
},
  "geometry": {"coordinates":[-71.215892,42.325329],"type":"Point"}
}