{
  "type": "Feature",
  "properties": {
    "iso:country":"US",
    "sg:address":"65 Industrial Way",
    "sg:city":"Wilmington",
    "sg:classifiers":[
        {
            "category":"Home & Garden",
            "subcategory":"Furniture",
            "type":"Retail Goods"
        }
    ],
    "sg:phone":"+1 978 988 9088",
    "sg:postcode":"01887",
    "sg:province":"MA",
    "sg:tags":[
        "top",
        "counter"
    ],
    "wof:name":"E-Top Supply",
    "wof:placetype":"venue"
},
  "geometry": {"coordinates":[-71.13651900000001,42.533473],"type":"Point"}
}