{
  "type": "Feature",
  "properties": {
    "iso:country":"US",
    "sg:address":"110 2nd St",
    "sg:city":"Cambridge",
    "sg:classifiers":[
        {
            "category":"Real Estate",
            "subcategory":"Real Estate Operator",
            "type":"Services"
        }
    ],
    "sg:phone":"+1 617 783 0039",
    "sg:postcode":"02141",
    "sg:province":"MA",
    "sg:tags":[
        "apartment"
    ],
    "sg:website":"www.thehamiltoncompany.com/resid...",
    "wof:name":"Charles Passage",
    "wof:placetype":"venue"
},
  "geometry": {"coordinates":[-71.07924300000001,42.367944],"type":"Point"}
}