{
  "type": "Feature",
  "properties": {
    "addr:full":"35 Central St Stoneham MA 02180",
    "addr:housenumber":"35",
    "addr:postcode":"02180",
    "addr:street":"Central St",
    "iso:country":"US",
    "sg:address":"35 Central St",
    "sg:city":"Stoneham",
    "sg:classifiers":[
        {
            "category":"Government",
            "subcategory":"Office",
            "type":"Public Place"
        }
    ],
    "sg:phone":"+1 781 279 2610",
    "sg:postcode":"02180",
    "sg:province":"MA",
    "sg:tags":[
        "village"
    ],
    "wof:name":"Personnel Office",
    "wof:placetype":"venue"
},
  "geometry": {"coordinates":[-71.098884,42.480663],"type":"Point"}
}