{
  "type": "Feature",
  "properties": {
    "addr:full":"650 Cambridge St Cambridge MA 02141",
    "addr:housenumber":"650",
    "addr:postcode":"02141",
    "addr:street":"Cambridge St",
    "iso:country":"US",
    "sg:address":"650 Cambridge St",
    "sg:city":"Cambridge",
    "sg:classifiers":[
        {
            "category":"Shopping",
            "subcategory":"Department Store",
            "type":"Retail Goods"
        }
    ],
    "sg:phone":"+1 617 225 0012",
    "sg:postcode":"02141",
    "sg:province":"MA",
    "sg:website":"www.errolmorris.com",
    "wof:name":"Globe Department Store",
    "wof:placetype":"venue"
},
  "geometry": {"coordinates":[-71.08726799999999,42.371891],"type":"Point"}
}