{
  "type": "Feature",
  "properties": {
    "iso:country":"US",
    "sg:address":"769 Plain St",
    "sg:city":"Marshfield",
    "sg:classifiers":[
        {
            "category":"Professional",
            "subcategory":"Management & Consulting",
            "type":"Services"
        }
    ],
    "sg:phone":"+1 781 319 9886",
    "sg:postcode":"02050",
    "sg:province":"MA",
    "sg:tags":[
        "consultant",
        "training"
    ],
    "wof:name":"Boston Training Collaborative",
    "wof:placetype":"venue"
},
  "geometry": {"coordinates":[-70.74822399999999,42.106224],"type":"Point"}
}