{
  "type": "Feature",
  "properties": {
    "addr:full": "70 Spectacle Hill Rd Bolton MA 01740",
    "addr:housenumber": "70",
    "addr:postcode": "01740",
    "addr:street": "Spectacle Hill Rd",
    "iso:country": "US",
    "sg:address": "70 Spectacle Hill Rd",
    "sg:city": "Bolton",
    "sg:classifiers": [
      {
        "category": "Retail",
        "subcategory": "Auto Repair",
        "type": "Services"
      }
    ],
    "sg:phone": "+1 978 779 5445",
    "sg:postcode": "01740",
    "sg:province": "MA",
    "sg:tags": [
      "repairing",
      "automobile"
    ],
    "wof:name": "Mitchell Motors",
    "wof:placetype": "venue"
  },
  "geometry": {"coordinates":[-71.59868,42.406592],"type":"Point"}
}
