{
  "type": "Feature",
  "properties": {
    "iso:country":"US",
    "sg:address":"28 Penniman Rd",
    "sg:city":"Brookline",
    "sg:classifiers":[
        {
            "category":"Real Estate",
            "subcategory":"Real Estate Agent",
            "type":"Services"
        }
    ],
    "sg:phone":"+1 617 782 4520",
    "sg:postcode":"02445",
    "sg:province":"MA",
    "sg:tags":[
        "consultant"
    ],
    "wof:name":"Henry Joseph & Assoc",
    "wof:placetype":"venue"
},
  "geometry": {"coordinates":[-71.149518,42.333986],"type":"Point"}
}