{
  "type": "Feature",
  "properties": {
    "iso:country":"US",
    "sg:address":"63 Canal Rd",
    "sg:city":"Orleans",
    "sg:classifiers":[
        {
            "category":"Organizations",
            "subcategory":"Religious Organization",
            "type":"Services"
        }
    ],
    "sg:phone":"+1 508 255 5096",
    "sg:postcode":"02653",
    "sg:province":"MA",
    "sg:tags":[
        "church"
    ],
    "wof:name":"St Joan Of Arc Church",
    "wof:placetype":"venue"
},
  "geometry": {"coordinates":[-69.987038,41.79678],"type":"Point"}
}