{
  "type": "Feature",
  "properties": {
    "iso:country":"US",
    "sg:address":"485 Andover St",
    "sg:city":"North Andover",
    "sg:classifiers":[
        {
            "category":"Professional",
            "subcategory":"Lawyer & Legal Services",
            "type":"Services"
        }
    ],
    "sg:phone":"+1 978 683 1313",
    "sg:postcode":"01845",
    "sg:province":"MA",
    "sg:tags":[
        "attorney"
    ],
    "wof:name":"Robert O'Neill Law Offices",
    "wof:placetype":"venue"
},
  "geometry": {"coordinates":[-71.12673599999999,42.672096],"type":"Point"}
}