{
  "type": "Feature",
  "properties": {
    "addr:full": "485 Andover St North Andover MA 01845",
    "addr:housenumber": "485",
    "addr:postcode": "01845",
    "addr:street": "Andover St",
    "iso:country": "US",
    "sg:address": "485 Andover St",
    "sg:city": "North Andover",
    "sg:classifiers": [
      {
        "category": "Professional",
        "subcategory": "Lawyer \u0026 Legal Services",
        "type": "Services"
      }
    ],
    "sg:phone": "+1 978 683 1313",
    "sg:postcode": "01845",
    "sg:province": "MA",
    "sg:tags": [
      "attorney"
    ],
    "wof:name": "Robert O'Neill Law Offices",
    "wof:placetype": "venue"
  },
  "geometry": {"coordinates":[-71.126736,42.672096],"type":"Point"}
}
