{
  "type": "Feature",
  "properties": {
    "addr:full":"1855 Beacon Street Brookline MA 02445",
    "addr:housenumber":"1855",
    "addr:postcode":"02445",
    "addr:street":"Beacon Street",
    "iso:country":"US",
    "sg:address":"1855 Beacon Street",
    "sg:city":"Brookline",
    "sg:classifiers":[
        {
            "category":"Professional",
            "subcategory":"Lawyer & Legal Services",
            "type":"Services"
        }
    ],
    "sg:phone":"+1 617 277 2101",
    "sg:postcode":"02445",
    "sg:province":"MA",
    "wof:name":"Wilson Susan Atty",
    "wof:placetype":"venue"
},
  "geometry": {"coordinates":[-71.145748,42.336744],"type":"Point"}
}