{
  "type": "Feature",
  "properties": {
    "addr:full": "100 John St Tewksbury MA 01876",
    "addr:housenumber": "100",
    "addr:postcode": "01876",
    "addr:street": "John St",
    "iso:country": "US",
    "sg:address": "100 John St",
    "sg:city": "Tewksbury",
    "sg:classifiers": [
      {
        "category": "Professional",
        "subcategory": "Lawyer \u0026 Legal Services",
        "type": "Services"
      }
    ],
    "sg:phone": "+1 978 569 1111",
    "sg:postcode": "01876",
    "sg:province": "MA",
    "sg:tags": [
      "attorney"
    ],
    "wof:name": "Duval \u0026 Assoc",
    "wof:placetype": "venue"
  },
  "geometry": {"coordinates":[-71.229603,42.593024],"type":"Point"}
}
