{
  "type": "Feature",
  "properties": {
    "addr:full":"107 Main St Charlemont MA 01339",
    "addr:housenumber":"107",
    "addr:postcode":"01339",
    "addr:street":"Main St",
    "iso:country":"US",
    "sg:address":"107 Main St",
    "sg:city":"Charlemont",
    "sg:classifiers":[
        {
            "category":"Banks & Credit Unions",
            "subcategory":"Bank",
            "type":"Services"
        }
    ],
    "sg:phone":"+1 413 337 4062",
    "sg:postcode":"01339",
    "sg:province":"MA",
    "sg:tags":[
        "cashing",
        "check"
    ],
    "wof:name":"Grahams Check Cashing Inc",
    "wof:placetype":"venue"
},
  "geometry": {"coordinates":[-72.875376,42.627872],"type":"Point"}
}