{
  "type": "Feature",
  "properties": {
    "iso:country":"US",
    "sg:address":"274 Westfield St",
    "sg:city":"West Springfield",
    "sg:classifiers":[
        {
            "category":"Retail",
            "subcategory":"Repair Shop",
            "type":"Services"
        }
    ],
    "sg:phone":"+1 413 737 4117",
    "sg:postcode":"01089",
    "sg:province":"MA",
    "sg:tags":[
        "electrical",
        "main",
        "computer"
    ],
    "wof:name":"Samtronix Inc",
    "wof:placetype":"venue"
},
  "geometry": {"coordinates":[-72.627914,42.105558],"type":"Point"}
}