{
  "type": "Feature",
  "properties": {
    "addr:full": "420 Boylston St Boston MA 02116",
    "addr:housenumber": "420",
    "addr:postcode": "02116",
    "addr:street": "Boylston St",
    "iso:country": "US",
    "sg:address": "420 Boylston St",
    "sg:city": "Boston",
    "sg:classifiers": [
      {
        "category": "Social Services",
        "type": "Services"
      },
      {
        "category": "Organizations",
        "subcategory": "Non-profit Organization",
        "type": "Services"
      }
    ],
    "sg:phone": "+1 617 266 7534",
    "sg:postcode": "02116",
    "sg:province": "MA",
    "sg:tags": [
      "charity",
      "foundations-educational",
      "philanthropic",
      "research"
    ],
    "wof:name": "Unicef Us Fund",
    "wof:placetype": "venue"
  },
  "geometry": {"coordinates":[-71.072627,42.351344],"type":"Point"}
}
