{
  "type": "Feature",
  "properties": {
    "iso:country":"US",
    "sg:address":"1105 Massachusetts Ave",
    "sg:city":"Cambridge",
    "sg:classifiers":[
        {
            "category":"Shopping",
            "subcategory":"Clothing, Apparel, & Fashions",
            "type":"Retail Goods"
        }
    ],
    "sg:phone":"+1 617 498 0999",
    "sg:postcode":"02138",
    "sg:province":"MA",
    "sg:tags":[
        "vintage",
        "period",
        "clothing-collectible",
        "clothing",
        "store"
    ],
    "sg:website":"http://www.vintagerevenge.net",
    "wof:name":"Vintage Revenge",
    "wof:placetype":"venue"
},
  "geometry": {"coordinates":[-71.113589,42.370576],"type":"Point"}
}