{
  "type": "Feature",
  "properties": {
    "addr:full": "85 Cedar Cliff Rd Braintree MA 02184",
    "addr:housenumber": "85",
    "addr:postcode": "02184",
    "addr:street": "Cedar Cliff Rd",
    "iso:country": "US",
    "sg:address": "85 Cedar Cliff Rd",
    "sg:city": "Braintree",
    "sg:classifiers": [
      {
        "category": "Manufacturing",
        "subcategory": "Metals",
        "type": "Manufacturing \u0026 Wholesale Goods"
      }
    ],
    "sg:phone": "+1 781 843 2873",
    "sg:postcode": "02184",
    "sg:province": "MA",
    "sg:tags": [
      "hardware"
    ],
    "wof:name": "Inline Technical Svc",
    "wof:placetype": "venue"
  },
  "geometry": {"coordinates":[-70.974077,42.224353],"type":"Point"}
}
