{
  "type": "Feature",
  "properties": {
    "iso:country":"US",
    "sg:address":"85 Cedar Cliff Rd",
    "sg:city":"Braintree",
    "sg:classifiers":[
        {
            "category":"Manufacturing",
            "subcategory":"Metals",
            "type":"Manufacturing & Wholesale Goods"
        }
    ],
    "sg:phone":"+1 781 843 2873",
    "sg:postcode":"02184",
    "sg:province":"MA",
    "sg:tags":[
        "hardware"
    ],
    "wof:name":"Inline Technical Svc",
    "wof:placetype":"venue"
},
  "geometry": {"coordinates":[-70.97407699999999,42.224353],"type":"Point"}
}