{
  "type": "Feature",
  "properties": {
    "addr:full": "10 Roessler Rd Woburn MA 01801",
    "addr:housenumber": "10",
    "addr:postcode": "01801",
    "addr:street": "Roessler Rd",
    "iso:country": "US",
    "sg:address": "10 Roessler Rd",
    "sg:city": "Woburn",
    "sg:classifiers": [
      {
        "category": "Utilities",
        "subcategory": "Telephone",
        "type": "Services"
      }
    ],
    "sg:phone": "+1   ",
    "sg:postcode": "01801",
    "sg:province": "MA",
    "sg:tags": [
      "communications"
    ],
    "wof:name": "Sanz Inc",
    "wof:placetype": "venue"
  },
  "geometry": {"coordinates":[-71.143593,42.510209],"type":"Point"}
}
