{
  "type": "Feature",
  "properties": {
    "addr:full": "90 Park Ave Natick MA 01760",
    "addr:housenumber": "90",
    "addr:postcode": "01760",
    "addr:street": "Park Ave",
    "iso:country": "US",
    "sg:address": "90 Park Ave",
    "sg:city": "Natick",
    "sg:classifiers": [
      {
        "category": "Professional",
        "subcategory": "Computer Services",
        "type": "Services"
      }
    ],
    "sg:phone": "+1 508 650 9917",
    "sg:postcode": "01760",
    "sg:province": "MA",
    "sg:tags": [
      "repair"
    ],
    "sg:website": "www.thecomputerguys.com",
    "wof:name": "Computer Guys Inc",
    "wof:placetype": "venue"
  },
  "geometry": {"coordinates":[-71.355911,42.300107],"type":"Point"}
}
