{
  "type": "Feature",
  "properties": {
    "iso:country":"US",
    "sg:address":"90 Park Ave",
    "sg:city":"Natick",
    "sg:classifiers":[
        {
            "category":"Professional",
            "subcategory":"Computer Services",
            "type":"Services"
        }
    ],
    "sg:phone":"+1 508 650 9917",
    "sg:postcode":"01760",
    "sg:province":"MA",
    "sg:tags":[
        "repair"
    ],
    "sg:website":"www.thecomputerguys.com",
    "wof:name":"Computer Guys Inc",
    "wof:placetype":"venue"
},
  "geometry": {"coordinates":[-71.35591100000001,42.300107],"type":"Point"}
}