{
  "type": "Feature",
  "properties": {
    "addr:full": "1 Walker Ct Gloucester MA 01930",
    "addr:housenumber": "1",
    "addr:postcode": "01930",
    "addr:street": "Walker Ct",
    "iso:country": "US",
    "sg:address": "1 Walker Ct",
    "sg:city": "Gloucester",
    "sg:classifiers": [
      {
        "category": "Building \u0026 Trades",
        "subcategory": "Construction",
        "type": "Services"
      }
    ],
    "sg:phone": "+1 978 283 6616",
    "sg:postcode": "01930",
    "sg:province": "MA",
    "sg:tags": [
      "general",
      "contractor"
    ],
    "wof:name": "Performance Excavation",
    "wof:placetype": "venue"
  },
  "geometry": {"coordinates":[-70.741353,42.63117],"type":"Point"}
}
