{
  "type": "Feature",
  "properties": {
    "iso:country":"US",
    "sg:address":"300 Bent St",
    "sg:city":"Cambridge",
    "sg:classifiers":[
        {
            "category":"Personal",
            "type":"Services"
        }
    ],
    "sg:phone":"+1 617 475 9000",
    "sg:postcode":"02141",
    "sg:province":"MA",
    "sg:tags":[
        "dating"
    ],
    "wof:name":"Lavalife",
    "wof:placetype":"venue"
},
  "geometry": {"coordinates":[-71.086967,42.367628],"type":"Point"}
}