{
  "type": "Feature",
  "properties": {
    "addr:full": "9 Gary Ln North Easton MA 02356",
    "addr:housenumber": "9",
    "addr:postcode": "02356",
    "addr:street": "Gary Ln",
    "iso:country": "US",
    "sg:address": "9 Gary Ln",
    "sg:city": "North Easton",
    "sg:classifiers": [
      {
        "category": "Building \u0026 Trades",
        "subcategory": "Construction",
        "type": "Services"
      }
    ],
    "sg:phone": "+1 508 230 8166",
    "sg:postcode": "02356",
    "sg:province": "MA",
    "sg:tags": [
      "contractor"
    ],
    "wof:name": "Colangelo Construction",
    "wof:placetype": "venue"
  },
  "geometry": {"coordinates":[-71.099062,42.049725],"type":"Point"}
}
