{
  "type": "Feature",
  "properties": {
    "addr:full": "690 Depot St North Easton MA 02356",
    "addr:housenumber": "690",
    "addr:postcode": "02356",
    "addr:street": "Depot St",
    "iso:country": "US",
    "ovtr:label": "Citizens Bank, 690 Depot St North Easton MA US",
    "ovtr:similarity": 2.3145790100097656,
    "sg:address": "690 Depot St",
    "sg:city": "North Easton",
    "sg:classifiers": [
      {
        "category": "Banks \u0026 Credit Unions",
        "subcategory": "Bank",
        "type": "Services"
      }
    ],
    "sg:phone": "+1 508 230 3578",
    "sg:postcode": "02356",
    "sg:province": "MA",
    "wof:name": "Citizens Bank",
    "wof:placetype": "venue"
  },
  "geometry": {"coordinates":[-71.119042,42.024517],"type":"Point"}
}
