{
  "type": "Feature",
  "properties": {
    "iso:country":"US",
    "sg:address":"12 Shawmut Ave Exd",
    "sg:city":"Wayland",
    "sg:classifiers":[
        {
            "category":"Professional",
            "subcategory":"Management & Consulting",
            "type":"Services"
        }
    ],
    "sg:phone":"+1   ",
    "sg:postcode":"01778",
    "sg:province":"MA",
    "sg:tags":[
        "business"
    ],
    "wof:name":"N B Consulting Corporation",
    "wof:placetype":"venue"
},
  "geometry": {"coordinates":[-71.368414,42.319562],"type":"Point"}
}