{
  "type": "Feature",
  "properties": {
    "iso:country":"US",
    "sg:address":"507 High St",
    "sg:city":"Medford",
    "sg:classifiers":[
        {
            "category":"Shopping",
            "subcategory":"Jewelry",
            "type":"Retail Goods"
        }
    ],
    "sg:phone":"+1 781 646 6300",
    "sg:postcode":"02155",
    "sg:province":"MA",
    "sg:website":"www.nataliesjewelers.com",
    "wof:name":"Natalie's Jewelers",
    "wof:placetype":"venue"
},
  "geometry": {"coordinates":[-71.133354,42.421311],"type":"Point"}
}