{
  "type": "Feature",
  "properties": {
    "iso:country":"US",
    "sg:address":"999 S Washington St",
    "sg:city":"North Attleboro",
    "sg:classifiers":[
        {
            "category":"Shopping",
            "subcategory":"Jewelry",
            "type":"Retail Goods"
        }
    ],
    "sg:phone":"+1 508 643 9539",
    "sg:postcode":"02760",
    "sg:province":"MA",
    "wof:name":"Arias Jewelers",
    "wof:placetype":"venue"
},
  "geometry": {"coordinates":[-71.323898,41.976101],"type":"Point"}
}