{
  "type": "Feature",
  "properties": {
    "addr:full": "43 Thorndike St Ste 2 Cambridge MA 02141",
    "addr:housenumber": "43",
    "addr:postcode": "02141",
    "addr:street": "Thorndike St Ste 2",
    "iso:country": "US",
    "sg:address": "43 Thorndike St Ste 2",
    "sg:city": "Cambridge",
    "sg:classifiers": [
      {
        "category": "Professional",
        "subcategory": "Lawyer \u0026 Legal Services",
        "type": "Services"
      }
    ],
    "sg:phone": "+1 617 621 3333",
    "sg:postcode": "02141",
    "sg:province": "MA",
    "wof:name": "O'neill and Young PC",
    "wof:placetype": "venue"
  },
  "geometry": {"coordinates":[-71.079498,42.369598],"type":"Point"}
}
