{
  "type": "Feature",
  "properties": {
    "addr:full": "6 West Rd Orleans MA 02653",
    "addr:housenumber": "6",
    "addr:postcode": "02653",
    "addr:street": "West Rd",
    "iso:country": "US",
    "sg:address": "6 West Rd",
    "sg:city": "Orleans",
    "sg:classifiers": [
      {
        "category": "Autos \u0026 Motor Vehicles",
        "subcategory": "Automobile Sales",
        "type": "Retail Goods"
      }
    ],
    "sg:phone": "+1 508 240 7978",
    "sg:postcode": "02653",
    "sg:province": "MA",
    "sg:tags": [
      "new",
      "car"
    ],
    "wof:name": "Hyannis Honda",
    "wof:placetype": "venue"
  },
  "geometry": {"coordinates":[-70.00024,41.780703],"type":"Point"}
}
