{
  "type": "Feature",
  "properties": {
    "addr:full": "315 Cabot St Beverly MA 01915",
    "addr:housenumber": "315",
    "addr:postcode": "01915",
    "addr:street": "Cabot St",
    "iso:country": "US",
    "sg:address": "315 Cabot St",
    "sg:city": "Beverly",
    "sg:classifiers": [
      {
        "category": "Personal",
        "subcategory": "Beauty Salon",
        "type": "Services"
      }
    ],
    "sg:phone": "+1 978 922 7980",
    "sg:postcode": "01915",
    "sg:province": "MA",
    "wof:name": "Jeanne At Spectrum Hair \u0026 Nail",
    "wof:placetype": "venue"
  },
  "geometry": {"coordinates":[-70.8786,42.552998],"type":"Point"}
}
