{
  "type": "Feature",
  "properties": {
    "iso:country":"US",
    "sg:address":"315 Cabot St",
    "sg:city":"Beverly",
    "sg:classifiers":[
        {
            "category":"Personal",
            "subcategory":"Beauty Salon",
            "type":"Services"
        }
    ],
    "sg:phone":"+1 978 922 7980",
    "sg:postcode":"01915",
    "sg:province":"MA",
    "wof:name":"Jeanne At Spectrum Hair & Nail",
    "wof:placetype":"venue"
},
  "geometry": {"coordinates":[-70.87860000000001,42.552998],"type":"Point"}
}