{
  "type": "Feature",
  "properties": {
    "iso:country":"US",
    "sg:address":"91 Summer St",
    "sg:city":"Boston",
    "sg:classifiers":[
        {
            "category":"Restaurant",
            "type":"Food & Drink"
        }
    ],
    "sg:menulink":"http://www.allmenus.com/ma/boston/257-burger-king/menu/",
    "sg:phone":"+1 617 350 6126",
    "sg:postcode":"02110",
    "sg:province":"MA",
    "sg:tags":[
        "burger",
        "american"
    ],
    "wof:name":"Burger King",
    "wof:placetype":"venue"
},
  "geometry": {"coordinates":[-71.058325,42.353987],"type":"Point"}
}