{
  "type": "Feature",
  "properties": {
    "iso:country":"US",
    "sg:address":"1492 Grand Army Hwy",
    "sg:city":"Swansea",
    "sg:classifiers":[
        {
            "category":"Professional",
            "type":"Services"
        }
    ],
    "sg:phone":"+1   ",
    "sg:postcode":"02777",
    "sg:province":"MA",
    "wof:name":"Columbus Energies Inc",
    "wof:placetype":"venue"
},
  "geometry": {"coordinates":[-71.23925,41.754387],"type":"Point"}
}