{
  "type": "Feature",
  "properties": {
    "addr:full": "13 Franklin St Salem MA 01970",
    "addr:housenumber": "13",
    "addr:postcode": "01970",
    "addr:street": "Franklin St",
    "iso:country": "US",
    "ovtr:label": "Auto Haus Import Auto Care, 17 Franklin St Salem MA US",
    "ovtr:similarity": 3.016645908355713,
    "sg:address": "13 Franklin St",
    "sg:city": "Salem",
    "sg:classifiers": [
      {
        "category": "Retail",
        "subcategory": "Auto Repair",
        "type": "Services"
      }
    ],
    "sg:phone": "+1 978 745 1118",
    "sg:postcode": "01970",
    "sg:province": "MA",
    "sg:tags": [
      "repairing",
      "automobile"
    ],
    "wof:name": "Auto Haus Import Auto Care",
    "wof:placetype": "venue"
  },
  "geometry": {"coordinates":[-70.899547,42.525728],"type":"Point"}
}
