{
  "type": "Feature",
  "properties": {
    "iso:country":"US",
    "sg:address":"13 Franklin St",
    "sg:city":"Salem",
    "sg:classifiers":[
        {
            "category":"Retail",
            "subcategory":"Auto Repair",
            "type":"Services"
        }
    ],
    "sg:phone":"+1 978 745 1118",
    "sg:postcode":"01970",
    "sg:province":"MA",
    "sg:tags":[
        "repairing",
        "automobile"
    ],
    "wof:name":"Auto Haus Import Auto Care",
    "wof:placetype":"venue"
},
  "geometry": {"coordinates":[-70.899547,42.525728],"type":"Point"}
}