{
  "type": "Feature",
  "properties": {
    "iso:country":"US",
    "sg:address":"5 Bolton St",
    "sg:city":"Cambridge",
    "sg:classifiers":[
        {
            "category":"Health Services",
            "subcategory":"Optometrist",
            "type":"Services"
        }
    ],
    "sg:phone":"+1 617 497 6753",
    "sg:postcode":"02140",
    "sg:province":"MA",
    "wof:name":"Cambridge Vision Specialist",
    "wof:placetype":"venue"
},
  "geometry": {"coordinates":[-71.131844,42.390208],"type":"Point"}
}