{
  "type": "Feature",
  "properties": {
    "iso:country":"US",
    "sg:address":"552 Massachusetts Ave Ste 203",
    "sg:city":"Cambridge",
    "sg:classifiers":[
        {
            "category":"Health Services",
            "subcategory":"Clinic",
            "type":"Services"
        }
    ],
    "sg:phone":"+1 617 441 0700",
    "sg:postcode":"02139",
    "sg:province":"MA",
    "sg:tags":[
        "information",
        "outpatient",
        "alcoholism",
        "treatment"
    ],
    "sg:website":"http://www.mountauburneap.org",
    "wof:name":"Massachusetts Prevention",
    "wof:placetype":"venue"
},
  "geometry": {"coordinates":[-71.102278,42.364535],"type":"Point"}
}