{
  "type": "Feature",
  "properties": {
    "addr:full": "1786 Washington St Roxbury MA 02118",
    "addr:housenumber": "1786",
    "addr:postcode": "02118",
    "addr:street": "Washington St",
    "iso:country": "US",
    "sg:address": "1786 Washington St",
    "sg:city": "Roxbury",
    "sg:classifiers": [
      {
        "category": "Insurance",
        "subcategory": "Insurance Agent",
        "type": "Services"
      }
    ],
    "sg:phone": "+1 617 541 1700",
    "sg:postcode": "02118",
    "sg:province": "MA",
    "wof:name": "Comzer Insurance Brokerage",
    "wof:placetype": "venue"
  },
  "geometry": {"coordinates":[-71.078265,42.335451],"type":"Point"}
}
