{
  "type": "Feature",
  "properties": {
    "addr:full": "34 Main St Natick MA 01760",
    "addr:housenumber": "34",
    "addr:postcode": "01760",
    "addr:street": "Main St",
    "iso:country": "US",
    "sg:address": "34 Main St",
    "sg:city": "Natick",
    "sg:classifiers": [
      {
        "category": "Professional",
        "subcategory": "Advertising",
        "type": "Services"
      }
    ],
    "sg:phone": "+1 508 650 3972",
    "sg:postcode": "01760",
    "sg:province": "MA",
    "sg:tags": [
      "counselor"
    ],
    "sg:website": "www.sundininc.com",
    "wof:name": "Sundin Associates",
    "wof:placetype": "venue"
  },
  "geometry": {"coordinates":[-71.347729,42.285498],"type":"Point"}
}
