{
  "type": "Feature",
  "properties": {
    "addr:full": "18 Cambria St Somerville MA 02143",
    "addr:housenumber": "18",
    "addr:postcode": "02143",
    "addr:street": "Cambria St",
    "iso:country": "US",
    "sg:address": "18 Cambria St",
    "sg:city": "Somerville",
    "sg:classifiers": [
      {
        "category": "Building \u0026 Trades",
        "subcategory": "Construction",
        "type": "Services"
      }
    ],
    "sg:phone": "+1 617 625 3289",
    "sg:postcode": "02143",
    "sg:province": "MA",
    "sg:tags": [
      "repair",
      "handyman",
      "maintenance",
      "home"
    ],
    "wof:name": "Jeff Quateman Overeducated Handyman",
    "wof:placetype": "venue"
  },
  "geometry": {"coordinates":[-71.104474,42.387454],"type":"Point"}
}
