{
  "type": "Feature",
  "properties": {
    "addr:full":"378 Highland Ave Somerville MA 02144",
    "addr:housenumber":"378",
    "addr:postcode":"02144",
    "addr:street":"Highland Ave",
    "iso:country":"US",
    "sg:address":"378 Highland Ave",
    "sg:city":"Somerville",
    "sg:classifiers":[
        {
            "category":"Shopping",
            "subcategory":"Used Merchandise",
            "type":"Retail Goods"
        }
    ],
    "sg:phone":"+1 617 623 3330",
    "sg:postcode":"02144",
    "sg:province":"MA",
    "sg:tags":[
        "antique"
    ],
    "wof:name":"Magpie On Huron",
    "wof:placetype":"venue"
},
  "geometry": {"coordinates":[-71.11909799999999,42.394965],"type":"Point"}
}