{
  "type": "Feature",
  "properties": {
    "addr:full": "7 Summer St Ste 17-18 Chelmsford MA 01824",
    "addr:housenumber": "7",
    "addr:postcode": "01824",
    "addr:street": "Summer St Ste 17-18",
    "iso:country": "US",
    "ovtr:label": "Sichuan Palace, 7 Summer St Chelmsford MA US",
    "ovtr:similarity": 3.5864500999450684,
    "sg:address": "7 Summer St Ste 17-18",
    "sg:city": "Chelmsford",
    "sg:classifiers": [
      {
        "category": "Restaurant",
        "type": "Food \u0026 Drink"
      }
    ],
    "sg:phone": "+1 978 256 8545",
    "sg:postcode": "01824",
    "sg:province": "MA",
    "sg:tags": [
      "chinese"
    ],
    "sg:website": "www.sichuanpalacema.com",
    "wof:name": "Sichuan Palace",
    "wof:placetype": "venue"
  },
  "geometry": {"coordinates":[-71.349316,42.594062],"type":"Point"}
}
