{
  "type": "Feature",
  "properties": {
    "addr:full": "25 Mulberry St Haverhill MA 01830",
    "addr:housenumber": "25",
    "addr:postcode": "01830",
    "addr:street": "Mulberry St",
    "iso:country": "US",
    "sg:address": "25 Mulberry St",
    "sg:city": "Haverhill",
    "sg:classifiers": [
      {
        "category": "Retail",
        "subcategory": "Laundry \u0026 Dry Cleaning",
        "type": "Services"
      }
    ],
    "sg:phone": "+1 978 521 5720",
    "sg:postcode": "01830",
    "sg:province": "MA",
    "wof:name": "Heartland Commercial Laundry",
    "wof:placetype": "venue"
  },
  "geometry": {"coordinates":[-71.087749,42.781582],"type":"Point"}
}
