{
  "type": "Feature",
  "properties": {
    "addr:full": "124 Harvard Street Brookline MA 02446",
    "addr:housenumber": "124",
    "addr:postcode": "02446",
    "addr:street": "Harvard Street",
    "iso:country": "US",
    "sg:address": "124 Harvard Street",
    "sg:city": "Brookline",
    "sg:classifiers": [
      {
        "category": "Sports \u0026 Exercise",
        "subcategory": "Gym",
        "type": "Entertainment"
      }
    ],
    "sg:phone": "+1 617 232 4350",
    "sg:postcode": "02446",
    "sg:province": "MA",
    "sg:tags": [
      "trainer"
    ],
    "wof:name": "Rutter Anne Licsw",
    "wof:placetype": "venue"
  },
  "geometry": {"coordinates":[-71.120569,42.344361],"type":"Point"}
}
