{
  "type": "Feature",
  "properties": {
    "addr:full":"30 Carleton St Methuen MA 01844",
    "addr:housenumber":"30",
    "addr:postcode":"01844",
    "addr:street":"Carleton St",
    "iso:country":"US",
    "sg:address":"30 Carleton St",
    "sg:city":"Methuen",
    "sg:classifiers":[
        {
            "category":"Professional",
            "subcategory":"Management & Consulting",
            "type":"Services"
        },
        {
            "category":"Professional",
            "subcategory":"Business Services",
            "type":"Services"
        }
    ],
    "sg:phone":"+1 978 208 0552",
    "sg:postcode":"01844",
    "sg:province":"MA",
    "sg:tags":[
        "relation",
        "counselor",
        "publicity",
        "public"
    ],
    "wof:name":"Grant Communications",
    "wof:placetype":"venue"
},
  "geometry": {"coordinates":[-71.17912800000001,42.720241],"type":"Point"}
}