{
  "type": "Feature",
  "properties": {
    "iso:country":"US",
    "sg:address":"251 Pleasant Street",
    "sg:city":"Arlington",
    "sg:classifiers":[
        {
            "category":"Professional",
            "subcategory":"Research",
            "type":"Services"
        }
    ],
    "sg:phone":"+1 617 202 9156",
    "sg:postcode":"02476",
    "sg:province":"MA",
    "sg:website":"http://www.purposeenergy.com/",
    "wof:name":"PurposeEnergy",
    "wof:placetype":"venue"
},
  "geometry": {"coordinates":[-71.16030499999999,42.408046],"type":"Point"}
}