{
  "type": "Feature",
  "properties": {
    "addr:full":"1 Lockland Ave Framingham MA 01701",
    "addr:housenumber":"1",
    "addr:postcode":"01701",
    "addr:street":"Lockland Ave",
    "iso:country":"US",
    "sg:address":"1 Lockland Ave",
    "sg:city":"Framingham",
    "sg:classifiers":[
        {
            "category":"Personal",
            "subcategory":"Barber",
            "type":"Services"
        }
    ],
    "sg:phone":"+1 508 620 0550",
    "sg:postcode":"01701",
    "sg:province":"MA",
    "wof:name":"Shears",
    "wof:placetype":"venue"
},
  "geometry": {"coordinates":[-71.417728,42.299912],"type":"Point"}
}