{
  "type": "Feature",
  "properties": {
    "addr:full":"460 New Ludlow Rd Chicopee MA 01020",
    "addr:housenumber":"460",
    "addr:postcode":"01020",
    "addr:street":"New Ludlow Rd",
    "iso:country":"US",
    "sg:address":"460 New Ludlow Rd",
    "sg:city":"Chicopee",
    "sg:classifiers":[
        {
            "category":"Professional",
            "subcategory":"Employment Agencies",
            "type":"Services"
        }
    ],
    "sg:phone":"+1 413 536 3838",
    "sg:postcode":"01020",
    "sg:province":"MA",
    "sg:tags":[
        "employer"
    ],
    "wof:name":"Barthelette Bruce",
    "wof:placetype":"venue"
},
  "geometry": {"coordinates":[-72.562996,42.213208],"type":"Point"}
}