{
  "type": "Feature",
  "properties": {
    "addr:full": "2406 Cranberry Hwy Wareham MA 02571",
    "addr:housenumber": "2406",
    "addr:postcode": "02571",
    "addr:street": "Cranberry Hwy",
    "iso:country": "US",
    "sg:address": "2406 Cranberry Hwy",
    "sg:city": "Wareham",
    "sg:classifiers": [
      {
        "category": "Food \u0026 Beverages",
        "subcategory": "Bakery",
        "type": "Retail Goods"
      },
      {
        "category": "Bakery",
        "type": "Food \u0026 Drink"
      }
    ],
    "sg:phone": "+1 508 295 2337",
    "sg:postcode": "02571",
    "sg:province": "MA",
    "sg:tags": [
      "bakers-wholesale"
    ],
    "wof:name": "Nissen, John J Baking Company Inc",
    "wof:placetype": "venue"
  },
  "geometry": {"coordinates":[-70.73848,41.774736],"type":"Point"}
}
