{
  "type": "Feature",
  "properties": {
    "iso:country":"US",
    "sg:address":"2406 Cranberry Hwy",
    "sg:city":"Wareham",
    "sg:classifiers":[
        {
            "category":"Food & Beverages",
            "subcategory":"Bakery",
            "type":"Retail Goods"
        },
        {
            "category":"Bakery",
            "type":"Food & Drink"
        }
    ],
    "sg:phone":"+1 508 295 2337",
    "sg:postcode":"02571",
    "sg:province":"MA",
    "sg:tags":[
        "bakers-wholesale"
    ],
    "wof:name":"Nissen, John J Baking Company Inc",
    "wof:placetype":"venue"
},
  "geometry": {"coordinates":[-70.73848,41.774736],"type":"Point"}
}