{
  "type": "Feature",
  "properties": {
    "addr:full": "36 Sumner Rd Brookline MA 02445",
    "addr:housenumber": "36",
    "addr:postcode": "02445",
    "addr:street": "Sumner Rd",
    "iso:country": "US",
    "sg:address": "36 Sumner Rd",
    "sg:city": "Brookline",
    "sg:classifiers": [
      {
        "category": "Organizations",
        "subcategory": "Professional Association",
        "type": "Services"
      }
    ],
    "sg:phone": "+1 617 566 3238",
    "sg:postcode": "02445",
    "sg:province": "MA",
    "wof:name": "League Of Women Voters",
    "wof:placetype": "venue"
  },
  "geometry": {"coordinates":[-71.131474,42.331391],"type":"Point"}
}
