{
  "type": "Feature",
  "properties": {
    "iso:country":"US",
    "sg:address":"211 Lowell St",
    "sg:city":"Wilmington",
    "sg:classifiers":[
        {
            "category":"Food & Beverages",
            "subcategory":"Liquor & Beverages",
            "type":"Retail Goods"
        }
    ],
    "sg:phone":"+1 978 658 8650",
    "sg:postcode":"01887",
    "sg:province":"MA",
    "sg:tags":[
        "beer",
        "spirit",
        "wine"
    ],
    "wof:name":"East Gate Liquor",
    "wof:placetype":"venue"
},
  "geometry": {"coordinates":[-71.14919999999999,42.5396],"type":"Point"}
}