{
  "type": "Feature",
  "properties": {
    "addr:full": "1775 Washington St Hanover MA 02339",
    "addr:housenumber": "1775",
    "addr:postcode": "02339",
    "addr:street": "Washington St",
    "iso:country": "US",
    "sg:address": "1775 Washington St",
    "sg:city": "Hanover",
    "sg:classifiers": [
      {
        "category": "Health Services",
        "subcategory": "Doctor",
        "type": "Services"
      }
    ],
    "sg:phone": "+1 781 826 8866",
    "sg:postcode": "02339",
    "sg:province": "MA",
    "sg:tags": [
      "dentist"
    ],
    "wof:name": "Unident Dental Ctr",
    "wof:placetype": "venue"
  },
  "geometry": {"coordinates":[-70.845333,42.147529],"type":"Point"}
}
