{
  "type": "Feature",
  "properties": {
    "addr:full": "171 Reservoir St Needham MA 02494",
    "addr:housenumber": "171",
    "addr:postcode": "02494",
    "addr:street": "Reservoir St",
    "iso:country": "US",
    "sg:address": "171 Reservoir St",
    "sg:city": "Needham",
    "sg:classifiers": [
      {
        "category": "Building \u0026 Trades",
        "subcategory": "Construction",
        "type": "Services"
      }
    ],
    "sg:phone": "+1 781 237 0505",
    "sg:postcode": "02494",
    "sg:province": "MA",
    "sg:tags": [
      "contractor"
    ],
    "wof:name": "Fallon Development Inc",
    "wof:placetype": "venue"
  },
  "geometry": {"coordinates":[-71.228631,42.310829],"type":"Point"}
}
