{
  "type": "Feature",
  "properties": {
    "iso:country":"US",
    "sg:address":"171 Reservoir St",
    "sg:city":"Needham",
    "sg:classifiers":[
        {
            "category":"Building & Trades",
            "subcategory":"Construction",
            "type":"Services"
        }
    ],
    "sg:phone":"+1 781 237 0505",
    "sg:postcode":"02494",
    "sg:province":"MA",
    "sg:tags":[
        "contractor"
    ],
    "wof:name":"Fallon Development Inc",
    "wof:placetype":"venue"
},
  "geometry": {"coordinates":[-71.22863099999999,42.310829],"type":"Point"}
}