{
  "type": "Feature",
  "properties": {
    "iso:country":"US",
    "sg:address":"63 Morgan St",
    "sg:city":"New Bedford",
    "sg:classifiers":[
        {
            "category":"Professional",
            "type":"Services"
        }
    ],
    "sg:phone":"+1   ",
    "sg:postcode":"02740",
    "sg:province":"MA",
    "wof:name":"Amy Gracia",
    "wof:placetype":"venue"
},
  "geometry": {"coordinates":[-70.934611,41.634849],"type":"Point"}
}