{
  "type": "Feature",
  "properties": {
    "iso:country":"US",
    "sg:address":"370 S Main St",
    "sg:city":"Hopedale",
    "sg:classifiers":[
        {
            "category":"Home & Garden",
            "subcategory":"Garden Supply",
            "type":"Retail Goods"
        }
    ],
    "sg:phone":"+1 508 473 0908",
    "sg:postcode":"01747",
    "sg:province":"MA",
    "sg:tags":[
        "mulch"
    ],
    "wof:name":"R Bethel Son Inc",
    "wof:placetype":"venue"
},
  "geometry": {"coordinates":[-71.504583,42.104497],"type":"Point"}
}