{
  "type": "Feature",
  "properties": {
    "addr:full": "20 Locust St Danvers MA 01923",
    "addr:housenumber": "20",
    "addr:postcode": "01923",
    "addr:street": "Locust St",
    "iso:country": "US",
    "sg:address": "20 Locust St",
    "sg:city": "Danvers",
    "sg:classifiers": [
      {
        "category": "Building \u0026 Trades",
        "subcategory": "Construction",
        "type": "Services"
      }
    ],
    "sg:phone": "+1 978 774 4420",
    "sg:postcode": "01923",
    "sg:province": "MA",
    "sg:tags": [
      "designer"
    ],
    "wof:name": "Robert De Felice Assoc",
    "wof:placetype": "venue"
  },
  "geometry": {"coordinates":[-70.937918,42.568455],"type":"Point"}
}
