{
  "type": "Feature",
  "properties": {
    "addr:full": "27 Market Sq Lynn MA 01905",
    "addr:housenumber": "27",
    "addr:postcode": "01905",
    "addr:street": "Market Sq",
    "iso:country": "US",
    "sg:address": "27 Market Sq",
    "sg:city": "Lynn",
    "sg:classifiers": [
      {
        "category": "Professional",
        "subcategory": "Advertising",
        "type": "Services"
      }
    ],
    "sg:phone": "+1 781 581 1718",
    "sg:postcode": "01905",
    "sg:province": "MA",
    "sg:tags": [
      "distributing",
      "sample"
    ],
    "wof:name": "Latino Travel",
    "wof:placetype": "venue"
  },
  "geometry": {"coordinates":[-70.964875,42.462607],"type":"Point"}
}
