{
  "type": "Feature",
  "properties": {
    "iso:country":"US",
    "sg:address":"27 Market Sq",
    "sg:city":"Lynn",
    "sg:classifiers":[
        {
            "category":"Professional",
            "subcategory":"Advertising",
            "type":"Services"
        }
    ],
    "sg:phone":"+1 781 581 1718",
    "sg:postcode":"01905",
    "sg:province":"MA",
    "sg:tags":[
        "distributing",
        "sample"
    ],
    "wof:name":"Latino Travel",
    "wof:placetype":"venue"
},
  "geometry": {"coordinates":[-70.96487500000001,42.462607],"type":"Point"}
}