{
  "type": "Feature",
  "properties": {
    "iso:country":"US",
    "sg:address":"206 E Main St",
    "sg:city":"Milford",
    "sg:classifiers":[
        {
            "category":"Real Estate",
            "subcategory":"Real Estate Agent",
            "type":"Services"
        }
    ],
    "sg:phone":"+1 508 482 9444",
    "sg:postcode":"01757",
    "sg:province":"MA",
    "wof:name":"Prudential Premium Properties",
    "wof:placetype":"venue"
},
  "geometry": {"coordinates":[-71.500176,42.150921],"type":"Point"}
}