{
  "type": "Feature",
  "properties": {
    "iso:country":"US",
    "sg:address":"371 Main St",
    "sg:city":"Brockton",
    "sg:classifiers":[
        {
            "category":"Health Services",
            "subcategory":"Clinic",
            "type":"Services"
        }
    ],
    "sg:phone":"+1 508 559 6510",
    "sg:postcode":"02301",
    "sg:province":"MA",
    "sg:tags":[
        "aids",
        "testing",
        "information"
    ],
    "wof:name":"Brockton Area Aids Consortium",
    "wof:placetype":"venue"
},
  "geometry": {"coordinates":[-71.019712,42.077507],"type":"Point"}
}