{
  "type": "Feature",
  "properties": {
    "addr:full": "255 Park Ave Worcester MA 01609",
    "addr:housenumber": "255",
    "addr:postcode": "01609",
    "addr:street": "Park Ave",
    "iso:country": "US",
    "ovtr:label": "Worcester Endodontics, 255 Park Ave Worcester MA US",
    "ovtr:similarity": 3.1775588989257812,
    "sg:address": "255 Park Ave",
    "sg:city": "Worcester",
    "sg:classifiers": [
      {
        "category": "Health Services",
        "subcategory": "Doctor",
        "type": "Services"
      }
    ],
    "sg:phone": "+1 508 755 3636",
    "sg:postcode": "01609",
    "sg:province": "MA",
    "sg:tags": [
      "dentist"
    ],
    "wof:name": "Endodontics Of Worcester",
    "wof:placetype": "venue"
  },
  "geometry": {"coordinates":[-71.8187,42.265516],"type":"Point"}
}
