{
  "type": "Feature",
  "properties": {
    "addr:full":"21 Baldwin St West Springfield MA 01089",
    "addr:housenumber":"21",
    "addr:postcode":"01089",
    "addr:street":"Baldwin St",
    "iso:country":"US",
    "sg:address":"21 Baldwin St",
    "sg:city":"West Springfield",
    "sg:classifiers":[
        {
            "category":"Travel",
            "subcategory":"Hotels & Motels",
            "type":"Entertainment"
        }
    ],
    "sg:phone":"+1 413 781 2300",
    "sg:postcode":"01089",
    "sg:province":"MA",
    "sg:website":"www.ramada.com",
    "wof:name":"Regency Inn",
    "wof:placetype":"venue"
},
  "geometry": {"coordinates":[-72.62281400000001,42.096514],"type":"Point"}
}