{
  "type": "Feature",
  "properties": {
    "addr:full":"177 Wells Ave Newton Center MA 02459",
    "addr:housenumber":"177",
    "addr:postcode":"02459",
    "addr:street":"Wells Ave Newton Center",
    "iso:country":"US",
    "sg:address":"177 Wells Ave",
    "sg:city":"Newton Center",
    "sg:phone":"+1 781 235 1531",
    "sg:postcode":"02459",
    "sg:province":"MA",
    "sg:tags":[
        "oil"
    ],
    "sg:website":"www.jamesdevaneyfuel.com",
    "wof:name":"Diehl Oil",
    "wof:placetype":"venue"
},
  "geometry": {"coordinates":[-71.19671099999999,42.29305],"type":"Point"}
}