{
  "type": "Feature",
  "properties": {
    "addr:full": "6 Bowdoin Sq Boston MA 02114",
    "addr:housenumber": "6",
    "addr:postcode": "02114",
    "addr:street": "Bowdoin Sq",
    "iso:country": "US",
    "sg:address": "6 Bowdoin Sq",
    "sg:city": "Boston",
    "sg:classifiers": [
      {
        "category": "Professional",
        "subcategory": "Lawyer \u0026 Legal Services",
        "type": "Services"
      }
    ],
    "sg:phone": "+1 617 353 0684",
    "sg:postcode": "02114",
    "sg:province": "MA",
    "wof:name": "Mailloux Robt J",
    "wof:placetype": "venue"
  },
  "geometry": {"coordinates":[-71.062698,42.3615],"type":"Point"}
}
