{
  "type": "Feature",
  "properties": {
    "addr:full":"229 White St 2 Belmont MA 02478",
    "addr:housenumber":"229;2",
    "addr:postcode":"02478",
    "addr:street":"White St",
    "iso:country":"US",
    "sg:address":"229 White St 2",
    "sg:city":"Belmont",
    "sg:classifiers":[
        {
            "category":"Professional",
            "subcategory":"Computer Services",
            "type":"Services"
        }
    ],
    "sg:phone":"+1 617 357 4720",
    "sg:postcode":"02478",
    "sg:province":"MA",
    "sg:tags":[
        "design",
        "system",
        "network"
    ],
    "sg:website":"http://www.wizzywigg.com",
    "wof:name":"Wizzywigg Communications",
    "wof:placetype":"venue"
},
  "geometry": {"coordinates":[-71.187218,42.381222],"type":"Point"}
}