{
  "type": "Feature",
  "properties": {
    "addr:full":"200 Pleasant St Lbby 1 Malden MA 02148",
    "addr:housenumber":"200;1",
    "addr:postcode":"02148",
    "addr:street":"Pleasant St Lbby",
    "iso:country":"US",
    "sg:address":"200 Pleasant St Lbby 1",
    "sg:city":"Malden",
    "sg:classifiers":[
        {
            "category":"Education",
            "subcategory":"School",
            "type":"Public Place"
        }
    ],
    "sg:phone":"+1 781 397 7130",
    "sg:postcode":"02148",
    "sg:province":"MA",
    "sg:tags":[
        "high",
        "middle",
        "elementary"
    ],
    "wof:name":"Malden City of",
    "wof:placetype":"venue"
},
  "geometry": {"coordinates":[-71.07341,42.427193],"type":"Point"}
}