{
  "type": "Feature",
  "properties": {
    "iso:country":"US",
    "sg:address":"1644 Falmouth Rd",
    "sg:city":"Centerville",
    "sg:classifiers":[
        {
            "category":"Personal",
            "subcategory":"Tanning Parlor",
            "type":"Services"
        }
    ],
    "sg:phone":"+1 508 771 9009",
    "sg:postcode":"02632",
    "sg:province":"MA",
    "sg:website":"Tanlinescenterville.com",
    "wof:name":"Tanlines Apparel & Tanning",
    "wof:placetype":"venue"
},
  "geometry": {"coordinates":[-70.349602,41.657101],"type":"Point"}
}