{
  "type": "Feature",
  "properties": {
    "addr:full": "68 Elm St Georgetown MA 01833",
    "addr:housenumber": "68",
    "addr:postcode": "01833",
    "addr:street": "Elm St",
    "iso:country": "US",
    "sg:address": "68 Elm St",
    "sg:city": "Georgetown",
    "sg:classifiers": [
      {
        "category": "Education",
        "subcategory": "School",
        "type": "Public Place"
      }
    ],
    "sg:phone": "+1 978 352 5785",
    "sg:postcode": "01833",
    "sg:province": "MA",
    "wof:name": "Gps Pennbrook School",
    "wof:placetype": "venue"
  },
  "geometry": {"coordinates":[-70.987343,42.716514],"type":"Point"}
}
