{
  "type": "Feature",
  "properties": {
    "addr:full": "166 E Bacon St Plainville MA 02762",
    "addr:housenumber": "166",
    "addr:postcode": "02762",
    "addr:street": "E Bacon St",
    "iso:country": "US",
    "sg:address": "166 E Bacon St",
    "sg:city": "Plainville",
    "sg:classifiers": [
      {
        "category": "Manufacturing",
        "subcategory": "Printing",
        "type": "Manufacturing \u0026 Wholesale Goods"
      }
    ],
    "sg:phone": "+1 508 695 3431",
    "sg:postcode": "02762",
    "sg:province": "MA",
    "sg:tags": [
      "publisher"
    ],
    "wof:name": "Grand Publishing Co",
    "wof:placetype": "venue"
  },
  "geometry": {"coordinates":[-71.31412,42.0085],"type":"Point"}
}
