{
  "type": "Feature",
  "properties": {
    "iso:country":"US",
    "sg:address":"181 Ludlow Rd",
    "sg:city":"Chicopee",
    "sg:classifiers":[
        {
            "category":"Manufacturing",
            "subcategory":"Tools & Machinery",
            "type":"Manufacturing & Wholesale Goods"
        }
    ],
    "sg:phone":"+1 413 532 4673",
    "sg:postcode":"01020",
    "sg:province":"MA",
    "sg:tags":[
        "machine",
        "shop"
    ],
    "wof:name":"Roger's General Machining Inc",
    "wof:placetype":"venue"
},
  "geometry": {"coordinates":[-72.552284,42.212086],"type":"Point"}
}