{
  "type": "Feature",
  "properties": {
    "addr:full": "288 Newbury St Boston MA 02115",
    "addr:housenumber": "288",
    "addr:postcode": "02115",
    "addr:street": "Newbury St",
    "iso:country": "US",
    "sg:address": "288 Newbury St",
    "sg:city": "Boston",
    "sg:classifiers": [
      {
        "category": "Coffee \u0026 Tea",
        "type": "Food \u0026 Drink"
      },
      {
        "category": "Bagels",
        "type": "Food \u0026 Drink"
      }
    ],
    "sg:menulink": "http://www.allmenus.com/ma/boston/116-bagel-rising/menu/",
    "sg:phone": "+1 617 859 9515",
    "sg:postcode": "02115",
    "sg:province": "MA",
    "sg:tags": [
      "wrap",
      "american",
      "sandwich"
    ],
    "wof:name": "Bagel Rising",
    "wof:placetype": "venue"
  },
  "geometry": {"coordinates":[-71.084409,42.349086],"type":"Point"}
}
