{
  "type": "Feature",
  "properties": {
    "iso:country":"US",
    "sg:address":"288 Newbury St",
    "sg:city":"Boston",
    "sg:classifiers":[
        {
            "category":"Coffee & Tea",
            "type":"Food & Drink"
        },
        {
            "category":"Bagels",
            "type":"Food & Drink"
        }
    ],
    "sg:menulink":"http://www.allmenus.com/ma/boston/116-bagel-rising/menu/",
    "sg:phone":"+1 617 859 9515",
    "sg:postcode":"02115",
    "sg:province":"MA",
    "sg:tags":[
        "wrap",
        "american",
        "sandwich"
    ],
    "wof:name":"Bagel Rising",
    "wof:placetype":"venue"
},
  "geometry": {"coordinates":[-71.08440899999999,42.349086],"type":"Point"}
}