{
  "type": "Feature",
  "properties": {
    "addr:full": "193 Rockland St Hanover MA 02339",
    "addr:housenumber": "193",
    "addr:postcode": "02339",
    "addr:street": "Rockland St",
    "iso:country": "US",
    "sg:address": "193 Rockland St",
    "sg:city": "Hanover",
    "sg:classifiers": [
      {
        "category": "Shopping",
        "type": "Retail Goods"
      }
    ],
    "sg:phone": "+1 781 826 4711",
    "sg:postcode": "02339",
    "sg:province": "MA",
    "sg:tags": [
      "hearing",
      "equipment",
      "supply",
      "impaired"
    ],
    "wof:name": "Suburban Hearing Aid Svc",
    "wof:placetype": "venue"
  },
  "geometry": {"coordinates":[-70.821572,42.114316],"type":"Point"}
}
