{
  "type": "Feature",
  "properties": {
    "addr:full": "187 Stuart St Springfield MA 01119",
    "addr:housenumber": "187",
    "addr:postcode": "01119",
    "addr:street": "Stuart St",
    "iso:country": "US",
    "sg:address": "187 Stuart St",
    "sg:city": "Springfield",
    "sg:classifiers": [
      {
        "category": "Organizations",
        "subcategory": "Religious Organization",
        "type": "Services"
      }
    ],
    "sg:phone": "+1 413 783 9772",
    "sg:postcode": "01119",
    "sg:province": "MA",
    "sg:tags": [
      "church"
    ],
    "wof:name": "Jehovah's Witnesses",
    "wof:placetype": "venue"
  },
  "geometry": {"coordinates":[-72.525574,42.136265],"type":"Point"}
}
