{
  "type": "Feature",
  "properties": {
    "addr:full":"225 Friend St Boston MA 02114",
    "addr:housenumber":"225",
    "addr:postcode":"02114",
    "addr:street":"Friend St",
    "iso:country":"US",
    "sg:address":"225 Friend St",
    "sg:city":"Boston",
    "sg:classifiers":[
        {
            "category":"Professional",
            "subcategory":"Lawyer & Legal Services",
            "type":"Services"
        }
    ],
    "sg:phone":"+1 617 723 8100",
    "sg:postcode":"02114",
    "sg:province":"MA",
    "wof:name":"Ramsey Gordon P Lwyr",
    "wof:placetype":"venue"
},
  "geometry": {"coordinates":[-71.060799,42.364399],"type":"Point"}
}