{
  "type": "Feature",
  "properties": {
    "iso:country":"US",
    "sg:address":"20 Custom House St",
    "sg:city":"Boston",
    "sg:classifiers":[
        {
            "category":"Banks & Credit Unions",
            "subcategory":"Investment Brokerage",
            "type":"Services"
        },
        {
            "category":"Insurance",
            "subcategory":"Hazard Insurance",
            "type":"Services"
        }
    ],
    "sg:phone":"+1 617 951 0600",
    "sg:postcode":"02110",
    "sg:province":"MA",
    "sg:tags":[
        "agent",
        "resume"
    ],
    "wof:name":"Thomas Black Corporation",
    "wof:placetype":"venue"
},
  "geometry": {"coordinates":[-71.053009,42.357971],"type":"Point"}
}