{
  "type": "Feature",
  "properties": {
    "addr:full":"581 Massachusetts Ave Cambridge MA 02139",
    "addr:housenumber":"581",
    "addr:postcode":"02139",
    "addr:street":"Massachusetts Ave",
    "iso:country":"US",
    "sg:address":"581 Massachusetts Ave",
    "sg:city":"Cambridge",
    "sg:classifiers":[
        {
            "category":"Food & Beverages",
            "subcategory":"Groceries & Convenience Stores",
            "type":"Retail Goods"
        }
    ],
    "sg:phone":"+1 617 661 1580",
    "sg:postcode":"02139",
    "sg:province":"MA",
    "sg:tags":[
        "grocer",
        "health",
        "bakers-wholesale",
        "market"
    ],
    "sg:website":"www.harvestcoop.com",
    "wof:name":"Harvest Co-Op Markets",
    "wof:placetype":"venue"
},
  "geometry": {"coordinates":[-71.1036,42.3652],"type":"Point"}
}