{
  "type": "Feature",
  "properties": {
    "iso:country":"US",
    "sg:address":"770 Cochituate Rd",
    "sg:city":"Framingham",
    "sg:classifiers":[
        {
            "category":"Shopping",
            "subcategory":"Department Store",
            "type":"Retail Goods"
        },
        {
            "category":"Shopping",
            "subcategory":"Clothing, Apparel, & Fashions",
            "type":"Retail Goods"
        },
        {
            "category":"Shopping",
            "subcategory":"Discount & Variety Stores",
            "type":"Retail Goods"
        }
    ],
    "sg:phone":"+1 508 390 1000",
    "sg:postcode":"01701",
    "sg:province":"MA",
    "sg:tags":[
        "clothing"
    ],
    "sg:website":"http://www.tjx.com",
    "wof:name":"T.J. Maxx",
    "wof:placetype":"venue"
},
  "geometry": {"coordinates":[-71.38294,42.308642],"type":"Point"}
}