{
  "type": "Feature",
  "properties": {
    "addr:full": "452 Park St New Bedford MA 02740",
    "addr:housenumber": "452",
    "addr:postcode": "02740",
    "addr:street": "Park St",
    "iso:country": "US",
    "sg:address": "452 Park St",
    "sg:city": "New Bedford",
    "sg:classifiers": [
      {
        "category": "Professional",
        "type": "Services"
      }
    ],
    "sg:phone": "+1 508 992 5557",
    "sg:postcode": "02740",
    "sg:province": "MA",
    "sg:tags": [
      "establishment"
    ],
    "wof:name": "Us A Boxing New England",
    "wof:placetype": "venue"
  },
  "geometry": {"coordinates":[-70.939623,41.642184],"type":"Point"}
}
