{
  "type": "Feature",
  "properties": {
    "addr:full": "8 N Water St Nantucket MA 02554",
    "addr:housenumber": "8",
    "addr:postcode": "02554",
    "addr:street": "N Water St",
    "iso:country": "US",
    "sg:address": "8 N Water St",
    "sg:city": "Nantucket",
    "sg:classifiers": [
      {
        "category": "Travel",
        "subcategory": "Hotels \u0026 Motels",
        "type": "Entertainment"
      }
    ],
    "sg:phone": "+1 508 228 6597",
    "sg:postcode": "02554",
    "sg:province": "MA",
    "sg:tags": [
      "lodging"
    ],
    "sg:website": "www.nantucketwhaler.com",
    "wof:name": "Nantucket Whaler Guest House",
    "wof:placetype": "venue"
  },
  "geometry": {"coordinates":[-70.099571,41.285801],"type":"Point"}
}
