{
  "type": "Feature",
  "properties": {
    "iso:country":"US",
    "sg:address":"8 N Water St",
    "sg:city":"Nantucket",
    "sg:classifiers":[
        {
            "category":"Travel",
            "subcategory":"Hotels & Motels",
            "type":"Entertainment"
        }
    ],
    "sg:phone":"+1 508 228 6597",
    "sg:postcode":"02554",
    "sg:province":"MA",
    "sg:tags":[
        "lodging"
    ],
    "sg:website":"www.nantucketwhaler.com",
    "wof:name":"Nantucket Whaler Guest House",
    "wof:placetype":"venue"
},
  "geometry": {"coordinates":[-70.099571,41.285801],"type":"Point"}
}