{
  "type": "Feature",
  "properties": {
    "iso:country":"US",
    "sg:address":"75 Concord Rd",
    "sg:city":"Chelmsford",
    "sg:classifiers":[
        {
            "category":"Health Services",
            "subcategory":"Podiatrist",
            "type":"Services"
        }
    ],
    "sg:phone":"+1 978 256 1611",
    "sg:postcode":"01824",
    "sg:province":"MA",
    "wof:name":"A Family Foot Specialist",
    "wof:placetype":"venue"
},
  "geometry": {"coordinates":[-71.345339,42.57534],"type":"Point"}
}