{
  "type": "Feature",
  "properties": {
    "iso:country":"US",
    "sg:address":"45 Walter St",
    "sg:city":"Hyde Park",
    "sg:classifiers":[
        {
            "category":"Shopping",
            "subcategory":"Bicycles & Sporting Goods",
            "type":"Retail Goods"
        }
    ],
    "sg:phone":"+1 617 361 8011",
    "sg:postcode":"02136",
    "sg:province":"MA",
    "sg:website":"www.beantownsports.com",
    "wof:name":"Beantown Sports Inc",
    "wof:placetype":"venue"
},
  "geometry": {"coordinates":[-71.117277,42.25594],"type":"Point"}
}