{
  "type": "Feature",
  "properties": {
    "iso:country":"US",
    "sg:address":"160 Federal St",
    "sg:city":"Boston",
    "sg:classifiers":[
        {
            "category":"Banks & Credit Unions",
            "subcategory":"Investment Brokerage",
            "type":"Services"
        }
    ],
    "sg:phone":"+1 617 912 1492",
    "sg:postcode":"02110",
    "sg:province":"MA",
    "sg:tags":[
        "advisory",
        "security",
        "financial"
    ],
    "sg:website":"www.rockportcap.com",
    "wof:name":"Rockport Capital Partners",
    "wof:placetype":"venue"
},
  "geometry": {"coordinates":[-71.056023,42.353927],"type":"Point"}
}