{
  "type": "Feature",
  "properties": {
    "addr:full":"18 Muzzey St Lexington MA 02421",
    "addr:housenumber":"18",
    "addr:postcode":"02421",
    "addr:street":"Muzzey St",
    "iso:country":"US",
    "sg:address":"18 Muzzey St",
    "sg:city":"Lexington",
    "sg:classifiers":[
        {
            "category":"Government",
            "subcategory":"Office",
            "type":"Public Place"
        }
    ],
    "sg:phone":"+1 781 861 7305",
    "sg:postcode":"02421",
    "sg:province":"MA",
    "sg:tags":[
        "authorities",
        "transportation"
    ],
    "wof:name":"Grove Associates",
    "wof:placetype":"venue"
},
  "geometry": {"coordinates":[-71.228472,42.448042],"type":"Point"}
}