{
  "type": "Feature",
  "properties": {
    "addr:full":"40 Ash St Somerset MA 02726",
    "addr:housenumber":"40",
    "addr:postcode":"02726",
    "addr:street":"Ash St",
    "iso:country":"US",
    "sg:address":"40 Ash St",
    "sg:city":"Somerset",
    "sg:classifiers":[
        {
            "category":"Professional",
            "subcategory":"Accounting & Tax Preparation",
            "type":"Services"
        }
    ],
    "sg:phone":"+1 508 679 1858",
    "sg:postcode":"02726",
    "sg:province":"MA",
    "sg:tags":[
        "payroll"
    ],
    "wof:name":"Payroll Express Inc",
    "wof:placetype":"venue"
},
  "geometry": {"coordinates":[-71.145229,41.746119],"type":"Point"}
}