{
  "type": "Feature",
  "properties": {
    "iso:country":"US",
    "sg:address":"5 Sparks Ave",
    "sg:city":"Nantucket",
    "sg:classifiers":[
        {
            "category":"Shopping",
            "subcategory":"Computers & Home Electronics",
            "type":"Retail Goods"
        }
    ],
    "sg:phone":"+1 508 825 2019",
    "sg:postcode":"02554",
    "sg:province":"MA",
    "sg:tags":[
        "equipment",
        "dealer"
    ],
    "wof:name":"Computer Assistance Svc",
    "wof:placetype":"venue"
},
  "geometry": {"coordinates":[-70.089658,41.270766],"type":"Point"}
}