{
  "type": "Feature",
  "properties": {
    "iso:country":"US",
    "sg:address":"301 Herman Melville Blvd",
    "sg:city":"New Bedford",
    "sg:classifiers":[
        {
            "category":"Retail",
            "subcategory":"Auto Repair",
            "type":"Services"
        }
    ],
    "sg:phone":"+1 508 996 6867",
    "sg:postcode":"02740",
    "sg:province":"MA",
    "sg:tags":[
        "machine",
        "automobile",
        "shop"
    ],
    "wof:name":"Motor Tech Inc",
    "wof:placetype":"venue"
},
  "geometry": {"coordinates":[-70.92391499999999,41.64875],"type":"Point"}
}