{
  "type": "Feature",
  "properties": {
    "addr:full":"67 Forest St Marlborough MA 01752",
    "addr:housenumber":"67",
    "addr:postcode":"01752",
    "addr:street":"Forest St",
    "iso:country":"US",
    "sg:address":"67 Forest St",
    "sg:city":"Marlborough",
    "sg:classifiers":[
        {
            "category":"Manufacturing",
            "subcategory":"Tools & Machinery",
            "type":"Manufacturing & Wholesale Goods"
        }
    ],
    "sg:phone":"+1 508 787 1900",
    "sg:postcode":"01752",
    "sg:province":"MA",
    "sg:tags":[
        "computer"
    ],
    "wof:name":"IBM Corp",
    "wof:placetype":"venue"
},
  "geometry": {"coordinates":[-71.57178999999999,42.333529],"type":"Point"}
}