{
  "type": "Feature",
  "properties": {
    "iso:country":"US",
    "sg:address":"505 Washington Ave",
    "sg:city":"Revere",
    "sg:classifiers":[
        {
            "category":"Building & Trades",
            "subcategory":"Construction",
            "type":"Services"
        }
    ],
    "sg:phone":"+1 781 485 1621",
    "sg:postcode":"02151",
    "sg:province":"MA",
    "sg:tags":[
        "asbestos",
        "removal",
        "contractor"
    ],
    "wof:name":"Northshore Environmental Svc",
    "wof:placetype":"venue"
},
  "geometry": {"coordinates":[-71.025936,42.424521],"type":"Point"}
}