{
  "type": "Feature",
  "properties": {
    "iso:country":"US",
    "sg:address":"107 Broadway",
    "sg:city":"Salem",
    "sg:classifiers":[
        {
            "category":"Wholesale",
            "subcategory":"Durable Goods & Equipment",
            "type":"Manufacturing & Wholesale Goods"
        }
    ],
    "sg:phone":"+1 978 745 8660",
    "sg:postcode":"01970",
    "sg:province":"MA",
    "sg:tags":[
        "appliances-major-wholesale",
        "manufacturer"
    ],
    "wof:name":"Chimneys By Brownie",
    "wof:placetype":"venue"
},
  "geometry": {"coordinates":[-70.894989,42.503349],"type":"Point"}
}