{
  "type": "Feature",
  "properties": {
    "addr:full": "1040 Franklin St Melrose MA 02176",
    "addr:housenumber": "1040",
    "addr:postcode": "02176",
    "addr:street": "Franklin St",
    "iso:country": "US",
    "sg:address": "1040 Franklin St",
    "sg:city": "Melrose",
    "sg:classifiers": [
      {
        "category": "Building \u0026 Trades",
        "subcategory": "Plumbing",
        "type": "Services"
      }
    ],
    "sg:phone": "+1 781 662 0816",
    "sg:postcode": "02176",
    "sg:province": "MA",
    "sg:tags": [
      "heating",
      "contractor"
    ],
    "wof:name": "Bob's Heating",
    "wof:placetype": "venue"
  },
  "geometry": {"coordinates":[-71.07644,42.470163],"type":"Point"}
}
