{
  "type": "Feature",
  "properties": {
    "iso:country":"US",
    "sg:address":"1040 Franklin St",
    "sg:city":"Melrose",
    "sg:classifiers":[
        {
            "category":"Building & Trades",
            "subcategory":"Plumbing",
            "type":"Services"
        }
    ],
    "sg:phone":"+1 781 662 0816",
    "sg:postcode":"02176",
    "sg:province":"MA",
    "sg:tags":[
        "heating",
        "contractor"
    ],
    "wof:name":"Bob's Heating",
    "wof:placetype":"venue"
},
  "geometry": {"coordinates":[-71.07644000000001,42.470163],"type":"Point"}
}