{
  "type": "Feature",
  "properties": {
    "iso:country":"US",
    "sg:address":"201 Washington St",
    "sg:city":"Auburn",
    "sg:classifiers":[
        {
            "category":"Manufacturing",
            "subcategory":"Chemicals & Compounds",
            "type":"Manufacturing & Wholesale Goods"
        }
    ],
    "sg:phone":"+1 508 832 5785",
    "sg:postcode":"01501",
    "sg:province":"MA",
    "sg:tags":[
        "gas"
    ],
    "wof:name":"AIM Safety Products",
    "wof:placetype":"venue"
},
  "geometry": {"coordinates":[-71.814633,42.203102],"type":"Point"}
}