{
  "type": "Feature",
  "properties": {
    "addr:full": "41 Belvidere St Boston MA 02115",
    "addr:housenumber": "41",
    "addr:postcode": "02115",
    "addr:street": "Belvidere St",
    "iso:country": "US",
    "sg:address": "41 Belvidere St",
    "sg:city": "Boston",
    "sg:classifiers": [
      {
        "category": "Retail",
        "subcategory": "Laundry \u0026 Dry Cleaning",
        "type": "Services"
      }
    ],
    "sg:phone": "+1 617 859 7525",
    "sg:postcode": "02115",
    "sg:province": "MA",
    "wof:name": "Cappy's Cleaners \u0026 Laundromat",
    "wof:placetype": "venue"
  },
  "geometry": {"coordinates":[-71.086304,42.346401],"type":"Point"}
}
