{
  "type": "Feature",
  "properties": {
    "iso:country":"US",
    "sg:address":"90 Western Avenue",
    "sg:city":"Boston",
    "sg:classifiers":[
        {
            "category":"Retail",
            "subcategory":"Auto Repair",
            "type":"Services"
        }
    ],
    "sg:phone":"+1 617 783 5911",
    "sg:postcode":"02134",
    "sg:province":"MA",
    "wof:name":"Mike's Auto & Truck Repair",
    "wof:placetype":"venue"
},
  "geometry": {"coordinates":[-71.119709,42.363916],"type":"Point"}
}