{
  "type": "Feature",
  "properties": {
    "addr:full": "90 Western Avenue Boston MA 02134",
    "addr:housenumber": "90",
    "addr:postcode": "02134",
    "addr:street": "Western Avenue",
    "iso:country": "US",
    "sg:address": "90 Western Avenue",
    "sg:city": "Boston",
    "sg:classifiers": [
      {
        "category": "Retail",
        "subcategory": "Auto Repair",
        "type": "Services"
      }
    ],
    "sg:phone": "+1 617 783 5911",
    "sg:postcode": "02134",
    "sg:province": "MA",
    "wof:name": "Mike's Auto \u0026 Truck Repair",
    "wof:placetype": "venue"
  },
  "geometry": {"coordinates":[-71.119709,42.363916],"type":"Point"}
}
