{
  "type": "Feature",
  "properties": {
    "addr:full":"5 Albert St Auburn MA 01501",
    "addr:housenumber":"5",
    "addr:postcode":"01501",
    "addr:street":"Albert St",
    "iso:country":"US",
    "sg:address":"5 Albert St",
    "sg:city":"Auburn",
    "sg:classifiers":[
        {
            "category":"Real Estate",
            "subcategory":"Real Estate Agent",
            "type":"Services"
        }
    ],
    "sg:phone":"+1 508 832 8832",
    "sg:postcode":"01501",
    "sg:province":"MA",
    "wof:name":"Executive Rentals",
    "wof:placetype":"venue"
},
  "geometry": {"coordinates":[-71.87687,42.177312],"type":"Point"}
}