{
  "type": "Feature",
  "properties": {
    "addr:full":"45 Walden St Concord MA 01742",
    "addr:housenumber":"45",
    "addr:postcode":"01742",
    "addr:street":"Walden St",
    "iso:country":"US",
    "sg:address":"45 Walden St",
    "sg:city":"Concord",
    "sg:classifiers":[
        {
            "category":"Professional",
            "subcategory":"Lawyer & Legal Services",
            "type":"Services"
        }
    ],
    "sg:phone":"+1 978 369 9760",
    "sg:postcode":"01742",
    "sg:province":"MA",
    "wof:name":"Sheehan John J Lwyr",
    "wof:placetype":"venue"
},
  "geometry": {"coordinates":[-71.349503,42.4589],"type":"Point"}
}