{
  "type": "Feature",
  "properties": {
    "iso:country":"US",
    "sg:address":"69 Summer Street",
    "sg:city":"Malden",
    "sg:classifiers":[
        {
            "category":"Retail",
            "subcategory":"Laundry & Dry Cleaning",
            "type":"Services"
        }
    ],
    "sg:phone":"+1 781 322 1260",
    "sg:postcode":"02148",
    "sg:province":"MA",
    "wof:name":"Fishman Tailors Quality Plus Clnsrs",
    "wof:placetype":"venue"
},
  "geometry": {"coordinates":[-71.07414199999999,42.42886],"type":"Point"}
}