{
  "type": "Feature",
  "properties": {
    "addr:full": "69 Summer Street Malden MA 02148",
    "addr:housenumber": "69",
    "addr:postcode": "02148",
    "addr:street": "Summer Street",
    "iso:country": "US",
    "sg:address": "69 Summer Street",
    "sg:city": "Malden",
    "sg:classifiers": [
      {
        "category": "Retail",
        "subcategory": "Laundry \u0026 Dry Cleaning",
        "type": "Services"
      }
    ],
    "sg:phone": "+1 781 322 1260",
    "sg:postcode": "02148",
    "sg:province": "MA",
    "wof:name": "Fishman Tailors Quality Plus Clnsrs",
    "wof:placetype": "venue"
  },
  "geometry": {"coordinates":[-71.074142,42.42886],"type":"Point"}
}
