{
  "type": "Feature",
  "properties": {
    "addr:full": "28 Forest St Danvers MA 01923",
    "addr:housenumber": "28",
    "addr:postcode": "01923",
    "addr:street": "Forest St",
    "iso:country": "US",
    "sg:address": "28 Forest St",
    "sg:city": "Danvers",
    "sg:classifiers": [
      {
        "category": "Professional",
        "subcategory": "Business Services",
        "type": "Services"
      }
    ],
    "sg:phone": "+1   ",
    "sg:postcode": "01923",
    "sg:province": "MA",
    "sg:tags": [
      "alteration"
    ],
    "wof:name": "American Stiches",
    "wof:placetype": "venue"
  },
  "geometry": {"coordinates":[-70.959706,42.576431],"type":"Point"}
}
