{
  "type": "Feature",
  "properties": {
    "addr:full": "131 Tremont St Boston MA 02111",
    "addr:housenumber": "131",
    "addr:postcode": "02111",
    "addr:street": "Tremont St",
    "iso:country": "US",
    "sg:address": "131 Tremont St",
    "sg:city": "Boston",
    "sg:classifiers": [
      {
        "category": "Local Transit",
        "type": "Transportation"
      }
    ],
    "sg:phone": "+1 617 728 0440",
    "sg:postcode": "02111",
    "sg:province": "MA",
    "sg:tags": [
      "limousine"
    ],
    "wof:name": "Discover Boston Limousine",
    "wof:placetype": "venue"
  },
  "geometry": {"coordinates":[-71.062876,42.355674],"type":"Point"}
}
