{
  "type": "Feature",
  "properties": {
    "addr:full":"55 Bromont St Chicopee MA 01020",
    "addr:housenumber":"55",
    "addr:postcode":"01020",
    "addr:street":"Bromont St",
    "iso:country":"US",
    "sg:address":"55 Bromont St",
    "sg:city":"Chicopee",
    "sg:classifiers":[
        {
            "category":"Building & Trades",
            "subcategory":"Construction",
            "type":"Services"
        }
    ],
    "sg:phone":"+1   ",
    "sg:postcode":"01020",
    "sg:province":"MA",
    "sg:tags":[
        "nonresidential"
    ],
    "wof:name":"Rd Construction",
    "wof:placetype":"venue"
},
  "geometry": {"coordinates":[-72.560621,42.150563],"type":"Point"}
}