{
  "type": "Feature",
  "properties": {
    "iso:country":"US",
    "sg:address":"1215 Main St",
    "sg:city":"Holden",
    "sg:classifiers":[
        {
            "category":"Organizations",
            "subcategory":"Community Association",
            "type":"Services"
        }
    ],
    "sg:phone":"+1 508 829 8083",
    "sg:postcode":"01520",
    "sg:province":"MA",
    "sg:tags":[
        "environmental",
        "org"
    ],
    "wof:name":"White Oak Land Conservation",
    "wof:placetype":"venue"
},
  "geometry": {"coordinates":[-71.864845,42.351374],"type":"Point"}
}