{
  "type": "Feature",
  "properties": {
    "addr:full": "75 Sandwich Rd Buzzards Bay MA 02532",
    "addr:housenumber": "75",
    "addr:postcode": "02532",
    "addr:street": "Sandwich Rd",
    "iso:country": "US",
    "sg:address": "75 Sandwich Rd",
    "sg:city": "Buzzards Bay",
    "sg:classifiers": [
      {
        "category": "Building \u0026 Trades",
        "subcategory": "Construction",
        "type": "Services"
      }
    ],
    "sg:phone": "+1 508 759 6410",
    "sg:postcode": "02532",
    "sg:province": "MA",
    "sg:tags": [
      "painter"
    ],
    "wof:name": "Eagle Painting \u0026 Mntnc Co",
    "wof:placetype": "venue"
  },
  "geometry": {"coordinates":[-70.592826,41.743529],"type":"Point"}
}
