{
  "type": "Feature",
  "properties": {
    "iso:country":"US",
    "sg:address":"75 Sandwich Rd",
    "sg:city":"Buzzards Bay",
    "sg:classifiers":[
        {
            "category":"Building & Trades",
            "subcategory":"Construction",
            "type":"Services"
        }
    ],
    "sg:phone":"+1 508 759 6410",
    "sg:postcode":"02532",
    "sg:province":"MA",
    "sg:tags":[
        "painter"
    ],
    "wof:name":"Eagle Painting & Mntnc Co",
    "wof:placetype":"venue"
},
  "geometry": {"coordinates":[-70.592826,41.743529],"type":"Point"}
}