{
  "type": "Feature",
  "properties": {
    "addr:full": "107 Center St # 3 Groveland MA 01834",
    "addr:housenumber": "107",
    "addr:postcode": "01834",
    "addr:street": "Center St # 3",
    "iso:country": "US",
    "sg:address": "107 Center St # 3",
    "sg:city": "Groveland",
    "sg:classifiers": [
      {
        "category": "Building \u0026 Trades",
        "subcategory": "Electrical",
        "type": "Services"
      }
    ],
    "sg:phone": "+1 978 373 7838",
    "sg:postcode": "01834",
    "sg:province": "MA",
    "sg:tags": [
      "electrician"
    ],
    "wof:name": "Clausnitzer Arthur R Electrn - CLOSED",
    "wof:placetype": "venue"
  },
  "geometry": {"coordinates":[-71.041496,42.742802],"type":"Point"}
}
