{
  "type": "Feature",
  "properties": {
    "iso:country":"US",
    "sg:address":"107 Center St # 3",
    "sg:city":"Groveland",
    "sg:classifiers":[
        {
            "category":"Building & Trades",
            "subcategory":"Electrical",
            "type":"Services"
        }
    ],
    "sg:phone":"+1 978 373 7838",
    "sg:postcode":"01834",
    "sg:province":"MA",
    "sg:tags":[
        "electrician"
    ],
    "wof:name":"Clausnitzer Arthur R Electrn - CLOSED",
    "wof:placetype":"venue"
},
  "geometry": {"coordinates":[-71.041496,42.742802],"type":"Point"}
}