{
  "type": "Feature",
  "properties": {
    "addr:full": "43 Sparhawk St Amesbury MA 01913",
    "addr:housenumber": "43",
    "addr:postcode": "01913",
    "addr:street": "Sparhawk St",
    "iso:country": "US",
    "sg:address": "43 Sparhawk St",
    "sg:city": "Amesbury",
    "sg:classifiers": [
      {
        "category": "Health Services",
        "subcategory": "Doctor",
        "type": "Services"
      }
    ],
    "sg:phone": "+1 978 388 4411",
    "sg:postcode": "01913",
    "sg:province": "MA",
    "sg:tags": [
      "dentist"
    ],
    "wof:name": "Thomas G Leonard DDS",
    "wof:placetype": "venue"
  },
  "geometry": {"coordinates":[-70.936265,42.852939],"type":"Point"}
}
