{
  "type": "Feature",
  "properties": {
    "addr:full": "273 Littleton Rd Harvard MA 01451",
    "addr:housenumber": "273",
    "addr:postcode": "01451",
    "addr:street": "Littleton Rd",
    "iso:country": "US",
    "sg:address": "273 Littleton Rd",
    "sg:city": "Harvard",
    "sg:classifiers": [
      {
        "category": "Building \u0026 Trades",
        "subcategory": "Landscaping Services",
        "type": "Services"
      }
    ],
    "sg:phone": "+1 978 456 2377",
    "sg:postcode": "01451",
    "sg:province": "MA",
    "sg:tags": [
      "landscape",
      "contractor"
    ],
    "sg:website": "http://www.wholeearthlandscapedesign.com",
    "wof:name": "Whole Earth Landscaping Design Inc",
    "wof:placetype": "venue"
  },
  "geometry": {"coordinates":[-71.548779,42.525657],"type":"Point"}
}
