{
  "type": "Feature",
  "properties": {
    "addr:full": "10 Genevieve Ln Webster MA 01570",
    "addr:housenumber": "10",
    "addr:postcode": "01570",
    "addr:street": "Genevieve Ln",
    "iso:country": "US",
    "sg:address": "10 Genevieve Ln",
    "sg:city": "Webster",
    "sg:classifiers": [
      {
        "category": "Professional",
        "subcategory": "Engineering",
        "type": "Services"
      }
    ],
    "sg:phone": "+1 508 943 5093",
    "sg:postcode": "01570",
    "sg:province": "MA",
    "sg:tags": [
      "engineer"
    ],
    "wof:name": "Cullinan Engineering Co Inc",
    "wof:placetype": "venue"
  },
  "geometry": {"coordinates":[-71.877382,42.064516],"type":"Point"}
}
