{
  "type": "Feature",
  "properties": {
    "addr:full":"79 Great Neck Rd Wareham MA 02571",
    "addr:housenumber":"79",
    "addr:postcode":"02571",
    "addr:street":"Great Neck Rd",
    "iso:country":"US",
    "sg:address":"79 Great Neck Rd",
    "sg:city":"Wareham",
    "sg:classifiers":[
        {
            "category":"Professional",
            "subcategory":"Business Services",
            "type":"Services"
        }
    ],
    "sg:phone":"+1   ",
    "sg:postcode":"02571",
    "sg:province":"MA",
    "wof:name":"Louden Design",
    "wof:placetype":"venue"
},
  "geometry": {"coordinates":[-70.68533499999999,41.749177],"type":"Point"}
}