{
  "type": "Feature",
  "properties": {
    "addr:full":"200 County St New Bedford MA 02740",
    "addr:housenumber":"200",
    "addr:postcode":"02740",
    "addr:street":"County St",
    "iso:country":"US",
    "sg:address":"200 County St",
    "sg:city":"New Bedford",
    "sg:classifiers":[
        {
            "category":"Shopping",
            "type":"Retail Goods"
        }
    ],
    "sg:phone":"+1 508 993 1121",
    "sg:postcode":"02740",
    "sg:province":"MA",
    "sg:tags":[
        "telephone",
        "cellular"
    ],
    "wof:name":"Carlos Electronics",
    "wof:placetype":"venue"
},
  "geometry": {"coordinates":[-70.924727,41.622346],"type":"Point"}
}