{
  "type": "Feature",
  "properties": {
    "addr:full": "54 A St Framingham MA 01701",
    "addr:housenumber": "54",
    "addr:postcode": "01701",
    "addr:street": "A St",
    "iso:country": "US",
    "sg:address": "54 A St",
    "sg:city": "Framingham",
    "sg:classifiers": [
      {
        "category": "Building \u0026 Trades",
        "subcategory": "Construction",
        "type": "Services"
      }
    ],
    "sg:phone": "+1 508 875 9944",
    "sg:postcode": "01701",
    "sg:province": "MA",
    "sg:tags": [
      "general",
      "contractor"
    ],
    "wof:name": "Home Comfort Plus",
    "wof:placetype": "venue"
  },
  "geometry": {"coordinates":[-71.399182,42.320346],"type":"Point"}
}
