{
  "type": "Feature",
  "properties": {
    "iso:country":"US",
    "sg:address":"59 Boileau Ter",
    "sg:city":"Chicopee",
    "sg:classifiers":[
        {
            "category":"Personal",
            "subcategory":"Tanning Parlor",
            "type":"Services"
        },
        {
            "category":"Personal",
            "subcategory":"Beauty Salon",
            "type":"Services"
        }
    ],
    "sg:phone":"+1 413 536 6786",
    "sg:postcode":"01020",
    "sg:province":"MA",
    "sg:tags":[
        "shop"
    ],
    "wof:name":"Shear Sensations",
    "wof:placetype":"venue"
},
  "geometry": {"coordinates":[-72.581777,42.165463],"type":"Point"}
}