{
  "type": "Feature",
  "properties": {
    "addr:full": "10 Cathy Rd Burlington MA 01803",
    "addr:housenumber": "10",
    "addr:postcode": "01803",
    "addr:street": "Cathy Rd",
    "iso:country": "US",
    "sg:address": "10 Cathy Rd",
    "sg:city": "Burlington",
    "sg:classifiers": [
      {
        "category": "Building \u0026 Trades",
        "subcategory": "Construction",
        "type": "Services"
      }
    ],
    "sg:phone": "+1 781 993 9210",
    "sg:postcode": "01803",
    "sg:province": "MA",
    "sg:tags": [
      "general",
      "contractor"
    ],
    "wof:name": "Milinazzo Construction Co Inc",
    "wof:placetype": "venue"
  },
  "geometry": {"coordinates":[-71.197137,42.531439],"type":"Point"}
}
