{
  "type": "Feature",
  "properties": {
    "addr:full": "39 Elm St Blackstone MA 01504",
    "addr:housenumber": "39",
    "addr:postcode": "01504",
    "addr:street": "Elm St",
    "iso:country": "US",
    "sg:address": "39 Elm St",
    "sg:city": "Blackstone",
    "sg:classifiers": [
      {
        "category": "Building \u0026 Trades",
        "subcategory": "Construction",
        "type": "Services"
      }
    ],
    "sg:phone": "+1 617 449 5814",
    "sg:postcode": "01504",
    "sg:province": "MA",
    "sg:tags": [
      "excavation",
      "contractor"
    ],
    "wof:name": "Excavating Solutions",
    "wof:placetype": "venue"
  },
  "geometry": {"coordinates":[-71.503892,42.03653],"type":"Point"}
}
