{
  "type": "Feature",
  "properties": {
    "iso:country":"US",
    "sg:address":"39 Elm St",
    "sg:city":"Blackstone",
    "sg:classifiers":[
        {
            "category":"Building & Trades",
            "subcategory":"Construction",
            "type":"Services"
        }
    ],
    "sg:phone":"+1 617 449 5814",
    "sg:postcode":"01504",
    "sg:province":"MA",
    "sg:tags":[
        "excavation",
        "contractor"
    ],
    "wof:name":"Excavating Solutions",
    "wof:placetype":"venue"
},
  "geometry": {"coordinates":[-71.50389199999999,42.03653],"type":"Point"}
}