{
  "type": "Feature",
  "properties": {
    "iso:country":"US",
    "sg:address":"26 Park Plz",
    "sg:city":"Boston",
    "sg:classifiers":[
        {
            "category":"Fast Food",
            "type":"Food & Drink"
        },
        {
            "category":"Coffee & Tea",
            "type":"Food & Drink"
        },
        {
            "category":"Restaurant",
            "type":"Food & Drink"
        },
        {
            "category":"Bakery",
            "type":"Food & Drink"
        },
        {
            "category":"Food & Beverages",
            "subcategory":"Groceries & Convenience Stores",
            "type":"Retail Goods"
        }
    ],
    "sg:phone":"+1 617 338 8948",
    "sg:postcode":"02116",
    "sg:province":"MA",
    "sg:tags":[
        "shop",
        "american",
        "sandwich",
        "espresso",
        "take"
    ],
    "sg:website":"http://www.aubonpain.com",
    "wof:name":"Au Bon Pain",
    "wof:placetype":"venue"
},
  "geometry": {"coordinates":[-71.068398,42.351799],"type":"Point"}
}