{
  "type": "Feature",
  "properties": {
    "addr:full": "26 Park Plz Boston MA 02116",
    "addr:housenumber": "26",
    "addr:postcode": "02116",
    "addr:street": "Park Plz",
    "iso:country": "US",
    "sg:address": "26 Park Plz",
    "sg:city": "Boston",
    "sg:classifiers": [
      {
        "category": "Fast Food",
        "type": "Food \u0026 Drink"
      },
      {
        "category": "Coffee \u0026 Tea",
        "type": "Food \u0026 Drink"
      },
      {
        "category": "Restaurant",
        "type": "Food \u0026 Drink"
      },
      {
        "category": "Bakery",
        "type": "Food \u0026 Drink"
      },
      {
        "category": "Food \u0026 Beverages",
        "subcategory": "Groceries \u0026 Convenience Stores",
        "type": "Retail Goods"
      }
    ],
    "sg:phone": "+1 617 338 8948",
    "sg:postcode": "02116",
    "sg:province": "MA",
    "sg:tags": [
      "shop",
      "american",
      "sandwich",
      "espresso",
      "take"
    ],
    "sg:website": "http://www.aubonpain.com",
    "wof:name": "Au Bon Pain",
    "wof:placetype": "venue"
  },
  "geometry": {"coordinates":[-71.068398,42.351799],"type":"Point"}
}
