{
  "type": "Feature",
  "properties": {
    "iso:country":"US",
    "sg:address":"1011 Main St",
    "sg:city":"Hanson",
    "sg:classifiers":[
        {
            "category":"Shopping",
            "subcategory":"Used Merchandise",
            "type":"Retail Goods"
        }
    ],
    "sg:phone":"+1   ",
    "sg:postcode":"02341",
    "sg:province":"MA",
    "wof:name":"New To You Resale Shop",
    "wof:placetype":"venue"
},
  "geometry": {"coordinates":[-70.87597599999999,42.041951],"type":"Point"}
}