{
  "type": "Feature",
  "properties": {
    "addr:full":"72 W Yarmouth Rd West Yarmouth MA 02673",
    "addr:housenumber":"72",
    "addr:postcode":"02673",
    "addr:street":"W Yarmouth Rd",
    "iso:country":"US",
    "sg:address":"72 W Yarmouth Rd",
    "sg:city":"West Yarmouth",
    "sg:classifiers":[
        {
            "category":"Professional",
            "subcategory":"Management & Consulting",
            "type":"Services"
        }
    ],
    "sg:phone":"+1   ",
    "sg:postcode":"02673",
    "sg:province":"MA",
    "sg:tags":[
        "business"
    ],
    "wof:name":"FCD Consulting Inc",
    "wof:placetype":"venue"
},
  "geometry": {"coordinates":[-70.233165,41.653808],"type":"Point"}
}