{
  "type": "Feature",
  "properties": {
    "iso:country":"US",
    "sg:address":"330 Woodland St",
    "sg:city":"Holliston",
    "sg:classifiers":[
        {
            "category":"Building & Trades",
            "subcategory":"Pest Control",
            "type":"Services"
        }
    ],
    "sg:phone":"+1 508 429 7755",
    "sg:postcode":"01746",
    "sg:province":"MA",
    "wof:name":"Security Pest Elimination",
    "wof:placetype":"venue"
},
  "geometry": {"coordinates":[-71.422422,42.203772],"type":"Point"}
}