{
  "type": "Feature",
  "properties": {
    "addr:full": "590 Boston Ave Medford MA 02155",
    "addr:housenumber": "590",
    "addr:postcode": "02155",
    "addr:street": "Boston Ave",
    "iso:country": "US",
    "sg:address": "590 Boston Ave",
    "sg:city": "Medford",
    "sg:classifiers": [
      {
        "category": "Autos \u0026 Motor Vehicles",
        "subcategory": "Fuel \u0026 Gas Station",
        "type": "Retail Goods"
      },
      {
        "category": "Retail",
        "subcategory": "Car Wash",
        "type": "Services"
      }
    ],
    "sg:phone": "+1 781 396 3319",
    "sg:postcode": "02155",
    "sg:province": "MA",
    "wof:name": "Titan Gas",
    "wof:placetype": "venue"
  },
  "geometry": {"coordinates":[-71.113739,42.402699],"type":"Point"}
}
