{
  "type": "Feature",
  "properties": {
    "iso:country":"US",
    "sg:address":"575 Washington St",
    "sg:city":"Wellesley",
    "sg:classifiers":[
        {
            "category":"Retail",
            "subcategory":"Repair Shop",
            "type":"Services"
        }
    ],
    "sg:phone":"+1 781 481 0305",
    "sg:postcode":"02482",
    "sg:province":"MA",
    "sg:tags":[
        "lock",
        "locksmith"
    ],
    "wof:name":"Any Place Locksmith",
    "wof:placetype":"venue"
},
  "geometry": {"coordinates":[-71.29294,42.296589],"type":"Point"}
}