{
  "type": "Feature",
  "properties": {
    "addr:full": "455 John Hancock Rd Taunton MA 02780",
    "addr:housenumber": "455",
    "addr:postcode": "02780",
    "addr:street": "John Hancock Rd",
    "iso:country": "US",
    "sg:address": "455 John Hancock Rd",
    "sg:city": "Taunton",
    "sg:classifiers": [
      {
        "category": "Home \u0026 Garden",
        "subcategory": "Household Appliances",
        "type": "Retail Goods"
      }
    ],
    "sg:phone": "+1   ",
    "sg:postcode": "02780",
    "sg:province": "MA",
    "wof:name": "P\u0026O Cold Logistics",
    "wof:placetype": "venue"
  },
  "geometry": {"coordinates":[-71.12584,41.93173],"type":"Point"}
}
