{
  "type": "Feature",
  "properties": {
    "iso:country":"US",
    "sg:address":"92 Pearl St",
    "sg:city":"Chelsea",
    "sg:classifiers":[
        {
            "category":"Freight",
            "type":"Transportation"
        }
    ],
    "sg:phone":"+1   ",
    "sg:postcode":"02150",
    "sg:province":"MA",
    "sg:tags":[
        "operator",
        "local",
        "trucking"
    ],
    "wof:name":"Atra",
    "wof:placetype":"venue"
},
  "geometry": {"coordinates":[-71.037719,42.389526],"type":"Point"}
}