{
  "type": "Feature",
  "properties": {
    "addr:full": "92 Pearl St Chelsea MA 02150",
    "addr:housenumber": "92",
    "addr:postcode": "02150",
    "addr:street": "Pearl St",
    "iso:country": "US",
    "sg:address": "92 Pearl St",
    "sg:city": "Chelsea",
    "sg:classifiers": [
      {
        "category": "Freight",
        "type": "Transportation"
      }
    ],
    "sg:phone": "+1   ",
    "sg:postcode": "02150",
    "sg:province": "MA",
    "sg:tags": [
      "operator",
      "local",
      "trucking"
    ],
    "wof:name": "Atra",
    "wof:placetype": "venue"
  },
  "geometry": {"coordinates":[-71.037719,42.389526],"type":"Point"}
}
