{
  "type": "Feature",
  "properties": {
    "addr:full": "458 Russell St Ste 3 Hadley MA 01035",
    "addr:housenumber": "458",
    "addr:postcode": "01035",
    "addr:street": "Russell St Ste 3",
    "iso:country": "US",
    "ovtr:label": "Dollar Tree, 458 Russell St Hadley MA US",
    "ovtr:similarity": 3.344125986099243,
    "sg:address": "458 Russell St Ste 3",
    "sg:city": "Hadley",
    "sg:classifiers": [
      {
        "category": "Shopping",
        "subcategory": "Department Store",
        "type": "Retail Goods"
      },
      {
        "category": "Shopping",
        "subcategory": "Discount \u0026 Variety Stores",
        "type": "Retail Goods"
      },
      {
        "category": "Shopping",
        "type": "Retail Goods"
      }
    ],
    "sg:phone": "+1 413 253 0142",
    "sg:postcode": "01035",
    "sg:province": "MA",
    "sg:tags": [
      "merchandise"
    ],
    "sg:website": "http://www.dollartree.com/",
    "wof:name": "Dollar Tree",
    "wof:placetype": "venue"
  },
  "geometry": {"coordinates":[-72.538038,42.364316],"type":"Point"}
}
