{
  "type": "Feature",
  "properties": {
    "iso:country":"US",
    "sg:address":"458 Russell St Ste 3",
    "sg:city":"Hadley",
    "sg:classifiers":[
        {
            "category":"Shopping",
            "subcategory":"Department Store",
            "type":"Retail Goods"
        },
        {
            "category":"Shopping",
            "subcategory":"Discount & Variety Stores",
            "type":"Retail Goods"
        },
        {
            "category":"Shopping",
            "type":"Retail Goods"
        }
    ],
    "sg:phone":"+1 413 253 0142",
    "sg:postcode":"01035",
    "sg:province":"MA",
    "sg:tags":[
        "merchandise"
    ],
    "sg:website":"http://www.dollartree.com/",
    "wof:name":"Dollar Tree",
    "wof:placetype":"venue"
},
  "geometry": {"coordinates":[-72.538038,42.364316],"type":"Point"}
}