{
  "type": "Feature",
  "properties": {
    "addr:full": "400 Blue Hill Dr Westwood MA 02090",
    "addr:housenumber": "400",
    "addr:postcode": "02090",
    "addr:street": "Blue Hill Dr",
    "iso:country": "US",
    "sg:address": "400 Blue Hill Dr",
    "sg:city": "Westwood",
    "sg:classifiers": [
      {
        "category": "Home \u0026 Garden",
        "subcategory": "Household Appliances",
        "type": "Retail Goods"
      }
    ],
    "sg:phone": "+1 781 329 0638",
    "sg:postcode": "02090",
    "sg:province": "MA",
    "wof:name": "Delia Associates Inc",
    "wof:placetype": "venue"
  },
  "geometry": {"coordinates":[-71.154701,42.2146],"type":"Point"}
}
