{
  "type": "Feature",
  "properties": {
    "iso:country":"US",
    "sg:address":"400 Blue Hill Dr",
    "sg:city":"Westwood",
    "sg:classifiers":[
        {
            "category":"Home & Garden",
            "subcategory":"Household Appliances",
            "type":"Retail Goods"
        }
    ],
    "sg:phone":"+1 781 329 0638",
    "sg:postcode":"02090",
    "sg:province":"MA",
    "wof:name":"Delia Associates Inc",
    "wof:placetype":"venue"
},
  "geometry": {"coordinates":[-71.154701,42.2146],"type":"Point"}
}