{
  "type": "Feature",
  "properties": {
    "iso:country":"US",
    "sg:address":"377 S Main St",
    "sg:city":"Athol",
    "sg:classifiers":[
        {
            "category":"Building & Trades",
            "subcategory":"Construction",
            "type":"Services"
        }
    ],
    "sg:phone":"+1 978 249 6570",
    "sg:postcode":"01331",
    "sg:province":"MA",
    "sg:tags":[
        "masonry",
        "contractor"
    ],
    "wof:name":"Maplewood Masonry Div",
    "wof:placetype":"venue"
},
  "geometry": {"coordinates":[-72.244264,42.589124],"type":"Point"}
}