{
  "type": "Feature",
  "properties": {
    "addr:full":"44 Deerfield St Greenfield MA 01301",
    "addr:housenumber":"44",
    "addr:postcode":"01301",
    "addr:street":"Deerfield St",
    "iso:country":"US",
    "sg:address":"44 Deerfield St",
    "sg:city":"Greenfield",
    "sg:classifiers":[
        {
            "category":"Shopping",
            "type":"Retail Goods"
        }
    ],
    "sg:phone":"+1 413 774 7346",
    "sg:postcode":"01301",
    "sg:province":"MA",
    "sg:tags":[
        "pet",
        "shop"
    ],
    "wof:name":"Animal Crackers Inc",
    "wof:placetype":"venue"
},
  "geometry": {"coordinates":[-72.600762,42.584363],"type":"Point"}
}