{
  "type": "Feature",
  "properties": {
    "iso:country":"US",
    "sg:address":"32 Belmont St",
    "sg:city":"Malden",
    "sg:classifiers":[
        {
            "category":"Professional",
            "subcategory":"Business Services",
            "type":"Services"
        }
    ],
    "sg:phone":"+1   ",
    "sg:postcode":"02148",
    "sg:province":"MA",
    "wof:name":"Marcotte Driscoll Solutions",
    "wof:placetype":"venue"
},
  "geometry": {"coordinates":[-71.06194000000001,42.41563],"type":"Point"}
}