{
  "type": "Feature",
  "properties": {
    "iso:country":"US",
    "sg:address":"35 Osgood St",
    "sg:city":"Somerville",
    "sg:classifiers":[
        {
            "category":"Professional",
            "subcategory":"Computer Services",
            "type":"Services"
        }
    ],
    "sg:phone":"+1 617 629 0100",
    "sg:postcode":"02143",
    "sg:province":"MA",
    "wof:name":"Abacus Computer Svc A Soft",
    "wof:placetype":"venue"
},
  "geometry": {"coordinates":[-71.102469,42.383652],"type":"Point"}
}