{
  "type": "Feature",
  "properties": {
    "iso:country":"US",
    "sg:address":"204 Auburn St",
    "sg:city":"Auburn",
    "sg:classifiers":[
        {
            "category":"Building & Trades",
            "subcategory":"Plumbing",
            "type":"Services"
        }
    ],
    "sg:phone":"+1   ",
    "sg:postcode":"01501",
    "sg:province":"MA",
    "sg:tags":[
        "contractor"
    ],
    "wof:name":"Jeff Bernard Plmbng Htng Drn",
    "wof:placetype":"venue"
},
  "geometry": {"coordinates":[-71.84386000000001,42.214023],"type":"Point"}
}