{
  "type": "Feature",
  "properties": {
    "addr:full": "204 Auburn St Auburn MA 01501",
    "addr:housenumber": "204",
    "addr:postcode": "01501",
    "addr:street": "Auburn St",
    "iso:country": "US",
    "sg:address": "204 Auburn St",
    "sg:city": "Auburn",
    "sg:classifiers": [
      {
        "category": "Building \u0026 Trades",
        "subcategory": "Plumbing",
        "type": "Services"
      }
    ],
    "sg:phone": "+1   ",
    "sg:postcode": "01501",
    "sg:province": "MA",
    "sg:tags": [
      "contractor"
    ],
    "wof:name": "Jeff Bernard Plmbng Htng Drn",
    "wof:placetype": "venue"
  },
  "geometry": {"coordinates":[-71.84386,42.214023],"type":"Point"}
}
