{
  "type": "Feature",
  "properties": {
    "iso:country":"US",
    "sg:address":"5 Commercial Cir",
    "sg:city":"Dedham",
    "sg:classifiers":[
        {
            "category":"Professional",
            "subcategory":"Lawyer & Legal Services",
            "type":"Services"
        }
    ],
    "sg:phone":"+1 781 251 0962",
    "sg:postcode":"02026",
    "sg:province":"MA",
    "wof:name":"Crossland & Crossland",
    "wof:placetype":"venue"
},
  "geometry": {"coordinates":[-71.177803,42.233898],"type":"Point"}
}