{
  "type": "Feature",
  "properties": {
    "addr:full": "5 Commercial Cir Dedham MA 02026",
    "addr:housenumber": "5",
    "addr:postcode": "02026",
    "addr:street": "Commercial Cir",
    "iso:country": "US",
    "sg:address": "5 Commercial Cir",
    "sg:city": "Dedham",
    "sg:classifiers": [
      {
        "category": "Professional",
        "subcategory": "Lawyer \u0026 Legal Services",
        "type": "Services"
      }
    ],
    "sg:phone": "+1 781 251 0962",
    "sg:postcode": "02026",
    "sg:province": "MA",
    "wof:name": "Crossland \u0026 Crossland",
    "wof:placetype": "venue"
  },
  "geometry": {"coordinates":[-71.177803,42.233898],"type":"Point"}
}
