{
  "type": "Feature",
  "properties": {
    "iso:country":"US",
    "sg:address":"85 Mercury St",
    "sg:city":"Weymouth",
    "sg:classifiers":[
        {
            "category":"Professional",
            "subcategory":"Secretarial Services",
            "type":"Services"
        }
    ],
    "sg:phone":"+1 781 340 6552",
    "sg:postcode":"02188",
    "sg:province":"MA",
    "sg:tags":[
        "reporting"
    ],
    "wof:name":"Perfection Typing",
    "wof:placetype":"venue"
},
  "geometry": {"coordinates":[-70.96862900000001,42.184744],"type":"Point"}
}