{
  "type": "Feature",
  "properties": {
    "addr:full": "4 Cabot Pl Ste 2 Stoughton MA 02072",
    "addr:housenumber": "4",
    "addr:postcode": "02072",
    "addr:street": "Cabot Pl Ste 2",
    "iso:country": "US",
    "sg:address": "4 Cabot Pl Ste 2",
    "sg:city": "Stoughton",
    "sg:classifiers": [
      {
        "category": "Banks \u0026 Credit Unions",
        "subcategory": "Financial Services",
        "type": "Services"
      }
    ],
    "sg:phone": "+1 781 341 4000",
    "sg:postcode": "02072",
    "sg:province": "MA",
    "sg:tags": [
      "broker",
      "mortgage"
    ],
    "wof:name": "Maritime Mortgage Corp - CLOSED",
    "wof:placetype": "venue"
  },
  "geometry": {"coordinates":[-71.075302,42.152699],"type":"Point"}
}
