{
  "type": "Feature",
  "properties": {
    "addr:full": "1 Acton Pl Acton MA 01720",
    "addr:housenumber": "1",
    "addr:postcode": "01720",
    "addr:street": "Acton Pl",
    "iso:country": "US",
    "sg:address": "1 Acton Pl",
    "sg:city": "Acton",
    "sg:classifiers": [
      {
        "category": "Manufacturing",
        "subcategory": "Tools \u0026 Machinery",
        "type": "Manufacturing \u0026 Wholesale Goods"
      }
    ],
    "sg:phone": "+1 978 776 2000",
    "sg:postcode": "01720",
    "sg:province": "MA",
    "sg:tags": [
      "mill",
      "paper"
    ],
    "wof:name": "Kadant Inc",
    "wof:placetype": "venue"
  },
  "geometry": {"coordinates":[-71.427669,42.491802],"type":"Point"}
}
