{
  "type": "Feature",
  "properties": {
    "iso:country":"US",
    "sg:address":"1 Acton Pl",
    "sg:city":"Acton",
    "sg:classifiers":[
        {
            "category":"Manufacturing",
            "subcategory":"Tools & Machinery",
            "type":"Manufacturing & Wholesale Goods"
        }
    ],
    "sg:phone":"+1 978 776 2000",
    "sg:postcode":"01720",
    "sg:province":"MA",
    "sg:tags":[
        "mill",
        "paper"
    ],
    "wof:name":"Kadant Inc",
    "wof:placetype":"venue"
},
  "geometry": {"coordinates":[-71.42766899999999,42.491802],"type":"Point"}
}