{
  "type": "Feature",
  "properties": {
    "addr:full":"9 Deacons Path Sandwich MA 02563",
    "addr:housenumber":"9",
    "addr:postcode":"02563",
    "addr:street":"Deacons Path",
    "iso:country":"US",
    "sg:address":"9 Deacons Path",
    "sg:city":"Sandwich",
    "sg:classifiers":[
        {
            "category":"Personal",
            "type":"Services"
        }
    ],
    "sg:phone":"+1 508 833 8314",
    "sg:postcode":"02563",
    "sg:province":"MA",
    "sg:tags":[
        "consultant",
        "planning",
        "wedding"
    ],
    "wof:name":"Elegant Engagements",
    "wof:placetype":"venue"
},
  "geometry": {"coordinates":[-70.486812,41.746546],"type":"Point"}
}