{
  "type": "Feature",
  "properties": {
    "iso:country":"US",
    "sg:address":"859 Bedford St",
    "sg:city":"Fall River",
    "sg:classifiers":[
        {
            "category":"Insurance",
            "subcategory":"Insurance Agent",
            "type":"Services"
        }
    ],
    "sg:phone":"+1 508 676 6328",
    "sg:postcode":"02723",
    "sg:province":"MA",
    "wof:name":"Resendes Insurance",
    "wof:placetype":"venue"
},
  "geometry": {"coordinates":[-71.13932699999999,41.698915],"type":"Point"}
}