{
  "type": "Feature",
  "properties": {
    "addr:full": "311 Arsenal St Watertown MA 02472",
    "addr:housenumber": "311",
    "addr:postcode": "02472",
    "addr:street": "Arsenal St",
    "iso:country": "US",
    "sg:address": "311 Arsenal St",
    "sg:city": "Watertown",
    "sg:classifiers": [
      {
        "category": "Professional",
        "subcategory": "Advertising",
        "type": "Services"
      }
    ],
    "sg:phone": "+1 617 972 1884",
    "sg:postcode": "02472",
    "sg:province": "MA",
    "sg:tags": [
      "promotion",
      "sale"
    ],
    "wof:name": "A\u0026G Brand Promotion",
    "wof:placetype": "venue"
  },
  "geometry": {"coordinates":[-71.169693,42.36409],"type":"Point"}
}
