{
  "type": "Feature",
  "properties": {
    "addr:full": "3267 Main St Barnstable Town MA 02630",
    "addr:housenumber": "3267",
    "addr:postcode": "02630",
    "addr:street": "Main St",
    "iso:country": "US",
    "sg:address": "3267 Main St",
    "sg:city": "Barnstable Town",
    "sg:classifiers": [
      {
        "category": "Arts \u0026 Performance",
        "subcategory": "Art Gallery",
        "type": "Entertainment"
      }
    ],
    "sg:postcode": "02630",
    "sg:province": "MA",
    "wof:name": "Barnstable Pottery",
    "wof:placetype": "venue"
  },
  "geometry": {"coordinates":[-70.303543,41.701634],"type":"Point"}
}
