{
  "type": "Feature",
  "properties": {
    "iso:country":"US",
    "sg:address":"110 Turnpike Rd",
    "sg:city":"Westborough",
    "sg:classifiers":[
        {
            "category":"Professional",
            "subcategory":"Computer Services",
            "type":"Services"
        }
    ],
    "sg:phone":"+1 508 599 2000",
    "sg:postcode":"01581",
    "sg:province":"MA",
    "sg:website":"www.openservice.com",
    "wof:name":"Openservice",
    "wof:placetype":"venue"
},
  "geometry": {"coordinates":[-71.602603,42.285063],"type":"Point"}
}