{
  "type": "Feature",
  "properties": {
    "addr:full": "101 Tremont St Boston MA 02108",
    "addr:housenumber": "101",
    "addr:postcode": "02108",
    "addr:street": "Tremont St",
    "iso:country": "US",
    "sg:address": "101 Tremont St",
    "sg:city": "Boston",
    "sg:classifiers": [
      {
        "category": "Professional",
        "subcategory": "Lawyer \u0026 Legal Services",
        "type": "Services"
      }
    ],
    "sg:phone": "+1 617 426 4460",
    "sg:postcode": "02108",
    "sg:province": "MA",
    "wof:name": "Mayers Abraham J Atty",
    "wof:placetype": "venue"
  },
  "geometry": {"coordinates":[-71.060898,42.357498],"type":"Point"}
}
