{
  "type": "Feature",
  "properties": {
    "addr:full":"127 Pleasant St Millis MA 02054",
    "addr:housenumber":"127",
    "addr:postcode":"02054",
    "addr:street":"Pleasant St",
    "iso:country":"US",
    "sg:address":"127 Pleasant St",
    "sg:city":"Millis",
    "sg:classifiers":[
        {
            "category":"Wholesale",
            "subcategory":"Meat",
            "type":"Manufacturing & Wholesale Goods"
        }
    ],
    "sg:phone":"+1 508 376 5547",
    "sg:postcode":"02054",
    "sg:province":"MA",
    "wof:name":"Metro West Provisions",
    "wof:placetype":"venue"
},
  "geometry": {"coordinates":[-71.36096499999999,42.151672],"type":"Point"}
}