{
  "type": "Feature",
  "properties": {
    "addr:full":"29 Bromfield St Boston MA 02108",
    "addr:housenumber":"29",
    "addr:postcode":"02108",
    "addr:street":"Bromfield St",
    "iso:country":"US",
    "sg:address":"29 Bromfield St",
    "sg:city":"Boston",
    "sg:classifiers":[
        {
            "category":"Shopping",
            "subcategory":"Hobbies, Toys, & Games",
            "type":"Retail Goods"
        },
        {
            "category":"Shopping",
            "subcategory":"Jewelry",
            "type":"Retail Goods"
        },
        {
            "category":"Manufacturing",
            "subcategory":"Jewelry",
            "type":"Manufacturing & Wholesale Goods"
        },
        {
            "category":"Government",
            "subcategory":"Post Office",
            "type":"Public Place"
        }
    ],
    "sg:phone":"+1 617 778 0409",
    "sg:postcode":"02108",
    "sg:province":"MA",
    "sg:tags":[
        "platinum",
        "diamond",
        "gold",
        "supply",
        "stamp",
        "buyer",
        "coin",
        "silver"
    ],
    "sg:website":"http://www.MinuteManCoin.net",
    "wof:name":"Minuteman Coin & Jewelry",
    "wof:placetype":"venue"
},
  "geometry": {"coordinates":[-71.060226,42.356689],"type":"Point"}
}