{
  "type": "Feature",
  "properties": {
    "iso:country":"US",
    "sg:address":"45 Plant Rd",
    "sg:city":"Hyannis",
    "sg:classifiers":[
        {
            "category":"Shopping",
            "type":"Retail Goods"
        }
    ],
    "sg:phone":"+1 508 771 2130",
    "sg:postcode":"02601",
    "sg:province":"MA",
    "sg:tags":[
        "trophy",
        "medal",
        "merchandise",
        "award"
    ],
    "wof:name":"East Coast Trophy & Engraving",
    "wof:placetype":"venue"
},
  "geometry": {"coordinates":[-70.295496,41.671446],"type":"Point"}
}