{
  "type": "Feature",
  "properties": {
    "iso:country":"US",
    "sg:address":"102 Pease Rd",
    "sg:city":"East Longmeadow",
    "sg:classifiers":[
        {
            "category":"Building & Trades",
            "subcategory":"Landscaping Services",
            "type":"Services"
        }
    ],
    "sg:phone":"+1 413 525 2825",
    "sg:postcode":"01028",
    "sg:province":"MA",
    "sg:tags":[
        "landscape",
        "contractor"
    ],
    "wof:name":"E Edward Pallotta",
    "wof:placetype":"venue"
},
  "geometry": {"coordinates":[-72.48902,42.044614],"type":"Point"}
}