{
  "type": "Feature",
  "properties": {
    "addr:full": "290 Barnstable Rd Hyannis MA 02601",
    "addr:housenumber": "290",
    "addr:postcode": "02601",
    "addr:street": "Barnstable Rd",
    "iso:country": "US",
    "ovtr:label": "Ocean State Job Lot, 390 Barnstable Rd Hyannis MA US",
    "ovtr:similarity": 3.4268128871917725,
    "sg:address": "290 Barnstable Rd",
    "sg:city": "Hyannis",
    "sg:classifiers": [
      {
        "category": "Wholesale",
        "subcategory": "Durable Goods \u0026 Equipment",
        "type": "Manufacturing \u0026 Wholesale Goods"
      }
    ],
    "sg:phone": "+1 508 790 2156",
    "sg:postcode": "02601",
    "sg:province": "MA",
    "sg:tags": [
      "job",
      "lot",
      "merchandise"
    ],
    "wof:name": "Ocean State Job Lot",
    "wof:placetype": "venue"
  },
  "geometry": {"coordinates":[-70.285549,41.661313],"type":"Point"}
}
