{
  "type": "Feature",
  "properties": {
    "iso:country":"US",
    "sg:address":"290 Barnstable Rd",
    "sg:city":"Hyannis",
    "sg:classifiers":[
        {
            "category":"Wholesale",
            "subcategory":"Durable Goods & Equipment",
            "type":"Manufacturing & Wholesale Goods"
        }
    ],
    "sg:phone":"+1 508 790 2156",
    "sg:postcode":"02601",
    "sg:province":"MA",
    "sg:tags":[
        "job",
        "lot",
        "merchandise"
    ],
    "wof:name":"Ocean State Job Lot",
    "wof:placetype":"venue"
},
  "geometry": {"coordinates":[-70.285549,41.661313],"type":"Point"}
}