{
  "type": "Feature",
  "properties": {
    "iso:country":"US",
    "sg:address":"544 Milford Rd",
    "sg:city":"Swansea",
    "sg:classifiers":[
        {
            "category":"Retail",
            "subcategory":"Animal Services",
            "type":"Services"
        }
    ],
    "sg:phone":"+1 508 677 0119",
    "sg:postcode":"02777",
    "sg:province":"MA",
    "sg:tags":[
        "pet",
        "grooming",
        "washing"
    ],
    "wof:name":"Spot Wash Groomers",
    "wof:placetype":"venue"
},
  "geometry": {"coordinates":[-71.215706,41.748872],"type":"Point"}
}