{
  "type": "Feature",
  "properties": {
    "addr:full": "2144 Boston Rd Wilbraham MA 01095",
    "addr:housenumber": "2144",
    "addr:postcode": "01095",
    "addr:street": "Boston Rd",
    "iso:country": "US",
    "sg:address": "2144 Boston Rd",
    "sg:city": "Wilbraham",
    "sg:classifiers": [
      {
        "category": "Bakery",
        "type": "Food \u0026 Drink"
      },
      {
        "category": "Coffee \u0026 Tea",
        "type": "Food \u0026 Drink"
      },
      {
        "category": "Bagels",
        "type": "Food \u0026 Drink"
      },
      {
        "category": "Donuts",
        "type": "Food \u0026 Drink"
      }
    ],
    "sg:menulink": "http://www.allmenus.com/ma/wilbraham/143539-dunkin-donuts/menu/",
    "sg:phone": "+1 413 596 5787",
    "sg:postcode": "01095",
    "sg:province": "MA",
    "sg:tags": [
      "american",
      "diner",
      "pastry"
    ],
    "wof:name": "Dunkin' Donuts",
    "wof:placetype": "venue"
  },
  "geometry": {"coordinates":[-72.470737,42.150212],"type":"Point"}
}
