{
  "type": "Feature",
  "properties": {
    "iso:country":"US",
    "sg:address":"826 Willard St",
    "sg:city":"Quincy",
    "sg:classifiers":[
        {
            "category":"Building & Trades",
            "subcategory":"Cleaning & Sanitation",
            "type":"Services"
        }
    ],
    "sg:phone":"+1 617 328 9090",
    "sg:postcode":"02169",
    "sg:province":"MA",
    "sg:tags":[
        "house"
    ],
    "wof:name":"Marvel Maids",
    "wof:placetype":"venue"
},
  "geometry": {"coordinates":[-71.030745,42.230322],"type":"Point"}
}