{
  "type": "Feature",
  "properties": {
    "addr:full": "109 2nd Ave Needham Heights MA 02494",
    "addr:housenumber": "109",
    "addr:postcode": "02494",
    "addr:street": "2Nd Ave",
    "iso:country": "US",
    "sg:address": "109 2nd Ave",
    "sg:city": "Needham Heights",
    "sg:classifiers": [
      {
        "category": "Real Estate",
        "subcategory": "Developer",
        "type": "Services"
      }
    ],
    "sg:phone": "+1 781 455 6646",
    "sg:postcode": "02494",
    "sg:province": "MA",
    "sg:website": "www.sleepave.com",
    "wof:name": "Sleep Ave LLC",
    "wof:placetype": "venue"
  },
  "geometry": {"coordinates":[-71.218822,42.304578],"type":"Point"}
}
