{
  "type": "Feature",
  "properties": {
    "addr:full":"151 Buffington Hill Rd Worthington MA 01098",
    "addr:housenumber":"151",
    "addr:postcode":"01098",
    "addr:street":"Buffington Hill Rd",
    "iso:country":"US",
    "sg:address":"151 Buffington Hill Rd",
    "sg:city":"Worthington",
    "sg:classifiers":[
        {
            "category":"Professional",
            "subcategory":"Business Services",
            "type":"Services"
        }
    ],
    "sg:phone":"+1 413 238 5813",
    "sg:postcode":"01098",
    "sg:province":"MA",
    "sg:tags":[
        "auctioneer"
    ],
    "wof:name":"Sena's Auction Barn",
    "wof:placetype":"venue"
},
  "geometry": {"coordinates":[-72.949544,42.413837],"type":"Point"}
}