{
  "type": "Feature",
  "properties": {
    "iso:country":"US",
    "sg:address":"133 Evelyn Rd",
    "sg:city":"Waban",
    "sg:classifiers":[
        {
            "category":"Personal",
            "subcategory":"Hair Removal",
            "type":"Services"
        }
    ],
    "sg:phone":"+1 617 796 9682",
    "sg:postcode":"02468",
    "sg:province":"MA",
    "sg:tags":[
        "reporting",
        "tax"
    ],
    "wof:name":"Shelly Miller Bernson",
    "wof:placetype":"venue"
},
  "geometry": {"coordinates":[-71.218642,42.334978],"type":"Point"}
}