{
  "type": "Feature",
  "properties": {
    "addr:full": "68 Mystic St Arlington MA 02474",
    "addr:housenumber": "68",
    "addr:postcode": "02474",
    "addr:street": "Mystic St",
    "iso:country": "US",
    "sg:address": "68 Mystic St",
    "sg:city": "Arlington",
    "sg:classifiers": [
      {
        "category": "Professional",
        "subcategory": "Engineering",
        "type": "Services"
      }
    ],
    "sg:phone": "+1   ",
    "sg:postcode": "02474",
    "sg:province": "MA",
    "wof:name": "Selverstone Peter",
    "wof:placetype": "venue"
  },
  "geometry": {"coordinates":[-71.150944,42.417566],"type":"Point"}
}
