{
  "type": "Feature",
  "properties": {
    "iso:country":"US",
    "sg:address":"404 N Washington St",
    "sg:city":"North Attleboro",
    "sg:classifiers":[
        {
            "category":"Retail",
            "subcategory":"Auto Repair",
            "type":"Services"
        }
    ],
    "sg:phone":"+1 508 699 5990",
    "sg:postcode":"02760",
    "sg:province":"MA",
    "sg:tags":[
        "repairing",
        "automobile"
    ],
    "wof:name":"Brennan's Auto Svc",
    "wof:placetype":"venue"
},
  "geometry": {"coordinates":[-71.32928,41.993378],"type":"Point"}
}