{
  "type": "Feature",
  "properties": {
    "addr:full": "314 Harvard St Brookline MA 02446",
    "addr:housenumber": "314",
    "addr:postcode": "02446",
    "addr:street": "Harvard St",
    "iso:country": "US",
    "sg:address": "314 Harvard St",
    "sg:city": "Brookline",
    "sg:classifiers": [
      {
        "category": "Shopping",
        "type": "Retail Goods"
      }
    ],
    "sg:phone": "+1 617 738 8817",
    "sg:postcode": "02446",
    "sg:province": "MA",
    "wof:name": "Delhi International Boutique",
    "wof:placetype": "venue"
  },
  "geometry": {"coordinates":[-71.123503,42.343157],"type":"Point"}
}
