{
  "type": "Feature",
  "properties": {
    "addr:full": "61 Cheshire Rd Pittsfield MA 01201",
    "addr:housenumber": "61",
    "addr:postcode": "01201",
    "addr:street": "Cheshire Rd",
    "iso:country": "US",
    "sg:address": "61 Cheshire Rd",
    "sg:city": "Pittsfield",
    "sg:classifiers": [
      {
        "category": "Wholesale",
        "subcategory": "Machinery \u0026 Supplies",
        "type": "Manufacturing \u0026 Wholesale Goods"
      }
    ],
    "sg:phone": "+1 413 442 2223",
    "sg:postcode": "01201",
    "sg:province": "MA",
    "sg:tags": [
      "salon",
      "beauty"
    ],
    "wof:name": "Ace Beauty Supply",
    "wof:placetype": "venue"
  },
  "geometry": {"coordinates":[-73.20378,42.468893],"type":"Point"}
}
