{
  "type": "Feature",
  "properties": {
    "iso:country":"US",
    "sg:address":"12 Main St",
    "sg:city":"Orleans",
    "sg:classifiers":[
        {
            "category":"Building & Trades",
            "subcategory":"Construction",
            "type":"Services"
        }
    ],
    "sg:phone":"+1 508 255 6743",
    "sg:postcode":"02653",
    "sg:province":"MA",
    "sg:tags":[
        "contractor"
    ],
    "wof:name":"Sisson Construction",
    "wof:placetype":"venue"
},
  "geometry": {"coordinates":[-69.99240399999999,41.788685],"type":"Point"}
}