{
  "type": "Feature",
  "properties": {
    "iso:country":"US",
    "sg:address":"714 Southbridge St",
    "sg:city":"Auburn",
    "sg:classifiers":[
        {
            "category":"Insurance",
            "subcategory":"Life Insurance",
            "type":"Services"
        }
    ],
    "sg:phone":"+1   ",
    "sg:postcode":"01501",
    "sg:province":"MA",
    "sg:tags":[
        "carrier"
    ],
    "wof:name":"Primerica",
    "wof:placetype":"venue"
},
  "geometry": {"coordinates":[-71.859599,42.183422],"type":"Point"}
}