{
  "type": "Feature",
  "properties": {
    "addr:full": "84 Highland Ave Salem MA 01970",
    "addr:housenumber": "84",
    "addr:postcode": "01970",
    "addr:street": "Highland Ave",
    "iso:country": "US",
    "ovtr:label": "Star Dry Cleaners Salem, 84 Highland Ave Salem MA US",
    "ovtr:similarity": 2.7023940086364746,
    "sg:address": "84 Highland Ave",
    "sg:city": "Salem",
    "sg:classifiers": [
      {
        "category": "Retail",
        "subcategory": "Laundry \u0026 Dry Cleaning",
        "type": "Services"
      }
    ],
    "sg:phone": "+1 978 741 7827",
    "sg:postcode": "01970",
    "sg:province": "MA",
    "sg:tags": [
      "cleaners"
    ],
    "wof:name": "Star Dry Cleaners",
    "wof:placetype": "venue"
  },
  "geometry": {"coordinates":[-70.908431,42.512173],"type":"Point"}
}
