{
  "type": "Feature",
  "properties": {
    "iso:country":"US",
    "sg:address":"46 Powder Mill Rd",
    "sg:city":"Southwick",
    "sg:classifiers":[
        {
            "category":"Organizations",
            "subcategory":"Community Association",
            "type":"Services"
        }
    ],
    "sg:phone":"+1 413 569 5177",
    "sg:postcode":"01077",
    "sg:province":"MA",
    "sg:tags":[
        "military"
    ],
    "wof:name":"American Legion",
    "wof:placetype":"venue"
},
  "geometry": {"coordinates":[-72.755696,42.057507],"type":"Point"}
}