{
  "type": "Feature",
  "properties": {
    "addr:full": "38 E Main St Georgetown MA 01833",
    "addr:housenumber": "38",
    "addr:postcode": "01833",
    "addr:street": "E Main St",
    "iso:country": "US",
    "sg:address": "38 E Main St",
    "sg:city": "Georgetown",
    "sg:classifiers": [
      {
        "category": "Banks \u0026 Credit Unions",
        "subcategory": "Bank",
        "type": "Services"
      }
    ],
    "sg:phone": "+1 978 000 1111",
    "sg:postcode": "01833",
    "sg:province": "MA",
    "wof:name": "Bank Of America",
    "wof:placetype": "venue"
  },
  "geometry": {"coordinates":[-70.990597,42.723934],"type":"Point"}
}
