{
  "type": "Feature",
  "properties": {
    "iso:country":"US",
    "sg:address":"38 E Main St",
    "sg:city":"Georgetown",
    "sg:classifiers":[
        {
            "category":"Banks & Credit Unions",
            "subcategory":"Bank",
            "type":"Services"
        }
    ],
    "sg:phone":"+1 978 000 1111",
    "sg:postcode":"01833",
    "sg:province":"MA",
    "wof:name":"Bank Of America",
    "wof:placetype":"venue"
},
  "geometry": {"coordinates":[-70.99059699999999,42.723934],"type":"Point"}
}