{
  "type": "Feature",
  "properties": {
    "addr:full": "25 Grant St Waltham MA 02453",
    "addr:housenumber": "25",
    "addr:postcode": "02453",
    "addr:street": "Grant St",
    "iso:country": "US",
    "sg:address": "25 Grant St",
    "sg:city": "Waltham",
    "sg:classifiers": [
      {
        "category": "Building \u0026 Trades",
        "subcategory": "Construction",
        "type": "Services"
      }
    ],
    "sg:phone": "+1 781 899 5300",
    "sg:postcode": "02453",
    "sg:province": "MA",
    "sg:tags": [
      "roofing",
      "contractor"
    ],
    "wof:name": "G Gagnon \u0026 Brothers Roofing",
    "wof:placetype": "venue"
  },
  "geometry": {"coordinates":[-71.241713,42.376052],"type":"Point"}
}
