{
  "type": "Feature",
  "properties": {
    "addr:full":"100 Village Shoppes Canton MA 02021",
    "addr:housenumber":"100",
    "addr:postcode":"02021",
    "addr:street":"Village Shoppes",
    "iso:country":"US",
    "sg:address":"100 Village Shoppes",
    "sg:city":"Canton",
    "sg:classifiers":[
        {
            "category":"Coffee & Tea",
            "type":"Food & Drink"
        }
    ],
    "sg:phone":"+1 781 830 9136",
    "sg:postcode":"02021",
    "sg:province":"MA",
    "sg:website":"www.starbucks.com",
    "wof:name":"Starbucks Coffee",
    "wof:placetype":"venue"
},
  "geometry": {"coordinates":[-71.127701,42.164101],"type":"Point"}
}