{
  "type": "Feature",
  "properties": {
    "addr:full": "119 Dayton St Danvers MA 01923",
    "addr:housenumber": "119",
    "addr:postcode": "01923",
    "addr:street": "Dayton St",
    "iso:country": "US",
    "sg:address": "119 Dayton St",
    "sg:city": "Danvers",
    "sg:classifiers": [
      {
        "category": "Building \u0026 Trades",
        "subcategory": "Construction",
        "type": "Services"
      }
    ],
    "sg:phone": "+1   ",
    "sg:postcode": "01923",
    "sg:province": "MA",
    "sg:tags": [
      "carpentry",
      "contractor"
    ],
    "wof:name": "Guays Architectural Cnstr",
    "wof:placetype": "venue"
  },
  "geometry": {"coordinates":[-70.982252,42.576],"type":"Point"}
}
