{
  "type": "Feature",
  "properties": {
    "addr:full":"14 Page Ter Stoughton MA 02072",
    "addr:housenumber":"14",
    "addr:postcode":"02072",
    "addr:street":"Page Ter",
    "iso:country":"US",
    "sg:address":"14 Page Ter",
    "sg:city":"Stoughton",
    "sg:classifiers":[
        {
            "category":"Professional",
            "subcategory":"Management & Consulting",
            "type":"Services"
        }
    ],
    "sg:phone":"+1 781 367 4780",
    "sg:postcode":"02072",
    "sg:province":"MA",
    "sg:tags":[
        "consultant",
        "motel",
        "hotel"
    ],
    "wof:name":"Buffalo Lodging Assoc Ne Regl",
    "wof:placetype":"venue"
},
  "geometry": {"coordinates":[-71.07598299999999,42.15107],"type":"Point"}
}