{
  "type": "Feature",
  "properties": {
    "addr:full":"125 Main St Spencer MA 01562",
    "addr:housenumber":"125",
    "addr:postcode":"01562",
    "addr:street":"Main St",
    "iso:country":"US",
    "sg:address":"125 Main St",
    "sg:city":"Spencer",
    "sg:classifiers":[
        {
            "category":"Personal",
            "subcategory":"Tanning Parlor",
            "type":"Services"
        }
    ],
    "sg:phone":"+1 508 885 4100",
    "sg:postcode":"01562",
    "sg:province":"MA",
    "sg:tags":[
        "salon"
    ],
    "wof:name":"Under The Sun",
    "wof:placetype":"venue"
},
  "geometry": {"coordinates":[-71.994783,42.243883],"type":"Point"}
}