{
  "type": "Feature",
  "properties": {
    "iso:country":"US",
    "sg:address":"288 Norfolk St. Suite 4",
    "sg:city":"Cambridge",
    "sg:classifiers":[
        {
            "category":"Professional",
            "subcategory":"Research",
            "type":"Services"
        }
    ],
    "sg:phone":"+1 617 313 0822",
    "sg:postcode":"02139",
    "sg:province":"MA",
    "sg:tags":[
        "transportation",
        "regenerative",
        "shock-absorbers",
        "fuel-efficiency",
        "automotive",
        "heavy-trucking",
        "defense",
        "hybrids"
    ],
    "sg:website":"http://www.levantpower.com",
    "wof:name":"Levant Power",
    "wof:placetype":"venue"
},
  "geometry": {"coordinates":[-71.096351,42.37269],"type":"Point"}
}