{
  "type": "Feature",
  "properties": {
    "iso:country":"US",
    "sg:address":"75 Edwin St",
    "sg:city":"Dorchester Ctr",
    "sg:classifiers":[
        {
            "category":"Professional",
            "subcategory":"Business Services",
            "type":"Services"
        }
    ],
    "sg:phone":"+1 617 288 5022",
    "sg:postcode":"02124",
    "sg:province":"MA",
    "wof:name":"Circle Of Svc Unlimited",
    "wof:placetype":"venue"
},
  "geometry": {"coordinates":[-71.060501,42.289248],"type":"Point"}
}