{
  "type": "Feature",
  "properties": {
    "iso:country":"US",
    "sg:address":"192 Pearl St",
    "sg:city":"Springfield",
    "sg:classifiers":[
        {
            "category":"Retail",
            "subcategory":"Auto Repair",
            "type":"Services"
        }
    ],
    "sg:phone":"+1   ",
    "sg:postcode":"01105",
    "sg:province":"MA",
    "sg:tags":[
        "automotive",
        "customizing"
    ],
    "wof:name":"Lovada Stephan",
    "wof:placetype":"venue"
},
  "geometry": {"coordinates":[-72.58238900000001,42.110205],"type":"Point"}
}