{
  "type": "Feature",
  "properties": {
    "addr:full": "192 Pearl St Springfield MA 01105",
    "addr:housenumber": "192",
    "addr:postcode": "01105",
    "addr:street": "Pearl St",
    "iso:country": "US",
    "sg:address": "192 Pearl St",
    "sg:city": "Springfield",
    "sg:classifiers": [
      {
        "category": "Retail",
        "subcategory": "Auto Repair",
        "type": "Services"
      }
    ],
    "sg:phone": "+1   ",
    "sg:postcode": "01105",
    "sg:province": "MA",
    "sg:tags": [
      "automotive",
      "customizing"
    ],
    "wof:name": "Lovada Stephan",
    "wof:placetype": "venue"
  },
  "geometry": {"coordinates":[-72.582389,42.110205],"type":"Point"}
}
