{
  "type": "Feature",
  "properties": {
    "iso:country":"US",
    "sg:address":"32 Baker St",
    "sg:city":"Foxboro",
    "sg:classifiers":[
        {
            "category":"Health Services",
            "subcategory":"Health Practitioner",
            "type":"Services"
        }
    ],
    "sg:phone":"+1 508 543 8888",
    "sg:postcode":"02035",
    "sg:province":"MA",
    "sg:tags":[
        "psychotherapist"
    ],
    "wof:name":"Marsha L Getter Psychothrpst",
    "wof:placetype":"venue"
},
  "geometry": {"coordinates":[-71.25152199999999,42.069656],"type":"Point"}
}