{
  "type": "Feature",
  "properties": {
    "addr:full": "97 Webster St Worcester MA 01603",
    "addr:housenumber": "97",
    "addr:postcode": "01603",
    "addr:street": "Webster St",
    "iso:country": "US",
    "sg:address": "97 Webster St",
    "sg:city": "Worcester",
    "sg:classifiers": [
      {
        "category": "Recreation",
        "type": "Entertainment"
      }
    ],
    "sg:phone": "+1 508 799 9106",
    "sg:postcode": "01603",
    "sg:province": "MA",
    "sg:tags": [
      "martial",
      "arts",
      "instruction"
    ],
    "wof:name": "Zenshinkan Aikido Dojo",
    "wof:placetype": "venue"
  },
  "geometry": {"coordinates":[-71.832634,42.240772],"type":"Point"}
}
