{
  "type": "Feature",
  "properties": {
    "addr:full":"1561 Acushnet Ave New Bedford MA 02746",
    "addr:housenumber":"1561",
    "addr:postcode":"02746",
    "addr:street":"Acushnet Ave",
    "iso:country":"US",
    "sg:address":"1561 Acushnet Ave",
    "sg:city":"New Bedford",
    "sg:classifiers":[
        {
            "category":"Professional",
            "type":"Services"
        }
    ],
    "sg:phone":"+1 508 992 8649",
    "sg:postcode":"02746",
    "sg:province":"MA",
    "sg:tags":[
        "establishment"
    ],
    "wof:name":"Angelina's",
    "wof:placetype":"venue"
},
  "geometry": {"coordinates":[-70.928501,41.662995],"type":"Point"}
}