{
  "type": "Feature",
  "properties": {
    "iso:country":"US",
    "sg:address":"231 Main St",
    "sg:city":"Marlborough",
    "sg:classifiers":[
        {
            "category":"Restaurant",
            "type":"Food & Drink"
        }
    ],
    "sg:phone":"+1 508 481 9509",
    "sg:postcode":"01752",
    "sg:province":"MA",
    "wof:name":"Escargot Restaurant",
    "wof:placetype":"venue"
},
  "geometry": {"coordinates":[-71.551012,42.346572],"type":"Point"}
}