{
  "type": "Feature",
  "properties": {
    "addr:full": "8 Craig St Carver MA 02330",
    "addr:housenumber": "8",
    "addr:postcode": "02330",
    "addr:street": "Craig St",
    "iso:country": "US",
    "sg:address": "8 Craig St",
    "sg:city": "Carver",
    "sg:classifiers": [
      {
        "category": "Building \u0026 Trades",
        "subcategory": "Construction",
        "type": "Services"
      }
    ],
    "sg:phone": "+1 617 288 3448",
    "sg:postcode": "02330",
    "sg:province": "MA",
    "sg:tags": [
      "roofing",
      "contractor"
    ],
    "wof:name": "Mc Donnell Roofing Co",
    "wof:placetype": "venue"
  },
  "geometry": {"coordinates":[-70.793811,41.895818],"type":"Point"}
}
