{
  "type": "Feature",
  "properties": {
    "addr:full":"40 West St Belchertown MA 01007",
    "addr:housenumber":"40",
    "addr:postcode":"01007",
    "addr:street":"West St",
    "iso:country":"US",
    "sg:address":"40 West St",
    "sg:city":"Belchertown",
    "sg:classifiers":[
        {
            "category":"Building & Trades",
            "subcategory":"Cleaning & Sanitation",
            "type":"Services"
        }
    ],
    "sg:phone":"+1 978 835 9868",
    "sg:postcode":"01007",
    "sg:province":"MA",
    "sg:tags":[
        "polish"
    ],
    "sg:website":"http://www.steadfastinternational.com",
    "wof:name":"Steadfast International Inc",
    "wof:placetype":"venue"
},
  "geometry": {"coordinates":[-72.368945,42.209821],"type":"Point"}
}