{
  "type": "Feature",
  "properties": {
    "addr:full":"346 Merrimac St # R Newburyport MA 01950",
    "addr:housenumber":"346",
    "addr:postcode":"01950",
    "addr:street":"Merrimac St # R",
    "iso:country":"US",
    "sg:address":"346 Merrimac St # R",
    "sg:city":"Newburyport",
    "sg:classifiers":[
        {
            "category":"Building & Trades",
            "subcategory":"Plumbing",
            "type":"Services"
        }
    ],
    "sg:phone":"+1 978 465 5729",
    "sg:postcode":"01950",
    "sg:province":"MA",
    "wof:name":"Welch Peter E Plumbing & Heating",
    "wof:placetype":"venue"
},
  "geometry": {"coordinates":[-70.8862,42.821899],"type":"Point"}
}