{
  "type": "Feature",
  "properties": {
    "addr:full":"749 Main St Reading MA 01867",
    "addr:housenumber":"749",
    "addr:postcode":"01867",
    "addr:street":"Main St",
    "iso:country":"US",
    "sg:address":"749 Main St",
    "sg:city":"Reading",
    "sg:classifiers":[
        {
            "category":"Autos & Motor Vehicles",
            "subcategory":"Fuel & Gas Station",
            "type":"Retail Goods"
        }
    ],
    "sg:phone":"+1 781 944 6177",
    "sg:postcode":"01867",
    "sg:province":"MA",
    "wof:name":"Reading Square Texaco",
    "wof:placetype":"venue"
},
  "geometry": {"coordinates":[-71.10279800000001,42.524399],"type":"Point"}
}