{
  "type": "Feature",
  "properties": {
    "addr:full": "199 Sudbury Rd Concord MA 01742",
    "addr:housenumber": "199",
    "addr:postcode": "01742",
    "addr:street": "Sudbury Rd",
    "iso:country": "US",
    "sg:address": "199 Sudbury Rd",
    "sg:city": "Concord",
    "sg:classifiers": [
      {
        "category": "Real Estate",
        "subcategory": "Real Estate Services",
        "type": "Services"
      }
    ],
    "sg:phone": "+1 978 369 1982",
    "sg:postcode": "01742",
    "sg:province": "MA",
    "sg:website": "www.boyntoncompany.com",
    "wof:name": "Boynton Company",
    "wof:placetype": "venue"
  },
  "geometry": {"coordinates":[-71.356201,42.455799],"type":"Point"}
}
