{
  "type": "Feature",
  "properties": {
    "addr:full":"2660 Boston Rd Wilbraham MA 01095",
    "addr:housenumber":"2660",
    "addr:postcode":"01095",
    "addr:street":"Boston Rd",
    "iso:country":"US",
    "sg:address":"2660 Boston Rd",
    "sg:city":"Wilbraham",
    "sg:classifiers":[
        {
            "category":"Mining & Drilling",
            "type":"Manufacturing & Wholesale Goods"
        }
    ],
    "sg:phone":"+1 413 596 4453",
    "sg:postcode":"01095",
    "sg:province":"MA",
    "sg:tags":[
        "stone"
    ],
    "wof:name":"Stoney Hill Sand & Gravel",
    "wof:placetype":"venue"
},
  "geometry": {"coordinates":[-72.432957,42.151385],"type":"Point"}
}