{
  "type": "Feature",
  "properties": {
    "addr:full":"191 Cabot St Beverly MA 01915",
    "addr:housenumber":"191",
    "addr:postcode":"01915",
    "addr:street":"Cabot St",
    "iso:country":"US",
    "sg:address":"191 Cabot St",
    "sg:city":"Beverly",
    "sg:classifiers":[
        {
            "category":"Government",
            "subcategory":"Office",
            "type":"Public Place"
        }
    ],
    "sg:phone":"+1 978 921 6030",
    "sg:postcode":"01915",
    "sg:province":"MA",
    "sg:tags":[
        "village"
    ],
    "wof:name":"Beverly Cemetery Dept",
    "wof:placetype":"venue"
},
  "geometry": {"coordinates":[-70.878888,42.547701],"type":"Point"}
}