{
  "type": "Feature",
  "properties": {
    "addr:full":"285 Morse St Norwood MA 02062",
    "addr:housenumber":"285",
    "addr:postcode":"02062",
    "addr:street":"Morse St",
    "iso:country":"US",
    "sg:address":"285 Morse St",
    "sg:city":"Norwood",
    "sg:classifiers":[
        {
            "category":"Donuts",
            "subcategory":"None",
            "type":"Food & Drink"
        }
    ],
    "sg:phone":"+1 781 551 9919",
    "sg:postcode":"02062",
    "sg:province":"MA",
    "wof:name":"Honey Dew Donuts",
    "wof:placetype":"venue"
},
  "geometry": {"coordinates":[-71.198303,42.171101],"type":"Point"}
}