{
  "type": "Feature",
  "properties": {
    "addr:full":"499B Washington St Boston MA 02111",
    "addr:housenumber":"499b",
    "addr:postcode":"02111",
    "addr:street":"Washington St",
    "iso:country":"US",
    "sg:address":"499B Washington St",
    "sg:city":"Boston",
    "sg:classifiers":[
        {
            "category":"Professional",
            "type":"Services"
        }
    ],
    "sg:phone":"+1 617 265 2220",
    "sg:postcode":"02111",
    "sg:province":"MA",
    "sg:tags":[
        "caterer"
    ],
    "sg:website":"www.perrysgourmet.com",
    "wof:name":"Perry's Gourmet Service",
    "wof:placetype":"venue"
},
  "geometry": {"coordinates":[-71.061611,42.354659],"type":"Point"}
}