{
  "type": "Feature",
  "properties": {
    "iso:country":"US",
    "sg:address":"75 Washington St",
    "sg:city":"Marblehead",
    "sg:classifiers":[
        {
            "category":"Restaurant",
            "type":"Food & Drink"
        }
    ],
    "sg:phone":"+1 781 631 8993",
    "sg:postcode":"01945",
    "sg:province":"MA",
    "sg:tags":[
        "eating"
    ],
    "wof:name":"Sandwich Shop",
    "wof:placetype":"venue"
},
  "geometry": {"coordinates":[-70.84877299999999,42.505925],"type":"Point"}
}