{
  "type": "Feature",
  "properties": {
    "addr:full": "75 Washington St Marblehead MA 01945",
    "addr:housenumber": "75",
    "addr:postcode": "01945",
    "addr:street": "Washington St",
    "iso:country": "US",
    "sg:address": "75 Washington St",
    "sg:city": "Marblehead",
    "sg:classifiers": [
      {
        "category": "Restaurant",
        "type": "Food \u0026 Drink"
      }
    ],
    "sg:phone": "+1 781 631 8993",
    "sg:postcode": "01945",
    "sg:province": "MA",
    "sg:tags": [
      "eating"
    ],
    "wof:name": "Sandwich Shop",
    "wof:placetype": "venue"
  },
  "geometry": {"coordinates":[-70.848773,42.505925],"type":"Point"}
}
