{
  "type": "Feature",
  "properties": {
    "addr:full": "14 Loblolly Ln Wayland MA 01778",
    "addr:housenumber": "14",
    "addr:postcode": "01778",
    "addr:street": "Loblolly Ln",
    "iso:country": "US",
    "sg:address": "14 Loblolly Ln",
    "sg:city": "Wayland",
    "sg:classifiers": [
      {
        "category": "Professional",
        "subcategory": "Management \u0026 Consulting",
        "type": "Services"
      }
    ],
    "sg:phone": "+1   ",
    "sg:postcode": "01778",
    "sg:province": "MA",
    "sg:tags": [
      "business"
    ],
    "wof:name": "Alan Vogt Database Consulting",
    "wof:placetype": "venue"
  },
  "geometry": {"coordinates":[-71.362334,42.383267],"type":"Point"}
}
