{
  "type": "Feature",
  "properties": {
    "iso:country":"US",
    "sg:address":"818 Kempton St",
    "sg:city":"New Bedford",
    "sg:classifiers":[
        {
            "category":"Bars & Pubs",
            "type":"Food & Drink"
        }
    ],
    "sg:phone":"+1 508 993 0990",
    "sg:postcode":"02740",
    "sg:province":"MA",
    "wof:name":"Irish Immigrant Pub",
    "wof:placetype":"venue"
},
  "geometry": {"coordinates":[-70.947328,41.635545],"type":"Point"}
}