{
  "type": "Feature",
  "properties": {
    "addr:full":"26 Main St Orleans MA 02653",
    "addr:housenumber":"26",
    "addr:postcode":"02653",
    "addr:street":"Main St",
    "iso:country":"US",
    "sg:address":"26 Main St",
    "sg:city":"Orleans",
    "sg:classifiers":[
        {
            "category":"Shopping",
            "type":"Retail Goods"
        }
    ],
    "sg:phone":"+1 508 240 1063",
    "sg:postcode":"02653",
    "sg:province":"MA",
    "sg:tags":[
        "cards",
        "sport",
        "baseball",
        "memorabilia"
    ],
    "wof:name":"Baseball Shop",
    "wof:placetype":"venue"
},
  "geometry": {"coordinates":[-69.992024,41.788386],"type":"Point"}
}