{
  "type": "Feature",
  "properties": {
    "addr:full": "476 Purchase St New Bedford MA 02740",
    "addr:housenumber": "476",
    "addr:postcode": "02740",
    "addr:street": "Purchase St",
    "iso:country": "US",
    "sg:address": "476 Purchase St",
    "sg:city": "New Bedford",
    "sg:classifiers": [
      {
        "category": "Freight",
        "type": "Transportation"
      }
    ],
    "sg:phone": "+1   ",
    "sg:postcode": "02740",
    "sg:province": "MA",
    "sg:tags": [
      "operator",
      "local",
      "trucking"
    ],
    "wof:name": "T R C Trucking",
    "wof:placetype": "venue"
  },
  "geometry": {"coordinates":[-70.925146,41.630678],"type":"Point"}
}
