{
  "type": "Feature",
  "properties": {
    "addr:full": "51 Bacon Hill Rd Spencer MA 01562",
    "addr:housenumber": "51",
    "addr:postcode": "01562",
    "addr:street": "Bacon Hill Rd",
    "iso:country": "US",
    "sg:address": "51 Bacon Hill Rd",
    "sg:city": "Spencer",
    "sg:classifiers": [
      {
        "category": "Building \u0026 Trades",
        "subcategory": "Construction",
        "type": "Services"
      }
    ],
    "sg:phone": "+1 508 885 4143",
    "sg:postcode": "01562",
    "sg:province": "MA",
    "sg:tags": [
      "plastering",
      "contractor"
    ],
    "wof:name": "Todd Vitkos Plastering Inc",
    "wof:placetype": "venue"
  },
  "geometry": {"coordinates":[-71.980469,42.199716],"type":"Point"}
}
