{
  "type": "Feature",
  "properties": {
    "iso:country":"US",
    "sg:address":"4467 Washington St",
    "sg:city":"Roslindale",
    "sg:classifiers":[
        {
            "category":"Health Services",
            "subcategory":"Health Practitioner",
            "type":"Services"
        }
    ],
    "sg:phone":"+1 617 469 6700",
    "sg:postcode":"02131",
    "sg:province":"MA",
    "sg:tags":[
        "pathologist",
        "speech"
    ],
    "sg:website":"www.on-sitetherapists.com",
    "wof:name":"On-Site Therapists",
    "wof:placetype":"venue"
},
  "geometry": {"coordinates":[-71.134928,42.280117],"type":"Point"}
}