{
  "type": "Feature",
  "properties": {
    "addr:full":"715 Broadway Everett MA 02149",
    "addr:housenumber":"715",
    "addr:postcode":"02149",
    "addr:street":"Broadway",
    "iso:country":"US",
    "sg:address":"715 Broadway",
    "sg:city":"Everett",
    "sg:classifiers":[
        {
            "category":"Personal",
            "subcategory":"Barber",
            "type":"Services"
        }
    ],
    "sg:phone":"+1 617 381 9559",
    "sg:postcode":"02149",
    "sg:province":"MA",
    "wof:name":"Lou Diamond's Barbershop",
    "wof:placetype":"venue"
},
  "geometry": {"coordinates":[-71.048359,42.414777],"type":"Point"}
}