{
  "type": "Feature",
  "properties": {
    "addr:full": "20 Charlotte St Dorchester MA 02121",
    "addr:housenumber": "20",
    "addr:postcode": "02121",
    "addr:street": "Charlotte St",
    "iso:country": "US",
    "sg:address": "20 Charlotte St",
    "sg:city": "Dorchester",
    "sg:classifiers": [
      {
        "category": "Organizations",
        "subcategory": "Religious Organization",
        "type": "Services"
      }
    ],
    "sg:phone": "+1 617 427 8797",
    "sg:postcode": "02121",
    "sg:province": "MA",
    "sg:tags": [
      "church"
    ],
    "wof:name": "Asambleas Cristianas Unidas",
    "wof:placetype": "venue"
  },
  "geometry": {"coordinates":[-71.084055,42.298903],"type":"Point"}
}
