{
  "type": "Feature",
  "properties": {
    "addr:full":"36 Chestnut St Marblehead MA 01945",
    "addr:housenumber":"36",
    "addr:postcode":"01945",
    "addr:street":"Chestnut St",
    "iso:country":"US",
    "sg:address":"36 Chestnut St",
    "sg:city":"Marblehead",
    "sg:classifiers":[
        {
            "category":"Professional",
            "type":"Services"
        }
    ],
    "sg:phone":"+1 781 631 9536",
    "sg:postcode":"01945",
    "sg:province":"MA",
    "sg:tags":[
        "establishment"
    ],
    "wof:name":"Management Design Assoc Inc",
    "wof:placetype":"venue"
},
  "geometry": {"coordinates":[-70.856937,42.497443],"type":"Point"}
}