{
  "type": "Feature",
  "properties": {
    "iso:country":"US",
    "sg:address":"130 S Broadway",
    "sg:city":"Lawrence",
    "sg:classifiers":[
        {
            "category":"Shopping",
            "subcategory":"Clothing, Apparel, & Fashions",
            "type":"Retail Goods"
        }
    ],
    "sg:phone":"+1 978 686 6676",
    "sg:postcode":"01843",
    "sg:province":"MA",
    "sg:tags":[
        "work"
    ],
    "wof:name":"O'Neill Golf & Sport",
    "wof:placetype":"venue"
},
  "geometry": {"coordinates":[-71.162735,42.695884],"type":"Point"}
}