{
  "type": "Feature",
  "properties": {
    "addr:full": "130 S Broadway Lawrence MA 01843",
    "addr:housenumber": "130",
    "addr:postcode": "01843",
    "addr:street": "S Broadway",
    "iso:country": "US",
    "sg:address": "130 S Broadway",
    "sg:city": "Lawrence",
    "sg:classifiers": [
      {
        "category": "Shopping",
        "subcategory": "Clothing, Apparel, \u0026 Fashions",
        "type": "Retail Goods"
      }
    ],
    "sg:phone": "+1 978 686 6676",
    "sg:postcode": "01843",
    "sg:province": "MA",
    "sg:tags": [
      "work"
    ],
    "wof:name": "O'Neill Golf \u0026 Sport",
    "wof:placetype": "venue"
  },
  "geometry": {"coordinates":[-71.162735,42.695884],"type":"Point"}
}
