{
  "type": "Feature",
  "properties": {
    "addr:full": "131 Samoset St Plymouth MA 02360",
    "addr:housenumber": "131",
    "addr:postcode": "02360",
    "addr:street": "Samoset St",
    "iso:country": "US",
    "ovtr:label": "Staples, 131 Samoset St Plymouth MA US",
    "ovtr:similarity": 2.62552809715271,
    "sg:address": "131 Samoset St",
    "sg:city": "Plymouth",
    "sg:classifiers": [
      {
        "category": "Shopping",
        "subcategory": "Stationery \u0026 Office Supplies",
        "type": "Retail Goods"
      }
    ],
    "sg:phone": "+1 508 746 5215",
    "sg:postcode": "02360",
    "sg:province": "MA",
    "sg:tags": [
      "equipment"
    ],
    "sg:website": "www.staples.com",
    "wof:name": "Staples",
    "wof:placetype": "venue"
  },
  "geometry": {"coordinates":[-70.684384,41.953667],"type":"Point"}
}
