{
  "type": "Feature",
  "properties": {
    "addr:full": "190 North St Pittsfield MA 01201",
    "addr:housenumber": "190",
    "addr:postcode": "01201",
    "addr:street": "North St",
    "iso:country": "US",
    "sg:address": "190 North St",
    "sg:city": "Pittsfield",
    "sg:classifiers": [
      {
        "category": "Government",
        "subcategory": "Court House",
        "type": "Public Place"
      }
    ],
    "sg:phone": "+1   ",
    "sg:postcode": "01201",
    "sg:province": "MA",
    "wof:name": "County Msschtte Jvnile Crt Div",
    "wof:placetype": "venue"
  },
  "geometry": {"coordinates":[-73.253208,42.450402],"type":"Point"}
}
