{
  "type": "Feature",
  "properties": {
    "addr:full":"32 Bearskin Neck Rockport MA 01966",
    "addr:housenumber":"32",
    "addr:postcode":"01966",
    "addr:street":"Bearskin Neck",
    "iso:country":"US",
    "sg:address":"32 Bearskin Neck",
    "sg:city":"Rockport",
    "sg:classifiers":[
        {
            "category":"Restaurant",
            "type":"Food & Drink"
        }
    ],
    "sg:phone":"+1 978 546 0090",
    "sg:postcode":"01966",
    "sg:province":"MA",
    "wof:name":"Prticella Bistro",
    "wof:placetype":"venue"
},
  "geometry": {"coordinates":[-70.615651,42.659854],"type":"Point"}
}