{
  "type": "Feature",
  "properties": {
    "addr:full": "84 Prospect St Somerville MA 02143",
    "addr:housenumber": "84",
    "addr:postcode": "02143",
    "addr:street": "Prospect St",
    "iso:country": "US",
    "sg:address": "84 Prospect St",
    "sg:city": "Somerville",
    "sg:classifiers": [
      {
        "category": "Wholesale",
        "subcategory": "Machinery \u0026 Supplies",
        "type": "Manufacturing \u0026 Wholesale Goods"
      }
    ],
    "sg:phone": "+1 617 482 6100",
    "sg:postcode": "02143",
    "sg:province": "MA",
    "sg:tags": [
      "fire",
      "department",
      "equipment"
    ],
    "wof:name": "Fire Escape Svc",
    "wof:placetype": "venue"
  },
  "geometry": {"coordinates":[-71.096154,42.376166],"type":"Point"}
}
