{
  "type": "Feature",
  "properties": {
    "iso:country":"US",
    "sg:address":"7 Maymont Dr",
    "sg:city":"Framingham",
    "sg:classifiers":[
        {
            "category":"Health Services",
            "subcategory":"Chiropractor",
            "type":"Services"
        }
    ],
    "sg:phone":"+1 508 405 0777",
    "sg:postcode":"01701",
    "sg:province":"MA",
    "wof:name":"Framingham Sports & Family",
    "wof:placetype":"venue"
},
  "geometry": {"coordinates":[-71.386061,42.315631],"type":"Point"}
}