{
  "type": "Feature",
  "properties": {
    "addr:full": "19 Pinckney St Boston MA 02114",
    "addr:housenumber": "19",
    "addr:postcode": "02114",
    "addr:street": "Pinckney St",
    "iso:country": "US",
    "sg:address": "19 Pinckney St",
    "sg:city": "Boston",
    "sg:classifiers": [
      {
        "category": "Health Services",
        "subcategory": "Doctor",
        "type": "Services"
      }
    ],
    "sg:phone": "+1 617 523 3800",
    "sg:postcode": "02114",
    "sg:province": "MA",
    "sg:website": "www.odysseyjourney.com",
    "wof:name": "Odyssey Journey",
    "wof:placetype": "venue"
  },
  "geometry": {"coordinates":[-71.065843,42.358993],"type":"Point"}
}
