{
  "type": "Feature",
  "properties": {
    "iso:country":"US",
    "sg:address":"1101 Beacon St Ste 201W",
    "sg:city":"Brookline",
    "sg:classifiers":[
        {
            "category":"Health Services",
            "subcategory":"Doctor",
            "type":"Services"
        }
    ],
    "sg:phone":"+1 617 731 4400",
    "sg:postcode":"02446",
    "sg:province":"MA",
    "wof:name":"Goldberg William E MD",
    "wof:placetype":"venue"
},
  "geometry": {"coordinates":[-71.110822,42.344748],"type":"Point"}
}