{
  "type": "Feature",
  "properties": {
    "addr:full":"213 Dexter Ave Watertown MA 02472",
    "addr:housenumber":"213",
    "addr:postcode":"02472",
    "addr:street":"Dexter Ave",
    "iso:country":"US",
    "sg:address":"213 Dexter Ave",
    "sg:city":"Watertown",
    "sg:classifiers":[
        {
            "category":"Banks & Credit Unions",
            "subcategory":"Bank",
            "type":"Services"
        }
    ],
    "sg:phone":"+1 617 926 9100",
    "sg:postcode":"02472",
    "sg:province":"MA",
    "sg:tags":[
        "loan",
        "real estate"
    ],
    "wof:name":"Bay State Mortgage Group",
    "wof:placetype":"venue"
},
  "geometry": {"coordinates":[-71.165459,42.364729],"type":"Point"}
}