{
  "type": "Feature",
  "properties": {
    "iso:country":"US",
    "sg:address":"350 Oak St",
    "sg:city":"Brockton",
    "sg:classifiers":[
        {
            "category":"Food & Beverages",
            "subcategory":"Groceries & Convenience Stores",
            "type":"Retail Goods"
        }
    ],
    "sg:phone":"+1 508 436 7459",
    "sg:postcode":"02301",
    "sg:province":"MA",
    "wof:name":"Oak Street Convenience Store",
    "wof:placetype":"venue"
},
  "geometry": {"coordinates":[-71.04095,42.101213],"type":"Point"}
}