{
  "type": "Feature",
  "properties": {
    "addr:full":"370 High Plain Rd Andover MA 01810",
    "addr:housenumber":"370",
    "addr:postcode":"01810",
    "addr:street":"High Plain Rd",
    "iso:country":"US",
    "sg:address":"370 High Plain Rd",
    "sg:city":"Andover",
    "sg:classifiers":[
        {
            "category":"Professional",
            "type":"Services"
        }
    ],
    "sg:phone":"+1 978 470 8856",
    "sg:postcode":"01810",
    "sg:province":"MA",
    "sg:tags":[
        "establishment"
    ],
    "wof:name":"Heavey Nicolette",
    "wof:placetype":"venue"
},
  "geometry": {"coordinates":[-71.218942,42.664609],"type":"Point"}
}