{
  "type": "Feature",
  "properties": {
    "addr:full": "101 Buckskin Dr Weston MA 02493",
    "addr:housenumber": "101",
    "addr:postcode": "02493",
    "addr:street": "Buckskin Dr",
    "iso:country": "US",
    "sg:address": "101 Buckskin Dr",
    "sg:city": "Weston",
    "sg:classifiers": [
      {
        "category": "Professional",
        "subcategory": "Management \u0026 Consulting",
        "type": "Services"
      }
    ],
    "sg:phone": "+1 781 647 5335",
    "sg:postcode": "02493",
    "sg:province": "MA",
    "sg:tags": [
      "party",
      "planning"
    ],
    "wof:name": "Settings",
    "wof:placetype": "venue"
  },
  "geometry": {"coordinates":[-71.329808,42.356036],"type":"Point"}
}
