{
  "type": "Feature",
  "properties": {
    "addr:full": "199 Sherbert Rd Ashburnham MA 01430",
    "addr:housenumber": "199",
    "addr:postcode": "01430",
    "addr:street": "Sherbert Rd",
    "iso:country": "US",
    "sg:address": "199 Sherbert Rd",
    "sg:city": "Ashburnham",
    "sg:classifiers": [
      {
        "category": "Building \u0026 Trades",
        "subcategory": "Landscaping Services",
        "type": "Services"
      }
    ],
    "sg:phone": "+1 978 827 4459",
    "sg:postcode": "01430",
    "sg:province": "MA",
    "sg:tags": [
      "landscape",
      "contractor"
    ],
    "wof:name": "Frank's The 1",
    "wof:placetype": "venue"
  },
  "geometry": {"coordinates":[-71.963777,42.662444],"type":"Point"}
}
