{
  "type": "Feature",
  "properties": {
    "addr:full": "150 Blacksmith Shop Rd East Falmouth MA 02536",
    "addr:housenumber": "150",
    "addr:postcode": "02536",
    "addr:street": "Blacksmith Shop Rd",
    "iso:country": "US",
    "sg:address": "150 Blacksmith Shop Rd",
    "sg:city": "East Falmouth",
    "sg:classifiers": [
      {
        "category": "Animal Shelter",
        "type": "Public Place"
      },
      {
        "category": "Shopping",
        "subcategory": "Pets \u0026 Pet Supplies",
        "type": "Retail Goods"
      }
    ],
    "sg:phone": "+1 508 548 7742",
    "sg:postcode": "02536",
    "sg:province": "MA",
    "sg:tags": [
      "store"
    ],
    "wof:name": "Friends of Falmouth Dogs",
    "wof:placetype": "venue"
  },
  "geometry": {"coordinates":[-70.610703,41.601002],"type":"Point"}
}
