{
  "type": "Feature",
  "properties": {
    "iso:country":"US",
    "sg:address":"330 E Main St",
    "sg:city":"Westfield",
    "sg:classifiers":[
        {
            "category":"Autos & Motor Vehicles",
            "subcategory":"Auto Supplies",
            "type":"Retail Goods"
        }
    ],
    "sg:phone":"+1 413 562 5500",
    "sg:postcode":"01085",
    "sg:province":"MA",
    "sg:tags":[
        "automobile",
        "parts"
    ],
    "wof:name":"Autozone",
    "wof:placetype":"venue"
},
  "geometry": {"coordinates":[-72.724295,42.113685],"type":"Point"}
}