{
  "type": "Feature",
  "properties": {
    "addr:full": "330 E Main St Westfield MA 01085",
    "addr:housenumber": "330",
    "addr:postcode": "01085",
    "addr:street": "E Main St",
    "iso:country": "US",
    "ovtr:label": "AutoZone, 200 E Main St Westfield MA US",
    "ovtr:similarity": 3.6610779762268066,
    "sg:address": "330 E Main St",
    "sg:city": "Westfield",
    "sg:classifiers": [
      {
        "category": "Autos \u0026 Motor Vehicles",
        "subcategory": "Auto Supplies",
        "type": "Retail Goods"
      }
    ],
    "sg:phone": "+1 413 562 5500",
    "sg:postcode": "01085",
    "sg:province": "MA",
    "sg:tags": [
      "automobile",
      "parts"
    ],
    "wof:name": "Autozone",
    "wof:placetype": "venue"
  },
  "geometry": {"coordinates":[-72.724295,42.113685],"type":"Point"}
}
