{
  "type": "Feature",
  "properties": {
    "iso:country":"US",
    "sg:address":"43 Bancroft Rd",
    "sg:city":"Stoughton",
    "sg:classifiers":[
        {
            "category":"Professional",
            "subcategory":"Computer Services",
            "type":"Services"
        }
    ],
    "sg:phone":"+1 617 610 1527",
    "sg:postcode":"02072",
    "sg:province":"MA",
    "sg:tags":[
        "information",
        "technology"
    ],
    "wof:name":"Systo Technology Consulting",
    "wof:placetype":"venue"
},
  "geometry": {"coordinates":[-71.090861,42.116988],"type":"Point"}
}