{
  "type": "Feature",
  "properties": {
    "addr:full": "86 Summer St Haverhill MA 01830",
    "addr:housenumber": "86",
    "addr:postcode": "01830",
    "addr:street": "Summer St",
    "iso:country": "US",
    "sg:address": "86 Summer St",
    "sg:city": "Haverhill",
    "sg:classifiers": [
      {
        "category": "Professional",
        "subcategory": "Lawyer \u0026 Legal Services",
        "type": "Services"
      }
    ],
    "sg:phone": "+1 978 374 1941",
    "sg:postcode": "01830",
    "sg:province": "MA",
    "sg:tags": [
      "attorney"
    ],
    "sg:website": "www.perronelaw.com",
    "wof:name": "John H Perrone \u0026 Assoc",
    "wof:placetype": "venue"
  },
  "geometry": {"coordinates":[-71.073974,42.777697],"type":"Point"}
}
