{
  "type": "Feature",
  "properties": {
    "iso:country":"US",
    "sg:address":"146 Montello St",
    "sg:city":"Brockton",
    "sg:classifiers":[
        {
            "category":"Restaurant",
            "type":"Food & Drink"
        }
    ],
    "sg:phone":"+1 508 586 3091",
    "sg:postcode":"02301",
    "sg:province":"MA",
    "wof:name":"Cardoso Cafe",
    "wof:placetype":"venue"
},
  "geometry": {"coordinates":[-71.017156,42.082404],"type":"Point"}
}