{
  "type": "Feature",
  "properties": {
    "addr:full": "146 Montello St Brockton MA 02301",
    "addr:housenumber": "146",
    "addr:postcode": "02301",
    "addr:street": "Montello St",
    "iso:country": "US",
    "ovtr:label": "Cardoso Cafe, 146 Montello St Brockton MA US",
    "ovtr:similarity": 2.2461791038513184,
    "sg:address": "146 Montello St",
    "sg:city": "Brockton",
    "sg:classifiers": [
      {
        "category": "Restaurant",
        "type": "Food \u0026 Drink"
      }
    ],
    "sg:phone": "+1 508 586 3091",
    "sg:postcode": "02301",
    "sg:province": "MA",
    "wof:name": "Cardoso Cafe",
    "wof:placetype": "venue"
  },
  "geometry": {"coordinates":[-71.017156,42.082404],"type":"Point"}
}
