{
  "type": "Feature",
  "properties": {
    "iso:country":"US",
    "sg:address":"137 Broadway",
    "sg:city":"Somerville",
    "sg:classifiers":[
        {
            "category":"Wholesale",
            "subcategory":"Books, Periodicals, & Newspapers",
            "type":"Manufacturing & Wholesale Goods"
        }
    ],
    "sg:phone":"+1 617 623 4460",
    "sg:postcode":"02145",
    "sg:province":"MA",
    "sg:tags":[
        "dealer"
    ],
    "wof:name":"Brazilian Book Store",
    "wof:placetype":"venue"
},
  "geometry": {"coordinates":[-71.08418399999999,42.3878],"type":"Point"}
}