{
  "type": "Feature",
  "properties": {
    "addr:full": "137 Broadway Somerville MA 02145",
    "addr:housenumber": "137",
    "addr:postcode": "02145",
    "addr:street": "Broadway",
    "iso:country": "US",
    "sg:address": "137 Broadway",
    "sg:city": "Somerville",
    "sg:classifiers": [
      {
        "category": "Wholesale",
        "subcategory": "Books, Periodicals, \u0026 Newspapers",
        "type": "Manufacturing \u0026 Wholesale Goods"
      }
    ],
    "sg:phone": "+1 617 623 4460",
    "sg:postcode": "02145",
    "sg:province": "MA",
    "sg:tags": [
      "dealer"
    ],
    "wof:name": "Brazilian Book Store",
    "wof:placetype": "venue"
  },
  "geometry": {"coordinates":[-71.084184,42.3878],"type":"Point"}
}
