{
  "type": "Feature",
  "properties": {
    "addr:full": "15 Wallis St Peabody MA 01960",
    "addr:housenumber": "15",
    "addr:postcode": "01960",
    "addr:street": "Wallis St",
    "iso:country": "US",
    "sg:address": "15 Wallis St",
    "sg:city": "Peabody",
    "sg:classifiers": [
      {
        "category": "Building \u0026 Trades",
        "subcategory": "Construction",
        "type": "Services"
      }
    ],
    "sg:phone": "+1 978 531 0580",
    "sg:postcode": "01960",
    "sg:province": "MA",
    "sg:tags": [
      "general",
      "contractor"
    ],
    "wof:name": "E H Porter Construction Co",
    "wof:placetype": "venue"
  },
  "geometry": {"coordinates":[-70.924303,42.526679],"type":"Point"}
}
