{
  "type": "Feature",
  "properties": {
    "addr:full": "27 Lanark Rd Brighton MA 02135",
    "addr:housenumber": "27",
    "addr:postcode": "02135",
    "addr:street": "Lanark Rd",
    "iso:country": "US",
    "sg:address": "27 Lanark Rd",
    "sg:city": "Brighton",
    "sg:classifiers": [
      {
        "category": "Professional",
        "subcategory": "Art Services",
        "type": "Services"
      }
    ],
    "sg:phone": "+1   ",
    "sg:postcode": "02135",
    "sg:province": "MA",
    "sg:tags": [
      "commercial",
      "design"
    ],
    "wof:name": "Keith Maclelland",
    "wof:placetype": "venue"
  },
  "geometry": {"coordinates":[-71.145941,42.339112],"type":"Point"}
}
