{
  "type": "Feature",
  "properties": {
    "iso:country":"US",
    "sg:address":"48 Riverhurst Rd",
    "sg:city":"Billerica",
    "sg:classifiers":[
        {
            "category":"Shopping",
            "type":"Retail Goods"
        }
    ],
    "sg:phone":"+1   ",
    "sg:postcode":"01821",
    "sg:province":"MA",
    "sg:tags":[
        "merchandise"
    ],
    "wof:name":"Wastenot Warehouse Inc",
    "wof:placetype":"venue"
},
  "geometry": {"coordinates":[-71.291149,42.54277],"type":"Point"}
}