{
  "type": "Feature",
  "properties": {
    "iso:country":"US",
    "sg:address":"31 State Hwy 145",
    "sg:city":"Boston",
    "sg:classifiers":[
        {
            "category":"Travel",
            "subcategory":"Travel Agent",
            "type":"Entertainment"
        }
    ],
    "sg:phone":"+1 617 292 7775",
    "sg:postcode":"02151",
    "sg:province":"MA",
    "sg:tags":[
        "agency",
        "bureau"
    ],
    "wof:name":"Dorado International Travel",
    "wof:placetype":"venue"
},
  "geometry": {"coordinates":[-70.98835800000001,42.401494],"type":"Point"}
}