{
  "type": "Feature",
  "properties": {
    "addr:full": "33 Park Plz Lee MA 01238",
    "addr:housenumber": "33",
    "addr:postcode": "01238",
    "addr:street": "Park Plz",
    "iso:country": "US",
    "sg:address": "33 Park Plz",
    "sg:city": "Lee",
    "sg:classifiers": [
      {
        "category": "Restaurant",
        "type": "Food \u0026 Drink"
      }
    ],
    "sg:phone": "+1 413 243 4041",
    "sg:postcode": "01238",
    "sg:province": "MA",
    "wof:name": "Bagel Smith",
    "wof:placetype": "venue"
  },
  "geometry": {"coordinates":[-73.24633,42.303877],"type":"Point"}
}
