{
  "type": "Feature",
  "properties": {
    "addr:full": "40 West St Beverly MA 01915",
    "addr:housenumber": "40",
    "addr:postcode": "01915",
    "addr:street": "West St",
    "iso:country": "US",
    "ovtr:label": "Book Shop of Beverly Farms, 40 West St Beverly MA US",
    "ovtr:similarity": 2.9989049434661865,
    "sg:address": "40 West St",
    "sg:city": "Beverly",
    "sg:classifiers": [
      {
        "category": "Shopping",
        "subcategory": "Books",
        "type": "Retail Goods"
      }
    ],
    "sg:phone": "+1 978 927 2122",
    "sg:postcode": "01915",
    "sg:province": "MA",
    "sg:tags": [
      "dealer"
    ],
    "sg:website": "www.realbookshop.com",
    "wof:name": "Book Shop Of Beverly Farms",
    "wof:placetype": "venue"
  },
  "geometry": {"coordinates":[-70.814472,42.562526],"type":"Point"}
}
