{
  "type": "Feature",
  "properties": {
    "iso:country":"US",
    "sg:address":"423 Old Connecticut Path",
    "sg:city":"Framingham",
    "sg:classifiers":[
        {
            "category":"Professional",
            "subcategory":"Accounting & Tax Preparation",
            "type":"Services"
        }
    ],
    "sg:phone":"+1   ",
    "sg:postcode":"01701",
    "sg:province":"MA",
    "wof:name":"Harvey Resnick Ea",
    "wof:placetype":"venue"
},
  "geometry": {"coordinates":[-71.394603,42.310928],"type":"Point"}
}