{
  "type": "Feature",
  "properties": {
    "addr:full": "423 Old Connecticut Path Framingham MA 01701",
    "addr:housenumber": "423",
    "addr:postcode": "01701",
    "addr:street": "Old Connecticut Path",
    "iso:country": "US",
    "sg:address": "423 Old Connecticut Path",
    "sg:city": "Framingham",
    "sg:classifiers": [
      {
        "category": "Professional",
        "subcategory": "Accounting \u0026 Tax Preparation",
        "type": "Services"
      }
    ],
    "sg:phone": "+1   ",
    "sg:postcode": "01701",
    "sg:province": "MA",
    "wof:name": "Harvey Resnick Ea",
    "wof:placetype": "venue"
  },
  "geometry": {"coordinates":[-71.394603,42.310928],"type":"Point"}
}
