{
  "type": "Feature",
  "properties": {
    "addr:full": "404 Main St Hyannis MA 02601",
    "addr:housenumber": "404",
    "addr:postcode": "02601",
    "addr:street": "Main St",
    "iso:country": "US",
    "sg:address": "404 Main St",
    "sg:city": "Hyannis",
    "sg:classifiers": [
      {
        "category": "Professional",
        "subcategory": "Lawyer \u0026 Legal Services",
        "type": "Services"
      }
    ],
    "sg:phone": "+1 508 775 4560",
    "sg:postcode": "02601",
    "sg:province": "MA",
    "sg:tags": [
      "attorney"
    ],
    "wof:name": "Caggiano Joakim \u0026 Kennan",
    "wof:placetype": "venue"
  },
  "geometry": {"coordinates":[-70.284687,41.652492],"type":"Point"}
}
