{
  "type": "Feature",
  "properties": {
    "addr:full": "16 Highland Ridge Rd Assonet MA 02702",
    "addr:housenumber": "16",
    "addr:postcode": "02702",
    "addr:street": "Highland Ridge Rd",
    "iso:country": "US",
    "sg:address": "16 Highland Ridge Rd",
    "sg:city": "Assonet",
    "sg:classifiers": [
      {
        "category": "Building \u0026 Trades",
        "subcategory": "Construction",
        "type": "Services"
      }
    ],
    "sg:phone": "+1 508 644 9909",
    "sg:postcode": "02702",
    "sg:province": "MA",
    "sg:tags": [
      "contractor"
    ],
    "wof:name": "Main Frame Builders",
    "wof:placetype": "venue"
  },
  "geometry": {"coordinates":[-71.095579,41.786875],"type":"Point"}
}
