{
  "type": "Feature",
  "properties": {
    "iso:country":"US",
    "sg:address":"16 Highland Ridge Rd",
    "sg:city":"Assonet",
    "sg:classifiers":[
        {
            "category":"Building & Trades",
            "subcategory":"Construction",
            "type":"Services"
        }
    ],
    "sg:phone":"+1 508 644 9909",
    "sg:postcode":"02702",
    "sg:province":"MA",
    "sg:tags":[
        "contractor"
    ],
    "wof:name":"Main Frame Builders",
    "wof:placetype":"venue"
},
  "geometry": {"coordinates":[-71.095579,41.786875],"type":"Point"}
}