{
  "type": "Feature",
  "properties": {
    "iso:country":"US",
    "sg:address":"2259 Northampton St",
    "sg:city":"Holyoke",
    "sg:classifiers":[
        {
            "category":"Shopping",
            "subcategory":"Clothing, Apparel, & Fashions",
            "type":"Retail Goods"
        }
    ],
    "sg:phone":"+1 413 532 9130",
    "sg:postcode":"01040",
    "sg:province":"MA",
    "wof:name":"Dots Inc",
    "wof:placetype":"venue"
},
  "geometry": {"coordinates":[-72.63045200000001,42.186436],"type":"Point"}
}