{
  "type": "Feature",
  "properties": {
    "addr:full": "2259 Northampton St Holyoke MA 01040",
    "addr:housenumber": "2259",
    "addr:postcode": "01040",
    "addr:street": "Northampton St",
    "iso:country": "US",
    "sg:address": "2259 Northampton St",
    "sg:city": "Holyoke",
    "sg:classifiers": [
      {
        "category": "Shopping",
        "subcategory": "Clothing, Apparel, \u0026 Fashions",
        "type": "Retail Goods"
      }
    ],
    "sg:phone": "+1 413 532 9130",
    "sg:postcode": "01040",
    "sg:province": "MA",
    "wof:name": "Dots Inc",
    "wof:placetype": "venue"
  },
  "geometry": {"coordinates":[-72.630452,42.186436],"type":"Point"}
}
