{
  "type": "Feature",
  "properties": {
    "addr:full":"540 Main St West Springfield MA 01089",
    "addr:housenumber":"540",
    "addr:postcode":"01089",
    "addr:street":"Main St",
    "iso:country":"US",
    "sg:address":"540 Main St",
    "sg:city":"West Springfield",
    "sg:classifiers":[
        {
            "category":"Wholesale",
            "subcategory":"Electrical",
            "type":"Manufacturing & Wholesale Goods"
        }
    ],
    "sg:phone":"+1 413 736 5181",
    "sg:postcode":"01089",
    "sg:province":"MA",
    "sg:tags":[
        "alarm",
        "burglar",
        "system"
    ],
    "wof:name":"Eastern Electronic & Security",
    "wof:placetype":"venue"
},
  "geometry": {"coordinates":[-72.608845,42.101803],"type":"Point"}
}