{
  "type": "Feature",
  "properties": {
    "addr:full":"202 Arsenal St Watertown MA 02472",
    "addr:housenumber":"202",
    "addr:postcode":"02472",
    "addr:street":"Arsenal St",
    "iso:country":"US",
    "sg:address":"202 Arsenal St",
    "sg:city":"Watertown",
    "sg:classifiers":[
        {
            "category":"Retail",
            "subcategory":"Repair Shop",
            "type":"Services"
        }
    ],
    "sg:phone":"+1 617 923 4390",
    "sg:postcode":"02472",
    "sg:province":"MA",
    "sg:tags":[
        "upholsterer"
    ],
    "sg:website":"www.fabricshowroom.com",
    "wof:name":"Crimson Upholstering Co",
    "wof:placetype":"venue"
},
  "geometry": {"coordinates":[-71.178045,42.364872],"type":"Point"}
}