{
  "type": "Feature",
  "properties": {
    "iso:country":"US",
    "sg:address":"38 Austin St",
    "sg:city":"Charlestown",
    "sg:classifiers":[
        {
            "category":"Real Estate",
            "subcategory":"Developer",
            "type":"Services"
        },
        {
            "category":"Real Estate",
            "subcategory":"Real Estate Agent",
            "type":"Services"
        }
    ],
    "sg:phone":"+1 617 241 0360",
    "sg:postcode":"02129",
    "sg:province":"MA",
    "wof:name":"P & A Realty Development Trust",
    "wof:placetype":"venue"
},
  "geometry": {"coordinates":[-71.065977,42.374787],"type":"Point"}
}