{
  "type": "Feature",
  "properties": {
    "iso:country":"US",
    "sg:address":"205 Arlington St",
    "sg:city":"Watertown",
    "sg:classifiers":[
        {
            "category":"Communications",
            "subcategory":"Film & Video Production",
            "type":"Services"
        }
    ],
    "sg:phone":"+1 617 923 4646",
    "sg:postcode":"02472",
    "sg:province":"MA",
    "sg:tags":[
        "taping"
    ],
    "wof:name":"Pulse Productions",
    "wof:placetype":"venue"
},
  "geometry": {"coordinates":[-71.155753,42.370176],"type":"Point"}
}