{
  "type": "Feature",
  "properties": {
    "addr:full": "3166 Main St Barnstable MA 02630",
    "addr:housenumber": "3166",
    "addr:postcode": "02630",
    "addr:street": "Main St",
    "iso:country": "US",
    "sg:address": "3166 Main St",
    "sg:city": "Barnstable",
    "sg:classifiers": [
      {
        "category": "Professional",
        "subcategory": "Lawyer \u0026 Legal Services",
        "type": "Services"
      }
    ],
    "sg:phone": "+1 508 362 9666",
    "sg:postcode": "02630",
    "sg:province": "MA",
    "sg:tags": [
      "attorney"
    ],
    "wof:name": "Lawless \u0026 Lawless",
    "wof:placetype": "venue"
  },
  "geometry": {"coordinates":[-70.304869,41.702063],"type":"Point"}
}
