{
  "type": "Feature",
  "properties": {
    "addr:full": "95 Boston Rd North Billerica MA 01862",
    "addr:housenumber": "95",
    "addr:postcode": "01862",
    "addr:street": "Boston Rd",
    "iso:country": "US",
    "sg:address": "95 Boston Rd",
    "sg:city": "North Billerica",
    "sg:classifiers": [
      {
        "category": "Retail",
        "subcategory": "Repair Shop",
        "type": "Services"
      }
    ],
    "sg:phone": "+1 978 826 2770",
    "sg:postcode": "01862",
    "sg:province": "MA",
    "sg:tags": [
      "lock",
      "locksmith"
    ],
    "wof:name": "All Day Emergency Locksmith",
    "wof:placetype": "venue"
  },
  "geometry": {"coordinates":[-71.296863,42.591867],"type":"Point"}
}
