{
  "type": "Feature",
  "properties": {
    "addr:full":"29 Main St Leominster MA 01453",
    "addr:housenumber":"29",
    "addr:postcode":"01453",
    "addr:street":"Main St",
    "iso:country":"US",
    "sg:address":"29 Main St",
    "sg:city":"Leominster",
    "sg:classifiers":[
        {
            "category":"Banks & Credit Unions",
            "subcategory":"Investment Brokerage",
            "type":"Services"
        }
    ],
    "sg:phone":"+1   ",
    "sg:postcode":"01453",
    "sg:province":"MA",
    "sg:tags":[
        "planning",
        "financial"
    ],
    "wof:name":"Fitzgerald Associates",
    "wof:placetype":"venue"
},
  "geometry": {"coordinates":[-71.758752,42.527635],"type":"Point"}
}