{
  "type": "Feature",
  "properties": {
    "iso:country":"US",
    "sg:address":"388 Broadway",
    "sg:city":"Revere",
    "sg:classifiers":[
        {
            "category":"Building & Trades",
            "subcategory":"Locksmith",
            "type":"Services"
        }
    ],
    "sg:phone":"+1 781 922 9060",
    "sg:postcode":"02151",
    "sg:province":"MA",
    "sg:tags":[
        "key"
    ],
    "wof:name":"Available Locksmith 24 7",
    "wof:placetype":"venue"
},
  "geometry": {"coordinates":[-71.012421,42.410236],"type":"Point"}
}