{
  "type": "Feature",
  "properties": {
    "addr:full": "388 Broadway Revere MA 02151",
    "addr:housenumber": "388",
    "addr:postcode": "02151",
    "addr:street": "Broadway",
    "iso:country": "US",
    "sg:address": "388 Broadway",
    "sg:city": "Revere",
    "sg:classifiers": [
      {
        "category": "Building \u0026 Trades",
        "subcategory": "Locksmith",
        "type": "Services"
      }
    ],
    "sg:phone": "+1 781 922 9060",
    "sg:postcode": "02151",
    "sg:province": "MA",
    "sg:tags": [
      "key"
    ],
    "wof:name": "Available Locksmith 24 7",
    "wof:placetype": "venue"
  },
  "geometry": {"coordinates":[-71.012421,42.410236],"type":"Point"}
}
