{
  "type": "Feature",
  "properties": {
    "iso:country":"US",
    "sg:address":"3892 Washington St",
    "sg:city":"Roslindale",
    "sg:classifiers":[
        {
            "category":"Manufacturing",
            "subcategory":"Food",
            "type":"Manufacturing & Wholesale Goods"
        }
    ],
    "sg:phone":"+1 617 524 6852",
    "sg:postcode":"02131",
    "sg:province":"MA",
    "sg:tags":[
        "ice"
    ],
    "wof:name":"Bostonice Co",
    "wof:placetype":"venue"
},
  "geometry": {"coordinates":[-71.118583,42.295359],"type":"Point"}
}