{
  "type": "Feature",
  "properties": {
    "addr:full":"500 Victory Rd Ste 13 Quincy MA 02171",
    "addr:housenumber":"500;13",
    "addr:postcode":"02171",
    "addr:street":"Victory Rd Ste",
    "iso:country":"US",
    "sg:address":"500 Victory Rd Ste 13",
    "sg:city":"Quincy",
    "sg:classifiers":[
        {
            "category":"Professional",
            "subcategory":"Computer Services",
            "type":"Services"
        }
    ],
    "sg:phone":"+1 617 479 1600",
    "sg:postcode":"02171",
    "sg:province":"MA",
    "sg:tags":[
        "information",
        "recovery",
        "processing",
        "system",
        "equipment",
        "data",
        "retrieval"
    ],
    "wof:name":"Copyright Research Group Div",
    "wof:placetype":"venue"
},
  "geometry": {"coordinates":[-71.030828,42.29916],"type":"Point"}
}