{
  "type": "Feature",
  "properties": {
    "addr:full":"273 S Union St Lawrence MA 01843",
    "addr:housenumber":"273",
    "addr:postcode":"01843",
    "addr:street":"S Union St",
    "iso:country":"US",
    "sg:address":"273 S Union St",
    "sg:city":"Lawrence",
    "sg:classifiers":[
        {
            "category":"Real Estate",
            "subcategory":"Real Estate Agent",
            "type":"Services"
        }
    ],
    "sg:phone":"+1 978 975 5239",
    "sg:postcode":"01843",
    "sg:province":"MA",
    "sg:tags":[
        "agency",
        "rental"
    ],
    "wof:name":"Rent Way",
    "wof:placetype":"venue"
},
  "geometry": {"coordinates":[-71.153476,42.695199],"type":"Point"}
}