{
  "type": "Feature",
  "properties": {
    "addr:full": "40 Moreland St Somerville MA 02145",
    "addr:housenumber": "40",
    "addr:postcode": "02145",
    "addr:street": "Moreland St",
    "iso:country": "US",
    "sg:address": "40 Moreland St",
    "sg:city": "Somerville",
    "sg:classifiers": [
      {
        "category": "Building \u0026 Trades",
        "subcategory": "Construction",
        "type": "Services"
      }
    ],
    "sg:phone": "+1 617 625 0737",
    "sg:postcode": "02145",
    "sg:province": "MA",
    "sg:tags": [
      "contractor"
    ],
    "wof:name": "Scd Renovations",
    "wof:placetype": "venue"
  },
  "geometry": {"coordinates":[-71.097528,42.397361],"type":"Point"}
}
