{
  "type": "Feature",
  "properties": {
    "iso:country":"US",
    "sg:address":"40 Moreland St",
    "sg:city":"Somerville",
    "sg:classifiers":[
        {
            "category":"Building & Trades",
            "subcategory":"Construction",
            "type":"Services"
        }
    ],
    "sg:phone":"+1 617 625 0737",
    "sg:postcode":"02145",
    "sg:province":"MA",
    "sg:tags":[
        "contractor"
    ],
    "wof:name":"Scd Renovations",
    "wof:placetype":"venue"
},
  "geometry": {"coordinates":[-71.097528,42.397361],"type":"Point"}
}