{
  "type": "Feature",
  "properties": {
    "addr:full":"6 Church St Merrimac MA 01860",
    "addr:housenumber":"6",
    "addr:postcode":"01860",
    "addr:street":"Church St",
    "iso:country":"US",
    "sg:address":"6 Church St",
    "sg:city":"Merrimac",
    "sg:classifiers":[
        {
            "category":"Personal",
            "subcategory":"Beauty Salon",
            "type":"Services"
        },
        {
            "category":"Personal",
            "subcategory":"Skin Care",
            "type":"Services"
        }
    ],
    "sg:phone":"+1 978 346 9359",
    "sg:postcode":"01860",
    "sg:province":"MA",
    "wof:name":"Skin Essentials",
    "wof:placetype":"venue"
},
  "geometry": {"coordinates":[-71.002602,42.833801],"type":"Point"}
}