{
  "type": "Feature",
  "properties": {
    "iso:country":"US",
    "sg:address":"179 Main St",
    "sg:city":"Fitchburg",
    "sg:classifiers":[
        {
            "category":"Cinema",
            "subcategory":"Movie Rental",
            "type":"Entertainment"
        }
    ],
    "sg:phone":"+1 978 345 1328",
    "sg:postcode":"01420",
    "sg:province":"MA",
    "sg:tags":[
        "leasing",
        "video",
        "disc",
        "tape"
    ],
    "wof:name":"Video Paradise",
    "wof:placetype":"venue"
},
  "geometry": {"coordinates":[-71.793975,42.581866],"type":"Point"}
}