{
  "type": "Feature",
  "properties": {
    "addr:full": "179 Main St Fitchburg MA 01420",
    "addr:housenumber": "179",
    "addr:postcode": "01420",
    "addr:street": "Main St",
    "iso:country": "US",
    "sg:address": "179 Main St",
    "sg:city": "Fitchburg",
    "sg:classifiers": [
      {
        "category": "Cinema",
        "subcategory": "Movie Rental",
        "type": "Entertainment"
      }
    ],
    "sg:phone": "+1 978 345 1328",
    "sg:postcode": "01420",
    "sg:province": "MA",
    "sg:tags": [
      "leasing",
      "video",
      "disc",
      "tape"
    ],
    "wof:name": "Video Paradise",
    "wof:placetype": "venue"
  },
  "geometry": {"coordinates":[-71.793975,42.581866],"type":"Point"}
}
