{
  "type": "Feature",
  "properties": {
    "iso:country":"US",
    "sg:address":"637 Washington Street Suite 210",
    "sg:city":"Brookline",
    "sg:classifiers":[
        {
            "category":"Health Services",
            "subcategory":"Dentist",
            "type":"Services"
        }
    ],
    "sg:phone":"+1 617 566 4420",
    "sg:postcode":"02446",
    "sg:province":"MA",
    "wof:name":"Rofe Dental Assoc",
    "wof:placetype":"venue"
},
  "geometry": {"coordinates":[-71.131587,42.338388],"type":"Point"}
}