{
  "type": "Feature",
  "properties": {
    "addr:full": "695 Eastern Avenue Malden MA 02148",
    "addr:housenumber": "695",
    "addr:postcode": "02148",
    "addr:street": "Eastern Avenue",
    "atp:label": "Subway, 695 Eastern Ave Malden Middlesex MA US",
    "atp:similarity": 3.342395067214966,
    "iso:country": "US",
    "ovtr:label": "Subway, 695 Eastern Ave Malden MA US",
    "ovtr:similarity": 3.3107941150665283,
    "sg:address": "695 Eastern Avenue",
    "sg:city": "Malden",
    "sg:classifiers": [
      {
        "category": "Restaurant",
        "type": "Food \u0026 Drink"
      }
    ],
    "sg:phone": "+1 781 333 3058",
    "sg:postcode": "02148",
    "sg:province": "MA",
    "wof:name": "Subway",
    "wof:placetype": "venue"
  },
  "geometry": {"coordinates":[-71.049863,42.429708],"type":"Point"}
}
