{
  "type": "Feature",
  "properties": {
    "iso:country":"US",
    "sg:address":"695 Eastern Avenue",
    "sg:city":"Malden",
    "sg:classifiers":[
        {
            "category":"Restaurant",
            "type":"Food & Drink"
        }
    ],
    "sg:phone":"+1 781 333 3058",
    "sg:postcode":"02148",
    "sg:province":"MA",
    "wof:name":"Subway",
    "wof:placetype":"venue"
},
  "geometry": {"coordinates":[-71.049863,42.429708],"type":"Point"}
}