{
  "type": "Feature",
  "properties": {
    "iso:country":"US",
    "sg:address":"484 Western Avenue",
    "sg:city":"Brighton",
    "sg:classifiers":[
        {
            "category":"Building & Trades",
            "subcategory":"Locksmith",
            "type":"Services"
        }
    ],
    "sg:phone":"+1 617 370 0352",
    "sg:postcode":"02135",
    "sg:province":"MA",
    "sg:tags":[
        "key"
    ],
    "wof:name":"1 Hour 7 Day Emerge Locksmith",
    "wof:placetype":"venue"
},
  "geometry": {"coordinates":[-71.14303700000001,42.362115],"type":"Point"}
}