{
  "type": "Feature",
  "properties": {
    "addr:full": "6 Montvale Ave Stoneham MA 02180",
    "addr:housenumber": "6",
    "addr:postcode": "02180",
    "addr:street": "Montvale Ave",
    "iso:country": "US",
    "sg:address": "6 Montvale Ave",
    "sg:city": "Stoneham",
    "sg:classifiers": [
      {
        "category": "Bakery",
        "type": "Food \u0026 Drink"
      }
    ],
    "sg:phone": "+1 781 420 9361",
    "sg:postcode": "02180",
    "sg:province": "MA",
    "wof:name": "Pao Paulo Bakery",
    "wof:placetype": "venue"
  },
  "geometry": {"coordinates":[-71.100604,42.482103],"type":"Point"}
}
