{
  "type": "Feature",
  "properties": {
    "addr:full":"338 Lowell St Wakefield MA 01880",
    "addr:housenumber":"338",
    "addr:postcode":"01880",
    "addr:street":"Lowell St",
    "iso:country":"US",
    "sg:address":"338 Lowell St",
    "sg:city":"Wakefield",
    "sg:classifiers":[
        {
            "category":"Building & Trades",
            "subcategory":"Electrical",
            "type":"Services"
        }
    ],
    "sg:phone":"+1 781 245 3040",
    "sg:postcode":"01880",
    "sg:province":"MA",
    "sg:tags":[
        "electric",
        "contractor"
    ],
    "wof:name":"ETC Svc Solutions Inc",
    "wof:placetype":"venue"
},
  "geometry": {"coordinates":[-71.065236,42.518052],"type":"Point"}
}