{
  "type": "Feature",
  "properties": {
    "iso:country":"US",
    "sg:address":"1350 Belmont St",
    "sg:city":"Brockton",
    "sg:classifiers":[
        {
            "category":"Professional",
            "subcategory":"Business Services",
            "type":"Services"
        }
    ],
    "sg:phone":"+1 508 584 1587",
    "sg:postcode":"02301",
    "sg:province":"MA",
    "wof:name":"Horizon Business Valuations",
    "wof:placetype":"venue"
},
  "geometry": {"coordinates":[-71.070125,42.057089],"type":"Point"}
}