{
  "type": "Feature",
  "properties": {
    "iso:country":"US",
    "sg:address":"1690 Hyde Park Ave",
    "sg:city":"Hyde Park",
    "sg:classifiers":[
        {
            "category":"Autos & Motor Vehicles",
            "subcategory":"Auto Supplies",
            "type":"Retail Goods"
        }
    ],
    "sg:phone":"+1 617 364 3660",
    "sg:postcode":"02136",
    "sg:province":"MA",
    "sg:tags":[
        "tire"
    ],
    "wof:name":"Readville Tire",
    "wof:placetype":"venue"
},
  "geometry": {"coordinates":[-71.12989399999999,42.243647],"type":"Point"}
}