{
  "type": "Feature",
  "properties": {
    "addr:full": "224 Beal St Hingham MA 02043",
    "addr:housenumber": "224",
    "addr:postcode": "02043",
    "addr:street": "Beal St",
    "iso:country": "US",
    "sg:address": "224 Beal St",
    "sg:city": "Hingham",
    "sg:classifiers": [
      {
        "category": "Social Services",
        "type": "Services"
      }
    ],
    "sg:phone": "+1 781 749 6320",
    "sg:postcode": "02043",
    "sg:province": "MA",
    "sg:tags": [
      "organization",
      "welfare"
    ],
    "wof:name": "Project Turnabout Inc",
    "wof:placetype": "venue"
  },
  "geometry": {"coordinates":[-70.921433,42.245459],"type":"Point"}
}
