{
  "type": "Feature",
  "properties": {
    "addr:full":"24 Green St Fall River MA 02720",
    "addr:housenumber":"24",
    "addr:postcode":"02720",
    "addr:street":"Green St",
    "iso:country":"US",
    "sg:address":"24 Green St",
    "sg:city":"Fall River",
    "sg:classifiers":[
        {
            "category":"Real Estate",
            "subcategory":"Real Estate Operator",
            "type":"Services"
        }
    ],
    "sg:phone":"+1 508 678 9500",
    "sg:postcode":"02720",
    "sg:province":"MA",
    "sg:tags":[
        "apartment"
    ],
    "wof:name":"South Winds",
    "wof:placetype":"venue"
},
  "geometry": {"coordinates":[-71.15768199999999,41.703236],"type":"Point"}
}