{
  "type": "Feature",
  "properties": {
    "addr:full": "396 Adams St Dorchester MA 02122",
    "addr:housenumber": "396",
    "addr:postcode": "02122",
    "addr:street": "Adams St",
    "iso:country": "US",
    "sg:address": "396 Adams St",
    "sg:city": "Dorchester",
    "sg:classifiers": [
      {
        "category": "Shopping",
        "subcategory": "Used Merchandise",
        "type": "Retail Goods"
      }
    ],
    "sg:phone": "+1 617 288 7893",
    "sg:postcode": "02122",
    "sg:province": "MA",
    "sg:tags": [
      "antique"
    ],
    "wof:name": "Erik Diedrichsen Antiques",
    "wof:placetype": "venue"
  },
  "geometry": {"coordinates":[-71.056457,42.296369],"type":"Point"}
}
