{
  "type": "Feature",
  "properties": {
    "iso:country":"US",
    "sg:address":"10 Airport Rd",
    "sg:city":"Hopedale",
    "sg:classifiers":[
        {
            "category":"Wholesale",
            "subcategory":"Machinery & Supplies",
            "type":"Manufacturing & Wholesale Goods"
        }
    ],
    "sg:phone":"+1 508 473 0041",
    "sg:postcode":"01747",
    "sg:province":"MA",
    "sg:tags":[
        "crane",
        "derrick"
    ],
    "sg:website":"www.dcbates.com",
    "wof:name":"D C Bates Equipment Co Inc",
    "wof:placetype":"venue"
},
  "geometry": {"coordinates":[-71.51196899999999,42.106359],"type":"Point"}
}