{
  "type": "Feature",
  "properties": {
    "addr:full": "10 Airport Rd Hopedale MA 01747",
    "addr:housenumber": "10",
    "addr:postcode": "01747",
    "addr:street": "Airport Rd",
    "iso:country": "US",
    "sg:address": "10 Airport Rd",
    "sg:city": "Hopedale",
    "sg:classifiers": [
      {
        "category": "Wholesale",
        "subcategory": "Machinery \u0026 Supplies",
        "type": "Manufacturing \u0026 Wholesale Goods"
      }
    ],
    "sg:phone": "+1 508 473 0041",
    "sg:postcode": "01747",
    "sg:province": "MA",
    "sg:tags": [
      "crane",
      "derrick"
    ],
    "sg:website": "www.dcbates.com",
    "wof:name": "D C Bates Equipment Co Inc",
    "wof:placetype": "venue"
  },
  "geometry": {"coordinates":[-71.511969,42.106359],"type":"Point"}
}
