{
  "type": "Feature",
  "properties": {
    "iso:country":"US",
    "sg:address":"13 Beeching Ave",
    "sg:city":"Wilmington",
    "sg:classifiers":[
        {
            "category":"Professional",
            "subcategory":"Accounting & Tax Preparation",
            "type":"Services"
        }
    ],
    "sg:phone":"+1 978 658 1540",
    "sg:postcode":"01887",
    "sg:province":"MA",
    "sg:tags":[
        "accountant"
    ],
    "wof:name":"Paolini Stephen PC",
    "wof:placetype":"venue"
},
  "geometry": {"coordinates":[-71.180199,42.570099],"type":"Point"}
}