{
  "type": "Feature",
  "properties": {
    "addr:full": "895 Parker St Springfield MA 01129",
    "addr:housenumber": "895",
    "addr:postcode": "01129",
    "addr:street": "Parker St",
    "iso:country": "US",
    "sg:address": "895 Parker St",
    "sg:city": "Springfield",
    "sg:classifiers": [
      {
        "category": "Real Estate",
        "subcategory": "Developer",
        "type": "Services"
      }
    ],
    "sg:phone": "+1 413 782 2311",
    "sg:postcode": "01129",
    "sg:province": "MA",
    "sg:tags": [
      "cemetery"
    ],
    "wof:name": "Hillcrest Park Cemetery",
    "wof:placetype": "venue"
  },
  "geometry": {"coordinates":[-72.4965,42.126208],"type":"Point"}
}
