{
  "type": "Feature",
  "properties": {
    "addr:full": "42 Evergreen St Saugus MA 01906",
    "addr:housenumber": "42",
    "addr:postcode": "01906",
    "addr:street": "Evergreen St",
    "iso:country": "US",
    "sg:address": "42 Evergreen St",
    "sg:city": "Saugus",
    "sg:classifiers": [
      {
        "category": "Home \u0026 Garden",
        "subcategory": "Carpets \u0026 Floor Coverings",
        "type": "Retail Goods"
      }
    ],
    "sg:phone": "+1 781 231 5137",
    "sg:postcode": "01906",
    "sg:province": "MA",
    "sg:tags": [
      "linoleum"
    ],
    "wof:name": "M A Carpet",
    "wof:placetype": "venue"
  },
  "geometry": {"coordinates":[-71.005952,42.475624],"type":"Point"}
}
