{
  "type": "Feature",
  "properties": {
    "iso:country":"US",
    "sg:address":"42 Evergreen St",
    "sg:city":"Saugus",
    "sg:classifiers":[
        {
            "category":"Home & Garden",
            "subcategory":"Carpets & Floor Coverings",
            "type":"Retail Goods"
        }
    ],
    "sg:phone":"+1 781 231 5137",
    "sg:postcode":"01906",
    "sg:province":"MA",
    "sg:tags":[
        "linoleum"
    ],
    "wof:name":"M A Carpet",
    "wof:placetype":"venue"
},
  "geometry": {"coordinates":[-71.00595199999999,42.475624],"type":"Point"}
}