{
  "type": "Feature",
  "properties": {
    "iso:country":"US",
    "sg:address":"138 Wellesley St",
    "sg:city":"Weston",
    "sg:classifiers":[
        {
            "category":"Professional",
            "subcategory":"Business Services",
            "type":"Services"
        }
    ],
    "sg:phone":"+1   ",
    "sg:postcode":"02493",
    "sg:province":"MA",
    "wof:name":"Emanem Partners Inc",
    "wof:placetype":"venue"
},
  "geometry": {"coordinates":[-71.295292,42.35919],"type":"Point"}
}