{
  "type": "Feature",
  "properties": {
    "addr:full":"840 Oak Hill Rd Fitchburg MA 01420",
    "addr:housenumber":"840",
    "addr:postcode":"01420",
    "addr:street":"Oak Hill Rd",
    "iso:country":"US",
    "sg:address":"840 Oak Hill Rd",
    "sg:city":"Fitchburg",
    "sg:classifiers":[
        {
            "category":"Shopping",
            "subcategory":"Bicycles & Sporting Goods",
            "type":"Retail Goods"
        },
        {
            "category":"Sports & Exercise",
            "subcategory":"Golf",
            "type":"Entertainment"
        }
    ],
    "sg:phone":"+1 978 342 0237",
    "sg:postcode":"01420",
    "sg:province":"MA",
    "sg:tags":[
        "equipment",
        "course",
        "supply"
    ],
    "wof:name":"O'leary's, Jim Golf Shop",
    "wof:placetype":"venue"
},
  "geometry": {"coordinates":[-71.830473,42.559958],"type":"Point"}
}