{
  "type": "Feature",
  "properties": {
    "addr:full":"335 Boylston St Newton Center MA 02459",
    "addr:housenumber":"335",
    "addr:postcode":"02459",
    "addr:street":"Boylston St",
    "iso:country":"US",
    "sg:address":"335 Boylston St",
    "sg:city":"Newton Center",
    "sg:classifiers":[
        {
            "category":"Education",
            "subcategory":"Special Training",
            "type":"Public Place"
        }
    ],
    "sg:phone":"+1 617 559 9944",
    "sg:postcode":"02459",
    "sg:province":"MA",
    "sg:tags":[
        "tutoring"
    ],
    "wof:name":"Learningworks",
    "wof:placetype":"venue"
},
  "geometry": {"coordinates":[-71.183161,42.319095],"type":"Point"}
}