{
  "type": "Feature",
  "properties": {
    "addr:full":"1003 Broadway Haverhill MA 01832",
    "addr:housenumber":"1003",
    "addr:postcode":"01832",
    "addr:street":"Broadway",
    "iso:country":"US",
    "sg:address":"1003 Broadway",
    "sg:city":"Haverhill",
    "sg:classifiers":[
        {
            "category":"Home & Garden",
            "subcategory":"Building Materials",
            "type":"Retail Goods"
        }
    ],
    "sg:phone":"+1 978 374 7005",
    "sg:postcode":"01832",
    "sg:province":"MA",
    "sg:tags":[
        "windows"
    ],
    "wof:name":"Cash Windows",
    "wof:placetype":"venue"
},
  "geometry": {"coordinates":[-71.146629,42.789879],"type":"Point"}
}