{
  "type": "Feature",
  "properties": {
    "iso:country":"US",
    "sg:address":"880 Boston Rd",
    "sg:city":"Billerica",
    "sg:classifiers":[
        {
            "category":"Personal",
            "subcategory":"Beauty Salon",
            "type":"Services"
        }
    ],
    "sg:phone":"+1 978 663 9200",
    "sg:postcode":"01821",
    "sg:province":"MA",
    "wof:name":"Salon De'Von",
    "wof:placetype":"venue"
},
  "geometry": {"coordinates":[-71.22611000000001,42.527567],"type":"Point"}
}