{
  "type": "Feature",
  "properties": {
    "iso:country":"US",
    "sg:address":"136 Main St",
    "sg:city":"Acton",
    "sg:classifiers":[
        {
            "category":"Personal",
            "subcategory":"Beauty Salon",
            "type":"Services"
        }
    ],
    "sg:phone":"+1 978 263 2759",
    "sg:postcode":"01720",
    "sg:province":"MA",
    "wof:name":"Feathers Hair Salon",
    "wof:placetype":"venue"
},
  "geometry": {"coordinates":[-71.455085,42.461245],"type":"Point"}
}