{
  "type": "Feature",
  "properties": {
    "addr:full":"22 High St Greenfield MA 01301",
    "addr:housenumber":"22",
    "addr:postcode":"01301",
    "addr:street":"High St",
    "iso:country":"US",
    "sg:address":"22 High St",
    "sg:city":"Greenfield",
    "sg:classifiers":[
        {
            "category":"Education",
            "subcategory":"Special Training",
            "type":"Public Place"
        }
    ],
    "sg:phone":"+1 413 774 3335",
    "sg:postcode":"01301",
    "sg:province":"MA",
    "sg:tags":[
        "instruction",
        "music"
    ],
    "wof:name":"Music Academy Of Greenfield",
    "wof:placetype":"venue"
},
  "geometry": {"coordinates":[-72.595592,42.588104],"type":"Point"}
}