{
  "type": "Feature",
  "properties": {
    "addr:full": "9 Strathmore Rd Natick MA 01760",
    "addr:housenumber": "9",
    "addr:postcode": "01760",
    "addr:street": "Strathmore Rd",
    "iso:country": "US",
    "sg:address": "9 Strathmore Rd",
    "sg:city": "Natick",
    "sg:classifiers": [
      {
        "category": "Manufacturing",
        "subcategory": "Tools \u0026 Machinery",
        "type": "Manufacturing \u0026 Wholesale Goods"
      }
    ],
    "sg:phone": "+1 508 650 9971",
    "sg:postcode": "01760",
    "sg:province": "MA",
    "sg:tags": [
      "physician",
      "surgeon"
    ],
    "sg:website": "www.visionsciences.com",
    "wof:name": "Vision-Sciences Inc",
    "wof:placetype": "venue"
  },
  "geometry": {"coordinates":[-71.387601,42.294965],"type":"Point"}
}
