{
  "type": "Feature",
  "properties": {
    "iso:country":"US",
    "sg:address":"9 Strathmore Rd",
    "sg:city":"Natick",
    "sg:classifiers":[
        {
            "category":"Manufacturing",
            "subcategory":"Tools & Machinery",
            "type":"Manufacturing & Wholesale Goods"
        }
    ],
    "sg:phone":"+1 508 650 9971",
    "sg:postcode":"01760",
    "sg:province":"MA",
    "sg:tags":[
        "physician",
        "surgeon"
    ],
    "sg:website":"www.visionsciences.com",
    "wof:name":"Vision-Sciences Inc",
    "wof:placetype":"venue"
},
  "geometry": {"coordinates":[-71.387601,42.294965],"type":"Point"}
}