{
  "type": "Feature",
  "properties": {
    "iso:country":"US",
    "sg:address":"99 Searle Rd",
    "sg:city":"Huntington",
    "sg:classifiers":[
        {
            "category":"Manufacturing",
            "subcategory":"Buildings",
            "type":"Manufacturing & Wholesale Goods"
        },
        {
            "category":"Building & Trades",
            "subcategory":"Construction",
            "type":"Services"
        }
    ],
    "sg:phone":"+1 413 667 3925",
    "sg:postcode":"01050",
    "sg:province":"MA",
    "sg:tags":[
        "home",
        "builder",
        "contractor"
    ],
    "wof:name":"Carleton Construction",
    "wof:placetype":"venue"
},
  "geometry": {"coordinates":[-72.840889,42.304321],"type":"Point"}
}