{
  "type": "Feature",
  "properties": {
    "addr:full":"272 Washington St Dedham MA 02026",
    "addr:housenumber":"272",
    "addr:postcode":"02026",
    "addr:street":"Washington St",
    "iso:country":"US",
    "sg:address":"272 Washington St",
    "sg:city":"Dedham",
    "sg:classifiers":[
        {
            "category":"Bars & Pubs",
            "type":"Food & Drink"
        }
    ],
    "sg:phone":"+1 781 326 3957",
    "sg:postcode":"02026",
    "sg:province":"MA",
    "wof:name":"Auld Sod",
    "wof:placetype":"venue"
},
  "geometry": {"coordinates":[-71.1657,42.25429],"type":"Point"}
}