{
  "type": "Feature",
  "properties": {
    "addr:full":"68 Deerview Way Franklin MA 02038",
    "addr:housenumber":"68",
    "addr:postcode":"02038",
    "addr:street":"Deerview Way",
    "iso:country":"US",
    "sg:address":"68 Deerview Way",
    "sg:city":"Franklin",
    "sg:classifiers":[
        {
            "category":"Professional",
            "type":"Services"
        }
    ],
    "sg:phone":"+1   ",
    "sg:postcode":"02038",
    "sg:province":"MA",
    "wof:name":"Wendy A Dwyer",
    "wof:placetype":"venue"
},
  "geometry": {"coordinates":[-71.407853,42.114411],"type":"Point"}
}