{
  "type": "Feature",
  "properties": {
    "iso:country":"US",
    "sg:address":"41 West St",
    "sg:city":"Randolph",
    "sg:classifiers":[
        {
            "category":"Banks & Credit Unions",
            "subcategory":"Bank",
            "type":"Services"
        }
    ],
    "sg:phone":"+1 781 963 0612",
    "sg:postcode":"02368",
    "sg:province":"MA",
    "sg:tags":[
        "financing"
    ],
    "wof:name":"Diversified Funding Inc",
    "wof:placetype":"venue"
},
  "geometry": {"coordinates":[-71.046644,42.168959],"type":"Point"}
}