{
  "type": "Feature",
  "properties": {
    "addr:full": "41 West St Randolph MA 02368",
    "addr:housenumber": "41",
    "addr:postcode": "02368",
    "addr:street": "West St",
    "iso:country": "US",
    "sg:address": "41 West St",
    "sg:city": "Randolph",
    "sg:classifiers": [
      {
        "category": "Banks \u0026 Credit Unions",
        "subcategory": "Bank",
        "type": "Services"
      }
    ],
    "sg:phone": "+1 781 963 0612",
    "sg:postcode": "02368",
    "sg:province": "MA",
    "sg:tags": [
      "financing"
    ],
    "wof:name": "Diversified Funding Inc",
    "wof:placetype": "venue"
  },
  "geometry": {"coordinates":[-71.046644,42.168959],"type":"Point"}
}
