{
  "type": "Feature",
  "properties": {
    "addr:full":"365 Plantation St Worcester MA 01605",
    "addr:housenumber":"365",
    "addr:postcode":"01605",
    "addr:street":"Plantation St",
    "iso:country":"US",
    "sg:address":"365 Plantation St",
    "sg:city":"Worcester",
    "sg:classifiers":[
        {
            "category":"Health Services",
            "subcategory":"Clinic",
            "type":"Services"
        },
        {
            "category":"Health Services",
            "subcategory":"Doctor",
            "type":"Services"
        }
    ],
    "sg:phone":"+1 508 334 0100",
    "sg:postcode":"01605",
    "sg:province":"MA",
    "sg:tags":[
        "physician",
        "surgeon"
    ],
    "wof:name":"Umass Memorial Health Care Sys",
    "wof:placetype":"venue"
},
  "geometry": {"coordinates":[-71.76554899999999,42.276874],"type":"Point"}
}