{
  "type": "Feature",
  "properties": {
    "addr:full":"40 Industrial Park Rd Plymouth MA 02360",
    "addr:housenumber":"40",
    "addr:postcode":"02360",
    "addr:street":"Industrial Park Rd",
    "iso:country":"US",
    "sg:address":"40 Industrial Park Rd",
    "sg:city":"Plymouth",
    "sg:classifiers":[
        {
            "category":"Government",
            "subcategory":"Office",
            "type":"Public Place"
        }
    ],
    "sg:phone":"+1 508 747 5922",
    "sg:postcode":"02360",
    "sg:province":"MA",
    "sg:tags":[
        "state",
        "program"
    ],
    "wof:name":"Rehabilitation Commission",
    "wof:placetype":"venue"
},
  "geometry": {"coordinates":[-70.699253,41.961157],"type":"Point"}
}