{
  "type": "Feature",
  "properties": {
    "addr:full": "10 Cedar St Woburn MA 01801",
    "addr:housenumber": "10",
    "addr:postcode": "01801",
    "addr:street": "Cedar St",
    "iso:country": "US",
    "sg:address": "10 Cedar St",
    "sg:city": "Woburn",
    "sg:classifiers": [
      {
        "category": "Professional",
        "subcategory": "Employment Agencies",
        "type": "Services"
      }
    ],
    "sg:phone": "+1 781 938 8200",
    "sg:postcode": "01801",
    "sg:province": "MA",
    "wof:name": "Research Data Tech",
    "wof:placetype": "venue"
  },
  "geometry": {"coordinates":[-71.125895,42.494124],"type":"Point"}
}
