{
  "type": "Feature",
  "properties": {
    "addr:full": "516 Boston Tpke Shrewsbury MA 01545",
    "addr:housenumber": "516",
    "addr:postcode": "01545",
    "addr:street": "Boston Tpke",
    "iso:country": "US",
    "sg:address": "516 Boston Tpke",
    "sg:city": "Shrewsbury",
    "sg:classifiers": [
      {
        "category": "Wholesale",
        "subcategory": "Construction Materials",
        "type": "Manufacturing \u0026 Wholesale Goods"
      }
    ],
    "sg:phone": "+1 508 845 3100",
    "sg:postcode": "01545",
    "sg:province": "MA",
    "sg:tags": [
      "equipment",
      "masonry",
      "supply"
    ],
    "wof:name": "Cassa Stone Marble",
    "wof:placetype": "venue"
  },
  "geometry": {"coordinates":[-71.716601,42.276664],"type":"Point"}
}
