{
  "type": "Feature",
  "properties": {
    "addr:full": "1775 Andover St Tewksbury MA 01876",
    "addr:housenumber": "1775",
    "addr:postcode": "01876",
    "addr:street": "Andover St",
    "atp:label": "Residence Inn Boston Tewksbury/Andover, 1775 Andover Street Tewksbury MA US",
    "atp:similarity": 3.6987829208374023,
    "iso:country": "US",
    "sg:address": "1775 Andover St",
    "sg:city": "Tewksbury",
    "sg:classifiers": [
      {
        "category": "Travel",
        "subcategory": "Hotels \u0026 Motels",
        "type": "Entertainment"
      }
    ],
    "sg:phone": "+1 978 640 1003",
    "sg:postcode": "01876",
    "sg:province": "MA",
    "sg:tags": [
      "lodging"
    ],
    "sg:website": "http://marriott.com/BOSBT",
    "wof:name": "Residence Inn Boston - Tewksbury",
    "wof:placetype": "venue"
  },
  "geometry": {"coordinates":[-71.236658,42.64278],"type":"Point"}
}
