{
  "type": "Feature",
  "properties": {
    "iso:country":"US",
    "sg:address":"5 Quaboag St",
    "sg:city":"Brookfield",
    "sg:classifiers":[
        {
            "category":"Manufacturing",
            "subcategory":"Tools & Machinery",
            "type":"Manufacturing & Wholesale Goods"
        }
    ],
    "sg:phone":"+1 508 867 4021",
    "sg:postcode":"01506",
    "sg:province":"MA",
    "sg:tags":[
        "machine",
        "shop"
    ],
    "wof:name":"Performance Machine Inc",
    "wof:placetype":"venue"
},
  "geometry": {"coordinates":[-72.085171,42.210769],"type":"Point"}
}