{
  "type": "Feature",
  "properties": {
    "addr:full":"1 Harborside Dr Boston MA 02128",
    "addr:housenumber":"1",
    "addr:postcode":"02128",
    "addr:street":"Harborside Dr",
    "iso:country":"US",
    "sg:address":"1 Harborside Dr",
    "sg:city":"Boston",
    "sg:classifiers":[
        {
            "category":"Ice Cream",
            "type":"Food & Drink"
        }
    ],
    "sg:menulink":"http://www.allmenus.com/ma/boston/217700-ben--jerrys/menu/",
    "sg:phone":"0",
    "sg:postcode":"02128",
    "sg:province":"MA",
    "sg:tags":[
        "american"
    ],
    "wof:name":"Ben & Jerry's",
    "wof:placetype":"venue"
},
  "geometry": {"coordinates":[-71.02752,42.366782],"type":"Point"}
}