{
  "type": "Feature",
  "properties": {
    "addr:full": "26 N Warren St Woburn MA 01801",
    "addr:housenumber": "26",
    "addr:postcode": "01801",
    "addr:street": "N Warren St",
    "iso:country": "US",
    "sg:address": "26 N Warren St",
    "sg:city": "Woburn",
    "sg:classifiers": [
      {
        "category": "Building \u0026 Trades",
        "subcategory": "Locksmith",
        "type": "Services"
      }
    ],
    "sg:phone": "+1 781 404 4615",
    "sg:postcode": "01801",
    "sg:province": "MA",
    "sg:tags": [
      "key"
    ],
    "wof:name": "Locksmith Needs",
    "wof:placetype": "venue"
  },
  "geometry": {"coordinates":[-71.15751,42.479282],"type":"Point"}
}
