{
  "type": "Feature",
  "properties": {
    "addr:full":"2 Taunton St Plainville MA 02762",
    "addr:housenumber":"2",
    "addr:postcode":"02762",
    "addr:street":"Taunton St",
    "iso:country":"US",
    "sg:address":"2 Taunton St",
    "sg:city":"Plainville",
    "sg:classifiers":[
        {
            "category":"Food & Beverages",
            "subcategory":"Bakery",
            "type":"Retail Goods"
        }
    ],
    "sg:phone":"+1 508 695 6469",
    "sg:postcode":"02762",
    "sg:province":"MA",
    "sg:tags":[
        "sandwich"
    ],
    "sg:website":"www.dangelos.com",
    "wof:name":"D'angelo Sandwich Shops",
    "wof:placetype":"venue"
},
  "geometry": {"coordinates":[-71.304901,42.009701],"type":"Point"}
}