{
  "type": "Feature",
  "properties": {
    "addr:full": "247 Elm St Somerville MA 02144",
    "addr:housenumber": "247",
    "addr:postcode": "02144",
    "addr:street": "Elm St",
    "iso:country": "US",
    "sg:address": "247 Elm St",
    "sg:city": "Somerville",
    "sg:classifiers": [
      {
        "category": "Arts \u0026 Performance",
        "subcategory": "Theater",
        "type": "Entertainment"
      }
    ],
    "sg:phone": "+1 617 776 2913",
    "sg:postcode": "02144",
    "sg:province": "MA",
    "sg:tags": [
      "bureau"
    ],
    "wof:name": "Binky Boy Entertainment",
    "wof:placetype": "venue"
  },
  "geometry": {"coordinates":[-71.121423,42.394734],"type":"Point"}
}
