{
  "type": "Feature",
  "properties": {
    "iso:country":"US",
    "sg:address":"300 Nahatan St",
    "sg:city":"Westwood",
    "sg:classifiers":[
        {
            "category":"Building & Trades",
            "subcategory":"Construction",
            "type":"Services"
        }
    ],
    "sg:phone":"+1 781 329 5530",
    "sg:postcode":"02090",
    "sg:province":"MA",
    "sg:tags":[
        "designer"
    ],
    "wof:name":"Kentceptions",
    "wof:placetype":"venue"
},
  "geometry": {"coordinates":[-71.211325,42.209543],"type":"Point"}
}