{
  "type": "Feature",
  "properties": {
    "iso:country":"US",
    "sg:address":"71 Jasons Ln",
    "sg:city":"Rochester",
    "sg:classifiers":[
        {
            "category":"Farming",
            "subcategory":"Berry Farm",
            "type":"Manufacturing & Wholesale Goods"
        }
    ],
    "sg:phone":"+1   ",
    "sg:postcode":"02770",
    "sg:province":"MA",
    "sg:tags":[
        "crop"
    ],
    "wof:name":"Darren Morris",
    "wof:placetype":"venue"
},
  "geometry": {"coordinates":[-70.86441600000001,41.732114],"type":"Point"}
}