{
  "type": "Feature",
  "properties": {
    "addr:full": "71 Jasons Ln Rochester MA 02770",
    "addr:housenumber": "71",
    "addr:postcode": "02770",
    "addr:street": "Jasons Ln",
    "iso:country": "US",
    "sg:address": "71 Jasons Ln",
    "sg:city": "Rochester",
    "sg:classifiers": [
      {
        "category": "Farming",
        "subcategory": "Berry Farm",
        "type": "Manufacturing \u0026 Wholesale Goods"
      }
    ],
    "sg:phone": "+1   ",
    "sg:postcode": "02770",
    "sg:province": "MA",
    "sg:tags": [
      "crop"
    ],
    "wof:name": "Darren Morris",
    "wof:placetype": "venue"
  },
  "geometry": {"coordinates":[-70.864416,41.732114],"type":"Point"}
}
