{
  "type": "Feature",
  "properties": {
    "iso:country":"US",
    "sg:address":"245 County St",
    "sg:city":"Attleboro",
    "sg:classifiers":[
        {
            "category":"Building & Trades",
            "subcategory":"Plumbing",
            "type":"Services"
        }
    ],
    "sg:phone":"+1 508 226 2101",
    "sg:postcode":"02703",
    "sg:province":"MA",
    "sg:tags":[
        "heating",
        "contractor"
    ],
    "wof:name":"All Systems Mechanical Inc",
    "wof:placetype":"venue"
},
  "geometry": {"coordinates":[-71.297545,41.935583],"type":"Point"}
}