{
  "type": "Feature",
  "properties": {
    "addr:full": "868 Worcester St Wellesley MA 02482",
    "addr:housenumber": "868",
    "addr:postcode": "02482",
    "addr:street": "Worcester St",
    "iso:country": "US",
    "sg:address": "868 Worcester St",
    "sg:city": "Wellesley",
    "sg:classifiers": [
      {
        "category": "Restaurant",
        "type": "Food \u0026 Drink"
      }
    ],
    "sg:phone": "+1 781 235 0020",
    "sg:postcode": "02482",
    "sg:province": "MA",
    "wof:name": "Domino's Pizza",
    "wof:placetype": "venue"
  },
  "geometry": {"coordinates":[-71.31326,42.30529],"type":"Point"}
}
