{
  "type": "Feature",
  "properties": {
    "iso:country":"US",
    "sg:address":"157 High Rd",
    "sg:city":"Newbury",
    "sg:classifiers":[
        {
            "category":"Home & Garden",
            "subcategory":"Garden Supply",
            "type":"Retail Goods"
        }
    ],
    "sg:phone":"+1 978 499 0038",
    "sg:postcode":"01951",
    "sg:province":"MA",
    "sg:tags":[
        "nurseryman"
    ],
    "wof:name":"Ould Towne Gardens",
    "wof:placetype":"venue"
},
  "geometry": {"coordinates":[-70.84446699999999,42.780383],"type":"Point"}
}