{
  "type": "Feature",
  "properties": {
    "addr:full": "157 High Rd Newbury MA 01951",
    "addr:housenumber": "157",
    "addr:postcode": "01951",
    "addr:street": "High Rd",
    "iso:country": "US",
    "sg:address": "157 High Rd",
    "sg:city": "Newbury",
    "sg:classifiers": [
      {
        "category": "Home \u0026 Garden",
        "subcategory": "Garden Supply",
        "type": "Retail Goods"
      }
    ],
    "sg:phone": "+1 978 499 0038",
    "sg:postcode": "01951",
    "sg:province": "MA",
    "sg:tags": [
      "nurseryman"
    ],
    "wof:name": "Ould Towne Gardens",
    "wof:placetype": "venue"
  },
  "geometry": {"coordinates":[-70.844467,42.780383],"type":"Point"}
}
