{
  "type": "Feature",
  "properties": {
    "addr:full":"21 Williams St Watertown MA 02472",
    "addr:housenumber":"21",
    "addr:postcode":"02472",
    "addr:street":"Williams St",
    "iso:country":"US",
    "sg:address":"21 Williams St",
    "sg:city":"Watertown",
    "sg:classifiers":[
        {
            "category":"Building & Trades",
            "subcategory":"Plumbing",
            "type":"Services"
        }
    ],
    "sg:phone":"+1 617 923 1452",
    "sg:postcode":"02472",
    "sg:province":"MA",
    "sg:tags":[
        "plumbing",
        "contractor"
    ],
    "wof:name":"Barbato Plumbing",
    "wof:placetype":"venue"
},
  "geometry": {"coordinates":[-71.183849,42.359266],"type":"Point"}
}