{
  "type": "Feature",
  "properties": {
    "addr:full": "635 Pulaski Blvd Bellingham MA 02019",
    "addr:housenumber": "635",
    "addr:postcode": "02019",
    "addr:street": "Pulaski Blvd",
    "iso:country": "US",
    "sg:address": "635 Pulaski Blvd",
    "sg:city": "Bellingham",
    "sg:classifiers": [
      {
        "category": "Professional",
        "subcategory": "Computer Services",
        "type": "Services"
      }
    ],
    "sg:phone": "+1 508 883 0307",
    "sg:postcode": "02019",
    "sg:province": "MA",
    "sg:tags": [
      "repair"
    ],
    "wof:name": "Down East Technology",
    "wof:placetype": "venue"
  },
  "geometry": {"coordinates":[-71.485054,42.032296],"type":"Point"}
}
