{
  "type": "Feature",
  "properties": {
    "addr:full": "4 Emerson Pl Apt 616 Boston MA 02114",
    "addr:housenumber": "4;616",
    "addr:postcode": "02114",
    "addr:street": "Emerson Pl Apt",
    "iso:country": "US",
    "sg:address": "4 Emerson Pl Apt 616",
    "sg:city": "Boston",
    "sg:classifiers": [
      {
        "category": "Wholesale",
        "subcategory": "Books, Periodicals, \u0026 Newspapers",
        "type": "Manufacturing \u0026 Wholesale Goods"
      }
    ],
    "sg:phone": "+1 617 242 3202",
    "sg:postcode": "02114",
    "sg:province": "MA",
    "sg:tags": [
      "publishers-periodical"
    ],
    "wof:name": "Nuclear News Magazine",
    "wof:placetype": "venue"
  },
  "geometry": {"coordinates":[-71.068287,42.364579],"type":"Point"}
}
