{
  "type": "Feature",
  "properties": {
    "iso:country":"US",
    "sg:address":"4 Emerson Pl Apt 616",
    "sg:city":"Boston",
    "sg:classifiers":[
        {
            "category":"Wholesale",
            "subcategory":"Books, Periodicals, & Newspapers",
            "type":"Manufacturing & Wholesale Goods"
        }
    ],
    "sg:phone":"+1 617 242 3202",
    "sg:postcode":"02114",
    "sg:province":"MA",
    "sg:tags":[
        "publishers-periodical"
    ],
    "wof:name":"Nuclear News Magazine",
    "wof:placetype":"venue"
},
  "geometry": {"coordinates":[-71.068287,42.364579],"type":"Point"}
}