{
  "type": "Feature",
  "properties": {
    "addr:full": "2341 Main St Tewksbury MA 01876",
    "addr:housenumber": "2341",
    "addr:postcode": "01876",
    "addr:street": "Main St",
    "iso:country": "US",
    "sg:address": "2341 Main St",
    "sg:city": "Tewksbury",
    "sg:classifiers": [
      {
        "category": "Wholesale",
        "subcategory": "Medical Equipment \u0026 Supplies",
        "type": "Manufacturing \u0026 Wholesale Goods"
      },
      {
        "category": "Shopping",
        "subcategory": "Beauty \u0026 Cosmetics",
        "type": "Retail Goods"
      },
      {
        "category": "Food \u0026 Beverages",
        "subcategory": "Specialty",
        "type": "Retail Goods"
      },
      {
        "category": "Shopping",
        "subcategory": "Computers \u0026 Home Electronics",
        "type": "Retail Goods"
      },
      {
        "category": "Shopping",
        "subcategory": "Optical Goods",
        "type": "Retail Goods"
      },
      {
        "category": "Personal",
        "subcategory": "Skin Care",
        "type": "Services"
      },
      {
        "category": "Manufacturing",
        "subcategory": "Chemicals \u0026 Compounds",
        "type": "Manufacturing \u0026 Wholesale Goods"
      },
      {
        "category": "Retail",
        "subcategory": "Photofinishing",
        "type": "Services"
      },
      {
        "category": "Shopping",
        "subcategory": "Pharmacy",
        "type": "Retail Goods"
      },
      {
        "category": "Health Services",
        "subcategory": "Optometrist",
        "type": "Services"
      },
      {
        "category": "Food \u0026 Beverages",
        "subcategory": "Groceries \u0026 Convenience Stores",
        "type": "Retail Goods"
      }
    ],
    "sg:phone": "+1 978 988 5534",
    "sg:postcode": "01876",
    "sg:province": "MA",
    "sg:tags": [
      "pharmaceutical",
      "product",
      "photo",
      "wheelchair",
      "vitamin",
      "perfume",
      "lens",
      "supplement",
      "contact",
      "wellness",
      "finishing",
      "consumer"
    ],
    "sg:website": "http://www.walgreens.com/default.jsp?ec=iyp_yellowpages_trademark",
    "wof:name": "Walgreens Pharmacies",
    "wof:placetype": "venue"
  },
  "geometry": {"coordinates":[-71.193687,42.579609],"type":"Point"}
}
