{
  "type": "Feature",
  "properties": {
    "addr:full": "240 Bedford St Ste 4 Lexington MA 02420",
    "addr:housenumber": "240",
    "addr:postcode": "02420",
    "addr:street": "Bedford St Ste 4",
    "iso:country": "US",
    "sg:address": "240 Bedford St Ste 4",
    "sg:city": "Lexington",
    "sg:classifiers": [
      {
        "category": "Personal",
        "subcategory": "Beauty Salon",
        "type": "Services"
      }
    ],
    "sg:phone": "+1 781 862 5780",
    "sg:postcode": "02420",
    "sg:province": "MA",
    "sg:tags": [
      "hair",
      "stylist"
    ],
    "wof:name": "Vail's Studio Hair Designing",
    "wof:placetype": "venue"
  },
  "geometry": {"coordinates":[-71.239695,42.461997],"type":"Point"}
}
