{
  "type": "Feature",
  "properties": {
    "iso:country":"US",
    "sg:address":"165 Enterprise Dr",
    "sg:city":"Marshfield",
    "sg:classifiers":[
        {
            "category":"Professional",
            "type":"Services"
        }
    ],
    "sg:phone":"+1 781 843 2937",
    "sg:postcode":"02050",
    "sg:province":"MA",
    "sg:tags":[
        "establishment"
    ],
    "wof:name":"Braintree Forum",
    "wof:placetype":"venue"
},
  "geometry": {"coordinates":[-70.750787,42.100369],"type":"Point"}
}