{
  "type": "Feature",
  "properties": {
    "addr:full": "3 Baldwin Green Cmn # 304 Woburn MA 01801",
    "addr:housenumber": "3",
    "addr:postcode": "01801",
    "addr:street": "Baldwin Green Cmn # 304",
    "iso:country": "US",
    "sg:address": "3 Baldwin Green Cmn # 304",
    "sg:city": "Woburn",
    "sg:classifiers": [
      {
        "category": "Professional",
        "subcategory": "Lawyer \u0026 Legal Services",
        "type": "Services"
      }
    ],
    "sg:phone": "+1 781 932 0220",
    "sg:postcode": "01801",
    "sg:province": "MA",
    "sg:tags": [
      "plan"
    ],
    "wof:name": "Levenson Goldberg \u0026 Co",
    "wof:placetype": "venue"
  },
  "geometry": {"coordinates":[-71.158609,42.501731],"type":"Point"}
}
