{
  "type": "Feature",
  "properties": {
    "iso:country":"US",
    "sg:address":"542 Liberty St",
    "sg:city":"Hanson",
    "sg:classifiers":[
        {
            "category":"Government",
            "subcategory":"Office",
            "type":"Public Place"
        }
    ],
    "sg:phone":"+1 781 293 5165",
    "sg:postcode":"02341",
    "sg:province":"MA",
    "sg:tags":[
        "village"
    ],
    "wof:name":"Hanson Appeal Board",
    "wof:placetype":"venue"
},
  "geometry": {"coordinates":[-70.868849,42.065912],"type":"Point"}
}