{
  "type": "Feature",
  "properties": {
    "iso:country":"US",
    "sg:address":"33 Stanton St",
    "sg:city":"Dorchester Center",
    "sg:classifiers":[
        {
            "category":"Education",
            "subcategory":"School",
            "type":"Public Place"
        }
    ],
    "sg:phone":"+1 617 287 8622",
    "sg:postcode":"02124",
    "sg:province":"MA",
    "wof:name":"St Matthews Rectory",
    "wof:placetype":"venue"
},
  "geometry": {"coordinates":[-71.080101,42.285301],"type":"Point"}
}