{
  "type": "Feature",
  "properties": {
    "addr:full":"56 Carew Ter Springfield MA 01104",
    "addr:housenumber":"56",
    "addr:postcode":"01104",
    "addr:street":"Carew Ter",
    "iso:country":"US",
    "sg:address":"56 Carew Ter",
    "sg:city":"Springfield",
    "sg:classifiers":[
        {
            "category":"Building & Trades",
            "subcategory":"Construction",
            "type":"Services"
        }
    ],
    "sg:phone":"+1 413 734 8438",
    "sg:postcode":"01104",
    "sg:province":"MA",
    "sg:tags":[
        "roofing",
        "industrial",
        "contractors-commercial",
        "contractor"
    ],
    "wof:name":"Fitzgerald Roofing",
    "wof:placetype":"venue"
},
  "geometry": {"coordinates":[-72.570908,42.132276],"type":"Point"}
}