{
  "type": "Feature",
  "properties": {
    "iso:country":"US",
    "sg:address":"500 Commercial St",
    "sg:city":"Boston",
    "sg:classifiers":[
        {
            "category":"Professional",
            "subcategory":"Lawyer & Legal Services",
            "type":"Services"
        },
        {
            "category":"Professional",
            "subcategory":"Business Services",
            "type":"Services"
        }
    ],
    "sg:phone":"+1 617 723 3400",
    "sg:postcode":"02109",
    "sg:province":"MA",
    "sg:tags":[
        "arbitration"
    ],
    "wof:name":"Probate/Family Law Mediation",
    "wof:placetype":"venue"
},
  "geometry": {"coordinates":[-71.054714,42.367918],"type":"Point"}
}