{
  "type": "Feature",
  "properties": {
    "addr:full": "500 Commercial St Boston MA 02109",
    "addr:housenumber": "500",
    "addr:postcode": "02109",
    "addr:street": "Commercial St",
    "iso:country": "US",
    "sg:address": "500 Commercial St",
    "sg:city": "Boston",
    "sg:classifiers": [
      {
        "category": "Professional",
        "subcategory": "Lawyer \u0026 Legal Services",
        "type": "Services"
      },
      {
        "category": "Professional",
        "subcategory": "Business Services",
        "type": "Services"
      }
    ],
    "sg:phone": "+1 617 723 3400",
    "sg:postcode": "02109",
    "sg:province": "MA",
    "sg:tags": [
      "arbitration"
    ],
    "wof:name": "Probate/Family Law Mediation",
    "wof:placetype": "venue"
  },
  "geometry": {"coordinates":[-71.054714,42.367918],"type":"Point"}
}
