{
  "type": "Feature",
  "properties": {
    "iso:country":"US",
    "sg:address":"14 Beckman St",
    "sg:city":"Worcester",
    "sg:classifiers":[
        {
            "category":"Professional",
            "subcategory":"Art Services",
            "type":"Services"
        }
    ],
    "sg:phone":"+1   ",
    "sg:postcode":"01607",
    "sg:province":"MA",
    "sg:tags":[
        "commercial",
        "design"
    ],
    "wof:name":"Daniel Holmes",
    "wof:placetype":"venue"
},
  "geometry": {"coordinates":[-71.800342,42.231539],"type":"Point"}
}