{
  "type": "Feature",
  "properties": {
    "iso:country":"US",
    "sg:address":"25 5th St",
    "sg:city":"Norwood",
    "sg:classifiers":[
        {
            "category":"Building & Trades",
            "subcategory":"Construction",
            "type":"Services"
        }
    ],
    "sg:phone":"+1 781 769 2760",
    "sg:postcode":"02062",
    "sg:province":"MA",
    "sg:tags":[
        "fence",
        "contractor"
    ],
    "wof:name":"Fences By Mark Williams",
    "wof:placetype":"venue"
},
  "geometry": {"coordinates":[-71.189151,42.185082],"type":"Point"}
}