{
  "type": "Feature",
  "properties": {
    "addr:full": "3 Samuel Dr Phillipston MA 01331",
    "addr:housenumber": "3",
    "addr:postcode": "01331",
    "addr:street": "Samuel Dr",
    "iso:country": "US",
    "sg:address": "3 Samuel Dr",
    "sg:city": "Phillipston",
    "sg:classifiers": [
      {
        "category": "Restaurant",
        "type": "Food \u0026 Drink"
      }
    ],
    "sg:phone": "+1 978 939 1070",
    "sg:postcode": "01331",
    "sg:province": "MA",
    "sg:tags": [
      "caterer"
    ],
    "wof:name": "Royer's Catering Svc",
    "wof:placetype": "venue"
  },
  "geometry": {"coordinates":[-72.114911,42.526156],"type":"Point"}
}
