{
  "type": "Feature",
  "properties": {
    "addr:full":"495 Columbia St Somerville MA 02143",
    "addr:housenumber":"495",
    "addr:postcode":"02143",
    "addr:street":"Columbia St",
    "iso:country":"US",
    "sg:address":"495 Columbia St",
    "sg:city":"Somerville",
    "sg:classifiers":[
        {
            "category":"Personal",
            "type":"Services"
        }
    ],
    "sg:phone":"+1 617 623 7700",
    "sg:postcode":"02143",
    "sg:province":"MA",
    "sg:tags":[
        "mover"
    ],
    "sg:website":"www.precisionmoving.com/",
    "wof:name":"Precision Moving Company",
    "wof:placetype":"venue"
},
  "geometry": {"coordinates":[-71.094025,42.375051],"type":"Point"}
}