{
  "type": "Feature",
  "properties": {
    "iso:country":"US",
    "sg:address":"9 Parkvale Ave",
    "sg:city":"Allston",
    "sg:classifiers":[
        {
            "category":"Professional",
            "type":"Services"
        }
    ],
    "sg:phone":"+1   ",
    "sg:postcode":"02134",
    "sg:province":"MA",
    "wof:name":"Jennifer Goldstein",
    "wof:placetype":"venue"
},
  "geometry": {"coordinates":[-71.13311400000001,42.352866],"type":"Point"}
}