{
  "type": "Feature",
  "properties": {
    "addr:full": "9 Parkvale Ave Allston MA 02134",
    "addr:housenumber": "9",
    "addr:postcode": "02134",
    "addr:street": "Parkvale Ave",
    "iso:country": "US",
    "sg:address": "9 Parkvale Ave",
    "sg:city": "Allston",
    "sg:classifiers": [
      {
        "category": "Professional",
        "type": "Services"
      }
    ],
    "sg:phone": "+1   ",
    "sg:postcode": "02134",
    "sg:province": "MA",
    "wof:name": "Jennifer Goldstein",
    "wof:placetype": "venue"
  },
  "geometry": {"coordinates":[-71.133114,42.352866],"type":"Point"}
}
