{
  "type": "Feature",
  "properties": {
    "addr:full":"185 Commercial St Malden MA 02148",
    "addr:housenumber":"185",
    "addr:postcode":"02148",
    "addr:street":"Commercial St",
    "iso:country":"US",
    "sg:address":"185 Commercial St",
    "sg:city":"Malden",
    "sg:classifiers":[
        {
            "category":"Manufacturing",
            "subcategory":"Printing",
            "type":"Manufacturing & Wholesale Goods"
        },
        {
            "category":"Home & Garden",
            "subcategory":"Building Materials",
            "type":"Retail Goods"
        },
        {
            "category":"Building & Trades",
            "subcategory":"Construction",
            "type":"Services"
        },
        {
            "category":"Manufacturing",
            "subcategory":"Building Materials",
            "type":"Manufacturing & Wholesale Goods"
        }
    ],
    "sg:phone":"+1 781 324 8100",
    "sg:postcode":"02148",
    "sg:province":"MA",
    "sg:tags":[
        "roofing",
        "supply",
        "materials-wholesale",
        "contractor",
        "equipment",
        "siding",
        "manufacturer"
    ],
    "sg:website":"http://www.heritagewholesalers.com",
    "wof:name":"Heritage Wholesalers Inc",
    "wof:placetype":"venue"
},
  "geometry": {"coordinates":[-71.075474,42.420925],"type":"Point"}
}