{
  "type": "Feature",
  "properties": {
    "addr:full": "164 Northern Ave Boston MA 02210",
    "addr:housenumber": "164",
    "addr:postcode": "02210",
    "addr:street": "Northern Ave",
    "iso:country": "US",
    "sg:address": "164 Northern Ave",
    "sg:city": "Boston",
    "sg:classifiers": [
      {
        "category": "Real Estate",
        "subcategory": "Developer",
        "type": "Services"
      }
    ],
    "sg:phone": "+1 617 385 5060",
    "sg:postcode": "02210",
    "sg:province": "MA",
    "wof:name": "Drew Co",
    "wof:placetype": "venue"
  },
  "geometry": {"coordinates":[-71.042207,42.350318],"type":"Point"}
}
