{
  "type": "Feature",
  "properties": {
    "addr:full":"73 Andover St North Andover MA 01845",
    "addr:housenumber":"73",
    "addr:postcode":"01845",
    "addr:street":"Andover St",
    "iso:country":"US",
    "sg:address":"73 Andover St",
    "sg:city":"North Andover",
    "sg:classifiers":[
        {
            "category":"Real Estate",
            "subcategory":"Real Estate Agent",
            "type":"Services"
        }
    ],
    "sg:phone":"+1   ",
    "sg:postcode":"01845",
    "sg:province":"MA",
    "wof:name":"Eastern Massachusetts RE",
    "wof:placetype":"venue"
},
  "geometry": {"coordinates":[-71.11552,42.683045],"type":"Point"}
}