{
  "type": "Feature",
  "properties": {
    "addr:full": "98 Appleton St Boston MA 02116",
    "addr:housenumber": "98",
    "addr:postcode": "02116",
    "addr:street": "Appleton St",
    "iso:country": "US",
    "sg:address": "98 Appleton St",
    "sg:city": "Boston",
    "sg:classifiers": [
      {
        "category": "Professional",
        "subcategory": "Lawyer \u0026 Legal Services",
        "type": "Services"
      }
    ],
    "sg:phone": "+1 617 247 0804",
    "sg:postcode": "02116",
    "sg:province": "MA",
    "sg:tags": [
      "attorney",
      "estate",
      "wills",
      "planning",
      "trust"
    ],
    "wof:name": "98 Appleton St Condo Trust",
    "wof:placetype": "venue"
  },
  "geometry": {"coordinates":[-71.073753,42.345394],"type":"Point"}
}
