{
  "type": "Feature",
  "properties": {
    "addr:full":"16 Plantation Rd Plymouth MA 02360",
    "addr:housenumber":"16",
    "addr:postcode":"02360",
    "addr:street":"Plantation Rd",
    "iso:country":"US",
    "sg:address":"16 Plantation Rd",
    "sg:city":"Plymouth",
    "sg:classifiers":[
        {
            "category":"Recreation",
            "type":"Entertainment"
        }
    ],
    "sg:phone":"+1 508 746 4809",
    "sg:postcode":"02360",
    "sg:province":"MA",
    "sg:tags":[
        "party",
        "charter",
        "fishing",
        "boat"
    ],
    "sg:website":"www.fishchart.com",
    "wof:name":"Captain Tim Brady & Sons",
    "wof:placetype":"venue"
},
  "geometry": {"coordinates":[-70.707375,41.926471],"type":"Point"}
}