{
  "type": "Feature",
  "properties": {
    "iso:country":"US",
    "sg:address":"140 Marion Rd",
    "sg:city":"Wareham",
    "sg:classifiers":[
        {
            "category":"Real Estate",
            "subcategory":"Real Estate Agent",
            "type":"Services"
        }
    ],
    "sg:phone":"+1 508 295 4900",
    "sg:postcode":"02571",
    "sg:province":"MA",
    "wof:name":"Linn Real Estate",
    "wof:placetype":"venue"
},
  "geometry": {"coordinates":[-70.72964399999999,41.757734],"type":"Point"}
}