{
  "type": "Feature",
  "properties": {
    "iso:country":"US",
    "sg:address":"110 Pulpit Hill Rd",
    "sg:city":"Amherst",
    "sg:classifiers":[
        {
            "category":"Real Estate",
            "subcategory":"Real Estate Agent",
            "type":"Services"
        }
    ],
    "sg:phone":"+1 413 549 4848",
    "sg:postcode":"01002",
    "sg:province":"MA",
    "sg:tags":[
        "consultant"
    ],
    "sg:website":"www.devcycles.com",
    "wof:name":"Development Cycles",
    "wof:placetype":"venue"
},
  "geometry": {"coordinates":[-72.512169,42.419758],"type":"Point"}
}