{
  "type": "Feature",
  "properties": {
    "iso:country":"US",
    "sg:address":"1201 Broadway",
    "sg:city":"Saugus",
    "sg:classifiers":[
        {
            "category":"Home & Garden",
            "subcategory":"Furniture",
            "type":"Retail Goods"
        }
    ],
    "sg:phone":"+1 781 231 9941",
    "sg:postcode":"01906",
    "sg:province":"MA",
    "sg:tags":[
        "mattress"
    ],
    "wof:name":"Select Comfort Corp",
    "wof:placetype":"venue"
},
  "geometry": {"coordinates":[-71.024805,42.463018],"type":"Point"}
}