{
  "type": "Feature",
  "properties": {
    "addr:full":"637 Broadway Malden MA 02148",
    "addr:housenumber":"637",
    "addr:postcode":"02148",
    "addr:street":"Broadway",
    "iso:country":"US",
    "sg:address":"637 Broadway",
    "sg:city":"Malden",
    "sg:classifiers":[
        {
            "category":"Professional",
            "type":"Services"
        },
        {
            "category":"Food & Beverages",
            "subcategory":"Bakery",
            "type":"Retail Goods"
        },
        {
            "category":"Restaurant",
            "type":"Food & Drink"
        }
    ],
    "sg:phone":"+1 781 399 4811",
    "sg:postcode":"02148",
    "sg:province":"MA",
    "sg:tags":[
        "sandwich",
        "pizza",
        "caterer"
    ],
    "sg:website":"www.JimbosPlaceMalden.com",
    "wof:name":"Jimbo's Place",
    "wof:placetype":"venue"
},
  "geometry": {"coordinates":[-71.030838,42.442056],"type":"Point"}
}