{
  "type": "Feature",
  "properties": {
    "addr:full": "100 Maple Ave Rutland MA 01543",
    "addr:housenumber": "100",
    "addr:postcode": "01543",
    "addr:street": "Maple Ave",
    "iso:country": "US",
    "sg:address": "100 Maple Ave",
    "sg:city": "Rutland",
    "sg:classifiers": [
      {
        "category": "Social Services",
        "subcategory": "Child Care",
        "type": "Services"
      }
    ],
    "sg:phone": "+1 508 886 2492",
    "sg:postcode": "01543",
    "sg:province": "MA",
    "wof:name": "Little Wonders Learning",
    "wof:placetype": "venue"
  },
  "geometry": {"coordinates":[-71.945782,42.366581],"type":"Point"}
}
