{
  "type": "Feature",
  "properties": {
    "addr:full":"7 S Oxford Rd Millbury MA 01527",
    "addr:housenumber":"7",
    "addr:postcode":"01527",
    "addr:street":"S Oxford Rd",
    "iso:country":"US",
    "sg:address":"7 S Oxford Rd",
    "sg:city":"Millbury",
    "sg:classifiers":[
        {
            "category":"Professional",
            "type":"Services"
        }
    ],
    "sg:phone":"+1 508 865 4869",
    "sg:postcode":"01527",
    "sg:province":"MA",
    "sg:tags":[
        "establishment"
    ],
    "wof:name":"Kroll & Sons",
    "wof:placetype":"venue"
},
  "geometry": {"coordinates":[-71.806207,42.16883],"type":"Point"}
}