{
  "type": "Feature",
  "properties": {
    "iso:country":"US",
    "sg:address":"777 Dedham St",
    "sg:city":"Newton",
    "sg:classifiers":[
        {
            "category":"Education",
            "subcategory":"Vocational School",
            "type":"Public Place"
        }
    ],
    "sg:phone":"+1 617 928 4714",
    "sg:postcode":"02459",
    "sg:province":"MA",
    "wof:name":"Ne Institute Of Funeral Svc",
    "wof:placetype":"venue"
},
  "geometry": {"coordinates":[-71.187822,42.299821],"type":"Point"}
}