{
  "type": "Feature",
  "properties": {
    "addr:full": "130 New Boston St Ste 104 Woburn MA 01801",
    "addr:housenumber": "130",
    "addr:postcode": "01801",
    "addr:street": "New Boston St Ste 104",
    "iso:country": "US",
    "sg:address": "130 New Boston St Ste 104",
    "sg:city": "Woburn",
    "sg:classifiers": [
      {
        "category": "Professional",
        "subcategory": "Printing \u0026 Photocopies",
        "type": "Services"
      }
    ],
    "sg:phone": "+1 781 838 8963",
    "sg:postcode": "01801",
    "sg:province": "MA",
    "sg:website": "www.alphagraphics.com",
    "wof:name": "Alphagraphics",
    "wof:placetype": "venue"
  },
  "geometry": {"coordinates":[-71.14507,42.506384],"type":"Point"}
}
