{
  "type": "Feature",
  "properties": {
    "iso:country":"US",
    "sg:address":"8 Norwood Ct",
    "sg:city":"Gloucester",
    "sg:classifiers":[
        {
            "category":"Retail",
            "subcategory":"Repair Shop",
            "type":"Services"
        }
    ],
    "sg:phone":"+1 978 281 3595",
    "sg:postcode":"01930",
    "sg:province":"MA",
    "sg:tags":[
        "welding"
    ],
    "wof:name":"Phoenix Iron Works",
    "wof:placetype":"venue"
},
  "geometry": {"coordinates":[-70.650023,42.611302],"type":"Point"}
}