{
  "type": "Feature",
  "properties": {
    "addr:full": "85 Montague Rd Leverett MA 01054",
    "addr:housenumber": "85",
    "addr:postcode": "01054",
    "addr:street": "Montague Rd",
    "iso:country": "US",
    "ovtr:label": "Leverett Elementary School, 85 Montague Rd Leverett MA US",
    "ovtr:similarity": 3.3071129322052,
    "sg:address": "85 Montague Rd",
    "sg:city": "Leverett",
    "sg:classifiers": [
      {
        "category": "Education",
        "subcategory": "School",
        "type": "Public Place"
      }
    ],
    "sg:phone": "+1 413 548 9144",
    "sg:postcode": "01054",
    "sg:province": "MA",
    "sg:website": "www.leverett.mass.edu",
    "wof:name": "Leverett Elementary School",
    "wof:placetype": "venue"
  },
  "geometry": {"coordinates":[-72.49806,42.463571],"type":"Point"}
}
