{
  "type": "Feature",
  "properties": {
    "iso:country":"US",
    "sg:address":"85 Montague Rd",
    "sg:city":"Leverett",
    "sg:classifiers":[
        {
            "category":"Education",
            "subcategory":"School",
            "type":"Public Place"
        }
    ],
    "sg:phone":"+1 413 548 9144",
    "sg:postcode":"01054",
    "sg:province":"MA",
    "sg:website":"www.leverett.mass.edu",
    "wof:name":"Leverett Elementary School",
    "wof:placetype":"venue"
},
  "geometry": {"coordinates":[-72.49806,42.463571],"type":"Point"}
}