{
  "type": "Feature",
  "properties": {
    "iso:country":"US",
    "sg:address":"100 Broadway",
    "sg:city":"Norwood",
    "sg:classifiers":[
        {
            "category":"Professional",
            "subcategory":"Business Services",
            "type":"Services"
        },
        {
            "category":"Autos & Motor Vehicles",
            "subcategory":"Auto Supplies",
            "type":"Retail Goods"
        }
    ],
    "sg:phone":"+1 781 769 3320",
    "sg:postcode":"02062",
    "sg:province":"MA",
    "sg:tags":[
        "automobile",
        "stereo",
        "radio"
    ],
    "wof:name":"Reagan Audio Design LLC",
    "wof:placetype":"venue"
},
  "geometry": {"coordinates":[-71.199763,42.190158],"type":"Point"}
}