{
  "type": "Feature",
  "properties": {
    "addr:full": "80 Cliff Rd Nantucket MA 02554",
    "addr:housenumber": "80",
    "addr:postcode": "02554",
    "addr:street": "Cliff Rd",
    "iso:country": "US",
    "sg:address": "80 Cliff Rd",
    "sg:city": "Nantucket",
    "sg:classifiers": [
      {
        "category": "Professional",
        "subcategory": "Management \u0026 Consulting",
        "type": "Services"
      }
    ],
    "sg:phone": "+1 508 325 4044",
    "sg:postcode": "02554",
    "sg:province": "MA",
    "sg:tags": [
      "construction"
    ],
    "wof:name": "UCI Corp",
    "wof:placetype": "venue"
  },
  "geometry": {"coordinates":[-70.112366,41.291212],"type":"Point"}
}
