{
  "type": "Feature",
  "properties": {
    "iso:country":"US",
    "sg:address":"80 Cliff Rd",
    "sg:city":"Nantucket",
    "sg:classifiers":[
        {
            "category":"Professional",
            "subcategory":"Management & Consulting",
            "type":"Services"
        }
    ],
    "sg:phone":"+1 508 325 4044",
    "sg:postcode":"02554",
    "sg:province":"MA",
    "sg:tags":[
        "construction"
    ],
    "wof:name":"UCI Corp",
    "wof:placetype":"venue"
},
  "geometry": {"coordinates":[-70.11236599999999,41.291212],"type":"Point"}
}