{
  "type": "Feature",
  "properties": {
    "addr:full": "167 Elm St Salisbury MA 01952",
    "addr:housenumber": "167",
    "addr:postcode": "01952",
    "addr:street": "Elm St",
    "iso:country": "US",
    "sg:address": "167 Elm St",
    "sg:city": "Salisbury",
    "sg:classifiers": [
      {
        "category": "Retail",
        "subcategory": "Auto Rental",
        "type": "Services"
      }
    ],
    "sg:phone": "+1 978 463 0341",
    "sg:postcode": "01952",
    "sg:province": "MA",
    "sg:tags": [
      "renting",
      "truck",
      "leasing"
    ],
    "wof:name": "Penske Truck Rental",
    "wof:placetype": "venue"
  },
  "geometry": {"coordinates":[-70.889567,42.843754],"type":"Point"}
}
