{
  "type": "Feature",
  "properties": {
    "addr:full":"1160 Boylston St Chestnut Hill MA 02464",
    "addr:housenumber":"1160",
    "addr:postcode":"02464",
    "addr:street":"Boylston St",
    "iso:country":"US",
    "sg:address":"1160 Boylston St",
    "sg:city":"Chestnut Hill",
    "sg:classifiers":[
        {
            "category":"Personal",
            "subcategory":"Beauty Salon",
            "type":"Services"
        }
    ],
    "sg:phone":"+1 617 566 6520",
    "sg:postcode":"02464",
    "sg:province":"MA",
    "wof:name":"Changes Salon",
    "wof:placetype":"venue"
},
  "geometry": {"coordinates":[-71.220401,42.317735],"type":"Point"}
}