{
  "type": "Feature",
  "properties": {
    "addr:full":"830 Main St Brockton MA 02301",
    "addr:housenumber":"830",
    "addr:postcode":"02301",
    "addr:street":"Main St",
    "iso:country":"US",
    "sg:address":"830 Main St",
    "sg:city":"Brockton",
    "sg:classifiers":[
        {
            "category":"Real Estate",
            "subcategory":"Real Estate Agent",
            "type":"Services"
        }
    ],
    "sg:phone":"+1 508 586 5035",
    "sg:postcode":"02301",
    "sg:province":"MA",
    "sg:tags":[
        "preparation",
        "property",
        "tax",
        "casualty"
    ],
    "wof:name":"Goncalves Real Estate",
    "wof:placetype":"venue"
},
  "geometry": {"coordinates":[-71.01739999999999,42.068925],"type":"Point"}
}