{
  "type": "Feature",
  "properties": {
    "iso:country":"US",
    "sg:address":"148 Park Ln",
    "sg:city":"Sheffield",
    "sg:classifiers":[
        {
            "category":"Building & Trades",
            "subcategory":"Construction",
            "type":"Services"
        }
    ],
    "sg:phone":"+1   ",
    "sg:postcode":"01257",
    "sg:province":"MA",
    "sg:tags":[
        "house",
        "contract"
    ],
    "wof:name":"Buellworks",
    "wof:placetype":"venue"
},
  "geometry": {"coordinates":[-73.36592400000001,42.104876],"type":"Point"}
}