{
  "type": "Feature",
  "properties": {
    "addr:full": "148 Park Ln Sheffield MA 01257",
    "addr:housenumber": "148",
    "addr:postcode": "01257",
    "addr:street": "Park Ln",
    "iso:country": "US",
    "sg:address": "148 Park Ln",
    "sg:city": "Sheffield",
    "sg:classifiers": [
      {
        "category": "Building \u0026 Trades",
        "subcategory": "Construction",
        "type": "Services"
      }
    ],
    "sg:phone": "+1   ",
    "sg:postcode": "01257",
    "sg:province": "MA",
    "sg:tags": [
      "house",
      "contract"
    ],
    "wof:name": "Buellworks",
    "wof:placetype": "venue"
  },
  "geometry": {"coordinates":[-73.365924,42.104876],"type":"Point"}
}
