{
  "type": "Feature",
  "properties": {
    "addr:full": "2 Elmwood Cir Peabody MA 01960",
    "addr:housenumber": "2",
    "addr:postcode": "01960",
    "addr:street": "Elmwood Cir",
    "iso:country": "US",
    "sg:address": "2 Elmwood Cir",
    "sg:city": "Peabody",
    "sg:classifiers": [
      {
        "category": "Home \u0026 Garden",
        "subcategory": "Building Materials",
        "type": "Retail Goods"
      }
    ],
    "sg:phone": "+1 978 532 2644",
    "sg:postcode": "01960",
    "sg:province": "MA",
    "sg:tags": [
      "door"
    ],
    "wof:name": "Budget Overhead Door",
    "wof:placetype": "venue"
  },
  "geometry": {"coordinates":[-70.984541,42.511737],"type":"Point"}
}
