{
  "type": "Feature",
  "properties": {
    "iso:country":"US",
    "sg:address":"2 Elmwood Cir",
    "sg:city":"Peabody",
    "sg:classifiers":[
        {
            "category":"Home & Garden",
            "subcategory":"Building Materials",
            "type":"Retail Goods"
        }
    ],
    "sg:phone":"+1 978 532 2644",
    "sg:postcode":"01960",
    "sg:province":"MA",
    "sg:tags":[
        "door"
    ],
    "wof:name":"Budget Overhead Door",
    "wof:placetype":"venue"
},
  "geometry": {"coordinates":[-70.98454099999999,42.511737],"type":"Point"}
}