{
  "type": "Feature",
  "properties": {
    "addr:full":"257 Sandwich St Plymouth MA 02360",
    "addr:housenumber":"257",
    "addr:postcode":"02360",
    "addr:street":"Sandwich St",
    "iso:country":"US",
    "sg:address":"257 Sandwich St",
    "sg:city":"Plymouth",
    "sg:classifiers":[
        {
            "category":"Building & Trades",
            "subcategory":"Landscaping Services",
            "type":"Services"
        }
    ],
    "sg:phone":"+1   ",
    "sg:postcode":"02360",
    "sg:province":"MA",
    "wof:name":"Custom Coastal Landcare",
    "wof:placetype":"venue"
},
  "geometry": {"coordinates":[-70.64604199999999,41.945232],"type":"Point"}
}