{
  "type": "Feature",
  "properties": {
    "iso:country":"US",
    "sg:address":"15 Thompson Ave",
    "sg:city":"Brockton",
    "sg:classifiers":[
        {
            "category":"Government",
            "subcategory":"Office",
            "type":"Public Place"
        }
    ],
    "sg:phone":"+1 508 588 4909",
    "sg:postcode":"02301",
    "sg:province":"MA",
    "sg:tags":[
        "village"
    ],
    "wof:name":"Brockton City Council",
    "wof:placetype":"venue"
},
  "geometry": {"coordinates":[-71.03609,42.094534],"type":"Point"}
}