{
  "type": "Feature",
  "properties": {
    "addr:full": "460 Salem Street Medford MA 02155",
    "addr:housenumber": "460",
    "addr:postcode": "02155",
    "addr:street": "Salem Street",
    "iso:country": "US",
    "sg:address": "460 Salem Street",
    "sg:city": "Medford",
    "sg:classifiers": [
      {
        "category": "Personal",
        "subcategory": "Barber",
        "type": "Services"
      }
    ],
    "sg:phone": "+1 781 391 1422",
    "sg:postcode": "02155",
    "sg:province": "MA",
    "wof:name": "Valley Barber Shop",
    "wof:placetype": "venue"
  },
  "geometry": {"coordinates":[-71.090824,42.423245],"type":"Point"}
}
