{
  "type": "Feature",
  "properties": {
    "addr:full": "19 Warren St Randolph MA 02368",
    "addr:housenumber": "19",
    "addr:postcode": "02368",
    "addr:street": "Warren St",
    "iso:country": "US",
    "sg:address": "19 Warren St",
    "sg:city": "Randolph",
    "sg:classifiers": [
      {
        "category": "Restaurant",
        "type": "Food \u0026 Drink"
      }
    ],
    "sg:phone": "+1 781 961 7729",
    "sg:postcode": "02368",
    "sg:province": "MA",
    "sg:tags": [
      "italian"
    ],
    "wof:name": "Caffe Bella",
    "wof:placetype": "venue"
  },
  "geometry": {"coordinates":[-71.044166,42.165499],"type":"Point"}
}
