{
  "type": "Feature",
  "properties": {
    "iso:country":"US",
    "sg:address":"24 Commonwealth Ave",
    "sg:city":"Boston",
    "sg:classifiers":[
        {
            "category":"Manufacturing",
            "subcategory":"Printing",
            "type":"Manufacturing & Wholesale Goods"
        }
    ],
    "sg:phone":"+1 617 424 8732",
    "sg:postcode":"02116",
    "sg:province":"MA",
    "sg:tags":[
        "menu",
        "printer"
    ],
    "wof:name":"First Impressions",
    "wof:placetype":"venue"
},
  "geometry": {"coordinates":[-71.07292200000001,42.353033],"type":"Point"}
}