{
  "type": "Feature",
  "properties": {
    "addr:full": "24 Commonwealth Ave Boston MA 02116",
    "addr:housenumber": "24",
    "addr:postcode": "02116",
    "addr:street": "Commonwealth Ave",
    "iso:country": "US",
    "sg:address": "24 Commonwealth Ave",
    "sg:city": "Boston",
    "sg:classifiers": [
      {
        "category": "Manufacturing",
        "subcategory": "Printing",
        "type": "Manufacturing \u0026 Wholesale Goods"
      }
    ],
    "sg:phone": "+1 617 424 8732",
    "sg:postcode": "02116",
    "sg:province": "MA",
    "sg:tags": [
      "menu",
      "printer"
    ],
    "wof:name": "First Impressions",
    "wof:placetype": "venue"
  },
  "geometry": {"coordinates":[-71.072922,42.353033],"type":"Point"}
}
