{
  "type": "Feature",
  "properties": {
    "addr:full":"53 N Main St Randolph MA 02368",
    "addr:housenumber":"53",
    "addr:postcode":"02368",
    "addr:street":"N Main St",
    "iso:country":"US",
    "sg:address":"53 N Main St",
    "sg:city":"Randolph",
    "sg:classifiers":[
        {
            "category":"Retail",
            "subcategory":"Repair Shop",
            "type":"Services"
        }
    ],
    "sg:phone":"+1 781 300 0114",
    "sg:postcode":"02368",
    "sg:province":"MA",
    "sg:tags":[
        "lock",
        "locksmith"
    ],
    "wof:name":"24 Hour 7 Day Emerg Lcksmth",
    "wof:placetype":"venue"
},
  "geometry": {"coordinates":[-71.042596,42.164604],"type":"Point"}
}