{
  "type": "Feature",
  "properties": {
    "iso:country":"US",
    "sg:address":"381 Broadway",
    "sg:city":"Chelsea",
    "sg:classifiers":[
        {
            "category":"Shopping",
            "subcategory":"Computers & Home Electronics",
            "type":"Retail Goods"
        }
    ],
    "sg:phone":"+1 617 889 5404",
    "sg:postcode":"02150",
    "sg:province":"MA",
    "sg:tags":[
        "equipment",
        "electronic",
        "supply"
    ],
    "wof:name":"Castillo Production",
    "wof:placetype":"venue"
},
  "geometry": {"coordinates":[-71.035141,42.391928],"type":"Point"}
}