{
  "type": "Feature",
  "properties": {
    "iso:country":"US",
    "sg:address":"64 Union St",
    "sg:city":"Bridgewater",
    "sg:classifiers":[
        {
            "category":"Shopping",
            "type":"Retail Goods"
        }
    ],
    "sg:phone":"+1 508 697 5531",
    "sg:postcode":"02324",
    "sg:province":"MA",
    "sg:tags":[
        "equipment",
        "telephone",
        "supply"
    ],
    "wof:name":"Johnson Telecom",
    "wof:placetype":"venue"
},
  "geometry": {"coordinates":[-70.980447,41.988787],"type":"Point"}
}