{
  "type": "Feature",
  "properties": {
    "addr:full": "51 Knower Rd Westminster MA 01473",
    "addr:housenumber": "51",
    "addr:postcode": "01473",
    "addr:street": "Knower Rd",
    "iso:country": "US",
    "sg:address": "51 Knower Rd",
    "sg:city": "Westminster",
    "sg:classifiers": [
      {
        "category": "Professional",
        "type": "Services"
      }
    ],
    "sg:phone": "+1 978 874 2929",
    "sg:postcode": "01473",
    "sg:province": "MA",
    "sg:tags": [
      "establishment"
    ],
    "wof:name": "Country Hen",
    "wof:placetype": "venue"
  },
  "geometry": {"coordinates":[-71.926825,42.536505],"type":"Point"}
}
