{
  "type": "Feature",
  "properties": {
    "iso:country":"US",
    "sg:address":"51 Knower Rd",
    "sg:city":"Westminster",
    "sg:classifiers":[
        {
            "category":"Professional",
            "type":"Services"
        }
    ],
    "sg:phone":"+1 978 874 2929",
    "sg:postcode":"01473",
    "sg:province":"MA",
    "sg:tags":[
        "establishment"
    ],
    "wof:name":"Country Hen",
    "wof:placetype":"venue"
},
  "geometry": {"coordinates":[-71.92682499999999,42.536505],"type":"Point"}
}