{
  "type": "Feature",
  "properties": {
    "addr:full": "58 Stevens St East Taunton MA 02718",
    "addr:housenumber": "58",
    "addr:postcode": "02718",
    "addr:street": "Stevens St",
    "iso:country": "US",
    "ovtr:label": "East Taunton Elementary School, 58 Stevens St Taunton MA US",
    "ovtr:similarity": 3.485266923904419,
    "sg:address": "58 Stevens St",
    "sg:city": "East Taunton",
    "sg:classifiers": [
      {
        "category": "Education",
        "subcategory": "School",
        "type": "Public Place"
      }
    ],
    "sg:phone": "+1 508 821 1330",
    "sg:postcode": "02718",
    "sg:province": "MA",
    "sg:website": "www.tauntonschools.org",
    "wof:name": "East Taunton Elementary School",
    "wof:placetype": "venue"
  },
  "geometry": {"coordinates":[-71.0453,41.870617],"type":"Point"}
}
