{
  "type": "Feature",
  "properties": {
    "addr:full":"3 Turnpike Rd Southborough MA 01772",
    "addr:housenumber":"3",
    "addr:postcode":"01772",
    "addr:street":"Turnpike Rd",
    "iso:country":"US",
    "sg:address":"3 Turnpike Rd",
    "sg:city":"Southborough",
    "sg:classifiers":[
        {
            "category":"Utilities",
            "subcategory":"Mobile Phone",
            "type":"Services"
        }
    ],
    "sg:phone":"+1 508 303 0808",
    "sg:postcode":"01772",
    "sg:province":"MA",
    "sg:tags":[
        "telephone",
        "cellular"
    ],
    "wof:name":"Atlantic Wireless Inc",
    "wof:placetype":"venue"
},
  "geometry": {"coordinates":[-71.493601,42.296921],"type":"Point"}
}