{
  "type": "Feature",
  "properties": {
    "iso:country":"US",
    "sg:address":"11 Massasoit St",
    "sg:city":"Medway",
    "sg:classifiers":[
        {
            "category":"Recreation",
            "type":"Entertainment"
        }
    ],
    "sg:phone":"+1 508 533 7631",
    "sg:postcode":"02053",
    "sg:province":"MA",
    "sg:tags":[
        "tennis",
        "court"
    ],
    "wof:name":"Charles River Tennis Club",
    "wof:placetype":"venue"
},
  "geometry": {"coordinates":[-71.409294,42.137251],"type":"Point"}
}