{
  "type": "Feature",
  "properties": {
    "addr:full":"13 Symphony Rd Boston MA 02115",
    "addr:housenumber":"13",
    "addr:postcode":"02115",
    "addr:street":"Symphony Rd",
    "iso:country":"US",
    "sg:address":"13 Symphony Rd",
    "sg:city":"Boston",
    "sg:classifiers":[
        {
            "category":"Sports & Exercise",
            "subcategory":"Gym",
            "type":"Entertainment"
        }
    ],
    "sg:phone":"+1 617 859 0088",
    "sg:postcode":"02115",
    "sg:province":"MA",
    "sg:tags":[
        "gymnasium"
    ],
    "wof:name":"Augustin Joy Certified Fitness",
    "wof:placetype":"venue"
},
  "geometry": {"coordinates":[-71.087159,42.342777],"type":"Point"}
}