{
  "type": "Feature",
  "properties": {
    "addr:full": "48 Pearl St Chelsea MA 02150",
    "addr:housenumber": "48",
    "addr:postcode": "02150",
    "addr:street": "Pearl St",
    "iso:country": "US",
    "sg:address": "48 Pearl St",
    "sg:city": "Chelsea",
    "sg:classifiers": [
      {
        "category": "Autos \u0026 Motor Vehicles",
        "subcategory": "Automobile Sales",
        "type": "Retail Goods"
      }
    ],
    "sg:phone": "+1 617 889 0084",
    "sg:postcode": "02150",
    "sg:province": "MA",
    "sg:tags": [
      "car",
      "used"
    ],
    "wof:name": "Eddie's Auto Sales",
    "wof:placetype": "venue"
  },
  "geometry": {"coordinates":[-71.038661,42.387973],"type":"Point"}
}
