{
  "type": "Feature",
  "properties": {
    "iso:country":"US",
    "sg:address":"116 Norfolk St",
    "sg:city":"Cambridge",
    "sg:classifiers":[
        {
            "category":"Real Estate",
            "subcategory":"Real Estate Operator",
            "type":"Services"
        }
    ],
    "sg:phone":"+1 617 547 3543",
    "sg:postcode":"02139",
    "sg:province":"MA",
    "sg:tags":[
        "apartment"
    ],
    "wof:name":"Norfolk Street Elderly Ctr and Congruent Facility",
    "wof:placetype":"venue"
},
  "geometry": {"coordinates":[-71.099998,42.367001],"type":"Point"}
}