{
  "type": "Feature",
  "properties": {
    "iso:country":"US",
    "sg:address":"7 Harvard Street",
    "sg:city":"Brookline",
    "sg:classifiers":[
        {
            "category":"Professional",
            "subcategory":"Lawyer & Legal Services",
            "type":"Services"
        }
    ],
    "sg:phone":"+1 617 566 2300",
    "sg:postcode":"02445",
    "sg:province":"MA",
    "wof:name":"Goldenberg Stephen B Atty",
    "wof:placetype":"venue"
},
  "geometry": {"coordinates":[-71.118669,42.333606],"type":"Point"}
}