{
  "type": "Feature",
  "properties": {
    "addr:full":"1 Oxbow Dr Acton MA 01720",
    "addr:housenumber":"1",
    "addr:postcode":"01720",
    "addr:street":"Oxbow Dr",
    "iso:country":"US",
    "sg:address":"1 Oxbow Dr",
    "sg:city":"Acton",
    "sg:classifiers":[
        {
            "category":"Professional",
            "subcategory":"Computer Services",
            "type":"Services"
        }
    ],
    "sg:phone":"+1   ",
    "sg:postcode":"01720",
    "sg:province":"MA",
    "sg:tags":[
        "programmer"
    ],
    "wof:name":"Eswarappa Shailamma",
    "wof:placetype":"venue"
},
  "geometry": {"coordinates":[-71.41306899999999,42.498925],"type":"Point"}
}