{
  "type": "Feature",
  "properties": {
    "addr:full":"82 Scott Cir Dedham MA 02026",
    "addr:housenumber":"82",
    "addr:postcode":"02026",
    "addr:street":"Scott Cir",
    "iso:country":"US",
    "sg:address":"82 Scott Cir",
    "sg:city":"Dedham",
    "sg:classifiers":[
        {
            "category":"Building & Trades",
            "subcategory":"Locksmith",
            "type":"Services"
        }
    ],
    "sg:phone":"+1 781 366 9156",
    "sg:postcode":"02026",
    "sg:province":"MA",
    "sg:tags":[
        "key"
    ],
    "wof:name":"Available Emergency Locksmith",
    "wof:placetype":"venue"
},
  "geometry": {"coordinates":[-71.15331500000001,42.221578],"type":"Point"}
}