{
  "type": "Feature",
  "properties": {
    "addr:full":"211 Alewife Brook Pkwy Cambridge MA 02138",
    "addr:housenumber":"211",
    "addr:postcode":"02138",
    "addr:street":"Alewife Brook Pkwy",
    "iso:country":"US",
    "sg:address":"211 Alewife Brook Pkwy",
    "sg:city":"Cambridge",
    "sg:classifiers":[
        {
            "category":"Shopping",
            "type":"Retail Goods"
        }
    ],
    "sg:phone":"+1 617 489 7387",
    "sg:postcode":"02138",
    "sg:province":"MA",
    "sg:tags":[
        "pet",
        "food",
        "store",
        "supply"
    ],
    "wof:name":"Pet Supply Outlet Store",
    "wof:placetype":"venue"
},
  "geometry": {"coordinates":[-71.143012,42.389085],"type":"Point"}
}