{
  "type": "Feature",
  "properties": {
    "addr:full": "14 Clifford St Pittsfield MA 01201",
    "addr:housenumber": "14",
    "addr:postcode": "01201",
    "addr:street": "Clifford St",
    "iso:country": "US",
    "sg:address": "14 Clifford St",
    "sg:city": "Pittsfield",
    "sg:classifiers": [
      {
        "category": "Food \u0026 Beverages",
        "subcategory": "Groceries \u0026 Convenience Stores",
        "type": "Retail Goods"
      }
    ],
    "sg:phone": "+1   ",
    "sg:postcode": "01201",
    "sg:province": "MA",
    "wof:name": "New Winthrop Deli",
    "wof:placetype": "venue"
  },
  "geometry": {"coordinates":[-73.246354,42.478874],"type":"Point"}
}
