{
  "type": "Feature",
  "properties": {
    "iso:country":"US",
    "sg:address":"14 Clifford St",
    "sg:city":"Pittsfield",
    "sg:classifiers":[
        {
            "category":"Food & Beverages",
            "subcategory":"Groceries & Convenience Stores",
            "type":"Retail Goods"
        }
    ],
    "sg:phone":"+1   ",
    "sg:postcode":"01201",
    "sg:province":"MA",
    "wof:name":"New Winthrop Deli",
    "wof:placetype":"venue"
},
  "geometry": {"coordinates":[-73.246354,42.478874],"type":"Point"}
}