{
  "type": "Feature",
  "properties": {
    "addr:full":"330 West St Braintree MA 02184",
    "addr:housenumber":"330",
    "addr:postcode":"02184",
    "addr:street":"West St",
    "iso:country":"US",
    "sg:address":"330 West St",
    "sg:city":"Braintree",
    "sg:classifiers":[
        {
            "category":"Retail",
            "subcategory":"Auto Repair",
            "type":"Services"
        }
    ],
    "sg:phone":"+1 781 843 6404",
    "sg:postcode":"02184",
    "sg:province":"MA",
    "sg:tags":[
        "automobile",
        "top",
        "upholstery"
    ],
    "wof:name":"Dr Vinyl",
    "wof:placetype":"venue"
},
  "geometry": {"coordinates":[-71.019201,42.212212],"type":"Point"}
}