{
  "type": "Feature",
  "properties": {
    "addr:full":"27 Beach Rd Vineyard Haven MA 02568",
    "addr:housenumber":"27",
    "addr:postcode":"02568",
    "addr:street":"Beach Rd",
    "iso:country":"US",
    "sg:address":"27 Beach Rd",
    "sg:city":"Vineyard Haven",
    "sg:classifiers":[
        {
            "category":"Home & Garden",
            "subcategory":"Building Materials",
            "type":"Retail Goods"
        }
    ],
    "sg:phone":"+1 508 693 0075",
    "sg:postcode":"02568",
    "sg:province":"MA",
    "sg:tags":[
        "lumber"
    ],
    "wof:name":"H N Hinckley & Sons Inc",
    "wof:placetype":"venue"
},
  "geometry": {"coordinates":[-70.60080499999999,41.453692],"type":"Point"}
}