{
  "type": "Feature",
  "properties": {
    "addr:full": "38 Nathan Ellis Hwy Mashpee MA 02649",
    "addr:housenumber": "38",
    "addr:postcode": "02649",
    "addr:street": "Nathan Ellis Hwy",
    "iso:country": "US",
    "sg:address": "38 Nathan Ellis Hwy",
    "sg:city": "Mashpee",
    "sg:classifiers": [
      {
        "category": "Restaurant",
        "type": "Food \u0026 Drink"
      }
    ],
    "sg:phone": "+1 508 477 5806",
    "sg:postcode": "02649",
    "sg:province": "MA",
    "sg:tags": [
      "shop",
      "coffee"
    ],
    "wof:name": "Starbucks",
    "wof:placetype": "venue"
  },
  "geometry": {"coordinates":[-70.49057,41.618158],"type":"Point"}
}
