{
  "type": "Feature",
  "properties": {
    "iso:country":"US",
    "sg:address":"287 Grafton St",
    "sg:city":"Shrewsbury",
    "sg:classifiers":[
        {
            "category":"Autos & Motor Vehicles",
            "subcategory":"Auto Supplies",
            "type":"Retail Goods"
        }
    ],
    "sg:phone":"+1 508 845 6116",
    "sg:postcode":"01545",
    "sg:province":"MA",
    "sg:tags":[
        "repair",
        "brake",
        "tire"
    ],
    "sg:website":"http://www.ntb.com",
    "wof:name":"NTB - National Tire & Battery",
    "wof:placetype":"venue"
},
  "geometry": {"coordinates":[-71.711477,42.277225],"type":"Point"}
}