{
  "type": "Feature",
  "properties": {
    "addr:full": "247 Commercial St Lynn MA 01905",
    "addr:housenumber": "247",
    "addr:postcode": "01905",
    "addr:street": "Commercial St",
    "iso:country": "US",
    "sg:address": "247 Commercial St",
    "sg:city": "Lynn",
    "sg:classifiers": [
      {
        "category": "Utilities",
        "subcategory": "Refuse",
        "type": "Services"
      }
    ],
    "sg:phone": "+1 781 593 8106",
    "sg:postcode": "01905",
    "sg:province": "MA",
    "sg:tags": [
      "recycling",
      "center",
      "system"
    ],
    "wof:name": "American Ref Fuel Ops Semass",
    "wof:placetype": "venue"
  },
  "geometry": {"coordinates":[-70.957287,42.454682],"type":"Point"}
}
