{
  "type": "Feature",
  "properties": {
    "addr:full": "425 Plymouth St Abington MA 02351",
    "addr:housenumber": "425",
    "addr:postcode": "02351",
    "addr:street": "Plymouth St",
    "iso:country": "US",
    "sg:address": "425 Plymouth St",
    "sg:city": "Abington",
    "sg:classifiers": [
      {
        "category": "Organizations",
        "subcategory": "Religious Organization",
        "type": "Services"
      }
    ],
    "sg:phone": "+1 781 878 1194",
    "sg:postcode": "02351",
    "sg:province": "MA",
    "wof:name": "Society Of St Vincent De Paul",
    "wof:placetype": "venue"
  },
  "geometry": {"coordinates":[-70.936593,42.11789],"type":"Point"}
}
