{
  "type": "Feature",
  "properties": {
    "iso:country":"US",
    "sg:address":"126 Walnut St",
    "sg:city":"Springfield",
    "sg:classifiers":[
        {
            "category":"Restaurant",
            "type":"Food & Drink"
        }
    ],
    "sg:phone":"+1 413 733 4820",
    "sg:postcode":"01105",
    "sg:province":"MA",
    "wof:name":"Juncos & Cayey Restaurant",
    "wof:placetype":"venue"
},
  "geometry": {"coordinates":[-72.57303,42.105191],"type":"Point"}
}