{
  "type": "Feature",
  "properties": {
    "iso:country":"US",
    "sg:address":"26 Winthrop St",
    "sg:city":"Melrose",
    "sg:classifiers":[
        {
            "category":"Manufacturing",
            "subcategory":"Tools & Machinery",
            "type":"Manufacturing & Wholesale Goods"
        }
    ],
    "sg:phone":"+1 781 665 4428",
    "sg:postcode":"02176",
    "sg:province":"MA",
    "sg:tags":[
        "electric",
        "motor"
    ],
    "wof:name":"Hoagland Instrument",
    "wof:placetype":"venue"
},
  "geometry": {"coordinates":[-71.066148,42.457944],"type":"Point"}
}