{
  "type": "Feature",
  "properties": {
    "addr:full": "26 Winthrop St Melrose MA 02176",
    "addr:housenumber": "26",
    "addr:postcode": "02176",
    "addr:street": "Winthrop St",
    "iso:country": "US",
    "sg:address": "26 Winthrop St",
    "sg:city": "Melrose",
    "sg:classifiers": [
      {
        "category": "Manufacturing",
        "subcategory": "Tools \u0026 Machinery",
        "type": "Manufacturing \u0026 Wholesale Goods"
      }
    ],
    "sg:phone": "+1 781 665 4428",
    "sg:postcode": "02176",
    "sg:province": "MA",
    "sg:tags": [
      "electric",
      "motor"
    ],
    "wof:name": "Hoagland Instrument",
    "wof:placetype": "venue"
  },
  "geometry": {"coordinates":[-71.066148,42.457944],"type":"Point"}
}
