{
  "type": "Feature",
  "properties": {
    "addr:full":"89 Access Rd Ste A Norwood MA 02062",
    "addr:housenumber":"89",
    "addr:postcode":"02062",
    "addr:street":"Access Rd Ste A",
    "iso:country":"US",
    "sg:address":"89 Access Rd Ste A",
    "sg:city":"Norwood",
    "sg:classifiers":[
        {
            "category":"Professional",
            "subcategory":"Lawyer & Legal Services",
            "type":"Services"
        }
    ],
    "sg:phone":"+1 781 762 0077",
    "sg:postcode":"02062",
    "sg:province":"MA",
    "sg:tags":[
        "information",
        "attorney",
        "referral"
    ],
    "wof:name":"Duggan & Caccavaro",
    "wof:placetype":"venue"
},
  "geometry": {"coordinates":[-71.17797299999999,42.18517],"type":"Point"}
}