{
  "type": "Feature",
  "properties": {
    "addr:full": "219 Memorial Dr Springfield MA 01104",
    "addr:housenumber": "219",
    "addr:postcode": "01104",
    "addr:street": "Memorial Dr",
    "iso:country": "US",
    "sg:address": "219 Memorial Dr",
    "sg:city": "Springfield",
    "sg:classifiers": [
      {
        "category": "Utilities",
        "subcategory": "Water",
        "type": "Services"
      },
      {
        "category": "Coffee \u0026 Tea",
        "type": "Food \u0026 Drink"
      },
      {
        "category": "Wholesale",
        "subcategory": "Vending Machines",
        "type": "Manufacturing \u0026 Wholesale Goods"
      }
    ],
    "sg:phone": "+1 413 739 9603",
    "sg:postcode": "01104",
    "sg:province": "MA",
    "sg:tags": [
      "bulk",
      "companies-bottled"
    ],
    "sg:website": "http://www.aramaticcoffee.com",
    "wof:name": "Aramatic Coffee Service",
    "wof:placetype": "venue"
  },
  "geometry": {"coordinates":[-72.535962,42.140087],"type":"Point"}
}
