{
  "type": "Feature",
  "properties": {
    "addr:full": "223 Clover Hill Dr Feeding Hills MA 01030",
    "addr:housenumber": "223",
    "addr:postcode": "01030",
    "addr:street": "Clover Hill Dr",
    "iso:country": "US",
    "sg:address": "223 Clover Hill Dr",
    "sg:city": "Feeding Hills",
    "sg:classifiers": [
      {
        "category": "Manufacturing",
        "subcategory": "Paper Products",
        "type": "Manufacturing \u0026 Wholesale Goods"
      }
    ],
    "sg:phone": "+1 413 789 2660",
    "sg:postcode": "01030",
    "sg:province": "MA",
    "sg:tags": [
      "box"
    ],
    "sg:website": "www.akmpackaging.com",
    "wof:name": "AKM Packaging",
    "wof:placetype": "venue"
  },
  "geometry": {"coordinates":[-72.687378,42.082966],"type":"Point"}
}
