{
  "type": "Feature",
  "properties": {
    "addr:full": "264 Main St Rutland MA 01543",
    "addr:housenumber": "264",
    "addr:postcode": "01543",
    "addr:street": "Main St",
    "iso:country": "US",
    "ovtr:label": "Small Steps Preschool Inc, 264 Main St Rutland MA US",
    "ovtr:similarity": 2.5070559978485107,
    "sg:address": "264 Main St",
    "sg:city": "Rutland",
    "sg:classifiers": [
      {
        "category": "Education",
        "subcategory": "School",
        "type": "Public Place"
      }
    ],
    "sg:phone": "+1 508 886 8800",
    "sg:postcode": "01543",
    "sg:province": "MA",
    "wof:name": "Small Steps Preschool Inc",
    "wof:placetype": "venue"
  },
  "geometry": {"coordinates":[-71.955034,42.376221],"type":"Point"}
}
