{
  "type": "Feature",
  "properties": {
    "addr:full": "1321 Main St Reading MA 01867",
    "addr:housenumber": "1321",
    "addr:postcode": "01867",
    "addr:street": "Main St",
    "iso:country": "US",
    "sg:address": "1321 Main St",
    "sg:city": "Reading",
    "sg:classifiers": [
      {
        "category": "Health Services",
        "subcategory": "Health Practitioner",
        "type": "Services"
      }
    ],
    "sg:phone": "+1   ",
    "sg:postcode": "01867",
    "sg:province": "MA",
    "wof:name": "Kathleen M Barry",
    "wof:placetype": "venue"
  },
  "geometry": {"coordinates":[-71.104938,42.554278],"type":"Point"}
}
