{
  "type": "Feature",
  "properties": {
    "iso:country":"US",
    "sg:address":"18 Newfield Ln",
    "sg:city":"Yarmouth Port",
    "sg:classifiers":[
        {
            "category":"Professional",
            "subcategory":"Business Services",
            "type":"Services"
        }
    ],
    "sg:phone":"+1 508 375 9066",
    "sg:postcode":"02675",
    "sg:province":"MA",
    "sg:tags":[
        "recording",
        "studio"
    ],
    "wof:name":"10 MM Bootleg Studio",
    "wof:placetype":"venue"
},
  "geometry": {"coordinates":[-70.228942,41.692278],"type":"Point"}
}