{
  "type": "Feature",
  "properties": {
    "addr:full": "107 Salem Street Boston MA 02113",
    "addr:housenumber": "107",
    "addr:postcode": "02113",
    "addr:street": "Salem Street",
    "iso:country": "US",
    "ovtr:label": "Bacco Ristorante \u0026 Bar, 107 Salem St Boston MA US",
    "ovtr:similarity": 3.210618019104004,
    "sg:address": "107 Salem Street",
    "sg:city": "Boston",
    "sg:classifiers": [
      {
        "category": "Restaurant",
        "type": "Food \u0026 Drink"
      }
    ],
    "sg:phone": "+1 617 624 0454",
    "sg:postcode": "02113",
    "sg:province": "MA",
    "sg:tags": [
      "italian"
    ],
    "sg:website": "www.bacconorthend.com",
    "wof:name": "Bacco Ristorante",
    "wof:placetype": "venue"
  },
  "geometry": {"coordinates":[-71.05554,42.364124],"type":"Point"}
}
