{
  "type": "Feature",
  "properties": {
    "addr:full": "10 Main St Lakeville MA 02347",
    "addr:housenumber": "10",
    "addr:postcode": "02347",
    "addr:street": "Main St",
    "iso:country": "US",
    "sg:address": "10 Main St",
    "sg:city": "Lakeville",
    "sg:classifiers": [
      {
        "category": "Professional",
        "subcategory": "Lawyer \u0026 Legal Services",
        "type": "Services"
      }
    ],
    "sg:phone": "+1 508 946 9648",
    "sg:postcode": "02347",
    "sg:province": "MA",
    "sg:tags": [
      "attorney"
    ],
    "wof:name": "Arter Law Offices",
    "wof:placetype": "venue"
  },
  "geometry": {"coordinates":[-70.923054,41.880624],"type":"Point"}
}
