{
  "type": "Feature",
  "properties": {
    "addr:full":"56 West St Methuen MA 01844",
    "addr:housenumber":"56",
    "addr:postcode":"01844",
    "addr:street":"West St",
    "iso:country":"US",
    "sg:address":"56 West St",
    "sg:city":"Methuen",
    "sg:classifiers":[
        {
            "category":"Insurance",
            "subcategory":"Insurance Agent",
            "type":"Services"
        }
    ],
    "sg:phone":"+1 978 689 0566",
    "sg:postcode":"01844",
    "sg:province":"MA",
    "wof:name":"Ritter Associates",
    "wof:placetype":"venue"
},
  "geometry": {"coordinates":[-71.233852,42.727157],"type":"Point"}
}