{
  "type": "Feature",
  "properties": {
    "iso:country":"US",
    "sg:address":"298 Prospect St",
    "sg:city":"Stoughton",
    "sg:classifiers":[
        {
            "category":"Professional",
            "subcategory":"Computer Services",
            "type":"Services"
        }
    ],
    "sg:phone":"+1 781 344 0087",
    "sg:postcode":"02072",
    "sg:province":"MA",
    "sg:tags":[
        "consultant",
        "designer"
    ],
    "wof:name":"Graphical Software Co",
    "wof:placetype":"venue"
},
  "geometry": {"coordinates":[-71.090557,42.12309],"type":"Point"}
}