{
  "type": "Feature",
  "properties": {
    "addr:full": "39 Prospect St Wakefield MA 01880",
    "addr:housenumber": "39",
    "addr:postcode": "01880",
    "addr:street": "Prospect St",
    "iso:country": "US",
    "sg:address": "39 Prospect St",
    "sg:city": "Wakefield",
    "sg:classifiers": [
      {
        "category": "Education",
        "subcategory": "School",
        "type": "Public Place"
      }
    ],
    "sg:phone": "+1 781 246 6490",
    "sg:postcode": "01880",
    "sg:province": "MA",
    "wof:name": "West Ward School",
    "wof:placetype": "venue"
  },
  "geometry": {"coordinates":[-71.083278,42.505698],"type":"Point"}
}
