{
  "type": "Feature",
  "properties": {
    "iso:country":"US",
    "sg:address":"627 Hancock St",
    "sg:city":"Abington",
    "sg:classifiers":[
        {
            "category":"Manufacturing",
            "subcategory":"Signs",
            "type":"Manufacturing & Wholesale Goods"
        }
    ],
    "sg:phone":"+1 781 871 0411",
    "sg:postcode":"02351",
    "sg:province":"MA",
    "wof:name":"Abington Suburban Sign Co",
    "wof:placetype":"venue"
},
  "geometry": {"coordinates":[-70.975436,42.128424],"type":"Point"}
}