{
  "type": "Feature",
  "properties": {
    "iso:country":"US",
    "sg:address":"263 Brook St",
    "sg:city":"New Bedford",
    "sg:classifiers":[
        {
            "category":"Wholesale",
            "subcategory":"Machinery & Supplies",
            "type":"Manufacturing & Wholesale Goods"
        }
    ],
    "sg:phone":"+1 508 997 3448",
    "sg:postcode":"02745",
    "sg:province":"MA",
    "sg:tags":[
        "belting"
    ],
    "wof:name":"Gaj Industries Inc",
    "wof:placetype":"venue"
},
  "geometry": {"coordinates":[-70.93340999999999,41.666208],"type":"Point"}
}