{
  "type": "Feature",
  "properties": {
    "addr:full": "444 Pittsfield Rd Lenox MA 01240",
    "addr:housenumber": "444",
    "addr:postcode": "01240",
    "addr:street": "Pittsfield Rd",
    "iso:country": "US",
    "sg:address": "444 Pittsfield Rd",
    "sg:city": "Lenox",
    "sg:classifiers": [
      {
        "category": "Shopping",
        "subcategory": "Shoes",
        "type": "Retail Goods"
      }
    ],
    "sg:phone": "+1 413 442 6330",
    "sg:postcode": "01240",
    "sg:province": "MA",
    "wof:name": "Family Footwear Ctr",
    "wof:placetype": "venue"
  },
  "geometry": {"coordinates":[-73.266506,42.401934],"type":"Point"}
}
