{
  "type": "Feature",
  "properties": {
    "addr:full": "462 River Rd Westport MA 02790",
    "addr:housenumber": "462",
    "addr:postcode": "02790",
    "addr:street": "River Rd",
    "iso:country": "US",
    "sg:address": "462 River Rd",
    "sg:city": "Westport",
    "sg:classifiers": [
      {
        "category": "Professional",
        "type": "Services"
      }
    ],
    "sg:phone": "+1 508 636 6363",
    "sg:postcode": "02790",
    "sg:province": "MA",
    "sg:tags": [
      "establishment"
    ],
    "wof:name": "Harry T Whitin Inc",
    "wof:placetype": "venue"
  },
  "geometry": {"coordinates":[-71.105213,41.528865],"type":"Point"}
}
