{
  "type": "Feature",
  "properties": {
    "addr:full": "1020 Plain St Marshfield MA 02050",
    "addr:housenumber": "1020",
    "addr:postcode": "02050",
    "addr:street": "Plain St",
    "iso:country": "US",
    "sg:address": "1020 Plain St",
    "sg:city": "Marshfield",
    "sg:classifiers": [
      {
        "category": "Insurance",
        "subcategory": "Hazard Insurance",
        "type": "Services"
      }
    ],
    "sg:phone": "+1 781 837 6141",
    "sg:postcode": "02050",
    "sg:province": "MA",
    "sg:tags": [
      "commercial",
      "business"
    ],
    "wof:name": "Anderson Hokanson Insurance Agency",
    "wof:placetype": "venue"
  },
  "geometry": {"coordinates":[-70.759277,42.107021],"type":"Point"}
}
