{
  "type": "Feature",
  "properties": {
    "iso:country":"US",
    "sg:address":"100 1st Ave",
    "sg:city":"Charlestown",
    "sg:classifiers":[
        {
            "category":"Utilities",
            "subcategory":"Sewage",
            "type":"Services"
        }
    ],
    "sg:phone":"+1   ",
    "sg:postcode":"02129",
    "sg:province":"MA",
    "sg:tags":[
        "water",
        "sewer",
        "treatment"
    ],
    "wof:name":"Mwra",
    "wof:placetype":"venue"
},
  "geometry": {"coordinates":[-71.051191,42.376937],"type":"Point"}
}