{
  "type": "Feature",
  "properties": {
    "addr:full":"5 Cabot Pl Stoughton MA 02072",
    "addr:housenumber":"5",
    "addr:postcode":"02072",
    "addr:street":"Cabot Pl",
    "iso:country":"US",
    "sg:address":"5 Cabot Pl",
    "sg:city":"Stoughton",
    "sg:classifiers":[
        {
            "category":"Building & Trades",
            "subcategory":"Construction",
            "type":"Services"
        }
    ],
    "sg:phone":"+1 781 341 4454",
    "sg:postcode":"02072",
    "sg:province":"MA",
    "sg:tags":[
        "general",
        "contractor"
    ],
    "wof:name":"Landtech General Contracting",
    "wof:placetype":"venue"
},
  "geometry": {"coordinates":[-71.073973,42.152829],"type":"Point"}
}