{
  "type": "Feature",
  "properties": {
    "iso:country":"US",
    "sg:address":"50 Summer St",
    "sg:city":"Leominster",
    "sg:classifiers":[
        {
            "category":"Building & Trades",
            "subcategory":"Construction",
            "type":"Services"
        }
    ],
    "sg:phone":"+1   ",
    "sg:postcode":"01453",
    "sg:province":"MA",
    "sg:tags":[
        "contractor"
    ],
    "wof:name":"Bernard J Collette",
    "wof:placetype":"venue"
},
  "geometry": {"coordinates":[-71.756615,42.529019],"type":"Point"}
}