{
  "type": "Feature",
  "properties": {
    "iso:country":"US",
    "sg:address":"49 Seekonk St",
    "sg:city":"Norfolk",
    "sg:classifiers":[
        {
            "category":"Building & Trades",
            "subcategory":"Construction",
            "type":"Services"
        }
    ],
    "sg:phone":"+1 508 528 4307",
    "sg:postcode":"02056",
    "sg:province":"MA",
    "sg:tags":[
        "bathroom",
        "remodeling"
    ],
    "wof:name":"H & D Tile",
    "wof:placetype":"venue"
},
  "geometry": {"coordinates":[-71.311093,42.123109],"type":"Point"}
}