{
  "type": "Feature",
  "properties": {
    "addr:full": "49 Seekonk St Norfolk MA 02056",
    "addr:housenumber": "49",
    "addr:postcode": "02056",
    "addr:street": "Seekonk St",
    "iso:country": "US",
    "sg:address": "49 Seekonk St",
    "sg:city": "Norfolk",
    "sg:classifiers": [
      {
        "category": "Building \u0026 Trades",
        "subcategory": "Construction",
        "type": "Services"
      }
    ],
    "sg:phone": "+1 508 528 4307",
    "sg:postcode": "02056",
    "sg:province": "MA",
    "sg:tags": [
      "bathroom",
      "remodeling"
    ],
    "wof:name": "H \u0026 D Tile",
    "wof:placetype": "venue"
  },
  "geometry": {"coordinates":[-71.311093,42.123109],"type":"Point"}
}
