{
  "type": "Feature",
  "properties": {
    "addr:full":"180 Middlesex Rd Chestnut Hill MA 02467",
    "addr:housenumber":"180",
    "addr:postcode":"02467",
    "addr:street":"Middlesex Rd",
    "iso:country":"US",
    "sg:address":"180 Middlesex Rd",
    "sg:city":"Chestnut Hill",
    "sg:classifiers":[
        {
            "category":"Professional",
            "subcategory":"Computer Services",
            "type":"Services"
        }
    ],
    "sg:phone":"+1   ",
    "sg:postcode":"02467",
    "sg:province":"MA",
    "sg:tags":[
        "prepackaged",
        "software"
    ],
    "wof:name":"Computer Software Program",
    "wof:placetype":"venue"
},
  "geometry": {"coordinates":[-71.158259,42.329167],"type":"Point"}
}