{
  "type": "Feature",
  "properties": {
    "addr:full":"257 Washington St Westwood MA 02090",
    "addr:housenumber":"257",
    "addr:postcode":"02090",
    "addr:street":"Washington St",
    "iso:country":"US",
    "sg:address":"257 Washington St",
    "sg:city":"Westwood",
    "sg:classifiers":[
        {
            "category":"Shopping",
            "subcategory":"Mobile Phones",
            "type":"Retail Goods"
        }
    ],
    "sg:phone":"+1 781 326 1780",
    "sg:postcode":"02090",
    "sg:province":"MA",
    "wof:name":"Powarewave Technologies Inc - CLOSED",
    "wof:placetype":"venue"
},
  "geometry": {"coordinates":[-71.18789700000001,42.220699],"type":"Point"}
}