{
  "type": "Feature",
  "properties": {
    "iso:country":"US",
    "sg:address":"74 Beech St",
    "sg:city":"New Bedford",
    "sg:classifiers":[
        {
            "category":"Organizations",
            "subcategory":"Professional Association",
            "type":"Services"
        }
    ],
    "sg:phone":"+1 508 984 4850",
    "sg:postcode":"02740",
    "sg:province":"MA",
    "sg:website":"www.nbysa.org",
    "wof:name":"New Bedford Youth Soccer Assn",
    "wof:placetype":"venue"
},
  "geometry": {"coordinates":[-70.947855,41.639174],"type":"Point"}
}