{
  "type": "Feature",
  "properties": {
    "addr:full":"122 Chestnut St North Attleboro MA 02760",
    "addr:housenumber":"122",
    "addr:postcode":"02760",
    "addr:street":"Chestnut St",
    "iso:country":"US",
    "sg:address":"122 Chestnut St",
    "sg:city":"North Attleboro",
    "sg:classifiers":[
        {
            "category":"Travel",
            "subcategory":"Travel Agent",
            "type":"Entertainment"
        }
    ],
    "sg:phone":"+1 508 695 0271",
    "sg:postcode":"02760",
    "sg:province":"MA",
    "sg:tags":[
        "agency",
        "bureau"
    ],
    "wof:name":"ABC Travel Of Attleboro Inc",
    "wof:placetype":"venue"
},
  "geometry": {"coordinates":[-71.328625,41.977358],"type":"Point"}
}