{
  "type": "Feature",
  "properties": {
    "addr:full": "45 School St Brockton MA 02301",
    "addr:housenumber": "45",
    "addr:postcode": "02301",
    "addr:street": "School St",
    "iso:country": "US",
    "sg:address": "45 School St",
    "sg:city": "Brockton",
    "sg:classifiers": [
      {
        "category": "Government",
        "subcategory": "Office",
        "type": "Public Place"
      }
    ],
    "sg:phone": "+1 508 580 7153",
    "sg:postcode": "02301",
    "sg:province": "MA",
    "sg:tags": [
      "city",
      "taxation"
    ],
    "sg:website": "www.brockton.ma.us",
    "wof:name": "Brockton Auditors Dept",
    "wof:placetype": "venue"
  },
  "geometry": {"coordinates":[-71.018788,42.083],"type":"Point"}
}
