{
  "type": "Feature",
  "properties": {
    "iso:country":"US",
    "sg:address":"34 Agawam Village",
    "sg:city":"Ipswich",
    "sg:classifiers":[
        {
            "category":"Social Services",
            "subcategory":"Adult Care",
            "type":"Services"
        }
    ],
    "sg:phone":"+1 978 356 3150",
    "sg:postcode":"01938",
    "sg:province":"MA",
    "sg:tags":[
        "home",
        "residential"
    ],
    "wof:name":"Agawam Village",
    "wof:placetype":"venue"
},
  "geometry": {"coordinates":[-70.83713,42.670815],"type":"Point"}
}