{
  "type": "Feature",
  "properties": {
    "addr:full": "1 S Market St Boston MA 02109",
    "addr:housenumber": "1",
    "addr:postcode": "02109",
    "addr:street": "S Market St",
    "iso:country": "US",
    "sg:address": "1 S Market St",
    "sg:city": "Boston",
    "sg:classifiers": [
      {
        "category": "Professional",
        "subcategory": "Advertising",
        "type": "Services"
      }
    ],
    "sg:phone": "+1 617 973 5160",
    "sg:postcode": "02109",
    "sg:province": "MA",
    "sg:tags": [
      "counselor"
    ],
    "wof:name": "Icon Digital",
    "wof:placetype": "venue"
  },
  "geometry": {"coordinates":[-71.053998,42.360126],"type":"Point"}
}
