{
  "type": "Feature",
  "properties": {
    "iso:country":"US",
    "sg:address":"27 Copeland Dr",
    "sg:city":"Ayer",
    "sg:classifiers":[
        {
            "category":"Manufacturing",
            "subcategory":"Paper Products",
            "type":"Manufacturing & Wholesale Goods"
        }
    ],
    "sg:phone":"+1 978 772 7393",
    "sg:postcode":"01432",
    "sg:province":"MA",
    "sg:tags":[
        "packaging",
        "container"
    ],
    "wof:name":"Plastipak Packaging Inc",
    "wof:placetype":"venue"
},
  "geometry": {"coordinates":[-71.566896,42.553196],"type":"Point"}
}