{
  "type": "Feature",
  "properties": {
    "addr:full": "60 Thoreau St Ste 182 Concord MA 01742",
    "addr:housenumber": "60",
    "addr:postcode": "01742",
    "addr:street": "Thoreau St Ste 182",
    "iso:country": "US",
    "sg:address": "60 Thoreau St Ste 182",
    "sg:city": "Concord",
    "sg:classifiers": [
      {
        "category": "Building \u0026 Trades",
        "subcategory": "Construction",
        "type": "Services"
      }
    ],
    "sg:phone": "+1 866 885 2334",
    "sg:postcode": "01742",
    "sg:province": "MA",
    "sg:tags": [
      "painter"
    ],
    "sg:website": "www.protectpainters.com",
    "wof:name": "ProTect Painters",
    "wof:placetype": "venue"
  },
  "geometry": {"coordinates":[-71.358054,42.457217],"type":"Point"}
}
