{
  "type": "Feature",
  "properties": {
    "iso:country":"US",
    "sg:address":"4 Cherry St",
    "sg:city":"Haverhill",
    "sg:classifiers":[
        {
            "category":"Social Services",
            "type":"Services"
        }
    ],
    "sg:phone":"+1 978 556 0143",
    "sg:postcode":"01830",
    "sg:province":"MA",
    "sg:tags":[
        "organization",
        "welfare"
    ],
    "wof:name":"Capstone House Ministries",
    "wof:placetype":"venue"
},
  "geometry": {"coordinates":[-71.075906,42.77924],"type":"Point"}
}