{
  "type": "Feature",
  "properties": {
    "addr:full":"44 Hunt St Ste 2 Watertown MA 02472",
    "addr:housenumber":"44",
    "addr:postcode":"02472",
    "addr:street":"Hunt St Ste 2",
    "iso:country":"US",
    "sg:address":"44 Hunt St Ste 2",
    "sg:city":"Watertown",
    "sg:classifiers":[
        {
            "category":"Manufacturing",
            "subcategory":"Electronics",
            "type":"Manufacturing & Wholesale Goods"
        }
    ],
    "sg:phone":"+1 617 926 1167",
    "sg:postcode":"02472",
    "sg:province":"MA",
    "sg:tags":[
        "equipment",
        "electronic",
        "supplies-wholesale",
        "manufacturer"
    ],
    "sg:website":"http://www.rmdinc.com",
    "wof:name":"Radiation Monitoring Devices",
    "wof:placetype":"venue"
},
  "geometry": {"coordinates":[-71.183639,42.360685],"type":"Point"}
}