{
  "type": "Feature",
  "properties": {
    "addr:full":"860 N Main St West Bridgewater MA 02379",
    "addr:housenumber":"860",
    "addr:postcode":"02379",
    "addr:street":"N Main St",
    "iso:country":"US",
    "sg:address":"860 N Main St",
    "sg:city":"West Bridgewater",
    "sg:classifiers":[
        {
            "category":"Shopping",
            "subcategory":"Department Store",
            "type":"Retail Goods"
        }
    ],
    "sg:phone":"+1 508 584 3275",
    "sg:postcode":"02379",
    "sg:province":"MA",
    "sg:tags":[
        "shop"
    ],
    "wof:name":"Big Lots",
    "wof:placetype":"venue"
},
  "geometry": {"coordinates":[-71.00953199999999,42.043053],"type":"Point"}
}