{
  "type": "Feature",
  "properties": {
    "addr:full":"131 Plumtree Rd Sunderland MA 01375",
    "addr:housenumber":"131",
    "addr:postcode":"01375",
    "addr:street":"Plumtree Rd",
    "iso:country":"US",
    "sg:address":"131 Plumtree Rd",
    "sg:city":"Sunderland",
    "sg:classifiers":[
        {
            "category":"Professional",
            "subcategory":"Lawyer & Legal Services",
            "type":"Services"
        }
    ],
    "sg:phone":"+1 413 548 8100",
    "sg:postcode":"01375",
    "sg:province":"MA",
    "sg:tags":[
        "attorney"
    ],
    "wof:name":"Michael A Zewski Atty",
    "wof:placetype":"venue"
},
  "geometry": {"coordinates":[-72.556071,42.431584],"type":"Point"}
}