{
  "type": "Feature",
  "properties": {
    "iso:country":"US",
    "sg:address":"47 Elm St",
    "sg:city":"Westfield",
    "sg:classifiers":[
        {
            "category":"Food & Beverages",
            "subcategory":"Groceries & Convenience Stores",
            "type":"Retail Goods"
        }
    ],
    "sg:phone":"+1 413 562 7602",
    "sg:postcode":"01085",
    "sg:province":"MA",
    "wof:name":"Victory Store",
    "wof:placetype":"venue"
},
  "geometry": {"coordinates":[-72.748497,42.122442],"type":"Point"}
}