{
  "type": "Feature",
  "properties": {
    "addr:full": "47 Elm St Westfield MA 01085",
    "addr:housenumber": "47",
    "addr:postcode": "01085",
    "addr:street": "Elm St",
    "iso:country": "US",
    "sg:address": "47 Elm St",
    "sg:city": "Westfield",
    "sg:classifiers": [
      {
        "category": "Food \u0026 Beverages",
        "subcategory": "Groceries \u0026 Convenience Stores",
        "type": "Retail Goods"
      }
    ],
    "sg:phone": "+1 413 562 7602",
    "sg:postcode": "01085",
    "sg:province": "MA",
    "wof:name": "Victory Store",
    "wof:placetype": "venue"
  },
  "geometry": {"coordinates":[-72.748497,42.122442],"type":"Point"}
}
