{
  "type": "Feature",
  "properties": {
    "iso:country":"US",
    "sg:address":"229 Newbury St",
    "sg:city":"Boston",
    "sg:classifiers":[
        {
            "category":"Shopping",
            "subcategory":"Clothing, Apparel, & Fashions",
            "type":"Retail Goods"
        }
    ],
    "sg:phone":"+1 617 375 7848",
    "sg:postcode":"02116",
    "sg:province":"MA",
    "sg:tags":[
        "swimwear",
        "accessory"
    ],
    "wof:name":"Canyon Beachwear",
    "wof:placetype":"venue"
},
  "geometry": {"coordinates":[-71.080606,42.35026],"type":"Point"}
}