{
  "type": "Feature",
  "properties": {
    "addr:full":"116 Salem St Boston MA 02113",
    "addr:housenumber":"116",
    "addr:postcode":"02113",
    "addr:street":"Salem St",
    "iso:country":"US",
    "sg:address":"116 Salem St",
    "sg:city":"Boston",
    "sg:classifiers":[
        {
            "category":"Restaurant",
            "type":"Food & Drink"
        },
        {
            "category":"Organizations",
            "subcategory":"Community Association",
            "type":"Services"
        }
    ],
    "sg:phone":"+1 617 720 0339",
    "sg:postcode":"02113",
    "sg:province":"MA",
    "sg:tags":[
        "club",
        "italian"
    ],
    "sg:website":"www.locontes.com/",
    "wof:name":"Loconte's Italian Cuisine",
    "wof:placetype":"venue"
},
  "geometry": {"coordinates":[-71.05529799999999,42.3647],"type":"Point"}
}