{
  "type": "Feature",
  "properties": {
    "addr:full":"248 Glendale St Uxbridge MA 01569",
    "addr:housenumber":"248",
    "addr:postcode":"01569",
    "addr:street":"Glendale St",
    "iso:country":"US",
    "sg:address":"248 Glendale St",
    "sg:city":"Uxbridge",
    "sg:classifiers":[
        {
            "category":"Shopping",
            "subcategory":"Used Merchandise",
            "type":"Retail Goods"
        }
    ],
    "sg:phone":"+1 508 278 3763",
    "sg:postcode":"01569",
    "sg:province":"MA",
    "sg:tags":[
        "clothing"
    ],
    "wof:name":"Kids Kupboard",
    "wof:placetype":"venue"
},
  "geometry": {"coordinates":[-71.646366,42.014746],"type":"Point"}
}