{
  "type": "Feature",
  "properties": {
    "addr:full": "19 Bartlett St Everett MA 02149",
    "addr:housenumber": "19",
    "addr:postcode": "02149",
    "addr:street": "Bartlett St",
    "iso:country": "US",
    "ovtr:label": "Ramos Iron Works, 19 Bartlett St Everett MA US",
    "ovtr:similarity": 2.735766887664795,
    "sg:address": "19 Bartlett St",
    "sg:city": "Everett",
    "sg:classifiers": [
      {
        "category": "Retail",
        "subcategory": "Repair Shop",
        "type": "Services"
      }
    ],
    "sg:phone": "+1 617 387 7858",
    "sg:postcode": "02149",
    "sg:province": "MA",
    "sg:tags": [
      "ironwork"
    ],
    "wof:name": "Ramos Iron Works",
    "wof:placetype": "venue"
  },
  "geometry": {"coordinates":[-71.05982,42.399808],"type":"Point"}
}
