{
  "type": "Feature",
  "properties": {
    "addr:full":"10 Main St Cotuit MA 02635",
    "addr:housenumber":"10",
    "addr:postcode":"02635",
    "addr:street":"Main St",
    "iso:country":"US",
    "sg:address":"10 Main St",
    "sg:city":"Cotuit",
    "sg:classifiers":[
        {
            "category":"Health Services",
            "subcategory":"Doctor",
            "type":"Services"
        }
    ],
    "sg:phone":"+1 508 428 3677",
    "sg:postcode":"02635",
    "sg:province":"MA",
    "sg:tags":[
        "dentist"
    ],
    "wof:name":"Aesthetic Dental Care",
    "wof:placetype":"venue"
},
  "geometry": {"coordinates":[-70.450557,41.637689],"type":"Point"}
}