{
  "type": "Feature",
  "properties": {
    "iso:country":"US",
    "sg:address":"47 Whitcomb St",
    "sg:city":"Webster",
    "sg:classifiers":[
        {
            "category":"Education",
            "subcategory":"School",
            "type":"Public Place"
        }
    ],
    "sg:phone":"+1 508 943 0378",
    "sg:postcode":"01570",
    "sg:province":"MA",
    "sg:website":"www.saintjosephschool.net",
    "wof:name":"St Joseph's School",
    "wof:placetype":"venue"
},
  "geometry": {"coordinates":[-71.874264,42.051348],"type":"Point"}
}