{
  "type": "Feature",
  "properties": {
    "iso:country":"US",
    "sg:address":"45 Garden Rd",
    "sg:city":"Lowell",
    "sg:classifiers":[
        {
            "category":"Banks & Credit Unions",
            "subcategory":"Bank",
            "type":"Services"
        }
    ],
    "sg:phone":"+1 978 459 7315",
    "sg:postcode":"01852",
    "sg:province":"MA",
    "wof:name":"Shamsdl Inc",
    "wof:placetype":"venue"
},
  "geometry": {"coordinates":[-71.27919,42.643715],"type":"Point"}
}