{
  "type": "Feature",
  "properties": {
    "addr:full": "45 Garden Rd Lowell MA 01852",
    "addr:housenumber": "45",
    "addr:postcode": "01852",
    "addr:street": "Garden Rd",
    "iso:country": "US",
    "sg:address": "45 Garden Rd",
    "sg:city": "Lowell",
    "sg:classifiers": [
      {
        "category": "Banks \u0026 Credit Unions",
        "subcategory": "Bank",
        "type": "Services"
      }
    ],
    "sg:phone": "+1 978 459 7315",
    "sg:postcode": "01852",
    "sg:province": "MA",
    "wof:name": "Shamsdl Inc",
    "wof:placetype": "venue"
  },
  "geometry": {"coordinates":[-71.27919,42.643715],"type":"Point"}
}
