{
  "type": "Feature",
  "properties": {
    "addr:full":"176 E Main St Westborough MA 01581",
    "addr:housenumber":"176",
    "addr:postcode":"01581",
    "addr:street":"E Main St",
    "iso:country":"US",
    "sg:address":"176 E Main St",
    "sg:city":"Westborough",
    "sg:classifiers":[
        {
            "category":"Health Services",
            "subcategory":"Doctor",
            "type":"Services"
        }
    ],
    "sg:phone":"+1 508 366 7100",
    "sg:postcode":"01581",
    "sg:province":"MA",
    "sg:tags":[
        "physician",
        "surgeon"
    ],
    "wof:name":"Westborough Family Medicine",
    "wof:placetype":"venue"
},
  "geometry": {"coordinates":[-71.59568299999999,42.286885],"type":"Point"}
}