{
  "type": "Feature",
  "properties": {
    "addr:full": "39 Pleasant St Hopkinton MA 01748",
    "addr:housenumber": "39",
    "addr:postcode": "01748",
    "addr:street": "Pleasant St",
    "iso:country": "US",
    "sg:address": "39 Pleasant St",
    "sg:city": "Hopkinton",
    "sg:classifiers": [
      {
        "category": "Building \u0026 Trades",
        "subcategory": "Construction",
        "type": "Services"
      }
    ],
    "sg:phone": "+1 508 435 5473",
    "sg:postcode": "01748",
    "sg:province": "MA",
    "sg:tags": [
      "wallcoverings-installation",
      "wallpaper",
      "painting",
      "contractor"
    ],
    "wof:name": "Kinney Painting Inc",
    "wof:placetype": "venue"
  },
  "geometry": {"coordinates":[-71.524019,42.224065],"type":"Point"}
}
