{
  "type": "Feature",
  "properties": {
    "addr:full": "1255 Oblong Rd Williamstown MA 01267",
    "addr:housenumber": "1255",
    "addr:postcode": "01267",
    "addr:street": "Oblong Rd",
    "iso:country": "US",
    "ovtr:label": "Cricket Creek Farm, 1255 Oblong Rd Williamstown MA US",
    "ovtr:similarity": 2.192028045654297,
    "sg:address": "1255 Oblong Rd",
    "sg:city": "Williamstown",
    "sg:classifiers": [
      {
        "category": "Farming",
        "subcategory": "Farm",
        "type": "Manufacturing \u0026 Wholesale Goods"
      }
    ],
    "sg:phone": "+1 413 458 5888",
    "sg:postcode": "01267",
    "sg:province": "MA",
    "wof:name": "Cricket Creek Farm",
    "wof:placetype": "venue"
  },
  "geometry": {"coordinates":[-73.266322,42.662023],"type":"Point"}
}
