{
  "type": "Feature",
  "properties": {
    "addr:full":"1255 Oblong Rd Williamstown MA 01267",
    "addr:housenumber":"1255",
    "addr:postcode":"01267",
    "addr:street":"Oblong Rd",
    "iso:country":"US",
    "sg:address":"1255 Oblong Rd",
    "sg:city":"Williamstown",
    "sg:classifiers":[
        {
            "category":"Farming",
            "subcategory":"Farm",
            "type":"Manufacturing & Wholesale Goods"
        }
    ],
    "sg:phone":"+1 413 458 5888",
    "sg:postcode":"01267",
    "sg:province":"MA",
    "wof:name":"Cricket Creek Farm",
    "wof:placetype":"venue"
},
  "geometry": {"coordinates":[-73.266322,42.662023],"type":"Point"}
}