{
  "type": "Feature",
  "properties": {
    "addr:full": "41 Marion St Brookline MA 02446",
    "addr:housenumber": "41",
    "addr:postcode": "02446",
    "addr:street": "Marion St",
    "iso:country": "US",
    "sg:address": "41 Marion St",
    "sg:city": "Brookline",
    "sg:classifiers": [
      {
        "category": "Wholesale",
        "subcategory": "Apparel",
        "type": "Manufacturing \u0026 Wholesale Goods"
      }
    ],
    "sg:phone": "+1 617 566 2233",
    "sg:postcode": "02446",
    "sg:province": "MA",
    "sg:tags": [
      "maternity"
    ],
    "wof:name": "9 Months",
    "wof:placetype": "venue"
  },
  "geometry": {"coordinates":[-71.122222,42.339968],"type":"Point"}
}
