{
  "type": "Feature",
  "properties": {
    "iso:country":"US",
    "sg:address":"41 Marion St",
    "sg:city":"Brookline",
    "sg:classifiers":[
        {
            "category":"Wholesale",
            "subcategory":"Apparel",
            "type":"Manufacturing & Wholesale Goods"
        }
    ],
    "sg:phone":"+1 617 566 2233",
    "sg:postcode":"02446",
    "sg:province":"MA",
    "sg:tags":[
        "maternity"
    ],
    "wof:name":"9 Months",
    "wof:placetype":"venue"
},
  "geometry": {"coordinates":[-71.12222199999999,42.339968],"type":"Point"}
}