{
  "type": "Feature",
  "properties": {
    "addr:full": "82 Hillside Street Roxbury Crossing MA 02120",
    "addr:housenumber": "82",
    "addr:postcode": "02120",
    "addr:street": "Hillside Street",
    "iso:country": "US",
    "sg:address": "82 Hillside Street",
    "sg:city": "Roxbury Crossing",
    "sg:classifiers": [
      {
        "category": "Food \u0026 Beverages",
        "subcategory": "Groceries \u0026 Convenience Stores",
        "type": "Retail Goods"
      }
    ],
    "sg:phone": "+1 617 427 6067",
    "sg:postcode": "02120",
    "sg:province": "MA",
    "wof:name": "Hillside Market",
    "wof:placetype": "venue"
  },
  "geometry": {"coordinates":[-71.103001,42.330512],"type":"Point"}
}
