{
  "type": "Feature",
  "properties": {
    "iso:country":"US",
    "sg:address":"82 Hillside Street",
    "sg:city":"Roxbury Crossing",
    "sg:classifiers":[
        {
            "category":"Food & Beverages",
            "subcategory":"Groceries & Convenience Stores",
            "type":"Retail Goods"
        }
    ],
    "sg:phone":"+1 617 427 6067",
    "sg:postcode":"02120",
    "sg:province":"MA",
    "wof:name":"Hillside Market",
    "wof:placetype":"venue"
},
  "geometry": {"coordinates":[-71.10300100000001,42.330512],"type":"Point"}
}