{
  "type": "Feature",
  "properties": {
    "addr:full":"8 Stearns St Framingham MA 01701",
    "addr:housenumber":"8",
    "addr:postcode":"01701",
    "addr:street":"Stearns St",
    "iso:country":"US",
    "sg:address":"8 Stearns St",
    "sg:city":"Framingham",
    "sg:classifiers":[
        {
            "category":"Building & Trades",
            "subcategory":"Construction",
            "type":"Services"
        }
    ],
    "sg:phone":"+1 508 877 5650",
    "sg:postcode":"01701",
    "sg:province":"MA",
    "sg:tags":[
        "general",
        "contractor"
    ],
    "wof:name":"CRM Construction",
    "wof:placetype":"venue"
},
  "geometry": {"coordinates":[-71.39534399999999,42.325165],"type":"Point"}
}