{
  "type": "Feature",
  "properties": {
    "iso:country":"US",
    "sg:address":"66 Washburn St",
    "sg:city":"Northborough",
    "sg:classifiers":[
        {
            "category":"Building & Trades",
            "subcategory":"Construction",
            "type":"Services"
        }
    ],
    "sg:phone":"+1 508 393 1905",
    "sg:postcode":"01532",
    "sg:province":"MA",
    "sg:tags":[
        "stone",
        "setting",
        "contractor"
    ],
    "wof:name":"Granchelli Landscape Inc",
    "wof:placetype":"venue"
},
  "geometry": {"coordinates":[-71.647617,42.333217],"type":"Point"}
}