{
  "type": "Feature",
  "properties": {
    "addr:full":"56 South St Upton MA 01568",
    "addr:housenumber":"56",
    "addr:postcode":"01568",
    "addr:street":"South St",
    "iso:country":"US",
    "sg:address":"56 South St",
    "sg:city":"Upton",
    "sg:classifiers":[
        {
            "category":"Shopping",
            "subcategory":"Gifts & Souvenirs",
            "type":"Retail Goods"
        }
    ],
    "sg:phone":"+1   ",
    "sg:postcode":"01568",
    "sg:province":"MA",
    "wof:name":"Blackstone Valley Ceramics",
    "wof:placetype":"venue"
},
  "geometry": {"coordinates":[-71.60383899999999,42.154407],"type":"Point"}
}