{
  "type": "Feature",
  "properties": {
    "iso:country":"US",
    "sg:address":"165 Sharon St",
    "sg:city":"Medford",
    "sg:classifiers":[
        {
            "category":"Building & Trades",
            "subcategory":"Locksmith",
            "type":"Services"
        }
    ],
    "sg:phone":"+1 781 219 0418",
    "sg:postcode":"02155",
    "sg:province":"MA",
    "sg:tags":[
        "key"
    ],
    "wof:name":"Anywhere A Locksmith Service",
    "wof:placetype":"venue"
},
  "geometry": {"coordinates":[-71.132972,42.416513],"type":"Point"}
}