{
  "type": "Feature",
  "properties": {
    "iso:country":"US",
    "sg:address":"101 Coolidge St",
    "sg:city":"Hudson",
    "sg:classifiers":[
        {
            "category":"Health Services",
            "subcategory":"Doctor",
            "type":"Services"
        }
    ],
    "sg:phone":"+1 978 562 8633",
    "sg:postcode":"01749",
    "sg:province":"MA",
    "sg:tags":[
        "physician",
        "surgeon"
    ],
    "wof:name":"New England Rfrctv/Glaucoma",
    "wof:placetype":"venue"
},
  "geometry": {"coordinates":[-71.598305,42.397456],"type":"Point"}
}