{
  "type": "Feature",
  "properties": {
    "addr:full":"1090 Chicopee St Chicopee MA 01013",
    "addr:housenumber":"1090",
    "addr:postcode":"01013",
    "addr:street":"Chicopee St",
    "iso:country":"US",
    "sg:address":"1090 Chicopee St",
    "sg:city":"Chicopee",
    "sg:classifiers":[
        {
            "category":"Retail",
            "subcategory":"Auto Repair",
            "type":"Services"
        }
    ],
    "sg:phone":"+1   ",
    "sg:postcode":"01013",
    "sg:province":"MA",
    "sg:tags":[
        "transmission"
    ],
    "wof:name":"A B M Transmission Repair",
    "wof:placetype":"venue"
},
  "geometry": {"coordinates":[-72.600084,42.193312],"type":"Point"}
}