{
  "type": "Feature",
  "properties": {
    "iso:country":"US",
    "sg:address":"12 Housatonic St",
    "sg:city":"Lenox",
    "sg:classifiers":[
        {
            "category":"Bars & Pubs",
            "type":"Food & Drink"
        }
    ],
    "sg:phone":"+1 413 637 0884",
    "sg:postcode":"01240",
    "sg:province":"MA",
    "wof:name":"Old Heritage Tavern",
    "wof:placetype":"venue"
},
  "geometry": {"coordinates":[-73.28422999999999,42.357866],"type":"Point"}
}