{
  "type": "Feature",
  "properties": {
    "addr:full": "12 Housatonic St Lenox MA 01240",
    "addr:housenumber": "12",
    "addr:postcode": "01240",
    "addr:street": "Housatonic St",
    "iso:country": "US",
    "ovtr:label": "Olde Heritage Tavern, 12 Housatonic St Lenox MA US",
    "ovtr:similarity": 3.2157089710235596,
    "sg:address": "12 Housatonic St",
    "sg:city": "Lenox",
    "sg:classifiers": [
      {
        "category": "Bars \u0026 Pubs",
        "type": "Food \u0026 Drink"
      }
    ],
    "sg:phone": "+1 413 637 0884",
    "sg:postcode": "01240",
    "sg:province": "MA",
    "wof:name": "Old Heritage Tavern",
    "wof:placetype": "venue"
  },
  "geometry": {"coordinates":[-73.28423,42.357866],"type":"Point"}
}
