{
  "type": "Feature",
  "properties": {
    "iso:country":"US",
    "sg:address":"29 Normandy Ave",
    "sg:city":"Cambridge",
    "sg:classifiers":[
        {
            "category":"Health Services",
            "subcategory":"Doctor",
            "type":"Services"
        }
    ],
    "sg:phone":"+1 617 491 5555",
    "sg:postcode":"02138",
    "sg:province":"MA",
    "wof:name":"Cahill Thomas",
    "wof:placetype":"venue"
},
  "geometry": {"coordinates":[-71.156717,42.393982],"type":"Point"}
}