{
  "type": "Feature",
  "properties": {
    "addr:full": "130 Gardiner Rd Quincy MA 02169",
    "addr:housenumber": "130",
    "addr:postcode": "02169",
    "addr:street": "Gardiner Rd",
    "iso:country": "US",
    "sg:address": "130 Gardiner Rd",
    "sg:city": "Quincy",
    "sg:classifiers": [
      {
        "category": "Building \u0026 Trades",
        "subcategory": "Construction",
        "type": "Services"
      }
    ],
    "sg:phone": "+1 617 479 9400",
    "sg:postcode": "02169",
    "sg:province": "MA",
    "sg:tags": [
      "paving",
      "contractor"
    ],
    "wof:name": "Donegal Paving",
    "wof:placetype": "venue"
  },
  "geometry": {"coordinates":[-71.041463,42.250661],"type":"Point"}
}
