{
  "type": "Feature",
  "properties": {
    "iso:country":"US",
    "sg:address":"130 Gardiner Rd",
    "sg:city":"Quincy",
    "sg:classifiers":[
        {
            "category":"Building & Trades",
            "subcategory":"Construction",
            "type":"Services"
        }
    ],
    "sg:phone":"+1 617 479 9400",
    "sg:postcode":"02169",
    "sg:province":"MA",
    "sg:tags":[
        "paving",
        "contractor"
    ],
    "wof:name":"Donegal Paving",
    "wof:placetype":"venue"
},
  "geometry": {"coordinates":[-71.04146299999999,42.250661],"type":"Point"}
}