{
  "type": "Feature",
  "properties": {
    "addr:full": "6 Debra Ln Bellingham MA 02019",
    "addr:housenumber": "6",
    "addr:postcode": "02019",
    "addr:street": "Debra Ln",
    "iso:country": "US",
    "sg:address": "6 Debra Ln",
    "sg:city": "Bellingham",
    "sg:classifiers": [
      {
        "category": "Building \u0026 Trades",
        "subcategory": "Construction",
        "type": "Services"
      }
    ],
    "sg:phone": "+1 508 966 3267",
    "sg:postcode": "02019",
    "sg:province": "MA",
    "sg:tags": [
      "wallcoverings-installation",
      "wallpaper",
      "painting",
      "contractor"
    ],
    "wof:name": "Happy Hayes Painting",
    "wof:placetype": "venue"
  },
  "geometry": {"coordinates":[-71.468476,42.077593],"type":"Point"}
}
