{
  "type": "Feature",
  "properties": {
    "iso:country":"US",
    "sg:address":"25 Common St",
    "sg:city":"Southborough",
    "sg:classifiers":[
        {
            "category":"Organizations",
            "subcategory":"Membership Organization",
            "type":"Services"
        }
    ],
    "sg:phone":"+1 508 229 8055",
    "sg:postcode":"01772",
    "sg:province":"MA",
    "sg:tags":[
        "historical"
    ],
    "wof:name":"Southborough Historical Scty",
    "wof:placetype":"venue"
},
  "geometry": {"coordinates":[-71.531572,42.305993],"type":"Point"}
}