{
  "type": "Feature",
  "properties": {
    "addr:full": "1395 N Main St Randolph MA 02368",
    "addr:housenumber": "1395",
    "addr:postcode": "02368",
    "addr:street": "N Main St",
    "iso:country": "US",
    "sg:address": "1395 N Main St",
    "sg:city": "Randolph",
    "sg:classifiers": [
      {
        "category": "Health Services",
        "subcategory": "Doctor",
        "type": "Services"
      }
    ],
    "sg:phone": "+1 781 961 7887",
    "sg:postcode": "02368",
    "sg:province": "MA",
    "sg:tags": [
      "clinic",
      "pizza"
    ],
    "sg:website": "www.hyperbaricoxygenchamber.com",
    "wof:name": "Hotc",
    "wof:placetype": "venue"
  },
  "geometry": {"coordinates":[-71.062897,42.201599],"type":"Point"}
}
