{
  "type": "Feature",
  "properties": {
    "iso:country":"US",
    "sg:address":"1395 N Main St",
    "sg:city":"Randolph",
    "sg:classifiers":[
        {
            "category":"Health Services",
            "subcategory":"Doctor",
            "type":"Services"
        }
    ],
    "sg:phone":"+1 781 961 7887",
    "sg:postcode":"02368",
    "sg:province":"MA",
    "sg:tags":[
        "clinic",
        "pizza"
    ],
    "sg:website":"www.hyperbaricoxygenchamber.com",
    "wof:name":"Hotc",
    "wof:placetype":"venue"
},
  "geometry": {"coordinates":[-71.06289700000001,42.201599],"type":"Point"}
}