{
  "type": "Feature",
  "properties": {
    "iso:country":"US",
    "sg:address":"1 Tremont St",
    "sg:city":"Provincetown",
    "sg:classifiers":[
        {
            "category":"Food & Beverages",
            "subcategory":"Liquor & Beverages",
            "type":"Retail Goods"
        }
    ],
    "sg:phone":"+1 508 487 0140",
    "sg:postcode":"02657",
    "sg:province":"MA",
    "wof:name":"Perry's Liquors",
    "wof:placetype":"venue"
},
  "geometry": {"coordinates":[-70.192517,42.045103],"type":"Point"}
}