{
  "type": "Feature",
  "properties": {
    "iso:country":"US",
    "sg:address":"99 Fulton St",
    "sg:city":"Boston",
    "sg:classifiers":[
        {
            "category":"Manufacturing",
            "subcategory":"Pottery",
            "type":"Manufacturing & Wholesale Goods"
        }
    ],
    "sg:phone":"+1   ",
    "sg:postcode":"02109",
    "sg:province":"MA",
    "sg:tags":[
        "product",
        "mfg"
    ],
    "wof:name":"Rooter Man",
    "wof:placetype":"venue"
},
  "geometry": {"coordinates":[-71.053817,42.361694],"type":"Point"}
}