{
  "type": "Feature",
  "properties": {
    "addr:full": "99 Fulton St Boston MA 02109",
    "addr:housenumber": "99",
    "addr:postcode": "02109",
    "addr:street": "Fulton St",
    "iso:country": "US",
    "sg:address": "99 Fulton St",
    "sg:city": "Boston",
    "sg:classifiers": [
      {
        "category": "Manufacturing",
        "subcategory": "Pottery",
        "type": "Manufacturing \u0026 Wholesale Goods"
      }
    ],
    "sg:phone": "+1   ",
    "sg:postcode": "02109",
    "sg:province": "MA",
    "sg:tags": [
      "product",
      "mfg"
    ],
    "wof:name": "Rooter Man",
    "wof:placetype": "venue"
  },
  "geometry": {"coordinates":[-71.053817,42.361694],"type":"Point"}
}
