{
  "type": "Feature",
  "properties": {
    "addr:full": "6 W Brookfield Rd West Brookfield MA 01506",
    "addr:housenumber": "6",
    "addr:postcode": "01506",
    "addr:street": "W Brookfield Rd",
    "iso:country": "US",
    "sg:address": "6 W Brookfield Rd",
    "sg:city": "West Brookfield",
    "sg:classifiers": [
      {
        "category": "Professional",
        "subcategory": "Management \u0026 Consulting",
        "type": "Services"
      }
    ],
    "sg:phone": "+1   ",
    "sg:postcode": "01506",
    "sg:province": "MA",
    "sg:tags": [
      "business"
    ],
    "wof:name": "Hooven Engineering",
    "wof:placetype": "venue"
  },
  "geometry": {"coordinates":[-72.116969,42.220269],"type":"Point"}
}
