{
  "type": "Feature",
  "properties": {
    "addr:full":"32 Highland Ave Saugus MA 01906",
    "addr:housenumber":"32",
    "addr:postcode":"01906",
    "addr:street":"Highland Ave",
    "iso:country":"US",
    "sg:address":"32 Highland Ave",
    "sg:city":"Saugus",
    "sg:classifiers":[
        {
            "category":"Building & Trades",
            "subcategory":"Construction",
            "type":"Services"
        }
    ],
    "sg:phone":"+1 781 231 0102",
    "sg:postcode":"01906",
    "sg:province":"MA",
    "sg:tags":[
        "excavation",
        "contractor"
    ],
    "wof:name":"Memont's San Man Inc",
    "wof:placetype":"venue"
},
  "geometry": {"coordinates":[-71.02169000000001,42.462639],"type":"Point"}
}