{
  "type": "Feature",
  "properties": {
    "addr:full": "33 Church St Cambridge MA 02138",
    "addr:housenumber": "33",
    "addr:postcode": "02138",
    "addr:street": "Church St",
    "iso:country": "US",
    "sg:address": "33 Church St",
    "sg:city": "Cambridge",
    "sg:classifiers": [
      {
        "category": "Personal",
        "subcategory": "Beauty Salon",
        "type": "Services"
      }
    ],
    "sg:phone": "+1 617 868 7800",
    "sg:postcode": "02138",
    "sg:province": "MA",
    "sg:tags": [
      "hair"
    ],
    "sg:website": "www.carriagehousesalon.com/",
    "wof:name": "Carriage House Salon",
    "wof:placetype": "venue"
  },
  "geometry": {"coordinates":[-71.120154,42.374392],"type":"Point"}
}
