{
  "type": "Feature",
  "properties": {
    "iso:country":"US",
    "sg:address":"44 Elm St",
    "sg:city":"Worcester",
    "sg:classifiers":[
        {
            "category":"Government",
            "subcategory":"Court House",
            "type":"Public Place"
        }
    ],
    "sg:phone":"+1 508 752 3369",
    "sg:postcode":"01609",
    "sg:province":"MA",
    "sg:tags":[
        "justice",
        "peace"
    ],
    "wof:name":"Peter C Stearns",
    "wof:placetype":"venue"
},
  "geometry": {"coordinates":[-71.804164,42.265085],"type":"Point"}
}