{
  "type": "Feature",
  "properties": {
    "iso:country":"US",
    "sg:address":"4 Royal Oaks Way",
    "sg:city":"Leominster",
    "sg:classifiers":[
        {
            "category":"Professional",
            "subcategory":"Computer Services",
            "type":"Services"
        }
    ],
    "sg:phone":"+1 508 331 8835",
    "sg:postcode":"01453",
    "sg:province":"MA",
    "sg:tags":[
        "consultant",
        "designer",
        "system"
    ],
    "wof:name":"Clickware",
    "wof:placetype":"venue"
},
  "geometry": {"coordinates":[-71.787778,42.541016],"type":"Point"}
}