{
  "type": "Feature",
  "properties": {
    "addr:full": "21 Lime St Marblehead MA 01945",
    "addr:housenumber": "21",
    "addr:postcode": "01945",
    "addr:street": "Lime St",
    "iso:country": "US",
    "sg:address": "21 Lime St",
    "sg:city": "Marblehead",
    "sg:classifiers": [
      {
        "category": "Manufacturing",
        "subcategory": "Tools \u0026 Machinery",
        "type": "Manufacturing \u0026 Wholesale Goods"
      }
    ],
    "sg:phone": "+1 781 639 1900",
    "sg:postcode": "01945",
    "sg:province": "MA",
    "sg:tags": [
      "physician",
      "surgeon"
    ],
    "sg:website": "www.questusmarine.com",
    "wof:name": "Qestus Marine Inc",
    "wof:placetype": "venue"
  },
  "geometry": {"coordinates":[-70.852927,42.507319],"type":"Point"}
}
