{
  "type": "Feature",
  "properties": {
    "iso:country":"US",
    "sg:address":"21 Lime St",
    "sg:city":"Marblehead",
    "sg:classifiers":[
        {
            "category":"Manufacturing",
            "subcategory":"Tools & Machinery",
            "type":"Manufacturing & Wholesale Goods"
        }
    ],
    "sg:phone":"+1 781 639 1900",
    "sg:postcode":"01945",
    "sg:province":"MA",
    "sg:tags":[
        "physician",
        "surgeon"
    ],
    "sg:website":"www.questusmarine.com",
    "wof:name":"Qestus Marine Inc",
    "wof:placetype":"venue"
},
  "geometry": {"coordinates":[-70.85292699999999,42.507319],"type":"Point"}
}