{
  "type": "Feature",
  "properties": {
    "iso:country":"US",
    "sg:address":"78 Main St",
    "sg:city":"Marshfield",
    "sg:classifiers":[
        {
            "category":"Professional",
            "type":"Services"
        }
    ],
    "sg:phone":"+1   ",
    "sg:postcode":"02050",
    "sg:province":"MA",
    "wof:name":"Primerica Fincial Services",
    "wof:placetype":"venue"
},
  "geometry": {"coordinates":[-70.71795299999999,42.097256],"type":"Point"}
}