{
  "type": "Feature",
  "properties": {
    "addr:full": "78 Main St Marshfield MA 02050",
    "addr:housenumber": "78",
    "addr:postcode": "02050",
    "addr:street": "Main St",
    "iso:country": "US",
    "sg:address": "78 Main St",
    "sg:city": "Marshfield",
    "sg:classifiers": [
      {
        "category": "Professional",
        "type": "Services"
      }
    ],
    "sg:phone": "+1   ",
    "sg:postcode": "02050",
    "sg:province": "MA",
    "wof:name": "Primerica Fincial Services",
    "wof:placetype": "venue"
  },
  "geometry": {"coordinates":[-70.717953,42.097256],"type":"Point"}
}
