{
  "type": "Feature",
  "properties": {
    "addr:full":"892 State St Springfield MA 01109",
    "addr:housenumber":"892",
    "addr:postcode":"01109",
    "addr:street":"State St",
    "iso:country":"US",
    "sg:address":"892 State St",
    "sg:city":"Springfield",
    "sg:classifiers":[
        {
            "category":"Restaurant",
            "type":"Food & Drink"
        }
    ],
    "sg:phone":"+1 413 731 7309",
    "sg:postcode":"01109",
    "sg:province":"MA",
    "sg:tags":[
        "eating"
    ],
    "wof:name":"Negrill Restaurant",
    "wof:placetype":"venue"
},
  "geometry": {"coordinates":[-72.56180500000001,42.112339],"type":"Point"}
}