{
  "type": "Feature",
  "properties": {
    "iso:country":"US",
    "sg:address":"155 S Main St",
    "sg:city":"Middleboro",
    "sg:classifiers":[
        {
            "category":"Autos & Motor Vehicles",
            "subcategory":"Fuel & Gas Station",
            "type":"Retail Goods"
        }
    ],
    "sg:phone":"+1 508 947 1521",
    "sg:postcode":"02346",
    "sg:province":"MA",
    "sg:tags":[
        "oil"
    ],
    "wof:name":"Middleboro Sunoco",
    "wof:placetype":"venue"
},
  "geometry": {"coordinates":[-70.91894600000001,41.884286],"type":"Point"}
}