{
  "type": "Feature",
  "properties": {
    "addr:full": "155 S Main St Middleboro MA 02346",
    "addr:housenumber": "155",
    "addr:postcode": "02346",
    "addr:street": "S Main St",
    "iso:country": "US",
    "sg:address": "155 S Main St",
    "sg:city": "Middleboro",
    "sg:classifiers": [
      {
        "category": "Autos \u0026 Motor Vehicles",
        "subcategory": "Fuel \u0026 Gas Station",
        "type": "Retail Goods"
      }
    ],
    "sg:phone": "+1 508 947 1521",
    "sg:postcode": "02346",
    "sg:province": "MA",
    "sg:tags": [
      "oil"
    ],
    "wof:name": "Middleboro Sunoco",
    "wof:placetype": "venue"
  },
  "geometry": {"coordinates":[-70.918946,41.884286],"type":"Point"}
}
