{
  "type": "Feature",
  "properties": {
    "addr:full":"6 Jefferson Park Cambridge MA 02140",
    "addr:housenumber":"6",
    "addr:postcode":"02140",
    "addr:street":"Jefferson",
    "iso:country":"US",
    "sg:address":"6 Jefferson Park",
    "sg:city":"Cambridge",
    "sg:classifiers":[
        {
            "category":"Education",
            "subcategory":"School",
            "type":"Public Place"
        }
    ],
    "sg:phone":"+1 617 497 4411",
    "sg:postcode":"02140",
    "sg:province":"MA",
    "sg:tags":[
        "high",
        "middle",
        "elementary"
    ],
    "wof:name":"Jefferson Park Learning Center",
    "wof:placetype":"venue"
},
  "geometry": {"coordinates":[-71.133932,42.393463],"type":"Point"}
}