{
  "type": "Feature",
  "properties": {
    "addr:full": "216 Bolivar St Canton MA 02021",
    "addr:housenumber": "216",
    "addr:postcode": "02021",
    "addr:street": "Bolivar St",
    "iso:country": "US",
    "sg:address": "216 Bolivar St",
    "sg:city": "Canton",
    "sg:classifiers": [
      {
        "category": "Manufacturing",
        "subcategory": "Chemicals \u0026 Compounds",
        "type": "Manufacturing \u0026 Wholesale Goods"
      }
    ],
    "sg:phone": "+1 781 821 8222",
    "sg:postcode": "02021",
    "sg:province": "MA",
    "sg:tags": [
      "adhesive",
      "sealant"
    ],
    "wof:name": "Advanced ECO-Adhesives Inc",
    "wof:placetype": "venue"
  },
  "geometry": {"coordinates":[-71.138278,42.152124],"type":"Point"}
}
