{
  "type": "Feature",
  "properties": {
    "addr:full":"26 Jefferson St Billerica MA 01821",
    "addr:housenumber":"26",
    "addr:postcode":"01821",
    "addr:street":"Jefferson St",
    "iso:country":"US",
    "sg:address":"26 Jefferson St",
    "sg:city":"Billerica",
    "sg:classifiers":[
        {
            "category":"Social Services",
            "subcategory":"Child Care",
            "type":"Services"
        }
    ],
    "sg:phone":"+1   ",
    "sg:postcode":"01821",
    "sg:province":"MA",
    "sg:tags":[
        "day"
    ],
    "wof:name":"Diana Judd",
    "wof:placetype":"venue"
},
  "geometry": {"coordinates":[-71.21735200000001,42.555639],"type":"Point"}
}