{
  "type": "Feature",
  "properties": {
    "addr:full": "23 Fleet St Boston MA 02113",
    "addr:housenumber": "23",
    "addr:postcode": "02113",
    "addr:street": "Fleet St",
    "iso:country": "US",
    "sg:address": "23 Fleet St",
    "sg:city": "Boston",
    "sg:classifiers": [
      {
        "category": "Building \u0026 Trades",
        "subcategory": "Construction",
        "type": "Services"
      }
    ],
    "sg:phone": "+1   ",
    "sg:postcode": "02113",
    "sg:province": "MA",
    "sg:tags": [
      "hanging",
      "nonresidential",
      "contractor"
    ],
    "wof:name": "Jj Gray Maint \u0026 Repairs",
    "wof:placetype": "venue"
  },
  "geometry": {"coordinates":[-71.052825,42.364608],"type":"Point"}
}
