{
  "type": "Feature",
  "properties": {
    "iso:country":"US",
    "sg:address":"23 Fleet St",
    "sg:city":"Boston",
    "sg:classifiers":[
        {
            "category":"Building & Trades",
            "subcategory":"Construction",
            "type":"Services"
        }
    ],
    "sg:phone":"+1   ",
    "sg:postcode":"02113",
    "sg:province":"MA",
    "sg:tags":[
        "hanging",
        "nonresidential",
        "contractor"
    ],
    "wof:name":"Jj Gray Maint & Repairs",
    "wof:placetype":"venue"
},
  "geometry": {"coordinates":[-71.052825,42.364608],"type":"Point"}
}