{
  "type": "Feature",
  "properties": {
    "iso:country":"US",
    "sg:address":"49 Heritage Ln",
    "sg:city":"Leominster",
    "sg:classifiers":[
        {
            "category":"Communications",
            "subcategory":"Film & Video Production",
            "type":"Services"
        }
    ],
    "sg:phone":"+1   ",
    "sg:postcode":"01453",
    "sg:province":"MA",
    "sg:tags":[
        "motion"
    ],
    "wof:name":"Jason Dokulil",
    "wof:placetype":"venue"
},
  "geometry": {"coordinates":[-71.749889,42.557027],"type":"Point"}
}