{
  "type": "Feature",
  "properties": {
    "addr:full":"31 Dorchester St Wilmington MA 01887",
    "addr:housenumber":"31",
    "addr:postcode":"01887",
    "addr:street":"Dorchester St",
    "iso:country":"US",
    "sg:address":"31 Dorchester St",
    "sg:city":"Wilmington",
    "sg:classifiers":[
        {
            "category":"Real Estate",
            "subcategory":"Real Estate Services",
            "type":"Services"
        },
        {
            "category":"Real Estate",
            "subcategory":"Real Estate Agent",
            "type":"Services"
        }
    ],
    "sg:phone":"+1 978 909 3004",
    "sg:postcode":"01887",
    "sg:province":"MA",
    "sg:tags":[
        "buyer",
        "broker"
    ],
    "wof:name":"Wile Real Estate Organization. Inc.",
    "wof:placetype":"venue"
},
  "geometry": {"coordinates":[-71.214699,42.561008],"type":"Point"}
}