{
  "type": "Feature",
  "properties": {
    "addr:full":"19 N Main St Randolph MA 02368",
    "addr:housenumber":"19",
    "addr:postcode":"02368",
    "addr:street":"N Main St",
    "iso:country":"US",
    "sg:address":"19 N Main St",
    "sg:city":"Randolph",
    "sg:classifiers":[
        {
            "category":"Government",
            "subcategory":"Office",
            "type":"Public Place"
        }
    ],
    "sg:phone":"+1 781 961 0936",
    "sg:postcode":"02368",
    "sg:province":"MA",
    "sg:tags":[
        "village"
    ],
    "wof:name":"Youth Coordinator",
    "wof:placetype":"venue"
},
  "geometry": {"coordinates":[-71.04137,42.16261],"type":"Point"}
}