{
  "type": "Feature",
  "properties": {
    "addr:full": "5 Crystal St Lenox Dale MA 01242",
    "addr:housenumber": "5",
    "addr:postcode": "01242",
    "addr:street": "Crystal St",
    "iso:country": "US",
    "sg:address": "5 Crystal St",
    "sg:city": "Lenox Dale",
    "sg:classifiers": [
      {
        "category": "Building \u0026 Trades",
        "subcategory": "Landscaping Services",
        "type": "Services"
      }
    ],
    "sg:phone": "+1 413 637 2678",
    "sg:postcode": "01242",
    "sg:province": "MA",
    "sg:tags": [
      "lawn",
      "maintenance",
      "grounds"
    ],
    "wof:name": "Rick's Complete Lawn \u0026 Landscp",
    "wof:placetype": "venue"
  },
  "geometry": {"coordinates":[-73.245924,42.334009],"type":"Point"}
}
