{
  "type": "Feature",
  "properties": {
    "iso:country":"US",
    "sg:address":"13 Hamilton St",
    "sg:city":"New Bedford",
    "sg:classifiers":[
        {
            "category":"Professional",
            "subcategory":"Lawyer & Legal Services",
            "type":"Services"
        }
    ],
    "sg:phone":"+1   ",
    "sg:postcode":"02740",
    "sg:province":"MA",
    "wof:name":"Keches & Mallen PC",
    "wof:placetype":"venue"
},
  "geometry": {"coordinates":[-70.92209200000001,41.635702],"type":"Point"}
}