{
  "type": "Feature",
  "properties": {
    "iso:country":"US",
    "sg:address":"25 Stuart St",
    "sg:city":"Boston",
    "sg:classifiers":[
        {
            "category":"Health Services",
            "subcategory":"Clinic",
            "type":"Services"
        }
    ],
    "sg:phone":"+1 617 426 1628",
    "sg:postcode":"02116",
    "sg:province":"MA",
    "wof:name":"Midtown Home Health Svc",
    "wof:placetype":"venue"
},
  "geometry": {"coordinates":[-71.06370200000001,42.351033],"type":"Point"}
}