{
  "type": "Feature",
  "properties": {
    "addr:full":"972 Massachusetts Ave Boxborough MA 01719",
    "addr:housenumber":"972",
    "addr:postcode":"01719",
    "addr:street":"Massachusetts Ave",
    "iso:country":"US",
    "sg:address":"972 Massachusetts Ave",
    "sg:city":"Boxborough",
    "sg:classifiers":[
        {
            "category":"Building & Trades",
            "subcategory":"Construction",
            "type":"Services"
        }
    ],
    "sg:phone":"+1 978 263 4322",
    "sg:postcode":"01719",
    "sg:province":"MA",
    "sg:tags":[
        "maker",
        "cabinet"
    ],
    "sg:website":"www.woodwork.com",
    "wof:name":"Fine Line Woodworking",
    "wof:placetype":"venue"
},
  "geometry": {"coordinates":[-71.522929,42.482782],"type":"Point"}
}