{
  "type": "Feature",
  "properties": {
    "iso:country":"US",
    "sg:address":"665 Beacon St Ste 100",
    "sg:city":"Boston",
    "sg:classifiers":[
        {
            "category":"Organizations",
            "subcategory":"Membership Organization",
            "type":"Services"
        }
    ],
    "sg:phone":"+1 617 424 0665",
    "sg:postcode":"02215",
    "sg:province":"MA",
    "sg:tags":[
        "military",
        "veteran"
    ],
    "sg:website":"http://www.cmop.com",
    "wof:name":"Boston Vet Center",
    "wof:placetype":"venue"
},
  "geometry": {"coordinates":[-71.09871200000001,42.348393],"type":"Point"}
}