{
  "type": "Feature",
  "properties": {
    "addr:full":"40 Edwin H Land Blvd Cambridge MA 02142",
    "addr:housenumber":"40;h",
    "addr:postcode":"02142",
    "addr:street":"Edwin;Land Blvd",
    "iso:country":"US",
    "sg:address":"40 Edwin H Land Blvd",
    "sg:city":"Cambridge",
    "sg:phone":"+1 617 401 7653",
    "sg:postcode":"02142",
    "sg:province":"MA",
    "sg:website":"http://boston.citysearch.com/profile/external/41920704/cambridge_ma/dante.html?publisher=yellowpages&reference_id=1&placement=ypwebsitemip",
    "wof:name":"Dante",
    "wof:placetype":"venue"
},
  "geometry": {"coordinates":[-71.078327,42.362894],"type":"Point"}
}