{
  "type": "Feature",
  "properties": {
    "addr:full": "1 Financial Center Boston MA 02111",
    "addr:housenumber": "1",
    "addr:postcode": "02111",
    "iso:country": "US",
    "sg:address": "1 Financial Center",
    "sg:city": "Boston",
    "sg:classifiers": [
      {
        "category": "Professional",
        "subcategory": "Lawyer \u0026 Legal Services",
        "type": "Services"
      }
    ],
    "sg:phone": "+1 617 856 8200",
    "sg:postcode": "02111",
    "sg:province": "MA",
    "wof:name": "Hickey Michael J Atty Jr",
    "wof:placetype": "venue"
  },
  "geometry": {"coordinates":[-71.056204,42.352537],"type":"Point"}
}
