{
  "type": "Feature",
  "properties": {
    "addr:full":"95 Wexford St Needham MA 02494",
    "addr:housenumber":"95",
    "addr:postcode":"02494",
    "addr:street":"Wexford St",
    "iso:country":"US",
    "sg:address":"95 Wexford St",
    "sg:city":"Needham",
    "sg:classifiers":[
        {
            "category":"Professional",
            "type":"Services"
        }
    ],
    "sg:phone":"+1 781 444 2080",
    "sg:postcode":"02494",
    "sg:province":"MA",
    "sg:tags":[
        "establishment"
    ],
    "wof:name":"Celtic Vision",
    "wof:placetype":"venue"
},
  "geometry": {"coordinates":[-71.223862,42.30572],"type":"Point"}
}