{
  "type": "Feature",
  "properties": {
    "addr:full": "2 Atwood Ave Millbury MA 01527",
    "addr:housenumber": "2",
    "addr:postcode": "01527",
    "addr:street": "Atwood Ave",
    "iso:country": "US",
    "sg:address": "2 Atwood Ave",
    "sg:city": "Millbury",
    "sg:classifiers": [
      {
        "category": "Restaurant",
        "type": "Food \u0026 Drink"
      }
    ],
    "sg:phone": "+1 508 865 1356",
    "sg:postcode": "01527",
    "sg:province": "MA",
    "sg:tags": [
      "italian"
    ],
    "wof:name": "My Place Family Restaurant",
    "wof:placetype": "venue"
  },
  "geometry": {"coordinates":[-71.760262,42.196529],"type":"Point"}
}
