{
  "type": "Feature",
  "properties": {
    "addr:full":"100 Southampton St Boston MA 02118",
    "addr:housenumber":"100",
    "addr:postcode":"02118",
    "addr:street":"Southampton St",
    "iso:country":"US",
    "sg:address":"100 Southampton St",
    "sg:city":"Boston",
    "sg:classifiers":[
        {
            "category":"Retail",
            "subcategory":"Portrait Studio",
            "type":"Services"
        },
        {
            "category":"Professional",
            "subcategory":"Art Services",
            "type":"Services"
        }
    ],
    "sg:phone":"+1 617 427 8300",
    "sg:postcode":"02118",
    "sg:province":"MA",
    "sg:tags":[
        "photographer",
        "photography",
        "store"
    ],
    "sg:website":"www.atph.com",
    "wof:name":"Atlantic Photography",
    "wof:placetype":"venue"
},
  "geometry": {"coordinates":[-71.069999,42.332487],"type":"Point"}
}