{
  "type": "Feature",
  "properties": {
    "iso:country":"US",
    "sg:address":"10 Anderson Ave",
    "sg:city":"Kingston",
    "sg:classifiers":[
        {
            "category":"Retail",
            "subcategory":"Repair Shop",
            "type":"Services"
        }
    ],
    "sg:phone":"+1 781 585 7591",
    "sg:postcode":"02364",
    "sg:province":"MA",
    "sg:tags":[
        "upholsterer"
    ],
    "wof:name":"Werner's Upholstering",
    "wof:placetype":"venue"
},
  "geometry": {"coordinates":[-70.70771999999999,41.975307],"type":"Point"}
}