{
  "type": "Feature",
  "properties": {
    "addr:full": "1109 River St Hyde Park MA 02136",
    "addr:housenumber": "1109",
    "addr:postcode": "02136",
    "addr:street": "River St",
    "iso:country": "US",
    "sg:address": "1109 River St",
    "sg:city": "Hyde Park",
    "sg:classifiers": [
      {
        "category": "Organizations",
        "subcategory": "Religious Organization",
        "type": "Services"
      }
    ],
    "sg:phone": "+1 617 361 0051",
    "sg:postcode": "02136",
    "sg:province": "MA",
    "sg:tags": [
      "church"
    ],
    "wof:name": "Hyde Park Presbyterian Church",
    "wof:placetype": "venue"
  },
  "geometry": {"coordinates":[-71.119133,42.257904],"type":"Point"}
}
