{
  "type": "Feature",
  "properties": {
    "iso:country":"US",
    "sg:address":"1109 River St",
    "sg:city":"Hyde Park",
    "sg:classifiers":[
        {
            "category":"Organizations",
            "subcategory":"Religious Organization",
            "type":"Services"
        }
    ],
    "sg:phone":"+1 617 361 0051",
    "sg:postcode":"02136",
    "sg:province":"MA",
    "sg:tags":[
        "church"
    ],
    "wof:name":"Hyde Park Presbyterian Church",
    "wof:placetype":"venue"
},
  "geometry": {"coordinates":[-71.11913300000001,42.257904],"type":"Point"}
}