{
  "type": "Feature",
  "properties": {
    "iso:country":"US",
    "sg:address":"81 Wyman St",
    "sg:city":"Waban",
    "sg:classifiers":[
        {
            "category":"Health Services",
            "subcategory":"Medical Lab",
            "type":"Services"
        }
    ],
    "sg:phone":"+1 617 244 2516",
    "sg:postcode":"02468",
    "sg:province":"MA",
    "sg:tags":[
        "laboratory"
    ],
    "wof:name":"Laboratory For Stone Research",
    "wof:placetype":"venue"
},
  "geometry": {"coordinates":[-71.23022899999999,42.326445],"type":"Point"}
}