{
  "type": "Feature",
  "properties": {
    "addr:full": "15 Hall St Medford MA 02155",
    "addr:housenumber": "15",
    "addr:postcode": "02155",
    "addr:street": "Hall St",
    "iso:country": "US",
    "sg:address": "15 Hall St",
    "sg:city": "Medford",
    "sg:classifiers": [
      {
        "category": "Real Estate",
        "subcategory": "Surveying",
        "type": "Services"
      }
    ],
    "sg:phone": "+1 781 396 4466",
    "sg:postcode": "02155",
    "sg:province": "MA",
    "sg:tags": [
      "surveyor"
    ],
    "wof:name": "ABV Survey",
    "wof:placetype": "venue"
  },
  "geometry": {"coordinates":[-71.089983,42.409748],"type":"Point"}
}
