{
  "type": "Feature",
  "properties": {
    "addr:full": "117 Birch Hill Rd Stow MA 01775",
    "addr:housenumber": "117",
    "addr:postcode": "01775",
    "addr:street": "Birch Hill Rd",
    "iso:country": "US",
    "sg:address": "117 Birch Hill Rd",
    "sg:city": "Stow",
    "sg:classifiers": [
      {
        "category": "Professional",
        "subcategory": "Management \u0026 Consulting",
        "type": "Services"
      }
    ],
    "sg:phone": "+1   ",
    "sg:postcode": "01775",
    "sg:province": "MA",
    "sg:tags": [
      "business"
    ],
    "wof:name": "Kmpq Consulting Inc",
    "wof:placetype": "venue"
  },
  "geometry": {"coordinates":[-71.510212,42.418582],"type":"Point"}
}
