{
  "type": "Feature",
  "properties": {
    "addr:full":"157 Main St Sandwich MA 02563",
    "addr:housenumber":"157",
    "addr:postcode":"02563",
    "addr:street":"Main St",
    "iso:country":"US",
    "sg:address":"157 Main St",
    "sg:city":"Sandwich",
    "sg:classifiers":[
        {
            "category":"Shopping",
            "subcategory":"Gifts & Souvenirs",
            "type":"Retail Goods"
        }
    ],
    "sg:phone":"+1 508 888 5508",
    "sg:postcode":"02563",
    "sg:province":"MA",
    "sg:tags":[
        "shop"
    ],
    "wof:name":"A Village Gift Shop",
    "wof:placetype":"venue"
},
  "geometry": {"coordinates":[-70.496425,41.757735],"type":"Point"}
}