{
  "type": "Feature",
  "properties": {
    "addr:full": "100 River Ridge Dr Norwood MA 02062",
    "addr:housenumber": "100",
    "addr:postcode": "02062",
    "addr:street": "River Ridge Dr",
    "iso:country": "US",
    "sg:address": "100 River Ridge Dr",
    "sg:city": "Norwood",
    "sg:classifiers": [
      {
        "category": "Coffee \u0026 Tea",
        "type": "Food \u0026 Drink"
      },
      {
        "category": "Restaurant",
        "type": "Food \u0026 Drink"
      }
    ],
    "sg:phone": "+1 781 762 3494",
    "sg:postcode": "02062",
    "sg:province": "MA",
    "sg:tags": [
      "espresso"
    ],
    "sg:website": "http://www.riverridgeconsultinggroup.com",
    "wof:name": "River Ridge Consulting Group L",
    "wof:placetype": "venue"
  },
  "geometry": {"coordinates":[-71.191448,42.175281],"type":"Point"}
}
