{
  "type": "Feature",
  "properties": {
    "addr:full":"193 Concord St Framingham MA 01702",
    "addr:housenumber":"193",
    "addr:postcode":"01702",
    "addr:street":"Concord St",
    "iso:country":"US",
    "sg:address":"193 Concord St",
    "sg:city":"Framingham",
    "sg:classifiers":[
        {
            "category":"Retail",
            "subcategory":"Repair Shop",
            "type":"Services"
        }
    ],
    "sg:phone":"+1 508 879 3292",
    "sg:postcode":"01702",
    "sg:province":"MA",
    "sg:tags":[
        "lock",
        "locksmith"
    ],
    "wof:name":"A Locksmith",
    "wof:placetype":"venue"
},
  "geometry": {"coordinates":[-71.41593,42.280253],"type":"Point"}
}