{
  "type": "Feature",
  "properties": {
    "addr:full": "56 Beach St. Boston MA 02111",
    "addr:housenumber": "56",
    "addr:postcode": "02111",
    "addr:street": "Beach St.",
    "iso:country": "US",
    "ovtr:label": "101 Bakery, 56 Beach St Boston MA US",
    "ovtr:similarity": 2.495089054107666,
    "sg:address": "56 Beach St.",
    "sg:city": "Boston",
    "sg:classifiers": [
      {
        "category": "Food \u0026 Beverages",
        "subcategory": "Bakery",
        "type": "Retail Goods"
      },
      {
        "category": "Bakery",
        "type": "Food \u0026 Drink"
      }
    ],
    "sg:phone": "+1 617 451 9988",
    "sg:postcode": "02111",
    "sg:province": "MA",
    "sg:tags": [
      "bakers-wholesale"
    ],
    "sg:website": "www.101bakery.com",
    "wof:name": "101 Bakery",
    "wof:placetype": "venue"
  },
  "geometry": {"coordinates":[-71.06052,42.351493],"type":"Point"}
}
