{
  "type": "Feature",
  "properties": {
    "iso:country":"US",
    "sg:address":"56 Beach St.",
    "sg:city":"Boston",
    "sg:classifiers":[
        {
            "category":"Food & Beverages",
            "subcategory":"Bakery",
            "type":"Retail Goods"
        },
        {
            "category":"Bakery",
            "type":"Food & Drink"
        }
    ],
    "sg:phone":"+1 617 451 9988",
    "sg:postcode":"02111",
    "sg:province":"MA",
    "sg:tags":[
        "bakers-wholesale"
    ],
    "sg:website":"www.101bakery.com",
    "wof:name":"101 Bakery",
    "wof:placetype":"venue"
},
  "geometry": {"coordinates":[-71.06052,42.351493],"type":"Point"}
}