{
  "type": "Feature",
  "properties": {
    "addr:full": "75 Arlington Street Suite 500 Boston MA 02116",
    "addr:housenumber": "75",
    "addr:postcode": "02116",
    "addr:street": "Arlington Street Suite 500",
    "iso:country": "US",
    "sg:address": "75 Arlington Street Suite 500",
    "sg:city": "Boston",
    "sg:classifiers": [
      {
        "category": "Building \u0026 Trades",
        "subcategory": "Construction",
        "type": "Services"
      }
    ],
    "sg:phone": "+1 617 275 2313",
    "sg:postcode": "02116",
    "sg:province": "MA",
    "sg:tags": [
      "interior",
      "design"
    ],
    "sg:website": "www.strackainteriors.com",
    "wof:name": "Stracka Nancy Interiors",
    "wof:placetype": "venue"
  },
  "geometry": {"coordinates":[-71.070138,42.350584],"type":"Point"}
}
