{
  "type": "Feature",
  "properties": {
    "iso:country":"US",
    "sg:address":"763 White St",
    "sg:city":"Springfield",
    "sg:classifiers":[
        {
            "category":"Professional",
            "subcategory":"Accounting & Tax Preparation",
            "type":"Services"
        }
    ],
    "sg:phone":"+1 413 731 0999",
    "sg:postcode":"01108",
    "sg:province":"MA",
    "sg:tags":[
        "return",
        "filing"
    ],
    "wof:name":"JEM Assoc",
    "wof:placetype":"venue"
},
  "geometry": {"coordinates":[-72.541634,42.082248],"type":"Point"}
}