{
  "type": "Feature",
  "properties": {
    "iso:country":"US",
    "sg:address":"744 Main St",
    "sg:city":"Dennis",
    "sg:classifiers":[
        {
            "category":"Real Estate",
            "subcategory":"Real Estate Agent",
            "type":"Services"
        }
    ],
    "sg:phone":"+1 508 385 4595",
    "sg:postcode":"02638",
    "sg:province":"MA",
    "wof:name":"Paul W Sullivan Assoc",
    "wof:placetype":"venue"
},
  "geometry": {"coordinates":[-70.192436,41.73786],"type":"Point"}
}