{
  "type": "Feature",
  "properties": {
    "addr:full":"635 Purchase St New Bedford MA 02740",
    "addr:housenumber":"635",
    "addr:postcode":"02740",
    "addr:street":"Purchase St",
    "iso:country":"US",
    "sg:address":"635 Purchase St",
    "sg:city":"New Bedford",
    "sg:classifiers":[
        {
            "category":"Professional",
            "type":"Services"
        }
    ],
    "sg:phone":"+1 508 993 8976",
    "sg:postcode":"02740",
    "sg:province":"MA",
    "sg:tags":[
        "establishment"
    ],
    "wof:name":"United Interfaith Action",
    "wof:placetype":"venue"
},
  "geometry": {"coordinates":[-70.925529,41.631957],"type":"Point"}
}