{
  "type": "Feature",
  "properties": {
    "addr:full":"43 Revere St Boston MA 02114",
    "addr:housenumber":"43",
    "addr:postcode":"02114",
    "addr:street":"Revere St",
    "iso:country":"US",
    "sg:address":"43 Revere St",
    "sg:city":"Boston",
    "sg:classifiers":[
        {
            "category":"Professional",
            "subcategory":"Business Services",
            "type":"Services"
        }
    ],
    "sg:phone":"+1   ",
    "sg:postcode":"02114",
    "sg:province":"MA",
    "wof:name":"Beacon Services Group",
    "wof:placetype":"venue"
},
  "geometry": {"coordinates":[-71.067977,42.359654],"type":"Point"}
}