{
  "type": "Feature",
  "properties": {
    "iso:country":"US",
    "sg:address":"868 Worcester St",
    "sg:city":"Wellesley",
    "sg:classifiers":[
        {
            "category":"Home & Garden",
            "subcategory":"Furniture",
            "type":"Retail Goods"
        }
    ],
    "sg:phone":"+1 781 237 7100",
    "sg:postcode":"02482",
    "sg:province":"MA",
    "sg:tags":[
        "equipment",
        "kitchen",
        "cabinet"
    ],
    "wof:name":"Weston Kitchens",
    "wof:placetype":"venue"
},
  "geometry": {"coordinates":[-71.31326,42.30529],"type":"Point"}
}