{
  "type": "Feature",
  "properties": {
    "addr:full":"274 Main St Hingham MA 02043",
    "addr:housenumber":"274",
    "addr:postcode":"02043",
    "addr:street":"Main St",
    "iso:country":"US",
    "sg:address":"274 Main St",
    "sg:city":"Hingham",
    "sg:classifiers":[
        {
            "category":"Banks & Credit Unions",
            "subcategory":"Bank",
            "type":"Services"
        }
    ],
    "sg:phone":"+1 781 740 4830",
    "sg:postcode":"02043",
    "sg:province":"MA",
    "wof:name":"Eastern Bank",
    "wof:placetype":"venue"
},
  "geometry": {"coordinates":[-70.880763,42.233911],"type":"Point"}
}