{
  "type": "Feature",
  "properties": {
    "addr:full": "80 Trim Way Randolph MA 02368",
    "addr:housenumber": "80",
    "addr:postcode": "02368",
    "addr:street": "Trim Way",
    "iso:country": "US",
    "sg:address": "80 Trim Way",
    "sg:city": "Randolph",
    "sg:classifiers": [
      {
        "category": "Manufacturing",
        "subcategory": "Metals",
        "type": "Manufacturing \u0026 Wholesale Goods"
      }
    ],
    "sg:phone": "+1 781 963 7200",
    "sg:postcode": "02368",
    "sg:province": "MA",
    "sg:tags": [
      "extruded",
      "product",
      "aluminum"
    ],
    "sg:website": "www.extrusiontechnology.com",
    "wof:name": "Extrusion Technology Inc",
    "wof:placetype": "venue"
  },
  "geometry": {"coordinates":[-71.036056,42.1735],"type":"Point"}
}
