{
  "type": "Feature",
  "properties": {
    "addr:full":"40 York Rd Wayland MA 01778",
    "addr:housenumber":"40",
    "addr:postcode":"01778",
    "addr:street":"York Rd",
    "iso:country":"US",
    "sg:address":"40 York Rd",
    "sg:city":"Wayland",
    "sg:classifiers":[
        {
            "category":"Professional",
            "subcategory":"Business Services",
            "type":"Services"
        }
    ],
    "sg:phone":"+1   ",
    "sg:postcode":"01778",
    "sg:province":"MA",
    "wof:name":"RKL Enterprises Ltd",
    "wof:placetype":"venue"
},
  "geometry": {"coordinates":[-71.356131,42.404203],"type":"Point"}
}