{
  "type": "Feature",
  "properties": {
    "addr:full":"2 Maple Ave Upton MA 01568",
    "addr:housenumber":"2",
    "addr:postcode":"01568",
    "addr:street":"Maple Ave",
    "iso:country":"US",
    "sg:address":"2 Maple Ave",
    "sg:city":"Upton",
    "sg:classifiers":[
        {
            "category":"Shopping",
            "subcategory":"Computers & Home Electronics",
            "type":"Retail Goods"
        }
    ],
    "sg:phone":"+1 508 529 4300",
    "sg:postcode":"01568",
    "sg:province":"MA",
    "sg:tags":[
        "software"
    ],
    "wof:name":"Sageful Corp",
    "wof:placetype":"venue"
},
  "geometry": {"coordinates":[-71.620589,42.166705],"type":"Point"}
}