{
  "type": "Feature",
  "properties": {
    "iso:country":"US",
    "sg:address":"49 Barker Rd",
    "sg:city":"Scituate",
    "sg:classifiers":[
        {
            "category":"Shopping",
            "subcategory":"Gifts & Souvenirs",
            "type":"Retail Goods"
        }
    ],
    "sg:phone":"+1 781 545 5050",
    "sg:postcode":"02066",
    "sg:province":"MA",
    "sg:tags":[
        "shop"
    ],
    "wof:name":"Linda Harrison Assoc Inc",
    "wof:placetype":"venue"
},
  "geometry": {"coordinates":[-70.72721900000001,42.2052],"type":"Point"}
}