{
  "type": "Feature",
  "properties": {
    "addr:full":"337 Summer St Boston MA 02210",
    "addr:housenumber":"337",
    "addr:postcode":"02210",
    "addr:street":"Summer St",
    "iso:country":"US",
    "sg:address":"337 Summer St",
    "sg:city":"Boston",
    "sg:classifiers":[
        {
            "category":"Arts & Performance",
            "subcategory":"Arts Center",
            "type":"Entertainment"
        },
        {
            "category":"Education",
            "subcategory":"School",
            "type":"Public Place"
        }
    ],
    "sg:phone":"+1 617 227 1522",
    "sg:postcode":"02210",
    "sg:province":"MA",
    "sg:website":"www.e-action.us",
    "wof:name":"E-Inc Enviromental Learning & Action Center",
    "wof:placetype":"venue"
},
  "geometry": {"coordinates":[-71.048159,42.349126],"type":"Point"}
}