{
  "type": "Feature",
  "properties": {
    "addr:full":"499 E Main St Southbridge MA 01550",
    "addr:housenumber":"499",
    "addr:postcode":"01550",
    "addr:street":"E Main St",
    "iso:country":"US",
    "sg:address":"499 E Main St",
    "sg:city":"Southbridge",
    "sg:classifiers":[
        {
            "category":"Autos & Motor Vehicles",
            "subcategory":"Auto Supplies",
            "type":"Retail Goods"
        }
    ],
    "sg:phone":"+1 508 764 1900",
    "sg:postcode":"01550",
    "sg:province":"MA",
    "sg:tags":[
        "part"
    ],
    "wof:name":"Advance Auto Parts",
    "wof:placetype":"venue"
},
  "geometry": {"coordinates":[-72.008003,42.067501],"type":"Point"}
}