{
  "type": "Feature",
  "properties": {
    "iso:country":"US",
    "sg:address":"67 Church St",
    "sg:city":"Lenox",
    "sg:classifiers":[
        {
            "category":"Professional",
            "subcategory":"Lawyer & Legal Services",
            "type":"Services"
        }
    ],
    "sg:phone":"+1 413 637 1300",
    "sg:postcode":"01240",
    "sg:province":"MA",
    "sg:tags":[
        "attorney",
        "practice",
        "plan"
    ],
    "wof:name":"Lynch Scrimo Attorneys",
    "wof:placetype":"venue"
},
  "geometry": {"coordinates":[-73.282826,42.357869],"type":"Point"}
}