{
  "type": "Feature",
  "properties": {
    "addr:full": "67 Church St Lenox MA 01240",
    "addr:housenumber": "67",
    "addr:postcode": "01240",
    "addr:street": "Church St",
    "iso:country": "US",
    "sg:address": "67 Church St",
    "sg:city": "Lenox",
    "sg:classifiers": [
      {
        "category": "Professional",
        "subcategory": "Lawyer \u0026 Legal Services",
        "type": "Services"
      }
    ],
    "sg:phone": "+1 413 637 1300",
    "sg:postcode": "01240",
    "sg:province": "MA",
    "sg:tags": [
      "attorney",
      "practice",
      "plan"
    ],
    "wof:name": "Lynch Scrimo Attorneys",
    "wof:placetype": "venue"
  },
  "geometry": {"coordinates":[-73.282826,42.357869],"type":"Point"}
}
