{
  "type": "Feature",
  "properties": {
    "addr:full": "31 Whisper Dr Worcester MA 01609",
    "addr:housenumber": "31",
    "addr:postcode": "01609",
    "addr:street": "Whisper Dr",
    "iso:country": "US",
    "sg:address": "31 Whisper Dr",
    "sg:city": "Worcester",
    "sg:classifiers": [
      {
        "category": "Professional",
        "subcategory": "Management \u0026 Consulting",
        "type": "Services"
      }
    ],
    "sg:phone": "+1 508 754 5082",
    "sg:postcode": "01609",
    "sg:province": "MA",
    "sg:tags": [
      "science",
      "consultant",
      "academic"
    ],
    "wof:name": "Y Mendelson",
    "wof:placetype": "venue"
  },
  "geometry": {"coordinates":[-71.846421,42.296953],"type":"Point"}
}
