{
  "type": "Feature",
  "properties": {
    "iso:country":"US",
    "sg:address":"31 Whisper Dr",
    "sg:city":"Worcester",
    "sg:classifiers":[
        {
            "category":"Professional",
            "subcategory":"Management & Consulting",
            "type":"Services"
        }
    ],
    "sg:phone":"+1 508 754 5082",
    "sg:postcode":"01609",
    "sg:province":"MA",
    "sg:tags":[
        "science",
        "consultant",
        "academic"
    ],
    "wof:name":"Y Mendelson",
    "wof:placetype":"venue"
},
  "geometry": {"coordinates":[-71.84642100000001,42.296953],"type":"Point"}
}