{
  "type": "Feature",
  "properties": {
    "iso:country":"US",
    "sg:address":"72 King St",
    "sg:city":"Norfolk",
    "sg:classifiers":[
        {
            "category":"Professional",
            "subcategory":"Computer Services",
            "type":"Services"
        }
    ],
    "sg:phone":"+1   ",
    "sg:postcode":"02056",
    "sg:province":"MA",
    "sg:tags":[
        "related"
    ],
    "wof:name":"DJL Consulting",
    "wof:placetype":"venue"
},
  "geometry": {"coordinates":[-71.34002,42.09917],"type":"Point"}
}