{
  "type": "Feature",
  "properties": {
    "iso:country":"US",
    "sg:address":"7 Walden St",
    "sg:city":"Winthrop",
    "sg:classifiers":[
        {
            "category":"Real Estate",
            "subcategory":"Real Estate Operator",
            "type":"Services"
        }
    ],
    "sg:phone":"+1 617 846 4115",
    "sg:postcode":"02152",
    "sg:province":"MA",
    "sg:tags":[
        "apartment"
    ],
    "wof:name":"Pillar House Apartments, The",
    "wof:placetype":"venue"
},
  "geometry": {"coordinates":[-70.987122,42.378071],"type":"Point"}
}