{
  "type": "Feature",
  "properties": {
    "addr:full":"22 Irene Dr Westport MA 02790",
    "addr:housenumber":"22",
    "addr:postcode":"02790",
    "addr:street":"Irene Dr",
    "iso:country":"US",
    "sg:address":"22 Irene Dr",
    "sg:city":"Westport",
    "sg:classifiers":[
        {
            "category":"Building & Trades",
            "subcategory":"Landscaping Services",
            "type":"Services"
        }
    ],
    "sg:phone":"+1   ",
    "sg:postcode":"02790",
    "sg:province":"MA",
    "sg:tags":[
        "landscape"
    ],
    "wof:name":"Raposo Landscape",
    "wof:placetype":"venue"
},
  "geometry": {"coordinates":[-71.087924,41.676084],"type":"Point"}
}