{
  "type": "Feature",
  "properties": {
    "iso:country":"US",
    "sg:address":"294 Middlesex Ave",
    "sg:city":"Wilmington",
    "sg:classifiers":[
        {
            "category":"Real Estate",
            "subcategory":"Real Estate Services",
            "type":"Services"
        }
    ],
    "sg:phone":"+1 800 924 6637",
    "sg:postcode":"01887",
    "sg:province":"MA",
    "sg:tags":[
        "home",
        "inspector"
    ],
    "wof:name":"Anderson Home Inspection Inc",
    "wof:placetype":"venue"
},
  "geometry": {"coordinates":[-71.159598,42.564189],"type":"Point"}
}