{
  "type": "Feature",
  "properties": {
    "iso:country":"US",
    "sg:address":"1314 Main St",
    "sg:city":"Leominster",
    "sg:classifiers":[
        {
            "category":"Restaurant",
            "type":"Food & Drink"
        }
    ],
    "sg:phone":"+1 978 343 7722",
    "sg:postcode":"01453",
    "sg:province":"MA",
    "sg:tags":[
        "pizza"
    ],
    "wof:name":"Village House Of Pizza",
    "wof:placetype":"venue"
},
  "geometry": {"coordinates":[-71.747471,42.566266],"type":"Point"}
}