{
  "type": "Feature",
  "properties": {
    "iso:country":"US",
    "sg:address":"57 Washington St",
    "sg:city":"Natick",
    "sg:classifiers":[
        {
            "category":"Banks & Credit Unions",
            "subcategory":"Investment Brokerage",
            "type":"Services"
        }
    ],
    "sg:phone":"+1 508 651 2008",
    "sg:postcode":"01760",
    "sg:province":"MA",
    "sg:tags":[
        "advisory",
        "financial"
    ],
    "wof:name":"Icon Capital Corp",
    "wof:placetype":"venue"
},
  "geometry": {"coordinates":[-71.347157,42.289236],"type":"Point"}
}