{
  "type": "Feature",
  "properties": {
    "iso:country":"US",
    "sg:address":"906 Main St",
    "sg:city":"Williamstown",
    "sg:classifiers":[
        {
            "category":"Organizations",
            "subcategory":"Religious Organization",
            "type":"Services"
        }
    ],
    "sg:phone":"+1 413 458 4273",
    "sg:postcode":"01267",
    "sg:province":"MA",
    "sg:tags":[
        "church"
    ],
    "wof:name":"First Cong Church",
    "wof:placetype":"venue"
},
  "geometry": {"coordinates":[-73.203626,42.712365],"type":"Point"}
}