{
  "type": "Feature",
  "properties": {
    "addr:full": "103 Nagog Park Acton MA 01720",
    "addr:housenumber": "103",
    "addr:postcode": "01720",
    "addr:street": "Nagog Park",
    "iso:country": "US",
    "sg:address": "103 Nagog Park",
    "sg:city": "Acton",
    "sg:classifiers": [
      {
        "category": "Restaurant",
        "type": "Food \u0026 Drink"
      }
    ],
    "sg:phone": "+1   ",
    "sg:postcode": "01720",
    "sg:province": "MA",
    "wof:name": "Sichuan Pavilion Inc",
    "wof:placetype": "venue"
  },
  "geometry": {"coordinates":[-71.421692,42.522415],"type":"Point"}
}
