{
  "type": "Feature",
  "properties": {
    "iso:country":"US",
    "sg:address":"12 Irving St",
    "sg:city":"Framingham",
    "sg:classifiers":[
        {
            "category":"Professional",
            "subcategory":"Lawyer & Legal Services",
            "type":"Services"
        }
    ],
    "sg:phone":"+1 508 820 0408",
    "sg:postcode":"01702",
    "sg:province":"MA",
    "sg:tags":[
        "naturalization",
        "immigration"
    ],
    "wof:name":"Catholic Legal Immigration",
    "wof:placetype":"venue"
},
  "geometry": {"coordinates":[-71.415998,42.275825],"type":"Point"}
}