{
  "type": "Feature",
  "properties": {
    "addr:full":"31 Collins Street Ter Lynn MA 01902",
    "addr:housenumber":"31",
    "addr:postcode":"01902",
    "addr:street":"Collins Street Ter",
    "iso:country":"US",
    "sg:address":"31 Collins Street Ter",
    "sg:city":"Lynn",
    "sg:classifiers":[
        {
            "category":"Real Estate",
            "subcategory":"Real Estate Agent",
            "type":"Services"
        }
    ],
    "sg:phone":"+1   ",
    "sg:postcode":"01902",
    "sg:province":"MA",
    "wof:name":"Central Plaza Associates Inc",
    "wof:placetype":"venue"
},
  "geometry": {"coordinates":[-70.937585,42.472169],"type":"Point"}
}