{
  "type": "Feature",
  "properties": {
    "addr:full": "396 Gifford St Falmouth MA 02540",
    "addr:housenumber": "396",
    "addr:postcode": "02540",
    "addr:street": "Gifford St",
    "iso:country": "US",
    "ovtr:label": "Lawrence-Lynch Corp, 396 Gifford St Falmouth MA US",
    "ovtr:similarity": 2.1703169345855713,
    "sg:address": "396 Gifford St",
    "sg:city": "Falmouth",
    "sg:classifiers": [
      {
        "category": "Building \u0026 Trades",
        "subcategory": "Construction",
        "type": "Services"
      }
    ],
    "sg:phone": "+1 508 444 8152",
    "sg:postcode": "02540",
    "sg:province": "MA",
    "sg:tags": [
      "contractor",
      "driveway",
      "paving"
    ],
    "sg:website": "http://www.lawrencelynch.com",
    "wof:name": "Lawrence-Lynch Corp",
    "wof:placetype": "venue"
  },
  "geometry": {"coordinates":[-70.609012,41.565541],"type":"Point"}
}
