{
  "type": "Feature",
  "properties": {
    "iso:country":"US",
    "sg:address":"400 Linebrook Rd",
    "sg:city":"Ipswich",
    "sg:classifiers":[
        {
            "category":"Professional",
            "subcategory":"Art Services",
            "type":"Services"
        }
    ],
    "sg:phone":"+1   ",
    "sg:postcode":"01938",
    "sg:province":"MA",
    "sg:tags":[
        "commercial",
        "design"
    ],
    "wof:name":"Anne Graham Graphic Design",
    "wof:placetype":"venue"
},
  "geometry": {"coordinates":[-70.936779,42.675875],"type":"Point"}
}