{
  "type": "Feature",
  "properties": {
    "addr:full":"71 Fuller Brook Ave Needham MA 02492",
    "addr:housenumber":"71",
    "addr:postcode":"02492",
    "addr:street":"Fuller Brook Ave",
    "iso:country":"US",
    "sg:address":"71 Fuller Brook Ave",
    "sg:city":"Needham",
    "sg:classifiers":[
        {
            "category":"Professional",
            "type":"Services"
        }
    ],
    "sg:phone":"+1   ",
    "sg:postcode":"02492",
    "sg:province":"MA",
    "wof:name":"Daniel L Lintz Inc",
    "wof:placetype":"venue"
},
  "geometry": {"coordinates":[-71.260373,42.287902],"type":"Point"}
}