{
  "type": "Feature",
  "properties": {
    "addr:full": "373 River St Haverhill MA 01832",
    "addr:housenumber": "373",
    "addr:postcode": "01832",
    "addr:street": "River St",
    "iso:country": "US",
    "sg:address": "373 River St",
    "sg:city": "Haverhill",
    "sg:classifiers": [
      {
        "category": "Wholesale",
        "subcategory": "Apparel",
        "type": "Manufacturing \u0026 Wholesale Goods"
      }
    ],
    "sg:phone": "+1 978 372 5321",
    "sg:postcode": "01832",
    "sg:province": "MA",
    "sg:tags": [
      "embroidery"
    ],
    "sg:website": "www.leisureline.com",
    "wof:name": "Leisure Line Custom Embroidery",
    "wof:placetype": "venue"
  },
  "geometry": {"coordinates":[-71.096143,42.766322],"type":"Point"}
}
