{
  "type": "Feature",
  "properties": {
    "addr:full":"603 Tremont St Boston MA 02118",
    "addr:housenumber":"603",
    "addr:postcode":"02118",
    "addr:street":"Tremont St",
    "iso:country":"US",
    "sg:address":"603 Tremont St",
    "sg:city":"Boston",
    "sg:classifiers":[
        {
            "category":"Arts & Performance",
            "subcategory":"Theater",
            "type":"Entertainment"
        }
    ],
    "sg:phone":"+1 617 859 9779",
    "sg:postcode":"02118",
    "sg:province":"MA",
    "sg:tags":[
        "entertainer",
        "family"
    ],
    "wof:name":"Clay Room",
    "wof:placetype":"venue"
},
  "geometry": {"coordinates":[-71.07345599999999,42.343147],"type":"Point"}
}