{
  "type": "Feature",
  "properties": {
    "addr:full":"221 King St Northampton MA 01060",
    "addr:housenumber":"221",
    "addr:postcode":"01060",
    "addr:street":"King St",
    "iso:country":"US",
    "sg:address":"221 King St",
    "sg:city":"Northampton",
    "sg:classifiers":[
        {
            "category":"Restaurant",
            "type":"Food & Drink"
        }
    ],
    "sg:menulink":"http://www.allmenus.com/ma/northampton/188679-mcdonalds/menu/",
    "sg:postcode":"01060",
    "sg:province":"MA",
    "sg:tags":[
        "burger",
        "american"
    ],
    "wof:name":"McDonald's",
    "wof:placetype":"venue"
},
  "geometry": {"coordinates":[-72.633475,42.327689],"type":"Point"}
}