{
  "type": "Feature",
  "properties": {
    "iso:country":"US",
    "sg:address":"62 Washington St",
    "sg:city":"Brighton",
    "sg:classifiers":[
        {
            "category":"Building & Trades",
            "subcategory":"Locksmith",
            "type":"Services"
        }
    ],
    "sg:phone":"+1 617 415 9075",
    "sg:postcode":"02135",
    "sg:province":"MA",
    "sg:tags":[
        "key"
    ],
    "wof:name":"Anytime Any Place Locksmith",
    "wof:placetype":"venue"
},
  "geometry": {"coordinates":[-71.14266000000001,42.343447],"type":"Point"}
}