{
  "type": "Feature",
  "properties": {
    "addr:full": "62 Washington St Brighton MA 02135",
    "addr:housenumber": "62",
    "addr:postcode": "02135",
    "addr:street": "Washington St",
    "iso:country": "US",
    "sg:address": "62 Washington St",
    "sg:city": "Brighton",
    "sg:classifiers": [
      {
        "category": "Building \u0026 Trades",
        "subcategory": "Locksmith",
        "type": "Services"
      }
    ],
    "sg:phone": "+1 617 415 9075",
    "sg:postcode": "02135",
    "sg:province": "MA",
    "sg:tags": [
      "key"
    ],
    "wof:name": "Anytime Any Place Locksmith",
    "wof:placetype": "venue"
  },
  "geometry": {"coordinates":[-71.14266,42.343447],"type":"Point"}
}
