{
  "type": "Feature",
  "properties": {
    "addr:full": "154 Grove St Chicopee MA 01020",
    "addr:housenumber": "154",
    "addr:postcode": "01020",
    "addr:street": "Grove St",
    "iso:country": "US",
    "sg:address": "154 Grove St",
    "sg:city": "Chicopee",
    "sg:classifiers": [
      {
        "category": "Professional",
        "type": "Services"
      }
    ],
    "sg:phone": "+1 413 592 0700",
    "sg:postcode": "01020",
    "sg:province": "MA",
    "sg:tags": [
      "establishment"
    ],
    "wof:name": "Milestone LLC",
    "wof:placetype": "venue"
  },
  "geometry": {"coordinates":[-72.584586,42.153818],"type":"Point"}
}
