{
  "type": "Feature",
  "properties": {
    "addr:full":"285 Main St Shrewsbury MA 01545",
    "addr:housenumber":"285",
    "addr:postcode":"01545",
    "addr:street":"Main St",
    "iso:country":"US",
    "sg:address":"285 Main St",
    "sg:city":"Shrewsbury",
    "sg:classifiers":[
        {
            "category":"Communications",
            "subcategory":"Film & Video Production",
            "type":"Services"
        }
    ],
    "sg:phone":"+1   ",
    "sg:postcode":"01545",
    "sg:province":"MA",
    "sg:tags":[
        "motion"
    ],
    "wof:name":"Hye Meadow Productions Inc",
    "wof:placetype":"venue"
},
  "geometry": {"coordinates":[-71.73768200000001,42.291865],"type":"Point"}
}