{
  "type": "Feature",
  "properties": {
    "iso:country":"US",
    "sg:address":"28 Griffin Rd",
    "sg:city":"Framingham",
    "sg:classifiers":[
        {
            "category":"Building & Trades",
            "subcategory":"Construction",
            "type":"Services"
        }
    ],
    "sg:phone":"+1 508 309 6959",
    "sg:postcode":"01701",
    "sg:province":"MA",
    "sg:tags":[
        "wallcoverings-installation",
        "wallpaper",
        "painting",
        "contractor"
    ],
    "wof:name":"Leslie Gorman Dbad & E Painting",
    "wof:placetype":"venue"
},
  "geometry": {"coordinates":[-71.40469400000001,42.335899],"type":"Point"}
}