{
  "type": "Feature",
  "properties": {
    "addr:full": "1071 Worcester Rd Framingham MA 01701",
    "addr:housenumber": "1071",
    "addr:postcode": "01701",
    "addr:street": "Worcester Rd",
    "iso:country": "US",
    "sg:address": "1071 Worcester Rd",
    "sg:city": "Framingham",
    "sg:classifiers": [
      {
        "category": "Health Services",
        "subcategory": "Optometrist",
        "type": "Services"
      }
    ],
    "sg:phone": "+1 508 875 7900",
    "sg:postcode": "01701",
    "sg:province": "MA",
    "wof:name": "Massachusetts Society-Optmtrst",
    "wof:placetype": "venue"
  },
  "geometry": {"coordinates":[-71.441876,42.299448],"type":"Point"}
}
