{
  "type": "Feature",
  "properties": {
    "iso:country":"US",
    "sg:address":"3 Smith Rd",
    "sg:city":"Mansfield",
    "sg:classifiers":[
        {
            "category":"Building & Trades",
            "subcategory":"Construction",
            "type":"Services"
        }
    ],
    "sg:phone":"+1 508 339 3044",
    "sg:postcode":"02048",
    "sg:province":"MA",
    "sg:tags":[
        "wallcoverings-installation",
        "wallpaper",
        "painting",
        "contractor"
    ],
    "wof:name":"Coyne Painting",
    "wof:placetype":"venue"
},
  "geometry": {"coordinates":[-71.25681299999999,42.012733],"type":"Point"}
}