{
  "type": "Feature",
  "properties": {
    "addr:full": "3 Smith Rd Mansfield MA 02048",
    "addr:housenumber": "3",
    "addr:postcode": "02048",
    "addr:street": "Smith Rd",
    "iso:country": "US",
    "sg:address": "3 Smith Rd",
    "sg:city": "Mansfield",
    "sg:classifiers": [
      {
        "category": "Building \u0026 Trades",
        "subcategory": "Construction",
        "type": "Services"
      }
    ],
    "sg:phone": "+1 508 339 3044",
    "sg:postcode": "02048",
    "sg:province": "MA",
    "sg:tags": [
      "wallcoverings-installation",
      "wallpaper",
      "painting",
      "contractor"
    ],
    "wof:name": "Coyne Painting",
    "wof:placetype": "venue"
  },
  "geometry": {"coordinates":[-71.256813,42.012733],"type":"Point"}
}
