{
  "type": "Feature",
  "properties": {
    "addr:full":"81 Edgewater Rd Hull MA 02045",
    "addr:housenumber":"81",
    "addr:postcode":"02045",
    "addr:street":"Edgewater Rd",
    "iso:country":"US",
    "sg:address":"81 Edgewater Rd",
    "sg:city":"Hull",
    "sg:classifiers":[
        {
            "category":"Arena",
            "subcategory":"Sports Club",
            "type":"Entertainment"
        }
    ],
    "sg:phone":"+1 781 925 4313",
    "sg:postcode":"02045",
    "sg:province":"MA",
    "sg:tags":[
        "health"
    ],
    "wof:name":"Fitness Solutions",
    "wof:placetype":"venue"
},
  "geometry": {"coordinates":[-70.87308899999999,42.27635],"type":"Point"}
}