{
  "type": "Feature",
  "properties": {
    "addr:full":"121 Duchaine Blvd New Bedford MA 02745",
    "addr:housenumber":"121",
    "addr:postcode":"02745",
    "addr:street":"Duchaine Blvd",
    "iso:country":"US",
    "sg:address":"121 Duchaine Blvd",
    "sg:city":"New Bedford",
    "sg:classifiers":[
        {
            "category":"Wholesale",
            "subcategory":"Machinery & Supplies",
            "type":"Manufacturing & Wholesale Goods"
        }
    ],
    "sg:phone":"+1 508 995 8331",
    "sg:postcode":"02745",
    "sg:province":"MA",
    "sg:tags":[
        "janitor"
    ],
    "sg:website":"www.milhench.com",
    "wof:name":"Milhench Supply Co",
    "wof:placetype":"venue"
},
  "geometry": {"coordinates":[-70.952946,41.720622],"type":"Point"}
}