{
  "type": "Feature",
  "properties": {
    "addr:full": "2304 Washington St Roxbury MA 02119",
    "addr:housenumber": "2304",
    "addr:postcode": "02119",
    "addr:street": "Washington St",
    "iso:country": "US",
    "sg:address": "2304 Washington St",
    "sg:city": "Roxbury",
    "sg:classifiers": [
      {
        "category": "Shopping",
        "subcategory": "Clothing, Apparel, \u0026 Fashions",
        "type": "Retail Goods"
      }
    ],
    "sg:phone": "+1 617 442 0849",
    "sg:postcode": "02119",
    "sg:province": "MA",
    "wof:name": "Manhattan Square Fashions",
    "wof:placetype": "venue"
  },
  "geometry": {"coordinates":[-71.084335,42.329959],"type":"Point"}
}
