{
  "type": "Feature",
  "properties": {
    "addr:full":"50 Sprague St Hyde Park MA 02136",
    "addr:housenumber":"50",
    "addr:postcode":"02136",
    "addr:street":"Sprague St",
    "iso:country":"US",
    "sg:address":"50 Sprague St",
    "sg:city":"Hyde Park",
    "sg:classifiers":[
        {
            "category":"Building & Trades",
            "subcategory":"Construction",
            "type":"Services"
        }
    ],
    "sg:phone":"+1 617 364 5800",
    "sg:postcode":"02136",
    "sg:province":"MA",
    "sg:tags":[
        "general",
        "contractor"
    ],
    "sg:website":"www.pgioioso.com",
    "wof:name":"P Gioioso & Sons Inc",
    "wof:placetype":"venue"
},
  "geometry": {"coordinates":[-71.13656400000001,42.236083],"type":"Point"}
}