{
  "type": "Feature",
  "properties": {
    "addr:full":"127 Padelford St Berkley MA 02779",
    "addr:housenumber":"127",
    "addr:postcode":"02779",
    "addr:street":"Padelford St",
    "iso:country":"US",
    "sg:address":"127 Padelford St",
    "sg:city":"Berkley",
    "sg:classifiers":[
        {
            "category":"Building & Trades",
            "subcategory":"Landscaping Services",
            "type":"Services"
        }
    ],
    "sg:phone":"+1 508 880 8855",
    "sg:postcode":"02779",
    "sg:province":"MA",
    "sg:tags":[
        "landscape",
        "contractor"
    ],
    "wof:name":"Professional Landscaping",
    "wof:placetype":"venue"
},
  "geometry": {"coordinates":[-71.041335,41.839644],"type":"Point"}
}