{
  "type": "Feature",
  "properties": {
    "iso:country":"US",
    "sg:address":"11 Miller St",
    "sg:city":"Medfield",
    "sg:classifiers":[
        {
            "category":"Professional",
            "subcategory":"Advertising",
            "type":"Services"
        }
    ],
    "sg:phone":"+1   ",
    "sg:postcode":"02052",
    "sg:province":"MA",
    "sg:tags":[
        "agency"
    ],
    "wof:name":"L J Miller Associates",
    "wof:placetype":"venue"
},
  "geometry": {"coordinates":[-71.30366100000001,42.184038],"type":"Point"}
}