{
  "type": "Feature",
  "properties": {
    "addr:full": "1050 Main St Brockton MA 02301",
    "addr:housenumber": "1050",
    "addr:postcode": "02301",
    "addr:street": "Main St",
    "iso:country": "US",
    "sg:address": "1050 Main St",
    "sg:city": "Brockton",
    "sg:classifiers": [
      {
        "category": "Banks \u0026 Credit Unions",
        "subcategory": "Bank",
        "type": "Services"
      }
    ],
    "sg:phone": "+1 508 427 4743",
    "sg:postcode": "02301",
    "sg:province": "MA",
    "sg:tags": [
      "cashing",
      "check"
    ],
    "wof:name": "Larapidita Corp",
    "wof:placetype": "venue"
  },
  "geometry": {"coordinates":[-71.015701,42.064501],"type":"Point"}
}
