{
  "type": "Feature",
  "properties": {
    "addr:full":"82 Suffolk St 1 Chelsea MA 02150",
    "addr:housenumber":"82;1",
    "addr:postcode":"02150",
    "addr:street":"Suffolk St",
    "iso:country":"US",
    "sg:address":"82 Suffolk St 1",
    "sg:city":"Chelsea",
    "sg:classifiers":[
        {
            "category":"Shopping",
            "subcategory":"Used Merchandise",
            "type":"Retail Goods"
        }
    ],
    "sg:phone":"+1 617 889 0545",
    "sg:postcode":"02150",
    "sg:province":"MA",
    "sg:tags":[
        "resale",
        "shop"
    ],
    "wof:name":"Esmeralda Fashion",
    "wof:placetype":"venue"
},
  "geometry": {"coordinates":[-71.032715,42.387093],"type":"Point"}
}