{
  "type": "Feature",
  "properties": {
    "iso:country":"US",
    "sg:address":"27 Riverside Ave",
    "sg:city":"Medford",
    "sg:phone":"+1 781 391 5606",
    "sg:postcode":"02155",
    "sg:province":"MA",
    "sg:website":"http://www.tokyoseoulrestaurant.com",
    "wof:name":"Chung Ki Wa Restaurant",
    "wof:placetype":"venue"
},
  "geometry": {"coordinates":[-71.10887700000001,42.41801],"type":"Point"}
}