{
  "type": "Feature",
  "properties": {
    "iso:country":"US",
    "sg:address":"1313 Water St",
    "sg:city":"Fitchburg",
    "sg:classifiers":[
        {
            "category":"Autos & Motor Vehicles",
            "subcategory":"Fuel & Gas Station",
            "type":"Retail Goods"
        }
    ],
    "sg:phone":"+1 978 342 5672",
    "sg:postcode":"01420",
    "sg:province":"MA",
    "sg:tags":[
        "oil"
    ],
    "wof:name":"Fitchburg Mobil",
    "wof:placetype":"venue"
},
  "geometry": {"coordinates":[-71.779471,42.562003],"type":"Point"}
}