{
  "type": "Feature",
  "properties": {
    "addr:full": "251 Broadway Lawrence MA 01841",
    "addr:housenumber": "251",
    "addr:postcode": "01841",
    "addr:street": "Broadway",
    "iso:country": "US",
    "sg:address": "251 Broadway",
    "sg:city": "Lawrence",
    "sg:classifiers": [
      {
        "category": "Professional",
        "subcategory": "Business Services",
        "type": "Services"
      }
    ],
    "sg:phone": "+1 978 725 6597",
    "sg:postcode": "01841",
    "sg:province": "MA",
    "sg:tags": [
      "water",
      "treatment"
    ],
    "wof:name": "Super Plastic Cover",
    "wof:placetype": "venue"
  },
  "geometry": {"coordinates":[-71.171584,42.708994],"type":"Point"}
}
