{
  "type": "Feature",
  "properties": {
    "addr:full":"40 Merrimack St Haverhill MA 01830",
    "addr:housenumber":"40",
    "addr:postcode":"01830",
    "addr:street":"Merrimack St",
    "iso:country":"US",
    "sg:address":"40 Merrimack St",
    "sg:city":"Haverhill",
    "sg:classifiers":[
        {
            "category":"Home & Garden",
            "subcategory":"Furniture",
            "type":"Retail Goods"
        }
    ],
    "sg:phone":"+1 978 372 1261",
    "sg:postcode":"01830",
    "sg:province":"MA",
    "wof:name":"Newman's Discount Furn Wrhse",
    "wof:placetype":"venue"
},
  "geometry": {"coordinates":[-71.077395,42.774828],"type":"Point"}
}