{
  "type": "Feature",
  "properties": {
    "addr:full": "97 Depot St Bellingham MA 02019",
    "addr:housenumber": "97",
    "addr:postcode": "02019",
    "addr:street": "Depot St",
    "iso:country": "US",
    "sg:address": "97 Depot St",
    "sg:city": "Bellingham",
    "sg:classifiers": [
      {
        "category": "Manufacturing",
        "subcategory": "Tools \u0026 Machinery",
        "type": "Manufacturing \u0026 Wholesale Goods"
      }
    ],
    "sg:phone": "+1 508 966 0733",
    "sg:postcode": "02019",
    "sg:province": "MA",
    "sg:tags": [
      "machine",
      "shop"
    ],
    "wof:name": "Van-Wal Machine Inc",
    "wof:placetype": "venue"
  },
  "geometry": {"coordinates":[-71.48325,42.09497],"type":"Point"}
}
