{
  "type": "Feature",
  "properties": {
    "addr:full":"35 Jackson St Lawrence MA 01840",
    "addr:housenumber":"35",
    "addr:postcode":"01840",
    "addr:street":"Jackson St",
    "iso:country":"US",
    "sg:address":"35 Jackson St",
    "sg:city":"Lawrence",
    "sg:classifiers":[
        {
            "category":"Organizations",
            "subcategory":"Non-profit Organization",
            "type":"Services"
        }
    ],
    "sg:phone":"+1 978 681 8858",
    "sg:postcode":"01840",
    "sg:province":"MA",
    "sg:tags":[
        "human"
    ],
    "wof:name":"Habitat For Humanity",
    "wof:placetype":"venue"
},
  "geometry": {"coordinates":[-71.15789100000001,42.708487],"type":"Point"}
}