{
  "type": "Feature",
  "properties": {
    "addr:full":"150 Great Rd Acton MA 01720",
    "addr:housenumber":"150",
    "addr:postcode":"01720",
    "addr:street":"Great Rd",
    "iso:country":"US",
    "sg:address":"150 Great Rd",
    "sg:city":"Acton",
    "sg:classifiers":[
        {
            "category":"Professional",
            "subcategory":"Computer Services",
            "type":"Services"
        }
    ],
    "sg:phone":"+1 978 461 0400",
    "sg:postcode":"01720",
    "sg:province":"MA",
    "sg:tags":[
        "repair"
    ],
    "sg:website":"www.drivetech.net",
    "wof:name":"Drivetech",
    "wof:placetype":"venue"
},
  "geometry": {"coordinates":[-71.413766,42.478406],"type":"Point"}
}