{
  "type": "Feature",
  "properties": {
    "iso:country":"US",
    "sg:address":"346 N Main St",
    "sg:city":"Randolph",
    "sg:classifiers":[
        {
            "category":"Restaurant",
            "type":"Food & Drink"
        }
    ],
    "sg:phone":"+1 781 961 5337",
    "sg:postcode":"02368",
    "sg:province":"MA",
    "sg:tags":[
        "chinese"
    ],
    "wof:name":"Ming Restaurant",
    "wof:placetype":"venue"
},
  "geometry": {"coordinates":[-71.045519,42.169164],"type":"Point"}
}