{
  "type": "Feature",
  "properties": {
    "iso:country":"US",
    "sg:address":"100 State St",
    "sg:city":"Whately",
    "sg:classifiers":[
        {
            "category":"Building & Trades",
            "subcategory":"Construction",
            "type":"Services"
        }
    ],
    "sg:phone":"+1 413 665 2237",
    "sg:postcode":"01069",
    "sg:province":"MA",
    "sg:tags":[
        "demolition",
        "contractor"
    ],
    "wof:name":"Pioneer Supply Corp",
    "wof:placetype":"venue"
},
  "geometry": {"coordinates":[-72.33928,42.209053],"type":"Point"}
}