{
  "type": "Feature",
  "properties": {
    "addr:full": "100 State St Whately MA 01069",
    "addr:housenumber": "100",
    "addr:postcode": "01069",
    "addr:street": "State St",
    "iso:country": "US",
    "sg:address": "100 State St",
    "sg:city": "Whately",
    "sg:classifiers": [
      {
        "category": "Building \u0026 Trades",
        "subcategory": "Construction",
        "type": "Services"
      }
    ],
    "sg:phone": "+1 413 665 2237",
    "sg:postcode": "01069",
    "sg:province": "MA",
    "sg:tags": [
      "demolition",
      "contractor"
    ],
    "wof:name": "Pioneer Supply Corp",
    "wof:placetype": "venue"
  },
  "geometry": {"coordinates":[-72.33928,42.209053],"type":"Point"}
}
