{
  "type": "Feature",
  "properties": {
    "addr:full":"96 Newland Ave Bellingham MA 02019",
    "addr:housenumber":"96",
    "addr:postcode":"02019",
    "addr:street":"Newland Ave",
    "iso:country":"US",
    "sg:address":"96 Newland Ave",
    "sg:city":"Bellingham",
    "sg:classifiers":[
        {
            "category":"Personal",
            "type":"Services"
        }
    ],
    "sg:phone":"+1 508 883 3800",
    "sg:postcode":"02019",
    "sg:province":"MA",
    "sg:tags":[
        "therapist",
        "massage"
    ],
    "wof:name":"Massage Heaven",
    "wof:placetype":"venue"
},
  "geometry": {"coordinates":[-71.483076,42.03927],"type":"Point"}
}