{
  "type": "Feature",
  "properties": {
    "iso:country":"US",
    "sg:address":"1299 Cambridge St",
    "sg:city":"Cambridge",
    "sg:classifiers":[
        {
            "category":"Shopping",
            "subcategory":"Books",
            "type":"Retail Goods"
        }
    ],
    "sg:phone":"+1 617 497 7669",
    "sg:postcode":"02139",
    "sg:province":"MA",
    "sg:tags":[
        "bookstore"
    ],
    "sg:website":"www.loremipsumbooks.com",
    "wof:name":"Lorem Ipsum Books",
    "wof:placetype":"venue"
},
  "geometry": {"coordinates":[-71.099136,42.37353],"type":"Point"}
}