{
  "type": "Feature",
  "properties": {
    "iso:country":"US",
    "sg:address":"47 Maple St",
    "sg:city":"Mansfield",
    "sg:classifiers":[
        {
            "category":"Freight",
            "type":"Transportation"
        }
    ],
    "sg:phone":"+1 508 261 1199",
    "sg:postcode":"02048",
    "sg:province":"MA",
    "sg:tags":[
        "trucking"
    ],
    "wof:name":"Universal Logistics Svc",
    "wof:placetype":"venue"
},
  "geometry": {"coordinates":[-71.21052,42.04223],"type":"Point"}
}