{
  "type": "Feature",
  "properties": {
    "iso:country":"US",
    "sg:address":"22 Rhodes Cir",
    "sg:city":"Hingham",
    "sg:classifiers":[
        {
            "category":"Building & Trades",
            "subcategory":"Construction",
            "type":"Services"
        }
    ],
    "sg:phone":"+1   ",
    "sg:postcode":"02043",
    "sg:province":"MA",
    "sg:tags":[
        "hanging",
        "contractor"
    ],
    "wof:name":"Commesso Painting",
    "wof:placetype":"venue"
},
  "geometry": {"coordinates":[-70.91266,42.245571],"type":"Point"}
}