{
  "type": "Feature",
  "properties": {
    "addr:full":"22 Rhodes Cir Hingham MA 02043",
    "addr:housenumber":"22",
    "addr:postcode":"02043",
    "addr:street":"Rhodes Cir",
    "iso:country":"US",
    "sg:address":"22 Rhodes Cir",
    "sg:city":"Hingham",
    "sg:classifiers":[
        {
            "category":"Building & Trades",
            "subcategory":"Construction",
            "type":"Services"
        }
    ],
    "sg:phone":"+1   ",
    "sg:postcode":"02043",
    "sg:province":"MA",
    "sg:tags":[
        "hanging",
        "contractor"
    ],
    "wof:name":"Commesso Painting",
    "wof:placetype":"venue"
},
  "geometry": {"coordinates":[-70.91266,42.245571],"type":"Point"}
}