{
  "type": "Feature",
  "properties": {
    "addr:full":"51 Main St Ste 2 Hyannis MA 02601",
    "addr:housenumber":"51",
    "addr:postcode":"02601",
    "addr:street":"Main St Ste 2",
    "iso:country":"US",
    "sg:address":"51 Main St Ste 2",
    "sg:city":"Hyannis",
    "sg:classifiers":[
        {
            "category":"Health Services",
            "subcategory":"Doctor",
            "type":"Services"
        }
    ],
    "sg:phone":"+1 508 775 3112",
    "sg:postcode":"02601",
    "sg:province":"MA",
    "wof:name":"Cavanaugh James J A",
    "wof:placetype":"venue"
},
  "geometry": {"coordinates":[-70.27258,41.656468],"type":"Point"}
}