{
  "type": "Feature",
  "properties": {
    "addr:full":"3 5th St Natick MA 01760",
    "addr:housenumber":"3",
    "addr:postcode":"01760",
    "addr:street":"5Th St",
    "iso:country":"US",
    "sg:address":"3 5th St",
    "sg:city":"Natick",
    "sg:classifiers":[
        {
            "category":"Building & Trades",
            "subcategory":"Construction",
            "type":"Services"
        }
    ],
    "sg:phone":"+1   ",
    "sg:postcode":"01760",
    "sg:province":"MA",
    "sg:tags":[
        "contractor"
    ],
    "wof:name":"Ferrera Masonry",
    "wof:placetype":"venue"
},
  "geometry": {"coordinates":[-71.36634599999999,42.292965],"type":"Point"}
}