{
  "type": "Feature",
  "properties": {
    "iso:country":"US",
    "sg:address":"407 West St",
    "sg:city":"Ludlow",
    "sg:classifiers":[
        {
            "category":"Autos & Motor Vehicles",
            "subcategory":"Automobile Sales",
            "type":"Retail Goods"
        },
        {
            "category":"Retail",
            "subcategory":"Auto Repair",
            "type":"Services"
        }
    ],
    "sg:phone":"+1 413 547 6005",
    "sg:postcode":"01056",
    "sg:province":"MA",
    "sg:tags":[
        "dealers-used",
        "car",
        "used",
        "cars-wholesale"
    ],
    "wof:name":"Gillespie Car Care",
    "wof:placetype":"venue"
},
  "geometry": {"coordinates":[-72.50473,42.186401],"type":"Point"}
}