{
  "type": "Feature",
  "properties": {
    "iso:country":"US",
    "sg:address":"15 Oliver St",
    "sg:city":"Fitchburg",
    "sg:classifiers":[
        {
            "category":"Real Estate",
            "subcategory":"Architect",
            "type":"Services"
        }
    ],
    "sg:phone":"+1   ",
    "sg:postcode":"01420",
    "sg:province":"MA",
    "sg:tags":[
        "architectural"
    ],
    "wof:name":"Ssd Asscociates",
    "wof:placetype":"venue"
},
  "geometry": {"coordinates":[-71.79956799999999,42.583517],"type":"Point"}
}