{
  "type": "Feature",
  "properties": {
    "addr:full":"66 Shawsheen Rd Billerica MA 01821",
    "addr:housenumber":"66",
    "addr:postcode":"01821",
    "addr:street":"Shawsheen Rd",
    "iso:country":"US",
    "sg:address":"66 Shawsheen Rd",
    "sg:city":"Billerica",
    "sg:classifiers":[
        {
            "category":"Building & Trades",
            "subcategory":"Locksmith",
            "type":"Services"
        }
    ],
    "sg:phone":"+1 978 901 6018",
    "sg:postcode":"01821",
    "sg:province":"MA",
    "sg:tags":[
        "key"
    ],
    "wof:name":"Locksmith In",
    "wof:placetype":"venue"
},
  "geometry": {"coordinates":[-71.238753,42.525537],"type":"Point"}
}