{
  "type": "Feature",
  "properties": {
    "addr:full":"225 Boston Post Rd W Marlborough MA 01752",
    "addr:housenumber":"225",
    "addr:postcode":"01752",
    "addr:street":"Boston Post Rd W",
    "iso:country":"US",
    "sg:address":"225 Boston Post Rd W",
    "sg:city":"Marlborough",
    "sg:classifiers":[
        {
            "category":"Personal",
            "type":"Services"
        },
        {
            "category":"Arena",
            "subcategory":"Sports Club",
            "type":"Entertainment"
        }
    ],
    "sg:phone":"+1 508 786 3000",
    "sg:postcode":"01752",
    "sg:province":"MA",
    "sg:tags":[
        "trainer",
        "consultant",
        "physical",
        "health",
        "fitness"
    ],
    "wof:name":"Planet Fitness",
    "wof:placetype":"venue"
},
  "geometry": {"coordinates":[-71.59169199999999,42.338147],"type":"Point"}
}