{
  "type": "Feature",
  "properties": {
    "addr:full":"1620 Purchase St New Bedford MA 02740",
    "addr:housenumber":"1620",
    "addr:postcode":"02740",
    "addr:street":"Purchase St",
    "iso:country":"US",
    "sg:address":"1620 Purchase St",
    "sg:city":"New Bedford",
    "sg:classifiers":[
        {
            "category":"Professional",
            "type":"Services"
        }
    ],
    "sg:phone":"+1 508 996 3966",
    "sg:postcode":"02740",
    "sg:province":"MA",
    "sg:tags":[
        "establishment"
    ],
    "wof:name":"Parts Plus",
    "wof:placetype":"venue"
},
  "geometry": {"coordinates":[-70.928274,41.647672],"type":"Point"}
}