{
  "type": "Feature",
  "properties": {
    "iso:country":"US",
    "sg:address":"10 Speare Pl",
    "sg:city":"Boston",
    "sg:classifiers":[
        {
            "category":"Restaurant",
            "type":"Food & Drink"
        }
    ],
    "sg:phone":"+1   ",
    "sg:postcode":"02115",
    "sg:province":"MA",
    "sg:tags":[
        "eating"
    ],
    "wof:name":"Neu Catering Department",
    "wof:placetype":"venue"
},
  "geometry": {"coordinates":[-71.089696,42.340878],"type":"Point"}
}