{
  "type": "Feature",
  "properties": {
    "addr:full":"367 Court St Plymouth MA 02360",
    "addr:housenumber":"367",
    "addr:postcode":"02360",
    "addr:street":"Court St",
    "iso:country":"US",
    "sg:address":"367 Court St",
    "sg:city":"Plymouth",
    "sg:classifiers":[
        {
            "category":"Food & Beverages",
            "subcategory":"Groceries & Convenience Stores",
            "type":"Retail Goods"
        }
    ],
    "sg:phone":"+1 508 747 1178",
    "sg:postcode":"02360",
    "sg:province":"MA",
    "wof:name":"7-Eleven",
    "wof:placetype":"venue"
},
  "geometry": {"coordinates":[-70.688827,41.977816],"type":"Point"}
}