{
  "type": "Feature",
  "properties": {
    "addr:full":"416 Commonwealth Ave Boston MA 02215",
    "addr:housenumber":"416",
    "addr:postcode":"02215",
    "addr:street":"Commonwealth Ave",
    "iso:country":"US",
    "sg:address":"416 Commonwealth Ave",
    "sg:city":"Boston",
    "sg:classifiers":[
        {
            "category":"Health Services",
            "subcategory":"Clinic",
            "type":"Services"
        }
    ],
    "sg:phone":"+1 617 266 1146",
    "sg:postcode":"02215",
    "sg:province":"MA",
    "sg:tags":[
        "counseling",
        "mental"
    ],
    "wof:name":"Spitalny Gloria Edd",
    "wof:placetype":"venue"
},
  "geometry": {"coordinates":[-71.089996,42.3489],"type":"Point"}
}