{
  "type": "Feature",
  "properties": {
    "addr:full":"450 Pittsfield Rd Lenox MA 01240",
    "addr:housenumber":"450",
    "addr:postcode":"01240",
    "addr:street":"Pittsfield Rd",
    "iso:country":"US",
    "sg:address":"450 Pittsfield Rd",
    "sg:city":"Lenox",
    "sg:classifiers":[
        {
            "category":"Sports & Exercise",
            "subcategory":"Gym",
            "type":"Entertainment"
        }
    ],
    "sg:phone":"+1 413 236 6965",
    "sg:postcode":"01240",
    "sg:province":"MA",
    "sg:tags":[
        "club",
        "health",
        "studio",
        "gymnasium"
    ],
    "wof:name":"Curves For Women",
    "wof:placetype":"venue"
},
  "geometry": {"coordinates":[-73.265867,42.402978],"type":"Point"}
}