{
  "type": "Feature",
  "properties": {
    "addr:full": "80 Border St Boston MA 02128",
    "addr:housenumber": "80",
    "addr:postcode": "02128",
    "addr:street": "Border St",
    "iso:country": "US",
    "sg:address": "80 Border St",
    "sg:city": "Boston",
    "sg:classifiers": [
      {
        "category": "Organizations",
        "subcategory": "Membership Organization",
        "type": "Services"
      }
    ],
    "sg:phone": "+1   ",
    "sg:postcode": "02128",
    "sg:province": "MA",
    "sg:tags": [
      "association"
    ],
    "wof:name": "Shining Sea Foundation",
    "wof:placetype": "venue"
  },
  "geometry": {"coordinates":[-71.041753,42.372291],"type":"Point"}
}
