{
  "type": "Feature",
  "properties": {
    "iso:country":"US",
    "sg:address":"110 Milton Ave",
    "sg:city":"Dorchester Ctr",
    "sg:classifiers":[
        {
            "category":"Professional",
            "type":"Services"
        }
    ],
    "sg:phone":"+1 617 825 6948",
    "sg:postcode":"02124",
    "sg:province":"MA",
    "sg:tags":[
        "establishment"
    ],
    "wof:name":"Missionary Funds",
    "wof:placetype":"venue"
},
  "geometry": {"coordinates":[-71.076027,42.281805],"type":"Point"}
}