{
  "type": "Feature",
  "properties": {
    "addr:full":"1017 Turnpike St Ste 31 Canton MA 02021",
    "addr:housenumber":"1017",
    "addr:postcode":"02021",
    "addr:street":"Turnpike St Ste 31",
    "iso:country":"US",
    "sg:address":"1017 Turnpike St Ste 31",
    "sg:city":"Canton",
    "sg:classifiers":[
        {
            "category":"Insurance",
            "subcategory":"Hazard Insurance",
            "type":"Services"
        }
    ],
    "sg:phone":"+1 781 821 4165",
    "sg:postcode":"02021",
    "sg:province":"MA",
    "sg:tags":[
        "commercial",
        "business"
    ],
    "sg:website":"http://www.flur.com",
    "wof:name":"The New England Life Insurance Company",
    "wof:placetype":"venue"
},
  "geometry": {"coordinates":[-71.104561,42.148977],"type":"Point"}
}