{
  "type": "Feature",
  "properties": {
    "iso:country":"US",
    "sg:address":"446 Blue Hill Ave",
    "sg:city":"Dorchester",
    "sg:classifiers":[
        {
            "category":"Personal",
            "subcategory":"Nail Salon",
            "type":"Services"
        }
    ],
    "sg:phone":"+1 617 541 9750",
    "sg:postcode":"02121",
    "sg:province":"MA",
    "wof:name":"Golden Nail",
    "wof:placetype":"venue"
},
  "geometry": {"coordinates":[-71.082703,42.309502],"type":"Point"}
}