{
  "type": "Feature",
  "properties": {
    "addr:full": "230 Linden St Holyoke MA 01040",
    "addr:housenumber": "230",
    "addr:postcode": "01040",
    "addr:street": "Linden St",
    "iso:country": "US",
    "sg:address": "230 Linden St",
    "sg:city": "Holyoke",
    "sg:classifiers": [
      {
        "category": "Professional",
        "type": "Services"
      }
    ],
    "sg:phone": "+1   ",
    "sg:postcode": "01040",
    "sg:province": "MA",
    "wof:name": "H A Chicopee Inc",
    "wof:placetype": "venue"
  },
  "geometry": {"coordinates":[-72.619751,42.205728],"type":"Point"}
}
