{
  "type": "Feature",
  "properties": {
    "addr:full":"454 College Hwy Southwick MA 01077",
    "addr:housenumber":"454",
    "addr:postcode":"01077",
    "addr:street":"College Hwy",
    "iso:country":"US",
    "sg:address":"454 College Hwy",
    "sg:city":"Southwick",
    "sg:classifiers":[
        {
            "category":"Government",
            "subcategory":"Office",
            "type":"Public Place"
        }
    ],
    "sg:phone":"+1 413 569 0565",
    "sg:postcode":"01077",
    "sg:province":"MA",
    "sg:tags":[
        "city",
        "taxation"
    ],
    "wof:name":"Southwick Assessors",
    "wof:placetype":"venue"
},
  "geometry": {"coordinates":[-72.772874,42.052507],"type":"Point"}
}