{
  "type": "Feature",
  "properties": {
    "iso:country":"US",
    "sg:address":"6 Summer St",
    "sg:city":"North Easton",
    "sg:classifiers":[
        {
            "category":"Professional",
            "subcategory":"Business Services",
            "type":"Services"
        }
    ],
    "sg:phone":"+1 508 238 4353",
    "sg:postcode":"02356",
    "sg:province":"MA",
    "sg:tags":[
        "interior",
        "consultant",
        "design",
        "decorator"
    ],
    "wof:name":"Decorating Den Interiors",
    "wof:placetype":"venue"
},
  "geometry": {"coordinates":[-71.104823,42.046944],"type":"Point"}
}