{
  "type": "Feature",
  "properties": {
    "addr:full":"548 Tremont St Boston MA 02116",
    "addr:housenumber":"548",
    "addr:postcode":"02116",
    "addr:street":"Tremont St",
    "iso:country":"US",
    "sg:address":"548 Tremont St",
    "sg:city":"Boston",
    "sg:classifiers":[
        {
            "category":"Home & Garden",
            "subcategory":"Building Materials",
            "type":"Retail Goods"
        }
    ],
    "sg:phone":"+1 617 357 5166",
    "sg:postcode":"02116",
    "sg:province":"MA",
    "sg:tags":[
        "glass",
        "leaded"
    ],
    "wof:name":"Jim Anderson Stained Glass",
    "wof:placetype":"venue"
},
  "geometry": {"coordinates":[-71.071235,42.344133],"type":"Point"}
}