{
  "type": "Feature",
  "properties": {
    "iso:country":"US",
    "sg:address":"80 Worcester Rd",
    "sg:city":"Sterling",
    "sg:classifiers":[
        {
            "category":"Shopping",
            "subcategory":"Used Merchandise",
            "type":"Retail Goods"
        }
    ],
    "sg:phone":"+1 978 422 7129",
    "sg:postcode":"01564",
    "sg:province":"MA",
    "sg:tags":[
        "antique"
    ],
    "wof:name":"Purple Moon Antiques",
    "wof:placetype":"venue"
},
  "geometry": {"coordinates":[-71.77287099999999,42.412247],"type":"Point"}
}