{
  "type": "Feature",
  "properties": {
    "addr:full":"156 Clay Pit Rd Marshfield MA 02050",
    "addr:housenumber":"156",
    "addr:postcode":"02050",
    "addr:street":"Clay Pit Rd",
    "iso:country":"US",
    "sg:address":"156 Clay Pit Rd",
    "sg:city":"Marshfield",
    "sg:classifiers":[
        {
            "category":"Government",
            "subcategory":"Office",
            "type":"Public Place"
        }
    ],
    "sg:phone":"+1 781 834 5550",
    "sg:postcode":"02050",
    "sg:province":"MA",
    "sg:tags":[
        "village"
    ],
    "wof:name":"Marshfield Animal Control",
    "wof:placetype":"venue"
},
  "geometry": {"coordinates":[-70.71190300000001,42.11135],"type":"Point"}
}