{
  "type": "Feature",
  "properties": {
    "addr:full": "7 Howe St Auburn MA 01501",
    "addr:housenumber": "7",
    "addr:postcode": "01501",
    "addr:street": "Howe St",
    "iso:country": "US",
    "sg:address": "7 Howe St",
    "sg:city": "Auburn",
    "sg:classifiers": [
      {
        "category": "Personal",
        "subcategory": "Beauty Salon",
        "type": "Services"
      }
    ],
    "sg:phone": "+1 508 832 2374",
    "sg:postcode": "01501",
    "sg:province": "MA",
    "wof:name": "Pats Place Family Hair Design",
    "wof:placetype": "venue"
  },
  "geometry": {"coordinates":[-71.839144,42.203824],"type":"Point"}
}
