{
  "type": "Feature",
  "properties": {
    "addr:full":"68 Main St Montague MA 01351",
    "addr:housenumber":"68",
    "addr:postcode":"01351",
    "addr:street":"Main St",
    "iso:country":"US",
    "sg:address":"68 Main St",
    "sg:city":"Montague",
    "sg:classifiers":[
        {
            "category":"Retail",
            "subcategory":"Repair Shop",
            "type":"Services"
        }
    ],
    "sg:phone":"+1 413 367 2010",
    "sg:postcode":"01351",
    "sg:province":"MA",
    "sg:tags":[
        "machine",
        "automobile"
    ],
    "wof:name":"Ted Arman",
    "wof:placetype":"venue"
},
  "geometry": {"coordinates":[-72.532021,42.532016],"type":"Point"}
}