{
  "type": "Feature",
  "properties": {
    "iso:country":"US",
    "sg:address":"35 Maple St Ste 16",
    "sg:city":"Lowell",
    "sg:classifiers":[
        {
            "category":"Autos & Motor Vehicles",
            "subcategory":"Auto Supplies",
            "type":"Retail Goods"
        },
        {
            "category":"Retail",
            "subcategory":"Auto Repair",
            "type":"Services"
        }
    ],
    "sg:phone":"+1 978 453 4455",
    "sg:postcode":"01852",
    "sg:province":"MA",
    "sg:tags":[
        "exhaust",
        "automobile",
        "system",
        "accessory",
        "part",
        "brake",
        "muffler"
    ],
    "wof:name":"All Pro Exhaust",
    "wof:placetype":"venue"
},
  "geometry": {"coordinates":[-71.309349,42.627999],"type":"Point"}
}