{
  "type": "Feature",
  "properties": {
    "addr:full": "200 West St Dedham MA 02027",
    "addr:housenumber": "200",
    "addr:postcode": "02027",
    "addr:street": "West St",
    "iso:country": "US",
    "sg:address": "200 West St",
    "sg:city": "Dedham",
    "sg:classifiers": [
      {
        "category": "Government",
        "subcategory": "Jail",
        "type": "Public Place"
      }
    ],
    "sg:phone": "+1 781 329 3705",
    "sg:postcode": "02027",
    "sg:province": "MA",
    "sg:tags": [
      "county",
      "govt",
      "institution"
    ],
    "wof:name": "Norfolk County Jail",
    "wof:placetype": "venue"
  },
  "geometry": {"coordinates":[-71.20777,42.265138],"type":"Point"}
}
