{
  "type": "Feature",
  "properties": {
    "addr:full":"151 Iyannough Rd Hyannis MA 02601",
    "addr:housenumber":"151",
    "addr:postcode":"02601",
    "addr:street":"Iyannough Rd",
    "iso:country":"US",
    "sg:address":"151 Iyannough Rd",
    "sg:city":"Hyannis",
    "sg:classifiers":[
        {
            "category":"Retail",
            "subcategory":"Auto Repair",
            "type":"Services"
        }
    ],
    "sg:phone":"+1 508 775 2722",
    "sg:postcode":"02601",
    "sg:province":"MA",
    "sg:tags":[
        "body",
        "shop"
    ],
    "wof:name":"Cape Cod Auto Collision & Restoration",
    "wof:placetype":"venue"
},
  "geometry": {"coordinates":[-70.275002,41.659401],"type":"Point"}
}