{
  "type": "Feature",
  "properties": {
    "iso:country":"US",
    "sg:address":"37 State St Ste 3",
    "sg:city":"Belchertown",
    "sg:phone":"+1 413 323 0706",
    "sg:postcode":"01007",
    "sg:province":"MA",
    "wof:name":"Pizza Lovers",
    "wof:placetype":"venue"
},
  "geometry": {"coordinates":[-72.41055900000001,42.272806],"type":"Point"}
}