{
  "type": "Feature",
  "properties": {
    "iso:country":"US",
    "sg:address":"76 Blanchard Rd",
    "sg:city":"Burlington",
    "sg:classifiers":[
        {
            "category":"Professional",
            "subcategory":"Employment Agencies",
            "type":"Services"
        }
    ],
    "sg:phone":"+1 781 272 4900",
    "sg:postcode":"01803",
    "sg:province":"MA",
    "sg:tags":[
        "help",
        "contractor"
    ],
    "wof:name":"Genesis Consolidated Svc",
    "wof:placetype":"venue"
},
  "geometry": {"coordinates":[-71.201851,42.478785],"type":"Point"}
}