{
  "type": "Feature",
  "properties": {
    "addr:full": "1 6th Rd Woburn MA 01801",
    "addr:housenumber": "1",
    "addr:postcode": "01801",
    "addr:street": "6Th Rd",
    "iso:country": "US",
    "sg:address": "1 6th Rd",
    "sg:city": "Woburn",
    "sg:classifiers": [
      {
        "category": "Home \u0026 Garden",
        "subcategory": "Household Appliances",
        "type": "Retail Goods"
      }
    ],
    "sg:phone": "+1 781 933 2081",
    "sg:postcode": "01801",
    "sg:province": "MA",
    "sg:tags": [
      "repair"
    ],
    "wof:name": "Tas Discount - CLOSED",
    "wof:placetype": "venue"
  },
  "geometry": {"coordinates":[-71.143898,42.512299],"type":"Point"}
}
