{
  "type": "Feature",
  "properties": {
    "iso:country":"US",
    "sg:address":"1 6th Rd",
    "sg:city":"Woburn",
    "sg:classifiers":[
        {
            "category":"Home & Garden",
            "subcategory":"Household Appliances",
            "type":"Retail Goods"
        }
    ],
    "sg:phone":"+1 781 933 2081",
    "sg:postcode":"01801",
    "sg:province":"MA",
    "sg:tags":[
        "repair"
    ],
    "wof:name":"Tas Discount - CLOSED",
    "wof:placetype":"venue"
},
  "geometry": {"coordinates":[-71.14389799999999,42.512299],"type":"Point"}
}