{
  "type": "Feature",
  "properties": {
    "addr:full": "10 Federal St Salem MA 01970",
    "addr:housenumber": "10",
    "addr:postcode": "01970",
    "addr:street": "Federal St",
    "iso:country": "US",
    "ovtr:label": "Explorers Lifelong Learning, 10 Federal St Salem MA US",
    "ovtr:similarity": 2.3454220294952393,
    "sg:address": "10 Federal St",
    "sg:city": "Salem",
    "sg:classifiers": [
      {
        "category": "Education",
        "subcategory": "College",
        "type": "Public Place"
      }
    ],
    "sg:phone": "+1 978 744 0804",
    "sg:postcode": "01970",
    "sg:province": "MA",
    "sg:tags": [
      "academic",
      "school"
    ],
    "wof:name": "Explorers Lifelong Learning",
    "wof:placetype": "venue"
  },
  "geometry": {"coordinates":[-70.894066,42.523329],"type":"Point"}
}
