{
  "type": "Feature",
  "properties": {
    "addr:full":"153 Quabbin Blvd Orange MA 01364",
    "addr:housenumber":"153",
    "addr:postcode":"01364",
    "addr:street":"Quabbin Blvd",
    "iso:country":"US",
    "sg:address":"153 Quabbin Blvd",
    "sg:city":"Orange",
    "sg:classifiers":[
        {
            "category":"Professional",
            "subcategory":"Management & Consulting",
            "type":"Services"
        }
    ],
    "sg:phone":"+1 978 544 8770",
    "sg:postcode":"01364",
    "sg:province":"MA",
    "sg:tags":[
        "consultant",
        "business"
    ],
    "wof:name":"Carbon Industries Inc",
    "wof:placetype":"venue"
},
  "geometry": {"coordinates":[-72.303032,42.568815],"type":"Point"}
}