{
  "type": "Feature",
  "properties": {
    "iso:country":"US",
    "sg:address":"1501 Main St",
    "sg:city":"Tewksbury",
    "sg:classifiers":[
        {
            "category":"Utilities",
            "subcategory":"Telephone",
            "type":"Services"
        }
    ],
    "sg:phone":"+1 978 858 0080",
    "sg:postcode":"01876",
    "sg:province":"MA",
    "sg:tags":[
        "telecommunication"
    ],
    "wof:name":"Powers & Co",
    "wof:placetype":"venue"
},
  "geometry": {"coordinates":[-71.221599,42.599709],"type":"Point"}
}