{
  "type": "Feature",
  "properties": {
    "addr:full":"1190 S Washington St North Attleborough MA 02760",
    "addr:housenumber":"1190",
    "addr:postcode":"02760",
    "addr:street":"S Washington St",
    "iso:country":"US",
    "sg:address":"1190 S Washington St",
    "sg:city":"North Attleborough",
    "sg:classifiers":[
        {
            "category":"Food & Beverages",
            "subcategory":"Liquor & Beverages",
            "type":"Retail Goods"
        }
    ],
    "sg:phone":"+1 508 699 9463",
    "sg:postcode":"02760",
    "sg:province":"MA",
    "sg:tags":[
        "beer",
        "spirit",
        "wine"
    ],
    "wof:name":"Chris Gasbarro's Wine & Spirits",
    "wof:placetype":"venue"
},
  "geometry": {"coordinates":[-71.3464,41.942],"type":"Point"}
}