{
  "type": "Feature",
  "properties": {
    "iso:country":"US",
    "sg:address":"2 Gates Rd",
    "sg:city":"Marshfield",
    "sg:classifiers":[
        {
            "category":"Autos & Motor Vehicles",
            "subcategory":"Auto Supplies",
            "type":"Retail Goods"
        }
    ],
    "sg:phone":"+1 781 837 3115",
    "sg:postcode":"02050",
    "sg:province":"MA",
    "sg:tags":[
        "accessories-wholesale",
        "automobile",
        "part",
        "parts",
        "manufacturer"
    ],
    "sg:website":"http://www.marshautoparts.com",
    "wof:name":"Marsh Auto Parts",
    "wof:placetype":"venue"
},
  "geometry": {"coordinates":[-70.690353,42.100231],"type":"Point"}
}