{
  "type": "Feature",
  "properties": {
    "addr:full": "16 Mann Ter Florence MA 01062",
    "addr:housenumber": "16",
    "addr:postcode": "01062",
    "addr:street": "Mann Ter",
    "iso:country": "US",
    "sg:address": "16 Mann Ter",
    "sg:city": "Florence",
    "sg:classifiers": [
      {
        "category": "Restaurant",
        "type": "Food \u0026 Drink"
      }
    ],
    "sg:menulink": "http://www.allmenus.com/ma/northampton/35383-fire-cuisine/menu/",
    "sg:phone": "+1 413 582 0755",
    "sg:postcode": "01062",
    "sg:province": "MA",
    "sg:tags": [
      "italian"
    ],
    "wof:name": "Fire Cuisine",
    "wof:placetype": "venue"
  },
  "geometry": {"coordinates":[-72.667114,42.334674],"type":"Point"}
}
