{
  "type": "Feature",
  "properties": {
    "addr:full":"169 Gifford St Falmouth MA 02540",
    "addr:housenumber":"169",
    "addr:postcode":"02540",
    "addr:street":"Gifford St",
    "iso:country":"US",
    "sg:address":"169 Gifford St",
    "sg:city":"Falmouth",
    "sg:classifiers":[
        {
            "category":"Health Services",
            "subcategory":"Chiropractor",
            "type":"Services"
        }
    ],
    "sg:phone":"+1 508 548 2201",
    "sg:postcode":"02540",
    "sg:province":"MA",
    "wof:name":"Mac Donald Chiropractic",
    "wof:placetype":"venue"
},
  "geometry": {"coordinates":[-70.61096999999999,41.556281],"type":"Point"}
}