{
  "type": "Feature",
  "properties": {
    "iso:country":"US",
    "sg:address":"44 Wood Ave",
    "sg:city":"Mansfield",
    "sg:classifiers":[
        {
            "category":"Banks & Credit Unions",
            "subcategory":"Bank",
            "type":"Services"
        }
    ],
    "sg:phone":"+1 508 261 8833",
    "sg:postcode":"02048",
    "sg:province":"MA",
    "sg:tags":[
        "loan",
        "real estate"
    ],
    "wof:name":"VIP Mortgage Corp",
    "wof:placetype":"venue"
},
  "geometry": {"coordinates":[-71.22888399999999,42.029906],"type":"Point"}
}