{
  "type": "Feature",
  "properties": {
    "addr:full":"2475 Main St Springfield MA 01107",
    "addr:housenumber":"2475",
    "addr:postcode":"01107",
    "addr:street":"Main St",
    "iso:country":"US",
    "sg:address":"2475 Main St",
    "sg:city":"Springfield",
    "sg:classifiers":[
        {
            "category":"Shopping",
            "subcategory":"Hobbies, Toys, & Games",
            "type":"Retail Goods"
        }
    ],
    "sg:phone":"+1 413 734 6858",
    "sg:postcode":"01107",
    "sg:province":"MA",
    "sg:tags":[
        "model",
        "supply"
    ],
    "wof:name":"P Hobbies Fashions & Music",
    "wof:placetype":"venue"
},
  "geometry": {"coordinates":[-72.603696,42.111745],"type":"Point"}
}