{
  "type": "Feature",
  "properties": {
    "addr:full": "1 Ahab Way Eastham MA 02642",
    "addr:housenumber": "1",
    "addr:postcode": "02642",
    "addr:street": "Ahab Way",
    "iso:country": "US",
    "sg:address": "1 Ahab Way",
    "sg:city": "Eastham",
    "sg:classifiers": [
      {
        "category": "Freight",
        "type": "Transportation"
      }
    ],
    "sg:phone": "+1 508 247 9898",
    "sg:postcode": "02642",
    "sg:province": "MA",
    "sg:tags": [
      "broker",
      "trucking"
    ],
    "wof:name": "Pro Transportation Inc",
    "wof:placetype": "venue"
  },
  "geometry": {"coordinates":[-69.983908,41.819478],"type":"Point"}
}
