{
  "type": "Feature",
  "properties": {
    "addr:full": "111 Payson Ave Rockland MA 02370",
    "addr:housenumber": "111",
    "addr:postcode": "02370",
    "addr:street": "Payson Ave",
    "iso:country": "US",
    "sg:address": "111 Payson Ave",
    "sg:city": "Rockland",
    "sg:classifiers": [
      {
        "category": "Building \u0026 Trades",
        "subcategory": "Construction",
        "type": "Services"
      }
    ],
    "sg:phone": "+1 781 982 9164",
    "sg:postcode": "02370",
    "sg:province": "MA",
    "sg:tags": [
      "pavement",
      "marking"
    ],
    "wof:name": "Guide Lines Pavement Mntnc",
    "wof:placetype": "venue"
  },
  "geometry": {"coordinates":[-70.916666,42.124443],"type":"Point"}
}
