{
  "type": "Feature",
  "properties": {
    "iso:country":"US",
    "sg:address":"111 Payson Ave",
    "sg:city":"Rockland",
    "sg:classifiers":[
        {
            "category":"Building & Trades",
            "subcategory":"Construction",
            "type":"Services"
        }
    ],
    "sg:phone":"+1 781 982 9164",
    "sg:postcode":"02370",
    "sg:province":"MA",
    "sg:tags":[
        "pavement",
        "marking"
    ],
    "wof:name":"Guide Lines Pavement Mntnc",
    "wof:placetype":"venue"
},
  "geometry": {"coordinates":[-70.91666600000001,42.124443],"type":"Point"}
}