{
  "type": "Feature",
  "properties": {
    "iso:country":"US",
    "sg:address":"33 Bartlett St",
    "sg:city":"Lowell",
    "sg:classifiers":[
        {
            "category":"Health Services",
            "subcategory":"Doctor",
            "type":"Services"
        }
    ],
    "sg:phone":"+1 978 256 1858",
    "sg:postcode":"01852",
    "sg:province":"MA",
    "sg:tags":[
        "physician",
        "surgeon"
    ],
    "wof:name":"Womanhealth Ob-Gyn",
    "wof:placetype":"venue"
},
  "geometry": {"coordinates":[-71.30107599999999,42.645292],"type":"Point"}
}