{
  "type": "Feature",
  "properties": {
    "addr:full": "33 Bartlett St Lowell MA 01852",
    "addr:housenumber": "33",
    "addr:postcode": "01852",
    "addr:street": "Bartlett St",
    "iso:country": "US",
    "sg:address": "33 Bartlett St",
    "sg:city": "Lowell",
    "sg:classifiers": [
      {
        "category": "Health Services",
        "subcategory": "Doctor",
        "type": "Services"
      }
    ],
    "sg:phone": "+1 978 256 1858",
    "sg:postcode": "01852",
    "sg:province": "MA",
    "sg:tags": [
      "physician",
      "surgeon"
    ],
    "wof:name": "Womanhealth Ob-Gyn",
    "wof:placetype": "venue"
  },
  "geometry": {"coordinates":[-71.301076,42.645292],"type":"Point"}
}
