{
  "type": "Feature",
  "properties": {
    "iso:country":"US",
    "sg:address":"5 Navin Hts",
    "sg:city":"Lee",
    "sg:classifiers":[
        {
            "category":"Wholesale",
            "subcategory":"Electrical",
            "type":"Manufacturing & Wholesale Goods"
        }
    ],
    "sg:phone":"+1 413 243 4004",
    "sg:postcode":"01238",
    "sg:province":"MA",
    "sg:tags":[
        "control"
    ],
    "wof:name":"M & C Plant Instruments",
    "wof:placetype":"venue"
},
  "geometry": {"coordinates":[-73.252955,42.313508],"type":"Point"}
}