{
  "type": "Feature",
  "properties": {
    "addr:full":"37 Depot St North Attleboro MA 02760",
    "addr:housenumber":"37",
    "addr:postcode":"02760",
    "addr:street":"Depot St",
    "iso:country":"US",
    "sg:address":"37 Depot St",
    "sg:city":"North Attleboro",
    "sg:classifiers":[
        {
            "category":"Real Estate",
            "subcategory":"Real Estate Agent",
            "type":"Services"
        }
    ],
    "sg:phone":"+1 774 219 6021",
    "sg:postcode":"02760",
    "sg:province":"MA",
    "sg:tags":[
        "appraiser"
    ],
    "wof:name":"Eagle Real Estate Svc Inc",
    "wof:placetype":"venue"
},
  "geometry": {"coordinates":[-71.374628,41.928487],"type":"Point"}
}