{
  "type": "Feature",
  "properties": {
    "addr:full":"300 E Main St Milford MA 01757",
    "addr:housenumber":"300",
    "addr:postcode":"01757",
    "addr:street":"E Main St",
    "iso:country":"US",
    "sg:address":"300 E Main St",
    "sg:city":"Milford",
    "sg:classifiers":[
        {
            "category":"Professional",
            "subcategory":"Lawyer & Legal Services",
            "type":"Services"
        }
    ],
    "sg:phone":"+1 508 478 9700",
    "sg:postcode":"01757",
    "sg:province":"MA",
    "sg:tags":[
        "attorney"
    ],
    "wof:name":"Molloy & Assoc",
    "wof:placetype":"venue"
},
  "geometry": {"coordinates":[-71.48952199999999,42.153408],"type":"Point"}
}