{
  "type": "Feature",
  "properties": {
    "addr:full": "825 Middle St Weymouth MA 02188",
    "addr:housenumber": "825",
    "addr:postcode": "02188",
    "addr:street": "Middle St",
    "iso:country": "US",
    "ovtr:label": "Towers Liquor Mart, 825 Middle St Weymouth MA US",
    "ovtr:similarity": 2.0579919815063477,
    "sg:address": "825 Middle St",
    "sg:city": "Weymouth",
    "sg:classifiers": [
      {
        "category": "Food \u0026 Beverages",
        "subcategory": "Liquor \u0026 Beverages",
        "type": "Retail Goods"
      }
    ],
    "sg:phone": "+1 781 335 9741",
    "sg:postcode": "02188",
    "sg:province": "MA",
    "wof:name": "Towers Liquor Mart",
    "wof:placetype": "venue"
  },
  "geometry": {"coordinates":[-70.946769,42.198255],"type":"Point"}
}
