{
  "type": "Feature",
  "properties": {
    "iso:country":"US",
    "sg:address":"8 Faneuil Hall Market Pl",
    "sg:city":"Boston",
    "sg:classifiers":[
        {
            "category":"Banks & Credit Unions",
            "subcategory":"Bank",
            "type":"Services"
        }
    ],
    "sg:phone":"+1 617 973 5062",
    "sg:postcode":"02109",
    "sg:province":"MA",
    "sg:website":"www.usbank.com",
    "wof:name":"US Bancorp",
    "wof:placetype":"venue"
},
  "geometry": {"coordinates":[-71.053785,42.359706],"type":"Point"}
}