{
  "type": "Feature",
  "properties": {
    "iso:country":"US",
    "sg:address":"28 Putnam St",
    "sg:city":"Beverly",
    "sg:classifiers":[
        {
            "category":"Building & Trades",
            "subcategory":"Construction",
            "type":"Services"
        }
    ],
    "sg:phone":"+1   ",
    "sg:postcode":"01915",
    "sg:province":"MA",
    "sg:tags":[
        "contractor"
    ],
    "wof:name":"Mason Duzz Contractors",
    "wof:placetype":"venue"
},
  "geometry": {"coordinates":[-70.882525,42.583023],"type":"Point"}
}