{
  "type": "Feature",
  "properties": {
    "iso:country":"US",
    "sg:address":"120 W Boylston St",
    "sg:city":"West Boylston",
    "sg:classifiers":[
        {
            "category":"Government",
            "subcategory":"Office",
            "type":"Public Place"
        }
    ],
    "sg:phone":"+1 508 835 6093",
    "sg:postcode":"01583",
    "sg:province":"MA",
    "sg:tags":[
        "city",
        "taxation"
    ],
    "wof:name":"West Boylston Assessor",
    "wof:placetype":"venue"
},
  "geometry": {"coordinates":[-71.784441,42.357349],"type":"Point"}
}