{
  "type": "Feature",
  "properties": {
    "iso:country":"US",
    "sg:address":"41 High St",
    "sg:city":"Amherst",
    "sg:classifiers":[
        {
            "category":"Professional",
            "subcategory":"Research",
            "type":"Services"
        }
    ],
    "sg:phone":"+1   ",
    "sg:postcode":"01002",
    "sg:province":"MA",
    "sg:tags":[
        "sociology"
    ],
    "wof:name":"Jan Dizard PHD",
    "wof:placetype":"venue"
},
  "geometry": {"coordinates":[-72.509457,42.377468],"type":"Point"}
}