{
  "type": "Feature",
  "properties": {
    "addr:full": "61 Summer St Maynard MA 01754",
    "addr:housenumber": "61",
    "addr:postcode": "01754",
    "addr:street": "Summer St",
    "iso:country": "US",
    "ovtr:label": "Acme Theater, 61 Summer St Maynard MA US",
    "ovtr:similarity": 2.7631020545959473,
    "sg:address": "61 Summer St",
    "sg:city": "Maynard",
    "sg:classifiers": [
      {
        "category": "Professional",
        "type": "Services"
      }
    ],
    "sg:phone": "+1 978 823 0003",
    "sg:postcode": "01754",
    "sg:province": "MA",
    "sg:tags": [
      "establishment"
    ],
    "wof:name": "ACME Theater",
    "wof:placetype": "venue"
  },
  "geometry": {"coordinates":[-71.455748,42.43432],"type":"Point"}
}
