{
  "type": "Feature",
  "properties": {
    "addr:full": "157 Water St Newburyport MA 01950",
    "addr:housenumber": "157",
    "addr:postcode": "01950",
    "addr:street": "Water St",
    "iso:country": "US",
    "sg:address": "157 Water St",
    "sg:city": "Newburyport",
    "sg:classifiers": [
      {
        "category": "Government",
        "subcategory": "Office",
        "type": "Public Place"
      }
    ],
    "sg:phone": "+1 978 465 4461",
    "sg:postcode": "01950",
    "sg:province": "MA",
    "sg:tags": [
      "village"
    ],
    "wof:name": "Newburyport Sewerage Plant",
    "wof:placetype": "venue"
  },
  "geometry": {"coordinates":[-70.861994,42.808574],"type":"Point"}
}
