{
  "type": "Feature",
  "properties": {
    "addr:full": "72 Harrison Avenue Boston MA 02111",
    "addr:housenumber": "72",
    "addr:postcode": "02111",
    "addr:street": "Harrison Avenue",
    "iso:country": "US",
    "sg:address": "72 Harrison Avenue",
    "sg:city": "Boston",
    "sg:classifiers": [
      {
        "category": "Arts \u0026 Performance",
        "subcategory": "Art Gallery",
        "type": "Entertainment"
      }
    ],
    "sg:phone": "+1 617 695 3731",
    "sg:postcode": "02111",
    "sg:province": "MA",
    "wof:name": "China Arts Gallery",
    "wof:placetype": "venue"
  },
  "geometry": {"coordinates":[-71.06142,42.351244],"type":"Point"}
}
