{
  "type": "Feature",
  "properties": {
    "iso:country":"US",
    "sg:address":"140 Wood Rd",
    "sg:city":"Braintree",
    "sg:classifiers":[
        {
            "category":"Wholesale",
            "subcategory":"Computers",
            "type":"Manufacturing & Wholesale Goods"
        }
    ],
    "sg:phone":"+1 781 794 9905",
    "sg:postcode":"02184",
    "sg:province":"MA",
    "sg:tags":[
        "duplication"
    ],
    "wof:name":"Clear Orbit",
    "wof:placetype":"venue"
},
  "geometry": {"coordinates":[-71.03574999999999,42.22329],"type":"Point"}
}