{
  "type": "Feature",
  "properties": {
    "addr:full": "140 Wood Rd Braintree MA 02184",
    "addr:housenumber": "140",
    "addr:postcode": "02184",
    "addr:street": "Wood Rd",
    "iso:country": "US",
    "sg:address": "140 Wood Rd",
    "sg:city": "Braintree",
    "sg:classifiers": [
      {
        "category": "Wholesale",
        "subcategory": "Computers",
        "type": "Manufacturing \u0026 Wholesale Goods"
      }
    ],
    "sg:phone": "+1 781 794 9905",
    "sg:postcode": "02184",
    "sg:province": "MA",
    "sg:tags": [
      "duplication"
    ],
    "wof:name": "Clear Orbit",
    "wof:placetype": "venue"
  },
  "geometry": {"coordinates":[-71.03575,42.22329],"type":"Point"}
}
