{
  "type": "Feature",
  "properties": {
    "addr:full": "60 S Deerfield Byp South Deerfield MA 01373",
    "addr:housenumber": "60",
    "addr:postcode": "01373",
    "addr:street": "S Deerfield Byp",
    "iso:country": "US",
    "sg:address": "60 S Deerfield Byp",
    "sg:city": "South Deerfield",
    "sg:classifiers": [
      {
        "category": "Government",
        "subcategory": "Post Office",
        "type": "Public Place"
      }
    ],
    "sg:phone": "+1 413 665 2587",
    "sg:postcode": "01373",
    "sg:province": "MA",
    "wof:name": "US Post Office",
    "wof:placetype": "venue"
  },
  "geometry": {"coordinates":[-72.613564,42.476508],"type":"Point"}
}
