{
  "type": "Feature",
  "properties": {
    "addr:full": "115 Elm St Amesbury MA 01913",
    "addr:housenumber": "115",
    "addr:postcode": "01913",
    "addr:street": "Elm St",
    "iso:country": "US",
    "sg:address": "115 Elm St",
    "sg:city": "Amesbury",
    "sg:classifiers": [
      {
        "category": "Recreation",
        "type": "Entertainment"
      }
    ],
    "sg:phone": "+1 978 834 0903",
    "sg:postcode": "01913",
    "sg:province": "MA",
    "sg:tags": [
      "diving",
      "instruction"
    ],
    "wof:name": "Amesbury Scuba Diving",
    "wof:placetype": "venue"
  },
  "geometry": {"coordinates":[-70.924868,42.85895],"type":"Point"}
}
