{
  "type": "Feature",
  "properties": {
    "addr:full":"552 Center St Ludlow MA 01056",
    "addr:housenumber":"552",
    "addr:postcode":"01056",
    "addr:street":"Center St",
    "iso:country":"US",
    "sg:address":"552 Center St",
    "sg:city":"Ludlow",
    "sg:classifiers":[
        {
            "category":"Autos & Motor Vehicles",
            "subcategory":"Automobile Sales",
            "type":"Retail Goods"
        }
    ],
    "sg:phone":"+1 413 547 6575",
    "sg:postcode":"01056",
    "sg:province":"MA",
    "sg:tags":[
        "car",
        "dealer"
    ],
    "wof:name":"MDS Auto Sales",
    "wof:placetype":"venue"
},
  "geometry": {"coordinates":[-72.473811,42.1754],"type":"Point"}
}