{
  "type": "Feature",
  "properties": {
    "iso:country":"US",
    "sg:address":"36 Essex Rd",
    "sg:city":"Nantucket",
    "sg:classifiers":[
        {
            "category":"Building & Trades",
            "subcategory":"Landscaping Services",
            "type":"Services"
        }
    ],
    "sg:phone":"+1 508 228 8485",
    "sg:postcode":"02554",
    "sg:province":"MA",
    "wof:name":"Earthlawns",
    "wof:placetype":"venue"
},
  "geometry": {"coordinates":[-70.10458800000001,41.264728],"type":"Point"}
}