{
  "type": "Feature",
  "properties": {
    "iso:country":"US",
    "sg:address":"268 Boston Post Rd",
    "sg:city":"Wayland",
    "sg:classifiers":[
        {
            "category":"Autos & Motor Vehicles",
            "subcategory":"Fuel & Gas Station",
            "type":"Retail Goods"
        }
    ],
    "sg:phone":"+1 508 358 2291",
    "sg:postcode":"01778",
    "sg:province":"MA",
    "sg:tags":[
        "oil"
    ],
    "wof:name":"Shepard's Mobil",
    "wof:placetype":"venue"
},
  "geometry": {"coordinates":[-71.367901,42.363253],"type":"Point"}
}