{
  "type": "Feature",
  "properties": {
    "iso:country":"US",
    "sg:address":"20 Tremont St",
    "sg:city":"Melrose",
    "sg:phone":"+1 781 665 0302",
    "sg:postcode":"02176",
    "sg:province":"MA",
    "sg:tags":[
        "oil"
    ],
    "wof:name":"Homeowner's Heating",
    "wof:placetype":"venue"
},
  "geometry": {"coordinates":[-71.069777,42.462692],"type":"Point"}
}