{
  "type": "Feature",
  "properties": {
    "addr:full": "227 Dedham St Norfolk MA 02056",
    "addr:housenumber": "227",
    "addr:postcode": "02056",
    "addr:street": "Dedham St",
    "iso:country": "US",
    "sg:address": "227 Dedham St",
    "sg:city": "Norfolk",
    "sg:classifiers": [
      {
        "category": "Health Services",
        "subcategory": "Health Practitioner",
        "type": "Services"
      }
    ],
    "sg:phone": "+1 508 384 7020",
    "sg:postcode": "02056",
    "sg:province": "MA",
    "sg:tags": [
      "therapist",
      "physical"
    ],
    "wof:name": "Physical Therapy \u0026 Sports",
    "wof:placetype": "venue"
  },
  "geometry": {"coordinates":[-71.300314,42.089779],"type":"Point"}
}
