{
  "type": "Feature",
  "properties": {
    "addr:full":"66 Pleasant St Sagamore MA 02561",
    "addr:housenumber":"66",
    "addr:postcode":"02561",
    "addr:street":"Pleasant St",
    "iso:country":"US",
    "sg:address":"66 Pleasant St",
    "sg:city":"Sagamore",
    "sg:classifiers":[
        {
            "category":"Health Services",
            "subcategory":"Optometrist",
            "type":"Services"
        }
    ],
    "sg:phone":"+1 508 888 4424",
    "sg:postcode":"02561",
    "sg:province":"MA",
    "wof:name":"Low Vision Clinics",
    "wof:placetype":"venue"
},
  "geometry": {"coordinates":[-70.532551,41.771908],"type":"Point"}
}