{
  "type": "Feature",
  "properties": {
    "iso:country":"US",
    "sg:address":"21 Jacob Amsden Rd",
    "sg:city":"Westborough",
    "sg:classifiers":[
        {
            "category":"Professional",
            "subcategory":"Computer Services",
            "type":"Services"
        }
    ],
    "sg:phone":"+1 508 366 2287",
    "sg:postcode":"01581",
    "sg:province":"MA",
    "sg:tags":[
        "repair"
    ],
    "wof:name":"Technology Providers Inc",
    "wof:placetype":"venue"
},
  "geometry": {"coordinates":[-71.585678,42.298029],"type":"Point"}
}