{
  "type": "Feature",
  "properties": {
    "addr:full": "49 Pearl St Brockton MA 02301",
    "addr:housenumber": "49",
    "addr:postcode": "02301",
    "addr:street": "Pearl St",
    "iso:country": "US",
    "sg:address": "49 Pearl St",
    "sg:city": "Brockton",
    "sg:classifiers": [
      {
        "category": "Health Services",
        "subcategory": "Doctor",
        "type": "Services"
      }
    ],
    "sg:phone": "+1 508 580 1020",
    "sg:postcode": "02301",
    "sg:province": "MA",
    "sg:tags": [
      "dermatologist"
    ],
    "wof:name": "DO Daihung MD",
    "wof:placetype": "venue"
  },
  "geometry": {"coordinates":[-71.064612,42.087381],"type":"Point"}
}
