{
  "type": "Feature",
  "properties": {
    "iso:country":"US",
    "sg:address":"40 Hobbs Brook Rd",
    "sg:city":"Waltham",
    "sg:classifiers":[
        {
            "category":"Building & Trades",
            "subcategory":"Landscaping Services",
            "type":"Services"
        }
    ],
    "sg:phone":"+1   ",
    "sg:postcode":"02451",
    "sg:province":"MA",
    "wof:name":"Ever Green Landscaping",
    "wof:placetype":"venue"
},
  "geometry": {"coordinates":[-71.26596000000001,42.416412],"type":"Point"}
}