{
  "type": "Feature",
  "properties": {
    "iso:country":"US",
    "sg:address":"707 Millbury St",
    "sg:city":"Worcester",
    "sg:classifiers":[
        {
            "category":"Retail",
            "subcategory":"Auto Repair",
            "type":"Services"
        }
    ],
    "sg:phone":"+1 508 753 8884",
    "sg:postcode":"01607",
    "sg:province":"MA",
    "sg:tags":[
        "repairing",
        "automobile"
    ],
    "wof:name":"P & B Auto & Truck Repair",
    "wof:placetype":"venue"
},
  "geometry": {"coordinates":[-71.797499,42.237984],"type":"Point"}
}