{
  "type": "Feature",
  "properties": {
    "iso:country":"US",
    "sg:address":"672 Waverly St",
    "sg:city":"Framingham",
    "sg:classifiers":[
        {
            "category":"Wholesale",
            "subcategory":"Medical Equipment & Supplies",
            "type":"Manufacturing & Wholesale Goods"
        }
    ],
    "sg:phone":"+1 508 626 0660",
    "sg:postcode":"01702",
    "sg:province":"MA",
    "sg:tags":[
        "physician",
        "surgeon"
    ],
    "wof:name":"Block Scientific Inc",
    "wof:placetype":"venue"
},
  "geometry": {"coordinates":[-71.427387,42.272973],"type":"Point"}
}