{
  "type": "Feature",
  "properties": {
    "addr:full": "672 Waverly St Framingham MA 01702",
    "addr:housenumber": "672",
    "addr:postcode": "01702",
    "addr:street": "Waverly St",
    "iso:country": "US",
    "sg:address": "672 Waverly St",
    "sg:city": "Framingham",
    "sg:classifiers": [
      {
        "category": "Wholesale",
        "subcategory": "Medical Equipment \u0026 Supplies",
        "type": "Manufacturing \u0026 Wholesale Goods"
      }
    ],
    "sg:phone": "+1 508 626 0660",
    "sg:postcode": "01702",
    "sg:province": "MA",
    "sg:tags": [
      "physician",
      "surgeon"
    ],
    "wof:name": "Block Scientific Inc",
    "wof:placetype": "venue"
  },
  "geometry": {"coordinates":[-71.427387,42.272973],"type":"Point"}
}
