{
  "type": "Feature",
  "properties": {
    "iso:country":"US",
    "sg:address":"42 Beach Street",
    "sg:city":"Boston",
    "sg:classifiers":[
        {
            "category":"Food & Beverages",
            "subcategory":"Candy",
            "type":"Retail Goods"
        }
    ],
    "sg:postcode":"02111",
    "sg:province":"MA",
    "sg:tags":[
        "dessert"
    ],
    "wof:name":"Egg Puffs",
    "wof:placetype":"venue"
},
  "geometry": {"coordinates":[-71.061221,42.351491],"type":"Point"}
}