{
  "type": "Feature",
  "properties": {
    "addr:full": "42 Beach Street Boston MA 02111",
    "addr:housenumber": "42",
    "addr:postcode": "02111",
    "addr:street": "Beach Street",
    "iso:country": "US",
    "sg:address": "42 Beach Street",
    "sg:city": "Boston",
    "sg:classifiers": [
      {
        "category": "Food \u0026 Beverages",
        "subcategory": "Candy",
        "type": "Retail Goods"
      }
    ],
    "sg:postcode": "02111",
    "sg:province": "MA",
    "sg:tags": [
      "dessert"
    ],
    "wof:name": "Egg Puffs",
    "wof:placetype": "venue"
  },
  "geometry": {"coordinates":[-71.061221,42.351491],"type":"Point"}
}
