{
  "type": "Feature",
  "properties": {
    "addr:full": "38 Lyle Ter Malden MA 02148",
    "addr:housenumber": "38",
    "addr:postcode": "02148",
    "addr:street": "Lyle Ter",
    "iso:country": "US",
    "sg:address": "38 Lyle Ter",
    "sg:city": "Malden",
    "sg:classifiers": [
      {
        "category": "Professional",
        "subcategory": "Management \u0026 Consulting",
        "type": "Services"
      }
    ],
    "sg:phone": "+1   ",
    "sg:postcode": "02148",
    "sg:province": "MA",
    "sg:tags": [
      "business"
    ],
    "wof:name": "Wais Consulting",
    "wof:placetype": "venue"
  },
  "geometry": {"coordinates":[-71.072352,42.437926],"type":"Point"}
}
