{
  "type": "Feature",
  "properties": {
    "iso:country":"US",
    "sg:address":"61 Pleasant St",
    "sg:city":"Randolph",
    "sg:classifiers":[
        {
            "category":"Manufacturing",
            "subcategory":"Tools & Machinery",
            "type":"Manufacturing & Wholesale Goods"
        }
    ],
    "sg:phone":"+1 781 961 7220",
    "sg:postcode":"02368",
    "sg:province":"MA",
    "sg:tags":[
        "control",
        "static"
    ],
    "wof:name":"Static Technologies Corp",
    "wof:placetype":"venue"
},
  "geometry": {"coordinates":[-71.04043799999999,42.168958],"type":"Point"}
}