{
  "type": "Feature",
  "properties": {
    "addr:full": "61 Pleasant St Randolph MA 02368",
    "addr:housenumber": "61",
    "addr:postcode": "02368",
    "addr:street": "Pleasant St",
    "iso:country": "US",
    "sg:address": "61 Pleasant St",
    "sg:city": "Randolph",
    "sg:classifiers": [
      {
        "category": "Manufacturing",
        "subcategory": "Tools \u0026 Machinery",
        "type": "Manufacturing \u0026 Wholesale Goods"
      }
    ],
    "sg:phone": "+1 781 961 7220",
    "sg:postcode": "02368",
    "sg:province": "MA",
    "sg:tags": [
      "control",
      "static"
    ],
    "wof:name": "Static Technologies Corp",
    "wof:placetype": "venue"
  },
  "geometry": {"coordinates":[-71.040438,42.168958],"type":"Point"}
}
