{
  "type": "Feature",
  "properties": {
    "addr:full": "441 Chestnut St Gardner MA 01440",
    "addr:housenumber": "441",
    "addr:postcode": "01440",
    "addr:street": "Chestnut St",
    "iso:country": "US",
    "ovtr:label": "Parker Glass LLC, 441 Chestnut St Gardner MA US",
    "ovtr:similarity": 1.9930399656295776,
    "sg:address": "441 Chestnut St",
    "sg:city": "Gardner",
    "sg:classifiers": [
      {
        "category": "Home \u0026 Garden",
        "subcategory": "Building Materials",
        "type": "Retail Goods"
      }
    ],
    "sg:phone": "+1 978 632 5382",
    "sg:postcode": "01440",
    "sg:province": "MA",
    "sg:tags": [
      "glass",
      "window",
      "plate"
    ],
    "wof:name": "Parker Glass LLC",
    "wof:placetype": "venue"
  },
  "geometry": {"coordinates":[-71.984269,42.570825],"type":"Point"}
}
