{
  "type": "Feature",
  "properties": {
    "addr:full": "12 Forest St Medford MA 02155",
    "addr:housenumber": "12",
    "addr:postcode": "02155",
    "addr:street": "Forest St",
    "iso:country": "US",
    "sg:address": "12 Forest St",
    "sg:city": "Medford",
    "sg:classifiers": [
      {
        "category": "Restaurant",
        "type": "Food \u0026 Drink"
      }
    ],
    "sg:phone": "+1 781 391 2560",
    "sg:postcode": "02155",
    "sg:province": "MA",
    "wof:name": "Cafe Bon Vivant",
    "wof:placetype": "venue"
  },
  "geometry": {"coordinates":[-71.108208,42.420959],"type":"Point"}
}
