{
  "type": "Feature",
  "properties": {
    "iso:country":"US",
    "sg:address":"12 Craig Rd",
    "sg:city":"Acton",
    "sg:classifiers":[
        {
            "category":"Manufacturing",
            "subcategory":"Electronics",
            "type":"Manufacturing & Wholesale Goods"
        }
    ],
    "sg:phone":"+1 978 635 1144",
    "sg:postcode":"01720",
    "sg:province":"MA",
    "sg:tags":[
        "sound",
        "equipment",
        "system"
    ],
    "wof:name":"Concert Sound & Lighting",
    "wof:placetype":"venue"
},
  "geometry": {"coordinates":[-71.418398,42.466185],"type":"Point"}
}