{
  "type": "Feature",
  "properties": {
    "addr:full":"90 Orchard St Tewksbury MA 01876",
    "addr:housenumber":"90",
    "addr:postcode":"01876",
    "addr:street":"Orchard St",
    "iso:country":"US",
    "sg:address":"90 Orchard St",
    "sg:city":"Tewksbury",
    "sg:classifiers":[
        {
            "category":"Taxi",
            "type":"Transportation"
        }
    ],
    "sg:phone":"+1 978 441 0018",
    "sg:postcode":"01876",
    "sg:province":"MA",
    "wof:name":"Lowell Taxi",
    "wof:placetype":"venue"
},
  "geometry": {"coordinates":[-71.222813,42.605108],"type":"Point"}
}