{
  "type": "Feature",
  "properties": {
    "addr:full": "285 Washington St Boston MA 02108",
    "addr:housenumber": "285",
    "addr:postcode": "02108",
    "addr:street": "Washington St",
    "iso:country": "US",
    "sg:address": "285 Washington St",
    "sg:city": "Boston",
    "sg:classifiers": [
      {
        "category": "Food \u0026 Beverages",
        "subcategory": "Groceries \u0026 Convenience Stores",
        "type": "Retail Goods"
      }
    ],
    "sg:phone": "+1 617 265 0351",
    "sg:postcode": "02108",
    "sg:province": "MA",
    "wof:name": "Gomez Convenience Store",
    "wof:placetype": "venue"
  },
  "geometry": {"coordinates":[-71.057999,42.357601],"type":"Point"}
}
