{
  "type": "Feature",
  "properties": {
    "iso:country":"US",
    "sg:address":"638 N Main St",
    "sg:city":"Brockton",
    "sg:classifiers":[
        {
            "category":"Personal",
            "subcategory":"Beauty Salon",
            "type":"Services"
        }
    ],
    "sg:phone":"+1 508 587 3102",
    "sg:postcode":"02301",
    "sg:province":"MA",
    "wof:name":"Grace-Marie Beauty Salon",
    "wof:placetype":"venue"
},
  "geometry": {"coordinates":[-71.02024299999999,42.099115],"type":"Point"}
}