{
  "type": "Feature",
  "properties": {
    "iso:country":"US",
    "sg:address":"104 Moody St",
    "sg:city":"Ludlow",
    "sg:classifiers":[
        {
            "category":"Wholesale",
            "subcategory":"Durable Goods & Equipment",
            "type":"Manufacturing & Wholesale Goods"
        }
    ],
    "sg:phone":"+1 413 547 2600",
    "sg:postcode":"01056",
    "sg:province":"MA",
    "sg:tags":[
        "room",
        "drafting"
    ],
    "sg:website":"www.northsupp.com",
    "wof:name":"Northeast Supply Co",
    "wof:placetype":"venue"
},
  "geometry": {"coordinates":[-72.507698,42.186005],"type":"Point"}
}