{
  "type": "Feature",
  "properties": {
    "addr:full":"16 Chestnut St Boston MA 02108",
    "addr:housenumber":"16",
    "addr:postcode":"02108",
    "addr:street":"Chestnut St",
    "iso:country":"US",
    "sg:address":"16 Chestnut St",
    "sg:city":"Boston",
    "sg:classifiers":[
        {
            "category":"Banks & Credit Unions",
            "subcategory":"Financial Services",
            "type":"Services"
        },
        {
            "category":"Professional",
            "subcategory":"Business Services",
            "type":"Services"
        }
    ],
    "sg:phone":"+1 617 248 1510",
    "sg:postcode":"02108",
    "sg:province":"MA",
    "sg:tags":[
        "management"
    ],
    "wof:name":"Stockwell Wealth Management",
    "wof:placetype":"venue"
},
  "geometry": {"coordinates":[-71.066963,42.357619],"type":"Point"}
}