{
  "type": "Feature",
  "properties": {
    "addr:full": "90 Everett Avenue Suite 3 Chelsea MA 02150",
    "addr:housenumber": "90",
    "addr:postcode": "02150",
    "addr:street": "Everett Avenue Suite 3",
    "iso:country": "US",
    "sg:address": "90 Everett Avenue Suite 3",
    "sg:city": "Chelsea",
    "sg:classifiers": [
      {
        "category": "Sports \u0026 Exercise",
        "subcategory": "Gym",
        "type": "Entertainment"
      },
      {
        "category": "Health Services",
        "subcategory": "Health Practitioner",
        "type": "Services"
      },
      {
        "category": "Health Services",
        "subcategory": "Chiropractor",
        "type": "Services"
      }
    ],
    "sg:phone": "+1 617 887 2730",
    "sg:postcode": "02150",
    "sg:province": "MA",
    "sg:tags": [
      "trainer",
      "therapy",
      "physical"
    ],
    "wof:name": "Chelsea Chiropractic Office",
    "wof:placetype": "venue"
  },
  "geometry": {"coordinates":[-71.03954,42.39526],"type":"Point"}
}
