{
  "type": "Feature",
  "properties": {
    "addr:full":"336 Sugar Rd Bolton MA 01740",
    "addr:housenumber":"336",
    "addr:postcode":"01740",
    "addr:street":"Sugar Rd",
    "iso:country":"US",
    "sg:address":"336 Sugar Rd",
    "sg:city":"Bolton",
    "sg:classifiers":[
        {
            "category":"Arts & Performance",
            "subcategory":"Theater",
            "type":"Entertainment"
        }
    ],
    "sg:phone":"+1 978 779 8988",
    "sg:postcode":"01740",
    "sg:province":"MA",
    "sg:tags":[
        "group"
    ],
    "sg:website":"www.animaladventures.net",
    "wof:name":"Animal Adventures",
    "wof:placetype":"venue"
},
  "geometry": {"coordinates":[-71.584253,42.450591],"type":"Point"}
}