{
  "type": "Feature",
  "properties": {
    "addr:full": "333 Washington St Ste 435 Boston MA 02108",
    "addr:housenumber": "333",
    "addr:postcode": "02108",
    "addr:street": "Washington St Ste 435",
    "iso:country": "US",
    "sg:address": "333 Washington St Ste 435",
    "sg:city": "Boston",
    "sg:classifiers": [
      {
        "category": "Shopping",
        "subcategory": "Pawn Shop",
        "type": "Retail Goods"
      }
    ],
    "sg:phone": "+1 617 482 4403",
    "sg:postcode": "02108",
    "sg:province": "MA",
    "wof:name": "Williams of Boston Jewelry \u0026 Loan",
    "wof:placetype": "venue"
  },
  "geometry": {"coordinates":[-71.058981,42.356793],"type":"Point"}
}
