{
  "type": "Feature",
  "properties": {
    "iso:country":"US",
    "sg:address":"75 Stockwell Dr",
    "sg:city":"Avon",
    "sg:classifiers":[
        {
            "category":"Freight",
            "type":"Transportation"
        }
    ],
    "sg:phone":"+1 508 580 4697",
    "sg:postcode":"02322",
    "sg:province":"MA",
    "wof:name":"Exel Direct",
    "wof:placetype":"venue"
},
  "geometry": {"coordinates":[-71.066937,42.128166],"type":"Point"}
}