{
  "type": "Feature",
  "properties": {
    "iso:country":"US",
    "sg:address":"55 The Strand St",
    "sg:city":"Quincy",
    "sg:classifiers":[
        {
            "category":"Education",
            "subcategory":"Vocational School",
            "type":"Public Place"
        }
    ],
    "sg:phone":"+1 617 770 1267",
    "sg:postcode":"02170",
    "sg:province":"MA",
    "sg:tags":[
        "sewing",
        "instruction"
    ],
    "wof:name":"In Stitches Sewing & Design",
    "wof:placetype":"venue"
},
  "geometry": {"coordinates":[-71.00681899999999,42.275374],"type":"Point"}
}