{
  "type": "Feature",
  "properties": {
    "iso:country":"US",
    "sg:address":"95 Maple Ave",
    "sg:city":"Andover",
    "sg:classifiers":[
        {
            "category":"Real Estate",
            "subcategory":"Architect",
            "type":"Services"
        }
    ],
    "sg:phone":"+1 978 470 2393",
    "sg:postcode":"01810",
    "sg:province":"MA",
    "wof:name":"Andover Design Guild Inc",
    "wof:placetype":"venue"
},
  "geometry": {"coordinates":[-71.139207,42.660003],"type":"Point"}
}