{
  "type": "Feature",
  "properties": {
    "addr:full":"262 W Grove St Middleboro MA 02346",
    "addr:housenumber":"262",
    "addr:postcode":"02346",
    "addr:street":"W Grove St",
    "iso:country":"US",
    "sg:address":"262 W Grove St",
    "sg:city":"Middleboro",
    "sg:classifiers":[
        {
            "category":"Organizations",
            "subcategory":"Community Association",
            "type":"Services"
        }
    ],
    "sg:phone":"+1 508 947 9867",
    "sg:postcode":"02346",
    "sg:province":"MA",
    "sg:tags":[
        "fraternal"
    ],
    "wof:name":"Knights Of Columbus",
    "wof:placetype":"venue"
},
  "geometry": {"coordinates":[-70.93722099999999,41.892421],"type":"Point"}
}