{
  "type": "Feature",
  "properties": {
    "iso:country":"US",
    "sg:address":"35 West St",
    "sg:city":"Westborough",
    "sg:classifiers":[
        {
            "category":"Professional",
            "subcategory":"Management & Consulting",
            "type":"Services"
        }
    ],
    "sg:phone":"+1   ",
    "sg:postcode":"01581",
    "sg:province":"MA",
    "sg:tags":[
        "technical"
    ],
    "wof:name":"William M Higgins",
    "wof:placetype":"venue"
},
  "geometry": {"coordinates":[-71.61999900000001,42.268868],"type":"Point"}
}