{
  "type": "Feature",
  "properties": {
    "addr:full":"50 Ardmore Rd Worcester MA 01609",
    "addr:housenumber":"50",
    "addr:postcode":"01609",
    "addr:street":"Ardmore Rd",
    "iso:country":"US",
    "sg:address":"50 Ardmore Rd",
    "sg:city":"Worcester",
    "sg:classifiers":[
        {
            "category":"Building & Trades",
            "subcategory":"Landscaping Services",
            "type":"Services"
        }
    ],
    "sg:phone":"+1 508 791 2668",
    "sg:postcode":"01609",
    "sg:province":"MA",
    "sg:tags":[
        "landscape",
        "contractor"
    ],
    "wof:name":"Jack Longone Landscape Contr",
    "wof:placetype":"venue"
},
  "geometry": {"coordinates":[-71.81908,42.287026],"type":"Point"}
}