{
  "type": "Feature",
  "properties": {
    "iso:country":"US",
    "sg:address":"725 Grafton St",
    "sg:city":"Worcester",
    "sg:classifiers":[
        {
            "category":"Food & Beverages",
            "subcategory":"Liquor & Beverages",
            "type":"Retail Goods"
        }
    ],
    "sg:phone":"+1 508 756 7167",
    "sg:postcode":"01604",
    "sg:province":"MA",
    "sg:website":"http://www.hbwines.com",
    "wof:name":"H & B Wines & Liquors",
    "wof:placetype":"venue"
},
  "geometry": {"coordinates":[-71.767708,42.250721],"type":"Point"}
}