{
  "type": "Feature",
  "properties": {
    "addr:full": "725 Grafton St Worcester MA 01604",
    "addr:housenumber": "725",
    "addr:postcode": "01604",
    "addr:street": "Grafton St",
    "iso:country": "US",
    "ovtr:label": "H\u0026B Wines \u0026 Liquors, 725 Grafton St Worcester MA US",
    "ovtr:similarity": 2.33388090133667,
    "sg:address": "725 Grafton St",
    "sg:city": "Worcester",
    "sg:classifiers": [
      {
        "category": "Food \u0026 Beverages",
        "subcategory": "Liquor \u0026 Beverages",
        "type": "Retail Goods"
      }
    ],
    "sg:phone": "+1 508 756 7167",
    "sg:postcode": "01604",
    "sg:province": "MA",
    "sg:website": "http://www.hbwines.com",
    "wof:name": "H \u0026 B Wines \u0026 Liquors",
    "wof:placetype": "venue"
  },
  "geometry": {"coordinates":[-71.767708,42.250721],"type":"Point"}
}
