{
  "type": "Feature",
  "properties": {
    "addr:full": "27 Whitfield Rd Somerville MA 02144",
    "addr:housenumber": "27",
    "addr:postcode": "02144",
    "addr:street": "Whitfield Rd",
    "iso:country": "US",
    "sg:address": "27 Whitfield Rd",
    "sg:city": "Somerville",
    "sg:classifiers": [
      {
        "category": "Health Services",
        "subcategory": "Doctor",
        "type": "Services"
      },
      {
        "category": "Sports \u0026 Exercise",
        "subcategory": "Gym",
        "type": "Entertainment"
      },
      {
        "category": "Arena",
        "subcategory": "Sports Club",
        "type": "Entertainment"
      }
    ],
    "sg:phone": "+1 617 776 6161",
    "sg:postcode": "02144",
    "sg:province": "MA",
    "sg:tags": [
      "trainer",
      "martial art"
    ],
    "wof:name": "Central Institute of Tae Kwon DO",
    "wof:placetype": "venue"
  },
  "geometry": {"coordinates":[-71.123378,42.405836],"type":"Point"}
}
