{
  "type": "Feature",
  "properties": {
    "addr:full": "210 Bent St Cambridge MA 02141",
    "addr:housenumber": "210",
    "addr:postcode": "02141",
    "addr:street": "Bent St",
    "iso:country": "US",
    "sg:address": "210 Bent St",
    "sg:city": "Cambridge",
    "sg:classifiers": [
      {
        "category": "Professional",
        "subcategory": "Advertising",
        "type": "Services"
      }
    ],
    "sg:phone": "+1 617 577 7654",
    "sg:postcode": "02141",
    "sg:province": "MA",
    "sg:tags": [
      "counselor"
    ],
    "wof:name": "Flynn Advertising",
    "wof:placetype": "venue"
  },
  "geometry": {"coordinates":[-71.082042,42.367028],"type":"Point"}
}
