{
  "type": "Feature",
  "properties": {
    "iso:country":"US",
    "sg:address":"428 Boston Rd",
    "sg:city":"Billerica",
    "sg:classifiers":[
        {
            "category":"Sports & Exercise",
            "subcategory":"Bicycle Rental",
            "type":"Entertainment"
        }
    ],
    "sg:phone":"+1 978 671 0800",
    "sg:postcode":"01821",
    "sg:province":"MA",
    "sg:tags":[
        "bike"
    ],
    "wof:name":"Ridemakers Bike & Board - CLOSED",
    "wof:placetype":"venue"
},
  "geometry": {"coordinates":[-71.269203,42.559399],"type":"Point"}
}