{
  "type": "Feature",
  "properties": {
    "iso:country":"US",
    "sg:address":"182 Haverhill St",
    "sg:city":"Methuen",
    "sg:classifiers":[
        {
            "category":"Food & Beverages",
            "subcategory":"Liquor & Beverages",
            "type":"Retail Goods"
        }
    ],
    "sg:phone":"+1 978 686 2949",
    "sg:postcode":"01844",
    "sg:province":"MA",
    "wof:name":"Plaza Liquors",
    "wof:placetype":"venue"
},
  "geometry": {"coordinates":[-71.19874,42.706335],"type":"Point"}
}