{
  "type": "Feature",
  "properties": {
    "addr:full": "182 Haverhill St Methuen MA 01844",
    "addr:housenumber": "182",
    "addr:postcode": "01844",
    "addr:street": "Haverhill St",
    "iso:country": "US",
    "ovtr:label": "Plaza Liquors, 182 Haverhill St Methuen MA US",
    "ovtr:similarity": 2.568463087081909,
    "sg:address": "182 Haverhill St",
    "sg:city": "Methuen",
    "sg:classifiers": [
      {
        "category": "Food \u0026 Beverages",
        "subcategory": "Liquor \u0026 Beverages",
        "type": "Retail Goods"
      }
    ],
    "sg:phone": "+1 978 686 2949",
    "sg:postcode": "01844",
    "sg:province": "MA",
    "wof:name": "Plaza Liquors",
    "wof:placetype": "venue"
  },
  "geometry": {"coordinates":[-71.19874,42.706335],"type":"Point"}
}
