{
  "type": "Feature",
  "properties": {
    "addr:full": "29 Center St Nantucket MA 02554",
    "addr:housenumber": "29",
    "addr:postcode": "02554",
    "addr:street": "Center St",
    "iso:country": "US",
    "sg:address": "29 Center St",
    "sg:city": "Nantucket",
    "sg:classifiers": [
      {
        "category": "Wholesale",
        "subcategory": "Jewelry",
        "type": "Manufacturing \u0026 Wholesale Goods"
      }
    ],
    "sg:phone": "+1 508 228 6060",
    "sg:postcode": "02554",
    "sg:province": "MA",
    "sg:tags": [
      "beads"
    ],
    "wof:name": "No Strings Attached",
    "wof:placetype": "venue"
  },
  "geometry": {"coordinates":[-70.099983,41.283933],"type":"Point"}
}
