{
  "type": "Feature",
  "properties": {
    "iso:country":"US",
    "sg:address":"29 Center St",
    "sg:city":"Nantucket",
    "sg:classifiers":[
        {
            "category":"Wholesale",
            "subcategory":"Jewelry",
            "type":"Manufacturing & Wholesale Goods"
        }
    ],
    "sg:phone":"+1 508 228 6060",
    "sg:postcode":"02554",
    "sg:province":"MA",
    "sg:tags":[
        "beads"
    ],
    "wof:name":"No Strings Attached",
    "wof:placetype":"venue"
},
  "geometry": {"coordinates":[-70.09998299999999,41.283933],"type":"Point"}
}