{
  "type": "Feature",
  "properties": {
    "addr:full": "290 1/2 State St Boston MA 02109",
    "addr:housenumber": "290 1 / 2",
    "addr:postcode": "02109",
    "addr:street": "State St",
    "iso:country": "US",
    "sg:address": "290 1/2 State St",
    "sg:city": "Boston",
    "sg:classifiers": [
      {
        "category": "Real Estate",
        "subcategory": "Surveying",
        "type": "Services"
      }
    ],
    "sg:phone": "+1 617 445 7411",
    "sg:postcode": "02109",
    "sg:province": "MA",
    "sg:tags": [
      "planning",
      "land"
    ],
    "wof:name": "Vida Nueva Inc",
    "wof:placetype": "venue"
  },
  "geometry": {"coordinates":[-71.051064,42.359744],"type":"Point"}
}
