{
  "type": "Feature",
  "properties": {
    "iso:country":"US",
    "sg:address":"439 Bolton St",
    "sg:city":"New Bedford",
    "sg:classifiers":[
        {
            "category":"Local Transit",
            "type":"Transportation"
        }
    ],
    "sg:phone":"+1 508 999 5466",
    "sg:postcode":"02740",
    "sg:province":"MA",
    "sg:tags":[
        "limousine"
    ],
    "wof:name":"Ideal Limo",
    "wof:placetype":"venue"
},
  "geometry": {"coordinates":[-70.93069800000001,41.619384],"type":"Point"}
}