{
  "type": "Feature",
  "properties": {
    "addr:full":"460 Hancock St Springfield MA 01105",
    "addr:housenumber":"460",
    "addr:postcode":"01105",
    "addr:street":"Hancock St",
    "iso:country":"US",
    "sg:address":"460 Hancock St",
    "sg:city":"Springfield",
    "sg:classifiers":[
        {
            "category":"Real Estate",
            "subcategory":"Real Estate Operator",
            "type":"Services"
        }
    ],
    "sg:phone":"+1 413 737 3810",
    "sg:postcode":"01105",
    "sg:province":"MA",
    "sg:tags":[
        "apartment"
    ],
    "wof:name":"Hill Homes Housing Cooperative",
    "wof:placetype":"venue"
},
  "geometry": {"coordinates":[-72.56881,42.093574],"type":"Point"}
}