{
  "type": "Feature",
  "properties": {
    "addr:full":"150 W Park St Lee MA 01238",
    "addr:housenumber":"150",
    "addr:postcode":"01238",
    "addr:street":"W Park St",
    "iso:country":"US",
    "sg:address":"150 W Park St",
    "sg:city":"Lee",
    "sg:classifiers":[
        {
            "category":"Retail",
            "subcategory":"Auto Repair",
            "type":"Services"
        }
    ],
    "sg:phone":"+1 413 243 2112",
    "sg:postcode":"01238",
    "sg:province":"MA",
    "sg:tags":[
        "repairing",
        "automobile"
    ],
    "wof:name":"Bob Denley's Foreign Auto Rprs",
    "wof:placetype":"venue"
},
  "geometry": {"coordinates":[-73.250792,42.303885],"type":"Point"}
}