{
  "type": "Feature",
  "properties": {
    "addr:full":"796 Tyler St Pittsfield MA 01201",
    "addr:housenumber":"796",
    "addr:postcode":"01201",
    "addr:street":"Tyler St",
    "iso:country":"US",
    "sg:address":"796 Tyler St",
    "sg:city":"Pittsfield",
    "sg:classifiers":[
        {
            "category":"Restaurant",
            "type":"Food & Drink"
        }
    ],
    "sg:phone":"+1 413 447 9406",
    "sg:postcode":"01201",
    "sg:province":"MA",
    "wof:name":"Tyler Restaurant",
    "wof:placetype":"venue"
},
  "geometry": {"coordinates":[-73.234784,42.456379],"type":"Point"}
}