{
  "type": "Feature",
  "properties": {
    "iso:country":"US",
    "sg:address":"3 Industrial Park Rd",
    "sg:city":"Plymouth",
    "sg:classifiers":[
        {
            "category":"Home & Garden",
            "subcategory":"Home Furnishings",
            "type":"Retail Goods"
        }
    ],
    "sg:phone":"+1 508 747 3000",
    "sg:postcode":"02360",
    "sg:province":"MA",
    "sg:tags":[
        "lighting",
        "fixture"
    ],
    "wof:name":"Granite City Electric Supply",
    "wof:placetype":"venue"
},
  "geometry": {"coordinates":[-70.69873699999999,41.962139],"type":"Point"}
}