{
  "type": "Feature",
  "properties": {
    "addr:full": "28 Walker Street Charlestown MA 02129",
    "addr:housenumber": "28",
    "addr:postcode": "02129",
    "addr:street": "Walker Street",
    "iso:country": "US",
    "sg:address": "28 Walker Street",
    "sg:city": "Charlestown",
    "sg:classifiers": [
      {
        "category": "Education",
        "subcategory": "School",
        "type": "Public Place"
      }
    ],
    "sg:phone": "+1 617 635 8516",
    "sg:postcode": "02129",
    "sg:province": "MA",
    "sg:tags": [
      "high",
      "middle",
      "elementary"
    ],
    "wof:name": "Boston City of",
    "wof:placetype": "venue"
  },
  "geometry": {"coordinates":[-71.066786,42.379007],"type":"Point"}
}
