{
  "type": "Feature",
  "properties": {
    "addr:full": "142 State Rd Westminster MA 01436",
    "addr:housenumber": "142",
    "addr:postcode": "01436",
    "addr:street": "State Rd",
    "iso:country": "US",
    "sg:address": "142 State Rd",
    "sg:city": "Westminster",
    "sg:classifiers": [
      {
        "category": "Retail",
        "subcategory": "Auto Repair",
        "type": "Services"
      }
    ],
    "sg:phone": "+1 978 874 0319",
    "sg:postcode": "01436",
    "sg:province": "MA",
    "sg:tags": [
      "automobile",
      "lubrication"
    ],
    "wof:name": "Hal Smith Engineering",
    "wof:placetype": "venue"
  },
  "geometry": {"coordinates":[-72.062098,42.601514],"type":"Point"}
}
