{
  "type": "Feature",
  "properties": {
    "iso:country":"US",
    "sg:address":"536 Broad St",
    "sg:city":"East Weymouth",
    "sg:classifiers":[
        {
            "category":"Health Services",
            "subcategory":"Doctor",
            "type":"Services"
        }
    ],
    "sg:phone":"+1 781 331 2442",
    "sg:postcode":"02189",
    "sg:province":"MA",
    "sg:tags":[
        "dentist"
    ],
    "wof:name":"Richard A Zuppardi DDS",
    "wof:placetype":"venue"
},
  "geometry": {"coordinates":[-70.937586,42.217644],"type":"Point"}
}