{
  "type": "Feature",
  "properties": {
    "iso:country":"US",
    "sg:address":"4 Brookfield Rd",
    "sg:city":"Milford",
    "sg:classifiers":[
        {
            "category":"Manufacturing",
            "subcategory":"Food",
            "type":"Manufacturing & Wholesale Goods"
        }
    ],
    "sg:phone":"+1 508 482 5554",
    "sg:postcode":"01757",
    "sg:province":"MA",
    "sg:tags":[
        "product",
        "manufacturer"
    ],
    "wof:name":"Next Proteins",
    "wof:placetype":"venue"
},
  "geometry": {"coordinates":[-71.535431,42.164881],"type":"Point"}
}