{
  "type": "Feature",
  "properties": {
    "iso:country":"US",
    "sg:address":"2 Pickard Ln",
    "sg:city":"Littleton",
    "sg:classifiers":[
        {
            "category":"Education",
            "subcategory":"Preschool",
            "type":"Public Place"
        },
        {
            "category":"Education",
            "subcategory":"School",
            "type":"Public Place"
        }
    ],
    "sg:phone":"+1 978 486 9874",
    "sg:postcode":"01460",
    "sg:province":"MA",
    "sg:tags":[
        "elementary"
    ],
    "wof:name":"Oak Meadow Montessori",
    "wof:placetype":"venue"
},
  "geometry": {"coordinates":[-71.444901,42.531101],"type":"Point"}
}