{
  "type": "Feature",
  "properties": {
    "addr:full":"14 Clyde St Newton MA 02460",
    "addr:housenumber":"14",
    "addr:postcode":"02460",
    "addr:street":"Clyde St",
    "iso:country":"US",
    "sg:address":"14 Clyde St",
    "sg:city":"Newton",
    "sg:classifiers":[
        {
            "category":"Communications",
            "subcategory":"Film & Video Production",
            "type":"Services"
        }
    ],
    "sg:phone":"+1 617 964 4466",
    "sg:postcode":"02460",
    "sg:province":"MA",
    "sg:tags":[
        "taping"
    ],
    "wof:name":"Nick Kaufman Productions",
    "wof:placetype":"venue"
},
  "geometry": {"coordinates":[-71.20438799999999,42.346463],"type":"Point"}
}