{
  "type": "Feature",
  "properties": {
    "iso:country":"US",
    "sg:address":"1308 Commonwealth Ave",
    "sg:city":"Allston",
    "sg:classifiers":[
        {
            "category":"Building & Trades",
            "subcategory":"Locksmith",
            "type":"Services"
        }
    ],
    "sg:phone":"+1 617 415 9041",
    "sg:postcode":"02134",
    "sg:province":"MA",
    "sg:tags":[
        "key"
    ],
    "wof:name":"24 7 Available Commonwealth Ave Locksm",
    "wof:placetype":"venue"
},
  "geometry": {"coordinates":[-71.13416100000001,42.348403],"type":"Point"}
}