{
  "type": "Feature",
  "properties": {
    "addr:full":"80 Main St Essex MA 01929",
    "addr:housenumber":"80",
    "addr:postcode":"01929",
    "addr:street":"Main St",
    "iso:country":"US",
    "sg:address":"80 Main St",
    "sg:city":"Essex",
    "sg:classifiers":[
        {
            "category":"Recreation",
            "subcategory":"Marina",
            "type":"Entertainment"
        }
    ],
    "sg:phone":"+1 978 768 7161",
    "sg:postcode":"01929",
    "sg:province":"MA",
    "wof:name":"Pike Marine",
    "wof:placetype":"venue"
},
  "geometry": {"coordinates":[-70.77456599999999,42.630832],"type":"Point"}
}