{
  "type": "Feature",
  "properties": {
    "addr:full":"88 Black Falcon Ave Boston MA 02210",
    "addr:housenumber":"88",
    "addr:postcode":"02210",
    "addr:street":"Black Falcon Ave",
    "iso:country":"US",
    "sg:address":"88 Black Falcon Ave",
    "sg:city":"Boston",
    "sg:classifiers":[
        {
            "category":"Freight",
            "type":"Transportation"
        }
    ],
    "sg:phone":"+1 617 439 8989",
    "sg:postcode":"02210",
    "sg:province":"MA",
    "wof:name":"Amb Intl Airport Ctr LLC",
    "wof:placetype":"venue"
},
  "geometry": {"coordinates":[-71.027368,42.3448],"type":"Point"}
}