{
  "type": "Feature",
  "properties": {
    "addr:full":"280 Worcester Rd Framingham MA 01702",
    "addr:housenumber":"280",
    "addr:postcode":"01702",
    "addr:street":"Worcester Rd",
    "iso:country":"US",
    "sg:address":"280 Worcester Rd",
    "sg:city":"Framingham",
    "sg:classifiers":[
        {
            "category":"Building & Trades",
            "subcategory":"Construction",
            "type":"Services"
        }
    ],
    "sg:phone":"+1 508 820 7727",
    "sg:postcode":"01702",
    "sg:province":"MA",
    "sg:tags":[
        "designer",
        "dealer",
        "pool",
        "swimming"
    ],
    "sg:website":"www.spadiscounters.com",
    "wof:name":"SPADISCOUNTERS.COM",
    "wof:placetype":"venue"
},
  "geometry": {"coordinates":[-71.40557099999999,42.298291],"type":"Point"}
}