{
  "type": "Feature",
  "properties": {
    "iso:country":"US",
    "sg:address":"51 Harding St",
    "sg:city":"Worcester",
    "sg:classifiers":[
        {
            "category":"Wholesale",
            "subcategory":"Scrap",
            "type":"Manufacturing & Wholesale Goods"
        }
    ],
    "sg:phone":"+1 508 754 5711",
    "sg:postcode":"01604",
    "sg:province":"MA",
    "sg:tags":[
        "metal",
        "iron"
    ],
    "wof:name":"Goldstein Scrap Metal Inc",
    "wof:placetype":"venue"
},
  "geometry": {"coordinates":[-71.795288,42.259669],"type":"Point"}
}