{
  "type": "Feature",
  "properties": {
    "addr:full": "160 Commonwealth Ave Boston MA 02116",
    "addr:housenumber": "160",
    "addr:postcode": "02116",
    "addr:street": "Commonwealth Ave",
    "iso:country": "US",
    "sg:address": "160 Commonwealth Ave",
    "sg:city": "Boston",
    "sg:phone": "+1 617 266 1122",
    "sg:postcode": "02116",
    "sg:province": "MA",
    "wof:name": "Dartmouth Cafe",
    "wof:placetype": "venue"
  },
  "geometry": {"coordinates":[-71.078492,42.351623],"type":"Point"}
}
