{
  "type": "Feature",
  "properties": {
    "iso:country":"US",
    "sg:address":"1480 Blue Hill Ave",
    "sg:city":"Mattapan",
    "sg:classifiers":[
        {
            "category":"Retail",
            "subcategory":"Car Wash",
            "type":"Services"
        }
    ],
    "sg:phone":"+1 617 298 4466",
    "sg:postcode":"02126",
    "sg:province":"MA",
    "sg:tags":[
        "polishing",
        "washing"
    ],
    "wof:name":"Mattapan Car Wash & Quick Lube",
    "wof:placetype":"venue"
},
  "geometry": {"coordinates":[-71.093394,42.273741],"type":"Point"}
}