{
  "type": "Feature",
  "properties": {
    "iso:country":"US",
    "sg:address":"202 Bradford St",
    "sg:city":"Pittsfield",
    "sg:classifiers":[
        {
            "category":"Organizations",
            "subcategory":"Non-profit Organization",
            "type":"Services"
        }
    ],
    "sg:phone":"+1 413 499 2756",
    "sg:postcode":"01201",
    "sg:province":"MA",
    "sg:tags":[
        "info",
        "addiction",
        "abuse",
        "treatment",
        "drug"
    ],
    "wof:name":"Keenan House",
    "wof:placetype":"venue"
},
  "geometry": {"coordinates":[-73.25545,42.454724],"type":"Point"}
}