{
  "type": "Feature",
  "properties": {
    "addr:full":"92 Washington St Fairhaven MA 02719",
    "addr:housenumber":"92",
    "addr:postcode":"02719",
    "addr:street":"Washington St",
    "iso:country":"US",
    "sg:address":"92 Washington St",
    "sg:city":"Fairhaven",
    "sg:classifiers":[
        {
            "category":"Personal",
            "subcategory":"Beauty Salon",
            "type":"Services"
        }
    ],
    "sg:phone":"+1 508 991 8338",
    "sg:postcode":"02719",
    "sg:province":"MA",
    "wof:name":"Mirelia Hair Designs",
    "wof:placetype":"venue"
},
  "geometry": {"coordinates":[-70.897693,41.637938],"type":"Point"}
}