{
  "type": "Feature",
  "properties": {
    "iso:country":"US",
    "sg:address":"197 Main St",
    "sg:city":"Foxboro",
    "sg:classifiers":[
        {
            "category":"Building & Trades",
            "subcategory":"Construction",
            "type":"Services"
        }
    ],
    "sg:phone":"+1 508 698 0459",
    "sg:postcode":"02035",
    "sg:province":"MA",
    "sg:tags":[
        "general",
        "contractor"
    ],
    "wof:name":"Whitehouse Contracting Co",
    "wof:placetype":"venue"
},
  "geometry": {"coordinates":[-71.269865,42.075758],"type":"Point"}
}