{
  "type": "Feature",
  "properties": {
    "addr:full": "400 Arsenal St Watertown MA 02472",
    "addr:housenumber": "400",
    "addr:postcode": "02472",
    "addr:street": "Arsenal St",
    "iso:country": "US",
    "sg:address": "400 Arsenal St",
    "sg:city": "Watertown",
    "sg:classifiers": [
      {
        "category": "Wholesale",
        "subcategory": "Machinery \u0026 Supplies",
        "type": "Manufacturing \u0026 Wholesale Goods"
      }
    ],
    "sg:phone": "+1 617 923 1730",
    "sg:postcode": "02472",
    "sg:province": "MA",
    "sg:tags": [
      "industrial",
      "machinery-new",
      "equipment",
      "used",
      "supplies-wholesale"
    ],
    "sg:website": "http://www.grainger.com",
    "wof:name": "Grainger Industrial Supply",
    "wof:placetype": "venue"
  },
  "geometry": {"coordinates":[-71.165154,42.363682],"type":"Point"}
}
