{
  "type": "Feature",
  "properties": {
    "iso:country":"US",
    "sg:address":"1280 Soldiers Field Rd Ste 1",
    "sg:city":"Brighton",
    "sg:classifiers":[
        {
            "category":"Professional",
            "subcategory":"Accounting & Tax Preparation",
            "type":"Services"
        }
    ],
    "sg:phone":"+1 617 783 2500",
    "sg:postcode":"02135",
    "sg:province":"MA",
    "sg:tags":[
        "accountant"
    ],
    "sg:website":"www.starrllp.com",
    "wof:name":"Starr Finer Starr Llp",
    "wof:placetype":"venue"
},
  "geometry": {"coordinates":[-71.137604,42.363998],"type":"Point"}
}