{
  "type": "Feature",
  "properties": {
    "addr:full":"520 North Ave Wakefield MA 01880",
    "addr:housenumber":"520",
    "addr:postcode":"01880",
    "addr:street":"North Ave",
    "iso:country":"US",
    "sg:address":"520 North Ave",
    "sg:city":"Wakefield",
    "sg:classifiers":[
        {
            "category":"Building & Trades",
            "subcategory":"Construction",
            "type":"Services"
        }
    ],
    "sg:phone":"+1 781 246 3634",
    "sg:postcode":"01880",
    "sg:province":"MA",
    "sg:tags":[
        "roofing",
        "contractor"
    ],
    "wof:name":"Mike Robbins Roofing & Home",
    "wof:placetype":"venue"
},
  "geometry": {"coordinates":[-71.082534,42.510582],"type":"Point"}
}