{
  "type": "Feature",
  "properties": {
    "iso:country":"US",
    "sg:address":"30 Greenleaves Dr",
    "sg:city":"Hadley",
    "sg:classifiers":[
        {
            "category":"Building & Trades",
            "subcategory":"Construction",
            "type":"Services"
        }
    ],
    "sg:phone":"+1 413 253 0081",
    "sg:postcode":"01002",
    "sg:province":"MA",
    "sg:tags":[
        "general",
        "contractor"
    ],
    "wof:name":"Russell Street Contractors",
    "wof:placetype":"venue"
},
  "geometry": {"coordinates":[-72.535512,42.362742],"type":"Point"}
}