{
  "type": "Feature",
  "properties": {
    "iso:country":"US",
    "sg:address":"7 Robert Bonazzoli Ave",
    "sg:city":"Hudson",
    "sg:classifiers":[
        {
            "category":"Manufacturing",
            "subcategory":"Metals",
            "type":"Manufacturing & Wholesale Goods"
        }
    ],
    "sg:phone":"+1 978 568 9292",
    "sg:postcode":"01749",
    "sg:province":"MA",
    "sg:tags":[
        "tool"
    ],
    "sg:website":"www.sharptool.com",
    "wof:name":"Sharp Tool Co",
    "wof:placetype":"venue"
},
  "geometry": {"coordinates":[-71.548536,42.391981],"type":"Point"}
}