{
  "type": "Feature",
  "properties": {
    "addr:full": "7 Robert Bonazzoli Ave Hudson MA 01749",
    "addr:housenumber": "7",
    "addr:postcode": "01749",
    "addr:street": "Robert Bonazzoli Ave",
    "iso:country": "US",
    "ovtr:label": "Sharp Tool Company, 7 Bonazzoli Ave Hudson MA US",
    "ovtr:similarity": 3.9886159896850586,
    "sg:address": "7 Robert Bonazzoli Ave",
    "sg:city": "Hudson",
    "sg:classifiers": [
      {
        "category": "Manufacturing",
        "subcategory": "Metals",
        "type": "Manufacturing \u0026 Wholesale Goods"
      }
    ],
    "sg:phone": "+1 978 568 9292",
    "sg:postcode": "01749",
    "sg:province": "MA",
    "sg:tags": [
      "tool"
    ],
    "sg:website": "www.sharptool.com",
    "wof:name": "Sharp Tool Co",
    "wof:placetype": "venue"
  },
  "geometry": {"coordinates":[-71.548536,42.391981],"type":"Point"}
}
