{
  "type": "Feature",
  "properties": {
    "addr:full":"602 Great Rd Stow MA 01775",
    "addr:housenumber":"602",
    "addr:postcode":"01775",
    "addr:street":"Great Rd",
    "iso:country":"US",
    "sg:address":"602 Great Rd",
    "sg:city":"Stow",
    "sg:classifiers":[
        {
            "category":"Professional",
            "subcategory":"Secretarial Services",
            "type":"Services"
        }
    ],
    "sg:phone":"+1 978 897 9066",
    "sg:postcode":"01775",
    "sg:province":"MA",
    "sg:tags":[
        "convention",
        "reporting",
        "court",
        "reporter"
    ],
    "wof:name":"Assurance Court Reporting Serv",
    "wof:placetype":"venue"
},
  "geometry": {"coordinates":[-71.525862,42.434225],"type":"Point"}
}