{
  "type": "Feature",
  "properties": {
    "iso:country":"US",
    "sg:address":"28 High St",
    "sg:city":"Clinton",
    "sg:classifiers":[
        {
            "category":"Home & Garden",
            "subcategory":"Carpets & Floor Coverings",
            "type":"Retail Goods"
        }
    ],
    "sg:phone":"+1 978 368 1223",
    "sg:postcode":"01510",
    "sg:province":"MA",
    "sg:tags":[
        "dealer",
        "rug"
    ],
    "wof:name":"Depot Floor Covering",
    "wof:placetype":"venue"
},
  "geometry": {"coordinates":[-71.68490799999999,42.416335],"type":"Point"}
}