{
  "type": "Feature",
  "properties": {
    "addr:full": "28 High St Clinton MA 01510",
    "addr:housenumber": "28",
    "addr:postcode": "01510",
    "addr:street": "High St",
    "iso:country": "US",
    "sg:address": "28 High St",
    "sg:city": "Clinton",
    "sg:classifiers": [
      {
        "category": "Home \u0026 Garden",
        "subcategory": "Carpets \u0026 Floor Coverings",
        "type": "Retail Goods"
      }
    ],
    "sg:phone": "+1 978 368 1223",
    "sg:postcode": "01510",
    "sg:province": "MA",
    "sg:tags": [
      "dealer",
      "rug"
    ],
    "wof:name": "Depot Floor Covering",
    "wof:placetype": "venue"
  },
  "geometry": {"coordinates":[-71.684908,42.416335],"type":"Point"}
}
