{
  "type": "Feature",
  "properties": {
    "iso:country":"US",
    "sg:address":"2655 Main St",
    "sg:city":"Brewster",
    "sg:classifiers":[
        {
            "category":"Real Estate",
            "subcategory":"Real Estate Agent",
            "type":"Services"
        }
    ],
    "sg:phone":"+1 508 896 2290",
    "sg:postcode":"02631",
    "sg:province":"MA",
    "wof:name":"Stonecroft-Abbott Real Estate",
    "wof:placetype":"venue"
},
  "geometry": {"coordinates":[-70.057536,41.767984],"type":"Point"}
}