{
  "type": "Feature",
  "properties": {
    "addr:full":"6 Arsene Way Fairhaven MA 02719",
    "addr:housenumber":"6",
    "addr:postcode":"02719",
    "addr:street":"Arsene Way",
    "iso:country":"US",
    "sg:address":"6 Arsene Way",
    "sg:city":"Fairhaven",
    "sg:classifiers":[
        {
            "category":"Wholesale",
            "subcategory":"Auto Parts",
            "type":"Manufacturing & Wholesale Goods"
        }
    ],
    "sg:phone":"+1   ",
    "sg:postcode":"02719",
    "sg:province":"MA",
    "wof:name":"Dynamic Automotive Distributor",
    "wof:placetype":"venue"
},
  "geometry": {"coordinates":[-70.880278,41.640323],"type":"Point"}
}