{
  "type": "Feature",
  "properties": {
    "addr:full": "150 Eastern Ave Chelsea MA 02150",
    "addr:housenumber": "150",
    "addr:postcode": "02150",
    "addr:street": "Eastern Ave",
    "iso:country": "US",
    "sg:address": "150 Eastern Ave",
    "sg:city": "Chelsea",
    "sg:classifiers": [
      {
        "category": "Freight",
        "type": "Transportation"
      }
    ],
    "sg:phone": "+1 617 887 1399",
    "sg:postcode": "02150",
    "sg:province": "MA",
    "wof:name": "Kamino International Transport",
    "wof:placetype": "venue"
  },
  "geometry": {"coordinates":[-71.022373,42.391992],"type":"Point"}
}
