{
  "type": "Feature",
  "properties": {
    "iso:country":"US",
    "sg:address":"133 Market St",
    "sg:city":"Lowell",
    "sg:classifiers":[
        {
            "category":"Professional",
            "subcategory":"Lawyer & Legal Services",
            "type":"Services"
        }
    ],
    "sg:phone":"+1 978 453 1999",
    "sg:postcode":"01852",
    "sg:province":"MA",
    "sg:tags":[
        "attorney"
    ],
    "wof:name":"George C Eliades Jr",
    "wof:placetype":"venue"
},
  "geometry": {"coordinates":[-71.311128,42.644586],"type":"Point"}
}