{
  "type": "Feature",
  "properties": {
    "iso:country":"US",
    "sg:address":"561 Virginia Rd",
    "sg:city":"Concord",
    "sg:classifiers":[
        {
            "category":"Professional",
            "subcategory":"Computer Services",
            "type":"Services"
        }
    ],
    "sg:phone":"+1   ",
    "sg:postcode":"01742",
    "sg:province":"MA",
    "sg:tags":[
        "development",
        "software"
    ],
    "wof:name":"Sybase Inc",
    "wof:placetype":"venue"
},
  "geometry": {"coordinates":[-71.30147700000001,42.46626],"type":"Point"}
}