{
  "type": "Feature",
  "properties": {
    "iso:country":"US",
    "sg:address":"1201 Broadway",
    "sg:city":"Saugus",
    "sg:classifiers":[
        {
            "category":"Shopping",
            "subcategory":"Clothing, Apparel, & Fashions",
            "type":"Retail Goods"
        }
    ],
    "sg:phone":"+1 781 233 2118",
    "sg:postcode":"01906",
    "sg:province":"MA",
    "wof:name":"Forever 21",
    "wof:placetype":"venue"
},
  "geometry": {"coordinates":[-71.024805,42.463018],"type":"Point"}
}