{
  "type": "Feature",
  "properties": {
    "addr:full": "834 Morton St Mattapan MA 02126",
    "addr:housenumber": "834",
    "addr:postcode": "02126",
    "addr:street": "Morton St",
    "iso:country": "US",
    "sg:address": "834 Morton St",
    "sg:city": "Mattapan",
    "sg:classifiers": [
      {
        "category": "Personal",
        "subcategory": "Barber",
        "type": "Services"
      }
    ],
    "sg:phone": "+1 617 288 1787",
    "sg:postcode": "02126",
    "sg:province": "MA",
    "wof:name": "King Kuts",
    "wof:placetype": "venue"
  },
  "geometry": {"coordinates":[-71.085979,42.281169],"type":"Point"}
}
