{
  "type": "Feature",
  "properties": {
    "iso:country":"US",
    "sg:address":"8 Spring St",
    "sg:city":"West Springfield",
    "sg:classifiers":[
        {
            "category":"Health Services",
            "subcategory":"Clinic",
            "type":"Services"
        }
    ],
    "sg:phone":"+1 413 746 3070",
    "sg:postcode":"01089",
    "sg:province":"MA",
    "wof:name":"William Mc Keon",
    "wof:placetype":"venue"
},
  "geometry": {"coordinates":[-72.61326699999999,42.101652],"type":"Point"}
}