{
  "type": "Feature",
  "properties": {
    "iso:country":"US",
    "sg:address":"58 Andover St",
    "sg:city":"North Andover",
    "sg:classifiers":[
        {
            "category":"Retail",
            "subcategory":"Repair Shop",
            "type":"Services"
        }
    ],
    "sg:phone":"+1   ",
    "sg:postcode":"01845",
    "sg:province":"MA",
    "wof:name":"Pars Vcr Repair",
    "wof:placetype":"venue"
},
  "geometry": {"coordinates":[-71.115742,42.682949],"type":"Point"}
}