{
  "type": "Feature",
  "properties": {
    "iso:country":"US",
    "sg:address":"14 Loon Hill Rd",
    "sg:city":"Dracut",
    "sg:classifiers":[
        {
            "category":"Professional",
            "subcategory":"Lawyer & Legal Services",
            "type":"Services"
        }
    ],
    "sg:phone":"+1 978 458 1400",
    "sg:postcode":"01826",
    "sg:province":"MA",
    "sg:tags":[
        "attorney"
    ],
    "wof:name":"Grisley & Dristiliaris Law Ofc",
    "wof:placetype":"venue"
},
  "geometry": {"coordinates":[-71.287457,42.673146],"type":"Point"}
}