{
  "type": "Feature",
  "properties": {
    "addr:full": "97 Orient Ave Arlington MA 02474",
    "addr:housenumber": "97",
    "addr:postcode": "02474",
    "addr:street": "Orient Ave",
    "iso:country": "US",
    "sg:address": "97 Orient Ave",
    "sg:city": "Arlington",
    "sg:classifiers": [
      {
        "category": "Professional",
        "type": "Services"
      }
    ],
    "sg:phone": "+1   ",
    "sg:postcode": "02474",
    "sg:province": "MA",
    "wof:name": "Demand Planning LLC",
    "wof:placetype": "venue"
  },
  "geometry": {"coordinates":[-71.183049,42.432174],"type":"Point"}
}
