{
  "type": "Feature",
  "properties": {
    "addr:full":"16 School St Dedham MA 02026",
    "addr:housenumber":"16",
    "addr:postcode":"02026",
    "addr:street":"School St",
    "iso:country":"US",
    "sg:address":"16 School St",
    "sg:city":"Dedham",
    "sg:classifiers":[
        {
            "category":"Real Estate",
            "subcategory":"Real Estate Agent",
            "type":"Services"
        }
    ],
    "sg:phone":"+1 781 329 9919",
    "sg:postcode":"02026",
    "sg:province":"MA",
    "wof:name":"Valle Group",
    "wof:placetype":"venue"
},
  "geometry": {"coordinates":[-71.174572,42.247262],"type":"Point"}
}