{
  "type": "Feature",
  "properties": {
    "iso:country":"US",
    "sg:address":"1401 Boston-Providence Tpke",
    "sg:city":"Norwood",
    "sg:classifiers":[
        {
            "category":"Utilities",
            "subcategory":"Mobile Phone",
            "type":"Services"
        }
    ],
    "sg:phone":"+1 781 769 5521",
    "sg:postcode":"02062",
    "sg:province":"MA",
    "sg:tags":[
        "telephone",
        "cellular"
    ],
    "wof:name":"Wizard Wireless",
    "wof:placetype":"venue"
},
  "geometry": {"coordinates":[-71.198897,42.16487],"type":"Point"}
}