{
  "type": "Feature",
  "properties": {
    "iso:country":"US",
    "sg:address":"480 Lincoln Ave",
    "sg:city":"Saugus",
    "sg:classifiers":[
        {
            "category":"Professional",
            "subcategory":"Management & Consulting",
            "type":"Services"
        }
    ],
    "sg:phone":"+1 781 233 4440",
    "sg:postcode":"01906",
    "sg:province":"MA",
    "sg:tags":[
        "consultant",
        "security",
        "system"
    ],
    "wof:name":"Custom Security Svc",
    "wof:placetype":"venue"
},
  "geometry": {"coordinates":[-71.00892399999999,42.448577],"type":"Point"}
}