{
  "type": "Feature",
  "properties": {
    "addr:full":"53 State St Boston MA 02109",
    "addr:housenumber":"53",
    "addr:postcode":"02109",
    "addr:street":"State St",
    "iso:country":"US",
    "sg:address":"53 State St",
    "sg:city":"Boston",
    "sg:classifiers":[
        {
            "category":"Professional",
            "subcategory":"Lawyer & Legal Services",
            "type":"Services"
        }
    ],
    "sg:phone":"+1 617 227 5540",
    "sg:postcode":"02109",
    "sg:province":"MA",
    "wof:name":"Kozol Matthew S Lwyr",
    "wof:placetype":"venue"
},
  "geometry": {"coordinates":[-71.056702,42.358898],"type":"Point"}
}