{
  "type": "Feature",
  "properties": {
    "iso:country":"US",
    "sg:address":"23 Plymouth Rd",
    "sg:city":"Wellesley",
    "sg:classifiers":[
        {
            "category":"Personal",
            "type":"Services"
        }
    ],
    "sg:phone":"+1   ",
    "sg:postcode":"02481",
    "sg:province":"MA",
    "sg:tags":[
        "communications",
        "telephone"
    ],
    "wof:name":"World Lighting Index Inc",
    "wof:placetype":"venue"
},
  "geometry": {"coordinates":[-71.288507,42.310438],"type":"Point"}
}