{
  "type": "Feature",
  "properties": {
    "addr:full": "185 Powder Mill Rd Concord MA 01742",
    "addr:housenumber": "185",
    "addr:postcode": "01742",
    "addr:street": "Powder Mill Rd",
    "iso:country": "US",
    "ovtr:label": "Willard Elementary School, 185 Powder Mill Rd Concord MA US",
    "ovtr:similarity": 2.708415985107422,
    "sg:address": "185 Powder Mill Rd",
    "sg:city": "Concord",
    "sg:classifiers": [
      {
        "category": "Education",
        "subcategory": "School",
        "type": "Public Place"
      }
    ],
    "sg:phone": "+1 978 318 1340",
    "sg:postcode": "01742",
    "sg:province": "MA",
    "sg:tags": [
      "elementary"
    ],
    "wof:name": "Willard Elementary School",
    "wof:placetype": "venue"
  },
  "geometry": {"coordinates":[-71.382952,42.430865],"type":"Point"}
}
