{
  "type": "Feature",
  "properties": {
    "iso:country":"US",
    "sg:address":"401 Wareham Rd",
    "sg:city":"Marion",
    "sg:classifiers":[
        {
            "category":"Real Estate",
            "subcategory":"Real Estate Services",
            "type":"Services"
        },
        {
            "category":"Real Estate",
            "subcategory":"Real Estate Agent",
            "type":"Services"
        }
    ],
    "sg:phone":"+1 508 748 2234",
    "sg:postcode":"02738",
    "sg:province":"MA",
    "sg:tags":[
        "buyer",
        "broker"
    ],
    "sg:website":"http://www.johnsonbayside.com",
    "wof:name":"Johnson Bayside Real Estate Ltd",
    "wof:placetype":"venue"
},
  "geometry": {"coordinates":[-70.769974,41.71542],"type":"Point"}
}