{
  "type": "Feature",
  "properties": {
    "addr:full":"249 Burntmeadow Rd Groton MA 01450",
    "addr:housenumber":"249",
    "addr:postcode":"01450",
    "addr:street":"Burntmeadow Rd",
    "iso:country":"US",
    "sg:address":"249 Burntmeadow Rd",
    "sg:city":"Groton",
    "sg:classifiers":[
        {
            "category":"Professional",
            "subcategory":"Management & Consulting",
            "type":"Services"
        }
    ],
    "sg:phone":"+1 978 448 3400",
    "sg:postcode":"01450",
    "sg:province":"MA",
    "wof:name":"New Market Technologies",
    "wof:placetype":"venue"
},
  "geometry": {"coordinates":[-71.515698,42.617571],"type":"Point"}
}