{
  "type": "Feature",
  "properties": {
    "addr:full": "129 N Main St Bellingham MA 02019",
    "addr:housenumber": "129",
    "addr:postcode": "02019",
    "addr:street": "N Main St",
    "iso:country": "US",
    "sg:address": "129 N Main St",
    "sg:city": "Bellingham",
    "sg:classifiers": [
      {
        "category": "Personal",
        "subcategory": "Beauty Salon",
        "type": "Services"
      }
    ],
    "sg:phone": "+1 508 966 0890",
    "sg:postcode": "02019",
    "sg:province": "MA",
    "sg:tags": [
      "shop"
    ],
    "wof:name": "Linda's Beauty Corner",
    "wof:placetype": "venue"
  },
  "geometry": {"coordinates":[-71.472964,42.101248],"type":"Point"}
}
