{
  "type": "Feature",
  "properties": {
    "iso:country":"US",
    "sg:address":"233 Warren Ave",
    "sg:city":"Brockton",
    "sg:classifiers":[
        {
            "category":"Organizations",
            "subcategory":"Non-profit Organization",
            "type":"Services"
        }
    ],
    "sg:phone":"+1 508 584 5209",
    "sg:postcode":"02301",
    "sg:province":"MA",
    "sg:website":"www.bgcbrockton.org",
    "wof:name":"Boys & Girls Club Of Brockton",
    "wof:placetype":"venue"
},
  "geometry": {"coordinates":[-71.02298,42.081415],"type":"Point"}
}