{
  "type": "Feature",
  "properties": {
    "addr:full": "233 Warren Ave Brockton MA 02301",
    "addr:housenumber": "233",
    "addr:postcode": "02301",
    "addr:street": "Warren Ave",
    "iso:country": "US",
    "sg:address": "233 Warren Ave",
    "sg:city": "Brockton",
    "sg:classifiers": [
      {
        "category": "Organizations",
        "subcategory": "Non-profit Organization",
        "type": "Services"
      }
    ],
    "sg:phone": "+1 508 584 5209",
    "sg:postcode": "02301",
    "sg:province": "MA",
    "sg:website": "www.bgcbrockton.org",
    "wof:name": "Boys \u0026 Girls Club Of Brockton",
    "wof:placetype": "venue"
  },
  "geometry": {"coordinates":[-71.02298,42.081415],"type":"Point"}
}
