{
  "type": "Feature",
  "properties": {
    "iso:country":"US",
    "sg:address":"100 Route 44",
    "sg:city":"Raynham",
    "sg:classifiers":[
        {
            "category":"Professional",
            "subcategory":"Advertising",
            "type":"Services"
        }
    ],
    "sg:phone":"+1 508 822 3062",
    "sg:postcode":"02767",
    "sg:province":"MA",
    "sg:tags":[
        "mail",
        "direct"
    ],
    "wof:name":"Mail Room Etc",
    "wof:placetype":"venue"
},
  "geometry": {"coordinates":[-71.06259900000001,41.904966],"type":"Point"}
}