{
  "type": "Feature",
  "properties": {
    "addr:full": "82 Forest Street Medford MA 02155",
    "addr:housenumber": "82",
    "addr:postcode": "02155",
    "addr:street": "Forest Street",
    "iso:country": "US",
    "sg:address": "82 Forest Street",
    "sg:city": "Medford",
    "sg:classifiers": [
      {
        "category": "Health Services",
        "subcategory": "Doctor",
        "type": "Services"
      },
      {
        "category": "Sports \u0026 Exercise",
        "subcategory": "Gym",
        "type": "Entertainment"
      }
    ],
    "sg:phone": "+1 781 391 8333",
    "sg:postcode": "02155",
    "sg:province": "MA",
    "sg:tags": [
      "trainer",
      "practice",
      "family"
    ],
    "wof:name": "Lafontaine Paul D Phys",
    "wof:placetype": "venue"
  },
  "geometry": {"coordinates":[-71.108076,42.421094],"type":"Point"}
}
