{
  "type": "Feature",
  "properties": {
    "addr:full":"48 Boylston St Boston MA 02116",
    "addr:housenumber":"48",
    "addr:postcode":"02116",
    "addr:street":"Boylston St",
    "iso:country":"US",
    "sg:address":"48 Boylston St",
    "sg:city":"Boston",
    "sg:classifiers":[
        {
            "category":"Personal",
            "subcategory":"Massage",
            "type":"Services"
        }
    ],
    "sg:phone":"+1 617 460 0342",
    "sg:postcode":"02116",
    "sg:province":"MA",
    "sg:website":"www.bostonabsolutemassage.com",
    "wof:name":"Absolute Massage",
    "wof:placetype":"venue"
},
  "geometry": {"coordinates":[-71.063975,42.352303],"type":"Point"}
}