{
  "type": "Feature",
  "properties": {
    "addr:full": "11 Lafayette St Newburyport MA 01950",
    "addr:housenumber": "11",
    "addr:postcode": "01950",
    "addr:street": "Lafayette St",
    "iso:country": "US",
    "sg:address": "11 Lafayette St",
    "sg:city": "Newburyport",
    "sg:classifiers": [
      {
        "category": "Banks \u0026 Credit Unions",
        "subcategory": "Investment Brokerage",
        "type": "Services"
      }
    ],
    "sg:phone": "+1 978 462 9740",
    "sg:postcode": "01950",
    "sg:province": "MA",
    "sg:tags": [
      "consultant",
      "planning",
      "financial"
    ],
    "wof:name": "Thomas G Dwyer Assoc",
    "wof:placetype": "venue"
  },
  "geometry": {"coordinates":[-70.890094,42.815377],"type":"Point"}
}
