{
  "type": "Feature",
  "properties": {
    "addr:full": "240 Andover St North Andover MA 01845",
    "addr:housenumber": "240",
    "addr:postcode": "01845",
    "addr:street": "Andover St",
    "iso:country": "US",
    "sg:address": "240 Andover St",
    "sg:city": "North Andover",
    "sg:classifiers": [
      {
        "category": "Home \u0026 Garden",
        "subcategory": "Garden Supply",
        "type": "Retail Goods"
      }
    ],
    "sg:phone": "+1 978 725 0974",
    "sg:postcode": "01845",
    "sg:province": "MA",
    "sg:tags": [
      "fertilizer"
    ],
    "wof:name": "Ne Fertilizer Co",
    "wof:placetype": "venue"
  },
  "geometry": {"coordinates":[-71.120457,42.679507],"type":"Point"}
}
