{
  "type": "Feature",
  "properties": {
    "iso:country":"US",
    "sg:address":"240 Andover St",
    "sg:city":"North Andover",
    "sg:classifiers":[
        {
            "category":"Home & Garden",
            "subcategory":"Garden Supply",
            "type":"Retail Goods"
        }
    ],
    "sg:phone":"+1 978 725 0974",
    "sg:postcode":"01845",
    "sg:province":"MA",
    "sg:tags":[
        "fertilizer"
    ],
    "wof:name":"Ne Fertilizer Co",
    "wof:placetype":"venue"
},
  "geometry": {"coordinates":[-71.120457,42.679507],"type":"Point"}
}