{
  "type": "Feature",
  "properties": {
    "iso:country":"US",
    "sg:address":"72 Hathorne St",
    "sg:city":"Salem",
    "sg:classifiers":[
        {
            "category":"Health Services",
            "subcategory":"Chiropractor",
            "type":"Services"
        }
    ],
    "sg:phone":"+1 978 741 3016",
    "sg:postcode":"01970",
    "sg:province":"MA",
    "sg:tags":[
        "chiropractic"
    ],
    "wof:name":"Sheilagh",
    "wof:placetype":"venue"
},
  "geometry": {"coordinates":[-70.89959,42.515455],"type":"Point"}
}