{
  "type": "Feature",
  "properties": {
    "iso:country":"US",
    "sg:address":"24 High St",
    "sg:city":"Amesbury",
    "sg:classifiers":[
        {
            "category":"Manufacturing",
            "subcategory":"Tools & Machinery",
            "type":"Manufacturing & Wholesale Goods"
        },
        {
            "category":"Wholesale",
            "subcategory":"Machinery & Supplies",
            "type":"Manufacturing & Wholesale Goods"
        },
        {
            "category":"Home & Garden",
            "subcategory":"Hardware",
            "type":"Retail Goods"
        },
        {
            "category":"Manufacturing",
            "subcategory":"Building Materials",
            "type":"Manufacturing & Wholesale Goods"
        },
        {
            "category":"Sports & Exercise",
            "subcategory":"Ski Resort",
            "type":"Entertainment"
        }
    ],
    "sg:phone":"+1 978 801 0211",
    "sg:postcode":"01913",
    "sg:province":"MA",
    "sg:tags":[
        "abrasive",
        "nut",
        "pump",
        "pipe",
        "equipment",
        "fitting",
        "store",
        "painter",
        "bolt"
    ],
    "sg:website":"http://www.amesburyindustrial.com/index.html",
    "wof:name":"Amesbury Industrial Supply Company Incorporated",
    "wof:placetype":"venue"
},
  "geometry": {"coordinates":[-70.931837,42.858403],"type":"Point"}
}