{
  "type": "Feature",
  "properties": {
    "addr:full": "24 High St Amesbury MA 01913",
    "addr:housenumber": "24",
    "addr:postcode": "01913",
    "addr:street": "High St",
    "iso:country": "US",
    "sg:address": "24 High St",
    "sg:city": "Amesbury",
    "sg:classifiers": [
      {
        "category": "Manufacturing",
        "subcategory": "Tools \u0026 Machinery",
        "type": "Manufacturing \u0026 Wholesale Goods"
      },
      {
        "category": "Wholesale",
        "subcategory": "Machinery \u0026 Supplies",
        "type": "Manufacturing \u0026 Wholesale Goods"
      },
      {
        "category": "Home \u0026 Garden",
        "subcategory": "Hardware",
        "type": "Retail Goods"
      },
      {
        "category": "Manufacturing",
        "subcategory": "Building Materials",
        "type": "Manufacturing \u0026 Wholesale Goods"
      },
      {
        "category": "Sports \u0026 Exercise",
        "subcategory": "Ski Resort",
        "type": "Entertainment"
      }
    ],
    "sg:phone": "+1 978 801 0211",
    "sg:postcode": "01913",
    "sg:province": "MA",
    "sg:tags": [
      "abrasive",
      "nut",
      "pump",
      "pipe",
      "equipment",
      "fitting",
      "store",
      "painter",
      "bolt"
    ],
    "sg:website": "http://www.amesburyindustrial.com/index.html",
    "wof:name": "Amesbury Industrial Supply Company Incorporated",
    "wof:placetype": "venue"
  },
  "geometry": {"coordinates":[-70.931837,42.858403],"type":"Point"}
}
