{
  "type": "Feature",
  "properties": {
    "iso:country":"US",
    "sg:address":"498 Main St",
    "sg:city":"Centerville",
    "sg:classifiers":[
        {
            "category":"Professional",
            "subcategory":"Lawyer & Legal Services",
            "type":"Services"
        }
    ],
    "sg:phone":"+1 508 771 8756",
    "sg:postcode":"02632",
    "sg:province":"MA",
    "wof:name":"Mills Kenneth E Atty - CLOSED",
    "wof:placetype":"venue"
},
  "geometry": {"coordinates":[-70.34760300000001,41.6483],"type":"Point"}
}