{
  "type": "Feature",
  "properties": {
    "iso:country":"US",
    "sg:address":"231 Highland Ave",
    "sg:city":"Somerville",
    "sg:classifiers":[
        {
            "category":"Arts & Performance",
            "subcategory":"Theater",
            "type":"Entertainment"
        }
    ],
    "sg:phone":"+1   ",
    "sg:postcode":"02143",
    "sg:province":"MA",
    "sg:tags":[
        "theatrical"
    ],
    "wof:name":"Lightbourne Performing AR",
    "wof:placetype":"venue"
},
  "geometry": {"coordinates":[-71.10924,42.390847],"type":"Point"}
}