{
  "type": "Feature",
  "properties": {
    "addr:full":"774 Albany St Boston MA 02118",
    "addr:housenumber":"774",
    "addr:postcode":"02118",
    "addr:street":"Albany St",
    "iso:country":"US",
    "sg:address":"774 Albany St",
    "sg:city":"Boston",
    "sg:classifiers":[
        {
            "category":"Health Services",
            "subcategory":"Doctor",
            "type":"Services"
        }
    ],
    "sg:phone":"+1   ",
    "sg:postcode":"02118",
    "sg:province":"MA",
    "sg:tags":[
        "medical"
    ],
    "wof:name":"Dr Joanne Harris",
    "wof:placetype":"venue"
},
  "geometry": {"coordinates":[-71.06768099999999,42.337641],"type":"Point"}
}