{
  "type": "Feature",
  "properties": {
    "addr:full": "193 Elm St Salisbury MA 01952",
    "addr:housenumber": "193",
    "addr:postcode": "01952",
    "addr:street": "Elm St",
    "iso:country": "US",
    "sg:address": "193 Elm St",
    "sg:city": "Salisbury",
    "sg:classifiers": [
      {
        "category": "Retail",
        "subcategory": "Auto Rental",
        "type": "Services"
      }
    ],
    "sg:phone": "+1 978 499 0021",
    "sg:postcode": "01952",
    "sg:province": "MA",
    "sg:tags": [
      "renting",
      "automobile"
    ],
    "wof:name": "Enterprise Rent-A-Car",
    "wof:placetype": "venue"
  },
  "geometry": {"coordinates":[-70.893402,42.844132],"type":"Point"}
}
