{
  "type": "Feature",
  "properties": {
    "addr:full":"15 Marie Way Randolph MA 02368",
    "addr:housenumber":"15",
    "addr:postcode":"02368",
    "addr:street":"Marie Way",
    "iso:country":"US",
    "sg:address":"15 Marie Way",
    "sg:city":"Randolph",
    "sg:classifiers":[
        {
            "category":"Professional",
            "subcategory":"Computer Services",
            "type":"Services"
        }
    ],
    "sg:phone":"+1 781 958 0464",
    "sg:postcode":"02368",
    "sg:province":"MA",
    "sg:tags":[
        "website",
        "design"
    ],
    "wof:name":"Haynes Consulting",
    "wof:placetype":"venue"
},
  "geometry": {"coordinates":[-71.07058000000001,42.172019],"type":"Point"}
}