{
  "type": "Feature",
  "properties": {
    "addr:full":"108 Concord Ave Somerville MA 02143",
    "addr:housenumber":"108",
    "addr:postcode":"02143",
    "addr:street":"Concord Ave",
    "iso:country":"US",
    "sg:address":"108 Concord Ave",
    "sg:city":"Somerville",
    "sg:classifiers":[
        {
            "category":"Real Estate",
            "subcategory":"Real Estate Agent",
            "type":"Services"
        }
    ],
    "sg:phone":"+1   ",
    "sg:postcode":"02143",
    "sg:province":"MA",
    "sg:tags":[
        "property",
        "commercial",
        "operates"
    ],
    "wof:name":"Rodes Realty",
    "wof:placetype":"venue"
},
  "geometry": {"coordinates":[-71.10242,42.375105],"type":"Point"}
}