{
  "type": "Feature",
  "properties": {
    "addr:full": "3065 Cranberry Hwy East Wareham MA 02538",
    "addr:housenumber": "3065",
    "addr:postcode": "02538",
    "addr:street": "Cranberry Hwy",
    "iso:country": "US",
    "sg:address": "3065 Cranberry Hwy",
    "sg:city": "East Wareham",
    "sg:classifiers": [
      {
        "category": "Wholesale",
        "subcategory": "Construction Materials",
        "type": "Manufacturing \u0026 Wholesale Goods"
      }
    ],
    "sg:phone": "+1 508 273 0047",
    "sg:postcode": "02538",
    "sg:province": "MA",
    "sg:tags": [
      "concrete",
      "product"
    ],
    "sg:website": "www.fireslate.com",
    "wof:name": "Fireslate II Inc",
    "wof:placetype": "venue"
  },
  "geometry": {"coordinates":[-70.654044,41.756927],"type":"Point"}
}
