{
  "type": "Feature",
  "properties": {
    "iso:country":"US",
    "sg:address":"3065 Cranberry Hwy",
    "sg:city":"East Wareham",
    "sg:classifiers":[
        {
            "category":"Wholesale",
            "subcategory":"Construction Materials",
            "type":"Manufacturing & Wholesale Goods"
        }
    ],
    "sg:phone":"+1 508 273 0047",
    "sg:postcode":"02538",
    "sg:province":"MA",
    "sg:tags":[
        "concrete",
        "product"
    ],
    "sg:website":"www.fireslate.com",
    "wof:name":"Fireslate II Inc",
    "wof:placetype":"venue"
},
  "geometry": {"coordinates":[-70.654044,41.756927],"type":"Point"}
}