{
  "type": "Feature",
  "properties": {
    "addr:full": "57 Winesap Rd Pittsfield MA 01201",
    "addr:housenumber": "57",
    "addr:postcode": "01201",
    "addr:street": "Winesap Rd",
    "iso:country": "US",
    "sg:address": "57 Winesap Rd",
    "sg:city": "Pittsfield",
    "sg:classifiers": [
      {
        "category": "Restaurant",
        "type": "Food \u0026 Drink"
      }
    ],
    "sg:phone": "+1   ",
    "sg:postcode": "01201",
    "sg:province": "MA",
    "sg:tags": [
      "eating"
    ],
    "wof:name": "M\u0026M Catering Inc",
    "wof:placetype": "venue"
  },
  "geometry": {"coordinates":[-73.201043,42.446606],"type":"Point"}
}
