{
  "type": "Feature",
  "properties": {
    "iso:country":"US",
    "sg:address":"57 Winesap Rd",
    "sg:city":"Pittsfield",
    "sg:classifiers":[
        {
            "category":"Restaurant",
            "type":"Food & Drink"
        }
    ],
    "sg:phone":"+1   ",
    "sg:postcode":"01201",
    "sg:province":"MA",
    "sg:tags":[
        "eating"
    ],
    "wof:name":"M&M Catering Inc",
    "wof:placetype":"venue"
},
  "geometry": {"coordinates":[-73.201043,42.446606],"type":"Point"}
}