{
  "type": "Feature",
  "properties": {
    "addr:full":"165 Front St Chicopee MA 01013",
    "addr:housenumber":"165",
    "addr:postcode":"01013",
    "addr:street":"Front St",
    "iso:country":"US",
    "sg:address":"165 Front St",
    "sg:city":"Chicopee",
    "sg:classifiers":[
        {
            "category":"Wholesale",
            "subcategory":"Metals & Minerals",
            "type":"Manufacturing & Wholesale Goods"
        }
    ],
    "sg:phone":"+1 413 592 7877",
    "sg:postcode":"01013",
    "sg:province":"MA",
    "sg:tags":[
        "specialty"
    ],
    "wof:name":"Abstract Metal Fabrication",
    "wof:placetype":"venue"
},
  "geometry": {"coordinates":[-72.611739,42.148052],"type":"Point"}
}