{
  "type": "Feature",
  "properties": {
    "addr:full":"50 Merrimack St Haverhill MA 01830",
    "addr:housenumber":"50",
    "addr:postcode":"01830",
    "addr:street":"Merrimack St",
    "iso:country":"US",
    "sg:address":"50 Merrimack St",
    "sg:city":"Haverhill",
    "sg:classifiers":[
        {
            "category":"Recreation",
            "type":"Entertainment"
        }
    ],
    "sg:phone":"+1 978 373 4100",
    "sg:postcode":"01830",
    "sg:province":"MA",
    "sg:tags":[
        "martial",
        "arts",
        "instruction"
    ],
    "sg:website":"www.ocasiostruemartialarts.com",
    "wof:name":"Ocasio's True Martial Arts",
    "wof:placetype":"venue"
},
  "geometry": {"coordinates":[-71.078405,42.77464],"type":"Point"}
}