{
  "type": "Feature",
  "properties": {
    "addr:full":"5 Burlington Woods Burlington MA 01803",
    "addr:housenumber":"5",
    "addr:postcode":"01803",
    "addr:street":"Burlington",
    "iso:country":"US",
    "sg:address":"5 Burlington Woods",
    "sg:city":"Burlington",
    "sg:classifiers":[
        {
            "category":"Restaurant",
            "type":"Food & Drink"
        }
    ],
    "sg:phone":"+1 781 273 1270",
    "sg:postcode":"01803",
    "sg:province":"MA",
    "sg:tags":[
        "cafe"
    ],
    "wof:name":"Cafe Jazmin",
    "wof:placetype":"venue"
},
  "geometry": {"coordinates":[-71.198488,42.489786],"type":"Point"}
}