{
  "type": "Feature",
  "properties": {
    "iso:country":"US",
    "sg:address":"5 Washington Street",
    "sg:city":"Brighton",
    "sg:classifiers":[
        {
            "category":"Retail",
            "subcategory":"Auto Repair",
            "type":"Services"
        }
    ],
    "sg:phone":"+1 617 566 5050",
    "sg:postcode":"02135",
    "sg:province":"MA",
    "wof:name":"Brookline Auto Clinic",
    "wof:placetype":"venue"
},
  "geometry": {"coordinates":[-71.140101,42.342073],"type":"Point"}
}