{
  "type": "Feature",
  "properties": {
    "iso:country":"US",
    "sg:address":"19 Robin Rd",
    "sg:city":"Wakefield",
    "sg:classifiers":[
        {
            "category":"Wholesale",
            "subcategory":"Machinery & Supplies",
            "type":"Manufacturing & Wholesale Goods"
        }
    ],
    "sg:phone":"+1 781 245 0300",
    "sg:postcode":"01880",
    "sg:province":"MA",
    "sg:tags":[
        "equipment",
        "material",
        "handling"
    ],
    "sg:website":"www.dcgraves.com",
    "wof:name":"D C Graves Co",
    "wof:placetype":"venue"
},
  "geometry": {"coordinates":[-71.06735999999999,42.52148],"type":"Point"}
}