{
  "type": "Feature",
  "properties": {
    "addr:full": "19 Robin Rd Wakefield MA 01880",
    "addr:housenumber": "19",
    "addr:postcode": "01880",
    "addr:street": "Robin Rd",
    "iso:country": "US",
    "sg:address": "19 Robin Rd",
    "sg:city": "Wakefield",
    "sg:classifiers": [
      {
        "category": "Wholesale",
        "subcategory": "Machinery \u0026 Supplies",
        "type": "Manufacturing \u0026 Wholesale Goods"
      }
    ],
    "sg:phone": "+1 781 245 0300",
    "sg:postcode": "01880",
    "sg:province": "MA",
    "sg:tags": [
      "equipment",
      "material",
      "handling"
    ],
    "sg:website": "www.dcgraves.com",
    "wof:name": "D C Graves Co",
    "wof:placetype": "venue"
  },
  "geometry": {"coordinates":[-71.06736,42.52148],"type":"Point"}
}
