{
  "type": "Feature",
  "properties": {
    "iso:country":"US",
    "sg:address":"7 Trinity Ave",
    "sg:city":"Lakeville",
    "sg:classifiers":[
        {
            "category":"Professional",
            "subcategory":"Lawyer & Legal Services",
            "type":"Services"
        }
    ],
    "sg:phone":"+1 508 824 4806",
    "sg:postcode":"02338",
    "sg:province":"MA",
    "sg:tags":[
        "attorney"
    ],
    "wof:name":"Arter Law Offices",
    "wof:placetype":"venue"
},
  "geometry": {"coordinates":[-70.844686,42.015412],"type":"Point"}
}