{
  "type": "Feature",
  "properties": {
    "addr:full": "725 High St Westwood MA 02090",
    "addr:housenumber": "725",
    "addr:postcode": "02090",
    "addr:street": "High St",
    "iso:country": "US",
    "sg:address": "725 High St",
    "sg:city": "Westwood",
    "sg:classifiers": [
      {
        "category": "Restaurant",
        "type": "Food \u0026 Drink"
      }
    ],
    "sg:phone": "+1 781 326 8092",
    "sg:postcode": "02090",
    "sg:province": "MA",
    "sg:tags": [
      "eating"
    ],
    "wof:name": "Cobblers Inn",
    "wof:placetype": "venue"
  },
  "geometry": {"coordinates":[-71.222305,42.226258],"type":"Point"}
}
