{
  "type": "Feature",
  "properties": {
    "iso:country":"US",
    "sg:address":"725 High St",
    "sg:city":"Westwood",
    "sg:classifiers":[
        {
            "category":"Restaurant",
            "type":"Food & Drink"
        }
    ],
    "sg:phone":"+1 781 326 8092",
    "sg:postcode":"02090",
    "sg:province":"MA",
    "sg:tags":[
        "eating"
    ],
    "wof:name":"Cobblers Inn",
    "wof:placetype":"venue"
},
  "geometry": {"coordinates":[-71.22230500000001,42.226258],"type":"Point"}
}