{
  "type": "Feature",
  "properties": {
    "iso:country":"US",
    "sg:address":"83 Mill St",
    "sg:city":"Springfield",
    "sg:classifiers":[
        {
            "category":"Home & Garden",
            "subcategory":"Building Materials",
            "type":"Retail Goods"
        }
    ],
    "sg:phone":"+1 413 734 0495",
    "sg:postcode":"01108",
    "sg:province":"MA",
    "sg:tags":[
        "repair",
        "window",
        "windshield",
        "glass",
        "plate"
    ],
    "wof:name":"Joakin Auto Glass",
    "wof:placetype":"venue"
},
  "geometry": {"coordinates":[-72.576455,42.090925],"type":"Point"}
}