{
  "type": "Feature",
  "properties": {
    "addr:full":"163 Mystic Ave Medford MA 02155",
    "addr:housenumber":"163",
    "addr:postcode":"02155",
    "addr:street":"Mystic Ave",
    "iso:country":"US",
    "sg:address":"163 Mystic Ave",
    "sg:city":"Medford",
    "sg:classifiers":[
        {
            "category":"Wholesale",
            "subcategory":"Auto Parts",
            "type":"Manufacturing & Wholesale Goods"
        }
    ],
    "sg:phone":"+1 781 395 2176",
    "sg:postcode":"02155",
    "sg:province":"MA",
    "sg:tags":[
        "body",
        "automobile",
        "shop"
    ],
    "sg:website":"www.kwikauto.com",
    "wof:name":"KWIK Auto Body Supplies Inc",
    "wof:placetype":"venue"
},
  "geometry": {"coordinates":[-71.10485199999999,42.409113],"type":"Point"}
}