{
  "type": "Feature",
  "properties": {
    "addr:full":"450 Cambridge St Allston MA 02134",
    "addr:housenumber":"450",
    "addr:postcode":"02134",
    "addr:street":"Cambridge St",
    "iso:country":"US",
    "sg:address":"450 Cambridge St",
    "sg:city":"Allston",
    "sg:classifiers":[
        {
            "category":"Personal",
            "type":"Services"
        }
    ],
    "sg:phone":"+1 617 254 0025",
    "sg:postcode":"02134",
    "sg:province":"MA",
    "sg:tags":[
        "mover"
    ],
    "wof:name":"Boston Express Movers",
    "wof:placetype":"venue"
},
  "geometry": {"coordinates":[-71.135817,42.354218],"type":"Point"}
}