{
  "type": "Feature",
  "properties": {
    "iso:country":"US",
    "sg:address":"50 Maple Ave",
    "sg:city":"Sudbury",
    "sg:classifiers":[
        {
            "category":"Building & Trades",
            "subcategory":"Construction",
            "type":"Services"
        }
    ],
    "sg:phone":"+1   ",
    "sg:postcode":"01776",
    "sg:province":"MA",
    "sg:tags":[
        "carpentry",
        "contractor"
    ],
    "wof:name":"Hebb Carpentry",
    "wof:placetype":"venue"
},
  "geometry": {"coordinates":[-71.414925,42.359416],"type":"Point"}
}