{
  "type": "Feature",
  "properties": {
    "iso:country":"US",
    "sg:address":"58 Ridgewood Rd",
    "sg:city":"New Bedford",
    "sg:classifiers":[
        {
            "category":"Building & Trades",
            "subcategory":"Construction",
            "type":"Services"
        }
    ],
    "sg:phone":"+1 508 995 1449",
    "sg:postcode":"02745",
    "sg:province":"MA",
    "sg:tags":[
        "excavating",
        "contractor"
    ],
    "wof:name":"W C Smith & Son Inc",
    "wof:placetype":"venue"
},
  "geometry": {"coordinates":[-70.946941,41.714511],"type":"Point"}
}