{
  "type": "Feature",
  "properties": {
    "addr:full": "434 Hyde Park Ave Roslindale MA 02131",
    "addr:housenumber": "434",
    "addr:postcode": "02131",
    "addr:street": "Hyde Park Ave",
    "iso:country": "US",
    "sg:address": "434 Hyde Park Ave",
    "sg:city": "Roslindale",
    "sg:classifiers": [
      {
        "category": "Organizations",
        "subcategory": "Labor Organization",
        "type": "Services"
      }
    ],
    "sg:phone": "+1 617 325 3938",
    "sg:postcode": "02131",
    "sg:province": "MA",
    "sg:website": "www.bpdbs.com",
    "wof:name": "Boston Police Detective",
    "wof:placetype": "venue"
  },
  "geometry": {"coordinates":[-71.118641,42.28626],"type":"Point"}
}
