{
  "type": "Feature",
  "properties": {
    "iso:country":"US",
    "sg:address":"92 Harbor St",
    "sg:city":"New Bedford",
    "sg:classifiers":[
        {
            "category":"Wholesale",
            "subcategory":"Apparel",
            "type":"Manufacturing & Wholesale Goods"
        }
    ],
    "sg:phone":"+1 508 999 4584",
    "sg:postcode":"02744",
    "sg:province":"MA",
    "sg:tags":[
        "sportswear"
    ],
    "sg:website":"www.darn-it.com",
    "wof:name":"Darn It Inc",
    "wof:placetype":"venue"
},
  "geometry": {"coordinates":[-70.916433,41.616389],"type":"Point"}
}