{
  "type": "Feature",
  "properties": {
    "addr:full":"8 Chestnut St West Springfield MA 01089",
    "addr:housenumber":"8",
    "addr:postcode":"01089",
    "addr:street":"Chestnut St",
    "iso:country":"US",
    "sg:address":"8 Chestnut St",
    "sg:city":"West Springfield",
    "sg:classifiers":[
        {
            "category":"Personal",
            "subcategory":"Beauty Salon",
            "type":"Services"
        }
    ],
    "sg:phone":"+1   ",
    "sg:postcode":"01089",
    "sg:province":"MA",
    "sg:tags":[
        "shop"
    ],
    "wof:name":"Hair East Inc",
    "wof:placetype":"venue"
},
  "geometry": {"coordinates":[-72.63843300000001,42.105072],"type":"Point"}
}