{
  "type": "Feature",
  "properties": {
    "addr:full": "742 Washington St Canton MA 02021",
    "addr:housenumber": "742",
    "addr:postcode": "02021",
    "addr:street": "Washington St",
    "iso:country": "US",
    "sg:address": "742 Washington St",
    "sg:city": "Canton",
    "sg:classifiers": [
      {
        "category": "Professional",
        "subcategory": "Lawyer \u0026 Legal Services",
        "type": "Services"
      }
    ],
    "sg:phone": "+1 781 828 7660",
    "sg:postcode": "02021",
    "sg:province": "MA",
    "sg:tags": [
      "attorney"
    ],
    "wof:name": "Reuki Schutt",
    "wof:placetype": "venue"
  },
  "geometry": {"coordinates":[-71.145637,42.157498],"type":"Point"}
}
