{
  "type": "Feature",
  "properties": {
    "addr:full": "681 Main St Charlestown MA 02129",
    "addr:housenumber": "681",
    "addr:postcode": "02129",
    "addr:street": "Main St",
    "iso:country": "US",
    "sg:address": "681 Main St",
    "sg:city": "Charlestown",
    "sg:classifiers": [
      {
        "category": "Professional",
        "subcategory": "Printing \u0026 Photocopies",
        "type": "Services"
      }
    ],
    "sg:phone": "+1 617 783 3640",
    "sg:postcode": "02129",
    "sg:province": "MA",
    "sg:tags": [
      "photographers-commercial"
    ],
    "wof:name": "Evelyn Images",
    "wof:placetype": "venue"
  },
  "geometry": {"coordinates":[-71.075844,42.385452],"type":"Point"}
}
