{
  "type": "Feature",
  "properties": {
    "addr:full": "89 Main St Taunton MA 02780",
    "addr:housenumber": "89",
    "addr:postcode": "02780",
    "addr:street": "Main St",
    "iso:country": "US",
    "sg:address": "89 Main St",
    "sg:city": "Taunton",
    "sg:classifiers": [
      {
        "category": "Shopping",
        "subcategory": "Clothing, Apparel, \u0026 Fashions",
        "type": "Retail Goods"
      }
    ],
    "sg:phone": "+1 508 824 6900",
    "sg:postcode": "02780",
    "sg:province": "MA",
    "sg:tags": [
      "shop",
      "bridal"
    ],
    "wof:name": "New York Lace Store LTD",
    "wof:placetype": "venue"
  },
  "geometry": {"coordinates":[-71.090184,41.901561],"type":"Point"}
}
