{
  "type": "Feature",
  "properties": {
    "iso:country":"US",
    "sg:address":"714 Snipatuit Rd",
    "sg:city":"Rochester",
    "sg:classifiers":[
        {
            "category":"Recreation",
            "type":"Entertainment"
        }
    ],
    "sg:phone":"+1 508 763 3224",
    "sg:postcode":"02770",
    "sg:province":"MA",
    "wof:name":"Fairfield Farm",
    "wof:placetype":"venue"
},
  "geometry": {"coordinates":[-70.889168,41.781821],"type":"Point"}
}