{
  "type": "Feature",
  "properties": {
    "iso:country":"US",
    "sg:address":"6 Concord Ln",
    "sg:city":"Cambridge",
    "sg:classifiers":[
        {
            "category":"Restaurant",
            "type":"Food & Drink"
        }
    ],
    "sg:phone":"+1 617 354 9139",
    "sg:postcode":"02138",
    "sg:province":"MA",
    "sg:tags":[
        "pizza"
    ],
    "wof:name":"Ma Magoo's Pizza & Sub Shop",
    "wof:placetype":"venue"
},
  "geometry": {"coordinates":[-71.14116,42.388676],"type":"Point"}
}