{
  "type": "Feature",
  "properties": {
    "addr:full": "142 Main St Northampton MA 01060",
    "addr:housenumber": "142",
    "addr:postcode": "01060",
    "addr:street": "Main St",
    "iso:country": "US",
    "sg:address": "142 Main St",
    "sg:city": "Northampton",
    "sg:classifiers": [
      {
        "category": "Real Estate",
        "subcategory": "Architect",
        "type": "Services"
      }
    ],
    "sg:phone": "+1 413 586 5775",
    "sg:postcode": "01060",
    "sg:province": "MA",
    "wof:name": "Metcalfe Associates Arch",
    "wof:placetype": "venue"
  },
  "geometry": {"coordinates":[-72.631053,42.318572],"type":"Point"}
}
