{
  "type": "Feature",
  "properties": {
    "addr:full":"132 Central St Wrentham MA 02072",
    "addr:housenumber":"132",
    "addr:postcode":"02072",
    "addr:street":"Central St",
    "iso:country":"US",
    "sg:address":"132 Central St",
    "sg:city":"Wrentham",
    "sg:classifiers":[
        {
            "category":"Health Services",
            "subcategory":"Doctor",
            "type":"Services"
        }
    ],
    "sg:phone":"+1 508 543 8140",
    "sg:postcode":"02072",
    "sg:province":"MA",
    "sg:tags":[
        "physician",
        "surgeon"
    ],
    "wof:name":"Pediatric Specialists-Foxboro",
    "wof:placetype":"venue"
},
  "geometry": {"coordinates":[-71.072006,42.126169],"type":"Point"}
}