{
  "type": "Feature",
  "properties": {
    "addr:full":"915 Norton Ave Taunton MA 02780",
    "addr:housenumber":"915",
    "addr:postcode":"02780",
    "addr:street":"Norton Ave",
    "iso:country":"US",
    "sg:address":"915 Norton Ave",
    "sg:city":"Taunton",
    "sg:classifiers":[
        {
            "category":"Home & Garden",
            "subcategory":"Building Materials",
            "type":"Retail Goods"
        }
    ],
    "sg:phone":"+1 508 823 5648",
    "sg:postcode":"02780",
    "sg:province":"MA",
    "sg:tags":[
        "door"
    ],
    "wof:name":"Mulcahy Overhead Door",
    "wof:placetype":"venue"
},
  "geometry": {"coordinates":[-71.144268,41.927647],"type":"Point"}
}