{
  "type": "Feature",
  "properties": {
    "addr:full": "16 Sturbridge Rd Charlton MA 01507",
    "addr:housenumber": "16",
    "addr:postcode": "01507",
    "addr:street": "Sturbridge Rd",
    "iso:country": "US",
    "sg:address": "16 Sturbridge Rd",
    "sg:city": "Charlton",
    "sg:classifiers": [
      {
        "category": "Insurance",
        "subcategory": "Insurance Agent",
        "type": "Services"
      }
    ],
    "sg:phone": "+1 508 347 5511",
    "sg:postcode": "01507",
    "sg:province": "MA",
    "wof:name": "Sturbridge Insurance Agcy Inc",
    "wof:placetype": "venue"
  },
  "geometry": {"coordinates":[-71.997284,42.144456],"type":"Point"}
}
