{
  "type": "Feature",
  "properties": {
    "iso:country":"US",
    "sg:address":"16 Sturbridge Rd",
    "sg:city":"Charlton",
    "sg:classifiers":[
        {
            "category":"Insurance",
            "subcategory":"Insurance Agent",
            "type":"Services"
        }
    ],
    "sg:phone":"+1 508 347 5511",
    "sg:postcode":"01507",
    "sg:province":"MA",
    "wof:name":"Sturbridge Insurance Agcy Inc",
    "wof:placetype":"venue"
},
  "geometry": {"coordinates":[-71.99728399999999,42.144456],"type":"Point"}
}