{
  "type": "Feature",
  "properties": {
    "addr:full":"29 Bellis Cir Cambridge MA 02140",
    "addr:housenumber":"29",
    "addr:postcode":"02140",
    "addr:street":"Bellis Cir",
    "iso:country":"US",
    "sg:address":"29 Bellis Cir",
    "sg:city":"Cambridge",
    "sg:classifiers":[
        {
            "category":"Professional",
            "type":"Services"
        }
    ],
    "sg:phone":"+1 617 864 6050",
    "sg:postcode":"02140",
    "sg:province":"MA",
    "sg:website":"www.leodassolymar.com",
    "wof:name":"Leodas Solymar Inc",
    "wof:placetype":"venue"
},
  "geometry": {"coordinates":[-71.13266299999999,42.389627],"type":"Point"}
}