{
  "type": "Feature",
  "properties": {
    "addr:full":"1560 Beacon St Brookline MA 02446",
    "addr:housenumber":"1560",
    "addr:postcode":"02446",
    "addr:street":"Beacon St",
    "iso:country":"US",
    "sg:address":"1560 Beacon St",
    "sg:city":"Brookline",
    "sg:classifiers":[
        {
            "category":"Professional",
            "subcategory":"Lawyer & Legal Services",
            "type":"Services"
        }
    ],
    "sg:phone":"+1 617 734 4446",
    "sg:postcode":"02446",
    "sg:province":"MA",
    "sg:tags":[
        "attorney"
    ],
    "wof:name":"Jeffrey A Stern Law Office",
    "wof:placetype":"venue"
},
  "geometry": {"coordinates":[-71.13087,42.339839],"type":"Point"}
}