{
  "type": "Feature",
  "properties": {
    "iso:country":"US",
    "sg:address":"350 Newbury St Bsmt",
    "sg:city":"Boston",
    "sg:classifiers":[
        {
            "category":"Personal",
            "subcategory":"Tanning Parlor",
            "type":"Services"
        }
    ],
    "sg:phone":"+1 617 266 8600",
    "sg:postcode":"02115",
    "sg:province":"MA",
    "wof:name":"Studio Tan",
    "wof:placetype":"venue"
},
  "geometry": {"coordinates":[-71.08719600000001,42.3484],"type":"Point"}
}