{
  "type": "Feature",
  "properties": {
    "addr:full": "350 Newbury St Bsmt Boston MA 02115",
    "addr:housenumber": "350",
    "addr:postcode": "02115",
    "addr:street": "Newbury St",
    "iso:country": "US",
    "sg:address": "350 Newbury St Bsmt",
    "sg:city": "Boston",
    "sg:classifiers": [
      {
        "category": "Personal",
        "subcategory": "Tanning Parlor",
        "type": "Services"
      }
    ],
    "sg:phone": "+1 617 266 8600",
    "sg:postcode": "02115",
    "sg:province": "MA",
    "wof:name": "Studio Tan",
    "wof:placetype": "venue"
  },
  "geometry": {"coordinates":[-71.087196,42.3484],"type":"Point"}
}
