{
  "type": "Feature",
  "properties": {
    "iso:country":"US",
    "sg:address":"19 Kelley Rd",
    "sg:city":"Mendon",
    "sg:classifiers":[
        {
            "category":"Building & Trades",
            "subcategory":"Construction",
            "type":"Services"
        }
    ],
    "sg:phone":"+1 508 478 5410",
    "sg:postcode":"01756",
    "sg:province":"MA",
    "sg:tags":[
        "general",
        "contractor"
    ],
    "wof:name":"Tetreault Inc",
    "wof:placetype":"venue"
},
  "geometry": {"coordinates":[-71.557241,42.096534],"type":"Point"}
}