{
  "type": "Feature",
  "properties": {
    "iso:country":"US",
    "sg:address":"566 Rogers St",
    "sg:city":"Lowell",
    "sg:classifiers":[
        {
            "category":"Real Estate",
            "subcategory":"Surveying",
            "type":"Services"
        }
    ],
    "sg:phone":"+1 978 459 9860",
    "sg:postcode":"01852",
    "sg:province":"MA",
    "sg:tags":[
        "surveyor"
    ],
    "wof:name":"Belvidere Land Surveying",
    "wof:placetype":"venue"
},
  "geometry": {"coordinates":[-71.283931,42.631612],"type":"Point"}
}