{
  "type": "Feature",
  "properties": {
    "iso:country":"US",
    "sg:address":"153 Broadway St",
    "sg:city":"Raynham",
    "sg:classifiers":[
        {
            "category":"Banks & Credit Unions",
            "subcategory":"Bank",
            "type":"Services"
        }
    ],
    "sg:phone":"+1 508 823 5810",
    "sg:postcode":"02767",
    "sg:province":"MA",
    "sg:tags":[
        "loan"
    ],
    "wof:name":"First Mortgage Assoc Inc",
    "wof:placetype":"venue"
},
  "geometry": {"coordinates":[-71.083861,41.932812],"type":"Point"}
}