{
  "type": "Feature",
  "properties": {
    "iso:country":"US",
    "sg:address":"326 Concord St",
    "sg:city":"Framingham",
    "sg:classifiers":[
        {
            "category":"Restaurant",
            "type":"Food & Drink"
        }
    ],
    "sg:phone":"+1 508 872 3312",
    "sg:postcode":"01702",
    "sg:province":"MA",
    "wof:name":"Joa Take Out",
    "wof:placetype":"venue"
},
  "geometry": {"coordinates":[-71.41258999999999,42.28389],"type":"Point"}
}