{
  "type": "Feature",
  "properties": {
    "iso:country":"US",
    "sg:address":"68 Pine St",
    "sg:city":"Natick",
    "sg:classifiers":[
        {
            "category":"Building & Trades",
            "subcategory":"Landscaping Services",
            "type":"Services"
        }
    ],
    "sg:phone":"+1   ",
    "sg:postcode":"01760",
    "sg:province":"MA",
    "wof:name":"Kenosians Landscape",
    "wof:placetype":"venue"
},
  "geometry": {"coordinates":[-71.355267,42.314761],"type":"Point"}
}