{
  "type": "Feature",
  "properties": {
    "iso:country":"US",
    "sg:address":"56 Pickering St",
    "sg:city":"Needham",
    "sg:classifiers":[
        {
            "category":"Shopping",
            "subcategory":"Computers & Home Electronics",
            "type":"Retail Goods"
        }
    ],
    "sg:phone":"+1 781 453 7390",
    "sg:postcode":"02492",
    "sg:province":"MA",
    "sg:tags":[
        "software"
    ],
    "wof:name":"Net Tech Svc",
    "wof:placetype":"venue"
},
  "geometry": {"coordinates":[-71.234531,42.280749],"type":"Point"}
}