{
  "type": "Feature",
  "properties": {
    "addr:full": "72 Sheridan St Woburn MA 01801",
    "addr:housenumber": "72",
    "addr:postcode": "01801",
    "addr:street": "Sheridan St",
    "iso:country": "US",
    "sg:address": "72 Sheridan St",
    "sg:city": "Woburn",
    "sg:classifiers": [
      {
        "category": "Building \u0026 Trades",
        "subcategory": "Plumbing",
        "type": "Services"
      }
    ],
    "sg:phone": "+1 781 938 3999",
    "sg:postcode": "01801",
    "sg:province": "MA",
    "sg:tags": [
      "plumbing",
      "contractor"
    ],
    "wof:name": "K M Ryan Plumbing",
    "wof:placetype": "venue"
  },
  "geometry": {"coordinates":[-71.173379,42.48395],"type":"Point"}
}
