{
  "type": "Feature",
  "properties": {
    "addr:full":"456 Sumner Ave Springfield MA 01108",
    "addr:housenumber":"456",
    "addr:postcode":"01108",
    "addr:street":"Sumner Ave",
    "iso:country":"US",
    "sg:address":"456 Sumner Ave",
    "sg:city":"Springfield",
    "sg:classifiers":[
        {
            "category":"Restaurant",
            "type":"Food & Drink"
        }
    ],
    "sg:menulink":"http://www.allmenus.com/ma/springfield/207630-taco-bell/menu/",
    "sg:phone":"+1 413 739 8674",
    "sg:postcode":"01108",
    "sg:province":"MA",
    "sg:tags":[
        "mexican"
    ],
    "wof:name":"Taco Bell",
    "wof:placetype":"venue"
},
  "geometry": {"coordinates":[-72.559939,42.085784],"type":"Point"}
}