{
  "type": "Feature",
  "properties": {
    "addr:full":"310 Barnstable Rd Hyannis MA 02601",
    "addr:housenumber":"310",
    "addr:postcode":"02601",
    "addr:street":"Barnstable Rd",
    "iso:country":"US",
    "sg:address":"310 Barnstable Rd",
    "sg:city":"Hyannis",
    "sg:classifiers":[
        {
            "category":"Health Services",
            "subcategory":"Clinic",
            "type":"Services"
        }
    ],
    "sg:phone":"+1 508 771 4117",
    "sg:postcode":"02601",
    "sg:province":"MA",
    "sg:tags":[
        "home"
    ],
    "wof:name":"Interim Healthcare",
    "wof:placetype":"venue"
},
  "geometry": {"coordinates":[-70.28581699999999,41.661887],"type":"Point"}
}