{
  "type": "Feature",
  "properties": {
    "addr:full": "155 Katherine Lee Bates Rd Falmouth MA 02540",
    "addr:housenumber": "155",
    "addr:postcode": "02540",
    "addr:street": "Katherine Lee Bates Rd",
    "iso:country": "US",
    "sg:address": "155 Katherine Lee Bates Rd",
    "sg:city": "Falmouth",
    "sg:classifiers": [
      {
        "category": "Government",
        "subcategory": "Office",
        "type": "Public Place"
      }
    ],
    "sg:phone": "+1 508 495 1400",
    "sg:postcode": "02540",
    "sg:province": "MA",
    "sg:tags": [
      "state",
      "resource"
    ],
    "wof:name": "Transitional Assistance Dept",
    "wof:placetype": "venue"
  },
  "geometry": {"coordinates":[-70.611115,41.553034],"type":"Point"}
}
