{
  "type": "Feature",
  "properties": {
    "addr:full": "29 Maple Ridge Rd Reading MA 01867",
    "addr:housenumber": "29",
    "addr:postcode": "01867",
    "addr:street": "Maple Ridge Rd",
    "iso:country": "US",
    "sg:address": "29 Maple Ridge Rd",
    "sg:city": "Reading",
    "sg:classifiers": [
      {
        "category": "Wholesale",
        "subcategory": "Non-durable Goods",
        "type": "Manufacturing \u0026 Wholesale Goods"
      }
    ],
    "sg:phone": "+1   ",
    "sg:postcode": "01867",
    "sg:province": "MA",
    "sg:tags": [
      "automotive",
      "parts",
      "export",
      "supply"
    ],
    "wof:name": "General Commerce \u0026 Mdsg",
    "wof:placetype": "venue"
  },
  "geometry": {"coordinates":[-71.112179,42.509176],"type":"Point"}
}
