{
  "type": "Feature",
  "properties": {
    "iso:country":"US",
    "sg:address":"325 Broadway",
    "sg:city":"Revere",
    "sg:classifiers":[
        {
            "category":"Travel",
            "subcategory":"Travel Agent",
            "type":"Entertainment"
        }
    ],
    "sg:phone":"+1 781 286 1400",
    "sg:postcode":"02151",
    "sg:province":"MA",
    "sg:tags":[
        "agency",
        "services-commercial"
    ],
    "wof:name":"Travel Reports",
    "wof:placetype":"venue"
},
  "geometry": {"coordinates":[-71.013049,42.408942],"type":"Point"}
}