{
  "type": "Feature",
  "properties": {
    "iso:country":"US",
    "sg:address":"1550 Worcester Rd",
    "sg:city":"Framingham",
    "sg:classifiers":[
        {
            "category":"Real Estate",
            "subcategory":"Real Estate Operator",
            "type":"Services"
        }
    ],
    "sg:phone":"+1 508 872 5847",
    "sg:postcode":"01702",
    "sg:province":"MA",
    "sg:tags":[
        "apartment"
    ],
    "wof:name":"Chapel Hill West Condominium",
    "wof:placetype":"venue"
},
  "geometry": {"coordinates":[-71.4633,42.293874],"type":"Point"}
}