{
  "type": "Feature",
  "properties": {
    "addr:full":"579 Adams St Quincy MA 02169",
    "addr:housenumber":"579",
    "addr:postcode":"02169",
    "addr:street":"Adams St",
    "iso:country":"US",
    "sg:address":"579 Adams St",
    "sg:city":"Quincy",
    "sg:classifiers":[
        {
            "category":"Retail",
            "subcategory":"Veterinary Services",
            "type":"Services"
        }
    ],
    "sg:phone":"+1 617 773 8247",
    "sg:postcode":"02169",
    "sg:province":"MA",
    "sg:tags":[
        "hospital",
        "animal"
    ],
    "wof:name":"VCA Southshore Animal Hosp",
    "wof:placetype":"venue"
},
  "geometry": {"coordinates":[-71.025147,42.253453],"type":"Point"}
}