{
  "type": "Feature",
  "properties": {
    "addr:full":"49 Lexington St Springfield MA 01107",
    "addr:housenumber":"49",
    "addr:postcode":"01107",
    "addr:street":"Lexington St",
    "iso:country":"US",
    "sg:address":"49 Lexington St",
    "sg:city":"Springfield",
    "sg:classifiers":[
        {
            "category":"Professional",
            "subcategory":"Employment Agencies",
            "type":"Services"
        }
    ],
    "sg:phone":"+1   ",
    "sg:postcode":"01107",
    "sg:province":"MA",
    "sg:tags":[
        "help",
        "supply"
    ],
    "wof:name":"Antonio M Zayas",
    "wof:placetype":"venue"
},
  "geometry": {"coordinates":[-72.600647,42.116832],"type":"Point"}
}