{
  "type": "Feature",
  "properties": {
    "addr:full": "152 Turnpike St South Easton MA 02375",
    "addr:housenumber": "152",
    "addr:postcode": "02375",
    "addr:street": "Turnpike St",
    "iso:country": "US",
    "sg:address": "152 Turnpike St",
    "sg:city": "South Easton",
    "sg:classifiers": [
      {
        "category": "Shopping",
        "subcategory": "Clothing, Apparel, \u0026 Fashions",
        "type": "Retail Goods"
      }
    ],
    "sg:phone": "+1 508 238 6326",
    "sg:postcode": "02375",
    "sg:province": "MA",
    "sg:tags": [
      "uniform"
    ],
    "wof:name": "USA Uniforms \u0026 Career",
    "wof:placetype": "venue"
  },
  "geometry": {"coordinates":[-71.066209,42.029242],"type":"Point"}
}
