{
  "type": "Feature",
  "properties": {
    "iso:country":"US",
    "sg:address":"377 Wilbur Ave",
    "sg:city":"Swansea",
    "sg:classifiers":[
        {
            "category":"Professional",
            "subcategory":"Management & Consulting",
            "type":"Services"
        },
        {
            "category":"Professional",
            "subcategory":"Advertising",
            "type":"Services"
        }
    ],
    "sg:phone":"+1 508 675 3603",
    "sg:postcode":"02777",
    "sg:province":"MA",
    "sg:tags":[
        "marketing",
        "program",
        "consultant"
    ],
    "wof:name":"Impact Marketing",
    "wof:placetype":"venue"
},
  "geometry": {"coordinates":[-71.20697,41.731899],"type":"Point"}
}