{
  "type": "Feature",
  "properties": {
    "iso:country":"US",
    "sg:address":"1724 Washington St",
    "sg:city":"Walpole",
    "sg:classifiers":[
        {
            "category":"Building & Trades",
            "subcategory":"Construction",
            "type":"Services"
        }
    ],
    "sg:phone":"+1 508 668 1011",
    "sg:postcode":"02081",
    "sg:province":"MA",
    "sg:tags":[
        "roofing",
        "contractor"
    ],
    "wof:name":"Shamrock Roofing & Contracting",
    "wof:placetype":"venue"
},
  "geometry": {"coordinates":[-71.25732600000001,42.109679],"type":"Point"}
}