{
  "type": "Feature",
  "properties": {
    "addr:full":"195 Chestnut St North Attleboro MA 02760",
    "addr:housenumber":"195",
    "addr:postcode":"ma 02760",
    "addr:street":"Chestnut St",
    "iso:country":"US",
    "sg:address":"195 Chestnut St",
    "sg:city":"North Attleboro",
    "sg:classifiers":[
        {
            "category":"Shopping",
            "subcategory":"Computers & Home Electronics",
            "type":"Retail Goods"
        }
    ],
    "sg:phone":"+1 508 643 1008",
    "sg:postcode":"02760",
    "sg:province":"MA",
    "sg:tags":[
        "publishing"
    ],
    "wof:name":"New England Digital Prepress",
    "wof:placetype":"venue"
},
  "geometry": {"coordinates":[-71.32526,41.976266],"type":"Point"}
}