{
  "type": "Feature",
  "properties": {
    "iso:country":"US",
    "sg:address":"44 Nelson St",
    "sg:city":"Warren",
    "sg:classifiers":[
        {
            "category":"Manufacturing",
            "subcategory":"Printing",
            "type":"Manufacturing & Wholesale Goods"
        }
    ],
    "sg:phone":"+1 413 436 7600",
    "sg:postcode":"01083",
    "sg:province":"MA",
    "sg:tags":[
        "printer"
    ],
    "wof:name":"Quaboag Auctioneers",
    "wof:placetype":"venue"
},
  "geometry": {"coordinates":[-72.19131,42.210708],"type":"Point"}
}