{
  "type": "Feature",
  "properties": {
    "iso:country":"US",
    "sg:address":"4 Hyde Park Ave",
    "sg:city":"Jamaica Plain",
    "sg:classifiers":[
        {
            "category":"Organizations",
            "subcategory":"Religious Organization",
            "type":"Services"
        }
    ],
    "sg:phone":"+1 617 983 3464",
    "sg:postcode":"02130",
    "sg:province":"MA",
    "sg:tags":[
        "church"
    ],
    "wof:name":"International Outreach Mnstrs",
    "wof:placetype":"venue"
},
  "geometry": {"coordinates":[-71.113754,42.29953],"type":"Point"}
}