{
  "type": "Feature",
  "properties": {
    "iso:country":"US",
    "sg:address":"11 Fenton Rd",
    "sg:city":"Monson",
    "sg:classifiers":[
        {
            "category":"Building & Trades",
            "subcategory":"Construction",
            "type":"Services"
        }
    ],
    "sg:phone":"+1 413 284 0555",
    "sg:postcode":"01057",
    "sg:province":"MA",
    "sg:tags":[
        "designer",
        "dealer",
        "pool",
        "swimming"
    ],
    "wof:name":"Sun Splash Pools",
    "wof:placetype":"venue"
},
  "geometry": {"coordinates":[-72.307006,42.141618],"type":"Point"}
}