{
  "type": "Feature",
  "properties": {
    "iso:country":"US",
    "sg:address":"1161 Hildreth St",
    "sg:city":"Dracut",
    "sg:classifiers":[
        {
            "category":"Building & Trades",
            "subcategory":"Construction",
            "type":"Services"
        }
    ],
    "sg:phone":"+1 978 957 1110",
    "sg:postcode":"01826",
    "sg:province":"MA",
    "sg:tags":[
        "excavating",
        "contractor"
    ],
    "wof:name":"K & K Equipment",
    "wof:placetype":"venue"
},
  "geometry": {"coordinates":[-71.330545,42.686025],"type":"Point"}
}