{
  "type": "Feature",
  "properties": {
    "addr:full": "1161 Hildreth St Dracut MA 01826",
    "addr:housenumber": "1161",
    "addr:postcode": "01826",
    "addr:street": "Hildreth St",
    "iso:country": "US",
    "sg:address": "1161 Hildreth St",
    "sg:city": "Dracut",
    "sg:classifiers": [
      {
        "category": "Building \u0026 Trades",
        "subcategory": "Construction",
        "type": "Services"
      }
    ],
    "sg:phone": "+1 978 957 1110",
    "sg:postcode": "01826",
    "sg:province": "MA",
    "sg:tags": [
      "excavating",
      "contractor"
    ],
    "wof:name": "K \u0026 K Equipment",
    "wof:placetype": "venue"
  },
  "geometry": {"coordinates":[-71.330545,42.686025],"type":"Point"}
}
