{
  "type": "Feature",
  "properties": {
    "addr:full": "33 Robinhood Rd Winchester MA 01890",
    "addr:housenumber": "33",
    "addr:postcode": "01890",
    "addr:street": "Robinhood Rd",
    "iso:country": "US",
    "sg:address": "33 Robinhood Rd",
    "sg:city": "Winchester",
    "sg:classifiers": [
      {
        "category": "Building \u0026 Trades",
        "subcategory": "Electrical",
        "type": "Services"
      }
    ],
    "sg:phone": "+1 781 729 8909",
    "sg:postcode": "01890",
    "sg:province": "MA",
    "sg:tags": [
      "electric",
      "contractor"
    ],
    "wof:name": "Christopher Electric",
    "wof:placetype": "venue"
  },
  "geometry": {"coordinates":[-71.160149,42.450277],"type":"Point"}
}
