{
  "type": "Feature",
  "properties": {
    "iso:country":"US",
    "sg:address":"22 Walnut St",
    "sg:city":"Gardner",
    "sg:classifiers":[
        {
            "category":"Real Estate",
            "subcategory":"Real Estate Agent",
            "type":"Services"
        }
    ],
    "sg:phone":"+1 978 632 0625",
    "sg:postcode":"01440",
    "sg:province":"MA",
    "wof:name":"General Realty Co",
    "wof:placetype":"venue"
},
  "geometry": {"coordinates":[-71.98656099999999,42.577791],"type":"Point"}
}