{
  "type": "Feature",
  "properties": {
    "addr:full":"9 Avenue E Hopkinton MA 01748",
    "addr:housenumber":"9",
    "addr:postcode":"01748",
    "addr:street":"Avenue E",
    "iso:country":"US",
    "sg:address":"9 Avenue E",
    "sg:city":"Hopkinton",
    "sg:classifiers":[
        {
            "category":"Freight",
            "type":"Transportation"
        }
    ],
    "sg:phone":"+1 508 435 3400",
    "sg:postcode":"01748",
    "sg:province":"MA",
    "sg:tags":[
        "trucking"
    ],
    "wof:name":"Tantara New England",
    "wof:placetype":"venue"
},
  "geometry": {"coordinates":[-71.54113599999999,42.194696],"type":"Point"}
}