{
  "type": "Feature",
  "properties": {
    "addr:full":"79 Charles St Boston MA 02114",
    "addr:housenumber":"79",
    "addr:postcode":"02114",
    "addr:street":"Charles St",
    "iso:country":"US",
    "sg:address":"79 Charles St",
    "sg:city":"Boston",
    "sg:classifiers":[
        {
            "category":"Building & Trades",
            "subcategory":"Locksmith",
            "type":"Services"
        }
    ],
    "sg:phone":"+1 617 531 0899",
    "sg:postcode":"02114",
    "sg:province":"MA",
    "sg:tags":[
        "key"
    ],
    "wof:name":"24 Hour 7 Day Emergency Locksmith",
    "wof:placetype":"venue"
},
  "geometry": {"coordinates":[-71.070446,42.35842],"type":"Point"}
}