{
  "type": "Feature",
  "properties": {
    "iso:country":"US",
    "sg:address":"52 Ship Ave",
    "sg:city":"Medford",
    "sg:classifiers":[
        {
            "category":"Recreation",
            "subcategory":"Marina",
            "type":"Entertainment"
        }
    ],
    "sg:phone":"+1 781 395 9872",
    "sg:postcode":"02155",
    "sg:province":"MA",
    "wof:name":"Riverside Yacht Club Inc",
    "wof:placetype":"venue"
},
  "geometry": {"coordinates":[-71.10129499999999,42.414324],"type":"Point"}
}