{
  "type": "Feature",
  "properties": {
    "addr:full": "52 Ship Ave Medford MA 02155",
    "addr:housenumber": "52",
    "addr:postcode": "02155",
    "addr:street": "Ship Ave",
    "iso:country": "US",
    "ovtr:label": "Riverside Yacht Club, 52 Ship Ave Medford MA US",
    "ovtr:similarity": 3.832796096801758,
    "sg:address": "52 Ship Ave",
    "sg:city": "Medford",
    "sg:classifiers": [
      {
        "category": "Recreation",
        "subcategory": "Marina",
        "type": "Entertainment"
      }
    ],
    "sg:phone": "+1 781 395 9872",
    "sg:postcode": "02155",
    "sg:province": "MA",
    "wof:name": "Riverside Yacht Club Inc",
    "wof:placetype": "venue"
  },
  "geometry": {"coordinates":[-71.101295,42.414324],"type":"Point"}
}
