{
  "type": "Feature",
  "properties": {
    "addr:full":"179 Massachusetts Ave Boston MA 02115",
    "addr:housenumber":"179",
    "addr:postcode":"02115",
    "addr:street":"Massachusetts Ave",
    "iso:country":"US",
    "sg:address":"179 Massachusetts Ave",
    "sg:city":"Boston",
    "sg:classifiers":[
        {
            "category":"Retail",
            "subcategory":"Auto Repair",
            "type":"Services"
        }
    ],
    "sg:phone":"+1 617 208 1178",
    "sg:postcode":"02115",
    "sg:province":"MA",
    "sg:tags":[
        "wrecker"
    ],
    "wof:name":"7 Day Emergency 24 Hr",
    "wof:placetype":"venue"
},
  "geometry": {"coordinates":[-71.08729200000001,42.346267],"type":"Point"}
}