{
  "type": "Feature",
  "properties": {
    "addr:full":"37 Barnstable Rd Hyannis MA 02601",
    "addr:housenumber":"37",
    "addr:postcode":"02601",
    "addr:street":"Barnstable Rd",
    "iso:country":"US",
    "sg:address":"37 Barnstable Rd",
    "sg:city":"Hyannis",
    "sg:classifiers":[
        {
            "category":"Shopping",
            "subcategory":"Clothing, Apparel, & Fashions",
            "type":"Retail Goods"
        }
    ],
    "sg:phone":"+1 508 790 0877",
    "sg:postcode":"02601",
    "sg:province":"MA",
    "wof:name":"Europa Imports",
    "wof:placetype":"venue"
},
  "geometry": {"coordinates":[-70.283225,41.654689],"type":"Point"}
}