{
  "type": "Feature",
  "properties": {
    "addr:full":"200 Clarendon Street Boston MA 02116",
    "addr:housenumber":"200",
    "addr:postcode":"02116",
    "addr:street":"Clarendon Street",
    "iso:country":"US",
    "sg:address":"200 Clarendon Street",
    "sg:city":"Boston",
    "sg:classifiers":[
        {
            "category":"Professional",
            "subcategory":"Accounting & Tax Preparation",
            "type":"Services"
        }
    ],
    "sg:phone":"+1 617 266 2000",
    "sg:postcode":"02116",
    "sg:province":"MA",
    "sg:tags":[
        "accountant"
    ],
    "wof:name":"Ernst & Young",
    "wof:placetype":"venue"
},
  "geometry": {"coordinates":[-71.07436800000001,42.348922],"type":"Point"}
}