{
  "type": "Feature",
  "properties": {
    "iso:country":"US",
    "sg:address":"60 Worcester Rd",
    "sg:city":"Barre",
    "sg:classifiers":[
        {
            "category":"Retail",
            "subcategory":"Auto Repair",
            "type":"Services"
        }
    ],
    "sg:phone":"+1 978 355 4848",
    "sg:postcode":"01005",
    "sg:province":"MA",
    "sg:tags":[
        "body",
        "automobile",
        "painting"
    ],
    "wof:name":"State Road Collision Ctr",
    "wof:placetype":"venue"
},
  "geometry": {"coordinates":[-72.096296,42.408208],"type":"Point"}
}