{
  "type": "Feature",
  "properties": {
    "iso:country":"US",
    "sg:address":"1189 Massachusetts Ave",
    "sg:city":"Arlington",
    "sg:classifiers":[
        {
            "category":"Shopping",
            "subcategory":"Florist",
            "type":"Retail Goods"
        }
    ],
    "sg:phone":"+1 781 643 6660",
    "sg:postcode":"02476",
    "sg:province":"MA",
    "wof:name":"Scott Flowers",
    "wof:placetype":"venue"
},
  "geometry": {"coordinates":[-71.174611,42.423308],"type":"Point"}
}