{
  "type": "Feature",
  "properties": {
    "iso:country":"US",
    "sg:address":"146 Hampshire St",
    "sg:city":"Cambridge",
    "sg:classifiers":[
        {
            "category":"Organizations",
            "subcategory":"Religious Organization",
            "type":"Services"
        }
    ],
    "sg:phone":"+1 617 868 4853",
    "sg:postcode":"02139",
    "sg:province":"MA",
    "sg:tags":[
        "church"
    ],
    "sg:website":"www.massavebaptist.org",
    "wof:name":"Massachusetts Avenue Baptist",
    "wof:placetype":"venue"
},
  "geometry": {"coordinates":[-71.096875,42.370475],"type":"Point"}
}