{
  "type": "Feature",
  "properties": {
    "addr:full": "146 Hampshire St Cambridge MA 02139",
    "addr:housenumber": "146",
    "addr:postcode": "02139",
    "addr:street": "Hampshire St",
    "iso:country": "US",
    "ovtr:label": "Massachusetts Avenue Baptist, 146 Hampshire St Cambridge MA US",
    "ovtr:similarity": 2.7234880924224854,
    "sg:address": "146 Hampshire St",
    "sg:city": "Cambridge",
    "sg:classifiers": [
      {
        "category": "Organizations",
        "subcategory": "Religious Organization",
        "type": "Services"
      }
    ],
    "sg:phone": "+1 617 868 4853",
    "sg:postcode": "02139",
    "sg:province": "MA",
    "sg:tags": [
      "church"
    ],
    "sg:website": "www.massavebaptist.org",
    "wof:name": "Massachusetts Avenue Baptist",
    "wof:placetype": "venue"
  },
  "geometry": {"coordinates":[-71.096875,42.370475],"type":"Point"}
}
