{
  "type": "Feature",
  "properties": {
    "iso:country":"US",
    "sg:address":"40 Tucker St",
    "sg:city":"Lenox",
    "sg:classifiers":[
        {
            "category":"Shopping",
            "subcategory":"Musical Instruments",
            "type":"Retail Goods"
        }
    ],
    "sg:phone":"+1 413 637 1101",
    "sg:postcode":"01240",
    "sg:province":"MA",
    "wof:name":"Persistor Instruments",
    "wof:placetype":"venue"
},
  "geometry": {"coordinates":[-73.279583,42.358977],"type":"Point"}
}