{
  "type": "Feature",
  "properties": {
    "addr:full": "17 Concord Rd Sudbury MA 01776",
    "addr:housenumber": "17",
    "addr:postcode": "01776",
    "addr:street": "Concord Rd",
    "iso:country": "US",
    "sg:address": "17 Concord Rd",
    "sg:city": "Sudbury",
    "sg:classifiers": [
      {
        "category": "Shopping",
        "subcategory": "Jewelry",
        "type": "Retail Goods"
      }
    ],
    "sg:phone": "+1 978 443 2770",
    "sg:postcode": "01776",
    "sg:province": "MA",
    "sg:tags": [
      "jeweler"
    ],
    "wof:name": "Hill Jewelers",
    "wof:placetype": "venue"
  },
  "geometry": {"coordinates":[-71.416095,42.362891],"type":"Point"}
}
