{
  "type": "Feature",
  "properties": {
    "addr:full":"70 Moose Brook Rd Southampton MA 01073",
    "addr:housenumber":"70",
    "addr:postcode":"01073",
    "addr:street":"Moose Brook Rd",
    "iso:country":"US",
    "sg:address":"70 Moose Brook Rd",
    "sg:city":"Southampton",
    "sg:classifiers":[
        {
            "category":"Building & Trades",
            "subcategory":"Plumbing",
            "type":"Services"
        }
    ],
    "sg:phone":"+1   ",
    "sg:postcode":"01073",
    "sg:province":"MA",
    "sg:tags":[
        "contractor"
    ],
    "wof:name":"Dan Gipperich Heating",
    "wof:placetype":"venue"
},
  "geometry": {"coordinates":[-72.715087,42.209606],"type":"Point"}
}