{
  "type": "Feature",
  "properties": {
    "addr:full": "185 Shore Rd Buzzards Bay MA 02532",
    "addr:housenumber": "185",
    "addr:postcode": "02532",
    "addr:street": "Shore Rd",
    "iso:country": "US",
    "ovtr:label": "Gray Gables Market, 185 Shore Rd Buzzards Bay MA US",
    "ovtr:similarity": 3.890925884246826,
    "sg:address": "185 Shore Rd",
    "sg:city": "Buzzards Bay",
    "sg:classifiers": [
      {
        "category": "Food \u0026 Beverages",
        "subcategory": "Groceries \u0026 Convenience Stores",
        "type": "Retail Goods"
      }
    ],
    "sg:phone": "+1 508 759 3066",
    "sg:postcode": "02532",
    "sg:province": "MA",
    "wof:name": "Gray Gables Country Market",
    "wof:placetype": "venue"
  },
  "geometry": {"coordinates":[-70.612583,41.735926],"type":"Point"}
}
