{
  "type": "Feature",
  "properties": {
    "addr:full": "19 Coolidge Hill Rd Watertown MA 02472",
    "addr:housenumber": "19",
    "addr:postcode": "02472",
    "addr:street": "Coolidge Hill Rd",
    "iso:country": "US",
    "sg:address": "19 Coolidge Hill Rd",
    "sg:city": "Watertown",
    "sg:classifiers": [
      {
        "category": "Manufacturing",
        "subcategory": "Tools \u0026 Machinery",
        "type": "Manufacturing \u0026 Wholesale Goods"
      },
      {
        "category": "Building \u0026 Trades",
        "subcategory": "Construction",
        "type": "Services"
      },
      {
        "category": "Home \u0026 Garden",
        "subcategory": "Carpets \u0026 Floor Coverings",
        "type": "Retail Goods"
      }
    ],
    "sg:phone": "+1 617 924 6027",
    "sg:postcode": "02472",
    "sg:province": "MA",
    "sg:tags": [
      "aerial",
      "scaffolding",
      "lift",
      "rigger",
      "erectors",
      "mover"
    ],
    "sg:website": "http://www.apmdelivers.com",
    "wof:name": "Atlantic Plant Maintenance, Inc.",
    "wof:placetype": "venue"
  },
  "geometry": {"coordinates":[-71.154881,42.367705],"type":"Point"}
}
