{
  "type": "Feature",
  "properties": {
    "iso:country":"US",
    "sg:address":"19 Coolidge Hill Rd",
    "sg:city":"Watertown",
    "sg:classifiers":[
        {
            "category":"Manufacturing",
            "subcategory":"Tools & Machinery",
            "type":"Manufacturing & Wholesale Goods"
        },
        {
            "category":"Building & Trades",
            "subcategory":"Construction",
            "type":"Services"
        },
        {
            "category":"Home & Garden",
            "subcategory":"Carpets & Floor Coverings",
            "type":"Retail Goods"
        }
    ],
    "sg:phone":"+1 617 924 6027",
    "sg:postcode":"02472",
    "sg:province":"MA",
    "sg:tags":[
        "aerial",
        "scaffolding",
        "lift",
        "rigger",
        "erectors",
        "mover"
    ],
    "sg:website":"http://www.apmdelivers.com",
    "wof:name":"Atlantic Plant Maintenance, Inc.",
    "wof:placetype":"venue"
},
  "geometry": {"coordinates":[-71.154881,42.367705],"type":"Point"}
}