{
  "type": "Feature",
  "properties": {
    "addr:full": "50 Butternut Dr Agawam MA 01001",
    "addr:housenumber": "50",
    "addr:postcode": "01001",
    "addr:street": "Butternut Dr",
    "iso:country": "US",
    "sg:address": "50 Butternut Dr",
    "sg:city": "Agawam",
    "sg:classifiers": [
      {
        "category": "Building \u0026 Trades",
        "subcategory": "Plumbing",
        "type": "Services"
      }
    ],
    "sg:phone": "+1 413 786 2261",
    "sg:postcode": "01001",
    "sg:province": "MA",
    "sg:tags": [
      "plumbing",
      "contractor"
    ],
    "wof:name": "Mickey's Plumbing \u0026 Heating",
    "wof:placetype": "venue"
  },
  "geometry": {"coordinates":[-72.626515,42.054802],"type":"Point"}
}
