{
  "type": "Feature",
  "properties": {
    "iso:country":"US",
    "sg:address":"50 Butternut Dr",
    "sg:city":"Agawam",
    "sg:classifiers":[
        {
            "category":"Building & Trades",
            "subcategory":"Plumbing",
            "type":"Services"
        }
    ],
    "sg:phone":"+1 413 786 2261",
    "sg:postcode":"01001",
    "sg:province":"MA",
    "sg:tags":[
        "plumbing",
        "contractor"
    ],
    "wof:name":"Mickey's Plumbing & Heating",
    "wof:placetype":"venue"
},
  "geometry": {"coordinates":[-72.626515,42.054802],"type":"Point"}
}