{
  "type": "Feature",
  "properties": {
    "iso:country":"US",
    "sg:address":"15 Messenger St",
    "sg:city":"Plainville",
    "sg:classifiers":[
        {
            "category":"Recreation",
            "type":"Entertainment"
        }
    ],
    "sg:phone":"+1 508 699 5627",
    "sg:postcode":"02762",
    "sg:province":"MA",
    "sg:tags":[
        "parlor",
        "billiard",
        "hall",
        "pool"
    ],
    "wof:name":"Fast Break Billiards Inc",
    "wof:placetype":"venue"
},
  "geometry": {"coordinates":[-71.309601,42.008801],"type":"Point"}
}