{
  "type": "Feature",
  "properties": {
    "addr:full":"75 Mechanic St Shelburne Falls MA 01370",
    "addr:housenumber":"75",
    "addr:postcode":"01370",
    "addr:street":"Mechanic St",
    "iso:country":"US",
    "sg:address":"75 Mechanic St",
    "sg:city":"Shelburne Falls",
    "sg:classifiers":[
        {
            "category":"Education",
            "subcategory":"School",
            "type":"Public Place"
        }
    ],
    "sg:phone":"+1 413 625 2521",
    "sg:postcode":"01370",
    "sg:province":"MA",
    "wof:name":"Buckland-Shelburne Elementary",
    "wof:placetype":"venue"
},
  "geometry": {"coordinates":[-72.73536799999999,42.609435],"type":"Point"}
}