{
  "type": "Feature",
  "properties": {
    "iso:country":"US",
    "sg:address":"70 Church St",
    "sg:city":"Winchester",
    "sg:classifiers":[
        {
            "category":"Organizations",
            "subcategory":"Professional Association",
            "type":"Services"
        }
    ],
    "sg:phone":"+1 781 721 4663",
    "sg:postcode":"01890",
    "sg:province":"MA",
    "wof:name":"Winchester Housing Corp",
    "wof:placetype":"venue"
},
  "geometry": {"coordinates":[-71.144334,42.450112],"type":"Point"}
}