{
  "type": "Feature",
  "properties": {
    "addr:full": "244 East St Ludlow MA 01056",
    "addr:housenumber": "244",
    "addr:postcode": "01056",
    "addr:street": "East St",
    "iso:country": "US",
    "sg:address": "244 East St",
    "sg:city": "Ludlow",
    "sg:classifiers": [
      {
        "category": "Education",
        "subcategory": "Special Training",
        "type": "Public Place"
      }
    ],
    "sg:phone": "+1 413 589 7158",
    "sg:postcode": "01056",
    "sg:province": "MA",
    "sg:tags": [
      "instruction",
      "music"
    ],
    "wof:name": "Chris Starz Pro Guitar Lesson",
    "wof:placetype": "venue"
  },
  "geometry": {"coordinates":[-72.475957,42.158459],"type":"Point"}
}
