{
  "type": "Feature",
  "properties": {
    "addr:full": "45 Harrison St Roslindale MA 02131",
    "addr:housenumber": "45",
    "addr:postcode": "02131",
    "addr:street": "Harrison St",
    "iso:country": "US",
    "sg:address": "45 Harrison St",
    "sg:city": "Roslindale",
    "sg:classifiers": [
      {
        "category": "Real Estate",
        "subcategory": "Real Estate Agent",
        "type": "Services"
      }
    ],
    "sg:phone": "+1 617 323 4554",
    "sg:postcode": "02131",
    "sg:province": "MA",
    "sg:tags": [
      "management"
    ],
    "wof:name": "Anze Management Group",
    "wof:placetype": "venue"
  },
  "geometry": {"coordinates":[-71.12039,42.287915],"type":"Point"}
}
