{
  "type": "Feature",
  "properties": {
    "iso:country":"US",
    "sg:address":"75 Webster St",
    "sg:city":"Worcester",
    "sg:classifiers":[
        {
            "category":"Building & Trades",
            "subcategory":"Construction",
            "type":"Services"
        }
    ],
    "sg:phone":"+1 508 438 0549",
    "sg:postcode":"01603",
    "sg:province":"MA",
    "sg:tags":[
        "tile",
        "tile-contractors"
    ],
    "wof:name":"Elements Tile & Pottery",
    "wof:placetype":"venue"
},
  "geometry": {"coordinates":[-71.83344200000001,42.242307],"type":"Point"}
}