{
  "type": "Feature",
  "properties": {
    "addr:full": "67 Union Ct Natick MA 01760",
    "addr:housenumber": "67",
    "addr:postcode": "01760",
    "addr:street": "Union Ct",
    "iso:country": "US",
    "sg:address": "67 Union Ct",
    "sg:city": "Natick",
    "sg:classifiers": [
      {
        "category": "Professional",
        "type": "Services"
      }
    ],
    "sg:phone": "+1 508 651 2849",
    "sg:postcode": "01760",
    "sg:province": "MA",
    "sg:tags": [
      "establishment"
    ],
    "wof:name": "Neho",
    "wof:placetype": "venue"
  },
  "geometry": {"coordinates":[-71.348216,42.285775],"type":"Point"}
}
