{
  "type": "Feature",
  "properties": {
    "iso:country":"US",
    "sg:address":"67 Union Ct",
    "sg:city":"Natick",
    "sg:classifiers":[
        {
            "category":"Professional",
            "type":"Services"
        }
    ],
    "sg:phone":"+1 508 651 2849",
    "sg:postcode":"01760",
    "sg:province":"MA",
    "sg:tags":[
        "establishment"
    ],
    "wof:name":"Neho",
    "wof:placetype":"venue"
},
  "geometry": {"coordinates":[-71.34821599999999,42.285775],"type":"Point"}
}