{
  "type": "Feature",
  "properties": {
    "iso:country":"US",
    "sg:address":"202 Winthrop St",
    "sg:city":"Taunton",
    "sg:classifiers":[
        {
            "category":"Wholesale",
            "subcategory":"Wine & Distilled Alcoholic Beverages",
            "type":"Manufacturing & Wholesale Goods"
        }
    ],
    "sg:phone":"+1 508 823 9925",
    "sg:postcode":"02780",
    "sg:province":"MA",
    "sg:tags":[
        "liquors-wholesale"
    ],
    "wof:name":"Dna Liquors Corp",
    "wof:placetype":"venue"
},
  "geometry": {"coordinates":[-71.110603,41.891553],"type":"Point"}
}