{
  "type": "Feature",
  "properties": {
    "iso:country":"US",
    "sg:address":"2087 Acushnet Ave",
    "sg:city":"New Bedford",
    "sg:classifiers":[
        {
            "category":"Real Estate",
            "subcategory":"Real Estate Agent",
            "type":"Services"
        }
    ],
    "sg:phone":"+1 508 995 6060",
    "sg:postcode":"02745",
    "sg:province":"MA",
    "sg:website":"www.suzette-realty.com",
    "wof:name":"Suzette & Assoc Realty",
    "wof:placetype":"venue"
},
  "geometry": {"coordinates":[-70.923199,41.679071],"type":"Point"}
}