{
  "type": "Feature",
  "properties": {
    "addr:full": "2087 Acushnet Ave New Bedford MA 02745",
    "addr:housenumber": "2087",
    "addr:postcode": "02745",
    "addr:street": "Acushnet Ave",
    "iso:country": "US",
    "sg:address": "2087 Acushnet Ave",
    "sg:city": "New Bedford",
    "sg:classifiers": [
      {
        "category": "Real Estate",
        "subcategory": "Real Estate Agent",
        "type": "Services"
      }
    ],
    "sg:phone": "+1 508 995 6060",
    "sg:postcode": "02745",
    "sg:province": "MA",
    "sg:website": "www.suzette-realty.com",
    "wof:name": "Suzette \u0026 Assoc Realty",
    "wof:placetype": "venue"
  },
  "geometry": {"coordinates":[-70.923199,41.679071],"type":"Point"}
}
