{
  "type": "Feature",
  "properties": {
    "iso:country":"US",
    "sg:address":"6 Holyoke St",
    "sg:city":"Malden",
    "sg:classifiers":[
        {
            "category":"Manufacturing",
            "subcategory":"Metals",
            "type":"Manufacturing & Wholesale Goods"
        }
    ],
    "sg:phone":"+1 781 322 3611",
    "sg:postcode":"02148",
    "sg:province":"MA",
    "sg:tags":[
        "electronic",
        "grinding",
        "equipment",
        "production",
        "supplies-wholesale",
        "manufacturer"
    ],
    "sg:website":"http://www.quartzite.net",
    "wof:name":"Quartzite Processing Inc",
    "wof:placetype":"venue"
},
  "geometry": {"coordinates":[-71.063101,42.423338],"type":"Point"}
}