{
  "type": "Feature",
  "properties": {
    "iso:country":"US",
    "sg:address":"63 Main St",
    "sg:city":"Amherst",
    "sg:classifiers":[
        {
            "category":"Restaurant",
            "type":"Food & Drink"
        }
    ],
    "sg:phone":"+1 413 253 9200",
    "sg:postcode":"01002",
    "sg:province":"MA",
    "wof:name":"Amber Waves Far East",
    "wof:placetype":"venue"
},
  "geometry": {"coordinates":[-72.518959,42.375637],"type":"Point"}
}