{
  "type": "Feature",
  "properties": {
    "iso:country":"US",
    "sg:address":"151 High Rd",
    "sg:city":"Newbury",
    "sg:classifiers":[
        {
            "category":"Manufacturing",
            "subcategory":"Lumber",
            "type":"Manufacturing & Wholesale Goods"
        }
    ],
    "sg:phone":"+1 978 465 3439",
    "sg:postcode":"01951",
    "sg:province":"MA",
    "sg:tags":[
        "carrier"
    ],
    "wof:name":"Sullivan Transport",
    "wof:placetype":"venue"
},
  "geometry": {"coordinates":[-70.845505,42.781788],"type":"Point"}
}