{
  "type": "Feature",
  "properties": {
    "iso:country":"US",
    "sg:address":"186 West St",
    "sg:city":"Paxton",
    "sg:classifiers":[
        {
            "category":"Building & Trades",
            "subcategory":"Construction",
            "type":"Services"
        }
    ],
    "sg:phone":"+1 508 798 6922",
    "sg:postcode":"01612",
    "sg:province":"MA",
    "sg:tags":[
        "painting",
        "contractor"
    ],
    "wof:name":"Emerald Painting Co",
    "wof:placetype":"venue"
},
  "geometry": {"coordinates":[-71.942808,42.307393],"type":"Point"}
}