{
  "type": "Feature",
  "properties": {
    "addr:full": "26 Forest Acres Dr Haverhill MA 01835",
    "addr:housenumber": "26",
    "addr:postcode": "01835",
    "addr:street": "Forest Acres Dr",
    "iso:country": "US",
    "sg:address": "26 Forest Acres Dr",
    "sg:city": "Haverhill",
    "sg:classifiers": [
      {
        "category": "Building \u0026 Trades",
        "subcategory": "Landscaping Services",
        "type": "Services"
      }
    ],
    "sg:phone": "+1 978 681 9111",
    "sg:postcode": "01835",
    "sg:province": "MA",
    "sg:tags": [
      "lawn",
      "maintenance",
      "grounds"
    ],
    "wof:name": "Lawnmaster Of Greater Lawrence",
    "wof:placetype": "venue"
  },
  "geometry": {"coordinates":[-71.095379,42.756018],"type":"Point"}
}
