{
  "type": "Feature",
  "properties": {
    "addr:full":"35 Corporate Dr Burlington MA 01803",
    "addr:housenumber":"35",
    "addr:postcode":"01803",
    "addr:street":"Corporate Dr",
    "iso:country":"US",
    "sg:address":"35 Corporate Dr",
    "sg:city":"Burlington",
    "sg:classifiers":[
        {
            "category":"Shopping",
            "subcategory":"Computers & Home Electronics",
            "type":"Retail Goods"
        }
    ],
    "sg:phone":"+1 781 221 0300",
    "sg:postcode":"01803",
    "sg:province":"MA",
    "sg:tags":[
        "software"
    ],
    "wof:name":"KADA Systems",
    "wof:placetype":"venue"
},
  "geometry": {"coordinates":[-71.189652,42.494267],"type":"Point"}
}