{
  "type": "Feature",
  "properties": {
    "addr:full": "31 Sterling Rd North Billerica MA 01862",
    "addr:housenumber": "31",
    "addr:postcode": "01862",
    "addr:street": "Sterling Rd",
    "iso:country": "US",
    "sg:address": "31 Sterling Rd",
    "sg:city": "North Billerica",
    "sg:classifiers": [
      {
        "category": "Freight",
        "type": "Transportation"
      }
    ],
    "sg:phone": "+1 978 670 1290",
    "sg:postcode": "01862",
    "sg:province": "MA",
    "sg:tags": [
      "trucking"
    ],
    "wof:name": "Overnite Transportation Co",
    "wof:placetype": "venue"
  },
  "geometry": {"coordinates":[-71.307694,42.569217],"type":"Point"}
}
