{
  "type": "Feature",
  "properties": {
    "iso:country":"US",
    "sg:address":"20 Mall Rd",
    "sg:city":"Burlington",
    "sg:classifiers":[
        {
            "category":"Real Estate",
            "subcategory":"Real Estate Services",
            "type":"Services"
        }
    ],
    "sg:phone":"+1 781 229 6987",
    "sg:postcode":"01803",
    "sg:province":"MA",
    "sg:tags":[
        "management",
        "property"
    ],
    "sg:website":"www.bostonproperties.com",
    "wof:name":"Boston Properties",
    "wof:placetype":"venue"
},
  "geometry": {"coordinates":[-71.195503,42.491001],"type":"Point"}
}