{
  "type": "Feature",
  "properties": {
    "addr:full": "110 S Deerfield Byp South Deerfield MA 01373",
    "addr:housenumber": "110",
    "addr:postcode": "01373",
    "addr:street": "S Deerfield Byp",
    "iso:country": "US",
    "sg:address": "110 S Deerfield Byp",
    "sg:city": "South Deerfield",
    "sg:classifiers": [
      {
        "category": "Building \u0026 Trades",
        "subcategory": "Cleaning \u0026 Sanitation",
        "type": "Services"
      }
    ],
    "sg:phone": "+1 413 397 9900",
    "sg:postcode": "01373",
    "sg:province": "MA",
    "sg:tags": [
      "house"
    ],
    "sg:website": "www.kathiskleaning.com",
    "wof:name": "Kathi's Kleaning LLC",
    "wof:placetype": "venue"
  },
  "geometry": {"coordinates":[-72.61121,42.489294],"type":"Point"}
}
