{
  "type": "Feature",
  "properties": {
    "iso:country":"US",
    "sg:address":"110 S Deerfield Byp",
    "sg:city":"South Deerfield",
    "sg:classifiers":[
        {
            "category":"Building & Trades",
            "subcategory":"Cleaning & Sanitation",
            "type":"Services"
        }
    ],
    "sg:phone":"+1 413 397 9900",
    "sg:postcode":"01373",
    "sg:province":"MA",
    "sg:tags":[
        "house"
    ],
    "sg:website":"www.kathiskleaning.com",
    "wof:name":"Kathi's Kleaning LLC",
    "wof:placetype":"venue"
},
  "geometry": {"coordinates":[-72.61121,42.489294],"type":"Point"}
}