{
  "type": "Feature",
  "properties": {
    "addr:full": "90 Providence Hwy East Walpole MA 02032",
    "addr:housenumber": "90",
    "addr:postcode": "02032",
    "addr:street": "Providence Hwy",
    "iso:country": "US",
    "sg:address": "90 Providence Hwy",
    "sg:city": "East Walpole",
    "sg:classifiers": [
      {
        "category": "Retail",
        "subcategory": "Repair Shop",
        "type": "Services"
      }
    ],
    "sg:phone": "+1 508 668 2601",
    "sg:postcode": "02032",
    "sg:province": "MA",
    "sg:tags": [
      "jewelry"
    ],
    "wof:name": "D \u0026 M Jeweler",
    "wof:placetype": "venue"
  },
  "geometry": {"coordinates":[-71.20557,42.15409],"type":"Point"}
}
