{
  "type": "Feature",
  "properties": {
    "addr:full":"28 Morgan Dr Methuen MA 01844",
    "addr:housenumber":"28",
    "addr:postcode":"01844",
    "addr:street":"Morgan Dr",
    "iso:country":"US",
    "sg:address":"28 Morgan Dr",
    "sg:city":"Methuen",
    "sg:classifiers":[
        {
            "category":"Building & Trades",
            "subcategory":"Construction",
            "type":"Services"
        }
    ],
    "sg:phone":"+1 978 687 7105",
    "sg:postcode":"01844",
    "sg:province":"MA",
    "sg:tags":[
        "contractor"
    ],
    "wof:name":"Riverside Contracting Inc",
    "wof:placetype":"venue"
},
  "geometry": {"coordinates":[-71.18387199999999,42.784303],"type":"Point"}
}