{
  "type": "Feature",
  "properties": {
    "iso:country":"US",
    "sg:address":"48 Robeson St",
    "sg:city":"Jamaica Plain",
    "sg:classifiers":[
        {
            "category":"Professional",
            "subcategory":"Lawyer & Legal Services",
            "type":"Services"
        }
    ],
    "sg:phone":"+1 617 524 7911",
    "sg:postcode":"02130",
    "sg:province":"MA",
    "wof:name":"Johnson Arthur L Atty",
    "wof:placetype":"venue"
},
  "geometry": {"coordinates":[-71.09989899999999,42.3097],"type":"Point"}
}