{
  "type": "Feature",
  "properties": {
    "addr:full": "48 Robeson St Jamaica Plain MA 02130",
    "addr:housenumber": "48",
    "addr:postcode": "02130",
    "addr:street": "Robeson St",
    "iso:country": "US",
    "sg:address": "48 Robeson St",
    "sg:city": "Jamaica Plain",
    "sg:classifiers": [
      {
        "category": "Professional",
        "subcategory": "Lawyer \u0026 Legal Services",
        "type": "Services"
      }
    ],
    "sg:phone": "+1 617 524 7911",
    "sg:postcode": "02130",
    "sg:province": "MA",
    "wof:name": "Johnson Arthur L Atty",
    "wof:placetype": "venue"
  },
  "geometry": {"coordinates":[-71.099899,42.3097],"type":"Point"}
}
