{
  "type": "Feature",
  "properties": {
    "iso:country":"US",
    "sg:address":"1 Gardner Perry Ln",
    "sg:city":"Nantucket",
    "sg:classifiers":[
        {
            "category":"Education",
            "subcategory":"Special Training",
            "type":"Public Place"
        }
    ],
    "sg:phone":"+1 508 325 5251",
    "sg:postcode":"02554",
    "sg:province":"MA",
    "sg:tags":[
        "school",
        "instruction",
        "art"
    ],
    "wof:name":"Artist's Assoc Arts Program",
    "wof:placetype":"venue"
},
  "geometry": {"coordinates":[-70.09752,41.276039],"type":"Point"}
}