{
  "type": "Feature",
  "properties": {
    "addr:full": "30 High St Medford MA 02155",
    "addr:housenumber": "30",
    "addr:postcode": "02155",
    "addr:street": "High St",
    "iso:country": "US",
    "sg:address": "30 High St",
    "sg:city": "Medford",
    "sg:classifiers": [
      {
        "category": "Professional",
        "subcategory": "Accounting \u0026 Tax Preparation",
        "type": "Services"
      }
    ],
    "sg:phone": "+1 781 395 0016",
    "sg:postcode": "02155",
    "sg:province": "MA",
    "sg:tags": [
      "accountant"
    ],
    "wof:name": "Stanley Eckstein CPA",
    "wof:placetype": "venue"
  },
  "geometry": {"coordinates":[-71.110765,42.418448],"type":"Point"}
}
