{
  "type": "Feature",
  "properties": {
    "iso:country":"US",
    "sg:address":"741 Purchase St",
    "sg:city":"New Bedford",
    "sg:classifiers":[
        {
            "category":"Shopping",
            "subcategory":"News",
            "type":"Retail Goods"
        }
    ],
    "sg:phone":"+1 508 993 8639",
    "sg:postcode":"02740",
    "sg:province":"MA",
    "sg:tags":[
        "magazine"
    ],
    "wof:name":"Dusty's Magazine Store",
    "wof:placetype":"venue"
},
  "geometry": {"coordinates":[-70.926016,41.634897],"type":"Point"}
}