{
  "type": "Feature",
  "properties": {
    "addr:full": "88 Maple St Waltham MA 02453",
    "addr:housenumber": "88",
    "addr:postcode": "02453",
    "addr:street": "Maple St",
    "iso:country": "US",
    "sg:address": "88 Maple St",
    "sg:city": "Waltham",
    "sg:classifiers": [
      {
        "category": "Health Services",
        "subcategory": "Chiropractor",
        "type": "Services"
      }
    ],
    "sg:phone": "+1 781 478 0011",
    "sg:postcode": "02453",
    "sg:province": "MA",
    "wof:name": "Medical Chiropractic Neurolgcl",
    "wof:placetype": "venue"
  },
  "geometry": {"coordinates":[-71.240136,42.368127],"type":"Point"}
}
