{
  "type": "Feature",
  "properties": {
    "addr:full": "25 Acorn Park Cambridge MA 02140",
    "addr:housenumber": "25",
    "addr:postcode": "02140",
    "addr:street": "Acorn Park",
    "iso:country": "US",
    "sg:address": "25 Acorn Park",
    "sg:city": "Cambridge",
    "sg:phone": "+1 617 498 7300",
    "sg:postcode": "02140",
    "sg:province": "MA",
    "sg:tags": [
      "oil"
    ],
    "wof:name": "Nuvera Fuel Cells",
    "wof:placetype": "venue"
  },
  "geometry": {"coordinates":[-71.149772,42.397893],"type":"Point"}
}
