{
  "type": "Feature",
  "properties": {
    "addr:full": "37 Hutchings St Dorchester MA 02121",
    "addr:housenumber": "37",
    "addr:postcode": "02121",
    "addr:street": "Hutchings St",
    "iso:country": "US",
    "sg:address": "37 Hutchings St",
    "sg:city": "Dorchester",
    "sg:classifiers": [
      {
        "category": "Building \u0026 Trades",
        "subcategory": "Construction",
        "type": "Services"
      }
    ],
    "sg:phone": "+1 617 427 4287",
    "sg:postcode": "02121",
    "sg:province": "MA",
    "sg:tags": [
      "painter"
    ],
    "wof:name": "All Interiors \u0026 Exterior Paint",
    "wof:placetype": "venue"
  },
  "geometry": {"coordinates":[-71.088922,42.310128],"type":"Point"}
}
