{
  "type": "Feature",
  "properties": {
    "iso:country":"US",
    "sg:address":"37 Hutchings St",
    "sg:city":"Dorchester",
    "sg:classifiers":[
        {
            "category":"Building & Trades",
            "subcategory":"Construction",
            "type":"Services"
        }
    ],
    "sg:phone":"+1 617 427 4287",
    "sg:postcode":"02121",
    "sg:province":"MA",
    "sg:tags":[
        "painter"
    ],
    "wof:name":"All Interiors & Exterior Paint",
    "wof:placetype":"venue"
},
  "geometry": {"coordinates":[-71.088922,42.310128],"type":"Point"}
}