{
  "type": "Feature",
  "properties": {
    "addr:full":"196 Turnpike Rd Westborough MA 01581",
    "addr:housenumber":"196",
    "addr:postcode":"01581",
    "addr:street":"Turnpike Rd",
    "iso:country":"US",
    "sg:address":"196 Turnpike Rd",
    "sg:city":"Westborough",
    "sg:classifiers":[
        {
            "category":"Science Facility",
            "type":"Public Place"
        }
    ],
    "sg:phone":"+1 508 366 0494",
    "sg:postcode":"01581",
    "sg:province":"MA",
    "sg:tags":[
        "development",
        "laboratories-research"
    ],
    "wof:name":"Basement Transformation Technologies Metro West",
    "wof:placetype":"venue"
},
  "geometry": {"coordinates":[-71.62591,42.284098],"type":"Point"}
}