{
  "type": "Feature",
  "properties": {
    "iso:country":"US",
    "sg:address":"291 Pecks Rd",
    "sg:city":"Pittsfield",
    "sg:classifiers":[
        {
            "category":"Recreation",
            "type":"Entertainment"
        }
    ],
    "sg:phone":"+1 413 443 5229",
    "sg:postcode":"01201",
    "sg:province":"MA",
    "sg:tags":[
        "carnival"
    ],
    "wof:name":"Gillette Shows Inc",
    "wof:placetype":"venue"
},
  "geometry": {"coordinates":[-73.260706,42.473594],"type":"Point"}
}