{
  "type": "Feature",
  "properties": {
    "addr:full":"95 Salem St Boston MA 02113",
    "addr:housenumber":"95",
    "addr:postcode":"02113",
    "addr:street":"Salem St",
    "iso:country":"US",
    "sg:address":"95 Salem St",
    "sg:city":"Boston",
    "sg:classifiers":[
        {
            "category":"Building & Trades",
            "subcategory":"Locksmith",
            "type":"Services"
        }
    ],
    "sg:phone":"+1 617 303 2782",
    "sg:postcode":"02113",
    "sg:province":"MA",
    "sg:tags":[
        "key"
    ],
    "wof:name":"Super Duper Locksmith",
    "wof:placetype":"venue"
},
  "geometry": {"coordinates":[-71.05553500000001,42.363795],"type":"Point"}
}