{
  "type": "Feature",
  "properties": {
    "iso:country":"US",
    "sg:address":"560 Tremont St",
    "sg:city":"Boston",
    "sg:classifiers":[
        {
            "category":"Restaurant",
            "type":"Food & Drink"
        }
    ],
    "sg:menulink":"http://www.allmenus.com/ma/boston/260710-pops/menu/",
    "sg:phone":"+1 617 695 1250",
    "sg:postcode":"02118",
    "sg:province":"MA",
    "sg:tags":[
        "american"
    ],
    "wof:name":"POPS",
    "wof:placetype":"venue"
},
  "geometry": {"coordinates":[-71.071759,42.343627],"type":"Point"}
}