{
  "type": "Feature",
  "properties": {
    "iso:country":"US",
    "sg:address":"10 Manning Ave",
    "sg:city":"Leominster",
    "sg:classifiers":[
        {
            "category":"Retail",
            "subcategory":"Auto Repair",
            "type":"Services"
        }
    ],
    "sg:phone":"+1 978 534 8996",
    "sg:postcode":"01453",
    "sg:province":"MA",
    "sg:tags":[
        "automobile",
        "top",
        "upholstery"
    ],
    "wof:name":"Blanchette's Auto Tops",
    "wof:placetype":"venue"
},
  "geometry": {"coordinates":[-71.75877199999999,42.525322],"type":"Point"}
}