{
  "type": "Feature",
  "properties": {
    "iso:country":"US",
    "sg:address":"10 Milk Street",
    "sg:city":"Boston",
    "sg:classifiers":[
        {
            "category":"Professional",
            "subcategory":"Lawyer & Legal Services",
            "type":"Services"
        }
    ],
    "sg:phone":"+1 617 338 3177",
    "sg:postcode":"02108",
    "sg:province":"MA",
    "wof:name":"Gilbert Galen Atty",
    "wof:placetype":"venue"
},
  "geometry": {"coordinates":[-71.058047,42.358955],"type":"Point"}
}