{
  "type": "Feature",
  "properties": {
    "addr:full": "10 Milk Street Boston MA 02108",
    "addr:housenumber": "10",
    "addr:postcode": "02108",
    "addr:street": "Milk Street",
    "iso:country": "US",
    "sg:address": "10 Milk Street",
    "sg:city": "Boston",
    "sg:classifiers": [
      {
        "category": "Professional",
        "subcategory": "Lawyer \u0026 Legal Services",
        "type": "Services"
      }
    ],
    "sg:phone": "+1 617 338 3177",
    "sg:postcode": "02108",
    "sg:province": "MA",
    "wof:name": "Gilbert Galen Atty",
    "wof:placetype": "venue"
  },
  "geometry": {"coordinates":[-71.058047,42.358955],"type":"Point"}
}
