{
  "type": "Feature",
  "properties": {
    "iso:country":"US",
    "sg:address":"161 Pleasant St",
    "sg:city":"Lynn",
    "sg:classifiers":[
        {
            "category":"Manufacturing",
            "subcategory":"Paper Products",
            "type":"Manufacturing & Wholesale Goods"
        }
    ],
    "sg:phone":"+1 781 595 1030",
    "sg:postcode":"01901",
    "sg:province":"MA",
    "sg:tags":[
        "bag"
    ],
    "wof:name":"Pleasant Poly Intl",
    "wof:placetype":"venue"
},
  "geometry": {"coordinates":[-70.948268,42.459681],"type":"Point"}
}