{
  "type": "Feature",
  "properties": {
    "addr:full":"170 Temple St Newton MA 02465",
    "addr:housenumber":"170",
    "addr:postcode":"02465",
    "addr:street":"Temple St",
    "iso:country":"US",
    "sg:address":"170 Temple St",
    "sg:city":"Newton",
    "sg:classifiers":[
        {
            "category":"Education",
            "subcategory":"School",
            "type":"Public Place"
        }
    ],
    "sg:phone":"+1 617 559 9630",
    "sg:postcode":"02465",
    "sg:province":"MA",
    "wof:name":"Pierce Elementary School",
    "wof:placetype":"venue"
},
  "geometry": {"coordinates":[-71.231661,42.342608],"type":"Point"}
}