{
  "type": "Feature",
  "properties": {
    "iso:country":"US",
    "sg:address":"11 Red Coat Ln",
    "sg:city":"Plainville",
    "sg:classifiers":[
        {
            "category":"Retail",
            "subcategory":"Auto Repair",
            "type":"Services"
        }
    ],
    "sg:phone":"+1   ",
    "sg:postcode":"02762",
    "sg:province":"MA",
    "sg:tags":[
        "general"
    ],
    "wof:name":"Cyr Bros",
    "wof:placetype":"venue"
},
  "geometry": {"coordinates":[-71.29698500000001,42.020382],"type":"Point"}
}