{
  "type": "Feature",
  "properties": {
    "addr:full":"10 Rayber Rd Orleans MA 02653",
    "addr:housenumber":"10",
    "addr:postcode":"02653",
    "addr:street":"Rayber Rd",
    "iso:country":"US",
    "sg:address":"10 Rayber Rd",
    "sg:city":"Orleans",
    "sg:classifiers":[
        {
            "category":"Retail",
            "subcategory":"Auto Repair",
            "type":"Services"
        }
    ],
    "sg:phone":"+1   ",
    "sg:postcode":"02653",
    "sg:province":"MA",
    "sg:tags":[
        "body"
    ],
    "wof:name":"Greggs Auto Body",
    "wof:placetype":"venue"
},
  "geometry": {"coordinates":[-69.991827,41.775662],"type":"Point"}
}