{
  "type": "Feature",
  "properties": {
    "addr:full": "35 Professors Row Medford MA 02155",
    "addr:housenumber": "35",
    "addr:postcode": "02155",
    "addr:street": "Professors Row",
    "iso:country": "US",
    "ovtr:label": "Tisch Library, 35 Professors Row Medford MA US",
    "ovtr:similarity": 3.3500618934631348,
    "sg:address": "35 Professors Row",
    "sg:city": "Medford",
    "sg:classifiers": [
      {
        "category": "Education",
        "subcategory": "Library",
        "type": "Public Place"
      }
    ],
    "sg:phone": "+1 617 627 3345",
    "sg:postcode": "02155",
    "sg:province": "MA",
    "sg:website": "www.library.tufts.edu",
    "wof:name": "Tisch Library",
    "wof:placetype": "venue"
  },
  "geometry": {"coordinates":[-71.117445,42.40564],"type":"Point"}
}
