{
  "type": "Feature",
  "properties": {
    "iso:country":"US",
    "sg:address":"1 E Main St",
    "sg:city":"Georgetown",
    "sg:classifiers":[
        {
            "category":"Personal",
            "subcategory":"Beauty Salon",
            "type":"Services"
        }
    ],
    "sg:phone":"+1 978 352 7484",
    "sg:postcode":"01833",
    "sg:province":"MA",
    "sg:tags":[
        "shop"
    ],
    "wof:name":"Tip To Toe",
    "wof:placetype":"venue"
},
  "geometry": {"coordinates":[-70.991066,42.724166],"type":"Point"}
}