{
  "type": "Feature",
  "properties": {
    "iso:country":"US",
    "sg:address":"56 Miles St",
    "sg:city":"Millbury",
    "sg:classifiers":[
        {
            "category":"Building & Trades",
            "subcategory":"Construction",
            "type":"Services"
        }
    ],
    "sg:phone":"+1 508 865 1575",
    "sg:postcode":"01527",
    "sg:province":"MA",
    "sg:tags":[
        "industrial",
        "painting",
        "contractors-commercial",
        "contractor"
    ],
    "wof:name":"Johnson & Johnson Painting Co",
    "wof:placetype":"venue"
},
  "geometry": {"coordinates":[-71.761099,42.197911],"type":"Point"}
}