{
  "type": "Feature",
  "properties": {
    "addr:full": "56 Miles St Millbury MA 01527",
    "addr:housenumber": "56",
    "addr:postcode": "01527",
    "addr:street": "Miles St",
    "iso:country": "US",
    "sg:address": "56 Miles St",
    "sg:city": "Millbury",
    "sg:classifiers": [
      {
        "category": "Building \u0026 Trades",
        "subcategory": "Construction",
        "type": "Services"
      }
    ],
    "sg:phone": "+1 508 865 1575",
    "sg:postcode": "01527",
    "sg:province": "MA",
    "sg:tags": [
      "industrial",
      "painting",
      "contractors-commercial",
      "contractor"
    ],
    "wof:name": "Johnson \u0026 Johnson Painting Co",
    "wof:placetype": "venue"
  },
  "geometry": {"coordinates":[-71.761099,42.197911],"type":"Point"}
}
