{
  "type": "Feature",
  "properties": {
    "iso:country":"US",
    "sg:address":"91 Pittsfield Rd",
    "sg:city":"Lenox",
    "sg:classifiers":[
        {
            "category":"Shopping",
            "subcategory":"Bicycles & Sporting Goods",
            "type":"Retail Goods"
        }
    ],
    "sg:phone":"+1 413 637 3010",
    "sg:postcode":"01240",
    "sg:province":"MA",
    "sg:website":"www.arcadian.com",
    "wof:name":"Arcadian Shop Inc",
    "wof:placetype":"venue"
},
  "geometry": {"coordinates":[-73.27674399999999,42.380009],"type":"Point"}
}