{
  "type": "Feature",
  "properties": {
    "addr:full": "6 State Park Rd Hull MA 02045",
    "addr:housenumber": "6",
    "addr:postcode": "02045",
    "addr:street": "State Park Rd",
    "iso:country": "US",
    "sg:address": "6 State Park Rd",
    "sg:city": "Hull",
    "sg:classifiers": [
      {
        "category": "Building \u0026 Trades",
        "subcategory": "Construction",
        "type": "Services"
      }
    ],
    "sg:phone": "+1 781 925 5600",
    "sg:postcode": "02045",
    "sg:province": "MA",
    "sg:tags": [
      "paving",
      "contractor"
    ],
    "wof:name": "Callaghan Paving",
    "wof:placetype": "venue"
  },
  "geometry": {"coordinates":[-70.847232,42.266993],"type":"Point"}
}
