{
  "type": "Feature",
  "properties": {
    "addr:full":"354 Merrimack St Lawrence MA 01843",
    "addr:housenumber":"354",
    "addr:postcode":"01843",
    "addr:street":"Merrimack St",
    "iso:country":"US",
    "sg:address":"354 Merrimack St",
    "sg:city":"Lawrence",
    "sg:classifiers":[
        {
            "category":"Professional",
            "type":"Services"
        }
    ],
    "sg:phone":"+1 978 946 9290",
    "sg:postcode":"01843",
    "sg:province":"MA",
    "sg:tags":[
        "establishment"
    ],
    "wof:name":"C4N",
    "wof:placetype":"venue"
},
  "geometry": {"coordinates":[-71.141403,42.703557],"type":"Point"}
}