{
  "type": "Feature",
  "properties": {
    "addr:full":"4 Downing Dr Norton MA 02766",
    "addr:housenumber":"4",
    "addr:postcode":"02766",
    "addr:street":"Downing Dr",
    "iso:country":"US",
    "sg:address":"4 Downing Dr",
    "sg:city":"Norton",
    "sg:classifiers":[
        {
            "category":"Cinema",
            "subcategory":"Movie Theater",
            "type":"Entertainment"
        }
    ],
    "sg:phone":"+1 508 285 0005",
    "sg:postcode":"02766",
    "sg:province":"MA",
    "sg:website":"http://www.reelworldmanagement.com",
    "wof:name":"Reel World Theatre",
    "wof:placetype":"venue"
},
  "geometry": {"coordinates":[-71.145781,41.991012],"type":"Point"}
}