{
  "type": "Feature",
  "properties": {
    "iso:country":"US",
    "sg:address":"507 E Central St",
    "sg:city":"Franklin",
    "sg:classifiers":[
        {
            "category":"Autos & Motor Vehicles",
            "subcategory":"Auto Supplies",
            "type":"Retail Goods"
        },
        {
            "category":"Wholesale",
            "subcategory":"Electrical",
            "type":"Manufacturing & Wholesale Goods"
        }
    ],
    "sg:phone":"+1 508 528 5342",
    "sg:postcode":"02038",
    "sg:province":"MA",
    "sg:tags":[
        "battery",
        "part",
        "accessory",
        "automobile"
    ],
    "sg:website":"http://www.carquest.com",
    "wof:name":"Carquest Auto Parts",
    "wof:placetype":"venue"
},
  "geometry": {"coordinates":[-71.37608299999999,42.079708],"type":"Point"}
}