{
  "type": "Feature",
  "properties": {
    "addr:full": "507 E Central St Franklin MA 02038",
    "addr:housenumber": "507",
    "addr:postcode": "02038",
    "addr:street": "E Central St",
    "iso:country": "US",
    "sg:address": "507 E Central St",
    "sg:city": "Franklin",
    "sg:classifiers": [
      {
        "category": "Autos \u0026 Motor Vehicles",
        "subcategory": "Auto Supplies",
        "type": "Retail Goods"
      },
      {
        "category": "Wholesale",
        "subcategory": "Electrical",
        "type": "Manufacturing \u0026 Wholesale Goods"
      }
    ],
    "sg:phone": "+1 508 528 5342",
    "sg:postcode": "02038",
    "sg:province": "MA",
    "sg:tags": [
      "battery",
      "part",
      "accessory",
      "automobile"
    ],
    "sg:website": "http://www.carquest.com",
    "wof:name": "Carquest Auto Parts",
    "wof:placetype": "venue"
  },
  "geometry": {"coordinates":[-71.376083,42.079708],"type":"Point"}
}
