{
  "type": "Feature",
  "properties": {
    "iso:country":"US",
    "sg:address":"168 Elm St",
    "sg:city":"Agawam",
    "sg:classifiers":[
        {
            "category":"Professional",
            "subcategory":"Business Services",
            "type":"Services"
        }
    ],
    "sg:phone":"+1 413 786 8304",
    "sg:postcode":"01001",
    "sg:province":"MA",
    "sg:tags":[
        "packaging"
    ],
    "wof:name":"Packaging Service Inc",
    "wof:placetype":"venue"
},
  "geometry": {"coordinates":[-72.623659,42.065445],"type":"Point"}
}