{
  "type": "Feature",
  "properties": {
    "addr:full": "215 Cambridge Tpke Concord MA 01742",
    "addr:housenumber": "215",
    "addr:postcode": "01742",
    "addr:street": "Cambridge Tpke",
    "iso:country": "US",
    "sg:address": "215 Cambridge Tpke",
    "sg:city": "Concord",
    "sg:classifiers": [
      {
        "category": "Wholesale",
        "subcategory": "Fruits \u0026 Vegetables",
        "type": "Manufacturing \u0026 Wholesale Goods"
      }
    ],
    "sg:phone": "+1 978 369 1523",
    "sg:postcode": "01742",
    "sg:province": "MA",
    "sg:tags": [
      "veggie"
    ],
    "wof:name": "Millbrook Farms Inc",
    "wof:placetype": "venue"
  },
  "geometry": {"coordinates":[-71.33707,42.455746],"type":"Point"}
}
