{
  "type": "Feature",
  "properties": {
    "iso:country":"US",
    "sg:address":"215 Cambridge Tpke",
    "sg:city":"Concord",
    "sg:classifiers":[
        {
            "category":"Wholesale",
            "subcategory":"Fruits & Vegetables",
            "type":"Manufacturing & Wholesale Goods"
        }
    ],
    "sg:phone":"+1 978 369 1523",
    "sg:postcode":"01742",
    "sg:province":"MA",
    "sg:tags":[
        "veggie"
    ],
    "wof:name":"Millbrook Farms Inc",
    "wof:placetype":"venue"
},
  "geometry": {"coordinates":[-71.33707,42.455746],"type":"Point"}
}