{
  "type": "Feature",
  "properties": {
    "addr:full":"43 Highland Ave Cohasset MA 02025",
    "addr:housenumber":"43",
    "addr:postcode":"02025",
    "addr:street":"Highland Ave",
    "iso:country":"US",
    "sg:address":"43 Highland Ave",
    "sg:city":"Cohasset",
    "sg:classifiers":[
        {
            "category":"Organizations",
            "subcategory":"Religious Organization",
            "type":"Services"
        }
    ],
    "sg:phone":"+1 781 383 0345",
    "sg:postcode":"02025",
    "sg:province":"MA",
    "sg:tags":[
        "church"
    ],
    "wof:name":"Second Congregational Church",
    "wof:placetype":"venue"
},
  "geometry": {"coordinates":[-70.80288899999999,42.243],"type":"Point"}
}