{
  "type": "Feature",
  "properties": {
    "iso:country":"US",
    "sg:address":"23 Broadway",
    "sg:city":"Hanover",
    "sg:classifiers":[
        {
            "category":"Recreation",
            "type":"Entertainment"
        }
    ],
    "sg:phone":"+1 781 829 9145",
    "sg:postcode":"02339",
    "sg:province":"MA",
    "sg:tags":[
        "stable"
    ],
    "wof:name":"MAJIC Penny Farm",
    "wof:placetype":"venue"
},
  "geometry": {"coordinates":[-70.810121,42.117109],"type":"Point"}
}