{
  "type": "Feature",
  "properties": {
    "iso:country":"US",
    "sg:address":"837 Daniel Shays Hwy",
    "sg:city":"New Salem",
    "sg:classifiers":[
        {
            "category":"Wholesale",
            "subcategory":"Groceries",
            "type":"Manufacturing & Wholesale Goods"
        }
    ],
    "sg:phone":"+1 978 544 2806",
    "sg:postcode":"01355",
    "sg:province":"MA",
    "sg:tags":[
        "tea",
        "coffee"
    ],
    "wof:name":"Swift River Coffee Co",
    "wof:placetype":"venue"
},
  "geometry": {"coordinates":[-72.375147,42.461369],"type":"Point"}
}