{
  "type": "Feature",
  "properties": {
    "iso:country":"US",
    "sg:address":"31 Villa Dr",
    "sg:city":"Foxboro",
    "sg:classifiers":[
        {
            "category":"Building & Trades",
            "subcategory":"Landscaping Services",
            "type":"Services"
        }
    ],
    "sg:phone":"+1   ",
    "sg:postcode":"02035",
    "sg:province":"MA",
    "sg:tags":[
        "landscape"
    ],
    "wof:name":"Coviello Landscape",
    "wof:placetype":"venue"
},
  "geometry": {"coordinates":[-71.22910899999999,42.07201],"type":"Point"}
}