{
  "type": "Feature",
  "properties": {
    "addr:full": "31 Villa Dr Foxboro MA 02035",
    "addr:housenumber": "31",
    "addr:postcode": "02035",
    "addr:street": "Villa Dr",
    "iso:country": "US",
    "sg:address": "31 Villa Dr",
    "sg:city": "Foxboro",
    "sg:classifiers": [
      {
        "category": "Building \u0026 Trades",
        "subcategory": "Landscaping Services",
        "type": "Services"
      }
    ],
    "sg:phone": "+1   ",
    "sg:postcode": "02035",
    "sg:province": "MA",
    "sg:tags": [
      "landscape"
    ],
    "wof:name": "Coviello Landscape",
    "wof:placetype": "venue"
  },
  "geometry": {"coordinates":[-71.229109,42.07201],"type":"Point"}
}
