{
  "type": "Feature",
  "properties": {
    "iso:country":"US",
    "sg:address":"1815 Main St",
    "sg:city":"Agawam",
    "sg:classifiers":[
        {
            "category":"Professional",
            "type":"Services"
        },
        {
            "category":"Shopping",
            "subcategory":"Bicycles & Sporting Goods",
            "type":"Retail Goods"
        },
        {
            "category":"Wholesale",
            "subcategory":"Chemicals & Plastics",
            "type":"Manufacturing & Wholesale Goods"
        }
    ],
    "sg:phone":"+1 413 786 7214",
    "sg:postcode":"01001",
    "sg:province":"MA",
    "sg:tags":[
        "supply",
        "tubs-repair",
        "equipment",
        "hot",
        "spa",
        "manufacturer",
        "supplies-wholesale",
        "pool",
        "swimming"
    ],
    "sg:website":"http://www.drewnowskipoolsandspas.com",
    "wof:name":"Drewnowski Pools and Spas - A BioGuard Platinum Dealer",
    "wof:placetype":"venue"
},
  "geometry": {"coordinates":[-72.616882,42.031689],"type":"Point"}
}