{
  "type": "Feature",
  "properties": {
    "iso:country":"US",
    "sg:address":"757 Turnpike St",
    "sg:city":"North Andover",
    "sg:classifiers":[
        {
            "category":"Shopping",
            "subcategory":"Pharmacy",
            "type":"Retail Goods"
        }
    ],
    "sg:phone":"+1 978 683 4925",
    "sg:postcode":"01845",
    "sg:province":"MA",
    "wof:name":"Stop & Shop Pharmacy",
    "wof:placetype":"venue"
},
  "geometry": {"coordinates":[-71.106106,42.658791],"type":"Point"}
}