{
  "type": "Feature",
  "properties": {
    "addr:full":"127 County Rd North Falmouth MA 02556",
    "addr:housenumber":"127",
    "addr:postcode":"02556",
    "addr:street":"County Rd North",
    "iso:country":"US",
    "sg:address":"127 County Rd",
    "sg:city":"North Falmouth",
    "sg:classifiers":[
        {
            "category":"Retail",
            "subcategory":"Auto Repair",
            "type":"Services"
        }
    ],
    "sg:phone":"+1 508 563 3848",
    "sg:postcode":"02556",
    "sg:province":"MA",
    "sg:tags":[
        "repairing",
        "automobile"
    ],
    "wof:name":"Sports Imports of Cape Cod",
    "wof:placetype":"venue"
},
  "geometry": {"coordinates":[-70.619598,41.650799],"type":"Point"}
}