{
  "type": "Feature",
  "properties": {
    "addr:full":"15 Lucas Dr Allston MA 02190",
    "addr:housenumber":"15",
    "addr:postcode":"02190",
    "addr:street":"Lucas Dr",
    "iso:country":"US",
    "sg:address":"15 Lucas Dr",
    "sg:city":"Allston",
    "sg:classifiers":[
        {
            "category":"Professional",
            "subcategory":"Computer Services",
            "type":"Services"
        }
    ],
    "sg:phone":"+1 617 254 6700",
    "sg:postcode":"02190",
    "sg:province":"MA",
    "sg:tags":[
        "website",
        "design"
    ],
    "wof:name":"Fireghost Web Development",
    "wof:placetype":"venue"
},
  "geometry": {"coordinates":[-70.928301,42.157581],"type":"Point"}
}