{
  "type": "Feature",
  "properties": {
    "iso:country":"US",
    "sg:address":"38 N Main St",
    "sg:city":"North Grafton",
    "sg:classifiers":[
        {
            "category":"Retail",
            "subcategory":"Laundry & Dry Cleaning",
            "type":"Services"
        }
    ],
    "sg:phone":"+1 508 839 4982",
    "sg:postcode":"01536",
    "sg:province":"MA",
    "sg:tags":[
        "cleaners"
    ],
    "wof:name":"Rudy's Dry Cleaning",
    "wof:placetype":"venue"
},
  "geometry": {"coordinates":[-71.708044,42.233337],"type":"Point"}
}