{
  "type": "Feature",
  "properties": {
    "addr:full":"187 Blueberry Pond Dr Brewster MA 02631",
    "addr:housenumber":"187",
    "addr:postcode":"02631",
    "addr:street":"Blueberry Pond Dr",
    "iso:country":"US",
    "sg:address":"187 Blueberry Pond Dr",
    "sg:city":"Brewster",
    "sg:classifiers":[
        {
            "category":"Professional",
            "subcategory":"Business Services",
            "type":"Services"
        }
    ],
    "sg:phone":"+1   ",
    "sg:postcode":"02631",
    "sg:province":"MA",
    "wof:name":"Walden Design",
    "wof:placetype":"venue"
},
  "geometry": {"coordinates":[-70.047698,41.765388],"type":"Point"}
}