{
  "type": "Feature",
  "properties": {
    "iso:country":"US",
    "sg:address":"5 Great Pond Rd",
    "sg:city":"Wenham",
    "sg:classifiers":[
        {
            "category":"Professional",
            "subcategory":"Business Services",
            "type":"Services"
        }
    ],
    "sg:phone":"+1 978 468 2638",
    "sg:postcode":"01984",
    "sg:province":"MA",
    "sg:tags":[
        "interior",
        "consultant",
        "design",
        "decorator"
    ],
    "wof:name":"Gracyn R Whitman Designs",
    "wof:placetype":"venue"
},
  "geometry": {"coordinates":[-70.88248,42.592098],"type":"Point"}
}