{
  "type": "Feature",
  "properties": {
    "addr:full": "1235 Washington St Weymouth MA 02189",
    "addr:housenumber": "1235",
    "addr:postcode": "02189",
    "addr:street": "Washington St",
    "iso:country": "US",
    "sg:address": "1235 Washington St",
    "sg:city": "Weymouth",
    "sg:classifiers": [
      {
        "category": "Personal",
        "subcategory": "Beauty Salon",
        "type": "Services"
      }
    ],
    "sg:phone": "+1 781 340 0919",
    "sg:postcode": "02189",
    "sg:province": "MA",
    "sg:tags": [
      "manicuring"
    ],
    "wof:name": "Nail Express",
    "wof:placetype": "venue"
  },
  "geometry": {"coordinates":[-70.925783,42.195565],"type":"Point"}
}
