{
  "type": "Feature",
  "properties": {
    "addr:full":"126 Fair St New Bedford MA 02740",
    "addr:housenumber":"126",
    "addr:postcode":"02740",
    "addr:street":"Fair St",
    "iso:country":"US",
    "sg:address":"126 Fair St",
    "sg:city":"New Bedford",
    "sg:classifiers":[
        {
            "category":"Insurance",
            "subcategory":"Hazard Insurance",
            "type":"Services"
        }
    ],
    "sg:phone":"+1   ",
    "sg:postcode":"02740",
    "sg:province":"MA",
    "sg:tags":[
        "carrier",
        "surety"
    ],
    "wof:name":"Insurence",
    "wof:placetype":"venue"
},
  "geometry": {"coordinates":[-70.93114799999999,41.623235],"type":"Point"}
}