{
  "type": "Feature",
  "properties": {
    "iso:country":"US",
    "sg:address":"50 Pacella Dr",
    "sg:city":"Dedham",
    "sg:classifiers":[
        {
            "category":"Banks & Credit Unions",
            "subcategory":"Financial Services",
            "type":"Services"
        }
    ],
    "sg:phone":"+1 781 329 1239",
    "sg:postcode":"02026",
    "sg:province":"MA",
    "sg:tags":[
        "scholarship"
    ],
    "wof:name":"The William D Guiod Memorial Scholarship Fund",
    "wof:placetype":"venue"
},
  "geometry": {"coordinates":[-71.186367,42.236678],"type":"Point"}
}