{
  "type": "Feature",
  "properties": {
    "iso:country":"US",
    "sg:address":"161 Lovell's Ln",
    "sg:city":"Marstons Mills",
    "sg:classifiers":[
        {
            "category":"Organizations",
            "subcategory":"Religious Organization",
            "type":"Services"
        }
    ],
    "sg:phone":"+1 508 420 1415",
    "sg:postcode":"02648",
    "sg:province":"MA",
    "sg:tags":[
        "church"
    ],
    "sg:website":"www.newbeginningsfoursquare.com",
    "wof:name":"New Beginnings Foursquare Chr",
    "wof:placetype":"venue"
},
  "geometry": {"coordinates":[-70.409621,41.656077],"type":"Point"}
}