{
  "type": "Feature",
  "properties": {
    "addr:full":"509 Main St Shrewsbury MA 01545",
    "addr:housenumber":"509",
    "addr:postcode":"01545",
    "addr:street":"Main St",
    "iso:country":"US",
    "sg:address":"509 Main St",
    "sg:city":"Shrewsbury",
    "sg:classifiers":[
        {
            "category":"Organizations",
            "subcategory":"Religious Organization",
            "type":"Services"
        }
    ],
    "sg:phone":"+1   ",
    "sg:postcode":"01545",
    "sg:province":"MA",
    "wof:name":"Shrewsbury Clnl Chptr 4831",
    "wof:placetype":"venue"
},
  "geometry": {"coordinates":[-71.717612,42.295708],"type":"Point"}
}