{
  "type": "Feature",
  "properties": {
    "addr:full": "276 South St Pittsfield MA 01201",
    "addr:housenumber": "276",
    "addr:postcode": "01201",
    "addr:street": "South St",
    "iso:country": "US",
    "sg:address": "276 South St",
    "sg:city": "Pittsfield",
    "sg:classifiers": [
      {
        "category": "Social Services",
        "type": "Services"
      }
    ],
    "sg:phone": "+1 413 448 6202",
    "sg:postcode": "01201",
    "sg:province": "MA",
    "sg:tags": [
      "counselor",
      "marriage",
      "family"
    ],
    "wof:name": "Benavides-Mc Cann Assoc",
    "wof:placetype": "venue"
  },
  "geometry": {"coordinates":[-73.257037,42.439856],"type":"Point"}
}
