{
  "type": "Feature",
  "properties": {
    "iso:country":"US",
    "sg:address":"315 Cotuit Rd Ste 10",
    "sg:city":"Sandwich",
    "sg:classifiers":[
        {
            "category":"Personal",
            "type":"Services"
        },
        {
            "category":"Arena",
            "subcategory":"Sports Club",
            "type":"Entertainment"
        }
    ],
    "sg:phone":"+1 508 888 7900",
    "sg:postcode":"02563",
    "sg:province":"MA",
    "sg:tags":[
        "trainer",
        "consultant",
        "physical",
        "health",
        "fitness"
    ],
    "sg:website":"http://www.sportsitehealthclub.com",
    "wof:name":"Sportsite Health & Racquet Clb",
    "wof:placetype":"venue"
},
  "geometry": {"coordinates":[-70.486498,41.708116],"type":"Point"}
}