{
  "type": "Feature",
  "properties": {
    "iso:country":"US",
    "sg:address":"360 South Main Street",
    "sg:city":"Centerville",
    "sg:classifiers":[
        {
            "category":"Ice Cream",
            "type":"Food & Drink"
        }
    ],
    "sg:phone":"+1 508 775 1394",
    "sg:postcode":"02632",
    "sg:province":"MA",
    "sg:tags":[
        "frozen",
        "yogurt"
    ],
    "sg:website":"www.fourseasicecream.com/",
    "wof:name":"Four Seas Ice Cream",
    "wof:placetype":"venue"
},
  "geometry": {"coordinates":[-70.345743,41.644627],"type":"Point"}
}