{
  "type": "Feature",
  "properties": {
    "iso:country":"US",
    "sg:address":"463 Broadway",
    "sg:city":"Lawrence",
    "sg:classifiers":[
        {
            "category":"Bars & Pubs",
            "type":"Food & Drink"
        },
        {
            "category":"Restaurant",
            "type":"Food & Drink"
        },
        {
            "category":"Bars & Pubs",
            "subcategory":"Lounge",
            "type":"Food & Drink"
        }
    ],
    "sg:phone":"+1 978 258 2932",
    "sg:postcode":"01841",
    "sg:province":"MA",
    "sg:tags":[
        "cocktail"
    ],
    "wof:name":"D'wendy Bar And Restaurant",
    "wof:placetype":"venue"
},
  "geometry": {"coordinates":[-71.175613,42.713948],"type":"Point"}
}