{
  "type": "Feature",
  "properties": {
    "addr:full":"24 Bolton St Reading MA 01867",
    "addr:housenumber":"24",
    "addr:postcode":"01867",
    "addr:street":"Bolton St",
    "iso:country":"US",
    "sg:address":"24 Bolton St",
    "sg:city":"Reading",
    "sg:classifiers":[
        {
            "category":"Professional",
            "subcategory":"Business Services",
            "type":"Services"
        }
    ],
    "sg:phone":"+1   ",
    "sg:postcode":"01867",
    "sg:province":"MA",
    "wof:name":"Making Room",
    "wof:placetype":"venue"
},
  "geometry": {"coordinates":[-71.1015,42.520206],"type":"Point"}
}