{
  "type": "Feature",
  "properties": {
    "addr:full": "17 Elcott Rd Quincy MA 02169",
    "addr:housenumber": "17",
    "addr:postcode": "02169",
    "addr:street": "Elcott Rd",
    "iso:country": "US",
    "sg:address": "17 Elcott Rd",
    "sg:city": "Quincy",
    "sg:classifiers": [
      {
        "category": "Professional",
        "subcategory": "Business Services",
        "type": "Services"
      }
    ],
    "sg:phone": "+1   ",
    "sg:postcode": "02169",
    "sg:province": "MA",
    "wof:name": "Girard \u0026 Associates",
    "wof:placetype": "venue"
  },
  "geometry": {"coordinates":[-70.977282,42.26287],"type":"Point"}
}
