{
  "type": "Feature",
  "properties": {
    "iso:country":"US",
    "sg:address":"55 New Athol Rd",
    "sg:city":"Orange",
    "sg:classifiers":[
        {
            "category":"Shopping",
            "type":"Retail Goods"
        }
    ],
    "sg:phone":"+1 978 544 3900",
    "sg:postcode":"01364",
    "sg:province":"MA",
    "sg:tags":[
        "candle"
    ],
    "wof:name":"Bakers Batch Candle Factory",
    "wof:placetype":"venue"
},
  "geometry": {"coordinates":[-72.273397,42.585513],"type":"Point"}
}