{
  "type": "Feature",
  "properties": {
    "iso:country":"US",
    "sg:address":"1206 Massachusetts Ave",
    "sg:city":"Cambridge",
    "sg:classifiers":[
        {
            "category":"Personal",
            "subcategory":"Beauty Salon",
            "type":"Services"
        }
    ],
    "sg:phone":"+1 617 354 5210",
    "sg:postcode":"02138",
    "sg:province":"MA",
    "wof:name":"Andre Hair Salon",
    "wof:placetype":"venue"
},
  "geometry": {"coordinates":[-71.115972,42.372355],"type":"Point"}
}