{
  "type": "Feature",
  "properties": {
    "addr:full": "1206 Massachusetts Ave Cambridge MA 02138",
    "addr:housenumber": "1206",
    "addr:postcode": "02138",
    "addr:street": "Massachusetts Ave",
    "iso:country": "US",
    "ovtr:label": "Andre Hair Salon, 1206 Massachusetts Ave Cambridge MA US",
    "ovtr:similarity": 2.3057620525360107,
    "sg:address": "1206 Massachusetts Ave",
    "sg:city": "Cambridge",
    "sg:classifiers": [
      {
        "category": "Personal",
        "subcategory": "Beauty Salon",
        "type": "Services"
      }
    ],
    "sg:phone": "+1 617 354 5210",
    "sg:postcode": "02138",
    "sg:province": "MA",
    "wof:name": "Andre Hair Salon",
    "wof:placetype": "venue"
  },
  "geometry": {"coordinates":[-71.115972,42.372355],"type":"Point"}
}
