{
  "type": "Feature",
  "properties": {
    "iso:country":"US",
    "sg:address":"43 Village Post Rd",
    "sg:city":"Danvers",
    "sg:classifiers":[
        {
            "category":"Real Estate",
            "subcategory":"Real Estate Operator",
            "type":"Services"
        }
    ],
    "sg:phone":"+1 978 777 4710",
    "sg:postcode":"01923",
    "sg:province":"MA",
    "sg:tags":[
        "condominium"
    ],
    "wof:name":"Olde Salem Village Condo Trust",
    "wof:placetype":"venue"
},
  "geometry": {"coordinates":[-70.957559,42.555068],"type":"Point"}
}