{
  "type": "Feature",
  "properties": {
    "addr:full": "21 University Rd Canton MA 02021",
    "addr:housenumber": "21",
    "addr:postcode": "02021",
    "addr:street": "University Rd",
    "iso:country": "US",
    "sg:address": "21 University Rd",
    "sg:city": "Canton",
    "sg:classifiers": [
      {
        "category": "Professional",
        "subcategory": "Testing Lab",
        "type": "Services"
      },
      {
        "category": "Shopping",
        "subcategory": "Gifts \u0026 Souvenirs",
        "type": "Retail Goods"
      }
    ],
    "sg:phone": "+1 781 821 2221",
    "sg:postcode": "02021",
    "sg:province": "MA",
    "sg:tags": [
      "material",
      "wrapping",
      "chemist"
    ],
    "wof:name": "Shipps Inc",
    "wof:placetype": "venue"
  },
  "geometry": {"coordinates":[-71.154391,42.196163],"type":"Point"}
}
