{
  "type": "Feature",
  "properties": {
    "addr:full": "96 West St Ware MA 01082",
    "addr:housenumber": "96",
    "addr:postcode": "01082",
    "addr:street": "West St",
    "iso:country": "US",
    "sg:address": "96 West St",
    "sg:city": "Ware",
    "sg:classifiers": [
      {
        "category": "Retail",
        "subcategory": "Auto Repair",
        "type": "Services"
      }
    ],
    "sg:phone": "+1 413 967 5101",
    "sg:postcode": "01082",
    "sg:province": "MA",
    "sg:tags": [
      "repairing",
      "automobile"
    ],
    "wof:name": "West Street Auto Svc",
    "wof:placetype": "venue"
  },
  "geometry": {"coordinates":[-72.247857,42.257742],"type":"Point"}
}
