{
  "type": "Feature",
  "properties": {
    "iso:country":"US",
    "sg:address":"400 Lincoln St",
    "sg:city":"Hingham",
    "sg:classifiers":[
        {
            "category":"Shopping",
            "subcategory":"Bicycles & Sporting Goods",
            "type":"Retail Goods"
        }
    ],
    "sg:phone":"+1 781 740 2304",
    "sg:postcode":"02043",
    "sg:province":"MA",
    "wof:name":"Pro Sports",
    "wof:placetype":"venue"
},
  "geometry": {"coordinates":[-70.925062,42.248161],"type":"Point"}
}