{
  "type": "Feature",
  "properties": {
    "addr:full": "12 Swampscott Ave Peabody MA 01960",
    "addr:housenumber": "12",
    "addr:postcode": "01960",
    "addr:street": "Swampscott Ave",
    "iso:country": "US",
    "sg:address": "12 Swampscott Ave",
    "sg:city": "Peabody",
    "sg:classifiers": [
      {
        "category": "Building \u0026 Trades",
        "subcategory": "Construction",
        "type": "Services"
      }
    ],
    "sg:phone": "+1   ",
    "sg:postcode": "01960",
    "sg:province": "MA",
    "sg:tags": [
      "contractor"
    ],
    "wof:name": "Paul Dulkis Plastering \u0026 Cnstr",
    "wof:placetype": "venue"
  },
  "geometry": {"coordinates":[-70.931984,42.518256],"type":"Point"}
}
