{
  "type": "Feature",
  "properties": {
    "addr:full": "101 Fenn St Pittsfield MA 01201",
    "addr:housenumber": "101",
    "addr:postcode": "01201",
    "addr:street": "Fenn St",
    "iso:country": "US",
    "sg:address": "101 Fenn St",
    "sg:city": "Pittsfield",
    "sg:classifiers": [
      {
        "category": "Banks \u0026 Credit Unions",
        "subcategory": "Bank",
        "type": "Services"
      }
    ],
    "sg:phone": "+1 413 442 6501",
    "sg:postcode": "01201",
    "sg:province": "MA",
    "wof:name": "My Com Federal Credit Union",
    "wof:placetype": "venue"
  },
  "geometry": {"coordinates":[-73.25087,42.449901],"type":"Point"}
}
