{
  "type": "Feature",
  "properties": {
    "addr:full": "202 K St Ste 1 Boston MA 02127",
    "addr:housenumber": "202",
    "addr:postcode": "02127",
    "addr:street": "K St Ste 1",
    "iso:country": "US",
    "sg:address": "202 K St Ste 1",
    "sg:city": "Boston",
    "sg:classifiers": [
      {
        "category": "Real Estate",
        "subcategory": "Real Estate Services",
        "type": "Services"
      },
      {
        "category": "Banks \u0026 Credit Unions",
        "subcategory": "Financial Services",
        "type": "Services"
      }
    ],
    "sg:phone": "+1 617 464 1004",
    "sg:postcode": "02127",
    "sg:province": "MA",
    "sg:tags": [
      "loan",
      "processing",
      "broker",
      "mortgage"
    ],
    "wof:name": "First Capital Mortgage Group Llc",
    "wof:placetype": "venue"
  },
  "geometry": {"coordinates":[-71.037241,42.336406],"type":"Point"}
}
