{
  "type": "Feature",
  "properties": {
    "iso:country":"US",
    "sg:address":"261 Park Ave",
    "sg:city":"Worcester",
    "sg:classifiers":[
        {
            "category":"Shopping",
            "subcategory":"Gifts & Souvenirs",
            "type":"Retail Goods"
        }
    ],
    "sg:phone":"+1 508 755 7808",
    "sg:postcode":"01609",
    "sg:province":"MA",
    "sg:tags":[
        "shop"
    ],
    "wof:name":"Artworks Gallery",
    "wof:placetype":"venue"
},
  "geometry": {"coordinates":[-71.819288,42.264267],"type":"Point"}
}