{
  "type": "Feature",
  "properties": {
    "addr:full": "177 Tremont St Boston MA 02111",
    "addr:housenumber": "177",
    "addr:postcode": "02111",
    "addr:street": "Tremont St",
    "iso:country": "US",
    "sg:address": "177 Tremont St",
    "sg:city": "Boston",
    "sg:classifiers": [
      {
        "category": "Shopping",
        "subcategory": "Computers \u0026 Home Electronics",
        "type": "Retail Goods"
      }
    ],
    "sg:phone": "+1 617 338 7898",
    "sg:postcode": "02111",
    "sg:province": "MA",
    "sg:tags": [
      "software"
    ],
    "wof:name": "Client Server Engineering Svc",
    "wof:placetype": "venue"
  },
  "geometry": {"coordinates":[-71.064265,42.353142],"type":"Point"}
}
