{
  "type": "Feature",
  "properties": {
    "iso:country":"US",
    "sg:address":"177 Tremont St",
    "sg:city":"Boston",
    "sg:classifiers":[
        {
            "category":"Shopping",
            "subcategory":"Computers & Home Electronics",
            "type":"Retail Goods"
        }
    ],
    "sg:phone":"+1 617 338 7898",
    "sg:postcode":"02111",
    "sg:province":"MA",
    "sg:tags":[
        "software"
    ],
    "wof:name":"Client Server Engineering Svc",
    "wof:placetype":"venue"
},
  "geometry": {"coordinates":[-71.06426500000001,42.353142],"type":"Point"}
}