{
  "type": "Feature",
  "properties": {
    "addr:full":"432 N Falmouth Hwy North Falmouth MA 02556",
    "addr:housenumber":"432",
    "addr:postcode":"02556",
    "addr:street":"N Falmouth Hwy North",
    "iso:country":"US",
    "sg:address":"432 N Falmouth Hwy",
    "sg:city":"North Falmouth",
    "sg:classifiers":[
        {
            "category":"Building & Trades",
            "subcategory":"Equipment Rental",
            "type":"Services"
        }
    ],
    "sg:phone":"+1 508 563 1960",
    "sg:postcode":"02556",
    "sg:province":"MA",
    "sg:tags":[
        "yard"
    ],
    "sg:website":"www.taylorrental-capecod.com",
    "wof:name":"Taylor Rental Ctr",
    "wof:placetype":"venue"
},
  "geometry": {"coordinates":[-70.61600799999999,41.639622],"type":"Point"}
}