{
  "type": "Feature",
  "properties": {
    "addr:full":"774 College Hwy Southwick MA 01077",
    "addr:housenumber":"774",
    "addr:postcode":"01077",
    "addr:street":"College Hwy",
    "iso:country":"US",
    "sg:address":"774 College Hwy",
    "sg:city":"Southwick",
    "sg:classifiers":[
        {
            "category":"Health Services",
            "subcategory":"Doctor",
            "type":"Services"
        }
    ],
    "sg:phone":"+1 413 569 5837",
    "sg:postcode":"01077",
    "sg:province":"MA",
    "sg:tags":[
        "physician",
        "surgeon"
    ],
    "wof:name":"Paul A Lagac MD",
    "wof:placetype":"venue"
},
  "geometry": {"coordinates":[-72.768597,42.077241],"type":"Point"}
}