{
  "type": "Feature",
  "properties": {
    "addr:full": "47 Gerald Rd Marblehead MA 01945",
    "addr:housenumber": "47",
    "addr:postcode": "01945",
    "addr:street": "Gerald Rd",
    "iso:country": "US",
    "sg:address": "47 Gerald Rd",
    "sg:city": "Marblehead",
    "sg:classifiers": [
      {
        "category": "Professional",
        "subcategory": "Management \u0026 Consulting",
        "type": "Services"
      }
    ],
    "sg:phone": "+1   ",
    "sg:postcode": "01945",
    "sg:province": "MA",
    "wof:name": "Lewis Jaffe",
    "wof:placetype": "venue"
  },
  "geometry": {"coordinates":[-70.868701,42.489644],"type":"Point"}
}
