{
  "type": "Feature",
  "properties": {
    "iso:country":"US",
    "sg:address":"47 Gerald Rd",
    "sg:city":"Marblehead",
    "sg:classifiers":[
        {
            "category":"Professional",
            "subcategory":"Management & Consulting",
            "type":"Services"
        }
    ],
    "sg:phone":"+1   ",
    "sg:postcode":"01945",
    "sg:province":"MA",
    "wof:name":"Lewis Jaffe",
    "wof:placetype":"venue"
},
  "geometry": {"coordinates":[-70.868701,42.489644],"type":"Point"}
}