{
  "type": "Feature",
  "properties": {
    "addr:full": "57 High Street Medford MA 02155",
    "addr:housenumber": "57",
    "addr:postcode": "02155",
    "addr:street": "High Street",
    "iso:country": "US",
    "sg:address": "57 High Street",
    "sg:city": "Medford",
    "sg:classifiers": [
      {
        "category": "Communications",
        "subcategory": "Newspaper",
        "type": "Services"
      }
    ],
    "sg:phone": "+1 781 322 6957",
    "sg:postcode": "02155",
    "sg:province": "MA",
    "sg:tags": [
      "print",
      "medium"
    ],
    "wof:name": "Malden Observer",
    "wof:placetype": "venue"
  },
  "geometry": {"coordinates":[-71.111374,42.418552],"type":"Point"}
}
