{
  "type": "Feature",
  "properties": {
    "iso:country":"US",
    "sg:address":"685 N Bedford St",
    "sg:city":"East Bridgewater",
    "sg:classifiers":[
        {
            "category":"Personal",
            "subcategory":"Beauty Salon",
            "type":"Services"
        }
    ],
    "sg:phone":"+1 508 350 0008",
    "sg:postcode":"02333",
    "sg:province":"MA",
    "sg:tags":[
        "manicuring"
    ],
    "wof:name":"Angel's Nails",
    "wof:placetype":"venue"
},
  "geometry": {"coordinates":[-70.95187199999999,42.056926],"type":"Point"}
}