{
  "type": "Feature",
  "properties": {
    "iso:country":"US",
    "sg:address":"72 Main St",
    "sg:city":"Harwich",
    "sg:classifiers":[
        {
            "category":"Health Services",
            "subcategory":"Health Practitioner",
            "type":"Services"
        }
    ],
    "sg:phone":"+1 508 430 0693",
    "sg:postcode":"02645",
    "sg:province":"MA",
    "sg:tags":[
        "psychologist"
    ],
    "wof:name":"Robert D Aron PHD",
    "wof:placetype":"venue"
},
  "geometry": {"coordinates":[-70.12815399999999,41.699444],"type":"Point"}
}