{
  "type": "Feature",
  "properties": {
    "iso:country":"US",
    "sg:address":"15 Keniston Rd",
    "sg:city":"Melrose",
    "sg:classifiers":[
        {
            "category":"Building & Trades",
            "subcategory":"Construction",
            "type":"Services"
        }
    ],
    "sg:phone":"+1   ",
    "sg:postcode":"02176",
    "sg:province":"MA",
    "sg:tags":[
        "house"
    ],
    "wof:name":"Scully Const Co Inc",
    "wof:placetype":"venue"
},
  "geometry": {"coordinates":[-71.056084,42.462672],"type":"Point"}
}