{
  "type": "Feature",
  "properties": {
    "addr:full":"420 Main St Malden MA 02148",
    "addr:housenumber":"420",
    "addr:postcode":"02148",
    "addr:street":"Main St",
    "iso:country":"US",
    "sg:address":"420 Main St",
    "sg:city":"Malden",
    "sg:classifiers":[
        {
            "category":"Shopping",
            "subcategory":"Mobile Phones",
            "type":"Retail Goods"
        }
    ],
    "sg:phone":"+1 781 397 2200",
    "sg:postcode":"02148",
    "sg:province":"MA",
    "wof:name":"Wireless World",
    "wof:placetype":"venue"
},
  "geometry": {"coordinates":[-71.06735999999999,42.426694],"type":"Point"}
}