{
  "type": "Feature",
  "properties": {
    "addr:full": "375 South St Northampton MA 01060",
    "addr:housenumber": "375",
    "addr:postcode": "01060",
    "addr:street": "South St",
    "iso:country": "US",
    "sg:address": "375 South St",
    "sg:city": "Northampton",
    "sg:classifiers": [
      {
        "category": "Autos \u0026 Motor Vehicles",
        "subcategory": "Automobile Sales",
        "type": "Retail Goods"
      }
    ],
    "sg:phone": "+1 413 584 3792",
    "sg:postcode": "01060",
    "sg:province": "MA",
    "sg:tags": [
      "car",
      "dealer"
    ],
    "sg:website": "www.cahillane.com",
    "wof:name": "Cahillane Dodge",
    "wof:placetype": "venue"
  },
  "geometry": {"coordinates":[-72.645093,42.306698],"type":"Point"}
}
