{
  "type": "Feature",
  "properties": {
    "addr:full": "117 Old Church St Pembroke MA 02359",
    "addr:housenumber": "117",
    "addr:postcode": "02359",
    "addr:street": "Old Church St",
    "iso:country": "US",
    "sg:address": "117 Old Church St",
    "sg:city": "Pembroke",
    "sg:classifiers": [
      {
        "category": "Food \u0026 Beverages",
        "subcategory": "Fruits \u0026 Vegetables",
        "type": "Retail Goods"
      }
    ],
    "sg:phone": "+1 781 826 2436",
    "sg:postcode": "02359",
    "sg:province": "MA",
    "sg:tags": [
      "produce"
    ],
    "wof:name": "Lamberts Rainbow Fruit",
    "wof:placetype": "venue"
  },
  "geometry": {"coordinates":[-70.771729,42.108469],"type":"Point"}
}
