{
  "type": "Feature",
  "properties": {
    "addr:full":"117 Old Church St Pembroke MA 02359",
    "addr:housenumber":"117",
    "addr:postcode":"02359",
    "addr:street":"Old Church St",
    "iso:country":"US",
    "sg:address":"117 Old Church St",
    "sg:city":"Pembroke",
    "sg:classifiers":[
        {
            "category":"Food & Beverages",
            "subcategory":"Fruits & Vegetables",
            "type":"Retail Goods"
        }
    ],
    "sg:phone":"+1 781 826 2436",
    "sg:postcode":"02359",
    "sg:province":"MA",
    "sg:tags":[
        "produce"
    ],
    "wof:name":"Lamberts Rainbow Fruit",
    "wof:placetype":"venue"
},
  "geometry": {"coordinates":[-70.77172899999999,42.108469],"type":"Point"}
}