{
  "type": "Feature",
  "properties": {
    "addr:full":"15 Church St Concord MA 01742",
    "addr:housenumber":"15",
    "addr:postcode":"01742",
    "addr:street":"Church St",
    "iso:country":"US",
    "sg:address":"15 Church St",
    "sg:city":"Concord",
    "sg:classifiers":[
        {
            "category":"Shopping",
            "subcategory":"Clothing, Apparel, & Fashions",
            "type":"Retail Goods"
        }
    ],
    "sg:phone":"+1   ",
    "sg:postcode":"01742",
    "sg:province":"MA",
    "wof:name":"Elios Tailoring",
    "wof:placetype":"venue"
},
  "geometry": {"coordinates":[-71.394949,42.456377],"type":"Point"}
}