{
  "type": "Feature",
  "properties": {
    "iso:country":"US",
    "sg:address":"67 Rocky Pond Rd",
    "sg:city":"Princeton",
    "sg:classifiers":[
        {
            "category":"Professional",
            "subcategory":"Business Services",
            "type":"Services"
        }
    ],
    "sg:phone":"+1 978 479 0654",
    "sg:postcode":"01541",
    "sg:province":"MA",
    "sg:tags":[
        "consultant",
        "coach"
    ],
    "wof:name":"Datalynx Consulting",
    "wof:placetype":"venue"
},
  "geometry": {"coordinates":[-71.85852800000001,42.510208],"type":"Point"}
}