{
  "type": "Feature",
  "properties": {
    "addr:full": "149 Washington St Brighton MA 02135",
    "addr:housenumber": "149",
    "addr:postcode": "02135",
    "addr:street": "Washington St",
    "iso:country": "US",
    "sg:address": "149 Washington St",
    "sg:city": "Brighton",
    "sg:classifiers": [
      {
        "category": "Social Services",
        "subcategory": "Child Care",
        "type": "Services"
      }
    ],
    "sg:phone": "+1 617 357 6000",
    "sg:postcode": "02135",
    "sg:province": "MA",
    "wof:name": "ABCD Inc",
    "wof:placetype": "venue"
  },
  "geometry": {"coordinates":[-71.147422,42.346664],"type":"Point"}
}
