{
  "type": "Feature",
  "properties": {
    "iso:country":"US",
    "sg:address":"520 Pleasant St",
    "sg:city":"Winthrop",
    "sg:classifiers":[
        {
            "category":"Real Estate",
            "subcategory":"Architect",
            "type":"Services"
        }
    ],
    "sg:phone":"+1   ",
    "sg:postcode":"02152",
    "sg:province":"MA",
    "sg:tags":[
        "interior",
        "design",
        "architectural"
    ],
    "wof:name":"M T Design Development",
    "wof:placetype":"venue"
},
  "geometry": {"coordinates":[-70.99196999999999,42.378781],"type":"Point"}
}