{
  "type": "Feature",
  "properties": {
    "addr:full": "296 Canal St Salem MA 01970",
    "addr:housenumber": "296",
    "addr:postcode": "01970",
    "addr:street": "Canal St",
    "iso:country": "US",
    "sg:address": "296 Canal St",
    "sg:city": "Salem",
    "sg:classifiers": [
      {
        "category": "Local Transit",
        "type": "Transportation"
      }
    ],
    "sg:phone": "+1 978 741 2775",
    "sg:postcode": "01970",
    "sg:province": "MA",
    "sg:tags": [
      "ambulance"
    ],
    "wof:name": "Northshore Ambulance Mntnc",
    "wof:placetype": "venue"
  },
  "geometry": {"coordinates":[-70.89606,42.501118],"type":"Point"}
}
