{
  "type": "Feature",
  "properties": {
    "addr:full": "110 Haven St Reading MA 01867",
    "addr:housenumber": "110",
    "addr:postcode": "01867",
    "addr:street": "Haven St",
    "iso:country": "US",
    "sg:address": "110 Haven St",
    "sg:city": "Reading",
    "sg:classifiers": [
      {
        "category": "Organizations",
        "subcategory": "Community Association",
        "type": "Services"
      }
    ],
    "sg:phone": "+1 781 944 9717",
    "sg:postcode": "01867",
    "sg:province": "MA",
    "sg:tags": [
      "fraternal"
    ],
    "wof:name": "Masonic Lodge",
    "wof:placetype": "venue"
  },
  "geometry": {"coordinates":[-71.105339,42.522959],"type":"Point"}
}
