{
  "type": "Feature",
  "properties": {
    "addr:full":"22 Adams Ave Everett MA 02149",
    "addr:housenumber":"22",
    "addr:postcode":"02149",
    "addr:street":"Adams Ave",
    "iso:country":"US",
    "sg:address":"22 Adams Ave",
    "sg:city":"Everett",
    "sg:classifiers":[
        {
            "category":"Building & Trades",
            "subcategory":"Construction",
            "type":"Services"
        }
    ],
    "sg:phone":"+1 617 387 8333",
    "sg:postcode":"02149",
    "sg:province":"MA",
    "sg:tags":[
        "general",
        "contractor"
    ],
    "wof:name":"Four Season's Roofing Corp",
    "wof:placetype":"venue"
},
  "geometry": {"coordinates":[-71.038515,42.415036],"type":"Point"}
}