{
  "type": "Feature",
  "properties": {
    "addr:full": "225 Stoney Point Rd Cummaquid MA 02637",
    "addr:housenumber": "225",
    "addr:postcode": "02637",
    "addr:street": "Stoney Point Rd",
    "iso:country": "US",
    "sg:address": "225 Stoney Point Rd",
    "sg:city": "Cummaquid",
    "sg:classifiers": [
      {
        "category": "Banks \u0026 Credit Unions",
        "subcategory": "Financial Services",
        "type": "Services"
      }
    ],
    "sg:phone": "+1 508 790 1130",
    "sg:postcode": "02637",
    "sg:province": "MA",
    "sg:tags": [
      "broker",
      "mortgage"
    ],
    "wof:name": "Coastal Funding - CLOSED",
    "wof:placetype": "venue"
  },
  "geometry": {"coordinates":[-70.2724,41.702301],"type":"Point"}
}
