{
  "type": "Feature",
  "properties": {
    "addr:full":"1418 Boston Providence Hwy #226 Norwood MA 02062",
    "addr:housenumber":"1418",
    "addr:postcode":"02062",
    "addr:street":"Boston Providence Hwy # 226",
    "iso:country":"US",
    "sg:address":"1418 Boston Providence Hwy #226",
    "sg:city":"Norwood",
    "sg:classifiers":[
        {
            "category":"Health Services",
            "subcategory":"Clinic",
            "type":"Services"
        },
        {
            "category":"Health Services",
            "subcategory":"Health Practitioner",
            "type":"Services"
        }
    ],
    "sg:phone":"+1 617 792 2136",
    "sg:postcode":"02062",
    "sg:province":"MA",
    "sg:tags":[
        "acupuncture",
        "loss",
        "weight"
    ],
    "sg:website":"www.eastwayherbs.com",
    "wof:name":"Eastway Acupuncture & Wellness",
    "wof:placetype":"venue"
},
  "geometry": {"coordinates":[-71.19929999999999,42.16322],"type":"Point"}
}