{
  "type": "Feature",
  "properties": {
    "iso:country":"US",
    "sg:address":"480 Maple St",
    "sg:city":"Danvers",
    "sg:classifiers":[
        {
            "category":"Health Services",
            "subcategory":"Doctor",
            "type":"Services"
        }
    ],
    "sg:phone":"+1 978 741 4133",
    "sg:postcode":"01923",
    "sg:province":"MA",
    "sg:tags":[
        "physician",
        "surgeon"
    ],
    "wof:name":"Pursell Susan E",
    "wof:placetype":"venue"
},
  "geometry": {"coordinates":[-70.970688,42.58569],"type":"Point"}
}