{
  "type": "Feature",
  "properties": {
    "addr:full": "1 1st Ave Waltham MA 02451",
    "addr:housenumber": "1",
    "addr:postcode": "02451",
    "addr:street": "1St Ave",
    "iso:country": "US",
    "sg:address": "1 1st Ave",
    "sg:city": "Waltham",
    "sg:classifiers": [
      {
        "category": "Professional",
        "type": "Services"
      }
    ],
    "sg:phone": "+1 781 891 6622",
    "sg:postcode": "02451",
    "sg:province": "MA",
    "sg:tags": [
      "establishment"
    ],
    "wof:name": "BGS Systems",
    "wof:placetype": "venue"
  },
  "geometry": {"coordinates":[-71.268093,42.3942],"type":"Point"}
}
