{
  "type": "Feature",
  "properties": {
    "iso:country":"US",
    "sg:address":"54 Cummings Park",
    "sg:city":"Woburn",
    "sg:classifiers":[
        {
            "category":"Personal",
            "type":"Services"
        }
    ],
    "sg:phone":"+1 781 932 0292",
    "sg:postcode":"01801",
    "sg:province":"MA",
    "sg:tags":[
        "credit",
        "debt",
        "counseling"
    ],
    "wof:name":"Advantage Independent Credit",
    "wof:placetype":"venue"
},
  "geometry": {"coordinates":[-71.12425,42.497295],"type":"Point"}
}