{
  "type": "Feature",
  "properties": {
    "addr:full": "25 Olympia Ave Woburn MA 01801",
    "addr:housenumber": "25",
    "addr:postcode": "01801",
    "addr:street": "Olympia Ave",
    "iso:country": "US",
    "ovtr:label": "Just Dancin, 25 Olympia Ave Woburn MA US",
    "ovtr:similarity": 2.667807102203369,
    "sg:address": "25 Olympia Ave",
    "sg:city": "Woburn",
    "sg:classifiers": [
      {
        "category": "Arts \u0026 Performance",
        "subcategory": "Arts Center",
        "type": "Entertainment"
      }
    ],
    "sg:phone": "+1 781 935 7886",
    "sg:postcode": "01801",
    "sg:province": "MA",
    "sg:tags": [
      "performing"
    ],
    "wof:name": "Just Dancin",
    "wof:placetype": "venue"
  },
  "geometry": {"coordinates":[-71.129751,42.499848],"type":"Point"}
}
