{
  "type": "Feature",
  "properties": {
    "iso:country":"US",
    "sg:address":"120 Bluff Ave",
    "sg:city":"Swansea",
    "sg:classifiers":[
        {
            "category":"Professional",
            "subcategory":"Management & Consulting",
            "type":"Services"
        }
    ],
    "sg:phone":"+1   ",
    "sg:postcode":"02777",
    "sg:province":"MA",
    "sg:tags":[
        "public",
        "relations"
    ],
    "wof:name":"Casi & Bessette Associates",
    "wof:placetype":"venue"
},
  "geometry": {"coordinates":[-71.212638,41.723603],"type":"Point"}
}