{
  "type": "Feature",
  "properties": {
    "addr:full": "120 Bluff Ave Swansea MA 02777",
    "addr:housenumber": "120",
    "addr:postcode": "02777",
    "addr:street": "Bluff Ave",
    "iso:country": "US",
    "sg:address": "120 Bluff Ave",
    "sg:city": "Swansea",
    "sg:classifiers": [
      {
        "category": "Professional",
        "subcategory": "Management \u0026 Consulting",
        "type": "Services"
      }
    ],
    "sg:phone": "+1   ",
    "sg:postcode": "02777",
    "sg:province": "MA",
    "sg:tags": [
      "public",
      "relations"
    ],
    "wof:name": "Casi \u0026 Bessette Associates",
    "wof:placetype": "venue"
  },
  "geometry": {"coordinates":[-71.212638,41.723603],"type":"Point"}
}
