{
  "type": "Feature",
  "properties": {
    "addr:full":"10 Devon Dr Acton MA 01720",
    "addr:housenumber":"10",
    "addr:postcode":"01720",
    "addr:street":"Devon Dr",
    "iso:country":"US",
    "sg:address":"10 Devon Dr",
    "sg:city":"Acton",
    "sg:classifiers":[
        {
            "category":"Social Services",
            "subcategory":"Retirement Home",
            "type":"Services"
        }
    ],
    "sg:phone":"+1 978 268 0131",
    "sg:postcode":"01720",
    "sg:province":"MA",
    "sg:website":"www.kapdev.com/assisted_living/A...",
    "wof:name":"Inn At Robbins Brook",
    "wof:placetype":"venue"
},
  "geometry": {"coordinates":[-71.403999,42.5214],"type":"Point"}
}