{
  "type": "Feature",
  "properties": {
    "addr:full": "Dorchester Ave and Charles St Boston MA 02122",
    "addr:postcode": "02122",
    "addr:street": "Dorchester Ave And Charles St",
    "iso:country": "US",
    "sg:address": "Dorchester Ave and Charles St",
    "sg:city": "Boston",
    "sg:postcode": "02122",
    "sg:province": "MA",
    "sg:website": "www.mbta.com/schedules_and_maps/...",
    "wof:name": "Fields Corner Station - MBTA - Red Line",
    "wof:placetype": "venue"
  },
  "geometry": {"coordinates":[-71.060015,42.300759],"type":"Point"}
}
