{
  "type": "Feature",
  "properties": {
    "iso:country":"US",
    "sg:address":"34 Saint Martin Dr",
    "sg:city":"Marlborough",
    "sg:classifiers":[
        {
            "category":"Building & Trades",
            "subcategory":"Landscaping Services",
            "type":"Services"
        }
    ],
    "sg:phone":"+1 508 481 5290",
    "sg:postcode":"01752",
    "sg:province":"MA",
    "sg:tags":[
        "lawn",
        "maintenance",
        "grounds"
    ],
    "wof:name":"Seascape Lawn Care",
    "wof:placetype":"venue"
},
  "geometry": {"coordinates":[-71.581356,42.313906],"type":"Point"}
}