{
  "type": "Feature",
  "properties": {
    "iso:country":"US",
    "sg:address":"261 South St",
    "sg:city":"Pittsfield",
    "sg:classifiers":[
        {
            "category":"Health Services",
            "subcategory":"Health Practitioner",
            "type":"Services"
        }
    ],
    "sg:phone":"+1   ",
    "sg:postcode":"01201",
    "sg:province":"MA",
    "wof:name":"Elizabeth Wilen-Berg",
    "wof:placetype":"venue"
},
  "geometry": {"coordinates":[-73.256033,42.441353],"type":"Point"}
}