{
  "type": "Feature",
  "properties": {
    "addr:full":"404 Wyman St. Suite 320 Waltham MA 02451",
    "addr:housenumber":"404",
    "addr:postcode":"02451",
    "addr:street":"Wyman St. Suite 320",
    "iso:country":"US",
    "sg:address":"404 Wyman St. Suite 320",
    "sg:city":"Waltham",
    "sg:classifiers":[
        {
            "category":"Professional",
            "subcategory":"Computer Services",
            "type":"Services"
        }
    ],
    "sg:phone":"+1 781 788 8180",
    "sg:postcode":"02451",
    "sg:province":"MA",
    "sg:website":"http://www.verdasys.com",
    "wof:name":"Verdasys",
    "wof:placetype":"venue"
},
  "geometry": {"coordinates":[-71.255292,42.409776],"type":"Point"}
}