{
  "type": "Feature",
  "properties": {
    "iso:country":"US",
    "sg:address":"253 Mansfield Ave",
    "sg:city":"Norton",
    "sg:classifiers":[
        {
            "category":"Manufacturing",
            "subcategory":"Printing",
            "type":"Manufacturing & Wholesale Goods"
        }
    ],
    "sg:phone":"+1 508 285 0017",
    "sg:postcode":"02766",
    "sg:province":"MA",
    "sg:tags":[
        "screen"
    ],
    "sg:website":"www.espsolutions.com",
    "wof:name":"ESP Solutions Inc",
    "wof:placetype":"venue"
},
  "geometry": {"coordinates":[-71.210488,41.988439],"type":"Point"}
}