{
  "type": "Feature",
  "properties": {
    "iso:country":"US",
    "sg:address":"1 Liberty Sq Ste 2",
    "sg:city":"Boston",
    "sg:classifiers":[
        {
            "category":"Wholesale",
            "subcategory":"Machinery & Supplies",
            "type":"Manufacturing & Wholesale Goods"
        }
    ],
    "sg:phone":"+1 617 451 2326",
    "sg:postcode":"02109",
    "sg:province":"MA",
    "sg:tags":[
        "equipment",
        "industrial"
    ],
    "wof:name":"Liberty Central Industrial Par",
    "wof:placetype":"venue"
},
  "geometry": {"coordinates":[-71.05464600000001,42.357485],"type":"Point"}
}