{
  "type": "Feature",
  "properties": {
    "addr:full": "1 Liberty Sq Ste 2 Boston MA 02109",
    "addr:housenumber": "1",
    "addr:postcode": "02109",
    "addr:street": "Liberty Sq Ste 2",
    "iso:country": "US",
    "sg:address": "1 Liberty Sq Ste 2",
    "sg:city": "Boston",
    "sg:classifiers": [
      {
        "category": "Wholesale",
        "subcategory": "Machinery \u0026 Supplies",
        "type": "Manufacturing \u0026 Wholesale Goods"
      }
    ],
    "sg:phone": "+1 617 451 2326",
    "sg:postcode": "02109",
    "sg:province": "MA",
    "sg:tags": [
      "equipment",
      "industrial"
    ],
    "wof:name": "Liberty Central Industrial Par",
    "wof:placetype": "venue"
  },
  "geometry": {"coordinates":[-71.054646,42.357485],"type":"Point"}
}
