{
  "type": "Feature",
  "properties": {
    "addr:full":"186 Hampshire St Cambridge MA 02139",
    "addr:housenumber":"186",
    "addr:postcode":"02139",
    "addr:street":"Hampshire St",
    "iso:country":"US",
    "sg:address":"186 Hampshire St",
    "sg:city":"Cambridge",
    "sg:classifiers":[
        {
            "category":"Sports & Exercise",
            "subcategory":"Gym",
            "type":"Entertainment"
        }
    ],
    "sg:phone":"+1 617 497 4244",
    "sg:postcode":"02139",
    "sg:province":"MA",
    "sg:tags":[
        "yoga"
    ],
    "sg:website":"www.ashtangayogaboston.com/",
    "wof:name":"Ashtanga Yoga Boston",
    "wof:placetype":"venue"
},
  "geometry": {"coordinates":[-71.0996,42.3724],"type":"Point"}
}