{
  "type": "Feature",
  "properties": {
    "addr:full":"57 Corbett St Lowell MA 01852",
    "addr:housenumber":"57",
    "addr:postcode":"01852",
    "addr:street":"Corbett St",
    "iso:country":"US",
    "sg:address":"57 Corbett St",
    "sg:city":"Lowell",
    "sg:classifiers":[
        {
            "category":"Building & Trades",
            "subcategory":"Plumbing",
            "type":"Services"
        }
    ],
    "sg:phone":"+1 978 458 0217",
    "sg:postcode":"01852",
    "sg:province":"MA",
    "sg:tags":[
        "repair",
        "contractor"
    ],
    "wof:name":"M-R-S Rooter",
    "wof:placetype":"venue"
},
  "geometry": {"coordinates":[-71.303189,42.620327],"type":"Point"}
}