{
  "type": "Feature",
  "properties": {
    "addr:full":"7 Hammond Rd Natick MA 01760",
    "addr:housenumber":"7",
    "addr:postcode":"01760",
    "addr:street":"Hammond Rd",
    "iso:country":"US",
    "sg:address":"7 Hammond Rd",
    "sg:city":"Natick",
    "sg:classifiers":[
        {
            "category":"Retail",
            "subcategory":"Auto Repair",
            "type":"Services"
        }
    ],
    "sg:phone":"+1 508 653 1588",
    "sg:postcode":"01760",
    "sg:province":"MA",
    "wof:name":"Downing's Garage",
    "wof:placetype":"venue"
},
  "geometry": {"coordinates":[-71.362253,42.314467],"type":"Point"}
}