{
  "type": "Feature",
  "properties": {
    "addr:full": "1256 John Fitch Hwy Fitchburg MA 01420",
    "addr:housenumber": "1256",
    "addr:postcode": "01420",
    "addr:street": "John Fitch Hwy",
    "iso:country": "US",
    "sg:address": "1256 John Fitch Hwy",
    "sg:city": "Fitchburg",
    "sg:classifiers": [
      {
        "category": "Home \u0026 Garden",
        "subcategory": "Building Materials",
        "type": "Retail Goods"
      },
      {
        "category": "Building \u0026 Trades",
        "subcategory": "Construction",
        "type": "Services"
      }
    ],
    "sg:phone": "+1 978 343 2818",
    "sg:postcode": "01420",
    "sg:province": "MA",
    "sg:tags": [
      "concrete",
      "staining",
      "contractor"
    ],
    "wof:name": "Pittman Concrete Finishers",
    "wof:placetype": "venue"
  },
  "geometry": {"coordinates":[-71.795631,42.599708],"type":"Point"}
}
