{
  "type": "Feature",
  "properties": {
    "addr:full": "74 Willowdale Rd Groton MA 01450",
    "addr:housenumber": "74",
    "addr:postcode": "01450",
    "addr:street": "Willowdale Rd",
    "iso:country": "US",
    "sg:address": "74 Willowdale Rd",
    "sg:city": "Groton",
    "sg:classifiers": [
      {
        "category": "Real Estate",
        "subcategory": "Real Estate Operator",
        "type": "Services"
      }
    ],
    "sg:phone": "+1 978 448 9551",
    "sg:postcode": "01450",
    "sg:province": "MA",
    "sg:tags": [
      "apartment"
    ],
    "wof:name": "Groton Commons",
    "wof:placetype": "venue"
  },
  "geometry": {"coordinates":[-71.571441,42.611365],"type":"Point"}
}
