{
  "type": "Feature",
  "properties": {
    "iso:country":"US",
    "sg:address":"479 S Broadway",
    "sg:city":"Lawrence",
    "sg:classifiers":[
        {
            "category":"Real Estate",
            "subcategory":"Real Estate Operator",
            "type":"Services"
        }
    ],
    "sg:phone":"+1 978 470 8282",
    "sg:postcode":"01843",
    "sg:province":"MA",
    "sg:tags":[
        "apartment"
    ],
    "wof:name":"Princeton At Mount Vernon",
    "wof:placetype":"venue"
},
  "geometry": {"coordinates":[-71.154833,42.683782],"type":"Point"}
}