{
  "type": "Feature",
  "properties": {
    "addr:full":"54 Queensberry St Boston MA 02115",
    "addr:housenumber":"54",
    "addr:postcode":"02115",
    "addr:street":"Queensberry St",
    "iso:country":"US",
    "sg:address":"54 Queensberry St",
    "sg:city":"Boston",
    "sg:classifiers":[
        {
            "category":"Personal",
            "subcategory":"Beauty Salon",
            "type":"Services"
        }
    ],
    "sg:phone":"+1 617 267 5454",
    "sg:postcode":"02115",
    "sg:province":"MA",
    "sg:tags":[
        "hair"
    ],
    "sg:website":"www.bostonsalon54.com",
    "wof:name":"Salon 54",
    "wof:placetype":"venue"
},
  "geometry": {"coordinates":[-71.097511,42.342727],"type":"Point"}
}