{
  "type": "Feature",
  "properties": {
    "addr:full": "1237 Commonwealth Ave Allston MA 02134",
    "addr:housenumber": "1237",
    "addr:postcode": "02134",
    "addr:street": "Commonwealth Ave",
    "iso:country": "US",
    "sg:address": "1237 Commonwealth Ave",
    "sg:city": "Allston",
    "sg:classifiers": [
      {
        "category": "Banks \u0026 Credit Unions",
        "subcategory": "Bank",
        "type": "Services"
      }
    ],
    "sg:phone": "+1 800 432 1000",
    "sg:postcode": "02134",
    "sg:province": "MA",
    "wof:name": "Bank of America",
    "wof:placetype": "venue"
  },
  "geometry": {"coordinates":[-71.131443,42.350322],"type":"Point"}
}
