{
  "type": "Feature",
  "properties": {
    "iso:country":"US",
    "sg:address":"835 Springfield St",
    "sg:city":"Feeding Hills",
    "sg:classifiers":[
        {
            "category":"Personal",
            "subcategory":"Beauty Salon",
            "type":"Services"
        }
    ],
    "sg:phone":"+1 413 786 8206",
    "sg:postcode":"01030",
    "sg:province":"MA",
    "wof:name":"Ellen's Place",
    "wof:placetype":"venue"
},
  "geometry": {"coordinates":[-72.65653399999999,42.074861],"type":"Point"}
}