{
  "type": "Feature",
  "properties": {
    "addr:full":"15 Midstate Dr Auburn MA 01501",
    "addr:housenumber":"15",
    "addr:postcode":"01501",
    "addr:street":"Midstate Dr",
    "iso:country":"US",
    "sg:address":"15 Midstate Dr",
    "sg:city":"Auburn",
    "sg:classifiers":[
        {
            "category":"Professional",
            "subcategory":"Credit Reporting & Collection",
            "type":"Services"
        }
    ],
    "sg:phone":"+1 508 721 7997",
    "sg:postcode":"01501",
    "sg:province":"MA",
    "sg:tags":[
        "agency"
    ],
    "wof:name":"Transworld Systems",
    "wof:placetype":"venue"
},
  "geometry": {"coordinates":[-71.855474,42.190112],"type":"Point"}
}