{
  "type": "Feature",
  "properties": {
    "addr:full":"84 Tosca Dr Stoughton MA 02072",
    "addr:housenumber":"84",
    "addr:postcode":"02072",
    "addr:street":"Tosca Dr",
    "iso:country":"US",
    "sg:address":"84 Tosca Dr",
    "sg:city":"Stoughton",
    "sg:classifiers":[
        {
            "category":"Wholesale",
            "subcategory":"Sporting Goods",
            "type":"Manufacturing & Wholesale Goods"
        }
    ],
    "sg:phone":"+1 781 297 7422",
    "sg:postcode":"02072",
    "sg:province":"MA",
    "sg:tags":[
        "pool",
        "swimming"
    ],
    "sg:website":"www.robelleind.com",
    "wof:name":"Robelle Industries",
    "wof:placetype":"venue"
},
  "geometry": {"coordinates":[-71.125134,42.134336],"type":"Point"}
}