{
  "type": "Feature",
  "properties": {
    "addr:full": "141 Memorial Pkwy Randolph MA 02368",
    "addr:housenumber": "141",
    "addr:postcode": "02368",
    "addr:street": "Memorial Pkwy",
    "iso:country": "US",
    "sg:address": "141 Memorial Pkwy",
    "sg:city": "Randolph",
    "sg:classifiers": [
      {
        "category": "Professional",
        "subcategory": "Computer Services",
        "type": "Services"
      }
    ],
    "sg:phone": "+1   ",
    "sg:postcode": "02368",
    "sg:province": "MA",
    "sg:tags": [
      "related"
    ],
    "wof:name": "Michael R Morrill",
    "wof:placetype": "venue"
  },
  "geometry": {"coordinates":[-71.045661,42.162885],"type":"Point"}
}
