{
  "type": "Feature",
  "properties": {
    "iso:country":"US",
    "sg:address":"10 Derne St",
    "sg:city":"Boston",
    "sg:classifiers":[
        {
            "category":"Organizations",
            "subcategory":"Community Association",
            "type":"Services"
        }
    ],
    "sg:phone":"+1 617 227 4392",
    "sg:postcode":"02114",
    "sg:province":"MA",
    "sg:tags":[
        "club"
    ],
    "wof:name":"Beacon Hill Garden Club Inc",
    "wof:placetype":"venue"
},
  "geometry": {"coordinates":[-71.063256,42.359423],"type":"Point"}
}