{
  "type": "Feature",
  "properties": {
    "addr:full":"2 Appleton Street Cambridge MA 02138",
    "addr:housenumber":"2",
    "addr:postcode":"02138",
    "addr:street":"Appleton Street",
    "iso:country":"US",
    "sg:address":"2 Appleton Street",
    "sg:city":"Cambridge",
    "sg:classifiers":[
        {
            "category":"Health Services",
            "subcategory":"Doctor",
            "type":"Services"
        },
        {
            "category":"Sports & Exercise",
            "subcategory":"Gym",
            "type":"Entertainment"
        }
    ],
    "sg:phone":"+1 617 547 5988",
    "sg:postcode":"02138",
    "sg:province":"MA",
    "sg:tags":[
        "trainer"
    ],
    "wof:name":"Chasin Laura Socl Workr",
    "wof:placetype":"venue"
},
  "geometry": {"coordinates":[-71.133263,42.377557],"type":"Point"}
}