{
  "type": "Feature",
  "properties": {
    "iso:country":"US",
    "sg:address":"75 Finnell Dr",
    "sg:city":"Weymouth",
    "sg:classifiers":[
        {
            "category":"Health Services",
            "subcategory":"Health Practitioner",
            "type":"Services"
        }
    ],
    "sg:phone":"+1 781 335 1151",
    "sg:postcode":"02188",
    "sg:province":"MA",
    "sg:tags":[
        "therapist",
        "physical"
    ],
    "wof:name":"Baystate Physical Therapy",
    "wof:placetype":"venue"
},
  "geometry": {"coordinates":[-70.96780200000001,42.18956],"type":"Point"}
}