{
  "type": "Feature",
  "properties": {
    "addr:full": "10 Mcdonald Ave Granby MA 01033",
    "addr:housenumber": "10",
    "addr:postcode": "01033",
    "addr:street": "Mcdonald Ave",
    "iso:country": "US",
    "sg:address": "10 Mcdonald Ave",
    "sg:city": "Granby",
    "sg:classifiers": [
      {
        "category": "Home \u0026 Garden",
        "subcategory": "Home Furnishings",
        "type": "Retail Goods"
      },
      {
        "category": "Home \u0026 Garden",
        "subcategory": "Furniture",
        "type": "Retail Goods"
      },
      {
        "category": "Building \u0026 Trades",
        "subcategory": "Construction",
        "type": "Services"
      },
      {
        "category": "Manufacturing",
        "subcategory": "Building Materials",
        "type": "Manufacturing \u0026 Wholesale Goods"
      },
      {
        "category": "Wholesale",
        "subcategory": "Home Furnishings",
        "type": "Manufacturing \u0026 Wholesale Goods"
      }
    ],
    "sg:phone": "+1 413 467 7789",
    "sg:postcode": "01033",
    "sg:province": "MA",
    "sg:tags": [
      "manufacturer",
      "industrial",
      "equipment-wholesale",
      "cabinetmakers-commercial",
      "cabinet",
      "refacing",
      "resurfacing",
      "equipment-household",
      "maker",
      "cabinets-refinishing",
      "kitchen"
    ],
    "wof:name": "Fabricius Specialties",
    "wof:placetype": "venue"
  },
  "geometry": {"coordinates":[-72.484299,42.282938],"type":"Point"}
}
