{
  "type": "Feature",
  "properties": {
    "iso:country":"US",
    "sg:address":"10 Mcdonald Ave",
    "sg:city":"Granby",
    "sg:classifiers":[
        {
            "category":"Home & Garden",
            "subcategory":"Home Furnishings",
            "type":"Retail Goods"
        },
        {
            "category":"Home & Garden",
            "subcategory":"Furniture",
            "type":"Retail Goods"
        },
        {
            "category":"Building & Trades",
            "subcategory":"Construction",
            "type":"Services"
        },
        {
            "category":"Manufacturing",
            "subcategory":"Building Materials",
            "type":"Manufacturing & Wholesale Goods"
        },
        {
            "category":"Wholesale",
            "subcategory":"Home Furnishings",
            "type":"Manufacturing & Wholesale Goods"
        }
    ],
    "sg:phone":"+1 413 467 7789",
    "sg:postcode":"01033",
    "sg:province":"MA",
    "sg:tags":[
        "manufacturer",
        "industrial",
        "equipment-wholesale",
        "cabinetmakers-commercial",
        "cabinet",
        "refacing",
        "resurfacing",
        "equipment-household",
        "maker",
        "cabinets-refinishing",
        "kitchen"
    ],
    "wof:name":"Fabricius Specialties",
    "wof:placetype":"venue"
},
  "geometry": {"coordinates":[-72.48429899999999,42.282938],"type":"Point"}
}