{
  "type": "Feature",
  "properties": {
    "iso:country":"US",
    "sg:address":"15 Cambridge St",
    "sg:city":"Burlington",
    "sg:classifiers":[
        {
            "category":"Home & Garden",
            "subcategory":"Furniture",
            "type":"Retail Goods"
        }
    ],
    "sg:phone":"+1 781 272 7470",
    "sg:postcode":"01803",
    "sg:province":"MA",
    "sg:tags":[
        "store"
    ],
    "wof:name":"Jennifer Convertibles Leather",
    "wof:placetype":"venue"
},
  "geometry": {"coordinates":[-71.187698,42.482101],"type":"Point"}
}