{
  "type": "Feature",
  "properties": {
    "addr:full": "1180 Beacon St Ste 4A Brookline MA 02446",
    "addr:housenumber": "1180",
    "addr:postcode": "02446",
    "addr:street": "Beacon St Ste 4A",
    "iso:country": "US",
    "sg:address": "1180 Beacon St Ste 4A",
    "sg:city": "Brookline",
    "sg:classifiers": [
      {
        "category": "Health Services",
        "subcategory": "Doctor",
        "type": "Services"
      }
    ],
    "sg:phone": "+1 617 232 2915",
    "sg:postcode": "02446",
    "sg:province": "MA",
    "sg:tags": [
      "physician",
      "family",
      "practice",
      "surgeons",
      "medicine",
      "surgeon"
    ],
    "wof:name": "M L Reiner Md",
    "wof:placetype": "venue"
  },
  "geometry": {"coordinates":[-71.114403,42.344151],"type":"Point"}
}
