{
  "type": "Feature",
  "properties": {
    "addr:full":"11 S Main St Ipswich MA 01938",
    "addr:housenumber":"11",
    "addr:postcode":"01938",
    "addr:street":"S Main St",
    "iso:country":"US",
    "sg:address":"11 S Main St",
    "sg:city":"Ipswich",
    "sg:classifiers":[
        {
            "category":"Professional",
            "subcategory":"Computer Services",
            "type":"Services"
        }
    ],
    "sg:phone":"+1 978 356 2488",
    "sg:postcode":"01938",
    "sg:province":"MA",
    "sg:tags":[
        "related"
    ],
    "wof:name":"Odd Job Computing",
    "wof:placetype":"venue"
},
  "geometry": {"coordinates":[-70.837301,42.679714],"type":"Point"}
}