{
  "type": "Feature",
  "properties": {
    "addr:full": "3 Durso Ave Lawrence MA 01843",
    "addr:housenumber": "3",
    "addr:postcode": "01843",
    "addr:street": "Durso Ave",
    "iso:country": "US",
    "sg:address": "3 Durso Ave",
    "sg:city": "Lawrence",
    "sg:classifiers": [
      {
        "category": "Health Services",
        "subcategory": "Podiatrist",
        "type": "Services"
      }
    ],
    "sg:phone": "+1 978 683 8132",
    "sg:postcode": "01843",
    "sg:province": "MA",
    "wof:name": "Florence J Hood DPM",
    "wof:placetype": "venue"
  },
  "geometry": {"coordinates":[-71.149948,42.68866],"type":"Point"}
}
