{
  "type": "Feature",
  "properties": {
    "iso:country":"US",
    "sg:address":"71 Menlo Ave",
    "sg:city":"Lynn",
    "sg:classifiers":[
        {
            "category":"Home & Garden",
            "subcategory":"Hardware",
            "type":"Retail Goods"
        }
    ],
    "sg:phone":"+1   ",
    "sg:postcode":"01905",
    "sg:province":"MA",
    "wof:name":"Contractors Choice",
    "wof:placetype":"venue"
},
  "geometry": {"coordinates":[-70.983902,42.475745],"type":"Point"}
}