{
  "type": "Feature",
  "properties": {
    "addr:full":"35 Bedford Street Lexington MA 02420",
    "addr:housenumber":"35",
    "addr:postcode":"02420",
    "addr:street":"Bedford Street",
    "iso:country":"US",
    "sg:address":"35 Bedford Street",
    "sg:city":"Lexington",
    "sg:classifiers":[
        {
            "category":"Health Services",
            "subcategory":"Dentist",
            "type":"Services"
        }
    ],
    "sg:phone":"+1 781 863 0096",
    "sg:postcode":"02420",
    "sg:province":"MA",
    "wof:name":"Cunha & Ibrahim DDS PC",
    "wof:placetype":"venue"
},
  "geometry": {"coordinates":[-71.231927,42.452235],"type":"Point"}
}