{
  "type": "Feature",
  "properties": {
    "addr:full":"9 Herring Pond Rd Plymouth MA 02360",
    "addr:housenumber":"9",
    "addr:postcode":"02360",
    "addr:street":"Herring Pond Rd",
    "iso:country":"US",
    "sg:address":"9 Herring Pond Rd",
    "sg:city":"Plymouth",
    "sg:classifiers":[
        {
            "category":"Building & Trades",
            "subcategory":"Plumbing",
            "type":"Services"
        }
    ],
    "sg:phone":"+1 508 833 2959",
    "sg:postcode":"02360",
    "sg:province":"MA",
    "sg:website":"www.maybruckplumbing.com",
    "wof:name":"Dan Maybruck Plumbing & Heating, Inc.",
    "wof:placetype":"venue"
},
  "geometry": {"coordinates":[-70.553155,41.814843],"type":"Point"}
}