{
  "type": "Feature",
  "properties": {
    "addr:full": "21 Cottage St Everett MA 02149",
    "addr:housenumber": "21",
    "addr:postcode": "02149",
    "addr:street": "Cottage St",
    "iso:country": "US",
    "sg:address": "21 Cottage St",
    "sg:city": "Everett",
    "sg:classifiers": [
      {
        "category": "Social Services",
        "type": "Services"
      }
    ],
    "sg:phone": "+1 617 387 3300",
    "sg:postcode": "02149",
    "sg:province": "MA",
    "sg:tags": [
      "youth",
      "organization",
      "center"
    ],
    "wof:name": "Igreja Adventista Do Se'Timo",
    "wof:placetype": "venue"
  },
  "geometry": {"coordinates":[-71.054997,42.407356],"type":"Point"}
}
