{
  "type": "Feature",
  "properties": {
    "addr:full":"37 Midland St Worcester MA 01602",
    "addr:housenumber":"37",
    "addr:postcode":"01602",
    "addr:street":"Midland St",
    "iso:country":"US",
    "sg:address":"37 Midland St",
    "sg:city":"Worcester",
    "sg:classifiers":[
        {
            "category":"Shopping",
            "subcategory":"Used Merchandise",
            "type":"Retail Goods"
        }
    ],
    "sg:phone":"+1   ",
    "sg:postcode":"01602",
    "sg:province":"MA",
    "wof:name":"Rss Antiques",
    "wof:placetype":"venue"
},
  "geometry": {"coordinates":[-71.826741,42.271335],"type":"Point"}
}