{
  "type": "Feature",
  "properties": {
    "addr:full":"457 Chelmsford St Lowell MA 01851",
    "addr:housenumber":"457",
    "addr:postcode":"01851",
    "addr:street":"Chelmsford St",
    "iso:country":"US",
    "sg:address":"457 Chelmsford St",
    "sg:city":"Lowell",
    "sg:classifiers":[
        {
            "category":"Restaurant",
            "type":"Food & Drink"
        }
    ],
    "sg:phone":"+1 978 934 9077",
    "sg:postcode":"01851",
    "sg:province":"MA",
    "wof:name":"Wah Sang Chinese Restaurant",
    "wof:placetype":"venue"
},
  "geometry": {"coordinates":[-71.323037,42.626234],"type":"Point"}
}