{
  "type": "Feature",
  "properties": {
    "iso:country":"US",
    "sg:address":"1485 Washington St",
    "sg:city":"Holliston",
    "sg:classifiers":[
        {
            "category":"Retail",
            "subcategory":"Auto Repair",
            "type":"Services"
        }
    ],
    "sg:phone":"+1 508 429 0050",
    "sg:postcode":"01746",
    "sg:province":"MA",
    "sg:tags":[
        "machine",
        "automobile",
        "shop"
    ],
    "wof:name":"Map Machine Co Inc",
    "wof:placetype":"venue"
},
  "geometry": {"coordinates":[-71.446462,42.181787],"type":"Point"}
}