{
  "type": "Feature",
  "properties": {
    "iso:country":"US",
    "sg:address":"540 W Boylston St",
    "sg:city":"Worcester",
    "sg:classifiers":[
        {
            "category":"Shopping",
            "subcategory":"Clothing, Apparel, & Fashions",
            "type":"Retail Goods"
        }
    ],
    "sg:phone":"+1 508 852 4500",
    "sg:postcode":"01606",
    "sg:province":"MA",
    "sg:tags":[
        "theatrical",
        "costume"
    ],
    "sg:website":"www.halween.com",
    "wof:name":"Halloween Outlet",
    "wof:placetype":"venue"
},
  "geometry": {"coordinates":[-71.798247,42.310003],"type":"Point"}
}