{
  "type": "Feature",
  "properties": {
    "addr:full":"2400 Boston Rd Wilbraham MA 01095",
    "addr:housenumber":"2400",
    "addr:postcode":"01095",
    "addr:street":"Boston Rd",
    "iso:country":"US",
    "sg:address":"2400 Boston Rd",
    "sg:city":"Wilbraham",
    "sg:classifiers":[
        {
            "category":"Wholesale",
            "subcategory":"Electrical",
            "type":"Manufacturing & Wholesale Goods"
        }
    ],
    "sg:phone":"+1 413 596 2406",
    "sg:postcode":"01095",
    "sg:province":"MA",
    "sg:tags":[
        "fire",
        "alarm",
        "system"
    ],
    "wof:name":"Wel-Design Alarm System Inc",
    "wof:placetype":"venue"
},
  "geometry": {"coordinates":[-72.44745500000001,42.149246],"type":"Point"}
}