{
  "type": "Feature",
  "properties": {
    "iso:country":"US",
    "sg:address":"411 Adams St",
    "sg:city":"Dorchester",
    "sg:classifiers":[
        {
            "category":"Travel",
            "subcategory":"Travel Agent",
            "type":"Entertainment"
        }
    ],
    "sg:phone":"+1 617 265 6033",
    "sg:postcode":"02122",
    "sg:province":"MA",
    "sg:tags":[
        "agency",
        "services-commercial"
    ],
    "wof:name":"Dv Travel And Printing",
    "wof:placetype":"venue"
},
  "geometry": {"coordinates":[-71.05622099999999,42.295158],"type":"Point"}
}