{
  "type": "Feature",
  "properties": {
    "addr:full":"68 Harvard St Brookline MA 02445",
    "addr:housenumber":"68",
    "addr:postcode":"02445",
    "addr:street":"Harvard St",
    "iso:country":"US",
    "sg:address":"68 Harvard St",
    "sg:city":"Brookline",
    "sg:classifiers":[
        {
            "category":"Sports & Exercise",
            "subcategory":"Gym",
            "type":"Entertainment"
        }
    ],
    "sg:phone":"+1 617 515 9784",
    "sg:postcode":"02445",
    "sg:province":"MA",
    "sg:tags":[
        "trainer"
    ],
    "sg:website":"www.jonashealth.com",
    "wof:name":"Jonas Health",
    "wof:placetype":"venue"
},
  "geometry": {"coordinates":[-71.11993699999999,42.335383],"type":"Point"}
}