{
  "type": "Feature",
  "properties": {
    "addr:full": "22 Batterymarch St Boston MA 02109",
    "addr:housenumber": "22",
    "addr:postcode": "02109",
    "addr:street": "Batterymarch St",
    "iso:country": "US",
    "sg:address": "22 Batterymarch St",
    "sg:city": "Boston",
    "sg:classifiers": [
      {
        "category": "Organizations",
        "subcategory": "Community Association",
        "type": "Services"
      }
    ],
    "sg:phone": "+1 617 338 6379",
    "sg:postcode": "02109",
    "sg:province": "MA",
    "wof:name": "Lorenz \u0026 Laura Family Foundati",
    "wof:placetype": "venue"
  },
  "geometry": {"coordinates":[-71.05439,42.357658],"type":"Point"}
}
