{
  "type": "Feature",
  "properties": {
    "addr:full":"328 Mason Ter Brookline MA 02446",
    "addr:housenumber":"328",
    "addr:postcode":"02446",
    "addr:street":"Mason Ter",
    "iso:country":"US",
    "sg:address":"328 Mason Ter",
    "sg:city":"Brookline",
    "sg:classifiers":[
        {
            "category":"Health Services",
            "subcategory":"Doctor",
            "type":"Services"
        }
    ],
    "sg:phone":"+1 617 558 1278",
    "sg:postcode":"02446",
    "sg:province":"MA",
    "sg:tags":[
        "physician",
        "surgeon"
    ],
    "wof:name":"Bennett S Gurian MD",
    "wof:placetype":"venue"
},
  "geometry": {"coordinates":[-71.134281,42.344581],"type":"Point"}
}