{
  "type": "Feature",
  "properties": {
    "addr:full":"388 County St New Bedford MA 02740",
    "addr:housenumber":"388",
    "addr:postcode":"02740",
    "addr:street":"County St",
    "iso:country":"US",
    "sg:address":"388 County St",
    "sg:city":"New Bedford",
    "sg:classifiers":[
        {
            "category":"Professional",
            "subcategory":"Lawyer & Legal Services",
            "type":"Services"
        }
    ],
    "sg:phone":"+1 508 996 8291",
    "sg:postcode":"02740",
    "sg:province":"MA",
    "sg:tags":[
        "attorney"
    ],
    "sg:website":"www.perryhicks.net",
    "wof:name":"Perry Hicks Crotty & Deshaies",
    "wof:placetype":"venue"
},
  "geometry": {"coordinates":[-70.92861499999999,41.6298],"type":"Point"}
}