{
  "type": "Feature",
  "properties": {
    "iso:country":"US",
    "sg:address":"311 Elm St",
    "sg:city":"West Springfield",
    "sg:classifiers":[
        {
            "category":"Personal",
            "subcategory":"Tanning Parlor",
            "type":"Services"
        }
    ],
    "sg:phone":"+1 413 781 2550",
    "sg:postcode":"01089",
    "sg:province":"MA",
    "sg:tags":[
        "salon"
    ],
    "wof:name":"Cool Runnings Tanning Salon",
    "wof:placetype":"venue"
},
  "geometry": {"coordinates":[-72.62392,42.10867],"type":"Point"}
}