{
  "type": "Feature",
  "properties": {
    "addr:full": "172 South St Jamaica Plain MA 02130",
    "addr:housenumber": "172",
    "addr:postcode": "02130",
    "addr:street": "South St",
    "iso:country": "US",
    "sg:address": "172 South St",
    "sg:city": "Jamaica Plain",
    "sg:classifiers": [
      {
        "category": "Restaurant",
        "type": "Food \u0026 Drink"
      }
    ],
    "sg:phone": "+1 617 477 8303",
    "sg:postcode": "02130",
    "sg:province": "MA",
    "sg:tags": [
      "pizza"
    ],
    "sg:website": "www.primopizzajp.com",
    "wof:name": "Primo Brothers Pizza",
    "wof:placetype": "venue"
  },
  "geometry": {"coordinates":[-71.114505,42.304046],"type":"Point"}
}
