{
  "type": "Feature",
  "properties": {
    "iso:country":"US",
    "sg:address":"172 South St",
    "sg:city":"Jamaica Plain",
    "sg:classifiers":[
        {
            "category":"Restaurant",
            "type":"Food & Drink"
        }
    ],
    "sg:phone":"+1 617 477 8303",
    "sg:postcode":"02130",
    "sg:province":"MA",
    "sg:tags":[
        "pizza"
    ],
    "sg:website":"www.primopizzajp.com",
    "wof:name":"Primo Brothers Pizza",
    "wof:placetype":"venue"
},
  "geometry": {"coordinates":[-71.11450499999999,42.304046],"type":"Point"}
}