{
  "type": "Feature",
  "properties": {
    "addr:full": "1200 Soldiers Field Rd Allston MA 02134",
    "addr:housenumber": "1200",
    "addr:postcode": "02134",
    "addr:street": "Soldiers Field Rd",
    "iso:country": "US",
    "sg:address": "1200 Soldiers Field Rd",
    "sg:city": "Allston",
    "sg:classifiers": [
      {
        "category": "Professional",
        "subcategory": "Management \u0026 Consulting",
        "type": "Services"
      }
    ],
    "sg:phone": "+1 617 254 4100",
    "sg:postcode": "02134",
    "sg:province": "MA",
    "sg:tags": [
      "marketing",
      "program"
    ],
    "sg:website": "www.eidetics.com",
    "wof:name": "Eidetics",
    "wof:placetype": "venue"
  },
  "geometry": {"coordinates":[-71.134435,42.365137],"type":"Point"}
}
