{
  "type": "Feature",
  "properties": {
    "iso:country":"US",
    "sg:address":"1200 Soldiers Field Rd",
    "sg:city":"Allston",
    "sg:classifiers":[
        {
            "category":"Professional",
            "subcategory":"Management & Consulting",
            "type":"Services"
        }
    ],
    "sg:phone":"+1 617 254 4100",
    "sg:postcode":"02134",
    "sg:province":"MA",
    "sg:tags":[
        "marketing",
        "program"
    ],
    "sg:website":"www.eidetics.com",
    "wof:name":"Eidetics",
    "wof:placetype":"venue"
},
  "geometry": {"coordinates":[-71.134435,42.365137],"type":"Point"}
}