{
  "type": "Feature",
  "properties": {
    "iso:country":"US",
    "sg:address":"1141 Beacon St",
    "sg:city":"Brookline",
    "sg:classifiers":[
        {
            "category":"Recreation",
            "type":"Entertainment"
        }
    ],
    "sg:phone":"+1   ",
    "sg:postcode":"02446",
    "sg:province":"MA",
    "wof:name":"Coffey Ali",
    "wof:placetype":"venue"
},
  "geometry": {"coordinates":[-71.11262000000001,42.34433],"type":"Point"}
}