{
  "type": "Feature",
  "properties": {
    "addr:full": "125 Cambridgepark Dr Cambridge MA 02140",
    "addr:housenumber": "125",
    "addr:postcode": "02140",
    "addr:street": "Cambridgepark Dr",
    "iso:country": "US",
    "sg:address": "125 Cambridgepark Dr",
    "sg:city": "Cambridge",
    "sg:classifiers": [
      {
        "category": "Professional",
        "subcategory": "Employment Agencies",
        "type": "Services"
      }
    ],
    "sg:phone": "+1 617 864 3808",
    "sg:postcode": "02140",
    "sg:province": "MA",
    "wof:name": "Employment Resources",
    "wof:placetype": "venue"
  },
  "geometry": {"coordinates":[-71.145401,42.394699],"type":"Point"}
}
