{
  "type": "Feature",
  "properties": {
    "iso:country":"US",
    "sg:address":"125 Summer St",
    "sg:city":"Boston",
    "sg:classifiers":[
        {
            "category":"Shopping",
            "subcategory":"Optical Goods",
            "type":"Retail Goods"
        }
    ],
    "sg:phone":"+1 617 261 1813",
    "sg:postcode":"02110",
    "sg:province":"MA",
    "sg:tags":[
        "optician",
        "eyewear"
    ],
    "wof:name":"For Eyes Optical",
    "wof:placetype":"venue"
},
  "geometry": {"coordinates":[-71.057439,42.353348],"type":"Point"}
}