{
  "type": "Feature",
  "properties": {
    "iso:country":"US",
    "sg:address":"225 Cranberry Hwy",
    "sg:city":"Orleans",
    "sg:classifiers":[
        {
            "category":"Personal",
            "subcategory":"Beauty Salon",
            "type":"Services"
        }
    ],
    "sg:phone":"+1 508 240 1016",
    "sg:postcode":"02653",
    "sg:province":"MA",
    "wof:name":"New York Hair Co",
    "wof:placetype":"venue"
},
  "geometry": {"coordinates":[-70.001695,41.779043],"type":"Point"}
}