{
  "type": "Feature",
  "properties": {
    "iso:country":"US",
    "sg:address":"17 Lord St",
    "sg:city":"Waltham",
    "sg:classifiers":[
        {
            "category":"Local Transit",
            "type":"Transportation"
        }
    ],
    "sg:phone":"+1 617 281 0460",
    "sg:postcode":"02451",
    "sg:province":"MA",
    "sg:tags":[
        "airport"
    ],
    "wof:name":"Ski Executive Sedan Svc",
    "wof:placetype":"venue"
},
  "geometry": {"coordinates":[-71.245527,42.383789],"type":"Point"}
}