{
  "type": "Feature",
  "properties": {
    "iso:country":"US",
    "sg:address":"16 Commonwealth Ave",
    "sg:city":"Swampscott",
    "sg:classifiers":[
        {
            "category":"Real Estate",
            "subcategory":"Real Estate Services",
            "type":"Services"
        },
        {
            "category":"Real Estate",
            "subcategory":"Real Estate Agent",
            "type":"Services"
        }
    ],
    "sg:phone":"+1 781 595 1752",
    "sg:postcode":"01907",
    "sg:province":"MA",
    "sg:tags":[
        "buyer",
        "broker"
    ],
    "wof:name":"Black Cat Jv Realty Trust",
    "wof:placetype":"venue"
},
  "geometry": {"coordinates":[-70.905396,42.467169],"type":"Point"}
}