{
  "type": "Feature",
  "properties": {
    "addr:full": "774 High St Dedham MA 02026",
    "addr:housenumber": "774",
    "addr:postcode": "02026",
    "addr:street": "High St",
    "iso:country": "US",
    "sg:address": "774 High St",
    "sg:city": "Dedham",
    "sg:classifiers": [
      {
        "category": "Professional",
        "subcategory": "Lawyer \u0026 Legal Services",
        "type": "Services"
      }
    ],
    "sg:phone": "+1 781 326 1444",
    "sg:postcode": "02026",
    "sg:province": "MA",
    "sg:tags": [
      "attorney"
    ],
    "sg:website": "www.mabeck.com",
    "wof:name": "Marylin A Beck Law Office",
    "wof:placetype": "venue"
  },
  "geometry": {"coordinates":[-71.182212,42.250532],"type":"Point"}
}
