{
  "type": "Feature",
  "properties": {
    "addr:full": "5 Cutter Avenue Somerville MA 02144",
    "addr:housenumber": "5",
    "addr:postcode": "02144",
    "addr:street": "Cutter Avenue",
    "iso:country": "US",
    "ovtr:label": "Winter Hill Bank, 5 Cutter Ave Somerville MA US",
    "ovtr:similarity": 2.6160531044006348,
    "sg:address": "5 Cutter Avenue",
    "sg:city": "Somerville",
    "sg:classifiers": [
      {
        "category": "Banks \u0026 Credit Unions",
        "subcategory": "Bank",
        "type": "Services"
      }
    ],
    "sg:phone": "+1 617 629 3330",
    "sg:postcode": "02144",
    "sg:province": "MA",
    "wof:name": "Winter Hill Bank",
    "wof:placetype": "venue"
  },
  "geometry": {"coordinates":[-71.120522,42.394194],"type":"Point"}
}
