{
  "type": "Feature",
  "properties": {
    "iso:country":"US",
    "sg:address":"148 Columbia St",
    "sg:city":"Cambridge",
    "sg:classifiers":[
        {
            "category":"Organizations",
            "subcategory":"Religious Organization",
            "type":"Services"
        }
    ],
    "sg:phone":"+1 617 492 1736",
    "sg:postcode":"02139",
    "sg:province":"MA",
    "sg:tags":[
        "church"
    ],
    "wof:name":"Faithful & True Witness Apstlc",
    "wof:placetype":"venue"
},
  "geometry": {"coordinates":[-71.09802500000001,42.366477],"type":"Point"}
}