{
  "type": "Feature",
  "properties": {
    "addr:full": "345 Broadway Revere MA 02151",
    "addr:housenumber": "345",
    "addr:postcode": "02151",
    "addr:street": "Broadway",
    "iso:country": "US",
    "sg:address": "345 Broadway",
    "sg:city": "Revere",
    "sg:classifiers": [
      {
        "category": "Shopping",
        "subcategory": "Jewelry",
        "type": "Retail Goods"
      }
    ],
    "sg:phone": "+1 781 284 0011",
    "sg:postcode": "02151",
    "sg:province": "MA",
    "wof:name": "Jewelry Box",
    "wof:placetype": "venue"
  },
  "geometry": {"coordinates":[-71.012983,42.409287],"type":"Point"}
}
