{
  "type": "Feature",
  "properties": {
    "addr:full":"286 W Main St Marlborough MA 01752",
    "addr:housenumber":"286",
    "addr:postcode":"01752",
    "addr:street":"W Main St",
    "iso:country":"US",
    "sg:address":"286 W Main St",
    "sg:city":"Marlborough",
    "sg:classifiers":[
        {
            "category":"Restaurant",
            "type":"Food & Drink"
        }
    ],
    "sg:menulink":"http://www.allmenus.com/ma/marlborough/91103-dangelo-sandwich-shops/menu/",
    "sg:phone":"+1 508 485 8579",
    "sg:postcode":"01752",
    "sg:province":"MA",
    "sg:tags":[
        "wrap",
        "soup",
        "american",
        "sandwich",
        "salad"
    ],
    "wof:name":"D'Angelo Sandwich Shops",
    "wof:placetype":"venue"
},
  "geometry": {"coordinates":[-71.56103,42.339873],"type":"Point"}
}