{
  "type": "Feature",
  "properties": {
    "iso:country":"US",
    "sg:address":"74 Warren St",
    "sg:city":"Roxbury",
    "sg:classifiers":[
        {
            "category":"Shopping",
            "subcategory":"Music",
            "type":"Retail Goods"
        }
    ],
    "sg:phone":"+1 617 427 6316",
    "sg:postcode":"02119",
    "sg:province":"MA",
    "sg:tags":[
        "compact",
        "used",
        "tapes",
        "records",
        "vintage",
        "record",
        "disc",
        "tape",
        "cd's"
    ],
    "wof:name":"Funky Fresh 1 Inc",
    "wof:placetype":"venue"
},
  "geometry": {"coordinates":[-71.083099,42.328078],"type":"Point"}
}