{
  "type": "Feature",
  "properties": {
    "addr:full": "79 Masonic St Northampton MA 01060",
    "addr:housenumber": "79",
    "addr:postcode": "01060",
    "addr:street": "Masonic St",
    "iso:country": "US",
    "sg:address": "79 Masonic St",
    "sg:city": "Northampton",
    "sg:classifiers": [
      {
        "category": "Organizations",
        "subcategory": "Religious Organization",
        "type": "Services"
      }
    ],
    "sg:phone": "+1 413 584 3420",
    "sg:postcode": "01060",
    "sg:province": "MA",
    "sg:tags": [
      "church"
    ],
    "wof:name": "First Church-Christ Scientist",
    "wof:placetype": "venue"
  },
  "geometry": {"coordinates":[-72.632861,42.319366],"type":"Point"}
}
