{
  "type": "Feature",
  "properties": {
    "iso:country":"US",
    "sg:address":"145 E Berkeley",
    "sg:city":"Boston",
    "sg:classifiers":[
        {
            "category":"Professional",
            "type":"Services"
        }
    ],
    "sg:phone":"+1 646 595 6386",
    "sg:postcode":"02118",
    "sg:province":"MA",
    "sg:tags":[
        "caterer"
    ],
    "sg:website":"www.rentaprivatechef.com",
    "wof:name":"R.a.P.C.",
    "wof:placetype":"venue"
},
  "geometry": {"coordinates":[-71.064863,42.343521],"type":"Point"}
}