{
  "type": "Feature",
  "properties": {
    "iso:country":"US",
    "sg:address":"199 Highland St",
    "sg:city":"Worcester",
    "sg:classifiers":[
        {
            "category":"Health Services",
            "subcategory":"Doctor",
            "type":"Services"
        }
    ],
    "sg:phone":"+1 508 755 7171",
    "sg:postcode":"01609",
    "sg:province":"MA",
    "sg:tags":[
        "dentist"
    ],
    "wof:name":"Peter A Stathoulopoulo DDS",
    "wof:placetype":"venue"
},
  "geometry": {"coordinates":[-71.811593,42.270678],"type":"Point"}
}