{
  "type": "Feature",
  "properties": {
    "addr:full":"800 Chief Justice Cushing Hwy Cohasset MA 02025",
    "addr:housenumber":"800",
    "addr:postcode":"02025",
    "addr:street":"Chief Justice Cushing Hwy",
    "iso:country":"US",
    "sg:address":"800 Chief Justice Cushing Hwy",
    "sg:city":"Cohasset",
    "sg:classifiers":[
        {
            "category":"Banks & Credit Unions",
            "subcategory":"Bank",
            "type":"Services"
        }
    ],
    "sg:phone":"+1 781 383 8441",
    "sg:postcode":"02025",
    "sg:province":"MA",
    "sg:website":"www.pilgrimco-op.com",
    "wof:name":"Pilgrim Co Operative Bank",
    "wof:placetype":"venue"
},
  "geometry": {"coordinates":[-70.80226500000001,42.221337],"type":"Point"}
}