{
  "type": "Feature",
  "properties": {
    "addr:full": "43 Fremont St Needham MA 02494",
    "addr:housenumber": "43",
    "addr:postcode": "02494",
    "addr:street": "Fremont St",
    "iso:country": "US",
    "sg:address": "43 Fremont St",
    "sg:city": "Needham",
    "sg:classifiers": [
      {
        "category": "Wholesale",
        "subcategory": "Electrical",
        "type": "Manufacturing \u0026 Wholesale Goods"
      }
    ],
    "sg:phone": "+1 781 444 6800",
    "sg:postcode": "02494",
    "sg:province": "MA",
    "sg:tags": [
      "electric",
      "motor"
    ],
    "sg:website": "www.weco-group.com",
    "wof:name": "Williamson New England Elec",
    "wof:placetype": "venue"
  },
  "geometry": {"coordinates":[-71.225119,42.305713],"type":"Point"}
}
