{
  "type": "Feature",
  "properties": {
    "addr:full":"11 Overlook Dr Sandwich MA 02563",
    "addr:housenumber":"11",
    "addr:postcode":"02563",
    "addr:street":"Overlook Dr",
    "iso:country":"US",
    "sg:address":"11 Overlook Dr",
    "sg:city":"Sandwich",
    "sg:classifiers":[
        {
            "category":"Local Transit",
            "type":"Transportation"
        }
    ],
    "sg:phone":"+1 508 888 8369",
    "sg:postcode":"02563",
    "sg:province":"MA",
    "sg:tags":[
        "limousine"
    ],
    "sg:website":"www.capecodlimo.com",
    "wof:name":"Connexions Inc",
    "wof:placetype":"venue"
},
  "geometry": {"coordinates":[-70.481737,41.735857],"type":"Point"}
}