{
  "type": "Feature",
  "properties": {
    "iso:country":"US",
    "sg:address":"590 State Rd",
    "sg:city":"Westport",
    "sg:classifiers":[
        {
            "category":"Insurance",
            "subcategory":"Insurance Agent",
            "type":"Services"
        }
    ],
    "sg:phone":"+1 508 676 8222",
    "sg:postcode":"02790",
    "sg:province":"MA",
    "wof:name":"All Neads Insurance",
    "wof:placetype":"venue"
},
  "geometry": {"coordinates":[-71.08497300000001,41.661579],"type":"Point"}
}