{
  "type": "Feature",
  "properties": {
    "addr:full": "65 Mystic Ave Somerville MA 02145",
    "addr:housenumber": "65",
    "addr:postcode": "02145",
    "addr:street": "Mystic Ave",
    "iso:country": "US",
    "sg:address": "65 Mystic Ave",
    "sg:city": "Somerville",
    "sg:classifiers": [
      {
        "category": "Shopping",
        "subcategory": "Computers \u0026 Home Electronics",
        "type": "Retail Goods"
      }
    ],
    "sg:phone": "+1 617 623 3400",
    "sg:postcode": "02145",
    "sg:province": "MA",
    "sg:tags": [
      "equipment",
      "electronic",
      "supply"
    ],
    "wof:name": "Circuit City",
    "wof:placetype": "venue"
  },
  "geometry": {"coordinates":[-71.081303,42.389872],"type":"Point"}
}
