{
  "type": "Feature",
  "properties": {
    "iso:country":"US",
    "sg:address":"65 Mystic Ave",
    "sg:city":"Somerville",
    "sg:classifiers":[
        {
            "category":"Shopping",
            "subcategory":"Computers & Home Electronics",
            "type":"Retail Goods"
        }
    ],
    "sg:phone":"+1 617 623 3400",
    "sg:postcode":"02145",
    "sg:province":"MA",
    "sg:tags":[
        "equipment",
        "electronic",
        "supply"
    ],
    "wof:name":"Circuit City",
    "wof:placetype":"venue"
},
  "geometry": {"coordinates":[-71.08130300000001,42.389872],"type":"Point"}
}