{
  "type": "Feature",
  "properties": {
    "addr:full":"15 Elmwood Ave Cambridge MA 02138",
    "addr:housenumber":"15",
    "addr:postcode":"02138",
    "addr:street":"Elmwood Ave",
    "iso:country":"US",
    "sg:address":"15 Elmwood Ave",
    "sg:city":"Cambridge",
    "sg:classifiers":[
        {
            "category":"Shopping",
            "subcategory":"Used Merchandise",
            "type":"Retail Goods"
        }
    ],
    "sg:phone":"+1 617 868 1711",
    "sg:postcode":"02138",
    "sg:province":"MA",
    "sg:tags":[
        "book",
        "rare",
        "dealer"
    ],
    "wof:name":"Charles B Wood III Rare Books",
    "wof:placetype":"venue"
},
  "geometry": {"coordinates":[-71.137546,42.375926],"type":"Point"}
}