{
  "type": "Feature",
  "properties": {
    "iso:country":"US",
    "sg:address":"52 Sanborn St",
    "sg:city":"Reading",
    "sg:classifiers":[
        {
            "category":"Education",
            "subcategory":"School",
            "type":"Public Place"
        }
    ],
    "sg:phone":"+1 781 944 6200",
    "sg:postcode":"01867",
    "sg:province":"MA",
    "sg:tags":[
        "high",
        "middle",
        "elementary"
    ],
    "wof:name":"Reading School House Condominium",
    "wof:placetype":"venue"
},
  "geometry": {"coordinates":[-71.104797,42.5256],"type":"Point"}
}