{
  "type": "Feature",
  "properties": {
    "addr:full": "67 Althea Rd North Falmouth MA 02556",
    "addr:housenumber": "67",
    "addr:postcode": "02556",
    "addr:street": "Althea Rd",
    "iso:country": "US",
    "sg:address": "67 Althea Rd",
    "sg:city": "North Falmouth",
    "sg:classifiers": [
      {
        "category": "Real Estate",
        "subcategory": "Real Estate Agent",
        "type": "Services"
      }
    ],
    "sg:phone": "+1 508 540 2807",
    "sg:postcode": "02556",
    "sg:province": "MA",
    "sg:tags": [
      "appraiser"
    ],
    "wof:name": "Action Appraisals",
    "wof:placetype": "venue"
  },
  "geometry": {"coordinates":[-70.613892,41.630102],"type":"Point"}
}
