{
  "type": "Feature",
  "properties": {
    "addr:full":"628 Main St Mashpee MA 02649",
    "addr:housenumber":"628",
    "addr:postcode":"02649",
    "addr:street":"Main St",
    "iso:country":"US",
    "sg:address":"628 Main St",
    "sg:city":"Mashpee",
    "sg:classifiers":[
        {
            "category":"Manufacturing",
            "subcategory":"Printing",
            "type":"Manufacturing & Wholesale Goods"
        }
    ],
    "sg:phone":"+1 508 477 6101",
    "sg:postcode":"02649",
    "sg:province":"MA",
    "sg:tags":[
        "screen"
    ],
    "wof:name":"Kidcut Sportwear",
    "wof:placetype":"venue"
},
  "geometry": {"coordinates":[-70.505347,41.666863],"type":"Point"}
}