{
  "type": "Feature",
  "properties": {
    "addr:full": "100 Maple Ave Shrewsbury MA 01545",
    "addr:housenumber": "100",
    "addr:postcode": "01545",
    "addr:street": "Maple Ave",
    "iso:country": "US",
    "sg:address": "100 Maple Ave",
    "sg:city": "Shrewsbury",
    "sg:classifiers": [
      {
        "category": "Government",
        "subcategory": "Office",
        "type": "Public Place"
      }
    ],
    "sg:phone": "+1   ",
    "sg:postcode": "01545",
    "sg:province": "MA",
    "sg:tags": [
      "conservation"
    ],
    "wof:name": "Shrewsbury Park Department Par",
    "wof:placetype": "venue"
  },
  "geometry": {"coordinates":[-71.722984,42.289671],"type":"Point"}
}
