{
  "type": "Feature",
  "properties": {
    "iso:country":"US",
    "sg:address":"12 Oak Knoll Ter",
    "sg:city":"Needham",
    "sg:classifiers":[
        {
            "category":"Professional",
            "subcategory":"Management & Consulting",
            "type":"Services"
        }
    ],
    "sg:phone":"+1 781 455 9050",
    "sg:postcode":"02492",
    "sg:province":"MA",
    "sg:tags":[
        "counselor",
        "public",
        "relations"
    ],
    "sg:website":"www.roweassoc.com",
    "wof:name":"Kathleen Rowe Assoc",
    "wof:placetype":"venue"
},
  "geometry": {"coordinates":[-71.24686199999999,42.282616],"type":"Point"}
}