{
  "type": "Feature",
  "properties": {
    "addr:full": "2 Athens Ter Cambridge MA 02138",
    "addr:housenumber": "2",
    "addr:postcode": "02138",
    "addr:street": "Athens Ter",
    "iso:country": "US",
    "sg:address": "2 Athens Ter",
    "sg:city": "Cambridge",
    "sg:classifiers": [
      {
        "category": "Professional",
        "subcategory": "Business Services",
        "type": "Services"
      }
    ],
    "sg:phone": "+1   ",
    "sg:postcode": "02138",
    "sg:province": "MA",
    "wof:name": "Frank Geoffrion",
    "wof:placetype": "venue"
  },
  "geometry": {"coordinates":[-71.115141,42.369971],"type":"Point"}
}
