{
  "type": "Feature",
  "properties": {
    "iso:country":"US",
    "sg:address":"2 Athens Ter",
    "sg:city":"Cambridge",
    "sg:classifiers":[
        {
            "category":"Professional",
            "subcategory":"Business Services",
            "type":"Services"
        }
    ],
    "sg:phone":"+1   ",
    "sg:postcode":"02138",
    "sg:province":"MA",
    "wof:name":"Frank Geoffrion",
    "wof:placetype":"venue"
},
  "geometry": {"coordinates":[-71.11514099999999,42.369971],"type":"Point"}
}