{
  "type": "Feature",
  "properties": {
    "addr:full":"58 Hummock Pond Rd Nantucket MA 02554",
    "addr:housenumber":"58",
    "addr:postcode":"02554",
    "addr:street":"Hummock Pond Rd",
    "iso:country":"US",
    "sg:address":"58 Hummock Pond Rd",
    "sg:city":"Nantucket",
    "sg:classifiers":[
        {
            "category":"Building & Trades",
            "subcategory":"Construction",
            "type":"Services"
        }
    ],
    "sg:phone":"+1   ",
    "sg:postcode":"02554",
    "sg:province":"MA",
    "sg:tags":[
        "house"
    ],
    "wof:name":"Cross Rip Const Corp",
    "wof:placetype":"venue"
},
  "geometry": {"coordinates":[-70.121875,41.272767],"type":"Point"}
}