{
  "type": "Feature",
  "properties": {
    "addr:full": "21 Court St Taunton MA 02780",
    "addr:housenumber": "21",
    "addr:postcode": "02780",
    "addr:street": "Court St",
    "iso:country": "US",
    "sg:address": "21 Court St",
    "sg:city": "Taunton",
    "sg:classifiers": [
      {
        "category": "Retail",
        "subcategory": "Auto Repair",
        "type": "Services"
      }
    ],
    "sg:phone": "+1 508 824 9344",
    "sg:postcode": "02780",
    "sg:province": "MA",
    "sg:tags": [
      "repairing",
      "automobile"
    ],
    "wof:name": "Sam's Tire \u0026 Auto Repair",
    "wof:placetype": "venue"
  },
  "geometry": {"coordinates":[-71.095088,41.902557],"type":"Point"}
}
