{
  "type": "Feature",
  "properties": {
    "iso:country":"US",
    "sg:address":"4253 Washington St",
    "sg:city":"Roslindale",
    "sg:classifiers":[
        {
            "category":"Food & Beverages",
            "subcategory":"Meat & Fish",
            "type":"Retail Goods"
        },
        {
            "category":"Food & Beverages",
            "subcategory":"Groceries & Convenience Stores",
            "type":"Retail Goods"
        }
    ],
    "sg:phone":"+1 617 323 7313",
    "sg:postcode":"02131",
    "sg:province":"MA",
    "sg:tags":[
        "grocer",
        "ethnic"
    ],
    "sg:website":"www.tonysmarketroslindale.com",
    "wof:name":"Tony's Market",
    "wof:placetype":"venue"
},
  "geometry": {"coordinates":[-71.12930299999999,42.285198],"type":"Point"}
}