{
  "type": "Feature",
  "properties": {
    "addr:full": "4253 Washington St Roslindale MA 02131",
    "addr:housenumber": "4253",
    "addr:postcode": "02131",
    "addr:street": "Washington St",
    "iso:country": "US",
    "ovtr:label": "Tony's Market Roslindale, 4381 Washington St Roslindale MA US",
    "ovtr:similarity": 3.993201971054077,
    "sg:address": "4253 Washington St",
    "sg:city": "Roslindale",
    "sg:classifiers": [
      {
        "category": "Food \u0026 Beverages",
        "subcategory": "Meat \u0026 Fish",
        "type": "Retail Goods"
      },
      {
        "category": "Food \u0026 Beverages",
        "subcategory": "Groceries \u0026 Convenience Stores",
        "type": "Retail Goods"
      }
    ],
    "sg:phone": "+1 617 323 7313",
    "sg:postcode": "02131",
    "sg:province": "MA",
    "sg:tags": [
      "grocer",
      "ethnic"
    ],
    "sg:website": "www.tonysmarketroslindale.com",
    "wof:name": "Tony's Market",
    "wof:placetype": "venue"
  },
  "geometry": {"coordinates":[-71.129303,42.285198],"type":"Point"}
}
