{
  "type": "Feature",
  "properties": {
    "addr:full":"23 W Bay Rd Osterville MA 02655",
    "addr:housenumber":"23",
    "addr:postcode":"02655",
    "addr:street":"W Bay Rd",
    "iso:country":"US",
    "sg:address":"23 W Bay Rd",
    "sg:city":"Osterville",
    "sg:classifiers":[
        {
            "category":"Health Services",
            "subcategory":"Doctor",
            "type":"Services"
        }
    ],
    "sg:phone":"+1 508 420 8877",
    "sg:postcode":"02655",
    "sg:province":"MA",
    "sg:tags":[
        "physician",
        "surgeon"
    ],
    "wof:name":"Delvecchio Daniel A MD",
    "wof:placetype":"venue"
},
  "geometry": {"coordinates":[-70.38359800000001,41.6273],"type":"Point"}
}