{
  "type": "Feature",
  "properties": {
    "addr:full":"145 Simpson St Stoughton MA 02072",
    "addr:housenumber":"145",
    "addr:postcode":"02072",
    "addr:street":"Simpson St",
    "iso:country":"US",
    "sg:address":"145 Simpson St",
    "sg:city":"Stoughton",
    "sg:classifiers":[
        {
            "category":"Building & Trades",
            "subcategory":"Cleaning & Sanitation",
            "type":"Services"
        }
    ],
    "sg:phone":"+1 781 341 1169",
    "sg:postcode":"02072",
    "sg:province":"MA",
    "sg:tags":[
        "carpet"
    ],
    "wof:name":"Zechello James Professional Cleaning",
    "wof:placetype":"venue"
},
  "geometry": {"coordinates":[-71.115196,42.128399],"type":"Point"}
}