{
  "type": "Feature",
  "properties": {
    "iso:country":"US",
    "sg:address":"134 Old Rd To 9 Acre Cor",
    "sg:city":"Concord",
    "sg:classifiers":[
        {
            "category":"Social Services",
            "subcategory":"Child Care",
            "type":"Services"
        }
    ],
    "sg:phone":"+1 978 369 0492",
    "sg:postcode":"01742",
    "sg:province":"MA",
    "sg:website":"www.concordchildrenscenter.org",
    "wof:name":"Concord Children's Ctr",
    "wof:placetype":"venue"
},
  "geometry": {"coordinates":[-71.37676399999999,42.453327],"type":"Point"}
}