{
  "type": "Feature",
  "properties": {
    "addr:full": "134 Old Rd To 9 Acre Cor Concord MA 01742",
    "addr:housenumber": "134",
    "addr:postcode": "01742",
    "addr:street": "Old Rd To 9 Acre Cor",
    "iso:country": "US",
    "sg:address": "134 Old Rd To 9 Acre Cor",
    "sg:city": "Concord",
    "sg:classifiers": [
      {
        "category": "Social Services",
        "subcategory": "Child Care",
        "type": "Services"
      }
    ],
    "sg:phone": "+1 978 369 0492",
    "sg:postcode": "01742",
    "sg:province": "MA",
    "sg:website": "www.concordchildrenscenter.org",
    "wof:name": "Concord Children's Ctr",
    "wof:placetype": "venue"
  },
  "geometry": {"coordinates":[-71.376764,42.453327],"type":"Point"}
}
