{
  "type": "Feature",
  "properties": {
    "addr:full": "22 Sunnyside Ave Arlington MA 02474",
    "addr:housenumber": "22",
    "addr:postcode": "02474",
    "addr:street": "Sunnyside Ave",
    "iso:country": "US",
    "sg:address": "22 Sunnyside Ave",
    "sg:city": "Arlington",
    "sg:classifiers": [
      {
        "category": "Manufacturing",
        "subcategory": "Motor Vehicles \u0026 Parts",
        "type": "Manufacturing \u0026 Wholesale Goods"
      }
    ],
    "sg:phone": "+1 781 643 4900",
    "sg:postcode": "02474",
    "sg:province": "MA",
    "sg:tags": [
      "equipment",
      "truck"
    ],
    "sg:website": "www.hinoworld.com",
    "wof:name": "Automotive Truck",
    "wof:placetype": "venue"
  },
  "geometry": {"coordinates":[-71.134701,42.407416],"type":"Point"}
}
