{
  "type": "Feature",
  "properties": {
    "addr:full":"195 Summer St Kingston MA 02364",
    "addr:housenumber":"195",
    "addr:postcode":"02364",
    "addr:street":"Summer St",
    "iso:country":"US",
    "sg:address":"195 Summer St",
    "sg:city":"Kingston",
    "sg:classifiers":[
        {
            "category":"Health Services",
            "subcategory":"Health Practitioner",
            "type":"Services"
        }
    ],
    "sg:phone":"+1 781 585 7722",
    "sg:postcode":"02364",
    "sg:province":"MA",
    "sg:tags":[
        "therapist",
        "physical"
    ],
    "wof:name":"Plymouth-Kingston Physical",
    "wof:placetype":"venue"
},
  "geometry": {"coordinates":[-70.733333,42.01412],"type":"Point"}
}