{
  "type": "Feature",
  "properties": {
    "iso:country":"US",
    "sg:address":"9 Prichard St",
    "sg:city":"Fitchburg",
    "sg:classifiers":[
        {
            "category":"Health Services",
            "subcategory":"Health Practitioner",
            "type":"Services"
        }
    ],
    "sg:phone":"+1 978 343 6886",
    "sg:postcode":"01420",
    "sg:province":"MA",
    "sg:tags":[
        "therapist",
        "physical"
    ],
    "wof:name":"Fitchburg Center Physcl Thrpy",
    "wof:placetype":"venue"
},
  "geometry": {"coordinates":[-71.79835799999999,42.58304],"type":"Point"}
}