{
  "type": "Feature",
  "properties": {
    "iso:country":"US",
    "sg:address":"3 Gerrish Rd",
    "sg:city":"Salisbury",
    "sg:classifiers":[
        {
            "category":"Professional",
            "subcategory":"Computer Services",
            "type":"Services"
        }
    ],
    "sg:phone":"+1 978 465 9328",
    "sg:postcode":"01952",
    "sg:province":"MA",
    "sg:tags":[
        "scanning"
    ],
    "sg:website":"www.picturebits.com",
    "wof:name":"Picture Bits Digital Imaging",
    "wof:placetype":"venue"
},
  "geometry": {"coordinates":[-70.864695,42.850043],"type":"Point"}
}