{
  "type": "Feature",
  "properties": {
    "iso:country":"US",
    "sg:address":"20 Malia Ter",
    "sg:city":"Chestnut Hill",
    "sg:classifiers":[
        {
            "category":"Professional",
            "subcategory":"Management & Consulting",
            "type":"Services"
        }
    ],
    "sg:phone":"+1 617 566 6474",
    "sg:postcode":"02467",
    "sg:province":"MA",
    "wof:name":"Schmalensee Partners",
    "wof:placetype":"venue"
},
  "geometry": {"coordinates":[-71.159173,42.330712],"type":"Point"}
}