{
  "type": "Feature",
  "properties": {
    "addr:full":"236 Forest St Waltham MA 02452",
    "addr:housenumber":"236",
    "addr:postcode":"02452",
    "addr:street":"Forest St",
    "iso:country":"US",
    "sg:address":"236 Forest St",
    "sg:city":"Waltham",
    "sg:classifiers":[
        {
            "category":"Professional",
            "type":"Services"
        }
    ],
    "sg:phone":"+1   ",
    "sg:postcode":"02452",
    "sg:province":"MA",
    "wof:name":"Jimike Corporation",
    "wof:placetype":"venue"
},
  "geometry": {"coordinates":[-71.22054300000001,42.392947],"type":"Point"}
}