{
  "type": "Feature",
  "properties": {
    "iso:country":"US",
    "sg:address":"2 Edwards Rd",
    "sg:city":"Burlington",
    "sg:classifiers":[
        {
            "category":"Building & Trades",
            "subcategory":"Construction",
            "type":"Services"
        }
    ],
    "sg:phone":"+1 781 272 6916",
    "sg:postcode":"01803",
    "sg:province":"MA",
    "sg:tags":[
        "restoration",
        "cleaning",
        "patio",
        "deck"
    ],
    "wof:name":"Royal Shine Auto Sales",
    "wof:placetype":"venue"
},
  "geometry": {"coordinates":[-71.19288,42.498833],"type":"Point"}
}