{
  "type": "Feature",
  "properties": {
    "addr:full": "203 S Union St Lawrence MA 01843",
    "addr:housenumber": "203",
    "addr:postcode": "01843",
    "addr:street": "S Union St",
    "iso:country": "US",
    "sg:address": "203 S Union St",
    "sg:city": "Lawrence",
    "sg:classifiers": [
      {
        "category": "Restaurant",
        "type": "Food \u0026 Drink"
      }
    ],
    "sg:phone": "+1 978 689 2255",
    "sg:postcode": "01843",
    "sg:province": "MA",
    "sg:tags": [
      "eating"
    ],
    "wof:name": "Bella Fiore Caterers",
    "wof:placetype": "venue"
  },
  "geometry": {"coordinates":[-71.153403,42.697472],"type":"Point"}
}
