{
  "type": "Feature",
  "properties": {
    "iso:country":"US",
    "sg:address":"203 S Union St",
    "sg:city":"Lawrence",
    "sg:classifiers":[
        {
            "category":"Restaurant",
            "type":"Food & Drink"
        }
    ],
    "sg:phone":"+1 978 689 2255",
    "sg:postcode":"01843",
    "sg:province":"MA",
    "sg:tags":[
        "eating"
    ],
    "wof:name":"Bella Fiore Caterers",
    "wof:placetype":"venue"
},
  "geometry": {"coordinates":[-71.153403,42.697472],"type":"Point"}
}