{
  "type": "Feature",
  "properties": {
    "iso:country":"US",
    "sg:address":"37 Union St",
    "sg:city":"Attleboro",
    "sg:classifiers":[
        {
            "category":"Retail",
            "subcategory":"Portrait Studio",
            "type":"Services"
        }
    ],
    "sg:phone":"+1 508 226 1560",
    "sg:postcode":"02703",
    "sg:province":"MA",
    "sg:tags":[
        "photographer"
    ],
    "wof:name":"Loft Photographic",
    "wof:placetype":"venue"
},
  "geometry": {"coordinates":[-71.282174,41.943275],"type":"Point"}
}