{
  "type": "Feature",
  "properties": {
    "iso:country":"US",
    "sg:address":"245 Western Ave",
    "sg:city":"Lynn",
    "sg:classifiers":[
        {
            "category":"Real Estate",
            "subcategory":"Real Estate Agent",
            "type":"Services"
        }
    ],
    "sg:phone":"+1 781 599 2500",
    "sg:postcode":"01904",
    "sg:province":"MA",
    "wof:name":"Martel Real Estate",
    "wof:placetype":"venue"
},
  "geometry": {"coordinates":[-70.94946400000001,42.476801],"type":"Point"}
}