{
  "type": "Feature",
  "properties": {
    "addr:full": "245 Western Ave Lynn MA 01904",
    "addr:housenumber": "245",
    "addr:postcode": "01904",
    "addr:street": "Western Ave",
    "iso:country": "US",
    "ovtr:label": "Martel Real Estate, 245 Western Ave Lynn MA US",
    "ovtr:similarity": 2.0947530269622803,
    "sg:address": "245 Western Ave",
    "sg:city": "Lynn",
    "sg:classifiers": [
      {
        "category": "Real Estate",
        "subcategory": "Real Estate Agent",
        "type": "Services"
      }
    ],
    "sg:phone": "+1 781 599 2500",
    "sg:postcode": "01904",
    "sg:province": "MA",
    "wof:name": "Martel Real Estate",
    "wof:placetype": "venue"
  },
  "geometry": {"coordinates":[-70.949464,42.476801],"type":"Point"}
}
