{
  "type": "Feature",
  "properties": {
    "addr:full": "174 Colonial Dr Somerset MA 02726",
    "addr:housenumber": "174",
    "addr:postcode": "02726",
    "addr:street": "Colonial Dr",
    "iso:country": "US",
    "sg:address": "174 Colonial Dr",
    "sg:city": "Somerset",
    "sg:classifiers": [
      {
        "category": "Professional",
        "type": "Services"
      }
    ],
    "sg:phone": "+1   ",
    "sg:postcode": "02726",
    "sg:province": "MA",
    "wof:name": "Rewards Incorporated",
    "wof:placetype": "venue"
  },
  "geometry": {"coordinates":[-71.151134,41.745624],"type":"Point"}
}
