{
  "type": "Feature",
  "properties": {
    "addr:full":"140 Andrew St Springfield MA 01109",
    "addr:housenumber":"140",
    "addr:postcode":"01109",
    "addr:street":"Andrew St",
    "iso:country":"US",
    "sg:address":"140 Andrew St",
    "sg:city":"Springfield",
    "sg:classifiers":[
        {
            "category":"Organizations",
            "subcategory":"Religious Organization",
            "type":"Services"
        }
    ],
    "sg:phone":"+1 413 737 8605",
    "sg:postcode":"01109",
    "sg:province":"MA",
    "sg:tags":[
        "church"
    ],
    "wof:name":"True Vine Church",
    "wof:placetype":"venue"
},
  "geometry": {"coordinates":[-72.562862,42.11502],"type":"Point"}
}