{
  "type": "Feature",
  "properties": {
    "addr:full": "152 Lynnway Lynn MA 01902",
    "addr:housenumber": "152",
    "addr:postcode": "01902",
    "addr:street": "Lynnway Lynn",
    "iso:country": "US",
    "sg:address": "152 Lynnway",
    "sg:city": "Lynn",
    "sg:classifiers": [
      {
        "category": "Professional",
        "subcategory": "Lawyer \u0026 Legal Services",
        "type": "Services"
      }
    ],
    "sg:phone": "+1 781 581 9880",
    "sg:postcode": "01902",
    "sg:province": "MA",
    "sg:tags": [
      "attorney"
    ],
    "wof:name": "Ronan Riley \u0026 Dever",
    "wof:placetype": "venue"
  },
  "geometry": {"coordinates":[-70.945237,42.459994],"type":"Point"}
}
