{
  "type": "Feature",
  "properties": {
    "iso:country":"US",
    "sg:address":"324 Rantoul St",
    "sg:city":"Beverly",
    "sg:classifiers":[
        {
            "category":"Manufacturing",
            "subcategory":"Signs",
            "type":"Manufacturing & Wholesale Goods"
        }
    ],
    "sg:phone":"+1 978 927 7057",
    "sg:postcode":"01915",
    "sg:province":"MA",
    "wof:name":"Star Neon Sign Mfg Co",
    "wof:placetype":"venue"
},
  "geometry": {"coordinates":[-70.882981,42.551357],"type":"Point"}
}