{
  "type": "Feature",
  "properties": {
    "iso:country":"US",
    "sg:address":"393 Meridian St",
    "sg:city":"Boston",
    "sg:classifiers":[
        {
            "category":"Wholesale",
            "subcategory":"Durable Goods & Equipment",
            "type":"Manufacturing & Wholesale Goods"
        }
    ],
    "sg:phone":"+1   ",
    "sg:postcode":"02128",
    "sg:province":"MA",
    "wof:name":"Servicio De Encomiendas",
    "wof:placetype":"venue"
},
  "geometry": {"coordinates":[-71.03916599999999,42.379852],"type":"Point"}
}