{
  "type": "Feature",
  "properties": {
    "addr:full": "100 Hospital Rd Malden MA 02148",
    "addr:housenumber": "100",
    "addr:postcode": "02148",
    "addr:street": "Hospital Rd",
    "iso:country": "US",
    "sg:address": "100 Hospital Rd",
    "sg:city": "Malden",
    "sg:classifiers": [
      {
        "category": "Health Services",
        "subcategory": "Doctor",
        "type": "Services"
      }
    ],
    "sg:phone": "+1 781 338 7248",
    "sg:postcode": "02148",
    "sg:province": "MA",
    "sg:tags": [
      "physician",
      "surgeon"
    ],
    "wof:name": "Hallmark Health",
    "wof:placetype": "venue"
  },
  "geometry": {"coordinates":[-71.088072,42.426608],"type":"Point"}
}
