{
  "type": "Feature",
  "properties": {
    "addr:full":"1207 S Main St Palmer MA 01069",
    "addr:housenumber":"1207",
    "addr:postcode":"01069",
    "addr:street":"S Main St",
    "iso:country":"US",
    "sg:address":"1207 S Main St",
    "sg:city":"Palmer",
    "sg:classifiers":[
        {
            "category":"Home & Garden",
            "subcategory":"Carpets & Floor Coverings",
            "type":"Retail Goods"
        }
    ],
    "sg:phone":"+1 413 283 5050",
    "sg:postcode":"01069",
    "sg:province":"MA",
    "sg:tags":[
        "material"
    ],
    "wof:name":"Buchmans Floor Covering",
    "wof:placetype":"venue"
},
  "geometry": {"coordinates":[-72.320982,42.151331],"type":"Point"}
}