{
  "type": "Feature",
  "properties": {
    "iso:country":"US",
    "sg:address":"16 Deacons Folly Rd",
    "sg:city":"Harwich",
    "sg:classifiers":[
        {
            "category":"Building & Trades",
            "subcategory":"Electrical",
            "type":"Services"
        }
    ],
    "sg:phone":"+1   ",
    "sg:postcode":"02645",
    "sg:province":"MA",
    "sg:tags":[
        "electrical",
        "contractor"
    ],
    "wof:name":"Thomas R Whelan Electrician",
    "wof:placetype":"venue"
},
  "geometry": {"coordinates":[-70.11107,41.690654],"type":"Point"}
}