{
  "type": "Feature",
  "properties": {
    "addr:full": "16 Deacons Folly Rd Harwich MA 02645",
    "addr:housenumber": "16",
    "addr:postcode": "02645",
    "addr:street": "Deacons Folly Rd",
    "iso:country": "US",
    "sg:address": "16 Deacons Folly Rd",
    "sg:city": "Harwich",
    "sg:classifiers": [
      {
        "category": "Building \u0026 Trades",
        "subcategory": "Electrical",
        "type": "Services"
      }
    ],
    "sg:phone": "+1   ",
    "sg:postcode": "02645",
    "sg:province": "MA",
    "sg:tags": [
      "electrical",
      "contractor"
    ],
    "wof:name": "Thomas R Whelan Electrician",
    "wof:placetype": "venue"
  },
  "geometry": {"coordinates":[-70.11107,41.690654],"type":"Point"}
}
