{
  "type": "Feature",
  "properties": {
    "addr:full": "100 S Kimball St Haverhill MA 01835",
    "addr:housenumber": "100",
    "addr:postcode": "01835",
    "addr:street": "S Kimball St",
    "iso:country": "US",
    "sg:address": "100 S Kimball St",
    "sg:city": "Haverhill",
    "sg:classifiers": [
      {
        "category": "Professional",
        "type": "Services"
      }
    ],
    "sg:phone": "+1 978 687 7100",
    "sg:postcode": "01835",
    "sg:province": "MA",
    "sg:tags": [
      "establishment"
    ],
    "wof:name": "Newark Atlantic Paperboard",
    "wof:placetype": "venue"
  },
  "geometry": {"coordinates":[-71.067043,42.767764],"type":"Point"}
}
