{
  "type": "Feature",
  "properties": {
    "addr:full":"36 Hadley St South Hadley MA 01075",
    "addr:housenumber":"36",
    "addr:postcode":"01075",
    "addr:street":"Hadley St",
    "iso:country":"US",
    "sg:address":"36 Hadley St",
    "sg:city":"South Hadley",
    "sg:classifiers":[
        {
            "category":"Education",
            "subcategory":"School",
            "type":"Public Place"
        }
    ],
    "sg:phone":"+1 413 533 8544",
    "sg:postcode":"01075",
    "sg:province":"MA",
    "wof:name":"Valley Christian School",
    "wof:placetype":"venue"
},
  "geometry": {"coordinates":[-72.583443,42.264334],"type":"Point"}
}