{
  "type": "Feature",
  "properties": {
    "addr:full": "26 Court St Boston MA 02108",
    "addr:housenumber": "26",
    "addr:postcode": "02108",
    "addr:street": "Court St",
    "iso:country": "US",
    "sg:address": "26 Court St",
    "sg:city": "Boston",
    "sg:classifiers": [
      {
        "category": "Education",
        "subcategory": "School",
        "type": "Public Place"
      }
    ],
    "sg:phone": "+1 617 635 9000",
    "sg:postcode": "02108",
    "sg:province": "MA",
    "sg:website": "boston.k12.ma.us/",
    "wof:name": "Boston Public Schools",
    "wof:placetype": "venue"
  },
  "geometry": {"coordinates":[-71.058667,42.359069],"type":"Point"}
}
