{
  "type": "Feature",
  "properties": {
    "iso:country":"US",
    "sg:address":"9 Pickering St",
    "sg:city":"Salem",
    "sg:classifiers":[
        {
            "category":"Museum",
            "type":"Entertainment"
        }
    ],
    "sg:phone":"+1 978 740 4060",
    "sg:postcode":"01970",
    "sg:province":"MA",
    "wof:name":"Witch Mansion",
    "wof:placetype":"venue"
},
  "geometry": {"coordinates":[-70.901481,42.519245],"type":"Point"}
}