{
  "type": "Feature",
  "properties": {
    "addr:full":"4 Mill St Shirley MA 01464",
    "addr:housenumber":"4",
    "addr:postcode":"01464",
    "addr:street":"Mill St",
    "iso:country":"US",
    "sg:address":"4 Mill St",
    "sg:city":"Shirley",
    "sg:classifiers":[
        {
            "category":"Restaurant",
            "type":"Food & Drink"
        }
    ],
    "sg:phone":"+1 978 425 9000",
    "sg:postcode":"01464",
    "sg:province":"MA",
    "wof:name":"Riccolino's Restaurant",
    "wof:placetype":"venue"
},
  "geometry": {"coordinates":[-71.65206999999999,42.54383],"type":"Point"}
}