{
  "type": "Feature",
  "properties": {
    "addr:full":"225 Winthrop St Taunton MA 02780",
    "addr:housenumber":"225",
    "addr:postcode":"02780",
    "addr:street":"Winthrop St",
    "iso:country":"US",
    "sg:address":"225 Winthrop St",
    "sg:city":"Taunton",
    "sg:classifiers":[
        {
            "category":"Health Services",
            "subcategory":"Doctor",
            "type":"Services"
        },
        {
            "category":"Health Services",
            "subcategory":"Dentist",
            "type":"Services"
        }
    ],
    "sg:phone":"+1 508 880 2011",
    "sg:postcode":"02780",
    "sg:province":"MA",
    "sg:tags":[
        "dentists-oral",
        "physician",
        "maxillofacial",
        "surgeons",
        "surgery",
        "oral"
    ],
    "wof:name":"Siogros Joyce",
    "wof:placetype":"venue"
},
  "geometry": {"coordinates":[-71.112137,41.89093],"type":"Point"}
}