{
  "type": "Feature",
  "properties": {
    "addr:full": "690 Grattan St Chicopee MA 01020",
    "addr:housenumber": "690",
    "addr:postcode": "01020",
    "addr:street": "Grattan St",
    "iso:country": "US",
    "ovtr:label": "Great China Restaurant, 690 Grattan St Chicopee MA US",
    "ovtr:similarity": 2.043454885482788,
    "sg:address": "690 Grattan St",
    "sg:city": "Chicopee",
    "sg:classifiers": [
      {
        "category": "Restaurant",
        "type": "Food \u0026 Drink"
      }
    ],
    "sg:phone": "+1 413 534 5600",
    "sg:postcode": "01020",
    "sg:province": "MA",
    "wof:name": "Great China Restaurant",
    "wof:placetype": "venue"
  },
  "geometry": {"coordinates":[-72.5993,42.173902],"type":"Point"}
}
