{
  "type": "Feature",
  "properties": {
    "iso:country":"US",
    "sg:address":"690 Grattan St",
    "sg:city":"Chicopee",
    "sg:classifiers":[
        {
            "category":"Restaurant",
            "type":"Food & Drink"
        }
    ],
    "sg:phone":"+1 413 534 5600",
    "sg:postcode":"01020",
    "sg:province":"MA",
    "wof:name":"Great China Restaurant",
    "wof:placetype":"venue"
},
  "geometry": {"coordinates":[-72.5993,42.173902],"type":"Point"}
}