{
  "type": "Feature",
  "properties": {
    "addr:full":"476 Elliott St Beverly MA 01915",
    "addr:housenumber":"476",
    "addr:postcode":"01915",
    "addr:street":"Elliott St",
    "iso:country":"US",
    "sg:address":"476 Elliott St",
    "sg:city":"Beverly",
    "sg:classifiers":[
        {
            "category":"Home & Garden",
            "subcategory":"Hardware",
            "type":"Retail Goods"
        }
    ],
    "sg:phone":"+1 978 774 2184",
    "sg:postcode":"01915",
    "sg:province":"MA",
    "wof:name":"Elm St Hardware Inc",
    "wof:placetype":"venue"
},
  "geometry": {"coordinates":[-70.906082,42.556616],"type":"Point"}
}