{
  "type": "Feature",
  "properties": {
    "iso:country":"US",
    "sg:address":"13 3rd St",
    "sg:city":"Medford",
    "sg:classifiers":[
        {
            "category":"Professional",
            "subcategory":"Accounting & Tax Preparation",
            "type":"Services"
        }
    ],
    "sg:phone":"+1 781 396 8516",
    "sg:postcode":"02155",
    "sg:province":"MA",
    "sg:tags":[
        "return",
        "preparation-business"
    ],
    "wof:name":"Bresnahan Accounting",
    "wof:placetype":"venue"
},
  "geometry": {"coordinates":[-71.07781,42.409929],"type":"Point"}
}