{
  "type": "Feature",
  "properties": {
    "addr:full": "13 3rd St Medford MA 02155",
    "addr:housenumber": "13",
    "addr:postcode": "02155",
    "addr:street": "3Rd St",
    "iso:country": "US",
    "sg:address": "13 3rd St",
    "sg:city": "Medford",
    "sg:classifiers": [
      {
        "category": "Professional",
        "subcategory": "Accounting \u0026 Tax Preparation",
        "type": "Services"
      }
    ],
    "sg:phone": "+1 781 396 8516",
    "sg:postcode": "02155",
    "sg:province": "MA",
    "sg:tags": [
      "return",
      "preparation-business"
    ],
    "wof:name": "Bresnahan Accounting",
    "wof:placetype": "venue"
  },
  "geometry": {"coordinates":[-71.07781,42.409929],"type":"Point"}
}
