{
  "type": "Feature",
  "properties": {
    "iso:country":"US",
    "sg:address":"26 Boutwell Rd",
    "sg:city":"Andover",
    "sg:classifiers":[
        {
            "category":"Professional",
            "subcategory":"Business Services",
            "type":"Services"
        }
    ],
    "sg:phone":"+1   ",
    "sg:postcode":"01810",
    "sg:province":"MA",
    "wof:name":"Bsm Enterprises Inc",
    "wof:placetype":"venue"
},
  "geometry": {"coordinates":[-71.233047,42.665752],"type":"Point"}
}