{
  "type": "Feature",
  "properties": {
    "addr:full": "345 Washington St Stoughton MA 02072",
    "addr:housenumber": "345",
    "addr:postcode": "02072",
    "addr:street": "Washington St",
    "iso:country": "US",
    "sg:address": "345 Washington St",
    "sg:city": "Stoughton",
    "sg:classifiers": [
      {
        "category": "Building \u0026 Trades",
        "subcategory": "Locksmith",
        "type": "Services"
      }
    ],
    "sg:phone": "+1 781 997 0788",
    "sg:postcode": "02072",
    "sg:province": "MA",
    "sg:tags": [
      "key"
    ],
    "wof:name": "1 24 Hour 7 Day Emerg Locksmith",
    "wof:placetype": "venue"
  },
  "geometry": {"coordinates":[-71.101799,42.136799],"type":"Point"}
}
