{
  "type": "Feature",
  "properties": {
    "iso:country":"US",
    "sg:address":"345 Washington St",
    "sg:city":"Stoughton",
    "sg:classifiers":[
        {
            "category":"Building & Trades",
            "subcategory":"Locksmith",
            "type":"Services"
        }
    ],
    "sg:phone":"+1 781 997 0788",
    "sg:postcode":"02072",
    "sg:province":"MA",
    "sg:tags":[
        "key"
    ],
    "wof:name":"1 24 Hour 7 Day Emerg Locksmith",
    "wof:placetype":"venue"
},
  "geometry": {"coordinates":[-71.101799,42.136799],"type":"Point"}
}