{
  "type": "Feature",
  "properties": {
    "addr:full":"97 Lowell Rd Ste 7 Concord MA 01742",
    "addr:housenumber":"97",
    "addr:postcode":"01742",
    "addr:street":"Lowell Rd Ste 7",
    "iso:country":"US",
    "sg:address":"97 Lowell Rd Ste 7",
    "sg:city":"Concord",
    "sg:classifiers":[
        {
            "category":"Professional",
            "subcategory":"Lawyer & Legal Services",
            "type":"Services"
        }
    ],
    "sg:phone":"+1 978 369 4314",
    "sg:postcode":"01742",
    "sg:province":"MA",
    "sg:tags":[
        "attorney",
        "practice"
    ],
    "wof:name":"Mcwalter, Robert E Law Office",
    "wof:placetype":"venue"
},
  "geometry": {"coordinates":[-71.35182500000001,42.463409],"type":"Point"}
}