{
  "type": "Feature",
  "properties": {
    "addr:full":"66 Day St Fitchburg MA 01420",
    "addr:housenumber":"66",
    "addr:postcode":"01420",
    "addr:street":"Day St",
    "iso:country":"US",
    "sg:address":"66 Day St",
    "sg:city":"Fitchburg",
    "sg:classifiers":[
        {
            "category":"Social Services",
            "type":"Services"
        }
    ],
    "sg:phone":"+1 978 345 8501",
    "sg:postcode":"01420",
    "sg:province":"MA",
    "sg:tags":[
        "organization",
        "welfare"
    ],
    "wof:name":"MOC Elder Svc",
    "wof:placetype":"venue"
},
  "geometry": {"coordinates":[-71.795288,42.583113],"type":"Point"}
}