{
  "type": "Feature",
  "properties": {
    "iso:country":"US",
    "sg:address":"29 Endicott St",
    "sg:city":"Worcester",
    "sg:classifiers":[
        {
            "category":"Social Services",
            "subcategory":"Child Care",
            "type":"Services"
        }
    ],
    "sg:phone":"+1 508 751 4160",
    "sg:postcode":"01610",
    "sg:province":"MA",
    "wof:name":"CSR Worcester Family Day",
    "wof:placetype":"venue"
},
  "geometry": {"coordinates":[-71.80417199999999,42.250768],"type":"Point"}
}