{
  "type": "Feature",
  "properties": {
    "iso:country":"US",
    "sg:address":"45 Kilby St",
    "sg:city":"Boston",
    "sg:classifiers":[
        {
            "category":"Manufacturing",
            "subcategory":"Printing",
            "type":"Manufacturing & Wholesale Goods"
        }
    ],
    "sg:phone":"+1 617 742 7900",
    "sg:postcode":"02109",
    "sg:province":"MA",
    "sg:tags":[
        "commercial"
    ],
    "sg:website":"www.allegraboston.com",
    "wof:name":"Allegra Print & Imaging",
    "wof:placetype":"venue"
},
  "geometry": {"coordinates":[-71.05556199999999,42.358295],"type":"Point"}
}