{
  "type": "Feature",
  "properties": {
    "addr:full":"218 Lewis Wharf Boston MA 02110",
    "addr:housenumber":"218",
    "addr:postcode":"02110",
    "addr:street":"Lewis Wharf",
    "iso:country":"US",
    "sg:address":"218 Lewis Wharf",
    "sg:city":"Boston",
    "sg:classifiers":[
        {
            "category":"Professional",
            "subcategory":"Lawyer & Legal Services",
            "type":"Services"
        }
    ],
    "sg:phone":"+1 617 720 2002",
    "sg:postcode":"02110",
    "sg:province":"MA",
    "wof:name":"White Jr Law Offices William M & Associates",
    "wof:placetype":"venue"
},
  "geometry": {"coordinates":[-71.05073400000001,42.36374],"type":"Point"}
}