{
  "type": "Feature",
  "properties": {
    "addr:full": "226 Charles St Malden MA 02148",
    "addr:housenumber": "226",
    "addr:postcode": "02148",
    "addr:street": "Charles St",
    "iso:country": "US",
    "sg:address": "226 Charles St",
    "sg:city": "Malden",
    "sg:classifiers": [
      {
        "category": "Wholesale",
        "subcategory": "Non-durable Goods",
        "type": "Manufacturing \u0026 Wholesale Goods"
      }
    ],
    "sg:phone": "+1 781 321 3037",
    "sg:postcode": "02148",
    "sg:province": "MA",
    "sg:tags": [
      "merchandise-wholesale"
    ],
    "wof:name": "Lins Import Export Inc",
    "wof:placetype": "venue"
  },
  "geometry": {"coordinates":[-71.076102,42.423322],"type":"Point"}
}
