{
  "type": "Feature",
  "properties": {
    "iso:country":"US",
    "sg:address":"226 Charles St",
    "sg:city":"Malden",
    "sg:classifiers":[
        {
            "category":"Wholesale",
            "subcategory":"Non-durable Goods",
            "type":"Manufacturing & Wholesale Goods"
        }
    ],
    "sg:phone":"+1 781 321 3037",
    "sg:postcode":"02148",
    "sg:province":"MA",
    "sg:tags":[
        "merchandise-wholesale"
    ],
    "wof:name":"Lins Import Export Inc",
    "wof:placetype":"venue"
},
  "geometry": {"coordinates":[-71.07610200000001,42.423322],"type":"Point"}
}