{
  "type": "Feature",
  "properties": {
    "addr:full":"37 Woodlawn Ave Wellesley MA 02481",
    "addr:housenumber":"37",
    "addr:postcode":"02481",
    "addr:street":"Woodlawn Ave",
    "iso:country":"US",
    "sg:address":"37 Woodlawn Ave",
    "sg:city":"Wellesley",
    "sg:classifiers":[
        {
            "category":"Professional",
            "subcategory":"Computer Services",
            "type":"Services"
        }
    ],
    "sg:phone":"+1   ",
    "sg:postcode":"02481",
    "sg:province":"MA",
    "sg:tags":[
        "datum"
    ],
    "wof:name":"Class of 1970 Whs",
    "wof:placetype":"venue"
},
  "geometry": {"coordinates":[-71.269903,42.315978],"type":"Point"}
}