{
  "type": "Feature",
  "properties": {
    "addr:full":"25 Robert Dr South Easton MA 02375",
    "addr:housenumber":"25",
    "addr:postcode":"02375",
    "addr:street":"Robert Dr",
    "iso:country":"US",
    "sg:address":"25 Robert Dr",
    "sg:city":"South Easton",
    "sg:classifiers":[
        {
            "category":"Wholesale",
            "subcategory":"Stationery",
            "type":"Manufacturing & Wholesale Goods"
        }
    ],
    "sg:phone":"+1 508 230 8500",
    "sg:postcode":"02375",
    "sg:province":"MA",
    "sg:tags":[
        "card"
    ],
    "wof:name":"Winthrop's Hallmark",
    "wof:placetype":"venue"
},
  "geometry": {"coordinates":[-71.141479,42.025022],"type":"Point"}
}