{
  "type": "Feature",
  "properties": {
    "iso:country":"US",
    "sg:address":"6 Preston Sq",
    "sg:city":"Quincy",
    "sg:classifiers":[
        {
            "category":"Travel",
            "subcategory":"Travel Agent",
            "type":"Entertainment"
        },
        {
            "category":"Marine",
            "type":"Transportation"
        }
    ],
    "sg:phone":"+1 617 536 1999",
    "sg:postcode":"02171",
    "sg:province":"MA",
    "sg:tags":[
        "agency",
        "services-commercial",
        "steamship"
    ],
    "sg:website":"http://www.5star-travel.com",
    "wof:name":"Morebar Company",
    "wof:placetype":"venue"
},
  "geometry": {"coordinates":[-71.02736299999999,42.296843],"type":"Point"}
}