{
  "type": "Feature",
  "properties": {
    "addr:full":"41 Main St Edgartown MA 02539",
    "addr:housenumber":"41",
    "addr:postcode":"02539",
    "addr:street":"Main St",
    "iso:country":"US",
    "sg:address":"41 Main St",
    "sg:city":"Edgartown",
    "sg:classifiers":[
        {
            "category":"Shopping",
            "subcategory":"Clothing, Apparel, & Fashions",
            "type":"Retail Goods"
        }
    ],
    "sg:phone":"+1 508 627 5254",
    "sg:postcode":"02539",
    "sg:province":"MA",
    "wof:name":"Sundog Inc",
    "wof:placetype":"venue"
},
  "geometry": {"coordinates":[-70.513688,41.389734],"type":"Point"}
}