{
  "type": "Feature",
  "properties": {
    "iso:country":"US",
    "sg:address":"174 Orchard St",
    "sg:city":"Millis",
    "sg:classifiers":[
        {
            "category":"Shopping",
            "subcategory":"Computers & Home Electronics",
            "type":"Retail Goods"
        }
    ],
    "sg:phone":"+1 508 376 2995",
    "sg:postcode":"02054",
    "sg:province":"MA",
    "sg:tags":[
        "software"
    ],
    "wof:name":"Mermaid Software Inc",
    "wof:placetype":"venue"
},
  "geometry": {"coordinates":[-71.37993899999999,42.184263],"type":"Point"}
}