{
  "type": "Feature",
  "properties": {
    "iso:country":"US",
    "sg:address":"95 Water St",
    "sg:city":"Bridgewater",
    "sg:classifiers":[
        {
            "category":"Wholesale",
            "subcategory":"Auto Parts",
            "type":"Manufacturing & Wholesale Goods"
        }
    ],
    "sg:phone":"+1 508 697 1660",
    "sg:postcode":"02324",
    "sg:province":"MA",
    "sg:tags":[
        "automobile",
        "rebuilt"
    ],
    "wof:name":"Wood's Auto Parts",
    "wof:placetype":"venue"
},
  "geometry": {"coordinates":[-70.95355600000001,41.985394],"type":"Point"}
}