{
  "type": "Feature",
  "properties": {
    "addr:full": "95 Water St Bridgewater MA 02324",
    "addr:housenumber": "95",
    "addr:postcode": "02324",
    "addr:street": "Water St",
    "iso:country": "US",
    "ovtr:label": "Wood's Auto Parts, 95 Water St Bridgewater MA US",
    "ovtr:similarity": 2.0201640129089355,
    "sg:address": "95 Water St",
    "sg:city": "Bridgewater",
    "sg:classifiers": [
      {
        "category": "Wholesale",
        "subcategory": "Auto Parts",
        "type": "Manufacturing \u0026 Wholesale Goods"
      }
    ],
    "sg:phone": "+1 508 697 1660",
    "sg:postcode": "02324",
    "sg:province": "MA",
    "sg:tags": [
      "automobile",
      "rebuilt"
    ],
    "wof:name": "Wood's Auto Parts",
    "wof:placetype": "venue"
  },
  "geometry": {"coordinates":[-70.953556,41.985394],"type":"Point"}
}
