{
  "type": "Feature",
  "properties": {
    "iso:country":"US",
    "sg:address":"41 Wellman Street",
    "sg:city":"Lowell",
    "sg:classifiers":[
        {
            "category":"Professional",
            "subcategory":"Computer Services",
            "type":"Services"
        }
    ],
    "sg:phone":"+1 206 272 5555",
    "sg:postcode":"01851",
    "sg:province":"MA",
    "sg:tags":[
        "load-balancing",
        "application-delivery",
        "security",
        "remote-access",
        "web-application-security",
        "web-services",
        "optimization",
        "acceleration",
        "high-availability",
        "scalability",
        "failover",
        "virtualization"
    ],
    "sg:website":"http://www.f5.com",
    "wof:name":"F5 Networks",
    "wof:placetype":"venue"
},
  "geometry": {"coordinates":[-71.323297,42.619606],"type":"Point"}
}