{
  "type": "Feature",
  "properties": {
    "addr:full":"3 Washington Sq Haverhill MA 01830",
    "addr:housenumber":"3",
    "addr:postcode":"01830",
    "addr:street":"Washington Sq",
    "iso:country":"US",
    "sg:address":"3 Washington Sq",
    "sg:city":"Haverhill",
    "sg:classifiers":[
        {
            "category":"Social Services",
            "type":"Services"
        }
    ],
    "sg:phone":"+1   ",
    "sg:postcode":"01830",
    "sg:province":"MA",
    "sg:tags":[
        "medical"
    ],
    "wof:name":"Rafferty Cyndia",
    "wof:placetype":"venue"
},
  "geometry": {"coordinates":[-71.08232,42.77384],"type":"Point"}
}