{
  "type": "Feature",
  "properties": {
    "addr:full":"955 E Falmouth Hwy East Falmouth MA 02536",
    "addr:housenumber":"955",
    "addr:postcode":"02536",
    "addr:street":"E Falmouth Hwy",
    "iso:country":"US",
    "sg:address":"955 E Falmouth Hwy",
    "sg:city":"East Falmouth",
    "sg:classifiers":[
        {
            "category":"Building & Trades",
            "subcategory":"Landscaping Services",
            "type":"Services"
        }
    ],
    "sg:phone":"+1 508 833 4781",
    "sg:postcode":"02536",
    "sg:province":"MA",
    "sg:tags":[
        "landscape",
        "contractor"
    ],
    "wof:name":"Greener Image Landscaping",
    "wof:placetype":"venue"
},
  "geometry": {"coordinates":[-70.541011,41.579021],"type":"Point"}
}