{
  "type": "Feature",
  "properties": {
    "addr:full":"20 Canal St Turners Falls MA 01376",
    "addr:housenumber":"20",
    "addr:postcode":"01376",
    "addr:street":"Canal St",
    "iso:country":"US",
    "sg:address":"20 Canal St",
    "sg:city":"Turners Falls",
    "sg:classifiers":[
        {
            "category":"Professional",
            "type":"Services"
        }
    ],
    "sg:phone":"+1 413 863 8566",
    "sg:postcode":"01376",
    "sg:province":"MA",
    "sg:tags":[
        "establishment"
    ],
    "wof:name":"Turners Falls Hydro",
    "wof:placetype":"venue"
},
  "geometry": {"coordinates":[-72.558086,42.609717],"type":"Point"}
}