{
  "type": "Feature",
  "properties": {
    "addr:full":"15 Feeding Hills Rd Southwick MA 01077",
    "addr:housenumber":"15",
    "addr:postcode":"01077",
    "addr:street":"Feeding Hills Rd",
    "iso:country":"US",
    "sg:address":"15 Feeding Hills Rd",
    "sg:city":"Southwick",
    "sg:classifiers":[
        {
            "category":"Professional",
            "subcategory":"Business Services",
            "type":"Services"
        }
    ],
    "sg:phone":"+1 413 569 9978",
    "sg:postcode":"01077",
    "sg:province":"MA",
    "sg:tags":[
        "labeling"
    ],
    "wof:name":"Sandy's Packaging",
    "wof:placetype":"venue"
},
  "geometry": {"coordinates":[-72.76178,42.06237],"type":"Point"}
}