{
  "type": "Feature",
  "properties": {
    "addr:full": "85 Wilbraham Rd Springfield MA 01109",
    "addr:housenumber": "85",
    "addr:postcode": "01109",
    "addr:street": "Wilbraham Rd",
    "iso:country": "US",
    "sg:address": "85 Wilbraham Rd",
    "sg:city": "Springfield",
    "sg:classifiers": [
      {
        "category": "Professional",
        "subcategory": "Business Services",
        "type": "Services"
      }
    ],
    "sg:phone": "+1 413 733 5630",
    "sg:postcode": "01109",
    "sg:province": "MA",
    "sg:tags": [
      "notary"
    ],
    "wof:name": "Alban Insurance",
    "wof:placetype": "venue"
  },
  "geometry": {"coordinates":[-72.560798,42.111524],"type":"Point"}
}
