{
  "type": "Feature",
  "properties": {
    "addr:full": "8 Purchase St Salem MA 01970",
    "addr:housenumber": "8",
    "addr:postcode": "01970",
    "addr:street": "Purchase St",
    "iso:country": "US",
    "sg:address": "8 Purchase St",
    "sg:city": "Salem",
    "sg:classifiers": [
      {
        "category": "Building \u0026 Trades",
        "subcategory": "Landscaping Services",
        "type": "Services"
      }
    ],
    "sg:phone": "+1   ",
    "sg:postcode": "01970",
    "sg:province": "MA",
    "sg:tags": [
      "landscape"
    ],
    "wof:name": "Plants \u0026 Pleasantrees",
    "wof:placetype": "venue"
  },
  "geometry": {"coordinates":[-70.916497,42.520246],"type":"Point"}
}
