{
  "type": "Feature",
  "properties": {
    "iso:country":"US",
    "sg:address":"8 Purchase St",
    "sg:city":"Salem",
    "sg:classifiers":[
        {
            "category":"Building & Trades",
            "subcategory":"Landscaping Services",
            "type":"Services"
        }
    ],
    "sg:phone":"+1   ",
    "sg:postcode":"01970",
    "sg:province":"MA",
    "sg:tags":[
        "landscape"
    ],
    "wof:name":"Plants & Pleasantrees",
    "wof:placetype":"venue"
},
  "geometry": {"coordinates":[-70.91649700000001,42.520246],"type":"Point"}
}