{
  "type": "Feature",
  "properties": {
    "iso:country":"US",
    "sg:address":"376 Russell St",
    "sg:city":"Hadley",
    "sg:classifiers":[
        {
            "category":"Restaurant",
            "type":"Food & Drink"
        }
    ],
    "sg:menulink":"http://www.allmenus.com/ma/hadley/173248-wendys/menu/",
    "sg:phone":"+1 413 586 4885",
    "sg:postcode":"01035",
    "sg:province":"MA",
    "sg:tags":[
        "burger",
        "american",
        "soup"
    ],
    "wof:name":"Wendy's",
    "wof:placetype":"venue"
},
  "geometry": {"coordinates":[-72.549639,42.359285],"type":"Point"}
}