{
  "type": "Feature",
  "properties": {
    "addr:full":"1157 Slade St Fall River MA 02724",
    "addr:housenumber":"1157",
    "addr:postcode":"02724",
    "addr:street":"Slade St",
    "iso:country":"US",
    "sg:address":"1157 Slade St",
    "sg:city":"Fall River",
    "sg:classifiers":[
        {
            "category":"Shopping",
            "type":"Retail Goods"
        }
    ],
    "sg:phone":"+1 508 679 5385",
    "sg:postcode":"02724",
    "sg:province":"MA",
    "sg:tags":[
        "equipment",
        "house",
        "cleaning",
        "supply"
    ],
    "wof:name":"Fuller Brush Independent Distr",
    "wof:placetype":"venue"
},
  "geometry": {"coordinates":[-71.166837,41.684157],"type":"Point"}
}