{
  "type": "Feature",
  "properties": {
    "iso:country":"US",
    "sg:address":"265 Taunton Ave",
    "sg:city":"Seekonk",
    "sg:classifiers":[
        {
            "category":"Retail",
            "subcategory":"Car Wash",
            "type":"Services"
        }
    ],
    "sg:phone":"+1 508 336 7232",
    "sg:postcode":"02771",
    "sg:province":"MA",
    "wof:name":"Anthony's Auto Reconditioning",
    "wof:placetype":"venue"
},
  "geometry": {"coordinates":[-71.331497,41.826199],"type":"Point"}
}