{
  "type": "Feature",
  "properties": {
    "addr:full":"18 A St Burlington MA 01803",
    "addr:housenumber":"18",
    "addr:postcode":"01803",
    "addr:street":"A St",
    "iso:country":"US",
    "sg:address":"18 A St",
    "sg:city":"Burlington",
    "sg:classifiers":[
        {
            "category":"Manufacturing",
            "subcategory":"Tools & Machinery",
            "type":"Manufacturing & Wholesale Goods"
        }
    ],
    "sg:phone":"+1 781 272 3750",
    "sg:postcode":"01803",
    "sg:province":"MA",
    "sg:tags":[
        "ind",
        "general"
    ],
    "wof:name":"Galaxie Laboratory",
    "wof:placetype":"venue"
},
  "geometry": {"coordinates":[-71.227317,42.498036],"type":"Point"}
}