{
  "type": "Feature",
  "properties": {
    "iso:country":"US",
    "sg:address":"312 Salem St",
    "sg:city":"Medford",
    "sg:classifiers":[
        {
            "category":"Shopping",
            "subcategory":"Pets & Pet Supplies",
            "type":"Retail Goods"
        }
    ],
    "sg:phone":"+1 781 393 5877",
    "sg:postcode":"02155",
    "sg:province":"MA",
    "sg:tags":[
        "groomers"
    ],
    "sg:website":"www.happyhoundspetsalon.com",
    "wof:name":"Happy Hounds Pet Salon",
    "wof:placetype":"venue"
},
  "geometry": {"coordinates":[-71.09788399999999,42.421222],"type":"Point"}
}