{
  "type": "Feature",
  "properties": {
    "iso:country":"US",
    "sg:address":"11 Massasoit Dr",
    "sg:city":"Leicester",
    "sg:classifiers":[
        {
            "category":"Professional",
            "subcategory":"Business Services",
            "type":"Services"
        }
    ],
    "sg:phone":"+1   ",
    "sg:postcode":"01524",
    "sg:province":"MA",
    "wof:name":"Interiors By Christine",
    "wof:placetype":"venue"
},
  "geometry": {"coordinates":[-71.892684,42.247249],"type":"Point"}
}