{
  "type": "Feature",
  "properties": {
    "iso:country":"US",
    "sg:address":"15 Union Square",
    "sg:city":"Somerville",
    "sg:classifiers":[
        {
            "category":"Food & Beverages",
            "subcategory":"Groceries & Convenience Stores",
            "type":"Retail Goods"
        }
    ],
    "sg:phone":"+1 617 628 1137",
    "sg:postcode":"02143",
    "sg:province":"MA",
    "wof:name":"Mid-nite Convenience",
    "wof:placetype":"venue"
},
  "geometry": {"coordinates":[-71.09520000000001,42.379501],"type":"Point"}
}