{
  "type": "Feature",
  "properties": {
    "addr:full":"6 Akeson Rd Woburn MA 01801",
    "addr:housenumber":"6",
    "addr:postcode":"01801",
    "addr:street":"Akeson Rd",
    "iso:country":"US",
    "sg:address":"6 Akeson Rd",
    "sg:city":"Woburn",
    "sg:classifiers":[
        {
            "category":"Bus Charters",
            "type":"Transportation"
        }
    ],
    "sg:phone":"+1 781 938 9404",
    "sg:postcode":"01801",
    "sg:province":"MA",
    "sg:tags":[
        "rental"
    ],
    "wof:name":"Allen Coach LLC",
    "wof:placetype":"venue"
},
  "geometry": {"coordinates":[-71.16694,42.47706],"type":"Point"}
}