{
  "type": "Feature",
  "properties": {
    "addr:full": "719 Adams St North Adams MA 01267",
    "addr:housenumber": "719",
    "addr:postcode": "01267",
    "addr:street": "Adams St",
    "iso:country": "US",
    "sg:address": "719 Adams St",
    "sg:city": "North Adams",
    "sg:classifiers": [
      {
        "category": "Personal",
        "subcategory": "Beauty Salon",
        "type": "Services"
      }
    ],
    "sg:phone": "+1 413 663 6345",
    "sg:postcode": "01267",
    "sg:province": "MA",
    "sg:tags": [
      "shop"
    ],
    "wof:name": "Michele's Hair Styling Salon",
    "wof:placetype": "venue"
  },
  "geometry": {"coordinates":[-73.191232,42.70605],"type":"Point"}
}
