{
  "type": "Feature",
  "properties": {
    "addr:full":"274 Main St Reading MA 01867",
    "addr:housenumber":"274",
    "addr:postcode":"01867",
    "addr:street":"Main St",
    "iso:country":"US",
    "sg:address":"274 Main St",
    "sg:city":"Reading",
    "sg:classifiers":[
        {
            "category":"Professional",
            "subcategory":"Lawyer & Legal Services",
            "type":"Services"
        }
    ],
    "sg:phone":"+1 781 942 0200",
    "sg:postcode":"01867",
    "sg:province":"MA",
    "wof:name":"Shor Robert Bartley Atty",
    "wof:placetype":"venue"
},
  "geometry": {"coordinates":[-71.10369900000001,42.515301],"type":"Point"}
}