{
  "type": "Feature",
  "properties": {
    "addr:full":"7 Puritan Rd Danvers MA 01923",
    "addr:housenumber":"7",
    "addr:postcode":"01923",
    "addr:street":"Puritan Rd",
    "iso:country":"US",
    "sg:address":"7 Puritan Rd",
    "sg:city":"Danvers",
    "sg:classifiers":[
        {
            "category":"Sports & Exercise",
            "subcategory":"Gym",
            "type":"Entertainment"
        }
    ],
    "sg:phone":"+1 978 777 1880",
    "sg:postcode":"01923",
    "sg:province":"MA",
    "sg:tags":[
        "club",
        "health",
        "studio",
        "gymnasium"
    ],
    "wof:name":"Circuit Studio",
    "wof:placetype":"venue"
},
  "geometry": {"coordinates":[-70.932636,42.569921],"type":"Point"}
}