{
  "type": "Feature",
  "properties": {
    "iso:country":"US",
    "sg:address":"199 Worcester-Providence Tpke",
    "sg:city":"Sutton",
    "sg:classifiers":[
        {
            "category":"Building & Trades",
            "subcategory":"Construction",
            "type":"Services"
        }
    ],
    "sg:phone":"+1 508 865 7645",
    "sg:postcode":"01590",
    "sg:province":"MA",
    "sg:tags":[
        "shed",
        "utility"
    ],
    "wof:name":"Skip's Outdoor Accents Sheds",
    "wof:placetype":"venue"
},
  "geometry": {"coordinates":[-71.73456400000001,42.159275],"type":"Point"}
}