{
  "type": "Feature",
  "properties": {
    "iso:country":"US",
    "sg:address":"118 Granite Ave",
    "sg:city":"Boston",
    "sg:classifiers":[
        {
            "category":"Building & Trades",
            "subcategory":"Construction",
            "type":"Services"
        }
    ],
    "sg:phone":"+1   ",
    "sg:postcode":"02124",
    "sg:province":"MA",
    "sg:tags":[
        "house"
    ],
    "wof:name":"Three Lakes Construction",
    "wof:placetype":"venue"
},
  "geometry": {"coordinates":[-71.05438100000001,42.279892],"type":"Point"}
}