{
  "type": "Feature",
  "properties": {
    "addr:full": "118 Granite Ave Boston MA 02124",
    "addr:housenumber": "118",
    "addr:postcode": "02124",
    "addr:street": "Granite Ave",
    "iso:country": "US",
    "sg:address": "118 Granite Ave",
    "sg:city": "Boston",
    "sg:classifiers": [
      {
        "category": "Building \u0026 Trades",
        "subcategory": "Construction",
        "type": "Services"
      }
    ],
    "sg:phone": "+1   ",
    "sg:postcode": "02124",
    "sg:province": "MA",
    "sg:tags": [
      "house"
    ],
    "wof:name": "Three Lakes Construction",
    "wof:placetype": "venue"
  },
  "geometry": {"coordinates":[-71.054381,42.279892],"type":"Point"}
}
