{
  "type": "Feature",
  "properties": {
    "iso:country":"US",
    "sg:address":"1570 Boston Provdnce Tpke",
    "sg:city":"Norwood",
    "sg:classifiers":[
        {
            "category":"Shopping",
            "subcategory":"Mobile Phones",
            "type":"Retail Goods"
        }
    ],
    "sg:phone":"+1 781 278 8880",
    "sg:postcode":"02062",
    "sg:province":"MA",
    "wof:name":"Odyssey Solutions Inc - CLOSED",
    "wof:placetype":"venue"
},
  "geometry": {"coordinates":[-71.198898,42.164799],"type":"Point"}
}