{
  "type": "Feature",
  "properties": {
    "addr:full":"1 Campbell Path Marshfield MA 02050",
    "addr:housenumber":"1",
    "addr:postcode":"02050",
    "addr:street":"Campbell Path",
    "iso:country":"US",
    "sg:address":"1 Campbell Path",
    "sg:city":"Marshfield",
    "sg:classifiers":[
        {
            "category":"Home & Garden",
            "subcategory":"Building Materials",
            "type":"Retail Goods"
        }
    ],
    "sg:phone":"+1 781 834 8345",
    "sg:postcode":"02050",
    "sg:province":"MA",
    "sg:tags":[
        "door"
    ],
    "wof:name":"Campbell Door Co",
    "wof:placetype":"venue"
},
  "geometry": {"coordinates":[-70.684754,42.073679],"type":"Point"}
}