{
  "type": "Feature",
  "properties": {
    "addr:full": "10 Providence St Millbury MA 01527",
    "addr:housenumber": "10",
    "addr:postcode": "01527",
    "addr:street": "Providence St",
    "iso:country": "US",
    "sg:address": "10 Providence St",
    "sg:city": "Millbury",
    "sg:classifiers": [
      {
        "category": "Restaurant",
        "type": "Food \u0026 Drink"
      }
    ],
    "sg:phone": "+1 508 865 3889",
    "sg:postcode": "01527",
    "sg:province": "MA",
    "wof:name": "Dino's Of Sutton",
    "wof:placetype": "venue"
  },
  "geometry": {"coordinates":[-71.753609,42.19236],"type":"Point"}
}
