{
  "type": "Feature",
  "properties": {
    "iso:country":"US",
    "sg:address":"10 Providence St",
    "sg:city":"Millbury",
    "sg:classifiers":[
        {
            "category":"Restaurant",
            "type":"Food & Drink"
        }
    ],
    "sg:phone":"+1 508 865 3889",
    "sg:postcode":"01527",
    "sg:province":"MA",
    "wof:name":"Dino's Of Sutton",
    "wof:placetype":"venue"
},
  "geometry": {"coordinates":[-71.753609,42.19236],"type":"Point"}
}