{
  "type": "Feature",
  "properties": {
    "addr:full":"99 Main St Rockport MA 01966",
    "addr:housenumber":"99",
    "addr:postcode":"01966",
    "addr:street":"Main St",
    "iso:country":"US",
    "sg:address":"99 Main St",
    "sg:city":"Rockport",
    "sg:classifiers":[
        {
            "category":"Place Of Worship",
            "type":"Public Place"
        }
    ],
    "sg:phone":"+1 978 546 5834",
    "sg:postcode":"01966",
    "sg:province":"MA",
    "sg:tags":[
        "church"
    ],
    "wof:name":"Love Healing Center",
    "wof:placetype":"venue"
},
  "geometry": {"coordinates":[-70.623169,42.654541],"type":"Point"}
}