{
  "type": "Feature",
  "properties": {
    "iso:country":"US",
    "sg:address":"40 Strafello Dr",
    "sg:city":"Avon",
    "sg:classifiers":[
        {
            "category":"Wholesale",
            "subcategory":"Fruits & Vegetables",
            "type":"Manufacturing & Wholesale Goods"
        }
    ],
    "sg:phone":"+1 508 583 2277",
    "sg:postcode":"02322",
    "sg:province":"MA",
    "wof:name":"Cambridge Farms Inc",
    "wof:placetype":"venue"
},
  "geometry": {"coordinates":[-71.060119,42.132241],"type":"Point"}
}