{
  "type": "Feature",
  "properties": {
    "iso:country":"US",
    "sg:address":"13 Industrial Dr",
    "sg:city":"Mattapoisett",
    "sg:classifiers":[
        {
            "category":"Retail",
            "subcategory":"Auto Repair",
            "type":"Services"
        }
    ],
    "sg:phone":"+1 508 758 9414",
    "sg:postcode":"02739",
    "sg:province":"MA",
    "sg:tags":[
        "truck"
    ],
    "wof:name":"Mattapoisett Truck Equipment",
    "wof:placetype":"venue"
},
  "geometry": {"coordinates":[-70.81273299999999,41.681004],"type":"Point"}
}