{
  "type": "Feature",
  "properties": {
    "iso:country":"US",
    "sg:address":"88 Great Rd",
    "sg:city":"Bedford",
    "sg:classifiers":[
        {
            "category":"Banks & Credit Unions",
            "subcategory":"Investment Brokerage",
            "type":"Services"
        }
    ],
    "sg:phone":"+1 781 275 6224",
    "sg:postcode":"01730",
    "sg:province":"MA",
    "sg:tags":[
        "security"
    ],
    "wof:name":"Edward Jones Co",
    "wof:placetype":"venue"
},
  "geometry": {"coordinates":[-71.27927800000001,42.491971],"type":"Point"}
}