{
  "type": "Feature",
  "properties": {
    "addr:full": "88 Great Rd Bedford MA 01730",
    "addr:housenumber": "88",
    "addr:postcode": "01730",
    "addr:street": "Great Rd",
    "iso:country": "US",
    "sg:address": "88 Great Rd",
    "sg:city": "Bedford",
    "sg:classifiers": [
      {
        "category": "Banks \u0026 Credit Unions",
        "subcategory": "Investment Brokerage",
        "type": "Services"
      }
    ],
    "sg:phone": "+1 781 275 6224",
    "sg:postcode": "01730",
    "sg:province": "MA",
    "sg:tags": [
      "security"
    ],
    "wof:name": "Edward Jones Co",
    "wof:placetype": "venue"
  },
  "geometry": {"coordinates":[-71.279278,42.491971],"type":"Point"}
}
