{
  "type": "Feature",
  "properties": {
    "addr:full": "30 Laurel Street Malden MA 02148",
    "addr:housenumber": "30",
    "addr:postcode": "02148",
    "addr:street": "Laurel Street",
    "iso:country": "US",
    "sg:address": "30 Laurel Street",
    "sg:city": "Malden",
    "sg:classifiers": [
      {
        "category": "Education",
        "subcategory": "School",
        "type": "Public Place"
      }
    ],
    "sg:phone": "+1 781 321 5688",
    "sg:postcode": "02148",
    "sg:province": "MA",
    "sg:tags": [
      "high",
      "middle",
      "elementary"
    ],
    "wof:name": "Mystic Valley Regional Middle School",
    "wof:placetype": "venue"
  },
  "geometry": {"coordinates":[-71.044538,42.434383],"type":"Point"}
}
