{
  "type": "Feature",
  "properties": {
    "iso:country":"US",
    "sg:address":"177 Main St",
    "sg:city":"Wareham",
    "sg:classifiers":[
        {
            "category":"Professional",
            "subcategory":"Art Services",
            "type":"Services"
        }
    ],
    "sg:phone":"+1 508 291 4144",
    "sg:postcode":"02571",
    "sg:province":"MA",
    "sg:tags":[
        "artist"
    ],
    "wof:name":"Sail Away Studio",
    "wof:placetype":"venue"
},
  "geometry": {"coordinates":[-70.714465,41.757729],"type":"Point"}
}