{
  "type": "Feature",
  "properties": {
    "addr:full":"44 Grove St Somerville MA 02144",
    "addr:housenumber":"44",
    "addr:postcode":"02144",
    "addr:street":"Grove St",
    "iso:country":"US",
    "sg:address":"44 Grove St",
    "sg:city":"Somerville",
    "sg:classifiers":[
        {
            "category":"Professional",
            "subcategory":"Advertising",
            "type":"Services"
        }
    ],
    "sg:phone":"+1 617 628 0800",
    "sg:postcode":"02144",
    "sg:province":"MA",
    "sg:tags":[
        "counselor"
    ],
    "wof:name":"Rattle",
    "wof:placetype":"venue"
},
  "geometry": {"coordinates":[-71.11983499999999,42.396757],"type":"Point"}
}