{
  "type": "Feature",
  "properties": {
    "addr:full":"1656 Massachusetts Ave Lexington MA 02420",
    "addr:housenumber":"1656",
    "addr:postcode":"02420",
    "addr:street":"Massachusetts Ave",
    "iso:country":"US",
    "sg:address":"1656 Massachusetts Ave",
    "sg:city":"Lexington",
    "sg:classifiers":[
        {
            "category":"Banks & Credit Unions",
            "subcategory":"Investment Brokerage",
            "type":"Services"
        }
    ],
    "sg:phone":"+1 781 863 8100",
    "sg:postcode":"02420",
    "sg:province":"MA",
    "sg:tags":[
        "advisory",
        "financial"
    ],
    "wof:name":"Linsco Private Ledger",
    "wof:placetype":"venue"
},
  "geometry": {"coordinates":[-71.22490999999999,42.446563],"type":"Point"}
}