{
  "type": "Feature",
  "properties": {
    "iso:country":"US",
    "sg:address":"63 Enterprise Rd",
    "sg:city":"Hyannis",
    "sg:classifiers":[
        {
            "category":"Retail",
            "subcategory":"Auto Repair",
            "type":"Services"
        }
    ],
    "sg:phone":"+1 508 771 7597",
    "sg:postcode":"02601",
    "sg:province":"MA",
    "sg:tags":[
        "body",
        "automobile",
        "painting"
    ],
    "sg:website":"www.capecodcollision.com",
    "wof:name":"Cape Cod Collision",
    "wof:placetype":"venue"
},
  "geometry": {"coordinates":[-70.30185,41.668573],"type":"Point"}
}