{
  "type": "Feature",
  "properties": {
    "iso:country":"US",
    "sg:address":"263 Grand Ave",
    "sg:city":"Falmouth",
    "sg:classifiers":[
        {
            "category":"Travel",
            "subcategory":"Hotels & Motels",
            "type":"Entertainment"
        }
    ],
    "sg:phone":"+1 508 540 4120",
    "sg:postcode":"02540",
    "sg:province":"MA",
    "sg:website":"http://www.seasideinnfalmouth.com",
    "wof:name":"Seaside Inn",
    "wof:placetype":"venue"
},
  "geometry": {"coordinates":[-70.59638200000001,41.54533],"type":"Point"}
}