{
  "type": "Feature",
  "properties": {
    "addr:full": "263 Grand Ave Falmouth MA 02540",
    "addr:housenumber": "263",
    "addr:postcode": "02540",
    "addr:street": "Grand Ave",
    "iso:country": "US",
    "sg:address": "263 Grand Ave",
    "sg:city": "Falmouth",
    "sg:classifiers": [
      {
        "category": "Travel",
        "subcategory": "Hotels \u0026 Motels",
        "type": "Entertainment"
      }
    ],
    "sg:phone": "+1 508 540 4120",
    "sg:postcode": "02540",
    "sg:province": "MA",
    "sg:website": "http://www.seasideinnfalmouth.com",
    "wof:name": "Seaside Inn",
    "wof:placetype": "venue"
  },
  "geometry": {"coordinates":[-70.596382,41.54533],"type":"Point"}
}
