{
  "type": "Feature",
  "properties": {
    "iso:country":"US",
    "sg:address":"227 E Main St",
    "sg:city":"Gloucester",
    "sg:classifiers":[
        {
            "category":"Home & Garden",
            "subcategory":"Building Materials",
            "type":"Retail Goods"
        }
    ],
    "sg:phone":"+1 978 283 5369",
    "sg:postcode":"01930",
    "sg:province":"MA",
    "sg:tags":[
        "hardwood"
    ],
    "wof:name":"Cape Ann Hardwood Supply",
    "wof:placetype":"venue"
},
  "geometry": {"coordinates":[-70.65105699999999,42.608728],"type":"Point"}
}