{
  "type": "Feature",
  "properties": {
    "addr:full": "72 Hosmer St Marlborough MA 01752",
    "addr:housenumber": "72",
    "addr:postcode": "01752",
    "addr:street": "Hosmer St",
    "iso:country": "US",
    "sg:address": "72 Hosmer St",
    "sg:city": "Marlborough",
    "sg:classifiers": [
      {
        "category": "Wholesale",
        "subcategory": "Durable Goods \u0026 Equipment",
        "type": "Manufacturing \u0026 Wholesale Goods"
      }
    ],
    "sg:phone": "+1 508 485 5550",
    "sg:postcode": "01752",
    "sg:province": "MA",
    "sg:tags": [
      "representative",
      "manufacturer"
    ],
    "wof:name": "Ben-Tech",
    "wof:placetype": "venue"
  },
  "geometry": {"coordinates":[-71.533054,42.352522],"type":"Point"}
}
