{
  "type": "Feature",
  "properties": {
    "iso:country":"US",
    "sg:address":"72 Hosmer St",
    "sg:city":"Marlborough",
    "sg:classifiers":[
        {
            "category":"Wholesale",
            "subcategory":"Durable Goods & Equipment",
            "type":"Manufacturing & Wholesale Goods"
        }
    ],
    "sg:phone":"+1 508 485 5550",
    "sg:postcode":"01752",
    "sg:province":"MA",
    "sg:tags":[
        "representative",
        "manufacturer"
    ],
    "wof:name":"Ben-Tech",
    "wof:placetype":"venue"
},
  "geometry": {"coordinates":[-71.53305400000001,42.352522],"type":"Point"}
}