{
  "type": "Feature",
  "properties": {
    "addr:full": "24 N Brookfield Rd Barre MA 01005",
    "addr:housenumber": "24",
    "addr:postcode": "01005",
    "addr:street": "N Brookfield Rd",
    "iso:country": "US",
    "ovtr:label": "Shear Expressions Hair Design, 24 N Brookfield Rd Barre MA US",
    "ovtr:similarity": 2.045362949371338,
    "sg:address": "24 N Brookfield Rd",
    "sg:city": "Barre",
    "sg:classifiers": [
      {
        "category": "Personal",
        "subcategory": "Beauty Salon",
        "type": "Services"
      }
    ],
    "sg:phone": "+1 978 355 4467",
    "sg:postcode": "01005",
    "sg:province": "MA",
    "sg:tags": [
      "hair",
      "stylist"
    ],
    "wof:name": "Shear Expressions Hair Design",
    "wof:placetype": "venue"
  },
  "geometry": {"coordinates":[-72.108434,42.378357],"type":"Point"}
}
