{
  "type": "Feature",
  "properties": {
    "iso:country":"US",
    "sg:address":"24 N Brookfield Rd",
    "sg:city":"Barre",
    "sg:classifiers":[
        {
            "category":"Personal",
            "subcategory":"Beauty Salon",
            "type":"Services"
        }
    ],
    "sg:phone":"+1 978 355 4467",
    "sg:postcode":"01005",
    "sg:province":"MA",
    "sg:tags":[
        "hair",
        "stylist"
    ],
    "wof:name":"Shear Expressions Hair Design",
    "wof:placetype":"venue"
},
  "geometry": {"coordinates":[-72.108434,42.378357],"type":"Point"}
}