{
  "type": "Feature",
  "properties": {
    "addr:full": "513 Codman Hill Rd Boxborough MA 01719",
    "addr:housenumber": "513",
    "addr:postcode": "01719",
    "addr:street": "Codman Hill Rd",
    "iso:country": "US",
    "sg:address": "513 Codman Hill Rd",
    "sg:city": "Boxborough",
    "sg:classifiers": [
      {
        "category": "Retail",
        "subcategory": "Laundry \u0026 Dry Cleaning",
        "type": "Services"
      }
    ],
    "sg:phone": "+1 978 264 4130",
    "sg:postcode": "01719",
    "sg:province": "MA",
    "sg:tags": [
      "cleaners",
      "rug",
      "carpet"
    ],
    "wof:name": "E J Carpet \u0026 Upholstery Clng",
    "wof:placetype": "venue"
  },
  "geometry": {"coordinates":[-71.560076,42.474395],"type":"Point"}
}
