{
  "type": "Feature",
  "properties": {
    "iso:country":"US",
    "sg:address":"513 Codman Hill Rd",
    "sg:city":"Boxborough",
    "sg:classifiers":[
        {
            "category":"Retail",
            "subcategory":"Laundry & Dry Cleaning",
            "type":"Services"
        }
    ],
    "sg:phone":"+1 978 264 4130",
    "sg:postcode":"01719",
    "sg:province":"MA",
    "sg:tags":[
        "cleaners",
        "rug",
        "carpet"
    ],
    "wof:name":"E J Carpet & Upholstery Clng",
    "wof:placetype":"venue"
},
  "geometry": {"coordinates":[-71.560076,42.474395],"type":"Point"}
}