{
  "type": "Feature",
  "properties": {
    "iso:country":"US",
    "sg:address":"171 Goddard Avenue",
    "sg:city":"Brookline",
    "sg:classifiers":[
        {
            "category":"Building & Trades",
            "subcategory":"Construction",
            "type":"Services"
        }
    ],
    "sg:phone":"+1 617 738 6218",
    "sg:postcode":"02445",
    "sg:province":"MA",
    "sg:tags":[
        "contractor"
    ],
    "wof:name":"Floyd C E Company",
    "wof:placetype":"venue"
},
  "geometry": {"coordinates":[-71.130606,42.316059],"type":"Point"}
}