{
  "type": "Feature",
  "properties": {
    "addr:full":"102 Duff St Watertown MA 02472",
    "addr:housenumber":"102",
    "addr:postcode":"02472",
    "addr:street":"Duff St",
    "iso:country":"US",
    "sg:address":"102 Duff St",
    "sg:city":"Watertown",
    "sg:classifiers":[
        {
            "category":"Professional",
            "subcategory":"Computer Services",
            "type":"Services"
        }
    ],
    "sg:phone":"+1 617 923 0463",
    "sg:postcode":"02472",
    "sg:province":"MA",
    "sg:tags":[
        "website",
        "design"
    ],
    "sg:website":"www.outnet.com",
    "wof:name":"Outnet",
    "wof:placetype":"venue"
},
  "geometry": {"coordinates":[-71.194553,42.378344],"type":"Point"}
}