{
  "type": "Feature",
  "properties": {
    "iso:country":"US",
    "sg:address":"366 Massachusetts Ave",
    "sg:city":"Arlington",
    "sg:classifiers":[
        {
            "category":"Personal",
            "type":"Services"
        }
    ],
    "sg:phone":"+1 781 648 0914",
    "sg:postcode":"02474",
    "sg:province":"MA",
    "sg:tags":[
        "therapist",
        "massage"
    ],
    "wof:name":"Arlington Reiki Assoc",
    "wof:placetype":"venue"
},
  "geometry": {"coordinates":[-71.14828799999999,42.4114],"type":"Point"}
}