{
  "type": "Feature",
  "properties": {
    "addr:full":"11 Emerson Rd Wellesley MA 02481",
    "addr:housenumber":"11",
    "addr:postcode":"02481",
    "addr:street":"Emerson Rd",
    "iso:country":"US",
    "sg:address":"11 Emerson Rd",
    "sg:city":"Wellesley",
    "sg:classifiers":[
        {
            "category":"Recreation",
            "type":"Entertainment"
        }
    ],
    "sg:phone":"+1   ",
    "sg:postcode":"02481",
    "sg:province":"MA",
    "wof:name":"Maximum Performance",
    "wof:placetype":"venue"
},
  "geometry": {"coordinates":[-71.25851400000001,42.320947],"type":"Point"}
}