{
  "type": "Feature",
  "properties": {
    "addr:full":"3 Stadler St Belchertown MA 01007",
    "addr:housenumber":"3",
    "addr:postcode":"01007",
    "addr:street":"Stadler St",
    "iso:country":"US",
    "sg:address":"3 Stadler St",
    "sg:city":"Belchertown",
    "sg:classifiers":[
        {
            "category":"Education",
            "subcategory":"Dance Studio",
            "type":"Public Place"
        }
    ],
    "sg:phone":"+1 413 323 0096",
    "sg:postcode":"01007",
    "sg:province":"MA",
    "wof:name":"Creative Dance",
    "wof:placetype":"venue"
},
  "geometry": {"coordinates":[-72.409842,42.272288],"type":"Point"}
}