{
  "type": "Feature",
  "properties": {
    "iso:country":"US",
    "sg:address":"69 Sherwood Ave",
    "sg:city":"Westfield",
    "sg:classifiers":[
        {
            "category":"Building & Trades",
            "subcategory":"Plumbing",
            "type":"Services"
        }
    ],
    "sg:phone":"+1 413 572 1096",
    "sg:postcode":"01085",
    "sg:province":"MA",
    "sg:tags":[
        "plumbing",
        "contractor"
    ],
    "wof:name":"John F Pitoniak Plumbing & Htg",
    "wof:placetype":"venue"
},
  "geometry": {"coordinates":[-72.70256500000001,42.134552],"type":"Point"}
}