{
  "type": "Feature",
  "properties": {
    "addr:full": "69 Sherwood Ave Westfield MA 01085",
    "addr:housenumber": "69",
    "addr:postcode": "01085",
    "addr:street": "Sherwood Ave",
    "iso:country": "US",
    "sg:address": "69 Sherwood Ave",
    "sg:city": "Westfield",
    "sg:classifiers": [
      {
        "category": "Building \u0026 Trades",
        "subcategory": "Plumbing",
        "type": "Services"
      }
    ],
    "sg:phone": "+1 413 572 1096",
    "sg:postcode": "01085",
    "sg:province": "MA",
    "sg:tags": [
      "plumbing",
      "contractor"
    ],
    "wof:name": "John F Pitoniak Plumbing \u0026 Htg",
    "wof:placetype": "venue"
  },
  "geometry": {"coordinates":[-72.702565,42.134552],"type":"Point"}
}
