{
  "type": "Feature",
  "properties": {
    "addr:full": "93 Fairfax Rd Worcester MA 01610",
    "addr:housenumber": "93",
    "addr:postcode": "01610",
    "addr:street": "Fairfax Rd",
    "iso:country": "US",
    "sg:address": "93 Fairfax Rd",
    "sg:city": "Worcester",
    "sg:classifiers": [
      {
        "category": "Manufacturing",
        "subcategory": "Retail Goods",
        "type": "Manufacturing \u0026 Wholesale Goods"
      }
    ],
    "sg:phone": "+1   ",
    "sg:postcode": "01610",
    "sg:province": "MA",
    "sg:tags": [
      "pencil",
      "mfg"
    ],
    "wof:name": "Pens By Charles",
    "wof:placetype": "venue"
  },
  "geometry": {"coordinates":[-71.798396,42.242988],"type":"Point"}
}
