{
  "type": "Feature",
  "properties": {
    "addr:full": "99 Mill St Springfield MA 01108",
    "addr:housenumber": "99",
    "addr:postcode": "01108",
    "addr:street": "Mill St",
    "iso:country": "US",
    "sg:address": "99 Mill St",
    "sg:city": "Springfield",
    "sg:classifiers": [
      {
        "category": "Building \u0026 Trades",
        "subcategory": "Construction",
        "type": "Services"
      }
    ],
    "sg:phone": "+1 413 746 9262",
    "sg:postcode": "01108",
    "sg:province": "MA",
    "sg:tags": [
      "painter"
    ],
    "wof:name": "A A Painting",
    "wof:placetype": "venue"
  },
  "geometry": {"coordinates":[-72.576067,42.091059],"type":"Point"}
}
