{
  "type": "Feature",
  "properties": {
    "addr:full": "190 High St Ipswich MA 01938",
    "addr:housenumber": "190",
    "addr:postcode": "01938",
    "addr:street": "High St",
    "iso:country": "US",
    "sg:address": "190 High St",
    "sg:city": "Ipswich",
    "sg:classifiers": [
      {
        "category": "Shopping",
        "subcategory": "Crafts \u0026 Fabrics",
        "type": "Retail Goods"
      }
    ],
    "sg:phone": "+1 978 356 5551",
    "sg:postcode": "01938",
    "sg:province": "MA",
    "sg:tags": [
      "store"
    ],
    "sg:website": "www.loomnshuttle.com",
    "wof:name": "Loom'n Shuttle",
    "wof:placetype": "venue"
  },
  "geometry": {"coordinates":[-70.854401,42.691299],"type":"Point"}
}
