{
  "type": "Feature",
  "properties": {
    "iso:country":"US",
    "sg:address":"190 High St",
    "sg:city":"Ipswich",
    "sg:classifiers":[
        {
            "category":"Shopping",
            "subcategory":"Crafts & Fabrics",
            "type":"Retail Goods"
        }
    ],
    "sg:phone":"+1 978 356 5551",
    "sg:postcode":"01938",
    "sg:province":"MA",
    "sg:tags":[
        "store"
    ],
    "sg:website":"www.loomnshuttle.com",
    "wof:name":"Loom'n Shuttle",
    "wof:placetype":"venue"
},
  "geometry": {"coordinates":[-70.854401,42.691299],"type":"Point"}
}