{
  "type": "Feature",
  "properties": {
    "iso:country":"US",
    "sg:address":"237 King St",
    "sg:city":"Northampton",
    "sg:classifiers":[
        {
            "category":"Professional",
            "type":"Services"
        }
    ],
    "sg:phone":"+1 413 582 0025",
    "sg:postcode":"01060",
    "sg:province":"MA",
    "sg:tags":[
        "establishment"
    ],
    "wof:name":"Fsp",
    "wof:placetype":"venue"
},
  "geometry": {"coordinates":[-72.63349599999999,42.328025],"type":"Point"}
}