{
  "type": "Feature",
  "properties": {
    "addr:full":"376 Granite Ave Milton MA 02186",
    "addr:housenumber":"376",
    "addr:postcode":"02186",
    "addr:street":"Granite Ave",
    "iso:country":"US",
    "sg:address":"376 Granite Ave",
    "sg:city":"Milton",
    "sg:classifiers":[
        {
            "category":"Retail",
            "subcategory":"Auto Repair",
            "type":"Services"
        }
    ],
    "sg:phone":"+1 617 477 0231",
    "sg:postcode":"02186",
    "sg:province":"MA",
    "sg:tags":[
        "wrecker"
    ],
    "wof:name":"7 Day Emergency 24 Hr Lcksmth",
    "wof:placetype":"venue"
},
  "geometry": {"coordinates":[-71.041476,42.258794],"type":"Point"}
}