{
  "type": "Feature",
  "properties": {
    "addr:full":"182 Endicott St Danvers MA 01923",
    "addr:housenumber":"182",
    "addr:postcode":"01923",
    "addr:street":"Endicott St",
    "iso:country":"US",
    "sg:address":"182 Endicott St",
    "sg:city":"Danvers",
    "sg:classifiers":[
        {
            "category":"Home & Garden",
            "subcategory":"Household Appliances",
            "type":"Retail Goods"
        },
        {
            "category":"Autos & Motor Vehicles",
            "subcategory":"Auto Supplies",
            "type":"Retail Goods"
        },
        {
            "category":"Shopping",
            "subcategory":"Computers & Home Electronics",
            "type":"Retail Goods"
        }
    ],
    "sg:phone":"+1 877 666 3007",
    "sg:postcode":"01923",
    "sg:province":"MA",
    "sg:tags":[
        "stereo",
        "theater",
        "automobile",
        "television",
        "appliances-small",
        "system",
        "hardware",
        "video",
        "equipment-dealers",
        "radio",
        "major",
        "audio",
        "consumer",
        "store"
    ],
    "sg:website":"http://national.citysearch.com/profile/external/604361552/danvers_ma/ultimate_electronics.html?publisher=yellowpages&reference_id=1&placement=ypwebsitemip",
    "wof:name":"Ultimate Electronics",
    "wof:placetype":"venue"
},
  "geometry": {"coordinates":[-70.942916,42.548238],"type":"Point"}
}