{
  "type": "Feature",
  "properties": {
    "iso:country":"US",
    "sg:address":"139 Chapin St",
    "sg:city":"Ludlow",
    "sg:classifiers":[
        {
            "category":"Real Estate",
            "subcategory":"Real Estate Operator",
            "type":"Services"
        }
    ],
    "sg:phone":"+1   ",
    "sg:postcode":"01056",
    "sg:province":"MA",
    "sg:tags":[
        "property",
        "lessor"
    ],
    "wof:name":"Highland East Inc",
    "wof:placetype":"venue"
},
  "geometry": {"coordinates":[-72.436204,42.158548],"type":"Point"}
}