{
  "type": "Feature",
  "properties": {
    "iso:country":"US",
    "sg:address":"70 Coolidge Rd",
    "sg:city":"Worcester",
    "sg:classifiers":[
        {
            "category":"Professional",
            "subcategory":"Accounting & Tax Preparation",
            "type":"Services"
        }
    ],
    "sg:phone":"+1   ",
    "sg:postcode":"01602",
    "sg:province":"MA",
    "wof:name":"Buckley Lloyd Jr CPA",
    "wof:placetype":"venue"
},
  "geometry": {"coordinates":[-71.824715,42.265634],"type":"Point"}
}