{
  "type": "Feature",
  "properties": {
    "addr:full": "70 Coolidge Rd Worcester MA 01602",
    "addr:housenumber": "70",
    "addr:postcode": "01602",
    "addr:street": "Coolidge Rd",
    "iso:country": "US",
    "sg:address": "70 Coolidge Rd",
    "sg:city": "Worcester",
    "sg:classifiers": [
      {
        "category": "Professional",
        "subcategory": "Accounting \u0026 Tax Preparation",
        "type": "Services"
      }
    ],
    "sg:phone": "+1   ",
    "sg:postcode": "01602",
    "sg:province": "MA",
    "wof:name": "Buckley Lloyd Jr CPA",
    "wof:placetype": "venue"
  },
  "geometry": {"coordinates":[-71.824715,42.265634],"type":"Point"}
}
