{
  "type": "Feature",
  "properties": {
    "addr:full":"520 Fletcher St Lowell MA 01854",
    "addr:housenumber":"520",
    "addr:postcode":"01854",
    "addr:street":"Fletcher St",
    "iso:country":"US",
    "sg:address":"520 Fletcher St",
    "sg:city":"Lowell",
    "sg:classifiers":[
        {
            "category":"Organizations",
            "subcategory":"Non-profit Organization",
            "type":"Services"
        }
    ],
    "sg:phone":"+1 978 452 6071",
    "sg:postcode":"01854",
    "sg:province":"MA",
    "sg:website":"www.rivervalleyhouse.org",
    "wof:name":"Merrimack River Valley House",
    "wof:placetype":"venue"
},
  "geometry": {"coordinates":[-71.324753,42.648534],"type":"Point"}
}