{
  "type": "Feature",
  "properties": {
    "addr:full": "73 N Main St Middleton MA 01949",
    "addr:housenumber": "73",
    "addr:postcode": "01949",
    "addr:street": "N Main St",
    "iso:country": "US",
    "sg:address": "73 N Main St",
    "sg:city": "Middleton",
    "sg:classifiers": [
      {
        "category": "Utilities",
        "subcategory": "Natural Gas",
        "type": "Services"
      }
    ],
    "sg:phone": "+1 978 774 0462",
    "sg:postcode": "01949",
    "sg:province": "MA",
    "sg:tags": [
      "company"
    ],
    "wof:name": "M W Gas",
    "wof:placetype": "venue"
  },
  "geometry": {"coordinates":[-71.02035,42.598293],"type":"Point"}
}
