{
  "type": "Feature",
  "properties": {
    "iso:country":"US",
    "sg:address":"73 N Main St",
    "sg:city":"Middleton",
    "sg:classifiers":[
        {
            "category":"Utilities",
            "subcategory":"Natural Gas",
            "type":"Services"
        }
    ],
    "sg:phone":"+1 978 774 0462",
    "sg:postcode":"01949",
    "sg:province":"MA",
    "sg:tags":[
        "company"
    ],
    "wof:name":"M W Gas",
    "wof:placetype":"venue"
},
  "geometry": {"coordinates":[-71.02034999999999,42.598293],"type":"Point"}
}