{
  "type": "Feature",
  "properties": {
    "addr:full":"369 Pleasant St Weymouth MA 02190",
    "addr:housenumber":"369",
    "addr:postcode":"02190",
    "addr:street":"Pleasant St",
    "iso:country":"US",
    "sg:address":"369 Pleasant St",
    "sg:city":"Weymouth",
    "sg:classifiers":[
        {
            "category":"Professional",
            "subcategory":"Accounting & Tax Preparation",
            "type":"Services"
        }
    ],
    "sg:phone":"+1 781 331 5734",
    "sg:postcode":"02190",
    "sg:province":"MA",
    "sg:tags":[
        "return",
        "filing"
    ],
    "wof:name":"Sandra L Greene",
    "wof:placetype":"venue"
},
  "geometry": {"coordinates":[-70.940899,42.181014],"type":"Point"}
}