{
  "type": "Feature",
  "properties": {
    "addr:full": "40 Murphy Dr Avon MA 02322",
    "addr:housenumber": "40",
    "addr:postcode": "02322",
    "addr:street": "Murphy Dr",
    "iso:country": "US",
    "sg:address": "40 Murphy Dr",
    "sg:city": "Avon",
    "sg:classifiers": [
      {
        "category": "Manufacturing",
        "subcategory": "Retail Goods",
        "type": "Manufacturing \u0026 Wholesale Goods"
      }
    ],
    "sg:phone": "+1 508 588 4845",
    "sg:postcode": "02322",
    "sg:province": "MA",
    "sg:tags": [
      "manufacturer"
    ],
    "wof:name": "Architectural Glazing Systems",
    "wof:placetype": "venue"
  },
  "geometry": {"coordinates":[-71.053828,42.130529],"type":"Point"}
}
