{
  "type": "Feature",
  "properties": {
    "addr:full":"12 Parker St Newbury MA 01951",
    "addr:housenumber":"12",
    "addr:postcode":"01951",
    "addr:street":"Parker St",
    "iso:country":"US",
    "sg:address":"12 Parker St",
    "sg:city":"Newbury",
    "sg:classifiers":[
        {
            "category":"Banks & Credit Unions",
            "subcategory":"Investment Brokerage",
            "type":"Services"
        }
    ],
    "sg:phone":"+1 978 499 9191",
    "sg:postcode":"01951",
    "sg:province":"MA",
    "sg:tags":[
        "security"
    ],
    "wof:name":"Christopher Bergin",
    "wof:placetype":"venue"
},
  "geometry": {"coordinates":[-70.863788,42.797999],"type":"Point"}
}