{
  "type": "Feature",
  "properties": {
    "addr:full": "137 Center St Pembroke MA 02359",
    "addr:housenumber": "137",
    "addr:postcode": "02359",
    "addr:street": "Center St",
    "iso:country": "US",
    "ovtr:label": "Cumberland Farms, 137 Center St Pembroke MA US",
    "ovtr:similarity": 2.7236270904541016,
    "sg:address": "137 Center St",
    "sg:city": "Pembroke",
    "sg:classifiers": [
      {
        "category": "Food \u0026 Beverages",
        "subcategory": "Groceries \u0026 Convenience Stores",
        "type": "Retail Goods"
      }
    ],
    "sg:phone": "+1 781 293 5426",
    "sg:postcode": "02359",
    "sg:province": "MA",
    "wof:name": "Cumberland Farms",
    "wof:placetype": "venue"
  },
  "geometry": {"coordinates":[-70.810136,42.069328],"type":"Point"}
}
