{
  "type": "Feature",
  "properties": {
    "iso:country":"US",
    "sg:address":"137 Center St",
    "sg:city":"Pembroke",
    "sg:classifiers":[
        {
            "category":"Food & Beverages",
            "subcategory":"Groceries & Convenience Stores",
            "type":"Retail Goods"
        }
    ],
    "sg:phone":"+1 781 293 5426",
    "sg:postcode":"02359",
    "sg:province":"MA",
    "wof:name":"Cumberland Farms",
    "wof:placetype":"venue"
},
  "geometry": {"coordinates":[-70.810136,42.069328],"type":"Point"}
}