{
  "type": "Feature",
  "properties": {
    "iso:country":"US",
    "sg:address":"817 State Rd",
    "sg:city":"Westport",
    "sg:classifiers":[
        {
            "category":"Autos & Motor Vehicles",
            "subcategory":"Auto Supplies",
            "type":"Retail Goods"
        }
    ],
    "sg:phone":"+1 508 676 0276",
    "sg:postcode":"02790",
    "sg:province":"MA",
    "sg:tags":[
        "automobile",
        "parts"
    ],
    "wof:name":"Vel-Parts Of Westport",
    "wof:placetype":"venue"
},
  "geometry": {"coordinates":[-71.071134,41.652885],"type":"Point"}
}