{
  "type": "Feature",
  "properties": {
    "iso:country":"US",
    "sg:address":"16 Pierpont St",
    "sg:city":"Peabody",
    "sg:classifiers":[
        {
            "category":"Professional",
            "subcategory":"Computer Services",
            "type":"Services"
        }
    ],
    "sg:phone":"+1   ",
    "sg:postcode":"01960",
    "sg:province":"MA",
    "sg:tags":[
        "related"
    ],
    "wof:name":"Randhir S Chhatwal",
    "wof:placetype":"venue"
},
  "geometry": {"coordinates":[-70.920852,42.523213],"type":"Point"}
}