{
  "type": "Feature",
  "properties": {
    "addr:full": "545 Concord Ave Ste 14B Cambridge MA 02138",
    "addr:housenumber": "545",
    "addr:postcode": "02138",
    "addr:street": "Concord Ave Ste 14B",
    "iso:country": "US",
    "sg:address": "545 Concord Ave Ste 14B",
    "sg:city": "Cambridge",
    "sg:classifiers": [
      {
        "category": "Education",
        "subcategory": "School",
        "type": "Public Place"
      }
    ],
    "sg:phone": "+1 617 491 0041",
    "sg:postcode": "02138",
    "sg:province": "MA",
    "wof:name": "Boston Education Consulting Inc",
    "wof:placetype": "venue"
  },
  "geometry": {"coordinates":[-71.142925,42.388451],"type":"Point"}
}
