{
  "type": "Feature",
  "properties": {
    "addr:full": "69 Charles Street Boston MA 02114",
    "addr:housenumber": "69",
    "addr:postcode": "02114",
    "addr:street": "Charles Street",
    "iso:country": "US",
    "sg:address": "69 Charles Street",
    "sg:city": "Boston",
    "sg:classifiers": [
      {
        "category": "Shopping",
        "subcategory": "Clothing, Apparel, \u0026 Fashions",
        "type": "Retail Goods"
      }
    ],
    "sg:phone": "+1 617 523 3211",
    "sg:postcode": "02114",
    "sg:province": "MA",
    "sg:website": "www.pixiestixboston.com",
    "wof:name": "Pixie Stix",
    "wof:placetype": "venue"
  },
  "geometry": {"coordinates":[-71.070259,42.358138],"type":"Point"}
}
