{
  "type": "Feature",
  "properties": {
    "iso:country":"US",
    "sg:address":"69 Charles Street",
    "sg:city":"Boston",
    "sg:classifiers":[
        {
            "category":"Shopping",
            "subcategory":"Clothing, Apparel, & Fashions",
            "type":"Retail Goods"
        }
    ],
    "sg:phone":"+1 617 523 3211",
    "sg:postcode":"02114",
    "sg:province":"MA",
    "sg:website":"www.pixiestixboston.com",
    "wof:name":"Pixie Stix",
    "wof:placetype":"venue"
},
  "geometry": {"coordinates":[-71.07025899999999,42.358138],"type":"Point"}
}