{
  "type": "Feature",
  "properties": {
    "iso:country":"US",
    "sg:address":"445 Rantoul St",
    "sg:city":"Beverly",
    "sg:classifiers":[
        {
            "category":"Retail",
            "subcategory":"Auto Repair",
            "type":"Services"
        }
    ],
    "sg:phone":"+1 978 922 0555",
    "sg:postcode":"01915",
    "sg:province":"MA",
    "sg:tags":[
        "repairing",
        "automobile"
    ],
    "wof:name":"Pages Auto Repair",
    "wof:placetype":"venue"
},
  "geometry": {"coordinates":[-70.881052,42.555431],"type":"Point"}
}