{
  "type": "Feature",
  "properties": {
    "addr:full": "20 Church St Hopkinton MA 01748",
    "addr:housenumber": "20",
    "addr:postcode": "01748",
    "addr:street": "Church St",
    "iso:country": "US",
    "sg:address": "20 Church St",
    "sg:city": "Hopkinton",
    "sg:classifiers": [
      {
        "category": "Organizations",
        "subcategory": "Religious Organization",
        "type": "Services"
      }
    ],
    "sg:phone": "+1 508 435 3094",
    "sg:postcode": "01748",
    "sg:province": "MA",
    "sg:tags": [
      "church"
    ],
    "sg:website": "www.stjohntheevangelist.com",
    "wof:name": "St John The Evangelist Church",
    "wof:placetype": "venue"
  },
  "geometry": {"coordinates":[-71.518728,42.226051],"type":"Point"}
}
