{
  "type": "Feature",
  "properties": {
    "addr:full": "5 Charlesview Rd Hopedale MA 01747",
    "addr:housenumber": "5",
    "addr:postcode": "01747",
    "addr:street": "Charlesview Rd",
    "iso:country": "US",
    "sg:address": "5 Charlesview Rd",
    "sg:city": "Hopedale",
    "sg:classifiers": [
      {
        "category": "Home \u0026 Garden",
        "subcategory": "Building Materials",
        "type": "Retail Goods"
      }
    ],
    "sg:phone": "+1 508 473 0030",
    "sg:postcode": "01747",
    "sg:province": "MA",
    "sg:tags": [
      "door"
    ],
    "sg:website": "www.neodg.com",
    "wof:name": "New England Overhead Doors",
    "wof:placetype": "venue"
  },
  "geometry": {"coordinates":[-71.502932,42.104761],"type":"Point"}
}
