{
  "type": "Feature",
  "properties": {
    "addr:full":"Washington St and Winter St Malden MA 02148",
    "addr:postcode":"02148",
    "addr:street":"Washington St;Winter St",
    "iso:country":"US",
    "sg:address":"Washington St and Winter St",
    "sg:city":"Malden",
    "sg:classifiers":[
        {
            "category":"Local Transit",
            "type":"Transportation"
        }
    ],
    "sg:postcode":"02148",
    "sg:province":"MA",
    "sg:tags":[
        "public"
    ],
    "wof:name":"Oak Grove Station",
    "wof:placetype":"venue"
},
  "geometry": {"coordinates":[-71.071986,42.435331],"type":"Point"}
}