{
  "type": "Feature",
  "properties": {
    "iso:country":"US",
    "sg:address":"12 Bowles Rd",
    "sg:city":"Agawam",
    "sg:classifiers":[
        {
            "category":"Building & Trades",
            "subcategory":"Construction",
            "type":"Services"
        }
    ],
    "sg:phone":"+1 413 786 7000",
    "sg:postcode":"01001",
    "sg:province":"MA",
    "sg:tags":[
        "elevator"
    ],
    "sg:website":"www.bseco.com",
    "wof:name":"Bay State Elevator Co",
    "wof:placetype":"venue"
},
  "geometry": {"coordinates":[-72.648329,42.05995],"type":"Point"}
}