{
  "type": "Feature",
  "properties": {
    "addr:full":"40 Raynor Cir Roxbury Crossing MA 02120",
    "addr:housenumber":"40",
    "addr:postcode":"02120",
    "addr:street":"Raynor Cir",
    "iso:country":"US",
    "sg:address":"40 Raynor Cir",
    "sg:city":"Roxbury Crossing",
    "sg:classifiers":[
        {
            "category":"Real Estate",
            "subcategory":"Real Estate Agent",
            "type":"Services"
        }
    ],
    "sg:phone":"+1 617 442 9945",
    "sg:postcode":"02120",
    "sg:province":"MA",
    "sg:tags":[
        "management"
    ],
    "wof:name":"Madison Park Phase Four",
    "wof:placetype":"venue"
},
  "geometry": {"coordinates":[-71.087267,42.334543],"type":"Point"}
}