{
  "type": "Feature",
  "properties": {
    "addr:full": "241 Main St Wareham MA 02571",
    "addr:housenumber": "241",
    "addr:postcode": "02571",
    "addr:street": "Main St",
    "iso:country": "US",
    "sg:address": "241 Main St",
    "sg:city": "Wareham",
    "sg:classifiers": [
      {
        "category": "Restaurant",
        "type": "Food \u0026 Drink"
      }
    ],
    "sg:phone": "+1 508 295 3264",
    "sg:postcode": "02571",
    "sg:province": "MA",
    "wof:name": "Merchants Way Cafe \u0026 Bakery the",
    "wof:placetype": "venue"
  },
  "geometry": {"coordinates":[-70.718498,41.760502],"type":"Point"}
}
