{
  "type": "Feature",
  "properties": {
    "addr:full":"11 Fells Rd Wellesley MA 02482",
    "addr:housenumber":"11",
    "addr:postcode":"02482",
    "addr:street":"Fells Rd",
    "iso:country":"US",
    "sg:address":"11 Fells Rd",
    "sg:city":"Wellesley",
    "sg:classifiers":[
        {
            "category":"Shopping",
            "subcategory":"Computers & Home Electronics",
            "type":"Retail Goods"
        }
    ],
    "sg:phone":"+1 781 239 9800",
    "sg:postcode":"02482",
    "sg:province":"MA",
    "sg:tags":[
        "software"
    ],
    "wof:name":"Pre Vision Corp",
    "wof:placetype":"venue"
},
  "geometry": {"coordinates":[-71.313069,42.303876],"type":"Point"}
}