{
  "type": "Feature",
  "properties": {
    "addr:full": "8 Panas Rd Foxboro MA 02035",
    "addr:housenumber": "8",
    "addr:postcode": "02035",
    "addr:street": "Panas Rd",
    "iso:country": "US",
    "sg:address": "8 Panas Rd",
    "sg:city": "Foxboro",
    "sg:classifiers": [
      {
        "category": "Wholesale",
        "subcategory": "Machinery \u0026 Supplies",
        "type": "Manufacturing \u0026 Wholesale Goods"
      }
    ],
    "sg:phone": "+1 508 543 3545",
    "sg:postcode": "02035",
    "sg:province": "MA",
    "sg:tags": [
      "janitor"
    ],
    "sg:website": "www.caseyemi.com",
    "wof:name": "Casey Engineered Maintenance",
    "wof:placetype": "venue"
  },
  "geometry": {"coordinates":[-71.246281,42.10367],"type":"Point"}
}
