{
  "type": "Feature",
  "properties": {
    "iso:country":"US",
    "sg:address":"8 Panas Rd",
    "sg:city":"Foxboro",
    "sg:classifiers":[
        {
            "category":"Wholesale",
            "subcategory":"Machinery & Supplies",
            "type":"Manufacturing & Wholesale Goods"
        }
    ],
    "sg:phone":"+1 508 543 3545",
    "sg:postcode":"02035",
    "sg:province":"MA",
    "sg:tags":[
        "janitor"
    ],
    "sg:website":"www.caseyemi.com",
    "wof:name":"Casey Engineered Maintenance",
    "wof:placetype":"venue"
},
  "geometry": {"coordinates":[-71.246281,42.10367],"type":"Point"}
}