{
  "type": "Feature",
  "properties": {
    "iso:country":"US",
    "sg:address":"887 Main St",
    "sg:city":"Walpole",
    "sg:classifiers":[
        {
            "category":"Restaurant",
            "type":"Food & Drink"
        }
    ],
    "sg:phone":"+1 508 660 2888",
    "sg:postcode":"02081",
    "sg:province":"MA",
    "wof:name":"Feng's 88",
    "wof:placetype":"venue"
},
  "geometry": {"coordinates":[-71.251667,42.14776],"type":"Point"}
}