{
  "type": "Feature",
  "properties": {
    "iso:country":"US",
    "sg:address":"1921 Main St",
    "sg:city":"Tewksbury",
    "sg:classifiers":[
        {
            "category":"Restaurant",
            "type":"Food & Drink"
        }
    ],
    "sg:phone":"+1 978 851 4955",
    "sg:postcode":"01876",
    "sg:province":"MA",
    "wof:name":"Kostas Korner Inc",
    "wof:placetype":"venue"
},
  "geometry": {"coordinates":[-71.20390500000001,42.590185],"type":"Point"}
}