{
  "type": "Feature",
  "properties": {
    "iso:country":"US",
    "sg:address":"444 Massachusetts Ave ",
    "sg:city":"Arlington",
    "sg:classifiers":[
        {
            "category":"Restaurant",
            "type":"Food & Drink"
        }
    ],
    "sg:menulink":"http://www.allmenus.com/ma/arlington/293581-midami/menu/",
    "sg:phone":"+1 781 642 7878",
    "sg:postcode":"02474",
    "sg:province":"MA",
    "sg:tags":[
        "korean",
        "sushi",
        "thai",
        "japanese",
        "asian"
    ],
    "wof:name":"Midami",
    "wof:placetype":"venue"
},
  "geometry": {"coordinates":[-71.151099,42.414243],"type":"Point"}
}