{
  "type": "Feature",
  "properties": {
    "addr:full": "105 Summer St Everett MA 02149",
    "addr:housenumber": "105",
    "addr:postcode": "02149",
    "addr:street": "Summer St",
    "iso:country": "US",
    "sg:address": "105 Summer St",
    "sg:city": "Everett",
    "sg:classifiers": [
      {
        "category": "Building \u0026 Trades",
        "subcategory": "Construction",
        "type": "Services"
      }
    ],
    "sg:phone": "+1 617 803 9725",
    "sg:postcode": "02149",
    "sg:province": "MA",
    "sg:tags": [
      "altering",
      "remodeling",
      "contractor"
    ],
    "wof:name": "Flores Remodeling",
    "wof:placetype": "venue"
  },
  "geometry": {"coordinates":[-71.049685,42.408267],"type":"Point"}
}
