{
  "type": "Feature",
  "properties": {
    "iso:country":"US",
    "sg:address":"694 State Rd",
    "sg:city":"Vineyard Haven",
    "sg:classifiers":[
        {
            "category":"Travel",
            "subcategory":"Hotels & Motels",
            "type":"Entertainment"
        }
    ],
    "sg:phone":"+1 508 693 5354",
    "sg:postcode":"02575",
    "sg:province":"MA",
    "sg:tags":[
        "breakfast",
        "accommodation",
        "bed"
    ],
    "wof:name":"Farm House",
    "wof:placetype":"venue"
},
  "geometry": {"coordinates":[-70.67739899999999,41.402814],"type":"Point"}
}