{
  "type": "Feature",
  "properties": {
    "addr:full": "694 State Rd Vineyard Haven MA 02575",
    "addr:housenumber": "694",
    "addr:postcode": "02575",
    "addr:street": "State Rd",
    "iso:country": "US",
    "sg:address": "694 State Rd",
    "sg:city": "Vineyard Haven",
    "sg:classifiers": [
      {
        "category": "Travel",
        "subcategory": "Hotels \u0026 Motels",
        "type": "Entertainment"
      }
    ],
    "sg:phone": "+1 508 693 5354",
    "sg:postcode": "02575",
    "sg:province": "MA",
    "sg:tags": [
      "breakfast",
      "accommodation",
      "bed"
    ],
    "wof:name": "Farm House",
    "wof:placetype": "venue"
  },
  "geometry": {"coordinates":[-70.677399,41.402814],"type":"Point"}
}
