{
  "type": "Feature",
  "properties": {
    "addr:full":"42 Broad St Medway MA 02053",
    "addr:housenumber":"42",
    "addr:postcode":"02053",
    "addr:street":"Broad St",
    "iso:country":"US",
    "sg:address":"42 Broad St",
    "sg:city":"Medway",
    "sg:classifiers":[
        {
            "category":"Building & Trades",
            "subcategory":"Construction",
            "type":"Services"
        }
    ],
    "sg:phone":"+1 508 533 5040",
    "sg:postcode":"02053",
    "sg:province":"MA",
    "sg:tags":[
        "roofing",
        "contractor"
    ],
    "wof:name":"Essary Roofing",
    "wof:placetype":"venue"
},
  "geometry": {"coordinates":[-71.397633,42.145811],"type":"Point"}
}