{
  "type": "Feature",
  "properties": {
    "iso:country":"US",
    "sg:address":"169 Davis St",
    "sg:city":"Douglas",
    "sg:classifiers":[
        {
            "category":"Autos & Motor Vehicles",
            "subcategory":"Motorcycle Sales",
            "type":"Retail Goods"
        }
    ],
    "sg:phone":"+1 508 476 3737",
    "sg:postcode":"01516",
    "sg:province":"MA",
    "sg:tags":[
        "scooter"
    ],
    "wof:name":"Bill's Cycles & Repair",
    "wof:placetype":"venue"
},
  "geometry": {"coordinates":[-71.68645600000001,42.0581],"type":"Point"}
}