{
  "type": "Feature",
  "properties": {
    "iso:country":"US",
    "sg:address":"660 Merrill Rd",
    "sg:city":"Pittsfield",
    "sg:classifiers":[
        {
            "category":"Shopping",
            "subcategory":"Jewelry",
            "type":"Retail Goods"
        }
    ],
    "sg:phone":"+1 413 442 6911",
    "sg:postcode":"01201",
    "sg:province":"MA",
    "sg:tags":[
        "jeweler"
    ],
    "wof:name":"M Edward Jewelers",
    "wof:placetype":"venue"
},
  "geometry": {"coordinates":[-73.20398900000001,42.466881],"type":"Point"}
}