{
  "type": "Feature",
  "properties": {
    "addr:full": "24 Central St Georgetown MA 01833",
    "addr:housenumber": "24",
    "addr:postcode": "01833",
    "addr:street": "Central St",
    "iso:country": "US",
    "sg:address": "24 Central St",
    "sg:city": "Georgetown",
    "sg:classifiers": [
      {
        "category": "Health Services",
        "subcategory": "Doctor",
        "type": "Services"
      }
    ],
    "sg:phone": "+1 978 352 8421",
    "sg:postcode": "01833",
    "sg:province": "MA",
    "sg:tags": [
      "dentist"
    ],
    "wof:name": "Lewis Skeirik Dmd Inc",
    "wof:placetype": "venue"
  },
  "geometry": {"coordinates":[-70.992289,42.723288],"type":"Point"}
}
