{
  "type": "Feature",
  "properties": {
    "addr:full":"91 Kilmarnock St Apt 1 Boston MA 02215",
    "addr:housenumber":"91;1",
    "addr:postcode":"02215",
    "addr:street":"Kilmarnock St Apt",
    "iso:country":"US",
    "sg:address":"91 Kilmarnock St Apt 1",
    "sg:city":"Boston",
    "sg:classifiers":[
        {
            "category":"Professional",
            "type":"Services"
        }
    ],
    "sg:phone":"+1 617 536 2208",
    "sg:postcode":"02215",
    "sg:province":"MA",
    "sg:tags":[
        "transportation"
    ],
    "wof:name":"James W Jones Transportation",
    "wof:placetype":"venue"
},
  "geometry": {"coordinates":[-71.099182,42.342251],"type":"Point"}
}