{
  "type": "Feature",
  "properties": {
    "iso:country":"US",
    "sg:address":"1863 Ocean St",
    "sg:city":"Marshfield",
    "sg:classifiers":[
        {
            "category":"Wholesale",
            "subcategory":"Hardware",
            "type":"Manufacturing & Wholesale Goods"
        }
    ],
    "sg:phone":"+1 781 837 3568",
    "sg:postcode":"02050",
    "sg:province":"MA",
    "sg:tags":[
        "equipment",
        "heating",
        "system"
    ],
    "wof:name":"Guardian Heating & Air Cond",
    "wof:placetype":"venue"
},
  "geometry": {"coordinates":[-70.70364499999999,42.092045],"type":"Point"}
}