{
  "type": "Feature",
  "properties": {
    "addr:full":"9 Beach St Millbury MA 01527",
    "addr:housenumber":"9",
    "addr:postcode":"01527",
    "addr:street":"Beach St",
    "iso:country":"US",
    "sg:address":"9 Beach St",
    "sg:city":"Millbury",
    "sg:classifiers":[
        {
            "category":"Building & Trades",
            "subcategory":"Landscaping Services",
            "type":"Services"
        }
    ],
    "sg:phone":"+1   ",
    "sg:postcode":"01527",
    "sg:province":"MA",
    "wof:name":"Bob S Tree Service",
    "wof:placetype":"venue"
},
  "geometry": {"coordinates":[-71.77385599999999,42.178007],"type":"Point"}
}