{
  "type": "Feature",
  "properties": {
    "addr:full":"10 Central St Framingham MA 01701",
    "addr:housenumber":"10",
    "addr:postcode":"01701",
    "addr:street":"Central St",
    "iso:country":"US",
    "sg:address":"10 Central St",
    "sg:city":"Framingham",
    "sg:classifiers":[
        {
            "category":"Professional",
            "subcategory":"Business Services",
            "type":"Services"
        }
    ],
    "sg:phone":"+1 508 788 1000",
    "sg:postcode":"01701",
    "sg:province":"MA",
    "sg:tags":[
        "broker"
    ],
    "wof:name":"Oxford Business Brokers Inc",
    "wof:placetype":"venue"
},
  "geometry": {"coordinates":[-71.40081000000001,42.325031],"type":"Point"}
}