{
  "type": "Feature",
  "properties": {
    "addr:full": "637 High St Westwood MA 02090",
    "addr:housenumber": "637",
    "addr:postcode": "02090",
    "addr:street": "High St",
    "iso:country": "US",
    "ovtr:label": "Westwood Fire Department, 637 High St Westwood MA US",
    "ovtr:similarity": 2.831913948059082,
    "sg:address": "637 High St",
    "sg:city": "Westwood",
    "sg:classifiers": [
      {
        "category": "Government",
        "subcategory": "Fire Station",
        "type": "Public Place"
      }
    ],
    "sg:phone": "+1 781 326 3885",
    "sg:postcode": "02090",
    "sg:province": "MA",
    "sg:tags": [
      "department"
    ],
    "wof:name": "Westwood Fire Dept",
    "wof:placetype": "venue"
  },
  "geometry": {"coordinates":[-71.220671,42.23084],"type":"Point"}
}
