{
  "type": "Feature",
  "properties": {
    "addr:full": "89 West St Westford MA 01886",
    "addr:housenumber": "89",
    "addr:postcode": "01886",
    "addr:street": "West St",
    "iso:country": "US",
    "sg:address": "89 West St",
    "sg:city": "Westford",
    "sg:classifiers": [
      {
        "category": "Building \u0026 Trades",
        "subcategory": "Plumbing",
        "type": "Services"
      }
    ],
    "sg:phone": "+1   ",
    "sg:postcode": "01886",
    "sg:province": "MA",
    "sg:tags": [
      "contractor"
    ],
    "wof:name": "Theide Francis",
    "wof:placetype": "venue"
  },
  "geometry": {"coordinates":[-71.493714,42.59975],"type":"Point"}
}
