{
  "type": "Feature",
  "properties": {
    "addr:full":"95 Mechanic St Bellingham MA 02019",
    "addr:housenumber":"95",
    "addr:postcode":"02019",
    "addr:street":"Mechanic St",
    "iso:country":"US",
    "sg:address":"95 Mechanic St",
    "sg:city":"Bellingham",
    "sg:classifiers":[
        {
            "category":"Building & Trades",
            "subcategory":"Construction",
            "type":"Services"
        }
    ],
    "sg:phone":"+1 508 966 1322",
    "sg:postcode":"02019",
    "sg:province":"MA",
    "sg:tags":[
        "designer",
        "dealer",
        "pool",
        "swimming"
    ],
    "wof:name":"Crystal Industries Inc",
    "wof:placetype":"venue"
},
  "geometry": {"coordinates":[-71.46533100000001,42.081773],"type":"Point"}
}