{
  "type": "Feature",
  "properties": {
    "addr:full":"58 May Ln Auburn MA 01501",
    "addr:housenumber":"58",
    "addr:postcode":"01501",
    "addr:street":"May Ln",
    "iso:country":"US",
    "sg:address":"58 May Ln",
    "sg:city":"Auburn",
    "sg:classifiers":[
        {
            "category":"Shopping",
            "subcategory":"Used Merchandise",
            "type":"Retail Goods"
        }
    ],
    "sg:phone":"+1 508 832 5805",
    "sg:postcode":"01501",
    "sg:province":"MA",
    "sg:tags":[
        "antique"
    ],
    "wof:name":"Tom's Collectibles & Things",
    "wof:placetype":"venue"
},
  "geometry": {"coordinates":[-71.81846899999999,42.192582],"type":"Point"}
}