{
  "type": "Feature",
  "properties": {
    "addr:full": "349 Maple St Lynn MA 01904",
    "addr:housenumber": "349",
    "addr:postcode": "01904",
    "addr:street": "Maple St",
    "iso:country": "US",
    "sg:address": "349 Maple St",
    "sg:city": "Lynn",
    "sg:classifiers": [
      {
        "category": "Government",
        "subcategory": "Office",
        "type": "Public Place"
      }
    ],
    "sg:phone": "+1 781 477 7100",
    "sg:postcode": "01904",
    "sg:province": "MA",
    "sg:tags": [
      "village"
    ],
    "wof:name": "Manning Bowl Club House",
    "wof:placetype": "venue"
  },
  "geometry": {"coordinates":[-70.952406,42.47369],"type":"Point"}
}
