{
  "type": "Feature",
  "properties": {
    "addr:full": "64 Marlborough Rd Salem MA 01970",
    "addr:housenumber": "64",
    "addr:postcode": "01970",
    "addr:street": "Marlborough Rd",
    "iso:country": "US",
    "sg:address": "64 Marlborough Rd",
    "sg:city": "Salem",
    "sg:classifiers": [
      {
        "category": "Travel",
        "subcategory": "Travel Agent",
        "type": "Entertainment"
      }
    ],
    "sg:phone": "+1   ",
    "sg:postcode": "01970",
    "sg:province": "MA",
    "sg:tags": [
      "agency"
    ],
    "wof:name": "Cruiseone",
    "wof:placetype": "venue"
  },
  "geometry": {"coordinates":[-70.927305,42.512161],"type":"Point"}
}
