{
  "type": "Feature",
  "properties": {
    "iso:country":"US",
    "sg:address":"306 Salem St",
    "sg:city":"Medford",
    "sg:classifiers":[
        {
            "category":"Shopping",
            "subcategory":"Gifts & Souvenirs",
            "type":"Retail Goods"
        }
    ],
    "sg:phone":"+1 781 396 0500",
    "sg:postcode":"02155",
    "sg:province":"MA",
    "sg:tags":[
        "greeting",
        "card"
    ],
    "wof:name":"Connect Phone Cards Inc",
    "wof:placetype":"venue"
},
  "geometry": {"coordinates":[-71.098062,42.421145],"type":"Point"}
}