{
  "type": "Feature",
  "properties": {
    "addr:full":"210 E Falmouth Hwy East Falmouth MA 02536",
    "addr:housenumber":"210",
    "addr:postcode":"02536",
    "addr:street":"E Falmouth Hwy",
    "iso:country":"US",
    "sg:address":"210 E Falmouth Hwy",
    "sg:city":"East Falmouth",
    "sg:classifiers":[
        {
            "category":"Retail",
            "subcategory":"Repair Shop",
            "type":"Services"
        }
    ],
    "sg:phone":"+1 508 563 5239",
    "sg:postcode":"02536",
    "sg:province":"MA",
    "wof:name":"Cavossa Septic Pumping",
    "wof:placetype":"venue"
},
  "geometry": {"coordinates":[-70.564947,41.578751],"type":"Point"}
}