{
  "type": "Feature",
  "properties": {
    "addr:full":"9B Safford St Ipswich MA 01938",
    "addr:housenumber":"9b",
    "addr:postcode":"01938",
    "addr:street":"Safford St",
    "iso:country":"US",
    "sg:address":"9B Safford St",
    "sg:city":"Ipswich",
    "sg:classifiers":[
        {
            "category":"Wholesale",
            "subcategory":"Motor Vehicles",
            "type":"Manufacturing & Wholesale Goods"
        },
        {
            "category":"Autos & Motor Vehicles",
            "subcategory":"Auto Supplies",
            "type":"Retail Goods"
        },
        {
            "category":"Travel",
            "subcategory":"Travel Agent",
            "type":"Entertainment"
        }
    ],
    "sg:phone":"+1 978 356 6116",
    "sg:postcode":"01938",
    "sg:province":"MA",
    "sg:tags":[
        "recreational",
        "manufacturer",
        "campers-wholesale",
        "trailer",
        "hitch"
    ],
    "wof:name":"The Trailer Connection",
    "wof:placetype":"venue"
},
  "geometry": {"coordinates":[-70.846239,42.675],"type":"Point"}
}