{
  "type": "Feature",
  "properties": {
    "iso:country":"US",
    "sg:address":"netBlazr Inc. 421 Watertown St.",
    "sg:city":"Newton",
    "sg:classifiers":[
        {
            "category":"Professional",
            "subcategory":"Computer Services",
            "type":"Services"
        }
    ],
    "sg:phone":"+1 617 606 3448",
    "sg:postcode":"02458",
    "sg:province":"MA",
    "sg:tags":[
        "broadband",
        "fixed-wireless",
        "isp",
        "wisp",
        "freemium"
    ],
    "sg:website":"http://www.netblazr.com",
    "wof:name":"netBlazr",
    "wof:placetype":"venue"
},
  "geometry": {"coordinates":[-71.195814,42.361689],"type":"Point"}
}