{
  "type": "Feature",
  "properties": {
    "iso:country":"US",
    "sg:address":"144 Newburyport Tpke",
    "sg:city":"Rowley",
    "sg:classifiers":[
        {
            "category":"Personal",
            "type":"Services"
        }
    ],
    "sg:phone":"+1   ",
    "sg:postcode":"01969",
    "sg:province":"MA",
    "wof:name":"Endless Summer Tanning",
    "wof:placetype":"venue"
},
  "geometry": {"coordinates":[-70.909987,42.70299],"type":"Point"}
}