{
  "type": "Feature",
  "properties": {
    "addr:full": "501 S Broadway Lawrence MA 01843",
    "addr:housenumber": "501",
    "addr:postcode": "01843",
    "addr:street": "S Broadway",
    "iso:country": "US",
    "sg:address": "501 S Broadway",
    "sg:city": "Lawrence",
    "sg:classifiers": [
      {
        "category": "Food \u0026 Beverages",
        "subcategory": "Groceries \u0026 Convenience Stores",
        "type": "Retail Goods"
      }
    ],
    "sg:phone": "+1 978 794 9878",
    "sg:postcode": "01843",
    "sg:province": "MA",
    "wof:name": "John's Family Market",
    "wof:placetype": "venue"
  },
  "geometry": {"coordinates":[-71.155378,42.684563],"type":"Point"}
}
