{
  "type": "Feature",
  "properties": {
    "addr:full":"421 US Hwy 44 Raynham MA 02767",
    "addr:housenumber":"421",
    "addr:postcode":"02767",
    "addr:street":"Us Hwy 44",
    "iso:country":"US",
    "sg:address":"421 US Hwy 44",
    "sg:city":"Raynham",
    "sg:classifiers":[
        {
            "category":"Shopping",
            "subcategory":"Bicycles & Sporting Goods",
            "type":"Retail Goods"
        }
    ],
    "sg:phone":"+1   ",
    "sg:postcode":"02767",
    "sg:province":"MA",
    "wof:name":"Petersons Bike Shop",
    "wof:placetype":"venue"
},
  "geometry": {"coordinates":[-71.04929799999999,41.90606],"type":"Point"}
}