{
  "type": "Feature",
  "properties": {
    "iso:country":"US",
    "sg:address":"154 Water St",
    "sg:city":"Newburyport",
    "sg:classifiers":[
        {
            "category":"Banks & Credit Unions",
            "subcategory":"Investment Brokerage",
            "type":"Services"
        }
    ],
    "sg:phone":"+1 978 463 8979",
    "sg:postcode":"01950",
    "sg:province":"MA",
    "sg:tags":[
        "consultant",
        "planning",
        "financial"
    ],
    "wof:name":"Money Sense",
    "wof:placetype":"venue"
},
  "geometry": {"coordinates":[-70.86084700000001,42.808043],"type":"Point"}
}