{
  "type": "Feature",
  "properties": {
    "addr:full":"1842 Beacon Street Brookline MA 02445",
    "addr:housenumber":"1842",
    "addr:postcode":"02445",
    "addr:street":"Beacon Street",
    "iso:country":"US",
    "sg:address":"1842 Beacon Street",
    "sg:city":"Brookline",
    "sg:classifiers":[
        {
            "category":"Sports & Exercise",
            "subcategory":"Gym",
            "type":"Entertainment"
        },
        {
            "category":"Health Services",
            "subcategory":"Health Practitioner",
            "type":"Services"
        }
    ],
    "sg:phone":"+1 617 277 8400",
    "sg:postcode":"02445",
    "sg:province":"MA",
    "sg:tags":[
        "trainer",
        "therapy",
        "physical"
    ],
    "wof:name":"Advanced Physical Therapy",
    "wof:placetype":"venue"
},
  "geometry": {"coordinates":[-71.145315,42.337225],"type":"Point"}
}