{
  "type": "Feature",
  "properties": {
    "iso:country":"US",
    "sg:address":"12 Victorian Dr",
    "sg:city":"West Springfield",
    "sg:classifiers":[
        {
            "category":"Shopping",
            "subcategory":"Clothing, Apparel, & Fashions",
            "type":"Retail Goods"
        }
    ],
    "sg:phone":"+1 413 785 1661",
    "sg:postcode":"01089",
    "sg:province":"MA",
    "sg:tags":[
        "handbag"
    ],
    "wof:name":"Handbag Outlet",
    "wof:placetype":"venue"
},
  "geometry": {"coordinates":[-72.641668,42.151757],"type":"Point"}
}