{
  "type": "Feature",
  "properties": {
    "addr:full":"3371 Acushnet Ave New Bedford MA 02745",
    "addr:housenumber":"3371",
    "addr:postcode":"02745",
    "addr:street":"Acushnet Ave",
    "iso:country":"US",
    "sg:address":"3371 Acushnet Ave",
    "sg:city":"New Bedford",
    "sg:classifiers":[
        {
            "category":"Restaurant",
            "type":"Food & Drink"
        }
    ],
    "sg:phone":"+1 508 998 5281",
    "sg:postcode":"02745",
    "sg:province":"MA",
    "wof:name":"Cafe Roma",
    "wof:placetype":"venue"
},
  "geometry": {"coordinates":[-70.932439,41.707643],"type":"Point"}
}