{
  "type": "Feature",
  "properties": {
    "addr:full": "340 Main St Worcester MA 01608",
    "addr:housenumber": "340",
    "addr:postcode": "01608",
    "addr:street": "Main St",
    "iso:country": "US",
    "sg:address": "340 Main St",
    "sg:city": "Worcester",
    "sg:classifiers": [
      {
        "category": "Manufacturing",
        "subcategory": "Chemicals \u0026 Compounds",
        "type": "Manufacturing \u0026 Wholesale Goods"
      }
    ],
    "sg:phone": "+1 508 831 7100",
    "sg:postcode": "01608",
    "sg:province": "MA",
    "sg:tags": [
      "plastic"
    ],
    "wof:name": "Protech Plastics",
    "wof:placetype": "venue"
  },
  "geometry": {"coordinates":[-71.801555,42.265125],"type":"Point"}
}
