{
  "type": "Feature",
  "properties": {
    "addr:full": "707 Main St Norwell MA 02061",
    "addr:housenumber": "707",
    "addr:postcode": "02061",
    "addr:street": "Main St",
    "iso:country": "US",
    "sg:address": "707 Main St",
    "sg:city": "Norwell",
    "sg:classifiers": [
      {
        "category": "Personal",
        "subcategory": "Beauty Salon",
        "type": "Services"
      }
    ],
    "sg:phone": "+1 781 659 9979",
    "sg:postcode": "02061",
    "sg:province": "MA",
    "wof:name": "Hair By Donna",
    "wof:placetype": "venue"
  },
  "geometry": {"coordinates":[-70.790594,42.161048],"type":"Point"}
}
