{
  "type": "Feature",
  "properties": {
    "iso:country":"US",
    "sg:address":"2 Cabot Pl",
    "sg:city":"Stoughton",
    "sg:classifiers":[
        {
            "category":"Professional",
            "subcategory":"Lawyer & Legal Services",
            "type":"Services"
        }
    ],
    "sg:phone":"+1 781 344 2100",
    "sg:postcode":"02072",
    "sg:province":"MA",
    "sg:tags":[
        "divorce",
        "law",
        "family"
    ],
    "wof:name":"Kesselman Law Associates",
    "wof:placetype":"venue"
},
  "geometry": {"coordinates":[-71.075203,42.152699],"type":"Point"}
}