{
  "type": "Feature",
  "properties": {
    "iso:country":"US",
    "sg:address":"15 Draycoach Dr",
    "sg:city":"Chelmsford",
    "sg:classifiers":[
        {
            "category":"Building & Trades",
            "subcategory":"Construction",
            "type":"Services"
        }
    ],
    "sg:phone":"+1   ",
    "sg:postcode":"01824",
    "sg:province":"MA",
    "sg:tags":[
        "contractor"
    ],
    "wof:name":"Stephen Scomis",
    "wof:placetype":"venue"
},
  "geometry": {"coordinates":[-71.40018499999999,42.605529],"type":"Point"}
}