{
  "type": "Feature",
  "properties": {
    "iso:country":"US",
    "sg:address":"359 Manley St",
    "sg:city":"West Bridgewater",
    "sg:classifiers":[
        {
            "category":"Social Services",
            "subcategory":"Child Care",
            "type":"Services"
        }
    ],
    "sg:phone":"+1 508 588 6644",
    "sg:postcode":"02379",
    "sg:province":"MA",
    "wof:name":"Childrens Express Learning Ctr",
    "wof:placetype":"venue"
},
  "geometry": {"coordinates":[-71.055184,42.030764],"type":"Point"}
}