{
  "type": "Feature",
  "properties": {
    "addr:full": "70 Walnut Street Boston MA 02108",
    "addr:housenumber": "70",
    "addr:postcode": "02108",
    "addr:street": "Walnut Street",
    "iso:country": "US",
    "sg:address": "70 Walnut Street",
    "sg:city": "Boston",
    "sg:classifiers": [
      {
        "category": "Health Services",
        "subcategory": "Doctor",
        "type": "Services"
      }
    ],
    "sg:phone": "+1 781 239 8255",
    "sg:postcode": "02108",
    "sg:province": "MA",
    "sg:website": "www.epill.com",
    "wof:name": "E-Pill",
    "wof:placetype": "venue"
  },
  "geometry": {"coordinates":[-71.066079,42.358174],"type":"Point"}
}
