{
  "type": "Feature",
  "properties": {
    "addr:full": "97 Pearl St South Hadley MA 01075",
    "addr:housenumber": "97",
    "addr:postcode": "01075",
    "addr:street": "Pearl St",
    "iso:country": "US",
    "sg:address": "97 Pearl St",
    "sg:city": "South Hadley",
    "sg:classifiers": [
      {
        "category": "Wholesale",
        "subcategory": "Auto Parts",
        "type": "Manufacturing \u0026 Wholesale Goods"
      }
    ],
    "sg:phone": "+1 413 536 8151",
    "sg:postcode": "01075",
    "sg:province": "MA",
    "sg:tags": [
      "body",
      "automobile",
      "shop"
    ],
    "wof:name": "Outback Paint Booths",
    "wof:placetype": "venue"
  },
  "geometry": {"coordinates":[-72.564118,42.283458],"type":"Point"}
}
