{
  "type": "Feature",
  "properties": {
    "iso:country":"US",
    "sg:address":"97 Pearl St",
    "sg:city":"South Hadley",
    "sg:classifiers":[
        {
            "category":"Wholesale",
            "subcategory":"Auto Parts",
            "type":"Manufacturing & Wholesale Goods"
        }
    ],
    "sg:phone":"+1 413 536 8151",
    "sg:postcode":"01075",
    "sg:province":"MA",
    "sg:tags":[
        "body",
        "automobile",
        "shop"
    ],
    "wof:name":"Outback Paint Booths",
    "wof:placetype":"venue"
},
  "geometry": {"coordinates":[-72.56411799999999,42.283458],"type":"Point"}
}