{
  "type": "Feature",
  "properties": {
    "iso:country":"US",
    "sg:address":"919 Main St",
    "sg:city":"Clinton",
    "sg:classifiers":[
        {
            "category":"Building & Trades",
            "subcategory":"Construction",
            "type":"Services"
        }
    ],
    "sg:phone":"+1 978 365 6135",
    "sg:postcode":"01510",
    "sg:province":"MA",
    "sg:tags":[
        "general",
        "contractor"
    ],
    "wof:name":"Innamorati Brothers Inc",
    "wof:placetype":"venue"
},
  "geometry": {"coordinates":[-71.688045,42.429242],"type":"Point"}
}