{
  "type": "Feature",
  "properties": {
    "addr:full": "919 Main St Clinton MA 01510",
    "addr:housenumber": "919",
    "addr:postcode": "01510",
    "addr:street": "Main St",
    "iso:country": "US",
    "sg:address": "919 Main St",
    "sg:city": "Clinton",
    "sg:classifiers": [
      {
        "category": "Building \u0026 Trades",
        "subcategory": "Construction",
        "type": "Services"
      }
    ],
    "sg:phone": "+1 978 365 6135",
    "sg:postcode": "01510",
    "sg:province": "MA",
    "sg:tags": [
      "general",
      "contractor"
    ],
    "wof:name": "Innamorati Brothers Inc",
    "wof:placetype": "venue"
  },
  "geometry": {"coordinates":[-71.688045,42.429242],"type":"Point"}
}
