{
  "type": "Feature",
  "properties": {
    "addr:full":"7 Progress Ave Chelmsford MA 01824",
    "addr:housenumber":"7",
    "addr:postcode":"01824",
    "addr:street":"Progress Ave",
    "iso:country":"US",
    "sg:address":"7 Progress Ave",
    "sg:city":"Chelmsford",
    "sg:classifiers":[
        {
            "category":"Professional",
            "subcategory":"Business Services",
            "type":"Services"
        }
    ],
    "sg:phone":"+1 978 250 0019",
    "sg:postcode":"01824",
    "sg:province":"MA",
    "sg:tags":[
        "pool",
        "swimming"
    ],
    "sg:website":"www.southshoregunitepools.com",
    "wof:name":"Guarino's Swimming Pool Svc",
    "wof:placetype":"venue"
},
  "geometry": {"coordinates":[-71.324995,42.599963],"type":"Point"}
}