{
  "type": "Feature",
  "properties": {
    "iso:country":"US",
    "sg:address":"30 Main St",
    "sg:city":"Amherst",
    "sg:classifiers":[
        {
            "category":"Shopping",
            "subcategory":"Shoes",
            "type":"Retail Goods"
        }
    ],
    "sg:phone":"+1 413 256 0727",
    "sg:postcode":"01002",
    "sg:province":"MA",
    "wof:name":"Footwear Den",
    "wof:placetype":"venue"
},
  "geometry": {"coordinates":[-72.519549,42.37574],"type":"Point"}
}