{
  "type": "Feature",
  "properties": {
    "addr:full": "Arsenal St Watertown MA 02471",
    "addr:postcode": "02471",
    "addr:street": "Arsenal St",
    "iso:country": "US",
    "sg:address": "Arsenal St",
    "sg:city": "Watertown",
    "sg:classifiers": [
      {
        "category": "Shopping",
        "subcategory": "Clothing, Apparel, \u0026 Fashions",
        "type": "Retail Goods"
      }
    ],
    "sg:phone": "+1 617 926 9325",
    "sg:postcode": "02471",
    "sg:province": "MA",
    "sg:tags": [
      "lingerie"
    ],
    "sg:website": "www.victoriassecret.com",
    "wof:name": "Victoria's Secret",
    "wof:placetype": "venue"
  },
  "geometry": {"coordinates":[-71.165105,42.363672],"type":"Point"}
}
