{
  "type": "Feature",
  "properties": {
    "iso:country":"US",
    "sg:address":"29 Wescott Street",
    "sg:city":"Malden",
    "sg:classifiers":[
        {
            "category":"Education",
            "subcategory":"School",
            "type":"Public Place"
        }
    ],
    "sg:phone":"+1 781 397 7329",
    "sg:postcode":"02148",
    "sg:province":"MA",
    "wof:name":"Malden City of",
    "wof:placetype":"venue"
},
  "geometry": {"coordinates":[-71.033652,42.434025],"type":"Point"}
}