{
  "type": "Feature",
  "properties": {
    "iso:country":"US",
    "sg:address":"152 Apremont Way",
    "sg:city":"Westfield",
    "sg:classifiers":[
        {
            "category":"Home & Garden",
            "subcategory":"Building Materials",
            "type":"Retail Goods"
        }
    ],
    "sg:phone":"+1 413 564 0003",
    "sg:postcode":"01085",
    "sg:province":"MA",
    "sg:tags":[
        "roofing"
    ],
    "wof:name":"Stacy Industrial Supply Co",
    "wof:placetype":"venue"
},
  "geometry": {"coordinates":[-72.723828,42.155421],"type":"Point"}
}