{
  "type": "Feature",
  "properties": {
    "iso:country":"US",
    "sg:address":"39 Glenville Ave",
    "sg:city":"Allston",
    "sg:classifiers":[
        {
            "category":"Building & Trades",
            "subcategory":"Construction",
            "type":"Services"
        }
    ],
    "sg:phone":"+1 617 444 9020",
    "sg:postcode":"02134",
    "sg:province":"MA",
    "sg:tags":[
        "roofing",
        "contractor"
    ],
    "sg:website":"www.roofing-ma.com/",
    "wof:name":"Roofing Contractor",
    "wof:placetype":"venue"
},
  "geometry": {"coordinates":[-71.13347899999999,42.350223],"type":"Point"}
}