{
  "type": "Feature",
  "properties": {
    "addr:full": "122 Bowen Street Boston MA 02127",
    "addr:housenumber": "122",
    "addr:postcode": "02127",
    "addr:street": "Bowen Street",
    "iso:country": "US",
    "sg:address": "122 Bowen Street",
    "sg:city": "Boston",
    "sg:classifiers": [
      {
        "category": "Coffee \u0026 Tea",
        "type": "Food \u0026 Drink"
      }
    ],
    "sg:phone": "+1 617 227 4865",
    "sg:postcode": "02127",
    "sg:province": "MA",
    "wof:name": "Capital Coffee House",
    "wof:placetype": "venue"
  },
  "geometry": {"coordinates":[-71.052774,42.337018],"type":"Point"}
}
