{
  "type": "Feature",
  "properties": {
    "iso:country":"US",
    "sg:address":"257 Rice Ave",
    "sg:city":"Northborough",
    "sg:classifiers":[
        {
            "category":"Building & Trades",
            "subcategory":"Plumbing",
            "type":"Services"
        }
    ],
    "sg:phone":"+1   ",
    "sg:postcode":"01532",
    "sg:province":"MA",
    "sg:tags":[
        "excavation",
        "tank",
        "installation",
        "septic",
        "contractor"
    ],
    "wof:name":"Back Hoe Dozer",
    "wof:placetype":"venue"
},
  "geometry": {"coordinates":[-71.629334,42.336391],"type":"Point"}
}