{
  "type": "Feature",
  "properties": {
    "iso:country":"US",
    "sg:address":"19 Anne Dr",
    "sg:city":"Peabody",
    "sg:classifiers":[
        {
            "category":"Professional",
            "subcategory":"Computer Services",
            "type":"Services"
        }
    ],
    "sg:phone":"+1   ",
    "sg:postcode":"01960",
    "sg:province":"MA",
    "sg:tags":[
        "related"
    ],
    "wof:name":"Administrative Services",
    "wof:placetype":"venue"
},
  "geometry": {"coordinates":[-71.014703,42.543977],"type":"Point"}
}