{
  "type": "Feature",
  "properties": {
    "addr:full":"92 Eastern Ave Arlington MA 02476",
    "addr:housenumber":"92",
    "addr:postcode":"02476",
    "addr:street":"Eastern Ave",
    "iso:country":"US",
    "sg:address":"92 Eastern Ave",
    "sg:city":"Arlington",
    "sg:classifiers":[
        {
            "category":"Real Estate",
            "subcategory":"Real Estate Agent",
            "type":"Services"
        }
    ],
    "sg:phone":"+1 781 643 0052",
    "sg:postcode":"02476",
    "sg:province":"MA",
    "sg:tags":[
        "appraiser"
    ],
    "wof:name":"Don Griffin Appraisals",
    "wof:placetype":"venue"
},
  "geometry": {"coordinates":[-71.17838399999999,42.413844],"type":"Point"}
}