{
  "type": "Feature",
  "properties": {
    "iso:country":"US",
    "sg:address":"205 Van Norden Rd",
    "sg:city":"Reading",
    "sg:classifiers":[
        {
            "category":"Building & Trades",
            "subcategory":"Construction",
            "type":"Services"
        }
    ],
    "sg:phone":"+1 781 944 8339",
    "sg:postcode":"01867",
    "sg:province":"MA",
    "sg:tags":[
        "contractor"
    ],
    "wof:name":"Whitney Construction",
    "wof:placetype":"venue"
},
  "geometry": {"coordinates":[-71.115402,42.5443],"type":"Point"}
}