{
  "type": "Feature",
  "properties": {
    "iso:country":"US",
    "sg:address":"39 Glasheen Rd",
    "sg:city":"Petersham",
    "sg:classifiers":[
        {
            "category":"Organizations",
            "subcategory":"Religious Organization",
            "type":"Services"
        }
    ],
    "sg:phone":"+1 978 724 3428",
    "sg:postcode":"01366",
    "sg:province":"MA",
    "sg:tags":[
        "house",
        "retreat"
    ],
    "wof:name":"Earthlands North Quabbin Farms",
    "wof:placetype":"venue"
},
  "geometry": {"coordinates":[-72.130684,42.505469],"type":"Point"}
}