{
  "type": "Feature",
  "properties": {
    "iso:country":"US",
    "sg:address":"435 Main St",
    "sg:city":"Fitchburg",
    "sg:classifiers":[
        {
            "category":"Professional",
            "subcategory":"Lawyer & Legal Services",
            "type":"Services"
        }
    ],
    "sg:phone":"+1 978 343 7772",
    "sg:postcode":"01420",
    "sg:province":"MA",
    "sg:tags":[
        "attorney"
    ],
    "wof:name":"Pall G Kalmansson Law Offices",
    "wof:placetype":"venue"
},
  "geometry": {"coordinates":[-71.799559,42.583135],"type":"Point"}
}