{
  "type": "Feature",
  "properties": {
    "addr:full": "292 Main St Hyannis MA 02601",
    "addr:housenumber": "292",
    "addr:postcode": "02601",
    "addr:street": "Main St",
    "iso:country": "US",
    "ovtr:label": "The Studio by the Sea, 292 Main St Hyannis MA US",
    "ovtr:similarity": 3.2138209342956543,
    "sg:address": "292 Main St",
    "sg:city": "Hyannis",
    "sg:classifiers": [
      {
        "category": "Retail",
        "subcategory": "Portrait Studio",
        "type": "Services"
      }
    ],
    "sg:phone": "+1 508 775 2552",
    "sg:postcode": "02601",
    "sg:province": "MA",
    "sg:tags": [
      "photography",
      "store"
    ],
    "wof:name": "Studio by the Sea the",
    "wof:placetype": "venue"
  },
  "geometry": {"coordinates":[-70.279198,41.654999],"type":"Point"}
}
