{
  "type": "Feature",
  "properties": {
    "iso:country":"US",
    "sg:address":"888 Worcester St",
    "sg:city":"Wellesley",
    "sg:classifiers":[
        {
            "category":"Professional",
            "subcategory":"Lawyer & Legal Services",
            "type":"Services"
        }
    ],
    "sg:phone":"+1 781 237 3030",
    "sg:postcode":"02482",
    "sg:province":"MA",
    "sg:tags":[
        "attorney",
        "practice"
    ],
    "wof:name":"The Law Offices of Anthony J Voci",
    "wof:placetype":"venue"
},
  "geometry": {"coordinates":[-71.317252,42.304959],"type":"Point"}
}