{
  "type": "Feature",
  "properties": {
    "iso:country":"US",
    "sg:address":"194 E Center St",
    "sg:city":"Lee",
    "sg:classifiers":[
        {
            "category":"Personal",
            "subcategory":"Beauty Salon",
            "type":"Services"
        }
    ],
    "sg:phone":"+1 413 243 2616",
    "sg:postcode":"01238",
    "sg:province":"MA",
    "sg:tags":[
        "shop"
    ],
    "wof:name":"Sandy's Place",
    "wof:placetype":"venue"
},
  "geometry": {"coordinates":[-73.245977,42.311906],"type":"Point"}
}