{
  "type": "Feature",
  "properties": {
    "iso:country":"US",
    "sg:address":"196 Hawthorn Rd",
    "sg:city":"Braintree",
    "sg:classifiers":[
        {
            "category":"Professional",
            "subcategory":"Lawyer & Legal Services",
            "type":"Services"
        }
    ],
    "sg:phone":"+1 781 843 8393",
    "sg:postcode":"02184",
    "sg:province":"MA",
    "sg:tags":[
        "attorney"
    ],
    "wof:name":"Peter Sorgi Attorney",
    "wof:placetype":"venue"
},
  "geometry": {"coordinates":[-71.001192,42.228599],"type":"Point"}
}