{
  "type": "Feature",
  "properties": {
    "addr:full": "196 Hawthorn Rd Braintree MA 02184",
    "addr:housenumber": "196",
    "addr:postcode": "02184",
    "addr:street": "Hawthorn Rd",
    "iso:country": "US",
    "sg:address": "196 Hawthorn Rd",
    "sg:city": "Braintree",
    "sg:classifiers": [
      {
        "category": "Professional",
        "subcategory": "Lawyer \u0026 Legal Services",
        "type": "Services"
      }
    ],
    "sg:phone": "+1 781 843 8393",
    "sg:postcode": "02184",
    "sg:province": "MA",
    "sg:tags": [
      "attorney"
    ],
    "wof:name": "Peter Sorgi Attorney",
    "wof:placetype": "venue"
  },
  "geometry": {"coordinates":[-71.001192,42.228599],"type":"Point"}
}
