{
  "type": "Feature",
  "properties": {
    "iso:country":"US",
    "sg:address":"1855 Washington Street",
    "sg:city":"Roxbury",
    "sg:classifiers":[
        {
            "category":"Real Estate",
            "subcategory":"Real Estate Services",
            "type":"Services"
        },
        {
            "category":"Real Estate",
            "subcategory":"Real Estate Operator",
            "type":"Services"
        }
    ],
    "sg:phone":"+1 617 427 1909",
    "sg:postcode":"02118",
    "sg:province":"MA",
    "sg:tags":[
        "apartment",
        "property",
        "management"
    ],
    "wof:name":"Mandela Homes",
    "wof:placetype":"venue"
},
  "geometry": {"coordinates":[-71.078682,42.33526],"type":"Point"}
}