{
  "type": "Feature",
  "properties": {
    "addr:full": "80 Park St Brookline MA 02446",
    "addr:housenumber": "80",
    "addr:postcode": "02446",
    "addr:street": "Park St",
    "iso:country": "US",
    "sg:address": "80 Park St",
    "sg:city": "Brookline",
    "sg:classifiers": [
      {
        "category": "Professional",
        "type": "Services"
      },
      {
        "category": "Professional",
        "subcategory": "Management \u0026 Consulting",
        "type": "Services"
      }
    ],
    "sg:phone": "+1 617 734 8113",
    "sg:postcode": "02446",
    "sg:province": "MA",
    "sg:tags": [
      "consultant",
      "manufacturing",
      "physicist"
    ],
    "wof:name": "Nonlinear Systems Inc",
    "wof:placetype": "venue"
  },
  "geometry": {"coordinates":[-71.124607,42.338649],"type":"Point"}
}
