{
  "type": "Feature",
  "properties": {
    "addr:full": "222 Broadway Chelsea MA 02150",
    "addr:housenumber": "222",
    "addr:postcode": "02150",
    "addr:street": "Broadway",
    "iso:country": "US",
    "sg:address": "222 Broadway",
    "sg:city": "Chelsea",
    "sg:classifiers": [
      {
        "category": "Food \u0026 Beverages",
        "subcategory": "Supermarket",
        "type": "Retail Goods"
      },
      {
        "category": "Retail",
        "subcategory": "Storage",
        "type": "Services"
      },
      {
        "category": "Food \u0026 Beverages",
        "subcategory": "Groceries \u0026 Convenience Stores",
        "type": "Retail Goods"
      }
    ],
    "sg:phone": "+1 617 884 0300",
    "sg:postcode": "02150",
    "sg:province": "MA",
    "sg:tags": [
      "kosher",
      "super"
    ],
    "wof:name": "Casablanca Market",
    "wof:placetype": "venue"
  },
  "geometry": {"coordinates":[-71.03858,42.390421],"type":"Point"}
}
