{
  "type": "Feature",
  "properties": {
    "addr:full": "182 Mount Tom Rd Northampton MA 01060",
    "addr:housenumber": "182",
    "addr:postcode": "01060",
    "addr:street": "Mount Tom Rd",
    "iso:country": "US",
    "sg:address": "182 Mount Tom Rd",
    "sg:city": "Northampton",
    "sg:classifiers": [
      {
        "category": "Wholesale",
        "subcategory": "Auto Parts",
        "type": "Manufacturing \u0026 Wholesale Goods"
      }
    ],
    "sg:phone": "+1 413 586 0690",
    "sg:postcode": "01060",
    "sg:province": "MA",
    "sg:tags": [
      "material",
      "used"
    ],
    "wof:name": "Highway Auto Salvage Inc",
    "wof:placetype": "venue"
  },
  "geometry": {"coordinates":[-72.622292,42.304103],"type":"Point"}
}
