{
  "type": "Feature",
  "properties": {
    "iso:country":"US",
    "sg:address":"88 Cocasset St",
    "sg:city":"Foxboro",
    "sg:classifiers":[
        {
            "category":"Real Estate",
            "subcategory":"Real Estate Agent",
            "type":"Services"
        }
    ],
    "sg:phone":"+1 508 543 6501",
    "sg:postcode":"02035",
    "sg:province":"MA",
    "sg:tags":[
        "appraiser"
    ],
    "wof:name":"Crown Appraisals",
    "wof:placetype":"venue"
},
  "geometry": {"coordinates":[-71.23693,42.06402],"type":"Point"}
}