{
  "type": "Feature",
  "properties": {
    "addr:full": "249 Oceana Way Norwood MA 02062",
    "addr:housenumber": "249",
    "addr:postcode": "02062",
    "addr:street": "Oceana Way",
    "iso:country": "US",
    "sg:address": "249 Oceana Way",
    "sg:city": "Norwood",
    "sg:classifiers": [
      {
        "category": "Freight",
        "type": "Transportation"
      }
    ],
    "sg:phone": "+1 617 277 7724",
    "sg:postcode": "02062",
    "sg:province": "MA",
    "wof:name": "Brookline Transportation Mvrs",
    "wof:placetype": "venue"
  },
  "geometry": {"coordinates":[-71.163933,42.201833],"type":"Point"}
}
