{
  "type": "Feature",
  "properties": {
    "iso:country":"US",
    "sg:address":"3 Boston Rd",
    "sg:city":"Sutton",
    "sg:classifiers":[
        {
            "category":"Restaurant",
            "type":"Food & Drink"
        }
    ],
    "sg:phone":"+1 508 865 7158",
    "sg:postcode":"01590",
    "sg:province":"MA",
    "sg:tags":[
        "parlor",
        "ice",
        "cream"
    ],
    "wof:name":"Kettle & KONE Cafe",
    "wof:placetype":"venue"
},
  "geometry": {"coordinates":[-71.72264699999999,42.174199],"type":"Point"}
}