{
  "type": "Feature",
  "properties": {
    "addr:full": "3 Boston Rd Sutton MA 01590",
    "addr:housenumber": "3",
    "addr:postcode": "01590",
    "addr:street": "Boston Rd",
    "iso:country": "US",
    "sg:address": "3 Boston Rd",
    "sg:city": "Sutton",
    "sg:classifiers": [
      {
        "category": "Restaurant",
        "type": "Food \u0026 Drink"
      }
    ],
    "sg:phone": "+1 508 865 7158",
    "sg:postcode": "01590",
    "sg:province": "MA",
    "sg:tags": [
      "parlor",
      "ice",
      "cream"
    ],
    "wof:name": "Kettle \u0026 KONE Cafe",
    "wof:placetype": "venue"
  },
  "geometry": {"coordinates":[-71.722647,42.174199],"type":"Point"}
}
