{
  "type": "Feature",
  "properties": {
    "iso:country":"US",
    "sg:address":"29 Russell St",
    "sg:city":"Hadley",
    "sg:classifiers":[
        {
            "category":"Restaurant",
            "type":"Food & Drink"
        }
    ],
    "sg:phone":"+1 413 584 9892",
    "sg:postcode":"01035",
    "sg:province":"MA",
    "wof:name":"Aqua Vitae Restaurant",
    "wof:placetype":"venue"
},
  "geometry": {"coordinates":[-72.609846,42.339294],"type":"Point"}
}