{
  "type": "Feature",
  "properties": {
    "addr:full": "29 Russell St Hadley MA 01035",
    "addr:housenumber": "29",
    "addr:postcode": "01035",
    "addr:street": "Russell St",
    "iso:country": "US",
    "sg:address": "29 Russell St",
    "sg:city": "Hadley",
    "sg:classifiers": [
      {
        "category": "Restaurant",
        "type": "Food \u0026 Drink"
      }
    ],
    "sg:phone": "+1 413 584 9892",
    "sg:postcode": "01035",
    "sg:province": "MA",
    "wof:name": "Aqua Vitae Restaurant",
    "wof:placetype": "venue"
  },
  "geometry": {"coordinates":[-72.609846,42.339294],"type":"Point"}
}
