{
  "type": "Feature",
  "properties": {
    "iso:country":"US",
    "sg:address":"459 S Main St",
    "sg:city":"Fall River",
    "sg:classifiers":[
        {
            "category":"Restaurant",
            "type":"Food & Drink"
        }
    ],
    "sg:phone":"+1 508 675 2420",
    "sg:postcode":"02721",
    "sg:province":"MA",
    "sg:tags":[
        "cafe"
    ],
    "wof:name":"Cafe Clipper",
    "wof:placetype":"venue"
},
  "geometry": {"coordinates":[-71.161337,41.696757],"type":"Point"}
}