{
  "type": "Feature",
  "properties": {
    "addr:full":"19 Peter Parley Rd Jamaica Plain MA 02130",
    "addr:housenumber":"19",
    "addr:postcode":"02130",
    "addr:street":"Peter Parley Rd",
    "iso:country":"US",
    "sg:address":"19 Peter Parley Rd",
    "sg:city":"Jamaica Plain",
    "sg:classifiers":[
        {
            "category":"Social Services",
            "subcategory":"Job Training",
            "type":"Services"
        }
    ],
    "sg:phone":"+1   ",
    "sg:postcode":"02130",
    "sg:province":"MA",
    "wof:name":"Family Solutions Institute",
    "wof:placetype":"venue"
},
  "geometry": {"coordinates":[-71.100787,42.310732],"type":"Point"}
}