{
  "type": "Feature",
  "properties": {
    "iso:country":"US",
    "sg:address":"356 Pleasant St",
    "sg:city":"Fall River",
    "sg:classifiers":[
        {
            "category":"Manufacturing",
            "subcategory":"Tools & Machinery",
            "type":"Manufacturing & Wholesale Goods"
        }
    ],
    "sg:phone":"+1 508 678 7432",
    "sg:postcode":"02721",
    "sg:province":"MA",
    "sg:tags":[
        "control"
    ],
    "sg:website":"www.gmrefrig.com",
    "wof:name":"G M Refrigeration Co",
    "wof:placetype":"venue"
},
  "geometry": {"coordinates":[-71.14957099999999,41.699463],"type":"Point"}
}