{
  "type": "Feature",
  "properties": {
    "iso:country":"US",
    "sg:address":"345 Court St",
    "sg:city":"Plymouth",
    "sg:classifiers":[
        {
            "category":"Professional",
            "subcategory":"Lawyer & Legal Services",
            "type":"Services"
        }
    ],
    "sg:phone":"+1 508 224 6060",
    "sg:postcode":"02360",
    "sg:province":"MA",
    "sg:tags":[
        "attorney"
    ],
    "wof:name":"Lewinger Mason & Duffy",
    "wof:placetype":"venue"
},
  "geometry": {"coordinates":[-70.68632100000001,41.975528],"type":"Point"}
}