{
  "type": "Feature",
  "properties": {
    "addr:full": "345 Court St Plymouth MA 02360",
    "addr:housenumber": "345",
    "addr:postcode": "02360",
    "addr:street": "Court St",
    "iso:country": "US",
    "sg:address": "345 Court St",
    "sg:city": "Plymouth",
    "sg:classifiers": [
      {
        "category": "Professional",
        "subcategory": "Lawyer \u0026 Legal Services",
        "type": "Services"
      }
    ],
    "sg:phone": "+1 508 224 6060",
    "sg:postcode": "02360",
    "sg:province": "MA",
    "sg:tags": [
      "attorney"
    ],
    "wof:name": "Lewinger Mason \u0026 Duffy",
    "wof:placetype": "venue"
  },
  "geometry": {"coordinates":[-70.686321,41.975528],"type":"Point"}
}
