{
  "type": "Feature",
  "properties": {
    "addr:full": "244 Willard St Quincy MA 02169",
    "addr:housenumber": "244",
    "addr:postcode": "02169",
    "addr:street": "Willard St",
    "iso:country": "US",
    "sg:address": "244 Willard St",
    "sg:city": "Quincy",
    "sg:classifiers": [
      {
        "category": "Building \u0026 Trades",
        "subcategory": "Plumbing",
        "type": "Services"
      }
    ],
    "sg:phone": "+1 617 770 9696",
    "sg:postcode": "02169",
    "sg:province": "MA",
    "sg:tags": [
      "conditioning",
      "air",
      "system",
      "contractor"
    ],
    "wof:name": "Sheehan Mechanical Contractors",
    "wof:placetype": "venue"
  },
  "geometry": {"coordinates":[-71.032939,42.247117],"type":"Point"}
}
