{
  "type": "Feature",
  "properties": {
    "addr:full":"135 Parker St Lawrence MA 01843",
    "addr:housenumber":"135",
    "addr:postcode":"01843",
    "addr:street":"Parker St",
    "iso:country":"US",
    "sg:address":"135 Parker St",
    "sg:city":"Lawrence",
    "sg:classifiers":[
        {
            "category":"Education",
            "subcategory":"Library",
            "type":"Public Place"
        }
    ],
    "sg:phone":"+1 978 794 5789",
    "sg:postcode":"01843",
    "sg:province":"MA",
    "wof:name":"Lawrence Library",
    "wof:placetype":"venue"
},
  "geometry": {"coordinates":[-71.158393,42.696894],"type":"Point"}
}