{
  "type": "Feature",
  "properties": {
    "addr:full": "Alewife Brook Parkway at Hight Street Somerville MA 02144",
    "addr:postcode": "02144",
    "addr:street": "Alewife Brook Parkway;Street",
    "iso:country": "US",
    "sg:address": "Alewife Brook Parkway at Hight Street",
    "sg:city": "Somerville",
    "sg:classifiers": [
      {
        "category": "Sports \u0026 Exercise",
        "subcategory": "Swimming Pool",
        "type": "Entertainment"
      }
    ],
    "sg:phone": "+1 617 623 9321",
    "sg:postcode": "02144",
    "sg:province": "MA",
    "sg:website": "www.mass.gov/dcr/recreate/pools.htm",
    "wof:name": "Dilboy Memorial Swimming and Wading Pool",
    "wof:placetype": "venue"
  },
  "geometry": {"coordinates":[-71.130882,42.410693],"type":"Point"}
}
