{
  "type": "Feature",
  "properties": {
    "iso:country":"US",
    "sg:address":"1437 Bedford St",
    "sg:city":"Abington",
    "sg:classifiers":[
        {
            "category":"Wholesale",
            "subcategory":"Durable Goods & Equipment",
            "type":"Manufacturing & Wholesale Goods"
        }
    ],
    "sg:phone":"+1 781 871 0508",
    "sg:postcode":"02351",
    "sg:province":"MA",
    "sg:tags":[
        "representative",
        "manufacturer"
    ],
    "sg:website":"www.johnsonmcgill.com",
    "wof:name":"Johnson & Mc Gill",
    "wof:placetype":"venue"
},
  "geometry": {"coordinates":[-70.952562,42.141763],"type":"Point"}
}