{
  "type": "Feature",
  "properties": {
    "addr:full": "30 Warren Street Brighton MA 02135",
    "addr:housenumber": "30",
    "addr:postcode": "02135",
    "addr:street": "Warren Street",
    "iso:country": "US",
    "sg:address": "30 Warren Street",
    "sg:city": "Brighton",
    "sg:classifiers": [
      {
        "category": "Sports \u0026 Exercise",
        "subcategory": "Gym",
        "type": "Entertainment"
      }
    ],
    "sg:phone": "+1 617 789 3667",
    "sg:postcode": "02135",
    "sg:province": "MA",
    "sg:tags": [
      "trainer"
    ],
    "wof:name": "Haelen Health Systems",
    "wof:placetype": "venue"
  },
  "geometry": {"coordinates":[-71.14354,42.349502],"type":"Point"}
}
