{
  "type": "Feature",
  "properties": {
    "addr:full": "1129 Walnut St Newton MA 02461",
    "addr:housenumber": "1129",
    "addr:postcode": "02461",
    "addr:street": "Walnut St",
    "iso:country": "US",
    "sg:address": "1129 Walnut St",
    "sg:city": "Newton",
    "sg:classifiers": [
      {
        "category": "Social Services",
        "type": "Services"
      }
    ],
    "sg:phone": "+1 617 965 7433",
    "sg:postcode": "02461",
    "sg:province": "MA",
    "wof:name": "ABF Counseling",
    "wof:placetype": "venue"
  },
  "geometry": {"coordinates":[-71.207064,42.3227],"type":"Point"}
}
