{
  "type": "Feature",
  "properties": {
    "iso:country":"US",
    "sg:address":"89 Otis St",
    "sg:city":"Milton",
    "sg:classifiers":[
        {
            "category":"Professional",
            "subcategory":"Business Services",
            "type":"Services"
        }
    ],
    "sg:phone":"+1   ",
    "sg:postcode":"02186",
    "sg:province":"MA",
    "wof:name":"Drumin Financial",
    "wof:placetype":"venue"
},
  "geometry": {"coordinates":[-71.049498,42.257889],"type":"Point"}
}