{
  "type": "Feature",
  "properties": {
    "addr:full":"43 Green Street Charlestown MA 02129",
    "addr:housenumber":"43",
    "addr:postcode":"02129",
    "addr:street":"Green Street",
    "iso:country":"US",
    "sg:address":"43 Green Street",
    "sg:city":"Charlestown",
    "sg:classifiers":[
        {
            "category":"Professional",
            "subcategory":"Lawyer & Legal Services",
            "type":"Services"
        }
    ],
    "sg:phone":"+1 617 242 2266",
    "sg:postcode":"02129",
    "sg:province":"MA",
    "wof:name":"McNally Paul Atty",
    "wof:placetype":"venue"
},
  "geometry": {"coordinates":[-71.06303699999999,42.377378],"type":"Point"}
}