{
  "type": "Feature",
  "properties": {
    "iso:country":"US",
    "sg:address":"72 Spring St",
    "sg:city":"Millis",
    "sg:classifiers":[
        {
            "category":"Professional",
            "type":"Services"
        }
    ],
    "sg:phone":"+1   ",
    "sg:postcode":"02054",
    "sg:province":"MA",
    "wof:name":"Millis Senior League Baseball",
    "wof:placetype":"venue"
},
  "geometry": {"coordinates":[-71.361379,42.163719],"type":"Point"}
}