{
  "type": "Feature",
  "properties": {
    "addr:full": "611 Common St Lawrence MA 01840",
    "addr:housenumber": "611",
    "addr:postcode": "01840",
    "addr:street": "Common",
    "iso:country": "US",
    "sg:address": "611 Common St",
    "sg:city": "Lawrence",
    "sg:classifiers": [
      {
        "category": "Health Services",
        "subcategory": "Clinic",
        "type": "Services"
      }
    ],
    "sg:phone": "+1 978 989 0808",
    "sg:postcode": "01840",
    "sg:province": "MA",
    "wof:name": "Synergy Health Care",
    "wof:placetype": "venue"
  },
  "geometry": {"coordinates":[-71.169413,42.7052],"type":"Point"}
}
