{
  "type": "Feature",
  "properties": {
    "iso:country":"US",
    "sg:address":"6 Florence St",
    "sg:city":"Somerville",
    "sg:classifiers":[
        {
            "category":"Professional",
            "subcategory":"Employment Agencies",
            "type":"Services"
        }
    ],
    "sg:phone":"+1   ",
    "sg:postcode":"02145",
    "sg:province":"MA",
    "sg:tags":[
        "help",
        "supply"
    ],
    "wof:name":"White Bear Cleaning & Maint",
    "wof:placetype":"venue"
},
  "geometry": {"coordinates":[-71.08321100000001,42.382707],"type":"Point"}
}