{
  "type": "Feature",
  "properties": {
    "addr:full": "6 Florence St Somerville MA 02145",
    "addr:housenumber": "6",
    "addr:postcode": "02145",
    "addr:street": "Florence St",
    "iso:country": "US",
    "sg:address": "6 Florence St",
    "sg:city": "Somerville",
    "sg:classifiers": [
      {
        "category": "Professional",
        "subcategory": "Employment Agencies",
        "type": "Services"
      }
    ],
    "sg:phone": "+1   ",
    "sg:postcode": "02145",
    "sg:province": "MA",
    "sg:tags": [
      "help",
      "supply"
    ],
    "wof:name": "White Bear Cleaning \u0026 Maint",
    "wof:placetype": "venue"
  },
  "geometry": {"coordinates":[-71.083211,42.382707],"type":"Point"}
}
