{
  "type": "Feature",
  "properties": {
    "addr:full": "22 Waterview Dr Medway MA 02053",
    "addr:housenumber": "22",
    "addr:postcode": "02053",
    "addr:street": "Waterview Dr",
    "iso:country": "US",
    "sg:address": "22 Waterview Dr",
    "sg:city": "Medway",
    "sg:classifiers": [
      {
        "category": "Professional",
        "subcategory": "Accounting \u0026 Tax Preparation",
        "type": "Services"
      }
    ],
    "sg:phone": "+1 508 533 4692",
    "sg:postcode": "02053",
    "sg:province": "MA",
    "sg:tags": [
      "return",
      "filing"
    ],
    "wof:name": "Rolando Yap \u0026 Co",
    "wof:placetype": "venue"
  },
  "geometry": {"coordinates":[-71.434783,42.137487],"type":"Point"}
}
