{
  "type": "Feature",
  "properties": {
    "addr:full":"29 Agnes Ln Chatham MA 02633",
    "addr:housenumber":"29",
    "addr:postcode":"02633",
    "addr:street":"Agnes Ln",
    "iso:country":"US",
    "sg:address":"29 Agnes Ln",
    "sg:city":"Chatham",
    "sg:classifiers":[
        {
            "category":"Building & Trades",
            "subcategory":"Construction",
            "type":"Services"
        }
    ],
    "sg:phone":"+1   ",
    "sg:postcode":"02633",
    "sg:province":"MA",
    "sg:tags":[
        "house"
    ],
    "wof:name":"Wilkins Construction",
    "wof:placetype":"venue"
},
  "geometry": {"coordinates":[-69.98350000000001,41.694036],"type":"Point"}
}