{
  "type": "Feature",
  "properties": {
    "iso:country":"US",
    "sg:address":"252 Grange Hall Rd",
    "sg:city":"Dalton",
    "sg:classifiers":[
        {
            "category":"Building & Trades",
            "subcategory":"Pest Control",
            "type":"Services"
        }
    ],
    "sg:phone":"+1 413 684 3204",
    "sg:postcode":"01226",
    "sg:province":"MA",
    "sg:tags":[
        "deodorizing",
        "disinfecting"
    ],
    "wof:name":"Bryant Companies",
    "wof:placetype":"venue"
},
  "geometry": {"coordinates":[-73.173359,42.460617],"type":"Point"}
}