{
  "type": "Feature",
  "properties": {
    "iso:country":"US",
    "sg:address":"200 Partridgeville Rd",
    "sg:city":"Templeton",
    "sg:classifiers":[
        {
            "category":"Organizations",
            "subcategory":"Community Association",
            "type":"Services"
        }
    ],
    "sg:phone":"+1 978 939 2126",
    "sg:postcode":"01468",
    "sg:province":"MA",
    "sg:tags":[
        "club"
    ],
    "wof:name":"Templeton Fish & Game Club Inc",
    "wof:placetype":"venue"
},
  "geometry": {"coordinates":[-72.04004399999999,42.547588],"type":"Point"}
}