{
  "type": "Feature",
  "properties": {
    "addr:full":"50 Tower Rd Newton MA 02464",
    "addr:housenumber":"50",
    "addr:postcode":"02464",
    "addr:street":"Tower Rd",
    "iso:country":"US",
    "sg:address":"50 Tower Rd",
    "sg:city":"Newton",
    "sg:classifiers":[
        {
            "category":"Autos & Motor Vehicles",
            "subcategory":"Automobile Sales",
            "type":"Retail Goods"
        }
    ],
    "sg:phone":"+1 617 964 9500",
    "sg:postcode":"02464",
    "sg:province":"MA",
    "sg:tags":[
        "car",
        "dealer"
    ],
    "wof:name":"Prestige Auto",
    "wof:placetype":"venue"
},
  "geometry": {"coordinates":[-71.216415,42.310974],"type":"Point"}
}