{
  "type": "Feature",
  "properties": {
    "addr:full": "832 Converse St Longmeadow MA 01106",
    "addr:housenumber": "832",
    "addr:postcode": "01106",
    "addr:street": "Converse St",
    "iso:country": "US",
    "ovtr:label": "Genesis House, 832 Converse St Longmeadow MA US",
    "ovtr:similarity": 2.3515539169311523,
    "sg:address": "832 Converse St",
    "sg:city": "Longmeadow",
    "sg:classifiers": [
      {
        "category": "Real Estate",
        "subcategory": "Real Estate Operator",
        "type": "Services"
      }
    ],
    "sg:phone": "+1 413 567 0350",
    "sg:postcode": "01106",
    "sg:province": "MA",
    "sg:tags": [
      "apartment"
    ],
    "wof:name": "Genesis House",
    "wof:placetype": "venue"
  },
  "geometry": {"coordinates":[-72.549469,42.061668],"type":"Point"}
}
