{
  "type": "Feature",
  "properties": {
    "addr:full":"26 Hampton Rd Natick MA 01760",
    "addr:housenumber":"26",
    "addr:postcode":"01760",
    "addr:street":"Hampton Rd",
    "iso:country":"US",
    "sg:address":"26 Hampton Rd",
    "sg:city":"Natick",
    "sg:classifiers":[
        {
            "category":"Professional",
            "subcategory":"Management & Consulting",
            "type":"Services"
        }
    ],
    "sg:phone":"+1 508 655 2929",
    "sg:postcode":"01760",
    "sg:province":"MA",
    "sg:tags":[
        "consultant",
        "business"
    ],
    "wof:name":"Henry Reeves & Associates",
    "wof:placetype":"venue"
},
  "geometry": {"coordinates":[-71.376589,42.297632],"type":"Point"}
}