{
  "type": "Feature",
  "properties": {
    "addr:full":"1 Milk St 2nd Fl Boston MA 02109",
    "addr:housenumber":"1",
    "addr:postcode":"02109",
    "addr:street":"Milk St",
    "iso:country":"US",
    "sg:address":"1 Milk St 2nd Fl",
    "sg:city":"Boston",
    "sg:classifiers":[
        {
            "category":"Professional",
            "type":"Services"
        },
        {
            "category":"Education",
            "subcategory":"School",
            "type":"Public Place"
        }
    ],
    "sg:phone":"+1 617 350 6300",
    "sg:postcode":"02109",
    "sg:province":"MA",
    "sg:website":"www.interise.org/",
    "wof:name":"Interise",
    "wof:placetype":"venue"
},
  "geometry": {"coordinates":[-71.0586,42.3566],"type":"Point"}
}