{
  "type": "Feature",
  "properties": {
    "addr:full":"16 Broadway Salisbury MA 01952",
    "addr:housenumber":"16",
    "addr:postcode":"01952",
    "addr:street":"Broadway",
    "iso:country":"US",
    "sg:address":"16 Broadway",
    "sg:city":"Salisbury",
    "sg:classifiers":[
        {
            "category":"Shopping",
            "subcategory":"Gifts & Souvenirs",
            "type":"Retail Goods"
        }
    ],
    "sg:phone":"+1 978 499 0607",
    "sg:postcode":"01952",
    "sg:province":"MA",
    "wof:name":"Sand Dollar Gifts",
    "wof:placetype":"venue"
},
  "geometry": {"coordinates":[-70.817061,42.842274],"type":"Point"}
}