{
  "type": "Feature",
  "properties": {
    "iso:country":"US",
    "sg:address":"21A Olympia Ave",
    "sg:city":"Woburn",
    "sg:classifiers":[
        {
            "category":"Building & Trades",
            "subcategory":"Locksmith",
            "type":"Services"
        }
    ],
    "sg:phone":"+1 781 904 0343",
    "sg:postcode":"01801",
    "sg:province":"MA",
    "sg:tags":[
        "key"
    ],
    "wof:name":"Woburn Emergency Locksmith",
    "wof:placetype":"venue"
},
  "geometry": {"coordinates":[-71.128398,42.500124],"type":"Point"}
}