{
  "type": "Feature",
  "properties": {
    "addr:full":"1130 Pleasant St Worcester MA 01602",
    "addr:housenumber":"1130",
    "addr:postcode":"01602",
    "addr:street":"Pleasant St",
    "iso:country":"US",
    "sg:address":"1130 Pleasant St",
    "sg:city":"Worcester",
    "sg:classifiers":[
        {
            "category":"Restaurant",
            "type":"Food & Drink"
        }
    ],
    "sg:phone":"+1 508 795 1111",
    "sg:postcode":"01602",
    "sg:province":"MA",
    "sg:tags":[
        "delicatessen"
    ],
    "wof:name":"Express Line",
    "wof:placetype":"venue"
},
  "geometry": {"coordinates":[-71.85351199999999,42.278302],"type":"Point"}
}