{
  "type": "Feature",
  "properties": {
    "iso:country":"US",
    "sg:address":"350 Merrimac St",
    "sg:city":"Newburyport",
    "sg:classifiers":[
        {
            "category":"Real Estate",
            "subcategory":"Developer",
            "type":"Services"
        }
    ],
    "sg:phone":"+1 978 463 7771",
    "sg:postcode":"01950",
    "sg:province":"MA",
    "wof:name":"O'Reilly & Cunningham",
    "wof:placetype":"venue"
},
  "geometry": {"coordinates":[-70.888081,42.823227],"type":"Point"}
}