{
  "type": "Feature",
  "properties": {
    "addr:full":"149 Longwood Ave Brookline MA 02446",
    "addr:housenumber":"149",
    "addr:postcode":"02446",
    "addr:street":"Longwood Ave",
    "iso:country":"US",
    "sg:address":"149 Longwood Ave",
    "sg:city":"Brookline",
    "sg:classifiers":[
        {
            "category":"Professional",
            "subcategory":"Research",
            "type":"Services"
        }
    ],
    "sg:phone":"+1 617 278 9851",
    "sg:postcode":"02446",
    "sg:province":"MA",
    "wof:name":"Webonomics",
    "wof:placetype":"venue"
},
  "geometry": {"coordinates":[-71.11301899999999,42.340399],"type":"Point"}
}