{
  "type": "Feature",
  "properties": {
    "iso:country":"US",
    "sg:address":"56 Pleasant Street",
    "sg:city":"Malden",
    "sg:classifiers":[
        {
            "category":"Shopping",
            "subcategory":"Jewelry",
            "type":"Retail Goods"
        },
        {
            "category":"Shopping",
            "subcategory":"Pawn Shop",
            "type":"Retail Goods"
        }
    ],
    "sg:phone":"+1 781 321 2242",
    "sg:postcode":"02148",
    "sg:province":"MA",
    "wof:name":"Appraisal Authority of America",
    "wof:placetype":"venue"
},
  "geometry": {"coordinates":[-71.068516,42.426891],"type":"Point"}
}