{
  "type": "Feature",
  "properties": {
    "addr:full": "4 Longfellow Pl Boston MA 02114",
    "addr:housenumber": "4",
    "addr:postcode": "02114",
    "addr:street": "Longfellow Pl",
    "iso:country": "US",
    "sg:address": "4 Longfellow Pl",
    "sg:city": "Boston",
    "sg:classifiers": [
      {
        "category": "Professional",
        "subcategory": "Lawyer \u0026 Legal Services",
        "type": "Services"
      }
    ],
    "sg:phone": "+1 617 227 4999",
    "sg:postcode": "02114",
    "sg:province": "MA",
    "wof:name": "Amoroso Thos J Atty",
    "wof:placetype": "venue"
  },
  "geometry": {"coordinates":[-71.063698,42.3634],"type":"Point"}
}
