{
  "type": "Feature",
  "properties": {
    "addr:full":"19 Yawkey Way Ste 23 Boston MA 02215",
    "addr:housenumber":"19",
    "addr:postcode":"02215",
    "addr:street":"Yawkey Way Ste 23",
    "iso:country":"US",
    "sg:address":"19 Yawkey Way Ste 23",
    "sg:city":"Boston",
    "sg:classifiers":[
        {
            "category":"Shopping",
            "subcategory":"Gifts & Souvenirs",
            "type":"Retail Goods"
        },
        {
            "category":"Retail",
            "subcategory":"Repair Shop",
            "type":"Services"
        },
        {
            "category":"Shopping",
            "subcategory":"Antiques",
            "type":"Retail Goods"
        }
    ],
    "sg:phone":"+1 617 437 1384",
    "sg:postcode":"02215",
    "sg:province":"MA",
    "sg:tags":[
        "dealers-wholesale",
        "pleating",
        "hemstitching"
    ],
    "sg:website":"http://www.twins.com",
    "wof:name":"Twins New York",
    "wof:placetype":"venue"
},
  "geometry": {"coordinates":[-71.09858699999999,42.346111],"type":"Point"}
}