{
  "type": "Feature",
  "properties": {
    "addr:full":"1 Court Sq Orange MA 01351",
    "addr:housenumber":"1",
    "addr:postcode":"01351",
    "addr:street":"Court Sq",
    "iso:country":"US",
    "sg:address":"1 Court Sq",
    "sg:city":"Orange",
    "sg:classifiers":[
        {
            "category":"Social Services",
            "type":"Services"
        }
    ],
    "sg:phone":"+1 978 544 8281",
    "sg:postcode":"01351",
    "sg:province":"MA",
    "sg:tags":[
        "probation"
    ],
    "wof:name":"Probation Office",
    "wof:placetype":"venue"
},
  "geometry": {"coordinates":[-72.53530499999999,42.535384],"type":"Point"}
}