{
  "type": "Feature",
  "properties": {
    "addr:full":"109 Main St Amesbury MA 01913",
    "addr:housenumber":"109",
    "addr:postcode":"01913",
    "addr:street":"Main St",
    "iso:country":"US",
    "sg:address":"109 Main St",
    "sg:city":"Amesbury",
    "sg:classifiers":[
        {
            "category":"Arts & Performance",
            "subcategory":"Theater",
            "type":"Entertainment"
        }
    ],
    "sg:phone":"+1 978 388 6555",
    "sg:postcode":"01913",
    "sg:province":"MA",
    "wof:name":"Stage Two Cinema Pub",
    "wof:placetype":"venue"
},
  "geometry": {"coordinates":[-70.931375,42.856217],"type":"Point"}
}