{
  "type": "Feature",
  "properties": {
    "iso:country":"US",
    "sg:address":"403 Main St",
    "sg:city":"Chatham",
    "sg:classifiers":[
        {
            "category":"Shopping",
            "subcategory":"Gifts & Souvenirs",
            "type":"Retail Goods"
        }
    ],
    "sg:phone":"+1 508 945 4729",
    "sg:postcode":"02633",
    "sg:province":"MA",
    "sg:tags":[
        "shop"
    ],
    "wof:name":"Lion's Paw",
    "wof:placetype":"venue"
},
  "geometry": {"coordinates":[-69.954303,41.678882],"type":"Point"}
}