{
  "type": "Feature",
  "properties": {
    "iso:country":"US",
    "sg:address":"31 S Deerfield Byp",
    "sg:city":"South Deerfield",
    "sg:classifiers":[
        {
            "category":"Shopping",
            "subcategory":"Computers & Home Electronics",
            "type":"Retail Goods"
        }
    ],
    "sg:phone":"+1 413 665 2341",
    "sg:postcode":"01373",
    "sg:province":"MA",
    "sg:tags":[
        "equipment",
        "dealer"
    ],
    "wof:name":"East Coast Modular PC",
    "wof:placetype":"venue"
},
  "geometry": {"coordinates":[-72.614267,42.473587],"type":"Point"}
}