{
  "type": "Feature",
  "properties": {
    "addr:full": "31 S Deerfield Byp South Deerfield MA 01373",
    "addr:housenumber": "31",
    "addr:postcode": "01373",
    "addr:street": "S Deerfield Byp",
    "iso:country": "US",
    "sg:address": "31 S Deerfield Byp",
    "sg:city": "South Deerfield",
    "sg:classifiers": [
      {
        "category": "Shopping",
        "subcategory": "Computers \u0026 Home Electronics",
        "type": "Retail Goods"
      }
    ],
    "sg:phone": "+1 413 665 2341",
    "sg:postcode": "01373",
    "sg:province": "MA",
    "sg:tags": [
      "equipment",
      "dealer"
    ],
    "wof:name": "East Coast Modular PC",
    "wof:placetype": "venue"
  },
  "geometry": {"coordinates":[-72.614267,42.473587],"type":"Point"}
}
