{
  "type": "Feature",
  "properties": {
    "addr:full":"502 Stafford St Cherry Valley MA 01611",
    "addr:housenumber":"502",
    "addr:postcode":"01611",
    "addr:street":"Stafford St",
    "iso:country":"US",
    "sg:address":"502 Stafford St",
    "sg:city":"Cherry Valley",
    "sg:classifiers":[
        {
            "category":"Building & Trades",
            "subcategory":"Construction",
            "type":"Services"
        }
    ],
    "sg:phone":"+1   ",
    "sg:postcode":"01611",
    "sg:province":"MA",
    "sg:tags":[
        "carpentry",
        "contractor"
    ],
    "wof:name":"Christopher Splaine",
    "wof:placetype":"venue"
},
  "geometry": {"coordinates":[-71.867931,42.225722],"type":"Point"}
}