{
  "type": "Feature",
  "properties": {
    "addr:full":"161 Neponset Avenue Dorchester MA 02122",
    "addr:housenumber":"161",
    "addr:postcode":"02122",
    "addr:street":"Neponset Avenue",
    "iso:country":"US",
    "sg:address":"161 Neponset Avenue",
    "sg:city":"Dorchester",
    "sg:classifiers":[
        {
            "category":"Professional",
            "subcategory":"Lawyer & Legal Services",
            "type":"Services"
        }
    ],
    "sg:phone":"+1 617 282 2712",
    "sg:postcode":"02122",
    "sg:province":"MA",
    "wof:name":"Baker & Pinson",
    "wof:placetype":"venue"
},
  "geometry": {"coordinates":[-71.050833,42.293245],"type":"Point"}
}