{
  "type": "Feature",
  "properties": {
    "addr:full": "730 Boston Post Rd Ste 26 Sudbury MA 01776",
    "addr:housenumber": "730",
    "addr:postcode": "01776",
    "addr:street": "Boston Post Rd Ste 26",
    "iso:country": "US",
    "sg:address": "730 Boston Post Rd Ste 26",
    "sg:city": "Sudbury",
    "sg:classifiers": [
      {
        "category": "Real Estate",
        "subcategory": "Real Estate Services",
        "type": "Services"
      },
      {
        "category": "Real Estate",
        "subcategory": "Real Estate Agent",
        "type": "Services"
      }
    ],
    "sg:phone": "+1 978 443 6330",
    "sg:postcode": "01776",
    "sg:province": "MA",
    "sg:tags": [
      "buyer",
      "broker"
    ],
    "wof:name": "Bill Stone Realty",
    "wof:placetype": "venue"
  },
  "geometry": {"coordinates":[-71.450011,42.360252],"type":"Point"}
}
