{
  "type": "Feature",
  "properties": {
    "addr:full":"84 Bow Street Medford MA 02155",
    "addr:housenumber":"84",
    "addr:postcode":"02155",
    "addr:street":"Bow Street",
    "iso:country":"US",
    "sg:address":"84 Bow Street",
    "sg:city":"Medford",
    "sg:classifiers":[
        {
            "category":"Retail",
            "subcategory":"Laundry & Dry Cleaning",
            "type":"Services"
        }
    ],
    "sg:phone":"+1 781 393 4471",
    "sg:postcode":"02155",
    "sg:province":"MA",
    "wof:name":"Star Cleaning & Maintenance Company",
    "wof:placetype":"venue"
},
  "geometry": {"coordinates":[-71.100042,42.397056],"type":"Point"}
}