{
  "type": "Feature",
  "properties": {
    "iso:country":"US",
    "sg:address":"149 Providence St",
    "sg:city":"Hyde Park",
    "sg:classifiers":[
        {
            "category":"Building & Trades",
            "subcategory":"Construction",
            "type":"Services"
        }
    ],
    "sg:phone":"+1 617 360 9986",
    "sg:postcode":"02136",
    "sg:province":"MA",
    "sg:tags":[
        "driveway"
    ],
    "wof:name":"Wildeca Corp",
    "wof:placetype":"venue"
},
  "geometry": {"coordinates":[-71.122175,42.267191],"type":"Point"}
}