{
  "type": "Feature",
  "properties": {
    "addr:full": "1025 Main St South Weymouth MA 02190",
    "addr:housenumber": "1025",
    "addr:postcode": "02190",
    "addr:street": "Main St",
    "iso:country": "US",
    "sg:address": "1025 Main St",
    "sg:city": "South Weymouth",
    "sg:classifiers": [
      {
        "category": "Restaurant",
        "type": "Food \u0026 Drink"
      }
    ],
    "sg:phone": "+1 781 331 1360",
    "sg:postcode": "02190",
    "sg:province": "MA",
    "wof:name": "Chinese Food",
    "wof:placetype": "venue"
  },
  "geometry": {"coordinates":[-70.955351,42.170691],"type":"Point"}
}
