{
  "type": "Feature",
  "properties": {
    "iso:country":"US",
    "sg:address":"92 Poplar St",
    "sg:city":"Feeding Hills",
    "sg:classifiers":[
        {
            "category":"Autos & Motor Vehicles",
            "subcategory":"Automobile Sales",
            "type":"Retail Goods"
        }
    ],
    "sg:phone":"+1 413 786 3164",
    "sg:postcode":"01030",
    "sg:province":"MA",
    "sg:tags":[
        "car",
        "dealer"
    ],
    "wof:name":"Laser Auto Ctr",
    "wof:placetype":"venue"
},
  "geometry": {"coordinates":[-72.662935,42.068351],"type":"Point"}
}