{
  "type": "Feature",
  "properties": {
    "iso:country":"US",
    "sg:address":"35 Main St",
    "sg:city":"Vineyard Haven",
    "sg:classifiers":[
        {
            "category":"Home & Garden",
            "subcategory":"Furniture",
            "type":"Retail Goods"
        }
    ],
    "sg:phone":"+1 508 693 9441",
    "sg:postcode":"02568",
    "sg:province":"MA",
    "wof:name":"Bowl & Board Of The Vineyard",
    "wof:placetype":"venue"
},
  "geometry": {"coordinates":[-70.602755,41.455175],"type":"Point"}
}