{
  "type": "Feature",
  "properties": {
    "addr:full": "35 Main St Vineyard Haven MA 02568",
    "addr:housenumber": "35",
    "addr:postcode": "02568",
    "addr:street": "Main St",
    "iso:country": "US",
    "sg:address": "35 Main St",
    "sg:city": "Vineyard Haven",
    "sg:classifiers": [
      {
        "category": "Home \u0026 Garden",
        "subcategory": "Furniture",
        "type": "Retail Goods"
      }
    ],
    "sg:phone": "+1 508 693 9441",
    "sg:postcode": "02568",
    "sg:province": "MA",
    "wof:name": "Bowl \u0026 Board Of The Vineyard",
    "wof:placetype": "venue"
  },
  "geometry": {"coordinates":[-70.602755,41.455175],"type":"Point"}
}
