{
  "type": "Feature",
  "properties": {
    "iso:country":"US",
    "sg:address":"26 Quobaug Ave",
    "sg:city":"Oxford",
    "sg:classifiers":[
        {
            "category":"Professional",
            "type":"Services"
        }
    ],
    "sg:phone":"+1 508 987 8666",
    "sg:postcode":"01540",
    "sg:province":"MA",
    "sg:tags":[
        "contractor"
    ],
    "wof:name":"Bedard G",
    "wof:placetype":"venue"
},
  "geometry": {"coordinates":[-71.87026,42.112805],"type":"Point"}
}