{
  "type": "Feature",
  "properties": {
    "addr:full": "130 Rosary Ln Hyannis MA 02601",
    "addr:housenumber": "130",
    "addr:postcode": "02601",
    "addr:street": "Rosary Ln",
    "iso:country": "US",
    "sg:address": "130 Rosary Ln",
    "sg:city": "Hyannis",
    "sg:classifiers": [
      {
        "category": "Autos \u0026 Motor Vehicles",
        "subcategory": "Auto Supplies",
        "type": "Retail Goods"
      },
      {
        "category": "Retail",
        "subcategory": "Auto Repair",
        "type": "Services"
      }
    ],
    "sg:phone": "+1 508 771 4581",
    "sg:postcode": "02601",
    "sg:province": "MA",
    "sg:tags": [
      "tire"
    ],
    "wof:name": "Nitro-Tire \u0026 Brake Shop",
    "wof:placetype": "venue"
  },
  "geometry": {"coordinates":[-70.267521,41.66992],"type":"Point"}
}
