{
  "type": "Feature",
  "properties": {
    "iso:country":"US",
    "sg:address":"130 Rosary Ln",
    "sg:city":"Hyannis",
    "sg:classifiers":[
        {
            "category":"Autos & Motor Vehicles",
            "subcategory":"Auto Supplies",
            "type":"Retail Goods"
        },
        {
            "category":"Retail",
            "subcategory":"Auto Repair",
            "type":"Services"
        }
    ],
    "sg:phone":"+1 508 771 4581",
    "sg:postcode":"02601",
    "sg:province":"MA",
    "sg:tags":[
        "tire"
    ],
    "wof:name":"Nitro-Tire & Brake Shop",
    "wof:placetype":"venue"
},
  "geometry": {"coordinates":[-70.267521,41.66992],"type":"Point"}
}