{
  "type": "Feature",
  "properties": {
    "addr:full": "140 Chestnut St Wilmington MA 01887",
    "addr:housenumber": "140",
    "addr:postcode": "01887",
    "addr:street": "Chestnut St",
    "iso:country": "US",
    "sg:address": "140 Chestnut St",
    "sg:city": "Wilmington",
    "sg:classifiers": [
      {
        "category": "Building \u0026 Trades",
        "subcategory": "Construction",
        "type": "Services"
      }
    ],
    "sg:phone": "+1   ",
    "sg:postcode": "01887",
    "sg:province": "MA",
    "sg:tags": [
      "house"
    ],
    "wof:name": "Dream Builders \u0026 Remodeling",
    "wof:placetype": "venue"
  },
  "geometry": {"coordinates":[-71.175131,42.533051],"type":"Point"}
}
