{
  "type": "Feature",
  "properties": {
    "iso:country":"US",
    "sg:address":"196 Middleton Rd",
    "sg:city":"Boxford",
    "sg:classifiers":[
        {
            "category":"Professional",
            "subcategory":"Advertising",
            "type":"Services"
        }
    ],
    "sg:phone":"+1 978 887 2598",
    "sg:postcode":"01921",
    "sg:province":"MA",
    "sg:tags":[
        "counselor"
    ],
    "sg:website":"www.thedahlgroup.com",
    "wof:name":"Dahl Group",
    "wof:placetype":"venue"
},
  "geometry": {"coordinates":[-70.992479,42.643273],"type":"Point"}
}