{
  "type": "Feature",
  "properties": {
    "iso:country":"US",
    "sg:address":"68 Main St",
    "sg:city":"Andover",
    "sg:classifiers":[
        {
            "category":"Professional",
            "type":"Services"
        }
    ],
    "sg:phone":"+1 978 474 9180",
    "sg:postcode":"01810",
    "sg:province":"MA",
    "sg:tags":[
        "establishment"
    ],
    "wof:name":"Barcelos Bros Andover",
    "wof:placetype":"venue"
},
  "geometry": {"coordinates":[-71.138704,42.653963],"type":"Point"}
}