{
  "type": "Feature",
  "properties": {
    "iso:country":"US",
    "sg:address":"156 Rowley Hill Rd",
    "sg:city":"Sterling",
    "sg:classifiers":[
        {
            "category":"Retail",
            "subcategory":"Repair Shop",
            "type":"Services"
        }
    ],
    "sg:phone":"+1   ",
    "sg:postcode":"01564",
    "sg:province":"MA",
    "wof:name":"Steve Torode",
    "wof:placetype":"venue"
},
  "geometry": {"coordinates":[-71.783607,42.461919],"type":"Point"}
}