{
  "type": "Feature",
  "properties": {
    "iso:country":"US",
    "sg:address":"689 Main St",
    "sg:city":"Haverhill",
    "sg:classifiers":[
        {
            "category":"Health Services",
            "subcategory":"Nursing And Care Facility",
            "type":"Services"
        }
    ],
    "sg:phone":"+1 978 373 1131",
    "sg:postcode":"01830",
    "sg:province":"MA",
    "sg:tags":[
        "home",
        "convalescent"
    ],
    "wof:name":"Oxford Manor Rehabilitation",
    "wof:placetype":"venue"
},
  "geometry": {"coordinates":[-71.085593,42.795308],"type":"Point"}
}