{
  "type": "Feature",
  "properties": {
    "addr:full": "160 Old Derby St Hingham MA 02043",
    "addr:housenumber": "160",
    "addr:postcode": "02043",
    "addr:street": "Old Derby St",
    "iso:country": "US",
    "sg:address": "160 Old Derby St",
    "sg:city": "Hingham",
    "sg:classifiers": [
      {
        "category": "Banks \u0026 Credit Unions",
        "subcategory": "Investment Brokerage",
        "type": "Services"
      }
    ],
    "sg:phone": "+1 781 749 7514",
    "sg:postcode": "02043",
    "sg:province": "MA",
    "wof:name": "Partners Investment Properties",
    "wof:placetype": "venue"
  },
  "geometry": {"coordinates":[-70.914722,42.18073],"type":"Point"}
}
