{
  "type": "Feature",
  "properties": {
    "addr:full":"541 Main St South Weymouth MA 02190",
    "addr:housenumber":"541",
    "addr:postcode":"02190",
    "addr:street":"Main St",
    "iso:country":"US",
    "sg:address":"541 Main St",
    "sg:city":"South Weymouth",
    "sg:classifiers":[
        {
            "category":"Shopping",
            "subcategory":"Shoes",
            "type":"Retail Goods"
        }
    ],
    "sg:phone":"+1 781 340 0444",
    "sg:postcode":"02190",
    "sg:province":"MA",
    "wof:name":"Orthotic Concepts Inc",
    "wof:placetype":"venue"
},
  "geometry": {"coordinates":[-70.955613,42.187754],"type":"Point"}
}