{
  "type": "Feature",
  "properties": {
    "addr:full": "24 North St Randolph MA 02368",
    "addr:housenumber": "24",
    "addr:postcode": "02368",
    "addr:street": "North St",
    "iso:country": "US",
    "sg:address": "24 North St",
    "sg:city": "Randolph",
    "sg:classifiers": [
      {
        "category": "Insurance",
        "subcategory": "Insurance Agent",
        "type": "Services"
      }
    ],
    "sg:phone": "+1 781 963 1112",
    "sg:postcode": "02368",
    "sg:province": "MA",
    "sg:website": "http://www.aicins.com/",
    "wof:name": "Acceptance Insurance Agency",
    "wof:placetype": "venue"
  },
  "geometry": {"coordinates":[-71.040593,42.163562],"type":"Point"}
}
