{
  "type": "Feature",
  "properties": {
    "addr:full":"9 Little Tree Ln Bellingham MA 02019",
    "addr:housenumber":"9",
    "addr:postcode":"02019",
    "addr:street":"Little Tree Ln",
    "iso:country":"US",
    "sg:address":"9 Little Tree Ln",
    "sg:city":"Bellingham",
    "sg:classifiers":[
        {
            "category":"Professional",
            "type":"Services"
        }
    ],
    "sg:phone":"+1   ",
    "sg:postcode":"02019",
    "sg:province":"MA",
    "wof:name":"Sterling Perrin",
    "wof:placetype":"venue"
},
  "geometry": {"coordinates":[-71.49466700000001,42.042111],"type":"Point"}
}