{
  "type": "Feature",
  "properties": {
    "addr:full": "22 Summer St Stoughton MA 02072",
    "addr:housenumber": "22",
    "addr:postcode": "02072",
    "addr:street": "Summer St",
    "iso:country": "US",
    "sg:address": "22 Summer St",
    "sg:city": "Stoughton",
    "sg:classifiers": [
      {
        "category": "Wholesale",
        "subcategory": "Durable Goods \u0026 Equipment",
        "type": "Manufacturing \u0026 Wholesale Goods"
      }
    ],
    "sg:phone": "+1 781 341 8740",
    "sg:postcode": "02072",
    "sg:province": "MA",
    "sg:tags": [
      "representative",
      "manufacturer"
    ],
    "wof:name": "Thomas Register-American Mfg",
    "wof:placetype": "venue"
  },
  "geometry": {"coordinates":[-71.104562,42.12372],"type":"Point"}
}
