{
  "type": "Feature",
  "properties": {
    "addr:full":"180 State Hwy 115 Dedham MA 02054",
    "addr:housenumber":"180",
    "addr:postcode":"02054",
    "addr:street":"State Hwy 115",
    "iso:country":"US",
    "sg:address":"180 State Hwy 115",
    "sg:city":"Dedham",
    "sg:classifiers":[
        {
            "category":"Organizations",
            "subcategory":"Membership Organization",
            "type":"Services"
        }
    ],
    "sg:phone":"+1 781 461 2212",
    "sg:postcode":"02054",
    "sg:province":"MA",
    "wof:name":"American Red Cross",
    "wof:placetype":"venue"
},
  "geometry": {"coordinates":[-71.355667,42.165723],"type":"Point"}
}