{
  "type": "Feature",
  "properties": {
    "iso:country":"US",
    "sg:address":"587 Washington Street",
    "sg:city":"Boston",
    "sg:classifiers":[
        {
            "category":"Real Estate",
            "subcategory":"Real Estate Services",
            "type":"Services"
        }
    ],
    "sg:phone":"+1 617 825 4224",
    "sg:postcode":"02111",
    "sg:province":"MA",
    "sg:tags":[
        "management",
        "property"
    ],
    "wof:name":"Codman Square Neighborhood Development Corporation",
    "wof:placetype":"venue"
},
  "geometry": {"coordinates":[-71.06238500000001,42.353168],"type":"Point"}
}