{
  "type": "Feature",
  "properties": {
    "addr:full":"1604 Hancock St Quincy MA 02169",
    "addr:housenumber":"1604",
    "addr:postcode":"02169",
    "addr:street":"Hancock St",
    "iso:country":"US",
    "sg:address":"1604 Hancock St",
    "sg:city":"Quincy",
    "sg:classifiers":[
        {
            "category":"Personal",
            "subcategory":"Beauty Salon",
            "type":"Services"
        }
    ],
    "sg:phone":"+1 617 984 5800",
    "sg:postcode":"02169",
    "sg:province":"MA",
    "wof:name":"Bliss Salon & Spa",
    "wof:placetype":"venue"
},
  "geometry": {"coordinates":[-71.00044699999999,42.246171],"type":"Point"}
}