{
  "type": "Feature",
  "properties": {
    "addr:full": "2 Kristen Ln Wareham MA 02571",
    "addr:housenumber": "2",
    "addr:postcode": "02571",
    "addr:street": "Kristen Ln",
    "iso:country": "US",
    "sg:address": "2 Kristen Ln",
    "sg:city": "Wareham",
    "sg:classifiers": [
      {
        "category": "Freight",
        "type": "Transportation"
      }
    ],
    "sg:phone": "+1 508 295 7159",
    "sg:postcode": "02571",
    "sg:province": "MA",
    "sg:tags": [
      "trucking"
    ],
    "wof:name": "R \u0026 S Oldfield",
    "wof:placetype": "venue"
  },
  "geometry": {"coordinates":[-70.687438,41.768186],"type":"Point"}
}
