{
  "type": "Feature",
  "properties": {
    "addr:full":"93 N Main St Randolph MA 02368",
    "addr:housenumber":"93",
    "addr:postcode":"02368",
    "addr:street":"N Main St",
    "iso:country":"US",
    "sg:address":"93 N Main St",
    "sg:city":"Randolph",
    "sg:classifiers":[
        {
            "category":"Professional",
            "subcategory":"Computer Services",
            "type":"Services"
        }
    ],
    "sg:phone":"+1 781 986 2947",
    "sg:postcode":"02368",
    "sg:province":"MA",
    "sg:tags":[
        "consultant",
        "designer"
    ],
    "wof:name":"Audeo Group Inc",
    "wof:placetype":"venue"
},
  "geometry": {"coordinates":[-71.042334,42.164037],"type":"Point"}
}