{
  "type": "Feature",
  "properties": {
    "addr:full": "449 Broadway Ave Cambridge MA 02138",
    "addr:housenumber": "449",
    "addr:postcode": "02138",
    "addr:street": "Broadway Ave",
    "iso:country": "US",
    "sg:address": "449 Broadway Ave",
    "sg:city": "Cambridge",
    "sg:classifiers": [
      {
        "category": "Education",
        "subcategory": "Library",
        "type": "Public Place"
      }
    ],
    "sg:phone": "+1 617 349 4040",
    "sg:postcode": "02138",
    "sg:province": "MA",
    "sg:website": "www.cambridgema.gov/CPL/",
    "wof:name": "Cambridge Main Public Library",
    "wof:placetype": "venue"
  },
  "geometry": {"coordinates":[-71.111112,42.373294],"type":"Point"}
}
