{
  "type": "Feature",
  "properties": {
    "addr:full":"362 Main St Falmouth MA 02540",
    "addr:housenumber":"362",
    "addr:postcode":"02540",
    "addr:street":"Main St",
    "iso:country":"US",
    "sg:address":"362 Main St",
    "sg:city":"Falmouth",
    "sg:classifiers":[
        {
            "category":"Professional",
            "subcategory":"Business Services",
            "type":"Services"
        }
    ],
    "sg:phone":"+1 508 548 3431",
    "sg:postcode":"02540",
    "sg:province":"MA",
    "sg:tags":[
        "interior",
        "consultant",
        "design",
        "decorator"
    ],
    "wof:name":"Edwards Interior Decorator",
    "wof:placetype":"venue"
},
  "geometry": {"coordinates":[-70.612475,41.552228],"type":"Point"}
}