{
  "type": "Feature",
  "properties": {
    "iso:country":"US",
    "sg:address":"10 Rose Morin Ln",
    "sg:city":"Falmouth",
    "sg:classifiers":[
        {
            "category":"Recreation",
            "type":"Entertainment"
        }
    ],
    "sg:phone":"+1 508 540 7991",
    "sg:postcode":"02540",
    "sg:province":"MA",
    "sg:tags":[
        "martial",
        "arts",
        "instruction"
    ],
    "wof:name":"Seven Stars Academy Of Martial",
    "wof:placetype":"venue"
},
  "geometry": {"coordinates":[-70.600853,41.557423],"type":"Point"}
}