{
  "type": "Feature",
  "properties": {
    "iso:country":"US",
    "sg:address":"3 Cook Rd",
    "sg:city":"Vineyard Haven",
    "sg:classifiers":[
        {
            "category":"Shopping",
            "subcategory":"Gifts & Souvenirs",
            "type":"Retail Goods"
        }
    ],
    "sg:phone":"+1 508 693 0556",
    "sg:postcode":"02568",
    "sg:province":"MA",
    "sg:tags":[
        "party",
        "supply"
    ],
    "wof:name":"Seaside Celebrations Tent Rntl",
    "wof:placetype":"venue"
},
  "geometry": {"coordinates":[-70.607894,41.448484],"type":"Point"}
}