{
  "type": "Feature",
  "properties": {
    "iso:country":"US",
    "sg:address":"10 Post Office Ave",
    "sg:city":"Andover",
    "sg:classifiers":[
        {
            "category":"Shopping",
            "subcategory":"Beauty & Cosmetics",
            "type":"Retail Goods"
        },
        {
            "category":"Personal",
            "subcategory":"Beauty Salon",
            "type":"Services"
        }
    ],
    "sg:phone":"+1 978 623 0985",
    "sg:postcode":"01810",
    "sg:province":"MA",
    "sg:tags":[
        "perfume",
        "salons-equipment",
        "supply"
    ],
    "wof:name":"Beauty and Main",
    "wof:placetype":"venue"
},
  "geometry": {"coordinates":[-71.14052599999999,42.656583],"type":"Point"}
}