{
  "type": "Feature",
  "properties": {
    "addr:full": "45 White Pond Rd Stow MA 01775",
    "addr:housenumber": "45",
    "addr:postcode": "01775",
    "addr:street": "White Pond Rd",
    "iso:country": "US",
    "sg:address": "45 White Pond Rd",
    "sg:city": "Stow",
    "sg:classifiers": [
      {
        "category": "Professional",
        "subcategory": "Engineering",
        "type": "Services"
      }
    ],
    "sg:phone": "+1 978 897 3600",
    "sg:postcode": "01775",
    "sg:province": "MA",
    "sg:tags": [
      "engineer"
    ],
    "wof:name": "Automation Technologies LLC",
    "wof:placetype": "venue"
  },
  "geometry": {"coordinates":[-71.481189,42.427002],"type":"Point"}
}
