{
  "type": "Feature",
  "properties": {
    "iso:country":"US",
    "sg:address":"164 Still River Rd",
    "sg:city":"Bolton",
    "sg:classifiers":[
        {
            "category":"Wholesale",
            "subcategory":"Electrical",
            "type":"Manufacturing & Wholesale Goods"
        }
    ],
    "sg:phone":"+1 978 368 0931",
    "sg:postcode":"01740",
    "sg:province":"MA",
    "sg:tags":[
        "coil",
        "machinery",
        "winding"
    ],
    "sg:website":"www.broomfieldusa.com",
    "wof:name":"Broomfield Laboratories Inc",
    "wof:placetype":"venue"
},
  "geometry": {"coordinates":[-71.63871399999999,42.459565],"type":"Point"}
}