{
  "type": "Feature",
  "properties": {
    "addr:full": "61 Greenwood Ave Swampscott MA 01907",
    "addr:housenumber": "61",
    "addr:postcode": "01907",
    "addr:street": "Greenwood Ave",
    "iso:country": "US",
    "sg:address": "61 Greenwood Ave",
    "sg:city": "Swampscott",
    "sg:classifiers": [
      {
        "category": "Arts \u0026 Performance",
        "subcategory": "Music",
        "type": "Entertainment"
      }
    ],
    "sg:phone": "+1 781 599 3527",
    "sg:postcode": "01907",
    "sg:province": "MA",
    "sg:tags": [
      "musician"
    ],
    "wof:name": "Barry Goudreau",
    "wof:placetype": "venue"
  },
  "geometry": {"coordinates":[-70.91065,42.469379],"type":"Point"}
}
