{
  "type": "Feature",
  "properties": {
    "addr:full": "247 S Main St Attleboro MA 02703",
    "addr:housenumber": "247",
    "addr:postcode": "02703",
    "addr:street": "S Main St",
    "iso:country": "US",
    "sg:address": "247 S Main St",
    "sg:city": "Attleboro",
    "sg:classifiers": [
      {
        "category": "Shopping",
        "subcategory": "Gifts \u0026 Souvenirs",
        "type": "Retail Goods"
      }
    ],
    "sg:phone": "+1 508 223 4300",
    "sg:postcode": "02703",
    "sg:province": "MA",
    "sg:tags": [
      "flower"
    ],
    "sg:website": "www.thecornerflowershoppe.net",
    "wof:name": "The Corner Flower Shoppe",
    "wof:placetype": "venue"
  },
  "geometry": {"coordinates":[-71.285048,41.933025],"type":"Point"}
}
