{
  "type": "Feature",
  "properties": {
    "addr:full": "330 Brookline Ave Boston MA 02215",
    "addr:housenumber": "330",
    "addr:postcode": "02215",
    "addr:street": "Brookline Ave",
    "iso:country": "US",
    "sg:address": "330 Brookline Ave",
    "sg:city": "Boston",
    "sg:classifiers": [
      {
        "category": "Professional",
        "subcategory": "Employment Agencies",
        "type": "Services"
      }
    ],
    "sg:phone": "+1   ",
    "sg:postcode": "02215",
    "sg:province": "MA",
    "sg:tags": [
      "help",
      "supply"
    ],
    "wof:name": "Technical Aid Corporation",
    "wof:placetype": "venue"
  },
  "geometry": {"coordinates":[-71.107459,42.338701],"type":"Point"}
}
