{
  "type": "Feature",
  "properties": {
    "iso:country":"US",
    "sg:address":"540 Barnstable Rd",
    "sg:city":"Hyannis",
    "sg:classifiers":[
        {
            "category":"Parking",
            "type":"Transportation"
        },
        {
            "category":"Parking",
            "subcategory":"Garage",
            "type":"Transportation"
        }
    ],
    "sg:phone":"+1 508 778 0054",
    "sg:postcode":"02601",
    "sg:province":"MA",
    "sg:tags":[
        "attendant",
        "lot"
    ],
    "wof:name":"Barnstable Municipal Airport",
    "wof:placetype":"venue"
},
  "geometry": {"coordinates":[-70.287977,41.666728],"type":"Point"}
}