{
  "type": "Feature",
  "properties": {
    "addr:full":"126 Prospect St Cambridge MA 02139",
    "addr:housenumber":"126",
    "addr:postcode":"02139",
    "addr:street":"Prospect St",
    "iso:country":"US",
    "sg:address":"126 Prospect St",
    "sg:city":"Cambridge",
    "sg:classifiers":[
        {
            "category":"Professional",
            "subcategory":"Lawyer & Legal Services",
            "type":"Services"
        }
    ],
    "sg:phone":"+1 617 868 5000",
    "sg:postcode":"02139",
    "sg:province":"MA",
    "wof:name":"Ferrante Santino Atty",
    "wof:placetype":"venue"
},
  "geometry": {"coordinates":[-71.101799,42.368198],"type":"Point"}
}