{
  "type": "Feature",
  "properties": {
    "addr:full":"29 Oaks Rd Framingham MA 01702",
    "addr:postcode":"01702",
    "addr:street":"29 Oaks Rd",
    "iso:country":"US",
    "sg:address":"29 Oaks Rd",
    "sg:city":"Framingham",
    "sg:classifiers":[
        {
            "category":"Education",
            "subcategory":"School",
            "type":"Public Place"
        }
    ],
    "sg:phone":"+1 508 872 4234",
    "sg:postcode":"01702",
    "sg:province":"MA",
    "wof:name":"Happy Hollow Nursery School",
    "wof:placetype":"venue"
},
  "geometry": {"coordinates":[-71.418857,42.290811],"type":"Point"}
}