{
  "type": "Feature",
  "properties": {
    "iso:country":"US",
    "sg:address":"18 Bretts Farm Rd",
    "sg:city":"Norfolk",
    "sg:classifiers":[
        {
            "category":"Banks & Credit Unions",
            "subcategory":"Investment Brokerage",
            "type":"Services"
        }
    ],
    "sg:phone":"+1 508 528 1394",
    "sg:postcode":"02056",
    "sg:province":"MA",
    "sg:tags":[
        "advisory",
        "financial"
    ],
    "wof:name":"Fisher Investments",
    "wof:placetype":"venue"
},
  "geometry": {"coordinates":[-71.35907,42.092861],"type":"Point"}
}