{
  "type": "Feature",
  "properties": {
    "addr:full":"63 Ogden St Indian Orchard MA 01151",
    "addr:housenumber":"63",
    "addr:postcode":"01151",
    "addr:street":"Ogden St",
    "iso:country":"US",
    "sg:address":"63 Ogden St",
    "sg:city":"Indian Orchard",
    "sg:classifiers":[
        {
            "category":"Organizations",
            "subcategory":"Religious Organization",
            "type":"Services"
        }
    ],
    "sg:phone":"+1 413 543 4843",
    "sg:postcode":"01151",
    "sg:province":"MA",
    "sg:tags":[
        "church"
    ],
    "wof:name":"Bible Baptist Temple",
    "wof:placetype":"venue"
},
  "geometry": {"coordinates":[-72.516991,42.148189],"type":"Point"}
}