{
  "type": "Feature",
  "properties": {
    "addr:full":"7 Harris Ave Teele Square, Somerville Jamaica Plain MA 02130",
    "addr:housenumber":"7",
    "addr:postcode":"02130",
    "addr:street":"Harris Ave",
    "iso:country":"US",
    "sg:address":"7 Harris Ave Teele Square, Somerville",
    "sg:city":"Jamaica Plain",
    "sg:classifiers":[
        {
            "category":"Health Services",
            "subcategory":"Clinic",
            "type":"Services"
        }
    ],
    "sg:phone":"+1 781 929 8677",
    "sg:postcode":"02130",
    "sg:province":"MA",
    "sg:tags":[
        "medical"
    ],
    "sg:website":"www.taproothealing.com",
    "wof:name":"Taproot Healing - Shiatsu, Herbs & Self Care Consults",
    "wof:placetype":"venue"
},
  "geometry": {"coordinates":[-71.11439900000001,42.310968],"type":"Point"}
}