{
  "type": "Feature",
  "properties": {
    "addr:full":"22 Mill St Arlington MA 02474",
    "addr:housenumber":"22",
    "addr:postcode":"02474",
    "addr:street":"Mill St",
    "iso:country":"US",
    "sg:address":"22 Mill St",
    "sg:city":"Arlington",
    "sg:classifiers":[
        {
            "category":"Health Services",
            "subcategory":"Health Practitioner",
            "type":"Services"
        }
    ],
    "sg:phone":"+1 781 646 0500",
    "sg:postcode":"02474",
    "sg:province":"MA",
    "sg:tags":[
        "counseling",
        "psychologist",
        "mental"
    ],
    "wof:name":"Psychological Care Associates",
    "wof:placetype":"venue"
},
  "geometry": {"coordinates":[-71.15799699999999,42.417301],"type":"Point"}
}