{
  "type": "Feature",
  "properties": {
    "addr:full": "191 Old Burley St Danvers MA 01923",
    "addr:housenumber": "191",
    "addr:postcode": "01923",
    "addr:street": "Old Burley St",
    "iso:country": "US",
    "sg:address": "191 Old Burley St",
    "sg:city": "Danvers",
    "sg:classifiers": [
      {
        "category": "Freight",
        "type": "Transportation"
      }
    ],
    "sg:phone": "+1 978 750 8782",
    "sg:postcode": "01923",
    "sg:province": "MA",
    "sg:tags": [
      "mover"
    ],
    "wof:name": "Lipsky Moving \u0026 Storage",
    "wof:placetype": "venue"
  },
  "geometry": {"coordinates":[-70.923636,42.586876],"type":"Point"}
}
