{
  "type": "Feature",
  "properties": {
    "addr:full": "110 S Main St Gardner MA 01440",
    "addr:housenumber": "110",
    "addr:postcode": "01440",
    "addr:street": "S Main St",
    "iso:country": "US",
    "sg:address": "110 S Main St",
    "sg:city": "Gardner",
    "sg:classifiers": [
      {
        "category": "Organizations",
        "subcategory": "Community Association",
        "type": "Services"
      },
      {
        "category": "Organizations",
        "subcategory": "Membership Organization",
        "type": "Services"
      }
    ],
    "sg:phone": "+1 978 630 1076",
    "sg:postcode": "01440",
    "sg:province": "MA",
    "sg:tags": [
      "fraternal"
    ],
    "wof:name": "Knights Of Columbus",
    "wof:placetype": "venue"
  },
  "geometry": {"coordinates":[-71.98174,42.55996],"type":"Point"}
}
