{
  "type": "Feature",
  "properties": {
    "iso:country":"US",
    "sg:address":"753 Memorial Dr",
    "sg:city":"Chicopee",
    "sg:classifiers":[
        {
            "category":"Fast Food",
            "type":"Food & Drink"
        },
        {
            "category":"Restaurant",
            "type":"Food & Drink"
        }
    ],
    "sg:phone":"+1 413 593 3088",
    "sg:postcode":"01020",
    "sg:province":"MA",
    "sg:tags":[
        "american",
        "take",
        "chicken"
    ],
    "sg:website":"http://www.popeyes.com",
    "wof:name":"Popeyes Chicken & Biscuits",
    "wof:placetype":"venue"
},
  "geometry": {"coordinates":[-72.576916,42.178078],"type":"Point"}
}