{
  "type": "Feature",
  "properties": {
    "iso:country":"US",
    "sg:address":"87 Lake Ave",
    "sg:city":"Walpole",
    "sg:classifiers":[
        {
            "category":"Real Estate",
            "subcategory":"Real Estate Services",
            "type":"Services"
        }
    ],
    "sg:phone":"+1 508 660 2270",
    "sg:postcode":"02081",
    "sg:province":"MA",
    "sg:tags":[
        "home",
        "inspector"
    ],
    "wof:name":"US Inspect - CLOSED",
    "wof:placetype":"venue"
},
  "geometry": {"coordinates":[-71.24369799999999,42.1376],"type":"Point"}
}