{
  "type": "Feature",
  "properties": {
    "iso:country":"US",
    "sg:address":"20 Tashama Ln",
    "sg:city":"Nantucket",
    "sg:classifiers":[
        {
            "category":"Social Services",
            "subcategory":"Adult Care",
            "type":"Services"
        }
    ],
    "sg:phone":"+1   ",
    "sg:postcode":"02554",
    "sg:province":"MA",
    "sg:tags":[
        "residential",
        "day",
        "child"
    ],
    "wof:name":"PIP Squeaks Daycare",
    "wof:placetype":"venue"
},
  "geometry": {"coordinates":[-70.104331,41.269285],"type":"Point"}
}