{
  "type": "Feature",
  "properties": {
    "addr:full": "337 Cocasset St Foxboro MA 02035",
    "addr:housenumber": "337",
    "addr:postcode": "02035",
    "addr:street": "Cocasset St",
    "iso:country": "US",
    "sg:address": "337 Cocasset St",
    "sg:city": "Foxboro",
    "sg:classifiers": [
      {
        "category": "Organizations",
        "subcategory": "Community Association",
        "type": "Services"
      }
    ],
    "sg:phone": "+1 508 543 8293",
    "sg:postcode": "02035",
    "sg:province": "MA",
    "sg:tags": [
      "military"
    ],
    "wof:name": "Veterans Of Foreign Wars 2626",
    "wof:placetype": "venue"
  },
  "geometry": {"coordinates":[-71.2021,42.061196],"type":"Point"}
}
