{
  "type": "Feature",
  "properties": {
    "iso:country":"US",
    "sg:address":"337 Cocasset St",
    "sg:city":"Foxboro",
    "sg:classifiers":[
        {
            "category":"Organizations",
            "subcategory":"Community Association",
            "type":"Services"
        }
    ],
    "sg:phone":"+1 508 543 8293",
    "sg:postcode":"02035",
    "sg:province":"MA",
    "sg:tags":[
        "military"
    ],
    "wof:name":"Veterans Of Foreign Wars 2626",
    "wof:placetype":"venue"
},
  "geometry": {"coordinates":[-71.2021,42.061196],"type":"Point"}
}