{
  "type": "Feature",
  "properties": {
    "addr:full": "314 Essex St Lawrence MA 01840",
    "addr:housenumber": "314",
    "addr:postcode": "01840",
    "addr:street": "Essex St",
    "iso:country": "US",
    "sg:address": "314 Essex St",
    "sg:city": "Lawrence",
    "sg:classifiers": [
      {
        "category": "Health Services",
        "subcategory": "Doctor",
        "type": "Services"
      }
    ],
    "sg:phone": "+1 978 327 5151",
    "sg:postcode": "01840",
    "sg:province": "MA",
    "sg:tags": [
      "dentist"
    ],
    "wof:name": "Lawrence Dental Ctr",
    "wof:placetype": "venue"
  },
  "geometry": {"coordinates":[-71.162574,42.707183],"type":"Point"}
}
