{
  "type": "Feature",
  "properties": {
    "iso:country":"US",
    "sg:address":"694 East Street Ste. 1",
    "sg:city":"Pittsfield",
    "sg:classifiers":[
        {
            "category":"Autos & Motor Vehicles",
            "subcategory":"Automobile Sales",
            "type":"Retail Goods"
        }
    ],
    "sg:phone":"+1 800 639 8743",
    "sg:postcode":"01201",
    "sg:province":"MA",
    "sg:tags":[
        "new",
        "used",
        "car"
    ],
    "sg:website":"http://www.drivejohnson.com",
    "wof:name":"Johnson Ford",
    "wof:placetype":"venue"
},
  "geometry": {"coordinates":[-73.241208,42.448602],"type":"Point"}
}