{
  "type": "Feature",
  "properties": {
    "addr:full": "694 East Street Ste. 1 Pittsfield MA 01201",
    "addr:housenumber": "694",
    "addr:postcode": "01201",
    "addr:street": "East Street Ste. 1",
    "iso:country": "US",
    "ovtr:label": "Johnson Ford, 694 East St Pittsfield MA US",
    "ovtr:similarity": 2.905683994293213,
    "sg:address": "694 East Street Ste. 1",
    "sg:city": "Pittsfield",
    "sg:classifiers": [
      {
        "category": "Autos \u0026 Motor Vehicles",
        "subcategory": "Automobile Sales",
        "type": "Retail Goods"
      }
    ],
    "sg:phone": "+1 800 639 8743",
    "sg:postcode": "01201",
    "sg:province": "MA",
    "sg:tags": [
      "new",
      "used",
      "car"
    ],
    "sg:website": "http://www.drivejohnson.com",
    "wof:name": "Johnson Ford",
    "wof:placetype": "venue"
  },
  "geometry": {"coordinates":[-73.241208,42.448602],"type":"Point"}
}
