{
  "type": "Feature",
  "properties": {
    "addr:full": "12 Jeffrey Cir Bedford MA 01730",
    "addr:housenumber": "12",
    "addr:postcode": "01730",
    "addr:street": "Jeffrey Cir",
    "iso:country": "US",
    "sg:address": "12 Jeffrey Cir",
    "sg:city": "Bedford",
    "sg:classifiers": [
      {
        "category": "Professional",
        "subcategory": "Business Services",
        "type": "Services"
      }
    ],
    "sg:phone": "+1 781 275 7556",
    "sg:postcode": "01730",
    "sg:province": "MA",
    "sg:tags": [
      "hanger",
      "sign"
    ],
    "wof:name": "Northeast Sign Builders",
    "wof:placetype": "venue"
  },
  "geometry": {"coordinates":[-71.306666,42.496627],"type":"Point"}
}
