{
  "type": "Feature",
  "properties": {
    "addr:full":"230 SW Cutoff Worcester MA 01604",
    "addr:housenumber":"230",
    "addr:postcode":"01604",
    "addr:street":"Sw Cutoff",
    "iso:country":"US",
    "sg:address":"230 SW Cutoff",
    "sg:city":"Worcester",
    "sg:classifiers":[
        {
            "category":"Retail",
            "subcategory":"Auto Repair",
            "type":"Services"
        }
    ],
    "sg:phone":"+1 508 754 3330",
    "sg:postcode":"01604",
    "sg:province":"MA",
    "sg:tags":[
        "body",
        "automobile",
        "painting"
    ],
    "wof:name":"Desantis Collision Ctr",
    "wof:placetype":"venue"
},
  "geometry": {"coordinates":[-71.75877699999999,42.227503],"type":"Point"}
}