{
  "type": "Feature",
  "properties": {
    "addr:full": "27 Ingleside St Dorchester MA 02125",
    "addr:housenumber": "27",
    "addr:postcode": "02125",
    "addr:street": "Ingleside St",
    "iso:country": "US",
    "sg:address": "27 Ingleside St",
    "sg:city": "Dorchester",
    "sg:classifiers": [
      {
        "category": "Building \u0026 Trades",
        "subcategory": "Locksmith",
        "type": "Services"
      }
    ],
    "sg:phone": "+1 617 602 1145",
    "sg:postcode": "02125",
    "sg:province": "MA",
    "sg:tags": [
      "key"
    ],
    "wof:name": "AAA Locksmith",
    "wof:placetype": "venue"
  },
  "geometry": {"coordinates":[-71.077587,42.317257],"type":"Point"}
}
