{
  "type": "Feature",
  "properties": {
    "iso:country":"US",
    "sg:address":"6 Cypress Street",
    "sg:city":"Brookline",
    "sg:classifiers":[
        {
            "category":"Wholesale",
            "subcategory":"Computers",
            "type":"Manufacturing & Wholesale Goods"
        },
        {
            "category":"Professional",
            "subcategory":"Computer Services",
            "type":"Services"
        }
    ],
    "sg:phone":"+1 617 232 7166",
    "sg:postcode":"02445",
    "sg:province":"MA",
    "sg:tags":[
        "repair"
    ],
    "wof:name":"Microtech Computer Service",
    "wof:placetype":"venue"
},
  "geometry": {"coordinates":[-71.123141,42.334745],"type":"Point"}
}