{
  "type": "Feature",
  "properties": {
    "addr:full":"13 Ventura Dr North Dartmouth MA 02747",
    "addr:housenumber":"13",
    "addr:postcode":"02747",
    "addr:street":"Ventura Dr",
    "iso:country":"US",
    "sg:address":"13 Ventura Dr",
    "sg:city":"North Dartmouth",
    "sg:classifiers":[
        {
            "category":"Wholesale",
            "subcategory":"Stationery",
            "type":"Manufacturing & Wholesale Goods"
        }
    ],
    "sg:phone":"+1 508 999 9001",
    "sg:postcode":"02747",
    "sg:province":"MA",
    "sg:tags":[
        "business",
        "form",
        "system"
    ],
    "wof:name":"North American Business Forms",
    "wof:placetype":"venue"
},
  "geometry": {"coordinates":[-70.99074400000001,41.67019],"type":"Point"}
}