{
  "type": "Feature",
  "properties": {
    "addr:full": "34 Cambridge St Burlington MA 01803",
    "addr:housenumber": "34",
    "addr:postcode": "01803",
    "addr:street": "Cambridge St",
    "iso:country": "US",
    "sg:address": "34 Cambridge St",
    "sg:city": "Burlington",
    "sg:classifiers": [
      {
        "category": "Building \u0026 Trades",
        "subcategory": "Construction",
        "type": "Services"
      },
      {
        "category": "Home \u0026 Garden",
        "subcategory": "Furniture",
        "type": "Retail Goods"
      }
    ],
    "sg:phone": "+1 781 273 2515",
    "sg:postcode": "01803",
    "sg:province": "MA",
    "sg:tags": [
      "interior",
      "design",
      "store"
    ],
    "wof:name": "Ethan Allen Home Interiors",
    "wof:placetype": "venue"
  },
  "geometry": {"coordinates":[-71.189102,42.483898],"type":"Point"}
}
