{
  "type": "Feature",
  "properties": {
    "iso:country":"US",
    "sg:address":"34 Cambridge St",
    "sg:city":"Burlington",
    "sg:classifiers":[
        {
            "category":"Building & Trades",
            "subcategory":"Construction",
            "type":"Services"
        },
        {
            "category":"Home & Garden",
            "subcategory":"Furniture",
            "type":"Retail Goods"
        }
    ],
    "sg:phone":"+1 781 273 2515",
    "sg:postcode":"01803",
    "sg:province":"MA",
    "sg:tags":[
        "interior",
        "design",
        "store"
    ],
    "wof:name":"Ethan Allen Home Interiors",
    "wof:placetype":"venue"
},
  "geometry": {"coordinates":[-71.18910200000001,42.483898],"type":"Point"}
}