{
  "type": "Feature",
  "properties": {
    "iso:country":"US",
    "sg:address":"196 Park St",
    "sg:city":"North Reading",
    "sg:classifiers":[
        {
            "category":"Home & Garden",
            "subcategory":"Building Materials",
            "type":"Retail Goods"
        }
    ],
    "sg:phone":"+1 781 944 2401",
    "sg:postcode":"01864",
    "sg:province":"MA",
    "sg:tags":[
        "windows",
        "door",
        "storm"
    ],
    "wof:name":"Shower Queen Glass Co",
    "wof:placetype":"venue"
},
  "geometry": {"coordinates":[-71.08617599999999,42.573677],"type":"Point"}
}