{
  "type": "Feature",
  "properties": {
    "iso:country":"US",
    "sg:address":"50 Ferncroft Rd",
    "sg:city":"Danvers",
    "sg:classifiers":[
        {
            "category":"Personal",
            "subcategory":"Beauty Salon",
            "type":"Services"
        }
    ],
    "sg:phone":"+1 978 774 0420",
    "sg:postcode":"01923",
    "sg:province":"MA",
    "wof:name":"Deidre Spence Day Spa",
    "wof:placetype":"venue"
},
  "geometry": {"coordinates":[-70.96648999999999,42.592567],"type":"Point"}
}