{
  "type": "Feature",
  "properties": {
    "addr:full":"25 William St Stoneham MA 02180",
    "addr:housenumber":"25",
    "addr:postcode":"02180",
    "addr:street":"William St",
    "iso:country":"US",
    "sg:address":"25 William St",
    "sg:city":"Stoneham",
    "sg:classifiers":[
        {
            "category":"Education",
            "subcategory":"School",
            "type":"Public Place"
        }
    ],
    "sg:phone":"+1   ",
    "sg:postcode":"02180",
    "sg:province":"MA",
    "wof:name":"Central Elementary School",
    "wof:placetype":"venue"
},
  "geometry": {"coordinates":[-71.096515,42.482496],"type":"Point"}
}