{
  "type": "Feature",
  "properties": {
    "iso:country":"US",
    "sg:address":"99 Newland St",
    "sg:city":"Boston",
    "sg:classifiers":[
        {
            "category":"Building & Trades",
            "subcategory":"Locksmith",
            "type":"Services"
        }
    ],
    "sg:phone":"+1 617 303 2831",
    "sg:postcode":"02118",
    "sg:province":"MA",
    "sg:tags":[
        "key"
    ],
    "wof:name":"Wall Street Locksmith",
    "wof:placetype":"venue"
},
  "geometry": {"coordinates":[-71.07643,42.339056],"type":"Point"}
}