{
  "type": "Feature",
  "properties": {
    "addr:full":"363 Revere St Revere MA 02151",
    "addr:housenumber":"363",
    "addr:postcode":"02151",
    "addr:street":"Revere St",
    "iso:country":"US",
    "sg:address":"363 Revere St",
    "sg:city":"Revere",
    "sg:classifiers":[
        {
            "category":"Building & Trades",
            "subcategory":"Locksmith",
            "type":"Services"
        }
    ],
    "sg:phone":"+1 781 922 9084",
    "sg:postcode":"02151",
    "sg:province":"MA",
    "sg:tags":[
        "key"
    ],
    "wof:name":"Always Available 24 Hour Emergency Locksmi",
    "wof:placetype":"venue"
},
  "geometry": {"coordinates":[-70.99689600000001,42.418378],"type":"Point"}
}