{
  "type": "Feature",
  "properties": {
    "addr:full":"57 E Main St Westborough MA 01581",
    "addr:housenumber":"57",
    "addr:postcode":"01581",
    "addr:street":"E Main St",
    "iso:country":"US",
    "sg:address":"57 E Main St",
    "sg:city":"Westborough",
    "sg:classifiers":[
        {
            "category":"Professional",
            "type":"Services"
        }
    ],
    "sg:phone":"+1 508 366 9086",
    "sg:postcode":"01581",
    "sg:province":"MA",
    "sg:tags":[
        "establishment"
    ],
    "wof:name":"7 East Main St",
    "wof:placetype":"venue"
},
  "geometry": {"coordinates":[-71.61053200000001,42.273769],"type":"Point"}
}