{
  "type": "Feature",
  "properties": {
    "addr:full": "168 State Hwy 28 West Harwich MA 02671",
    "addr:housenumber": "168",
    "addr:postcode": "02671",
    "addr:street": "State Hwy 28",
    "iso:country": "US",
    "ovtr:label": "Weatherdeck, 168 Route 28 West Harwich MA US",
    "ovtr:similarity": 3.8401739597320557,
    "sg:address": "168 State Hwy 28",
    "sg:city": "West Harwich",
    "sg:classifiers": [
      {
        "category": "Restaurant",
        "type": "Food \u0026 Drink"
      }
    ],
    "sg:phone": "+1 508 432 8240",
    "sg:postcode": "02671",
    "sg:province": "MA",
    "wof:name": "Weatherdeck",
    "wof:placetype": "venue"
  },
  "geometry": {"coordinates":[-70.107287,41.668574],"type":"Point"}
}
