{
  "type": "Feature",
  "properties": {
    "iso:country":"US",
    "sg:address":"168 State Hwy 28",
    "sg:city":"West Harwich",
    "sg:classifiers":[
        {
            "category":"Restaurant",
            "type":"Food & Drink"
        }
    ],
    "sg:phone":"+1 508 432 8240",
    "sg:postcode":"02671",
    "sg:province":"MA",
    "wof:name":"Weatherdeck",
    "wof:placetype":"venue"
},
  "geometry": {"coordinates":[-70.107287,41.668574],"type":"Point"}
}