{
  "type": "Feature",
  "properties": {
    "iso:country":"US",
    "sg:address":"565 University Ave",
    "sg:city":"Norwood",
    "sg:classifiers":[
        {
            "category":"Manufacturing",
            "subcategory":"Printing",
            "type":"Manufacturing & Wholesale Goods"
        }
    ],
    "sg:phone":"+1 781 762 0277",
    "sg:postcode":"02062",
    "sg:province":"MA",
    "sg:tags":[
        "printer"
    ],
    "sg:website":"www.gannett.com",
    "wof:name":"Gannett Offset",
    "wof:placetype":"venue"
},
  "geometry": {"coordinates":[-71.163196,42.199085],"type":"Point"}
}