{
  "type": "Feature",
  "properties": {
    "iso:country":"US",
    "sg:address":"319 Longwood Avenue",
    "sg:city":"Boston",
    "sg:classifiers":[
        {
            "category":"Health Services",
            "subcategory":"Doctor",
            "type":"Services"
        }
    ],
    "sg:phone":"+1 617 731 0854",
    "sg:postcode":"02115",
    "sg:province":"MA",
    "sg:tags":[
        "physician",
        "surgeon",
        "neurology",
        "surgeons"
    ],
    "wof:name":"Lombroso Cesare MD PHD",
    "wof:placetype":"venue"
},
  "geometry": {"coordinates":[-71.105749,42.338068],"type":"Point"}
}