{
  "type": "Feature",
  "properties": {
    "addr:full": "9 Maple St Wilbraham MA 01095",
    "addr:housenumber": "9",
    "addr:postcode": "01095",
    "addr:street": "Maple St",
    "iso:country": "US",
    "sg:address": "9 Maple St",
    "sg:city": "Wilbraham",
    "sg:classifiers": [
      {
        "category": "Health Services",
        "subcategory": "Nursing And Care Facility",
        "type": "Services"
      }
    ],
    "sg:phone": "+1 413 596 2411",
    "sg:postcode": "01095",
    "sg:province": "MA",
    "sg:tags": [
      "home",
      "convalescent"
    ],
    "wof:name": "Wingate At Wilbraham",
    "wof:placetype": "venue"
  },
  "geometry": {"coordinates":[-72.425409,42.151581],"type":"Point"}
}
