{
  "type": "Feature",
  "properties": {
    "iso:country":"US",
    "sg:address":"21 Holyoke St",
    "sg:city":"Holyoke",
    "sg:classifiers":[
        {
            "category":"Shopping",
            "subcategory":"Clothing, Apparel, & Fashions",
            "type":"Retail Goods"
        }
    ],
    "sg:phone":"+1 413 533 9266",
    "sg:postcode":"01040",
    "sg:province":"MA",
    "sg:tags":[
        "furnishing"
    ],
    "sg:website":"www.menswearhouse.com",
    "wof:name":"Men's Wearhouse",
    "wof:placetype":"venue"
},
  "geometry": {"coordinates":[-72.640502,42.173117],"type":"Point"}
}