{
  "type": "Feature",
  "properties": {
    "addr:full":"3 Riverbend Rd Upton MA 01568",
    "addr:housenumber":"3",
    "addr:postcode":"01568",
    "addr:street":"Riverbend Rd",
    "iso:country":"US",
    "sg:address":"3 Riverbend Rd",
    "sg:city":"Upton",
    "sg:classifiers":[
        {
            "category":"Professional",
            "subcategory":"Lawyer & Legal Services",
            "type":"Services"
        }
    ],
    "sg:phone":"+1 508 529 3088",
    "sg:postcode":"01568",
    "sg:province":"MA",
    "sg:tags":[
        "attorney"
    ],
    "wof:name":"Joseph P Mc Inerny",
    "wof:placetype":"venue"
},
  "geometry": {"coordinates":[-71.609448,42.151817],"type":"Point"}
}