{
  "type": "Feature",
  "properties": {
    "iso:country":"US",
    "sg:address":"225 Main St",
    "sg:city":"Charlestown",
    "sg:classifiers":[
        {
            "category":"Personal",
            "subcategory":"Beauty Salon",
            "type":"Services"
        }
    ],
    "sg:phone":"+1 617 241 8686",
    "sg:postcode":"02129",
    "sg:province":"MA",
    "sg:tags":[
        "hair"
    ],
    "sg:website":"www.reynees.com",
    "wof:name":"Reynee's",
    "wof:placetype":"venue"
},
  "geometry": {"coordinates":[-71.065804,42.3764],"type":"Point"}
}