{
  "type": "Feature",
  "properties": {
    "iso:country":"US",
    "sg:address":"360 Massachusetts Ave",
    "sg:city":"Acton",
    "sg:classifiers":[
        {
            "category":"Food & Beverages",
            "subcategory":"Specialty",
            "type":"Retail Goods"
        }
    ],
    "sg:phone":"+1 978 263 8488",
    "sg:postcode":"01720",
    "sg:province":"MA",
    "sg:tags":[
        "vitamin"
    ],
    "wof:name":"Mothernature",
    "wof:placetype":"venue"
},
  "geometry": {"coordinates":[-71.442414,42.473611],"type":"Point"}
}