{
  "type": "Feature",
  "properties": {
    "addr:full":"3 Scott Aly Boston MA 02109",
    "addr:housenumber":"3",
    "addr:postcode":"02109",
    "addr:street":"Scott Aly",
    "iso:country":"US",
    "sg:address":"3 Scott Aly",
    "sg:city":"Boston",
    "sg:classifiers":[
        {
            "category":"Professional",
            "subcategory":"Lawyer & Legal Services",
            "type":"Services"
        }
    ],
    "sg:phone":"+1 617 523 9000",
    "sg:postcode":"02109",
    "sg:province":"MA",
    "sg:tags":[
        "attorney"
    ],
    "wof:name":"Riemer & Braunstein",
    "wof:placetype":"venue"
},
  "geometry": {"coordinates":[-71.056335,42.36111],"type":"Point"}
}