{
  "type": "Feature",
  "properties": {
    "iso:country":"US",
    "sg:address":"34 Uxbridge Rd",
    "sg:city":"Mendon",
    "sg:classifiers":[
        {
            "category":"Professional",
            "subcategory":"Computer Services",
            "type":"Services"
        }
    ],
    "sg:phone":"+1 508 478 0112",
    "sg:postcode":"01756",
    "sg:province":"MA",
    "sg:tags":[
        "home",
        "consulting",
        "page",
        "dev",
        "internet"
    ],
    "wof:name":"J C's Web Design",
    "wof:placetype":"venue"
},
  "geometry": {"coordinates":[-71.568702,42.102215],"type":"Point"}
}