{
  "type": "Feature",
  "properties": {
    "iso:country":"US",
    "sg:address":"32 Alexander Hill Rd",
    "sg:city":"Northfield",
    "sg:classifiers":[
        {
            "category":"Professional",
            "subcategory":"Research",
            "type":"Services"
        }
    ],
    "sg:phone":"+1 413 498 5461",
    "sg:postcode":"01360",
    "sg:province":"MA",
    "sg:tags":[
        "development",
        "electronics",
        "technology-research"
    ],
    "wof:name":"Dickerman Electronics",
    "wof:placetype":"venue"
},
  "geometry": {"coordinates":[-72.435368,42.682959],"type":"Point"}
}