{
  "type": "Feature",
  "properties": {
    "iso:country":"US",
    "sg:address":"11 School St",
    "sg:city":"Amesbury",
    "sg:classifiers":[
        {
            "category":"Government",
            "subcategory":"Office",
            "type":"Public Place"
        }
    ],
    "sg:phone":"+1 978 388 8133",
    "sg:postcode":"01913",
    "sg:province":"MA",
    "sg:tags":[
        "city",
        "program",
        "health"
    ],
    "wof:name":"Amesbury Health Dept",
    "wof:placetype":"venue"
},
  "geometry": {"coordinates":[-70.933154,42.854772],"type":"Point"}
}