{
  "type": "Feature",
  "properties": {
    "iso:country":"US",
    "sg:address":"142 D St",
    "sg:city":"Weymouth",
    "sg:classifiers":[
        {
            "category":"Wholesale",
            "subcategory":"Hardware",
            "type":"Manufacturing & Wholesale Goods"
        }
    ],
    "sg:phone":"+1 781 337 0039",
    "sg:postcode":"02127",
    "sg:province":"MA",
    "sg:tags":[
        "heater"
    ],
    "wof:name":"Ken Bishop Enterprises Inc",
    "wof:placetype":"venue"
},
  "geometry": {"coordinates":[-71.054104,42.336114],"type":"Point"}
}