{
  "type": "Feature",
  "properties": {
    "iso:country":"US",
    "sg:address":"128 Read St",
    "sg:city":"Fall River",
    "sg:classifiers":[
        {
            "category":"Personal",
            "subcategory":"Beauty Salon",
            "type":"Services"
        }
    ],
    "sg:phone":"+1   ",
    "sg:postcode":"02720",
    "sg:province":"MA",
    "sg:tags":[
        "shop"
    ],
    "wof:name":"Natalie Wig Wam",
    "wof:placetype":"venue"
},
  "geometry": {"coordinates":[-71.141156,41.710741],"type":"Point"}
}