{
  "type": "Feature",
  "properties": {
    "iso:country":"US",
    "sg:address":"14 Arnold St",
    "sg:city":"Methuen",
    "sg:classifiers":[
        {
            "category":"Building & Trades",
            "subcategory":"Construction",
            "type":"Services"
        }
    ],
    "sg:phone":"+1   ",
    "sg:postcode":"01844",
    "sg:province":"MA",
    "sg:tags":[
        "builder",
        "operative"
    ],
    "wof:name":"Bob Zanni",
    "wof:placetype":"venue"
},
  "geometry": {"coordinates":[-71.187889,42.721703],"type":"Point"}
}