{
  "type": "Feature",
  "properties": {
    "addr:full":"1432 Beacon St Brookline MA 02446",
    "addr:housenumber":"1432",
    "addr:postcode":"02446",
    "addr:street":"Beacon St",
    "iso:country":"US",
    "sg:address":"1432 Beacon St",
    "sg:city":"Brookline",
    "sg:classifiers":[
        {
            "category":"Food & Beverages",
            "subcategory":"Specialty",
            "type":"Retail Goods"
        }
    ],
    "sg:phone":"+1 617 739 8450",
    "sg:postcode":"02446",
    "sg:province":"MA",
    "sg:tags":[
        "gourmet",
        "shop",
        "ethnic"
    ],
    "sg:website":"www.bazaarboston.com/",
    "wof:name":"Bazaar International Gourmet",
    "wof:placetype":"venue"
},
  "geometry": {"coordinates":[-71.12649500000001,42.341019],"type":"Point"}
}