{
  "type": "Feature",
  "properties": {
    "iso:country":"US",
    "sg:address":"15 Keith Hill Rd",
    "sg:city":"Grafton",
    "sg:classifiers":[
        {
            "category":"Professional",
            "subcategory":"Business Services",
            "type":"Services"
        }
    ],
    "sg:phone":"+1 508 839 1828",
    "sg:postcode":"01519",
    "sg:province":"MA",
    "sg:tags":[
        "consultant",
        "coach"
    ],
    "wof:name":"Argus Management Corporation",
    "wof:placetype":"venue"
},
  "geometry": {"coordinates":[-71.667722,42.1908],"type":"Point"}
}