{
  "type": "Feature",
  "properties": {
    "iso:country":"US",
    "sg:address":"155 State Rd",
    "sg:city":"Vineyard Haven",
    "sg:classifiers":[
        {
            "category":"Health Services",
            "subcategory":"Chiropractor",
            "type":"Services"
        }
    ],
    "sg:phone":"+1 508 696 8400",
    "sg:postcode":"02568",
    "sg:province":"MA",
    "wof:name":"Gallagher Family Chiropractics",
    "wof:placetype":"venue"
},
  "geometry": {"coordinates":[-70.60987299999999,41.450517],"type":"Point"}
}