{
  "type": "Feature",
  "properties": {
    "addr:full": "123 Main St Pepperell MA 01463",
    "addr:housenumber": "123",
    "addr:postcode": "01463",
    "addr:street": "Main St",
    "iso:country": "US",
    "ovtr:label": "Patriot Barber Shop, 127 Main St Pepperell MA US",
    "ovtr:similarity": 3.0667641162872314,
    "sg:address": "123 Main St",
    "sg:city": "Pepperell",
    "sg:classifiers": [
      {
        "category": "Personal",
        "subcategory": "Barber",
        "type": "Services"
      }
    ],
    "sg:phone": "+1 978 433 6975",
    "sg:postcode": "01463",
    "sg:province": "MA",
    "wof:name": "Patriot Barber Shop",
    "wof:placetype": "venue"
  },
  "geometry": {"coordinates":[-71.579163,42.665042],"type":"Point"}
}
