{
  "type": "Feature",
  "properties": {
    "iso:country":"US",
    "sg:address":"123 Main St",
    "sg:city":"Pepperell",
    "sg:classifiers":[
        {
            "category":"Personal",
            "subcategory":"Barber",
            "type":"Services"
        }
    ],
    "sg:phone":"+1 978 433 6975",
    "sg:postcode":"01463",
    "sg:province":"MA",
    "wof:name":"Patriot Barber Shop",
    "wof:placetype":"venue"
},
  "geometry": {"coordinates":[-71.57916299999999,42.665042],"type":"Point"}
}