{
  "type": "Feature",
  "properties": {
    "addr:full":"32 Hospital Hill Rd Gardner MA 01440",
    "addr:housenumber":"32",
    "addr:postcode":"01440",
    "addr:street":"Hospital Hill Rd",
    "iso:country":"US",
    "sg:address":"32 Hospital Hill Rd",
    "sg:city":"Gardner",
    "sg:classifiers":[
        {
            "category":"Health Services",
            "subcategory":"Nursing And Care Facility",
            "type":"Services"
        }
    ],
    "sg:phone":"+1 978 632 5477",
    "sg:postcode":"01440",
    "sg:province":"MA",
    "sg:tags":[
        "home",
        "convalescent"
    ],
    "wof:name":"Wachusett Manor",
    "wof:placetype":"venue"
},
  "geometry": {"coordinates":[-71.976325,42.571574],"type":"Point"}
}