{
  "type": "Feature",
  "properties": {
    "addr:full": "109 Wagon Trl Hanson MA 02341",
    "addr:housenumber": "109",
    "addr:postcode": "02341",
    "addr:street": "Wagon Trl",
    "iso:country": "US",
    "sg:address": "109 Wagon Trl",
    "sg:city": "Hanson",
    "sg:classifiers": [
      {
        "category": "Building \u0026 Trades",
        "subcategory": "Plumbing",
        "type": "Services"
      }
    ],
    "sg:phone": "+1   ",
    "sg:postcode": "02341",
    "sg:province": "MA",
    "sg:tags": [
      "air",
      "heating",
      "conditioning",
      "contractor"
    ],
    "wof:name": "Raynard Heating \u0026 AC",
    "wof:placetype": "venue"
  },
  "geometry": {"coordinates":[-70.855631,42.089487],"type":"Point"}
}
