{
  "type": "Feature",
  "properties": {
    "iso:country":"US",
    "sg:address":"109 Wagon Trl",
    "sg:city":"Hanson",
    "sg:classifiers":[
        {
            "category":"Building & Trades",
            "subcategory":"Plumbing",
            "type":"Services"
        }
    ],
    "sg:phone":"+1   ",
    "sg:postcode":"02341",
    "sg:province":"MA",
    "sg:tags":[
        "air",
        "heating",
        "conditioning",
        "contractor"
    ],
    "wof:name":"Raynard Heating & AC",
    "wof:placetype":"venue"
},
  "geometry": {"coordinates":[-70.855631,42.089487],"type":"Point"}
}