{
  "type": "Feature",
  "properties": {
    "iso:country":"US",
    "sg:address":"30 Oxford St",
    "sg:city":"Pittsfield",
    "sg:classifiers":[
        {
            "category":"Professional",
            "subcategory":"Business Services",
            "type":"Services"
        }
    ],
    "sg:phone":"+1 413 441 4667",
    "sg:postcode":"01201",
    "sg:province":"MA",
    "sg:tags":[
        "consultant",
        "coach"
    ],
    "wof:name":"Berkshire Accounting Solutions",
    "wof:placetype":"venue"
},
  "geometry": {"coordinates":[-73.262653,42.444709],"type":"Point"}
}