{
  "type": "Feature",
  "properties": {
    "addr:full": "437 Main St Woburn MA 01801",
    "addr:housenumber": "437",
    "addr:postcode": "01801",
    "addr:street": "Main St",
    "iso:country": "US",
    "sg:address": "437 Main St",
    "sg:city": "Woburn",
    "sg:classifiers": [
      {
        "category": "Restaurant",
        "type": "Food \u0026 Drink"
      }
    ],
    "sg:phone": "+1 781 932 9004",
    "sg:postcode": "01801",
    "sg:province": "MA",
    "sg:tags": [
      "pizza"
    ],
    "wof:name": "My Brother's Place Inc",
    "wof:placetype": "venue"
  },
  "geometry": {"coordinates":[-71.1511,42.483501],"type":"Point"}
}
