{
  "type": "Feature",
  "properties": {
    "iso:country":"US",
    "sg:address":"425 High St",
    "sg:city":"Medford",
    "sg:classifiers":[
        {
            "category":"Personal",
            "subcategory":"Beauty Salon",
            "type":"Services"
        }
    ],
    "sg:phone":"+1 781 935 2521",
    "sg:postcode":"02155",
    "sg:province":"MA",
    "sg:tags":[
        "spa"
    ],
    "wof:name":"Sally's Place for Health and Relaxation",
    "wof:placetype":"venue"
},
  "geometry": {"coordinates":[-71.130409,42.421196],"type":"Point"}
}