{
  "type": "Feature",
  "properties": {
    "addr:full": "23 Elm Ct Cohasset MA 02025",
    "addr:housenumber": "23",
    "addr:postcode": "02025",
    "addr:street": "Elm Ct",
    "iso:country": "US",
    "sg:address": "23 Elm Ct",
    "sg:city": "Cohasset",
    "sg:classifiers": [
      {
        "category": "Building \u0026 Trades",
        "subcategory": "Construction",
        "type": "Services"
      }
    ],
    "sg:phone": "+1 781 383 2278",
    "sg:postcode": "02025",
    "sg:province": "MA",
    "sg:tags": [
      "contractor"
    ],
    "wof:name": "Kearns Contractings",
    "wof:placetype": "venue"
  },
  "geometry": {"coordinates":[-70.796206,42.241119],"type":"Point"}
}
