{
  "type": "Feature",
  "properties": {
    "iso:country":"US",
    "sg:address":"470 Shawmut Ave",
    "sg:city":"Boston",
    "sg:classifiers":[
        {
            "category":"Home & Garden",
            "subcategory":"Home Furnishings",
            "type":"Retail Goods"
        }
    ],
    "sg:phone":"+1 617 391 0490",
    "sg:postcode":"02118",
    "sg:province":"MA",
    "sg:tags":[
        "decor"
    ],
    "sg:website":"www.jemhome.com/",
    "wof:name":"J.E.M.",
    "wof:placetype":"venue"
},
  "geometry": {"coordinates":[-71.075884,42.338752],"type":"Point"}
}