{
  "type": "Feature",
  "properties": {
    "addr:full":"160 Village St Millis MA 02054",
    "addr:housenumber":"160",
    "addr:postcode":"02054",
    "addr:street":"Village St",
    "iso:country":"US",
    "sg:address":"160 Village St",
    "sg:city":"Millis",
    "sg:classifiers":[
        {
            "category":"Retail",
            "subcategory":"Repair Shop",
            "type":"Services"
        }
    ],
    "sg:phone":"+1 508 376 5090",
    "sg:postcode":"02054",
    "sg:province":"MA",
    "sg:tags":[
        "welding"
    ],
    "wof:name":"Hope Welding",
    "wof:placetype":"venue"
},
  "geometry": {"coordinates":[-71.349576,42.160543],"type":"Point"}
}