{
  "type": "Feature",
  "properties": {
    "addr:full": "656 Beacon St Boston MA 02215",
    "addr:housenumber": "656",
    "addr:postcode": "02215",
    "addr:street": "Beacon St",
    "iso:country": "US",
    "sg:address": "656 Beacon St",
    "sg:city": "Boston",
    "sg:classifiers": [
      {
        "category": "Professional",
        "subcategory": "Research",
        "type": "Services"
      }
    ],
    "sg:phone": "+1 617 353 6570",
    "sg:postcode": "02215",
    "sg:province": "MA",
    "sg:website": "www.asor.org",
    "wof:name": "American Schools Of Oriental",
    "wof:placetype": "venue"
  },
  "geometry": {"coordinates":[-71.095703,42.349277],"type":"Point"}
}
