{
  "type": "Feature",
  "properties": {
    "addr:full":"25 Colpitts Rd Weston MA 02493",
    "addr:housenumber":"25",
    "addr:postcode":"02493",
    "addr:street":"Colpitts Rd",
    "iso:country":"US",
    "sg:address":"25 Colpitts Rd",
    "sg:city":"Weston",
    "sg:classifiers":[
        {
            "category":"Government",
            "subcategory":"Post Office",
            "type":"Public Place"
        }
    ],
    "sg:phone":"+1 781 893 7667",
    "sg:postcode":"02493",
    "sg:province":"MA",
    "wof:name":"US Post Office",
    "wof:placetype":"venue"
},
  "geometry": {"coordinates":[-71.304007,42.365749],"type":"Point"}
}