{
  "type": "Feature",
  "properties": {
    "iso:country":"US",
    "sg:address":"71 Burlington St",
    "sg:city":"Woburn",
    "sg:classifiers":[
        {
            "category":"Home & Garden",
            "subcategory":"Garden Supply",
            "type":"Retail Goods"
        }
    ],
    "sg:phone":"+1 781 933 9815",
    "sg:postcode":"01801",
    "sg:province":"MA",
    "sg:tags":[
        "center"
    ],
    "wof:name":"Heimlich's Nursery & Garden",
    "wof:placetype":"venue"
},
  "geometry": {"coordinates":[-71.168419,42.477875],"type":"Point"}
}