{
  "type": "Feature",
  "properties": {
    "iso:country":"US",
    "sg:address":"41 Ennell St",
    "sg:city":"Lowell",
    "sg:classifiers":[
        {
            "category":"Organizations",
            "subcategory":"Religious Organization",
            "type":"Services"
        }
    ],
    "sg:phone":"+1 978 452 1110",
    "sg:postcode":"01850",
    "sg:province":"MA",
    "sg:tags":[
        "church"
    ],
    "wof:name":"Peniel Spanish Assemblies-God",
    "wof:placetype":"venue"
},
  "geometry": {"coordinates":[-71.312242,42.656296],"type":"Point"}
}