{
  "type": "Feature",
  "properties": {
    "addr:full":"18 Tremont St Ste 120 Boston MA 02108",
    "addr:housenumber":"18",
    "addr:postcode":"02108",
    "addr:street":"Tremont St Ste 120",
    "iso:country":"US",
    "sg:address":"18 Tremont St Ste 120",
    "sg:city":"Boston",
    "sg:classifiers":[
        {
            "category":"Banks & Credit Unions",
            "subcategory":"Financial Services",
            "type":"Services"
        }
    ],
    "sg:phone":"+1 617 742 7600",
    "sg:postcode":"02108",
    "sg:province":"MA",
    "sg:tags":[
        "payday",
        "loan",
        "alternative"
    ],
    "wof:name":"Ironwood Equity",
    "wof:placetype":"venue"
},
  "geometry": {"coordinates":[-71.059786,42.358877],"type":"Point"}
}