{
  "type": "Feature",
  "properties": {
    "iso:country":"US",
    "sg:address":"55 Alden Rd",
    "sg:city":"Fairhaven",
    "sg:classifiers":[
        {
            "category":"Professional",
            "subcategory":"Lawyer & Legal Services",
            "type":"Services"
        }
    ],
    "sg:phone":"+1 508 997 7788",
    "sg:postcode":"02719",
    "sg:province":"MA",
    "sg:tags":[
        "attorney"
    ],
    "wof:name":"Winfred Eckenreiter Law Office",
    "wof:placetype":"venue"
},
  "geometry": {"coordinates":[-70.905287,41.665998],"type":"Point"}
}