{
  "type": "Feature",
  "properties": {
    "addr:full": "55 Alden Rd Fairhaven MA 02719",
    "addr:housenumber": "55",
    "addr:postcode": "02719",
    "addr:street": "Alden Rd",
    "iso:country": "US",
    "sg:address": "55 Alden Rd",
    "sg:city": "Fairhaven",
    "sg:classifiers": [
      {
        "category": "Professional",
        "subcategory": "Lawyer \u0026 Legal Services",
        "type": "Services"
      }
    ],
    "sg:phone": "+1 508 997 7788",
    "sg:postcode": "02719",
    "sg:province": "MA",
    "sg:tags": [
      "attorney"
    ],
    "wof:name": "Winfred Eckenreiter Law Office",
    "wof:placetype": "venue"
  },
  "geometry": {"coordinates":[-70.905287,41.665998],"type":"Point"}
}
