{
  "type": "Feature",
  "properties": {
    "addr:full": "15 Lawrence St Cambridge MA 02139",
    "addr:housenumber": "15",
    "addr:postcode": "02139",
    "addr:street": "Lawrence St",
    "iso:country": "US",
    "sg:address": "15 Lawrence St",
    "sg:city": "Cambridge",
    "sg:classifiers": [
      {
        "category": "Government",
        "subcategory": "Office",
        "type": "Public Place"
      }
    ],
    "sg:phone": "+1 617 876 6465",
    "sg:postcode": "02139",
    "sg:province": "MA",
    "sg:tags": [
      "authorities",
      "transportation"
    ],
    "wof:name": "Warner Transportation Consltng",
    "wof:placetype": "venue"
  },
  "geometry": {"coordinates":[-71.107768,42.361872],"type":"Point"}
}
