{
  "type": "Feature",
  "properties": {
    "iso:country":"US",
    "sg:address":"Market Place Ctr",
    "sg:city":"Boston",
    "sg:classifiers":[
        {
            "category":"Home & Garden",
            "subcategory":"Hardware",
            "type":"Retail Goods"
        }
    ],
    "sg:phone":"+1 617 439 4460",
    "sg:postcode":"02109",
    "sg:province":"MA",
    "sg:tags":[
        "store"
    ],
    "wof:name":"Brookstone",
    "wof:placetype":"venue"
},
  "geometry": {"coordinates":[-71.052696,42.362202],"type":"Point"}
}