{
  "type": "Feature",
  "properties": {
    "iso:country":"US",
    "sg:address":"218 Exchange St",
    "sg:city":"Chicopee",
    "sg:classifiers":[
        {
            "category":"Food & Beverages",
            "subcategory":"Bakery",
            "type":"Retail Goods"
        }
    ],
    "sg:phone":"+1 413 592 9416",
    "sg:postcode":"01013",
    "sg:province":"MA",
    "sg:tags":[
        "baker"
    ],
    "wof:name":"Bob's Bakery",
    "wof:placetype":"venue"
},
  "geometry": {"coordinates":[-72.609897,42.147796],"type":"Point"}
}