{
  "type": "Feature",
  "properties": {
    "iso:country":"US",
    "sg:address":"336 Westford St",
    "sg:city":"Lowell",
    "sg:classifiers":[
        {
            "category":"Health Services",
            "subcategory":"Health Practitioner",
            "type":"Services"
        }
    ],
    "sg:phone":"+1 978 458 7800",
    "sg:postcode":"01851",
    "sg:province":"MA",
    "sg:tags":[
        "therapist",
        "physical"
    ],
    "wof:name":"East Coast Physical Therapy",
    "wof:placetype":"venue"
},
  "geometry": {"coordinates":[-71.327749,42.634851],"type":"Point"}
}