{
  "type": "Feature",
  "properties": {
    "iso:country":"US",
    "sg:address":"178 Everett Ave",
    "sg:city":"Chelsea",
    "sg:classifiers":[
        {
            "category":"Fast Food",
            "type":"Food & Drink"
        },
        {
            "category":"Restaurant",
            "type":"Food & Drink"
        },
        {
            "category":"Professional",
            "type":"Services"
        }
    ],
    "sg:phone":"+1 617 889 6818",
    "sg:postcode":"02150",
    "sg:province":"MA",
    "sg:tags":[
        "delivery",
        "take",
        "pizza"
    ],
    "sg:website":"http://www.pizzahut.com",
    "wof:name":"Pizza Hut",
    "wof:placetype":"venue"
},
  "geometry": {"coordinates":[-71.04001599999999,42.396852],"type":"Point"}
}