{
  "type": "Feature",
  "properties": {
    "addr:full": "178 Everett Ave Chelsea MA 02150",
    "addr:housenumber": "178",
    "addr:postcode": "02150",
    "addr:street": "Everett Ave",
    "iso:country": "US",
    "sg:address": "178 Everett Ave",
    "sg:city": "Chelsea",
    "sg:classifiers": [
      {
        "category": "Fast Food",
        "type": "Food \u0026 Drink"
      },
      {
        "category": "Restaurant",
        "type": "Food \u0026 Drink"
      },
      {
        "category": "Professional",
        "type": "Services"
      }
    ],
    "sg:phone": "+1 617 889 6818",
    "sg:postcode": "02150",
    "sg:province": "MA",
    "sg:tags": [
      "delivery",
      "take",
      "pizza"
    ],
    "sg:website": "http://www.pizzahut.com",
    "wof:name": "Pizza Hut",
    "wof:placetype": "venue"
  },
  "geometry": {"coordinates":[-71.040016,42.396852],"type":"Point"}
}
