{
  "type": "Feature",
  "properties": {
    "addr:full": "1100 Revere Beach Pkwy #8979 Chelsea MA 02150",
    "addr:housenumber": "1100",
    "addr:postcode": "02150",
    "addr:street": "Revere Beach Pkwy # 8979",
    "iso:country": "US",
    "ovtr:label": "The Home Depot, 1100 Revere Beach Pkwy Chelsea MA US",
    "ovtr:similarity": 3.617518901824951,
    "sg:address": "1100 Revere Beach Pkwy #8979",
    "sg:city": "Chelsea",
    "sg:classifiers": [
      {
        "category": "Home \u0026 Garden",
        "subcategory": "Hardware",
        "type": "Retail Goods"
      },
      {
        "category": "Home \u0026 Garden",
        "subcategory": "Building Materials",
        "type": "Retail Goods"
      }
    ],
    "sg:phone": "+1 617 889 4258",
    "sg:postcode": "02150",
    "sg:province": "MA",
    "sg:tags": [
      "store",
      "supply"
    ],
    "sg:website": "www.homedepot.com",
    "wof:name": "The Home Depot",
    "wof:placetype": "venue"
  },
  "geometry": {"coordinates":[-71.0241,42.4039],"type":"Point"}
}
