{
  "type": "Feature",
  "properties": {
    "iso:country":"US",
    "sg:address":"179 Washington St",
    "sg:city":"Norwell",
    "sg:classifiers":[
        {
            "category":"Freight",
            "type":"Transportation"
        }
    ],
    "sg:phone":"+1 781 878 9922",
    "sg:postcode":"02061",
    "sg:province":"MA",
    "sg:tags":[
        "commercial",
        "storage"
    ],
    "wof:name":"Walk-In Closet Self Storage",
    "wof:placetype":"venue"
},
  "geometry": {"coordinates":[-70.87167599999999,42.166599],"type":"Point"}
}