{
  "type": "Feature",
  "properties": {
    "addr:full": "179 Washington St Norwell MA 02061",
    "addr:housenumber": "179",
    "addr:postcode": "02061",
    "addr:street": "Washington St",
    "iso:country": "US",
    "sg:address": "179 Washington St",
    "sg:city": "Norwell",
    "sg:classifiers": [
      {
        "category": "Freight",
        "type": "Transportation"
      }
    ],
    "sg:phone": "+1 781 878 9922",
    "sg:postcode": "02061",
    "sg:province": "MA",
    "sg:tags": [
      "commercial",
      "storage"
    ],
    "wof:name": "Walk-In Closet Self Storage",
    "wof:placetype": "venue"
  },
  "geometry": {"coordinates":[-70.871676,42.166599],"type":"Point"}
}
