{
  "type": "Feature",
  "properties": {
    "addr:full": "66 Chestnut St Needham MA 02492",
    "addr:housenumber": "66",
    "addr:postcode": "02492",
    "addr:street": "Chestnut St",
    "iso:country": "US",
    "sg:address": "66 Chestnut St",
    "sg:city": "Needham",
    "sg:classifiers": [
      {
        "category": "Restaurant",
        "type": "Food \u0026 Drink"
      }
    ],
    "sg:phone": "+1 781 453 1000",
    "sg:postcode": "02492",
    "sg:province": "MA",
    "sg:tags": [
      "mexican"
    ],
    "wof:name": "Tu Y Yo Mexican Cuisine",
    "wof:placetype": "venue"
  },
  "geometry": {"coordinates":[-71.237162,42.278876],"type":"Point"}
}
