{
  "type": "Feature",
  "properties": {
    "iso:country":"US",
    "sg:address":"24 Golf St",
    "sg:city":"Fairhaven",
    "sg:classifiers":[
        {
            "category":"Building & Trades",
            "subcategory":"Construction",
            "type":"Services"
        }
    ],
    "sg:phone":"+1 508 994 9090",
    "sg:postcode":"02719",
    "sg:province":"MA",
    "sg:tags":[
        "wallpaper"
    ],
    "wof:name":"Interiors By Ron",
    "wof:placetype":"venue"
},
  "geometry": {"coordinates":[-70.87282399999999,41.631476],"type":"Point"}
}