{
  "type": "Feature",
  "properties": {
    "addr:full": "24 Golf St Fairhaven MA 02719",
    "addr:housenumber": "24",
    "addr:postcode": "02719",
    "addr:street": "Golf St",
    "iso:country": "US",
    "sg:address": "24 Golf St",
    "sg:city": "Fairhaven",
    "sg:classifiers": [
      {
        "category": "Building \u0026 Trades",
        "subcategory": "Construction",
        "type": "Services"
      }
    ],
    "sg:phone": "+1 508 994 9090",
    "sg:postcode": "02719",
    "sg:province": "MA",
    "sg:tags": [
      "wallpaper"
    ],
    "wof:name": "Interiors By Ron",
    "wof:placetype": "venue"
  },
  "geometry": {"coordinates":[-70.872824,41.631476],"type":"Point"}
}
