{
  "type": "Feature",
  "properties": {
    "addr:full": "105 Myrtle St Quincy MA 02171",
    "addr:housenumber": "105",
    "addr:postcode": "02171",
    "addr:street": "Myrtle St",
    "iso:country": "US",
    "sg:address": "105 Myrtle St",
    "sg:city": "Quincy",
    "sg:classifiers": [
      {
        "category": "Home \u0026 Garden",
        "subcategory": "Building Materials",
        "type": "Retail Goods"
      },
      {
        "category": "Building \u0026 Trades",
        "subcategory": "Construction",
        "type": "Services"
      }
    ],
    "sg:phone": "+1 617 328 9300",
    "sg:postcode": "02171",
    "sg:province": "MA",
    "sg:tags": [
      "concrete",
      "staining",
      "contractor"
    ],
    "wof:name": "Gardiner Concrete Corp",
    "wof:placetype": "venue"
  },
  "geometry": {"coordinates":[-71.036814,42.278827],"type":"Point"}
}
