{
  "type": "Feature",
  "properties": {
    "iso:country":"US",
    "sg:address":"100 City Hall Plz Ste 550",
    "sg:city":"Boston",
    "sg:classifiers":[
        {
            "category":"Professional",
            "subcategory":"Employment Agencies",
            "type":"Services"
        }
    ],
    "sg:phone":"+1 617 723 1919",
    "sg:postcode":"02108",
    "sg:province":"MA",
    "wof:name":"Preferred Temporaries",
    "wof:placetype":"venue"
},
  "geometry": {"coordinates":[-71.057999,42.3591],"type":"Point"}
}