{
  "type": "Feature",
  "properties": {
    "addr:full":"104 Swansom Rd Swansea MA 02777",
    "addr:housenumber":"104",
    "addr:postcode":"02777",
    "addr:street":"Swansom Rd",
    "iso:country":"US",
    "sg:address":"104 Swansom Rd",
    "sg:city":"Swansea",
    "sg:classifiers":[
        {
            "category":"Building & Trades",
            "subcategory":"Construction",
            "type":"Services"
        }
    ],
    "sg:phone":"+1   ",
    "sg:postcode":"02777",
    "sg:province":"MA",
    "sg:tags":[
        "hanging",
        "contractor"
    ],
    "wof:name":"Cire Painting Inc",
    "wof:placetype":"venue"
},
  "geometry": {"coordinates":[-71.16677199999999,41.74378],"type":"Point"}
}