{
  "type": "Feature",
  "properties": {
    "addr:full":"419 Bremen St Boston MA 02128",
    "addr:housenumber":"419",
    "addr:postcode":"02128",
    "addr:street":"Bremen St",
    "iso:country":"US",
    "sg:address":"419 Bremen St",
    "sg:city":"Boston",
    "sg:classifiers":[
        {
            "category":"Transit Center",
            "subcategory":"Freight",
            "type":"Transportation"
        }
    ],
    "sg:phone":"+1 617 561 1280",
    "sg:postcode":"02128",
    "sg:province":"MA",
    "sg:tags":[
        "forwarding"
    ],
    "wof:name":"Team Air Express",
    "wof:placetype":"venue"
},
  "geometry": {"coordinates":[-71.026443,42.379601],"type":"Point"}
}