{
  "type": "Feature",
  "properties": {
    "addr:full":"49 Rose St Stoughton MA 02072",
    "addr:housenumber":"49",
    "addr:postcode":"02072",
    "addr:street":"Rose St",
    "iso:country":"US",
    "sg:address":"49 Rose St",
    "sg:city":"Stoughton",
    "sg:classifiers":[
        {
            "category":"Shopping",
            "subcategory":"Clothing, Apparel, & Fashions",
            "type":"Retail Goods"
        }
    ],
    "sg:phone":"+1 781 344 1400",
    "sg:postcode":"02072",
    "sg:province":"MA",
    "sg:tags":[
        "garment"
    ],
    "wof:name":"Volume Apparel",
    "wof:placetype":"venue"
},
  "geometry": {"coordinates":[-71.10424,42.125762],"type":"Point"}
}