{
  "type": "Feature",
  "properties": {
    "addr:full":"119 Clarence St Everett MA 02149",
    "addr:housenumber":"119",
    "addr:postcode":"02149",
    "addr:street":"Clarence St",
    "iso:country":"US",
    "sg:address":"119 Clarence St",
    "sg:city":"Everett",
    "sg:classifiers":[
        {
            "category":"Professional",
            "subcategory":"Research",
            "type":"Services"
        },
        {
            "category":"Education",
            "subcategory":"Library",
            "type":"Public Place"
        }
    ],
    "sg:phone":"+1 617 387 3060",
    "sg:postcode":"02149",
    "sg:province":"MA",
    "sg:website":"http://www.agencyforchange.com",
    "wof:name":"Cambrdge Inst Psychlgcal Types",
    "wof:placetype":"venue"
},
  "geometry": {"coordinates":[-71.04387800000001,42.411896],"type":"Point"}
}