{
  "type": "Feature",
  "properties": {
    "addr:full": "11 Court St Plymouth MA 02360",
    "addr:housenumber": "11",
    "addr:postcode": "02360",
    "addr:street": "Court St",
    "iso:country": "US",
    "sg:address": "11 Court St",
    "sg:city": "Plymouth",
    "sg:classifiers": [
      {
        "category": "Wholesale",
        "subcategory": "Construction Materials",
        "type": "Manufacturing \u0026 Wholesale Goods"
      }
    ],
    "sg:phone": "+1 508 746 0555",
    "sg:postcode": "02360",
    "sg:province": "MA",
    "sg:tags": [
      "marble"
    ],
    "wof:name": "Mayflower Mahogany \u0026 Marble",
    "wof:placetype": "venue"
  },
  "geometry": {"coordinates":[-70.665782,41.957469],"type":"Point"}
}
