{
  "type": "Feature",
  "properties": {
    "iso:country":"US",
    "sg:address":"346 Salem Street",
    "sg:city":"Revere",
    "sg:classifiers":[
        {
            "category":"Retail",
            "subcategory":"Auto Repair",
            "type":"Services"
        }
    ],
    "sg:phone":"+1 781 321 0880",
    "sg:postcode":"02151",
    "sg:province":"MA",
    "wof:name":"Gary's Auto Service",
    "wof:placetype":"venue"
},
  "geometry": {"coordinates":[-71.013519,42.443066],"type":"Point"}
}