{
  "type": "Feature",
  "properties": {
    "iso:country":"US",
    "sg:address":"29 Academy Ave",
    "sg:city":"Fairhaven",
    "sg:classifiers":[
        {
            "category":"Building & Trades",
            "subcategory":"Plumbing",
            "type":"Services"
        }
    ],
    "sg:phone":"+1 508 984 7405",
    "sg:postcode":"02719",
    "sg:province":"MA",
    "sg:tags":[
        "plumber",
        "industrial",
        "contractors-commercial"
    ],
    "wof:name":"Randy Oliveira Plumbing Htg A/C",
    "wof:placetype":"venue"
},
  "geometry": {"coordinates":[-70.906987,41.645498],"type":"Point"}
}