{
  "type": "Feature",
  "properties": {
    "addr:full": "29 Academy Ave Fairhaven MA 02719",
    "addr:housenumber": "29",
    "addr:postcode": "02719",
    "addr:street": "Academy Ave",
    "iso:country": "US",
    "sg:address": "29 Academy Ave",
    "sg:city": "Fairhaven",
    "sg:classifiers": [
      {
        "category": "Building \u0026 Trades",
        "subcategory": "Plumbing",
        "type": "Services"
      }
    ],
    "sg:phone": "+1 508 984 7405",
    "sg:postcode": "02719",
    "sg:province": "MA",
    "sg:tags": [
      "plumber",
      "industrial",
      "contractors-commercial"
    ],
    "wof:name": "Randy Oliveira Plumbing Htg A/C",
    "wof:placetype": "venue"
  },
  "geometry": {"coordinates":[-70.906987,41.645498],"type":"Point"}
}
