{
  "type": "Feature",
  "properties": {
    "iso:country":"US",
    "sg:address":"233 Haven St",
    "sg:city":"Reading",
    "sg:classifiers":[
        {
            "category":"Personal",
            "subcategory":"Beauty Salon",
            "type":"Services"
        }
    ],
    "sg:phone":"+1 781 205 4188",
    "sg:postcode":"01867",
    "sg:province":"MA",
    "sg:tags":[
        "hair"
    ],
    "wof:name":"Embelleish Salon",
    "wof:placetype":"venue"
},
  "geometry": {"coordinates":[-71.10235299999999,42.523431],"type":"Point"}
}