{
  "type": "Feature",
  "properties": {
    "iso:country":"US",
    "sg:address":"591 Elm St",
    "sg:city":"West Springfield",
    "sg:classifiers":[
        {
            "category":"Building & Trades",
            "subcategory":"Electrical",
            "type":"Services"
        }
    ],
    "sg:phone":"+1   ",
    "sg:postcode":"01089",
    "sg:province":"MA",
    "sg:tags":[
        "electrical",
        "contractor"
    ],
    "wof:name":"J A Jalbert Electric",
    "wof:placetype":"venue"
},
  "geometry": {"coordinates":[-72.624954,42.113377],"type":"Point"}
}