{
  "type": "Feature",
  "properties": {
    "addr:full": "167 Broadway Everett MA 02149",
    "addr:housenumber": "167",
    "addr:postcode": "02149",
    "addr:street": "Broadway",
    "iso:country": "US",
    "sg:address": "167 Broadway",
    "sg:city": "Everett",
    "sg:classifiers": [
      {
        "category": "Retail",
        "subcategory": "Auto Repair",
        "type": "Services"
      }
    ],
    "sg:phone": "+1 617 387 8118",
    "sg:postcode": "02149",
    "sg:province": "MA",
    "sg:tags": [
      "repairing",
      "automobile"
    ],
    "wof:name": "Perfect Grinding Company",
    "wof:placetype": "venue"
  },
  "geometry": {"coordinates":[-71.063029,42.399175],"type":"Point"}
}
