{
  "type": "Feature",
  "properties": {
    "iso:country":"US",
    "sg:address":"21 Union Sq Ste A",
    "sg:city":"Somerville",
    "sg:classifiers":[
        {
            "category":"Personal",
            "subcategory":"Barber",
            "type":"Services"
        }
    ],
    "sg:phone":"+1 617 628 8020",
    "sg:postcode":"02143",
    "sg:province":"MA",
    "wof:name":"Robert Charles Hair Cutters",
    "wof:placetype":"venue"
},
  "geometry": {"coordinates":[-71.09636999999999,42.379688],"type":"Point"}
}