{
  "type": "Feature",
  "properties": {
    "addr:full": "52 Province St Boston MA 02108",
    "addr:housenumber": "52",
    "addr:postcode": "02108",
    "addr:street": "Province St",
    "iso:country": "US",
    "sg:address": "52 Province St",
    "sg:city": "Boston",
    "sg:classifiers": [
      {
        "category": "Parking",
        "type": "Transportation"
      }
    ],
    "sg:phone": "+1 617 426 0604",
    "sg:postcode": "02108",
    "sg:province": "MA",
    "sg:tags": [
      "garage"
    ],
    "wof:name": "Laz Parking LTD",
    "wof:placetype": "venue"
  },
  "geometry": {"coordinates":[-71.060009,42.356867],"type":"Point"}
}
