{
  "type": "Feature",
  "properties": {
    "iso:country":"US",
    "sg:address":"360 Pearl St",
    "sg:city":"Malden",
    "sg:classifiers":[
        {
            "category":"Building & Trades",
            "subcategory":"Cleaning & Sanitation",
            "type":"Services"
        }
    ],
    "sg:phone":"+1 781 324 2900",
    "sg:postcode":"02148",
    "sg:province":"MA",
    "sg:tags":[
        "janitor",
        "janitorial"
    ],
    "sg:website":"http://www.pbsclean.com",
    "wof:name":"Prospect Building Services Corp",
    "wof:placetype":"venue"
},
  "geometry": {"coordinates":[-71.07766599999999,42.417467],"type":"Point"}
}