{
  "type": "Feature",
  "properties": {
    "addr:full":"71 Worcester St Apt 4 Boston MA 02118",
    "addr:housenumber":"71;4",
    "addr:postcode":"02118",
    "addr:street":"Worcester St Apt",
    "iso:country":"US",
    "sg:address":"71 Worcester St Apt 4",
    "sg:city":"Boston",
    "sg:classifiers":[
        {
            "category":"Food & Beverages",
            "subcategory":"Liquor & Beverages",
            "type":"Retail Goods"
        }
    ],
    "sg:phone":"+1 617 859 7141",
    "sg:postcode":"02118",
    "sg:province":"MA",
    "sg:tags":[
        "store"
    ],
    "wof:name":"Rex Assoc",
    "wof:placetype":"venue"
},
  "geometry": {"coordinates":[-71.077794,42.339228],"type":"Point"}
}