{
  "type": "Feature",
  "properties": {
    "addr:full": "314 Hadley St South Hadley MA 01075",
    "addr:housenumber": "314",
    "addr:postcode": "01075",
    "addr:street": "Hadley St",
    "iso:country": "US",
    "sg:address": "314 Hadley St",
    "sg:city": "South Hadley",
    "sg:classifiers": [
      {
        "category": "Food \u0026 Beverages",
        "subcategory": "Liquor \u0026 Beverages",
        "type": "Retail Goods"
      }
    ],
    "sg:phone": "+1 413 532 5188",
    "sg:postcode": "01075",
    "sg:province": "MA",
    "wof:name": "Allery's Package Store",
    "wof:placetype": "venue"
  },
  "geometry": {"coordinates":[-72.592441,42.283273],"type":"Point"}
}
