{
  "type": "Feature",
  "properties": {
    "iso:country":"US",
    "sg:address":"314 Hadley St",
    "sg:city":"South Hadley",
    "sg:classifiers":[
        {
            "category":"Food & Beverages",
            "subcategory":"Liquor & Beverages",
            "type":"Retail Goods"
        }
    ],
    "sg:phone":"+1 413 532 5188",
    "sg:postcode":"01075",
    "sg:province":"MA",
    "wof:name":"Allery's Package Store",
    "wof:placetype":"venue"
},
  "geometry": {"coordinates":[-72.59244099999999,42.283273],"type":"Point"}
}