{
  "type": "Feature",
  "properties": {
    "iso:country":"US",
    "sg:address":"112 Main St",
    "sg:city":"North Easton",
    "sg:classifiers":[
        {
            "category":"Personal",
            "subcategory":"Barber",
            "type":"Services"
        }
    ],
    "sg:phone":"+1 508 238 2530",
    "sg:postcode":"02356",
    "sg:province":"MA",
    "wof:name":"North Easton Barber Shop",
    "wof:placetype":"venue"
},
  "geometry": {"coordinates":[-71.101,42.066009],"type":"Point"}
}