{
  "type": "Feature",
  "properties": {
    "addr:full": "361 Main St Ste 5 Tewksbury MA 01876",
    "addr:housenumber": "361",
    "addr:postcode": "01876",
    "addr:street": "Main St Ste 5",
    "iso:country": "US",
    "sg:address": "361 Main St Ste 5",
    "sg:city": "Tewksbury",
    "sg:classifiers": [
      {
        "category": "Home \u0026 Garden",
        "subcategory": "Kitchen Supply",
        "type": "Retail Goods"
      }
    ],
    "sg:phone": "+1 978 446 0588",
    "sg:postcode": "01876",
    "sg:province": "MA",
    "sg:tags": [
      "utensil",
      "cookware"
    ],
    "wof:name": "Magic Brush",
    "wof:placetype": "venue"
  },
  "geometry": {"coordinates":[-71.261585,42.621137],"type":"Point"}
}
