{
  "type": "Feature",
  "properties": {
    "addr:full": "607 North Ave Ste 17-10 Wakefield MA 01880",
    "addr:housenumber": "607",
    "addr:postcode": "01880",
    "addr:street": "North Ave Ste 17-10",
    "iso:country": "US",
    "sg:address": "607 North Ave Ste 17-10",
    "sg:city": "Wakefield",
    "sg:classifiers": [
      {
        "category": "Coffee \u0026 Tea",
        "type": "Food \u0026 Drink"
      },
      {
        "category": "Restaurant",
        "type": "Food \u0026 Drink"
      },
      {
        "category": "Deli",
        "type": "Food \u0026 Drink"
      }
    ],
    "sg:phone": "+1 781 246 2038",
    "sg:postcode": "01880",
    "sg:province": "MA",
    "sg:tags": [
      "shop",
      "delicatessen",
      "espresso"
    ],
    "wof:name": "Lakeside Coffee Shop",
    "wof:placetype": "venue"
  },
  "geometry": {"coordinates":[-71.087298,42.515297],"type":"Point"}
}
