{
  "type": "Feature",
  "properties": {
    "iso:country":"US",
    "sg:address":"607 North Ave Ste 17-10",
    "sg:city":"Wakefield",
    "sg:classifiers":[
        {
            "category":"Coffee & Tea",
            "type":"Food & Drink"
        },
        {
            "category":"Restaurant",
            "type":"Food & Drink"
        },
        {
            "category":"Deli",
            "type":"Food & Drink"
        }
    ],
    "sg:phone":"+1 781 246 2038",
    "sg:postcode":"01880",
    "sg:province":"MA",
    "sg:tags":[
        "shop",
        "delicatessen",
        "espresso"
    ],
    "wof:name":"Lakeside Coffee Shop",
    "wof:placetype":"venue"
},
  "geometry": {"coordinates":[-71.087298,42.515297],"type":"Point"}
}