{
  "type": "Feature",
  "properties": {
    "iso:country":"US",
    "sg:address":"45 Cranston St",
    "sg:city":"Jamaica Plain",
    "sg:classifiers":[
        {
            "category":"Professional",
            "subcategory":"Management & Consulting",
            "type":"Services"
        }
    ],
    "sg:phone":"+1   ",
    "sg:postcode":"02130",
    "sg:province":"MA",
    "sg:tags":[
        "business"
    ],
    "wof:name":"Itnet Consulting Services Inc",
    "wof:placetype":"venue"
},
  "geometry": {"coordinates":[-71.10734600000001,42.32028],"type":"Point"}
}