{
  "type": "Feature",
  "properties": {
    "addr:full": "45 Cranston St Jamaica Plain MA 02130",
    "addr:housenumber": "45",
    "addr:postcode": "02130",
    "addr:street": "Cranston St",
    "iso:country": "US",
    "sg:address": "45 Cranston St",
    "sg:city": "Jamaica Plain",
    "sg:classifiers": [
      {
        "category": "Professional",
        "subcategory": "Management \u0026 Consulting",
        "type": "Services"
      }
    ],
    "sg:phone": "+1   ",
    "sg:postcode": "02130",
    "sg:province": "MA",
    "sg:tags": [
      "business"
    ],
    "wof:name": "Itnet Consulting Services Inc",
    "wof:placetype": "venue"
  },
  "geometry": {"coordinates":[-71.107346,42.32028],"type":"Point"}
}
