{
  "type": "Feature",
  "properties": {
    "addr:full": "975 Elm St West Springfield MA 01089",
    "addr:housenumber": "975",
    "addr:postcode": "01089",
    "addr:street": "Elm St",
    "iso:country": "US",
    "sg:address": "975 Elm St",
    "sg:city": "West Springfield",
    "sg:classifiers": [
      {
        "category": "Building \u0026 Trades",
        "subcategory": "Construction",
        "type": "Services"
      }
    ],
    "sg:phone": "+1 413 737 9628",
    "sg:postcode": "01089",
    "sg:province": "MA",
    "sg:tags": [
      "general",
      "contractor"
    ],
    "wof:name": "C \u0026 A Construction Co",
    "wof:placetype": "venue"
  },
  "geometry": {"coordinates":[-72.627674,42.117546],"type":"Point"}
}
