{
  "type": "Feature",
  "properties": {
    "iso:country":"US",
    "sg:address":"975 Elm St",
    "sg:city":"West Springfield",
    "sg:classifiers":[
        {
            "category":"Building & Trades",
            "subcategory":"Construction",
            "type":"Services"
        }
    ],
    "sg:phone":"+1 413 737 9628",
    "sg:postcode":"01089",
    "sg:province":"MA",
    "sg:tags":[
        "general",
        "contractor"
    ],
    "wof:name":"C & A Construction Co",
    "wof:placetype":"venue"
},
  "geometry": {"coordinates":[-72.627674,42.117546],"type":"Point"}
}