{
  "type": "Feature",
  "properties": {
    "iso:country":"US",
    "sg:address":"499 S Broadway",
    "sg:city":"Lawrence",
    "sg:classifiers":[
        {
            "category":"Restaurant",
            "type":"Food & Drink"
        }
    ],
    "sg:phone":"+1 978 725 8076",
    "sg:postcode":"01843",
    "sg:province":"MA",
    "wof:name":"Pizzeria Bravo",
    "wof:placetype":"venue"
},
  "geometry": {"coordinates":[-71.155377,42.68446],"type":"Point"}
}