{
  "type": "Feature",
  "properties": {
    "iso:country":"US",
    "sg:address":"5 Lakeview Ave",
    "sg:city":"Danvers",
    "sg:classifiers":[
        {
            "category":"Professional",
            "subcategory":"Management & Consulting",
            "type":"Services"
        }
    ],
    "sg:phone":"+1 978 774 6655",
    "sg:postcode":"01923",
    "sg:province":"MA",
    "sg:tags":[
        "marketing",
        "consultant"
    ],
    "wof:name":"Boylan & Assoc",
    "wof:placetype":"venue"
},
  "geometry": {"coordinates":[-70.942999,42.607376],"type":"Point"}
}