{
  "type": "Feature",
  "properties": {
    "addr:full": "5 Lakeview Ave Danvers MA 01923",
    "addr:housenumber": "5",
    "addr:postcode": "01923",
    "addr:street": "Lakeview Ave",
    "iso:country": "US",
    "sg:address": "5 Lakeview Ave",
    "sg:city": "Danvers",
    "sg:classifiers": [
      {
        "category": "Professional",
        "subcategory": "Management \u0026 Consulting",
        "type": "Services"
      }
    ],
    "sg:phone": "+1 978 774 6655",
    "sg:postcode": "01923",
    "sg:province": "MA",
    "sg:tags": [
      "marketing",
      "consultant"
    ],
    "wof:name": "Boylan \u0026 Assoc",
    "wof:placetype": "venue"
  },
  "geometry": {"coordinates":[-70.942999,42.607376],"type":"Point"}
}
