{
  "type": "Feature",
  "properties": {
    "addr:full": "99 Summer St Boston MA 02110",
    "addr:housenumber": "99",
    "addr:postcode": "02110",
    "addr:street": "Summer St",
    "iso:country": "US",
    "sg:address": "99 Summer St",
    "sg:city": "Boston",
    "sg:classifiers": [
      {
        "category": "Professional",
        "subcategory": "Art Services",
        "type": "Services"
      }
    ],
    "sg:phone": "+1 617 439 8888",
    "sg:postcode": "02110",
    "sg:province": "MA",
    "wof:name": "Offtech Inc",
    "wof:placetype": "venue"
  },
  "geometry": {"coordinates":[-71.057991,42.353743],"type":"Point"}
}
