{
  "type": "Feature",
  "properties": {
    "addr:full":"299 Salem St Swampscott MA 01907",
    "addr:housenumber":"299",
    "addr:postcode":"01907",
    "addr:street":"Salem St",
    "iso:country":"US",
    "sg:address":"299 Salem St",
    "sg:city":"Swampscott",
    "sg:classifiers":[
        {
            "category":"Bars & Pubs",
            "subcategory":"Lounge",
            "type":"Food & Drink"
        },
        {
            "category":"Restaurant",
            "type":"Food & Drink"
        }
    ],
    "sg:phone":"+1 781 595 5151",
    "sg:postcode":"01907",
    "sg:province":"MA",
    "sg:tags":[
        "seafood",
        "cocktail"
    ],
    "sg:website":"http://www.pier4.com",
    "wof:name":"Anthony's Pier 4 Restaurant",
    "wof:placetype":"venue"
},
  "geometry": {"coordinates":[-70.898928,42.483903],"type":"Point"}
}