{
  "type": "Feature",
  "properties": {
    "iso:country":"US",
    "sg:address":"279 Yarmouth Rd",
    "sg:city":"Hyannis",
    "sg:classifiers":[
        {
            "category":"Building & Trades",
            "subcategory":"Plumbing",
            "type":"Services"
        }
    ],
    "sg:phone":"+1 508 775 3083",
    "sg:postcode":"02601",
    "sg:province":"MA",
    "sg:tags":[
        "conditioning",
        "air",
        "system",
        "contractor"
    ],
    "wof:name":"Robie's Refrigeration Inc",
    "wof:placetype":"venue"
},
  "geometry": {"coordinates":[-70.27321000000001,41.664044],"type":"Point"}
}