{
  "type": "Feature",
  "properties": {
    "addr:full": "66 Summer St Manchester MA 01944",
    "addr:housenumber": "66",
    "addr:postcode": "01944",
    "addr:street": "Summer St",
    "iso:country": "US",
    "sg:address": "66 Summer St",
    "sg:city": "Manchester",
    "sg:classifiers": [
      {
        "category": "Manufacturing",
        "subcategory": "Electronics",
        "type": "Manufacturing \u0026 Wholesale Goods"
      }
    ],
    "sg:phone": "+1 978 526 7999",
    "sg:postcode": "01944",
    "sg:province": "MA",
    "sg:tags": [
      "semiconductor",
      "devices"
    ],
    "wof:name": "Patricia Murray",
    "wof:placetype": "venue"
  },
  "geometry": {"coordinates":[-70.765147,42.57691],"type":"Point"}
}
