{
  "type": "Feature",
  "properties": {
    "addr:full":"25 Holcott Dr Attleboro MA 02703",
    "addr:housenumber":"25",
    "addr:postcode":"02703",
    "addr:street":"Holcott Dr",
    "iso:country":"US",
    "sg:address":"25 Holcott Dr",
    "sg:city":"Attleboro",
    "sg:classifiers":[
        {
            "category":"Manufacturing",
            "subcategory":"Tools & Machinery",
            "type":"Manufacturing & Wholesale Goods"
        }
    ],
    "sg:phone":"+1 508 431 2300",
    "sg:postcode":"02703",
    "sg:province":"MA",
    "sg:tags":[
        "measuring",
        "material",
        "temperature"
    ],
    "wof:name":"Protemp Calibration & Svc",
    "wof:placetype":"venue"
},
  "geometry": {"coordinates":[-71.292379,41.966063],"type":"Point"}
}