{
  "type": "Feature",
  "properties": {
    "addr:full":"3 Crossing Plz Franklin MA 02038",
    "addr:housenumber":"3",
    "addr:postcode":"02038",
    "addr:street":"Crossing Plz",
    "iso:country":"US",
    "sg:address":"3 Crossing Plz",
    "sg:city":"Franklin",
    "sg:classifiers":[
        {
            "category":"Restaurant",
            "type":"Food & Drink"
        }
    ],
    "sg:phone":"+1 508 541 5414",
    "sg:postcode":"02038",
    "sg:province":"MA",
    "wof:name":"Cafe At The Crossing",
    "wof:placetype":"venue"
},
  "geometry": {"coordinates":[-71.40237999999999,42.0778],"type":"Point"}
}