{
  "type": "Feature",
  "properties": {
    "addr:full": "62 Ohio Ave West Springfield MA 01089",
    "addr:housenumber": "62",
    "addr:postcode": "01089",
    "addr:street": "Ohio Ave",
    "iso:country": "US",
    "sg:address": "62 Ohio Ave",
    "sg:city": "West Springfield",
    "sg:classifiers": [
      {
        "category": "Real Estate",
        "subcategory": "Real Estate Agent",
        "type": "Services"
      }
    ],
    "sg:phone": "+1 413 731 9839",
    "sg:postcode": "01089",
    "sg:province": "MA",
    "wof:name": "Realty West",
    "wof:placetype": "venue"
  },
  "geometry": {"coordinates":[-72.670245,42.108454],"type":"Point"}
}
