{
  "type": "Feature",
  "properties": {
    "addr:full": "26 S Main St Leicester MA 01524",
    "addr:housenumber": "26",
    "addr:postcode": "01524",
    "addr:street": "S Main St",
    "iso:country": "US",
    "sg:address": "26 S Main St",
    "sg:city": "Leicester",
    "sg:classifiers": [
      {
        "category": "Wholesale",
        "subcategory": "Non-durable Goods",
        "type": "Manufacturing \u0026 Wholesale Goods"
      }
    ],
    "sg:phone": "+1 508 892 1555",
    "sg:postcode": "01524",
    "sg:province": "MA",
    "sg:tags": [
      "advertising"
    ],
    "wof:name": "Creative Services",
    "wof:placetype": "venue"
  },
  "geometry": {"coordinates":[-71.907362,42.245262],"type":"Point"}
}
