{
  "type": "Feature",
  "properties": {
    "addr:full": "990 Washington St Dedham MA 02026",
    "addr:housenumber": "990",
    "addr:postcode": "02026",
    "addr:street": "Washington St",
    "iso:country": "US",
    "sg:address": "990 Washington St",
    "sg:city": "Dedham",
    "sg:classifiers": [
      {
        "category": "Professional",
        "subcategory": "Employment Agencies",
        "type": "Services"
      }
    ],
    "sg:phone": "+1 781 329 2660",
    "sg:postcode": "02026",
    "sg:province": "MA",
    "wof:name": "Reardon Associates Emply Agcy",
    "wof:placetype": "venue"
  },
  "geometry": {"coordinates":[-71.185699,42.229698],"type":"Point"}
}
