{
  "type": "Feature",
  "properties": {
    "addr:full": "30 Monument Sq Concord MA 01742",
    "addr:housenumber": "30",
    "addr:postcode": "01742",
    "addr:street": "Monument Sq",
    "iso:country": "US",
    "sg:address": "30 Monument Sq",
    "sg:city": "Concord",
    "sg:classifiers": [
      {
        "category": "Professional",
        "subcategory": "Lawyer \u0026 Legal Services",
        "type": "Services"
      }
    ],
    "sg:phone": "+1 978 369 2252",
    "sg:postcode": "01742",
    "sg:province": "MA",
    "sg:tags": [
      "divorce",
      "law",
      "family"
    ],
    "wof:name": "McWalter Maurice Jr Atty",
    "wof:placetype": "venue"
  },
  "geometry": {"coordinates":[-71.371002,42.456501],"type":"Point"}
}
