{
  "type": "Feature",
  "properties": {
    "iso:country":"US",
    "sg:address":"175 W Main St",
    "sg:city":"Millbury",
    "sg:classifiers":[
        {
            "category":"Wholesale",
            "subcategory":"Toys & Hobbies",
            "type":"Manufacturing & Wholesale Goods"
        }
    ],
    "sg:phone":"+1 508 865 7544",
    "sg:postcode":"01527",
    "sg:province":"MA",
    "wof:name":"Ceramic Decor",
    "wof:placetype":"venue"
},
  "geometry": {"coordinates":[-71.77965,42.172366],"type":"Point"}
}