{
  "type": "Feature",
  "properties": {
    "addr:full": "2 Old Farm Rd Hopkinton MA 01748",
    "addr:housenumber": "2",
    "addr:postcode": "01748",
    "addr:street": "Old Farm Rd",
    "iso:country": "US",
    "sg:address": "2 Old Farm Rd",
    "sg:city": "Hopkinton",
    "sg:classifiers": [
      {
        "category": "Building \u0026 Trades",
        "subcategory": "Construction",
        "type": "Services"
      }
    ],
    "sg:phone": "+1 508 435 4186",
    "sg:postcode": "01748",
    "sg:province": "MA",
    "sg:tags": [
      "contractor"
    ],
    "wof:name": "Bay State Housewrights Inc",
    "wof:placetype": "venue"
  },
  "geometry": {"coordinates":[-71.563374,42.209542],"type":"Point"}
}
