{
  "type": "Feature",
  "properties": {
    "iso:country":"US",
    "sg:address":"6 Lynde St",
    "sg:city":"Salem",
    "sg:classifiers":[
        {
            "category":"Professional",
            "subcategory":"Lawyer & Legal Services",
            "type":"Services"
        }
    ],
    "sg:phone":"+1   ",
    "sg:postcode":"01970",
    "sg:province":"MA",
    "wof:name":"James F Rennick",
    "wof:placetype":"venue"
},
  "geometry": {"coordinates":[-70.896282,42.522401],"type":"Point"}
}