{
  "type": "Feature",
  "properties": {
    "addr:full": "6 Lynde St Salem MA 01970",
    "addr:housenumber": "6",
    "addr:postcode": "01970",
    "addr:street": "Lynde St",
    "iso:country": "US",
    "sg:address": "6 Lynde St",
    "sg:city": "Salem",
    "sg:classifiers": [
      {
        "category": "Professional",
        "subcategory": "Lawyer \u0026 Legal Services",
        "type": "Services"
      }
    ],
    "sg:phone": "+1   ",
    "sg:postcode": "01970",
    "sg:province": "MA",
    "wof:name": "James F Rennick",
    "wof:placetype": "venue"
  },
  "geometry": {"coordinates":[-70.896282,42.522401],"type":"Point"}
}
