{
  "type": "Feature",
  "properties": {
    "addr:full": "10 Adams St North Chelmsford MA 01863",
    "addr:housenumber": "10",
    "addr:postcode": "01863",
    "addr:street": "Adams St",
    "iso:country": "US",
    "sg:address": "10 Adams St",
    "sg:city": "North Chelmsford",
    "sg:classifiers": [
      {
        "category": "Health Services",
        "subcategory": "Health Practitioner",
        "type": "Services"
      }
    ],
    "sg:phone": "+1 978 251 7337",
    "sg:postcode": "01863",
    "sg:province": "MA",
    "sg:tags": [
      "psychologist"
    ],
    "wof:name": "Middlesex Psychological Assoc",
    "wof:placetype": "venue"
  },
  "geometry": {"coordinates":[-71.384395,42.638489],"type":"Point"}
}
