{
  "type": "Feature",
  "properties": {
    "addr:full":"17 Bartlett Street Everett MA 02149",
    "addr:housenumber":"17",
    "addr:postcode":"02149",
    "addr:street":"Bartlett Street",
    "iso:country":"US",
    "sg:address":"17 Bartlett Street",
    "sg:city":"Everett",
    "sg:classifiers":[
        {
            "category":"Retail",
            "subcategory":"Laundry & Dry Cleaning",
            "type":"Services"
        }
    ],
    "sg:phone":"+1 617 389 3811",
    "sg:postcode":"02149",
    "sg:province":"MA",
    "wof:name":"Hn Shirt",
    "wof:placetype":"venue"
},
  "geometry": {"coordinates":[-71.06119200000001,42.400451],"type":"Point"}
}