{
  "type": "Feature",
  "properties": {
    "addr:full": "1 Snow Rd Marshfield MA 02050",
    "addr:housenumber": "1",
    "addr:postcode": "02050",
    "addr:street": "Snow Rd",
    "iso:country": "US",
    "sg:address": "1 Snow Rd",
    "sg:city": "Marshfield",
    "sg:classifiers": [
      {
        "category": "Food \u0026 Beverages",
        "subcategory": "Supermarket",
        "type": "Retail Goods"
      }
    ],
    "sg:phone": "+1 781 837 5100",
    "sg:postcode": "02050",
    "sg:province": "MA",
    "sg:tags": [
      "super",
      "store"
    ],
    "sg:website": "http://www.shaws.com",
    "wof:name": "Star 574",
    "wof:placetype": "venue"
  },
  "geometry": {"coordinates":[-70.704514,42.0914],"type":"Point"}
}
