{
  "type": "Feature",
  "properties": {
    "iso:country":"US",
    "sg:address":"835 W Central St",
    "sg:city":"Franklin",
    "sg:classifiers":[
        {
            "category":"Sports & Exercise",
            "subcategory":"Gym",
            "type":"Entertainment"
        }
    ],
    "sg:phone":"+1 508 541 8746",
    "sg:postcode":"02038",
    "sg:province":"MA",
    "sg:tags":[
        "club",
        "health",
        "studio",
        "gymnasium"
    ],
    "wof:name":"It Figures",
    "wof:placetype":"venue"
},
  "geometry": {"coordinates":[-71.432801,42.090716],"type":"Point"}
}