{
  "type": "Feature",
  "properties": {
    "iso:country":"US",
    "sg:address":"1537 Main St",
    "sg:city":"Springfield",
    "sg:classifiers":[
        {
            "category":"Real Estate",
            "subcategory":"Real Estate Agent",
            "type":"Services"
        }
    ],
    "sg:phone":"+1 413 736 8338",
    "sg:postcode":"01103",
    "sg:province":"MA",
    "wof:name":"Mac Millan & Son Inc",
    "wof:placetype":"venue"
},
  "geometry": {"coordinates":[-72.592173,42.103422],"type":"Point"}
}