{
  "type": "Feature",
  "properties": {
    "addr:full":"400 Auburn St Whitman MA 02382",
    "addr:housenumber":"400",
    "addr:postcode":"02382",
    "addr:street":"Auburn St",
    "iso:country":"US",
    "sg:address":"400 Auburn St",
    "sg:city":"Whitman",
    "sg:classifiers":[
        {
            "category":"Health Services",
            "subcategory":"Clinic",
            "type":"Services"
        }
    ],
    "sg:phone":"+1 781 447 8999",
    "sg:postcode":"02382",
    "sg:province":"MA",
    "sg:tags":[
        "home"
    ],
    "sg:website":"www.homeinstead.com",
    "wof:name":"Home Instead Senior Care",
    "wof:placetype":"venue"
},
  "geometry": {"coordinates":[-70.945111,42.070854],"type":"Point"}
}