{
  "type": "Feature",
  "properties": {
    "iso:country":"US",
    "sg:address":"33 Hodgkins Rd",
    "sg:city":"Rockport",
    "sg:classifiers":[
        {
            "category":"Organizations",
            "subcategory":"Religious Organization",
            "type":"Services"
        }
    ],
    "sg:phone":"+1 978 546 2224",
    "sg:postcode":"01966",
    "sg:province":"MA",
    "sg:tags":[
        "church"
    ],
    "wof:name":"Rockport United Methodist Ch",
    "wof:placetype":"venue"
},
  "geometry": {"coordinates":[-70.631073,42.646628],"type":"Point"}
}