{
  "type": "Feature",
  "properties": {
    "addr:full":"30 Larch Ave Fairhaven MA 02719",
    "addr:housenumber":"30",
    "addr:postcode":"02719",
    "addr:street":"Larch Ave",
    "iso:country":"US",
    "sg:address":"30 Larch Ave",
    "sg:city":"Fairhaven",
    "sg:classifiers":[
        {
            "category":"Restaurant",
            "type":"Food & Drink"
        }
    ],
    "sg:phone":"+1 508 997 2917",
    "sg:postcode":"02719",
    "sg:province":"MA",
    "wof:name":"Ocean View Sports Bar & Grill",
    "wof:placetype":"venue"
},
  "geometry": {"coordinates":[-70.905281,41.644218],"type":"Point"}
}