{
  "type": "Feature",
  "properties": {
    "addr:full":"90 Echo Rd Mashpee MA 02649",
    "addr:housenumber":"90",
    "addr:postcode":"02649",
    "addr:street":"Echo Rd",
    "iso:country":"US",
    "sg:address":"90 Echo Rd",
    "sg:city":"Mashpee",
    "sg:classifiers":[
        {
            "category":"Home & Garden",
            "subcategory":"Garden Supply",
            "type":"Retail Goods"
        },
        {
            "category":"Manufacturing",
            "subcategory":"Paper Products",
            "type":"Manufacturing & Wholesale Goods"
        }
    ],
    "sg:phone":"+1 508 539 0627",
    "sg:postcode":"02649",
    "sg:province":"MA",
    "sg:tags":[
        "fertilizer",
        "equipment",
        "bamboo",
        "landscaping"
    ],
    "sg:website":"http://www.lesco.com",
    "wof:name":"Lesco",
    "wof:placetype":"venue"
},
  "geometry": {"coordinates":[-70.495318,41.657587],"type":"Point"}
}