{
  "type": "Feature",
  "properties": {
    "iso:country":"US",
    "sg:address":"270 Lincoln St",
    "sg:city":"North Easton",
    "sg:classifiers":[
        {
            "category":"Wholesale",
            "subcategory":"Machinery & Supplies",
            "type":"Manufacturing & Wholesale Goods"
        }
    ],
    "sg:phone":"+1 508 230 8818",
    "sg:postcode":"02356",
    "sg:province":"MA",
    "sg:tags":[
        "equipment",
        "printing"
    ],
    "wof:name":"Certigraph Printing Equipment",
    "wof:placetype":"venue"
},
  "geometry": {"coordinates":[-71.126082,42.066565],"type":"Point"}
}