{
  "type": "Feature",
  "properties": {
    "addr:full": "270 Lincoln St North Easton MA 02356",
    "addr:housenumber": "270",
    "addr:postcode": "02356",
    "addr:street": "Lincoln St",
    "iso:country": "US",
    "sg:address": "270 Lincoln St",
    "sg:city": "North Easton",
    "sg:classifiers": [
      {
        "category": "Wholesale",
        "subcategory": "Machinery \u0026 Supplies",
        "type": "Manufacturing \u0026 Wholesale Goods"
      }
    ],
    "sg:phone": "+1 508 230 8818",
    "sg:postcode": "02356",
    "sg:province": "MA",
    "sg:tags": [
      "equipment",
      "printing"
    ],
    "wof:name": "Certigraph Printing Equipment",
    "wof:placetype": "venue"
  },
  "geometry": {"coordinates":[-71.126082,42.066565],"type":"Point"}
}
