{
  "type": "Feature",
  "properties": {
    "iso:country":"US",
    "sg:address":"2345 Commonwealth Ave",
    "sg:city":"Auburndale",
    "sg:classifiers":[
        {
            "category":"Travel",
            "subcategory":"Hotels & Motels",
            "type":"Entertainment"
        }
    ],
    "sg:phone":"+1 617 969 1000",
    "sg:postcode":"02466",
    "sg:province":"MA",
    "sg:tags":[
        "lodging"
    ],
    "sg:website":"http://ad.doubleclick.net/clk;227436162;51130857;c?http://www.marriott.com/hotels/travel/BOSNT",
    "wof:name":"Boston Marriott Newton",
    "wof:placetype":"venue"
},
  "geometry": {"coordinates":[-71.257408,42.34569],"type":"Point"}
}