{
  "type": "Feature",
  "properties": {
    "iso:country":"US",
    "sg:address":"57 Morton Pl",
    "sg:city":"East Boston",
    "sg:classifiers":[
        {
            "category":"Real Estate",
            "subcategory":"Real Estate Agent",
            "type":"Services"
        }
    ],
    "sg:phone":"+1 617 567 1600",
    "sg:postcode":"02128",
    "sg:province":"MA",
    "wof:name":"Dorado Real Estate",
    "wof:placetype":"venue"
},
  "geometry": {"coordinates":[-71.037843,42.376185],"type":"Point"}
}