{
  "type": "Feature",
  "properties": {
    "addr:full": "579 Cooper St Agawam MA 01001",
    "addr:housenumber": "579",
    "addr:postcode": "01001",
    "addr:street": "Cooper St",
    "iso:country": "US",
    "sg:address": "579 Cooper St",
    "sg:city": "Agawam",
    "sg:classifiers": [
      {
        "category": "Personal",
        "subcategory": "Beauty Salon",
        "type": "Services"
      }
    ],
    "sg:phone": "+1 413 786 8014",
    "sg:postcode": "01001",
    "sg:province": "MA",
    "wof:name": "Joseph Hair Styles",
    "wof:placetype": "venue"
  },
  "geometry": {"coordinates":[-72.636647,42.07475],"type":"Point"}
}
