{
  "type": "Feature",
  "properties": {
    "iso:country":"US",
    "sg:address":"813 County St",
    "sg:city":"Seekonk",
    "sg:classifiers":[
        {
            "category":"Building & Trades",
            "subcategory":"Construction",
            "type":"Services"
        }
    ],
    "sg:phone":"+1 508 336 2119",
    "sg:postcode":"02771",
    "sg:province":"MA",
    "sg:tags":[
        "contractor"
    ],
    "sg:website":"bairosconstruction.com",
    "wof:name":"Bairos Construction Inc",
    "wof:placetype":"venue"
},
  "geometry": {"coordinates":[-71.304604,41.814499],"type":"Point"}
}