{
  "type": "Feature",
  "properties": {
    "addr:full":"6 Newport Rd Cambridge MA 02140",
    "addr:housenumber":"6",
    "addr:postcode":"02140",
    "addr:street":"Newport Rd",
    "iso:country":"US",
    "sg:address":"6 Newport Rd",
    "sg:city":"Cambridge",
    "sg:classifiers":[
        {
            "category":"Health Services",
            "subcategory":"Health Practitioner",
            "type":"Services"
        }
    ],
    "sg:phone":"+1   ",
    "sg:postcode":"02140",
    "sg:province":"MA",
    "wof:name":"Shalom I Newman",
    "wof:placetype":"venue"
},
  "geometry": {"coordinates":[-71.11923299999999,42.385813],"type":"Point"}
}