{
  "type": "Feature",
  "properties": {
    "addr:full": "20 Pond Park Rd Hingham MA 02043",
    "addr:housenumber": "20",
    "addr:postcode": "02043",
    "addr:street": "Pond Park Rd",
    "iso:country": "US",
    "sg:address": "20 Pond Park Rd",
    "sg:city": "Hingham",
    "sg:classifiers": [
      {
        "category": "Manufacturing",
        "subcategory": "Tools \u0026 Machinery",
        "type": "Manufacturing \u0026 Wholesale Goods"
      }
    ],
    "sg:phone": "+1 781 741 8800",
    "sg:postcode": "02043",
    "sg:province": "MA",
    "sg:tags": [
      "storage"
    ],
    "sg:website": "www.evercel.com",
    "wof:name": "Evercel Inc",
    "wof:placetype": "venue"
  },
  "geometry": {"coordinates":[-70.919337,42.174226],"type":"Point"}
}
