{
  "type": "Feature",
  "properties": {
    "addr:full": "49 Ashland Ave Methuen MA 01844",
    "addr:housenumber": "49",
    "addr:postcode": "01844",
    "addr:street": "Ashland Ave",
    "iso:country": "US",
    "sg:address": "49 Ashland Ave",
    "sg:city": "Methuen",
    "sg:classifiers": [
      {
        "category": "Building \u0026 Trades",
        "subcategory": "Electrical",
        "type": "Services"
      }
    ],
    "sg:phone": "+1 978 689 8356",
    "sg:postcode": "01844",
    "sg:province": "MA",
    "sg:tags": [
      "industrial",
      "electrician",
      "contractors-commercial",
      "electric"
    ],
    "wof:name": "Dragon Electric",
    "wof:placetype": "venue"
  },
  "geometry": {"coordinates":[-71.192518,42.718977],"type":"Point"}
}
