{
  "type": "Feature",
  "properties": {
    "iso:country":"US",
    "sg:address":"49 Ashland Ave",
    "sg:city":"Methuen",
    "sg:classifiers":[
        {
            "category":"Building & Trades",
            "subcategory":"Electrical",
            "type":"Services"
        }
    ],
    "sg:phone":"+1 978 689 8356",
    "sg:postcode":"01844",
    "sg:province":"MA",
    "sg:tags":[
        "industrial",
        "electrician",
        "contractors-commercial",
        "electric"
    ],
    "wof:name":"Dragon Electric",
    "wof:placetype":"venue"
},
  "geometry": {"coordinates":[-71.19251800000001,42.718977],"type":"Point"}
}