{
  "type": "Feature",
  "properties": {
    "addr:full": "1792 Pleasant St Fall River MA 02723",
    "addr:housenumber": "1792",
    "addr:postcode": "02723",
    "addr:street": "Pleasant St",
    "iso:country": "US",
    "sg:address": "1792 Pleasant St",
    "sg:city": "Fall River",
    "sg:classifiers": [
      {
        "category": "Professional",
        "subcategory": "Lawyer \u0026 Legal Services",
        "type": "Services"
      }
    ],
    "sg:phone": "+1 508 672 1200",
    "sg:postcode": "02723",
    "sg:province": "MA",
    "sg:tags": [
      "attorney"
    ],
    "wof:name": "Wanda Brito Law Office",
    "wof:placetype": "venue"
  },
  "geometry": {"coordinates":[-71.128549,41.686106],"type":"Point"}
}
