{
  "type": "Feature",
  "properties": {
    "iso:country":"US",
    "sg:address":"1792 Pleasant St",
    "sg:city":"Fall River",
    "sg:classifiers":[
        {
            "category":"Professional",
            "subcategory":"Lawyer & Legal Services",
            "type":"Services"
        }
    ],
    "sg:phone":"+1 508 672 1200",
    "sg:postcode":"02723",
    "sg:province":"MA",
    "sg:tags":[
        "attorney"
    ],
    "wof:name":"Wanda Brito Law Office",
    "wof:placetype":"venue"
},
  "geometry": {"coordinates":[-71.12854900000001,41.686106],"type":"Point"}
}