{
  "type": "Feature",
  "properties": {
    "iso:country":"US",
    "sg:address":"74 Race Point Rd",
    "sg:city":"Provincetown",
    "sg:classifiers":[
        {
            "category":"Autos & Motor Vehicles",
            "subcategory":"Boat Sales",
            "type":"Retail Goods"
        }
    ],
    "sg:phone":"+1 508 487 0054",
    "sg:postcode":"02657",
    "sg:province":"MA",
    "sg:tags":[
        "equipment",
        "supply"
    ],
    "wof:name":"Screaming Eagle Boatworks",
    "wof:placetype":"venue"
},
  "geometry": {"coordinates":[-70.21699,42.077371],"type":"Point"}
}