{
  "type": "Feature",
  "properties": {
    "addr:full":"3850 Mystic Valley Pkwy Medford MA 02155",
    "addr:housenumber":"3850",
    "addr:postcode":"02155",
    "addr:street":"Mystic Valley Pkwy",
    "iso:country":"US",
    "sg:address":"3850 Mystic Valley Pkwy",
    "sg:city":"Medford",
    "sg:classifiers":[
        {
            "category":"Shopping",
            "subcategory":"Music",
            "type":"Retail Goods"
        }
    ],
    "sg:phone":"+1 781 396 5550",
    "sg:postcode":"02155",
    "sg:province":"MA",
    "sg:tags":[
        "compact",
        "record",
        "disc",
        "tape"
    ],
    "wof:name":"Fye",
    "wof:placetype":"venue"
},
  "geometry": {"coordinates":[-71.094967,42.4058],"type":"Point"}
}