{
  "type": "Feature",
  "properties": {
    "iso:country":"US",
    "sg:address":"1220 Washington St",
    "sg:city":"West Newton",
    "sg:classifiers":[
        {
            "category":"Wholesale",
            "subcategory":"Groceries",
            "type":"Manufacturing & Wholesale Goods"
        }
    ],
    "sg:phone":"+1 617 969 5400",
    "sg:postcode":"02465",
    "sg:province":"MA",
    "sg:tags":[
        "food",
        "product"
    ],
    "sg:website":"www.dcontinuum.com",
    "wof:name":"Design Continuum Inc",
    "wof:placetype":"venue"
},
  "geometry": {"coordinates":[-71.223816,42.349151],"type":"Point"}
}