{
  "type": "Feature",
  "properties": {
    "iso:country":"US",
    "sg:address":"38 Essex Rd",
    "sg:city":"Ipswich",
    "sg:classifiers":[
        {
            "category":"Shopping",
            "subcategory":"Bicycles & Sporting Goods",
            "type":"Retail Goods"
        }
    ],
    "sg:phone":"+1 978 356 1180",
    "sg:postcode":"01938",
    "sg:province":"MA",
    "sg:tags":[
        "horse",
        "furnishing"
    ],
    "wof:name":"Equestrian Crossing",
    "wof:placetype":"venue"
},
  "geometry": {"coordinates":[-70.832438,42.663463],"type":"Point"}
}