{
  "type": "Feature",
  "properties": {
    "addr:full": "1053 Belmont St Watertown MA 02472",
    "addr:housenumber": "1053",
    "addr:postcode": "02472",
    "addr:street": "Belmont St",
    "iso:country": "US",
    "ovtr:label": "Alden Lock \u0026 Security, Inc., 1053 Belmont St Watertown MA US",
    "ovtr:similarity": 2.3813529014587402,
    "sg:address": "1053 Belmont St",
    "sg:city": "Watertown",
    "sg:classifiers": [
      {
        "category": "Retail",
        "subcategory": "Repair Shop",
        "type": "Services"
      }
    ],
    "sg:phone": "+1 617 484 2239",
    "sg:postcode": "02472",
    "sg:province": "MA",
    "sg:tags": [
      "lock",
      "locksmith"
    ],
    "wof:name": "Alden Lock \u0026 Security Inc",
    "wof:placetype": "venue"
  },
  "geometry": {"coordinates":[-71.196532,42.382272],"type":"Point"}
}
