{
  "type": "Feature",
  "properties": {
    "iso:country":"US",
    "sg:address":"17 McKinnon Ave",
    "sg:city":"Milton",
    "sg:classifiers":[
        {
            "category":"Building & Trades",
            "subcategory":"Construction",
            "type":"Services"
        }
    ],
    "sg:phone":"+1 617 698 4698",
    "sg:postcode":"02186",
    "sg:province":"MA",
    "sg:tags":[
        "roofing",
        "contractor"
    ],
    "wof:name":"George H Richard & Son Roofing",
    "wof:placetype":"venue"
},
  "geometry": {"coordinates":[-71.05323799999999,42.253396],"type":"Point"}
}