{
  "type": "Feature",
  "properties": {
    "iso:country":"US",
    "sg:address":"1629 Lakeview Ave",
    "sg:city":"Dracut",
    "sg:classifiers":[
        {
            "category":"Bars & Pubs",
            "type":"Food & Drink"
        }
    ],
    "sg:phone":"+1 978 957 0999",
    "sg:postcode":"01826",
    "sg:province":"MA",
    "sg:tags":[
        "lounge",
        "cocktail"
    ],
    "wof:name":"Avenue Pub",
    "wof:placetype":"venue"
},
  "geometry": {"coordinates":[-71.337977,42.677552],"type":"Point"}
}