{
  "type": "Feature",
  "properties": {
    "iso:country":"US",
    "sg:address":"25 Industrial Way Ste 4",
    "sg:city":"Wilmington",
    "sg:classifiers":[
        {
            "category":"Transit Center",
            "subcategory":"Freight",
            "type":"Transportation"
        },
        {
            "category":"Freight",
            "type":"Transportation"
        },
        {
            "category":"Retail",
            "subcategory":"Storage",
            "type":"Services"
        }
    ],
    "sg:phone":"+1 978 988 9398",
    "sg:postcode":"01887",
    "sg:province":"MA",
    "sg:tags":[
        "self",
        "local",
        "trucking-motor",
        "trucking"
    ],
    "sg:website":"http://www.crystalwarehouse.com",
    "wof:name":"Crystal Motor Express",
    "wof:placetype":"venue"
},
  "geometry": {"coordinates":[-71.14536099999999,42.527142],"type":"Point"}
}