{
  "type": "Feature",
  "properties": {
    "addr:full": "5 Commonwealth Rd Natick MA 01778",
    "addr:housenumber": "5",
    "addr:postcode": "01778",
    "addr:street": "Commonwealth Rd",
    "iso:country": "US",
    "sg:address": "5 Commonwealth Rd",
    "sg:city": "Natick",
    "sg:classifiers": [
      {
        "category": "Professional",
        "subcategory": "Accounting \u0026 Tax Preparation",
        "type": "Services"
      }
    ],
    "sg:phone": "+1 508 651 1313",
    "sg:postcode": "01778",
    "sg:province": "MA",
    "sg:tags": [
      "accountant"
    ],
    "sg:website": "www.cpatax.com",
    "wof:name": "Zack \u0026 Co",
    "wof:placetype": "venue"
  },
  "geometry": {"coordinates":[-71.380473,42.308921],"type":"Point"}
}
