{
  "type": "Feature",
  "properties": {
    "iso:country":"US",
    "sg:address":"157 Federal St",
    "sg:city":"Salem",
    "sg:classifiers":[
        {
            "category":"Professional",
            "subcategory":"Management & Consulting",
            "type":"Services"
        }
    ],
    "sg:phone":"+1   ",
    "sg:postcode":"01970",
    "sg:province":"MA",
    "wof:name":"Scarlet Letters",
    "wof:placetype":"venue"
},
  "geometry": {"coordinates":[-70.90498100000001,42.52016],"type":"Point"}
}