{
  "type": "Feature",
  "properties": {
    "addr:full": "157 Federal St Salem MA 01970",
    "addr:housenumber": "157",
    "addr:postcode": "01970",
    "addr:street": "Federal St",
    "iso:country": "US",
    "sg:address": "157 Federal St",
    "sg:city": "Salem",
    "sg:classifiers": [
      {
        "category": "Professional",
        "subcategory": "Management \u0026 Consulting",
        "type": "Services"
      }
    ],
    "sg:phone": "+1   ",
    "sg:postcode": "01970",
    "sg:province": "MA",
    "wof:name": "Scarlet Letters",
    "wof:placetype": "venue"
  },
  "geometry": {"coordinates":[-70.904981,42.52016],"type":"Point"}
}
