{
  "type": "Feature",
  "properties": {
    "addr:full": "118 Great Rd Stow MA 01775",
    "addr:housenumber": "118",
    "addr:postcode": "01775",
    "addr:street": "Great Rd",
    "iso:country": "US",
    "sg:address": "118 Great Rd",
    "sg:city": "Stow",
    "sg:classifiers": [
      {
        "category": "Professional",
        "type": "Services"
      }
    ],
    "sg:phone": "+1 978 897 3190",
    "sg:postcode": "01775",
    "sg:province": "MA",
    "sg:tags": [
      "establishment"
    ],
    "wof:name": "H G Assoc",
    "wof:placetype": "venue"
  },
  "geometry": {"coordinates":[-71.486289,42.433277],"type":"Point"}
}
