{
  "type": "Feature",
  "properties": {
    "addr:full": "44 Foskett St Somerville MA 02144",
    "addr:housenumber": "44",
    "addr:postcode": "02144",
    "addr:street": "Foskett St",
    "iso:country": "US",
    "sg:address": "44 Foskett St",
    "sg:city": "Somerville",
    "sg:classifiers": [
      {
        "category": "Professional",
        "type": "Services"
      }
    ],
    "sg:phone": "+1 617 666 0460",
    "sg:postcode": "02144",
    "sg:province": "MA",
    "sg:tags": [
      "establishment"
    ],
    "wof:name": "Center For The Study Of Public",
    "wof:placetype": "venue"
  },
  "geometry": {"coordinates":[-71.117239,42.397647],"type":"Point"}
}
