{
  "type": "Feature",
  "properties": {
    "iso:country":"US",
    "sg:address":"56 Housatonic St",
    "sg:city":"Lenox",
    "sg:classifiers":[
        {
            "category":"Professional",
            "subcategory":"Computer Services",
            "type":"Services"
        }
    ],
    "sg:phone":"+1 413 637 1484",
    "sg:postcode":"01240",
    "sg:province":"MA",
    "sg:tags":[
        "consultant",
        "designer"
    ],
    "wof:name":"Home Base Technologies",
    "wof:placetype":"venue"
},
  "geometry": {"coordinates":[-73.281881,42.357423],"type":"Point"}
}