{
  "type": "Feature",
  "properties": {
    "iso:country":"US",
    "sg:address":"85 Coggeshall St",
    "sg:city":"New Bedford",
    "sg:classifiers":[
        {
            "category":"Manufacturing",
            "subcategory":"Printing",
            "type":"Manufacturing & Wholesale Goods"
        }
    ],
    "sg:phone":"+1 508 979 5577",
    "sg:postcode":"02746",
    "sg:province":"MA",
    "sg:tags":[
        "screen"
    ],
    "wof:name":"Imperial Screen Printing",
    "wof:placetype":"venue"
},
  "geometry": {"coordinates":[-70.91927699999999,41.656165],"type":"Point"}
}