{
  "type": "Feature",
  "properties": {
    "iso:country":"US",
    "sg:address":"86 Pond Rd",
    "sg:city":"Rowe",
    "sg:classifiers":[
        {
            "category":"Education",
            "subcategory":"School",
            "type":"Public Place"
        }
    ],
    "sg:phone":"+1 413 339 8381",
    "sg:postcode":"01367",
    "sg:province":"MA",
    "wof:name":"Rowe Elementary School",
    "wof:placetype":"venue"
},
  "geometry": {"coordinates":[-72.88903500000001,42.702951],"type":"Point"}
}