{
  "type": "Feature",
  "properties": {
    "addr:full": "86 Pond Rd Rowe MA 01367",
    "addr:housenumber": "86",
    "addr:postcode": "01367",
    "addr:street": "Pond Rd",
    "iso:country": "US",
    "ovtr:label": "Rowe Elementary School, 86 Pond Rd Rowe MA US",
    "ovtr:similarity": 3.145756959915161,
    "sg:address": "86 Pond Rd",
    "sg:city": "Rowe",
    "sg:classifiers": [
      {
        "category": "Education",
        "subcategory": "School",
        "type": "Public Place"
      }
    ],
    "sg:phone": "+1 413 339 8381",
    "sg:postcode": "01367",
    "sg:province": "MA",
    "wof:name": "Rowe Elementary School",
    "wof:placetype": "venue"
  },
  "geometry": {"coordinates":[-72.889035,42.702951],"type":"Point"}
}
