{
  "type": "Feature",
  "properties": {
    "addr:full": "850 Washington St East Weymouth MA 02189",
    "addr:housenumber": "850",
    "addr:postcode": "02189",
    "addr:street": "Washington St",
    "iso:country": "US",
    "sg:address": "850 Washington St",
    "sg:city": "East Weymouth",
    "sg:classifiers": [
      {
        "category": "Restaurant",
        "type": "Food \u0026 Drink"
      }
    ],
    "sg:menulink": "http://www.allmenus.com/ma/weymouth/80961-papa-johns-pizza/menu/",
    "sg:phone": "+1 781 337 3131",
    "sg:postcode": "02189",
    "sg:province": "MA",
    "sg:tags": [
      "american",
      "pizza"
    ],
    "wof:name": "Papa John's Pizza",
    "wof:placetype": "venue"
  },
  "geometry": {"coordinates":[-70.942506,42.200635],"type":"Point"}
}
