{
  "type": "Feature",
  "properties": {
    "iso:country":"US",
    "sg:address":"850 Washington St",
    "sg:city":"East Weymouth",
    "sg:classifiers":[
        {
            "category":"Restaurant",
            "type":"Food & Drink"
        }
    ],
    "sg:menulink":"http://www.allmenus.com/ma/weymouth/80961-papa-johns-pizza/menu/",
    "sg:phone":"+1 781 337 3131",
    "sg:postcode":"02189",
    "sg:province":"MA",
    "sg:tags":[
        "american",
        "pizza"
    ],
    "wof:name":"Papa John's Pizza",
    "wof:placetype":"venue"
},
  "geometry": {"coordinates":[-70.94250599999999,42.200635],"type":"Point"}
}