{
  "type": "Feature",
  "properties": {
    "addr:full": "600 Old W Warren Rd West Warren MA 01585",
    "addr:housenumber": "600",
    "addr:postcode": "01585",
    "addr:street": "Old W Warren Rd",
    "iso:country": "US",
    "sg:address": "600 Old W Warren Rd",
    "sg:city": "West Warren",
    "sg:classifiers": [
      {
        "category": "Building \u0026 Trades",
        "subcategory": "Construction",
        "type": "Services"
      }
    ],
    "sg:phone": "+1 413 436 5674",
    "sg:postcode": "01585",
    "sg:province": "MA",
    "sg:tags": [
      "general",
      "contractor"
    ],
    "wof:name": "R J Fijol Inc",
    "wof:placetype": "venue"
  },
  "geometry": {"coordinates":[-72.17361,42.235408],"type":"Point"}
}
