{
  "type": "Feature",
  "properties": {
    "iso:country":"US",
    "sg:address":"24 Hale St",
    "sg:city":"Beverly",
    "sg:classifiers":[
        {
            "category":"Health Services",
            "subcategory":"Doctor",
            "type":"Services"
        }
    ],
    "sg:phone":"+1 978 927 2670",
    "sg:postcode":"01915",
    "sg:province":"MA",
    "sg:tags":[
        "dentist"
    ],
    "wof:name":"Robert W Mattson DDS",
    "wof:placetype":"venue"
},
  "geometry": {"coordinates":[-70.87597700000001,42.548602],"type":"Point"}
}