{
  "type": "Feature",
  "properties": {
    "addr:full": "100 Apremont Way Westfield MA 01085",
    "addr:housenumber": "100",
    "addr:postcode": "01085",
    "addr:street": "Apremont Way",
    "iso:country": "US",
    "sg:address": "100 Apremont Way",
    "sg:city": "Westfield",
    "sg:classifiers": [
      {
        "category": "Home \u0026 Garden",
        "subcategory": "Building Materials",
        "type": "Retail Goods"
      }
    ],
    "sg:phone": "+1 413 562 3861",
    "sg:postcode": "01085",
    "sg:province": "MA",
    "sg:tags": [
      "truss"
    ],
    "wof:name": "Western Mass Truss Co",
    "wof:placetype": "venue"
  },
  "geometry": {"coordinates":[-72.724203,42.154883],"type":"Point"}
}
