{
  "type": "Feature",
  "properties": {
    "iso:country":"US",
    "sg:address":"50 Mooney St",
    "sg:city":"Cambridge",
    "sg:classifiers":[
        {
            "category":"Building & Trades",
            "subcategory":"Construction",
            "type":"Services"
        }
    ],
    "sg:phone":"+1 617 354 1839",
    "sg:postcode":"02138",
    "sg:province":"MA",
    "sg:tags":[
        "excavating",
        "contractor"
    ],
    "wof:name":"C J Mabardy",
    "wof:placetype":"venue"
},
  "geometry": {"coordinates":[-71.15298300000001,42.394672],"type":"Point"}
}