{
  "type": "Feature",
  "properties": {
    "addr:full":"228 King St Northampton MA 01060",
    "addr:housenumber":"228",
    "addr:postcode":"01060",
    "addr:street":"King St",
    "iso:country":"US",
    "sg:address":"228 King St",
    "sg:city":"Northampton",
    "sg:classifiers":[
        {
            "category":"Banks & Credit Unions",
            "subcategory":"Bank",
            "type":"Services"
        },
        {
            "category":"Banks & Credit Unions",
            "subcategory":"Financial Services",
            "type":"Services"
        }
    ],
    "sg:phone":"+1 413 584 7928",
    "sg:postcode":"01060",
    "sg:province":"MA",
    "sg:tags":[
        "commercial",
        "loan",
        "saving"
    ],
    "sg:website":"http://www.citizensbank.com",
    "wof:name":"Citizens Bank",
    "wof:placetype":"venue"
},
  "geometry": {"coordinates":[-72.633522,42.3281],"type":"Point"}
}