{
  "type": "Feature",
  "properties": {
    "addr:full": "67 High St Danvers MA 01923",
    "addr:housenumber": "67",
    "addr:postcode": "01923",
    "addr:street": "High St",
    "iso:country": "US",
    "sg:address": "67 High St",
    "sg:city": "Danvers",
    "sg:classifiers": [
      {
        "category": "Manufacturing",
        "subcategory": "Printing",
        "type": "Manufacturing \u0026 Wholesale Goods"
      }
    ],
    "sg:phone": "+1 978 774 6704",
    "sg:postcode": "01923",
    "sg:province": "MA",
    "sg:tags": [
      "printer"
    ],
    "wof:name": "PIP Printing",
    "wof:placetype": "venue"
  },
  "geometry": {"coordinates":[-70.932628,42.561977],"type":"Point"}
}
