{
  "type": "Feature",
  "properties": {
    "iso:country":"US",
    "sg:address":"1130 Main St",
    "sg:city":"Tewksbury",
    "sg:classifiers":[
        {
            "category":"Real Estate",
            "subcategory":"Real Estate Agent",
            "type":"Services"
        }
    ],
    "sg:phone":"+1 978 851 3731",
    "sg:postcode":"01876",
    "sg:province":"MA",
    "sg:website":"www.nemoves.com",
    "wof:name":"Coldwell Banker",
    "wof:placetype":"venue"
},
  "geometry": {"coordinates":[-71.23038,42.609912],"type":"Point"}
}