{
  "type": "Feature",
  "properties": {
    "iso:country":"US",
    "sg:address":"147 Swansea Mall Dr",
    "sg:city":"Swansea",
    "sg:classifiers":[
        {
            "category":"Shopping",
            "subcategory":"Hobbies, Toys, & Games",
            "type":"Retail Goods"
        }
    ],
    "sg:phone":"+1 508 678 8688",
    "sg:postcode":"02777",
    "sg:province":"MA",
    "sg:tags":[
        "model",
        "supply"
    ],
    "wof:name":"Hobby Tower",
    "wof:placetype":"venue"
},
  "geometry": {"coordinates":[-71.21449200000001,41.754],"type":"Point"}
}