{
  "type": "Feature",
  "properties": {
    "addr:full": "33 Mount Pleasant St Westborough MA 01581",
    "addr:housenumber": "33",
    "addr:postcode": "01581",
    "addr:street": "Mount Pleasant St",
    "iso:country": "US",
    "sg:address": "33 Mount Pleasant St",
    "sg:city": "Westborough",
    "sg:classifiers": [
      {
        "category": "Professional",
        "subcategory": "Management \u0026 Consulting",
        "type": "Services"
      }
    ],
    "sg:phone": "+1 508 870 2226",
    "sg:postcode": "01581",
    "sg:province": "MA",
    "sg:tags": [
      "consultant",
      "business"
    ],
    "wof:name": "Visionaries Partnership Inc",
    "wof:placetype": "venue"
  },
  "geometry": {"coordinates":[-71.609276,42.25837],"type":"Point"}
}
