{
  "type": "Feature",
  "properties": {
    "iso:country":"US",
    "sg:address":"23 Bourque St",
    "sg:city":"Lawrence",
    "sg:classifiers":[
        {
            "category":"Building & Trades",
            "subcategory":"Electrical",
            "type":"Services"
        }
    ],
    "sg:phone":"+1 978 975 8532",
    "sg:postcode":"01843",
    "sg:province":"MA",
    "sg:tags":[
        "industrial",
        "electrician",
        "contractors-commercial",
        "electric"
    ],
    "wof:name":"Brimac Electrical Services",
    "wof:placetype":"venue"
},
  "geometry": {"coordinates":[-71.174111,42.685059],"type":"Point"}
}