{
  "type": "Feature",
  "properties": {
    "iso:country":"US",
    "sg:address":"17 Hull St",
    "sg:city":"Beverly",
    "sg:classifiers":[
        {
            "category":"Education",
            "subcategory":"School",
            "type":"Public Place"
        }
    ],
    "sg:phone":"+1 978 921 6120",
    "sg:postcode":"01915",
    "sg:province":"MA",
    "wof:name":"Centerville School",
    "wof:placetype":"venue"
},
  "geometry": {"coordinates":[-70.84376899999999,42.579796],"type":"Point"}
}