{
  "type": "Feature",
  "properties": {
    "addr:full": "17 Hull St Beverly MA 01915",
    "addr:housenumber": "17",
    "addr:postcode": "01915",
    "addr:street": "Hull St",
    "iso:country": "US",
    "ovtr:label": "Centerville School, 17 Hull St Beverly MA US",
    "ovtr:similarity": 3.138612985610962,
    "sg:address": "17 Hull St",
    "sg:city": "Beverly",
    "sg:classifiers": [
      {
        "category": "Education",
        "subcategory": "School",
        "type": "Public Place"
      }
    ],
    "sg:phone": "+1 978 921 6120",
    "sg:postcode": "01915",
    "sg:province": "MA",
    "wof:name": "Centerville School",
    "wof:placetype": "venue"
  },
  "geometry": {"coordinates":[-70.843769,42.579796],"type":"Point"}
}
