{
  "type": "Feature",
  "properties": {
    "iso:country":"US",
    "sg:address":"1756 Massachusetts Ave",
    "sg:city":"Cambridge",
    "sg:classifiers":[
        {
            "category":"Retail",
            "subcategory":"Repair Shop",
            "type":"Services"
        }
    ],
    "sg:phone":"+1 781 648 0096",
    "sg:postcode":"02140",
    "sg:province":"MA",
    "sg:tags":[
        "repairing",
        "piano",
        "refinishing"
    ],
    "wof:name":"Brownfield Piano Co",
    "wof:placetype":"venue"
},
  "geometry": {"coordinates":[-71.119496,42.385178],"type":"Point"}
}