{
  "type": "Feature",
  "properties": {
    "addr:full": "185 Massachusetts Ave Arlington MA 02474",
    "addr:housenumber": "185",
    "addr:postcode": "02474",
    "addr:street": "Massachusetts Ave",
    "iso:country": "US",
    "sg:address": "185 Massachusetts Ave",
    "sg:city": "Arlington",
    "sg:classifiers": [
      {
        "category": "Arts \u0026 Performance",
        "subcategory": "Art Gallery",
        "type": "Entertainment"
      },
      {
        "category": "Home \u0026 Garden",
        "subcategory": "Home Furnishings",
        "type": "Retail Goods"
      },
      {
        "category": "Home \u0026 Garden",
        "subcategory": "Furniture",
        "type": "Retail Goods"
      }
    ],
    "sg:phone": "+1 781 646 3009",
    "sg:postcode": "02474",
    "sg:province": "MA",
    "sg:tags": [
      "decor",
      "store"
    ],
    "sg:website": "www.talltreeguild.com",
    "wof:name": "Tall Tree Guild",
    "wof:placetype": "venue"
  },
  "geometry": {"coordinates":[-71.142042,42.405798],"type":"Point"}
}
