{
  "type": "Feature",
  "properties": {
    "iso:country":"US",
    "sg:address":"18 Water St",
    "sg:city":"Orange",
    "sg:classifiers":[
        {
            "category":"Government",
            "subcategory":"Fire Station",
            "type":"Public Place"
        }
    ],
    "sg:phone":"+1 978 544 3145",
    "sg:postcode":"01301",
    "sg:province":"MA",
    "sg:tags":[
        "department"
    ],
    "sg:website":"www.orangefiredepartment.org",
    "wof:name":"Orange Fire Dept",
    "wof:placetype":"venue"
},
  "geometry": {"coordinates":[-72.601479,42.581875],"type":"Point"}
}