{
  "type": "Feature",
  "properties": {
    "addr:full": "115 Pine St South Easton MA 02375",
    "addr:housenumber": "115",
    "addr:postcode": "02375",
    "addr:street": "Pine St",
    "iso:country": "US",
    "sg:address": "115 Pine St",
    "sg:city": "South Easton",
    "sg:classifiers": [
      {
        "category": "Retail",
        "subcategory": "Auto Repair",
        "type": "Services"
      }
    ],
    "sg:phone": "+1 508 230 5787",
    "sg:postcode": "02375",
    "sg:province": "MA",
    "sg:tags": [
      "lettering",
      "truck"
    ],
    "wof:name": "Artistic Design",
    "wof:placetype": "venue"
  },
  "geometry": {"coordinates":[-71.066819,42.029425],"type":"Point"}
}
