{
  "type": "Feature",
  "properties": {
    "addr:full":"961 Main St Warren MA 01083",
    "addr:housenumber":"961",
    "addr:postcode":"01083",
    "addr:street":"Main St",
    "iso:country":"US",
    "sg:address":"961 Main St",
    "sg:city":"Warren",
    "sg:classifiers":[
        {
            "category":"Autos & Motor Vehicles",
            "subcategory":"Fuel & Gas Station",
            "type":"Retail Goods"
        }
    ],
    "sg:phone":"+1 413 436 5665",
    "sg:postcode":"01083",
    "sg:province":"MA",
    "sg:tags":[
        "oil"
    ],
    "wof:name":"Bill's CITGO",
    "wof:placetype":"venue"
},
  "geometry": {"coordinates":[-72.194889,42.213222],"type":"Point"}
}