{
  "type": "Feature",
  "properties": {
    "iso:country":"US",
    "sg:address":"12 Silver St",
    "sg:city":"Great Barrington",
    "sg:classifiers":[
        {
            "category":"Home & Garden",
            "subcategory":"Garden Supply",
            "type":"Retail Goods"
        }
    ],
    "sg:phone":"+1 413 644 0010",
    "sg:postcode":"01230",
    "sg:province":"MA",
    "sg:tags":[
        "nurseryman"
    ],
    "wof:name":"Monrovia",
    "wof:placetype":"venue"
},
  "geometry": {"coordinates":[-73.36971,42.184036],"type":"Point"}
}