{
  "type": "Feature",
  "properties": {
    "iso:country":"US",
    "sg:address":"544 Main St",
    "sg:city":"Medford",
    "sg:classifiers":[
        {
            "category":"Building & Trades",
            "subcategory":"Construction",
            "type":"Services"
        }
    ],
    "sg:phone":"+1   ",
    "sg:postcode":"02155",
    "sg:province":"MA",
    "sg:tags":[
        "carpentry",
        "contractor"
    ],
    "wof:name":"Peter Paul Restorations",
    "wof:placetype":"venue"
},
  "geometry": {"coordinates":[-71.10302900000001,42.399615],"type":"Point"}
}