{
  "type": "Feature",
  "properties": {
    "addr:full": "544 Main St Medford MA 02155",
    "addr:housenumber": "544",
    "addr:postcode": "02155",
    "addr:street": "Main St",
    "iso:country": "US",
    "sg:address": "544 Main St",
    "sg:city": "Medford",
    "sg:classifiers": [
      {
        "category": "Building \u0026 Trades",
        "subcategory": "Construction",
        "type": "Services"
      }
    ],
    "sg:phone": "+1   ",
    "sg:postcode": "02155",
    "sg:province": "MA",
    "sg:tags": [
      "carpentry",
      "contractor"
    ],
    "wof:name": "Peter Paul Restorations",
    "wof:placetype": "venue"
  },
  "geometry": {"coordinates":[-71.103029,42.399615],"type":"Point"}
}
