{
  "type": "Feature",
  "properties": {
    "addr:full": "67 May St Needham MA 02492",
    "addr:housenumber": "67",
    "addr:postcode": "02492",
    "addr:street": "May St",
    "iso:country": "US",
    "sg:address": "67 May St",
    "sg:city": "Needham",
    "sg:classifiers": [
      {
        "category": "Wholesale",
        "subcategory": "Non-durable Goods",
        "type": "Manufacturing \u0026 Wholesale Goods"
      }
    ],
    "sg:phone": "+1 781 449 6059",
    "sg:postcode": "02492",
    "sg:province": "MA",
    "sg:tags": [
      "merchandise-wholesale"
    ],
    "wof:name": "Reagan Trading Co",
    "wof:placetype": "venue"
  },
  "geometry": {"coordinates":[-71.233258,42.282829],"type":"Point"}
}
