{
  "type": "Feature",
  "properties": {
    "iso:country":"US",
    "sg:address":"725 Belmont St",
    "sg:city":"Brockton",
    "sg:classifiers":[
        {
            "category":"Shopping",
            "subcategory":"Jewelry",
            "type":"Retail Goods"
        }
    ],
    "sg:phone":"+1 508 586 1988",
    "sg:postcode":"02301",
    "sg:province":"MA",
    "sg:tags":[
        "jeweler"
    ],
    "wof:name":"Grady Jewelers Inc",
    "wof:placetype":"venue"
},
  "geometry": {"coordinates":[-71.047588,42.069506],"type":"Point"}
}