{
  "type": "Feature",
  "properties": {
    "addr:full":"215 Salem St Woburn MA 01801",
    "addr:housenumber":"215",
    "addr:postcode":"01801",
    "addr:street":"Salem St",
    "iso:country":"US",
    "sg:address":"215 Salem St",
    "sg:city":"Woburn",
    "sg:classifiers":[
        {
            "category":"Banks & Credit Unions",
            "subcategory":"Bank",
            "type":"Services"
        }
    ],
    "sg:phone":"+1 781 503 0292",
    "sg:postcode":"01801",
    "sg:province":"MA",
    "sg:tags":[
        "other",
        "plan",
        "card"
    ],
    "wof:name":"Nationwide Payment Solutions",
    "wof:placetype":"venue"
},
  "geometry": {"coordinates":[-71.13521799999999,42.487921],"type":"Point"}
}