{
  "type": "Feature",
  "properties": {
    "addr:full": "1740 Massachusetts Ave Boxborough MA 01719",
    "addr:housenumber": "1740",
    "addr:postcode": "01719",
    "addr:street": "Massachusetts Ave",
    "iso:country": "US",
    "sg:address": "1740 Massachusetts Ave",
    "sg:city": "Boxborough",
    "sg:classifiers": [
      {
        "category": "Professional",
        "subcategory": "Secretarial Services",
        "type": "Services"
      }
    ],
    "sg:phone": "+1 978 263 9914",
    "sg:postcode": "01719",
    "sg:province": "MA",
    "sg:tags": [
      "resume"
    ],
    "wof:name": "Total Package",
    "wof:placetype": "venue"
  },
  "geometry": {"coordinates":[-71.550599,42.489034],"type":"Point"}
}
