{
  "type": "Feature",
  "properties": {
    "iso:country":"US",
    "sg:address":"250 Boylston St",
    "sg:city":"Boston",
    "sg:classifiers":[
        {
            "category":"Professional",
            "subcategory":"Management & Consulting",
            "type":"Services"
        }
    ],
    "sg:phone":"+1   ",
    "sg:postcode":"02116",
    "sg:province":"MA",
    "wof:name":"Derby Management Consultants",
    "wof:placetype":"venue"
},
  "geometry": {"coordinates":[-71.070487,42.35181],"type":"Point"}
}