{
  "type": "Feature",
  "properties": {
    "addr:full":"73 South St Hingham MA 02043",
    "addr:housenumber":"73",
    "addr:postcode":"02043",
    "addr:street":"South St",
    "iso:country":"US",
    "sg:address":"73 South St",
    "sg:city":"Hingham",
    "sg:classifiers":[
        {
            "category":"Manufacturing",
            "subcategory":"Printing",
            "type":"Manufacturing & Wholesale Goods"
        }
    ],
    "sg:phone":"+1 781 749 0031",
    "sg:postcode":"02043",
    "sg:province":"MA",
    "sg:tags":[
        "newspaper"
    ],
    "sg:website":"www.townonline.com",
    "wof:name":"Hingham Journal & Mariner",
    "wof:placetype":"venue"
},
  "geometry": {"coordinates":[-70.89021099999999,42.241799],"type":"Point"}
}