{
  "type": "Feature",
  "properties": {
    "addr:full": "9 Memorial Pkwy Randolph MA 02368",
    "addr:housenumber": "9",
    "addr:postcode": "02368",
    "addr:street": "Memorial Pkwy",
    "iso:country": "US",
    "sg:address": "9 Memorial Pkwy",
    "sg:city": "Randolph",
    "sg:classifiers": [
      {
        "category": "Professional",
        "subcategory": "Lawyer \u0026 Legal Services",
        "type": "Services"
      }
    ],
    "sg:phone": "+1 781 986 6025",
    "sg:postcode": "02368",
    "sg:province": "MA",
    "wof:name": "Kaufman Paul Atty",
    "wof:placetype": "venue"
  },
  "geometry": {"coordinates":[-71.042099,42.1632],"type":"Point"}
}
