{
  "type": "Feature",
  "properties": {
    "addr:full": "77 Edinboro St Marlborough MA 01752",
    "addr:housenumber": "77",
    "addr:postcode": "01752",
    "addr:street": "Edinboro St",
    "iso:country": "US",
    "ovtr:label": "Edinboro Flower Shop, 77 Edinboro St Marlborough MA US",
    "ovtr:similarity": 2.8069119453430176,
    "sg:address": "77 Edinboro St",
    "sg:city": "Marlborough",
    "sg:classifiers": [
      {
        "category": "Shopping",
        "subcategory": "Florist",
        "type": "Retail Goods"
      }
    ],
    "sg:phone": "+1 508 485 5852",
    "sg:postcode": "01752",
    "sg:province": "MA",
    "wof:name": "Edinboro Flower Shop",
    "wof:placetype": "venue"
  },
  "geometry": {"coordinates":[-71.539418,42.341446],"type":"Point"}
}
