{
  "type": "Feature",
  "properties": {
    "iso:country":"US",
    "sg:address":"77 Edinboro St",
    "sg:city":"Marlborough",
    "sg:classifiers":[
        {
            "category":"Shopping",
            "subcategory":"Florist",
            "type":"Retail Goods"
        }
    ],
    "sg:phone":"+1 508 485 5852",
    "sg:postcode":"01752",
    "sg:province":"MA",
    "wof:name":"Edinboro Flower Shop",
    "wof:placetype":"venue"
},
  "geometry": {"coordinates":[-71.539418,42.341446],"type":"Point"}
}