{
  "type": "Feature",
  "properties": {
    "iso:country":"US",
    "sg:address":"5 Wilson Rd",
    "sg:city":"Bedford",
    "sg:classifiers":[
        {
            "category":"Wholesale",
            "subcategory":"Computers",
            "type":"Manufacturing & Wholesale Goods"
        }
    ],
    "sg:phone":"+1   ",
    "sg:postcode":"01730",
    "sg:province":"MA",
    "wof:name":"Pelorus Equipment Inc",
    "wof:placetype":"venue"
},
  "geometry": {"coordinates":[-71.251739,42.494317],"type":"Point"}
}