{
  "type": "Feature",
  "properties": {
    "addr:full": "5 Wilson Rd Bedford MA 01730",
    "addr:housenumber": "5",
    "addr:postcode": "01730",
    "addr:street": "Wilson Rd",
    "iso:country": "US",
    "sg:address": "5 Wilson Rd",
    "sg:city": "Bedford",
    "sg:classifiers": [
      {
        "category": "Wholesale",
        "subcategory": "Computers",
        "type": "Manufacturing \u0026 Wholesale Goods"
      }
    ],
    "sg:phone": "+1   ",
    "sg:postcode": "01730",
    "sg:province": "MA",
    "wof:name": "Pelorus Equipment Inc",
    "wof:placetype": "venue"
  },
  "geometry": {"coordinates":[-71.251739,42.494317],"type":"Point"}
}
