{
  "type": "Feature",
  "properties": {
    "iso:country":"US",
    "sg:address":"825 Washington St",
    "sg:city":"Norwood",
    "sg:classifiers":[
        {
            "category":"Health Services",
            "subcategory":"Doctor",
            "type":"Services"
        }
    ],
    "sg:phone":"+1 781 440 9476",
    "sg:postcode":"02062",
    "sg:province":"MA",
    "sg:tags":[
        "obstetrician",
        "gynecologist"
    ],
    "wof:name":"Caritas OB-Gyn",
    "wof:placetype":"venue"
},
  "geometry": {"coordinates":[-71.202698,42.189301],"type":"Point"}
}