{
  "type": "Feature",
  "properties": {
    "iso:country":"US",
    "sg:address":"482 Columbus Ave",
    "sg:city":"Boston",
    "sg:classifiers":[
        {
            "category":"Personal",
            "subcategory":"Beauty Salon",
            "type":"Services"
        }
    ],
    "sg:phone":"+1 617 266 2668",
    "sg:postcode":"02118",
    "sg:province":"MA",
    "wof:name":"Anita KURL Hair Salon",
    "wof:placetype":"venue"
},
  "geometry": {"coordinates":[-71.07908500000001,42.342689],"type":"Point"}
}