{
  "type": "Feature",
  "properties": {
    "addr:full": "482 Columbus Ave Boston MA 02118",
    "addr:housenumber": "482",
    "addr:postcode": "02118",
    "addr:street": "Columbus Ave",
    "iso:country": "US",
    "sg:address": "482 Columbus Ave",
    "sg:city": "Boston",
    "sg:classifiers": [
      {
        "category": "Personal",
        "subcategory": "Beauty Salon",
        "type": "Services"
      }
    ],
    "sg:phone": "+1 617 266 2668",
    "sg:postcode": "02118",
    "sg:province": "MA",
    "wof:name": "Anita KURL Hair Salon",
    "wof:placetype": "venue"
  },
  "geometry": {"coordinates":[-71.079085,42.342689],"type":"Point"}
}
