{
  "type": "Feature",
  "properties": {
    "iso:country":"US",
    "sg:address":"108 Beacon St",
    "sg:city":"Worcester",
    "sg:classifiers":[
        {
            "category":"Wholesale",
            "subcategory":"Painting Supplies",
            "type":"Manufacturing & Wholesale Goods"
        }
    ],
    "sg:phone":"+1 508 799 7297",
    "sg:postcode":"01608",
    "sg:province":"MA",
    "sg:tags":[
        "wallpaper"
    ],
    "wof:name":"A J Robbins Co",
    "wof:placetype":"venue"
},
  "geometry": {"coordinates":[-71.809848,42.254233],"type":"Point"}
}