{
  "type": "Feature",
  "properties": {
    "addr:full": "108 Beacon St Worcester MA 01608",
    "addr:housenumber": "108",
    "addr:postcode": "01608",
    "addr:street": "Beacon St",
    "iso:country": "US",
    "sg:address": "108 Beacon St",
    "sg:city": "Worcester",
    "sg:classifiers": [
      {
        "category": "Wholesale",
        "subcategory": "Painting Supplies",
        "type": "Manufacturing \u0026 Wholesale Goods"
      }
    ],
    "sg:phone": "+1 508 799 7297",
    "sg:postcode": "01608",
    "sg:province": "MA",
    "sg:tags": [
      "wallpaper"
    ],
    "wof:name": "A J Robbins Co",
    "wof:placetype": "venue"
  },
  "geometry": {"coordinates":[-71.809848,42.254233],"type":"Point"}
}
