{
  "type": "Feature",
  "properties": {
    "addr:full":"740 Main St Brockton MA 02301",
    "addr:housenumber":"740",
    "addr:postcode":"02301",
    "addr:street":"Main St",
    "iso:country":"US",
    "sg:address":"740 Main St",
    "sg:city":"Brockton",
    "sg:classifiers":[
        {
            "category":"Retail",
            "subcategory":"Auto Repair",
            "type":"Services"
        }
    ],
    "sg:phone":"+1 508 586 4676",
    "sg:postcode":"02301",
    "sg:province":"MA",
    "sg:tags":[
        "repairing",
        "automobile"
    ],
    "wof:name":"Brockton Foreign Automotive Co",
    "wof:placetype":"venue"
},
  "geometry": {"coordinates":[-71.01822199999999,42.071006],"type":"Point"}
}