{
  "type": "Feature",
  "properties": {
    "addr:full": "200 E Cross St Norwood MA 02062",
    "addr:housenumber": "200",
    "addr:postcode": "02062",
    "addr:street": "E Cross St",
    "iso:country": "US",
    "sg:address": "200 E Cross St",
    "sg:city": "Norwood",
    "sg:classifiers": [
      {
        "category": "Wholesale",
        "subcategory": "Construction Materials",
        "type": "Manufacturing \u0026 Wholesale Goods"
      }
    ],
    "sg:phone": "+1 781 255 6965",
    "sg:postcode": "02062",
    "sg:province": "MA",
    "sg:tags": [
      "concrete",
      "form"
    ],
    "wof:name": "B R Concrete Forms",
    "wof:placetype": "venue"
  },
  "geometry": {"coordinates":[-71.185202,42.185148],"type":"Point"}
}
