{
  "type": "Feature",
  "properties": {
    "addr:full": "215 Elm St Framingham MA 01701",
    "addr:housenumber": "215",
    "addr:postcode": "01701",
    "addr:street": "Elm St",
    "iso:country": "US",
    "ovtr:label": "Cameron Middle School, 215 Elm St Framingham MA US",
    "ovtr:similarity": 2.7865428924560547,
    "sg:address": "215 Elm St",
    "sg:city": "Framingham",
    "sg:classifiers": [
      {
        "category": "Education",
        "subcategory": "School",
        "type": "Public Place"
      }
    ],
    "sg:phone": "+1 508 879 2290",
    "sg:postcode": "01701",
    "sg:province": "MA",
    "wof:name": "Cameron Middle School",
    "wof:placetype": "venue"
  },
  "geometry": {"coordinates":[-71.401183,42.333566],"type":"Point"}
}
