{
  "type": "Feature",
  "properties": {
    "iso:country":"US",
    "sg:address":"215 Elm St",
    "sg:city":"Framingham",
    "sg:classifiers":[
        {
            "category":"Education",
            "subcategory":"School",
            "type":"Public Place"
        }
    ],
    "sg:phone":"+1 508 879 2290",
    "sg:postcode":"01701",
    "sg:province":"MA",
    "wof:name":"Cameron Middle School",
    "wof:placetype":"venue"
},
  "geometry": {"coordinates":[-71.401183,42.333566],"type":"Point"}
}