{
  "type": "Feature",
  "properties": {
    "iso:country":"US",
    "sg:address":"76 Loomis St",
    "sg:city":"Bedford",
    "sg:classifiers":[
        {
            "category":"Organizations",
            "subcategory":"Non-profit Organization",
            "type":"Services"
        }
    ],
    "sg:phone":"+1 781 275 4150",
    "sg:postcode":"01730",
    "sg:province":"MA",
    "wof:name":"Veterans Of Foreign Wars",
    "wof:placetype":"venue"
},
  "geometry": {"coordinates":[-71.277511,42.486014],"type":"Point"}
}