{
  "type": "Feature",
  "properties": {
    "iso:country":"US",
    "sg:address":"4 Franklin St",
    "sg:city":"Lawrence",
    "sg:classifiers":[
        {
            "category":"Retail",
            "subcategory":"Car Wash",
            "type":"Services"
        }
    ],
    "sg:phone":"+1 978 725 0008",
    "sg:postcode":"01840",
    "sg:province":"MA",
    "sg:tags":[
        "automobile",
        "detail",
        "clean"
    ],
    "wof:name":"M 1 Detailing",
    "wof:placetype":"venue"
},
  "geometry": {"coordinates":[-71.16545499999999,42.703907],"type":"Point"}
}