{
  "type": "Feature",
  "properties": {
    "iso:country":"US",
    "sg:address":"55 Wales St",
    "sg:city":"Abington",
    "sg:classifiers":[
        {
            "category":"Recreation",
            "type":"Entertainment"
        }
    ],
    "sg:phone":"+1 781 878 9822",
    "sg:postcode":"02351",
    "sg:province":"MA",
    "sg:tags":[
        "hall",
        "auditorium"
    ],
    "wof:name":"Polish Club",
    "wof:placetype":"venue"
},
  "geometry": {"coordinates":[-70.94908599999999,42.129295],"type":"Point"}
}