{
  "type": "Feature",
  "properties": {
    "addr:full": "55 Wales St Abington MA 02351",
    "addr:housenumber": "55",
    "addr:postcode": "02351",
    "addr:street": "Wales St",
    "iso:country": "US",
    "sg:address": "55 Wales St",
    "sg:city": "Abington",
    "sg:classifiers": [
      {
        "category": "Recreation",
        "type": "Entertainment"
      }
    ],
    "sg:phone": "+1 781 878 9822",
    "sg:postcode": "02351",
    "sg:province": "MA",
    "sg:tags": [
      "hall",
      "auditorium"
    ],
    "wof:name": "Polish Club",
    "wof:placetype": "venue"
  },
  "geometry": {"coordinates":[-70.949086,42.129295],"type":"Point"}
}
