{
  "type": "Feature",
  "properties": {
    "iso:country":"US",
    "sg:address":"483 County Rd",
    "sg:city":"Pocasset",
    "sg:classifiers":[
        {
            "category":"Building & Trades",
            "subcategory":"Plumbing",
            "type":"Services"
        }
    ],
    "sg:phone":"+1 508 759 5133",
    "sg:postcode":"02559",
    "sg:province":"MA",
    "sg:tags":[
        "heating",
        "contractor"
    ],
    "wof:name":"Canalside Heating Svc",
    "wof:placetype":"venue"
},
  "geometry": {"coordinates":[-70.60899999999999,41.710653],"type":"Point"}
}