{
  "type": "Feature",
  "properties": {
    "addr:full": "483 County Rd Pocasset MA 02559",
    "addr:housenumber": "483",
    "addr:postcode": "02559",
    "addr:street": "County Rd",
    "iso:country": "US",
    "sg:address": "483 County Rd",
    "sg:city": "Pocasset",
    "sg:classifiers": [
      {
        "category": "Building \u0026 Trades",
        "subcategory": "Plumbing",
        "type": "Services"
      }
    ],
    "sg:phone": "+1 508 759 5133",
    "sg:postcode": "02559",
    "sg:province": "MA",
    "sg:tags": [
      "heating",
      "contractor"
    ],
    "wof:name": "Canalside Heating Svc",
    "wof:placetype": "venue"
  },
  "geometry": {"coordinates":[-70.609,41.710653],"type":"Point"}
}
