{
  "type": "Feature",
  "properties": {
    "addr:full":"1005 Broadway Chelsea MA 02150",
    "addr:housenumber":"1005",
    "addr:postcode":"02150",
    "addr:street":"Broadway",
    "iso:country":"US",
    "sg:address":"1005 Broadway",
    "sg:city":"Chelsea",
    "sg:classifiers":[
        {
            "category":"Autos & Motor Vehicles",
            "subcategory":"Auto Supplies",
            "type":"Retail Goods"
        }
    ],
    "sg:phone":"+1 617 884 0240",
    "sg:postcode":"02150",
    "sg:province":"MA",
    "sg:tags":[
        "tire"
    ],
    "sg:website":"www.midas.com",
    "wof:name":"Midas Auto Service Experts",
    "wof:placetype":"venue"
},
  "geometry": {"coordinates":[-71.01949399999999,42.402317],"type":"Point"}
}