{
  "type": "Feature",
  "properties": {
    "iso:country":"US",
    "sg:address":"9 Old Webster St",
    "sg:city":"Hanover",
    "sg:classifiers":[
        {
            "category":"Retail",
            "subcategory":"Laundry & Dry Cleaning",
            "type":"Services"
        }
    ],
    "sg:phone":"+1 781 871 0198",
    "sg:postcode":"02339",
    "sg:province":"MA",
    "sg:tags":[
        "cleaners",
        "rug",
        "carpet"
    ],
    "wof:name":"A & A Carpet & Cleaning Svc",
    "wof:placetype":"venue"
},
  "geometry": {"coordinates":[-70.855332,42.154443],"type":"Point"}
}