{
  "type": "Feature",
  "properties": {
    "addr:full":"7 Eastview Dr Belchertown MA 01007",
    "addr:housenumber":"7",
    "addr:postcode":"01007",
    "addr:street":"Eastview Dr",
    "iso:country":"US",
    "sg:address":"7 Eastview Dr",
    "sg:city":"Belchertown",
    "sg:classifiers":[
        {
            "category":"Building & Trades",
            "subcategory":"Construction",
            "type":"Services"
        }
    ],
    "sg:phone":"+1   ",
    "sg:postcode":"01007",
    "sg:province":"MA",
    "sg:tags":[
        "house"
    ],
    "wof:name":"Robert A Sharpe Jr",
    "wof:placetype":"venue"
},
  "geometry": {"coordinates":[-72.397643,42.283535],"type":"Point"}
}