{
  "type": "Feature",
  "properties": {
    "iso:country":"US",
    "sg:address":"245 Cape Hwy",
    "sg:city":"East Taunton",
    "sg:classifiers":[
        {
            "category":"Food & Beverages",
            "subcategory":"Bakery",
            "type":"Retail Goods"
        }
    ],
    "sg:phone":"+1 508 824 3592",
    "sg:postcode":"02718",
    "sg:province":"MA",
    "sg:tags":[
        "bagel"
    ],
    "wof:name":"Honey Dew Donuts",
    "wof:placetype":"venue"
},
  "geometry": {"coordinates":[-70.99350099999999,41.902908],"type":"Point"}
}