{
  "type": "Feature",
  "properties": {
    "addr:full": "290 S Eastham St North Eastham MA 02642",
    "addr:housenumber": "290",
    "addr:postcode": "02642",
    "addr:street": "S Eastham St",
    "iso:country": "US",
    "sg:address": "290 S Eastham St",
    "sg:city": "North Eastham",
    "sg:classifiers": [
      {
        "category": "Building \u0026 Trades",
        "subcategory": "Construction",
        "type": "Services"
      }
    ],
    "sg:phone": "+1   ",
    "sg:postcode": "02642",
    "sg:province": "MA",
    "sg:tags": [
      "house"
    ],
    "wof:name": "R \u0026 A Construction",
    "wof:placetype": "venue"
  },
  "geometry": {"coordinates":[-69.978852,41.807334],"type":"Point"}
}
