{
  "type": "Feature",
  "properties": {
    "addr:full": "45 Lawn St Cambridge MA 02138",
    "addr:housenumber": "45",
    "addr:postcode": "02138",
    "addr:street": "Lawn St",
    "iso:country": "US",
    "sg:address": "45 Lawn St",
    "sg:city": "Cambridge",
    "sg:classifiers": [
      {
        "category": "Real Estate",
        "subcategory": "Real Estate Services",
        "type": "Services"
      }
    ],
    "sg:phone": "+1 617 868 1144",
    "sg:postcode": "02138",
    "sg:province": "MA",
    "sg:tags": [
      "vacancy",
      "apartment",
      "rental",
      "finder",
      "listing"
    ],
    "wof:name": "Upland Studio",
    "wof:placetype": "venue"
  },
  "geometry": {"coordinates":[-71.153986,42.377805],"type":"Point"}
}
