{
  "type": "Feature",
  "properties": {
    "iso:country":"US",
    "sg:address":"198 Sherrin St",
    "sg:city":"Hyde Park",
    "sg:classifiers":[
        {
            "category":"Professional",
            "type":"Services"
        }
    ],
    "sg:phone":"+1   ",
    "sg:postcode":"02136",
    "sg:province":"MA",
    "sg:tags":[
        "good",
        "lead",
        "mfg"
    ],
    "wof:name":"Hilary McHugh",
    "wof:placetype":"venue"
},
  "geometry": {"coordinates":[-71.125719,42.266005],"type":"Point"}
}