{
  "type": "Feature",
  "properties": {
    "iso:country":"US",
    "sg:address":"10 HIGH STREET / 155 FEDERAL STREET, SUITE 803",
    "sg:city":"Boston",
    "sg:classifiers":[
        {
            "category":"Education",
            "subcategory":"Special Training",
            "type":"Public Place"
        }
    ],
    "sg:phone":"+1 800 288 8221",
    "sg:postcode":"02110",
    "sg:province":"MA",
    "sg:tags":[
        "school",
        "computer",
        "technology"
    ],
    "sg:website":"http://ONLC.com",
    "wof:name":"ONLC Training Centers - Boston",
    "wof:placetype":"venue"
},
  "geometry": {"coordinates":[-71.055954,42.356499],"type":"Point"}
}