{
  "type": "Feature",
  "properties": {
    "iso:country":"US",
    "sg:address":"26 Highland Cir",
    "sg:city":"Needham",
    "sg:classifiers":[
        {
            "category":"Wholesale",
            "subcategory":"Groceries",
            "type":"Manufacturing & Wholesale Goods"
        }
    ],
    "sg:phone":"+1 781 444 0313",
    "sg:postcode":"02494",
    "sg:province":"MA",
    "sg:tags":[
        "food",
        "product"
    ],
    "wof:name":"M & M Marketing",
    "wof:placetype":"venue"
},
  "geometry": {"coordinates":[-71.21772300000001,42.306077],"type":"Point"}
}