{
  "type": "Feature",
  "properties": {
    "addr:full": "26 Highland Cir Needham MA 02494",
    "addr:housenumber": "26",
    "addr:postcode": "02494",
    "addr:street": "Highland Cir",
    "iso:country": "US",
    "sg:address": "26 Highland Cir",
    "sg:city": "Needham",
    "sg:classifiers": [
      {
        "category": "Wholesale",
        "subcategory": "Groceries",
        "type": "Manufacturing \u0026 Wholesale Goods"
      }
    ],
    "sg:phone": "+1 781 444 0313",
    "sg:postcode": "02494",
    "sg:province": "MA",
    "sg:tags": [
      "food",
      "product"
    ],
    "wof:name": "M \u0026 M Marketing",
    "wof:placetype": "venue"
  },
  "geometry": {"coordinates":[-71.217723,42.306077],"type":"Point"}
}
