{
  "type": "Feature",
  "properties": {
    "iso:country":"US",
    "sg:address":"44 Front St",
    "sg:city":"Ashland",
    "sg:classifiers":[
        {
            "category":"Health Services",
            "subcategory":"Medical Lab",
            "type":"Services"
        }
    ],
    "sg:phone":"+1 508 881 3335",
    "sg:postcode":"01721",
    "sg:province":"MA",
    "sg:tags":[
        "laboratory"
    ],
    "wof:name":"Ashland Dental Lab",
    "wof:placetype":"venue"
},
  "geometry": {"coordinates":[-71.45702199999999,42.260153],"type":"Point"}
}