{
  "type": "Feature",
  "properties": {
    "iso:country":"US",
    "sg:address":"27 Andrews Pkwy",
    "sg:city":"Devens",
    "sg:classifiers":[
        {
            "category":"Travel",
            "subcategory":"Hotels & Motels",
            "type":"Entertainment"
        }
    ],
    "sg:phone":"+1 978 772 3030",
    "sg:postcode":"01434",
    "sg:province":"MA",
    "sg:tags":[
        "lodging"
    ],
    "sg:website":"http://marriott.com/BOSSD",
    "wof:name":"Springhill Suites Boston Devens",
    "wof:placetype":"venue"
},
  "geometry": {"coordinates":[-71.614401,42.540795],"type":"Point"}
}