{
  "type": "Feature",
  "properties": {
    "addr:full":"1291 Dorchester Ave Dorchester MA 02122",
    "addr:housenumber":"1291",
    "addr:postcode":"02122",
    "addr:street":"Dorchester Ave",
    "iso:country":"US",
    "sg:address":"1291 Dorchester Ave",
    "sg:city":"Dorchester",
    "sg:classifiers":[
        {
            "category":"Shopping",
            "subcategory":"Beauty & Cosmetics",
            "type":"Retail Goods"
        }
    ],
    "sg:phone":"+1 617 288 6077",
    "sg:postcode":"02122",
    "sg:province":"MA",
    "sg:tags":[
        "supply"
    ],
    "wof:name":"Tulip Supply",
    "wof:placetype":"venue"
},
  "geometry": {"coordinates":[-71.05880000000001,42.2967],"type":"Point"}
}