{
  "type": "Feature",
  "properties": {
    "iso:country":"US",
    "sg:address":"10 Sandy Ln",
    "sg:city":"Buzzards Bay",
    "sg:classifiers":[
        {
            "category":"Wholesale",
            "subcategory":"Electrical",
            "type":"Manufacturing & Wholesale Goods"
        }
    ],
    "sg:phone":"+1 508 759 0738",
    "sg:postcode":"02532",
    "sg:province":"MA",
    "sg:tags":[
        "appliance"
    ],
    "wof:name":"Warren All Appliance",
    "wof:placetype":"venue"
},
  "geometry": {"coordinates":[-70.58801099999999,41.740467],"type":"Point"}
}