{
  "type": "Feature",
  "properties": {
    "addr:full": "10 Sandy Ln Buzzards Bay MA 02532",
    "addr:housenumber": "10",
    "addr:postcode": "02532",
    "addr:street": "Sandy Ln",
    "iso:country": "US",
    "sg:address": "10 Sandy Ln",
    "sg:city": "Buzzards Bay",
    "sg:classifiers": [
      {
        "category": "Wholesale",
        "subcategory": "Electrical",
        "type": "Manufacturing \u0026 Wholesale Goods"
      }
    ],
    "sg:phone": "+1 508 759 0738",
    "sg:postcode": "02532",
    "sg:province": "MA",
    "sg:tags": [
      "appliance"
    ],
    "wof:name": "Warren All Appliance",
    "wof:placetype": "venue"
  },
  "geometry": {"coordinates":[-70.588011,41.740467],"type":"Point"}
}
