{
  "type": "Feature",
  "properties": {
    "iso:country":"US",
    "sg:address":"51 Parmenter Rd",
    "sg:city":"Hudson",
    "sg:classifiers":[
        {
            "category":"Manufacturing",
            "subcategory":"Metals",
            "type":"Manufacturing & Wholesale Goods"
        }
    ],
    "sg:phone":"+1 978 562 7561",
    "sg:postcode":"01749",
    "sg:province":"MA",
    "sg:tags":[
        "coating"
    ],
    "sg:website":"www.boydcoatings.com",
    "wof:name":"Boyd Coating Research Co",
    "wof:placetype":"venue"
},
  "geometry": {"coordinates":[-71.497264,42.389978],"type":"Point"}
}