{
  "type": "Feature",
  "properties": {
    "iso:country":"US",
    "sg:address":"8 Fountain Inn Ln",
    "sg:city":"Marblehead",
    "sg:classifiers":[
        {
            "category":"Professional",
            "type":"Services"
        }
    ],
    "sg:phone":"+1 781 631 7256",
    "sg:postcode":"01945",
    "sg:province":"MA",
    "sg:tags":[
        "establishment"
    ],
    "wof:name":"Fred Bauer The Writer",
    "wof:placetype":"venue"
},
  "geometry": {"coordinates":[-70.845097,42.510024],"type":"Point"}
}