{
  "type": "Feature",
  "properties": {
    "addr:full": "10 Main St Florence MA 01062",
    "addr:housenumber": "10",
    "addr:postcode": "01062",
    "addr:street": "Main St",
    "iso:country": "US",
    "sg:address": "10 Main St",
    "sg:city": "Florence",
    "sg:classifiers": [
      {
        "category": "Health Services",
        "subcategory": "Doctor",
        "type": "Services"
      }
    ],
    "sg:phone": "+1 413 584 1588",
    "sg:postcode": "01062",
    "sg:province": "MA",
    "sg:tags": [
      "physician",
      "surgeon"
    ],
    "wof:name": "Northampton Cardiology Assoc",
    "wof:placetype": "venue"
  },
  "geometry": {"coordinates":[-72.6663,42.334618],"type":"Point"}
}
