{
  "type": "Feature",
  "properties": {
    "addr:full":"801 Main St Ste 14 Concord MA 01742",
    "addr:housenumber":"801",
    "addr:postcode":"01742",
    "addr:street":"Main St Ste 14",
    "iso:country":"US",
    "sg:address":"801 Main St Ste 14",
    "sg:city":"Concord",
    "sg:classifiers":[
        {
            "category":"Professional",
            "subcategory":"Lawyer & Legal Services",
            "type":"Services"
        }
    ],
    "sg:phone":"+1 978 369 0960",
    "sg:postcode":"01742",
    "sg:province":"MA",
    "wof:name":"Woodman & Eaton PC",
    "wof:placetype":"venue"
},
  "geometry": {"coordinates":[-71.37370300000001,42.455399],"type":"Point"}
}