{
  "type": "Feature",
  "properties": {
    "iso:country":"US",
    "sg:address":"655 Mount Auburn Street",
    "sg:city":"Watertown",
    "sg:classifiers":[
        {
            "category":"Retail",
            "subcategory":"Auto Rental",
            "type":"Services"
        }
    ],
    "sg:phone":"+1 617 926 6026",
    "sg:postcode":"02472",
    "sg:province":"MA",
    "sg:tags":[
        "car"
    ],
    "sg:website":"www.budgettruck.com",
    "wof:name":"Budget Truck Rental",
    "wof:placetype":"venue"
},
  "geometry": {"coordinates":[-71.156998,42.371799],"type":"Point"}
}