{
  "type": "Feature",
  "properties": {
    "addr:full": "672 Union St Rockland MA 02370",
    "addr:housenumber": "672",
    "addr:postcode": "02370",
    "addr:street": "Union St",
    "iso:country": "US",
    "sg:address": "672 Union St",
    "sg:city": "Rockland",
    "sg:classifiers": [
      {
        "category": "Building \u0026 Trades",
        "subcategory": "Plumbing",
        "type": "Services"
      }
    ],
    "sg:phone": "+1 781 878 8098",
    "sg:postcode": "02370",
    "sg:province": "MA",
    "sg:tags": [
      "plumber"
    ],
    "sg:website": "http://www.hoadleyandsons.com",
    "wof:name": "John Hoadley and Sons, Inc.",
    "wof:placetype": "venue"
  },
  "geometry": {"coordinates":[-70.919342,42.139919],"type":"Point"}
}
