{
  "type": "Feature",
  "properties": {
    "addr:full":"10 New England Executive Park Burlington MA 01803",
    "addr:housenumber":"10",
    "addr:postcode":"01803",
    "addr:street":"New England Executive Park",
    "iso:country":"US",
    "sg:address":"10 New England Executive Park",
    "sg:city":"Burlington",
    "sg:classifiers":[
        {
            "category":"Banks & Credit Unions",
            "subcategory":"Investment Brokerage",
            "type":"Services"
        }
    ],
    "sg:phone":"+1 781 203 3766",
    "sg:postcode":"01803",
    "sg:province":"MA",
    "sg:tags":[
        "investing"
    ],
    "wof:name":"Exodus Arca Securities",
    "wof:placetype":"venue"
},
  "geometry": {"coordinates":[-71.211516,42.48532],"type":"Point"}
}