{
  "type": "Feature",
  "properties": {
    "addr:full": "242 John Wise Ave Essex MA 01929",
    "addr:housenumber": "242",
    "addr:postcode": "01929",
    "addr:street": "John Wise Ave",
    "iso:country": "US",
    "sg:address": "242 John Wise Ave",
    "sg:city": "Essex",
    "sg:classifiers": [
      {
        "category": "Home \u0026 Garden",
        "subcategory": "Furniture",
        "type": "Retail Goods"
      }
    ],
    "sg:phone": "+1 978 768 7018",
    "sg:postcode": "01929",
    "sg:province": "MA",
    "sg:tags": [
      "builder",
      "custom"
    ],
    "wof:name": "Shea Brothers Interiors",
    "wof:placetype": "venue"
  },
  "geometry": {"coordinates":[-70.806026,42.653678],"type":"Point"}
}
