{
  "type": "Feature",
  "properties": {
    "addr:full": "11 Bartlett St Salisbury MA 01952",
    "addr:housenumber": "11",
    "addr:postcode": "01952",
    "addr:street": "Bartlett St",
    "iso:country": "US",
    "sg:address": "11 Bartlett St",
    "sg:city": "Salisbury",
    "sg:classifiers": [
      {
        "category": "Wholesale",
        "subcategory": "Seafood",
        "type": "Manufacturing \u0026 Wholesale Goods"
      }
    ],
    "sg:phone": "+1 978 465 3575",
    "sg:postcode": "01952",
    "sg:province": "MA",
    "sg:tags": [
      "fish"
    ],
    "wof:name": "Seafood East",
    "wof:placetype": "venue"
  },
  "geometry": {"coordinates":[-70.875293,42.846108],"type":"Point"}
}
