{
  "type": "Feature",
  "properties": {
    "addr:full": "22 Bates Road Mashpee MA 02649",
    "addr:housenumber": "22",
    "addr:postcode": "02649",
    "addr:street": "Bates Road",
    "iso:country": "US",
    "sg:address": "22 Bates Road",
    "sg:city": "Mashpee",
    "sg:classifiers": [
      {
        "category": "Professional",
        "subcategory": "Advertising",
        "type": "Services"
      },
      {
        "category": "Professional",
        "subcategory": "Computer Services",
        "type": "Services"
      },
      {
        "category": "Internet Cafe",
        "subcategory": "None",
        "type": "Food \u0026 Drink"
      }
    ],
    "sg:phone": "+1 508 274 2398",
    "sg:postcode": "02649",
    "sg:province": "MA",
    "sg:tags": [
      "web",
      "product",
      "graphic",
      "marketing",
      "site",
      "hosting",
      "online"
    ],
    "sg:website": "http://www.allcapewebsitedesign.com",
    "wof:name": "All Cape Website Design",
    "wof:placetype": "venue"
  },
  "geometry": {"coordinates":[-70.490122,41.619177],"type":"Point"}
}
