{
  "type": "Feature",
  "properties": {
    "addr:full": "4 Avery St Boston MA 02111",
    "addr:housenumber": "4",
    "addr:postcode": "02111",
    "addr:street": "Avery St",
    "iso:country": "US",
    "sg:address": "4 Avery St",
    "sg:city": "Boston",
    "sg:classifiers": [
      {
        "category": "Health Services",
        "subcategory": "Chiropractor",
        "type": "Services"
      }
    ],
    "sg:phone": "+1 617 375 8580",
    "sg:postcode": "02111",
    "sg:province": "MA",
    "sg:tags": [
      "chiropractic"
    ],
    "wof:name": "Green Richard L",
    "wof:placetype": "venue"
  },
  "geometry": {"coordinates":[-71.062646,42.353183],"type":"Point"}
}
