{
  "type": "Feature",
  "properties": {
    "addr:full":"100 W State St Whately MA 01075",
    "addr:housenumber":"100",
    "addr:postcode":"01075",
    "addr:street":"W State St",
    "iso:country":"US",
    "sg:address":"100 W State St",
    "sg:city":"Whately",
    "sg:classifiers":[
        {
            "category":"Sports & Exercise",
            "subcategory":"Gym",
            "type":"Entertainment"
        }
    ],
    "sg:phone":"+1 413 665 6660",
    "sg:postcode":"01075",
    "sg:province":"MA",
    "sg:tags":[
        "club",
        "health",
        "studio",
        "gymnasium"
    ],
    "wof:name":"Curves For Women",
    "wof:placetype":"venue"
},
  "geometry": {"coordinates":[-72.581925,42.22321],"type":"Point"}
}