{
  "type": "Feature",
  "properties": {
    "addr:full":"226 Westminster St Fitchburg MA 01420",
    "addr:housenumber":"226",
    "addr:postcode":"01420",
    "addr:street":"Westminster St",
    "iso:country":"US",
    "sg:address":"226 Westminster St",
    "sg:city":"Fitchburg",
    "sg:classifiers":[
        {
            "category":"Restaurant",
            "type":"Food & Drink"
        }
    ],
    "sg:phone":"+1 978 345 4046",
    "sg:postcode":"01420",
    "sg:province":"MA",
    "sg:tags":[
        "pizza"
    ],
    "wof:name":"West Fitchburg Pizza",
    "wof:placetype":"venue"
},
  "geometry": {"coordinates":[-71.84159200000001,42.571109],"type":"Point"}
}