{
  "type": "Feature",
  "properties": {
    "addr:full":"85 Main St Ware MA 01082",
    "addr:housenumber":"85",
    "addr:postcode":"01082",
    "addr:street":"Main St",
    "iso:country":"US",
    "sg:address":"85 Main St",
    "sg:city":"Ware",
    "sg:classifiers":[
        {
            "category":"Shopping",
            "subcategory":"Computers & Home Electronics",
            "type":"Retail Goods"
        }
    ],
    "sg:phone":"+1 413 967 5431",
    "sg:postcode":"01082",
    "sg:province":"MA",
    "sg:tags":[
        "television",
        "radio"
    ],
    "wof:name":"Tva Electronics",
    "wof:placetype":"venue"
},
  "geometry": {"coordinates":[-72.24133500000001,42.260399],"type":"Point"}
}