{
  "type": "Feature",
  "properties": {
    "addr:full": "22 Reynolds St North Easton MA 02356",
    "addr:housenumber": "22",
    "addr:postcode": "02356",
    "addr:street": "Reynolds St",
    "iso:country": "US",
    "sg:address": "22 Reynolds St",
    "sg:city": "North Easton",
    "sg:classifiers": [
      {
        "category": "Building \u0026 Trades",
        "subcategory": "Construction",
        "type": "Services"
      }
    ],
    "sg:phone": "+1   ",
    "sg:postcode": "02356",
    "sg:province": "MA",
    "sg:tags": [
      "house"
    ],
    "wof:name": "CM Construction Inc",
    "wof:placetype": "venue"
  },
  "geometry": {"coordinates":[-71.098231,42.063407],"type":"Point"}
}
