{
  "type": "Feature",
  "properties": {
    "iso:country":"US",
    "sg:address":"22 Reynolds St",
    "sg:city":"North Easton",
    "sg:classifiers":[
        {
            "category":"Building & Trades",
            "subcategory":"Construction",
            "type":"Services"
        }
    ],
    "sg:phone":"+1   ",
    "sg:postcode":"02356",
    "sg:province":"MA",
    "sg:tags":[
        "house"
    ],
    "wof:name":"CM Construction Inc",
    "wof:placetype":"venue"
},
  "geometry": {"coordinates":[-71.098231,42.063407],"type":"Point"}
}