{
  "type": "Feature",
  "properties": {
    "addr:full":"26 Locke St Cambridge MA 02140",
    "addr:housenumber":"26",
    "addr:postcode":"02140",
    "addr:street":"Locke St",
    "iso:country":"US",
    "sg:address":"26 Locke St",
    "sg:city":"Cambridge",
    "sg:classifiers":[
        {
            "category":"Building & Trades",
            "subcategory":"Construction",
            "type":"Services"
        }
    ],
    "sg:phone":"+1 617 864 3025",
    "sg:postcode":"02140",
    "sg:province":"MA",
    "sg:tags":[
        "contractor"
    ],
    "wof:name":"Klt Contracting Co",
    "wof:placetype":"venue"
},
  "geometry": {"coordinates":[-71.12760900000001,42.39695],"type":"Point"}
}