{
  "type": "Feature",
  "properties": {
    "addr:full": "24 Plain St Rehoboth MA 02769",
    "addr:housenumber": "24",
    "addr:postcode": "02769",
    "addr:street": "Plain St",
    "iso:country": "US",
    "sg:address": "24 Plain St",
    "sg:city": "Rehoboth",
    "sg:classifiers": [
      {
        "category": "Professional",
        "subcategory": "Business Services",
        "type": "Services"
      }
    ],
    "sg:phone": "+1   ",
    "sg:postcode": "02769",
    "sg:province": "MA",
    "wof:name": "Adirondack Technology Corp",
    "wof:placetype": "venue"
  },
  "geometry": {"coordinates":[-71.229825,41.813144],"type":"Point"}
}
