{
  "type": "Feature",
  "properties": {
    "iso:country":"US",
    "sg:address":"112 Middle St",
    "sg:city":"Lowell",
    "sg:classifiers":[
        {
            "category":"Restaurant",
            "type":"Food & Drink"
        }
    ],
    "sg:phone":"+1   ",
    "sg:postcode":"01852",
    "sg:province":"MA",
    "sg:tags":[
        "eating"
    ],
    "wof:name":"Fortunatos Restaurant",
    "wof:placetype":"venue"
},
  "geometry": {"coordinates":[-71.31237400000001,42.645181],"type":"Point"}
}