{
  "type": "Feature",
  "properties": {
    "addr:full": "8 Independence Ln Millis MA 02054",
    "addr:housenumber": "8",
    "addr:postcode": "02054",
    "addr:street": "Independence Ln",
    "iso:country": "US",
    "sg:address": "8 Independence Ln",
    "sg:city": "Millis",
    "sg:classifiers": [
      {
        "category": "Manufacturing",
        "subcategory": "Printing",
        "type": "Manufacturing \u0026 Wholesale Goods"
      }
    ],
    "sg:phone": "+1 508 376 9002",
    "sg:postcode": "02054",
    "sg:province": "MA",
    "sg:tags": [
      "printer"
    ],
    "wof:name": "Forms \u0026 Supplies Unlimited Inc",
    "wof:placetype": "venue"
  },
  "geometry": {"coordinates":[-71.375334,42.142286],"type":"Point"}
}
