{
  "type": "Feature",
  "properties": {
    "iso:country":"US",
    "sg:address":"8 Independence Ln",
    "sg:city":"Millis",
    "sg:classifiers":[
        {
            "category":"Manufacturing",
            "subcategory":"Printing",
            "type":"Manufacturing & Wholesale Goods"
        }
    ],
    "sg:phone":"+1 508 376 9002",
    "sg:postcode":"02054",
    "sg:province":"MA",
    "sg:tags":[
        "printer"
    ],
    "wof:name":"Forms & Supplies Unlimited Inc",
    "wof:placetype":"venue"
},
  "geometry": {"coordinates":[-71.375334,42.142286],"type":"Point"}
}