{
  "type": "Feature",
  "properties": {
    "addr:full": "491 Parker St Gardner MA 01440",
    "addr:housenumber": "491",
    "addr:postcode": "01440",
    "addr:street": "Parker St",
    "iso:country": "US",
    "sg:address": "491 Parker St",
    "sg:city": "Gardner",
    "sg:classifiers": [
      {
        "category": "Building \u0026 Trades",
        "subcategory": "Construction",
        "type": "Services"
      }
    ],
    "sg:phone": "+1   ",
    "sg:postcode": "01440",
    "sg:province": "MA",
    "sg:tags": [
      "general"
    ],
    "wof:name": "Jambs Construction",
    "wof:placetype": "venue"
  },
  "geometry": {"coordinates":[-72.010454,42.57445],"type":"Point"}
}
