{
  "type": "Feature",
  "properties": {
    "addr:full": "63 Donna Ave Pittsfield MA 01201",
    "addr:housenumber": "63",
    "addr:postcode": "01201",
    "addr:street": "Donna Ave",
    "iso:country": "US",
    "sg:address": "63 Donna Ave",
    "sg:city": "Pittsfield",
    "sg:classifiers": [
      {
        "category": "Building \u0026 Trades",
        "subcategory": "Electrical",
        "type": "Services"
      }
    ],
    "sg:phone": "+1 413 448 8132",
    "sg:postcode": "01201",
    "sg:province": "MA",
    "sg:tags": [
      "electric",
      "contractor"
    ],
    "wof:name": "Monument Electric Co Inc",
    "wof:placetype": "venue"
  },
  "geometry": {"coordinates":[-73.223692,42.436416],"type":"Point"}
}
