{
  "type": "Feature",
  "properties": {
    "iso:country":"US",
    "sg:address":"501 S Main St",
    "sg:city":"Andover",
    "sg:classifiers":[
        {
            "category":"Organizations",
            "subcategory":"Religious Organization",
            "type":"Services"
        }
    ],
    "sg:phone":"+1 978 474 0540",
    "sg:postcode":"01810",
    "sg:province":"MA",
    "sg:tags":[
        "synagogue"
    ],
    "wof:name":"Congregation Beth Israel",
    "wof:placetype":"venue"
},
  "geometry": {"coordinates":[-71.12237399999999,42.605407],"type":"Point"}
}