{
  "type": "Feature",
  "properties": {
    "addr:full": "2 Park Plz Boston MA 02116",
    "addr:housenumber": "2",
    "addr:postcode": "02116",
    "addr:street": "Park Plz",
    "iso:country": "US",
    "sg:address": "2 Park Plz",
    "sg:city": "Boston",
    "sg:classifiers": [
      {
        "category": "Professional",
        "subcategory": "Lawyer \u0026 Legal Services",
        "type": "Services"
      }
    ],
    "sg:phone": "+1 617 348 4368",
    "sg:postcode": "02116",
    "sg:province": "MA",
    "sg:tags": [
      "attorney"
    ],
    "wof:name": "Paul Walsh",
    "wof:placetype": "venue"
  },
  "geometry": {"coordinates":[-71.067469,42.352495],"type":"Point"}
}
