{
  "type": "Feature",
  "properties": {
    "iso:country":"US",
    "sg:address":"650 Cambridge St",
    "sg:city":"Cambridge",
    "sg:classifiers":[
        {
            "category":"Communications",
            "type":"Services"
        }
    ],
    "sg:phone":"+1 617 669 9354",
    "sg:postcode":"02141",
    "sg:province":"MA",
    "wof:name":"Wgr Media",
    "wof:placetype":"venue"
},
  "geometry": {"coordinates":[-71.087372,42.37199],"type":"Point"}
}