{
  "type": "Feature",
  "properties": {
    "iso:country":"US",
    "sg:address":"145 Kenoza Ave",
    "sg:city":"Haverhill",
    "sg:classifiers":[
        {
            "category":"Health Services",
            "subcategory":"Doctor",
            "type":"Services"
        }
    ],
    "sg:phone":"+1 978 374 0863",
    "sg:postcode":"01830",
    "sg:province":"MA",
    "sg:tags":[
        "dentist"
    ],
    "wof:name":"Peter L Manis DDS",
    "wof:placetype":"venue"
},
  "geometry": {"coordinates":[-71.072773,42.784192],"type":"Point"}
}