{
  "type": "Feature",
  "properties": {
    "addr:full":"673 Tremont St Boston MA 02118",
    "addr:housenumber":"673",
    "addr:postcode":"02118",
    "addr:street":"Tremont St",
    "iso:country":"US",
    "sg:address":"673 Tremont St",
    "sg:city":"Boston",
    "sg:classifiers":[
        {
            "category":"Personal",
            "subcategory":"Beauty Salon",
            "type":"Services"
        }
    ],
    "sg:phone":"+1 617 236 1222",
    "sg:postcode":"02118",
    "sg:province":"MA",
    "wof:name":"Pure Image Design",
    "wof:placetype":"venue"
},
  "geometry": {"coordinates":[-71.07657,42.341443],"type":"Point"}
}