{
  "type": "Feature",
  "properties": {
    "addr:full": "174A Main St Medway MA 02053",
    "addr:housenumber": "174a",
    "addr:postcode": "02053",
    "addr:street": "Main St",
    "iso:country": "US",
    "sg:address": "174A Main St",
    "sg:city": "Medway",
    "sg:classifiers": [
      {
        "category": "Shopping",
        "subcategory": "Books",
        "type": "Retail Goods"
      }
    ],
    "sg:phone": "+1 508 533 4440",
    "sg:postcode": "02053",
    "sg:province": "MA",
    "sg:tags": [
      "store"
    ],
    "sg:website": "http://www.enchantedfox.net",
    "wof:name": "Enchanted Fox Inc",
    "wof:placetype": "venue"
  },
  "geometry": {"coordinates":[-71.428886,42.146],"type":"Point"}
}
