{
  "type": "Feature",
  "properties": {
    "addr:full": "116 Front St Scituate MA 02066",
    "addr:housenumber": "116",
    "addr:postcode": "02066",
    "addr:street": "Front St",
    "iso:country": "US",
    "sg:address": "116 Front St",
    "sg:city": "Scituate",
    "sg:classifiers": [
      {
        "category": "Restaurant",
        "type": "Food \u0026 Drink"
      }
    ],
    "sg:phone": "+1 781 545 5881",
    "sg:postcode": "02066",
    "sg:province": "MA",
    "sg:tags": [
      "style",
      "family",
      "italian"
    ],
    "wof:name": "Riva Restaurant",
    "wof:placetype": "venue"
  },
  "geometry": {"coordinates":[-70.72506,42.19503],"type":"Point"}
}
