{
  "type": "Feature",
  "properties": {
    "addr:full":"271 Prospect St Northampton MA 01060",
    "addr:housenumber":"271",
    "addr:postcode":"01060",
    "addr:street":"Prospect St",
    "iso:country":"US",
    "sg:address":"271 Prospect St",
    "sg:city":"Northampton",
    "sg:classifiers":[
        {
            "category":"Building & Trades",
            "subcategory":"Construction",
            "type":"Services"
        }
    ],
    "sg:phone":"+1   ",
    "sg:postcode":"01060",
    "sg:province":"MA",
    "sg:tags":[
        "general"
    ],
    "wof:name":"Messeck Harvey P Construction",
    "wof:placetype":"venue"
},
  "geometry": {"coordinates":[-72.64226600000001,42.3291],"type":"Point"}
}