{
  "type": "Feature",
  "properties": {
    "iso:country":"US",
    "sg:address":"85 Garland Street",
    "sg:city":"Chelsea",
    "sg:classifiers":[
        {
            "category":"Professional",
            "subcategory":"Computer Services",
            "type":"Services"
        }
    ],
    "sg:phone":"+1 617 889 3920",
    "sg:postcode":"02150",
    "sg:province":"MA",
    "sg:tags":[
        "repair"
    ],
    "wof:name":"Simply PC",
    "wof:placetype":"venue"
},
  "geometry": {"coordinates":[-71.035768,42.408244],"type":"Point"}
}