{
  "type": "Feature",
  "properties": {
    "iso:country":"US",
    "sg:address":"186 Duchaine Blvd",
    "sg:city":"New Bedford",
    "sg:classifiers":[
        {
            "category":"Manufacturing",
            "subcategory":"Printing",
            "type":"Manufacturing & Wholesale Goods"
        }
    ],
    "sg:phone":"+1 508 995 5118",
    "sg:postcode":"02745",
    "sg:province":"MA",
    "sg:tags":[
        "printer"
    ],
    "sg:website":"www.reynoldsdewalt.com",
    "wof:name":"Reynolds-De Walt Printing Inc",
    "wof:placetype":"venue"
},
  "geometry": {"coordinates":[-70.954121,41.724385],"type":"Point"}
}