{
  "type": "Feature",
  "properties": {
    "addr:full": "353 Main St Spencer MA 01562",
    "addr:housenumber": "353",
    "addr:postcode": "01562",
    "addr:street": "Main St",
    "iso:country": "US",
    "sg:address": "353 Main St",
    "sg:city": "Spencer",
    "sg:classifiers": [
      {
        "category": "Freight",
        "type": "Transportation"
      }
    ],
    "sg:phone": "+1 508 885 6692",
    "sg:postcode": "01562",
    "sg:province": "MA",
    "sg:tags": [
      "commercial",
      "storage"
    ],
    "wof:name": "Laney's",
    "wof:placetype": "venue"
  },
  "geometry": {"coordinates":[-71.96488,42.255133],"type":"Point"}
}
