{
  "type": "Feature",
  "properties": {
    "iso:country":"US",
    "sg:address":"353 Main St",
    "sg:city":"Spencer",
    "sg:classifiers":[
        {
            "category":"Freight",
            "type":"Transportation"
        }
    ],
    "sg:phone":"+1 508 885 6692",
    "sg:postcode":"01562",
    "sg:province":"MA",
    "sg:tags":[
        "commercial",
        "storage"
    ],
    "wof:name":"Laney's",
    "wof:placetype":"venue"
},
  "geometry": {"coordinates":[-71.96487999999999,42.255133],"type":"Point"}
}