{
  "type": "Feature",
  "properties": {
    "addr:full": "22 Wellington Ave Framingham MA 01702",
    "addr:housenumber": "22",
    "addr:postcode": "01702",
    "addr:street": "Wellington Ave",
    "iso:country": "US",
    "sg:address": "22 Wellington Ave",
    "sg:city": "Framingham",
    "sg:classifiers": [
      {
        "category": "Utilities",
        "subcategory": "Refuse",
        "type": "Services"
      }
    ],
    "sg:phone": "+1 508 620 0155",
    "sg:postcode": "01702",
    "sg:province": "MA",
    "sg:tags": [
      "garbage",
      "collection"
    ],
    "wof:name": "H A Sancomb Trucking Co",
    "wof:placetype": "venue"
  },
  "geometry": {"coordinates":[-71.411187,42.270564],"type":"Point"}
}
