{
  "type": "Feature",
  "properties": {
    "iso:country":"US",
    "sg:address":"34 Hampshire St",
    "sg:city":"Methuen",
    "sg:classifiers":[
        {
            "category":"Restaurant",
            "type":"Food & Drink"
        }
    ],
    "sg:phone":"+1 978 327 5049",
    "sg:postcode":"01844",
    "sg:province":"MA",
    "wof:name":"Rudolpho's Restaurante",
    "wof:placetype":"venue"
},
  "geometry": {"coordinates":[-71.18891000000001,42.72783],"type":"Point"}
}