{
  "type": "Feature",
  "properties": {
    "addr:full":"726 Putnam Ave Cotuit MA 02635",
    "addr:housenumber":"726",
    "addr:postcode":"02635",
    "addr:street":"Putnam Ave",
    "iso:country":"US",
    "sg:address":"726 Putnam Ave",
    "sg:city":"Cotuit",
    "sg:classifiers":[
        {
            "category":"Building & Trades",
            "subcategory":"Landscaping Services",
            "type":"Services"
        }
    ],
    "sg:phone":"+1 508 428 6146",
    "sg:postcode":"02635",
    "sg:province":"MA",
    "sg:tags":[
        "landscape",
        "contractor"
    ],
    "wof:name":"Jeffery Williams Landscaping",
    "wof:placetype":"venue"
},
  "geometry": {"coordinates":[-70.427367,41.641869],"type":"Point"}
}