{
  "type": "Feature",
  "properties": {
    "addr:full": "20 Bowdoin Ter Springfield MA 01109",
    "addr:housenumber": "20",
    "addr:postcode": "01109",
    "addr:street": "Bowdoin Ter",
    "iso:country": "US",
    "sg:address": "20 Bowdoin Ter",
    "sg:city": "Springfield",
    "sg:classifiers": [
      {
        "category": "Organizations",
        "subcategory": "Religious Organization",
        "type": "Services"
      }
    ],
    "sg:phone": "+1 413 858 8111",
    "sg:postcode": "01109",
    "sg:province": "MA",
    "sg:tags": [
      "church"
    ],
    "wof:name": "Mission Church",
    "wof:placetype": "venue"
  },
  "geometry": {"coordinates":[-72.575011,42.112234],"type":"Point"}
}
