{
  "type": "Feature",
  "properties": {
    "addr:full": "27 North Way Mashpee MA 02649",
    "addr:housenumber": "27",
    "addr:postcode": "02649",
    "addr:street": "North Way",
    "iso:country": "US",
    "sg:address": "27 North Way",
    "sg:city": "Mashpee",
    "sg:classifiers": [
      {
        "category": "Retail",
        "subcategory": "Animal Services",
        "type": "Services"
      }
    ],
    "sg:phone": "+1 508 477 7053",
    "sg:postcode": "02649",
    "sg:province": "MA",
    "sg:tags": [
      "pet"
    ],
    "wof:name": "Sandy Paws",
    "wof:placetype": "venue"
  },
  "geometry": {"coordinates":[-70.484397,41.610579],"type":"Point"}
}
