{
  "type": "Feature",
  "properties": {
    "iso:country":"US",
    "sg:address":"202 Glen St",
    "sg:city":"Natick",
    "sg:classifiers":[
        {
            "category":"Professional",
            "subcategory":"Business Services",
            "type":"Services"
        }
    ],
    "sg:phone":"+1   ",
    "sg:postcode":"01760",
    "sg:province":"MA",
    "wof:name":"Invenio Partners LLC",
    "wof:placetype":"venue"
},
  "geometry": {"coordinates":[-71.316912,42.251657],"type":"Point"}
}