{
  "type": "Feature",
  "properties": {
    "iso:country":"US",
    "sg:address":"280 Eastern Ave",
    "sg:city":"Chelsea",
    "sg:phone":"+1 617 884 5980",
    "sg:postcode":"02150",
    "sg:province":"MA",
    "sg:tags":[
        "product",
        "petroleum"
    ],
    "wof:name":"Gulf Oil Terminal",
    "wof:placetype":"venue"
},
  "geometry": {"coordinates":[-71.021298,42.395129],"type":"Point"}
}