{
  "type": "Feature",
  "properties": {
    "addr:full":"410 Rutherford Ave Charlestown MA 02129",
    "addr:housenumber":"410",
    "addr:postcode":"02129",
    "addr:street":"Rutherford Ave",
    "iso:country":"US",
    "sg:address":"410 Rutherford Ave",
    "sg:city":"Charlestown",
    "sg:classifiers":[
        {
            "category":"Shopping",
            "subcategory":"Department Store",
            "type":"Retail Goods"
        }
    ],
    "sg:phone":"+1 617 720 8036",
    "sg:postcode":"02129",
    "sg:province":"MA",
    "wof:name":"Raymond W Couture",
    "wof:placetype":"venue"
},
  "geometry": {"coordinates":[-71.070457,42.379141],"type":"Point"}
}