{
  "type": "Feature",
  "properties": {
    "iso:country":"US",
    "sg:address":"1 Enterprise Dr",
    "sg:city":"Quincy",
    "sg:classifiers":[
        {
            "category":"Social Services",
            "subcategory":"Child Care",
            "type":"Services"
        }
    ],
    "sg:phone":"+1 617 246 8002",
    "sg:postcode":"02171",
    "sg:province":"MA",
    "sg:tags":[
        "nursery",
        "day"
    ],
    "wof:name":"Bcbs- Ma Center For Children",
    "wof:placetype":"venue"
},
  "geometry": {"coordinates":[-71.03967299999999,42.276321],"type":"Point"}
}