{
  "type": "Feature",
  "properties": {
    "addr:full": "345 Washington St Boston MA 02108",
    "addr:housenumber": "345",
    "addr:postcode": "02108",
    "addr:street": "Washington St",
    "iso:country": "US",
    "sg:address": "345 Washington St",
    "sg:city": "Boston",
    "sg:classifiers": [
      {
        "category": "Shopping",
        "subcategory": "Jewelry",
        "type": "Retail Goods"
      }
    ],
    "sg:phone": "+1 617 720 5909",
    "sg:postcode": "02108",
    "sg:province": "MA",
    "wof:name": "Jenny's Jewelry",
    "wof:placetype": "venue"
  },
  "geometry": {"coordinates":[-71.0588,42.356701],"type":"Point"}
}
