{
  "type": "Feature",
  "properties": {
    "iso:country":"US",
    "sg:address":"28 Bay Rd",
    "sg:city":"South Hamilton",
    "sg:classifiers":[
        {
            "category":"Sports & Exercise",
            "subcategory":"Gym",
            "type":"Entertainment"
        }
    ],
    "sg:phone":"+1 978 468 7511",
    "sg:postcode":"01982",
    "sg:province":"MA",
    "sg:tags":[
        "spa",
        "health"
    ],
    "wof:name":"Danielle Taylor Day Spa",
    "wof:placetype":"venue"
},
  "geometry": {"coordinates":[-70.875225,42.610043],"type":"Point"}
}