{
  "type": "Feature",
  "properties": {
    "addr:full": "28 Bay Rd South Hamilton MA 01982",
    "addr:housenumber": "28",
    "addr:postcode": "01982",
    "addr:street": "Bay Rd South",
    "iso:country": "US",
    "sg:address": "28 Bay Rd",
    "sg:city": "South Hamilton",
    "sg:classifiers": [
      {
        "category": "Sports \u0026 Exercise",
        "subcategory": "Gym",
        "type": "Entertainment"
      }
    ],
    "sg:phone": "+1 978 468 7511",
    "sg:postcode": "01982",
    "sg:province": "MA",
    "sg:tags": [
      "spa",
      "health"
    ],
    "wof:name": "Danielle Taylor Day Spa",
    "wof:placetype": "venue"
  },
  "geometry": {"coordinates":[-70.875225,42.610043],"type":"Point"}
}
