{
  "type": "Feature",
  "properties": {
    "addr:full": "109 Ballard St Worcester MA 01607",
    "addr:housenumber": "109",
    "addr:postcode": "01607",
    "addr:street": "Ballard St",
    "iso:country": "US",
    "sg:address": "109 Ballard St",
    "sg:city": "Worcester",
    "sg:classifiers": [
      {
        "category": "Home \u0026 Garden",
        "subcategory": "Building Materials",
        "type": "Retail Goods"
      }
    ],
    "sg:phone": "+1 508 757 3483",
    "sg:postcode": "01607",
    "sg:province": "MA",
    "sg:tags": [
      "glass",
      "window",
      "plate"
    ],
    "wof:name": "United Auto Glass",
    "wof:placetype": "venue"
  },
  "geometry": {"coordinates":[-71.786122,42.23093],"type":"Point"}
}
