{
  "type": "Feature",
  "properties": {
    "iso:country":"US",
    "sg:address":"59 Groton St",
    "sg:city":"Dunstable",
    "sg:classifiers":[
        {
            "category":"Professional",
            "type":"Services"
        }
    ],
    "sg:phone":"+1   ",
    "sg:postcode":"01827",
    "sg:province":"MA",
    "wof:name":"B C W Corp",
    "wof:placetype":"venue"
},
  "geometry": {"coordinates":[-71.500221,42.667873],"type":"Point"}
}