{
  "type": "Feature",
  "properties": {
    "addr:full": "12 Union Park St Boston MA 02118",
    "addr:housenumber": "12",
    "addr:postcode": "02118",
    "addr:street": "Union Park St",
    "iso:country": "US",
    "sg:address": "12 Union Park St",
    "sg:city": "Boston",
    "sg:classifiers": [
      {
        "category": "Shopping",
        "subcategory": "Clothing, Apparel, \u0026 Fashions",
        "type": "Retail Goods"
      }
    ],
    "sg:phone": "+1 617 357 5333",
    "sg:postcode": "02118",
    "sg:province": "MA",
    "sg:tags": [
      "clothing",
      "women's"
    ],
    "sg:website": "www.loocboutique.com/",
    "wof:name": "Looc Boutique",
    "wof:placetype": "venue"
  },
  "geometry": {"coordinates":[-71.070436,42.341991],"type":"Point"}
}
