{
  "type": "Feature",
  "properties": {
    "iso:country":"US",
    "sg:address":"215 W Main St",
    "sg:city":"Hyannis",
    "sg:classifiers":[
        {
            "category":"Restaurant",
            "type":"Food & Drink"
        }
    ],
    "sg:phone":"+1 508 778 8860",
    "sg:postcode":"02601",
    "sg:province":"MA",
    "sg:tags":[
        "pizza"
    ],
    "sg:website":"www.papajohns.com",
    "wof:name":"Papa John's",
    "wof:placetype":"venue"
},
  "geometry": {"coordinates":[-70.302902,41.647499],"type":"Point"}
}