{
  "type": "Feature",
  "properties": {
    "iso:country":"US",
    "sg:address":"55 Ferncroft Rd",
    "sg:city":"Danvers",
    "sg:classifiers":[
        {
            "category":"Manufacturing",
            "subcategory":"Printing",
            "type":"Manufacturing & Wholesale Goods"
        }
    ],
    "sg:phone":"+1 978 646 3900",
    "sg:postcode":"01923",
    "sg:province":"MA",
    "sg:tags":[
        "periodical"
    ],
    "wof:name":"Boston Globe",
    "wof:placetype":"venue"
},
  "geometry": {"coordinates":[-70.969255,42.595606],"type":"Point"}
}