{
  "type": "Feature",
  "properties": {
    "iso:country":"US",
    "sg:address":"25 Sampson Rd",
    "sg:city":"Huntington",
    "sg:classifiers":[
        {
            "category":"Banks & Credit Unions",
            "subcategory":"Investment Brokerage",
            "type":"Services"
        }
    ],
    "sg:phone":"+1 413 667 3118",
    "sg:postcode":"01050",
    "sg:province":"MA",
    "sg:tags":[
        "trust"
    ],
    "wof:name":"Hilltown Land Trust Inc",
    "wof:placetype":"venue"
},
  "geometry": {"coordinates":[-72.82886999999999,42.269666],"type":"Point"}
}