{
  "type": "Feature",
  "properties": {
    "addr:full":"574 Boston Ave Medford MA 02155",
    "addr:housenumber":"574",
    "addr:postcode":"02155",
    "addr:street":"Boston Ave",
    "iso:country":"US",
    "sg:address":"574 Boston Ave",
    "sg:city":"Medford",
    "sg:classifiers":[
        {
            "category":"Manufacturing",
            "subcategory":"Building Materials",
            "type":"Manufacturing & Wholesale Goods"
        },
        {
            "category":"Building & Trades",
            "subcategory":"Construction",
            "type":"Services"
        }
    ],
    "sg:phone":"+1 781 391 1411",
    "sg:postcode":"02155",
    "sg:province":"MA",
    "sg:tags":[
        "mfg",
        "woodworker"
    ],
    "wof:name":"Strokington & Co",
    "wof:placetype":"venue"
},
  "geometry": {"coordinates":[-71.114475,42.404198],"type":"Point"}
}