{
  "type": "Feature",
  "properties": {
    "addr:full": "715 Crescent St Brockton MA 02302",
    "addr:housenumber": "715",
    "addr:postcode": "02302",
    "addr:street": "Crescent St",
    "iso:country": "US",
    "sg:address": "715 Crescent St",
    "sg:city": "Brockton",
    "sg:classifiers": [
      {
        "category": "Food \u0026 Beverages",
        "subcategory": "Specialty",
        "type": "Retail Goods"
      }
    ],
    "sg:phone": "+1 508 583 1946",
    "sg:postcode": "02302",
    "sg:province": "MA",
    "sg:tags": [
      "health",
      "diet"
    ],
    "wof:name": "GNC",
    "wof:placetype": "venue"
  },
  "geometry": {"coordinates":[-70.988187,42.081402],"type":"Point"}
}
