{
  "type": "Feature",
  "properties": {
    "addr:full": "1900 W Park Dr Ste 150 Westborough MA 01581",
    "addr:housenumber": "1900",
    "addr:postcode": "01581",
    "addr:street": "W Park Dr Ste 150",
    "iso:country": "US",
    "sg:address": "1900 W Park Dr Ste 150",
    "sg:city": "Westborough",
    "sg:classifiers": [
      {
        "category": "Organizations",
        "subcategory": "Professional Association",
        "type": "Services"
      }
    ],
    "sg:phone": "+1 508 599 3422",
    "sg:postcode": "01581",
    "sg:province": "MA",
    "sg:tags": [
      "business",
      "trade"
    ],
    "sg:website": "http://www.purma.org",
    "wof:name": "Purma",
    "wof:placetype": "venue"
  },
  "geometry": {"coordinates":[-71.569939,42.281212],"type":"Point"}
}
