{
  "type": "Feature",
  "properties": {
    "addr:full":"190 E Grove St Middleboro MA 02346",
    "addr:housenumber":"190",
    "addr:postcode":"02346",
    "addr:street":"E Grove St",
    "iso:country":"US",
    "sg:address":"190 E Grove St",
    "sg:city":"Middleboro",
    "sg:classifiers":[
        {
            "category":"Professional",
            "subcategory":"Management & Consulting",
            "type":"Services"
        }
    ],
    "sg:phone":"+1 774 406 0647",
    "sg:postcode":"02346",
    "sg:province":"MA",
    "sg:tags":[
        "personnel",
        "consultant"
    ],
    "wof:name":"Darcy Development",
    "wof:placetype":"venue"
},
  "geometry": {"coordinates":[-70.875557,41.86684],"type":"Point"}
}