{
  "type": "Feature",
  "properties": {
    "iso:country":"US",
    "sg:address":"409 Upham St",
    "sg:city":"Melrose",
    "sg:classifiers":[
        {
            "category":"Place Of Worship",
            "subcategory":"Church",
            "type":"Public Place"
        },
        {
            "category":"Place Of Worship",
            "type":"Public Place"
        }
    ],
    "sg:phone":"+1 781 665 7877",
    "sg:postcode":"02176",
    "sg:province":"MA",
    "sg:tags":[
        "testament",
        "christ-new",
        "christ",
        "churches-church"
    ],
    "wof:name":"Melrose Church Of Christ",
    "wof:placetype":"venue"
},
  "geometry": {"coordinates":[-71.04569499999999,42.459422],"type":"Point"}
}