{
  "type": "Feature",
  "properties": {
    "addr:full": "409 Upham St Melrose MA 02176",
    "addr:housenumber": "409",
    "addr:postcode": "02176",
    "addr:street": "Upham St",
    "iso:country": "US",
    "ovtr:label": "Melrose Church of Christ, 409 Upham St Melrose MA US",
    "ovtr:similarity": 3.4769210815429688,
    "sg:address": "409 Upham St",
    "sg:city": "Melrose",
    "sg:classifiers": [
      {
        "category": "Place Of Worship",
        "subcategory": "Church",
        "type": "Public Place"
      },
      {
        "category": "Place Of Worship",
        "type": "Public Place"
      }
    ],
    "sg:phone": "+1 781 665 7877",
    "sg:postcode": "02176",
    "sg:province": "MA",
    "sg:tags": [
      "testament",
      "christ-new",
      "christ",
      "churches-church"
    ],
    "wof:name": "Melrose Church Of Christ",
    "wof:placetype": "venue"
  },
  "geometry": {"coordinates":[-71.045695,42.459422],"type":"Point"}
}
