{
  "type": "Feature",
  "properties": {
    "iso:country":"US",
    "sg:address":"33 Norman Ter Exd",
    "sg:city":"Feeding Hills",
    "sg:classifiers":[
        {
            "category":"Real Estate",
            "subcategory":"Real Estate Operator",
            "type":"Services"
        }
    ],
    "sg:phone":"+1 413 786 6323",
    "sg:postcode":"01030",
    "sg:province":"MA",
    "sg:tags":[
        "apartment"
    ],
    "wof:name":"Shibley Court Apartments",
    "wof:placetype":"venue"
},
  "geometry": {"coordinates":[-72.651353,42.083744],"type":"Point"}
}