{
  "type": "Feature",
  "properties": {
    "addr:full": "516 E 2nd St Boston MA 02127",
    "addr:housenumber": "516",
    "addr:postcode": "02127",
    "addr:street": "E 2Nd St",
    "iso:country": "US",
    "sg:address": "516 E 2nd St",
    "sg:city": "Boston",
    "sg:classifiers": [
      {
        "category": "Professional",
        "type": "Services"
      }
    ],
    "sg:phone": "+1 617 268 2391",
    "sg:postcode": "02127",
    "sg:province": "MA",
    "sg:tags": [
      "establishment"
    ],
    "wof:name": "Designers Draperies",
    "wof:placetype": "venue"
  },
  "geometry": {"coordinates":[-71.043214,42.33732],"type":"Point"}
}
