{
  "type": "Feature",
  "properties": {
    "addr:full": "99 Summer St Boston MA 02110",
    "addr:housenumber": "99",
    "addr:postcode": "02110",
    "addr:street": "Summer St",
    "iso:country": "US",
    "sg:address": "99 Summer St",
    "sg:city": "Boston",
    "sg:classifiers": [
      {
        "category": "Professional",
        "subcategory": "Computer Services",
        "type": "Services"
      }
    ],
    "sg:phone": "+1 617 345 0440",
    "sg:postcode": "02110",
    "sg:province": "MA",
    "sg:tags": [
      "systems-consultants",
      "designer",
      "data"
    ],
    "wof:name": "Ajilon Finance",
    "wof:placetype": "venue"
  },
  "geometry": {"coordinates":[-71.058026,42.353708],"type":"Point"}
}
