{
  "type": "Feature",
  "properties": {
    "iso:country":"US",
    "sg:address":"322 Paper Mill Rd",
    "sg:city":"Westfield",
    "sg:classifiers":[
        {
            "category":"Building & Trades",
            "subcategory":"Cleaning & Sanitation",
            "type":"Services"
        }
    ],
    "sg:phone":"+1 413 568 2967",
    "sg:postcode":"01085",
    "sg:province":"MA",
    "sg:tags":[
        "janitor"
    ],
    "wof:name":"Geneva 3 Cleaning",
    "wof:placetype":"venue"
},
  "geometry": {"coordinates":[-72.710097,42.128596],"type":"Point"}
}