{
  "type": "Feature",
  "properties": {
    "addr:full":"2344 Massachusetts Ave Cambridge MA 02140",
    "addr:housenumber":"2344",
    "addr:postcode":"02140",
    "addr:street":"Massachusetts Ave",
    "iso:country":"US",
    "sg:address":"2344 Massachusetts Ave",
    "sg:city":"Cambridge",
    "sg:classifiers":[
        {
            "category":"Food & Beverages",
            "subcategory":"Bakery",
            "type":"Retail Goods"
        }
    ],
    "sg:phone":"+1 617 354 4110",
    "sg:postcode":"02140",
    "sg:province":"MA",
    "sg:tags":[
        "donut",
        "doughnut"
    ],
    "sg:website":"www.vernaspastry.com",
    "wof:name":"Verna's Donut Shop",
    "wof:placetype":"venue"
},
  "geometry": {"coordinates":[-71.128304,42.395802],"type":"Point"}
}