{
  "type": "Feature",
  "properties": {
    "iso:country":"US",
    "sg:address":"10 Dunham Rd",
    "sg:city":"Billerica",
    "sg:classifiers":[
        {
            "category":"Wholesale",
            "subcategory":"Durable Goods & Equipment",
            "type":"Manufacturing & Wholesale Goods"
        }
    ],
    "sg:phone":"+1 978 667 6399",
    "sg:postcode":"01821",
    "sg:province":"MA",
    "sg:tags":[
        "representative",
        "manufacturer"
    ],
    "wof:name":"Edward Stephen Co",
    "wof:placetype":"venue"
},
  "geometry": {"coordinates":[-71.236599,42.519568],"type":"Point"}
}