{
  "type": "Feature",
  "properties": {
    "addr:full":"681 Main St Worcester MA 01610",
    "addr:housenumber":"681",
    "addr:postcode":"01610",
    "addr:street":"Main St",
    "iso:country":"US",
    "sg:address":"681 Main St",
    "sg:city":"Worcester",
    "sg:classifiers":[
        {
            "category":"Autos & Motor Vehicles",
            "subcategory":"Automobile Sales",
            "type":"Retail Goods"
        }
    ],
    "sg:phone":"+1 508 752 2454",
    "sg:postcode":"01610",
    "sg:province":"MA",
    "sg:tags":[
        "car",
        "dealer"
    ],
    "wof:name":"Dasilva Auto Sales",
    "wof:placetype":"venue"
},
  "geometry": {"coordinates":[-71.805938,42.259038],"type":"Point"}
}