{
  "type": "Feature",
  "properties": {
    "iso:country":"US",
    "sg:address":"45 N Catamount Hill Rd",
    "sg:city":"Colrain",
    "sg:classifiers":[
        {
            "category":"Manufacturing",
            "subcategory":"Food",
            "type":"Manufacturing & Wholesale Goods"
        }
    ],
    "sg:phone":"+1 413 624 3481",
    "sg:postcode":"01340",
    "sg:province":"MA",
    "sg:tags":[
        "winery"
    ],
    "wof:name":"Maloney & Maoloney",
    "wof:placetype":"venue"
},
  "geometry": {"coordinates":[-72.75426,42.670998],"type":"Point"}
}