{
  "type": "Feature",
  "properties": {
    "addr:full": "45 N Catamount Hill Rd Colrain MA 01340",
    "addr:housenumber": "45",
    "addr:postcode": "01340",
    "addr:street": "N Catamount Hill Rd",
    "iso:country": "US",
    "sg:address": "45 N Catamount Hill Rd",
    "sg:city": "Colrain",
    "sg:classifiers": [
      {
        "category": "Manufacturing",
        "subcategory": "Food",
        "type": "Manufacturing \u0026 Wholesale Goods"
      }
    ],
    "sg:phone": "+1 413 624 3481",
    "sg:postcode": "01340",
    "sg:province": "MA",
    "sg:tags": [
      "winery"
    ],
    "wof:name": "Maloney \u0026 Maoloney",
    "wof:placetype": "venue"
  },
  "geometry": {"coordinates":[-72.75426,42.670998],"type":"Point"}
}
