{
  "type": "Feature",
  "properties": {
    "iso:country":"US",
    "sg:address":"375 Cambridge St",
    "sg:city":"Winchester",
    "sg:classifiers":[
        {
            "category":"Retail",
            "subcategory":"Event Space",
            "type":"Services"
        }
    ],
    "sg:phone":"+1 781 729 9801",
    "sg:postcode":"01890",
    "sg:province":"MA",
    "sg:tags":[
        "venue"
    ],
    "wof:name":"Elks Lodge of Winchester",
    "wof:placetype":"venue"
},
  "geometry": {"coordinates":[-71.1605,42.4571],"type":"Point"}
}