{
  "type": "Feature",
  "properties": {
    "addr:full":"24 Front St Marion MA 02738",
    "addr:housenumber":"24",
    "addr:postcode":"02738",
    "addr:street":"Front St",
    "iso:country":"US",
    "sg:address":"24 Front St",
    "sg:city":"Marion",
    "sg:classifiers":[
        {
            "category":"Recreation",
            "type":"Entertainment"
        }
    ],
    "sg:phone":"+1 508 748 2310",
    "sg:postcode":"02738",
    "sg:province":"MA",
    "sg:tags":[
        "parks"
    ],
    "wof:name":"Recreation Dept",
    "wof:placetype":"venue"
},
  "geometry": {"coordinates":[-70.75790000000001,41.695246],"type":"Point"}
}