{
  "type": "Feature",
  "properties": {
    "addr:full": "26 Crown St Milton MA 02186",
    "addr:housenumber": "26",
    "addr:postcode": "02186",
    "addr:street": "Crown St",
    "iso:country": "US",
    "sg:address": "26 Crown St",
    "sg:city": "Milton",
    "sg:classifiers": [
      {
        "category": "Freight",
        "type": "Transportation"
      }
    ],
    "sg:phone": "+1 617 696 2816",
    "sg:postcode": "02186",
    "sg:province": "MA",
    "sg:tags": [
      "operator",
      "local",
      "landscape",
      "trucking"
    ],
    "wof:name": "Scott W Macdonald Inc",
    "wof:placetype": "venue"
  },
  "geometry": {"coordinates":[-71.095254,42.256486],"type":"Point"}
}
