{
  "type": "Feature",
  "properties": {
    "iso:country":"US",
    "sg:address":"67 Fieldstone Rd",
    "sg:city":"Taunton",
    "sg:classifiers":[
        {
            "category":"Professional",
            "subcategory":"Management & Consulting",
            "type":"Services"
        }
    ],
    "sg:phone":"+1   ",
    "sg:postcode":"02780",
    "sg:province":"MA",
    "sg:tags":[
        "business"
    ],
    "wof:name":"Robert Barbour Prof Consulting",
    "wof:placetype":"venue"
},
  "geometry": {"coordinates":[-71.145478,41.87864],"type":"Point"}
}