{
  "type": "Feature",
  "properties": {
    "addr:full": "67 Fieldstone Rd Taunton MA 02780",
    "addr:housenumber": "67",
    "addr:postcode": "02780",
    "addr:street": "Fieldstone Rd",
    "iso:country": "US",
    "sg:address": "67 Fieldstone Rd",
    "sg:city": "Taunton",
    "sg:classifiers": [
      {
        "category": "Professional",
        "subcategory": "Management \u0026 Consulting",
        "type": "Services"
      }
    ],
    "sg:phone": "+1   ",
    "sg:postcode": "02780",
    "sg:province": "MA",
    "sg:tags": [
      "business"
    ],
    "wof:name": "Robert Barbour Prof Consulting",
    "wof:placetype": "venue"
  },
  "geometry": {"coordinates":[-71.145478,41.87864],"type":"Point"}
}
