{
  "type": "Feature",
  "properties": {
    "addr:full": "191 Pawtucket Blvd Lowell MA 01854",
    "addr:housenumber": "191",
    "addr:postcode": "01854",
    "addr:street": "Pawtucket Blvd",
    "iso:country": "US",
    "sg:address": "191 Pawtucket Blvd",
    "sg:city": "Lowell",
    "sg:classifiers": [
      {
        "category": "Insurance",
        "subcategory": "Insurance Agent",
        "type": "Services"
      }
    ],
    "sg:phone": "+1 978 454 2926",
    "sg:postcode": "01854",
    "sg:province": "MA",
    "wof:name": "Byam Bros-Mahoney Insurance",
    "wof:placetype": "venue"
  },
  "geometry": {"coordinates":[-71.340831,42.643291],"type":"Point"}
}
