{
  "type": "Feature",
  "properties": {
    "addr:full": "70 Church St Whitinsville MA 01588",
    "addr:housenumber": "70",
    "addr:postcode": "01588",
    "addr:street": "Church St",
    "iso:country": "US",
    "sg:address": "70 Church St",
    "sg:city": "Whitinsville",
    "sg:classifiers": [
      {
        "category": "Wholesale",
        "subcategory": "Durable Goods \u0026 Equipment",
        "type": "Manufacturing \u0026 Wholesale Goods"
      }
    ],
    "sg:phone": "+1 508 234 0276",
    "sg:postcode": "01588",
    "sg:province": "MA",
    "sg:tags": [
      "representative",
      "manufacturer"
    ],
    "wof:name": "Whirley Industries Inc",
    "wof:placetype": "venue"
  },
  "geometry": {"coordinates":[-71.661227,42.111675],"type":"Point"}
}
