{
  "type": "Feature",
  "properties": {
    "iso:country":"US",
    "sg:address":"70 Church St",
    "sg:city":"Whitinsville",
    "sg:classifiers":[
        {
            "category":"Wholesale",
            "subcategory":"Durable Goods & Equipment",
            "type":"Manufacturing & Wholesale Goods"
        }
    ],
    "sg:phone":"+1 508 234 0276",
    "sg:postcode":"01588",
    "sg:province":"MA",
    "sg:tags":[
        "representative",
        "manufacturer"
    ],
    "wof:name":"Whirley Industries Inc",
    "wof:placetype":"venue"
},
  "geometry": {"coordinates":[-71.661227,42.111675],"type":"Point"}
}