{
  "type": "Feature",
  "properties": {
    "addr:full":"90 Banks St Cambridge MA 02138",
    "addr:housenumber":"90",
    "addr:postcode":"02138",
    "addr:street":"Banks St",
    "iso:country":"US",
    "sg:address":"90 Banks St",
    "sg:city":"Cambridge",
    "sg:classifiers":[
        {
            "category":"Manufacturing",
            "subcategory":"Electronics",
            "type":"Manufacturing & Wholesale Goods"
        },
        {
            "category":"Shopping",
            "subcategory":"Computers & Home Electronics",
            "type":"Retail Goods"
        }
    ],
    "sg:phone":"+1 617 864 3953",
    "sg:postcode":"02138",
    "sg:province":"MA",
    "sg:tags":[
        "audio-visual",
        "stereo",
        "equipment-wholesale",
        "video",
        "equipment-dealers",
        "audio",
        "manufacturer"
    ],
    "wof:name":"Conextion Systems Inc",
    "wof:placetype":"venue"
},
  "geometry": {"coordinates":[-71.1147,42.368312],"type":"Point"}
}