{
  "type": "Feature",
  "properties": {
    "addr:full": "1 W Center St Amherst MA 01062",
    "addr:housenumber": "1",
    "addr:postcode": "01062",
    "addr:street": "W Center St",
    "iso:country": "US",
    "sg:address": "1 W Center St",
    "sg:city": "Amherst",
    "sg:classifiers": [
      {
        "category": "Travel",
        "subcategory": "Hotels \u0026 Motels",
        "type": "Entertainment"
      }
    ],
    "sg:phone": "+1 413 549 6000",
    "sg:postcode": "01062",
    "sg:province": "MA",
    "wof:name": "Campus Center Hotel",
    "wof:placetype": "venue"
  },
  "geometry": {"coordinates":[-72.674369,42.333238],"type":"Point"}
}
