{
  "type": "Feature",
  "properties": {
    "addr:full": "126 Prospect St Cambridge MA 02139",
    "addr:housenumber": "126",
    "addr:postcode": "02139",
    "addr:street": "Prospect St",
    "iso:country": "US",
    "sg:address": "126 Prospect St",
    "sg:city": "Cambridge",
    "sg:classifiers": [
      {
        "category": "Manufacturing",
        "subcategory": "Metals",
        "type": "Manufacturing \u0026 Wholesale Goods"
      }
    ],
    "sg:phone": "+1 617 547 6016",
    "sg:postcode": "02139",
    "sg:province": "MA",
    "wof:name": "Wheeler Industries Inc",
    "wof:placetype": "venue"
  },
  "geometry": {"coordinates":[-71.102387,42.367367],"type":"Point"}
}
