{
  "type": "Feature",
  "properties": {
    "iso:country":"US",
    "sg:address":"59 Fountain St Ste 10",
    "sg:city":"Framingham",
    "sg:classifiers":[
        {
            "category":"Wholesale",
            "subcategory":"Office Equipment",
            "type":"Manufacturing & Wholesale Goods"
        }
    ],
    "sg:phone":"+1 508 620 0421",
    "sg:postcode":"01702",
    "sg:province":"MA",
    "sg:tags":[
        "equipment-wholesale",
        "manufacturer",
        "furniture"
    ],
    "wof:name":"Imagex Technology",
    "wof:placetype":"venue"
},
  "geometry": {"coordinates":[-71.426812,42.274994],"type":"Point"}
}