{
  "type": "Feature",
  "properties": {
    "addr:full": "15 Covey Hill Rd Reading MA 01867",
    "addr:housenumber": "15",
    "addr:postcode": "01867",
    "addr:street": "Covey Hill Rd",
    "iso:country": "US",
    "sg:address": "15 Covey Hill Rd",
    "sg:city": "Reading",
    "sg:classifiers": [
      {
        "category": "Professional",
        "subcategory": "Business Services",
        "type": "Services"
      }
    ],
    "sg:phone": "+1 781 944 6119",
    "sg:postcode": "01867",
    "sg:province": "MA",
    "sg:tags": [
      "interior",
      "consultant",
      "design",
      "decorator"
    ],
    "wof:name": "A Creative Touch",
    "wof:placetype": "venue"
  },
  "geometry": {"coordinates":[-71.122678,42.543515],"type":"Point"}
}
