{
  "type": "Feature",
  "properties": {
    "iso:country":"US",
    "sg:address":"15 Covey Hill Rd",
    "sg:city":"Reading",
    "sg:classifiers":[
        {
            "category":"Professional",
            "subcategory":"Business Services",
            "type":"Services"
        }
    ],
    "sg:phone":"+1 781 944 6119",
    "sg:postcode":"01867",
    "sg:province":"MA",
    "sg:tags":[
        "interior",
        "consultant",
        "design",
        "decorator"
    ],
    "wof:name":"A Creative Touch",
    "wof:placetype":"venue"
},
  "geometry": {"coordinates":[-71.12267799999999,42.543515],"type":"Point"}
}