{
  "type": "Feature",
  "properties": {
    "addr:full": "305 Stockbridge Rd Great Barrington MA 01230",
    "addr:housenumber": "305",
    "addr:postcode": "01230",
    "addr:street": "Stockbridge Rd",
    "iso:country": "US",
    "sg:address": "305 Stockbridge Rd",
    "sg:city": "Great Barrington",
    "sg:classifiers": [
      {
        "category": "Building \u0026 Trades",
        "subcategory": "Plumbing",
        "type": "Services"
      }
    ],
    "sg:phone": "+1 413 644 8988",
    "sg:postcode": "01230",
    "sg:province": "MA",
    "sg:tags": [
      "conditioning",
      "air",
      "system",
      "contractor"
    ],
    "wof:name": "Gennari Plumbing \u0026 Heating",
    "wof:placetype": "venue"
  },
  "geometry": {"coordinates":[-73.345636,42.210648],"type":"Point"}
}
