{
  "type": "Feature",
  "properties": {
    "addr:full": "1111 Riverdale St West Springfield MA 01089",
    "addr:housenumber": "1111",
    "addr:postcode": "01089",
    "addr:street": "Riverdale St",
    "iso:country": "US",
    "sg:address": "1111 Riverdale St",
    "sg:city": "West Springfield",
    "sg:classifiers": [
      {
        "category": "Home \u0026 Garden",
        "subcategory": "Furniture",
        "type": "Retail Goods"
      }
    ],
    "sg:phone": "+1 413 747 1717",
    "sg:postcode": "01089",
    "sg:province": "MA",
    "sg:tags": [
      "mattress"
    ],
    "wof:name": "Boston Bedding Bunk \u0026 Bedroom",
    "wof:placetype": "venue"
  },
  "geometry": {"coordinates":[-72.626121,42.138684],"type":"Point"}
}
