{
  "type": "Feature",
  "properties": {
    "iso:country":"US",
    "sg:address":"543 Lawton St",
    "sg:city":"Fall River",
    "sg:classifiers":[
        {
            "category":"Building & Trades",
            "subcategory":"Construction",
            "type":"Services"
        }
    ],
    "sg:phone":"+1 508 679 4139",
    "sg:postcode":"02721",
    "sg:province":"MA",
    "sg:tags":[
        "general",
        "contractor"
    ],
    "wof:name":"Soares Construction",
    "wof:placetype":"venue"
},
  "geometry": {"coordinates":[-71.153453,41.673887],"type":"Point"}
}