{
  "type": "Feature",
  "properties": {
    "addr:full":"120 Osgood Rd Charlton MA 01507",
    "addr:housenumber":"120",
    "addr:postcode":"01507",
    "addr:street":"Osgood Rd",
    "iso:country":"US",
    "sg:address":"120 Osgood Rd",
    "sg:city":"Charlton",
    "sg:classifiers":[
        {
            "category":"Professional",
            "type":"Services"
        }
    ],
    "sg:phone":"+1   ",
    "sg:postcode":"01507",
    "sg:province":"MA",
    "wof:name":"Excitation Inc",
    "wof:placetype":"venue"
},
  "geometry": {"coordinates":[-71.995035,42.166003],"type":"Point"}
}