{
  "type": "Feature",
  "properties": {
    "addr:full":"55 Springfield St Chicopee MA 01013",
    "addr:housenumber":"55",
    "addr:postcode":"01013",
    "addr:street":"Springfield St",
    "iso:country":"US",
    "sg:address":"55 Springfield St",
    "sg:city":"Chicopee",
    "sg:classifiers":[
        {
            "category":"Health Services",
            "subcategory":"Medical Lab",
            "type":"Services"
        }
    ],
    "sg:phone":"+1 413 592 1616",
    "sg:postcode":"01013",
    "sg:province":"MA",
    "sg:tags":[
        "laboratory"
    ],
    "wof:name":"Pioneer Dental Laboratory",
    "wof:placetype":"venue"
},
  "geometry": {"coordinates":[-72.606481,42.147999],"type":"Point"}
}