{
  "type": "Feature",
  "properties": {
    "iso:country":"US",
    "sg:address":"11 Blake Ct",
    "sg:city":"Gloucester",
    "sg:classifiers":[
        {
            "category":"Building & Trades",
            "subcategory":"Construction",
            "type":"Services"
        }
    ],
    "sg:phone":"+1   ",
    "sg:postcode":"01930",
    "sg:province":"MA",
    "sg:tags":[
        "carpentry",
        "contractor",
        "hanging"
    ],
    "wof:name":"Bay State Painters",
    "wof:placetype":"venue"
},
  "geometry": {"coordinates":[-70.64597500000001,42.614618],"type":"Point"}
}