{
  "type": "Feature",
  "properties": {
    "addr:full": "11 Blake Ct Gloucester MA 01930",
    "addr:housenumber": "11",
    "addr:postcode": "01930",
    "addr:street": "Blake Ct",
    "iso:country": "US",
    "sg:address": "11 Blake Ct",
    "sg:city": "Gloucester",
    "sg:classifiers": [
      {
        "category": "Building \u0026 Trades",
        "subcategory": "Construction",
        "type": "Services"
      }
    ],
    "sg:phone": "+1   ",
    "sg:postcode": "01930",
    "sg:province": "MA",
    "sg:tags": [
      "carpentry",
      "contractor",
      "hanging"
    ],
    "wof:name": "Bay State Painters",
    "wof:placetype": "venue"
  },
  "geometry": {"coordinates":[-70.645975,42.614618],"type":"Point"}
}
