{
  "type": "Feature",
  "properties": {
    "iso:country":"US",
    "sg:address":"37 Eldridge Ct",
    "sg:city":"Hingham",
    "sg:classifiers":[
        {
            "category":"Professional",
            "subcategory":"Computer Services",
            "type":"Services"
        }
    ],
    "sg:phone":"+1   ",
    "sg:postcode":"02043",
    "sg:province":"MA",
    "sg:tags":[
        "related"
    ],
    "wof:name":"Zack Lesko",
    "wof:placetype":"venue"
},
  "geometry": {"coordinates":[-70.88122,42.24392],"type":"Point"}
}