{
  "type": "Feature",
  "properties": {
    "iso:country":"US",
    "sg:address":"21 Park Ave",
    "sg:city":"Attleboro",
    "sg:classifiers":[
        {
            "category":"Real Estate",
            "subcategory":"Real Estate Agent",
            "type":"Services"
        }
    ],
    "sg:phone":"+1 508 223 4441",
    "sg:postcode":"02703",
    "sg:province":"MA",
    "sg:tags":[
        "agency",
        "rental"
    ],
    "wof:name":"Better Bounce Inflatables",
    "wof:placetype":"venue"
},
  "geometry": {"coordinates":[-71.279105,41.942307],"type":"Point"}
}