{
  "type": "Feature",
  "properties": {
    "addr:full":"11 Mendon St Upton MA 01568",
    "addr:housenumber":"11",
    "addr:postcode":"01568",
    "addr:street":"Mendon St",
    "iso:country":"US",
    "sg:address":"11 Mendon St",
    "sg:city":"Upton",
    "sg:classifiers":[
        {
            "category":"Professional",
            "subcategory":"Accounting & Tax Preparation",
            "type":"Services"
        }
    ],
    "sg:phone":"+1 508 529 6889",
    "sg:postcode":"01568",
    "sg:province":"MA",
    "sg:tags":[
        "accountant"
    ],
    "wof:name":"Brian Donovan CPA",
    "wof:placetype":"venue"
},
  "geometry": {"coordinates":[-71.613111,42.166763],"type":"Point"}
}