{
  "type": "Feature",
  "properties": {
    "iso:country":"US",
    "sg:address":"75 Russell St",
    "sg:city":"Quincy",
    "sg:classifiers":[
        {
            "category":"Organizations",
            "subcategory":"Religious Organization",
            "type":"Services"
        }
    ],
    "sg:phone":"+1 617 328 1622",
    "sg:postcode":"02171",
    "sg:province":"MA",
    "sg:tags":[
        "monastery",
        "convent"
    ],
    "wof:name":"Sisters Of Charity Convent",
    "wof:placetype":"venue"
},
  "geometry": {"coordinates":[-71.02899600000001,42.283627],"type":"Point"}
}