{
  "type": "Feature",
  "properties": {
    "iso:country":"US",
    "sg:address":"148 Massachusetts Ave",
    "sg:city":"Arlington",
    "sg:classifiers":[
        {
            "category":"Shopping",
            "subcategory":"Books",
            "type":"Retail Goods"
        },
        {
            "category":"Shopping",
            "subcategory":"Discount & Variety Stores",
            "type":"Retail Goods"
        }
    ],
    "sg:phone":"+1 617 308 5250",
    "sg:postcode":"02474",
    "sg:province":"MA",
    "sg:tags":[
        "mags",
        "music",
        "books",
        "video"
    ],
    "wof:name":"Store 1001",
    "wof:placetype":"venue"
},
  "geometry": {"coordinates":[-71.140731,42.404537],"type":"Point"}
}