{
  "type": "Feature",
  "properties": {
    "iso:country":"US",
    "sg:address":"19 Northbriar Rd",
    "sg:city":"Acton",
    "sg:classifiers":[
        {
            "category":"Shopping",
            "subcategory":"Florist",
            "type":"Retail Goods"
        }
    ],
    "sg:phone":"+1 978 263 2721",
    "sg:postcode":"01720",
    "sg:province":"MA",
    "wof:name":"Flower Wagon",
    "wof:placetype":"venue"
},
  "geometry": {"coordinates":[-71.409308,42.511571],"type":"Point"}
}