{
  "type": "Feature",
  "properties": {
    "iso:country":"US",
    "sg:address":"15 Day St",
    "sg:city":"Haverhill",
    "sg:classifiers":[
        {
            "category":"Real Estate",
            "subcategory":"Real Estate Agent",
            "type":"Services"
        }
    ],
    "sg:phone":"+1 978 372 2528",
    "sg:postcode":"01832",
    "sg:province":"MA",
    "wof:name":"Country & Town Realty Inc",
    "wof:placetype":"venue"
},
  "geometry": {"coordinates":[-71.103278,42.767397],"type":"Point"}
}