{
  "type": "Feature",
  "properties": {
    "addr:full":"95 Pamela Dr Swansea MA 02777",
    "addr:housenumber":"95",
    "addr:postcode":"02777",
    "addr:street":"Pamela Dr",
    "iso:country":"US",
    "sg:address":"95 Pamela Dr",
    "sg:city":"Swansea",
    "sg:classifiers":[
        {
            "category":"Professional",
            "subcategory":"Business Services",
            "type":"Services"
        }
    ],
    "sg:phone":"+1 508 679 5167",
    "sg:postcode":"02777",
    "sg:province":"MA",
    "sg:tags":[
        "organizing",
        "services-household"
    ],
    "wof:name":"Maduro S Property Management",
    "wof:placetype":"venue"
},
  "geometry": {"coordinates":[-71.247269,41.738991],"type":"Point"}
}