{
  "type": "Feature",
  "properties": {
    "addr:full": "1335 Massachusetts Ave Lunenburg MA 01462",
    "addr:housenumber": "1335",
    "addr:postcode": "01462",
    "addr:street": "Massachusetts Ave",
    "iso:country": "US",
    "ovtr:label": "Drawbridge Puppet Theatre, 1335 Massachusetts Ave Lunenburg MA US",
    "ovtr:similarity": 1.8967100381851196,
    "sg:address": "1335 Massachusetts Ave",
    "sg:city": "Lunenburg",
    "sg:classifiers": [
      {
        "category": "Arts \u0026 Performance",
        "subcategory": "Theater",
        "type": "Entertainment"
      }
    ],
    "sg:phone": "+1 978 582 6565",
    "sg:postcode": "01462",
    "sg:province": "MA",
    "wof:name": "Drawbridge Puppet Theatre",
    "wof:placetype": "venue"
  },
  "geometry": {"coordinates":[-71.707769,42.599148],"type":"Point"}
}
