{
  "type": "Feature",
  "properties": {
    "addr:full":"974 Blue Hill Avenue Dorchester Center MA 02124",
    "addr:housenumber":"974",
    "addr:postcode":"02124",
    "addr:street":"Blue Hill Avenue",
    "iso:country":"US",
    "sg:address":"974 Blue Hill Avenue",
    "sg:city":"Dorchester Center",
    "sg:classifiers":[
        {
            "category":"Social Services",
            "subcategory":"Child Care",
            "type":"Services"
        },
        {
            "category":"Sports & Exercise",
            "subcategory":"Gym",
            "type":"Entertainment"
        }
    ],
    "sg:phone":"+1 617 446 0214",
    "sg:postcode":"02124",
    "sg:province":"MA",
    "sg:tags":[
        "trainer",
        "day"
    ],
    "wof:name":"Kids Choice Preschool",
    "wof:placetype":"venue"
},
  "geometry": {"coordinates":[-71.089437,42.290486],"type":"Point"}
}