{
  "type": "Feature",
  "properties": {
    "iso:country":"US",
    "sg:address":"247 Newman Ave",
    "sg:city":"Seekonk",
    "sg:classifiers":[
        {
            "category":"Food & Beverages",
            "subcategory":"Meat & Fish",
            "type":"Retail Goods"
        }
    ],
    "sg:phone":"+1 508 336 7331",
    "sg:postcode":"02771",
    "sg:province":"MA",
    "sg:tags":[
        "seafood",
        "market"
    ],
    "wof:name":"Great Island Seafood",
    "wof:placetype":"venue"
},
  "geometry": {"coordinates":[-71.332802,41.8484],"type":"Point"}
}