{
  "type": "Feature",
  "properties": {
    "addr:full": "247 Newman Ave Seekonk MA 02771",
    "addr:housenumber": "247",
    "addr:postcode": "02771",
    "addr:street": "Newman Ave",
    "iso:country": "US",
    "sg:address": "247 Newman Ave",
    "sg:city": "Seekonk",
    "sg:classifiers": [
      {
        "category": "Food \u0026 Beverages",
        "subcategory": "Meat \u0026 Fish",
        "type": "Retail Goods"
      }
    ],
    "sg:phone": "+1 508 336 7331",
    "sg:postcode": "02771",
    "sg:province": "MA",
    "sg:tags": [
      "seafood",
      "market"
    ],
    "wof:name": "Great Island Seafood",
    "wof:placetype": "venue"
  },
  "geometry": {"coordinates":[-71.332802,41.8484],"type":"Point"}
}
