{
  "type": "Feature",
  "properties": {
    "addr:full": "29 N Main St Middleboro MA 02346",
    "addr:housenumber": "29",
    "addr:postcode": "02346",
    "addr:street": "N Main St",
    "iso:country": "US",
    "sg:address": "29 N Main St",
    "sg:city": "Middleboro",
    "sg:classifiers": [
      {
        "category": "Restaurant",
        "type": "Food \u0026 Drink"
      }
    ],
    "sg:phone": "+1 508 947 7438",
    "sg:postcode": "02346",
    "sg:province": "MA",
    "sg:tags": [
      "pizza"
    ],
    "wof:name": "Middleboro House Of Pizza",
    "wof:placetype": "venue"
  },
  "geometry": {"coordinates":[-70.90857,41.892819],"type":"Point"}
}
