{
  "type": "Feature",
  "properties": {
    "iso:country":"US",
    "sg:address":"143 Newbury St",
    "sg:city":"Boston",
    "sg:classifiers":[
        {
            "category":"Professional",
            "subcategory":"Lawyer & Legal Services",
            "type":"Services"
        }
    ],
    "sg:phone":"+1 617 424 8780",
    "sg:postcode":"02116",
    "sg:province":"MA",
    "sg:tags":[
        "attorney"
    ],
    "wof:name":"David F Cavers",
    "wof:placetype":"venue"
},
  "geometry": {"coordinates":[-71.075952,42.351474],"type":"Point"}
}