{
  "type": "Feature",
  "properties": {
    "addr:full": "11 Baker Rd Salisbury MA 01952",
    "addr:housenumber": "11",
    "addr:postcode": "01952",
    "addr:street": "Baker Rd",
    "iso:country": "US",
    "sg:address": "11 Baker Rd",
    "sg:city": "Salisbury",
    "sg:classifiers": [
      {
        "category": "Building \u0026 Trades",
        "subcategory": "Construction",
        "type": "Services"
      }
    ],
    "sg:phone": "+1 978 462 8878",
    "sg:postcode": "01952",
    "sg:province": "MA",
    "sg:tags": [
      "general",
      "contractor"
    ],
    "wof:name": "Emery Lake Carpenter Inc",
    "wof:placetype": "venue"
  },
  "geometry": {"coordinates":[-70.895446,42.854739],"type":"Point"}
}
