{
  "type": "Feature",
  "properties": {
    "iso:country":"US",
    "sg:address":"11 Baker Rd",
    "sg:city":"Salisbury",
    "sg:classifiers":[
        {
            "category":"Building & Trades",
            "subcategory":"Construction",
            "type":"Services"
        }
    ],
    "sg:phone":"+1 978 462 8878",
    "sg:postcode":"01952",
    "sg:province":"MA",
    "sg:tags":[
        "general",
        "contractor"
    ],
    "wof:name":"Emery Lake Carpenter Inc",
    "wof:placetype":"venue"
},
  "geometry": {"coordinates":[-70.89544600000001,42.854739],"type":"Point"}
}