{
  "type": "Feature",
  "properties": {
    "iso:country":"US",
    "sg:address":"154 Horn Pond Brook Rd",
    "sg:city":"Winchester",
    "sg:classifiers":[
        {
            "category":"Education",
            "subcategory":"School",
            "type":"Public Place"
        }
    ],
    "sg:phone":"+1 781 721 7000",
    "sg:postcode":"01890",
    "sg:province":"MA",
    "wof:name":"Winchester School District",
    "wof:placetype":"venue"
},
  "geometry": {"coordinates":[-71.148793,42.460918],"type":"Point"}
}