{
  "type": "Feature",
  "properties": {
    "addr:full": "580 Ferry St Marshfield MA 02050",
    "addr:housenumber": "580",
    "addr:postcode": "02050",
    "addr:street": "Ferry St",
    "iso:country": "US",
    "sg:address": "580 Ferry St",
    "sg:city": "Marshfield",
    "sg:classifiers": [
      {
        "category": "Professional",
        "subcategory": "Management \u0026 Consulting",
        "type": "Services"
      }
    ],
    "sg:phone": "+1   ",
    "sg:postcode": "02050",
    "sg:province": "MA",
    "sg:tags": [
      "business"
    ],
    "wof:name": "Rfg Consulting Inc",
    "wof:placetype": "venue"
  },
  "geometry": {"coordinates":[-70.708545,42.119958],"type":"Point"}
}
