{
  "type": "Feature",
  "properties": {
    "iso:country":"US",
    "sg:address":"580 Ferry St",
    "sg:city":"Marshfield",
    "sg:classifiers":[
        {
            "category":"Professional",
            "subcategory":"Management & Consulting",
            "type":"Services"
        }
    ],
    "sg:phone":"+1   ",
    "sg:postcode":"02050",
    "sg:province":"MA",
    "sg:tags":[
        "business"
    ],
    "wof:name":"Rfg Consulting Inc",
    "wof:placetype":"venue"
},
  "geometry": {"coordinates":[-70.708545,42.119958],"type":"Point"}
}