{
  "type": "Feature",
  "properties": {
    "iso:country":"US",
    "sg:address":"182 Arlington Street",
    "sg:city":"Watertown",
    "sg:classifiers":[
        {
            "category":"Place Of Worship",
            "subcategory":"Church",
            "type":"Public Place"
        },
        {
            "category":"Place Of Worship",
            "type":"Public Place"
        },
        {
            "category":"Organizations",
            "subcategory":"Religious Organization",
            "type":"Services"
        }
    ],
    "sg:phone":"+1 617 924 1778",
    "sg:postcode":"02472",
    "sg:province":"MA",
    "sg:tags":[
        "churches-evangelical",
        "denomination",
        "covenant",
        "churches-interdenominational",
        "churches-covenant",
        "churches-various"
    ],
    "sg:website":"www.watertownevangelicalchurch.org",
    "wof:name":"Watertown Evangelical Church",
    "wof:placetype":"venue"
},
  "geometry": {"coordinates":[-71.15583700000001,42.36788],"type":"Point"}
}