{
  "type": "Feature",
  "properties": {
    "addr:full": "182 Arlington Street Watertown MA 02472",
    "addr:housenumber": "182",
    "addr:postcode": "02472",
    "addr:street": "Arlington Street",
    "iso:country": "US",
    "ovtr:label": "Watertown Evangelical Church, 182 Arlington St Watertown MA US",
    "ovtr:similarity": 3.0385820865631104,
    "sg:address": "182 Arlington Street",
    "sg:city": "Watertown",
    "sg:classifiers": [
      {
        "category": "Place Of Worship",
        "subcategory": "Church",
        "type": "Public Place"
      },
      {
        "category": "Place Of Worship",
        "type": "Public Place"
      },
      {
        "category": "Organizations",
        "subcategory": "Religious Organization",
        "type": "Services"
      }
    ],
    "sg:phone": "+1 617 924 1778",
    "sg:postcode": "02472",
    "sg:province": "MA",
    "sg:tags": [
      "churches-evangelical",
      "denomination",
      "covenant",
      "churches-interdenominational",
      "churches-covenant",
      "churches-various"
    ],
    "sg:website": "www.watertownevangelicalchurch.org",
    "wof:name": "Watertown Evangelical Church",
    "wof:placetype": "venue"
  },
  "geometry": {"coordinates":[-71.155837,42.36788],"type":"Point"}
}
