{
  "type": "Feature",
  "properties": {
    "addr:full": "989 River St Hyde Park MA 02136",
    "addr:housenumber": "989",
    "addr:postcode": "02136",
    "addr:street": "River St",
    "iso:country": "US",
    "sg:address": "989 River St",
    "sg:city": "Hyde Park",
    "sg:classifiers": [
      {
        "category": "Personal",
        "subcategory": "Barber",
        "type": "Services"
      }
    ],
    "sg:phone": "+1 617 361 9820",
    "sg:postcode": "02136",
    "sg:province": "MA",
    "wof:name": "Classic Cuts",
    "wof:placetype": "venue"
  },
  "geometry": {"coordinates":[-71.114551,42.261015],"type":"Point"}
}
