{
  "type": "Feature",
  "properties": {
    "addr:full": "51 Old Marlboro Rd Maynard MA 01754",
    "addr:housenumber": "51",
    "addr:postcode": "01754",
    "addr:street": "Old Marlboro Rd",
    "iso:country": "US",
    "sg:address": "51 Old Marlboro Rd",
    "sg:city": "Maynard",
    "sg:classifiers": [
      {
        "category": "Place Of Worship",
        "subcategory": "Church",
        "type": "Public Place"
      },
      {
        "category": "Place Of Worship",
        "type": "Public Place"
      }
    ],
    "sg:phone": "+1 978 461 0922",
    "sg:postcode": "01754",
    "sg:province": "MA",
    "sg:tags": [
      "nazarene",
      "churches-church",
      "churches-nazarene"
    ],
    "wof:name": "New Hope Fellowship-A Church of The Nazarene",
    "wof:placetype": "venue"
  },
  "geometry": {"coordinates":[-71.445924,42.416429],"type":"Point"}
}
