{
  "type": "Feature",
  "properties": {
    "iso:country":"US",
    "sg:address":"12 Mattson Ave",
    "sg:city":"Worcester",
    "sg:classifiers":[
        {
            "category":"Shopping",
            "subcategory":"Clothing, Apparel, & Fashions",
            "type":"Retail Goods"
        }
    ],
    "sg:phone":"+1 508 753 8882",
    "sg:postcode":"01606",
    "sg:province":"MA",
    "sg:tags":[
        "clothing",
        "store"
    ],
    "sg:website":"http://www.wormtown.com",
    "wof:name":"Wormtown Trading Co",
    "wof:placetype":"venue"
},
  "geometry": {"coordinates":[-71.805252,42.299119],"type":"Point"}
}