{
  "type": "Feature",
  "properties": {
    "iso:country":"US",
    "sg:address":"319 Broadway",
    "sg:city":"Lynn",
    "sg:classifiers":[
        {
            "category":"Personal",
            "subcategory":"Beauty Salon",
            "type":"Services"
        }
    ],
    "sg:phone":"+1 781 593 1844",
    "sg:postcode":"01904",
    "sg:province":"MA",
    "wof:name":"Lillian's Beauty Shop",
    "wof:placetype":"venue"
},
  "geometry": {"coordinates":[-70.95993300000001,42.484719],"type":"Point"}
}