{
  "type": "Feature",
  "properties": {
    "addr:full": "319 Broadway Lynn MA 01904",
    "addr:housenumber": "319",
    "addr:postcode": "01904",
    "addr:street": "Broadway",
    "iso:country": "US",
    "sg:address": "319 Broadway",
    "sg:city": "Lynn",
    "sg:classifiers": [
      {
        "category": "Personal",
        "subcategory": "Beauty Salon",
        "type": "Services"
      }
    ],
    "sg:phone": "+1 781 593 1844",
    "sg:postcode": "01904",
    "sg:province": "MA",
    "wof:name": "Lillian's Beauty Shop",
    "wof:placetype": "venue"
  },
  "geometry": {"coordinates":[-70.959933,42.484719],"type":"Point"}
}
