{
  "type": "Feature",
  "properties": {
    "iso:country":"US",
    "sg:address":"49 Cedar St",
    "sg:city":"Waltham",
    "sg:classifiers":[
        {
            "category":"Building & Trades",
            "subcategory":"Electrical",
            "type":"Services"
        }
    ],
    "sg:phone":"+1 781 894 7184",
    "sg:postcode":"02453",
    "sg:province":"MA",
    "sg:tags":[
        "electric",
        "contractor"
    ],
    "wof:name":"Norman E Kenney Co",
    "wof:placetype":"venue"
},
  "geometry": {"coordinates":[-71.228082,42.366915],"type":"Point"}
}