{
  "type": "Feature",
  "properties": {
    "addr:full": "6 Republic Rd North Billerica MA 01862",
    "addr:housenumber": "6",
    "addr:postcode": "01862",
    "addr:street": "Republic Rd",
    "iso:country": "US",
    "sg:address": "6 Republic Rd",
    "sg:city": "North Billerica",
    "sg:classifiers": [
      {
        "category": "Building \u0026 Trades",
        "subcategory": "Construction",
        "type": "Services"
      }
    ],
    "sg:phone": "+1 978 663 0724",
    "sg:postcode": "01862",
    "sg:province": "MA",
    "sg:tags": [
      "designer",
      "dealer",
      "pool",
      "swimming"
    ],
    "wof:name": "Andrews Gunite Co Inc",
    "wof:placetype": "venue"
  },
  "geometry": {"coordinates":[-71.301407,42.558834],"type":"Point"}
}
