{
  "type": "Feature",
  "properties": {
    "addr:full":"125 Essex St Lawrence MA 01840",
    "addr:housenumber":"125",
    "addr:postcode":"01840",
    "addr:street":"Essex St",
    "iso:country":"US",
    "sg:address":"125 Essex St",
    "sg:city":"Lawrence",
    "sg:classifiers":[
        {
            "category":"Wholesale",
            "subcategory":"Vending Machines",
            "type":"Manufacturing & Wholesale Goods"
        }
    ],
    "sg:phone":"+1 978 686 6353",
    "sg:postcode":"01840",
    "sg:province":"MA",
    "sg:tags":[
        "operator",
        "commercial"
    ],
    "wof:name":"Diamond Music & Vending",
    "wof:placetype":"venue"
},
  "geometry": {"coordinates":[-71.156007,42.707812],"type":"Point"}
}