{
  "type": "Feature",
  "properties": {
    "addr:full": "119 Hampshire St Cambridge MA 02139",
    "addr:housenumber": "119",
    "addr:postcode": "02139",
    "addr:street": "Hampshire St",
    "iso:country": "US",
    "sg:address": "119 Hampshire St",
    "sg:city": "Cambridge",
    "sg:classifiers": [
      {
        "category": "Building \u0026 Trades",
        "subcategory": "Locksmith",
        "type": "Services"
      }
    ],
    "sg:phone": "+1 617 914 0570",
    "sg:postcode": "02139",
    "sg:province": "MA",
    "sg:tags": [
      "key"
    ],
    "wof:name": "Anywhere A Locksmith Service",
    "wof:placetype": "venue"
  },
  "geometry": {"coordinates":[-71.096073,42.370036],"type":"Point"}
}
