{
  "type": "Feature",
  "properties": {
    "addr:full":"44 Sunset Ln Attleboro MA 02703",
    "addr:housenumber":"44",
    "addr:postcode":"02703",
    "addr:street":"Sunset Ln",
    "iso:country":"US",
    "sg:address":"44 Sunset Ln",
    "sg:city":"Attleboro",
    "sg:classifiers":[
        {
            "category":"Professional",
            "subcategory":"Management & Consulting",
            "type":"Services"
        }
    ],
    "sg:phone":"+1 508 223 2884",
    "sg:postcode":"02703",
    "sg:province":"MA",
    "sg:tags":[
        "consultant",
        "business"
    ],
    "wof:name":"For Profit",
    "wof:placetype":"venue"
},
  "geometry": {"coordinates":[-71.270853,41.909472],"type":"Point"}
}