{
  "type": "Feature",
  "properties": {
    "addr:full":"15 Ruthellen Rd Framingham MA 01701",
    "addr:housenumber":"15",
    "addr:postcode":"01701",
    "addr:street":"Ruthellen Rd",
    "iso:country":"US",
    "sg:address":"15 Ruthellen Rd",
    "sg:city":"Framingham",
    "sg:classifiers":[
        {
            "category":"Building & Trades",
            "subcategory":"Construction",
            "type":"Services"
        }
    ],
    "sg:phone":"+1   ",
    "sg:postcode":"01701",
    "sg:province":"MA",
    "sg:tags":[
        "hanging",
        "contractor"
    ],
    "wof:name":"Nobscot Painting",
    "wof:placetype":"venue"
},
  "geometry": {"coordinates":[-71.44185299999999,42.316478],"type":"Point"}
}