{
  "type": "Feature",
  "properties": {
    "iso:country":"US",
    "sg:address":"6 Hartford St",
    "sg:city":"Dorchester",
    "sg:classifiers":[
        {
            "category":"Professional",
            "subcategory":"Management & Consulting",
            "type":"Services"
        }
    ],
    "sg:phone":"+1 617 442 4506",
    "sg:postcode":"02125",
    "sg:province":"MA",
    "sg:tags":[
        "consultant",
        "training"
    ],
    "wof:name":"Cox Technology Training",
    "wof:placetype":"venue"
},
  "geometry": {"coordinates":[-71.074243,42.318239],"type":"Point"}
}