{
  "type": "Feature",
  "properties": {
    "addr:full": "6 Hartford St Dorchester MA 02125",
    "addr:housenumber": "6",
    "addr:postcode": "02125",
    "addr:street": "Hartford St",
    "iso:country": "US",
    "sg:address": "6 Hartford St",
    "sg:city": "Dorchester",
    "sg:classifiers": [
      {
        "category": "Professional",
        "subcategory": "Management \u0026 Consulting",
        "type": "Services"
      }
    ],
    "sg:phone": "+1 617 442 4506",
    "sg:postcode": "02125",
    "sg:province": "MA",
    "sg:tags": [
      "consultant",
      "training"
    ],
    "wof:name": "Cox Technology Training",
    "wof:placetype": "venue"
  },
  "geometry": {"coordinates":[-71.074243,42.318239],"type":"Point"}
}
