{
  "type": "Feature",
  "properties": {
    "addr:full": "1135 Washington St Holliston MA 01746",
    "addr:housenumber": "1135",
    "addr:postcode": "01746",
    "addr:street": "Washington St",
    "iso:country": "US",
    "sg:address": "1135 Washington St",
    "sg:city": "Holliston",
    "sg:classifiers": [
      {
        "category": "Shopping",
        "subcategory": "Used Merchandise",
        "type": "Retail Goods"
      }
    ],
    "sg:phone": "+1 508 429 8989",
    "sg:postcode": "01746",
    "sg:province": "MA",
    "sg:tags": [
      "antique"
    ],
    "wof:name": "J D Antiques",
    "wof:placetype": "venue"
  },
  "geometry": {"coordinates":[-71.438013,42.190435],"type":"Point"}
}
