{
  "type": "Feature",
  "properties": {
    "addr:full": "387 Taylor St Springfield MA 01105",
    "addr:housenumber": "387",
    "addr:postcode": "01105",
    "addr:street": "Taylor St",
    "iso:country": "US",
    "ovtr:label": "Mastroianni Auto Body, 387 Taylor St Springfield MA US",
    "ovtr:similarity": 1.9526569843292236,
    "sg:address": "387 Taylor St",
    "sg:city": "Springfield",
    "sg:classifiers": [
      {
        "category": "Retail",
        "subcategory": "Auto Repair",
        "type": "Services"
      }
    ],
    "sg:phone": "+1 413 733 9477",
    "sg:postcode": "01105",
    "sg:province": "MA",
    "sg:tags": [
      "body",
      "automobile",
      "painting"
    ],
    "wof:name": "Mastroianni Auto Body",
    "wof:placetype": "venue"
  },
  "geometry": {"coordinates":[-72.586905,42.109812],"type":"Point"}
}
