{
  "type": "Feature",
  "properties": {
    "addr:full":"380 E Main St Milford MA 01757",
    "addr:housenumber":"380",
    "addr:postcode":"01757",
    "addr:street":"E Main St",
    "iso:country":"US",
    "sg:address":"380 E Main St",
    "sg:city":"Milford",
    "sg:classifiers":[
        {
            "category":"Restaurant",
            "type":"Food & Drink"
        }
    ],
    "sg:phone":"+1 508 478 1222",
    "sg:postcode":"01757",
    "sg:province":"MA",
    "sg:tags":[
        "caterer"
    ],
    "wof:name":"Classic Delihaus",
    "wof:placetype":"venue"
},
  "geometry": {"coordinates":[-71.48915100000001,42.153793],"type":"Point"}
}