{
  "type": "Feature",
  "properties": {
    "iso:country":"US",
    "sg:address":"105 Hamilton St Apt B",
    "sg:city":"Belchertown",
    "sg:classifiers":[
        {
            "category":"Home & Garden",
            "subcategory":"Carpets & Floor Coverings",
            "type":"Retail Goods"
        }
    ],
    "sg:phone":"+1 413 301 4214",
    "sg:postcode":"01007",
    "sg:province":"MA",
    "sg:tags":[
        "material"
    ],
    "wof:name":"Jh Hardwood Flooring",
    "wof:placetype":"venue"
},
  "geometry": {"coordinates":[-72.424949,42.29046],"type":"Point"}
}