{
  "type": "Feature",
  "properties": {
    "addr:full":"25 Brittany Ln North Dartmouth MA 02747",
    "addr:housenumber":"25",
    "addr:postcode":"02747",
    "addr:street":"Brittany Ln",
    "iso:country":"US",
    "sg:address":"25 Brittany Ln",
    "sg:city":"North Dartmouth",
    "sg:classifiers":[
        {
            "category":"Farming",
            "subcategory":"Fish & Marine Products",
            "type":"Manufacturing & Wholesale Goods"
        }
    ],
    "sg:phone":"+1   ",
    "sg:postcode":"02747",
    "sg:province":"MA",
    "wof:name":"Aurora Northern",
    "wof:placetype":"venue"
},
  "geometry": {"coordinates":[-70.99003999999999,41.704627],"type":"Point"}
}