{
  "type": "Feature",
  "properties": {
    "iso:country":"US",
    "sg:address":"490 Commonwealth Ave",
    "sg:city":"Boston",
    "sg:classifiers":[
        {
            "category":"Professional",
            "subcategory":"Computer Services",
            "type":"Services"
        }
    ],
    "sg:phone":"+1 617 859 1704",
    "sg:postcode":"02215",
    "sg:province":"MA",
    "sg:tags":[
        "consultant",
        "designer",
        "programing",
        "custom"
    ],
    "wof:name":"Rose Ashara Unlimited",
    "wof:placetype":"venue"
},
  "geometry": {"coordinates":[-71.093233,42.348763],"type":"Point"}
}