{
  "type": "Feature",
  "properties": {
    "addr:full":"102 Ellery St Cambridge MA 02138",
    "addr:housenumber":"102",
    "addr:postcode":"02138",
    "addr:street":"Ellery St",
    "iso:country":"US",
    "sg:address":"102 Ellery St",
    "sg:city":"Cambridge",
    "sg:classifiers":[
        {
            "category":"Professional",
            "subcategory":"Art Services",
            "type":"Services"
        }
    ],
    "sg:phone":"+1 617 547 6892",
    "sg:postcode":"02138",
    "sg:province":"MA",
    "sg:tags":[
        "sculptor"
    ],
    "wof:name":"John Tagiuri Studios",
    "wof:placetype":"venue"
},
  "geometry": {"coordinates":[-71.10946300000001,42.373112],"type":"Point"}
}