{
  "type": "Feature",
  "properties": {
    "addr:full":"118 Beacon St Boston MA 02116",
    "addr:housenumber":"118",
    "addr:postcode":"02116",
    "addr:street":"Beacon St",
    "iso:country":"US",
    "sg:address":"118 Beacon St",
    "sg:city":"Boston",
    "sg:classifiers":[
        {
            "category":"Professional",
            "subcategory":"Management & Consulting",
            "type":"Services"
        }
    ],
    "sg:phone":"+1   ",
    "sg:postcode":"02116",
    "sg:province":"MA",
    "wof:name":"Sodexho Operations Llc (de)",
    "wof:placetype":"venue"
},
  "geometry": {"coordinates":[-71.074095,42.355166],"type":"Point"}
}