{
  "type": "Feature",
  "properties": {
    "addr:full": "389 Canton Ave Milton MA 02186",
    "addr:housenumber": "389",
    "addr:postcode": "02186",
    "addr:street": "Canton Ave",
    "iso:country": "US",
    "sg:address": "389 Canton Ave",
    "sg:city": "Milton",
    "sg:classifiers": [
      {
        "category": "Health Services",
        "subcategory": "Optometrist",
        "type": "Services"
      }
    ],
    "sg:phone": "+1 617 698 6700",
    "sg:postcode": "02186",
    "sg:province": "MA",
    "wof:name": "Rodney L Immerman",
    "wof:placetype": "venue"
  },
  "geometry": {"coordinates":[-71.076523,42.256962],"type":"Point"}
}
