{
  "type": "Feature",
  "properties": {
    "addr:full": "95 Central St Wellesley MA 02482",
    "addr:housenumber": "95",
    "addr:postcode": "02482",
    "addr:street": "Central St",
    "iso:country": "US",
    "ovtr:label": "Grettacole, 95 Central St Wellesley MA US",
    "ovtr:similarity": 2.5354080200195312,
    "sg:address": "95 Central St",
    "sg:city": "Wellesley",
    "sg:classifiers": [
      {
        "category": "Personal",
        "subcategory": "Beauty Salon",
        "type": "Services"
      }
    ],
    "sg:phone": "+1 781 237 5201",
    "sg:postcode": "02482",
    "sg:province": "MA",
    "sg:tags": [
      "spa",
      "day"
    ],
    "wof:name": "Grettacole",
    "wof:placetype": "venue"
  },
  "geometry": {"coordinates":[-71.298383,42.295912],"type":"Point"}
}
