{
  "type": "Feature",
  "properties": {
    "addr:full":"269 Middlesex Avenue Medford MA 02155",
    "addr:housenumber":"269",
    "addr:postcode":"02155",
    "addr:street":"Middlesex Avenue",
    "iso:country":"US",
    "sg:address":"269 Middlesex Avenue",
    "sg:city":"Medford",
    "sg:classifiers":[
        {
            "category":"Arts & Performance",
            "subcategory":"Arts Center",
            "type":"Entertainment"
        },
        {
            "category":"Education",
            "subcategory":"Special Training",
            "type":"Public Place"
        }
    ],
    "sg:phone":"+1 781 396 2066",
    "sg:postcode":"02155",
    "sg:province":"MA",
    "sg:tags":[
        "school",
        "performing"
    ],
    "wof:name":"Sullivan's Cheryl A School of Dance",
    "wof:placetype":"venue"
},
  "geometry": {"coordinates":[-71.07911900000001,42.412122],"type":"Point"}
}