{
  "type": "Feature",
  "properties": {
    "iso:country":"US",
    "sg:address":"50 Rowes Wharf",
    "sg:city":"Boston",
    "sg:classifiers":[
        {
            "category":"Professional",
            "subcategory":"Lawyer & Legal Services",
            "type":"Services"
        }
    ],
    "sg:phone":"+1   ",
    "sg:postcode":"02110",
    "sg:province":"MA",
    "wof:name":"Ruben and Rudmen",
    "wof:placetype":"venue"
},
  "geometry": {"coordinates":[-71.05001900000001,42.357087],"type":"Point"}
}