{
  "type": "Feature",
  "properties": {
    "addr:full": "68 Messenger St Plainville MA 02762",
    "addr:housenumber": "68",
    "addr:postcode": "02762",
    "addr:street": "Messenger St",
    "iso:country": "US",
    "sg:address": "68 Messenger St",
    "sg:city": "Plainville",
    "sg:classifiers": [
      {
        "category": "Education",
        "subcategory": "School",
        "type": "Public Place"
      }
    ],
    "sg:phone": "+1 508 699 1304",
    "sg:postcode": "02762",
    "sg:province": "MA",
    "wof:name": "Anns Ware Jackson School",
    "wof:placetype": "venue"
  },
  "geometry": {"coordinates":[-71.303863,42.011408],"type":"Point"}
}
