{
  "type": "Feature",
  "properties": {
    "iso:country":"US",
    "sg:address":"68 Messenger St",
    "sg:city":"Plainville",
    "sg:classifiers":[
        {
            "category":"Education",
            "subcategory":"School",
            "type":"Public Place"
        }
    ],
    "sg:phone":"+1 508 699 1304",
    "sg:postcode":"02762",
    "sg:province":"MA",
    "wof:name":"Anns Ware Jackson School",
    "wof:placetype":"venue"
},
  "geometry": {"coordinates":[-71.30386300000001,42.011408],"type":"Point"}
}