{
  "type": "Feature",
  "properties": {
    "addr:full": "2001 Boston Rd Wilbraham MA 01095",
    "addr:housenumber": "2001",
    "addr:postcode": "01095",
    "addr:street": "Boston Rd",
    "iso:country": "US",
    "sg:address": "2001 Boston Rd",
    "sg:city": "Wilbraham",
    "sg:classifiers": [
      {
        "category": "Manufacturing",
        "subcategory": "Tools \u0026 Machinery",
        "type": "Manufacturing \u0026 Wholesale Goods"
      },
      {
        "category": "Retail",
        "subcategory": "Repair Shop",
        "type": "Services"
      },
      {
        "category": "Home \u0026 Garden",
        "subcategory": "Hardware",
        "type": "Retail Goods"
      },
      {
        "category": "Home \u0026 Garden",
        "subcategory": "Building Materials",
        "type": "Retail Goods"
      },
      {
        "category": "Wholesale",
        "subcategory": "Painting Supplies",
        "type": "Manufacturing \u0026 Wholesale Goods"
      },
      {
        "category": "Retail",
        "subcategory": "Auto Rental",
        "type": "Services"
      },
      {
        "category": "Building \u0026 Trades",
        "subcategory": "Equipment Rental",
        "type": "Services"
      }
    ],
    "sg:phone": "+1 413 543 8100",
    "sg:postcode": "01095",
    "sg:province": "MA",
    "sg:tags": [
      "yard",
      "rug",
      "improvement",
      "paint",
      "truck",
      "cleaning",
      "tools-renting",
      "contractors'",
      "store",
      "carpet"
    ],
    "sg:website": "http://clk.atdmt.com/IWC/go/266744407/direct/01/",
    "wof:name": "The Home Depot Tool Rental",
    "wof:placetype": "venue"
  },
  "geometry": {"coordinates":[-72.476462,42.149143],"type":"Point"}
}
