{
  "type": "Feature",
  "properties": {
    "iso:country":"US",
    "sg:address":"55 Saltonstall Rd",
    "sg:city":"Haverhill",
    "sg:classifiers":[
        {
            "category":"Organizations",
            "subcategory":"Religious Organization",
            "type":"Services"
        }
    ],
    "sg:phone":"+1 978 372 6322",
    "sg:postcode":"01830",
    "sg:province":"MA",
    "sg:tags":[
        "monastery",
        "convent"
    ],
    "wof:name":"Sisters Of St Joseph",
    "wof:placetype":"venue"
},
  "geometry": {"coordinates":[-71.06932500000001,42.784816],"type":"Point"}
}