{
  "type": "Feature",
  "properties": {
    "addr:full": "190 Newbury St Boston MA 02116",
    "addr:housenumber": "190",
    "addr:postcode": "02116",
    "addr:street": "Newbury St",
    "iso:country": "US",
    "ovtr:label": "Stephanie's On Newbury, 190 Newbury St Boston MA US",
    "ovtr:similarity": 2.294110059738159,
    "sg:address": "190 Newbury St",
    "sg:city": "Boston",
    "sg:classifiers": [
      {
        "category": "Restaurant",
        "type": "Food \u0026 Drink"
      }
    ],
    "sg:phone": "+1 617 236 0990",
    "sg:postcode": "02116",
    "sg:province": "MA",
    "sg:tags": [
      "traditional",
      "new",
      "american",
      "brunch",
      "breakfast"
    ],
    "sg:website": "www.stephaniesonnewbury.com",
    "wof:name": "Stephanie's On Newbury",
    "wof:placetype": "venue"
  },
  "geometry": {"coordinates":[-71.079498,42.350498],"type":"Point"}
}
