{
  "type": "Feature",
  "properties": {
    "iso:country":"US",
    "sg:address":"190 Newbury St",
    "sg:city":"Boston",
    "sg:classifiers":[
        {
            "category":"Restaurant",
            "type":"Food & Drink"
        }
    ],
    "sg:phone":"+1 617 236 0990",
    "sg:postcode":"02116",
    "sg:province":"MA",
    "sg:tags":[
        "traditional",
        "new",
        "american",
        "brunch",
        "breakfast"
    ],
    "sg:website":"www.stephaniesonnewbury.com",
    "wof:name":"Stephanie's On Newbury",
    "wof:placetype":"venue"
},
  "geometry": {"coordinates":[-71.079498,42.350498],"type":"Point"}
}