{
  "type": "Feature",
  "properties": {
    "addr:full":"345 Main St Sturbridge MA 01566",
    "addr:housenumber":"345",
    "addr:postcode":"01566",
    "addr:street":"Main St",
    "iso:country":"US",
    "sg:address":"345 Main St",
    "sg:city":"Sturbridge",
    "sg:classifiers":[
        {
            "category":"Organizations",
            "subcategory":"Religious Organization",
            "type":"Services"
        }
    ],
    "sg:phone":"+1 508 347 7297",
    "sg:postcode":"01566",
    "sg:province":"MA",
    "sg:tags":[
        "church"
    ],
    "wof:name":"Bethlehem Lutheran Church",
    "wof:placetype":"venue"
},
  "geometry": {"coordinates":[-72.083845,42.110667],"type":"Point"}
}