{
  "type": "Feature",
  "properties": {
    "addr:full": "150 Main St Gardner MA 01440",
    "addr:housenumber": "150",
    "addr:postcode": "01440",
    "addr:street": "Main St",
    "iso:country": "US",
    "sg:address": "150 Main St",
    "sg:city": "Gardner",
    "sg:classifiers": [
      {
        "category": "Retail",
        "subcategory": "Laundry \u0026 Dry Cleaning",
        "type": "Services"
      }
    ],
    "sg:phone": "+1 978 632 0239",
    "sg:postcode": "01440",
    "sg:province": "MA",
    "sg:tags": [
      "cleaners"
    ],
    "wof:name": "Landry Cleaners",
    "wof:placetype": "venue"
  },
  "geometry": {"coordinates":[-71.994633,42.574627],"type":"Point"}
}
