{
  "type": "Feature",
  "properties": {
    "iso:country":"US",
    "sg:address":"150 Main St",
    "sg:city":"Gardner",
    "sg:classifiers":[
        {
            "category":"Retail",
            "subcategory":"Laundry & Dry Cleaning",
            "type":"Services"
        }
    ],
    "sg:phone":"+1 978 632 0239",
    "sg:postcode":"01440",
    "sg:province":"MA",
    "sg:tags":[
        "cleaners"
    ],
    "wof:name":"Landry Cleaners",
    "wof:placetype":"venue"
},
  "geometry": {"coordinates":[-71.99463299999999,42.574627],"type":"Point"}
}