{
  "type": "Feature",
  "properties": {
    "iso:country":"US",
    "sg:address":"79 North St",
    "sg:city":"Mattapoisett",
    "sg:classifiers":[
        {
            "category":"Social Services",
            "subcategory":"Child Care",
            "type":"Services"
        }
    ],
    "sg:phone":"+1 508 758 4884",
    "sg:postcode":"02739",
    "sg:province":"MA",
    "wof:name":"Lighthouse Learning Ctr",
    "wof:placetype":"venue"
},
  "geometry": {"coordinates":[-70.81541799999999,41.668411],"type":"Point"}
}