{
  "type": "Feature",
  "properties": {
    "iso:country":"US",
    "sg:address":"390 N Main St",
    "sg:city":"Andover",
    "sg:classifiers":[
        {
            "category":"Retail",
            "subcategory":"Funeral Services",
            "type":"Services"
        }
    ],
    "sg:phone":"+1 978 475 5200",
    "sg:postcode":"01810",
    "sg:province":"MA",
    "sg:tags":[
        "home"
    ],
    "wof:name":"Burke Funeral Home",
    "wof:placetype":"venue"
},
  "geometry": {"coordinates":[-71.152103,42.676366],"type":"Point"}
}