{
  "type": "Feature",
  "properties": {
    "iso:country":"US",
    "sg:address":"32 Chestnut St",
    "sg:city":"Needham",
    "sg:classifiers":[
        {
            "category":"Shopping",
            "type":"Retail Goods"
        }
    ],
    "sg:phone":"+1 781 449 6722",
    "sg:postcode":"02492",
    "sg:province":"MA",
    "sg:tags":[
        "material",
        "artist",
        "supply"
    ],
    "wof:name":"Art Emporium",
    "wof:placetype":"venue"
},
  "geometry": {"coordinates":[-71.23712999999999,42.27868],"type":"Point"}
}