{
  "type": "Feature",
  "properties": {
    "iso:country":"US",
    "sg:address":"16 Winter St",
    "sg:city":"Peabody",
    "sg:classifiers":[
        {
            "category":"Professional",
            "type":"Services"
        }
    ],
    "sg:phone":"+1 978 538 3981",
    "sg:postcode":"01960",
    "sg:province":"MA",
    "sg:tags":[
        "establishment"
    ],
    "wof:name":"Loveland Don Co Inc",
    "wof:placetype":"venue"
},
  "geometry": {"coordinates":[-70.927336,42.523656],"type":"Point"}
}