{
  "type": "Feature",
  "properties": {
    "addr:full": "378 Pleasant St East Bridgewater MA 02333",
    "addr:housenumber": "378",
    "addr:postcode": "02333",
    "addr:street": "Pleasant St",
    "iso:country": "US",
    "sg:address": "378 Pleasant St",
    "sg:city": "East Bridgewater",
    "sg:classifiers": [
      {
        "category": "Wholesale",
        "subcategory": "Meat",
        "type": "Manufacturing \u0026 Wholesale Goods"
      }
    ],
    "sg:phone": "+1 508 587 0035",
    "sg:postcode": "02333",
    "sg:province": "MA",
    "sg:tags": [
      "packer"
    ],
    "wof:name": "Crocetti's Oakdale Packing Co",
    "wof:placetype": "venue"
  },
  "geometry": {"coordinates":[-70.983097,42.040741],"type":"Point"}
}
