{
  "type": "Feature",
  "properties": {
    "addr:full":"632 Washington St Canton MA 02021",
    "addr:housenumber":"632",
    "addr:postcode":"02021",
    "addr:street":"Washington St",
    "iso:country":"US",
    "sg:address":"632 Washington St",
    "sg:city":"Canton",
    "sg:classifiers":[
        {
            "category":"Building & Trades",
            "subcategory":"Pest Control",
            "type":"Services"
        }
    ],
    "sg:phone":"+1 781 830 6080",
    "sg:postcode":"02021",
    "sg:province":"MA",
    "sg:tags":[
        "trapper",
        "animal"
    ],
    "sg:website":"www.baystatewildlife.com",
    "wof:name":"Baystate Wildlife Management",
    "wof:placetype":"venue"
},
  "geometry": {"coordinates":[-71.1455,42.1544],"type":"Point"}
}