{
  "type": "Feature",
  "properties": {
    "addr:full":"78 Main St Marshfield MA 02050",
    "addr:housenumber":"78",
    "addr:postcode":"02050",
    "addr:street":"Main St",
    "iso:country":"US",
    "sg:address":"78 Main St",
    "sg:city":"Marshfield",
    "sg:classifiers":[
        {
            "category":"Education",
            "subcategory":"Dance Studio",
            "type":"Public Place"
        }
    ],
    "sg:phone":"+1 781 837 1888",
    "sg:postcode":"02050",
    "sg:province":"MA",
    "sg:tags":[
        "instruction",
        "dancing"
    ],
    "wof:name":"Miss Vicki's School Of Dance",
    "wof:placetype":"venue"
},
  "geometry": {"coordinates":[-70.71795299999999,42.097256],"type":"Point"}
}