{
  "type": "Feature",
  "properties": {
    "iso:country":"US",
    "sg:address":"603 Tremont St",
    "sg:city":"Boston",
    "sg:classifiers":[
        {
            "category":"Personal",
            "subcategory":"Barber",
            "type":"Services"
        }
    ],
    "sg:phone":"+1 617 267 2200",
    "sg:postcode":"02118",
    "sg:province":"MA",
    "sg:website":"www.bladebarbershop.com",
    "wof:name":"Blade Barber Shop",
    "wof:placetype":"venue"
},
  "geometry": {"coordinates":[-71.073537,42.343148],"type":"Point"}
}