{
  "type": "Feature",
  "properties": {
    "addr:full": "101 Cottage St Melrose MA 02176",
    "addr:housenumber": "101",
    "addr:postcode": "02176",
    "addr:street": "Cottage St",
    "iso:country": "US",
    "sg:address": "101 Cottage St",
    "sg:city": "Melrose",
    "sg:classifiers": [
      {
        "category": "Organizations",
        "subcategory": "Community Association",
        "type": "Services"
      }
    ],
    "sg:phone": "+1 781 662 7676",
    "sg:postcode": "02176",
    "sg:province": "MA",
    "sg:tags": [
      "club"
    ],
    "wof:name": "200 Club",
    "wof:placetype": "venue"
  },
  "geometry": {"coordinates":[-71.069854,42.455343],"type":"Point"}
}
