{
  "type": "Feature",
  "properties": {
    "addr:full": "130 N Beacon St Brighton MA 02135",
    "addr:housenumber": "130",
    "addr:postcode": "02135",
    "addr:street": "N Beacon St",
    "iso:country": "US",
    "sg:address": "130 N Beacon St",
    "sg:city": "Brighton",
    "sg:classifiers": [
      {
        "category": "Building \u0026 Trades",
        "subcategory": "Construction",
        "type": "Services"
      }
    ],
    "sg:phone": "+1 617 783 1072",
    "sg:postcode": "02135",
    "sg:province": "MA",
    "sg:tags": [
      "system",
      "specialty",
      "heating",
      "mechanical",
      "contractor",
      "air conditioning"
    ],
    "wof:name": "Champion Mechanical",
    "wof:placetype": "venue"
  },
  "geometry": {"coordinates":[-71.144849,42.355077],"type":"Point"}
}
