{
  "type": "Feature",
  "properties": {
    "iso:country":"US",
    "sg:address":"130 N Beacon St",
    "sg:city":"Brighton",
    "sg:classifiers":[
        {
            "category":"Building & Trades",
            "subcategory":"Construction",
            "type":"Services"
        }
    ],
    "sg:phone":"+1 617 783 1072",
    "sg:postcode":"02135",
    "sg:province":"MA",
    "sg:tags":[
        "system",
        "specialty",
        "heating",
        "mechanical",
        "contractor",
        "air conditioning"
    ],
    "wof:name":"Champion Mechanical",
    "wof:placetype":"venue"
},
  "geometry": {"coordinates":[-71.14484899999999,42.355077],"type":"Point"}
}