{
  "type": "Feature",
  "properties": {
    "addr:full": "57 State St Belchertown MA 01007",
    "addr:housenumber": "57",
    "addr:postcode": "01007",
    "addr:street": "State St",
    "iso:country": "US",
    "ovtr:label": "Swift River Elementary School, 57 State St Belchertown MA US",
    "ovtr:similarity": 2.395535945892334,
    "sg:address": "57 State St",
    "sg:city": "Belchertown",
    "sg:classifiers": [
      {
        "category": "Education",
        "subcategory": "School",
        "type": "Public Place"
      }
    ],
    "sg:phone": "+1 413 323 0471",
    "sg:postcode": "01007",
    "sg:province": "MA",
    "wof:name": "Swift River Elementary School",
    "wof:placetype": "venue"
  },
  "geometry": {"coordinates":[-72.413578,42.271193],"type":"Point"}
}
