{
  "type": "Feature",
  "properties": {
    "addr:full": "2 Harris Ave Jamaica Plain MA 02130",
    "addr:housenumber": "2",
    "addr:postcode": "02130",
    "addr:street": "Harris Ave",
    "iso:country": "US",
    "sg:address": "2 Harris Ave",
    "sg:city": "Jamaica Plain",
    "sg:classifiers": [
      {
        "category": "Professional",
        "subcategory": "Lawyer \u0026 Legal Services",
        "type": "Services"
      }
    ],
    "sg:phone": "+1 617 971 0400",
    "sg:postcode": "02130",
    "sg:province": "MA",
    "sg:website": "www.bfattorneys.com",
    "wof:name": "Burgos \u0026 Figueroa Attorneys At Law",
    "wof:placetype": "venue"
  },
  "geometry": {"coordinates":[-71.114564,42.311097],"type":"Point"}
}
