{
  "type": "Feature",
  "properties": {
    "iso:country":"US",
    "sg:address":"628 E 5th Street",
    "sg:city":"Boston",
    "sg:classifiers":[
        {
            "category":"Food & Beverages",
            "subcategory":"Groceries & Convenience Stores",
            "type":"Retail Goods"
        }
    ],
    "sg:phone":"+1 617 268 0728",
    "sg:postcode":"02127",
    "sg:province":"MA",
    "sg:website":"www.cumberlandfarms.com",
    "wof:name":"Cumberland Farms",
    "wof:placetype":"venue"
},
  "geometry": {"coordinates":[-71.037412,42.333781],"type":"Point"}
}