{
  "type": "Feature",
  "properties": {
    "addr:full": "628 E 5th Street Boston MA 02127",
    "addr:housenumber": "628",
    "addr:postcode": "02127",
    "addr:street": "E 5Th Street",
    "iso:country": "US",
    "ovtr:label": "Cumberland Farms, 628 E 5th St Boston MA US",
    "ovtr:similarity": 2.6417551040649414,
    "sg:address": "628 E 5th Street",
    "sg:city": "Boston",
    "sg:classifiers": [
      {
        "category": "Food \u0026 Beverages",
        "subcategory": "Groceries \u0026 Convenience Stores",
        "type": "Retail Goods"
      }
    ],
    "sg:phone": "+1 617 268 0728",
    "sg:postcode": "02127",
    "sg:province": "MA",
    "sg:website": "www.cumberlandfarms.com",
    "wof:name": "Cumberland Farms",
    "wof:placetype": "venue"
  },
  "geometry": {"coordinates":[-71.037412,42.333781],"type":"Point"}
}
