{
  "type": "Feature",
  "properties": {
    "addr:full": "1157 Dorchester Ave Dorchester MA 02125",
    "addr:housenumber": "1157",
    "addr:postcode": "02125",
    "addr:street": "Dorchester Ave",
    "iso:country": "US",
    "sg:address": "1157 Dorchester Ave",
    "sg:city": "Dorchester",
    "sg:classifiers": [
      {
        "category": "Restaurant",
        "type": "Food \u0026 Drink"
      }
    ],
    "sg:phone": "+1 617 288 7314",
    "sg:postcode": "02125",
    "sg:province": "MA",
    "sg:tags": [
      "vietnamese"
    ],
    "wof:name": "Sunrise Restaurant",
    "wof:placetype": "venue"
  },
  "geometry": {"coordinates":[-71.057503,42.311199],"type":"Point"}
}
