{
  "type": "Feature",
  "properties": {
    "addr:full": "Marston Mills Mkt Pl Osterville MA 02655",
    "addr:postcode": "02655",
    "iso:country": "US",
    "sg:address": "Marston Mills Mkt Pl",
    "sg:city": "Osterville",
    "sg:classifiers": [
      {
        "category": "Home \u0026 Garden",
        "subcategory": "Garden Supply",
        "type": "Retail Goods"
      },
      {
        "category": "Home \u0026 Garden",
        "subcategory": "Hardware",
        "type": "Retail Goods"
      }
    ],
    "sg:phone": "+1 508 428 7100",
    "sg:postcode": "02655",
    "sg:province": "MA",
    "sg:tags": [
      "nursery",
      "gardening",
      "store"
    ],
    "wof:name": "Aubuchon Hardware",
    "wof:placetype": "venue"
  },
  "geometry": {"coordinates":[-70.386002,41.630299],"type":"Point"}
}
