{
  "type": "Feature",
  "properties": {
    "iso:country":"US",
    "sg:address":"200 S Main St",
    "sg:city":"Leicester",
    "sg:classifiers":[
        {
            "category":"Retail",
            "subcategory":"Auto Repair",
            "type":"Services"
        }
    ],
    "sg:phone":"+1 508 892 9441",
    "sg:postcode":"01524",
    "sg:province":"MA",
    "sg:tags":[
        "body",
        "shop"
    ],
    "wof:name":"Greenwood Tire & Service Center",
    "wof:placetype":"venue"
},
  "geometry": {"coordinates":[-71.90589900000001,42.244701],"type":"Point"}
}