{
  "type": "Feature",
  "properties": {
    "addr:full": "316 Newbury St Boston MA 02115",
    "addr:housenumber": "316",
    "addr:postcode": "02115",
    "addr:street": "Newbury St",
    "iso:country": "US",
    "sg:address": "316 Newbury St",
    "sg:city": "Boston",
    "sg:classifiers": [
      {
        "category": "Building \u0026 Trades",
        "subcategory": "Locksmith",
        "type": "Services"
      }
    ],
    "sg:phone": "+1 617 449 9850",
    "sg:postcode": "02115",
    "sg:province": "MA",
    "sg:tags": [
      "key"
    ],
    "wof:name": "Locksmith 24 Hour Service",
    "wof:placetype": "venue"
  },
  "geometry": {"coordinates":[-71.085482,42.348643],"type":"Point"}
}
