{
  "type": "Feature",
  "properties": {
    "addr:full":"30 A St Canton MA 02045",
    "addr:housenumber":"30",
    "addr:postcode":"02045",
    "addr:street":"A St",
    "iso:country":"US",
    "sg:address":"30 A St",
    "sg:city":"Canton",
    "sg:classifiers":[
        {
            "category":"Wholesale",
            "subcategory":"Medical Equipment & Supplies",
            "type":"Manufacturing & Wholesale Goods"
        }
    ],
    "sg:phone":"+1 781 828 7772",
    "sg:postcode":"02045",
    "sg:province":"MA",
    "sg:tags":[
        "hospital"
    ],
    "wof:name":"Westnet Inc",
    "wof:placetype":"venue"
},
  "geometry": {"coordinates":[-70.88041699999999,42.291881],"type":"Point"}
}