{
  "type": "Feature",
  "properties": {
    "iso:country":"US",
    "sg:address":"245 Winthrop St",
    "sg:city":"Rehoboth",
    "sg:classifiers":[
        {
            "category":"Organizations",
            "subcategory":"Religious Organization",
            "type":"Services"
        }
    ],
    "sg:phone":"+1 508 252 6919",
    "sg:postcode":"02769",
    "sg:province":"MA",
    "sg:tags":[
        "church"
    ],
    "wof:name":"Circle Of Salgion Church",
    "wof:placetype":"venue"
},
  "geometry": {"coordinates":[-71.24055799999999,41.853667],"type":"Point"}
}