{
  "type": "Feature",
  "properties": {
    "iso:country":"US",
    "sg:address":"11 Seconset St",
    "sg:city":"Worcester",
    "sg:classifiers":[
        {
            "category":"Real Estate",
            "subcategory":"Architect",
            "type":"Services"
        }
    ],
    "sg:phone":"+1 508 791 0476",
    "sg:postcode":"01602",
    "sg:province":"MA",
    "wof:name":"DRB Architects",
    "wof:placetype":"venue"
},
  "geometry": {"coordinates":[-71.851066,42.284222],"type":"Point"}
}