{
  "type": "Feature",
  "properties": {
    "iso:country":"US",
    "sg:address":"586 Park St",
    "sg:city":"Dorchester Ctr",
    "sg:classifiers":[
        {
            "category":"Real Estate",
            "subcategory":"Real Estate Agent",
            "type":"Services"
        }
    ],
    "sg:phone":"+1 617 825 6048",
    "sg:postcode":"02124",
    "sg:province":"MA",
    "wof:name":"John's Realty",
    "wof:placetype":"venue"
},
  "geometry": {"coordinates":[-71.076958,42.294599],"type":"Point"}
}