{
  "type": "Feature",
  "properties": {
    "addr:full": "256 N Pleasant St Amherst MA 01002",
    "addr:housenumber": "256",
    "addr:postcode": "01002",
    "addr:street": "N Pleasant St",
    "iso:country": "US",
    "sg:address": "256 N Pleasant St",
    "sg:city": "Amherst",
    "sg:classifiers": [
      {
        "category": "Health Services",
        "subcategory": "Health Practitioner",
        "type": "Services"
      }
    ],
    "sg:phone": "+1 413 658 0039",
    "sg:postcode": "01002",
    "sg:province": "MA",
    "sg:tags": [
      "therapist",
      "physical"
    ],
    "wof:name": "Holistic PT Specialists",
    "wof:placetype": "venue"
  },
  "geometry": {"coordinates":[-72.520161,42.381453],"type":"Point"}
}
