{
  "type": "Feature",
  "properties": {
    "addr:full":"21 Thomas Park Boston MA 02127",
    "addr:housenumber":"21",
    "addr:postcode":"02127",
    "addr:street":"Thomas Park",
    "iso:country":"US",
    "sg:address":"21 Thomas Park",
    "sg:city":"Boston",
    "sg:classifiers":[
        {
            "category":"Professional",
            "subcategory":"Computer Services",
            "type":"Services"
        },
        {
            "category":"Wholesale",
            "subcategory":"Computers",
            "type":"Manufacturing & Wholesale Goods"
        }
    ],
    "sg:phone":"+1 617 269 3200",
    "sg:postcode":"02127",
    "sg:province":"MA",
    "sg:tags":[
        "equipment",
        "cd-rom",
        "software"
    ],
    "wof:name":"Penfact Inc",
    "wof:placetype":"venue"
},
  "geometry": {"coordinates":[-71.04603899999999,42.333606],"type":"Point"}
}