{
  "type": "Feature",
  "properties": {
    "addr:full":"63 Shore Rd Ste 24 Winchester MA 01890",
    "addr:housenumber":"63;24",
    "addr:postcode":"01890",
    "addr:street":"Shore Rd Ste",
    "iso:country":"US",
    "sg:address":"63 Shore Rd Ste 24",
    "sg:city":"Winchester",
    "sg:classifiers":[
        {
            "category":"Professional",
            "subcategory":"Lawyer & Legal Services",
            "type":"Services"
        }
    ],
    "sg:phone":"+1 781 721 0404",
    "sg:postcode":"01890",
    "sg:province":"MA",
    "wof:name":"Law Office of George T Crowley - CLOSED",
    "wof:placetype":"venue"
},
  "geometry": {"coordinates":[-71.136002,42.4548],"type":"Point"}
}