{
  "type": "Feature",
  "properties": {
    "iso:country":"US",
    "sg:address":"338 Tremont St",
    "sg:city":"Rehoboth",
    "sg:classifiers":[
        {
            "category":"Health Services",
            "subcategory":"Clinic",
            "type":"Services"
        }
    ],
    "sg:phone":"+1 508 223 3320",
    "sg:postcode":"02769",
    "sg:province":"MA",
    "sg:tags":[
        "welfare"
    ],
    "wof:name":"American Behavioral Health Ins",
    "wof:placetype":"venue"
},
  "geometry": {"coordinates":[-71.252182,41.903358],"type":"Point"}
}