{
  "type": "Feature",
  "properties": {
    "addr:full": "10 Merchant St Sharon MA 02067",
    "addr:housenumber": "10",
    "addr:postcode": "02067",
    "addr:street": "Merchant St",
    "iso:country": "US",
    "sg:address": "10 Merchant St",
    "sg:city": "Sharon",
    "sg:classifiers": [
      {
        "category": "Wholesale",
        "subcategory": "Tobacco Products",
        "type": "Manufacturing \u0026 Wholesale Goods"
      }
    ],
    "sg:phone": "+1 781 784 5550",
    "sg:postcode": "02067",
    "sg:province": "MA",
    "sg:tags": [
      "cigarette",
      "cigar",
      "store",
      "candy"
    ],
    "wof:name": "George Melhado \u0026 Co",
    "wof:placetype": "venue"
  },
  "geometry": {"coordinates":[-71.235298,42.117802],"type":"Point"}
}
