{
  "type": "Feature",
  "properties": {
    "addr:full":"56 Patricia Ln South Weymouth MA 02190",
    "addr:housenumber":"56",
    "addr:postcode":"02190",
    "addr:street":"Patricia Ln",
    "iso:country":"US",
    "sg:address":"56 Patricia Ln",
    "sg:city":"South Weymouth",
    "sg:classifiers":[
        {
            "category":"Social Services",
            "subcategory":"Child Care",
            "type":"Services"
        }
    ],
    "sg:phone":"+1 781 335 6169",
    "sg:postcode":"02190",
    "sg:province":"MA",
    "sg:tags":[
        "day"
    ],
    "wof:name":"Sharon Lee Nursery School",
    "wof:placetype":"venue"
},
  "geometry": {"coordinates":[-70.960615,42.150721],"type":"Point"}
}