{
  "type": "Feature",
  "properties": {
    "addr:full": "31 Saint James Ave Boston MA 02116",
    "addr:housenumber": "31",
    "addr:postcode": "02116",
    "addr:street": "Saint James Ave",
    "iso:country": "US",
    "sg:address": "31 Saint James Ave",
    "sg:city": "Boston",
    "sg:classifiers": [
      {
        "category": "Professional",
        "subcategory": "Lawyer \u0026 Legal Services",
        "type": "Services"
      }
    ],
    "sg:phone": "+1 617 574 1700",
    "sg:postcode": "02116",
    "sg:province": "MA",
    "wof:name": "McLucas Jeffery C Atty",
    "wof:placetype": "venue"
  },
  "geometry": {"coordinates":[-71.071501,42.350778],"type":"Point"}
}
