{
  "type": "Feature",
  "properties": {
    "addr:full":"7 Summer St Chelmsford MA 01824",
    "addr:housenumber":"7",
    "addr:postcode":"01824",
    "addr:street":"Summer St",
    "iso:country":"US",
    "sg:address":"7 Summer St",
    "sg:city":"Chelmsford",
    "sg:classifiers":[
        {
            "category":"Building & Trades",
            "subcategory":"Construction",
            "type":"Services"
        }
    ],
    "sg:phone":"+1 978 256 6328",
    "sg:postcode":"01824",
    "sg:province":"MA",
    "sg:tags":[
        "contractor",
        "conditioning/hvac",
        "heating",
        "air"
    ],
    "sg:website":"www.chelmsfordfireplace.com/",
    "wof:name":"Chelmsford Fireplace Center",
    "wof:placetype":"venue"
},
  "geometry": {"coordinates":[-71.349316,42.594062],"type":"Point"}
}