{
  "type": "Feature",
  "properties": {
    "iso:country":"US",
    "sg:address":"31 Division St",
    "sg:city":"Great Barrington",
    "sg:classifiers":[
        {
            "category":"Professional",
            "subcategory":"Management & Consulting",
            "type":"Services"
        }
    ],
    "sg:phone":"+1   ",
    "sg:postcode":"01230",
    "sg:province":"MA",
    "wof:name":"D&P Interventure Inc",
    "wof:placetype":"venue"
},
  "geometry": {"coordinates":[-73.350216,42.232392],"type":"Point"}
}