{
  "type": "Feature",
  "properties": {
    "addr:full": "15 Letchworth Ave North Billerica MA 01862",
    "addr:housenumber": "15",
    "addr:postcode": "01862",
    "addr:street": "Letchworth Ave North",
    "iso:country": "US",
    "sg:address": "15 Letchworth Ave",
    "sg:city": "North Billerica",
    "sg:classifiers": [
      {
        "category": "Home \u0026 Garden",
        "subcategory": "Building Materials",
        "type": "Retail Goods"
      }
    ],
    "sg:phone": "+1 978 663 3546",
    "sg:postcode": "01862",
    "sg:province": "MA",
    "sg:tags": [
      "supply"
    ],
    "wof:name": "Hughes Lumber Co Inc",
    "wof:placetype": "venue"
  },
  "geometry": {"coordinates":[-71.2826,42.593498],"type":"Point"}
}
