{
  "type": "Feature",
  "properties": {
    "iso:country":"US",
    "sg:address":"15 Letchworth Ave",
    "sg:city":"North Billerica",
    "sg:classifiers":[
        {
            "category":"Home & Garden",
            "subcategory":"Building Materials",
            "type":"Retail Goods"
        }
    ],
    "sg:phone":"+1 978 663 3546",
    "sg:postcode":"01862",
    "sg:province":"MA",
    "sg:tags":[
        "supply"
    ],
    "wof:name":"Hughes Lumber Co Inc",
    "wof:placetype":"venue"
},
  "geometry": {"coordinates":[-71.2826,42.593498],"type":"Point"}
}