{
  "type": "Feature",
  "properties": {
    "addr:full":"300 Howard St Framingham MA 01702",
    "addr:housenumber":"300",
    "addr:postcode":"01702",
    "addr:street":"Howard St",
    "iso:country":"US",
    "sg:address":"300 Howard St",
    "sg:city":"Framingham",
    "sg:classifiers":[
        {
            "category":"Social Services",
            "subcategory":"Job Training",
            "type":"Services"
        }
    ],
    "sg:phone":"+1 508 620 2677",
    "sg:postcode":"01702",
    "sg:province":"MA",
    "sg:tags":[
        "career",
        "counseling",
        "vocational"
    ],
    "sg:website":"www.smoc.org",
    "wof:name":"Metrowest Career Ctr",
    "wof:placetype":"venue"
},
  "geometry": {"coordinates":[-71.41040599999999,42.278721],"type":"Point"}
}