{
  "type": "Feature",
  "properties": {
    "iso:country":"US",
    "sg:address":"42 N Monson Rd",
    "sg:city":"Hampden",
    "sg:classifiers":[
        {
            "category":"Freight",
            "type":"Transportation"
        }
    ],
    "sg:phone":"+1   ",
    "sg:postcode":"01036",
    "sg:province":"MA",
    "sg:tags":[
        "operator",
        "local",
        "trucking"
    ],
    "wof:name":"All Waste Removal Inc",
    "wof:placetype":"venue"
},
  "geometry": {"coordinates":[-72.389263,42.081765],"type":"Point"}
}