{
  "type": "Feature",
  "properties": {
    "addr:full":"34 Cambridge St Burlington MA 01803",
    "addr:housenumber":"34",
    "addr:postcode":"01803",
    "addr:street":"Cambridge St",
    "iso:country":"US",
    "sg:address":"34 Cambridge St",
    "sg:city":"Burlington",
    "sg:classifiers":[
        {
            "category":"Fast Food",
            "type":"Food & Drink"
        },
        {
            "category":"Coffee & Tea",
            "type":"Food & Drink"
        },
        {
            "category":"Restaurant",
            "type":"Food & Drink"
        },
        {
            "category":"Bakery",
            "type":"Food & Drink"
        },
        {
            "category":"Food & Beverages",
            "subcategory":"Groceries & Convenience Stores",
            "type":"Retail Goods"
        }
    ],
    "sg:phone":"+1 781 272 1365",
    "sg:postcode":"01803",
    "sg:province":"MA",
    "sg:tags":[
        "shop",
        "sandwich",
        "espresso",
        "take"
    ],
    "sg:website":"www.panera.com",
    "wof:name":"Panera Bread",
    "wof:placetype":"venue"
},
  "geometry": {"coordinates":[-71.18910200000001,42.483898],"type":"Point"}
}