{
  "type": "Feature",
  "properties": {
    "addr:full": "34 Cambridge St Burlington MA 01803",
    "addr:housenumber": "34",
    "addr:postcode": "01803",
    "addr:street": "Cambridge St",
    "iso:country": "US",
    "ovtr:label": "Panera Bread, 34 Cambridge St Burlington MA US",
    "ovtr:similarity": 3.047729969024658,
    "sg:address": "34 Cambridge St",
    "sg:city": "Burlington",
    "sg:classifiers": [
      {
        "category": "Fast Food",
        "type": "Food \u0026 Drink"
      },
      {
        "category": "Coffee \u0026 Tea",
        "type": "Food \u0026 Drink"
      },
      {
        "category": "Restaurant",
        "type": "Food \u0026 Drink"
      },
      {
        "category": "Bakery",
        "type": "Food \u0026 Drink"
      },
      {
        "category": "Food \u0026 Beverages",
        "subcategory": "Groceries \u0026 Convenience Stores",
        "type": "Retail Goods"
      }
    ],
    "sg:phone": "+1 781 272 1365",
    "sg:postcode": "01803",
    "sg:province": "MA",
    "sg:tags": [
      "shop",
      "sandwich",
      "espresso",
      "take"
    ],
    "sg:website": "www.panera.com",
    "wof:name": "Panera Bread",
    "wof:placetype": "venue"
  },
  "geometry": {"coordinates":[-71.189102,42.483898],"type":"Point"}
}
