{
  "type": "Feature",
  "properties": {
    "addr:full": "4 Midland Cir Andover MA 01810",
    "addr:housenumber": "4",
    "addr:postcode": "01810",
    "addr:street": "Midland Cir",
    "iso:country": "US",
    "sg:address": "4 Midland Cir",
    "sg:city": "Andover",
    "sg:classifiers": [
      {
        "category": "Professional",
        "subcategory": "Management \u0026 Consulting",
        "type": "Services"
      }
    ],
    "sg:phone": "+1 978 470 3454",
    "sg:postcode": "01810",
    "sg:province": "MA",
    "sg:tags": [
      "consultant",
      "business"
    ],
    "sg:website": "www.salesconsulting.com",
    "wof:name": "Commonwealth Sales Consulting",
    "wof:placetype": "venue"
  },
  "geometry": {"coordinates":[-71.16186,42.64679],"type":"Point"}
}
