{
  "type": "Feature",
  "properties": {
    "iso:country":"US",
    "sg:address":"91 Montvale Ave",
    "sg:city":"Stoneham",
    "sg:classifiers":[
        {
            "category":"Community Center",
            "type":"Public Place"
        }
    ],
    "sg:phone":"+1 781 835 2111",
    "sg:postcode":"02180",
    "sg:province":"MA",
    "sg:tags":[
        "medical"
    ],
    "wof:name":"Dha Endoscopy",
    "wof:placetype":"venue"
},
  "geometry": {"coordinates":[-71.111643,42.480663],"type":"Point"}
}