{
  "type": "Feature",
  "properties": {
    "addr:full": "91 Montvale Ave Stoneham MA 02180",
    "addr:housenumber": "91",
    "addr:postcode": "02180",
    "addr:street": "Montvale Ave",
    "iso:country": "US",
    "ovtr:label": "DHA Endoscopy, 91 Montvale Ave Stoneham MA US",
    "ovtr:similarity": 1.9840949773788452,
    "sg:address": "91 Montvale Ave",
    "sg:city": "Stoneham",
    "sg:classifiers": [
      {
        "category": "Community Center",
        "type": "Public Place"
      }
    ],
    "sg:phone": "+1 781 835 2111",
    "sg:postcode": "02180",
    "sg:province": "MA",
    "sg:tags": [
      "medical"
    ],
    "wof:name": "Dha Endoscopy",
    "wof:placetype": "venue"
  },
  "geometry": {"coordinates":[-71.111643,42.480663],"type":"Point"}
}
