{
  "type": "Feature",
  "properties": {
    "addr:full": "221 Five Corners Rd Centerville MA 02632",
    "addr:housenumber": "221",
    "addr:postcode": "02632",
    "addr:street": "Five Corners Rd",
    "iso:country": "US",
    "sg:address": "221 Five Corners Rd",
    "sg:city": "Centerville",
    "sg:classifiers": [
      {
        "category": "Education",
        "subcategory": "Special Training",
        "type": "Public Place"
      }
    ],
    "sg:phone": "+1   ",
    "sg:postcode": "02632",
    "sg:province": "MA",
    "wof:name": "Cape Cod Language School",
    "wof:placetype": "venue"
  },
  "geometry": {"coordinates":[-70.36706,41.652675],"type":"Point"}
}
