{
  "type": "Feature",
  "properties": {
    "addr:full":"1430 Massachusetts Ave Cambridge MA 02138",
    "addr:housenumber":"1430",
    "addr:postcode":"02138",
    "addr:street":"Massachusetts Ave",
    "iso:country":"US",
    "sg:address":"1430 Massachusetts Ave",
    "sg:city":"Cambridge",
    "sg:classifiers":[
        {
            "category":"Professional",
            "subcategory":"Employment Agencies",
            "type":"Services"
        }
    ],
    "sg:phone":"+1 617 354 7215",
    "sg:postcode":"02138",
    "sg:province":"MA",
    "sg:tags":[
        "help",
        "contractor"
    ],
    "sg:website":"www.randstadu.com",
    "wof:name":"Randstad",
    "wof:placetype":"venue"
},
  "geometry": {"coordinates":[-71.118951,42.374099],"type":"Point"}
}