{
  "type": "Feature",
  "properties": {
    "addr:full":"22 Atlantic Ave Marblehead MA 01945",
    "addr:housenumber":"22",
    "addr:postcode":"01945",
    "addr:street":"Atlantic Ave",
    "iso:country":"US",
    "sg:address":"22 Atlantic Ave",
    "sg:city":"Marblehead",
    "sg:classifiers":[
        {
            "category":"Professional",
            "type":"Services"
        }
    ],
    "sg:phone":"+1 781 639 7728",
    "sg:postcode":"01945",
    "sg:province":"MA",
    "sg:tags":[
        "establishment"
    ],
    "wof:name":"Yankee Associates LLC",
    "wof:placetype":"venue"
},
  "geometry": {"coordinates":[-70.855,42.499805],"type":"Point"}
}