{
  "type": "Feature",
  "properties": {
    "addr:full": "21 Housatonic St Lenox MA 01240",
    "addr:housenumber": "21",
    "addr:postcode": "01240",
    "addr:street": "Housatonic St",
    "iso:country": "US",
    "sg:address": "21 Housatonic St",
    "sg:city": "Lenox",
    "sg:classifiers": [
      {
        "category": "Shopping",
        "subcategory": "Clothing, Apparel, \u0026 Fashions",
        "type": "Retail Goods"
      }
    ],
    "sg:phone": "+1 413 637 2680",
    "sg:postcode": "01240",
    "sg:province": "MA",
    "wof:name": "Casablanca",
    "wof:placetype": "venue"
  },
  "geometry": {"coordinates":[-73.2837,42.357883],"type":"Point"}
}
