{
  "type": "Feature",
  "properties": {
    "iso:country":"US",
    "sg:address":"21 Housatonic St",
    "sg:city":"Lenox",
    "sg:classifiers":[
        {
            "category":"Shopping",
            "subcategory":"Clothing, Apparel, & Fashions",
            "type":"Retail Goods"
        }
    ],
    "sg:phone":"+1 413 637 2680",
    "sg:postcode":"01240",
    "sg:province":"MA",
    "wof:name":"Casablanca",
    "wof:placetype":"venue"
},
  "geometry": {"coordinates":[-73.2837,42.357883],"type":"Point"}
}