{
  "type": "Feature",
  "properties": {
    "iso:country":"US",
    "sg:address":"171 Broadway",
    "sg:city":"Saugus",
    "sg:classifiers":[
        {
            "category":"Banks & Credit Unions",
            "subcategory":"Bank",
            "type":"Services"
        }
    ],
    "sg:phone":"+1 781 941 7000",
    "sg:postcode":"01906",
    "sg:province":"MA",
    "sg:tags":[
        "loan",
        "real estate"
    ],
    "wof:name":"Flexible Funding",
    "wof:placetype":"venue"
},
  "geometry": {"coordinates":[-71.01643199999999,42.490961],"type":"Point"}
}