{
  "type": "Feature",
  "properties": {
    "addr:full":"788 Main St Holden MA 01520",
    "addr:housenumber":"788",
    "addr:postcode":"01520",
    "addr:street":"Main St",
    "iso:country":"US",
    "sg:address":"788 Main St",
    "sg:city":"Holden",
    "sg:classifiers":[
        {
            "category":"Recreation",
            "type":"Entertainment"
        }
    ],
    "sg:phone":"+1 508 829 7435",
    "sg:postcode":"01520",
    "sg:province":"MA",
    "sg:tags":[
        "instruction",
        "yoga"
    ],
    "wof:name":"Opening Lotus Yoga",
    "wof:placetype":"venue"
},
  "geometry": {"coordinates":[-71.84574499999999,42.342543],"type":"Point"}
}