{
  "type": "Feature",
  "properties": {
    "iso:country":"US",
    "sg:address":"45 South St",
    "sg:city":"Plymouth",
    "sg:classifiers":[
        {
            "category":"Retail",
            "subcategory":"Auto Repair",
            "type":"Services"
        }
    ],
    "sg:phone":"+1 508 830 4689",
    "sg:postcode":"02360",
    "sg:province":"MA",
    "wof:name":"Performance Auto & Towing",
    "wof:placetype":"venue"
},
  "geometry": {"coordinates":[-70.65969800000001,41.950001],"type":"Point"}
}