{
  "type": "Feature",
  "properties": {
    "iso:country":"US",
    "sg:address":"58 Evergreen St",
    "sg:city":"Kingston",
    "sg:classifiers":[
        {
            "category":"Real Estate",
            "subcategory":"Architect",
            "type":"Services"
        }
    ],
    "sg:phone":"+1   ",
    "sg:postcode":"02364",
    "sg:province":"MA",
    "sg:tags":[
        "architectural"
    ],
    "wof:name":"Russell Design Assoc",
    "wof:placetype":"venue"
},
  "geometry": {"coordinates":[-70.731312,41.997863],"type":"Point"}
}