{
  "type": "Feature",
  "properties": {
    "iso:country":"US",
    "sg:address":"93 Holland St",
    "sg:city":"Somerville",
    "sg:classifiers":[
        {
            "category":"Retail",
            "subcategory":"Repair Shop",
            "type":"Services"
        },
        {
            "category":"Shopping",
            "subcategory":"Antiques",
            "type":"Retail Goods"
        },
        {
            "category":"Home & Garden",
            "subcategory":"Furniture",
            "type":"Retail Goods"
        }
    ],
    "sg:phone":"+1 617 776 2011",
    "sg:postcode":"02144",
    "sg:province":"MA",
    "sg:tags":[
        "reupholstery",
        "store"
    ],
    "sg:website":"www.sunshinelucys.com",
    "wof:name":"Sunshine Lucy's New & Used Furniture",
    "wof:placetype":"venue"
},
  "geometry": {"coordinates":[-71.124431,42.398893],"type":"Point"}
}