{
  "type": "Feature",
  "properties": {
    "addr:full": "93 Holland St Somerville MA 02144",
    "addr:housenumber": "93",
    "addr:postcode": "02144",
    "addr:street": "Holland St",
    "iso:country": "US",
    "sg:address": "93 Holland St",
    "sg:city": "Somerville",
    "sg:classifiers": [
      {
        "category": "Retail",
        "subcategory": "Repair Shop",
        "type": "Services"
      },
      {
        "category": "Shopping",
        "subcategory": "Antiques",
        "type": "Retail Goods"
      },
      {
        "category": "Home \u0026 Garden",
        "subcategory": "Furniture",
        "type": "Retail Goods"
      }
    ],
    "sg:phone": "+1 617 776 2011",
    "sg:postcode": "02144",
    "sg:province": "MA",
    "sg:tags": [
      "reupholstery",
      "store"
    ],
    "sg:website": "www.sunshinelucys.com",
    "wof:name": "Sunshine Lucy's New \u0026 Used Furniture",
    "wof:placetype": "venue"
  },
  "geometry": {"coordinates":[-71.124431,42.398893],"type":"Point"}
}
