{
  "type": "Feature",
  "properties": {
    "addr:full": "111 Millbury St Worcester MA 01610",
    "addr:housenumber": "111",
    "addr:postcode": "01610",
    "addr:street": "Millbury St",
    "iso:country": "US",
    "sg:address": "111 Millbury St",
    "sg:city": "Worcester",
    "sg:classifiers": [
      {
        "category": "Utilities",
        "subcategory": "Mobile Phone",
        "type": "Services"
      }
    ],
    "sg:phone": "+1 508 791 7626",
    "sg:postcode": "01610",
    "sg:province": "MA",
    "sg:tags": [
      "telephone",
      "cellular"
    ],
    "wof:name": "Roaming Wireless",
    "wof:placetype": "venue"
  },
  "geometry": {"coordinates":[-71.799129,42.252605],"type":"Point"}
}
