{
  "type": "Feature",
  "properties": {
    "iso:country":"US",
    "sg:address":"26 Hampson St",
    "sg:city":"Dracut",
    "sg:classifiers":[
        {
            "category":"Building & Trades",
            "subcategory":"Equipment Rental",
            "type":"Services"
        }
    ],
    "sg:phone":"+1 978 957 2900",
    "sg:postcode":"01826",
    "sg:province":"MA",
    "sg:tags":[
        "crane"
    ],
    "wof:name":"Allan Crane & Sign Svc",
    "wof:placetype":"venue"
},
  "geometry": {"coordinates":[-71.32748100000001,42.662432],"type":"Point"}
}