{
  "type": "Feature",
  "properties": {
    "addr:full":"266 Main St Medfield MA 02052",
    "addr:housenumber":"266",
    "addr:postcode":"02052",
    "addr:street":"Main St",
    "iso:country":"US",
    "sg:address":"266 Main St",
    "sg:city":"Medfield",
    "sg:classifiers":[
        {
            "category":"Professional",
            "type":"Services"
        }
    ],
    "sg:phone":"+1 508 242 9500",
    "sg:postcode":"02052",
    "sg:province":"MA",
    "sg:tags":[
        "establishment"
    ],
    "wof:name":"Hot Off The Wire",
    "wof:placetype":"venue"
},
  "geometry": {"coordinates":[-71.29174,42.192657],"type":"Point"}
}