{
  "type": "Feature",
  "properties": {
    "iso:country":"US",
    "sg:address":"21 Merrill Rd",
    "sg:city":"Wilbraham",
    "sg:classifiers":[
        {
            "category":"Retail",
            "subcategory":"Repair Shop",
            "type":"Services"
        }
    ],
    "sg:phone":"+1 413 586 9868",
    "sg:postcode":"01095",
    "sg:province":"MA",
    "sg:tags":[
        "plumbing",
        "drain",
        "cleaning",
        "sewer"
    ],
    "wof:name":"A Fletcher Sewer & Drain Clng",
    "wof:placetype":"venue"
},
  "geometry": {"coordinates":[-72.42677399999999,42.141452],"type":"Point"}
}