{
  "type": "Feature",
  "properties": {
    "addr:full": "21 Merrill Rd Wilbraham MA 01095",
    "addr:housenumber": "21",
    "addr:postcode": "01095",
    "addr:street": "Merrill Rd",
    "iso:country": "US",
    "sg:address": "21 Merrill Rd",
    "sg:city": "Wilbraham",
    "sg:classifiers": [
      {
        "category": "Retail",
        "subcategory": "Repair Shop",
        "type": "Services"
      }
    ],
    "sg:phone": "+1 413 586 9868",
    "sg:postcode": "01095",
    "sg:province": "MA",
    "sg:tags": [
      "plumbing",
      "drain",
      "cleaning",
      "sewer"
    ],
    "wof:name": "A Fletcher Sewer \u0026 Drain Clng",
    "wof:placetype": "venue"
  },
  "geometry": {"coordinates":[-72.426774,42.141452],"type":"Point"}
}
