{
  "type": "Feature",
  "properties": {
    "addr:full": "62 Union St Ashland MA 01721",
    "addr:housenumber": "62",
    "addr:postcode": "01721",
    "addr:street": "Union St",
    "iso:country": "US",
    "ovtr:label": "Fitzy's Super Stop \u0026 Wash, 62 Union St Ashland MA US",
    "ovtr:similarity": 2.2421700954437256,
    "sg:address": "62 Union St",
    "sg:city": "Ashland",
    "sg:classifiers": [
      {
        "category": "Retail",
        "subcategory": "Car Wash",
        "type": "Services"
      }
    ],
    "sg:phone": "+1 508 881 2980",
    "sg:postcode": "01721",
    "sg:province": "MA",
    "sg:tags": [
      "polishing",
      "washing"
    ],
    "wof:name": "Fitzy's Super Stop \u0026 Wash",
    "wof:placetype": "venue"
  },
  "geometry": {"coordinates":[-71.454244,42.258608],"type":"Point"}
}
