{
  "type": "Feature",
  "properties": {
    "iso:country":"US",
    "sg:address":"62 Union St",
    "sg:city":"Ashland",
    "sg:classifiers":[
        {
            "category":"Retail",
            "subcategory":"Car Wash",
            "type":"Services"
        }
    ],
    "sg:phone":"+1 508 881 2980",
    "sg:postcode":"01721",
    "sg:province":"MA",
    "sg:tags":[
        "polishing",
        "washing"
    ],
    "wof:name":"Fitzy's Super Stop & Wash",
    "wof:placetype":"venue"
},
  "geometry": {"coordinates":[-71.454244,42.258608],"type":"Point"}
}