{
  "type": "Feature",
  "properties": {
    "addr:full":"248 Hampden Ave Westfield MA 01085",
    "addr:housenumber":"248",
    "addr:postcode":"01085",
    "addr:street":"Hampden Ave",
    "iso:country":"US",
    "sg:address":"248 Hampden Ave",
    "sg:city":"Westfield",
    "sg:classifiers":[
        {
            "category":"Professional",
            "type":"Services"
        }
    ],
    "sg:phone":"+1 413 532 6346",
    "sg:postcode":"01085",
    "sg:province":"MA",
    "sg:tags":[
        "establishment"
    ],
    "wof:name":"Pelletier AJ Restorations",
    "wof:placetype":"venue"
},
  "geometry": {"coordinates":[-72.697986,42.173851],"type":"Point"}
}