{
  "type": "Feature",
  "properties": {
    "addr:full": "143 Walker Pond Rd Sturbridge MA 01566",
    "addr:housenumber": "143",
    "addr:postcode": "01566",
    "addr:street": "Walker Pond Rd",
    "iso:country": "US",
    "sg:address": "143 Walker Pond Rd",
    "sg:city": "Sturbridge",
    "sg:classifiers": [
      {
        "category": "Insurance",
        "subcategory": "Insurance Agent",
        "type": "Services"
      }
    ],
    "sg:phone": "+1   ",
    "sg:postcode": "01566",
    "sg:province": "MA",
    "wof:name": "Joseph Insurance Agency Inc",
    "wof:placetype": "venue"
  },
  "geometry": {"coordinates":[-72.055861,42.145845],"type":"Point"}
}
