{
  "type": "Feature",
  "properties": {
    "iso:country":"US",
    "sg:address":"65 Bay State Dr",
    "sg:city":"Braintree",
    "sg:classifiers":[
        {
            "category":"Professional",
            "subcategory":"Advertising",
            "type":"Services"
        }
    ],
    "sg:phone":"+1 781 356 7800",
    "sg:postcode":"02184",
    "sg:province":"MA",
    "sg:tags":[
        "distribution"
    ],
    "wof:name":"Superseal Manufacturing",
    "wof:placetype":"venue"
},
  "geometry": {"coordinates":[-71.02965,42.200701],"type":"Point"}
}