{
  "type": "Feature",
  "properties": {
    "addr:full":"54 Cummings Park Woburn MA 01801",
    "addr:housenumber":"54",
    "addr:postcode":"01801",
    "addr:street":"Cummings Park",
    "iso:country":"US",
    "sg:address":"54 Cummings Park",
    "sg:city":"Woburn",
    "sg:classifiers":[
        {
            "category":"Building & Trades",
            "subcategory":"Locksmith",
            "type":"Services"
        }
    ],
    "sg:phone":"+1 781 904 0392",
    "sg:postcode":"01801",
    "sg:province":"MA",
    "sg:tags":[
        "key"
    ],
    "wof:name":"24 Hour 7 Day Emergency Locksmith",
    "wof:placetype":"venue"
},
  "geometry": {"coordinates":[-71.124403,42.497824],"type":"Point"}
}