{
  "type": "Feature",
  "properties": {
    "addr:full": "771 Page Blvd Springfield MA 01104",
    "addr:housenumber": "771",
    "addr:postcode": "01104",
    "addr:street": "Page Blvd",
    "iso:country": "US",
    "sg:address": "771 Page Blvd",
    "sg:city": "Springfield",
    "sg:classifiers": [
      {
        "category": "Restaurant",
        "type": "Food \u0026 Drink"
      }
    ],
    "sg:menulink": "http://www.allmenus.com/ma/springfield/188730-mcdonalds/menu/",
    "sg:postcode": "01104",
    "sg:province": "MA",
    "sg:tags": [
      "burger",
      "american"
    ],
    "wof:name": "McDonald's",
    "wof:placetype": "venue"
  },
  "geometry": {"coordinates":[-72.554072,42.142928],"type":"Point"}
}
