{
  "type": "Feature",
  "properties": {
    "iso:country":"US",
    "sg:address":"771 Page Blvd",
    "sg:city":"Springfield",
    "sg:classifiers":[
        {
            "category":"Restaurant",
            "type":"Food & Drink"
        }
    ],
    "sg:menulink":"http://www.allmenus.com/ma/springfield/188730-mcdonalds/menu/",
    "sg:postcode":"01104",
    "sg:province":"MA",
    "sg:tags":[
        "burger",
        "american"
    ],
    "wof:name":"McDonald's",
    "wof:placetype":"venue"
},
  "geometry": {"coordinates":[-72.55407200000001,42.142928],"type":"Point"}
}