{
  "type": "Feature",
  "properties": {
    "iso:country":"US",
    "sg:address":"1359 Acushnet Ave",
    "sg:city":"New Bedford",
    "sg:classifiers":[
        {
            "category":"Organizations",
            "subcategory":"Religious Organization",
            "type":"Services"
        }
    ],
    "sg:phone":"+1 508 993 1691",
    "sg:postcode":"02746",
    "sg:province":"MA",
    "sg:tags":[
        "church"
    ],
    "wof:name":"St Anthony Of Padua Parish",
    "wof:placetype":"venue"
},
  "geometry": {"coordinates":[-70.927528,41.660486],"type":"Point"}
}