{
  "type": "Feature",
  "properties": {
    "iso:country":"US",
    "sg:address":"22 Brook St",
    "sg:city":"Quincy",
    "sg:classifiers":[
        {
            "category":"Personal",
            "subcategory":"Tanning Parlor",
            "type":"Services"
        }
    ],
    "sg:phone":"+1 617 479 3623",
    "sg:postcode":"02170",
    "sg:province":"MA",
    "sg:tags":[
        "salon"
    ],
    "wof:name":"Super Tan",
    "wof:placetype":"venue"
},
  "geometry": {"coordinates":[-71.02169499999999,42.265693],"type":"Point"}
}