{
  "type": "Feature",
  "properties": {
    "addr:full": "101 Summer St Holliston MA 01746",
    "addr:housenumber": "101",
    "addr:postcode": "01746",
    "addr:street": "Summer St",
    "iso:country": "US",
    "sg:address": "101 Summer St",
    "sg:city": "Holliston",
    "sg:classifiers": [
      {
        "category": "Shopping",
        "subcategory": "Gifts \u0026 Souvenirs",
        "type": "Retail Goods"
      }
    ],
    "sg:phone": "+1 508 429 8172",
    "sg:postcode": "01746",
    "sg:province": "MA",
    "sg:tags": [
      "shop"
    ],
    "wof:name": "Our Lady Of Fatima Shrine",
    "wof:placetype": "venue"
  },
  "geometry": {"coordinates":[-71.44447,42.180465],"type":"Point"}
}
