{
  "type": "Feature",
  "properties": {
    "addr:full": "879 N Main St Fall River MA 02720",
    "addr:housenumber": "879",
    "addr:postcode": "02720",
    "addr:street": "N Main St",
    "iso:country": "US",
    "sg:address": "879 N Main St",
    "sg:city": "Fall River",
    "sg:classifiers": [
      {
        "category": "Social Services",
        "type": "Services"
      }
    ],
    "sg:phone": "+1 508 672 4237",
    "sg:postcode": "02720",
    "sg:province": "MA",
    "sg:tags": [
      "counselor",
      "marriage",
      "family"
    ],
    "wof:name": "True Hope Professional Counsel",
    "wof:placetype": "venue"
  },
  "geometry": {"coordinates":[-71.152917,41.713489],"type":"Point"}
}
