{
  "type": "Feature",
  "properties": {
    "iso:country":"US",
    "sg:address":"127 W Silver St",
    "sg:city":"Westfield",
    "sg:classifiers":[
        {
            "category":"Professional",
            "subcategory":"Lawyer & Legal Services",
            "type":"Services"
        }
    ],
    "sg:phone":"+1 413 568 7913",
    "sg:postcode":"01085",
    "sg:province":"MA",
    "sg:tags":[
        "plan"
    ],
    "wof:name":"Albert & Amelia Ferst Cha",
    "wof:placetype":"venue"
},
  "geometry": {"coordinates":[-72.761169,42.11816],"type":"Point"}
}