{
  "type": "Feature",
  "properties": {
    "addr:full": "742 N Hoosac Rd Williamstown MA 01267",
    "addr:housenumber": "742",
    "addr:postcode": "01267",
    "addr:street": "N Hoosac Rd",
    "iso:country": "US",
    "sg:address": "742 N Hoosac Rd",
    "sg:city": "Williamstown",
    "sg:classifiers": [
      {
        "category": "Food \u0026 Beverages",
        "subcategory": "Groceries \u0026 Convenience Stores",
        "type": "Retail Goods"
      }
    ],
    "sg:phone": "+1 413 458 4142",
    "sg:postcode": "01267",
    "sg:province": "MA",
    "sg:tags": [
      "market"
    ],
    "wof:name": "Tupelo Honey Market Place",
    "wof:placetype": "venue"
  },
  "geometry": {"coordinates":[-73.189426,42.721659],"type":"Point"}
}
