{
  "type": "Feature",
  "properties": {
    "iso:country":"US",
    "sg:address":"285 Main St",
    "sg:city":"Rutland",
    "sg:classifiers":[
        {
            "category":"Social Services",
            "subcategory":"Child Care",
            "type":"Services"
        }
    ],
    "sg:phone":"+1 508 886 2732",
    "sg:postcode":"01543",
    "sg:province":"MA",
    "wof:name":"Safe Place",
    "wof:placetype":"venue"
},
  "geometry": {"coordinates":[-71.955173,42.376146],"type":"Point"}
}