{
  "type": "Feature",
  "properties": {
    "addr:full": "40 Samoset St Plymouth MA 02360",
    "addr:housenumber": "40",
    "addr:postcode": "02360",
    "addr:street": "Samoset St",
    "iso:country": "US",
    "sg:address": "40 Samoset St",
    "sg:city": "Plymouth",
    "sg:classifiers": [
      {
        "category": "Retail",
        "subcategory": "Auto Rental",
        "type": "Services"
      }
    ],
    "sg:phone": "+1 508 747 1212",
    "sg:postcode": "02360",
    "sg:province": "MA",
    "sg:tags": [
      "car"
    ],
    "sg:website": "www.enterprise.com",
    "wof:name": "Enterprise Rent-A-Car",
    "wof:placetype": "venue"
  },
  "geometry": {"coordinates":[-70.674301,41.957802],"type":"Point"}
}
