{
  "type": "Feature",
  "properties": {
    "iso:country":"US",
    "sg:address":"1707 Massachusetts Avenue Suite 5",
    "sg:city":"Lexington",
    "sg:classifiers":[
        {
            "category":"Personal",
            "subcategory":"Shoe Repair & Shine",
            "type":"Services"
        }
    ],
    "sg:phone":"+1 781 861 8033",
    "sg:postcode":"02420",
    "sg:province":"MA",
    "wof:name":"Colonial Shoe Repair",
    "wof:placetype":"venue"
},
  "geometry": {"coordinates":[-71.22635200000001,42.44711],"type":"Point"}
}