{
  "type": "Feature",
  "properties": {
    "addr:full": "130 Merrimack St Methuen MA 01844",
    "addr:housenumber": "130",
    "addr:postcode": "01844",
    "addr:street": "Merrimack St",
    "iso:country": "US",
    "sg:address": "130 Merrimack St",
    "sg:city": "Methuen",
    "sg:classifiers": [
      {
        "category": "Retail",
        "subcategory": "Auto Repair",
        "type": "Services"
      }
    ],
    "sg:phone": "+1   ",
    "sg:postcode": "01844",
    "sg:province": "MA",
    "sg:tags": [
      "general"
    ],
    "wof:name": "Foreign Car Works",
    "wof:placetype": "venue"
  },
  "geometry": {"coordinates":[-71.137256,42.730272],"type":"Point"}
}
