{
  "type": "Feature",
  "properties": {
    "iso:country":"US",
    "sg:address":"106 Main St",
    "sg:city":"Rutland",
    "sg:classifiers":[
        {
            "category":"Banks & Credit Unions",
            "subcategory":"Financial Services",
            "type":"Services"
        }
    ],
    "sg:phone":"+1 508 886 6920",
    "sg:postcode":"01543",
    "sg:province":"MA",
    "sg:tags":[
        "investor"
    ],
    "wof:name":"Hawthorne Hill Elderly Housing",
    "wof:placetype":"venue"
},
  "geometry": {"coordinates":[-71.938631,42.378817],"type":"Point"}
}