{
  "type": "Feature",
  "properties": {
    "iso:country":"US",
    "sg:address":"327 Roosevelt Ave",
    "sg:city":"Springfield",
    "sg:classifiers":[
        {
            "category":"Building & Trades",
            "subcategory":"Plumbing",
            "type":"Services"
        }
    ],
    "sg:phone":"+1 413 732 4719",
    "sg:postcode":"01118",
    "sg:province":"MA",
    "sg:tags":[
        "plumbing",
        "business",
        "contractor"
    ],
    "wof:name":"Puppolo Plumbing and Heating",
    "wof:placetype":"venue"
},
  "geometry": {"coordinates":[-72.53804,42.099476],"type":"Point"}
}