{
  "type": "Feature",
  "properties": {
    "iso:country":"US",
    "sg:address":"161 High St",
    "sg:city":"Greenfield",
    "sg:classifiers":[
        {
            "category":"Building & Trades",
            "subcategory":"Cleaning & Sanitation",
            "type":"Services"
        }
    ],
    "sg:phone":"+1 413 773 9203",
    "sg:postcode":"01301",
    "sg:province":"MA",
    "sg:tags":[
        "janitorial"
    ],
    "wof:name":"D D Ventures",
    "wof:placetype":"venue"
},
  "geometry": {"coordinates":[-72.59161,42.595279],"type":"Point"}
}