{
  "type": "Feature",
  "properties": {
    "addr:full": "161 High St Greenfield MA 01301",
    "addr:housenumber": "161",
    "addr:postcode": "01301",
    "addr:street": "High St",
    "iso:country": "US",
    "sg:address": "161 High St",
    "sg:city": "Greenfield",
    "sg:classifiers": [
      {
        "category": "Building \u0026 Trades",
        "subcategory": "Cleaning \u0026 Sanitation",
        "type": "Services"
      }
    ],
    "sg:phone": "+1 413 773 9203",
    "sg:postcode": "01301",
    "sg:province": "MA",
    "sg:tags": [
      "janitorial"
    ],
    "wof:name": "D D Ventures",
    "wof:placetype": "venue"
  },
  "geometry": {"coordinates":[-72.59161,42.595279],"type":"Point"}
}
