{
  "type": "Feature",
  "properties": {
    "addr:full": "99 Mill St Springfield MA 01108",
    "addr:housenumber": "99",
    "addr:postcode": "01108",
    "addr:street": "Mill St",
    "iso:country": "US",
    "sg:address": "99 Mill St",
    "sg:city": "Springfield",
    "sg:classifiers": [
      {
        "category": "Professional",
        "subcategory": "Employment Agencies",
        "type": "Services"
      }
    ],
    "sg:phone": "+1 413 733 9506",
    "sg:postcode": "01108",
    "sg:province": "MA",
    "sg:tags": [
      "contractor"
    ],
    "wof:name": "Summit Temps",
    "wof:placetype": "venue"
  },
  "geometry": {"coordinates":[-72.575889,42.091282],"type":"Point"}
}
