{
  "type": "Feature",
  "properties": {
    "iso:country":"US",
    "sg:address":"135 Meadow Ln",
    "sg:city":"Boxborough",
    "sg:classifiers":[
        {
            "category":"Professional",
            "subcategory":"Lawyer & Legal Services",
            "type":"Services"
        }
    ],
    "sg:phone":"+1 978 263 4499",
    "sg:postcode":"01719",
    "sg:province":"MA",
    "sg:tags":[
        "attorney"
    ],
    "wof:name":"Barry S Harsip",
    "wof:placetype":"venue"
},
  "geometry": {"coordinates":[-71.51949,42.471197],"type":"Point"}
}