{
  "type": "Feature",
  "properties": {
    "iso:country":"US",
    "sg:address":"482 Southbridge St",
    "sg:city":"Auburn",
    "sg:classifiers":[
        {
            "category":"Health Services",
            "subcategory":"Doctor",
            "type":"Services"
        }
    ],
    "sg:phone":"+1 508 832 0011",
    "sg:postcode":"01501",
    "sg:province":"MA",
    "sg:tags":[
        "clinic"
    ],
    "wof:name":"Auburn Mens Clinic",
    "wof:placetype":"venue"
},
  "geometry": {"coordinates":[-71.84137,42.199417],"type":"Point"}
}