{
  "type": "Feature",
  "properties": {
    "addr:full":"868 Springfield St Agawam MA 01001",
    "addr:housenumber":"868",
    "addr:postcode":"01001",
    "addr:street":"Springfield St",
    "iso:country":"US",
    "sg:address":"868 Springfield St",
    "sg:city":"Agawam",
    "sg:classifiers":[
        {
            "category":"Insurance",
            "subcategory":"Hazard Insurance",
            "type":"Services"
        },
        {
            "category":"Insurance",
            "subcategory":"Insurance Agent",
            "type":"Services"
        },
        {
            "category":"Professional",
            "subcategory":"Lawyer & Legal Services",
            "type":"Services"
        },
        {
            "category":"Insurance",
            "subcategory":"Title Insurance",
            "type":"Services"
        },
        {
            "category":"Insurance",
            "subcategory":"Life Insurance",
            "type":"Services"
        }
    ],
    "sg:phone":"+1 413 789 3995",
    "sg:postcode":"01001",
    "sg:province":"MA",
    "sg:tags":[
        "auto",
        "attorney",
        "renter",
        "homeowner"
    ],
    "sg:website":"http://www.canaryblomstrom.com",
    "wof:name":"Canary Blomstrom Insurance Agency Inc",
    "wof:placetype":"venue"
},
  "geometry": {"coordinates":[-72.64509200000001,42.08375],"type":"Point"}
}