{
  "type": "Feature",
  "properties": {
    "iso:country":"US",
    "sg:address":"978 Gorham St",
    "sg:city":"Lowell",
    "sg:classifiers":[
        {
            "category":"Retail",
            "subcategory":"Laundry & Dry Cleaning",
            "type":"Services"
        }
    ],
    "sg:phone":"+1 978 446 9559",
    "sg:postcode":"01852",
    "sg:province":"MA",
    "wof:name":"Gorham St Laundromat",
    "wof:placetype":"venue"
},
  "geometry": {"coordinates":[-71.308076,42.628734],"type":"Point"}
}