{
  "type": "Feature",
  "properties": {
    "addr:full": "1 Knob Ln Buzzards Bay MA 02532",
    "addr:housenumber": "1",
    "addr:postcode": "02532",
    "addr:street": "Knob Ln",
    "iso:country": "US",
    "sg:address": "1 Knob Ln",
    "sg:city": "Buzzards Bay",
    "sg:classifiers": [
      {
        "category": "Professional",
        "subcategory": "Accounting \u0026 Tax Preparation",
        "type": "Services"
      }
    ],
    "sg:phone": "+1 508 759 4342",
    "sg:postcode": "02532",
    "sg:province": "MA",
    "sg:tags": [
      "accountant"
    ],
    "wof:name": "May Donald A CPA",
    "wof:placetype": "venue"
  },
  "geometry": {"coordinates":[-70.600098,41.760601],"type":"Point"}
}
