{
  "type": "Feature",
  "properties": {
    "iso:country":"US",
    "sg:address":"1 Knob Ln",
    "sg:city":"Buzzards Bay",
    "sg:classifiers":[
        {
            "category":"Professional",
            "subcategory":"Accounting & Tax Preparation",
            "type":"Services"
        }
    ],
    "sg:phone":"+1 508 759 4342",
    "sg:postcode":"02532",
    "sg:province":"MA",
    "sg:tags":[
        "accountant"
    ],
    "wof:name":"May Donald A CPA",
    "wof:placetype":"venue"
},
  "geometry": {"coordinates":[-70.600098,41.760601],"type":"Point"}
}