{
  "type": "Feature",
  "properties": {
    "iso:country":"US",
    "sg:address":"85 Lincoln St",
    "sg:city":"Framingham",
    "sg:classifiers":[
        {
            "category":"Health Services",
            "subcategory":"Health Practitioner",
            "type":"Services"
        }
    ],
    "sg:phone":"+1 508 370 7344",
    "sg:postcode":"01702",
    "sg:province":"MA",
    "sg:tags":[
        "occupational",
        "safety"
    ],
    "wof:name":"Fallon Clinic",
    "wof:placetype":"venue"
},
  "geometry": {"coordinates":[-71.41841100000001,42.28348],"type":"Point"}
}