{
  "type": "Feature",
  "properties": {
    "addr:full": "139 Pleasant St Tewksbury MA 01876",
    "addr:housenumber": "139",
    "addr:postcode": "01876",
    "addr:street": "Pleasant St",
    "iso:country": "US",
    "sg:address": "139 Pleasant St",
    "sg:city": "Tewksbury",
    "sg:classifiers": [
      {
        "category": "Education",
        "subcategory": "School",
        "type": "Public Place"
      },
      {
        "category": "Education",
        "subcategory": "Special Training",
        "type": "Public Place"
      }
    ],
    "sg:phone": "+1 978 640 7805",
    "sg:postcode": "01876",
    "sg:province": "MA",
    "sg:tags": [
      "educational"
    ],
    "sg:website": "www.mec.edu/tewksbury",
    "wof:name": "Tewksbury Town School Dept",
    "wof:placetype": "venue"
  },
  "geometry": {"coordinates":[-71.238181,42.606853],"type":"Point"}
}
