{
  "type": "Feature",
  "properties": {
    "iso:country":"US",
    "sg:address":"50 Jackson St",
    "sg:city":"Dracut",
    "sg:classifiers":[
        {
            "category":"Wholesale",
            "subcategory":"Scrap",
            "type":"Manufacturing & Wholesale Goods"
        }
    ],
    "sg:phone":"+1 978 458 6502",
    "sg:postcode":"01826",
    "sg:province":"MA",
    "sg:tags":[
        "recycling",
        "center"
    ],
    "wof:name":"Agretech Corp",
    "wof:placetype":"venue"
},
  "geometry": {"coordinates":[-71.252825,42.663022],"type":"Point"}
}