{
  "type": "Feature",
  "properties": {
    "addr:full": "50 Jackson St Dracut MA 01826",
    "addr:housenumber": "50",
    "addr:postcode": "01826",
    "addr:street": "Jackson St",
    "iso:country": "US",
    "ovtr:label": "Agretech Corp, 50 Jackson St Dracut MA US",
    "ovtr:similarity": 1.9610060453414917,
    "sg:address": "50 Jackson St",
    "sg:city": "Dracut",
    "sg:classifiers": [
      {
        "category": "Wholesale",
        "subcategory": "Scrap",
        "type": "Manufacturing \u0026 Wholesale Goods"
      }
    ],
    "sg:phone": "+1 978 458 6502",
    "sg:postcode": "01826",
    "sg:province": "MA",
    "sg:tags": [
      "recycling",
      "center"
    ],
    "wof:name": "Agretech Corp",
    "wof:placetype": "venue"
  },
  "geometry": {"coordinates":[-71.252825,42.663022],"type":"Point"}
}
