{
  "type": "Feature",
  "properties": {
    "addr:full": "222 Cambridge St Burlington MA 01803",
    "addr:housenumber": "222",
    "addr:postcode": "01803",
    "addr:street": "Cambridge St",
    "iso:country": "US",
    "sg:address": "222 Cambridge St",
    "sg:city": "Burlington",
    "sg:classifiers": [
      {
        "category": "Restaurant",
        "type": "Food \u0026 Drink"
      }
    ],
    "sg:menulink": "http://www.allmenus.com/ma/burlington/49248-the-pizza-works/menu/",
    "sg:phone": "+1 781 229 6757",
    "sg:postcode": "01803",
    "sg:province": "MA",
    "sg:tags": [
      "american",
      "pizza"
    ],
    "wof:name": "The Pizza Works",
    "wof:placetype": "venue"
  },
  "geometry": {"coordinates":[-71.201875,42.512132],"type":"Point"}
}
