{
  "type": "Feature",
  "properties": {
    "addr:full":"37 Main St Charlton MA 01507",
    "addr:housenumber":"37",
    "addr:postcode":"01507",
    "addr:street":"Main St",
    "iso:country":"US",
    "sg:address":"37 Main St",
    "sg:city":"Charlton",
    "sg:classifiers":[
        {
            "category":"Government",
            "subcategory":"Office",
            "type":"Public Place"
        }
    ],
    "sg:phone":"+1 508 248 2233",
    "sg:postcode":"01507",
    "sg:province":"MA",
    "sg:tags":[
        "city",
        "taxation",
        "village"
    ],
    "wof:name":"Charlton Assessors Office",
    "wof:placetype":"venue"
},
  "geometry": {"coordinates":[-71.969323,42.134205],"type":"Point"}
}