{
  "type": "Feature",
  "properties": {
    "addr:full": "390 Proctor Ave Revere MA 02151",
    "addr:housenumber": "390",
    "addr:postcode": "02151",
    "addr:street": "Proctor Ave",
    "iso:country": "US",
    "sg:address": "390 Proctor Ave",
    "sg:city": "Revere",
    "sg:classifiers": [
      {
        "category": "Professional",
        "subcategory": "Business Services",
        "type": "Services"
      },
      {
        "category": "Wholesale",
        "subcategory": "Books, Periodicals, \u0026 Newspapers",
        "type": "Manufacturing \u0026 Wholesale Goods"
      }
    ],
    "sg:phone": "+1 781 284 0743",
    "sg:postcode": "02151",
    "sg:province": "MA",
    "sg:tags": [
      "consultant",
      "publishing",
      "representative",
      "publisher"
    ],
    "wof:name": "Oceanview Enterprises",
    "wof:placetype": "venue"
  },
  "geometry": {"coordinates":[-71.02453,42.416315],"type":"Point"}
}
