{
  "type": "Feature",
  "properties": {
    "addr:full": "31 Warwick St Lawrence MA 01841",
    "addr:housenumber": "31",
    "addr:postcode": "01841",
    "addr:street": "Warwick St",
    "iso:country": "US",
    "sg:address": "31 Warwick St",
    "sg:city": "Lawrence",
    "sg:classifiers": [
      {
        "category": "Manufacturing",
        "subcategory": "Metals",
        "type": "Manufacturing \u0026 Wholesale Goods"
      }
    ],
    "sg:phone": "+1 978 683 1984",
    "sg:postcode": "01841",
    "sg:province": "MA",
    "sg:tags": [
      "work"
    ],
    "wof:name": "Universal Iron Works Co",
    "wof:placetype": "venue"
  },
  "geometry": {"coordinates":[-71.189951,42.706029],"type":"Point"}
}
