{
  "type": "Feature",
  "properties": {
    "addr:full": "70 Branch Ter Marstons Mills MA 02648",
    "addr:housenumber": "70",
    "addr:postcode": "02648",
    "addr:street": "Branch Ter",
    "iso:country": "US",
    "sg:address": "70 Branch Ter",
    "sg:city": "Marstons Mills",
    "sg:classifiers": [
      {
        "category": "Building \u0026 Trades",
        "subcategory": "Construction",
        "type": "Services"
      }
    ],
    "sg:phone": "+1 508 420 4502",
    "sg:postcode": "02648",
    "sg:province": "MA",
    "sg:tags": [
      "masonry",
      "contractor"
    ],
    "wof:name": "John Lopes \u0026 Sons Concrete",
    "wof:placetype": "venue"
  },
  "geometry": {"coordinates":[-70.38463,41.678354],"type":"Point"}
}
