{
  "type": "Feature",
  "properties": {
    "iso:country":"US",
    "sg:address":"70 Branch Ter",
    "sg:city":"Marstons Mills",
    "sg:classifiers":[
        {
            "category":"Building & Trades",
            "subcategory":"Construction",
            "type":"Services"
        }
    ],
    "sg:phone":"+1 508 420 4502",
    "sg:postcode":"02648",
    "sg:province":"MA",
    "sg:tags":[
        "masonry",
        "contractor"
    ],
    "wof:name":"John Lopes & Sons Concrete",
    "wof:placetype":"venue"
},
  "geometry": {"coordinates":[-70.38463,41.678354],"type":"Point"}
}