{
  "type": "Feature",
  "properties": {
    "iso:country":"US",
    "sg:address":"34 S Broad St",
    "sg:city":"Westfield",
    "sg:classifiers":[
        {
            "category":"Manufacturing",
            "subcategory":"Wood Products",
            "type":"Manufacturing & Wholesale Goods"
        }
    ],
    "sg:phone":"+1 413 568 3511",
    "sg:postcode":"01085",
    "sg:province":"MA",
    "sg:tags":[
        "pallet",
        "skid"
    ],
    "wof:name":"Day Lumber Co",
    "wof:placetype":"venue"
},
  "geometry": {"coordinates":[-72.74772400000001,42.111995],"type":"Point"}
}