{
  "type": "Feature",
  "properties": {
    "iso:country":"US",
    "sg:address":"33 Fish Pier",
    "sg:city":"Boston",
    "sg:classifiers":[
        {
            "category":"Building & Trades",
            "subcategory":"Locksmith",
            "type":"Services"
        }
    ],
    "sg:phone":"+1 617 272 4316",
    "sg:postcode":"02210",
    "sg:province":"MA",
    "sg:tags":[
        "key"
    ],
    "wof:name":"Locksmith Services",
    "wof:placetype":"venue"
},
  "geometry": {"coordinates":[-71.038597,42.350082],"type":"Point"}
}