{
  "type": "Feature",
  "properties": {
    "addr:full": "57 Pine St Warren MA 01083",
    "addr:housenumber": "57",
    "addr:postcode": "01083",
    "addr:street": "Pine St",
    "iso:country": "US",
    "sg:address": "57 Pine St",
    "sg:city": "Warren",
    "sg:classifiers": [
      {
        "category": "Building \u0026 Trades",
        "subcategory": "Landscaping Services",
        "type": "Services"
      }
    ],
    "sg:phone": "+1 413 436 5449",
    "sg:postcode": "01083",
    "sg:province": "MA",
    "sg:tags": [
      "tree"
    ],
    "wof:name": "Ken's Tree Removal \u0026 Land",
    "wof:placetype": "venue"
  },
  "geometry": {"coordinates":[-72.190938,42.209118],"type":"Point"}
}
