{
  "type": "Feature",
  "properties": {
    "iso:country":"US",
    "sg:address":"57 Pine St",
    "sg:city":"Warren",
    "sg:classifiers":[
        {
            "category":"Building & Trades",
            "subcategory":"Landscaping Services",
            "type":"Services"
        }
    ],
    "sg:phone":"+1 413 436 5449",
    "sg:postcode":"01083",
    "sg:province":"MA",
    "sg:tags":[
        "tree"
    ],
    "wof:name":"Ken's Tree Removal & Land",
    "wof:placetype":"venue"
},
  "geometry": {"coordinates":[-72.190938,42.209118],"type":"Point"}
}