{
  "type": "Feature",
  "properties": {
    "iso:country":"US",
    "sg:address":"19 Stony Brook Rd",
    "sg:city":"Marblehead",
    "sg:classifiers":[
        {
            "category":"Building & Trades",
            "subcategory":"Construction",
            "type":"Services"
        }
    ],
    "sg:phone":"+1 781 631 9407",
    "sg:postcode":"01945",
    "sg:province":"MA",
    "sg:tags":[
        "masonry",
        "contractor",
        "mason"
    ],
    "wof:name":"C T Titus Mason Contractor",
    "wof:placetype":"venue"
},
  "geometry": {"coordinates":[-70.851669,42.511589],"type":"Point"}
}