{
  "type": "Feature",
  "properties": {
    "addr:full": "354 Adams St Dorchester MA 02122",
    "addr:housenumber": "354",
    "addr:postcode": "02122",
    "addr:street": "Adams St",
    "iso:country": "US",
    "sg:address": "354 Adams St",
    "sg:city": "Dorchester",
    "sg:classifiers": [
      {
        "category": "Cemetery",
        "type": "Public Place"
      }
    ],
    "sg:phone": "+1 508 695 5651",
    "sg:postcode": "02122",
    "sg:province": "MA",
    "sg:tags": [
      "crematory"
    ],
    "sg:website": "http://www.sperrymchoul.com",
    "wof:name": "Sperry \u0026 Mc Houl Inc",
    "wof:placetype": "venue"
  },
  "geometry": {"coordinates":[-71.056475,42.297396],"type":"Point"}
}
