{
  "type": "Feature",
  "properties": {
    "addr:full":"110 Cambridge Street Burlington MA 01803",
    "addr:housenumber":"110",
    "addr:postcode":"01803",
    "addr:street":"Cambridge Street",
    "iso:country":"US",
    "sg:address":"110 Cambridge Street",
    "sg:city":"Burlington",
    "sg:classifiers":[
        {
            "category":"Autos & Motor Vehicles",
            "subcategory":"Fuel & Gas Station",
            "type":"Retail Goods"
        }
    ],
    "sg:phone":"+1 781 229 1862",
    "sg:postcode":"01803",
    "sg:province":"MA",
    "wof:name":"Hess",
    "wof:placetype":"venue"
},
  "geometry": {"coordinates":[-71.193832,42.498038],"type":"Point"}
}