{
  "type": "Feature",
  "properties": {
    "addr:full": "19 Salem St Medford MA 02155",
    "addr:housenumber": "19",
    "addr:postcode": "02155",
    "addr:street": "Salem St",
    "iso:country": "US",
    "sg:address": "19 Salem St",
    "sg:city": "Medford",
    "sg:classifiers": [
      {
        "category": "Professional",
        "subcategory": "Business Services",
        "type": "Services"
      }
    ],
    "sg:phone": "+1   ",
    "sg:postcode": "02155",
    "sg:province": "MA",
    "wof:name": "Primerica",
    "wof:placetype": "venue"
  },
  "geometry": {"coordinates":[-71.108812,42.418329],"type":"Point"}
}
