{
  "type": "Feature",
  "properties": {
    "iso:country":"US",
    "sg:address":"86 Spring St",
    "sg:city":"Williamstown",
    "sg:classifiers":[
        {
            "category":"Professional",
            "subcategory":"Management & Consulting",
            "type":"Services"
        }
    ],
    "sg:phone":"+1 413 458 1356",
    "sg:postcode":"01267",
    "sg:province":"MA",
    "sg:tags":[
        "marketing",
        "consultant"
    ],
    "wof:name":"Greylock Media",
    "wof:placetype":"venue"
},
  "geometry": {"coordinates":[-73.204599,42.709731],"type":"Point"}
}