{
  "type": "Feature",
  "properties": {
    "iso:country":"US",
    "sg:address":"503 Plymouth St",
    "sg:city":"Halifax",
    "sg:classifiers":[
        {
            "category":"Place Of Worship",
            "subcategory":"Church",
            "type":"Public Place"
        },
        {
            "category":"Place Of Worship",
            "type":"Public Place"
        }
    ],
    "sg:phone":"+1 781 293 6393",
    "sg:postcode":"02338",
    "sg:province":"MA",
    "sg:tags":[
        "testament",
        "churches-church",
        "christ",
        "christ-new"
    ],
    "wof:name":"United Church Of Christ",
    "wof:placetype":"venue"
},
  "geometry": {"coordinates":[-70.8601,41.991051],"type":"Point"}
}