{
  "type": "Feature",
  "properties": {
    "addr:full": "55 Van Deene Ave West Springfield MA 01089",
    "addr:housenumber": "55",
    "addr:postcode": "01089",
    "addr:street": "Van Deene Ave",
    "iso:country": "US",
    "sg:address": "55 Van Deene Ave",
    "sg:city": "West Springfield",
    "sg:classifiers": [
      {
        "category": "Real Estate",
        "subcategory": "Real Estate Operator",
        "type": "Services"
      }
    ],
    "sg:phone": "+1 413 737 0001",
    "sg:postcode": "01089",
    "sg:province": "MA",
    "sg:tags": [
      "apartment"
    ],
    "wof:name": "Security Manor",
    "wof:placetype": "venue"
  },
  "geometry": {"coordinates":[-72.625636,42.106118],"type":"Point"}
}
