{
  "type": "Feature",
  "properties": {
    "addr:full": "616 Main St Shrewsbury MA 01545",
    "addr:housenumber": "616",
    "addr:postcode": "01545",
    "addr:street": "Main St",
    "iso:country": "US",
    "sg:address": "616 Main St",
    "sg:city": "Shrewsbury",
    "sg:classifiers": [
      {
        "category": "Professional",
        "subcategory": "Lawyer \u0026 Legal Services",
        "type": "Services"
      }
    ],
    "sg:phone": "+1 508 842 4993",
    "sg:postcode": "01545",
    "sg:province": "MA",
    "sg:tags": [
      "attorney"
    ],
    "wof:name": "Kevin J Shea",
    "wof:placetype": "venue"
  },
  "geometry": {"coordinates":[-71.713661,42.296637],"type":"Point"}
}
