{
  "type": "Feature",
  "properties": {
    "iso:country":"US",
    "sg:address":"4 Kennedy Dr",
    "sg:city":"North Chelmsford",
    "sg:classifiers":[
        {
            "category":"Retail",
            "subcategory":"Repair Shop",
            "type":"Services"
        }
    ],
    "sg:phone":"+1 978 251 7877",
    "sg:postcode":"01863",
    "sg:province":"MA",
    "sg:tags":[
        "typewriter"
    ],
    "wof:name":"Merrimack Valley Business Mach",
    "wof:placetype":"venue"
},
  "geometry": {"coordinates":[-71.38180699999999,42.63919],"type":"Point"}
}