{
  "type": "Feature",
  "properties": {
    "addr:full": "128 E Main St Webster MA 01570",
    "addr:housenumber": "128",
    "addr:postcode": "01570",
    "addr:street": "E Main St",
    "iso:country": "US",
    "ovtr:label": "Burger King, 128 E Main St Webster MA US",
    "ovtr:similarity": 2.7606101036071777,
    "sg:address": "128 E Main St",
    "sg:city": "Webster",
    "sg:classifiers": [
      {
        "category": "Restaurant",
        "type": "Food \u0026 Drink"
      }
    ],
    "sg:menulink": "http://www.allmenus.com/ma/webster/197596-burger-king/menu/",
    "sg:phone": "+1 508 949 0848",
    "sg:postcode": "01570",
    "sg:province": "MA",
    "sg:tags": [
      "burger",
      "american"
    ],
    "wof:name": "Burger King",
    "wof:placetype": "venue"
  },
  "geometry": {"coordinates":[-71.865518,42.05934],"type":"Point"}
}
