{
  "type": "Feature",
  "properties": {
    "iso:country":"US",
    "sg:address":"128 E Main St",
    "sg:city":"Webster",
    "sg:classifiers":[
        {
            "category":"Restaurant",
            "type":"Food & Drink"
        }
    ],
    "sg:menulink":"http://www.allmenus.com/ma/webster/197596-burger-king/menu/",
    "sg:phone":"+1 508 949 0848",
    "sg:postcode":"01570",
    "sg:province":"MA",
    "sg:tags":[
        "burger",
        "american"
    ],
    "wof:name":"Burger King",
    "wof:placetype":"venue"
},
  "geometry": {"coordinates":[-71.86551799999999,42.05934],"type":"Point"}
}