{
  "type": "Feature",
  "properties": {
    "iso:country":"US",
    "sg:address":"18 Kellogg Ave",
    "sg:city":"Amherst",
    "sg:classifiers":[
        {
            "category":"Retail",
            "subcategory":"Repair Shop",
            "type":"Services"
        }
    ],
    "sg:phone":"+1 413 256 0936",
    "sg:postcode":"01002",
    "sg:province":"MA",
    "sg:tags":[
        "instrument",
        "musical"
    ],
    "sg:website":"www.stamellstring.com",
    "wof:name":"Stamell Stringed Instruments",
    "wof:placetype":"venue"
},
  "geometry": {"coordinates":[-72.519148,42.377634],"type":"Point"}
}