{
  "type": "Feature",
  "properties": {
    "addr:full": "7 State St Worcester MA 01609",
    "addr:housenumber": "7",
    "addr:postcode": "01609",
    "addr:street": "State St",
    "iso:country": "US",
    "sg:address": "7 State St",
    "sg:city": "Worcester",
    "sg:classifiers": [
      {
        "category": "Professional",
        "subcategory": "Lawyer \u0026 Legal Services",
        "type": "Services"
      }
    ],
    "sg:phone": "+1 508 752 4512",
    "sg:postcode": "01609",
    "sg:province": "MA",
    "sg:tags": [
      "attorney"
    ],
    "wof:name": "James K Holland",
    "wof:placetype": "venue"
  },
  "geometry": {"coordinates":[-71.801188,42.269701],"type":"Point"}
}
