{
  "type": "Feature",
  "properties": {
    "iso:country":"US",
    "sg:address":"11 Bradfield Ave",
    "sg:city":"Roslindale",
    "sg:classifiers":[
        {
            "category":"Building & Trades",
            "subcategory":"Plumbing",
            "type":"Services"
        }
    ],
    "sg:phone":"+1 617 325 4869",
    "sg:postcode":"02131",
    "sg:province":"MA",
    "sg:tags":[
        "plumber",
        "industrial",
        "contractors-commercial"
    ],
    "wof:name":"Mark Giordano Plumbing",
    "wof:placetype":"venue"
},
  "geometry": {"coordinates":[-71.138334,42.287839],"type":"Point"}
}