{
  "type": "Feature",
  "properties": {
    "addr:full":"759 Chief Justice Cushing Hwy Cohasset MA 02025",
    "addr:housenumber":"759",
    "addr:postcode":"02025",
    "addr:street":"Chief Justice Cushing Hwy",
    "iso:country":"US",
    "sg:address":"759 Chief Justice Cushing Hwy",
    "sg:city":"Cohasset",
    "sg:classifiers":[
        {
            "category":"Communications",
            "subcategory":"News Services",
            "type":"Services"
        },
        {
            "category":"Transit Center",
            "subcategory":"Freight",
            "type":"Transportation"
        },
        {
            "category":"Professional",
            "subcategory":"Business Services",
            "type":"Services"
        },
        {
            "category":"Professional",
            "subcategory":"Printing & Photocopies",
            "type":"Services"
        },
        {
            "category":"Government",
            "subcategory":"Post Office",
            "type":"Public Place"
        }
    ],
    "sg:phone":"+1 781 383 1711",
    "sg:postcode":"02025",
    "sg:province":"MA",
    "sg:tags":[
        "cargo",
        "fax",
        "transparency",
        "package",
        "color",
        "express",
        "duplicating",
        "shipping",
        "mailbox-rental",
        "air",
        "copying",
        "mail",
        "print",
        "notary",
        "receiving",
        "photographic"
    ],
    "sg:website":"http://www.upsstore.com",
    "wof:name":"The UPS Store",
    "wof:placetype":"venue"
},
  "geometry": {"coordinates":[-70.803416,42.222202],"type":"Point"}
}