{
  "type": "Feature",
  "properties": {
    "addr:full": "166 Central St Lowell MA 01852",
    "addr:housenumber": "166",
    "addr:postcode": "01852",
    "addr:street": "Central St",
    "iso:country": "US",
    "sg:address": "166 Central St",
    "sg:city": "Lowell",
    "sg:classifiers": [
      {
        "category": "Health Services",
        "subcategory": "Doctor",
        "type": "Services"
      }
    ],
    "sg:phone": "+1 978 459 4949",
    "sg:postcode": "01852",
    "sg:province": "MA",
    "sg:tags": [
      "dentist"
    ],
    "wof:name": "Community Dentists",
    "wof:placetype": "venue"
  },
  "geometry": {"coordinates":[-71.308439,42.643159],"type":"Point"}
}
