{
  "type": "Feature",
  "properties": {
    "iso:country":"US",
    "sg:address":"93 Main St",
    "sg:city":"Kingston",
    "sg:classifiers":[
        {
            "category":"Professional",
            "type":"Services"
        }
    ],
    "sg:phone":"+1 781 582 1290",
    "sg:postcode":"02364",
    "sg:province":"MA",
    "sg:tags":[
        "establishment"
    ],
    "wof:name":"C Sanderson Corp",
    "wof:placetype":"venue"
},
  "geometry": {"coordinates":[-70.708544,41.987635],"type":"Point"}
}