{
  "type": "Feature",
  "properties": {
    "addr:full":"185 New Boston Road Woburn MA 01880",
    "addr:housenumber":"185",
    "addr:postcode":"01880",
    "addr:street":"New Boston Road",
    "iso:country":"US",
    "sg:address":"185 New Boston Road",
    "sg:city":"Woburn",
    "sg:classifiers":[
        {
            "category":"Professional",
            "type":"Services"
        }
    ],
    "sg:phone":"+1 781 215 9515",
    "sg:postcode":"01880",
    "sg:province":"MA",
    "sg:tags":[
        "planning",
        "event"
    ],
    "wof:name":"Shutterbooth Boston",
    "wof:placetype":"venue"
},
  "geometry": {"coordinates":[-71.143953,42.512892],"type":"Point"}
}