{
  "type": "Feature",
  "properties": {
    "addr:full":"40 Pioneer Dr Lunenburg MA 01462",
    "addr:housenumber":"40",
    "addr:postcode":"01462",
    "addr:street":"Pioneer Dr",
    "iso:country":"US",
    "sg:address":"40 Pioneer Dr",
    "sg:city":"Lunenburg",
    "sg:classifiers":[
        {
            "category":"Manufacturing",
            "subcategory":"Paper Products",
            "type":"Manufacturing & Wholesale Goods"
        }
    ],
    "sg:phone":"+1 978 537 0003",
    "sg:postcode":"01462",
    "sg:province":"MA",
    "sg:tags":[
        "coated",
        "laminated"
    ],
    "sg:website":"www.ecofibers.com",
    "wof:name":"Ecological Fibers Inc",
    "wof:placetype":"venue"
},
  "geometry": {"coordinates":[-71.706926,42.534617],"type":"Point"}
}