{
  "type": "Feature",
  "properties": {
    "iso:country":"US",
    "sg:address":"735 Meadow St",
    "sg:city":"Chicopee",
    "sg:classifiers":[
        {
            "category":"Professional",
            "subcategory":"Advertising",
            "type":"Services"
        }
    ],
    "sg:phone":"+1 413 592 3605",
    "sg:postcode":"01013",
    "sg:province":"MA",
    "sg:tags":[
        "distribution"
    ],
    "wof:name":"J Polep Distribution Svc",
    "wof:placetype":"venue"
},
  "geometry": {"coordinates":[-72.614155,42.167574],"type":"Point"}
}