{
  "type": "Feature",
  "properties": {
    "addr:full": "64 Grove St East Bridgewater MA 02333",
    "addr:housenumber": "64",
    "addr:postcode": "02333",
    "addr:street": "Grove St",
    "iso:country": "US",
    "sg:address": "64 Grove St",
    "sg:city": "East Bridgewater",
    "sg:classifiers": [
      {
        "category": "Building \u0026 Trades",
        "subcategory": "Electrical",
        "type": "Services"
      }
    ],
    "sg:phone": "+1 508 378 3132",
    "sg:postcode": "02333",
    "sg:province": "MA",
    "sg:tags": [
      "electric",
      "contractor"
    ],
    "wof:name": "Meserve Electric Inc",
    "wof:placetype": "venue"
  },
  "geometry": {"coordinates":[-70.956898,42.042876],"type":"Point"}
}
