{
  "type": "Feature",
  "properties": {
    "addr:full": "53 Main St Rockport MA 01966",
    "addr:housenumber": "53",
    "addr:postcode": "01966",
    "addr:street": "Main St",
    "iso:country": "US",
    "sg:address": "53 Main St",
    "sg:city": "Rockport",
    "sg:classifiers": [
      {
        "category": "Professional",
        "subcategory": "Computer Services",
        "type": "Services"
      }
    ],
    "sg:phone": "+1 978 546 7236",
    "sg:postcode": "01966",
    "sg:province": "MA",
    "sg:tags": [
      "technical",
      "assistance",
      "support"
    ],
    "wof:name": "Blue Kid",
    "wof:placetype": "venue"
  },
  "geometry": {"coordinates":[-70.621483,42.657604],"type":"Point"}
}
