{
  "type": "Feature",
  "properties": {
    "iso:country":"US",
    "sg:address":"28 Vane St",
    "sg:city":"Quincy",
    "sg:classifiers":[
        {
            "category":"Education",
            "subcategory":"Dance Studio",
            "type":"Public Place"
        }
    ],
    "sg:phone":"+1   ",
    "sg:postcode":"02171",
    "sg:province":"MA",
    "wof:name":"In Sync Dance Co Inc",
    "wof:placetype":"venue"
},
  "geometry": {"coordinates":[-71.022752,42.272904],"type":"Point"}
}