{
  "type": "Feature",
  "properties": {
    "addr:full":"135 Turnpike Rd Westborough MA 01581",
    "addr:housenumber":"135",
    "addr:postcode":"01581",
    "addr:street":"Turnpike Rd",
    "iso:country":"US",
    "sg:address":"135 Turnpike Rd",
    "sg:city":"Westborough",
    "sg:classifiers":[
        {
            "category":"Utilities",
            "subcategory":"Mobile Phone",
            "type":"Services"
        }
    ],
    "sg:phone":"+1 508 616 9000",
    "sg:postcode":"01581",
    "sg:province":"MA",
    "sg:tags":[
        "telephone",
        "cellular"
    ],
    "wof:name":"Cingular Wireless",
    "wof:placetype":"venue"
},
  "geometry": {"coordinates":[-71.60688399999999,42.285177],"type":"Point"}
}