{
  "type": "Feature",
  "properties": {
    "addr:full": "260 Marion Rd Wareham MA 02571",
    "addr:housenumber": "260",
    "addr:postcode": "02571",
    "addr:street": "Marion Rd",
    "iso:country": "US",
    "ovtr:label": "Sullivan Wine \u0026 Spirits, 260 Marion Rd Wareham MA US",
    "ovtr:similarity": 2.3589189052581787,
    "sg:address": "260 Marion Rd",
    "sg:city": "Wareham",
    "sg:classifiers": [
      {
        "category": "Food \u0026 Beverages",
        "subcategory": "Liquor \u0026 Beverages",
        "type": "Retail Goods"
      }
    ],
    "sg:phone": "+1 508 295 0016",
    "sg:postcode": "02571",
    "sg:province": "MA",
    "wof:name": "Sullivan Wine \u0026 Spirits",
    "wof:placetype": "venue"
  },
  "geometry": {"coordinates":[-70.734162,41.752594],"type":"Point"}
}
