{
  "type": "Feature",
  "properties": {
    "addr:full":"346 Salem St North Andover MA 01845",
    "addr:housenumber":"346",
    "addr:postcode":"01845",
    "addr:street":"Salem St",
    "iso:country":"US",
    "sg:address":"346 Salem St",
    "sg:city":"North Andover",
    "sg:classifiers":[
        {
            "category":"Building & Trades",
            "subcategory":"Landscaping Services",
            "type":"Services"
        }
    ],
    "sg:phone":"+1 978 688 4944",
    "sg:postcode":"01845",
    "sg:province":"MA",
    "sg:tags":[
        "landscape",
        "contractor"
    ],
    "wof:name":"R J Butts Landscaping",
    "wof:placetype":"venue"
},
  "geometry": {"coordinates":[-71.09773,42.677933],"type":"Point"}
}