{
  "type": "Feature",
  "properties": {
    "addr:full": "27 Bow St Plainville MA 02762",
    "addr:housenumber": "27",
    "addr:postcode": "02762",
    "addr:street": "Bow St",
    "iso:country": "US",
    "sg:address": "27 Bow St",
    "sg:city": "Plainville",
    "sg:classifiers": [
      {
        "category": "Sports \u0026 Exercise",
        "subcategory": "Golf",
        "type": "Entertainment"
      }
    ],
    "sg:phone": "+1 508 699 9406",
    "sg:postcode": "02762",
    "sg:province": "MA",
    "sg:tags": [
      "course"
    ],
    "wof:name": "Wentworth Hills Golf \u0026 Country",
    "wof:placetype": "venue"
  },
  "geometry": {"coordinates":[-71.374119,42.0136],"type":"Point"}
}
