{
  "type": "Feature",
  "properties": {
    "iso:country":"US",
    "sg:address":"27 Bow St",
    "sg:city":"Plainville",
    "sg:classifiers":[
        {
            "category":"Sports & Exercise",
            "subcategory":"Golf",
            "type":"Entertainment"
        }
    ],
    "sg:phone":"+1 508 699 9406",
    "sg:postcode":"02762",
    "sg:province":"MA",
    "sg:tags":[
        "course"
    ],
    "wof:name":"Wentworth Hills Golf & Country",
    "wof:placetype":"venue"
},
  "geometry": {"coordinates":[-71.37411899999999,42.0136],"type":"Point"}
}