{
  "type": "Feature",
  "properties": {
    "iso:country":"US",
    "sg:address":"257 Quincy Street",
    "sg:city":"Dorchester",
    "sg:classifiers":[
        {
            "category":"Building & Trades",
            "subcategory":"Construction",
            "type":"Services"
        }
    ],
    "sg:phone":"+1 617 427 0086",
    "sg:postcode":"02121",
    "sg:province":"MA",
    "sg:tags":[
        "contractor"
    ],
    "wof:name":"Renovations Specialties",
    "wof:placetype":"venue"
},
  "geometry": {"coordinates":[-71.07216,42.312136],"type":"Point"}
}