{
  "type": "Feature",
  "properties": {
    "iso:country":"US",
    "sg:address":"22 Noble Hill Rd",
    "sg:city":"Beverly",
    "sg:classifiers":[
        {
            "category":"Wholesale",
            "subcategory":"Vending Machines",
            "type":"Manufacturing & Wholesale Goods"
        }
    ],
    "sg:phone":"+1   ",
    "sg:postcode":"01915",
    "sg:province":"MA",
    "sg:tags":[
        "operator"
    ],
    "wof:name":"James Amatucci",
    "wof:placetype":"venue"
},
  "geometry": {"coordinates":[-70.83825,42.579202],"type":"Point"}
}