{
  "type": "Feature",
  "properties": {
    "addr:full":"15 Tennis Rd Mattapan MA 02126",
    "addr:housenumber":"15",
    "addr:postcode":"02126",
    "addr:street":"Tennis Rd",
    "iso:country":"US",
    "sg:address":"15 Tennis Rd",
    "sg:city":"Mattapan",
    "sg:classifiers":[
        {
            "category":"Social Services",
            "subcategory":"Child Care",
            "type":"Services"
        }
    ],
    "sg:phone":"+1 617 298 9450",
    "sg:postcode":"02126",
    "sg:province":"MA",
    "wof:name":"Clarendon Family Day Care",
    "wof:placetype":"venue"
},
  "geometry": {"coordinates":[-71.097437,42.277128],"type":"Point"}
}