{
  "type": "Feature",
  "properties": {
    "iso:country":"US",
    "sg:address":"320 Union St",
    "sg:city":"Holbrook",
    "sg:classifiers":[
        {
            "category":"Organizations",
            "subcategory":"Membership Organization",
            "type":"Services"
        }
    ],
    "sg:phone":"+1 781 767 5885",
    "sg:postcode":"02343",
    "sg:province":"MA",
    "wof:name":"Holbrook Historical Society",
    "wof:placetype":"venue"
},
  "geometry": {"coordinates":[-71.02319,42.15522],"type":"Point"}
}