{
  "type": "Feature",
  "properties": {
    "addr:full": "54 Boyden Rd Pelham MA 01002",
    "addr:housenumber": "54",
    "addr:postcode": "01002",
    "addr:street": "Boyden Rd",
    "iso:country": "US",
    "sg:address": "54 Boyden Rd",
    "sg:city": "Pelham",
    "sg:classifiers": [
      {
        "category": "Professional",
        "subcategory": "Management \u0026 Consulting",
        "type": "Services"
      }
    ],
    "sg:phone": "+1 413 256 1157",
    "sg:postcode": "01002",
    "sg:province": "MA",
    "sg:tags": [
      "counselor",
      "relation",
      "public"
    ],
    "wof:name": "Bangert Communications",
    "wof:placetype": "venue"
  },
  "geometry": {"coordinates":[-72.437042,42.409624],"type":"Point"}
}
