{
  "type": "Feature",
  "properties": {
    "iso:country":"US",
    "sg:address":"54 Boyden Rd",
    "sg:city":"Pelham",
    "sg:classifiers":[
        {
            "category":"Professional",
            "subcategory":"Management & Consulting",
            "type":"Services"
        }
    ],
    "sg:phone":"+1 413 256 1157",
    "sg:postcode":"01002",
    "sg:province":"MA",
    "sg:tags":[
        "counselor",
        "relation",
        "public"
    ],
    "wof:name":"Bangert Communications",
    "wof:placetype":"venue"
},
  "geometry": {"coordinates":[-72.43704200000001,42.409624],"type":"Point"}
}