{
  "type": "Feature",
  "properties": {
    "iso:country":"US",
    "sg:address":"805 Massachusetts Ave",
    "sg:city":"Lexington",
    "sg:classifiers":[
        {
            "category":"Travel",
            "subcategory":"Travel Agent",
            "type":"Entertainment"
        }
    ],
    "sg:phone":"+1 781 862 3700",
    "sg:postcode":"02420",
    "sg:province":"MA",
    "sg:tags":[
        "agency",
        "services-commercial"
    ],
    "wof:name":"Majestic Cruises & Tours",
    "wof:placetype":"venue"
},
  "geometry": {"coordinates":[-71.207672,42.430515],"type":"Point"}
}