{
  "type": "Feature",
  "properties": {
    "addr:full": "805 Massachusetts Ave Lexington MA 02420",
    "addr:housenumber": "805",
    "addr:postcode": "02420",
    "addr:street": "Massachusetts Ave",
    "iso:country": "US",
    "sg:address": "805 Massachusetts Ave",
    "sg:city": "Lexington",
    "sg:classifiers": [
      {
        "category": "Travel",
        "subcategory": "Travel Agent",
        "type": "Entertainment"
      }
    ],
    "sg:phone": "+1 781 862 3700",
    "sg:postcode": "02420",
    "sg:province": "MA",
    "sg:tags": [
      "agency",
      "services-commercial"
    ],
    "wof:name": "Majestic Cruises \u0026 Tours",
    "wof:placetype": "venue"
  },
  "geometry": {"coordinates":[-71.207672,42.430515],"type":"Point"}
}
