{
  "type": "Feature",
  "properties": {
    "iso:country":"US",
    "sg:address":"169 Massachusetts Ave",
    "sg:city":"Boston",
    "sg:classifiers":[
        {
            "category":"Professional",
            "type":"Services"
        }
    ],
    "sg:phone":"+1 617 247 8689",
    "sg:postcode":"02115",
    "sg:province":"MA",
    "sg:tags":[
        "rehearsal",
        "recording",
        "arranger",
        "studio",
        "composer",
        "music"
    ],
    "sg:website":"www.bristolstudios.com",
    "wof:name":"Bristol Recording & Voice Studios",
    "wof:placetype":"venue"
},
  "geometry": {"coordinates":[-71.087163,42.346033],"type":"Point"}
}