{
  "type": "Feature",
  "properties": {
    "iso:country":"US",
    "sg:address":"130 Bishop Richard Allen",
    "sg:city":"Cambridge",
    "sg:classifiers":[
        {
            "category":"Social Services",
            "subcategory":"Child Care",
            "type":"Services"
        }
    ],
    "sg:phone":"+1 617 547 1063",
    "sg:postcode":"02139",
    "sg:province":"MA",
    "sg:tags":[
        "day"
    ],
    "wof:name":"Child Care Resources Center",
    "wof:placetype":"venue"
},
  "geometry": {"coordinates":[-71.103623,42.366614],"type":"Point"}
}