{
  "type": "Feature",
  "properties": {
    "iso:country":"US",
    "sg:address":"206 Holden Wood Rd",
    "sg:city":"Concord",
    "sg:classifiers":[
        {
            "category":"Recreation",
            "type":"Entertainment"
        }
    ],
    "sg:phone":"+1 978 369 8132",
    "sg:postcode":"01742",
    "sg:province":"MA",
    "sg:tags":[
        "diving",
        "instruction"
    ],
    "wof:name":"Under Water Academy",
    "wof:placetype":"venue"
},
  "geometry": {"coordinates":[-71.369226,42.436372],"type":"Point"}
}