{
  "type": "Feature",
  "properties": {
    "addr:full":"600 Worcester Rd Framingham MA 01702",
    "addr:housenumber":"600",
    "addr:postcode":"01702",
    "addr:street":"Worcester Rd",
    "iso:country":"US",
    "sg:address":"600 Worcester Rd",
    "sg:city":"Framingham",
    "sg:classifiers":[
        {
            "category":"Health Services",
            "subcategory":"Doctor",
            "type":"Services"
        }
    ],
    "sg:phone":"+1 508 879 6500",
    "sg:postcode":"01702",
    "sg:province":"MA",
    "sg:tags":[
        "physician",
        "surgeon"
    ],
    "wof:name":"Richard G Salerno MD",
    "wof:placetype":"venue"
},
  "geometry": {"coordinates":[-71.42108899999999,42.297841],"type":"Point"}
}