{
  "type": "Feature",
  "properties": {
    "addr:full":"156 Liberty St Hanson MA 02341",
    "addr:housenumber":"156",
    "addr:postcode":"02341",
    "addr:street":"Liberty St",
    "iso:country":"US",
    "sg:address":"156 Liberty St",
    "sg:city":"Hanson",
    "sg:classifiers":[
        {
            "category":"Food & Beverages",
            "subcategory":"Groceries & Convenience Stores",
            "type":"Retail Goods"
        }
    ],
    "sg:phone":"+1 781 293 0210",
    "sg:postcode":"02341",
    "sg:province":"MA",
    "wof:name":"Myettes General Store",
    "wof:placetype":"venue"
},
  "geometry": {"coordinates":[-70.877478,42.07228],"type":"Point"}
}