{
  "type": "Feature",
  "properties": {
    "addr:full":"99 Longwater Cir Norwell MA 02061",
    "addr:housenumber":"99",
    "addr:postcode":"02061",
    "addr:street":"Longwater Cir",
    "iso:country":"US",
    "sg:address":"99 Longwater Cir",
    "sg:city":"Norwell",
    "sg:classifiers":[
        {
            "category":"Real Estate",
            "subcategory":"Real Estate Agent",
            "type":"Services"
        }
    ],
    "sg:phone":"+1 781 982 6020",
    "sg:postcode":"02061",
    "sg:province":"MA",
    "sg:tags":[
        "management"
    ],
    "wof:name":"Davis Property Group LLC",
    "wof:placetype":"venue"
},
  "geometry": {"coordinates":[-70.880888,42.155861],"type":"Point"}
}