{
  "type": "Feature",
  "properties": {
    "addr:full":"4198 Washington St Roslindale MA 02131",
    "addr:housenumber":"4198",
    "addr:postcode":"02131",
    "addr:street":"Washington St",
    "iso:country":"US",
    "sg:address":"4198 Washington St",
    "sg:city":"Roslindale",
    "sg:classifiers":[
        {
            "category":"Restaurant",
            "type":"Food & Drink"
        }
    ],
    "sg:phone":"+1 617 327 3650",
    "sg:postcode":"02131",
    "sg:province":"MA",
    "wof:name":"Dragon Chef",
    "wof:placetype":"venue"
},
  "geometry": {"coordinates":[-71.128128,42.286448],"type":"Point"}
}