{
  "type": "Feature",
  "properties": {
    "iso:country":"US",
    "sg:address":"80 Old Turnpike Rd S",
    "sg:city":"Canaan",
    "sg:classifiers":[
        {
            "category":"Wholesale",
            "subcategory":"Machinery & Supplies",
            "type":"Manufacturing & Wholesale Goods"
        }
    ],
    "sg:phone":"+1 860 824 0436",
    "sg:postcode":"06018",
    "sg:province":"MA",
    "sg:tags":[
        "industrial"
    ],
    "wof:name":"Clayton Cooperage",
    "wof:placetype":"venue"
},
  "geometry": {"coordinates":[-73.260513,42.015523],"type":"Point"}
}