{
  "type": "Feature",
  "properties": {
    "iso:country":"US",
    "sg:address":"6 Patriot Ln Unit 1",
    "sg:city":"Georgetown",
    "sg:classifiers":[
        {
            "category":"Shopping",
            "subcategory":"Pets & Pet Supplies",
            "type":"Retail Goods"
        },
        {
            "category":"Retail",
            "subcategory":"Animal Services",
            "type":"Services"
        }
    ],
    "sg:phone":"+1 978 352 6226",
    "sg:postcode":"01833",
    "sg:province":"MA",
    "sg:tags":[
        "grooming",
        "dog",
        "cat"
    ],
    "wof:name":"Sea Coast Dog Grooming",
    "wof:placetype":"venue"
},
  "geometry": {"coordinates":[-70.95769900000001,42.718138],"type":"Point"}
}