{
  "type": "Feature",
  "properties": {
    "iso:country":"US",
    "sg:address":"59 Abbey St",
    "sg:city":"Marshfield",
    "sg:classifiers":[
        {
            "category":"Education",
            "subcategory":"Special Training",
            "type":"Public Place"
        }
    ],
    "sg:phone":"+1 781 837 8885",
    "sg:postcode":"02050",
    "sg:province":"MA",
    "sg:tags":[
        "educational"
    ],
    "wof:name":"Campbell's Are Coming",
    "wof:placetype":"venue"
},
  "geometry": {"coordinates":[-70.676238,42.119475],"type":"Point"}
}