{
  "type": "Feature",
  "properties": {
    "addr:full": "150 Oaks Rd Framingham MA 01702",
    "addr:housenumber": "150",
    "addr:postcode": "01702",
    "addr:street": "Oaks Rd",
    "iso:country": "US",
    "sg:address": "150 Oaks Rd",
    "sg:city": "Framingham",
    "sg:classifiers": [
      {
        "category": "Professional",
        "subcategory": "Business Services",
        "type": "Services"
      }
    ],
    "sg:phone": "+1   ",
    "sg:postcode": "01702",
    "sg:province": "MA",
    "wof:name": "Designs By Denault",
    "wof:placetype": "venue"
  },
  "geometry": {"coordinates":[-71.419821,42.294515],"type":"Point"}
}
