{
  "type": "Feature",
  "properties": {
    "addr:full":"1313 Water St Fitchburg MA 01420",
    "addr:housenumber":"1313",
    "addr:postcode":"01420",
    "addr:street":"Water St",
    "iso:country":"US",
    "sg:address":"1313 Water St",
    "sg:city":"Fitchburg",
    "sg:classifiers":[
        {
            "category":"Restaurant",
            "type":"Food & Drink"
        }
    ],
    "sg:phone":"+1 978 342 4391",
    "sg:postcode":"01420",
    "sg:province":"MA",
    "wof:name":"Subway Sandwiches & Salads",
    "wof:placetype":"venue"
},
  "geometry": {"coordinates":[-71.779471,42.562003],"type":"Point"}
}