{
  "type": "Feature",
  "properties": {
    "addr:full":"163 Crescent St Brockton MA 02302",
    "addr:housenumber":"163",
    "addr:postcode":"02302",
    "addr:street":"Crescent St",
    "iso:country":"US",
    "sg:address":"163 Crescent St",
    "sg:city":"Brockton",
    "sg:classifiers":[
        {
            "category":"Retail",
            "subcategory":"Auto Repair",
            "type":"Services"
        }
    ],
    "sg:phone":"+1 508 588 8200",
    "sg:postcode":"02302",
    "sg:province":"MA",
    "sg:tags":[
        "body",
        "repairing",
        "painting",
        "automobile"
    ],
    "wof:name":"Jim's Auto And Truck Repair",
    "wof:placetype":"venue"
},
  "geometry": {"coordinates":[-71.01496299999999,42.080886],"type":"Point"}
}