{
  "type": "Feature",
  "properties": {
    "addr:full": "530 Turnpike St North Andover MA 01845",
    "addr:housenumber": "530",
    "addr:postcode": "01845",
    "addr:street": "Turnpike St",
    "iso:country": "US",
    "sg:address": "530 Turnpike St",
    "sg:city": "North Andover",
    "sg:classifiers": [
      {
        "category": "Banks \u0026 Credit Unions",
        "subcategory": "Bank",
        "type": "Services"
      }
    ],
    "sg:phone": "+1 978 975 8026",
    "sg:postcode": "01845",
    "sg:province": "MA",
    "wof:name": "Salem Five Cent Savings Bank",
    "wof:placetype": "venue"
  },
  "geometry": {"coordinates":[-71.115215,42.665634],"type":"Point"}
}
