{
  "type": "Feature",
  "properties": {
    "iso:country":"US",
    "sg:address":"530 Turnpike St",
    "sg:city":"North Andover",
    "sg:classifiers":[
        {
            "category":"Banks & Credit Unions",
            "subcategory":"Bank",
            "type":"Services"
        }
    ],
    "sg:phone":"+1 978 975 8026",
    "sg:postcode":"01845",
    "sg:province":"MA",
    "wof:name":"Salem Five Cent Savings Bank",
    "wof:placetype":"venue"
},
  "geometry": {"coordinates":[-71.11521500000001,42.665634],"type":"Point"}
}