{
  "type": "Feature",
  "properties": {
    "addr:full":"Stoneham Red Stone S Stoneham MA 02180",
    "addr:postcode":"02180",
    "addr:street":"S",
    "iso:country":"US",
    "sg:address":"Stoneham Red Stone S",
    "sg:city":"Stoneham",
    "sg:classifiers":[
        {
            "category":"Shopping",
            "subcategory":"Mobile Phones",
            "type":"Retail Goods"
        }
    ],
    "sg:phone":"+1 781 438 2857",
    "sg:postcode":"02180",
    "sg:province":"MA",
    "wof:name":"Radioshack-A Division of Tandy Corp",
    "wof:placetype":"venue"
},
  "geometry": {"coordinates":[-71.099098,42.480301],"type":"Point"}
}