{
  "type": "Feature",
  "properties": {
    "iso:country":"US",
    "sg:address":"31 County St",
    "sg:city":"Ipswich",
    "sg:classifiers":[
        {
            "category":"Organizations",
            "subcategory":"Religious Organization",
            "type":"Services"
        }
    ],
    "sg:phone":"+1 978 356 2560",
    "sg:postcode":"01938",
    "sg:province":"MA",
    "sg:tags":[
        "church"
    ],
    "wof:name":"Ascension Memorial Church",
    "wof:placetype":"venue"
},
  "geometry": {"coordinates":[-70.834965,42.680254],"type":"Point"}
}