{
  "type": "Feature",
  "properties": {
    "addr:full":"75 Federal St Ste 410 Boston MA 02110",
    "addr:housenumber":"75",
    "addr:postcode":"02110",
    "addr:street":"Federal St Ste 410",
    "iso:country":"US",
    "sg:address":"75 Federal St Ste 410",
    "sg:city":"Boston",
    "sg:classifiers":[
        {
            "category":"Professional",
            "subcategory":"Lawyer & Legal Services",
            "type":"Services"
        }
    ],
    "sg:phone":"+1 617 348 9800",
    "sg:postcode":"02110",
    "sg:province":"MA",
    "wof:name":"Murphy Hesse Toomey & Lehaney",
    "wof:placetype":"venue"
},
  "geometry": {"coordinates":[-71.056624,42.355513],"type":"Point"}
}