{
  "type": "Feature",
  "properties": {
    "iso:country":"US",
    "sg:address":"461 Main St",
    "sg:city":"Holyoke",
    "sg:classifiers":[
        {
            "category":"Home & Garden",
            "subcategory":"Furniture",
            "type":"Retail Goods"
        }
    ],
    "sg:phone":"+1 413 533 3931",
    "sg:postcode":"01040",
    "sg:province":"MA",
    "wof:name":"Grace-Demos Furniture Inc",
    "wof:placetype":"venue"
},
  "geometry": {"coordinates":[-72.608549,42.198883],"type":"Point"}
}