{
  "type": "Feature",
  "properties": {
    "addr:full":"243 Newbury St Peabody MA 01960",
    "addr:housenumber":"243",
    "addr:postcode":"01960",
    "addr:street":"Newbury St",
    "iso:country":"US",
    "sg:address":"243 Newbury St",
    "sg:city":"Peabody",
    "sg:classifiers":[
        {
            "category":"Autos & Motor Vehicles",
            "subcategory":"Boat Sales",
            "type":"Retail Goods"
        }
    ],
    "sg:phone":"+1 978 535 7332",
    "sg:postcode":"01960",
    "sg:province":"MA",
    "sg:tags":[
        "equipment",
        "marine",
        "supply"
    ],
    "sg:website":"www.westmarine.com",
    "wof:name":"West Marine",
    "wof:placetype":"venue"
},
  "geometry": {"coordinates":[-70.98142199999999,42.551854],"type":"Point"}
}