{
  "type": "Feature",
  "properties": {
    "iso:country":"US",
    "sg:address":"394 Lowell St",
    "sg:city":"Lexington",
    "sg:classifiers":[
        {
            "category":"Personal",
            "subcategory":"Day Spa",
            "type":"Services"
        }
    ],
    "sg:phone":"+1 781 861 0681",
    "sg:postcode":"02420",
    "sg:province":"MA",
    "wof:name":"Jenelle Marie Esthetics & Makeup Artistry",
    "wof:placetype":"venue"
},
  "geometry": {"coordinates":[-71.19913699999999,42.448835],"type":"Point"}
}