{
  "type": "Feature",
  "properties": {
    "iso:country":"US",
    "sg:address":"276 Falmouth Rd",
    "sg:city":"Hyannis",
    "sg:classifiers":[
        {
            "category":"Home & Garden",
            "subcategory":"Furniture",
            "type":"Retail Goods"
        }
    ],
    "sg:phone":"+1 508 778 4466",
    "sg:postcode":"02601",
    "sg:province":"MA",
    "sg:tags":[
        "store"
    ],
    "wof:name":"Hides N'seats - CLOSED",
    "wof:placetype":"venue"
},
  "geometry": {"coordinates":[-70.29209899999999,41.664501],"type":"Point"}
}