{
  "type": "Feature",
  "properties": {
    "addr:full": "645 William T Morrissey Blvd Dorchester MA 02122",
    "addr:housenumber": "645",
    "addr:postcode": "02122",
    "addr:street": "William T Morrissey Blvd",
    "iso:country": "US",
    "sg:address": "645 William T Morrissey Blvd",
    "sg:city": "Dorchester",
    "sg:classifiers": [
      {
        "category": "Organizations",
        "subcategory": "Labor Organization",
        "type": "Services"
      }
    ],
    "sg:phone": "+1 617 436 5500",
    "sg:postcode": "02122",
    "sg:province": "MA",
    "sg:website": "www.mabricktrustfunds.com",
    "wof:name": "Bricklayers \u0026 Masons Health",
    "wof:placetype": "venue"
  },
  "geometry": {"coordinates":[-71.047995,42.303148],"type":"Point"}
}
