{
  "type": "Feature",
  "properties": {
    "iso:country":"US",
    "sg:address":"645 William T Morrissey Blvd",
    "sg:city":"Dorchester",
    "sg:classifiers":[
        {
            "category":"Organizations",
            "subcategory":"Labor Organization",
            "type":"Services"
        }
    ],
    "sg:phone":"+1 617 436 5500",
    "sg:postcode":"02122",
    "sg:province":"MA",
    "sg:website":"www.mabricktrustfunds.com",
    "wof:name":"Bricklayers & Masons Health",
    "wof:placetype":"venue"
},
  "geometry": {"coordinates":[-71.047995,42.303148],"type":"Point"}
}