{
  "type": "Feature",
  "properties": {
    "addr:full":"106 Cold Spring Rd Westford MA 01886",
    "addr:housenumber":"106",
    "addr:postcode":"01886",
    "addr:street":"Cold Spring Rd",
    "iso:country":"US",
    "sg:address":"106 Cold Spring Rd",
    "sg:city":"Westford",
    "sg:classifiers":[
        {
            "category":"Building & Trades",
            "subcategory":"Landscaping Services",
            "type":"Services"
        }
    ],
    "sg:phone":"+1 978 692 1100",
    "sg:postcode":"01886",
    "sg:province":"MA",
    "sg:tags":[
        "landscape",
        "contractor"
    ],
    "wof:name":"Blackwell Landscape Constr",
    "wof:placetype":"venue"
},
  "geometry": {"coordinates":[-71.4597,42.585259],"type":"Point"}
}