{
  "type": "Feature",
  "properties": {
    "iso:country":"US",
    "sg:address":"1 Federal St",
    "sg:city":"Springfield",
    "sg:classifiers":[
        {
            "category":"Professional",
            "subcategory":"Business Services",
            "type":"Services"
        }
    ],
    "sg:phone":"+1 413 734 2345",
    "sg:postcode":"01105",
    "sg:province":"MA",
    "wof:name":"Val Pak",
    "wof:placetype":"venue"
},
  "geometry": {"coordinates":[-72.57948399999999,42.111348],"type":"Point"}
}