{
  "type": "Feature",
  "properties": {
    "addr:full":"604 Boston Rd Springfield MA 01119",
    "addr:housenumber":"604",
    "addr:postcode":"01119",
    "addr:street":"Boston Rd",
    "iso:country":"US",
    "sg:address":"604 Boston Rd",
    "sg:city":"Springfield",
    "sg:classifiers":[
        {
            "category":"Retail",
            "subcategory":"Auto Repair",
            "type":"Services"
        }
    ],
    "sg:phone":"+1 413 783 4848",
    "sg:postcode":"01119",
    "sg:province":"MA",
    "sg:tags":[
        "repairing",
        "automobile"
    ],
    "wof:name":"Grez Automotive",
    "wof:placetype":"venue"
},
  "geometry": {"coordinates":[-72.523972,42.134892],"type":"Point"}
}