{
  "type": "Feature",
  "properties": {
    "addr:full": "30 Julio Dr Shrewsbury MA 01545",
    "addr:postcode": "01545",
    "addr:street": "30 Julio Dr",
    "iso:country": "US",
    "sg:address": "30 Julio Dr",
    "sg:city": "Shrewsbury",
    "sg:classifiers": [
      {
        "category": "Professional",
        "subcategory": "Management \u0026 Consulting",
        "type": "Services"
      }
    ],
    "sg:phone": "+1   ",
    "sg:postcode": "01545",
    "sg:province": "MA",
    "wof:name": "Tower Associates",
    "wof:placetype": "venue"
  },
  "geometry": {"coordinates":[-71.701324,42.291307],"type":"Point"}
}
