{
  "type": "Feature",
  "properties": {
    "addr:full": "49 Winchester Rd Newton MA 02458",
    "addr:housenumber": "49",
    "addr:postcode": "02458",
    "addr:street": "Winchester Rd",
    "iso:country": "US",
    "sg:address": "49 Winchester Rd",
    "sg:city": "Newton",
    "sg:classifiers": [
      {
        "category": "Wholesale",
        "subcategory": "Groceries",
        "type": "Manufacturing \u0026 Wholesale Goods"
      }
    ],
    "sg:phone": "+1 617 244 3635",
    "sg:postcode": "02458",
    "sg:province": "MA",
    "sg:tags": [
      "food",
      "product",
      "health"
    ],
    "sg:website": "www.zoefoods.com",
    "wof:name": "Zoe Foods",
    "wof:placetype": "venue"
  },
  "geometry": {"coordinates":[-71.196032,42.349783],"type":"Point"}
}
