{
  "type": "Feature",
  "properties": {
    "addr:full": "32 Driftway Scituate MA 02066",
    "addr:housenumber": "32",
    "addr:postcode": "02066",
    "addr:street": "Driftway",
    "iso:country": "US",
    "sg:address": "32 Driftway",
    "sg:city": "Scituate",
    "sg:classifiers": [
      {
        "category": "Food \u0026 Beverages",
        "subcategory": "Bakery",
        "type": "Retail Goods"
      }
    ],
    "sg:phone": "+1 781 544 3047",
    "sg:postcode": "02066",
    "sg:province": "MA",
    "sg:tags": [
      "doughnut"
    ],
    "wof:name": "Dunkin Donuts",
    "wof:placetype": "venue"
  },
  "geometry": {"coordinates":[-70.717469,42.176496],"type":"Point"}
}
