{
  "type": "Feature",
  "properties": {
    "iso:country":"US",
    "sg:address":"32 Driftway",
    "sg:city":"Scituate",
    "sg:classifiers":[
        {
            "category":"Food & Beverages",
            "subcategory":"Bakery",
            "type":"Retail Goods"
        }
    ],
    "sg:phone":"+1 781 544 3047",
    "sg:postcode":"02066",
    "sg:province":"MA",
    "sg:tags":[
        "doughnut"
    ],
    "wof:name":"Dunkin Donuts",
    "wof:placetype":"venue"
},
  "geometry": {"coordinates":[-70.71746899999999,42.176496],"type":"Point"}
}