{
  "type": "Feature",
  "properties": {
    "addr:full": "27 Woodleigh Rd Watertown MA 02472",
    "addr:housenumber": "27",
    "addr:postcode": "02472",
    "addr:street": "Woodleigh Rd",
    "iso:country": "US",
    "sg:address": "27 Woodleigh Rd",
    "sg:city": "Watertown",
    "sg:classifiers": [
      {
        "category": "Building \u0026 Trades",
        "subcategory": "Construction",
        "type": "Services"
      },
      {
        "category": "Home \u0026 Garden",
        "subcategory": "Household Appliances",
        "type": "Retail Goods"
      },
      {
        "category": "Retail",
        "subcategory": "Laundry \u0026 Dry Cleaning",
        "type": "Services"
      },
      {
        "category": "Home \u0026 Garden",
        "subcategory": "Carpets \u0026 Floor Coverings",
        "type": "Retail Goods"
      },
      {
        "category": "Manufacturing",
        "subcategory": "Tools \u0026 Machinery",
        "type": "Manufacturing \u0026 Wholesale Goods"
      },
      {
        "category": "Utilities",
        "subcategory": "Water",
        "type": "Services"
      },
      {
        "category": "Personal",
        "type": "Services"
      },
      {
        "category": "Building \u0026 Trades",
        "subcategory": "Cleaning \u0026 Sanitation",
        "type": "Services"
      }
    ],
    "sg:phone": "+1 617 926 4220",
    "sg:postcode": "02472",
    "sg:province": "MA",
    "sg:tags": [
      "control",
      "cleaner",
      "duct",
      "house",
      "mold",
      "janitorial",
      "site-clean-up",
      "equipment",
      "damage",
      "contractor",
      "extraction",
      "window",
      "cleaning-industrial",
      "curtain",
      "drapery",
      "counteracting",
      "emergency",
      "fire",
      "cleaners-water",
      "odor",
      "rug",
      "restoration",
      "vacuum",
      "remediation",
      "upholstery",
      "flood",
      "air",
      "waxing",
      "ventilation",
      "smoke",
      "polishing"
    ],
    "sg:website": "http://www.servicemasterclean.com/reslf/smclean_leadform.asp?url=http://www.servicemasterclean.com/reslf/smclean_leadform.asp\u0026partnerName=YellowPages.com\u0026adName=yptl\u0026HGProp=SMClean",
    "wof:name": "ServiceMaster Clean",
    "wof:placetype": "venue"
  },
  "geometry": {"coordinates":[-71.160169,42.376412],"type":"Point"}
}
