{
  "type": "Feature",
  "properties": {
    "iso:country":"US",
    "sg:address":"209 Harvard St",
    "sg:city":"Brookline",
    "sg:classifiers":[
        {
            "category":"Health Services",
            "subcategory":"Dentist",
            "type":"Services"
        }
    ],
    "sg:phone":"+1 617 277 3127",
    "sg:postcode":"02446",
    "sg:province":"MA",
    "wof:name":"Childs Warren C DDS",
    "wof:placetype":"venue"
},
  "geometry": {"coordinates":[-71.120684,42.339795],"type":"Point"}
}