{
  "type": "Feature",
  "properties": {
    "addr:full":"80 Auburn Park Cambridge MA 02139",
    "addr:housenumber":"80",
    "addr:postcode":"02139",
    "addr:street":"Auburn Park",
    "iso:country":"US",
    "sg:address":"80 Auburn Park",
    "sg:city":"Cambridge",
    "sg:classifiers":[
        {
            "category":"Professional",
            "subcategory":"Research",
            "type":"Services"
        }
    ],
    "sg:phone":"+1 617 423 0692",
    "sg:postcode":"02139",
    "sg:province":"MA",
    "sg:tags":[
        "market",
        "analysis"
    ],
    "wof:name":"Eglean Inc",
    "wof:placetype":"venue"
},
  "geometry": {"coordinates":[-71.102755,42.362362],"type":"Point"}
}