{
  "type": "Feature",
  "properties": {
    "iso:country":"US",
    "sg:address":"75 Princeton St",
    "sg:city":"North Chelmsford",
    "sg:classifiers":[
        {
            "category":"Health Services",
            "subcategory":"Hospital",
            "type":"Services"
        }
    ],
    "sg:phone":"+1 978 251 7778",
    "sg:postcode":"01863",
    "sg:province":"MA",
    "sg:tags":[
        "treatment",
        "psychiatric",
        "facility"
    ],
    "wof:name":"Tanya Korkosz",
    "wof:placetype":"venue"
},
  "geometry": {"coordinates":[-71.379186,42.635908],"type":"Point"}
}