{
  "type": "Feature",
  "properties": {
    "addr:full":"584 Main St Athol MA 01331",
    "addr:housenumber":"584",
    "addr:postcode":"01331",
    "addr:street":"Main St",
    "iso:country":"US",
    "sg:address":"584 Main St",
    "sg:city":"Athol",
    "sg:classifiers":[
        {
            "category":"Government",
            "subcategory":"Office",
            "type":"Public Place"
        }
    ],
    "sg:phone":"+1 978 249 6618",
    "sg:postcode":"01331",
    "sg:province":"MA",
    "sg:tags":[
        "village"
    ],
    "wof:name":"Athol Accountant",
    "wof:placetype":"venue"
},
  "geometry": {"coordinates":[-72.227633,42.593906],"type":"Point"}
}