{
  "type": "Feature",
  "properties": {
    "addr:full":"5 Natasha Cir Methuen MA 01844",
    "addr:housenumber":"5",
    "addr:postcode":"01844",
    "addr:street":"Natasha Cir",
    "iso:country":"US",
    "sg:address":"5 Natasha Cir",
    "sg:city":"Methuen",
    "sg:classifiers":[
        {
            "category":"Communications",
            "subcategory":"Film & Video Production",
            "type":"Services"
        }
    ],
    "sg:phone":"+1   ",
    "sg:postcode":"01844",
    "sg:province":"MA",
    "sg:tags":[
        "motion"
    ],
    "wof:name":"Bunker Hill Production",
    "wof:placetype":"venue"
},
  "geometry": {"coordinates":[-71.14206,42.761718],"type":"Point"}
}