{
  "type": "Feature",
  "properties": {
    "iso:country":"US",
    "sg:address":"5 Cole Ave",
    "sg:city":"Sutton",
    "sg:classifiers":[
        {
            "category":"Health Services",
            "subcategory":"Clinic",
            "type":"Services"
        }
    ],
    "sg:phone":"+1 508 865 0448",
    "sg:postcode":"01590",
    "sg:province":"MA",
    "sg:tags":[
        "holistic",
        "practitioner"
    ],
    "wof:name":"Massage Therapy",
    "wof:placetype":"venue"
},
  "geometry": {"coordinates":[-71.76220000000001,42.152965],"type":"Point"}
}