{
  "type": "Feature",
  "properties": {
    "addr:full": "5 Cole Ave Sutton MA 01590",
    "addr:housenumber": "5",
    "addr:postcode": "01590",
    "addr:street": "Cole Ave",
    "iso:country": "US",
    "sg:address": "5 Cole Ave",
    "sg:city": "Sutton",
    "sg:classifiers": [
      {
        "category": "Health Services",
        "subcategory": "Clinic",
        "type": "Services"
      }
    ],
    "sg:phone": "+1 508 865 0448",
    "sg:postcode": "01590",
    "sg:province": "MA",
    "sg:tags": [
      "holistic",
      "practitioner"
    ],
    "wof:name": "Massage Therapy",
    "wof:placetype": "venue"
  },
  "geometry": {"coordinates":[-71.7622,42.152965],"type":"Point"}
}
