{
  "type": "Feature",
  "properties": {
    "iso:country":"US",
    "sg:address":"111 River Rd",
    "sg:city":"Topsfield",
    "sg:classifiers":[
        {
            "category":"Building & Trades",
            "subcategory":"Construction",
            "type":"Services"
        }
    ],
    "sg:phone":"+1 978 887 6889",
    "sg:postcode":"01983",
    "sg:province":"MA",
    "sg:tags":[
        "altering",
        "remodeling",
        "contractor"
    ],
    "wof:name":"Bobs Home Improvement",
    "wof:placetype":"venue"
},
  "geometry": {"coordinates":[-70.96446899999999,42.633912],"type":"Point"}
}