{
  "type": "Feature",
  "properties": {
    "addr:full": "167 California St Newton MA 02458",
    "addr:housenumber": "167",
    "addr:postcode": "02458",
    "addr:street": "California St",
    "iso:country": "US",
    "sg:address": "167 California St",
    "sg:city": "Newton",
    "sg:classifiers": [
      {
        "category": "Building \u0026 Trades",
        "subcategory": "Landscaping Services",
        "type": "Services"
      }
    ],
    "sg:phone": "+1 617 630 9282",
    "sg:postcode": "02458",
    "sg:province": "MA",
    "sg:tags": [
      "landscape",
      "contractor"
    ],
    "wof:name": "Carbone Ciro Landscaping",
    "wof:placetype": "venue"
  },
  "geometry": {"coordinates":[-71.19481,42.364685],"type":"Point"}
}
