{
  "type": "Feature",
  "properties": {
    "iso:country":"US",
    "sg:address":"21 Western Ave",
    "sg:city":"Essex",
    "sg:classifiers":[
        {
            "category":"Building & Trades",
            "subcategory":"Construction",
            "type":"Services"
        }
    ],
    "sg:phone":"+1   ",
    "sg:postcode":"01929",
    "sg:province":"MA",
    "sg:tags":[
        "contractor"
    ],
    "wof:name":"Industrial Abrsive Blstg Cting",
    "wof:placetype":"venue"
},
  "geometry": {"coordinates":[-70.78628999999999,42.633861],"type":"Point"}
}