{
  "type": "Feature",
  "properties": {
    "addr:full":"5 Washington St Nantucket MA 02554",
    "addr:housenumber":"5",
    "addr:postcode":"02554",
    "addr:street":"Washington St",
    "iso:country":"US",
    "sg:address":"5 Washington St",
    "sg:city":"Nantucket",
    "sg:classifiers":[
        {
            "category":"Shopping",
            "subcategory":"Gifts & Souvenirs",
            "type":"Retail Goods"
        }
    ],
    "sg:phone":"+1 508 228 4409",
    "sg:postcode":"02554",
    "sg:province":"MA",
    "sg:tags":[
        "basket",
        "parcel"
    ],
    "wof:name":"Basket Of Roses",
    "wof:placetype":"venue"
},
  "geometry": {"coordinates":[-70.097567,41.283255],"type":"Point"}
}