{
  "type": "Feature",
  "properties": {
    "addr:full":"540 Arcade Ave Seekonk MA 02771",
    "addr:housenumber":"540",
    "addr:postcode":"02771",
    "addr:street":"Arcade Ave",
    "iso:country":"US",
    "sg:address":"540 Arcade Ave",
    "sg:city":"Seekonk",
    "sg:classifiers":[
        {
            "category":"Building & Trades",
            "subcategory":"Construction",
            "type":"Services"
        }
    ],
    "sg:phone":"+1 508 336 7577",
    "sg:postcode":"02771",
    "sg:province":"MA",
    "sg:tags":[
        "designer",
        "dealer",
        "pool",
        "swimming"
    ],
    "wof:name":"American Gunite Pools Inc",
    "wof:placetype":"venue"
},
  "geometry": {"coordinates":[-71.328408,41.827425],"type":"Point"}
}