{
  "type": "Feature",
  "properties": {
    "iso:country":"US",
    "sg:address":"260 Harrison St",
    "sg:city":"Fall River",
    "sg:classifiers":[
        {
            "category":"Food & Beverages",
            "subcategory":"Bakery",
            "type":"Retail Goods"
        }
    ],
    "sg:phone":"+1 508 672 8218",
    "sg:postcode":"02723",
    "sg:province":"MA",
    "sg:tags":[
        "baker"
    ],
    "wof:name":"George's Lebanese Bakery",
    "wof:placetype":"venue"
},
  "geometry": {"coordinates":[-71.137162,41.691127],"type":"Point"}
}