{
  "type": "Feature",
  "properties": {
    "iso:country":"US",
    "sg:address":"14 Fordham Road # 2",
    "sg:city":"Allston",
    "sg:classifiers":[
        {
            "category":"Communications",
            "type":"Services"
        }
    ],
    "sg:phone":"+1 617 782 4100",
    "sg:postcode":"02134",
    "sg:province":"MA",
    "sg:tags":[
        "recording",
        "rehearsal",
        "studio"
    ],
    "wof:name":"Heart Punch Studio",
    "wof:placetype":"venue"
},
  "geometry": {"coordinates":[-71.12797399999999,42.351996],"type":"Point"}
}