{
  "type": "Feature",
  "properties": {
    "addr:full": "14 Fordham Road # 2 Allston MA 02134",
    "addr:housenumber": "14",
    "addr:postcode": "02134",
    "addr:street": "Fordham Road # 2",
    "iso:country": "US",
    "sg:address": "14 Fordham Road # 2",
    "sg:city": "Allston",
    "sg:classifiers": [
      {
        "category": "Communications",
        "type": "Services"
      }
    ],
    "sg:phone": "+1 617 782 4100",
    "sg:postcode": "02134",
    "sg:province": "MA",
    "sg:tags": [
      "recording",
      "rehearsal",
      "studio"
    ],
    "wof:name": "Heart Punch Studio",
    "wof:placetype": "venue"
  },
  "geometry": {"coordinates":[-71.127974,42.351996],"type":"Point"}
}
