{
  "type": "Feature",
  "properties": {
    "addr:full":"486 Green Street Cambridge MA 02139",
    "addr:housenumber":"486",
    "addr:postcode":"02139",
    "addr:street":"Green Street",
    "iso:country":"US",
    "sg:address":"486 Green Street",
    "sg:city":"Cambridge",
    "sg:classifiers":[
        {
            "category":"Professional",
            "subcategory":"Advertising",
            "type":"Services"
        }
    ],
    "sg:phone":"+1 888 268 6035",
    "sg:postcode":"02139",
    "sg:province":"MA",
    "sg:tags":[
        "marketing-automation",
        "web-analytics",
        "lifecycle-marketing",
        "landing-pages",
        "ab-testing",
        "split-testing",
        "optimization",
        "conversion",
        "marketing"
    ],
    "sg:website":"http://www.performable.com/",
    "wof:name":"Performable",
    "wof:placetype":"venue"
},
  "geometry": {"coordinates":[-71.108923,42.367311],"type":"Point"}
}