{
  "type": "Feature",
  "properties": {
    "addr:full":"8 Pine St Swampscott MA 01907",
    "addr:housenumber":"8",
    "addr:postcode":"01907",
    "addr:street":"Pine St",
    "iso:country":"US",
    "sg:address":"8 Pine St",
    "sg:city":"Swampscott",
    "sg:classifiers":[
        {
            "category":"Organizations",
            "subcategory":"Community Association",
            "type":"Services"
        }
    ],
    "sg:phone":"+1 781 599 1240",
    "sg:postcode":"01907",
    "sg:province":"MA",
    "sg:tags":[
        "club"
    ],
    "wof:name":"Veterans Of Foreign Wars",
    "wof:placetype":"venue"
},
  "geometry": {"coordinates":[-70.92285800000001,42.470422],"type":"Point"}
}