{
  "type": "Feature",
  "properties": {
    "addr:full":"33 Green St Newburyport MA 01950",
    "addr:housenumber":"33",
    "addr:postcode":"01950",
    "addr:street":"Green St",
    "iso:country":"US",
    "sg:address":"33 Green St",
    "sg:city":"Newburyport",
    "sg:classifiers":[
        {
            "category":"Professional",
            "subcategory":"Lawyer & Legal Services",
            "type":"Services"
        }
    ],
    "sg:phone":"+1 978 465 4320",
    "sg:postcode":"01950",
    "sg:province":"MA",
    "sg:tags":[
        "attorney"
    ],
    "wof:name":"Karen R Galat",
    "wof:placetype":"venue"
},
  "geometry": {"coordinates":[-70.87276900000001,42.81036],"type":"Point"}
}