{
  "type": "Feature",
  "properties": {
    "iso:country":"US",
    "sg:address":"21 Highland Ave",
    "sg:city":"Newburyport",
    "sg:classifiers":[
        {
            "category":"Health Services",
            "subcategory":"Doctor",
            "type":"Services"
        }
    ],
    "sg:phone":"+1 978 462 7060",
    "sg:postcode":"01950",
    "sg:province":"MA",
    "sg:tags":[
        "surgeon",
        "oral"
    ],
    "wof:name":"Andreas Jos M Oral Surg",
    "wof:placetype":"venue"
},
  "geometry": {"coordinates":[-70.890297,42.814602],"type":"Point"}
}