{
  "type": "Feature",
  "properties": {
    "addr:full":"129 Airport Rd Hyannis MA 02601",
    "addr:housenumber":"129",
    "addr:postcode":"02601",
    "addr:street":"Airport Rd",
    "iso:country":"US",
    "sg:address":"129 Airport Rd",
    "sg:city":"Hyannis",
    "sg:classifiers":[
        {
            "category":"Professional",
            "subcategory":"Employment Agencies",
            "type":"Services"
        }
    ],
    "sg:phone":"+1 508 778 7700",
    "sg:postcode":"02601",
    "sg:province":"MA",
    "wof:name":"Executive Suite the",
    "wof:placetype":"venue"
},
  "geometry": {"coordinates":[-70.293679,41.672899],"type":"Point"}
}