{
  "type": "Feature",
  "properties": {
    "addr:full":"115 Cedar St Milford MA 01757",
    "addr:housenumber":"115",
    "addr:postcode":"01757",
    "addr:street":"Cedar St",
    "iso:country":"US",
    "sg:address":"115 Cedar St",
    "sg:city":"Milford",
    "sg:classifiers":[
        {
            "category":"Manufacturing",
            "subcategory":"Tools & Machinery",
            "type":"Manufacturing & Wholesale Goods"
        }
    ],
    "sg:phone":"+1 508 478 0042",
    "sg:postcode":"01757",
    "sg:province":"MA",
    "sg:tags":[
        "physician",
        "surgeon"
    ],
    "sg:website":"www.techen.com",
    "wof:name":"Techen Inc",
    "wof:placetype":"venue"
},
  "geometry": {"coordinates":[-71.508306,42.173737],"type":"Point"}
}