{
  "type": "Feature",
  "properties": {
    "iso:country":"US",
    "sg:address":"18 Church St",
    "sg:city":"Wilmington",
    "sg:classifiers":[
        {
            "category":"Government",
            "subcategory":"Post Office",
            "type":"Public Place"
        }
    ],
    "sg:phone":"+1 978 000 1111",
    "sg:postcode":"01887",
    "sg:province":"MA",
    "wof:name":"US Post Office",
    "wof:placetype":"venue"
},
  "geometry": {"coordinates":[-71.171515,42.549014],"type":"Point"}
}