{
  "type": "Feature",
  "properties": {
    "iso:country":"US",
    "sg:address":"69 Home St",
    "sg:city":"Malden",
    "sg:classifiers":[
        {
            "category":"Food & Beverages",
            "subcategory":"Meat & Fish",
            "type":"Retail Goods"
        }
    ],
    "sg:phone":"+1 781 389 2042",
    "sg:postcode":"02148",
    "sg:province":"MA",
    "sg:tags":[
        "market"
    ],
    "wof:name":"L&P Meat Distributors",
    "wof:placetype":"venue"
},
  "geometry": {"coordinates":[-71.039973,42.435602],"type":"Point"}
}