{
  "type": "Feature",
  "properties": {
    "addr:full": "69 Home St Malden MA 02148",
    "addr:housenumber": "69",
    "addr:postcode": "02148",
    "addr:street": "Home St",
    "iso:country": "US",
    "sg:address": "69 Home St",
    "sg:city": "Malden",
    "sg:classifiers": [
      {
        "category": "Food \u0026 Beverages",
        "subcategory": "Meat \u0026 Fish",
        "type": "Retail Goods"
      }
    ],
    "sg:phone": "+1 781 389 2042",
    "sg:postcode": "02148",
    "sg:province": "MA",
    "sg:tags": [
      "market"
    ],
    "wof:name": "L\u0026P Meat Distributors",
    "wof:placetype": "venue"
  },
  "geometry": {"coordinates":[-71.039973,42.435602],"type":"Point"}
}
