{
  "type": "Feature",
  "properties": {
    "addr:full": "14 N Main St Middleton MA 01949",
    "addr:housenumber": "14",
    "addr:postcode": "01949",
    "addr:street": "N Main St",
    "iso:country": "US",
    "sg:address": "14 N Main St",
    "sg:city": "Middleton",
    "sg:classifiers": [
      {
        "category": "Professional",
        "subcategory": "Management \u0026 Consulting",
        "type": "Services"
      }
    ],
    "sg:phone": "+1 978 777 5666",
    "sg:postcode": "01949",
    "sg:province": "MA",
    "sg:tags": [
      "personnel",
      "consultant"
    ],
    "wof:name": "Millennium Staffing Solutions",
    "wof:placetype": "venue"
  },
  "geometry": {"coordinates":[-71.015813,42.595172],"type":"Point"}
}
