{
  "type": "Feature",
  "properties": {
    "iso:country":"US",
    "sg:address":"14 N Main St",
    "sg:city":"Middleton",
    "sg:classifiers":[
        {
            "category":"Professional",
            "subcategory":"Management & Consulting",
            "type":"Services"
        }
    ],
    "sg:phone":"+1 978 777 5666",
    "sg:postcode":"01949",
    "sg:province":"MA",
    "sg:tags":[
        "personnel",
        "consultant"
    ],
    "wof:name":"Millennium Staffing Solutions",
    "wof:placetype":"venue"
},
  "geometry": {"coordinates":[-71.01581299999999,42.595172],"type":"Point"}
}