{
  "type": "Feature",
  "properties": {
    "iso:country":"US",
    "sg:address":"192 Washington St",
    "sg:city":"Wellesley",
    "sg:classifiers":[
        {
            "category":"Professional",
            "subcategory":"Computer Services",
            "type":"Services"
        }
    ],
    "sg:phone":"+1   ",
    "sg:postcode":"02481",
    "sg:province":"MA",
    "sg:tags":[
        "datum"
    ],
    "wof:name":"Websoft Technologies Inc",
    "wof:placetype":"venue"
},
  "geometry": {"coordinates":[-71.2688,42.3165],"type":"Point"}
}