{
  "type": "Feature",
  "properties": {
    "addr:full": "192 Washington St Wellesley MA 02481",
    "addr:housenumber": "192",
    "addr:postcode": "02481",
    "addr:street": "Washington St",
    "iso:country": "US",
    "sg:address": "192 Washington St",
    "sg:city": "Wellesley",
    "sg:classifiers": [
      {
        "category": "Professional",
        "subcategory": "Computer Services",
        "type": "Services"
      }
    ],
    "sg:phone": "+1   ",
    "sg:postcode": "02481",
    "sg:province": "MA",
    "sg:tags": [
      "datum"
    ],
    "wof:name": "Websoft Technologies Inc",
    "wof:placetype": "venue"
  },
  "geometry": {"coordinates":[-71.2688,42.3165],"type":"Point"}
}
