{
  "type": "Feature",
  "properties": {
    "addr:full":"138 Larch Road Cambridge MA 02138",
    "addr:housenumber":"138",
    "addr:postcode":"02138",
    "addr:street":"Larch Road",
    "iso:country":"US",
    "sg:address":"138 Larch Road",
    "sg:city":"Cambridge",
    "sg:classifiers":[
        {
            "category":"Professional",
            "subcategory":"Advertising",
            "type":"Services"
        },
        {
            "category":"Professional",
            "subcategory":"Computer Services",
            "type":"Services"
        }
    ],
    "sg:phone":"+1 617 997 1654",
    "sg:postcode":"02138",
    "sg:province":"MA",
    "sg:tags":[
        "consultant",
        "marketing",
        "internet"
    ],
    "sg:website":"http://searchbenefit.com",
    "wof:name":"Search Benefit SEO Consultancy",
    "wof:placetype":"venue"
},
  "geometry": {"coordinates":[-71.142723,42.378435],"type":"Point"}
}