{
  "type": "Feature",
  "properties": {
    "iso:country":"US",
    "sg:address":"12 Achilles Way",
    "sg:city":"Attleboro Falls",
    "sg:classifiers":[
        {
            "category":"Professional",
            "subcategory":"Business Services",
            "type":"Services"
        }
    ],
    "sg:phone":"+1   ",
    "sg:postcode":"02763",
    "sg:province":"MA",
    "wof:name":"Granite Bay Solutions Inc",
    "wof:placetype":"venue"
},
  "geometry": {"coordinates":[-71.319061,41.958963],"type":"Point"}
}