{
  "type": "Feature",
  "properties": {
    "iso:country":"US",
    "sg:address":"130 Water St",
    "sg:city":"Fitchburg",
    "sg:classifiers":[
        {
            "category":"Food & Beverages",
            "subcategory":"Groceries & Convenience Stores",
            "type":"Retail Goods"
        }
    ],
    "sg:phone":"+1 978 345 5882",
    "sg:postcode":"01420",
    "sg:province":"MA",
    "sg:tags":[
        "grocer"
    ],
    "wof:name":"De Moulas Supermarket",
    "wof:placetype":"venue"
},
  "geometry": {"coordinates":[-71.795047,42.580344],"type":"Point"}
}