{
  "type": "Feature",
  "properties": {
    "addr:full": "130 Water St Fitchburg MA 01420",
    "addr:housenumber": "130",
    "addr:postcode": "01420",
    "addr:street": "Water St",
    "iso:country": "US",
    "sg:address": "130 Water St",
    "sg:city": "Fitchburg",
    "sg:classifiers": [
      {
        "category": "Food \u0026 Beverages",
        "subcategory": "Groceries \u0026 Convenience Stores",
        "type": "Retail Goods"
      }
    ],
    "sg:phone": "+1 978 345 5882",
    "sg:postcode": "01420",
    "sg:province": "MA",
    "sg:tags": [
      "grocer"
    ],
    "wof:name": "De Moulas Supermarket",
    "wof:placetype": "venue"
  },
  "geometry": {"coordinates":[-71.795047,42.580344],"type":"Point"}
}
