{
  "type": "Feature",
  "properties": {
    "addr:full": "32 Robinwood Rd Norwood MA 02062",
    "addr:housenumber": "32",
    "addr:postcode": "02062",
    "addr:street": "Robinwood Rd",
    "iso:country": "US",
    "sg:address": "32 Robinwood Rd",
    "sg:city": "Norwood",
    "sg:classifiers": [
      {
        "category": "Building \u0026 Trades",
        "subcategory": "Construction",
        "type": "Services"
      }
    ],
    "sg:phone": "+1 781 769 1146",
    "sg:postcode": "02062",
    "sg:province": "MA",
    "sg:tags": [
      "contractor"
    ],
    "wof:name": "A Andreassi \u0026 Son Inc",
    "wof:placetype": "venue"
  },
  "geometry": {"coordinates":[-71.178802,42.1721],"type":"Point"}
}
