{
  "type": "Feature",
  "properties": {
    "addr:full":"3 Main St Ste C Eastham MA 02642",
    "addr:housenumber":"3",
    "addr:postcode":"02642",
    "addr:street":"Main St Ste C",
    "iso:country":"US",
    "sg:address":"3 Main St Ste C",
    "sg:city":"Eastham",
    "sg:classifiers":[
        {
            "category":"Personal",
            "subcategory":"Beauty Salon",
            "type":"Services"
        }
    ],
    "sg:phone":"+1 508 240 1481",
    "sg:postcode":"02642",
    "sg:province":"MA",
    "wof:name":"Free Stylen Hair Salon",
    "wof:placetype":"venue"
},
  "geometry": {"coordinates":[-69.987544,41.852671],"type":"Point"}
}