{
  "type": "Feature",
  "properties": {
    "iso:country":"US",
    "sg:address":"1525 Main St",
    "sg:city":"Springfield",
    "sg:classifiers":[
        {
            "category":"Shopping",
            "subcategory":"Jewelry",
            "type":"Retail Goods"
        }
    ],
    "sg:phone":"+1 413 781 6655",
    "sg:postcode":"01103",
    "sg:province":"MA",
    "sg:tags":[
        "jeweler"
    ],
    "wof:name":"Kim's Jewelry",
    "wof:placetype":"venue"
},
  "geometry": {"coordinates":[-72.59133799999999,42.102999],"type":"Point"}
}