{
  "type": "Feature",
  "properties": {
    "iso:country":"US",
    "sg:address":"50 Congress Street Suite 620",
    "sg:city":"Boston",
    "sg:classifiers":[
        {
            "category":"Professional",
            "subcategory":"Accounting & Tax Preparation",
            "type":"Services"
        }
    ],
    "sg:phone":"+1 617 523 4412",
    "sg:postcode":"02109",
    "sg:province":"MA",
    "sg:tags":[
        "accountant"
    ],
    "wof:name":"Beattie & Company",
    "wof:placetype":"venue"
},
  "geometry": {"coordinates":[-71.053326,42.36222],"type":"Point"}
}