{
  "type": "Feature",
  "properties": {
    "addr:full":"14 Kelly's Way Vineyard Haven MA 02568",
    "addr:housenumber":"14",
    "addr:postcode":"02568",
    "addr:street":"Kelly'S Way",
    "iso:country":"US",
    "sg:address":"14 Kelly's Way",
    "sg:city":"Vineyard Haven",
    "sg:classifiers":[
        {
            "category":"Restaurant",
            "type":"Food & Drink"
        }
    ],
    "sg:phone":"+1 508 693 4394",
    "sg:postcode":"02568",
    "sg:province":"MA",
    "sg:tags":[
        "caterer"
    ],
    "wof:name":"O'Shucks Rawbars",
    "wof:placetype":"venue"
},
  "geometry": {"coordinates":[-70.60986200000001,41.451293],"type":"Point"}
}