{
  "type": "Feature",
  "properties": {
    "addr:full":"681 Falmouth Rd Ste A29 Mashpee MA 02649",
    "addr:housenumber":"681",
    "addr:postcode":"02649",
    "addr:street":"Falmouth Rd Ste A29",
    "iso:country":"US",
    "sg:address":"681 Falmouth Rd Ste A29",
    "sg:city":"Mashpee",
    "sg:classifiers":[
        {
            "category":"Autos & Motor Vehicles",
            "subcategory":"Automobile Sales",
            "type":"Retail Goods"
        }
    ],
    "sg:phone":"+1 508 477 3322",
    "sg:postcode":"02649",
    "sg:province":"MA",
    "sg:tags":[
        "used",
        "car",
        "broker",
        "dealers-used",
        "truck",
        "cars-wholesale"
    ],
    "wof:name":"Mashpee Auto Brokers",
    "wof:placetype":"venue"
},
  "geometry": {"coordinates":[-70.490663,41.610342],"type":"Point"}
}