{
  "type": "Feature",
  "properties": {
    "addr:full": "56 Pulaski St Peabody MA 01960",
    "addr:housenumber": "56",
    "addr:postcode": "01960",
    "addr:street": "Pulaski St",
    "iso:country": "US",
    "sg:address": "56 Pulaski St",
    "sg:city": "Peabody",
    "sg:classifiers": [
      {
        "category": "Manufacturing",
        "subcategory": "Textiles",
        "type": "Manufacturing \u0026 Wholesale Goods"
      }
    ],
    "sg:phone": "+1 978 532 1670",
    "sg:postcode": "01960",
    "sg:province": "MA",
    "sg:tags": [
      "mills",
      "fabric"
    ],
    "sg:website": "www.cushmar.com",
    "wof:name": "Cushman \u0026 Marden",
    "wof:placetype": "venue"
  },
  "geometry": {"coordinates":[-70.921677,42.543057],"type":"Point"}
}
