{
  "type": "Feature",
  "properties": {
    "addr:full":"48 Stoddard St Stoughton MA 02072",
    "addr:housenumber":"48",
    "addr:postcode":"02072",
    "addr:street":"Stoddard St",
    "iso:country":"US",
    "sg:address":"48 Stoddard St",
    "sg:city":"Stoughton",
    "sg:classifiers":[
        {
            "category":"Building & Trades",
            "subcategory":"Construction",
            "type":"Services"
        }
    ],
    "sg:phone":"+1   ",
    "sg:postcode":"02072",
    "sg:province":"MA",
    "sg:tags":[
        "house"
    ],
    "wof:name":"McCabe Construction",
    "wof:placetype":"venue"
},
  "geometry": {"coordinates":[-71.110692,42.124623],"type":"Point"}
}