{
  "type": "Feature",
  "properties": {
    "iso:country":"US",
    "sg:address":"214 Humphrey St",
    "sg:city":"Marblehead",
    "sg:classifiers":[
        {
            "category":"Health Services",
            "subcategory":"Clinic",
            "type":"Services"
        }
    ],
    "sg:phone":"+1 781 639 7766",
    "sg:postcode":"01945",
    "sg:province":"MA",
    "sg:tags":[
        "home"
    ],
    "sg:website":"www.coastalcare.com",
    "wof:name":"Coastal Care",
    "wof:placetype":"venue"
},
  "geometry": {"coordinates":[-70.887029,42.484459],"type":"Point"}
}