{
  "type": "Feature",
  "properties": {
    "iso:country":"US",
    "sg:address":"21 Elm St",
    "sg:city":"Springfield",
    "sg:classifiers":[
        {
            "category":"Manufacturing",
            "subcategory":"Printing",
            "type":"Manufacturing & Wholesale Goods"
        }
    ],
    "sg:phone":"+1 413 781 6724",
    "sg:postcode":"01103",
    "sg:province":"MA",
    "sg:tags":[
        "printer"
    ],
    "wof:name":"KNE Printing & Coping",
    "wof:placetype":"venue"
},
  "geometry": {"coordinates":[-72.58806,42.101302],"type":"Point"}
}