{
  "type": "Feature",
  "properties": {
    "addr:full": "21 Elm St Springfield MA 01103",
    "addr:housenumber": "21",
    "addr:postcode": "01103",
    "addr:street": "Elm St",
    "iso:country": "US",
    "sg:address": "21 Elm St",
    "sg:city": "Springfield",
    "sg:classifiers": [
      {
        "category": "Manufacturing",
        "subcategory": "Printing",
        "type": "Manufacturing \u0026 Wholesale Goods"
      }
    ],
    "sg:phone": "+1 413 781 6724",
    "sg:postcode": "01103",
    "sg:province": "MA",
    "sg:tags": [
      "printer"
    ],
    "wof:name": "KNE Printing \u0026 Coping",
    "wof:placetype": "venue"
  },
  "geometry": {"coordinates":[-72.58806,42.101302],"type":"Point"}
}
