{
  "type": "Feature",
  "properties": {
    "iso:country":"US",
    "sg:address":"430 E Britannia St",
    "sg:city":"Taunton",
    "sg:classifiers":[
        {
            "category":"Recreation",
            "type":"Entertainment"
        }
    ],
    "sg:phone":"+1 508 823 8024",
    "sg:postcode":"02780",
    "sg:province":"MA",
    "sg:tags":[
        "club",
        "membership"
    ],
    "wof:name":"Taunton Rifle & Pistol Club",
    "wof:placetype":"venue"
},
  "geometry": {"coordinates":[-71.083095,41.922439],"type":"Point"}
}