{
  "type": "Feature",
  "properties": {
    "iso:country":"US",
    "sg:address":"21 Olympia Ave",
    "sg:city":"Woburn",
    "sg:classifiers":[
        {
            "category":"Health Services",
            "subcategory":"Clinic",
            "type":"Services"
        }
    ],
    "sg:phone":"+1 781 935 0060",
    "sg:postcode":"01801",
    "sg:province":"MA",
    "sg:tags":[
        "organization",
        "medical",
        "surgical"
    ],
    "wof:name":"Emergency Response Training",
    "wof:placetype":"venue"
},
  "geometry": {"coordinates":[-71.12894799999999,42.499846],"type":"Point"}
}