{
  "type": "Feature",
  "properties": {
    "iso:country":"US",
    "sg:address":"136 Dwight Rd",
    "sg:city":"Longmeadow",
    "sg:classifiers":[
        {
            "category":"Banks & Credit Unions",
            "subcategory":"Investment Brokerage",
            "type":"Services"
        }
    ],
    "sg:phone":"+1 413 567 8200",
    "sg:postcode":"01106",
    "sg:province":"MA",
    "sg:tags":[
        "advisory",
        "financial"
    ],
    "wof:name":"Gateway Capitol Management",
    "wof:placetype":"venue"
},
  "geometry": {"coordinates":[-72.538831,42.061181],"type":"Point"}
}