{
  "type": "Feature",
  "properties": {
    "addr:full": "136 Dwight Rd Longmeadow MA 01106",
    "addr:housenumber": "136",
    "addr:postcode": "01106",
    "addr:street": "Dwight Rd",
    "iso:country": "US",
    "sg:address": "136 Dwight Rd",
    "sg:city": "Longmeadow",
    "sg:classifiers": [
      {
        "category": "Banks \u0026 Credit Unions",
        "subcategory": "Investment Brokerage",
        "type": "Services"
      }
    ],
    "sg:phone": "+1 413 567 8200",
    "sg:postcode": "01106",
    "sg:province": "MA",
    "sg:tags": [
      "advisory",
      "financial"
    ],
    "wof:name": "Gateway Capitol Management",
    "wof:placetype": "venue"
  },
  "geometry": {"coordinates":[-72.538831,42.061181],"type":"Point"}
}
