{
  "type": "Feature",
  "properties": {
    "iso:country":"US",
    "sg:address":"46 Bass Ave",
    "sg:city":"Gloucester",
    "sg:classifiers":[
        {
            "category":"Personal",
            "subcategory":"Beauty Salon",
            "type":"Services"
        }
    ],
    "sg:phone":"+1 978 281 3431",
    "sg:postcode":"01930",
    "sg:province":"MA",
    "sg:tags":[
        "manicuring"
    ],
    "wof:name":"Ultimate Skin & Nail Care",
    "wof:placetype":"venue"
},
  "geometry": {"coordinates":[-70.645011,42.616583],"type":"Point"}
}