{
  "type": "Feature",
  "properties": {
    "iso:country":"US",
    "sg:address":"65 Walnut St",
    "sg:city":"Wellesley",
    "sg:classifiers":[
        {
            "category":"Health Services",
            "subcategory":"Health Practitioner",
            "type":"Services"
        }
    ],
    "sg:phone":"+1 781 237 7353",
    "sg:postcode":"02481",
    "sg:province":"MA",
    "sg:tags":[
        "therapist",
        "physical"
    ],
    "wof:name":"Physical Therapy Advantage",
    "wof:placetype":"venue"
},
  "geometry": {"coordinates":[-71.25333000000001,42.324257],"type":"Point"}
}