{
  "type": "Feature",
  "properties": {
    "addr:full":"13 Logan St New Bedford MA 02740",
    "addr:housenumber":"13",
    "addr:postcode":"02740",
    "addr:street":"Logan St",
    "iso:country":"US",
    "sg:address":"13 Logan St",
    "sg:city":"New Bedford",
    "sg:classifiers":[
        {
            "category":"Wholesale",
            "subcategory":"Metals & Minerals",
            "type":"Manufacturing & Wholesale Goods"
        }
    ],
    "sg:phone":"+1 508 994 2652",
    "sg:postcode":"02740",
    "sg:province":"MA",
    "sg:tags":[
        "steel",
        "warehouse"
    ],
    "wof:name":"Whaling City Iron Co",
    "wof:placetype":"venue"
},
  "geometry": {"coordinates":[-70.92506400000001,41.651755],"type":"Point"}
}