{
  "type": "Feature",
  "properties": {
    "addr:full":"1782 Main St Athol MA 01331",
    "addr:housenumber":"1782",
    "addr:postcode":"01331",
    "addr:street":"Main St",
    "iso:country":"US",
    "sg:address":"1782 Main St",
    "sg:city":"Athol",
    "sg:classifiers":[
        {
            "category":"Banks & Credit Unions",
            "subcategory":"Investment Brokerage",
            "type":"Services"
        }
    ],
    "sg:phone":"+1 978 249 4322",
    "sg:postcode":"01331",
    "sg:province":"MA",
    "sg:tags":[
        "consultant",
        "planning",
        "financial"
    ],
    "wof:name":"American Express Financial Adv",
    "wof:placetype":"venue"
},
  "geometry": {"coordinates":[-72.212585,42.587381],"type":"Point"}
}