{
  "type": "Feature",
  "properties": {
    "iso:country":"US",
    "sg:address":"200 Emerson St",
    "sg:city":"South Boston",
    "sg:classifiers":[
        {
            "category":"Building & Trades",
            "subcategory":"Locksmith",
            "type":"Services"
        }
    ],
    "sg:phone":"+1 617 303 2934",
    "sg:postcode":"02127",
    "sg:province":"MA",
    "sg:tags":[
        "key"
    ],
    "wof:name":"Economy Locksmith",
    "wof:placetype":"venue"
},
  "geometry": {"coordinates":[-71.037639,42.335028],"type":"Point"}
}