{
  "type": "Feature",
  "properties": {
    "addr:full": "200 Emerson St South Boston MA 02127",
    "addr:housenumber": "200",
    "addr:postcode": "02127",
    "addr:street": "Emerson St",
    "iso:country": "US",
    "sg:address": "200 Emerson St",
    "sg:city": "South Boston",
    "sg:classifiers": [
      {
        "category": "Building \u0026 Trades",
        "subcategory": "Locksmith",
        "type": "Services"
      }
    ],
    "sg:phone": "+1 617 303 2934",
    "sg:postcode": "02127",
    "sg:province": "MA",
    "sg:tags": [
      "key"
    ],
    "wof:name": "Economy Locksmith",
    "wof:placetype": "venue"
  },
  "geometry": {"coordinates":[-71.037639,42.335028],"type":"Point"}
}
