{
  "type": "Feature",
  "properties": {
    "addr:full": "45 Rumford Ave Waltham MA 02453",
    "addr:housenumber": "45",
    "addr:postcode": "02453",
    "addr:street": "Rumford Ave",
    "iso:country": "US",
    "sg:address": "45 Rumford Ave",
    "sg:city": "Waltham",
    "sg:classifiers": [
      {
        "category": "Wholesale",
        "subcategory": "Electrical",
        "type": "Manufacturing \u0026 Wholesale Goods"
      }
    ],
    "sg:phone": "+1 781 647 1010",
    "sg:postcode": "02453",
    "sg:province": "MA",
    "sg:tags": [
      "communication",
      "radio",
      "system"
    ],
    "sg:website": "www.cybercomm.cc",
    "wof:name": "Cyber Communications",
    "wof:placetype": "venue"
  },
  "geometry": {"coordinates":[-71.244783,42.360539],"type":"Point"}
}
