{
  "type": "Feature",
  "properties": {
    "iso:country":"US",
    "sg:address":"95 Willis St",
    "sg:city":"South Dartmouth",
    "sg:classifiers":[
        {
            "category":"Professional",
            "type":"Services"
        }
    ],
    "sg:phone":"+1 508 991 4668",
    "sg:postcode":"02748",
    "sg:province":"MA",
    "sg:tags":[
        "establishment"
    ],
    "wof:name":"Convivia Inc",
    "wof:placetype":"venue"
},
  "geometry": {"coordinates":[-70.935005,41.595277],"type":"Point"}
}