{
  "type": "Feature",
  "properties": {
    "iso:country":"US",
    "sg:address":"1493 Cambridge St",
    "sg:city":"Cambridge",
    "sg:classifiers":[
        {
            "category":"Health Services",
            "subcategory":"Doctor",
            "type":"Services"
        }
    ],
    "sg:phone":"+1 617 665 1566",
    "sg:postcode":"02139",
    "sg:province":"MA",
    "sg:tags":[
        "orthopedist"
    ],
    "sg:website":"cambridge.photobooks.com/directo...",
    "wof:name":"Robert Nicoletta, MD",
    "wof:placetype":"venue"
},
  "geometry": {"coordinates":[-71.103362,42.374238],"type":"Point"}
}