{
  "type": "Feature",
  "properties": {
    "addr:full": "137 Lafayette Rd Salisbury MA 01952",
    "addr:housenumber": "137",
    "addr:postcode": "01952",
    "iso:country": "US",
    "sg:address": "137 Lafayette Rd",
    "sg:city": "Salisbury",
    "sg:classifiers": [
      {
        "category": "Autos \u0026 Motor Vehicles",
        "subcategory": "Fuel \u0026 Gas Station",
        "type": "Retail Goods"
      }
    ],
    "sg:phone": "+1 978 465 8326",
    "sg:postcode": "01952",
    "sg:province": "MA",
    "sg:tags": [
      "station",
      "gasoline"
    ],
    "wof:name": "Affordable Transmissions",
    "wof:placetype": "venue"
  },
  "geometry": {"coordinates":[-70.872597,42.857763],"type":"Point"}
}
