{
  "type": "Feature",
  "properties": {
    "iso:country":"US",
    "sg:address":"137 Lafayette Rd",
    "sg:city":"Salisbury",
    "sg:classifiers":[
        {
            "category":"Autos & Motor Vehicles",
            "subcategory":"Fuel & Gas Station",
            "type":"Retail Goods"
        }
    ],
    "sg:phone":"+1 978 465 8326",
    "sg:postcode":"01952",
    "sg:province":"MA",
    "sg:tags":[
        "station",
        "gasoline"
    ],
    "wof:name":"Affordable Transmissions",
    "wof:placetype":"venue"
},
  "geometry": {"coordinates":[-70.872597,42.857763],"type":"Point"}
}