{
  "type": "Feature",
  "properties": {
    "iso:country":"US",
    "sg:address":"200 Great Rd",
    "sg:city":"Bedford",
    "sg:classifiers":[
        {
            "category":"Health Services",
            "subcategory":"Health Practitioner",
            "type":"Services"
        }
    ],
    "sg:phone":"+1 781 275 1800",
    "sg:postcode":"01730",
    "sg:province":"MA",
    "sg:tags":[
        "psychologist"
    ],
    "wof:name":"Naomi M Dogan",
    "wof:placetype":"venue"
},
  "geometry": {"coordinates":[-71.27252799999999,42.489573],"type":"Point"}
}