{
  "type": "Feature",
  "properties": {
    "addr:full":"289 Elm St Everett MA 02149",
    "addr:housenumber":"289",
    "addr:postcode":"02149",
    "addr:street":"Elm St",
    "iso:country":"US",
    "sg:address":"289 Elm St",
    "sg:city":"Everett",
    "sg:phone":"+1 617 389 9300",
    "sg:postcode":"02149",
    "sg:province":"MA",
    "sg:website":"http://www.everett-nursing.com",
    "wof:name":"Everett Nursing and Rehabilitation Center",
    "wof:placetype":"venue"
},
  "geometry": {"coordinates":[-71.035383,42.414944],"type":"Point"}
}