{
  "type": "Feature",
  "properties": {
    "addr:full":"16 Scott Hollow Dr Holyoke MA 01040",
    "addr:housenumber":"16",
    "addr:postcode":"01040",
    "addr:street":"Scott Hollow Dr",
    "iso:country":"US",
    "sg:address":"16 Scott Hollow Dr",
    "sg:city":"Holyoke",
    "sg:classifiers":[
        {
            "category":"Home & Garden",
            "subcategory":"Home Furnishings",
            "type":"Retail Goods"
        }
    ],
    "sg:phone":"+1   ",
    "sg:postcode":"01040",
    "sg:province":"MA",
    "wof:name":"Pampered Chef",
    "wof:placetype":"venue"
},
  "geometry": {"coordinates":[-72.640018,42.213582],"type":"Point"}
}