{
  "type": "Feature",
  "properties": {
    "iso:country":"US",
    "sg:address":"362 N Bedford St",
    "sg:city":"East Bridgewater",
    "sg:classifiers":[
        {
            "category":"Manufacturing",
            "subcategory":"Printing",
            "type":"Manufacturing & Wholesale Goods"
        },
        {
            "category":"Shopping",
            "subcategory":"Computers & Home Electronics",
            "type":"Retail Goods"
        }
    ],
    "sg:phone":"+1 508 378 1110",
    "sg:postcode":"02333",
    "sg:province":"MA",
    "sg:tags":[
        "book",
        "publishing"
    ],
    "wof:name":"Drummond Publishing Group Inc",
    "wof:placetype":"venue"
},
  "geometry": {"coordinates":[-70.955001,42.047109],"type":"Point"}
}