{
  "type": "Feature",
  "properties": {
    "addr:full": "362 N Bedford St East Bridgewater MA 02333",
    "addr:housenumber": "362",
    "addr:postcode": "02333",
    "addr:street": "N Bedford St",
    "iso:country": "US",
    "sg:address": "362 N Bedford St",
    "sg:city": "East Bridgewater",
    "sg:classifiers": [
      {
        "category": "Manufacturing",
        "subcategory": "Printing",
        "type": "Manufacturing \u0026 Wholesale Goods"
      },
      {
        "category": "Shopping",
        "subcategory": "Computers \u0026 Home Electronics",
        "type": "Retail Goods"
      }
    ],
    "sg:phone": "+1 508 378 1110",
    "sg:postcode": "02333",
    "sg:province": "MA",
    "sg:tags": [
      "book",
      "publishing"
    ],
    "wof:name": "Drummond Publishing Group Inc",
    "wof:placetype": "venue"
  },
  "geometry": {"coordinates":[-70.955001,42.047109],"type":"Point"}
}
