{
  "type": "Feature",
  "properties": {
    "addr:full": "86 E Main St Westborough MA 01581",
    "addr:housenumber": "86",
    "addr:postcode": "01581",
    "addr:street": "E Main St",
    "iso:country": "US",
    "sg:address": "86 E Main St",
    "sg:city": "Westborough",
    "sg:classifiers": [
      {
        "category": "Health Services",
        "subcategory": "Health Practitioner",
        "type": "Services"
      }
    ],
    "sg:phone": "+1 508 366 0342",
    "sg:postcode": "01581",
    "sg:province": "MA",
    "sg:tags": [
      "psychologist"
    ],
    "wof:name": "Jay L Ryan PHD",
    "wof:placetype": "venue"
  },
  "geometry": {"coordinates":[-71.609143,42.276081],"type":"Point"}
}
