{
  "type": "Feature",
  "properties": {
    "iso:country":"US",
    "sg:address":"86 E Main St",
    "sg:city":"Westborough",
    "sg:classifiers":[
        {
            "category":"Health Services",
            "subcategory":"Health Practitioner",
            "type":"Services"
        }
    ],
    "sg:phone":"+1 508 366 0342",
    "sg:postcode":"01581",
    "sg:province":"MA",
    "sg:tags":[
        "psychologist"
    ],
    "wof:name":"Jay L Ryan PHD",
    "wof:placetype":"venue"
},
  "geometry": {"coordinates":[-71.609143,42.276081],"type":"Point"}
}