{
  "type": "Feature",
  "properties": {
    "iso:country":"US",
    "sg:address":"16 Everett St",
    "sg:city":"Holliston",
    "sg:classifiers":[
        {
            "category":"Recreation",
            "type":"Entertainment"
        }
    ],
    "sg:phone":"+1 508 429 7779",
    "sg:postcode":"01749",
    "sg:province":"MA",
    "sg:tags":[
        "instruction",
        "gymnastic"
    ],
    "wof:name":"Gymnastics Training Ctr",
    "wof:placetype":"venue"
},
  "geometry": {"coordinates":[-71.572692,42.387501],"type":"Point"}
}