{
  "type": "Feature",
  "properties": {
    "addr:full": "1 General St Lawrence MA 01841",
    "addr:housenumber": "1",
    "addr:postcode": "01841",
    "addr:street": "General St",
    "iso:country": "US",
    "sg:address": "1 General St",
    "sg:city": "Lawrence",
    "sg:classifiers": [
      {
        "category": "Health Services",
        "subcategory": "Doctor",
        "type": "Services"
      }
    ],
    "sg:phone": "+1 978 688 8076",
    "sg:postcode": "01841",
    "sg:province": "MA",
    "sg:tags": [
      "physician",
      "surgeon"
    ],
    "wof:name": "Merrimack Valley Cardiac-Cath",
    "wof:placetype": "venue"
  },
  "geometry": {"coordinates":[-71.151378,42.709157],"type":"Point"}
}
