{
  "type": "Feature",
  "properties": {
    "addr:full":"914 Grafton St Worcester MA 01604",
    "addr:housenumber":"914",
    "addr:postcode":"01604",
    "addr:street":"Grafton St",
    "iso:country":"US",
    "sg:address":"914 Grafton St",
    "sg:city":"Worcester",
    "sg:classifiers":[
        {
            "category":"Shopping",
            "subcategory":"Jewelry",
            "type":"Retail Goods"
        }
    ],
    "sg:phone":"+1 508 791 2222",
    "sg:postcode":"01604",
    "sg:province":"MA",
    "wof:name":"Birjan Fine Jewelry",
    "wof:placetype":"venue"
},
  "geometry": {"coordinates":[-71.760289,42.246584],"type":"Point"}
}