{
  "type": "Feature",
  "properties": {
    "addr:full": "29 Pearl St Braintree MA 02184",
    "addr:housenumber": "29",
    "addr:postcode": "02184",
    "addr:street": "Pearl St",
    "iso:country": "US",
    "sg:address": "29 Pearl St",
    "sg:city": "Braintree",
    "sg:classifiers": [
      {
        "category": "Building \u0026 Trades",
        "subcategory": "Construction",
        "type": "Services"
      }
    ],
    "sg:phone": "+1 781 380 0555",
    "sg:postcode": "02184",
    "sg:province": "MA",
    "sg:tags": [
      "painter"
    ],
    "wof:name": "M \u0026 J Painting Contractors",
    "wof:placetype": "venue"
  },
  "geometry": {"coordinates":[-71.004872,42.202175],"type":"Point"}
}
