{
  "type": "Feature",
  "properties": {
    "addr:full": "941 Mary Dunn Rd Hyannis MA 02601",
    "addr:housenumber": "941",
    "addr:postcode": "02601",
    "addr:street": "Mary Dunn Rd",
    "iso:country": "US",
    "sg:address": "941 Mary Dunn Rd",
    "sg:city": "Hyannis",
    "sg:classifiers": [
      {
        "category": "Organizations",
        "subcategory": "Religious Organization",
        "type": "Services"
      }
    ],
    "sg:phone": "+1 508 778 4442",
    "sg:postcode": "02601",
    "sg:province": "MA",
    "sg:tags": [
      "church"
    ],
    "wof:name": "Brazilian Assembly Of God",
    "wof:placetype": "venue"
  },
  "geometry": {"coordinates":[-70.280991,41.687007],"type":"Point"}
}
