{
  "type": "Feature",
  "properties": {
    "addr:full":"1245 Worcester St Natick MA 01760",
    "addr:housenumber":"1245",
    "addr:postcode":"01760",
    "addr:street":"Worcester St",
    "iso:country":"US",
    "sg:address":"1245 Worcester St",
    "sg:city":"Natick",
    "sg:classifiers":[
        {
            "category":"Building & Trades",
            "subcategory":"Plumbing",
            "type":"Services"
        }
    ],
    "sg:phone":"+1 508 651 2200",
    "sg:postcode":"01760",
    "sg:province":"MA",
    "sg:tags":[
        "heating",
        "contractor"
    ],
    "wof:name":"Sudden Service",
    "wof:placetype":"venue"
},
  "geometry": {"coordinates":[-71.385413,42.299141],"type":"Point"}
}