{
  "type": "Feature",
  "properties": {
    "addr:full": "136 Chatham St Lynn MA 01902",
    "addr:housenumber": "136",
    "addr:postcode": "01902",
    "addr:street": "Chatham St",
    "iso:country": "US",
    "sg:address": "136 Chatham St",
    "sg:city": "Lynn",
    "sg:classifiers": [
      {
        "category": "Shopping",
        "subcategory": "Computers \u0026 Home Electronics",
        "type": "Retail Goods"
      }
    ],
    "sg:phone": "+1 781 581 0776",
    "sg:postcode": "01902",
    "sg:province": "MA",
    "sg:tags": [
      "equipment",
      "satellite",
      "system"
    ],
    "wof:name": "Satellite Pro",
    "wof:placetype": "venue"
  },
  "geometry": {"coordinates":[-70.934567,42.471576],"type":"Point"}
}
