{
  "type": "Feature",
  "properties": {
    "addr:full":"3 Hamilton Ave South Hamilton MA 01982",
    "addr:housenumber":"3",
    "addr:postcode":"01982",
    "addr:street":"Hamilton Ave South",
    "iso:country":"US",
    "sg:address":"3 Hamilton Ave",
    "sg:city":"South Hamilton",
    "sg:classifiers":[
        {
            "category":"Utilities",
            "subcategory":"Fuel Oil & Lpg",
            "type":"Services"
        }
    ],
    "sg:phone":"+1 978 468 1695",
    "sg:postcode":"01982",
    "sg:province":"MA",
    "sg:tags":[
        "dealer"
    ],
    "wof:name":"Covert Oil Co",
    "wof:placetype":"venue"
},
  "geometry": {"coordinates":[-70.87513800000001,42.612484],"type":"Point"}
}