{
  "type": "Feature",
  "properties": {
    "iso:country":"US",
    "sg:address":"170 Common St",
    "sg:city":"Lawrence",
    "sg:classifiers":[
        {
            "category":"Banks & Credit Unions",
            "subcategory":"Bank",
            "type":"Services"
        }
    ],
    "sg:phone":"+1 978 725 6766",
    "sg:postcode":"01840",
    "sg:province":"MA",
    "sg:tags":[
        "loan",
        "real estate"
    ],
    "wof:name":"Confidence Mortgage",
    "wof:placetype":"venue"
},
  "geometry": {"coordinates":[-71.15952299999999,42.708409],"type":"Point"}
}