{
  "type": "Feature",
  "properties": {
    "addr:full": "170 Common St Lawrence MA 01840",
    "addr:housenumber": "170",
    "addr:postcode": "01840",
    "addr:street": "Common",
    "iso:country": "US",
    "sg:address": "170 Common St",
    "sg:city": "Lawrence",
    "sg:classifiers": [
      {
        "category": "Banks \u0026 Credit Unions",
        "subcategory": "Bank",
        "type": "Services"
      }
    ],
    "sg:phone": "+1 978 725 6766",
    "sg:postcode": "01840",
    "sg:province": "MA",
    "sg:tags": [
      "loan",
      "real estate"
    ],
    "wof:name": "Confidence Mortgage",
    "wof:placetype": "venue"
  },
  "geometry": {"coordinates":[-71.159523,42.708409],"type":"Point"}
}
