{
  "type": "Feature",
  "properties": {
    "iso:country":"US",
    "sg:address":"106 Walford Way",
    "sg:city":"Charlestown",
    "sg:classifiers":[
        {
            "category":"Professional",
            "subcategory":"Employment Agencies",
            "type":"Services"
        }
    ],
    "sg:phone":"+1 617 242 5474",
    "sg:postcode":"02129",
    "sg:province":"MA",
    "wof:name":"Housing Opportunities Unlimited",
    "wof:placetype":"venue"
},
  "geometry": {"coordinates":[-71.05816900000001,42.378387],"type":"Point"}
}