{
  "type": "Feature",
  "properties": {
    "addr:full":"186 Kent St Brookline MA 02446",
    "addr:housenumber":"186",
    "addr:postcode":"02446",
    "addr:street":"Kent St",
    "iso:country":"US",
    "sg:address":"186 Kent St",
    "sg:city":"Brookline",
    "sg:classifiers":[
        {
            "category":"Professional",
            "subcategory":"Advertising",
            "type":"Services"
        }
    ],
    "sg:phone":"+1 617 277 9687",
    "sg:postcode":"02446",
    "sg:province":"MA",
    "sg:tags":[
        "station",
        "radio",
        "representative"
    ],
    "wof:name":"WVUD",
    "wof:placetype":"venue"
},
  "geometry": {"coordinates":[-71.113444,42.336256],"type":"Point"}
}