{
  "type": "Feature",
  "properties": {
    "iso:country":"US",
    "sg:address":"21 Commerce Way",
    "sg:city":"Plymouth",
    "sg:classifiers":[
        {
            "category":"Banks & Credit Unions",
            "subcategory":"Bank",
            "type":"Services"
        }
    ],
    "sg:phone":"+1 508 830 6822",
    "sg:postcode":"02360",
    "sg:province":"MA",
    "sg:website":"www.sovereignbank.com",
    "wof:name":"Sovereign Bank",
    "wof:placetype":"venue"
},
  "geometry": {"coordinates":[-70.715127,41.949656],"type":"Point"}
}