{
  "type": "Feature",
  "properties": {
    "addr:full":"840 Winter St Waltham MA 02451",
    "addr:housenumber":"840",
    "addr:postcode":"02451",
    "addr:street":"Winter St",
    "iso:country":"US",
    "sg:address":"840 Winter St",
    "sg:city":"Waltham",
    "sg:classifiers":[
        {
            "category":"Personal",
            "subcategory":"Beauty Salon",
            "type":"Services"
        }
    ],
    "sg:phone":"+1 781 890 9211",
    "sg:postcode":"02451",
    "sg:province":"MA",
    "sg:website":"www.darylchristopher.com",
    "wof:name":"Christopher Daryl LTD",
    "wof:placetype":"venue"
},
  "geometry": {"coordinates":[-71.273869,42.398651],"type":"Point"}
}