{
  "type": "Feature",
  "properties": {
    "addr:full": "495 Main St Southbridge MA 01550",
    "addr:housenumber": "495",
    "addr:postcode": "01550",
    "addr:street": "Main St",
    "iso:country": "US",
    "sg:address": "495 Main St",
    "sg:city": "Southbridge",
    "sg:classifiers": [
      {
        "category": "Health Services",
        "subcategory": "Doctor",
        "type": "Services"
      }
    ],
    "sg:phone": "+1 508 765 9855",
    "sg:postcode": "01550",
    "sg:province": "MA",
    "wof:name": "Thomas T K MD PC",
    "wof:placetype": "venue"
  },
  "geometry": {"coordinates":[-72.037498,42.0774],"type":"Point"}
}
