{
  "type": "Feature",
  "properties": {
    "addr:full": "38 Phillips St Lawrence MA 01843",
    "addr:housenumber": "38",
    "addr:postcode": "01843",
    "addr:street": "Phillips St",
    "iso:country": "US",
    "sg:address": "38 Phillips St",
    "sg:city": "Lawrence",
    "sg:classifiers": [
      {
        "category": "Organizations",
        "subcategory": "Religious Organization",
        "type": "Services"
      }
    ],
    "sg:phone": "+1 978 682 1987",
    "sg:postcode": "01843",
    "sg:province": "MA",
    "sg:tags": [
      "church"
    ],
    "wof:name": "Immaculate Conception Parish",
    "wof:placetype": "venue"
  },
  "geometry": {"coordinates":[-71.150691,42.696268],"type":"Point"}
}
