{
  "type": "Feature",
  "properties": {
    "addr:full":"1 Broadway Lawrence MA 01840",
    "addr:housenumber":"1",
    "addr:postcode":"01840",
    "addr:street":"Broadway",
    "iso:country":"US",
    "sg:address":"1 Broadway",
    "sg:city":"Lawrence",
    "sg:classifiers":[
        {
            "category":"Building & Trades",
            "subcategory":"Construction",
            "type":"Services"
        }
    ],
    "sg:phone":"+1 978 687 9350",
    "sg:postcode":"01840",
    "sg:province":"MA",
    "sg:tags":[
        "welder"
    ],
    "wof:name":"Steelworks Inc",
    "wof:placetype":"venue"
},
  "geometry": {"coordinates":[-71.166748,42.703079],"type":"Point"}
}