{
  "type": "Feature",
  "properties": {
    "addr:full":"3 W Hill Pl Boston MA 02114",
    "addr:housenumber":"3",
    "addr:postcode":"02114",
    "addr:street":"W Hill Pl",
    "iso:country":"US",
    "sg:address":"3 W Hill Pl",
    "sg:city":"Boston",
    "sg:classifiers":[
        {
            "category":"Professional",
            "type":"Services"
        }
    ],
    "sg:phone":"+1 617 367 3882",
    "sg:postcode":"02114",
    "sg:province":"MA",
    "sg:tags":[
        "establishment"
    ],
    "wof:name":"KNOX V",
    "wof:placetype":"venue"
},
  "geometry": {"coordinates":[-71.07136800000001,42.360387],"type":"Point"}
}