{
  "type": "Feature",
  "properties": {
    "addr:full":"29 Henderson St Everett MA 02149",
    "addr:housenumber":"29",
    "addr:postcode":"02149",
    "addr:street":"Henderson St",
    "iso:country":"US",
    "sg:address":"29 Henderson St",
    "sg:city":"Everett",
    "sg:classifiers":[
        {
            "category":"Manufacturing",
            "subcategory":"Printing",
            "type":"Manufacturing & Wholesale Goods"
        }
    ],
    "sg:phone":"+1 617 387 7171",
    "sg:postcode":"02149",
    "sg:province":"MA",
    "sg:tags":[
        "screen"
    ],
    "sg:website":"www.jandm.us",
    "wof:name":"J & M Enterprises",
    "wof:placetype":"venue"
},
  "geometry": {"coordinates":[-71.06071300000001,42.405854],"type":"Point"}
}