{
  "type": "Feature",
  "properties": {
    "addr:full": "227 Church St New Bedford MA 02745",
    "addr:housenumber": "227",
    "addr:postcode": "02745",
    "addr:street": "Church St",
    "iso:country": "US",
    "sg:address": "227 Church St",
    "sg:city": "New Bedford",
    "sg:classifiers": [
      {
        "category": "Shopping",
        "subcategory": "Clothing, Apparel, \u0026 Fashions",
        "type": "Retail Goods"
      }
    ],
    "sg:phone": "+1 508 994 9367",
    "sg:postcode": "02745",
    "sg:province": "MA",
    "wof:name": "D J At Large",
    "wof:placetype": "venue"
  },
  "geometry": {"coordinates":[-70.936561,41.669061],"type":"Point"}
}
