{
  "type": "Feature",
  "properties": {
    "iso:country":"US",
    "sg:address":"63 Hanover St",
    "sg:city":"Newbury",
    "sg:classifiers":[
        {
            "category":"Government",
            "subcategory":"Office",
            "type":"Public Place"
        }
    ],
    "sg:phone":"+1 978 462 8114",
    "sg:postcode":"01951",
    "sg:province":"MA",
    "sg:tags":[
        "city",
        "resource",
        "human"
    ],
    "wof:name":"Council On Aging",
    "wof:placetype":"venue"
},
  "geometry": {"coordinates":[-70.87169799999999,42.791827],"type":"Point"}
}