{
  "type": "Feature",
  "properties": {
    "addr:full": "65 Middlesex Road Tyngsboro MA 01879",
    "addr:housenumber": "65",
    "addr:postcode": "01879",
    "addr:street": "Middlesex Road",
    "iso:country": "US",
    "sg:address": "65 Middlesex Road",
    "sg:city": "Tyngsboro",
    "sg:classifiers": [
      {
        "category": "Professional",
        "subcategory": "Research",
        "type": "Services"
      }
    ],
    "sg:phone": "+1 978 694 9121",
    "sg:postcode": "01879",
    "sg:province": "MA",
    "sg:website": "http://www.beaconpower.com/",
    "wof:name": "Beacon Power",
    "wof:placetype": "venue"
  },
  "geometry": {"coordinates":[-71.408028,42.662226],"type":"Point"}
}
