{
  "type": "Feature",
  "properties": {
    "addr:full": "485 Arsenal St Watertown MA 02472",
    "addr:housenumber": "485",
    "addr:postcode": "02472",
    "addr:street": "Arsenal St",
    "iso:country": "US",
    "sg:address": "485 Arsenal St",
    "sg:city": "Watertown",
    "sg:classifiers": [
      {
        "category": "Restaurant",
        "type": "Food \u0026 Drink"
      }
    ],
    "sg:menulink": "http://www.allmenus.com/ma/watertown/103647-ruby-tuesdays/menu/",
    "sg:phone": "+1 617 926 6070",
    "sg:postcode": "02472",
    "sg:province": "MA",
    "sg:tags": [
      "burger",
      "american"
    ],
    "wof:name": "Ruby Tuesdays",
    "wof:placetype": "venue"
  },
  "geometry": {"coordinates":[-71.158536,42.362897],"type":"Point"}
}
