{
  "type": "Feature",
  "properties": {
    "iso:country":"US",
    "sg:address":"20 Nichols St",
    "sg:city":"Everett",
    "sg:classifiers":[
        {
            "category":"Education",
            "subcategory":"School",
            "type":"Public Place"
        }
    ],
    "sg:phone":"+1 617 394 5020",
    "sg:postcode":"02149",
    "sg:province":"MA",
    "wof:name":"Keverian School",
    "wof:placetype":"venue"
},
  "geometry": {"coordinates":[-71.045788,42.408474],"type":"Point"}
}