{
  "type": "Feature",
  "properties": {
    "addr:full":"659 Washington St Braintree MA 02184",
    "addr:housenumber":"659",
    "addr:postcode":"02184",
    "addr:street":"Washington St",
    "iso:country":"US",
    "sg:address":"659 Washington St",
    "sg:city":"Braintree",
    "sg:classifiers":[
        {
            "category":"Health Services",
            "subcategory":"Doctor",
            "type":"Services"
        }
    ],
    "sg:phone":"+1 617 786 0141",
    "sg:postcode":"02184",
    "sg:province":"MA",
    "sg:tags":[
        "physician",
        "surgeon"
    ],
    "wof:name":"John W Dalton MD",
    "wof:placetype":"venue"
},
  "geometry": {"coordinates":[-71.00390899999999,42.210823],"type":"Point"}
}