{
  "type": "Feature",
  "properties": {
    "iso:country":"US",
    "sg:address":"1212 Hancock St",
    "sg:city":"Quincy",
    "sg:classifiers":[
        {
            "category":"Professional",
            "subcategory":"Lawyer & Legal Services",
            "type":"Services"
        }
    ],
    "sg:phone":"+1 617 479 8222",
    "sg:postcode":"02169",
    "sg:province":"MA",
    "sg:tags":[
        "attorney"
    ],
    "wof:name":"De Miranda Pires & Phelps",
    "wof:placetype":"venue"
},
  "geometry": {"coordinates":[-71.004222,42.25252],"type":"Point"}
}