{
  "type": "Feature",
  "properties": {
    "addr:full": "1320 Belmont St Brockton MA 02301",
    "addr:housenumber": "1320",
    "addr:postcode": "02301",
    "addr:street": "Belmont St",
    "iso:country": "US",
    "sg:address": "1320 Belmont St",
    "sg:city": "Brockton",
    "sg:classifiers": [
      {
        "category": "Autos \u0026 Motor Vehicles",
        "subcategory": "Auto Supplies",
        "type": "Retail Goods"
      }
    ],
    "sg:phone": "+1 508 584 6247",
    "sg:postcode": "02301",
    "sg:province": "MA",
    "sg:tags": [
      "tire"
    ],
    "wof:name": "Sullivan Tire \u0026 Auto Svc Co",
    "wof:placetype": "venue"
  },
  "geometry": {"coordinates":[-71.069466,42.057558],"type":"Point"}
}
