{
  "type": "Feature",
  "properties": {
    "iso:country":"US",
    "sg:address":"1320 Belmont St",
    "sg:city":"Brockton",
    "sg:classifiers":[
        {
            "category":"Autos & Motor Vehicles",
            "subcategory":"Auto Supplies",
            "type":"Retail Goods"
        }
    ],
    "sg:phone":"+1 508 584 6247",
    "sg:postcode":"02301",
    "sg:province":"MA",
    "sg:tags":[
        "tire"
    ],
    "wof:name":"Sullivan Tire & Auto Svc Co",
    "wof:placetype":"venue"
},
  "geometry": {"coordinates":[-71.06946600000001,42.057558],"type":"Point"}
}