{
  "type": "Feature",
  "properties": {
    "iso:country":"US",
    "sg:address":"2 Atlantic Ave",
    "sg:city":"Boston",
    "sg:classifiers":[
        {
            "category":"Utilities",
            "subcategory":"Electric",
            "type":"Services"
        }
    ],
    "sg:phone":"+1 617 720 5206",
    "sg:postcode":"02110",
    "sg:province":"MA",
    "sg:tags":[
        "company"
    ],
    "wof:name":"Calpine Eastern Corp",
    "wof:placetype":"venue"
},
  "geometry": {"coordinates":[-71.051063,42.363651],"type":"Point"}
}