{
  "type": "Feature",
  "properties": {
    "iso:country":"US",
    "sg:address":"270 Benton Dr",
    "sg:city":"East Longmeadow",
    "sg:classifiers":[
        {
            "category":"Professional",
            "subcategory":"Management & Consulting",
            "type":"Services"
        }
    ],
    "sg:phone":"+1 413 759 0000",
    "sg:postcode":"01028",
    "sg:province":"MA",
    "sg:tags":[
        "consultant",
        "business"
    ],
    "wof:name":"Berriman & Assoc",
    "wof:placetype":"venue"
},
  "geometry": {"coordinates":[-72.53213,42.044941],"type":"Point"}
}