{
  "type": "Feature",
  "properties": {
    "addr:full":"162 Thompson Rd Webster MA 01570",
    "addr:housenumber":"162",
    "addr:postcode":"01570",
    "addr:street":"Thompson Rd",
    "iso:country":"US",
    "sg:address":"162 Thompson Rd",
    "sg:city":"Webster",
    "sg:classifiers":[
        {
            "category":"Building & Trades",
            "subcategory":"Construction",
            "type":"Services"
        }
    ],
    "sg:phone":"+1 508 949 8448",
    "sg:postcode":"01570",
    "sg:province":"MA",
    "sg:tags":[
        "designer",
        "dealer",
        "pool",
        "swimming"
    ],
    "wof:name":"Fisher Pool & Spa",
    "wof:placetype":"venue"
},
  "geometry": {"coordinates":[-71.862365,42.042897],"type":"Point"}
}