{
  "type": "Feature",
  "properties": {
    "iso:country":"US",
    "sg:address":"15 Rocsam Park Rd",
    "sg:city":"Braintree",
    "sg:classifiers":[
        {
            "category":"Building & Trades",
            "subcategory":"Construction",
            "type":"Services"
        }
    ],
    "sg:phone":"+1 781 843 4114",
    "sg:postcode":"02184",
    "sg:province":"MA",
    "sg:tags":[
        "home",
        "builder"
    ],
    "wof:name":"Bosworth Group LLC",
    "wof:placetype":"venue"
},
  "geometry": {"coordinates":[-71.03335800000001,42.194826],"type":"Point"}
}