{
  "type": "Feature",
  "properties": {
    "addr:full": "Corner of Beacon and Sutherland Brighton MA 02135",
    "addr:postcode": "02135",
    "addr:street": "Corner",
    "iso:country": "US",
    "sg:address": "Corner of Beacon and Sutherland",
    "sg:city": "Brighton",
    "sg:classifiers": [
      {
        "category": "Restaurant",
        "type": "Food \u0026 Drink"
      },
      {
        "category": "Shopping Center",
        "type": "Public Place"
      }
    ],
    "sg:postcode": "02135",
    "sg:province": "MA",
    "sg:tags": [
      "flavor",
      "local"
    ],
    "wof:name": "Cleveland Circle",
    "wof:placetype": "venue"
  },
  "geometry": {"coordinates":[-71.150292,42.336082],"type":"Point"}
}
