{
  "type": "Feature",
  "properties": {
    "addr:full":"25 Water St Sandwich MA 02563",
    "addr:housenumber":"25",
    "addr:postcode":"02563",
    "addr:street":"Water St",
    "iso:country":"US",
    "sg:address":"25 Water St",
    "sg:city":"Sandwich",
    "sg:classifiers":[
        {
            "category":"Manufacturing",
            "subcategory":"Apparel",
            "type":"Manufacturing & Wholesale Goods"
        }
    ],
    "sg:phone":"+1 508 833 8382",
    "sg:postcode":"02563",
    "sg:province":"MA",
    "sg:tags":[
        "emblem"
    ],
    "wof:name":"Tharpe Co",
    "wof:placetype":"venue"
},
  "geometry": {"coordinates":[-70.497276,41.753756],"type":"Point"}
}