{
  "type": "Feature",
  "properties": {
    "addr:full":"580 Commercial St Boston MA 02109",
    "addr:housenumber":"580",
    "addr:postcode":"02109",
    "addr:street":"Commercial St",
    "iso:country":"US",
    "sg:address":"580 Commercial St",
    "sg:city":"Boston",
    "sg:classifiers":[
        {
            "category":"Retail",
            "subcategory":"Funeral Services",
            "type":"Services"
        }
    ],
    "sg:phone":"+1 617 536 4110",
    "sg:postcode":"02109",
    "sg:province":"MA",
    "sg:tags":[
        "director",
        "plans-pre-arranged"
    ],
    "wof:name":"Boston Harborside Home Of Js Waterman -",
    "wof:placetype":"venue"
},
  "geometry": {"coordinates":[-71.057457,42.367729],"type":"Point"}
}