{
  "type": "Feature",
  "properties": {
    "iso:country":"US",
    "sg:address":"1101 Beacon St",
    "sg:city":"Brookline",
    "sg:classifiers":[
        {
            "category":"Health Services",
            "subcategory":"Clinic",
            "type":"Services"
        }
    ],
    "sg:phone":"+1 617 232 6633",
    "sg:postcode":"02446",
    "sg:province":"MA",
    "sg:tags":[
        "medical"
    ],
    "wof:name":"Sports & Physical Therapy Associates",
    "wof:placetype":"venue"
},
  "geometry": {"coordinates":[-71.111,42.3447],"type":"Point"}
}