{
  "type": "Feature",
  "properties": {
    "addr:full": "106 Broad St Lynn MA 01902",
    "addr:housenumber": "106",
    "addr:postcode": "01902",
    "addr:street": "Broad St",
    "iso:country": "US",
    "sg:address": "106 Broad St",
    "sg:city": "Lynn",
    "sg:classifiers": [
      {
        "category": "Education",
        "subcategory": "School",
        "type": "Public Place"
      }
    ],
    "sg:phone": "+1 781 477 0312",
    "sg:postcode": "01902",
    "sg:province": "MA",
    "wof:name": "Lynn Community Charter School",
    "wof:placetype": "venue"
  },
  "geometry": {"coordinates":[-70.939315,42.46337],"type":"Point"}
}
