{
  "type": "Feature",
  "properties": {
    "iso:country":"US",
    "sg:address":"106 Broad St",
    "sg:city":"Lynn",
    "sg:classifiers":[
        {
            "category":"Education",
            "subcategory":"School",
            "type":"Public Place"
        }
    ],
    "sg:phone":"+1 781 477 0312",
    "sg:postcode":"01902",
    "sg:province":"MA",
    "wof:name":"Lynn Community Charter School",
    "wof:placetype":"venue"
},
  "geometry": {"coordinates":[-70.93931499999999,42.46337],"type":"Point"}
}