{
  "type": "Feature",
  "properties": {
    "iso:country":"US",
    "sg:address":"263 Grafton St",
    "sg:city":"Worcester",
    "sg:classifiers":[
        {
            "category":"Bagels",
            "type":"Food & Drink"
        },
        {
            "category":"Coffee & Tea",
            "type":"Food & Drink"
        },
        {
            "category":"Food & Beverages",
            "subcategory":"Bakery",
            "type":"Retail Goods"
        },
        {
            "category":"Bakery",
            "type":"Food & Drink"
        },
        {
            "category":"Donuts",
            "type":"Food & Drink"
        }
    ],
    "sg:menulink":"http://www.allmenus.com/ma/worcester/143571-dunkin-donuts/menu/",
    "sg:phone":"+1 508 754 0541",
    "sg:postcode":"01604",
    "sg:province":"MA",
    "sg:tags":[
        "coffee",
        "diner",
        "tea",
        "bakery",
        "bagel",
        "american",
        "pastry"
    ],
    "wof:name":"Dunkin' Donuts",
    "wof:placetype":"venue"
},
  "geometry": {"coordinates":[-71.788546,42.256291],"type":"Point"}
}