{
  "type": "Feature",
  "properties": {
    "addr:full": "310 S Main St Attleboro MA 02703",
    "addr:housenumber": "310",
    "addr:postcode": "02703",
    "addr:street": "S Main St",
    "iso:country": "US",
    "ovtr:label": "Claudino's Auto Repair, 310 S Main St Attleboro MA US",
    "ovtr:similarity": 3.1127309799194336,
    "sg:address": "310 S Main St",
    "sg:city": "Attleboro",
    "sg:classifiers": [
      {
        "category": "Recreation",
        "subcategory": "Boat Charter",
        "type": "Entertainment"
      },
      {
        "category": "Autos \u0026 Motor Vehicles",
        "subcategory": "Auto Supplies",
        "type": "Retail Goods"
      },
      {
        "category": "Retail",
        "subcategory": "Auto Repair",
        "type": "Services"
      }
    ],
    "sg:phone": "+1 508 226 8545",
    "sg:postcode": "02703",
    "sg:province": "MA",
    "sg:tags": [
      "boating",
      "part",
      "automobile",
      "accessory"
    ],
    "wof:name": "Claudino Auto Repair",
    "wof:placetype": "venue"
  },
  "geometry": {"coordinates":[-71.284599,41.928799],"type":"Point"}
}
