{
  "type": "Feature",
  "properties": {
    "iso:country":"US",
    "sg:address":"15 Sleeper St",
    "sg:city":"Boston",
    "sg:classifiers":[
        {
            "category":"Professional",
            "subcategory":"Management & Consulting",
            "type":"Services"
        }
    ],
    "sg:phone":"+1 617 451 1963",
    "sg:postcode":"02210",
    "sg:province":"MA",
    "sg:tags":[
        "consultant",
        "business"
    ],
    "wof:name":"Can AM Consultants Inc",
    "wof:placetype":"venue"
},
  "geometry": {"coordinates":[-71.049859,42.351251],"type":"Point"}
}