{
  "type": "Feature",
  "properties": {
    "addr:full": "253 W Acton Rd Stow MA 01775",
    "addr:housenumber": "253",
    "addr:postcode": "01775",
    "addr:street": "W Acton Rd",
    "iso:country": "US",
    "sg:address": "253 W Acton Rd",
    "sg:city": "Stow",
    "sg:classifiers": [
      {
        "category": "Retail",
        "subcategory": "Repair Shop",
        "type": "Services"
      }
    ],
    "sg:phone": "+1 978 897 5519",
    "sg:postcode": "01775",
    "sg:province": "MA",
    "wof:name": "A Cavossa Locksmithing",
    "wof:placetype": "venue"
  },
  "geometry": {"coordinates":[-71.492582,42.454616],"type":"Point"}
}
