{
  "type": "Feature",
  "properties": {
    "addr:full":"8 Beacon St Fl 4 Boston MA 02108",
    "addr:housenumber":"8;4",
    "addr:postcode":"02108",
    "addr:street":"Beacon St",
    "iso:country":"US",
    "sg:address":"8 Beacon St Fl 4",
    "sg:city":"Boston",
    "sg:classifiers":[
        {
            "category":"Organizations",
            "subcategory":"Political Organization",
            "type":"Services"
        }
    ],
    "sg:phone":"+1 617 723 6866",
    "sg:postcode":"02108",
    "sg:province":"MA",
    "sg:website":"http://www.n2nma.org",
    "wof:name":"Neighbor To Neighbor",
    "wof:placetype":"venue"
},
  "geometry": {"coordinates":[-71.061493,42.358238],"type":"Point"}
}