{
  "type": "Feature",
  "properties": {
    "iso:country":"US",
    "sg:address":"20 Hampshire St",
    "sg:city":"Cambridge",
    "sg:classifiers":[
        {
            "category":"Professional",
            "type":"Services"
        }
    ],
    "sg:phone":"+1 617 475 2347",
    "sg:postcode":"02139",
    "sg:province":"MA",
    "sg:tags":[
        "establishment"
    ],
    "wof:name":"Archemix",
    "wof:placetype":"venue"
},
  "geometry": {"coordinates":[-71.09105700000001,42.365525],"type":"Point"}
}