{
  "type": "Feature",
  "properties": {
    "addr:full": "20 Hampshire St Cambridge MA 02139",
    "addr:housenumber": "20",
    "addr:postcode": "02139",
    "addr:street": "Hampshire St",
    "iso:country": "US",
    "sg:address": "20 Hampshire St",
    "sg:city": "Cambridge",
    "sg:classifiers": [
      {
        "category": "Professional",
        "type": "Services"
      }
    ],
    "sg:phone": "+1 617 475 2347",
    "sg:postcode": "02139",
    "sg:province": "MA",
    "sg:tags": [
      "establishment"
    ],
    "wof:name": "Archemix",
    "wof:placetype": "venue"
  },
  "geometry": {"coordinates":[-71.091057,42.365525],"type":"Point"}
}
