{
  "type": "Feature",
  "properties": {
    "addr:full":"60 Marion Rd Mattapoisett MA 02739",
    "addr:housenumber":"60",
    "addr:postcode":"02739",
    "addr:street":"Marion Rd",
    "iso:country":"US",
    "sg:address":"60 Marion Rd",
    "sg:city":"Mattapoisett",
    "sg:classifiers":[
        {
            "category":"Shopping",
            "subcategory":"Used Merchandise",
            "type":"Retail Goods"
        }
    ],
    "sg:phone":"+1 508 758 3111",
    "sg:postcode":"02739",
    "sg:province":"MA",
    "sg:tags":[
        "book",
        "rare",
        "dealer"
    ],
    "wof:name":"Book N'Board",
    "wof:placetype":"venue"
},
  "geometry": {"coordinates":[-70.785241,41.664531],"type":"Point"}
}