{
  "type": "Feature",
  "properties": {
    "iso:country":"US",
    "sg:address":"231 Newbury St",
    "sg:city":"Boston",
    "sg:classifiers":[
        {
            "category":"Personal",
            "subcategory":"Beauty Salon",
            "type":"Services"
        }
    ],
    "sg:phone":"+1 617 236 1727",
    "sg:postcode":"02116",
    "sg:province":"MA",
    "wof:name":"Salonpini & Co",
    "wof:placetype":"venue"
},
  "geometry": {"coordinates":[-71.08053099999999,42.350289],"type":"Point"}
}