{
  "type": "Feature",
  "properties": {
    "iso:country":"US",
    "sg:address":"10 Putnam St",
    "sg:city":"Boston",
    "sg:classifiers":[
        {
            "category":"Organizations",
            "subcategory":"Religious Organization",
            "type":"Services"
        }
    ],
    "sg:phone":"+1 617 318 6010",
    "sg:postcode":"02128",
    "sg:province":"MA",
    "wof:name":"First Church In Roxbury",
    "wof:placetype":"venue"
},
  "geometry": {"coordinates":[-71.033501,42.382198],"type":"Point"}
}