{
  "type": "Feature",
  "properties": {
    "addr:full":"32 Delano Rd Truro MA 02660",
    "addr:housenumber":"32",
    "addr:postcode":"02660",
    "addr:street":"Delano Rd",
    "iso:country":"US",
    "sg:address":"32 Delano Rd",
    "sg:city":"Truro",
    "sg:classifiers":[
        {
            "category":"Government",
            "subcategory":"Office",
            "type":"Public Place"
        }
    ],
    "sg:phone":"+1 508 487 3262",
    "sg:postcode":"02660",
    "sg:province":"MA",
    "sg:tags":[
        "federal"
    ],
    "wof:name":"US Interior Dept",
    "wof:placetype":"venue"
},
  "geometry": {"coordinates":[-70.168098,41.731069],"type":"Point"}
}