{
  "type": "Feature",
  "properties": {
    "addr:full": "56 Commercial Wharf N Boston MA 02110",
    "addr:housenumber": "56",
    "addr:postcode": "02110",
    "addr:street": "Commercial Wharf N",
    "iso:country": "US",
    "sg:address": "56 Commercial Wharf N",
    "sg:city": "Boston",
    "sg:classifiers": [
      {
        "category": "Mining \u0026 Drilling",
        "type": "Manufacturing \u0026 Wholesale Goods"
      }
    ],
    "sg:phone": "+1 617 248 9966",
    "sg:postcode": "02110",
    "sg:province": "MA",
    "sg:tags": [
      "geologist"
    ],
    "wof:name": "Sailors For The Sea, Inc.",
    "wof:placetype": "venue"
  },
  "geometry": {"coordinates":[-71.051546,42.362952],"type":"Point"}
}
