{
  "type": "Feature",
  "properties": {
    "iso:country":"US",
    "sg:address":"56 Commercial Wharf N",
    "sg:city":"Boston",
    "sg:classifiers":[
        {
            "category":"Mining & Drilling",
            "type":"Manufacturing & Wholesale Goods"
        }
    ],
    "sg:phone":"+1 617 248 9966",
    "sg:postcode":"02110",
    "sg:province":"MA",
    "sg:tags":[
        "geologist"
    ],
    "wof:name":"Sailors For The Sea, Inc.",
    "wof:placetype":"venue"
},
  "geometry": {"coordinates":[-71.051546,42.362952],"type":"Point"}
}