{
  "type": "Feature",
  "properties": {
    "iso:country":"US",
    "sg:address":"1256 Park St Ste 203",
    "sg:city":"Stoughton",
    "sg:classifiers":[
        {
            "category":"Health Services",
            "subcategory":"Dentist",
            "type":"Services"
        }
    ],
    "sg:phone":"+1 781 341 5300",
    "sg:postcode":"02072",
    "sg:province":"MA",
    "sg:tags":[
        "dentists-orthodontists"
    ],
    "wof:name":"Hoyo, Jose M",
    "wof:placetype":"venue"
},
  "geometry": {"coordinates":[-71.068415,42.103844],"type":"Point"}
}