{
  "type": "Feature",
  "properties": {
    "iso:country":"US",
    "sg:address":"28 Main St",
    "sg:city":"Northborough",
    "sg:classifiers":[
        {
            "category":"Professional",
            "subcategory":"Lawyer & Legal Services",
            "type":"Services"
        }
    ],
    "sg:phone":"+1 508 351 6656",
    "sg:postcode":"01532",
    "sg:province":"MA",
    "sg:tags":[
        "attorney"
    ],
    "wof:name":"James R Davis Esquire PC",
    "wof:placetype":"venue"
},
  "geometry": {"coordinates":[-71.639286,42.319661],"type":"Point"}
}