{
  "type": "Feature",
  "properties": {
    "addr:full":"11 Walnut Dr Fayville MA 01745",
    "addr:housenumber":"11",
    "addr:postcode":"01745",
    "addr:street":"Walnut Dr",
    "iso:country":"US",
    "sg:address":"11 Walnut Dr",
    "sg:city":"Fayville",
    "sg:classifiers":[
        {
            "category":"Manufacturing",
            "subcategory":"Tools & Machinery",
            "type":"Manufacturing & Wholesale Goods"
        }
    ],
    "sg:phone":"+1 508 229 8088",
    "sg:postcode":"01745",
    "sg:province":"MA",
    "sg:tags":[
        "building",
        "equipment",
        "construction"
    ],
    "wof:name":"Metrowest Contracting Associates Inc",
    "wof:placetype":"venue"
},
  "geometry": {"coordinates":[-71.501986,42.288748],"type":"Point"}
}