{
  "type": "Feature",
  "properties": {
    "addr:full":"575 N Washington St North Attleboro MA 02760",
    "addr:housenumber":"575",
    "addr:postcode":"02760",
    "addr:street":"N Washington St",
    "iso:country":"US",
    "sg:address":"575 N Washington St",
    "sg:city":"North Attleboro",
    "sg:classifiers":[
        {
            "category":"Wholesale",
            "subcategory":"Medical Equipment & Supplies",
            "type":"Manufacturing & Wholesale Goods"
        }
    ],
    "sg:phone":"+1 508 699 2090",
    "sg:postcode":"02760",
    "sg:province":"MA",
    "sg:tags":[
        "hospital"
    ],
    "wof:name":"Advantage Home Medical Equip",
    "wof:placetype":"venue"
},
  "geometry": {"coordinates":[-71.329905,41.99758],"type":"Point"}
}