{
  "type": "Feature",
  "properties": {
    "iso:country":"US",
    "sg:address":"586 Strawberry Hill Rd",
    "sg:city":"Centerville",
    "sg:classifiers":[
        {
            "category":"Professional",
            "subcategory":"Management & Consulting",
            "type":"Services"
        },
        {
            "category":"Banks & Credit Unions",
            "subcategory":"Investment Brokerage",
            "type":"Services"
        },
        {
            "category":"Banks & Credit Unions",
            "subcategory":"Bank",
            "type":"Services"
        },
        {
            "category":"Banks & Credit Unions",
            "subcategory":"Financial Services",
            "type":"Services"
        }
    ],
    "sg:phone":"+1 508 771 2300",
    "sg:postcode":"02632",
    "sg:province":"MA",
    "sg:tags":[
        "financing",
        "consultant",
        "broker",
        "agent",
        "planning",
        "transfer",
        "bond",
        "stock"
    ],
    "wof:name":"Wachovia Offices",
    "wof:placetype":"venue"
},
  "geometry": {"coordinates":[-70.326629,41.654725],"type":"Point"}
}