{
  "type": "Feature",
  "properties": {
    "iso:country":"US",
    "sg:address":"60 Pleasant St",
    "sg:city":"Newburyport",
    "sg:classifiers":[
        {
            "category":"Government",
            "subcategory":"Office",
            "type":"Public Place"
        }
    ],
    "sg:phone":"+1   ",
    "sg:postcode":"01950",
    "sg:province":"MA",
    "wof:name":"Newburyport Mayors Office",
    "wof:placetype":"venue"
},
  "geometry": {"coordinates":[-70.872557,42.810917],"type":"Point"}
}