{
  "type": "Feature",
  "properties": {
    "addr:full":"10 Summer St Fitchburg MA 01420",
    "addr:housenumber":"10",
    "addr:postcode":"01420",
    "addr:street":"Summer St",
    "iso:country":"US",
    "sg:address":"10 Summer St",
    "sg:city":"Fitchburg",
    "sg:classifiers":[
        {
            "category":"Shopping",
            "type":"Retail Goods"
        },
        {
            "category":"Wholesale",
            "subcategory":"Electrical",
            "type":"Manufacturing & Wholesale Goods"
        }
    ],
    "sg:phone":"+1 978 342 8047",
    "sg:postcode":"01420",
    "sg:province":"MA",
    "sg:tags":[
        "communication",
        "system",
        "accessory",
        "equipment",
        "2",
        "radio"
    ],
    "wof:name":"F E Communications",
    "wof:placetype":"venue"
},
  "geometry": {"coordinates":[-71.78998799999999,42.581449],"type":"Point"}
}