{
  "type": "Feature",
  "properties": {
    "addr:full":"528 Forest Rd West Yarmouth MA 02673",
    "addr:housenumber":"528",
    "addr:postcode":"02673",
    "addr:street":"Forest Rd",
    "iso:country":"US",
    "sg:address":"528 Forest Rd",
    "sg:city":"West Yarmouth",
    "sg:classifiers":[
        {
            "category":"Restaurant",
            "type":"Food & Drink"
        }
    ],
    "sg:phone":"+1 508 394 7606",
    "sg:postcode":"02673",
    "sg:province":"MA",
    "sg:tags":[
        "banquet",
        "rooms"
    ],
    "wof:name":"Yarmouth Senior Ctr Comptr",
    "wof:placetype":"venue"
},
  "geometry": {"coordinates":[-70.218007,41.682045],"type":"Point"}
}