{
  "type": "Feature",
  "properties": {
    "addr:full": "61 Acorn Dr West Barnstable MA 02668",
    "addr:housenumber": "61",
    "addr:postcode": "02668",
    "addr:street": "Acorn Dr",
    "iso:country": "US",
    "sg:address": "61 Acorn Dr",
    "sg:city": "West Barnstable",
    "sg:classifiers": [
      {
        "category": "Shopping",
        "subcategory": "Gifts \u0026 Souvenirs",
        "type": "Retail Goods"
      }
    ],
    "sg:phone": "+1 508 375 0038",
    "sg:postcode": "02668",
    "sg:province": "MA",
    "sg:tags": [
      "shop"
    ],
    "wof:name": "Humanity",
    "wof:placetype": "venue"
  },
  "geometry": {"coordinates":[-70.347694,41.693736],"type":"Point"}
}
