{
  "type": "Feature",
  "properties": {
    "addr:full": "36 Dunham Rd Billerica MA 01821",
    "addr:housenumber": "36",
    "addr:postcode": "01821",
    "addr:street": "Dunham Rd",
    "iso:country": "US",
    "sg:address": "36 Dunham Rd",
    "sg:city": "Billerica",
    "sg:classifiers": [
      {
        "category": "Building \u0026 Trades",
        "subcategory": "Landscaping Services",
        "type": "Services"
      }
    ],
    "sg:phone": "+1 978 670 2837",
    "sg:postcode": "01821",
    "sg:province": "MA",
    "sg:tags": [
      "landscape",
      "contractor"
    ],
    "wof:name": "Eastern Brothers Landscaping",
    "wof:placetype": "venue"
  },
  "geometry": {"coordinates":[-71.229565,42.521789],"type":"Point"}
}
