{
  "type": "Feature",
  "properties": {
    "addr:full": "12 Villanova Dr Westford MA 01886",
    "addr:housenumber": "12",
    "addr:postcode": "01886",
    "addr:street": "Villanova Dr",
    "iso:country": "US",
    "sg:address": "12 Villanova Dr",
    "sg:city": "Westford",
    "sg:classifiers": [
      {
        "category": "Professional",
        "subcategory": "Business Services",
        "type": "Services"
      }
    ],
    "sg:phone": "+1   ",
    "sg:postcode": "01886",
    "sg:province": "MA",
    "wof:name": "Atlas Technology Inc",
    "wof:placetype": "venue"
  },
  "geometry": {"coordinates":[-71.430299,42.602925],"type":"Point"}
}
