{
  "type": "Feature",
  "properties": {
    "addr:full": "131 Spring St Everett MA 02149",
    "addr:housenumber": "131",
    "addr:postcode": "02149",
    "addr:street": "Spring St",
    "iso:country": "US",
    "sg:address": "131 Spring St",
    "sg:city": "Everett",
    "sg:classifiers": [
      {
        "category": "Manufacturing",
        "subcategory": "Food",
        "type": "Manufacturing \u0026 Wholesale Goods"
      }
    ],
    "sg:phone": "+1 617 389 4700",
    "sg:postcode": "02149",
    "sg:province": "MA",
    "sg:tags": [
      "ice"
    ],
    "wof:name": "Tube Ice Mfg",
    "wof:placetype": "venue"
  },
  "geometry": {"coordinates":[-71.052836,42.400625],"type":"Point"}
}
