{
  "type": "Feature",
  "properties": {
    "addr:full":"440 Commercial St Boston MA 02109",
    "addr:housenumber":"440",
    "addr:postcode":"02109",
    "addr:street":"Commercial St",
    "iso:country":"US",
    "sg:address":"440 Commercial St",
    "sg:city":"Boston",
    "sg:classifiers":[
        {
            "category":"Utilities",
            "subcategory":"Electric",
            "type":"Services"
        }
    ],
    "sg:phone":"+1 781 453 1114",
    "sg:postcode":"02109",
    "sg:province":"MA",
    "sg:tags":[
        "company"
    ],
    "wof:name":"Pinpoint Power",
    "wof:placetype":"venue"
},
  "geometry": {"coordinates":[-71.05266,42.367162],"type":"Point"}
}