{
  "type": "Feature",
  "properties": {
    "iso:country":"US",
    "sg:address":"1 Holts Ave",
    "sg:city":"Somerville",
    "sg:classifiers":[
        {
            "category":"Banks & Credit Unions",
            "subcategory":"Investment Brokerage",
            "type":"Services"
        }
    ],
    "sg:phone":"+1 781 239 0635",
    "sg:postcode":"02143",
    "sg:province":"MA",
    "sg:tags":[
        "investing"
    ],
    "wof:name":"Lmc Investments Inc",
    "wof:placetype":"venue"
},
  "geometry": {"coordinates":[-71.099013,42.375321],"type":"Point"}
}