{
  "type": "Feature",
  "properties": {
    "iso:country":"US",
    "sg:address":"34 Mason St",
    "sg:city":"Brockton",
    "sg:classifiers":[
        {
            "category":"Building & Trades",
            "subcategory":"Construction",
            "type":"Services"
        }
    ],
    "sg:phone":"+1   ",
    "sg:postcode":"02302",
    "sg:province":"MA",
    "sg:tags":[
        "house"
    ],
    "wof:name":"Centeio Home Repair",
    "wof:placetype":"venue"
},
  "geometry": {"coordinates":[-71.005875,42.08483],"type":"Point"}
}