{
  "type": "Feature",
  "properties": {
    "addr:full":"159 Thornton Rd Needham MA 02492",
    "addr:housenumber":"159",
    "addr:postcode":"02492",
    "addr:street":"Thornton Rd",
    "iso:country":"US",
    "sg:address":"159 Thornton Rd",
    "sg:city":"Needham",
    "sg:classifiers":[
        {
            "category":"Building & Trades",
            "subcategory":"Construction",
            "type":"Services"
        }
    ],
    "sg:phone":"+1 781 444 3569",
    "sg:postcode":"02492",
    "sg:province":"MA",
    "sg:tags":[
        "roofing",
        "contractor"
    ],
    "wof:name":"Rogers Roofing",
    "wof:placetype":"venue"
},
  "geometry": {"coordinates":[-71.21492499999999,42.282305],"type":"Point"}
}