{
  "type": "Feature",
  "properties": {
    "addr:full": "1459 River St Hyde Park MA 02136",
    "addr:housenumber": "1459",
    "addr:postcode": "02136",
    "addr:street": "River St",
    "iso:country": "US",
    "sg:address": "1459 River St",
    "sg:city": "Hyde Park",
    "sg:classifiers": [
      {
        "category": "Personal",
        "subcategory": "Beauty Salon",
        "type": "Services"
      }
    ],
    "sg:phone": "+1 617 361 3900",
    "sg:postcode": "02136",
    "sg:province": "MA",
    "wof:name": "Royal Tree Hair Care \u0026 Barber",
    "wof:placetype": "venue"
  },
  "geometry": {"coordinates":[-71.130888,42.251627],"type":"Point"}
}
