{
  "type": "Feature",
  "properties": {
    "addr:full": "181 Canal St Lawrence MA 01840",
    "addr:housenumber": "181",
    "addr:postcode": "01840",
    "addr:street": "Canal St",
    "iso:country": "US",
    "sg:address": "181 Canal St",
    "sg:city": "Lawrence",
    "sg:classifiers": [
      {
        "category": "Professional",
        "subcategory": "Computer Services",
        "type": "Services"
      }
    ],
    "sg:phone": "+1 978 794 4744",
    "sg:postcode": "01840",
    "sg:province": "MA",
    "sg:tags": [
      "internet"
    ],
    "sg:website": "www.latinosen.com",
    "wof:name": "MVE Network",
    "wof:placetype": "venue"
  },
  "geometry": {"coordinates":[-71.154697,42.70655],"type":"Point"}
}
