{
  "type": "Feature",
  "properties": {
    "iso:country":"US",
    "sg:address":"350 Lincoln St",
    "sg:city":"Hingham",
    "sg:classifiers":[
        {
            "category":"Professional",
            "subcategory":"Lawyer & Legal Services",
            "type":"Services"
        }
    ],
    "sg:phone":"+1 781 749 7377",
    "sg:postcode":"02043",
    "sg:province":"MA",
    "sg:tags":[
        "attorney"
    ],
    "wof:name":"Christine M Farrell",
    "wof:placetype":"venue"
},
  "geometry": {"coordinates":[-70.921544,42.249078],"type":"Point"}
}