{
  "type": "Feature",
  "properties": {
    "addr:full":"228 Everett Ave Chelsea MA 02150",
    "addr:housenumber":"228",
    "addr:postcode":"02150",
    "addr:street":"Everett Ave",
    "iso:country":"US",
    "sg:address":"228 Everett Ave",
    "sg:city":"Chelsea",
    "sg:classifiers":[
        {
            "category":"Retail",
            "subcategory":"Laundry & Dry Cleaning",
            "type":"Services"
        }
    ],
    "sg:phone":"+1 617 889 4453",
    "sg:postcode":"02150",
    "sg:province":"MA",
    "wof:name":"Dryco Cleaning Company",
    "wof:placetype":"venue"
},
  "geometry": {"coordinates":[-71.0408,42.398],"type":"Point"}
}