{
  "type": "Feature",
  "properties": {
    "addr:full": "5 Medford Street Arlington MA 02474",
    "addr:housenumber": "5",
    "addr:postcode": "02474",
    "addr:street": "Medford Street",
    "iso:country": "US",
    "sg:address": "5 Medford Street",
    "sg:city": "Arlington",
    "sg:classifiers": [
      {
        "category": "Shopping",
        "subcategory": "Baby Store",
        "type": "Retail Goods"
      },
      {
        "category": "Shopping",
        "subcategory": "Clothing, Apparel, \u0026 Fashions",
        "type": "Retail Goods"
      },
      {
        "category": "Wholesale",
        "subcategory": "Apparel",
        "type": "Manufacturing \u0026 Wholesale Goods"
      }
    ],
    "sg:phone": "+1 781 483 3566",
    "sg:postcode": "02474",
    "sg:province": "MA",
    "sg:tags": [
      "wear-wholesale",
      "infant",
      "gear",
      "women's",
      "children's",
      "wear",
      "girls'",
      "manufacturer",
      "clothing",
      "furniture"
    ],
    "sg:website": "www.wildchildgear.com",
    "wof:name": "Wild Child",
    "wof:placetype": "venue"
  },
  "geometry": {"coordinates":[-71.150959,42.41488],"type":"Point"}
}
