{
  "type": "Feature",
  "properties": {
    "iso:country":"US",
    "sg:address":"218 Somerville Ave",
    "sg:city":"Somerville",
    "sg:classifiers":[
        {
            "category":"Building & Trades",
            "subcategory":"Construction",
            "type":"Services"
        }
    ],
    "sg:phone":"+1   ",
    "sg:postcode":"02143",
    "sg:province":"MA",
    "sg:tags":[
        "hanging",
        "contractor"
    ],
    "wof:name":"Santana Painting Co",
    "wof:placetype":"venue"
},
  "geometry": {"coordinates":[-71.09152899999999,42.378028],"type":"Point"}
}