{
  "type": "Feature",
  "properties": {
    "addr:full": "218 Somerville Ave Somerville MA 02143",
    "addr:housenumber": "218",
    "addr:postcode": "02143",
    "addr:street": "Somerville Ave",
    "iso:country": "US",
    "sg:address": "218 Somerville Ave",
    "sg:city": "Somerville",
    "sg:classifiers": [
      {
        "category": "Building \u0026 Trades",
        "subcategory": "Construction",
        "type": "Services"
      }
    ],
    "sg:phone": "+1   ",
    "sg:postcode": "02143",
    "sg:province": "MA",
    "sg:tags": [
      "hanging",
      "contractor"
    ],
    "wof:name": "Santana Painting Co",
    "wof:placetype": "venue"
  },
  "geometry": {"coordinates":[-71.091529,42.378028],"type":"Point"}
}
