{
  "type": "Feature",
  "properties": {
    "addr:full":"677 Timpany Blvd Gardner MA 01440",
    "addr:housenumber":"677",
    "addr:postcode":"01440",
    "addr:street":"Timpany Blvd",
    "iso:country":"US",
    "sg:address":"677 Timpany Blvd",
    "sg:city":"Gardner",
    "sg:classifiers":[
        {
            "category":"Education",
            "subcategory":"Vocational School",
            "type":"Public Place"
        }
    ],
    "sg:phone":"+1 978 630 2749",
    "sg:postcode":"01440",
    "sg:province":"MA",
    "sg:tags":[
        "secretarial"
    ],
    "wof:name":"H & R Block Tax Svc",
    "wof:placetype":"venue"
},
  "geometry": {"coordinates":[-71.991882,42.550315],"type":"Point"}
}