{
  "type": "Feature",
  "properties": {
    "iso:country":"US",
    "sg:address":"109 Main St",
    "sg:city":"Marlborough",
    "sg:classifiers":[
        {
            "category":"Arts & Performance",
            "subcategory":"Theater",
            "type":"Entertainment"
        }
    ],
    "sg:phone":"+1 508 480 0335",
    "sg:postcode":"01752",
    "sg:province":"MA",
    "sg:tags":[
        "live",
        "music"
    ],
    "wof:name":"Advantage Agency",
    "wof:placetype":"venue"
},
  "geometry": {"coordinates":[-71.54568999999999,42.347196],"type":"Point"}
}