{
  "type": "Feature",
  "properties": {
    "addr:full": "109 Main St Marlborough MA 01752",
    "addr:housenumber": "109",
    "addr:postcode": "01752",
    "addr:street": "Main St",
    "iso:country": "US",
    "sg:address": "109 Main St",
    "sg:city": "Marlborough",
    "sg:classifiers": [
      {
        "category": "Arts \u0026 Performance",
        "subcategory": "Theater",
        "type": "Entertainment"
      }
    ],
    "sg:phone": "+1 508 480 0335",
    "sg:postcode": "01752",
    "sg:province": "MA",
    "sg:tags": [
      "live",
      "music"
    ],
    "wof:name": "Advantage Agency",
    "wof:placetype": "venue"
  },
  "geometry": {"coordinates":[-71.54569,42.347196],"type":"Point"}
}
