{
  "type": "Feature",
  "properties": {
    "addr:full": "44 Hammond St Clinton MA 01510",
    "addr:housenumber": "44",
    "addr:postcode": "01510",
    "addr:street": "Hammond St",
    "iso:country": "US",
    "sg:address": "44 Hammond St",
    "sg:city": "Clinton",
    "sg:classifiers": [
      {
        "category": "Social Services",
        "subcategory": "Child Care",
        "type": "Services"
      }
    ],
    "sg:phone": "+1 978 365 3162",
    "sg:postcode": "01510",
    "sg:province": "MA",
    "sg:tags": [
      "nursery",
      "day"
    ],
    "wof:name": "Storybook Designs Incorporated",
    "wof:placetype": "venue"
  },
  "geometry": {"coordinates":[-71.678926,42.420802],"type":"Point"}
}
