{
  "type": "Feature",
  "properties": {
    "iso:country":"US",
    "sg:address":"44 Hammond St",
    "sg:city":"Clinton",
    "sg:classifiers":[
        {
            "category":"Social Services",
            "subcategory":"Child Care",
            "type":"Services"
        }
    ],
    "sg:phone":"+1 978 365 3162",
    "sg:postcode":"01510",
    "sg:province":"MA",
    "sg:tags":[
        "nursery",
        "day"
    ],
    "wof:name":"Storybook Designs Incorporated",
    "wof:placetype":"venue"
},
  "geometry": {"coordinates":[-71.678926,42.420802],"type":"Point"}
}