{
  "type": "Feature",
  "properties": {
    "iso:country":"US",
    "sg:address":"35 Ship Ave",
    "sg:city":"Medford",
    "sg:classifiers":[
        {
            "category":"Retail",
            "subcategory":"Repair Shop",
            "type":"Services"
        }
    ],
    "sg:phone":"+1   ",
    "sg:postcode":"02155",
    "sg:province":"MA",
    "sg:tags":[
        "electrical"
    ],
    "wof:name":"Richard Rockford",
    "wof:placetype":"venue"
},
  "geometry": {"coordinates":[-71.099917,42.413616],"type":"Point"}
}