{
  "type": "Feature",
  "properties": {
    "addr:full":"1047 Falmouth Rd Hyannis MA 02601",
    "addr:housenumber":"1047",
    "addr:postcode":"02601",
    "addr:street":"Falmouth Rd",
    "iso:country":"US",
    "sg:address":"1047 Falmouth Rd",
    "sg:city":"Hyannis",
    "sg:classifiers":[
        {
            "category":"Retail",
            "subcategory":"Animal Services",
            "type":"Services"
        }
    ],
    "sg:phone":"+1 508 771 9247",
    "sg:postcode":"02601",
    "sg:province":"MA",
    "sg:tags":[
        "pet"
    ],
    "sg:website":"www.wagthisway.net",
    "wof:name":"Wag This Way",
    "wof:placetype":"venue"
},
  "geometry": {"coordinates":[-70.32461000000001,41.659345],"type":"Point"}
}