{
  "type": "Feature",
  "properties": {
    "addr:full": "46 Lowell Junction Rd Andover MA 01810",
    "addr:housenumber": "46",
    "addr:postcode": "01810",
    "addr:street": "Lowell Junction Rd",
    "iso:country": "US",
    "sg:address": "46 Lowell Junction Rd",
    "sg:city": "Andover",
    "sg:classifiers": [
      {
        "category": "Wholesale",
        "subcategory": "Scrap",
        "type": "Manufacturing \u0026 Wholesale Goods"
      }
    ],
    "sg:phone": "+1 978 475 8153",
    "sg:postcode": "01810",
    "sg:province": "MA",
    "sg:tags": [
      "recycling",
      "center"
    ],
    "sg:website": "www.deloury.com",
    "wof:name": "Agretech Corp",
    "wof:placetype": "venue"
  },
  "geometry": {"coordinates":[-71.16319,42.61579],"type":"Point"}
}
