{
  "type": "Feature",
  "properties": {
    "iso:country":"US",
    "sg:address":"23 4th Ave",
    "sg:city":"Burlington",
    "sg:classifiers":[
        {
            "category":"Communications",
            "type":"Services"
        }
    ],
    "sg:phone":"+1 781 359 9500",
    "sg:postcode":"01803",
    "sg:province":"MA",
    "sg:website":"www.mayflowercom.com",
    "wof:name":"Mayflower Communications Co",
    "wof:placetype":"venue"
},
  "geometry": {"coordinates":[-71.224705,42.49124],"type":"Point"}
}