{
  "type": "Feature",
  "properties": {
    "addr:full":"854 Main St Worcester MA 01610",
    "addr:housenumber":"854",
    "addr:postcode":"01610",
    "addr:street":"Main St",
    "iso:country":"US",
    "sg:address":"854 Main St",
    "sg:city":"Worcester",
    "sg:classifiers":[
        {
            "category":"Shopping",
            "subcategory":"Jewelry",
            "type":"Retail Goods"
        },
        {
            "category":"Manufacturing",
            "subcategory":"Jewelry",
            "type":"Manufacturing & Wholesale Goods"
        }
    ],
    "sg:phone":"+1 508 754 8992",
    "sg:postcode":"01610",
    "sg:province":"MA",
    "sg:tags":[
        "designer",
        "jeweler"
    ],
    "wof:name":"Mai Ngoc Jewelry",
    "wof:placetype":"venue"
},
  "geometry": {"coordinates":[-71.814899,42.254244],"type":"Point"}
}