{
  "type": "Feature",
  "properties": {
    "addr:full": "895 Randolph Ave Milton MA 02186",
    "addr:housenumber": "895",
    "addr:postcode": "02186",
    "addr:street": "Randolph Ave",
    "iso:country": "US",
    "sg:address": "895 Randolph Ave",
    "sg:city": "Milton",
    "sg:classifiers": [
      {
        "category": "Education",
        "subcategory": "Junior College",
        "type": "Public Place"
      },
      {
        "category": "Shopping",
        "subcategory": "Hobbies, Toys, \u0026 Games",
        "type": "Retail Goods"
      }
    ],
    "sg:phone": "+1 617 696 6666",
    "sg:postcode": "02186",
    "sg:province": "MA",
    "sg:tags": [
      "house",
      "doll",
      "accessory"
    ],
    "wof:name": "The Mann Gallery",
    "wof:placetype": "venue"
  },
  "geometry": {"coordinates":[-71.069572,42.23856],"type":"Point"}
}
