{
  "type": "Feature",
  "properties": {
    "addr:full":"29 Pumpkin Hollow Rd Great Barrington MA 01230",
    "addr:housenumber":"29",
    "addr:postcode":"01230",
    "addr:street":"Pumpkin Hollow Rd",
    "iso:country":"US",
    "sg:address":"29 Pumpkin Hollow Rd",
    "sg:city":"Great Barrington",
    "sg:classifiers":[
        {
            "category":"Home & Garden",
            "subcategory":"Carpets & Floor Coverings",
            "type":"Retail Goods"
        }
    ],
    "sg:phone":"+1 413 528 9000",
    "sg:postcode":"01230",
    "sg:province":"MA",
    "sg:tags":[
        "material"
    ],
    "sg:website":"www.greenriverlumber.com",
    "wof:name":"Green River Lumber Co",
    "wof:placetype":"venue"
},
  "geometry": {"coordinates":[-73.414278,42.193808],"type":"Point"}
}