{
  "type": "Feature",
  "properties": {
    "addr:full":"167 Washington St Norwell MA 02061",
    "addr:housenumber":"167",
    "addr:postcode":"02061",
    "addr:street":"Washington St",
    "iso:country":"US",
    "sg:address":"167 Washington St",
    "sg:city":"Norwell",
    "sg:classifiers":[
        {
            "category":"Banks & Credit Unions",
            "subcategory":"Bank",
            "type":"Services"
        }
    ],
    "sg:phone":"+1 781 871 2122",
    "sg:postcode":"02061",
    "sg:province":"MA",
    "sg:tags":[
        "loan",
        "real estate"
    ],
    "wof:name":"Allied Home Mortgage Capital",
    "wof:placetype":"venue"
},
  "geometry": {"coordinates":[-70.874551,42.168367],"type":"Point"}
}