{
  "type": "Feature",
  "properties": {
    "addr:full":"4 E Central St Franklin MA 02038",
    "addr:housenumber":"4",
    "addr:postcode":"02038",
    "addr:street":"E Central St",
    "iso:country":"US",
    "sg:address":"4 E Central St",
    "sg:city":"Franklin",
    "sg:classifiers":[
        {
            "category":"Restaurant",
            "type":"Food & Drink"
        }
    ],
    "sg:phone":"+1 508 528 4740",
    "sg:postcode":"02038",
    "sg:province":"MA",
    "sg:website":"www.the-rome.com",
    "wof:name":"Rome Restaurant",
    "wof:placetype":"venue"
},
  "geometry": {"coordinates":[-71.39685799999999,42.08246],"type":"Point"}
}