{
  "type": "Feature",
  "properties": {
    "addr:full": "37 Old Douglas Rd East Douglas MA 01516",
    "addr:housenumber": "37",
    "addr:postcode": "01516",
    "addr:street": "Old Douglas Rd",
    "iso:country": "US",
    "sg:address": "37 Old Douglas Rd",
    "sg:city": "East Douglas",
    "sg:classifiers": [
      {
        "category": "Building \u0026 Trades",
        "subcategory": "Construction",
        "type": "Services"
      }
    ],
    "sg:phone": "+1   ",
    "sg:postcode": "01516",
    "sg:province": "MA",
    "sg:tags": [
      "house"
    ],
    "wof:name": "Haire Colin Carpenter Builder",
    "wof:placetype": "venue"
  },
  "geometry": {"coordinates":[-72.181019,42.246042],"type":"Point"}
}
