{
  "type": "Feature",
  "properties": {
    "iso:country":"US",
    "sg:address":"37 Old Douglas Rd",
    "sg:city":"East Douglas",
    "sg:classifiers":[
        {
            "category":"Building & Trades",
            "subcategory":"Construction",
            "type":"Services"
        }
    ],
    "sg:phone":"+1   ",
    "sg:postcode":"01516",
    "sg:province":"MA",
    "sg:tags":[
        "house"
    ],
    "wof:name":"Haire Colin Carpenter Builder",
    "wof:placetype":"venue"
},
  "geometry": {"coordinates":[-72.18101900000001,42.246042],"type":"Point"}
}