{
  "type": "Feature",
  "properties": {
    "iso:country":"US",
    "sg:address":"49 Leach St",
    "sg:city":"Salem",
    "sg:classifiers":[
        {
            "category":"Professional",
            "subcategory":"Computer Services",
            "type":"Services"
        }
    ],
    "sg:phone":"+1 978 741 2427",
    "sg:postcode":"01970",
    "sg:province":"MA",
    "sg:tags":[
        "consultant",
        "internet"
    ],
    "wof:name":"Sbs Communicaitons Inc",
    "wof:placetype":"venue"
},
  "geometry": {"coordinates":[-70.889459,42.511667],"type":"Point"}
}