{
  "type": "Feature",
  "properties": {
    "addr:full":"24 Roosevelt Ave Dracut MA 01826",
    "addr:housenumber":"24",
    "addr:postcode":"01826",
    "addr:street":"Roosevelt Ave",
    "iso:country":"US",
    "sg:address":"24 Roosevelt Ave",
    "sg:city":"Dracut",
    "sg:classifiers":[
        {
            "category":"Restaurant",
            "type":"Food & Drink"
        }
    ],
    "sg:phone":"+1 781 246 2038",
    "sg:postcode":"01826",
    "sg:province":"MA",
    "sg:tags":[
        "sandwich"
    ],
    "wof:name":"Lakeside Cafe",
    "wof:placetype":"venue"
},
  "geometry": {"coordinates":[-71.280312,42.658827],"type":"Point"}
}