{
  "type": "Feature",
  "properties": {
    "iso:country":"US",
    "sg:address":"121 Brackett Rd",
    "sg:city":"Newton",
    "sg:classifiers":[
        {
            "category":"Professional",
            "type":"Services"
        }
    ],
    "sg:phone":"+1   ",
    "sg:postcode":"02458",
    "sg:province":"MA",
    "wof:name":"Aging Link Inc",
    "wof:placetype":"venue"
},
  "geometry": {"coordinates":[-71.1857,42.34309],"type":"Point"}
}