{
  "type": "Feature",
  "properties": {
    "addr:full": "121 Brackett Rd Newton MA 02458",
    "addr:housenumber": "121",
    "addr:postcode": "02458",
    "addr:street": "Brackett Rd",
    "iso:country": "US",
    "sg:address": "121 Brackett Rd",
    "sg:city": "Newton",
    "sg:classifiers": [
      {
        "category": "Professional",
        "type": "Services"
      }
    ],
    "sg:phone": "+1   ",
    "sg:postcode": "02458",
    "sg:province": "MA",
    "wof:name": "Aging Link Inc",
    "wof:placetype": "venue"
  },
  "geometry": {"coordinates":[-71.1857,42.34309],"type":"Point"}
}
