{
  "type": "Feature",
  "properties": {
    "addr:full": "624 Webster St Marshfield MA 02050",
    "addr:housenumber": "624",
    "addr:postcode": "02050",
    "addr:street": "Webster St",
    "iso:country": "US",
    "ovtr:label": "Green Harbor Golf Club, 624 Webster St Marshfield MA US",
    "ovtr:similarity": 2.2150230407714844,
    "sg:address": "624 Webster St",
    "sg:city": "Marshfield",
    "sg:classifiers": [
      {
        "category": "Sports \u0026 Exercise",
        "subcategory": "Golf",
        "type": "Entertainment"
      }
    ],
    "sg:phone": "+1 781 834 7303",
    "sg:postcode": "02050",
    "sg:province": "MA",
    "sg:tags": [
      "course"
    ],
    "wof:name": "Green Harbor Golf Club",
    "wof:placetype": "venue"
  },
  "geometry": {"coordinates":[-70.696268,42.083765],"type":"Point"}
}
