{
  "type": "Feature",
  "properties": {
    "iso:country":"US",
    "sg:address":"624 Webster St",
    "sg:city":"Marshfield",
    "sg:classifiers":[
        {
            "category":"Sports & Exercise",
            "subcategory":"Golf",
            "type":"Entertainment"
        }
    ],
    "sg:phone":"+1 781 834 7303",
    "sg:postcode":"02050",
    "sg:province":"MA",
    "sg:tags":[
        "course"
    ],
    "wof:name":"Green Harbor Golf Club",
    "wof:placetype":"venue"
},
  "geometry": {"coordinates":[-70.696268,42.083765],"type":"Point"}
}