{
  "type": "Feature",
  "properties": {
    "iso:country":"US",
    "sg:address":"325 John Fitch Hwy",
    "sg:city":"Fitchburg",
    "sg:classifiers":[
        {
            "category":"Restaurant",
            "type":"Food & Drink"
        }
    ],
    "sg:menulink":"http://www.allmenus.com/ma/fitchburg/207625-taco-bell/menu/",
    "sg:phone":"+1 978 348 2444",
    "sg:postcode":"01420",
    "sg:province":"MA",
    "sg:tags":[
        "mexican"
    ],
    "wof:name":"Taco Bell",
    "wof:placetype":"venue"
},
  "geometry": {"coordinates":[-71.77449300000001,42.579437],"type":"Point"}
}