{
  "type": "Feature",
  "properties": {
    "addr:full": "325 John Fitch Hwy Fitchburg MA 01420",
    "addr:housenumber": "325",
    "addr:postcode": "01420",
    "addr:street": "John Fitch Hwy",
    "atp:label": "Taco Bell, 325 John Fitch Hwy Fitchburg MA US",
    "atp:similarity": 2.6851189136505127,
    "iso:country": "US",
    "ovtr:label": "Taco Bell, 325 John Fitch Hwy Fitchburg MA US",
    "ovtr:similarity": 2.6851038932800293,
    "sg:address": "325 John Fitch Hwy",
    "sg:city": "Fitchburg",
    "sg:classifiers": [
      {
        "category": "Restaurant",
        "type": "Food \u0026 Drink"
      }
    ],
    "sg:menulink": "http://www.allmenus.com/ma/fitchburg/207625-taco-bell/menu/",
    "sg:phone": "+1 978 348 2444",
    "sg:postcode": "01420",
    "sg:province": "MA",
    "sg:tags": [
      "mexican"
    ],
    "wof:name": "Taco Bell",
    "wof:placetype": "venue"
  },
  "geometry": {"coordinates":[-71.774493,42.579437],"type":"Point"}
}
