{
  "type": "Feature",
  "properties": {
    "addr:full":"26 Kingman St Weymouth MA 02188",
    "addr:housenumber":"26",
    "addr:postcode":"02188",
    "addr:street":"Kingman St",
    "iso:country":"US",
    "sg:address":"26 Kingman St",
    "sg:city":"Weymouth",
    "sg:classifiers":[
        {
            "category":"Professional",
            "subcategory":"Computer Services",
            "type":"Services"
        }
    ],
    "sg:phone":"+1   ",
    "sg:postcode":"02188",
    "sg:province":"MA",
    "sg:tags":[
        "related"
    ],
    "wof:name":"Gateway Computer",
    "wof:placetype":"venue"
},
  "geometry": {"coordinates":[-70.965493,42.211146],"type":"Point"}
}