{
  "type": "Feature",
  "properties": {
    "addr:full":"11 Robert Frost Rd Sudbury MA 01776",
    "addr:housenumber":"11",
    "addr:postcode":"01776",
    "addr:street":"Robert Frost Rd",
    "iso:country":"US",
    "sg:address":"11 Robert Frost Rd",
    "sg:city":"Sudbury",
    "sg:classifiers":[
        {
            "category":"Manufacturing",
            "subcategory":"Retail Goods",
            "type":"Manufacturing & Wholesale Goods"
        }
    ],
    "sg:phone":"+1   ",
    "sg:postcode":"01776",
    "sg:province":"MA",
    "sg:tags":[
        "lead",
        "mfg"
    ],
    "wof:name":"Framed For Life",
    "wof:placetype":"venue"
},
  "geometry": {"coordinates":[-71.421409,42.346551],"type":"Point"}
}