{
  "type": "Feature",
  "properties": {
    "addr:full": "393 Commercial St Provincetown MA 02657",
    "addr:housenumber": "393",
    "addr:postcode": "02657",
    "addr:street": "Commercial St",
    "iso:country": "US",
    "sg:address": "393 Commercial St",
    "sg:city": "Provincetown",
    "sg:classifiers": [
      {
        "category": "Home \u0026 Garden",
        "subcategory": "Furniture",
        "type": "Retail Goods"
      },
      {
        "category": "Manufacturing",
        "subcategory": "Soap",
        "type": "Manufacturing \u0026 Wholesale Goods"
      },
      {
        "category": "Home \u0026 Garden",
        "subcategory": "Home Furnishings",
        "type": "Retail Goods"
      },
      {
        "category": "Manufacturing",
        "subcategory": "Glass \u0026 Minerals",
        "type": "Manufacturing \u0026 Wholesale Goods"
      },
      {
        "category": "Home \u0026 Garden",
        "subcategory": "Kitchen Supply",
        "type": "Retail Goods"
      }
    ],
    "sg:phone": "+1 508 487 6800",
    "sg:postcode": "02657",
    "sg:province": "MA",
    "sg:tags": [
      "utensil",
      "crystal",
      "cookware",
      "china",
      "housewares-wholesale",
      "housewares",
      "glassware",
      "store",
      "manufacturer"
    ],
    "wof:name": "Utilities Inc",
    "wof:placetype": "venue"
  },
  "geometry": {"coordinates":[-70.182614,42.054264],"type":"Point"}
}
