{
  "type": "Feature",
  "properties": {
    "iso:country":"US",
    "sg:address":"393 Commercial St",
    "sg:city":"Provincetown",
    "sg:classifiers":[
        {
            "category":"Home & Garden",
            "subcategory":"Furniture",
            "type":"Retail Goods"
        },
        {
            "category":"Manufacturing",
            "subcategory":"Soap",
            "type":"Manufacturing & Wholesale Goods"
        },
        {
            "category":"Home & Garden",
            "subcategory":"Home Furnishings",
            "type":"Retail Goods"
        },
        {
            "category":"Manufacturing",
            "subcategory":"Glass & Minerals",
            "type":"Manufacturing & Wholesale Goods"
        },
        {
            "category":"Home & Garden",
            "subcategory":"Kitchen Supply",
            "type":"Retail Goods"
        }
    ],
    "sg:phone":"+1 508 487 6800",
    "sg:postcode":"02657",
    "sg:province":"MA",
    "sg:tags":[
        "utensil",
        "crystal",
        "cookware",
        "china",
        "housewares-wholesale",
        "housewares",
        "glassware",
        "store",
        "manufacturer"
    ],
    "wof:name":"Utilities Inc",
    "wof:placetype":"venue"
},
  "geometry": {"coordinates":[-70.182614,42.054264],"type":"Point"}
}