{
  "type": "Feature",
  "properties": {
    "addr:full":"93 Gardner Rd Winchendon MA 01475",
    "addr:housenumber":"93",
    "addr:postcode":"01475",
    "addr:street":"Gardner Rd",
    "iso:country":"US",
    "sg:address":"93 Gardner Rd",
    "sg:city":"Winchendon",
    "sg:classifiers":[
        {
            "category":"Bakery",
            "type":"Food & Drink"
        },
        {
            "category":"Coffee & Tea",
            "type":"Food & Drink"
        },
        {
            "category":"Bagels",
            "type":"Food & Drink"
        },
        {
            "category":"Donuts",
            "type":"Food & Drink"
        }
    ],
    "sg:menulink":"http://www.allmenus.com/ma/winchendon/143548-dunkin-donuts/menu/",
    "sg:phone":"+1 978 297 3445",
    "sg:postcode":"01475",
    "sg:province":"MA",
    "sg:tags":[
        "american",
        "diner",
        "pastry"
    ],
    "wof:name":"Dunkin' Donuts",
    "wof:placetype":"venue"
},
  "geometry": {"coordinates":[-72.00535000000001,42.640865],"type":"Point"}
}