{
  "type": "Feature",
  "properties": {
    "addr:full": "132 E Central St Natick MA 01760",
    "addr:housenumber": "132",
    "addr:postcode": "01760",
    "addr:street": "E Central St",
    "iso:country": "US",
    "sg:address": "132 E Central St",
    "sg:city": "Natick",
    "sg:classifiers": [
      {
        "category": "Retail",
        "subcategory": "Laundry \u0026 Dry Cleaning",
        "type": "Services"
      }
    ],
    "sg:phone": "+1   ",
    "sg:postcode": "01760",
    "sg:province": "MA",
    "sg:tags": [
      "drycleaning",
      "plant"
    ],
    "wof:name": "Sylvias Tailoring and Dry Clg",
    "wof:placetype": "venue"
  },
  "geometry": {"coordinates":[-71.333936,42.28759],"type":"Point"}
}
