{
  "type": "Feature",
  "properties": {
    "addr:full":"68 Thorndyke St Springfield MA 01118",
    "addr:housenumber":"68",
    "addr:postcode":"01118",
    "addr:street":"Thorndyke St",
    "iso:country":"US",
    "sg:address":"68 Thorndyke St",
    "sg:city":"Springfield",
    "sg:classifiers":[
        {
            "category":"Building & Trades",
            "subcategory":"Plumbing",
            "type":"Services"
        }
    ],
    "sg:phone":"+1 413 737 3275",
    "sg:postcode":"01118",
    "sg:province":"MA",
    "sg:tags":[
        "plumbing",
        "contractor"
    ],
    "wof:name":"Siciliano Plumbing & Heating",
    "wof:placetype":"venue"
},
  "geometry": {"coordinates":[-72.541549,42.088521],"type":"Point"}
}