{
  "type": "Feature",
  "properties": {
    "iso:country":"US",
    "sg:address":"301 Meeting House Path",
    "sg:city":"Ashland",
    "sg:classifiers":[
        {
            "category":"Health Services",
            "subcategory":"Dentist",
            "type":"Services"
        }
    ],
    "sg:phone":"+1 978 681 4553",
    "sg:postcode":"01721",
    "sg:province":"MA",
    "sg:tags":[
        "equipment",
        "dental",
        "supply"
    ],
    "wof:name":"Universal Dental Supply",
    "wof:placetype":"venue"
},
  "geometry": {"coordinates":[-71.43644,42.236891],"type":"Point"}
}