{
  "type": "Feature",
  "properties": {
    "iso:country":"US",
    "sg:address":"292 Partridge Hill Rd",
    "sg:city":"Charlton",
    "sg:classifiers":[
        {
            "category":"Building & Trades",
            "subcategory":"Construction",
            "type":"Services"
        }
    ],
    "sg:phone":"+1 508 248 6671",
    "sg:postcode":"01507",
    "sg:province":"MA",
    "sg:tags":[
        "contractor"
    ],
    "wof:name":"Webb W H Construction Co Inc",
    "wof:placetype":"venue"
},
  "geometry": {"coordinates":[-71.930199,42.092098],"type":"Point"}
}