{
  "type": "Feature",
  "properties": {
    "iso:country":"US",
    "sg:address":"339 Hancock St",
    "sg:city":"Quincy",
    "sg:classifiers":[
        {
            "category":"Professional",
            "subcategory":"Lawyer & Legal Services",
            "type":"Services"
        }
    ],
    "sg:phone":"+1 617 770 4422",
    "sg:postcode":"02171",
    "sg:province":"MA",
    "sg:tags":[
        "attorney"
    ],
    "wof:name":"Francis X Aylward",
    "wof:placetype":"venue"
},
  "geometry": {"coordinates":[-71.027051,42.274956],"type":"Point"}
}