{
  "type": "Feature",
  "properties": {
    "iso:country":"US",
    "sg:address":"220 W Main St",
    "sg:city":"Wellfleet",
    "sg:classifiers":[
        {
            "category":"Government",
            "subcategory":"Office",
            "type":"Public Place"
        }
    ],
    "sg:phone":"+1 508 349 0309",
    "sg:postcode":"02667",
    "sg:province":"MA",
    "sg:tags":[
        "village"
    ],
    "wof:name":"Wellfleet Building Inspector",
    "wof:placetype":"venue"
},
  "geometry": {"coordinates":[-70.040859,41.942184],"type":"Point"}
}