{
  "type": "Feature",
  "properties": {
    "iso:country":"US",
    "sg:address":"2 Pond St",
    "sg:city":"Canton",
    "sg:classifiers":[
        {
            "category":"Restaurant",
            "type":"Food & Drink"
        }
    ],
    "sg:phone":"+1 781 821 1022",
    "sg:postcode":"02021",
    "sg:province":"MA",
    "wof:name":"Centerfields Bar & Grille",
    "wof:placetype":"venue"
},
  "geometry": {"coordinates":[-71.14961,42.14521],"type":"Point"}
}