{
  "type": "Feature",
  "properties": {
    "iso:country":"US",
    "sg:address":"642 Main St",
    "sg:city":"Reading",
    "sg:classifiers":[
        {
            "category":"Personal",
            "subcategory":"Nail Salon",
            "type":"Services"
        }
    ],
    "sg:phone":"+1 781 942 1919",
    "sg:postcode":"01867",
    "sg:province":"MA",
    "wof:name":"Cathy's Nails",
    "wof:placetype":"venue"
},
  "geometry": {"coordinates":[-71.1026,42.5242],"type":"Point"}
}