{
  "type": "Feature",
  "properties": {
    "addr:full": "12 Exchange St Barre MA 01005",
    "addr:housenumber": "12",
    "addr:postcode": "01005",
    "addr:street": "Exchange St",
    "iso:country": "US",
    "sg:address": "12 Exchange St",
    "sg:city": "Barre",
    "sg:classifiers": [
      {
        "category": "Shopping",
        "subcategory": "Bicycles \u0026 Sporting Goods",
        "type": "Retail Goods"
      }
    ],
    "sg:phone": "+1 978 355 2219",
    "sg:postcode": "01005",
    "sg:province": "MA",
    "wof:name": "Country Bike \u0026 Sports",
    "wof:placetype": "venue"
  },
  "geometry": {"coordinates":[-72.104755,42.423193],"type":"Point"}
}
