{
  "type": "Feature",
  "properties": {
    "iso:country":"US",
    "sg:address":"12 Exchange St",
    "sg:city":"Barre",
    "sg:classifiers":[
        {
            "category":"Shopping",
            "subcategory":"Bicycles & Sporting Goods",
            "type":"Retail Goods"
        }
    ],
    "sg:phone":"+1 978 355 2219",
    "sg:postcode":"01005",
    "sg:province":"MA",
    "wof:name":"Country Bike & Sports",
    "wof:placetype":"venue"
},
  "geometry": {"coordinates":[-72.104755,42.423193],"type":"Point"}
}