{
  "type": "Feature",
  "properties": {
    "iso:country":"US",
    "sg:address":"1 Westinghouse Plz",
    "sg:city":"Hyde Park",
    "sg:classifiers":[
        {
            "category":"Retail",
            "subcategory":"Repair Shop",
            "type":"Services"
        }
    ],
    "sg:phone":"+1 617 370 0434",
    "sg:postcode":"02136",
    "sg:province":"MA",
    "sg:tags":[
        "lock",
        "locksmith"
    ],
    "wof:name":"24 Hour Emergency Locksmith",
    "wof:placetype":"venue"
},
  "geometry": {"coordinates":[-71.13300099999999,42.244368],"type":"Point"}
}