{
  "type": "Feature",
  "properties": {
    "addr:full": "1 Westinghouse Plz Hyde Park MA 02136",
    "addr:housenumber": "1",
    "addr:postcode": "02136",
    "addr:street": "Westinghouse Plz;Park",
    "iso:country": "US",
    "sg:address": "1 Westinghouse Plz",
    "sg:city": "Hyde Park",
    "sg:classifiers": [
      {
        "category": "Retail",
        "subcategory": "Repair Shop",
        "type": "Services"
      }
    ],
    "sg:phone": "+1 617 370 0434",
    "sg:postcode": "02136",
    "sg:province": "MA",
    "sg:tags": [
      "lock",
      "locksmith"
    ],
    "wof:name": "24 Hour Emergency Locksmith",
    "wof:placetype": "venue"
  },
  "geometry": {"coordinates":[-71.133001,42.244368],"type":"Point"}
}
