{
  "type": "Feature",
  "properties": {
    "iso:country":"US",
    "sg:address":"21 Alpha Rd",
    "sg:city":"Chelmsford",
    "sg:classifiers":[
        {
            "category":"Professional",
            "subcategory":"Computer Services",
            "type":"Services"
        }
    ],
    "sg:phone":"+1 978 256 0819",
    "sg:postcode":"01824",
    "sg:province":"MA",
    "sg:tags":[
        "processing",
        "datum"
    ],
    "wof:name":"Fidelity Information Svc",
    "wof:placetype":"venue"
},
  "geometry": {"coordinates":[-71.326289,42.592402],"type":"Point"}
}