{
  "type": "Feature",
  "properties": {
    "iso:country":"US",
    "sg:address":"51 Mystic St",
    "sg:city":"Everett",
    "sg:classifiers":[
        {
            "category":"Building & Trades",
            "subcategory":"Construction",
            "type":"Services"
        }
    ],
    "sg:phone":"+1 617 294 1924",
    "sg:postcode":"02149",
    "sg:province":"MA",
    "sg:tags":[
        "masonry",
        "contractor"
    ],
    "wof:name":"Jeo Masonry & Tile",
    "wof:placetype":"venue"
},
  "geometry": {"coordinates":[-71.064514,42.394343],"type":"Point"}
}