{
  "type": "Feature",
  "properties": {
    "addr:full": "51 Mystic St Everett MA 02149",
    "addr:housenumber": "51",
    "addr:postcode": "02149",
    "addr:street": "Mystic St",
    "iso:country": "US",
    "sg:address": "51 Mystic St",
    "sg:city": "Everett",
    "sg:classifiers": [
      {
        "category": "Building \u0026 Trades",
        "subcategory": "Construction",
        "type": "Services"
      }
    ],
    "sg:phone": "+1 617 294 1924",
    "sg:postcode": "02149",
    "sg:province": "MA",
    "sg:tags": [
      "masonry",
      "contractor"
    ],
    "wof:name": "Jeo Masonry \u0026 Tile",
    "wof:placetype": "venue"
  },
  "geometry": {"coordinates":[-71.064514,42.394343],"type":"Point"}
}
