{
  "type": "Feature",
  "properties": {
    "addr:full":"777 Brockton Ave Abington MA 02351",
    "addr:housenumber":"777",
    "addr:postcode":"02351",
    "addr:street":"Brockton Ave",
    "iso:country":"US",
    "sg:address":"777 Brockton Ave",
    "sg:city":"Abington",
    "sg:classifiers":[
        {
            "category":"Shopping",
            "subcategory":"Department Store",
            "type":"Retail Goods"
        }
    ],
    "sg:phone":"+1 781 857 2345",
    "sg:postcode":"02351",
    "sg:province":"MA",
    "sg:tags":[
        "clothing"
    ],
    "sg:website":"http://www.walmart.com",
    "wof:name":"Wal-Mart",
    "wof:placetype":"venue"
},
  "geometry": {"coordinates":[-70.96963700000001,42.093014],"type":"Point"}
}