{
  "type": "Feature",
  "properties": {
    "addr:full":"98 E Riding Dr Carlisle MA 01741",
    "addr:housenumber":"98",
    "addr:postcode":"01741",
    "addr:street":"E Riding Dr",
    "iso:country":"US",
    "sg:address":"98 E Riding Dr",
    "sg:city":"Carlisle",
    "sg:classifiers":[
        {
            "category":"Professional",
            "subcategory":"Business Services",
            "type":"Services"
        }
    ],
    "sg:phone":"+1   ",
    "sg:postcode":"01741",
    "sg:province":"MA",
    "wof:name":"Thomas Hedden",
    "wof:placetype":"venue"
},
  "geometry": {"coordinates":[-71.33358699999999,42.536277],"type":"Point"}
}