{
  "type": "Feature",
  "properties": {
    "addr:full":"30 Lyman St Worcester MA 01603",
    "addr:housenumber":"30",
    "addr:postcode":"01603",
    "addr:street":"Lyman St",
    "iso:country":"US",
    "sg:address":"30 Lyman St",
    "sg:city":"Worcester",
    "sg:classifiers":[
        {
            "category":"Retail",
            "subcategory":"Laundry & Dry Cleaning",
            "type":"Services"
        }
    ],
    "sg:phone":"+1 508 898 2272",
    "sg:postcode":"01603",
    "sg:province":"MA",
    "sg:tags":[
        "cleaners"
    ],
    "wof:name":"Elite Cleaners",
    "wof:placetype":"venue"
},
  "geometry": {"coordinates":[-71.83510699999999,42.238468],"type":"Point"}
}