{
  "type": "Feature",
  "properties": {
    "addr:full": "23 Harrison St Taunton MA 02780",
    "addr:housenumber": "23",
    "addr:postcode": "02780",
    "addr:street": "Harrison St",
    "iso:country": "US",
    "sg:address": "23 Harrison St",
    "sg:city": "Taunton",
    "sg:classifiers": [
      {
        "category": "Wholesale",
        "subcategory": "Computers",
        "type": "Manufacturing \u0026 Wholesale Goods"
      }
    ],
    "sg:phone": "+1 508 272 8078",
    "sg:postcode": "02780",
    "sg:province": "MA",
    "sg:tags": [
      "equipment"
    ],
    "wof:name": "Computer Solutions",
    "wof:placetype": "venue"
  },
  "geometry": {"coordinates":[-71.092869,41.897115],"type":"Point"}
}
