{
  "type": "Feature",
  "properties": {
    "iso:country":"US",
    "sg:address":"8 Farm St",
    "sg:city":"Bellingham",
    "sg:classifiers":[
        {
            "category":"Building & Trades",
            "subcategory":"Plumbing",
            "type":"Services"
        }
    ],
    "sg:phone":"+1   ",
    "sg:postcode":"02019",
    "sg:province":"MA",
    "sg:tags":[
        "plumbing"
    ],
    "wof:name":"Scott S Marley",
    "wof:placetype":"venue"
},
  "geometry": {"coordinates":[-71.474897,42.117467],"type":"Point"}
}