{
  "type": "Feature",
  "properties": {
    "addr:full":"14 Infield Ave Dracut MA 01826",
    "addr:housenumber":"14",
    "addr:postcode":"01826",
    "addr:street":"Infield Ave",
    "iso:country":"US",
    "sg:address":"14 Infield Ave",
    "sg:city":"Dracut",
    "sg:classifiers":[
        {
            "category":"Professional",
            "subcategory":"Business Services",
            "type":"Services"
        }
    ],
    "sg:phone":"+1   ",
    "sg:postcode":"01826",
    "sg:province":"MA",
    "wof:name":"Cheryl A Finnegan Inc",
    "wof:placetype":"venue"
},
  "geometry": {"coordinates":[-71.310726,42.669217],"type":"Point"}
}