{
  "type": "Feature",
  "properties": {
    "addr:full":"6 Learned St Framingham MA 01702",
    "addr:housenumber":"6",
    "addr:postcode":"01702",
    "addr:street":"Learned St",
    "iso:country":"US",
    "sg:address":"6 Learned St",
    "sg:city":"Framingham",
    "sg:classifiers":[
        {
            "category":"Building & Trades",
            "subcategory":"Construction",
            "type":"Services"
        }
    ],
    "sg:phone":"+1   ",
    "sg:postcode":"01702",
    "sg:province":"MA",
    "sg:tags":[
        "restoration"
    ],
    "wof:name":"New Face Restoration",
    "wof:placetype":"venue"
},
  "geometry": {"coordinates":[-71.420349,42.286148],"type":"Point"}
}