{
  "type": "Feature",
  "properties": {
    "iso:country":"US",
    "sg:address":"120 Beacon St",
    "sg:city":"Somerville",
    "sg:classifiers":[
        {
            "category":"Cinema",
            "subcategory":"Movie Rental",
            "type":"Entertainment"
        }
    ],
    "sg:phone":"+1 617 497 4100",
    "sg:postcode":"02143",
    "sg:province":"MA",
    "sg:tags":[
        "leasing",
        "video",
        "disc",
        "tape"
    ],
    "wof:name":"Knapp Video",
    "wof:placetype":"venue"
},
  "geometry": {"coordinates":[-71.105947,42.377687],"type":"Point"}
}