{
  "type": "Feature",
  "properties": {
    "addr:full": "124 Beacon St Boston MA 02116",
    "addr:housenumber": "124",
    "addr:postcode": "02116",
    "addr:street": "Beacon St",
    "iso:country": "US",
    "sg:address": "124 Beacon St",
    "sg:city": "Boston",
    "sg:classifiers": [
      {
        "category": "Professional",
        "subcategory": "Computer Services",
        "type": "Services"
      }
    ],
    "sg:phone": "+1   ",
    "sg:postcode": "02116",
    "sg:province": "MA",
    "sg:tags": [
      "programing",
      "custom"
    ],
    "wof:name": "Christopher Wisdo",
    "wof:placetype": "venue"
  },
  "geometry": {"coordinates":[-71.073847,42.355258],"type":"Point"}
}
