{
  "type": "Feature",
  "properties": {
    "iso:country":"US",
    "sg:address":"290 Dutton Rd",
    "sg:city":"Sudbury",
    "sg:classifiers":[
        {
            "category":"Retail",
            "subcategory":"Animal Services",
            "type":"Services"
        }
    ],
    "sg:phone":"+1   ",
    "sg:postcode":"01776",
    "sg:province":"MA",
    "wof:name":"Dutton Downs",
    "wof:placetype":"venue"
},
  "geometry": {"coordinates":[-71.457728,42.373611],"type":"Point"}
}