{
  "type": "Feature",
  "properties": {
    "iso:country":"US",
    "sg:address":"419 Crescent St",
    "sg:city":"Brockton",
    "sg:classifiers":[
        {
            "category":"Autos & Motor Vehicles",
            "subcategory":"Auto Supplies",
            "type":"Retail Goods"
        }
    ],
    "sg:phone":"+1 508 586 9776",
    "sg:postcode":"02302",
    "sg:province":"MA",
    "sg:tags":[
        "automobile",
        "stereo",
        "radio"
    ],
    "wof:name":"Boomer Mc Loud Performance",
    "wof:placetype":"venue"
},
  "geometry": {"coordinates":[-71.00473,42.080169],"type":"Point"}
}