{
  "type": "Feature",
  "properties": {
    "iso:country":"US",
    "sg:address":"423 Main St",
    "sg:city":"Athol",
    "sg:classifiers":[
        {
            "category":"Organizations",
            "subcategory":"Non-profit Organization",
            "type":"Services"
        }
    ],
    "sg:phone":"+1 978 249 7481",
    "sg:postcode":"01331",
    "sg:province":"MA",
    "wof:name":"FCAC Healthy Families",
    "wof:placetype":"venue"
},
  "geometry": {"coordinates":[-72.23136700000001,42.593945],"type":"Point"}
}