{
  "type": "Feature",
  "properties": {
    "addr:full": "434 Massachusetts Ave Boston MA 02118",
    "addr:housenumber": "434",
    "addr:postcode": "02118",
    "addr:street": "Massachusetts Ave",
    "iso:country": "US",
    "sg:address": "434 Massachusetts Ave",
    "sg:city": "Boston",
    "sg:classifiers": [
      {
        "category": "Education",
        "subcategory": "School",
        "type": "Public Place"
      }
    ],
    "sg:phone": "+1 617 437 9388",
    "sg:postcode": "02118",
    "sg:province": "MA",
    "sg:website": "www.academicstudies.com",
    "wof:name": "Academic Studies Abroad",
    "wof:placetype": "venue"
  },
  "geometry": {"coordinates":[-71.082593,42.34142],"type":"Point"}
}
