{
  "type": "Feature",
  "properties": {
    "addr:full": "62 Haverhill Rd Amesbury MA 01913",
    "addr:housenumber": "62",
    "addr:postcode": "01913",
    "addr:street": "Haverhill Rd",
    "iso:country": "US",
    "sg:address": "62 Haverhill Rd",
    "sg:city": "Amesbury",
    "sg:classifiers": [
      {
        "category": "Retail",
        "subcategory": "Car Wash",
        "type": "Services"
      }
    ],
    "sg:phone": "+1 978 388 6262",
    "sg:postcode": "01913",
    "sg:province": "MA",
    "sg:tags": [
      "polishing",
      "washing"
    ],
    "wof:name": "E Z Car Wash",
    "wof:placetype": "venue"
  },
  "geometry": {"coordinates":[-70.947972,42.841853],"type":"Point"}
}
