{
  "type": "Feature",
  "properties": {
    "iso:country":"US",
    "sg:address":"86 Worcester Rd",
    "sg:city":"Webster",
    "sg:classifiers":[
        {
            "category":"Banks & Credit Unions",
            "subcategory":"Bank",
            "type":"Services"
        },
        {
            "category":"Banks & Credit Unions",
            "subcategory":"Financial Services",
            "type":"Services"
        }
    ],
    "sg:phone":"+1 800 939 9103",
    "sg:postcode":"01570",
    "sg:province":"MA",
    "sg:tags":[
        "broker",
        "mortgage"
    ],
    "sg:website":"www.southbridgesavingsbank.com",
    "wof:name":"Southbridge Savings Bank",
    "wof:placetype":"venue"
},
  "geometry": {"coordinates":[-71.86731399999999,42.072272],"type":"Point"}
}