{
  "type": "Feature",
  "properties": {
    "addr:full": "86 Worcester Rd Webster MA 01570",
    "addr:housenumber": "86",
    "addr:postcode": "01570",
    "addr:street": "Worcester Rd",
    "iso:country": "US",
    "sg:address": "86 Worcester Rd",
    "sg:city": "Webster",
    "sg:classifiers": [
      {
        "category": "Banks \u0026 Credit Unions",
        "subcategory": "Bank",
        "type": "Services"
      },
      {
        "category": "Banks \u0026 Credit Unions",
        "subcategory": "Financial Services",
        "type": "Services"
      }
    ],
    "sg:phone": "+1 800 939 9103",
    "sg:postcode": "01570",
    "sg:province": "MA",
    "sg:tags": [
      "broker",
      "mortgage"
    ],
    "sg:website": "www.southbridgesavingsbank.com",
    "wof:name": "Southbridge Savings Bank",
    "wof:placetype": "venue"
  },
  "geometry": {"coordinates":[-71.867314,42.072272],"type":"Point"}
}
