{
  "type": "Feature",
  "properties": {
    "addr:full": "166 Andover St North Andover MA 01845",
    "addr:housenumber": "166",
    "addr:postcode": "01845",
    "addr:street": "Andover St",
    "iso:country": "US",
    "sg:address": "166 Andover St",
    "sg:city": "North Andover",
    "sg:classifiers": [
      {
        "category": "Shopping",
        "subcategory": "Hobbies, Toys, \u0026 Games",
        "type": "Retail Goods"
      }
    ],
    "sg:phone": "+1 978 688 7283",
    "sg:postcode": "01845",
    "sg:province": "MA",
    "sg:tags": [
      "model",
      "supply"
    ],
    "sg:website": "www.collectaire.com",
    "wof:name": "Collect-Aire Models Inc",
    "wof:placetype": "venue"
  },
  "geometry": {"coordinates":[-71.11819,42.68099],"type":"Point"}
}
