{
  "type": "Feature",
  "properties": {
    "addr:full":"195 West St Waltham MA 02451",
    "addr:housenumber":"195",
    "addr:postcode":"02451",
    "addr:street":"West St",
    "iso:country":"US",
    "sg:address":"195 West St",
    "sg:city":"Waltham",
    "sg:classifiers":[
        {
            "category":"Restaurant",
            "type":"Food & Drink"
        }
    ],
    "sg:phone":"+1 781 684 0705",
    "sg:postcode":"02451",
    "sg:province":"MA",
    "wof:name":"Corporate Chef's Inc",
    "wof:placetype":"venue"
},
  "geometry": {"coordinates":[-71.270293,42.394166],"type":"Point"}
}