{
  "type": "Feature",
  "properties": {
    "addr:full":"1953 Massachusetts Ave Cambridge MA 02140",
    "addr:housenumber":"1953",
    "addr:postcode":"02140",
    "addr:street":"Massachusetts Ave",
    "iso:country":"US",
    "sg:address":"1953 Massachusetts Ave",
    "sg:city":"Cambridge",
    "sg:classifiers":[
        {
            "category":"Personal",
            "type":"Services"
        }
    ],
    "sg:phone":"+1 857 284 1655",
    "sg:postcode":"02140",
    "sg:province":"MA",
    "sg:tags":[
        "towing"
    ],
    "wof:name":"Mass Car Junks",
    "wof:placetype":"venue"
},
  "geometry": {"coordinates":[-71.12023600000001,42.389868],"type":"Point"}
}