{
  "type": "Feature",
  "properties": {
    "addr:full": "17 Riverview Ter New Bedford MA 02744",
    "addr:housenumber": "17",
    "addr:postcode": "02744",
    "addr:street": "Riverview Ter",
    "iso:country": "US",
    "sg:address": "17 Riverview Ter",
    "sg:city": "New Bedford",
    "sg:classifiers": [
      {
        "category": "Shopping",
        "type": "Retail Goods"
      },
      {
        "category": "Home \u0026 Garden",
        "subcategory": "Household Appliances",
        "type": "Retail Goods"
      }
    ],
    "sg:phone": "+1 508 999 4567",
    "sg:postcode": "02744",
    "sg:province": "MA",
    "sg:tags": [
      "cleaners",
      "merchandise",
      "vacuum"
    ],
    "wof:name": "Nick's Central Vacuum Systems",
    "wof:placetype": "venue"
  },
  "geometry": {"coordinates":[-70.90444,41.601792],"type":"Point"}
}
