{
  "type": "Feature",
  "properties": {
    "iso:country":"US",
    "sg:address":"17 Riverview Ter",
    "sg:city":"New Bedford",
    "sg:classifiers":[
        {
            "category":"Shopping",
            "type":"Retail Goods"
        },
        {
            "category":"Home & Garden",
            "subcategory":"Household Appliances",
            "type":"Retail Goods"
        }
    ],
    "sg:phone":"+1 508 999 4567",
    "sg:postcode":"02744",
    "sg:province":"MA",
    "sg:tags":[
        "cleaners",
        "merchandise",
        "vacuum"
    ],
    "wof:name":"Nick's Central Vacuum Systems",
    "wof:placetype":"venue"
},
  "geometry": {"coordinates":[-70.90443999999999,41.601792],"type":"Point"}
}