{
  "type": "Feature",
  "properties": {
    "iso:country":"US",
    "sg:address":"75 Warren Ave",
    "sg:city":"Hyde Park",
    "sg:classifiers":[
        {
            "category":"Professional",
            "subcategory":"Computer Services",
            "type":"Services"
        }
    ],
    "sg:phone":"+1 617 361 6465",
    "sg:postcode":"02136",
    "sg:province":"MA",
    "sg:tags":[
        "consultant",
        "designer",
        "programing",
        "custom"
    ],
    "wof:name":"Sem Consulting Co Inc",
    "wof:placetype":"venue"
},
  "geometry": {"coordinates":[-71.11542900000001,42.25105],"type":"Point"}
}