{
  "type": "Feature",
  "properties": {
    "iso:country":"US",
    "sg:address":"216 S Silver Ln",
    "sg:city":"Sunderland",
    "sg:classifiers":[
        {
            "category":"Education",
            "subcategory":"Junior College",
            "type":"Public Place"
        }
    ],
    "sg:phone":"+1 413 665 4880",
    "sg:postcode":"01375",
    "sg:province":"MA",
    "sg:tags":[
        "technical",
        "institute"
    ],
    "wof:name":"New England Art Therapy Inst",
    "wof:placetype":"venue"
},
  "geometry": {"coordinates":[-72.56413000000001,42.440291],"type":"Point"}
}