{
  "type": "Feature",
  "properties": {
    "iso:country":"US",
    "sg:address":"440 Common St",
    "sg:city":"Belmont",
    "sg:classifiers":[
        {
            "category":"Shopping",
            "subcategory":"Hobbies, Toys, & Games",
            "type":"Retail Goods"
        }
    ],
    "sg:phone":"+1 617 484 1700",
    "sg:postcode":"02478",
    "sg:province":"MA",
    "sg:tags":[
        "product",
        "ceramic"
    ],
    "wof:name":"Sfoggio Limited",
    "wof:placetype":"venue"
},
  "geometry": {"coordinates":[-71.174593,42.380509],"type":"Point"}
}