{
  "type": "Feature",
  "properties": {
    "addr:full": "650 Huntington Ave Boston MA 02115",
    "addr:housenumber": "650",
    "addr:postcode": "02115",
    "addr:street": "Huntington Ave",
    "iso:country": "US",
    "sg:address": "650 Huntington Ave",
    "sg:city": "Boston",
    "sg:classifiers": [
      {
        "category": "Communications",
        "subcategory": "Radio Station",
        "type": "Services"
      }
    ],
    "sg:phone": "+1 617 734 8593",
    "sg:postcode": "02115",
    "sg:province": "MA",
    "sg:tags": [
      "broadcast"
    ],
    "wof:name": "Powermix Music Productions",
    "wof:placetype": "venue"
  },
  "geometry": {"coordinates":[-71.100597,42.335615],"type":"Point"}
}
