{
  "type": "Feature",
  "properties": {
    "iso:country":"US",
    "sg:address":"324 Newbury St.",
    "sg:city":"Boston",
    "sg:classifiers":[
        {
            "category":"Shopping",
            "subcategory":"Used Merchandise",
            "type":"Retail Goods"
        }
    ],
    "sg:phone":"+1 617 236 2028",
    "sg:postcode":"02115",
    "sg:province":"MA",
    "sg:tags":[
        "vintage",
        "consignment"
    ],
    "sg:website":"www.secondtimearound.net",
    "wof:name":"Second Time Around",
    "wof:placetype":"venue"
},
  "geometry": {"coordinates":[-71.086,42.3484],"type":"Point"}
}