{
  "type": "Feature",
  "properties": {
    "iso:country":"US",
    "sg:address":"1 W Union St",
    "sg:city":"Ashland",
    "sg:classifiers":[
        {
            "category":"Retail",
            "subcategory":"Laundry & Dry Cleaning",
            "type":"Services"
        }
    ],
    "sg:phone":"+1 508 881 7742",
    "sg:postcode":"01721",
    "sg:province":"MA",
    "sg:tags":[
        "cleaners"
    ],
    "wof:name":"B & H Cleaners",
    "wof:placetype":"venue"
},
  "geometry": {"coordinates":[-71.466994,42.255425],"type":"Point"}
}