{
  "type": "Feature",
  "properties": {
    "addr:full":"12 Humboldt St Cambridge MA 02140",
    "addr:housenumber":"12",
    "addr:postcode":"02140",
    "addr:street":"Humboldt St",
    "iso:country":"US",
    "sg:address":"12 Humboldt St",
    "sg:city":"Cambridge",
    "sg:classifiers":[
        {
            "category":"Professional",
            "subcategory":"Business Services",
            "type":"Services"
        }
    ],
    "sg:phone":"+1 617 491 8067",
    "sg:postcode":"02140",
    "sg:province":"MA",
    "sg:tags":[
        "interior",
        "consultant",
        "design",
        "decorator"
    ],
    "wof:name":"Karin Weller Interior Design",
    "wof:placetype":"venue"
},
  "geometry": {"coordinates":[-71.120986,42.38558],"type":"Point"}
}