{
  "type": "Feature",
  "properties": {
    "addr:full":"296 Cooley St Springfield MA 01128",
    "addr:housenumber":"296",
    "addr:postcode":"01128",
    "addr:street":"Cooley St",
    "iso:country":"US",
    "sg:address":"296 Cooley St",
    "sg:city":"Springfield",
    "sg:classifiers":[
        {
            "category":"Utilities",
            "subcategory":"Mobile Phone",
            "type":"Services"
        },
        {
            "category":"Communications",
            "type":"Services"
        }
    ],
    "sg:phone":"+1 413 782 7203",
    "sg:postcode":"01128",
    "sg:province":"MA",
    "sg:tags":[
        "data",
        "telephone",
        "cellular"
    ],
    "sg:website":"http://www.cingular.com",
    "wof:name":"One Solution Wireless",
    "wof:placetype":"venue"
},
  "geometry": {"coordinates":[-72.49836999999999,42.095245],"type":"Point"}
}