{
  "type": "Feature",
  "properties": {
    "iso:country":"US",
    "sg:address":"457 Main Street",
    "sg:city":"Stoneham",
    "sg:classifiers":[
        {
            "category":"Education",
            "subcategory":"Preschool",
            "type":"Public Place"
        },
        {
            "category":"Education",
            "subcategory":"School",
            "type":"Public Place"
        }
    ],
    "sg:phone":"+1 781 279 9182",
    "sg:postcode":"02180",
    "sg:province":"MA",
    "sg:tags":[
        "elementary"
    ],
    "wof:name":"Tri-Cap Head Start",
    "wof:placetype":"venue"
},
  "geometry": {"coordinates":[-71.100324,42.476884],"type":"Point"}
}