{
  "type": "Feature",
  "properties": {
    "iso:country":"US",
    "sg:address":"10 Woodside Dr",
    "sg:city":"Agawam",
    "sg:classifiers":[
        {
            "category":"Building & Trades",
            "subcategory":"Construction",
            "type":"Services"
        }
    ],
    "sg:phone":"+1 413 786 2412",
    "sg:postcode":"01001",
    "sg:province":"MA",
    "sg:tags":[
        "general",
        "contractor"
    ],
    "wof:name":"Calabrese Construction Co",
    "wof:placetype":"venue"
},
  "geometry": {"coordinates":[-72.627233,42.071914],"type":"Point"}
}