{
  "type": "Feature",
  "properties": {
    "addr:full": "12 Frederick St Framingham MA 01702",
    "addr:housenumber": "12",
    "addr:postcode": "01702",
    "addr:street": "Frederick St",
    "iso:country": "US",
    "ovtr:label": "Camaro Auto Service, 12 Frederick St Framingham MA US",
    "ovtr:similarity": 2.1847310066223145,
    "sg:address": "12 Frederick St",
    "sg:city": "Framingham",
    "sg:classifiers": [
      {
        "category": "Professional",
        "subcategory": "Detective \u0026 Security Services",
        "type": "Services"
      }
    ],
    "sg:phone": "+1 508 901 0162",
    "sg:postcode": "01702",
    "sg:province": "MA",
    "sg:tags": [
      "information",
      "bureau"
    ],
    "wof:name": "Camaro Auto Service",
    "wof:placetype": "venue"
  },
  "geometry": {"coordinates":[-71.415653,42.279755],"type":"Point"}
}
