{
  "type": "Feature",
  "properties": {
    "iso:country":"US",
    "sg:address":"12 Frederick St",
    "sg:city":"Framingham",
    "sg:classifiers":[
        {
            "category":"Professional",
            "subcategory":"Detective & Security Services",
            "type":"Services"
        }
    ],
    "sg:phone":"+1 508 901 0162",
    "sg:postcode":"01702",
    "sg:province":"MA",
    "sg:tags":[
        "information",
        "bureau"
    ],
    "wof:name":"Camaro Auto Service",
    "wof:placetype":"venue"
},
  "geometry": {"coordinates":[-71.41565300000001,42.279755],"type":"Point"}
}