{
  "type": "Feature",
  "properties": {
    "iso:country":"US",
    "sg:address":"54 Woodrow Ave",
    "sg:city":"Boston",
    "sg:classifiers":[
        {
            "category":"Organizations",
            "subcategory":"Community Association",
            "type":"Services"
        }
    ],
    "sg:phone":"+1   ",
    "sg:postcode":"02124",
    "sg:province":"MA",
    "wof:name":"Ramsey Dave L VFW Post 8772",
    "wof:placetype":"venue"
},
  "geometry": {"coordinates":[-71.08064,42.287857],"type":"Point"}
}