{
  "type": "Feature",
  "properties": {
    "iso:country":"US",
    "sg:address":"315 Durfee St",
    "sg:city":"Fall River",
    "sg:classifiers":[
        {
            "category":"Local Transit",
            "type":"Transportation"
        }
    ],
    "sg:phone":"+1 508 677 9377",
    "sg:postcode":"02720",
    "sg:province":"MA",
    "sg:tags":[
        "limousine"
    ],
    "wof:name":"Princess Limousine",
    "wof:placetype":"venue"
},
  "geometry": {"coordinates":[-71.155861,41.70736],"type":"Point"}
}