{
  "type": "Feature",
  "properties": {
    "addr:full":"235 W Center St West Bridgewater MA 02379",
    "addr:housenumber":"235",
    "addr:postcode":"02379",
    "addr:street":"W Center St",
    "iso:country":"US",
    "sg:address":"235 W Center St",
    "sg:city":"West Bridgewater",
    "sg:classifiers":[
        {
            "category":"Wholesale",
            "subcategory":"Groceries",
            "type":"Manufacturing & Wholesale Goods"
        }
    ],
    "sg:phone":"+1 508 588 5474",
    "sg:postcode":"02379",
    "sg:province":"MA",
    "sg:tags":[
        "food",
        "broker"
    ],
    "wof:name":"Lorray Food Brokers",
    "wof:placetype":"venue"
},
  "geometry": {"coordinates":[-71.021455,42.016804],"type":"Point"}
}