{
  "type": "Feature",
  "properties": {
    "addr:full":"106 Middlesex St Winchester MA 01890",
    "addr:housenumber":"106",
    "addr:postcode":"01890",
    "addr:street":"Middlesex St",
    "iso:country":"US",
    "sg:address":"106 Middlesex St",
    "sg:city":"Winchester",
    "sg:classifiers":[
        {
            "category":"Building & Trades",
            "subcategory":"Landscaping Services",
            "type":"Services"
        }
    ],
    "sg:phone":"+1 781 729 5296",
    "sg:postcode":"01890",
    "sg:province":"MA",
    "sg:tags":[
        "landscape",
        "contractor"
    ],
    "wof:name":"Country Landscape & Design Inc",
    "wof:placetype":"venue"
},
  "geometry": {"coordinates":[-71.146824,42.460148],"type":"Point"}
}