{
  "type": "Feature",
  "properties": {
    "addr:full":"762 Dutton St Lowell MA 01854",
    "addr:housenumber":"762",
    "addr:postcode":"01854",
    "addr:street":"Dutton St",
    "iso:country":"US",
    "sg:address":"762 Dutton St",
    "sg:city":"Lowell",
    "sg:classifiers":[
        {
            "category":"Wholesale",
            "subcategory":"Vending Machines",
            "type":"Manufacturing & Wholesale Goods"
        }
    ],
    "sg:phone":"+1 978 452 2233",
    "sg:postcode":"01854",
    "sg:province":"MA",
    "sg:tags":[
        "machines-parts",
        "machines-wholesale",
        "manufacturer",
        "supply"
    ],
    "wof:name":"Alpha Vending",
    "wof:placetype":"venue"
},
  "geometry": {"coordinates":[-71.320699,42.640619],"type":"Point"}
}