{
  "type": "Feature",
  "properties": {
    "addr:full": "13 Bailey St Everett MA 02149",
    "addr:housenumber": "13",
    "addr:postcode": "02149",
    "addr:street": "Bailey St",
    "iso:country": "US",
    "sg:address": "13 Bailey St",
    "sg:city": "Everett",
    "sg:classifiers": [
      {
        "category": "Professional",
        "subcategory": "Computer Services",
        "type": "Services"
      }
    ],
    "sg:phone": "+1   ",
    "sg:postcode": "02149",
    "sg:province": "MA",
    "wof:name": "Samia Financial",
    "wof:placetype": "venue"
  },
  "geometry": {"coordinates":[-71.058623,42.402516],"type":"Point"}
}
