{
  "type": "Feature",
  "properties": {
    "iso:country":"US",
    "sg:address":"13 Bailey St",
    "sg:city":"Everett",
    "sg:classifiers":[
        {
            "category":"Professional",
            "subcategory":"Computer Services",
            "type":"Services"
        }
    ],
    "sg:phone":"+1   ",
    "sg:postcode":"02149",
    "sg:province":"MA",
    "wof:name":"Samia Financial",
    "wof:placetype":"venue"
},
  "geometry": {"coordinates":[-71.058623,42.402516],"type":"Point"}
}