{
  "type": "Feature",
  "properties": {
    "iso:country":"US",
    "sg:address":"1 Cambridge Center",
    "sg:city":"Cambridge",
    "sg:classifiers":[
        {
            "category":"Professional",
            "subcategory":"Computer Services",
            "type":"Services"
        }
    ],
    "sg:phone":"+1   ",
    "sg:postcode":"02142",
    "sg:province":"MA",
    "sg:tags":[
        "consulting"
    ],
    "wof:name":"Chase Manhattan",
    "wof:placetype":"venue"
},
  "geometry": {"coordinates":[-71.085588,42.362646],"type":"Point"}
}