{
  "type": "Feature",
  "properties": {
    "addr:full": "199 Hemlock St New Bedford MA 02740",
    "addr:housenumber": "199",
    "addr:postcode": "02740",
    "addr:street": "Hemlock St",
    "iso:country": "US",
    "sg:address": "199 Hemlock St",
    "sg:city": "New Bedford",
    "sg:classifiers": [
      {
        "category": "Organizations",
        "subcategory": "Community Association",
        "type": "Services"
      }
    ],
    "sg:phone": "+1 508 996 9510",
    "sg:postcode": "02740",
    "sg:province": "MA",
    "sg:tags": [
      "military"
    ],
    "wof:name": "American Portuguese War Vets",
    "wof:placetype": "venue"
  },
  "geometry": {"coordinates":[-70.933818,41.61725],"type":"Point"}
}
