{
  "type": "Feature",
  "properties": {
    "iso:country":"US",
    "sg:address":"379 Cambridge St",
    "sg:city":"Allston",
    "sg:classifiers":[
        {
            "category":"Professional",
            "type":"Services"
        }
    ],
    "sg:phone":"+1 617 783 9779",
    "sg:postcode":"02134",
    "sg:province":"MA",
    "sg:tags":[
        "establishment"
    ],
    "wof:name":"AAAAA New England Wildlife",
    "wof:placetype":"venue"
},
  "geometry": {"coordinates":[-71.13314200000001,42.35548],"type":"Point"}
}