{
  "type": "Feature",
  "properties": {
    "addr:full": "51 S Main St North Brookfield MA 01535",
    "addr:housenumber": "51",
    "addr:postcode": "01535",
    "addr:street": "S Main St",
    "iso:country": "US",
    "sg:address": "51 S Main St",
    "sg:city": "North Brookfield",
    "sg:classifiers": [
      {
        "category": "Personal",
        "subcategory": "Beauty Salon",
        "type": "Services"
      }
    ],
    "sg:phone": "+1 508 867 7220",
    "sg:postcode": "01535",
    "sg:province": "MA",
    "wof:name": "Crop Stop",
    "wof:placetype": "venue"
  },
  "geometry": {"coordinates":[-72.08784,42.262209],"type":"Point"}
}
