{
  "type": "Feature",
  "properties": {
    "addr:full":"214 Plantation Cir Norwood MA 02062",
    "addr:housenumber":"214",
    "addr:postcode":"02062",
    "addr:street":"Plantation Cir",
    "iso:country":"US",
    "sg:address":"214 Plantation Cir",
    "sg:city":"Norwood",
    "sg:classifiers":[
        {
            "category":"Professional",
            "type":"Services"
        }
    ],
    "sg:phone":"+1 781 255 9904",
    "sg:postcode":"02062",
    "sg:province":"MA",
    "sg:tags":[
        "establishment"
    ],
    "wof:name":"Three Oaks Development",
    "wof:placetype":"venue"
},
  "geometry": {"coordinates":[-71.19503400000001,42.15404],"type":"Point"}
}