{
  "type": "Feature",
  "properties": {
    "iso:country":"US",
    "sg:address":"458 Monponsett St",
    "sg:city":"Hanson",
    "sg:classifiers":[
        {
            "category":"Shopping",
            "subcategory":"Gifts & Souvenirs",
            "type":"Retail Goods"
        }
    ],
    "sg:phone":"+1 781 294 8425",
    "sg:postcode":"02341",
    "sg:province":"MA",
    "sg:tags":[
        "party",
        "supply"
    ],
    "wof:name":"Country Rentals",
    "wof:placetype":"venue"
},
  "geometry": {"coordinates":[-70.843827,42.031417],"type":"Point"}
}