{
  "type": "Feature",
  "properties": {
    "addr:full": "458 Monponsett St Hanson MA 02341",
    "addr:housenumber": "458",
    "addr:postcode": "02341",
    "addr:street": "Monponsett St",
    "iso:country": "US",
    "sg:address": "458 Monponsett St",
    "sg:city": "Hanson",
    "sg:classifiers": [
      {
        "category": "Shopping",
        "subcategory": "Gifts \u0026 Souvenirs",
        "type": "Retail Goods"
      }
    ],
    "sg:phone": "+1 781 294 8425",
    "sg:postcode": "02341",
    "sg:province": "MA",
    "sg:tags": [
      "party",
      "supply"
    ],
    "wof:name": "Country Rentals",
    "wof:placetype": "venue"
  },
  "geometry": {"coordinates":[-70.843827,42.031417],"type":"Point"}
}
