{
  "type": "Feature",
  "properties": {
    "addr:full":"332 Main St Indian Orchard MA 01151",
    "addr:housenumber":"332",
    "addr:postcode":"01151",
    "addr:street":"Main St",
    "iso:country":"US",
    "sg:address":"332 Main St",
    "sg:city":"Indian Orchard",
    "sg:classifiers":[
        {
            "category":"Food & Beverages",
            "subcategory":"Groceries & Convenience Stores",
            "type":"Retail Goods"
        }
    ],
    "sg:phone":"+1 413 543 3104",
    "sg:postcode":"01151",
    "sg:province":"MA",
    "sg:tags":[
        "market"
    ],
    "wof:name":"Manny's Butcher Shop",
    "wof:placetype":"venue"
},
  "geometry": {"coordinates":[-72.494381,42.158612],"type":"Point"}
}