{
  "type": "Feature",
  "properties": {
    "addr:full": "26 Ridgewood Cir Lawrence MA 01843",
    "addr:housenumber": "26",
    "addr:postcode": "01843",
    "addr:street": "Ridgewood Cir",
    "iso:country": "US",
    "sg:address": "26 Ridgewood Cir",
    "sg:city": "Lawrence",
    "sg:classifiers": [
      {
        "category": "Local Transit",
        "type": "Transportation"
      }
    ],
    "sg:phone": "+1 978 682 3535",
    "sg:postcode": "01843",
    "sg:province": "MA",
    "sg:tags": [
      "line"
    ],
    "wof:name": "First Choice Transit Inc",
    "wof:placetype": "venue"
  },
  "geometry": {"coordinates":[-71.182952,42.676708],"type":"Point"}
}
