{
  "type": "Feature",
  "properties": {
    "addr:full": "83 York Ave Randolph MA 02368",
    "addr:housenumber": "83",
    "addr:postcode": "02368",
    "addr:street": "York Ave",
    "iso:country": "US",
    "sg:address": "83 York Ave",
    "sg:city": "Randolph",
    "sg:classifiers": [
      {
        "category": "Health Services",
        "subcategory": "Doctor",
        "type": "Services"
      }
    ],
    "sg:phone": "+1 781 961 1300",
    "sg:postcode": "02368",
    "sg:province": "MA",
    "wof:name": "Ner Construction Management Inc",
    "wof:placetype": "venue"
  },
  "geometry": {"coordinates":[-71.07,42.181499],"type":"Point"}
}
