{
  "type": "Feature",
  "properties": {
    "addr:full":"134 Lowell Rd Pepperell MA 01463",
    "addr:housenumber":"134",
    "addr:postcode":"01463",
    "addr:street":"Lowell Rd",
    "iso:country":"US",
    "sg:address":"134 Lowell Rd",
    "sg:city":"Pepperell",
    "sg:classifiers":[
        {
            "category":"Building & Trades",
            "subcategory":"Construction",
            "type":"Services"
        }
    ],
    "sg:phone":"+1 978 423 1213",
    "sg:postcode":"01463",
    "sg:province":"MA",
    "sg:tags":[
        "siding",
        "contractor"
    ],
    "wof:name":"Kenstruction Co",
    "wof:placetype":"venue"
},
  "geometry": {"coordinates":[-71.53781600000001,42.666889],"type":"Point"}
}