{
  "type": "Feature",
  "properties": {
    "iso:country":"US",
    "sg:address":"77 Warren St",
    "sg:city":"Brighton",
    "sg:classifiers":[
        {
            "category":"Professional",
            "type":"Services"
        }
    ],
    "sg:phone":"+1   ",
    "sg:postcode":"02135",
    "sg:province":"MA",
    "sg:tags":[
        "psychological",
        "consultant"
    ],
    "wof:name":"Alan J Lieberman PHD",
    "wof:placetype":"venue"
},
  "geometry": {"coordinates":[-71.14243500000001,42.349362],"type":"Point"}
}