{
  "type": "Feature",
  "properties": {
    "addr:full":"401 Harvard St Brookline MA 02446",
    "addr:housenumber":"401",
    "addr:postcode":"02446",
    "addr:street":"Harvard St",
    "iso:country":"US",
    "sg:address":"401 Harvard St",
    "sg:city":"Brookline",
    "sg:classifiers":[
        {
            "category":"Restaurant",
            "type":"Food & Drink"
        }
    ],
    "sg:menulink":"http://www.allmenus.com/ma/brookline/258564-ruths-kitchen/menu/",
    "sg:phone":"+1 617 734 9810",
    "sg:postcode":"02446",
    "sg:province":"MA",
    "sg:tags":[
        "korean",
        "asian",
        "chinese"
    ],
    "wof:name":"Ruth's Kitchen",
    "wof:placetype":"venue"
},
  "geometry": {"coordinates":[-71.126566,42.345172],"type":"Point"}
}