{
  "type": "Feature",
  "properties": {
    "iso:country":"US",
    "sg:address":"1476 River St",
    "sg:city":"Hyde Park",
    "sg:classifiers":[
        {
            "category":"Retail",
            "subcategory":"Auto Repair",
            "type":"Services"
        }
    ],
    "sg:phone":"+1   ",
    "sg:postcode":"02136",
    "sg:province":"MA",
    "sg:tags":[
        "parts",
        "rebuilds",
        "drive"
    ],
    "wof:name":"Silent Drive",
    "wof:placetype":"venue"
},
  "geometry": {"coordinates":[-71.13099200000001,42.250899],"type":"Point"}
}