{
  "type": "Feature",
  "properties": {
    "addr:full": "28 Fairhaven Rd Mattapoisett MA 02739",
    "addr:housenumber": "28",
    "addr:postcode": "02739",
    "addr:street": "Fairhaven Rd",
    "iso:country": "US",
    "sg:address": "28 Fairhaven Rd",
    "sg:city": "Mattapoisett",
    "sg:classifiers": [
      {
        "category": "Health Services",
        "subcategory": "Doctor",
        "type": "Services"
      }
    ],
    "sg:phone": "+1 508 758 4818",
    "sg:postcode": "02739",
    "sg:province": "MA",
    "sg:tags": [
      "dentist"
    ],
    "wof:name": "Louis P Kenyon DDS",
    "wof:placetype": "venue"
  },
  "geometry": {"coordinates":[-70.823421,41.660758],"type":"Point"}
}
