{
  "type": "Feature",
  "properties": {
    "addr:full":"340 Oak Grove Ave Fall River MA 02723",
    "addr:housenumber":"340",
    "addr:postcode":"02723",
    "addr:street":"Oak Grove Ave",
    "iso:country":"US",
    "sg:address":"340 Oak Grove Ave",
    "sg:city":"Fall River",
    "sg:classifiers":[
        {
            "category":"Food & Beverages",
            "subcategory":"Groceries & Convenience Stores",
            "type":"Retail Goods"
        }
    ],
    "sg:phone":"+1 508 678 5430",
    "sg:postcode":"02723",
    "sg:province":"MA",
    "wof:name":"New Way Mini Mart",
    "wof:placetype":"venue"
},
  "geometry": {"coordinates":[-71.13272499999999,41.703567],"type":"Point"}
}