{
  "type": "Feature",
  "properties": {
    "addr:full":"568 Broadway Everett MA 02149",
    "addr:housenumber":"568",
    "addr:postcode":"02149",
    "addr:street":"Broadway",
    "iso:country":"US",
    "sg:address":"568 Broadway",
    "sg:city":"Everett",
    "sg:classifiers":[
        {
            "category":"Personal",
            "subcategory":"Barber",
            "type":"Services"
        }
    ],
    "sg:phone":"+1 617 387 8110",
    "sg:postcode":"02149",
    "sg:province":"MA",
    "wof:name":"Casablanca Barber Shop",
    "wof:placetype":"venue"
},
  "geometry": {"coordinates":[-71.052059,42.41054],"type":"Point"}
}