{
  "type": "Feature",
  "properties": {
    "iso:country":"US",
    "sg:address":"3 Kneeland Rd",
    "sg:city":"Tewksbury",
    "sg:classifiers":[
        {
            "category":"Building & Trades",
            "subcategory":"Plumbing",
            "type":"Services"
        }
    ],
    "sg:phone":"+1   ",
    "sg:postcode":"01876",
    "sg:province":"MA",
    "sg:tags":[
        "contractor"
    ],
    "wof:name":"Clifford AC & Htg Co",
    "wof:placetype":"venue"
},
  "geometry": {"coordinates":[-71.197901,42.579017],"type":"Point"}
}