{
  "type": "Feature",
  "properties": {
    "addr:full": "3 Kneeland Rd Tewksbury MA 01876",
    "addr:housenumber": "3",
    "addr:postcode": "01876",
    "addr:street": "Kneeland Rd",
    "iso:country": "US",
    "sg:address": "3 Kneeland Rd",
    "sg:city": "Tewksbury",
    "sg:classifiers": [
      {
        "category": "Building \u0026 Trades",
        "subcategory": "Plumbing",
        "type": "Services"
      }
    ],
    "sg:phone": "+1   ",
    "sg:postcode": "01876",
    "sg:province": "MA",
    "sg:tags": [
      "contractor"
    ],
    "wof:name": "Clifford AC \u0026 Htg Co",
    "wof:placetype": "venue"
  },
  "geometry": {"coordinates":[-71.197901,42.579017],"type":"Point"}
}
