{
  "type": "Feature",
  "properties": {
    "addr:full": "7 Trapelo St Brighton MA 02135",
    "addr:housenumber": "7",
    "addr:postcode": "02135",
    "addr:street": "Trapelo St",
    "iso:country": "US",
    "sg:address": "7 Trapelo St",
    "sg:city": "Brighton",
    "sg:classifiers": [
      {
        "category": "Professional",
        "subcategory": "Art Services",
        "type": "Services"
      }
    ],
    "sg:phone": "+1   ",
    "sg:postcode": "02135",
    "sg:province": "MA",
    "sg:tags": [
      "commercial",
      "design"
    ],
    "wof:name": "Levy Pamela R Illustration",
    "wof:placetype": "venue"
  },
  "geometry": {"coordinates":[-71.161013,42.346714],"type":"Point"}
}
