{
  "type": "Feature",
  "properties": {
    "iso:country":"US",
    "sg:address":"800 Boylston St",
    "sg:city":"Boston",
    "sg:classifiers":[
        {
            "category":"Restaurant",
            "type":"Food & Drink"
        }
    ],
    "sg:menulink":"http://www.allmenus.com/ma/boston/1171-sarku-japan/menu/",
    "sg:phone":"+1 617 236 0009",
    "sg:postcode":"02199",
    "sg:province":"MA",
    "sg:tags":[
        "japanese",
        "asian"
    ],
    "wof:name":"Sarku Japan",
    "wof:placetype":"venue"
},
  "geometry": {"coordinates":[-71.08181399999999,42.348883],"type":"Point"}
}