{
  "type": "Feature",
  "properties": {
    "addr:full": "800 Boylston St Boston MA 02199",
    "addr:housenumber": "800",
    "addr:postcode": "02199",
    "addr:street": "Boylston St",
    "iso:country": "US",
    "sg:address": "800 Boylston St",
    "sg:city": "Boston",
    "sg:classifiers": [
      {
        "category": "Restaurant",
        "type": "Food \u0026 Drink"
      }
    ],
    "sg:menulink": "http://www.allmenus.com/ma/boston/1171-sarku-japan/menu/",
    "sg:phone": "+1 617 236 0009",
    "sg:postcode": "02199",
    "sg:province": "MA",
    "sg:tags": [
      "japanese",
      "asian"
    ],
    "wof:name": "Sarku Japan",
    "wof:placetype": "venue"
  },
  "geometry": {"coordinates":[-71.081814,42.348883],"type":"Point"}
}
