{
  "type": "Feature",
  "properties": {
    "iso:country":"US",
    "sg:address":"12 Channel St Ste 805",
    "sg:city":"Boston",
    "sg:classifiers":[
        {
            "category":"Shopping",
            "subcategory":"Party Supplies",
            "type":"Retail Goods"
        },
        {
            "category":"Retail",
            "subcategory":"Portrait Studio",
            "type":"Services"
        }
    ],
    "sg:phone":"+1 617 737 6060",
    "sg:postcode":"02210",
    "sg:province":"MA",
    "sg:tags":[
        "photography",
        "store"
    ],
    "sg:website":"www.madpropsboston.com",
    "wof:name":"Mad Props",
    "wof:placetype":"venue"
},
  "geometry": {"coordinates":[-71.037721,42.34514],"type":"Point"}
}