{
  "type": "Feature",
  "properties": {
    "addr:full":"547 Kelley Blvd North Attleboro MA 02760",
    "addr:housenumber":"547",
    "addr:postcode":"02760",
    "addr:street":"Kelley Blvd",
    "iso:country":"US",
    "sg:address":"547 Kelley Blvd",
    "sg:city":"North Attleboro",
    "sg:classifiers":[
        {
            "category":"Retail",
            "subcategory":"Auto Repair",
            "type":"Services"
        }
    ],
    "sg:phone":"+1 508 699 8983",
    "sg:postcode":"02760",
    "sg:province":"MA",
    "sg:tags":[
        "repairing",
        "automobile"
    ],
    "wof:name":"Speedee Oil Change & Tune Up",
    "wof:placetype":"venue"
},
  "geometry": {"coordinates":[-71.302888,42.008],"type":"Point"}
}