{
  "type": "Feature",
  "properties": {
    "addr:full": "265 N Pearl St Brockton MA 02301",
    "addr:housenumber": "265",
    "addr:postcode": "02301",
    "addr:street": "N Pearl St",
    "iso:country": "US",
    "sg:address": "265 N Pearl St",
    "sg:city": "Brockton",
    "sg:classifiers": [
      {
        "category": "Shopping",
        "subcategory": "Adult",
        "type": "Retail Goods"
      }
    ],
    "sg:phone": "+1 508 894 4040",
    "sg:postcode": "02301",
    "sg:province": "MA",
    "sg:tags": [
      "entertainment"
    ],
    "wof:name": "The Foxy Lady",
    "wof:placetype": "venue"
  },
  "geometry": {"coordinates":[-71.065804,42.096802],"type":"Point"}
}
