{
  "type": "Feature",
  "properties": {
    "iso:country":"US",
    "sg:address":"103 Esta Rd",
    "sg:city":"Plymouth",
    "sg:classifiers":[
        {
            "category":"Personal",
            "subcategory":"Beauty Salon",
            "type":"Services"
        }
    ],
    "sg:phone":"+1 781 249 7438",
    "sg:postcode":"02360",
    "sg:province":"MA",
    "wof:name":"Relaxation By Rae",
    "wof:placetype":"venue"
},
  "geometry": {"coordinates":[-70.731331,41.935059],"type":"Point"}
}