{
  "type": "Feature",
  "properties": {
    "addr:full":"567 Bennington St Boston MA 02128",
    "addr:housenumber":"567",
    "addr:postcode":"02128",
    "addr:street":"Bennington St",
    "iso:country":"US",
    "sg:address":"567 Bennington St",
    "sg:city":"Boston",
    "sg:classifiers":[
        {
            "category":"Food & Beverages",
            "subcategory":"Groceries & Convenience Stores",
            "type":"Retail Goods"
        }
    ],
    "sg:phone":"+1 617 567 0058",
    "sg:postcode":"02128",
    "sg:province":"MA",
    "sg:tags":[
        "market"
    ],
    "wof:name":"Carlo's Mkt & Cold Cut Ctr",
    "wof:placetype":"venue"
},
  "geometry": {"coordinates":[-71.016502,42.3834],"type":"Point"}
}