{
  "type": "Feature",
  "properties": {
    "addr:full":"31 Channing St Newton MA 02458",
    "addr:housenumber":"31",
    "addr:postcode":"02458",
    "addr:street":"Channing St",
    "iso:country":"US",
    "sg:address":"31 Channing St",
    "sg:city":"Newton",
    "sg:classifiers":[
        {
            "category":"Real Estate",
            "subcategory":"Real Estate Agent",
            "type":"Services"
        }
    ],
    "sg:phone":"+1 617 527 2709",
    "sg:postcode":"02458",
    "sg:province":"MA",
    "wof:name":"C A Houle Realty",
    "wof:placetype":"venue"
},
  "geometry": {"coordinates":[-71.187516,42.356702],"type":"Point"}
}