{
  "type": "Feature",
  "properties": {
    "iso:country":"US",
    "sg:address":"92 Cedar St",
    "sg:city":"Lexington",
    "sg:classifiers":[
        {
            "category":"Professional",
            "subcategory":"Management & Consulting",
            "type":"Services"
        }
    ],
    "sg:phone":"+1 781 862 1771",
    "sg:postcode":"02421",
    "sg:province":"MA",
    "sg:tags":[
        "consultant",
        "energy",
        "conservation",
        "business"
    ],
    "wof:name":"Arthur Orenberg Assoc Inc",
    "wof:placetype":"venue"
},
  "geometry": {"coordinates":[-71.247018,42.452171],"type":"Point"}
}