{
  "type": "Feature",
  "properties": {
    "iso:country":"US",
    "sg:address":"1408 Providence Hwy",
    "sg:city":"Norwood",
    "sg:classifiers":[
        {
            "category":"Organizations",
            "subcategory":"Professional Association",
            "type":"Services"
        }
    ],
    "sg:phone":"+1 781 278 0077",
    "sg:postcode":"02062",
    "sg:province":"MA",
    "wof:name":"Mass Independent Auto Dealers",
    "wof:placetype":"venue"
},
  "geometry": {"coordinates":[-71.198922,42.164012],"type":"Point"}
}