{
  "type": "Feature",
  "properties": {
    "addr:full":"14 Jacob Dr Mansfield MA 02048",
    "addr:housenumber":"14",
    "addr:postcode":"02048",
    "addr:street":"Jacob Dr",
    "iso:country":"US",
    "sg:address":"14 Jacob Dr",
    "sg:city":"Mansfield",
    "sg:classifiers":[
        {
            "category":"Building & Trades",
            "subcategory":"Plumbing",
            "type":"Services"
        }
    ],
    "sg:phone":"+1 508 339 8237",
    "sg:postcode":"02048",
    "sg:province":"MA",
    "wof:name":"Young Bob Plumbing & Heating",
    "wof:placetype":"venue"
},
  "geometry": {"coordinates":[-71.260498,42.0168],"type":"Point"}
}