{
  "type": "Feature",
  "properties": {
    "addr:full": "45 Granite St Leominster MA 01453",
    "addr:housenumber": "45",
    "addr:postcode": "01453",
    "addr:street": "Granite St",
    "iso:country": "US",
    "sg:address": "45 Granite St",
    "sg:city": "Leominster",
    "sg:classifiers": [
      {
        "category": "Recreation",
        "type": "Entertainment"
      }
    ],
    "sg:phone": "+1 978 840 2830",
    "sg:postcode": "01453",
    "sg:province": "MA",
    "sg:tags": [
      "amusement"
    ],
    "wof:name": "Myles Recreation Accessories",
    "wof:placetype": "venue"
  },
  "geometry": {"coordinates":[-71.774682,42.534414],"type":"Point"}
}
