{
  "type": "Feature",
  "properties": {
    "iso:country":"US",
    "sg:address":"133 Mariano Bishop Blvd",
    "sg:city":"Fall River",
    "sg:classifiers":[
        {
            "category":"Shopping",
            "subcategory":"Department Store",
            "type":"Retail Goods"
        }
    ],
    "sg:phone":"+1 508 646 0054",
    "sg:postcode":"02721",
    "sg:province":"MA",
    "wof:name":"Sears Roebuck & Co",
    "wof:placetype":"venue"
},
  "geometry": {"coordinates":[-71.163409,41.673717],"type":"Point"}
}