{
  "type": "Feature",
  "properties": {
    "iso:country":"US",
    "sg:address":"76 Judith Rd",
    "sg:city":"Newton Center",
    "sg:classifiers":[
        {
            "category":"Professional",
            "subcategory":"Management & Consulting",
            "type":"Services"
        }
    ],
    "sg:phone":"+1 617 332 5762",
    "sg:postcode":"02459",
    "sg:province":"MA",
    "sg:tags":[
        "consultant",
        "property",
        "business",
        "intellectual"
    ],
    "wof:name":"Techroadmap Inc",
    "wof:placetype":"venue"
},
  "geometry": {"coordinates":[-71.206591,42.334925],"type":"Point"}
}