{
  "type": "Feature",
  "properties": {
    "addr:full": "55 N Street Cir Walpole MA 02081",
    "addr:housenumber": "55",
    "addr:postcode": "02081",
    "addr:street": "N Street Cir",
    "iso:country": "US",
    "sg:address": "55 N Street Cir",
    "sg:city": "Walpole",
    "sg:classifiers": [
      {
        "category": "Organizations",
        "subcategory": "Non-profit Organization",
        "type": "Services"
      }
    ],
    "sg:phone": "+1 508 668 1066",
    "sg:postcode": "02081",
    "sg:province": "MA",
    "wof:name": "Walpole Area Visiting Nurse",
    "wof:placetype": "venue"
  },
  "geometry": {"coordinates":[-71.249761,42.161588],"type":"Point"}
}
