{
  "type": "Feature",
  "properties": {
    "addr:full":"122 Turnpike Road Suite 6 Westborough MA 01581",
    "addr:housenumber":"122",
    "addr:postcode":"01581",
    "addr:street":"Turnpike Road Suite 6",
    "iso:country":"US",
    "sg:address":"122 Turnpike Road Suite 6",
    "sg:city":"Westborough",
    "sg:classifiers":[
        {
            "category":"Personal",
            "subcategory":"Nail Salon",
            "type":"Services"
        }
    ],
    "sg:phone":"+1 508 389 9995",
    "sg:postcode":"01581",
    "sg:province":"MA",
    "sg:website":"http://mamasndivas.com",
    "wof:name":"Mamas n Divas Nail Lounge",
    "wof:placetype":"venue"
},
  "geometry": {"coordinates":[-71.605009,42.284941],"type":"Point"}
}