{
  "type": "Feature",
  "properties": {
    "addr:full":"392 Whitlow St New Bedford MA 02746",
    "addr:housenumber":"392",
    "addr:postcode":"02746",
    "addr:street":"Whitlow St",
    "iso:country":"US",
    "sg:address":"392 Whitlow St",
    "sg:city":"New Bedford",
    "sg:classifiers":[
        {
            "category":"Building & Trades",
            "subcategory":"Construction",
            "type":"Services"
        }
    ],
    "sg:phone":"+1   ",
    "sg:postcode":"02746",
    "sg:province":"MA",
    "sg:tags":[
        "hanging",
        "contractor"
    ],
    "wof:name":"C & T Home Care Service",
    "wof:placetype":"venue"
},
  "geometry": {"coordinates":[-70.951527,41.657527],"type":"Point"}
}