{
  "type": "Feature",
  "properties": {
    "addr:full":"45 West Newton St Boston MA 02118",
    "addr:housenumber":"45",
    "addr:postcode":"02118",
    "addr:street":"West Newton St",
    "iso:country":"US",
    "sg:address":"45 West Newton St",
    "sg:city":"Boston",
    "sg:classifiers":[
        {
            "category":"Real Estate",
            "subcategory":"Real Estate Operator",
            "type":"Services"
        }
    ],
    "sg:phone":"+1 617 369 9400",
    "sg:postcode":"02118",
    "sg:province":"MA",
    "sg:tags":[
        "apartment"
    ],
    "wof:name":"Fulton Properties",
    "wof:placetype":"venue"
},
  "geometry": {"coordinates":[-71.072294,42.337566],"type":"Point"}
}