{
  "type": "Feature",
  "properties": {
    "addr:full": "50 Commerce Way Norton MA 02766",
    "addr:housenumber": "50",
    "addr:postcode": "02766",
    "addr:street": "Commerce Way",
    "iso:country": "US",
    "sg:address": "50 Commerce Way",
    "sg:city": "Norton",
    "sg:classifiers": [
      {
        "category": "Real Estate",
        "subcategory": "Real Estate Operator",
        "type": "Services"
      }
    ],
    "sg:phone": "+1 508 285 3381",
    "sg:postcode": "02766",
    "sg:province": "MA",
    "sg:tags": [
      "apartment"
    ],
    "wof:name": "The Flatley Co",
    "wof:placetype": "venue"
  },
  "geometry": {"coordinates":[-71.138704,41.957072],"type":"Point"}
}
