{
  "type": "Feature",
  "properties": {
    "addr:full":"25 School St. Quincy MA 02169",
    "addr:housenumber":"25",
    "addr:postcode":"02169",
    "addr:street":"School St.",
    "iso:country":"US",
    "sg:address":"25 School St.",
    "sg:city":"Quincy",
    "sg:classifiers":[
        {
            "category":"Professional",
            "subcategory":"Computer Services",
            "type":"Services"
        }
    ],
    "sg:phone":"+1 617 934 0822",
    "sg:postcode":"02169",
    "sg:province":"MA",
    "sg:tags":[
        "e-commerce",
        "comparison-shopping-engines",
        "order-status",
        "x-cart",
        "shopping-cart",
        "cse",
        "mail-order-manager"
    ],
    "sg:website":"http://www.freeportway.com",
    "wof:name":"Freeportway",
    "wof:placetype":"venue"
},
  "geometry": {"coordinates":[-71.00102,42.24503],"type":"Point"}
}