{
  "type": "Feature",
  "properties": {
    "addr:full":"167 Highland Ave Watertown MA 02472",
    "addr:housenumber":"167",
    "addr:postcode":"02472",
    "addr:street":"Highland Ave",
    "iso:country":"US",
    "sg:address":"167 Highland Ave",
    "sg:city":"Watertown",
    "sg:classifiers":[
        {
            "category":"Professional",
            "subcategory":"Lawyer & Legal Services",
            "type":"Services"
        }
    ],
    "sg:phone":"+1   ",
    "sg:postcode":"02472",
    "sg:province":"MA",
    "sg:tags":[
        "development",
        "construction",
        "for",
        "contract"
    ],
    "wof:name":"Julie A Ahern Attorney",
    "wof:placetype":"venue"
},
  "geometry": {"coordinates":[-71.200841,42.375394],"type":"Point"}
}