{
  "type": "Feature",
  "properties": {
    "addr:full":"18 Tripp St Framingham MA 01702",
    "addr:housenumber":"18",
    "addr:postcode":"01702",
    "addr:street":"Tripp St",
    "iso:country":"US",
    "sg:address":"18 Tripp St",
    "sg:city":"Framingham",
    "sg:classifiers":[
        {
            "category":"Wholesale",
            "subcategory":"Stationery",
            "type":"Manufacturing & Wholesale Goods"
        }
    ],
    "sg:phone":"+1 508 879 1141",
    "sg:postcode":"01702",
    "sg:province":"MA",
    "sg:tags":[
        "core",
        "tube",
        "paper"
    ],
    "sg:website":"www.americanpaperproducts.com",
    "wof:name":"American Paper Products",
    "wof:placetype":"venue"
},
  "geometry": {"coordinates":[-71.411976,42.268218],"type":"Point"}
}