{
  "type": "Feature",
  "properties": {
    "addr:full":"1415 Beacon St Brookline MA 02446",
    "addr:housenumber":"1415",
    "addr:postcode":"02446",
    "addr:street":"Beacon St",
    "iso:country":"US",
    "sg:address":"1415 Beacon St",
    "sg:city":"Brookline",
    "sg:classifiers":[
        {
            "category":"Health Services",
            "subcategory":"Health Practitioner",
            "type":"Services"
        }
    ],
    "sg:phone":"+1   ",
    "sg:postcode":"02446",
    "sg:province":"MA",
    "wof:name":"Susan Silveira",
    "wof:placetype":"venue"
},
  "geometry": {"coordinates":[-71.12563,42.340903],"type":"Point"}
}