{
  "type": "Feature",
  "properties": {
    "addr:full": "3 Dodge St Salem MA 01970",
    "addr:housenumber": "3",
    "addr:postcode": "01970",
    "addr:street": "Dodge St",
    "iso:country": "US",
    "sg:address": "3 Dodge St",
    "sg:city": "Salem",
    "sg:classifiers": [
      {
        "category": "Manufacturing",
        "subcategory": "Printing",
        "type": "Manufacturing \u0026 Wholesale Goods"
      }
    ],
    "sg:phone": "+1 978 744 2152",
    "sg:postcode": "01970",
    "sg:province": "MA",
    "sg:tags": [
      "commercial"
    ],
    "sg:website": "www.deschampsprinting.com",
    "wof:name": "Deschamps Printing Co Inc",
    "wof:placetype": "venue"
  },
  "geometry": {"coordinates":[-70.894146,42.518847],"type":"Point"}
}
