{
  "type": "Feature",
  "properties": {
    "iso:country":"US",
    "sg:address":"19 Pillings Rd",
    "sg:city":"Saugus",
    "sg:classifiers":[
        {
            "category":"Building & Trades",
            "subcategory":"Landscaping Services",
            "type":"Services"
        }
    ],
    "sg:phone":"+1 781 233 1915",
    "sg:postcode":"01906",
    "sg:province":"MA",
    "sg:tags":[
        "landscape",
        "contractor"
    ],
    "wof:name":"All Seasons Landscaping Inc",
    "wof:placetype":"venue"
},
  "geometry": {"coordinates":[-71.01000000000001,42.472736],"type":"Point"}
}