{
  "type": "Feature",
  "properties": {
    "addr:full": "917 Lynnfield St Lynn MA 01904",
    "addr:housenumber": "917",
    "addr:postcode": "01904",
    "addr:street": "Lynnfield St",
    "iso:country": "US",
    "sg:address": "917 Lynnfield St",
    "sg:city": "Lynn",
    "sg:classifiers": [
      {
        "category": "Professional",
        "type": "Services"
      }
    ],
    "sg:phone": "+1 781 592 6757",
    "sg:postcode": "01904",
    "sg:province": "MA",
    "sg:tags": [
      "establishment"
    ],
    "wof:name": "Lyndun LLC",
    "wof:placetype": "venue"
  },
  "geometry": {"coordinates":[-70.991731,42.511376],"type":"Point"}
}
