{
  "type": "Feature",
  "properties": {
    "iso:country":"US",
    "sg:address":"917 Lynnfield St",
    "sg:city":"Lynn",
    "sg:classifiers":[
        {
            "category":"Professional",
            "type":"Services"
        }
    ],
    "sg:phone":"+1 781 592 6757",
    "sg:postcode":"01904",
    "sg:province":"MA",
    "sg:tags":[
        "establishment"
    ],
    "wof:name":"Lyndun LLC",
    "wof:placetype":"venue"
},
  "geometry": {"coordinates":[-70.991731,42.511376],"type":"Point"}
}