{
  "type": "Feature",
  "properties": {
    "addr:full": "15 Indian Dawn Wayland MA 01778",
    "addr:housenumber": "15",
    "addr:postcode": "01778",
    "addr:street": "Indian Dawn",
    "iso:country": "US",
    "sg:address": "15 Indian Dawn",
    "sg:city": "Wayland",
    "sg:classifiers": [
      {
        "category": "Professional",
        "subcategory": "Management \u0026 Consulting",
        "type": "Services"
      }
    ],
    "sg:phone": "+1   ",
    "sg:postcode": "01778",
    "sg:province": "MA",
    "wof:name": "Mainstone Advisors",
    "wof:placetype": "venue"
  },
  "geometry": {"coordinates":[-71.331447,42.335451],"type":"Point"}
}
