{
  "type": "Feature",
  "properties": {
    "iso:country":"US",
    "sg:address":"15 Indian Dawn",
    "sg:city":"Wayland",
    "sg:classifiers":[
        {
            "category":"Professional",
            "subcategory":"Management & Consulting",
            "type":"Services"
        }
    ],
    "sg:phone":"+1   ",
    "sg:postcode":"01778",
    "sg:province":"MA",
    "wof:name":"Mainstone Advisors",
    "wof:placetype":"venue"
},
  "geometry": {"coordinates":[-71.331447,42.335451],"type":"Point"}
}