{
  "type": "Feature",
  "properties": {
    "iso:country":"US",
    "sg:address":"96 Main St",
    "sg:city":"Medway",
    "sg:classifiers":[
        {
            "category":"Manufacturing",
            "subcategory":"Printing",
            "type":"Manufacturing & Wholesale Goods"
        }
    ],
    "sg:phone":"+1 508 533 7411",
    "sg:postcode":"02053",
    "sg:province":"MA",
    "sg:tags":[
        "printer"
    ],
    "wof:name":"Ad-Print",
    "wof:placetype":"venue"
},
  "geometry": {"coordinates":[-71.413083,42.150983],"type":"Point"}
}