{
  "type": "Feature",
  "properties": {
    "addr:full": "450 Washington St Boston MA 02111",
    "addr:housenumber": "450",
    "addr:postcode": "02111",
    "addr:street": "Washington St",
    "iso:country": "US",
    "sg:address": "450 Washington St",
    "sg:city": "Boston",
    "sg:classifiers": [
      {
        "category": "Utilities",
        "subcategory": "Telephone",
        "type": "Services"
      },
      {
        "category": "Professional",
        "subcategory": "Computer Services",
        "type": "Services"
      }
    ],
    "sg:phone": "+1 617 542 6973",
    "sg:postcode": "02111",
    "sg:province": "MA",
    "sg:tags": [
      "telecommunication"
    ],
    "sg:website": "http://www.att.com",
    "wof:name": "AT\u0026T Communications",
    "wof:placetype": "venue"
  },
  "geometry": {"coordinates":[-71.060827,42.355083],"type":"Point"}
}
