{
  "type": "Feature",
  "properties": {
    "iso:country":"US",
    "sg:address":"18 Logan Airport Svc Rd",
    "sg:city":"East Boston",
    "sg:classifiers":[
        {
            "category":"Shopping",
            "subcategory":"Gifts & Souvenirs",
            "type":"Retail Goods"
        }
    ],
    "sg:phone":"+1 617 567 2994",
    "sg:postcode":"02128",
    "sg:province":"MA",
    "wof:name":"Boston Store",
    "wof:placetype":"venue"
},
  "geometry": {"coordinates":[-71.025808,42.375601],"type":"Point"}
}