{
  "type": "Feature",
  "properties": {
    "iso:country":"US",
    "sg:address":"226 Highland Ave",
    "sg:city":"Somerville",
    "sg:classifiers":[
        {
            "category":"Health Services",
            "subcategory":"Health Practitioner",
            "type":"Services"
        }
    ],
    "sg:phone":"+1 617 591 8688",
    "sg:postcode":"02143",
    "sg:province":"MA",
    "sg:tags":[
        "acupuncture"
    ],
    "wof:name":"Ching Ling Kung Acupuncture",
    "wof:placetype":"venue"
},
  "geometry": {"coordinates":[-71.108323,42.390222],"type":"Point"}
}