{
  "type": "Feature",
  "properties": {
    "addr:full": "1 Exchange Pl Boston MA 02109",
    "addr:housenumber": "1",
    "addr:postcode": "02109",
    "addr:street": "Exchange Pl",
    "iso:country": "US",
    "sg:address": "1 Exchange Pl",
    "sg:city": "Boston",
    "sg:classifiers": [
      {
        "category": "Professional",
        "subcategory": "Lawyer \u0026 Legal Services",
        "type": "Services"
      }
    ],
    "sg:phone": "+1 617 570 1559",
    "sg:postcode": "02109",
    "sg:province": "MA",
    "sg:tags": [
      "attorney",
      "practice",
      "plan"
    ],
    "wof:name": "Elizabeth Shea Fries",
    "wof:placetype": "venue"
  },
  "geometry": {"coordinates":[-71.056488,42.35804],"type":"Point"}
}
