{
  "type": "Feature",
  "properties": {
    "iso:country":"US",
    "sg:address":"171 Brockton Ave Ste C",
    "sg:city":"Abington",
    "sg:classifiers":[
        {
            "category":"Personal",
            "subcategory":"Beauty Salon",
            "type":"Services"
        }
    ],
    "sg:phone":"+1 781 871 3999",
    "sg:postcode":"02351",
    "sg:province":"MA",
    "wof:name":"Cindy's Full Service Salon",
    "wof:placetype":"venue"
},
  "geometry": {"coordinates":[-70.952099,42.105352],"type":"Point"}
}