{
  "type": "Feature",
  "properties": {
    "iso:country":"US",
    "sg:address":"14 Monmouth St",
    "sg:city":"Boston",
    "sg:classifiers":[
        {
            "category":"Building & Trades",
            "subcategory":"Plumbing",
            "type":"Services"
        }
    ],
    "sg:phone":"+1 617 436 0353",
    "sg:postcode":"02128",
    "sg:province":"MA",
    "sg:tags":[
        "plumber",
        "industrial",
        "contractors-commercial"
    ],
    "wof:name":"Neponset Plumbing Inc",
    "wof:placetype":"venue"
},
  "geometry": {"coordinates":[-71.03860299999999,42.379704],"type":"Point"}
}