{
  "type": "Feature",
  "properties": {
    "addr:full": "14 Monmouth St Boston MA 02128",
    "addr:housenumber": "14",
    "addr:postcode": "02128",
    "addr:street": "Monmouth St",
    "iso:country": "US",
    "sg:address": "14 Monmouth St",
    "sg:city": "Boston",
    "sg:classifiers": [
      {
        "category": "Building \u0026 Trades",
        "subcategory": "Plumbing",
        "type": "Services"
      }
    ],
    "sg:phone": "+1 617 436 0353",
    "sg:postcode": "02128",
    "sg:province": "MA",
    "sg:tags": [
      "plumber",
      "industrial",
      "contractors-commercial"
    ],
    "wof:name": "Neponset Plumbing Inc",
    "wof:placetype": "venue"
  },
  "geometry": {"coordinates":[-71.038603,42.379704],"type":"Point"}
}
