{
  "type": "Feature",
  "properties": {
    "iso:country":"US",
    "sg:address":"22 Vine St",
    "sg:city":"Gloucester",
    "sg:classifiers":[
        {
            "category":"Real Estate",
            "subcategory":"Real Estate Agent",
            "type":"Services"
        }
    ],
    "sg:phone":"+1 978 283 2070",
    "sg:postcode":"01930",
    "sg:province":"MA",
    "sg:tags":[
        "appraiser"
    ],
    "wof:name":"Stroman Associates",
    "wof:placetype":"venue"
},
  "geometry": {"coordinates":[-70.67354,42.643358],"type":"Point"}
}