{
  "type": "Feature",
  "properties": {
    "iso:country":"US",
    "sg:address":"90 Adams St",
    "sg:city":"Milton",
    "sg:classifiers":[
        {
            "category":"Building & Trades",
            "subcategory":"Plumbing",
            "type":"Services"
        }
    ],
    "sg:phone":"+1 617 698 0631",
    "sg:postcode":"02186",
    "sg:province":"MA",
    "sg:tags":[
        "plumbing",
        "contractor"
    ],
    "wof:name":"F A King & Sons",
    "wof:placetype":"venue"
},
  "geometry": {"coordinates":[-71.067669,42.270135],"type":"Point"}
}