{
  "type": "Feature",
  "properties": {
    "addr:full":"25 Grant St Cambridge MA 02138",
    "addr:housenumber":"25",
    "addr:postcode":"02138",
    "addr:street":"Grant St",
    "iso:country":"US",
    "sg:address":"25 Grant St",
    "sg:city":"Cambridge",
    "sg:classifiers":[
        {
            "category":"Professional",
            "subcategory":"Research",
            "type":"Services"
        }
    ],
    "sg:phone":"+1   ",
    "sg:postcode":"02138",
    "sg:province":"MA",
    "sg:tags":[
        "nonphysical",
        "commercial"
    ],
    "wof:name":"Institute For Parallel Studies",
    "wof:placetype":"venue"
},
  "geometry": {"coordinates":[-71.116686,42.369966],"type":"Point"}
}