{
  "type": "Feature",
  "properties": {
    "iso:country":"US",
    "sg:address":"16 Bourbon St",
    "sg:city":"Peabody",
    "sg:classifiers":[
        {
            "category":"Wholesale",
            "subcategory":"Office Equipment",
            "type":"Manufacturing & Wholesale Goods"
        }
    ],
    "sg:phone":"+1 978 535 5141",
    "sg:postcode":"01960",
    "sg:province":"MA",
    "sg:tags":[
        "machine",
        "duplicating",
        "copying"
    ],
    "wof:name":"Complete Copier Sales & Svc",
    "wof:placetype":"venue"
},
  "geometry": {"coordinates":[-70.976866,42.549618],"type":"Point"}
}