{
  "type": "Feature",
  "properties": {
    "iso:country":"US",
    "sg:address":"25 Huntington Ave",
    "sg:city":"Boston",
    "sg:classifiers":[
        {
            "category":"Banks & Credit Unions",
            "subcategory":"Investment Brokerage",
            "type":"Services"
        }
    ],
    "sg:phone":"+1 617 424 8252",
    "sg:postcode":"02116",
    "sg:province":"MA",
    "sg:tags":[
        "investing"
    ],
    "wof:name":"New England Finance & Investment",
    "wof:placetype":"venue"
},
  "geometry": {"coordinates":[-71.077003,42.349098],"type":"Point"}
}