{
  "type": "Feature",
  "properties": {
    "iso:country":"US",
    "sg:address":"5 Market Sq",
    "sg:city":"Amesbury",
    "sg:classifiers":[
        {
            "category":"Health Services",
            "subcategory":"Health Practitioner",
            "type":"Services"
        }
    ],
    "sg:phone":"+1 978 388 0022",
    "sg:postcode":"01913",
    "sg:province":"MA",
    "sg:tags":[
        "psychologist"
    ],
    "wof:name":"Seacoast Counseling Ctr Inc",
    "wof:placetype":"venue"
},
  "geometry": {"coordinates":[-70.92862,42.866599],"type":"Point"}
}