{
  "type": "Feature",
  "properties": {
    "addr:full":"35 Wallis St Douglas MA 01516",
    "addr:housenumber":"35",
    "addr:postcode":"01516",
    "addr:street":"Wallis St",
    "iso:country":"US",
    "sg:address":"35 Wallis St",
    "sg:city":"Douglas",
    "sg:classifiers":[
        {
            "category":"Wholesale",
            "subcategory":"Auto Parts",
            "type":"Manufacturing & Wholesale Goods"
        }
    ],
    "sg:phone":"+1 508 476 4400",
    "sg:postcode":"01516",
    "sg:province":"MA",
    "sg:tags":[
        "automobile"
    ],
    "wof:name":"Toke Products Inc",
    "wof:placetype":"venue"
},
  "geometry": {"coordinates":[-71.763452,42.059355],"type":"Point"}
}