{
  "type": "Feature",
  "properties": {
    "addr:full": "326 A St Unit 5B Boston MA 02210",
    "addr:housenumber": "326;5b",
    "addr:postcode": "02210",
    "addr:street": "A St Unit",
    "iso:country": "US",
    "sg:address": "326 A St Unit 5B",
    "sg:city": "Boston",
    "sg:classifiers": [
      {
        "category": "Shopping",
        "subcategory": "Florist",
        "type": "Retail Goods"
      }
    ],
    "sg:phone": "+1 617 413 9790",
    "sg:postcode": "02210",
    "sg:province": "MA",
    "sg:website": "www.florallab.com",
    "wof:name": "Floral Lab",
    "wof:placetype": "venue"
  },
  "geometry": {"coordinates":[-71.049358,42.349233],"type":"Point"}
}
