{
  "type": "Feature",
  "properties": {
    "addr:full": "750 Washington St Boston MA 02111",
    "addr:housenumber": "750",
    "addr:postcode": "02111",
    "addr:street": "Washington St",
    "iso:country": "US",
    "sg:address": "750 Washington St",
    "sg:city": "Boston",
    "sg:classifiers": [
      {
        "category": "Health Services",
        "subcategory": "Medical Lab",
        "type": "Services"
      },
      {
        "category": "Insurance",
        "subcategory": "Health Insurance",
        "type": "Services"
      }
    ],
    "sg:phone": "+1 617 636 8683",
    "sg:postcode": "02111",
    "sg:province": "MA",
    "sg:tags": [
      "maintenance"
    ],
    "wof:name": "International Pediatric Association",
    "wof:placetype": "venue"
  },
  "geometry": {"coordinates":[-71.063583,42.349751],"type":"Point"}
}
