{
  "type": "Feature",
  "properties": {
    "addr:full":"24 Washington St Gloucester MA 01930",
    "addr:housenumber":"24",
    "addr:postcode":"01930",
    "addr:street":"Washington St",
    "iso:country":"US",
    "sg:address":"24 Washington St",
    "sg:city":"Gloucester",
    "sg:classifiers":[
        {
            "category":"Food & Beverages",
            "subcategory":"Bakery",
            "type":"Retail Goods"
        }
    ],
    "sg:phone":"+1 978 283 3383",
    "sg:postcode":"01930",
    "sg:province":"MA",
    "sg:tags":[
        "baker"
    ],
    "wof:name":"Jim's Bagel & Bake Shoppe",
    "wof:placetype":"venue"
},
  "geometry": {"coordinates":[-70.66748699999999,42.612689],"type":"Point"}
}