{
  "type": "Feature",
  "properties": {
    "addr:full": "27 Beloit Rd Dedham MA 02026",
    "addr:housenumber": "27",
    "addr:postcode": "02026",
    "addr:street": "Beloit Rd",
    "iso:country": "US",
    "sg:address": "27 Beloit Rd",
    "sg:city": "Dedham",
    "sg:classifiers": [
      {
        "category": "Manufacturing",
        "subcategory": "Glass \u0026 Minerals",
        "type": "Manufacturing \u0026 Wholesale Goods"
      }
    ],
    "sg:phone": "+1   ",
    "sg:postcode": "02026",
    "sg:province": "MA",
    "sg:tags": [
      "product",
      "mfg"
    ],
    "wof:name": "Dunrite Glass",
    "wof:placetype": "venue"
  },
  "geometry": {"coordinates":[-71.141642,42.228017],"type":"Point"}
}
