{
  "type": "Feature",
  "properties": {
    "addr:full": "79 Beach Rd Vineyard Haven MA 02568",
    "addr:housenumber": "79",
    "addr:postcode": "02568",
    "addr:street": "Beach Rd",
    "iso:country": "US",
    "sg:address": "79 Beach Rd",
    "sg:city": "Vineyard Haven",
    "sg:classifiers": [
      {
        "category": "Health Services",
        "subcategory": "Doctor",
        "type": "Services"
      }
    ],
    "sg:phone": "+1 508 693 7300",
    "sg:postcode": "02568",
    "sg:province": "MA",
    "sg:tags": [
      "dentist"
    ],
    "wof:name": "Steven G Mills DDS",
    "wof:placetype": "venue"
  },
  "geometry": {"coordinates":[-70.591425,41.456049],"type":"Point"}
}
