{
  "type": "Feature",
  "properties": {
    "iso:country":"US",
    "sg:address":"347 Prospect St",
    "sg:city":"Brockton",
    "sg:classifiers":[
        {
            "category":"Professional",
            "subcategory":"Computer Services",
            "type":"Services"
        }
    ],
    "sg:phone":"+1   ",
    "sg:postcode":"02301",
    "sg:province":"MA",
    "sg:tags":[
        "datum"
    ],
    "wof:name":"Stephen Cords",
    "wof:placetype":"venue"
},
  "geometry": {"coordinates":[-71.03719700000001,42.090222],"type":"Point"}
}