{
  "type": "Feature",
  "properties": {
    "addr:full": "32 Town Farm Rd Ipswich MA 01938",
    "addr:housenumber": "32",
    "addr:postcode": "01938",
    "addr:street": "Town Farm Rd",
    "iso:country": "US",
    "sg:address": "32 Town Farm Rd",
    "sg:city": "Ipswich",
    "sg:classifiers": [
      {
        "category": "Building \u0026 Trades",
        "subcategory": "Plumbing",
        "type": "Services"
      }
    ],
    "sg:phone": "+1 978 356 8919",
    "sg:postcode": "01938",
    "sg:province": "MA",
    "sg:tags": [
      "plumber",
      "industrial",
      "contractors-commercial"
    ],
    "wof:name": "Roto Rooter Plumbing \u0026 Drain Services",
    "wof:placetype": "venue"
  },
  "geometry": {"coordinates":[-70.84449,42.690947],"type":"Point"}
}
