{
  "type": "Feature",
  "properties": {
    "iso:country":"US",
    "sg:address":"32 Town Farm Rd",
    "sg:city":"Ipswich",
    "sg:classifiers":[
        {
            "category":"Building & Trades",
            "subcategory":"Plumbing",
            "type":"Services"
        }
    ],
    "sg:phone":"+1 978 356 8919",
    "sg:postcode":"01938",
    "sg:province":"MA",
    "sg:tags":[
        "plumber",
        "industrial",
        "contractors-commercial"
    ],
    "wof:name":"Roto Rooter Plumbing & Drain Services",
    "wof:placetype":"venue"
},
  "geometry": {"coordinates":[-70.84448999999999,42.690947],"type":"Point"}
}