{
  "type": "Feature",
  "properties": {
    "addr:full":"123 Marion St Brookline MA 02446",
    "addr:housenumber":"123",
    "addr:postcode":"02446",
    "addr:street":"Marion St",
    "iso:country":"US",
    "sg:address":"123 Marion St",
    "sg:city":"Brookline",
    "sg:classifiers":[
        {
            "category":"Social Services",
            "type":"Services"
        }
    ],
    "sg:phone":"+1 617 566 6555",
    "sg:postcode":"02446",
    "sg:province":"MA",
    "sg:tags":[
        "organization",
        "welfare"
    ],
    "wof:name":"Parent Child Ctr-Life Studies",
    "wof:placetype":"venue"
},
  "geometry": {"coordinates":[-71.12660200000001,42.340508],"type":"Point"}
}