{
  "type": "Feature",
  "properties": {
    "addr:full": "16 Neponset St Norwood MA 02062",
    "addr:housenumber": "16",
    "addr:postcode": "02062",
    "addr:street": "Neponset St",
    "iso:country": "US",
    "sg:address": "16 Neponset St",
    "sg:city": "Norwood",
    "sg:classifiers": [
      {
        "category": "Building \u0026 Trades",
        "subcategory": "Locksmith",
        "type": "Services"
      }
    ],
    "sg:phone": "+1 781 680 3002",
    "sg:postcode": "02062",
    "sg:province": "MA",
    "sg:tags": [
      "key"
    ],
    "wof:name": "Yale Locksmith",
    "wof:placetype": "venue"
  },
  "geometry": {"coordinates":[-71.192778,42.206697],"type":"Point"}
}
