{
  "type": "Feature",
  "properties": {
    "addr:full":"429 Maple St Bellingham MA 02019",
    "addr:housenumber":"429",
    "addr:postcode":"02019",
    "addr:street":"Maple St",
    "iso:country":"US",
    "sg:address":"429 Maple St",
    "sg:city":"Bellingham",
    "sg:classifiers":[
        {
            "category":"Building & Trades",
            "subcategory":"Construction",
            "type":"Services"
        }
    ],
    "sg:phone":"+1 508 966 4244",
    "sg:postcode":"02019",
    "sg:province":"MA",
    "sg:tags":[
        "material",
        "paving"
    ],
    "wof:name":"Bevilacqua Asphalt",
    "wof:placetype":"venue"
},
  "geometry": {"coordinates":[-71.452274,42.085539],"type":"Point"}
}