{
  "type": "Feature",
  "properties": {
    "addr:full":"485 Merrimack Ave Dracut MA 01826",
    "addr:housenumber":"485",
    "addr:postcode":"01826",
    "addr:street":"Merrimack Ave",
    "iso:country":"US",
    "sg:address":"485 Merrimack Ave",
    "sg:city":"Dracut",
    "sg:classifiers":[
        {
            "category":"Retail",
            "subcategory":"Auto Repair",
            "type":"Services"
        }
    ],
    "sg:phone":"+1 978 970 2800",
    "sg:postcode":"01826",
    "sg:province":"MA",
    "sg:tags":[
        "repairing",
        "automobile"
    ],
    "wof:name":"Merrimac Valley Svc",
    "wof:placetype":"venue"
},
  "geometry": {"coordinates":[-71.269429,42.658012],"type":"Point"}
}