{
  "type": "Feature",
  "properties": {
    "iso:country":"US",
    "sg:address":"255 North St",
    "sg:city":"Pittsfield",
    "sg:classifiers":[
        {
            "category":"Autos & Motor Vehicles",
            "subcategory":"Automobile Sales",
            "type":"Retail Goods"
        }
    ],
    "sg:phone":"+1 413 448 2927",
    "sg:postcode":"01201",
    "sg:province":"MA",
    "sg:tags":[
        "car",
        "dealer"
    ],
    "wof:name":"Wholesale Auto",
    "wof:placetype":"venue"
},
  "geometry": {"coordinates":[-73.25311499999999,42.451836],"type":"Point"}
}