{
  "type": "Feature",
  "properties": {
    "iso:country":"US",
    "sg:address":"26 Otis St",
    "sg:city":"Mansfield",
    "sg:classifiers":[
        {
            "category":"Food & Beverages",
            "subcategory":"Candy",
            "type":"Retail Goods"
        },
        {
            "category":"Home & Garden",
            "subcategory":"Home Furnishings",
            "type":"Retail Goods"
        },
        {
            "category":"Restaurant",
            "type":"Food & Drink"
        },
        {
            "category":"Shopping",
            "subcategory":"Antiques",
            "type":"Retail Goods"
        },
        {
            "category":"Home & Garden",
            "subcategory":"Furniture",
            "type":"Retail Goods"
        }
    ],
    "sg:phone":"+1 508 339 8128",
    "sg:postcode":"02048",
    "sg:province":"MA",
    "sg:tags":[
        "decor",
        "local",
        "flavor",
        "store"
    ],
    "wof:name":"Mansfield Country Store",
    "wof:placetype":"venue"
},
  "geometry": {"coordinates":[-71.245458,41.997397],"type":"Point"}
}