{
  "type": "Feature",
  "properties": {
    "iso:country":"US",
    "sg:address":"1 Merrimac St",
    "sg:city":"Newburyport",
    "sg:classifiers":[
        {
            "category":"Banks & Credit Unions",
            "subcategory":"Investment Brokerage",
            "type":"Services"
        }
    ],
    "sg:phone":"+1 978 462 0500",
    "sg:postcode":"01950",
    "sg:province":"MA",
    "sg:tags":[
        "stock",
        "bond"
    ],
    "wof:name":"Raymond James Financial Svc",
    "wof:placetype":"venue"
},
  "geometry": {"coordinates":[-70.87105699999999,42.811817],"type":"Point"}
}