{
  "type": "Feature",
  "properties": {
    "iso:country":"US",
    "sg:address":"9 N Main St",
    "sg:city":"Florence",
    "sg:classifiers":[
        {
            "category":"Personal",
            "subcategory":"Beauty Salon",
            "type":"Services"
        }
    ],
    "sg:phone":"+1 413 584 6165",
    "sg:postcode":"01062",
    "sg:province":"MA",
    "sg:tags":[
        "shop"
    ],
    "wof:name":"Modern Image Salon",
    "wof:placetype":"venue"
},
  "geometry": {"coordinates":[-72.671966,42.335522],"type":"Point"}
}