{
  "type": "Feature",
  "properties": {
    "addr:full": "4 Highland Ave Wakefield MA 01880",
    "addr:housenumber": "4",
    "addr:postcode": "01880",
    "addr:street": "Highland Ave",
    "iso:country": "US",
    "sg:address": "4 Highland Ave",
    "sg:city": "Wakefield",
    "sg:classifiers": [
      {
        "category": "Real Estate",
        "subcategory": "Surveying",
        "type": "Services"
      }
    ],
    "sg:phone": "+1 781 395 7662",
    "sg:postcode": "01880",
    "sg:province": "MA",
    "sg:tags": [
      "surveyor"
    ],
    "wof:name": "Pjf \u0026 Assoc",
    "wof:placetype": "venue"
  },
  "geometry": {"coordinates":[-71.08238,42.498674],"type":"Point"}
}
