{
  "type": "Feature",
  "properties": {
    "addr:full":"150 Quincy Shore Dr # 16 Quincy MA 02171",
    "addr:housenumber":"150;16",
    "addr:postcode":"02171",
    "addr:street":"Quincy Shore Dr #",
    "iso:country":"US",
    "sg:address":"150 Quincy Shore Dr # 16",
    "sg:city":"Quincy",
    "sg:classifiers":[
        {
            "category":"Health Services",
            "subcategory":"Dentist",
            "type":"Services"
        }
    ],
    "sg:phone":"+1 617 481 2539",
    "sg:postcode":"02171",
    "sg:province":"MA",
    "sg:tags":[
        "equipment",
        "dental",
        "supply"
    ],
    "wof:name":"Rejuvedent",
    "wof:placetype":"venue"
},
  "geometry": {"coordinates":[-71.030428,42.28472],"type":"Point"}
}