{
  "type": "Feature",
  "properties": {
    "addr:full": "295 D St Boston MA 02127",
    "addr:housenumber": "295",
    "addr:postcode": "02127",
    "addr:street": "D St",
    "iso:country": "US",
    "sg:address": "295 D St",
    "sg:city": "Boston",
    "sg:classifiers": [
      {
        "category": "Building \u0026 Trades",
        "subcategory": "Locksmith",
        "type": "Services"
      }
    ],
    "sg:phone": "+1 617 752 9123",
    "sg:postcode": "02127",
    "sg:province": "MA",
    "sg:tags": [
      "key"
    ],
    "wof:name": "A 1 Emergency Locksmith",
    "wof:placetype": "venue"
  },
  "geometry": {"coordinates":[-71.049475,42.339763],"type":"Point"}
}
