{
  "type": "Feature",
  "properties": {
    "addr:full": "201 Spring Street Lexington MA 02421",
    "addr:housenumber": "201",
    "addr:postcode": "02421",
    "addr:street": "Spring Street",
    "iso:country": "US",
    "sg:address": "201 Spring Street",
    "sg:city": "Lexington",
    "sg:classifiers": [
      {
        "category": "Professional",
        "subcategory": "Computer Services",
        "type": "Services"
      }
    ],
    "sg:postcode": "02421",
    "sg:province": "MA",
    "sg:website": "http://www.abinitio.com",
    "wof:name": "Ab Initio",
    "wof:placetype": "venue"
  },
  "geometry": {"coordinates":[-71.251519,42.419399],"type":"Point"}
}
