{
  "type": "Feature",
  "properties": {
    "addr:full": "2216 Dorchester Ave Boston MA 02124",
    "addr:housenumber": "2216",
    "addr:postcode": "02124",
    "addr:street": "Dorchester Ave",
    "iso:country": "US",
    "sg:address": "2216 Dorchester Ave",
    "sg:city": "Boston",
    "sg:classifiers": [
      {
        "category": "Social Services",
        "type": "Services"
      }
    ],
    "sg:phone": "+1 617 296 5100",
    "sg:postcode": "02124",
    "sg:province": "MA",
    "sg:tags": [
      "care",
      "center",
      "day"
    ],
    "wof:name": "Elder Service Plan",
    "wof:placetype": "venue"
  },
  "geometry": {"coordinates":[-71.067624,42.273608],"type":"Point"}
}
