{
  "type": "Feature",
  "properties": {
    "addr:full":"1399 Washington St Hanover MA 02339",
    "addr:housenumber":"1399",
    "addr:postcode":"02339",
    "addr:street":"Washington St",
    "iso:country":"US",
    "sg:address":"1399 Washington St",
    "sg:city":"Hanover",
    "sg:classifiers":[
        {
            "category":"Professional",
            "subcategory":"Lawyer & Legal Services",
            "type":"Services"
        }
    ],
    "sg:phone":"+1 781 829 2029",
    "sg:postcode":"02339",
    "sg:province":"MA",
    "sg:tags":[
        "attorney"
    ],
    "wof:name":"Sorgi & Minichiello",
    "wof:placetype":"venue"
},
  "geometry": {"coordinates":[-70.844168,42.143887],"type":"Point"}
}