{
  "type": "Feature",
  "properties": {
    "iso:country":"US",
    "sg:address":"47 Chelmsford St",
    "sg:city":"Chelmsford",
    "sg:classifiers":[
        {
            "category":"Professional",
            "subcategory":"Lawyer & Legal Services",
            "type":"Services"
        }
    ],
    "sg:phone":"+1 978 250 1122",
    "sg:postcode":"01824",
    "sg:province":"MA",
    "sg:tags":[
        "attorney"
    ],
    "wof:name":"Harvey William L III Law Ofc",
    "wof:placetype":"venue"
},
  "geometry": {"coordinates":[-71.349495,42.598742],"type":"Point"}
}