{
  "type": "Feature",
  "properties": {
    "addr:full": "47 Chelmsford St Chelmsford MA 01824",
    "addr:housenumber": "47",
    "addr:postcode": "01824",
    "addr:street": "Chelmsford St",
    "iso:country": "US",
    "sg:address": "47 Chelmsford St",
    "sg:city": "Chelmsford",
    "sg:classifiers": [
      {
        "category": "Professional",
        "subcategory": "Lawyer \u0026 Legal Services",
        "type": "Services"
      }
    ],
    "sg:phone": "+1 978 250 1122",
    "sg:postcode": "01824",
    "sg:province": "MA",
    "sg:tags": [
      "attorney"
    ],
    "wof:name": "Harvey William L III Law Ofc",
    "wof:placetype": "venue"
  },
  "geometry": {"coordinates":[-71.349495,42.598742],"type":"Point"}
}
