{
  "type": "Feature",
  "properties": {
    "addr:full":"271 Carew St Springfield MA 01104",
    "addr:housenumber":"271",
    "addr:postcode":"01104",
    "addr:street":"Carew St",
    "iso:country":"US",
    "sg:address":"271 Carew St",
    "sg:city":"Springfield",
    "sg:classifiers":[
        {
            "category":"Shopping",
            "subcategory":"Gifts & Souvenirs",
            "type":"Retail Goods"
        }
    ],
    "sg:phone":"+1   ",
    "sg:postcode":"01104",
    "sg:province":"MA",
    "wof:name":"Gazebo Gift Shop",
    "wof:placetype":"venue"
},
  "geometry": {"coordinates":[-72.595615,42.114904],"type":"Point"}
}