{
  "type": "Feature",
  "properties": {
    "iso:country":"US",
    "sg:address":"85 Main St",
    "sg:city":"North Andover",
    "sg:classifiers":[
        {
            "category":"Professional",
            "subcategory":"Business Services",
            "type":"Services"
        },
        {
            "category":"Manufacturing",
            "subcategory":"Apparel",
            "type":"Manufacturing & Wholesale Goods"
        }
    ],
    "sg:phone":"+1 978 975 4044",
    "sg:postcode":"01845",
    "sg:province":"MA",
    "sg:tags":[
        "embroidery"
    ],
    "wof:name":"Creative Embroidery",
    "wof:placetype":"venue"
},
  "geometry": {"coordinates":[-71.132779,42.704144],"type":"Point"}
}