{
  "type": "Feature",
  "properties": {
    "iso:country":"US",
    "sg:address":"457 E Main St",
    "sg:city":"Southbridge",
    "sg:classifiers":[
        {
            "category":"Autos & Motor Vehicles",
            "subcategory":"Fuel & Gas Station",
            "type":"Retail Goods"
        }
    ],
    "sg:phone":"+1 508 765 8067",
    "sg:postcode":"01550",
    "sg:province":"MA",
    "wof:name":"Mobil Xtramart",
    "wof:placetype":"venue"
},
  "geometry": {"coordinates":[-72.014999,42.071201],"type":"Point"}
}