{
  "type": "Feature",
  "properties": {
    "addr:full": "36 Dania St Mattapan MA 02126",
    "addr:housenumber": "36",
    "addr:postcode": "02126",
    "addr:street": "Dania St",
    "iso:country": "US",
    "sg:address": "36 Dania St",
    "sg:city": "Mattapan",
    "sg:classifiers": [
      {
        "category": "Organizations",
        "subcategory": "Community Association",
        "type": "Services"
      }
    ],
    "sg:phone": "+1 617 298 2164",
    "sg:postcode": "02126",
    "sg:province": "MA",
    "sg:tags": [
      "fraternal"
    ],
    "wof:name": "United Supreme Council Inc",
    "wof:placetype": "venue"
  },
  "geometry": {"coordinates":[-71.08905,42.2729],"type":"Point"}
}
