{
  "type": "Feature",
  "properties": {
    "addr:full":"29 Mill Rd Littleton MA 01460",
    "addr:housenumber":"29",
    "addr:postcode":"01460",
    "addr:street":"Mill Rd",
    "iso:country":"US",
    "sg:address":"29 Mill Rd",
    "sg:city":"Littleton",
    "sg:classifiers":[
        {
            "category":"Utilities",
            "subcategory":"Water",
            "type":"Services"
        }
    ],
    "sg:phone":"+1 978 486 1008",
    "sg:postcode":"01460",
    "sg:province":"MA",
    "sg:tags":[
        "system",
        "supply"
    ],
    "wof:name":"Small Water Systems Svc",
    "wof:placetype":"venue"
},
  "geometry": {"coordinates":[-71.50211,42.538126],"type":"Point"}
}