{
  "type": "Feature",
  "properties": {
    "addr:full":"115 Mechanic St Foxboro MA 02035",
    "addr:housenumber":"115",
    "addr:postcode":"02035",
    "addr:street":"Mechanic St",
    "iso:country":"US",
    "sg:address":"115 Mechanic St",
    "sg:city":"Foxboro",
    "sg:classifiers":[
        {
            "category":"Organizations",
            "subcategory":"Religious Organization",
            "type":"Services"
        }
    ],
    "sg:phone":"+1 508 543 5124",
    "sg:postcode":"02035",
    "sg:province":"MA",
    "sg:tags":[
        "churches-baptist",
        "church"
    ],
    "sg:website":"http://www.abc-usa.org",
    "wof:name":"First Baptist Church",
    "wof:placetype":"venue"
},
  "geometry": {"coordinates":[-71.237707,42.074661],"type":"Point"}
}