{
  "type": "Feature",
  "properties": {
    "addr:full": "704 Southbridge St Worcester MA 01610",
    "addr:housenumber": "704",
    "addr:postcode": "01610",
    "addr:street": "Southbridge St",
    "iso:country": "US",
    "ovtr:label": "Mainstream Insurance Agency, Inc., 704 Southbridge St Worcester MA US",
    "ovtr:similarity": 2.2587549686431885,
    "sg:address": "704 Southbridge St",
    "sg:city": "Worcester",
    "sg:classifiers": [
      {
        "category": "Insurance",
        "subcategory": "Insurance Agent",
        "type": "Services"
      },
      {
        "category": "Insurance",
        "subcategory": "Hazard Insurance",
        "type": "Services"
      },
      {
        "category": "Insurance",
        "subcategory": "Title Insurance",
        "type": "Services"
      },
      {
        "category": "Professional",
        "subcategory": "Lawyer \u0026 Legal Services",
        "type": "Services"
      }
    ],
    "sg:phone": "+1 508 797 4500",
    "sg:postcode": "01610",
    "sg:province": "MA",
    "sg:tags": [
      "attorney",
      "business",
      "auto",
      "commercial",
      "homeowner",
      "motorcycle",
      "renter"
    ],
    "sg:website": "http://www.mainstreamins.com",
    "wof:name": "Mainstream Insurance Agency Inc.",
    "wof:placetype": "venue"
  },
  "geometry": {"coordinates":[-71.811653,42.242569],"type":"Point"}
}
