{
  "type": "Feature",
  "properties": {
    "iso:country":"US",
    "sg:address":"704 Southbridge St",
    "sg:city":"Worcester",
    "sg:classifiers":[
        {
            "category":"Insurance",
            "subcategory":"Insurance Agent",
            "type":"Services"
        },
        {
            "category":"Insurance",
            "subcategory":"Hazard Insurance",
            "type":"Services"
        },
        {
            "category":"Insurance",
            "subcategory":"Title Insurance",
            "type":"Services"
        },
        {
            "category":"Professional",
            "subcategory":"Lawyer & Legal Services",
            "type":"Services"
        }
    ],
    "sg:phone":"+1 508 797 4500",
    "sg:postcode":"01610",
    "sg:province":"MA",
    "sg:tags":[
        "attorney",
        "business",
        "auto",
        "commercial",
        "homeowner",
        "motorcycle",
        "renter"
    ],
    "sg:website":"http://www.mainstreamins.com",
    "wof:name":"Mainstream Insurance Agency Inc.",
    "wof:placetype":"venue"
},
  "geometry": {"coordinates":[-71.81165300000001,42.242569],"type":"Point"}
}