{
  "type": "Feature",
  "properties": {
    "iso:country":"US",
    "sg:address":"23 Cummings Street",
    "sg:city":"Somerville",
    "sg:classifiers":[
        {
            "category":"Travel",
            "subcategory":"Hotels & Motels",
            "type":"Entertainment"
        }
    ],
    "sg:phone":"+1 617 625 5300",
    "sg:postcode":"02145",
    "sg:province":"MA",
    "wof:name":"La Quinta",
    "wof:placetype":"venue"
},
  "geometry": {"coordinates":[-71.08422,42.394199],"type":"Point"}
}