{
  "type": "Feature",
  "properties": {
    "addr:full": "23 Cummings Street Somerville MA 02145",
    "addr:housenumber": "23",
    "addr:postcode": "02145",
    "addr:street": "Cummings Street",
    "iso:country": "US",
    "sg:address": "23 Cummings Street",
    "sg:city": "Somerville",
    "sg:classifiers": [
      {
        "category": "Travel",
        "subcategory": "Hotels \u0026 Motels",
        "type": "Entertainment"
      }
    ],
    "sg:phone": "+1 617 625 5300",
    "sg:postcode": "02145",
    "sg:province": "MA",
    "wof:name": "La Quinta",
    "wof:placetype": "venue"
  },
  "geometry": {"coordinates":[-71.08422,42.394199],"type":"Point"}
}
