{
  "type": "Feature",
  "properties": {
    "addr:full":"108 William St Vineyard Haven MA 02568",
    "addr:housenumber":"108",
    "addr:postcode":"02568",
    "addr:street":"William St",
    "iso:country":"US",
    "sg:address":"108 William St",
    "sg:city":"Vineyard Haven",
    "sg:classifiers":[
        {
            "category":"Organizations",
            "subcategory":"Community Association",
            "type":"Services"
        }
    ],
    "sg:phone":"+1 508 693 0856",
    "sg:postcode":"02568",
    "sg:province":"MA",
    "sg:tags":[
        "environmental",
        "org"
    ],
    "wof:name":"Chan Chich Lodge",
    "wof:placetype":"venue"
},
  "geometry": {"coordinates":[-70.60439700000001,41.455934],"type":"Point"}
}