{
  "type": "Feature",
  "properties": {
    "addr:full":"22 Central St Ipswich MA 01938",
    "addr:housenumber":"22",
    "addr:postcode":"01938",
    "addr:street":"Central St",
    "iso:country":"US",
    "sg:address":"22 Central St",
    "sg:city":"Ipswich",
    "sg:classifiers":[
        {
            "category":"Building & Trades",
            "subcategory":"Construction",
            "type":"Services"
        }
    ],
    "sg:phone":"+1 978 356 1211",
    "sg:postcode":"01938",
    "sg:province":"MA",
    "sg:tags":[
        "painter"
    ],
    "wof:name":"B & K Painting",
    "wof:placetype":"venue"
},
  "geometry": {"coordinates":[-70.83820900000001,42.680434],"type":"Point"}
}