{
  "type": "Feature",
  "properties": {
    "addr:full": "200 University Ave Lowell MA 01854",
    "addr:housenumber": "200",
    "addr:postcode": "01854",
    "addr:street": "University Ave",
    "iso:country": "US",
    "sg:address": "200 University Ave",
    "sg:city": "Lowell",
    "sg:classifiers": [
      {
        "category": "Shopping",
        "subcategory": "Gifts \u0026 Souvenirs",
        "type": "Retail Goods"
      }
    ],
    "sg:phone": "+1 978 459 7077",
    "sg:postcode": "01854",
    "sg:province": "MA",
    "sg:tags": [
      "shop"
    ],
    "wof:name": "Living Room",
    "wof:placetype": "venue"
  },
  "geometry": {"coordinates":[-71.329683,42.655382],"type":"Point"}
}
