{
  "type": "Feature",
  "properties": {
    "iso:country":"US",
    "sg:address":"33 Middle St",
    "sg:city":"Lowell",
    "sg:classifiers":[
        {
            "category":"Shopping",
            "subcategory":"Used Merchandise",
            "type":"Retail Goods"
        }
    ],
    "sg:phone":"+1 978 654 5059",
    "sg:postcode":"01852",
    "sg:province":"MA",
    "sg:tags":[
        "antique"
    ],
    "wof:name":"Found",
    "wof:placetype":"venue"
},
  "geometry": {"coordinates":[-71.310529,42.645209],"type":"Point"}
}