{
  "type": "Feature",
  "properties": {
    "addr:full": "30 Porter Rd Boxford MA 01921",
    "addr:housenumber": "30",
    "addr:postcode": "01921",
    "addr:street": "Porter Rd",
    "iso:country": "US",
    "sg:address": "30 Porter Rd",
    "sg:city": "Boxford",
    "sg:classifiers": [
      {
        "category": "Professional",
        "subcategory": "Management \u0026 Consulting",
        "type": "Services"
      }
    ],
    "sg:phone": "+1 978 352 9099",
    "sg:postcode": "01921",
    "sg:province": "MA",
    "sg:tags": [
      "consultant"
    ],
    "wof:name": "Bay State Consultants",
    "wof:placetype": "venue"
  },
  "geometry": {"coordinates":[-71.049628,42.70362],"type":"Point"}
}
