{
  "type": "Feature",
  "properties": {
    "iso:country":"US",
    "sg:address":"242 Andover St",
    "sg:city":"Peabody",
    "sg:classifiers":[
        {
            "category":"Shopping",
            "subcategory":"Computers & Home Electronics",
            "type":"Retail Goods"
        }
    ],
    "sg:phone":"+1 978 531 7500",
    "sg:postcode":"01960",
    "sg:province":"MA",
    "sg:tags":[
        "high",
        "fidelity",
        "stereophonic"
    ],
    "sg:website":"www.tweeter.com",
    "wof:name":"Tweeter",
    "wof:placetype":"venue"
},
  "geometry": {"coordinates":[-70.948195,42.546977],"type":"Point"}
}