{
  "type": "Feature",
  "properties": {
    "addr:full": "242 Andover St Peabody MA 01960",
    "addr:housenumber": "242",
    "addr:postcode": "01960",
    "addr:street": "Andover St",
    "iso:country": "US",
    "sg:address": "242 Andover St",
    "sg:city": "Peabody",
    "sg:classifiers": [
      {
        "category": "Shopping",
        "subcategory": "Computers \u0026 Home Electronics",
        "type": "Retail Goods"
      }
    ],
    "sg:phone": "+1 978 531 7500",
    "sg:postcode": "01960",
    "sg:province": "MA",
    "sg:tags": [
      "high",
      "fidelity",
      "stereophonic"
    ],
    "sg:website": "www.tweeter.com",
    "wof:name": "Tweeter",
    "wof:placetype": "venue"
  },
  "geometry": {"coordinates":[-70.948195,42.546977],"type":"Point"}
}
