{
  "type": "Feature",
  "properties": {
    "iso:country":"US",
    "sg:address":"234 Tucker St",
    "sg:city":"Fall River",
    "sg:classifiers":[
        {
            "category":"Building & Trades",
            "subcategory":"Equipment Rental",
            "type":"Services"
        }
    ],
    "sg:phone":"+1 508 324 0696",
    "sg:postcode":"02721",
    "sg:province":"MA",
    "sg:tags":[
        "leasing",
        "furniture"
    ],
    "wof:name":"Aarons Sales & Lease Ownership",
    "wof:placetype":"venue"
},
  "geometry": {"coordinates":[-71.162582,41.677763],"type":"Point"}
}