{
  "type": "Feature",
  "properties": {
    "addr:full":"69 Greenleaf St Quincy MA 02169",
    "addr:housenumber":"69",
    "addr:postcode":"02169",
    "addr:street":"Greenleaf St",
    "iso:country":"US",
    "sg:address":"69 Greenleaf St",
    "sg:city":"Quincy",
    "sg:classifiers":[
        {
            "category":"Building & Trades",
            "subcategory":"Construction",
            "type":"Services"
        }
    ],
    "sg:phone":"+1 617 770 3360",
    "sg:postcode":"02169",
    "sg:province":"MA",
    "sg:tags":[
        "floor"
    ],
    "wof:name":"Le's Enterprise Svc",
    "wof:placetype":"venue"
},
  "geometry": {"coordinates":[-71.004214,42.256378],"type":"Point"}
}