{
  "type": "Feature",
  "properties": {
    "addr:full":"21 Main St Nantucket MA 02554",
    "addr:housenumber":"21",
    "addr:postcode":"02554",
    "addr:street":"Main St",
    "iso:country":"US",
    "sg:address":"21 Main St",
    "sg:city":"Nantucket",
    "sg:classifiers":[
        {
            "category":"Shopping",
            "subcategory":"Clothing, Apparel, & Fashions",
            "type":"Retail Goods"
        }
    ],
    "sg:phone":"+1 508 228 3552",
    "sg:postcode":"02554",
    "sg:province":"MA",
    "sg:tags":[
        "sweater"
    ],
    "wof:name":"Wolfhound Imports",
    "wof:placetype":"venue"
},
  "geometry": {"coordinates":[-70.09770899999999,41.283704],"type":"Point"}
}