{
  "type": "Feature",
  "properties": {
    "addr:full": "53 E Plain St Wayland MA 01778",
    "addr:housenumber": "53",
    "addr:postcode": "01778",
    "addr:street": "E Plain St",
    "iso:country": "US",
    "sg:address": "53 E Plain St",
    "sg:city": "Wayland",
    "sg:classifiers": [
      {
        "category": "Organizations",
        "subcategory": "Religious Organization",
        "type": "Services"
      }
    ],
    "sg:phone": "+1 508 653 0577",
    "sg:postcode": "01778",
    "sg:province": "MA",
    "sg:tags": [
      "church"
    ],
    "wof:name": "Community United Methodist Chr",
    "wof:placetype": "venue"
  },
  "geometry": {"coordinates":[-71.360925,42.321784],"type":"Point"}
}
