{
  "type": "Feature",
  "properties": {
    "addr:full": "384 Lowell St Wakefield MA 01880",
    "addr:housenumber": "384",
    "addr:postcode": "01880",
    "addr:street": "Lowell St",
    "iso:country": "US",
    "sg:address": "384 Lowell St",
    "sg:city": "Wakefield",
    "sg:classifiers": [
      {
        "category": "Health Services",
        "subcategory": "Health Practitioner",
        "type": "Services"
      }
    ],
    "sg:phone": "+1 781 246 2266",
    "sg:postcode": "01880",
    "sg:province": "MA",
    "sg:tags": [
      "therapist",
      "physical"
    ],
    "wof:name": "Wakefield Physical Therapy",
    "wof:placetype": "venue"
  },
  "geometry": {"coordinates":[-71.062378,42.517094],"type":"Point"}
}
