{
  "type": "Feature",
  "properties": {
    "addr:full":"1221 Westford St Lowell MA 01851",
    "addr:housenumber":"1221",
    "addr:postcode":"01851",
    "addr:street":"Westford St",
    "iso:country":"US",
    "sg:address":"1221 Westford St",
    "sg:city":"Lowell",
    "sg:classifiers":[
        {
            "category":"Local Transit",
            "type":"Transportation"
        }
    ],
    "sg:phone":"+1 978 441 9999",
    "sg:postcode":"01851",
    "sg:province":"MA",
    "sg:tags":[
        "ambulance"
    ],
    "wof:name":"Trinity EMS",
    "wof:placetype":"venue"
},
  "geometry": {"coordinates":[-71.357119,42.627636],"type":"Point"}
}