{
  "type": "Feature",
  "properties": {
    "iso:country":"US",
    "sg:address":"190 Crystal St",
    "sg:city":"Haverhill",
    "sg:classifiers":[
        {
            "category":"Building & Trades",
            "subcategory":"Electrical",
            "type":"Services"
        }
    ],
    "sg:phone":"+1   ",
    "sg:postcode":"01832",
    "sg:province":"MA",
    "sg:tags":[
        "electrical",
        "contractor"
    ],
    "wof:name":"Whittier Ray Electric",
    "wof:placetype":"venue"
},
  "geometry": {"coordinates":[-71.164249,42.795882],"type":"Point"}
}