{
  "type": "Feature",
  "properties": {
    "addr:full": "190 Crystal St Haverhill MA 01832",
    "addr:housenumber": "190",
    "addr:postcode": "01832",
    "addr:street": "Crystal St",
    "iso:country": "US",
    "sg:address": "190 Crystal St",
    "sg:city": "Haverhill",
    "sg:classifiers": [
      {
        "category": "Building \u0026 Trades",
        "subcategory": "Electrical",
        "type": "Services"
      }
    ],
    "sg:phone": "+1   ",
    "sg:postcode": "01832",
    "sg:province": "MA",
    "sg:tags": [
      "electrical",
      "contractor"
    ],
    "wof:name": "Whittier Ray Electric",
    "wof:placetype": "venue"
  },
  "geometry": {"coordinates":[-71.164249,42.795882],"type":"Point"}
}
