{
  "type": "Feature",
  "properties": {
    "addr:full":"347 Massachusetts Avenue Arlington MA 02474",
    "addr:housenumber":"347",
    "addr:postcode":"02474",
    "addr:street":"Massachusetts Avenue",
    "iso:country":"US",
    "sg:address":"347 Massachusetts Avenue",
    "sg:city":"Arlington",
    "sg:classifiers":[
        {
            "category":"Sports & Exercise",
            "subcategory":"Gym",
            "type":"Entertainment"
        },
        {
            "category":"Health Services",
            "subcategory":"Health Practitioner",
            "type":"Services"
        }
    ],
    "sg:phone":"+1 781 643 3679",
    "sg:postcode":"02474",
    "sg:province":"MA",
    "sg:tags":[
        "acupuncture",
        "trainer"
    ],
    "wof:name":"Kim Myung Acupuncture & Herbal Clinic",
    "wof:placetype":"venue"
},
  "geometry": {"coordinates":[-71.148206,42.410989],"type":"Point"}
}