{
  "type": "Feature",
  "properties": {
    "iso:country":"US",
    "sg:address":"2068 State Hwy Rte 6",
    "sg:city":"Wellfleet",
    "sg:classifiers":[
        {
            "category":"Travel",
            "subcategory":"Hotels & Motels",
            "type":"Entertainment"
        }
    ],
    "sg:phone":"+1 508 744 6327",
    "sg:postcode":"02667",
    "sg:province":"MA",
    "sg:tags":[
        "cottage"
    ],
    "sg:website":"http://www.mainstaymotorinn.com",
    "wof:name":"The Mainstay Motor Inn",
    "wof:placetype":"venue"
},
  "geometry": {"coordinates":[-70.00972,41.922798],"type":"Point"}
}