{
  "type": "Feature",
  "properties": {
    "iso:country":"US",
    "sg:address":"68 Great Rd",
    "sg:city":"Bedford",
    "sg:classifiers":[
        {
            "category":"Autos & Motor Vehicles",
            "subcategory":"Automobile Sales",
            "type":"Retail Goods"
        }
    ],
    "sg:phone":"+1 781 275 7800",
    "sg:postcode":"01730",
    "sg:province":"MA",
    "sg:tags":[
        "limo"
    ],
    "wof:name":"Bedford Limousine - CLOSED",
    "wof:placetype":"venue"
},
  "geometry": {"coordinates":[-71.28299699999999,42.493099],"type":"Point"}
}