{
  "type": "Feature",
  "properties": {
    "iso:country":"US",
    "sg:address":"15 N Main St",
    "sg:city":"Bellingham",
    "sg:classifiers":[
        {
            "category":"Manufacturing",
            "subcategory":"Printing",
            "type":"Manufacturing & Wholesale Goods"
        }
    ],
    "sg:phone":"+1 508 966 2970",
    "sg:postcode":"02019",
    "sg:province":"MA",
    "sg:tags":[
        "printer"
    ],
    "wof:name":"Son-Co Printing & Copying",
    "wof:placetype":"venue"
},
  "geometry": {"coordinates":[-71.47619899999999,42.08979],"type":"Point"}
}