{
  "type": "Feature",
  "properties": {
    "addr:full":"230 Canton Ave Milton MA 02186",
    "addr:housenumber":"230",
    "addr:postcode":"02186",
    "addr:street":"Canton Ave",
    "iso:country":"US",
    "sg:address":"230 Canton Ave",
    "sg:city":"Milton",
    "sg:classifiers":[
        {
            "category":"Professional",
            "subcategory":"Management & Consulting",
            "type":"Services"
        }
    ],
    "sg:phone":"+1 617 698 7236",
    "sg:postcode":"02186",
    "sg:province":"MA",
    "sg:tags":[
        "ecological",
        "business",
        "engineer"
    ],
    "wof:name":"Houqua & Co Inc",
    "wof:placetype":"venue"
},
  "geometry": {"coordinates":[-71.072886,42.261684],"type":"Point"}
}