{
  "type": "Feature",
  "properties": {
    "addr:full": "564 State Hwy 28 Harwich Port MA 02646",
    "addr:housenumber": "564",
    "addr:postcode": "02646",
    "addr:street": "State Hwy 28",
    "iso:country": "US",
    "sg:address": "564 State Hwy 28",
    "sg:city": "Harwich Port",
    "sg:classifiers": [
      {
        "category": "Shopping",
        "subcategory": "Hobbies, Toys, \u0026 Games",
        "type": "Retail Goods"
      }
    ],
    "sg:phone": "+1 508 430 0437",
    "sg:postcode": "02646",
    "sg:province": "MA",
    "sg:tags": [
      "kite"
    ],
    "wof:name": "Doctor Gravity's Kite Shop",
    "wof:placetype": "venue"
  },
  "geometry": {"coordinates":[-70.074004,41.667895],"type":"Point"}
}
