{
  "type": "Feature",
  "properties": {
    "iso:country":"US",
    "sg:address":"564 State Hwy 28",
    "sg:city":"Harwich Port",
    "sg:classifiers":[
        {
            "category":"Shopping",
            "subcategory":"Hobbies, Toys, & Games",
            "type":"Retail Goods"
        }
    ],
    "sg:phone":"+1 508 430 0437",
    "sg:postcode":"02646",
    "sg:province":"MA",
    "sg:tags":[
        "kite"
    ],
    "wof:name":"Doctor Gravity's Kite Shop",
    "wof:placetype":"venue"
},
  "geometry": {"coordinates":[-70.074004,41.667895],"type":"Point"}
}