{
  "type": "Feature",
  "properties": {
    "iso:country":"US",
    "sg:address":"45 School St Fl 5",
    "sg:city":"Boston",
    "sg:classifiers":[
        {
            "category":"Government",
            "subcategory":"Office",
            "type":"Public Place"
        }
    ],
    "sg:phone":"+1 617 523 1635",
    "sg:postcode":"02108",
    "sg:province":"MA",
    "sg:tags":[
        "township",
        "government-city",
        "village"
    ],
    "wof:name":"Lowell Inst Trustee",
    "wof:placetype":"venue"
},
  "geometry": {"coordinates":[-71.05946400000001,42.357712],"type":"Point"}
}