{
  "type": "Feature",
  "properties": {
    "addr:full": "187 Leland Farm Rd Ashland MA 01721",
    "addr:housenumber": "187",
    "addr:postcode": "01721",
    "addr:street": "Leland Farm Rd",
    "iso:country": "US",
    "sg:address": "187 Leland Farm Rd",
    "sg:city": "Ashland",
    "sg:classifiers": [
      {
        "category": "Communications",
        "subcategory": "Film \u0026 Video Production",
        "type": "Services"
      }
    ],
    "sg:phone": "+1 508 881 3686",
    "sg:postcode": "01721",
    "sg:province": "MA",
    "sg:tags": [
      "taping"
    ],
    "sg:website": "www.arnoldvideo.com",
    "wof:name": "Arnold Video Productions Inc",
    "wof:placetype": "venue"
  },
  "geometry": {"coordinates":[-71.434001,42.238081],"type":"Point"}
}
