{
  "type": "Feature",
  "properties": {
    "iso:country":"US",
    "sg:address":"187 Leland Farm Rd",
    "sg:city":"Ashland",
    "sg:classifiers":[
        {
            "category":"Communications",
            "subcategory":"Film & Video Production",
            "type":"Services"
        }
    ],
    "sg:phone":"+1 508 881 3686",
    "sg:postcode":"01721",
    "sg:province":"MA",
    "sg:tags":[
        "taping"
    ],
    "sg:website":"www.arnoldvideo.com",
    "wof:name":"Arnold Video Productions Inc",
    "wof:placetype":"venue"
},
  "geometry": {"coordinates":[-71.43400099999999,42.238081],"type":"Point"}
}