{
  "type": "Feature",
  "properties": {
    "iso:country":"US",
    "sg:address":"257 Popes Is",
    "sg:city":"New Bedford",
    "sg:classifiers":[
        {
            "category":"Shopping",
            "subcategory":"Bicycles & Sporting Goods",
            "type":"Retail Goods"
        }
    ],
    "sg:phone":"+1 508 996 8682",
    "sg:postcode":"02740",
    "sg:province":"MA",
    "sg:tags":[
        "tackle",
        "fishing"
    ],
    "wof:name":"Dockside Bait & Tackle",
    "wof:placetype":"venue"
},
  "geometry": {"coordinates":[-70.915211,41.640179],"type":"Point"}
}