{
  "type": "Feature",
  "properties": {
    "addr:full":"5 S Orleans Rd Orleans MA 02653",
    "addr:housenumber":"5",
    "addr:postcode":"02653",
    "addr:street":"S Orleans Rd",
    "iso:country":"US",
    "sg:address":"5 S Orleans Rd",
    "sg:city":"Orleans",
    "sg:classifiers":[
        {
            "category":"Restaurant",
            "type":"Food & Drink"
        }
    ],
    "sg:phone":"+1 508 240 0003",
    "sg:postcode":"02653",
    "sg:province":"MA",
    "sg:tags":[
        "parlor",
        "ice",
        "cream"
    ],
    "wof:name":"Ice Cream Cafe",
    "wof:placetype":"venue"
},
  "geometry": {"coordinates":[-69.986921,41.79153],"type":"Point"}
}