{
  "type": "Feature",
  "properties": {
    "addr:full":"862 Main St Acushnet MA 02743",
    "addr:housenumber":"862",
    "addr:postcode":"02743",
    "addr:street":"Main St",
    "iso:country":"US",
    "sg:address":"862 Main St",
    "sg:city":"Acushnet",
    "sg:classifiers":[
        {
            "category":"Building & Trades",
            "subcategory":"Construction",
            "type":"Services"
        }
    ],
    "sg:phone":"+1 508 998 1236",
    "sg:postcode":"02743",
    "sg:province":"MA",
    "sg:tags":[
        "carpenter"
    ],
    "wof:name":"Leo Beaudoin Carpenter",
    "wof:placetype":"venue"
},
  "geometry": {"coordinates":[-70.888715,41.721978],"type":"Point"}
}