{
  "type": "Feature",
  "properties": {
    "addr:full":"494 School St North Dighton MA 02764",
    "addr:housenumber":"494",
    "addr:postcode":"02764",
    "addr:street":"School St",
    "iso:country":"US",
    "sg:address":"494 School St",
    "sg:city":"North Dighton",
    "sg:classifiers":[
        {
            "category":"Freight",
            "type":"Transportation"
        }
    ],
    "sg:phone":"+1 508 822 4099",
    "sg:postcode":"02764",
    "sg:province":"MA",
    "sg:tags":[
        "trucking"
    ],
    "wof:name":"Rivard Trucking",
    "wof:placetype":"venue"
},
  "geometry": {"coordinates":[-71.126327,41.862717],"type":"Point"}
}