{
  "type": "Feature",
  "properties": {
    "addr:full": "6 Merchant St Sharon MA 02067",
    "addr:housenumber": "6",
    "addr:postcode": "02067",
    "addr:street": "Merchant St",
    "iso:country": "US",
    "sg:address": "6 Merchant St",
    "sg:city": "Sharon",
    "sg:classifiers": [
      {
        "category": "Utilities",
        "subcategory": "Telephone",
        "type": "Services"
      }
    ],
    "sg:phone": "+1   ",
    "sg:postcode": "02067",
    "sg:province": "MA",
    "sg:tags": [
      "wireless",
      "communications"
    ],
    "wof:name": "Lenbrook USA Corp",
    "wof:placetype": "venue"
  },
  "geometry": {"coordinates":[-71.234892,42.117809],"type":"Point"}
}
