{
  "type": "Feature",
  "properties": {
    "iso:country":"US",
    "sg:address":"139 Central St",
    "sg:city":"Leominster",
    "sg:classifiers":[
        {
            "category":"Autos & Motor Vehicles",
            "subcategory":"Auto Supplies",
            "type":"Retail Goods"
        },
        {
            "category":"Manufacturing",
            "subcategory":"Motor Vehicles & Parts",
            "type":"Manufacturing & Wholesale Goods"
        },
        {
            "category":"Wholesale",
            "subcategory":"Auto Parts",
            "type":"Manufacturing & Wholesale Goods"
        },
        {
            "category":"Retail",
            "subcategory":"Auto Repair",
            "type":"Services"
        }
    ],
    "sg:phone":"+1 978 840 4476",
    "sg:postcode":"01453",
    "sg:province":"MA",
    "sg:tags":[
        "body",
        "shop",
        "automobile",
        "supply-wholesale",
        "equipment",
        "service-equipment",
        "painting",
        "repairing",
        "manufacturer"
    ],
    "wof:name":"Custom Aerosols & Paint Supplies",
    "wof:placetype":"venue"
},
  "geometry": {"coordinates":[-71.758506,42.521398],"type":"Point"}
}