{
  "type": "Feature",
  "properties": {
    "addr:full": "139 Central St Leominster MA 01453",
    "addr:housenumber": "139",
    "addr:postcode": "01453",
    "addr:street": "Central St",
    "iso:country": "US",
    "sg:address": "139 Central St",
    "sg:city": "Leominster",
    "sg:classifiers": [
      {
        "category": "Autos \u0026 Motor Vehicles",
        "subcategory": "Auto Supplies",
        "type": "Retail Goods"
      },
      {
        "category": "Manufacturing",
        "subcategory": "Motor Vehicles \u0026 Parts",
        "type": "Manufacturing \u0026 Wholesale Goods"
      },
      {
        "category": "Wholesale",
        "subcategory": "Auto Parts",
        "type": "Manufacturing \u0026 Wholesale Goods"
      },
      {
        "category": "Retail",
        "subcategory": "Auto Repair",
        "type": "Services"
      }
    ],
    "sg:phone": "+1 978 840 4476",
    "sg:postcode": "01453",
    "sg:province": "MA",
    "sg:tags": [
      "body",
      "shop",
      "automobile",
      "supply-wholesale",
      "equipment",
      "service-equipment",
      "painting",
      "repairing",
      "manufacturer"
    ],
    "wof:name": "Custom Aerosols \u0026 Paint Supplies",
    "wof:placetype": "venue"
  },
  "geometry": {"coordinates":[-71.758506,42.521398],"type":"Point"}
}
