{
  "type": "Feature",
  "properties": {
    "addr:full": "40 Atwood St Wellesley MA 02482",
    "addr:housenumber": "40",
    "addr:postcode": "02482",
    "addr:street": "Atwood St",
    "iso:country": "US",
    "sg:address": "40 Atwood St",
    "sg:city": "Wellesley",
    "sg:classifiers": [
      {
        "category": "Professional",
        "subcategory": "Research",
        "type": "Services"
      }
    ],
    "sg:phone": "+1 781 235 4466",
    "sg:postcode": "02482",
    "sg:province": "MA",
    "sg:tags": [
      "ergonomics"
    ],
    "wof:name": "Ergonomics International Inc",
    "wof:placetype": "venue"
  },
  "geometry": {"coordinates":[-71.286439,42.300466],"type":"Point"}
}
