{
  "type": "Feature",
  "properties": {
    "iso:country":"US",
    "sg:address":"540 Gallivan Blvd",
    "sg:city":"Dorchester Center",
    "sg:classifiers":[
        {
            "category":"Professional",
            "subcategory":"Computer Services",
            "type":"Services"
        }
    ],
    "sg:phone":"+1 617 287 2200",
    "sg:postcode":"02124",
    "sg:province":"MA",
    "sg:tags":[
        "repair"
    ],
    "wof:name":"G C Computer Center",
    "wof:placetype":"venue"
},
  "geometry": {"coordinates":[-71.05500000000001,42.2826],"type":"Point"}
}