{
  "type": "Feature",
  "properties": {
    "addr:full": "540 Gallivan Blvd Dorchester Center MA 02124",
    "addr:housenumber": "540",
    "addr:postcode": "02124",
    "addr:street": "Gallivan Blvd",
    "iso:country": "US",
    "sg:address": "540 Gallivan Blvd",
    "sg:city": "Dorchester Center",
    "sg:classifiers": [
      {
        "category": "Professional",
        "subcategory": "Computer Services",
        "type": "Services"
      }
    ],
    "sg:phone": "+1 617 287 2200",
    "sg:postcode": "02124",
    "sg:province": "MA",
    "sg:tags": [
      "repair"
    ],
    "wof:name": "G C Computer Center",
    "wof:placetype": "venue"
  },
  "geometry": {"coordinates":[-71.055,42.2826],"type":"Point"}
}
