{
  "type": "Feature",
  "properties": {
    "iso:country":"US",
    "sg:address":"100 Nickerson Rd",
    "sg:city":"Marlborough",
    "sg:classifiers":[
        {
            "category":"Manufacturing",
            "subcategory":"Tools & Machinery",
            "type":"Manufacturing & Wholesale Goods"
        }
    ],
    "sg:phone":"+1 508 485 4447",
    "sg:postcode":"01752",
    "sg:province":"MA",
    "sg:tags":[
        "equipment",
        "electric"
    ],
    "sg:website":"www.rockwellautomation.com",
    "wof:name":"Rockwell Automation",
    "wof:placetype":"venue"
},
  "geometry": {"coordinates":[-71.59783899999999,42.332756],"type":"Point"}
}