{
  "type": "Feature",
  "properties": {
    "iso:country":"US",
    "sg:address":"655 Boxberry Hill Rd",
    "sg:city":"East Falmouth",
    "sg:classifiers":[
        {
            "category":"Education",
            "subcategory":"School",
            "type":"Public Place"
        }
    ],
    "sg:phone":"+1 508 564 6341",
    "sg:postcode":"02536",
    "sg:province":"MA",
    "sg:website":"www.heritageccag.com",
    "wof:name":"Heritage Christian Academy",
    "wof:placetype":"venue"
},
  "geometry": {"coordinates":[-70.582703,41.6343],"type":"Point"}
}