{
  "type": "Feature",
  "properties": {
    "addr:full": "655 Boxberry Hill Rd East Falmouth MA 02536",
    "addr:housenumber": "655",
    "addr:postcode": "02536",
    "addr:street": "Boxberry Hill Rd",
    "iso:country": "US",
    "sg:address": "655 Boxberry Hill Rd",
    "sg:city": "East Falmouth",
    "sg:classifiers": [
      {
        "category": "Education",
        "subcategory": "School",
        "type": "Public Place"
      }
    ],
    "sg:phone": "+1 508 564 6341",
    "sg:postcode": "02536",
    "sg:province": "MA",
    "sg:website": "www.heritageccag.com",
    "wof:name": "Heritage Christian Academy",
    "wof:placetype": "venue"
  },
  "geometry": {"coordinates":[-70.582703,41.6343],"type":"Point"}
}
