{
  "type": "Feature",
  "properties": {
    "addr:full":"269 Mechanic St Marlborough MA 01752",
    "addr:housenumber":"269",
    "addr:postcode":"01752",
    "addr:street":"Mechanic St",
    "iso:country":"US",
    "sg:address":"269 Mechanic St",
    "sg:city":"Marlborough",
    "sg:classifiers":[
        {
            "category":"Freight",
            "type":"Transportation"
        }
    ],
    "sg:phone":"+1 508 485 0348",
    "sg:postcode":"01752",
    "sg:province":"MA",
    "sg:tags":[
        "mover"
    ],
    "wof:name":"Marlboro Transportation",
    "wof:placetype":"venue"
},
  "geometry": {"coordinates":[-71.559622,42.353586],"type":"Point"}
}