{
  "type": "Feature",
  "properties": {
    "iso:country":"US",
    "sg:address":"129 Cabot St",
    "sg:city":"Beverly",
    "sg:classifiers":[
        {
            "category":"Bars & Pubs",
            "type":"Food & Drink"
        }
    ],
    "sg:phone":"+1 978 922 4899",
    "sg:postcode":"01915",
    "sg:province":"MA",
    "wof:name":"Lucky Dog",
    "wof:placetype":"venue"
},
  "geometry": {"coordinates":[-70.87955700000001,42.5466],"type":"Point"}
}