{
  "type": "Feature",
  "properties": {
    "iso:country":"US",
    "sg:address":"475 Pine St",
    "sg:city":"Feeding Hills",
    "sg:classifiers":[
        {
            "category":"Organizations",
            "subcategory":"Religious Organization",
            "type":"Services"
        }
    ],
    "sg:phone":"+1 413 821 0112",
    "sg:postcode":"01030",
    "sg:province":"MA",
    "sg:tags":[
        "church"
    ],
    "wof:name":"Grace Baptist Church",
    "wof:placetype":"venue"
},
  "geometry": {"coordinates":[-72.685276,42.037998],"type":"Point"}
}