{
  "type": "Feature",
  "properties": {
    "addr:full": "166 Summer St Haverhill MA 01830",
    "addr:housenumber": "166",
    "addr:postcode": "01830",
    "addr:street": "Summer St",
    "iso:country": "US",
    "sg:address": "166 Summer St",
    "sg:city": "Haverhill",
    "sg:classifiers": [
      {
        "category": "Health Services",
        "subcategory": "Doctor",
        "type": "Services"
      }
    ],
    "sg:phone": "+1 978 374 0166",
    "sg:postcode": "01830",
    "sg:province": "MA",
    "sg:tags": [
      "dentist"
    ],
    "wof:name": "Philip A Minichiello DDS",
    "wof:placetype": "venue"
  },
  "geometry": {"coordinates":[-71.069256,42.776865],"type":"Point"}
}
