{
  "type": "Feature",
  "properties": {
    "addr:full": "750 Worcester St Indian Orchard MA 01151",
    "addr:housenumber": "750",
    "addr:postcode": "01151",
    "addr:street": "Worcester St",
    "iso:country": "US",
    "sg:address": "750 Worcester St",
    "sg:city": "Indian Orchard",
    "sg:classifiers": [
      {
        "category": "Utilities",
        "subcategory": "Electric",
        "type": "Services"
      }
    ],
    "sg:phone": "+1 413 731 6611",
    "sg:postcode": "01151",
    "sg:province": "MA",
    "sg:tags": [
      "company"
    ],
    "wof:name": "Masspower",
    "wof:placetype": "venue"
  },
  "geometry": {"coordinates":[-72.523951,42.153836],"type":"Point"}
}
