{
  "type": "Feature",
  "properties": {
    "addr:full": "6 Echo Ave Beverly MA 01915",
    "addr:housenumber": "6",
    "addr:postcode": "01915",
    "addr:street": "Echo Ave",
    "iso:country": "US",
    "sg:address": "6 Echo Ave",
    "sg:city": "Beverly",
    "sg:classifiers": [
      {
        "category": "Professional",
        "type": "Services"
      }
    ],
    "sg:phone": "+1 978 921 0900",
    "sg:postcode": "01915",
    "sg:province": "MA",
    "sg:tags": [
      "establishment"
    ],
    "wof:name": "Children's Connection",
    "wof:placetype": "venue"
  },
  "geometry": {"coordinates":[-70.891803,42.556733],"type":"Point"}
}
