{
  "type": "Feature",
  "properties": {
    "iso:country":"US",
    "sg:address":"140 E Main St",
    "sg:city":"Norton",
    "sg:classifiers":[
        {
            "category":"Manufacturing",
            "subcategory":"Electronics",
            "type":"Manufacturing & Wholesale Goods"
        }
    ],
    "sg:phone":"+1 508 285 5043",
    "sg:postcode":"02766",
    "sg:province":"MA",
    "sg:tags":[
        "equipment",
        "electronic",
        "supply"
    ],
    "wof:name":"Electronic Solution",
    "wof:placetype":"venue"
},
  "geometry": {"coordinates":[-71.170596,41.974744],"type":"Point"}
}