{
  "type": "Feature",
  "properties": {
    "iso:country":"US",
    "sg:address":"21 Central St",
    "sg:city":"Manchester",
    "sg:classifiers":[
        {
            "category":"Shopping",
            "subcategory":"Clothing, Apparel, & Fashions",
            "type":"Retail Goods"
        }
    ],
    "sg:phone":"+1 978 526 8886",
    "sg:postcode":"01944",
    "sg:province":"MA",
    "wof:name":"T Lloyd Clothiers",
    "wof:placetype":"venue"
},
  "geometry": {"coordinates":[-70.77282599999999,42.575247],"type":"Point"}
}