{
  "type": "Feature",
  "properties": {
    "addr:full": "15 Pleasant St Con Framingham MA 01701",
    "addr:housenumber": "15",
    "addr:postcode": "01701",
    "addr:street": "Pleasant St Con",
    "iso:country": "US",
    "sg:address": "15 Pleasant St Con",
    "sg:city": "Framingham",
    "sg:classifiers": [
      {
        "category": "Professional",
        "type": "Services"
      }
    ],
    "sg:phone": "+1 508 620 1000",
    "sg:postcode": "01701",
    "sg:province": "MA",
    "sg:tags": [
      "establishment"
    ],
    "wof:name": "Consolidated Group",
    "wof:placetype": "venue"
  },
  "geometry": {"coordinates":[-71.490322,42.297625],"type":"Point"}
}
