{
  "type": "Feature",
  "properties": {
    "addr:full":"1462 Grafton Rd Millbury MA 01527",
    "addr:housenumber":"1462",
    "addr:postcode":"01527",
    "addr:street":"Grafton Rd",
    "iso:country":"US",
    "sg:address":"1462 Grafton Rd",
    "sg:city":"Millbury",
    "sg:classifiers":[
        {
            "category":"Retail",
            "subcategory":"Auto Repair",
            "type":"Services"
        }
    ],
    "sg:phone":"+1 508 799 4164",
    "sg:postcode":"01527",
    "sg:province":"MA",
    "sg:tags":[
        "truck"
    ],
    "wof:name":"Weston Truck & Trailer Svc Co",
    "wof:placetype":"venue"
},
  "geometry": {"coordinates":[-71.74499299999999,42.232448],"type":"Point"}
}