{
  "type": "Feature",
  "properties": {
    "addr:full":"580 South St Athol MA 01331",
    "addr:housenumber":"580",
    "addr:postcode":"01331",
    "addr:street":"South St",
    "iso:country":"US",
    "sg:address":"580 South St",
    "sg:city":"Athol",
    "sg:classifiers":[
        {
            "category":"Personal",
            "subcategory":"Barber",
            "type":"Services"
        }
    ],
    "sg:phone":"+1 978 249 4303",
    "sg:postcode":"01331",
    "sg:province":"MA",
    "wof:name":"Roussel's Barber Shop",
    "wof:placetype":"venue"
},
  "geometry": {"coordinates":[-72.230921,42.592389],"type":"Point"}
}