{
  "type": "Feature",
  "properties": {
    "addr:full":"106 Bassett Ln Hyannis MA 02601",
    "addr:housenumber":"106",
    "addr:postcode":"02601",
    "addr:street":"Bassett Ln",
    "iso:country":"US",
    "sg:address":"106 Bassett Ln",
    "sg:city":"Hyannis",
    "sg:classifiers":[
        {
            "category":"Home & Garden",
            "subcategory":"Furniture",
            "type":"Retail Goods"
        }
    ],
    "sg:phone":"+1 508 790 8212",
    "sg:postcode":"02601",
    "sg:province":"MA",
    "wof:name":"Home Furnishings By Bon Repose",
    "wof:placetype":"venue"
},
  "geometry": {"coordinates":[-70.291529,41.654612],"type":"Point"}
}