{
  "type": "Feature",
  "properties": {
    "addr:full":"11 Enon St Beverly MA 01915",
    "addr:housenumber":"11",
    "addr:postcode":"01915",
    "addr:street":"Enon St",
    "iso:country":"US",
    "sg:address":"11 Enon St",
    "sg:city":"Beverly",
    "sg:classifiers":[
        {
            "category":"Professional",
            "subcategory":"Business Services",
            "type":"Services"
        }
    ],
    "sg:phone":"+1 978 922 5755",
    "sg:postcode":"01915",
    "sg:province":"MA",
    "sg:tags":[
        "interior",
        "consultant",
        "design",
        "decorator"
    ],
    "wof:name":"Calico Corners",
    "wof:placetype":"venue"
},
  "geometry": {"coordinates":[-70.884479,42.584035],"type":"Point"}
}