{
  "type": "Feature",
  "properties": {
    "addr:full": "273 E Berkeley Street Roxbury MA 02118",
    "addr:housenumber": "273",
    "addr:postcode": "02118",
    "addr:street": "E Berkeley Street",
    "iso:country": "US",
    "sg:address": "273 E Berkeley Street",
    "sg:city": "Roxbury",
    "sg:classifiers": [
      {
        "category": "Retail",
        "subcategory": "Auto Repair",
        "type": "Services"
      }
    ],
    "sg:phone": "+1 617 426 1002",
    "sg:postcode": "02118",
    "sg:province": "MA",
    "wof:name": "E \u0026 S Auto",
    "wof:placetype": "venue"
  },
  "geometry": {"coordinates":[-71.063055,42.34325],"type":"Point"}
}
