{
  "type": "Feature",
  "properties": {
    "iso:country":"US",
    "sg:address":"273 E Berkeley Street",
    "sg:city":"Roxbury",
    "sg:classifiers":[
        {
            "category":"Retail",
            "subcategory":"Auto Repair",
            "type":"Services"
        }
    ],
    "sg:phone":"+1 617 426 1002",
    "sg:postcode":"02118",
    "sg:province":"MA",
    "wof:name":"E & S Auto",
    "wof:placetype":"venue"
},
  "geometry": {"coordinates":[-71.06305500000001,42.34325],"type":"Point"}
}