{
  "type": "Feature",
  "properties": {
    "addr:full":"470 Liberty St Hanson MA 02341",
    "addr:housenumber":"470",
    "addr:postcode":"02341",
    "addr:street":"Liberty St",
    "iso:country":"US",
    "sg:address":"470 Liberty St",
    "sg:city":"Hanson",
    "sg:classifiers":[
        {
            "category":"Personal",
            "subcategory":"Beauty Salon",
            "type":"Services"
        }
    ],
    "sg:phone":"+1 781 293 6973",
    "sg:postcode":"02341",
    "sg:province":"MA",
    "wof:name":"Salon Marquis",
    "wof:placetype":"venue"
},
  "geometry": {"coordinates":[-70.869562,42.066261],"type":"Point"}
}