{
  "type": "Feature",
  "properties": {
    "addr:full": "533 Ferry Street Everett MA 02149",
    "addr:housenumber": "533",
    "addr:postcode": "02149",
    "addr:street": "Ferry Street",
    "iso:country": "US",
    "ovtr:label": "Cold-Cut Factory, 533 Ferry St Everett MA US",
    "ovtr:similarity": 2.3961570262908936,
    "sg:address": "533 Ferry Street",
    "sg:city": "Everett",
    "sg:classifiers": [
      {
        "category": "Restaurant",
        "type": "Food \u0026 Drink"
      }
    ],
    "sg:phone": "+1 617 381 6328",
    "sg:postcode": "02149",
    "sg:province": "MA",
    "wof:name": "Cold-Cut Factory",
    "wof:placetype": "venue"
  },
  "geometry": {"coordinates":[-71.053913,42.419536],"type":"Point"}
}
