{
  "type": "Feature",
  "properties": {
    "iso:country":"US",
    "sg:address":"533 Ferry Street",
    "sg:city":"Everett",
    "sg:classifiers":[
        {
            "category":"Restaurant",
            "type":"Food & Drink"
        }
    ],
    "sg:phone":"+1 617 381 6328",
    "sg:postcode":"02149",
    "sg:province":"MA",
    "wof:name":"Cold-Cut Factory",
    "wof:placetype":"venue"
},
  "geometry": {"coordinates":[-71.05391299999999,42.419536],"type":"Point"}
}