{
  "type": "Feature",
  "properties": {
    "addr:full": "47 Marion Dr Kingston MA 02364",
    "addr:housenumber": "47",
    "addr:postcode": "02364",
    "addr:street": "Marion Dr",
    "iso:country": "US",
    "sg:address": "47 Marion Dr",
    "sg:city": "Kingston",
    "sg:classifiers": [
      {
        "category": "Real Estate",
        "subcategory": "Architect",
        "type": "Services"
      }
    ],
    "sg:phone": "+1 781 585 0280",
    "sg:postcode": "02364",
    "sg:province": "MA",
    "wof:name": "Braidenview Architects",
    "wof:placetype": "venue"
  },
  "geometry": {"coordinates":[-70.717898,41.976831],"type":"Point"}
}
