{
  "type": "Feature",
  "properties": {
    "iso:country":"US",
    "sg:address":"1001 Providence Rd",
    "sg:city":"Whitinsville",
    "sg:classifiers":[
        {
            "category":"Health Services",
            "subcategory":"Health Practitioner",
            "type":"Services"
        }
    ],
    "sg:phone":"+1 508 234 7544",
    "sg:postcode":"01588",
    "sg:province":"MA",
    "sg:tags":[
        "therapist",
        "physical"
    ],
    "wof:name":"Blackstone Valley Physical",
    "wof:placetype":"venue"
},
  "geometry": {"coordinates":[-71.643237,42.121508],"type":"Point"}
}