{
  "type": "Feature",
  "properties": {
    "addr:full":"173 Adams St North Adams MA 01267",
    "addr:housenumber":"173",
    "addr:postcode":"01267",
    "addr:street":"Adams St",
    "iso:country":"US",
    "sg:address":"173 Adams St",
    "sg:city":"North Adams",
    "sg:classifiers":[
        {
            "category":"Food & Beverages",
            "subcategory":"Groceries & Convenience Stores",
            "type":"Retail Goods"
        }
    ],
    "sg:phone":"+1 413 743 1535",
    "sg:postcode":"01267",
    "sg:province":"MA",
    "wof:name":"O'Connell Convenience Plus",
    "wof:placetype":"venue"
},
  "geometry": {"coordinates":[-73.189016,42.703576],"type":"Point"}
}