{
  "type": "Feature",
  "properties": {
    "addr:full":"166 County St Lakeville MA 02347",
    "addr:housenumber":"166",
    "addr:postcode":"02347",
    "addr:street":"County St",
    "iso:country":"US",
    "sg:address":"166 County St",
    "sg:city":"Lakeville",
    "sg:classifiers":[
        {
            "category":"Banks & Credit Unions",
            "subcategory":"Bank",
            "type":"Services"
        }
    ],
    "sg:phone":"+1 508 923 3415",
    "sg:postcode":"02347",
    "sg:province":"MA",
    "wof:name":"Mayflower Co Operative Bank",
    "wof:placetype":"venue"
},
  "geometry": {"coordinates":[-70.968706,41.807127],"type":"Point"}
}