{
  "type": "Feature",
  "properties": {
    "iso:country":"US",
    "sg:address":"8 Maple Ave",
    "sg:city":"Medford",
    "sg:classifiers":[
        {
            "category":"Manufacturing",
            "subcategory":"Wood Products",
            "type":"Manufacturing & Wholesale Goods"
        }
    ],
    "sg:phone":"+1 617 650 1512",
    "sg:postcode":"02155",
    "sg:province":"MA",
    "sg:tags":[
        "millwork-wholesale",
        "millwork",
        "manufacturer"
    ],
    "wof:name":"Joseph D Orsini",
    "wof:placetype":"venue"
},
  "geometry": {"coordinates":[-71.11588999999999,42.417496],"type":"Point"}
}