{
  "type": "Feature",
  "properties": {
    "iso:country":"US",
    "sg:address":"57 Fairfield St",
    "sg:city":"Dedham",
    "sg:classifiers":[
        {
            "category":"Professional",
            "subcategory":"Business Services",
            "type":"Services"
        }
    ],
    "sg:phone":"+1   ",
    "sg:postcode":"02026",
    "sg:province":"MA",
    "wof:name":"J & R Partnership",
    "wof:placetype":"venue"
},
  "geometry": {"coordinates":[-71.177781,42.266124],"type":"Point"}
}