{
  "type": "Feature",
  "properties": {
    "iso:country":"US",
    "sg:address":"699 Silver St",
    "sg:city":"Agawam",
    "sg:classifiers":[
        {
            "category":"Manufacturing",
            "subcategory":"Rubber & Plastics",
            "type":"Manufacturing & Wholesale Goods"
        }
    ],
    "sg:phone":"+1 413 789 1300",
    "sg:postcode":"01001",
    "sg:province":"MA",
    "sg:website":"www.campingcrafts.com",
    "wof:name":"Toner Plastic",
    "wof:placetype":"venue"
},
  "geometry": {"coordinates":[-72.652424,42.052827],"type":"Point"}
}