{
  "type": "Feature",
  "properties": {
    "addr:full": "699 Silver St Agawam MA 01001",
    "addr:housenumber": "699",
    "addr:postcode": "01001",
    "addr:street": "Silver St",
    "iso:country": "US",
    "sg:address": "699 Silver St",
    "sg:city": "Agawam",
    "sg:classifiers": [
      {
        "category": "Manufacturing",
        "subcategory": "Rubber \u0026 Plastics",
        "type": "Manufacturing \u0026 Wholesale Goods"
      }
    ],
    "sg:phone": "+1 413 789 1300",
    "sg:postcode": "01001",
    "sg:province": "MA",
    "sg:website": "www.campingcrafts.com",
    "wof:name": "Toner Plastic",
    "wof:placetype": "venue"
  },
  "geometry": {"coordinates":[-72.652424,42.052827],"type":"Point"}
}
