{
  "type": "Feature",
  "properties": {
    "addr:full":"200 North St Lot 26B Danvers MA 01923",
    "addr:housenumber":"200;26b",
    "addr:postcode":"01923",
    "addr:street":"North St Lot",
    "iso:country":"US",
    "sg:address":"200 North St Lot 26B",
    "sg:city":"Danvers",
    "sg:classifiers":[
        {
            "category":"Real Estate",
            "subcategory":"Real Estate Services",
            "type":"Services"
        },
        {
            "category":"Building & Trades",
            "subcategory":"Cleaning & Sanitation",
            "type":"Services"
        }
    ],
    "sg:phone":"+1 978 777 1745",
    "sg:postcode":"01923",
    "sg:province":"MA",
    "sg:tags":[
        "maintenance",
        "cleaners-interior"
    ],
    "wof:name":"Partners In Grime",
    "wof:placetype":"venue"
},
  "geometry": {"coordinates":[-70.959782,42.598151],"type":"Point"}
}