{
  "type": "Feature",
  "properties": {
    "addr:full": "105 Rockdale Ave New Bedford MA 02740",
    "addr:housenumber": "105",
    "addr:postcode": "02740",
    "addr:street": "Rockdale Ave",
    "iso:country": "US",
    "sg:address": "105 Rockdale Ave",
    "sg:city": "New Bedford",
    "sg:classifiers": [
      {
        "category": "Home \u0026 Garden",
        "subcategory": "Furniture",
        "type": "Retail Goods"
      }
    ],
    "sg:phone": "+1 508 997 7137",
    "sg:postcode": "02740",
    "sg:province": "MA",
    "wof:name": "Wayside Furniture Co",
    "wof:placetype": "venue"
  },
  "geometry": {"coordinates":[-70.935616,41.614425],"type":"Point"}
}
