{
  "type": "Feature",
  "properties": {
    "addr:full": "1125 Providence Hwy Walpole MA 02081",
    "addr:housenumber": "1125",
    "addr:postcode": "02081",
    "addr:street": "Providence Hwy",
    "iso:country": "US",
    "sg:address": "1125 Providence Hwy",
    "sg:city": "Walpole",
    "sg:classifiers": [
      {
        "category": "Travel",
        "subcategory": "Hotels \u0026 Motels",
        "type": "Entertainment"
      }
    ],
    "sg:phone": "+1 781 769 7900",
    "sg:postcode": "02081",
    "sg:province": "MA",
    "wof:name": "Four Points Hotel \u0026 Conference Center Norwood",
    "wof:placetype": "venue"
  },
  "geometry": {"coordinates":[-71.232498,42.121201],"type":"Point"}
}
