{
  "type": "Feature",
  "properties": {
    "addr:full": "380 Washington St Weymouth MA 02188",
    "addr:housenumber": "380",
    "addr:postcode": "02188",
    "addr:street": "Washington St",
    "iso:country": "US",
    "sg:address": "380 Washington St",
    "sg:city": "Weymouth",
    "sg:classifiers": [
      {
        "category": "Restaurant",
        "type": "Food \u0026 Drink"
      }
    ],
    "sg:phone": "+1 781 335 9817",
    "sg:postcode": "02188",
    "sg:province": "MA",
    "wof:name": "Caswell's Seafood",
    "wof:placetype": "venue"
  },
  "geometry": {"coordinates":[-70.958792,42.209869],"type":"Point"}
}
