{
  "type": "Feature",
  "properties": {
    "addr:full": "175 Edward Foster Rd Scituate MA 02066",
    "addr:housenumber": "175",
    "addr:postcode": "02066",
    "addr:street": "Edward Foster Rd",
    "iso:country": "US",
    "sg:address": "175 Edward Foster Rd",
    "sg:city": "Scituate",
    "sg:classifiers": [
      {
        "category": "Government",
        "subcategory": "Office",
        "type": "Public Place"
      }
    ],
    "sg:phone": "+1 781 544 9201",
    "sg:postcode": "02066",
    "sg:province": "MA",
    "sg:tags": [
      "government-state"
    ],
    "wof:name": "Massachusetts Dept Of Fish And Game",
    "wof:placetype": "venue"
  },
  "geometry": {"coordinates":[-70.716209,42.199001],"type":"Point"}
}
