{
  "type": "Feature",
  "properties": {
    "iso:country":"US",
    "sg:address":"14 Crystal Lake Dr",
    "sg:city":"Sudbury",
    "sg:classifiers":[
        {
            "category":"Communications",
            "type":"Services"
        }
    ],
    "sg:phone":"+1   ",
    "sg:postcode":"01776",
    "sg:province":"MA",
    "sg:tags":[
        "communication"
    ],
    "wof:name":"Vibe Communications",
    "wof:placetype":"venue"
},
  "geometry": {"coordinates":[-71.460741,42.392893],"type":"Point"}
}