{
  "type": "Feature",
  "properties": {
    "addr:full":"54 Canal Street Boston MA 02114",
    "addr:housenumber":"54",
    "addr:postcode":"02114",
    "addr:street":"Canal Street",
    "iso:country":"US",
    "sg:address":"54 Canal Street",
    "sg:city":"Boston",
    "sg:classifiers":[
        {
            "category":"Arts & Performance",
            "subcategory":"Art Gallery",
            "type":"Entertainment"
        },
        {
            "category":"Professional",
            "subcategory":"Computer Services",
            "type":"Services"
        }
    ],
    "sg:phone":"+1 617 723 8600",
    "sg:postcode":"02114",
    "sg:province":"MA",
    "sg:tags":[
        "cd-rom",
        "software"
    ],
    "wof:name":"Cognitive Arts",
    "wof:placetype":"venue"
},
  "geometry": {"coordinates":[-71.05944599999999,42.363926],"type":"Point"}
}