{
  "type": "Feature",
  "properties": {
    "addr:full": "105 Ash St Hopkinton MA 01748",
    "addr:housenumber": "105",
    "addr:postcode": "01748",
    "addr:street": "Ash St",
    "iso:country": "US",
    "sg:address": "105 Ash St",
    "sg:city": "Hopkinton",
    "sg:classifiers": [
      {
        "category": "Professional",
        "subcategory": "Advertising",
        "type": "Services"
      }
    ],
    "sg:phone": "+1 508 497 8900",
    "sg:postcode": "01748",
    "sg:province": "MA",
    "sg:tags": [
      "counselor"
    ],
    "wof:name": "Thomas Marketing Svc Corp",
    "wof:placetype": "venue"
  },
  "geometry": {"coordinates":[-71.507718,42.22093],"type":"Point"}
}
