{
  "type": "Feature",
  "properties": {
    "iso:country":"US",
    "sg:address":"537 Bolton St",
    "sg:city":"Marlborough",
    "sg:classifiers":[
        {
            "category":"Place Of Worship",
            "subcategory":"Church",
            "type":"Public Place"
        },
        {
            "category":"Place Of Worship",
            "type":"Public Place"
        }
    ],
    "sg:phone":"+1 508 485 9585",
    "sg:postcode":"01752",
    "sg:province":"MA",
    "sg:tags":[
        "lutheran",
        "america",
        "churches-lutheran",
        "churches-lutheran-evangelical"
    ],
    "wof:name":"St Stephen Lutheran Church",
    "wof:placetype":"venue"
},
  "geometry": {"coordinates":[-71.55315299999999,42.362582],"type":"Point"}
}