{
  "type": "Feature",
  "properties": {
    "addr:full":"9 Railroad Ave Wilbraham MA 01095",
    "addr:housenumber":"9",
    "addr:postcode":"01095",
    "addr:street":"Railroad Ave",
    "iso:country":"US",
    "sg:address":"9 Railroad Ave",
    "sg:city":"Wilbraham",
    "sg:classifiers":[
        {
            "category":"Retail",
            "subcategory":"Auto Repair",
            "type":"Services"
        }
    ],
    "sg:phone":"+1 413 596 4374",
    "sg:postcode":"01095",
    "sg:province":"MA",
    "sg:tags":[
        "wrecker"
    ],
    "wof:name":"R & S Towing & Recovery",
    "wof:placetype":"venue"
},
  "geometry": {"coordinates":[-72.43063100000001,42.151803],"type":"Point"}
}