{
  "type": "Feature",
  "properties": {
    "addr:full":"14 Mc Grath Hwy Somerville MA 02143",
    "addr:housenumber":"14",
    "addr:postcode":"02143",
    "addr:street":"Mc Grath Hwy",
    "iso:country":"US",
    "sg:address":"14 Mc Grath Hwy",
    "sg:city":"Somerville",
    "sg:classifiers":[
        {
            "category":"Health Services",
            "subcategory":"Health Practitioner",
            "type":"Services"
        }
    ],
    "sg:phone":"+1 617 623 6300",
    "sg:postcode":"02143",
    "sg:province":"MA",
    "sg:tags":[
        "therapy",
        "physical"
    ],
    "sg:website":"www.bostonsportsmed.com",
    "wof:name":"Boston Sports Medicine",
    "wof:placetype":"venue"
},
  "geometry": {"coordinates":[-71.085553,42.374515],"type":"Point"}
}