{
  "type": "Feature",
  "properties": {
    "addr:full": "1 Monroe Ln West Yarmouth MA 02673",
    "addr:housenumber": "1",
    "addr:postcode": "02673",
    "addr:street": "Monroe Ln",
    "iso:country": "US",
    "sg:address": "1 Monroe Ln",
    "sg:city": "West Yarmouth",
    "sg:classifiers": [
      {
        "category": "Building \u0026 Trades",
        "subcategory": "Construction",
        "type": "Services"
      }
    ],
    "sg:phone": "+1   ",
    "sg:postcode": "02673",
    "sg:province": "MA",
    "sg:tags": [
      "hanging",
      "contractor"
    ],
    "wof:name": "Eric Swanson Painting",
    "wof:placetype": "venue"
  },
  "geometry": {"coordinates":[-70.218223,41.668829],"type":"Point"}
}
