{
  "type": "Feature",
  "properties": {
    "iso:country":"US",
    "sg:address":"1 Monroe Ln",
    "sg:city":"West Yarmouth",
    "sg:classifiers":[
        {
            "category":"Building & Trades",
            "subcategory":"Construction",
            "type":"Services"
        }
    ],
    "sg:phone":"+1   ",
    "sg:postcode":"02673",
    "sg:province":"MA",
    "sg:tags":[
        "hanging",
        "contractor"
    ],
    "wof:name":"Eric Swanson Painting",
    "wof:placetype":"venue"
},
  "geometry": {"coordinates":[-70.21822299999999,41.668829],"type":"Point"}
}