{
  "type": "Feature",
  "properties": {
    "iso:country":"US",
    "sg:address":"17 Warren St",
    "sg:city":"Lowell",
    "sg:classifiers":[
        {
            "category":"Health Services",
            "subcategory":"Doctor",
            "type":"Services"
        }
    ],
    "sg:phone":"+1 978 937 9448",
    "sg:postcode":"01852",
    "sg:province":"MA",
    "sg:tags":[
        "physician",
        "surgeon"
    ],
    "wof:name":"Lowell Community Health Ctr",
    "wof:placetype":"venue"
},
  "geometry": {"coordinates":[-71.30657100000001,42.642868],"type":"Point"}
}