{
  "type": "Feature",
  "properties": {
    "addr:full": "59 E Haverhill St Lawrence MA 01841",
    "addr:housenumber": "59",
    "addr:postcode": "01841",
    "addr:street": "E Haverhill St",
    "iso:country": "US",
    "sg:address": "59 E Haverhill St",
    "sg:city": "Lawrence",
    "sg:classifiers": [
      {
        "category": "Real Estate",
        "subcategory": "Real Estate Agent",
        "type": "Services"
      }
    ],
    "sg:phone": "+1 978 688 8479",
    "sg:postcode": "01841",
    "sg:province": "MA",
    "wof:name": "Preview Realty",
    "wof:placetype": "venue"
  },
  "geometry": {"coordinates":[-71.156281,42.714779],"type":"Point"}
}
