{
  "type": "Feature",
  "properties": {
    "addr:full":"53 Exchange St Boston MA 02109",
    "addr:housenumber":"53",
    "addr:postcode":"02109",
    "addr:street":"Exchange St",
    "iso:country":"US",
    "sg:address":"53 Exchange St",
    "sg:city":"Boston",
    "sg:classifiers":[
        {
            "category":"Professional",
            "subcategory":"Lawyer & Legal Services",
            "type":"Services"
        }
    ],
    "sg:phone":"+1 617 570 1764",
    "sg:postcode":"02109",
    "sg:province":"MA",
    "sg:tags":[
        "attorney"
    ],
    "wof:name":"Jennifer L Burns Lwyr",
    "wof:placetype":"venue"
},
  "geometry": {"coordinates":[-71.055927,42.358107],"type":"Point"}
}