{
  "type": "Feature",
  "properties": {
    "addr:full": "10 Ayers Village Rd Methuen MA 01844",
    "addr:housenumber": "10",
    "addr:postcode": "01844",
    "addr:street": "Ayers Village Rd",
    "iso:country": "US",
    "sg:address": "10 Ayers Village Rd",
    "sg:city": "Methuen",
    "sg:classifiers": [
      {
        "category": "Recreation",
        "type": "Entertainment"
      }
    ],
    "sg:phone": "+1 978 683 4353",
    "sg:postcode": "01844",
    "sg:province": "MA",
    "sg:tags": [
      "lottery",
      "agent"
    ],
    "wof:name": "Common Grounds Cafe",
    "wof:placetype": "venue"
  },
  "geometry": {"coordinates":[-71.183003,42.791981],"type":"Point"}
}
