{
  "type": "Feature",
  "properties": {
    "iso:country":"US",
    "sg:address":"40 Schofield Dr",
    "sg:city":"Newton",
    "sg:classifiers":[
        {
            "category":"Professional",
            "subcategory":"Management & Consulting",
            "type":"Services"
        }
    ],
    "sg:phone":"+1   ",
    "sg:postcode":"02460",
    "sg:province":"MA",
    "sg:tags":[
        "business"
    ],
    "wof:name":"Dejean and Clemens",
    "wof:placetype":"venue"
},
  "geometry": {"coordinates":[-71.213031,42.361562],"type":"Point"}
}