{
  "type": "Feature",
  "properties": {
    "addr:full": "40 Schofield Dr Newton MA 02460",
    "addr:housenumber": "40",
    "addr:postcode": "02460",
    "addr:street": "Schofield Dr",
    "iso:country": "US",
    "sg:address": "40 Schofield Dr",
    "sg:city": "Newton",
    "sg:classifiers": [
      {
        "category": "Professional",
        "subcategory": "Management \u0026 Consulting",
        "type": "Services"
      }
    ],
    "sg:phone": "+1   ",
    "sg:postcode": "02460",
    "sg:province": "MA",
    "sg:tags": [
      "business"
    ],
    "wof:name": "Dejean and Clemens",
    "wof:placetype": "venue"
  },
  "geometry": {"coordinates":[-71.213031,42.361562],"type":"Point"}
}
