{
  "type": "Feature",
  "properties": {
    "addr:full":"44 5th St Norwood MA 02062",
    "addr:housenumber":"44",
    "addr:postcode":"02062",
    "addr:street":"5Th St",
    "iso:country":"US",
    "sg:address":"44 5th St",
    "sg:city":"Norwood",
    "sg:classifiers":[
        {
            "category":"Professional",
            "subcategory":"Engineering",
            "type":"Services"
        }
    ],
    "sg:phone":"+1   ",
    "sg:postcode":"02062",
    "sg:province":"MA",
    "wof:name":"Arttech USA Inc",
    "wof:placetype":"venue"
},
  "geometry": {"coordinates":[-71.18875199999999,42.185232],"type":"Point"}
}