{
  "type": "Feature",
  "properties": {
    "addr:full": "407 Mystic Ave Medford MA 02155",
    "addr:housenumber": "407",
    "addr:postcode": "02155",
    "addr:street": "Mystic Ave",
    "iso:country": "US",
    "sg:address": "407 Mystic Ave",
    "sg:city": "Medford",
    "sg:classifiers": [
      {
        "category": "Retail",
        "subcategory": "Auto Rental",
        "type": "Services"
      }
    ],
    "sg:phone": "+1 781 391 3224",
    "sg:postcode": "02155",
    "sg:province": "MA",
    "sg:tags": [
      "renting",
      "truck",
      "leasing"
    ],
    "wof:name": "Penske Truck Leasing",
    "wof:placetype": "venue"
  },
  "geometry": {"coordinates":[-71.09793,42.401701],"type":"Point"}
}
