{
  "type": "Feature",
  "properties": {
    "iso:country":"US",
    "sg:address":"407 Mystic Ave",
    "sg:city":"Medford",
    "sg:classifiers":[
        {
            "category":"Retail",
            "subcategory":"Auto Rental",
            "type":"Services"
        }
    ],
    "sg:phone":"+1 781 391 3224",
    "sg:postcode":"02155",
    "sg:province":"MA",
    "sg:tags":[
        "renting",
        "truck",
        "leasing"
    ],
    "wof:name":"Penske Truck Leasing",
    "wof:placetype":"venue"
},
  "geometry": {"coordinates":[-71.09793000000001,42.401701],"type":"Point"}
}