{
  "type": "Feature",
  "properties": {
    "iso:country":"US",
    "sg:address":"189 Clinton St",
    "sg:city":"Brockton",
    "sg:classifiers":[
        {
            "category":"Retail",
            "subcategory":"Car Wash",
            "type":"Services"
        }
    ],
    "sg:phone":"+1 508 580 0213",
    "sg:postcode":"02302",
    "sg:province":"MA",
    "sg:tags":[
        "polishing",
        "washing"
    ],
    "wof:name":"Campello Car Care",
    "wof:placetype":"venue"
},
  "geometry": {"coordinates":[-71.013375,42.065245],"type":"Point"}
}