{
  "type": "Feature",
  "properties": {
    "addr:full": "2504 Main St West Barnstable MA 02668",
    "addr:housenumber": "2504",
    "addr:postcode": "02668",
    "addr:street": "Main St",
    "iso:country": "US",
    "sg:address": "2504 Main St",
    "sg:city": "West Barnstable",
    "sg:classifiers": [
      {
        "category": "Arts \u0026 Performance",
        "subcategory": "Art Gallery",
        "type": "Entertainment"
      }
    ],
    "sg:phone": "+1 508 744 6984",
    "sg:postcode": "02668",
    "sg:province": "MA",
    "wof:name": "Dog Day Studio \u0026 Gallery",
    "wof:placetype": "venue"
  },
  "geometry": {"coordinates":[-70.323994,41.701592],"type":"Point"}
}
