{
  "type": "Feature",
  "properties": {
    "iso:country":"US",
    "sg:address":"2504 Main St",
    "sg:city":"West Barnstable",
    "sg:classifiers":[
        {
            "category":"Arts & Performance",
            "subcategory":"Art Gallery",
            "type":"Entertainment"
        }
    ],
    "sg:phone":"+1 508 744 6984",
    "sg:postcode":"02668",
    "sg:province":"MA",
    "wof:name":"Dog Day Studio & Gallery",
    "wof:placetype":"venue"
},
  "geometry": {"coordinates":[-70.323994,41.701592],"type":"Point"}
}