{
  "type": "Feature",
  "properties": {
    "iso:country":"US",
    "sg:address":"3850 Mystic Valley Parkway",
    "sg:city":"Medford",
    "sg:classifiers":[
        {
            "category":"Shopping",
            "subcategory":"Crafts & Fabrics",
            "type":"Retail Goods"
        }
    ],
    "sg:phone":"+1 781 396 2090",
    "sg:postcode":"02155",
    "sg:province":"MA",
    "sg:tags":[
        "art"
    ],
    "wof:name":"Oriental Arts & Crafts Company",
    "wof:placetype":"venue"
},
  "geometry": {"coordinates":[-71.092286,42.404903],"type":"Point"}
}