{
  "type": "Feature",
  "properties": {
    "iso:country":"US",
    "sg:address":"27 Shore Dr",
    "sg:city":"Forestdale",
    "sg:classifiers":[
        {
            "category":"Professional",
            "type":"Services"
        }
    ],
    "sg:phone":"+1   ",
    "sg:postcode":"02644",
    "sg:province":"MA",
    "wof:name":"F & F Fabrication",
    "wof:placetype":"venue"
},
  "geometry": {"coordinates":[-70.499386,41.677854],"type":"Point"}
}