{
  "type": "Feature",
  "properties": {
    "iso:country":"US",
    "sg:address":"60 Needham St",
    "sg:city":"Newton",
    "sg:classifiers":[
        {
            "category":"Shopping",
            "type":"Retail Goods"
        }
    ],
    "sg:phone":"+1 617 527 9330",
    "sg:postcode":"02461",
    "sg:province":"MA",
    "sg:tags":[
        "picture",
        "frame"
    ],
    "sg:website":"www.cornersframing.com",
    "wof:name":"Corners Picture Framing",
    "wof:placetype":"venue"
},
  "geometry": {"coordinates":[-71.210874,42.314879],"type":"Point"}
}