{
  "type": "Feature",
  "properties": {
    "iso:country":"US",
    "sg:address":"305 Main St",
    "sg:city":"Southbridge",
    "sg:classifiers":[
        {
            "category":"Health Services",
            "subcategory":"Doctor",
            "type":"Services"
        }
    ],
    "sg:phone":"+1 508 765 0880",
    "sg:postcode":"01550",
    "sg:province":"MA",
    "sg:tags":[
        "dentist"
    ],
    "wof:name":"Southbridge Family Dental Center",
    "wof:placetype":"venue"
},
  "geometry": {"coordinates":[-72.034103,42.0751],"type":"Point"}
}