{
  "type": "Feature",
  "properties": {
    "addr:full": "305 Main St Southbridge MA 01550",
    "addr:housenumber": "305",
    "addr:postcode": "01550",
    "addr:street": "Main St",
    "iso:country": "US",
    "ovtr:label": "Southbridge Family Dental, 305 Main St Southbridge MA US",
    "ovtr:similarity": 3.882812023162842,
    "sg:address": "305 Main St",
    "sg:city": "Southbridge",
    "sg:classifiers": [
      {
        "category": "Health Services",
        "subcategory": "Doctor",
        "type": "Services"
      }
    ],
    "sg:phone": "+1 508 765 0880",
    "sg:postcode": "01550",
    "sg:province": "MA",
    "sg:tags": [
      "dentist"
    ],
    "wof:name": "Southbridge Family Dental Center",
    "wof:placetype": "venue"
  },
  "geometry": {"coordinates":[-72.034103,42.0751],"type":"Point"}
}
