{
  "type": "Feature",
  "properties": {
    "addr:full":"129 Mount Auburn St Cambridge MA 02138",
    "addr:housenumber":"129",
    "addr:postcode":"02138",
    "addr:street":"Mount Auburn St",
    "iso:country":"US",
    "sg:address":"129 Mount Auburn St",
    "sg:city":"Cambridge",
    "sg:classifiers":[
        {
            "category":"Professional",
            "subcategory":"Lawyer & Legal Services",
            "type":"Services"
        }
    ],
    "sg:phone":"+1 617 576 0600",
    "sg:postcode":"02138",
    "sg:province":"MA",
    "wof:name":"McCabe Kathleen C Atty",
    "wof:placetype":"venue"
},
  "geometry": {"coordinates":[-71.12359600000001,42.3736],"type":"Point"}
}