{
  "type": "Feature",
  "properties": {
    "addr:full":"51 Ludlow St Belchertown MA 01007",
    "addr:housenumber":"51",
    "addr:postcode":"01007",
    "addr:street":"Ludlow St",
    "iso:country":"US",
    "sg:address":"51 Ludlow St",
    "sg:city":"Belchertown",
    "sg:classifiers":[
        {
            "category":"Farming",
            "subcategory":"Poultry Farm",
            "type":"Manufacturing & Wholesale Goods"
        }
    ],
    "sg:phone":"+1 413 323 6046",
    "sg:postcode":"01007",
    "sg:province":"MA",
    "sg:tags":[
        "egg"
    ],
    "wof:name":"Twin Willows Turkey Farm",
    "wof:placetype":"venue"
},
  "geometry": {"coordinates":[-72.410481,42.237999],"type":"Point"}
}