{
  "type": "Feature",
  "properties": {
    "addr:full": "4052 County St Somerset MA 02726",
    "addr:housenumber": "4052",
    "addr:postcode": "02726",
    "addr:street": "County St",
    "iso:country": "US",
    "sg:address": "4052 County St",
    "sg:city": "Somerset",
    "sg:classifiers": [
      {
        "category": "Autos \u0026 Motor Vehicles",
        "subcategory": "Automobile Sales",
        "type": "Retail Goods"
      }
    ],
    "sg:phone": "+1   ",
    "sg:postcode": "02726",
    "sg:province": "MA",
    "sg:tags": [
      "used"
    ],
    "wof:name": "Shady Tree Auto Sales",
    "wof:placetype": "venue"
  },
  "geometry": {"coordinates":[-71.133201,41.79023],"type":"Point"}
}
