{
  "type": "Feature",
  "properties": {
    "addr:full": "5 Revere St 2 Cambridge MA 02138",
    "addr:housenumber": "5;2",
    "addr:postcode": "02138",
    "addr:street": "Revere St",
    "iso:country": "US",
    "sg:address": "5 Revere St 2",
    "sg:city": "Cambridge",
    "sg:classifiers": [
      {
        "category": "Health Services",
        "subcategory": "Doctor",
        "type": "Services"
      }
    ],
    "sg:phone": "+1 617 876 9416",
    "sg:postcode": "02138",
    "sg:province": "MA",
    "sg:tags": [
      "psychiatry",
      "physician",
      "surgeon",
      "surgeons"
    ],
    "wof:name": "Stephen E Sternbach",
    "wof:placetype": "venue"
  },
  "geometry": {"coordinates":[-71.124123,42.373699],"type":"Point"}
}
