{
  "type": "Feature",
  "properties": {
    "iso:country":"US",
    "sg:address":"28 Middlesex Rd",
    "sg:city":"Chestnut Hill",
    "sg:classifiers":[
        {
            "category":"Organizations",
            "subcategory":"Community Association",
            "type":"Services"
        }
    ],
    "sg:phone":"+1 617 566 9066",
    "sg:postcode":"02467",
    "sg:province":"MA",
    "sg:tags":[
        "club"
    ],
    "wof:name":"Longwood Covered Courts",
    "wof:placetype":"venue"
},
  "geometry": {"coordinates":[-71.165232,42.326006],"type":"Point"}
}