{
  "type": "Feature",
  "properties": {
    "addr:full": "28 Middlesex Rd Chestnut Hill MA 02467",
    "addr:housenumber": "28",
    "addr:postcode": "02467",
    "addr:street": "Middlesex Rd",
    "iso:country": "US",
    "ovtr:label": "Longwood Covered Courts, 28 Middlesex Rd Chestnut Hill MA US",
    "ovtr:similarity": 2.342094898223877,
    "sg:address": "28 Middlesex Rd",
    "sg:city": "Chestnut Hill",
    "sg:classifiers": [
      {
        "category": "Organizations",
        "subcategory": "Community Association",
        "type": "Services"
      }
    ],
    "sg:phone": "+1 617 566 9066",
    "sg:postcode": "02467",
    "sg:province": "MA",
    "sg:tags": [
      "club"
    ],
    "wof:name": "Longwood Covered Courts",
    "wof:placetype": "venue"
  },
  "geometry": {"coordinates":[-71.165232,42.326006],"type":"Point"}
}
