{
  "type": "Feature",
  "properties": {
    "addr:full":"195 Mountain Ave Malden MA 02148",
    "addr:housenumber":"195",
    "addr:postcode":"02148",
    "addr:street":"Mountain Ave",
    "iso:country":"US",
    "sg:address":"195 Mountain Ave",
    "sg:city":"Malden",
    "sg:classifiers":[
        {
            "category":"Restaurant",
            "type":"Food & Drink"
        }
    ],
    "sg:phone":"+1   ",
    "sg:postcode":"02148",
    "sg:province":"MA",
    "sg:tags":[
        "eating"
    ],
    "wof:name":"J & B Pizza and Subs Inc",
    "wof:placetype":"venue"
},
  "geometry": {"coordinates":[-71.064143,42.431218],"type":"Point"}
}