{
  "type": "Feature",
  "properties": {
    "iso:country":"US",
    "sg:address":"1 Park St",
    "sg:city":"Leominster",
    "sg:classifiers":[
        {
            "category":"Restaurant",
            "type":"Food & Drink"
        }
    ],
    "sg:menulink":"http://www.allmenus.com/ma/leominster/131714-subway/menu/",
    "sg:phone":"+1 978 534 7055",
    "sg:postcode":"01453",
    "sg:province":"MA",
    "sg:tags":[
        "american",
        "sandwich"
    ],
    "wof:name":"Subway",
    "wof:placetype":"venue"
},
  "geometry": {"coordinates":[-71.760153,42.525866],"type":"Point"}
}