{
  "type": "Feature",
  "properties": {
    "addr:full": "1 Park St Leominster MA 01453",
    "addr:housenumber": "1",
    "addr:postcode": "01453",
    "addr:street": "Park St",
    "iso:country": "US",
    "ovtr:label": "Subway, 1 Park St Leominster MA US",
    "ovtr:similarity": 3.0403099060058594,
    "sg:address": "1 Park St",
    "sg:city": "Leominster",
    "sg:classifiers": [
      {
        "category": "Restaurant",
        "type": "Food \u0026 Drink"
      }
    ],
    "sg:menulink": "http://www.allmenus.com/ma/leominster/131714-subway/menu/",
    "sg:phone": "+1 978 534 7055",
    "sg:postcode": "01453",
    "sg:province": "MA",
    "sg:tags": [
      "american",
      "sandwich"
    ],
    "wof:name": "Subway",
    "wof:placetype": "venue"
  },
  "geometry": {"coordinates":[-71.760153,42.525866],"type":"Point"}
}
