{
  "type": "Feature",
  "properties": {
    "iso:country":"US",
    "sg:address":"296 Highland Ave",
    "sg:city":"Salem",
    "sg:classifiers":[
        {
            "category":"Food & Beverages",
            "subcategory":"Bakery",
            "type":"Retail Goods"
        }
    ],
    "sg:phone":"+1 978 740 0001",
    "sg:postcode":"01970",
    "sg:province":"MA",
    "sg:tags":[
        "bagel"
    ],
    "wof:name":"Bagel Place",
    "wof:placetype":"venue"
},
  "geometry": {"coordinates":[-70.926062,42.501211],"type":"Point"}
}