{
  "type": "Feature",
  "properties": {
    "addr:full":"116 Union St Lynn MA 01902",
    "addr:housenumber":"116",
    "addr:postcode":"01902",
    "addr:street":"Union St",
    "iso:country":"US",
    "sg:address":"116 Union St",
    "sg:city":"Lynn",
    "sg:classifiers":[
        {
            "category":"Banks & Credit Unions",
            "subcategory":"Bank",
            "type":"Services"
        }
    ],
    "sg:phone":"+1 781 581 6390",
    "sg:postcode":"01902",
    "sg:province":"MA",
    "sg:tags":[
        "money",
        "order"
    ],
    "wof:name":"LA Nacional Corp",
    "wof:placetype":"venue"
},
  "geometry": {"coordinates":[-70.941124,42.467181],"type":"Point"}
}