{
  "type": "Feature",
  "properties": {
    "addr:full": "60 Brewster Dr Bridgewater MA 02324",
    "addr:housenumber": "60",
    "addr:postcode": "02324",
    "addr:street": "Brewster Dr",
    "iso:country": "US",
    "sg:address": "60 Brewster Dr",
    "sg:city": "Bridgewater",
    "sg:classifiers": [
      {
        "category": "Government",
        "subcategory": "Court House",
        "type": "Public Place"
      }
    ],
    "sg:phone": "+1 508 697 4707",
    "sg:postcode": "02324",
    "sg:province": "MA",
    "sg:tags": [
      "justice",
      "peace"
    ],
    "wof:name": "Happily Ever After",
    "wof:placetype": "venue"
  },
  "geometry": {"coordinates":[-70.999138,41.984063],"type":"Point"}
}
