{
  "type": "Feature",
  "properties": {
    "iso:country":"US",
    "sg:address":"3 Middle St",
    "sg:city":"Newburyport",
    "sg:classifiers":[
        {
            "category":"Shopping",
            "subcategory":"Books",
            "type":"Retail Goods"
        }
    ],
    "sg:phone":"+1 978 463 2000",
    "sg:postcode":"01950",
    "sg:province":"MA",
    "sg:tags":[
        "dealer"
    ],
    "wof:name":"Middle Street Bookstore",
    "wof:placetype":"venue"
},
  "geometry": {"coordinates":[-70.868881,42.810406],"type":"Point"}
}