{
  "type": "Feature",
  "properties": {
    "iso:country":"US",
    "sg:address":"120 Mount Auburn St",
    "sg:city":"Watertown",
    "sg:classifiers":[
        {
            "category":"Social Services",
            "subcategory":"Retirement Home",
            "type":"Services"
        },
        {
            "category":"Social Services",
            "subcategory":"Adult Care",
            "type":"Services"
        }
    ],
    "sg:phone":"+1 617 924 4510",
    "sg:postcode":"02472",
    "sg:province":"MA",
    "sg:tags":[
        "living",
        "apartment",
        "facility",
        "assisted",
        "hotel",
        "community",
        "elder"
    ],
    "sg:website":"http://www.seniorcare.org",
    "wof:name":"Marshall Home Retirement Living with Assisted Living Services",
    "wof:placetype":"venue"
},
  "geometry": {"coordinates":[-71.179169,42.367764],"type":"Point"}
}