{
  "type": "Feature",
  "properties": {
    "addr:full": "35 Arbor St Wenham MA 01984",
    "addr:housenumber": "35",
    "addr:postcode": "01984",
    "addr:street": "Arbor St",
    "iso:country": "US",
    "sg:address": "35 Arbor St",
    "sg:city": "Wenham",
    "sg:classifiers": [
      {
        "category": "Home \u0026 Garden",
        "subcategory": "Household Appliances",
        "type": "Retail Goods"
      },
      {
        "category": "Building \u0026 Trades",
        "subcategory": "Construction",
        "type": "Services"
      }
    ],
    "sg:phone": "+1 978 468 5892",
    "sg:postcode": "01984",
    "sg:province": "MA",
    "sg:tags": [
      "repair",
      "major",
      "dishwashing",
      "system",
      "machine",
      "contractor",
      "air conditioning"
    ],
    "sg:website": "http://www.theperfectclimate4you.com",
    "wof:name": "The Perfect Climate",
    "wof:placetype": "venue"
  },
  "geometry": {"coordinates":[-70.887329,42.609482],"type":"Point"}
}
