{
  "type": "Feature",
  "properties": {
    "iso:country":"US",
    "sg:address":"35 Arbor St",
    "sg:city":"Wenham",
    "sg:classifiers":[
        {
            "category":"Home & Garden",
            "subcategory":"Household Appliances",
            "type":"Retail Goods"
        },
        {
            "category":"Building & Trades",
            "subcategory":"Construction",
            "type":"Services"
        }
    ],
    "sg:phone":"+1 978 468 5892",
    "sg:postcode":"01984",
    "sg:province":"MA",
    "sg:tags":[
        "repair",
        "major",
        "dishwashing",
        "system",
        "machine",
        "contractor",
        "air conditioning"
    ],
    "sg:website":"http://www.theperfectclimate4you.com",
    "wof:name":"The Perfect Climate",
    "wof:placetype":"venue"
},
  "geometry": {"coordinates":[-70.88732899999999,42.609482],"type":"Point"}
}