{
  "type": "Feature",
  "properties": {
    "iso:country":"US",
    "sg:address":"467 Huron Ave",
    "sg:city":"Cambridge",
    "sg:classifiers":[
        {
            "category":"Professional",
            "type":"Services"
        }
    ],
    "sg:phone":"+1 617 876 4119",
    "sg:postcode":"02138",
    "sg:province":"MA",
    "sg:tags":[
        "establishment"
    ],
    "wof:name":"Ann Kearsley Design",
    "wof:placetype":"venue"
},
  "geometry": {"coordinates":[-71.14346999999999,42.380338],"type":"Point"}
}