{
  "type": "Feature",
  "properties": {
    "addr:full": "467 Huron Ave Cambridge MA 02138",
    "addr:housenumber": "467",
    "addr:postcode": "02138",
    "addr:street": "Huron Ave",
    "iso:country": "US",
    "sg:address": "467 Huron Ave",
    "sg:city": "Cambridge",
    "sg:classifiers": [
      {
        "category": "Professional",
        "type": "Services"
      }
    ],
    "sg:phone": "+1 617 876 4119",
    "sg:postcode": "02138",
    "sg:province": "MA",
    "sg:tags": [
      "establishment"
    ],
    "wof:name": "Ann Kearsley Design",
    "wof:placetype": "venue"
  },
  "geometry": {"coordinates":[-71.14347,42.380338],"type":"Point"}
}
