{
  "type": "Feature",
  "properties": {
    "addr:full":"11 Park Ln Newton MA 02459",
    "addr:housenumber":"11",
    "addr:postcode":"02459",
    "addr:street":"Park Ln",
    "iso:country":"US",
    "sg:address":"11 Park Ln",
    "sg:city":"Newton",
    "sg:classifiers":[
        {
            "category":"Travel",
            "subcategory":"Hotels & Motels",
            "type":"Entertainment"
        }
    ],
    "sg:phone":"+1   ",
    "sg:postcode":"02459",
    "sg:province":"MA",
    "sg:tags":[
        "operation"
    ],
    "wof:name":"Lane Park Bed & Breakfast",
    "wof:placetype":"venue"
},
  "geometry": {"coordinates":[-71.202055,42.333116],"type":"Point"}
}