{
  "type": "Feature",
  "properties": {
    "iso:country":"US",
    "sg:address":"2222 Massachusetts Ave",
    "sg:city":"Cambridge",
    "sg:classifiers":[
        {
            "category":"Organizations",
            "subcategory":"Religious Organization",
            "type":"Services"
        }
    ],
    "sg:phone":"+1 617 868 5032",
    "sg:postcode":"02140",
    "sg:province":"MA",
    "wof:name":"Weston Jesuit Community",
    "wof:placetype":"venue"
},
  "geometry": {"coordinates":[-71.125405,42.393017],"type":"Point"}
}