{
  "type": "Feature",
  "properties": {
    "addr:full":"1420 State Hwy 6 Alt East Dennis MA 02660",
    "addr:housenumber":"1420",
    "addr:postcode":"02660",
    "addr:street":"State Hwy 6",
    "iso:country":"US",
    "sg:address":"1420 State Hwy 6 Alt",
    "sg:city":"East Dennis",
    "sg:classifiers":[
        {
            "category":"Professional",
            "subcategory":"Lawyer & Legal Services",
            "type":"Services"
        }
    ],
    "sg:phone":"+1 508 385 8301",
    "sg:postcode":"02660",
    "sg:province":"MA",
    "sg:tags":[
        "attorney"
    ],
    "wof:name":"James J Higgins",
    "wof:placetype":"venue"
},
  "geometry": {"coordinates":[-70.163431,41.743062],"type":"Point"}
}