{
  "type": "Feature",
  "properties": {
    "addr:full": "357 Hanover St Boston MA 02113",
    "addr:housenumber": "357",
    "addr:postcode": "02113",
    "addr:street": "Hanover St",
    "iso:country": "US",
    "sg:address": "357 Hanover St",
    "sg:city": "Boston",
    "sg:classifiers": [
      {
        "category": "Health Services",
        "subcategory": "Clinic",
        "type": "Services"
      }
    ],
    "sg:phone": "+1 617 742 8111",
    "sg:postcode": "02113",
    "sg:province": "MA",
    "sg:tags": [
      "parapsychologist"
    ],
    "wof:name": "Anastasia's Card \u0026 Palm",
    "wof:placetype": "venue"
  },
  "geometry": {"coordinates":[-71.053654,42.364356],"type":"Point"}
}
