{
  "type": "Feature",
  "properties": {
    "iso:country":"US",
    "sg:address":"357 Hanover St",
    "sg:city":"Boston",
    "sg:classifiers":[
        {
            "category":"Health Services",
            "subcategory":"Clinic",
            "type":"Services"
        }
    ],
    "sg:phone":"+1 617 742 8111",
    "sg:postcode":"02113",
    "sg:province":"MA",
    "sg:tags":[
        "parapsychologist"
    ],
    "wof:name":"Anastasia's Card & Palm",
    "wof:placetype":"venue"
},
  "geometry": {"coordinates":[-71.05365399999999,42.364356],"type":"Point"}
}