{
  "type": "Feature",
  "properties": {
    "addr:full":"3 Family Circle Dr Charlton MA 01507",
    "addr:housenumber":"3",
    "addr:postcode":"01507",
    "addr:street":"Family Circle Dr",
    "iso:country":"US",
    "sg:address":"3 Family Circle Dr",
    "sg:city":"Charlton",
    "sg:classifiers":[
        {
            "category":"Professional",
            "subcategory":"Business Services",
            "type":"Services"
        }
    ],
    "sg:phone":"+1 508 248 0576",
    "sg:postcode":"01507",
    "sg:province":"MA",
    "sg:tags":[
        "interior",
        "consultant",
        "design",
        "decorator"
    ],
    "wof:name":"American Installations",
    "wof:placetype":"venue"
},
  "geometry": {"coordinates":[-71.990188,42.08687],"type":"Point"}
}