{
  "type": "Feature",
  "properties": {
    "iso:country":"US",
    "sg:address":"6 Anthony St",
    "sg:city":"Adams",
    "sg:classifiers":[
        {
            "category":"Organizations",
            "subcategory":"Community Association",
            "type":"Services"
        }
    ],
    "sg:phone":"+1 413 743 3600",
    "sg:postcode":"01220",
    "sg:province":"MA",
    "sg:tags":[
        "club"
    ],
    "wof:name":"Mountain Club",
    "wof:placetype":"venue"
},
  "geometry": {"coordinates":[-73.104313,42.631549],"type":"Point"}
}