{
  "type": "Feature",
  "properties": {
    "addr:full": "6 Anthony St Adams MA 01220",
    "addr:housenumber": "6",
    "addr:postcode": "01220",
    "addr:street": "Anthony St",
    "iso:country": "US",
    "ovtr:label": "Mountain Club, 6 Anthony St Adams MA US",
    "ovtr:similarity": 2.924138069152832,
    "sg:address": "6 Anthony St",
    "sg:city": "Adams",
    "sg:classifiers": [
      {
        "category": "Organizations",
        "subcategory": "Community Association",
        "type": "Services"
      }
    ],
    "sg:phone": "+1 413 743 3600",
    "sg:postcode": "01220",
    "sg:province": "MA",
    "sg:tags": [
      "club"
    ],
    "wof:name": "Mountain Club",
    "wof:placetype": "venue"
  },
  "geometry": {"coordinates":[-73.104313,42.631549],"type":"Point"}
}
