{
  "type": "Feature",
  "properties": {
    "addr:full":"84 Gainsborough St Boston MA 02115",
    "addr:housenumber":"84",
    "addr:postcode":"02115",
    "addr:street":"Gainsborough St",
    "iso:country":"US",
    "sg:address":"84 Gainsborough St",
    "sg:city":"Boston",
    "sg:classifiers":[
        {
            "category":"Wholesale",
            "subcategory":"Medical Equipment & Supplies",
            "type":"Manufacturing & Wholesale Goods"
        }
    ],
    "sg:phone":"+1 617 267 2951",
    "sg:postcode":"02115",
    "sg:province":"MA",
    "sg:tags":[
        "pharmaceutical",
        "products-wholesale",
        "manufacturer"
    ],
    "wof:name":"Bioventures Consulting",
    "wof:placetype":"venue"
},
  "geometry": {"coordinates":[-71.087778,42.342234],"type":"Point"}
}