{
  "type": "Feature",
  "properties": {
    "iso:country":"US",
    "sg:address":"15 South Rd",
    "sg:city":"Heath",
    "sg:phone":"+1 413 337 5754",
    "sg:postcode":"01346",
    "sg:province":"MA",
    "sg:tags":[
        "vegetable",
        "farm",
        "fruit",
        "shipper",
        "grower"
    ],
    "wof:name":"Full Circle Farm",
    "wof:placetype":"venue"
},
  "geometry": {"coordinates":[-72.82260100000001,42.671379],"type":"Point"}
}