{
  "type": "Feature",
  "properties": {
    "addr:full":"100 Copeland Dr Ste 5 Mansfield MA 02048",
    "addr:housenumber":"100",
    "addr:postcode":"02048",
    "addr:street":"Copeland Dr Ste 5",
    "iso:country":"US",
    "sg:address":"100 Copeland Dr Ste 5",
    "sg:city":"Mansfield",
    "sg:classifiers":[
        {
            "category":"Health Services",
            "subcategory":"Doctor",
            "type":"Services"
        },
        {
            "category":"Health Services",
            "subcategory":"Dentist",
            "type":"Services"
        }
    ],
    "sg:phone":"+1 508 339 3055",
    "sg:postcode":"02048",
    "sg:province":"MA",
    "sg:tags":[
        "dentists-oral",
        "physician",
        "maxillofacial",
        "surgeons",
        "surgery",
        "oral"
    ],
    "wof:name":"Roxana Z Delcea Dmd",
    "wof:placetype":"venue"
},
  "geometry": {"coordinates":[-71.22923299999999,42.030449],"type":"Point"}
}