{
  "type": "Feature",
  "properties": {
    "iso:country":"US",
    "sg:address":"9 West Rd",
    "sg:city":"Orleans",
    "sg:classifiers":[
        {
            "category":"Shopping",
            "subcategory":"Bicycles & Sporting Goods",
            "type":"Retail Goods"
        }
    ],
    "sg:phone":"+1 508 255 9154",
    "sg:postcode":"02653",
    "sg:province":"MA",
    "wof:name":"Olympia Sports",
    "wof:placetype":"venue"
},
  "geometry": {"coordinates":[-70.00010399999999,41.780525],"type":"Point"}
}