{
  "type": "Feature",
  "properties": {
    "addr:full": "9 West Rd Orleans MA 02653",
    "addr:housenumber": "9",
    "addr:postcode": "02653",
    "addr:street": "West Rd",
    "iso:country": "US",
    "sg:address": "9 West Rd",
    "sg:city": "Orleans",
    "sg:classifiers": [
      {
        "category": "Shopping",
        "subcategory": "Bicycles \u0026 Sporting Goods",
        "type": "Retail Goods"
      }
    ],
    "sg:phone": "+1 508 255 9154",
    "sg:postcode": "02653",
    "sg:province": "MA",
    "wof:name": "Olympia Sports",
    "wof:placetype": "venue"
  },
  "geometry": {"coordinates":[-70.000104,41.780525],"type":"Point"}
}
