{
  "type": "Feature",
  "properties": {
    "iso:country":"US",
    "sg:address":"2 Sutton Ave",
    "sg:city":"Oxford",
    "sg:classifiers":[
        {
            "category":"Restaurant",
            "type":"Food & Drink"
        }
    ],
    "sg:phone":"+1 508 987 5106",
    "sg:postcode":"01540",
    "sg:province":"MA",
    "sg:tags":[
        "pizza"
    ],
    "wof:name":"Dairy Express",
    "wof:placetype":"venue"
},
  "geometry": {"coordinates":[-71.863619,42.116957],"type":"Point"}
}