{
  "type": "Feature",
  "properties": {
    "iso:country":"US",
    "sg:address":"245 Maple St",
    "sg:city":"Lynn",
    "sg:classifiers":[
        {
            "category":"Government",
            "subcategory":"Post Office",
            "type":"Public Place"
        }
    ],
    "sg:phone":"+1 781 000 1111",
    "sg:postcode":"01904",
    "sg:province":"MA",
    "wof:name":"US Post Office",
    "wof:placetype":"venue"
},
  "geometry": {"coordinates":[-70.949917,42.478378],"type":"Point"}
}