{
  "type": "Feature",
  "properties": {
    "iso:country":"US",
    "sg:address":"227 Arlington St",
    "sg:city":"Framingham",
    "sg:classifiers":[
        {
            "category":"Freight",
            "type":"Transportation"
        }
    ],
    "sg:phone":"+1 508 370 9988",
    "sg:postcode":"01702",
    "sg:province":"MA",
    "sg:tags":[
        "mover"
    ],
    "wof:name":"Confianca Moving Inc",
    "wof:placetype":"venue"
},
  "geometry": {"coordinates":[-71.41716700000001,42.268068],"type":"Point"}
}