{
  "type": "Feature",
  "properties": {
    "iso:country":"US",
    "sg:address":"103 West St",
    "sg:city":"Ludlow",
    "sg:classifiers":[
        {
            "category":"Restaurant",
            "type":"Food & Drink"
        }
    ],
    "sg:phone":"+1 413 547 0333",
    "sg:postcode":"01056",
    "sg:province":"MA",
    "wof:name":"Two Brothers Pizza",
    "wof:placetype":"venue"
},
  "geometry": {"coordinates":[-72.512497,42.170651],"type":"Point"}
}