{
  "type": "Feature",
  "properties": {
    "addr:full": "387 Page St Stoughton MA 02072",
    "addr:housenumber": "387",
    "addr:postcode": "02072",
    "addr:street": "Page St",
    "iso:country": "US",
    "sg:address": "387 Page St",
    "sg:city": "Stoughton",
    "sg:classifiers": [
      {
        "category": "Building \u0026 Trades",
        "subcategory": "Plumbing",
        "type": "Services"
      }
    ],
    "sg:phone": "+1 781 341 2777",
    "sg:postcode": "02072",
    "sg:province": "MA",
    "sg:tags": [
      "heating",
      "contractor"
    ],
    "wof:name": "Recom Heating \u0026 Air Cond Inc",
    "wof:placetype": "venue"
  },
  "geometry": {"coordinates":[-71.07423,42.1515],"type":"Point"}
}
