{
  "type": "Feature",
  "properties": {
    "iso:country":"US",
    "sg:address":"12 Oak Pt",
    "sg:city":"Wrentham",
    "sg:classifiers":[
        {
            "category":"Professional",
            "type":"Services"
        }
    ],
    "sg:phone":"+1 508 384 2255",
    "sg:postcode":"02093",
    "sg:province":"MA",
    "wof:name":"New Places LLC",
    "wof:placetype":"venue"
},
  "geometry": {"coordinates":[-71.34233500000001,42.069307],"type":"Point"}
}