{
  "type": "Feature",
  "properties": {
    "addr:full": "10 W Main St Merrimac MA 01860",
    "addr:housenumber": "10",
    "addr:postcode": "01860",
    "addr:street": "W Main St",
    "iso:country": "US",
    "sg:address": "10 W Main St",
    "sg:city": "Merrimac",
    "sg:classifiers": [
      {
        "category": "Government",
        "subcategory": "Office",
        "type": "Public Place"
      }
    ],
    "sg:phone": "+1 978 346 8311",
    "sg:postcode": "01860",
    "sg:province": "MA",
    "sg:tags": [
      "village"
    ],
    "wof:name": "Merrimac Light Dept",
    "wof:placetype": "venue"
  },
  "geometry": {"coordinates":[-71.007356,42.829648],"type":"Point"}
}
