{
  "type": "Feature",
  "properties": {
    "iso:country":"US",
    "sg:address":"57 Mechanic St",
    "sg:city":"Marlborough",
    "sg:classifiers":[
        {
            "category":"Social Services",
            "type":"Services"
        }
    ],
    "sg:phone":"+1 508 481 7847",
    "sg:postcode":"01752",
    "sg:province":"MA",
    "sg:tags":[
        "shelter",
        "homeless"
    ],
    "wof:name":"Marlborough Shelter Ctr",
    "wof:placetype":"venue"
},
  "geometry": {"coordinates":[-71.55485,42.347366],"type":"Point"}
}