{
  "type": "Feature",
  "properties": {
    "addr:full":"275 Millway Barnstable MA 02630",
    "addr:housenumber":"275",
    "addr:postcode":"02630",
    "addr:street":"Millway",
    "iso:country":"US",
    "sg:address":"275 Millway",
    "sg:city":"Barnstable",
    "sg:classifiers":[
        {
            "category":"Health Services",
            "subcategory":"Doctor",
            "type":"Services"
        }
    ],
    "sg:phone":"+1 508 760 6868",
    "sg:postcode":"02630",
    "sg:province":"MA",
    "sg:tags":[
        "psychiatrist"
    ],
    "wof:name":"Boyd Jean K",
    "wof:placetype":"venue"
},
  "geometry": {"coordinates":[-70.29877,41.706187],"type":"Point"}
}