{
  "type": "Feature",
  "properties": {
    "iso:country":"US",
    "sg:address":"34 Philbrick Road",
    "sg:city":"Brookline",
    "sg:classifiers":[
        {
            "category":"Education",
            "subcategory":"School",
            "type":"Public Place"
        }
    ],
    "sg:phone":"+1 617 232 4414",
    "sg:postcode":"02445",
    "sg:province":"MA",
    "sg:tags":[
        "high",
        "middle",
        "elementary"
    ],
    "sg:website":"www.maimonides.org",
    "wof:name":"Maimonides School",
    "wof:placetype":"venue"
},
  "geometry": {"coordinates":[-71.12921,42.329738],"type":"Point"}
}