{
  "type": "Feature",
  "properties": {
    "addr:full":"196 N Main St South Yarmouth MA 02664",
    "addr:housenumber":"196",
    "addr:postcode":"02664",
    "addr:street":"N Main St",
    "iso:country":"US",
    "sg:address":"196 N Main St",
    "sg:city":"South Yarmouth",
    "sg:classifiers":[
        {
            "category":"Building & Trades",
            "subcategory":"Construction",
            "type":"Services"
        }
    ],
    "sg:phone":"+1 508 398 9113",
    "sg:postcode":"02664",
    "sg:province":"MA",
    "sg:tags":[
        "painter"
    ],
    "wof:name":"TLC Painting",
    "wof:placetype":"venue"
},
  "geometry": {"coordinates":[-70.18329199999999,41.675957],"type":"Point"}
}