{
  "type": "Feature",
  "properties": {
    "addr:full":"3 Centennial Dr Blackstone MA 01504",
    "addr:housenumber":"3",
    "addr:postcode":"01504",
    "addr:street":"Centennial Dr",
    "iso:country":"US",
    "sg:address":"3 Centennial Dr",
    "sg:city":"Blackstone",
    "sg:classifiers":[
        {
            "category":"Utilities",
            "subcategory":"Water",
            "type":"Services"
        },
        {
            "category":"Retail",
            "subcategory":"Laundry & Dry Cleaning",
            "type":"Services"
        },
        {
            "category":"Building & Trades",
            "subcategory":"Cleaning & Sanitation",
            "type":"Services"
        },
        {
            "category":"Home & Garden",
            "subcategory":"Carpets & Floor Coverings",
            "type":"Retail Goods"
        }
    ],
    "sg:phone":"+1 978 767 2925",
    "sg:postcode":"01504",
    "sg:province":"MA",
    "sg:tags":[
        "cleaner",
        "emergency",
        "fire",
        "cleaners-water",
        "rug",
        "damage",
        "extraction",
        "restoration"
    ],
    "sg:website":"http://www.mark2carpets.com",
    "wof:name":"Mark 2 Enterprises",
    "wof:placetype":"venue"
},
  "geometry": {"coordinates":[-71.54256100000001,42.046613],"type":"Point"}
}