{
  "type": "Feature",
  "properties": {
    "addr:full": "3 Centennial Dr Blackstone MA 01504",
    "addr:housenumber": "3",
    "addr:postcode": "01504",
    "addr:street": "Centennial Dr",
    "iso:country": "US",
    "sg:address": "3 Centennial Dr",
    "sg:city": "Blackstone",
    "sg:classifiers": [
      {
        "category": "Utilities",
        "subcategory": "Water",
        "type": "Services"
      },
      {
        "category": "Retail",
        "subcategory": "Laundry \u0026 Dry Cleaning",
        "type": "Services"
      },
      {
        "category": "Building \u0026 Trades",
        "subcategory": "Cleaning \u0026 Sanitation",
        "type": "Services"
      },
      {
        "category": "Home \u0026 Garden",
        "subcategory": "Carpets \u0026 Floor Coverings",
        "type": "Retail Goods"
      }
    ],
    "sg:phone": "+1 978 767 2925",
    "sg:postcode": "01504",
    "sg:province": "MA",
    "sg:tags": [
      "cleaner",
      "emergency",
      "fire",
      "cleaners-water",
      "rug",
      "damage",
      "extraction",
      "restoration"
    ],
    "sg:website": "http://www.mark2carpets.com",
    "wof:name": "Mark 2 Enterprises",
    "wof:placetype": "venue"
  },
  "geometry": {"coordinates":[-71.542561,42.046613],"type":"Point"}
}
