{
  "type": "Feature",
  "properties": {
    "addr:full":"1200 Suffield St Agawam MA 01001",
    "addr:housenumber":"1200",
    "addr:postcode":"01001",
    "addr:street":"Suffield St",
    "iso:country":"US",
    "sg:address":"1200 Suffield St",
    "sg:city":"Agawam",
    "sg:classifiers":[
        {
            "category":"Social Services",
            "subcategory":"Job Training",
            "type":"Services"
        },
        {
            "category":"Social Services",
            "subcategory":"Retirement Home",
            "type":"Services"
        }
    ],
    "sg:phone":"+1 413 789 2200",
    "sg:postcode":"01001",
    "sg:province":"MA",
    "sg:tags":[
        "convalescent",
        "nursing",
        "homes-skilled",
        "facility"
    ],
    "sg:website":"http://www.salemhaven.com",
    "wof:name":"Country Estates-Agawam",
    "wof:placetype":"venue"
},
  "geometry": {"coordinates":[-72.63564100000001,42.045341],"type":"Point"}
}