{
  "type": "Feature",
  "properties": {
    "addr:full":"36 Massachusetts Ave Chicopee MA 01013",
    "addr:housenumber":"36",
    "addr:postcode":"01013",
    "addr:street":"Massachusetts Ave",
    "iso:country":"US",
    "sg:address":"36 Massachusetts Ave",
    "sg:city":"Chicopee",
    "sg:classifiers":[
        {
            "category":"Building & Trades",
            "subcategory":"Cleaning & Sanitation",
            "type":"Services"
        }
    ],
    "sg:phone":"+1   ",
    "sg:postcode":"01013",
    "sg:province":"MA",
    "sg:tags":[
        "maintenance"
    ],
    "wof:name":"White Glove Cleaning",
    "wof:placetype":"venue"
},
  "geometry": {"coordinates":[-72.59783899999999,42.190011],"type":"Point"}
}