{
  "type": "Feature",
  "properties": {
    "iso:country":"US",
    "sg:address":"882 Providence Hwy",
    "sg:city":"Dedham",
    "sg:classifiers":[
        {
            "category":"Wholesale",
            "subcategory":"Electrical",
            "type":"Manufacturing & Wholesale Goods"
        }
    ],
    "sg:phone":"+1 781 320 0611",
    "sg:postcode":"02026",
    "sg:province":"MA",
    "sg:tags":[
        "alarm",
        "burglar",
        "system"
    ],
    "wof:name":"Atlas Alarm Corp",
    "wof:placetype":"venue"
},
  "geometry": {"coordinates":[-71.17977999999999,42.233301],"type":"Point"}
}