{
  "type": "Feature",
  "properties": {
    "addr:full":"43 Careswell St Marshfield MA 02050",
    "addr:housenumber":"43",
    "addr:postcode":"02050",
    "addr:street":"Careswell St",
    "iso:country":"US",
    "sg:address":"43 Careswell St",
    "sg:city":"Marshfield",
    "sg:classifiers":[
        {
            "category":"Restaurant",
            "type":"Food & Drink"
        }
    ],
    "sg:phone":"+1 781 837 4440",
    "sg:postcode":"02050",
    "sg:province":"MA",
    "wof:name":"Hung's Chinese Cuisine",
    "wof:placetype":"venue"
},
  "geometry": {"coordinates":[-70.65262,42.082366],"type":"Point"}
}