{
  "type": "Feature",
  "properties": {
    "iso:country":"US",
    "sg:address":"157 Main St",
    "sg:city":"Charlemont",
    "sg:classifiers":[
        {
            "category":"Government",
            "subcategory":"Office",
            "type":"Public Place"
        }
    ],
    "sg:phone":"+1 413 339 8586",
    "sg:postcode":"01339",
    "sg:province":"MA",
    "sg:tags":[
        "city",
        "taxation"
    ],
    "wof:name":"Charlemont Assessors Office",
    "wof:placetype":"venue"
},
  "geometry": {"coordinates":[-72.862859,42.627849],"type":"Point"}
}