{
  "type": "Feature",
  "properties": {
    "addr:full": "68 Commonwealth Ave Concord MA 01742",
    "addr:housenumber": "68",
    "addr:postcode": "01742",
    "addr:street": "Commonwealth Ave",
    "iso:country": "US",
    "sg:address": "68 Commonwealth Ave",
    "sg:city": "Concord",
    "sg:classifiers": [
      {
        "category": "Health Services",
        "subcategory": "Nursing And Care Facility",
        "type": "Services"
      }
    ],
    "sg:phone": "+1 978 369 4728",
    "sg:postcode": "01742",
    "sg:province": "MA",
    "sg:tags": [
      "adult"
    ],
    "wof:name": "Concord Park Assisted Living",
    "wof:placetype": "venue"
  },
  "geometry": {"coordinates":[-71.39472,42.45694],"type":"Point"}
}
