{
  "type": "Feature",
  "properties": {
    "addr:full": "555 Fenn St Pittsfield MA 01201",
    "addr:housenumber": "555",
    "addr:postcode": "01201",
    "addr:street": "Fenn St",
    "iso:country": "US",
    "sg:address": "555 Fenn St",
    "sg:city": "Pittsfield",
    "sg:classifiers": [
      {
        "category": "Professional",
        "subcategory": "Management \u0026 Consulting",
        "type": "Services"
      }
    ],
    "sg:phone": "+1 413 442 8500",
    "sg:postcode": "01201",
    "sg:province": "MA",
    "sg:tags": [
      "construction"
    ],
    "wof:name": "Cardan Construction",
    "wof:placetype": "venue"
  },
  "geometry": {"coordinates":[-73.241308,42.448656],"type":"Point"}
}
