{
  "type": "Feature",
  "properties": {
    "addr:full": "2 Worcester Rd Webster MA 01570",
    "addr:housenumber": "2",
    "addr:postcode": "01570",
    "addr:street": "Worcester Rd",
    "iso:country": "US",
    "sg:address": "2 Worcester Rd",
    "sg:city": "Webster",
    "sg:classifiers": [
      {
        "category": "Manufacturing",
        "subcategory": "Textiles",
        "type": "Manufacturing \u0026 Wholesale Goods"
      }
    ],
    "sg:phone": "+1 508 943 0520",
    "sg:postcode": "01570",
    "sg:province": "MA",
    "sg:tags": [
      "finishing"
    ],
    "sg:website": "www.cranstonvillage.com",
    "wof:name": "Cranston Print Works Co",
    "wof:placetype": "venue"
  },
  "geometry": {"coordinates":[-71.863785,42.060672],"type":"Point"}
}
