{
  "type": "Feature",
  "properties": {
    "addr:full": "17 Wilson St Chelmsford MA 01824",
    "addr:housenumber": "17",
    "addr:postcode": "01824",
    "addr:street": "Wilson St",
    "iso:country": "US",
    "sg:address": "17 Wilson St",
    "sg:city": "Chelmsford",
    "sg:classifiers": [
      {
        "category": "Professional",
        "type": "Services"
      }
    ],
    "sg:phone": "+1 978 244 0280",
    "sg:postcode": "01824",
    "sg:province": "MA",
    "sg:tags": [
      "establishment"
    ],
    "wof:name": "Autumn Riders",
    "wof:placetype": "venue"
  },
  "geometry": {"coordinates":[-71.348381,42.59829],"type":"Point"}
}
