{
  "type": "Feature",
  "properties": {
    "addr:full":"51 Green St North Weymouth MA 02191",
    "addr:housenumber":"51",
    "addr:postcode":"02191",
    "addr:street":"Green St",
    "iso:country":"US",
    "sg:address":"51 Green St",
    "sg:city":"North Weymouth",
    "sg:classifiers":[
        {
            "category":"Taxi",
            "type":"Transportation"
        }
    ],
    "sg:phone":"+1 781 337 2954",
    "sg:postcode":"02191",
    "sg:province":"MA",
    "sg:tags":[
        "taxicab"
    ],
    "wof:name":"Boston's Best Transportation",
    "wof:placetype":"venue"
},
  "geometry": {"coordinates":[-70.93991,42.242431],"type":"Point"}
}