{
  "type": "Feature",
  "properties": {
    "addr:full":"56 Trowbridge St Belmont MA 02478",
    "addr:housenumber":"56",
    "addr:postcode":"02478",
    "addr:street":"Trowbridge St",
    "iso:country":"US",
    "sg:address":"56 Trowbridge St",
    "sg:city":"Belmont",
    "sg:classifiers":[
        {
            "category":"Professional",
            "subcategory":"Management & Consulting",
            "type":"Services"
        }
    ],
    "sg:phone":"+1   ",
    "sg:postcode":"02478",
    "sg:province":"MA",
    "wof:name":"Peak Dynamics",
    "wof:placetype":"venue"
},
  "geometry": {"coordinates":[-71.161078,42.39306],"type":"Point"}
}