{
  "type": "Feature",
  "properties": {
    "iso:country":"US",
    "sg:address":"112 Wapping Rd",
    "sg:city":"Kingston",
    "sg:classifiers":[
        {
            "category":"Shopping",
            "subcategory":"Discount & Variety Stores",
            "type":"Retail Goods"
        }
    ],
    "sg:phone":"+1 781 585 9911",
    "sg:postcode":"02364",
    "sg:province":"MA",
    "sg:tags":[
        "merchandise",
        "general"
    ],
    "wof:name":"Global Classic Auto Sales",
    "wof:placetype":"venue"
},
  "geometry": {"coordinates":[-70.78371199999999,41.989017],"type":"Point"}
}