{
  "type": "Feature",
  "properties": {
    "iso:country":"US",
    "sg:address":"152 Trapelo Rd",
    "sg:city":"Lincoln",
    "sg:classifiers":[
        {
            "category":"Professional",
            "subcategory":"Business Services",
            "type":"Services"
        }
    ],
    "sg:phone":"+1   ",
    "sg:postcode":"01773",
    "sg:province":"MA",
    "wof:name":"Jack Fultz Associates",
    "wof:placetype":"venue"
},
  "geometry": {"coordinates":[-71.279043,42.422786],"type":"Point"}
}