{
  "type": "Feature",
  "properties": {
    "iso:country":"US",
    "sg:address":"3 Elm St",
    "sg:city":"Andover",
    "sg:classifiers":[
        {
            "category":"Personal",
            "subcategory":"Beauty Salon",
            "type":"Services"
        }
    ],
    "sg:phone":"+1 978 623 8048",
    "sg:postcode":"01810",
    "sg:province":"MA",
    "sg:tags":[
        "manicuring"
    ],
    "wof:name":"Raini Nail Salon",
    "wof:placetype":"venue"
},
  "geometry": {"coordinates":[-71.13967,42.658144],"type":"Point"}
}