{
  "type": "Feature",
  "properties": {
    "iso:country":"US",
    "sg:address":"1 Cohasset Ave",
    "sg:city":"Buzzards Bay",
    "sg:classifiers":[
        {
            "category":"Professional",
            "subcategory":"Lawyer & Legal Services",
            "type":"Services"
        }
    ],
    "sg:phone":"+1 508 759 2133",
    "sg:postcode":"02532",
    "sg:province":"MA",
    "wof:name":"Markir Marsha Atty",
    "wof:placetype":"venue"
},
  "geometry": {"coordinates":[-70.616501,41.745899],"type":"Point"}
}