{
  "type": "Feature",
  "properties": {
    "addr:full": "108 Douglas Rd Webster MA 01570",
    "addr:housenumber": "108",
    "addr:postcode": "01570",
    "addr:street": "Douglas Rd",
    "iso:country": "US",
    "sg:address": "108 Douglas Rd",
    "sg:city": "Webster",
    "sg:classifiers": [
      {
        "category": "Travel",
        "subcategory": "Campground",
        "type": "Entertainment"
      }
    ],
    "sg:phone": "+1 508 943 1895",
    "sg:postcode": "01570",
    "sg:province": "MA",
    "wof:name": "KOA Kampgrounds",
    "wof:placetype": "venue"
  },
  "geometry": {"coordinates":[-71.826629,42.058283],"type":"Point"}
}
