{
  "type": "Feature",
  "properties": {
    "addr:full":"35 Suffolk Ln Carlisle MA 01741",
    "addr:housenumber":"35",
    "addr:postcode":"01741",
    "addr:street":"Suffolk Ln",
    "iso:country":"US",
    "sg:address":"35 Suffolk Ln",
    "sg:city":"Carlisle",
    "sg:classifiers":[
        {
            "category":"Restaurant",
            "type":"Food & Drink"
        }
    ],
    "sg:phone":"+1 978 369 6822",
    "sg:postcode":"01741",
    "sg:province":"MA",
    "wof:name":"Richard W Chick",
    "wof:placetype":"venue"
},
  "geometry": {"coordinates":[-71.328773,42.510843],"type":"Point"}
}