{
  "type": "Feature",
  "properties": {
    "addr:full":"477 Southwick Rd Westfield MA 01085",
    "addr:housenumber":"477",
    "addr:postcode":"01085",
    "addr:street":"Southwick Rd",
    "iso:country":"US",
    "sg:address":"477 Southwick Rd",
    "sg:city":"Westfield",
    "sg:classifiers":[
        {
            "category":"Health Services",
            "subcategory":"Doctor",
            "type":"Services"
        }
    ],
    "sg:phone":"+1 413 562 5256",
    "sg:postcode":"01085",
    "sg:province":"MA",
    "sg:tags":[
        "physician",
        "surgeon"
    ],
    "wof:name":"Peskin Robert M",
    "wof:placetype":"venue"
},
  "geometry": {"coordinates":[-72.76297,42.094131],"type":"Point"}
}