{
  "type": "Feature",
  "properties": {
    "addr:full": "84 Pleasant St Granby MA 01033",
    "addr:housenumber": "84",
    "addr:postcode": "01033",
    "addr:street": "Pleasant St",
    "iso:country": "US",
    "ovtr:label": "Pleasant Brook Farm \u0026 Feed, 84 Pleasant St Granby MA US",
    "ovtr:similarity": 2.6772470474243164,
    "sg:address": "84 Pleasant St",
    "sg:city": "Granby",
    "sg:classifiers": [
      {
        "category": "Wholesale",
        "subcategory": "Farm Supplies",
        "type": "Manufacturing \u0026 Wholesale Goods"
      }
    ],
    "sg:phone": "+1 413 467 9464",
    "sg:postcode": "01033",
    "sg:province": "MA",
    "sg:tags": [
      "feed"
    ],
    "wof:name": "Pleasant Brook Farm \u0026 Feed",
    "wof:placetype": "venue"
  },
  "geometry": {"coordinates":[-72.541011,42.245157],"type":"Point"}
}
