{
  "type": "Feature",
  "properties": {
    "iso:country":"US",
    "sg:address":"84 Pleasant St",
    "sg:city":"Granby",
    "sg:classifiers":[
        {
            "category":"Wholesale",
            "subcategory":"Farm Supplies",
            "type":"Manufacturing & Wholesale Goods"
        }
    ],
    "sg:phone":"+1 413 467 9464",
    "sg:postcode":"01033",
    "sg:province":"MA",
    "sg:tags":[
        "feed"
    ],
    "wof:name":"Pleasant Brook Farm & Feed",
    "wof:placetype":"venue"
},
  "geometry": {"coordinates":[-72.541011,42.245157],"type":"Point"}
}