{
  "type": "Feature",
  "properties": {
    "addr:full": "937 Summit Rd Richmond MA 01254",
    "addr:housenumber": "937",
    "addr:postcode": "01254",
    "addr:street": "Summit Rd",
    "iso:country": "US",
    "sg:address": "937 Summit Rd",
    "sg:city": "Richmond",
    "sg:classifiers": [
      {
        "category": "Professional",
        "subcategory": "Business Services",
        "type": "Services"
      }
    ],
    "sg:phone": "+1 413 698 2599",
    "sg:postcode": "01254",
    "sg:province": "MA",
    "sg:tags": [
      "interior",
      "consultant",
      "design",
      "decorator"
    ],
    "wof:name": "Grant Larkin",
    "wof:placetype": "venue"
  },
  "geometry": {"coordinates":[-73.33618,42.399105],"type":"Point"}
}
