{
  "type": "Feature",
  "properties": {
    "iso:country":"US",
    "sg:address":"46 Main St Apt 31",
    "sg:city":"Charlestown",
    "sg:classifiers":[
        {
            "category":"Building & Trades",
            "subcategory":"Construction",
            "type":"Services"
        }
    ],
    "sg:phone":"+1 617 241 0182",
    "sg:postcode":"02129",
    "sg:province":"MA",
    "sg:tags":[
        "mason",
        "masonry",
        "industrial",
        "contractors-commercial",
        "contractor"
    ],
    "wof:name":"Pt Rich Masonry Inc",
    "wof:placetype":"venue"
},
  "geometry": {"coordinates":[-71.062162,42.373294],"type":"Point"}
}