{
  "type": "Feature",
  "properties": {
    "addr:full":"25 8th St Leominster MA 01453",
    "addr:housenumber":"25",
    "addr:postcode":"01453",
    "addr:street":"8Th St",
    "iso:country":"US",
    "sg:address":"25 8th St",
    "sg:city":"Leominster",
    "sg:classifiers":[
        {
            "category":"Government",
            "subcategory":"Office",
            "type":"Public Place"
        }
    ],
    "sg:phone":"+1 978 534 7505",
    "sg:postcode":"01453",
    "sg:province":"MA",
    "sg:tags":[
        "village"
    ],
    "wof:name":"Leominster Plumbing Inspector",
    "wof:placetype":"venue"
},
  "geometry": {"coordinates":[-71.74533599999999,42.524771],"type":"Point"}
}