{
  "type": "Feature",
  "properties": {
    "iso:country":"US",
    "sg:address":"99 Hart St",
    "sg:city":"Taunton",
    "sg:classifiers":[
        {
            "category":"Autos & Motor Vehicles",
            "subcategory":"Automobile Sales",
            "type":"Retail Goods"
        }
    ],
    "sg:phone":"+1 508 824 5345",
    "sg:postcode":"02780",
    "sg:province":"MA",
    "sg:tags":[
        "car",
        "dealer"
    ],
    "wof:name":"R & W Motor Sales",
    "wof:placetype":"venue"
},
  "geometry": {"coordinates":[-71.073204,41.883491],"type":"Point"}
}