{
  "type": "Feature",
  "properties": {
    "iso:country":"US",
    "sg:address":"31 Lenox St",
    "sg:city":"Roxbury",
    "sg:classifiers":[
        {
            "category":"Organizations",
            "subcategory":"Religious Organization",
            "type":"Services"
        }
    ],
    "sg:phone":"+1 617 442 6395",
    "sg:postcode":"02118",
    "sg:province":"MA",
    "sg:tags":[
        "church"
    ],
    "wof:name":"St Augustine & St Martin's",
    "wof:placetype":"venue"
},
  "geometry": {"coordinates":[-71.079063,42.335222],"type":"Point"}
}