{
  "type": "Feature",
  "properties": {
    "iso:country":"US",
    "sg:address":"954 American Legion Hwy",
    "sg:city":"Roslindale",
    "sg:classifiers":[
        {
            "category":"Retail",
            "subcategory":"Self-service Laundry",
            "type":"Services"
        }
    ],
    "sg:phone":"+1   ",
    "sg:postcode":"02131",
    "sg:province":"MA",
    "sg:tags":[
        "coin"
    ],
    "wof:name":"Kens Coin Op Laundry",
    "wof:placetype":"venue"
},
  "geometry": {"coordinates":[-71.115644,42.27663],"type":"Point"}
}