{
  "type": "Feature",
  "properties": {
    "iso:country":"US",
    "sg:address":"17 Teasdale Cir",
    "sg:city":"Nantucket",
    "sg:classifiers":[
        {
            "category":"Building & Trades",
            "subcategory":"Construction",
            "type":"Services"
        }
    ],
    "sg:phone":"+1 508 228 8480",
    "sg:postcode":"02554",
    "sg:province":"MA",
    "sg:tags":[
        "resurfacing",
        "refinishing",
        "floor"
    ],
    "wof:name":"Nantucket Works",
    "wof:placetype":"venue"
},
  "geometry": {"coordinates":[-70.06024499999999,41.263293],"type":"Point"}
}