{
  "type": "Feature",
  "properties": {
    "addr:full": "17 Teasdale Cir Nantucket MA 02554",
    "addr:housenumber": "17",
    "addr:postcode": "02554",
    "addr:street": "Teasdale Cir",
    "iso:country": "US",
    "sg:address": "17 Teasdale Cir",
    "sg:city": "Nantucket",
    "sg:classifiers": [
      {
        "category": "Building \u0026 Trades",
        "subcategory": "Construction",
        "type": "Services"
      }
    ],
    "sg:phone": "+1 508 228 8480",
    "sg:postcode": "02554",
    "sg:province": "MA",
    "sg:tags": [
      "resurfacing",
      "refinishing",
      "floor"
    ],
    "wof:name": "Nantucket Works",
    "wof:placetype": "venue"
  },
  "geometry": {"coordinates":[-70.060245,41.263293],"type":"Point"}
}
