{
  "type": "Feature",
  "properties": {
    "addr:full":"1 Constitution Plz Charlestown MA 02129",
    "addr:housenumber":"1",
    "addr:postcode":"02129",
    "addr:street":"Constitution Plz",
    "iso:country":"US",
    "sg:address":"1 Constitution Plz",
    "sg:city":"Charlestown",
    "sg:classifiers":[
        {
            "category":"Professional",
            "subcategory":"Lawyer & Legal Services",
            "type":"Services"
        }
    ],
    "sg:phone":"+1 617 542 4365",
    "sg:postcode":"02129",
    "sg:province":"MA",
    "wof:name":"Bergstresser & Assoc PC",
    "wof:placetype":"venue"
},
  "geometry": {"coordinates":[-71.0616,42.371101],"type":"Point"}
}