{
  "type": "Feature",
  "properties": {
    "iso:country":"US",
    "sg:address":"696 Plain St",
    "sg:city":"Marshfield",
    "sg:classifiers":[
        {
            "category":"Health Services",
            "subcategory":"Clinic",
            "type":"Services"
        }
    ],
    "sg:phone":"+1   ",
    "sg:postcode":"02050",
    "sg:province":"MA",
    "wof:name":"New Life Services",
    "wof:placetype":"venue"
},
  "geometry": {"coordinates":[-70.73944299999999,42.105369],"type":"Point"}
}