{
  "type": "Feature",
  "properties": {
    "iso:country":"US",
    "sg:address":"100 Lancaster Ave",
    "sg:city":"Lunenburg",
    "sg:classifiers":[
        {
            "category":"Sports & Exercise",
            "subcategory":"Gym",
            "type":"Entertainment"
        }
    ],
    "sg:phone":"+1 978 582 0786",
    "sg:postcode":"01462",
    "sg:province":"MA",
    "sg:tags":[
        "club",
        "health",
        "studio",
        "gymnasium"
    ],
    "wof:name":"Freedom Of Movement Pilates",
    "wof:placetype":"venue"
},
  "geometry": {"coordinates":[-71.721496,42.592195],"type":"Point"}
}