{
  "type": "Feature",
  "properties": {
    "iso:country":"US",
    "sg:address":"6 Stratford Ave",
    "sg:city":"Avon",
    "sg:classifiers":[
        {
            "category":"Organizations",
            "subcategory":"Non-profit Organization",
            "type":"Services"
        }
    ],
    "sg:phone":"+1 781 235 7055",
    "sg:postcode":"02322",
    "sg:province":"MA",
    "sg:tags":[
        "charity",
        "foundations-educational",
        "philanthropic",
        "research"
    ],
    "wof:name":"Henry L Blanchard Foundation",
    "wof:placetype":"venue"
},
  "geometry": {"coordinates":[-71.030083,42.132902],"type":"Point"}
}