{
  "type": "Feature",
  "properties": {
    "addr:full": "39 Spring St Easthampton MA 01027",
    "addr:housenumber": "39",
    "addr:postcode": "01027",
    "addr:street": "Spring St",
    "iso:country": "US",
    "sg:address": "39 Spring St",
    "sg:city": "Easthampton",
    "sg:classifiers": [
      {
        "category": "Building \u0026 Trades",
        "subcategory": "Plumbing",
        "type": "Services"
      }
    ],
    "sg:phone": "+1 413 527 7722",
    "sg:postcode": "01027",
    "sg:province": "MA",
    "sg:tags": [
      "heating",
      "contractor"
    ],
    "wof:name": "Tin Man Heating \u0026 Air Cond",
    "wof:placetype": "venue"
  },
  "geometry": {"coordinates":[-72.65721,42.261326],"type":"Point"}
}
