{
  "type": "Feature",
  "properties": {
    "iso:country":"US",
    "sg:address":"39 Spring St",
    "sg:city":"Easthampton",
    "sg:classifiers":[
        {
            "category":"Building & Trades",
            "subcategory":"Plumbing",
            "type":"Services"
        }
    ],
    "sg:phone":"+1 413 527 7722",
    "sg:postcode":"01027",
    "sg:province":"MA",
    "sg:tags":[
        "heating",
        "contractor"
    ],
    "wof:name":"Tin Man Heating & Air Cond",
    "wof:placetype":"venue"
},
  "geometry": {"coordinates":[-72.65721000000001,42.261326],"type":"Point"}
}