{
  "type": "Feature",
  "properties": {
    "addr:full":"272 Chauncy St Mansfield MA 02048",
    "addr:housenumber":"272",
    "addr:postcode":"02048",
    "addr:street":"Chauncy St",
    "iso:country":"US",
    "sg:address":"272 Chauncy St",
    "sg:city":"Mansfield",
    "sg:classifiers":[
        {
            "category":"Social Services",
            "type":"Services"
        }
    ],
    "sg:phone":"+1 508 339 1717",
    "sg:postcode":"02048",
    "sg:province":"MA",
    "sg:tags":[
        "instruction",
        "health",
        "care"
    ],
    "wof:name":"Doran Enterprises",
    "wof:placetype":"venue"
},
  "geometry": {"coordinates":[-71.231202,42.030718],"type":"Point"}
}