{
  "type": "Feature",
  "properties": {
    "addr:full":"105 County St New Bedford MA 02744",
    "addr:housenumber":"105",
    "addr:postcode":"02744",
    "addr:street":"County St",
    "iso:country":"US",
    "sg:address":"105 County St",
    "sg:city":"New Bedford",
    "sg:classifiers":[
        {
            "category":"Retail",
            "subcategory":"Self-service Laundry",
            "type":"Services"
        }
    ],
    "sg:phone":"+1 508 992 3141",
    "sg:postcode":"02744",
    "sg:province":"MA",
    "wof:name":"Whistle Kleen Laundereete",
    "wof:placetype":"venue"
},
  "geometry": {"coordinates":[-70.92336299999999,41.619274],"type":"Point"}
}