{
  "type": "Feature",
  "properties": {
    "iso:country":"US",
    "sg:address":"318 Harvard St. Ste 10",
    "sg:city":"Brookline",
    "sg:classifiers":[
        {
            "category":"Health Services",
            "subcategory":"Optometrist",
            "type":"Services"
        },
        {
            "category":"Recreation",
            "subcategory":"Arcade",
            "type":"Entertainment"
        },
        {
            "category":"Recreation",
            "subcategory":"Picnic Area",
            "type":"Entertainment"
        }
    ],
    "sg:phone":"+1 617 232 9200",
    "sg:postcode":"02446",
    "sg:province":"MA",
    "sg:tags":[
        "place",
        "game",
        "video",
        "amusement"
    ],
    "wof:name":"Arcade Optical",
    "wof:placetype":"venue"
},
  "geometry": {"coordinates":[-71.123491,42.343513],"type":"Point"}
}