{
  "type": "Feature",
  "properties": {
    "addr:full": "731 Moody St Waltham MA 02453",
    "addr:housenumber": "731",
    "addr:postcode": "02453",
    "addr:street": "Moody St",
    "iso:country": "US",
    "sg:address": "731 Moody St",
    "sg:city": "Waltham",
    "sg:classifiers": [
      {
        "category": "Bars \u0026 Pubs",
        "type": "Food \u0026 Drink"
      },
      {
        "category": "Cafe",
        "type": "Food \u0026 Drink"
      }
    ],
    "sg:menulink": "http://www.allmenus.com/ma/waltham/280163-shoppers-cafe-bar--grille/menu/",
    "sg:phone": "+1 781 892 1180",
    "sg:postcode": "02453",
    "sg:province": "MA",
    "sg:tags": [
      "american"
    ],
    "wof:name": "Shopper's Cafe Bar \u0026 Grille",
    "wof:placetype": "venue"
  },
  "geometry": {"coordinates":[-71.238885,42.363825],"type":"Point"}
}
