{
  "type": "Feature",
  "properties": {
    "addr:full": "292 West St Pittsfield MA 01201",
    "addr:housenumber": "292",
    "addr:postcode": "01201",
    "addr:street": "West St",
    "iso:country": "US",
    "sg:address": "292 West St",
    "sg:city": "Pittsfield",
    "sg:classifiers": [
      {
        "category": "Social Services",
        "type": "Services"
      }
    ],
    "sg:phone": "+1 413 499 2877",
    "sg:postcode": "01201",
    "sg:province": "MA",
    "sg:tags": [
      "organization",
      "welfare"
    ],
    "wof:name": "Berkshire Community Action",
    "wof:placetype": "venue"
  },
  "geometry": {"coordinates":[-73.262691,42.449904],"type":"Point"}
}
