{
  "type": "Feature",
  "properties": {
    "addr:full": "398 Plumb Rd Becket MA 01223",
    "addr:housenumber": "398",
    "addr:postcode": "01223",
    "addr:street": "Plumb Rd",
    "iso:country": "US",
    "sg:address": "398 Plumb Rd",
    "sg:city": "Becket",
    "sg:classifiers": [
      {
        "category": "Shopping",
        "subcategory": "Bicycles \u0026 Sporting Goods",
        "type": "Retail Goods"
      }
    ],
    "sg:phone": "+1 413 243 5761",
    "sg:postcode": "01223",
    "sg:province": "MA",
    "sg:tags": [
      "tackle",
      "fishing"
    ],
    "sg:website": "www.berkshirefishing.com",
    "wof:name": "Berkshire Fishing Club",
    "wof:placetype": "venue"
  },
  "geometry": {"coordinates":[-73.123085,42.27441],"type":"Point"}
}
