{
  "type": "Feature",
  "properties": {
    "addr:full": "41 Commercial Rd Leominster MA 01453",
    "addr:housenumber": "41",
    "addr:postcode": "01453",
    "addr:street": "Commercial Rd",
    "atp:label": "Burger King, 41 Commercial Rd LEOMINSTER MA US",
    "atp:similarity": 2.3698248863220215,
    "iso:country": "US",
    "ovtr:label": "Burger King, 41 Commercial Rd Leominster MA US",
    "ovtr:similarity": 2.370081901550293,
    "sg:address": "41 Commercial Rd",
    "sg:city": "Leominster",
    "sg:classifiers": [
      {
        "category": "Restaurant",
        "type": "Food \u0026 Drink"
      }
    ],
    "sg:menulink": "http://www.allmenus.com/ma/leominster/197590-burger-king/menu/",
    "sg:phone": "+1 978 534 0213",
    "sg:postcode": "01453",
    "sg:province": "MA",
    "sg:tags": [
      "burger",
      "american"
    ],
    "wof:name": "Burger King",
    "wof:placetype": "venue"
  },
  "geometry": {"coordinates":[-71.742907,42.533421],"type":"Point"}
}
