{
  "type": "Feature",
  "properties": {
    "iso:country":"US",
    "sg:address":"41 Commercial Rd",
    "sg:city":"Leominster",
    "sg:classifiers":[
        {
            "category":"Restaurant",
            "type":"Food & Drink"
        }
    ],
    "sg:menulink":"http://www.allmenus.com/ma/leominster/197590-burger-king/menu/",
    "sg:phone":"+1 978 534 0213",
    "sg:postcode":"01453",
    "sg:province":"MA",
    "sg:tags":[
        "burger",
        "american"
    ],
    "wof:name":"Burger King",
    "wof:placetype":"venue"
},
  "geometry": {"coordinates":[-71.742907,42.533421],"type":"Point"}
}