{
  "type": "Feature",
  "properties": {
    "iso:country":"US",
    "sg:address":"60 Brookside Ave",
    "sg:city":"Newton",
    "sg:classifiers":[
        {
            "category":"Local Transit",
            "type":"Transportation"
        }
    ],
    "sg:phone":"+1 617 964 4089",
    "sg:postcode":"02460",
    "sg:province":"MA",
    "sg:tags":[
        "airport"
    ],
    "wof:name":"Brookside Transportation Group",
    "wof:placetype":"venue"
},
  "geometry": {"coordinates":[-71.213928,42.35209],"type":"Point"}
}