{
  "type": "Feature",
  "properties": {
    "iso:country":"US",
    "sg:address":"80 Edward Kelleher Dr",
    "sg:city":"Stoughton",
    "sg:classifiers":[
        {
            "category":"Wholesale",
            "subcategory":"Non-durable Goods",
            "type":"Manufacturing & Wholesale Goods"
        },
        {
            "category":"Professional",
            "subcategory":"Business Services",
            "type":"Services"
        }
    ],
    "sg:phone":"+1 781 341 8747",
    "sg:postcode":"02072",
    "sg:province":"MA",
    "sg:tags":[
        "broker",
        "merchandise",
        "merchandise-wholesale"
    ],
    "wof:name":"S K Sales Inc",
    "wof:placetype":"venue"
},
  "geometry": {"coordinates":[-71.11248000000001,42.110531],"type":"Point"}
}