{
  "type": "Feature",
  "properties": {
    "addr:full":"451 E Main St Westfield MA 01085",
    "addr:housenumber":"451",
    "addr:postcode":"01085",
    "addr:street":"E Main St",
    "iso:country":"US",
    "sg:address":"451 E Main St",
    "sg:city":"Westfield",
    "sg:classifiers":[
        {
            "category":"Shopping",
            "subcategory":"Shoes",
            "type":"Retail Goods"
        }
    ],
    "sg:phone":"+1 413 572 9051",
    "sg:postcode":"01085",
    "sg:province":"MA",
    "wof:name":"Payless Shoe Source",
    "wof:placetype":"venue"
},
  "geometry": {"coordinates":[-72.721711,42.112905],"type":"Point"}
}