{
  "type": "Feature",
  "properties": {
    "iso:country":"US",
    "sg:address":"820 Turnpike St",
    "sg:city":"North Andover",
    "sg:classifiers":[
        {
            "category":"Government",
            "subcategory":"Office",
            "type":"Public Place"
        }
    ],
    "sg:phone":"+1 978 686 3786",
    "sg:postcode":"01845",
    "sg:province":"MA",
    "wof:name":"United States Government Mrne",
    "wof:placetype":"venue"
},
  "geometry": {"coordinates":[-71.106443,42.659319],"type":"Point"}
}