{
  "type": "Feature",
  "properties": {
    "iso:country":"US",
    "sg:address":"2 Dundee Park Dr",
    "sg:city":"Andover",
    "sg:classifiers":[
        {
            "category":"Professional",
            "type":"Services"
        }
    ],
    "sg:phone":"+1 978 475 7676",
    "sg:postcode":"01810",
    "sg:province":"MA",
    "sg:tags":[
        "establishment"
    ],
    "wof:name":"Diamondesign",
    "wof:placetype":"venue"
},
  "geometry": {"coordinates":[-71.14586799999999,42.655128],"type":"Point"}
}