{
  "type": "Feature",
  "properties": {
    "addr:full": "2 Dundee Park Dr Andover MA 01810",
    "addr:housenumber": "2",
    "addr:postcode": "01810",
    "addr:street": "Dundee Park Dr",
    "iso:country": "US",
    "sg:address": "2 Dundee Park Dr",
    "sg:city": "Andover",
    "sg:classifiers": [
      {
        "category": "Professional",
        "type": "Services"
      }
    ],
    "sg:phone": "+1 978 475 7676",
    "sg:postcode": "01810",
    "sg:province": "MA",
    "sg:tags": [
      "establishment"
    ],
    "wof:name": "Diamondesign",
    "wof:placetype": "venue"
  },
  "geometry": {"coordinates":[-71.145868,42.655128],"type":"Point"}
}
