{
  "type": "Feature",
  "properties": {
    "iso:country":"US",
    "sg:address":"18 Hyannis Pl",
    "sg:city":"Worcester",
    "sg:classifiers":[
        {
            "category":"Building & Trades",
            "subcategory":"Construction",
            "type":"Services"
        }
    ],
    "sg:phone":"+1 508 752 1436",
    "sg:postcode":"01604",
    "sg:province":"MA",
    "sg:tags":[
        "dry wall",
        "contractor"
    ],
    "wof:name":"Drywall Construction Svc",
    "wof:placetype":"venue"
},
  "geometry": {"coordinates":[-71.77031100000001,42.251123],"type":"Point"}
}