{
  "type": "Feature",
  "properties": {
    "iso:country":"US",
    "sg:address":"150 Huntington Ave",
    "sg:city":"Boston",
    "sg:classifiers":[
        {
            "category":"Shopping",
            "subcategory":"Clothing, Apparel, & Fashions",
            "type":"Retail Goods"
        }
    ],
    "sg:postcode":"02115",
    "sg:province":"MA",
    "sg:tags":[
        "men's",
        "clothing"
    ],
    "wof:name":"Lord's Tailored Menswear",
    "wof:placetype":"venue"
},
  "geometry": {"coordinates":[-71.08179699999999,42.345231],"type":"Point"}
}