{
  "type": "Feature",
  "properties": {
    "addr:full": "150 Huntington Ave Boston MA 02115",
    "addr:housenumber": "150",
    "addr:postcode": "02115",
    "addr:street": "Huntington Ave",
    "iso:country": "US",
    "sg:address": "150 Huntington Ave",
    "sg:city": "Boston",
    "sg:classifiers": [
      {
        "category": "Shopping",
        "subcategory": "Clothing, Apparel, \u0026 Fashions",
        "type": "Retail Goods"
      }
    ],
    "sg:postcode": "02115",
    "sg:province": "MA",
    "sg:tags": [
      "men's",
      "clothing"
    ],
    "wof:name": "Lord's Tailored Menswear",
    "wof:placetype": "venue"
  },
  "geometry": {"coordinates":[-71.081797,42.345231],"type":"Point"}
}
