{
  "type": "Feature",
  "properties": {
    "addr:full":"183 Grove St Chestnut Hill MA 02467",
    "addr:housenumber":"183",
    "addr:postcode":"02467",
    "addr:street":"Grove St",
    "iso:country":"US",
    "sg:address":"183 Grove St",
    "sg:city":"Chestnut Hill",
    "sg:classifiers":[
        {
            "category":"Coffee & Tea",
            "type":"Food & Drink"
        }
    ],
    "sg:phone":"+1 617 325 6261",
    "sg:postcode":"02467",
    "sg:province":"MA",
    "sg:website":"www.starbucks.com",
    "wof:name":"Starbucks",
    "wof:placetype":"venue"
},
  "geometry": {"coordinates":[-71.152331,42.302579],"type":"Point"}
}