{
  "type": "Feature",
  "properties": {
    "addr:full": "271 Grafton St Worcester MA 01604",
    "addr:housenumber": "271",
    "addr:postcode": "01604",
    "addr:street": "Grafton St",
    "iso:country": "US",
    "sg:address": "271 Grafton St",
    "sg:city": "Worcester",
    "sg:classifiers": [
      {
        "category": "Bars \u0026 Pubs",
        "type": "Food \u0026 Drink"
      }
    ],
    "sg:phone": "+1 508 753 9247",
    "sg:postcode": "01604",
    "sg:province": "MA",
    "wof:name": "Diamond Inn",
    "wof:placetype": "venue"
  },
  "geometry": {"coordinates":[-71.788137,42.256319],"type":"Point"}
}
