{
  "type": "Feature",
  "properties": {
    "iso:country":"US",
    "sg:address":"271 Grafton St",
    "sg:city":"Worcester",
    "sg:classifiers":[
        {
            "category":"Bars & Pubs",
            "type":"Food & Drink"
        }
    ],
    "sg:phone":"+1 508 753 9247",
    "sg:postcode":"01604",
    "sg:province":"MA",
    "wof:name":"Diamond Inn",
    "wof:placetype":"venue"
},
  "geometry": {"coordinates":[-71.78813700000001,42.256319],"type":"Point"}
}