{
  "type": "Feature",
  "properties": {
    "iso:country":"US",
    "sg:address":"210 Hobart St",
    "sg:city":"Hingham",
    "sg:classifiers":[
        {
            "category":"Professional",
            "subcategory":"Computer Services",
            "type":"Services"
        }
    ],
    "sg:phone":"+1   ",
    "sg:postcode":"02043",
    "sg:province":"MA",
    "sg:tags":[
        "related"
    ],
    "wof:name":"Fiver Computing Corporation",
    "wof:placetype":"venue"
},
  "geometry": {"coordinates":[-70.909603,42.222567],"type":"Point"}
}