{
  "type": "Feature",
  "properties": {
    "iso:country":"US",
    "sg:address":"39 Tyngsboro Rd",
    "sg:city":"North Chelmsford",
    "sg:classifiers":[
        {
            "category":"Restaurant",
            "type":"Food & Drink"
        }
    ],
    "sg:phone":"+1 978 251 8812",
    "sg:postcode":"01863",
    "sg:province":"MA",
    "sg:tags":[
        "eating"
    ],
    "wof:name":"China Mountain Restaurant Inc",
    "wof:placetype":"venue"
},
  "geometry": {"coordinates":[-71.38802699999999,42.642522],"type":"Point"}
}