{
  "type": "Feature",
  "properties": {
    "addr:full":"4 Governor's Dr Andover MA 01810",
    "addr:housenumber":"4",
    "addr:postcode":"01810",
    "addr:street":"Governor'S Dr",
    "iso:country":"US",
    "sg:address":"4 Governor's Dr",
    "sg:city":"Andover",
    "sg:classifiers":[
        {
            "category":"Building & Trades",
            "subcategory":"Construction",
            "type":"Services"
        }
    ],
    "sg:phone":"+1   ",
    "sg:postcode":"01810",
    "sg:province":"MA",
    "sg:tags":[
        "general",
        "contractor"
    ],
    "wof:name":"Marble Equipment",
    "wof:placetype":"venue"
},
  "geometry": {"coordinates":[-71.242634,42.651611],"type":"Point"}
}