{
  "type": "Feature",
  "properties": {
    "addr:full":"566 Washington St Wellesley MA 02482",
    "addr:housenumber":"566",
    "addr:postcode":"02482",
    "addr:street":"Washington St",
    "iso:country":"US",
    "sg:address":"566 Washington St",
    "sg:city":"Wellesley",
    "sg:classifiers":[
        {
            "category":"Shopping",
            "subcategory":"Gifts & Souvenirs",
            "type":"Retail Goods"
        }
    ],
    "sg:phone":"+1 781 431 2180",
    "sg:postcode":"02482",
    "sg:province":"MA",
    "sg:tags":[
        "shop"
    ],
    "wof:name":"Comina Inc",
    "wof:placetype":"venue"
},
  "geometry": {"coordinates":[-71.29316,42.296216],"type":"Point"}
}