{
  "type": "Feature",
  "properties": {
    "addr:full":"57 Oakvale Rd Framingham MA 01701",
    "addr:housenumber":"57",
    "addr:postcode":"01701",
    "addr:street":"Oakvale Rd",
    "iso:country":"US",
    "sg:address":"57 Oakvale Rd",
    "sg:city":"Framingham",
    "sg:classifiers":[
        {
            "category":"Building & Trades",
            "subcategory":"Electrical",
            "type":"Services"
        }
    ],
    "sg:phone":"+1 508 877 0100",
    "sg:postcode":"01701",
    "sg:province":"MA",
    "sg:tags":[
        "electric",
        "contractor"
    ],
    "wof:name":"Cushing Electrical Co Inc",
    "wof:placetype":"venue"
},
  "geometry": {"coordinates":[-71.420805,42.336664],"type":"Point"}
}