{
  "type": "Feature",
  "properties": {
    "iso:country":"US",
    "sg:address":"99 Pond Ave",
    "sg:city":"Brookline",
    "sg:classifiers":[
        {
            "category":"Health Services",
            "subcategory":"Doctor",
            "type":"Services"
        }
    ],
    "sg:phone":"+1   ",
    "sg:postcode":"02445",
    "sg:province":"MA",
    "sg:tags":[
        "physician",
        "pathologist"
    ],
    "wof:name":"Helmut G Rennke",
    "wof:placetype":"venue"
},
  "geometry": {"coordinates":[-71.11439799999999,42.330915],"type":"Point"}
}