{
  "type": "Feature",
  "properties": {
    "addr:full": "17 Columbia St Swampscott MA 01907",
    "addr:housenumber": "17",
    "addr:postcode": "01907",
    "addr:street": "Columbia St",
    "iso:country": "US",
    "sg:address": "17 Columbia St",
    "sg:city": "Swampscott",
    "sg:classifiers": [
      {
        "category": "Wholesale",
        "subcategory": "Office Equipment",
        "type": "Manufacturing \u0026 Wholesale Goods"
      }
    ],
    "sg:phone": "+1 781 593 2200",
    "sg:postcode": "01907",
    "sg:province": "MA",
    "sg:tags": [
      "machine",
      "duplicating",
      "copying"
    ],
    "wof:name": "Laser Care Technology Inc",
    "wof:placetype": "venue"
  },
  "geometry": {"coordinates":[-70.924575,42.473052],"type":"Point"}
}
