{
  "type": "Feature",
  "properties": {
    "addr:full": "280 Tubman Rd Brewster MA 02631",
    "addr:housenumber": "280",
    "addr:postcode": "02631",
    "addr:street": "Tubman Rd",
    "iso:country": "US",
    "ovtr:label": "Brewster Sportsman's Club, 280 Tubman Rd Brewster MA US",
    "ovtr:similarity": 2.5059540271759033,
    "sg:address": "280 Tubman Rd",
    "sg:city": "Brewster",
    "sg:classifiers": [
      {
        "category": "Organizations",
        "subcategory": "Community Association",
        "type": "Services"
      }
    ],
    "sg:phone": "+1 508 896 7788",
    "sg:postcode": "02631",
    "sg:province": "MA",
    "sg:tags": [
      "club"
    ],
    "wof:name": "Brewster Sportsman's Club",
    "wof:placetype": "venue"
  },
  "geometry": {"coordinates":[-70.09149,41.747847],"type":"Point"}
}
