{
  "type": "Feature",
  "properties": {
    "iso:country":"US",
    "sg:address":"280 Tubman Rd",
    "sg:city":"Brewster",
    "sg:classifiers":[
        {
            "category":"Organizations",
            "subcategory":"Community Association",
            "type":"Services"
        }
    ],
    "sg:phone":"+1 508 896 7788",
    "sg:postcode":"02631",
    "sg:province":"MA",
    "sg:tags":[
        "club"
    ],
    "wof:name":"Brewster Sportsman's Club",
    "wof:placetype":"venue"
},
  "geometry": {"coordinates":[-70.09148999999999,41.747847],"type":"Point"}
}