{
  "type": "Feature",
  "properties": {
    "addr:full": "31 Lexington Ave Gloucester MA 01930",
    "addr:housenumber": "31",
    "addr:postcode": "01930",
    "addr:street": "Lexington Ave",
    "iso:country": "US",
    "sg:address": "31 Lexington Ave",
    "sg:city": "Gloucester",
    "sg:classifiers": [
      {
        "category": "Personal",
        "type": "Services"
      }
    ],
    "sg:phone": "+1 978 525 3744",
    "sg:postcode": "01930",
    "sg:province": "MA",
    "sg:tags": [
      "therapist",
      "massage"
    ],
    "wof:name": "Magnolia Massage Therapy",
    "wof:placetype": "venue"
  },
  "geometry": {"coordinates":[-70.712252,42.575365],"type":"Point"}
}
