{
  "type": "Feature",
  "properties": {
    "addr:full": "1 Haven Ln Wayland MA 01778",
    "addr:housenumber": "1",
    "addr:postcode": "01778",
    "addr:street": "Haven Ln",
    "iso:country": "US",
    "sg:address": "1 Haven Ln",
    "sg:city": "Wayland",
    "sg:classifiers": [
      {
        "category": "Building \u0026 Trades",
        "subcategory": "Landscaping Services",
        "type": "Services"
      }
    ],
    "sg:phone": "+1 508 653 3422",
    "sg:postcode": "01778",
    "sg:province": "MA",
    "sg:tags": [
      "lawn"
    ],
    "wof:name": "Anthonys Images Inc",
    "wof:placetype": "venue"
  },
  "geometry": {"coordinates":[-71.344757,42.321041],"type":"Point"}
}
