{
  "type": "Feature",
  "properties": {
    "addr:full": "10 Frederick St Framingham MA 01702",
    "addr:housenumber": "10",
    "addr:postcode": "01702",
    "addr:street": "Frederick St",
    "iso:country": "US",
    "sg:address": "10 Frederick St",
    "sg:city": "Framingham",
    "sg:classifiers": [
      {
        "category": "Organizations",
        "subcategory": "Religious Organization",
        "type": "Services"
      }
    ],
    "sg:phone": "+1 508 620 7177",
    "sg:postcode": "01702",
    "sg:province": "MA",
    "sg:tags": [
      "church"
    ],
    "wof:name": "New Jerusalem Baptist Church",
    "wof:placetype": "venue"
  },
  "geometry": {"coordinates":[-71.415855,42.279987],"type":"Point"}
}
