{
  "type": "Feature",
  "properties": {
    "iso:country":"US",
    "sg:address":"280 Draper Ave",
    "sg:city":"North Attleboro",
    "sg:classifiers":[
        {
            "category":"Utilities",
            "subcategory":"Refuse",
            "type":"Services"
        }
    ],
    "sg:phone":"+1 508 699 7032",
    "sg:postcode":"02760",
    "sg:province":"MA",
    "sg:tags":[
        "garbage",
        "collection"
    ],
    "wof:name":"Thomas C Wright Rubbish Rmvl",
    "wof:placetype":"venue"
},
  "geometry": {"coordinates":[-71.34565000000001,41.952071],"type":"Point"}
}