{
  "type": "Feature",
  "properties": {
    "iso:country":"US",
    "sg:address":"470 Main St",
    "sg:city":"Harwich",
    "sg:classifiers":[
        {
            "category":"Shopping",
            "subcategory":"Computers & Home Electronics",
            "type":"Retail Goods"
        }
    ],
    "sg:phone":"+1 508 432 1811",
    "sg:postcode":"02645",
    "sg:province":"MA",
    "sg:tags":[
        "software"
    ],
    "wof:name":"Nteon",
    "wof:placetype":"venue"
},
  "geometry": {"coordinates":[-70.09633599999999,41.689057],"type":"Point"}
}