{
  "type": "Feature",
  "properties": {
    "addr:full": "470 Main St Harwich MA 02645",
    "addr:housenumber": "470",
    "addr:postcode": "02645",
    "addr:street": "Main St",
    "iso:country": "US",
    "sg:address": "470 Main St",
    "sg:city": "Harwich",
    "sg:classifiers": [
      {
        "category": "Shopping",
        "subcategory": "Computers \u0026 Home Electronics",
        "type": "Retail Goods"
      }
    ],
    "sg:phone": "+1 508 432 1811",
    "sg:postcode": "02645",
    "sg:province": "MA",
    "sg:tags": [
      "software"
    ],
    "wof:name": "Nteon",
    "wof:placetype": "venue"
  },
  "geometry": {"coordinates":[-70.096336,41.689057],"type":"Point"}
}
