{
  "type": "Feature",
  "properties": {
    "addr:full": "21 Newtonville Ave Newton MA 02458",
    "addr:housenumber": "21",
    "addr:postcode": "02458",
    "addr:street": "Newtonville Ave",
    "iso:country": "US",
    "sg:address": "21 Newtonville Ave",
    "sg:city": "Newton",
    "sg:classifiers": [
      {
        "category": "Professional",
        "type": "Services"
      }
    ],
    "sg:phone": "+1   ",
    "sg:postcode": "02458",
    "sg:province": "MA",
    "wof:name": "Astro Services",
    "wof:placetype": "venue"
  },
  "geometry": {"coordinates":[-71.186138,42.351632],"type":"Point"}
}
