{
  "type": "Feature",
  "properties": {
    "addr:full": "89 William St Vineyard Haven MA 02568",
    "addr:housenumber": "89",
    "addr:postcode": "02568",
    "addr:street": "William St",
    "iso:country": "US",
    "sg:address": "89 William St",
    "sg:city": "Vineyard Haven",
    "sg:classifiers": [
      {
        "category": "Organizations",
        "subcategory": "Religious Organization",
        "type": "Services"
      }
    ],
    "sg:phone": "+1 508 693 1177",
    "sg:postcode": "02568",
    "sg:province": "MA",
    "sg:tags": [
      "church"
    ],
    "wof:name": "Community Gospel Assembly-God",
    "wof:placetype": "venue"
  },
  "geometry": {"coordinates":[-70.604323,41.456114],"type":"Point"}
}
