{
  "type": "Feature",
  "properties": {
    "addr:full":"146-148 Harvard St Brookline MA 02446",
    "addr:housenumber":"146-148",
    "addr:postcode":"02446",
    "addr:street":"Harvard St",
    "iso:country":"US",
    "sg:address":"146-148 Harvard St",
    "sg:city":"Brookline",
    "sg:classifiers":[
        {
            "category":"Shopping",
            "subcategory":"Pets & Pet Supplies",
            "type":"Retail Goods"
        }
    ],
    "sg:phone":"+1 617 738 6682",
    "sg:postcode":"02446",
    "sg:province":"MA",
    "sg:tags":[
        "store",
        "groomers"
    ],
    "sg:website":"www.brooklinedoggrooming.com",
    "wof:name":"Brookline Grooming and Pet Supplies",
    "wof:placetype":"venue"
},
  "geometry": {"coordinates":[-71.121562,42.337852],"type":"Point"}
}