{
  "type": "Feature",
  "properties": {
    "addr:full": "79 Fairlawn Ave Southbridge MA 01550",
    "addr:housenumber": "79",
    "addr:postcode": "01550",
    "addr:street": "Fairlawn Ave",
    "iso:country": "US",
    "sg:address": "79 Fairlawn Ave",
    "sg:city": "Southbridge",
    "sg:classifiers": [
      {
        "category": "Building \u0026 Trades",
        "subcategory": "Construction",
        "type": "Services"
      }
    ],
    "sg:phone": "+1 508 764 3326",
    "sg:postcode": "01550",
    "sg:province": "MA",
    "sg:tags": [
      "designer",
      "dealer",
      "pool",
      "swimming"
    ],
    "wof:name": "Sturbridge Pool Co",
    "wof:placetype": "venue"
  },
  "geometry": {"coordinates":[-72.023483,42.082613],"type":"Point"}
}
