{
  "type": "Feature",
  "properties": {
    "addr:full": "30 River Rd Haverhill MA 01830",
    "addr:housenumber": "30",
    "addr:postcode": "01830",
    "addr:street": "River Rd",
    "iso:country": "US",
    "sg:address": "30 River Rd",
    "sg:city": "Haverhill",
    "sg:classifiers": [
      {
        "category": "Coffee \u0026 Tea",
        "type": "Food \u0026 Drink"
      }
    ],
    "sg:phone": "+1 978 469 9929",
    "sg:postcode": "01830",
    "sg:province": "MA",
    "wof:name": "Wireless Zone - CLOSED",
    "wof:placetype": "venue"
  },
  "geometry": {"coordinates":[-71.0103,42.810299],"type":"Point"}
}
