{
  "type": "Feature",
  "properties": {
    "iso:country":"US",
    "sg:address":"30 River Rd",
    "sg:city":"Haverhill",
    "sg:classifiers":[
        {
            "category":"Coffee & Tea",
            "type":"Food & Drink"
        }
    ],
    "sg:phone":"+1 978 469 9929",
    "sg:postcode":"01830",
    "sg:province":"MA",
    "wof:name":"Wireless Zone - CLOSED",
    "wof:placetype":"venue"
},
  "geometry": {"coordinates":[-71.0103,42.810299],"type":"Point"}
}