{
  "type": "Feature",
  "properties": {
    "addr:full": "14 Arrow Street Suite 11 Cambridge MA 02138 ",
    "addr:housenumber": "14;11",
    "addr:postcode": "02138",
    "addr:street": "Arrow Street Suite",
    "iso:country": "US",
    "sg:address": "14 Arrow Street Suite 11",
    "sg:city": "Cambridge",
    "sg:classifiers": [
      {
        "category": "Professional",
        "subcategory": "Computer Services",
        "type": "Services"
      }
    ],
    "sg:phone": "+1 617 517 7600",
    "sg:postcode": "02138 ",
    "sg:province": "MA",
    "sg:website": "http://www.actblue.com",
    "wof:name": "ActBlue",
    "wof:placetype": "venue"
  },
  "geometry": {"coordinates":[-71.11564,42.371401],"type":"Point"}
}
