{
  "type": "Feature",
  "properties": {
    "addr:full": "10 Concord Xing Concord MA 01742",
    "addr:housenumber": "10",
    "addr:postcode": "01742",
    "addr:street": "Concord Xing",
    "iso:country": "US",
    "sg:address": "10 Concord Xing",
    "sg:city": "Concord",
    "sg:classifiers": [
      {
        "category": "Restaurant",
        "type": "Food \u0026 Drink"
      }
    ],
    "sg:phone": "+1 978 369 5288",
    "sg:postcode": "01742",
    "sg:province": "MA",
    "sg:website": "www.changan-rest.com/",
    "wof:name": "Chang An Restaurant",
    "wof:placetype": "venue"
  },
  "geometry": {"coordinates":[-71.357141,42.455622],"type":"Point"}
}
