{
  "type": "Feature",
  "properties": {
    "iso:country":"US",
    "sg:address":"10 Concord Xing",
    "sg:city":"Concord",
    "sg:classifiers":[
        {
            "category":"Restaurant",
            "type":"Food & Drink"
        }
    ],
    "sg:phone":"+1 978 369 5288",
    "sg:postcode":"01742",
    "sg:province":"MA",
    "sg:website":"www.changan-rest.com/",
    "wof:name":"Chang An Restaurant",
    "wof:placetype":"venue"
},
  "geometry": {"coordinates":[-71.357141,42.455622],"type":"Point"}
}