{
  "type": "Feature",
  "properties": {
    "addr:full":"1044 Central Street Suite 201 Stoughton MA 02072",
    "addr:housenumber":"1044",
    "addr:postcode":"02072",
    "addr:street":"Central Street Suite 201",
    "iso:country":"US",
    "sg:address":"1044 Central Street Suite 201",
    "sg:city":"Stoughton",
    "sg:classifiers":[
        {
            "category":"Professional",
            "type":"Services"
        }
    ],
    "sg:phone":"+1 781 784 0905",
    "sg:postcode":"02072",
    "sg:province":"MA",
    "wof:name":"Divorce Mediation Strategies",
    "wof:placetype":"venue"
},
  "geometry": {"coordinates":[-71.103087,42.134975],"type":"Point"}
}