{
  "type": "Feature",
  "properties": {
    "addr:full": "35 Highland Ave Greenfield MA 01301",
    "addr:housenumber": "35",
    "addr:postcode": "01301",
    "addr:street": "Highland Ave",
    "iso:country": "US",
    "sg:address": "35 Highland Ave",
    "sg:city": "Greenfield",
    "sg:classifiers": [
      {
        "category": "Professional",
        "subcategory": "Lawyer \u0026 Legal Services",
        "type": "Services"
      }
    ],
    "sg:phone": "+1 413 773 9811",
    "sg:postcode": "01301",
    "sg:province": "MA",
    "sg:tags": [
      "attorney"
    ],
    "wof:name": "Elizabeth A Duffy",
    "wof:placetype": "venue"
  },
  "geometry": {"coordinates":[-72.592753,42.584331],"type":"Point"}
}
