{
  "type": "Feature",
  "properties": {
    "iso:country":"US",
    "sg:address":"1 International Pl Fl 17",
    "sg:city":"Boston",
    "sg:classifiers":[
        {
            "category":"Professional",
            "subcategory":"Lawyer & Legal Services",
            "type":"Services"
        }
    ],
    "sg:phone":"+1 617 345 4810",
    "sg:postcode":"02110",
    "sg:province":"MA",
    "wof:name":"Tennyson Erica Atty",
    "wof:placetype":"venue"
},
  "geometry": {"coordinates":[-71.052729,42.356072],"type":"Point"}
}