{
  "type": "Feature",
  "properties": {
    "iso:country":"US",
    "sg:address":"1425 Main St",
    "sg:city":"Acushnet",
    "sg:classifiers":[
        {
            "category":"Education",
            "subcategory":"School",
            "type":"Public Place"
        }
    ],
    "sg:phone":"+1   ",
    "sg:postcode":"02743",
    "sg:province":"MA",
    "wof:name":"Stage Door Academy Inc",
    "wof:placetype":"venue"
},
  "geometry": {"coordinates":[-70.90421000000001,41.753253],"type":"Point"}
}