{
  "type": "Feature",
  "properties": {
    "addr:full": "54 Cottage St Taunton MA 02780",
    "addr:housenumber": "54",
    "addr:postcode": "02780",
    "addr:street": "Cottage St",
    "iso:country": "US",
    "sg:address": "54 Cottage St",
    "sg:city": "Taunton",
    "sg:classifiers": [
      {
        "category": "Retail",
        "subcategory": "Auto Repair",
        "type": "Services"
      }
    ],
    "sg:phone": "+1   ",
    "sg:postcode": "02780",
    "sg:province": "MA",
    "sg:tags": [
      "automotive",
      "used",
      "general"
    ],
    "wof:name": "Harry Bear Auto Sales",
    "wof:placetype": "venue"
  },
  "geometry": {"coordinates":[-71.101815,41.922061],"type":"Point"}
}
