{
  "type": "Feature",
  "properties": {
    "addr:full":"19 Swift Ln Sharon MA 02067",
    "addr:housenumber":"19",
    "addr:postcode":"02067",
    "addr:street":"Swift Ln",
    "iso:country":"US",
    "sg:address":"19 Swift Ln",
    "sg:city":"Sharon",
    "sg:classifiers":[
        {
            "category":"Health Services",
            "subcategory":"Dentist",
            "type":"Services"
        }
    ],
    "sg:phone":"+1 617 698 8883",
    "sg:postcode":"02067",
    "sg:province":"MA",
    "sg:tags":[
        "dentists-orthodontists"
    ],
    "wof:name":"Dennis Sherman Dds Inc",
    "wof:placetype":"venue"
},
  "geometry": {"coordinates":[-71.146134,42.120319],"type":"Point"}
}