{
  "type": "Feature",
  "properties": {
    "iso:country":"US",
    "sg:address":"175 Federal Street",
    "sg:city":"Boston",
    "sg:classifiers":[
        {
            "category":"Insurance",
            "subcategory":"Hazard Insurance",
            "type":"Services"
        }
    ],
    "sg:phone":"+1 617 345 9643",
    "sg:postcode":"02110",
    "sg:province":"MA",
    "sg:website":"www.yozell.com",
    "wof:name":"Yozell Associates",
    "wof:placetype":"venue"
},
  "geometry": {"coordinates":[-71.05615299999999,42.35391],"type":"Point"}
}