{
  "type": "Feature",
  "properties": {
    "addr:full": "175 Federal Street Boston MA 02110",
    "addr:housenumber": "175",
    "addr:postcode": "02110",
    "addr:street": "Federal Street",
    "iso:country": "US",
    "sg:address": "175 Federal Street",
    "sg:city": "Boston",
    "sg:classifiers": [
      {
        "category": "Insurance",
        "subcategory": "Hazard Insurance",
        "type": "Services"
      }
    ],
    "sg:phone": "+1 617 345 9643",
    "sg:postcode": "02110",
    "sg:province": "MA",
    "sg:website": "www.yozell.com",
    "wof:name": "Yozell Associates",
    "wof:placetype": "venue"
  },
  "geometry": {"coordinates":[-71.056153,42.35391],"type":"Point"}
}
