{
  "type": "Feature",
  "properties": {
    "addr:full": "15 Dudley St Cambridge MA 02140",
    "addr:housenumber": "15",
    "addr:postcode": "02140",
    "addr:street": "Dudley St",
    "iso:country": "US",
    "sg:address": "15 Dudley St",
    "sg:city": "Cambridge",
    "sg:classifiers": [
      {
        "category": "Professional",
        "subcategory": "Lawyer \u0026 Legal Services",
        "type": "Services"
      }
    ],
    "sg:phone": "+1 617 354 3080",
    "sg:postcode": "02140",
    "sg:province": "MA",
    "sg:tags": [
      "attorney"
    ],
    "wof:name": "Stephen R Palange",
    "wof:placetype": "venue"
  },
  "geometry": {"coordinates":[-71.130357,42.396225],"type":"Point"}
}
