{
  "type": "Feature",
  "properties": {
    "addr:full": "209 Shute St Everett MA 02149",
    "addr:housenumber": "209",
    "addr:postcode": "02149",
    "addr:street": "Shute St",
    "iso:country": "US",
    "sg:address": "209 Shute St",
    "sg:city": "Everett",
    "sg:classifiers": [
      {
        "category": "Building \u0026 Trades",
        "subcategory": "Construction",
        "type": "Services"
      }
    ],
    "sg:phone": "+1   ",
    "sg:postcode": "02149",
    "sg:province": "MA",
    "sg:tags": [
      "contractor"
    ],
    "wof:name": "Sanco Contracting \u0026 Home Imprv",
    "wof:placetype": "venue"
  },
  "geometry": {"coordinates":[-71.0438,42.422221],"type":"Point"}
}
