{
  "type": "Feature",
  "properties": {
    "iso:country":"US",
    "sg:address":"209 Shute St",
    "sg:city":"Everett",
    "sg:classifiers":[
        {
            "category":"Building & Trades",
            "subcategory":"Construction",
            "type":"Services"
        }
    ],
    "sg:phone":"+1   ",
    "sg:postcode":"02149",
    "sg:province":"MA",
    "sg:tags":[
        "contractor"
    ],
    "wof:name":"Sanco Contracting & Home Imprv",
    "wof:placetype":"venue"
},
  "geometry": {"coordinates":[-71.0438,42.422221],"type":"Point"}
}