{
  "type": "Feature",
  "properties": {
    "iso:country":"US",
    "sg:address":"15 Court Sq Ste 980",
    "sg:city":"Boston",
    "sg:classifiers":[
        {
            "category":"Structure",
            "subcategory":"Office Building",
            "type":"Public Place"
        }
    ],
    "sg:phone":"+1 617 227 3477",
    "sg:postcode":"02108",
    "sg:province":"MA",
    "sg:tags":[
        "park"
    ],
    "wof:name":"Brickpoint Properties",
    "wof:placetype":"venue"
},
  "geometry": {"coordinates":[-71.058228,42.358817],"type":"Point"}
}