{
  "type": "Feature",
  "properties": {
    "addr:full":"1811 Acushnet Ave New Bedford MA 02746",
    "addr:housenumber":"1811",
    "addr:postcode":"02746",
    "addr:street":"Acushnet Ave",
    "iso:country":"US",
    "sg:address":"1811 Acushnet Ave",
    "sg:city":"New Bedford",
    "sg:classifiers":[
        {
            "category":"Insurance",
            "subcategory":"Insurance Agent",
            "type":"Services"
        }
    ],
    "sg:phone":"+1 508 995 1800",
    "sg:postcode":"02746",
    "sg:province":"MA",
    "wof:name":"John Rodrigues Insurance",
    "wof:placetype":"venue"
},
  "geometry": {"coordinates":[-70.927111,41.669827],"type":"Point"}
}