{
  "type": "Feature",
  "properties": {
    "iso:country":"US",
    "sg:address":"271 Salem St",
    "sg:city":"Woburn",
    "sg:classifiers":[
        {
            "category":"Building & Trades",
            "subcategory":"Cleaning & Sanitation",
            "type":"Services"
        }
    ],
    "sg:phone":"+1 781 933 1729",
    "sg:postcode":"01801",
    "sg:province":"MA",
    "sg:tags":[
        "carpet"
    ],
    "sg:website":"www.hexatrac.com",
    "wof:name":"Hexatrac",
    "wof:placetype":"venue"
},
  "geometry": {"coordinates":[-71.132103,42.489399],"type":"Point"}
}