{
  "type": "Feature",
  "properties": {
    "addr:full": "271 Salem St Woburn MA 01801",
    "addr:housenumber": "271",
    "addr:postcode": "01801",
    "addr:street": "Salem St",
    "iso:country": "US",
    "sg:address": "271 Salem St",
    "sg:city": "Woburn",
    "sg:classifiers": [
      {
        "category": "Building \u0026 Trades",
        "subcategory": "Cleaning \u0026 Sanitation",
        "type": "Services"
      }
    ],
    "sg:phone": "+1 781 933 1729",
    "sg:postcode": "01801",
    "sg:province": "MA",
    "sg:tags": [
      "carpet"
    ],
    "sg:website": "www.hexatrac.com",
    "wof:name": "Hexatrac",
    "wof:placetype": "venue"
  },
  "geometry": {"coordinates":[-71.132103,42.489399],"type":"Point"}
}
