{
  "type": "Feature",
  "properties": {
    "iso:country":"US",
    "sg:address":"700 Massachusetts Avenue",
    "sg:city":"Cambridge",
    "sg:classifiers":[
        {
            "category":"Real Estate",
            "subcategory":"Architect",
            "type":"Services"
        }
    ],
    "sg:phone":"+1 617 491 4100",
    "sg:postcode":"02139",
    "sg:province":"MA",
    "wof:name":"Zna Zeybekoglu Nayman Associates",
    "wof:placetype":"venue"
},
  "geometry": {"coordinates":[-71.10443100000001,42.365836],"type":"Point"}
}