{
  "type": "Feature",
  "properties": {
    "iso:country":"US",
    "sg:address":"47 Elm St",
    "sg:city":"Danvers",
    "sg:classifiers":[
        {
            "category":"Restaurant",
            "type":"Food & Drink"
        }
    ],
    "sg:phone":"+1 978 739 4511",
    "sg:postcode":"01923",
    "sg:province":"MA",
    "wof:name":"Giovanni's Pizza & Roast Beef",
    "wof:placetype":"venue"
},
  "geometry": {"coordinates":[-70.937963,42.56345],"type":"Point"}
}