{
  "type": "Feature",
  "properties": {
    "addr:full": "47 Elm St Danvers MA 01923",
    "addr:housenumber": "47",
    "addr:postcode": "01923",
    "addr:street": "Elm St",
    "iso:country": "US",
    "sg:address": "47 Elm St",
    "sg:city": "Danvers",
    "sg:classifiers": [
      {
        "category": "Restaurant",
        "type": "Food \u0026 Drink"
      }
    ],
    "sg:phone": "+1 978 739 4511",
    "sg:postcode": "01923",
    "sg:province": "MA",
    "wof:name": "Giovanni's Pizza \u0026 Roast Beef",
    "wof:placetype": "venue"
  },
  "geometry": {"coordinates":[-70.937963,42.56345],"type":"Point"}
}
