{
  "type": "Feature",
  "properties": {
    "addr:full":"20 Pond View Ln Chatham MA 02633",
    "addr:housenumber":"20",
    "addr:postcode":"02633",
    "addr:street":"Pond View Ln",
    "iso:country":"US",
    "sg:address":"20 Pond View Ln",
    "sg:city":"Chatham",
    "sg:classifiers":[
        {
            "category":"Communications",
            "subcategory":"Film & Video Production",
            "type":"Services"
        }
    ],
    "sg:phone":"+1 508 945 0850",
    "sg:postcode":"02633",
    "sg:province":"MA",
    "sg:tags":[
        "taping"
    ],
    "wof:name":"KANE Productions",
    "wof:placetype":"venue"
},
  "geometry": {"coordinates":[-69.981613,41.681604],"type":"Point"}
}