{
  "type": "Feature",
  "properties": {
    "addr:full": "54 King's Rd Norwood MA 02062",
    "addr:housenumber": "54",
    "addr:postcode": "02062",
    "addr:street": "King'S Rd",
    "iso:country": "US",
    "sg:address": "54 King's Rd",
    "sg:city": "Norwood",
    "sg:classifiers": [
      {
        "category": "Insurance",
        "subcategory": "Insurance Agent",
        "type": "Services"
      }
    ],
    "sg:phone": "+1 781 762 3824",
    "sg:postcode": "02062",
    "sg:province": "MA",
    "wof:name": "American Hardware Mutual Ins",
    "wof:placetype": "venue"
  },
  "geometry": {"coordinates":[-71.184184,42.173166],"type":"Point"}
}
