{
  "type": "Feature",
  "properties": {
    "addr:full":"471 Massachusetts Ave Arlington MA 02474",
    "addr:housenumber":"471",
    "addr:postcode":"02474",
    "addr:street":"Massachusetts Ave",
    "iso:country":"US",
    "sg:address":"471 Massachusetts Ave",
    "sg:city":"Arlington",
    "sg:classifiers":[
        {
            "category":"Sports & Exercise",
            "subcategory":"Gym",
            "type":"Entertainment"
        }
    ],
    "sg:phone":"+1 781 643 4300",
    "sg:postcode":"02474",
    "sg:province":"MA",
    "sg:website":"fitness-1st.net",
    "wof:name":"Fitness First",
    "wof:placetype":"venue"
},
  "geometry": {"coordinates":[-71.151914,42.415067],"type":"Point"}
}