{
  "type": "Feature",
  "properties": {
    "iso:country":"US",
    "sg:address":"34 Franklin Hill Ave",
    "sg:city":"Dorchester Center",
    "sg:classifiers":[
        {
            "category":"Real Estate",
            "subcategory":"Real Estate Operator",
            "type":"Services"
        }
    ],
    "sg:phone":"+1 617 474 2373",
    "sg:postcode":"02124",
    "sg:province":"MA",
    "sg:tags":[
        "apartment"
    ],
    "wof:name":"Cruz Management",
    "wof:placetype":"venue"
},
  "geometry": {"coordinates":[-71.090698,42.2953],"type":"Point"}
}