{
  "type": "Feature",
  "properties": {
    "addr:full": "317 Boston Ave Medford MA 02155",
    "addr:housenumber": "317",
    "addr:postcode": "02155",
    "addr:street": "Boston Ave",
    "iso:country": "US",
    "sg:address": "317 Boston Ave",
    "sg:city": "Medford",
    "sg:classifiers": [
      {
        "category": "Shopping",
        "subcategory": "Hobbies, Toys, \u0026 Games",
        "type": "Retail Goods"
      }
    ],
    "sg:phone": "+1 781 391 5357",
    "sg:postcode": "02155",
    "sg:province": "MA",
    "sg:tags": [
      "tile-wholesale",
      "product",
      "ceramic",
      "manufacturer"
    ],
    "wof:name": "Cozy Corner Makes Scents Ceramics",
    "wof:placetype": "venue"
  },
  "geometry": {"coordinates":[-71.122402,42.411964],"type":"Point"}
}
