{
  "type": "Feature",
  "properties": {
    "addr:full":"963 Main St Athol MA 01331",
    "addr:housenumber":"963",
    "addr:postcode":"01331",
    "addr:street":"Main St",
    "iso:country":"US",
    "sg:address":"963 Main St",
    "sg:city":"Athol",
    "sg:classifiers":[
        {
            "category":"Retail",
            "subcategory":"Auto Repair",
            "type":"Services"
        }
    ],
    "sg:phone":"+1 978 249 6116",
    "sg:postcode":"01331",
    "sg:province":"MA",
    "sg:tags":[
        "wrecker"
    ],
    "wof:name":"Stan's Body Shop",
    "wof:placetype":"venue"
},
  "geometry": {"coordinates":[-72.222781,42.594836],"type":"Point"}
}