{
  "type": "Feature",
  "properties": {
    "iso:country":"US",
    "sg:address":"256 Hamilton St",
    "sg:city":"Worcester",
    "sg:classifiers":[
        {
            "category":"Organizations",
            "subcategory":"Religious Organization",
            "type":"Services"
        }
    ],
    "sg:phone":"+1 508 752 4174",
    "sg:postcode":"01604",
    "sg:province":"MA",
    "sg:tags":[
        "church"
    ],
    "wof:name":"Our Lady Of Perpetual Help",
    "wof:placetype":"venue"
},
  "geometry": {"coordinates":[-71.770472,42.256814],"type":"Point"}
}