{
  "type": "Feature",
  "properties": {
    "addr:full": "256 Hamilton St Worcester MA 01604",
    "addr:housenumber": "256",
    "addr:postcode": "01604",
    "addr:street": "Hamilton St",
    "iso:country": "US",
    "ovtr:label": "Our Lady of Perpetual Help, 256 Hamilton St Worcester MA US",
    "ovtr:similarity": 2.9124629497528076,
    "sg:address": "256 Hamilton St",
    "sg:city": "Worcester",
    "sg:classifiers": [
      {
        "category": "Organizations",
        "subcategory": "Religious Organization",
        "type": "Services"
      }
    ],
    "sg:phone": "+1 508 752 4174",
    "sg:postcode": "01604",
    "sg:province": "MA",
    "sg:tags": [
      "church"
    ],
    "wof:name": "Our Lady Of Perpetual Help",
    "wof:placetype": "venue"
  },
  "geometry": {"coordinates":[-71.770472,42.256814],"type":"Point"}
}
