{
  "type": "Feature",
  "properties": {
    "addr:full":"1409 Main St Palmer MA 01069",
    "addr:housenumber":"1409",
    "addr:postcode":"01069",
    "addr:street":"Main St",
    "iso:country":"US",
    "sg:address":"1409 Main St",
    "sg:city":"Palmer",
    "sg:classifiers":[
        {
            "category":"Education",
            "subcategory":"Special Training",
            "type":"Public Place"
        }
    ],
    "sg:phone":"+1 413 289 1111",
    "sg:postcode":"01069",
    "sg:province":"MA",
    "sg:tags":[
        "instruction",
        "driving"
    ],
    "wof:name":"Palmer Auto School",
    "wof:placetype":"venue"
},
  "geometry": {"coordinates":[-72.32960300000001,42.157191],"type":"Point"}
}