{
  "type": "Feature",
  "properties": {
    "addr:full":"33 Winfield St Worcester MA 01610",
    "addr:housenumber":"33",
    "addr:postcode":"01610",
    "addr:street":"Winfield St",
    "iso:country":"US",
    "sg:address":"33 Winfield St",
    "sg:city":"Worcester",
    "sg:classifiers":[
        {
            "category":"Real Estate",
            "subcategory":"Real Estate Agent",
            "type":"Services"
        }
    ],
    "sg:phone":"+1 508 752 2233",
    "sg:postcode":"01610",
    "sg:province":"MA",
    "sg:tags":[
        "inspection"
    ],
    "sg:website":"www.lucivero.com",
    "wof:name":"John B Lucivero Assoc",
    "wof:placetype":"venue"
},
  "geometry": {"coordinates":[-71.81912699999999,42.260209],"type":"Point"}
}