{
  "type": "Feature",
  "properties": {
    "addr:full":"212 Gamache Dr Ludlow MA 01056",
    "addr:housenumber":"212",
    "addr:postcode":"01056",
    "addr:street":"Gamache Dr",
    "iso:country":"US",
    "sg:address":"212 Gamache Dr",
    "sg:city":"Ludlow",
    "sg:classifiers":[
        {
            "category":"Manufacturing",
            "subcategory":"Electronics",
            "type":"Manufacturing & Wholesale Goods"
        }
    ],
    "sg:phone":"+1 413 589 0712",
    "sg:postcode":"01056",
    "sg:province":"MA",
    "sg:tags":[
        "equipment",
        "electronic",
        "supplies-wholesale",
        "manufacturer"
    ],
    "sg:website":"http://www.northstarnet.com",
    "wof:name":"Northstar Network Group Inc",
    "wof:placetype":"venue"
},
  "geometry": {"coordinates":[-72.503716,42.172075],"type":"Point"}
}