{
  "type": "Feature",
  "properties": {
    "addr:full": "904 Waverly St Framingham MA 01702",
    "addr:housenumber": "904",
    "addr:postcode": "01702",
    "addr:street": "Waverly St",
    "iso:country": "US",
    "ovtr:label": "Tripoli Barber Stylist, 972 Waverly St Framingham MA US",
    "ovtr:similarity": 3.363943099975586,
    "sg:address": "904 Waverly St",
    "sg:city": "Framingham",
    "sg:classifiers": [
      {
        "category": "Personal",
        "subcategory": "Barber",
        "type": "Services"
      }
    ],
    "sg:phone": "+1 508 879 7785",
    "sg:postcode": "01702",
    "sg:province": "MA",
    "wof:name": "Tripoli Barber Stylist",
    "wof:placetype": "venue"
  },
  "geometry": {"coordinates":[-71.436562,42.274135],"type":"Point"}
}
