{
  "type": "Feature",
  "properties": {
    "iso:country":"US",
    "sg:address":"904 Waverly St",
    "sg:city":"Framingham",
    "sg:classifiers":[
        {
            "category":"Personal",
            "subcategory":"Barber",
            "type":"Services"
        }
    ],
    "sg:phone":"+1 508 879 7785",
    "sg:postcode":"01702",
    "sg:province":"MA",
    "wof:name":"Tripoli Barber Stylist",
    "wof:placetype":"venue"
},
  "geometry": {"coordinates":[-71.436562,42.274135],"type":"Point"}
}