{
  "type": "Feature",
  "properties": {
    "addr:full":"11 Oak St Wellesley MA 02482",
    "addr:housenumber":"11",
    "addr:postcode":"02482",
    "addr:street":"Oak St",
    "iso:country":"US",
    "sg:address":"11 Oak St",
    "sg:city":"Wellesley",
    "sg:classifiers":[
        {
            "category":"Real Estate",
            "subcategory":"Real Estate Agent",
            "type":"Services"
        }
    ],
    "sg:phone":"+1 781 416 0950",
    "sg:postcode":"02482",
    "sg:province":"MA",
    "sg:tags":[
        "buyer",
        "broker"
    ],
    "wof:name":"Mark Donohue Assoc",
    "wof:placetype":"venue"
},
  "geometry": {"coordinates":[-71.294866,42.301361],"type":"Point"}
}