{
  "type": "Feature",
  "properties": {
    "addr:full": "300 Granite St Braintree MA 02184",
    "addr:housenumber": "300",
    "addr:postcode": "02184",
    "addr:street": "Granite St",
    "iso:country": "US",
    "sg:address": "300 Granite St",
    "sg:city": "Braintree",
    "sg:classifiers": [
      {
        "category": "Professional",
        "subcategory": "Employment Agencies",
        "type": "Services"
      }
    ],
    "sg:phone": "+1 781 848 7774",
    "sg:postcode": "02184",
    "sg:province": "MA",
    "sg:tags": [
      "help",
      "contractor"
    ],
    "wof:name": "Clinical One",
    "wof:placetype": "venue"
  },
  "geometry": {"coordinates":[-71.02724,42.220021],"type":"Point"}
}
