{
  "type": "Feature",
  "properties": {
    "addr:full": "7 Wildon Rd Wellesley MA 02482",
    "addr:housenumber": "7",
    "addr:postcode": "02482",
    "addr:street": "Wildon Rd",
    "iso:country": "US",
    "sg:address": "7 Wildon Rd",
    "sg:city": "Wellesley",
    "sg:classifiers": [
      {
        "category": "Professional",
        "subcategory": "Management \u0026 Consulting",
        "type": "Services"
      }
    ],
    "sg:phone": "+1 781 235 6646",
    "sg:postcode": "02482",
    "sg:province": "MA",
    "sg:tags": [
      "consultant"
    ],
    "wof:name": "Barbara Kalfin \u0026 Assoc Inc",
    "wof:placetype": "venue"
  },
  "geometry": {"coordinates":[-71.277039,42.292419],"type":"Point"}
}
