{
  "type": "Feature",
  "properties": {
    "addr:full": "340 Rhode Island Ave Fall River MA 02721",
    "addr:housenumber": "340",
    "addr:postcode": "02721",
    "addr:street": "Rhode Island Ave",
    "iso:country": "US",
    "sg:address": "340 Rhode Island Ave",
    "sg:city": "Fall River",
    "sg:classifiers": [
      {
        "category": "Restaurant",
        "type": "Food \u0026 Drink"
      }
    ],
    "sg:menulink": "http://www.allmenus.com/ma/fall-river/228744-jersey-mikes/menu/",
    "sg:phone": "+1 508 676 1977",
    "sg:postcode": "02721",
    "sg:province": "MA",
    "sg:tags": [
      "american",
      "sandwich"
    ],
    "wof:name": "Jersey Mike's",
    "wof:placetype": "venue"
  },
  "geometry": {"coordinates":[-71.162738,41.679145],"type":"Point"}
}
