{
  "type": "Feature",
  "properties": {
    "iso:country":"US",
    "sg:address":"410 Ferry Street",
    "sg:city":"Malden",
    "sg:classifiers":[
        {
            "category":"Sports & Exercise",
            "subcategory":"Gym",
            "type":"Entertainment"
        }
    ],
    "sg:phone":"+1 781 322 8502",
    "sg:postcode":"02148",
    "sg:province":"MA",
    "sg:tags":[
        "trainer"
    ],
    "wof:name":"Faulkner Medical Laboratories",
    "wof:placetype":"venue"
},
  "geometry": {"coordinates":[-71.05756599999999,42.421188],"type":"Point"}
}