{
  "type": "Feature",
  "properties": {
    "addr:full": "410 Ferry Street Malden MA 02148",
    "addr:housenumber": "410",
    "addr:postcode": "02148",
    "addr:street": "Ferry Street",
    "iso:country": "US",
    "sg:address": "410 Ferry Street",
    "sg:city": "Malden",
    "sg:classifiers": [
      {
        "category": "Sports \u0026 Exercise",
        "subcategory": "Gym",
        "type": "Entertainment"
      }
    ],
    "sg:phone": "+1 781 322 8502",
    "sg:postcode": "02148",
    "sg:province": "MA",
    "sg:tags": [
      "trainer"
    ],
    "wof:name": "Faulkner Medical Laboratories",
    "wof:placetype": "venue"
  },
  "geometry": {"coordinates":[-71.057566,42.421188],"type":"Point"}
}
