{
  "type": "Feature",
  "properties": {
    "iso:country":"US",
    "sg:address":"17 Main St",
    "sg:city":"Lee",
    "sg:classifiers":[
        {
            "category":"Professional",
            "subcategory":"Advertising",
            "type":"Services"
        }
    ],
    "sg:phone":"+1 413 243 0375",
    "sg:postcode":"01238",
    "sg:province":"MA",
    "sg:tags":[
        "counselor",
        "specialty"
    ],
    "sg:website":"http://www.enertech.net",
    "wof:name":"Gb Advertising Consultant",
    "wof:placetype":"venue"
},
  "geometry": {"coordinates":[-73.249008,42.304859],"type":"Point"}
}