{
  "type": "Feature",
  "properties": {
    "addr:full":"645 Broadway Lawrence MA 01841",
    "addr:housenumber":"645",
    "addr:postcode":"01841",
    "addr:street":"Broadway",
    "iso:country":"US",
    "sg:address":"645 Broadway",
    "sg:city":"Lawrence",
    "sg:classifiers":[
        {
            "category":"Retail",
            "subcategory":"Portrait Studio",
            "type":"Services"
        }
    ],
    "sg:phone":"+1 978 975 3656",
    "sg:postcode":"01841",
    "sg:province":"MA",
    "sg:tags":[
        "photo"
    ],
    "wof:name":"True Photo",
    "wof:placetype":"venue"
},
  "geometry": {"coordinates":[-71.177668,42.716442],"type":"Point"}
}