{
  "type": "Feature",
  "properties": {
    "addr:full":"10 Furnace Brook Pkwy Quincy MA 02169",
    "addr:housenumber":"10",
    "addr:postcode":"02169",
    "addr:street":"Furnace Brook Pkwy",
    "iso:country":"US",
    "sg:address":"10 Furnace Brook Pkwy",
    "sg:city":"Quincy",
    "sg:classifiers":[
        {
            "category":"Manufacturing",
            "subcategory":"Food",
            "type":"Manufacturing & Wholesale Goods"
        }
    ],
    "sg:phone":"+1 617 773 9545",
    "sg:postcode":"02169",
    "sg:province":"MA",
    "sg:tags":[
        "product",
        "oil",
        "health",
        "fish",
        "animal"
    ],
    "wof:name":"Marine Products",
    "wof:placetype":"venue"
},
  "geometry": {"coordinates":[-70.997213,42.265181],"type":"Point"}
}