{
  "type": "Feature",
  "properties": {
    "iso:country":"US",
    "sg:address":"386 Columbia Rd",
    "sg:city":"Hanover",
    "sg:classifiers":[
        {
            "category":"Home & Garden",
            "subcategory":"Household Appliances",
            "type":"Retail Goods"
        },
        {
            "category":"Retail",
            "subcategory":"Repair Shop",
            "type":"Services"
        }
    ],
    "sg:phone":"+1 781 545 8542",
    "sg:postcode":"02339",
    "sg:province":"MA",
    "sg:tags":[
        "small",
        "major",
        "refinishing",
        "appliances-small"
    ],
    "wof:name":"D & L Appliances",
    "wof:placetype":"venue"
},
  "geometry": {"coordinates":[-70.811021,42.10887],"type":"Point"}
}