{
  "type": "Feature",
  "properties": {
    "addr:full":"333 Lynnway Lynn MA 01901",
    "addr:housenumber":"333",
    "addr:postcode":"01901",
    "addr:street":"Lynnway Lynn",
    "iso:country":"US",
    "sg:address":"333 Lynnway",
    "sg:city":"Lynn",
    "sg:classifiers":[
        {
            "category":"Bakery",
            "type":"Food & Drink"
        },
        {
            "category":"Coffee & Tea",
            "type":"Food & Drink"
        },
        {
            "category":"Bagels",
            "type":"Food & Drink"
        },
        {
            "category":"Donuts",
            "type":"Food & Drink"
        }
    ],
    "sg:menulink":"http://www.allmenus.com/ma/lynn/143049-dunkin-donuts/menu/",
    "sg:phone":"+1 781 599 9435",
    "sg:postcode":"01901",
    "sg:province":"MA",
    "sg:tags":[
        "american",
        "diner",
        "pastry"
    ],
    "wof:name":"Dunkin' Donuts",
    "wof:placetype":"venue"
},
  "geometry": {"coordinates":[-70.949951,42.457898],"type":"Point"}
}