{
  "type": "Feature",
  "properties": {
    "addr:full":"168 N Main St Attleboro MA 02703",
    "addr:housenumber":"168",
    "addr:postcode":"02703",
    "addr:street":"N Main St",
    "iso:country":"US",
    "sg:address":"168 N Main St",
    "sg:city":"Attleboro",
    "sg:classifiers":[
        {
            "category":"Health Services",
            "subcategory":"Doctor",
            "type":"Services"
        }
    ],
    "sg:phone":"+1 508 226 1300",
    "sg:postcode":"02703",
    "sg:province":"MA",
    "sg:tags":[
        "clinic"
    ],
    "wof:name":"General Health Care Inc",
    "wof:placetype":"venue"
},
  "geometry": {"coordinates":[-71.28889599999999,41.948198],"type":"Point"}
}