{
  "type": "Feature",
  "properties": {
    "addr:full": "245 Winch St Framingham MA 01701",
    "addr:housenumber": "245",
    "addr:postcode": "01701",
    "addr:street": "Winch St",
    "iso:country": "US",
    "sg:address": "245 Winch St",
    "sg:city": "Framingham",
    "sg:classifiers": [
      {
        "category": "Manufacturing",
        "subcategory": "Metals",
        "type": "Manufacturing \u0026 Wholesale Goods"
      }
    ],
    "sg:phone": "+1   ",
    "sg:postcode": "01701",
    "sg:province": "MA",
    "sg:tags": [
      "equipment",
      "heating",
      "mfg"
    ],
    "wof:name": "Roger Hanney Sales",
    "wof:placetype": "venue"
  },
  "geometry": {"coordinates":[-71.455062,42.325339],"type":"Point"}
}
