{
  "type": "Feature",
  "properties": {
    "iso:country":"US",
    "sg:address":"22 Church St",
    "sg:city":"Belmont",
    "sg:classifiers":[
        {
            "category":"Shopping",
            "subcategory":"Bicycles & Sporting Goods",
            "type":"Retail Goods"
        }
    ],
    "sg:phone":"+1 617 484 9247",
    "sg:postcode":"02478",
    "sg:province":"MA",
    "sg:tags":[
        "security",
        "system",
        "rack"
    ],
    "sg:website":"www.wheelworks.com",
    "wof:name":"Wheelworks Too",
    "wof:placetype":"venue"
},
  "geometry": {"coordinates":[-71.19019299999999,42.387341],"type":"Point"}
}