{
  "type": "Feature",
  "properties": {
    "addr:full": "7 Populatic St Medway MA 02053",
    "addr:housenumber": "7",
    "addr:postcode": "02053",
    "addr:street": "Populatic St",
    "iso:country": "US",
    "sg:address": "7 Populatic St",
    "sg:city": "Medway",
    "sg:classifiers": [
      {
        "category": "Manufacturing",
        "subcategory": "Paper Products",
        "type": "Manufacturing \u0026 Wholesale Goods"
      }
    ],
    "sg:phone": "+1 508 533 4898",
    "sg:postcode": "02053",
    "sg:province": "MA",
    "sg:tags": [
      "bamboo"
    ],
    "wof:name": "Chesapeake Nurseries",
    "wof:placetype": "venue"
  },
  "geometry": {"coordinates":[-71.38952,42.13966],"type":"Point"}
}
