{
  "type": "Feature",
  "properties": {
    "addr:full": "667 Boylston St Fl 2 Boston MA 02116",
    "addr:housenumber": "667;2",
    "addr:postcode": "02116",
    "addr:street": "Boylston St",
    "iso:country": "US",
    "sg:address": "667 Boylston St Fl 2",
    "sg:city": "Boston",
    "sg:classifiers": [
      {
        "category": "Manufacturing",
        "subcategory": "Toys \u0026 Sporting Goods",
        "type": "Manufacturing \u0026 Wholesale Goods"
      }
    ],
    "sg:phone": "+1 617 638 0001",
    "sg:postcode": "02116",
    "sg:province": "MA",
    "sg:tags": [
      "goods-wholesale",
      "manufacturer"
    ],
    "wof:name": "Pangea Brands",
    "wof:placetype": "venue"
  },
  "geometry": {"coordinates":[-71.078734,42.349702],"type":"Point"}
}
