{
  "type": "Feature",
  "properties": {
    "addr:full":"15 Salem St North Reading MA 01864",
    "addr:housenumber":"15",
    "addr:postcode":"01864",
    "addr:street":"Salem St",
    "iso:country":"US",
    "sg:address":"15 Salem St",
    "sg:city":"North Reading",
    "sg:classifiers":[
        {
            "category":"Building & Trades",
            "subcategory":"Cleaning & Sanitation",
            "type":"Services"
        }
    ],
    "sg:phone":"+1 978 664 6106",
    "sg:postcode":"01864",
    "sg:province":"MA",
    "sg:tags":[
        "house",
        "washing"
    ],
    "wof:name":"Elite Mobile Pressure Washing",
    "wof:placetype":"venue"
},
  "geometry": {"coordinates":[-71.063176,42.605791],"type":"Point"}
}