{
  "type": "Feature",
  "properties": {
    "iso:country":"US",
    "sg:address":"33 Albert St",
    "sg:city":"Indian Orchard",
    "sg:classifiers":[
        {
            "category":"Building & Trades",
            "subcategory":"Construction",
            "type":"Services"
        }
    ],
    "sg:phone":"+1 413 543 5200",
    "sg:postcode":"01151",
    "sg:province":"MA",
    "sg:tags":[
        "product",
        "asphalt"
    ],
    "wof:name":"Acme Site Work Inc",
    "wof:placetype":"venue"
},
  "geometry": {"coordinates":[-72.506351,42.146216],"type":"Point"}
}