{
  "type": "Feature",
  "properties": {
    "addr:full": "41 Trapelo Rd Belmont MA 02478",
    "addr:housenumber": "41",
    "addr:postcode": "02478",
    "addr:street": "Trapelo Rd",
    "iso:country": "US",
    "sg:address": "41 Trapelo Rd",
    "sg:city": "Belmont",
    "sg:classifiers": [
      {
        "category": "Health Services",
        "subcategory": "Doctor",
        "type": "Services"
      }
    ],
    "sg:phone": "+1 617 484 0536",
    "sg:postcode": "02478",
    "sg:province": "MA",
    "sg:tags": [
      "dentist"
    ],
    "wof:name": "Terry R Miller DDS",
    "wof:placetype": "venue"
  },
  "geometry": {"coordinates":[-71.172979,42.37974],"type":"Point"}
}
