{
  "type": "Feature",
  "properties": {
    "addr:full": "740 Springfield St Feeding Hills MA 01030",
    "addr:housenumber": "740",
    "addr:postcode": "01030",
    "addr:street": "Springfield St",
    "iso:country": "US",
    "sg:address": "740 Springfield St",
    "sg:city": "Feeding Hills",
    "sg:classifiers": [
      {
        "category": "Restaurant",
        "type": "Food \u0026 Drink"
      }
    ],
    "sg:phone": "+1 413 789 2203",
    "sg:postcode": "01030",
    "sg:province": "MA",
    "wof:name": "American Classics Restaurant",
    "wof:placetype": "venue"
  },
  "geometry": {"coordinates":[-72.653712,42.077237],"type":"Point"}
}
