{
  "type": "Feature",
  "properties": {
    "iso:country":"US",
    "sg:address":"222 Centre St",
    "sg:city":"Middleboro",
    "sg:classifiers":[
        {
            "category":"Shopping",
            "subcategory":"Used Merchandise",
            "type":"Retail Goods"
        }
    ],
    "sg:phone":"+1 508 947 6885",
    "sg:postcode":"02346",
    "sg:province":"MA",
    "sg:tags":[
        "book",
        "rare",
        "dealer"
    ],
    "wof:name":"Twice Upon A Time",
    "wof:placetype":"venue"
},
  "geometry": {"coordinates":[-70.914035,41.893629],"type":"Point"}
}