{
  "type": "Feature",
  "properties": {
    "iso:country":"US",
    "sg:address":"52 Old Webster Rd",
    "sg:city":"Oxford",
    "sg:classifiers":[
        {
            "category":"Place Of Worship",
            "subcategory":"Church",
            "type":"Public Place"
        },
        {
            "category":"Place Of Worship",
            "type":"Public Place"
        }
    ],
    "sg:phone":"+1 508 987 8878",
    "sg:postcode":"01540",
    "sg:province":"MA",
    "sg:tags":[
        "churches-jehovah's",
        "witness"
    ],
    "sg:website":"http://www.watchtower.org",
    "wof:name":"Jehovah's Witnesses Study",
    "wof:placetype":"venue"
},
  "geometry": {"coordinates":[-71.879355,42.087405],"type":"Point"}
}