{
  "type": "Feature",
  "properties": {
    "iso:country":"US",
    "sg:address":"23 Cottage St",
    "sg:city":"Norwood",
    "sg:classifiers":[
        {
            "category":"Home & Garden",
            "subcategory":"Building Materials",
            "type":"Retail Goods"
        }
    ],
    "sg:phone":"+1 781 762 3128",
    "sg:postcode":"02062",
    "sg:province":"MA",
    "sg:tags":[
        "blind",
        "paint",
        "shade"
    ],
    "sg:website":"www.benjaminmoore.com",
    "wof:name":"Babel's Paint & Decorating Store",
    "wof:placetype":"venue"
},
  "geometry": {"coordinates":[-71.201897,42.194],"type":"Point"}
}