{
  "type": "Feature",
  "properties": {
    "addr:full":"104 Winn St Burlington MA 01803",
    "addr:housenumber":"104",
    "addr:postcode":"01803",
    "addr:street":"Winn St",
    "iso:country":"US",
    "sg:address":"104 Winn St",
    "sg:city":"Burlington",
    "sg:classifiers":[
        {
            "category":"Health Services",
            "subcategory":"Dentist",
            "type":"Services"
        }
    ],
    "sg:phone":"+1 781 272 1150",
    "sg:postcode":"01803",
    "sg:province":"MA",
    "sg:website":"www.drpaullombardo.com/",
    "wof:name":"Dr. Paul Lombardo, DMD",
    "wof:placetype":"venue"
},
  "geometry": {"coordinates":[-71.18000000000001,42.498402],"type":"Point"}
}