{
  "type": "Feature",
  "properties": {
    "addr:full":"862 Washington St Stoughton MA 02072",
    "addr:housenumber":"862",
    "addr:postcode":"02072",
    "addr:street":"Washington St",
    "iso:country":"US",
    "sg:address":"862 Washington St",
    "sg:city":"Stoughton",
    "sg:classifiers":[
        {
            "category":"Education",
            "subcategory":"Dance Studio",
            "type":"Public Place"
        }
    ],
    "sg:phone":"+1 781 344 4145",
    "sg:postcode":"02072",
    "sg:province":"MA",
    "sg:tags":[
        "instruction",
        "dancing"
    ],
    "wof:name":"Arthur Murray Dance Studio",
    "wof:placetype":"venue"
},
  "geometry": {"coordinates":[-71.10159,42.123897],"type":"Point"}
}