{
  "type": "Feature",
  "properties": {
    "addr:full": "20 W 5th St South Boston MA 02127",
    "addr:housenumber": "20",
    "addr:postcode": "02127",
    "addr:street": "W 5Th St",
    "iso:country": "US",
    "sg:address": "20 W 5th St",
    "sg:city": "South Boston",
    "sg:classifiers": [
      {
        "category": "Wholesale",
        "subcategory": "Machinery \u0026 Supplies",
        "type": "Manufacturing \u0026 Wholesale Goods"
      }
    ],
    "sg:phone": "+1 617 269 7056",
    "sg:postcode": "02127",
    "sg:province": "MA",
    "sg:tags": [
      "belting"
    ],
    "sg:website": "www.colmarbelting.com",
    "wof:name": "Colmar Belting Co Inc",
    "wof:placetype": "venue"
  },
  "geometry": {"coordinates":[-71.056419,42.340248],"type":"Point"}
}
