{
  "type": "Feature",
  "properties": {
    "addr:full":"2438 Washington St Canton MA 02021",
    "addr:housenumber":"2438",
    "addr:postcode":"02021",
    "addr:street":"Washington St",
    "iso:country":"US",
    "sg:address":"2438 Washington St",
    "sg:city":"Canton",
    "sg:classifiers":[
        {
            "category":"Professional",
            "type":"Services"
        }
    ],
    "sg:phone":"+1 781 828 6306",
    "sg:postcode":"02021",
    "sg:province":"MA",
    "sg:tags":[
        "establishment"
    ],
    "wof:name":"Boston CGSA",
    "wof:placetype":"venue"
},
  "geometry": {"coordinates":[-71.11905899999999,42.199893],"type":"Point"}
}