{
  "type": "Feature",
  "properties": {
    "addr:full": "169 Monsignor Obrien Hwy Ofc Cambridge MA 02141",
    "addr:housenumber": "169",
    "addr:postcode": "02141",
    "addr:street": "Monsignor Obrien Hwy",
    "iso:country": "US",
    "sg:address": "169 Monsignor Obrien Hwy Ofc",
    "sg:city": "Cambridge",
    "sg:classifiers": [
      {
        "category": "Real Estate",
        "subcategory": "Real Estate Operator",
        "type": "Services"
      }
    ],
    "sg:phone": "+1 617 576 6701",
    "sg:postcode": "02141",
    "sg:province": "MA",
    "sg:tags": [
      "apartment"
    ],
    "wof:name": "Glass Factory Condominiums",
    "wof:placetype": "venue"
  },
  "geometry": {"coordinates":[-71.077888,42.371769],"type":"Point"}
}
