{
  "type": "Feature",
  "properties": {
    "iso:country":"US",
    "sg:address":"169 Monsignor Obrien Hwy Ofc",
    "sg:city":"Cambridge",
    "sg:classifiers":[
        {
            "category":"Real Estate",
            "subcategory":"Real Estate Operator",
            "type":"Services"
        }
    ],
    "sg:phone":"+1 617 576 6701",
    "sg:postcode":"02141",
    "sg:province":"MA",
    "sg:tags":[
        "apartment"
    ],
    "wof:name":"Glass Factory Condominiums",
    "wof:placetype":"venue"
},
  "geometry": {"coordinates":[-71.077888,42.371769],"type":"Point"}
}