{
  "type": "Feature",
  "properties": {
    "addr:full": "3 Pine Acres Rd Foxboro MA 02035",
    "addr:housenumber": "3",
    "addr:postcode": "02035",
    "addr:street": "Pine Acres Rd",
    "iso:country": "US",
    "sg:address": "3 Pine Acres Rd",
    "sg:city": "Foxboro",
    "sg:classifiers": [
      {
        "category": "Personal",
        "subcategory": "Beauty Salon",
        "type": "Services"
      }
    ],
    "sg:phone": "+1 508 549 0990",
    "sg:postcode": "02035",
    "sg:province": "MA",
    "sg:tags": [
      "manicuring"
    ],
    "wof:name": "Nails On The Run",
    "wof:placetype": "venue"
  },
  "geometry": {"coordinates":[-71.272707,42.078659],"type":"Point"}
}
