{
  "type": "Feature",
  "properties": {
    "addr:full":"1093 Montello St Brockton MA 02301",
    "addr:housenumber":"1093",
    "addr:postcode":"02301",
    "addr:street":"Montello St",
    "iso:country":"US",
    "sg:address":"1093 Montello St",
    "sg:city":"Brockton",
    "sg:classifiers":[
        {
            "category":"Professional",
            "type":"Services"
        }
    ],
    "sg:phone":"+1 508 427 7703",
    "sg:postcode":"02301",
    "sg:province":"MA",
    "sg:tags":[
        "establishment"
    ],
    "wof:name":"Waste Disposale Svc",
    "wof:placetype":"venue"
},
  "geometry": {"coordinates":[-71.014234,42.064623],"type":"Point"}
}