{
  "type": "Feature",
  "properties": {
    "addr:full": "1745 Washington St Ste 200 Boston MA 02118",
    "addr:housenumber": "1745",
    "addr:postcode": "02118",
    "addr:street": "Washington St Ste 200",
    "iso:country": "US",
    "sg:address": "1745 Washington St Ste 200",
    "sg:city": "Boston",
    "sg:classifiers": [
      {
        "category": "Building \u0026 Trades",
        "subcategory": "Construction",
        "type": "Services"
      }
    ],
    "sg:phone": "+1 617 576 6100",
    "sg:postcode": "02118",
    "sg:province": "MA",
    "sg:tags": [
      "contractor"
    ],
    "sg:website": "www.sleepingdogproperties.com",
    "wof:name": "Sleeping Dog Properties",
    "wof:placetype": "venue"
  },
  "geometry": {"coordinates":[-71.076726,42.336684],"type":"Point"}
}
