{
  "type": "Feature",
  "properties": {
    "iso:country":"US",
    "sg:address":"1745 Washington St Ste 200",
    "sg:city":"Boston",
    "sg:classifiers":[
        {
            "category":"Building & Trades",
            "subcategory":"Construction",
            "type":"Services"
        }
    ],
    "sg:phone":"+1 617 576 6100",
    "sg:postcode":"02118",
    "sg:province":"MA",
    "sg:tags":[
        "contractor"
    ],
    "sg:website":"www.sleepingdogproperties.com",
    "wof:name":"Sleeping Dog Properties",
    "wof:placetype":"venue"
},
  "geometry": {"coordinates":[-71.07672599999999,42.336684],"type":"Point"}
}