{
  "type": "Feature",
  "properties": {
    "addr:full":"11 S Main St Sherborn MA 01770",
    "addr:housenumber":"11",
    "addr:postcode":"01770",
    "addr:street":"S Main St",
    "iso:country":"US",
    "sg:address":"11 S Main St",
    "sg:city":"Sherborn",
    "sg:classifiers":[
        {
            "category":"Building & Trades",
            "subcategory":"Landscaping Services",
            "type":"Services"
        }
    ],
    "sg:phone":"+1 508 653 3390",
    "sg:postcode":"01770",
    "sg:province":"MA",
    "sg:tags":[
        "landscape",
        "contractor"
    ],
    "wof:name":"Cullen Landscapes Inc",
    "wof:placetype":"venue"
},
  "geometry": {"coordinates":[-71.36960999999999,42.24081],"type":"Point"}
}