{
  "type": "Feature",
  "properties": {
    "addr:full":"459 Broadway St Lowell MA 01854",
    "addr:housenumber":"459",
    "addr:postcode":"01854",
    "addr:street":"Broadway St",
    "iso:country":"US",
    "sg:address":"459 Broadway St",
    "sg:city":"Lowell",
    "sg:classifiers":[
        {
            "category":"Autos & Motor Vehicles",
            "subcategory":"Automobile Sales",
            "type":"Retail Goods"
        }
    ],
    "sg:phone":"+1 978 458 6036",
    "sg:postcode":"01854",
    "sg:province":"MA",
    "sg:tags":[
        "car",
        "dealer"
    ],
    "wof:name":"Advanced Auto Sales",
    "wof:placetype":"venue"
},
  "geometry": {"coordinates":[-71.322344,42.643783],"type":"Point"}
}