{
  "type": "Feature",
  "properties": {
    "iso:country":"US",
    "sg:address":"25 Huntington Ave",
    "sg:city":"Boston",
    "sg:classifiers":[
        {
            "category":"Health Services",
            "subcategory":"Health Practitioner",
            "type":"Services"
        }
    ],
    "sg:phone":"+1 617 437 6303",
    "sg:postcode":"02116",
    "sg:province":"MA",
    "sg:tags":[
        "psychotherapist"
    ],
    "wof:name":"Richard C Miller",
    "wof:placetype":"venue"
},
  "geometry": {"coordinates":[-71.078171,42.348453],"type":"Point"}
}