{
  "type": "Feature",
  "properties": {
    "addr:full": "25 Huntington Ave Boston MA 02116",
    "addr:housenumber": "25",
    "addr:postcode": "02116",
    "addr:street": "Huntington Ave",
    "iso:country": "US",
    "sg:address": "25 Huntington Ave",
    "sg:city": "Boston",
    "sg:classifiers": [
      {
        "category": "Health Services",
        "subcategory": "Health Practitioner",
        "type": "Services"
      }
    ],
    "sg:phone": "+1 617 437 6303",
    "sg:postcode": "02116",
    "sg:province": "MA",
    "sg:tags": [
      "psychotherapist"
    ],
    "wof:name": "Richard C Miller",
    "wof:placetype": "venue"
  },
  "geometry": {"coordinates":[-71.078171,42.348453],"type":"Point"}
}
