{
  "type": "Feature",
  "properties": {
    "iso:country":"US",
    "sg:address":"1157 Dorchester Ave",
    "sg:city":"Dorchester",
    "sg:classifiers":[
        {
            "category":"Personal",
            "subcategory":"Beauty Salon",
            "type":"Services"
        }
    ],
    "sg:phone":"+1 617 265 9929",
    "sg:postcode":"02125",
    "sg:province":"MA",
    "wof:name":"Vivi Hair Salon",
    "wof:placetype":"venue"
},
  "geometry": {"coordinates":[-71.05781500000001,42.31069],"type":"Point"}
}