{
  "type": "Feature",
  "properties": {
    "addr:full": "44 Dinsmore Ave Framingham MA 01702",
    "addr:housenumber": "44",
    "addr:postcode": "01702",
    "addr:street": "Dinsmore Ave",
    "iso:country": "US",
    "sg:address": "44 Dinsmore Ave",
    "sg:city": "Framingham",
    "sg:classifiers": [
      {
        "category": "Professional",
        "subcategory": "Business Services",
        "type": "Services"
      }
    ],
    "sg:phone": "+1   ",
    "sg:postcode": "01702",
    "sg:province": "MA",
    "wof:name": "Grambar Productions/Publi",
    "wof:placetype": "venue"
  },
  "geometry": {"coordinates":[-71.400398,42.296677],"type":"Point"}
}
