{
  "type": "Feature",
  "properties": {
    "addr:full": "58 Goddard St Southbridge MA 01550",
    "addr:housenumber": "58",
    "addr:postcode": "01550",
    "addr:street": "Goddard St",
    "iso:country": "US",
    "sg:address": "58 Goddard St",
    "sg:city": "Southbridge",
    "sg:classifiers": [
      {
        "category": "Bakery",
        "type": "Food \u0026 Drink"
      }
    ],
    "sg:phone": "+1 508 765 7933",
    "sg:postcode": "01550",
    "sg:province": "MA",
    "wof:name": "Hometown Bakery - CLOSED",
    "wof:placetype": "venue"
  },
  "geometry": {"coordinates":[-72.035797,42.075298],"type":"Point"}
}
