{
  "type": "Feature",
  "properties": {
    "iso:country":"US",
    "sg:address":"400 Totten Pond Rd",
    "sg:city":"Waltham",
    "sg:classifiers":[
        {
            "category":"Professional",
            "subcategory":"Management & Consulting",
            "type":"Services"
        }
    ],
    "sg:phone":"+1 781 530 3300",
    "sg:postcode":"02451",
    "sg:province":"MA",
    "sg:tags":[
        "consultant"
    ],
    "wof:name":"Winter Wyman & Co Sales",
    "wof:placetype":"venue"
},
  "geometry": {"coordinates":[-71.25545700000001,42.39718],"type":"Point"}
}