{
  "type": "Feature",
  "properties": {
    "addr:full": "400 Totten Pond Rd Waltham MA 02451",
    "addr:housenumber": "400",
    "addr:postcode": "02451",
    "addr:street": "Totten Pond Rd",
    "iso:country": "US",
    "sg:address": "400 Totten Pond Rd",
    "sg:city": "Waltham",
    "sg:classifiers": [
      {
        "category": "Professional",
        "subcategory": "Management \u0026 Consulting",
        "type": "Services"
      }
    ],
    "sg:phone": "+1 781 530 3300",
    "sg:postcode": "02451",
    "sg:province": "MA",
    "sg:tags": [
      "consultant"
    ],
    "wof:name": "Winter Wyman \u0026 Co Sales",
    "wof:placetype": "venue"
  },
  "geometry": {"coordinates":[-71.255457,42.39718],"type":"Point"}
}
