{
  "type": "Feature",
  "properties": {
    "iso:country":"US",
    "sg:address":"60 State Street Suite 25",
    "sg:city":"Boston",
    "sg:classifiers":[
        {
            "category":"Health Services",
            "subcategory":"Doctor",
            "type":"Services"
        },
        {
            "category":"Personal",
            "subcategory":"Tattoo Parlor",
            "type":"Services"
        },
        {
            "category":"Professional",
            "subcategory":"Lawyer & Legal Services",
            "type":"Services"
        }
    ],
    "sg:phone":"+1 617 526 6000",
    "sg:postcode":"02109",
    "sg:province":"MA",
    "sg:tags":[
        "practice",
        "family"
    ],
    "wof:name":"Lee Judy Lwyr",
    "wof:placetype":"venue"
},
  "geometry": {"coordinates":[-71.05621600000001,42.358973],"type":"Point"}
}