{
  "type": "Feature",
  "properties": {
    "addr:full":"200 Main St Stoneham MA 02180",
    "addr:housenumber":"200",
    "addr:postcode":"02180",
    "addr:street":"Main St",
    "iso:country":"US",
    "sg:address":"200 Main St",
    "sg:city":"Stoneham",
    "sg:classifiers":[
        {
            "category":"Shopping",
            "subcategory":"Jewelry",
            "type":"Retail Goods"
        }
    ],
    "sg:phone":"+1 781 438 1250",
    "sg:postcode":"02180",
    "sg:province":"MA",
    "sg:tags":[
        "jeweler"
    ],
    "wof:name":"A & K Jewelers",
    "wof:placetype":"venue"
},
  "geometry": {"coordinates":[-71.100037,42.486347],"type":"Point"}
}