{
  "type": "Feature",
  "properties": {
    "iso:country":"US",
    "sg:address":"404 County St",
    "sg:city":"New Bedford",
    "sg:classifiers":[
        {
            "category":"Shopping",
            "subcategory":"Computers & Home Electronics",
            "type":"Retail Goods"
        }
    ],
    "sg:phone":"+1 508 992 1097",
    "sg:postcode":"02740",
    "sg:province":"MA",
    "sg:tags":[
        "software"
    ],
    "wof:name":"Osprey Retail Systems Inc",
    "wof:placetype":"venue"
},
  "geometry": {"coordinates":[-70.928907,41.630626],"type":"Point"}
}