{
  "type": "Feature",
  "properties": {
    "addr:full":"422 Court St Plymouth MA 02360",
    "addr:housenumber":"422",
    "addr:postcode":"02360",
    "addr:street":"Court St",
    "iso:country":"US",
    "sg:address":"422 Court St",
    "sg:city":"Plymouth",
    "sg:classifiers":[
        {
            "category":"Recreation",
            "type":"Entertainment"
        }
    ],
    "sg:phone":"+1 508 732 7202",
    "sg:postcode":"02360",
    "sg:province":"MA",
    "sg:tags":[
        "paint",
        "ball",
        "sport"
    ],
    "wof:name":"Plymouth Paintball Supply",
    "wof:placetype":"venue"
},
  "geometry": {"coordinates":[-70.693607,41.980704],"type":"Point"}
}