{
  "type": "Feature",
  "properties": {
    "iso:country":"US",
    "sg:address":"30 Man-Mar Dr",
    "sg:city":"Plainville",
    "sg:classifiers":[
        {
            "category":"Personal",
            "type":"Services"
        }
    ],
    "sg:phone":"+1 508 695 1290",
    "sg:postcode":"02762",
    "sg:province":"MA",
    "sg:tags":[
        "control",
        "weight"
    ],
    "wof:name":"Personalized Weight Loss & Fit",
    "wof:placetype":"venue"
},
  "geometry": {"coordinates":[-71.308082,42.007834],"type":"Point"}
}