{
  "type": "Feature",
  "properties": {
    "addr:full": "30 Man-Mar Dr Plainville MA 02762",
    "addr:housenumber": "30",
    "addr:postcode": "02762",
    "addr:street": "Man-Mar Dr",
    "iso:country": "US",
    "sg:address": "30 Man-Mar Dr",
    "sg:city": "Plainville",
    "sg:classifiers": [
      {
        "category": "Personal",
        "type": "Services"
      }
    ],
    "sg:phone": "+1 508 695 1290",
    "sg:postcode": "02762",
    "sg:province": "MA",
    "sg:tags": [
      "control",
      "weight"
    ],
    "wof:name": "Personalized Weight Loss \u0026 Fit",
    "wof:placetype": "venue"
  },
  "geometry": {"coordinates":[-71.308082,42.007834],"type":"Point"}
}
