{
  "type": "Feature",
  "properties": {
    "addr:full": "88 N Pearl St Brockton MA 02301",
    "addr:housenumber": "88",
    "addr:postcode": "02301",
    "addr:street": "N Pearl St",
    "iso:country": "US",
    "ovtr:label": "Melrose Cemetery, 88 N Pearl St Brockton MA US",
    "ovtr:similarity": 2.621964931488037,
    "sg:address": "88 N Pearl St",
    "sg:city": "Brockton",
    "sg:classifiers": [
      {
        "category": "Government",
        "subcategory": "Office",
        "type": "Public Place"
      }
    ],
    "sg:phone": "+1 508 580 7833",
    "sg:postcode": "02301",
    "sg:province": "MA",
    "sg:tags": [
      "village"
    ],
    "wof:name": "Melrose Cemetery",
    "wof:placetype": "venue"
  },
  "geometry": {"coordinates":[-71.064698,42.092425],"type":"Point"}
}
