{
  "type": "Feature",
  "properties": {
    "iso:country":"US",
    "sg:address":"88 N Pearl St",
    "sg:city":"Brockton",
    "sg:classifiers":[
        {
            "category":"Government",
            "subcategory":"Office",
            "type":"Public Place"
        }
    ],
    "sg:phone":"+1 508 580 7833",
    "sg:postcode":"02301",
    "sg:province":"MA",
    "sg:tags":[
        "village"
    ],
    "wof:name":"Melrose Cemetery",
    "wof:placetype":"venue"
},
  "geometry": {"coordinates":[-71.06469800000001,42.092425],"type":"Point"}
}