{
  "type": "Feature",
  "properties": {
    "addr:full": "93 Apsley St Hudson MA 01749",
    "addr:housenumber": "93",
    "addr:postcode": "01749",
    "addr:street": "Apsley St",
    "iso:country": "US",
    "sg:address": "93 Apsley St",
    "sg:city": "Hudson",
    "sg:classifiers": [
      {
        "category": "Bars \u0026 Pubs",
        "subcategory": "Lounge",
        "type": "Food \u0026 Drink"
      },
      {
        "category": "Restaurant",
        "type": "Food \u0026 Drink"
      }
    ],
    "sg:phone": "+1 978 562 7934",
    "sg:postcode": "01749",
    "sg:province": "MA",
    "sg:tags": [
      "style",
      "cocktail",
      "family"
    ],
    "wof:name": "Paul \u0026 Jerry's Restauant",
    "wof:placetype": "venue"
  },
  "geometry": {"coordinates":[-71.573654,42.395279],"type":"Point"}
}
