{
  "type": "Feature",
  "properties": {
    "iso:country":"US",
    "sg:address":"93 Apsley St",
    "sg:city":"Hudson",
    "sg:classifiers":[
        {
            "category":"Bars & Pubs",
            "subcategory":"Lounge",
            "type":"Food & Drink"
        },
        {
            "category":"Restaurant",
            "type":"Food & Drink"
        }
    ],
    "sg:phone":"+1 978 562 7934",
    "sg:postcode":"01749",
    "sg:province":"MA",
    "sg:tags":[
        "style",
        "cocktail",
        "family"
    ],
    "wof:name":"Paul & Jerry's Restauant",
    "wof:placetype":"venue"
},
  "geometry": {"coordinates":[-71.573654,42.395279],"type":"Point"}
}