{
  "type": "Feature",
  "properties": {
    "addr:full":"85 Main St Holyoke MA 01040",
    "addr:housenumber":"85",
    "addr:postcode":"01040",
    "addr:street":"Main St",
    "iso:country":"US",
    "sg:address":"85 Main St",
    "sg:city":"Holyoke",
    "sg:classifiers":[
        {
            "category":"Organizations",
            "subcategory":"Religious Organization",
            "type":"Services"
        }
    ],
    "sg:phone":"+1   ",
    "sg:postcode":"01040",
    "sg:province":"MA",
    "wof:name":"El Olivar Pentecostal Church",
    "wof:placetype":"venue"
},
  "geometry": {"coordinates":[-72.603345,42.203735],"type":"Point"}
}