{
  "type": "Feature",
  "properties": {
    "iso:country":"US",
    "sg:address":"706 Broadway St",
    "sg:city":"Lowell",
    "sg:classifiers":[
        {
            "category":"Building & Trades",
            "subcategory":"Construction",
            "type":"Services"
        }
    ],
    "sg:phone":"+1 978 441 2000",
    "sg:postcode":"01854",
    "sg:province":"MA",
    "sg:tags":[
        "demolition",
        "paving",
        "contractor"
    ],
    "sg:website":"http://www.sandrcorp.com",
    "wof:name":"S & R Construction",
    "wof:placetype":"venue"
},
  "geometry": {"coordinates":[-71.32921899999999,42.642804],"type":"Point"}
}