{
  "type": "Feature",
  "properties": {
    "iso:country":"US",
    "sg:address":"48 Lakeview St",
    "sg:city":"Carver",
    "sg:classifiers":[
        {
            "category":"Government",
            "subcategory":"Office",
            "type":"Public Place"
        }
    ],
    "sg:phone":"+1 508 866 4698",
    "sg:postcode":"02330",
    "sg:province":"MA",
    "sg:tags":[
        "city",
        "resource",
        "human"
    ],
    "wof:name":"Carver Council On Aging",
    "wof:placetype":"venue"
},
  "geometry": {"coordinates":[-70.749402,41.844345],"type":"Point"}
}