{
  "type": "Feature",
  "properties": {
    "iso:country":"US",
    "sg:address":"89 Burrill St",
    "sg:city":"Swampscott",
    "sg:classifiers":[
        {
            "category":"Government",
            "subcategory":"Office",
            "type":"Public Place"
        }
    ],
    "sg:phone":"+1 781 596 8866",
    "sg:postcode":"01907",
    "sg:province":"MA",
    "sg:tags":[
        "city",
        "resource",
        "human"
    ],
    "wof:name":"Swampscott Council On Aging",
    "wof:placetype":"venue"
},
  "geometry": {"coordinates":[-70.920703,42.470169],"type":"Point"}
}