{
  "type": "Feature",
  "properties": {
    "addr:full": "89 Burrill St Swampscott MA 01907",
    "addr:housenumber": "89",
    "addr:postcode": "01907",
    "addr:street": "Burrill St",
    "iso:country": "US",
    "sg:address": "89 Burrill St",
    "sg:city": "Swampscott",
    "sg:classifiers": [
      {
        "category": "Government",
        "subcategory": "Office",
        "type": "Public Place"
      }
    ],
    "sg:phone": "+1 781 596 8866",
    "sg:postcode": "01907",
    "sg:province": "MA",
    "sg:tags": [
      "city",
      "resource",
      "human"
    ],
    "wof:name": "Swampscott Council On Aging",
    "wof:placetype": "venue"
  },
  "geometry": {"coordinates":[-70.920703,42.470169],"type":"Point"}
}
