{
  "type": "Feature",
  "properties": {
    "addr:full":"910 Boston Post Rd E Marlborough MA 01752",
    "addr:housenumber":"910",
    "addr:postcode":"01752",
    "addr:street":"Boston Post Rd E",
    "iso:country":"US",
    "sg:address":"910 Boston Post Rd E",
    "sg:city":"Marlborough",
    "sg:classifiers":[
        {
            "category":"Real Estate",
            "subcategory":"Real Estate Agent",
            "type":"Services"
        }
    ],
    "sg:phone":"+1 508 357 7977",
    "sg:postcode":"01752",
    "sg:province":"MA",
    "wof:name":"Re/Max First Choice",
    "wof:placetype":"venue"
},
  "geometry": {"coordinates":[-71.486801,42.351937],"type":"Point"}
}