{
  "type": "Feature",
  "properties": {
    "addr:full": "267 Chickering Rd North Andover MA 01845",
    "addr:housenumber": "267",
    "addr:postcode": "01845",
    "addr:street": "Chickering Rd",
    "iso:country": "US",
    "sg:address": "267 Chickering Rd",
    "sg:city": "North Andover",
    "sg:classifiers": [
      {
        "category": "Restaurant",
        "type": "Food \u0026 Drink"
      }
    ],
    "sg:menulink": "http://www.allmenus.com/ma/north-andover/222701-99-restaurant/menu/",
    "sg:phone": "+1 978 683 9999",
    "sg:postcode": "01845",
    "sg:province": "MA",
    "sg:tags": [
      "salad",
      "burger",
      "pub",
      "soup",
      "american",
      "tex-mex"
    ],
    "wof:name": "99 Restaurant",
    "wof:placetype": "venue"
  },
  "geometry": {"coordinates":[-71.121298,42.685957],"type":"Point"}
}
