{
  "type": "Feature",
  "properties": {
    "iso:country":"US",
    "sg:address":"267 Chickering Rd",
    "sg:city":"North Andover",
    "sg:classifiers":[
        {
            "category":"Restaurant",
            "type":"Food & Drink"
        }
    ],
    "sg:menulink":"http://www.allmenus.com/ma/north-andover/222701-99-restaurant/menu/",
    "sg:phone":"+1 978 683 9999",
    "sg:postcode":"01845",
    "sg:province":"MA",
    "sg:tags":[
        "salad",
        "burger",
        "pub",
        "soup",
        "american",
        "tex-mex"
    ],
    "wof:name":"99 Restaurant",
    "wof:placetype":"venue"
},
  "geometry": {"coordinates":[-71.121298,42.685957],"type":"Point"}
}