{
  "type": "Feature",
  "properties": {
    "addr:full":"100 Pearse Rd Swansea MA 02777",
    "addr:housenumber":"100",
    "addr:postcode":"02777",
    "addr:street":"Pearse Rd",
    "iso:country":"US",
    "sg:address":"100 Pearse Rd",
    "sg:city":"Swansea",
    "sg:classifiers":[
        {
            "category":"Education",
            "subcategory":"School",
            "type":"Public Place"
        }
    ],
    "sg:phone":"+1 508 675 7499",
    "sg:postcode":"02777",
    "sg:province":"MA",
    "wof:name":"Luther School",
    "wof:placetype":"venue"
},
  "geometry": {"coordinates":[-71.22333500000001,41.742693],"type":"Point"}
}