{
  "type": "Feature",
  "properties": {
    "addr:full": "500 Blue Hills Pkwy Milton MA 02186",
    "addr:housenumber": "500",
    "addr:postcode": "02186",
    "addr:street": "Blue Hills Pkwy",
    "iso:country": "US",
    "sg:address": "500 Blue Hills Pkwy",
    "sg:city": "Milton",
    "sg:classifiers": [
      {
        "category": "Social Services",
        "subcategory": "Retirement Home",
        "type": "Services"
      }
    ],
    "sg:phone": "+1 617 696 9486",
    "sg:postcode": "02186",
    "sg:province": "MA",
    "sg:tags": [
      "apartment",
      "hotel",
      "community"
    ],
    "wof:name": "Housing Opportunities Milton Elderly Inc",
    "wof:placetype": "venue"
  },
  "geometry": {"coordinates":[-71.093498,42.249454],"type":"Point"}
}
