{
  "type": "Feature",
  "properties": {
    "addr:full":"758 S Main St Randolph MA 02368",
    "addr:housenumber":"758",
    "addr:postcode":"02368",
    "addr:street":"S Main St",
    "iso:country":"US",
    "sg:address":"758 S Main St",
    "sg:city":"Randolph",
    "sg:classifiers":[
        {
            "category":"Wholesale",
            "subcategory":"Vending Machines",
            "type":"Manufacturing & Wholesale Goods"
        }
    ],
    "sg:phone":"+1   ",
    "sg:postcode":"02368",
    "sg:province":"MA",
    "sg:tags":[
        "operator"
    ],
    "wof:name":"Novelty Vending Inc",
    "wof:placetype":"venue"
},
  "geometry": {"coordinates":[-71.039997,42.137348],"type":"Point"}
}