{
  "type": "Feature",
  "properties": {
    "iso:country":"US",
    "sg:address":"92 Chelmsford St",
    "sg:city":"Chelmsford",
    "sg:classifiers":[
        {
            "category":"Arts & Performance",
            "subcategory":"Theater",
            "type":"Entertainment"
        }
    ],
    "sg:phone":"+1 978 250 1700",
    "sg:postcode":"01824",
    "sg:province":"MA",
    "sg:tags":[
        "bureau"
    ],
    "sg:website":"www.lytleticket.com",
    "wof:name":"Lytle Ticket",
    "wof:placetype":"venue"
},
  "geometry": {"coordinates":[-71.345596,42.60349],"type":"Point"}
}