{
  "type": "Feature",
  "properties": {
    "addr:full": "655 Atlantic Ave Boston MA 02111",
    "addr:housenumber": "655",
    "addr:postcode": "02111",
    "addr:street": "Atlantic Ave",
    "iso:country": "US",
    "sg:address": "655 Atlantic Ave",
    "sg:city": "Boston",
    "sg:classifiers": [
      {
        "category": "Professional",
        "subcategory": "Employment Agencies",
        "type": "Services"
      }
    ],
    "sg:postcode": "02111",
    "sg:province": "MA",
    "wof:name": "Daley \u0026 Associates",
    "wof:placetype": "venue"
  },
  "geometry": {"coordinates":[-71.0564,42.3523],"type":"Point"}
}
