{
  "type": "Feature",
  "properties": {
    "addr:full":"67 Mayflower Ln Rochester MA 02770",
    "addr:housenumber":"67",
    "addr:postcode":"02770",
    "addr:street":"Mayflower Ln",
    "iso:country":"US",
    "sg:address":"67 Mayflower Ln",
    "sg:city":"Rochester",
    "sg:classifiers":[
        {
            "category":"Professional",
            "subcategory":"Lawyer & Legal Services",
            "type":"Services"
        }
    ],
    "sg:phone":"+1 508 863 0518",
    "sg:postcode":"02770",
    "sg:province":"MA",
    "sg:tags":[
        "attorney"
    ],
    "wof:name":"Thomas V Flynn Law Offices",
    "wof:placetype":"venue"
},
  "geometry": {"coordinates":[-70.80959300000001,41.774958],"type":"Point"}
}