{
  "type": "Feature",
  "properties": {
    "addr:full":"2 E Falmouth Hwy East Falmouth MA 02536",
    "addr:housenumber":"2",
    "addr:postcode":"02536",
    "addr:street":"E Falmouth Hwy",
    "iso:country":"US",
    "sg:address":"2 E Falmouth Hwy",
    "sg:city":"East Falmouth",
    "sg:classifiers":[
        {
            "category":"Wholesale",
            "subcategory":"Durable Goods & Equipment",
            "type":"Manufacturing & Wholesale Goods"
        }
    ],
    "sg:phone":"+1 508 548 4404",
    "sg:postcode":"02536",
    "sg:province":"MA",
    "sg:tags":[
        "representative",
        "manufacturer"
    ],
    "wof:name":"Krayer Corp",
    "wof:placetype":"venue"
},
  "geometry": {"coordinates":[-70.573346,41.578192],"type":"Point"}
}