{
  "type": "Feature",
  "properties": {
    "iso:country":"US",
    "sg:address":"12 Mechanic St",
    "sg:city":"Foxboro",
    "sg:classifiers":[
        {
            "category":"Banks & Credit Unions",
            "subcategory":"Bank",
            "type":"Services"
        }
    ],
    "sg:phone":"+1 508 543 3833",
    "sg:postcode":"02035",
    "sg:province":"MA",
    "sg:tags":[
        "loan",
        "real estate"
    ],
    "wof:name":"Travis Mortgage",
    "wof:placetype":"venue"
},
  "geometry": {"coordinates":[-71.248907,42.065605],"type":"Point"}
}