{
  "type": "Feature",
  "properties": {
    "addr:full":"68 Leonard St Belmont MA 02478",
    "addr:housenumber":"68",
    "addr:postcode":"02478",
    "addr:street":"Leonard St",
    "iso:country":"US",
    "sg:address":"68 Leonard St",
    "sg:city":"Belmont",
    "sg:classifiers":[
        {
            "category":"Professional",
            "subcategory":"Lawyer & Legal Services",
            "type":"Services"
        }
    ],
    "sg:phone":"+1 617 484 6328",
    "sg:postcode":"02478",
    "sg:province":"MA",
    "sg:tags":[
        "attorney"
    ],
    "wof:name":"John N Kulas",
    "wof:placetype":"venue"
},
  "geometry": {"coordinates":[-71.175445,42.397557],"type":"Point"}
}