{
  "type": "Feature",
  "properties": {
    "iso:country":"US",
    "sg:address":"189 Dean St",
    "sg:city":"Norwood",
    "sg:classifiers":[
        {
            "category":"Manufacturing",
            "subcategory":"Rubber & Plastics",
            "type":"Manufacturing & Wholesale Goods"
        }
    ],
    "sg:phone":"+1 781 769 6311",
    "sg:postcode":"02062",
    "sg:province":"MA",
    "sg:website":"www.innovmem.com",
    "wof:name":"Innovative Membrane Systems",
    "wof:placetype":"venue"
},
  "geometry": {"coordinates":[-71.19065999999999,42.178889],"type":"Point"}
}