{
  "type": "Feature",
  "properties": {
    "addr:full": "189 Dean St Norwood MA 02062",
    "addr:housenumber": "189",
    "addr:postcode": "02062",
    "addr:street": "Dean St",
    "iso:country": "US",
    "sg:address": "189 Dean St",
    "sg:city": "Norwood",
    "sg:classifiers": [
      {
        "category": "Manufacturing",
        "subcategory": "Rubber \u0026 Plastics",
        "type": "Manufacturing \u0026 Wholesale Goods"
      }
    ],
    "sg:phone": "+1 781 769 6311",
    "sg:postcode": "02062",
    "sg:province": "MA",
    "sg:website": "www.innovmem.com",
    "wof:name": "Innovative Membrane Systems",
    "wof:placetype": "venue"
  },
  "geometry": {"coordinates":[-71.19066,42.178889],"type":"Point"}
}
