{
  "type": "Feature",
  "properties": {
    "addr:full":"79 Pleasant St Canton MA 02021",
    "addr:housenumber":"79",
    "addr:postcode":"02021",
    "addr:street":"Pleasant St",
    "iso:country":"US",
    "sg:address":"79 Pleasant St",
    "sg:city":"Canton",
    "sg:classifiers":[
        {
            "category":"Government",
            "subcategory":"Office",
            "type":"Public Place"
        }
    ],
    "sg:phone":"+1 781 821 5021",
    "sg:postcode":"02021",
    "sg:province":"MA",
    "sg:tags":[
        "village"
    ],
    "wof:name":"Canton Health Board",
    "wof:placetype":"venue"
},
  "geometry": {"coordinates":[-71.135592,42.172775],"type":"Point"}
}