{
  "type": "Feature",
  "properties": {
    "iso:country":"US",
    "sg:address":"625 Lincoln St",
    "sg:city":"Worcester",
    "sg:classifiers":[
        {
            "category":"Organizations",
            "subcategory":"Community Association",
            "type":"Services"
        }
    ],
    "sg:phone":"+1 508 856 0700",
    "sg:postcode":"01605",
    "sg:province":"MA",
    "wof:name":"Problem Pregnancy Of Worcester",
    "wof:placetype":"venue"
},
  "geometry": {"coordinates":[-71.76522799999999,42.297821],"type":"Point"}
}