{
  "type": "Feature",
  "properties": {
    "iso:country":"US",
    "sg:address":"3 Shepard Rd",
    "sg:city":"Sturbridge",
    "sg:classifiers":[
        {
            "category":"Retail",
            "subcategory":"Repair Shop",
            "type":"Services"
        }
    ],
    "sg:phone":"+1 508 347 5271",
    "sg:postcode":"01566",
    "sg:province":"MA",
    "sg:tags":[
        "equipment",
        "conditioning",
        "air"
    ],
    "wof:name":"Cooper's Air Conditioning",
    "wof:placetype":"venue"
},
  "geometry": {"coordinates":[-72.06715699999999,42.073977],"type":"Point"}
}