{
  "type": "Feature",
  "properties": {
    "addr:full":"25 Monmouth St Brookline MA 02446",
    "addr:housenumber":"25",
    "addr:postcode":"02446",
    "addr:street":"Monmouth St",
    "iso:country":"US",
    "sg:address":"25 Monmouth St",
    "sg:city":"Brookline",
    "sg:classifiers":[
        {
            "category":"Place Of Worship",
            "subcategory":"Church",
            "type":"Public Place"
        }
    ],
    "sg:phone":"+1 617 277 7334",
    "sg:postcode":"02446",
    "sg:province":"MA",
    "sg:tags":[
        "churches-episcopal"
    ],
    "sg:website":"www.oursaviourbrookline.org",
    "wof:name":"Church of Our Saviour",
    "wof:placetype":"venue"
},
  "geometry": {"coordinates":[-71.10870300000001,42.344553],"type":"Point"}
}