{
  "type": "Feature",
  "properties": {
    "addr:full":"697 Cambridge St Cambridge MA 02141",
    "addr:housenumber":"697",
    "addr:postcode":"02141",
    "addr:street":"Cambridge St",
    "iso:country":"US",
    "sg:address":"697 Cambridge St",
    "sg:city":"Cambridge",
    "sg:classifiers":[
        {
            "category":"Health Services",
            "subcategory":"Doctor",
            "type":"Services"
        }
    ],
    "sg:phone":"+1 617 782 3030",
    "sg:postcode":"02141",
    "sg:province":"MA",
    "sg:tags":[
        "physician",
        "surgeon"
    ],
    "wof:name":"Neurological Medicine",
    "wof:placetype":"venue"
},
  "geometry": {"coordinates":[-71.08802900000001,42.372131],"type":"Point"}
}