{
  "type": "Feature",
  "properties": {
    "addr:full": "979 Main St Springfield MA 01103",
    "addr:housenumber": "979",
    "addr:postcode": "01103",
    "addr:street": "Main St",
    "iso:country": "US",
    "sg:address": "979 Main St",
    "sg:city": "Springfield",
    "sg:classifiers": [
      {
        "category": "Real Estate",
        "subcategory": "Architect",
        "type": "Services"
      }
    ],
    "sg:phone": "+1 413 733 7332",
    "sg:postcode": "01103",
    "sg:province": "MA",
    "sg:website": "www.studioonearchitects.com",
    "wof:name": "Studio One Inc",
    "wof:placetype": "venue"
  },
  "geometry": {"coordinates":[-72.584094,42.098949],"type":"Point"}
}
