{
  "type": "Feature",
  "properties": {
    "iso:country":"US",
    "sg:address":"95 Old Colony Ave",
    "sg:city":"Quincy",
    "sg:classifiers":[
        {
            "category":"Professional",
            "subcategory":"Business Services",
            "type":"Services"
        }
    ],
    "sg:phone":"+1 617 770 0060",
    "sg:postcode":"02170",
    "sg:province":"MA",
    "sg:tags":[
        "record",
        "document"
    ],
    "sg:website":"www.moonflight.net",
    "wof:name":"Granite City Package & Postal",
    "wof:placetype":"venue"
},
  "geometry": {"coordinates":[-71.017459,42.264421],"type":"Point"}
}