{
  "type": "Feature",
  "properties": {
    "iso:country":"US",
    "sg:address":"531 Broadway",
    "sg:city":"Haverhill",
    "sg:classifiers":[
        {
            "category":"Building & Trades",
            "subcategory":"Equipment Rental",
            "type":"Services"
        }
    ],
    "sg:phone":"+1 978 374 0136",
    "sg:postcode":"01832",
    "sg:province":"MA",
    "sg:tags":[
        "yard"
    ],
    "wof:name":"Taylor Rental-Party Plus",
    "wof:placetype":"venue"
},
  "geometry": {"coordinates":[-71.121949,42.784533],"type":"Point"}
}