{
  "type": "Feature",
  "properties": {
    "iso:country":"US",
    "sg:address":"60 Main St",
    "sg:city":"Watertown",
    "sg:classifiers":[
        {
            "category":"Banks & Credit Unions",
            "subcategory":"Bank",
            "type":"Services"
        }
    ],
    "sg:phone":"+1 617 000 1111",
    "sg:postcode":"02472",
    "sg:province":"MA",
    "sg:website":"www.watertownsavings.com",
    "wof:name":"Watertown Savings Bank",
    "wof:placetype":"venue"
},
  "geometry": {"coordinates":[-71.185317,42.365948],"type":"Point"}
}