{
  "type": "Feature",
  "properties": {
    "addr:full": "60 Main St Watertown MA 02472",
    "addr:housenumber": "60",
    "addr:postcode": "02472",
    "addr:street": "Main St",
    "iso:country": "US",
    "ovtr:label": "Watertown Savings Bank, 60 Main St Watertown MA US",
    "ovtr:similarity": 3.433058977127075,
    "sg:address": "60 Main St",
    "sg:city": "Watertown",
    "sg:classifiers": [
      {
        "category": "Banks \u0026 Credit Unions",
        "subcategory": "Bank",
        "type": "Services"
      }
    ],
    "sg:phone": "+1 617 000 1111",
    "sg:postcode": "02472",
    "sg:province": "MA",
    "sg:website": "www.watertownsavings.com",
    "wof:name": "Watertown Savings Bank",
    "wof:placetype": "venue"
  },
  "geometry": {"coordinates":[-71.185317,42.365948],"type":"Point"}
}
