{
  "type": "Feature",
  "properties": {
    "addr:full":"54 Cameron Ave Somerville MA 02144",
    "addr:housenumber":"54",
    "addr:postcode":"02144",
    "addr:street":"Cameron Ave",
    "iso:country":"US",
    "sg:address":"54 Cameron Ave",
    "sg:city":"Somerville",
    "sg:classifiers":[
        {
            "category":"Professional",
            "subcategory":"Management & Consulting",
            "type":"Services"
        }
    ],
    "sg:phone":"+1   ",
    "sg:postcode":"02144",
    "sg:province":"MA",
    "wof:name":"Strategies For Success",
    "wof:placetype":"venue"
},
  "geometry": {"coordinates":[-71.128698,42.398726],"type":"Point"}
}