{
  "type": "Feature",
  "properties": {
    "addr:full":"167 Corporation Rd Hyannis MA 02601",
    "addr:housenumber":"167",
    "addr:postcode":"02601",
    "addr:street":"Corporation Rd",
    "iso:country":"US",
    "sg:address":"167 Corporation Rd",
    "sg:city":"Hyannis",
    "sg:classifiers":[
        {
            "category":"Food & Beverages",
            "subcategory":"Liquor & Beverages",
            "type":"Retail Goods"
        }
    ],
    "sg:phone":"+1 508 790 4770",
    "sg:postcode":"02601",
    "sg:province":"MA",
    "sg:tags":[
        "beer",
        "spirit",
        "wine"
    ],
    "sg:website":"www.blanchardsliquor.com",
    "wof:name":"Blanchard's Wine and Spirits",
    "wof:placetype":"venue"
},
  "geometry": {"coordinates":[-70.301188,41.666955],"type":"Point"}
}