{
  "type": "Feature",
  "properties": {
    "iso:country":"US",
    "sg:address":"683 Main St",
    "sg:city":"Falmouth",
    "sg:classifiers":[
        {
            "category":"Real Estate",
            "subcategory":"Real Estate Agent",
            "type":"Services"
        }
    ],
    "sg:phone":"+1 508 540 0979",
    "sg:postcode":"02540",
    "sg:province":"MA",
    "wof:name":"Laliberte Pauline Rl Est",
    "wof:placetype":"venue"
},
  "geometry": {"coordinates":[-70.603754,41.552954],"type":"Point"}
}