{
  "type": "Feature",
  "properties": {
    "iso:country":"US",
    "sg:address":"367 Main St",
    "sg:city":"Haverhill",
    "sg:classifiers":[
        {
            "category":"Government",
            "subcategory":"Office",
            "type":"Public Place"
        }
    ],
    "sg:phone":"+1 978 374 1960",
    "sg:postcode":"01830",
    "sg:province":"MA",
    "sg:tags":[
        "federal",
        "human"
    ],
    "wof:name":"US Social Security Adm",
    "wof:placetype":"venue"
},
  "geometry": {"coordinates":[-71.077547,42.783109],"type":"Point"}
}