{
  "type": "Feature",
  "properties": {
    "iso:country":"US",
    "sg:address":"16 School St",
    "sg:city":"Marblehead",
    "sg:classifiers":[
        {
            "category":"Building & Trades",
            "subcategory":"Construction",
            "type":"Services"
        }
    ],
    "sg:phone":"+1 781 639 2084",
    "sg:postcode":"01945",
    "sg:province":"MA",
    "sg:tags":[
        "carpenter"
    ],
    "wof:name":"Hutchinson Construction",
    "wof:placetype":"venue"
},
  "geometry": {"coordinates":[-70.85608000000001,42.501483],"type":"Point"}
}