{
  "type": "Feature",
  "properties": {
    "addr:full": "16 School St Marblehead MA 01945",
    "addr:housenumber": "16",
    "addr:postcode": "01945",
    "addr:street": "School St",
    "iso:country": "US",
    "sg:address": "16 School St",
    "sg:city": "Marblehead",
    "sg:classifiers": [
      {
        "category": "Building \u0026 Trades",
        "subcategory": "Construction",
        "type": "Services"
      }
    ],
    "sg:phone": "+1 781 639 2084",
    "sg:postcode": "01945",
    "sg:province": "MA",
    "sg:tags": [
      "carpenter"
    ],
    "wof:name": "Hutchinson Construction",
    "wof:placetype": "venue"
  },
  "geometry": {"coordinates":[-70.85608,42.501483],"type":"Point"}
}
