{
  "type": "Feature",
  "properties": {
    "iso:country":"US",
    "sg:address":"91 Hartwell Ave",
    "sg:city":"Lexington",
    "sg:classifiers":[
        {
            "category":"Professional",
            "subcategory":"Management & Consulting",
            "type":"Services"
        }
    ],
    "sg:phone":"+1   ",
    "sg:postcode":"02421",
    "sg:province":"MA",
    "sg:tags":[
        "business"
    ],
    "wof:name":"Boeing",
    "wof:placetype":"venue"
},
  "geometry": {"coordinates":[-71.25943599999999,42.470093],"type":"Point"}
}