{
  "type": "Feature",
  "properties": {
    "iso:country":"US",
    "sg:address":"54 Bromfield Rd",
    "sg:city":"Somerville",
    "sg:classifiers":[
        {
            "category":"Building & Trades",
            "subcategory":"Landscaping Services",
            "type":"Services"
        }
    ],
    "sg:phone":"+1 617 776 1361",
    "sg:postcode":"02144",
    "sg:province":"MA",
    "sg:tags":[
        "consultant",
        "lawn",
        "designer",
        "landscape"
    ],
    "wof:name":"Signature Lawns By Andy",
    "wof:placetype":"venue"
},
  "geometry": {"coordinates":[-71.115994,42.401519],"type":"Point"}
}