{
  "type": "Feature",
  "properties": {
    "iso:country":"US",
    "sg:address":"37 Briggs Ave",
    "sg:city":"Pittsfield",
    "sg:classifiers":[
        {
            "category":"Building & Trades",
            "subcategory":"Cleaning & Sanitation",
            "type":"Services"
        }
    ],
    "sg:phone":"+1 413 443 1809",
    "sg:postcode":"01201",
    "sg:province":"MA",
    "sg:tags":[
        "janitor"
    ],
    "wof:name":"After Hours Cleaning Co",
    "wof:placetype":"venue"
},
  "geometry": {"coordinates":[-73.250455,42.464318],"type":"Point"}
}