{
  "type": "Feature",
  "properties": {
    "addr:full":"691 Broadway Raynham MA 02767",
    "addr:housenumber":"691",
    "addr:postcode":"02767",
    "addr:street":"Broadway",
    "iso:country":"US",
    "sg:address":"691 Broadway",
    "sg:city":"Raynham",
    "sg:classifiers":[
        {
            "category":"Social Services",
            "subcategory":"Child Care",
            "type":"Services"
        }
    ],
    "sg:phone":"+1 508 880 3556",
    "sg:postcode":"02767",
    "sg:province":"MA",
    "sg:tags":[
        "nursery",
        "day"
    ],
    "sg:website":"http://www.commonwealthfamilychildcare.com",
    "wof:name":"Commonwealth Family Child Care",
    "wof:placetype":"venue"
},
  "geometry": {"coordinates":[-71.074051,41.947092],"type":"Point"}
}