{
  "type": "Feature",
  "properties": {
    "addr:full":"81 Samoset St Plymouth MA 02360",
    "addr:housenumber":"81",
    "addr:postcode":"02360",
    "addr:street":"Samoset St",
    "iso:country":"US",
    "sg:address":"81 Samoset St",
    "sg:city":"Plymouth",
    "sg:classifiers":[
        {
            "category":"Health Services",
            "subcategory":"Doctor",
            "type":"Services"
        }
    ],
    "sg:phone":"+1 508 747 0587",
    "sg:postcode":"02360",
    "sg:province":"MA",
    "sg:tags":[
        "throat",
        "ear",
        "nose"
    ],
    "wof:name":"Dadagian Andrew J Surg",
    "wof:placetype":"venue"
},
  "geometry": {"coordinates":[-70.677498,41.9566],"type":"Point"}
}