{
  "type": "Feature",
  "properties": {
    "addr:full": "12 Buckingham Rd Milton MA 02186",
    "addr:housenumber": "12",
    "addr:postcode": "02186",
    "addr:street": "Buckingham Rd",
    "iso:country": "US",
    "sg:address": "12 Buckingham Rd",
    "sg:city": "Milton",
    "sg:classifiers": [
      {
        "category": "Shopping",
        "subcategory": "Gifts \u0026 Souvenirs",
        "type": "Retail Goods"
      }
    ],
    "sg:phone": "+1   ",
    "sg:postcode": "02186",
    "sg:province": "MA",
    "sg:tags": [
      "shop"
    ],
    "wof:name": "Its A Wrap",
    "wof:placetype": "venue"
  },
  "geometry": {"coordinates":[-71.076223,42.248591],"type":"Point"}
}
