{
  "type": "Feature",
  "properties": {
    "addr:full":"49 Treetop Park Westborough MA 01581",
    "addr:housenumber":"49",
    "addr:postcode":"01581",
    "addr:street":"Treetop Park",
    "iso:country":"US",
    "sg:address":"49 Treetop Park",
    "sg:city":"Westborough",
    "sg:classifiers":[
        {
            "category":"Building & Trades",
            "subcategory":"Construction",
            "type":"Services"
        }
    ],
    "sg:phone":"+1   ",
    "sg:postcode":"01581",
    "sg:province":"MA",
    "sg:tags":[
        "nonresidential"
    ],
    "wof:name":"Mathieu Construction",
    "wof:placetype":"venue"
},
  "geometry": {"coordinates":[-71.62633599999999,42.279684],"type":"Point"}
}