{
  "type": "Feature",
  "properties": {
    "addr:full": "128 Eastern Ave Essex MA 01929",
    "addr:housenumber": "128",
    "addr:postcode": "01929",
    "addr:street": "Eastern Ave",
    "iso:country": "US",
    "sg:address": "128 Eastern Ave",
    "sg:city": "Essex",
    "sg:classifiers": [
      {
        "category": "Shopping",
        "subcategory": "Gifts \u0026 Souvenirs",
        "type": "Retail Goods"
      }
    ],
    "sg:phone": "+1 978 768 6232",
    "sg:postcode": "01929",
    "sg:province": "MA",
    "wof:name": "Crafters Cottage",
    "wof:placetype": "venue"
  },
  "geometry": {"coordinates":[-70.757351,42.630655],"type":"Point"}
}
