{
  "type": "Feature",
  "properties": {
    "iso:country":"US",
    "sg:address":"128 Eastern Ave",
    "sg:city":"Essex",
    "sg:classifiers":[
        {
            "category":"Shopping",
            "subcategory":"Gifts & Souvenirs",
            "type":"Retail Goods"
        }
    ],
    "sg:phone":"+1 978 768 6232",
    "sg:postcode":"01929",
    "sg:province":"MA",
    "wof:name":"Crafters Cottage",
    "wof:placetype":"venue"
},
  "geometry": {"coordinates":[-70.757351,42.630655],"type":"Point"}
}