{
  "type": "Feature",
  "properties": {
    "addr:full":"118 Colburn Rd Charlton MA 01507",
    "addr:housenumber":"118",
    "addr:postcode":"01507",
    "addr:street":"Colburn Rd",
    "iso:country":"US",
    "sg:address":"118 Colburn Rd",
    "sg:city":"Charlton",
    "sg:classifiers":[
        {
            "category":"Education",
            "subcategory":"Preschool",
            "type":"Public Place"
        },
        {
            "category":"Education",
            "subcategory":"School",
            "type":"Public Place"
        }
    ],
    "sg:phone":"+1 508 248 7337",
    "sg:postcode":"01507",
    "sg:province":"MA",
    "sg:tags":[
        "elementary"
    ],
    "wof:name":"Rainbow Riders Preschool - CLOSED",
    "wof:placetype":"venue"
},
  "geometry": {"coordinates":[-71.945503,42.110901],"type":"Point"}
}