{
  "type": "Feature",
  "properties": {
    "addr:full": "12 Pond Rd Gloucester MA 01930",
    "addr:housenumber": "12",
    "addr:postcode": "01930",
    "addr:street": "Pond Rd",
    "iso:country": "US",
    "sg:address": "12 Pond Rd",
    "sg:city": "Gloucester",
    "sg:classifiers": [
      {
        "category": "Retail",
        "subcategory": "Auto Repair",
        "type": "Services"
      }
    ],
    "sg:phone": "+1 978 283 1533",
    "sg:postcode": "01930",
    "sg:province": "MA",
    "sg:tags": [
      "body",
      "automobile",
      "painting"
    ],
    "wof:name": "Annisquam Auto Inc",
    "wof:placetype": "venue"
  },
  "geometry": {"coordinates":[-70.63802,42.629351],"type":"Point"}
}
