{
  "type": "Feature",
  "properties": {
    "addr:full":"800 Broad St East Weymouth MA 02189",
    "addr:housenumber":"800",
    "addr:postcode":"02189",
    "addr:street":"Broad St East",
    "iso:country":"US",
    "sg:address":"800 Broad St",
    "sg:city":"East Weymouth",
    "sg:classifiers":[
        {
            "category":"Restaurant",
            "type":"Food & Drink"
        }
    ],
    "sg:phone":"+1 781 337 3322",
    "sg:postcode":"02189",
    "sg:province":"MA",
    "wof:name":"Red Rose Cafe",
    "wof:placetype":"venue"
},
  "geometry": {"coordinates":[-70.925501,42.215896],"type":"Point"}
}