{
  "type": "Feature",
  "properties": {
    "addr:full": "800 Broad St East Weymouth MA 02189",
    "addr:housenumber": "800",
    "addr:postcode": "02189",
    "addr:street": "Broad St East",
    "iso:country": "US",
    "ovtr:label": "The Red Rose Cafe, 800 Broad St Weymouth MA US",
    "ovtr:similarity": 3.686742067337036,
    "sg:address": "800 Broad St",
    "sg:city": "East Weymouth",
    "sg:classifiers": [
      {
        "category": "Restaurant",
        "type": "Food \u0026 Drink"
      }
    ],
    "sg:phone": "+1 781 337 3322",
    "sg:postcode": "02189",
    "sg:province": "MA",
    "wof:name": "Red Rose Cafe",
    "wof:placetype": "venue"
  },
  "geometry": {"coordinates":[-70.925501,42.215896],"type":"Point"}
}
