{
  "type": "Feature",
  "properties": {
    "iso:country":"US",
    "sg:address":"415 Haverhill St",
    "sg:city":"Lawrence",
    "sg:classifiers":[
        {
            "category":"Autos & Motor Vehicles",
            "subcategory":"Automobile Sales",
            "type":"Retail Goods"
        }
    ],
    "sg:phone":"+1 978 974 0222",
    "sg:postcode":"01840",
    "sg:province":"MA",
    "sg:tags":[
        "car",
        "dealer"
    ],
    "wof:name":"A & R Auto Music",
    "wof:placetype":"venue"
},
  "geometry": {"coordinates":[-71.17317,42.707716],"type":"Point"}
}