{
  "type": "Feature",
  "properties": {
    "addr:full": "415 Haverhill St Lawrence MA 01840",
    "addr:housenumber": "415",
    "addr:postcode": "01840",
    "addr:street": "Haverhill St",
    "iso:country": "US",
    "sg:address": "415 Haverhill St",
    "sg:city": "Lawrence",
    "sg:classifiers": [
      {
        "category": "Autos \u0026 Motor Vehicles",
        "subcategory": "Automobile Sales",
        "type": "Retail Goods"
      }
    ],
    "sg:phone": "+1 978 974 0222",
    "sg:postcode": "01840",
    "sg:province": "MA",
    "sg:tags": [
      "car",
      "dealer"
    ],
    "wof:name": "A \u0026 R Auto Music",
    "wof:placetype": "venue"
  },
  "geometry": {"coordinates":[-71.17317,42.707716],"type":"Point"}
}
