{
  "type": "Feature",
  "properties": {
    "addr:full":"215 Arlington St Acton MA 01720",
    "addr:housenumber":"215",
    "addr:postcode":"01720",
    "addr:street":"Arlington St",
    "iso:country":"US",
    "sg:address":"215 Arlington St",
    "sg:city":"Acton",
    "sg:classifiers":[
        {
            "category":"Professional",
            "type":"Services"
        }
    ],
    "sg:phone":"+1   ",
    "sg:postcode":"01720",
    "sg:province":"MA",
    "sg:tags":[
        "training",
        "consulting",
        "scientific"
    ],
    "wof:name":"Vicki L Burnett",
    "wof:placetype":"venue"
},
  "geometry": {"coordinates":[-71.471057,42.478699],"type":"Point"}
}