{
  "type": "Feature",
  "properties": {
    "iso:country":"US",
    "sg:address":"29 Straits Rd",
    "sg:city":"South Deerfield",
    "sg:classifiers":[
        {
            "category":"Retail",
            "subcategory":"Laundry & Dry Cleaning",
            "type":"Services"
        }
    ],
    "sg:phone":"+1 413 665 8311",
    "sg:postcode":"01373",
    "sg:province":"MA",
    "sg:tags":[
        "cleaners",
        "upholstery"
    ],
    "wof:name":"A & J Carpet Cleaning",
    "wof:placetype":"venue"
},
  "geometry": {"coordinates":[-72.59717499999999,42.437029],"type":"Point"}
}