{
  "type": "Feature",
  "properties": {
    "addr:full": "29 Straits Rd South Deerfield MA 01373",
    "addr:housenumber": "29",
    "addr:postcode": "01373",
    "addr:street": "Straits Rd",
    "iso:country": "US",
    "sg:address": "29 Straits Rd",
    "sg:city": "South Deerfield",
    "sg:classifiers": [
      {
        "category": "Retail",
        "subcategory": "Laundry \u0026 Dry Cleaning",
        "type": "Services"
      }
    ],
    "sg:phone": "+1 413 665 8311",
    "sg:postcode": "01373",
    "sg:province": "MA",
    "sg:tags": [
      "cleaners",
      "upholstery"
    ],
    "wof:name": "A \u0026 J Carpet Cleaning",
    "wof:placetype": "venue"
  },
  "geometry": {"coordinates":[-72.597175,42.437029],"type":"Point"}
}
