{
  "type": "Feature",
  "properties": {
    "iso:country":"US",
    "sg:address":"2 Elm St",
    "sg:city":"Braintree",
    "sg:classifiers":[
        {
            "category":"Restaurant",
            "type":"Food & Drink"
        }
    ],
    "sg:phone":"+1 781 849 3354",
    "sg:postcode":"02184",
    "sg:province":"MA",
    "sg:tags":[
        "delicatessen"
    ],
    "wof:name":"Murray's Deli",
    "wof:placetype":"venue"
},
  "geometry": {"coordinates":[-71.00285,42.221329],"type":"Point"}
}