{
  "type": "Feature",
  "properties": {
    "addr:full": "161 Essex St Lynn MA 01902",
    "addr:housenumber": "161",
    "addr:postcode": "01902",
    "addr:street": "Essex St",
    "iso:country": "US",
    "sg:address": "161 Essex St",
    "sg:city": "Lynn",
    "sg:classifiers": [
      {
        "category": "Food \u0026 Beverages",
        "subcategory": "Groceries \u0026 Convenience Stores",
        "type": "Retail Goods"
      }
    ],
    "sg:phone": "+1 781 477 2399",
    "sg:postcode": "01902",
    "sg:province": "MA",
    "sg:tags": [
      "market"
    ],
    "wof:name": "Alnour Market",
    "wof:placetype": "venue"
  },
  "geometry": {"coordinates":[-70.932641,42.472711],"type":"Point"}
}
