{
  "type": "Feature",
  "properties": {
    "iso:country":"US",
    "sg:address":"161 Essex St",
    "sg:city":"Lynn",
    "sg:classifiers":[
        {
            "category":"Food & Beverages",
            "subcategory":"Groceries & Convenience Stores",
            "type":"Retail Goods"
        }
    ],
    "sg:phone":"+1 781 477 2399",
    "sg:postcode":"01902",
    "sg:province":"MA",
    "sg:tags":[
        "market"
    ],
    "wof:name":"Alnour Market",
    "wof:placetype":"venue"
},
  "geometry": {"coordinates":[-70.932641,42.472711],"type":"Point"}
}