{
  "type": "Feature",
  "properties": {
    "iso:country":"US",
    "sg:address":"303 Tremont St",
    "sg:city":"Carver",
    "sg:classifiers":[
        {
            "category":"Autos & Motor Vehicles",
            "subcategory":"Fuel & Gas Station",
            "type":"Retail Goods"
        }
    ],
    "sg:phone":"+1 508 866 3081",
    "sg:postcode":"02330",
    "sg:province":"MA",
    "wof:name":"Delta Gas & Service Center",
    "wof:placetype":"venue"
},
  "geometry": {"coordinates":[-70.7509,41.832199],"type":"Point"}
}