{
  "type": "Feature",
  "properties": {
    "addr:full": "303 Tremont St Carver MA 02330",
    "addr:housenumber": "303",
    "addr:postcode": "02330",
    "addr:street": "Tremont St",
    "iso:country": "US",
    "sg:address": "303 Tremont St",
    "sg:city": "Carver",
    "sg:classifiers": [
      {
        "category": "Autos \u0026 Motor Vehicles",
        "subcategory": "Fuel \u0026 Gas Station",
        "type": "Retail Goods"
      }
    ],
    "sg:phone": "+1 508 866 3081",
    "sg:postcode": "02330",
    "sg:province": "MA",
    "wof:name": "Delta Gas \u0026 Service Center",
    "wof:placetype": "venue"
  },
  "geometry": {"coordinates":[-70.7509,41.832199],"type":"Point"}
}
