{
  "type": "Feature",
  "properties": {
    "iso:country":"US",
    "sg:address":"82 Elm St",
    "sg:city":"Millbury",
    "sg:classifiers":[
        {
            "category":"Real Estate",
            "subcategory":"Real Estate Agent",
            "type":"Services"
        }
    ],
    "sg:phone":"+1 508 865 1177",
    "sg:postcode":"01527",
    "sg:province":"MA",
    "wof:name":"Cross County Realty",
    "wof:placetype":"venue"
},
  "geometry": {"coordinates":[-71.758016,42.192479],"type":"Point"}
}