{
  "type": "Feature",
  "properties": {
    "addr:full": "82 Elm St Millbury MA 01527",
    "addr:housenumber": "82",
    "addr:postcode": "01527",
    "addr:street": "Elm St",
    "iso:country": "US",
    "sg:address": "82 Elm St",
    "sg:city": "Millbury",
    "sg:classifiers": [
      {
        "category": "Real Estate",
        "subcategory": "Real Estate Agent",
        "type": "Services"
      }
    ],
    "sg:phone": "+1 508 865 1177",
    "sg:postcode": "01527",
    "sg:province": "MA",
    "wof:name": "Cross County Realty",
    "wof:placetype": "venue"
  },
  "geometry": {"coordinates":[-71.758016,42.192479],"type":"Point"}
}
