{
  "type": "Feature",
  "properties": {
    "iso:country":"US",
    "sg:address":"249 Great Western Rd",
    "sg:city":"South Dennis",
    "sg:classifiers":[
        {
            "category":"Autos & Motor Vehicles",
            "subcategory":"Motorcycle Sales",
            "type":"Retail Goods"
        }
    ],
    "sg:phone":"+1 508 760 5075",
    "sg:postcode":"02660",
    "sg:province":"MA",
    "wof:name":"Rancourt Motorsports",
    "wof:placetype":"venue"
},
  "geometry": {"coordinates":[-70.131248,41.689783],"type":"Point"}
}