{
  "type": "Feature",
  "properties": {
    "iso:country":"US",
    "sg:address":"124 Harvard St",
    "sg:city":"Brookline",
    "sg:classifiers":[
        {
            "category":"Health Services",
            "subcategory":"Health Practitioner",
            "type":"Services"
        }
    ],
    "sg:phone":"+1   ",
    "sg:postcode":"02446",
    "sg:province":"MA",
    "wof:name":"Phyllis Y Beineke",
    "wof:placetype":"venue"
},
  "geometry": {"coordinates":[-71.121498,42.336936],"type":"Point"}
}