{
  "type": "Feature",
  "properties": {
    "addr:full": "85 W Newton St Boston MA 02228",
    "addr:housenumber": "85",
    "addr:postcode": "02228",
    "addr:street": "W Newton St",
    "iso:country": "US",
    "sg:address": "85 W Newton St",
    "sg:city": "Boston",
    "sg:classifiers": [
      {
        "category": "Arts \u0026 Performance",
        "subcategory": "Arts Center",
        "type": "Entertainment"
      },
      {
        "category": "Retail",
        "subcategory": "Event Space",
        "type": "Services"
      }
    ],
    "sg:phone": "+1 617 927 1722",
    "sg:postcode": "02228",
    "sg:province": "MA",
    "sg:tags": [
      "performing",
      "venue"
    ],
    "sg:website": "www.villavictoriaarts.org",
    "wof:name": "Villa Victoria Center for the Arts",
    "wof:placetype": "venue"
  },
  "geometry": {"coordinates":[-71.0758,42.341],"type":"Point"}
}
