{
  "type": "Feature",
  "properties": {
    "iso:country":"US",
    "sg:address":"8 Truro Center Rd",
    "sg:city":"Truro",
    "sg:classifiers":[
        {
            "category":"Shopping",
            "subcategory":"Bicycles & Sporting Goods",
            "type":"Retail Goods"
        }
    ],
    "sg:phone":"+1 508 349 3228",
    "sg:postcode":"02666",
    "sg:province":"MA",
    "sg:tags":[
        "bait",
        "fishing"
    ],
    "wof:name":"Pamet Bait & Tackle",
    "wof:placetype":"venue"
},
  "geometry": {"coordinates":[-70.049137,41.99213],"type":"Point"}
}