{
  "type": "Feature",
  "properties": {
    "addr:full": "1442 Grafton St Worcester MA 01604",
    "addr:housenumber": "1442",
    "addr:postcode": "01604",
    "addr:street": "Grafton St",
    "iso:country": "US",
    "ovtr:label": "7-Eleven, 1442 Grafton St Worcester MA US",
    "ovtr:similarity": 2.540395975112915,
    "sg:address": "1442 Grafton St",
    "sg:city": "Worcester",
    "sg:classifiers": [
      {
        "category": "Food \u0026 Beverages",
        "subcategory": "Groceries \u0026 Convenience Stores",
        "type": "Retail Goods"
      }
    ],
    "sg:phone": "+1 508 754 0220",
    "sg:postcode": "01604",
    "sg:province": "MA",
    "wof:name": "7-Eleven",
    "wof:placetype": "venue"
  },
  "geometry": {"coordinates":[-71.746189,42.233478],"type":"Point"}
}
