{
  "type": "Feature",
  "properties": {
    "iso:country":"US",
    "sg:address":"1442 Grafton St",
    "sg:city":"Worcester",
    "sg:classifiers":[
        {
            "category":"Food & Beverages",
            "subcategory":"Groceries & Convenience Stores",
            "type":"Retail Goods"
        }
    ],
    "sg:phone":"+1 508 754 0220",
    "sg:postcode":"01604",
    "sg:province":"MA",
    "wof:name":"7-Eleven",
    "wof:placetype":"venue"
},
  "geometry": {"coordinates":[-71.746189,42.233478],"type":"Point"}
}