{
  "type": "Feature",
  "properties": {
    "iso:country":"US",
    "sg:address":"20 Washington Street Apt 232",
    "sg:city":"Brighton",
    "sg:classifiers":[
        {
            "category":"Real Estate",
            "subcategory":"Real Estate Operator",
            "type":"Services"
        }
    ],
    "sg:phone":"+1 617 734 1005",
    "sg:postcode":"02135",
    "sg:province":"MA",
    "sg:tags":[
        "apartment"
    ],
    "wof:name":"Patricia White Apartments",
    "wof:placetype":"venue"
},
  "geometry": {"coordinates":[-71.141176,42.342737],"type":"Point"}
}