{
  "type": "Feature",
  "properties": {
    "addr:full": "54 Dodge St Beverly MA 01915",
    "addr:housenumber": "54",
    "addr:postcode": "01915",
    "addr:street": "Dodge St",
    "iso:country": "US",
    "sg:address": "54 Dodge St",
    "sg:city": "Beverly",
    "sg:classifiers": [
      {
        "category": "Real Estate",
        "subcategory": "Real Estate Services",
        "type": "Services"
      },
      {
        "category": "Real Estate",
        "subcategory": "Real Estate Agent",
        "type": "Services"
      }
    ],
    "sg:phone": "+1 978 927 1111",
    "sg:postcode": "01915",
    "sg:province": "MA",
    "sg:tags": [
      "buyer",
      "broker"
    ],
    "wof:name": "Nrt",
    "wof:placetype": "venue"
  },
  "geometry": {"coordinates":[-70.89109,42.576809],"type":"Point"}
}
