{
  "type": "Feature",
  "properties": {
    "iso:country":"US",
    "sg:address":"5 Julia St",
    "sg:city":"Newburyport",
    "sg:classifiers":[
        {
            "category":"Professional",
            "subcategory":"Computer Services",
            "type":"Services"
        }
    ],
    "sg:phone":"+1 978 465 8448",
    "sg:postcode":"01950",
    "sg:province":"MA",
    "sg:tags":[
        "website",
        "design"
    ],
    "wof:name":"Beth Durkee",
    "wof:placetype":"venue"
},
  "geometry": {"coordinates":[-70.818557,42.809011],"type":"Point"}
}