{
  "type": "Feature",
  "properties": {
    "addr:full":"1334 Park St Stoughton MA 02072",
    "addr:housenumber":"1334",
    "addr:postcode":"02072",
    "addr:street":"Park St",
    "iso:country":"US",
    "sg:address":"1334 Park St",
    "sg:city":"Stoughton",
    "sg:classifiers":[
        {
            "category":"Shopping",
            "subcategory":"Department Store",
            "type":"Retail Goods"
        }
    ],
    "sg:phone":"+1 781 297 9611",
    "sg:postcode":"02072",
    "sg:province":"MA",
    "sg:tags":[
        "shop"
    ],
    "wof:name":"Dollar Tree",
    "wof:placetype":"venue"
},
  "geometry": {"coordinates":[-71.067936,42.103525],"type":"Point"}
}