{
  "type": "Feature",
  "properties": {
    "iso:country":"US",
    "sg:address":"253 Hyde Park Ave",
    "sg:city":"Jamaica Plain",
    "sg:classifiers":[
        {
            "category":"Shopping",
            "subcategory":"Computers & Home Electronics",
            "type":"Retail Goods"
        }
    ],
    "sg:phone":"+1 617 522 6286",
    "sg:postcode":"02130",
    "sg:province":"MA",
    "sg:tags":[
        "equipment",
        "dealer"
    ],
    "wof:name":"Jose Computer Repair",
    "wof:placetype":"venue"
},
  "geometry": {"coordinates":[-71.117909,42.291581],"type":"Point"}
}