{
  "type": "Feature",
  "properties": {
    "addr:full": "253 Hyde Park Ave Jamaica Plain MA 02130",
    "addr:housenumber": "253",
    "addr:postcode": "02130",
    "addr:street": "Hyde Park Ave",
    "iso:country": "US",
    "sg:address": "253 Hyde Park Ave",
    "sg:city": "Jamaica Plain",
    "sg:classifiers": [
      {
        "category": "Shopping",
        "subcategory": "Computers \u0026 Home Electronics",
        "type": "Retail Goods"
      }
    ],
    "sg:phone": "+1 617 522 6286",
    "sg:postcode": "02130",
    "sg:province": "MA",
    "sg:tags": [
      "equipment",
      "dealer"
    ],
    "wof:name": "Jose Computer Repair",
    "wof:placetype": "venue"
  },
  "geometry": {"coordinates":[-71.117909,42.291581],"type":"Point"}
}
