{
  "type": "Feature",
  "properties": {
    "addr:full": "694 Tremont St Apt 5 Boston MA 02118",
    "addr:housenumber": "694;5",
    "addr:postcode": "02118",
    "addr:street": "Tremont St Apt",
    "iso:country": "US",
    "sg:address": "694 Tremont St Apt 5",
    "sg:city": "Boston",
    "sg:classifiers": [
      {
        "category": "Travel",
        "subcategory": "Travel Agent",
        "type": "Entertainment"
      }
    ],
    "sg:phone": "+1 617 236 1376",
    "sg:postcode": "02118",
    "sg:province": "MA",
    "sg:tags": [
      "agency"
    ],
    "wof:name": "Word To Russia",
    "wof:placetype": "venue"
  },
  "geometry": {"coordinates":[-71.077316,42.340939],"type":"Point"}
}
