{
  "type": "Feature",
  "properties": {
    "iso:country":"US",
    "sg:address":"20 W Central St",
    "sg:city":"Franklin",
    "sg:classifiers":[
        {
            "category":"Food & Beverages",
            "subcategory":"Groceries & Convenience Stores",
            "type":"Retail Goods"
        }
    ],
    "sg:phone":"+1   ",
    "sg:postcode":"02038",
    "sg:province":"MA",
    "wof:name":"Ferraras Market",
    "wof:placetype":"venue"
},
  "geometry": {"coordinates":[-71.397734,42.082553],"type":"Point"}
}