{
  "type": "Feature",
  "properties": {
    "addr:full": "31 Grant St Exd Milford MA 01757",
    "addr:housenumber": "31",
    "addr:postcode": "01757",
    "addr:street": "Grant St Exd",
    "iso:country": "US",
    "sg:address": "31 Grant St Exd",
    "sg:city": "Milford",
    "sg:classifiers": [
      {
        "category": "Professional",
        "subcategory": "Engineering",
        "type": "Services"
      }
    ],
    "sg:phone": "+1   ",
    "sg:postcode": "01757",
    "sg:province": "MA",
    "wof:name": "Nces Equipment Co",
    "wof:placetype": "venue"
  },
  "geometry": {"coordinates":[-71.523708,42.151673],"type":"Point"}
}
