{
  "type": "Feature",
  "properties": {
    "addr:full": "195 Main St Wayland MA 01778",
    "addr:housenumber": "195",
    "addr:postcode": "01778",
    "addr:street": "Main St",
    "iso:country": "US",
    "sg:address": "195 Main St",
    "sg:city": "Wayland",
    "sg:classifiers": [
      {
        "category": "Government",
        "subcategory": "City Hall",
        "type": "Public Place"
      },
      {
        "category": "Government",
        "subcategory": "Office",
        "type": "Public Place"
      }
    ],
    "sg:phone": "+1 508 653 4126",
    "sg:postcode": "01778",
    "sg:province": "MA",
    "sg:tags": [
      "town",
      "township",
      "planner",
      "government-city",
      "village"
    ],
    "sg:website": "http://www.wayland.k12.ma.us",
    "wof:name": "Highway Department",
    "wof:placetype": "venue"
  },
  "geometry": {"coordinates":[-71.364571,42.324545],"type":"Point"}
}
