{
  "type": "Feature",
  "properties": {
    "addr:full":"14 Clement St Worcester MA 01603",
    "addr:housenumber":"14",
    "addr:postcode":"01603",
    "addr:street":"Clement St",
    "iso:country":"US",
    "sg:address":"14 Clement St",
    "sg:city":"Worcester",
    "sg:classifiers":[
        {
            "category":"Organizations",
            "subcategory":"Religious Organization",
            "type":"Services"
        }
    ],
    "sg:phone":"+1 508 752 5036",
    "sg:postcode":"01603",
    "sg:province":"MA",
    "sg:tags":[
        "church"
    ],
    "wof:name":"Pentecostal Movement Christian",
    "wof:placetype":"venue"
},
  "geometry": {"coordinates":[-71.826964,42.24932],"type":"Point"}
}