{
  "type": "Feature",
  "properties": {
    "addr:full":"5 Birdland Dr Boylston MA 01505",
    "addr:housenumber":"5",
    "addr:postcode":"01505",
    "addr:street":"Birdland Dr",
    "iso:country":"US",
    "sg:address":"5 Birdland Dr",
    "sg:city":"Boylston",
    "sg:classifiers":[
        {
            "category":"Professional",
            "subcategory":"Accounting & Tax Preparation",
            "type":"Services"
        }
    ],
    "sg:phone":"+1 508 869 6411",
    "sg:postcode":"01505",
    "sg:province":"MA",
    "sg:tags":[
        "return",
        "filing"
    ],
    "wof:name":"Donald Johnson",
    "wof:placetype":"venue"
},
  "geometry": {"coordinates":[-71.763277,42.314674],"type":"Point"}
}