{
  "type": "Feature",
  "properties": {
    "iso:country":"US",
    "sg:address":"20 Roch Cir",
    "sg:city":"Easton",
    "sg:classifiers":[
        {
            "category":"Personal",
            "subcategory":"Beauty Salon",
            "type":"Services"
        }
    ],
    "sg:phone":"+1 508 238 3555",
    "sg:postcode":"02301",
    "sg:province":"MA",
    "sg:tags":[
        "manicuring"
    ],
    "wof:name":"Check Nails",
    "wof:placetype":"venue"
},
  "geometry": {"coordinates":[-71.070875,42.068123],"type":"Point"}
}