{
  "type": "Feature",
  "properties": {
    "iso:country":"US",
    "sg:address":"69 Adams St",
    "sg:city":"Newton",
    "sg:classifiers":[
        {
            "category":"Manufacturing",
            "subcategory":"Chemicals & Compounds",
            "type":"Manufacturing & Wholesale Goods"
        }
    ],
    "sg:phone":"+1 617 964 9400",
    "sg:postcode":"02458",
    "sg:province":"MA",
    "sg:tags":[
        "plastic"
    ],
    "sg:website":"www.masspolymers.com",
    "wof:name":"Mass Polymers Corp",
    "wof:placetype":"venue"
},
  "geometry": {"coordinates":[-71.204069,42.36116],"type":"Point"}
}