{
  "type": "Feature",
  "properties": {
    "addr:full": "803 Belmont Ave Springfield MA 01108",
    "addr:housenumber": "803",
    "addr:postcode": "01108",
    "addr:street": "Belmont Ave",
    "iso:country": "US",
    "sg:address": "803 Belmont Ave",
    "sg:city": "Springfield",
    "sg:classifiers": [
      {
        "category": "Insurance",
        "subcategory": "Insurance Agent",
        "type": "Services"
      }
    ],
    "sg:phone": "+1 413 739 2579",
    "sg:postcode": "01108",
    "sg:province": "MA",
    "wof:name": "Scatolini Insurance",
    "wof:placetype": "venue"
  },
  "geometry": {"coordinates":[-72.548432,42.084527],"type":"Point"}
}
