{
  "type": "Feature",
  "properties": {
    "iso:country":"US",
    "sg:address":"803 Belmont Ave",
    "sg:city":"Springfield",
    "sg:classifiers":[
        {
            "category":"Insurance",
            "subcategory":"Insurance Agent",
            "type":"Services"
        }
    ],
    "sg:phone":"+1 413 739 2579",
    "sg:postcode":"01108",
    "sg:province":"MA",
    "wof:name":"Scatolini Insurance",
    "wof:placetype":"venue"
},
  "geometry": {"coordinates":[-72.54843200000001,42.084527],"type":"Point"}
}