{
  "type": "Feature",
  "properties": {
    "addr:full": "34 Mechanic St Worcester MA 01608",
    "addr:housenumber": "34",
    "addr:postcode": "01608",
    "addr:street": "Mechanic St",
    "iso:country": "US",
    "sg:address": "34 Mechanic St",
    "sg:city": "Worcester",
    "sg:classifiers": [
      {
        "category": "Professional",
        "subcategory": "Lawyer \u0026 Legal Services",
        "type": "Services"
      }
    ],
    "sg:phone": "+1 508 791 1300",
    "sg:postcode": "01608",
    "sg:province": "MA",
    "sg:tags": [
      "attorney"
    ],
    "sg:website": "www.malofsky-schwartz.com",
    "wof:name": "Malofsky \u0026 Schwartz",
    "wof:placetype": "venue"
  },
  "geometry": {"coordinates":[-71.800256,42.26374],"type":"Point"}
}
