{
  "type": "Feature",
  "properties": {
    "iso:country":"US",
    "sg:address":"142 Doty Cir",
    "sg:city":"West Springfield",
    "sg:classifiers":[
        {
            "category":"Retail",
            "subcategory":"Auto Rental",
            "type":"Services"
        }
    ],
    "sg:phone":"+1 413 732 0715",
    "sg:postcode":"01089",
    "sg:province":"MA",
    "sg:tags":[
        "renting",
        "automobile"
    ],
    "sg:website":"www.hertz.com",
    "wof:name":"Hertz Rent A Car",
    "wof:placetype":"venue"
},
  "geometry": {"coordinates":[-72.624573,42.144957],"type":"Point"}
}