{
  "type": "Feature",
  "properties": {
    "addr:full": "619 Dwight Rd Springfield MA 01108",
    "addr:housenumber": "619",
    "addr:postcode": "01108",
    "addr:street": "Dwight Rd",
    "iso:country": "US",
    "ovtr:label": "Franconia Golf Course, 619 Dwight Rd Springfield MA US",
    "ovtr:similarity": 2.3934218883514404,
    "sg:address": "619 Dwight Rd",
    "sg:city": "Springfield",
    "sg:classifiers": [
      {
        "category": "Sports \u0026 Exercise",
        "subcategory": "Golf",
        "type": "Entertainment"
      }
    ],
    "sg:phone": "+1 413 734 9334",
    "sg:postcode": "01108",
    "sg:province": "MA",
    "sg:tags": [
      "course"
    ],
    "wof:name": "Franconia Golf Course",
    "wof:placetype": "venue"
  },
  "geometry": {"coordinates":[-72.539563,42.065636],"type":"Point"}
}
