{
  "type": "Feature",
  "properties": {
    "iso:country":"US",
    "sg:address":"619 Dwight Rd",
    "sg:city":"Springfield",
    "sg:classifiers":[
        {
            "category":"Sports & Exercise",
            "subcategory":"Golf",
            "type":"Entertainment"
        }
    ],
    "sg:phone":"+1 413 734 9334",
    "sg:postcode":"01108",
    "sg:province":"MA",
    "sg:tags":[
        "course"
    ],
    "wof:name":"Franconia Golf Course",
    "wof:placetype":"venue"
},
  "geometry": {"coordinates":[-72.539563,42.065636],"type":"Point"}
}