{
  "type": "Feature",
  "properties": {
    "addr:full":"804 Main St Osterville MA 02655",
    "addr:housenumber":"804",
    "addr:postcode":"02655",
    "addr:street":"Main St",
    "iso:country":"US",
    "sg:address":"804 Main St",
    "sg:city":"Osterville",
    "sg:classifiers":[
        {
            "category":"Professional",
            "subcategory":"Advertising",
            "type":"Services"
        }
    ],
    "sg:phone":"+1 508 420 5566",
    "sg:postcode":"02655",
    "sg:province":"MA",
    "sg:tags":[
        "counselor"
    ],
    "sg:website":"www.pierce-cote.com",
    "wof:name":"Pierce Cote' Advertising",
    "wof:placetype":"venue"
},
  "geometry": {"coordinates":[-70.385356,41.628237],"type":"Point"}
}