{
  "type": "Feature",
  "properties": {
    "addr:full": "825 2nd St Fall River MA 02721",
    "addr:housenumber": "825",
    "addr:postcode": "02721",
    "addr:street": "2Nd St",
    "iso:country": "US",
    "sg:address": "825 2nd St",
    "sg:city": "Fall River",
    "sg:classifiers": [
      {
        "category": "Real Estate",
        "subcategory": "Real Estate Agent",
        "type": "Services"
      }
    ],
    "sg:phone": "+1 508 678 5000",
    "sg:postcode": "02721",
    "sg:province": "MA",
    "wof:name": "Affordable Real Estate",
    "wof:placetype": "venue"
  },
  "geometry": {"coordinates":[-71.159257,41.691059],"type":"Point"}
}
