{
  "type": "Feature",
  "properties": {
    "iso:country":"US",
    "sg:address":"15 Blackstone St",
    "sg:city":"Shrewsbury",
    "sg:classifiers":[
        {
            "category":"Building & Trades",
            "subcategory":"Construction",
            "type":"Services"
        }
    ],
    "sg:phone":"+1   ",
    "sg:postcode":"01545",
    "sg:province":"MA",
    "sg:tags":[
        "contractor"
    ],
    "wof:name":"J M Welding",
    "wof:placetype":"venue"
},
  "geometry": {"coordinates":[-71.73119,42.247056],"type":"Point"}
}