{
  "type": "Feature",
  "properties": {
    "addr:full": "15 Blackstone St Shrewsbury MA 01545",
    "addr:housenumber": "15",
    "addr:postcode": "01545",
    "addr:street": "Blackstone St",
    "iso:country": "US",
    "sg:address": "15 Blackstone St",
    "sg:city": "Shrewsbury",
    "sg:classifiers": [
      {
        "category": "Building \u0026 Trades",
        "subcategory": "Construction",
        "type": "Services"
      }
    ],
    "sg:phone": "+1   ",
    "sg:postcode": "01545",
    "sg:province": "MA",
    "sg:tags": [
      "contractor"
    ],
    "wof:name": "J M Welding",
    "wof:placetype": "venue"
  },
  "geometry": {"coordinates":[-71.73119,42.247056],"type":"Point"}
}
