{
  "type": "Feature",
  "properties": {
    "iso:country":"US",
    "sg:address":"4 Fish Island",
    "sg:city":"New Bedford",
    "sg:classifiers":[
        {
            "category":"Wholesale",
            "subcategory":"Seafood",
            "type":"Manufacturing & Wholesale Goods"
        }
    ],
    "sg:phone":"+1 508 979 1171",
    "sg:postcode":"02740",
    "sg:province":"MA",
    "sg:website":"www.norpel.com",
    "wof:name":"Northern Palegic Group",
    "wof:placetype":"venue"
},
  "geometry": {"coordinates":[-70.918622,41.63878],"type":"Point"}
}