{
  "type": "Feature",
  "properties": {
    "addr:full": "58 Middlesex St Quincy MA 02171",
    "addr:housenumber": "58",
    "addr:postcode": "02171",
    "addr:street": "Middlesex St",
    "iso:country": "US",
    "sg:address": "58 Middlesex St",
    "sg:city": "Quincy",
    "sg:classifiers": [
      {
        "category": "Professional",
        "subcategory": "Management \u0026 Consulting",
        "type": "Services"
      }
    ],
    "sg:phone": "+1 617 773 6615",
    "sg:postcode": "02171",
    "sg:province": "MA",
    "sg:tags": [
      "business"
    ],
    "wof:name": "Fire \u0026 Rescue Training Inc",
    "wof:placetype": "venue"
  },
  "geometry": {"coordinates":[-71.007264,42.299947],"type":"Point"}
}
