{
  "type": "Feature",
  "properties": {
    "iso:country":"US",
    "sg:address":"58 Middlesex St",
    "sg:city":"Quincy",
    "sg:classifiers":[
        {
            "category":"Professional",
            "subcategory":"Management & Consulting",
            "type":"Services"
        }
    ],
    "sg:phone":"+1 617 773 6615",
    "sg:postcode":"02171",
    "sg:province":"MA",
    "sg:tags":[
        "business"
    ],
    "wof:name":"Fire & Rescue Training Inc",
    "wof:placetype":"venue"
},
  "geometry": {"coordinates":[-71.00726400000001,42.299947],"type":"Point"}
}