{
  "type": "Feature",
  "properties": {
    "addr:full": "265 Washington St Hudson MA 01749",
    "addr:housenumber": "265",
    "addr:postcode": "01749",
    "addr:street": "Washington St",
    "iso:country": "US",
    "sg:address": "265 Washington St",
    "sg:city": "Hudson",
    "sg:classifiers": [
      {
        "category": "Recreation",
        "type": "Entertainment"
      }
    ],
    "sg:phone": "+1 978 562 9642",
    "sg:postcode": "01749",
    "sg:province": "MA",
    "sg:tags": [
      "instruction",
      "yoga"
    ],
    "wof:name": "Yoga Pathways",
    "wof:placetype": "venue"
  },
  "geometry": {"coordinates":[-71.564504,42.37544],"type":"Point"}
}
