{
  "type": "Feature",
  "properties": {
    "addr:full": "35 Hamilton Rd Waltham MA 02453",
    "addr:housenumber": "35",
    "addr:postcode": "02453",
    "addr:street": "Hamilton Rd",
    "iso:country": "US",
    "sg:address": "35 Hamilton Rd",
    "sg:city": "Waltham",
    "sg:classifiers": [
      {
        "category": "Building \u0026 Trades",
        "subcategory": "Electrical",
        "type": "Services"
      }
    ],
    "sg:phone": "+1   ",
    "sg:postcode": "02453",
    "sg:province": "MA",
    "sg:tags": [
      "electrical",
      "contractor"
    ],
    "wof:name": "Coates Electric",
    "wof:placetype": "venue"
  },
  "geometry": {"coordinates":[-71.261207,42.37004],"type":"Point"}
}
