{
  "type": "Feature",
  "properties": {
    "iso:country":"US",
    "sg:address":"35 Hamilton Rd",
    "sg:city":"Waltham",
    "sg:classifiers":[
        {
            "category":"Building & Trades",
            "subcategory":"Electrical",
            "type":"Services"
        }
    ],
    "sg:phone":"+1   ",
    "sg:postcode":"02453",
    "sg:province":"MA",
    "sg:tags":[
        "electrical",
        "contractor"
    ],
    "wof:name":"Coates Electric",
    "wof:placetype":"venue"
},
  "geometry": {"coordinates":[-71.261207,42.37004],"type":"Point"}
}