{
  "type": "Feature",
  "properties": {
    "addr:full": "8 Lantern Ln Sandwich MA 02563",
    "addr:housenumber": "8",
    "addr:postcode": "02563",
    "addr:street": "Lantern Ln",
    "iso:country": "US",
    "sg:address": "8 Lantern Ln",
    "sg:city": "Sandwich",
    "sg:classifiers": [
      {
        "category": "Professional",
        "type": "Services"
      }
    ],
    "sg:phone": "+1 508 420 3860",
    "sg:postcode": "02563",
    "sg:province": "MA",
    "sg:tags": [
      "establishment"
    ],
    "wof:name": "Jamen Inc",
    "wof:placetype": "venue"
  },
  "geometry": {"coordinates":[-70.431257,41.695838],"type":"Point"}
}
