{
  "type": "Feature",
  "properties": {
    "addr:full":"6 New England Executive Park Burlington MA 01803",
    "addr:housenumber":"6",
    "addr:postcode":"01803",
    "addr:street":"New England Executive Park",
    "iso:country":"US",
    "sg:address":"6 New England Executive Park",
    "sg:city":"Burlington",
    "sg:classifiers":[
        {
            "category":"Shopping",
            "subcategory":"Stationery & Office Supplies",
            "type":"Retail Goods"
        }
    ],
    "sg:phone":"+1 781 270 4466",
    "sg:postcode":"01803",
    "sg:province":"MA",
    "sg:tags":[
        "equipment"
    ],
    "wof:name":"Xerox",
    "wof:placetype":"venue"
},
  "geometry": {"coordinates":[-71.209576,42.482911],"type":"Point"}
}