{
  "type": "Feature",
  "properties": {
    "iso:country":"US",
    "sg:address":"21 Burlington Ave",
    "sg:city":"Boston",
    "sg:classifiers":[
        {
            "category":"Organizations",
            "subcategory":"Professional Association",
            "type":"Services"
        }
    ],
    "sg:phone":"+1 617 437 1015",
    "sg:postcode":"02215",
    "sg:province":"MA",
    "wof:name":"Association Of Data Terminal",
    "wof:placetype":"venue"
},
  "geometry": {"coordinates":[-71.10162099999999,42.346266],"type":"Point"}
}