{
  "type": "Feature",
  "properties": {
    "addr:full": "16 Spring St West Springfield MA 01089",
    "addr:housenumber": "16",
    "addr:postcode": "01089",
    "addr:street": "Spring St",
    "iso:country": "US",
    "sg:address": "16 Spring St",
    "sg:city": "West Springfield",
    "sg:classifiers": [
      {
        "category": "Arts \u0026 Performance",
        "subcategory": "Theater",
        "type": "Entertainment"
      }
    ],
    "sg:phone": "+1   ",
    "sg:postcode": "01089",
    "sg:province": "MA",
    "sg:tags": [
      "group"
    ],
    "wof:name": "and The Beat Goes On",
    "wof:placetype": "venue"
  },
  "geometry": {"coordinates":[-72.613122,42.101827],"type":"Point"}
}
