{
  "type": "Feature",
  "properties": {
    "iso:country":"US",
    "sg:address":"80 Benton Hill Rd",
    "sg:city":"Becket",
    "sg:classifiers":[
        {
            "category":"Home & Garden",
            "subcategory":"Home Furnishings",
            "type":"Retail Goods"
        }
    ],
    "sg:phone":"+1 413 623 5633",
    "sg:postcode":"01223",
    "sg:province":"MA",
    "sg:tags":[
        "pottery"
    ],
    "wof:name":"East Knoll North Pottery",
    "wof:placetype":"venue"
},
  "geometry": {"coordinates":[-73.06289599999999,42.31086],"type":"Point"}
}