{
  "type": "Feature",
  "properties": {
    "addr:full": "80 Benton Hill Rd Becket MA 01223",
    "addr:housenumber": "80",
    "addr:postcode": "01223",
    "addr:street": "Benton Hill Rd",
    "iso:country": "US",
    "sg:address": "80 Benton Hill Rd",
    "sg:city": "Becket",
    "sg:classifiers": [
      {
        "category": "Home \u0026 Garden",
        "subcategory": "Home Furnishings",
        "type": "Retail Goods"
      }
    ],
    "sg:phone": "+1 413 623 5633",
    "sg:postcode": "01223",
    "sg:province": "MA",
    "sg:tags": [
      "pottery"
    ],
    "wof:name": "East Knoll North Pottery",
    "wof:placetype": "venue"
  },
  "geometry": {"coordinates":[-73.062896,42.31086],"type":"Point"}
}
