{
  "type": "Feature",
  "properties": {
    "addr:full": "1199 N Pleasant St Amherst MA 01002",
    "addr:housenumber": "1199",
    "addr:postcode": "01002",
    "addr:street": "N Pleasant St",
    "iso:country": "US",
    "sg:address": "1199 N Pleasant St",
    "sg:city": "Amherst",
    "sg:classifiers": [
      {
        "category": "Organizations",
        "subcategory": "Religious Organization",
        "type": "Services"
      }
    ],
    "sg:phone": "+1 413 549 0500",
    "sg:postcode": "01002",
    "sg:province": "MA",
    "sg:tags": [
      "church"
    ],
    "sg:website": "www.north-church.org",
    "wof:name": "North Congregational Church",
    "wof:placetype": "venue"
  },
  "geometry": {"coordinates":[-72.530699,42.409226],"type":"Point"}
}
