{
  "type": "Feature",
  "properties": {
    "iso:country":"US",
    "sg:address":"70 Arnold Rd",
    "sg:city":"Quincy",
    "sg:classifiers":[
        {
            "category":"Home & Garden",
            "subcategory":"Garden Supply",
            "type":"Retail Goods"
        }
    ],
    "sg:phone":"+1 617 302 2271",
    "sg:postcode":"02171",
    "sg:province":"MA",
    "sg:tags":[
        "bulb",
        "seed"
    ],
    "wof:name":"Janco Greenhouse",
    "wof:placetype":"venue"
},
  "geometry": {"coordinates":[-71.017461,42.279167],"type":"Point"}
}