{
  "type": "Feature",
  "properties": {
    "addr:full": "180 Commonwealth Ave # 11 Boston MA 02116",
    "addr:housenumber": "180",
    "addr:postcode": "02116",
    "addr:street": "Commonwealth Ave # 11",
    "iso:country": "US",
    "sg:address": "180 Commonwealth Ave # 11",
    "sg:city": "Boston",
    "sg:classifiers": [
      {
        "category": "Professional",
        "subcategory": "Management \u0026 Consulting",
        "type": "Services"
      },
      {
        "category": "Professional",
        "subcategory": "Advertising",
        "type": "Services"
      }
    ],
    "sg:phone": "+1 617 421 6920",
    "sg:postcode": "02116",
    "sg:province": "MA",
    "sg:tags": [
      "marketing",
      "program",
      "consultant"
    ],
    "wof:name": "Sn Marketing",
    "wof:placetype": "venue"
  },
  "geometry": {"coordinates":[-71.079641,42.351328],"type":"Point"}
}
