{
  "type": "Feature",
  "properties": {
    "iso:country":"US",
    "sg:address":"119 Lewis Wharf",
    "sg:city":"Boston",
    "sg:classifiers":[
        {
            "category":"Wholesale",
            "subcategory":"Machinery & Supplies",
            "type":"Manufacturing & Wholesale Goods"
        }
    ],
    "sg:phone":"+1 617 227 3713",
    "sg:postcode":"02110",
    "sg:province":"MA",
    "sg:tags":[
        "parking"
    ],
    "wof:name":"Lewis Wharf Parking",
    "wof:placetype":"venue"
},
  "geometry": {"coordinates":[-71.050585,42.363279],"type":"Point"}
}