{
  "type": "Feature",
  "properties": {
    "addr:full":"2447 Massachusetts Ave Cambridge MA 02140",
    "addr:housenumber":"2447",
    "addr:postcode":"02140",
    "addr:street":"Massachusetts Ave",
    "iso:country":"US",
    "sg:address":"2447 Massachusetts Ave",
    "sg:city":"Cambridge",
    "sg:classifiers":[
        {
            "category":"Professional",
            "type":"Services"
        }
    ],
    "sg:phone":"+1   ",
    "sg:postcode":"02140",
    "sg:province":"MA",
    "wof:name":"Nikitas Hsptlity Incorporarted",
    "wof:placetype":"venue"
},
  "geometry": {"coordinates":[-71.130319,42.397394],"type":"Point"}
}