{
  "type": "Feature",
  "properties": {
    "addr:full":"17 Greenwich St Ludlow MA 01056",
    "addr:housenumber":"17",
    "addr:postcode":"01056",
    "addr:street":"Greenwich St",
    "iso:country":"US",
    "sg:address":"17 Greenwich St",
    "sg:city":"Ludlow",
    "sg:classifiers":[
        {
            "category":"Personal",
            "type":"Services"
        }
    ],
    "sg:phone":"+1   ",
    "sg:postcode":"01056",
    "sg:province":"MA",
    "wof:name":"Armentano Ssan Thrptic Massage",
    "wof:placetype":"venue"
},
  "geometry": {"coordinates":[-72.474378,42.161821],"type":"Point"}
}