{
  "type": "Feature",
  "properties": {
    "addr:full":"147 Lawrence St Lawrence MA 01841",
    "addr:housenumber":"147",
    "addr:postcode":"01841",
    "addr:street":"Lawrence St",
    "iso:country":"US",
    "sg:address":"147 Lawrence St",
    "sg:city":"Lawrence",
    "sg:classifiers":[
        {
            "category":"Restaurant",
            "type":"Food & Drink"
        }
    ],
    "sg:phone":"+1 978 975 3715",
    "sg:postcode":"01841",
    "sg:province":"MA",
    "wof:name":"El Tipico Restaurant",
    "wof:placetype":"venue"
},
  "geometry": {"coordinates":[-71.16405,42.714728],"type":"Point"}
}