{
  "type": "Feature",
  "properties": {
    "addr:full":"55 Hill Street Lexington MA 02421",
    "addr:housenumber":"55",
    "addr:postcode":"02421",
    "addr:street":"Hill Street",
    "iso:country":"US",
    "sg:address":"55 Hill Street",
    "sg:city":"Lexington",
    "sg:classifiers":[
        {
            "category":"Sports & Exercise",
            "subcategory":"Golf",
            "type":"Entertainment"
        }
    ],
    "sg:phone":"+1 781 862 9614",
    "sg:postcode":"02421",
    "sg:province":"MA",
    "wof:name":"Lexington Golf Club",
    "wof:placetype":"venue"
},
  "geometry": {"coordinates":[-71.241839,42.454856],"type":"Point"}
}