{
  "type": "Feature",
  "properties": {
    "iso:country":"US",
    "sg:address":"64 B St",
    "sg:city":"Dracut",
    "sg:classifiers":[
        {
            "category":"Retail",
            "subcategory":"Auto Repair",
            "type":"Services"
        }
    ],
    "sg:phone":"+1 978 957 3235",
    "sg:postcode":"01826",
    "sg:province":"MA",
    "sg:tags":[
        "repairing",
        "automobile"
    ],
    "wof:name":"Wally Dunn's General Repair",
    "wof:placetype":"venue"
},
  "geometry": {"coordinates":[-71.366445,42.693184],"type":"Point"}
}