{
  "type": "Feature",
  "properties": {
    "addr:full":"101 Hartwell Avenue Lexington MA 02421",
    "addr:housenumber":"101",
    "addr:postcode":"02421",
    "addr:street":"Hartwell Avenue",
    "iso:country":"US",
    "sg:address":"101 Hartwell Avenue",
    "sg:city":"Lexington",
    "sg:classifiers":[
        {
            "category":"Sports & Exercise",
            "subcategory":"Gym",
            "type":"Entertainment"
        }
    ],
    "sg:phone":"+1 781 861 4064",
    "sg:postcode":"02421",
    "sg:province":"MA",
    "sg:tags":[
        "trainer"
    ],
    "wof:name":"Biokit USA",
    "wof:placetype":"venue"
},
  "geometry": {"coordinates":[-71.262725,42.465453],"type":"Point"}
}