{
  "type": "Feature",
  "properties": {
    "addr:full": "83 Main St Charlestown MA 02129",
    "addr:housenumber": "83",
    "addr:postcode": "02129",
    "addr:street": "Main St",
    "iso:country": "US",
    "sg:address": "83 Main St",
    "sg:city": "Charlestown",
    "sg:classifiers": [
      {
        "category": "Professional",
        "type": "Services"
      }
    ],
    "sg:phone": "+1 617 241 0333",
    "sg:postcode": "02129",
    "sg:province": "MA",
    "sg:tags": [
      "establishment"
    ],
    "wof:name": "You Achieve",
    "wof:placetype": "venue"
  },
  "geometry": {"coordinates":[-71.062903,42.373826],"type":"Point"}
}
