{
  "type": "Feature",
  "properties": {
    "addr:full":"722 Florence Rd Florence MA 01062",
    "addr:housenumber":"722",
    "addr:postcode":"01062",
    "addr:street":"Florence Rd",
    "iso:country":"US",
    "sg:address":"722 Florence Rd",
    "sg:city":"Florence",
    "sg:classifiers":[
        {
            "category":"Education",
            "subcategory":"School",
            "type":"Public Place"
        }
    ],
    "sg:phone":"+1 413 586 2290",
    "sg:postcode":"01062",
    "sg:province":"MA",
    "sg:tags":[
        "organization",
        "evangelism",
        "religious",
        "worship",
        "for"
    ],
    "wof:name":"Bible Baptist Church",
    "wof:placetype":"venue"
},
  "geometry": {"coordinates":[-72.672124,42.315202],"type":"Point"}
}