{
  "type": "Feature",
  "properties": {
    "iso:country":"US",
    "sg:address":"738 Plain St",
    "sg:city":"Marshfield",
    "sg:classifiers":[
        {
            "category":"Real Estate",
            "subcategory":"Real Estate Operator",
            "type":"Services"
        }
    ],
    "sg:phone":"+1 781 837 1103",
    "sg:postcode":"02050",
    "sg:province":"MA",
    "sg:tags":[
        "apartment"
    ],
    "wof:name":"Village At Marshfield",
    "wof:placetype":"venue"
},
  "geometry": {"coordinates":[-70.74485900000001,42.106135],"type":"Point"}
}