{
  "type": "Feature",
  "properties": {
    "addr:full": "24 Sandwich Rd Wareham MA 02571",
    "addr:housenumber": "24",
    "addr:postcode": "02571",
    "addr:street": "Sandwich Rd",
    "iso:country": "US",
    "sg:address": "24 Sandwich Rd",
    "sg:city": "Wareham",
    "sg:classifiers": [
      {
        "category": "Professional",
        "subcategory": "Computer Services",
        "type": "Services"
      }
    ],
    "sg:phone": "+1 508 273 2363",
    "sg:postcode": "02571",
    "sg:province": "MA",
    "sg:tags": [
      "repair"
    ],
    "wof:name": "Rogue Wave Networks",
    "wof:placetype": "venue"
  },
  "geometry": {"coordinates":[-70.708973,41.757701],"type":"Point"}
}
