{
  "type": "Feature",
  "properties": {
    "iso:country":"US",
    "sg:address":"17 Columbia St",
    "sg:city":"Swampscott",
    "sg:classifiers":[
        {
            "category":"Food & Beverages",
            "subcategory":"Candy",
            "type":"Retail Goods"
        }
    ],
    "sg:phone":"+1 781 595 8240",
    "sg:postcode":"01907",
    "sg:province":"MA",
    "sg:tags":[
        "confectionery"
    ],
    "wof:name":"Creative Custom Chocolate",
    "wof:placetype":"venue"
},
  "geometry": {"coordinates":[-70.924575,42.473052],"type":"Point"}
}