{
  "type": "Feature",
  "properties": {
    "iso:country":"US",
    "sg:address":"51 Locust St",
    "sg:city":"Northampton",
    "sg:classifiers":[
        {
            "category":"Health Services",
            "subcategory":"Doctor",
            "type":"Services"
        }
    ],
    "sg:phone":"+1 413 584 3741",
    "sg:postcode":"01060",
    "sg:province":"MA",
    "sg:tags":[
        "dentist"
    ],
    "wof:name":"Alan P Branch DDS",
    "wof:placetype":"venue"
},
  "geometry": {"coordinates":[-72.65490200000001,42.332255],"type":"Point"}
}