{
  "type": "Feature",
  "properties": {
    "addr:full":"9 Mystic Street Arlington MA 02474",
    "addr:housenumber":"9",
    "addr:postcode":"02474",
    "addr:street":"Mystic Street",
    "iso:country":"US",
    "sg:address":"9 Mystic Street",
    "sg:city":"Arlington",
    "sg:classifiers":[
        {
            "category":"Shopping",
            "subcategory":"Antiques",
            "type":"Retail Goods"
        }
    ],
    "sg:phone":"+1 781 648 3322",
    "sg:postcode":"02474",
    "sg:province":"MA",
    "wof:name":"Restoration Services",
    "wof:placetype":"venue"
},
  "geometry": {"coordinates":[-71.152564,42.415944],"type":"Point"}
}