{
  "type": "Feature",
  "properties": {
    "addr:full": "168 Old Ferry Rd Haverhill MA 01830",
    "addr:housenumber": "168",
    "addr:postcode": "01830",
    "addr:street": "Old Ferry Rd",
    "iso:country": "US",
    "sg:address": "168 Old Ferry Rd",
    "sg:city": "Haverhill",
    "sg:classifiers": [
      {
        "category": "Building \u0026 Trades",
        "subcategory": "Construction",
        "type": "Services"
      }
    ],
    "sg:phone": "+1 978 373 3620",
    "sg:postcode": "01830",
    "sg:province": "MA",
    "sg:tags": [
      "contractor"
    ],
    "wof:name": "Personal Touch Construction",
    "wof:placetype": "venue"
  },
  "geometry": {"coordinates":[-71.041397,42.770699],"type":"Point"}
}
