{
  "type": "Feature",
  "properties": {
    "addr:full": "128 Wheeler Rd Ste 5 Burlington MA 01803",
    "addr:housenumber": "128",
    "addr:postcode": "01803",
    "addr:street": "Wheeler Rd Ste 5",
    "iso:country": "US",
    "sg:address": "128 Wheeler Rd Ste 5",
    "sg:city": "Burlington",
    "sg:classifiers": [
      {
        "category": "Real Estate",
        "subcategory": "Real Estate Services",
        "type": "Services"
      }
    ],
    "sg:phone": "+1 781 270 3655",
    "sg:postcode": "01803",
    "sg:province": "MA",
    "sg:tags": [
      "management",
      "property"
    ],
    "wof:name": "M N M Services Inc",
    "wof:placetype": "venue"
  },
  "geometry": {"coordinates":[-71.21479,42.476515],"type":"Point"}
}
