{
  "type": "Feature",
  "properties": {
    "iso:country":"US",
    "sg:address":"909 Wendell Rd",
    "sg:city":"Warwick",
    "sg:classifiers":[
        {
            "category":"Travel",
            "subcategory":"Campground",
            "type":"Entertainment"
        }
    ],
    "sg:phone":"+1 978 544 3425",
    "sg:postcode":"01378",
    "sg:province":"MA",
    "sg:tags":[
        "trailer"
    ],
    "wof:name":"Wagon Wheel Camping Area",
    "wof:placetype":"venue"
},
  "geometry": {"coordinates":[-72.356172,42.623394],"type":"Point"}
}