{
  "type": "Feature",
  "properties": {
    "addr:full":"794 Elm St Concord MA 01742",
    "addr:housenumber":"794",
    "addr:postcode":"01742",
    "addr:street":"Elm St",
    "iso:country":"US",
    "sg:address":"794 Elm St",
    "sg:city":"Concord",
    "sg:classifiers":[
        {
            "category":"Restaurant",
            "type":"Food & Drink"
        }
    ],
    "sg:phone":"+1 978 369 8856",
    "sg:postcode":"01742",
    "sg:province":"MA",
    "wof:name":"Sushi House",
    "wof:placetype":"venue"
},
  "geometry": {"coordinates":[-71.38927700000001,42.465571],"type":"Point"}
}