{
  "type": "Feature",
  "properties": {
    "addr:full":"786 Boston Rd Springfield MA 01119",
    "addr:housenumber":"786",
    "addr:postcode":"01119",
    "addr:street":"Boston Rd",
    "iso:country":"US",
    "sg:address":"786 Boston Rd",
    "sg:city":"Springfield",
    "sg:classifiers":[
        {
            "category":"Shopping",
            "subcategory":"Department Store",
            "type":"Retail Goods"
        }
    ],
    "sg:phone":"+1 413 783 1910",
    "sg:postcode":"01119",
    "sg:province":"MA",
    "sg:tags":[
        "shop"
    ],
    "wof:name":"Family Dollar Store",
    "wof:placetype":"venue"
},
  "geometry": {"coordinates":[-72.51886399999999,42.136917],"type":"Point"}
}