{
  "type": "Feature",
  "properties": {
    "addr:full":"45 Frank Rd Stoughton MA 02072",
    "addr:housenumber":"45",
    "addr:postcode":"02072",
    "addr:street":"Frank Rd",
    "iso:country":"US",
    "sg:address":"45 Frank Rd",
    "sg:city":"Stoughton",
    "sg:classifiers":[
        {
            "category":"Health Services",
            "subcategory":"Podiatrist",
            "type":"Services"
        }
    ],
    "sg:phone":"+1   ",
    "sg:postcode":"02072",
    "sg:province":"MA",
    "wof:name":"Donald W Clayman",
    "wof:placetype":"venue"
},
  "geometry": {"coordinates":[-71.130396,42.110466],"type":"Point"}
}