{
  "type": "Feature",
  "properties": {
    "addr:full": "37 High St Danvers MA 01923",
    "addr:housenumber": "37",
    "addr:postcode": "01923",
    "addr:street": "High St",
    "iso:country": "US",
    "ovtr:label": "Village Food Shop, 37 High St Danvers MA US",
    "ovtr:similarity": 2.4649670124053955,
    "sg:address": "37 High St",
    "sg:city": "Danvers",
    "sg:classifiers": [
      {
        "category": "Food \u0026 Beverages",
        "subcategory": "Groceries \u0026 Convenience Stores",
        "type": "Retail Goods"
      }
    ],
    "sg:phone": "+1 978 777 1402",
    "sg:postcode": "01923",
    "sg:province": "MA",
    "sg:tags": [
      "grocer"
    ],
    "wof:name": "Village Food Shop",
    "wof:placetype": "venue"
  },
  "geometry": {"coordinates":[-70.934069,42.563644],"type":"Point"}
}
