{
  "type": "Feature",
  "properties": {
    "addr:full": "2181 Washington St Roxbury MA 02119",
    "addr:housenumber": "2181",
    "addr:postcode": "02119",
    "addr:street": "Washington St",
    "iso:country": "US",
    "sg:address": "2181 Washington St",
    "sg:city": "Roxbury",
    "sg:classifiers": [
      {
        "category": "Professional",
        "subcategory": "Lawyer \u0026 Legal Services",
        "type": "Services"
      }
    ],
    "sg:phone": "+1 617 445 8409",
    "sg:postcode": "02119",
    "sg:province": "MA",
    "sg:tags": [
      "attorney",
      "practice",
      "plan"
    ],
    "wof:name": "Norton Mary F",
    "wof:placetype": "venue"
  },
  "geometry": {"coordinates":[-71.082562,42.331197],"type":"Point"}
}
