{
  "type": "Feature",
  "properties": {
    "addr:full": "6 Edmons St Worcester MA 01605",
    "addr:housenumber": "6",
    "addr:postcode": "01605",
    "addr:street": "Edmons St",
    "iso:country": "US",
    "sg:address": "6 Edmons St",
    "sg:city": "Worcester",
    "sg:classifiers": [
      {
        "category": "Utilities",
        "subcategory": "Refuse",
        "type": "Services"
      }
    ],
    "sg:phone": "+1   ",
    "sg:postcode": "01605",
    "sg:province": "MA",
    "sg:tags": [
      "system"
    ],
    "wof:name": "Oneill Rubbish Removal",
    "wof:placetype": "venue"
  },
  "geometry": {"coordinates":[-71.828592,42.300509],"type":"Point"}
}
