{
  "type": "Feature",
  "properties": {
    "addr:full": "3 Carney St Medford MA 02155",
    "addr:housenumber": "3",
    "addr:postcode": "02155",
    "addr:street": "Carney St",
    "iso:country": "US",
    "sg:address": "3 Carney St",
    "sg:city": "Medford",
    "sg:classifiers": [
      {
        "category": "Building \u0026 Trades",
        "subcategory": "Construction",
        "type": "Services"
      }
    ],
    "sg:phone": "+1 781 395 1790",
    "sg:postcode": "02155",
    "sg:province": "MA",
    "sg:tags": [
      "painter"
    ],
    "wof:name": "Crimson Painting Svc",
    "wof:placetype": "venue"
  },
  "geometry": {"coordinates":[-71.0901,42.420508],"type":"Point"}
}
