{
  "type": "Feature",
  "properties": {
    "iso:country":"US",
    "sg:address":"657 Adams St",
    "sg:city":"Quincy",
    "sg:classifiers":[
        {
            "category":"Real Estate",
            "subcategory":"Real Estate Agent",
            "type":"Services"
        }
    ],
    "sg:phone":"+1 617 328 3200",
    "sg:postcode":"02169",
    "sg:province":"MA",
    "wof:name":"Re/Max Realty Pros",
    "wof:placetype":"venue"
},
  "geometry": {"coordinates":[-71.030598,42.255331],"type":"Point"}
}