{
  "type": "Feature",
  "properties": {
    "iso:country":"US",
    "sg:address":"149 N Falmouth Hwy",
    "sg:city":"North Falmouth",
    "sg:classifiers":[
        {
            "category":"Shopping",
            "subcategory":"Used Merchandise",
            "type":"Retail Goods"
        }
    ],
    "sg:phone":"+1 508 564 4075",
    "sg:postcode":"02556",
    "sg:province":"MA",
    "sg:tags":[
        "shop",
        "thrift"
    ],
    "wof:name":"North Falmouth Congrgtnl Shop",
    "wof:placetype":"venue"
},
  "geometry": {"coordinates":[-70.622564,41.620851],"type":"Point"}
}