{
  "type": "Feature",
  "properties": {
    "addr:full": "305 Main Street Stoneham MA 02180",
    "addr:housenumber": "305",
    "addr:postcode": "02180",
    "addr:street": "Main Street",
    "iso:country": "US",
    "sg:address": "305 Main Street",
    "sg:city": "Stoneham",
    "sg:classifiers": [
      {
        "category": "Personal",
        "subcategory": "Shoe Repair \u0026 Shine",
        "type": "Services"
      }
    ],
    "sg:phone": "+1 781 438 0712",
    "sg:postcode": "02180",
    "sg:province": "MA",
    "wof:name": "Stoneham Shoe Hospital - CLOSED",
    "wof:placetype": "venue"
  },
  "geometry": {"coordinates":[-71.100034,42.481503],"type":"Point"}
}
