{
  "type": "Feature",
  "properties": {
    "addr:full": "360 Newman Ave Seekonk MA 02771",
    "addr:housenumber": "360",
    "addr:postcode": "02771",
    "addr:street": "Newman Ave",
    "iso:country": "US",
    "sg:address": "360 Newman Ave",
    "sg:city": "Seekonk",
    "sg:classifiers": [
      {
        "category": "Retail",
        "subcategory": "Repair Shop",
        "type": "Services"
      }
    ],
    "sg:phone": "+1 508 336 8072",
    "sg:postcode": "02771",
    "sg:province": "MA",
    "sg:tags": [
      "repairing",
      "lawn",
      "mower"
    ],
    "wof:name": "Tim's Repair",
    "wof:placetype": "venue"
  },
  "geometry": {"coordinates":[-71.330434,41.850982],"type":"Point"}
}
