{
  "type": "Feature",
  "properties": {
    "iso:country":"US",
    "sg:address":"92 School St",
    "sg:city":"Quincy",
    "sg:classifiers":[
        {
            "category":"Manufacturing",
            "subcategory":"Metals",
            "type":"Manufacturing & Wholesale Goods"
        }
    ],
    "sg:phone":"+1 617 471 6900",
    "sg:postcode":"02169",
    "sg:province":"MA",
    "sg:tags":[
        "windows"
    ],
    "wof:name":"Northeast Vinyl Window",
    "wof:placetype":"venue"
},
  "geometry": {"coordinates":[-71.003486,42.243839],"type":"Point"}
}