{
  "type": "Feature",
  "properties": {
    "addr:full":"114 Robinson St Lynn MA 01905",
    "addr:housenumber":"114",
    "addr:postcode":"01905",
    "addr:street":"Robinson St",
    "iso:country":"US",
    "sg:address":"114 Robinson St",
    "sg:city":"Lynn",
    "sg:classifiers":[
        {
            "category":"Manufacturing",
            "subcategory":"Printing",
            "type":"Manufacturing & Wholesale Goods"
        }
    ],
    "sg:phone":"+1 781 883 5883",
    "sg:postcode":"01905",
    "sg:province":"MA",
    "sg:tags":[
        "printer"
    ],
    "wof:name":"As Labeled Printing",
    "wof:placetype":"venue"
},
  "geometry": {"coordinates":[-70.970343,42.468024],"type":"Point"}
}