{
  "type": "Feature",
  "properties": {
    "addr:full": "313 Congress St Boston MA 02210",
    "addr:housenumber": "313",
    "addr:postcode": "02210",
    "addr:street": "Congress St",
    "iso:country": "US",
    "sg:address": "313 Congress St",
    "sg:city": "Boston",
    "sg:classifiers": [
      {
        "category": "Banks \u0026 Credit Unions",
        "subcategory": "Investment Brokerage",
        "type": "Services"
      }
    ],
    "sg:phone": "+1 617 439 0913",
    "sg:postcode": "02210",
    "sg:province": "MA",
    "sg:tags": [
      "advisory",
      "financial"
    ],
    "wof:name": "Colonial Financial Advisors",
    "wof:placetype": "venue"
  },
  "geometry": {"coordinates":[-71.050381,42.351496],"type":"Point"}
}
