{
  "type": "Feature",
  "properties": {
    "iso:country":"US",
    "sg:address":"135 Bremen St",
    "sg:city":"Boston",
    "sg:phone":"+1 617 561 0156",
    "sg:postcode":"02128",
    "sg:province":"MA",
    "wof:name":"Paul's Lo Cost Airport Parking",
    "wof:placetype":"venue"
},
  "geometry": {"coordinates":[-71.03549599999999,42.371728],"type":"Point"}
}