{
  "type": "Feature",
  "properties": {
    "iso:country":"US",
    "sg:address":"29 Spruce St",
    "sg:city":"Milford",
    "sg:classifiers":[
        {
            "category":"Organizations",
            "subcategory":"Religious Organization",
            "type":"Services"
        }
    ],
    "sg:phone":"+1 508 473 7576",
    "sg:postcode":"01757",
    "sg:province":"MA",
    "sg:tags":[
        "church"
    ],
    "wof:name":"Assembly Of God Of Bosotn",
    "wof:placetype":"venue"
},
  "geometry": {"coordinates":[-71.51850899999999,42.142413],"type":"Point"}
}