{
  "type": "Feature",
  "properties": {
    "addr:full": "31 State St Bsmt Boston MA 02109",
    "addr:housenumber": "31",
    "addr:postcode": "02109",
    "addr:street": "State St",
    "iso:country": "US",
    "sg:address": "31 State St Bsmt",
    "sg:city": "Boston",
    "sg:classifiers": [
      {
        "category": "Professional",
        "subcategory": "Accounting \u0026 Tax Preparation",
        "type": "Services"
      },
      {
        "category": "Professional",
        "subcategory": "Lawyer \u0026 Legal Services",
        "type": "Services"
      }
    ],
    "sg:phone": "+1 617 742 1000",
    "sg:postcode": "02109",
    "sg:province": "MA",
    "sg:tags": [
      "accountant"
    ],
    "wof:name": "O'brien Daniel F Atty",
    "wof:placetype": "venue"
  },
  "geometry": {"coordinates":[-71.057297,42.358898],"type":"Point"}
}
