{
  "type": "Feature",
  "properties": {
    "addr:full": "61 Endicott St Norwood MA 02062",
    "addr:housenumber": "61",
    "addr:postcode": "02062",
    "addr:street": "Endicott St",
    "iso:country": "US",
    "sg:address": "61 Endicott St",
    "sg:city": "Norwood",
    "sg:classifiers": [
      {
        "category": "Professional",
        "subcategory": "Computer Services",
        "type": "Services"
      }
    ],
    "sg:phone": "+1 781 762 4615",
    "sg:postcode": "02062",
    "sg:province": "MA",
    "sg:tags": [
      "repair",
      "related"
    ],
    "wof:name": "American Compu Help Inc",
    "wof:placetype": "venue"
  },
  "geometry": {"coordinates":[-71.217218,42.178643],"type":"Point"}
}
