{
  "type": "Feature",
  "properties": {
    "iso:country":"US",
    "sg:address":"39 Charles St",
    "sg:city":"Wakefield",
    "sg:classifiers":[
        {
            "category":"Retail",
            "subcategory":"Laundry & Dry Cleaning",
            "type":"Services"
        }
    ],
    "sg:phone":"+1 781 245 6393",
    "sg:postcode":"01880",
    "sg:province":"MA",
    "sg:tags":[
        "cleaners",
        "rug",
        "carpet"
    ],
    "wof:name":"Sullivan Carpet & Upholstery",
    "wof:placetype":"venue"
},
  "geometry": {"coordinates":[-71.063401,42.49405],"type":"Point"}
}