{
  "type": "Feature",
  "properties": {
    "iso:country":"US",
    "sg:address":"46 Asheville Rd",
    "sg:city":"Chestnut Hill",
    "sg:classifiers":[
        {
            "category":"Organizations",
            "subcategory":"Religious Organization",
            "type":"Services"
        }
    ],
    "sg:phone":"+1   ",
    "sg:postcode":"02445",
    "sg:province":"MA",
    "wof:name":"Emmanuel B & Marleen Green",
    "wof:placetype":"venue"
},
  "geometry": {"coordinates":[-71.15429,42.296929],"type":"Point"}
}