{
  "type": "Feature",
  "properties": {
    "iso:country":"US",
    "sg:address":"368 Congress St",
    "sg:city":"Boston",
    "sg:classifiers":[
        {
            "category":"Manufacturing",
            "subcategory":"Printing",
            "type":"Manufacturing & Wholesale Goods"
        }
    ],
    "sg:phone":"+1 617 426 0609",
    "sg:postcode":"02210",
    "sg:province":"MA",
    "sg:tags":[
        "multimedia"
    ],
    "sg:website":"www.ifactory.com",
    "wof:name":"Interactive Factory",
    "wof:placetype":"venue"
},
  "geometry": {"coordinates":[-71.047893,42.350119],"type":"Point"}
}