{
  "type": "Feature",
  "properties": {
    "addr:full": "35 Market St Rockland MA 02370",
    "addr:housenumber": "35",
    "addr:postcode": "02370",
    "addr:street": "Market St",
    "iso:country": "US",
    "ovtr:label": "China Plaza Restaurant, 35 Market St Rockland MA US",
    "ovtr:similarity": 2.126913070678711,
    "sg:address": "35 Market St",
    "sg:city": "Rockland",
    "sg:classifiers": [
      {
        "category": "Restaurant",
        "type": "Food \u0026 Drink"
      }
    ],
    "sg:phone": "+1 781 878 7183",
    "sg:postcode": "02370",
    "sg:province": "MA",
    "sg:website": "http://www.chinaplaza.com",
    "wof:name": "China Plaza Restaurant",
    "wof:placetype": "venue"
  },
  "geometry": {"coordinates":[-70.916761,42.119989],"type":"Point"}
}
