{
  "type": "Feature",
  "properties": {
    "iso:country":"US",
    "sg:address":"35 Market St",
    "sg:city":"Rockland",
    "sg:classifiers":[
        {
            "category":"Restaurant",
            "type":"Food & Drink"
        }
    ],
    "sg:phone":"+1 781 878 7183",
    "sg:postcode":"02370",
    "sg:province":"MA",
    "sg:website":"http://www.chinaplaza.com",
    "wof:name":"China Plaza Restaurant",
    "wof:placetype":"venue"
},
  "geometry": {"coordinates":[-70.91676099999999,42.119989],"type":"Point"}
}