{
  "type": "Feature",
  "properties": {
    "addr:full":"2013 Massachusetts Ave Cambridge MA 02140",
    "addr:housenumber":"2013",
    "addr:postcode":"02140",
    "addr:street":"Massachusetts Ave",
    "iso:country":"US",
    "sg:address":"2013 Massachusetts Ave",
    "sg:city":"Cambridge",
    "sg:classifiers":[
        {
            "category":"Retail",
            "subcategory":"Car Wash",
            "type":"Services"
        }
    ],
    "sg:phone":"+1 617 547 1368",
    "sg:postcode":"02140",
    "sg:province":"MA",
    "wof:name":"Lechmere Auto Wash Centers",
    "wof:placetype":"venue"
},
  "geometry": {"coordinates":[-71.11930099999999,42.3885],"type":"Point"}
}