{
  "type": "Feature",
  "properties": {
    "iso:country":"US",
    "sg:address":"51 Longmeadow Dr",
    "sg:city":"Lowell",
    "sg:classifiers":[
        {
            "category":"Building & Trades",
            "subcategory":"Construction",
            "type":"Services"
        }
    ],
    "sg:phone":"+1 978 454 4105",
    "sg:postcode":"01852",
    "sg:province":"MA",
    "sg:tags":[
        "roofing",
        "industrial",
        "contractors-commercial",
        "contractor"
    ],
    "wof:name":"Abco Roofing Co",
    "wof:placetype":"venue"
},
  "geometry": {"coordinates":[-71.274963,42.64204],"type":"Point"}
}