{
  "type": "Feature",
  "properties": {
    "iso:country":"US",
    "sg:address":"50 Wetherell St",
    "sg:city":"Newton",
    "sg:classifiers":[
        {
            "category":"Professional",
            "subcategory":"Business Services",
            "type":"Services"
        }
    ],
    "sg:phone":"+1 617 928 1600",
    "sg:postcode":"02464",
    "sg:province":"MA",
    "sg:tags":[
        "water",
        "treatment"
    ],
    "wof:name":"GE Osmonics",
    "wof:placetype":"venue"
},
  "geometry": {"coordinates":[-71.21679899999999,42.312087],"type":"Point"}
}