{
  "type": "Feature",
  "properties": {
    "addr:full": "50 Wetherell St Newton MA 02464",
    "addr:housenumber": "50",
    "addr:postcode": "02464",
    "addr:street": "Wetherell St",
    "iso:country": "US",
    "sg:address": "50 Wetherell St",
    "sg:city": "Newton",
    "sg:classifiers": [
      {
        "category": "Professional",
        "subcategory": "Business Services",
        "type": "Services"
      }
    ],
    "sg:phone": "+1 617 928 1600",
    "sg:postcode": "02464",
    "sg:province": "MA",
    "sg:tags": [
      "water",
      "treatment"
    ],
    "wof:name": "GE Osmonics",
    "wof:placetype": "venue"
  },
  "geometry": {"coordinates":[-71.216799,42.312087],"type":"Point"}
}
