{
  "type": "Feature",
  "properties": {
    "iso:country":"US",
    "sg:address":"209 Main St",
    "sg:city":"East Orleans",
    "sg:classifiers":[
        {
            "category":"Personal",
            "subcategory":"Beauty Salon",
            "type":"Services"
        }
    ],
    "sg:phone":"+1 508 255 0913",
    "sg:postcode":"02653",
    "sg:province":"MA",
    "wof:name":"Janie's Hair & Things",
    "wof:placetype":"venue"
},
  "geometry": {"coordinates":[-69.968086,41.784788],"type":"Point"}
}