{
  "type": "Feature",
  "properties": {
    "addr:full": "209 Main St East Orleans MA 02653",
    "addr:housenumber": "209",
    "addr:postcode": "02653",
    "addr:street": "Main St East",
    "iso:country": "US",
    "sg:address": "209 Main St",
    "sg:city": "East Orleans",
    "sg:classifiers": [
      {
        "category": "Personal",
        "subcategory": "Beauty Salon",
        "type": "Services"
      }
    ],
    "sg:phone": "+1 508 255 0913",
    "sg:postcode": "02653",
    "sg:province": "MA",
    "wof:name": "Janie's Hair \u0026 Things",
    "wof:placetype": "venue"
  },
  "geometry": {"coordinates":[-69.968086,41.784788],"type":"Point"}
}
