{
  "type": "Feature",
  "properties": {
    "addr:full": "65 Hale St Haverhill MA 01830",
    "addr:housenumber": "65",
    "addr:postcode": "01830",
    "addr:street": "Hale St",
    "iso:country": "US",
    "sg:address": "65 Hale St",
    "sg:city": "Haverhill",
    "sg:classifiers": [
      {
        "category": "Freight",
        "type": "Transportation"
      }
    ],
    "sg:phone": "+1 978 521 6230",
    "sg:postcode": "01830",
    "sg:province": "MA",
    "sg:tags": [
      "trucking"
    ],
    "wof:name": "Mccarthy Transportation",
    "wof:placetype": "venue"
  },
  "geometry": {"coordinates":[-71.087812,42.780664],"type":"Point"}
}
