{
  "type": "Feature",
  "properties": {
    "addr:full": "331 Peru Rd Hinsdale MA 01226",
    "addr:housenumber": "331",
    "addr:postcode": "01226",
    "addr:street": "Peru Rd",
    "iso:country": "US",
    "sg:address": "331 Peru Rd",
    "sg:city": "Hinsdale",
    "sg:classifiers": [
      {
        "category": "Freight",
        "type": "Transportation"
      }
    ],
    "sg:phone": "+1 413 655 8100",
    "sg:postcode": "01226",
    "sg:province": "MA",
    "sg:tags": [
      "commercial",
      "storage"
    ],
    "wof:name": "Hinsdale Mini Storage",
    "wof:placetype": "venue"
  },
  "geometry": {"coordinates":[-73.102978,42.442048],"type":"Point"}
}
