{
  "type": "Feature",
  "properties": {
    "addr:full": "518 Westfield Rd Holyoke MA 01040",
    "addr:housenumber": "518",
    "addr:postcode": "01040",
    "addr:street": "Westfield Rd",
    "iso:country": "US",
    "ovtr:label": "202 Liquors, 518 Westfield Rd Holyoke MA US",
    "ovtr:similarity": 1.9928309917449951,
    "sg:address": "518 Westfield Rd",
    "sg:city": "Holyoke",
    "sg:classifiers": [
      {
        "category": "Food \u0026 Beverages",
        "subcategory": "Liquor \u0026 Beverages",
        "type": "Retail Goods"
      }
    ],
    "sg:phone": "+1 413 532 4303",
    "sg:postcode": "01040",
    "sg:province": "MA",
    "wof:name": "202 Liquors",
    "wof:placetype": "venue"
  },
  "geometry": {"coordinates":[-72.682499,42.180254],"type":"Point"}
}
