{
  "type": "Feature",
  "properties": {
    "iso:country":"US",
    "sg:address":"518 Westfield Rd",
    "sg:city":"Holyoke",
    "sg:classifiers":[
        {
            "category":"Food & Beverages",
            "subcategory":"Liquor & Beverages",
            "type":"Retail Goods"
        }
    ],
    "sg:phone":"+1 413 532 4303",
    "sg:postcode":"01040",
    "sg:province":"MA",
    "wof:name":"202 Liquors",
    "wof:placetype":"venue"
},
  "geometry": {"coordinates":[-72.68249900000001,42.180254],"type":"Point"}
}