{
  "type": "Feature",
  "properties": {
    "iso:country":"US",
    "sg:address":"108 Salem St",
    "sg:city":"Andover",
    "sg:classifiers":[
        {
            "category":"Professional",
            "subcategory":"Engineering",
            "type":"Services"
        }
    ],
    "sg:phone":"+1   ",
    "sg:postcode":"01810",
    "sg:province":"MA",
    "wof:name":"Mark Delisio",
    "wof:placetype":"venue"
},
  "geometry": {"coordinates":[-71.117448,42.639055],"type":"Point"}
}