{
  "type": "Feature",
  "properties": {
    "iso:country":"US",
    "sg:address":"33 Kingston St",
    "sg:city":"Boston",
    "sg:classifiers":[
        {
            "category":"Professional",
            "subcategory":"Lawyer & Legal Services",
            "type":"Services"
        }
    ],
    "sg:phone":"+1 617 451 0531",
    "sg:postcode":"02111",
    "sg:province":"MA",
    "sg:tags":[
        "attorney"
    ],
    "wof:name":"Esthuer C Dezube LAW Office",
    "wof:placetype":"venue"
},
  "geometry": {"coordinates":[-71.05929399999999,42.353558],"type":"Point"}
}