{
  "type": "Feature",
  "properties": {
    "addr:full":"129 Mount Auburn St Watertown MA 02472",
    "addr:housenumber":"129",
    "addr:postcode":"02472",
    "addr:street":"Mount Auburn St",
    "iso:country":"US",
    "sg:address":"129 Mount Auburn St",
    "sg:city":"Watertown",
    "sg:classifiers":[
        {
            "category":"Wholesale",
            "subcategory":"Apparel",
            "type":"Manufacturing & Wholesale Goods"
        },
        {
            "category":"Manufacturing",
            "subcategory":"Apparel",
            "type":"Manufacturing & Wholesale Goods"
        }
    ],
    "sg:phone":"+1 617 926 6962",
    "sg:postcode":"02472",
    "sg:province":"MA",
    "sg:tags":[
        "dress",
        "sportswear",
        "mfg"
    ],
    "wof:name":"John's Sportswear",
    "wof:placetype":"venue"
},
  "geometry": {"coordinates":[-71.178882,42.367908],"type":"Point"}
}