{
  "type": "Feature",
  "properties": {
    "iso:country":"US",
    "sg:address":"27 Kimball Rd",
    "sg:city":"Fitchburg",
    "sg:classifiers":[
        {
            "category":"Arts & Performance",
            "subcategory":"Theater",
            "type":"Entertainment"
        }
    ],
    "sg:phone":"+1 978 345 1354",
    "sg:postcode":"01420",
    "sg:province":"MA",
    "sg:tags":[
        "live",
        "music"
    ],
    "wof:name":"A Sonic DJ",
    "wof:placetype":"venue"
},
  "geometry": {"coordinates":[-71.830372,42.581257],"type":"Point"}
}