{
  "type": "Feature",
  "properties": {
    "addr:full": "549 Bedford St Whitman MA 02382",
    "addr:housenumber": "549",
    "addr:postcode": "02382",
    "addr:street": "Bedford St",
    "iso:country": "US",
    "sg:address": "549 Bedford St",
    "sg:city": "Whitman",
    "sg:classifiers": [
      {
        "category": "Insurance",
        "subcategory": "Insurance Agent",
        "type": "Services"
      }
    ],
    "sg:phone": "+1 781 447 4400",
    "sg:postcode": "02382",
    "sg:province": "MA",
    "wof:name": "Johnson Insurance",
    "wof:placetype": "venue"
  },
  "geometry": {"coordinates":[-70.947223,42.074228],"type":"Point"}
}
