{
  "type": "Feature",
  "properties": {
    "addr:full":"70 Adams St North Adams MA 01247",
    "addr:housenumber":"70",
    "addr:postcode":"01247",
    "addr:street":"Adams St",
    "iso:country":"US",
    "sg:address":"70 Adams St",
    "sg:city":"North Adams",
    "sg:classifiers":[
        {
            "category":"Education",
            "subcategory":"School",
            "type":"Public Place"
        }
    ],
    "sg:phone":"+1 413 663 5383",
    "sg:postcode":"01247",
    "sg:province":"MA",
    "wof:name":"Charles H Mc Cann High School",
    "wof:placetype":"venue"
},
  "geometry": {"coordinates":[-73.122866,42.704154],"type":"Point"}
}