{
  "type": "Feature",
  "properties": {
    "addr:full": "97 Linden St Waltham MA 02452",
    "addr:housenumber": "97",
    "addr:postcode": "02452",
    "addr:street": "Linden St",
    "iso:country": "US",
    "sg:address": "97 Linden St",
    "sg:city": "Waltham",
    "sg:classifiers": [
      {
        "category": "Retail",
        "subcategory": "Auto Repair",
        "type": "Services"
      }
    ],
    "sg:phone": "+1 781 899 7353",
    "sg:postcode": "02452",
    "sg:province": "MA",
    "sg:tags": [
      "body",
      "automobile",
      "painting"
    ],
    "wof:name": "Abko Auto Body",
    "wof:placetype": "venue"
  },
  "geometry": {"coordinates":[-71.22172,42.379497],"type":"Point"}
}
