{
  "type": "Feature",
  "properties": {
    "iso:country":"US",
    "sg:address":"350 W Roxbury Pkwy",
    "sg:city":"West Roxbury",
    "sg:classifiers":[
        {
            "category":"Building & Trades",
            "subcategory":"Plumbing",
            "type":"Services"
        }
    ],
    "sg:phone":"+1 617 323 5180",
    "sg:postcode":"02131",
    "sg:province":"MA",
    "sg:tags":[
        "plumbing",
        "contractor"
    ],
    "wof:name":"Best Jobbing",
    "wof:placetype":"venue"
},
  "geometry": {"coordinates":[-71.145884,42.29539],"type":"Point"}
}