{
  "type": "Feature",
  "properties": {
    "addr:full": "350 W Roxbury Pkwy West Roxbury MA 02131",
    "addr:housenumber": "350",
    "addr:postcode": "02131",
    "addr:street": "W Roxbury Pkwy",
    "iso:country": "US",
    "sg:address": "350 W Roxbury Pkwy",
    "sg:city": "West Roxbury",
    "sg:classifiers": [
      {
        "category": "Building \u0026 Trades",
        "subcategory": "Plumbing",
        "type": "Services"
      }
    ],
    "sg:phone": "+1 617 323 5180",
    "sg:postcode": "02131",
    "sg:province": "MA",
    "sg:tags": [
      "plumbing",
      "contractor"
    ],
    "wof:name": "Best Jobbing",
    "wof:placetype": "venue"
  },
  "geometry": {"coordinates":[-71.145884,42.29539],"type":"Point"}
}
