{
  "type": "Feature",
  "properties": {
    "iso:country":"US",
    "sg:address":"1500 Main St",
    "sg:city":"Springfield",
    "sg:classifiers":[
        {
            "category":"Professional",
            "subcategory":"Lawyer & Legal Services",
            "type":"Services"
        }
    ],
    "sg:phone":"+1 413 739 7094",
    "sg:postcode":"01103",
    "sg:province":"MA",
    "sg:tags":[
        "attorney"
    ],
    "wof:name":"Bart Heemskerk",
    "wof:placetype":"venue"
},
  "geometry": {"coordinates":[-72.59178799999999,42.103075],"type":"Point"}
}