{
  "type": "Feature",
  "properties": {
    "iso:country":"US",
    "sg:address":"989 Commonwealth Ave",
    "sg:city":"Boston",
    "sg:classifiers":[
        {
            "category":"Social Services",
            "type":"Services"
        }
    ],
    "sg:phone":"+1 617 293 3841",
    "sg:postcode":"02215",
    "sg:province":"MA",
    "sg:tags":[
        "human"
    ],
    "wof:name":"Link Up Education Network, Inc",
    "wof:placetype":"venue"
},
  "geometry": {"coordinates":[-71.120209,42.35173],"type":"Point"}
}