{
  "type": "Feature",
  "properties": {
    "addr:full": "213 Cedar St Fiskdale MA 01518",
    "addr:housenumber": "213",
    "addr:postcode": "01518",
    "addr:street": "Cedar St",
    "iso:country": "US",
    "sg:address": "213 Cedar St",
    "sg:city": "Fiskdale",
    "sg:classifiers": [
      {
        "category": "Building \u0026 Trades",
        "subcategory": "Construction",
        "type": "Services"
      }
    ],
    "sg:phone": "+1 508 347 0110",
    "sg:postcode": "01518",
    "sg:province": "MA",
    "sg:tags": [
      "altering",
      "remodeling",
      "contractor"
    ],
    "wof:name": "Morin Maintenance",
    "wof:placetype": "venue"
  },
  "geometry": {"coordinates":[-72.096008,42.13599],"type":"Point"}
}
