{
  "type": "Feature",
  "properties": {
    "iso:country":"US",
    "sg:address":"213 Cedar St",
    "sg:city":"Fiskdale",
    "sg:classifiers":[
        {
            "category":"Building & Trades",
            "subcategory":"Construction",
            "type":"Services"
        }
    ],
    "sg:phone":"+1 508 347 0110",
    "sg:postcode":"01518",
    "sg:province":"MA",
    "sg:tags":[
        "altering",
        "remodeling",
        "contractor"
    ],
    "wof:name":"Morin Maintenance",
    "wof:placetype":"venue"
},
  "geometry": {"coordinates":[-72.096008,42.13599],"type":"Point"}
}