{
  "type": "Feature",
  "properties": {
    "addr:full":"207 Main St Milford MA 01757",
    "addr:housenumber":"207",
    "addr:postcode":"01757",
    "addr:street":"Main St",
    "iso:country":"US",
    "sg:address":"207 Main St",
    "sg:city":"Milford",
    "sg:classifiers":[
        {
            "category":"Personal",
            "subcategory":"Beauty Salon",
            "type":"Services"
        }
    ],
    "sg:phone":"+1 508 473 9721",
    "sg:postcode":"01757",
    "sg:province":"MA",
    "sg:tags":[
        "shop"
    ],
    "wof:name":"Sartee's Coiffures",
    "wof:placetype":"venue"
},
  "geometry": {"coordinates":[-71.52089100000001,42.139629],"type":"Point"}
}