{
  "type": "Feature",
  "properties": {
    "addr:full":"484 Main St Sturbridge MA 01518",
    "addr:housenumber":"484",
    "addr:postcode":"01518",
    "addr:street":"Main St",
    "iso:country":"US",
    "sg:address":"484 Main St",
    "sg:city":"Sturbridge",
    "sg:classifiers":[
        {
            "category":"Restaurant",
            "type":"Food & Drink"
        }
    ],
    "sg:phone":"+1 508 347 3097",
    "sg:postcode":"01518",
    "sg:province":"MA",
    "wof:name":"Sunburst Restaurant",
    "wof:placetype":"venue"
},
  "geometry": {"coordinates":[-72.05659,42.085156],"type":"Point"}
}