{
  "type": "Feature",
  "properties": {
    "addr:full": "40 Forest Rd Leominster MA 01453",
    "addr:housenumber": "40",
    "addr:postcode": "01453",
    "addr:street": "Forest Rd",
    "iso:country": "US",
    "sg:address": "40 Forest Rd",
    "sg:city": "Leominster",
    "sg:classifiers": [
      {
        "category": "Retail",
        "subcategory": "Repair Shop",
        "type": "Services"
      }
    ],
    "sg:phone": "+1 978 537 2435",
    "sg:postcode": "01453",
    "sg:province": "MA",
    "sg:tags": [
      "welding"
    ],
    "wof:name": "Peter Tamas Welding Specialist",
    "wof:placetype": "venue"
  },
  "geometry": {"coordinates":[-71.75921,42.495332],"type":"Point"}
}
