{
  "type": "Feature",
  "properties": {
    "addr:full": "51 E Mountain Rd Westfield MA 01085",
    "addr:housenumber": "51",
    "addr:postcode": "01085",
    "addr:street": "E Mountain Rd",
    "iso:country": "US",
    "sg:address": "51 E Mountain Rd",
    "sg:city": "Westfield",
    "sg:classifiers": [
      {
        "category": "Organizations",
        "subcategory": "Professional Association",
        "type": "Services"
      }
    ],
    "sg:phone": "+1 413 568 8636",
    "sg:postcode": "01085",
    "sg:province": "MA",
    "wof:name": "Westfield Youth Svc Ctr",
    "wof:placetype": "venue"
  },
  "geometry": {"coordinates":[-72.702451,42.109184],"type":"Point"}
}
