{
  "type": "Feature",
  "properties": {
    "iso:country":"US",
    "sg:address":"50 Mount Blue St",
    "sg:city":"Norwell",
    "sg:classifiers":[
        {
            "category":"Wholesale",
            "subcategory":"Electrical",
            "type":"Manufacturing & Wholesale Goods"
        }
    ],
    "sg:phone":"+1 781 659 2054",
    "sg:postcode":"02061",
    "sg:province":"MA",
    "sg:tags":[
        "alarm",
        "burglar",
        "system"
    ],
    "wof:name":"Reed Security Systems",
    "wof:placetype":"venue"
},
  "geometry": {"coordinates":[-70.80282099999999,42.177543],"type":"Point"}
}