{
  "type": "Feature",
  "properties": {
    "addr:full":"40 Nagog Park Acton MA 01720",
    "addr:housenumber":"40",
    "addr:postcode":"01720",
    "addr:street":"Nagog Park",
    "iso:country":"US",
    "sg:address":"40 Nagog Park",
    "sg:city":"Acton",
    "sg:classifiers":[
        {
            "category":"Shopping",
            "subcategory":"Computers & Home Electronics",
            "type":"Retail Goods"
        }
    ],
    "sg:phone":"+1 978 635 3900",
    "sg:postcode":"01720",
    "sg:province":"MA",
    "sg:tags":[
        "software"
    ],
    "wof:name":"Block Island Software LTD",
    "wof:placetype":"venue"
},
  "geometry": {"coordinates":[-71.43189599999999,42.525096],"type":"Point"}
}