{
  "type": "Feature",
  "properties": {
    "addr:full": "63 Court St Plymouth MA 02360",
    "addr:housenumber": "63",
    "addr:postcode": "02360",
    "addr:street": "Court St",
    "iso:country": "US",
    "sg:address": "63 Court St",
    "sg:city": "Plymouth",
    "sg:classifiers": [
      {
        "category": "Personal",
        "subcategory": "Beauty Salon",
        "type": "Services"
      }
    ],
    "sg:phone": "+1 508 746 9333",
    "sg:postcode": "02360",
    "sg:province": "MA",
    "sg:tags": [
      "shop"
    ],
    "wof:name": "Kelly Nail Salon",
    "wof:placetype": "venue"
  },
  "geometry": {"coordinates":[-70.66753,41.958615],"type":"Point"}
}
