{
  "type": "Feature",
  "properties": {
    "addr:full":"100 Stuart St Boston MA 02116",
    "addr:housenumber":"100",
    "addr:postcode":"02116",
    "addr:street":"Stuart St",
    "iso:country":"US",
    "sg:address":"100 Stuart St",
    "sg:city":"Boston",
    "sg:classifiers":[
        {
            "category":"Travel",
            "subcategory":"Hotels & Motels",
            "type":"Entertainment"
        }
    ],
    "sg:phone":"+1 617 261 8700",
    "sg:postcode":"02116",
    "sg:province":"MA",
    "sg:website":"www.starwoodhotels.com/whotels/p...",
    "wof:name":"W Hotel",
    "wof:placetype":"venue"
},
  "geometry": {"coordinates":[-71.065259,42.350941],"type":"Point"}
}