{
  "type": "Feature",
  "properties": {
    "addr:full":"291 Worcester St Natick MA 01760",
    "addr:housenumber":"291",
    "addr:postcode":"01760",
    "addr:street":"Worcester St",
    "iso:country":"US",
    "sg:address":"291 Worcester St",
    "sg:city":"Natick",
    "sg:classifiers":[
        {
            "category":"Restaurant",
            "type":"Food & Drink"
        }
    ],
    "sg:menulink":"http://www.allmenus.com/ma/natick/69916-papa-ginos/menu/",
    "sg:phone":"+1 508 651 0050",
    "sg:postcode":"01760",
    "sg:province":"MA",
    "sg:tags":[
        "american",
        "pizza"
    ],
    "wof:name":"Papa Gino's",
    "wof:placetype":"venue"
},
  "geometry": {"coordinates":[-71.33694800000001,42.302652],"type":"Point"}
}