{
  "type": "Feature",
  "properties": {
    "iso:country":"US",
    "sg:address":"2 Gault Rd",
    "sg:city":"West Wareham",
    "sg:classifiers":[
        {
            "category":"Building & Trades",
            "subcategory":"Plumbing",
            "type":"Services"
        }
    ],
    "sg:phone":"+1 508 295 3739",
    "sg:postcode":"02576",
    "sg:province":"MA",
    "sg:tags":[
        "plumbing",
        "contractor"
    ],
    "wof:name":"Charles E Hunter Plumbing Co",
    "wof:placetype":"venue"
},
  "geometry": {"coordinates":[-70.75243399999999,41.788593],"type":"Point"}
}