{
  "type": "Feature",
  "properties": {
    "addr:full":"30 Addison St Arlington MA 02476",
    "addr:housenumber":"30",
    "addr:postcode":"02476",
    "addr:street":"Addison St",
    "iso:country":"US",
    "sg:address":"30 Addison St",
    "sg:city":"Arlington",
    "sg:classifiers":[
        {
            "category":"Professional",
            "subcategory":"Art Services",
            "type":"Services"
        }
    ],
    "sg:phone":"+1   ",
    "sg:postcode":"02476",
    "sg:province":"MA",
    "sg:tags":[
        "commercial",
        "design"
    ],
    "wof:name":"Conant Design",
    "wof:placetype":"venue"
},
  "geometry": {"coordinates":[-71.154859,42.411867],"type":"Point"}
}