{
  "type": "Feature",
  "properties": {
    "iso:country":"US",
    "sg:address":"466 Lowell St",
    "sg:city":"Methuen",
    "sg:classifiers":[
        {
            "category":"Utilities",
            "subcategory":"Mobile Phone",
            "type":"Services"
        },
        {
            "category":"Shopping",
            "subcategory":"Mobile Phones",
            "type":"Retail Goods"
        },
        {
            "category":"Utilities",
            "subcategory":"Telephone",
            "type":"Services"
        },
        {
            "category":"Communications",
            "type":"Services"
        }
    ],
    "sg:phone":"+1 978 685 1505",
    "sg:postcode":"01844",
    "sg:province":"MA",
    "sg:tags":[
        "wireless",
        "equipment",
        "supplies-rental",
        "cellular",
        "supply"
    ],
    "wof:name":"Sprint Nextel Repair Center",
    "wof:placetype":"venue"
},
  "geometry": {"coordinates":[-71.215581,42.703307],"type":"Point"}
}