{
  "type": "Feature",
  "properties": {
    "addr:full":"169 Clay Pond Rd Bourne MA 02532",
    "addr:housenumber":"169",
    "addr:postcode":"02532",
    "addr:street":"Clay Pond Rd",
    "iso:country":"US",
    "sg:address":"169 Clay Pond Rd",
    "sg:city":"Bourne",
    "sg:classifiers":[
        {
            "category":"Retail",
            "subcategory":"Repair Shop",
            "type":"Services"
        }
    ],
    "sg:phone":"+1 508 759 1177",
    "sg:postcode":"02532",
    "sg:province":"MA",
    "sg:tags":[
        "glass",
        "fiber"
    ],
    "wof:name":"Offshore Systems",
    "wof:placetype":"venue"
},
  "geometry": {"coordinates":[-70.58890700000001,41.717187],"type":"Point"}
}