{
  "type": "Feature",
  "properties": {
    "iso:country":"US",
    "sg:address":"47 East St",
    "sg:city":"Northampton",
    "sg:classifiers":[
        {
            "category":"Education",
            "subcategory":"School",
            "type":"Public Place"
        }
    ],
    "sg:phone":"+1 413 586 3888",
    "sg:postcode":"01060",
    "sg:province":"MA",
    "wof:name":"East Street Ballet",
    "wof:placetype":"venue"
},
  "geometry": {"coordinates":[-72.63359,42.30994],"type":"Point"}
}