{
  "type": "Feature",
  "properties": {
    "addr:full":"355 Broadway Everett MA 02149",
    "addr:housenumber":"355",
    "addr:postcode":"02149",
    "addr:street":"Broadway",
    "iso:country":"US",
    "sg:address":"355 Broadway",
    "sg:city":"Everett",
    "sg:classifiers":[
        {
            "category":"Place Of Worship",
            "subcategory":"Church",
            "type":"Public Place"
        },
        {
            "category":"Place Of Worship",
            "type":"Public Place"
        },
        {
            "category":"Organizations",
            "subcategory":"Religious Organization",
            "type":"Services"
        }
    ],
    "sg:phone":"+1 617 389 2538",
    "sg:postcode":"02149",
    "sg:province":"MA",
    "sg:tags":[
        "god",
        "god-independent",
        "churches-assemblies"
    ],
    "wof:name":"New Life Assembly Of",
    "wof:placetype":"venue"
},
  "geometry": {"coordinates":[-71.05785,42.404512],"type":"Point"}
}