{
  "type": "Feature",
  "properties": {
    "iso:country":"US",
    "sg:address":"14 Hamilton st",
    "sg:city":"Southbridge",
    "sg:classifiers":[
        {
            "category":"Personal",
            "subcategory":"Barber",
            "type":"Services"
        }
    ],
    "sg:phone":"+1 508 764 4774",
    "sg:postcode":"01550",
    "sg:province":"MA",
    "wof:name":"Colin's barbershop",
    "wof:placetype":"venue"
},
  "geometry": {"coordinates":[-72.034685,42.076287],"type":"Point"}
}