{
  "type": "Feature",
  "properties": {
    "addr:full": "479 Ferry St Malden MA 02148",
    "addr:housenumber": "479",
    "addr:postcode": "02148",
    "addr:street": "Ferry St",
    "iso:country": "US",
    "sg:address": "479 Ferry St",
    "sg:city": "Malden",
    "sg:classifiers": [
      {
        "category": "Shopping",
        "subcategory": "Clothing, Apparel, \u0026 Fashions",
        "type": "Retail Goods"
      }
    ],
    "sg:phone": "+1 781 322 7059",
    "sg:postcode": "02148",
    "sg:province": "MA",
    "wof:name": "City Stars Clothing",
    "wof:placetype": "venue"
  },
  "geometry": {"coordinates":[-71.054878,42.420104],"type":"Point"}
}
