{
  "type": "Feature",
  "properties": {
    "iso:country":"US",
    "sg:address":"72 Tolman St",
    "sg:city":"West Newton",
    "sg:classifiers":[
        {
            "category":"Professional",
            "subcategory":"Computer Services",
            "type":"Services"
        }
    ],
    "sg:phone":"+1 617 332 8522",
    "sg:postcode":"02465",
    "sg:province":"MA",
    "wof:name":"One 8 Solutions",
    "wof:placetype":"venue"
},
  "geometry": {"coordinates":[-71.234638,42.361412],"type":"Point"}
}