{
  "type": "Feature",
  "properties": {
    "addr:full":"282 Main St Wellfleet MA 02667",
    "addr:housenumber":"282",
    "addr:postcode":"02667",
    "addr:street":"Main St",
    "iso:country":"US",
    "sg:address":"282 Main St",
    "sg:city":"Wellfleet",
    "sg:classifiers":[
        {
            "category":"Real Estate",
            "subcategory":"Real Estate Agent",
            "type":"Services"
        }
    ],
    "sg:phone":"+1 508 349 1000",
    "sg:postcode":"02667",
    "sg:province":"MA",
    "sg:website":"www.capeshores.com",
    "wof:name":"Cape Shores Real Estate",
    "wof:placetype":"venue"
},
  "geometry": {"coordinates":[-70.030468,41.938228],"type":"Point"}
}