{
  "type": "Feature",
  "properties": {
    "addr:full": "224 Quincy Ave Braintree MA 02184",
    "addr:housenumber": "224",
    "addr:postcode": "02184",
    "addr:street": "Quincy Ave",
    "iso:country": "US",
    "sg:address": "224 Quincy Ave",
    "sg:city": "Braintree",
    "sg:classifiers": [
      {
        "category": "Personal",
        "type": "Services"
      },
      {
        "category": "Sports \u0026 Exercise",
        "subcategory": "Gym",
        "type": "Entertainment"
      },
      {
        "category": "Health Services",
        "subcategory": "Health Practitioner",
        "type": "Services"
      },
      {
        "category": "Arena",
        "subcategory": "Sports Club",
        "type": "Entertainment"
      }
    ],
    "sg:phone": "+1 781 535 6456",
    "sg:postcode": "02184",
    "sg:province": "MA",
    "sg:tags": [
      "control",
      "weight",
      "consultant",
      "program",
      "fitness",
      "physical"
    ],
    "sg:website": "http://www.curves.com",
    "wof:name": "Curves",
    "wof:placetype": "venue"
  },
  "geometry": {"coordinates":[-70.970915,42.229185],"type":"Point"}
}
