{
  "type": "Feature",
  "properties": {
    "addr:full":"80 Worcester St North Grafton MA 01536",
    "addr:housenumber":"80",
    "addr:postcode":"01536",
    "addr:street":"Worcester St",
    "iso:country":"US",
    "sg:address":"80 Worcester St",
    "sg:city":"North Grafton",
    "sg:classifiers":[
        {
            "category":"Professional",
            "subcategory":"Advertising",
            "type":"Services"
        },
        {
            "category":"Manufacturing",
            "subcategory":"Printing",
            "type":"Manufacturing & Wholesale Goods"
        }
    ],
    "sg:phone":"+1 508 839 1839",
    "sg:postcode":"01536",
    "sg:province":"MA",
    "sg:tags":[
        "printer",
        "specialty"
    ],
    "wof:name":"Image Boosters",
    "wof:placetype":"venue"
},
  "geometry": {"coordinates":[-71.69366599999999,42.21631],"type":"Point"}
}