{
  "type": "Feature",
  "properties": {
    "addr:full": "175 Cabot Street Suite 210 Lowell MA 01854",
    "addr:housenumber": "175",
    "addr:postcode": "01854",
    "addr:street": "Cabot Street Suite 210",
    "iso:country": "US",
    "sg:address": "175 Cabot Street Suite 210",
    "sg:city": "Lowell",
    "sg:classifiers": [
      {
        "category": "Professional",
        "subcategory": "Computer Services",
        "type": "Services"
      }
    ],
    "sg:phone": "+1 877 523 4368",
    "sg:postcode": "01854",
    "sg:province": "MA",
    "sg:website": "http://www.kadient.com/",
    "wof:name": "Kadient",
    "wof:placetype": "venue"
  },
  "geometry": {"coordinates":[-71.317133,42.650175],"type":"Point"}
}
