{
  "type": "Feature",
  "properties": {
    "iso:country":"US",
    "sg:address":"23 Pleasant St",
    "sg:city":"Plymouth",
    "sg:classifiers":[
        {
            "category":"Travel",
            "subcategory":"Hotels & Motels",
            "type":"Entertainment"
        }
    ],
    "sg:phone":"+1 508 746 7412",
    "sg:postcode":"02360",
    "sg:province":"MA",
    "sg:tags":[
        "breakfast",
        "accommodation",
        "bed"
    ],
    "wof:name":"In-Town Bed & Breakfast",
    "wof:placetype":"venue"
},
  "geometry": {"coordinates":[-70.662361,41.953511],"type":"Point"}
}