{
  "type": "Feature",
  "properties": {
    "addr:full": "23 Pleasant St Plymouth MA 02360",
    "addr:housenumber": "23",
    "addr:postcode": "02360",
    "addr:street": "Pleasant St",
    "iso:country": "US",
    "sg:address": "23 Pleasant St",
    "sg:city": "Plymouth",
    "sg:classifiers": [
      {
        "category": "Travel",
        "subcategory": "Hotels \u0026 Motels",
        "type": "Entertainment"
      }
    ],
    "sg:phone": "+1 508 746 7412",
    "sg:postcode": "02360",
    "sg:province": "MA",
    "sg:tags": [
      "breakfast",
      "accommodation",
      "bed"
    ],
    "wof:name": "In-Town Bed \u0026 Breakfast",
    "wof:placetype": "venue"
  },
  "geometry": {"coordinates":[-70.662361,41.953511],"type":"Point"}
}
