{
  "type": "Feature",
  "properties": {
    "addr:full":"242 East St Wrentham MA 02093",
    "addr:housenumber":"242",
    "addr:postcode":"02093",
    "addr:street":"East St",
    "iso:country":"US",
    "sg:address":"242 East St",
    "sg:city":"Wrentham",
    "sg:classifiers":[
        {
            "category":"Shopping",
            "subcategory":"Used Merchandise",
            "type":"Retail Goods"
        }
    ],
    "sg:phone":"+1 508 384 4441",
    "sg:postcode":"02093",
    "sg:province":"MA",
    "sg:tags":[
        "antique"
    ],
    "wof:name":"East Street Antiques",
    "wof:placetype":"venue"
},
  "geometry": {"coordinates":[-71.315009,42.065012],"type":"Point"}
}