{
  "type": "Feature",
  "properties": {
    "addr:full": "195 E Main St Milford MA 01757",
    "addr:housenumber": "195",
    "addr:postcode": "01757",
    "addr:street": "E Main St",
    "iso:country": "US",
    "sg:address": "195 E Main St",
    "sg:city": "Milford",
    "sg:classifiers": [
      {
        "category": "Shopping",
        "subcategory": "Computers \u0026 Home Electronics",
        "type": "Retail Goods"
      }
    ],
    "sg:phone": "+1 508 473 4500",
    "sg:postcode": "01757",
    "sg:province": "MA",
    "sg:tags": [
      "software"
    ],
    "sg:website": "www.ejustifyit.com",
    "wof:name": "EJUSTIFYIT.COM",
    "wof:placetype": "venue"
  },
  "geometry": {"coordinates":[-71.499958,42.15076],"type":"Point"}
}
