{
  "type": "Feature",
  "properties": {
    "iso:country":"US",
    "sg:address":"2 Grove Ter",
    "sg:city":"West Roxbury",
    "sg:classifiers":[
        {
            "category":"Building & Trades",
            "subcategory":"Landscaping Services",
            "type":"Services"
        }
    ],
    "sg:phone":"+1 617 325 7756",
    "sg:postcode":"02132",
    "sg:province":"MA",
    "sg:tags":[
        "tree"
    ],
    "wof:name":"Specialized Rigging & Tree Car",
    "wof:placetype":"venue"
},
  "geometry": {"coordinates":[-71.16122300000001,42.266729],"type":"Point"}
}