{
  "type": "Feature",
  "properties": {
    "addr:full": "2 Grove Ter West Roxbury MA 02132",
    "addr:housenumber": "2",
    "addr:postcode": "02132",
    "addr:street": "Grove Ter",
    "iso:country": "US",
    "sg:address": "2 Grove Ter",
    "sg:city": "West Roxbury",
    "sg:classifiers": [
      {
        "category": "Building \u0026 Trades",
        "subcategory": "Landscaping Services",
        "type": "Services"
      }
    ],
    "sg:phone": "+1 617 325 7756",
    "sg:postcode": "02132",
    "sg:province": "MA",
    "sg:tags": [
      "tree"
    ],
    "wof:name": "Specialized Rigging \u0026 Tree Car",
    "wof:placetype": "venue"
  },
  "geometry": {"coordinates":[-71.161223,42.266729],"type":"Point"}
}
