{
  "type": "Feature",
  "properties": {
    "iso:country":"US",
    "sg:address":"105 High Rock St",
    "sg:city":"Lynn",
    "sg:classifiers":[
        {
            "category":"Organizations",
            "subcategory":"Religious Organization",
            "type":"Services"
        }
    ],
    "sg:phone":"+1   ",
    "sg:postcode":"01902",
    "sg:province":"MA",
    "wof:name":"Lynn Cambodian Baptist Church",
    "wof:placetype":"venue"
},
  "geometry": {"coordinates":[-70.949883,42.468919],"type":"Point"}
}