{
  "type": "Feature",
  "properties": {
    "iso:country":"US",
    "sg:address":"130 Front St",
    "sg:city":"Scituate",
    "sg:classifiers":[
        {
            "category":"Personal",
            "subcategory":"Beauty Salon",
            "type":"Services"
        }
    ],
    "sg:phone":"+1 781 545 2822",
    "sg:postcode":"02066",
    "sg:province":"MA",
    "wof:name":"Salon Botticelli",
    "wof:placetype":"venue"
},
  "geometry": {"coordinates":[-70.724941,42.195535],"type":"Point"}
}