{
  "type": "Feature",
  "properties": {
    "iso:country":"US",
    "sg:address":"1203 Parker St",
    "sg:city":"Springfield",
    "sg:classifiers":[
        {
            "category":"Restaurant",
            "type":"Food & Drink"
        }
    ],
    "sg:phone":"+1 413 783 8300",
    "sg:postcode":"01129",
    "sg:province":"MA",
    "wof:name":"Ginger Blossom",
    "wof:placetype":"venue"
},
  "geometry": {"coordinates":[-72.498802,42.117968],"type":"Point"}
}