{
  "type": "Feature",
  "properties": {
    "addr:full": "1203 Parker St Springfield MA 01129",
    "addr:housenumber": "1203",
    "addr:postcode": "01129",
    "addr:street": "Parker St",
    "iso:country": "US",
    "sg:address": "1203 Parker St",
    "sg:city": "Springfield",
    "sg:classifiers": [
      {
        "category": "Restaurant",
        "type": "Food \u0026 Drink"
      }
    ],
    "sg:phone": "+1 413 783 8300",
    "sg:postcode": "01129",
    "sg:province": "MA",
    "wof:name": "Ginger Blossom",
    "wof:placetype": "venue"
  },
  "geometry": {"coordinates":[-72.498802,42.117968],"type":"Point"}
}
