{
  "type": "Feature",
  "properties": {
    "addr:full":"170 Great Rd Bedford MA 01730",
    "addr:housenumber":"170",
    "addr:postcode":"01730",
    "addr:street":"Great Rd",
    "iso:country":"US",
    "sg:address":"170 Great Rd",
    "sg:city":"Bedford",
    "sg:classifiers":[
        {
            "category":"Building & Trades",
            "subcategory":"Locksmith",
            "type":"Services"
        }
    ],
    "sg:phone":"+1 617 517 9034",
    "sg:postcode":"01730",
    "sg:province":"MA",
    "sg:tags":[
        "key"
    ],
    "wof:name":"Emergency A Locksmith",
    "wof:placetype":"venue"
},
  "geometry": {"coordinates":[-71.274693,42.490218],"type":"Point"}
}