{
  "type": "Feature",
  "properties": {
    "addr:full": "73 W State St Granby MA 01033",
    "addr:housenumber": "73",
    "addr:postcode": "01033",
    "addr:street": "W State St",
    "iso:country": "US",
    "sg:address": "73 W State St",
    "sg:city": "Granby",
    "sg:classifiers": [
      {
        "category": "Restaurant",
        "type": "Food \u0026 Drink"
      }
    ],
    "sg:phone": "+1   ",
    "sg:postcode": "01033",
    "sg:province": "MA",
    "sg:tags": [
      "eating"
    ],
    "wof:name": "Subway",
    "wof:placetype": "venue"
  },
  "geometry": {"coordinates":[-72.548391,42.243665],"type":"Point"}
}
