{
  "type": "Feature",
  "properties": {
    "iso:country":"US",
    "sg:address":"242 Chauncy St",
    "sg:city":"Mansfield",
    "sg:classifiers":[
        {
            "category":"Cinema",
            "subcategory":"Movie Rental",
            "type":"Entertainment"
        }
    ],
    "sg:phone":"+1 508 337 9422",
    "sg:postcode":"02048",
    "sg:province":"MA",
    "sg:tags":[
        "leasing",
        "video",
        "disc",
        "tape"
    ],
    "wof:name":"Blockbuster Video",
    "wof:placetype":"venue"
},
  "geometry": {"coordinates":[-71.229241,42.030471],"type":"Point"}
}