{
  "type": "Feature",
  "properties": {
    "addr:full":"265 Howard St Melrose MA 02176",
    "addr:housenumber":"265",
    "addr:postcode":"02176",
    "addr:street":"Howard St",
    "iso:country":"US",
    "sg:address":"265 Howard St",
    "sg:city":"Melrose",
    "sg:classifiers":[
        {
            "category":"Retail",
            "subcategory":"Auto Repair",
            "type":"Services"
        }
    ],
    "sg:phone":"+1 781 665 2368",
    "sg:postcode":"02176",
    "sg:province":"MA",
    "sg:tags":[
        "body",
        "automobile",
        "painting",
        "repairing"
    ],
    "wof:name":"Bobs Auto Body",
    "wof:placetype":"venue"
},
  "geometry": {"coordinates":[-71.048466,42.469328],"type":"Point"}
}