{
  "type": "Feature",
  "properties": {
    "addr:full":"750 Washington St Boston MA 02111",
    "addr:housenumber":"750",
    "addr:postcode":"02111",
    "addr:street":"Washington St",
    "iso:country":"US",
    "sg:address":"750 Washington St",
    "sg:city":"Boston",
    "sg:classifiers":[
        {
            "category":"Health Services",
            "subcategory":"Doctor",
            "type":"Services"
        }
    ],
    "sg:phone":"+1 617 636 7947",
    "sg:postcode":"02111",
    "sg:province":"MA",
    "wof:name":"Hinds Phillips W MD",
    "wof:placetype":"venue"
},
  "geometry": {"coordinates":[-71.06339800000001,42.350017],"type":"Point"}
}