{
  "type": "Feature",
  "properties": {
    "iso:country":"US",
    "sg:address":"5 Cornell Rd",
    "sg:city":"Marblehead",
    "sg:classifiers":[
        {
            "category":"Professional",
            "subcategory":"Management & Consulting",
            "type":"Services"
        },
        {
            "category":"Wholesale",
            "subcategory":"Chemicals & Plastics",
            "type":"Manufacturing & Wholesale Goods"
        }
    ],
    "sg:phone":"+1 781 631 3464",
    "sg:postcode":"01945",
    "sg:province":"MA",
    "sg:tags":[
        "home",
        "demonstration"
    ],
    "wof:name":"Amway Home Products Distrs",
    "wof:placetype":"venue"
},
  "geometry": {"coordinates":[-70.874819,42.496877],"type":"Point"}
}