{
  "type": "Feature",
  "properties": {
    "iso:country":"US",
    "sg:address":"329 N Washington St",
    "sg:city":"North Attleboro",
    "sg:classifiers":[
        {
            "category":"Restaurant",
            "type":"Food & Drink"
        }
    ],
    "sg:phone":"+1   ",
    "sg:postcode":"02760",
    "sg:province":"MA",
    "sg:tags":[
        "eating"
    ],
    "wof:name":"Aldos Restaurant",
    "wof:placetype":"venue"
},
  "geometry": {"coordinates":[-71.32976600000001,41.992116],"type":"Point"}
}