{
  "type": "Feature",
  "properties": {
    "iso:country":"US",
    "sg:address":"109 Creeper Hill Rd",
    "sg:city":"North Grafton",
    "sg:classifiers":[
        {
            "category":"Building & Trades",
            "subcategory":"Cleaning & Sanitation",
            "type":"Services"
        }
    ],
    "sg:phone":"+1 508 839 8882",
    "sg:postcode":"01536",
    "sg:province":"MA",
    "wof:name":"Minerva Enterprises Inc",
    "wof:placetype":"venue"
},
  "geometry": {"coordinates":[-71.72732499999999,42.236227],"type":"Point"}
}