{
  "type": "Feature",
  "properties": {
    "iso:country":"US",
    "sg:address":"2493 Main St",
    "sg:city":"Tewksbury",
    "sg:classifiers":[
        {
            "category":"Restaurant",
            "type":"Food & Drink"
        }
    ],
    "sg:phone":"+1 978 658 0870",
    "sg:postcode":"01876",
    "sg:province":"MA",
    "sg:tags":[
        "breakfast",
        "brunch"
    ],
    "wof:name":"Route 38 Cafe",
    "wof:placetype":"venue"
},
  "geometry": {"coordinates":[-71.192188,42.574045],"type":"Point"}
}