{
  "type": "Feature",
  "properties": {
    "iso:country":"US",
    "sg:address":"36 King St",
    "sg:city":"Northampton",
    "sg:classifiers":[
        {
            "category":"Travel",
            "subcategory":"Hotels & Motels",
            "type":"Entertainment"
        }
    ],
    "sg:phone":"+1 413 584 3100",
    "sg:postcode":"01060",
    "sg:province":"MA",
    "sg:website":"www.hotelnorthhampton.com",
    "wof:name":"Hotel Northampton",
    "wof:placetype":"venue"
},
  "geometry": {"coordinates":[-72.630807,42.320433],"type":"Point"}
}