{
  "type": "Feature",
  "properties": {
    "addr:full": "36 King St Northampton MA 01060",
    "addr:housenumber": "36",
    "addr:postcode": "01060",
    "addr:street": "King St",
    "iso:country": "US",
    "ovtr:label": "Hotel Northampton, 36 King St Northampton MA US",
    "ovtr:similarity": 2.930393934249878,
    "sg:address": "36 King St",
    "sg:city": "Northampton",
    "sg:classifiers": [
      {
        "category": "Travel",
        "subcategory": "Hotels \u0026 Motels",
        "type": "Entertainment"
      }
    ],
    "sg:phone": "+1 413 584 3100",
    "sg:postcode": "01060",
    "sg:province": "MA",
    "sg:website": "www.hotelnorthhampton.com",
    "wof:name": "Hotel Northampton",
    "wof:placetype": "venue"
  },
  "geometry": {"coordinates":[-72.630807,42.320433],"type":"Point"}
}
