{
  "type": "Feature",
  "properties": {
    "iso:country":"US",
    "sg:address":"25 Dorchester Ave",
    "sg:city":"Boston",
    "sg:classifiers":[
        {
            "category":"Personal",
            "type":"Services"
        }
    ],
    "sg:phone":"+1 617 515 9886",
    "sg:postcode":"02205",
    "sg:province":"MA",
    "sg:tags":[
        "mover"
    ],
    "wof:name":"Piece by Piece Movers",
    "wof:placetype":"venue"
},
  "geometry": {"coordinates":[-71.053646,42.350221],"type":"Point"}
}