{
  "type": "Feature",
  "properties": {
    "addr:full":"415 Porter Lake Dr Longmeadow MA 01106",
    "addr:housenumber":"415",
    "addr:postcode":"01106",
    "addr:street":"Porter Lake Dr",
    "iso:country":"US",
    "sg:address":"415 Porter Lake Dr",
    "sg:city":"Longmeadow",
    "sg:classifiers":[
        {
            "category":"Real Estate",
            "subcategory":"Real Estate Agent",
            "type":"Services"
        }
    ],
    "sg:phone":"+1 413 886 0007",
    "sg:postcode":"01106",
    "sg:province":"MA",
    "wof:name":"J C Realty Consultant Inc",
    "wof:placetype":"venue"
},
  "geometry": {"coordinates":[-72.55553999999999,42.071029],"type":"Point"}
}