{
  "type": "Feature",
  "properties": {
    "addr:full": "500 Main St Great Barrington MA 01230",
    "addr:housenumber": "500",
    "addr:postcode": "01230",
    "addr:street": "Main St",
    "iso:country": "US",
    "sg:address": "500 Main St",
    "sg:city": "Great Barrington",
    "sg:classifiers": [
      {
        "category": "Social Services",
        "subcategory": "Child Care",
        "type": "Services"
      }
    ],
    "sg:phone": "+1 413 528 5660",
    "sg:postcode": "01230",
    "sg:province": "MA",
    "sg:tags": [
      "school",
      "program",
      "after"
    ],
    "wof:name": "Kids' Place",
    "wof:placetype": "venue"
  },
  "geometry": {"coordinates":[-73.364454,42.18774],"type":"Point"}
}
