{
  "type": "Feature",
  "properties": {
    "iso:country":"US",
    "sg:address":"500 Main St",
    "sg:city":"Great Barrington",
    "sg:classifiers":[
        {
            "category":"Social Services",
            "subcategory":"Child Care",
            "type":"Services"
        }
    ],
    "sg:phone":"+1 413 528 5660",
    "sg:postcode":"01230",
    "sg:province":"MA",
    "sg:tags":[
        "school",
        "program",
        "after"
    ],
    "wof:name":"Kids' Place",
    "wof:placetype":"venue"
},
  "geometry": {"coordinates":[-73.36445399999999,42.18774],"type":"Point"}
}