{
  "type": "Feature",
  "properties": {
    "addr:full":"59 Stadium Way Allston MA 02134",
    "addr:housenumber":"59",
    "addr:postcode":"02134",
    "addr:street":"Stadium Way",
    "iso:country":"US",
    "sg:address":"59 Stadium Way",
    "sg:city":"Allston",
    "sg:classifiers":[
        {
            "category":"Organizations",
            "subcategory":"Religious Organization",
            "type":"Services"
        }
    ],
    "sg:phone":"+1   ",
    "sg:postcode":"02134",
    "sg:province":"MA",
    "wof:name":"Jesus S Berrio",
    "wof:placetype":"venue"
},
  "geometry": {"coordinates":[-71.12712999999999,42.363659],"type":"Point"}
}