{
  "type": "Feature",
  "properties": {
    "addr:full": "57 Reservoir St Northborough MA 01532",
    "addr:housenumber": "57",
    "addr:postcode": "01532",
    "addr:street": "Reservoir St",
    "iso:country": "US",
    "sg:address": "57 Reservoir St",
    "sg:city": "Northborough",
    "sg:classifiers": [
      {
        "category": "Building \u0026 Trades",
        "subcategory": "Construction",
        "type": "Services"
      }
    ],
    "sg:phone": "+1   ",
    "sg:postcode": "01532",
    "sg:province": "MA",
    "sg:tags": [
      "contractor"
    ],
    "wof:name": "Xrs",
    "wof:placetype": "venue"
  },
  "geometry": {"coordinates":[-71.684611,42.330326],"type":"Point"}
}
