{
  "type": "Feature",
  "properties": {
    "addr:full":"7 Fielding St Wakefield MA 01880",
    "addr:housenumber":"7",
    "addr:postcode":"01880",
    "addr:street":"Fielding St",
    "iso:country":"US",
    "sg:address":"7 Fielding St",
    "sg:city":"Wakefield",
    "sg:classifiers":[
        {
            "category":"Real Estate",
            "subcategory":"Real Estate Agent",
            "type":"Services"
        }
    ],
    "sg:phone":"+1   ",
    "sg:postcode":"01880",
    "sg:province":"MA",
    "wof:name":"Maxwell Realty Trust",
    "wof:placetype":"venue"
},
  "geometry": {"coordinates":[-71.08327800000001,42.514038],"type":"Point"}
}