{
  "type": "Feature",
  "properties": {
    "addr:full":"45 Newbury Street Suite 512 Boston MA 02116",
    "addr:housenumber":"45",
    "addr:postcode":"02116",
    "addr:street":"Newbury Street Suite 512",
    "iso:country":"US",
    "sg:address":"45 Newbury Street Suite 512",
    "sg:city":"Boston",
    "sg:classifiers":[
        {
            "category":"Sports & Exercise",
            "subcategory":"Gym",
            "type":"Entertainment"
        }
    ],
    "sg:phone":"+1 617 262 8787",
    "sg:postcode":"02116",
    "sg:province":"MA",
    "sg:tags":[
        "trainer"
    ],
    "wof:name":"Salubrious Touch",
    "wof:placetype":"venue"
},
  "geometry": {"coordinates":[-71.07762099999999,42.348863],"type":"Point"}
}