{
  "type": "Feature",
  "properties": {
    "iso:country":"US",
    "sg:address":"68 Winthrop St",
    "sg:city":"Taunton",
    "sg:classifiers":[
        {
            "category":"Professional",
            "subcategory":"Computer Services",
            "type":"Services"
        }
    ],
    "sg:phone":"+1 508 828 2667",
    "sg:postcode":"02780",
    "sg:province":"MA",
    "sg:tags":[
        "internet"
    ],
    "wof:name":"Computer Forensics-Ma",
    "wof:placetype":"venue"
},
  "geometry": {"coordinates":[-71.0973,41.897532],"type":"Point"}
}