{
  "type": "Feature",
  "properties": {
    "addr:full":"71 Country Club Way Ipswich MA 01938",
    "addr:housenumber":"71",
    "addr:postcode":"01938",
    "addr:street":"Country Club Way",
    "iso:country":"US",
    "sg:address":"71 Country Club Way",
    "sg:city":"Ipswich",
    "sg:classifiers":[
        {
            "category":"Professional",
            "subcategory":"Management & Consulting",
            "type":"Services"
        }
    ],
    "sg:phone":"+1 978 356 7144",
    "sg:postcode":"01938",
    "sg:province":"MA",
    "sg:tags":[
        "marketing",
        "program",
        "business"
    ],
    "sg:website":"www.meetwithsuccess.com",
    "wof:name":"Meet With Success Inc",
    "wof:placetype":"venue"
},
  "geometry": {"coordinates":[-70.906744,42.694676],"type":"Point"}
}