{
  "type": "Feature",
  "properties": {
    "addr:full": "629 Tremont St Roxbury MA 02118",
    "addr:housenumber": "629",
    "addr:postcode": "02118",
    "addr:street": "Tremont St",
    "iso:country": "US",
    "sg:address": "629 Tremont St",
    "sg:city": "Roxbury",
    "sg:classifiers": [
      {
        "category": "Food \u0026 Beverages",
        "subcategory": "Groceries \u0026 Convenience Stores",
        "type": "Retail Goods"
      }
    ],
    "sg:phone": "+1 617 421 9889",
    "sg:postcode": "02118",
    "sg:province": "MA",
    "sg:tags": [
      "grocer"
    ],
    "wof:name": "Casa Cuong",
    "wof:placetype": "venue"
  },
  "geometry": {"coordinates":[-71.074618,42.342389],"type":"Point"}
}
