{
  "type": "Feature",
  "properties": {
    "iso:country":"US",
    "sg:address":"629 Tremont St",
    "sg:city":"Roxbury",
    "sg:classifiers":[
        {
            "category":"Food & Beverages",
            "subcategory":"Groceries & Convenience Stores",
            "type":"Retail Goods"
        }
    ],
    "sg:phone":"+1 617 421 9889",
    "sg:postcode":"02118",
    "sg:province":"MA",
    "sg:tags":[
        "grocer"
    ],
    "wof:name":"Casa Cuong",
    "wof:placetype":"venue"
},
  "geometry": {"coordinates":[-71.074618,42.342389],"type":"Point"}
}