{
  "type": "Feature",
  "properties": {
    "iso:country":"US",
    "sg:address":"10 Bassett St",
    "sg:city":"Milton",
    "sg:classifiers":[
        {
            "category":"Shopping",
            "subcategory":"Crafts & Fabrics",
            "type":"Retail Goods"
        }
    ],
    "sg:phone":"+1 617 698 1190",
    "sg:postcode":"02186",
    "sg:province":"MA",
    "sg:tags":[
        "shop",
        "yarn"
    ],
    "sg:website":"http://www.snowgooseyarn.com",
    "wof:name":"Snow Goose Yarn",
    "wof:placetype":"venue"
},
  "geometry": {"coordinates":[-71.041557,42.259239],"type":"Point"}
}