{
  "type": "Feature",
  "properties": {
    "iso:country":"US",
    "sg:address":"13 Providence Rd",
    "sg:city":"Sutton",
    "sg:classifiers":[
        {
            "category":"Organizations",
            "subcategory":"Non-profit Organization",
            "type":"Services"
        }
    ],
    "sg:phone":"+1 508 865 5920",
    "sg:postcode":"01590",
    "sg:province":"MA",
    "wof:name":"Beginning Years Family Network",
    "wof:placetype":"venue"
},
  "geometry": {"coordinates":[-71.72089200000001,42.174977],"type":"Point"}
}