{
  "type": "Feature",
  "properties": {
    "addr:full": "900 Commonwealth Ave Boston MA 02215",
    "addr:housenumber": "900",
    "addr:postcode": "02215",
    "addr:street": "Commonwealth Ave",
    "iso:country": "US",
    "sg:address": "900 Commonwealth Ave",
    "sg:city": "Boston",
    "sg:classifiers": [
      {
        "category": "Organizations",
        "subcategory": "Non-profit Organization",
        "type": "Services"
      }
    ],
    "sg:phone": "+1 617 632 2000",
    "sg:postcode": "02215",
    "sg:province": "MA",
    "sg:website": "www.ecog.org",
    "wof:name": "Frontier Science \u0026 Technology",
    "wof:placetype": "venue"
  },
  "geometry": {"coordinates":[-71.115808,42.351017],"type":"Point"}
}
