{
  "type": "Feature",
  "properties": {
    "iso:country":"US",
    "sg:address":"900 Commonwealth Ave",
    "sg:city":"Boston",
    "sg:classifiers":[
        {
            "category":"Organizations",
            "subcategory":"Non-profit Organization",
            "type":"Services"
        }
    ],
    "sg:phone":"+1 617 632 2000",
    "sg:postcode":"02215",
    "sg:province":"MA",
    "sg:website":"www.ecog.org",
    "wof:name":"Frontier Science & Technology",
    "wof:placetype":"venue"
},
  "geometry": {"coordinates":[-71.115808,42.351017],"type":"Point"}
}