{
  "type": "Feature",
  "properties": {
    "addr:full":"69 Parsons St Easthampton MA 01027",
    "addr:housenumber":"69",
    "addr:postcode":"01027",
    "addr:street":"Parsons St",
    "iso:country":"US",
    "sg:address":"69 Parsons St",
    "sg:city":"Easthampton",
    "sg:classifiers":[
        {
            "category":"Retail",
            "subcategory":"Funeral Services",
            "type":"Services"
        }
    ],
    "sg:phone":"+1 413 527 2820",
    "sg:postcode":"01027",
    "sg:province":"MA",
    "sg:tags":[
        "director"
    ],
    "wof:name":"Czelusniak Funeral Home",
    "wof:placetype":"venue"
},
  "geometry": {"coordinates":[-72.651217,42.271828],"type":"Point"}
}