{
  "type": "Feature",
  "properties": {
    "iso:country":"US",
    "sg:address":"23 Centennial Dr",
    "sg:city":"Peabody",
    "sg:classifiers":[
        {
            "category":"Shopping",
            "subcategory":"Pharmacy",
            "type":"Retail Goods"
        }
    ],
    "sg:phone":"+1 978 532 3732",
    "sg:postcode":"01960",
    "sg:province":"MA",
    "wof:name":"Eaton Apothecary",
    "wof:placetype":"venue"
},
  "geometry": {"coordinates":[-70.968278,42.522239],"type":"Point"}
}