{
  "type": "Feature",
  "properties": {
    "iso:country":"US",
    "sg:address":"1029 Blue Hill Ave",
    "sg:city":"Dorchester Center",
    "sg:classifiers":[
        {
            "category":"Education",
            "subcategory":"Dance Studio",
            "type":"Public Place"
        }
    ],
    "sg:phone":"+1 617 282 4561",
    "sg:postcode":"02124",
    "sg:province":"MA",
    "sg:tags":[
        "art",
        "performing",
        "instruction",
        "dancing"
    ],
    "wof:name":"Roxbury Center For the Performing Arts",
    "wof:placetype":"venue"
},
  "geometry": {"coordinates":[-71.089699,42.2892],"type":"Point"}
}