{
  "type": "Feature",
  "properties": {
    "iso:country":"US",
    "sg:address":"27 Melrose St",
    "sg:city":"Adams",
    "sg:classifiers":[
        {
            "category":"Manufacturing",
            "subcategory":"Buildings",
            "type":"Manufacturing & Wholesale Goods"
        },
        {
            "category":"Building & Trades",
            "subcategory":"Construction",
            "type":"Services"
        }
    ],
    "sg:phone":"+1 413 664 4306",
    "sg:postcode":"01220",
    "sg:province":"MA",
    "sg:tags":[
        "roofing",
        "industrial",
        "system",
        "builder",
        "specialty",
        "heating",
        "contractors-commercial",
        "home",
        "contractor",
        "air conditioning"
    ],
    "wof:name":"C & R Contracting",
    "wof:placetype":"venue"
},
  "geometry": {"coordinates":[-73.12261700000001,42.623581],"type":"Point"}
}