{
  "type": "Feature",
  "properties": {
    "addr:full": "27 Melrose St Adams MA 01220",
    "addr:housenumber": "27",
    "addr:postcode": "01220",
    "addr:street": "Melrose St",
    "iso:country": "US",
    "sg:address": "27 Melrose St",
    "sg:city": "Adams",
    "sg:classifiers": [
      {
        "category": "Manufacturing",
        "subcategory": "Buildings",
        "type": "Manufacturing \u0026 Wholesale Goods"
      },
      {
        "category": "Building \u0026 Trades",
        "subcategory": "Construction",
        "type": "Services"
      }
    ],
    "sg:phone": "+1 413 664 4306",
    "sg:postcode": "01220",
    "sg:province": "MA",
    "sg:tags": [
      "roofing",
      "industrial",
      "system",
      "builder",
      "specialty",
      "heating",
      "contractors-commercial",
      "home",
      "contractor",
      "air conditioning"
    ],
    "wof:name": "C \u0026 R Contracting",
    "wof:placetype": "venue"
  },
  "geometry": {"coordinates":[-73.122617,42.623581],"type":"Point"}
}
