{
  "type": "Feature",
  "properties": {
    "addr:full": "40 Sconticut Neck Rd Fairhaven MA 02719",
    "addr:housenumber": "40",
    "addr:postcode": "02719",
    "addr:street": "Sconticut Neck Rd",
    "iso:country": "US",
    "sg:address": "40 Sconticut Neck Rd",
    "sg:city": "Fairhaven",
    "sg:classifiers": [
      {
        "category": "Social Services",
        "type": "Services"
      }
    ],
    "sg:phone": "+1 508 990 0607",
    "sg:postcode": "02719",
    "sg:province": "MA",
    "sg:tags": [
      "care",
      "center",
      "day"
    ],
    "wof:name": "Friendly Harbor Active Day Ctr",
    "wof:placetype": "venue"
  },
  "geometry": {"coordinates":[-70.880784,41.63709],"type":"Point"}
}
