{
  "type": "Feature",
  "properties": {
    "addr:full":"1 Wharf Rd Rockport MA 01966",
    "addr:housenumber":"1",
    "addr:postcode":"01966",
    "addr:street":"Wharf Rd",
    "iso:country":"US",
    "sg:address":"1 Wharf Rd",
    "sg:city":"Rockport",
    "sg:classifiers":[
        {
            "category":"Restaurant",
            "type":"Food & Drink"
        }
    ],
    "sg:phone":"+1 978 546 2512",
    "sg:postcode":"01966",
    "sg:province":"MA",
    "wof:name":"Ellen's Harborside",
    "wof:placetype":"venue"
},
  "geometry": {"coordinates":[-70.625083,42.667263],"type":"Point"}
}