{
  "type": "Feature",
  "properties": {
    "iso:country":"US",
    "sg:address":"131 Saint Nicholas Ave",
    "sg:city":"Worcester",
    "sg:classifiers":[
        {
            "category":"Wholesale",
            "subcategory":"Hardware",
            "type":"Manufacturing & Wholesale Goods"
        }
    ],
    "sg:phone":"+1 508 852 1099",
    "sg:postcode":"01606",
    "sg:province":"MA",
    "sg:tags":[
        "screw"
    ],
    "wof:name":"R B Distributors",
    "wof:placetype":"venue"
},
  "geometry": {"coordinates":[-71.782208,42.311759],"type":"Point"}
}