{
  "type": "Feature",
  "properties": {
    "addr:full": "131 Saint Nicholas Ave Worcester MA 01606",
    "addr:housenumber": "131",
    "addr:postcode": "01606",
    "addr:street": "Saint Nicholas Ave",
    "iso:country": "US",
    "sg:address": "131 Saint Nicholas Ave",
    "sg:city": "Worcester",
    "sg:classifiers": [
      {
        "category": "Wholesale",
        "subcategory": "Hardware",
        "type": "Manufacturing \u0026 Wholesale Goods"
      }
    ],
    "sg:phone": "+1 508 852 1099",
    "sg:postcode": "01606",
    "sg:province": "MA",
    "sg:tags": [
      "screw"
    ],
    "wof:name": "R B Distributors",
    "wof:placetype": "venue"
  },
  "geometry": {"coordinates":[-71.782208,42.311759],"type":"Point"}
}
