{
  "type": "Feature",
  "properties": {
    "addr:full":"131 Scituate Rd Mashpee MA 02649",
    "addr:housenumber":"131",
    "addr:postcode":"02649",
    "addr:street":"Scituate Rd",
    "iso:country":"US",
    "sg:address":"131 Scituate Rd",
    "sg:city":"Mashpee",
    "sg:classifiers":[
        {
            "category":"Education",
            "subcategory":"Special Training",
            "type":"Public Place"
        }
    ],
    "sg:phone":"+1 508 292 2730",
    "sg:postcode":"02649",
    "sg:province":"MA",
    "sg:tags":[
        "school",
        "instruction",
        "art"
    ],
    "wof:name":"Artistic Image",
    "wof:placetype":"venue"
},
  "geometry": {"coordinates":[-70.468722,41.660815],"type":"Point"}
}