{
  "type": "Feature",
  "properties": {
    "iso:country":"US",
    "sg:address":"19 Old Coach Rd",
    "sg:city":"Westborough",
    "sg:classifiers":[
        {
            "category":"Retail",
            "subcategory":"Animal Services",
            "type":"Services"
        }
    ],
    "sg:phone":"+1   ",
    "sg:postcode":"01581",
    "sg:province":"MA",
    "wof:name":"Sherah Cavaliers",
    "wof:placetype":"venue"
},
  "geometry": {"coordinates":[-71.610677,42.243378],"type":"Point"}
}