{
  "type": "Feature",
  "properties": {
    "iso:country":"US",
    "sg:address":"1 Taunton Green",
    "sg:city":"Taunton",
    "sg:classifiers":[
        {
            "category":"Real Estate",
            "subcategory":"Real Estate Agent",
            "type":"Services"
        }
    ],
    "sg:phone":"+1 508 824 7946",
    "sg:postcode":"02780",
    "sg:province":"MA",
    "wof:name":"Dean Industrial Real Estate",
    "wof:placetype":"venue"
},
  "geometry": {"coordinates":[-71.094016,41.90204],"type":"Point"}
}