{
  "type": "Feature",
  "properties": {
    "iso:country":"US",
    "sg:address":"319 Longwood Avenue",
    "sg:city":"Boston",
    "sg:classifiers":[
        {
            "category":"Health Services",
            "subcategory":"Doctor",
            "type":"Services"
        },
        {
            "category":"Sports & Exercise",
            "subcategory":"Gym",
            "type":"Entertainment"
        }
    ],
    "sg:phone":"+1 617 975 2321",
    "sg:postcode":"02115",
    "sg:province":"MA",
    "sg:tags":[
        "trainer",
        "practice",
        "family"
    ],
    "wof:name":"Urology Practice Associates Caregroup",
    "wof:placetype":"venue"
},
  "geometry": {"coordinates":[-71.105749,42.338068],"type":"Point"}
}