{
  "type": "Feature",
  "properties": {
    "addr:full":"47 Brown Ave Mansfield MA 02048",
    "addr:housenumber":"47",
    "addr:postcode":"02048",
    "addr:street":"Brown Ave",
    "iso:country":"US",
    "sg:address":"47 Brown Ave",
    "sg:city":"Mansfield",
    "sg:classifiers":[
        {
            "category":"Building & Trades",
            "subcategory":"Construction",
            "type":"Services"
        }
    ],
    "sg:phone":"+1   ",
    "sg:postcode":"02048",
    "sg:province":"MA",
    "sg:tags":[
        "house"
    ],
    "wof:name":"Steve White Construc",
    "wof:placetype":"venue"
},
  "geometry": {"coordinates":[-71.279583,42.006764],"type":"Point"}
}