{
  "type": "Feature",
  "properties": {
    "addr:full": "933 Gorham St Lowell MA 01852",
    "addr:housenumber": "933",
    "addr:postcode": "01852",
    "addr:street": "Gorham St",
    "iso:country": "US",
    "sg:address": "933 Gorham St",
    "sg:city": "Lowell",
    "sg:classifiers": [
      {
        "category": "Personal",
        "subcategory": "Beauty Salon",
        "type": "Services"
      },
      {
        "category": "Personal",
        "subcategory": "Nail Salon",
        "type": "Services"
      }
    ],
    "sg:phone": "+1 978 454 5922",
    "sg:postcode": "01852",
    "sg:province": "MA",
    "sg:tags": [
      "hair",
      "stylist"
    ],
    "wof:name": "Diana's Hair Fashion \u0026 Design",
    "wof:placetype": "venue"
  },
  "geometry": {"coordinates":[-71.308193,42.629138],"type":"Point"}
}
