{
  "type": "Feature",
  "properties": {
    "iso:country":"US",
    "sg:address":"933 Gorham St",
    "sg:city":"Lowell",
    "sg:classifiers":[
        {
            "category":"Personal",
            "subcategory":"Beauty Salon",
            "type":"Services"
        },
        {
            "category":"Personal",
            "subcategory":"Nail Salon",
            "type":"Services"
        }
    ],
    "sg:phone":"+1 978 454 5922",
    "sg:postcode":"01852",
    "sg:province":"MA",
    "sg:tags":[
        "hair",
        "stylist"
    ],
    "wof:name":"Diana's Hair Fashion & Design",
    "wof:placetype":"venue"
},
  "geometry": {"coordinates":[-71.308193,42.629138],"type":"Point"}
}