{
  "type": "Feature",
  "properties": {
    "addr:full": "53 Hermon St Worcester MA 01610",
    "addr:housenumber": "53",
    "addr:postcode": "01610",
    "addr:street": "Hermon St",
    "iso:country": "US",
    "sg:address": "53 Hermon St",
    "sg:city": "Worcester",
    "sg:classifiers": [
      {
        "category": "Manufacturing",
        "subcategory": "Metals",
        "type": "Manufacturing \u0026 Wholesale Goods"
      }
    ],
    "sg:phone": "+1 508 756 2647",
    "sg:postcode": "01610",
    "sg:province": "MA",
    "sg:tags": [
      "fabricator",
      "sheet"
    ],
    "wof:name": "William Morrill Assoc Inc",
    "wof:placetype": "venue"
  },
  "geometry": {"coordinates":[-71.806086,42.256252],"type":"Point"}
}
