{
  "type": "Feature",
  "properties": {
    "addr:full": "6 Riverside Dr Marblehead MA 01945",
    "addr:housenumber": "6",
    "addr:postcode": "01945",
    "addr:street": "Riverside Dr",
    "iso:country": "US",
    "sg:address": "6 Riverside Dr",
    "sg:city": "Marblehead",
    "sg:classifiers": [
      {
        "category": "Utilities",
        "subcategory": "Telephone",
        "type": "Services"
      }
    ],
    "sg:phone": "+1   ",
    "sg:postcode": "01945",
    "sg:province": "MA",
    "sg:tags": [
      "communications"
    ],
    "wof:name": "Spencer Communications Inc",
    "wof:placetype": "venue"
  },
  "geometry": {"coordinates":[-70.888782,42.491375],"type":"Point"}
}
