{
  "type": "Feature",
  "properties": {
    "iso:country":"US",
    "sg:address":"6 Riverside Dr",
    "sg:city":"Marblehead",
    "sg:classifiers":[
        {
            "category":"Utilities",
            "subcategory":"Telephone",
            "type":"Services"
        }
    ],
    "sg:phone":"+1   ",
    "sg:postcode":"01945",
    "sg:province":"MA",
    "sg:tags":[
        "communications"
    ],
    "wof:name":"Spencer Communications Inc",
    "wof:placetype":"venue"
},
  "geometry": {"coordinates":[-70.88878200000001,42.491375],"type":"Point"}
}