{
  "type": "Feature",
  "properties": {
    "iso:country":"US",
    "sg:address":"23 Everett St",
    "sg:city":"Woburn",
    "sg:classifiers":[
        {
            "category":"Building & Trades",
            "subcategory":"Plumbing",
            "type":"Services"
        }
    ],
    "sg:phone":"+1 781 933 7878",
    "sg:postcode":"01801",
    "sg:province":"MA",
    "sg:tags":[
        "conditioning",
        "air",
        "system",
        "contractor"
    ],
    "wof:name":"Climate Technologies",
    "wof:placetype":"venue"
},
  "geometry": {"coordinates":[-71.149156,42.480037],"type":"Point"}
}