{
  "type": "Feature",
  "properties": {
    "addr:full": "15 W Yarmouth Rd West Yarmouth MA 02673",
    "addr:housenumber": "15",
    "addr:postcode": "02673",
    "addr:street": "W Yarmouth Rd",
    "iso:country": "US",
    "sg:address": "15 W Yarmouth Rd",
    "sg:city": "West Yarmouth",
    "sg:classifiers": [
      {
        "category": "Building \u0026 Trades",
        "subcategory": "Construction",
        "type": "Services"
      }
    ],
    "sg:phone": "+1   ",
    "sg:postcode": "02673",
    "sg:province": "MA",
    "sg:tags": [
      "contractor"
    ],
    "wof:name": "Schofield Shon Hm Maint \u0026 Repr",
    "wof:placetype": "venue"
  },
  "geometry": {"coordinates":[-70.23317,41.651921],"type":"Point"}
}
