{
  "type": "Feature",
  "properties": {
    "addr:full": "280 Russellville Rd Westfield MA 01085",
    "addr:housenumber": "280",
    "addr:postcode": "01085",
    "addr:street": "Russellville Rd",
    "iso:country": "US",
    "sg:address": "280 Russellville Rd",
    "sg:city": "Westfield",
    "sg:classifiers": [
      {
        "category": "Personal",
        "subcategory": "Tanning Parlor",
        "type": "Services"
      }
    ],
    "sg:phone": "+1 413 562 8600",
    "sg:postcode": "01085",
    "sg:province": "MA",
    "sg:tags": [
      "salon"
    ],
    "wof:name": "Magic Tan Vt-WMAS",
    "wof:placetype": "venue"
  },
  "geometry": {"coordinates":[-72.759273,42.178258],"type":"Point"}
}
