{
  "type": "Feature",
  "properties": {
    "addr:full": "365 Main St Winthrop MA 02152",
    "addr:housenumber": "365",
    "addr:postcode": "02152",
    "addr:street": "Main St",
    "iso:country": "US",
    "sg:address": "365 Main St",
    "sg:city": "Winthrop",
    "sg:classifiers": [
      {
        "category": "Health Services",
        "subcategory": "Doctor",
        "type": "Services"
      }
    ],
    "sg:phone": "+1 617 846 5352",
    "sg:postcode": "02152",
    "sg:province": "MA",
    "wof:name": "Shah PC Dr \u0026 Inc",
    "wof:placetype": "venue"
  },
  "geometry": {"coordinates":[-70.981686,42.381035],"type":"Point"}
}
