{
  "type": "Feature",
  "properties": {
    "iso:country":"US",
    "sg:address":"327 Elm St",
    "sg:city":"Salisbury",
    "sg:classifiers":[
        {
            "category":"Autos & Motor Vehicles",
            "subcategory":"Automobile Sales",
            "type":"Retail Goods"
        }
    ],
    "sg:phone":"+1 978 462 3500",
    "sg:postcode":"01952",
    "sg:province":"MA",
    "sg:tags":[
        "car",
        "dealer"
    ],
    "wof:name":"Autoventures",
    "wof:placetype":"venue"
},
  "geometry": {"coordinates":[-70.899321,42.844214],"type":"Point"}
}