{
  "type": "Feature",
  "properties": {
    "addr:full":"41 Russell St Hadley MA 01035",
    "addr:housenumber":"41",
    "addr:postcode":"01035",
    "addr:street":"Russell St",
    "iso:country":"US",
    "sg:address":"41 Russell St",
    "sg:city":"Hadley",
    "sg:classifiers":[
        {
            "category":"Home & Garden",
            "subcategory":"Household Appliances",
            "type":"Retail Goods"
        }
    ],
    "sg:phone":"+1 413 587 9500",
    "sg:postcode":"01035",
    "sg:province":"MA",
    "sg:tags":[
        "cleaners",
        "vacuum"
    ],
    "wof:name":"Electrolux",
    "wof:placetype":"venue"
},
  "geometry": {"coordinates":[-72.60699,42.339744],"type":"Point"}
}