{
  "type": "Feature",
  "properties": {
    "addr:full": "15 Scotland Blvd Bridgewater MA 02324",
    "addr:housenumber": "15",
    "addr:postcode": "02324",
    "addr:street": "Scotland Blvd",
    "iso:country": "US",
    "sg:address": "15 Scotland Blvd",
    "sg:city": "Bridgewater",
    "sg:classifiers": [
      {
        "category": "Professional",
        "type": "Services"
      }
    ],
    "sg:phone": "+1 508 279 2160",
    "sg:postcode": "02324",
    "sg:province": "MA",
    "sg:tags": [
      "establishment"
    ],
    "wof:name": "CLS",
    "wof:placetype": "venue"
  },
  "geometry": {"coordinates":[-71.003886,41.973577],"type":"Point"}
}
