{
  "type": "Feature",
  "properties": {
    "iso:country":"US",
    "sg:address":"131 West Concord St., Suite 1",
    "sg:city":"Boston",
    "sg:classifiers":[
        {
            "category":"Education",
            "subcategory":"Music School",
            "type":"Public Place"
        }
    ],
    "sg:phone":"+1 857 207 2248",
    "sg:postcode":"02118",
    "sg:province":"MA",
    "sg:tags":[
        "instrument",
        "teacher",
        "musical"
    ],
    "sg:website":"www.bostonguitarrepaircenter.com",
    "wof:name":"Boston Guitar Repair Center",
    "wof:placetype":"venue"
},
  "geometry": {"coordinates":[-71.0767,42.3397],"type":"Point"}
}