{
  "type": "Feature",
  "properties": {
    "iso:country":"US",
    "sg:address":"200 Andover St",
    "sg:city":"Wilmington",
    "sg:classifiers":[
        {
            "category":"Retail",
            "subcategory":"Auto Repair",
            "type":"Services"
        }
    ],
    "sg:phone":"+1 978 657 7088",
    "sg:postcode":"01887",
    "sg:province":"MA",
    "sg:tags":[
        "truck"
    ],
    "wof:name":"RPM Diesel & Marine",
    "wof:placetype":"venue"
},
  "geometry": {"coordinates":[-71.14657099999999,42.585961],"type":"Point"}
}