{
  "type": "Feature",
  "properties": {
    "iso:country":"US",
    "sg:address":"71 South St",
    "sg:city":"Ware",
    "sg:classifiers":[
        {
            "category":"Social Services",
            "subcategory":"Job Training",
            "type":"Services"
        }
    ],
    "sg:phone":"+1 413 967 7290",
    "sg:postcode":"01082",
    "sg:province":"MA",
    "sg:tags":[
        "career",
        "counseling",
        "vocational"
    ],
    "wof:name":"Commonwealth Of Massachusetts",
    "wof:placetype":"venue"
},
  "geometry": {"coordinates":[-72.240984,42.254677],"type":"Point"}
}