{
  "type": "Feature",
  "properties": {
    "addr:full": "75 Sunderland Rd Amherst MA 01002",
    "addr:housenumber": "75",
    "addr:postcode": "01002",
    "addr:street": "Sunderland Rd",
    "iso:country": "US",
    "sg:address": "75 Sunderland Rd",
    "sg:city": "Amherst",
    "sg:classifiers": [
      {
        "category": "Building \u0026 Trades",
        "subcategory": "Construction",
        "type": "Services"
      }
    ],
    "sg:phone": "+1 413 549 0812",
    "sg:postcode": "01002",
    "sg:province": "MA",
    "sg:tags": [
      "welder"
    ],
    "wof:name": "Northeast Pipeline Service",
    "wof:placetype": "venue"
  },
  "geometry": {"coordinates":[-72.532033,42.413653],"type":"Point"}
}
