{
  "type": "Feature",
  "properties": {
    "iso:country":"US",
    "sg:address":"51 Hartford Ave W",
    "sg:city":"Uxbridge",
    "sg:classifiers":[
        {
            "category":"Social Services",
            "subcategory":"Adult Care",
            "type":"Services"
        }
    ],
    "sg:phone":"+1 508 278 6146",
    "sg:postcode":"01569",
    "sg:province":"MA",
    "sg:tags":[
        "home",
        "group"
    ],
    "wof:name":"Evergreen Center",
    "wof:placetype":"venue"
},
  "geometry": {"coordinates":[-71.646979,42.090317],"type":"Point"}
}