{
  "type": "Feature",
  "properties": {
    "iso:country":"US",
    "sg:address":"6 Pleasant St",
    "sg:city":"Taunton",
    "sg:classifiers":[
        {
            "category":"Real Estate",
            "subcategory":"Real Estate Agent",
            "type":"Services"
        }
    ],
    "sg:phone":"+1 508 822 3100",
    "sg:postcode":"02780",
    "sg:province":"MA",
    "wof:name":"Victory Realty Group Inc",
    "wof:placetype":"venue"
},
  "geometry": {"coordinates":[-71.09560999999999,41.904459],"type":"Point"}
}