{
  "type": "Feature",
  "properties": {
    "addr:full": "6 Pleasant St Taunton MA 02780",
    "addr:housenumber": "6",
    "addr:postcode": "02780",
    "addr:street": "Pleasant St",
    "iso:country": "US",
    "sg:address": "6 Pleasant St",
    "sg:city": "Taunton",
    "sg:classifiers": [
      {
        "category": "Real Estate",
        "subcategory": "Real Estate Agent",
        "type": "Services"
      }
    ],
    "sg:phone": "+1 508 822 3100",
    "sg:postcode": "02780",
    "sg:province": "MA",
    "wof:name": "Victory Realty Group Inc",
    "wof:placetype": "venue"
  },
  "geometry": {"coordinates":[-71.09561,41.904459],"type":"Point"}
}
