{
  "type": "Feature",
  "properties": {
    "iso:country":"US",
    "sg:address":"14 Franklin St",
    "sg:city":"Quincy",
    "sg:classifiers":[
        {
            "category":"Professional",
            "subcategory":"Management & Consulting",
            "type":"Services"
        },
        {
            "category":"Banks & Credit Unions",
            "subcategory":"Investment Brokerage",
            "type":"Services"
        },
        {
            "category":"Insurance",
            "subcategory":"Hazard Insurance",
            "type":"Services"
        },
        {
            "category":"Banks & Credit Unions",
            "subcategory":"Financial Services",
            "type":"Services"
        }
    ],
    "sg:phone":"+1 617 472 3000",
    "sg:postcode":"02169",
    "sg:province":"MA",
    "sg:tags":[
        "financing",
        "business",
        "resume",
        "consultant",
        "commercial",
        "agent",
        "planning"
    ],
    "sg:website":"http://www.bphins.com",
    "wof:name":"Burgin Pltner Hrley Insur Agcy",
    "wof:placetype":"venue"
},
  "geometry": {"coordinates":[-71.003372,42.243511],"type":"Point"}
}