{
  "type": "Feature",
  "properties": {
    "iso:country":"US",
    "sg:address":"13 Cee Jay Ter",
    "sg:city":"Wrentham",
    "sg:classifiers":[
        {
            "category":"Professional",
            "type":"Services"
        }
    ],
    "sg:phone":"+1   ",
    "sg:postcode":"02093",
    "sg:province":"MA",
    "wof:name":"Little Extras Inc",
    "wof:placetype":"venue"
},
  "geometry": {"coordinates":[-71.311817,42.076076],"type":"Point"}
}