{
  "type": "Feature",
  "properties": {
    "addr:full":"308 Pawtucket St Lowell MA 01854",
    "addr:housenumber":"308",
    "addr:postcode":"01854",
    "addr:street":"Pawtucket St",
    "iso:country":"US",
    "sg:address":"308 Pawtucket St",
    "sg:city":"Lowell",
    "sg:classifiers":[
        {
            "category":"Cemetery",
            "type":"Public Place"
        },
        {
            "category":"Retail",
            "subcategory":"Funeral Services",
            "type":"Services"
        }
    ],
    "sg:phone":"+1 978 454 5214",
    "sg:postcode":"01854",
    "sg:province":"MA",
    "sg:tags":[
        "director",
        "crematory",
        "plans-pre-arranged",
        "supply"
    ],
    "sg:website":"http://www.martinfuneralhome.net",
    "wof:name":"Martin Funeral Home",
    "wof:placetype":"venue"
},
  "geometry": {"coordinates":[-71.32692,42.649078],"type":"Point"}
}