{
  "type": "Feature",
  "properties": {
    "addr:full": "3 Christmas Tree Ln North Grafton MA 01536",
    "addr:housenumber": "3",
    "addr:postcode": "01536",
    "addr:street": "Christmas Tree Ln North",
    "iso:country": "US",
    "sg:address": "3 Christmas Tree Ln",
    "sg:city": "North Grafton",
    "sg:classifiers": [
      {
        "category": "Manufacturing",
        "subcategory": "Wood Products",
        "type": "Manufacturing \u0026 Wholesale Goods"
      }
    ],
    "sg:phone": "+1 508 839 2686",
    "sg:postcode": "01536",
    "sg:province": "MA",
    "sg:tags": [
      "line",
      "clothes",
      "supply"
    ],
    "wof:name": "E Swalec Clothes Reel Co",
    "wof:placetype": "venue"
  },
  "geometry": {"coordinates":[-71.69803,42.224725],"type":"Point"}
}
