{
  "type": "Feature",
  "properties": {
    "addr:full": "333 Washington St Boston MA 02108",
    "addr:housenumber": "333",
    "addr:postcode": "02108",
    "addr:street": "Washington St",
    "iso:country": "US",
    "ovtr:label": "Gartaganis Brothers, Inc., 333 Washington St Boston MA US",
    "ovtr:similarity": 2.9287729263305664,
    "sg:address": "333 Washington St",
    "sg:city": "Boston",
    "sg:classifiers": [
      {
        "category": "Shopping",
        "subcategory": "Jewelry",
        "type": "Retail Goods"
      }
    ],
    "sg:phone": "+1 617 227 4550",
    "sg:postcode": "02108",
    "sg:province": "MA",
    "sg:tags": [
      "jeweler"
    ],
    "sg:website": "www.goldcrosses.com",
    "wof:name": "Gartaganis Brothers Inc",
    "wof:placetype": "venue"
  },
  "geometry": {"coordinates":[-71.059047,42.356881],"type":"Point"}
}
