{
  "type": "Feature",
  "properties": {
    "addr:full":"1218 Westfield St West Springfield MA 01089",
    "addr:housenumber":"1218",
    "addr:postcode":"01089",
    "addr:street":"Westfield St",
    "iso:country":"US",
    "sg:address":"1218 Westfield St",
    "sg:city":"West Springfield",
    "sg:classifiers":[
        {
            "category":"Insurance",
            "subcategory":"Insurance Agent",
            "type":"Services"
        }
    ],
    "sg:phone":"+1 413 739 2156",
    "sg:postcode":"01089",
    "sg:province":"MA",
    "wof:name":"Richard S Thomas Insurance",
    "wof:placetype":"venue"
},
  "geometry": {"coordinates":[-72.644942,42.106658],"type":"Point"}
}