{
  "type": "Feature",
  "properties": {
    "addr:full":"316 W Housatonic St Pittsfield MA 01201",
    "addr:housenumber":"316",
    "addr:postcode":"01201",
    "addr:street":"W Housatonic St",
    "iso:country":"US",
    "sg:address":"316 W Housatonic St",
    "sg:city":"Pittsfield",
    "sg:classifiers":[
        {
            "category":"Autos & Motor Vehicles",
            "subcategory":"Auto Supplies",
            "type":"Retail Goods"
        }
    ],
    "sg:phone":"+1 413 442 8363",
    "sg:postcode":"01201",
    "sg:province":"MA",
    "sg:tags":[
        "automobile",
        "parts"
    ],
    "wof:name":"Tire Warehouse Auto Parts",
    "wof:placetype":"venue"
},
  "geometry": {"coordinates":[-73.26956199999999,42.443622],"type":"Point"}
}