{
  "type": "Feature",
  "properties": {
    "addr:full": "719 Broadway Somerville MA 02144",
    "addr:housenumber": "719",
    "addr:postcode": "02144",
    "addr:street": "Broadway",
    "iso:country": "US",
    "sg:address": "719 Broadway",
    "sg:city": "Somerville",
    "sg:classifiers": [
      {
        "category": "Restaurant",
        "type": "Food \u0026 Drink"
      }
    ],
    "sg:menulink": "http://www.allmenus.com/ma/somerville/260771-golden-jade/menu/",
    "sg:phone": "+1 617 625 9460",
    "sg:postcode": "02144",
    "sg:province": "MA",
    "sg:tags": [
      "thai",
      "asian",
      "chinese"
    ],
    "wof:name": "Golden Jade",
    "wof:placetype": "venue"
  },
  "geometry": {"coordinates":[-71.112564,42.400041],"type":"Point"}
}
