{
  "type": "Feature",
  "properties": {
    "addr:full": "154 Grove St Chicopee MA 01020",
    "addr:housenumber": "154",
    "addr:postcode": "01020",
    "addr:street": "Grove St",
    "iso:country": "US",
    "sg:address": "154 Grove St",
    "sg:city": "Chicopee",
    "sg:classifiers": [
      {
        "category": "Manufacturing",
        "subcategory": "Printing",
        "type": "Manufacturing \u0026 Wholesale Goods"
      }
    ],
    "sg:phone": "+1 413 594 6613",
    "sg:postcode": "01020",
    "sg:province": "MA",
    "sg:tags": [
      "publisher"
    ],
    "wof:name": "Northeast Woods \u0026 Waters",
    "wof:placetype": "venue"
  },
  "geometry": {"coordinates":[-72.584586,42.153818],"type":"Point"}
}
