{
  "type": "Feature",
  "properties": {
    "addr:full":"195 Walnut St Stoughton MA 02072",
    "addr:housenumber":"195",
    "addr:postcode":"02072",
    "addr:street":"Walnut St",
    "iso:country":"US",
    "sg:address":"195 Walnut St",
    "sg:city":"Stoughton",
    "sg:classifiers":[
        {
            "category":"Building & Trades",
            "subcategory":"Electrical",
            "type":"Services"
        }
    ],
    "sg:phone":"+1   ",
    "sg:postcode":"02072",
    "sg:province":"MA",
    "sg:tags":[
        "electrical",
        "contractor"
    ],
    "wof:name":"Pat Byron Electric",
    "wof:placetype":"venue"
},
  "geometry": {"coordinates":[-71.096125,42.124751],"type":"Point"}
}