{
  "type": "Feature",
  "properties": {
    "addr:full": "320 E Eagle St Boston MA 02128",
    "addr:housenumber": "320",
    "addr:postcode": "02128",
    "addr:street": "E Eagle St",
    "iso:country": "US",
    "sg:address": "320 E Eagle St",
    "sg:city": "Boston",
    "sg:classifiers": [
      {
        "category": "Home \u0026 Garden",
        "subcategory": "Building Materials",
        "type": "Retail Goods"
      },
      {
        "category": "Building \u0026 Trades",
        "subcategory": "Construction",
        "type": "Services"
      }
    ],
    "sg:phone": "+1 617 635 7525",
    "sg:postcode": "02128",
    "sg:province": "MA",
    "sg:tags": [
      "industrial",
      "contractor",
      "concrete",
      "contractors-commercial",
      "staining",
      "masonry"
    ],
    "wof:name": "East Boston Public Works Dept",
    "wof:placetype": "venue"
  },
  "geometry": {"coordinates":[-71.028351,42.38139],"type":"Point"}
}
