{
  "type": "Feature",
  "properties": {
    "iso:country":"US",
    "sg:address":"320 E Eagle St",
    "sg:city":"Boston",
    "sg:classifiers":[
        {
            "category":"Home & Garden",
            "subcategory":"Building Materials",
            "type":"Retail Goods"
        },
        {
            "category":"Building & Trades",
            "subcategory":"Construction",
            "type":"Services"
        }
    ],
    "sg:phone":"+1 617 635 7525",
    "sg:postcode":"02128",
    "sg:province":"MA",
    "sg:tags":[
        "industrial",
        "contractor",
        "concrete",
        "contractors-commercial",
        "staining",
        "masonry"
    ],
    "wof:name":"East Boston Public Works Dept",
    "wof:placetype":"venue"
},
  "geometry": {"coordinates":[-71.028351,42.38139],"type":"Point"}
}