{
  "type": "Feature",
  "properties": {
    "iso:country":"US",
    "sg:address":"Victory Road",
    "sg:city":"Dorchester",
    "sg:classifiers":[
        {
            "category":"Park",
            "type":"Public Place"
        }
    ],
    "sg:phone":"+1 617 727 5290",
    "sg:postcode":"02124",
    "sg:province":"MA",
    "sg:website":"www.mass.gov/dcr/parks/metrobost...",
    "wof:name":"Victory Road Park",
    "wof:placetype":"venue"
},
  "geometry": {"coordinates":[-71.044898,42.299855],"type":"Point"}
}