{
  "type": "Feature",
  "properties": {
    "addr:full":"120 Huntington Ave Boston MA 02116",
    "addr:housenumber":"120",
    "addr:postcode":"02116",
    "addr:street":"Huntington Ave",
    "iso:country":"US",
    "sg:address":"120 Huntington Ave",
    "sg:city":"Boston",
    "sg:classifiers":[
        {
            "category":"Travel",
            "subcategory":"Hotels & Motels",
            "type":"Entertainment"
        }
    ],
    "sg:phone":"+1 617 424 7000",
    "sg:postcode":"02116",
    "sg:province":"MA",
    "sg:website":"www.colonnadehotel.com/",
    "wof:name":"Colonnade Hotel",
    "wof:placetype":"venue"
},
  "geometry": {"coordinates":[-71.080985,42.345822],"type":"Point"}
}