{
  "type": "Feature",
  "properties": {
    "iso:country":"US",
    "sg:address":"45 Commercial St",
    "sg:city":"Pittsfield",
    "sg:classifiers":[
        {
            "category":"Building & Trades",
            "subcategory":"Plumbing",
            "type":"Services"
        }
    ],
    "sg:phone":"+1 413 499 1902",
    "sg:postcode":"01201",
    "sg:province":"MA",
    "sg:tags":[
        "plumbing",
        "contractor"
    ],
    "wof:name":"Pittsfield Plumbing Supply",
    "wof:placetype":"venue"
},
  "geometry": {"coordinates":[-73.21548,42.453022],"type":"Point"}
}