{
  "type": "Feature",
  "properties": {
    "addr:full": "26 Dudley St Arlington MA 02476",
    "addr:housenumber": "26",
    "addr:postcode": "02476",
    "addr:street": "Dudley St",
    "iso:country": "US",
    "sg:address": "26 Dudley St",
    "sg:city": "Arlington",
    "sg:classifiers": [
      {
        "category": "Building \u0026 Trades",
        "subcategory": "Cleaning \u0026 Sanitation",
        "type": "Services"
      }
    ],
    "sg:phone": "+1 781 646 0405",
    "sg:postcode": "02476",
    "sg:province": "MA",
    "sg:tags": [
      "window",
      "cleaning-exterior"
    ],
    "sg:website": "http://www.fishwindowcleaning.com",
    "wof:name": "Fish Window Cleaning",
    "wof:placetype": "venue"
  },
  "geometry": {"coordinates":[-71.165548,42.420717],"type":"Point"}
}
