{
  "type": "Feature",
  "properties": {
    "addr:full": "52 Ansie Rd Chelmsford MA 01824",
    "addr:housenumber": "52",
    "addr:postcode": "01824",
    "addr:street": "Ansie Rd",
    "iso:country": "US",
    "sg:address": "52 Ansie Rd",
    "sg:city": "Chelmsford",
    "sg:classifiers": [
      {
        "category": "Building \u0026 Trades",
        "subcategory": "Construction",
        "type": "Services"
      }
    ],
    "sg:phone": "+1 978 250 0063",
    "sg:postcode": "01824",
    "sg:province": "MA",
    "sg:tags": [
      "carpentry",
      "carpenter",
      "contractor"
    ],
    "wof:name": "M C Carpentry",
    "wof:placetype": "venue"
  },
  "geometry": {"coordinates":[-71.33748,42.583978],"type":"Point"}
}
