{
  "type": "Feature",
  "properties": {
    "iso:country":"US",
    "sg:address":"6 Logan St",
    "sg:city":"Roxbury",
    "sg:classifiers":[
        {
            "category":"Professional",
            "subcategory":"Business Services",
            "type":"Services"
        }
    ],
    "sg:phone":"+1 617 442 4611",
    "sg:postcode":"02119",
    "sg:province":"MA",
    "sg:tags":[
        "painter",
        "sign"
    ],
    "wof:name":"James Signs",
    "wof:placetype":"venue"
},
  "geometry": {"coordinates":[-71.090896,42.326632],"type":"Point"}
}