{
  "type": "Feature",
  "properties": {
    "addr:full": "283 Elm St West Springfield MA 01089",
    "addr:housenumber": "283",
    "addr:postcode": "01089",
    "addr:street": "Elm St",
    "iso:country": "US",
    "sg:address": "283 Elm St",
    "sg:city": "West Springfield",
    "sg:classifiers": [
      {
        "category": "Retail",
        "subcategory": "Repair Shop",
        "type": "Services"
      }
    ],
    "sg:phone": "+1 413 734 4941",
    "sg:postcode": "01089",
    "sg:province": "MA",
    "sg:tags": [
      "typewriter"
    ],
    "wof:name": "Hunter's Typewriter Shop",
    "wof:placetype": "venue"
  },
  "geometry": {"coordinates":[-72.623711,42.10838],"type":"Point"}
}
