{
  "type": "Feature",
  "properties": {
    "addr:full": "1 Fiske Ave Greenfield MA 01301",
    "addr:housenumber": "1",
    "addr:postcode": "01301",
    "addr:street": "Fiske Ave",
    "iso:country": "US",
    "sg:address": "1 Fiske Ave",
    "sg:city": "Greenfield",
    "sg:classifiers": [
      {
        "category": "Home \u0026 Garden",
        "subcategory": "Furniture",
        "type": "Retail Goods"
      }
    ],
    "sg:phone": "+1 413 773 5343",
    "sg:postcode": "01301",
    "sg:province": "MA",
    "wof:name": "Greenfield Furniture \u0026 Storage",
    "wof:placetype": "venue"
  },
  "geometry": {"coordinates":[-72.601766,42.587334],"type":"Point"}
}
