{
  "type": "Feature",
  "properties": {
    "iso:country":"US",
    "sg:address":"1834 Centre St",
    "sg:city":"West Roxbury",
    "sg:classifiers":[
        {
            "category":"Government",
            "subcategory":"Post Office",
            "type":"Public Place"
        }
    ],
    "sg:postcode":"02132",
    "sg:province":"MA",
    "sg:website":"usps.whitepages.com/service/post...",
    "wof:name":"US Post Office",
    "wof:placetype":"venue"
},
  "geometry": {"coordinates":[-71.15384899999999,42.286484],"type":"Point"}
}