{
  "type": "Feature",
  "properties": {
    "addr:full": "671 Grattan St Chicopee MA 01020",
    "addr:housenumber": "671",
    "addr:postcode": "01020",
    "addr:street": "Grattan St",
    "iso:country": "US",
    "sg:address": "671 Grattan St",
    "sg:city": "Chicopee",
    "sg:classifiers": [
      {
        "category": "Home \u0026 Garden",
        "subcategory": "Carpets \u0026 Floor Coverings",
        "type": "Retail Goods"
      }
    ],
    "sg:phone": "+1 413 533 3806",
    "sg:postcode": "01020",
    "sg:province": "MA",
    "sg:tags": [
      "dealer",
      "rug"
    ],
    "wof:name": "Bay State Rug Distributors Inc",
    "wof:placetype": "venue"
  },
  "geometry": {"coordinates":[-72.599438,42.173985],"type":"Point"}
}
