{
  "type": "Feature",
  "properties": {
    "iso:country":"US",
    "sg:address":"671 Grattan St",
    "sg:city":"Chicopee",
    "sg:classifiers":[
        {
            "category":"Home & Garden",
            "subcategory":"Carpets & Floor Coverings",
            "type":"Retail Goods"
        }
    ],
    "sg:phone":"+1 413 533 3806",
    "sg:postcode":"01020",
    "sg:province":"MA",
    "sg:tags":[
        "dealer",
        "rug"
    ],
    "wof:name":"Bay State Rug Distributors Inc",
    "wof:placetype":"venue"
},
  "geometry": {"coordinates":[-72.59943800000001,42.173985],"type":"Point"}
}