{
  "type": "Feature",
  "properties": {
    "addr:full": "154 W Park St Lee MA 01238",
    "addr:housenumber": "154",
    "addr:postcode": "01238",
    "addr:street": "W Park St",
    "iso:country": "US",
    "sg:address": "154 W Park St",
    "sg:city": "Lee",
    "sg:classifiers": [
      {
        "category": "Manufacturing",
        "subcategory": "Printing",
        "type": "Manufacturing \u0026 Wholesale Goods"
      }
    ],
    "sg:phone": "+1 413 243 2544",
    "sg:postcode": "01238",
    "sg:province": "MA",
    "sg:tags": [
      "printer"
    ],
    "wof:name": "Lee Print Plus Design",
    "wof:placetype": "venue"
  },
  "geometry": {"coordinates":[-73.250929,42.3038],"type":"Point"}
}
