{
  "type": "Feature",
  "properties": {
    "iso:country":"US",
    "sg:address":"340 Court St",
    "sg:city":"Plymouth",
    "sg:classifiers":[
        {
            "category":"Organizations",
            "subcategory":"Non-profit Organization",
            "type":"Services"
        }
    ],
    "sg:phone":"+1 508 746 8886",
    "sg:postcode":"02360",
    "sg:province":"MA",
    "sg:tags":[
        "information",
        "alcoholism",
        "treatment"
    ],
    "wof:name":"Harbor Counseling Assoc",
    "wof:placetype":"venue"
},
  "geometry": {"coordinates":[-70.685971,41.975142],"type":"Point"}
}