{
  "type": "Feature",
  "properties": {
    "addr:full":"1154 Park St Palmer MA 01069",
    "addr:housenumber":"1154",
    "addr:postcode":"01069",
    "addr:street":"Park St",
    "iso:country":"US",
    "sg:address":"1154 Park St",
    "sg:city":"Palmer",
    "sg:classifiers":[
        {
            "category":"Wholesale",
            "subcategory":"Machinery & Supplies",
            "type":"Manufacturing & Wholesale Goods"
        }
    ],
    "sg:phone":"+1 413 323 8571",
    "sg:postcode":"01069",
    "sg:province":"MA",
    "sg:tags":[
        "equipment",
        "industrial"
    ],
    "wof:name":"Emerald Industrial",
    "wof:placetype":"venue"
},
  "geometry": {"coordinates":[-72.314121,42.151191],"type":"Point"}
}