{
  "type": "Feature",
  "properties": {
    "addr:full":"147 Main St Webster MA 01570",
    "addr:housenumber":"147",
    "addr:postcode":"01570",
    "addr:street":"Main St",
    "iso:country":"US",
    "sg:address":"147 Main St",
    "sg:city":"Webster",
    "sg:classifiers":[
        {
            "category":"Wholesale",
            "subcategory":"Electrical",
            "type":"Manufacturing & Wholesale Goods"
        }
    ],
    "sg:phone":"+1 508 943 3686",
    "sg:postcode":"01570",
    "sg:province":"MA",
    "sg:tags":[
        "equipment",
        "electric",
        "supply"
    ],
    "wof:name":"Webster Electrical Supply",
    "wof:placetype":"venue"
},
  "geometry": {"coordinates":[-71.884319,42.049085],"type":"Point"}
}