{
  "type": "Feature",
  "properties": {
    "iso:country":"US",
    "sg:address":"317 Washington Street",
    "sg:city":"Brookline",
    "sg:classifiers":[
        {
            "category":"Health Services",
            "subcategory":"Doctor",
            "type":"Services"
        },
        {
            "category":"Sports & Exercise",
            "subcategory":"Gym",
            "type":"Entertainment"
        }
    ],
    "sg:phone":"+1 617 566 5233",
    "sg:postcode":"02445",
    "sg:province":"MA",
    "sg:tags":[
        "trainer"
    ],
    "wof:name":"Hartigan Joseph A Jr Podiatrist",
    "wof:placetype":"venue"
},
  "geometry": {"coordinates":[-71.119062,42.332996],"type":"Point"}
}