{
  "type": "Feature",
  "properties": {
    "addr:full": "38 Crawford St Rutland MA 01543",
    "addr:housenumber": "38",
    "addr:postcode": "01543",
    "addr:street": "Crawford St",
    "iso:country": "US",
    "sg:address": "38 Crawford St",
    "sg:city": "Rutland",
    "sg:classifiers": [
      {
        "category": "Professional",
        "subcategory": "Research",
        "type": "Services"
      }
    ],
    "sg:phone": "+1 508 886 2386",
    "sg:postcode": "01543",
    "sg:province": "MA",
    "sg:tags": [
      "environmental",
      "ecological"
    ],
    "wof:name": "Purington Associates Inc",
    "wof:placetype": "venue"
  },
  "geometry": {"coordinates":[-71.996034,42.360798],"type":"Point"}
}
