{
  "type": "Feature",
  "properties": {
    "addr:full": "216 Pleasant Valley St Methuen MA 01844",
    "addr:housenumber": "216",
    "addr:postcode": "01844",
    "addr:street": "Pleasant Valley St",
    "iso:country": "US",
    "sg:address": "216 Pleasant Valley St",
    "sg:city": "Methuen",
    "sg:classifiers": [
      {
        "category": "Building \u0026 Trades",
        "subcategory": "Landscaping Services",
        "type": "Services"
      }
    ],
    "sg:phone": "+1 978 686 1226",
    "sg:postcode": "01844",
    "sg:province": "MA",
    "sg:tags": [
      "landscape",
      "contractor"
    ],
    "wof:name": "J Posada Landscape Contr",
    "wof:placetype": "venue"
  },
  "geometry": {"coordinates":[-71.130704,42.745909],"type":"Point"}
}
