{
  "type": "Feature",
  "properties": {
    "iso:country":"US",
    "sg:address":"216 Pleasant Valley St",
    "sg:city":"Methuen",
    "sg:classifiers":[
        {
            "category":"Building & Trades",
            "subcategory":"Landscaping Services",
            "type":"Services"
        }
    ],
    "sg:phone":"+1 978 686 1226",
    "sg:postcode":"01844",
    "sg:province":"MA",
    "sg:tags":[
        "landscape",
        "contractor"
    ],
    "wof:name":"J Posada Landscape Contr",
    "wof:placetype":"venue"
},
  "geometry": {"coordinates":[-71.13070399999999,42.745909],"type":"Point"}
}