{
  "type": "Feature",
  "properties": {
    "addr:full":"406 W Main St Hyannis MA 02601",
    "addr:housenumber":"406",
    "addr:postcode":"02601",
    "addr:street":"W Main St",
    "iso:country":"US",
    "sg:address":"406 W Main St",
    "sg:city":"Hyannis",
    "sg:classifiers":[
        {
            "category":"Restaurant",
            "type":"Food & Drink"
        },
        {
            "category":"Food & Beverages",
            "subcategory":"Meat & Fish",
            "type":"Retail Goods"
        }
    ],
    "sg:phone":"+1 508 771 1122",
    "sg:postcode":"02601",
    "sg:province":"MA",
    "sg:tags":[
        "seafood",
        "market"
    ],
    "wof:name":"Cape Fish & Lobster",
    "wof:placetype":"venue"
},
  "geometry": {"coordinates":[-70.309799,41.6488],"type":"Point"}
}