{
  "type": "Feature",
  "properties": {
    "addr:full":"138 Cabot St Chicopee MA 01013",
    "addr:housenumber":"138",
    "addr:postcode":"01013",
    "addr:street":"Cabot St",
    "iso:country":"US",
    "sg:address":"138 Cabot St",
    "sg:city":"Chicopee",
    "sg:classifiers":[
        {
            "category":"Restaurant",
            "type":"Food & Drink"
        }
    ],
    "sg:phone":"+1 413 594 9468",
    "sg:postcode":"01013",
    "sg:province":"MA",
    "sg:tags":[
        "cafe"
    ],
    "wof:name":"Polish National Home Cafe",
    "wof:placetype":"venue"
},
  "geometry": {"coordinates":[-72.60891599999999,42.145581],"type":"Point"}
}