{
  "type": "Feature",
  "properties": {
    "iso:country":"US",
    "sg:address":"360 1st Parish Rd",
    "sg:city":"Scituate",
    "sg:classifiers":[
        {
            "category":"Building & Trades",
            "subcategory":"Construction",
            "type":"Services"
        }
    ],
    "sg:phone":"+1 781 544 0499",
    "sg:postcode":"02066",
    "sg:province":"MA",
    "sg:tags":[
        "painter"
    ],
    "wof:name":"No Grey Area",
    "wof:placetype":"venue"
},
  "geometry": {"coordinates":[-70.759002,42.199434],"type":"Point"}
}