{
  "type": "Feature",
  "properties": {
    "iso:country":"US",
    "sg:address":"21 Brown Rd",
    "sg:city":"Rowe",
    "sg:classifiers":[
        {
            "category":"Building & Trades",
            "subcategory":"Construction",
            "type":"Services"
        }
    ],
    "sg:phone":"+1   ",
    "sg:postcode":"01367",
    "sg:province":"MA",
    "sg:tags":[
        "painting"
    ],
    "wof:name":"Buck Painting",
    "wof:placetype":"venue"
},
  "geometry": {"coordinates":[-72.919417,42.708765],"type":"Point"}
}