{
  "type": "Feature",
  "properties": {
    "iso:country":"US",
    "sg:address":"112 Thorndike St",
    "sg:city":"Cambridge",
    "sg:classifiers":[
        {
            "category":"Professional",
            "subcategory":"Management & Consulting",
            "type":"Services"
        }
    ],
    "sg:phone":"+1 617 515 1256",
    "sg:postcode":"02141",
    "sg:province":"MA",
    "sg:tags":[
        "consultant"
    ],
    "wof:name":"Glenn Yamagata Consulting",
    "wof:placetype":"venue"
},
  "geometry": {"coordinates":[-71.08245700000001,42.36982],"type":"Point"}
}