{
  "type": "Feature",
  "properties": {
    "addr:full": "112 Thorndike St Cambridge MA 02141",
    "addr:housenumber": "112",
    "addr:postcode": "02141",
    "addr:street": "Thorndike St",
    "iso:country": "US",
    "sg:address": "112 Thorndike St",
    "sg:city": "Cambridge",
    "sg:classifiers": [
      {
        "category": "Professional",
        "subcategory": "Management \u0026 Consulting",
        "type": "Services"
      }
    ],
    "sg:phone": "+1 617 515 1256",
    "sg:postcode": "02141",
    "sg:province": "MA",
    "sg:tags": [
      "consultant"
    ],
    "wof:name": "Glenn Yamagata Consulting",
    "wof:placetype": "venue"
  },
  "geometry": {"coordinates":[-71.082457,42.36982],"type":"Point"}
}
