{
  "type": "Feature",
  "properties": {
    "iso:country":"US",
    "sg:address":"241 School St",
    "sg:city":"Winchendon",
    "sg:classifiers":[
        {
            "category":"Shopping",
            "subcategory":"Discount & Variety Stores",
            "type":"Retail Goods"
        }
    ],
    "sg:phone":"+1 978 297 9885",
    "sg:postcode":"01475",
    "sg:province":"MA",
    "sg:tags":[
        "merchandise",
        "general"
    ],
    "wof:name":"Germaine's Country Store",
    "wof:placetype":"venue"
},
  "geometry": {"coordinates":[-72.05786999999999,42.689145],"type":"Point"}
}