{
  "type": "Feature",
  "properties": {
    "iso:country":"US",
    "sg:address":"22 Woburn St",
    "sg:city":"Reading",
    "sg:classifiers":[
        {
            "category":"Building & Trades",
            "subcategory":"Construction",
            "type":"Services"
        }
    ],
    "sg:phone":"+1 781 944 5513",
    "sg:postcode":"01867",
    "sg:province":"MA",
    "sg:tags":[
        "splicing",
        "electrician",
        "cable"
    ],
    "wof:name":"Cable Splicing & Testing Inc",
    "wof:placetype":"venue"
},
  "geometry": {"coordinates":[-71.103302,42.525002],"type":"Point"}
}