{
  "type": "Feature",
  "properties": {
    "addr:full": "22 Woburn St Reading MA 01867",
    "addr:housenumber": "22",
    "addr:postcode": "01867",
    "addr:street": "Woburn St",
    "iso:country": "US",
    "sg:address": "22 Woburn St",
    "sg:city": "Reading",
    "sg:classifiers": [
      {
        "category": "Building \u0026 Trades",
        "subcategory": "Construction",
        "type": "Services"
      }
    ],
    "sg:phone": "+1 781 944 5513",
    "sg:postcode": "01867",
    "sg:province": "MA",
    "sg:tags": [
      "splicing",
      "electrician",
      "cable"
    ],
    "wof:name": "Cable Splicing \u0026 Testing Inc",
    "wof:placetype": "venue"
  },
  "geometry": {"coordinates":[-71.103302,42.525002],"type":"Point"}
}
