{
  "type": "Feature",
  "properties": {
    "iso:country":"US",
    "sg:address":"29 Old W Brookfield Rd",
    "sg:city":"Warren",
    "sg:classifiers":[
        {
            "category":"Retail",
            "subcategory":"Laundry & Dry Cleaning",
            "type":"Services"
        }
    ],
    "sg:phone":"+1 413 436 5655",
    "sg:postcode":"01083",
    "sg:province":"MA",
    "wof:name":"Warren Dry Cleaners & Lndrs",
    "wof:placetype":"venue"
},
  "geometry": {"coordinates":[-72.192803,42.217468],"type":"Point"}
}