{
  "type": "Feature",
  "properties": {
    "addr:city": "Cambridge",
    "addr:full": "32 Quincy Street Cambridge, Ma 02138",
    "addr:house_number": "32",
    "addr:housenumber": "32",
    "addr:phone": "+1 617-495-9400",
    "addr:postcode": "02138",
    "addr:road": "Quincy Street",
    "addr:state": "MA",
    "addr:street": "Quincy St",
    "iso:country": "US",
    "sg:address": "32 Quincy St",
    "sg:city": "Cambridge",
    "sg:classifiers": [
      {
        "category": "Museum",
        "type": "Entertainment"
      }
    ],
    "sg:phone": "+1   ",
    "sg:postcode": "02138",
    "sg:province": "MA",
    "sg:tags": [
      "art"
    ],
    "wof:airports": [
      102526195,
      102530741
    ],
    "wof:name": "Harvard University Art Museums",
    "wof:placetype": "venue"
  },
  "geometry": {"coordinates":[-71.11216,42.36977],"type":"Point"}
}
