{
  "type": "Feature",
  "properties": {
    "iso:country":"US",
    "sg:address":"32 Quincy St",
    "sg:city":"Cambridge",
    "sg:classifiers":[
        {
            "category":"Museum",
            "type":"Entertainment"
        }
    ],
    "sg:phone":"+1   ",
    "sg:postcode":"02138",
    "sg:province":"MA",
    "sg:tags":[
        "art"
    ],
    "wof:name":"Harvard University Art Museum",
    "wof:placetype":"venue"
},
  "geometry": {"coordinates":[-71.11495600000001,42.372633],"type":"Point"}
}