{
  "type": "Feature",
  "properties": {
    "addr:full":"83 Barbour Ter Quincy MA 02169",
    "addr:housenumber":"83",
    "addr:postcode":"02169",
    "addr:street":"Barbour Ter",
    "iso:country":"US",
    "sg:address":"83 Barbour Ter",
    "sg:city":"Quincy",
    "sg:classifiers":[
        {
            "category":"Building & Trades",
            "subcategory":"Construction",
            "type":"Services"
        }
    ],
    "sg:phone":"+1 617 472 0117",
    "sg:postcode":"02169",
    "sg:province":"MA",
    "sg:tags":[
        "general",
        "contractor"
    ],
    "wof:name":"ABC Construction Co",
    "wof:placetype":"venue"
},
  "geometry": {"coordinates":[-70.98549800000001,42.261513],"type":"Point"}
}