{
  "type": "Feature",
  "properties": {
    "addr:full": "103 Sheridan St Chicopee MA 01020",
    "addr:housenumber": "103",
    "addr:postcode": "01020",
    "addr:street": "Sheridan St",
    "iso:country": "US",
    "sg:address": "103 Sheridan St",
    "sg:city": "Chicopee",
    "sg:classifiers": [
      {
        "category": "Building \u0026 Trades",
        "subcategory": "Landscaping Services",
        "type": "Services"
      }
    ],
    "sg:phone": "+1 413 598 8358",
    "sg:postcode": "01020",
    "sg:province": "MA",
    "sg:tags": [
      "lawn"
    ],
    "wof:name": "Green Carpet Landscapes",
    "wof:placetype": "venue"
  },
  "geometry": {"coordinates":[-72.578708,42.162763],"type":"Point"}
}
