{
  "type": "Feature",
  "properties": {
    "iso:country":"US",
    "sg:address":"398 Columbus Ave Ste 287",
    "sg:city":"Boston",
    "sg:classifiers":[
        {
            "category":"Real Estate",
            "subcategory":"Architect",
            "type":"Services"
        }
    ],
    "sg:phone":"+1 617 517 4886",
    "sg:postcode":"02116",
    "sg:province":"MA",
    "sg:website":"www.rindaladesign.com",
    "wof:name":"Rindala Design",
    "wof:placetype":"venue"
},
  "geometry": {"coordinates":[-71.07665799999999,42.344681],"type":"Point"}
}