{
  "type": "Feature",
  "properties": {
    "addr:full": "44 Delancey St Westfield MA 01085",
    "addr:housenumber": "44",
    "addr:postcode": "01085",
    "addr:street": "Delancey St",
    "iso:country": "US",
    "sg:address": "44 Delancey St",
    "sg:city": "Westfield",
    "sg:classifiers": [
      {
        "category": "Wholesale",
        "subcategory": "Auto Parts",
        "type": "Manufacturing \u0026 Wholesale Goods"
      }
    ],
    "sg:phone": "+1 413 572 0007",
    "sg:postcode": "01085",
    "sg:province": "MA",
    "sg:tags": [
      "automobile",
      "rebuilt"
    ],
    "wof:name": "Ata Country Truck \u0026 Auto",
    "wof:placetype": "venue"
  },
  "geometry": {"coordinates":[-72.732204,42.126165],"type":"Point"}
}
