{
  "type": "Feature",
  "properties": {
    "iso:country":"US",
    "sg:address":"44 Delancey St",
    "sg:city":"Westfield",
    "sg:classifiers":[
        {
            "category":"Wholesale",
            "subcategory":"Auto Parts",
            "type":"Manufacturing & Wholesale Goods"
        }
    ],
    "sg:phone":"+1 413 572 0007",
    "sg:postcode":"01085",
    "sg:province":"MA",
    "sg:tags":[
        "automobile",
        "rebuilt"
    ],
    "wof:name":"Ata Country Truck & Auto",
    "wof:placetype":"venue"
},
  "geometry": {"coordinates":[-72.732204,42.126165],"type":"Point"}
}