{
  "type": "Feature",
  "properties": {
    "addr:full": "26 Hawley St Woburn MA 01801",
    "addr:housenumber": "26",
    "addr:postcode": "01801",
    "addr:street": "Hawley St",
    "iso:country": "US",
    "sg:address": "26 Hawley St",
    "sg:city": "Woburn",
    "sg:classifiers": [
      {
        "category": "Home \u0026 Garden",
        "subcategory": "Household Appliances",
        "type": "Retail Goods"
      },
      {
        "category": "Building \u0026 Trades",
        "subcategory": "Construction",
        "type": "Services"
      }
    ],
    "sg:phone": "+1 781 721 1919",
    "sg:postcode": "01801",
    "sg:province": "MA",
    "sg:tags": [
      "dishwashing",
      "specialty",
      "system",
      "machine",
      "heating",
      "contractor",
      "air conditioning"
    ],
    "wof:name": "Dry Air Systems",
    "wof:placetype": "venue"
  },
  "geometry": {"coordinates":[-71.13669,42.478331],"type":"Point"}
}
