{
  "type": "Feature",
  "properties": {
    "iso:country":"US",
    "sg:address":"402 Hudson St",
    "sg:city":"Marlborough",
    "sg:classifiers":[
        {
            "category":"Taxi",
            "type":"Transportation"
        }
    ],
    "sg:phone":"+1 508 481 5346",
    "sg:postcode":"01752",
    "sg:province":"MA",
    "wof:name":"First Student Inc",
    "wof:placetype":"venue"
},
  "geometry": {"coordinates":[-71.555543,42.361146],"type":"Point"}
}