{
  "type": "Feature",
  "properties": {
    "iso:country":"US",
    "sg:address":"1715 State Hwy 28",
    "sg:city":"West Chatham",
    "sg:classifiers":[
        {
            "category":"Retail",
            "subcategory":"Laundry & Dry Cleaning",
            "type":"Services"
        }
    ],
    "sg:phone":"+1 508 945 2584",
    "sg:postcode":"02632",
    "sg:province":"MA",
    "sg:tags":[
        "cleaners"
    ],
    "wof:name":"Princess Cleaners",
    "wof:placetype":"venue"
},
  "geometry": {"coordinates":[-70.349954,41.656836],"type":"Point"}
}