{
  "type": "Feature",
  "properties": {
    "addr:full":"51 Dudley St Arlington MA 02476",
    "addr:housenumber":"51",
    "addr:postcode":"02476",
    "addr:street":"Dudley St",
    "iso:country":"US",
    "sg:address":"51 Dudley St",
    "sg:city":"Arlington",
    "sg:classifiers":[
        {
            "category":"Real Estate",
            "subcategory":"Real Estate Agent",
            "type":"Services"
        }
    ],
    "sg:phone":"+1 781 641 0600",
    "sg:postcode":"02476",
    "sg:province":"MA",
    "sg:tags":[
        "inspection"
    ],
    "wof:name":"Carlson Co",
    "wof:placetype":"venue"
},
  "geometry": {"coordinates":[-71.16896699999999,42.421619],"type":"Point"}
}