{
  "type": "Feature",
  "properties": {
    "iso:country":"US",
    "sg:address":"1478 Acushnet Ave",
    "sg:city":"New Bedford",
    "sg:classifiers":[
        {
            "category":"Restaurant",
            "type":"Food & Drink"
        }
    ],
    "sg:phone":"+1 508 993 8158",
    "sg:postcode":"02746",
    "sg:province":"MA",
    "sg:tags":[
        "shop",
        "coffee"
    ],
    "wof:name":"Cafe Monte Carlo",
    "wof:placetype":"venue"
},
  "geometry": {"coordinates":[-70.92774199999999,41.661581],"type":"Point"}
}