{
  "type": "Feature",
  "properties": {
    "addr:full": "1478 Acushnet Ave New Bedford MA 02746",
    "addr:housenumber": "1478",
    "addr:postcode": "02746",
    "addr:street": "Acushnet Ave",
    "iso:country": "US",
    "sg:address": "1478 Acushnet Ave",
    "sg:city": "New Bedford",
    "sg:classifiers": [
      {
        "category": "Restaurant",
        "type": "Food \u0026 Drink"
      }
    ],
    "sg:phone": "+1 508 993 8158",
    "sg:postcode": "02746",
    "sg:province": "MA",
    "sg:tags": [
      "shop",
      "coffee"
    ],
    "wof:name": "Cafe Monte Carlo",
    "wof:placetype": "venue"
  },
  "geometry": {"coordinates":[-70.927742,41.661581],"type":"Point"}
}
