{
  "type": "Feature",
  "properties": {
    "addr:full":"36 Main St Lakeville MA 02347",
    "addr:housenumber":"36",
    "addr:postcode":"02347",
    "addr:street":"Main St",
    "iso:country":"US",
    "sg:address":"36 Main St",
    "sg:city":"Lakeville",
    "sg:classifiers":[
        {
            "category":"Retail",
            "subcategory":"Animal Services",
            "type":"Services"
        }
    ],
    "sg:phone":"+1 508 947 5270",
    "sg:postcode":"02347",
    "sg:province":"MA",
    "sg:tags":[
        "pet",
        "boarding",
        "sitting"
    ],
    "wof:name":"K-9 Country Club",
    "wof:placetype":"venue"
},
  "geometry": {"coordinates":[-70.925803,41.874939],"type":"Point"}
}