{
  "type": "Feature",
  "properties": {
    "addr:full":"4 Campground Rd Sterling MA 01564",
    "addr:housenumber":"4",
    "addr:postcode":"01564",
    "addr:street":"Campground Rd",
    "iso:country":"US",
    "sg:address":"4 Campground Rd",
    "sg:city":"Sterling",
    "sg:classifiers":[
        {
            "category":"Building & Trades",
            "subcategory":"Plumbing",
            "type":"Services"
        }
    ],
    "sg:phone":"+1 978 422 8430",
    "sg:postcode":"01564",
    "sg:province":"MA",
    "sg:tags":[
        "plumbing",
        "contractor"
    ],
    "wof:name":"Sterling Plumbing & Heating",
    "wof:placetype":"venue"
},
  "geometry": {"coordinates":[-71.76271199999999,42.407864],"type":"Point"}
}