{
  "type": "Feature",
  "properties": {
    "addr:full":"19 E Falmouth Hwy East Falmouth MA 02536",
    "addr:housenumber":"19",
    "addr:postcode":"02536",
    "addr:street":"E Falmouth Hwy",
    "iso:country":"US",
    "sg:address":"19 E Falmouth Hwy",
    "sg:city":"East Falmouth",
    "sg:classifiers":[
        {
            "category":"Organizations",
            "subcategory":"Membership Organization",
            "type":"Services"
        }
    ],
    "sg:phone":"+1   ",
    "sg:postcode":"02536",
    "sg:province":"MA",
    "wof:name":"American Bowling Congress",
    "wof:placetype":"venue"
},
  "geometry": {"coordinates":[-70.57210600000001,41.578247],"type":"Point"}
}