{
  "type": "Feature",
  "properties": {
    "iso:country":"US",
    "sg:address":"18 Olive St",
    "sg:city":"Newburyport",
    "sg:classifiers":[
        {
            "category":"Social Services",
            "type":"Services"
        }
    ],
    "sg:phone":"+1   ",
    "sg:postcode":"01950",
    "sg:province":"MA",
    "wof:name":"Whitlow Leona Marriage & Fmly",
    "wof:placetype":"venue"
},
  "geometry": {"coordinates":[-70.878388,42.813373],"type":"Point"}
}