{
  "type": "Feature",
  "properties": {
    "iso:country":"US",
    "sg:address":"83 Harnden St",
    "sg:city":"Reading",
    "sg:classifiers":[
        {
            "category":"Building & Trades",
            "subcategory":"Pest Control",
            "type":"Services"
        }
    ],
    "sg:phone":"+1 781 942 5785",
    "sg:postcode":"01867",
    "sg:province":"MA",
    "wof:name":"Aabsolute Pest Control",
    "wof:placetype":"venue"
},
  "geometry": {"coordinates":[-71.10164,42.525633],"type":"Point"}
}