{
  "type": "Feature",
  "properties": {
    "addr:full": "155 Federal St Boston MA 02110",
    "addr:housenumber": "155",
    "addr:postcode": "02110",
    "addr:street": "Federal St",
    "iso:country": "US",
    "sg:address": "155 Federal St",
    "sg:city": "Boston",
    "sg:classifiers": [
      {
        "category": "Professional",
        "subcategory": "Lawyer \u0026 Legal Services",
        "type": "Services"
      }
    ],
    "sg:phone": "+1 617 728 0888",
    "sg:postcode": "02110",
    "sg:province": "MA",
    "sg:website": "www.johnsonaceto.com",
    "wof:name": "Johnson \u0026 Aceto PC",
    "wof:placetype": "venue"
  },
  "geometry": {"coordinates":[-71.056198,42.354401],"type":"Point"}
}
