{
  "type": "Feature",
  "properties": {
    "iso:country":"US",
    "sg:address":"14 Harris St",
    "sg:city":"Newburyport",
    "sg:classifiers":[
        {
            "category":"Health Services",
            "subcategory":"Doctor",
            "type":"Services"
        }
    ],
    "sg:phone":"+1 978 462 2483",
    "sg:postcode":"01950",
    "sg:province":"MA",
    "sg:tags":[
        "podiatrist"
    ],
    "wof:name":"Kirsner Robt E Podiatrst",
    "wof:placetype":"venue"
},
  "geometry": {"coordinates":[-70.872902,42.809399],"type":"Point"}
}