{
  "type": "Feature",
  "properties": {
    "addr:full": "25 Thurston Rd. Newton MA 02464",
    "addr:housenumber": "25",
    "addr:postcode": "02464",
    "addr:street": "Thurston Rd.",
    "iso:country": "US",
    "sg:address": "25 Thurston Rd.",
    "sg:city": "Newton",
    "sg:classifiers": [
      {
        "category": "Professional",
        "subcategory": "Computer Services",
        "type": "Services"
      }
    ],
    "sg:phone": "+1 617 938 3956",
    "sg:postcode": "02464",
    "sg:province": "MA",
    "sg:tags": [
      "web-service-deployment"
    ],
    "sg:website": "http://www.crosschecknet.com/",
    "wof:name": "Crosscheck Networks",
    "wof:placetype": "venue"
  },
  "geometry": {"coordinates":[-71.21692,42.315857],"type":"Point"}
}
