{
  "type": "Feature",
  "properties": {
    "iso:country":"US",
    "sg:address":"293 Bedford St",
    "sg:city":"Whitman",
    "sg:classifiers":[
        {
            "category":"Banks & Credit Unions",
            "subcategory":"Investment Brokerage",
            "type":"Services"
        }
    ],
    "sg:phone":"+1 781 447 6066",
    "sg:postcode":"02382",
    "sg:province":"MA",
    "sg:tags":[
        "consultant",
        "planning",
        "financial"
    ],
    "wof:name":"American Express Financial Adv",
    "wof:placetype":"venue"
},
  "geometry": {"coordinates":[-70.94934499999999,42.064989],"type":"Point"}
}