{
  "type": "Feature",
  "properties": {
    "addr:full": "293 Bedford St Whitman MA 02382",
    "addr:housenumber": "293",
    "addr:postcode": "02382",
    "addr:street": "Bedford St",
    "iso:country": "US",
    "sg:address": "293 Bedford St",
    "sg:city": "Whitman",
    "sg:classifiers": [
      {
        "category": "Banks \u0026 Credit Unions",
        "subcategory": "Investment Brokerage",
        "type": "Services"
      }
    ],
    "sg:phone": "+1 781 447 6066",
    "sg:postcode": "02382",
    "sg:province": "MA",
    "sg:tags": [
      "consultant",
      "planning",
      "financial"
    ],
    "wof:name": "American Express Financial Adv",
    "wof:placetype": "venue"
  },
  "geometry": {"coordinates":[-70.949345,42.064989],"type":"Point"}
}
