{
  "type": "Feature",
  "properties": {
    "iso:country":"US",
    "sg:address":"53 School St",
    "sg:city":"Pembroke",
    "sg:classifiers":[
        {
            "category":"Retail",
            "subcategory":"Repair Shop",
            "type":"Services"
        }
    ],
    "sg:phone":"+1 781 294 0602",
    "sg:postcode":"02359",
    "sg:province":"MA",
    "sg:tags":[
        "taxidermist"
    ],
    "wof:name":"Hart's Taxidermy",
    "wof:placetype":"venue"
},
  "geometry": {"coordinates":[-70.838092,42.042322],"type":"Point"}
}