{
  "type": "Feature",
  "properties": {
    "addr:full": "29 Estabrook Rd Shrewsbury MA 01545",
    "addr:housenumber": "29",
    "addr:postcode": "01545",
    "addr:street": "Estabrook Rd",
    "iso:country": "US",
    "sg:address": "29 Estabrook Rd",
    "sg:city": "Shrewsbury",
    "sg:classifiers": [
      {
        "category": "Wholesale",
        "subcategory": "Groceries",
        "type": "Manufacturing \u0026 Wholesale Goods"
      }
    ],
    "sg:phone": "+1 508 845 9760",
    "sg:postcode": "01545",
    "sg:province": "MA",
    "sg:tags": [
      "beverage"
    ],
    "wof:name": "Nestle Beverage",
    "wof:placetype": "venue"
  },
  "geometry": {"coordinates":[-71.714246,42.286996],"type":"Point"}
}
