{
  "type": "Feature",
  "properties": {
    "iso:country":"US",
    "sg:address":"79 Commonwealth Ave",
    "sg:city":"Concord",
    "sg:classifiers":[
        {
            "category":"Shopping",
            "subcategory":"Clothing, Apparel, & Fashions",
            "type":"Retail Goods"
        },
        {
            "category":"Education",
            "subcategory":"Dance Studio",
            "type":"Public Place"
        }
    ],
    "sg:phone":"+1 978 318 1960",
    "sg:postcode":"01742",
    "sg:province":"MA",
    "sg:tags":[
        "supply",
        "sport",
        "wear",
        "dancing"
    ],
    "sg:website":"www.dancethisway.com",
    "wof:name":"Dance This Way Llc",
    "wof:placetype":"venue"
},
  "geometry": {"coordinates":[-71.395173,42.456882],"type":"Point"}
}