{
  "type": "Feature",
  "properties": {
    "iso:country":"US",
    "sg:address":"8 Virginia Rd",
    "sg:city":"Needham",
    "sg:classifiers":[
        {
            "category":"Professional",
            "subcategory":"Art Services",
            "type":"Services"
        }
    ],
    "sg:phone":"+1 781 444 7704",
    "sg:postcode":"02494",
    "sg:province":"MA",
    "sg:tags":[
        "photographer"
    ],
    "sg:website":"www.andycaulfield.com",
    "wof:name":"Andy Caulfield",
    "wof:placetype":"venue"
},
  "geometry": {"coordinates":[-71.222475,42.294232],"type":"Point"}
}