{
  "type": "Feature",
  "properties": {
    "addr:full": "4 Maple Rd Oxford MA 01540",
    "addr:housenumber": "4",
    "addr:postcode": "01540",
    "addr:street": "Maple Rd",
    "iso:country": "US",
    "sg:address": "4 Maple Rd",
    "sg:city": "Oxford",
    "sg:classifiers": [
      {
        "category": "Communications",
        "subcategory": "Television Station",
        "type": "Services"
      }
    ],
    "sg:phone": "+1 508 987 6930",
    "sg:postcode": "01540",
    "sg:province": "MA",
    "sg:website": "www.accessoxfordinc.com",
    "wof:name": "Access Oxford Inc",
    "wof:placetype": "venue"
  },
  "geometry": {"coordinates":[-71.883645,42.160698],"type":"Point"}
}
