{
  "type": "Feature",
  "properties": {
    "iso:country":"US",
    "sg:address":"169 Spring St",
    "sg:city":"Bridgewater",
    "sg:classifiers":[
        {
            "category":"Restaurant",
            "type":"Food & Drink"
        }
    ],
    "sg:phone":"+1 508 697 5663",
    "sg:postcode":"02324",
    "sg:province":"MA",
    "sg:tags":[
        "shop",
        "coffee"
    ],
    "sg:website":"www.marylous.com",
    "wof:name":"Marylou's",
    "wof:placetype":"venue"
},
  "geometry": {"coordinates":[-70.968639,41.99173],"type":"Point"}
}