{
  "type": "Feature",
  "properties": {
    "addr:full":"352 Main St Dennis Port MA 02639",
    "addr:housenumber":"352",
    "addr:postcode":"02639",
    "addr:street":"Main St",
    "iso:country":"US",
    "sg:address":"352 Main St",
    "sg:city":"Dennis Port",
    "sg:classifiers":[
        {
            "category":"Travel",
            "subcategory":"Hotels & Motels",
            "type":"Entertainment"
        }
    ],
    "sg:phone":"+1 508 394 5577",
    "sg:postcode":"02639",
    "sg:province":"MA",
    "sg:website":"www.holidayhillmotorinn.com",
    "wof:name":"Holiday Hill Motor Inn",
    "wof:placetype":"venue"
},
  "geometry": {"coordinates":[-70.13411600000001,41.665835],"type":"Point"}
}