{
  "type": "Feature",
  "properties": {
    "iso:country":"US",
    "sg:address":"199 Boylston St",
    "sg:city":"Chestnut Hill",
    "sg:classifiers":[
        {
            "category":"Shopping",
            "subcategory":"Clothing, Apparel, & Fashions",
            "type":"Retail Goods"
        }
    ],
    "sg:phone":"+1 617 332 0751",
    "sg:postcode":"02467",
    "sg:province":"MA",
    "wof:name":"J Jill",
    "wof:placetype":"venue"
},
  "geometry": {"coordinates":[-71.173576,42.320968],"type":"Point"}
}