{
  "type": "Feature",
  "properties": {
    "iso:country":"US",
    "sg:address":"2351 Purchase St",
    "sg:city":"New Bedford",
    "sg:classifiers":[
        {
            "category":"Retail",
            "subcategory":"Car Wash",
            "type":"Services"
        }
    ],
    "sg:phone":"+1 508 994 2535",
    "sg:postcode":"02746",
    "sg:province":"MA",
    "sg:tags":[
        "polishing",
        "washing"
    ],
    "wof:name":"Minit Man Auto Wash",
    "wof:placetype":"venue"
},
  "geometry": {"coordinates":[-70.935078,41.661001],"type":"Point"}
}