{
  "type": "Feature",
  "properties": {
    "addr:full": "2351 Purchase St New Bedford MA 02746",
    "addr:housenumber": "2351",
    "addr:postcode": "02746",
    "addr:street": "Purchase St",
    "iso:country": "US",
    "ovtr:label": "Minit Man Auto Wash, 2351 Purchase St New Bedford MA US",
    "ovtr:similarity": 1.927610993385315,
    "sg:address": "2351 Purchase St",
    "sg:city": "New Bedford",
    "sg:classifiers": [
      {
        "category": "Retail",
        "subcategory": "Car Wash",
        "type": "Services"
      }
    ],
    "sg:phone": "+1 508 994 2535",
    "sg:postcode": "02746",
    "sg:province": "MA",
    "sg:tags": [
      "polishing",
      "washing"
    ],
    "wof:name": "Minit Man Auto Wash",
    "wof:placetype": "venue"
  },
  "geometry": {"coordinates":[-70.935078,41.661001],"type":"Point"}
}
