{
  "type": "Feature",
  "properties": {
    "addr:full":"104 Crowell Rd Chatham MA 02633",
    "addr:housenumber":"104",
    "addr:postcode":"02633",
    "addr:street":"Crowell Rd",
    "iso:country":"US",
    "sg:address":"104 Crowell Rd",
    "sg:city":"Chatham",
    "sg:classifiers":[
        {
            "category":"Professional",
            "subcategory":"Accounting & Tax Preparation",
            "type":"Services"
        }
    ],
    "sg:phone":"+1 508 945 2200",
    "sg:postcode":"02633",
    "sg:province":"MA",
    "sg:tags":[
        "accountant"
    ],
    "wof:name":"Meservey Accountancy",
    "wof:placetype":"venue"
},
  "geometry": {"coordinates":[-69.96667100000001,41.68791],"type":"Point"}
}