{
  "type": "Feature",
  "properties": {
    "addr:full": "39 Slater St Attleboro MA 02703",
    "addr:housenumber": "39",
    "addr:postcode": "02703",
    "addr:street": "Slater St",
    "iso:country": "US",
    "sg:address": "39 Slater St",
    "sg:city": "Attleboro",
    "sg:classifiers": [
      {
        "category": "Manufacturing",
        "subcategory": "Tools \u0026 Machinery",
        "type": "Manufacturing \u0026 Wholesale Goods"
      }
    ],
    "sg:phone": "+1 508 226 5316",
    "sg:postcode": "02703",
    "sg:province": "MA",
    "sg:tags": [
      "mold"
    ],
    "wof:name": "Torngren Associates",
    "wof:placetype": "venue"
  },
  "geometry": {"coordinates":[-71.224688,41.929067],"type":"Point"}
}
