{
  "type": "Feature",
  "properties": {
    "addr:full": "171 Locke Dr Marlborough MA 01752",
    "addr:housenumber": "171",
    "addr:postcode": "01752",
    "addr:street": "Locke Dr",
    "iso:country": "US",
    "sg:address": "171 Locke Dr",
    "sg:city": "Marlborough",
    "sg:classifiers": [
      {
        "category": "Professional",
        "subcategory": "Lawyer \u0026 Legal Services",
        "type": "Services"
      }
    ],
    "sg:phone": "+1 508 485 1911",
    "sg:postcode": "01752",
    "sg:province": "MA",
    "sg:tags": [
      "attorney"
    ],
    "wof:name": "Jonathan Roth Attny At Law",
    "wof:placetype": "venue"
  },
  "geometry": {"coordinates":[-71.581439,42.351111],"type":"Point"}
}
