{
  "type": "Feature",
  "properties": {
    "iso:country":"US",
    "sg:address":"219 Newbury St",
    "sg:city":"Boston",
    "sg:classifiers":[
        {
            "category":"Shopping",
            "subcategory":"Clothing, Apparel, & Fashions",
            "type":"Retail Goods"
        }
    ],
    "sg:phone":"+1   ",
    "sg:postcode":"02116",
    "sg:province":"MA",
    "wof:name":"Elizabeth Harris",
    "wof:placetype":"venue"
},
  "geometry": {"coordinates":[-71.080985,42.350117],"type":"Point"}
}