{
  "type": "Feature",
  "properties": {
    "addr:full":"452 River St Dunstable MA 01827",
    "addr:housenumber":"452",
    "addr:postcode":"01827",
    "addr:street":"River St",
    "iso:country":"US",
    "sg:address":"452 River St",
    "sg:city":"Dunstable",
    "sg:classifiers":[
        {
            "category":"Building & Trades",
            "subcategory":"Electrical",
            "type":"Services"
        }
    ],
    "sg:phone":"+1 978 649 4224",
    "sg:postcode":"01827",
    "sg:province":"MA",
    "sg:tags":[
        "electrician"
    ],
    "wof:name":"William F Krygowski Jr",
    "wof:placetype":"venue"
},
  "geometry": {"coordinates":[-71.54959100000001,42.688568],"type":"Point"}
}