{
  "type": "Feature",
  "properties": {
    "iso:country":"US",
    "sg:address":"50 Holyoke St",
    "sg:city":"Holyoke",
    "sg:classifiers":[
        {
            "category":"Shopping",
            "subcategory":"Gifts & Souvenirs",
            "type":"Retail Goods"
        }
    ],
    "sg:phone":"+1 413 536 5149",
    "sg:postcode":"01040",
    "sg:province":"MA",
    "sg:tags":[
        "shop"
    ],
    "sg:website":"www.hallmark.com",
    "wof:name":"Amy's Hallmark",
    "wof:placetype":"venue"
},
  "geometry": {"coordinates":[-72.640165,42.172916],"type":"Point"}
}