{
  "type": "Feature",
  "properties": {
    "addr:full": "385 Broadway Lynn MA 01904",
    "addr:housenumber": "385",
    "addr:postcode": "01904",
    "addr:street": "Broadway",
    "iso:country": "US",
    "sg:address": "385 Broadway",
    "sg:city": "Lynn",
    "sg:classifiers": [
      {
        "category": "Autos \u0026 Motor Vehicles",
        "subcategory": "Automobile Sales",
        "type": "Retail Goods"
      }
    ],
    "sg:phone": "+1   ",
    "sg:postcode": "01904",
    "sg:province": "MA",
    "wof:name": "Kia of Lynnfield",
    "wof:placetype": "venue"
  },
  "geometry": {"coordinates":[-70.958066,42.483339],"type":"Point"}
}
