{
  "type": "Feature",
  "properties": {
    "iso:country":"US",
    "sg:address":"5 Thatcher St",
    "sg:city":"Brockton",
    "sg:classifiers":[
        {
            "category":"Manufacturing",
            "subcategory":"Tools & Machinery",
            "type":"Manufacturing & Wholesale Goods"
        }
    ],
    "sg:phone":"+1 508 583 8221",
    "sg:postcode":"02302",
    "sg:province":"MA",
    "sg:tags":[
        "control"
    ],
    "wof:name":"Arvin Associates Inc",
    "wof:placetype":"venue"
},
  "geometry": {"coordinates":[-71.002082,42.076764],"type":"Point"}
}