{
  "type": "Feature",
  "properties": {
    "addr:full": "5 Thatcher St Brockton MA 02302",
    "addr:housenumber": "5",
    "addr:postcode": "02302",
    "addr:street": "Thatcher St",
    "iso:country": "US",
    "sg:address": "5 Thatcher St",
    "sg:city": "Brockton",
    "sg:classifiers": [
      {
        "category": "Manufacturing",
        "subcategory": "Tools \u0026 Machinery",
        "type": "Manufacturing \u0026 Wholesale Goods"
      }
    ],
    "sg:phone": "+1 508 583 8221",
    "sg:postcode": "02302",
    "sg:province": "MA",
    "sg:tags": [
      "control"
    ],
    "wof:name": "Arvin Associates Inc",
    "wof:placetype": "venue"
  },
  "geometry": {"coordinates":[-71.002082,42.076764],"type":"Point"}
}
