{
  "type": "Feature",
  "properties": {
    "iso:country":"US",
    "sg:address":"60 Bedford Street",
    "sg:city":"Lexington",
    "sg:classifiers":[
        {
            "category":"Retail",
            "subcategory":"Portrait Studio",
            "type":"Services"
        },
        {
            "category":"Shopping",
            "subcategory":"Pharmacy",
            "type":"Retail Goods"
        }
    ],
    "sg:phone":"+1 781 863 1111",
    "sg:postcode":"02420",
    "sg:province":"MA",
    "sg:tags":[
        "photography",
        "drugstore",
        "store"
    ],
    "sg:website":"walgreens.com",
    "wof:name":"Walgreen Drug Stores",
    "wof:placetype":"venue"
},
  "geometry": {"coordinates":[-71.23267300000001,42.45336],"type":"Point"}
}