{
  "type": "Feature",
  "properties": {
    "addr:full": "787 Keene St Duxbury MA 02332",
    "addr:housenumber": "787",
    "addr:postcode": "02332",
    "addr:street": "Keene St",
    "iso:country": "US",
    "sg:address": "787 Keene St",
    "sg:city": "Duxbury",
    "sg:classifiers": [
      {
        "category": "Professional",
        "subcategory": "Management \u0026 Consulting",
        "type": "Services"
      }
    ],
    "sg:phone": "+1 781 834 2838",
    "sg:postcode": "02332",
    "sg:province": "MA",
    "sg:tags": [
      "marketing",
      "program"
    ],
    "wof:name": "Marketing Alchemy Inc",
    "wof:placetype": "venue"
  },
  "geometry": {"coordinates":[-70.749005,42.080663],"type":"Point"}
}
