{
  "type": "Feature",
  "properties": {
    "iso:country":"US",
    "sg:address":"787 Keene St",
    "sg:city":"Duxbury",
    "sg:classifiers":[
        {
            "category":"Professional",
            "subcategory":"Management & Consulting",
            "type":"Services"
        }
    ],
    "sg:phone":"+1 781 834 2838",
    "sg:postcode":"02332",
    "sg:province":"MA",
    "sg:tags":[
        "marketing",
        "program"
    ],
    "wof:name":"Marketing Alchemy Inc",
    "wof:placetype":"venue"
},
  "geometry": {"coordinates":[-70.749005,42.080663],"type":"Point"}
}