{
  "type": "Feature",
  "properties": {
    "addr:full":"35 Windemere Rd Wellesley MA 02481",
    "addr:housenumber":"35",
    "addr:postcode":"02481",
    "addr:street":"Windemere Rd",
    "iso:country":"US",
    "sg:address":"35 Windemere Rd",
    "sg:city":"Wellesley",
    "sg:classifiers":[
        {
            "category":"Arts & Performance",
            "subcategory":"Theater",
            "type":"Entertainment"
        }
    ],
    "sg:phone":"+1   ",
    "sg:postcode":"02481",
    "sg:province":"MA",
    "sg:tags":[
        "theatrical"
    ],
    "wof:name":"Bill Stanwood Scrpt/Prduction",
    "wof:placetype":"venue"
},
  "geometry": {"coordinates":[-71.286788,42.306736],"type":"Point"}
}