{
  "type": "Feature",
  "properties": {
    "addr:full": "70 Perkins St Somerville MA 02145",
    "addr:housenumber": "70",
    "addr:postcode": "02145",
    "addr:street": "Perkins St",
    "iso:country": "US",
    "sg:address": "70 Perkins St",
    "sg:city": "Somerville",
    "sg:classifiers": [
      {
        "category": "Building \u0026 Trades",
        "subcategory": "Cleaning \u0026 Sanitation",
        "type": "Services"
      }
    ],
    "sg:phone": "+1   ",
    "sg:postcode": "02145",
    "sg:province": "MA",
    "sg:tags": [
      "maintenance"
    ],
    "wof:name": "Sra Cleaning Service",
    "wof:placetype": "venue"
  },
  "geometry": {"coordinates":[-71.079937,42.384706],"type":"Point"}
}
