{
  "type": "Feature",
  "properties": {
    "addr:full": "119 Palmer Ave Falmouth MA 02540",
    "addr:housenumber": "119",
    "addr:postcode": "02540",
    "addr:street": "Palmer Ave",
    "iso:country": "US",
    "sg:address": "119 Palmer Ave",
    "sg:city": "Falmouth",
    "sg:classifiers": [
      {
        "category": "Shopping",
        "subcategory": "Clothing, Apparel, \u0026 Fashions",
        "type": "Retail Goods"
      }
    ],
    "sg:phone": "+1 508 548 3900",
    "sg:postcode": "02540",
    "sg:province": "MA",
    "wof:name": "Liberty House",
    "wof:placetype": "venue"
  },
  "geometry": {"coordinates":[-70.621206,41.556518],"type":"Point"}
}
