{
  "type": "Feature",
  "properties": {
    "iso:country":"US",
    "sg:address":"150 Shirley Street",
    "sg:city":"Roxbury",
    "sg:classifiers":[
        {
            "category":"Building & Trades",
            "subcategory":"Construction",
            "type":"Services"
        }
    ],
    "sg:phone":"+1 617 541 9777",
    "sg:postcode":"02119",
    "sg:province":"MA",
    "sg:tags":[
        "contractor"
    ],
    "wof:name":"Bilt-Rite Contruction",
    "wof:placetype":"venue"
},
  "geometry": {"coordinates":[-71.06766399999999,42.325877],"type":"Point"}
}