{
  "type": "Feature",
  "properties": {
    "addr:full":"56 College Ave Arlington MA 02474",
    "addr:housenumber":"56",
    "addr:postcode":"02474",
    "addr:street":"College Ave",
    "iso:country":"US",
    "sg:address":"56 College Ave",
    "sg:city":"Arlington",
    "sg:classifiers":[
        {
            "category":"Manufacturing",
            "subcategory":"Printing",
            "type":"Manufacturing & Wholesale Goods"
        }
    ],
    "sg:phone":"+1 781 648 0302",
    "sg:postcode":"02474",
    "sg:province":"MA",
    "sg:tags":[
        "publishers-directory",
        "guide",
        "publisher"
    ],
    "wof:name":"Russell Group",
    "wof:placetype":"venue"
},
  "geometry": {"coordinates":[-71.156628,42.426977],"type":"Point"}
}