{
  "type": "Feature",
  "properties": {
    "iso:country":"US",
    "sg:address":"175 Megunko Rd",
    "sg:city":"Ashland",
    "sg:classifiers":[
        {
            "category":"Building & Trades",
            "subcategory":"Plumbing",
            "type":"Services"
        }
    ],
    "sg:phone":"+1 508 881 4554",
    "sg:postcode":"01721",
    "sg:province":"MA",
    "sg:tags":[
        "conditioning",
        "air",
        "system",
        "contractor"
    ],
    "wof:name":"A & J Air Conditioning Svc",
    "wof:placetype":"venue"
},
  "geometry": {"coordinates":[-71.47216899999999,42.259707],"type":"Point"}
}