{
  "type": "Feature",
  "properties": {
    "iso:country":"US",
    "sg:address":"300 Technology Square Fifth Floor",
    "sg:city":"Cambridge",
    "sg:classifiers":[
        {
            "category":"Professional",
            "subcategory":"Research",
            "type":"Services"
        }
    ],
    "sg:phone":"+1 617 551 4700",
    "sg:postcode":"02139",
    "sg:province":"MA",
    "sg:website":"http://www.radiuspharm.com",
    "wof:name":"Radius Health",
    "wof:placetype":"venue"
},
  "geometry": {"coordinates":[-71.092209,42.363982],"type":"Point"}
}