{
  "type": "Feature",
  "properties": {
    "iso:country":"US",
    "sg:address":"883 Main St",
    "sg:city":"Winchester",
    "sg:classifiers":[
        {
            "category":"Restaurant",
            "type":"Food & Drink"
        }
    ],
    "sg:phone":"+1 781 729 5555",
    "sg:postcode":"01890",
    "sg:province":"MA",
    "sg:tags":[
        "pizza"
    ],
    "wof:name":"Andrea's Pizza",
    "wof:placetype":"venue"
},
  "geometry": {"coordinates":[-71.142303,42.4618],"type":"Point"}
}