{
  "type": "Feature",
  "properties": {
    "iso:country":"US",
    "sg:address":"1 Fall St",
    "sg:city":"Fall River",
    "sg:classifiers":[
        {
            "category":"Organizations",
            "subcategory":"Non-profit Organization",
            "type":"Services"
        }
    ],
    "sg:phone":"+1 508 675 1302",
    "sg:postcode":"02769",
    "sg:province":"MA",
    "wof:name":"Bristol Regional Employment",
    "wof:placetype":"venue"
},
  "geometry": {"coordinates":[-71.290869,41.779416],"type":"Point"}
}