{
  "type": "Feature",
  "properties": {
    "addr:full": "27 Congress St Salem MA 01970",
    "addr:housenumber": "27",
    "addr:postcode": "01970",
    "addr:street": "Congress St",
    "iso:country": "US",
    "sg:address": "27 Congress St",
    "sg:city": "Salem",
    "sg:classifiers": [
      {
        "category": "Professional",
        "subcategory": "Lawyer \u0026 Legal Services",
        "type": "Services"
      }
    ],
    "sg:phone": "+1 978 745 0914",
    "sg:postcode": "01970",
    "sg:province": "MA",
    "sg:tags": [
      "attorney"
    ],
    "wof:name": "Alan S Pierce \u0026 Assoc",
    "wof:placetype": "venue"
  },
  "geometry": {"coordinates":[-70.889406,42.518307],"type":"Point"}
}
