{
  "type": "Feature",
  "properties": {
    "addr:full":"13 County Rd North Falmouth MA 02556",
    "addr:housenumber":"13",
    "addr:postcode":"02556",
    "addr:street":"County Rd North",
    "iso:country":"US",
    "sg:address":"13 County Rd",
    "sg:city":"North Falmouth",
    "sg:classifiers":[
        {
            "category":"Personal",
            "type":"Services"
        },
        {
            "category":"Retail",
            "subcategory":"Laundry & Dry Cleaning",
            "type":"Services"
        }
    ],
    "sg:phone":"+1 508 563 6052",
    "sg:postcode":"02556",
    "sg:province":"MA",
    "sg:tags":[
        "sewing",
        "alteration"
    ],
    "wof:name":"Cataumet Dry Cleaners",
    "wof:placetype":"venue"
},
  "geometry": {"coordinates":[-70.6147,41.647701],"type":"Point"}
}