{
  "type": "Feature",
  "properties": {
    "iso:country":"US",
    "sg:address":"53 Belleville Rd",
    "sg:city":"New Bedford",
    "sg:classifiers":[
        {
            "category":"Food & Beverages",
            "subcategory":"Meat & Fish",
            "type":"Retail Goods"
        }
    ],
    "sg:phone":"+1 508 997 0538",
    "sg:postcode":"02745",
    "sg:province":"MA",
    "wof:name":"New Bedford Salchicharia",
    "wof:placetype":"venue"
},
  "geometry": {"coordinates":[-70.924266,41.669148],"type":"Point"}
}