{
  "type": "Feature",
  "properties": {
    "iso:country":"US",
    "sg:address":"12 Randolph St",
    "sg:city":"Newton",
    "sg:classifiers":[
        {
            "category":"Professional",
            "subcategory":"Business Services",
            "type":"Services"
        }
    ],
    "sg:phone":"+1 617 332 2487",
    "sg:postcode":"02461",
    "sg:province":"MA",
    "sg:tags":[
        "organizing"
    ],
    "wof:name":"All Together Now",
    "wof:placetype":"venue"
},
  "geometry": {"coordinates":[-71.215664,42.32118],"type":"Point"}
}