{
  "type": "Feature",
  "properties": {
    "addr:full": "15 Gleason St Clarksburg MA 01247",
    "addr:housenumber": "15",
    "addr:postcode": "01247",
    "addr:street": "Gleason St",
    "iso:country": "US",
    "sg:address": "15 Gleason St",
    "sg:city": "Clarksburg",
    "sg:classifiers": [
      {
        "category": "Personal",
        "subcategory": "Beauty Salon",
        "type": "Services"
      }
    ],
    "sg:phone": "+1 413 664 9079",
    "sg:postcode": "01247",
    "sg:province": "MA",
    "wof:name": "Partings",
    "wof:placetype": "venue"
  },
  "geometry": {"coordinates":[-73.110626,42.713532],"type":"Point"}
}
