{
  "type": "Feature",
  "properties": {
    "addr:full":"179 W Central St Natick MA 01760",
    "addr:housenumber":"179",
    "addr:postcode":"01760",
    "addr:street":"W Central St",
    "iso:country":"US",
    "sg:address":"179 W Central St",
    "sg:city":"Natick",
    "sg:classifiers":[
        {
            "category":"Restaurant",
            "type":"Food & Drink"
        }
    ],
    "sg:menulink":"http://www.allmenus.com/ma/natick/49208-3-lucky-stars/menu/",
    "sg:phone":"+1 508 653 5272",
    "sg:postcode":"01760",
    "sg:province":"MA",
    "sg:tags":[
        "asian",
        "chinese"
    ],
    "wof:name":"3 Lucky Stars",
    "wof:placetype":"venue"
},
  "geometry": {"coordinates":[-71.38038899999999,42.282492],"type":"Point"}
}