{
  "type": "Feature",
  "properties": {
    "addr:full": "135 Ward St Revere MA 02151",
    "addr:housenumber": "135",
    "addr:postcode": "02151",
    "addr:street": "Ward St",
    "iso:country": "US",
    "sg:address": "135 Ward St",
    "sg:city": "Revere",
    "sg:classifiers": [
      {
        "category": "Building \u0026 Trades",
        "subcategory": "Construction",
        "type": "Services"
      }
    ],
    "sg:phone": "+1 781 485 0418",
    "sg:postcode": "02151",
    "sg:province": "MA",
    "sg:tags": [
      "resurfacing",
      "floor",
      "laying",
      "refinishing",
      "contractor"
    ],
    "wof:name": "Frank's Hardwood Floors",
    "wof:placetype": "venue"
  },
  "geometry": {"coordinates":[-71.008161,42.425305],"type":"Point"}
}
