{
  "type": "Feature",
  "properties": {
    "iso:country":"US",
    "sg:address":"164 N Main St",
    "sg:city":"Natick",
    "sg:classifiers":[
        {
            "category":"Professional",
            "subcategory":"Accounting & Tax Preparation",
            "type":"Services"
        }
    ],
    "sg:phone":"+1 508 653 0045",
    "sg:postcode":"01760",
    "sg:province":"MA",
    "sg:tags":[
        "return",
        "filing"
    ],
    "wof:name":"C K Tax Svc",
    "wof:placetype":"venue"
},
  "geometry": {"coordinates":[-71.358921,42.296599],"type":"Point"}
}