{
  "type": "Feature",
  "properties": {
    "addr:full": "164 N Main St Natick MA 01760",
    "addr:housenumber": "164",
    "addr:postcode": "01760",
    "addr:street": "N Main St",
    "iso:country": "US",
    "sg:address": "164 N Main St",
    "sg:city": "Natick",
    "sg:classifiers": [
      {
        "category": "Professional",
        "subcategory": "Accounting \u0026 Tax Preparation",
        "type": "Services"
      }
    ],
    "sg:phone": "+1 508 653 0045",
    "sg:postcode": "01760",
    "sg:province": "MA",
    "sg:tags": [
      "return",
      "filing"
    ],
    "wof:name": "C K Tax Svc",
    "wof:placetype": "venue"
  },
  "geometry": {"coordinates":[-71.358921,42.296599],"type":"Point"}
}
