{
  "type": "Feature",
  "properties": {
    "iso:country":"US",
    "sg:address":"81 Hadley St",
    "sg:city":"South Hadley",
    "sg:classifiers":[
        {
            "category":"Professional",
            "subcategory":"Management & Consulting",
            "type":"Services"
        }
    ],
    "sg:phone":"+1   ",
    "sg:postcode":"01075",
    "sg:province":"MA",
    "sg:tags":[
        "public",
        "relations"
    ],
    "wof:name":"Sales Tech Corp",
    "wof:placetype":"venue"
},
  "geometry": {"coordinates":[-72.579201,42.260949],"type":"Point"}
}