{
  "type": "Feature",
  "properties": {
    "addr:full": "9 Bicknell Rd Weymouth MA 02191",
    "addr:housenumber": "9",
    "addr:postcode": "02191",
    "addr:street": "Bicknell Rd",
    "iso:country": "US",
    "sg:address": "9 Bicknell Rd",
    "sg:city": "Weymouth",
    "sg:classifiers": [
      {
        "category": "Professional",
        "subcategory": "Lawyer \u0026 Legal Services",
        "type": "Services"
      }
    ],
    "sg:phone": "+1 781 331 0340",
    "sg:postcode": "02191",
    "sg:province": "MA",
    "sg:tags": [
      "attorney"
    ],
    "wof:name": "Elizabeth Cusick",
    "wof:placetype": "venue"
  },
  "geometry": {"coordinates":[-70.955026,42.246614],"type":"Point"}
}
