{
  "type": "Feature",
  "properties": {
    "addr:full": "884 Washington St Norwood MA 02062",
    "addr:housenumber": "884",
    "addr:postcode": "02062",
    "addr:street": "Washington St",
    "iso:country": "US",
    "sg:address": "884 Washington St",
    "sg:city": "Norwood",
    "sg:classifiers": [
      {
        "category": "Retail",
        "subcategory": "Laundry \u0026 Dry Cleaning",
        "type": "Services"
      }
    ],
    "sg:phone": "+1 781 769 5549",
    "sg:postcode": "02062",
    "sg:province": "MA",
    "wof:name": "Rama Dry Cleaners \u0026 Tailors",
    "wof:placetype": "venue"
  },
  "geometry": {"coordinates":[-71.203003,42.186798],"type":"Point"}
}
