{
  "type": "Feature",
  "properties": {
    "addr:full": "11 Parker Ct Gloucester MA 01930",
    "addr:housenumber": "11",
    "addr:postcode": "01930",
    "addr:street": "Parker Ct",
    "iso:country": "US",
    "sg:address": "11 Parker Ct",
    "sg:city": "Gloucester",
    "sg:classifiers": [
      {
        "category": "Personal",
        "type": "Services"
      }
    ],
    "sg:phone": "+1 978 282 1401",
    "sg:postcode": "01930",
    "sg:province": "MA",
    "sg:tags": [
      "counseling"
    ],
    "wof:name": "Gloucester Fishermen Wives",
    "wof:placetype": "venue"
  },
  "geometry": {"coordinates":[-70.648698,42.616908],"type":"Point"}
}
