{
  "type": "Feature",
  "properties": {
    "addr:full": "604 Main St Shrewsbury MA 01545",
    "addr:housenumber": "604",
    "addr:postcode": "01545",
    "addr:street": "Main St",
    "iso:country": "US",
    "sg:address": "604 Main St",
    "sg:city": "Shrewsbury",
    "sg:classifiers": [
      {
        "category": "Health Services",
        "subcategory": "Doctor",
        "type": "Services"
      }
    ],
    "sg:phone": "+1 508 842 6502",
    "sg:postcode": "01545",
    "sg:province": "MA",
    "sg:tags": [
      "physician",
      "surgeon"
    ],
    "wof:name": "U Mass Memorial Medical Group",
    "wof:placetype": "venue"
  },
  "geometry": {"coordinates":[-71.712591,42.296584],"type":"Point"}
}
