{
  "type": "Feature",
  "properties": {
    "iso:country":"US",
    "sg:address":"20 Thoreau Dr",
    "sg:city":"South Easton",
    "sg:classifiers":[
        {
            "category":"Professional",
            "subcategory":"Computer Services",
            "type":"Services"
        }
    ],
    "sg:phone":"+1   ",
    "sg:postcode":"02375",
    "sg:province":"MA",
    "sg:tags":[
        "related",
        "programing",
        "custom"
    ],
    "wof:name":"Qlogic Corporation",
    "wof:placetype":"venue"
},
  "geometry": {"coordinates":[-71.142562,42.013912],"type":"Point"}
}