{
  "type": "Feature",
  "properties": {
    "addr:full":"134 S 2nd St New Bedford MA 02740",
    "addr:housenumber":"134",
    "addr:postcode":"02740",
    "addr:street":"S 2Nd St",
    "iso:country":"US",
    "sg:address":"134 S 2nd St",
    "sg:city":"New Bedford",
    "sg:classifiers":[
        {
            "category":"Real Estate",
            "subcategory":"Real Estate Agent",
            "type":"Services"
        }
    ],
    "sg:phone":"+1 508 997 4829",
    "sg:postcode":"02740",
    "sg:province":"MA",
    "sg:tags":[
        "authorities",
        "housing"
    ],
    "wof:name":"New Bedford Housing Authority",
    "wof:placetype":"venue"
},
  "geometry": {"coordinates":[-70.923305,41.630232],"type":"Point"}
}