{
  "type": "Feature",
  "properties": {
    "iso:country":"US",
    "sg:address":"19 W Central St",
    "sg:city":"Natick",
    "sg:classifiers":[
        {
            "category":"Insurance",
            "subcategory":"Insurance Agent",
            "type":"Services"
        }
    ],
    "sg:phone":"+1 508 655 1112",
    "sg:postcode":"01760",
    "sg:province":"MA",
    "sg:website":"http://www.connellcurley.com",
    "wof:name":"Connell & Curley Insurance",
    "wof:placetype":"venue"
},
  "geometry": {"coordinates":[-71.349245,42.283551],"type":"Point"}
}