{
  "type": "Feature",
  "properties": {
    "iso:country":"US",
    "sg:address":"205 Industrial Ave E",
    "sg:city":"Lowell",
    "sg:classifiers":[
        {
            "category":"Building & Trades",
            "subcategory":"Construction",
            "type":"Services"
        }
    ],
    "sg:phone":"+1 978 275 0177",
    "sg:postcode":"01852",
    "sg:province":"MA",
    "sg:tags":[
        "piping",
        "contractor"
    ],
    "sg:website":"www.gmppiping.com",
    "wof:name":"GMP Systems Inc",
    "wof:placetype":"venue"
},
  "geometry": {"coordinates":[-71.31737800000001,42.619371],"type":"Point"}
}