{
  "type": "Feature",
  "properties": {
    "addr:full": "1414 Washington St Hanover MA 02339",
    "addr:housenumber": "1414",
    "addr:postcode": "02339",
    "addr:street": "Washington St",
    "iso:country": "US",
    "sg:address": "1414 Washington St",
    "sg:city": "Hanover",
    "sg:classifiers": [
      {
        "category": "Autos \u0026 Motor Vehicles",
        "subcategory": "Auto Supplies",
        "type": "Retail Goods"
      },
      {
        "category": "Retail",
        "subcategory": "Auto Repair",
        "type": "Services"
      }
    ],
    "sg:phone": "+1 781 829 1017",
    "sg:postcode": "02339",
    "sg:province": "MA",
    "sg:tags": [
      "wheel",
      "balancing",
      "tire",
      "wheels-aligning"
    ],
    "sg:website": "http://www.townfairtire.com",
    "wof:name": "Town Fair Tire",
    "wof:placetype": "venue"
  },
  "geometry": {"coordinates":[-70.844227,42.143525],"type":"Point"}
}
