{
  "type": "Feature",
  "properties": {
    "addr:full":"2889 Cranberry Hwy East Wareham MA 02538",
    "addr:housenumber":"2889",
    "addr:postcode":"02538",
    "addr:street":"Cranberry Hwy",
    "iso:country":"US",
    "sg:address":"2889 Cranberry Hwy",
    "sg:city":"East Wareham",
    "sg:classifiers":[
        {
            "category":"Government",
            "subcategory":"Post Office",
            "type":"Public Place"
        }
    ],
    "sg:phone":"+1 508 000 1111",
    "sg:postcode":"02538",
    "sg:province":"MA",
    "wof:name":"US Post Office",
    "wof:placetype":"venue"
},
  "geometry": {"coordinates":[-70.671863,41.759949],"type":"Point"}
}