{
  "type": "Feature",
  "properties": {
    "addr:full":"366 Lowell Street Lexington MA 02420",
    "addr:housenumber":"366",
    "addr:postcode":"02420",
    "addr:street":"Lowell Street",
    "iso:country":"US",
    "sg:address":"366 Lowell Street",
    "sg:city":"Lexington",
    "sg:classifiers":[
        {
            "category":"Professional",
            "subcategory":"Lawyer & Legal Services",
            "type":"Services"
        }
    ],
    "sg:phone":"+1 781 862 0489",
    "sg:postcode":"02420",
    "sg:province":"MA",
    "wof:name":"Rockwell Susan R Lwyr",
    "wof:placetype":"venue"
},
  "geometry": {"coordinates":[-71.19788800000001,42.447669],"type":"Point"}
}