{
  "type": "Feature",
  "properties": {
    "addr:full":"145 Fairview St Lee MA 01238",
    "addr:housenumber":"145",
    "addr:postcode":"01238",
    "addr:street":"Fairview St",
    "iso:country":"US",
    "sg:address":"145 Fairview St",
    "sg:city":"Lee",
    "sg:classifiers":[
        {
            "category":"Manufacturing",
            "subcategory":"Buildings",
            "type":"Manufacturing & Wholesale Goods"
        },
        {
            "category":"Building & Trades",
            "subcategory":"Construction",
            "type":"Services"
        }
    ],
    "sg:phone":"+1 413 243 4064",
    "sg:postcode":"01238",
    "sg:province":"MA",
    "sg:tags":[
        "home",
        "builder",
        "contractor"
    ],
    "wof:name":"Gangell Construction",
    "wof:placetype":"venue"
},
  "geometry": {"coordinates":[-73.25765199999999,42.29606],"type":"Point"}
}