{
  "type": "Feature",
  "properties": {
    "iso:country":"US",
    "sg:address":"206 Claflin St",
    "sg:city":"Belmont",
    "sg:classifiers":[
        {
            "category":"Professional",
            "type":"Services"
        }
    ],
    "sg:phone":"+1   ",
    "sg:postcode":"02478",
    "sg:province":"MA",
    "wof:name":"Valerie Sutter",
    "wof:placetype":"venue"
},
  "geometry": {"coordinates":[-71.16779,42.402443],"type":"Point"}
}