{
  "type": "Feature",
  "properties": {
    "iso:country":"US",
    "sg:address":"1256 Washington St",
    "sg:city":"Weymouth",
    "sg:classifiers":[
        {
            "category":"Freight",
            "type":"Transportation"
        }
    ],
    "sg:phone":"+1 781 337 5775",
    "sg:postcode":"02189",
    "sg:province":"MA",
    "sg:tags":[
        "commercial",
        "storage"
    ],
    "wof:name":"Extra Space Storage",
    "wof:placetype":"venue"
},
  "geometry": {"coordinates":[-70.925449,42.195584],"type":"Point"}
}