{
  "type": "Feature",
  "properties": {
    "addr:full": "1256 Washington St Weymouth MA 02189",
    "addr:housenumber": "1256",
    "addr:postcode": "02189",
    "addr:street": "Washington St",
    "iso:country": "US",
    "ovtr:label": "Extra Space Storage, 1256 Washington St East Weymouth MA US",
    "ovtr:similarity": 2.739392042160034,
    "sg:address": "1256 Washington St",
    "sg:city": "Weymouth",
    "sg:classifiers": [
      {
        "category": "Freight",
        "type": "Transportation"
      }
    ],
    "sg:phone": "+1 781 337 5775",
    "sg:postcode": "02189",
    "sg:province": "MA",
    "sg:tags": [
      "commercial",
      "storage"
    ],
    "wof:name": "Extra Space Storage",
    "wof:placetype": "venue"
  },
  "geometry": {"coordinates":[-70.925449,42.195584],"type":"Point"}
}
