{
  "type": "Feature",
  "properties": {
    "addr:full":"15 Royal Crest Dr Marlborough MA 01752",
    "addr:housenumber":"15",
    "addr:postcode":"01752",
    "addr:street":"Royal Crest Dr",
    "iso:country":"US",
    "sg:address":"15 Royal Crest Dr",
    "sg:city":"Marlborough",
    "sg:classifiers":[
        {
            "category":"Shopping",
            "subcategory":"Clothing, Apparel, & Fashions",
            "type":"Retail Goods"
        }
    ],
    "sg:phone":"+1   ",
    "sg:postcode":"01752",
    "sg:province":"MA",
    "sg:tags":[
        "family"
    ],
    "wof:name":"New England Jeans Co",
    "wof:placetype":"venue"
},
  "geometry": {"coordinates":[-71.53360499999999,42.356261],"type":"Point"}
}