{
  "type": "Feature",
  "properties": {
    "addr:full": "21 Summer St Kingston MA 02364",
    "addr:housenumber": "21",
    "addr:postcode": "02364",
    "addr:street": "Summer St",
    "iso:country": "US",
    "sg:address": "21 Summer St",
    "sg:city": "Kingston",
    "sg:classifiers": [
      {
        "category": "Government",
        "subcategory": "Office",
        "type": "Public Place"
      }
    ],
    "sg:phone": "+1 781 585 0520",
    "sg:postcode": "02364",
    "sg:province": "MA",
    "sg:tags": [
      "village"
    ],
    "wof:name": "Kingston Youth Commission",
    "wof:placetype": "venue"
  },
  "geometry": {"coordinates":[-70.729389,41.99603],"type":"Point"}
}
