{
  "type": "Feature",
  "properties": {
    "iso:country":"US",
    "sg:address":"627 S Main St",
    "sg:city":"Sharon",
    "sg:classifiers":[
        {
            "category":"Professional",
            "subcategory":"Lawyer & Legal Services",
            "type":"Services"
        }
    ],
    "sg:phone":"+1 781 793 9989",
    "sg:postcode":"02067",
    "sg:province":"MA",
    "wof:name":"Posh Peddler the - CLOSED",
    "wof:placetype":"venue"
},
  "geometry": {"coordinates":[-71.21579699999999,42.099998],"type":"Point"}
}