{
  "type": "Feature",
  "properties": {
    "addr:full": "627 S Main St Sharon MA 02067",
    "addr:housenumber": "627",
    "addr:postcode": "02067",
    "addr:street": "S Main St",
    "iso:country": "US",
    "sg:address": "627 S Main St",
    "sg:city": "Sharon",
    "sg:classifiers": [
      {
        "category": "Professional",
        "subcategory": "Lawyer \u0026 Legal Services",
        "type": "Services"
      }
    ],
    "sg:phone": "+1 781 793 9989",
    "sg:postcode": "02067",
    "sg:province": "MA",
    "wof:name": "Posh Peddler the - CLOSED",
    "wof:placetype": "venue"
  },
  "geometry": {"coordinates":[-71.215797,42.099998],"type":"Point"}
}
