{
  "type": "Feature",
  "properties": {
    "addr:full": "1 River Ct Amesbury MA 01913",
    "addr:housenumber": "1",
    "addr:postcode": "01913",
    "addr:street": "River Ct",
    "iso:country": "US",
    "sg:address": "1 River Ct",
    "sg:city": "Amesbury",
    "sg:classifiers": [
      {
        "category": "Real Estate",
        "subcategory": "Real Estate Services",
        "type": "Services"
      }
    ],
    "sg:phone": "+1 978 834 0900",
    "sg:postcode": "01913",
    "sg:province": "MA",
    "sg:tags": [
      "management",
      "vacancy",
      "apartment",
      "listing",
      "rental",
      "finder"
    ],
    "wof:name": "Residences at Riverwalk",
    "wof:placetype": "venue"
  },
  "geometry": {"coordinates":[-70.924828,42.851879],"type":"Point"}
}
