{
  "type": "Feature",
  "properties": {
    "addr:full":"603 Berkshire Ave Springfield MA 01109",
    "addr:housenumber":"603",
    "addr:postcode":"01109",
    "addr:street":"Berkshire Ave",
    "iso:country":"US",
    "sg:address":"603 Berkshire Ave",
    "sg:city":"Springfield",
    "sg:classifiers":[
        {
            "category":"Social Services",
            "type":"Services"
        }
    ],
    "sg:phone":"+1 413 732 2391",
    "sg:postcode":"01109",
    "sg:province":"MA",
    "sg:tags":[
        "organization",
        "welfare"
    ],
    "wof:name":"Robert O Morris Congregate",
    "wof:placetype":"venue"
},
  "geometry": {"coordinates":[-72.524795,42.139606],"type":"Point"}
}