{
  "type": "Feature",
  "properties": {
    "addr:full": "145 Falmouth Rd Hyannis MA 02601",
    "addr:housenumber": "145",
    "addr:postcode": "02601",
    "addr:street": "Falmouth Rd",
    "iso:country": "US",
    "sg:address": "145 Falmouth Rd",
    "sg:city": "Hyannis",
    "sg:classifiers": [
      {
        "category": "Government",
        "subcategory": "Office",
        "type": "Public Place"
      }
    ],
    "sg:phone": "+1 508 771 3190",
    "sg:postcode": "02601",
    "sg:province": "MA",
    "sg:tags": [
      "federal",
      "affairs",
      "govt",
      "admin"
    ],
    "wof:name": "Us Veterans Affairs Dept",
    "wof:placetype": "venue"
  },
  "geometry": {"coordinates":[-70.292691,41.664248],"type":"Point"}
}
