{
  "type": "Feature",
  "properties": {
    "addr:full": "330 Winthrop St Taunton MA 02780",
    "addr:housenumber": "330",
    "addr:postcode": "02780",
    "addr:street": "Winthrop St",
    "iso:country": "US",
    "sg:address": "330 Winthrop St",
    "sg:city": "Taunton",
    "sg:classifiers": [
      {
        "category": "Shopping",
        "subcategory": "Books",
        "type": "Retail Goods"
      }
    ],
    "sg:phone": "+1 508 822 3074",
    "sg:postcode": "02780",
    "sg:province": "MA",
    "sg:tags": [
      "dealer"
    ],
    "wof:name": "Readmore Books",
    "wof:placetype": "venue"
  },
  "geometry": {"coordinates":[-71.123289,41.888459],"type":"Point"}
}
