{
  "type": "Feature",
  "properties": {
    "iso:country":"US",
    "sg:address":"52 Hillmans Point Way",
    "sg:city":"Vineyard Haven",
    "sg:classifiers":[
        {
            "category":"Building & Trades",
            "subcategory":"Construction",
            "type":"Services"
        }
    ],
    "sg:phone":"+1 508 693 7783",
    "sg:postcode":"02568",
    "sg:province":"MA",
    "sg:tags":[
        "contractor"
    ],
    "wof:name":"Thomas Tate",
    "wof:placetype":"venue"
},
  "geometry": {"coordinates":[-70.627135,41.458748],"type":"Point"}
}