{
  "type": "Feature",
  "properties": {
    "addr:full": "52 Hillmans Point Way Vineyard Haven MA 02568",
    "addr:housenumber": "52",
    "addr:postcode": "02568",
    "addr:street": "Hillmans Point Way",
    "iso:country": "US",
    "sg:address": "52 Hillmans Point Way",
    "sg:city": "Vineyard Haven",
    "sg:classifiers": [
      {
        "category": "Building \u0026 Trades",
        "subcategory": "Construction",
        "type": "Services"
      }
    ],
    "sg:phone": "+1 508 693 7783",
    "sg:postcode": "02568",
    "sg:province": "MA",
    "sg:tags": [
      "contractor"
    ],
    "wof:name": "Thomas Tate",
    "wof:placetype": "venue"
  },
  "geometry": {"coordinates":[-70.627135,41.458748],"type":"Point"}
}
