{
  "type": "Feature",
  "properties": {
    "addr:full": "33 Harrison Ave Boston MA 02111",
    "addr:housenumber": "33",
    "addr:postcode": "02111",
    "addr:street": "Harrison Ave",
    "iso:country": "US",
    "sg:address": "33 Harrison Ave",
    "sg:city": "Boston",
    "sg:classifiers": [
      {
        "category": "Building \u0026 Trades",
        "subcategory": "Construction",
        "type": "Services"
      }
    ],
    "sg:phone": "+1 617 338 0899",
    "sg:postcode": "02111",
    "sg:province": "MA",
    "sg:tags": [
      "general",
      "contractor"
    ],
    "wof:name": "Quality Home Construction",
    "wof:placetype": "venue"
  },
  "geometry": {"coordinates":[-71.061246,42.351575],"type":"Point"}
}
