{
  "type": "Feature",
  "properties": {
    "iso:country":"US",
    "sg:address":"161 Southbridge Rd",
    "sg:city":"Charlton",
    "sg:classifiers":[
        {
            "category":"Home & Garden",
            "subcategory":"Building Materials",
            "type":"Retail Goods"
        }
    ],
    "sg:phone":"+1 508 248 0860",
    "sg:postcode":"01507",
    "sg:province":"MA",
    "sg:tags":[
        "lumber"
    ],
    "wof:name":"A & F Instltn Tile & Hardwood",
    "wof:placetype":"venue"
},
  "geometry": {"coordinates":[-72.006725,42.123473],"type":"Point"}
}