{
  "type": "Feature",
  "properties": {
    "addr:full":"23 Gay Rd Brookfield MA 01506",
    "addr:housenumber":"23",
    "addr:postcode":"01506",
    "addr:street":"Gay Rd",
    "iso:country":"US",
    "sg:address":"23 Gay Rd",
    "sg:city":"Brookfield",
    "sg:classifiers":[
        {
            "category":"Professional",
            "type":"Services"
        }
    ],
    "sg:phone":"+1   ",
    "sg:postcode":"01506",
    "sg:province":"MA",
    "wof:name":"Yankee Pony of Americas C",
    "wof:placetype":"venue"
},
  "geometry": {"coordinates":[-72.08953099999999,42.169654],"type":"Point"}
}