{
  "type": "Feature",
  "properties": {
    "iso:country":"US",
    "sg:address":"7 Thomas Dr",
    "sg:city":"Reading",
    "sg:classifiers":[
        {
            "category":"Building & Trades",
            "subcategory":"Construction",
            "type":"Services"
        }
    ],
    "sg:phone":"+1 781 942 0911",
    "sg:postcode":"01867",
    "sg:province":"MA",
    "sg:tags":[
        "mason",
        "masonry",
        "industrial",
        "contractors-commercial",
        "contractor"
    ],
    "wof:name":"Aa Masonry",
    "wof:placetype":"venue"
},
  "geometry": {"coordinates":[-71.116513,42.557681],"type":"Point"}
}