{
  "type": "Feature",
  "properties": {
    "iso:country":"US",
    "sg:address":"153 W Main St",
    "sg:city":"Norton",
    "sg:classifiers":[
        {
            "category":"Social Services",
            "subcategory":"Child Care",
            "type":"Services"
        }
    ],
    "sg:phone":"+1 508 285 7119",
    "sg:postcode":"02766",
    "sg:province":"MA",
    "sg:tags":[
        "elementary",
        "school"
    ],
    "wof:name":"Miss Sheila's Preschool Academy",
    "wof:placetype":"venue"
},
  "geometry": {"coordinates":[-71.204803,41.959499],"type":"Point"}
}