{
  "type": "Feature",
  "properties": {
    "iso:country":"US",
    "sg:address":"349 Washington St",
    "sg:city":"Braintree",
    "sg:classifiers":[
        {
            "category":"Restaurant",
            "type":"Food & Drink"
        }
    ],
    "sg:phone":"+1 781 843 2022",
    "sg:postcode":"02184",
    "sg:province":"MA",
    "wof:name":"Kristin Restaurant",
    "wof:placetype":"venue"
},
  "geometry": {"coordinates":[-71.003925,42.220272],"type":"Point"}
}