{
  "type": "Feature",
  "properties": {
    "iso:country":"US",
    "sg:address":"310 3rd St",
    "sg:city":"Fall River",
    "sg:classifiers":[
        {
            "category":"Building & Trades",
            "subcategory":"Construction",
            "type":"Services"
        }
    ],
    "sg:phone":"+1 508 679 6171",
    "sg:postcode":"02721",
    "sg:province":"MA",
    "sg:tags":[
        "roofing",
        "contractor"
    ],
    "wof:name":"J C Roofing Co",
    "wof:placetype":"venue"
},
  "geometry": {"coordinates":[-71.156172,41.698059],"type":"Point"}
}