{
  "type": "Feature",
  "properties": {
    "addr:full":"400 Hillside Ave Needham MA 02494",
    "addr:housenumber":"400",
    "addr:postcode":"02494",
    "addr:street":"Hillside Ave",
    "iso:country":"US",
    "sg:address":"400 Hillside Ave",
    "sg:city":"Needham",
    "sg:classifiers":[
        {
            "category":"Health Services",
            "subcategory":"Doctor",
            "type":"Services"
        }
    ],
    "sg:phone":"+1 781 444 6610",
    "sg:postcode":"02494",
    "sg:province":"MA",
    "sg:tags":[
        "physician",
        "surgeon"
    ],
    "wof:name":"Eye Associates Of Needham",
    "wof:placetype":"venue"
},
  "geometry": {"coordinates":[-71.237645,42.290585],"type":"Point"}
}