{
  "type": "Feature",
  "properties": {
    "iso:country":"US",
    "sg:address":"1494 E Rodney French Blvd",
    "sg:city":"New Bedford",
    "sg:classifiers":[
        {
            "category":"Recreation",
            "type":"Entertainment"
        }
    ],
    "sg:phone":"+1 508 997 1688",
    "sg:postcode":"02744",
    "sg:province":"MA",
    "sg:tags":[
        "charter",
        "boat"
    ],
    "wof:name":"Steamship Authority",
    "wof:placetype":"venue"
},
  "geometry": {"coordinates":[-70.906307,41.610714],"type":"Point"}
}