{
  "type": "Feature",
  "properties": {
    "addr:full": "594 Columbia Rd Ste 302 Dorchester MA 02125",
    "addr:housenumber": "594",
    "addr:postcode": "02125",
    "addr:street": "Columbia Rd Ste 302",
    "iso:country": "US",
    "sg:address": "594 Columbia Rd Ste 302",
    "sg:city": "Dorchester",
    "sg:classifiers": [
      {
        "category": "Government",
        "subcategory": "City Hall",
        "type": "Public Place"
      }
    ],
    "sg:phone": "+1 617 265 0363",
    "sg:postcode": "02125",
    "sg:province": "MA",
    "sg:website": "www.uphamscorner.org",
    "wof:name": "Upham Corner Main Street",
    "wof:placetype": "venue"
  },
  "geometry": {"coordinates":[-71.064796,42.317299],"type":"Point"}
}
