{
  "type": "Feature",
  "properties": {
    "iso:country":"US",
    "sg:address":"3 Centre Pl",
    "sg:city":"Boston",
    "sg:classifiers":[
        {
            "category":"Banks & Credit Unions",
            "subcategory":"Bank",
            "type":"Services"
        }
    ],
    "sg:phone":"+1 617 000 1111",
    "sg:postcode":"02124",
    "sg:province":"MA",
    "wof:name":"Bank Of America",
    "wof:placetype":"venue"
},
  "geometry": {"coordinates":[-71.064032,42.293592],"type":"Point"}
}