{
  "type": "Feature",
  "properties": {
    "addr:full": "139 Mattapoisett Neck Rd Mattapoisett MA 02739",
    "addr:housenumber": "139",
    "addr:postcode": "02739",
    "addr:street": "Mattapoisett Neck Rd",
    "iso:country": "US",
    "sg:address": "139 Mattapoisett Neck Rd",
    "sg:city": "Mattapoisett",
    "sg:classifiers": [
      {
        "category": "Manufacturing",
        "subcategory": "Chemicals \u0026 Compounds",
        "type": "Manufacturing \u0026 Wholesale Goods"
      }
    ],
    "sg:phone": "+1 508 758 2809",
    "sg:postcode": "02739",
    "sg:province": "MA",
    "sg:tags": [
      "electrolysis"
    ],
    "wof:name": "Gayle Jarvis Electrolysis",
    "wof:placetype": "venue"
  },
  "geometry": {"coordinates":[-70.810148,41.631829],"type":"Point"}
}
