{
  "type": "Feature",
  "properties": {
    "iso:country":"US",
    "sg:address":"175 Bedford St Ste 6",
    "sg:city":"Lexington",
    "sg:classifiers":[
        {
            "category":"Professional",
            "subcategory":"Management & Consulting",
            "type":"Services"
        },
        {
            "category":"Professional",
            "subcategory":"Business Services",
            "type":"Services"
        }
    ],
    "sg:phone":"+1 781 863 1222",
    "sg:postcode":"02420",
    "sg:province":"MA",
    "sg:tags":[
        "consultant",
        "coach"
    ],
    "sg:website":"http://www.consultingresources.net",
    "wof:name":"Consulting Resources Corporation",
    "wof:placetype":"venue"
},
  "geometry": {"coordinates":[-71.237729,42.458734],"type":"Point"}
}