{
  "type": "Feature",
  "properties": {
    "addr:full":"218 E Main St Avon MA 02322",
    "addr:housenumber":"218",
    "addr:postcode":"02322",
    "addr:street":"E Main St",
    "iso:country":"US",
    "sg:address":"218 E Main St",
    "sg:city":"Avon",
    "sg:classifiers":[
        {
            "category":"Banks & Credit Unions",
            "subcategory":"Bank",
            "type":"Services"
        }
    ],
    "sg:phone":"+1 508 583 2633",
    "sg:postcode":"02322",
    "sg:province":"MA",
    "sg:tags":[
        "loan",
        "real estate"
    ],
    "wof:name":"Lenders Capital Corp",
    "wof:placetype":"venue"
},
  "geometry": {"coordinates":[-71.03534999999999,42.125071],"type":"Point"}
}