{
  "type": "Feature",
  "properties": {
    "iso:country":"US",
    "sg:address":"233 Wilbraham St",
    "sg:city":"Palmer",
    "sg:classifiers":[
        {
            "category":"Restaurant",
            "type":"Food & Drink"
        }
    ],
    "sg:phone":"+1 413 283 3553",
    "sg:postcode":"01069",
    "sg:province":"MA",
    "wof:name":"Dee's Diner",
    "wof:placetype":"venue"
},
  "geometry": {"coordinates":[-72.358217,42.1594],"type":"Point"}
}