{
  "type": "Feature",
  "properties": {
    "iso:country":"US",
    "sg:address":"9 Teasdale Cir",
    "sg:city":"Nantucket",
    "sg:classifiers":[
        {
            "category":"Manufacturing",
            "subcategory":"Building Materials",
            "type":"Manufacturing & Wholesale Goods"
        }
    ],
    "sg:phone":"+1 508 228 8679",
    "sg:postcode":"02554",
    "sg:province":"MA",
    "wof:name":"Bradford Fleming Mill Works",
    "wof:placetype":"venue"
},
  "geometry": {"coordinates":[-70.06145600000001,41.262747],"type":"Point"}
}