{
  "type": "Feature",
  "properties": {
    "addr:full":"89 Bethany Rd Framingham MA 01702",
    "addr:housenumber":"89",
    "addr:postcode":"01702",
    "addr:street":"Bethany Rd",
    "iso:country":"US",
    "sg:address":"89 Bethany Rd",
    "sg:city":"Framingham",
    "sg:classifiers":[
        {
            "category":"Social Services",
            "type":"Services"
        }
    ],
    "sg:phone":"+1 508 370 3968",
    "sg:postcode":"01702",
    "sg:province":"MA",
    "sg:tags":[
        "organization",
        "welfare"
    ],
    "wof:name":"Bethany Hill School Program",
    "wof:placetype":"venue"
},
  "geometry": {"coordinates":[-71.43086099999999,42.264828],"type":"Point"}
}