{
  "type": "Feature",
  "properties": {
    "addr:full":"68 Main St Falmouth MA 02540",
    "addr:housenumber":"68",
    "addr:postcode":"02540",
    "addr:street":"Main St",
    "iso:country":"US",
    "sg:address":"68 Main St",
    "sg:city":"Falmouth",
    "sg:classifiers":[
        {
            "category":"Education",
            "subcategory":"School",
            "type":"Public Place"
        }
    ],
    "sg:phone":"+1 508 548 2804",
    "sg:postcode":"02540",
    "sg:province":"MA",
    "wof:name":"Little Harbor Montessori Schl",
    "wof:placetype":"venue"
},
  "geometry": {"coordinates":[-70.61915399999999,41.554111],"type":"Point"}
}