{
  "type": "Feature",
  "properties": {
    "iso:country":"US",
    "sg:address":"352 High St",
    "sg:city":"Holyoke",
    "sg:classifiers":[
        {
            "category":"Shopping",
            "subcategory":"Clothing, Apparel, & Fashions",
            "type":"Retail Goods"
        }
    ],
    "sg:phone":"+1 413 533 3774",
    "sg:postcode":"01040",
    "sg:province":"MA",
    "sg:tags":[
        "shop",
        "bridal"
    ],
    "wof:name":"Lorraine's Fashion Showcase",
    "wof:placetype":"venue"
},
  "geometry": {"coordinates":[-72.609559,42.205022],"type":"Point"}
}