{
  "type": "Feature",
  "properties": {
    "addr:full": "352 High St Holyoke MA 01040",
    "addr:housenumber": "352",
    "addr:postcode": "01040",
    "addr:street": "High St",
    "iso:country": "US",
    "sg:address": "352 High St",
    "sg:city": "Holyoke",
    "sg:classifiers": [
      {
        "category": "Shopping",
        "subcategory": "Clothing, Apparel, \u0026 Fashions",
        "type": "Retail Goods"
      }
    ],
    "sg:phone": "+1 413 533 3774",
    "sg:postcode": "01040",
    "sg:province": "MA",
    "sg:tags": [
      "shop",
      "bridal"
    ],
    "wof:name": "Lorraine's Fashion Showcase",
    "wof:placetype": "venue"
  },
  "geometry": {"coordinates":[-72.609559,42.205022],"type":"Point"}
}
