{
  "type": "Feature",
  "properties": {
    "iso:country":"US",
    "sg:address":"381 Main St",
    "sg:city":"Tewksbury",
    "sg:classifiers":[
        {
            "category":"Health Services",
            "subcategory":"Doctor",
            "type":"Services"
        }
    ],
    "sg:phone":"+1 978 640 1114",
    "sg:postcode":"01876",
    "sg:province":"MA",
    "sg:tags":[
        "dentist"
    ],
    "wof:name":"Boutselis Family Dental Care",
    "wof:placetype":"venue"
},
  "geometry": {"coordinates":[-71.260654,42.620871],"type":"Point"}
}