{
  "type": "Feature",
  "properties": {
    "addr:full": "381 Main St Tewksbury MA 01876",
    "addr:housenumber": "381",
    "addr:postcode": "01876",
    "addr:street": "Main St",
    "iso:country": "US",
    "ovtr:label": "Boutselis Family Dental Care, 381 Main St Tewksbury MA US",
    "ovtr:similarity": 2.183779001235962,
    "sg:address": "381 Main St",
    "sg:city": "Tewksbury",
    "sg:classifiers": [
      {
        "category": "Health Services",
        "subcategory": "Doctor",
        "type": "Services"
      }
    ],
    "sg:phone": "+1 978 640 1114",
    "sg:postcode": "01876",
    "sg:province": "MA",
    "sg:tags": [
      "dentist"
    ],
    "wof:name": "Boutselis Family Dental Care",
    "wof:placetype": "venue"
  },
  "geometry": {"coordinates":[-71.260654,42.620871],"type":"Point"}
}
