{
  "type": "Feature",
  "properties": {
    "addr:full": "1658 Falmouth Rd Centerville MA 02632",
    "addr:housenumber": "1658",
    "addr:postcode": "02632",
    "addr:street": "Falmouth Rd",
    "iso:country": "US",
    "ovtr:label": "Sassy Nails, 1658 Falmouth Rd Centerville MA US",
    "ovtr:similarity": 2.2136800289154053,
    "sg:address": "1658 Falmouth Rd",
    "sg:city": "Centerville",
    "sg:classifiers": [
      {
        "category": "Personal",
        "subcategory": "Nail Salon",
        "type": "Services"
      }
    ],
    "sg:phone": "+1 508 862 0237",
    "sg:postcode": "02632",
    "sg:province": "MA",
    "wof:name": "Sassy Nails",
    "wof:placetype": "venue"
  },
  "geometry": {"coordinates":[-70.349998,41.657101],"type":"Point"}
}
