{
  "type": "Feature",
  "properties": {
    "iso:country":"US",
    "sg:address":"1658 Falmouth Rd",
    "sg:city":"Centerville",
    "sg:classifiers":[
        {
            "category":"Personal",
            "subcategory":"Nail Salon",
            "type":"Services"
        }
    ],
    "sg:phone":"+1 508 862 0237",
    "sg:postcode":"02632",
    "sg:province":"MA",
    "wof:name":"Sassy Nails",
    "wof:placetype":"venue"
},
  "geometry": {"coordinates":[-70.349998,41.657101],"type":"Point"}
}