{
  "type": "Feature",
  "properties": {
    "iso:country":"US",
    "sg:address":"20 Riverside Dr",
    "sg:city":"Wrentham",
    "sg:classifiers":[
        {
            "category":"Building & Trades",
            "subcategory":"Construction",
            "type":"Services"
        }
    ],
    "sg:phone":"+1   ",
    "sg:postcode":"02093",
    "sg:province":"MA",
    "sg:tags":[
        "carpentry",
        "contractor"
    ],
    "wof:name":"Richard Duquette",
    "wof:placetype":"venue"
},
  "geometry": {"coordinates":[-71.348319,42.053447],"type":"Point"}
}