{
  "type": "Feature",
  "properties": {
    "iso:country":"US",
    "sg:address":"255 Mohawk Trl",
    "sg:city":"Greenfield",
    "sg:classifiers":[
        {
            "category":"Shopping",
            "subcategory":"Computers & Home Electronics",
            "type":"Retail Goods"
        }
    ],
    "sg:phone":"+1 413 772 2912",
    "sg:postcode":"01301",
    "sg:province":"MA",
    "sg:tags":[
        "equipment",
        "dealer"
    ],
    "wof:name":"Radio Shack",
    "wof:placetype":"venue"
},
  "geometry": {"coordinates":[-72.627549,42.586763],"type":"Point"}
}