{
  "type": "Feature",
  "properties": {
    "iso:country":"US",
    "sg:address":"1485 Middlesex St",
    "sg:city":"Lowell",
    "sg:classifiers":[
        {
            "category":"Retail",
            "subcategory":"Auto Repair",
            "type":"Services"
        }
    ],
    "sg:phone":"+1 978 934 0773",
    "sg:postcode":"01851",
    "sg:province":"MA",
    "sg:tags":[
        "repairing",
        "automobile"
    ],
    "wof:name":"Speedee Oil Change & Tune Up",
    "wof:placetype":"venue"
},
  "geometry": {"coordinates":[-71.345268,42.637698],"type":"Point"}
}