{
  "type": "Feature",
  "properties": {
    "addr:full": "1485 Middlesex St Lowell MA 01851",
    "addr:housenumber": "1485",
    "addr:postcode": "01851",
    "addr:street": "Middlesex St",
    "iso:country": "US",
    "sg:address": "1485 Middlesex St",
    "sg:city": "Lowell",
    "sg:classifiers": [
      {
        "category": "Retail",
        "subcategory": "Auto Repair",
        "type": "Services"
      }
    ],
    "sg:phone": "+1 978 934 0773",
    "sg:postcode": "01851",
    "sg:province": "MA",
    "sg:tags": [
      "repairing",
      "automobile"
    ],
    "wof:name": "Speedee Oil Change \u0026 Tune Up",
    "wof:placetype": "venue"
  },
  "geometry": {"coordinates":[-71.345268,42.637698],"type":"Point"}
}
