{
  "type": "Feature",
  "properties": {
    "addr:full": "1 Lan Dr Westford MA 01886",
    "addr:housenumber": "1",
    "addr:postcode": "01886",
    "addr:street": "Lan Dr",
    "iso:country": "US",
    "sg:address": "1 Lan Dr",
    "sg:city": "Westford",
    "sg:classifiers": [
      {
        "category": "Restaurant",
        "type": "Food \u0026 Drink"
      }
    ],
    "sg:menulink": "http://www.allmenus.com/ma/westford/49201-bamboo/menu/",
    "sg:phone": "+1 978 589 9666",
    "sg:postcode": "01886",
    "sg:province": "MA",
    "sg:tags": [
      "asian",
      "chinese"
    ],
    "wof:name": "Bamboo",
    "wof:placetype": "venue"
  },
  "geometry": {"coordinates":[-71.430498,42.560127],"type":"Point"}
}
