{
  "type": "Feature",
  "properties": {
    "iso:country":"US",
    "sg:address":"8 Winchester Pl",
    "sg:city":"Winchester",
    "sg:classifiers":[
        {
            "category":"Health Services",
            "subcategory":"Doctor",
            "type":"Services"
        }
    ],
    "sg:phone":"+1 781 729 1810",
    "sg:postcode":"01890",
    "sg:province":"MA",
    "sg:tags":[
        "medicine",
        "practice",
        "internal",
        "family"
    ],
    "wof:name":"Kerouz Nada MD",
    "wof:placetype":"venue"
},
  "geometry": {"coordinates":[-71.13629899999999,42.452801],"type":"Point"}
}