{
  "type": "Feature",
  "properties": {
    "addr:full":"105 Edward Kelleher Dr Stoughton MA 02072",
    "addr:housenumber":"105",
    "addr:postcode":"02072",
    "addr:street":"Edward Kelleher Dr",
    "iso:country":"US",
    "sg:address":"105 Edward Kelleher Dr",
    "sg:city":"Stoughton",
    "sg:classifiers":[
        {
            "category":"Landmark",
            "subcategory":"Tourist Information",
            "type":"Public Place"
        }
    ],
    "sg:phone":"+1 781 344 9029",
    "sg:postcode":"02072",
    "sg:province":"MA",
    "sg:tags":[
        "attraction"
    ],
    "wof:name":"Holyland Workshops Inc",
    "wof:placetype":"venue"
},
  "geometry": {"coordinates":[-71.111874,42.109995],"type":"Point"}
}