{
  "type": "Feature",
  "properties": {
    "addr:full": "44 Bromfield St Boston MA 02108",
    "addr:housenumber": "44",
    "addr:postcode": "02108",
    "addr:street": "Bromfield St",
    "iso:country": "US",
    "sg:address": "44 Bromfield St",
    "sg:city": "Boston",
    "sg:classifiers": [
      {
        "category": "Professional",
        "subcategory": "Employment Agencies",
        "type": "Services"
      }
    ],
    "sg:phone": "+1 617 542 0260",
    "sg:postcode": "02108",
    "sg:province": "MA",
    "sg:website": "www.carneysandoe.com/",
    "wof:name": "Carney Sandoe \u0026 Associates",
    "wof:placetype": "venue"
  },
  "geometry": {"coordinates":[-71.06071,42.35691],"type":"Point"}
}
