{
  "type": "Feature",
  "properties": {
    "addr:full":"29 South St Medfield MA 02052",
    "addr:housenumber":"29",
    "addr:postcode":"02052",
    "addr:street":"South St",
    "iso:country":"US",
    "sg:address":"29 South St",
    "sg:city":"Medfield",
    "sg:classifiers":[
        {
            "category":"Building & Trades",
            "subcategory":"Plumbing",
            "type":"Services"
        }
    ],
    "sg:phone":"+1 508 359 6099",
    "sg:postcode":"02052",
    "sg:province":"MA",
    "sg:tags":[
        "plumbing",
        "contractor"
    ],
    "wof:name":"Medfield Plumbing & Heating",
    "wof:placetype":"venue"
},
  "geometry": {"coordinates":[-71.30105,42.18515],"type":"Point"}
}