{
  "type": "Feature",
  "properties": {
    "iso:country":"US",
    "sg:address":"131 Mammoth Rd",
    "sg:city":"Lowell",
    "sg:classifiers":[
        {
            "category":"Education",
            "subcategory":"School",
            "type":"Public Place"
        }
    ],
    "sg:phone":"+1 978 937 2871",
    "sg:postcode":"01854",
    "sg:province":"MA",
    "wof:name":"Mc Avinnue Elementary School",
    "wof:placetype":"venue"
},
  "geometry": {"coordinates":[-71.335583,42.652522],"type":"Point"}
}