{
  "type": "Feature",
  "properties": {
    "addr:full": "131 Mammoth Rd Lowell MA 01854",
    "addr:housenumber": "131",
    "addr:postcode": "01854",
    "addr:street": "Mammoth Rd",
    "iso:country": "US",
    "ovtr:label": "Mc Avinnue Elementary School, 131 Mammoth Rd Lowell MA US",
    "ovtr:similarity": 2.4612479209899902,
    "sg:address": "131 Mammoth Rd",
    "sg:city": "Lowell",
    "sg:classifiers": [
      {
        "category": "Education",
        "subcategory": "School",
        "type": "Public Place"
      }
    ],
    "sg:phone": "+1 978 937 2871",
    "sg:postcode": "01854",
    "sg:province": "MA",
    "wof:name": "Mc Avinnue Elementary School",
    "wof:placetype": "venue"
  },
  "geometry": {"coordinates":[-71.335583,42.652522],"type":"Point"}
}
