{
  "type": "Feature",
  "properties": {
    "addr:full":"20 Debra Ln Framingham MA 01701",
    "addr:housenumber":"20",
    "addr:postcode":"01701",
    "addr:street":"Debra Ln",
    "iso:country":"US",
    "sg:address":"20 Debra Ln",
    "sg:city":"Framingham",
    "sg:classifiers":[
        {
            "category":"Autos & Motor Vehicles",
            "subcategory":"Auto Supplies",
            "type":"Retail Goods"
        }
    ],
    "sg:phone":"+1   ",
    "sg:postcode":"01701",
    "sg:province":"MA",
    "wof:name":"State Specialty",
    "wof:placetype":"venue"
},
  "geometry": {"coordinates":[-71.39781600000001,42.31043],"type":"Point"}
}