{
  "type": "Feature",
  "properties": {
    "iso:country":"US",
    "sg:address":"65 Main St",
    "sg:city":"Russell",
    "sg:classifiers":[
        {
            "category":"Government",
            "subcategory":"Office",
            "type":"Public Place"
        }
    ],
    "sg:phone":"+1 413 862 4707",
    "sg:postcode":"01071",
    "sg:province":"MA",
    "sg:tags":[
        "village"
    ],
    "wof:name":"Municipal Cable Television",
    "wof:placetype":"venue"
},
  "geometry": {"coordinates":[-72.85869099999999,42.189682],"type":"Point"}
}