{
  "type": "Feature",
  "properties": {
    "addr:full": "19 Woodward St Everett MA 02149",
    "addr:housenumber": "19",
    "addr:postcode": "02149",
    "addr:street": "Woodward St",
    "iso:country": "US",
    "sg:address": "19 Woodward St",
    "sg:city": "Everett",
    "sg:classifiers": [
      {
        "category": "Professional",
        "type": "Services"
      }
    ],
    "sg:phone": "+1 617 394 0427",
    "sg:postcode": "02149",
    "sg:province": "MA",
    "wof:name": "Ann Lorrey Mailings",
    "wof:placetype": "venue"
  },
  "geometry": {"coordinates":[-71.049783,42.419566],"type":"Point"}
}
