{
  "type": "Feature",
  "properties": {
    "iso:country":"US",
    "sg:address":"48 Johnson Rd",
    "sg:city":"Winchester",
    "sg:classifiers":[
        {
            "category":"Building & Trades",
            "subcategory":"Construction",
            "type":"Services"
        }
    ],
    "sg:phone":"+1   ",
    "sg:postcode":"01890",
    "sg:province":"MA",
    "sg:tags":[
        "hanging",
        "contractor"
    ],
    "wof:name":"Steven & Elaine Psiakis",
    "wof:placetype":"venue"
},
  "geometry": {"coordinates":[-71.16821299999999,42.450976],"type":"Point"}
}