{
  "type": "Feature",
  "properties": {
    "iso:country":"US",
    "sg:address":"300 TradeCenter Suite 2460",
    "sg:city":"Woburn",
    "sg:classifiers":[
        {
            "category":"Professional",
            "subcategory":"Research",
            "type":"Services"
        }
    ],
    "sg:phone":"+1 781 897 9977",
    "sg:postcode":"01801",
    "sg:province":"MA",
    "sg:website":"http://www.flexiontherapeutics.com",
    "wof:name":"Flexion Therapeutics",
    "wof:placetype":"venue"
},
  "geometry": {"coordinates":[-71.31158499999999,42.645579],"type":"Point"}
}