{
  "type": "Feature",
  "properties": {
    "addr:full": "386 Southampton Rd Westfield MA 01085",
    "addr:housenumber": "386",
    "addr:postcode": "01085",
    "addr:street": "Southampton Rd",
    "iso:country": "US",
    "sg:address": "386 Southampton Rd",
    "sg:city": "Westfield",
    "sg:classifiers": [
      {
        "category": "Retail",
        "subcategory": "Car Wash",
        "type": "Services"
      }
    ],
    "sg:phone": "+1   ",
    "sg:postcode": "01085",
    "sg:province": "MA",
    "sg:tags": [
      "carwash"
    ],
    "wof:name": "Reflections Auto Polishing",
    "wof:placetype": "venue"
  },
  "geometry": {"coordinates":[-72.726168,42.152081],"type":"Point"}
}
