{
  "type": "Feature",
  "properties": {
    "addr:full":"42 High St Ste 4 Medford MA 02155",
    "addr:housenumber":"42",
    "addr:postcode":"02155",
    "addr:street":"High St Ste 4",
    "iso:country":"US",
    "sg:address":"42 High St Ste 4",
    "sg:city":"Medford",
    "sg:classifiers":[
        {
            "category":"Shopping",
            "subcategory":"Musical Instruments",
            "type":"Retail Goods"
        }
    ],
    "sg:phone":"+1 781 405 8916",
    "sg:postcode":"02155",
    "sg:province":"MA",
    "sg:tags":[
        "guitar",
        "amplifier"
    ],
    "wof:name":"Kindermusik",
    "wof:placetype":"venue"
},
  "geometry": {"coordinates":[-71.110812,42.418554],"type":"Point"}
}