{
  "type": "Feature",
  "properties": {
    "iso:country":"US",
    "sg:address":"20 College Ln",
    "sg:city":"North Dartmouth",
    "sg:classifiers":[
        {
            "category":"Building & Trades",
            "subcategory":"Landscaping Services",
            "type":"Services"
        }
    ],
    "sg:phone":"+1 508 992 7007",
    "sg:postcode":"02747",
    "sg:province":"MA",
    "sg:tags":[
        "tree"
    ],
    "wof:name":"Speedy Tree and Stump Removal",
    "wof:placetype":"venue"
},
  "geometry": {"coordinates":[-71.001498,41.605722],"type":"Point"}
}