{
  "type": "Feature",
  "properties": {
    "addr:full": "150 Emmons St Franklin MA 02038",
    "addr:housenumber": "150",
    "addr:postcode": "02038",
    "addr:street": "Emmons St",
    "iso:country": "US",
    "sg:address": "150 Emmons St",
    "sg:city": "Franklin",
    "sg:classifiers": [
      {
        "category": "Government",
        "subcategory": "Office",
        "type": "Public Place"
      }
    ],
    "sg:phone": "+1 508 520 4929",
    "sg:postcode": "02038",
    "sg:province": "MA",
    "sg:tags": [
      "village"
    ],
    "wof:name": "Property Improvements",
    "wof:placetype": "venue"
  },
  "geometry": {"coordinates":[-71.399952,42.083638],"type":"Point"}
}
