{
  "type": "Feature",
  "properties": {
    "iso:country":"US",
    "sg:address":"20 Mount Vernon Street",
    "sg:city":"Boston",
    "sg:classifiers":[
        {
            "category":"Real Estate",
            "subcategory":"Real Estate Agent",
            "type":"Services"
        }
    ],
    "sg:phone":"+1 617 791 5663",
    "sg:postcode":"02129",
    "sg:province":"MA",
    "sg:website":"www.bostonpp.com",
    "wof:name":"Boston Portfolio Properties, LLC",
    "wof:placetype":"venue"
},
  "geometry": {"coordinates":[-71.0587,42.3753],"type":"Point"}
}