{
  "type": "Feature",
  "properties": {
    "addr:full": "6 Courthouse Ln Chelmsford MA 01824",
    "addr:housenumber": "6",
    "addr:postcode": "01824",
    "addr:street": "Courthouse Ln",
    "iso:country": "US",
    "sg:address": "6 Courthouse Ln",
    "sg:city": "Chelmsford",
    "sg:classifiers": [
      {
        "category": "Health Services",
        "subcategory": "Doctor",
        "type": "Services"
      }
    ],
    "sg:phone": "+1 978 458 5600",
    "sg:postcode": "01824",
    "sg:province": "MA",
    "sg:tags": [
      "physician",
      "surgeon"
    ],
    "wof:name": "Nashova Valley Urology",
    "wof:placetype": "venue"
  },
  "geometry": {"coordinates":[-71.357978,42.624478],"type":"Point"}
}
