{
  "type": "Feature",
  "properties": {
    "addr:full":"1 Washburn Sq Leicester MA 01524",
    "addr:housenumber":"1",
    "addr:postcode":"01524",
    "addr:street":"Washburn Sq",
    "iso:country":"US",
    "sg:address":"1 Washburn Sq",
    "sg:city":"Leicester",
    "sg:classifiers":[
        {
            "category":"Organizations",
            "subcategory":"Religious Organization",
            "type":"Services"
        }
    ],
    "sg:phone":"+1 508 892 3274",
    "sg:postcode":"01524",
    "sg:province":"MA",
    "sg:tags":[
        "church"
    ],
    "wof:name":"Leicester Federated Church",
    "wof:placetype":"venue"
},
  "geometry": {"coordinates":[-71.90594299999999,42.246812],"type":"Point"}
}