{
  "type": "Feature",
  "properties": {
    "iso:country":"US",
    "sg:address":"1 Walpole St",
    "sg:city":"Norwood",
    "sg:classifiers":[
        {
            "category":"Health Services",
            "subcategory":"Dentist",
            "type":"Services"
        }
    ],
    "sg:phone":"+1 781 762 7077",
    "sg:postcode":"02062",
    "sg:province":"MA",
    "wof:name":"Turesky Jon D PC",
    "wof:placetype":"venue"
},
  "geometry": {"coordinates":[-71.20259900000001,42.191601],"type":"Point"}
}