{
  "type": "Feature",
  "properties": {
    "iso:country":"US",
    "sg:address":"683 Westfield St",
    "sg:city":"West Springfield",
    "sg:classifiers":[
        {
            "category":"Shopping",
            "subcategory":"Hobbies, Toys, & Games",
            "type":"Retail Goods"
        }
    ],
    "sg:phone":"+1 413 214 7852",
    "sg:postcode":"01089",
    "sg:province":"MA",
    "sg:tags":[
        "supply"
    ],
    "wof:name":"Game Hunters 2",
    "wof:placetype":"venue"
},
  "geometry": {"coordinates":[-72.635897,42.103461],"type":"Point"}
}