{
  "type": "Feature",
  "properties": {
    "addr:full":"6 Vine St Webster MA 01570",
    "addr:housenumber":"6",
    "addr:postcode":"01570",
    "addr:street":"Vine St",
    "iso:country":"US",
    "sg:address":"6 Vine St",
    "sg:city":"Webster",
    "sg:classifiers":[
        {
            "category":"Real Estate",
            "subcategory":"Real Estate Agent",
            "type":"Services"
        }
    ],
    "sg:phone":"+1   ",
    "sg:postcode":"01570",
    "sg:province":"MA",
    "sg:tags":[
        "broker"
    ],
    "wof:name":"Apple Realty",
    "wof:placetype":"venue"
},
  "geometry": {"coordinates":[-71.877394,42.040843],"type":"Point"}
}