{
  "type": "Feature",
  "properties": {
    "addr:full": "335 Walnut St Exd Agawam MA 01001",
    "addr:housenumber": "335",
    "addr:postcode": "01001",
    "addr:street": "Walnut St Exd",
    "iso:country": "US",
    "sg:address": "335 Walnut St Exd",
    "sg:city": "Agawam",
    "sg:classifiers": [
      {
        "category": "Professional",
        "subcategory": "Computer Services",
        "type": "Services"
      }
    ],
    "sg:phone": "+1 413 786 0041",
    "sg:postcode": "01001",
    "sg:province": "MA",
    "sg:tags": [
      "consultant",
      "designer"
    ],
    "wof:name": "Mitem Corp",
    "wof:placetype": "venue"
  },
  "geometry": {"coordinates":[-72.629339,42.087806],"type":"Point"}
}
