{
  "type": "Feature",
  "properties": {
    "addr:full":"694 State Rd North Dartmouth MA 02747",
    "addr:housenumber":"694",
    "addr:postcode":"02747",
    "addr:street":"State Rd",
    "iso:country":"US",
    "sg:address":"694 State Rd",
    "sg:city":"North Dartmouth",
    "sg:classifiers":[
        {
            "category":"Autos & Motor Vehicles",
            "subcategory":"Boat Sales",
            "type":"Retail Goods"
        }
    ],
    "sg:phone":"+1 508 993 6120",
    "sg:postcode":"02747",
    "sg:province":"MA",
    "sg:tags":[
        "dealer",
        "sales"
    ],
    "wof:name":"Bibeau's Boat Mart",
    "wof:placetype":"venue"
},
  "geometry": {"coordinates":[-71.01696200000001,41.64019],"type":"Point"}
}