{
  "type": "Feature",
  "properties": {
    "iso:country":"US",
    "sg:address":"8 Hunton Cir",
    "sg:city":"Attleboro",
    "sg:classifiers":[
        {
            "category":"Professional",
            "subcategory":"Employment Agencies",
            "type":"Services"
        }
    ],
    "sg:phone":"+1 508 226 6735",
    "sg:postcode":"02703",
    "sg:province":"MA",
    "sg:tags":[
        "consultant",
        "search",
        "executive"
    ],
    "wof:name":"Tower Group",
    "wof:placetype":"venue"
},
  "geometry": {"coordinates":[-71.245574,41.935503],"type":"Point"}
}