{
  "type": "Feature",
  "properties": {
    "iso:country":"US",
    "sg:address":"22 Myrtle Ave",
    "sg:city":"Webster",
    "sg:classifiers":[
        {
            "category":"Professional",
            "subcategory":"Engineering",
            "type":"Services"
        }
    ],
    "sg:phone":"+1 508 949 0939",
    "sg:postcode":"01570",
    "sg:province":"MA",
    "sg:tags":[
        "engineer"
    ],
    "wof:name":"GVK Engineering & Assoc Inc",
    "wof:placetype":"venue"
},
  "geometry": {"coordinates":[-71.881024,42.047123],"type":"Point"}
}