{
  "type": "Feature",
  "properties": {
    "addr:full":"114 Waltham St Lexington MA 02421",
    "addr:housenumber":"114",
    "addr:postcode":"02421",
    "addr:street":"Waltham St",
    "iso:country":"US",
    "sg:address":"114 Waltham St",
    "sg:city":"Lexington",
    "sg:classifiers":[
        {
            "category":"Professional",
            "subcategory":"Lawyer & Legal Services",
            "type":"Services"
        }
    ],
    "sg:phone":"+1 781 862 8060",
    "sg:postcode":"02421",
    "sg:province":"MA",
    "sg:tags":[
        "attorney"
    ],
    "wof:name":"Belesi Donovan & Conroy",
    "wof:placetype":"venue"
},
  "geometry": {"coordinates":[-71.228854,42.444893],"type":"Point"}
}