{
  "type": "Feature",
  "properties": {
    "iso:country":"US",
    "sg:address":"12 Hawkes St",
    "sg:city":"Marblehead",
    "sg:classifiers":[
        {
            "category":"Insurance",
            "subcategory":"Insurance Agent",
            "type":"Services"
        }
    ],
    "sg:phone":"+1 781 631 8539",
    "sg:postcode":"01945",
    "sg:province":"MA",
    "wof:name":"D S Balser & Co Inc",
    "wof:placetype":"venue"
},
  "geometry": {"coordinates":[-70.855716,42.50001],"type":"Point"}
}