{
  "type": "Feature",
  "properties": {
    "addr:full": "112 Ball Hill Rd Berlin MA 01503",
    "addr:housenumber": "112",
    "addr:postcode": "01503",
    "addr:street": "Ball Hill Rd",
    "iso:country": "US",
    "sg:address": "112 Ball Hill Rd",
    "sg:city": "Berlin",
    "sg:classifiers": [
      {
        "category": "Professional",
        "subcategory": "Management \u0026 Consulting",
        "type": "Services"
      }
    ],
    "sg:phone": "+1 978 874 2400",
    "sg:postcode": "01503",
    "sg:province": "MA",
    "sg:tags": [
      "marketing",
      "consultant"
    ],
    "wof:name": "Take Aim",
    "wof:placetype": "venue"
  },
  "geometry": {"coordinates":[-71.668375,42.374946],"type":"Point"}
}
