{
  "type": "Feature",
  "properties": {
    "iso:country":"US",
    "sg:address":"112 Ball Hill Rd",
    "sg:city":"Berlin",
    "sg:classifiers":[
        {
            "category":"Professional",
            "subcategory":"Management & Consulting",
            "type":"Services"
        }
    ],
    "sg:phone":"+1 978 874 2400",
    "sg:postcode":"01503",
    "sg:province":"MA",
    "sg:tags":[
        "marketing",
        "consultant"
    ],
    "wof:name":"Take Aim",
    "wof:placetype":"venue"
},
  "geometry": {"coordinates":[-71.668375,42.374946],"type":"Point"}
}