{
  "type": "Feature",
  "properties": {
    "addr:full":"Fruit Boston MA 02114",
    "addr:postcode":"02114",
    "iso:country":"US",
    "sg:address":"Fruit",
    "sg:city":"Boston",
    "sg:classifiers":[
        {
            "category":"Health Services",
            "subcategory":"Doctor",
            "type":"Services"
        }
    ],
    "sg:phone":"+1 617 726 3969",
    "sg:postcode":"02114",
    "sg:province":"MA",
    "wof:name":"Kliman Bernard Dr",
    "wof:placetype":"venue"
},
  "geometry": {"coordinates":[-71.06698400000001,42.362178],"type":"Point"}
}