{
  "type": "Feature",
  "properties": {
    "addr:full": "36 2nd Street Chelsea MA 02150",
    "addr:housenumber": "36",
    "addr:postcode": "02150",
    "addr:street": "2Nd Street",
    "iso:country": "US",
    "ovtr:label": "Rancho Las Pupusas, 36 2nd St Chelsea MA US",
    "ovtr:similarity": 2.7481091022491455,
    "sg:address": "36 2nd Street",
    "sg:city": "Chelsea",
    "sg:classifiers": [
      {
        "category": "Restaurant",
        "type": "Food \u0026 Drink"
      }
    ],
    "sg:phone": "+1 617 884 1893",
    "sg:postcode": "02150",
    "sg:province": "MA",
    "wof:name": "Rancho Las Pupusas",
    "wof:placetype": "venue"
  },
  "geometry": {"coordinates":[-71.039831,42.390657],"type":"Point"}
}
