{
  "type": "Feature",
  "properties": {
    "addr:full": "220 Pine St Marshfield MA 02050",
    "addr:housenumber": "220",
    "addr:postcode": "02050",
    "addr:street": "Pine St",
    "iso:country": "US",
    "sg:address": "220 Pine St",
    "sg:city": "Marshfield",
    "sg:classifiers": [
      {
        "category": "Professional",
        "type": "Services"
      },
      {
        "category": "Shopping",
        "subcategory": "Party Supplies",
        "type": "Retail Goods"
      },
      {
        "category": "Retail",
        "subcategory": "Auto Rental",
        "type": "Services"
      },
      {
        "category": "Bus Charters",
        "type": "Transportation"
      },
      {
        "category": "Airport",
        "type": "Transportation"
      }
    ],
    "sg:phone": "+1 781 545 7551",
    "sg:postcode": "02050",
    "sg:province": "MA",
    "sg:tags": [
      "buses-charter",
      "limousine",
      "wedding"
    ],
    "sg:website": "http://www.keylimousine.net",
    "wof:name": "Key Limousine \u0026 Transportation Service",
    "wof:placetype": "venue"
  },
  "geometry": {"coordinates":[-70.750629,42.130347],"type":"Point"}
}
