{
  "type": "Feature",
  "properties": {
    "iso:country":"US",
    "sg:address":"197 8th Street",
    "sg:city":"Charlestown",
    "sg:classifiers":[
        {
            "category":"Real Estate",
            "subcategory":"Architect",
            "type":"Services"
        }
    ],
    "sg:phone":"+1 617 241 9006",
    "sg:postcode":"02129",
    "sg:province":"MA",
    "wof:name":"Ecodesign",
    "wof:placetype":"venue"
},
  "geometry": {"coordinates":[-71.051074,42.37354],"type":"Point"}
}