{
  "type": "Feature",
  "properties": {
    "iso:country":"US",
    "sg:address":"60 William St",
    "sg:city":"Wellesley",
    "sg:classifiers":[
        {
            "category":"Banks & Credit Unions",
            "subcategory":"Investment Brokerage",
            "type":"Services"
        }
    ],
    "sg:phone":"+1 781 489 1200",
    "sg:postcode":"02481",
    "sg:province":"MA",
    "wof:name":"GCC Investments LLC",
    "wof:placetype":"venue"
},
  "geometry": {"coordinates":[-71.231184,42.318485],"type":"Point"}
}