{
  "type": "Feature",
  "properties": {
    "addr:full":"10 Crane Ave East Longmeadow MA 01028",
    "addr:housenumber":"10",
    "addr:postcode":"01028",
    "addr:street":"Crane Ave",
    "iso:country":"US",
    "sg:address":"10 Crane Ave",
    "sg:city":"East Longmeadow",
    "sg:classifiers":[
        {
            "category":"Personal",
            "subcategory":"Beauty Salon",
            "type":"Services"
        }
    ],
    "sg:phone":"+1 413 525 6077",
    "sg:postcode":"01028",
    "sg:province":"MA",
    "wof:name":"New Beginnings",
    "wof:placetype":"venue"
},
  "geometry": {"coordinates":[-72.515649,42.064947],"type":"Point"}
}