{
  "type": "Feature",
  "properties": {
    "iso:country":"US",
    "sg:address":"208 Russett Rd",
    "sg:city":"Chestnut Hill",
    "sg:classifiers":[
        {
            "category":"Professional",
            "subcategory":"Management & Consulting",
            "type":"Services"
        }
    ],
    "sg:phone":"+1   ",
    "sg:postcode":"02467",
    "sg:province":"MA",
    "sg:tags":[
        "real estate"
    ],
    "wof:name":"Mohindra & Assoc Inc",
    "wof:placetype":"venue"
},
  "geometry": {"coordinates":[-71.15228500000001,42.295334],"type":"Point"}
}