{
  "type": "Feature",
  "properties": {
    "addr:full": "208 Russett Rd Chestnut Hill MA 02467",
    "addr:housenumber": "208",
    "addr:postcode": "02467",
    "addr:street": "Russett Rd",
    "iso:country": "US",
    "sg:address": "208 Russett Rd",
    "sg:city": "Chestnut Hill",
    "sg:classifiers": [
      {
        "category": "Professional",
        "subcategory": "Management \u0026 Consulting",
        "type": "Services"
      }
    ],
    "sg:phone": "+1   ",
    "sg:postcode": "02467",
    "sg:province": "MA",
    "sg:tags": [
      "real estate"
    ],
    "wof:name": "Mohindra \u0026 Assoc Inc",
    "wof:placetype": "venue"
  },
  "geometry": {"coordinates":[-71.152285,42.295334],"type":"Point"}
}
