{
  "type": "Feature",
  "properties": {
    "addr:full": "105 Dayton St Danvers MA 01923",
    "addr:housenumber": "105",
    "addr:postcode": "01923",
    "addr:street": "Dayton St",
    "iso:country": "US",
    "sg:address": "105 Dayton St",
    "sg:city": "Danvers",
    "sg:classifiers": [
      {
        "category": "Home \u0026 Garden",
        "subcategory": "Home Furnishings",
        "type": "Retail Goods"
      }
    ],
    "sg:phone": "+1   ",
    "sg:postcode": "01923",
    "sg:province": "MA",
    "wof:name": "Material Things",
    "wof:placetype": "venue"
  },
  "geometry": {"coordinates":[-70.983652,42.576913],"type":"Point"}
}
