{
  "type": "Feature",
  "properties": {
    "iso:country":"US",
    "sg:address":"105 Dayton St",
    "sg:city":"Danvers",
    "sg:classifiers":[
        {
            "category":"Home & Garden",
            "subcategory":"Home Furnishings",
            "type":"Retail Goods"
        }
    ],
    "sg:phone":"+1   ",
    "sg:postcode":"01923",
    "sg:province":"MA",
    "wof:name":"Material Things",
    "wof:placetype":"venue"
},
  "geometry": {"coordinates":[-70.98365200000001,42.576913],"type":"Point"}
}