{
  "type": "Feature",
  "properties": {
    "addr:full": "113 Conway St New Bedford MA 02740",
    "addr:housenumber": "113",
    "addr:postcode": "02740",
    "addr:street": "Conway St",
    "iso:country": "US",
    "sg:address": "113 Conway St",
    "sg:city": "New Bedford",
    "sg:classifiers": [
      {
        "category": "Restaurant",
        "type": "Food \u0026 Drink"
      }
    ],
    "sg:menulink": "http://www.allmenus.com/ma/new-bedford/131736-subway/menu/",
    "sg:phone": "+1 508 999 1911",
    "sg:postcode": "02740",
    "sg:province": "MA",
    "sg:tags": [
      "american",
      "sandwich"
    ],
    "wof:name": "Subway",
    "wof:placetype": "venue"
  },
  "geometry": {"coordinates":[-70.919375,41.626542],"type":"Point"}
}
