{
  "type": "Feature",
  "properties": {
    "iso:country":"US",
    "sg:address":"32 Quincy St Dept 1",
    "sg:city":"Cambridge",
    "sg:classifiers":[
        {
            "category":"Education",
            "subcategory":"Library",
            "type":"Public Place"
        }
    ],
    "sg:phone":"+1 617 495 3373",
    "sg:postcode":"02138",
    "sg:province":"MA",
    "sg:website":"http://www.gsd.harvard.edu",
    "wof:name":"Fine Arts Library",
    "wof:placetype":"venue"
},
  "geometry": {"coordinates":[-71.114464,42.374882],"type":"Point"}
}