{
  "type": "Feature",
  "properties": {
    "addr:full":"1 Cabot St Beverly MA 01915",
    "addr:housenumber":"1",
    "addr:postcode":"01915",
    "addr:street":"Cabot St",
    "iso:country":"US",
    "sg:address":"1 Cabot St",
    "sg:city":"Beverly",
    "sg:classifiers":[
        {
            "category":"Retail",
            "subcategory":"Repair Shop",
            "type":"Services"
        }
    ],
    "sg:phone":"+1 978 922 1416",
    "sg:postcode":"01915",
    "sg:province":"MA",
    "sg:tags":[
        "television",
        "radio"
    ],
    "wof:name":"TV Video LTD",
    "wof:placetype":"venue"
},
  "geometry": {"coordinates":[-70.886443,42.54083],"type":"Point"}
}