{
  "type": "Feature",
  "properties": {
    "iso:country":"US",
    "sg:address":"353 Washington St",
    "sg:city":"Norwell",
    "sg:classifiers":[
        {
            "category":"Health Services",
            "subcategory":"Doctor",
            "type":"Services"
        },
        {
            "category":"Health Services",
            "subcategory":"Dentist",
            "type":"Services"
        }
    ],
    "sg:phone":"+1 781 561 7400",
    "sg:postcode":"02061",
    "sg:province":"MA",
    "sg:tags":[
        "dentists-oral",
        "physician",
        "maxillofacial",
        "surgeons",
        "surgery",
        "oral",
        "surgeon"
    ],
    "wof:name":"Alikhani Kathy DR",
    "wof:placetype":"venue"
},
  "geometry": {"coordinates":[-70.86322,42.161781],"type":"Point"}
}