{
  "type": "Feature",
  "properties": {
    "iso:country":"US",
    "sg:address":"418 Woodward St",
    "sg:city":"Waban",
    "sg:classifiers":[
        {
            "category":"Retail",
            "subcategory":"Laundry & Dry Cleaning",
            "type":"Services"
        }
    ],
    "sg:phone":"+1 617 244 7905",
    "sg:postcode":"02468",
    "sg:province":"MA",
    "sg:tags":[
        "cleaners",
        "rug",
        "carpet"
    ],
    "wof:name":"Bob Wilcox Assoc",
    "wof:placetype":"venue"
},
  "geometry": {"coordinates":[-71.226647,42.326027],"type":"Point"}
}