{
  "type": "Feature",
  "properties": {
    "iso:country":"US",
    "sg:address":"71 Strong St",
    "sg:city":"Amherst",
    "sg:classifiers":[
        {
            "category":"Social Services",
            "subcategory":"Child Care",
            "type":"Services"
        }
    ],
    "sg:phone":"+1 413 549 1301",
    "sg:postcode":"01002",
    "sg:province":"MA",
    "wof:name":"Wildwood After-School Program",
    "wof:placetype":"venue"
},
  "geometry": {"coordinates":[-72.514043,42.388262],"type":"Point"}
}