{
  "type": "Feature",
  "properties": {
    "addr:full":"75-101 Federal St Boston MA 02110",
    "addr:housenumber":"75-101",
    "addr:postcode":"02110",
    "addr:street":"Federal St",
    "iso:country":"US",
    "sg:address":"75-101 Federal St",
    "sg:city":"Boston",
    "sg:classifiers":[
        {
            "category":"Coffee & Tea",
            "type":"Food & Drink"
        }
    ],
    "sg:phone":"+1 617 946 0535",
    "sg:postcode":"02110",
    "sg:province":"MA",
    "sg:website":"www.starbucks.com",
    "wof:name":"Starbucks",
    "wof:placetype":"venue"
},
  "geometry": {"coordinates":[-71.056826,42.354949],"type":"Point"}
}