{
  "type": "Feature",
  "properties": {
    "addr:full": "23 Temple St Boston MA 02114",
    "addr:housenumber": "23",
    "addr:postcode": "02114",
    "addr:street": "Temple St",
    "iso:country": "US",
    "sg:address": "23 Temple St",
    "sg:city": "Boston",
    "sg:classifiers": [
      {
        "category": "Health Services",
        "subcategory": "Health Practitioner",
        "type": "Services"
      }
    ],
    "sg:phone": "+1 617 742 1353",
    "sg:postcode": "02114",
    "sg:province": "MA",
    "sg:tags": [
      "psychotherapist"
    ],
    "wof:name": "Linda Carter",
    "wof:placetype": "venue"
  },
  "geometry": {"coordinates":[-71.063713,42.360576],"type":"Point"}
}
