{
  "type": "Feature",
  "properties": {
    "iso:country":"US",
    "sg:address":"23 Temple St",
    "sg:city":"Boston",
    "sg:classifiers":[
        {
            "category":"Health Services",
            "subcategory":"Health Practitioner",
            "type":"Services"
        }
    ],
    "sg:phone":"+1 617 742 1353",
    "sg:postcode":"02114",
    "sg:province":"MA",
    "sg:tags":[
        "psychotherapist"
    ],
    "wof:name":"Linda Carter",
    "wof:placetype":"venue"
},
  "geometry": {"coordinates":[-71.06371300000001,42.360576],"type":"Point"}
}