{
  "type": "Feature",
  "properties": {
    "iso:country":"US",
    "sg:address":"44 Pitman Ave",
    "sg:city":"Wakefield",
    "sg:classifiers":[
        {
            "category":"Professional",
            "subcategory":"Employment Agencies",
            "type":"Services"
        }
    ],
    "sg:phone":"+1   ",
    "sg:postcode":"01880",
    "sg:province":"MA",
    "sg:tags":[
        "medical",
        "consulting"
    ],
    "wof:name":"Medisci Consultants",
    "wof:placetype":"venue"
},
  "geometry": {"coordinates":[-71.05999799999999,42.478901],"type":"Point"}
}