{
  "type": "Feature",
  "properties": {
    "addr:full": "44 Pitman Ave Wakefield MA 01880",
    "addr:housenumber": "44",
    "addr:postcode": "01880",
    "addr:street": "Pitman Ave",
    "iso:country": "US",
    "sg:address": "44 Pitman Ave",
    "sg:city": "Wakefield",
    "sg:classifiers": [
      {
        "category": "Professional",
        "subcategory": "Employment Agencies",
        "type": "Services"
      }
    ],
    "sg:phone": "+1   ",
    "sg:postcode": "01880",
    "sg:province": "MA",
    "sg:tags": [
      "medical",
      "consulting"
    ],
    "wof:name": "Medisci Consultants",
    "wof:placetype": "venue"
  },
  "geometry": {"coordinates":[-71.059998,42.478901],"type":"Point"}
}
