{
  "type": "Feature",
  "properties": {
    "iso:country":"US",
    "sg:address":"136 Pond St",
    "sg:city":"Leominster",
    "sg:classifiers":[
        {
            "category":"Manufacturing",
            "subcategory":"Printing",
            "type":"Manufacturing & Wholesale Goods"
        }
    ],
    "sg:phone":"+1 978 537 9791",
    "sg:postcode":"01453",
    "sg:province":"MA",
    "sg:tags":[
        "printer"
    ],
    "sg:website":"www.rogersprinting.com",
    "wof:name":"Rogers Printing Corp",
    "wof:placetype":"venue"
},
  "geometry": {"coordinates":[-71.76784499999999,42.524108],"type":"Point"}
}