{
  "type": "Feature",
  "properties": {
    "addr:full":"490 Lincoln St  Worcester MA 01605",
    "addr:housenumber":"490",
    "addr:postcode":"01605",
    "addr:street":"Lincoln St",
    "iso:country":"US",
    "sg:address":"490 Lincoln St ",
    "sg:city":"Worcester",
    "sg:classifiers":[
        {
            "category":"Restaurant",
            "type":"Food & Drink"
        }
    ],
    "sg:menulink":"http://www.allmenus.com/ma/worcester/293625-ronzio-pizza/menu/",
    "sg:phone":"+1 508 853 3377",
    "sg:postcode":"01605",
    "sg:province":"MA",
    "sg:tags":[
        "sandwich",
        "pizza"
    ],
    "wof:name":"Ronzio Pizza & Subs",
    "wof:placetype":"venue"
},
  "geometry": {"coordinates":[-71.775938,42.294351],"type":"Point"}
}