{
  "type": "Feature",
  "properties": {
    "addr:full":"37 Main St North Reading MA 01864",
    "addr:housenumber":"37",
    "addr:postcode":"01864",
    "addr:street":"Main St",
    "iso:country":"US",
    "sg:address":"37 Main St",
    "sg:city":"North Reading",
    "sg:classifiers":[
        {
            "category":"Restaurant",
            "type":"Food & Drink"
        }
    ],
    "sg:phone":"+1 978 664 5223",
    "sg:postcode":"01864",
    "sg:province":"MA",
    "sg:tags":[
        "pizza"
    ],
    "sg:website":"www.coldcuts.com",
    "wof:name":"Andrea's House of Pizza",
    "wof:placetype":"venue"
},
  "geometry": {"coordinates":[-71.108937,42.568757],"type":"Point"}
}