{
  "type": "Feature",
  "properties": {
    "addr:full": "201 Whiting St Hingham MA 02043",
    "addr:housenumber": "201",
    "addr:postcode": "02043",
    "addr:street": "Whiting St",
    "iso:country": "US",
    "sg:address": "201 Whiting St",
    "sg:city": "Hingham",
    "sg:classifiers": [
      {
        "category": "Personal",
        "type": "Services"
      }
    ],
    "sg:phone": "+1 781 740 4700",
    "sg:postcode": "02043",
    "sg:province": "MA",
    "sg:tags": [
      "palmist"
    ],
    "wof:name": "Pia's Postive Vibrations",
    "wof:placetype": "venue"
  },
  "geometry": {"coordinates":[-70.900379,42.180637],"type":"Point"}
}
