{
  "type": "Feature",
  "properties": {
    "iso:country":"US",
    "sg:address":"1 School St Apt 404",
    "sg:city":"Arlington",
    "sg:classifiers":[
        {
            "category":"Professional",
            "subcategory":"Research",
            "type":"Services"
        }
    ],
    "sg:phone":"+1 781 641 2807",
    "sg:postcode":"02476",
    "sg:province":"MA",
    "sg:tags":[
        "market",
        "analysis"
    ],
    "wof:name":"Thinking Cap Productions",
    "wof:placetype":"venue"
},
  "geometry": {"coordinates":[-71.170517,42.420811],"type":"Point"}
}