{
  "type": "Feature",
  "properties": {
    "iso:country":"US",
    "sg:address":"241 Main St",
    "sg:city":"Norwell",
    "sg:classifiers":[
        {
            "category":"Travel",
            "subcategory":"Travel Agent",
            "type":"Entertainment"
        }
    ],
    "sg:phone":"+1 781 659 2476",
    "sg:postcode":"02061",
    "sg:province":"MA",
    "sg:tags":[
        "agency",
        "bureau"
    ],
    "wof:name":"Traditional Tours",
    "wof:placetype":"venue"
},
  "geometry": {"coordinates":[-70.827128,42.157846],"type":"Point"}
}