{
  "type": "Feature",
  "properties": {
    "iso:country":"US",
    "sg:address":"80 Meadow Ln",
    "sg:city":"Somerset",
    "sg:classifiers":[
        {
            "category":"Banks & Credit Unions",
            "subcategory":"Investment Brokerage",
            "type":"Services"
        }
    ],
    "sg:phone":"+1 508 672 5681",
    "sg:postcode":"02726",
    "sg:province":"MA",
    "sg:tags":[
        "advisory",
        "financial"
    ],
    "wof:name":"Saraiva Financial Inc",
    "wof:placetype":"venue"
},
  "geometry": {"coordinates":[-71.155326,41.735398],"type":"Point"}
}