{
  "type": "Feature",
  "properties": {
    "addr:full": "266 Atlantic Avenue Boston MA 02110",
    "addr:housenumber": "266",
    "addr:postcode": "02110",
    "addr:street": "Atlantic Avenue",
    "iso:country": "US",
    "ovtr:label": "Casablanca Salon, 266 Atlantic Ave Boston MA US",
    "ovtr:similarity": 2.807241916656494,
    "sg:address": "266 Atlantic Avenue",
    "sg:city": "Boston",
    "sg:classifiers": [
      {
        "category": "Personal",
        "subcategory": "Beauty Salon",
        "type": "Services"
      }
    ],
    "sg:phone": "+1 617 227 4310",
    "sg:postcode": "02110",
    "sg:province": "MA",
    "sg:tags": [
      "hair"
    ],
    "wof:name": "Casablanca Salon",
    "wof:placetype": "venue"
  },
  "geometry": {"coordinates":[-71.05176,42.359041],"type":"Point"}
}
