{
  "type": "Feature",
  "properties": {
    "addr:full": "141 Middlesex Rd Tyngsboro MA 01879",
    "addr:housenumber": "141",
    "addr:postcode": "01879",
    "addr:street": "Middlesex Rd",
    "iso:country": "US",
    "sg:address": "141 Middlesex Rd",
    "sg:city": "Tyngsboro",
    "sg:classifiers": [
      {
        "category": "Retail",
        "subcategory": "Portrait Studio",
        "type": "Services"
      }
    ],
    "sg:phone": "+1 978 649 9075",
    "sg:postcode": "01879",
    "sg:province": "MA",
    "sg:tags": [
      "photography"
    ],
    "wof:name": "Air Shotz USA",
    "wof:placetype": "venue"
  },
  "geometry": {"coordinates":[-71.420459,42.671336],"type":"Point"}
}
