{
  "type": "Feature",
  "properties": {
    "addr:full":"10 Goodrich St Pittsfield MA 01201",
    "addr:housenumber":"10",
    "addr:postcode":"01201",
    "addr:street":"Goodrich St",
    "iso:country":"US",
    "sg:address":"10 Goodrich St",
    "sg:city":"Pittsfield",
    "sg:classifiers":[
        {
            "category":"Home & Garden",
            "subcategory":"Garden Supply",
            "type":"Retail Goods"
        }
    ],
    "sg:phone":"+1 413 442 8300",
    "sg:postcode":"01201",
    "sg:province":"MA",
    "sg:tags":[
        "landscaping",
        "equipment"
    ],
    "wof:name":"Quick Mulch Inc",
    "wof:placetype":"venue"
},
  "geometry": {"coordinates":[-73.25645799999999,42.446694],"type":"Point"}
}