{
  "type": "Feature",
  "properties": {
    "iso:country":"US",
    "sg:address":"32 Billerica Ave",
    "sg:city":"North Billerica",
    "sg:classifiers":[
        {
            "category":"Building & Trades",
            "subcategory":"Construction",
            "type":"Services"
        }
    ],
    "sg:phone":"+1   ",
    "sg:postcode":"01862",
    "sg:province":"MA",
    "sg:tags":[
        "house"
    ],
    "wof:name":"Sherwood Builders & Remodeling",
    "wof:placetype":"venue"
},
  "geometry": {"coordinates":[-71.280585,42.59531],"type":"Point"}
}