{
  "type": "Feature",
  "properties": {
    "addr:full": "32 Billerica Ave North Billerica MA 01862",
    "addr:housenumber": "32",
    "addr:postcode": "01862",
    "addr:street": "Billerica Ave North",
    "iso:country": "US",
    "sg:address": "32 Billerica Ave",
    "sg:city": "North Billerica",
    "sg:classifiers": [
      {
        "category": "Building \u0026 Trades",
        "subcategory": "Construction",
        "type": "Services"
      }
    ],
    "sg:phone": "+1   ",
    "sg:postcode": "01862",
    "sg:province": "MA",
    "sg:tags": [
      "house"
    ],
    "wof:name": "Sherwood Builders \u0026 Remodeling",
    "wof:placetype": "venue"
  },
  "geometry": {"coordinates":[-71.280585,42.59531],"type":"Point"}
}
