{
  "type": "Feature",
  "properties": {
    "addr:full": "50 Dunster Dr Stow MA 01775",
    "addr:housenumber": "50",
    "addr:postcode": "01775",
    "addr:street": "Dunster Dr",
    "iso:country": "US",
    "sg:address": "50 Dunster Dr",
    "sg:city": "Stow",
    "sg:classifiers": [
      {
        "category": "Professional",
        "subcategory": "Engineering",
        "type": "Services"
      }
    ],
    "sg:phone": "+1   ",
    "sg:postcode": "01775",
    "sg:province": "MA",
    "wof:name": "L Avery William",
    "wof:placetype": "venue"
  },
  "geometry": {"coordinates":[-71.532293,42.449734],"type":"Point"}
}
