{
  "type": "Feature",
  "properties": {
    "addr:full":"105 Upland Rd Concord MA 01742",
    "addr:housenumber":"105",
    "addr:postcode":"01742",
    "addr:street":"Upland Rd",
    "iso:country":"US",
    "sg:address":"105 Upland Rd",
    "sg:city":"Concord",
    "sg:classifiers":[
        {
            "category":"Organizations",
            "subcategory":"Community Association",
            "type":"Services"
        }
    ],
    "sg:phone":"+1 978 287 6009",
    "sg:postcode":"01742",
    "sg:province":"MA",
    "wof:name":"Man Consulting",
    "wof:placetype":"venue"
},
  "geometry": {"coordinates":[-71.39400000000001,42.449934],"type":"Point"}
}