{
  "type": "Feature",
  "properties": {
    "addr:full": "29 Coolidge Hill Rd Watertown MA 02472",
    "addr:housenumber": "29",
    "addr:postcode": "02472",
    "addr:street": "Coolidge Hill Rd",
    "iso:country": "US",
    "sg:address": "29 Coolidge Hill Rd",
    "sg:city": "Watertown",
    "sg:classifiers": [
      {
        "category": "Building \u0026 Trades",
        "subcategory": "Cleaning \u0026 Sanitation",
        "type": "Services"
      }
    ],
    "sg:phone": "+1 617 923 1260",
    "sg:postcode": "02472",
    "sg:province": "MA",
    "sg:tags": [
      "carpet"
    ],
    "wof:name": "Elbag George",
    "wof:placetype": "venue"
  },
  "geometry": {"coordinates":[-71.154519,42.367565],"type":"Point"}
}
