{
  "type": "Feature",
  "properties": {
    "iso:country":"US",
    "sg:address":"29 Coolidge Hill Rd",
    "sg:city":"Watertown",
    "sg:classifiers":[
        {
            "category":"Building & Trades",
            "subcategory":"Cleaning & Sanitation",
            "type":"Services"
        }
    ],
    "sg:phone":"+1 617 923 1260",
    "sg:postcode":"02472",
    "sg:province":"MA",
    "sg:tags":[
        "carpet"
    ],
    "wof:name":"Elbag George",
    "wof:placetype":"venue"
},
  "geometry": {"coordinates":[-71.15451899999999,42.367565],"type":"Point"}
}