{
  "type": "Feature",
  "properties": {
    "addr:full":"228 Triangle St Amherst MA 01002",
    "addr:housenumber":"228",
    "addr:postcode":"01002",
    "addr:street":"Triangle St",
    "iso:country":"US",
    "sg:address":"228 Triangle St",
    "sg:city":"Amherst",
    "sg:classifiers":[
        {
            "category":"Building & Trades",
            "subcategory":"Construction",
            "type":"Services"
        }
    ],
    "sg:phone":"+1 413 549 0803",
    "sg:postcode":"01002",
    "sg:province":"MA",
    "sg:tags":[
        "general",
        "contractor"
    ],
    "sg:website":"www.teagnoconstruction.com",
    "wof:name":"Teagno Construction Inc",
    "wof:placetype":"venue"
},
  "geometry": {"coordinates":[-72.51847100000001,42.380723],"type":"Point"}
}