{
  "type": "Feature",
  "properties": {
    "addr:full":"137 Gilbert Ave Chicopee MA 01013",
    "addr:housenumber":"137",
    "addr:postcode":"01013",
    "addr:street":"Gilbert Ave",
    "iso:country":"US",
    "sg:address":"137 Gilbert Ave",
    "sg:city":"Chicopee",
    "sg:classifiers":[
        {
            "category":"Social Services",
            "subcategory":"Child Care",
            "type":"Services"
        }
    ],
    "sg:phone":"+1   ",
    "sg:postcode":"01013",
    "sg:province":"MA",
    "sg:tags":[
        "day"
    ],
    "wof:name":"Jacobs Friends Daycare",
    "wof:placetype":"venue"
},
  "geometry": {"coordinates":[-72.594735,42.13912],"type":"Point"}
}