{
  "type": "Feature",
  "properties": {
    "addr:full": "44 Falcon Dr Attleboro MA 02703",
    "addr:housenumber": "44",
    "addr:postcode": "02703",
    "addr:street": "Falcon Dr",
    "iso:country": "US",
    "sg:address": "44 Falcon Dr",
    "sg:city": "Attleboro",
    "sg:classifiers": [
      {
        "category": "Real Estate",
        "subcategory": "Real Estate Services",
        "type": "Services"
      },
      {
        "category": "Real Estate",
        "subcategory": "Real Estate Agent",
        "type": "Services"
      }
    ],
    "sg:phone": "+1 508 226 4672",
    "sg:postcode": "02703",
    "sg:province": "MA",
    "sg:tags": [
      "buyer",
      "broker"
    ],
    "wof:name": "Simmons Realty",
    "wof:placetype": "venue"
  },
  "geometry": {"coordinates":[-71.314939,41.912963],"type":"Point"}
}
