{
  "type": "Feature",
  "properties": {
    "addr:full": "10 Central St Manchester MA 01944",
    "addr:housenumber": "10",
    "addr:postcode": "01944",
    "addr:street": "Central St",
    "iso:country": "US",
    "sg:address": "10 Central St",
    "sg:city": "Manchester",
    "sg:classifiers": [
      {
        "category": "Government",
        "subcategory": "Police Station",
        "type": "Public Place"
      }
    ],
    "sg:phone": "+1 978 526 1212",
    "sg:postcode": "01944",
    "sg:province": "MA",
    "sg:tags": [
      "department"
    ],
    "wof:name": "Police Dept",
    "wof:placetype": "venue"
  },
  "geometry": {"coordinates":[-70.772404,42.575177],"type":"Point"}
}
