{
  "type": "Feature",
  "properties": {
    "iso:country":"US",
    "sg:address":"208 Adams St",
    "sg:city":"Dorchester",
    "sg:classifiers":[
        {
            "category":"Shopping",
            "subcategory":"Clothing, Apparel, & Fashions",
            "type":"Retail Goods"
        }
    ],
    "sg:phone":"+1 617 825 6138",
    "sg:postcode":"02122",
    "sg:province":"MA",
    "sg:tags":[
        "designer"
    ],
    "wof:name":"All Seasons Fashions",
    "wof:placetype":"venue"
},
  "geometry": {"coordinates":[-71.06007700000001,42.302041],"type":"Point"}
}