{
  "type": "Feature",
  "properties": {
    "addr:full":"407 West St Ludlow MA 01056",
    "addr:housenumber":"407",
    "addr:postcode":"01056",
    "addr:street":"West St",
    "iso:country":"US",
    "sg:address":"407 West St",
    "sg:city":"Ludlow",
    "sg:classifiers":[
        {
            "category":"Autos & Motor Vehicles",
            "subcategory":"Automobile Sales",
            "type":"Retail Goods"
        }
    ],
    "sg:phone":"+1 413 583 4621",
    "sg:postcode":"01056",
    "sg:province":"MA",
    "sg:tags":[
        "car",
        "dealer"
    ],
    "wof:name":"J F Auto Sales",
    "wof:placetype":"venue"
},
  "geometry": {"coordinates":[-72.50345,42.188665],"type":"Point"}
}