{
  "type": "Feature",
  "properties": {
    "iso:country":"US",
    "sg:address":"87 Woodside Ter",
    "sg:city":"Springfield",
    "sg:classifiers":[
        {
            "category":"Building & Trades",
            "subcategory":"Construction",
            "type":"Services"
        }
    ],
    "sg:phone":"+1 413 732 3417",
    "sg:postcode":"01108",
    "sg:province":"MA",
    "sg:tags":[
        "roofing",
        "industrial",
        "contractors-commercial",
        "contractor"
    ],
    "wof:name":"Acerra Roofing Co",
    "wof:placetype":"venue"
},
  "geometry": {"coordinates":[-72.572383,42.090103],"type":"Point"}
}