{
  "type": "Feature",
  "properties": {
    "iso:country":"US",
    "sg:address":"4231 Arbor Dr",
    "sg:city":"Shrewsbury",
    "sg:classifiers":[
        {
            "category":"Real Estate",
            "subcategory":"Real Estate Agent",
            "type":"Services"
        }
    ],
    "sg:phone":"+1 508 865 7403",
    "sg:postcode":"01545",
    "sg:province":"MA",
    "wof:name":"THK Realty Corp",
    "wof:placetype":"venue"
},
  "geometry": {"coordinates":[-71.68687,42.280019],"type":"Point"}
}