{
  "type": "Feature",
  "properties": {
    "addr:full":"101 Presidents Row Ashland MA 01721",
    "addr:housenumber":"101",
    "addr:postcode":"01721",
    "addr:street":"Presidents Row",
    "iso:country":"US",
    "sg:address":"101 Presidents Row",
    "sg:city":"Ashland",
    "sg:classifiers":[
        {
            "category":"Real Estate",
            "subcategory":"Real Estate Operator",
            "type":"Services"
        }
    ],
    "sg:phone":"+1 508 881 3314",
    "sg:postcode":"01721",
    "sg:province":"MA",
    "sg:tags":[
        "apartment"
    ],
    "wof:name":"Ashland Commons",
    "wof:placetype":"venue"
},
  "geometry": {"coordinates":[-71.465182,42.253793],"type":"Point"}
}