{
  "type": "Feature",
  "properties": {
    "iso:country":"US",
    "sg:address":"209 Oak St",
    "sg:city":"Halifax",
    "sg:classifiers":[
        {
            "category":"Local Transit",
            "type":"Transportation"
        }
    ],
    "sg:phone":"+1 781 293 4099",
    "sg:postcode":"02338",
    "sg:province":"MA",
    "sg:tags":[
        "airport"
    ],
    "wof:name":"Hogans Limousine",
    "wof:placetype":"venue"
},
  "geometry": {"coordinates":[-70.818403,42.016852],"type":"Point"}
}