{
  "type": "Feature",
  "properties": {
    "addr:full":"1 Cottage St Unit 45 Easthampton MA 01027",
    "addr:housenumber":"1;45",
    "addr:postcode":"01027",
    "addr:street":"Cottage St Unit",
    "iso:country":"US",
    "sg:address":"1 Cottage St Unit 45",
    "sg:city":"Easthampton",
    "sg:classifiers":[
        {
            "category":"Manufacturing",
            "subcategory":"Paper Products",
            "type":"Manufacturing & Wholesale Goods"
        }
    ],
    "sg:phone":"+1 413 527 3558",
    "sg:postcode":"01027",
    "sg:province":"MA",
    "sg:tags":[
        "bookbinder"
    ],
    "wof:name":"Mark Tomlinson Bookbinding",
    "wof:placetype":"venue"
},
  "geometry": {"coordinates":[-72.668999,42.265461],"type":"Point"}
}