{
  "type": "Feature",
  "properties": {
    "addr:full": "158 Main St Agawam MA 01001",
    "addr:housenumber": "158",
    "addr:postcode": "01001",
    "addr:street": "Main St",
    "iso:country": "US",
    "sg:address": "158 Main St",
    "sg:city": "Agawam",
    "sg:classifiers": [
      {
        "category": "Health Services",
        "subcategory": "Doctor",
        "type": "Services"
      }
    ],
    "sg:phone": "+1 413 786 2341",
    "sg:postcode": "01001",
    "sg:province": "MA",
    "sg:tags": [
      "dentist"
    ],
    "wof:name": "George A Vassos DDS",
    "wof:placetype": "venue"
  },
  "geometry": {"coordinates":[-72.620895,42.085865],"type":"Point"}
}
