{
  "type": "Feature",
  "properties": {
    "iso:country":"US",
    "sg:address":"55 Pine St",
    "sg:city":"Middleboro",
    "sg:classifiers":[
        {
            "category":"Manufacturing",
            "subcategory":"Tools & Machinery",
            "type":"Manufacturing & Wholesale Goods"
        }
    ],
    "sg:phone":"+1 508 923 0070",
    "sg:postcode":"02346",
    "sg:province":"MA",
    "sg:tags":[
        "machine",
        "shop",
        "industrial",
        "mfg"
    ],
    "wof:name":"Milton Machine Corp",
    "wof:placetype":"venue"
},
  "geometry": {"coordinates":[-70.789627,41.825787],"type":"Point"}
}