{
  "type": "Feature",
  "properties": {
    "addr:full": "55 Pine St Middleboro MA 02346",
    "addr:housenumber": "55",
    "addr:postcode": "02346",
    "addr:street": "Pine St",
    "iso:country": "US",
    "sg:address": "55 Pine St",
    "sg:city": "Middleboro",
    "sg:classifiers": [
      {
        "category": "Manufacturing",
        "subcategory": "Tools \u0026 Machinery",
        "type": "Manufacturing \u0026 Wholesale Goods"
      }
    ],
    "sg:phone": "+1 508 923 0070",
    "sg:postcode": "02346",
    "sg:province": "MA",
    "sg:tags": [
      "machine",
      "shop",
      "industrial",
      "mfg"
    ],
    "wof:name": "Milton Machine Corp",
    "wof:placetype": "venue"
  },
  "geometry": {"coordinates":[-70.789627,41.825787],"type":"Point"}
}
