{
  "type": "Feature",
  "properties": {
    "addr:full":"11 Melissa Cir Methuen MA 01844",
    "addr:housenumber":"11",
    "addr:postcode":"01844",
    "addr:street":"Melissa Cir",
    "iso:country":"US",
    "sg:address":"11 Melissa Cir",
    "sg:city":"Methuen",
    "sg:classifiers":[
        {
            "category":"Retail",
            "subcategory":"Laundry & Dry Cleaning",
            "type":"Services"
        },
        {
            "category":"Retail",
            "subcategory":"Repair Shop",
            "type":"Services"
        }
    ],
    "sg:phone":"+1 978 689 4099",
    "sg:postcode":"01844",
    "sg:province":"MA",
    "sg:tags":[
        "cleaner",
        "rug",
        "carpet"
    ],
    "wof:name":"Cd S",
    "wof:placetype":"venue"
},
  "geometry": {"coordinates":[-71.19328,42.73809],"type":"Point"}
}