{
  "type": "Feature",
  "properties": {
    "addr:full":"155 State Rd Vineyard Haven MA 02568",
    "addr:housenumber":"155",
    "addr:postcode":"02568",
    "addr:street":"State Rd",
    "iso:country":"US",
    "sg:address":"155 State Rd",
    "sg:city":"Vineyard Haven",
    "sg:classifiers":[
        {
            "category":"Real Estate",
            "subcategory":"Real Estate Agent",
            "type":"Services"
        }
    ],
    "sg:phone":"+1 508 693 9216",
    "sg:postcode":"02568",
    "sg:province":"MA",
    "sg:tags":[
        "inspection"
    ],
    "wof:name":"Beacon Home Inspections Inc",
    "wof:placetype":"venue"
},
  "geometry": {"coordinates":[-70.60987299999999,41.450517],"type":"Point"}
}