{
  "type": "Feature",
  "properties": {
    "iso:country":"US",
    "sg:address":"94 W Broadway",
    "sg:city":"South Boston",
    "sg:classifiers":[
        {
            "category":"Building & Trades",
            "subcategory":"Locksmith",
            "type":"Services"
        }
    ],
    "sg:phone":"+1 617 303 2621",
    "sg:postcode":"02127",
    "sg:province":"MA",
    "sg:tags":[
        "key"
    ],
    "wof:name":"Complete Locksmith",
    "wof:placetype":"venue"
},
  "geometry": {"coordinates":[-71.05504999999999,42.341703],"type":"Point"}
}