{
  "type": "Feature",
  "properties": {
    "addr:full": "61 Masonic St Northampton MA 01060",
    "addr:housenumber": "61",
    "addr:postcode": "01060",
    "addr:street": "Masonic St",
    "iso:country": "US",
    "sg:address": "61 Masonic St",
    "sg:city": "Northampton",
    "sg:phone": "+1 413 584 1602",
    "sg:postcode": "01060",
    "sg:province": "MA",
    "sg:tags": [
      "oil"
    ],
    "wof:name": "Emco Service Div",
    "wof:placetype": "venue"
  },
  "geometry": {"coordinates":[-72.633036,42.318628],"type":"Point"}
}
