{
  "type": "Feature",
  "properties": {
    "addr:full":"177 Main St Shrewsbury MA 01545",
    "addr:housenumber":"177",
    "addr:postcode":"01545",
    "addr:street":"Main St",
    "iso:country":"US",
    "sg:address":"177 Main St",
    "sg:city":"Shrewsbury",
    "sg:classifiers":[
        {
            "category":"Social Services",
            "subcategory":"Child Care",
            "type":"Services"
        }
    ],
    "sg:phone":"+1   ",
    "sg:postcode":"01545",
    "sg:province":"MA",
    "sg:tags":[
        "day"
    ],
    "wof:name":"Mulberry Child Care Ctrs Inc",
    "wof:placetype":"venue"
},
  "geometry": {"coordinates":[-71.748953,42.293258],"type":"Point"}
}