{
  "type": "Feature",
  "properties": {
    "addr:full": "355 Providence Hwy Westwood MA 02090",
    "addr:housenumber": "355",
    "addr:postcode": "02090",
    "addr:street": "Providence Hwy",
    "iso:country": "US",
    "sg:address": "355 Providence Hwy",
    "sg:city": "Westwood",
    "sg:classifiers": [
      {
        "category": "Professional",
        "subcategory": "Computer Services",
        "type": "Services"
      }
    ],
    "sg:phone": "+1 781 329 9200",
    "sg:postcode": "02090",
    "sg:province": "MA",
    "sg:tags": [
      "prepackaged",
      "software"
    ],
    "sg:website": "www.asthomas.com",
    "wof:name": "A S Thomas Inc",
    "wof:placetype": "venue"
  },
  "geometry": {"coordinates":[-71.18081,42.21762],"type":"Point"}
}
