{
  "type": "Feature",
  "properties": {
    "addr:full":"68 Von Hillern St Dorchester MA 02125",
    "addr:housenumber":"68",
    "addr:postcode":"02125",
    "addr:street":"Von Hillern St",
    "iso:country":"US",
    "sg:address":"68 Von Hillern St",
    "sg:city":"Dorchester",
    "sg:classifiers":[
        {
            "category":"Autos & Motor Vehicles",
            "subcategory":"Boat Sales",
            "type":"Retail Goods"
        }
    ],
    "sg:phone":"+1 617 288 3132",
    "sg:postcode":"02125",
    "sg:province":"MA",
    "sg:tags":[
        "propeller"
    ],
    "wof:name":"New England Propeller",
    "wof:placetype":"venue"
},
  "geometry": {"coordinates":[-71.054937,42.323266],"type":"Point"}
}