{
  "type": "Feature",
  "properties": {
    "addr:full": "310 Boston Post Rd Wayland MA 01778",
    "addr:housenumber": "310",
    "addr:postcode": "01778",
    "addr:street": "Boston Post Rd",
    "iso:country": "US",
    "sg:address": "310 Boston Post Rd",
    "sg:city": "Wayland",
    "sg:classifiers": [
      {
        "category": "Home \u0026 Garden",
        "subcategory": "Building Materials",
        "type": "Retail Goods"
      }
    ],
    "sg:phone": "+1 508 358 4010",
    "sg:postcode": "01778",
    "sg:province": "MA",
    "sg:tags": [
      "stone"
    ],
    "wof:name": "Levicaro Stone",
    "wof:placetype": "venue"
  },
  "geometry": {"coordinates":[-71.368839,42.363273],"type":"Point"}
}
