{
  "type": "Feature",
  "properties": {
    "iso:country":"US",
    "sg:address":"310 Boston Post Rd",
    "sg:city":"Wayland",
    "sg:classifiers":[
        {
            "category":"Home & Garden",
            "subcategory":"Building Materials",
            "type":"Retail Goods"
        }
    ],
    "sg:phone":"+1 508 358 4010",
    "sg:postcode":"01778",
    "sg:province":"MA",
    "sg:tags":[
        "stone"
    ],
    "wof:name":"Levicaro Stone",
    "wof:placetype":"venue"
},
  "geometry": {"coordinates":[-71.36883899999999,42.363273],"type":"Point"}
}