{
  "type": "Feature",
  "properties": {
    "addr:full": "50 Rowes Wharf Boston MA 02110",
    "addr:housenumber": "50",
    "addr:postcode": "02110",
    "addr:street": "Rowes Wharf",
    "iso:country": "US",
    "sg:address": "50 Rowes Wharf",
    "sg:city": "Boston",
    "sg:classifiers": [
      {
        "category": "Professional",
        "subcategory": "Lawyer \u0026 Legal Services",
        "type": "Services"
      }
    ],
    "sg:phone": "+1 617 951 2042",
    "sg:postcode": "02110",
    "sg:province": "MA",
    "wof:name": "Sorensen Ingrid Lwyr",
    "wof:placetype": "venue"
  },
  "geometry": {"coordinates":[-71.050003,42.356201],"type":"Point"}
}
