{
  "type": "Feature",
  "properties": {
    "iso:country":"US",
    "sg:address":"659 Brayton Ave",
    "sg:city":"Fall River",
    "sg:classifiers":[
        {
            "category":"Organizations",
            "subcategory":"Community Association",
            "type":"Services"
        }
    ],
    "sg:phone":"+1 508 676 9478",
    "sg:postcode":"02721",
    "sg:province":"MA",
    "sg:tags":[
        "military"
    ],
    "wof:name":"Louis Colon Amvets",
    "wof:placetype":"venue"
},
  "geometry": {"coordinates":[-71.147268,41.682752],"type":"Point"}
}