{
  "type": "Feature",
  "properties": {
    "addr:full":"60 State St Boston MA 02109",
    "addr:housenumber":"60",
    "addr:postcode":"02109",
    "addr:street":"State St",
    "iso:country":"US",
    "sg:address":"60 State St",
    "sg:city":"Boston",
    "sg:classifiers":[
        {
            "category":"Professional",
            "type":"Services"
        }
    ],
    "sg:phone":"+1 617 854 7423",
    "sg:postcode":"02109",
    "sg:province":"MA",
    "sg:tags":[
        "establishment"
    ],
    "wof:name":"Ardiff & Morse",
    "wof:placetype":"venue"
},
  "geometry": {"coordinates":[-71.055927,42.359114],"type":"Point"}
}