{
  "type": "Feature",
  "properties": {
    "addr:full":"41 Church St Westfield MA 01085",
    "addr:housenumber":"41",
    "addr:postcode":"01085",
    "addr:street":"Church St",
    "iso:country":"US",
    "sg:address":"41 Church St",
    "sg:city":"Westfield",
    "sg:classifiers":[
        {
            "category":"Health Services",
            "subcategory":"Health Practitioner",
            "type":"Services"
        }
    ],
    "sg:phone":"+1 413 562 8200",
    "sg:postcode":"01085",
    "sg:province":"MA",
    "sg:tags":[
        "nutritionist"
    ],
    "wof:name":"Christine M Keenan",
    "wof:placetype":"venue"
},
  "geometry": {"coordinates":[-72.749197,42.121862],"type":"Point"}
}