{
  "type": "Feature",
  "properties": {
    "addr:full":"1277 Broadway Saugus MA 01906",
    "addr:housenumber":"1277",
    "addr:postcode":"01906",
    "addr:street":"Broadway",
    "iso:country":"US",
    "sg:address":"1277 Broadway",
    "sg:city":"Saugus",
    "sg:classifiers":[
        {
            "category":"Shopping",
            "subcategory":"Clothing, Apparel, & Fashions",
            "type":"Retail Goods"
        }
    ],
    "sg:phone":"+1 781 231 5381",
    "sg:postcode":"01906",
    "sg:province":"MA",
    "sg:website":"www.tellos1.com",
    "wof:name":"Tello's",
    "wof:placetype":"venue"
},
  "geometry": {"coordinates":[-71.024711,42.462458],"type":"Point"}
}