{
  "type": "Feature",
  "properties": {
    "addr:full":"17 Carle Dr Dracut MA 01826",
    "addr:housenumber":"17",
    "addr:postcode":"01826",
    "addr:street":"Carle Dr",
    "iso:country":"US",
    "sg:address":"17 Carle Dr",
    "sg:city":"Dracut",
    "sg:classifiers":[
        {
            "category":"Professional",
            "type":"Services"
        }
    ],
    "sg:phone":"+1 978 258 5442",
    "sg:postcode":"01826",
    "sg:province":"MA",
    "sg:tags":[
        "establishment"
    ],
    "wof:name":"Slattery C & H",
    "wof:placetype":"venue"
},
  "geometry": {"coordinates":[-71.287216,42.665565],"type":"Point"}
}