{
  "type": "Feature",
  "properties": {
    "iso:country":"US",
    "sg:address":"124 Harvard St",
    "sg:city":"Brookline",
    "sg:classifiers":[
        {
            "category":"Health Services",
            "subcategory":"Doctor",
            "type":"Services"
        }
    ],
    "sg:phone":"+1 617 232 4447",
    "sg:postcode":"02446",
    "sg:province":"MA",
    "sg:tags":[
        "psychologist"
    ],
    "wof:name":"Avery Nancy",
    "wof:placetype":"venue"
},
  "geometry": {"coordinates":[-71.121431,42.337007],"type":"Point"}
}