{
  "type": "Feature",
  "properties": {
    "addr:full": "124 Harvard St Brookline MA 02446",
    "addr:housenumber": "124",
    "addr:postcode": "02446",
    "addr:street": "Harvard St",
    "iso:country": "US",
    "sg:address": "124 Harvard St",
    "sg:city": "Brookline",
    "sg:classifiers": [
      {
        "category": "Health Services",
        "subcategory": "Doctor",
        "type": "Services"
      }
    ],
    "sg:phone": "+1 617 232 4447",
    "sg:postcode": "02446",
    "sg:province": "MA",
    "sg:tags": [
      "psychologist"
    ],
    "wof:name": "Avery Nancy",
    "wof:placetype": "venue"
  },
  "geometry": {"coordinates":[-71.121431,42.337007],"type":"Point"}
}
