{
  "type": "Feature",
  "properties": {
    "addr:full": "970 Old Reed Rd North Dartmouth MA 02747",
    "addr:housenumber": "970",
    "addr:postcode": "02747",
    "addr:street": "Old Reed Rd",
    "iso:country": "US",
    "sg:address": "970 Old Reed Rd",
    "sg:city": "North Dartmouth",
    "sg:classifiers": [
      {
        "category": "Wholesale",
        "subcategory": "Beer",
        "type": "Manufacturing \u0026 Wholesale Goods"
      }
    ],
    "sg:phone": "+1 508 999 2337",
    "sg:postcode": "02747",
    "sg:province": "MA",
    "sg:tags": [
      "ale"
    ],
    "wof:name": "Colonial Wholesale Beverage",
    "wof:placetype": "venue"
  },
  "geometry": {"coordinates":[-71.039168,41.659489],"type":"Point"}
}
