{
  "type": "Feature",
  "properties": {
    "addr:full": "5 Deacons Path Sandwich MA 02563",
    "addr:housenumber": "5",
    "addr:postcode": "02563",
    "addr:street": "Deacons Path",
    "iso:country": "US",
    "sg:address": "5 Deacons Path",
    "sg:city": "Sandwich",
    "sg:classifiers": [
      {
        "category": "Building \u0026 Trades",
        "subcategory": "Construction",
        "type": "Services"
      }
    ],
    "sg:phone": "+1 508 833 8966",
    "sg:postcode": "02563",
    "sg:province": "MA",
    "sg:tags": [
      "wallcoverings-installation",
      "wallpaper",
      "painting",
      "contractor"
    ],
    "wof:name": "E B C Painting",
    "wof:placetype": "venue"
  },
  "geometry": {"coordinates":[-70.486817,41.746557],"type":"Point"}
}
