{
  "type": "Feature",
  "properties": {
    "iso:country":"US",
    "sg:address":"394 High St",
    "sg:city":"Holyoke",
    "sg:classifiers":[
        {
            "category":"Shopping",
            "subcategory":"Clothing, Apparel, & Fashions",
            "type":"Retail Goods"
        }
    ],
    "sg:phone":"+1 413 533 3468",
    "sg:postcode":"01040",
    "sg:province":"MA",
    "wof:name":"D Got Fashions",
    "wof:placetype":"venue"
},
  "geometry": {"coordinates":[-72.610546,42.20406],"type":"Point"}
}