{
  "type": "Feature",
  "properties": {
    "addr:full": "15 Davis Rd Beverly MA 01915",
    "addr:housenumber": "15",
    "addr:postcode": "01915",
    "addr:street": "Davis Rd",
    "iso:country": "US",
    "sg:address": "15 Davis Rd",
    "sg:city": "Beverly",
    "sg:classifiers": [
      {
        "category": "Government",
        "subcategory": "Office",
        "type": "Public Place"
      }
    ],
    "sg:phone": "+1 978 927 3233",
    "sg:postcode": "01915",
    "sg:province": "MA",
    "sg:tags": [
      "parish",
      "government-county"
    ],
    "wof:name": "Essex County Ne",
    "wof:placetype": "venue"
  },
  "geometry": {"coordinates":[-70.90314,42.556294],"type":"Point"}
}
