{
  "type": "Feature",
  "properties": {
    "iso:country":"US",
    "sg:address":"162 Main St",
    "sg:city":"Brockton",
    "sg:classifiers":[
        {
            "category":"Education",
            "subcategory":"School",
            "type":"Public Place"
        }
    ],
    "sg:phone":"+1 508 427 1750",
    "sg:postcode":"02301",
    "sg:province":"MA",
    "wof:name":"Israeli School-Universal Inc",
    "wof:placetype":"venue"
},
  "geometry": {"coordinates":[-71.02008600000001,42.081429],"type":"Point"}
}