{
  "type": "Feature",
  "properties": {
    "addr:full": "21 Morton Rd Swampscott MA 01907",
    "addr:housenumber": "21",
    "addr:postcode": "01907",
    "addr:street": "Morton Rd",
    "iso:country": "US",
    "sg:address": "21 Morton Rd",
    "sg:city": "Swampscott",
    "sg:classifiers": [
      {
        "category": "Restaurant",
        "type": "Food \u0026 Drink"
      }
    ],
    "sg:phone": "+1 781 596 2733",
    "sg:postcode": "01907",
    "sg:province": "MA",
    "wof:name": "The Dory Group Inc",
    "wof:placetype": "venue"
  },
  "geometry": {"coordinates":[-70.891815,42.476398],"type":"Point"}
}
