{
  "type": "Feature",
  "properties": {
    "iso:country":"US",
    "sg:address":"21 Morton Rd",
    "sg:city":"Swampscott",
    "sg:classifiers":[
        {
            "category":"Restaurant",
            "type":"Food & Drink"
        }
    ],
    "sg:phone":"+1 781 596 2733",
    "sg:postcode":"01907",
    "sg:province":"MA",
    "wof:name":"The Dory Group Inc",
    "wof:placetype":"venue"
},
  "geometry": {"coordinates":[-70.89181499999999,42.476398],"type":"Point"}
}