{
  "type": "Feature",
  "properties": {
    "addr:full": "651 Washington St Canton MA 02021",
    "addr:housenumber": "651",
    "addr:postcode": "02021",
    "addr:street": "Washington St",
    "iso:country": "US",
    "ovtr:label": "Apollo Sub \u0026 Pizza Shop Inc, 651 Washington St Canton MA US",
    "ovtr:similarity": 2.248579978942871,
    "sg:address": "651 Washington St",
    "sg:city": "Canton",
    "sg:classifiers": [
      {
        "category": "Restaurant",
        "type": "Food \u0026 Drink"
      }
    ],
    "sg:phone": "+1 781 821 0114",
    "sg:postcode": "02021",
    "sg:province": "MA",
    "sg:tags": [
      "pizza"
    ],
    "wof:name": "Apollo Sub \u0026 Pizza Shop Inc",
    "wof:placetype": "venue"
  },
  "geometry": {"coordinates":[-71.145699,42.154999],"type":"Point"}
}
