{
  "type": "Feature",
  "properties": {
    "addr:full":"35 Station St Hingham MA 02043",
    "addr:housenumber":"35",
    "addr:postcode":"02043",
    "addr:street":"Station St",
    "iso:country":"US",
    "sg:address":"35 Station St",
    "sg:city":"Hingham",
    "sg:classifiers":[
        {
            "category":"Personal",
            "subcategory":"Beauty Salon",
            "type":"Services"
        }
    ],
    "sg:phone":"+1 781 740 7880",
    "sg:postcode":"02043",
    "sg:province":"MA",
    "sg:tags":[
        "manicuring"
    ],
    "wof:name":"D J Nails",
    "wof:placetype":"venue"
},
  "geometry": {"coordinates":[-70.88459899999999,42.243883],"type":"Point"}
}