{
  "type": "Feature",
  "properties": {
    "addr:full": "81 L St Boston MA 02127",
    "addr:housenumber": "81",
    "addr:postcode": "02127",
    "addr:street": "L St",
    "iso:country": "US",
    "sg:address": "81 L St",
    "sg:city": "Boston",
    "sg:classifiers": [
      {
        "category": "Restaurant",
        "type": "Food \u0026 Drink"
      }
    ],
    "sg:phone": "+1 617 268 8900",
    "sg:postcode": "02127",
    "sg:province": "MA",
    "sg:tags": [
      "traditional",
      "american"
    ],
    "wof:name": "Original Kelly's Landing 11",
    "wof:placetype": "venue"
  },
  "geometry": {"coordinates":[-71.035202,42.334702],"type":"Point"}
}
