{
  "type": "Feature",
  "properties": {
    "iso:country":"US",
    "sg:address":"15 Samoset Rd",
    "sg:city":"Woburn",
    "sg:classifiers":[
        {
            "category":"Building & Trades",
            "subcategory":"Landscaping Services",
            "type":"Services"
        }
    ],
    "sg:phone":"+1 781 938 1730",
    "sg:postcode":"01801",
    "sg:province":"MA",
    "sg:tags":[
        "landscape",
        "contractor"
    ],
    "wof:name":"Pride Landscaping",
    "wof:placetype":"venue"
},
  "geometry": {"coordinates":[-71.19212,42.458535],"type":"Point"}
}