{
  "type": "Feature",
  "properties": {
    "addr:full": "Massachusetts Ave/Washington St Boston MA 02118",
    "addr:postcode": "02118",
    "addr:street": "Massachusetts Ave / Washington St",
    "iso:country": "US",
    "sg:address": "Massachusetts Ave/Washington St",
    "sg:city": "Boston",
    "sg:classifiers": [
      {
        "category": "Food \u0026 Beverages",
        "subcategory": "Groceries \u0026 Convenience Stores",
        "type": "Retail Goods"
      }
    ],
    "sg:postcode": "02118",
    "sg:province": "MA",
    "wof:name": "7 Eleven",
    "wof:placetype": "venue"
  },
  "geometry": {"coordinates":[-71.078915,42.338508],"type":"Point"}
}
