{
  "type": "Feature",
  "properties": {
    "iso:country":"US",
    "sg:address":"43 State St",
    "sg:city":"Lynn",
    "sg:classifiers":[
        {
            "category":"Banks & Credit Unions",
            "subcategory":"Bank",
            "type":"Services"
        }
    ],
    "sg:phone":"+1 781 599 1878",
    "sg:postcode":"01901",
    "sg:province":"MA",
    "wof:name":"CITIZENS Bank",
    "wof:placetype":"venue"
},
  "geometry": {"coordinates":[-70.94894499999999,42.461851],"type":"Point"}
}