{
  "type": "Feature",
  "properties": {
    "addr:full": "121C Riverneck Rd Chelmsford MA 01824",
    "addr:housenumber": "121c",
    "addr:postcode": "01824",
    "addr:street": "Riverneck Rd",
    "iso:country": "US",
    "sg:address": "121C Riverneck Rd",
    "sg:city": "Chelmsford",
    "sg:classifiers": [
      {
        "category": "Home \u0026 Garden",
        "subcategory": "Building Materials",
        "type": "Retail Goods"
      },
      {
        "category": "Building \u0026 Trades",
        "subcategory": "Construction",
        "type": "Services"
      },
      {
        "category": "Military Area",
        "subcategory": "Armory",
        "type": "Public Place"
      }
    ],
    "sg:phone": "+1 978 454 1163",
    "sg:postcode": "01824",
    "sg:province": "MA",
    "sg:tags": [
      "repair",
      "fence-sales",
      "fence",
      "contractor"
    ],
    "wof:name": "B And B Fence Inc",
    "wof:placetype": "venue"
  },
  "geometry": {"coordinates":[-71.317661,42.60569],"type":"Point"}
}
