{
  "type": "Feature",
  "properties": {
    "iso:country":"US",
    "sg:address":"230 Friend St",
    "sg:city":"Boston",
    "sg:classifiers":[
        {
            "category":"Retail",
            "subcategory":"Repair Shop",
            "type":"Services"
        }
    ],
    "sg:phone":"+1 617 523 0787",
    "sg:postcode":"02114",
    "sg:province":"MA",
    "sg:tags":[
        "lock",
        "key",
        "locksmith"
    ],
    "sg:website":"www.bentonofboston.com/",
    "wof:name":"Charles W Benton Company",
    "wof:placetype":"venue"
},
  "geometry": {"coordinates":[-71.06100499999999,42.364416],"type":"Point"}
}