{
  "type": "Feature",
  "properties": {
    "addr:full":"506 Boston Post Rd Weston MA 02493",
    "addr:housenumber":"506",
    "addr:postcode":"02493",
    "addr:street":"Boston Post Rd",
    "iso:country":"US",
    "sg:address":"506 Boston Post Rd",
    "sg:city":"Weston",
    "sg:classifiers":[
        {
            "category":"Health Services",
            "subcategory":"Health Practitioner",
            "type":"Services"
        }
    ],
    "sg:phone":"+1 781 894 0900",
    "sg:postcode":"02493",
    "sg:province":"MA",
    "sg:tags":[
        "nutritionist"
    ],
    "wof:name":"Nutrition Worxs",
    "wof:placetype":"venue"
},
  "geometry": {"coordinates":[-71.302485,42.366883],"type":"Point"}
}