{
  "type": "Feature",
  "properties": {
    "iso:country":"US",
    "sg:address":"180 Commonwealth Ave",
    "sg:city":"Boston",
    "sg:classifiers":[
        {
            "category":"Banks & Credit Unions",
            "subcategory":"Investment Brokerage",
            "type":"Services"
        }
    ],
    "sg:phone":"+1 617 262 3046",
    "sg:postcode":"02116",
    "sg:province":"MA",
    "sg:tags":[
        "trust"
    ],
    "wof:name":"180 Comm Condo Trust",
    "wof:placetype":"venue"
},
  "geometry": {"coordinates":[-71.079641,42.351328],"type":"Point"}
}