{
  "type": "Feature",
  "properties": {
    "iso:country":"US",
    "sg:address":"17 Youngs Rd",
    "sg:city":"Gloucester",
    "sg:classifiers":[
        {
            "category":"Social Services",
            "subcategory":"Child Care",
            "type":"Services"
        }
    ],
    "sg:phone":"+1 978 281 8990",
    "sg:postcode":"01930",
    "sg:province":"MA",
    "sg:tags":[
        "kindergarten",
        "academic",
        "school"
    ],
    "wof:name":"Goose Cove Nursery School",
    "wof:placetype":"venue"
},
  "geometry": {"coordinates":[-70.670907,42.652477],"type":"Point"}
}