{
  "type": "Feature",
  "properties": {
    "iso:country":"US",
    "sg:address":"785 Boston Rd",
    "sg:city":"Groton",
    "sg:classifiers":[
        {
            "category":"Personal",
            "type":"Services"
        }
    ],
    "sg:phone":"+1 978 449 0169",
    "sg:postcode":"01450",
    "sg:province":"MA",
    "sg:tags":[
        "therapist",
        "massage"
    ],
    "wof:name":"Forward Motion Holistic Center",
    "wof:placetype":"venue"
},
  "geometry": {"coordinates":[-71.521012,42.579341],"type":"Point"}
}