{
  "type": "Feature",
  "properties": {
    "addr:full":"199 Court St New Bedford MA 02740",
    "addr:housenumber":"199",
    "addr:postcode":"02740",
    "addr:street":"Court St",
    "iso:country":"US",
    "sg:address":"199 Court St",
    "sg:city":"New Bedford",
    "sg:classifiers":[
        {
            "category":"Personal",
            "type":"Services"
        }
    ],
    "sg:phone":"+1 508 994 6491",
    "sg:postcode":"02740",
    "sg:province":"MA",
    "sg:tags":[
        "therapist",
        "massage"
    ],
    "wof:name":"Cabana Tanning & Toning Salon",
    "wof:placetype":"venue"
},
  "geometry": {"coordinates":[-70.938884,41.633643],"type":"Point"}
}