{
  "type": "Feature",
  "properties": {
    "iso:country":"US",
    "sg:address":"1359 Hancock St",
    "sg:city":"Quincy",
    "sg:classifiers":[
        {
            "category":"Professional",
            "subcategory":"Lawyer & Legal Services",
            "type":"Services"
        }
    ],
    "sg:phone":"+1 617 479 1177",
    "sg:postcode":"02169",
    "sg:province":"MA",
    "sg:tags":[
        "attorney"
    ],
    "wof:name":"Frederick F Cohen",
    "wof:placetype":"venue"
},
  "geometry": {"coordinates":[-71.002724,42.250419],"type":"Point"}
}