{
  "type": "Feature",
  "properties": {
    "iso:country":"US",
    "sg:address":"776 Washington St",
    "sg:city":"Canton",
    "sg:classifiers":[
        {
            "category":"Real Estate",
            "subcategory":"Real Estate Services",
            "type":"Services"
        }
    ],
    "sg:phone":"+1 781 828 4550",
    "sg:postcode":"02021",
    "sg:province":"MA",
    "sg:website":"www.successincanton.com",
    "wof:name":"Success Real Estate",
    "wof:placetype":"venue"
},
  "geometry": {"coordinates":[-71.145411,42.15842],"type":"Point"}
}