{
  "type": "Feature",
  "properties": {
    "iso:country":"US",
    "sg:address":"10 N Front St",
    "sg:city":"New Bedford",
    "sg:classifiers":[
        {
            "category":"Wholesale",
            "subcategory":"Seafood",
            "type":"Manufacturing & Wholesale Goods"
        }
    ],
    "sg:phone":"+1 508 999 1502",
    "sg:postcode":"02740",
    "sg:province":"MA",
    "wof:name":"Mac Lean's Seafood",
    "wof:placetype":"venue"
},
  "geometry": {"coordinates":[-70.924352,41.651281],"type":"Point"}
}