{
  "type": "Feature",
  "properties": {
    "addr:full": "109 Front St Scituate MA 02066",
    "addr:housenumber": "109",
    "addr:postcode": "02066",
    "addr:street": "Front St",
    "iso:country": "US",
    "ovtr:label": "Harborside Wine \u0026 Spirits, 109 Front St Scituate MA US",
    "ovtr:similarity": 1.9758960008621216,
    "sg:address": "109 Front St",
    "sg:city": "Scituate",
    "sg:classifiers": [
      {
        "category": "Food \u0026 Beverages",
        "subcategory": "Liquor \u0026 Beverages",
        "type": "Retail Goods"
      }
    ],
    "sg:phone": "+1 781 545 0059",
    "sg:postcode": "02066",
    "sg:province": "MA",
    "wof:name": "Harborside Wine \u0026 Spirits",
    "wof:placetype": "venue"
  },
  "geometry": {"coordinates":[-70.724987,42.195628],"type":"Point"}
}
