{
  "type": "Feature",
  "properties": {
    "iso:country":"US",
    "sg:address":"109 Front St",
    "sg:city":"Scituate",
    "sg:classifiers":[
        {
            "category":"Food & Beverages",
            "subcategory":"Liquor & Beverages",
            "type":"Retail Goods"
        }
    ],
    "sg:phone":"+1 781 545 0059",
    "sg:postcode":"02066",
    "sg:province":"MA",
    "wof:name":"Harborside Wine & Spirits",
    "wof:placetype":"venue"
},
  "geometry": {"coordinates":[-70.724987,42.195628],"type":"Point"}
}