{
  "type": "Feature",
  "properties": {
    "addr:full":"2 Cranberry Ln Dover MA 02030",
    "addr:housenumber":"2",
    "addr:postcode":"02030",
    "addr:street":"Cranberry Ln",
    "iso:country":"US",
    "sg:address":"2 Cranberry Ln",
    "sg:city":"Dover",
    "sg:classifiers":[
        {
            "category":"Professional",
            "subcategory":"Business Services",
            "type":"Services"
        }
    ],
    "sg:phone":"+1 508 785 1241",
    "sg:postcode":"02030",
    "sg:province":"MA",
    "sg:tags":[
        "mail",
        "shipping"
    ],
    "wof:name":"Hub Mail Company Inc",
    "wof:placetype":"venue"
},
  "geometry": {"coordinates":[-71.297798,42.249722],"type":"Point"}
}