{
  "type": "Feature",
  "properties": {
    "iso:country":"US",
    "sg:address":"509 W Washington St",
    "sg:city":"Hanson",
    "sg:classifiers":[
        {
            "category":"Personal",
            "type":"Services"
        }
    ],
    "sg:phone":"+1 781 447 4741",
    "sg:postcode":"02341",
    "sg:province":"MA",
    "sg:tags":[
        "assistant"
    ],
    "wof:name":"Gerard A Lozeau",
    "wof:placetype":"venue"
},
  "geometry": {"coordinates":[-70.89210199999999,42.063832],"type":"Point"}
}