{
  "type": "Feature",
  "properties": {
    "iso:country":"US",
    "sg:address":"7 Essex Green Dr",
    "sg:city":"Peabody",
    "sg:classifiers":[
        {
            "category":"Manufacturing",
            "subcategory":"Jewelry",
            "type":"Manufacturing & Wholesale Goods"
        }
    ],
    "sg:phone":"+1 978 531 7766",
    "sg:postcode":"01960",
    "sg:province":"MA",
    "sg:website":"www.stanpauljewelers.com",
    "wof:name":"Stan Paul Jewelry Mfg Co",
    "wof:placetype":"venue"
},
  "geometry": {"coordinates":[-70.950333,42.537648],"type":"Point"}
}