{
  "type": "Feature",
  "properties": {
    "addr:full":"84 Congress St Greenfield MA 01301",
    "addr:housenumber":"84",
    "addr:postcode":"01301",
    "addr:street":"Congress St",
    "iso:country":"US",
    "sg:address":"84 Congress St",
    "sg:city":"Greenfield",
    "sg:classifiers":[
        {
            "category":"Professional",
            "subcategory":"Business Services",
            "type":"Services"
        }
    ],
    "sg:phone":"+1   ",
    "sg:postcode":"01301",
    "sg:province":"MA",
    "sg:tags":[
        "transcription"
    ],
    "wof:name":"Word of Mouth",
    "wof:placetype":"venue"
},
  "geometry": {"coordinates":[-72.596104,42.582272],"type":"Point"}
}