{
  "type": "Feature",
  "properties": {
    "addr:full":"51 Temahigan Ave Oak Bluffs MA 02557",
    "addr:housenumber":"51",
    "addr:postcode":"02557",
    "addr:street":"Temahigan Ave",
    "iso:country":"US",
    "sg:address":"51 Temahigan Ave",
    "sg:city":"Oak Bluffs",
    "sg:classifiers":[
        {
            "category":"Government",
            "subcategory":"Police Station",
            "type":"Public Place"
        }
    ],
    "sg:phone":"+1 508 693 0545",
    "sg:postcode":"02557",
    "sg:province":"MA",
    "sg:tags":[
        "state"
    ],
    "wof:name":"State Police",
    "wof:placetype":"venue"
},
  "geometry": {"coordinates":[-70.578423,41.462103],"type":"Point"}
}