{
  "type": "Feature",
  "properties": {
    "addr:full": "76 Central St Holliston MA 01746",
    "addr:housenumber": "76",
    "addr:postcode": "01746",
    "addr:street": "Central St",
    "iso:country": "US",
    "sg:address": "76 Central St",
    "sg:city": "Holliston",
    "sg:classifiers": [
      {
        "category": "Shopping",
        "subcategory": "Gifts \u0026 Souvenirs",
        "type": "Retail Goods"
      }
    ],
    "sg:phone": "+1 508 429 1774",
    "sg:postcode": "01746",
    "sg:province": "MA",
    "sg:tags": [
      "shop"
    ],
    "wof:name": "Crabapple Corner",
    "wof:placetype": "venue"
  },
  "geometry": {"coordinates":[-71.427519,42.199916],"type":"Point"}
}
