{
  "type": "Feature",
  "properties": {
    "addr:full": "845 Quincy Shore Dr Quincy MA 02170",
    "addr:housenumber": "845",
    "addr:postcode": "02170",
    "addr:street": "Quincy Shore Dr",
    "iso:country": "US",
    "sg:address": "845 Quincy Shore Dr",
    "sg:city": "Quincy",
    "sg:classifiers": [
      {
        "category": "Professional",
        "subcategory": "Business Services",
        "type": "Services"
      }
    ],
    "sg:phone": "+1   ",
    "sg:postcode": "02170",
    "sg:province": "MA",
    "wof:name": "Best Way Associates Inc",
    "wof:placetype": "venue"
  },
  "geometry": {"coordinates":[-71.00945,42.276579],"type":"Point"}
}
