{
  "type": "Feature",
  "properties": {
    "addr:full":"2946 Falmouth Rd Marstons Mills MA 02655",
    "addr:housenumber":"2946",
    "addr:postcode":"02655",
    "addr:street":"Falmouth Rd",
    "iso:country":"US",
    "sg:address":"2946 Falmouth Rd",
    "sg:city":"Marstons Mills",
    "sg:classifiers":[
        {
            "category":"Food & Beverages",
            "subcategory":"Groceries & Convenience Stores",
            "type":"Retail Goods"
        }
    ],
    "sg:phone":"+1 508 428 8720",
    "sg:postcode":"02655",
    "sg:province":"MA",
    "sg:tags":[
        "deli"
    ],
    "sg:website":"www.newenglandpantry.com",
    "wof:name":"White Hen Pantry",
    "wof:placetype":"venue"
},
  "geometry": {"coordinates":[-70.392718,41.653402],"type":"Point"}
}