{
  "type": "Feature",
  "properties": {
    "addr:full": "105 Allston St Allston MA 02134",
    "addr:housenumber": "105",
    "addr:postcode": "02134",
    "addr:street": "Allston St",
    "iso:country": "US",
    "sg:address": "105 Allston St",
    "sg:city": "Allston",
    "sg:classifiers": [
      {
        "category": "Organizations",
        "subcategory": "Community Association",
        "type": "Services"
      }
    ],
    "sg:phone": "+1 617 787 4044",
    "sg:postcode": "02134",
    "sg:province": "MA",
    "sg:tags": [
      "club"
    ],
    "sg:website": "www.wehbgc.org",
    "wof:name": "West End House Boys \u0026 Girls",
    "wof:placetype": "venue"
  },
  "geometry": {"coordinates":[-71.136771,42.350086],"type":"Point"}
}
