{
  "type": "Feature",
  "properties": {
    "iso:country":"US",
    "sg:address":"3 Kalmia Way",
    "sg:city":"Centerville",
    "sg:classifiers":[
        {
            "category":"Banks & Credit Unions",
            "subcategory":"Bank",
            "type":"Services"
        }
    ],
    "sg:phone":"+1   ",
    "sg:postcode":"02632",
    "sg:province":"MA",
    "sg:tags":[
        "federal",
        "agency"
    ],
    "wof:name":"Triangle Imaging Systems",
    "wof:placetype":"venue"
},
  "geometry": {"coordinates":[-70.351589,41.650133],"type":"Point"}
}