{
  "type": "Feature",
  "properties": {
    "iso:country":"US",
    "sg:address":"11 Arnold St",
    "sg:city":"Westfield",
    "sg:classifiers":[
        {
            "category":"Restaurant",
            "type":"Food & Drink"
        }
    ],
    "sg:phone":"+1 413 562 5068",
    "sg:postcode":"01085",
    "sg:province":"MA",
    "wof:name":"Maple Leaf Inn",
    "wof:placetype":"venue"
},
  "geometry": {"coordinates":[-72.749387,42.122938],"type":"Point"}
}