{
  "type": "Feature",
  "properties": {
    "addr:full": "15 Gates St Boston MA 02127",
    "addr:housenumber": "15",
    "addr:postcode": "02127",
    "addr:street": "Gates St",
    "iso:country": "US",
    "sg:address": "15 Gates St",
    "sg:city": "Boston",
    "sg:classifiers": [
      {
        "category": "Building \u0026 Trades",
        "subcategory": "Construction",
        "type": "Services"
      }
    ],
    "sg:phone": "+1 617 269 4604",
    "sg:postcode": "02127",
    "sg:province": "MA",
    "sg:tags": [
      "contractor"
    ],
    "sg:website": "www.mricemanco.com",
    "wof:name": "Mr Iceman Company",
    "wof:placetype": "venue"
  },
  "geometry": {"coordinates":[-71.0485,42.3334],"type":"Point"}
}
