{
  "type": "Feature",
  "properties": {
    "addr:full":"3 Roberge Dr Tyngsboro MA 01879",
    "addr:housenumber":"3",
    "addr:postcode":"01879",
    "addr:street":"Roberge Dr",
    "iso:country":"US",
    "sg:address":"3 Roberge Dr",
    "sg:city":"Tyngsboro",
    "sg:classifiers":[
        {
            "category":"Professional",
            "type":"Services"
        }
    ],
    "sg:phone":"+1 978 649 5711",
    "sg:postcode":"01879",
    "sg:province":"MA",
    "sg:tags":[
        "establishment"
    ],
    "wof:name":"Reportability",
    "wof:placetype":"venue"
},
  "geometry": {"coordinates":[-71.472354,42.643126],"type":"Point"}
}