{
  "type": "Feature",
  "properties": {
    "iso:country":"US",
    "sg:address":"8 Ashcroft Cir",
    "sg:city":"Groveland",
    "sg:classifiers":[
        {
            "category":"Wholesale",
            "subcategory":"Machinery & Supplies",
            "type":"Manufacturing & Wholesale Goods"
        }
    ],
    "sg:phone":"+1   ",
    "sg:postcode":"01834",
    "sg:province":"MA",
    "sg:tags":[
        "equipment",
        "industrial"
    ],
    "wof:name":"Form Liberty Tool Co",
    "wof:placetype":"venue"
},
  "geometry": {"coordinates":[-71.01888700000001,42.741938],"type":"Point"}
}