{
  "type": "Feature",
  "properties": {
    "addr:full": "8 Ashcroft Cir Groveland MA 01834",
    "addr:housenumber": "8",
    "addr:postcode": "01834",
    "addr:street": "Ashcroft Cir",
    "iso:country": "US",
    "sg:address": "8 Ashcroft Cir",
    "sg:city": "Groveland",
    "sg:classifiers": [
      {
        "category": "Wholesale",
        "subcategory": "Machinery \u0026 Supplies",
        "type": "Manufacturing \u0026 Wholesale Goods"
      }
    ],
    "sg:phone": "+1   ",
    "sg:postcode": "01834",
    "sg:province": "MA",
    "sg:tags": [
      "equipment",
      "industrial"
    ],
    "wof:name": "Form Liberty Tool Co",
    "wof:placetype": "venue"
  },
  "geometry": {"coordinates":[-71.018887,42.741938],"type":"Point"}
}
