{
  "type": "Feature",
  "properties": {
    "iso:country":"US",
    "sg:address":"15 N Bedford St",
    "sg:city":"East Bridgewater",
    "sg:classifiers":[
        {
            "category":"Personal",
            "type":"Services"
        }
    ],
    "sg:phone":"+1 508 378 4071",
    "sg:postcode":"02333",
    "sg:province":"MA",
    "sg:tags":[
        "palmist"
    ],
    "wof:name":"Jeanne Palm & Tarot",
    "wof:placetype":"venue"
},
  "geometry": {"coordinates":[-70.958108,42.035397],"type":"Point"}
}