{
  "type": "Feature",
  "properties": {
    "iso:country":"US",
    "sg:address":"612 Plain St",
    "sg:city":"Marshfield",
    "sg:classifiers":[
        {
            "category":"Building & Trades",
            "subcategory":"Plumbing",
            "type":"Services"
        }
    ],
    "sg:phone":"+1 781 837 4810",
    "sg:postcode":"02050",
    "sg:province":"MA",
    "sg:tags":[
        "contractor"
    ],
    "wof:name":"Dwight Plumbing & Heating",
    "wof:placetype":"venue"
},
  "geometry": {"coordinates":[-70.739935,42.105662],"type":"Point"}
}