{
  "type": "Feature",
  "properties": {
    "addr:full": "25 Depot Ave Falmouth MA 02540",
    "addr:housenumber": "25",
    "addr:postcode": "02540",
    "addr:street": "Depot Ave",
    "iso:country": "US",
    "sg:address": "25 Depot Ave",
    "sg:city": "Falmouth",
    "sg:classifiers": [
      {
        "category": "Professional",
        "subcategory": "Advertising",
        "type": "Services"
      }
    ],
    "sg:phone": "+1 508 540 3600",
    "sg:postcode": "02540",
    "sg:province": "MA",
    "sg:tags": [
      "agency",
      "specialty"
    ],
    "wof:name": "Mediastruction",
    "wof:placetype": "venue"
  },
  "geometry": {"coordinates":[-70.622169,41.555578],"type":"Point"}
}
