{
  "type": "Feature",
  "properties": {
    "addr:full": "49 N Falmouth Hwy North Falmouth MA 02556",
    "addr:housenumber": "49",
    "addr:postcode": "02556",
    "addr:street": "N Falmouth Hwy North",
    "iso:country": "US",
    "sg:address": "49 N Falmouth Hwy",
    "sg:city": "North Falmouth",
    "sg:phone": "+1 508 563 5920",
    "sg:postcode": "02556",
    "sg:province": "MA",
    "sg:tags": [
      "food",
      "equipment",
      "processing"
    ],
    "wof:name": "Tap Tone",
    "wof:placetype": "venue"
  },
  "geometry": {"coordinates":[-70.622779,41.618143],"type":"Point"}
}
