{
  "type": "Feature",
  "properties": {
    "iso:country":"US",
    "sg:address":"49 N Falmouth Hwy",
    "sg:city":"North Falmouth",
    "sg:phone":"+1 508 563 5920",
    "sg:postcode":"02556",
    "sg:province":"MA",
    "sg:tags":[
        "food",
        "equipment",
        "processing"
    ],
    "wof:name":"Tap Tone",
    "wof:placetype":"venue"
},
  "geometry": {"coordinates":[-70.62277899999999,41.618143],"type":"Point"}
}