{
  "type": "Feature",
  "properties": {
    "addr:full": "14 Julian Ave Worcester MA 01604",
    "addr:housenumber": "14",
    "addr:postcode": "01604",
    "addr:street": "Julian Ave",
    "iso:country": "US",
    "sg:address": "14 Julian Ave",
    "sg:city": "Worcester",
    "sg:classifiers": [
      {
        "category": "Building \u0026 Trades",
        "subcategory": "Construction",
        "type": "Services"
      }
    ],
    "sg:phone": "+1 508 753 7800",
    "sg:postcode": "01604",
    "sg:province": "MA",
    "sg:tags": [
      "mason",
      "masonry",
      "industrial",
      "contractors-commercial",
      "contractor"
    ],
    "wof:name": "A\u0026S Masonry Inc",
    "wof:placetype": "venue"
  },
  "geometry": {"coordinates":[-71.768333,42.236735],"type":"Point"}
}
