{
  "type": "Feature",
  "properties": {
    "iso:country":"US",
    "sg:address":"14 Julian Ave",
    "sg:city":"Worcester",
    "sg:classifiers":[
        {
            "category":"Building & Trades",
            "subcategory":"Construction",
            "type":"Services"
        }
    ],
    "sg:phone":"+1 508 753 7800",
    "sg:postcode":"01604",
    "sg:province":"MA",
    "sg:tags":[
        "mason",
        "masonry",
        "industrial",
        "contractors-commercial",
        "contractor"
    ],
    "wof:name":"A&S Masonry Inc",
    "wof:placetype":"venue"
},
  "geometry": {"coordinates":[-71.768333,42.236735],"type":"Point"}
}