{
  "type": "Feature",
  "properties": {
    "addr:full": "15 Julie Ln Cotuit MA 02635",
    "addr:housenumber": "15",
    "addr:postcode": "02635",
    "addr:street": "Julie Ln",
    "iso:country": "US",
    "sg:address": "15 Julie Ln",
    "sg:city": "Cotuit",
    "sg:classifiers": [
      {
        "category": "Building \u0026 Trades",
        "subcategory": "Electrical",
        "type": "Services"
      }
    ],
    "sg:phone": "+1 508 428 3849",
    "sg:postcode": "02635",
    "sg:province": "MA",
    "sg:tags": [
      "electrician"
    ],
    "wof:name": "Douglas J Askew's Electric",
    "wof:placetype": "venue"
  },
  "geometry": {"coordinates":[-70.445446,41.622194],"type":"Point"}
}
