{
  "type": "Feature",
  "properties": {
    "addr:full": "22 College Hwy Southwick MA 01077",
    "addr:housenumber": "22",
    "addr:postcode": "01077",
    "addr:street": "College Hwy",
    "iso:country": "US",
    "sg:address": "22 College Hwy",
    "sg:city": "Southwick",
    "sg:classifiers": [
      {
        "category": "Professional",
        "subcategory": "Business Services",
        "type": "Services"
      }
    ],
    "sg:phone": "+1   ",
    "sg:postcode": "01077",
    "sg:province": "MA",
    "wof:name": "Bushee Enterprises LLC",
    "wof:placetype": "venue"
  },
  "geometry": {"coordinates":[-72.794932,42.001571],"type":"Point"}
}
