{
  "type": "Feature",
  "properties": {
    "addr:full":"1 Faneuil Hall Market Boston MA 02109",
    "addr:housenumber":"1",
    "addr:postcode":"02109",
    "addr:street":"Faneuil Hall Market",
    "iso:country":"US",
    "sg:address":"1 Faneuil Hall Market",
    "sg:city":"Boston",
    "sg:classifiers":[
        {
            "category":"Sports & Exercise",
            "subcategory":"Bicycle Rental",
            "type":"Entertainment"
        }
    ],
    "sg:phone":"+1 617 227 2492",
    "sg:postcode":"02109",
    "sg:province":"MA",
    "sg:tags":[
        "wear"
    ],
    "wof:name":"Sea Boston USA",
    "wof:placetype":"venue"
},
  "geometry": {"coordinates":[-71.053639,42.359749],"type":"Point"}
}