{
  "type": "Feature",
  "properties": {
    "addr:full":"905 Beacon St 4 Boston MA 02215",
    "addr:housenumber":"905;4",
    "addr:postcode":"02215",
    "addr:street":"Beacon St",
    "iso:country":"US",
    "sg:address":"905 Beacon St 4",
    "sg:city":"Boston",
    "sg:classifiers":[
        {
            "category":"Professional",
            "subcategory":"Computer Services",
            "type":"Services"
        }
    ],
    "sg:phone":"+1 888 464 2140",
    "sg:postcode":"02215",
    "sg:province":"MA",
    "sg:tags":[
        "web",
        "design",
        "hosting",
        "site"
    ],
    "wof:name":"Drundo Software",
    "wof:placetype":"venue"
},
  "geometry": {"coordinates":[-71.105842,42.346286],"type":"Point"}
}