{
  "type": "Feature",
  "properties": {
    "addr:full": "1 W Union St Ashland MA 01721",
    "addr:housenumber": "1",
    "addr:postcode": "01721",
    "addr:street": "W Union St",
    "iso:country": "US",
    "sg:address": "1 W Union St",
    "sg:city": "Ashland",
    "sg:classifiers": [
      {
        "category": "Health Services",
        "subcategory": "Chiropractor",
        "type": "Services"
      }
    ],
    "sg:phone": "+1 508 881 4443",
    "sg:postcode": "01721",
    "sg:province": "MA",
    "wof:name": "Walter M Piasecki DC",
    "wof:placetype": "venue"
  },
  "geometry": {"coordinates":[-71.466994,42.255425],"type":"Point"}
}
