{
  "type": "Feature",
  "properties": {
    "addr:full":"2003 Riverdale St West Springfield MA 01089",
    "addr:housenumber":"2003",
    "addr:postcode":"01089",
    "addr:street":"Riverdale St",
    "iso:country":"US",
    "sg:address":"2003 Riverdale St",
    "sg:city":"West Springfield",
    "sg:classifiers":[
        {
            "category":"Health Services",
            "subcategory":"Health Practitioner",
            "type":"Services"
        }
    ],
    "sg:phone":"+1 413 732 3773",
    "sg:postcode":"01089",
    "sg:province":"MA",
    "sg:tags":[
        "nurse",
        "registry"
    ],
    "wof:name":"Nursefinders",
    "wof:placetype":"venue"
},
  "geometry": {"coordinates":[-72.63266900000001,42.156608],"type":"Point"}
}