{
  "type": "Feature",
  "properties": {
    "addr:full": "23 Water St Holliston MA 01746",
    "addr:housenumber": "23",
    "addr:postcode": "01746",
    "addr:street": "Water St",
    "iso:country": "US",
    "sg:address": "23 Water St",
    "sg:city": "Holliston",
    "sg:classifiers": [
      {
        "category": "Professional",
        "subcategory": "Accounting \u0026 Tax Preparation",
        "type": "Services"
      }
    ],
    "sg:phone": "+1 508 893 0875",
    "sg:postcode": "01746",
    "sg:province": "MA",
    "sg:tags": [
      "return",
      "filing"
    ],
    "wof:name": "SDB Accounting \u0026 Tax Svc",
    "wof:placetype": "venue"
  },
  "geometry": {"coordinates":[-71.426695,42.197232],"type":"Point"}
}
