{
  "type": "Feature",
  "properties": {
    "addr:full": "274 Cooper St Springfield MA 01108",
    "addr:housenumber": "274",
    "addr:postcode": "01108",
    "addr:street": "Cooper St",
    "iso:country": "US",
    "sg:address": "274 Cooper St",
    "sg:city": "Springfield",
    "sg:classifiers": [
      {
        "category": "Wholesale",
        "subcategory": "Non-durable Goods",
        "type": "Manufacturing \u0026 Wholesale Goods"
      }
    ],
    "sg:phone": "+1 413 328 5740",
    "sg:postcode": "01108",
    "sg:province": "MA",
    "sg:tags": [
      "merchandise-wholesale"
    ],
    "wof:name": "Sps Imports",
    "wof:placetype": "venue"
  },
  "geometry": {"coordinates":[-72.540321,42.070294],"type":"Point"}
}
