{
  "type": "Feature",
  "properties": {
    "iso:country":"US",
    "sg:address":"274 Cooper St",
    "sg:city":"Springfield",
    "sg:classifiers":[
        {
            "category":"Wholesale",
            "subcategory":"Non-durable Goods",
            "type":"Manufacturing & Wholesale Goods"
        }
    ],
    "sg:phone":"+1 413 328 5740",
    "sg:postcode":"01108",
    "sg:province":"MA",
    "sg:tags":[
        "merchandise-wholesale"
    ],
    "wof:name":"Sps Imports",
    "wof:placetype":"venue"
},
  "geometry": {"coordinates":[-72.54032100000001,42.070294],"type":"Point"}
}