{
  "type": "Feature",
  "properties": {
    "addr:full":"118 Emerson Street Boston MA 02127",
    "addr:housenumber":"118",
    "addr:postcode":"02127",
    "addr:street":"Emerson Street",
    "iso:country":"US",
    "sg:address":"118 Emerson Street",
    "sg:city":"Boston",
    "sg:classifiers":[
        {
            "category":"Bars & Pubs",
            "type":"Food & Drink"
        }
    ],
    "sg:phone":"+1 617 269 9805",
    "sg:postcode":"02127",
    "sg:province":"MA",
    "wof:name":"Tom English's Cottage",
    "wof:placetype":"venue"
},
  "geometry": {"coordinates":[-71.040384,42.335758],"type":"Point"}
}