{
  "type": "Feature",
  "properties": {
    "addr:full": "118 Emerson Street Boston MA 02127",
    "addr:housenumber": "118",
    "addr:postcode": "02127",
    "addr:street": "Emerson Street",
    "iso:country": "US",
    "ovtr:label": "Tom English's Cottage, 118 Emerson St Boston MA US",
    "ovtr:similarity": 2.839026927947998,
    "sg:address": "118 Emerson Street",
    "sg:city": "Boston",
    "sg:classifiers": [
      {
        "category": "Bars \u0026 Pubs",
        "type": "Food \u0026 Drink"
      }
    ],
    "sg:phone": "+1 617 269 9805",
    "sg:postcode": "02127",
    "sg:province": "MA",
    "wof:name": "Tom English's Cottage",
    "wof:placetype": "venue"
  },
  "geometry": {"coordinates":[-71.040384,42.335758],"type":"Point"}
}
