{
  "type": "Feature",
  "properties": {
    "iso:country":"US",
    "sg:address":"13 Lansdowne St",
    "sg:city":"Boston",
    "sg:classifiers":[
        {
            "category":"Bars & Pubs",
            "type":"Food & Drink"
        }
    ],
    "sg:phone":"+1 617 262 2437",
    "sg:postcode":"02215",
    "sg:province":"MA",
    "sg:tags":[
        "club",
        "night"
    ],
    "wof:name":"Axis",
    "wof:placetype":"venue"
},
  "geometry": {"coordinates":[-71.098196,42.347247],"type":"Point"}
}