{
  "type": "Feature",
  "properties": {
    "addr:full": "13 Lansdowne St Boston MA 02215",
    "addr:housenumber": "13",
    "addr:postcode": "02215",
    "addr:street": "Lansdowne St",
    "iso:country": "US",
    "sg:address": "13 Lansdowne St",
    "sg:city": "Boston",
    "sg:classifiers": [
      {
        "category": "Bars \u0026 Pubs",
        "type": "Food \u0026 Drink"
      }
    ],
    "sg:phone": "+1 617 262 2437",
    "sg:postcode": "02215",
    "sg:province": "MA",
    "sg:tags": [
      "club",
      "night"
    ],
    "wof:name": "Axis",
    "wof:placetype": "venue"
  },
  "geometry": {"coordinates":[-71.098196,42.347247],"type":"Point"}
}
