{
  "type": "Feature",
  "properties": {
    "addr:full": "990 Tremont Street Roxbury Crossing MA 02120",
    "addr:housenumber": "990",
    "addr:postcode": "02120",
    "addr:street": "Tremont Street",
    "iso:country": "US",
    "sg:address": "990 Tremont Street",
    "sg:city": "Roxbury Crossing",
    "sg:classifiers": [
      {
        "category": "Personal",
        "subcategory": "Beauty Salon",
        "type": "Services"
      }
    ],
    "sg:phone": "+1 617 427 2620",
    "sg:postcode": "02120",
    "sg:province": "MA",
    "sg:tags": [
      "hair"
    ],
    "sg:website": "monicatoddsalon.com/",
    "wof:name": "Monicatodd Salon",
    "wof:placetype": "venue"
  },
  "geometry": {"coordinates":[-71.084056,42.337137],"type":"Point"}
}
