{
  "type": "Feature",
  "properties": {
    "addr:full": "55 Accord Park Dr Rockland MA 02370",
    "addr:housenumber": "55",
    "addr:postcode": "02370",
    "addr:street": "Accord Park Dr",
    "iso:country": "US",
    "sg:address": "55 Accord Park Dr",
    "sg:city": "Rockland",
    "sg:classifiers": [
      {
        "category": "Professional",
        "subcategory": "Management \u0026 Consulting",
        "type": "Services"
      }
    ],
    "sg:phone": "+1 781 878 3380",
    "sg:postcode": "02370",
    "sg:province": "MA",
    "wof:name": "Consumer Advisory Resources",
    "wof:placetype": "venue"
  },
  "geometry": {"coordinates":[-70.889024,42.167145],"type":"Point"}
}
