{
  "type": "Feature",
  "properties": {
    "iso:country":"US",
    "sg:address":"12 Woodleigh Rd",
    "sg:city":"Watertown",
    "sg:classifiers":[
        {
            "category":"Real Estate",
            "subcategory":"Real Estate Services",
            "type":"Services"
        },
        {
            "category":"Professional",
            "subcategory":"Business Services",
            "type":"Services"
        },
        {
            "category":"Real Estate",
            "subcategory":"Surveying",
            "type":"Services"
        }
    ],
    "sg:phone":"+1 617 393 1772",
    "sg:postcode":"02472",
    "sg:province":"MA",
    "sg:tags":[
        "appraisers-business",
        "industrial",
        "appraisers-commercial",
        "commercial",
        "appraiser"
    ],
    "wof:name":"Arc Appraisals",
    "wof:placetype":"venue"
},
  "geometry": {"coordinates":[-71.160152,42.376499],"type":"Point"}
}