{
  "type": "Feature",
  "properties": {
    "addr:full": "10 Orange St Springfield MA 01108",
    "addr:housenumber": "10",
    "addr:postcode": "01108",
    "addr:street": "Orange St",
    "iso:country": "US",
    "ovtr:label": "Red Apple, 10 Orange St Springfield MA US",
    "ovtr:similarity": 2.8938119411468506,
    "sg:address": "10 Orange St",
    "sg:city": "Springfield",
    "sg:classifiers": [
      {
        "category": "Restaurant",
        "type": "Food \u0026 Drink"
      }
    ],
    "sg:phone": "+1 413 731 7722",
    "sg:postcode": "01108",
    "sg:province": "MA",
    "wof:name": "Red Apple",
    "wof:placetype": "venue"
  },
  "geometry": {"coordinates":[-72.568419,42.093096],"type":"Point"}
}
