{
  "type": "Feature",
  "properties": {
    "addr:full":"10 Orange St Springfield MA 01108",
    "addr:housenumber":"10",
    "addr:postcode":"01108",
    "addr:street":"Orange St",
    "iso:country":"US",
    "sg:address":"10 Orange St",
    "sg:city":"Springfield",
    "sg:classifiers":[
        {
            "category":"Restaurant",
            "type":"Food & Drink"
        }
    ],
    "sg:phone":"+1 413 731 7722",
    "sg:postcode":"01108",
    "sg:province":"MA",
    "wof:name":"Red Apple",
    "wof:placetype":"venue"
},
  "geometry": {"coordinates":[-72.56841900000001,42.093096],"type":"Point"}
}