{
  "type": "Feature",
  "properties": {
    "iso:country":"US",
    "sg:address":"187 South Rd",
    "sg:city":"Bedford",
    "sg:classifiers":[
        {
            "category":"Retail",
            "subcategory":"Animal Services",
            "type":"Services"
        }
    ],
    "sg:phone":"+1 781 275 7188",
    "sg:postcode":"01730",
    "sg:province":"MA",
    "sg:tags":[
        "pet",
        "boarding/pet",
        "sitting"
    ],
    "sg:website":"www.crestviewkennel.com",
    "wof:name":"Crestview Kennel",
    "wof:placetype":"venue"
},
  "geometry": {"coordinates":[-71.273032,42.482141],"type":"Point"}
}