{
  "type": "Feature",
  "properties": {
    "addr:full":"125 Pleasant St Hyannis MA 02601",
    "addr:housenumber":"125",
    "addr:postcode":"02601",
    "addr:street":"Pleasant St",
    "iso:country":"US",
    "sg:address":"125 Pleasant St",
    "sg:city":"Hyannis",
    "sg:classifiers":[
        {
            "category":"Professional",
            "subcategory":"Lawyer & Legal Services",
            "type":"Services"
        }
    ],
    "sg:phone":"+1 508 775 3330",
    "sg:postcode":"02601",
    "sg:province":"MA",
    "sg:tags":[
        "attorney"
    ],
    "sg:website":"www.spillanelaw.com",
    "wof:name":"Spillane & Spillane Llp",
    "wof:placetype":"venue"
},
  "geometry": {"coordinates":[-70.278397,41.651699],"type":"Point"}
}