{
  "type": "Feature",
  "properties": {
    "iso:country":"US",
    "sg:address":"185 Dean St",
    "sg:city":"Norwood",
    "sg:classifiers":[
        {
            "category":"Real Estate",
            "subcategory":"Real Estate Agent",
            "type":"Services"
        }
    ],
    "sg:phone":"+1 781 769 1153",
    "sg:postcode":"02062",
    "sg:province":"MA",
    "wof:name":"John T Curran & Assoc",
    "wof:placetype":"venue"
},
  "geometry": {"coordinates":[-71.19065999999999,42.178889],"type":"Point"}
}