{
  "type": "Feature",
  "properties": {
    "addr:full":"495 Worcester St Natick MA 01760",
    "addr:housenumber":"495",
    "addr:postcode":"01760",
    "addr:street":"Worcester St",
    "iso:country":"US",
    "sg:address":"495 Worcester St",
    "sg:city":"Natick",
    "sg:classifiers":[
        {
            "category":"Cinema",
            "subcategory":"Movie Rental",
            "type":"Entertainment"
        }
    ],
    "sg:phone":"+1 508 653 3220",
    "sg:postcode":"01760",
    "sg:province":"MA",
    "sg:tags":[
        "leasing",
        "video",
        "disc",
        "tape"
    ],
    "sg:website":"www.blockbuster.com",
    "wof:name":"Blockbuster Video",
    "wof:placetype":"venue"
},
  "geometry": {"coordinates":[-71.344189,42.301709],"type":"Point"}
}