{
  "type": "Feature",
  "properties": {
    "addr:full":"84 High St Medford MA 02155",
    "addr:housenumber":"84",
    "addr:postcode":"02155",
    "addr:street":"High St",
    "iso:country":"US",
    "sg:address":"84 High St",
    "sg:city":"Medford",
    "sg:classifiers":[
        {
            "category":"Social Services",
            "type":"Services"
        }
    ],
    "sg:phone":"+1 781 391 1640",
    "sg:postcode":"02155",
    "sg:province":"MA",
    "sg:tags":[
        "counselor",
        "marriage",
        "family"
    ],
    "wof:name":"Sharon Bonnell",
    "wof:placetype":"venue"
},
  "geometry": {"coordinates":[-71.11306999999999,42.419148],"type":"Point"}
}