{
  "type": "Feature",
  "properties": {
    "addr:full": "33 Topsfield Cir Shrewsbury MA 01545",
    "addr:housenumber": "33",
    "addr:postcode": "01545",
    "addr:street": "Topsfield Cir",
    "iso:country": "US",
    "sg:address": "33 Topsfield Cir",
    "sg:city": "Shrewsbury",
    "sg:classifiers": [
      {
        "category": "Building \u0026 Trades",
        "subcategory": "Construction",
        "type": "Services"
      }
    ],
    "sg:phone": "+1 508 842 0320",
    "sg:postcode": "01545",
    "sg:province": "MA",
    "sg:tags": [
      "contractor",
      "mechanical"
    ],
    "wof:name": "Central Mass Mechanical Inc",
    "wof:placetype": "venue"
  },
  "geometry": {"coordinates":[-71.722382,42.264671],"type":"Point"}
}
