{
  "type": "Feature",
  "properties": {
    "iso:country":"US",
    "sg:address":"6 Lothrup Way",
    "sg:city":"Sharon",
    "sg:classifiers":[
        {
            "category":"Professional",
            "subcategory":"Management & Consulting",
            "type":"Services"
        }
    ],
    "sg:phone":"+1 617 314 6280",
    "sg:postcode":"02067",
    "sg:province":"MA",
    "sg:tags":[
        "consultant"
    ],
    "wof:name":"Skout Group",
    "wof:placetype":"venue"
},
  "geometry": {"coordinates":[-71.166253,42.118486],"type":"Point"}
}