{
  "type": "Feature",
  "properties": {
    "addr:full": "749 Washington St Stoughton MA 02072",
    "addr:housenumber": "749",
    "addr:postcode": "02072",
    "addr:street": "Washington St",
    "iso:country": "US",
    "sg:address": "749 Washington St",
    "sg:city": "Stoughton",
    "sg:classifiers": [
      {
        "category": "Professional",
        "type": "Services"
      }
    ],
    "sg:phone": "+1 781 341 2877",
    "sg:postcode": "02072",
    "sg:province": "MA",
    "sg:tags": [
      "establishment"
    ],
    "wof:name": "Premier Printing",
    "wof:placetype": "venue"
  },
  "geometry": {"coordinates":[-71.102242,42.125486],"type":"Point"}
}
