{
  "type": "Feature",
  "properties": {
    "iso:country":"US",
    "sg:address":"1 Oakland St",
    "sg:city":"Amesbury",
    "sg:classifiers":[
        {
            "category":"Building & Trades",
            "subcategory":"Construction",
            "type":"Services"
        }
    ],
    "sg:phone":"+1 978 388 2487",
    "sg:postcode":"01913",
    "sg:province":"MA",
    "sg:tags":[
        "woodworker"
    ],
    "wof:name":"Johnson Woodworks",
    "wof:placetype":"venue"
},
  "geometry": {"coordinates":[-70.925454,42.857603],"type":"Point"}
}