{
  "type": "Feature",
  "properties": {
    "addr:full":"58 Waterview Cir Centerville MA 02632",
    "addr:housenumber":"58",
    "addr:postcode":"02632",
    "addr:street":"Waterview Cir",
    "iso:country":"US",
    "sg:address":"58 Waterview Cir",
    "sg:city":"Centerville",
    "sg:classifiers":[
        {
            "category":"Organizations",
            "subcategory":"Non-profit Organization",
            "type":"Services"
        }
    ],
    "sg:phone":"+1   ",
    "sg:postcode":"02632",
    "sg:province":"MA",
    "sg:tags":[
        "membership",
        "social"
    ],
    "wof:name":"Abwa Cape Cod Charter Chapter",
    "wof:placetype":"venue"
},
  "geometry": {"coordinates":[-70.329803,41.680931],"type":"Point"}
}