{
  "type": "Feature",
  "properties": {
    "addr:full": "35 Olde Farms Rd Boxford MA 01921",
    "addr:housenumber": "35",
    "addr:postcode": "01921",
    "addr:street": "Olde Farms Rd",
    "iso:country": "US",
    "sg:address": "35 Olde Farms Rd",
    "sg:city": "Boxford",
    "sg:classifiers": [
      {
        "category": "Building \u0026 Trades",
        "subcategory": "Landscaping Services",
        "type": "Services"
      }
    ],
    "sg:phone": "+1   ",
    "sg:postcode": "01921",
    "sg:province": "MA",
    "sg:tags": [
      "landscape"
    ],
    "wof:name": "CC Brewer Landscaping",
    "wof:placetype": "venue"
  },
  "geometry": {"coordinates":[-71.020581,42.680493],"type":"Point"}
}
