{
  "type": "Feature",
  "properties": {
    "iso:country":"US",
    "sg:address":"350 Martin Luther King Blvd",
    "sg:city":"Roxbury",
    "sg:classifiers":[
        {
            "category":"Building & Trades",
            "subcategory":"Locksmith",
            "type":"Services"
        }
    ],
    "sg:phone":"+1 617 602 1253",
    "sg:postcode":"02119",
    "sg:province":"MA",
    "sg:tags":[
        "key"
    ],
    "wof:name":"A 24 Hour Roxbury Emergency Locksmith",
    "wof:placetype":"venue"
},
  "geometry": {"coordinates":[-71.08265400000001,42.318223],"type":"Point"}
}