{
  "type": "Feature",
  "properties": {
    "addr:full":"777 North St Pittsfield MA 01201",
    "addr:housenumber":"777",
    "addr:postcode":"01201",
    "addr:street":"North St",
    "iso:country":"US",
    "sg:address":"777 North St",
    "sg:city":"Pittsfield",
    "sg:classifiers":[
        {
            "category":"Professional",
            "type":"Services"
        }
    ],
    "sg:phone":"+1 413 499 8591",
    "sg:postcode":"01201",
    "sg:province":"MA",
    "sg:tags":[
        "establishment"
    ],
    "wof:name":"Mammography Office-Berkshire",
    "wof:placetype":"venue"
},
  "geometry": {"coordinates":[-73.247381,42.460837],"type":"Point"}
}