{
  "type": "Feature",
  "properties": {
    "iso:country":"US",
    "sg:address":"68 E Main St",
    "sg:city":"Webster",
    "sg:classifiers":[
        {
            "category":"Restaurant",
            "type":"Food & Drink"
        }
    ],
    "sg:phone":"+1 508 949 2420",
    "sg:postcode":"01570",
    "sg:province":"MA",
    "wof:name":"Lam's Chinese Eastery",
    "wof:placetype":"venue"
},
  "geometry": {"coordinates":[-71.871132,42.056938],"type":"Point"}
}