{
  "type": "Feature",
  "properties": {
    "addr:full": "68 E Main St Webster MA 01570",
    "addr:housenumber": "68",
    "addr:postcode": "01570",
    "addr:street": "E Main St",
    "iso:country": "US",
    "sg:address": "68 E Main St",
    "sg:city": "Webster",
    "sg:classifiers": [
      {
        "category": "Restaurant",
        "type": "Food \u0026 Drink"
      }
    ],
    "sg:phone": "+1 508 949 2420",
    "sg:postcode": "01570",
    "sg:province": "MA",
    "wof:name": "Lam's Chinese Eastery",
    "wof:placetype": "venue"
  },
  "geometry": {"coordinates":[-71.871132,42.056938],"type":"Point"}
}
