{
  "type": "Feature",
  "properties": {
    "addr:full": "122 Pleasant St Easthampton MA 01027",
    "addr:housenumber": "122",
    "addr:postcode": "01027",
    "addr:street": "Pleasant St",
    "iso:country": "US",
    "sg:address": "122 Pleasant St",
    "sg:city": "Easthampton",
    "sg:classifiers": [
      {
        "category": "Home \u0026 Garden",
        "subcategory": "Furniture",
        "type": "Retail Goods"
      }
    ],
    "sg:phone": "+1 413 527 6268",
    "sg:postcode": "01027",
    "sg:province": "MA",
    "sg:tags": [
      "top",
      "counter"
    ],
    "wof:name": "Payne \u0026 Picard",
    "wof:placetype": "venue"
  },
  "geometry": {"coordinates":[-72.66153,42.274148],"type":"Point"}
}
