{
  "type": "Feature",
  "properties": {
    "addr:full": "122 Western Ave Ste A305 Lowell MA 01851",
    "addr:housenumber": "122",
    "addr:postcode": "01851",
    "addr:street": "Western Ave Ste A305",
    "iso:country": "US",
    "sg:address": "122 Western Ave Ste A305",
    "sg:city": "Lowell",
    "sg:classifiers": [
      {
        "category": "Shopping",
        "subcategory": "Crafts \u0026 Fabrics",
        "type": "Retail Goods"
      }
    ],
    "sg:phone": "+1 978 970 0711",
    "sg:postcode": "01851",
    "sg:province": "MA",
    "sg:tags": [
      "supplies-wholesale",
      "manufacturer",
      "art",
      "supply"
    ],
    "wof:name": "Made In Lowell",
    "wof:placetype": "venue"
  },
  "geometry": {"coordinates":[-71.320461,42.640106],"type":"Point"}
}
