{
  "type": "Feature",
  "properties": {
    "addr:full":"572 Washington St Wellesley MA 02482",
    "addr:housenumber":"572",
    "addr:postcode":"02482",
    "addr:street":"Washington St",
    "iso:country":"US",
    "sg:address":"572 Washington St",
    "sg:city":"Wellesley",
    "sg:classifiers":[
        {
            "category":"Professional",
            "subcategory":"Lawyer & Legal Services",
            "type":"Services"
        }
    ],
    "sg:phone":"+1 781 431 7878",
    "sg:postcode":"02482",
    "sg:province":"MA",
    "sg:tags":[
        "attorney"
    ],
    "wof:name":"Brand & Assoc",
    "wof:placetype":"venue"
},
  "geometry": {"coordinates":[-71.293053,42.296469],"type":"Point"}
}