{
  "type": "Feature",
  "properties": {
    "addr:full":"190 S Tessier St Northbridge MA 01534",
    "addr:housenumber":"190",
    "addr:postcode":"01534",
    "addr:street":"S Tessier St",
    "iso:country":"US",
    "sg:address":"190 S Tessier St",
    "sg:city":"Northbridge",
    "sg:classifiers":[
        {
            "category":"Building & Trades",
            "subcategory":"Construction",
            "type":"Services"
        }
    ],
    "sg:phone":"+1 508 901 0020",
    "sg:postcode":"01534",
    "sg:province":"MA",
    "sg:tags":[
        "concrete",
        "contractor"
    ],
    "wof:name":"Ryex Concrete Construction",
    "wof:placetype":"venue"
},
  "geometry": {"coordinates":[-71.649501,42.147267],"type":"Point"}
}