{
  "type": "Feature",
  "properties": {
    "addr:full": "218 W Main St Ste 3 Hyannis MA 02601",
    "addr:housenumber": "218",
    "addr:postcode": "02601",
    "addr:street": "W Main St Ste 3",
    "iso:country": "US",
    "sg:address": "218 W Main St Ste 3",
    "sg:city": "Hyannis",
    "sg:classifiers": [
      {
        "category": "Professional",
        "subcategory": "Lawyer \u0026 Legal Services",
        "type": "Services"
      }
    ],
    "sg:phone": "+1 508 771 1155",
    "sg:postcode": "02601",
    "sg:province": "MA",
    "wof:name": "Largay Richard",
    "wof:placetype": "venue"
  },
  "geometry": {"coordinates":[-70.303951,41.64793],"type":"Point"}
}
