{
  "type": "Feature",
  "properties": {
    "addr:full":"204 College Hwy Southampton MA 01073",
    "addr:housenumber":"204",
    "addr:postcode":"01073",
    "addr:street":"College Hwy",
    "iso:country":"US",
    "sg:address":"204 College Hwy",
    "sg:city":"Southampton",
    "sg:classifiers":[
        {
            "category":"Government",
            "subcategory":"Fire Station",
            "type":"Public Place"
        }
    ],
    "sg:phone":"+1   ",
    "sg:postcode":"01073",
    "sg:province":"MA",
    "sg:tags":[
        "protection"
    ],
    "wof:name":"Southampton Vlntr Fire Dept",
    "wof:placetype":"venue"
},
  "geometry": {"coordinates":[-72.729062,42.230433],"type":"Point"}
}