{
  "type": "Feature",
  "properties": {
    "addr:full": "74 Corneau St Fall River MA 02721",
    "addr:housenumber": "74",
    "addr:postcode": "02721",
    "addr:street": "Corneau St",
    "iso:country": "US",
    "sg:address": "74 Corneau St",
    "sg:city": "Fall River",
    "sg:classifiers": [
      {
        "category": "Real Estate",
        "subcategory": "Real Estate Agent",
        "type": "Services"
      }
    ],
    "sg:phone": "+1 508 675 5004",
    "sg:postcode": "02721",
    "sg:province": "MA",
    "sg:tags": [
      "management"
    ],
    "wof:name": "Dankar Inc",
    "wof:placetype": "venue"
  },
  "geometry": {"coordinates":[-71.151501,41.699964],"type":"Point"}
}
