{
  "type": "Feature",
  "properties": {
    "iso:country":"US",
    "sg:address":"15 Oak St",
    "sg:city":"Amesbury",
    "sg:classifiers":[
        {
            "category":"Building & Trades",
            "subcategory":"Plumbing",
            "type":"Services"
        }
    ],
    "sg:phone":"+1 978 388 0088",
    "sg:postcode":"01913",
    "sg:province":"MA",
    "sg:tags":[
        "plumbing",
        "contractor"
    ],
    "wof:name":"M E Reed Co",
    "wof:placetype":"venue"
},
  "geometry": {"coordinates":[-70.922884,42.853304],"type":"Point"}
}