{
  "type": "Feature",
  "properties": {
    "addr:full": "15 Oak St Amesbury MA 01913",
    "addr:housenumber": "15",
    "addr:postcode": "01913",
    "addr:street": "Oak St",
    "iso:country": "US",
    "sg:address": "15 Oak St",
    "sg:city": "Amesbury",
    "sg:classifiers": [
      {
        "category": "Building \u0026 Trades",
        "subcategory": "Plumbing",
        "type": "Services"
      }
    ],
    "sg:phone": "+1 978 388 0088",
    "sg:postcode": "01913",
    "sg:province": "MA",
    "sg:tags": [
      "plumbing",
      "contractor"
    ],
    "wof:name": "M E Reed Co",
    "wof:placetype": "venue"
  },
  "geometry": {"coordinates":[-70.922884,42.853304],"type":"Point"}
}
