{
  "type": "Feature",
  "properties": {
    "iso:country":"US",
    "sg:address":"115 Lowell St",
    "sg:city":"Peabody",
    "sg:classifiers":[
        {
            "category":"Restaurant",
            "type":"Food & Drink"
        }
    ],
    "sg:phone":"+1 978 977 7989",
    "sg:postcode":"01960",
    "sg:province":"MA",
    "sg:tags":[
        "eating"
    ],
    "wof:name":"Marcos Abbondante Pizzeria",
    "wof:placetype":"venue"
},
  "geometry": {"coordinates":[-70.933289,42.528242],"type":"Point"}
}