{
  "type": "Feature",
  "properties": {
    "iso:country":"US",
    "sg:address":"1471 Highland Ave",
    "sg:city":"Needham",
    "sg:classifiers":[
        {
            "category":"Government",
            "subcategory":"Office",
            "type":"Public Place"
        }
    ],
    "sg:phone":"+1 781 455 7515",
    "sg:postcode":"02492",
    "sg:province":"MA",
    "sg:tags":[
        "village"
    ],
    "wof:name":"Needham Town Counsel",
    "wof:placetype":"venue"
},
  "geometry": {"coordinates":[-71.236175,42.282113],"type":"Point"}
}