{
  "type": "Feature",
  "properties": {
    "addr:full":"1083 Pleasant St Worcester MA 01602",
    "addr:housenumber":"1083",
    "addr:postcode":"01602",
    "addr:street":"Pleasant St",
    "iso:country":"US",
    "sg:address":"1083 Pleasant St",
    "sg:city":"Worcester",
    "sg:classifiers":[
        {
            "category":"Education",
            "subcategory":"School",
            "type":"Public Place"
        }
    ],
    "sg:phone":"+1 508 799 3554",
    "sg:postcode":"01602",
    "sg:province":"MA",
    "wof:name":"Tatnuck Magnet Elementary Schl",
    "wof:placetype":"venue"
},
  "geometry": {"coordinates":[-71.849476,42.278196],"type":"Point"}
}