{
  "type": "Feature",
  "properties": {
    "iso:country":"US",
    "sg:address":"227 Prospect St",
    "sg:city":"Cambridge",
    "sg:classifiers":[
        {
            "category":"Retail",
            "subcategory":"Auto Repair",
            "type":"Services"
        }
    ],
    "sg:phone":"+1 617 547 1950",
    "sg:postcode":"02139",
    "sg:province":"MA",
    "sg:tags":[
        "repairing",
        "automobile"
    ],
    "sg:website":"www.hondarhouse.com",
    "wof:name":"Hondar House",
    "wof:placetype":"venue"
},
  "geometry": {"coordinates":[-71.1002,42.3711],"type":"Point"}
}