{
  "type": "Feature",
  "properties": {
    "iso:country":"US",
    "sg:address":"1900 Main St",
    "sg:city":"Tewksbury",
    "sg:classifiers":[
        {
            "category":"Food & Beverages",
            "subcategory":"Liquor & Beverages",
            "type":"Retail Goods"
        }
    ],
    "sg:phone":"+1 978 851 5512",
    "sg:postcode":"01876",
    "sg:province":"MA",
    "wof:name":"Oakdale Liquors",
    "wof:placetype":"venue"
},
  "geometry": {"coordinates":[-71.203125,42.589951],"type":"Point"}
}