{
  "type": "Feature",
  "properties": {
    "addr:full": "84 Sherman St Cambridge MA 02140",
    "addr:housenumber": "84",
    "addr:postcode": "02140",
    "addr:street": "Sherman St",
    "iso:country": "US",
    "sg:address": "84 Sherman St",
    "sg:city": "Cambridge",
    "sg:classifiers": [
      {
        "category": "Professional",
        "subcategory": "Engineering",
        "type": "Services"
      }
    ],
    "sg:phone": "+1 617 864 1944",
    "sg:postcode": "02140",
    "sg:province": "MA",
    "sg:tags": [
      "engineer"
    ],
    "sg:website": "www.anteon.com",
    "wof:name": "Cambridge Acoustical Assoc",
    "wof:placetype": "venue"
  },
  "geometry": {"coordinates":[-71.132148,42.387966],"type":"Point"}
}
