{
  "type": "Feature",
  "properties": {
    "iso:country":"US",
    "sg:address":"1071 Blue Hill Ave",
    "sg:city":"Milton",
    "sg:classifiers":[
        {
            "category":"Communications",
            "subcategory":"Radio Station",
            "type":"Services"
        }
    ],
    "sg:phone":"+1 617 333 0311",
    "sg:postcode":"02186",
    "sg:province":"MA",
    "sg:tags":[
        "company",
        "broadcasting"
    ],
    "sg:website":"www.curry.edu",
    "wof:name":"WMLN",
    "wof:placetype":"venue"
},
  "geometry": {"coordinates":[-71.11083000000001,42.235631],"type":"Point"}
}