{
  "type": "Feature",
  "properties": {
    "addr:full": "785 Washington St Canton MA 02021",
    "addr:housenumber": "785",
    "addr:postcode": "02021",
    "addr:street": "Washington St",
    "iso:country": "US",
    "sg:address": "785 Washington St",
    "sg:city": "Canton",
    "sg:classifiers": [
      {
        "category": "Professional",
        "subcategory": "Lawyer \u0026 Legal Services",
        "type": "Services"
      }
    ],
    "sg:phone": "+1 781 828 2007",
    "sg:postcode": "02021",
    "sg:province": "MA",
    "wof:name": "Connolly Christopher J Law Office of",
    "wof:placetype": "venue"
  },
  "geometry": {"coordinates":[-71.144965,42.158509],"type":"Point"}
}
