{
  "type": "Feature",
  "properties": {
    "iso:country":"US",
    "sg:address":"785 Washington St",
    "sg:city":"Canton",
    "sg:classifiers":[
        {
            "category":"Professional",
            "subcategory":"Lawyer & Legal Services",
            "type":"Services"
        }
    ],
    "sg:phone":"+1 781 828 2007",
    "sg:postcode":"02021",
    "sg:province":"MA",
    "wof:name":"Connolly Christopher J Law Office of",
    "wof:placetype":"venue"
},
  "geometry": {"coordinates":[-71.144965,42.158509],"type":"Point"}
}