{
  "type": "Feature",
  "properties": {
    "iso:country":"US",
    "sg:address":"251 Park St",
    "sg:city":"Easthampton",
    "sg:classifiers":[
        {
            "category":"Building & Trades",
            "subcategory":"Plumbing",
            "type":"Services"
        }
    ],
    "sg:phone":"+1   ",
    "sg:postcode":"01027",
    "sg:province":"MA",
    "sg:tags":[
        "contractor"
    ],
    "wof:name":"Norms Plumbing & Heating",
    "wof:placetype":"venue"
},
  "geometry": {"coordinates":[-72.68278599999999,42.244068],"type":"Point"}
}