{
  "type": "Feature",
  "properties": {
    "iso:country":"US",
    "sg:address":"288 Route 101",
    "sg:city":"Bedford",
    "sg:classifiers":[
        {
            "category":"Banks & Credit Unions",
            "subcategory":"Financial Services",
            "type":"Services"
        }
    ],
    "sg:phone":"+1 781 245 5111",
    "sg:postcode":"01730",
    "sg:province":"MA",
    "sg:tags":[
        "broker",
        "mortgage"
    ],
    "wof:name":"Guaranty Residential Lending Inc - CLOSED",
    "wof:placetype":"venue"
},
  "geometry": {"coordinates":[-71.278999,42.4949],"type":"Point"}
}