{
  "type": "Feature",
  "properties": {
    "iso:country":"US",
    "sg:address":"3 Dundee Park Dr",
    "sg:city":"Andover",
    "sg:classifiers":[
        {
            "category":"Shopping",
            "subcategory":"Shoes",
            "type":"Retail Goods"
        }
    ],
    "sg:phone":"+1 978 247 6049",
    "sg:postcode":"01810",
    "sg:province":"MA",
    "wof:name":"Global Shoeworks",
    "wof:placetype":"venue"
},
  "geometry": {"coordinates":[-71.145922,42.655195],"type":"Point"}
}