{
  "type": "Feature",
  "properties": {
    "iso:country":"US",
    "sg:address":"220 Crockers Neck Rd",
    "sg:city":"Cotuit",
    "sg:classifiers":[
        {
            "category":"Home & Garden",
            "subcategory":"Furniture",
            "type":"Retail Goods"
        }
    ],
    "sg:phone":"+1   ",
    "sg:postcode":"02635",
    "sg:province":"MA",
    "wof:name":"Finish Woodworks",
    "wof:placetype":"venue"
},
  "geometry": {"coordinates":[-70.448286,41.613474],"type":"Point"}
}