{
  "type": "Feature",
  "properties": {
    "addr:full": "220 Crockers Neck Rd Cotuit MA 02635",
    "addr:housenumber": "220",
    "addr:postcode": "02635",
    "addr:street": "Crockers Neck Rd",
    "iso:country": "US",
    "sg:address": "220 Crockers Neck Rd",
    "sg:city": "Cotuit",
    "sg:classifiers": [
      {
        "category": "Home \u0026 Garden",
        "subcategory": "Furniture",
        "type": "Retail Goods"
      }
    ],
    "sg:phone": "+1   ",
    "sg:postcode": "02635",
    "sg:province": "MA",
    "wof:name": "Finish Woodworks",
    "wof:placetype": "venue"
  },
  "geometry": {"coordinates":[-70.448286,41.613474],"type":"Point"}
}
