{
  "type": "Feature",
  "properties": {
    "iso:country":"US",
    "sg:address":"675 Oak St",
    "sg:city":"West Barnstable",
    "sg:classifiers":[
        {
            "category":"Building & Trades",
            "subcategory":"Construction",
            "type":"Services"
        }
    ],
    "sg:phone":"+1 508 362 8807",
    "sg:postcode":"02668",
    "sg:province":"MA",
    "sg:tags":[
        "insulation",
        "heat",
        "contractor"
    ],
    "wof:name":"Insulation Specialists",
    "wof:placetype":"venue"
},
  "geometry": {"coordinates":[-70.349507,41.688081],"type":"Point"}
}