{
  "type": "Feature",
  "properties": {
    "iso:country":"US",
    "sg:address":"112 Hollis St",
    "sg:city":"Framingham",
    "sg:classifiers":[
        {
            "category":"Social Services",
            "subcategory":"Child Care",
            "type":"Services"
        }
    ],
    "sg:phone":"+1 508 872 7698",
    "sg:postcode":"01702",
    "sg:province":"MA",
    "wof:name":"South Middlesex Latin Emrgncy",
    "wof:placetype":"venue"
},
  "geometry": {"coordinates":[-71.41669,42.275995],"type":"Point"}
}