{
  "type": "Feature",
  "properties": {
    "iso:country":"US",
    "sg:address":"56 Merrill St",
    "sg:city":"Amesbury",
    "sg:classifiers":[
        {
            "category":"Travel",
            "subcategory":"Travel Agent",
            "type":"Entertainment"
        }
    ],
    "sg:phone":"+1 978 388 7884",
    "sg:postcode":"01913",
    "sg:province":"MA",
    "sg:tags":[
        "agency",
        "bureau"
    ],
    "wof:name":"Roatan Resevations",
    "wof:placetype":"venue"
},
  "geometry": {"coordinates":[-70.903555,42.841025],"type":"Point"}
}