{
  "type": "Feature",
  "properties": {
    "iso:country":"US",
    "sg:address":"3 Glacier Way",
    "sg:city":"Buzzards Bay",
    "sg:classifiers":[
        {
            "category":"Personal",
            "subcategory":"Beauty Salon",
            "type":"Services"
        }
    ],
    "sg:phone":"+1 508 888 3401",
    "sg:postcode":"02532",
    "sg:province":"MA",
    "wof:name":"Jamie's Beauty Express",
    "wof:placetype":"venue"
},
  "geometry": {"coordinates":[-70.56824400000001,41.77481],"type":"Point"}
}