{
  "type": "Feature",
  "properties": {
    "iso:country":"US",
    "sg:address":"54 Chase Rd",
    "sg:city":"Lunenburg",
    "sg:classifiers":[
        {
            "category":"Shopping",
            "subcategory":"Used Merchandise",
            "type":"Retail Goods"
        }
    ],
    "sg:phone":"+1 978 582 7831",
    "sg:postcode":"01462",
    "sg:province":"MA",
    "sg:tags":[
        "antique"
    ],
    "wof:name":"Jeffrey's Antique Co-Op",
    "wof:placetype":"venue"
},
  "geometry": {"coordinates":[-71.750434,42.597099],"type":"Point"}
}