{
  "type": "Feature",
  "properties": {
    "addr:full": "65 Woodcliff Rd Chestnut Hill MA 02445",
    "addr:housenumber": "65",
    "addr:postcode": "02445",
    "addr:street": "Woodcliff Rd",
    "iso:country": "US",
    "sg:address": "65 Woodcliff Rd",
    "sg:city": "Chestnut Hill",
    "sg:classifiers": [
      {
        "category": "Professional",
        "subcategory": "Business Services",
        "type": "Services"
      }
    ],
    "sg:phone": "+1   ",
    "sg:postcode": "02445",
    "sg:province": "MA",
    "wof:name": "Atlantic Enterprises Group",
    "wof:placetype": "venue"
  },
  "geometry": {"coordinates":[-71.146821,42.297538],"type":"Point"}
}
