{
  "type": "Feature",
  "properties": {
    "addr:full":"24 Wadsworth Rd Ashland MA 01721",
    "addr:housenumber":"24",
    "addr:postcode":"01721",
    "addr:street":"Wadsworth Rd",
    "iso:country":"US",
    "sg:address":"24 Wadsworth Rd",
    "sg:city":"Ashland",
    "sg:classifiers":[
        {
            "category":"Wholesale",
            "subcategory":"Durable Goods & Equipment",
            "type":"Manufacturing & Wholesale Goods"
        }
    ],
    "sg:phone":"+1 508 881 1181",
    "sg:postcode":"01721",
    "sg:province":"MA",
    "sg:tags":[
        "video"
    ],
    "wof:name":"Austin Harley Enterprise",
    "wof:placetype":"venue"
},
  "geometry": {"coordinates":[-71.441771,42.256225],"type":"Point"}
}