{
  "type": "Feature",
  "properties": {
    "iso:country":"US",
    "sg:address":"55 Sunrise Ln",
    "sg:city":"Gardner",
    "sg:classifiers":[
        {
            "category":"Real Estate",
            "subcategory":"Real Estate Operator",
            "type":"Services"
        }
    ],
    "sg:phone":"+1 978 632 7375",
    "sg:postcode":"01440",
    "sg:province":"MA",
    "sg:tags":[
        "mobile",
        "home",
        "site"
    ],
    "wof:name":"Heritage Village",
    "wof:placetype":"venue"
},
  "geometry": {"coordinates":[-71.975961,42.557308],"type":"Point"}
}