{
  "type": "Feature",
  "properties": {
    "iso:country":"US",
    "sg:address":"67 Union St",
    "sg:city":"Natick",
    "sg:classifiers":[
        {
            "category":"Health Services",
            "subcategory":"Doctor",
            "type":"Services"
        }
    ],
    "sg:phone":"+1 508 650 5440",
    "sg:postcode":"01760",
    "sg:province":"MA",
    "sg:tags":[
        "dentist"
    ],
    "wof:name":"William F Mulroy DDS",
    "wof:placetype":"venue"
},
  "geometry": {"coordinates":[-71.33069399999999,42.279514],"type":"Point"}
}