{
  "type": "Feature",
  "properties": {
    "addr:full":"2 Edge Hill Rd Sharon MA 02067",
    "addr:housenumber":"2",
    "addr:postcode":"02067",
    "addr:street":"Edge Hill Rd",
    "iso:country":"US",
    "sg:address":"2 Edge Hill Rd",
    "sg:city":"Sharon",
    "sg:classifiers":[
        {
            "category":"Professional",
            "subcategory":"Employment Agencies",
            "type":"Services"
        }
    ],
    "sg:phone":"+1 781 793 9010",
    "sg:postcode":"02067",
    "sg:province":"MA",
    "wof:name":"First Rate Staffing - CLOSED",
    "wof:placetype":"venue"
},
  "geometry": {"coordinates":[-71.19909699999999,42.144402],"type":"Point"}
}