{
  "type": "Feature",
  "properties": {
    "addr:full": "18 Pearl St Middleboro MA 02346",
    "addr:housenumber": "18",
    "addr:postcode": "02346",
    "addr:street": "Pearl St",
    "iso:country": "US",
    "sg:address": "18 Pearl St",
    "sg:city": "Middleboro",
    "sg:classifiers": [
      {
        "category": "Banks \u0026 Credit Unions",
        "subcategory": "Bank",
        "type": "Services"
      }
    ],
    "sg:phone": "+1 508 947 3901",
    "sg:postcode": "02346",
    "sg:province": "MA",
    "sg:tags": [
      "loan"
    ],
    "wof:name": "Medfunds",
    "wof:placetype": "venue"
  },
  "geometry": {"coordinates":[-70.914049,41.89113],"type":"Point"}
}
