{
  "type": "Feature",
  "properties": {
    "iso:country":"US",
    "sg:address":"18 Pearl St",
    "sg:city":"Middleboro",
    "sg:classifiers":[
        {
            "category":"Banks & Credit Unions",
            "subcategory":"Bank",
            "type":"Services"
        }
    ],
    "sg:phone":"+1 508 947 3901",
    "sg:postcode":"02346",
    "sg:province":"MA",
    "sg:tags":[
        "loan"
    ],
    "wof:name":"Medfunds",
    "wof:placetype":"venue"
},
  "geometry": {"coordinates":[-70.91404900000001,41.89113],"type":"Point"}
}