{
  "type": "Feature",
  "properties": {
    "addr:full": "256 Beacon St Boston MA 02116",
    "addr:housenumber": "256",
    "addr:postcode": "02116",
    "addr:street": "Beacon St",
    "iso:country": "US",
    "sg:address": "256 Beacon St",
    "sg:city": "Boston",
    "sg:classifiers": [
      {
        "category": "Communications",
        "subcategory": "News Services",
        "type": "Services"
      }
    ],
    "sg:phone": "+1   ",
    "sg:postcode": "02116",
    "sg:province": "MA",
    "sg:tags": [
      "syndicate"
    ],
    "wof:name": "Christian SC Pbg SC Vol Tr",
    "wof:placetype": "venue"
  },
  "geometry": {"coordinates":[-71.080391,42.353395],"type":"Point"}
}
