{
  "type": "Feature",
  "properties": {
    "addr:full": "591 Memorial Dr Chicopee MA 01020",
    "addr:housenumber": "591",
    "addr:postcode": "01020",
    "addr:street": "Memorial Dr",
    "iso:country": "US",
    "sg:address": "591 Memorial Dr",
    "sg:city": "Chicopee",
    "sg:classifiers": [
      {
        "category": "Retail",
        "subcategory": "Portrait Studio",
        "type": "Services"
      }
    ],
    "sg:phone": "+1 413 593 9217",
    "sg:postcode": "01020",
    "sg:province": "MA",
    "sg:tags": [
      "photographer"
    ],
    "wof:name": "Wal-Mart Portrait Studio",
    "wof:placetype": "venue"
  },
  "geometry": {"coordinates":[-72.576331,42.1734],"type":"Point"}
}
