{
  "type": "Feature",
  "properties": {
    "addr:full": "35 Thomson Pl Boston MA 02210",
    "addr:housenumber": "35",
    "addr:postcode": "02210",
    "addr:street": "Thomson Pl",
    "iso:country": "US",
    "sg:address": "35 Thomson Pl",
    "sg:city": "Boston",
    "sg:classifiers": [
      {
        "category": "Professional",
        "subcategory": "Computer Services",
        "type": "Services"
      }
    ],
    "sg:phone": "+1 617 856 5040",
    "sg:postcode": "02210",
    "sg:province": "MA",
    "sg:tags": [
      "consultant",
      "designer"
    ],
    "sg:website": "www.sourcemedia.com",
    "wof:name": "National Regulatory Svc",
    "wof:placetype": "venue"
  },
  "geometry": {"coordinates":[-71.04721,42.35028],"type":"Point"}
}
