{
  "type": "Feature",
  "properties": {
    "iso:country":"US",
    "sg:address":"259 Piper Rd",
    "sg:city":"Ashby",
    "sg:classifiers":[
        {
            "category":"Farming",
            "subcategory":"Farm",
            "type":"Manufacturing & Wholesale Goods"
        }
    ],
    "sg:phone":"+1 978 386 7912",
    "sg:postcode":"01431",
    "sg:province":"MA",
    "wof:name":"Michael A Reggio",
    "wof:placetype":"venue"
},
  "geometry": {"coordinates":[-71.82513299999999,42.671182],"type":"Point"}
}