{
  "type": "Feature",
  "properties": {
    "addr:full": "259 Piper Rd Ashby MA 01431",
    "addr:housenumber": "259",
    "addr:postcode": "01431",
    "addr:street": "Piper Rd",
    "iso:country": "US",
    "sg:address": "259 Piper Rd",
    "sg:city": "Ashby",
    "sg:classifiers": [
      {
        "category": "Farming",
        "subcategory": "Farm",
        "type": "Manufacturing \u0026 Wholesale Goods"
      }
    ],
    "sg:phone": "+1 978 386 7912",
    "sg:postcode": "01431",
    "sg:province": "MA",
    "wof:name": "Michael A Reggio",
    "wof:placetype": "venue"
  },
  "geometry": {"coordinates":[-71.825133,42.671182],"type":"Point"}
}
