{
  "type": "Feature",
  "properties": {
    "addr:full":"650 Plymouth St East Bridgewater MA 02333",
    "addr:housenumber":"650",
    "addr:postcode":"02333",
    "addr:street":"Plymouth St",
    "iso:country":"US",
    "sg:address":"650 Plymouth St",
    "sg:city":"East Bridgewater",
    "sg:classifiers":[
        {
            "category":"Insurance",
            "subcategory":"Insurance Agent",
            "type":"Services"
        }
    ],
    "sg:phone":"+1 508 378 2388",
    "sg:postcode":"02333",
    "sg:province":"MA",
    "wof:name":"Primerica Financial Svc",
    "wof:placetype":"venue"
},
  "geometry": {"coordinates":[-70.939149,42.01529],"type":"Point"}
}