{
  "type": "Feature",
  "properties": {
    "iso:country":"US",
    "sg:address":"273 Osborne Rd",
    "sg:city":"Ware",
    "sg:classifiers":[
        {
            "category":"Building & Trades",
            "subcategory":"Pest Control",
            "type":"Services"
        }
    ],
    "sg:phone":"+1 413 967 7427",
    "sg:postcode":"01082",
    "sg:province":"MA",
    "wof:name":"Quality Pest Control",
    "wof:placetype":"venue"
},
  "geometry": {"coordinates":[-72.251986,42.300966],"type":"Point"}
}