{
  "type": "Feature",
  "properties": {
    "addr:full": "21 Spring Bars Rd Falmouth MA 02540",
    "addr:housenumber": "21",
    "addr:postcode": "02540",
    "addr:street": "Spring Bars Rd",
    "iso:country": "US",
    "sg:address": "21 Spring Bars Rd",
    "sg:city": "Falmouth",
    "sg:classifiers": [
      {
        "category": "Food \u0026 Beverages",
        "subcategory": "Liquor \u0026 Beverages",
        "type": "Retail Goods"
      }
    ],
    "sg:phone": "+1 508 548 2600",
    "sg:postcode": "02540",
    "sg:province": "MA",
    "sg:website": "www.kappys.com",
    "wof:name": "Kappy's Liquors",
    "wof:placetype": "venue"
  },
  "geometry": {"coordinates":[-70.597898,41.55772],"type":"Point"}
}
