{
  "type": "Feature",
  "properties": {
    "iso:country":"US",
    "sg:address":"21 Spring Bars Rd",
    "sg:city":"Falmouth",
    "sg:classifiers":[
        {
            "category":"Food & Beverages",
            "subcategory":"Liquor & Beverages",
            "type":"Retail Goods"
        }
    ],
    "sg:phone":"+1 508 548 2600",
    "sg:postcode":"02540",
    "sg:province":"MA",
    "sg:website":"www.kappys.com",
    "wof:name":"Kappy's Liquors",
    "wof:placetype":"venue"
},
  "geometry": {"coordinates":[-70.597898,41.55772],"type":"Point"}
}