{
  "type": "Feature",
  "properties": {
    "addr:full":"Riverview Avenue Mashpee MA 02649",
    "addr:postcode":"02649",
    "addr:street":"Riverview Avenue",
    "iso:country":"US",
    "sg:address":"Riverview Avenue",
    "sg:city":"Mashpee",
    "sg:classifiers":[
        {
            "category":"Professional",
            "subcategory":"Computer Services",
            "type":"Services"
        }
    ],
    "sg:phone":"+1 508 275 2268",
    "sg:postcode":"02649",
    "sg:province":"MA",
    "sg:tags":[
        "portfolio",
        "web-design",
        "drupal",
        "wordpress",
        "themes",
        "illustration",
        "print-design",
        "paintings",
        "book-covers"
    ],
    "sg:website":"http://bittennails.com",
    "wof:name":"BittenNails Design",
    "wof:placetype":"venue"
},
  "geometry": {"coordinates":[-70.45192,41.618477],"type":"Point"}
}