{
  "type": "Feature",
  "properties": {
    "addr:full":"1758 River St Hyde Park MA 02136",
    "addr:housenumber":"1758",
    "addr:postcode":"02136",
    "addr:street":"River St",
    "iso:country":"US",
    "sg:address":"1758 River St",
    "sg:city":"Hyde Park",
    "sg:classifiers":[
        {
            "category":"Food & Beverages",
            "subcategory":"Groceries & Convenience Stores",
            "type":"Retail Goods"
        }
    ],
    "sg:phone":"+1 617 361 6847",
    "sg:postcode":"02136",
    "sg:province":"MA",
    "sg:tags":[
        "market"
    ],
    "wof:name":"Marascio's Market",
    "wof:placetype":"venue"
},
  "geometry": {"coordinates":[-71.13712599999999,42.24453],"type":"Point"}
}