{
  "type": "Feature",
  "properties": {
    "addr:full": "105 E Grove St Middleboro MA 02346",
    "addr:housenumber": "105",
    "addr:postcode": "02346",
    "addr:street": "E Grove St",
    "iso:country": "US",
    "sg:address": "105 E Grove St",
    "sg:city": "Middleboro",
    "sg:classifiers": [
      {
        "category": "Health Services",
        "subcategory": "Doctor",
        "type": "Services"
      }
    ],
    "sg:phone": "+1 508 947 2423",
    "sg:postcode": "02346",
    "sg:province": "MA",
    "sg:tags": [
      "clinic"
    ],
    "wof:name": "READS Clinic Svc",
    "wof:placetype": "venue"
  },
  "geometry": {"coordinates":[-70.89173,41.876219],"type":"Point"}
}
