{
  "type": "Feature",
  "properties": {
    "addr:full": "522 Essex St Lawrence MA 01840",
    "addr:housenumber": "522",
    "addr:postcode": "01840",
    "addr:street": "Essex St",
    "iso:country": "US",
    "sg:address": "522 Essex St",
    "sg:city": "Lawrence",
    "sg:classifiers": [
      {
        "category": "Manufacturing",
        "subcategory": "Food",
        "type": "Manufacturing \u0026 Wholesale Goods"
      }
    ],
    "sg:phone": "+1 978 688 0474",
    "sg:postcode": "01840",
    "sg:province": "MA",
    "sg:tags": [
      "confectionery",
      "candy"
    ],
    "wof:name": "Silver Sweet Candies",
    "wof:placetype": "venue"
  },
  "geometry": {"coordinates":[-71.165505,42.706069],"type":"Point"}
}
