{
  "type": "Feature",
  "properties": {
    "addr:full":"18 Lomas Dr Framingham MA 01701",
    "addr:housenumber":"18",
    "addr:postcode":"01701",
    "addr:street":"Lomas Dr",
    "iso:country":"US",
    "sg:address":"18 Lomas Dr",
    "sg:city":"Framingham",
    "sg:classifiers":[
        {
            "category":"Professional",
            "subcategory":"Management & Consulting",
            "type":"Services"
        }
    ],
    "sg:phone":"+1 508 308 6041",
    "sg:postcode":"01701",
    "sg:province":"MA",
    "sg:tags":[
        "consultant",
        "educational"
    ],
    "wof:name":"Commonwealth-Hpo",
    "wof:placetype":"venue"
},
  "geometry": {"coordinates":[-71.433989,42.323826],"type":"Point"}
}