{
  "type": "Feature",
  "properties": {
    "iso:country":"US",
    "sg:address":"732 Harrison Ave",
    "sg:city":"Boston",
    "sg:classifiers":[
        {
            "category":"Health Services",
            "subcategory":"Doctor",
            "type":"Services"
        }
    ],
    "sg:phone":"+1 617 638 7310",
    "sg:postcode":"02118",
    "sg:province":"MA",
    "sg:tags":[
        "physician",
        "surgeon"
    ],
    "wof:name":"Rehabilitation Medicine",
    "wof:placetype":"venue"
},
  "geometry": {"coordinates":[-71.071974,42.337497],"type":"Point"}
}