{
  "type": "Feature",
  "properties": {
    "addr:full":"93 George Leven Dr North Attleboro MA 02760",
    "addr:housenumber":"93",
    "addr:postcode":"02760",
    "addr:street":"George Leven Dr",
    "iso:country":"US",
    "sg:address":"93 George Leven Dr",
    "sg:city":"North Attleboro",
    "sg:classifiers":[
        {
            "category":"Manufacturing",
            "subcategory":"Tools & Machinery",
            "type":"Manufacturing & Wholesale Goods"
        }
    ],
    "sg:phone":"+1   ",
    "sg:postcode":"02760",
    "sg:province":"MA",
    "wof:name":"Newfoil Machines Ltd",
    "wof:placetype":"venue"
},
  "geometry": {"coordinates":[-71.301202,42.006187],"type":"Point"}
}