{
  "type": "Feature",
  "properties": {
    "addr:full":"1029 Dorchester Avenue Dorchester MA 02125",
    "addr:housenumber":"1029",
    "addr:postcode":"02125",
    "addr:street":"Dorchester Avenue",
    "iso:country":"US",
    "sg:address":"1029 Dorchester Avenue",
    "sg:city":"Dorchester",
    "sg:classifiers":[
        {
            "category":"Sports & Exercise",
            "subcategory":"Gym",
            "type":"Entertainment"
        },
        {
            "category":"Health Services",
            "subcategory":"Health Practitioner",
            "type":"Services"
        }
    ],
    "sg:phone":"+1 617 287 9300",
    "sg:postcode":"02125",
    "sg:province":"MA",
    "sg:tags":[
        "trainer",
        "therapy",
        "physical"
    ],
    "wof:name":"General Rehabilitation",
    "wof:placetype":"venue"
},
  "geometry": {"coordinates":[-71.056513,42.315601],"type":"Point"}
}