{
  "type": "Feature",
  "properties": {
    "addr:full":"158 Meridian St Boston MA 02128",
    "addr:housenumber":"158",
    "addr:postcode":"02128",
    "addr:street":"Meridian St",
    "iso:country":"US",
    "sg:address":"158 Meridian St",
    "sg:city":"Boston",
    "sg:classifiers":[
        {
            "category":"Utilities",
            "subcategory":"Mobile Phone",
            "type":"Services"
        },
        {
            "category":"Shopping",
            "subcategory":"Mobile Phones",
            "type":"Retail Goods"
        },
        {
            "category":"Utilities",
            "subcategory":"Telephone",
            "type":"Services"
        },
        {
            "category":"Communications",
            "type":"Services"
        }
    ],
    "sg:phone":"+1 617 568 3044",
    "sg:postcode":"02128",
    "sg:province":"MA",
    "sg:tags":[
        "cellular"
    ],
    "wof:name":"Aries Communications",
    "wof:placetype":"venue"
},
  "geometry": {"coordinates":[-71.03924000000001,42.373741],"type":"Point"}
}