{
  "type": "Feature",
  "properties": {
    "addr:full":"1901 County St Dighton MA 02715",
    "addr:housenumber":"1901",
    "addr:postcode":"02715",
    "addr:street":"County St",
    "iso:country":"US",
    "sg:address":"1901 County St",
    "sg:city":"Dighton",
    "sg:classifiers":[
        {
            "category":"Sports & Exercise",
            "subcategory":"Gym",
            "type":"Entertainment"
        }
    ],
    "sg:phone":"+1 508 669 6060",
    "sg:postcode":"02715",
    "sg:province":"MA",
    "sg:tags":[
        "club",
        "health",
        "studio",
        "gymnasium"
    ],
    "wof:name":"Curves For Women",
    "wof:placetype":"venue"
},
  "geometry": {"coordinates":[-71.121278,41.815408],"type":"Point"}
}