{
  "type": "Feature",
  "properties": {
    "addr:full":"10 Liberty Sq Boston MA 02190",
    "addr:housenumber":"10",
    "addr:postcode":"02190",
    "addr:street":"Liberty Sq",
    "iso:country":"US",
    "sg:address":"10 Liberty Sq",
    "sg:city":"Boston",
    "sg:classifiers":[
        {
            "category":"Professional",
            "subcategory":"Management & Consulting",
            "type":"Services"
        }
    ],
    "sg:phone":"+1 617 574 3399",
    "sg:postcode":"02190",
    "sg:province":"MA",
    "sg:tags":[
        "lobbyist"
    ],
    "wof:name":"Lynch Associates",
    "wof:placetype":"venue"
},
  "geometry": {"coordinates":[-70.929277,42.162969],"type":"Point"}
}