{
  "type": "Feature",
  "properties": {
    "iso:country":"US",
    "sg:address":"700 Attucks Ln Unit 1E",
    "sg:city":"Hyannis",
    "sg:classifiers":[
        {
            "category":"Health Services",
            "subcategory":"Doctor",
            "type":"Services"
        }
    ],
    "sg:phone":"+1 508 771 5770",
    "sg:postcode":"02601",
    "sg:province":"MA",
    "wof:name":"Cape and Islands Occupational Medicine PC",
    "wof:placetype":"venue"
},
  "geometry": {"coordinates":[-70.29845,41.67584],"type":"Point"}
}