{
  "type": "Feature",
  "properties": {
    "iso:country":"US",
    "sg:address":"27 Christy Ln",
    "sg:city":"Ashland",
    "sg:classifiers":[
        {
            "category":"Professional",
            "subcategory":"Management & Consulting",
            "type":"Services"
        }
    ],
    "sg:phone":"+1   ",
    "sg:postcode":"01721",
    "sg:province":"MA",
    "wof:name":"Brookings Group",
    "wof:placetype":"venue"
},
  "geometry": {"coordinates":[-71.462767,42.254928],"type":"Point"}
}