{
  "type": "Feature",
  "properties": {
    "addr:full":"39 Warren St Newton MA 02459",
    "addr:housenumber":"39",
    "addr:postcode":"02459",
    "addr:street":"Warren St",
    "iso:country":"US",
    "sg:address":"39 Warren St",
    "sg:city":"Newton",
    "sg:classifiers":[
        {
            "category":"Building & Trades",
            "subcategory":"Construction",
            "type":"Services"
        }
    ],
    "sg:phone":"+1 617 244 9845",
    "sg:postcode":"02459",
    "sg:province":"MA",
    "sg:tags":[
        "masonry",
        "contractor"
    ],
    "wof:name":"Alan J Arduino",
    "wof:placetype":"venue"
},
  "geometry": {"coordinates":[-71.184422,42.328518],"type":"Point"}
}