{
  "type": "Feature",
  "properties": {
    "iso:country":"US",
    "sg:address":"367 Washington St",
    "sg:city":"Weymouth",
    "sg:classifiers":[
        {
            "category":"Retail",
            "subcategory":"Auto Repair",
            "type":"Services"
        }
    ],
    "sg:phone":"+1 781 335 2711",
    "sg:postcode":"02188",
    "sg:province":"MA",
    "sg:tags":[
        "automobile",
        "lubrication"
    ],
    "wof:name":"Oil Change Express",
    "wof:placetype":"venue"
},
  "geometry": {"coordinates":[-70.959964,42.211683],"type":"Point"}
}