{
  "type": "Feature",
  "properties": {
    "addr:full": "83 Boston Rd Westford MA 01886",
    "addr:housenumber": "83",
    "addr:postcode": "01886",
    "addr:street": "Boston Rd",
    "iso:country": "US",
    "sg:address": "83 Boston Rd",
    "sg:city": "Westford",
    "sg:classifiers": [
      {
        "category": "Building \u0026 Trades",
        "subcategory": "Cleaning \u0026 Sanitation",
        "type": "Services"
      }
    ],
    "sg:phone": "+1 978 589 8118",
    "sg:postcode": "01886",
    "sg:province": "MA",
    "sg:tags": [
      "home"
    ],
    "wof:name": "Cleaning Authority the - CLOSED",
    "wof:placetype": "venue"
  },
  "geometry": {"coordinates":[-71.427498,42.571701],"type":"Point"}
}
