{
  "type": "Feature",
  "properties": {
    "iso:country":"US",
    "sg:address":"83 Boston Rd",
    "sg:city":"Westford",
    "sg:classifiers":[
        {
            "category":"Building & Trades",
            "subcategory":"Cleaning & Sanitation",
            "type":"Services"
        }
    ],
    "sg:phone":"+1 978 589 8118",
    "sg:postcode":"01886",
    "sg:province":"MA",
    "sg:tags":[
        "home"
    ],
    "wof:name":"Cleaning Authority the - CLOSED",
    "wof:placetype":"venue"
},
  "geometry": {"coordinates":[-71.427498,42.571701],"type":"Point"}
}