{
  "type": "Feature",
  "properties": {
    "addr:full": "640 Pearl St Reading MA 01867",
    "addr:housenumber": "640",
    "addr:postcode": "01867",
    "addr:street": "Pearl St",
    "iso:country": "US",
    "sg:address": "640 Pearl St",
    "sg:city": "Reading",
    "sg:classifiers": [
      {
        "category": "Building \u0026 Trades",
        "subcategory": "Locksmith",
        "type": "Services"
      }
    ],
    "sg:phone": "+1 781 942 1350",
    "sg:postcode": "01867",
    "sg:province": "MA",
    "sg:tags": [
      "key"
    ],
    "wof:name": "Affordable Lock",
    "wof:placetype": "venue"
  },
  "geometry": {"coordinates":[-71.102501,42.555401],"type":"Point"}
}
