{
  "type": "Feature",
  "properties": {
    "iso:country":"US",
    "sg:address":"1437 Dorchester Avenue",
    "sg:city":"Dorchester",
    "sg:classifiers":[
        {
            "category":"Health Services",
            "subcategory":"Chiropractor",
            "type":"Services"
        }
    ],
    "sg:phone":"+1 617 474 0388",
    "sg:postcode":"02122",
    "sg:province":"MA",
    "sg:tags":[
        "chiropractic"
    ],
    "wof:name":"Fields Corner Chiropractic",
    "wof:placetype":"venue"
},
  "geometry": {"coordinates":[-71.059499,42.302153],"type":"Point"}
}