{
  "type": "Feature",
  "properties": {
    "addr:full":"44 Commercial St Raynham MA 02767",
    "addr:housenumber":"44",
    "addr:postcode":"02767",
    "addr:street":"Commercial St",
    "iso:country":"US",
    "sg:address":"44 Commercial St",
    "sg:city":"Raynham",
    "sg:classifiers":[
        {
            "category":"Retail",
            "subcategory":"Repair Shop",
            "type":"Services"
        }
    ],
    "sg:phone":"+1 508 824 1944",
    "sg:postcode":"02767",
    "sg:province":"MA",
    "sg:tags":[
        "related"
    ],
    "wof:name":"Majestic Medical",
    "wof:placetype":"venue"
},
  "geometry": {"coordinates":[-71.05495000000001,41.90952],"type":"Point"}
}