{
  "type": "Feature",
  "properties": {
    "addr:full":"659 Warren St Dorchester MA 02121",
    "addr:housenumber":"659",
    "addr:postcode":"02121",
    "addr:street":"Warren St",
    "iso:country":"US",
    "sg:address":"659 Warren St",
    "sg:city":"Dorchester",
    "sg:classifiers":[
        {
            "category":"Restaurant",
            "type":"Food & Drink"
        }
    ],
    "sg:phone":"+1 617 282 5611",
    "sg:postcode":"02121",
    "sg:province":"MA",
    "sg:tags":[
        "eating"
    ],
    "wof:name":"Red Island Restaurant",
    "wof:placetype":"venue"
},
  "geometry": {"coordinates":[-71.082703,42.309799],"type":"Point"}
}