{
  "type": "Feature",
  "properties": {
    "iso:country":"US",
    "sg:address":"290 Read St",
    "sg:city":"Somerset",
    "sg:classifiers":[
        {
            "category":"Building & Trades",
            "subcategory":"Cleaning & Sanitation",
            "type":"Services"
        }
    ],
    "sg:phone":"+1 508 646 1506",
    "sg:postcode":"02726",
    "sg:province":"MA",
    "sg:tags":[
        "house"
    ],
    "wof:name":"Ernie's Cleaning Svc",
    "wof:placetype":"venue"
},
  "geometry": {"coordinates":[-71.157236,41.735503],"type":"Point"}
}