{
  "type": "Feature",
  "properties": {
    "addr:full": "290 Read St Somerset MA 02726",
    "addr:housenumber": "290",
    "addr:postcode": "02726",
    "addr:street": "Read St",
    "iso:country": "US",
    "sg:address": "290 Read St",
    "sg:city": "Somerset",
    "sg:classifiers": [
      {
        "category": "Building \u0026 Trades",
        "subcategory": "Cleaning \u0026 Sanitation",
        "type": "Services"
      }
    ],
    "sg:phone": "+1 508 646 1506",
    "sg:postcode": "02726",
    "sg:province": "MA",
    "sg:tags": [
      "house"
    ],
    "wof:name": "Ernie's Cleaning Svc",
    "wof:placetype": "venue"
  },
  "geometry": {"coordinates":[-71.157236,41.735503],"type":"Point"}
}
