{
  "type": "Feature",
  "properties": {
    "addr:full": "76 Park St Attleboro MA 02703",
    "addr:housenumber": "76",
    "addr:postcode": "02703",
    "addr:street": "Park St",
    "iso:country": "US",
    "ovtr:label": "Neurology Partners, 76 Park St Attleboro MA US",
    "ovtr:similarity": 2.3063840866088867,
    "sg:address": "76 Park St",
    "sg:city": "Attleboro",
    "sg:classifiers": [
      {
        "category": "Health Services",
        "subcategory": "Doctor",
        "type": "Services"
      }
    ],
    "sg:phone": "+1 508 431 2026",
    "sg:postcode": "02703",
    "sg:province": "MA",
    "sg:tags": [
      "physician",
      "surgeon"
    ],
    "wof:name": "Neurology Partners",
    "wof:placetype": "venue"
  },
  "geometry": {"coordinates":[-71.2808,41.944],"type":"Point"}
}
