{
  "type": "Feature",
  "properties": {
    "iso:country":"US",
    "sg:address":"76 Park St",
    "sg:city":"Attleboro",
    "sg:classifiers":[
        {
            "category":"Health Services",
            "subcategory":"Doctor",
            "type":"Services"
        }
    ],
    "sg:phone":"+1 508 431 2026",
    "sg:postcode":"02703",
    "sg:province":"MA",
    "sg:tags":[
        "physician",
        "surgeon"
    ],
    "wof:name":"Neurology Partners",
    "wof:placetype":"venue"
},
  "geometry": {"coordinates":[-71.2808,41.944],"type":"Point"}
}