{
  "type": "Feature",
  "properties": {
    "iso:country":"US",
    "sg:address":"47 Esmond St",
    "sg:city":"Dorchester",
    "sg:classifiers":[
        {
            "category":"Transit Center",
            "subcategory":"Freight",
            "type":"Transportation"
        },
        {
            "category":"Freight",
            "type":"Transportation"
        }
    ],
    "sg:phone":"+1 617 822 3911",
    "sg:postcode":"02121",
    "sg:province":"MA",
    "sg:tags":[
        "local",
        "trucking-motor",
        "trucking"
    ],
    "wof:name":"Ross Clinton Assoc",
    "wof:placetype":"venue"
},
  "geometry": {"coordinates":[-71.083928,42.297889],"type":"Point"}
}