{
  "type": "Feature",
  "properties": {
    "iso:country":"US",
    "sg:address":"142 Pleasant St",
    "sg:city":"Malden",
    "sg:classifiers":[
        {
            "category":"Bars & Pubs",
            "type":"Food & Drink"
        },
        {
            "category":"Restaurant",
            "type":"Food & Drink"
        }
    ],
    "sg:phone":"+1 781 324 0111",
    "sg:postcode":"02148",
    "sg:province":"MA",
    "sg:tags":[
        "traditional",
        "american"
    ],
    "sg:website":"www.honeyfitzpub.com",
    "wof:name":"Honey Fitz Irish Pub",
    "wof:placetype":"venue"
},
  "geometry": {"coordinates":[-71.071214,42.427177],"type":"Point"}
}