{
  "type": "Feature",
  "properties": {
    "addr:full":"54 Canal St Boston MA 02114",
    "addr:housenumber":"54",
    "addr:postcode":"02114",
    "addr:street":"Canal St",
    "iso:country":"US",
    "sg:address":"54 Canal St",
    "sg:city":"Boston",
    "sg:classifiers":[
        {
            "category":"Real Estate",
            "subcategory":"Real Estate Services",
            "type":"Services"
        }
    ],
    "sg:phone":"+1 617 742 9955",
    "sg:postcode":"02114",
    "sg:province":"MA",
    "sg:tags":[
        "management",
        "property"
    ],
    "wof:name":"Hamlen Company",
    "wof:placetype":"venue"
},
  "geometry": {"coordinates":[-71.05950199999999,42.363998],"type":"Point"}
}