{
  "type": "Feature",
  "properties": {
    "addr:full":"71 Cross St Winchester MA 01890",
    "addr:housenumber":"71",
    "addr:postcode":"01890",
    "addr:street":"Cross St",
    "iso:country":"US",
    "sg:address":"71 Cross St",
    "sg:city":"Winchester",
    "sg:classifiers":[
        {
            "category":"Professional",
            "subcategory":"Lawyer & Legal Services",
            "type":"Services"
        }
    ],
    "sg:phone":"+1 781 729 8179",
    "sg:postcode":"01890",
    "sg:province":"MA",
    "wof:name":"Diloreto Michael E Law Offices of Atty",
    "wof:placetype":"venue"
},
  "geometry": {"coordinates":[-71.12930299999999,42.466202],"type":"Point"}
}