{
  "type": "Feature",
  "properties": {
    "addr:full":"1 Blackburn Dr Gloucester MA 01930",
    "addr:housenumber":"1",
    "addr:postcode":"01930",
    "addr:street":"Blackburn Dr",
    "iso:country":"US",
    "sg:address":"1 Blackburn Dr",
    "sg:city":"Gloucester",
    "sg:classifiers":[
        {
            "category":"Government",
            "subcategory":"Office",
            "type":"Public Place"
        }
    ],
    "sg:phone":"+1 978 283 0425",
    "sg:postcode":"01930",
    "sg:province":"MA",
    "sg:tags":[
        "federal",
        "taxation"
    ],
    "wof:name":"US Treasury Dept",
    "wof:placetype":"venue"
},
  "geometry": {"coordinates":[-70.65331999999999,42.625486],"type":"Point"}
}