{
  "type": "Feature",
  "properties": {
    "addr:full":"15 Robeson St Fall River MA 02720",
    "addr:housenumber":"15",
    "addr:postcode":"02720",
    "addr:street":"Robeson St",
    "iso:country":"US",
    "sg:address":"15 Robeson St",
    "sg:city":"Fall River",
    "sg:classifiers":[
        {
            "category":"Bakery",
            "type":"Food & Drink"
        },
        {
            "category":"Coffee & Tea",
            "type":"Food & Drink"
        },
        {
            "category":"Bagels",
            "type":"Food & Drink"
        },
        {
            "category":"Donuts",
            "type":"Food & Drink"
        }
    ],
    "sg:menulink":"http://www.allmenus.com/ma/fall-river/142891-dunkin-donuts/menu/",
    "sg:phone":"+1 508 672 9406",
    "sg:postcode":"02720",
    "sg:province":"MA",
    "sg:tags":[
        "american",
        "diner",
        "pastry"
    ],
    "wof:name":"Dunkin' Donuts",
    "wof:placetype":"venue"
},
  "geometry": {"coordinates":[-71.145371,41.700297],"type":"Point"}
}