{
  "type": "Feature",
  "properties": {
    "addr:full":"314 E Main St Unit 6 Norton MA 02766",
    "addr:housenumber":"314;6",
    "addr:postcode":"02766",
    "addr:street":"E Main St Unit",
    "iso:country":"US",
    "sg:address":"314 E Main St Unit 6",
    "sg:city":"Norton",
    "sg:phone":"+1 508 285 2373",
    "sg:postcode":"02766",
    "sg:province":"MA",
    "sg:website":"http://www.pattysplayandlearn.com",
    "wof:name":"Patty's Play & Learning Center",
    "wof:placetype":"venue"
},
  "geometry": {"coordinates":[-71.224501,41.951576],"type":"Point"}
}