{
  "type": "Feature",
  "properties": {
    "iso:country":"US",
    "sg:address":"755 Main St",
    "sg:city":"Haverhill",
    "sg:classifiers":[
        {
            "category":"Fast Food",
            "type":"Food & Drink"
        },
        {
            "category":"Restaurant",
            "type":"Food & Drink"
        }
    ],
    "sg:phone":"+1 978 373 8883",
    "sg:postcode":"01830",
    "sg:province":"MA",
    "sg:tags":[
        "pan",
        "buffet",
        "chinese",
        "asian"
    ],
    "wof:name":"China King Super Buffet",
    "wof:placetype":"venue"
},
  "geometry": {"coordinates":[-71.087754,42.796985],"type":"Point"}
}