{
  "type": "Feature",
  "properties": {
    "addr:full":"310 W Shore Dr Marblehead MA 01945",
    "addr:housenumber":"310",
    "addr:postcode":"01945",
    "addr:street":"W Shore Dr",
    "iso:country":"US",
    "sg:address":"310 W Shore Dr",
    "sg:city":"Marblehead",
    "sg:classifiers":[
        {
            "category":"Recreation",
            "type":"Entertainment"
        }
    ],
    "sg:phone":"+1 781 631 7571",
    "sg:postcode":"01945",
    "sg:province":"MA",
    "sg:tags":[
        "amusement"
    ],
    "wof:name":"Marblehead Youth Football Inc",
    "wof:placetype":"venue"
},
  "geometry": {"coordinates":[-70.86112799999999,42.511761],"type":"Point"}
}