{
  "type": "Feature",
  "properties": {
    "addr:full": "5 Newbury Ave Fairhaven MA 02719",
    "addr:housenumber": "5",
    "addr:postcode": "02719",
    "addr:street": "Newbury Ave",
    "iso:country": "US",
    "sg:address": "5 Newbury Ave",
    "sg:city": "Fairhaven",
    "sg:classifiers": [
      {
        "category": "Retail",
        "subcategory": "Auto Repair",
        "type": "Services"
      }
    ],
    "sg:phone": "+1 508 992 8349",
    "sg:postcode": "02719",
    "sg:province": "MA",
    "sg:tags": [
      "repairing",
      "automobile",
      "automotive"
    ],
    "wof:name": "Brian's Garage",
    "wof:placetype": "venue"
  },
  "geometry": {"coordinates":[-70.912242,41.65986],"type":"Point"}
}
