{
  "type": "Feature",
  "properties": {
    "addr:full":"240 Commonwealth Avenue Boston MA 02116",
    "addr:housenumber":"240",
    "addr:postcode":"02116",
    "addr:street":"Commonwealth Avenue",
    "iso:country":"US",
    "sg:address":"240 Commonwealth Avenue",
    "sg:city":"Boston",
    "sg:classifiers":[
        {
            "category":"Travel",
            "subcategory":"Hotels & Motels",
            "type":"Entertainment"
        },
        {
            "category":"Real Estate",
            "subcategory":"Real Estate Operator",
            "type":"Services"
        }
    ],
    "sg:phone":"+1 617 536 5510",
    "sg:postcode":"02116",
    "sg:province":"MA",
    "sg:tags":[
        "apartment"
    ],
    "sg:website":"www.buckinghambostonapartments.com/",
    "wof:name":"Buckingham Business Apartments",
    "wof:placetype":"venue"
},
  "geometry": {"coordinates":[-71.081093,42.350745],"type":"Point"}
}