{
  "type": "Feature",
  "properties": {
    "addr:full": "87 County Rd Plympton MA 02367",
    "addr:housenumber": "87",
    "addr:postcode": "02367",
    "addr:street": "County Rd",
    "iso:country": "US",
    "ovtr:label": "Plympton Cycles, 87 County Rd Plympton MA US",
    "ovtr:similarity": 2.581338882446289,
    "sg:address": "87 County Rd",
    "sg:city": "Plympton",
    "sg:classifiers": [
      {
        "category": "Retail",
        "subcategory": "Repair Shop",
        "type": "Services"
      }
    ],
    "sg:phone": "+1 781 582 0098",
    "sg:postcode": "02367",
    "sg:province": "MA",
    "sg:tags": [
      "scooter",
      "motorcycle",
      "motor"
    ],
    "wof:name": "Plympton Cycles",
    "wof:placetype": "venue"
  },
  "geometry": {"coordinates":[-70.803018,41.988143],"type":"Point"}
}
