{
  "type": "Feature",
  "properties": {
    "iso:country":"US",
    "sg:address":"87 County Rd",
    "sg:city":"Plympton",
    "sg:classifiers":[
        {
            "category":"Retail",
            "subcategory":"Repair Shop",
            "type":"Services"
        }
    ],
    "sg:phone":"+1 781 582 0098",
    "sg:postcode":"02367",
    "sg:province":"MA",
    "sg:tags":[
        "scooter",
        "motorcycle",
        "motor"
    ],
    "wof:name":"Plympton Cycles",
    "wof:placetype":"venue"
},
  "geometry": {"coordinates":[-70.80301799999999,41.988143],"type":"Point"}
}