{
  "type": "Feature",
  "properties": {
    "addr:full":"6 John Rd Peabody MA 01960",
    "addr:housenumber":"6",
    "addr:postcode":"01960",
    "addr:street":"John Rd",
    "iso:country":"US",
    "sg:address":"6 John Rd",
    "sg:city":"Peabody",
    "sg:classifiers":[
        {
            "category":"Building & Trades",
            "subcategory":"Equipment Rental",
            "type":"Services"
        }
    ],
    "sg:phone":"+1 978 977 3457",
    "sg:postcode":"01960",
    "sg:province":"MA",
    "sg:tags":[
        "contractors'"
    ],
    "wof:name":"R E Kerwin Sales",
    "wof:placetype":"venue"
},
  "geometry": {"coordinates":[-70.959845,42.511038],"type":"Point"}
}