{
  "type": "Feature",
  "properties": {
    "iso:country":"US",
    "sg:address":"1600 Providence Hwy",
    "sg:city":"Walpole",
    "sg:classifiers":[
        {
            "category":"Real Estate",
            "subcategory":"Real Estate Agent",
            "type":"Services"
        }
    ],
    "sg:phone":"+1 508 660 0196",
    "sg:postcode":"02081",
    "sg:province":"MA",
    "wof:name":"JMS Real Estate Svc",
    "wof:placetype":"venue"
},
  "geometry": {"coordinates":[-71.237831,42.116063],"type":"Point"}
}