{
  "type": "Feature",
  "properties": {
    "addr:full": "340 Lowell St Wakefield MA 01880",
    "addr:housenumber": "340",
    "addr:postcode": "01880",
    "addr:street": "Lowell St",
    "iso:country": "US",
    "sg:address": "340 Lowell St",
    "sg:city": "Wakefield",
    "sg:classifiers": [
      {
        "category": "Education",
        "subcategory": "School",
        "type": "Public Place"
      }
    ],
    "sg:phone": "+1 781 246 6480",
    "sg:postcode": "01880",
    "sg:province": "MA",
    "sg:website": "www.wakefield.k12.ma.us",
    "wof:name": "Dolbeare School",
    "wof:placetype": "venue"
  },
  "geometry": {"coordinates":[-71.065348,42.518102],"type":"Point"}
}
