{
  "type": "Feature",
  "properties": {
    "addr:full": "33 Sixth Rd Woburn MA 01801",
    "addr:housenumber": "33",
    "addr:postcode": "01801",
    "addr:street": "Sixth Rd",
    "iso:country": "US",
    "sg:address": "33 Sixth Rd",
    "sg:city": "Woburn",
    "sg:classifiers": [
      {
        "category": "Professional",
        "type": "Services"
      }
    ],
    "sg:phone": "+1 781 938 3700",
    "sg:postcode": "01801",
    "sg:province": "MA",
    "wof:name": "US Ground Logistics",
    "wof:placetype": "venue"
  },
  "geometry": {"coordinates":[-71.146599,42.511362],"type":"Point"}
}
