{
  "type": "Feature",
  "properties": {
    "iso:country":"US",
    "sg:address":"33 Sixth Rd",
    "sg:city":"Woburn",
    "sg:classifiers":[
        {
            "category":"Professional",
            "type":"Services"
        }
    ],
    "sg:phone":"+1 781 938 3700",
    "sg:postcode":"01801",
    "sg:province":"MA",
    "wof:name":"US Ground Logistics",
    "wof:placetype":"venue"
},
  "geometry": {"coordinates":[-71.14659899999999,42.511362],"type":"Point"}
}