{
  "type": "Feature",
  "properties": {
    "addr:full": "26 School St Bridgewater MA 02324",
    "addr:housenumber": "26",
    "addr:postcode": "02324",
    "addr:street": "School St",
    "iso:country": "US",
    "sg:address": "26 School St",
    "sg:city": "Bridgewater",
    "sg:classifiers": [
      {
        "category": "Education",
        "subcategory": "School",
        "type": "Public Place"
      }
    ],
    "sg:phone": "+1 508 697 6775",
    "sg:postcode": "02324",
    "sg:province": "MA",
    "wof:name": "A F Hunt School",
    "wof:placetype": "venue"
  },
  "geometry": {"coordinates":[-70.972903,41.987936],"type":"Point"}
}
