{
  "type": "Feature",
  "properties": {
    "addr:full":"22 Cranes Ct Woburn MA 01801",
    "addr:housenumber":"22",
    "addr:postcode":"01801",
    "addr:street":"Cranes Ct",
    "iso:country":"US",
    "sg:address":"22 Cranes Ct",
    "sg:city":"Woburn",
    "sg:classifiers":[
        {
            "category":"Social Services",
            "subcategory":"Job Training",
            "type":"Services"
        }
    ],
    "sg:phone":"+1 781 933 4830",
    "sg:postcode":"01801",
    "sg:province":"MA",
    "sg:tags":[
        "employment"
    ],
    "wof:name":"Management Software International",
    "wof:placetype":"venue"
},
  "geometry": {"coordinates":[-71.14664500000001,42.467167],"type":"Point"}
}