{
  "type": "Feature",
  "properties": {
    "iso:country":"US",
    "sg:address":"14 Harris St",
    "sg:city":"Belmont",
    "sg:classifiers":[
        {
            "category":"Insurance",
            "subcategory":"Health Insurance",
            "type":"Services"
        }
    ],
    "sg:phone":"+1   ",
    "sg:postcode":"02478",
    "sg:province":"MA",
    "sg:tags":[
        "carrier"
    ],
    "wof:name":"Bleiberg Associates",
    "wof:placetype":"venue"
},
  "geometry": {"coordinates":[-71.182367,42.388627],"type":"Point"}
}