{
  "type": "Feature",
  "properties": {
    "addr:full": "369 Main St Marshfield MA 02050",
    "addr:housenumber": "369",
    "addr:postcode": "02050",
    "addr:street": "Main St",
    "iso:country": "US",
    "sg:address": "369 Main St",
    "sg:city": "Marshfield",
    "sg:classifiers": [
      {
        "category": "Professional",
        "subcategory": "Art Services",
        "type": "Services"
      }
    ],
    "sg:phone": "+1   ",
    "sg:postcode": "02050",
    "sg:province": "MA",
    "sg:tags": [
      "photography",
      "commercial"
    ],
    "wof:name": "Ben Kerns Photography",
    "wof:placetype": "venue"
  },
  "geometry": {"coordinates":[-70.722791,42.10564],"type":"Point"}
}
