{
  "type": "Feature",
  "properties": {
    "addr:full":"72 Old Southbridge Rd Oxford MA 01540",
    "addr:housenumber":"72",
    "addr:postcode":"01540",
    "addr:street":"Old Southbridge Rd",
    "iso:country":"US",
    "sg:address":"72 Old Southbridge Rd",
    "sg:city":"Oxford",
    "sg:classifiers":[
        {
            "category":"Personal",
            "type":"Services"
        }
    ],
    "sg:phone":"+1   ",
    "sg:postcode":"01540",
    "sg:province":"MA",
    "wof:name":"Anchor Home Renovations",
    "wof:placetype":"venue"
},
  "geometry": {"coordinates":[-71.904032,42.097814],"type":"Point"}
}