{
  "type": "Feature",
  "properties": {
    "addr:full": "305 Union St Franklin MA 02038",
    "addr:housenumber": "305",
    "addr:postcode": "02038",
    "addr:street": "Union St",
    "iso:country": "US",
    "sg:address": "305 Union St",
    "sg:city": "Franklin",
    "sg:phone": "+1 508 520 7949",
    "sg:postcode": "02038",
    "sg:province": "MA",
    "sg:tags": [
      "equipment",
      "supply"
    ],
    "sg:website": "www.cbsequipment.com",
    "wof:name": "CBS Bar \u0026 Restaurant Equip",
    "wof:placetype": "venue"
  },
  "geometry": {"coordinates":[-71.40362,42.078208],"type":"Point"}
}
