{
  "type": "Feature",
  "properties": {
    "addr:full":"23 Fox Hill Rd Billerica MA 01821",
    "addr:housenumber":"23",
    "addr:postcode":"01821",
    "addr:street":"Fox Hill Rd",
    "iso:country":"US",
    "sg:address":"23 Fox Hill Rd",
    "sg:city":"Billerica",
    "sg:classifiers":[
        {
            "category":"Manufacturing",
            "subcategory":"Buildings",
            "type":"Manufacturing & Wholesale Goods"
        },
        {
            "category":"Building & Trades",
            "subcategory":"Construction",
            "type":"Services"
        },
        {
            "category":"Building & Trades",
            "subcategory":"Electrical",
            "type":"Services"
        }
    ],
    "sg:phone":"+1 978 663 9879",
    "sg:postcode":"01821",
    "sg:province":"MA",
    "sg:tags":[
        "industrial",
        "electrician",
        "builder",
        "contractor",
        "contractors-commercial",
        "home"
    ],
    "sg:website":"http://middlesexelectrical.com",
    "wof:name":"Middlesex Electrical Contracting, Inc.",
    "wof:placetype":"venue"
},
  "geometry": {"coordinates":[-71.255521,42.572688],"type":"Point"}
}