{
  "type": "Feature",
  "properties": {
    "iso:country":"US",
    "sg:address":"20 Concord Ln",
    "sg:city":"Cambridge",
    "sg:classifiers":[
        {
            "category":"Building & Trades",
            "subcategory":"Locksmith",
            "type":"Services"
        }
    ],
    "sg:phone":"+1 617 299 2143",
    "sg:postcode":"02138",
    "sg:province":"MA",
    "sg:tags":[
        "key"
    ],
    "wof:name":"Concord Ln Emergency Locksmith",
    "wof:placetype":"venue"
},
  "geometry": {"coordinates":[-71.141256,42.388422],"type":"Point"}
}