{
  "type": "Feature",
  "properties": {
    "addr:full":"200 Washington St Peabody MA 01960",
    "addr:housenumber":"200",
    "addr:postcode":"01960",
    "addr:street":"Washington St",
    "iso:country":"US",
    "sg:address":"200 Washington St",
    "sg:city":"Peabody",
    "sg:classifiers":[
        {
            "category":"Restaurant",
            "type":"Food & Drink"
        }
    ],
    "sg:phone":"+1 978 531 0992",
    "sg:postcode":"01960",
    "sg:province":"MA",
    "sg:tags":[
        "pizza"
    ],
    "wof:name":"Lena's Pizza & Subs",
    "wof:placetype":"venue"
},
  "geometry": {"coordinates":[-70.935436,42.52079],"type":"Point"}
}