{
  "type": "Feature",
  "properties": {
    "addr:full": "1040 Revere Beach Pkwy Chelsea MA 02150",
    "addr:housenumber": "1040",
    "addr:postcode": "02150",
    "addr:street": "Revere Beach Pkwy",
    "iso:country": "US",
    "ovtr:label": "Chili's Grill \u0026 Bar, 1040 Revere Beach Pkwy Chelsea MA US",
    "ovtr:similarity": 2.6308140754699707,
    "sg:address": "1040 Revere Beach Pkwy",
    "sg:city": "Chelsea",
    "sg:classifiers": [
      {
        "category": "Restaurant",
        "type": "Food \u0026 Drink"
      }
    ],
    "sg:phone": "+1 617 884 7960",
    "sg:postcode": "02150",
    "sg:province": "MA",
    "sg:tags": [
      "traditional",
      "american"
    ],
    "sg:website": "www.chilis.com",
    "wof:name": "Chili's Bar and Grill",
    "wof:placetype": "venue"
  },
  "geometry": {"coordinates":[-71.020504,42.405473],"type":"Point"}
}
