{
  "type": "Feature",
  "properties": {
    "iso:country":"US",
    "sg:address":"4 Everett Cir",
    "sg:city":"Hopkinton",
    "sg:classifiers":[
        {
            "category":"Building & Trades",
            "subcategory":"Construction",
            "type":"Services"
        }
    ],
    "sg:phone":"+1 508 497 9100",
    "sg:postcode":"01748",
    "sg:province":"MA",
    "sg:tags":[
        "repairing",
        "remodeling",
        "contractor"
    ],
    "wof:name":"Highlander Renovation Inc",
    "wof:placetype":"venue"
},
  "geometry": {"coordinates":[-71.541612,42.251032],"type":"Point"}
}