{
  "type": "Feature",
  "properties": {
    "addr:full": "5 Chatham Rd Longmeadow MA 01106",
    "addr:housenumber": "5",
    "addr:postcode": "01106",
    "addr:street": "Chatham Rd",
    "iso:country": "US",
    "sg:address": "5 Chatham Rd",
    "sg:city": "Longmeadow",
    "sg:classifiers": [
      {
        "category": "Health Services",
        "subcategory": "Podiatrist",
        "type": "Services"
      }
    ],
    "sg:phone": "+1 413 567 6713",
    "sg:postcode": "01106",
    "sg:province": "MA",
    "sg:tags": [
      "equipment",
      "supply"
    ],
    "wof:name": "Sorrell Medical Inc",
    "wof:placetype": "venue"
  },
  "geometry": {"coordinates":[-72.572648,42.067148],"type":"Point"}
}
