{
  "type": "Feature",
  "properties": {
    "iso:country":"US",
    "sg:address":"175 Adams St",
    "sg:city":"Dorchester",
    "sg:classifiers":[
        {
            "category":"Shopping",
            "subcategory":"Used Merchandise",
            "type":"Retail Goods"
        }
    ],
    "sg:phone":"+1 617 265 9000",
    "sg:postcode":"02122",
    "sg:province":"MA",
    "sg:tags":[
        "antique"
    ],
    "wof:name":"Time Trader Antiques",
    "wof:placetype":"venue"
},
  "geometry": {"coordinates":[-71.060284,42.302304],"type":"Point"}
}