{
  "type": "Feature",
  "properties": {
    "iso:country":"US",
    "sg:address":"44 Pond St",
    "sg:city":"Natick",
    "sg:classifiers":[
        {
            "category":"Communications",
            "type":"Services"
        }
    ],
    "sg:phone":"+1 508 655 0178",
    "sg:postcode":"01760",
    "sg:province":"MA",
    "wof:name":"Remedy Communications",
    "wof:placetype":"venue"
},
  "geometry": {"coordinates":[-71.35073300000001,42.282148],"type":"Point"}
}