{
  "type": "Feature",
  "properties": {
    "iso:country":"US",
    "sg:address":"132 Virginia Ave",
    "sg:city":"Attleboro Falls",
    "sg:classifiers":[
        {
            "category":"Manufacturing",
            "subcategory":"Textiles",
            "type":"Manufacturing & Wholesale Goods"
        }
    ],
    "sg:phone":"+1   ",
    "sg:postcode":"02763",
    "sg:province":"MA",
    "sg:tags":[
        "mill",
        "thread"
    ],
    "wof:name":"CJ Designs",
    "wof:placetype":"venue"
},
  "geometry": {"coordinates":[-71.31196199999999,41.962256],"type":"Point"}
}