{
  "type": "Feature",
  "properties": {
    "iso:country":"US",
    "sg:address":"125 High St",
    "sg:city":"Boston",
    "sg:classifiers":[
        {
            "category":"Professional",
            "subcategory":"Lawyer & Legal Services",
            "type":"Services"
        }
    ],
    "sg:phone":"+1 617 248 7000",
    "sg:postcode":"02110",
    "sg:province":"MA",
    "wof:name":"King Rufus C Atty",
    "wof:placetype":"venue"
},
  "geometry": {"coordinates":[-71.054199,42.355202],"type":"Point"}
}