{
  "type": "Feature",
  "properties": {
    "addr:full":"185 Jordan Rd Plymouth MA 02360",
    "addr:housenumber":"185",
    "addr:postcode":"02360",
    "addr:street":"Jordan Rd",
    "iso:country":"US",
    "sg:address":"185 Jordan Rd",
    "sg:city":"Plymouth",
    "sg:classifiers":[
        {
            "category":"Retail",
            "subcategory":"Animal Services",
            "type":"Services"
        }
    ],
    "sg:phone":"+1 508 747 7717",
    "sg:postcode":"02360",
    "sg:province":"MA",
    "sg:tags":[
        "pet",
        "grooming",
        "washing"
    ],
    "wof:name":"Grooming By Pia",
    "wof:placetype":"venue"
},
  "geometry": {"coordinates":[-70.623867,41.917634],"type":"Point"}
}