{
  "type": "Feature",
  "properties": {
    "iso:country":"US",
    "sg:address":"340 Boston Ave",
    "sg:city":"Medford",
    "sg:classifiers":[
        {
            "category":"Restaurant",
            "type":"Food & Drink"
        }
    ],
    "sg:phone":"+1 339 674 9740",
    "sg:postcode":"02155",
    "sg:province":"MA",
    "sg:tags":[
        "new",
        "american"
    ],
    "sg:website":"www.boloco.com",
    "wof:name":"Boloco - Tufts University",
    "wof:placetype":"venue"
},
  "geometry": {"coordinates":[-71.12153600000001,42.411373],"type":"Point"}
}