{
  "type": "Feature",
  "properties": {
    "addr:full": "10 Whelden Ln Acushnet MA 02743",
    "addr:housenumber": "10",
    "addr:postcode": "02743",
    "addr:street": "Whelden Ln",
    "iso:country": "US",
    "sg:address": "10 Whelden Ln",
    "sg:city": "Acushnet",
    "sg:classifiers": [
      {
        "category": "Retail",
        "subcategory": "Auto Repair",
        "type": "Services"
      }
    ],
    "sg:phone": "+1   ",
    "sg:postcode": "02743",
    "sg:province": "MA",
    "sg:tags": [
      "general"
    ],
    "wof:name": "R \u0026 J Truck Repair Inc",
    "wof:placetype": "venue"
  },
  "geometry": {"coordinates":[-70.917253,41.706996],"type":"Point"}
}
