{
  "type": "Feature",
  "properties": {
    "iso:country":"US",
    "sg:address":"23 Catherine Ave",
    "sg:city":"Franklin",
    "sg:classifiers":[
        {
            "category":"Professional",
            "type":"Services"
        }
    ],
    "sg:phone":"+1   ",
    "sg:postcode":"02038",
    "sg:province":"MA",
    "wof:name":"Youth Enjoying Sports Inc",
    "wof:placetype":"venue"
},
  "geometry": {"coordinates":[-71.43567899999999,42.11708],"type":"Point"}
}