{
  "type": "Feature",
  "properties": {
    "addr:full":"45 Felt St Salem MA 01970",
    "addr:housenumber":"45",
    "addr:postcode":"01970",
    "addr:street":"Felt St",
    "iso:country":"US",
    "sg:address":"45 Felt St",
    "sg:city":"Salem",
    "sg:classifiers":[
        {
            "category":"Wholesale",
            "subcategory":"Durable Goods & Equipment",
            "type":"Manufacturing & Wholesale Goods"
        }
    ],
    "sg:phone":"+1 978 741 3166",
    "sg:postcode":"01970",
    "sg:province":"MA",
    "sg:tags":[
        "representative",
        "manufacturer"
    ],
    "wof:name":"CDM Assoc",
    "wof:placetype":"venue"
},
  "geometry": {"coordinates":[-70.900125,42.533853],"type":"Point"}
}