{
  "type": "Feature",
  "properties": {
    "iso:country":"US",
    "sg:address":"104 Pleasant Valley Rd",
    "sg:city":"Westwood",
    "sg:classifiers":[
        {
            "category":"Manufacturing",
            "subcategory":"Printing",
            "type":"Manufacturing & Wholesale Goods"
        }
    ],
    "sg:phone":"+1 781 320 9090",
    "sg:postcode":"02090",
    "sg:province":"MA",
    "sg:tags":[
        "printer"
    ],
    "sg:website":"www.oliveriprinting.com",
    "wof:name":"Oliveri & Assoc",
    "wof:placetype":"venue"
},
  "geometry": {"coordinates":[-71.215754,42.235685],"type":"Point"}
}