{
  "type": "Feature",
  "properties": {
    "addr:full":"7 Elkins St Boston MA 02127",
    "addr:housenumber":"7",
    "addr:postcode":"02127",
    "addr:street":"Elkins St",
    "iso:country":"US",
    "sg:address":"7 Elkins St",
    "sg:city":"Boston",
    "sg:classifiers":[
        {
            "category":"Professional",
            "subcategory":"Detective & Security Services",
            "type":"Services"
        }
    ],
    "sg:phone":"+1 617 315 9014",
    "sg:postcode":"02127",
    "sg:province":"MA",
    "sg:tags":[
        "information",
        "bureau"
    ],
    "wof:name":"Aaa Road Service",
    "wof:placetype":"venue"
},
  "geometry": {"coordinates":[-71.035608,42.339216],"type":"Point"}
}