{
  "type": "Feature",
  "properties": {
    "iso:country":"US",
    "sg:address":"7 White Ter",
    "sg:city":"Lexington",
    "sg:classifiers":[
        {
            "category":"Professional",
            "subcategory":"Detective & Security Services",
            "type":"Services"
        }
    ],
    "sg:phone":"+1 781 301 6008",
    "sg:postcode":"02420",
    "sg:province":"MA",
    "sg:tags":[
        "information",
        "bureau"
    ],
    "wof:name":"Aaa Road Service",
    "wof:placetype":"venue"
},
  "geometry": {"coordinates":[-71.23257,42.470208],"type":"Point"}
}