{
  "type": "Feature",
  "properties": {
    "addr:full": "97 Marion Street Brookline MA 02446",
    "addr:housenumber": "97",
    "addr:postcode": "02446",
    "addr:street": "Marion Street",
    "iso:country": "US",
    "sg:address": "97 Marion Street",
    "sg:city": "Brookline",
    "sg:classifiers": [
      {
        "category": "Organizations",
        "subcategory": "Religious Organization",
        "type": "Services"
      }
    ],
    "sg:phone": "+1 617 278 2424",
    "sg:postcode": "02446",
    "sg:province": "MA",
    "wof:name": "Chai Center Chabad",
    "wof:placetype": "venue"
  },
  "geometry": {"coordinates":[-71.12534,42.3402],"type":"Point"}
}
