{
  "type": "Feature",
  "properties": {
    "iso:country":"US",
    "sg:address":"97 Marion Street",
    "sg:city":"Brookline",
    "sg:classifiers":[
        {
            "category":"Organizations",
            "subcategory":"Religious Organization",
            "type":"Services"
        }
    ],
    "sg:phone":"+1 617 278 2424",
    "sg:postcode":"02446",
    "sg:province":"MA",
    "wof:name":"Chai Center Chabad",
    "wof:placetype":"venue"
},
  "geometry": {"coordinates":[-71.12533999999999,42.3402],"type":"Point"}
}