{
  "type": "Feature",
  "properties": {
    "addr:full": "90 Bay State Rd Wakefield MA 01880",
    "addr:housenumber": "90",
    "addr:postcode": "01880",
    "addr:street": "Bay State Rd",
    "iso:country": "US",
    "sg:address": "90 Bay State Rd",
    "sg:city": "Wakefield",
    "sg:classifiers": [
      {
        "category": "Wholesale",
        "subcategory": "Machinery \u0026 Supplies",
        "type": "Manufacturing \u0026 Wholesale Goods"
      }
    ],
    "sg:phone": "+1 781 246 1810",
    "sg:postcode": "01880",
    "sg:province": "MA",
    "sg:tags": [
      "engine"
    ],
    "sg:website": "www.nedda.com",
    "wof:name": "New England Detroit Diesel",
    "wof:placetype": "venue"
  },
  "geometry": {"coordinates":[-71.075739,42.527699],"type":"Point"}
}
