{
  "type": "Feature",
  "properties": {
    "iso:country":"US",
    "sg:address":"90 Bay State Rd",
    "sg:city":"Wakefield",
    "sg:classifiers":[
        {
            "category":"Wholesale",
            "subcategory":"Machinery & Supplies",
            "type":"Manufacturing & Wholesale Goods"
        }
    ],
    "sg:phone":"+1 781 246 1810",
    "sg:postcode":"01880",
    "sg:province":"MA",
    "sg:tags":[
        "engine"
    ],
    "sg:website":"www.nedda.com",
    "wof:name":"New England Detroit Diesel",
    "wof:placetype":"venue"
},
  "geometry": {"coordinates":[-71.075739,42.527699],"type":"Point"}
}