{
  "type": "Feature",
  "properties": {
    "addr:full":"1 Design Center Pl Ste 600 Boston MA 02210",
    "addr:postcode":"02210",
    "addr:street":"Center Pl Ste 600",
    "iso:country":"US",
    "sg:address":"1 Design Center Pl Ste 600",
    "sg:city":"Boston",
    "sg:classifiers":[
        {
            "category":"Building & Trades",
            "subcategory":"Construction",
            "type":"Services"
        }
    ],
    "sg:phone":"+1 617 478 6200",
    "sg:postcode":"02210",
    "sg:province":"MA",
    "sg:tags":[
        "contractor"
    ],
    "wof:name":"Macomber Co George Bh",
    "wof:placetype":"venue"
},
  "geometry": {"coordinates":[-71.034302,42.343899],"type":"Point"}
}