{
  "type": "Feature",
  "properties": {
    "addr:full": "177 Winthrop St Rehoboth MA 02769",
    "addr:housenumber": "177",
    "addr:postcode": "02769",
    "addr:street": "Winthrop St",
    "iso:country": "US",
    "ovtr:label": "Propane Plus Corporation, 177 Winthrop St Rehoboth MA US",
    "ovtr:similarity": 2.7320919036865234,
    "sg:address": "177 Winthrop St",
    "sg:city": "Rehoboth",
    "sg:phone": "+1 508 252 3359",
    "sg:postcode": "02769",
    "sg:province": "MA",
    "sg:tags": [
      "gas"
    ],
    "wof:name": "Propane Plus Corp",
    "wof:placetype": "venue"
  },
  "geometry": {"coordinates":[-71.230325,41.859339],"type":"Point"}
}
