{
  "type": "Feature",
  "properties": {
    "iso:country":"US",
    "sg:address":"177 Winthrop St",
    "sg:city":"Rehoboth",
    "sg:phone":"+1 508 252 3359",
    "sg:postcode":"02769",
    "sg:province":"MA",
    "sg:tags":[
        "gas"
    ],
    "wof:name":"Propane Plus Corp",
    "wof:placetype":"venue"
},
  "geometry": {"coordinates":[-71.23032499999999,41.859339],"type":"Point"}
}