{
  "type": "Feature",
  "properties": {
    "iso:country":"US",
    "sg:address":"77 13th St N",
    "sg:city":"Edgartown",
    "sg:classifiers":[
        {
            "category":"Personal",
            "subcategory":"Beauty Salon",
            "type":"Services"
        }
    ],
    "sg:phone":"+1 508 627 6933",
    "sg:postcode":"02539",
    "sg:province":"MA",
    "wof:name":"Sheila Allen Styles",
    "wof:placetype":"venue"
},
  "geometry": {"coordinates":[-70.554018,41.402325],"type":"Point"}
}