{
  "type": "Feature",
  "properties": {
    "addr:full":"20 Aegean Dr Ste 16 Methuen MA 01844",
    "addr:housenumber":"20",
    "addr:postcode":"01844",
    "addr:street":"Aegean Dr Ste 16",
    "iso:country":"US",
    "sg:address":"20 Aegean Dr Ste 16",
    "sg:city":"Methuen",
    "sg:classifiers":[
        {
            "category":"Building & Trades",
            "subcategory":"Equipment Rental",
            "type":"Services"
        },
        {
            "category":"Shopping",
            "subcategory":"Computers & Home Electronics",
            "type":"Retail Goods"
        },
        {
            "category":"Arts & Performance",
            "subcategory":"Theater",
            "type":"Entertainment"
        }
    ],
    "sg:phone":"+1 978 975 3498",
    "sg:postcode":"01844",
    "sg:province":"MA",
    "sg:tags":[
        "sound",
        "theatrical",
        "leasing",
        "supply",
        "system",
        "equipment-renting",
        "audio-visual"
    ],
    "sg:website":"http://www.gtluminaires.com",
    "wof:name":"Galley Theatre Lighting",
    "wof:placetype":"venue"
},
  "geometry": {"coordinates":[-71.21241999999999,42.72954],"type":"Point"}
}