{
  "type": "Feature",
  "properties": {
    "addr:full":"859 Washington St South Easton MA 02375",
    "addr:housenumber":"859",
    "addr:postcode":"02375",
    "addr:street":"Washington St",
    "iso:country":"US",
    "sg:address":"859 Washington St",
    "sg:city":"South Easton",
    "sg:classifiers":[
        {
            "category":"Professional",
            "subcategory":"Lawyer & Legal Services",
            "type":"Services"
        }
    ],
    "sg:phone":"+1 508 580 6083",
    "sg:postcode":"02375",
    "sg:province":"MA",
    "sg:tags":[
        "attorney"
    ],
    "wof:name":"Stephanie A Sousa",
    "wof:placetype":"venue"
},
  "geometry": {"coordinates":[-71.070931,42.030571],"type":"Point"}
}