{
  "type": "Feature",
  "properties": {
    "iso:country":"US",
    "sg:address":"365 Washington St",
    "sg:city":"Boston",
    "sg:classifiers":[
        {
            "category":"Shopping",
            "subcategory":"Jewelry",
            "type":"Retail Goods"
        }
    ],
    "sg:phone":"+1 617 574 8822",
    "sg:postcode":"02108",
    "sg:province":"MA",
    "sg:tags":[
        "manufacturer",
        "jewelers-wholesale",
        "jeweler"
    ],
    "wof:name":"Gold Palace",
    "wof:placetype":"venue"
},
  "geometry": {"coordinates":[-71.059393,42.356387],"type":"Point"}
}