{
  "type": "Feature",
  "properties": {
    "addr:full":"333 Victory Rd. Quincy MA 02171",
    "addr:housenumber":"333",
    "addr:postcode":"02171",
    "addr:street":"Victory Rd.",
    "iso:country":"US",
    "sg:address":"333 Victory Rd.",
    "sg:city":"Quincy",
    "sg:classifiers":[
        {
            "category":"Recreation",
            "subcategory":"Dance Hall",
            "type":"Entertainment"
        }
    ],
    "sg:phone":"+1 617 689 0600",
    "sg:postcode":"02171",
    "sg:province":"MA",
    "sg:tags":[
        "club"
    ],
    "sg:website":"www.oceanclubatmarinabay.com/",
    "wof:name":"The Ocean Club at Marina Bay",
    "wof:placetype":"venue"
},
  "geometry": {"coordinates":[-71.028199,42.299532],"type":"Point"}
}