{
  "type": "Feature",
  "properties": {
    "addr:full":"68 Norfolk Rd Millis MA 02054",
    "addr:housenumber":"68",
    "addr:postcode":"02054",
    "addr:street":"Norfolk Rd",
    "iso:country":"US",
    "sg:address":"68 Norfolk Rd",
    "sg:city":"Millis",
    "sg:classifiers":[
        {
            "category":"Arena",
            "subcategory":"Sports Club",
            "type":"Entertainment"
        }
    ],
    "sg:phone":"+1 508 376 1250",
    "sg:postcode":"02054",
    "sg:province":"MA",
    "sg:tags":[
        "manager",
        "recruiter",
        "promoter"
    ],
    "wof:name":"Pro Motion Sports",
    "wof:placetype":"venue"
},
  "geometry": {"coordinates":[-71.351485,42.147971],"type":"Point"}
}