{
  "type": "Feature",
  "properties": {
    "iso:country":"US",
    "sg:address":"1 Weather Vane Ln",
    "sg:city":"East Sandwich",
    "sg:classifiers":[
        {
            "category":"Building & Trades",
            "subcategory":"Cleaning & Sanitation",
            "type":"Services"
        }
    ],
    "sg:phone":"+1 508 888 3375",
    "sg:postcode":"02537",
    "sg:province":"MA",
    "sg:tags":[
        "janitor"
    ],
    "wof:name":"A 1 Cleaning Svc",
    "wof:placetype":"venue"
},
  "geometry": {"coordinates":[-70.407883,41.738364],"type":"Point"}
}