{
  "type": "Feature",
  "properties": {
    "addr:full":"374 Salem St Malden MA 02148",
    "addr:housenumber":"374",
    "addr:postcode":"02148",
    "addr:street":"Salem St",
    "iso:country":"US",
    "sg:address":"374 Salem St",
    "sg:city":"Malden",
    "sg:classifiers":[
        {
            "category":"Personal",
            "subcategory":"Barber",
            "type":"Services"
        }
    ],
    "sg:phone":"+1 781 397 7673",
    "sg:postcode":"02148",
    "sg:province":"MA",
    "sg:tags":[
        "equipment",
        "supply"
    ],
    "wof:name":"Burma Beauty Supply",
    "wof:placetype":"venue"
},
  "geometry": {"coordinates":[-71.054739,42.431122],"type":"Point"}
}