{
  "type": "Feature",
  "properties": {
    "addr:full": "50 Braintree Hill Park # 205 Braintree MA 02184",
    "addr:housenumber": "50",
    "addr:postcode": "02184",
    "addr:street": "Braintree Hill Park # 205",
    "iso:country": "US",
    "sg:address": "50 Braintree Hill Park # 205",
    "sg:city": "Braintree",
    "sg:classifiers": [
      {
        "category": "Professional",
        "subcategory": "Management \u0026 Consulting",
        "type": "Services"
      }
    ],
    "sg:phone": "+1 781 535 6161",
    "sg:postcode": "02184",
    "sg:province": "MA",
    "sg:tags": [
      "consultant",
      "search",
      "executive"
    ],
    "wof:name": "Carter Mackay Of Massachusettes Inc",
    "wof:placetype": "venue"
  },
  "geometry": {"coordinates":[-71.028695,42.225711],"type":"Point"}
}
