{
  "type": "Feature",
  "properties": {
    "iso:country":"US",
    "sg:address":"1964 Boston Rd",
    "sg:city":"Wilbraham",
    "sg:classifiers":[
        {
            "category":"Health Services",
            "subcategory":"Optometrist",
            "type":"Services"
        }
    ],
    "sg:phone":"+1 413 543 5444",
    "sg:postcode":"01095",
    "sg:province":"MA",
    "wof:name":"John T Danielson OD",
    "wof:placetype":"venue"
},
  "geometry": {"coordinates":[-72.478585,42.14875],"type":"Point"}
}