{
  "type": "Feature",
  "properties": {
    "iso:country":"US",
    "sg:address":"33 Glenham St",
    "sg:city":"Springfield",
    "sg:classifiers":[
        {
            "category":"Professional",
            "type":"Services"
        }
    ],
    "sg:phone":"+1   ",
    "sg:postcode":"01104",
    "sg:province":"MA",
    "wof:name":"Harris Painting",
    "wof:placetype":"venue"
},
  "geometry": {"coordinates":[-72.57131099999999,42.131673],"type":"Point"}
}