{
  "type": "Feature",
  "properties": {
    "addr:full": "33 Glenham St Springfield MA 01104",
    "addr:housenumber": "33",
    "addr:postcode": "01104",
    "addr:street": "Glenham St",
    "iso:country": "US",
    "sg:address": "33 Glenham St",
    "sg:city": "Springfield",
    "sg:classifiers": [
      {
        "category": "Professional",
        "type": "Services"
      }
    ],
    "sg:phone": "+1   ",
    "sg:postcode": "01104",
    "sg:province": "MA",
    "wof:name": "Harris Painting",
    "wof:placetype": "venue"
  },
  "geometry": {"coordinates":[-72.571311,42.131673],"type":"Point"}
}
