{
  "type": "Feature",
  "properties": {
    "iso:country":"US",
    "sg:address":"128 Arlington St",
    "sg:city":"Watertown",
    "sg:classifiers":[
        {
            "category":"Food & Beverages",
            "subcategory":"Bakery",
            "type":"Retail Goods"
        },
        {
            "category":"Bakery",
            "type":"Food & Drink"
        }
    ],
    "sg:phone":"+1 617 923 1224",
    "sg:postcode":"02472",
    "sg:province":"MA",
    "sg:tags":[
        "bakers-wholesale"
    ],
    "wof:name":"International Natural Bakery",
    "wof:placetype":"venue"
},
  "geometry": {"coordinates":[-71.15535,42.366638],"type":"Point"}
}