{
  "type": "Feature",
  "properties": {
    "addr:full": "128 Arlington St Watertown MA 02472",
    "addr:housenumber": "128",
    "addr:postcode": "02472",
    "addr:street": "Arlington St",
    "iso:country": "US",
    "ovtr:label": "International Natural Bakery, 128 Arlington St Watertown MA US",
    "ovtr:similarity": 2.348206043243408,
    "sg:address": "128 Arlington St",
    "sg:city": "Watertown",
    "sg:classifiers": [
      {
        "category": "Food \u0026 Beverages",
        "subcategory": "Bakery",
        "type": "Retail Goods"
      },
      {
        "category": "Bakery",
        "type": "Food \u0026 Drink"
      }
    ],
    "sg:phone": "+1 617 923 1224",
    "sg:postcode": "02472",
    "sg:province": "MA",
    "sg:tags": [
      "bakers-wholesale"
    ],
    "wof:name": "International Natural Bakery",
    "wof:placetype": "venue"
  },
  "geometry": {"coordinates":[-71.15535,42.366638],"type":"Point"}
}
