{
  "type": "Feature",
  "properties": {
    "addr:full":"4 S Main St Millbury MA 01527",
    "addr:housenumber":"4",
    "addr:postcode":"01527",
    "addr:street":"S Main St",
    "iso:country":"US",
    "sg:address":"4 S Main St",
    "sg:city":"Millbury",
    "sg:classifiers":[
        {
            "category":"Shopping",
            "subcategory":"Florist",
            "type":"Retail Goods"
        }
    ],
    "sg:phone":"+1 508 865 5831",
    "sg:postcode":"01527",
    "sg:province":"MA",
    "wof:name":"Millbury Towne Florist",
    "wof:placetype":"venue"
},
  "geometry": {"coordinates":[-71.760367,42.190136],"type":"Point"}
}