{
  "type": "Feature",
  "properties": {
    "addr:full": "56 Court St Westfield MA 01085",
    "addr:housenumber": "56",
    "addr:postcode": "01085",
    "addr:street": "Court St",
    "iso:country": "US",
    "sg:address": "56 Court St",
    "sg:city": "Westfield",
    "sg:classifiers": [
      {
        "category": "Shopping",
        "type": "Retail Goods"
      }
    ],
    "sg:phone": "+1 413 572 3901",
    "sg:postcode": "01085",
    "sg:province": "MA",
    "sg:tags": [
      "hearing",
      "equipment",
      "supply",
      "impaired"
    ],
    "wof:name": "Avada Audiology \u0026 Hearing Care",
    "wof:placetype": "venue"
  },
  "geometry": {"coordinates":[-72.755341,42.120059],"type":"Point"}
}
