{
  "type": "Feature",
  "properties": {
    "iso:country":"US",
    "sg:address":"56 Court St",
    "sg:city":"Westfield",
    "sg:classifiers":[
        {
            "category":"Shopping",
            "type":"Retail Goods"
        }
    ],
    "sg:phone":"+1 413 572 3901",
    "sg:postcode":"01085",
    "sg:province":"MA",
    "sg:tags":[
        "hearing",
        "equipment",
        "supply",
        "impaired"
    ],
    "wof:name":"Avada Audiology & Hearing Care",
    "wof:placetype":"venue"
},
  "geometry": {"coordinates":[-72.755341,42.120059],"type":"Point"}
}