{
  "type": "Feature",
  "properties": {
    "addr:full": "47 Montvale Ave Stoneham MA 02180",
    "addr:housenumber": "47",
    "addr:postcode": "02180",
    "addr:street": "Montvale Ave",
    "iso:country": "US",
    "sg:address": "47 Montvale Ave",
    "sg:city": "Stoneham",
    "sg:classifiers": [
      {
        "category": "Health Services",
        "subcategory": "Chiropractor",
        "type": "Services"
      }
    ],
    "sg:phone": "+1 781 438 4252",
    "sg:postcode": "02180",
    "sg:province": "MA",
    "wof:name": "Powers Mary-Jo Dr",
    "wof:placetype": "venue"
  },
  "geometry": {"coordinates":[-71.104909,42.482127],"type":"Point"}
}
