{
  "type": "Feature",
  "properties": {
    "iso:country":"US",
    "sg:address":"47 Montvale Ave",
    "sg:city":"Stoneham",
    "sg:classifiers":[
        {
            "category":"Health Services",
            "subcategory":"Chiropractor",
            "type":"Services"
        }
    ],
    "sg:phone":"+1 781 438 4252",
    "sg:postcode":"02180",
    "sg:province":"MA",
    "wof:name":"Powers Mary-Jo Dr",
    "wof:placetype":"venue"
},
  "geometry": {"coordinates":[-71.10490900000001,42.482127],"type":"Point"}
}