{
  "type": "Feature",
  "properties": {
    "iso:country":"US",
    "sg:address":"59 Franklin St",
    "sg:city":"Allston",
    "sg:classifiers":[
        {
            "category":"Real Estate",
            "subcategory":"Real Estate Agent",
            "type":"Services"
        }
    ],
    "sg:phone":"+1 617 783 1867",
    "sg:postcode":"02134",
    "sg:province":"MA",
    "wof:name":"Trio Realty",
    "wof:placetype":"venue"
},
  "geometry": {"coordinates":[-71.133083,42.358556],"type":"Point"}
}