{
  "type": "Feature",
  "properties": {
    "iso:country":"US",
    "sg:address":"484 Lowell St",
    "sg:city":"Peabody",
    "sg:classifiers":[
        {
            "category":"Travel",
            "subcategory":"Travel Agent",
            "type":"Entertainment"
        }
    ],
    "sg:phone":"+1 978 535 4000",
    "sg:postcode":"01960",
    "sg:province":"MA",
    "sg:tags":[
        "agency",
        "bureau"
    ],
    "sg:website":"www.metrotours.com",
    "wof:name":"Metro Travel Of Peabody",
    "wof:placetype":"venue"
},
  "geometry": {"coordinates":[-70.97396999999999,42.541638],"type":"Point"}
}