{
  "type": "Feature",
  "properties": {
    "iso:country":"US",
    "sg:address":"657 Washington St",
    "sg:city":"Dorchester Center",
    "sg:classifiers":[
        {
            "category":"Arts & Performance",
            "subcategory":"Music",
            "type":"Entertainment"
        },
        {
            "category":"Restaurant",
            "type":"Food & Drink"
        }
    ],
    "sg:phone":"+1 617 506 6061",
    "sg:postcode":"02124",
    "sg:province":"MA",
    "sg:tags":[
        "venue",
        "caribbean"
    ],
    "sg:website":"www.lorenzislandkuisine.com",
    "wof:name":"Lorenz Island Kuisine",
    "wof:placetype":"venue"
},
  "geometry": {"coordinates":[-71.071168,42.288821],"type":"Point"}
}