{
  "type": "Feature",
  "properties": {
    "addr:full": "657 Washington St Dorchester Center MA 02124",
    "addr:housenumber": "657",
    "addr:postcode": "02124",
    "addr:street": "Washington St",
    "iso:country": "US",
    "sg:address": "657 Washington St",
    "sg:city": "Dorchester Center",
    "sg:classifiers": [
      {
        "category": "Arts \u0026 Performance",
        "subcategory": "Music",
        "type": "Entertainment"
      },
      {
        "category": "Restaurant",
        "type": "Food \u0026 Drink"
      }
    ],
    "sg:phone": "+1 617 506 6061",
    "sg:postcode": "02124",
    "sg:province": "MA",
    "sg:tags": [
      "venue",
      "caribbean"
    ],
    "sg:website": "www.lorenzislandkuisine.com",
    "wof:name": "Lorenz Island Kuisine",
    "wof:placetype": "venue"
  },
  "geometry": {"coordinates":[-71.071168,42.288821],"type":"Point"}
}
