{
  "type": "Feature",
  "properties": {
    "iso:country":"US",
    "sg:address":"227 Pleasant St",
    "sg:city":"Marblehead",
    "sg:classifiers":[
        {
            "category":"Shopping",
            "type":"Retail Goods"
        }
    ],
    "sg:phone":"+1 781 639 0122",
    "sg:postcode":"01945",
    "sg:province":"MA",
    "sg:tags":[
        "wedding",
        "supply"
    ],
    "wof:name":"Wedding Window",
    "wof:placetype":"venue"
},
  "geometry": {"coordinates":[-70.86179799999999,42.49717],"type":"Point"}
}