{
  "type": "Feature",
  "properties": {
    "addr:full": "30 Cottage St Amherst MA 01002",
    "addr:housenumber": "30",
    "addr:postcode": "01002",
    "addr:street": "Cottage St",
    "iso:country": "US",
    "sg:address": "30 Cottage St",
    "sg:city": "Amherst",
    "sg:classifiers": [
      {
        "category": "Organizations",
        "subcategory": "Community Association",
        "type": "Services"
      }
    ],
    "sg:phone": "+1 413 549 8118",
    "sg:postcode": "01002",
    "sg:province": "MA",
    "sg:tags": [
      "environmental",
      "org"
    ],
    "sg:website": "www.earthaction.org",
    "wof:name": "Earth Action",
    "wof:placetype": "venue"
  },
  "geometry": {"coordinates":[-72.516402,42.383562],"type":"Point"}
}
