{
  "type": "Feature",
  "properties": {
    "addr:full":"468 Main St Acton MA 01720",
    "addr:housenumber":"468",
    "addr:postcode":"01720",
    "addr:street":"Main St",
    "iso:country":"US",
    "sg:address":"468 Main St",
    "sg:city":"Acton",
    "sg:classifiers":[
        {
            "category":"Building & Trades",
            "subcategory":"Locksmith",
            "type":"Services"
        }
    ],
    "sg:phone":"+1 978 881 0016",
    "sg:postcode":"01720",
    "sg:province":"MA",
    "sg:tags":[
        "key"
    ],
    "wof:name":"A and J 24 Hour Locksmith",
    "wof:placetype":"venue"
},
  "geometry": {"coordinates":[-71.434118,42.485371],"type":"Point"}
}