{
  "type": "Feature",
  "properties": {
    "iso:country":"US",
    "sg:address":"7 Cole Rd",
    "sg:city":"Haydenville",
    "sg:classifiers":[
        {
            "category":"Communications",
            "subcategory":"Film & Video Production",
            "type":"Services"
        }
    ],
    "sg:phone":"+1 413 268 8200",
    "sg:postcode":"01039",
    "sg:province":"MA",
    "sg:tags":[
        "motion"
    ],
    "wof:name":"Horse Mountain Studio",
    "wof:placetype":"venue"
},
  "geometry": {"coordinates":[-72.674882,42.380509],"type":"Point"}
}