{
  "type": "Feature",
  "properties": {
    "addr:full": "15 Glenville Ave Allston MA 02134",
    "addr:housenumber": "15",
    "addr:postcode": "02134",
    "addr:street": "Glenville Ave",
    "iso:country": "US",
    "sg:address": "15 Glenville Ave",
    "sg:city": "Allston",
    "sg:classifiers": [
      {
        "category": "Arts \u0026 Performance",
        "subcategory": "Theater",
        "type": "Entertainment"
      }
    ],
    "sg:phone": "+1 617 734 4664",
    "sg:postcode": "02134",
    "sg:province": "MA",
    "sg:tags": [
      "bureau"
    ],
    "wof:name": "Gadfly Productions",
    "wof:placetype": "venue"
  },
  "geometry": {"coordinates":[-71.131447,42.351154],"type":"Point"}
}
