{
  "type": "Feature",
  "properties": {
    "iso:country":"US",
    "sg:address":"15 Glenville Ave",
    "sg:city":"Allston",
    "sg:classifiers":[
        {
            "category":"Arts & Performance",
            "subcategory":"Theater",
            "type":"Entertainment"
        }
    ],
    "sg:phone":"+1 617 734 4664",
    "sg:postcode":"02134",
    "sg:province":"MA",
    "sg:tags":[
        "bureau"
    ],
    "wof:name":"Gadfly Productions",
    "wof:placetype":"venue"
},
  "geometry": {"coordinates":[-71.13144699999999,42.351154],"type":"Point"}
}