{
  "type": "Feature",
  "properties": {
    "addr:full": "10 Read St Salem MA 01970",
    "addr:housenumber": "10",
    "addr:postcode": "01970",
    "addr:street": "Read St",
    "iso:country": "US",
    "sg:address": "10 Read St",
    "sg:city": "Salem",
    "sg:classifiers": [
      {
        "category": "Building \u0026 Trades",
        "subcategory": "Plumbing",
        "type": "Services"
      }
    ],
    "sg:phone": "+1 978 745 5233",
    "sg:postcode": "01970",
    "sg:province": "MA",
    "sg:tags": [
      "plumber",
      "industrial",
      "contractors-commercial"
    ],
    "wof:name": "Jeters Plumbing \u0026 Piping",
    "wof:placetype": "venue"
  },
  "geometry": {"coordinates":[-70.901141,42.504899],"type":"Point"}
}
