{
  "type": "Feature",
  "properties": {
    "addr:full": "30 Fairview Ave Beverly MA 01915",
    "addr:housenumber": "30",
    "addr:postcode": "01915",
    "addr:street": "Fairview Ave",
    "iso:country": "US",
    "sg:address": "30 Fairview Ave",
    "sg:city": "Beverly",
    "sg:classifiers": [
      {
        "category": "Building \u0026 Trades",
        "subcategory": "Construction",
        "type": "Services"
      }
    ],
    "sg:phone": "+1   ",
    "sg:postcode": "01915",
    "sg:province": "MA",
    "sg:tags": [
      "house"
    ],
    "wof:name": "Di Paolo \u0026 Sons",
    "wof:placetype": "venue"
  },
  "geometry": {"coordinates":[-70.895923,42.553426],"type":"Point"}
}
