{
  "type": "Feature",
  "properties": {
    "iso:country":"US",
    "sg:address":"30 Fairview Ave",
    "sg:city":"Beverly",
    "sg:classifiers":[
        {
            "category":"Building & Trades",
            "subcategory":"Construction",
            "type":"Services"
        }
    ],
    "sg:phone":"+1   ",
    "sg:postcode":"01915",
    "sg:province":"MA",
    "sg:tags":[
        "house"
    ],
    "wof:name":"Di Paolo & Sons",
    "wof:placetype":"venue"
},
  "geometry": {"coordinates":[-70.895923,42.553426],"type":"Point"}
}