{
  "type": "Feature",
  "properties": {
    "addr:full":"503 Main St Medfield MA 02052",
    "addr:housenumber":"503",
    "addr:postcode":"02052",
    "addr:street":"Main St",
    "iso:country":"US",
    "sg:address":"503 Main St",
    "sg:city":"Medfield",
    "sg:classifiers":[
        {
            "category":"Real Estate",
            "subcategory":"Real Estate Agent",
            "type":"Services"
        }
    ],
    "sg:phone":"+1 508 359 7351",
    "sg:postcode":"02052",
    "sg:province":"MA",
    "wof:name":"Delta Real Estate Inc",
    "wof:placetype":"venue"
},
  "geometry": {"coordinates":[-71.30651,42.1862],"type":"Point"}
}