{
  "type": "Feature",
  "properties": {
    "iso:country":"US",
    "sg:address":"951 N State Rd",
    "sg:city":"Cheshire",
    "sg:classifiers":[
        {
            "category":"Shopping",
            "subcategory":"Computers & Home Electronics",
            "type":"Retail Goods"
        }
    ],
    "sg:phone":"+1 413 743 8019",
    "sg:postcode":"01225",
    "sg:province":"MA",
    "sg:tags":[
        "equipment",
        "satellite",
        "system"
    ],
    "wof:name":"Nickum Telecom Svc",
    "wof:placetype":"venue"
},
  "geometry": {"coordinates":[-73.14745499999999,42.582899],"type":"Point"}
}