{
  "type": "Feature",
  "properties": {
    "iso:country":"US",
    "sg:address":"89 South St",
    "sg:city":"Brighton",
    "sg:classifiers":[
        {
            "category":"Real Estate",
            "subcategory":"Real Estate Agent",
            "type":"Services"
        }
    ],
    "sg:phone":"+1 617 330 1270",
    "sg:postcode":"02135",
    "sg:province":"MA",
    "sg:tags":[
        "management"
    ],
    "wof:name":"L L Lincoln Plaza",
    "wof:placetype":"venue"
},
  "geometry": {"coordinates":[-71.157466,42.339882],"type":"Point"}
}