{
  "type": "Feature",
  "properties": {
    "iso:country":"US",
    "sg:address":"1 Allen St",
    "sg:city":"Springfield",
    "sg:classifiers":[
        {
            "category":"Manufacturing",
            "subcategory":"Paper Products",
            "type":"Manufacturing & Wholesale Goods"
        }
    ],
    "sg:phone":"+1   ",
    "sg:postcode":"01108",
    "sg:province":"MA",
    "sg:tags":[
        "converted",
        "mfg"
    ],
    "wof:name":"D&R Realty",
    "wof:placetype":"venue"
},
  "geometry": {"coordinates":[-72.563569,42.097024],"type":"Point"}
}