{
  "type": "Feature",
  "properties": {
    "addr:full": "1 Allen St Springfield MA 01108",
    "addr:housenumber": "1",
    "addr:postcode": "01108",
    "addr:street": "Allen St",
    "iso:country": "US",
    "sg:address": "1 Allen St",
    "sg:city": "Springfield",
    "sg:classifiers": [
      {
        "category": "Manufacturing",
        "subcategory": "Paper Products",
        "type": "Manufacturing \u0026 Wholesale Goods"
      }
    ],
    "sg:phone": "+1   ",
    "sg:postcode": "01108",
    "sg:province": "MA",
    "sg:tags": [
      "converted",
      "mfg"
    ],
    "wof:name": "D\u0026R Realty",
    "wof:placetype": "venue"
  },
  "geometry": {"coordinates":[-72.563569,42.097024],"type":"Point"}
}
