{
  "type": "Feature",
  "properties": {
    "addr:full":"254 Concord Ave Cambridge MA 02138",
    "addr:housenumber":"254",
    "addr:postcode":"02138",
    "addr:street":"Concord Ave",
    "iso:country":"US",
    "sg:address":"254 Concord Ave",
    "sg:city":"Cambridge",
    "sg:classifiers":[
        {
            "category":"Organizations",
            "subcategory":"Religious Organization",
            "type":"Services"
        }
    ],
    "sg:phone":"+1 617 497 3334",
    "sg:postcode":"02138",
    "sg:province":"MA",
    "sg:tags":[
        "church"
    ],
    "sg:website":"www.berkland.org",
    "wof:name":"Berkland Baptist Church",
    "wof:placetype":"venue"
},
  "geometry": {"coordinates":[-71.13241600000001,42.382912],"type":"Point"}
}