{
  "type": "Feature",
  "properties": {
    "iso:country":"US",
    "sg:address":"23 Harborview Rd",
    "sg:city":"Hull",
    "sg:classifiers":[
        {
            "category":"Professional",
            "subcategory":"Management & Consulting",
            "type":"Services"
        }
    ],
    "sg:phone":"+1   ",
    "sg:postcode":"02045",
    "sg:province":"MA",
    "sg:tags":[
        "business"
    ],
    "wof:name":"Jan Dragin & Assoc",
    "wof:placetype":"venue"
},
  "geometry": {"coordinates":[-70.907112,42.307261],"type":"Point"}
}