{
  "type": "Feature",
  "properties": {
    "addr:full": "23 Harborview Rd Hull MA 02045",
    "addr:housenumber": "23",
    "addr:postcode": "02045",
    "addr:street": "Harborview Rd",
    "iso:country": "US",
    "sg:address": "23 Harborview Rd",
    "sg:city": "Hull",
    "sg:classifiers": [
      {
        "category": "Professional",
        "subcategory": "Management \u0026 Consulting",
        "type": "Services"
      }
    ],
    "sg:phone": "+1   ",
    "sg:postcode": "02045",
    "sg:province": "MA",
    "sg:tags": [
      "business"
    ],
    "wof:name": "Jan Dragin \u0026 Assoc",
    "wof:placetype": "venue"
  },
  "geometry": {"coordinates":[-70.907112,42.307261],"type":"Point"}
}
