{
  "type": "Feature",
  "properties": {
    "iso:country":"US",
    "sg:address":"1300 Liberty St",
    "sg:city":"Springfield",
    "sg:classifiers":[
        {
            "category":"Communications",
            "subcategory":"Television Station",
            "type":"Services"
        }
    ],
    "sg:phone":"+1 413 733 4040",
    "sg:postcode":"01104",
    "sg:province":"MA",
    "sg:tags":[
        "broadcasting",
        "co"
    ],
    "wof:name":"ABC 40",
    "wof:placetype":"venue"
},
  "geometry": {"coordinates":[-72.584065,42.13605],"type":"Point"}
}