{
  "type": "Feature",
  "properties": {
    "iso:country":"US",
    "sg:address":"214 Commercial Street suite 209",
    "sg:city":"Malden",
    "sg:classifiers":[
        {
            "category":"Arts & Performance",
            "subcategory":"Arts Center",
            "type":"Entertainment"
        }
    ],
    "sg:postcode":"02148",
    "sg:province":"MA",
    "sg:website":"www.flipsideboston.com/#/home",
    "wof:name":"Flip Side",
    "wof:placetype":"venue"
},
  "geometry": {"coordinates":[-71.07540400000001,42.421184],"type":"Point"}
}