{
  "type": "Feature",
  "properties": {
    "addr:full": "6 Gwen Cir Ware MA 01082",
    "addr:housenumber": "6",
    "addr:postcode": "01082",
    "addr:street": "Gwen Cir",
    "iso:country": "US",
    "sg:address": "6 Gwen Cir",
    "sg:city": "Ware",
    "sg:classifiers": [
      {
        "category": "Insurance",
        "subcategory": "Hazard Insurance",
        "type": "Services"
      }
    ],
    "sg:phone": "+1 413 277 0195",
    "sg:postcode": "01082",
    "sg:province": "MA",
    "wof:name": "Kiel Insurance Brokers Inc",
    "wof:placetype": "venue"
  },
  "geometry": {"coordinates":[-72.325729,42.263611],"type":"Point"}
}
