{
  "type": "Feature",
  "properties": {
    "addr:full":"1030 Turnpike St Canton MA 02021",
    "addr:housenumber":"1030",
    "addr:postcode":"02021",
    "addr:street":"Turnpike St",
    "iso:country":"US",
    "sg:address":"1030 Turnpike St",
    "sg:city":"Canton",
    "sg:classifiers":[
        {
            "category":"Insurance",
            "subcategory":"Insurance Agent",
            "type":"Services"
        }
    ],
    "sg:phone":"+1 781 828 3131",
    "sg:postcode":"02021",
    "sg:province":"MA",
    "sg:website":"www.alltown-insurance.com",
    "wof:name":"Alltown Insurance",
    "wof:placetype":"venue"
},
  "geometry": {"coordinates":[-71.10486899999999,42.149936],"type":"Point"}
}