{
  "type": "Feature",
  "properties": {
    "addr:full": "32 Rutland St Boston MA 02118",
    "addr:housenumber": "32",
    "addr:postcode": "02118",
    "addr:street": "Rutland St",
    "iso:country": "US",
    "sg:address": "32 Rutland St",
    "sg:city": "Boston",
    "sg:classifiers": [
      {
        "category": "Health Services",
        "subcategory": "Clinic",
        "type": "Services"
      }
    ],
    "sg:phone": "+1 617 236 1785",
    "sg:postcode": "02118",
    "sg:province": "MA",
    "sg:tags": [
      "medical",
      "group"
    ],
    "wof:name": "Learning \u0026 Traning Network",
    "wof:placetype": "venue"
  },
  "geometry": {"coordinates":[-71.076956,42.3406],"type":"Point"}
}
