{
  "type": "Feature",
  "properties": {
    "addr:full": "734 Page Blvd Springfield MA 01104",
    "addr:housenumber": "734",
    "addr:postcode": "01104",
    "addr:street": "Page Blvd",
    "iso:country": "US",
    "sg:address": "734 Page Blvd",
    "sg:city": "Springfield",
    "sg:classifiers": [
      {
        "category": "Retail",
        "subcategory": "Auto Repair",
        "type": "Services"
      }
    ],
    "sg:phone": "+1 413 734 9685",
    "sg:postcode": "01104",
    "sg:province": "MA",
    "sg:tags": [
      "repairing",
      "automobile"
    ],
    "wof:name": "B \u0026 G Auto Svc",
    "wof:placetype": "venue"
  },
  "geometry": {"coordinates":[-72.554292,42.142841],"type":"Point"}
}
