{
  "type": "Feature",
  "properties": {
    "addr:full":"36 Birch Rd Norfolk MA 02056",
    "addr:housenumber":"36",
    "addr:postcode":"02056",
    "addr:street":"Birch Rd",
    "iso:country":"US",
    "sg:address":"36 Birch Rd",
    "sg:city":"Norfolk",
    "sg:classifiers":[
        {
            "category":"Building & Trades",
            "subcategory":"Construction",
            "type":"Services"
        }
    ],
    "sg:phone":"+1 508 384 7989",
    "sg:postcode":"02056",
    "sg:province":"MA",
    "sg:tags":[
        "general",
        "contractor"
    ],
    "wof:name":"B & B Aluminum Products",
    "wof:placetype":"venue"
},
  "geometry": {"coordinates":[-71.318533,42.093452],"type":"Point"}
}