{
  "type": "Feature",
  "properties": {
    "iso:country":"US",
    "sg:address":"707 Middle St",
    "sg:city":"North Dighton",
    "sg:classifiers":[
        {
            "category":"Retail",
            "subcategory":"Auto Repair",
            "type":"Services"
        }
    ],
    "sg:phone":"+1 508 252 5404",
    "sg:postcode":"02764",
    "sg:province":"MA",
    "sg:tags":[
        "body",
        "automobile",
        "painting"
    ],
    "wof:name":"Bristol County Auto Body",
    "wof:placetype":"venue"
},
  "geometry": {"coordinates":[-71.142413,41.849059],"type":"Point"}
}