{
  "type": "Feature",
  "properties": {
    "addr:full": "60 Federal Street Boston MA 02110",
    "addr:housenumber": "60",
    "addr:postcode": "02110",
    "addr:street": "Federal Street",
    "iso:country": "US",
    "sg:address": "60 Federal Street",
    "sg:city": "Boston",
    "sg:classifiers": [
      {
        "category": "Sports \u0026 Exercise",
        "subcategory": "Gym",
        "type": "Entertainment"
      },
      {
        "category": "Health Services",
        "subcategory": "Dentist",
        "type": "Services"
      }
    ],
    "sg:phone": "+1 617 423 6165",
    "sg:postcode": "02110",
    "sg:province": "MA",
    "sg:tags": [
      "trainer"
    ],
    "wof:name": "Edwards David DMD",
    "wof:placetype": "venue"
  },
  "geometry": {"coordinates":[-71.056451,42.355946],"type":"Point"}
}
