{
  "type": "Feature",
  "properties": {
    "iso:country":"US",
    "sg:address":"29 Alden St",
    "sg:city":"Ashland",
    "sg:classifiers":[
        {
            "category":"Autos & Motor Vehicles",
            "subcategory":"Automobile Sales",
            "type":"Retail Goods"
        }
    ],
    "sg:phone":"+1 508 380 9277",
    "sg:postcode":"01721",
    "sg:province":"MA",
    "sg:tags":[
        "car",
        "used"
    ],
    "wof:name":"Pauls Pre Owned Auto Sales Co",
    "wof:placetype":"venue"
},
  "geometry": {"coordinates":[-71.462075,42.259135],"type":"Point"}
}