{
  "type": "Feature",
  "properties": {
    "iso:country":"US",
    "sg:address":"835 Broad St",
    "sg:city":"East Weymouth",
    "sg:classifiers":[
        {
            "category":"Insurance",
            "subcategory":"Insurance Agent",
            "type":"Services"
        }
    ],
    "sg:phone":"+1 781 335 1170",
    "sg:postcode":"02189",
    "sg:province":"MA",
    "sg:website":"www.duncanmackellar.com",
    "wof:name":"Duncan Mac Kellar Insurance",
    "wof:placetype":"venue"
},
  "geometry": {"coordinates":[-70.926575,42.216023],"type":"Point"}
}