{
  "type": "Feature",
  "properties": {
    "iso:country":"US",
    "sg:address":"64 Mandalay Rd",
    "sg:city":"Newton Center",
    "sg:classifiers":[
        {
            "category":"Shopping",
            "subcategory":"Discount & Variety Stores",
            "type":"Retail Goods"
        }
    ],
    "sg:phone":"+1 617 965 6269",
    "sg:postcode":"02459",
    "sg:province":"MA",
    "sg:tags":[
        "merchandise",
        "general"
    ],
    "wof:name":"Bud Ente Sales Co",
    "wof:placetype":"venue"
},
  "geometry": {"coordinates":[-71.180466,42.33981],"type":"Point"}
}