{
  "type": "Feature",
  "properties": {
    "iso:country":"US",
    "sg:address":"139 Main St",
    "sg:city":"Everett",
    "sg:classifiers":[
        {
            "category":"Real Estate",
            "subcategory":"Real Estate Services",
            "type":"Services"
        },
        {
            "category":"Real Estate",
            "subcategory":"Real Estate Operator",
            "type":"Services"
        }
    ],
    "sg:phone":"+1 617 394 0066",
    "sg:postcode":"02149",
    "sg:province":"MA",
    "sg:tags":[
        "property",
        "management",
        "apartment"
    ],
    "sg:website":"www.greatermetro.net",
    "wof:name":"Greater Metropolitan Real Estate",
    "wof:placetype":"venue"
},
  "geometry": {"coordinates":[-71.061606,42.405745],"type":"Point"}
}