{
  "type": "Feature",
  "properties": {
    "addr:full": "11 Kendall Rd Boylston MA 01505",
    "addr:housenumber": "11",
    "addr:postcode": "01505",
    "addr:street": "Kendall Rd",
    "iso:country": "US",
    "sg:address": "11 Kendall Rd",
    "sg:city": "Boylston",
    "sg:classifiers": [
      {
        "category": "Professional",
        "subcategory": "Management \u0026 Consulting",
        "type": "Services"
      }
    ],
    "sg:phone": "+1   ",
    "sg:postcode": "01505",
    "sg:province": "MA",
    "sg:tags": [
      "consultant"
    ],
    "wof:name": "Joanne D Cox",
    "wof:placetype": "venue"
  },
  "geometry": {"coordinates":[-71.761076,42.317783],"type":"Point"}
}
