{
  "type": "Feature",
  "properties": {
    "addr:full":"153 Boston Ave Medford MA 02155",
    "addr:housenumber":"153",
    "addr:postcode":"02155",
    "addr:street":"Boston Ave",
    "iso:country":"US",
    "sg:address":"153 Boston Ave",
    "sg:city":"Medford",
    "sg:classifiers":[
        {
            "category":"Building & Trades",
            "subcategory":"Locksmith",
            "type":"Services"
        }
    ],
    "sg:phone":"+1 781 443 7056",
    "sg:postcode":"02155",
    "sg:province":"MA",
    "sg:tags":[
        "key"
    ],
    "wof:name":"ABC 24 Locksmith Service",
    "wof:placetype":"venue"
},
  "geometry": {"coordinates":[-71.12965,42.416553],"type":"Point"}
}