{
  "type": "Feature",
  "properties": {
    "iso:country":"US",
    "sg:address":"77 Dragon Ct",
    "sg:city":"Woburn",
    "sg:classifiers":[
        {
            "category":"Manufacturing",
            "subcategory":"Electronics",
            "type":"Manufacturing & Wholesale Goods"
        }
    ],
    "sg:phone":"+1 781 935 4850",
    "sg:postcode":"01801",
    "sg:province":"MA",
    "sg:tags":[
        "equipment",
        "electronic",
        "supply"
    ],
    "sg:website":"www.chomericstest.com",
    "wof:name":"Chomerics Inc",
    "wof:placetype":"venue"
},
  "geometry": {"coordinates":[-71.128512,42.51233],"type":"Point"}
}