{
  "type": "Feature",
  "properties": {
    "iso:country":"US",
    "sg:address":"40 Hampshire St",
    "sg:city":"Cambridge",
    "sg:classifiers":[
        {
            "category":"Restaurant",
            "type":"Food & Drink"
        }
    ],
    "sg:menulink":"http://www.allmenus.com/ma/cambridge/547-emmas-pizza/menu/",
    "sg:phone":"+1 617 864 8534",
    "sg:postcode":"02139",
    "sg:province":"MA",
    "sg:tags":[
        "american",
        "pizza"
    ],
    "wof:name":"Emma's Pizza",
    "wof:placetype":"venue"
},
  "geometry": {"coordinates":[-71.09213800000001,42.366587],"type":"Point"}
}