{
  "type": "Feature",
  "properties": {
    "addr:full": "767 Centre St Jamaica Plain MA 02130",
    "addr:housenumber": "767",
    "addr:postcode": "02130",
    "addr:street": "Centre St",
    "iso:country": "US",
    "sg:address": "767 Centre St",
    "sg:city": "Jamaica Plain",
    "sg:classifiers": [
      {
        "category": "Personal",
        "subcategory": "Beauty Salon",
        "type": "Services"
      }
    ],
    "sg:phone": "+1 617 524 9711",
    "sg:postcode": "02130",
    "sg:province": "MA",
    "sg:tags": [
      "shop"
    ],
    "wof:name": "Julia's Beauty Shoppe",
    "wof:placetype": "venue"
  },
  "geometry": {"coordinates":[-71.115472,42.309675],"type":"Point"}
}
