{
  "type": "Feature",
  "properties": {
    "iso:country":"US",
    "sg:address":"111 Gordon Owen Pkwy",
    "sg:city":"Taunton",
    "sg:classifiers":[
        {
            "category":"Banks & Credit Unions",
            "subcategory":"Bank",
            "type":"Services"
        }
    ],
    "sg:phone":"+1   ",
    "sg:postcode":"02780",
    "sg:province":"MA",
    "sg:tags":[
        "national",
        "commercial"
    ],
    "wof:name":"National Gard Rcrting Rtention",
    "wof:placetype":"venue"
},
  "geometry": {"coordinates":[-71.07545500000001,41.897929],"type":"Point"}
}