{
  "type": "Feature",
  "properties": {
    "iso:country":"US",
    "sg:address":"6 May St",
    "sg:city":"Marblehead",
    "sg:classifiers":[
        {
            "category":"Wholesale",
            "subcategory":"Non-durable Goods",
            "type":"Manufacturing & Wholesale Goods"
        }
    ],
    "sg:phone":"+1   ",
    "sg:postcode":"01945",
    "sg:province":"MA",
    "sg:tags":[
        "import",
        "advertising",
        "specialty"
    ],
    "wof:name":"Carlsan Ames Co",
    "wof:placetype":"venue"
},
  "geometry": {"coordinates":[-70.887452,42.483932],"type":"Point"}
}