{
  "type": "Feature",
  "properties": {
    "addr:full": "129 South St Fl 2 Boston MA 02111",
    "addr:housenumber": "129;2",
    "addr:postcode": "02111",
    "addr:street": "South St",
    "iso:country": "US",
    "sg:address": "129 South St Fl 2",
    "sg:city": "Boston",
    "sg:classifiers": [
      {
        "category": "Professional",
        "subcategory": "Art Services",
        "type": "Services"
      }
    ],
    "sg:phone": "+1 617 424 8887",
    "sg:postcode": "02111",
    "sg:province": "MA",
    "sg:tags": [
      "designer",
      "display",
      "producer"
    ],
    "wof:name": "The Barbarian Group",
    "wof:placetype": "venue"
  },
  "geometry": {"coordinates":[-71.057292,42.351143],"type":"Point"}
}
