{
  "type": "Feature",
  "properties": {
    "addr:full": "205 Stevens Rd Swansea MA 02777",
    "addr:housenumber": "205",
    "addr:postcode": "02777",
    "addr:street": "Stevens Rd",
    "iso:country": "US",
    "sg:address": "205 Stevens Rd",
    "sg:city": "Swansea",
    "sg:classifiers": [
      {
        "category": "Home \u0026 Garden",
        "subcategory": "Garden Supply",
        "type": "Retail Goods"
      }
    ],
    "sg:phone": "+1 508 672 0577",
    "sg:postcode": "02777",
    "sg:province": "MA",
    "sg:tags": [
      "nurseryman"
    ],
    "wof:name": "Souza Nursery Landscaping Co",
    "wof:placetype": "venue"
  },
  "geometry": {"coordinates":[-71.173758,41.75154],"type":"Point"}
}
