{
  "type": "Feature",
  "properties": {
    "addr:full": "648 Washington St Ste 204 Norwood MA 02062",
    "addr:housenumber": "648",
    "addr:postcode": "02062",
    "addr:street": "Washington St Ste 204",
    "iso:country": "US",
    "sg:address": "648 Washington St Ste 204",
    "sg:city": "Norwood",
    "sg:classifiers": [
      {
        "category": "Health Services",
        "subcategory": "Dentist",
        "type": "Services"
      }
    ],
    "sg:phone": "+1 781 551 0235",
    "sg:postcode": "02062",
    "sg:province": "MA",
    "wof:name": "Family Dental Care",
    "wof:placetype": "venue"
  },
  "geometry": {"coordinates":[-71.200798,42.194199],"type":"Point"}
}
