{
  "type": "Feature",
  "properties": {
    "iso:country":"US",
    "sg:address":"648 Washington St Ste 204",
    "sg:city":"Norwood",
    "sg:classifiers":[
        {
            "category":"Health Services",
            "subcategory":"Dentist",
            "type":"Services"
        }
    ],
    "sg:phone":"+1 781 551 0235",
    "sg:postcode":"02062",
    "sg:province":"MA",
    "wof:name":"Family Dental Care",
    "wof:placetype":"venue"
},
  "geometry": {"coordinates":[-71.20079800000001,42.194199],"type":"Point"}
}