{
  "type": "Feature",
  "properties": {
    "iso:country":"US",
    "sg:address":"95 Lincoln St",
    "sg:city":"Framingham",
    "sg:classifiers":[
        {
            "category":"Health Services",
            "subcategory":"Chiropractor",
            "type":"Services"
        }
    ],
    "sg:phone":"+1 508 620 1940",
    "sg:postcode":"01702",
    "sg:province":"MA",
    "wof:name":"Metrowest Chiropractic Assoc",
    "wof:placetype":"venue"
},
  "geometry": {"coordinates":[-71.419076,42.283915],"type":"Point"}
}