{
  "type": "Feature",
  "properties": {
    "addr:full":"233 S Main St Randolph MA 02368",
    "addr:housenumber":"233",
    "addr:postcode":"02368",
    "addr:street":"S Main St",
    "iso:country":"US",
    "sg:address":"233 S Main St",
    "sg:city":"Randolph",
    "sg:classifiers":[
        {
            "category":"Organizations",
            "subcategory":"Religious Organization",
            "type":"Services"
        }
    ],
    "sg:phone":"+1 781 986 2186",
    "sg:postcode":"02368",
    "sg:province":"MA",
    "sg:tags":[
        "church"
    ],
    "wof:name":"International Assembly Of God",
    "wof:placetype":"venue"
},
  "geometry": {"coordinates":[-71.04496,42.15464],"type":"Point"}
}