{
  "type": "Feature",
  "properties": {
    "iso:country":"US",
    "sg:address":"41 Pleasant St",
    "sg:city":"Westford",
    "sg:classifiers":[
        {
            "category":"Building & Trades",
            "subcategory":"Construction",
            "type":"Services"
        }
    ],
    "sg:phone":"+1   ",
    "sg:postcode":"01886",
    "sg:province":"MA",
    "sg:tags":[
        "house"
    ],
    "wof:name":"Lemieux Constuction",
    "wof:placetype":"venue"
},
  "geometry": {"coordinates":[-71.482542,42.57899],"type":"Point"}
}