{
  "type": "Feature",
  "properties": {
    "addr:full": "263 Elm St Amesbury MA 01913",
    "addr:housenumber": "263",
    "addr:postcode": "01913",
    "addr:street": "Elm St",
    "iso:country": "US",
    "sg:address": "263 Elm St",
    "sg:city": "Amesbury",
    "sg:classifiers": [
      {
        "category": "Retail",
        "subcategory": "Auto Repair",
        "type": "Services"
      }
    ],
    "sg:phone": "+1 978 388 0881",
    "sg:postcode": "01913",
    "sg:province": "MA",
    "sg:tags": [
      "body",
      "automobile",
      "painting"
    ],
    "wof:name": "George's Auto Body",
    "wof:placetype": "venue"
  },
  "geometry": {"coordinates":[-70.910736,42.850009],"type":"Point"}
}
