{
  "type": "Feature",
  "properties": {
    "iso:country":"US",
    "sg:address":"81 Oak Hill Dr",
    "sg:city":"Sharon",
    "sg:classifiers":[
        {
            "category":"Professional",
            "subcategory":"Business Services",
            "type":"Services"
        }
    ],
    "sg:phone":"+1   ",
    "sg:postcode":"02067",
    "sg:province":"MA",
    "wof:name":"R Sipzener",
    "wof:placetype":"venue"
},
  "geometry": {"coordinates":[-71.154844,42.110428],"type":"Point"}
}