{
  "type": "Feature",
  "properties": {
    "addr:full":"545 Massachusetts Ave Lunenburg MA 01462",
    "addr:housenumber":"545",
    "addr:postcode":"01462",
    "addr:street":"Massachusetts Ave",
    "iso:country":"US",
    "sg:address":"545 Massachusetts Ave",
    "sg:city":"Lunenburg",
    "sg:classifiers":[
        {
            "category":"Building & Trades",
            "subcategory":"Construction",
            "type":"Services"
        }
    ],
    "sg:phone":"+1 978 582 6043",
    "sg:postcode":"01462",
    "sg:province":"MA",
    "sg:tags":[
        "excavating",
        "contractor"
    ],
    "wof:name":"A C Szocik Inc",
    "wof:placetype":"venue"
},
  "geometry": {"coordinates":[-71.747338,42.595341],"type":"Point"}
}