{
  "type": "Feature",
  "properties": {
    "iso:country":"US",
    "sg:address":"5 Perth St",
    "sg:city":"Dorchester",
    "sg:classifiers":[
        {
            "category":"Real Estate",
            "subcategory":"Real Estate Operator",
            "type":"Services"
        }
    ],
    "sg:phone":"+1 617 442 4242",
    "sg:postcode":"02121",
    "sg:province":"MA",
    "sg:tags":[
        "apartment"
    ],
    "wof:name":"Phillips Brooks School Housing",
    "wof:placetype":"venue"
},
  "geometry": {"coordinates":[-71.07626500000001,42.313429],"type":"Point"}
}