{
  "type": "Feature",
  "properties": {
    "addr:full": "5 Perth St Dorchester MA 02121",
    "addr:housenumber": "5",
    "addr:postcode": "02121",
    "addr:street": "Perth St",
    "iso:country": "US",
    "sg:address": "5 Perth St",
    "sg:city": "Dorchester",
    "sg:classifiers": [
      {
        "category": "Real Estate",
        "subcategory": "Real Estate Operator",
        "type": "Services"
      }
    ],
    "sg:phone": "+1 617 442 4242",
    "sg:postcode": "02121",
    "sg:province": "MA",
    "sg:tags": [
      "apartment"
    ],
    "wof:name": "Phillips Brooks School Housing",
    "wof:placetype": "venue"
  },
  "geometry": {"coordinates":[-71.076265,42.313429],"type":"Point"}
}
