{
  "type": "Feature",
  "properties": {
    "addr:full":"6 Number 10 Schoolhouse Rd Charlton MA 01507",
    "addr:housenumber":"6",
    "addr:postcode":"01507",
    "addr:street":"Number 10 Schoolhouse Rd",
    "iso:country":"US",
    "sg:address":"6 Number 10 Schoolhouse Rd",
    "sg:city":"Charlton",
    "sg:classifiers":[
        {
            "category":"Building & Trades",
            "subcategory":"Construction",
            "type":"Services"
        }
    ],
    "sg:phone":"+1 508 479 2608",
    "sg:postcode":"01507",
    "sg:province":"MA",
    "sg:tags":[
        "contractor"
    ],
    "wof:name":"Paul Dansereau Company",
    "wof:placetype":"venue"
},
  "geometry": {"coordinates":[-72.02896200000001,42.128399],"type":"Point"}
}