{
  "type": "Feature",
  "properties": {
    "addr:full":"918 Boston-Providence Tpke Norwood MA 02062",
    "addr:housenumber":"918",
    "addr:postcode":"02062",
    "addr:street":"Boston-Providence Tpke",
    "iso:country":"US",
    "sg:address":"918 Boston-Providence Tpke",
    "sg:city":"Norwood",
    "sg:classifiers":[
        {
            "category":"Autos & Motor Vehicles",
            "subcategory":"Auto Supplies",
            "type":"Retail Goods"
        }
    ],
    "sg:phone":"+1 781 255 7483",
    "sg:postcode":"02062",
    "sg:province":"MA",
    "sg:tags":[
        "automobile",
        "parts"
    ],
    "wof:name":"Gallery Automotive Group",
    "wof:placetype":"venue"
},
  "geometry": {"coordinates":[-71.18930400000001,42.180351],"type":"Point"}
}