{
  "type": "Feature",
  "properties": {
    "iso:country":"US",
    "sg:address":"122 Turnpike Rd",
    "sg:city":"Westborough",
    "sg:classifiers":[
        {
            "category":"Manufacturing",
            "subcategory":"Tools & Machinery",
            "type":"Manufacturing & Wholesale Goods"
        },
        {
            "category":"Wholesale",
            "subcategory":"Home Furnishings",
            "type":"Manufacturing & Wholesale Goods"
        }
    ],
    "sg:phone":"+1 508 898 2929",
    "sg:postcode":"01581",
    "sg:province":"MA",
    "sg:tags":[
        "shades-wholesale",
        "lamp",
        "shade",
        "manufacturer"
    ],
    "wof:name":"Boxwell's",
    "wof:placetype":"venue"
},
  "geometry": {"coordinates":[-71.605009,42.284941],"type":"Point"}
}