{
  "type": "Feature",
  "properties": {
    "iso:country":"US",
    "sg:address":"35 Fair Acres Dr",
    "sg:city":"Marstons Mills",
    "sg:classifiers":[
        {
            "category":"Professional",
            "type":"Services"
        }
    ],
    "sg:phone":"+1 508 428 5253",
    "sg:postcode":"02648",
    "sg:province":"MA",
    "sg:tags":[
        "establishment"
    ],
    "wof:name":"Bfi",
    "wof:placetype":"venue"
},
  "geometry": {"coordinates":[-70.394576,41.66867],"type":"Point"}
}