{
  "type": "Feature",
  "properties": {
    "addr:full":"42 Thomas Dr Chelmsford MA 01824",
    "addr:housenumber":"42",
    "addr:postcode":"01824",
    "addr:street":"Thomas Dr",
    "iso:country":"US",
    "sg:address":"42 Thomas Dr",
    "sg:city":"Chelmsford",
    "sg:classifiers":[
        {
            "category":"Shopping",
            "subcategory":"Gifts & Souvenirs",
            "type":"Retail Goods"
        }
    ],
    "sg:phone":"+1   ",
    "sg:postcode":"01824",
    "sg:province":"MA",
    "wof:name":"Country Baskets",
    "wof:placetype":"venue"
},
  "geometry": {"coordinates":[-71.390874,42.602361],"type":"Point"}
}