{
  "type": "Feature",
  "properties": {
    "iso:country":"US",
    "sg:address":"1 Coolidge Ave",
    "sg:city":"Greenfield",
    "sg:classifiers":[
        {
            "category":"Education",
            "subcategory":"College",
            "type":"Public Place"
        }
    ],
    "sg:phone":"+1 413 775 1000",
    "sg:postcode":"01301",
    "sg:province":"MA",
    "sg:tags":[
        "academic",
        "school"
    ],
    "wof:name":"Greenfield Community College",
    "wof:placetype":"venue"
},
  "geometry": {"coordinates":[-72.58008100000001,42.610369],"type":"Point"}
}