{
  "type": "Feature",
  "properties": {
    "iso:country":"US",
    "sg:address":"10 Brainerd Rd",
    "sg:city":"Allston",
    "sg:classifiers":[
        {
            "category":"Real Estate",
            "subcategory":"Real Estate Operator",
            "type":"Services"
        }
    ],
    "sg:phone":"+1 617 232 7844",
    "sg:postcode":"02134",
    "sg:province":"MA",
    "sg:tags":[
        "apartment"
    ],
    "wof:name":"Zee Paragon Suites",
    "wof:placetype":"venue"
},
  "geometry": {"coordinates":[-71.130487,42.348964],"type":"Point"}
}