{
  "type": "Feature",
  "properties": {
    "iso:country":"US",
    "sg:address":"120 Business St",
    "sg:city":"Hyde Park",
    "sg:classifiers":[
        {
            "category":"Retail",
            "subcategory":"Car Wash",
            "type":"Services"
        }
    ],
    "sg:phone":"+1 617 361 1001",
    "sg:postcode":"02136",
    "sg:province":"MA",
    "sg:tags":[
        "automobile",
        "detail",
        "clean"
    ],
    "wof:name":"Fluffed & Buffed",
    "wof:placetype":"venue"
},
  "geometry": {"coordinates":[-71.130906,42.250776],"type":"Point"}
}