{
  "type": "Feature",
  "properties": {
    "addr:full": "9 Billerica Rd Chelmsford MA 01824",
    "addr:housenumber": "9",
    "addr:postcode": "01824",
    "addr:street": "Billerica Rd",
    "iso:country": "US",
    "sg:address": "9 Billerica Rd",
    "sg:city": "Chelmsford",
    "sg:classifiers": [
      {
        "category": "Professional",
        "subcategory": "Lawyer \u0026 Legal Services",
        "type": "Services"
      }
    ],
    "sg:phone": "+1 978 244 0099",
    "sg:postcode": "01824",
    "sg:province": "MA",
    "wof:name": "Kristyn M Snyer",
    "wof:placetype": "venue"
  },
  "geometry": {"coordinates":[-71.349039,42.597057],"type":"Point"}
}
