{
  "type": "Feature",
  "properties": {
    "iso:country":"US",
    "sg:address":"8 Wymon Way",
    "sg:city":"Lynnfield",
    "sg:classifiers":[
        {
            "category":"Restaurant",
            "type":"Food & Drink"
        }
    ],
    "sg:phone":"+1 781 334 6009",
    "sg:postcode":"01940",
    "sg:province":"MA",
    "wof:name":"Lucky Thirteen Restaurant, Inc.",
    "wof:placetype":"venue"
},
  "geometry": {"coordinates":[-71.03710700000001,42.534111],"type":"Point"}
}