{
  "type": "Feature",
  "properties": {
    "addr:full": "8 Wymon Way Lynnfield MA 01940",
    "addr:housenumber": "8",
    "addr:postcode": "01940",
    "addr:street": "Wymon Way",
    "iso:country": "US",
    "sg:address": "8 Wymon Way",
    "sg:city": "Lynnfield",
    "sg:classifiers": [
      {
        "category": "Restaurant",
        "type": "Food \u0026 Drink"
      }
    ],
    "sg:phone": "+1 781 334 6009",
    "sg:postcode": "01940",
    "sg:province": "MA",
    "wof:name": "Lucky Thirteen Restaurant, Inc.",
    "wof:placetype": "venue"
  },
  "geometry": {"coordinates":[-71.037107,42.534111],"type":"Point"}
}
