{
  "type": "Feature",
  "properties": {
    "addr:full": "411 Front St Weymouth MA 02188",
    "addr:housenumber": "411",
    "addr:postcode": "02188",
    "addr:street": "Front St",
    "iso:country": "US",
    "sg:address": "411 Front St",
    "sg:city": "Weymouth",
    "sg:classifiers": [
      {
        "category": "Wholesale",
        "subcategory": "Medical Equipment \u0026 Supplies",
        "type": "Manufacturing \u0026 Wholesale Goods"
      },
      {
        "category": "Retail",
        "subcategory": "Repair Shop",
        "type": "Services"
      }
    ],
    "sg:phone": "+1 781 340 0351",
    "sg:postcode": "02188",
    "sg:province": "MA",
    "sg:tags": [
      "physician",
      "surgeon",
      "refinishing",
      "equipment-repairing"
    ],
    "wof:name": "Freedom Security \u0026 Medical Mec",
    "wof:placetype": "venue"
  },
  "geometry": {"coordinates":[-70.959222,42.206315],"type":"Point"}
}
