{
  "type": "Feature",
  "properties": {
    "iso:country":"US",
    "sg:address":"175 N Beacon St",
    "sg:city":"Watertown",
    "sg:classifiers":[
        {
            "category":"Social Services",
            "type":"Services"
        }
    ],
    "sg:phone":"+1 617 972 7442",
    "sg:postcode":"02472",
    "sg:province":"MA",
    "sg:tags":[
        "program",
        "services-information",
        "referral"
    ],
    "wof:name":"National Association For Paren",
    "wof:placetype":"venue"
},
  "geometry": {"coordinates":[-71.17447199999999,42.363477],"type":"Point"}
}