{
  "type": "Feature",
  "properties": {
    "addr:full": "12 Center St Fairhaven MA 02719",
    "addr:housenumber": "12",
    "addr:postcode": "02719",
    "addr:street": "Center St",
    "iso:country": "US",
    "sg:address": "12 Center St",
    "sg:city": "Fairhaven",
    "sg:classifiers": [
      {
        "category": "Professional",
        "subcategory": "Lawyer \u0026 Legal Services",
        "type": "Services"
      }
    ],
    "sg:phone": "+1 508 993 9991",
    "sg:postcode": "02719",
    "sg:province": "MA",
    "sg:tags": [
      "attorney",
      "practice"
    ],
    "wof:name": "Cyril O'leary",
    "wof:placetype": "venue"
  },
  "geometry": {"coordinates":[-70.90554,41.635769],"type":"Point"}
}
