{
  "type": "Feature",
  "properties": {
    "addr:full":"107 N Chicopee St Chicopee MA 01020",
    "addr:housenumber":"107",
    "addr:postcode":"01020",
    "addr:street":"N Chicopee St",
    "iso:country":"US",
    "sg:address":"107 N Chicopee St",
    "sg:city":"Chicopee",
    "sg:classifiers":[
        {
            "category":"Mining & Drilling",
            "type":"Manufacturing & Wholesale Goods"
        }
    ],
    "sg:phone":"+1 413 538 7279",
    "sg:postcode":"01020",
    "sg:province":"MA",
    "sg:tags":[
        "rigger"
    ],
    "sg:website":"www.chicopeeindustrial.com",
    "wof:name":"Chicopee Industrial Contractor",
    "wof:placetype":"venue"
},
  "geometry": {"coordinates":[-72.59637600000001,42.195599],"type":"Point"}
}