{
  "type": "Feature",
  "properties": {
    "addr:full":"3 Muriel Dr Westford MA 01886",
    "addr:housenumber":"3",
    "addr:postcode":"01886",
    "addr:street":"Muriel Dr",
    "iso:country":"US",
    "sg:address":"3 Muriel Dr",
    "sg:city":"Westford",
    "sg:classifiers":[
        {
            "category":"Building & Trades",
            "subcategory":"Plumbing",
            "type":"Services"
        }
    ],
    "sg:phone":"+1 978 692 4441",
    "sg:postcode":"01886",
    "sg:province":"MA",
    "sg:tags":[
        "plumbing",
        "contractor"
    ],
    "wof:name":"Topjian Plumbing & Heating Inc",
    "wof:placetype":"venue"
},
  "geometry": {"coordinates":[-71.434466,42.618283],"type":"Point"}
}