{
  "type": "Feature",
  "properties": {
    "iso:country":"US",
    "sg:address":"1147 Commonwealth Ave",
    "sg:city":"Allston",
    "sg:classifiers":[
        {
            "category":"Food & Beverages",
            "subcategory":"Groceries & Convenience Stores",
            "type":"Retail Goods"
        }
    ],
    "sg:phone":"+1 617 782 0087",
    "sg:postcode":"02134",
    "sg:province":"MA",
    "wof:name":"Lee's 1 Market",
    "wof:placetype":"venue"
},
  "geometry": {"coordinates":[-71.128516,42.350505],"type":"Point"}
}