{
  "type": "Feature",
  "properties": {
    "addr:full": "30 Summit Lock Rd Westfield MA 01085",
    "addr:housenumber": "30",
    "addr:postcode": "01085",
    "addr:street": "Summit Lock Rd",
    "iso:country": "US",
    "sg:address": "30 Summit Lock Rd",
    "sg:city": "Westfield",
    "sg:phone": "+1 413 562 6588",
    "sg:postcode": "01085",
    "sg:province": "MA",
    "sg:tags": [
      "gas"
    ],
    "wof:name": "Duke Energy",
    "wof:placetype": "venue"
  },
  "geometry": {"coordinates":[-72.74363,42.178236],"type":"Point"}
}
