{
  "type": "Feature",
  "properties": {
    "iso:country":"US",
    "sg:address":"30 Summit Lock Rd",
    "sg:city":"Westfield",
    "sg:phone":"+1 413 562 6588",
    "sg:postcode":"01085",
    "sg:province":"MA",
    "sg:tags":[
        "gas"
    ],
    "wof:name":"Duke Energy",
    "wof:placetype":"venue"
},
  "geometry": {"coordinates":[-72.74363,42.178236],"type":"Point"}
}