{
  "type": "Feature",
  "properties": {
    "iso:country":"US",
    "sg:address":"940 County St",
    "sg:city":"Taunton",
    "sg:classifiers":[
        {
            "category":"Education",
            "subcategory":"School",
            "type":"Public Place"
        }
    ],
    "sg:phone":"+1 508 823 5151",
    "sg:postcode":"02780",
    "sg:province":"MA",
    "sg:website":"www.bptech.org",
    "wof:name":"Bristol-Plymouth Regional Tech",
    "wof:placetype":"venue"
},
  "geometry": {"coordinates":[-71.058708,41.874819],"type":"Point"}
}