{
  "type": "Feature",
  "properties": {
    "addr:full": "940 County St Taunton MA 02780",
    "addr:housenumber": "940",
    "addr:postcode": "02780",
    "addr:street": "County St",
    "iso:country": "US",
    "sg:address": "940 County St",
    "sg:city": "Taunton",
    "sg:classifiers": [
      {
        "category": "Education",
        "subcategory": "School",
        "type": "Public Place"
      }
    ],
    "sg:phone": "+1 508 823 5151",
    "sg:postcode": "02780",
    "sg:province": "MA",
    "sg:website": "www.bptech.org",
    "wof:name": "Bristol-Plymouth Regional Tech",
    "wof:placetype": "venue"
  },
  "geometry": {"coordinates":[-71.058708,41.874819],"type":"Point"}
}
