{
  "type": "Feature",
  "properties": {
    "addr:full":"398 Essex St Beverly MA 01915",
    "addr:housenumber":"398",
    "addr:postcode":"01915",
    "addr:street":"Essex St",
    "iso:country":"US",
    "sg:address":"398 Essex St",
    "sg:city":"Beverly",
    "sg:classifiers":[
        {
            "category":"Professional",
            "subcategory":"Lawyer & Legal Services",
            "type":"Services"
        }
    ],
    "sg:phone":"+1 978 922 4443",
    "sg:postcode":"01915",
    "sg:province":"MA",
    "sg:tags":[
        "attorney"
    ],
    "wof:name":"George E Hazel Attorney-Law",
    "wof:placetype":"venue"
},
  "geometry": {"coordinates":[-70.85617499999999,42.572996],"type":"Point"}
}