{
  "type": "Feature",
  "properties": {
    "addr:full":"875 Massachusetts Ave. Ste 81 Cambridge MA 02139",
    "addr:housenumber":"875;81",
    "addr:postcode":"02139",
    "addr:street":"Massachusetts Ave. Ste",
    "iso:country":"US",
    "sg:address":"875 Massachusetts Ave. Ste 81",
    "sg:city":"Cambridge",
    "sg:classifiers":[
        {
            "category":"Health Services",
            "subcategory":"Clinic",
            "type":"Services"
        },
        {
            "category":"Sports & Exercise",
            "subcategory":"Gym",
            "type":"Entertainment"
        }
    ],
    "sg:phone":"+1 617 868 6496",
    "sg:postcode":"02139",
    "sg:province":"MA",
    "sg:tags":[
        "trainer",
        "medical"
    ],
    "wof:name":"Alchek Maxine Psycholgst",
    "wof:placetype":"venue"
},
  "geometry": {"coordinates":[-71.107567,42.367764],"type":"Point"}
}