{
  "type": "Feature",
  "properties": {
    "iso:country":"US",
    "sg:address":"34 Plunkett St",
    "sg:city":"Pittsfield",
    "sg:classifiers":[
        {
            "category":"Building & Trades",
            "subcategory":"Construction",
            "type":"Services"
        }
    ],
    "sg:phone":"+1 413 499 2205",
    "sg:postcode":"01201",
    "sg:province":"MA",
    "sg:tags":[
        "drywall",
        "contractor"
    ],
    "wof:name":"Howe Rj Drywall",
    "wof:placetype":"venue"
},
  "geometry": {"coordinates":[-73.23663000000001,42.455486],"type":"Point"}
}