{
  "type": "Feature",
  "properties": {
    "addr:full": "33 Pine Ridge Dr Ayer MA 01432",
    "addr:housenumber": "33",
    "addr:postcode": "01432",
    "addr:street": "Pine Ridge Dr",
    "iso:country": "US",
    "sg:address": "33 Pine Ridge Dr",
    "sg:city": "Ayer",
    "sg:classifiers": [
      {
        "category": "Manufacturing",
        "subcategory": "Tools \u0026 Machinery",
        "type": "Manufacturing \u0026 Wholesale Goods"
      }
    ],
    "sg:phone": "+1   ",
    "sg:postcode": "01432",
    "sg:province": "MA",
    "sg:tags": [
      "electrical",
      "mfg"
    ],
    "wof:name": "Kilroy Security \u0026 Electronics",
    "wof:placetype": "venue"
  },
  "geometry": {"coordinates":[-71.565293,42.56133],"type":"Point"}
}
