{
  "type": "Feature",
  "properties": {
    "iso:country":"US",
    "sg:address":"33 Pine Ridge Dr",
    "sg:city":"Ayer",
    "sg:classifiers":[
        {
            "category":"Manufacturing",
            "subcategory":"Tools & Machinery",
            "type":"Manufacturing & Wholesale Goods"
        }
    ],
    "sg:phone":"+1   ",
    "sg:postcode":"01432",
    "sg:province":"MA",
    "sg:tags":[
        "electrical",
        "mfg"
    ],
    "wof:name":"Kilroy Security & Electronics",
    "wof:placetype":"venue"
},
  "geometry": {"coordinates":[-71.565293,42.56133],"type":"Point"}
}