{
  "type": "Feature",
  "properties": {
    "addr:full": "297 Shore Rd Chatham MA 02633",
    "addr:housenumber": "297",
    "addr:postcode": "02633",
    "addr:street": "Shore Rd",
    "iso:country": "US",
    "ovtr:label": "Chatham Bars Inn, 297 Shore Rd Chatham MA US",
    "ovtr:similarity": 2.803776979446411,
    "sg:address": "297 Shore Rd",
    "sg:city": "Chatham",
    "sg:classifiers": [
      {
        "category": "Travel",
        "subcategory": "Hotels \u0026 Motels",
        "type": "Entertainment"
      }
    ],
    "sg:phone": "+1 508 945 0096",
    "sg:postcode": "02633",
    "sg:province": "MA",
    "sg:tags": [
      "resort"
    ],
    "sg:website": "www.chathambarsinn.com",
    "wof:name": "Chatham Bars Inn",
    "wof:placetype": "venue"
  },
  "geometry": {"coordinates":[-69.951334,41.683966],"type":"Point"}
}
