{
  "type": "Feature",
  "properties": {
    "addr:full":"23 President St Westport MA 02790",
    "addr:housenumber":"23",
    "addr:postcode":"02790",
    "addr:street":"President St",
    "iso:country":"US",
    "sg:address":"23 President St",
    "sg:city":"Westport",
    "sg:classifiers":[
        {
            "category":"Utilities",
            "subcategory":"Mobile Phone",
            "type":"Services"
        }
    ],
    "sg:phone":"+1   ",
    "sg:postcode":"02790",
    "sg:province":"MA",
    "sg:tags":[
        "communication",
        "radiotelephone"
    ],
    "wof:name":"Ajf Communications Plus",
    "wof:placetype":"venue"
},
  "geometry": {"coordinates":[-71.078095,41.660189],"type":"Point"}
}