{
  "type": "Feature",
  "properties": {
    "addr:full":"286 Centre St Newton MA 02458",
    "addr:housenumber":"286",
    "addr:postcode":"02458",
    "addr:street":"Centre St",
    "iso:country":"US",
    "sg:address":"286 Centre St",
    "sg:city":"Newton",
    "sg:classifiers":[
        {
            "category":"Personal",
            "subcategory":"Beauty Salon",
            "type":"Services"
        }
    ],
    "sg:phone":"+1 617 964 3319",
    "sg:postcode":"02458",
    "sg:province":"MA",
    "sg:tags":[
        "manicuring"
    ],
    "wof:name":"Anna's Nails",
    "wof:placetype":"venue"
},
  "geometry": {"coordinates":[-71.184764,42.358298],"type":"Point"}
}