{
  "type": "Feature",
  "properties": {
    "iso:country":"US",
    "sg:address":"20 Black Oak Dr",
    "sg:city":"Attleboro",
    "sg:classifiers":[
        {
            "category":"Shopping",
            "subcategory":"Computers & Home Electronics",
            "type":"Retail Goods"
        }
    ],
    "sg:phone":"+1 508 226 4565",
    "sg:postcode":"02703",
    "sg:province":"MA",
    "sg:tags":[
        "software"
    ],
    "wof:name":"Business Technologies-New",
    "wof:placetype":"venue"
},
  "geometry": {"coordinates":[-71.30559599999999,41.932487],"type":"Point"}
}