{
  "type": "Feature",
  "properties": {
    "addr:full": "20 Black Oak Dr Attleboro MA 02703",
    "addr:housenumber": "20",
    "addr:postcode": "02703",
    "addr:street": "Black Oak Dr",
    "iso:country": "US",
    "sg:address": "20 Black Oak Dr",
    "sg:city": "Attleboro",
    "sg:classifiers": [
      {
        "category": "Shopping",
        "subcategory": "Computers \u0026 Home Electronics",
        "type": "Retail Goods"
      }
    ],
    "sg:phone": "+1 508 226 4565",
    "sg:postcode": "02703",
    "sg:province": "MA",
    "sg:tags": [
      "software"
    ],
    "wof:name": "Business Technologies-New",
    "wof:placetype": "venue"
  },
  "geometry": {"coordinates":[-71.305596,41.932487],"type":"Point"}
}
