{
  "type": "Feature",
  "properties": {
    "addr:full":"76 Lansing Pl Springfield MA 01108",
    "addr:housenumber":"76",
    "addr:postcode":"01108",
    "addr:street":"Lansing Pl",
    "iso:country":"US",
    "sg:address":"76 Lansing Pl",
    "sg:city":"Springfield",
    "sg:classifiers":[
        {
            "category":"Retail",
            "subcategory":"Auto Repair",
            "type":"Services"
        }
    ],
    "sg:phone":"+1 413 739 8623",
    "sg:postcode":"01108",
    "sg:province":"MA",
    "sg:tags":[
        "body",
        "automobile",
        "painting"
    ],
    "wof:name":"Felix Auto Body",
    "wof:placetype":"venue"
},
  "geometry": {"coordinates":[-72.56308199999999,42.088388],"type":"Point"}
}