{
  "type": "Feature",
  "properties": {
    "iso:country":"US",
    "sg:address":"38 West St",
    "sg:city":"Plympton",
    "sg:classifiers":[
        {
            "category":"Building & Trades",
            "subcategory":"Plumbing",
            "type":"Services"
        }
    ],
    "sg:phone":"+1 781 585 3241",
    "sg:postcode":"02367",
    "sg:province":"MA",
    "sg:tags":[
        "tank",
        "septic"
    ],
    "wof:name":"J R Construction",
    "wof:placetype":"venue"
},
  "geometry": {"coordinates":[-70.83134699999999,41.949292],"type":"Point"}
}