{
  "type": "Feature",
  "properties": {
    "iso:country":"US",
    "sg:address":"315 Massachusetts Avenue",
    "sg:city":"Arlington",
    "sg:classifiers":[
        {
            "category":"Personal",
            "subcategory":"Hair Removal",
            "type":"Services"
        },
        {
            "category":"Sports & Exercise",
            "subcategory":"Gym",
            "type":"Entertainment"
        },
        {
            "category":"Personal",
            "subcategory":"Skin Care",
            "type":"Services"
        }
    ],
    "sg:phone":"+1 781 643 7100",
    "sg:postcode":"02474",
    "sg:province":"MA",
    "sg:tags":[
        "trainer"
    ],
    "wof:name":"McKenna Elaine Cipolla",
    "wof:placetype":"venue"
},
  "geometry": {"coordinates":[-71.147526,42.409839],"type":"Point"}
}