{
  "type": "Feature",
  "properties": {
    "iso:country":"US",
    "sg:address":"1365 Main St",
    "sg:city":"Springfield",
    "sg:classifiers":[
        {
            "category":"Professional",
            "subcategory":"Lawyer & Legal Services",
            "type":"Services"
        }
    ],
    "sg:phone":"+1 413 733 4147",
    "sg:postcode":"01103",
    "sg:province":"MA",
    "sg:tags":[
        "attorney"
    ],
    "wof:name":"Donahue & Cross PC",
    "wof:placetype":"venue"
},
  "geometry": {"coordinates":[-72.589163,42.10205],"type":"Point"}
}