{
  "type": "Feature",
  "properties": {
    "addr:full": "1309 Cambridge St Cambridge MA 02139",
    "addr:housenumber": "1309",
    "addr:postcode": "02139",
    "addr:street": "Cambridge St",
    "iso:country": "US",
    "sg:address": "1309 Cambridge St",
    "sg:city": "Cambridge",
    "sg:classifiers": [
      {
        "category": "Shopping",
        "subcategory": "Used Merchandise",
        "type": "Retail Goods"
      }
    ],
    "sg:phone": "+1 617 547 3447",
    "sg:postcode": "02139",
    "sg:province": "MA",
    "sg:tags": [
      "book",
      "rare",
      "dealer"
    ],
    "wof:name": "House Of Sarah Books",
    "wof:placetype": "venue"
  },
  "geometry": {"coordinates":[-71.099331,42.373607],"type":"Point"}
}
