{
  "type": "Feature",
  "properties": {
    "addr:full":"10 Scotia St Salem MA 01970",
    "addr:housenumber":"10",
    "addr:postcode":"01970",
    "addr:street":"Scotia St",
    "iso:country":"US",
    "sg:address":"10 Scotia St",
    "sg:city":"Salem",
    "sg:classifiers":[
        {
            "category":"Sports & Exercise",
            "subcategory":"Bowling",
            "type":"Entertainment"
        }
    ],
    "sg:phone":"+1 617 266 2695",
    "sg:postcode":"01970",
    "sg:province":"MA",
    "sg:tags":[
        "center"
    ],
    "wof:name":"Kings Bowling Billiards",
    "wof:placetype":"venue"
},
  "geometry": {"coordinates":[-70.914613,42.519134],"type":"Point"}
}