{
  "type": "Feature",
  "properties": {
    "addr:full":"59 Main St Carver MA 02330",
    "addr:housenumber":"59",
    "addr:postcode":"02330",
    "addr:street":"Main St",
    "iso:country":"US",
    "sg:address":"59 Main St",
    "sg:city":"Carver",
    "sg:classifiers":[
        {
            "category":"Building & Trades",
            "subcategory":"Landscaping Services",
            "type":"Services"
        }
    ],
    "sg:phone":"+1 781 934 1311",
    "sg:postcode":"02330",
    "sg:province":"MA",
    "sg:tags":[
        "landscape",
        "contractor"
    ],
    "wof:name":"Edward's Landscape Svc",
    "wof:placetype":"venue"
},
  "geometry": {"coordinates":[-70.776899,41.893624],"type":"Point"}
}