{
  "type": "Feature",
  "properties": {
    "addr:full":"24 Industrial Way Wilmington MA 01887",
    "addr:housenumber":"24",
    "addr:postcode":"01887",
    "addr:street":"Industrial Way",
    "iso:country":"US",
    "sg:address":"24 Industrial Way",
    "sg:city":"Wilmington",
    "sg:classifiers":[
        {
            "category":"Manufacturing",
            "subcategory":"Tools & Machinery",
            "type":"Manufacturing & Wholesale Goods"
        }
    ],
    "sg:phone":"+1 978 988 5781",
    "sg:postcode":"01887",
    "sg:province":"MA",
    "sg:tags":[
        "die",
        "maker"
    ],
    "wof:name":"Master Craft Die Co",
    "wof:placetype":"venue"
},
  "geometry": {"coordinates":[-71.144558,42.527496],"type":"Point"}
}