{
  "type": "Feature",
  "properties": {
    "iso:country":"US",
    "sg:address":"25 Chestnut Hill Ave",
    "sg:city":"Brighton",
    "sg:classifiers":[
        {
            "category":"Autos & Motor Vehicles",
            "subcategory":"Auto Supplies",
            "type":"Retail Goods"
        },
        {
            "category":"Retail",
            "subcategory":"Auto Repair",
            "type":"Services"
        }
    ],
    "sg:phone":"+1 617 254 9437",
    "sg:postcode":"02135",
    "sg:province":"MA",
    "sg:tags":[
        "automobile",
        "part",
        "truck"
    ],
    "sg:website":"http://brightonauto.mechanicnet.com",
    "wof:name":"Brighton Auto Service",
    "wof:placetype":"venue"
},
  "geometry": {"coordinates":[-71.15389999999999,42.347801],"type":"Point"}
}