{
  "type": "Feature",
  "properties": {
    "addr:full": "25 Chestnut Hill Ave Brighton MA 02135",
    "addr:housenumber": "25",
    "addr:postcode": "02135",
    "addr:street": "Chestnut Hill Ave",
    "iso:country": "US",
    "ovtr:label": "Brighton Auto Service, 25 Chestnut Hill Ave Brighton MA US",
    "ovtr:similarity": 2.649523973464966,
    "sg:address": "25 Chestnut Hill Ave",
    "sg:city": "Brighton",
    "sg:classifiers": [
      {
        "category": "Autos \u0026 Motor Vehicles",
        "subcategory": "Auto Supplies",
        "type": "Retail Goods"
      },
      {
        "category": "Retail",
        "subcategory": "Auto Repair",
        "type": "Services"
      }
    ],
    "sg:phone": "+1 617 254 9437",
    "sg:postcode": "02135",
    "sg:province": "MA",
    "sg:tags": [
      "automobile",
      "part",
      "truck"
    ],
    "sg:website": "http://brightonauto.mechanicnet.com",
    "wof:name": "Brighton Auto Service",
    "wof:placetype": "venue"
  },
  "geometry": {"coordinates":[-71.1539,42.347801],"type":"Point"}
}
