{
  "type": "Feature",
  "properties": {
    "iso:country":"US",
    "sg:address":"262 Main St",
    "sg:city":"Marlborough",
    "sg:classifiers":[
        {
            "category":"Personal",
            "subcategory":"Beauty Salon",
            "type":"Services"
        }
    ],
    "sg:phone":"+1 508 460 8855",
    "sg:postcode":"01752",
    "sg:province":"MA",
    "wof:name":"Amarildo's Hair Design Unisex",
    "wof:placetype":"venue"
},
  "geometry": {"coordinates":[-71.55231999999999,42.346582],"type":"Point"}
}