{
  "type": "Feature",
  "properties": {
    "iso:country":"US",
    "sg:address":"4632 Falmouth Rd",
    "sg:city":"Cotuit",
    "sg:classifiers":[
        {
            "category":"Shopping",
            "subcategory":"Used Merchandise",
            "type":"Retail Goods"
        }
    ],
    "sg:phone":"+1 508 428 2752",
    "sg:postcode":"02635",
    "sg:province":"MA",
    "sg:tags":[
        "book",
        "rare",
        "dealer"
    ],
    "wof:name":"Isaiah Thomas Books & Prints",
    "wof:placetype":"venue"
},
  "geometry": {"coordinates":[-70.449045,41.638309],"type":"Point"}
}