{
  "type": "Feature",
  "properties": {
    "addr:full": "4632 Falmouth Rd Cotuit MA 02635",
    "addr:housenumber": "4632",
    "addr:postcode": "02635",
    "addr:street": "Falmouth Rd",
    "iso:country": "US",
    "ovtr:label": "Isaiah Thomas Books and Prints, 4632 Falmouth Rd Cotuit MA US",
    "ovtr:similarity": 2.0069758892059326,
    "sg:address": "4632 Falmouth Rd",
    "sg:city": "Cotuit",
    "sg:classifiers": [
      {
        "category": "Shopping",
        "subcategory": "Used Merchandise",
        "type": "Retail Goods"
      }
    ],
    "sg:phone": "+1 508 428 2752",
    "sg:postcode": "02635",
    "sg:province": "MA",
    "sg:tags": [
      "book",
      "rare",
      "dealer"
    ],
    "wof:name": "Isaiah Thomas Books \u0026 Prints",
    "wof:placetype": "venue"
  },
  "geometry": {"coordinates":[-70.449045,41.638309],"type":"Point"}
}
