{
  "type": "Feature",
  "properties": {
    "addr:full": "181 Locust St Holliston MA 01746",
    "addr:housenumber": "181",
    "addr:postcode": "01746",
    "addr:street": "Locust St",
    "iso:country": "US",
    "sg:address": "181 Locust St",
    "sg:city": "Holliston",
    "sg:classifiers": [
      {
        "category": "Manufacturing",
        "subcategory": "Lumber",
        "type": "Manufacturing \u0026 Wholesale Goods"
      }
    ],
    "sg:phone": "+1   ",
    "sg:postcode": "01746",
    "sg:province": "MA",
    "sg:tags": [
      "operation",
      "timber",
      "tract"
    ],
    "wof:name": "Higgins Family Christmas Trees",
    "wof:placetype": "venue"
  },
  "geometry": {"coordinates":[-71.419753,42.219546],"type":"Point"}
}
