{
  "type": "Feature",
  "properties": {
    "iso:country":"US",
    "sg:address":"181 Locust St",
    "sg:city":"Holliston",
    "sg:classifiers":[
        {
            "category":"Manufacturing",
            "subcategory":"Lumber",
            "type":"Manufacturing & Wholesale Goods"
        }
    ],
    "sg:phone":"+1   ",
    "sg:postcode":"01746",
    "sg:province":"MA",
    "sg:tags":[
        "operation",
        "timber",
        "tract"
    ],
    "wof:name":"Higgins Family Christmas Trees",
    "wof:placetype":"venue"
},
  "geometry": {"coordinates":[-71.419753,42.219546],"type":"Point"}
}