{
  "type": "Feature",
  "properties": {
    "addr:full": "670 Washington St Dorchester Ctr MA 02124",
    "addr:housenumber": "670",
    "addr:postcode": "02124",
    "addr:street": "Washington St",
    "iso:country": "US",
    "sg:address": "670 Washington St",
    "sg:city": "Dorchester Ctr",
    "sg:classifiers": [
      {
        "category": "Organizations",
        "subcategory": "Religious Organization",
        "type": "Services"
      }
    ],
    "sg:phone": "+1 617 282 7794",
    "sg:postcode": "02124",
    "sg:province": "MA",
    "sg:tags": [
      "church"
    ],
    "wof:name": "Global Ministry Christain Chr",
    "wof:placetype": "venue"
  },
  "geometry": {"coordinates":[-71.071043,42.288347],"type":"Point"}
}
