{
  "type": "Feature",
  "properties": {
    "iso:country":"US",
    "sg:address":"670 Washington St",
    "sg:city":"Dorchester Ctr",
    "sg:classifiers":[
        {
            "category":"Organizations",
            "subcategory":"Religious Organization",
            "type":"Services"
        }
    ],
    "sg:phone":"+1 617 282 7794",
    "sg:postcode":"02124",
    "sg:province":"MA",
    "sg:tags":[
        "church"
    ],
    "wof:name":"Global Ministry Christain Chr",
    "wof:placetype":"venue"
},
  "geometry": {"coordinates":[-71.071043,42.288347],"type":"Point"}
}