{
  "type": "Feature",
  "properties": {
    "addr:full": "32 Main St Concord MA 01742",
    "addr:housenumber": "32",
    "addr:postcode": "01742",
    "addr:street": "Main St",
    "iso:country": "US",
    "ovtr:label": "Fairbank and Perry Goldsmiths, 32 Main St Concord MA US",
    "ovtr:similarity": 2.3714640140533447,
    "sg:address": "32 Main St",
    "sg:city": "Concord",
    "sg:classifiers": [
      {
        "category": "Shopping",
        "subcategory": "Jewelry",
        "type": "Retail Goods"
      }
    ],
    "sg:phone": "+1 978 371 1088",
    "sg:postcode": "01742",
    "sg:province": "MA",
    "sg:website": "www.fairbankandperry.com",
    "wof:name": "Fairbank and Perry Goldsmiths",
    "wof:placetype": "venue"
  },
  "geometry": {"coordinates":[-71.349936,42.460099],"type":"Point"}
}
