{
  "type": "Feature",
  "properties": {
    "iso:country":"US",
    "sg:address":"939 Main St",
    "sg:city":"West Springfield",
    "sg:classifiers":[
        {
            "category":"Health Services",
            "subcategory":"Chiropractor",
            "type":"Services"
        }
    ],
    "sg:phone":"+1 413 732 0004",
    "sg:postcode":"01089",
    "sg:province":"MA",
    "wof:name":"Accident & Injury Center",
    "wof:placetype":"venue"
},
  "geometry": {"coordinates":[-72.60309700000001,42.098662],"type":"Point"}
}