{
  "type": "Feature",
  "properties": {
    "iso:country":"US",
    "sg:address":"3 S Water St",
    "sg:city":"New Bedford",
    "sg:classifiers":[
        {
            "category":"Restaurant",
            "type":"Food & Drink"
        }
    ],
    "sg:phone":"+1 508 999 6975",
    "sg:postcode":"02740",
    "sg:province":"MA",
    "wof:name":"Riverhouse Grille",
    "wof:placetype":"venue"
},
  "geometry": {"coordinates":[-70.92277199999999,41.634164],"type":"Point"}
}