{
  "type": "Feature",
  "properties": {
    "addr:full": "322 Bunker Hill St Charlestown MA 02129",
    "addr:housenumber": "322",
    "addr:postcode": "02129",
    "addr:street": "Bunker Hill St",
    "iso:country": "US",
    "sg:address": "322 Bunker Hill St",
    "sg:city": "Charlestown",
    "sg:classifiers": [
      {
        "category": "Retail",
        "subcategory": "Funeral Services",
        "type": "Services"
      }
    ],
    "sg:phone": "+1 617 242 0026",
    "sg:postcode": "02129",
    "sg:province": "MA",
    "sg:tags": [
      "director"
    ],
    "wof:name": "Murphy \u0026 Turnbull",
    "wof:placetype": "venue"
  },
  "geometry": {"coordinates":[-71.068604,42.38192],"type":"Point"}
}
