{
  "type": "Feature",
  "properties": {
    "iso:country":"US",
    "sg:address":"322 Bunker Hill St",
    "sg:city":"Charlestown",
    "sg:classifiers":[
        {
            "category":"Retail",
            "subcategory":"Funeral Services",
            "type":"Services"
        }
    ],
    "sg:phone":"+1 617 242 0026",
    "sg:postcode":"02129",
    "sg:province":"MA",
    "sg:tags":[
        "director"
    ],
    "wof:name":"Murphy & Turnbull",
    "wof:placetype":"venue"
},
  "geometry": {"coordinates":[-71.06860399999999,42.38192],"type":"Point"}
}