{
  "type": "Feature",
  "properties": {
    "addr:full": "63 Prospect St Northampton MA 01060",
    "addr:housenumber": "63",
    "addr:postcode": "01060",
    "addr:street": "Prospect St",
    "iso:country": "US",
    "sg:address": "63 Prospect St",
    "sg:city": "Northampton",
    "sg:classifiers": [
      {
        "category": "Retail",
        "subcategory": "Auto Repair",
        "type": "Services"
      }
    ],
    "sg:phone": "+1 413 584 5356",
    "sg:postcode": "01060",
    "sg:province": "MA",
    "sg:tags": [
      "body",
      "automobile",
      "painting"
    ],
    "wof:name": "James E Clayton Jr Dent",
    "wof:placetype": "venue"
  },
  "geometry": {"coordinates":[-72.636055,42.323082],"type":"Point"}
}
