{
  "type": "Feature",
  "properties": {
    "iso:country":"US",
    "sg:address":"775 Main St",
    "sg:city":"Melrose",
    "sg:classifiers":[
        {
            "category":"Health Services",
            "subcategory":"Doctor",
            "type":"Services"
        }
    ],
    "sg:phone":"+1 781 599 0220",
    "sg:postcode":"02176",
    "sg:province":"MA",
    "sg:tags":[
        "physician",
        "surgeon",
        "urology",
        "surgeons"
    ],
    "wof:name":"John J Bucchiere Jr",
    "wof:placetype":"venue"
},
  "geometry": {"coordinates":[-71.062157,42.461281],"type":"Point"}
}