{
  "type": "Feature",
  "properties": {
    "addr:full": "124 School St West Dennis MA 02670",
    "addr:housenumber": "124",
    "addr:postcode": "02670",
    "addr:street": "School St",
    "iso:country": "US",
    "sg:address": "124 School St",
    "sg:city": "West Dennis",
    "sg:classifiers": [
      {
        "category": "Professional",
        "subcategory": "Advertising",
        "type": "Services"
      }
    ],
    "sg:phone": "+1 508 394 1101",
    "sg:postcode": "02670",
    "sg:province": "MA",
    "sg:tags": [
      "mail"
    ],
    "wof:name": "Val-Pak Of Cape Cod",
    "wof:placetype": "venue"
  },
  "geometry": {"coordinates":[-70.169274,41.660243],"type":"Point"}
}
