{
  "type": "Feature",
  "properties": {
    "iso:country":"US",
    "sg:address":"75 Riverdale St",
    "sg:city":"Methuen",
    "sg:classifiers":[
        {
            "category":"Health Services",
            "subcategory":"Doctor",
            "type":"Services"
        }
    ],
    "sg:phone":"+1 978 687 2290",
    "sg:postcode":"01844",
    "sg:province":"MA",
    "sg:tags":[
        "dentist"
    ],
    "wof:name":"Massachusetts Dental Hygenists",
    "wof:placetype":"venue"
},
  "geometry": {"coordinates":[-71.13314800000001,42.731873],"type":"Point"}
}