{
  "type": "Feature",
  "properties": {
    "iso:country":"US",
    "sg:address":"12 Mystic View Rd",
    "sg:city":"Everett",
    "sg:classifiers":[
        {
            "category":"Shopping",
            "subcategory":"Baby Store",
            "type":"Retail Goods"
        },
        {
            "category":"Shopping",
            "subcategory":"Hobbies, Toys, & Games",
            "type":"Retail Goods"
        },
        {
            "category":"Home & Garden",
            "subcategory":"Home Furnishings",
            "type":"Retail Goods"
        },
        {
            "category":"Shopping",
            "type":"Retail Goods"
        }
    ],
    "sg:phone":"+1 617 381 1897",
    "sg:postcode":"02149",
    "sg:province":"MA",
    "sg:tags":[
        "infant",
        "toy",
        "accessories",
        "furniture-children's",
        "children's",
        "wear"
    ],
    "sg:website":"http://Babiesrus.com",
    "wof:name":"Babies R Us",
    "wof:placetype":"venue"
},
  "geometry": {"coordinates":[-71.071198,42.400902],"type":"Point"}
}