{
  "type": "Feature",
  "properties": {
    "addr:full": "490 Kirchner Rd Dalton MA 01226",
    "addr:housenumber": "490",
    "addr:postcode": "01226",
    "addr:street": "Kirchner Rd",
    "iso:country": "US",
    "sg:address": "490 Kirchner Rd",
    "sg:city": "Dalton",
    "sg:classifiers": [
      {
        "category": "Professional",
        "subcategory": "Secretarial Services",
        "type": "Services"
      }
    ],
    "sg:phone": "+1 413 443 5329",
    "sg:postcode": "01226",
    "sg:province": "MA",
    "sg:tags": [
      "reporting"
    ],
    "wof:name": "Berkshire Court Reporting",
    "wof:placetype": "venue"
  },
  "geometry": {"coordinates":[-73.190953,42.427363],"type":"Point"}
}
