{
  "type": "Feature",
  "properties": {
    "iso:country":"US",
    "sg:address":"490 Kirchner Rd",
    "sg:city":"Dalton",
    "sg:classifiers":[
        {
            "category":"Professional",
            "subcategory":"Secretarial Services",
            "type":"Services"
        }
    ],
    "sg:phone":"+1 413 443 5329",
    "sg:postcode":"01226",
    "sg:province":"MA",
    "sg:tags":[
        "reporting"
    ],
    "wof:name":"Berkshire Court Reporting",
    "wof:placetype":"venue"
},
  "geometry": {"coordinates":[-73.19095299999999,42.427363],"type":"Point"}
}