{
  "type": "Feature",
  "properties": {
    "iso:country":"US",
    "sg:address":"75 Providence Hwy",
    "sg:city":"Norwood",
    "sg:classifiers":[
        {
            "category":"Shopping",
            "type":"Retail Goods"
        }
    ],
    "sg:phone":"+1 781 356 8161",
    "sg:postcode":"02062",
    "sg:province":"MA",
    "sg:tags":[
        "religious"
    ],
    "wof:name":"M J Curley Co",
    "wof:placetype":"venue"
},
  "geometry": {"coordinates":[-71.184561,42.209562],"type":"Point"}
}