{
  "type": "Feature",
  "properties": {
    "addr:full": "107 Elm St Pittsfield MA 01201",
    "addr:housenumber": "107",
    "addr:postcode": "01201",
    "addr:street": "Elm St",
    "iso:country": "US",
    "sg:address": "107 Elm St",
    "sg:city": "Pittsfield",
    "sg:classifiers": [
      {
        "category": "Shopping",
        "subcategory": "Jewelry",
        "type": "Retail Goods"
      }
    ],
    "sg:phone": "+1 413 442 1588",
    "sg:postcode": "01201",
    "sg:province": "MA",
    "sg:tags": [
      "jeweler"
    ],
    "wof:name": "Nelson's Inc",
    "wof:placetype": "venue"
  },
  "geometry": {"coordinates":[-73.241937,42.44439],"type":"Point"}
}
