{
  "type": "Feature",
  "properties": {
    "iso:country":"US",
    "sg:address":"35 Nagog Park",
    "sg:city":"Acton",
    "sg:classifiers":[
        {
            "category":"Wholesale",
            "subcategory":"Electrical",
            "type":"Manufacturing & Wholesale Goods"
        }
    ],
    "sg:phone":"+1 978 929 9098",
    "sg:postcode":"01720",
    "sg:province":"MA",
    "sg:tags":[
        "equipment",
        "electric"
    ],
    "wof:name":"Appian Communications Inc",
    "wof:placetype":"venue"
},
  "geometry": {"coordinates":[-71.43067499999999,42.525434],"type":"Point"}
}