{
  "type": "Feature",
  "properties": {
    "addr:full": "35 Nagog Park Acton MA 01720",
    "addr:housenumber": "35",
    "addr:postcode": "01720",
    "addr:street": "Nagog Park",
    "iso:country": "US",
    "sg:address": "35 Nagog Park",
    "sg:city": "Acton",
    "sg:classifiers": [
      {
        "category": "Wholesale",
        "subcategory": "Electrical",
        "type": "Manufacturing \u0026 Wholesale Goods"
      }
    ],
    "sg:phone": "+1 978 929 9098",
    "sg:postcode": "01720",
    "sg:province": "MA",
    "sg:tags": [
      "equipment",
      "electric"
    ],
    "wof:name": "Appian Communications Inc",
    "wof:placetype": "venue"
  },
  "geometry": {"coordinates":[-71.430675,42.525434],"type":"Point"}
}
