{
  "type": "Feature",
  "properties": {
    "addr:full": "3010 Main St Barnstable MA 02630",
    "addr:housenumber": "3010",
    "addr:postcode": "02630",
    "addr:street": "Main St",
    "iso:country": "US",
    "sg:address": "3010 Main St",
    "sg:city": "Barnstable",
    "sg:classifiers": [
      {
        "category": "Professional",
        "subcategory": "Lawyer \u0026 Legal Services",
        "type": "Services"
      }
    ],
    "sg:phone": "+1 508 375 9093",
    "sg:postcode": "02630",
    "sg:province": "MA",
    "wof:name": "Joyce Mary S",
    "wof:placetype": "venue"
  },
  "geometry": {"coordinates":[-70.3095,41.705],"type":"Point"}
}
