{
  "type": "Feature",
  "properties": {
    "iso:country":"US",
    "sg:address":"175 Highland Ave",
    "sg:city":"Needham",
    "sg:classifiers":[
        {
            "category":"Real Estate",
            "subcategory":"Real Estate Agent",
            "type":"Services"
        }
    ],
    "sg:phone":"+1 781 449 8020",
    "sg:postcode":"02494",
    "sg:province":"MA",
    "wof:name":"WATERFORD Group",
    "wof:placetype":"venue"
},
  "geometry": {"coordinates":[-71.21994599999999,42.304734],"type":"Point"}
}