{
  "type": "Feature",
  "properties": {
    "addr:full": "1815 Massachusetts Ave Ste P3 Cambridge MA 02140",
    "addr:housenumber": "1815",
    "addr:postcode": "02140",
    "addr:street": "Massachusetts Ave Ste P3",
    "iso:country": "US",
    "sg:address": "1815 Massachusetts Ave Ste P3",
    "sg:city": "Cambridge",
    "sg:classifiers": [
      {
        "category": "Shopping",
        "subcategory": "Books",
        "type": "Retail Goods"
      }
    ],
    "sg:phone": "+1 617 349 3698",
    "sg:postcode": "02140",
    "sg:province": "MA",
    "sg:tags": [
      "bookstore"
    ],
    "sg:website": "www.barnesandnoble.com",
    "wof:name": "Barnes \u0026 Noble",
    "wof:placetype": "venue"
  },
  "geometry": {"coordinates":[-71.11891,42.38717],"type":"Point"}
}
