{
  "type": "Feature",
  "properties": {
    "iso:country":"US",
    "sg:address":"34 North St",
    "sg:city":"Somerville",
    "sg:classifiers":[
        {
            "category":"Retail",
            "subcategory":"Laundry & Dry Cleaning",
            "type":"Services"
        }
    ],
    "sg:phone":"+1   ",
    "sg:postcode":"02144",
    "sg:province":"MA",
    "wof:name":"Santanas Carpetery Company",
    "wof:placetype":"venue"
},
  "geometry": {"coordinates":[-71.130653,42.406794],"type":"Point"}
}