{
  "type": "Feature",
  "properties": {
    "addr:full": "138 Belchertown Rd Amherst MA 01002",
    "addr:housenumber": "138",
    "addr:postcode": "01002",
    "addr:street": "Belchertown Rd",
    "iso:country": "US",
    "sg:address": "138 Belchertown Rd",
    "sg:city": "Amherst",
    "sg:classifiers": [
      {
        "category": "Restaurant",
        "type": "Food \u0026 Drink"
      }
    ],
    "sg:phone": "+1   ",
    "sg:postcode": "01002",
    "sg:province": "MA",
    "sg:tags": [
      "eating"
    ],
    "wof:name": "Maplewood Farms \u0026 Restaurant",
    "wof:placetype": "venue"
  },
  "geometry": {"coordinates":[-72.492502,42.366436],"type":"Point"}
}
