{
  "type": "Feature",
  "properties": {
    "addr:full": "739 Neponset St Norwood MA 02062",
    "addr:housenumber": "739",
    "addr:postcode": "02062",
    "addr:street": "Neponset St",
    "iso:country": "US",
    "sg:address": "739 Neponset St",
    "sg:city": "Norwood",
    "sg:classifiers": [
      {
        "category": "Real Estate",
        "subcategory": "Real Estate Services",
        "type": "Services"
      },
      {
        "category": "Building \u0026 Trades",
        "subcategory": "Cleaning \u0026 Sanitation",
        "type": "Services"
      }
    ],
    "sg:phone": "+1 617 943 8100",
    "sg:postcode": "02062",
    "sg:province": "MA",
    "sg:tags": [
      "maintenance",
      "cleaners-interior"
    ],
    "wof:name": "All Property Maintenance",
    "wof:placetype": "venue"
  },
  "geometry": {"coordinates":[-71.181618,42.181992],"type":"Point"}
}
