{
  "type": "Feature",
  "properties": {
    "addr:full":"25 Barquentine Dr Plymouth MA 02360",
    "addr:housenumber":"25",
    "addr:postcode":"02360",
    "addr:street":"Barquentine Dr",
    "iso:country":"US",
    "sg:address":"25 Barquentine Dr",
    "sg:city":"Plymouth",
    "sg:classifiers":[
        {
            "category":"Retail",
            "subcategory":"Auto Repair",
            "type":"Services"
        }
    ],
    "sg:phone":"+1 508 224 6514",
    "sg:postcode":"02360",
    "sg:province":"MA",
    "sg:tags":[
        "transmission"
    ],
    "wof:name":"All Pro Transmissions Inc",
    "wof:placetype":"venue"
},
  "geometry": {"coordinates":[-70.537092,41.879144],"type":"Point"}
}