{
  "type": "Feature",
  "properties": {
    "addr:full": "117 Elm St Somerville MA 02144",
    "addr:housenumber": "117",
    "addr:postcode": "02144",
    "addr:street": "Elm St",
    "iso:country": "US",
    "sg:address": "117 Elm St",
    "sg:city": "Somerville",
    "sg:classifiers": [
      {
        "category": "Health Services",
        "subcategory": "Health Practitioner",
        "type": "Services"
      }
    ],
    "sg:phone": "+1 617 776 2020",
    "sg:postcode": "02144",
    "sg:province": "MA",
    "sg:tags": [
      "acupuncture"
    ],
    "sg:website": "www.acupuncturealternativecare.com",
    "wof:name": "Acupuncture Alternative Care",
    "wof:placetype": "venue"
  },
  "geometry": {"coordinates":[-71.11743,42.390318],"type":"Point"}
}
