{
  "type": "Feature",
  "properties": {
    "addr:full": "47 Central St Norwood MA 02062",
    "addr:housenumber": "47",
    "addr:postcode": "02062",
    "addr:street": "Central St",
    "iso:country": "US",
    "sg:address": "47 Central St",
    "sg:city": "Norwood",
    "sg:classifiers": [
      {
        "category": "Health Services",
        "subcategory": "Dentist",
        "type": "Services"
      }
    ],
    "sg:phone": "+1 781 769 3566",
    "sg:postcode": "02062",
    "sg:province": "MA",
    "wof:name": "Giesecke Wm P Dent",
    "wof:placetype": "venue"
  },
  "geometry": {"coordinates":[-71.201202,42.191299],"type":"Point"}
}
