{
  "type": "Feature",
  "properties": {
    "iso:country":"US",
    "sg:address":"1 Fleetcenter Pl",
    "sg:city":"Boston",
    "sg:classifiers":[
        {
            "category":"Communications",
            "type":"Services"
        }
    ],
    "sg:phone":"+1 617 366 0084",
    "sg:postcode":"02114",
    "sg:province":"MA",
    "sg:tags":[
        "equipment",
        "satellite",
        "system"
    ],
    "wof:name":"Sirius Xm Radio, Inc.",
    "wof:placetype":"venue"
},
  "geometry": {"coordinates":[-71.06073000000001,42.365795],"type":"Point"}
}