{
  "type": "Feature",
  "properties": {
    "iso:country":"US",
    "sg:address":"13 Hamilton St",
    "sg:city":"New Bedford",
    "sg:classifiers":[
        {
            "category":"Professional",
            "subcategory":"Engineering",
            "type":"Services"
        }
    ],
    "sg:phone":"+1 508 992 6300",
    "sg:postcode":"02740",
    "sg:province":"MA",
    "sg:tags":[
        "engineer"
    ],
    "wof:name":"Atlantic Environmental Techs",
    "wof:placetype":"venue"
},
  "geometry": {"coordinates":[-70.92209200000001,41.635702],"type":"Point"}
}