{
  "type": "Feature",
  "properties": {
    "iso:country":"US",
    "sg:address":"200 Otis St",
    "sg:city":"Northborough",
    "sg:classifiers":[
        {
            "category":"Education",
            "subcategory":"Junior College",
            "type":"Public Place"
        }
    ],
    "sg:phone":"+1 508 393 0514",
    "sg:postcode":"01532",
    "sg:province":"MA",
    "sg:tags":[
        "technical",
        "institute"
    ],
    "wof:name":"H & R Block Tax Svc",
    "wof:placetype":"venue"
},
  "geometry": {"coordinates":[-71.65576799999999,42.289221],"type":"Point"}
}