{
  "type": "Feature",
  "properties": {
    "addr:full": "296 Salem Street Medford MA 02155",
    "addr:housenumber": "296",
    "addr:postcode": "02155",
    "addr:street": "Salem Street",
    "iso:country": "US",
    "sg:address": "296 Salem Street",
    "sg:city": "Medford",
    "sg:classifiers": [
      {
        "category": "Shopping",
        "subcategory": "Computers \u0026 Home Electronics",
        "type": "Retail Goods"
      }
    ],
    "sg:phone": "+1 781 395 9050",
    "sg:postcode": "02155",
    "sg:province": "MA",
    "wof:name": "East Coast Electronics Company",
    "wof:placetype": "venue"
  },
  "geometry": {"coordinates":[-71.097396,42.421268],"type":"Point"}
}
