{
  "type": "Feature",
  "properties": {
    "addr:full": "65 Newton St Somerville MA 02143",
    "addr:housenumber": "65",
    "addr:postcode": "02143",
    "addr:street": "Newton St",
    "iso:country": "US",
    "sg:address": "65 Newton St",
    "sg:city": "Somerville",
    "sg:classifiers": [
      {
        "category": "Shopping",
        "subcategory": "Catalog Store",
        "type": "Retail Goods"
      }
    ],
    "sg:phone": "+1   ",
    "sg:postcode": "02143",
    "sg:province": "MA",
    "sg:tags": [
      "merchandise",
      "general"
    ],
    "wof:name": "Hafi Trading \u0026 Industry Inc",
    "wof:placetype": "venue"
  },
  "geometry": {"coordinates":[-71.09676,42.37752],"type":"Point"}
}
