{
  "type": "Feature",
  "properties": {
    "addr:full": "398 Main St Medford MA 02155",
    "addr:housenumber": "398",
    "addr:postcode": "02155",
    "addr:street": "Main St",
    "iso:country": "US",
    "sg:address": "398 Main St",
    "sg:city": "Medford",
    "sg:classifiers": [
      {
        "category": "Food \u0026 Beverages",
        "subcategory": "Candy",
        "type": "Retail Goods"
      }
    ],
    "sg:phone": "+1 781 395 3535",
    "sg:postcode": "02155",
    "sg:province": "MA",
    "sg:tags": [
      "confectionery"
    ],
    "wof:name": "Sweeties Candy",
    "wof:placetype": "venue"
  },
  "geometry": {"coordinates":[-71.107554,42.404471],"type":"Point"}
}
