{
  "type": "Feature",
  "properties": {
    "iso:country":"US",
    "sg:address":"398 Main St",
    "sg:city":"Medford",
    "sg:classifiers":[
        {
            "category":"Food & Beverages",
            "subcategory":"Candy",
            "type":"Retail Goods"
        }
    ],
    "sg:phone":"+1 781 395 3535",
    "sg:postcode":"02155",
    "sg:province":"MA",
    "sg:tags":[
        "confectionery"
    ],
    "wof:name":"Sweeties Candy",
    "wof:placetype":"venue"
},
  "geometry": {"coordinates":[-71.10755399999999,42.404471],"type":"Point"}
}