{
  "type": "Feature",
  "properties": {
    "addr:full":"201 South St Boston MA 02111",
    "addr:housenumber":"201",
    "addr:postcode":"02111",
    "addr:street":"South St",
    "iso:country":"US",
    "sg:address":"201 South St",
    "sg:city":"Boston",
    "sg:phone":"+1 617 482 4340",
    "sg:postcode":"02111",
    "sg:province":"MA",
    "sg:tags":[
        "partition"
    ],
    "wof:name":"AMF Specialties",
    "wof:placetype":"venue"
},
  "geometry": {"coordinates":[-71.057652,42.349976],"type":"Point"}
}