{
  "type": "Feature",
  "properties": {
    "iso:country":"US",
    "sg:address":"1 Cross Rd",
    "sg:city":"Billerica",
    "sg:classifiers":[
        {
            "category":"Organizations",
            "subcategory":"Religious Organization",
            "type":"Services"
        }
    ],
    "sg:phone":"+1 978 663 8816",
    "sg:postcode":"01821",
    "sg:province":"MA",
    "sg:tags":[
        "church"
    ],
    "wof:name":"St Theresas Catholic Church",
    "wof:placetype":"venue"
},
  "geometry": {"coordinates":[-71.22314799999999,42.527473],"type":"Point"}
}