{
  "type": "Feature",
  "properties": {
    "addr:full": "47 Newcastle Rd Brighton MA 02135",
    "addr:housenumber": "47",
    "addr:postcode": "02135",
    "addr:street": "Newcastle Rd",
    "iso:country": "US",
    "sg:address": "47 Newcastle Rd",
    "sg:city": "Brighton",
    "sg:classifiers": [
      {
        "category": "Professional",
        "type": "Services"
      }
    ],
    "sg:phone": "+1   ",
    "sg:postcode": "02135",
    "sg:province": "MA",
    "wof:name": "Aj Sonbin \u0026 Sons",
    "wof:placetype": "venue"
  },
  "geometry": {"coordinates":[-71.160957,42.353889],"type":"Point"}
}
