{
  "type": "Feature",
  "properties": {
    "iso:country":"US",
    "sg:address":"47 Newcastle Rd",
    "sg:city":"Brighton",
    "sg:classifiers":[
        {
            "category":"Professional",
            "type":"Services"
        }
    ],
    "sg:phone":"+1   ",
    "sg:postcode":"02135",
    "sg:province":"MA",
    "wof:name":"Aj Sonbin & Sons",
    "wof:placetype":"venue"
},
  "geometry": {"coordinates":[-71.160957,42.353889],"type":"Point"}
}