{
  "type": "Feature",
  "properties": {
    "iso:country":"US",
    "sg:address":"550 Summer St",
    "sg:city":"Weymouth",
    "sg:classifiers":[
        {
            "category":"Professional",
            "type":"Services"
        }
    ],
    "sg:phone":"+1   ",
    "sg:postcode":"02188",
    "sg:province":"MA",
    "wof:name":"New England Net Systems",
    "wof:placetype":"venue"
},
  "geometry": {"coordinates":[-70.970652,42.195312],"type":"Point"}
}