{
  "type": "Feature",
  "properties": {
    "addr:full": "425 Summer St Boston MA 02210",
    "addr:housenumber": "425",
    "addr:postcode": "02210",
    "addr:street": "Summer St",
    "iso:country": "US",
    "sg:address": "425 Summer St",
    "sg:city": "Boston",
    "sg:classifiers": [
      {
        "category": "Banks \u0026 Credit Unions",
        "subcategory": "Bureau De Change",
        "type": "Services"
      },
      {
        "category": "Professional",
        "subcategory": "Printing \u0026 Photocopies",
        "type": "Services"
      }
    ],
    "sg:phone": "+1 617 756 7127",
    "sg:postcode": "02210",
    "sg:province": "MA",
    "sg:tags": [
      "form",
      "card",
      "business",
      "printers-business"
    ],
    "wof:name": "J' Printing \u0026 Computers",
    "wof:placetype": "venue"
  },
  "geometry": {"coordinates":[-71.043465,42.346984],"type":"Point"}
}
