{
  "type": "Feature",
  "properties": {
    "iso:country":"US",
    "sg:address":"432 Mechanic St",
    "sg:city":"Fitchburg",
    "sg:classifiers":[
        {
            "category":"Restaurant",
            "type":"Food & Drink"
        }
    ],
    "sg:phone":"+1 978 342 9383",
    "sg:postcode":"01420",
    "sg:province":"MA",
    "wof:name":"Castleway Pizza",
    "wof:placetype":"venue"
},
  "geometry": {"coordinates":[-71.80212899999999,42.5991],"type":"Point"}
}