{
  "type": "Feature",
  "properties": {
    "iso:country":"US",
    "sg:address":"179 Boylston St",
    "sg:city":"Jamaica Plain",
    "sg:classifiers":[
        {
            "category":"Professional",
            "subcategory":"Management & Consulting",
            "type":"Services"
        }
    ],
    "sg:phone":"+1 617 524 1400",
    "sg:postcode":"02130",
    "sg:province":"MA",
    "sg:tags":[
        "international",
        "consultant"
    ],
    "sg:website":"www.grassrootsonline.org",
    "wof:name":"Grassroots International",
    "wof:placetype":"venue"
},
  "geometry": {"coordinates":[-71.102508,42.315526],"type":"Point"}
}