{
  "type": "Feature",
  "properties": {
    "iso:country":"US",
    "sg:address":"157 Elm St",
    "sg:city":"Marblehead",
    "sg:classifiers":[
        {
            "category":"Shopping",
            "subcategory":"Pets & Pet Supplies",
            "type":"Retail Goods"
        }
    ],
    "sg:phone":"+1 781 631 3500",
    "sg:postcode":"01945",
    "sg:province":"MA",
    "sg:tags":[
        "store"
    ],
    "wof:name":"Marblehead Pet Supply",
    "wof:placetype":"venue"
},
  "geometry": {"coordinates":[-70.856324,42.503713],"type":"Point"}
}