{
  "type": "Feature",
  "properties": {
    "addr:full": "8 Vulcan St Gloucester MA 01930",
    "addr:housenumber": "8",
    "addr:postcode": "01930",
    "addr:street": "Vulcan St",
    "iso:country": "US",
    "ovtr:label": "Lanesville Community Center, 8 Vulcan St Gloucester MA US",
    "ovtr:similarity": 3.752074956893921,
    "sg:address": "8 Vulcan St",
    "sg:city": "Gloucester",
    "sg:classifiers": [
      {
        "category": "Community Center",
        "type": "Public Place"
      }
    ],
    "sg:phone": "+1 978 381 9522",
    "sg:postcode": "01930",
    "sg:province": "MA",
    "sg:tags": [
      "recreation"
    ],
    "wof:name": "Lanesville Community Center, Inc.",
    "wof:placetype": "venue"
  },
  "geometry": {"coordinates":[-70.653817,42.677094],"type":"Point"}
}
