{
  "type": "Feature",
  "properties": {
    "addr:full": "241 Dartmouth St Boston MA 02116",
    "addr:housenumber": "241",
    "addr:postcode": "02116",
    "addr:street": "Dartmouth St",
    "iso:country": "US",
    "sg:address": "241 Dartmouth St",
    "sg:city": "Boston",
    "sg:classifiers": [
      {
        "category": "Building \u0026 Trades",
        "subcategory": "Locksmith",
        "type": "Services"
      }
    ],
    "sg:phone": "+1 617 895 3490",
    "sg:postcode": "02116",
    "sg:province": "MA",
    "sg:tags": [
      "key"
    ],
    "wof:name": "24 Hours A Locksmith",
    "wof:placetype": "venue"
  },
  "geometry": {"coordinates":[-71.077012,42.349856],"type":"Point"}
}
