{
  "type": "Feature",
  "properties": {
    "addr:full":"61 Industrial Ln Agawam MA 01001",
    "addr:housenumber":"61",
    "addr:postcode":"01001",
    "addr:street":"Industrial Ln",
    "iso:country":"US",
    "sg:address":"61 Industrial Ln",
    "sg:city":"Agawam",
    "sg:classifiers":[
        {
            "category":"Manufacturing",
            "subcategory":"Tools & Machinery",
            "type":"Manufacturing & Wholesale Goods"
        }
    ],
    "sg:phone":"+1 413 786 0252",
    "sg:postcode":"01001",
    "sg:province":"MA",
    "sg:tags":[
        "machine",
        "shop"
    ],
    "wof:name":"Wayne Industries Inc",
    "wof:placetype":"venue"
},
  "geometry": {"coordinates":[-72.646423,42.043858],"type":"Point"}
}