{
  "type": "Feature",
  "properties": {
    "addr:full": "34 Chandler Ave Walpole MA 02081",
    "addr:housenumber": "34",
    "addr:postcode": "02081",
    "addr:street": "Chandler Ave",
    "iso:country": "US",
    "sg:address": "34 Chandler Ave",
    "sg:city": "Walpole",
    "sg:classifiers": [
      {
        "category": "Food \u0026 Beverages",
        "subcategory": "Groceries \u0026 Convenience Stores",
        "type": "Retail Goods"
      }
    ],
    "sg:phone": "+1 508 528 0677",
    "sg:postcode": "02081",
    "sg:province": "MA",
    "wof:name": "Lindas' Variety",
    "wof:placetype": "venue"
  },
  "geometry": {"coordinates":[-71.282591,42.133172],"type":"Point"}
}
