{
  "type": "Feature",
  "properties": {
    "iso:country":"US",
    "sg:address":"34 Chandler Ave",
    "sg:city":"Walpole",
    "sg:classifiers":[
        {
            "category":"Food & Beverages",
            "subcategory":"Groceries & Convenience Stores",
            "type":"Retail Goods"
        }
    ],
    "sg:phone":"+1 508 528 0677",
    "sg:postcode":"02081",
    "sg:province":"MA",
    "wof:name":"Lindas' Variety",
    "wof:placetype":"venue"
},
  "geometry": {"coordinates":[-71.282591,42.133172],"type":"Point"}
}