{
  "type": "Feature",
  "properties": {
    "iso:country":"US",
    "sg:address":"12 Sunnyside Ave",
    "sg:city":"Rutland",
    "sg:classifiers":[
        {
            "category":"Building & Trades",
            "subcategory":"Construction",
            "type":"Services"
        }
    ],
    "sg:phone":"+1 508 886 2969",
    "sg:postcode":"01543",
    "sg:province":"MA",
    "sg:tags":[
        "product",
        "asphalt"
    ],
    "wof:name":"Wachusett Sealcoat",
    "wof:placetype":"venue"
},
  "geometry": {"coordinates":[-71.951442,42.375978],"type":"Point"}
}