{
  "type": "Feature",
  "properties": {
    "iso:country":"US",
    "sg:address":"117 Grove St",
    "sg:city":"Lexington",
    "sg:classifiers":[
        {
            "category":"Building & Trades",
            "subcategory":"Locksmith",
            "type":"Services"
        }
    ],
    "sg:phone":"+1 781 301 6005",
    "sg:postcode":"02420",
    "sg:province":"MA",
    "sg:tags":[
        "key"
    ],
    "wof:name":"AAA Locksmith Service",
    "wof:placetype":"venue"
},
  "geometry": {"coordinates":[-71.239244,42.476325],"type":"Point"}
}