{
  "type": "Feature",
  "properties": {
    "addr:full": "113 E Bare Hill Rd Harvard MA 01451",
    "addr:housenumber": "113",
    "addr:postcode": "01451",
    "addr:street": "E Bare Hill Rd",
    "iso:country": "US",
    "sg:address": "113 E Bare Hill Rd",
    "sg:city": "Harvard",
    "sg:classifiers": [
      {
        "category": "Professional",
        "subcategory": "Lawyer \u0026 Legal Services",
        "type": "Services"
      }
    ],
    "sg:phone": "+1   ",
    "sg:postcode": "01451",
    "sg:province": "MA",
    "wof:name": "Dahlstrom Christophr M Law Off",
    "wof:placetype": "venue"
  },
  "geometry": {"coordinates":[-71.584139,42.470181],"type":"Point"}
}
