{
  "type": "Feature",
  "properties": {
    "addr:full": "256 College Hwy Southwick MA 01077",
    "addr:housenumber": "256",
    "addr:postcode": "01077",
    "addr:street": "College Hwy",
    "iso:country": "US",
    "ovtr:label": "Southwick Acres Campground, 256 College Hwy Southwick MA US",
    "ovtr:similarity": 3.9145750999450684,
    "sg:address": "256 College Hwy",
    "sg:city": "Southwick",
    "sg:classifiers": [
      {
        "category": "Recreation",
        "subcategory": "Campground",
        "type": "Entertainment"
      }
    ],
    "sg:phone": "+1 413 569 6339",
    "sg:postcode": "01077",
    "sg:province": "MA",
    "sg:tags": [
      "recreational",
      "park",
      "vehicle"
    ],
    "sg:website": "http://www.southwickacres.com",
    "wof:name": "Southwick Acres Campgrounds",
    "wof:placetype": "venue"
  },
  "geometry": {"coordinates":[-72.784907,42.032066],"type":"Point"}
}
