{
  "type": "Feature",
  "properties": {
    "iso:country":"US",
    "sg:address":"9 Ward St",
    "sg:city":"Somerville",
    "sg:classifiers":[
        {
            "category":"Organizations",
            "subcategory":"Professional Association",
            "type":"Services"
        }
    ],
    "sg:phone":"+1 617 354 9035",
    "sg:postcode":"02143",
    "sg:province":"MA",
    "wof:name":"Columbus Associates",
    "wof:placetype":"venue"
},
  "geometry": {"coordinates":[-71.08892,42.3748],"type":"Point"}
}