{
  "type": "Feature",
  "properties": {
    "addr:full": "129 Long Meadow Rd Belmont MA 02478",
    "addr:housenumber": "129",
    "addr:postcode": "02478",
    "addr:street": "Long Meadow Rd",
    "iso:country": "US",
    "sg:address": "129 Long Meadow Rd",
    "sg:city": "Belmont",
    "sg:classifiers": [
      {
        "category": "Local Transit",
        "type": "Transportation"
      }
    ],
    "sg:phone": "+1 617 484 4457",
    "sg:postcode": "02478",
    "sg:province": "MA",
    "sg:tags": [
      "limousine"
    ],
    "wof:name": "Boston Executive Coach",
    "wof:placetype": "venue"
  },
  "geometry": {"coordinates":[-71.193056,42.411016],"type":"Point"}
}
