{
  "type": "Feature",
  "properties": {
    "iso:country":"US",
    "sg:address":"1135 Tremont St",
    "sg:city":"Roxbury Crossing",
    "sg:classifiers":[
        {
            "category":"Real Estate",
            "subcategory":"Real Estate Agent",
            "type":"Services"
        }
    ],
    "sg:phone":"+1 617 266 9290",
    "sg:postcode":"02120",
    "sg:province":"MA",
    "sg:tags":[
        "management"
    ],
    "wof:name":"Finard & Co",
    "wof:placetype":"venue"
},
  "geometry": {"coordinates":[-71.08741499999999,42.335616],"type":"Point"}
}