{
  "type": "Feature",
  "properties": {
    "addr:full":"70 Beach Rd Salisbury MA 01952",
    "addr:housenumber":"70",
    "addr:postcode":"01952",
    "addr:street":"Beach Rd",
    "iso:country":"US",
    "sg:address":"70 Beach Rd",
    "sg:city":"Salisbury",
    "sg:classifiers":[
        {
            "category":"Building & Trades",
            "subcategory":"Construction",
            "type":"Services"
        }
    ],
    "sg:phone":"+1 781 985 2023",
    "sg:postcode":"01952",
    "sg:province":"MA",
    "sg:tags":[
        "painting",
        "contractor"
    ],
    "wof:name":"All Under One Roof",
    "wof:placetype":"venue"
},
  "geometry": {"coordinates":[-70.848724,42.838884],"type":"Point"}
}