{
  "type": "Feature",
  "properties": {
    "addr:full":"2 Canton St Stoughton MA 02072",
    "addr:housenumber":"2",
    "addr:postcode":"02072",
    "addr:street":"Canton St",
    "iso:country":"US",
    "sg:address":"2 Canton St",
    "sg:city":"Stoughton",
    "sg:classifiers":[
        {
            "category":"Real Estate",
            "subcategory":"Real Estate Services",
            "type":"Services"
        }
    ],
    "sg:phone":"+1 781 344 1755",
    "sg:postcode":"02072",
    "sg:province":"MA",
    "wof:name":"Pride Real Estate - CLOSED",
    "wof:placetype":"venue"
},
  "geometry": {"coordinates":[-71.104202,42.124599],"type":"Point"}
}