{
  "type": "Feature",
  "properties": {
    "iso:country":"US",
    "sg:address":"238 Spruce St",
    "sg:city":"Chelsea",
    "sg:classifiers":[
        {
            "category":"Retail",
            "subcategory":"Repair Shop",
            "type":"Services"
        }
    ],
    "sg:phone":"+1 617 884 8877",
    "sg:postcode":"02150",
    "sg:province":"MA",
    "sg:tags":[
        "scooter",
        "motorcycle",
        "motor"
    ],
    "wof:name":"G P Motor Cycle Supply",
    "wof:placetype":"venue"
},
  "geometry": {"coordinates":[-71.036304,42.397059],"type":"Point"}
}