{
  "type": "Feature",
  "properties": {
    "iso:country":"US",
    "sg:address":"88 North St",
    "sg:city":"Mattapoisett",
    "sg:classifiers":[
        {
            "category":"Restaurant",
            "type":"Food & Drink"
        }
    ],
    "sg:phone":"+1 508 758 4540",
    "sg:postcode":"02739",
    "sg:province":"MA",
    "sg:tags":[
        "shop",
        "coffee"
    ],
    "wof:name":"Uncle John's Java House",
    "wof:placetype":"venue"
},
  "geometry": {"coordinates":[-70.818473,41.672434],"type":"Point"}
}