{
  "type": "Feature",
  "properties": {
    "iso:country":"US",
    "sg:address":"465 N Main St",
    "sg:city":"West Bridgewater",
    "sg:classifiers":[
        {
            "category":"Shopping",
            "subcategory":"Florist",
            "type":"Retail Goods"
        }
    ],
    "sg:phone":"+1 508 588 6622",
    "sg:postcode":"02379",
    "sg:province":"MA",
    "wof:name":"Ultimate Florist",
    "wof:placetype":"venue"
},
  "geometry": {"coordinates":[-71.00890099999999,42.032953],"type":"Point"}
}