{
  "type": "Feature",
  "properties": {
    "addr:full": "465 N Main St West Bridgewater MA 02379",
    "addr:housenumber": "465",
    "addr:postcode": "02379",
    "addr:street": "N Main St",
    "iso:country": "US",
    "sg:address": "465 N Main St",
    "sg:city": "West Bridgewater",
    "sg:classifiers": [
      {
        "category": "Shopping",
        "subcategory": "Florist",
        "type": "Retail Goods"
      }
    ],
    "sg:phone": "+1 508 588 6622",
    "sg:postcode": "02379",
    "sg:province": "MA",
    "wof:name": "Ultimate Florist",
    "wof:placetype": "venue"
  },
  "geometry": {"coordinates":[-71.008901,42.032953],"type":"Point"}
}
