{
  "type": "Feature",
  "properties": {
    "iso:country":"US",
    "sg:address":"73 W Cedar St",
    "sg:city":"Boston",
    "sg:classifiers":[
        {
            "category":"Health Services",
            "subcategory":"Clinic",
            "type":"Services"
        }
    ],
    "sg:phone":"+1 617 872 5192",
    "sg:postcode":"02114",
    "sg:province":"MA",
    "sg:tags":[
        "welfare"
    ],
    "wof:name":"Ez Homecare Of Boston, Inc.",
    "wof:placetype":"venue"
},
  "geometry": {"coordinates":[-71.070026,42.360093],"type":"Point"}
}