{
  "type": "Feature",
  "properties": {
    "iso:country":"US",
    "sg:address":"237 Putnam Ave",
    "sg:city":"Cambridge",
    "sg:classifiers":[
        {
            "category":"Wholesale",
            "subcategory":"Durable Goods & Equipment",
            "type":"Manufacturing & Wholesale Goods"
        }
    ],
    "sg:phone":"+1 617 868 4330",
    "sg:postcode":"02139",
    "sg:province":"MA",
    "sg:tags":[
        "instrument",
        "scientific",
        "apparatus"
    ],
    "wof:name":"Digilab Inc",
    "wof:placetype":"venue"
},
  "geometry": {"coordinates":[-71.113936,42.364348],"type":"Point"}
}