{
  "type": "Feature",
  "properties": {
    "addr:full":"397 Great Plain Ave Needham MA 02492",
    "addr:housenumber":"397",
    "addr:postcode":"02492",
    "addr:street":"Great Plain Ave",
    "iso:country":"US",
    "sg:address":"397 Great Plain Ave",
    "sg:city":"Needham",
    "sg:classifiers":[
        {
            "category":"Retail",
            "subcategory":"Laundry & Dry Cleaning",
            "type":"Services"
        }
    ],
    "sg:phone":"+1 781 444 0030",
    "sg:postcode":"02492",
    "sg:province":"MA",
    "sg:tags":[
        "cleaners"
    ],
    "wof:name":"Mall Cleaners",
    "wof:placetype":"venue"
},
  "geometry": {"coordinates":[-71.21616,42.276587],"type":"Point"}
}