{
  "type": "Feature",
  "properties": {
    "iso:country":"US",
    "sg:address":"5 Melville Rd",
    "sg:city":"South Yarmouth",
    "sg:classifiers":[
        {
            "category":"Professional",
            "subcategory":"Research",
            "type":"Services"
        }
    ],
    "sg:phone":"+1   ",
    "sg:postcode":"02664",
    "sg:province":"MA",
    "sg:tags":[
        "technician",
        "biological"
    ],
    "wof:name":"Sean M Lucey",
    "wof:placetype":"venue"
},
  "geometry": {"coordinates":[-70.180733,41.687162],"type":"Point"}
}