{
  "type": "Feature",
  "properties": {
    "addr:full": "118 Main St Watertown MA 02472",
    "addr:housenumber": "118",
    "addr:postcode": "02472",
    "addr:street": "Main St",
    "iso:country": "US",
    "sg:address": "118 Main St",
    "sg:city": "Watertown",
    "sg:classifiers": [
      {
        "category": "Building \u0026 Trades",
        "subcategory": "Equipment Rental",
        "type": "Services"
      }
    ],
    "sg:phone": "+1 617 923 2020",
    "sg:postcode": "02472",
    "sg:province": "MA",
    "sg:tags": [
      "leasing"
    ],
    "wof:name": "Watertown Equipment",
    "wof:placetype": "venue"
  },
  "geometry": {"coordinates":[-71.186612,42.366825],"type":"Point"}
}
