{
  "type": "Feature",
  "properties": {
    "iso:country":"US",
    "sg:address":"149 Old Spring St",
    "sg:city":"Arlington",
    "sg:classifiers":[
        {
            "category":"Social Services",
            "subcategory":"Child Care",
            "type":"Services"
        }
    ],
    "sg:phone":"+1 781 863 2207",
    "sg:postcode":"02476",
    "sg:province":"MA",
    "wof:name":"Lexicare Children's Ctr",
    "wof:placetype":"venue"
},
  "geometry": {"coordinates":[-71.171277,42.410832],"type":"Point"}
}