{
  "type": "Feature",
  "properties": {
    "addr:full":"481 Boston Post Rd Weston MA 02493",
    "addr:housenumber":"481",
    "addr:postcode":"02493",
    "addr:street":"Boston Post Rd",
    "iso:country":"US",
    "sg:address":"481 Boston Post Rd",
    "sg:city":"Weston",
    "sg:classifiers":[
        {
            "category":"Professional",
            "subcategory":"Business Services",
            "type":"Services"
        }
    ],
    "sg:phone":"+1 781 894 3240",
    "sg:postcode":"02493",
    "sg:province":"MA",
    "sg:tags":[
        "interior",
        "consultant",
        "design",
        "decorator"
    ],
    "wof:name":"Weston Studio-Interior Design",
    "wof:placetype":"venue"
},
  "geometry": {"coordinates":[-71.303158,42.36697],"type":"Point"}
}