{
  "type": "Feature",
  "properties": {
    "addr:full":"194 Chelsea St Everett MA 02149",
    "addr:housenumber":"194",
    "addr:postcode":"02149",
    "addr:street":"Chelsea St",
    "iso:country":"US",
    "sg:address":"194 Chelsea St",
    "sg:city":"Everett",
    "sg:classifiers":[
        {
            "category":"Retail",
            "subcategory":"Laundry & Dry Cleaning",
            "type":"Services"
        },
        {
            "category":"Building & Trades",
            "subcategory":"Cleaning & Sanitation",
            "type":"Services"
        }
    ],
    "sg:phone":"+1 617 449 5892",
    "sg:postcode":"02149",
    "sg:province":"MA",
    "sg:tags":[
        "cleaner",
        "carpet",
        "rug",
        "house"
    ],
    "wof:name":"Costa Cleaning",
    "wof:placetype":"venue"
},
  "geometry": {"coordinates":[-71.047618,42.403466],"type":"Point"}
}