{
  "type": "Feature",
  "properties": {
    "addr:full": "515 Washington St Boston MA 02111",
    "addr:housenumber": "515",
    "addr:postcode": "02111",
    "addr:street": "Washington St",
    "iso:country": "US",
    "sg:address": "515 Washington St",
    "sg:city": "Boston",
    "sg:classifiers": [
      {
        "category": "Manufacturing",
        "subcategory": "Printing",
        "type": "Manufacturing \u0026 Wholesale Goods"
      }
    ],
    "sg:phone": "+1 617 426 5505",
    "sg:postcode": "02111",
    "sg:province": "MA",
    "sg:tags": [
      "publisher"
    ],
    "wof:name": "Teen Voices Magazine",
    "wof:placetype": "venue"
  },
  "geometry": {"coordinates":[-71.062281,42.353882],"type":"Point"}
}
