{
  "type": "Feature",
  "properties": {
    "iso:country":"US",
    "sg:address":"1935 Revere Beach Pkwy",
    "sg:city":"Everett",
    "sg:classifiers":[
        {
            "category":"Building & Trades",
            "subcategory":"Locksmith",
            "type":"Services"
        }
    ],
    "sg:phone":"+1 617 925 3555",
    "sg:postcode":"02149",
    "sg:province":"MA",
    "sg:tags":[
        "key"
    ],
    "wof:name":"A Emergency Locksmith",
    "wof:placetype":"venue"
},
  "geometry": {"coordinates":[-71.051388,42.403143],"type":"Point"}
}