{
  "type": "Feature",
  "properties": {
    "iso:country":"US",
    "sg:address":"1018 Lancaster St",
    "sg:city":"Leominster",
    "sg:classifiers":[
        {
            "category":"Building & Trades",
            "subcategory":"Electrical",
            "type":"Services"
        }
    ],
    "sg:phone":"+1 978 227 5165",
    "sg:postcode":"01453",
    "sg:province":"MA",
    "sg:tags":[
        "electrician"
    ],
    "wof:name":"Barton Electric Inc",
    "wof:placetype":"venue"
},
  "geometry": {"coordinates":[-71.72556,42.496793],"type":"Point"}
}