{
  "type": "Feature",
  "properties": {
    "iso:country":"US",
    "sg:address":"990 Paradise Rd",
    "sg:city":"Swampscott",
    "sg:classifiers":[
        {
            "category":"Professional",
            "subcategory":"Accounting & Tax Preparation",
            "type":"Services"
        },
        {
            "category":"Banks & Credit Unions",
            "subcategory":"Financial Services",
            "type":"Services"
        }
    ],
    "sg:phone":"+1 781 598 1411",
    "sg:postcode":"01907",
    "sg:province":"MA",
    "sg:tags":[
        "consultant",
        "planning",
        "return"
    ],
    "sg:website":"http://www.sagancpa.com",
    "wof:name":"Sagan & Company Certified Public Accountants P C",
    "wof:placetype":"venue"
},
  "geometry": {"coordinates":[-70.90033699999999,42.484099],"type":"Point"}
}