{
  "type": "Feature",
  "properties": {
    "addr:full": "990 Paradise Rd Swampscott MA 01907",
    "addr:housenumber": "990",
    "addr:postcode": "01907",
    "addr:street": "Paradise Rd",
    "iso:country": "US",
    "sg:address": "990 Paradise Rd",
    "sg:city": "Swampscott",
    "sg:classifiers": [
      {
        "category": "Professional",
        "subcategory": "Accounting \u0026 Tax Preparation",
        "type": "Services"
      },
      {
        "category": "Banks \u0026 Credit Unions",
        "subcategory": "Financial Services",
        "type": "Services"
      }
    ],
    "sg:phone": "+1 781 598 1411",
    "sg:postcode": "01907",
    "sg:province": "MA",
    "sg:tags": [
      "consultant",
      "planning",
      "return"
    ],
    "sg:website": "http://www.sagancpa.com",
    "wof:name": "Sagan \u0026 Company Certified Public Accountants P C",
    "wof:placetype": "venue"
  },
  "geometry": {"coordinates":[-70.900337,42.484099],"type":"Point"}
}
