{
  "type": "Feature",
  "properties": {
    "addr:full": "34 Southwest Park Westwood MA 02090",
    "addr:housenumber": "34",
    "addr:postcode": "02090",
    "addr:street": "Southwest Park",
    "iso:country": "US",
    "sg:address": "34 Southwest Park",
    "sg:city": "Westwood",
    "sg:classifiers": [
      {
        "category": "Professional",
        "subcategory": "Accounting \u0026 Tax Preparation",
        "type": "Services"
      }
    ],
    "sg:phone": "+1 781 407 0300",
    "sg:postcode": "02090",
    "sg:province": "MA",
    "sg:tags": [
      "accountant"
    ],
    "wof:name": "Gray Gray \u0026 Gray",
    "wof:placetype": "venue"
  },
  "geometry": {"coordinates":[-71.181375,42.224644],"type":"Point"}
}
