{
  "type": "Feature",
  "properties": {
    "addr:full": "100 Talcott Avenue Watertown MA 02472",
    "addr:housenumber": "100",
    "addr:postcode": "02472",
    "addr:street": "Talcott Avenue",
    "iso:country": "US",
    "sg:address": "100 Talcott Avenue",
    "sg:city": "Watertown",
    "sg:classifiers": [
      {
        "category": "Real Estate",
        "subcategory": "Architect",
        "type": "Services"
      }
    ],
    "sg:phone": "+1 617 393 3812",
    "sg:postcode": "02472",
    "sg:province": "MA",
    "sg:website": "www.hdsarchitecture.com",
    "wof:name": "Hds Architecture",
    "wof:placetype": "venue"
  },
  "geometry": {"coordinates":[-71.1628,42.360967],"type":"Point"}
}
