{
  "type": "Feature",
  "properties": {
    "addr:full": "5 Deerfield Rd Osterville MA 02655",
    "addr:housenumber": "5",
    "addr:postcode": "02655",
    "addr:street": "Deerfield Rd",
    "iso:country": "US",
    "sg:address": "5 Deerfield Rd",
    "sg:city": "Osterville",
    "sg:classifiers": [
      {
        "category": "Shopping",
        "subcategory": "Clothing, Apparel, \u0026 Fashions",
        "type": "Retail Goods"
      }
    ],
    "sg:phone": "+1 508 420 5701",
    "sg:postcode": "02655",
    "sg:province": "MA",
    "sg:tags": [
      "item",
      "boutique"
    ],
    "wof:name": "Claire's Inc",
    "wof:placetype": "venue"
  },
  "geometry": {"coordinates":[-70.369773,41.638644],"type":"Point"}
}
