{
  "type": "Feature",
  "properties": {
    "iso:country":"US",
    "sg:address":"133 Old Rd To 9 Acre Cor",
    "sg:city":"Concord",
    "sg:classifiers":[
        {
            "category":"Health Services",
            "subcategory":"Doctor",
            "type":"Services"
        }
    ],
    "sg:phone":"+1 978 287 3355",
    "sg:postcode":"01742",
    "sg:province":"MA",
    "sg:tags":[
        "physician",
        "surgeon"
    ],
    "wof:name":"Emerson Pathology Assoc",
    "wof:placetype":"venue"
},
  "geometry": {"coordinates":[-71.37766999999999,42.452026],"type":"Point"}
}