{
  "type": "Feature",
  "properties": {
    "addr:full":"1244 Boylston St Chestnut Hill MA 02467",
    "addr:housenumber":"1244",
    "addr:postcode":"02467",
    "addr:street":"Boylston St",
    "iso:country":"US",
    "sg:address":"1244 Boylston St",
    "sg:city":"Chestnut Hill",
    "sg:classifiers":[
        {
            "category":"Manufacturing",
            "subcategory":"Printing",
            "type":"Manufacturing & Wholesale Goods"
        }
    ],
    "sg:phone":"+1 617 731 8800",
    "sg:postcode":"02467",
    "sg:province":"MA",
    "sg:tags":[
        "printer"
    ],
    "wof:name":"Fed Ex Kinko's Ofc & Print Ctr",
    "wof:placetype":"venue"
},
  "geometry": {"coordinates":[-71.165751,42.323048],"type":"Point"}
}