{
  "type": "Feature",
  "properties": {
    "addr:full":"93 Lawson Ter Scituate MA 02066",
    "addr:housenumber":"93",
    "addr:postcode":"02066",
    "addr:street":"Lawson Ter",
    "iso:country":"US",
    "sg:address":"93 Lawson Ter",
    "sg:city":"Scituate",
    "sg:classifiers":[
        {
            "category":"Professional",
            "type":"Services"
        }
    ],
    "sg:phone":"+1   ",
    "sg:postcode":"02066",
    "sg:province":"MA",
    "wof:name":"Richard W & Jane E Lane",
    "wof:placetype":"venue"
},
  "geometry": {"coordinates":[-70.75363299999999,42.205253],"type":"Point"}
}