{
  "type": "Feature",
  "properties": {
    "addr:full": "58 Salem St Lawrence MA 01843",
    "addr:housenumber": "58",
    "addr:postcode": "01843",
    "addr:street": "Salem St",
    "iso:country": "US",
    "sg:address": "58 Salem St",
    "sg:city": "Lawrence",
    "sg:classifiers": [
      {
        "category": "Banks \u0026 Credit Unions",
        "subcategory": "Bank",
        "type": "Services"
      }
    ],
    "sg:phone": "+1 978 691 1111",
    "sg:postcode": "01843",
    "sg:province": "MA",
    "sg:tags": [
      "loan",
      "real estate"
    ],
    "wof:name": "LMS Mortgage Reduction Svc",
    "wof:placetype": "venue"
  },
  "geometry": {"coordinates":[-71.150899,42.699254],"type":"Point"}
}
