{
  "type": "Feature",
  "properties": {
    "addr:full":"156 N Harvard St Allston MA 02134",
    "addr:housenumber":"156",
    "addr:postcode":"02134",
    "addr:street":"N Harvard St",
    "iso:country":"US",
    "sg:address":"156 N Harvard St",
    "sg:city":"Allston",
    "sg:classifiers":[
        {
            "category":"Retail",
            "subcategory":"Repair Shop",
            "type":"Services"
        }
    ],
    "sg:phone":"+1 617 783 4828",
    "sg:postcode":"02134",
    "sg:province":"MA",
    "sg:tags":[
        "electrical"
    ],
    "wof:name":"Franklin Appliance",
    "wof:placetype":"venue"
},
  "geometry": {"coordinates":[-71.12839200000001,42.364243],"type":"Point"}
}