{
  "type": "Feature",
  "properties": {
    "iso:country":"US",
    "sg:address":"1568 Commonwealth Ave",
    "sg:city":"Brighton",
    "sg:classifiers":[
        {
            "category":"Real Estate",
            "subcategory":"Real Estate Operator",
            "type":"Services"
        }
    ],
    "sg:phone":"+1 617 731 1960",
    "sg:postcode":"02135",
    "sg:province":"MA",
    "sg:tags":[
        "condominium"
    ],
    "wof:name":"Washington Square Condominiums",
    "wof:placetype":"venue"
},
  "geometry": {"coordinates":[-71.142411,42.343993],"type":"Point"}
}