{
  "type": "Feature",
  "properties": {
    "addr:full": "435 Northampton St Holyoke MA 01040",
    "addr:housenumber": "435",
    "addr:postcode": "01040",
    "addr:street": "Northampton St",
    "iso:country": "US",
    "sg:address": "435 Northampton St",
    "sg:city": "Holyoke",
    "sg:classifiers": [
      {
        "category": "Retail",
        "subcategory": "Veterinary Services",
        "type": "Services"
      }
    ],
    "sg:phone": "+1 413 533 7387",
    "sg:postcode": "01040",
    "sg:province": "MA",
    "sg:tags": [
      "veterinarian"
    ],
    "wof:name": "Little Mountain Animal Hosp",
    "wof:placetype": "venue"
  },
  "geometry": {"coordinates":[-72.623658,42.242025],"type":"Point"}
}
