{
  "type": "Feature",
  "properties": {
    "addr:full": "68 S Branch Pkwy Springfield MA 01118",
    "addr:housenumber": "68",
    "addr:postcode": "01118",
    "addr:street": "S Branch Pkwy",
    "iso:country": "US",
    "sg:address": "68 S Branch Pkwy",
    "sg:city": "Springfield",
    "sg:classifiers": [
      {
        "category": "Food \u0026 Beverages",
        "subcategory": "Liquor \u0026 Beverages",
        "type": "Retail Goods"
      }
    ],
    "sg:phone": "+1   ",
    "sg:postcode": "01118",
    "sg:province": "MA",
    "sg:tags": [
      "alcoholic"
    ],
    "wof:name": "Janleeco Limited",
    "wof:placetype": "venue"
  },
  "geometry": {"coordinates":[-72.535767,42.103275],"type":"Point"}
}
