{
  "type": "Feature",
  "properties": {
    "addr:full": "486 Main St Hyannis MA 02601",
    "addr:housenumber": "486",
    "addr:postcode": "02601",
    "addr:street": "Main St",
    "iso:country": "US",
    "sg:address": "486 Main St",
    "sg:city": "Hyannis",
    "sg:classifiers": [
      {
        "category": "Organizations",
        "subcategory": "Religious Organization",
        "type": "Services"
      }
    ],
    "sg:phone": "+1 508 775 1846",
    "sg:postcode": "02601",
    "sg:province": "MA",
    "sg:tags": [
      "church"
    ],
    "wof:name": "First Baptist Church",
    "wof:placetype": "venue"
  },
  "geometry": {"coordinates":[-70.287369,41.651167],"type":"Point"}
}
