{
  "type": "Feature",
  "properties": {
    "addr:full": "1645 Falmouth Rd Centerville MA 02632",
    "addr:housenumber": "1645",
    "addr:postcode": "02632",
    "addr:street": "Falmouth Rd",
    "iso:country": "US",
    "sg:address": "1645 Falmouth Rd",
    "sg:city": "Centerville",
    "sg:classifiers": [
      {
        "category": "Insurance",
        "subcategory": "Insurance Agent",
        "type": "Services"
      }
    ],
    "sg:phone": "+1 508 775 7595",
    "sg:postcode": "02632",
    "sg:province": "MA",
    "wof:name": "William L Hebenstreit",
    "wof:placetype": "venue"
  },
  "geometry": {"coordinates":[-70.347887,41.656938],"type":"Point"}
}
