{
  "type": "Feature",
  "properties": {
    "addr:full": "93 Maxwell Rd Monson MA 01057",
    "addr:housenumber": "93",
    "addr:postcode": "01057",
    "addr:street": "Maxwell Rd",
    "iso:country": "US",
    "sg:address": "93 Maxwell Rd",
    "sg:city": "Monson",
    "sg:classifiers": [
      {
        "category": "Building \u0026 Trades",
        "subcategory": "Construction",
        "type": "Services"
      }
    ],
    "sg:phone": "+1 413 289 1434",
    "sg:postcode": "01057",
    "sg:province": "MA",
    "sg:tags": [
      "excavating",
      "contractor"
    ],
    "wof:name": "Tom Gregoire Excavation",
    "wof:placetype": "venue"
  },
  "geometry": {"coordinates":[-72.368615,42.146287],"type":"Point"}
}
