{
  "type": "Feature",
  "properties": {
    "iso:country":"US",
    "sg:address":"93 Maxwell Rd",
    "sg:city":"Monson",
    "sg:classifiers":[
        {
            "category":"Building & Trades",
            "subcategory":"Construction",
            "type":"Services"
        }
    ],
    "sg:phone":"+1 413 289 1434",
    "sg:postcode":"01057",
    "sg:province":"MA",
    "sg:tags":[
        "excavating",
        "contractor"
    ],
    "wof:name":"Tom Gregoire Excavation",
    "wof:placetype":"venue"
},
  "geometry": {"coordinates":[-72.36861500000001,42.146287],"type":"Point"}
}