{
  "type": "Feature",
  "properties": {
    "iso:country":"US",
    "sg:address":"36 Timberedge Rd",
    "sg:city":"Stow",
    "sg:classifiers":[
        {
            "category":"Retail",
            "subcategory":"Auto Repair",
            "type":"Services"
        }
    ],
    "sg:phone":"+1 978 263 3111",
    "sg:postcode":"01775",
    "sg:province":"MA",
    "sg:tags":[
        "repairing",
        "automobile",
        "part",
        "radiator",
        "supply"
    ],
    "wof:name":"Colonial Automotive Inc",
    "wof:placetype":"venue"
},
  "geometry": {"coordinates":[-71.501541,42.42289],"type":"Point"}
}