{
  "type": "Feature",
  "properties": {
    "iso:country":"US",
    "sg:address":"2 Going Rd",
    "sg:city":"Shirley",
    "sg:classifiers":[
        {
            "category":"Real Estate",
            "subcategory":"Developer",
            "type":"Services"
        }
    ],
    "sg:phone":"+1 978 425 0100",
    "sg:postcode":"01464",
    "sg:province":"MA",
    "wof:name":"Going Development Corp",
    "wof:placetype":"venue"
},
  "geometry": {"coordinates":[-71.661461,42.58839],"type":"Point"}
}