{
  "type": "Feature",
  "properties": {
    "iso:country":"US",
    "sg:address":"400 Commonwealth Ave",
    "sg:city":"Boston",
    "sg:classifiers":[
        {
            "category":"Health Services",
            "subcategory":"Dentist",
            "type":"Services"
        }
    ],
    "sg:phone":"+1 617 536 4620",
    "sg:postcode":"02215",
    "sg:province":"MA",
    "wof:name":"Varnerin Richard J Dent",
    "wof:placetype":"venue"
},
  "geometry": {"coordinates":[-71.0895,42.3489],"type":"Point"}
}