{
  "type": "Feature",
  "properties": {
    "addr:full":"247 Locke Rd Ashby MA 01431",
    "addr:housenumber":"247",
    "addr:postcode":"01431",
    "addr:street":"Locke Rd",
    "iso:country":"US",
    "sg:address":"247 Locke Rd",
    "sg:city":"Ashby",
    "sg:classifiers":[
        {
            "category":"Social Services",
            "subcategory":"Child Care",
            "type":"Services"
        }
    ],
    "sg:phone":"+1 978 386 5647",
    "sg:postcode":"01431",
    "sg:province":"MA",
    "wof:name":"Children's Garden Nursery Schl",
    "wof:placetype":"venue"
},
  "geometry": {"coordinates":[-71.789534,42.699508],"type":"Point"}
}