{
  "type": "Feature",
  "properties": {
    "iso:country":"US",
    "sg:address":"640 Main St",
    "sg:city":"Shrewsbury",
    "sg:classifiers":[
        {
            "category":"Recreation",
            "type":"Entertainment"
        }
    ],
    "sg:phone":"+1 508 842 9507",
    "sg:postcode":"01545",
    "sg:province":"MA",
    "sg:tags":[
        "hall",
        "auditorium"
    ],
    "wof:name":"St Mary's Church Hall",
    "wof:placetype":"venue"
},
  "geometry": {"coordinates":[-71.710695,42.296507],"type":"Point"}
}