{
  "type": "Feature",
  "properties": {
    "iso:country":"US",
    "sg:address":"11 Wing Rd",
    "sg:city":"Wilmington",
    "sg:classifiers":[
        {
            "category":"Professional",
            "subcategory":"Advertising",
            "type":"Services"
        }
    ],
    "sg:phone":"+1   ",
    "sg:postcode":"01887",
    "sg:province":"MA",
    "wof:name":"Das Advertising/Marketing",
    "wof:placetype":"venue"
},
  "geometry": {"coordinates":[-71.150419,42.548347],"type":"Point"}
}