{
  "type": "Feature",
  "properties": {
    "iso:country":"US",
    "sg:address":"46 Old Colony Rd",
    "sg:city":"Weston",
    "sg:classifiers":[
        {
            "category":"Professional",
            "subcategory":"Business Services",
            "type":"Services"
        }
    ],
    "sg:phone":"+1 781 235 6343",
    "sg:postcode":"02493",
    "sg:province":"MA",
    "wof:name":"Steven Drysdale Consultants",
    "wof:placetype":"venue"
},
  "geometry": {"coordinates":[-71.28048099999999,42.326593],"type":"Point"}
}