{
  "type": "Feature",
  "properties": {
    "iso:country":"US",
    "sg:address":"214 Lunenburg St",
    "sg:city":"Fitchburg",
    "sg:classifiers":[
        {
            "category":"Home & Garden",
            "subcategory":"Home Furnishings",
            "type":"Retail Goods"
        }
    ],
    "sg:phone":"+1 978 342 6988",
    "sg:postcode":"01420",
    "sg:province":"MA",
    "sg:tags":[
        "equipment",
        "electrical"
    ],
    "sg:website":"www.thelampcenter.com",
    "wof:name":"Lamp Center",
    "wof:placetype":"venue"
},
  "geometry": {"coordinates":[-71.779188,42.585627],"type":"Point"}
}