{
  "type": "Feature",
  "properties": {
    "addr:full": "17 Spring St Cohasset MA 02025",
    "addr:housenumber": "17",
    "addr:postcode": "02025",
    "addr:street": "Spring St",
    "iso:country": "US",
    "sg:address": "17 Spring St",
    "sg:city": "Cohasset",
    "sg:classifiers": [
      {
        "category": "Retail",
        "subcategory": "Repair Shop",
        "type": "Services"
      }
    ],
    "sg:phone": "+1   ",
    "sg:postcode": "02025",
    "sg:province": "MA",
    "wof:name": "Buttmans Marine Repair",
    "wof:placetype": "venue"
  },
  "geometry": {"coordinates":[-70.800677,42.237576],"type":"Point"}
}
