{
  "type": "Feature",
  "properties": {
    "addr:full":"362 Green St Gardner MA 01440",
    "addr:housenumber":"362",
    "addr:postcode":"01440",
    "addr:street":"Green St",
    "iso:country":"US",
    "sg:address":"362 Green St",
    "sg:city":"Gardner",
    "sg:classifiers":[
        {
            "category":"Communications",
            "subcategory":"Radio Station",
            "type":"Services"
        }
    ],
    "sg:phone":"+1 978 630 4488",
    "sg:postcode":"01440",
    "sg:province":"MA",
    "sg:tags":[
        "company",
        "broadcasting"
    ],
    "wof:name":"WXRV 92.5 FM The River Bus",
    "wof:placetype":"venue"
},
  "geometry": {"coordinates":[-71.986833,42.59059],"type":"Point"}
}