{
  "type": "Feature",
  "properties": {
    "addr:full":"108 Newbury St Boston MA 02116",
    "addr:housenumber":"108",
    "addr:postcode":"02116",
    "addr:street":"Newbury St",
    "iso:country":"US",
    "sg:address":"108 Newbury St",
    "sg:city":"Boston",
    "sg:classifiers":[
        {
            "category":"Coffee & Tea",
            "type":"Food & Drink"
        }
    ],
    "sg:menulink":"http://www.allmenus.com/ma/boston/2437-tealuxe/menu/",
    "sg:phone":"+1 617 927 0400",
    "sg:postcode":"02116",
    "sg:province":"MA",
    "sg:tags":[
        "american"
    ],
    "wof:name":"Tealuxe",
    "wof:placetype":"venue"
},
  "geometry": {"coordinates":[-71.075737,42.351431],"type":"Point"}
}