{
  "type": "Feature",
  "properties": {
    "iso:country":"US",
    "sg:address":"88 Lowell St",
    "sg:city":"Methuen",
    "sg:classifiers":[
        {
            "category":"Shopping",
            "subcategory":"Hobbies, Toys, & Games",
            "type":"Retail Goods"
        }
    ],
    "sg:phone":"+1 978 683 0885",
    "sg:postcode":"01844",
    "sg:province":"MA",
    "sg:website":"www.modelersjunction.com",
    "wof:name":"Modelers Junction",
    "wof:placetype":"venue"
},
  "geometry": {"coordinates":[-71.194029,42.722702],"type":"Point"}
}