{
  "type": "Feature",
  "properties": {
    "iso:country":"US",
    "sg:address":"583 E Columbus Ave",
    "sg:city":"Springfield",
    "sg:classifiers":[
        {
            "category":"Utilities",
            "subcategory":"Telephone",
            "type":"Services"
        }
    ],
    "sg:phone":"+1 413 781 8400",
    "sg:postcode":"01105",
    "sg:province":"MA",
    "sg:tags":[
        "company"
    ],
    "wof:name":"CTC Communications Corp",
    "wof:placetype":"venue"
},
  "geometry": {"coordinates":[-72.581475,42.090815],"type":"Point"}
}