{
  "type": "Feature",
  "properties": {
    "iso:country":"US",
    "sg:address":"1662 Falmouth Rd",
    "sg:city":"Centerville",
    "sg:classifiers":[
        {
            "category":"Health Services",
            "subcategory":"Optometrist",
            "type":"Services"
        }
    ],
    "sg:phone":"+1 508 771 1900",
    "sg:postcode":"02632",
    "sg:province":"MA",
    "wof:name":"Dowling Optical",
    "wof:placetype":"venue"
},
  "geometry": {"coordinates":[-70.350601,41.657001],"type":"Point"}
}