{
  "type": "Feature",
  "properties": {
    "addr:full":"111 Willard Rd Brookline MA 02445",
    "addr:housenumber":"111",
    "addr:postcode":"02445",
    "addr:street":"Willard Rd",
    "iso:country":"US",
    "sg:address":"111 Willard Rd",
    "sg:city":"Brookline",
    "sg:classifiers":[
        {
            "category":"Government",
            "subcategory":"Court House",
            "type":"Public Place"
        }
    ],
    "sg:phone":"+1 617 731 3338",
    "sg:postcode":"02445",
    "sg:province":"MA",
    "sg:tags":[
        "justice",
        "peace"
    ],
    "wof:name":"Phyllis F Blotner",
    "wof:placetype":"venue"
},
  "geometry": {"coordinates":[-71.150096,42.33185],"type":"Point"}
}