{
  "type": "Feature",
  "properties": {
    "addr:full": "1 Boston Pl Boston MA 02108",
    "addr:housenumber": "1",
    "addr:postcode": "02108",
    "addr:street": "Boston Pl",
    "iso:country": "US",
    "sg:address": "1 Boston Pl",
    "sg:city": "Boston",
    "sg:classifiers": [
      {
        "category": "Banks \u0026 Credit Unions",
        "subcategory": "Financial Services",
        "type": "Services"
      }
    ],
    "sg:phone": "+1 617 624 8300",
    "sg:postcode": "02108",
    "sg:province": "MA",
    "sg:tags": [
      "loan"
    ],
    "wof:name": "Crossharbor Capital Partners",
    "wof:placetype": "venue"
  },
  "geometry": {"coordinates":[-71.058044,42.358955],"type":"Point"}
}
