{
  "type": "Feature",
  "properties": {
    "iso:country":"US",
    "sg:address":"245 S Main St",
    "sg:city":"Attleboro",
    "sg:classifiers":[
        {
            "category":"Education",
            "subcategory":"Kindergarten",
            "type":"Public Place"
        }
    ],
    "sg:phone":"+1 508 222 7755",
    "sg:postcode":"02703",
    "sg:province":"MA",
    "sg:tags":[
        "school",
        "driving"
    ],
    "wof:name":"Drivers Choice Driving School",
    "wof:placetype":"venue"
},
  "geometry": {"coordinates":[-71.285027,41.933529],"type":"Point"}
}