{
  "type": "Feature",
  "properties": {
    "iso:country":"US",
    "sg:address":"47 W Elm St",
    "sg:city":"Brockton",
    "sg:classifiers":[
        {
            "category":"Shopping",
            "subcategory":"Gifts & Souvenirs",
            "type":"Retail Goods"
        }
    ],
    "sg:phone":"+1 508 580 0150",
    "sg:postcode":"02301",
    "sg:province":"MA",
    "sg:tags":[
        "shop"
    ],
    "wof:name":"Ebonique Gift Packages",
    "wof:placetype":"venue"
},
  "geometry": {"coordinates":[-71.022774,42.082215],"type":"Point"}
}