{
  "type": "Feature",
  "properties": {
    "addr:full": "955 Massachusetts Avenue Suite 500 Cambridge MA 02139",
    "addr:housenumber": "955",
    "addr:postcode": "02139",
    "addr:street": "Massachusetts Avenue Suite 500",
    "iso:country": "US",
    "sg:address": "955 Massachusetts Avenue Suite 500",
    "sg:city": "Cambridge",
    "sg:classifiers": [
      {
        "category": "Sports \u0026 Exercise",
        "subcategory": "Gym",
        "type": "Entertainment"
      }
    ],
    "sg:phone": "+1 617 876 2556",
    "sg:postcode": "02139",
    "sg:province": "MA",
    "sg:tags": [
      "trainer"
    ],
    "wof:name": "North Charles Foundation",
    "wof:placetype": "venue"
  },
  "geometry": {"coordinates":[-71.110399,42.369051],"type":"Point"}
}
