{
  "type": "Feature",
  "properties": {
    "iso:country":"US",
    "sg:address":"70 Princeton St",
    "sg:city":"North Chelmsford",
    "sg:classifiers":[
        {
            "category":"Recreation",
            "type":"Entertainment"
        }
    ],
    "sg:phone":"+1 978 251 3933",
    "sg:postcode":"01863",
    "sg:province":"MA",
    "sg:tags":[
        "instruction",
        "golf"
    ],
    "wof:name":"Bill Pappas Golf School",
    "wof:placetype":"venue"
},
  "geometry": {"coordinates":[-71.379803,42.636303],"type":"Point"}
}