{
  "type": "Feature",
  "properties": {
    "addr:full":"265 Lincoln Ave Winchendon MA 01475",
    "addr:housenumber":"265",
    "addr:postcode":"01475",
    "addr:street":"Lincoln Ave",
    "iso:country":"US",
    "sg:address":"265 Lincoln Ave",
    "sg:city":"Winchendon",
    "sg:classifiers":[
        {
            "category":"Building & Trades",
            "subcategory":"Landscaping Services",
            "type":"Services"
        }
    ],
    "sg:phone":"+1 978 297 0370",
    "sg:postcode":"01475",
    "sg:province":"MA",
    "sg:tags":[
        "landscape",
        "gardener",
        "contractor"
    ],
    "wof:name":"Plantscape Services",
    "wof:placetype":"venue"
},
  "geometry": {"coordinates":[-72.04967000000001,42.691508],"type":"Point"}
}