{
  "type": "Feature",
  "properties": {
    "iso:country":"US",
    "sg:address":"533 North Rd",
    "sg:city":"Westfield",
    "sg:classifiers":[
        {
            "category":"Education",
            "subcategory":"School",
            "type":"Public Place"
        }
    ],
    "sg:phone":"+1 413 562 9500",
    "sg:postcode":"01085",
    "sg:province":"MA",
    "wof:name":"White Oak School",
    "wof:placetype":"venue"
},
  "geometry": {"coordinates":[-72.72896,42.183388],"type":"Point"}
}