{
  "type": "Feature",
  "properties": {
    "iso:country":"US",
    "sg:address":"114 Mount Auburn St",
    "sg:city":"Cambridge",
    "sg:classifiers":[
        {
            "category":"Education",
            "subcategory":"Special Training",
            "type":"Public Place"
        }
    ],
    "sg:phone":"+1 617 491 0637",
    "sg:postcode":"02138",
    "sg:province":"MA",
    "sg:tags":[
        "school",
        "language"
    ],
    "wof:name":"Accel Inc",
    "wof:placetype":"venue"
},
  "geometry": {"coordinates":[-71.12143399999999,42.372851],"type":"Point"}
}