{
  "type": "Feature",
  "properties": {
    "addr:full": "454 College Hwy Southwick MA 01077",
    "addr:housenumber": "454",
    "addr:postcode": "01077",
    "addr:street": "College Hwy",
    "iso:country": "US",
    "sg:address": "454 College Hwy",
    "sg:city": "Southwick",
    "sg:classifiers": [
      {
        "category": "Organizations",
        "subcategory": "Community Association",
        "type": "Services"
      }
    ],
    "sg:phone": "+1 413 569 5498",
    "sg:postcode": "01077",
    "sg:province": "MA",
    "sg:tags": [
      "club"
    ],
    "wof:name": "Southwick Council On Aging",
    "wof:placetype": "venue"
  },
  "geometry": {"coordinates":[-72.772874,42.052507],"type":"Point"}
}
