{
  "type": "Feature",
  "properties": {
    "addr:full":"49 Hancock St Cambridge MA 02139",
    "addr:housenumber":"49",
    "addr:postcode":"02139",
    "addr:street":"Hancock St",
    "iso:country":"US",
    "sg:address":"49 Hancock St",
    "sg:city":"Cambridge",
    "sg:classifiers":[
        {
            "category":"Social Services",
            "type":"Services"
        }
    ],
    "sg:phone":"+1 617 868 7685",
    "sg:postcode":"02139",
    "sg:province":"MA",
    "sg:tags":[
        "counselor",
        "marriage",
        "family"
    ],
    "wof:name":"Mutlicultural Psychotherapy",
    "wof:placetype":"venue"
},
  "geometry": {"coordinates":[-71.109082,42.368128],"type":"Point"}
}