{
  "type": "Feature",
  "properties": {
    "iso:country":"US",
    "sg:address":"42 Bay Ridge Ln",
    "sg:city":"Orleans",
    "sg:classifiers":[
        {
            "category":"Retail",
            "subcategory":"Auto Repair",
            "type":"Services"
        }
    ],
    "sg:phone":"+1 508 240 5709",
    "sg:postcode":"02653",
    "sg:province":"MA",
    "wof:name":"Marshall",
    "wof:placetype":"venue"
},
  "geometry": {"coordinates":[-70.00671699999999,41.779835],"type":"Point"}
}