{
  "type": "Feature",
  "properties": {
    "iso:country":"US",
    "sg:address":"68 Mill Rd",
    "sg:city":"Brimfield",
    "sg:classifiers":[
        {
            "category":"Manufacturing",
            "subcategory":"Tools & Machinery",
            "type":"Manufacturing & Wholesale Goods"
        }
    ],
    "sg:phone":"+1 413 245 7144",
    "sg:postcode":"01010",
    "sg:province":"MA",
    "sg:tags":[
        "orthopedic"
    ],
    "wof:name":"Accellent Inc",
    "wof:placetype":"venue"
},
  "geometry": {"coordinates":[-72.205535,42.115711],"type":"Point"}
}