{
  "type": "Feature",
  "properties": {
    "addr:full": "68 Mill Rd Brimfield MA 01010",
    "addr:housenumber": "68",
    "addr:postcode": "01010",
    "addr:street": "Mill Rd",
    "iso:country": "US",
    "sg:address": "68 Mill Rd",
    "sg:city": "Brimfield",
    "sg:classifiers": [
      {
        "category": "Manufacturing",
        "subcategory": "Tools \u0026 Machinery",
        "type": "Manufacturing \u0026 Wholesale Goods"
      }
    ],
    "sg:phone": "+1 413 245 7144",
    "sg:postcode": "01010",
    "sg:province": "MA",
    "sg:tags": [
      "orthopedic"
    ],
    "wof:name": "Accellent Inc",
    "wof:placetype": "venue"
  },
  "geometry": {"coordinates":[-72.205535,42.115711],"type":"Point"}
}
