{
  "type": "Feature",
  "properties": {
    "iso:country":"US",
    "sg:address":"56 Westland Ave",
    "sg:city":"Boston",
    "sg:classifiers":[
        {
            "category":"Food & Beverages",
            "subcategory":"Groceries & Convenience Stores",
            "type":"Retail Goods"
        }
    ],
    "sg:phone":"+1 617 262 6947",
    "sg:postcode":"02115",
    "sg:province":"MA",
    "sg:tags":[
        "grocer"
    ],
    "wof:name":"Westland Market",
    "wof:placetype":"venue"
},
  "geometry": {"coordinates":[-71.087597,42.343475],"type":"Point"}
}