{
  "type": "Feature",
  "properties": {
    "addr:full":"24 Vine St Everett MA 02149",
    "addr:housenumber":"24",
    "addr:postcode":"02149",
    "addr:street":"Vine St",
    "iso:country":"US",
    "sg:address":"24 Vine St",
    "sg:city":"Everett",
    "sg:classifiers":[
        {
            "category":"Building & Trades",
            "subcategory":"Locksmith",
            "type":"Services"
        }
    ],
    "sg:phone":"+1 617 420 9169",
    "sg:postcode":"02149",
    "sg:province":"MA",
    "sg:tags":[
        "key"
    ],
    "wof:name":"24 Hour Everett Emergency Locksmith A",
    "wof:placetype":"venue"
},
  "geometry": {"coordinates":[-71.047956,42.400235],"type":"Point"}
}