{
  "type": "Feature",
  "properties": {
    "iso:country":"US",
    "sg:address":"21 Pottle St",
    "sg:city":"Kingston",
    "sg:classifiers":[
        {
            "category":"Home & Garden",
            "subcategory":"Building Materials",
            "type":"Retail Goods"
        }
    ],
    "sg:phone":"+1 781 585 3745",
    "sg:postcode":"02364",
    "sg:province":"MA",
    "sg:tags":[
        "shower",
        "door",
        "enclosure"
    ],
    "wof:name":"Butterfield Glass & Aluminum",
    "wof:placetype":"venue"
},
  "geometry": {"coordinates":[-70.73693799999999,41.999703],"type":"Point"}
}