{
  "type": "Feature",
  "properties": {
    "addr:full": "21 Pottle St Kingston MA 02364",
    "addr:housenumber": "21",
    "addr:postcode": "02364",
    "addr:street": "Pottle St",
    "iso:country": "US",
    "sg:address": "21 Pottle St",
    "sg:city": "Kingston",
    "sg:classifiers": [
      {
        "category": "Home \u0026 Garden",
        "subcategory": "Building Materials",
        "type": "Retail Goods"
      }
    ],
    "sg:phone": "+1 781 585 3745",
    "sg:postcode": "02364",
    "sg:province": "MA",
    "sg:tags": [
      "shower",
      "door",
      "enclosure"
    ],
    "wof:name": "Butterfield Glass \u0026 Aluminum",
    "wof:placetype": "venue"
  },
  "geometry": {"coordinates":[-70.736938,41.999703],"type":"Point"}
}
