{
  "type": "Feature",
  "properties": {
    "addr:full":"206 Western Ave Cambridge MA 02139",
    "addr:housenumber":"206",
    "addr:postcode":"02139",
    "addr:street":"Western Ave",
    "iso:country":"US",
    "sg:address":"206 Western Ave",
    "sg:city":"Cambridge",
    "sg:classifiers":[
        {
            "category":"Retail",
            "subcategory":"Auto Repair",
            "type":"Services"
        }
    ],
    "sg:phone":"+1 617 497 7760",
    "sg:postcode":"02139",
    "sg:province":"MA",
    "sg:tags":[
        "repairing",
        "automobile"
    ],
    "wof:name":"Western Avenue Auto",
    "wof:placetype":"venue"
},
  "geometry": {"coordinates":[-71.11019899999999,42.364899],"type":"Point"}
}