{
  "type": "Feature",
  "properties": {
    "addr:full": "4 Copley St Boston MA 02170",
    "addr:housenumber": "4",
    "addr:postcode": "02170",
    "addr:street": "Copley St",
    "iso:country": "US",
    "sg:address": "4 Copley St",
    "sg:city": "Boston",
    "sg:classifiers": [
      {
        "category": "Professional",
        "subcategory": "Lawyer \u0026 Legal Services",
        "type": "Services"
      }
    ],
    "sg:phone": "+1 617 266 3500",
    "sg:postcode": "02170",
    "sg:province": "MA",
    "sg:tags": [
      "attorney"
    ],
    "wof:name": "Anthony Guadalupe",
    "wof:placetype": "venue"
  },
  "geometry": {"coordinates":[-71.00877,42.273446],"type":"Point"}
}
