{
  "type": "Feature",
  "properties": {
    "iso:country":"US",
    "sg:address":"10 Wrentham Mnr",
    "sg:city":"Bellingham",
    "sg:classifiers":[
        {
            "category":"Government",
            "subcategory":"Office",
            "type":"Public Place"
        }
    ],
    "sg:phone":"+1 508 883 4999",
    "sg:postcode":"02019",
    "sg:province":"MA",
    "sg:tags":[
        "government-united",
        "state"
    ],
    "wof:name":"Bellingham Housing Authority",
    "wof:placetype":"venue"
},
  "geometry": {"coordinates":[-71.48464800000001,42.0254],"type":"Point"}
}