{
  "type": "Feature",
  "properties": {
    "iso:country":"US",
    "sg:address":"95 Princeton St",
    "sg:city":"Springfield",
    "sg:classifiers":[
        {
            "category":"Personal",
            "subcategory":"Beauty Salon",
            "type":"Services"
        }
    ],
    "sg:phone":"+1 413 785 5602",
    "sg:postcode":"01109",
    "sg:province":"ME",
    "sg:tags":[
        "treatment",
        "skin"
    ],
    "wof:name":"Matis Paris",
    "wof:placetype":"venue"
},
  "geometry": {"coordinates":[-72.569485,42.119116],"type":"Point"}
}