{
  "type": "Feature",
  "properties": {
    "addr:full": "7 Channel St Boston MA 02210",
    "addr:housenumber": "7",
    "addr:postcode": "02210",
    "addr:street": "Channel St",
    "iso:country": "US",
    "sg:address": "7 Channel St",
    "sg:city": "Boston",
    "sg:phone": "+1 617 482 6349",
    "sg:postcode": "02210",
    "sg:province": "MA",
    "wof:name": "Stavis Seafoods, Inc.",
    "wof:placetype": "venue"
  },
  "geometry": {"coordinates":[-71.036864,42.344834],"type":"Point"}
}
