{
  "type": "Feature",
  "properties": {
    "iso:country":"US",
    "sg:address":"7 Channel St",
    "sg:city":"Boston",
    "sg:phone":"+1 617 482 6349",
    "sg:postcode":"02210",
    "sg:province":"MA",
    "wof:name":"Stavis Seafoods, Inc.",
    "wof:placetype":"venue"
},
  "geometry": {"coordinates":[-71.03686399999999,42.344834],"type":"Point"}
}