{
  "type": "Feature",
  "properties": {
    "addr:full":"124 Washington St Foxboro MA 02035",
    "addr:housenumber":"124",
    "addr:postcode":"02035",
    "addr:street":"Washington St",
    "iso:country":"US",
    "sg:address":"124 Washington St",
    "sg:city":"Foxboro",
    "sg:classifiers":[
        {
            "category":"Wholesale",
            "subcategory":"Home Furnishings",
            "type":"Manufacturing & Wholesale Goods"
        }
    ],
    "sg:phone":"+1 508 543 6555",
    "sg:postcode":"02035",
    "sg:province":"MA",
    "sg:tags":[
        "rug",
        "carpet"
    ],
    "wof:name":"Monterey Carpets Inc",
    "wof:placetype":"venue"
},
  "geometry": {"coordinates":[-71.28236,42.07933],"type":"Point"}
}