{
  "type": "Feature",
  "properties": {
    "addr:full": "176 Southville Rd Southborough MA 01772",
    "addr:housenumber": "176",
    "addr:postcode": "01772",
    "addr:street": "Southville Rd",
    "iso:country": "US",
    "sg:address": "176 Southville Rd",
    "sg:city": "Southborough",
    "sg:classifiers": [
      {
        "category": "Building \u0026 Trades",
        "subcategory": "Construction",
        "type": "Services"
      }
    ],
    "sg:phone": "+1 508 481 2411",
    "sg:postcode": "01772",
    "sg:province": "MA",
    "sg:tags": [
      "masonry",
      "contractor"
    ],
    "wof:name": "Sunrise Tree Landscape \u0026 Dsgn",
    "wof:placetype": "venue"
  },
  "geometry": {"coordinates":[-71.53743,42.266651],"type":"Point"}
}
