{
  "type": "Feature",
  "properties": {
    "addr:full": "1170 Main St West Barnstable MA 02668",
    "addr:housenumber": "1170",
    "addr:postcode": "02668",
    "addr:street": "Main St",
    "iso:country": "US",
    "sg:address": "1170 Main St",
    "sg:city": "West Barnstable",
    "sg:classifiers": [
      {
        "category": "Professional",
        "subcategory": "Computer Services",
        "type": "Services"
      }
    ],
    "sg:phone": "+1 508 362 4171",
    "sg:postcode": "02668",
    "sg:province": "MA",
    "sg:tags": [
      "repair"
    ],
    "sg:website": "www.imediatech.com",
    "wof:name": "Imedia Technology Inc",
    "wof:placetype": "venue"
  },
  "geometry": {"coordinates":[-70.361386,41.701639],"type":"Point"}
}
