{
  "type": "Feature",
  "properties": {
    "iso:country":"US",
    "sg:address":"12 Enterprise Rd",
    "sg:city":"Hyannis",
    "sg:classifiers":[
        {
            "category":"Personal",
            "type":"Services"
        }
    ],
    "sg:phone":"+1 508 775 3466",
    "sg:postcode":"02601",
    "sg:province":"MA",
    "sg:tags":[
        "wear",
        "formal"
    ],
    "wof:name":"Dennis-John Formals",
    "wof:placetype":"venue"
},
  "geometry": {"coordinates":[-70.302571,41.666731],"type":"Point"}
}