{
  "type": "Feature",
  "properties": {
    "iso:country":"US",
    "sg:address":"21 Main St",
    "sg:city":"Hingham",
    "sg:classifiers":[
        {
            "category":"Shopping",
            "subcategory":"Books",
            "type":"Retail Goods"
        }
    ],
    "sg:phone":"+1 781 749 2670",
    "sg:postcode":"02043",
    "sg:province":"MA",
    "sg:tags":[
        "dealer"
    ],
    "wof:name":"Bookport",
    "wof:placetype":"venue"
},
  "geometry": {"coordinates":[-70.88733499999999,42.240971],"type":"Point"}
}