{
  "type": "Feature",
  "properties": {
    "addr:full": "21 Main St Hingham MA 02043",
    "addr:housenumber": "21",
    "addr:postcode": "02043",
    "addr:street": "Main St",
    "iso:country": "US",
    "sg:address": "21 Main St",
    "sg:city": "Hingham",
    "sg:classifiers": [
      {
        "category": "Shopping",
        "subcategory": "Books",
        "type": "Retail Goods"
      }
    ],
    "sg:phone": "+1 781 749 2670",
    "sg:postcode": "02043",
    "sg:province": "MA",
    "sg:tags": [
      "dealer"
    ],
    "wof:name": "Bookport",
    "wof:placetype": "venue"
  },
  "geometry": {"coordinates":[-70.887335,42.240971],"type":"Point"}
}
