{
  "type": "Feature",
  "properties": {
    "iso:country":"US",
    "sg:address":"50 Laurel St",
    "sg:city":"Fitchburg",
    "sg:classifiers":[
        {
            "category":"Home & Garden",
            "subcategory":"Furniture",
            "type":"Retail Goods"
        }
    ],
    "sg:phone":"+1 978 342 3876",
    "sg:postcode":"01420",
    "sg:province":"MA",
    "wof:name":"C & M Furniture Outlet",
    "wof:placetype":"venue"
},
  "geometry": {"coordinates":[-71.79689999999999,42.580719],"type":"Point"}
}