{
  "type": "Feature",
  "properties": {
    "addr:full": "50 Laurel St Fitchburg MA 01420",
    "addr:housenumber": "50",
    "addr:postcode": "01420",
    "addr:street": "Laurel St",
    "iso:country": "US",
    "sg:address": "50 Laurel St",
    "sg:city": "Fitchburg",
    "sg:classifiers": [
      {
        "category": "Home \u0026 Garden",
        "subcategory": "Furniture",
        "type": "Retail Goods"
      }
    ],
    "sg:phone": "+1 978 342 3876",
    "sg:postcode": "01420",
    "sg:province": "MA",
    "wof:name": "C \u0026 M Furniture Outlet",
    "wof:placetype": "venue"
  },
  "geometry": {"coordinates":[-71.7969,42.580719],"type":"Point"}
}
