{
  "type": "Feature",
  "properties": {
    "addr:full":"892 Main St Wilmington MA 01887",
    "addr:housenumber":"892",
    "addr:postcode":"01887",
    "addr:street":"Main St",
    "iso:country":"US",
    "sg:address":"892 Main St",
    "sg:city":"Wilmington",
    "sg:classifiers":[
        {
            "category":"Sports & Exercise",
            "subcategory":"Gym",
            "type":"Entertainment"
        }
    ],
    "sg:phone":"+1 978 657 7800",
    "sg:postcode":"01887",
    "sg:province":"MA",
    "wof:name":"Metro Fitness Inc",
    "wof:placetype":"venue"
},
  "geometry": {"coordinates":[-71.15969800000001,42.525002],"type":"Point"}
}