{
  "type": "Feature",
  "properties": {
    "addr:full":"57 Cedar St Worcester MA 01609",
    "addr:housenumber":"57",
    "addr:postcode":"01609",
    "addr:street":"Cedar St",
    "iso:country":"US",
    "sg:address":"57 Cedar St",
    "sg:city":"Worcester",
    "sg:classifiers":[
        {
            "category":"Banks & Credit Unions",
            "subcategory":"Investment Brokerage",
            "type":"Services"
        }
    ],
    "sg:phone":"+1 508 752 8284",
    "sg:postcode":"01609",
    "sg:province":"MA",
    "sg:tags":[
        "consultant",
        "planning",
        "financial"
    ],
    "sg:website":"www.cliffordrano.com",
    "wof:name":"Clifford & Rano Insurance",
    "wof:placetype":"venue"
},
  "geometry": {"coordinates":[-71.811882,42.266833],"type":"Point"}
}