{
  "type": "Feature",
  "properties": {
    "addr:full": "20 Rowes Wharf Boston MA 02110",
    "addr:housenumber": "20",
    "addr:postcode": "02110",
    "addr:street": "Rowes Wharf",
    "iso:country": "US",
    "sg:address": "20 Rowes Wharf",
    "sg:city": "Boston",
    "sg:classifiers": [
      {
        "category": "Personal",
        "type": "Services"
      }
    ],
    "sg:phone": "+1 617 492 1200",
    "sg:postcode": "02110",
    "sg:province": "MA",
    "sg:tags": [
      "mover"
    ],
    "wof:name": "Gentlepeople",
    "wof:placetype": "venue"
  },
  "geometry": {"coordinates":[-71.049844,42.3558],"type":"Point"}
}
