{
  "type": "Feature",
  "properties": {
    "addr:full": "1001 Randolph Ave Milton MA 02186",
    "addr:housenumber": "1001",
    "addr:postcode": "02186",
    "addr:street": "Randolph Ave",
    "iso:country": "US",
    "sg:address": "1001 Randolph Ave",
    "sg:city": "Milton",
    "sg:classifiers": [
      {
        "category": "Building \u0026 Trades",
        "subcategory": "Locksmith",
        "type": "Services"
      }
    ],
    "sg:phone": "+1 617 925 3755",
    "sg:postcode": "02186",
    "sg:province": "MA",
    "sg:tags": [
      "key"
    ],
    "wof:name": "Boston A Locksmith",
    "wof:placetype": "venue"
  },
  "geometry": {"coordinates":[-71.070336,42.233753],"type":"Point"}
}
