{
  "type": "Feature",
  "properties": {
    "addr:full":"161 Worcester Rd Framingham MA 01701",
    "addr:housenumber":"161",
    "addr:postcode":"01701",
    "addr:street":"Worcester Rd",
    "iso:country":"US",
    "sg:address":"161 Worcester Rd",
    "sg:city":"Framingham",
    "sg:classifiers":[
        {
            "category":"Professional",
            "subcategory":"Lawyer & Legal Services",
            "type":"Services"
        }
    ],
    "sg:phone":"+1 508 820 4343",
    "sg:postcode":"01701",
    "sg:province":"MA",
    "sg:tags":[
        "attorney"
    ],
    "wof:name":"Abrams & Cincotta",
    "wof:placetype":"venue"
},
  "geometry": {"coordinates":[-71.401022,42.298647],"type":"Point"}
}