{
  "type": "Feature",
  "properties": {
    "addr:full":"165 W Shore Dr Marblehead MA 01945",
    "addr:housenumber":"165",
    "addr:postcode":"01945",
    "addr:street":"W Shore Dr",
    "iso:country":"US",
    "sg:address":"165 W Shore Dr",
    "sg:city":"Marblehead",
    "sg:classifiers":[
        {
            "category":"Professional",
            "subcategory":"Management & Consulting",
            "type":"Services"
        }
    ],
    "sg:phone":"+1   ",
    "sg:postcode":"01945",
    "sg:province":"MA",
    "sg:tags":[
        "consultant",
        "education"
    ],
    "wof:name":"Mary Mader",
    "wof:placetype":"venue"
},
  "geometry": {"coordinates":[-70.869051,42.50295],"type":"Point"}
}