{
  "type": "Feature",
  "properties": {
    "addr:full": "25 Winthrop Ave Beverly MA 01915",
    "addr:housenumber": "25",
    "addr:postcode": "01915",
    "addr:street": "Winthrop Ave",
    "iso:country": "US",
    "sg:address": "25 Winthrop Ave",
    "sg:city": "Beverly",
    "sg:classifiers": [
      {
        "category": "Professional",
        "subcategory": "Lawyer \u0026 Legal Services",
        "type": "Services"
      }
    ],
    "sg:phone": "+1 978 927 4002",
    "sg:postcode": "01915",
    "sg:province": "MA",
    "sg:tags": [
      "attorney"
    ],
    "wof:name": "Ralph H Hardy",
    "wof:placetype": "venue"
  },
  "geometry": {"coordinates":[-70.89238,42.548234],"type":"Point"}
}
