{
  "type": "Feature",
  "properties": {
    "addr:full": "103 Garland St Everett MA 02149",
    "addr:housenumber": "103",
    "addr:postcode": "02149",
    "addr:street": "Garland St",
    "iso:country": "US",
    "sg:address": "103 Garland St",
    "sg:city": "Everett",
    "sg:classifiers": [
      {
        "category": "Health Services",
        "subcategory": "Doctor",
        "type": "Services"
      }
    ],
    "sg:phone": "+1 617 389 4666",
    "sg:postcode": "02149",
    "sg:province": "MA",
    "sg:tags": [
      "physician",
      "surgeon"
    ],
    "wof:name": "Strongin, D Jonathan M.D.",
    "wof:placetype": "venue"
  },
  "geometry": {"coordinates":[-71.039165,42.409493],"type":"Point"}
}
