{
  "type": "Feature",
  "properties": {
    "addr:full":"75 McNeil Way Dedham MA 02026",
    "addr:housenumber":"75",
    "addr:postcode":"02026",
    "addr:street":"Mcneil Way",
    "iso:country":"US",
    "sg:address":"75 McNeil Way",
    "sg:city":"Dedham",
    "sg:classifiers":[
        {
            "category":"Real Estate",
            "subcategory":"Real Estate Agent",
            "type":"Services"
        }
    ],
    "sg:phone":"+1 781 326 5800",
    "sg:postcode":"02026",
    "sg:province":"MA",
    "wof:name":"Mc Neil Real Estate Group",
    "wof:placetype":"venue"
},
  "geometry": {"coordinates":[-71.17731000000001,42.235431],"type":"Point"}
}