{
  "type": "Feature",
  "properties": {
    "addr:full":"108 Thornberry Rd Winchester MA 01890",
    "addr:housenumber":"108",
    "addr:postcode":"01890",
    "addr:street":"Thornberry Rd",
    "iso:country":"US",
    "sg:address":"108 Thornberry Rd",
    "sg:city":"Winchester",
    "sg:classifiers":[
        {
            "category":"Professional",
            "subcategory":"Lawyer & Legal Services",
            "type":"Services"
        }
    ],
    "sg:phone":"+1 781 721 2325",
    "sg:postcode":"01890",
    "sg:province":"MA",
    "sg:tags":[
        "attorney",
        "practice"
    ],
    "wof:name":"Donato, Julianne Mba Attorney At Law",
    "wof:placetype":"venue"
},
  "geometry": {"coordinates":[-71.17980900000001,42.446733],"type":"Point"}
}