{
  "type": "Feature",
  "properties": {
    "addr:full":"217 Main St Spencer MA 01562",
    "addr:housenumber":"217",
    "addr:postcode":"01562",
    "addr:street":"Main St",
    "iso:country":"US",
    "sg:address":"217 Main St",
    "sg:city":"Spencer",
    "sg:classifiers":[
        {
            "category":"Travel",
            "subcategory":"Hotels & Motels",
            "type":"Entertainment"
        },
        {
            "category":"Travel",
            "subcategory":"Bed & Breakfast",
            "type":"Entertainment"
        }
    ],
    "sg:phone":"+1 508 885 9205",
    "sg:postcode":"01562",
    "sg:province":"MA",
    "wof:name":"Red Maple Inn",
    "wof:placetype":"venue"
},
  "geometry": {"coordinates":[-71.988297,42.246399],"type":"Point"}
}