{
  "type": "Feature",
  "properties": {
    "iso:country":"US",
    "sg:address":"16 Palma Ln",
    "sg:city":"Westfield",
    "sg:classifiers":[
        {
            "category":"Freight",
            "type":"Transportation"
        }
    ],
    "sg:phone":"+1 413 562 4087",
    "sg:postcode":"01085",
    "sg:province":"MA",
    "sg:tags":[
        "operator",
        "trucking"
    ],
    "wof:name":"Caravan Movers",
    "wof:placetype":"venue"
},
  "geometry": {"coordinates":[-72.707224,42.183298],"type":"Point"}
}