{
  "type": "Feature",
  "properties": {
    "iso:country":"US",
    "sg:address":"6 Cottage St",
    "sg:city":"Pepperell",
    "sg:classifiers":[
        {
            "category":"Professional",
            "subcategory":"Lawyer & Legal Services",
            "type":"Services"
        }
    ],
    "sg:phone":"+1 978 433 7770",
    "sg:postcode":"01463",
    "sg:province":"MA",
    "sg:tags":[
        "attorney"
    ],
    "wof:name":"Morrissey Law Office",
    "wof:placetype":"venue"
},
  "geometry": {"coordinates":[-71.580928,42.666037],"type":"Point"}
}