{
  "type": "Feature",
  "properties": {
    "addr:full": "542 Liberty St Hanson MA 02341",
    "addr:housenumber": "542",
    "addr:postcode": "02341",
    "addr:street": "Liberty St",
    "iso:country": "US",
    "sg:address": "542 Liberty St",
    "sg:city": "Hanson",
    "sg:classifiers": [
      {
        "category": "Government",
        "subcategory": "Office",
        "type": "Public Place"
      }
    ],
    "sg:phone": "+1 781 293 5070",
    "sg:postcode": "02341",
    "sg:province": "MA",
    "sg:tags": [
      "village"
    ],
    "wof:name": "Hanson Town Accountant",
    "wof:placetype": "venue"
  },
  "geometry": {"coordinates":[-70.868849,42.065912],"type":"Point"}
}
