{
  "type": "Feature",
  "properties": {
    "iso:country":"US",
    "sg:address":"175 Front St",
    "sg:city":"Housatonic",
    "sg:classifiers":[
        {
            "category":"Building & Trades",
            "subcategory":"Electrical",
            "type":"Services"
        }
    ],
    "sg:phone":"+1 413 274 6605",
    "sg:postcode":"01236",
    "sg:province":"MA",
    "sg:tags":[
        "electric",
        "contractor"
    ],
    "wof:name":"Piontek Electrical Contracting",
    "wof:placetype":"venue"
},
  "geometry": {"coordinates":[-73.363855,42.257366],"type":"Point"}
}