{
  "type": "Feature",
  "properties": {
    "iso:country":"US",
    "sg:address":"40 Grove St",
    "sg:city":"Lynnfield",
    "sg:classifiers":[
        {
            "category":"Place Of Worship",
            "subcategory":"Church",
            "type":"Public Place"
        },
        {
            "category":"Place Of Worship",
            "type":"Public Place"
        },
        {
            "category":"Education",
            "subcategory":"School",
            "type":"Public Place"
        },
        {
            "category":"Education",
            "subcategory":"Special Training",
            "type":"Public Place"
        }
    ],
    "sg:phone":"+1 781 599 4422",
    "sg:postcode":"01940",
    "sg:province":"MA",
    "sg:tags":[
        "k-",
        "churches-catholic-traditional",
        "churches-catholic",
        "private",
        "educational"
    ],
    "wof:name":"Our Lady Assumption School",
    "wof:placetype":"venue"
},
  "geometry": {"coordinates":[-71.00525500000001,42.515173],"type":"Point"}
}