{
  "type": "Feature",
  "properties": {
    "iso:country":"US",
    "sg:address":"61 Bowers St",
    "sg:city":"Lowell",
    "sg:classifiers":[
        {
            "category":"Recreation",
            "type":"Entertainment"
        }
    ],
    "sg:phone":"+1 978 452 8878",
    "sg:postcode":"01854",
    "sg:province":"MA",
    "sg:tags":[
        "hall",
        "auditorium"
    ],
    "wof:name":"St George Antiochian Church",
    "wof:placetype":"venue"
},
  "geometry": {"coordinates":[-71.324426,42.647735],"type":"Point"}
}