{
  "type": "Feature",
  "properties": {
    "addr:full":"19 Wildcat Ln Norwell MA 02061",
    "addr:housenumber":"19",
    "addr:postcode":"02061",
    "addr:street":"Wildcat Ln",
    "iso:country":"US",
    "sg:address":"19 Wildcat Ln",
    "sg:city":"Norwell",
    "sg:classifiers":[
        {
            "category":"Real Estate",
            "subcategory":"Real Estate Services",
            "type":"Services"
        },
        {
            "category":"Real Estate",
            "subcategory":"Real Estate Agent",
            "type":"Services"
        }
    ],
    "sg:phone":"+1 781 659 4532",
    "sg:postcode":"02061",
    "sg:province":"MA",
    "sg:tags":[
        "buyer",
        "broker"
    ],
    "wof:name":"Swingline Realty",
    "wof:placetype":"venue"
},
  "geometry": {"coordinates":[-70.80514100000001,42.140543],"type":"Point"}
}