{
  "type": "Feature",
  "properties": {
    "iso:country":"US",
    "sg:address":"41 Athletic Field Rd",
    "sg:city":"Waltham",
    "sg:classifiers":[
        {
            "category":"Manufacturing",
            "subcategory":"Metals",
            "type":"Manufacturing & Wholesale Goods"
        }
    ],
    "sg:phone":"+1 781 893 5890",
    "sg:postcode":"02451",
    "sg:province":"MA",
    "sg:tags":[
        "plating"
    ],
    "wof:name":"Acton Metal Processing Corp",
    "wof:placetype":"venue"
},
  "geometry": {"coordinates":[-71.24028300000001,42.381446],"type":"Point"}
}