{
  "type": "Feature",
  "properties": {
    "addr:full": "41 Athletic Field Rd Waltham MA 02451",
    "addr:housenumber": "41",
    "addr:postcode": "02451",
    "addr:street": "Athletic Field Rd",
    "iso:country": "US",
    "sg:address": "41 Athletic Field Rd",
    "sg:city": "Waltham",
    "sg:classifiers": [
      {
        "category": "Manufacturing",
        "subcategory": "Metals",
        "type": "Manufacturing \u0026 Wholesale Goods"
      }
    ],
    "sg:phone": "+1 781 893 5890",
    "sg:postcode": "02451",
    "sg:province": "MA",
    "sg:tags": [
      "plating"
    ],
    "wof:name": "Acton Metal Processing Corp",
    "wof:placetype": "venue"
  },
  "geometry": {"coordinates":[-71.240283,42.381446],"type":"Point"}
}
