{
  "type": "Feature",
  "properties": {
    "addr:full":"403 Oak St Shrewsbury MA 01545",
    "addr:housenumber":"403",
    "addr:postcode":"01545",
    "addr:street":"Oak St",
    "iso:country":"US",
    "sg:address":"403 Oak St",
    "sg:city":"Shrewsbury",
    "sg:classifiers":[
        {
            "category":"Wholesale",
            "subcategory":"Machinery & Supplies",
            "type":"Manufacturing & Wholesale Goods"
        }
    ],
    "sg:phone":"+1 508 754 7369",
    "sg:postcode":"01545",
    "sg:province":"MA",
    "sg:tags":[
        "machine",
        "tool"
    ],
    "wof:name":"Walter Grinders Inc",
    "wof:placetype":"venue"
},
  "geometry": {"coordinates":[-71.735079,42.263647],"type":"Point"}
}