{
  "type": "Feature",
  "properties": {
    "iso:country":"US",
    "sg:address":"919 Main St",
    "sg:city":"Wilbraham",
    "sg:classifiers":[
        {
            "category":"Health Services",
            "subcategory":"Health Practitioner",
            "type":"Services"
        }
    ],
    "sg:phone":"+1 413 596 9059",
    "sg:postcode":"01095",
    "sg:province":"MA",
    "sg:tags":[
        "psychotherapist"
    ],
    "wof:name":"James Counseling Assoc",
    "wof:placetype":"venue"
},
  "geometry": {"coordinates":[-72.435281,42.096127],"type":"Point"}
}