{
  "type": "Feature",
  "properties": {
    "addr:full":"465 Park Ave Worcester MA 01610",
    "addr:housenumber":"465",
    "addr:postcode":"01610",
    "addr:street":"Park Ave",
    "iso:country":"US",
    "sg:address":"465 Park Ave",
    "sg:city":"Worcester",
    "sg:classifiers":[
        {
            "category":"Personal",
            "type":"Services"
        }
    ],
    "sg:phone":"+1 508 756 9406",
    "sg:postcode":"01610",
    "sg:province":"MA",
    "sg:tags":[
        "electrolysis"
    ],
    "wof:name":"Nancy E Toomey",
    "wof:placetype":"venue"
},
  "geometry": {"coordinates":[-71.826576,42.25399],"type":"Point"}
}