{
  "type": "Feature",
  "properties": {
    "addr:full": "2 South St Pittsfield MA 01201",
    "addr:housenumber": "2",
    "addr:postcode": "01201",
    "addr:street": "South St",
    "iso:country": "US",
    "sg:address": "2 South St",
    "sg:city": "Pittsfield",
    "sg:classifiers": [
      {
        "category": "Professional",
        "subcategory": "Lawyer \u0026 Legal Services",
        "type": "Services"
      }
    ],
    "sg:phone": "+1 413 443 6100",
    "sg:postcode": "01201",
    "sg:province": "MA",
    "sg:tags": [
      "attorney"
    ],
    "wof:name": "Kopelman \u0026 Paige PC",
    "wof:placetype": "venue"
  },
  "geometry": {"coordinates":[-73.254438,42.446861],"type":"Point"}
}
