{
  "type": "Feature",
  "properties": {
    "addr:full": "194 Spring St Shrewsbury MA 01545",
    "addr:housenumber": "194",
    "addr:postcode": "01545",
    "addr:street": "Spring St",
    "iso:country": "US",
    "sg:address": "194 Spring St",
    "sg:city": "Shrewsbury",
    "sg:classifiers": [
      {
        "category": "Home \u0026 Garden",
        "subcategory": "Household Appliances",
        "type": "Retail Goods"
      }
    ],
    "sg:phone": "+1   ",
    "sg:postcode": "01545",
    "sg:province": "MA",
    "sg:tags": [
      "cleaners",
      "vacuum"
    ],
    "wof:name": "Treadwell Electric",
    "wof:placetype": "venue"
  },
  "geometry": {"coordinates":[-71.69553,42.303681],"type":"Point"}
}
