{
  "type": "Feature",
  "properties": {
    "addr:full":"2 Atlantic Ave Hull MA 02045",
    "addr:housenumber":"2",
    "addr:postcode":"02045",
    "addr:street":"Atlantic Ave",
    "iso:country":"US",
    "sg:address":"2 Atlantic Ave",
    "sg:city":"Hull",
    "sg:classifiers":[
        {
            "category":"Government",
            "subcategory":"Office",
            "type":"Public Place"
        }
    ],
    "sg:phone":"+1 781 925 2000",
    "sg:postcode":"02045",
    "sg:province":"MA",
    "sg:tags":[
        "city",
        "program",
        "health"
    ],
    "wof:name":"Hull Board Of Health",
    "wof:placetype":"venue"
},
  "geometry": {"coordinates":[-70.826246,42.264385],"type":"Point"}
}