{
  "type": "Feature",
  "properties": {
    "iso:country":"US",
    "sg:address":"25 Main St",
    "sg:city":"Northampton",
    "sg:classifiers":[
        {
            "category":"Personal",
            "type":"Services"
        }
    ],
    "sg:phone":"+1 413 582 9000",
    "sg:postcode":"01060",
    "sg:province":"MA",
    "sg:tags":[
        "therapist",
        "massage"
    ],
    "wof:name":"Bodyworks",
    "wof:placetype":"venue"
},
  "geometry": {"coordinates":[-72.629699,42.319523],"type":"Point"}
}