{
  "type": "Feature",
  "properties": {
    "iso:country":"US",
    "sg:address":"26 Old Elm St",
    "sg:city":"Salisbury",
    "sg:classifiers":[
        {
            "category":"Shopping",
            "type":"Retail Goods"
        }
    ],
    "sg:phone":"+1 978 462 6684",
    "sg:postcode":"01952",
    "sg:province":"MA",
    "sg:tags":[
        "water",
        "heater"
    ],
    "sg:website":"www.vaughncorp.com",
    "wof:name":"Vaughn Manufacturing",
    "wof:placetype":"venue"
},
  "geometry": {"coordinates":[-70.893531,42.844418],"type":"Point"}
}