{
  "type": "Feature",
  "properties": {
    "iso:country":"US",
    "sg:address":"24 School St",
    "sg:city":"Boston",
    "sg:classifiers":[
        {
            "category":"Manufacturing",
            "subcategory":"Printing",
            "type":"Manufacturing & Wholesale Goods"
        }
    ],
    "sg:phone":"+1   ",
    "sg:postcode":"02108",
    "sg:province":"MA",
    "sg:tags":[
        "information",
        "computer",
        "develop",
        "legal",
        "software"
    ],
    "wof:name":"Prosystem Fx",
    "wof:placetype":"venue"
},
  "geometry": {"coordinates":[-71.059242,42.357656],"type":"Point"}
}