{
  "type": "Feature",
  "properties": {
    "iso:country":"US",
    "sg:address":"15 Woburn St",
    "sg:city":"Waltham",
    "sg:classifiers":[
        {
            "category":"Building & Trades",
            "subcategory":"Construction",
            "type":"Services"
        }
    ],
    "sg:phone":"+1 781 893 1883",
    "sg:postcode":"02452",
    "sg:province":"MA",
    "sg:tags":[
        "general",
        "contractor"
    ],
    "wof:name":"Pat-C Inc",
    "wof:placetype":"venue"
},
  "geometry": {"coordinates":[-71.21909599999999,42.406992],"type":"Point"}
}