{
  "type": "Feature",
  "properties": {
    "iso:country":"US",
    "sg:address":"4 School St",
    "sg:city":"Westfield",
    "sg:classifiers":[
        {
            "category":"Organizations",
            "subcategory":"Non-profit Organization",
            "type":"Services"
        }
    ],
    "sg:phone":"+1 413 568 4494",
    "sg:postcode":"01085",
    "sg:province":"MA",
    "wof:name":"Domus Inc",
    "wof:placetype":"venue"
},
  "geometry": {"coordinates":[-72.75035,42.121418],"type":"Point"}
}