{
  "type": "Feature",
  "properties": {
    "iso:country":"US",
    "sg:address":"9 Dole Hill Ln",
    "sg:city":"Boxford",
    "sg:classifiers":[
        {
            "category":"Retail",
            "subcategory":"Repair Shop",
            "type":"Services"
        }
    ],
    "sg:phone":"+1   ",
    "sg:postcode":"01921",
    "sg:province":"MA",
    "wof:name":"McCallun Classic Piano",
    "wof:placetype":"venue"
},
  "geometry": {"coordinates":[-71.069782,42.703196],"type":"Point"}
}