{
  "type": "Feature",
  "properties": {
    "addr:full": "96 Water St Williamstown MA 01267",
    "addr:housenumber": "96",
    "addr:postcode": "01267",
    "addr:street": "Water St",
    "iso:country": "US",
    "sg:address": "96 Water St",
    "sg:city": "Williamstown",
    "sg:classifiers": [
      {
        "category": "Shopping",
        "subcategory": "Clothing, Apparel, \u0026 Fashions",
        "type": "Retail Goods"
      }
    ],
    "sg:phone": "+1 413 458 9394",
    "sg:postcode": "01267",
    "sg:province": "MA",
    "sg:tags": [
      "item",
      "boutique"
    ],
    "wof:name": "Room",
    "wof:placetype": "venue"
  },
  "geometry": {"coordinates":[-73.200536,42.708694],"type":"Point"}
}
