{
  "type": "Feature",
  "properties": {
    "addr:full": "146 Northern Ave Boston MA 02110",
    "addr:housenumber": "146",
    "addr:postcode": "02110",
    "addr:street": "Northern Ave",
    "iso:country": "US",
    "sg:address": "146 Northern Ave",
    "sg:city": "Boston",
    "sg:classifiers": [
      {
        "category": "Restaurant",
        "type": "Food \u0026 Drink"
      },
      {
        "category": "Food \u0026 Beverages",
        "subcategory": "Liquor \u0026 Beverages",
        "type": "Retail Goods"
      }
    ],
    "sg:postcode": "02110",
    "sg:province": "MA",
    "sg:tags": [
      "traditional",
      "american",
      "wine",
      "beer",
      "spirit"
    ],
    "sg:website": "www.atlanticbeergarden.com",
    "wof:name": "Atlantic Beer Garden",
    "wof:placetype": "venue"
  },
  "geometry": {"coordinates":[-71.043399,42.351138],"type":"Point"}
}
