{
  "type": "Feature",
  "properties": {
    "iso:country":"US",
    "sg:address":"146 Northern Ave",
    "sg:city":"Boston",
    "sg:classifiers":[
        {
            "category":"Restaurant",
            "type":"Food & Drink"
        },
        {
            "category":"Food & Beverages",
            "subcategory":"Liquor & Beverages",
            "type":"Retail Goods"
        }
    ],
    "sg:postcode":"02110",
    "sg:province":"MA",
    "sg:tags":[
        "traditional",
        "american",
        "wine",
        "beer",
        "spirit"
    ],
    "sg:website":"www.atlanticbeergarden.com",
    "wof:name":"Atlantic Beer Garden",
    "wof:placetype":"venue"
},
  "geometry": {"coordinates":[-71.04339899999999,42.351138],"type":"Point"}
}