{
  "type": "Feature",
  "properties": {
    "iso:country":"US",
    "sg:address":"825 Beacon St",
    "sg:city":"Newton",
    "sg:classifiers":[
        {
            "category":"Banks & Credit Unions",
            "subcategory":"Investment Brokerage",
            "type":"Services"
        }
    ],
    "sg:phone":"+1 617 964 4600",
    "sg:postcode":"02459",
    "sg:province":"MA",
    "wof:name":"Investment Properties LTD",
    "wof:placetype":"venue"
},
  "geometry": {"coordinates":[-71.197614,42.330419],"type":"Point"}
}