{
  "type": "Feature",
  "properties": {
    "addr:full": "1 Factory St Sagamore MA 02563",
    "addr:housenumber": "1",
    "addr:postcode": "02563",
    "addr:street": "Factory St",
    "iso:country": "US",
    "sg:address": "1 Factory St",
    "sg:city": "Sagamore",
    "sg:classifiers": [
      {
        "category": "Real Estate",
        "subcategory": "Real Estate Operator",
        "type": "Services"
      }
    ],
    "sg:phone": "+1 508 888 8417",
    "sg:postcode": "02563",
    "sg:province": "MA",
    "sg:tags": [
      "mall",
      "shopping",
      "center"
    ],
    "wof:name": "Cape Cod Factory Outlet Mall",
    "wof:placetype": "venue"
  },
  "geometry": {"coordinates":[-70.489406,41.757937],"type":"Point"}
}
