{
  "type": "Feature",
  "properties": {
    "iso:country":"US",
    "sg:address":"1 Factory St",
    "sg:city":"Sagamore",
    "sg:classifiers":[
        {
            "category":"Real Estate",
            "subcategory":"Real Estate Operator",
            "type":"Services"
        }
    ],
    "sg:phone":"+1 508 888 8417",
    "sg:postcode":"02563",
    "sg:province":"MA",
    "sg:tags":[
        "mall",
        "shopping",
        "center"
    ],
    "wof:name":"Cape Cod Factory Outlet Mall",
    "wof:placetype":"venue"
},
  "geometry": {"coordinates":[-70.489406,41.757937],"type":"Point"}
}