{
  "type": "Feature",
  "properties": {
    "iso:country":"US",
    "sg:address":"5 Coffins Field Rd",
    "sg:city":"Edgartown",
    "sg:classifiers":[
        {
            "category":"Taxi",
            "type":"Transportation"
        }
    ],
    "sg:phone":"+1 508 939 8504",
    "sg:postcode":"02539",
    "sg:province":"MA",
    "sg:tags":[
        "delivery"
    ],
    "wof:name":"Mario's Delivery Service",
    "wof:placetype":"venue"
},
  "geometry": {"coordinates":[-70.606363,41.384573],"type":"Point"}
}