{
  "type": "Feature",
  "properties": {
    "addr:full": "99 Spring St Brockton MA 02301",
    "addr:housenumber": "99",
    "addr:postcode": "02301",
    "addr:street": "Spring St",
    "iso:country": "US",
    "sg:address": "99 Spring St",
    "sg:city": "Brockton",
    "sg:classifiers": [
      {
        "category": "Retail",
        "subcategory": "Auto Repair",
        "type": "Services"
      }
    ],
    "sg:phone": "+1 508 580 6662",
    "sg:postcode": "02301",
    "sg:province": "MA",
    "sg:tags": [
      "repairing",
      "automobile"
    ],
    "wof:name": "Carlton's Auto Repair",
    "wof:placetype": "venue"
  },
  "geometry": {"coordinates":[-71.02411,42.086394],"type":"Point"}
}
