{
  "type": "Feature",
  "properties": {
    "iso:country":"US",
    "sg:address":"14 Page Ter",
    "sg:city":"Stoughton",
    "sg:classifiers":[
        {
            "category":"Professional",
            "subcategory":"Lawyer & Legal Services",
            "type":"Services"
        }
    ],
    "sg:phone":"+1 781 341 6375",
    "sg:postcode":"02072",
    "sg:province":"MA",
    "wof:name":"Rose Lawrence J Atty",
    "wof:placetype":"venue"
},
  "geometry": {"coordinates":[-71.074997,42.151798],"type":"Point"}
}