{
  "type": "Feature",
  "properties": {
    "addr:full": "605 Springs Rd Bedford MA 01730",
    "addr:housenumber": "605",
    "addr:postcode": "01730",
    "addr:street": "Springs Rd",
    "iso:country": "US",
    "sg:address": "605 Springs Rd",
    "sg:city": "Bedford",
    "sg:classifiers": [
      {
        "category": "Manufacturing",
        "subcategory": "Chemicals \u0026 Compounds",
        "type": "Manufacturing \u0026 Wholesale Goods"
      }
    ],
    "sg:phone": "+1 978 667 5161",
    "sg:postcode": "01730",
    "sg:province": "MA",
    "wof:name": "Perma Inc",
    "wof:placetype": "venue"
  },
  "geometry": {"coordinates":[-71.280832,42.526408],"type":"Point"}
}
