{
  "type": "Feature",
  "properties": {
    "iso:country":"US",
    "sg:address":"605 Springs Rd",
    "sg:city":"Bedford",
    "sg:classifiers":[
        {
            "category":"Manufacturing",
            "subcategory":"Chemicals & Compounds",
            "type":"Manufacturing & Wholesale Goods"
        }
    ],
    "sg:phone":"+1 978 667 5161",
    "sg:postcode":"01730",
    "sg:province":"MA",
    "wof:name":"Perma Inc",
    "wof:placetype":"venue"
},
  "geometry": {"coordinates":[-71.280832,42.526408],"type":"Point"}
}