{
  "type": "Feature",
  "properties": {
    "addr:full": "45 Border St West Newton MA 02465",
    "addr:housenumber": "45",
    "addr:postcode": "02465",
    "addr:street": "Border St",
    "iso:country": "US",
    "sg:address": "45 Border St",
    "sg:city": "West Newton",
    "sg:classifiers": [
      {
        "category": "Wholesale",
        "subcategory": "Hardware",
        "type": "Manufacturing \u0026 Wholesale Goods"
      }
    ],
    "sg:phone": "+1 617 965 8840",
    "sg:postcode": "02465",
    "sg:province": "MA",
    "sg:tags": [
      "nut",
      "bolt"
    ],
    "sg:website": "www.albecofast.com",
    "wof:name": "Albeco Fastener Co",
    "wof:placetype": "venue"
  },
  "geometry": {"coordinates":[-71.23074,42.348866],"type":"Point"}
}
