{
  "type": "Feature",
  "properties": {
    "addr:full": "715 Pleasant St Worcester MA 01602",
    "addr:housenumber": "715",
    "addr:postcode": "01602",
    "addr:street": "Pleasant St",
    "iso:country": "US",
    "sg:address": "715 Pleasant St",
    "sg:city": "Worcester",
    "sg:classifiers": [
      {
        "category": "Health Services",
        "subcategory": "Doctor",
        "type": "Services"
      }
    ],
    "sg:phone": "+1 508 754 0918",
    "sg:postcode": "01602",
    "sg:province": "MA",
    "sg:tags": [
      "dentist"
    ],
    "wof:name": "Terrance Mc Govern DDS",
    "wof:placetype": "venue"
  },
  "geometry": {"coordinates":[-71.826244,42.270167],"type":"Point"}
}
