{
  "type": "Feature",
  "properties": {
    "iso:country":"US",
    "sg:address":"221 Main St",
    "sg:city":"Stoneham",
    "sg:classifiers":[
        {
            "category":"Building & Trades",
            "subcategory":"Locksmith",
            "type":"Services"
        }
    ],
    "sg:phone":"+1 781 832 9036",
    "sg:postcode":"02180",
    "sg:province":"MA",
    "sg:tags":[
        "key"
    ],
    "wof:name":"Anytime Any Place Locksmth",
    "wof:placetype":"venue"
},
  "geometry": {"coordinates":[-71.10026000000001,42.486994],"type":"Point"}
}