{
  "type": "Feature",
  "properties": {
    "addr:full": "9 Standish St Duxbury MA 02332",
    "addr:housenumber": "9",
    "addr:postcode": "02332",
    "addr:street": "Standish St",
    "iso:country": "US",
    "sg:address": "9 Standish St",
    "sg:city": "Duxbury",
    "sg:classifiers": [
      {
        "category": "Shopping",
        "subcategory": "Gifts \u0026 Souvenirs",
        "type": "Retail Goods"
      }
    ],
    "sg:phone": "+1 781 934 9553",
    "sg:postcode": "02332",
    "sg:province": "MA",
    "sg:tags": [
      "shop"
    ],
    "wof:name": "Octavia's Gift Gallery",
    "wof:placetype": "venue"
  },
  "geometry": {"coordinates":[-70.68295,42.022883],"type":"Point"}
}
