{
  "type": "Feature",
  "properties": {
    "iso:country":"US",
    "sg:address":"9 Standish St",
    "sg:city":"Duxbury",
    "sg:classifiers":[
        {
            "category":"Shopping",
            "subcategory":"Gifts & Souvenirs",
            "type":"Retail Goods"
        }
    ],
    "sg:phone":"+1 781 934 9553",
    "sg:postcode":"02332",
    "sg:province":"MA",
    "sg:tags":[
        "shop"
    ],
    "wof:name":"Octavia's Gift Gallery",
    "wof:placetype":"venue"
},
  "geometry": {"coordinates":[-70.68295000000001,42.022883],"type":"Point"}
}