{
  "type": "Feature",
  "properties": {
    "iso:country":"US",
    "sg:address":"165P New Boston St",
    "sg:city":"Woburn",
    "sg:classifiers":[
        {
            "category":"Sports & Exercise",
            "subcategory":"Gym",
            "type":"Entertainment"
        }
    ],
    "sg:phone":"+1 781 935 7455",
    "sg:postcode":"01801",
    "sg:province":"MA",
    "sg:tags":[
        "trainer"
    ],
    "wof:name":"Smith & Nephew Inc New England",
    "wof:placetype":"venue"
},
  "geometry": {"coordinates":[-71.1437,42.5107],"type":"Point"}
}