{
  "type": "Feature",
  "properties": {
    "iso:country":"US",
    "sg:address":"32 Summer Ave",
    "sg:city":"Reading",
    "sg:classifiers":[
        {
            "category":"Cinema",
            "subcategory":"Movie Rental",
            "type":"Entertainment"
        }
    ],
    "sg:phone":"+1   ",
    "sg:postcode":"01867",
    "sg:province":"MA",
    "sg:tags":[
        "video",
        "tape"
    ],
    "wof:name":"Francis W OKeeffe",
    "wof:placetype":"venue"
},
  "geometry": {"coordinates":[-71.12302699999999,42.527095],"type":"Point"}
}