{
  "type": "Feature",
  "properties": {
    "addr:full":"23 Curtis St Wakefield MA 01880",
    "addr:housenumber":"23",
    "addr:postcode":"01880",
    "addr:street":"Curtis St",
    "iso:country":"US",
    "sg:address":"23 Curtis St",
    "sg:city":"Wakefield",
    "sg:classifiers":[
        {
            "category":"Professional",
            "subcategory":"Employment Agencies",
            "type":"Services"
        }
    ],
    "sg:phone":"+1   ",
    "sg:postcode":"01880",
    "sg:province":"MA",
    "sg:tags":[
        "help",
        "supply"
    ],
    "wof:name":"Typerite Transcription",
    "wof:placetype":"venue"
},
  "geometry": {"coordinates":[-71.056032,42.508107],"type":"Point"}
}