{
  "type": "Feature",
  "properties": {
    "iso:country":"US",
    "sg:address":"73 Lakewood Dr",
    "sg:city":"Mashpee",
    "sg:classifiers":[
        {
            "category":"Professional",
            "subcategory":"Business Services",
            "type":"Services"
        }
    ],
    "sg:phone":"+1 508 477 5874",
    "sg:postcode":"02649",
    "sg:province":"MA",
    "sg:tags":[
        "embroidery"
    ],
    "wof:name":"J C Designs",
    "wof:placetype":"venue"
},
  "geometry": {"coordinates":[-70.480459,41.653808],"type":"Point"}
}