{
  "type": "Feature",
  "properties": {
    "addr:full": "100 Charlton Rd Sturbridge MA 01566",
    "addr:housenumber": "100",
    "addr:postcode": "01566",
    "addr:street": "Charlton Rd",
    "iso:country": "US",
    "sg:address": "100 Charlton Rd",
    "sg:city": "Sturbridge",
    "sg:classifiers": [
      {
        "category": "Banks \u0026 Credit Unions",
        "subcategory": "Bank",
        "type": "Services"
      }
    ],
    "sg:phone": "+1 508 347 5183",
    "sg:postcode": "01566",
    "sg:province": "MA",
    "wof:name": "Citizen Bank",
    "wof:placetype": "venue"
  },
  "geometry": {"coordinates":[-72.056171,42.124833],"type":"Point"}
}
