{
  "type": "Feature",
  "properties": {
    "addr:full": "11 Robert Toner Blvd Attleboro Falls MA 02763",
    "addr:housenumber": "11",
    "addr:postcode": "02763",
    "addr:street": "Robert Toner Blvd",
    "iso:country": "US",
    "sg:address": "11 Robert Toner Blvd",
    "sg:city": "Attleboro Falls",
    "sg:classifiers": [
      {
        "category": "Banks \u0026 Credit Unions",
        "subcategory": "Financial Services",
        "type": "Services"
      }
    ],
    "sg:phone": "+1 508 695 7665",
    "sg:postcode": "02763",
    "sg:province": "MA",
    "sg:tags": [
      "broker",
      "mortgage"
    ],
    "sg:website": "www.citifinancial.com",
    "wof:name": "Citifinancial",
    "wof:placetype": "venue"
  },
  "geometry": {"coordinates":[-71.304001,41.968899],"type":"Point"}
}
