{
  "type": "Feature",
  "properties": {
    "iso:country":"US",
    "sg:address":"11 Robert Toner Blvd",
    "sg:city":"Attleboro Falls",
    "sg:classifiers":[
        {
            "category":"Banks & Credit Unions",
            "subcategory":"Financial Services",
            "type":"Services"
        }
    ],
    "sg:phone":"+1 508 695 7665",
    "sg:postcode":"02763",
    "sg:province":"MA",
    "sg:tags":[
        "broker",
        "mortgage"
    ],
    "sg:website":"www.citifinancial.com",
    "wof:name":"Citifinancial",
    "wof:placetype":"venue"
},
  "geometry": {"coordinates":[-71.304001,41.968899],"type":"Point"}
}