{
  "type": "Feature",
  "properties": {
    "iso:country":"US",
    "sg:address":"468 Merrimack St",
    "sg:city":"Methuen",
    "sg:classifiers":[
        {
            "category":"Education",
            "subcategory":"Music School",
            "type":"Public Place"
        },
        {
            "category":"Shopping",
            "subcategory":"Party Supplies",
            "type":"Retail Goods"
        },
        {
            "category":"Sports & Exercise",
            "subcategory":"Gym",
            "type":"Entertainment"
        },
        {
            "category":"Arts & Performance",
            "subcategory":"Dance",
            "type":"Entertainment"
        }
    ],
    "sg:phone":"+1 978 548 6107",
    "sg:postcode":"01844",
    "sg:province":"MA",
    "sg:tags":[
        "children's",
        "planning",
        "instruction",
        "instruction-vocal",
        "program",
        "instruction-instrumental",
        "fitness",
        "wedding",
        "dancing",
        "physical"
    ],
    "sg:website":"http://www.danceimages1.com/index.html",
    "wof:name":"Dance Images Dance & Music Center",
    "wof:placetype":"venue"
},
  "geometry": {"coordinates":[-71.12723,42.75012],"type":"Point"}
}