{
  "type": "Feature",
  "properties": {
    "iso:country":"US",
    "sg:address":"99 Heywood St",
    "sg:city":"Gardner",
    "sg:classifiers":[
        {
            "category":"Professional",
            "subcategory":"Research",
            "type":"Services"
        }
    ],
    "sg:phone":"+1 978 630 8791",
    "sg:postcode":"01440",
    "sg:province":"MA",
    "sg:tags":[
        "environmental",
        "ecological"
    ],
    "wof:name":"Earth Tech Inc",
    "wof:placetype":"venue"
},
  "geometry": {"coordinates":[-71.987679,42.581613],"type":"Point"}
}