{
  "type": "Feature",
  "properties": {
    "addr:full": "94 N Elm St Westfield MA 01085",
    "addr:housenumber": "94",
    "addr:postcode": "01085",
    "addr:street": "N Elm St",
    "iso:country": "US",
    "sg:address": "94 N Elm St",
    "sg:city": "Westfield",
    "sg:classifiers": [
      {
        "category": "Health Services",
        "subcategory": "Doctor",
        "type": "Services"
      }
    ],
    "sg:phone": "+1 413 568 1477",
    "sg:postcode": "01085",
    "sg:province": "MA",
    "sg:tags": [
      "physician",
      "surgeon"
    ],
    "wof:name": "Orthopedics Physicians",
    "wof:placetype": "venue"
  },
  "geometry": {"coordinates":[-72.743155,42.132315],"type":"Point"}
}
