{
  "type": "Feature",
  "properties": {
    "iso:country":"US",
    "sg:address":"4 Hemlock St",
    "sg:city":"Danvers",
    "sg:classifiers":[
        {
            "category":"Retail",
            "subcategory":"Repair Shop",
            "type":"Services"
        }
    ],
    "sg:phone":"+1 978 744 2763",
    "sg:postcode":"01923",
    "sg:province":"MA",
    "sg:tags":[
        "welding"
    ],
    "wof:name":"J & J Welding Co",
    "wof:placetype":"venue"
},
  "geometry": {"coordinates":[-70.928543,42.569855],"type":"Point"}
}