{
  "type": "Feature",
  "properties": {
    "addr:full":"50 Nagog Park Acton MA 01720",
    "addr:housenumber":"50",
    "addr:postcode":"01720",
    "addr:street":"Nagog Park",
    "iso:country":"US",
    "sg:address":"50 Nagog Park",
    "sg:city":"Acton",
    "sg:classifiers":[
        {
            "category":"Professional",
            "subcategory":"Business Services",
            "type":"Services"
        }
    ],
    "sg:phone":"+1 978 897 0100",
    "sg:postcode":"01720",
    "sg:province":"MA",
    "sg:website":"http://www.schange.com/",
    "wof:name":"SeaChange International",
    "wof:placetype":"venue"
},
  "geometry": {"coordinates":[-71.42964499999999,42.525601],"type":"Point"}
}