{
  "type": "Feature",
  "properties": {
    "iso:country":"US",
    "sg:address":"7 North St",
    "sg:city":"Pittsfield",
    "sg:classifiers":[
        {
            "category":"Government",
            "subcategory":"Office",
            "type":"Public Place"
        }
    ],
    "sg:phone":"+1 413 443 3500",
    "sg:postcode":"01201",
    "sg:province":"MA",
    "wof:name":"Berkshire County Victim Asstnc",
    "wof:placetype":"venue"
},
  "geometry": {"coordinates":[-73.25381299999999,42.449331],"type":"Point"}
}