{
  "type": "Feature",
  "properties": {
    "addr:full": "7 North St Pittsfield MA 01201",
    "addr:housenumber": "7",
    "addr:postcode": "01201",
    "addr:street": "North St",
    "iso:country": "US",
    "sg:address": "7 North St",
    "sg:city": "Pittsfield",
    "sg:classifiers": [
      {
        "category": "Government",
        "subcategory": "Office",
        "type": "Public Place"
      }
    ],
    "sg:phone": "+1 413 443 3500",
    "sg:postcode": "01201",
    "sg:province": "MA",
    "wof:name": "Berkshire County Victim Asstnc",
    "wof:placetype": "venue"
  },
  "geometry": {"coordinates":[-73.253813,42.449331],"type":"Point"}
}
