{
  "type": "Feature",
  "properties": {
    "iso:country":"US",
    "sg:address":"695 Main St",
    "sg:city":"Holden",
    "sg:classifiers":[
        {
            "category":"Retail",
            "subcategory":"Laundry & Dry Cleaning",
            "type":"Services"
        }
    ],
    "sg:phone":"+1 508 829 9459",
    "sg:postcode":"01520",
    "sg:province":"MA",
    "sg:tags":[
        "cleaners"
    ],
    "wof:name":"Holden Cleaners",
    "wof:placetype":"venue"
},
  "geometry": {"coordinates":[-71.83839399999999,42.33972],"type":"Point"}
}