{
  "type": "Feature",
  "properties": {
    "iso:country":"US",
    "sg:address":"344 Marlborough St",
    "sg:city":"Boston",
    "sg:classifiers":[
        {
            "category":"Professional",
            "subcategory":"Business Services",
            "type":"Services"
        }
    ],
    "sg:phone":"+1 617 536 0506",
    "sg:postcode":"02115",
    "sg:province":"MA",
    "sg:tags":[
        "management"
    ],
    "wof:name":"Integral Growth",
    "wof:placetype":"venue"
},
  "geometry": {"coordinates":[-71.085846,42.350935],"type":"Point"}
}