{
  "type": "Feature",
  "properties": {
    "iso:country":"US",
    "sg:address":"67 Mechanic St",
    "sg:city":"Foxboro",
    "sg:classifiers":[
        {
            "category":"Social Services",
            "subcategory":"Child Care",
            "type":"Services"
        }
    ],
    "sg:phone":"+1 508 543 2523",
    "sg:postcode":"02035",
    "sg:province":"MA",
    "wof:name":"YMCA Hockomock",
    "wof:placetype":"venue"
},
  "geometry": {"coordinates":[-71.242673,42.069657],"type":"Point"}
}