{
  "type": "Feature",
  "properties": {
    "addr:full":"55 Pacella Park Dr Randolph MA 02368",
    "addr:housenumber":"55",
    "addr:postcode":"02368",
    "addr:street":"Pacella Park Dr",
    "iso:country":"US",
    "sg:address":"55 Pacella Park Dr",
    "sg:city":"Randolph",
    "sg:classifiers":[
        {
            "category":"Professional",
            "subcategory":"Management & Consulting",
            "type":"Services"
        }
    ],
    "sg:phone":"+1 781 961 3000",
    "sg:postcode":"02368",
    "sg:province":"MA",
    "sg:tags":[
        "marketing",
        "program"
    ],
    "wof:name":"Schmid",
    "wof:placetype":"venue"
},
  "geometry": {"coordinates":[-71.057462,42.201392],"type":"Point"}
}