{
  "type": "Feature",
  "properties": {
    "iso:country":"US",
    "sg:address":"937 N Main St",
    "sg:city":"Randolph",
    "sg:classifiers":[
        {
            "category":"Retail",
            "subcategory":"Repair Shop",
            "type":"Services"
        }
    ],
    "sg:phone":"+1 781 569 0157",
    "sg:postcode":"02368",
    "sg:province":"MA",
    "sg:tags":[
        "lock",
        "locksmith"
    ],
    "wof:name":"Always Locksmith",
    "wof:placetype":"venue"
},
  "geometry": {"coordinates":[-71.055729,42.186194],"type":"Point"}
}