{
  "type": "Feature",
  "properties": {
    "addr:full": "46 Kings Way Waltham MA 02451",
    "addr:housenumber": "46",
    "addr:postcode": "02451",
    "addr:street": "Kings Way",
    "iso:country": "US",
    "sg:address": "46 Kings Way",
    "sg:city": "Waltham",
    "sg:classifiers": [
      {
        "category": "Professional",
        "subcategory": "Business Services",
        "type": "Services"
      }
    ],
    "sg:phone": "+1   ",
    "sg:postcode": "02451",
    "sg:province": "MA",
    "wof:name": "Dreamcatchers Group",
    "wof:placetype": "venue"
  },
  "geometry": {"coordinates":[-71.250363,42.406688],"type":"Point"}
}
