{
  "type": "Feature",
  "properties": {
    "iso:country":"US",
    "sg:address":"46 Kings Way",
    "sg:city":"Waltham",
    "sg:classifiers":[
        {
            "category":"Professional",
            "subcategory":"Business Services",
            "type":"Services"
        }
    ],
    "sg:phone":"+1   ",
    "sg:postcode":"02451",
    "sg:province":"MA",
    "wof:name":"Dreamcatchers Group",
    "wof:placetype":"venue"
},
  "geometry": {"coordinates":[-71.25036299999999,42.406688],"type":"Point"}
}