{
  "type": "Feature",
  "properties": {
    "addr:full": "237 Lafayette Rd Salisbury MA 01952",
    "addr:housenumber": "237",
    "addr:postcode": "01952",
    "iso:country": "US",
    "sg:address": "237 Lafayette Rd",
    "sg:city": "Salisbury",
    "sg:classifiers": [
      {
        "category": "Building \u0026 Trades",
        "subcategory": "Construction",
        "type": "Services"
      }
    ],
    "sg:phone": "+1 978 462 6106",
    "sg:postcode": "01952",
    "sg:province": "MA",
    "sg:tags": [
      "paving",
      "contractor"
    ],
    "wof:name": "Salisbury Hot Top Paving Co",
    "wof:placetype": "venue"
  },
  "geometry": {"coordinates":[-70.86983,42.869375],"type":"Point"}
}
