{
  "type": "Feature",
  "properties": {
    "iso:country":"US",
    "sg:address":"237 Lafayette Rd",
    "sg:city":"Salisbury",
    "sg:classifiers":[
        {
            "category":"Building & Trades",
            "subcategory":"Construction",
            "type":"Services"
        }
    ],
    "sg:phone":"+1 978 462 6106",
    "sg:postcode":"01952",
    "sg:province":"MA",
    "sg:tags":[
        "paving",
        "contractor"
    ],
    "wof:name":"Salisbury Hot Top Paving Co",
    "wof:placetype":"venue"
},
  "geometry": {"coordinates":[-70.86982999999999,42.869375],"type":"Point"}
}