{
  "type": "Feature",
  "properties": {
    "iso:country":"US",
    "sg:address":"85 Southern Ave",
    "sg:city":"Essex",
    "sg:classifiers":[
        {
            "category":"Manufacturing",
            "subcategory":"Furniture",
            "type":"Manufacturing & Wholesale Goods"
        },
        {
            "category":"Home & Garden",
            "subcategory":"Furniture",
            "type":"Retail Goods"
        }
    ],
    "sg:phone":"+1 978 768 1173",
    "sg:postcode":"01929",
    "sg:province":"MA",
    "sg:tags":[
        "household",
        "wood",
        "mfg"
    ],
    "wof:name":"New England Joinery",
    "wof:placetype":"venue"
},
  "geometry": {"coordinates":[-70.77301900000001,42.621595],"type":"Point"}
}