{
  "type": "Feature",
  "properties": {
    "addr:full": "85 Southern Ave Essex MA 01929",
    "addr:housenumber": "85",
    "addr:postcode": "01929",
    "addr:street": "Southern Ave",
    "iso:country": "US",
    "sg:address": "85 Southern Ave",
    "sg:city": "Essex",
    "sg:classifiers": [
      {
        "category": "Manufacturing",
        "subcategory": "Furniture",
        "type": "Manufacturing \u0026 Wholesale Goods"
      },
      {
        "category": "Home \u0026 Garden",
        "subcategory": "Furniture",
        "type": "Retail Goods"
      }
    ],
    "sg:phone": "+1 978 768 1173",
    "sg:postcode": "01929",
    "sg:province": "MA",
    "sg:tags": [
      "household",
      "wood",
      "mfg"
    ],
    "wof:name": "New England Joinery",
    "wof:placetype": "venue"
  },
  "geometry": {"coordinates":[-70.773019,42.621595],"type":"Point"}
}
