{
  "type": "Feature",
  "properties": {
    "addr:full":"51 Harbor St Salem MA 01970",
    "addr:housenumber":"51",
    "addr:postcode":"01970",
    "addr:street":"Harbor St",
    "iso:country":"US",
    "sg:address":"51 Harbor St",
    "sg:city":"Salem",
    "sg:classifiers":[
        {
            "category":"Food & Beverages",
            "subcategory":"Groceries & Convenience Stores",
            "type":"Retail Goods"
        }
    ],
    "sg:phone":"+1 978 745 8260",
    "sg:postcode":"01970",
    "sg:province":"MA",
    "sg:tags":[
        "market"
    ],
    "wof:name":"Marc's Market",
    "wof:placetype":"venue"
},
  "geometry": {"coordinates":[-70.891443,42.51774],"type":"Point"}
}