{
  "type": "Feature",
  "properties": {
    "addr:full": "33 E Falmouth Hwy East Falmouth MA 02536",
    "addr:housenumber": "33",
    "addr:postcode": "02536",
    "addr:street": "E Falmouth Hwy",
    "iso:country": "US",
    "sg:address": "33 E Falmouth Hwy",
    "sg:city": "East Falmouth",
    "sg:classifiers": [
      {
        "category": "Building \u0026 Trades",
        "subcategory": "Plumbing",
        "type": "Services"
      }
    ],
    "sg:phone": "+1 508 457 6541",
    "sg:postcode": "02536",
    "sg:province": "MA",
    "sg:tags": [
      "plumbing",
      "contractor"
    ],
    "wof:name": "T \u0026 T Plumbing",
    "wof:placetype": "venue"
  },
  "geometry": {"coordinates":[-70.572502,41.578187],"type":"Point"}
}
