{
  "type": "Feature",
  "properties": {
    "addr:full":"496 Lynnfield St Lynn MA 01904",
    "addr:housenumber":"496",
    "addr:postcode":"01904",
    "addr:street":"Lynnfield St",
    "iso:country":"US",
    "sg:address":"496 Lynnfield St",
    "sg:city":"Lynn",
    "sg:classifiers":[
        {
            "category":"Health Services",
            "subcategory":"Doctor",
            "type":"Services"
        }
    ],
    "sg:phone":"+1 781 586 9300",
    "sg:postcode":"01904",
    "sg:province":"MA",
    "sg:tags":[
        "a",
        "physician",
        "medical",
        "operates",
        "as",
        "surgeon",
        "specialized"
    ],
    "wof:name":"Northeast Cardiology Inc",
    "wof:placetype":"venue"
},
  "geometry": {"coordinates":[-70.97851900000001,42.50149],"type":"Point"}
}