{
  "type": "Feature",
  "properties": {
    "addr:full": "158 N Main St Uxbridge MA 01569",
    "addr:housenumber": "158",
    "addr:postcode": "01569",
    "addr:street": "N Main St",
    "iso:country": "US",
    "sg:address": "158 N Main St",
    "sg:city": "Uxbridge",
    "sg:classifiers": [
      {
        "category": "Restaurant",
        "type": "Food \u0026 Drink"
      }
    ],
    "sg:phone": "+1 508 278 9399",
    "sg:postcode": "01569",
    "sg:province": "MA",
    "wof:name": "China Dragon",
    "wof:placetype": "venue"
  },
  "geometry": {"coordinates":[-71.63804,42.082355],"type":"Point"}
}
