{
  "type": "Feature",
  "properties": {
    "iso:country":"US",
    "sg:address":"158 N Main St",
    "sg:city":"Uxbridge",
    "sg:classifiers":[
        {
            "category":"Restaurant",
            "type":"Food & Drink"
        }
    ],
    "sg:phone":"+1 508 278 9399",
    "sg:postcode":"01569",
    "sg:province":"MA",
    "wof:name":"China Dragon",
    "wof:placetype":"venue"
},
  "geometry": {"coordinates":[-71.63804,42.082355],"type":"Point"}
}