{
  "type": "Feature",
  "properties": {
    "iso:country":"US",
    "sg:address":"290 Eliot St",
    "sg:city":"Ashland",
    "sg:classifiers":[
        {
            "category":"Shopping",
            "type":"Retail Goods"
        }
    ],
    "sg:phone":"+1 508 881 4730",
    "sg:postcode":"01721",
    "sg:province":"MA",
    "sg:tags":[
        "picture",
        "frame"
    ],
    "sg:website":"www.premier-image.com",
    "wof:name":"Premier Image Gallery",
    "wof:placetype":"venue"
},
  "geometry": {"coordinates":[-71.431541,42.241878],"type":"Point"}
}