{
  "type": "Feature",
  "properties": {
    "addr:full": "150 Hopping Brook Rd Holliston MA 01746",
    "addr:housenumber": "150",
    "addr:postcode": "01746",
    "addr:street": "Hopping Brook Rd",
    "iso:country": "US",
    "sg:address": "150 Hopping Brook Rd",
    "sg:city": "Holliston",
    "sg:classifiers": [
      {
        "category": "Manufacturing",
        "subcategory": "Tools \u0026 Machinery",
        "type": "Manufacturing \u0026 Wholesale Goods"
      }
    ],
    "sg:phone": "+1 508 474 1100",
    "sg:postcode": "01746",
    "sg:province": "MA",
    "sg:tags": [
      "metalworking"
    ],
    "sg:website": "www.bostomatic.com",
    "wof:name": "Micron Bostomatic Corp",
    "wof:placetype": "venue"
  },
  "geometry": {"coordinates":[-71.467994,42.169379],"type":"Point"}
}
