{
  "type": "Feature",
  "properties": {
    "addr:full":"391 Liberty St Hanson MA 02341",
    "addr:housenumber":"391",
    "addr:postcode":"02341",
    "addr:street":"Liberty St",
    "iso:country":"US",
    "sg:address":"391 Liberty St",
    "sg:city":"Hanson",
    "sg:classifiers":[
        {
            "category":"Travel",
            "subcategory":"Travel Agent",
            "type":"Entertainment"
        }
    ],
    "sg:phone":"+1 781 294 2240",
    "sg:postcode":"02341",
    "sg:province":"MA",
    "sg:tags":[
        "cruise"
    ],
    "wof:name":"Cruise Planners",
    "wof:placetype":"venue"
},
  "geometry": {"coordinates":[-70.86752799999999,42.065753],"type":"Point"}
}