{
  "type": "Feature",
  "properties": {
    "addr:full":"27 Hollis St Framingham MA 01770",
    "addr:housenumber":"27",
    "addr:postcode":"01770",
    "addr:street":"Hollis St",
    "iso:country":"US",
    "sg:address":"27 Hollis St",
    "sg:city":"Framingham",
    "sg:classifiers":[
        {
            "category":"Professional",
            "type":"Services"
        }
    ],
    "sg:phone":"+1 508 935 0703",
    "sg:postcode":"01770",
    "sg:province":"MA",
    "sg:tags":[
        "establishment"
    ],
    "wof:name":"Tdd",
    "wof:placetype":"venue"
},
  "geometry": {"coordinates":[-71.381075,42.208005],"type":"Point"}
}