{
  "type": "Feature",
  "properties": {
    "addr:full":"70 James St Worcester MA 01603",
    "addr:housenumber":"70",
    "addr:postcode":"01603",
    "addr:street":"James St",
    "iso:country":"US",
    "sg:address":"70 James St",
    "sg:city":"Worcester",
    "sg:classifiers":[
        {
            "category":"Manufacturing",
            "subcategory":"Retail Goods",
            "type":"Manufacturing & Wholesale Goods"
        }
    ],
    "sg:phone":"+1 508 754 6580",
    "sg:postcode":"01603",
    "sg:province":"MA",
    "sg:tags":[
        "assembly",
        "fabricating"
    ],
    "wof:name":"Bill Cable Work Tech Svc",
    "wof:placetype":"venue"
},
  "geometry": {"coordinates":[-71.84970199999999,42.233116],"type":"Point"}
}