{
  "type": "Feature",
  "properties": {
    "addr:full":"15 Meadow Ln Southwick MA 01077",
    "addr:housenumber":"15",
    "addr:postcode":"01077",
    "addr:street":"Meadow Ln",
    "iso:country":"US",
    "sg:address":"15 Meadow Ln",
    "sg:city":"Southwick",
    "sg:classifiers":[
        {
            "category":"Building & Trades",
            "subcategory":"Plumbing",
            "type":"Services"
        }
    ],
    "sg:phone":"+1 413 525 9888",
    "sg:postcode":"01077",
    "sg:province":"MA",
    "sg:tags":[
        "plumber",
        "industrial",
        "contractors-commercial"
    ],
    "wof:name":"Eastern Mechanical Contractors",
    "wof:placetype":"venue"
},
  "geometry": {"coordinates":[-72.78721,42.081664],"type":"Point"}
}