{
  "type": "Feature",
  "properties": {
    "iso:country":"US",
    "sg:address":"31 St James Ave Ste 175",
    "sg:city":"Boston",
    "sg:classifiers":[
        {
            "category":"Food & Beverages",
            "subcategory":"Liquor & Beverages",
            "type":"Retail Goods"
        },
        {
            "category":"Food & Beverages",
            "subcategory":"Cheese",
            "type":"Retail Goods"
        }
    ],
    "sg:postcode":"02116",
    "sg:province":"MA",
    "sg:tags":[
        "shop",
        "beer",
        "spirit",
        "wine"
    ],
    "wof:name":"Bacco's Wine and Cheese",
    "wof:placetype":"venue"
},
  "geometry": {"coordinates":[-71.071619,42.350711],"type":"Point"}
}