{
  "type": "Feature",
  "properties": {
    "addr:full": "31 St James Ave Ste 175 Boston MA 02116",
    "addr:housenumber": "31",
    "addr:postcode": "02116",
    "addr:street": "St James Ave Ste 175",
    "iso:country": "US",
    "ovtr:label": "Bacco's Wine \u0026 Cheese, 31 St James Ave Boston MA US",
    "ovtr:similarity": 3.627746105194092,
    "sg:address": "31 St James Ave Ste 175",
    "sg:city": "Boston",
    "sg:classifiers": [
      {
        "category": "Food \u0026 Beverages",
        "subcategory": "Liquor \u0026 Beverages",
        "type": "Retail Goods"
      },
      {
        "category": "Food \u0026 Beverages",
        "subcategory": "Cheese",
        "type": "Retail Goods"
      }
    ],
    "sg:postcode": "02116",
    "sg:province": "MA",
    "sg:tags": [
      "shop",
      "beer",
      "spirit",
      "wine"
    ],
    "wof:name": "Bacco's Wine and Cheese",
    "wof:placetype": "venue"
  },
  "geometry": {"coordinates":[-71.071619,42.350711],"type":"Point"}
}
