{
  "type": "Feature",
  "properties": {
    "iso:country":"US",
    "sg:address":"94 Derby St Ste 279",
    "sg:city":"Hingham",
    "sg:classifiers":[
        {
            "category":"Restaurant",
            "type":"Food & Drink"
        }
    ],
    "sg:phone":"+1 781 749 1007",
    "sg:postcode":"02043",
    "sg:province":"MA",
    "sg:tags":[
        "grill",
        "seafood",
        "bar"
    ],
    "wof:name":"Burton's Grill Of Hingham",
    "wof:placetype":"venue"
},
  "geometry": {"coordinates":[-70.906549,42.180364],"type":"Point"}
}