{
  "type": "Feature",
  "properties": {
    "iso:country":"US",
    "sg:address":"59 Reading Street",
    "sg:city":"Roxbury",
    "sg:classifiers":[
        {
            "category":"Local Transit",
            "type":"Transportation"
        }
    ],
    "sg:phone":"+1 617 445 4334",
    "sg:postcode":"02119",
    "sg:province":"MA",
    "sg:tags":[
        "public"
    ],
    "wof:name":"Paul Revere Transportation",
    "wof:placetype":"venue"
},
  "geometry": {"coordinates":[-71.073589,42.330802],"type":"Point"}
}