{
  "type": "Feature",
  "properties": {
    "iso:country":"US",
    "sg:address":"90 Hamilton St",
    "sg:city":"Cambridge",
    "sg:classifiers":[
        {
            "category":"Communications",
            "subcategory":"Film & Video Production",
            "type":"Services"
        }
    ],
    "sg:phone":"+1 617 494 9965",
    "sg:postcode":"02139",
    "sg:province":"MA",
    "sg:tags":[
        "consultant",
        "audio"
    ],
    "wof:name":"Philip Clendaniel",
    "wof:placetype":"venue"
},
  "geometry": {"coordinates":[-71.10540399999999,42.357853],"type":"Point"}
}