{
  "type": "Feature",
  "properties": {
    "addr:full":"532 Franklin St Duxbury MA 02332",
    "addr:housenumber":"532",
    "addr:postcode":"02332",
    "addr:street":"Franklin St",
    "iso:country":"US",
    "sg:address":"532 Franklin St",
    "sg:city":"Duxbury",
    "sg:classifiers":[
        {
            "category":"Retail",
            "subcategory":"Animal Services",
            "type":"Services"
        }
    ],
    "sg:phone":"+1   ",
    "sg:postcode":"02332",
    "sg:province":"MA",
    "sg:tags":[
        "kennel"
    ],
    "wof:name":"Beresford Kennels",
    "wof:placetype":"venue"
},
  "geometry": {"coordinates":[-70.73567,42.065434],"type":"Point"}
}