{
  "type": "Feature",
  "properties": {
    "iso:country":"US",
    "sg:address":"18 Winter St",
    "sg:city":"Salem",
    "sg:classifiers":[
        {
            "category":"Home & Garden",
            "subcategory":"Hardware",
            "type":"Retail Goods"
        }
    ],
    "sg:phone":"+1 978 745 1033",
    "sg:postcode":"01970",
    "sg:province":"MA",
    "sg:tags":[
        "water",
        "equipment",
        "filtration",
        "purification"
    ],
    "wof:name":"Charnigo, Michael",
    "wof:placetype":"venue"
},
  "geometry": {"coordinates":[-70.89019399999999,42.525781],"type":"Point"}
}