{
  "type": "Feature",
  "properties": {
    "addr:full": "18 Winter St Salem MA 01970",
    "addr:housenumber": "18",
    "addr:postcode": "01970",
    "addr:street": "Winter St",
    "iso:country": "US",
    "sg:address": "18 Winter St",
    "sg:city": "Salem",
    "sg:classifiers": [
      {
        "category": "Home \u0026 Garden",
        "subcategory": "Hardware",
        "type": "Retail Goods"
      }
    ],
    "sg:phone": "+1 978 745 1033",
    "sg:postcode": "01970",
    "sg:province": "MA",
    "sg:tags": [
      "water",
      "equipment",
      "filtration",
      "purification"
    ],
    "wof:name": "Charnigo, Michael",
    "wof:placetype": "venue"
  },
  "geometry": {"coordinates":[-70.890194,42.525781],"type":"Point"}
}
