{
  "type": "Feature",
  "properties": {
    "addr:full":"71 Cross St Franklin MA 02038",
    "addr:housenumber":"71",
    "addr:postcode":"02038",
    "addr:street":"Cross St",
    "iso:country":"US",
    "sg:address":"71 Cross St",
    "sg:city":"Franklin",
    "sg:classifiers":[
        {
            "category":"Communications",
            "subcategory":"Film & Video Production",
            "type":"Services"
        }
    ],
    "sg:phone":"+1 508 528 4297",
    "sg:postcode":"02038",
    "sg:province":"MA",
    "sg:tags":[
        "taping"
    ],
    "wof:name":"Page Video Productions",
    "wof:placetype":"venue"
},
  "geometry": {"coordinates":[-71.392796,42.080177],"type":"Point"}
}