{
  "type": "Feature",
  "properties": {
    "addr:full": "29 Depot St Douglas MA 01516",
    "addr:housenumber": "29",
    "addr:postcode": "01516",
    "addr:street": "Depot St",
    "iso:country": "US",
    "sg:address": "29 Depot St",
    "sg:city": "Douglas",
    "sg:classifiers": [
      {
        "category": "Government",
        "subcategory": "Office",
        "type": "Public Place"
      }
    ],
    "sg:phone": "+1 508 476 4010",
    "sg:postcode": "01516",
    "sg:province": "MA",
    "sg:tags": [
      "village"
    ],
    "wof:name": "Douglas Treasurer's Office",
    "wof:placetype": "venue"
  },
  "geometry": {"coordinates":[-71.709448,42.06536],"type":"Point"}
}
