{
  "type": "Feature",
  "properties": {
    "iso:country":"US",
    "sg:address":"29 Depot St",
    "sg:city":"Douglas",
    "sg:classifiers":[
        {
            "category":"Government",
            "subcategory":"Office",
            "type":"Public Place"
        }
    ],
    "sg:phone":"+1 508 476 4010",
    "sg:postcode":"01516",
    "sg:province":"MA",
    "sg:tags":[
        "village"
    ],
    "wof:name":"Douglas Treasurer's Office",
    "wof:placetype":"venue"
},
  "geometry": {"coordinates":[-71.70944799999999,42.06536],"type":"Point"}
}