{
  "type": "Feature",
  "properties": {
    "addr:full":"4 Columbus Ter Newton MA 02461",
    "addr:housenumber":"4",
    "addr:postcode":"02461",
    "addr:street":"Columbus Ter",
    "iso:country":"US",
    "sg:address":"4 Columbus Ter",
    "sg:city":"Newton",
    "sg:classifiers":[
        {
            "category":"Professional",
            "subcategory":"Management & Consulting",
            "type":"Services"
        }
    ],
    "sg:phone":"+1 617 332 3660",
    "sg:postcode":"02461",
    "sg:province":"MA",
    "sg:tags":[
        "marketing",
        "program"
    ],
    "wof:name":"Mercer Marketing",
    "wof:placetype":"venue"
},
  "geometry": {"coordinates":[-71.20815,42.323819],"type":"Point"}
}