{
  "type": "Feature",
  "properties": {
    "addr:full": "810 Meadow St Chicopee MA 01013",
    "addr:housenumber": "810",
    "addr:postcode": "01013",
    "addr:street": "Meadow St",
    "iso:country": "US",
    "sg:address": "810 Meadow St",
    "sg:city": "Chicopee",
    "sg:classifiers": [
      {
        "category": "Autos \u0026 Motor Vehicles",
        "subcategory": "Fuel \u0026 Gas Station",
        "type": "Retail Goods"
      }
    ],
    "sg:phone": "+1 413 592 2328",
    "sg:postcode": "01013",
    "sg:province": "MA",
    "sg:tags": [
      "oil"
    ],
    "wof:name": "Sonoco A Plus",
    "wof:placetype": "venue"
  },
  "geometry": {"coordinates":[-72.614041,42.164185],"type":"Point"}
}
