{
  "type": "Feature",
  "properties": {
    "addr:full": "158 Commercial St Provincetown MA 02657",
    "addr:housenumber": "158",
    "addr:postcode": "02657",
    "addr:street": "Commercial St",
    "iso:country": "US",
    "sg:address": "158 Commercial St",
    "sg:city": "Provincetown",
    "sg:classifiers": [
      {
        "category": "Retail",
        "subcategory": "Repair Shop",
        "type": "Services"
      }
    ],
    "sg:phone": "+1   ",
    "sg:postcode": "02657",
    "sg:province": "MA",
    "sg:tags": [
      "picture",
      "framing",
      "custom"
    ],
    "wof:name": "Allerton Framing",
    "wof:placetype": "venue"
  },
  "geometry": {"coordinates":[-70.190252,42.047334],"type":"Point"}
}
