{
  "type": "Feature",
  "properties": {
    "iso:country":"US",
    "sg:address":"1771 Riverdale St",
    "sg:city":"West Springfield",
    "sg:classifiers":[
        {
            "category":"Professional",
            "subcategory":"Business Services",
            "type":"Services"
        }
    ],
    "sg:phone":"+1 413 525 5762",
    "sg:postcode":"01089",
    "sg:province":"MA",
    "sg:tags":[
        "interior",
        "consultant",
        "design",
        "decorator"
    ],
    "wof:name":"Janet Lyon Interiors",
    "wof:placetype":"venue"
},
  "geometry": {"coordinates":[-72.630498,42.150219],"type":"Point"}
}