{
  "type": "Feature",
  "properties": {
    "iso:country":"US",
    "sg:address":"1257 Worcester Rd",
    "sg:city":"Framingham",
    "sg:classifiers":[
        {
            "category":"Building & Trades",
            "subcategory":"Construction",
            "type":"Services"
        }
    ],
    "sg:phone":"+1 508 315 3195",
    "sg:postcode":"01701",
    "sg:province":"MA",
    "sg:tags":[
        "earth",
        "home"
    ],
    "wof:name":"Metrowest Contracting",
    "wof:placetype":"venue"
},
  "geometry": {"coordinates":[-71.447891,42.29845],"type":"Point"}
}