{
  "type": "Feature",
  "properties": {
    "iso:country":"US",
    "sg:address":"63 Manchester St",
    "sg:city":"Leominster",
    "sg:classifiers":[
        {
            "category":"Professional",
            "subcategory":"Business Services",
            "type":"Services"
        }
    ],
    "sg:phone":"+1   ",
    "sg:postcode":"01453",
    "sg:province":"MA",
    "wof:name":"Marcus Lewis Enterprises Inc",
    "wof:placetype":"venue"
},
  "geometry": {"coordinates":[-71.762997,42.516129],"type":"Point"}
}