{
  "type": "Feature",
  "properties": {
    "iso:country":"US",
    "sg:address":"77 Massachusetts Avenue Room 7-100",
    "sg:city":"Cambridge",
    "sg:classifiers":[
        {
            "category":"Restaurant",
            "type":"Food & Drink"
        },
        {
            "category":"Education",
            "subcategory":"School",
            "type":"Public Place"
        }
    ],
    "sg:postcode":"02139",
    "sg:province":"MA",
    "sg:tags":[
        "flavor",
        "local"
    ],
    "sg:website":"web.mit.edu/puzzle",
    "wof:name":"Mystery Hunt",
    "wof:placetype":"venue"
},
  "geometry": {"coordinates":[-71.093597,42.359299],"type":"Point"}
}