{
  "type": "Feature",
  "properties": {
    "addr:full":"174 Winter St Haverhill MA 01830",
    "addr:housenumber":"174",
    "addr:postcode":"01830",
    "addr:street":"Winter St",
    "iso:country":"US",
    "sg:address":"174 Winter St",
    "sg:city":"Haverhill",
    "sg:classifiers":[
        {
            "category":"Autos & Motor Vehicles",
            "subcategory":"Fuel & Gas Station",
            "type":"Retail Goods"
        }
    ],
    "sg:phone":"+1   ",
    "sg:postcode":"01830",
    "sg:province":"MA",
    "sg:tags":[
        "station",
        "gasoline"
    ],
    "wof:name":"Kosmes Inspection Station",
    "wof:placetype":"venue"
},
  "geometry": {"coordinates":[-71.083698,42.7777],"type":"Point"}
}