{
  "type": "Feature",
  "properties": {
    "addr:full":"1160 Beacon St Brookline MA 02446",
    "addr:housenumber":"1160",
    "addr:postcode":"02446",
    "addr:street":"Beacon St",
    "iso:country":"US",
    "sg:address":"1160 Beacon St",
    "sg:city":"Brookline",
    "sg:classifiers":[
        {
            "category":"Real Estate",
            "subcategory":"Real Estate Operator",
            "type":"Services"
        }
    ],
    "sg:phone":"+1 617 232 5840",
    "sg:postcode":"02446",
    "sg:province":"MA",
    "sg:tags":[
        "condominium"
    ],
    "wof:name":"1160 Beacon Street Condominium",
    "wof:placetype":"venue"
},
  "geometry": {"coordinates":[-71.113787,42.34438],"type":"Point"}
}