{
  "type": "Feature",
  "properties": {
    "addr:full":"398 Deerfield St Greenfield MA 01301",
    "addr:housenumber":"398",
    "addr:postcode":"01301",
    "addr:street":"Deerfield St",
    "iso:country":"US",
    "sg:address":"398 Deerfield St",
    "sg:city":"Greenfield",
    "sg:classifiers":[
        {
            "category":"Sports & Exercise",
            "subcategory":"Golf",
            "type":"Entertainment"
        }
    ],
    "sg:phone":"+1 413 773 9047",
    "sg:postcode":"01301",
    "sg:province":"MA",
    "sg:tags":[
        "course"
    ],
    "wof:name":"Meadows Golf Course",
    "wof:placetype":"venue"
},
  "geometry": {"coordinates":[-72.594039,42.571861],"type":"Point"}
}