{
  "type": "Feature",
  "properties": {
    "addr:full":"719 Washington St South Easton MA 02375",
    "addr:housenumber":"719",
    "addr:postcode":"02375",
    "addr:street":"Washington St",
    "iso:country":"US",
    "sg:address":"719 Washington St",
    "sg:city":"South Easton",
    "sg:classifiers":[
        {
            "category":"Building & Trades",
            "subcategory":"Construction",
            "type":"Services"
        }
    ],
    "sg:phone":"+1 508 238 6494",
    "sg:postcode":"02375",
    "sg:province":"MA",
    "sg:tags":[
        "roofing",
        "contractor"
    ],
    "wof:name":"John W Andrews",
    "wof:placetype":"venue"
},
  "geometry": {"coordinates":[-71.07540899999999,42.038442],"type":"Point"}
}