{
  "type": "Feature",
  "properties": {
    "addr:full": "355 Lowell St Peabody MA 01960",
    "addr:housenumber": "355",
    "addr:postcode": "01960",
    "addr:street": "Lowell St",
    "iso:country": "US",
    "sg:address": "355 Lowell St",
    "sg:city": "Peabody",
    "sg:classifiers": [
      {
        "category": "Health Services",
        "subcategory": "Doctor",
        "type": "Services"
      }
    ],
    "sg:phone": "+1 978 531 2185",
    "sg:postcode": "01960",
    "sg:province": "MA",
    "sg:tags": [
      "dentist"
    ],
    "wof:name": "Spiro Saati DDS",
    "wof:placetype": "venue"
  },
  "geometry": {"coordinates":[-70.955142,42.534872],"type":"Point"}
}
