{
  "type": "Feature",
  "properties": {
    "iso:country":"US",
    "sg:address":"252 Bridge St",
    "sg:city":"Weymouth",
    "sg:classifiers":[
        {
            "category":"Shopping",
            "subcategory":"Computers & Home Electronics",
            "type":"Retail Goods"
        }
    ],
    "sg:phone":"+1 781 337 4300",
    "sg:postcode":"02191",
    "sg:province":"MA",
    "sg:tags":[
        "audio"
    ],
    "wof:name":"Audio Techniques",
    "wof:placetype":"venue"
},
  "geometry": {"coordinates":[-70.95489999999999,42.24272],"type":"Point"}
}