{
  "type": "Feature",
  "properties": {
    "iso:country":"US",
    "sg:address":"256 Geneva Ave",
    "sg:city":"Dorchester",
    "sg:classifiers":[
        {
            "category":"Freight",
            "type":"Transportation"
        }
    ],
    "sg:phone":"+1 617 430 7741",
    "sg:postcode":"02121",
    "sg:province":"MA",
    "sg:tags":[
        "mover"
    ],
    "wof:name":"Mover",
    "wof:placetype":"venue"
},
  "geometry": {"coordinates":[-71.072563,42.304536],"type":"Point"}
}