{
  "type": "Feature",
  "properties": {
    "iso:country":"US",
    "sg:address":"25 Granby St",
    "sg:city":"East Longmeadow",
    "sg:classifiers":[
        {
            "category":"Professional",
            "subcategory":"Engineering",
            "type":"Services"
        }
    ],
    "sg:phone":"+1 413 731 9898",
    "sg:postcode":"01028",
    "sg:province":"MA",
    "sg:tags":[
        "engineer"
    ],
    "wof:name":"Pioneer Environmental Inc",
    "wof:placetype":"venue"
},
  "geometry": {"coordinates":[-72.53722999999999,42.080792],"type":"Point"}
}