{
  "type": "Feature",
  "properties": {
    "iso:country":"US",
    "sg:address":"2 Morningside Dr",
    "sg:city":"Swampscott",
    "sg:classifiers":[
        {
            "category":"Wholesale",
            "subcategory":"Non-durable Goods",
            "type":"Manufacturing & Wholesale Goods"
        }
    ],
    "sg:phone":"+1 781 598 3600",
    "sg:postcode":"01907",
    "sg:province":"MA",
    "sg:tags":[
        "advertising"
    ],
    "wof:name":"Edward Baum Co",
    "wof:placetype":"venue"
},
  "geometry": {"coordinates":[-70.910864,42.478721],"type":"Point"}
}