{
  "type": "Feature",
  "properties": {
    "addr:full":"1180 Beacon Street Brookline MA 02446",
    "addr:housenumber":"1180",
    "addr:postcode":"02446",
    "addr:street":"Beacon Street",
    "iso:country":"US",
    "sg:address":"1180 Beacon Street",
    "sg:city":"Brookline",
    "sg:classifiers":[
        {
            "category":"Health Services",
            "subcategory":"Doctor",
            "type":"Services"
        },
        {
            "category":"Sports & Exercise",
            "subcategory":"Gym",
            "type":"Entertainment"
        }
    ],
    "sg:phone":"+1 617 232 2915",
    "sg:postcode":"02446",
    "sg:province":"MA",
    "sg:tags":[
        "trainer"
    ],
    "wof:name":"Zuckerman Pamela M MD",
    "wof:placetype":"venue"
},
  "geometry": {"coordinates":[-71.114616,42.344099],"type":"Point"}
}