{
  "type": "Feature",
  "properties": {
    "addr:full": "70 Rock St Lowell MA 01854",
    "addr:housenumber": "70",
    "addr:postcode": "01854",
    "addr:street": "Rock St",
    "iso:country": "US",
    "sg:address": "70 Rock St",
    "sg:city": "Lowell",
    "sg:classifiers": [
      {
        "category": "Retail",
        "subcategory": "Auto Repair",
        "type": "Services"
      }
    ],
    "sg:phone": "+1 978 970 2828",
    "sg:postcode": "01854",
    "sg:province": "MA",
    "sg:tags": [
      "repairing",
      "automobile"
    ],
    "wof:name": "Luis' Garage",
    "wof:placetype": "venue"
  },
  "geometry": {"coordinates":[-71.319744,42.641728],"type":"Point"}
}
