{
  "type": "Feature",
  "properties": {
    "addr:full": "4 Muzzey Street Lexington MA 02421",
    "addr:housenumber": "4",
    "addr:postcode": "02421",
    "addr:street": "Muzzey Street",
    "iso:country": "US",
    "sg:address": "4 Muzzey Street",
    "sg:city": "Lexington",
    "sg:classifiers": [
      {
        "category": "Sports \u0026 Exercise",
        "subcategory": "Gym",
        "type": "Entertainment"
      }
    ],
    "sg:phone": "+1 781 862 3219",
    "sg:postcode": "02421",
    "sg:province": "MA",
    "sg:tags": [
      "trainer"
    ],
    "wof:name": "Fahey Jean Psycholgst",
    "wof:placetype": "venue"
  },
  "geometry": {"coordinates":[-71.228582,42.447919],"type":"Point"}
}
