{
  "type": "Feature",
  "properties": {
    "iso:country":"US",
    "sg:address":"20 Park Plz",
    "sg:city":"Boston",
    "sg:classifiers":[
        {
            "category":"Professional",
            "subcategory":"Management & Consulting",
            "type":"Services"
        }
    ],
    "sg:phone":"+1 617 338 7171",
    "sg:postcode":"02116",
    "sg:province":"MA",
    "sg:tags":[
        "consultant",
        "educational"
    ],
    "wof:name":"Center for Educational Documentation",
    "wof:placetype":"venue"
},
  "geometry": {"coordinates":[-71.068904,42.351601],"type":"Point"}
}