{
  "type": "Feature",
  "properties": {
    "addr:full":"800 Main St Holden MA 01520",
    "addr:housenumber":"800",
    "addr:postcode":"01520",
    "addr:street":"Main St",
    "iso:country":"US",
    "sg:address":"800 Main St",
    "sg:city":"Holden",
    "sg:classifiers":[
        {
            "category":"Real Estate",
            "subcategory":"Real Estate Agent",
            "type":"Services"
        }
    ],
    "sg:phone":"+1 508 829 3334",
    "sg:postcode":"01520",
    "sg:province":"MA",
    "wof:name":"Glen Echo Realty",
    "wof:placetype":"venue"
},
  "geometry": {"coordinates":[-71.84477,42.342181],"type":"Point"}
}