{
  "type": "Feature",
  "properties": {
    "iso:country":"US",
    "sg:address":"4 Station Street",
    "sg:city":"Brookline",
    "sg:phone":"+1 857 217 0400",
    "sg:postcode":"02445",
    "sg:province":"MA",
    "sg:website":"http://www.pluslocksmith.com",
    "wof:name":"Plus Locksmith Brookline MA",
    "wof:placetype":"venue"
},
  "geometry": {"coordinates":[-71.118156,42.332256],"type":"Point"}
}