{
  "type": "Feature",
  "properties": {
    "iso:country":"US",
    "sg:address":"149 E Falmouth Hwy",
    "sg:city":"East Falmouth",
    "sg:classifiers":[
        {
            "category":"Building & Trades",
            "subcategory":"Construction",
            "type":"Services"
        }
    ],
    "sg:phone":"+1   ",
    "sg:postcode":"02536",
    "sg:province":"MA",
    "sg:tags":[
        "house"
    ],
    "wof:name":"Monteiro Builders",
    "wof:placetype":"venue"
},
  "geometry": {"coordinates":[-70.568321,41.578573],"type":"Point"}
}