{
  "type": "Feature",
  "properties": {
    "iso:country":"US",
    "sg:address":"1250 Main St",
    "sg:city":"Waltham",
    "sg:classifiers":[
        {
            "category":"Professional",
            "type":"Services"
        }
    ],
    "sg:phone":"+1 781 891 1200",
    "sg:postcode":"02451",
    "sg:province":"MA",
    "sg:tags":[
        "establishment"
    ],
    "wof:name":"Corporate Mediators",
    "wof:placetype":"venue"
},
  "geometry": {"coordinates":[-71.261889,42.376404],"type":"Point"}
}