{
  "type": "Feature",
  "properties": {
    "iso:country":"US",
    "sg:address":"1 Mad Brook Rd",
    "sg:city":"North Brookfield",
    "sg:classifiers":[
        {
            "category":"Professional",
            "type":"Services"
        }
    ],
    "sg:phone":"+1 508 867 4422",
    "sg:postcode":"01535",
    "sg:province":"MA",
    "sg:tags":[
        "establishment"
    ],
    "wof:name":"Knobby Kneeds",
    "wof:placetype":"venue"
},
  "geometry": {"coordinates":[-72.05765100000001,42.288015],"type":"Point"}
}