{
  "type": "Feature",
  "properties": {
    "addr:full":"208 Holland Rd Fiskdale MA 01518",
    "addr:housenumber":"208",
    "addr:postcode":"01518",
    "addr:street":"Holland Rd",
    "iso:country":"US",
    "sg:address":"208 Holland Rd",
    "sg:city":"Fiskdale",
    "sg:classifiers":[
        {
            "category":"Building & Trades",
            "subcategory":"Equipment Rental",
            "type":"Services"
        }
    ],
    "sg:phone":"+1 413 245 3882",
    "sg:postcode":"01518",
    "sg:province":"MA",
    "sg:tags":[
        "leasing"
    ],
    "wof:name":"R J Poirier Heavy Equipment",
    "wof:placetype":"venue"
},
  "geometry": {"coordinates":[-72.12738,42.092378],"type":"Point"}
}