{
  "type": "Feature",
  "properties": {
    "iso:country":"US",
    "sg:address":"1164 Broadway 1164 Broadway",
    "sg:city":"Somerville",
    "sg:classifiers":[
        {
            "category":"Retail",
            "subcategory":"Laundry & Dry Cleaning",
            "type":"Services"
        }
    ],
    "sg:phone":"+1 617 623 9107",
    "sg:postcode":"02144",
    "sg:province":"MA",
    "sg:website":"www.hawkcleaners.com",
    "wof:name":"Hawk Cleaners",
    "wof:placetype":"venue"
},
  "geometry": {"coordinates":[-71.127622,42.403436],"type":"Point"}
}