{
  "type": "Feature",
  "properties": {
    "iso:country":"US",
    "sg:address":"20 Cabot Rd",
    "sg:city":"Woburn",
    "sg:classifiers":[
        {
            "category":"Retail",
            "subcategory":"Veterinary Services",
            "type":"Services"
        }
    ],
    "sg:phone":"+1 781 932 5802",
    "sg:postcode":"01801",
    "sg:province":"MA",
    "sg:tags":[
        "veterinarian"
    ],
    "sg:website":"www.InTownMassVet.com",
    "wof:name":"Massachusetts Veterinary Referral Hospital",
    "wof:placetype":"venue"
},
  "geometry": {"coordinates":[-71.13388399999999,42.509594],"type":"Point"}
}