{
  "type": "Feature",
  "properties": {
    "addr:full": "20 Cabot Rd Woburn MA 01801",
    "addr:housenumber": "20",
    "addr:postcode": "01801",
    "addr:street": "Cabot Rd",
    "iso:country": "US",
    "ovtr:label": "Massachusetts Veterinary Referral Hospital, 20 Cabot Rd Woburn MA US",
    "ovtr:similarity": 2.1375958919525146,
    "sg:address": "20 Cabot Rd",
    "sg:city": "Woburn",
    "sg:classifiers": [
      {
        "category": "Retail",
        "subcategory": "Veterinary Services",
        "type": "Services"
      }
    ],
    "sg:phone": "+1 781 932 5802",
    "sg:postcode": "01801",
    "sg:province": "MA",
    "sg:tags": [
      "veterinarian"
    ],
    "sg:website": "www.InTownMassVet.com",
    "wof:name": "Massachusetts Veterinary Referral Hospital",
    "wof:placetype": "venue"
  },
  "geometry": {"coordinates":[-71.133884,42.509594],"type":"Point"}
}
