{
  "type": "Feature",
  "properties": {
    "addr:full": "411 N Washington St North Attleboro MA 02760",
    "addr:housenumber": "411",
    "addr:postcode": "02760",
    "addr:street": "N Washington St",
    "iso:country": "US",
    "sg:address": "411 N Washington St",
    "sg:city": "North Attleboro",
    "sg:classifiers": [
      {
        "category": "Autos \u0026 Motor Vehicles",
        "subcategory": "Auto Supplies",
        "type": "Retail Goods"
      }
    ],
    "sg:phone": "+1 508 699 2476",
    "sg:postcode": "02760",
    "sg:province": "MA",
    "sg:tags": [
      "automobile",
      "parts"
    ],
    "wof:name": "Allied Auto Parts Co Inc",
    "wof:placetype": "venue"
  },
  "geometry": {"coordinates":[-71.32941,41.993538],"type":"Point"}
}
