{
  "type": "Feature",
  "properties": {
    "iso:country":"US",
    "sg:address":"411 N Washington St",
    "sg:city":"North Attleboro",
    "sg:classifiers":[
        {
            "category":"Autos & Motor Vehicles",
            "subcategory":"Auto Supplies",
            "type":"Retail Goods"
        }
    ],
    "sg:phone":"+1 508 699 2476",
    "sg:postcode":"02760",
    "sg:province":"MA",
    "sg:tags":[
        "automobile",
        "parts"
    ],
    "wof:name":"Allied Auto Parts Co Inc",
    "wof:placetype":"venue"
},
  "geometry": {"coordinates":[-71.32941,41.993538],"type":"Point"}
}