{
  "type": "Feature",
  "properties": {
    "iso:country":"US",
    "sg:address":"1196 River St",
    "sg:city":"Hyde Park",
    "sg:classifiers":[
        {
            "category":"Professional",
            "type":"Services"
        }
    ],
    "sg:phone":"+1 617 361 6849",
    "sg:postcode":"02136",
    "sg:province":"MA",
    "sg:tags":[
        "establishment"
    ],
    "wof:name":"Hyde Park Rates Line 1196",
    "wof:placetype":"venue"
},
  "geometry": {"coordinates":[-71.121379,42.255842],"type":"Point"}
}