{
  "type": "Feature",
  "properties": {
    "addr:full": "1196 River St Hyde Park MA 02136",
    "addr:housenumber": "1196",
    "addr:postcode": "02136",
    "addr:street": "River St",
    "iso:country": "US",
    "sg:address": "1196 River St",
    "sg:city": "Hyde Park",
    "sg:classifiers": [
      {
        "category": "Professional",
        "type": "Services"
      }
    ],
    "sg:phone": "+1 617 361 6849",
    "sg:postcode": "02136",
    "sg:province": "MA",
    "sg:tags": [
      "establishment"
    ],
    "wof:name": "Hyde Park Rates Line 1196",
    "wof:placetype": "venue"
  },
  "geometry": {"coordinates":[-71.121379,42.255842],"type":"Point"}
}
