{
  "type": "Feature",
  "properties": {
    "addr:full": "71 West St Medfield MA 02052",
    "addr:housenumber": "71",
    "addr:postcode": "02052",
    "addr:street": "West St",
    "iso:country": "US",
    "sg:address": "71 West St",
    "sg:city": "Medfield",
    "sg:classifiers": [
      {
        "category": "Wholesale",
        "subcategory": "Painting Supplies",
        "type": "Manufacturing \u0026 Wholesale Goods"
      }
    ],
    "sg:phone": "+1 508 359 8003",
    "sg:postcode": "02052",
    "sg:province": "MA",
    "sg:tags": [
      "equipment",
      "painter"
    ],
    "wof:name": "Paint Project",
    "wof:placetype": "venue"
  },
  "geometry": {"coordinates":[-71.325059,42.191526],"type":"Point"}
}
