{
  "type": "Feature",
  "properties": {
    "iso:country":"US",
    "sg:address":"71 West St",
    "sg:city":"Medfield",
    "sg:classifiers":[
        {
            "category":"Wholesale",
            "subcategory":"Painting Supplies",
            "type":"Manufacturing & Wholesale Goods"
        }
    ],
    "sg:phone":"+1 508 359 8003",
    "sg:postcode":"02052",
    "sg:province":"MA",
    "sg:tags":[
        "equipment",
        "painter"
    ],
    "wof:name":"Paint Project",
    "wof:placetype":"venue"
},
  "geometry": {"coordinates":[-71.325059,42.191526],"type":"Point"}
}