{
  "type": "Feature",
  "properties": {
    "iso:country":"US",
    "sg:address":"8 Palomino Way",
    "sg:city":"Walpole",
    "sg:classifiers":[
        {
            "category":"Building & Trades",
            "subcategory":"Electrical",
            "type":"Services"
        }
    ],
    "sg:phone":"+1 508 850 7999",
    "sg:postcode":"02081",
    "sg:province":"MA",
    "sg:tags":[
        "electric",
        "contractor"
    ],
    "wof:name":"Electrical Solutions Inc",
    "wof:placetype":"venue"
},
  "geometry": {"coordinates":[-71.223715,42.137531],"type":"Point"}
}