{
  "type": "Feature",
  "properties": {
    "addr:full":"321 Nashua Rd Billerica MA 01821",
    "addr:housenumber":"321",
    "addr:postcode":"01821",
    "addr:street":"Nashua Rd",
    "iso:country":"US",
    "sg:address":"321 Nashua Rd",
    "sg:city":"Billerica",
    "sg:classifiers":[
        {
            "category":"Building & Trades",
            "subcategory":"Plumbing",
            "type":"Services"
        }
    ],
    "sg:phone":"+1 978 671 5050",
    "sg:postcode":"01821",
    "sg:province":"MA",
    "sg:tags":[
        "conditioning",
        "air",
        "system",
        "contractor"
    ],
    "wof:name":"S G Mechanical",
    "wof:placetype":"venue"
},
  "geometry": {"coordinates":[-71.29190199999999,42.527021],"type":"Point"}
}