{
  "type": "Feature",
  "properties": {
    "addr:full": "964 Broadway Somerville MA 02144",
    "addr:housenumber": "964",
    "addr:postcode": "02144",
    "addr:street": "Broadway",
    "iso:country": "US",
    "sg:address": "964 Broadway",
    "sg:city": "Somerville",
    "sg:classifiers": [
      {
        "category": "Insurance",
        "subcategory": "Insurance Agent",
        "type": "Services"
      }
    ],
    "sg:phone": "+1 617 628 9470",
    "sg:postcode": "02144",
    "sg:province": "MA",
    "wof:name": "Registry Running Service",
    "wof:placetype": "venue"
  },
  "geometry": {"coordinates":[-71.121081,42.401294],"type":"Point"}
}
