{
  "type": "Feature",
  "properties": {
    "addr:full": "36 Commercial Dr Hampden MA 01036",
    "addr:housenumber": "36",
    "addr:postcode": "01036",
    "addr:street": "Commercial Dr",
    "iso:country": "US",
    "sg:address": "36 Commercial Dr",
    "sg:city": "Hampden",
    "sg:classifiers": [
      {
        "category": "Shopping",
        "type": "Retail Goods"
      }
    ],
    "sg:phone": "+1 413 566 3824",
    "sg:postcode": "01036",
    "sg:province": "MA",
    "sg:tags": [
      "awning",
      "canopy"
    ],
    "sg:website": "www.private-garden.com",
    "wof:name": "Hampden Structural Systems",
    "wof:placetype": "venue"
  },
  "geometry": {"coordinates":[-72.450667,42.060387],"type":"Point"}
}
