{
  "type": "Feature",
  "properties": {
    "iso:country":"US",
    "sg:address":"10 Mazzeo Dr",
    "sg:city":"Randolph",
    "sg:classifiers":[
        {
            "category":"Utilities",
            "type":"Services"
        }
    ],
    "sg:phone":"+1 781 986 1331",
    "sg:postcode":"02368",
    "sg:province":"MA",
    "sg:tags":[
        "provider",
        "internet"
    ],
    "wof:name":"Pleasure Ventures Inc - CLOSED",
    "wof:placetype":"venue"
},
  "geometry": {"coordinates":[-71.056099,42.165501],"type":"Point"}
}