{
  "type": "Feature",
  "properties": {
    "iso:country":"US",
    "sg:address":"541 Main St",
    "sg:city":"South Weymouth",
    "sg:classifiers":[
        {
            "category":"Real Estate",
            "subcategory":"Real Estate Agent",
            "type":"Services"
        }
    ],
    "sg:phone":"+1 781 337 3310",
    "sg:postcode":"02190",
    "sg:province":"MA",
    "sg:tags":[
        "management"
    ],
    "wof:name":"WND Management LLC",
    "wof:placetype":"venue"
},
  "geometry": {"coordinates":[-70.955613,42.187754],"type":"Point"}
}