{
  "type": "Feature",
  "properties": {
    "addr:full": "6 Kingdom Way Saugus MA 01906",
    "addr:housenumber": "6",
    "addr:postcode": "01906",
    "addr:street": "Kingdom Way",
    "iso:country": "US",
    "sg:address": "6 Kingdom Way",
    "sg:city": "Saugus",
    "sg:classifiers": [
      {
        "category": "Organizations",
        "subcategory": "Religious Organization",
        "type": "Services"
      }
    ],
    "sg:phone": "+1   ",
    "sg:postcode": "01906",
    "sg:province": "MA",
    "wof:name": "Saugus Kingdm Hall Jehovahs W",
    "wof:placetype": "venue"
  },
  "geometry": {"coordinates":[-71.037711,42.474772],"type":"Point"}
}
