{
  "type": "Feature",
  "properties": {
    "addr:full": "96 Russett Road West Roxbury MA 02132",
    "addr:housenumber": "96",
    "addr:postcode": "02132",
    "addr:street": "Russett Road",
    "iso:country": "US",
    "sg:address": "96 Russett Road",
    "sg:city": "West Roxbury",
    "sg:classifiers": [
      {
        "category": "Sports \u0026 Exercise",
        "subcategory": "Gym",
        "type": "Entertainment"
      },
      {
        "category": "Arena",
        "subcategory": "Sports Club",
        "type": "Entertainment"
      }
    ],
    "sg:phone": "+1 617 323 7666",
    "sg:postcode": "02132",
    "sg:province": "MA",
    "sg:tags": [
      "trainer",
      "martial art"
    ],
    "wof:name": "Dorri Li Fitness",
    "wof:placetype": "venue"
  },
  "geometry": {"coordinates":[-71.150824,42.291352],"type":"Point"}
}
