{
  "type": "Feature",
  "properties": {
    "iso:country":"US",
    "sg:address":"39 Phillips Dr",
    "sg:city":"Newburyport",
    "sg:classifiers":[
        {
            "category":"Shopping",
            "subcategory":"Crafts & Fabrics",
            "type":"Retail Goods"
        }
    ],
    "sg:phone":"+1 978 465 5003",
    "sg:postcode":"01950",
    "sg:province":"MA",
    "sg:tags":[
        "art",
        "supply"
    ],
    "wof:name":"Craft Basket the - CLOSED",
    "wof:placetype":"venue"
},
  "geometry": {"coordinates":[-70.92150100000001,42.816502],"type":"Point"}
}