{
  "type": "Feature",
  "properties": {
    "addr:full": "39 Phillips Dr Newburyport MA 01950",
    "addr:housenumber": "39",
    "addr:postcode": "01950",
    "addr:street": "Phillips Dr",
    "iso:country": "US",
    "sg:address": "39 Phillips Dr",
    "sg:city": "Newburyport",
    "sg:classifiers": [
      {
        "category": "Shopping",
        "subcategory": "Crafts \u0026 Fabrics",
        "type": "Retail Goods"
      }
    ],
    "sg:phone": "+1 978 465 5003",
    "sg:postcode": "01950",
    "sg:province": "MA",
    "sg:tags": [
      "art",
      "supply"
    ],
    "wof:name": "Craft Basket the - CLOSED",
    "wof:placetype": "venue"
  },
  "geometry": {"coordinates":[-70.921501,42.816502],"type":"Point"}
}
