{
  "type": "Feature",
  "properties": {
    "iso:country":"US",
    "sg:address":"29 Goshen Rd",
    "sg:city":"Williamsburg",
    "sg:classifiers":[
        {
            "category":"Autos & Motor Vehicles",
            "subcategory":"Auto Supplies",
            "type":"Retail Goods"
        }
    ],
    "sg:phone":"+1 413 268 3051",
    "sg:postcode":"01096",
    "sg:province":"MA",
    "sg:tags":[
        "automobile",
        "parts"
    ],
    "wof:name":"JMS Auto Parts",
    "wof:placetype":"venue"
},
  "geometry": {"coordinates":[-72.750305,42.404238],"type":"Point"}
}