{
  "type": "Feature",
  "properties": {
    "addr:full":"3 Kearley Ln Wakefield MA 01880",
    "addr:housenumber":"3",
    "addr:postcode":"01880",
    "addr:street":"Kearley Ln",
    "iso:country":"US",
    "sg:address":"3 Kearley Ln",
    "sg:city":"Wakefield",
    "sg:classifiers":[
        {
            "category":"Shopping",
            "subcategory":"Bicycles & Sporting Goods",
            "type":"Retail Goods"
        }
    ],
    "sg:phone":"+1 781 246 0707",
    "sg:postcode":"01880",
    "sg:province":"MA",
    "sg:tags":[
        "equipment",
        "snowboard",
        "rental",
        "ski"
    ],
    "sg:website":"http://www.hardyskiemporium.com",
    "wof:name":"Hardy's Ski Emporium Inc",
    "wof:placetype":"venue"
},
  "geometry": {"coordinates":[-71.075765,42.527722],"type":"Point"}
}