{
  "type": "Feature",
  "properties": {
    "addr:full": "88 Rhodes Rd Princeton MA 01541",
    "addr:housenumber": "88",
    "addr:postcode": "01541",
    "addr:street": "Rhodes Rd",
    "iso:country": "US",
    "sg:address": "88 Rhodes Rd",
    "sg:city": "Princeton",
    "sg:classifiers": [
      {
        "category": "Professional",
        "subcategory": "Management \u0026 Consulting",
        "type": "Services"
      }
    ],
    "sg:phone": "+1   ",
    "sg:postcode": "01541",
    "sg:province": "MA",
    "wof:name": "Zins \u0026 Associates",
    "wof:placetype": "venue"
  },
  "geometry": {"coordinates":[-71.918747,42.476904],"type":"Point"}
}
