{
  "type": "Feature",
  "properties": {
    "iso:country":"US",
    "sg:address":"88 Rhodes Rd",
    "sg:city":"Princeton",
    "sg:classifiers":[
        {
            "category":"Professional",
            "subcategory":"Management & Consulting",
            "type":"Services"
        }
    ],
    "sg:phone":"+1   ",
    "sg:postcode":"01541",
    "sg:province":"MA",
    "wof:name":"Zins & Associates",
    "wof:placetype":"venue"
},
  "geometry": {"coordinates":[-71.918747,42.476904],"type":"Point"}
}