{
  "type": "Feature",
  "properties": {
    "addr:full":"60 Echo St Malden MA 02148",
    "addr:housenumber":"60",
    "addr:postcode":"02148",
    "addr:street":"Echo St",
    "iso:country":"US",
    "sg:address":"60 Echo St",
    "sg:city":"Malden",
    "sg:classifiers":[
        {
            "category":"Social Services",
            "subcategory":"Child Care",
            "type":"Services"
        }
    ],
    "sg:phone":"+1   ",
    "sg:postcode":"02148",
    "sg:province":"MA",
    "sg:tags":[
        "day"
    ],
    "wof:name":"Nancys Daycare",
    "wof:placetype":"venue"
},
  "geometry": {"coordinates":[-71.055961,42.438453],"type":"Point"}
}