{
  "type": "Feature",
  "properties": {
    "addr:full":"345 Quincy Ave Braintree MA 02184",
    "addr:housenumber":"345",
    "addr:postcode":"02184",
    "addr:street":"Quincy Ave",
    "iso:country":"US",
    "sg:address":"345 Quincy Ave",
    "sg:city":"Braintree",
    "sg:phone":"+1 617 773 6496",
    "sg:postcode":"02184",
    "sg:province":"MA",
    "sg:tags":[
        "oil"
    ],
    "wof:name":"Scribi Oil Svc",
    "wof:placetype":"venue"
},
  "geometry": {"coordinates":[-70.974824,42.232254],"type":"Point"}
}