{
  "type": "Feature",
  "properties": {
    "iso:country":"US",
    "sg:address":"651 Broadway",
    "sg:city":"Lawrence",
    "sg:classifiers":[
        {
            "category":"Wholesale",
            "subcategory":"Scrap",
            "type":"Manufacturing & Wholesale Goods"
        }
    ],
    "sg:phone":"+1 978 691 5799",
    "sg:postcode":"01841",
    "sg:province":"MA",
    "sg:tags":[
        "recycling",
        "center"
    ],
    "wof:name":"Methuen Redemption",
    "wof:placetype":"venue"
},
  "geometry": {"coordinates":[-71.178771,42.717786],"type":"Point"}
}