{
  "type": "Feature",
  "properties": {
    "iso:country":"US",
    "sg:address":"66 Archer St",
    "sg:city":"Wrentham",
    "sg:classifiers":[
        {
            "category":"Building & Trades",
            "subcategory":"Electrical",
            "type":"Services"
        }
    ],
    "sg:phone":"+1 508 384 5167",
    "sg:postcode":"02093",
    "sg:province":"MA",
    "sg:tags":[
        "electrician"
    ],
    "wof:name":"David Electric",
    "wof:placetype":"venue"
},
  "geometry": {"coordinates":[-71.332032,42.069979],"type":"Point"}
}