{
  "type": "Feature",
  "properties": {
    "iso:country":"US",
    "sg:address":"17 Campbell Street",
    "sg:city":"Woburn",
    "sg:classifiers":[
        {
            "category":"Arts & Performance",
            "subcategory":"Arts Center",
            "type":"Entertainment"
        },
        {
            "category":"Arts & Performance",
            "subcategory":"Dance",
            "type":"Entertainment"
        }
    ],
    "sg:phone":"+1 781 932 6237",
    "sg:postcode":"01801",
    "sg:province":"MA",
    "sg:tags":[
        "school",
        "performing"
    ],
    "sg:website":"www.studio665.com/",
    "wof:name":"Studio 665",
    "wof:placetype":"venue"
},
  "geometry": {"coordinates":[-71.14980300000001,42.4818],"type":"Point"}
}