{
  "type": "Feature",
  "properties": {
    "addr:full": "17 Campbell Street Woburn MA 01801",
    "addr:housenumber": "17",
    "addr:postcode": "01801",
    "addr:street": "Campbell Street",
    "iso:country": "US",
    "sg:address": "17 Campbell Street",
    "sg:city": "Woburn",
    "sg:classifiers": [
      {
        "category": "Arts \u0026 Performance",
        "subcategory": "Arts Center",
        "type": "Entertainment"
      },
      {
        "category": "Arts \u0026 Performance",
        "subcategory": "Dance",
        "type": "Entertainment"
      }
    ],
    "sg:phone": "+1 781 932 6237",
    "sg:postcode": "01801",
    "sg:province": "MA",
    "sg:tags": [
      "school",
      "performing"
    ],
    "sg:website": "www.studio665.com/",
    "wof:name": "Studio 665",
    "wof:placetype": "venue"
  },
  "geometry": {"coordinates":[-71.149803,42.4818],"type":"Point"}
}
