{
  "type": "Feature",
  "properties": {
    "addr:full":"8 Jan Sebastian Dr Sandwich MA 02563",
    "addr:housenumber":"8",
    "addr:postcode":"02563",
    "addr:street":"Jan Sebastian Dr",
    "iso:country":"US",
    "sg:address":"8 Jan Sebastian Dr",
    "sg:city":"Sandwich",
    "sg:classifiers":[
        {
            "category":"Manufacturing",
            "subcategory":"Tools & Machinery",
            "type":"Manufacturing & Wholesale Goods"
        }
    ],
    "sg:phone":"+1 508 888 1340",
    "sg:postcode":"02563",
    "sg:province":"MA",
    "sg:tags":[
        "control"
    ],
    "sg:website":"www.appliedsystemseng.com",
    "wof:name":"Applied Systems Engineering",
    "wof:placetype":"venue"
},
  "geometry": {"coordinates":[-70.48720400000001,41.717924],"type":"Point"}
}