{
  "type": "Feature",
  "properties": {
    "iso:country":"US",
    "sg:address":"9 Main St",
    "sg:city":"Hull",
    "sg:classifiers":[
        {
            "category":"Education",
            "subcategory":"Library",
            "type":"Public Place"
        }
    ],
    "sg:phone":"+1 781 925 2295",
    "sg:postcode":"02045",
    "sg:province":"MA",
    "sg:website":"www.ocln.org",
    "wof:name":"Hull Public Library",
    "wof:placetype":"venue"
},
  "geometry": {"coordinates":[-70.906503,42.302311],"type":"Point"}
}