{
  "type": "Feature",
  "properties": {
    "addr:full": "9 Main St Hull MA 02045",
    "addr:housenumber": "9",
    "addr:postcode": "02045",
    "addr:street": "Main St",
    "iso:country": "US",
    "ovtr:label": "Hull Public Library, 9 Main St Hull MA US",
    "ovtr:similarity": 3.3171229362487793,
    "sg:address": "9 Main St",
    "sg:city": "Hull",
    "sg:classifiers": [
      {
        "category": "Education",
        "subcategory": "Library",
        "type": "Public Place"
      }
    ],
    "sg:phone": "+1 781 925 2295",
    "sg:postcode": "02045",
    "sg:province": "MA",
    "sg:website": "www.ocln.org",
    "wof:name": "Hull Public Library",
    "wof:placetype": "venue"
  },
  "geometry": {"coordinates":[-70.906503,42.302311],"type":"Point"}
}
