{
  "type": "Feature",
  "properties": {
    "iso:country":"US",
    "sg:address":"320 Main St",
    "sg:city":"Worcester",
    "sg:classifiers":[
        {
            "category":"Bars & Pubs",
            "type":"Food & Drink"
        }
    ],
    "sg:phone":"+1 508 799 4797",
    "sg:postcode":"01608",
    "sg:province":"MA",
    "sg:tags":[
        "club",
        "night"
    ],
    "wof:name":"Zara Inc",
    "wof:placetype":"venue"
},
  "geometry": {"coordinates":[-71.80123500000001,42.266056],"type":"Point"}
}