{
  "type": "Feature",
  "properties": {
    "addr:full": "320 Main St Worcester MA 01608",
    "addr:housenumber": "320",
    "addr:postcode": "01608",
    "addr:street": "Main St",
    "iso:country": "US",
    "sg:address": "320 Main St",
    "sg:city": "Worcester",
    "sg:classifiers": [
      {
        "category": "Bars \u0026 Pubs",
        "type": "Food \u0026 Drink"
      }
    ],
    "sg:phone": "+1 508 799 4797",
    "sg:postcode": "01608",
    "sg:province": "MA",
    "sg:tags": [
      "club",
      "night"
    ],
    "wof:name": "Zara Inc",
    "wof:placetype": "venue"
  },
  "geometry": {"coordinates":[-71.801235,42.266056],"type":"Point"}
}
