{
  "type": "Feature",
  "properties": {
    "addr:full":"46 Pleasant St Rockport MA 01966",
    "addr:housenumber":"46",
    "addr:postcode":"01966",
    "addr:street":"Pleasant St",
    "iso:country":"US",
    "sg:address":"46 Pleasant St",
    "sg:city":"Rockport",
    "sg:classifiers":[
        {
            "category":"Government",
            "subcategory":"Office",
            "type":"Public Place"
        }
    ],
    "sg:phone":"+1 978 546 7888",
    "sg:postcode":"01966",
    "sg:province":"MA",
    "sg:tags":[
        "govt",
        "city"
    ],
    "wof:name":"Rockport Waste Water Treatment",
    "wof:placetype":"venue"
},
  "geometry": {"coordinates":[-70.617621,42.653052],"type":"Point"}
}