{
  "type": "Feature",
  "properties": {
    "iso:country":"US",
    "sg:address":"74 Woodland Rd",
    "sg:city":"Wrentham",
    "sg:classifiers":[
        {
            "category":"Organizations",
            "subcategory":"Labor Organization",
            "type":"Services"
        }
    ],
    "sg:phone":"+1 508 384 9623",
    "sg:postcode":"02093",
    "sg:province":"MA",
    "wof:name":"H Cameron",
    "wof:placetype":"venue"
},
  "geometry": {"coordinates":[-71.314105,42.06701],"type":"Point"}
}