{
  "type": "Feature",
  "properties": {
    "addr:full":"204 N Main St East Longmeadow MA 01028",
    "addr:housenumber":"204",
    "addr:postcode":"01028",
    "addr:street":"N Main St",
    "iso:country":"US",
    "sg:address":"204 N Main St",
    "sg:city":"East Longmeadow",
    "sg:classifiers":[
        {
            "category":"Autos & Motor Vehicles",
            "subcategory":"Fuel & Gas Station",
            "type":"Retail Goods"
        }
    ],
    "sg:phone":"+1 413 525 3357",
    "sg:postcode":"01028",
    "sg:province":"MA",
    "sg:tags":[
        "oil"
    ],
    "wof:name":"Sunoco Gas Plus",
    "wof:placetype":"venue"
},
  "geometry": {"coordinates":[-72.518767,42.07244],"type":"Point"}
}