{
  "type": "Feature",
  "properties": {
    "addr:full":"97 Brigham Rd Worcester MA 01609",
    "addr:housenumber":"97",
    "addr:postcode":"01609",
    "addr:street":"Brigham Rd",
    "iso:country":"US",
    "sg:address":"97 Brigham Rd",
    "sg:city":"Worcester",
    "sg:classifiers":[
        {
            "category":"Retail",
            "subcategory":"Repair Shop",
            "type":"Services"
        }
    ],
    "sg:phone":"+1 508 795 1970",
    "sg:postcode":"01609",
    "sg:province":"MA",
    "sg:tags":[
        "scooter",
        "motorcycle",
        "motor"
    ],
    "wof:name":"Baystate Cycle",
    "wof:placetype":"venue"
},
  "geometry": {"coordinates":[-71.85166,42.293921],"type":"Point"}
}