{
  "type": "Feature",
  "properties": {
    "addr:full": "811 Jerusalem Rd Cohasset MA 02025",
    "addr:housenumber": "811",
    "addr:postcode": "02025",
    "addr:street": "Jerusalem Rd",
    "iso:country": "US",
    "sg:address": "811 Jerusalem Rd",
    "sg:city": "Cohasset",
    "sg:classifiers": [
      {
        "category": "Organizations",
        "subcategory": "Religious Organization",
        "type": "Services"
      }
    ],
    "sg:phone": "+1   ",
    "sg:postcode": "02025",
    "sg:province": "MA",
    "wof:name": "Nativity Virgin Mary Greek Ort",
    "wof:placetype": "venue"
  },
  "geometry": {"coordinates":[-70.843759,42.259638],"type":"Point"}
}
