{
  "type": "Feature",
  "properties": {
    "iso:country":"US",
    "sg:address":"811 Jerusalem Rd",
    "sg:city":"Cohasset",
    "sg:classifiers":[
        {
            "category":"Organizations",
            "subcategory":"Religious Organization",
            "type":"Services"
        }
    ],
    "sg:phone":"+1   ",
    "sg:postcode":"02025",
    "sg:province":"MA",
    "wof:name":"Nativity Virgin Mary Greek Ort",
    "wof:placetype":"venue"
},
  "geometry": {"coordinates":[-70.84375900000001,42.259638],"type":"Point"}
}