{
  "type": "Feature",
  "properties": {
    "addr:full":"300 East St Pittsfield MA 01201",
    "addr:housenumber":"300",
    "addr:postcode":"01201",
    "addr:street":"East St",
    "iso:country":"US",
    "sg:address":"300 East St",
    "sg:city":"Pittsfield",
    "sg:classifiers":[
        {
            "category":"Education",
            "subcategory":"School",
            "type":"Public Place"
        }
    ],
    "sg:phone":"+1 413 499 9535",
    "sg:postcode":"01201",
    "sg:province":"MA",
    "wof:name":"Pittsfield High School",
    "wof:placetype":"venue"
},
  "geometry": {"coordinates":[-73.247353,42.447321],"type":"Point"}
}