{
  "type": "Feature",
  "properties": {
    "iso:country":"US",
    "sg:address":"880 Commonwealth Ave",
    "sg:city":"Boston",
    "sg:classifiers":[
        {
            "category":"Retail",
            "subcategory":"Auto Repair",
            "type":"Services"
        }
    ],
    "sg:phone":"+1 617 277 0266",
    "sg:postcode":"02215",
    "sg:province":"MA",
    "sg:website":"brooklinejaguarbmw.com/",
    "wof:name":"Brookline Jaguar & BMW Service",
    "wof:placetype":"venue"
},
  "geometry": {"coordinates":[-71.11411699999999,42.350802],"type":"Point"}
}