{
  "type": "Feature",
  "properties": {
    "iso:country":"US",
    "sg:address":"35 New England Bus Ctr Dr",
    "sg:city":"Andover",
    "sg:classifiers":[
        {
            "category":"Wholesale",
            "subcategory":"Durable Goods & Equipment",
            "type":"Manufacturing & Wholesale Goods"
        }
    ],
    "sg:phone":"+1 978 685 6077",
    "sg:postcode":"01810",
    "sg:province":"MA",
    "sg:tags":[
        "professional"
    ],
    "wof:name":"Siemens Corp",
    "wof:placetype":"venue"
},
  "geometry": {"coordinates":[-71.202692,42.693812],"type":"Point"}
}