{
  "type": "Feature",
  "properties": {
    "addr:full":"33 Legion Pkwy Whitman MA 02382",
    "addr:housenumber":"33",
    "addr:postcode":"02382",
    "addr:street":"Legion Pkwy",
    "iso:country":"US",
    "sg:address":"33 Legion Pkwy",
    "sg:city":"Whitman",
    "sg:classifiers":[
        {
            "category":"Organizations",
            "subcategory":"Community Association",
            "type":"Services"
        }
    ],
    "sg:phone":"+1 781 447 5253",
    "sg:postcode":"02382",
    "sg:province":"MA",
    "sg:tags":[
        "military"
    ],
    "wof:name":"American Legion",
    "wof:placetype":"venue"
},
  "geometry": {"coordinates":[-70.939094,42.079751],"type":"Point"}
}