{
  "type": "Feature",
  "properties": {
    "addr:full": "85 Sturbridge Rd Charlton MA 01507",
    "addr:housenumber": "85",
    "addr:postcode": "01507",
    "addr:street": "Sturbridge Rd",
    "iso:country": "US",
    "sg:address": "85 Sturbridge Rd",
    "sg:city": "Charlton",
    "sg:classifiers": [
      {
        "category": "Shopping",
        "subcategory": "Clothing, Apparel, \u0026 Fashions",
        "type": "Retail Goods"
      }
    ],
    "sg:phone": "+1 508 248 9292",
    "sg:postcode": "01507",
    "sg:province": "MA",
    "sg:tags": [
      "shop",
      "bridal"
    ],
    "wof:name": "Gift Creek Bridal",
    "wof:placetype": "venue"
  },
  "geometry": {"coordinates":[-72.015695,42.139947],"type":"Point"}
}
