{
  "type": "Feature",
  "properties": {
    "iso:country":"US",
    "sg:address":"85 Sturbridge Rd",
    "sg:city":"Charlton",
    "sg:classifiers":[
        {
            "category":"Shopping",
            "subcategory":"Clothing, Apparel, & Fashions",
            "type":"Retail Goods"
        }
    ],
    "sg:phone":"+1 508 248 9292",
    "sg:postcode":"01507",
    "sg:province":"MA",
    "sg:tags":[
        "shop",
        "bridal"
    ],
    "wof:name":"Gift Creek Bridal",
    "wof:placetype":"venue"
},
  "geometry": {"coordinates":[-72.01569499999999,42.139947],"type":"Point"}
}