{
  "type": "Feature",
  "properties": {
    "iso:country":"US",
    "sg:address":"9 Dartmouth Rd",
    "sg:city":"Ipswich",
    "sg:classifiers":[
        {
            "category":"Shopping",
            "type":"Retail Goods"
        }
    ],
    "sg:phone":"+1 978 412 8121",
    "sg:postcode":"01938",
    "sg:province":"MA",
    "sg:tags":[
        "cosmetic",
        "perfume"
    ],
    "sg:website":"www.ipswichbaysoap.com",
    "wof:name":"Ipswich Bay Soap Co",
    "wof:placetype":"venue"
},
  "geometry": {"coordinates":[-70.79859,42.705885],"type":"Point"}
}