{
  "type": "Feature",
  "properties": {
    "addr:full": "220 Capt Beers Plain Rd Northfield MA 01360",
    "addr:housenumber": "220",
    "addr:postcode": "01360",
    "addr:street": "Capt Beers Plain Rd",
    "iso:country": "US",
    "sg:address": "220 Capt Beers Plain Rd",
    "sg:city": "Northfield",
    "sg:classifiers": [
      {
        "category": "Museum",
        "type": "Entertainment"
      }
    ],
    "sg:phone": "+1   ",
    "sg:postcode": "01360",
    "sg:province": "MA",
    "sg:tags": [
      "gallery"
    ],
    "wof:name": "Northfield Historical Society",
    "wof:placetype": "venue"
  },
  "geometry": {"coordinates":[-72.452799,42.685324],"type":"Point"}
}
