{
  "type": "Feature",
  "properties": {
    "addr:full":"43 Roxbury Street Roxbury MA 02119",
    "addr:housenumber":"43",
    "addr:postcode":"02119",
    "addr:street":"Roxbury Street",
    "iso:country":"US",
    "sg:address":"43 Roxbury Street",
    "sg:city":"Roxbury",
    "sg:classifiers":[
        {
            "category":"Food & Beverages",
            "subcategory":"Groceries & Convenience Stores",
            "type":"Retail Goods"
        }
    ],
    "sg:phone":"+1 617 989 0055",
    "sg:postcode":"02119",
    "sg:province":"MA",
    "wof:name":"Indian Ocean Grocery & Hala Meat",
    "wof:placetype":"venue"
},
  "geometry": {"coordinates":[-71.08599100000001,42.329422],"type":"Point"}
}