{
  "type": "Feature",
  "properties": {
    "addr:full":"172 Jackson St Jefferson MA 01522",
    "addr:housenumber":"172",
    "addr:postcode":"01522",
    "addr:street":"Jackson St",
    "iso:country":"US",
    "sg:address":"172 Jackson St",
    "sg:city":"Jefferson",
    "sg:classifiers":[
        {
            "category":"Restaurant",
            "type":"Food & Drink"
        }
    ],
    "sg:phone":"+1   ",
    "sg:postcode":"01522",
    "sg:province":"MA",
    "sg:tags":[
        "eating"
    ],
    "wof:name":"China Burma India Veteran",
    "wof:placetype":"venue"
},
  "geometry": {"coordinates":[-71.882074,42.372163],"type":"Point"}
}