{
  "type": "Feature",
  "properties": {
    "iso:country":"US",
    "sg:address":"33 State Street",
    "sg:city":"Boston",
    "sg:classifiers":[
        {
            "category":"Banks & Credit Unions",
            "subcategory":"Bank",
            "type":"Services"
        }
    ],
    "sg:phone":"+1 617 367 2200",
    "sg:postcode":"02109",
    "sg:province":"MA",
    "wof:name":"The First National Bank of Ipswich",
    "wof:placetype":"venue"
},
  "geometry": {"coordinates":[-71.053326,42.36222],"type":"Point"}
}