{
  "type": "Feature",
  "properties": {
    "addr:full":"67 Poplar Street Roslindale MA 02131",
    "addr:housenumber":"67",
    "addr:postcode":"02131",
    "addr:street":"Poplar Street",
    "iso:country":"US",
    "sg:address":"67 Poplar Street",
    "sg:city":"Roslindale",
    "sg:classifiers":[
        {
            "category":"Personal",
            "type":"Services"
        },
        {
            "category":"Sports & Exercise",
            "subcategory":"Gym",
            "type":"Entertainment"
        },
        {
            "category":"Health Services",
            "subcategory":"Health Practitioner",
            "type":"Services"
        },
        {
            "category":"Arena",
            "subcategory":"Sports Club",
            "type":"Entertainment"
        }
    ],
    "sg:phone":"+1 617 803 8904",
    "sg:postcode":"02131",
    "sg:province":"MA",
    "sg:tags":[
        "trainer",
        "control",
        "weight",
        "consultant",
        "program",
        "therapist",
        "fitness",
        "reducing",
        "physical"
    ],
    "wof:name":"Unified Fitness",
    "wof:placetype":"venue"
},
  "geometry": {"coordinates":[-71.12884099999999,42.285418],"type":"Point"}
}