{
  "type": "Feature",
  "properties": {
    "addr:full": "255 Baker St West Roxbury MA 02132",
    "addr:housenumber": "255",
    "addr:postcode": "02132",
    "addr:street": "Baker St",
    "iso:country": "US",
    "sg:address": "255 Baker St",
    "sg:city": "West Roxbury",
    "sg:classifiers": [
      {
        "category": "Social Services",
        "type": "Services"
      }
    ],
    "sg:phone": "+1 617 469 2084",
    "sg:postcode": "02132",
    "sg:province": "MA",
    "sg:tags": [
      "youth",
      "organization",
      "center"
    ],
    "wof:name": "Parkway Little League",
    "wof:placetype": "venue"
  },
  "geometry": {"coordinates":[-71.167305,42.279056],"type":"Point"}
}
