{
  "type": "Feature",
  "properties": {
    "addr:full":"318 Bear Hill Rd Waltham MA 02451",
    "addr:housenumber":"318",
    "addr:postcode":"02451",
    "addr:street":"Bear Hill Rd",
    "iso:country":"US",
    "sg:address":"318 Bear Hill Rd",
    "sg:city":"Waltham",
    "sg:classifiers":[
        {
            "category":"Arts & Performance",
            "subcategory":"Theater",
            "type":"Entertainment"
        }
    ],
    "sg:phone":"+1 781 466 6694",
    "sg:postcode":"02451",
    "sg:province":"MA",
    "sg:tags":[
        "musician"
    ],
    "wof:name":"Musicians Of The Old Post Road",
    "wof:placetype":"venue"
},
  "geometry": {"coordinates":[-71.265221,42.385806],"type":"Point"}
}