{
  "type": "Feature",
  "properties": {
    "addr:full": "125 Jackson St Lawrence MA 01841",
    "addr:housenumber": "125",
    "addr:postcode": "01841",
    "addr:street": "Jackson St",
    "iso:country": "US",
    "sg:address": "125 Jackson St",
    "sg:city": "Lawrence",
    "sg:classifiers": [
      {
        "category": "Personal",
        "subcategory": "Beauty Salon",
        "type": "Services"
      }
    ],
    "sg:phone": "+1 978 682 9945",
    "sg:postcode": "01841",
    "sg:province": "MA",
    "wof:name": "Karinas Beauty Salon",
    "wof:placetype": "venue"
  },
  "geometry": {"coordinates":[-71.157876,42.712713],"type":"Point"}
}
