{
  "type": "Feature",
  "properties": {
    "addr:full": "22 School St Marblehead MA 01945",
    "addr:housenumber": "22",
    "addr:postcode": "01945",
    "addr:street": "School St",
    "iso:country": "US",
    "sg:address": "22 School St",
    "sg:city": "Marblehead",
    "sg:classifiers": [
      {
        "category": "Banks \u0026 Credit Unions",
        "subcategory": "Investment Brokerage",
        "type": "Services"
      }
    ],
    "sg:phone": "+1 781 631 4100",
    "sg:postcode": "01945",
    "sg:province": "MA",
    "sg:tags": [
      "advisory",
      "financial"
    ],
    "wof:name": "Dowley \u0026 Co",
    "wof:placetype": "venue"
  },
  "geometry": {"coordinates":[-70.857207,42.502151],"type":"Point"}
}
