{
  "type": "Feature",
  "properties": {
    "iso:country":"US",
    "sg:address":"63 Ash St",
    "sg:city":"New Bedford",
    "sg:classifiers":[
        {
            "category":"Professional",
            "subcategory":"Lawyer & Legal Services",
            "type":"Services"
        }
    ],
    "sg:phone":"+1   ",
    "sg:postcode":"02740",
    "sg:province":"MA",
    "sg:tags":[
        "medical"
    ],
    "wof:name":"B G Cade PHD JD",
    "wof:placetype":"venue"
},
  "geometry": {"coordinates":[-70.93466100000001,41.629202],"type":"Point"}
}