{
  "type": "Feature",
  "properties": {
    "iso:country":"US",
    "sg:address":"478 Commonwealth Ave",
    "sg:city":"Boston",
    "sg:classifiers":[
        {
            "category":"Building & Trades",
            "subcategory":"Locksmith",
            "type":"Services"
        }
    ],
    "sg:phone":"+1 617 449 7703",
    "sg:postcode":"02215",
    "sg:province":"MA",
    "sg:tags":[
        "key"
    ],
    "wof:name":"Emergency Lcoksmith On Commonwe ABC Always 24 Hour",
    "wof:placetype":"venue"
},
  "geometry": {"coordinates":[-71.09438400000001,42.348677],"type":"Point"}
}