{
  "type": "Feature",
  "properties": {
    "addr:full": "478 Commonwealth Ave Boston MA 02215",
    "addr:housenumber": "478",
    "addr:postcode": "02215",
    "addr:street": "Commonwealth Ave",
    "iso:country": "US",
    "sg:address": "478 Commonwealth Ave",
    "sg:city": "Boston",
    "sg:classifiers": [
      {
        "category": "Building \u0026 Trades",
        "subcategory": "Locksmith",
        "type": "Services"
      }
    ],
    "sg:phone": "+1 617 449 7703",
    "sg:postcode": "02215",
    "sg:province": "MA",
    "sg:tags": [
      "key"
    ],
    "wof:name": "Emergency Lcoksmith On Commonwe ABC Always 24 Hour",
    "wof:placetype": "venue"
  },
  "geometry": {"coordinates":[-71.094384,42.348677],"type":"Point"}
}
