{
  "type": "Feature",
  "properties": {
    "iso:country":"US",
    "sg:address":"43 Lowell Junction Rd",
    "sg:city":"Andover",
    "sg:classifiers":[
        {
            "category":"Building & Trades",
            "subcategory":"Construction",
            "type":"Services"
        }
    ],
    "sg:phone":"+1 978 475 3262",
    "sg:postcode":"01810",
    "sg:province":"MA",
    "sg:tags":[
        "excavating",
        "paving",
        "contractor"
    ],
    "wof:name":"J W Watson Jr Inc",
    "wof:placetype":"venue"
},
  "geometry": {"coordinates":[-71.162758,42.615688],"type":"Point"}
}