{
  "type": "Feature",
  "properties": {
    "addr:full":"342 Longwood Ave Boston MA 02115",
    "addr:housenumber":"342",
    "addr:postcode":"02115",
    "addr:street":"Longwood Ave",
    "iso:country":"US",
    "sg:address":"342 Longwood Ave",
    "sg:city":"Boston",
    "sg:classifiers":[
        {
            "category":"Travel",
            "subcategory":"Hotels & Motels",
            "type":"Entertainment"
        }
    ],
    "sg:phone":"+1 617 731 4700",
    "sg:postcode":"02115",
    "sg:province":"MA",
    "wof:name":"Best Western",
    "wof:placetype":"venue"
},
  "geometry": {"coordinates":[-71.10668,42.33858],"type":"Point"}
}