{
  "type": "Feature",
  "properties": {
    "iso:country":"US",
    "sg:address":"132 Spring St",
    "sg:city":"Hanover",
    "sg:classifiers":[
        {
            "category":"Wholesale",
            "subcategory":"Chemicals & Plastics",
            "type":"Manufacturing & Wholesale Goods"
        }
    ],
    "sg:phone":"+1   ",
    "sg:postcode":"02339",
    "sg:province":"MA",
    "wof:name":"Success Options Skybizcom",
    "wof:placetype":"venue"
},
  "geometry": {"coordinates":[-70.83922,42.111388],"type":"Point"}
}