{
  "type": "Feature",
  "properties": {
    "addr:full": "132 Spring St Hanover MA 02339",
    "addr:housenumber": "132",
    "addr:postcode": "02339",
    "addr:street": "Spring St",
    "iso:country": "US",
    "sg:address": "132 Spring St",
    "sg:city": "Hanover",
    "sg:classifiers": [
      {
        "category": "Wholesale",
        "subcategory": "Chemicals \u0026 Plastics",
        "type": "Manufacturing \u0026 Wholesale Goods"
      }
    ],
    "sg:phone": "+1   ",
    "sg:postcode": "02339",
    "sg:province": "MA",
    "wof:name": "Success Options Skybizcom",
    "wof:placetype": "venue"
  },
  "geometry": {"coordinates":[-70.83922,42.111388],"type":"Point"}
}
