{
  "type": "Feature",
  "properties": {
    "addr:full": "1105 Washington St Newton MA 02465",
    "addr:housenumber": "1105",
    "addr:postcode": "02465",
    "addr:street": "Washington St",
    "iso:country": "US",
    "sg:address": "1105 Washington St",
    "sg:city": "Newton",
    "sg:classifiers": [
      {
        "category": "Professional",
        "subcategory": "Management \u0026 Consulting",
        "type": "Services"
      }
    ],
    "sg:phone": "+1 617 244 1662",
    "sg:postcode": "02465",
    "sg:province": "MA",
    "sg:tags": [
      "consultant",
      "business"
    ],
    "wof:name": "Structured Decisions Corp",
    "wof:placetype": "venue"
  },
  "geometry": {"coordinates":[-71.218349,42.349785],"type":"Point"}
}
