{
  "type": "Feature",
  "properties": {
    "addr:full":"23 Bridge St Quincy MA 02169",
    "addr:housenumber":"23",
    "addr:postcode":"02169",
    "addr:street":"Bridge St",
    "iso:country":"US",
    "sg:address":"23 Bridge St",
    "sg:city":"Quincy",
    "sg:classifiers":[
        {
            "category":"Professional",
            "type":"Services"
        }
    ],
    "sg:phone":"+1 617 773 0571",
    "sg:postcode":"02169",
    "sg:province":"MA",
    "sg:tags":[
        "establishment"
    ],
    "wof:name":"Bt Enterprises",
    "wof:placetype":"venue"
},
  "geometry": {"coordinates":[-71.008551,42.257585],"type":"Point"}
}