{
  "type": "Feature",
  "properties": {
    "iso:country":"US",
    "sg:address":"84 Norton Ave",
    "sg:city":"Taunton",
    "sg:classifiers":[
        {
            "category":"Recreation",
            "type":"Entertainment"
        }
    ],
    "sg:phone":"+1 508 823 8082",
    "sg:postcode":"02780",
    "sg:province":"MA",
    "sg:tags":[
        "club",
        "membership"
    ],
    "wof:name":"Taunton Western Little League",
    "wof:placetype":"venue"
},
  "geometry": {"coordinates":[-71.12535200000001,41.913969],"type":"Point"}
}