{
  "type": "Feature",
  "properties": {
    "addr:full": "129 Bank St Attleboro MA 02703",
    "addr:housenumber": "129",
    "addr:postcode": "02703",
    "addr:street": "Bank St",
    "iso:country": "US",
    "sg:address": "129 Bank St",
    "sg:city": "Attleboro",
    "sg:classifiers": [
      {
        "category": "Manufacturing",
        "subcategory": "Metals",
        "type": "Manufacturing \u0026 Wholesale Goods"
      }
    ],
    "sg:phone": "+1 508 222 8979",
    "sg:postcode": "02703",
    "sg:province": "MA",
    "sg:tags": [
      "deposition",
      "coating"
    ],
    "sg:website": "www.paratronix.com",
    "wof:name": "Paratronix Inc",
    "wof:placetype": "venue"
  },
  "geometry": {"coordinates":[-71.284157,41.949683],"type":"Point"}
}
