{
  "type": "Feature",
  "properties": {
    "addr:full": "1101 N Main St Randolph MA 02368",
    "addr:housenumber": "1101",
    "addr:postcode": "02368",
    "addr:street": "N Main St",
    "iso:country": "US",
    "ovtr:label": "Towne \u0026 Country Florist, 1101 N Main St Randolph MA US",
    "ovtr:similarity": 3.1619279384613037,
    "sg:address": "1101 N Main St",
    "sg:city": "Randolph",
    "sg:classifiers": [
      {
        "category": "Shopping",
        "subcategory": "Florist",
        "type": "Retail Goods"
      }
    ],
    "sg:phone": "+1 781 986 4420",
    "sg:postcode": "02368",
    "sg:province": "MA",
    "wof:name": "Towne \u0026 Country Florist Inc",
    "wof:placetype": "venue"
  },
  "geometry": {"coordinates":[-71.060303,42.193501],"type":"Point"}
}
