{
  "type": "Feature",
  "properties": {
    "iso:country":"US",
    "sg:address":"1101 N Main St",
    "sg:city":"Randolph",
    "sg:classifiers":[
        {
            "category":"Shopping",
            "subcategory":"Florist",
            "type":"Retail Goods"
        }
    ],
    "sg:phone":"+1 781 986 4420",
    "sg:postcode":"02368",
    "sg:province":"MA",
    "wof:name":"Towne & Country Florist Inc",
    "wof:placetype":"venue"
},
  "geometry": {"coordinates":[-71.060303,42.193501],"type":"Point"}
}