{
  "type": "Feature",
  "properties": {
    "addr:full":"92 Chelmsford St Chelmsford MA 01824",
    "addr:housenumber":"92",
    "addr:postcode":"01824",
    "addr:street":"Chelmsford St",
    "iso:country":"US",
    "sg:address":"92 Chelmsford St",
    "sg:city":"Chelmsford",
    "sg:classifiers":[
        {
            "category":"Personal",
            "subcategory":"Beauty Salon",
            "type":"Services"
        }
    ],
    "sg:phone":"+1 978 250 3837",
    "sg:postcode":"01824",
    "sg:province":"MA",
    "sg:tags":[
        "shop"
    ],
    "wof:name":"Expert Nails",
    "wof:placetype":"venue"
},
  "geometry": {"coordinates":[-71.345596,42.60349],"type":"Point"}
}