{
  "type": "Feature",
  "properties": {
    "addr:full": "248 Everett Avenue Chelsea MA 02150",
    "addr:housenumber": "248",
    "addr:postcode": "02150",
    "addr:street": "Everett Avenue",
    "iso:country": "US",
    "sg:address": "248 Everett Avenue",
    "sg:city": "Chelsea",
    "sg:classifiers": [
      {
        "category": "Building \u0026 Trades",
        "subcategory": "Construction",
        "type": "Services"
      }
    ],
    "sg:phone": "+1 617 884 1802",
    "sg:postcode": "02150",
    "sg:province": "MA",
    "sg:tags": [
      "contractor"
    ],
    "wof:name": "Deprizio \u0026 Garofano Construction",
    "wof:placetype": "venue"
  },
  "geometry": {"coordinates":[-71.04046,42.3978],"type":"Point"}
}
