{
  "type": "Feature",
  "properties": {
    "addr:full": "9 Bow Rd Orleans MA 02653",
    "addr:housenumber": "9",
    "addr:postcode": "02653",
    "addr:street": "Bow Rd",
    "iso:country": "US",
    "sg:address": "9 Bow Rd",
    "sg:city": "Orleans",
    "sg:classifiers": [
      {
        "category": "Home \u0026 Garden",
        "subcategory": "Furniture",
        "type": "Retail Goods"
      }
    ],
    "sg:phone": "+1 508 240 1073",
    "sg:postcode": "02653",
    "sg:province": "MA",
    "sg:tags": [
      "mattress"
    ],
    "wof:name": "Mattress World",
    "wof:placetype": "venue"
  },
  "geometry": {"coordinates":[-70.000197,41.858475],"type":"Point"}
}
