{
  "type": "Feature",
  "properties": {
    "iso:country":"US",
    "sg:address":"216 Shaker Rd",
    "sg:city":"Westfield",
    "sg:classifiers":[
        {
            "category":"Professional",
            "type":"Services"
        }
    ],
    "sg:phone":"+1 413 562 5809",
    "sg:postcode":"01085",
    "sg:province":"MA",
    "sg:tags":[
        "establishment"
    ],
    "wof:name":"Daniel O'Connell's Sons Inc",
    "wof:placetype":"venue"
},
  "geometry": {"coordinates":[-72.720046,42.095189],"type":"Point"}
}