{
  "type": "Feature",
  "properties": {
    "iso:country":"US",
    "sg:address":"556 Boston Rd",
    "sg:city":"Billerica",
    "sg:classifiers":[
        {
            "category":"Retail",
            "subcategory":"Auto Repair",
            "type":"Services"
        }
    ],
    "sg:phone":"+1   ",
    "sg:postcode":"01821",
    "sg:province":"MA",
    "sg:tags":[
        "muffler",
        "shop"
    ],
    "wof:name":"Midas Muffler",
    "wof:placetype":"venue"
},
  "geometry": {"coordinates":[-71.256984,42.54803],"type":"Point"}
}