{
  "type": "Feature",
  "properties": {
    "addr:full": "817 Harrison Ave Boston MA 02118",
    "addr:housenumber": "817",
    "addr:postcode": "02118",
    "addr:street": "Harrison Ave",
    "iso:country": "US",
    "sg:address": "817 Harrison Ave",
    "sg:city": "Boston",
    "sg:classifiers": [
      {
        "category": "Restaurant",
        "type": "Food \u0026 Drink"
      }
    ],
    "sg:phone": "+1 617 536 4889",
    "sg:postcode": "02118",
    "sg:province": "MA",
    "wof:name": "Kitas Luncheonette",
    "wof:placetype": "venue"
  },
  "geometry": {"coordinates":[-71.074121,42.335894],"type":"Point"}
}
