{
  "type": "Feature",
  "properties": {
    "iso:country":"US",
    "sg:address":"51 Harvard Avenue",
    "sg:city":"Allston",
    "sg:classifiers":[
        {
            "category":"Home & Garden",
            "subcategory":"Furniture",
            "type":"Retail Goods"
        }
    ],
    "sg:phone":"+1 617 789 3933",
    "sg:postcode":"02134",
    "sg:province":"MA",
    "sg:tags":[
        "store"
    ],
    "wof:name":"Woodcraft Furniture",
    "wof:placetype":"venue"
},
  "geometry": {"coordinates":[-71.13225,42.354282],"type":"Point"}
}