{
  "type": "Feature",
  "properties": {
    "addr:full":"578 Washington St Canton MA 02021",
    "addr:housenumber":"578",
    "addr:postcode":"02021",
    "addr:street":"Washington St",
    "iso:country":"US",
    "sg:address":"578 Washington St",
    "sg:city":"Canton",
    "sg:classifiers":[
        {
            "category":"Shopping",
            "subcategory":"Clothing, Apparel, & Fashions",
            "type":"Retail Goods"
        }
    ],
    "sg:phone":"+1 781 821 4580",
    "sg:postcode":"02021",
    "sg:province":"MA",
    "wof:name":"Kevin Michaels Inc",
    "wof:placetype":"venue"
},
  "geometry": {"coordinates":[-71.146665,42.15342],"type":"Point"}
}