{
  "type": "Feature",
  "properties": {
    "iso:country":"US",
    "sg:address":"1 Washington Mall Ste 1401",
    "sg:city":"Boston",
    "sg:classifiers":[
        {
            "category":"Professional",
            "subcategory":"Lawyer & Legal Services",
            "type":"Services"
        }
    ],
    "sg:phone":"+1 617 367 9449",
    "sg:postcode":"02108",
    "sg:province":"MA",
    "wof:name":"Kimball Brousseau & Michon",
    "wof:placetype":"venue"
},
  "geometry": {"coordinates":[-71.079882,42.33059],"type":"Point"}
}