{
  "type": "Feature",
  "properties": {
    "addr:full": "1 Washington Mall Ste 1401 Boston MA 02108",
    "addr:housenumber": "1;1401",
    "addr:postcode": "02108",
    "addr:street": "Washington Mall Ste",
    "iso:country": "US",
    "sg:address": "1 Washington Mall Ste 1401",
    "sg:city": "Boston",
    "sg:classifiers": [
      {
        "category": "Professional",
        "subcategory": "Lawyer \u0026 Legal Services",
        "type": "Services"
      }
    ],
    "sg:phone": "+1 617 367 9449",
    "sg:postcode": "02108",
    "sg:province": "MA",
    "wof:name": "Kimball Brousseau \u0026 Michon",
    "wof:placetype": "venue"
  },
  "geometry": {"coordinates":[-71.079882,42.33059],"type":"Point"}
}
