{
  "type": "Feature",
  "properties": {
    "addr:full": "2 Elm St Andover MA 01810",
    "addr:housenumber": "2",
    "addr:postcode": "01810",
    "addr:street": "Elm St",
    "iso:country": "US",
    "sg:address": "2 Elm St",
    "sg:city": "Andover",
    "sg:classifiers": [
      {
        "category": "Health Services",
        "subcategory": "Doctor",
        "type": "Services"
      }
    ],
    "sg:phone": "+1 978 475 4772",
    "sg:postcode": "01810",
    "sg:province": "MA",
    "sg:tags": [
      "dentist"
    ],
    "wof:name": "Browell \u0026 Murphy",
    "wof:placetype": "venue"
  },
  "geometry": {"coordinates":[-71.140649,42.657254],"type":"Point"}
}
