{
  "type": "Feature",
  "properties": {
    "addr:full": "15 Spring St Peabody MA 01960",
    "addr:housenumber": "15",
    "addr:postcode": "01960",
    "addr:street": "Spring St",
    "iso:country": "US",
    "sg:address": "15 Spring St",
    "sg:city": "Peabody",
    "sg:classifiers": [
      {
        "category": "Retail",
        "subcategory": "Auto Repair",
        "type": "Services"
      }
    ],
    "sg:phone": "+1 978 532 2382",
    "sg:postcode": "01960",
    "sg:province": "MA",
    "sg:tags": [
      "body",
      "automobile",
      "painting"
    ],
    "wof:name": "C \u0026 E Auto Body Shop",
    "wof:placetype": "venue"
  },
  "geometry": {"coordinates":[-70.927244,42.523885],"type":"Point"}
}
