{
  "type": "Feature",
  "properties": {
    "iso:country":"US",
    "sg:address":"440 Stafford Rd",
    "sg:city":"Fall River",
    "sg:classifiers":[
        {
            "category":"Food & Beverages",
            "subcategory":"Groceries & Convenience Stores",
            "type":"Retail Goods"
        }
    ],
    "sg:phone":"+1 508 675 3240",
    "sg:postcode":"02721",
    "sg:province":"MA",
    "sg:tags":[
        "grocer"
    ],
    "wof:name":"Seabra Supermarket Office",
    "wof:placetype":"venue"
},
  "geometry": {"coordinates":[-71.15698500000001,41.682528],"type":"Point"}
}