{
  "type": "Feature",
  "properties": {
    "addr:full":"230 Main St Medford MA 02155",
    "addr:housenumber":"230",
    "addr:postcode":"02155",
    "addr:street":"Main St",
    "iso:country":"US",
    "sg:address":"230 Main St",
    "sg:city":"Medford",
    "sg:classifiers":[
        {
            "category":"Health Services",
            "subcategory":"Health Practitioner",
            "type":"Services"
        }
    ],
    "sg:phone":"+1   ",
    "sg:postcode":"02155",
    "sg:province":"MA",
    "sg:tags":[
        "manager",
        "integrated",
        "care"
    ],
    "wof:name":"Denis P Donovan",
    "wof:placetype":"venue"
},
  "geometry": {"coordinates":[-71.11024999999999,42.410759],"type":"Point"}
}