{
  "type": "Feature",
  "properties": {
    "addr:full": "250 Southampton Rd Westhampton MA 01027",
    "addr:housenumber": "250",
    "addr:postcode": "01027",
    "addr:street": "Southampton Rd",
    "iso:country": "US",
    "sg:address": "250 Southampton Rd",
    "sg:city": "Westhampton",
    "sg:classifiers": [
      {
        "category": "Home \u0026 Garden",
        "subcategory": "Furniture",
        "type": "Retail Goods"
      }
    ],
    "sg:phone": "+1 413 529 0222",
    "sg:postcode": "01027",
    "sg:province": "MA",
    "sg:tags": [
      "equipment",
      "kitchen",
      "cabinet"
    ],
    "wof:name": "Paradox Solid Surface",
    "wof:placetype": "venue"
  },
  "geometry": {"coordinates":[-72.752016,42.277288],"type":"Point"}
}
