{
  "type": "Feature",
  "properties": {
    "iso:country":"US",
    "sg:address":"11 Gardner St",
    "sg:city":"Beverly",
    "sg:classifiers":[
        {
            "category":"Professional",
            "subcategory":"Advertising",
            "type":"Services"
        }
    ],
    "sg:phone":"+1   ",
    "sg:postcode":"01915",
    "sg:province":"MA",
    "sg:tags":[
        "agency"
    ],
    "wof:name":"Whats The Attraction",
    "wof:placetype":"venue"
},
  "geometry": {"coordinates":[-70.86964,42.55924],"type":"Point"}
}