{
  "type": "Feature",
  "properties": {
    "addr:full":"279 Cambridge St Burlington MA 01803",
    "addr:housenumber":"279",
    "addr:postcode":"01803",
    "addr:street":"Cambridge St",
    "iso:country":"US",
    "sg:address":"279 Cambridge St",
    "sg:city":"Burlington",
    "sg:classifiers":[
        {
            "category":"Education",
            "subcategory":"Dance Studio",
            "type":"Public Place"
        }
    ],
    "sg:phone":"+1 781 273 9320",
    "sg:postcode":"01803",
    "sg:province":"MA",
    "sg:website":"www.suzannesdanceconnection.com",
    "wof:name":"Suzanne's Dance Connection",
    "wof:placetype":"venue"
},
  "geometry": {"coordinates":[-71.20500199999999,42.5149],"type":"Point"}
}