{
  "type": "Feature",
  "properties": {
    "iso:country":"US",
    "sg:address":"10 Dewolf Street",
    "sg:city":"Cambridge",
    "sg:classifiers":[
        {
            "category":"Social Services",
            "subcategory":"Child Care",
            "type":"Services"
        },
        {
            "category":"Sports & Exercise",
            "subcategory":"Gym",
            "type":"Entertainment"
        }
    ],
    "sg:phone":"+1 617 495 3504",
    "sg:postcode":"02138",
    "sg:province":"MA",
    "sg:tags":[
        "trainer",
        "day"
    ],
    "wof:name":"Radcliffe Child Care Center",
    "wof:placetype":"venue"
},
  "geometry": {"coordinates":[-71.116254,42.370779],"type":"Point"}
}