{
  "type": "Feature",
  "properties": {
    "iso:country":"US",
    "sg:address":"2 Old County Rd",
    "sg:city":"Gloucester",
    "sg:classifiers":[
        {
            "category":"Social Services",
            "type":"Services"
        }
    ],
    "sg:phone":"+1 978 281 3489",
    "sg:postcode":"01930",
    "sg:province":"MA",
    "sg:tags":[
        "organization",
        "welfare"
    ],
    "wof:name":"Cape Ann Transportation Auth",
    "wof:placetype":"venue"
},
  "geometry": {"coordinates":[-70.63853899999999,42.627537],"type":"Point"}
}