{
  "type": "Feature",
  "properties": {
    "iso:country":"US",
    "sg:address":"106 Massachusetts Avenue",
    "sg:city":"Arlington",
    "sg:classifiers":[
        {
            "category":"Building & Trades",
            "subcategory":"Locksmith",
            "type":"Services"
        }
    ],
    "sg:phone":"+1 781 928 1749",
    "sg:postcode":"02474",
    "sg:province":"MA",
    "sg:tags":[
        "key"
    ],
    "wof:name":"A 24 Hour Always Available Emerg 24 Locksmith",
    "wof:placetype":"venue"
},
  "geometry": {"coordinates":[-71.138936,42.403344],"type":"Point"}
}