{
  "type": "Feature",
  "properties": {
    "iso:country":"US",
    "sg:address":"417 Canal St",
    "sg:city":"Lawrence",
    "sg:classifiers":[
        {
            "category":"Home & Garden",
            "subcategory":"Building Materials",
            "type":"Retail Goods"
        }
    ],
    "sg:phone":"+1 503 298 0552",
    "sg:postcode":"01840",
    "sg:province":"MA",
    "sg:tags":[
        "repair",
        "door"
    ],
    "sg:website":"http://wayne-dalton.com/",
    "wof:name":"Eastern Garage Door",
    "wof:placetype":"venue"
},
  "geometry": {"coordinates":[-71.16310199999999,42.705489],"type":"Point"}
}