{
  "type": "Feature",
  "properties": {
    "addr:full": "417 Canal St Lawrence MA 01840",
    "addr:housenumber": "417",
    "addr:postcode": "01840",
    "addr:street": "Canal St",
    "iso:country": "US",
    "sg:address": "417 Canal St",
    "sg:city": "Lawrence",
    "sg:classifiers": [
      {
        "category": "Home \u0026 Garden",
        "subcategory": "Building Materials",
        "type": "Retail Goods"
      }
    ],
    "sg:phone": "+1 503 298 0552",
    "sg:postcode": "01840",
    "sg:province": "MA",
    "sg:tags": [
      "repair",
      "door"
    ],
    "sg:website": "http://wayne-dalton.com/",
    "wof:name": "Eastern Garage Door",
    "wof:placetype": "venue"
  },
  "geometry": {"coordinates":[-71.163102,42.705489],"type":"Point"}
}
