{
  "type": "Feature",
  "properties": {
    "iso:country":"US",
    "sg:address":"68 Millbury Ave",
    "sg:city":"Millbury",
    "sg:classifiers":[
        {
            "category":"Building & Trades",
            "subcategory":"Construction",
            "type":"Services"
        }
    ],
    "sg:phone":"+1 508 865 7572",
    "sg:postcode":"01527",
    "sg:province":"MA",
    "sg:tags":[
        "paving",
        "contractor"
    ],
    "wof:name":"S & S Asphalt Paving",
    "wof:placetype":"venue"
},
  "geometry": {"coordinates":[-71.75560900000001,42.203809],"type":"Point"}
}