{
  "type": "Feature",
  "properties": {
    "addr:full": "68 Millbury Ave Millbury MA 01527",
    "addr:housenumber": "68",
    "addr:postcode": "01527",
    "addr:street": "Millbury Ave",
    "iso:country": "US",
    "sg:address": "68 Millbury Ave",
    "sg:city": "Millbury",
    "sg:classifiers": [
      {
        "category": "Building \u0026 Trades",
        "subcategory": "Construction",
        "type": "Services"
      }
    ],
    "sg:phone": "+1 508 865 7572",
    "sg:postcode": "01527",
    "sg:province": "MA",
    "sg:tags": [
      "paving",
      "contractor"
    ],
    "wof:name": "S \u0026 S Asphalt Paving",
    "wof:placetype": "venue"
  },
  "geometry": {"coordinates":[-71.755609,42.203809],"type":"Point"}
}
