{
  "type": "Feature",
  "properties": {
    "iso:country":"US",
    "sg:address":"4 Lovers Ln",
    "sg:city":"Southborough",
    "sg:classifiers":[
        {
            "category":"Professional",
            "subcategory":"Art Services",
            "type":"Services"
        }
    ],
    "sg:phone":"+1   ",
    "sg:postcode":"01772",
    "sg:province":"MA",
    "sg:tags":[
        "commercial",
        "design"
    ],
    "wof:name":"Intl Graphics",
    "wof:placetype":"venue"
},
  "geometry": {"coordinates":[-71.55611500000001,42.298174],"type":"Point"}
}