{
  "type": "Feature",
  "properties": {
    "addr:full":"20 Main St Natick MA 01760",
    "addr:housenumber":"20",
    "addr:postcode":"01760",
    "addr:street":"Main St",
    "iso:country":"US",
    "sg:address":"20 Main St",
    "sg:city":"Natick",
    "sg:classifiers":[
        {
            "category":"Professional",
            "subcategory":"Lawyer & Legal Services",
            "type":"Services"
        }
    ],
    "sg:phone":"+1 508 651 2244",
    "sg:postcode":"01760",
    "sg:province":"MA",
    "sg:tags":[
        "attorney"
    ],
    "wof:name":"Annette Hines",
    "wof:placetype":"venue"
},
  "geometry": {"coordinates":[-71.34736100000001,42.284499],"type":"Point"}
}