{
  "type": "Feature",
  "properties": {
    "addr:full": "218 Race St Holyoke MA 01040",
    "addr:housenumber": "218",
    "addr:postcode": "01040",
    "addr:street": "Race St",
    "iso:country": "US",
    "sg:address": "218 Race St",
    "sg:city": "Holyoke",
    "sg:classifiers": [
      {
        "category": "Manufacturing",
        "subcategory": "Chemicals \u0026 Compounds",
        "type": "Manufacturing \u0026 Wholesale Goods"
      }
    ],
    "sg:phone": "+1 413 532 3288",
    "sg:postcode": "01040",
    "sg:province": "MA",
    "sg:tags": [
      "adhesive",
      "glue"
    ],
    "sg:website": "www.dipoly.com",
    "wof:name": "Dielectric Polymers Inc",
    "wof:placetype": "venue"
  },
  "geometry": {"coordinates":[-72.606473,42.20206],"type":"Point"}
}
