{
  "type": "Feature",
  "properties": {
    "iso:country":"US",
    "sg:address":"740 Boston Post Rd",
    "sg:city":"Sudbury",
    "sg:classifiers":[
        {
            "category":"Building & Trades",
            "subcategory":"Landscaping Services",
            "type":"Services"
        }
    ],
    "sg:phone":"+1 978 443 3638",
    "sg:postcode":"01776",
    "sg:province":"MA",
    "sg:tags":[
        "designer",
        "landscape"
    ],
    "sg:website":"www.sudburydesign.com",
    "wof:name":"Sudbury Design Group Inc",
    "wof:placetype":"venue"
},
  "geometry": {"coordinates":[-71.45047700000001,42.360379],"type":"Point"}
}