{
  "type": "Feature",
  "properties": {
    "iso:country":"US",
    "sg:address":"78 S Main St",
    "sg:city":"Florence",
    "sg:classifiers":[
        {
            "category":"Professional",
            "subcategory":"Lawyer & Legal Services",
            "type":"Services"
        }
    ],
    "sg:phone":"+1 413 586 3700",
    "sg:postcode":"01062",
    "sg:province":"MA",
    "sg:tags":[
        "attorney",
        "criminal",
        "family",
        "personal",
        "corporation",
        "partnership",
        "real estate",
        "injury",
        "law"
    ],
    "sg:website":"http://www.northamptonlaw.com",
    "wof:name":"Burrows Weiss & Bloomberg",
    "wof:placetype":"venue"
},
  "geometry": {"coordinates":[-72.66285000000001,42.330529],"type":"Point"}
}