{
  "type": "Feature",
  "properties": {
    "addr:full": "50 Concord Rd Bedford MA 01730",
    "addr:housenumber": "50",
    "addr:postcode": "01730",
    "addr:street": "Concord Rd",
    "iso:country": "US",
    "sg:address": "50 Concord Rd",
    "sg:city": "Bedford",
    "sg:classifiers": [
      {
        "category": "Retail",
        "subcategory": "Auto Repair",
        "type": "Services"
      }
    ],
    "sg:phone": "+1 781 275 6882",
    "sg:postcode": "01730",
    "sg:province": "MA",
    "wof:name": "Bierens Garage",
    "wof:placetype": "venue"
  },
  "geometry": {"coordinates":[-71.289902,42.492699],"type":"Point"}
}
