{
  "type": "Feature",
  "properties": {
    "addr:full": "12 Harris St Wilmington MA 01887",
    "addr:housenumber": "12",
    "addr:postcode": "01887",
    "addr:street": "Harris St",
    "iso:country": "US",
    "sg:address": "12 Harris St",
    "sg:city": "Wilmington",
    "sg:classifiers": [
      {
        "category": "Building \u0026 Trades",
        "subcategory": "Plumbing",
        "type": "Services"
      }
    ],
    "sg:phone": "+1 978 657 0234",
    "sg:postcode": "01887",
    "sg:province": "MA",
    "sg:tags": [
      "plumbing",
      "contractor"
    ],
    "wof:name": "Abel Plumbing \u0026 Heating",
    "wof:placetype": "venue"
  },
  "geometry": {"coordinates":[-71.179003,42.544184],"type":"Point"}
}
