{
  "type": "Feature",
  "properties": {
    "iso:country":"US",
    "sg:address":"800 Providence Rd",
    "sg:city":"Whitinsville",
    "sg:classifiers":[
        {
            "category":"Health Services",
            "subcategory":"Chiropractor",
            "type":"Services"
        }
    ],
    "sg:phone":"+1 508 234 8222",
    "sg:postcode":"01588",
    "sg:province":"MA",
    "wof:name":"Chiropractic Health Ctr",
    "wof:placetype":"venue"
},
  "geometry": {"coordinates":[-71.63963099999999,42.116851],"type":"Point"}
}