{
  "type": "Feature",
  "properties": {
    "addr:full": "800 Providence Rd Whitinsville MA 01588",
    "addr:housenumber": "800",
    "addr:postcode": "01588",
    "addr:street": "Providence Rd",
    "iso:country": "US",
    "sg:address": "800 Providence Rd",
    "sg:city": "Whitinsville",
    "sg:classifiers": [
      {
        "category": "Health Services",
        "subcategory": "Chiropractor",
        "type": "Services"
      }
    ],
    "sg:phone": "+1 508 234 8222",
    "sg:postcode": "01588",
    "sg:province": "MA",
    "wof:name": "Chiropractic Health Ctr",
    "wof:placetype": "venue"
  },
  "geometry": {"coordinates":[-71.639631,42.116851],"type":"Point"}
}
