{
  "type": "Feature",
  "properties": {
    "addr:full":"193 Wood St Middleboro MA 02346",
    "addr:housenumber":"193",
    "addr:postcode":"02346",
    "addr:street":"Wood St",
    "iso:country":"US",
    "sg:address":"193 Wood St",
    "sg:city":"Middleboro",
    "sg:classifiers":[
        {
            "category":"Professional",
            "subcategory":"Management & Consulting",
            "type":"Services"
        }
    ],
    "sg:phone":"+1   ",
    "sg:postcode":"02346",
    "sg:province":"MA",
    "wof:name":"Sales Office",
    "wof:placetype":"venue"
},
  "geometry": {"coordinates":[-70.882402,41.885687],"type":"Point"}
}