{
  "type": "Feature",
  "properties": {
    "iso:country":"US",
    "sg:address":"11 Miller St",
    "sg:city":"Somerville",
    "sg:classifiers":[
        {
            "category":"Education",
            "subcategory":"Special Training",
            "type":"Public Place"
        }
    ],
    "sg:phone":"+1 617 233 9768",
    "sg:postcode":"02143",
    "sg:province":"MA",
    "sg:tags":[
        "school",
        "specialty"
    ],
    "sg:website":"cameraeyeworkshops.wordpress.com/",
    "wof:name":"Camera Eye Photography Workshops",
    "wof:placetype":"venue"
},
  "geometry": {"coordinates":[-71.11229299999999,42.383887],"type":"Point"}
}