{
  "type": "Feature",
  "properties": {
    "addr:full": "49 Robin Street Everett MA 02149",
    "addr:housenumber": "49",
    "addr:postcode": "02149",
    "addr:street": "Robin Street",
    "iso:country": "US",
    "sg:address": "49 Robin Street",
    "sg:city": "Everett",
    "sg:classifiers": [
      {
        "category": "Retail",
        "subcategory": "Auto Repair",
        "type": "Services"
      }
    ],
    "sg:phone": "+1 617 389 4344",
    "sg:postcode": "02149",
    "sg:province": "MA",
    "wof:name": "Caruso Automotive",
    "wof:placetype": "venue"
  },
  "geometry": {"coordinates":[-71.063925,42.394562],"type":"Point"}
}
