{
  "type": "Feature",
  "properties": {
    "addr:full": "36 Taylor Ave Plymouth MA 02360",
    "addr:housenumber": "36",
    "addr:postcode": "02360",
    "addr:street": "Taylor Ave",
    "iso:country": "US",
    "sg:address": "36 Taylor Ave",
    "sg:city": "Plymouth",
    "sg:classifiers": [
      {
        "category": "Professional",
        "subcategory": "Management \u0026 Consulting",
        "type": "Services"
      }
    ],
    "sg:phone": "+1   ",
    "sg:postcode": "02360",
    "sg:province": "MA",
    "sg:tags": [
      "business"
    ],
    "wof:name": "Tetrasolv Filtration Inc",
    "wof:placetype": "venue"
  },
  "geometry": {"coordinates":[-70.548222,41.926424],"type":"Point"}
}
