{
  "type": "Feature",
  "properties": {
    "addr:full": "87 Adams St North Adams MA 01267",
    "addr:housenumber": "87",
    "addr:postcode": "01267",
    "addr:street": "Adams St",
    "iso:country": "US",
    "sg:address": "87 Adams St",
    "sg:city": "North Adams",
    "sg:classifiers": [
      {
        "category": "Museum",
        "type": "Entertainment"
      }
    ],
    "sg:phone": "+1 413 663 8338",
    "sg:postcode": "01267",
    "sg:province": "MA",
    "sg:tags": [
      "organization",
      "arts",
      "information"
    ],
    "wof:name": "Northern Berkshire Creative",
    "wof:placetype": "venue"
  },
  "geometry": {"coordinates":[-73.121226,42.704187],"type":"Point"}
}
