{
  "type": "Feature",
  "properties": {
    "iso:country":"US",
    "sg:address":"56 Pine Ridge Rd",
    "sg:city":"Arlington",
    "sg:classifiers":[
        {
            "category":"Health Services",
            "subcategory":"Medical Lab",
            "type":"Services"
        }
    ],
    "sg:phone":"+1 781 646 2171",
    "sg:postcode":"02476",
    "sg:province":"MA",
    "sg:tags":[
        "detection",
        "equipment",
        "drug"
    ],
    "wof:name":"Antox Corp",
    "wof:placetype":"venue"
},
  "geometry": {"coordinates":[-71.17502399999999,42.415631],"type":"Point"}
}