{
  "type": "Feature",
  "properties": {
    "addr:full": "56 Pine Ridge Rd Arlington MA 02476",
    "addr:housenumber": "56",
    "addr:postcode": "02476",
    "addr:street": "Pine Ridge Rd",
    "iso:country": "US",
    "sg:address": "56 Pine Ridge Rd",
    "sg:city": "Arlington",
    "sg:classifiers": [
      {
        "category": "Health Services",
        "subcategory": "Medical Lab",
        "type": "Services"
      }
    ],
    "sg:phone": "+1 781 646 2171",
    "sg:postcode": "02476",
    "sg:province": "MA",
    "sg:tags": [
      "detection",
      "equipment",
      "drug"
    ],
    "wof:name": "Antox Corp",
    "wof:placetype": "venue"
  },
  "geometry": {"coordinates":[-71.175024,42.415631],"type":"Point"}
}
