{
  "type": "Feature",
  "properties": {
    "addr:full":"20 Hampton Ave Northampton MA 01060",
    "addr:housenumber":"20",
    "addr:postcode":"01060",
    "addr:street":"Hampton Ave",
    "iso:country":"US",
    "sg:address":"20 Hampton Ave",
    "sg:city":"Northampton",
    "sg:classifiers":[
        {
            "category":"Insurance",
            "subcategory":"Hazard Insurance",
            "type":"Services"
        }
    ],
    "sg:phone":"+1 413 586 4742",
    "sg:postcode":"01060",
    "sg:province":"MA",
    "wof:name":"Sean T Maloney & Associates",
    "wof:placetype":"venue"
},
  "geometry": {"coordinates":[-72.630911,42.317051],"type":"Point"}
}