{
  "type": "Feature",
  "properties": {
    "addr:full":"158 Upland Rd Newton MA 02460",
    "addr:housenumber":"158",
    "addr:postcode":"02460",
    "addr:street":"Upland Rd",
    "iso:country":"US",
    "sg:address":"158 Upland Rd",
    "sg:city":"Newton",
    "sg:classifiers":[
        {
            "category":"Health Services",
            "subcategory":"Health Practitioner",
            "type":"Services"
        }
    ],
    "sg:phone":"+1 617 527 5561",
    "sg:postcode":"02460",
    "sg:province":"MA",
    "sg:tags":[
        "psychologist"
    ],
    "wof:name":"Associates For Counseling",
    "wof:placetype":"venue"
},
  "geometry": {"coordinates":[-71.199366,42.344249],"type":"Point"}
}