{
  "type": "Feature",
  "properties": {
    "iso:country":"US",
    "sg:address":"59 Shearer Rd",
    "sg:city":"Colrain",
    "sg:classifiers":[
        {
            "category":"Arts & Performance",
            "subcategory":"Theater",
            "type":"Entertainment"
        }
    ],
    "sg:phone":"+1 413 625 9893",
    "sg:postcode":"01340",
    "sg:province":"MA",
    "sg:tags":[
        "television",
        "program",
        "producer"
    ],
    "sg:website":"www.globalamericantv.com",
    "wof:name":"Global American Television Inc",
    "wof:placetype":"venue"
},
  "geometry": {"coordinates":[-72.64494000000001,42.643996],"type":"Point"}
}