{
  "type": "Feature",
  "properties": {
    "addr:full": "519 Somerville Ave Somerville MA 02143",
    "addr:housenumber": "519",
    "addr:postcode": "02143",
    "addr:street": "Somerville Ave",
    "iso:country": "US",
    "sg:address": "519 Somerville Ave",
    "sg:city": "Somerville",
    "sg:classifiers": [
      {
        "category": "Building \u0026 Trades",
        "subcategory": "Construction",
        "type": "Services"
      }
    ],
    "sg:phone": "+1 617 528 8035",
    "sg:postcode": "02143",
    "sg:province": "MA",
    "sg:tags": [
      "roofing"
    ],
    "wof:name": "Top Coat Roofing",
    "wof:placetype": "venue"
  },
  "geometry": {"coordinates":[-71.106261,42.383193],"type":"Point"}
}
