{
  "type": "Feature",
  "properties": {
    "addr:full": "121 Holden Wood Rd Concord MA 01742",
    "addr:housenumber": "121",
    "addr:postcode": "01742",
    "addr:street": "Holden Wood Rd",
    "iso:country": "US",
    "sg:address": "121 Holden Wood Rd",
    "sg:city": "Concord",
    "sg:classifiers": [
      {
        "category": "Professional",
        "subcategory": "Management \u0026 Consulting",
        "type": "Services"
      }
    ],
    "sg:phone": "+1   ",
    "sg:postcode": "01742",
    "sg:province": "MA",
    "sg:tags": [
      "business"
    ],
    "wof:name": "Basic Literacy Services",
    "wof:placetype": "venue"
  },
  "geometry": {"coordinates":[-71.368855,42.433939],"type":"Point"}
}
