{
  "type": "Feature",
  "properties": {
    "iso:country":"US",
    "sg:address":"71 Wallis St",
    "sg:city":"Peabody",
    "sg:classifiers":[
        {
            "category":"Organizations",
            "subcategory":"Community Association",
            "type":"Services"
        }
    ],
    "sg:phone":"+1 978 531 9600",
    "sg:postcode":"01960",
    "sg:province":"MA",
    "sg:tags":[
        "fraternal"
    ],
    "wof:name":"Jordon Masonic Temple",
    "wof:placetype":"venue"
},
  "geometry": {"coordinates":[-70.92367299999999,42.528943],"type":"Point"}
}