{
  "type": "Feature",
  "properties": {
    "iso:country":"US",
    "sg:address":"741 Kempton St",
    "sg:city":"New Bedford",
    "sg:classifiers":[
        {
            "category":"Organizations",
            "subcategory":"Religious Organization",
            "type":"Services"
        }
    ],
    "sg:phone":"+1 508 997 2720",
    "sg:postcode":"02740",
    "sg:province":"MA",
    "sg:tags":[
        "church"
    ],
    "wof:name":"New Life Tabernacle UPC",
    "wof:placetype":"venue"
},
  "geometry": {"coordinates":[-70.945296,41.635932],"type":"Point"}
}