{
  "type": "Feature",
  "properties": {
    "addr:full": "84 Alford Rd Great Barrington MA 01230",
    "addr:housenumber": "84",
    "addr:postcode": "01230",
    "addr:street": "Alford Rd",
    "iso:country": "US",
    "sg:address": "84 Alford Rd",
    "sg:city": "Great Barrington",
    "sg:classifiers": [
      {
        "category": "Education",
        "subcategory": "College",
        "type": "Public Place"
      }
    ],
    "sg:phone": "+1 413 528 0771",
    "sg:postcode": "01230",
    "sg:province": "MA",
    "sg:tags": [
      "academic",
      "school"
    ],
    "sg:website": "www.sedigroup.org",
    "wof:name": "Simon's Rock College",
    "wof:placetype": "venue"
  },
  "geometry": {"coordinates":[-73.386847,42.210208],"type":"Point"}
}
