{
  "type": "Feature",
  "properties": {
    "iso:country":"US",
    "sg:address":"84 Alford Rd",
    "sg:city":"Great Barrington",
    "sg:classifiers":[
        {
            "category":"Education",
            "subcategory":"College",
            "type":"Public Place"
        }
    ],
    "sg:phone":"+1 413 528 0771",
    "sg:postcode":"01230",
    "sg:province":"MA",
    "sg:tags":[
        "academic",
        "school"
    ],
    "sg:website":"www.sedigroup.org",
    "wof:name":"Simon's Rock College",
    "wof:placetype":"venue"
},
  "geometry": {"coordinates":[-73.386847,42.210208],"type":"Point"}
}