{
  "type": "Feature",
  "properties": {
    "iso:country":"US",
    "sg:address":"195 Washington St",
    "sg:city":"Hanover",
    "sg:classifiers":[
        {
            "category":"Building & Trades",
            "subcategory":"Construction",
            "type":"Services"
        }
    ],
    "sg:phone":"+1 781 829 0123",
    "sg:postcode":"02339",
    "sg:province":"MA",
    "sg:tags":[
        "painter"
    ],
    "wof:name":"Horton Painting Co",
    "wof:placetype":"venue"
},
  "geometry": {"coordinates":[-70.81215899999999,42.113414],"type":"Point"}
}