{
  "type": "Feature",
  "properties": {
    "addr:full":"515 Massachusetts Ave Cambridge MA 02139",
    "addr:housenumber":"515",
    "addr:postcode":"02139",
    "addr:street":"Massachusetts Ave",
    "iso:country":"US",
    "sg:address":"515 Massachusetts Ave",
    "sg:city":"Cambridge",
    "sg:classifiers":[
        {
            "category":"Banks & Credit Unions",
            "subcategory":"Bank",
            "type":"Services"
        }
    ],
    "sg:phone":"+1 617 000 1111",
    "sg:postcode":"02139",
    "sg:province":"MA",
    "wof:name":"Sovereign Bank",
    "wof:placetype":"venue"
},
  "geometry": {"coordinates":[-71.101643,42.364196],"type":"Point"}
}