{
  "type": "Feature",
  "properties": {
    "addr:full":"331 State Rd North Dartmouth MA 02747",
    "addr:housenumber":"331",
    "addr:postcode":"02747",
    "addr:street":"State Rd",
    "iso:country":"US",
    "sg:address":"331 State Rd",
    "sg:city":"North Dartmouth",
    "sg:classifiers":[
        {
            "category":"Shopping",
            "subcategory":"Musical Instruments",
            "type":"Retail Goods"
        }
    ],
    "sg:phone":"+1 508 997 5928",
    "sg:postcode":"02747",
    "sg:province":"MA",
    "sg:tags":[
        "music",
        "dealer"
    ],
    "wof:name":"Newbury Comics",
    "wof:placetype":"venue"
},
  "geometry": {"coordinates":[-70.985764,41.639369],"type":"Point"}
}