{
  "type": "Feature",
  "properties": {
    "iso:country":"US",
    "sg:address":"25 Iroquois St",
    "sg:city":"Roxbury Crossing",
    "sg:classifiers":[
        {
            "category":"Insurance",
            "subcategory":"Insurance Agent",
            "type":"Services"
        }
    ],
    "sg:phone":"+1 617 232 1717",
    "sg:postcode":"02120",
    "sg:province":"MA",
    "sg:tags":[
        "accident"
    ],
    "wof:name":"Nase",
    "wof:placetype":"venue"
},
  "geometry": {"coordinates":[-71.105518,42.330422],"type":"Point"}
}