{
  "type": "Feature",
  "properties": {
    "addr:full": "4 Riverside Sq Hyde Park MA 02136",
    "addr:housenumber": "4",
    "addr:postcode": "02136",
    "addr:street": "Riverside Sq",
    "iso:country": "US",
    "sg:address": "4 Riverside Sq",
    "sg:city": "Hyde Park",
    "sg:classifiers": [
      {
        "category": "Professional",
        "subcategory": "Computer Services",
        "type": "Services"
      }
    ],
    "sg:phone": "+1   ",
    "sg:postcode": "02136",
    "sg:province": "MA",
    "sg:tags": [
      "datum"
    ],
    "wof:name": "Gevel Graphics",
    "wof:placetype": "venue"
  },
  "geometry": {"coordinates":[-71.113853,42.260172],"type":"Point"}
}
