{
  "type": "Feature",
  "properties": {
    "addr:full": "730 Boston Post Rd Sudbury MA 01776",
    "addr:housenumber": "730",
    "addr:postcode": "01776",
    "addr:street": "Boston Post Rd",
    "iso:country": "US",
    "ovtr:label": "In Vogue Spa, 730 Boston Post Rd Sudbury MA US",
    "ovtr:similarity": 2.3948910236358643,
    "sg:address": "730 Boston Post Rd",
    "sg:city": "Sudbury",
    "sg:classifiers": [
      {
        "category": "Personal",
        "subcategory": "Beauty Salon",
        "type": "Services"
      }
    ],
    "sg:phone": "+1 978 443 2277",
    "sg:postcode": "01776",
    "sg:province": "MA",
    "sg:tags": [
      "spa",
      "day"
    ],
    "wof:name": "In Vogue Spa",
    "wof:placetype": "venue"
  },
  "geometry": {"coordinates":[-71.450701,42.360409],"type":"Point"}
}
