{
  "type": "Feature",
  "properties": {
    "iso:country":"US",
    "sg:address":"230 Central St",
    "sg:city":"Auburndale",
    "sg:classifiers":[
        {
            "category":"Organizations",
            "subcategory":"Non-profit Organization",
            "type":"Services"
        }
    ],
    "sg:phone":"+1 617 527 0723",
    "sg:postcode":"02466",
    "sg:province":"MA",
    "wof:name":"Auburndale Community Nursery",
    "wof:placetype":"venue"
},
  "geometry": {"coordinates":[-71.250996,42.345011],"type":"Point"}
}