{
  "type": "Feature",
  "properties": {
    "addr:full": "230 Central St Auburndale MA 02466",
    "addr:housenumber": "230",
    "addr:postcode": "02466",
    "addr:street": "Central St",
    "iso:country": "US",
    "sg:address": "230 Central St",
    "sg:city": "Auburndale",
    "sg:classifiers": [
      {
        "category": "Organizations",
        "subcategory": "Non-profit Organization",
        "type": "Services"
      }
    ],
    "sg:phone": "+1 617 527 0723",
    "sg:postcode": "02466",
    "sg:province": "MA",
    "wof:name": "Auburndale Community Nursery",
    "wof:placetype": "venue"
  },
  "geometry": {"coordinates":[-71.250996,42.345011],"type":"Point"}
}
