{
  "type": "Feature",
  "properties": {
    "addr:full": "25 Goodenough St Brighton MA 02135",
    "addr:housenumber": "25",
    "addr:postcode": "02135",
    "addr:street": "Goodenough St",
    "iso:country": "US",
    "sg:address": "25 Goodenough St",
    "sg:city": "Brighton",
    "sg:classifiers": [
      {
        "category": "Personal",
        "type": "Services"
      }
    ],
    "sg:phone": "+1 617 566 8531",
    "sg:postcode": "02135",
    "sg:province": "MA",
    "sg:tags": [
      "towing"
    ],
    "wof:name": "Roberts Towing",
    "wof:placetype": "venue"
  },
  "geometry": {"coordinates":[-71.154014,42.356696],"type":"Point"}
}
