{
  "type": "Feature",
  "properties": {
    "addr:full": "7 West St Barre MA 01005",
    "addr:housenumber": "7",
    "addr:postcode": "01005",
    "addr:street": "West St",
    "iso:country": "US",
    "ovtr:label": "The Jenkins Inn, 7 West St Barre MA US",
    "ovtr:similarity": 3.9957408905029297,
    "sg:address": "7 West St",
    "sg:city": "Barre",
    "sg:classifiers": [
      {
        "category": "Restaurant",
        "type": "Food \u0026 Drink"
      }
    ],
    "sg:phone": "+1 978 355 6444",
    "sg:postcode": "01005",
    "sg:province": "MA",
    "sg:website": "http://www.jenkinsinn.com",
    "wof:name": "Jenkins Inn \u0026 Restaurant",
    "wof:placetype": "venue"
  },
  "geometry": {"coordinates":[-72.10768,42.42347],"type":"Point"}
}
