{
  "type": "Feature",
  "properties": {
    "iso:country":"US",
    "sg:address":"7 West St",
    "sg:city":"Barre",
    "sg:classifiers":[
        {
            "category":"Restaurant",
            "type":"Food & Drink"
        }
    ],
    "sg:phone":"+1 978 355 6444",
    "sg:postcode":"01005",
    "sg:province":"MA",
    "sg:website":"http://www.jenkinsinn.com",
    "wof:name":"Jenkins Inn & Restaurant",
    "wof:placetype":"venue"
},
  "geometry": {"coordinates":[-72.10768,42.42347],"type":"Point"}
}