{
  "type": "Feature",
  "properties": {
    "addr:full":"4550 US Hwy 6 Eastham MA 02642",
    "addr:housenumber":"4550",
    "addr:postcode":"02642",
    "addr:street":"Us Hwy 6",
    "iso:country":"US",
    "sg:address":"4550 US Hwy 6",
    "sg:city":"Eastham",
    "sg:classifiers":[
        {
            "category":"Shopping",
            "subcategory":"Bicycles & Sporting Goods",
            "type":"Retail Goods"
        }
    ],
    "sg:phone":"+1 508 255 8281",
    "sg:postcode":"02642",
    "sg:province":"MA",
    "sg:website":"www.idletimesbike.com",
    "wof:name":"Idle Times Bike Shop",
    "wof:placetype":"venue"
},
  "geometry": {"coordinates":[-69.986593,41.857793],"type":"Point"}
}