{
  "type": "Feature",
  "properties": {
    "iso:country":"US",
    "sg:address":"19 Amanda Way",
    "sg:city":"Mashpee",
    "sg:classifiers":[
        {
            "category":"Building & Trades",
            "subcategory":"Construction",
            "type":"Services"
        }
    ],
    "sg:phone":"+1 508 477 6900",
    "sg:postcode":"02649",
    "sg:province":"MA",
    "sg:tags":[
        "resurfacing",
        "laying",
        "refinishing",
        "floor"
    ],
    "wof:name":"Cape Cod Hardwood Floors",
    "wof:placetype":"venue"
},
  "geometry": {"coordinates":[-70.485814,41.64019],"type":"Point"}
}