{
  "type": "Feature",
  "properties": {
    "addr:full": "1 Faneuil St Boston MA 02135",
    "addr:housenumber": "1",
    "addr:postcode": "02135",
    "addr:street": "Faneuil St",
    "iso:country": "US",
    "sg:address": "1 Faneuil St",
    "sg:city": "Boston",
    "sg:classifiers": [
      {
        "category": "Shopping",
        "subcategory": "Clothing, Apparel, \u0026 Fashions",
        "type": "Retail Goods"
      }
    ],
    "sg:phone": "+1 617 523 0651",
    "sg:postcode": "02135",
    "sg:province": "MA",
    "wof:name": "Urban Outfitters",
    "wof:placetype": "venue"
  },
  "geometry": {"coordinates":[-71.150435,42.354983],"type":"Point"}
}
