{
  "type": "Feature",
  "properties": {
    "iso:country":"US",
    "sg:address":"170 Water St",
    "sg:city":"Plymouth",
    "sg:classifiers":[
        {
            "category":"Autos & Motor Vehicles",
            "subcategory":"Auto Supplies",
            "type":"Retail Goods"
        }
    ],
    "sg:phone":"+1 508 746 7779",
    "sg:postcode":"02360",
    "sg:province":"MA",
    "sg:tags":[
        "wheel",
        "cover"
    ],
    "wof:name":"Water Wheels",
    "wof:placetype":"venue"
},
  "geometry": {"coordinates":[-70.66995799999999,41.963625],"type":"Point"}
}