{
  "type": "Feature",
  "properties": {
    "addr:full":"379 Main St Fitchburg MA 01420",
    "addr:housenumber":"379",
    "addr:postcode":"01420",
    "addr:street":"Main St",
    "iso:country":"US",
    "sg:address":"379 Main St",
    "sg:city":"Fitchburg",
    "sg:classifiers":[
        {
            "category":"Retail",
            "subcategory":"Repair Shop",
            "type":"Services"
        }
    ],
    "sg:phone":"+1 978 342 4727",
    "sg:postcode":"01420",
    "sg:province":"MA",
    "sg:tags":[
        "jewelry"
    ],
    "wof:name":"Sam & Friends",
    "wof:placetype":"venue"
},
  "geometry": {"coordinates":[-71.79740700000001,42.582431],"type":"Point"}
}