{
  "type": "Feature",
  "properties": {
    "iso:country":"US",
    "sg:address":"2 C St",
    "sg:city":"Hull",
    "sg:classifiers":[
        {
            "category":"Professional",
            "subcategory":"Business Services",
            "type":"Services"
        }
    ],
    "sg:phone":"+1   ",
    "sg:postcode":"02045",
    "sg:province":"MA",
    "wof:name":"Beacon Interiors",
    "wof:placetype":"venue"
},
  "geometry": {"coordinates":[-70.882519,42.292747],"type":"Point"}
}