{
  "type": "Feature",
  "properties": {
    "addr:full": "11 Summer St Westborough MA 01581",
    "addr:housenumber": "11",
    "addr:postcode": "01581",
    "addr:street": "Summer St",
    "iso:country": "US",
    "sg:address": "11 Summer St",
    "sg:city": "Westborough",
    "sg:classifiers": [
      {
        "category": "Real Estate",
        "subcategory": "Surveying",
        "type": "Services"
      }
    ],
    "sg:phone": "+1 508 366 8800",
    "sg:postcode": "01581",
    "sg:province": "MA",
    "sg:tags": [
      "surveyor"
    ],
    "wof:name": "Guerard Survey Co \u0026 Assoc",
    "wof:placetype": "venue"
  },
  "geometry": {"coordinates":[-71.613637,42.270214],"type":"Point"}
}
