{
  "type": "Feature",
  "properties": {
    "addr:full":"8 Hazel St Uxbridge MA 01569",
    "addr:housenumber":"8",
    "addr:postcode":"01569",
    "addr:street":"Hazel St",
    "iso:country":"US",
    "sg:address":"8 Hazel St",
    "sg:city":"Uxbridge",
    "sg:classifiers":[
        {
            "category":"Real Estate",
            "subcategory":"Real Estate Agent",
            "type":"Services"
        }
    ],
    "sg:phone":"+1 508 278 2607",
    "sg:postcode":"01569",
    "sg:province":"MA",
    "wof:name":"Eastwood Group",
    "wof:placetype":"venue"
},
  "geometry": {"coordinates":[-71.637064,42.081091],"type":"Point"}
}