{
  "type": "Feature",
  "properties": {
    "addr:full": "417 Washington St Boston MA 02108",
    "addr:housenumber": "417",
    "addr:postcode": "02108",
    "addr:street": "Washington St",
    "iso:country": "US",
    "sg:address": "417 Washington St",
    "sg:city": "Boston",
    "sg:classifiers": [
      {
        "category": "Restaurant",
        "type": "Food \u0026 Drink"
      }
    ],
    "sg:postcode": "02108",
    "sg:province": "MA",
    "sg:tags": [
      "caribbean"
    ],
    "wof:name": "Calypso Grill",
    "wof:placetype": "venue"
  },
  "geometry": {"coordinates":[-71.060181,42.355757],"type":"Point"}
}
