{
  "type": "Feature",
  "properties": {
    "iso:country":"US",
    "sg:address":"417 Washington St",
    "sg:city":"Boston",
    "sg:classifiers":[
        {
            "category":"Restaurant",
            "type":"Food & Drink"
        }
    ],
    "sg:postcode":"02108",
    "sg:province":"MA",
    "sg:tags":[
        "caribbean"
    ],
    "wof:name":"Calypso Grill",
    "wof:placetype":"venue"
},
  "geometry": {"coordinates":[-71.060181,42.355757],"type":"Point"}
}