{
  "type": "Feature",
  "properties": {
    "iso:country":"US",
    "sg:address":"82 Water St",
    "sg:city":"Boston",
    "sg:classifiers":[
        {
            "category":"Deli",
            "type":"Food & Drink"
        },
        {
            "category":"Restaurant",
            "type":"Food & Drink"
        }
    ],
    "sg:phone":"+1 617 357 9013",
    "sg:postcode":"02109",
    "sg:province":"MA",
    "sg:tags":[
        "mexican",
        "delicatessen",
        "lunch",
        "american",
        "brunch",
        "breakfast"
    ],
    "sg:website":"http://www.boloco.com",
    "wof:name":"Boloco",
    "wof:placetype":"venue"
},
  "geometry": {"coordinates":[-71.05555,42.357745],"type":"Point"}
}