{
  "type": "Feature",
  "properties": {
    "addr:full": "82 Water St Boston MA 02109",
    "addr:housenumber": "82",
    "addr:postcode": "02109",
    "addr:street": "Water St",
    "iso:country": "US",
    "sg:address": "82 Water St",
    "sg:city": "Boston",
    "sg:classifiers": [
      {
        "category": "Deli",
        "type": "Food \u0026 Drink"
      },
      {
        "category": "Restaurant",
        "type": "Food \u0026 Drink"
      }
    ],
    "sg:phone": "+1 617 357 9013",
    "sg:postcode": "02109",
    "sg:province": "MA",
    "sg:tags": [
      "mexican",
      "delicatessen",
      "lunch",
      "american",
      "brunch",
      "breakfast"
    ],
    "sg:website": "http://www.boloco.com",
    "wof:name": "Boloco",
    "wof:placetype": "venue"
  },
  "geometry": {"coordinates":[-71.05555,42.357745],"type":"Point"}
}
