{
  "type": "Feature",
  "properties": {
    "iso:country":"US",
    "sg:address":"620 Essex St",
    "sg:city":"Lawrence",
    "sg:classifiers":[
        {
            "category":"Organizations",
            "subcategory":"Professional Association",
            "type":"Services"
        }
    ],
    "sg:phone":"+1 978 685 4900",
    "sg:postcode":"01841",
    "sg:province":"MA",
    "sg:tags":[
        "sales"
    ],
    "wof:name":"New England Affiliated Techs",
    "wof:placetype":"venue"
},
  "geometry": {"coordinates":[-71.169855,42.704024],"type":"Point"}
}