{
  "type": "Feature",
  "properties": {
    "addr:full":"2175 Massachusetts Ave Cambridge MA 02140",
    "addr:housenumber":"2175",
    "addr:postcode":"02140",
    "addr:street":"Massachusetts Ave",
    "iso:country":"US",
    "sg:address":"2175 Massachusetts Ave",
    "sg:city":"Cambridge",
    "sg:classifiers":[
        {
            "category":"Retail",
            "subcategory":"Funeral Services",
            "type":"Services"
        }
    ],
    "sg:phone":"+1 617 864 4080",
    "sg:postcode":"02140",
    "sg:province":"MA",
    "sg:tags":[
        "cemetery"
    ],
    "wof:name":"Keefe Funeral Homes",
    "wof:placetype":"venue"
},
  "geometry": {"coordinates":[-71.122902,42.391102],"type":"Point"}
}