{
  "type": "Feature",
  "properties": {
    "iso:country":"US",
    "sg:address":"1020 Plain St Ste 320",
    "sg:city":"Marshfield",
    "sg:classifiers":[
        {
            "category":"Banks & Credit Unions",
            "subcategory":"Investment Brokerage",
            "type":"Services"
        },
        {
            "category":"Insurance",
            "subcategory":"Hazard Insurance",
            "type":"Services"
        }
    ],
    "sg:phone":"+1 781 834 3311",
    "sg:postcode":"02050",
    "sg:province":"MA",
    "sg:tags":[
        "commercial",
        "agent",
        "business",
        "resume"
    ],
    "sg:website":"http://www.marketinternational.com",
    "wof:name":"Market International Insurance Agency",
    "wof:placetype":"venue"
},
  "geometry": {"coordinates":[-70.759277,42.107021],"type":"Point"}
}