{
  "type": "Feature",
  "properties": {
    "addr:full": "6 Dukes Rd Nantucket MA 02554",
    "addr:housenumber": "6",
    "addr:postcode": "02554",
    "addr:street": "Dukes Rd",
    "iso:country": "US",
    "sg:address": "6 Dukes Rd",
    "sg:city": "Nantucket",
    "sg:classifiers": [
      {
        "category": "Farming",
        "subcategory": "Nursery",
        "type": "Manufacturing \u0026 Wholesale Goods"
      }
    ],
    "sg:phone": "+1 508 228 2649",
    "sg:postcode": "02554",
    "sg:province": "MA",
    "sg:tags": [
      "greenhouse"
    ],
    "wof:name": "Nantucket Hydrangea \u0026 Botncl",
    "wof:placetype": "venue"
  },
  "geometry": {"coordinates":[-70.113403,41.280878],"type":"Point"}
}
