{
  "type": "Feature",
  "properties": {
    "iso:country":"US",
    "sg:address":"6 Dukes Rd",
    "sg:city":"Nantucket",
    "sg:classifiers":[
        {
            "category":"Farming",
            "subcategory":"Nursery",
            "type":"Manufacturing & Wholesale Goods"
        }
    ],
    "sg:phone":"+1 508 228 2649",
    "sg:postcode":"02554",
    "sg:province":"MA",
    "sg:tags":[
        "greenhouse"
    ],
    "wof:name":"Nantucket Hydrangea & Botncl",
    "wof:placetype":"venue"
},
  "geometry": {"coordinates":[-70.11340300000001,41.280878],"type":"Point"}
}