{
  "type": "Feature",
  "properties": {
    "iso:country":"US",
    "sg:address":"27 Spring St",
    "sg:city":"Waltham",
    "sg:classifiers":[
        {
            "category":"Manufacturing",
            "subcategory":"Retail Goods",
            "type":"Manufacturing & Wholesale Goods"
        }
    ],
    "sg:phone":"+1 781 894 8133",
    "sg:postcode":"02451",
    "sg:province":"MA",
    "sg:tags":[
        "manufacturer"
    ],
    "wof:name":"Touch Inc",
    "wof:placetype":"venue"
},
  "geometry": {"coordinates":[-71.238632,42.378096],"type":"Point"}
}