{
  "type": "Feature",
  "properties": {
    "addr:full": "754 Nantasket Ave Hull MA 02045",
    "addr:housenumber": "754",
    "addr:postcode": "02045",
    "addr:street": "Nantasket Ave",
    "iso:country": "US",
    "sg:address": "754 Nantasket Ave",
    "sg:city": "Hull",
    "sg:classifiers": [
      {
        "category": "Food \u0026 Beverages",
        "subcategory": "Candy",
        "type": "Retail Goods"
      }
    ],
    "sg:phone": "+1 781 925 9644",
    "sg:postcode": "02045",
    "sg:province": "MA",
    "sg:tags": [
      "confectionery"
    ],
    "wof:name": "L Street Deli \u0026 Pizza",
    "wof:placetype": "venue"
  },
  "geometry": {"coordinates":[-70.882302,42.299149],"type":"Point"}
}
