{
  "type": "Feature",
  "properties": {
    "iso:country":"US",
    "sg:address":"754 Nantasket Ave",
    "sg:city":"Hull",
    "sg:classifiers":[
        {
            "category":"Food & Beverages",
            "subcategory":"Candy",
            "type":"Retail Goods"
        }
    ],
    "sg:phone":"+1 781 925 9644",
    "sg:postcode":"02045",
    "sg:province":"MA",
    "sg:tags":[
        "confectionery"
    ],
    "wof:name":"L Street Deli & Pizza",
    "wof:placetype":"venue"
},
  "geometry": {"coordinates":[-70.882302,42.299149],"type":"Point"}
}