{
  "type": "Feature",
  "properties": {
    "addr:full": "58 Hamilton Ave South Hamilton MA 01982",
    "addr:housenumber": "58",
    "addr:postcode": "01982",
    "addr:street": "Hamilton Ave South",
    "iso:country": "US",
    "sg:address": "58 Hamilton Ave",
    "sg:city": "South Hamilton",
    "sg:classifiers": [
      {
        "category": "Manufacturing",
        "subcategory": "Tools \u0026 Machinery",
        "type": "Manufacturing \u0026 Wholesale Goods"
      }
    ],
    "sg:phone": "+1 978 468 5053",
    "sg:postcode": "01982",
    "sg:province": "MA",
    "sg:tags": [
      "model",
      "maker"
    ],
    "wof:name": "Hamilton Prototype \u0026 Model",
    "wof:placetype": "venue"
  },
  "geometry": {"coordinates":[-70.877879,42.614136],"type":"Point"}
}
