{
  "type": "Feature",
  "properties": {
    "iso:country":"US",
    "sg:address":"58 Hamilton Ave",
    "sg:city":"South Hamilton",
    "sg:classifiers":[
        {
            "category":"Manufacturing",
            "subcategory":"Tools & Machinery",
            "type":"Manufacturing & Wholesale Goods"
        }
    ],
    "sg:phone":"+1 978 468 5053",
    "sg:postcode":"01982",
    "sg:province":"MA",
    "sg:tags":[
        "model",
        "maker"
    ],
    "wof:name":"Hamilton Prototype & Model",
    "wof:placetype":"venue"
},
  "geometry": {"coordinates":[-70.87787899999999,42.614136],"type":"Point"}
}