{
  "type": "Feature",
  "properties": {
    "addr:full": "2 International Way Lawrence MA 01843",
    "addr:housenumber": "2",
    "addr:postcode": "01843",
    "addr:street": "International Way",
    "iso:country": "US",
    "sg:address": "2 International Way",
    "sg:city": "Lawrence",
    "sg:classifiers": [
      {
        "category": "Autos \u0026 Motor Vehicles",
        "subcategory": "Fuel \u0026 Gas Station",
        "type": "Retail Goods"
      },
      {
        "category": "Utilities",
        "subcategory": "Fuel Oil \u0026 Lpg",
        "type": "Services"
      },
      {
        "category": "Utilities",
        "subcategory": "Natural Gas",
        "type": "Services"
      }
    ],
    "sg:phone": "+1 781 683 2771",
    "sg:postcode": "01843",
    "sg:province": "MA",
    "sg:tags": [
      "propane",
      "oils-fuel",
      "burner"
    ],
    "sg:website": "http://www.haffnersoil.com",
    "wof:name": "Haffner's Oil",
    "wof:placetype": "venue"
  },
  "geometry": {"coordinates":[-71.17971,42.689602],"type":"Point"}
}
