{
  "type": "Feature",
  "properties": {
    "addr:full":"2351 Main St Brewster MA 02631",
    "addr:housenumber":"2351",
    "addr:postcode":"02631",
    "addr:street":"Main St",
    "iso:country":"US",
    "sg:address":"2351 Main St",
    "sg:city":"Brewster",
    "sg:classifiers":[
        {
            "category":"Personal",
            "subcategory":"Barber",
            "type":"Services"
        }
    ],
    "sg:phone":"+1 508 896 2622",
    "sg:postcode":"02631",
    "sg:province":"MA",
    "wof:name":"Blades",
    "wof:placetype":"venue"
},
  "geometry": {"coordinates":[-70.068691,41.7646],"type":"Point"}
}