{
  "type": "Feature",
  "properties": {
    "iso:country":"US",
    "sg:address":"30 Massasoit Ave",
    "sg:city":"West Springfield",
    "sg:classifiers":[
        {
            "category":"Organizations",
            "subcategory":"Religious Organization",
            "type":"Services"
        }
    ],
    "sg:phone":"+1 413 781 3754",
    "sg:postcode":"01089",
    "sg:province":"MA",
    "sg:tags":[
        "church"
    ],
    "wof:name":"Holy Ghost Temple Church",
    "wof:placetype":"venue"
},
  "geometry": {"coordinates":[-72.63236499999999,42.148755],"type":"Point"}
}