{
  "type": "Feature",
  "properties": {
    "iso:country":"US",
    "sg:address":"255 Park Ave",
    "sg:city":"Worcester",
    "sg:classifiers":[
        {
            "category":"Professional",
            "subcategory":"Lawyer & Legal Services",
            "type":"Services"
        }
    ],
    "sg:phone":"+1 508 757 9707",
    "sg:postcode":"01609",
    "sg:province":"MA",
    "sg:tags":[
        "attorney"
    ],
    "wof:name":"James A Maniatis Law Office",
    "wof:placetype":"venue"
},
  "geometry": {"coordinates":[-71.81870000000001,42.265516],"type":"Point"}
}