{
  "type": "Feature",
  "properties": {
    "iso:country":"US",
    "sg:address":"115 Williams St",
    "sg:city":"Wrentham",
    "sg:classifiers":[
        {
            "category":"Retail",
            "subcategory":"Portrait Studio",
            "type":"Services"
        }
    ],
    "sg:phone":"+1 508 660 0400",
    "sg:postcode":"02093",
    "sg:province":"MA",
    "sg:tags":[
        "photographer"
    ],
    "wof:name":"Coleman Photography",
    "wof:placetype":"venue"
},
  "geometry": {"coordinates":[-71.41411600000001,42.031095],"type":"Point"}
}