{
  "type": "Feature",
  "properties": {
    "addr:full":"34 Cambridge Tpke Lincoln MA 01773",
    "addr:housenumber":"34",
    "addr:postcode":"01773",
    "addr:street":"Cambridge Tpke",
    "iso:country":"US",
    "sg:address":"34 Cambridge Tpke",
    "sg:city":"Lincoln",
    "sg:classifiers":[
        {
            "category":"Arts & Performance",
            "subcategory":"Theater",
            "type":"Entertainment"
        }
    ],
    "sg:phone":"+1   ",
    "sg:postcode":"01773",
    "sg:province":"MA",
    "sg:tags":[
        "theatrical"
    ],
    "wof:name":"Smith Hill Productions",
    "wof:placetype":"venue"
},
  "geometry": {"coordinates":[-71.311787,42.446735],"type":"Point"}
}