{
  "type": "Feature",
  "properties": {
    "iso:country":"US",
    "sg:address":"114 Main St",
    "sg:city":"Carver",
    "sg:classifiers":[
        {
            "category":"Restaurant",
            "type":"Food & Drink"
        }
    ],
    "sg:phone":"+1 508 866 7422",
    "sg:postcode":"02330",
    "sg:province":"MA",
    "wof:name":"Dandy Donuts",
    "wof:placetype":"venue"
},
  "geometry": {"coordinates":[-70.767128,41.886299],"type":"Point"}
}