{
  "type": "Feature",
  "properties": {
    "addr:full": "77 Turnpike Rd Bldg B Ipswich MA 01938",
    "addr:housenumber": "77",
    "addr:postcode": "01938",
    "addr:street": "Turnpike Rd Bldg B",
    "iso:country": "US",
    "sg:address": "77 Turnpike Rd Bldg B",
    "sg:city": "Ipswich",
    "sg:classifiers": [
      {
        "category": "Personal",
        "subcategory": "Massage",
        "type": "Services"
      }
    ],
    "sg:phone": "+1 978 500 7807",
    "sg:postcode": "01938",
    "sg:province": "MA",
    "wof:name": "Jeffrey Dooling LMT NCTMB",
    "wof:placetype": "venue"
  },
  "geometry": {"coordinates":[-70.916818,42.686625],"type":"Point"}
}
