{
  "type": "Feature",
  "properties": {
    "iso:country":"US",
    "sg:address":"108 Devir St",
    "sg:city":"Malden",
    "sg:classifiers":[
        {
            "category":"Sports & Exercise",
            "subcategory":"Gym",
            "type":"Entertainment"
        }
    ],
    "sg:phone":"+1   ",
    "sg:postcode":"02148",
    "sg:province":"MA",
    "sg:tags":[
        "personal",
        "training",
        "fitness"
    ],
    "wof:name":"Progressive Muscle & Fitness",
    "wof:placetype":"venue"
},
  "geometry": {"coordinates":[-71.08251,42.415875],"type":"Point"}
}