{
  "type": "Feature",
  "properties": {
    "iso:country":"US",
    "sg:address":"751 Main St Ste 25",
    "sg:city":"Waltham",
    "sg:classifiers":[
        {
            "category":"Health Services",
            "subcategory":"Doctor",
            "type":"Services"
        },
        {
            "category":"Health Services",
            "subcategory":"Clinic",
            "type":"Services"
        },
        {
            "category":"Community Center",
            "type":"Public Place"
        },
        {
            "category":"Health Services",
            "subcategory":"Chiropractor",
            "type":"Services"
        }
    ],
    "sg:phone":"+1 781 894 4890",
    "sg:postcode":"02451",
    "sg:province":"MA",
    "sg:tags":[
        "physician",
        "medical",
        "surgeon",
        "chiropractic"
    ],
    "wof:name":"Wolk Ellen Dc",
    "wof:placetype":"venue"
},
  "geometry": {"coordinates":[-71.240313,42.376201],"type":"Point"}
}