{
  "type": "Feature",
  "properties": {
    "iso:country":"US",
    "sg:address":"1 State St",
    "sg:city":"Boston",
    "sg:classifiers":[
        {
            "category":"Wholesale",
            "subcategory":"Painting Supplies",
            "type":"Manufacturing & Wholesale Goods"
        },
        {
            "category":"Home & Garden",
            "subcategory":"Building Materials",
            "type":"Retail Goods"
        },
        {
            "category":"Building & Trades",
            "subcategory":"Construction",
            "type":"Services"
        }
    ],
    "sg:phone":"+1 617 263 7592",
    "sg:postcode":"02109",
    "sg:province":"MA",
    "sg:tags":[
        "paint",
        "wallpaper",
        "wallcoverings",
        "contractor"
    ],
    "wof:name":"Amex",
    "wof:placetype":"venue"
},
  "geometry": {"coordinates":[-71.05783099999999,42.35878],"type":"Point"}
}