{
  "type": "Feature",
  "properties": {
    "addr:full": "1 State St Boston MA 02109",
    "addr:housenumber": "1",
    "addr:postcode": "02109",
    "addr:street": "State St",
    "iso:country": "US",
    "sg:address": "1 State St",
    "sg:city": "Boston",
    "sg:classifiers": [
      {
        "category": "Wholesale",
        "subcategory": "Painting Supplies",
        "type": "Manufacturing \u0026 Wholesale Goods"
      },
      {
        "category": "Home \u0026 Garden",
        "subcategory": "Building Materials",
        "type": "Retail Goods"
      },
      {
        "category": "Building \u0026 Trades",
        "subcategory": "Construction",
        "type": "Services"
      }
    ],
    "sg:phone": "+1 617 263 7592",
    "sg:postcode": "02109",
    "sg:province": "MA",
    "sg:tags": [
      "paint",
      "wallpaper",
      "wallcoverings",
      "contractor"
    ],
    "wof:name": "Amex",
    "wof:placetype": "venue"
  },
  "geometry": {"coordinates":[-71.057831,42.35878],"type":"Point"}
}
