{
  "type": "Feature",
  "properties": {
    "addr:full": "121 Woodland Dr Framingham MA 01701",
    "addr:housenumber": "121",
    "addr:postcode": "01701",
    "addr:street": "Woodland Dr",
    "iso:country": "US",
    "sg:address": "121 Woodland Dr",
    "sg:city": "Framingham",
    "sg:classifiers": [
      {
        "category": "Banks \u0026 Credit Unions",
        "subcategory": "Investment Brokerage",
        "type": "Services"
      }
    ],
    "sg:phone": "+1 508 877 8600",
    "sg:postcode": "01701",
    "sg:province": "MA",
    "sg:tags": [
      "consultant",
      "planning",
      "financial"
    ],
    "wof:name": "Valcor Capital Insurance",
    "wof:placetype": "venue"
  },
  "geometry": {"coordinates":[-71.431238,42.312476],"type":"Point"}
}
