{
  "type": "Feature",
  "properties": {
    "iso:country":"US",
    "sg:address":"121 Woodland Dr",
    "sg:city":"Framingham",
    "sg:classifiers":[
        {
            "category":"Banks & Credit Unions",
            "subcategory":"Investment Brokerage",
            "type":"Services"
        }
    ],
    "sg:phone":"+1 508 877 8600",
    "sg:postcode":"01701",
    "sg:province":"MA",
    "sg:tags":[
        "consultant",
        "planning",
        "financial"
    ],
    "wof:name":"Valcor Capital Insurance",
    "wof:placetype":"venue"
},
  "geometry": {"coordinates":[-71.43123799999999,42.312476],"type":"Point"}
}