{
  "type": "Feature",
  "properties": {
    "addr:full":"325 Manomet Point Rd Plymouth MA 02360",
    "addr:housenumber":"325",
    "addr:postcode":"02360",
    "addr:street":"Manomet Point Rd",
    "iso:country":"US",
    "sg:address":"325 Manomet Point Rd",
    "sg:city":"Plymouth",
    "sg:classifiers":[
        {
            "category":"Wholesale",
            "subcategory":"Seafood",
            "type":"Manufacturing & Wholesale Goods"
        }
    ],
    "sg:phone":"+1 508 224 5600",
    "sg:postcode":"02360",
    "sg:province":"MA",
    "sg:website":"www.lobsterpound1.com",
    "wof:name":"Lobster Pound",
    "wof:placetype":"venue"
},
  "geometry": {"coordinates":[-70.541093,41.923543],"type":"Point"}
}