{
  "type": "Feature",
  "properties": {
    "addr:full": "33 Electric Ave Ste 102 - 205 Fitchburg MA 01420",
    "addr:housenumber": "33;205",
    "addr:postcode": "01420",
    "addr:street": "Electric Ave Ste 102",
    "iso:country": "US",
    "sg:address": "33 Electric Ave Ste 102 - 205",
    "sg:city": "Fitchburg",
    "sg:classifiers": [
      {
        "category": "Health Services",
        "subcategory": "Doctor",
        "type": "Services"
      },
      {
        "category": "Health Services",
        "subcategory": "Optometrist",
        "type": "Services"
      },
      {
        "category": "Health Services",
        "subcategory": "Health Practitioner",
        "type": "Services"
      }
    ],
    "sg:phone": "+1 978 342 8752",
    "sg:postcode": "01420",
    "sg:province": "MA",
    "sg:tags": [
      "physician",
      "reconstructive",
      "surgeons",
      "cosmetic",
      "plastic",
      "ophthalmology",
      "surgery",
      "surgeon"
    ],
    "sg:website": "http://www.eyedocs33.com",
    "wof:name": "Fay Stuart S MD PC",
    "wof:placetype": "venue"
  },
  "geometry": {"coordinates":[-71.798415,42.568316],"type":"Point"}
}
