{
  "type": "Feature",
  "properties": {
    "addr:full": "255 State St Boston MA 02109",
    "addr:housenumber": "255",
    "addr:postcode": "02109",
    "addr:street": "State St",
    "iso:country": "US",
    "sg:address": "255 State St",
    "sg:city": "Boston",
    "sg:classifiers": [
      {
        "category": "Government",
        "subcategory": "Office",
        "type": "Public Place"
      }
    ],
    "sg:phone": "+1   ",
    "sg:postcode": "02109",
    "sg:province": "MA",
    "sg:tags": [
      "executive"
    ],
    "wof:name": "Diversified Search",
    "wof:placetype": "venue"
  },
  "geometry": {"coordinates":[-71.051301,42.359661],"type":"Point"}
}
