{
  "type": "Feature",
  "properties": {
    "iso:country":"US",
    "sg:address":"259 Beacon St",
    "sg:city":"Boston",
    "sg:classifiers":[
        {
            "category":"Banks & Credit Unions",
            "subcategory":"Investment Brokerage",
            "type":"Services"
        }
    ],
    "sg:phone":"+1 617 424 1083",
    "sg:postcode":"02116",
    "sg:province":"MA",
    "sg:tags":[
        "trust"
    ],
    "wof:name":"259 Beacon St Condo Trust",
    "wof:placetype":"venue"
},
  "geometry": {"coordinates":[-71.07922499999999,42.353602],"type":"Point"}
}