{
  "type": "Feature",
  "properties": {
    "iso:country":"US",
    "sg:address":"32 Powder Mill Rd",
    "sg:city":"Maynard",
    "sg:classifiers":[
        {
            "category":"Professional",
            "subcategory":"Lawyer & Legal Services",
            "type":"Services"
        }
    ],
    "sg:phone":"+1   ",
    "sg:postcode":"01754",
    "sg:province":"MA",
    "wof:name":"Emile L Genest",
    "wof:placetype":"venue"
},
  "geometry": {"coordinates":[-71.446774,42.433994],"type":"Point"}
}