{
  "type": "Feature",
  "properties": {
    "iso:country":"US",
    "sg:address":"605 Centre St",
    "sg:city":"Brockton",
    "sg:classifiers":[
        {
            "category":"Insurance",
            "subcategory":"Insurance Agent",
            "type":"Services"
        }
    ],
    "sg:phone":"+1 508 583 3699",
    "sg:postcode":"02302",
    "sg:province":"MA",
    "wof:name":"Thompson Insurance",
    "wof:placetype":"venue"
},
  "geometry": {"coordinates":[-70.99375000000001,42.085773],"type":"Point"}
}