{
  "type": "Feature",
  "properties": {
    "addr:full": "605 Centre St Brockton MA 02302",
    "addr:housenumber": "605",
    "addr:postcode": "02302",
    "addr:street": "Centre St",
    "iso:country": "US",
    "sg:address": "605 Centre St",
    "sg:city": "Brockton",
    "sg:classifiers": [
      {
        "category": "Insurance",
        "subcategory": "Insurance Agent",
        "type": "Services"
      }
    ],
    "sg:phone": "+1 508 583 3699",
    "sg:postcode": "02302",
    "sg:province": "MA",
    "wof:name": "Thompson Insurance",
    "wof:placetype": "venue"
  },
  "geometry": {"coordinates":[-70.99375,42.085773],"type":"Point"}
}
