{
  "type": "Feature",
  "properties": {
    "addr:full":"272 Farrwood Dr Haverhill MA 01835",
    "addr:housenumber":"272",
    "addr:postcode":"01835",
    "addr:street":"Farrwood Dr",
    "iso:country":"US",
    "sg:address":"272 Farrwood Dr",
    "sg:city":"Haverhill",
    "sg:classifiers":[
        {
            "category":"Professional",
            "type":"Services"
        }
    ],
    "sg:phone":"+1   ",
    "sg:postcode":"01835",
    "sg:province":"MA",
    "wof:name":"Ms Margaret Bonanno",
    "wof:placetype":"venue"
},
  "geometry": {"coordinates":[-71.107125,42.740889],"type":"Point"}
}