{
  "type": "Feature",
  "properties": {
    "iso:country":"US",
    "sg:address":"17 Gray St",
    "sg:city":"Cambridge",
    "sg:classifiers":[
        {
            "category":"Professional",
            "subcategory":"Advertising",
            "type":"Services"
        }
    ],
    "sg:phone":"+1   ",
    "sg:postcode":"02138",
    "sg:province":"MA",
    "wof:name":"Ollie Hallowell Worldwide",
    "wof:placetype":"venue"
},
  "geometry": {"coordinates":[-71.122722,42.383617],"type":"Point"}
}