{
  "type": "Feature",
  "properties": {
    "iso:country":"US",
    "sg:address":"111 Washington St",
    "sg:city":"Quincy",
    "sg:classifiers":[
        {
            "category":"Restaurant",
            "type":"Food & Drink"
        }
    ],
    "sg:phone":"+1 617 479 3561",
    "sg:postcode":"02169",
    "sg:province":"MA",
    "wof:name":"Bickford's Family Restaurant",
    "wof:placetype":"venue"
},
  "geometry": {"coordinates":[-70.998634,42.250297],"type":"Point"}
}