{
  "type": "Feature",
  "properties": {
    "addr:full": "1106 N Main St Randolph MA 02368",
    "addr:housenumber": "1106",
    "addr:postcode": "02368",
    "addr:street": "N Main St",
    "iso:country": "US",
    "sg:address": "1106 N Main St",
    "sg:city": "Randolph",
    "sg:classifiers": [
      {
        "category": "Shopping",
        "subcategory": "Books",
        "type": "Retail Goods"
      }
    ],
    "sg:phone": "+1 781 961 4989",
    "sg:postcode": "02368",
    "sg:province": "MA",
    "sg:tags": [
      "dealer"
    ],
    "wof:name": "Israel Book Shop Inc",
    "wof:placetype": "venue"
  },
  "geometry": {"coordinates":[-71.060026,42.193096],"type":"Point"}
}
