{
  "type": "Feature",
  "properties": {
    "iso:country":"US",
    "sg:address":"1 Meeting House Rd",
    "sg:city":"Chelmsford",
    "sg:classifiers":[
        {
            "category":"Health Services",
            "subcategory":"Clinic",
            "type":"Services"
        }
    ],
    "sg:phone":"+1 978 256 1288",
    "sg:postcode":"01824",
    "sg:province":"MA",
    "sg:tags":[
        "counseling",
        "mental"
    ],
    "wof:name":"Stone Carolyn R",
    "wof:placetype":"venue"
},
  "geometry": {"coordinates":[-71.3498,42.600498],"type":"Point"}
}