{
  "type": "Feature",
  "properties": {
    "addr:full": "6 Holbrook Rd Oxford MA 01540",
    "addr:housenumber": "6",
    "addr:postcode": "01540",
    "addr:street": "Holbrook Rd",
    "iso:country": "US",
    "sg:address": "6 Holbrook Rd",
    "sg:city": "Oxford",
    "sg:classifiers": [
      {
        "category": "Manufacturing",
        "subcategory": "Signs",
        "type": "Manufacturing \u0026 Wholesale Goods"
      }
    ],
    "sg:phone": "+1 508 987 2233",
    "sg:postcode": "01540",
    "sg:province": "MA",
    "sg:tags": [
      "advertising",
      "specialty"
    ],
    "wof:name": "Flint Signs",
    "wof:placetype": "venue"
  },
  "geometry": {"coordinates":[-71.867488,42.097505],"type":"Point"}
}
