{
  "type": "Feature",
  "properties": {
    "iso:country":"US",
    "sg:address":"6 Holbrook Rd",
    "sg:city":"Oxford",
    "sg:classifiers":[
        {
            "category":"Manufacturing",
            "subcategory":"Signs",
            "type":"Manufacturing & Wholesale Goods"
        }
    ],
    "sg:phone":"+1 508 987 2233",
    "sg:postcode":"01540",
    "sg:province":"MA",
    "sg:tags":[
        "advertising",
        "specialty"
    ],
    "wof:name":"Flint Signs",
    "wof:placetype":"venue"
},
  "geometry": {"coordinates":[-71.86748799999999,42.097505],"type":"Point"}
}