{
  "type": "Feature",
  "properties": {
    "addr:full": "13 Greenleaf Rd Norwood MA 02062",
    "addr:housenumber": "13",
    "addr:postcode": "02062",
    "addr:street": "Greenleaf Rd",
    "iso:country": "US",
    "sg:address": "13 Greenleaf Rd",
    "sg:city": "Norwood",
    "sg:classifiers": [
      {
        "category": "Professional",
        "subcategory": "Management \u0026 Consulting",
        "type": "Services"
      }
    ],
    "sg:phone": "+1 781 762 1678",
    "sg:postcode": "02062",
    "sg:province": "MA",
    "sg:tags": [
      "consultant"
    ],
    "wof:name": "School Consulting Svc",
    "wof:placetype": "venue"
  },
  "geometry": {"coordinates":[-71.201399,42.205123],"type":"Point"}
}
