{
  "type": "Feature",
  "properties": {
    "iso:country":"US",
    "sg:address":"10 High St Ste 810",
    "sg:city":"Boston",
    "sg:classifiers":[
        {
            "category":"Professional",
            "subcategory":"Lawyer & Legal Services",
            "type":"Services"
        }
    ],
    "sg:phone":"+1 617 542 7688",
    "sg:postcode":"02110",
    "sg:province":"MA",
    "wof:name":"Joyce Wm D Lwyr",
    "wof:placetype":"venue"
},
  "geometry": {"coordinates":[-71.05680099999999,42.353401],"type":"Point"}
}