{
  "type": "Feature",
  "properties": {
    "addr:full": "7 Belmont St Northborough MA 01560",
    "addr:housenumber": "7",
    "addr:postcode": "01560",
    "addr:street": "Belmont St",
    "iso:country": "US",
    "sg:address": "7 Belmont St",
    "sg:city": "Northborough",
    "sg:classifiers": [
      {
        "category": "Shopping",
        "subcategory": "Bicycles \u0026 Sporting Goods",
        "type": "Retail Goods"
      }
    ],
    "sg:phone": "+1 508 366 6660",
    "sg:postcode": "01560",
    "sg:province": "MA",
    "sg:tags": [
      "gun",
      "gunsmith"
    ],
    "wof:name": "P G Dowd Firearms",
    "wof:placetype": "venue"
  },
  "geometry": {"coordinates":[-71.68716,42.175646],"type":"Point"}
}
