{
  "type": "Feature",
  "properties": {
    "iso:country":"US",
    "sg:address":"7 Belmont St",
    "sg:city":"Northborough",
    "sg:classifiers":[
        {
            "category":"Shopping",
            "subcategory":"Bicycles & Sporting Goods",
            "type":"Retail Goods"
        }
    ],
    "sg:phone":"+1 508 366 6660",
    "sg:postcode":"01560",
    "sg:province":"MA",
    "sg:tags":[
        "gun",
        "gunsmith"
    ],
    "wof:name":"P G Dowd Firearms",
    "wof:placetype":"venue"
},
  "geometry": {"coordinates":[-71.68716000000001,42.175646],"type":"Point"}
}