{
  "type": "Feature",
  "properties": {
    "iso:country":"US",
    "sg:address":"429 River St",
    "sg:city":"Waltham",
    "sg:classifiers":[
        {
            "category":"Bars & Pubs",
            "type":"Food & Drink"
        }
    ],
    "sg:phone":"+1 781 894 4699",
    "sg:postcode":"02453",
    "sg:province":"MA",
    "wof:name":"Reef",
    "wof:placetype":"venue"
},
  "geometry": {"coordinates":[-71.23251399999999,42.374165],"type":"Point"}
}