{
  "type": "Feature",
  "properties": {
    "addr:full": "429 River St Waltham MA 02453",
    "addr:housenumber": "429",
    "addr:postcode": "02453",
    "addr:street": "River St",
    "iso:country": "US",
    "sg:address": "429 River St",
    "sg:city": "Waltham",
    "sg:classifiers": [
      {
        "category": "Bars \u0026 Pubs",
        "type": "Food \u0026 Drink"
      }
    ],
    "sg:phone": "+1 781 894 4699",
    "sg:postcode": "02453",
    "sg:province": "MA",
    "wof:name": "Reef",
    "wof:placetype": "venue"
  },
  "geometry": {"coordinates":[-71.232514,42.374165],"type":"Point"}
}
