{
  "type": "Feature",
  "properties": {
    "addr:full":"43 Peregrine Rd Newton MA 02459",
    "addr:housenumber":"43",
    "addr:postcode":"02459",
    "addr:street":"Peregrine Rd",
    "iso:country":"US",
    "sg:address":"43 Peregrine Rd",
    "sg:city":"Newton",
    "sg:classifiers":[
        {
            "category":"Professional",
            "subcategory":"Engineering",
            "type":"Services"
        }
    ],
    "sg:phone":"+1 617 332 7101",
    "sg:postcode":"02459",
    "sg:province":"MA",
    "sg:tags":[
        "engineer"
    ],
    "wof:name":"Collaborative Consulting Group",
    "wof:placetype":"venue"
},
  "geometry": {"coordinates":[-71.177378,42.295701],"type":"Point"}
}