{
  "type": "Feature",
  "properties": {
    "iso:country":"US",
    "sg:address":"681 Tremont St Ste 2",
    "sg:city":"Boston",
    "sg:classifiers":[
        {
            "category":"Wholesale",
            "subcategory":"Painting Supplies",
            "type":"Manufacturing & Wholesale Goods"
        },
        {
            "category":"Manufacturing",
            "subcategory":"Chemicals & Compounds",
            "type":"Manufacturing & Wholesale Goods"
        },
        {
            "category":"Building & Trades",
            "subcategory":"Construction",
            "type":"Services"
        }
    ],
    "sg:phone":"+1 617 424 4969",
    "sg:postcode":"02118",
    "sg:province":"MA",
    "sg:tags":[
        "industrial",
        "altering",
        "removing",
        "contractor",
        "paint",
        "contractors-commercial",
        "remodeling"
    ],
    "sg:website":"http://www.newlookspainting.com",
    "wof:name":"New Looks Painting and Contracting",
    "wof:placetype":"venue"
},
  "geometry": {"coordinates":[-71.076453,42.341365],"type":"Point"}
}