{
  "type": "Feature",
  "properties": {
    "iso:country":"US",
    "sg:address":"176 Humboldt Ave",
    "sg:city":"Dorchester",
    "sg:classifiers":[
        {
            "category":"Health Services",
            "subcategory":"Nursing And Care Facility",
            "type":"Services"
        }
    ],
    "sg:phone":"+1 617 445 5224",
    "sg:postcode":"02121",
    "sg:province":"MA",
    "sg:tags":[
        "home",
        "convalescent"
    ],
    "wof:name":"Sheriff Manor Nursing Home",
    "wof:placetype":"venue"
},
  "geometry": {"coordinates":[-71.089399,42.313257],"type":"Point"}
}