{
  "type": "Feature",
  "properties": {
    "addr:full":"1071 Dwight St Springfield MA 01107",
    "addr:housenumber":"1071",
    "addr:postcode":"01107",
    "addr:street":"Dwight St",
    "iso:country":"US",
    "sg:address":"1071 Dwight St",
    "sg:city":"Springfield",
    "sg:classifiers":[
        {
            "category":"Freight",
            "type":"Transportation"
        }
    ],
    "sg:phone":"+1 413 732 7411",
    "sg:postcode":"01107",
    "sg:province":"MA",
    "sg:tags":[
        "broker",
        "trucking"
    ],
    "wof:name":"Bay State Transportation",
    "wof:placetype":"venue"
},
  "geometry": {"coordinates":[-72.59930799999999,42.111965],"type":"Point"}
}