{
  "type": "Feature",
  "properties": {
    "iso:country":"US",
    "sg:address":"211 Liberty Sq",
    "sg:city":"Danvers",
    "sg:classifiers":[
        {
            "category":"Manufacturing",
            "subcategory":"Tools & Machinery",
            "type":"Manufacturing & Wholesale Goods"
        }
    ],
    "sg:phone":"+1 978 762 5588",
    "sg:postcode":"01923",
    "sg:province":"MA",
    "sg:tags":[
        "physician",
        "surgeon"
    ],
    "wof:name":"Oliver Lipman & Assoc",
    "wof:placetype":"venue"
},
  "geometry": {"coordinates":[-70.922093,42.559579],"type":"Point"}
}