{
  "type": "Feature",
  "properties": {
    "addr:full": "675 Massachusetts Avenue Cambridge MA 02139",
    "addr:housenumber": "675",
    "addr:postcode": "02139",
    "addr:street": "Massachusetts Avenue",
    "iso:country": "US",
    "sg:address": "675 Massachusetts Avenue",
    "sg:city": "Cambridge",
    "sg:classifiers": [
      {
        "category": "Professional",
        "subcategory": "Computer Services",
        "type": "Services"
      }
    ],
    "sg:phone": "+1 877 777 9910",
    "sg:postcode": "02139",
    "sg:province": "MA",
    "sg:tags": [
      "digital-signage",
      "dooh",
      "digital-out-of-home",
      "outdoor-displays",
      "networked-displays",
      "advertising",
      "electronic-displays",
      "saas",
      "social-media",
      "mobile-interactivity",
      "widgets",
      "events",
      "interactive-campaign",
      "mobile",
      "digital-signage-software",
      "web-based",
      "media-content"
    ],
    "sg:website": "http://www.aerva.com",
    "wof:name": "Aerva",
    "wof:placetype": "venue"
  },
  "geometry": {"coordinates":[-71.10448,42.365912],"type":"Point"}
}
