{
  "type": "Feature",
  "properties": {
    "addr:full":"1425 Main St Waltham MA 02451",
    "addr:housenumber":"1425",
    "addr:postcode":"02451",
    "addr:street":"Main St",
    "iso:country":"US",
    "sg:address":"1425 Main St",
    "sg:city":"Waltham",
    "sg:classifiers":[
        {
            "category":"Food & Beverages",
            "subcategory":"Bakery",
            "type":"Retail Goods"
        }
    ],
    "sg:phone":"+1 508 660 6136",
    "sg:postcode":"02451",
    "sg:province":"MA",
    "sg:tags":[
        "bagel"
    ],
    "wof:name":"Dunkin Donuts",
    "wof:placetype":"venue"
},
  "geometry": {"coordinates":[-71.269488,42.376858],"type":"Point"}
}