{
  "type": "Feature",
  "properties": {
    "iso:country":"US",
    "sg:address":"47 Huntington Ave",
    "sg:city":"Boston",
    "sg:classifiers":[
        {
            "category":"Travel",
            "subcategory":"Hotels & Motels",
            "type":"Entertainment"
        }
    ],
    "sg:phone":"+1 617 536 9000",
    "sg:postcode":"02116",
    "sg:province":"MA",
    "sg:website":"CopleySquareHotel.com",
    "wof:name":"Copley Square Hotel",
    "wof:placetype":"venue"
},
  "geometry": {"coordinates":[-71.078654,42.348411],"type":"Point"}
}