{
  "type": "Feature",
  "properties": {
    "iso:country":"US",
    "sg:address":"6 Somerset Dr",
    "sg:city":"Andover",
    "sg:classifiers":[
        {
            "category":"Farming",
            "subcategory":"Nursery",
            "type":"Manufacturing & Wholesale Goods"
        }
    ],
    "sg:phone":"+1 978 974 9456",
    "sg:postcode":"01810",
    "sg:province":"MA",
    "sg:tags":[
        "greenhouse"
    ],
    "wof:name":"Griffin Greenhouse Supplies",
    "wof:placetype":"venue"
},
  "geometry": {"coordinates":[-71.19598999999999,42.683431],"type":"Point"}
}