{
  "type": "Feature",
  "properties": {
    "addr:full": "6 Somerset Dr Andover MA 01810",
    "addr:housenumber": "6",
    "addr:postcode": "01810",
    "addr:street": "Somerset Dr",
    "iso:country": "US",
    "sg:address": "6 Somerset Dr",
    "sg:city": "Andover",
    "sg:classifiers": [
      {
        "category": "Farming",
        "subcategory": "Nursery",
        "type": "Manufacturing \u0026 Wholesale Goods"
      }
    ],
    "sg:phone": "+1 978 974 9456",
    "sg:postcode": "01810",
    "sg:province": "MA",
    "sg:tags": [
      "greenhouse"
    ],
    "wof:name": "Griffin Greenhouse Supplies",
    "wof:placetype": "venue"
  },
  "geometry": {"coordinates":[-71.19599,42.683431],"type":"Point"}
}
