{
  "type": "Feature",
  "properties": {
    "addr:full":"6 Gill St Woburn MA 01801",
    "addr:housenumber":"6",
    "addr:postcode":"01801",
    "addr:street":"Gill St",
    "iso:country":"US",
    "sg:address":"6 Gill St",
    "sg:city":"Woburn",
    "sg:classifiers":[
        {
            "category":"Education",
            "subcategory":"Special Training",
            "type":"Public Place"
        }
    ],
    "sg:phone":"+1 781 376 0891",
    "sg:postcode":"01801",
    "sg:province":"MA",
    "sg:tags":[
        "educational"
    ],
    "wof:name":"Clinical Education",
    "wof:placetype":"venue"
},
  "geometry": {"coordinates":[-71.14711699999999,42.509818],"type":"Point"}
}