{
  "type": "Feature",
  "properties": {
    "addr:full":"14 Main St Upton MA 01568",
    "addr:housenumber":"14",
    "addr:postcode":"01568",
    "addr:street":"Main St",
    "iso:country":"US",
    "sg:address":"14 Main St",
    "sg:city":"Upton",
    "sg:classifiers":[
        {
            "category":"Retail",
            "subcategory":"Auto Repair",
            "type":"Services"
        }
    ],
    "sg:phone":"+1 508 529 1401",
    "sg:postcode":"01568",
    "sg:province":"MA",
    "sg:tags":[
        "repairing",
        "automobile"
    ],
    "wof:name":"MGM Auto Repair",
    "wof:placetype":"venue"
},
  "geometry": {"coordinates":[-71.604552,42.171295],"type":"Point"}
}