{
  "type": "Feature",
  "properties": {
    "addr:full":"55 Spring St Williamstown MA 01267",
    "addr:housenumber":"55",
    "addr:postcode":"01267",
    "addr:street":"Spring St",
    "iso:country":"US",
    "sg:address":"55 Spring St",
    "sg:city":"Williamstown",
    "sg:classifiers":[
        {
            "category":"Cinema",
            "subcategory":"Movie Theater",
            "type":"Entertainment"
        }
    ],
    "sg:phone":"+1 413 458 5612",
    "sg:postcode":"01267",
    "sg:province":"MA",
    "wof:name":"Images Cinema",
    "wof:placetype":"venue"
},
  "geometry": {"coordinates":[-73.20426399999999,42.7106],"type":"Point"}
}