{
  "type": "Feature",
  "properties": {
    "iso:country":"US",
    "sg:address":"74 Tennis Plaza Rd",
    "sg:city":"Dracut",
    "sg:classifiers":[
        {
            "category":"Retail",
            "subcategory":"Repair Shop",
            "type":"Services"
        }
    ],
    "sg:phone":"+1   ",
    "sg:postcode":"01826",
    "sg:province":"MA",
    "wof:name":"Startrite Small Engine Svc",
    "wof:placetype":"venue"
},
  "geometry": {"coordinates":[-71.34341999999999,42.677717],"type":"Point"}
}