{
  "type": "Feature",
  "properties": {
    "addr:full": "1316 Beacon St Brookline MA 02446",
    "addr:housenumber": "1316",
    "addr:postcode": "02446",
    "addr:street": "Beacon St",
    "iso:country": "US",
    "sg:address": "1316 Beacon St",
    "sg:city": "Brookline",
    "sg:classifiers": [
      {
        "category": "Building \u0026 Trades",
        "subcategory": "Locksmith",
        "type": "Services"
      }
    ],
    "sg:phone": "+1 617 245 8220",
    "sg:postcode": "02446",
    "sg:province": "MA",
    "sg:tags": [
      "key"
    ],
    "wof:name": "A 24 Locksmith",
    "wof:placetype": "venue"
  },
  "geometry": {"coordinates":[-71.12116,42.342429],"type":"Point"}
}
