{
  "type": "Feature",
  "properties": {
    "iso:country":"US",
    "sg:address":"175 Broadway",
    "sg:city":"Revere",
    "sg:classifiers":[
        {
            "category":"Manufacturing",
            "subcategory":"Glass & Minerals",
            "type":"Manufacturing & Wholesale Goods"
        }
    ],
    "sg:phone":"+1 781 286 7555",
    "sg:postcode":"02151",
    "sg:province":"MA",
    "sg:tags":[
        "glass-wholesale",
        "shape",
        "circle",
        "special",
        "manufacturer"
    ],
    "wof:name":"Glass A Touch Of",
    "wof:placetype":"venue"
},
  "geometry": {"coordinates":[-71.01509900000001,42.405998],"type":"Point"}
}