{
  "type": "Feature",
  "properties": {
    "iso:country":"US",
    "sg:address":"241 Commercial St",
    "sg:city":"Provincetown",
    "sg:classifiers":[
        {
            "category":"Recreation",
            "type":"Entertainment"
        }
    ],
    "sg:phone":"+1 508 487 0976",
    "sg:postcode":"02657",
    "sg:province":"MA",
    "sg:tags":[
        "psychic",
        "medium"
    ],
    "wof:name":"Third Eye",
    "wof:placetype":"venue"
},
  "geometry": {"coordinates":[-70.18778399999999,42.050322],"type":"Point"}
}