{
  "type": "Feature",
  "properties": {
    "addr:full":"150 Kerry Pl Norwood MA 02062",
    "addr:housenumber":"150",
    "addr:postcode":"02062",
    "addr:street":"Kerry Pl",
    "iso:country":"US",
    "sg:address":"150 Kerry Pl",
    "sg:city":"Norwood",
    "sg:classifiers":[
        {
            "category":"Building & Trades",
            "subcategory":"Electrical",
            "type":"Services"
        }
    ],
    "sg:phone":"+1 781 440 9666",
    "sg:postcode":"02062",
    "sg:province":"MA",
    "sg:tags":[
        "electrician"
    ],
    "wof:name":"Electrical Solutions",
    "wof:placetype":"venue"
},
  "geometry": {"coordinates":[-71.192497,42.181099],"type":"Point"}
}