{
  "type": "Feature",
  "properties": {
    "addr:full":"65 Merrimack St Lawrence MA 01843",
    "addr:housenumber":"65",
    "addr:postcode":"01843",
    "addr:street":"Merrimack St",
    "iso:country":"US",
    "sg:address":"65 Merrimack St",
    "sg:city":"Lawrence",
    "sg:classifiers":[
        {
            "category":"Professional",
            "subcategory":"Accounting & Tax Preparation",
            "type":"Services"
        }
    ],
    "sg:phone":"+1 978 681 1760",
    "sg:postcode":"01843",
    "sg:province":"MA",
    "sg:tags":[
        "return",
        "filing"
    ],
    "wof:name":"Meran Tax Svc",
    "wof:placetype":"venue"
},
  "geometry": {"coordinates":[-71.157625,42.701878],"type":"Point"}
}