{
  "type": "Feature",
  "properties": {
    "iso:country":"US",
    "sg:address":"19 Unicorn Cir",
    "sg:city":"Amesbury",
    "sg:classifiers":[
        {
            "category":"Professional",
            "subcategory":"Management & Consulting",
            "type":"Services"
        }
    ],
    "sg:phone":"+1   ",
    "sg:postcode":"01913",
    "sg:province":"MA",
    "wof:name":"Bblm Inc",
    "wof:placetype":"venue"
},
  "geometry": {"coordinates":[-70.950371,42.867914],"type":"Point"}
}