{
  "type": "Feature",
  "properties": {
    "addr:full": "200 E Main St Marlborough MA 01752",
    "addr:housenumber": "200",
    "addr:postcode": "01752",
    "addr:street": "E Main St",
    "iso:country": "US",
    "sg:address": "200 E Main St",
    "sg:city": "Marlborough",
    "sg:classifiers": [
      {
        "category": "Health Services",
        "subcategory": "Health Practitioner",
        "type": "Services"
      }
    ],
    "sg:phone": "+1 508 460 9662",
    "sg:postcode": "01752",
    "sg:province": "MA",
    "sg:tags": [
      "psychotherapist"
    ],
    "wof:name": "Edwards Betsey A Psychothrpst",
    "wof:placetype": "venue"
  },
  "geometry": {"coordinates":[-71.536016,42.351229],"type":"Point"}
}
