{
  "type": "Feature",
  "properties": {
    "iso:country":"US",
    "sg:address":"220 Eliot St",
    "sg:city":"Ashland",
    "sg:classifiers":[
        {
            "category":"Manufacturing",
            "subcategory":"Tools & Machinery",
            "type":"Manufacturing & Wholesale Goods"
        }
    ],
    "sg:phone":"+1 508 881 4428",
    "sg:postcode":"01721",
    "sg:province":"MA",
    "sg:tags":[
        "machine",
        "shop"
    ],
    "wof:name":"Alpha Omega Eng Inc",
    "wof:placetype":"venue"
},
  "geometry": {"coordinates":[-71.43841999999999,42.241362],"type":"Point"}
}