{
  "type": "Feature",
  "properties": {
    "addr:full": "220 Eliot St Ashland MA 01721",
    "addr:housenumber": "220",
    "addr:postcode": "01721",
    "addr:street": "Eliot St",
    "iso:country": "US",
    "sg:address": "220 Eliot St",
    "sg:city": "Ashland",
    "sg:classifiers": [
      {
        "category": "Manufacturing",
        "subcategory": "Tools \u0026 Machinery",
        "type": "Manufacturing \u0026 Wholesale Goods"
      }
    ],
    "sg:phone": "+1 508 881 4428",
    "sg:postcode": "01721",
    "sg:province": "MA",
    "sg:tags": [
      "machine",
      "shop"
    ],
    "wof:name": "Alpha Omega Eng Inc",
    "wof:placetype": "venue"
  },
  "geometry": {"coordinates":[-71.43842,42.241362],"type":"Point"}
}
