{
  "type": "Feature",
  "properties": {
    "iso:country":"US",
    "sg:address":"87 Main St",
    "sg:city":"Wilbraham",
    "sg:classifiers":[
        {
            "category":"Building & Trades",
            "subcategory":"Construction",
            "type":"Services"
        }
    ],
    "sg:phone":"+1   ",
    "sg:postcode":"01095",
    "sg:province":"MA",
    "sg:tags":[
        "house"
    ],
    "wof:name":"Creative Home Improvement",
    "wof:placetype":"venue"
},
  "geometry": {"coordinates":[-72.42738300000001,42.146703],"type":"Point"}
}