{
  "type": "Feature",
  "properties": {
    "addr:full": "87 Main St Wilbraham MA 01095",
    "addr:housenumber": "87",
    "addr:postcode": "01095",
    "addr:street": "Main St",
    "iso:country": "US",
    "sg:address": "87 Main St",
    "sg:city": "Wilbraham",
    "sg:classifiers": [
      {
        "category": "Building \u0026 Trades",
        "subcategory": "Construction",
        "type": "Services"
      }
    ],
    "sg:phone": "+1   ",
    "sg:postcode": "01095",
    "sg:province": "MA",
    "sg:tags": [
      "house"
    ],
    "wof:name": "Creative Home Improvement",
    "wof:placetype": "venue"
  },
  "geometry": {"coordinates":[-72.427383,42.146703],"type":"Point"}
}
