{
  "type": "Feature",
  "properties": {
    "iso:country":"US",
    "sg:address":"44 Grapevine Rd",
    "sg:city":"Gloucester",
    "sg:classifiers":[
        {
            "category":"Wholesale",
            "subcategory":"Seafood",
            "type":"Manufacturing & Wholesale Goods"
        }
    ],
    "sg:phone":"+1 978 283 0687",
    "sg:postcode":"01930",
    "sg:province":"MA",
    "sg:tags":[
        "fish"
    ],
    "wof:name":"Cape Ann Seafoods",
    "wof:placetype":"venue"
},
  "geometry": {"coordinates":[-70.64623,42.599751],"type":"Point"}
}