{
  "type": "Feature",
  "properties": {
    "addr:full":"1173 Bernardston Rd Greenfield MA 01301",
    "addr:housenumber":"1173",
    "addr:postcode":"01301",
    "addr:street":"Bernardston Rd",
    "iso:country":"US",
    "sg:address":"1173 Bernardston Rd",
    "sg:city":"Greenfield",
    "sg:classifiers":[
        {
            "category":"Home & Garden",
            "subcategory":"Furniture",
            "type":"Retail Goods"
        }
    ],
    "sg:phone":"+1 413 774 4714",
    "sg:postcode":"01301",
    "sg:province":"MA",
    "sg:tags":[
        "equipment",
        "kitchen",
        "cabinet"
    ],
    "sg:website":"www.classic-kitchens.com",
    "wof:name":"Classic Kitchens",
    "wof:placetype":"venue"
},
  "geometry": {"coordinates":[-72.562371,42.645629],"type":"Point"}
}