{
  "type": "Feature",
  "properties": {
    "iso:country":"US",
    "sg:address":"135 Market St",
    "sg:city":"Brighton",
    "sg:classifiers":[
        {
            "category":"Building & Trades",
            "subcategory":"Locksmith",
            "type":"Services"
        }
    ],
    "sg:phone":"+1 617 245 8210",
    "sg:postcode":"02135",
    "sg:province":"MA",
    "sg:tags":[
        "key"
    ],
    "wof:name":"A 24 Locksmith",
    "wof:placetype":"venue"
},
  "geometry": {"coordinates":[-71.14835600000001,42.357661],"type":"Point"}
}