{
  "type": "Feature",
  "properties": {
    "addr:full": "135 Market St Brighton MA 02135",
    "addr:housenumber": "135",
    "addr:postcode": "02135",
    "addr:street": "Market St",
    "iso:country": "US",
    "sg:address": "135 Market St",
    "sg:city": "Brighton",
    "sg:classifiers": [
      {
        "category": "Building \u0026 Trades",
        "subcategory": "Locksmith",
        "type": "Services"
      }
    ],
    "sg:phone": "+1 617 245 8210",
    "sg:postcode": "02135",
    "sg:province": "MA",
    "sg:tags": [
      "key"
    ],
    "wof:name": "A 24 Locksmith",
    "wof:placetype": "venue"
  },
  "geometry": {"coordinates":[-71.148356,42.357661],"type":"Point"}
}
