{
  "type": "Feature",
  "properties": {
    "iso:country":"US",
    "sg:address":"125 Tudor Rd",
    "sg:city":"Needham",
    "sg:classifiers":[
        {
            "category":"Real Estate",
            "subcategory":"Real Estate Agent",
            "type":"Services"
        }
    ],
    "sg:phone":"+1   ",
    "sg:postcode":"02492",
    "sg:province":"MA",
    "wof:name":"Korzon Realty Trust",
    "wof:placetype":"venue"
},
  "geometry": {"coordinates":[-71.210971,42.284138],"type":"Point"}
}