{
  "type": "Feature",
  "properties": {
    "iso:country":"US",
    "sg:address":"592 Main St",
    "sg:city":"Hyannis",
    "sg:classifiers":[
        {
            "category":"Shopping",
            "subcategory":"Clothing, Apparel, & Fashions",
            "type":"Retail Goods"
        }
    ],
    "sg:phone":"+1 508 771 6968",
    "sg:postcode":"02601",
    "sg:province":"MA",
    "sg:tags":[
        "item",
        "boutique"
    ],
    "wof:name":"Lot Sound & Style",
    "wof:placetype":"venue"
},
  "geometry": {"coordinates":[-70.29047799999999,41.649474],"type":"Point"}
}