{
  "type": "Feature",
  "properties": {
    "addr:full": "592 Main St Hyannis MA 02601",
    "addr:housenumber": "592",
    "addr:postcode": "02601",
    "addr:street": "Main St",
    "iso:country": "US",
    "sg:address": "592 Main St",
    "sg:city": "Hyannis",
    "sg:classifiers": [
      {
        "category": "Shopping",
        "subcategory": "Clothing, Apparel, \u0026 Fashions",
        "type": "Retail Goods"
      }
    ],
    "sg:phone": "+1 508 771 6968",
    "sg:postcode": "02601",
    "sg:province": "MA",
    "sg:tags": [
      "item",
      "boutique"
    ],
    "wof:name": "Lot Sound \u0026 Style",
    "wof:placetype": "venue"
  },
  "geometry": {"coordinates":[-70.290478,41.649474],"type":"Point"}
}
