{
  "type": "Feature",
  "properties": {
    "iso:country":"US",
    "sg:address":"7 Gerald Rd",
    "sg:city":"Marblehead",
    "sg:classifiers":[
        {
            "category":"Manufacturing",
            "subcategory":"Metals",
            "type":"Manufacturing & Wholesale Goods"
        }
    ],
    "sg:phone":"+1 617 884 7100",
    "sg:postcode":"01945",
    "sg:province":"MA",
    "sg:tags":[
        "steel"
    ],
    "wof:name":"Harold Strogoff Iron Metal",
    "wof:placetype":"venue"
},
  "geometry": {"coordinates":[-70.87069099999999,42.486618],"type":"Point"}
}