{
  "type": "Feature",
  "properties": {
    "addr:full": "7 Gerald Rd Marblehead MA 01945",
    "addr:housenumber": "7",
    "addr:postcode": "01945",
    "addr:street": "Gerald Rd",
    "iso:country": "US",
    "sg:address": "7 Gerald Rd",
    "sg:city": "Marblehead",
    "sg:classifiers": [
      {
        "category": "Manufacturing",
        "subcategory": "Metals",
        "type": "Manufacturing \u0026 Wholesale Goods"
      }
    ],
    "sg:phone": "+1 617 884 7100",
    "sg:postcode": "01945",
    "sg:province": "MA",
    "sg:tags": [
      "steel"
    ],
    "wof:name": "Harold Strogoff Iron Metal",
    "wof:placetype": "venue"
  },
  "geometry": {"coordinates":[-70.870691,42.486618],"type":"Point"}
}
