{
  "type": "Feature",
  "properties": {
    "iso:country":"US",
    "sg:address":"935 Riverdale St",
    "sg:city":"West Springfield",
    "sg:classifiers":[
        {
            "category":"Health Services",
            "subcategory":"Doctor",
            "type":"Services"
        }
    ],
    "sg:phone":"+1 413 737 1800",
    "sg:postcode":"01089",
    "sg:province":"MA",
    "sg:tags":[
        "dentist"
    ],
    "wof:name":"Aspen Dental Assoc",
    "wof:placetype":"venue"
},
  "geometry": {"coordinates":[-72.626548,42.128914],"type":"Point"}
}