{
  "type": "Feature",
  "properties": {
    "addr:full": "154 Whitman St New Bedford MA 02745",
    "addr:housenumber": "154",
    "addr:postcode": "02745",
    "addr:street": "Whitman St",
    "iso:country": "US",
    "sg:address": "154 Whitman St",
    "sg:city": "New Bedford",
    "sg:classifiers": [
      {
        "category": "Personal",
        "type": "Services"
      }
    ],
    "sg:phone": "+1   ",
    "sg:postcode": "02745",
    "sg:province": "MA",
    "wof:name": "To Detail",
    "wof:placetype": "venue"
  },
  "geometry": {"coordinates":[-70.928334,41.667317],"type":"Point"}
}
