{
  "type": "Feature",
  "properties": {
    "addr:full": "704 River St Fitchburg MA 01420",
    "addr:housenumber": "704",
    "addr:postcode": "01420",
    "addr:street": "River St",
    "iso:country": "US",
    "ovtr:label": "OPCO Laboratory, Inc., 704 River St Fitchburg MA US",
    "ovtr:similarity": 2.467329978942871,
    "sg:address": "704 River St",
    "sg:city": "Fitchburg",
    "sg:classifiers": [
      {
        "category": "Manufacturing",
        "subcategory": "Tools \u0026 Machinery",
        "type": "Manufacturing \u0026 Wholesale Goods"
      }
    ],
    "sg:phone": "+1 978 345 2522",
    "sg:postcode": "01420",
    "sg:province": "MA",
    "sg:tags": [
      "laboratory",
      "optical"
    ],
    "sg:website": "www.opcolab.com",
    "wof:name": "OPCO Laboratory Inc",
    "wof:placetype": "venue"
  },
  "geometry": {"coordinates":[-71.83258,42.578228],"type":"Point"}
}
