{
  "type": "Feature",
  "properties": {
    "iso:country":"US",
    "sg:address":"704 River St",
    "sg:city":"Fitchburg",
    "sg:classifiers":[
        {
            "category":"Manufacturing",
            "subcategory":"Tools & Machinery",
            "type":"Manufacturing & Wholesale Goods"
        }
    ],
    "sg:phone":"+1 978 345 2522",
    "sg:postcode":"01420",
    "sg:province":"MA",
    "sg:tags":[
        "laboratory",
        "optical"
    ],
    "sg:website":"www.opcolab.com",
    "wof:name":"OPCO Laboratory Inc",
    "wof:placetype":"venue"
},
  "geometry": {"coordinates":[-71.83257999999999,42.578228],"type":"Point"}
}