{
  "type": "Feature",
  "properties": {
    "addr:full":"9 Mount Pleasant Ave Roxbury MA 02119",
    "addr:housenumber":"9",
    "addr:postcode":"02119",
    "addr:street":"Mount Pleasant Ave",
    "iso:country":"US",
    "sg:address":"9 Mount Pleasant Ave",
    "sg:city":"Roxbury",
    "sg:classifiers":[
        {
            "category":"Building & Trades",
            "subcategory":"Cleaning & Sanitation",
            "type":"Services"
        }
    ],
    "sg:phone":"+1 617 427 4424",
    "sg:postcode":"02119",
    "sg:province":"MA",
    "sg:tags":[
        "cleaning-industrial",
        "contractor"
    ],
    "wof:name":"Bread Winner37 Hollander",
    "wof:placetype":"venue"
},
  "geometry": {"coordinates":[-71.07936100000001,42.32795],"type":"Point"}
}