{
  "type": "Feature",
  "properties": {
    "addr:full":"94 Church St Whitinsville MA 01588",
    "addr:housenumber":"94",
    "addr:postcode":"01588",
    "addr:street":"Church St",
    "iso:country":"US",
    "sg:address":"94 Church St",
    "sg:city":"Whitinsville",
    "sg:classifiers":[
        {
            "category":"Personal",
            "subcategory":"Tanning Parlor",
            "type":"Services"
        }
    ],
    "sg:phone":"+1 508 234 5333",
    "sg:postcode":"01588",
    "sg:province":"MA",
    "sg:tags":[
        "salon"
    ],
    "wof:name":"Copper Mist Airbrush Tanning",
    "wof:placetype":"venue"
},
  "geometry": {"coordinates":[-71.660742,42.111925],"type":"Point"}
}