{
  "type": "Feature",
  "properties": {
    "iso:country":"US",
    "sg:address":"570 Baldwinville Rd",
    "sg:city":"Baldwinville",
    "sg:classifiers":[
        {
            "category":"Health Services",
            "subcategory":"Doctor",
            "type":"Services"
        }
    ],
    "sg:phone":"+1 978 939 2133",
    "sg:postcode":"01436",
    "sg:province":"MA",
    "sg:tags":[
        "physician",
        "surgeon"
    ],
    "wof:name":"Narragansett Family Medicine",
    "wof:placetype":"venue"
},
  "geometry": {"coordinates":[-72.07365299999999,42.593069],"type":"Point"}
}