{
  "type": "Feature",
  "properties": {
    "addr:full": "570 Baldwinville Rd Baldwinville MA 01436",
    "addr:housenumber": "570",
    "addr:postcode": "01436",
    "addr:street": "Baldwinville Rd",
    "iso:country": "US",
    "sg:address": "570 Baldwinville Rd",
    "sg:city": "Baldwinville",
    "sg:classifiers": [
      {
        "category": "Health Services",
        "subcategory": "Doctor",
        "type": "Services"
      }
    ],
    "sg:phone": "+1 978 939 2133",
    "sg:postcode": "01436",
    "sg:province": "MA",
    "sg:tags": [
      "physician",
      "surgeon"
    ],
    "wof:name": "Narragansett Family Medicine",
    "wof:placetype": "venue"
  },
  "geometry": {"coordinates":[-72.073653,42.593069],"type":"Point"}
}
