{
  "type": "Feature",
  "properties": {
    "addr:full":"382 Union St Franklin MA 02038",
    "addr:housenumber":"382",
    "addr:postcode":"02038",
    "addr:street":"Union St",
    "iso:country":"US",
    "sg:address":"382 Union St",
    "sg:city":"Franklin",
    "sg:classifiers":[
        {
            "category":"Wholesale",
            "subcategory":"Non-durable Goods",
            "type":"Manufacturing & Wholesale Goods"
        },
        {
            "category":"Shopping",
            "subcategory":"Clothing, Apparel, & Fashions",
            "type":"Retail Goods"
        }
    ],
    "sg:phone":"+1 508 520 6744",
    "sg:postcode":"02038",
    "sg:province":"MA",
    "sg:tags":[
        "t"
    ],
    "wof:name":"Pisano Designs Inc",
    "wof:placetype":"venue"
},
  "geometry": {"coordinates":[-71.40349500000001,42.075489],"type":"Point"}
}