{
  "type": "Feature",
  "properties": {
    "addr:full": "7 Howard Rd Hudson MA 01749",
    "addr:housenumber": "7",
    "addr:postcode": "01749",
    "addr:street": "Howard Rd",
    "iso:country": "US",
    "sg:address": "7 Howard Rd",
    "sg:city": "Hudson",
    "sg:classifiers": [
      {
        "category": "Professional",
        "subcategory": "Management \u0026 Consulting",
        "type": "Services"
      }
    ],
    "sg:phone": "+1   ",
    "sg:postcode": "01749",
    "sg:province": "MA",
    "sg:tags": [
      "business"
    ],
    "wof:name": "Dahill Consulting",
    "wof:placetype": "venue"
  },
  "geometry": {"coordinates":[-71.572386,42.404422],"type":"Point"}
}
