{
  "type": "Feature",
  "properties": {
    "iso:country":"US",
    "sg:address":"7 Howard Rd",
    "sg:city":"Hudson",
    "sg:classifiers":[
        {
            "category":"Professional",
            "subcategory":"Management & Consulting",
            "type":"Services"
        }
    ],
    "sg:phone":"+1   ",
    "sg:postcode":"01749",
    "sg:province":"MA",
    "sg:tags":[
        "business"
    ],
    "wof:name":"Dahill Consulting",
    "wof:placetype":"venue"
},
  "geometry": {"coordinates":[-71.57238599999999,42.404422],"type":"Point"}
}