{
  "type": "Feature",
  "properties": {
    "addr:full": "103 Keets Rd Deerfield MA 01342",
    "addr:housenumber": "103",
    "addr:postcode": "01342",
    "addr:street": "Keets Rd",
    "iso:country": "US",
    "sg:address": "103 Keets Rd",
    "sg:city": "Deerfield",
    "sg:classifiers": [
      {
        "category": "Social Services",
        "type": "Services"
      }
    ],
    "sg:phone": "+1   ",
    "sg:postcode": "01342",
    "sg:province": "MA",
    "wof:name": "Traprock Peace Centre",
    "wof:placetype": "venue"
  },
  "geometry": {"coordinates":[-72.583638,42.560355],"type":"Point"}
}
