{
  "type": "Feature",
  "properties": {
    "iso:country":"US",
    "sg:address":"103 Keets Rd",
    "sg:city":"Deerfield",
    "sg:classifiers":[
        {
            "category":"Social Services",
            "type":"Services"
        }
    ],
    "sg:phone":"+1   ",
    "sg:postcode":"01342",
    "sg:province":"MA",
    "wof:name":"Traprock Peace Centre",
    "wof:placetype":"venue"
},
  "geometry": {"coordinates":[-72.58363799999999,42.560355],"type":"Point"}
}