{
  "type": "Feature",
  "properties": {
    "iso:country":"US",
    "sg:address":"135 Playstead Rd",
    "sg:city":"Medford",
    "sg:classifiers":[
        {
            "category":"Retail",
            "subcategory":"Auto Repair",
            "type":"Services"
        }
    ],
    "sg:phone":"+1   ",
    "sg:postcode":"02155",
    "sg:province":"MA",
    "sg:tags":[
        "automotive"
    ],
    "wof:name":"Steering Column Specialist",
    "wof:placetype":"venue"
},
  "geometry": {"coordinates":[-71.13457699999999,42.426697],"type":"Point"}
}