{
  "type": "Feature",
  "properties": {
    "addr:full": "135 Playstead Rd Medford MA 02155",
    "addr:housenumber": "135",
    "addr:postcode": "02155",
    "addr:street": "Playstead Rd",
    "iso:country": "US",
    "sg:address": "135 Playstead Rd",
    "sg:city": "Medford",
    "sg:classifiers": [
      {
        "category": "Retail",
        "subcategory": "Auto Repair",
        "type": "Services"
      }
    ],
    "sg:phone": "+1   ",
    "sg:postcode": "02155",
    "sg:province": "MA",
    "sg:tags": [
      "automotive"
    ],
    "wof:name": "Steering Column Specialist",
    "wof:placetype": "venue"
  },
  "geometry": {"coordinates":[-71.134577,42.426697],"type":"Point"}
}
