{
  "type": "Feature",
  "properties": {
    "iso:country":"US",
    "sg:address":"1 Harris St",
    "sg:city":"Newburyport",
    "sg:classifiers":[
        {
            "category":"Manufacturing",
            "subcategory":"Retail Goods",
            "type":"Manufacturing & Wholesale Goods"
        }
    ],
    "sg:phone":"+1 978 462 7343",
    "sg:postcode":"01950",
    "sg:province":"MA",
    "sg:tags":[
        "assembly",
        "fabricating"
    ],
    "sg:website":"www.gamebuilders.com",
    "wof:name":"Taitronics",
    "wof:placetype":"venue"
},
  "geometry": {"coordinates":[-70.871048,42.808516],"type":"Point"}
}