{
  "type": "Feature",
  "properties": {
    "addr:full": "274 South St Hingham MA 02043",
    "addr:housenumber": "274",
    "addr:postcode": "02043",
    "addr:street": "South St",
    "iso:country": "US",
    "sg:address": "274 South St",
    "sg:city": "Hingham",
    "sg:classifiers": [
      {
        "category": "Sports \u0026 Exercise",
        "subcategory": "Bowling",
        "type": "Entertainment"
      }
    ],
    "sg:phone": "+1 781 749 8400",
    "sg:postcode": "02043",
    "sg:province": "MA",
    "sg:tags": [
      "center"
    ],
    "wof:name": "Country Club Lanes",
    "wof:placetype": "venue"
  },
  "geometry": {"coordinates":[-70.902115,42.237626],"type":"Point"}
}
