{
  "type": "Feature",
  "properties": {
    "addr:full":"259 Rock Landing Rd Mashpee MA 02649",
    "addr:housenumber":"259",
    "addr:postcode":"02649",
    "addr:street":"Rock Landing Rd",
    "iso:country":"US",
    "sg:address":"259 Rock Landing Rd",
    "sg:city":"Mashpee",
    "sg:classifiers":[
        {
            "category":"Recreation",
            "type":"Entertainment"
        }
    ],
    "sg:phone":"+1 508 477 7556",
    "sg:postcode":"02649",
    "sg:province":"MA",
    "sg:tags":[
        "course",
        "golf"
    ],
    "wof:name":"Popponesset Mini Golf",
    "wof:placetype":"venue"
},
  "geometry": {"coordinates":[-70.47255,41.570116],"type":"Point"}
}