{
  "type": "Feature",
  "properties": {
    "addr:full":"28 Elm Street Haverhill MA 01833",
    "addr:housenumber":"28",
    "addr:postcode":"01833",
    "addr:street":"Elm Street",
    "iso:country":"US",
    "sg:address":"28 Elm Street",
    "sg:city":"Haverhill",
    "sg:classifiers":[
        {
            "category":"Professional",
            "subcategory":"Computer Services",
            "type":"Services"
        }
    ],
    "sg:phone":"+1 978 910 0500",
    "sg:postcode":"01833",
    "sg:province":"MA",
    "sg:tags":[
        "repair"
    ],
    "sg:website":"www.computerrepairboxford.com",
    "wof:name":"Computer Repair Boxford",
    "wof:placetype":"venue"
},
  "geometry": {"coordinates":[-70.986316,42.717849],"type":"Point"}
}