{
  "type": "Feature",
  "properties": {
    "iso:country":"US",
    "sg:address":"8 Brookfield Ln",
    "sg:city":"Saugus",
    "sg:classifiers":[
        {
            "category":"Professional",
            "subcategory":"Management & Consulting",
            "type":"Services"
        }
    ],
    "sg:phone":"+1 781 233 0599",
    "sg:postcode":"01906",
    "sg:province":"MA",
    "sg:tags":[
        "fuel"
    ],
    "wof:name":"Creative Expo Management",
    "wof:placetype":"venue"
},
  "geometry": {"coordinates":[-71.01076399999999,42.453398],"type":"Point"}
}