{
  "type": "Feature",
  "properties": {
    "addr:full": "8 Brookfield Ln Saugus MA 01906",
    "addr:housenumber": "8",
    "addr:postcode": "01906",
    "addr:street": "Brookfield Ln",
    "iso:country": "US",
    "sg:address": "8 Brookfield Ln",
    "sg:city": "Saugus",
    "sg:classifiers": [
      {
        "category": "Professional",
        "subcategory": "Management \u0026 Consulting",
        "type": "Services"
      }
    ],
    "sg:phone": "+1 781 233 0599",
    "sg:postcode": "01906",
    "sg:province": "MA",
    "sg:tags": [
      "fuel"
    ],
    "wof:name": "Creative Expo Management",
    "wof:placetype": "venue"
  },
  "geometry": {"coordinates":[-71.010764,42.453398],"type":"Point"}
}
