{
  "type": "Feature",
  "properties": {
    "addr:full": "115 Porter St Apt 1 Boston MA 02128",
    "addr:housenumber": "115;1",
    "addr:postcode": "02128",
    "addr:street": "Porter St Apt",
    "iso:country": "US",
    "sg:address": "115 Porter St Apt 1",
    "sg:city": "Boston",
    "sg:classifiers": [
      {
        "category": "Health Services",
        "subcategory": "Clinic",
        "type": "Services"
      },
      {
        "category": "Health Services",
        "subcategory": "Health Practitioner",
        "type": "Services"
      }
    ],
    "sg:phone": "+1 617 569 2929",
    "sg:postcode": "02128",
    "sg:province": "MA",
    "sg:tags": [
      "therapist",
      "therapy",
      "physical"
    ],
    "wof:name": "Marathon City Physical Therapy",
    "wof:placetype": "venue"
  },
  "geometry": {"coordinates":[-71.035806,42.373017],"type":"Point"}
}
