{
  "type": "Feature",
  "properties": {
    "iso:country":"US",
    "sg:address":"115 Porter St Apt 1",
    "sg:city":"Boston",
    "sg:classifiers":[
        {
            "category":"Health Services",
            "subcategory":"Clinic",
            "type":"Services"
        },
        {
            "category":"Health Services",
            "subcategory":"Health Practitioner",
            "type":"Services"
        }
    ],
    "sg:phone":"+1 617 569 2929",
    "sg:postcode":"02128",
    "sg:province":"MA",
    "sg:tags":[
        "therapist",
        "therapy",
        "physical"
    ],
    "wof:name":"Marathon City Physical Therapy",
    "wof:placetype":"venue"
},
  "geometry": {"coordinates":[-71.03580599999999,42.373017],"type":"Point"}
}