{
  "type": "Feature",
  "properties": {
    "iso:country":"US",
    "sg:address":"98 N Washington St",
    "sg:city":"Boston",
    "sg:classifiers":[
        {
            "category":"Organizations",
            "subcategory":"Professional Association",
            "type":"Services"
        }
    ],
    "sg:phone":"+1 617 723 4009",
    "sg:postcode":"02114",
    "sg:province":"MA",
    "sg:website":"www.newenglandcouncil.com",
    "wof:name":"New England Council",
    "wof:placetype":"venue"
},
  "geometry": {"coordinates":[-71.058465,42.365315],"type":"Point"}
}