{
  "type": "Feature",
  "properties": {
    "addr:full": "22 High St Medford MA 02155",
    "addr:housenumber": "22",
    "addr:postcode": "02155",
    "addr:street": "High St",
    "iso:country": "US",
    "sg:address": "22 High St",
    "sg:city": "Medford",
    "sg:classifiers": [
      {
        "category": "Personal",
        "type": "Services"
      }
    ],
    "sg:phone": "+1 781 393 2969",
    "sg:postcode": "02155",
    "sg:province": "MA",
    "sg:tags": [
      "therapist",
      "massage"
    ],
    "wof:name": "Mystical Therapies For Women",
    "wof:placetype": "venue"
  },
  "geometry": {"coordinates":[-71.110031,42.41819],"type":"Point"}
}
