{
  "type": "Feature",
  "properties": {
    "iso:country":"US",
    "sg:address":"116 Washington St",
    "sg:city":"Dorchester",
    "sg:classifiers":[
        {
            "category":"Restaurant",
            "type":"Food & Drink"
        }
    ],
    "sg:phone":"+1 617 288 1752",
    "sg:postcode":"02121",
    "sg:province":"MA",
    "sg:tags":[
        "chicken"
    ],
    "wof:name":"Royal Chicken",
    "wof:placetype":"venue"
},
  "geometry": {"coordinates":[-71.080376,42.305268],"type":"Point"}
}