{
  "type": "Feature",
  "properties": {
    "addr:full": "116 Washington St Dorchester MA 02121",
    "addr:housenumber": "116",
    "addr:postcode": "02121",
    "addr:street": "Washington St",
    "iso:country": "US",
    "sg:address": "116 Washington St",
    "sg:city": "Dorchester",
    "sg:classifiers": [
      {
        "category": "Restaurant",
        "type": "Food \u0026 Drink"
      }
    ],
    "sg:phone": "+1 617 288 1752",
    "sg:postcode": "02121",
    "sg:province": "MA",
    "sg:tags": [
      "chicken"
    ],
    "wof:name": "Royal Chicken",
    "wof:placetype": "venue"
  },
  "geometry": {"coordinates":[-71.080376,42.305268],"type":"Point"}
}
