{
  "type": "Feature",
  "properties": {
    "iso:country":"US",
    "sg:address":"21 Center St",
    "sg:city":"Watertown",
    "sg:classifiers":[
        {
            "category":"Government",
            "subcategory":"Office",
            "type":"Public Place"
        }
    ],
    "sg:phone":"+1 617 923 2192",
    "sg:postcode":"02472",
    "sg:province":"MA",
    "wof:name":"Ascs Inc",
    "wof:placetype":"venue"
},
  "geometry": {"coordinates":[-71.174834,42.367554],"type":"Point"}
}