{
  "type": "Feature",
  "properties": {
    "iso:country":"US",
    "sg:address":"10 Converse Pl",
    "sg:city":"Winchester",
    "sg:classifiers":[
        {
            "category":"Professional",
            "subcategory":"Engineering",
            "type":"Services"
        }
    ],
    "sg:phone":"+1 781 729 2733",
    "sg:postcode":"01890",
    "sg:province":"MA",
    "sg:tags":[
        "engineer"
    ],
    "wof:name":"EBM Inc",
    "wof:placetype":"venue"
},
  "geometry": {"coordinates":[-71.136188,42.452688],"type":"Point"}
}