{
  "type": "Feature",
  "properties": {
    "addr:full": "12 Field Dr Plainville MA 02762",
    "addr:housenumber": "12",
    "addr:postcode": "02762",
    "addr:street": "Field Dr",
    "iso:country": "US",
    "sg:address": "12 Field Dr",
    "sg:city": "Plainville",
    "sg:classifiers": [
      {
        "category": "Professional",
        "subcategory": "Business Services",
        "type": "Services"
      }
    ],
    "sg:phone": "+1 508 695 3949",
    "sg:postcode": "02762",
    "sg:province": "MA",
    "sg:tags": [
      "drafting"
    ],
    "wof:name": "Intex Drafting Svc",
    "wof:placetype": "venue"
  },
  "geometry": {"coordinates":[-71.35107,42.0043],"type":"Point"}
}
