{
  "type": "Feature",
  "properties": {
    "iso:country":"US",
    "sg:address":"387 Atlantic Ave",
    "sg:city":"Marblehead",
    "sg:classifiers":[
        {
            "category":"Home & Garden",
            "subcategory":"Building Materials",
            "type":"Retail Goods"
        }
    ],
    "sg:phone":"+1 781 639 9136",
    "sg:postcode":"01945",
    "sg:province":"MA",
    "sg:tags":[
        "glass",
        "window",
        "plate"
    ],
    "wof:name":"Oceanview Glass",
    "wof:placetype":"venue"
},
  "geometry": {"coordinates":[-70.87567900000001,42.482837],"type":"Point"}
}