{
  "type": "Feature",
  "properties": {
    "addr:full": "387 Atlantic Ave Marblehead MA 01945",
    "addr:housenumber": "387",
    "addr:postcode": "01945",
    "addr:street": "Atlantic Ave",
    "iso:country": "US",
    "sg:address": "387 Atlantic Ave",
    "sg:city": "Marblehead",
    "sg:classifiers": [
      {
        "category": "Home \u0026 Garden",
        "subcategory": "Building Materials",
        "type": "Retail Goods"
      }
    ],
    "sg:phone": "+1 781 639 9136",
    "sg:postcode": "01945",
    "sg:province": "MA",
    "sg:tags": [
      "glass",
      "window",
      "plate"
    ],
    "wof:name": "Oceanview Glass",
    "wof:placetype": "venue"
  },
  "geometry": {"coordinates":[-70.875679,42.482837],"type":"Point"}
}
