{
  "type": "Feature",
  "properties": {
    "iso:country":"US",
    "sg:address":"1 Exeter Plz",
    "sg:city":"Boston",
    "sg:classifiers":[
        {
            "category":"Professional",
            "subcategory":"Lawyer & Legal Services",
            "type":"Services"
        }
    ],
    "sg:phone":"+1 617 880 7100",
    "sg:postcode":"02116",
    "sg:province":"MA",
    "sg:website":"www.bhpklaw.com",
    "wof:name":"Sedney Jocelyn M Atty",
    "wof:placetype":"venue"
},
  "geometry": {"coordinates":[-71.0813,42.3528],"type":"Point"}
}