{
  "type": "Feature",
  "properties": {
    "addr:full":"5 Shawsheen Ave Bedford MA 01730",
    "addr:housenumber":"5",
    "addr:postcode":"01730",
    "addr:street":"Shawsheen Ave",
    "iso:country":"US",
    "sg:address":"5 Shawsheen Ave",
    "sg:city":"Bedford",
    "sg:classifiers":[
        {
            "category":"Retail",
            "subcategory":"Animal Services",
            "type":"Services"
        }
    ],
    "sg:phone":"+1 781 276 1700",
    "sg:postcode":"01730",
    "sg:province":"MA",
    "sg:tags":[
        "pet",
        "boarding/pet",
        "sitting"
    ],
    "wof:name":"Ladies Little Miss",
    "wof:placetype":"venue"
},
  "geometry": {"coordinates":[-71.260696,42.485802],"type":"Point"}
}