{
  "type": "Feature",
  "properties": {
    "addr:full":"393 Massachusetts Ave Acton MA 01720",
    "addr:housenumber":"393",
    "addr:postcode":"01720",
    "addr:street":"Massachusetts Ave",
    "iso:country":"US",
    "sg:address":"393 Massachusetts Ave",
    "sg:city":"Acton",
    "sg:classifiers":[
        {
            "category":"Shopping",
            "subcategory":"Pharmacy",
            "type":"Retail Goods"
        }
    ],
    "sg:phone":"+1 978 263 3385",
    "sg:postcode":"01720",
    "sg:province":"MA",
    "sg:tags":[
        "drugstore"
    ],
    "sg:website":"cvs.com",
    "wof:name":"CVS Pharmacy",
    "wof:placetype":"venue"
},
  "geometry": {"coordinates":[-71.450614,42.474525],"type":"Point"}
}