{
  "type": "Feature",
  "properties": {
    "addr:full": "207 Forest Ave Swampscott MA 01907",
    "addr:housenumber": "207",
    "addr:postcode": "01907",
    "addr:street": "Forest Ave",
    "iso:country": "US",
    "sg:address": "207 Forest Ave",
    "sg:city": "Swampscott",
    "sg:classifiers": [
      {
        "category": "Education",
        "subcategory": "School",
        "type": "Public Place"
      }
    ],
    "sg:phone": "+1 781 596 8802",
    "sg:postcode": "01907",
    "sg:province": "MA",
    "wof:name": "Swampscott School Business Ofc",
    "wof:placetype": "venue"
  },
  "geometry": {"coordinates":[-70.903352,42.473566],"type":"Point"}
}
