{
  "type": "Feature",
  "properties": {
    "addr:full":"230 Chauncey Walker St Belchertown MA 01007",
    "addr:housenumber":"230",
    "addr:postcode":"01007",
    "addr:street":"Chauncey Walker St",
    "iso:country":"US",
    "sg:address":"230 Chauncey Walker St",
    "sg:city":"Belchertown",
    "sg:classifiers":[
        {
            "category":"Autos & Motor Vehicles",
            "subcategory":"Auto Supplies",
            "type":"Retail Goods"
        }
    ],
    "sg:phone":"+1 413 323 5987",
    "sg:postcode":"01007",
    "sg:province":"MA",
    "sg:tags":[
        "battery"
    ],
    "wof:name":"Interstate Battery System",
    "wof:placetype":"venue"
},
  "geometry": {"coordinates":[-72.411675,42.247838],"type":"Point"}
}