{
  "type": "Feature",
  "properties": {
    "addr:full":"62 Longfellow Rd Watertown MA 02472",
    "addr:housenumber":"62",
    "addr:postcode":"02472",
    "addr:street":"Longfellow Rd",
    "iso:country":"US",
    "sg:address":"62 Longfellow Rd",
    "sg:city":"Watertown",
    "sg:classifiers":[
        {
            "category":"Real Estate",
            "subcategory":"Real Estate Agent",
            "type":"Services"
        }
    ],
    "sg:phone":"+1 617 924 1414",
    "sg:postcode":"02472",
    "sg:province":"MA",
    "wof:name":"Antinarelli Realty",
    "wof:placetype":"venue"
},
  "geometry": {"coordinates":[-71.205859,42.37621],"type":"Point"}
}