{
  "type": "Feature",
  "properties": {
    "iso:country":"US",
    "sg:address":"152 Main St",
    "sg:city":"Indian Orchard",
    "sg:classifiers":[
        {
            "category":"Shopping",
            "subcategory":"Discount & Variety Stores",
            "type":"Retail Goods"
        }
    ],
    "sg:phone":"+1 413 543 1396",
    "sg:postcode":"01151",
    "sg:province":"MA",
    "wof:name":"Orchard Variety Store",
    "wof:placetype":"venue"
},
  "geometry": {"coordinates":[-72.501105,42.159467],"type":"Point"}
}