{
  "type": "Feature",
  "properties": {
    "iso:country":"US",
    "sg:address":"41 Montvale Avenue",
    "sg:city":"Stoneham",
    "sg:classifiers":[
        {
            "category":"Sports & Exercise",
            "subcategory":"Gym",
            "type":"Entertainment"
        }
    ],
    "sg:phone":"+1 781 279 4100",
    "sg:postcode":"02180",
    "sg:province":"MA",
    "sg:tags":[
        "trainer"
    ],
    "wof:name":"Hospice Care - CLOSED",
    "wof:placetype":"venue"
},
  "geometry": {"coordinates":[-71.10375000000001,42.482122],"type":"Point"}
}