{
  "type": "Feature",
  "properties": {
    "iso:country":"US",
    "sg:address":"1646 Falmouth Rd",
    "sg:city":"Centerville",
    "sg:classifiers":[
        {
            "category":"Food & Beverages",
            "subcategory":"Specialty",
            "type":"Retail Goods"
        }
    ],
    "sg:phone":"+1 508 790 3580",
    "sg:postcode":"02632",
    "sg:province":"MA",
    "sg:tags":[
        "vitamin"
    ],
    "sg:website":"www.naturesyouth.com",
    "wof:name":"Nature's Youth Inc",
    "wof:placetype":"venue"
},
  "geometry": {"coordinates":[-70.347244,41.657109],"type":"Point"}
}