{
  "type": "Feature",
  "properties": {
    "iso:country":"US",
    "sg:address":"211 Commercial St",
    "sg:city":"Provincetown",
    "sg:classifiers":[
        {
            "category":"Government",
            "subcategory":"Post Office",
            "type":"Public Place"
        }
    ],
    "sg:phone":"+1 508 000 1111",
    "sg:postcode":"02657",
    "sg:province":"MA",
    "wof:name":"US Post Office",
    "wof:placetype":"venue"
},
  "geometry": {"coordinates":[-70.188698,42.049222],"type":"Point"}
}