{
  "type": "Feature",
  "properties": {
    "addr:full": "123 North St Andover MA 01810",
    "addr:housenumber": "123",
    "addr:postcode": "01810",
    "addr:street": "North St",
    "iso:country": "US",
    "sg:address": "123 North St",
    "sg:city": "Andover",
    "sg:classifiers": [
      {
        "category": "Building \u0026 Trades",
        "subcategory": "Landscaping Services",
        "type": "Services"
      }
    ],
    "sg:phone": "+1   ",
    "sg:postcode": "01810",
    "sg:province": "MA",
    "wof:name": "L M Lawn Care Plus Garden",
    "wof:placetype": "venue"
  },
  "geometry": {"coordinates":[-71.194915,42.687021],"type":"Point"}
}
