{
  "type": "Feature",
  "properties": {
    "addr:full": "610 Washington St Pembroke MA 02359",
    "addr:housenumber": "610",
    "addr:postcode": "02359",
    "addr:street": "Washington St",
    "iso:country": "US",
    "sg:address": "610 Washington St",
    "sg:city": "Pembroke",
    "sg:classifiers": [
      {
        "category": "Health Services",
        "subcategory": "Optometrist",
        "type": "Services"
      }
    ],
    "sg:phone": "+1 781 826 2600",
    "sg:postcode": "02359",
    "sg:province": "MA",
    "wof:name": "Discount Eyeglasses \u0026 Hearing",
    "wof:placetype": "venue"
  },
  "geometry": {"coordinates":[-70.780667,42.073823],"type":"Point"}
}
