{
  "type": "Feature",
  "properties": {
    "iso:country":"US",
    "sg:address":"2 Deer View Ln",
    "sg:city":"Uxbridge",
    "sg:classifiers":[
        {
            "category":"Building & Trades",
            "subcategory":"Electrical",
            "type":"Services"
        }
    ],
    "sg:phone":"+1 508 278 0160",
    "sg:postcode":"01569",
    "sg:province":"MA",
    "sg:tags":[
        "electric",
        "contractor"
    ],
    "wof:name":"Bettencourt Electrical Contrs",
    "wof:placetype":"venue"
},
  "geometry": {"coordinates":[-71.673104,42.056115],"type":"Point"}
}