{
  "type": "Feature",
  "properties": {
    "addr:full":"701 Winthrop St Taunton MA 02780",
    "addr:housenumber":"701",
    "addr:postcode":"02780",
    "addr:street":"Winthrop St",
    "iso:country":"US",
    "sg:address":"701 Winthrop St",
    "sg:city":"Taunton",
    "sg:classifiers":[
        {
            "category":"Freight",
            "type":"Transportation"
        },
        {
            "category":"Social Services",
            "subcategory":"Child Care",
            "type":"Services"
        }
    ],
    "sg:phone":"+1 508 822 8970",
    "sg:postcode":"02780",
    "sg:province":"MA",
    "sg:tags":[
        "day",
        "trucking"
    ],
    "wof:name":"Day & Ross Transportation",
    "wof:placetype":"venue"
},
  "geometry": {"coordinates":[-71.169561,41.878157],"type":"Point"}
}