{
  "type": "Feature",
  "properties": {
    "addr:full": "16 Harley St Dorchester Ctr MA 02124",
    "addr:housenumber": "16",
    "addr:postcode": "02124",
    "addr:street": "Harley St",
    "iso:country": "US",
    "sg:address": "16 Harley St",
    "sg:city": "Dorchester Ctr",
    "sg:classifiers": [
      {
        "category": "Professional",
        "type": "Services"
      }
    ],
    "sg:phone": "+1 617 265 7767",
    "sg:postcode": "02124",
    "sg:province": "MA",
    "sg:tags": [
      "establishment"
    ],
    "wof:name": "Libassi \u0026 Assoc",
    "wof:placetype": "venue"
  },
  "geometry": {"coordinates":[-71.069521,42.288396],"type":"Point"}
}
