{
  "type": "Feature",
  "properties": {
    "addr:full":"12 Brooker Hill Rd Becket MA 01223",
    "addr:housenumber":"12",
    "addr:postcode":"01223",
    "addr:street":"Brooker Hill Rd",
    "iso:country":"US",
    "sg:address":"12 Brooker Hill Rd",
    "sg:city":"Becket",
    "sg:classifiers":[
        {
            "category":"Banks & Credit Unions",
            "subcategory":"Bank",
            "type":"Services"
        }
    ],
    "sg:phone":"+1 413 623 2100",
    "sg:postcode":"01223",
    "sg:province":"MA",
    "sg:tags":[
        "trust"
    ],
    "wof:name":"Becket Land Trust & Historic Q",
    "wof:placetype":"venue"
},
  "geometry": {"coordinates":[-73.084326,42.331153],"type":"Point"}
}