{
  "type": "Feature",
  "properties": {
    "addr:city": "Becket",
    "addr:full": "12 Brooker Hill Rd Becket, Ma 01223",
    "addr:house_number": "12",
    "addr:housenumber": "12",
    "addr:phone": "+1 413-623-2100",
    "addr:postcode": "01223",
    "addr:road": "Brooker Hill Rd",
    "addr:state": "MA",
    "addr:street": "Brooker Hill Rd",
    "iso:country": "US",
    "sg:address": "12 Brooker Hill Rd",
    "sg:city": "Becket",
    "sg:classifiers": [
      {
        "category": "Banks \u0026 Credit Unions",
        "subcategory": "Bank",
        "type": "Services"
      }
    ],
    "sg:phone": "+1 413 623 2100",
    "sg:postcode": "01223",
    "sg:province": "MA",
    "sg:tags": [
      "trust"
    ],
    "wof:name": "Beckett Land Trust And Historic",
    "wof:placetype": "venue"
  },
  "geometry": {"coordinates":[-73.09124,42.33047],"type":"Point"}
}
