{
  "type": "Feature",
  "properties": {
    "addr:full": "113 Kelly St Auburn MA 01501",
    "addr:housenumber": "113",
    "addr:postcode": "01501",
    "addr:street": "Kelly St",
    "iso:country": "US",
    "sg:address": "113 Kelly St",
    "sg:city": "Auburn",
    "sg:classifiers": [
      {
        "category": "Farming",
        "subcategory": "Farm",
        "type": "Manufacturing \u0026 Wholesale Goods"
      }
    ],
    "sg:phone": "+1 508 832 2868",
    "sg:postcode": "01501",
    "sg:province": "MA",
    "wof:name": "Martin Brothers Farms",
    "wof:placetype": "venue"
  },
  "geometry": {"coordinates":[-71.860149,42.16786],"type":"Point"}
}
