{
  "type": "Feature",
  "properties": {
    "iso:country":"US",
    "sg:address":"113 Kelly St",
    "sg:city":"Auburn",
    "sg:classifiers":[
        {
            "category":"Farming",
            "subcategory":"Farm",
            "type":"Manufacturing & Wholesale Goods"
        }
    ],
    "sg:phone":"+1 508 832 2868",
    "sg:postcode":"01501",
    "sg:province":"MA",
    "wof:name":"Martin Brothers Farms",
    "wof:placetype":"venue"
},
  "geometry": {"coordinates":[-71.86014900000001,42.16786],"type":"Point"}
}