{
  "type": "Feature",
  "properties": {
    "iso:country":"US",
    "sg:address":"10 Cook St",
    "sg:city":"Billerica",
    "sg:classifiers":[
        {
            "category":"Professional",
            "subcategory":"Printing & Photocopies",
            "type":"Services"
        }
    ],
    "sg:phone":"+1 978 667 8655",
    "sg:postcode":"01821",
    "sg:province":"MA",
    "sg:website":"www.tecaprintusa.com",
    "wof:name":"Teca-Print USA Corporation",
    "wof:placetype":"venue"
},
  "geometry": {"coordinates":[-71.23083200000001,42.533923],"type":"Point"}
}