{
  "type": "Feature",
  "properties": {
    "addr:full": "248 Holland St Somerville MA 02144",
    "addr:housenumber": "248",
    "addr:postcode": "02144",
    "addr:street": "Holland St",
    "iso:country": "US",
    "sg:address": "248 Holland St",
    "sg:city": "Somerville",
    "sg:classifiers": [
      {
        "category": "Restaurant",
        "type": "Food \u0026 Drink"
      }
    ],
    "sg:phone": "+1 617 623 6144",
    "sg:postcode": "02144",
    "sg:province": "MA",
    "wof:name": "J \u0026 L Restaurant Inc",
    "wof:placetype": "venue"
  },
  "geometry": {"coordinates":[-71.127058,42.402831],"type":"Point"}
}
