{
  "type": "Feature",
  "properties": {
    "iso:country":"US",
    "sg:address":"248 Holland St",
    "sg:city":"Somerville",
    "sg:classifiers":[
        {
            "category":"Restaurant",
            "type":"Food & Drink"
        }
    ],
    "sg:phone":"+1 617 623 6144",
    "sg:postcode":"02144",
    "sg:province":"MA",
    "wof:name":"J & L Restaurant Inc",
    "wof:placetype":"venue"
},
  "geometry": {"coordinates":[-71.12705800000001,42.402831],"type":"Point"}
}