{
  "type": "Feature",
  "properties": {
    "addr:full": "89 Devonshire St Boston MA 02109",
    "addr:housenumber": "89",
    "addr:postcode": "02109",
    "addr:street": "Devonshire St",
    "iso:country": "US",
    "sg:address": "89 Devonshire St",
    "sg:city": "Boston",
    "sg:classifiers": [
      {
        "category": "Professional",
        "subcategory": "Employment Agencies",
        "type": "Services"
      }
    ],
    "sg:phone": "+1 617 250 1000",
    "sg:postcode": "02109",
    "sg:province": "MA",
    "sg:website": "www.psgstaffing.com",
    "wof:name": "Professional Staffing Group",
    "wof:placetype": "venue"
  },
  "geometry": {"coordinates":[-71.057503,42.357601],"type":"Point"}
}
