{
  "type": "Feature",
  "properties": {
    "addr:full":"90 Pleasant Valley St Methuen MA 01844",
    "addr:housenumber":"90",
    "addr:postcode":"01844",
    "addr:street":"Pleasant Valley St",
    "iso:country":"US",
    "sg:address":"90 Pleasant Valley St",
    "sg:city":"Methuen",
    "sg:classifiers":[
        {
            "category":"Utilities",
            "subcategory":"Mobile Phone",
            "type":"Services"
        }
    ],
    "sg:phone":"+1 978 989 0600",
    "sg:postcode":"01844",
    "sg:province":"MA",
    "sg:tags":[
        "telephone",
        "cellular"
    ],
    "wof:name":"Cingular Wireless",
    "wof:placetype":"venue"
},
  "geometry": {"coordinates":[-71.180126,42.732532],"type":"Point"}
}