{
  "type": "Feature",
  "properties": {
    "addr:full":"282 Talbot Ave Dorchester Center MA 02124",
    "addr:housenumber":"282",
    "addr:postcode":"02124",
    "addr:street":"Talbot Ave",
    "iso:country":"US",
    "sg:address":"282 Talbot Ave",
    "sg:city":"Dorchester Center",
    "sg:classifiers":[
        {
            "category":"Building & Trades",
            "subcategory":"Locksmith",
            "type":"Services"
        }
    ],
    "sg:phone":"+1 617 514 9507",
    "sg:postcode":"02124",
    "sg:province":"MA",
    "sg:tags":[
        "key"
    ],
    "wof:name":"Rc Locksmith",
    "wof:placetype":"venue"
},
  "geometry": {"coordinates":[-71.075008,42.291242],"type":"Point"}
}