{
  "type": "Feature",
  "properties": {
    "addr:full":"16 Adsit Crosby Rd Great Barrington MA 01230",
    "addr:housenumber":"16",
    "addr:postcode":"01230",
    "addr:street":"Adsit Crosby Rd",
    "iso:country":"US",
    "sg:address":"16 Adsit Crosby Rd",
    "sg:city":"Great Barrington",
    "sg:classifiers":[
        {
            "category":"Travel",
            "subcategory":"Hotels & Motels",
            "type":"Entertainment"
        }
    ],
    "sg:phone":"+1 413 229 2349",
    "sg:postcode":"01230",
    "sg:province":"MA",
    "sg:tags":[
        "breakfast",
        "accommodation",
        "bed"
    ],
    "wof:name":"Red Bird Inn",
    "wof:placetype":"venue"
},
  "geometry": {"coordinates":[-73.25922799999999,42.152201],"type":"Point"}
}