{
  "type": "Feature",
  "properties": {
    "addr:full": "177 Grafton St Worcester MA 01604",
    "addr:housenumber": "177",
    "addr:postcode": "01604",
    "addr:street": "Grafton St",
    "iso:country": "US",
    "sg:address": "177 Grafton St",
    "sg:city": "Worcester",
    "sg:classifiers": [
      {
        "category": "Personal",
        "subcategory": "Beauty Salon",
        "type": "Services"
      }
    ],
    "sg:phone": "+1 508 795 1024",
    "sg:postcode": "01604",
    "sg:province": "MA",
    "wof:name": "Nail 2000",
    "wof:placetype": "venue"
  },
  "geometry": {"coordinates":[-71.791354,42.257486],"type":"Point"}
}
