{
  "type": "Feature",
  "properties": {
    "iso:country":"US",
    "sg:address":"228 Main St",
    "sg:city":"Greenfield",
    "sg:classifiers":[
        {
            "category":"Shopping",
            "subcategory":"Hobbies, Toys, & Games",
            "type":"Retail Goods"
        }
    ],
    "sg:phone":"+1 413 774 5225",
    "sg:postcode":"01301",
    "sg:province":"MA",
    "sg:tags":[
        "supply"
    ],
    "wof:name":"Griffon Games Inc",
    "wof:placetype":"venue"
},
  "geometry": {"coordinates":[-72.60232000000001,42.587992],"type":"Point"}
}