{
  "type": "Feature",
  "properties": {
    "addr:full": "3300 Main St Springfield MA 01107",
    "addr:housenumber": "3300",
    "addr:postcode": "01107",
    "addr:street": "Main St",
    "iso:country": "US",
    "sg:address": "3300 Main St",
    "sg:city": "Springfield",
    "sg:classifiers": [
      {
        "category": "Professional",
        "type": "Services"
      }
    ],
    "sg:phone": "+1 413 794 5641",
    "sg:postcode": "01107",
    "sg:province": "MA",
    "wof:name": "Infertility Services Wesson",
    "wof:placetype": "venue"
  },
  "geometry": {"coordinates":[-72.609677,42.122946],"type":"Point"}
}
