{
  "type": "Feature",
  "properties": {
    "addr:full": "11 Stockbridge Rd Great Barrington MA 01230",
    "addr:housenumber": "11",
    "addr:postcode": "01230",
    "addr:street": "Stockbridge Rd",
    "iso:country": "US",
    "ovtr:label": "Elise Abrams Antiques, 11 Stockbridge Rd Great Barrington MA US",
    "ovtr:similarity": 2.108464002609253,
    "sg:address": "11 Stockbridge Rd",
    "sg:city": "Great Barrington",
    "sg:classifiers": [
      {
        "category": "Shopping",
        "subcategory": "Used Merchandise",
        "type": "Retail Goods"
      }
    ],
    "sg:phone": "+1 413 528 3201",
    "sg:postcode": "01230",
    "sg:province": "MA",
    "sg:tags": [
      "antique"
    ],
    "wof:name": "Elise Abrams Antiques",
    "wof:placetype": "venue"
  },
  "geometry": {"coordinates":[-73.347209,42.202621],"type":"Point"}
}
