{
  "type": "Feature",
  "properties": {
    "addr:full": "1098 Chicopee St Chicopee MA 01013",
    "addr:housenumber": "1098",
    "addr:postcode": "01013",
    "addr:street": "Chicopee St",
    "iso:country": "US",
    "sg:address": "1098 Chicopee St",
    "sg:city": "Chicopee",
    "sg:classifiers": [
      {
        "category": "Shopping",
        "subcategory": "Used Merchandise",
        "type": "Retail Goods"
      }
    ],
    "sg:phone": "+1 413 534 3280",
    "sg:postcode": "01013",
    "sg:province": "MA",
    "sg:tags": [
      "pawnbroker"
    ],
    "wof:name": "Money Stop Collateral Loans",
    "wof:placetype": "venue"
  },
  "geometry": {"coordinates":[-72.599925,42.193112],"type":"Point"}
}
