{
  "type": "Feature",
  "properties": {
    "addr:full":"222 Newbury St Peabody MA 01960",
    "addr:housenumber":"222",
    "addr:postcode":"01960",
    "addr:street":"Newbury St",
    "iso:country":"US",
    "sg:address":"222 Newbury St",
    "sg:city":"Peabody",
    "sg:classifiers":[
        {
            "category":"Retail",
            "subcategory":"Auto Repair",
            "type":"Services"
        }
    ],
    "sg:phone":"+1 978 535 9847",
    "sg:postcode":"01960",
    "sg:province":"MA",
    "sg:tags":[
        "wrecker"
    ],
    "wof:name":"Four Star Svc",
    "wof:placetype":"venue"
},
  "geometry": {"coordinates":[-70.984194,42.546663],"type":"Point"}
}