{
  "type": "Feature",
  "properties": {
    "addr:full":"23 Boston Rd North Billerica MA 01862",
    "addr:housenumber":"23",
    "addr:postcode":"01862",
    "addr:street":"Boston Rd",
    "iso:country":"US",
    "sg:address":"23 Boston Rd",
    "sg:city":"North Billerica",
    "sg:classifiers":[
        {
            "category":"Retail",
            "subcategory":"Car Wash",
            "type":"Services"
        }
    ],
    "sg:phone":"+1 978 459 0281",
    "sg:postcode":"01862",
    "sg:province":"MA",
    "sg:tags":[
        "automobile",
        "detail",
        "clean"
    ],
    "wof:name":"Valencia Detailing",
    "wof:placetype":"venue"
},
  "geometry": {"coordinates":[-71.299003,42.598937],"type":"Point"}
}