{
  "type": "Feature",
  "properties": {
    "iso:country":"US",
    "sg:address":"394 Revere Beach Pkwy",
    "sg:city":"Revere",
    "sg:classifiers":[
        {
            "category":"Professional",
            "type":"Services"
        }
    ],
    "sg:phone":"+1 781 284 7333",
    "sg:postcode":"02151",
    "sg:province":"MA",
    "sg:tags":[
        "establishment"
    ],
    "wof:name":"Alphamoters",
    "wof:placetype":"venue"
},
  "geometry": {"coordinates":[-70.999369,42.402176],"type":"Point"}
}