{
  "type": "Feature",
  "properties": {
    "iso:country":"US",
    "sg:address":"165 Water St",
    "sg:city":"Pembroke",
    "sg:classifiers":[
        {
            "category":"Building & Trades",
            "subcategory":"Electrical",
            "type":"Services"
        }
    ],
    "sg:phone":"+1 781 826 4111",
    "sg:postcode":"02359",
    "sg:province":"MA",
    "sg:tags":[
        "electric",
        "contractor"
    ],
    "wof:name":"Seacoast Electrical Constr",
    "wof:placetype":"venue"
},
  "geometry": {"coordinates":[-70.784077,42.103692],"type":"Point"}
}