{
  "type": "Feature",
  "properties": {
    "addr:full":"42 Whistler Ln Yarmouth Port MA 02675",
    "addr:housenumber":"42",
    "addr:postcode":"02675",
    "addr:street":"Whistler Ln",
    "iso:country":"US",
    "sg:address":"42 Whistler Ln",
    "sg:city":"Yarmouth Port",
    "sg:classifiers":[
        {
            "category":"Shopping",
            "subcategory":"Stationery & Office Supplies",
            "type":"Retail Goods"
        }
    ],
    "sg:phone":"+1 508 362 7619",
    "sg:postcode":"02675",
    "sg:province":"MA",
    "sg:tags":[
        "educational",
        "material"
    ],
    "wof:name":"Word Web Vocabulary",
    "wof:placetype":"venue"
},
  "geometry": {"coordinates":[-70.218193,41.709108],"type":"Point"}
}