{
  "type": "Feature",
  "properties": {
    "addr:full": "340 Harvard St Cambridge MA 02139",
    "addr:housenumber": "340",
    "addr:postcode": "02139",
    "addr:street": "Harvard St",
    "iso:country": "US",
    "sg:address": "340 Harvard St",
    "sg:city": "Cambridge",
    "sg:classifiers": [
      {
        "category": "Professional",
        "type": "Services"
      }
    ],
    "sg:phone": "+1 617 873 0880",
    "sg:postcode": "02139",
    "sg:province": "MA",
    "sg:tags": [
      "establishment"
    ],
    "wof:name": "Steve Patterson Sports",
    "wof:placetype": "venue"
  },
  "geometry": {"coordinates":[-71.107428,42.370089],"type":"Point"}
}
