{
  "type": "Feature",
  "properties": {
    "addr:full":"46 Castle St Great Barrington MA 01230",
    "addr:housenumber":"46",
    "addr:postcode":"01230",
    "addr:street":"Castle St",
    "iso:country":"US",
    "sg:address":"46 Castle St",
    "sg:city":"Great Barrington",
    "sg:classifiers":[
        {
            "category":"Wholesale",
            "subcategory":"Apparel",
            "type":"Manufacturing & Wholesale Goods"
        }
    ],
    "sg:phone":"+1 413 528 3300",
    "sg:postcode":"01230",
    "sg:province":"MA",
    "sg:tags":[
        "textile"
    ],
    "wof:name":"SKH",
    "wof:placetype":"venue"
},
  "geometry": {"coordinates":[-73.365515,42.193321],"type":"Point"}
}