{
  "type": "Feature",
  "properties": {
    "iso:country":"US",
    "sg:address":"737 Lakeview Ave",
    "sg:city":"Lowell",
    "sg:classifiers":[
        {
            "category":"Restaurant",
            "type":"Food & Drink"
        }
    ],
    "sg:phone":"+1 978 459 7961",
    "sg:postcode":"01850",
    "sg:province":"MA",
    "wof:name":"731 Corp",
    "wof:placetype":"venue"
},
  "geometry": {"coordinates":[-71.31266599999999,42.656331],"type":"Point"}
}