{
  "type": "Feature",
  "properties": {
    "addr:full":"2 Punchard Ave Andover MA 01810",
    "addr:housenumber":"2",
    "addr:postcode":"01810",
    "addr:street":"Punchard Ave",
    "iso:country":"US",
    "sg:address":"2 Punchard Ave",
    "sg:city":"Andover",
    "sg:classifiers":[
        {
            "category":"Professional",
            "subcategory":"Lawyer & Legal Services",
            "type":"Services"
        }
    ],
    "sg:phone":"+1 978 475 9445",
    "sg:postcode":"01810",
    "sg:province":"MA",
    "sg:tags":[
        "attorney"
    ],
    "wof:name":"Greeley & Shea",
    "wof:placetype":"venue"
},
  "geometry": {"coordinates":[-71.13712700000001,42.654427],"type":"Point"}
}