{
  "type": "Feature",
  "properties": {
    "addr:full":"3 Ives St Worcester MA 01603",
    "addr:housenumber":"3",
    "addr:postcode":"01603",
    "addr:street":"Ives St",
    "iso:country":"US",
    "sg:address":"3 Ives St",
    "sg:city":"Worcester",
    "sg:classifiers":[
        {
            "category":"Home & Garden",
            "subcategory":"Furniture",
            "type":"Retail Goods"
        }
    ],
    "sg:phone":"+1 508 752 3686",
    "sg:postcode":"01603",
    "sg:province":"MA",
    "sg:tags":[
        "equipment",
        "kitchen",
        "cabinet"
    ],
    "wof:name":"Final Touch",
    "wof:placetype":"venue"
},
  "geometry": {"coordinates":[-71.82601,42.243776],"type":"Point"}
}