{
  "type": "Feature",
  "properties": {
    "iso:country":"US",
    "sg:address":"418 Adams St",
    "sg:city":"Dorchester",
    "sg:classifiers":[
        {
            "category":"Personal",
            "type":"Services"
        }
    ],
    "sg:phone":"+1 617 288 7555",
    "sg:postcode":"02122",
    "sg:province":"MA",
    "sg:tags":[
        "sewing",
        "alteration"
    ],
    "wof:name":"Sen Sewing",
    "wof:placetype":"venue"
},
  "geometry": {"coordinates":[-71.05650300000001,42.294899],"type":"Point"}
}