{
  "type": "Feature",
  "properties": {
    "addr:full":"23 Railroad Ave Swampscott MA 01907",
    "addr:housenumber":"23",
    "addr:postcode":"01907",
    "addr:street":"Railroad Ave",
    "iso:country":"US",
    "sg:address":"23 Railroad Ave",
    "sg:city":"Swampscott",
    "sg:classifiers":[
        {
            "category":"Real Estate",
            "subcategory":"Real Estate Agent",
            "type":"Services"
        }
    ],
    "sg:phone":"+1 781 592 8009",
    "sg:postcode":"01907",
    "sg:province":"MA",
    "sg:tags":[
        "management"
    ],
    "wof:name":"Reliable Property Mgmt & Mntnc",
    "wof:placetype":"venue"
},
  "geometry": {"coordinates":[-70.922822,42.473104],"type":"Point"}
}