{
  "type": "Feature",
  "properties": {
    "addr:full":"1 Loomis Way Ste 13 Easthampton MA 01027",
    "addr:housenumber":"1",
    "addr:postcode":"01027",
    "addr:street":"Loomis Way Ste 13",
    "iso:country":"US",
    "sg:address":"1 Loomis Way Ste 13",
    "sg:city":"Easthampton",
    "sg:classifiers":[
        {
            "category":"Professional",
            "subcategory":"Art Services",
            "type":"Services"
        }
    ],
    "sg:phone":"+1 413 519 9390",
    "sg:postcode":"01027",
    "sg:province":"MA",
    "sg:tags":[
        "designer",
        "display",
        "producer"
    ],
    "wof:name":"Keith Brich Design",
    "wof:placetype":"venue"
},
  "geometry": {"coordinates":[-72.64904,42.27689],"type":"Point"}
}