{
  "type": "Feature",
  "properties": {
    "iso:country":"US",
    "sg:address":"270 Franklin St",
    "sg:city":"Quincy",
    "sg:classifiers":[
        {
            "category":"Organizations",
            "subcategory":"Religious Organization",
            "type":"Services"
        }
    ],
    "sg:phone":"+1 617 773 5575",
    "sg:postcode":"02169",
    "sg:province":"MA",
    "sg:tags":[
        "church"
    ],
    "sg:website":"www.firstpresbyquincy.org",
    "wof:name":"First Presbyterian Church",
    "wof:placetype":"venue"
},
  "geometry": {"coordinates":[-70.999656,42.234791],"type":"Point"}
}