{
  "type": "Feature",
  "properties": {
    "addr:full": "270 Franklin St Quincy MA 02169",
    "addr:housenumber": "270",
    "addr:postcode": "02169",
    "addr:street": "Franklin St",
    "iso:country": "US",
    "sg:address": "270 Franklin St",
    "sg:city": "Quincy",
    "sg:classifiers": [
      {
        "category": "Organizations",
        "subcategory": "Religious Organization",
        "type": "Services"
      }
    ],
    "sg:phone": "+1 617 773 5575",
    "sg:postcode": "02169",
    "sg:province": "MA",
    "sg:tags": [
      "church"
    ],
    "sg:website": "www.firstpresbyquincy.org",
    "wof:name": "First Presbyterian Church",
    "wof:placetype": "venue"
  },
  "geometry": {"coordinates":[-70.999656,42.234791],"type":"Point"}
}
