{
  "type": "Feature",
  "properties": {
    "addr:full":"751 Beacon St Newton Center MA 02459",
    "addr:housenumber":"751",
    "addr:postcode":"02459",
    "addr:street":"Beacon St",
    "iso:country":"US",
    "sg:address":"751 Beacon St",
    "sg:city":"Newton Center",
    "sg:classifiers":[
        {
            "category":"Shopping",
            "subcategory":"Books",
            "type":"Retail Goods"
        }
    ],
    "sg:phone":"+1 617 795 7257",
    "sg:postcode":"02459",
    "sg:province":"MA",
    "sg:tags":[
        "dealer"
    ],
    "wof:name":"Kabbalah Book Store",
    "wof:placetype":"venue"
},
  "geometry": {"coordinates":[-71.191664,42.330608],"type":"Point"}
}