{
  "type": "Feature",
  "properties": {
    "addr:full": "73 Columbia Road Dorchester MA 02121",
    "addr:housenumber": "73",
    "addr:postcode": "02121",
    "addr:street": "Columbia Road",
    "iso:country": "US",
    "sg:address": "73 Columbia Road",
    "sg:city": "Dorchester",
    "sg:classifiers": [
      {
        "category": "Social Services",
        "subcategory": "Child Care",
        "type": "Services"
      },
      {
        "category": "Sports \u0026 Exercise",
        "subcategory": "Gym",
        "type": "Entertainment"
      }
    ],
    "sg:phone": "+1 617 822 0820",
    "sg:postcode": "02121",
    "sg:province": "MA",
    "sg:tags": [
      "trainer",
      "day"
    ],
    "wof:name": "Learn \u0026 Play Child Care Center",
    "wof:placetype": "venue"
  },
  "geometry": {"coordinates":[-71.082015,42.304508],"type":"Point"}
}
