{
  "type": "Feature",
  "properties": {
    "iso:country":"US",
    "sg:address":"73 Columbia Road",
    "sg:city":"Dorchester",
    "sg:classifiers":[
        {
            "category":"Social Services",
            "subcategory":"Child Care",
            "type":"Services"
        },
        {
            "category":"Sports & Exercise",
            "subcategory":"Gym",
            "type":"Entertainment"
        }
    ],
    "sg:phone":"+1 617 822 0820",
    "sg:postcode":"02121",
    "sg:province":"MA",
    "sg:tags":[
        "trainer",
        "day"
    ],
    "wof:name":"Learn & Play Child Care Center",
    "wof:placetype":"venue"
},
  "geometry": {"coordinates":[-71.082015,42.304508],"type":"Point"}
}