{
  "type": "Feature",
  "properties": {
    "iso:country":"US",
    "sg:address":"541 Dorchester Ave",
    "sg:city":"Boston",
    "sg:classifiers":[
        {
            "category":"Retail",
            "subcategory":"Auto Repair",
            "type":"Services"
        }
    ],
    "sg:phone":"+1 617 307 6072",
    "sg:postcode":"02127",
    "sg:province":"MA",
    "wof:name":"D&D Auto Services",
    "wof:placetype":"venue"
},
  "geometry": {"coordinates":[-71.05695799999999,42.330947],"type":"Point"}
}