{
  "type": "Feature",
  "properties": {
    "addr:full": "128 Main St Westminster MA 01473",
    "addr:housenumber": "128",
    "addr:postcode": "01473",
    "addr:street": "Main St",
    "iso:country": "US",
    "sg:address": "128 Main St",
    "sg:city": "Westminster",
    "sg:classifiers": [
      {
        "category": "Food \u0026 Beverages",
        "subcategory": "Specialty",
        "type": "Retail Goods"
      }
    ],
    "sg:phone": "+1 978 874 2833",
    "sg:postcode": "01473",
    "sg:province": "MA",
    "sg:tags": [
      "product",
      "health",
      "diet"
    ],
    "sg:website": "www.naturaldrugstore.com",
    "wof:name": "Westminster Natural Health",
    "wof:placetype": "venue"
  },
  "geometry": {"coordinates":[-71.911957,42.545448],"type":"Point"}
}
