{
  "type": "Feature",
  "properties": {
    "iso:country":"US",
    "sg:address":"8 Westmoreland Rd",
    "sg:city":"Hingham",
    "sg:classifiers":[
        {
            "category":"Professional",
            "subcategory":"Employment Agencies",
            "type":"Services"
        }
    ],
    "sg:phone":"+1 781 741 9944",
    "sg:postcode":"02043",
    "sg:province":"MA",
    "sg:tags":[
        "consultant",
        "search",
        "executive"
    ],
    "wof:name":"O'Neill Search",
    "wof:placetype":"venue"
},
  "geometry": {"coordinates":[-70.883644,42.193705],"type":"Point"}
}