{
  "type": "Feature",
  "properties": {
    "addr:full": "46 Pawtucket Blvd Tyngsboro MA 01879",
    "addr:housenumber": "46",
    "addr:postcode": "01879",
    "addr:street": "Pawtucket Blvd",
    "iso:country": "US",
    "sg:address": "46 Pawtucket Blvd",
    "sg:city": "Tyngsboro",
    "sg:classifiers": [
      {
        "category": "Retail",
        "subcategory": "Repair Shop",
        "type": "Services"
      }
    ],
    "sg:phone": "+1 978 649 4994",
    "sg:postcode": "01879",
    "sg:province": "MA",
    "sg:tags": [
      "lock",
      "locksmith"
    ],
    "wof:name": "Shadow Locksmith Co",
    "wof:placetype": "venue"
  },
  "geometry": {"coordinates":[-71.415061,42.671096],"type":"Point"}
}
