{
  "type": "Feature",
  "properties": {
    "iso:country":"US",
    "sg:address":"46 Pawtucket Blvd",
    "sg:city":"Tyngsboro",
    "sg:classifiers":[
        {
            "category":"Retail",
            "subcategory":"Repair Shop",
            "type":"Services"
        }
    ],
    "sg:phone":"+1 978 649 4994",
    "sg:postcode":"01879",
    "sg:province":"MA",
    "sg:tags":[
        "lock",
        "locksmith"
    ],
    "wof:name":"Shadow Locksmith Co",
    "wof:placetype":"venue"
},
  "geometry": {"coordinates":[-71.41506099999999,42.671096],"type":"Point"}
}