{
  "type": "Feature",
  "properties": {
    "iso:country":"US",
    "sg:address":"637 Colrain Rd",
    "sg:city":"Greenfield",
    "sg:classifiers":[
        {
            "category":"Personal",
            "subcategory":"Beauty Salon",
            "type":"Services"
        }
    ],
    "sg:phone":"+1 413 774 6404",
    "sg:postcode":"01301",
    "sg:province":"MA",
    "sg:tags":[
        "shop"
    ],
    "wof:name":"Hair Shed",
    "wof:placetype":"venue"
},
  "geometry": {"coordinates":[-72.632976,42.614786],"type":"Point"}
}