{
  "type": "Feature",
  "properties": {
    "addr:full":"164 Main St Becket MA 01223",
    "addr:housenumber":"164",
    "addr:postcode":"01223",
    "addr:street":"Main St",
    "iso:country":"US",
    "sg:address":"164 Main St",
    "sg:city":"Becket",
    "sg:classifiers":[
        {
            "category":"Wholesale",
            "subcategory":"Computers",
            "type":"Manufacturing & Wholesale Goods"
        }
    ],
    "sg:phone":"+1 413 623 0172",
    "sg:postcode":"01223",
    "sg:province":"MA",
    "sg:tags":[
        "equipment"
    ],
    "sg:website":"http://www.net-engineering.com",
    "wof:name":"Network Engineering",
    "wof:placetype":"venue"
},
  "geometry": {"coordinates":[-73.051624,42.267094],"type":"Point"}
}