{
  "type": "Feature",
  "properties": {
    "addr:full":"220 Waverley Ave Watertown MA 02472",
    "addr:housenumber":"220",
    "addr:postcode":"02472",
    "addr:street":"Waverley Ave",
    "iso:country":"US",
    "sg:address":"220 Waverley Ave",
    "sg:city":"Watertown",
    "sg:classifiers":[
        {
            "category":"Education",
            "subcategory":"Dance Studio",
            "type":"Public Place"
        }
    ],
    "sg:phone":"+1 617 924 0763",
    "sg:postcode":"02472",
    "sg:province":"MA",
    "sg:tags":[
        "instruction",
        "dancing"
    ],
    "wof:name":"Dance Evolution",
    "wof:placetype":"venue"
},
  "geometry": {"coordinates":[-71.18823399999999,42.376985],"type":"Point"}
}