{
  "type": "Feature",
  "properties": {
    "addr:full":"14 Greenwood Rd Wilbraham MA 01095",
    "addr:housenumber":"14",
    "addr:postcode":"01095",
    "addr:street":"Greenwood Rd",
    "iso:country":"US",
    "sg:address":"14 Greenwood Rd",
    "sg:city":"Wilbraham",
    "sg:classifiers":[
        {
            "category":"Home & Garden",
            "subcategory":"Home Furnishings",
            "type":"Retail Goods"
        }
    ],
    "sg:phone":"+1   ",
    "sg:postcode":"01095",
    "sg:province":"MA",
    "sg:tags":[
        "business"
    ],
    "wof:name":"Green Interiors",
    "wof:placetype":"venue"
},
  "geometry": {"coordinates":[-72.426551,42.129607],"type":"Point"}
}