{
  "type": "Feature",
  "properties": {
    "iso:country":"US",
    "sg:address":"12 W Water St",
    "sg:city":"Rockland",
    "sg:classifiers":[
        {
            "category":"Recreation",
            "type":"Entertainment"
        }
    ],
    "sg:phone":"+1 781 871 2167",
    "sg:postcode":"02370",
    "sg:province":"MA",
    "sg:tags":[
        "martial",
        "arts",
        "instruction"
    ],
    "wof:name":"Tae KWON Do Authority-Martial",
    "wof:placetype":"venue"
},
  "geometry": {"coordinates":[-70.915059,42.127119],"type":"Point"}
}