{
  "type": "Feature",
  "properties": {
    "iso:country":"US",
    "sg:address":"950 Broadway",
    "sg:city":"Chelsea",
    "sg:classifiers":[
        {
            "category":"Real Estate",
            "subcategory":"Real Estate Agent",
            "type":"Services"
        }
    ],
    "sg:phone":"+1 617 889 0900",
    "sg:postcode":"02150",
    "sg:province":"MA",
    "sg:website":"www.richportrealestate.com",
    "wof:name":"Richport Real Estate",
    "wof:placetype":"venue"
},
  "geometry": {"coordinates":[-71.020162,42.401583],"type":"Point"}
}