{
  "type": "Feature",
  "properties": {
    "iso:country":"US",
    "sg:address":"41 Russo Cir",
    "sg:city":"Agawam",
    "sg:classifiers":[
        {
            "category":"Manufacturing",
            "subcategory":"Tools & Machinery",
            "type":"Manufacturing & Wholesale Goods"
        }
    ],
    "sg:phone":"+1 413 789 0613",
    "sg:postcode":"01001",
    "sg:province":"MA",
    "sg:tags":[
        "mold",
        "special"
    ],
    "sg:website":"www.j-ktool.com",
    "wof:name":"J K Tool Co",
    "wof:placetype":"venue"
},
  "geometry": {"coordinates":[-72.632062,42.084201],"type":"Point"}
}