{
  "type": "Feature",
  "properties": {
    "addr:full": "41 Russo Cir Agawam MA 01001",
    "addr:housenumber": "41",
    "addr:postcode": "01001",
    "addr:street": "Russo Cir",
    "iso:country": "US",
    "sg:address": "41 Russo Cir",
    "sg:city": "Agawam",
    "sg:classifiers": [
      {
        "category": "Manufacturing",
        "subcategory": "Tools \u0026 Machinery",
        "type": "Manufacturing \u0026 Wholesale Goods"
      }
    ],
    "sg:phone": "+1 413 789 0613",
    "sg:postcode": "01001",
    "sg:province": "MA",
    "sg:tags": [
      "mold",
      "special"
    ],
    "sg:website": "www.j-ktool.com",
    "wof:name": "J K Tool Co",
    "wof:placetype": "venue"
  },
  "geometry": {"coordinates":[-72.632062,42.084201],"type":"Point"}
}
