{
  "type": "Feature",
  "properties": {
    "addr:full": "10 Nye St New Bedford MA 02746",
    "addr:housenumber": "10",
    "addr:postcode": "02746",
    "addr:street": "Nye St",
    "iso:country": "US",
    "sg:address": "10 Nye St",
    "sg:city": "New Bedford",
    "sg:classifiers": [
      {
        "category": "Autos \u0026 Motor Vehicles",
        "subcategory": "Automobile Sales",
        "type": "Retail Goods"
      }
    ],
    "sg:phone": "+1 508 999 0295",
    "sg:postcode": "02746",
    "sg:province": "MA",
    "sg:tags": [
      "car",
      "dealer"
    ],
    "wof:name": "Roy's Auto \u0026 Cycle Sales",
    "wof:placetype": "venue"
  },
  "geometry": {"coordinates":[-70.925783,41.659961],"type":"Point"}
}
