{
  "type": "Feature",
  "properties": {
    "iso:country":"US",
    "sg:address":"42 Ann Vinal Rd",
    "sg:city":"Scituate",
    "sg:classifiers":[
        {
            "category":"Coffee & Tea",
            "type":"Food & Drink"
        },
        {
            "category":"Restaurant",
            "type":"Food & Drink"
        }
    ],
    "sg:phone":"+1 781 545 2708",
    "sg:postcode":"02066",
    "sg:province":"MA",
    "sg:tags":[
        "espresso"
    ],
    "wof:name":"Off Cuff Cafe",
    "wof:placetype":"venue"
},
  "geometry": {"coordinates":[-70.759811,42.21476],"type":"Point"}
}