{
  "type": "Feature",
  "properties": {
    "addr:full": "42 Ann Vinal Rd Scituate MA 02066",
    "addr:housenumber": "42",
    "addr:postcode": "02066",
    "addr:street": "Ann Vinal Rd",
    "iso:country": "US",
    "sg:address": "42 Ann Vinal Rd",
    "sg:city": "Scituate",
    "sg:classifiers": [
      {
        "category": "Coffee \u0026 Tea",
        "type": "Food \u0026 Drink"
      },
      {
        "category": "Restaurant",
        "type": "Food \u0026 Drink"
      }
    ],
    "sg:phone": "+1 781 545 2708",
    "sg:postcode": "02066",
    "sg:province": "MA",
    "sg:tags": [
      "espresso"
    ],
    "wof:name": "Off Cuff Cafe",
    "wof:placetype": "venue"
  },
  "geometry": {"coordinates":[-70.759811,42.21476],"type":"Point"}
}
