{
  "type": "Feature",
  "properties": {
    "iso:country":"US",
    "sg:address":"169 Lakeside Ave",
    "sg:city":"Marlborough",
    "sg:classifiers":[
        {
            "category":"Organizations",
            "subcategory":"Professional Association",
            "type":"Services"
        }
    ],
    "sg:phone":"+1 508 460 9333",
    "sg:postcode":"01752",
    "sg:province":"MA",
    "sg:website":"www.massvet.org",
    "wof:name":"Mass Veterinary Medical Assoc",
    "wof:placetype":"venue"
},
  "geometry": {"coordinates":[-71.56739399999999,42.342344],"type":"Point"}
}