{
  "type": "Feature",
  "properties": {
    "addr:full": "169 Lakeside Ave Marlborough MA 01752",
    "addr:housenumber": "169",
    "addr:postcode": "01752",
    "addr:street": "Lakeside Ave",
    "iso:country": "US",
    "sg:address": "169 Lakeside Ave",
    "sg:city": "Marlborough",
    "sg:classifiers": [
      {
        "category": "Organizations",
        "subcategory": "Professional Association",
        "type": "Services"
      }
    ],
    "sg:phone": "+1 508 460 9333",
    "sg:postcode": "01752",
    "sg:province": "MA",
    "sg:website": "www.massvet.org",
    "wof:name": "Mass Veterinary Medical Assoc",
    "wof:placetype": "venue"
  },
  "geometry": {"coordinates":[-71.567394,42.342344],"type":"Point"}
}
