{
  "type": "Feature",
  "properties": {
    "addr:full": "4 India St Nantucket MA 02554",
    "addr:housenumber": "4",
    "addr:postcode": "02554",
    "addr:street": "India St",
    "iso:country": "US",
    "sg:address": "4 India St",
    "sg:city": "Nantucket",
    "sg:classifiers": [
      {
        "category": "Food \u0026 Beverages",
        "subcategory": "Specialty",
        "type": "Retail Goods"
      }
    ],
    "sg:phone": "+1 508 228 4353",
    "sg:postcode": "02554",
    "sg:province": "MA",
    "sg:tags": [
      "gourmet",
      "shop"
    ],
    "sg:website": "www.nantucketgourmet.com",
    "wof:name": "Nantucket Gourmet",
    "wof:placetype": "venue"
  },
  "geometry": {"coordinates":[-70.099375,41.284009],"type":"Point"}
}
