{
  "type": "Feature",
  "properties": {
    "addr:full":"150 Wells Ave Newton MA 02459",
    "addr:housenumber":"150",
    "addr:postcode":"02459",
    "addr:street":"Wells Ave",
    "iso:country":"US",
    "sg:address":"150 Wells Ave",
    "sg:city":"Newton",
    "sg:classifiers":[
        {
            "category":"Insurance",
            "subcategory":"Insurance Agent",
            "type":"Services"
        }
    ],
    "sg:phone":"+1 617 964 5340",
    "sg:postcode":"02459",
    "sg:province":"MA",
    "sg:website":"www.telamonins.com",
    "wof:name":"Telamon Insurance Network",
    "wof:placetype":"venue"
},
  "geometry": {"coordinates":[-71.196609,42.292854],"type":"Point"}
}