{
  "type": "Feature",
  "properties": {
    "iso:country":"US",
    "sg:address":"65 W Main St",
    "sg:city":"Millbury",
    "sg:classifiers":[
        {
            "category":"Building & Trades",
            "subcategory":"Construction",
            "type":"Services"
        }
    ],
    "sg:phone":"+1   ",
    "sg:postcode":"01527",
    "sg:province":"MA",
    "sg:tags":[
        "contractor"
    ],
    "wof:name":"Magliaro Roofing",
    "wof:placetype":"venue"
},
  "geometry": {"coordinates":[-71.769318,42.182823],"type":"Point"}
}