{
  "type": "Feature",
  "properties": {
    "addr:full":"30 Nagog Park Acton MA 01720",
    "addr:housenumber":"30",
    "addr:postcode":"01720",
    "addr:street":"Nagog Park",
    "iso:country":"US",
    "sg:address":"30 Nagog Park",
    "sg:city":"Acton",
    "sg:classifiers":[
        {
            "category":"Wholesale",
            "subcategory":"Electrical",
            "type":"Manufacturing & Wholesale Goods"
        }
    ],
    "sg:phone":"+1 978 264 0051",
    "sg:postcode":"01720",
    "sg:province":"MA",
    "sg:tags":[
        "equipment",
        "electronic",
        "supply"
    ],
    "wof:name":"Motion Engineering Inc",
    "wof:placetype":"venue"
},
  "geometry": {"coordinates":[-71.43214399999999,42.524904],"type":"Point"}
}