{
  "type": "Feature",
  "properties": {
    "addr:full": "270 Pulaski Blvd Bellingham MA 02019",
    "addr:housenumber": "270",
    "addr:postcode": "02019",
    "addr:street": "Pulaski Blvd",
    "iso:country": "US",
    "sg:address": "270 Pulaski Blvd",
    "sg:city": "Bellingham",
    "sg:classifiers": [
      {
        "category": "Personal",
        "subcategory": "Barber",
        "type": "Services"
      }
    ],
    "sg:phone": "+1   ",
    "sg:postcode": "02019",
    "sg:province": "MA",
    "sg:tags": [
      "shop"
    ],
    "wof:name": "Charlands Barber Stylist",
    "wof:placetype": "venue"
  },
  "geometry": {"coordinates":[-71.493214,42.022239],"type":"Point"}
}
