{
  "type": "Feature",
  "properties": {
    "addr:full":"499 Rantoul St Beverly MA 01915",
    "addr:housenumber":"499",
    "addr:postcode":"01915",
    "addr:street":"Rantoul St",
    "iso:country":"US",
    "sg:address":"499 Rantoul St",
    "sg:city":"Beverly",
    "sg:classifiers":[
        {
            "category":"Organizations",
            "subcategory":"Religious Organization",
            "type":"Services"
        }
    ],
    "sg:phone":"+1 978 927 4066",
    "sg:postcode":"01915",
    "sg:province":"MA",
    "wof:name":"Seventh Day Adventist Church",
    "wof:placetype":"venue"
},
  "geometry": {"coordinates":[-70.880045,42.557687],"type":"Point"}
}