{
  "type": "Feature",
  "properties": {
    "addr:full": "252 Newbury St Peabody MA 01960",
    "addr:housenumber": "252",
    "addr:postcode": "01960",
    "addr:street": "Newbury St",
    "iso:country": "US",
    "sg:address": "252 Newbury St",
    "sg:city": "Peabody",
    "sg:classifiers": [
      {
        "category": "Wholesale",
        "subcategory": "Motor Vehicles",
        "type": "Manufacturing \u0026 Wholesale Goods"
      }
    ],
    "sg:phone": "+1   ",
    "sg:postcode": "01960",
    "sg:province": "MA",
    "wof:name": "Prestige Auto Classics",
    "wof:placetype": "venue"
  },
  "geometry": {"coordinates":[-70.983311,42.548384],"type":"Point"}
}
