{
  "type": "Feature",
  "properties": {
    "iso:country":"US",
    "sg:address":"252 Newbury St",
    "sg:city":"Peabody",
    "sg:classifiers":[
        {
            "category":"Wholesale",
            "subcategory":"Motor Vehicles",
            "type":"Manufacturing & Wholesale Goods"
        }
    ],
    "sg:phone":"+1   ",
    "sg:postcode":"01960",
    "sg:province":"MA",
    "wof:name":"Prestige Auto Classics",
    "wof:placetype":"venue"
},
  "geometry": {"coordinates":[-70.983311,42.548384],"type":"Point"}
}