{
  "type": "Feature",
  "properties": {
    "addr:full":"171 Hawthorne Ln Concord MA 01742",
    "addr:housenumber":"171",
    "addr:postcode":"01742",
    "addr:street":"Hawthorne Ln",
    "iso:country":"US",
    "sg:address":"171 Hawthorne Ln",
    "sg:city":"Concord",
    "sg:classifiers":[
        {
            "category":"Real Estate",
            "subcategory":"Real Estate Operator",
            "type":"Services"
        }
    ],
    "sg:phone":"+1   ",
    "sg:postcode":"01742",
    "sg:province":"MA",
    "sg:tags":[
        "building",
        "apartment",
        "construction",
        "residential"
    ],
    "wof:name":"D F Caccavoro Construction",
    "wof:placetype":"venue"
},
  "geometry": {"coordinates":[-71.332807,42.455411],"type":"Point"}
}