{
  "type": "Feature",
  "properties": {
    "addr:full":"354 Lowell St Lawrence MA 01841",
    "addr:housenumber":"354",
    "addr:postcode":"01841",
    "addr:street":"Lowell St",
    "iso:country":"US",
    "sg:address":"354 Lowell St",
    "sg:city":"Lawrence",
    "sg:classifiers":[
        {
            "category":"Personal",
            "subcategory":"Beauty Salon",
            "type":"Services"
        }
    ],
    "sg:phone":"+1 978 794 5738",
    "sg:postcode":"01841",
    "sg:province":"MA",
    "wof:name":"Patricia Hair Design",
    "wof:placetype":"venue"
},
  "geometry": {"coordinates":[-71.173728,42.704853],"type":"Point"}
}