{
  "type": "Feature",
  "properties": {
    "iso:country":"US",
    "sg:address":"63 Poplar St",
    "sg:city":"Roslindale",
    "sg:classifiers":[
        {
            "category":"Shopping",
            "subcategory":"Used Merchandise",
            "type":"Retail Goods"
        }
    ],
    "sg:phone":"+1   ",
    "sg:postcode":"02131",
    "sg:province":"MA",
    "wof:name":"Books & More",
    "wof:placetype":"venue"
},
  "geometry": {"coordinates":[-71.128827,42.285123],"type":"Point"}
}