{
  "type": "Feature",
  "properties": {
    "iso:country":"US",
    "sg:address":"1017 Turnpike St",
    "sg:city":"Canton",
    "sg:classifiers":[
        {
            "category":"Utilities",
            "subcategory":"Telephone",
            "type":"Services"
        }
    ],
    "sg:phone":"+1 781 828 5100",
    "sg:postcode":"02021",
    "sg:province":"MA",
    "sg:tags":[
        "company"
    ],
    "wof:name":"Atlantic Telephone Co",
    "wof:placetype":"venue"
},
  "geometry": {"coordinates":[-71.10486899999999,42.149936],"type":"Point"}
}