{
  "type": "Feature",
  "properties": {
    "addr:full": "106 Main Street Wareham MA 02571",
    "addr:housenumber": "106",
    "addr:postcode": "02571",
    "addr:street": "Main Street",
    "iso:country": "US",
    "sg:address": "106 Main Street",
    "sg:city": "Wareham",
    "sg:classifiers": [
      {
        "category": "Community Center",
        "type": "Public Place"
      }
    ],
    "sg:phone": "+1 800 639 6773",
    "sg:postcode": "02571",
    "sg:province": "MA",
    "sg:tags": [
      "medical"
    ],
    "sg:website": "www.localstdtesting.com/15",
    "wof:name": "Local STD Testing",
    "wof:placetype": "venue"
  },
  "geometry": {"coordinates":[-70.712708,41.755972],"type":"Point"}
}
