{
  "type": "Feature",
  "properties": {
    "iso:country":"US",
    "sg:address":"3211 Washington St",
    "sg:city":"Jamaica Plain",
    "sg:classifiers":[
        {
            "category":"Personal",
            "subcategory":"Beauty Salon",
            "type":"Services"
        }
    ],
    "sg:phone":"+1 617 524 0049",
    "sg:postcode":"02130",
    "sg:province":"MA",
    "wof:name":"Lisandro Beauty Salon",
    "wof:placetype":"venue"
},
  "geometry": {"coordinates":[-71.102498,42.311681],"type":"Point"}
}