{
  "type": "Feature",
  "properties": {
    "addr:full":"1981 Memorial Dr Chicopee MA 01020",
    "addr:housenumber":"1981",
    "addr:postcode":"01020",
    "addr:street":"Memorial Dr",
    "iso:country":"US",
    "sg:address":"1981 Memorial Dr",
    "sg:city":"Chicopee",
    "sg:classifiers":[
        {
            "category":"Professional",
            "subcategory":"Advertising",
            "type":"Services"
        }
    ],
    "sg:phone":"+1 413 539 9112",
    "sg:postcode":"01020",
    "sg:province":"MA",
    "sg:tags":[
        "mailing",
        "shipping"
    ],
    "wof:name":"UPS Store",
    "wof:placetype":"venue"
},
  "geometry": {"coordinates":[-72.571736,42.211808],"type":"Point"}
}