{
  "type": "Feature",
  "properties": {
    "addr:full": "9 Marlboro St Maynard MA 01754",
    "addr:housenumber": "9",
    "addr:postcode": "01754",
    "addr:street": "Marlboro St",
    "iso:country": "US",
    "sg:address": "9 Marlboro St",
    "sg:city": "Maynard",
    "sg:classifiers": [
      {
        "category": "Professional",
        "subcategory": "Business Services",
        "type": "Services"
      }
    ],
    "sg:phone": "+1 978 461 4932",
    "sg:postcode": "01754",
    "sg:province": "MA",
    "wof:name": "Practical Planner",
    "wof:placetype": "venue"
  },
  "geometry": {"coordinates":[-71.444855,42.421235],"type":"Point"}
}
