{
  "type": "Feature",
  "properties": {
    "iso:country":"US",
    "sg:address":"2 Maureen Rd",
    "sg:city":"Lexington",
    "sg:classifiers":[
        {
            "category":"Professional",
            "subcategory":"Business Services",
            "type":"Services"
        }
    ],
    "sg:phone":"+1   ",
    "sg:postcode":"02420",
    "sg:province":"MA",
    "wof:name":"Transit Solutions Inc",
    "wof:placetype":"venue"
},
  "geometry": {"coordinates":[-71.210228,42.457263],"type":"Point"}
}