{
  "type": "Feature",
  "properties": {
    "addr:full": "17 E Mountain St Worcester MA 01606",
    "addr:housenumber": "17",
    "addr:postcode": "01606",
    "addr:street": "E Mountain St",
    "iso:country": "US",
    "sg:address": "17 E Mountain St",
    "sg:city": "Worcester",
    "sg:classifiers": [
      {
        "category": "Restaurant",
        "type": "Food \u0026 Drink"
      }
    ],
    "sg:phone": "+1 508 856 0516",
    "sg:postcode": "01606",
    "sg:province": "MA",
    "sg:tags": [
      "delicatessen"
    ],
    "wof:name": "Elsa's Bushel 'n Peck",
    "wof:placetype": "venue"
  },
  "geometry": {"coordinates":[-71.79265,42.323671],"type":"Point"}
}
