{
  "type": "Feature",
  "properties": {
    "iso:country":"US",
    "sg:address":"17 E Mountain St",
    "sg:city":"Worcester",
    "sg:classifiers":[
        {
            "category":"Restaurant",
            "type":"Food & Drink"
        }
    ],
    "sg:phone":"+1 508 856 0516",
    "sg:postcode":"01606",
    "sg:province":"MA",
    "sg:tags":[
        "delicatessen"
    ],
    "wof:name":"Elsa's Bushel 'n Peck",
    "wof:placetype":"venue"
},
  "geometry": {"coordinates":[-71.79264999999999,42.323671],"type":"Point"}
}