{
  "type": "Feature",
  "properties": {
    "addr:full":"321 Somerville Ave Somerville MA 02143",
    "addr:housenumber":"321",
    "addr:postcode":"02143",
    "addr:street":"Somerville Ave",
    "iso:country":"US",
    "sg:address":"321 Somerville Ave",
    "sg:city":"Somerville",
    "sg:classifiers":[
        {
            "category":"Shopping",
            "subcategory":"Pets & Pet Supplies",
            "type":"Retail Goods"
        }
    ],
    "sg:phone":"+1 617 233 5496",
    "sg:postcode":"02143",
    "sg:province":"MA",
    "sg:tags":[
        "training"
    ],
    "sg:website":"www.zendogtraining.net",
    "wof:name":"Zen Dog Training",
    "wof:placetype":"venue"
},
  "geometry": {"coordinates":[-71.097537,42.380421],"type":"Point"}
}