{
  "type": "Feature",
  "properties": {
    "iso:country":"US",
    "sg:address":"126 Beaver St",
    "sg:city":"Framingham",
    "sg:classifiers":[
        {
            "category":"Shopping",
            "subcategory":"Party Supplies",
            "type":"Retail Goods"
        },
        {
            "category":"Personal",
            "type":"Services"
        }
    ],
    "sg:phone":"+1 508 820 7952",
    "sg:postcode":"01702",
    "sg:province":"MA",
    "sg:tags":[
        "delivery",
        "balloon",
        "balloons-retail",
        "decorator"
    ],
    "wof:name":"Balloons Over New England",
    "wof:placetype":"venue"
},
  "geometry": {"coordinates":[-71.40537999999999,42.275512],"type":"Point"}
}