{
  "type": "Feature",
  "properties": {
    "addr:full": "126 Beaver St Framingham MA 01702",
    "addr:housenumber": "126",
    "addr:postcode": "01702",
    "addr:street": "Beaver St",
    "iso:country": "US",
    "sg:address": "126 Beaver St",
    "sg:city": "Framingham",
    "sg:classifiers": [
      {
        "category": "Shopping",
        "subcategory": "Party Supplies",
        "type": "Retail Goods"
      },
      {
        "category": "Personal",
        "type": "Services"
      }
    ],
    "sg:phone": "+1 508 820 7952",
    "sg:postcode": "01702",
    "sg:province": "MA",
    "sg:tags": [
      "delivery",
      "balloon",
      "balloons-retail",
      "decorator"
    ],
    "wof:name": "Balloons Over New England",
    "wof:placetype": "venue"
  },
  "geometry": {"coordinates":[-71.40538,42.275512],"type":"Point"}
}
