{
  "type": "Feature",
  "properties": {
    "iso:country":"US",
    "sg:address":"44 Allen Cir",
    "sg:city":"Milton",
    "sg:classifiers":[
        {
            "category":"Professional",
            "type":"Services"
        }
    ],
    "sg:phone":"+1 617 696 0787",
    "sg:postcode":"02186",
    "sg:province":"MA",
    "sg:tags":[
        "writer"
    ],
    "wof:name":"Syntax The Word Co",
    "wof:placetype":"venue"
},
  "geometry": {"coordinates":[-71.08488,42.26704],"type":"Point"}
}