{
  "type": "Feature",
  "properties": {
    "addr:full": "3 Barnes Rd Hingham MA 02043",
    "addr:housenumber": "3",
    "addr:postcode": "02043",
    "addr:street": "Barnes Rd",
    "iso:country": "US",
    "sg:address": "3 Barnes Rd",
    "sg:city": "Hingham",
    "sg:classifiers": [
      {
        "category": "Professional",
        "subcategory": "Advertising",
        "type": "Services"
      }
    ],
    "sg:phone": "+1   ",
    "sg:postcode": "02043",
    "sg:province": "MA",
    "sg:tags": [
      "small",
      "magazine",
      "growth",
      "business"
    ],
    "wof:name": "Black Rock Advertising \u0026 Pubg",
    "wof:placetype": "venue"
  },
  "geometry": {"coordinates":[-70.876815,42.24724],"type":"Point"}
}
