{
  "type": "Feature",
  "properties": {
    "iso:country":"US",
    "sg:address":"8 S Market St",
    "sg:city":"Boston",
    "sg:classifiers":[
        {
            "category":"Professional",
            "type":"Services"
        }
    ],
    "sg:phone":"+1 617 973 6410",
    "sg:postcode":"02109",
    "sg:province":"MA",
    "sg:tags":[
        "establishment"
    ],
    "wof:name":"Norkom",
    "wof:placetype":"venue"
},
  "geometry": {"coordinates":[-71.053996,42.360049],"type":"Point"}
}