{
  "type": "Feature",
  "properties": {
    "addr:full":"100 Old Lancaster Rd Sudbury MA 01776",
    "addr:housenumber":"100",
    "addr:postcode":"01776",
    "addr:street":"Old Lancaster Rd",
    "iso:country":"US",
    "sg:address":"100 Old Lancaster Rd",
    "sg:city":"Sudbury",
    "sg:classifiers":[
        {
            "category":"Shopping",
            "subcategory":"Computers & Home Electronics",
            "type":"Retail Goods"
        }
    ],
    "sg:phone":"+1 978 443 7910",
    "sg:postcode":"01776",
    "sg:province":"MA",
    "sg:tags":[
        "software"
    ],
    "wof:name":"Speedwork Co Inc",
    "wof:placetype":"venue"
},
  "geometry": {"coordinates":[-71.41043500000001,42.370233],"type":"Point"}
}