{
  "type": "Feature",
  "properties": {
    "addr:full":"112 Tyngsboro Rd North Chelmsford MA 01863",
    "addr:housenumber":"112",
    "addr:postcode":"01863",
    "addr:street":"Tyngsboro Rd",
    "iso:country":"US",
    "sg:address":"112 Tyngsboro Rd",
    "sg:city":"North Chelmsford",
    "sg:classifiers":[
        {
            "category":"Retail",
            "subcategory":"Auto Repair",
            "type":"Services"
        }
    ],
    "sg:phone":"+1 978 251 8029",
    "sg:postcode":"01863",
    "sg:province":"MA",
    "sg:tags":[
        "body",
        "automobile",
        "painting"
    ],
    "wof:name":"Stony Brook Auto Body",
    "wof:placetype":"venue"
},
  "geometry": {"coordinates":[-71.391835,42.644838],"type":"Point"}
}