{
  "type": "Feature",
  "properties": {
    "iso:country":"US",
    "sg:address":"28 Goshen Rd",
    "sg:city":"Williamsburg",
    "sg:classifiers":[
        {
            "category":"Shopping",
            "subcategory":"Crafts & Fabrics",
            "type":"Retail Goods"
        }
    ],
    "sg:phone":"+1 413 268 7063",
    "sg:postcode":"01096",
    "sg:province":"MA",
    "sg:tags":[
        "sewing",
        "yarn"
    ],
    "wof:name":"Lois' Yarn Shop",
    "wof:placetype":"venue"
},
  "geometry": {"coordinates":[-72.741587,42.397402],"type":"Point"}
}