{
  "type": "Feature",
  "properties": {
    "iso:country":"US",
    "sg:address":"25 Commercial Dr",
    "sg:city":"Wrentham",
    "sg:classifiers":[
        {
            "category":"Professional",
            "subcategory":"Engineering",
            "type":"Services"
        }
    ],
    "sg:phone":"+1 508 384 9782",
    "sg:postcode":"02093",
    "sg:province":"MA",
    "sg:tags":[
        "consulting",
        "engineer"
    ],
    "wof:name":"Rb Carr Engineering Associates Inc",
    "wof:placetype":"venue"
},
  "geometry": {"coordinates":[-71.300538,42.051196],"type":"Point"}
}