{
  "type": "Feature",
  "properties": {
    "addr:full":"1522 Boston Rd Springfield MA 01129",
    "addr:housenumber":"1522",
    "addr:postcode":"01129",
    "addr:street":"Boston Rd",
    "iso:country":"US",
    "sg:address":"1522 Boston Rd",
    "sg:city":"Springfield",
    "sg:classifiers":[
        {
            "category":"Wholesale",
            "subcategory":"Electrical",
            "type":"Manufacturing & Wholesale Goods"
        }
    ],
    "sg:phone":"+1 413 543 5655",
    "sg:postcode":"01129",
    "sg:province":"MA",
    "sg:tags":[
        "appliance"
    ],
    "wof:name":"Bernie's House Of Television",
    "wof:placetype":"venue"
},
  "geometry": {"coordinates":[-72.49041099999999,42.142504],"type":"Point"}
}