{
  "type": "Feature",
  "properties": {
    "addr:full":"182 Dudley St Roxbury MA 02119",
    "addr:housenumber":"182",
    "addr:postcode":"02119",
    "addr:street":"Dudley St",
    "iso:country":"US",
    "sg:address":"182 Dudley St",
    "sg:city":"Roxbury",
    "sg:classifiers":[
        {
            "category":"Building & Trades",
            "subcategory":"Locksmith",
            "type":"Services"
        }
    ],
    "sg:phone":"+1 617 602 1119",
    "sg:postcode":"02119",
    "sg:province":"MA",
    "sg:tags":[
        "key"
    ],
    "wof:name":"Aaron Locksmith Service",
    "wof:placetype":"venue"
},
  "geometry": {"coordinates":[-71.082188,42.328682],"type":"Point"}
}