{
  "type": "Feature",
  "properties": {
    "addr:full": "406 State Rd North Dartmouth MA 02747",
    "addr:housenumber": "406",
    "addr:postcode": "02747",
    "addr:street": "State Rd",
    "iso:country": "US",
    "sg:address": "406 State Rd",
    "sg:city": "North Dartmouth",
    "sg:classifiers": [
      {
        "category": "Banks \u0026 Credit Unions",
        "subcategory": "Investment Brokerage",
        "type": "Services"
      }
    ],
    "sg:phone": "+1 508 992 7040",
    "sg:postcode": "02747",
    "sg:province": "MA",
    "sg:tags": [
      "advisory",
      "financial"
    ],
    "wof:name": "Conway Financial Svc",
    "wof:placetype": "venue"
  },
  "geometry": {"coordinates":[-70.996697,41.640369],"type":"Point"}
}
