{
  "type": "Feature",
  "properties": {
    "iso:country":"US",
    "sg:address":"406 State Rd",
    "sg:city":"North Dartmouth",
    "sg:classifiers":[
        {
            "category":"Banks & Credit Unions",
            "subcategory":"Investment Brokerage",
            "type":"Services"
        }
    ],
    "sg:phone":"+1 508 992 7040",
    "sg:postcode":"02747",
    "sg:province":"MA",
    "sg:tags":[
        "advisory",
        "financial"
    ],
    "wof:name":"Conway Financial Svc",
    "wof:placetype":"venue"
},
  "geometry": {"coordinates":[-70.996697,41.640369],"type":"Point"}
}