{
  "type": "Feature",
  "properties": {
    "addr:full": "1785 Centre St West Roxbury MA 02132",
    "addr:housenumber": "1785",
    "addr:postcode": "02132",
    "addr:street": "Centre St",
    "iso:country": "US",
    "sg:address": "1785 Centre St",
    "sg:city": "West Roxbury",
    "sg:classifiers": [
      {
        "category": "Retail",
        "subcategory": "Animal Services",
        "type": "Services"
      }
    ],
    "sg:phone": "+1 617 325 8412",
    "sg:postcode": "02132",
    "sg:province": "MA",
    "sg:tags": [
      "pet",
      "boarding",
      "sitting"
    ],
    "wof:name": "Casey's K-9 Clubhouse Inc",
    "wof:placetype": "venue"
  },
  "geometry": {"coordinates":[-71.151032,42.287396],"type":"Point"}
}
