{
  "type": "Feature",
  "properties": {
    "iso:country":"US",
    "sg:address":"251 Main St",
    "sg:city":"Oxford",
    "sg:classifiers":[
        {
            "category":"Professional",
            "subcategory":"Accounting & Tax Preparation",
            "type":"Services"
        }
    ],
    "sg:phone":"+1 508 987 7994",
    "sg:postcode":"01540",
    "sg:province":"MA",
    "sg:tags":[
        "accountant"
    ],
    "wof:name":"Heald & Bianculli LLP",
    "wof:placetype":"venue"
},
  "geometry": {"coordinates":[-71.865393,42.112515],"type":"Point"}
}