{
  "type": "Feature",
  "properties": {
    "addr:full": "251 Main St Oxford MA 01540",
    "addr:housenumber": "251",
    "addr:postcode": "01540",
    "addr:street": "Main St",
    "iso:country": "US",
    "sg:address": "251 Main St",
    "sg:city": "Oxford",
    "sg:classifiers": [
      {
        "category": "Professional",
        "subcategory": "Accounting \u0026 Tax Preparation",
        "type": "Services"
      }
    ],
    "sg:phone": "+1 508 987 7994",
    "sg:postcode": "01540",
    "sg:province": "MA",
    "sg:tags": [
      "accountant"
    ],
    "wof:name": "Heald \u0026 Bianculli LLP",
    "wof:placetype": "venue"
  },
  "geometry": {"coordinates":[-71.865393,42.112515],"type":"Point"}
}
