{
  "type": "Feature",
  "properties": {
    "addr:full": "25 Dorchester Ave Lbby Boston MA 02205",
    "addr:housenumber": "25",
    "addr:postcode": "02205",
    "addr:street": "Dorchester Ave",
    "iso:country": "US",
    "sg:address": "25 Dorchester Ave Lbby",
    "sg:city": "Boston",
    "sg:classifiers": [
      {
        "category": "Communications",
        "subcategory": "Newspaper",
        "type": "Services"
      }
    ],
    "sg:phone": "+1 617 292 0013",
    "sg:postcode": "02205",
    "sg:province": "MA",
    "sg:tags": [
      "print",
      "medium"
    ],
    "wof:name": "Rocco's News Stand",
    "wof:placetype": "venue"
  },
  "geometry": {"coordinates":[-71.055099,42.348499],"type":"Point"}
}
