{
  "type": "Feature",
  "properties": {
    "addr:full":"325 Foxboro Blvd Foxboro MA 02035",
    "addr:housenumber":"325",
    "addr:postcode":"02035",
    "addr:street":"Foxboro Blvd",
    "iso:country":"US",
    "sg:address":"325 Foxboro Blvd",
    "sg:city":"Foxboro",
    "sg:classifiers":[
        {
            "category":"Professional",
            "subcategory":"Computer Services",
            "type":"Services"
        }
    ],
    "sg:phone":"+1 508 698 3322",
    "sg:postcode":"02035",
    "sg:province":"MA",
    "sg:tags":[
        "consultant",
        "designer"
    ],
    "sg:website":"www.intellution.com",
    "wof:name":"GE Fanuc Intellution",
    "wof:placetype":"venue"
},
  "geometry": {"coordinates":[-71.23666799999999,42.043114],"type":"Point"}
}