{
  "type": "Feature",
  "properties": {
    "iso:country":"US",
    "sg:address":"227 Whiting Farms Rd",
    "sg:city":"Holyoke",
    "sg:classifiers":[
        {
            "category":"Bars & Pubs",
            "type":"Food & Drink"
        },
        {
            "category":"Restaurant",
            "type":"Food & Drink"
        }
    ],
    "sg:menulink":"http://www.allmenus.com/ma/holyoke/35251-cracker-barrel-old-country-store/menu/",
    "sg:phone":"+1 413 493 1831",
    "sg:postcode":"01040",
    "sg:province":"MA",
    "sg:tags":[
        "american",
        "southern"
    ],
    "wof:name":"Cracker Barrel Old Country Store",
    "wof:placetype":"venue"
},
  "geometry": {"coordinates":[-72.640378,42.177283],"type":"Point"}
}