{
  "type": "Feature",
  "properties": {
    "addr:full":"185 Washington St Attleboro MA 02703",
    "addr:housenumber":"185",
    "addr:postcode":"02703",
    "addr:street":"Washington St",
    "iso:country":"US",
    "sg:address":"185 Washington St",
    "sg:city":"Attleboro",
    "sg:classifiers":[
        {
            "category":"Shopping",
            "subcategory":"Books",
            "type":"Retail Goods"
        }
    ],
    "sg:phone":"+1 508 399 5941",
    "sg:postcode":"02703",
    "sg:province":"MA",
    "sg:tags":[
        "bookstore"
    ],
    "wof:name":"Morning Star Christian Book & Music Stores",
    "wof:placetype":"venue"
},
  "geometry": {"coordinates":[-71.356201,41.9254],"type":"Point"}
}