{
  "type": "Feature",
  "properties": {
    "addr:full": "22 Cummings Park Woburn MA 01801",
    "addr:housenumber": "22",
    "addr:postcode": "01801",
    "addr:street": "Cummings Park",
    "iso:country": "US",
    "sg:address": "22 Cummings Park",
    "sg:city": "Woburn",
    "sg:classifiers": [
      {
        "category": "Professional",
        "subcategory": "Research",
        "type": "Services"
      }
    ],
    "sg:phone": "+1 781 935 3212",
    "sg:postcode": "01801",
    "sg:province": "MA",
    "sg:tags": [
      "development",
      "laboratory"
    ],
    "sg:website": "www.proscience.net",
    "wof:name": "Proscience Analytical Svc",
    "wof:placetype": "venue"
  },
  "geometry": {"coordinates":[-71.124248,42.497435],"type":"Point"}
}
