{
  "type": "Feature",
  "properties": {
    "iso:country":"US",
    "sg:address":"24 Apple Ln",
    "sg:city":"Dennis",
    "sg:classifiers":[
        {
            "category":"Health Services",
            "subcategory":"Doctor",
            "type":"Services"
        }
    ],
    "sg:phone":"+1 508 385 2496",
    "sg:postcode":"02638",
    "sg:province":"MA",
    "sg:tags":[
        "medicine",
        "physician",
        "practice",
        "surgeons",
        "family"
    ],
    "wof:name":"Dr Edw A Hutchinson Md",
    "wof:placetype":"venue"
},
  "geometry": {"coordinates":[-70.19459000000001,41.725944],"type":"Point"}
}