{
  "type": "Feature",
  "properties": {
    "addr:full": "199 Dexter Ave Watertown MA 02472",
    "addr:housenumber": "199",
    "addr:postcode": "02472",
    "addr:street": "Dexter Ave",
    "iso:country": "US",
    "sg:address": "199 Dexter Ave",
    "sg:city": "Watertown",
    "sg:classifiers": [
      {
        "category": "Building \u0026 Trades",
        "subcategory": "Construction",
        "type": "Services"
      }
    ],
    "sg:phone": "+1 617 924 8130",
    "sg:postcode": "02472",
    "sg:province": "MA",
    "sg:tags": [
      "tile",
      "dealer"
    ],
    "wof:name": "Zani Tile Co",
    "wof:placetype": "venue"
  },
  "geometry": {"coordinates":[-71.165669,42.364598],"type":"Point"}
}
