{
  "type": "Feature",
  "properties": {
    "addr:full": "4 Chapin Ave Reading MA 01867",
    "addr:housenumber": "4",
    "addr:postcode": "01867",
    "addr:street": "Chapin Ave",
    "iso:country": "US",
    "sg:address": "4 Chapin Ave",
    "sg:city": "Reading",
    "sg:classifiers": [
      {
        "category": "Autos \u0026 Motor Vehicles",
        "subcategory": "Auto Supplies",
        "type": "Retail Goods"
      }
    ],
    "sg:phone": "+1 781 944 6540",
    "sg:postcode": "01867",
    "sg:province": "MA",
    "sg:tags": [
      "automobile",
      "parts"
    ],
    "wof:name": "Suppliers Automotive Parts Co",
    "wof:placetype": "venue"
  },
  "geometry": {"coordinates":[-71.101896,42.52266],"type":"Point"}
}
