{
  "type": "Feature",
  "properties": {
    "iso:country":"US",
    "sg:address":"42 Prospect St",
    "sg:city":"Cambridge",
    "sg:phone":"+1 617 868 8838",
    "sg:postcode":"02139",
    "sg:province":"MA",
    "wof:name":"Jimmy's Shoe Repair",
    "wof:placetype":"venue"
},
  "geometry": {"coordinates":[-71.103183,42.366291],"type":"Point"}
}