{
  "type": "Feature",
  "properties": {
    "addr:full":"25 Columbia St Adams MA 01220",
    "addr:housenumber":"25",
    "addr:postcode":"01220",
    "addr:street":"Columbia St",
    "iso:country":"US",
    "sg:address":"25 Columbia St",
    "sg:city":"Adams",
    "sg:classifiers":[
        {
            "category":"Retail",
            "subcategory":"Auto Rental",
            "type":"Services"
        }
    ],
    "sg:phone":"+1 413 743 1720",
    "sg:postcode":"01220",
    "sg:province":"MA",
    "sg:tags":[
        "renting",
        "truck",
        "leasing"
    ],
    "wof:name":"U-Haul Co",
    "wof:placetype":"venue"
},
  "geometry": {"coordinates":[-73.11688100000001,42.627283],"type":"Point"}
}