{
  "type": "Feature",
  "properties": {
    "addr:full":"5 North St Woods Hole MA 02543",
    "addr:housenumber":"5",
    "addr:postcode":"02543",
    "addr:street":"North St",
    "iso:country":"US",
    "sg:address":"5 North St",
    "sg:city":"Woods Hole",
    "sg:classifiers":[
        {
            "category":"Professional",
            "subcategory":"Management & Consulting",
            "type":"Services"
        }
    ],
    "sg:phone":"+1 508 457 9084",
    "sg:postcode":"02543",
    "sg:province":"MA",
    "sg:tags":[
        "food"
    ],
    "wof:name":"Sodexho",
    "wof:placetype":"venue"
},
  "geometry": {"coordinates":[-70.673171,41.527057],"type":"Point"}
}