{
  "type": "Feature",
  "properties": {
    "addr:full":"1045 Saratoga St Boston MA 02128",
    "addr:housenumber":"1045",
    "addr:postcode":"02128",
    "addr:street":"Saratoga St",
    "iso:country":"US",
    "sg:address":"1045 Saratoga St",
    "sg:city":"Boston",
    "sg:classifiers":[
        {
            "category":"Restaurant",
            "type":"Food & Drink"
        }
    ],
    "sg:phone":"+1 617 567 0659",
    "sg:postcode":"02128",
    "sg:province":"MA",
    "wof:name":"Taqueria Michoacan",
    "wof:placetype":"venue"
},
  "geometry": {"coordinates":[-71.004834,42.385989],"type":"Point"}
}