{
  "type": "Feature",
  "properties": {
    "iso:country":"US",
    "sg:address":"1045 Saratoga St",
    "sg:city":"Boston",
    "sg:classifiers":[
        {
            "category":"Restaurant",
            "type":"Food & Drink"
        }
    ],
    "sg:phone":"+1 617 567 0659",
    "sg:postcode":"02128",
    "sg:province":"MA",
    "wof:name":"Taqueria Michoacan",
    "wof:placetype":"venue"
},
  "geometry": {"coordinates":[-71.004834,42.385989],"type":"Point"}
}