{
  "type": "Feature",
  "properties": {
    "iso:country":"US",
    "sg:address":"899 Main St",
    "sg:city":"Springfield",
    "sg:classifiers":[
        {
            "category":"Manufacturing",
            "subcategory":"Food",
            "type":"Manufacturing & Wholesale Goods"
        }
    ],
    "sg:phone":"+1   ",
    "sg:postcode":"01103",
    "sg:province":"MA",
    "sg:tags":[
        "drink",
        "soft",
        "mfg"
    ],
    "wof:name":"Bocce",
    "wof:placetype":"venue"
},
  "geometry": {"coordinates":[-72.582897,42.097897],"type":"Point"}
}