{
  "type": "Feature",
  "properties": {
    "addr:full": "23 Lunenburg St Fitchburg MA 01420",
    "addr:housenumber": "23",
    "addr:postcode": "01420",
    "addr:street": "Lunenburg St",
    "iso:country": "US",
    "sg:address": "23 Lunenburg St",
    "sg:city": "Fitchburg",
    "sg:classifiers": [
      {
        "category": "Restaurant",
        "type": "Food \u0026 Drink"
      }
    ],
    "sg:phone": "+1 978 342 6044",
    "sg:postcode": "01420",
    "sg:province": "MA",
    "sg:tags": [
      "asian",
      "chinese",
      "pan"
    ],
    "wof:name": "Dragon Express Inc",
    "wof:placetype": "venue"
  },
  "geometry": {"coordinates":[-71.7898,42.582132],"type":"Point"}
}
