{
  "type": "Feature",
  "properties": {
    "iso:country":"US",
    "sg:address":"10 Dane St",
    "sg:city":"Beverly",
    "sg:classifiers":[
        {
            "category":"Organizations",
            "subcategory":"Religious Organization",
            "type":"Services"
        }
    ],
    "sg:phone":"+1 978 922 4325",
    "sg:postcode":"01915",
    "sg:province":"MA",
    "sg:tags":[
        "church"
    ],
    "sg:website":"www.danestchurch.org",
    "wof:name":"Dane Street Congregational Chr",
    "wof:placetype":"venue"
},
  "geometry": {"coordinates":[-70.87873999999999,42.55187],"type":"Point"}
}