{
  "type": "Feature",
  "properties": {
    "iso:country":"US",
    "sg:address":"15 Chestnut St",
    "sg:city":"Worcester",
    "sg:classifiers":[
        {
            "category":"Wholesale",
            "subcategory":"Office Equipment",
            "type":"Manufacturing & Wholesale Goods"
        }
    ],
    "sg:phone":"+1 508 890 8622",
    "sg:postcode":"01609",
    "sg:province":"MA",
    "sg:tags":[
        "machine",
        "duplicating",
        "copying"
    ],
    "wof:name":"Alliance Business Systems",
    "wof:placetype":"venue"
},
  "geometry": {"coordinates":[-71.80391299999999,42.266042],"type":"Point"}
}