{
  "type": "Feature",
  "properties": {
    "iso:country":"US",
    "sg:address":"15 Lincoln St",
    "sg:city":"Newton",
    "sg:classifiers":[
        {
            "category":"Shopping",
            "subcategory":"Clothing, Apparel, & Fashions",
            "type":"Retail Goods"
        }
    ],
    "sg:phone":"+1 617 630 0664",
    "sg:postcode":"02461",
    "sg:province":"MA",
    "wof:name":"Sharon's Fashions",
    "wof:placetype":"venue"
},
  "geometry": {"coordinates":[-71.20727599999999,42.321625],"type":"Point"}
}