{
  "type": "Feature",
  "properties": {
    "iso:country":"US",
    "sg:address":"1940 Beacon St",
    "sg:city":"Brighton",
    "sg:classifiers":[
        {
            "category":"Restaurant",
            "type":"Food & Drink"
        }
    ],
    "sg:menulink":"http://www.allmenus.com/ma/boston/196-boloco/menu/",
    "sg:phone":"+1 617 739 0340",
    "sg:postcode":"02135",
    "sg:province":"MA",
    "sg:tags":[
        "smoothy",
        "mexican",
        "salad",
        "juice",
        "american",
        "wrap",
        "tex-mex",
        "californian"
    ],
    "wof:name":"Boloco",
    "wof:placetype":"venue"
},
  "geometry": {"coordinates":[-71.149064,42.33638],"type":"Point"}
}