{
  "type": "Feature",
  "properties": {
    "addr:full": "11 Sable Rd Salem MA 01970",
    "addr:housenumber": "11",
    "addr:postcode": "01970",
    "addr:street": "Sable Rd",
    "iso:country": "US",
    "sg:address": "11 Sable Rd",
    "sg:city": "Salem",
    "sg:classifiers": [
      {
        "category": "Shopping",
        "subcategory": "Discount \u0026 Variety Stores",
        "type": "Retail Goods"
      }
    ],
    "sg:phone": "+1 617 387 0230",
    "sg:postcode": "01970",
    "sg:province": "MA",
    "sg:tags": [
      "merchandise",
      "general"
    ],
    "wof:name": "Solomson Products Plstcs",
    "wof:placetype": "venue"
  },
  "geometry": {"coordinates":[-70.924865,42.513002],"type":"Point"}
}
