{
  "type": "Feature",
  "properties": {
    "addr:full":"65 Forest St Marshfield MA 02050",
    "addr:housenumber":"65",
    "addr:postcode":"02050",
    "addr:street":"Forest St",
    "iso:country":"US",
    "sg:address":"65 Forest St",
    "sg:city":"Marshfield",
    "sg:classifiers":[
        {
            "category":"Social Services",
            "type":"Services"
        },
        {
            "category":"Personal",
            "type":"Services"
        }
    ],
    "sg:phone":"+1 781 834 7900",
    "sg:postcode":"02050",
    "sg:province":"MA",
    "sg:tags":[
        "family",
        "worker",
        "counselors-licensed",
        "individual",
        "marriage",
        "child",
        "professional",
        "counselor"
    ],
    "wof:name":"Cohan Amy Licsw",
    "wof:placetype":"venue"
},
  "geometry": {"coordinates":[-70.734634,42.105587],"type":"Point"}
}