{
  "type": "Feature",
  "properties": {
    "addr:full":"The Hong Kong Cafe 1238 Mass Ave Cambridge MA 02238",
    "addr:housenumber":"1238",
    "addr:postcode":"02238",
    "addr:street":"Mass Ave",
    "iso:country":"US",
    "sg:address":"The Hong Kong Cafe 1238 Mass Ave",
    "sg:city":"Cambridge",
    "sg:classifiers":[
        {
            "category":"Bars & Pubs",
            "subcategory":"Nightclub",
            "type":"Food & Drink"
        }
    ],
    "sg:postcode":"02238",
    "sg:province":"MA",
    "sg:tags":[
        "nightlife"
    ],
    "wof:name":"Club Fuxx",
    "wof:placetype":"venue"
},
  "geometry": {"coordinates":[-71.116238,42.37265],"type":"Point"}
}