{
  "type": "Feature",
  "properties": {
    "addr:full": "57 Forest St Danvers MA 01923",
    "addr:housenumber": "57",
    "addr:postcode": "01923",
    "addr:street": "Forest St",
    "iso:country": "US",
    "ovtr:label": "Endicott Park, 57 Forest St Danvers MA US",
    "ovtr:similarity": 3.314570903778076,
    "sg:address": "57 Forest St",
    "sg:city": "Danvers",
    "sg:classifiers": [
      {
        "category": "Recreation",
        "type": "Entertainment"
      }
    ],
    "sg:phone": "+1 978 774 6518",
    "sg:postcode": "01923",
    "sg:province": "MA",
    "sg:tags": [
      "parks"
    ],
    "wof:name": "Endicott Park",
    "wof:placetype": "venue"
  },
  "geometry": {"coordinates":[-70.961842,42.574283],"type":"Point"}
}
