{
  "type": "Feature",
  "properties": {
    "iso:country":"US",
    "sg:address":"43 Greystone Rd",
    "sg:city":"Malden",
    "sg:classifiers":[
        {
            "category":"Professional",
            "subcategory":"Art Services",
            "type":"Services"
        }
    ],
    "sg:phone":"+1 781 324 3922",
    "sg:postcode":"02148",
    "sg:province":"MA",
    "sg:tags":[
        "graphic",
        "designer"
    ],
    "wof:name":"Design Co",
    "wof:placetype":"venue"
},
  "geometry": {"coordinates":[-71.076052,42.435521],"type":"Point"}
}