{
  "type": "Feature",
  "properties": {
    "addr:full": "1973 Memorial Dr Chicopee MA 01020",
    "addr:housenumber": "1973",
    "addr:postcode": "01020",
    "addr:street": "Memorial Dr",
    "iso:country": "US",
    "ovtr:label": "Auto-Test World, 1973 Memorial Dr Chicopee MA US",
    "ovtr:similarity": 2.907322883605957,
    "sg:address": "1973 Memorial Dr",
    "sg:city": "Chicopee",
    "sg:classifiers": [
      {
        "category": "Retail",
        "subcategory": "Auto Repair",
        "type": "Services"
      }
    ],
    "sg:phone": "+1 413 493 1771",
    "sg:postcode": "01020",
    "sg:province": "MA",
    "sg:tags": [
      "repairing",
      "automobile",
      "general"
    ],
    "wof:name": "Auto Test World",
    "wof:placetype": "venue"
  },
  "geometry": {"coordinates":[-72.571806,42.212076],"type":"Point"}
}
