{
  "type": "Feature",
  "properties": {
    "addr:full": "765 Revere Beach Pkwy Revere MA 02151",
    "addr:housenumber": "765",
    "addr:postcode": "02151",
    "addr:street": "Revere Beach Pkwy",
    "iso:country": "US",
    "sg:address": "765 Revere Beach Pkwy",
    "sg:city": "Revere",
    "sg:classifiers": [
      {
        "category": "Freight",
        "type": "Transportation"
      }
    ],
    "sg:phone": "+1 781 289 0900",
    "sg:postcode": "02151",
    "sg:province": "MA",
    "sg:website": "www.monfreight.com",
    "wof:name": "Monfreight Inc",
    "wof:placetype": "venue"
  },
  "geometry": {"coordinates":[-71.011858,42.403181],"type":"Point"}
}
