{
  "type": "Feature",
  "properties": {
    "iso:country":"US",
    "sg:address":"910 Providence Hwy",
    "sg:city":"Dedham",
    "sg:classifiers":[
        {
            "category":"Home & Garden",
            "subcategory":"Furniture",
            "type":"Retail Goods"
        }
    ],
    "sg:phone":"+1 781 407 0606",
    "sg:postcode":"02026",
    "sg:province":"MA",
    "wof:name":"Furniture Factory Outlet",
    "wof:placetype":"venue"
},
  "geometry": {"coordinates":[-71.179585,42.233788],"type":"Point"}
}