{
  "type": "Feature",
  "properties": {
    "addr:full": "910 Providence Hwy Dedham MA 02026",
    "addr:housenumber": "910",
    "addr:postcode": "02026",
    "addr:street": "Providence Hwy",
    "iso:country": "US",
    "sg:address": "910 Providence Hwy",
    "sg:city": "Dedham",
    "sg:classifiers": [
      {
        "category": "Home \u0026 Garden",
        "subcategory": "Furniture",
        "type": "Retail Goods"
      }
    ],
    "sg:phone": "+1 781 407 0606",
    "sg:postcode": "02026",
    "sg:province": "MA",
    "wof:name": "Furniture Factory Outlet",
    "wof:placetype": "venue"
  },
  "geometry": {"coordinates":[-71.179585,42.233788],"type":"Point"}
}
