{
  "type": "Feature",
  "properties": {
    "iso:country":"US",
    "sg:address":"90 Desert Brook Rd",
    "sg:city":"Wrentham",
    "sg:classifiers":[
        {
            "category":"Professional",
            "type":"Services"
        }
    ],
    "sg:phone":"+1   ",
    "sg:postcode":"02093",
    "sg:province":"MA",
    "wof:name":"Ipd Latin America Inc",
    "wof:placetype":"venue"
},
  "geometry": {"coordinates":[-71.353086,42.053291],"type":"Point"}
}