{
  "type": "Feature",
  "properties": {
    "addr:full": "1337 Boston Providence Tpke Norwood MA 02062",
    "addr:housenumber": "1337",
    "addr:postcode": "02062",
    "addr:street": "Boston Providence Tpke",
    "iso:country": "US",
    "sg:address": "1337 Boston Providence Tpke",
    "sg:city": "Norwood",
    "sg:classifiers": [
      {
        "category": "Utilities",
        "subcategory": "Mobile Phone",
        "type": "Services"
      },
      {
        "category": "Shopping",
        "subcategory": "Mobile Phones",
        "type": "Retail Goods"
      }
    ],
    "sg:phone": "+1 781 255 5566",
    "sg:postcode": "02062",
    "sg:province": "MA",
    "sg:tags": [
      "supply",
      "communication",
      "telephone",
      "wireless",
      "equipment",
      "cellular"
    ],
    "sg:website": "http://www.sprint.com",
    "wof:name": "Sprint Store",
    "wof:placetype": "venue"
  },
  "geometry": {"coordinates":[-71.186539,42.198448],"type":"Point"}
}
