{
  "type": "Feature",
  "properties": {
    "iso:country":"US",
    "sg:address":"110 South St",
    "sg:city":"Plainville",
    "sg:classifiers":[
        {
            "category":"Retail",
            "subcategory":"Self-service Laundry",
            "type":"Services"
        }
    ],
    "sg:phone":"+1 508 699 3033",
    "sg:postcode":"02762",
    "sg:province":"MA",
    "wof:name":"Plainville Laundry",
    "wof:placetype":"venue"
},
  "geometry": {"coordinates":[-71.33556900000001,42.003989],"type":"Point"}
}