{
  "type": "Feature",
  "properties": {
    "iso:country":"US",
    "sg:address":"1 W Hill Rd",
    "sg:city":"Westborough",
    "sg:classifiers":[
        {
            "category":"Government",
            "subcategory":"Office",
            "type":"Public Place"
        }
    ],
    "sg:phone":"+1 508 792 7270",
    "sg:postcode":"01534",
    "sg:province":"MA",
    "sg:tags":[
        "state"
    ],
    "wof:name":"Fisheries & Game Div",
    "wof:placetype":"venue"
},
  "geometry": {"coordinates":[-71.60878599999999,42.113267],"type":"Point"}
}