{
  "type": "Feature",
  "properties": {
    "iso:country":"US",
    "sg:address":"365 Essex St",
    "sg:city":"Saugus",
    "sg:classifiers":[
        {
            "category":"Retail",
            "subcategory":"Veterinary Services",
            "type":"Services"
        }
    ],
    "sg:phone":"+1 781 233 0313",
    "sg:postcode":"01906",
    "sg:province":"MA",
    "sg:tags":[
        "veterinarian",
        "specialty"
    ],
    "wof:name":"Carol D Duca",
    "wof:placetype":"venue"
},
  "geometry": {"coordinates":[-71.030342,42.458562],"type":"Point"}
}