{
  "type": "Feature",
  "properties": {
    "iso:country":"US",
    "sg:address":"75 Saint Alphonsus St",
    "sg:city":"Boston",
    "sg:classifiers":[
        {
            "category":"Professional",
            "subcategory":"Management & Consulting",
            "type":"Services"
        }
    ],
    "sg:phone":"+1   ",
    "sg:postcode":"02120",
    "sg:province":"MA",
    "wof:name":"Custom Fitness Per Training",
    "wof:placetype":"venue"
},
  "geometry": {"coordinates":[-71.101315,42.333166],"type":"Point"}
}