{
  "type": "Feature",
  "properties": {
    "addr:full": "306 Central St Saugus MA 01906",
    "addr:housenumber": "306",
    "addr:postcode": "01906",
    "addr:street": "Central St",
    "iso:country": "US",
    "ovtr:label": "Center Pet Care \u0026 Grooming, 306 Central St Saugus MA US",
    "ovtr:similarity": 1.8597170114517212,
    "sg:address": "306 Central St",
    "sg:city": "Saugus",
    "sg:classifiers": [
      {
        "category": "Retail",
        "subcategory": "Animal Services",
        "type": "Services"
      }
    ],
    "sg:phone": "+1 781 233 0070",
    "sg:postcode": "01906",
    "sg:province": "MA",
    "sg:tags": [
      "pet",
      "grooming",
      "washing"
    ],
    "wof:name": "Center Pet Care \u0026 Grooming",
    "wof:placetype": "venue"
  },
  "geometry": {"coordinates":[-71.009824,42.464898],"type":"Point"}
}
