{
  "type": "Feature",
  "properties": {
    "addr:full": "246 Pleasant St Worcester MA 01609",
    "addr:housenumber": "246",
    "addr:postcode": "01609",
    "addr:street": "Pleasant St",
    "iso:country": "US",
    "sg:address": "246 Pleasant St",
    "sg:city": "Worcester",
    "sg:classifiers": [
      {
        "category": "Organizations",
        "subcategory": "Religious Organization",
        "type": "Services"
      }
    ],
    "sg:phone": "+1 508 798 9709",
    "sg:postcode": "01609",
    "sg:province": "MA",
    "sg:tags": [
      "church"
    ],
    "wof:name": "Apostolic Church",
    "wof:placetype": "venue"
  },
  "geometry": {"coordinates":[-71.809754,42.263932],"type":"Point"}
}
