{
  "type": "Feature",
  "properties": {
    "addr:full": "4 Grasshopper Ln Oxford MA 01566",
    "addr:housenumber": "4",
    "addr:postcode": "01566",
    "addr:street": "Grasshopper Ln",
    "iso:country": "US",
    "sg:address": "4 Grasshopper Ln",
    "sg:city": "Oxford",
    "sg:classifiers": [
      {
        "category": "Professional",
        "subcategory": "Detective \u0026 Security Services",
        "type": "Services"
      }
    ],
    "sg:phone": "+1   ",
    "sg:postcode": "01566",
    "sg:province": "MA",
    "sg:tags": [
      "system"
    ],
    "wof:name": "Wade Brenner Inc",
    "wof:placetype": "venue"
  },
  "geometry": {"coordinates":[-72.099117,42.115214],"type":"Point"}
}
