{
  "type": "Feature",
  "properties": {
    "iso:country":"US",
    "sg:address":"4 Grasshopper Ln",
    "sg:city":"Oxford",
    "sg:classifiers":[
        {
            "category":"Professional",
            "subcategory":"Detective & Security Services",
            "type":"Services"
        }
    ],
    "sg:phone":"+1   ",
    "sg:postcode":"01566",
    "sg:province":"MA",
    "sg:tags":[
        "system"
    ],
    "wof:name":"Wade Brenner Inc",
    "wof:placetype":"venue"
},
  "geometry": {"coordinates":[-72.09911700000001,42.115214],"type":"Point"}
}