{
  "type": "Feature",
  "properties": {
    "addr:full":"411 Main St Wakefield MA 01880",
    "addr:housenumber":"411",
    "addr:postcode":"01880",
    "addr:street":"Main St",
    "iso:country":"US",
    "sg:address":"411 Main St",
    "sg:city":"Wakefield",
    "sg:classifiers":[
        {
            "category":"Restaurant",
            "type":"Food & Drink"
        }
    ],
    "sg:phone":"+1 781 246 4848",
    "sg:postcode":"01880",
    "sg:province":"MA",
    "wof:name":"Center House Of Pizza",
    "wof:placetype":"venue"
},
  "geometry": {"coordinates":[-71.070448,42.503468],"type":"Point"}
}