{
  "type": "Feature",
  "properties": {
    "iso:country":"US",
    "sg:address":"332 John L Dietsch Blvd",
    "sg:city":"North Attleboro",
    "sg:classifiers":[
        {
            "category":"Manufacturing",
            "subcategory":"Metals",
            "type":"Manufacturing & Wholesale Goods"
        }
    ],
    "sg:phone":"+1 508 695 1007",
    "sg:postcode":"02763",
    "sg:province":"MA",
    "sg:tags":[
        "fabricator",
        "sheet"
    ],
    "sg:website":"www.metfabeng.com",
    "wof:name":"Metfab Engineering",
    "wof:placetype":"venue"
},
  "geometry": {"coordinates":[-71.30058,41.984398],"type":"Point"}
}