{
  "type": "Feature",
  "properties": {
    "addr:full":"243 Mystic Ave Medford MA 02155",
    "addr:housenumber":"243",
    "addr:postcode":"02155",
    "addr:street":"Mystic Ave",
    "iso:country":"US",
    "sg:address":"243 Mystic Ave",
    "sg:city":"Medford",
    "sg:classifiers":[
        {
            "category":"Retail",
            "subcategory":"Car Wash",
            "type":"Services"
        }
    ],
    "sg:phone":"+1   ",
    "sg:postcode":"02155",
    "sg:province":"MA",
    "sg:tags":[
        "carwash"
    ],
    "wof:name":"Bostonian Care Care Inc",
    "wof:placetype":"venue"
},
  "geometry": {"coordinates":[-71.102959,42.407136],"type":"Point"}
}