{
  "type": "Feature",
  "properties": {
    "iso:country":"US",
    "sg:address":"309 Taunton Ave",
    "sg:city":"Seekonk",
    "sg:classifiers":[
        {
            "category":"Banks & Credit Unions",
            "subcategory":"Investment Brokerage",
            "type":"Services"
        }
    ],
    "sg:phone":"+1 508 336 2276",
    "sg:postcode":"02771",
    "sg:province":"MA",
    "sg:tags":[
        "stock",
        "bond"
    ],
    "wof:name":"Chartwell Investments",
    "wof:placetype":"venue"
},
  "geometry": {"coordinates":[-71.337346,41.824793],"type":"Point"}
}