{
  "type": "Feature",
  "properties": {
    "iso:country":"US",
    "sg:address":"93 Vernon St",
    "sg:city":"Greenfield",
    "sg:classifiers":[
        {
            "category":"Retail",
            "subcategory":"Auto Repair",
            "type":"Services"
        }
    ],
    "sg:phone":"+1 413 773 3392",
    "sg:postcode":"01301",
    "sg:province":"MA",
    "sg:tags":[
        "repairing",
        "automobile",
        "general"
    ],
    "wof:name":"Cowan's Garage",
    "wof:placetype":"venue"
},
  "geometry": {"coordinates":[-72.60123299999999,42.606172],"type":"Point"}
}