{
  "type": "Feature",
  "properties": {
    "addr:full": "93 Vernon St Greenfield MA 01301",
    "addr:housenumber": "93",
    "addr:postcode": "01301",
    "addr:street": "Vernon St",
    "iso:country": "US",
    "sg:address": "93 Vernon St",
    "sg:city": "Greenfield",
    "sg:classifiers": [
      {
        "category": "Retail",
        "subcategory": "Auto Repair",
        "type": "Services"
      }
    ],
    "sg:phone": "+1 413 773 3392",
    "sg:postcode": "01301",
    "sg:province": "MA",
    "sg:tags": [
      "repairing",
      "automobile",
      "general"
    ],
    "wof:name": "Cowan's Garage",
    "wof:placetype": "venue"
  },
  "geometry": {"coordinates":[-72.601233,42.606172],"type":"Point"}
}
