{
  "type": "Feature",
  "properties": {
    "addr:full":"55 Grace St Malden MA 02148",
    "addr:housenumber":"55",
    "addr:postcode":"02148",
    "addr:street":"Grace St",
    "iso:country":"US",
    "sg:address":"55 Grace St",
    "sg:city":"Malden",
    "sg:classifiers":[
        {
            "category":"Professional",
            "subcategory":"Art Services",
            "type":"Services"
        }
    ],
    "sg:phone":"+1 781 322 4571",
    "sg:postcode":"02148",
    "sg:province":"MA",
    "sg:tags":[
        "photographer"
    ],
    "wof:name":"Applied Creative Arts",
    "wof:placetype":"venue"
},
  "geometry": {"coordinates":[-71.07829099999999,42.433568],"type":"Point"}
}