{
  "type": "Feature",
  "properties": {
    "addr:full":"21 Lakeview Rd Wayland MA 01778",
    "addr:housenumber":"21",
    "addr:postcode":"01778",
    "addr:street":"Lakeview Rd",
    "iso:country":"US",
    "sg:address":"21 Lakeview Rd",
    "sg:city":"Wayland",
    "sg:classifiers":[
        {
            "category":"Building & Trades",
            "subcategory":"Electrical",
            "type":"Services"
        }
    ],
    "sg:phone":"+1 508 653 5023",
    "sg:postcode":"01778",
    "sg:province":"MA",
    "sg:tags":[
        "electrician"
    ],
    "wof:name":"Curtis Electric Company",
    "wof:placetype":"venue"
},
  "geometry": {"coordinates":[-71.36490999999999,42.329456],"type":"Point"}
}