{
  "type": "Feature",
  "properties": {
    "iso:country":"US",
    "sg:address":"9 Audubon Rd",
    "sg:city":"Wakefield",
    "sg:classifiers":[
        {
            "category":"Banks & Credit Unions",
            "subcategory":"Bank",
            "type":"Services"
        }
    ],
    "sg:phone":"+1 781 246 4008",
    "sg:postcode":"01880",
    "sg:province":"MA",
    "sg:tags":[
        "loan",
        "real estate"
    ],
    "wof:name":"Fieldstone Mortgage",
    "wof:placetype":"venue"
},
  "geometry": {"coordinates":[-71.041214,42.513073],"type":"Point"}
}