{
  "type": "Feature",
  "properties": {
    "addr:full": "9 Audubon Rd Wakefield MA 01880",
    "addr:housenumber": "9",
    "addr:postcode": "01880",
    "addr:street": "Audubon Rd",
    "iso:country": "US",
    "sg:address": "9 Audubon Rd",
    "sg:city": "Wakefield",
    "sg:classifiers": [
      {
        "category": "Banks \u0026 Credit Unions",
        "subcategory": "Bank",
        "type": "Services"
      }
    ],
    "sg:phone": "+1 781 246 4008",
    "sg:postcode": "01880",
    "sg:province": "MA",
    "sg:tags": [
      "loan",
      "real estate"
    ],
    "wof:name": "Fieldstone Mortgage",
    "wof:placetype": "venue"
  },
  "geometry": {"coordinates":[-71.041214,42.513073],"type":"Point"}
}
