{
  "type": "Feature",
  "properties": {
    "iso:country":"US",
    "sg:address":"15 Stockwell Drive",
    "sg:city":"Avon",
    "sg:classifiers":[
        {
            "category":"Shopping",
            "type":"Retail Goods"
        }
    ],
    "sg:phone":"+1 508 586 6438",
    "sg:postcode":"02322",
    "sg:province":"MA",
    "sg:website":"www.christmastreeshops.com/frame...",
    "wof:name":"Christmas Tree Shops",
    "wof:placetype":"venue"
},
  "geometry": {"coordinates":[-71.06719200000001,42.127414],"type":"Point"}
}