{
  "type": "Feature",
  "properties": {
    "addr:full": "23 Central St Wellesley MA 02482",
    "addr:housenumber": "23",
    "addr:postcode": "02482",
    "addr:street": "Central St",
    "iso:country": "US",
    "sg:address": "23 Central St",
    "sg:city": "Wellesley",
    "sg:classifiers": [
      {
        "category": "Shopping",
        "subcategory": "Books",
        "type": "Retail Goods"
      }
    ],
    "sg:phone": "+1 781 239 1360",
    "sg:postcode": "02482",
    "sg:province": "MA",
    "sg:tags": [
      "dealer"
    ],
    "wof:name": "Blue Moon Bookshop",
    "wof:placetype": "venue"
  },
  "geometry": {"coordinates":[-71.296883,42.296145],"type":"Point"}
}
