{
  "type": "Feature",
  "properties": {
    "addr:full": "1170 Walnut St Newton MA 02461",
    "addr:housenumber": "1170",
    "addr:postcode": "02461",
    "addr:street": "Walnut St",
    "iso:country": "US",
    "sg:address": "1170 Walnut St",
    "sg:city": "Newton",
    "sg:classifiers": [
      {
        "category": "Shopping",
        "subcategory": "Computers \u0026 Home Electronics",
        "type": "Retail Goods"
      }
    ],
    "sg:phone": "+1 617 527 4000",
    "sg:postcode": "02461",
    "sg:province": "MA",
    "sg:tags": [
      "software"
    ],
    "wof:name": "Cheshire Software",
    "wof:placetype": "venue"
  },
  "geometry": {"coordinates":[-71.205888,42.32155],"type":"Point"}
}
