{
  "type": "Feature",
  "properties": {
    "addr:full": "201 Crapo St New Bedford MA 02744",
    "addr:housenumber": "201",
    "addr:postcode": "02744",
    "addr:street": "Crapo St",
    "iso:country": "US",
    "sg:address": "201 Crapo St",
    "sg:city": "New Bedford",
    "sg:classifiers": [
      {
        "category": "Professional",
        "type": "Services"
      }
    ],
    "sg:phone": "+1 508 991 5727",
    "sg:postcode": "02744",
    "sg:province": "MA",
    "sg:tags": [
      "establishment"
    ],
    "wof:name": "DVR Assoc",
    "wof:placetype": "venue"
  },
  "geometry": {"coordinates":[-70.92627,41.615511],"type":"Point"}
}
