{
  "type": "Feature",
  "properties": {
    "iso:country":"US",
    "sg:address":"1975 Main St",
    "sg:city":"Brockton",
    "sg:classifiers":[
        {
            "category":"Education",
            "subcategory":"Dance Studio",
            "type":"Public Place"
        }
    ],
    "sg:phone":"+1 508 588 1274",
    "sg:postcode":"02301",
    "sg:province":"MA",
    "sg:tags":[
        "instruction",
        "dancing"
    ],
    "wof:name":"Susan's School Of Dance",
    "wof:placetype":"venue"
},
  "geometry": {"coordinates":[-71.010909,42.048633],"type":"Point"}
}