{
  "type": "Feature",
  "properties": {
    "addr:full": "11 Scarsdale Rd Newton MA 02460",
    "addr:housenumber": "11",
    "addr:postcode": "02460",
    "addr:street": "Scarsdale Rd",
    "iso:country": "US",
    "sg:address": "11 Scarsdale Rd",
    "sg:city": "Newton",
    "sg:classifiers": [
      {
        "category": "Professional",
        "subcategory": "Management \u0026 Consulting",
        "type": "Services"
      }
    ],
    "sg:phone": "+1   ",
    "sg:postcode": "02460",
    "sg:province": "MA",
    "wof:name": "Bottomline Mktg Consulting",
    "wof:placetype": "venue"
  },
  "geometry": {"coordinates":[-71.209457,42.342045],"type":"Point"}
}
