{
  "type": "Feature",
  "properties": {
    "addr:full": "95 Haverhill Rd Amesbury MA 01913",
    "addr:housenumber": "95",
    "addr:postcode": "01913",
    "addr:street": "Haverhill Rd",
    "iso:country": "US",
    "sg:address": "95 Haverhill Rd",
    "sg:city": "Amesbury",
    "sg:classifiers": [
      {
        "category": "Wholesale",
        "subcategory": "Groceries",
        "type": "Manufacturing \u0026 Wholesale Goods"
      }
    ],
    "sg:phone": "+1 978 688 1844",
    "sg:postcode": "01913",
    "sg:province": "MA",
    "sg:tags": [
      "food",
      "product"
    ],
    "sg:website": "www.shaheenbros.com",
    "wof:name": "Shaheen Brothers Inc",
    "wof:placetype": "venue"
  },
  "geometry": {"coordinates":[-70.955861,42.843312],"type":"Point"}
}
