{
  "type": "Feature",
  "properties": {
    "addr:full": "14 Harding Ln Harwich MA 02645",
    "addr:housenumber": "14",
    "addr:postcode": "02645",
    "addr:street": "Harding Ln",
    "iso:country": "US",
    "sg:address": "14 Harding Ln",
    "sg:city": "Harwich",
    "sg:classifiers": [
      {
        "category": "Health Services",
        "subcategory": "Health Practitioner",
        "type": "Services"
      }
    ],
    "sg:phone": "+1 508 237 1634",
    "sg:postcode": "02645",
    "sg:province": "MA",
    "sg:tags": [
      "acupuncture",
      "medicine",
      "alternative"
    ],
    "wof:name": "Patz Acupuncture",
    "wof:placetype": "venue"
  },
  "geometry": {"coordinates":[-70.022236,41.720761],"type":"Point"}
}
