{
  "type": "Feature",
  "properties": {
    "iso:country":"US",
    "sg:address":"14 Harding Ln",
    "sg:city":"Harwich",
    "sg:classifiers":[
        {
            "category":"Health Services",
            "subcategory":"Health Practitioner",
            "type":"Services"
        }
    ],
    "sg:phone":"+1 508 237 1634",
    "sg:postcode":"02645",
    "sg:province":"MA",
    "sg:tags":[
        "acupuncture",
        "medicine",
        "alternative"
    ],
    "wof:name":"Patz Acupuncture",
    "wof:placetype":"venue"
},
  "geometry": {"coordinates":[-70.02223600000001,41.720761],"type":"Point"}
}