{
  "type": "Feature",
  "properties": {
    "addr:full": "200 Great Rd Bedford MA 01730",
    "addr:housenumber": "200",
    "addr:postcode": "01730",
    "addr:street": "Great Rd",
    "iso:country": "US",
    "sg:address": "200 Great Rd",
    "sg:city": "Bedford",
    "sg:classifiers": [
      {
        "category": "Professional",
        "type": "Services"
      }
    ],
    "sg:phone": "+1 781 275 1890",
    "sg:postcode": "01730",
    "sg:province": "MA",
    "sg:tags": [
      "establishment"
    ],
    "wof:name": "Atypica",
    "wof:placetype": "venue"
  },
  "geometry": {"coordinates":[-71.272528,42.489573],"type":"Point"}
}
