{
  "type": "Feature",
  "properties": {
    "addr:full": "24 Hampshire St Methuen MA 01844",
    "addr:housenumber": "24",
    "addr:postcode": "01844",
    "addr:street": "Hampshire St",
    "iso:country": "US",
    "ovtr:label": "Perfect Nails, 24 Hampshire St Methuen MA US",
    "ovtr:similarity": 3.102544069290161,
    "sg:address": "24 Hampshire St",
    "sg:city": "Methuen",
    "sg:classifiers": [
      {
        "category": "Personal",
        "subcategory": "Beauty Salon",
        "type": "Services"
      }
    ],
    "sg:phone": "+1 978 683 5477",
    "sg:postcode": "01844",
    "sg:province": "MA",
    "sg:tags": [
      "shop"
    ],
    "wof:name": "Perfect Nails",
    "wof:placetype": "venue"
  },
  "geometry": {"coordinates":[-71.189437,42.728022],"type":"Point"}
}
