{
  "type": "Feature",
  "properties": {
    "iso:country":"US",
    "sg:address":"24 Hampshire St",
    "sg:city":"Methuen",
    "sg:classifiers":[
        {
            "category":"Personal",
            "subcategory":"Beauty Salon",
            "type":"Services"
        }
    ],
    "sg:phone":"+1 978 683 5477",
    "sg:postcode":"01844",
    "sg:province":"MA",
    "sg:tags":[
        "shop"
    ],
    "wof:name":"Perfect Nails",
    "wof:placetype":"venue"
},
  "geometry": {"coordinates":[-71.189437,42.728022],"type":"Point"}
}