{
  "type": "Feature",
  "properties": {
    "addr:full": "15 Harvard Ave Hyde Park MA 02136",
    "addr:housenumber": "15",
    "addr:postcode": "02136",
    "addr:street": "Harvard Ave",
    "iso:country": "US",
    "sg:address": "15 Harvard Ave",
    "sg:city": "Hyde Park",
    "sg:classifiers": [
      {
        "category": "Restaurant",
        "type": "Food \u0026 Drink"
      }
    ],
    "sg:phone": "+1 617 364 2772",
    "sg:postcode": "02136",
    "sg:province": "MA",
    "wof:name": "Las Vegas Seafood Restaurant",
    "wof:placetype": "venue"
  },
  "geometry": {"coordinates":[-71.12243,42.257391],"type":"Point"}
}
