{
  "type": "Feature",
  "properties": {
    "iso:country":"US",
    "sg:address":"15 Harvard Ave",
    "sg:city":"Hyde Park",
    "sg:classifiers":[
        {
            "category":"Restaurant",
            "type":"Food & Drink"
        }
    ],
    "sg:phone":"+1 617 364 2772",
    "sg:postcode":"02136",
    "sg:province":"MA",
    "wof:name":"Las Vegas Seafood Restaurant",
    "wof:placetype":"venue"
},
  "geometry": {"coordinates":[-71.12242999999999,42.257391],"type":"Point"}
}