{
  "type": "Feature",
  "properties": {
    "iso:country":"US",
    "sg:address":"394 Washington St",
    "sg:city":"Franklin",
    "sg:classifiers":[
        {
            "category":"Professional",
            "type":"Services"
        }
    ],
    "sg:phone":"+1   ",
    "sg:postcode":"02038",
    "sg:province":"MA",
    "wof:name":"C Pizzelli & Sons Inc",
    "wof:placetype":"venue"
},
  "geometry": {"coordinates":[-71.41592900000001,42.059075],"type":"Point"}
}