{
  "type": "Feature",
  "properties": {
    "addr:full": "987 Worcester St Natick MA 01760",
    "addr:housenumber": "987",
    "addr:postcode": "01760",
    "addr:street": "Worcester St",
    "iso:country": "US",
    "sg:address": "987 Worcester St",
    "sg:city": "Natick",
    "sg:classifiers": [
      {
        "category": "Building \u0026 Trades",
        "subcategory": "Cleaning \u0026 Sanitation",
        "type": "Services"
      }
    ],
    "sg:phone": "+1 508 647 9952",
    "sg:postcode": "01760",
    "sg:province": "MA",
    "sg:tags": [
      "fireplace",
      "chimney"
    ],
    "wof:name": "American Chimney Pros",
    "wof:placetype": "venue"
  },
  "geometry": {"coordinates":[-71.364273,42.299517],"type":"Point"}
}
