{
  "type": "Feature",
  "properties": {
    "addr:full":"224 Harvard Street Brookline MA 02446",
    "addr:housenumber":"224",
    "addr:postcode":"02446",
    "addr:street":"Harvard Street",
    "iso:country":"US",
    "sg:address":"224 Harvard Street",
    "sg:city":"Brookline",
    "sg:classifiers":[
        {
            "category":"Personal",
            "subcategory":"Hair Removal",
            "type":"Services"
        },
        {
            "category":"Personal",
            "subcategory":"Skin Care",
            "type":"Services"
        }
    ],
    "sg:phone":"+1 617 733 2306",
    "sg:postcode":"02446",
    "sg:province":"MA",
    "wof:name":"European Skin Care",
    "wof:placetype":"venue"
},
  "geometry": {"coordinates":[-71.121173,42.340703],"type":"Point"}
}