{
  "type": "Feature",
  "properties": {
    "iso:country":"US",
    "sg:address":"1586 Ware St",
    "sg:city":"Palmer",
    "sg:classifiers":[
        {
            "category":"Building & Trades",
            "subcategory":"Construction",
            "type":"Services"
        }
    ],
    "sg:phone":"+1   ",
    "sg:postcode":"01069",
    "sg:province":"MA",
    "sg:tags":[
        "house"
    ],
    "wof:name":"Joseph Libera",
    "wof:placetype":"venue"
},
  "geometry": {"coordinates":[-72.296892,42.225617],"type":"Point"}
}