{
  "type": "Feature",
  "properties": {
    "addr:full":"19 Pierce St Rochester MA 02770",
    "addr:housenumber":"19",
    "addr:postcode":"02770",
    "addr:street":"Pierce St",
    "iso:country":"US",
    "sg:address":"19 Pierce St",
    "sg:city":"Rochester",
    "sg:classifiers":[
        {
            "category":"Real Estate",
            "subcategory":"Real Estate Operator",
            "type":"Services"
        }
    ],
    "sg:phone":"+1   ",
    "sg:postcode":"02770",
    "sg:province":"MA",
    "sg:tags":[
        "property",
        "lessor"
    ],
    "wof:name":"Talbair",
    "wof:placetype":"venue"
},
  "geometry": {"coordinates":[-70.78734799999999,41.76309],"type":"Point"}
}