{
  "type": "Feature",
  "properties": {
    "iso:country":"US",
    "sg:address":"26 Everett St",
    "sg:city":"Cambridge",
    "sg:classifiers":[
        {
            "category":"Health Services",
            "subcategory":"Health Practitioner",
            "type":"Services"
        }
    ],
    "sg:phone":"+1 617 441 2100",
    "sg:postcode":"02138",
    "sg:province":"MA",
    "sg:tags":[
        "psychologist"
    ],
    "wof:name":"Randi Kaufman",
    "wof:placetype":"venue"
},
  "geometry": {"coordinates":[-71.11898100000001,42.379865],"type":"Point"}
}