{
  "type": "Feature",
  "properties": {
    "addr:full":"215 Summer St Haverhill MA 01830",
    "addr:housenumber":"215",
    "addr:postcode":"01830",
    "addr:street":"Summer St",
    "iso:country":"US",
    "sg:address":"215 Summer St",
    "sg:city":"Haverhill",
    "sg:classifiers":[
        {
            "category":"Health Services",
            "subcategory":"Podiatrist",
            "type":"Services"
        }
    ],
    "sg:phone":"+1 978 373 2460",
    "sg:postcode":"01830",
    "sg:province":"MA",
    "wof:name":"Daniel Callahan Jr DPM",
    "wof:placetype":"venue"
},
  "geometry": {"coordinates":[-71.067447,42.776126],"type":"Point"}
}