{
  "type": "Feature",
  "properties": {
    "iso:country":"US",
    "sg:address":"165 Tremont St",
    "sg:city":"Melrose",
    "sg:classifiers":[
        {
            "category":"Wholesale",
            "subcategory":"Electrical",
            "type":"Manufacturing & Wholesale Goods"
        }
    ],
    "sg:phone":"+1 781 662 8640",
    "sg:postcode":"02176",
    "sg:province":"MA",
    "sg:tags":[
        "comm",
        "system",
        "microwave"
    ],
    "wof:name":"J P Parece",
    "wof:placetype":"venue"
},
  "geometry": {"coordinates":[-71.06929100000001,42.463831],"type":"Point"}
}