{
  "type": "Feature",
  "properties": {
    "addr:full": "21 Walnut St Assonet MA 02702",
    "addr:housenumber": "21",
    "addr:postcode": "02702",
    "addr:street": "Walnut St",
    "iso:country": "US",
    "sg:address": "21 Walnut St",
    "sg:city": "Assonet",
    "sg:classifiers": [
      {
        "category": "Retail",
        "subcategory": "Auto Repair",
        "type": "Services"
      }
    ],
    "sg:phone": "+1   ",
    "sg:postcode": "02702",
    "sg:province": "MA",
    "sg:tags": [
      "general"
    ],
    "wof:name": "Vics Auto Sales",
    "wof:placetype": "venue"
  },
  "geometry": {"coordinates":[-71.05878,41.79798],"type":"Point"}
}
