{
  "type": "Feature",
  "properties": {
    "addr:full": "177 W 8th St South Boston MA 02127",
    "addr:housenumber": "177",
    "addr:postcode": "02127",
    "addr:street": "W 8Th St",
    "iso:country": "US",
    "sg:address": "177 W 8th St",
    "sg:city": "South Boston",
    "sg:classifiers": [
      {
        "category": "Building \u0026 Trades",
        "subcategory": "Locksmith",
        "type": "Services"
      }
    ],
    "sg:phone": "+1 617 752 9202",
    "sg:postcode": "02127",
    "sg:province": "MA",
    "sg:tags": [
      "key"
    ],
    "wof:name": "ABC Emergecny Locksmith Service On W 8T",
    "wof:placetype": "venue"
  },
  "geometry": {"coordinates":[-71.052597,42.333854],"type":"Point"}
}
