{
  "type": "Feature",
  "properties": {
    "iso:country":"US",
    "sg:address":"50 Great Rd",
    "sg:city":"Bedford",
    "sg:classifiers":[
        {
            "category":"Personal",
            "subcategory":"Beauty Salon",
            "type":"Services"
        }
    ],
    "sg:phone":"+1 781 275 0141",
    "sg:postcode":"01730",
    "sg:province":"MA",
    "sg:tags":[
        "shop"
    ],
    "wof:name":"Hair Extrodinaire",
    "wof:placetype":"venue"
},
  "geometry": {"coordinates":[-71.28186100000001,42.493043],"type":"Point"}
}