{
  "type": "Feature",
  "properties": {
    "iso:country":"US",
    "sg:address":"92 Harvard Ave",
    "sg:city":"Allston",
    "sg:classifiers":[
        {
            "category":"Restaurant",
            "type":"Food & Drink"
        }
    ],
    "sg:phone":"+1 617 562 8888",
    "sg:postcode":"02134",
    "sg:province":"MA",
    "wof:name":"Tokyo City Restaurant",
    "wof:placetype":"venue"
},
  "geometry": {"coordinates":[-71.13205000000001,42.353153],"type":"Point"}
}