{
  "type": "Feature",
  "properties": {
    "addr:full": "158 Prospect St Waltham MA 02453",
    "addr:housenumber": "158",
    "addr:postcode": "02453",
    "addr:street": "Prospect St",
    "iso:country": "US",
    "sg:address": "158 Prospect St",
    "sg:city": "Waltham",
    "sg:classifiers": [
      {
        "category": "Building \u0026 Trades",
        "subcategory": "Construction",
        "type": "Services"
      }
    ],
    "sg:phone": "+1 781 642 7290",
    "sg:postcode": "02453",
    "sg:province": "MA",
    "sg:tags": [
      "contractor"
    ],
    "wof:name": "Northeast Take One Inc",
    "wof:placetype": "venue"
  },
  "geometry": {"coordinates":[-71.24639,42.371385],"type":"Point"}
}
