{
  "type": "Feature",
  "properties": {
    "iso:country":"US",
    "sg:address":"1571 High St",
    "sg:city":"Westwood",
    "sg:classifiers":[
        {
            "category":"Professional",
            "subcategory":"Computer Services",
            "type":"Services"
        }
    ],
    "sg:phone":"+1 781 255 7056",
    "sg:postcode":"02090",
    "sg:province":"MA",
    "sg:tags":[
        "consultant",
        "designer"
    ],
    "wof:name":"Intel Americas",
    "wof:placetype":"venue"
},
  "geometry": {"coordinates":[-71.243301,42.20376],"type":"Point"}
}