{
  "type": "Feature",
  "properties": {
    "iso:country":"US",
    "sg:address":"424 Crowell Rd",
    "sg:city":"North Chatham",
    "sg:classifiers":[
        {
            "category":"Shopping",
            "subcategory":"Clothing, Apparel, & Fashions",
            "type":"Retail Goods"
        }
    ],
    "sg:phone":"+1   ",
    "sg:postcode":"02650",
    "sg:province":"MA",
    "wof:name":"Sea Shell Monogram",
    "wof:placetype":"venue"
},
  "geometry": {"coordinates":[-69.969983,41.695015],"type":"Point"}
}