{
  "type": "Feature",
  "properties": {
    "addr:full": "11 Teddy Rd Worcester MA 01603",
    "addr:housenumber": "11",
    "addr:postcode": "01603",
    "addr:street": "Teddy Rd",
    "iso:country": "US",
    "sg:address": "11 Teddy Rd",
    "sg:city": "Worcester",
    "sg:classifiers": [
      {
        "category": "Building \u0026 Trades",
        "subcategory": "Cleaning \u0026 Sanitation",
        "type": "Services"
      }
    ],
    "sg:phone": "+1 508 756 5554",
    "sg:postcode": "01603",
    "sg:province": "MA",
    "sg:tags": [
      "ventilating",
      "system",
      "maintenance"
    ],
    "wof:name": "Done-Rite Duct Cleaning Servic",
    "wof:placetype": "venue"
  },
  "geometry": {"coordinates":[-71.851534,42.244862],"type":"Point"}
}
