{
  "type": "Feature",
  "properties": {
    "addr:full":"PO Box 315 Stoughton MA 02072",
    "addr:housenumber":"po",
    "addr:postcode":"02072",
    "addr:street":"Box 315",
    "iso:country":"US",
    "sg:address":"PO Box 315",
    "sg:city":"Stoughton",
    "sg:classifiers":[
        {
            "category":"Arts & Performance",
            "subcategory":"Arts Center",
            "type":"Entertainment"
        }
    ],
    "sg:phone":"+1 781 344 4145",
    "sg:postcode":"02072",
    "sg:province":"MA",
    "sg:tags":[
        "performing"
    ],
    "wof:name":"Arthur Murray Dance Center",
    "wof:placetype":"venue"
},
  "geometry": {"coordinates":[-71.107399,42.127602],"type":"Point"}
}