{
  "type": "Feature",
  "properties": {
    "addr:full": "691 E 4th St South Boston MA 02127",
    "addr:housenumber": "691",
    "addr:postcode": "02127",
    "addr:street": "E 4Th St",
    "iso:country": "US",
    "sg:address": "691 E 4th St",
    "sg:city": "South Boston",
    "sg:classifiers": [
      {
        "category": "Building \u0026 Trades",
        "subcategory": "Construction",
        "type": "Services"
      }
    ],
    "sg:phone": "+1 617 268 8820",
    "sg:postcode": "02127",
    "sg:province": "MA",
    "sg:tags": [
      "roofing",
      "contractor"
    ],
    "wof:name": "Fernald Roofing Co",
    "wof:placetype": "venue"
  },
  "geometry": {"coordinates":[-71.036626,42.334671],"type":"Point"}
}
