{
  "type": "Feature",
  "properties": {
    "iso:country":"US",
    "sg:address":"210 Ferry St",
    "sg:city":"Everett",
    "sg:classifiers":[
        {
            "category":"Animal Shelter",
            "type":"Public Place"
        }
    ],
    "sg:phone":"+1 781 391 6019",
    "sg:postcode":"02149",
    "sg:province":"MA",
    "sg:website":"www.pawsafe.org/",
    "wof:name":"Pawsafe Animal Rescue",
    "wof:placetype":"venue"
},
  "geometry": {"coordinates":[-71.045643,42.411228],"type":"Point"}
}