{
  "type": "Feature",
  "properties": {
    "addr:full": "40 Emerson St Medford MA 02155",
    "addr:housenumber": "40",
    "addr:postcode": "02155",
    "addr:street": "Emerson St",
    "iso:country": "US",
    "sg:address": "40 Emerson St",
    "sg:city": "Medford",
    "sg:classifiers": [
      {
        "category": "Building \u0026 Trades",
        "subcategory": "Locksmith",
        "type": "Services"
      }
    ],
    "sg:phone": "+1 617 615 3383",
    "sg:postcode": "02155",
    "sg:province": "MA",
    "sg:tags": [
      "key"
    ],
    "wof:name": "123 Locksmith",
    "wof:placetype": "venue"
  },
  "geometry": {"coordinates":[-71.111562,42.415552],"type":"Point"}
}
