{
  "type": "Feature",
  "properties": {
    "addr:full": "15 Central St Andover MA 01810",
    "addr:housenumber": "15",
    "addr:postcode": "01810",
    "addr:street": "Central St",
    "iso:country": "US",
    "sg:address": "15 Central St",
    "sg:city": "Andover",
    "sg:classifiers": [
      {
        "category": "Health Services",
        "subcategory": "Doctor",
        "type": "Services"
      },
      {
        "category": "Health Services",
        "subcategory": "Dentist",
        "type": "Services"
      }
    ],
    "sg:phone": "+1 978 470 0330",
    "sg:postcode": "01810",
    "sg:province": "MA",
    "sg:tags": [
      "dentists-oral",
      "physician",
      "maxillofacial",
      "surgeons",
      "surgery",
      "oral"
    ],
    "wof:name": "Bay State Oms Associates Pc",
    "wof:placetype": "venue"
  },
  "geometry": {"coordinates":[-71.141482,42.65568],"type":"Point"}
}
