{
  "type": "Feature",
  "properties": {
    "iso:country":"US",
    "sg:address":"31 W Fountain St",
    "sg:city":"Milford",
    "sg:classifiers":[
        {
            "category":"Organizations",
            "subcategory":"Membership Organization",
            "type":"Services"
        }
    ],
    "sg:phone":"+1 508 634 2356",
    "sg:postcode":"01757",
    "sg:province":"MA",
    "wof:name":"Family Network",
    "wof:placetype":"venue"
},
  "geometry": {"coordinates":[-71.53483799999999,42.150352],"type":"Point"}
}