{
  "type": "Feature",
  "properties": {
    "addr:full": "12 Bicknell St Dorchester MA 02121",
    "addr:housenumber": "12",
    "addr:postcode": "02121",
    "addr:street": "Bicknell St",
    "iso:country": "US",
    "sg:address": "12 Bicknell St",
    "sg:city": "Dorchester",
    "sg:classifiers": [
      {
        "category": "Social Services",
        "subcategory": "Child Care",
        "type": "Services"
      }
    ],
    "sg:phone": "+1 617 282 0620",
    "sg:postcode": "02121",
    "sg:province": "MA",
    "sg:tags": [
      "day"
    ],
    "wof:name": "Haitian Multi-Svc Ctr Day Nursry",
    "wof:placetype": "venue"
  },
  "geometry": {"coordinates":[-71.082199,42.2966],"type":"Point"}
}
