{
  "type": "Feature",
  "properties": {
    "iso:country":"US",
    "sg:address":"50 Derby St",
    "sg:city":"Hingham",
    "sg:classifiers":[
        {
            "category":"Professional",
            "type":"Services"
        }
    ],
    "sg:phone":"+1 781 740 8290",
    "sg:postcode":"02043",
    "sg:province":"MA",
    "sg:tags":[
        "establishment"
    ],
    "wof:name":"JPK Enterprises Inc",
    "wof:placetype":"venue"
},
  "geometry": {"coordinates":[-70.90423800000001,42.180412],"type":"Point"}
}