{
  "type": "Feature",
  "properties": {
    "iso:country":"US",
    "sg:address":"2 Bartlett Rd",
    "sg:city":"Nantucket",
    "sg:classifiers":[
        {
            "category":"Manufacturing",
            "subcategory":"Printing",
            "type":"Manufacturing & Wholesale Goods"
        }
    ],
    "sg:phone":"+1 508 228 1051",
    "sg:postcode":"02554",
    "sg:province":"MA",
    "sg:tags":[
        "commercial"
    ],
    "wof:name":"Poets Corner Press Inc",
    "wof:placetype":"venue"
},
  "geometry": {"coordinates":[-70.09990500000001,41.26853],"type":"Point"}
}