{
  "type": "Feature",
  "properties": {
    "addr:full": "2 Bartlett Rd Nantucket MA 02554",
    "addr:housenumber": "2",
    "addr:postcode": "02554",
    "addr:street": "Bartlett Rd",
    "iso:country": "US",
    "sg:address": "2 Bartlett Rd",
    "sg:city": "Nantucket",
    "sg:classifiers": [
      {
        "category": "Manufacturing",
        "subcategory": "Printing",
        "type": "Manufacturing \u0026 Wholesale Goods"
      }
    ],
    "sg:phone": "+1 508 228 1051",
    "sg:postcode": "02554",
    "sg:province": "MA",
    "sg:tags": [
      "commercial"
    ],
    "wof:name": "Poets Corner Press Inc",
    "wof:placetype": "venue"
  },
  "geometry": {"coordinates":[-70.099905,41.26853],"type":"Point"}
}
