{
  "type": "Feature",
  "properties": {
    "addr:full": "768 Washington St Hanover MA 02339",
    "addr:housenumber": "768",
    "addr:postcode": "02339",
    "addr:street": "Washington St",
    "iso:country": "US",
    "sg:address": "768 Washington St",
    "sg:city": "Hanover",
    "sg:classifiers": [
      {
        "category": "Building \u0026 Trades",
        "subcategory": "Construction",
        "type": "Services"
      }
    ],
    "sg:phone": "+1 866 231 1020",
    "sg:postcode": "02339",
    "sg:province": "MA",
    "sg:tags": [
      "siding",
      "contractor"
    ],
    "sg:website": "http://local.ingenio.com/Listings/Details.aspx?NUM=a%3a10068200%3a13%3a4859924%3a14%3a0%3a7",
    "wof:name": "North Star Bailey Vinyl Siding",
    "wof:placetype": "venue"
  },
  "geometry": {"coordinates":[-70.829153,42.126808],"type":"Point"}
}
