{
  "type": "Feature",
  "properties": {
    "iso:country":"US",
    "sg:address":"768 Washington St",
    "sg:city":"Hanover",
    "sg:classifiers":[
        {
            "category":"Building & Trades",
            "subcategory":"Construction",
            "type":"Services"
        }
    ],
    "sg:phone":"+1 866 231 1020",
    "sg:postcode":"02339",
    "sg:province":"MA",
    "sg:tags":[
        "siding",
        "contractor"
    ],
    "sg:website":"http://local.ingenio.com/Listings/Details.aspx?NUM=a%3a10068200%3a13%3a4859924%3a14%3a0%3a7",
    "wof:name":"North Star Bailey Vinyl Siding",
    "wof:placetype":"venue"
},
  "geometry": {"coordinates":[-70.82915300000001,42.126808],"type":"Point"}
}