{
  "type": "Feature",
  "properties": {
    "addr:full":"8 Winter St Boston MA 02108",
    "addr:housenumber":"8",
    "addr:postcode":"02108",
    "addr:street":"Winter St",
    "iso:country":"US",
    "sg:address":"8 Winter St",
    "sg:city":"Boston",
    "sg:classifiers":[
        {
            "category":"Professional",
            "subcategory":"Employment Agencies",
            "type":"Services"
        }
    ],
    "sg:phone":"+1 617 426 8884",
    "sg:postcode":"02108",
    "sg:province":"MA",
    "sg:tags":[
        "consultant",
        "search",
        "executive"
    ],
    "wof:name":"Open Systems Technologies Inc",
    "wof:placetype":"venue"
},
  "geometry": {"coordinates":[-71.060821,42.35551],"type":"Point"}
}