{
  "type": "Feature",
  "properties": {
    "iso:country":"US",
    "sg:address":"31 W Dudley Rd",
    "sg:city":"Dudley",
    "sg:classifiers":[
        {
            "category":"Building & Trades",
            "subcategory":"Cleaning & Sanitation",
            "type":"Services"
        }
    ],
    "sg:phone":"+1 508 764 3044",
    "sg:postcode":"01571",
    "sg:province":"MA",
    "sg:tags":[
        "cleaner",
        "upholstery"
    ],
    "wof:name":"Squeaky Clean Cleaning Service",
    "wof:placetype":"venue"
},
  "geometry": {"coordinates":[-71.979141,42.050011],"type":"Point"}
}