{
  "type": "Feature",
  "properties": {
    "iso:country":"US",
    "sg:address":"25 Lovell St",
    "sg:city":"Mendon",
    "sg:classifiers":[
        {
            "category":"Farming",
            "subcategory":"Farm",
            "type":"Manufacturing & Wholesale Goods"
        },
        {
            "category":"Manufacturing",
            "subcategory":"Lumber",
            "type":"Manufacturing & Wholesale Goods"
        }
    ],
    "sg:phone":"+1 508 478 8733",
    "sg:postcode":"01756",
    "sg:province":"MA",
    "sg:tags":[
        "operation",
        "timber",
        "tract"
    ],
    "wof:name":"Vandervalk Tree Farm",
    "wof:placetype":"venue"
},
  "geometry": {"coordinates":[-71.565264,42.082547],"type":"Point"}
}