{
  "type": "Feature",
  "properties": {
    "addr:full": "20 Cathedral Dr Attleboro MA 02703",
    "addr:housenumber": "20",
    "addr:postcode": "02703",
    "addr:street": "Cathedral Dr",
    "iso:country": "US",
    "sg:address": "20 Cathedral Dr",
    "sg:city": "Attleboro",
    "sg:classifiers": [
      {
        "category": "Sports \u0026 Exercise",
        "subcategory": "Gym",
        "type": "Entertainment"
      }
    ],
    "sg:phone": "+1 508 695 1133",
    "sg:postcode": "02703",
    "sg:province": "MA",
    "sg:tags": [
      "club",
      "health",
      "studio",
      "gymnasium"
    ],
    "wof:name": "Ladies Workout Express",
    "wof:placetype": "venue"
  },
  "geometry": {"coordinates":[-71.30387,41.908798],"type":"Point"}
}
