{
  "type": "Feature",
  "properties": {
    "iso:country":"US",
    "sg:address":"9 Brookdale Cir",
    "sg:city":"Billerica",
    "sg:classifiers":[
        {
            "category":"Real Estate",
            "subcategory":"Real Estate Services",
            "type":"Services"
        },
        {
            "category":"Real Estate",
            "subcategory":"Real Estate Agent",
            "type":"Services"
        }
    ],
    "sg:phone":"+1 978 667 2501",
    "sg:postcode":"01821",
    "sg:province":"MA",
    "sg:tags":[
        "buyer",
        "broker"
    ],
    "wof:name":"Joan Diorio Realtor",
    "wof:placetype":"venue"
},
  "geometry": {"coordinates":[-71.242121,42.555145],"type":"Point"}
}