{
  "type": "Feature",
  "properties": {
    "addr:full":"53 Shaw Rd Petersham MA 01366",
    "addr:housenumber":"53",
    "addr:postcode":"01366",
    "addr:street":"Shaw Rd",
    "iso:country":"US",
    "sg:address":"53 Shaw Rd",
    "sg:city":"Petersham",
    "sg:classifiers":[
        {
            "category":"Manufacturing",
            "subcategory":"Signs",
            "type":"Manufacturing & Wholesale Goods"
        }
    ],
    "sg:phone":"+1 978 724 7446",
    "sg:postcode":"01366",
    "sg:province":"MA",
    "sg:website":"www.armstrongsign.com",
    "wof:name":"Armstrong Sign & Design",
    "wof:placetype":"venue"
},
  "geometry": {"coordinates":[-72.167136,42.49236],"type":"Point"}
}