{
  "type": "Feature",
  "properties": {
    "addr:full":"36 Spring St Waltham MA 02451",
    "addr:housenumber":"36",
    "addr:postcode":"02451",
    "addr:street":"Spring St",
    "iso:country":"US",
    "sg:address":"36 Spring St",
    "sg:city":"Waltham",
    "sg:classifiers":[
        {
            "category":"Shopping",
            "type":"Retail Goods"
        }
    ],
    "sg:phone":"+1 781 642 7800",
    "sg:postcode":"02451",
    "sg:province":"MA",
    "sg:tags":[
        "pet",
        "shop"
    ],
    "wof:name":"Barker & Meow Pet Sitting",
    "wof:placetype":"venue"
},
  "geometry": {"coordinates":[-71.238792,42.378029],"type":"Point"}
}