{
  "type": "Feature",
  "properties": {
    "iso:country":"US",
    "sg:address":"510 Parker St",
    "sg:city":"Springfield",
    "sg:classifiers":[
        {
            "category":"Autos & Motor Vehicles",
            "subcategory":"Auto Supplies",
            "type":"Retail Goods"
        }
    ],
    "sg:phone":"+1 413 783 0256",
    "sg:postcode":"01129",
    "sg:province":"MA",
    "sg:tags":[
        "automobile",
        "parts"
    ],
    "wof:name":"Autozone",
    "wof:placetype":"venue"
},
  "geometry": {"coordinates":[-72.495981,42.13979],"type":"Point"}
}