{
  "type": "Feature",
  "properties": {
    "addr:full": "46 Crestview Dr East Sandwich MA 02537",
    "addr:housenumber": "46",
    "addr:postcode": "02537",
    "addr:street": "Crestview Dr",
    "iso:country": "US",
    "sg:address": "46 Crestview Dr",
    "sg:city": "East Sandwich",
    "sg:classifiers": [
      {
        "category": "Travel",
        "subcategory": "Travel Agent",
        "type": "Entertainment"
      }
    ],
    "sg:phone": "+1 508 398 8775",
    "sg:postcode": "02537",
    "sg:province": "MA",
    "sg:tags": [
      "tours",
      "promoter"
    ],
    "wof:name": "Camelot Tours",
    "wof:placetype": "venue"
  },
  "geometry": {"coordinates":[-70.451506,41.734468],"type":"Point"}
}
