{
  "type": "Feature",
  "properties": {
    "iso:country":"US",
    "sg:address":"46 Crestview Dr",
    "sg:city":"East Sandwich",
    "sg:classifiers":[
        {
            "category":"Travel",
            "subcategory":"Travel Agent",
            "type":"Entertainment"
        }
    ],
    "sg:phone":"+1 508 398 8775",
    "sg:postcode":"02537",
    "sg:province":"MA",
    "sg:tags":[
        "tours",
        "promoter"
    ],
    "wof:name":"Camelot Tours",
    "wof:placetype":"venue"
},
  "geometry": {"coordinates":[-70.45150599999999,41.734468],"type":"Point"}
}