{
  "type": "Feature",
  "properties": {
    "addr:full":"841 Kempton St New Bedford MA 02740",
    "addr:housenumber":"841",
    "addr:postcode":"02740",
    "addr:street":"Kempton St",
    "iso:country":"US",
    "sg:address":"841 Kempton St",
    "sg:city":"New Bedford",
    "sg:classifiers":[
        {
            "category":"Organizations",
            "subcategory":"Religious Organization",
            "type":"Services"
        }
    ],
    "sg:phone":"+1 508 999 1039",
    "sg:postcode":"02740",
    "sg:province":"MA",
    "sg:tags":[
        "church"
    ],
    "wof:name":"Christian Revival Temple",
    "wof:placetype":"venue"
},
  "geometry": {"coordinates":[-70.947778,41.635642],"type":"Point"}
}