{
  "type": "Feature",
  "properties": {
    "iso:country":"US",
    "sg:address":"128 Main St",
    "sg:city":"Monson",
    "sg:classifiers":[
        {
            "category":"Wholesale",
            "subcategory":"Machinery & Supplies",
            "type":"Manufacturing & Wholesale Goods"
        }
    ],
    "sg:phone":"+1 413 267 0590",
    "sg:postcode":"01057",
    "sg:province":"MA",
    "wof:name":"Sohre Turbo Machinery Inc",
    "wof:placetype":"venue"
},
  "geometry": {"coordinates":[-72.315594,42.099489],"type":"Point"}
}