{
  "type": "Feature",
  "properties": {
    "addr:full": "128 Main St Monson MA 01057",
    "addr:housenumber": "128",
    "addr:postcode": "01057",
    "addr:street": "Main St",
    "iso:country": "US",
    "sg:address": "128 Main St",
    "sg:city": "Monson",
    "sg:classifiers": [
      {
        "category": "Wholesale",
        "subcategory": "Machinery \u0026 Supplies",
        "type": "Manufacturing \u0026 Wholesale Goods"
      }
    ],
    "sg:phone": "+1 413 267 0590",
    "sg:postcode": "01057",
    "sg:province": "MA",
    "wof:name": "Sohre Turbo Machinery Inc",
    "wof:placetype": "venue"
  },
  "geometry": {"coordinates":[-72.315594,42.099489],"type":"Point"}
}
