{
  "type": "Feature",
  "properties": {
    "iso:country":"US",
    "sg:address":"15 Bonney Ln",
    "sg:city":"Norwood",
    "sg:classifiers":[
        {
            "category":"Professional",
            "subcategory":"Computer Services",
            "type":"Services"
        }
    ],
    "sg:phone":"+1 781 255 5590",
    "sg:postcode":"02062",
    "sg:province":"MA",
    "sg:tags":[
        "internet"
    ],
    "sg:website":"www.accuserve.net",
    "wof:name":"Accuserve Internet Inc",
    "wof:placetype":"venue"
},
  "geometry": {"coordinates":[-71.217602,42.190826],"type":"Point"}
}