{
  "type": "Feature",
  "properties": {
    "addr:full":"10 Ice Pond Dr Rowley MA 01969",
    "addr:housenumber":"10",
    "addr:postcode":"01969",
    "addr:street":"Ice Pond Dr",
    "iso:country":"US",
    "sg:address":"10 Ice Pond Dr",
    "sg:city":"Rowley",
    "sg:classifiers":[
        {
            "category":"Professional",
            "subcategory":"Art Services",
            "type":"Services"
        }
    ],
    "sg:phone":"+1 978 948 2355",
    "sg:postcode":"01969",
    "sg:province":"MA",
    "sg:tags":[
        "commercial",
        "design"
    ],
    "sg:website":"www.curleydesign.com",
    "wof:name":"Carrie Curley Design",
    "wof:placetype":"venue"
},
  "geometry": {"coordinates":[-70.935929,42.700409],"type":"Point"}
}