{
  "type": "Feature",
  "properties": {
    "iso:country":"US",
    "sg:address":"6 Day Ave",
    "sg:city":"Danvers",
    "sg:classifiers":[
        {
            "category":"Building & Trades",
            "subcategory":"Construction",
            "type":"Services"
        }
    ],
    "sg:phone":"+1 978 304 0077",
    "sg:postcode":"01923",
    "sg:province":"MA",
    "sg:tags":[
        "wallcoverings-installation",
        "wallpaper",
        "painting",
        "contractor"
    ],
    "wof:name":"Paul Canova Painting, Inc.",
    "wof:placetype":"venue"
},
  "geometry": {"coordinates":[-70.939995,42.581519],"type":"Point"}
}