{
  "type": "Feature",
  "properties": {
    "addr:full":"54 Prospect St Acton MA 01720",
    "addr:housenumber":"54",
    "addr:postcode":"01720",
    "addr:street":"Prospect St",
    "iso:country":"US",
    "sg:address":"54 Prospect St",
    "sg:city":"Acton",
    "sg:classifiers":[
        {
            "category":"Utilities",
            "subcategory":"Telephone",
            "type":"Services"
        }
    ],
    "sg:phone":"+1   ",
    "sg:postcode":"01720",
    "sg:province":"MA",
    "sg:tags":[
        "communications"
    ],
    "wof:name":"Patrick Rennich",
    "wof:placetype":"venue"
},
  "geometry": {"coordinates":[-71.456329,42.467552],"type":"Point"}
}