{
  "type": "Feature",
  "properties": {
    "iso:country":"US",
    "sg:address":"317 Haverhill St",
    "sg:city":"Rowley",
    "sg:classifiers":[
        {
            "category":"Shopping",
            "subcategory":"Pets & Pet Supplies",
            "type":"Retail Goods"
        }
    ],
    "sg:phone":"+1 978 948 3647",
    "sg:postcode":"01969",
    "sg:province":"MA",
    "sg:tags":[
        "store"
    ],
    "sg:website":"www.ciaobowwow.com",
    "wof:name":"Ciao Bow Wow",
    "wof:placetype":"venue"
},
  "geometry": {"coordinates":[-70.907017,42.705774],"type":"Point"}
}