{
  "type": "Feature",
  "properties": {
    "addr:full":"9 Foster St Wakefield MA 01880",
    "addr:housenumber":"9",
    "addr:postcode":"01880",
    "addr:street":"Foster St",
    "iso:country":"US",
    "sg:address":"9 Foster St",
    "sg:city":"Wakefield",
    "sg:classifiers":[
        {
            "category":"Health Services",
            "subcategory":"Health Practitioner",
            "type":"Services"
        }
    ],
    "sg:phone":"+1 781 245 5162",
    "sg:postcode":"01880",
    "sg:province":"MA",
    "sg:tags":[
        "psychologist"
    ],
    "wof:name":"Susan Rashba",
    "wof:placetype":"venue"
},
  "geometry": {"coordinates":[-71.070999,42.502499],"type":"Point"}
}