{
  "type": "Feature",
  "properties": {
    "addr:full":"433 Centre St Newton MA 02458",
    "addr:housenumber":"433",
    "addr:postcode":"02458",
    "addr:street":"Centre St",
    "iso:country":"US",
    "sg:address":"433 Centre St",
    "sg:city":"Newton",
    "sg:classifiers":[
        {
            "category":"Shopping",
            "subcategory":"Florist",
            "type":"Retail Goods"
        }
    ],
    "sg:phone":"+1 617 527 8024",
    "sg:postcode":"02458",
    "sg:province":"MA",
    "sg:website":"www.gleasonsflowers.net",
    "wof:name":"Gleason's Flowers",
    "wof:placetype":"venue"
},
  "geometry": {"coordinates":[-71.186365,42.355171],"type":"Point"}
}