{
  "type": "Feature",
  "properties": {
    "addr:full": "522 Massachusetts Ave Cambridge MA 02139",
    "addr:housenumber": "522",
    "addr:postcode": "02139",
    "addr:street": "Massachusetts Ave",
    "iso:country": "US",
    "sg:address": "522 Massachusetts Ave",
    "sg:city": "Cambridge",
    "sg:classifiers": [
      {
        "category": "Banks \u0026 Credit Unions",
        "subcategory": "Bank",
        "type": "Services"
      }
    ],
    "sg:phone": "+1 617 497 4218",
    "sg:postcode": "02139",
    "sg:province": "MA",
    "wof:name": "Western Union Cambridge",
    "wof:placetype": "venue"
  },
  "geometry": {"coordinates":[-71.10185,42.364281],"type":"Point"}
}
