{
  "type": "Feature",
  "properties": {
    "iso:country":"US",
    "sg:address":"522 Massachusetts Ave",
    "sg:city":"Cambridge",
    "sg:classifiers":[
        {
            "category":"Banks & Credit Unions",
            "subcategory":"Bank",
            "type":"Services"
        }
    ],
    "sg:phone":"+1 617 497 4218",
    "sg:postcode":"02139",
    "sg:province":"MA",
    "wof:name":"Western Union Cambridge",
    "wof:placetype":"venue"
},
  "geometry": {"coordinates":[-71.10185,42.364281],"type":"Point"}
}