{
  "type": "Feature",
  "properties": {
    "iso:country":"US",
    "sg:address":"1540 Bedford St",
    "sg:city":"Abington",
    "sg:classifiers":[
        {
            "category":"Banks & Credit Unions",
            "subcategory":"Bank",
            "type":"Services"
        }
    ],
    "sg:phone":"+1 781 871 7569",
    "sg:postcode":"02351",
    "sg:province":"MA",
    "sg:tags":[
        "loan",
        "real estate"
    ],
    "wof:name":"Approved Mortgages",
    "wof:placetype":"venue"
},
  "geometry": {"coordinates":[-70.95314,42.142584],"type":"Point"}
}