{
  "type": "Feature",
  "properties": {
    "addr:full": "240 King St Springfield MA 01109",
    "addr:housenumber": "240",
    "addr:postcode": "01109",
    "addr:street": "King St",
    "iso:country": "US",
    "sg:address": "240 King St",
    "sg:city": "Springfield",
    "sg:classifiers": [
      {
        "category": "Personal",
        "subcategory": "Barber",
        "type": "Services"
      }
    ],
    "sg:phone": "+1 413 739 1190",
    "sg:postcode": "01109",
    "sg:province": "MA",
    "wof:name": "Polite's Barber \u0026 Beauty Shop",
    "wof:placetype": "venue"
  },
  "geometry": {"coordinates":[-72.561333,42.105656],"type":"Point"}
}
