{
  "type": "Feature",
  "properties": {
    "addr:full":"1872 Acushnet Ave New Bedford MA 02746",
    "addr:housenumber":"1872",
    "addr:postcode":"02746",
    "addr:street":"Acushnet Ave",
    "iso:country":"US",
    "sg:address":"1872 Acushnet Ave",
    "sg:city":"New Bedford",
    "sg:classifiers":[
        {
            "category":"Education",
            "subcategory":"Junior College",
            "type":"Public Place"
        }
    ],
    "sg:phone":"+1 508 995 8711",
    "sg:postcode":"02746",
    "sg:province":"MA",
    "sg:tags":[
        "technical",
        "institute"
    ],
    "wof:name":"Rob Roy Academy",
    "wof:placetype":"venue"
},
  "geometry": {"coordinates":[-70.925421,41.671728],"type":"Point"}
}