{
  "type": "Feature",
  "properties": {
    "iso:country":"US",
    "sg:address":"198 Central St",
    "sg:city":"Norwood",
    "sg:classifiers":[
        {
            "category":"Bars & Pubs",
            "type":"Food & Drink"
        }
    ],
    "sg:phone":"+1 781 551 8165",
    "sg:postcode":"02062",
    "sg:province":"MA",
    "wof:name":"Lou & Deb's",
    "wof:placetype":"venue"
},
  "geometry": {"coordinates":[-71.19843899999999,42.195927],"type":"Point"}
}