{
  "type": "Feature",
  "properties": {
    "iso:country":"US",
    "sg:address":"167 Milk St",
    "sg:city":"Boston",
    "sg:classifiers":[
        {
            "category":"Arts & Performance",
            "subcategory":"Theater",
            "type":"Entertainment"
        }
    ],
    "sg:phone":"+1 781 982 6099",
    "sg:postcode":"02109",
    "sg:province":"MA",
    "sg:tags":[
        "entertainer"
    ],
    "wof:name":"Elvis The Boston",
    "wof:placetype":"venue"
},
  "geometry": {"coordinates":[-71.053583,42.358191],"type":"Point"}
}