{
  "type": "Feature",
  "properties": {
    "addr:full":"291 Quincy Ave Quincy MA 02169",
    "addr:housenumber":"291",
    "addr:postcode":"02169",
    "addr:street":"Quincy Ave",
    "iso:country":"US",
    "sg:address":"291 Quincy Ave",
    "sg:city":"Quincy",
    "sg:classifiers":[
        {
            "category":"Food & Beverages",
            "subcategory":"Groceries & Convenience Stores",
            "type":"Retail Goods"
        }
    ],
    "sg:phone":"+1 617 328 8427",
    "sg:postcode":"02169",
    "sg:province":"MA",
    "wof:name":"Dairy Mart",
    "wof:placetype":"venue"
},
  "geometry": {"coordinates":[-70.986233,42.239974],"type":"Point"}
}