{
  "type": "Feature",
  "properties": {
    "iso:country":"US",
    "sg:address":"16 Tech Cir",
    "sg:city":"Natick",
    "sg:classifiers":[
        {
            "category":"Shopping",
            "subcategory":"Computers & Home Electronics",
            "type":"Retail Goods"
        }
    ],
    "sg:phone":"+1 508 655 8801",
    "sg:postcode":"01760",
    "sg:province":"MA",
    "sg:tags":[
        "software"
    ],
    "wof:name":"Transdecision",
    "wof:placetype":"venue"
},
  "geometry": {"coordinates":[-71.336313,42.314798],"type":"Point"}
}