{
  "type": "Feature",
  "properties": {
    "addr:full": "16 Tech Cir Natick MA 01760",
    "addr:housenumber": "16",
    "addr:postcode": "01760",
    "addr:street": "Tech Cir",
    "iso:country": "US",
    "sg:address": "16 Tech Cir",
    "sg:city": "Natick",
    "sg:classifiers": [
      {
        "category": "Shopping",
        "subcategory": "Computers \u0026 Home Electronics",
        "type": "Retail Goods"
      }
    ],
    "sg:phone": "+1 508 655 8801",
    "sg:postcode": "01760",
    "sg:province": "MA",
    "sg:tags": [
      "software"
    ],
    "wof:name": "Transdecision",
    "wof:placetype": "venue"
  },
  "geometry": {"coordinates":[-71.336313,42.314798],"type":"Point"}
}
