{
  "type": "Feature",
  "properties": {
    "iso:country":"US",
    "sg:address":"321 Southbridge St",
    "sg:city":"Auburn",
    "sg:classifiers":[
        {
            "category":"Banks & Credit Unions",
            "subcategory":"Bank",
            "type":"Services"
        }
    ],
    "sg:phone":"+1 508 832 5798",
    "sg:postcode":"01501",
    "sg:province":"MA",
    "sg:tags":[
        "cashing",
        "check"
    ],
    "wof:name":"Graham's Check Cashing Atm",
    "wof:placetype":"venue"
},
  "geometry": {"coordinates":[-71.833659,42.206341],"type":"Point"}
}