{
  "type": "Feature",
  "properties": {
    "addr:full": "8 Southwick St Feeding Hills MA 01030",
    "addr:housenumber": "8",
    "addr:postcode": "01030",
    "addr:street": "Southwick St",
    "iso:country": "US",
    "sg:address": "8 Southwick St",
    "sg:city": "Feeding Hills",
    "sg:classifiers": [
      {
        "category": "Shopping",
        "type": "Retail Goods"
      }
    ],
    "sg:phone": "+1 413 786 1000",
    "sg:postcode": "01030",
    "sg:province": "MA",
    "sg:tags": [
      "aquarium"
    ],
    "sg:website": "www.aqua-dreams.com",
    "wof:name": "Aqua Dreams",
    "wof:placetype": "venue"
  },
  "geometry": {"coordinates":[-72.682276,42.066812],"type":"Point"}
}
