{
  "type": "Feature",
  "properties": {
    "addr:full":"9 Acton Rd Chelmsford MA 01824",
    "addr:housenumber":"9",
    "addr:postcode":"01824",
    "addr:street":"Acton Rd",
    "iso:country":"US",
    "sg:address":"9 Acton Rd",
    "sg:city":"Chelmsford",
    "sg:classifiers":[
        {
            "category":"Health Services",
            "subcategory":"Optometrist",
            "type":"Services"
        }
    ],
    "sg:phone":"+1 978 256 8501",
    "sg:postcode":"01824",
    "sg:province":"MA",
    "wof:name":"Henry Boroyan OD",
    "wof:placetype":"venue"
},
  "geometry": {"coordinates":[-71.352097,42.596001],"type":"Point"}
}