{
  "type": "Feature",
  "properties": {
    "addr:full": "120 Berkley St Taunton MA 02780",
    "addr:housenumber": "120",
    "addr:postcode": "02780",
    "addr:street": "Berkley St",
    "iso:country": "US",
    "sg:address": "120 Berkley St",
    "sg:city": "Taunton",
    "sg:classifiers": [
      {
        "category": "Home \u0026 Garden",
        "subcategory": "Building Materials",
        "type": "Retail Goods"
      }
    ],
    "sg:phone": "+1 508 823 0771",
    "sg:postcode": "02780",
    "sg:province": "MA",
    "sg:tags": [
      "mixed",
      "concrete"
    ],
    "wof:name": "Mc Cabe Sand \u0026 Gravel Co",
    "wof:placetype": "venue"
  },
  "geometry": {"coordinates":[-71.087966,41.88273],"type":"Point"}
}
