{
  "type": "Feature",
  "properties": {
    "addr:full": "24 Merrimack St Lowell MA 01852",
    "addr:housenumber": "24",
    "addr:postcode": "01852",
    "addr:street": "Merrimack St",
    "iso:country": "US",
    "sg:address": "24 Merrimack St",
    "sg:city": "Lowell",
    "sg:classifiers": [
      {
        "category": "Personal",
        "subcategory": "Beauty Salon",
        "type": "Services"
      }
    ],
    "sg:phone": "+1 978 453 3042",
    "sg:postcode": "01852",
    "sg:province": "MA",
    "sg:tags": [
      "shop"
    ],
    "wof:name": "ME Keon Beauty Shoppe",
    "wof:placetype": "venue"
  },
  "geometry": {"coordinates":[-71.308045,42.645445],"type":"Point"}
}
