{
  "type": "Feature",
  "properties": {
    "iso:country":"US",
    "sg:address":"870 State St",
    "sg:city":"Springfield",
    "sg:classifiers":[
        {
            "category":"Building & Trades",
            "subcategory":"Plumbing",
            "type":"Services"
        }
    ],
    "sg:phone":"+1 413 781 2789",
    "sg:postcode":"01109",
    "sg:province":"MA",
    "sg:tags":[
        "plumbing",
        "contractor"
    ],
    "wof:name":"Northeast Plumbing & Heating",
    "wof:placetype":"venue"
},
  "geometry": {"coordinates":[-72.561227,42.112463],"type":"Point"}
}