{
  "type": "Feature",
  "properties": {
    "addr:full":"45 Bedford St Lexington MA 02420",
    "addr:housenumber":"45",
    "addr:postcode":"02420",
    "addr:street":"Bedford St",
    "iso:country":"US",
    "sg:address":"45 Bedford St",
    "sg:city":"Lexington",
    "sg:classifiers":[
        {
            "category":"Building & Trades",
            "subcategory":"Locksmith",
            "type":"Services"
        }
    ],
    "sg:phone":"+1 781 301 6050",
    "sg:postcode":"02420",
    "sg:province":"MA",
    "sg:tags":[
        "key"
    ],
    "wof:name":"Bedford St Locksmith",
    "wof:placetype":"venue"
},
  "geometry": {"coordinates":[-71.232258,42.45289],"type":"Point"}
}