{
  "type": "Feature",
  "properties": {
    "addr:full":"135 Beaver St Waltham MA 02452",
    "addr:housenumber":"135",
    "addr:postcode":"02452",
    "addr:street":"Beaver St",
    "iso:country":"US",
    "sg:address":"135 Beaver St",
    "sg:city":"Waltham",
    "sg:classifiers":[
        {
            "category":"Professional",
            "subcategory":"Lawyer & Legal Services",
            "type":"Services"
        }
    ],
    "sg:phone":"+1 781 736 9600",
    "sg:postcode":"02452",
    "sg:province":"MA",
    "sg:tags":[
        "attorney"
    ],
    "wof:name":"Luke Stanton",
    "wof:placetype":"venue"
},
  "geometry": {"coordinates":[-71.20813699999999,42.38304],"type":"Point"}
}