{
  "type": "Feature",
  "properties": {
    "iso:country":"US",
    "sg:address":"165 Bearses Way",
    "sg:city":"Hyannis",
    "sg:classifiers":[
        {
            "category":"Education",
            "subcategory":"School",
            "type":"Public Place"
        }
    ],
    "sg:phone":"+1 508 790 6485",
    "sg:postcode":"02601",
    "sg:province":"MA",
    "sg:tags":[
        "high",
        "middle",
        "elementary"
    ],
    "wof:name":"Barnstable Town of",
    "wof:placetype":"venue"
},
  "geometry": {"coordinates":[-70.292666,41.655871],"type":"Point"}
}