{
  "type": "Feature",
  "properties": {
    "addr:full": "140 Gulf Rd Belchertown MA 01007",
    "addr:housenumber": "140",
    "addr:postcode": "01007",
    "addr:street": "Gulf Rd",
    "iso:country": "US",
    "sg:address": "140 Gulf Rd",
    "sg:city": "Belchertown",
    "sg:classifiers": [
      {
        "category": "Organizations",
        "subcategory": "Religious Organization",
        "type": "Services"
      }
    ],
    "sg:phone": "+1 413 253 9439",
    "sg:postcode": "01007",
    "sg:province": "MA",
    "sg:tags": [
      "church"
    ],
    "wof:name": "Nature Church",
    "wof:placetype": "venue"
  },
  "geometry": {"coordinates":[-72.444136,42.339149],"type":"Point"}
}
