{
  "type": "Feature",
  "properties": {
    "addr:full": "43 Roxbury St Roxbury MA 02119",
    "addr:housenumber": "43",
    "addr:postcode": "02119",
    "addr:street": "Roxbury St",
    "iso:country": "US",
    "sg:address": "43 Roxbury St",
    "sg:city": "Roxbury",
    "sg:classifiers": [
      {
        "category": "Building \u0026 Trades",
        "subcategory": "Locksmith",
        "type": "Services"
      }
    ],
    "sg:phone": "+1 617 303 2763",
    "sg:postcode": "02119",
    "sg:province": "MA",
    "sg:tags": [
      "key"
    ],
    "wof:name": "Economy Locksmith",
    "wof:placetype": "venue"
  },
  "geometry": {"coordinates":[-71.085146,42.329693],"type":"Point"}
}
