{
  "type": "Feature",
  "properties": {
    "addr:full": "9 Shelburne Ave Billerica MA 01821",
    "addr:housenumber": "9",
    "addr:postcode": "01821",
    "addr:street": "Shelburne Ave",
    "iso:country": "US",
    "sg:address": "9 Shelburne Ave",
    "sg:city": "Billerica",
    "sg:classifiers": [
      {
        "category": "Building \u0026 Trades",
        "subcategory": "Construction",
        "type": "Services"
      }
    ],
    "sg:phone": "+1 978 663 8445",
    "sg:postcode": "01821",
    "sg:province": "MA",
    "sg:tags": [
      "carpentry",
      "contractor"
    ],
    "wof:name": "Chaffee Carpentry",
    "wof:placetype": "venue"
  },
  "geometry": {"coordinates":[-71.207874,42.54373],"type":"Point"}
}
