{
  "type": "Feature",
  "properties": {
    "iso:country":"US",
    "sg:address":"59 Mercury St",
    "sg:city":"Weymouth",
    "sg:classifiers":[
        {
            "category":"Building & Trades",
            "subcategory":"Construction",
            "type":"Services"
        }
    ],
    "sg:phone":"+1   ",
    "sg:postcode":"02188",
    "sg:province":"MA",
    "sg:tags":[
        "hanging",
        "contractor"
    ],
    "wof:name":"Tolly Painting",
    "wof:placetype":"venue"
},
  "geometry": {"coordinates":[-70.96850999999999,42.185382],"type":"Point"}
}