{
  "type": "Feature",
  "properties": {
    "iso:country":"US",
    "sg:address":"254 Dorchester St",
    "sg:city":"Boston",
    "sg:classifiers":[
        {
            "category":"Shopping",
            "subcategory":"Department Store",
            "type":"Retail Goods"
        },
        {
            "category":"Shopping",
            "type":"Retail Goods"
        },
        {
            "category":"Shopping",
            "subcategory":"Discount & Variety Stores",
            "type":"Retail Goods"
        }
    ],
    "sg:phone":"+1 617 765 0444",
    "sg:postcode":"02127",
    "sg:province":"MA",
    "sg:tags":[
        "merchandising"
    ],
    "wof:name":"Quality Bargain Store",
    "wof:placetype":"venue"
},
  "geometry": {"coordinates":[-71.051586,42.332517],"type":"Point"}
}