{
  "type": "Feature",
  "properties": {
    "addr:full": "66 Sweetwater Ave Bedford MA 01730",
    "addr:housenumber": "66",
    "addr:postcode": "01730",
    "addr:street": "Sweetwater Ave",
    "iso:country": "US",
    "sg:address": "66 Sweetwater Ave",
    "sg:city": "Bedford",
    "sg:classifiers": [
      {
        "category": "Education",
        "subcategory": "Special Training",
        "type": "Public Place"
      },
      {
        "category": "Education",
        "subcategory": "School",
        "type": "Public Place"
      }
    ],
    "sg:phone": "+1 781 275 7606",
    "sg:postcode": "01730",
    "sg:province": "MA",
    "sg:tags": [
      "high",
      "middle",
      "specialty",
      "elementary"
    ],
    "wof:name": "Bedford Town of",
    "wof:placetype": "venue"
  },
  "geometry": {"coordinates":[-71.278057,42.514079],"type":"Point"}
}
