{
  "type": "Feature",
  "properties": {
    "addr:full": "29 Dunham Rd Billerica MA 01821",
    "addr:housenumber": "29",
    "addr:postcode": "01821",
    "addr:street": "Dunham Rd",
    "iso:country": "US",
    "sg:address": "29 Dunham Rd",
    "sg:city": "Billerica",
    "sg:classifiers": [
      {
        "category": "Manufacturing",
        "subcategory": "Tools \u0026 Machinery",
        "type": "Manufacturing \u0026 Wholesale Goods"
      }
    ],
    "sg:phone": "+1   ",
    "sg:postcode": "01821",
    "sg:province": "MA",
    "sg:tags": [
      "dist",
      "image",
      "sales",
      "system",
      "mfr",
      "setting",
      "design",
      "ha"
    ],
    "wof:name": "Prepress Direct",
    "wof:placetype": "venue"
  },
  "geometry": {"coordinates":[-71.232976,42.519508],"type":"Point"}
}
