{
  "type": "Feature",
  "properties": {
    "iso:country":"US",
    "sg:address":"29 Dunham Rd",
    "sg:city":"Billerica",
    "sg:classifiers":[
        {
            "category":"Manufacturing",
            "subcategory":"Tools & Machinery",
            "type":"Manufacturing & Wholesale Goods"
        }
    ],
    "sg:phone":"+1   ",
    "sg:postcode":"01821",
    "sg:province":"MA",
    "sg:tags":[
        "dist",
        "image",
        "sales",
        "system",
        "mfr",
        "setting",
        "design",
        "ha"
    ],
    "wof:name":"Prepress Direct",
    "wof:placetype":"venue"
},
  "geometry": {"coordinates":[-71.23297599999999,42.519508],"type":"Point"}
}