{
  "type": "Feature",
  "properties": {
    "addr:full": "204 Union St New Bedford MA 02740",
    "addr:housenumber": "204",
    "addr:postcode": "02740",
    "addr:street": "Union St",
    "iso:country": "US",
    "sg:address": "204 Union St",
    "sg:city": "New Bedford",
    "sg:classifiers": [
      {
        "category": "Professional",
        "subcategory": "Management \u0026 Consulting",
        "type": "Services"
      }
    ],
    "sg:phone": "+1 508 994 3861",
    "sg:postcode": "02740",
    "sg:province": "MA",
    "sg:tags": [
      "fuel"
    ],
    "wof:name": "Hallkeen Management",
    "wof:placetype": "venue"
  },
  "geometry": {"coordinates":[-70.926309,41.634123],"type":"Point"}
}
