{
  "type": "Feature",
  "properties": {
    "addr:full":"27 Central St East Bridgewater MA 02333",
    "addr:housenumber":"27",
    "addr:postcode":"02333",
    "addr:street":"Central St",
    "iso:country":"US",
    "sg:address":"27 Central St",
    "sg:city":"East Bridgewater",
    "sg:classifiers":[
        {
            "category":"Real Estate",
            "subcategory":"Surveying",
            "type":"Services"
        }
    ],
    "sg:phone":"+1 508 378 8178",
    "sg:postcode":"02333",
    "sg:province":"MA",
    "sg:tags":[
        "surveyor"
    ],
    "wof:name":"Professional Land Survey Assoc",
    "wof:placetype":"venue"
},
  "geometry": {"coordinates":[-70.95898099999999,42.032218],"type":"Point"}
}