{
  "type": "Feature",
  "properties": {
    "addr:full":"55 Cleveland Rd Wellesley MA 02481",
    "addr:housenumber":"55",
    "addr:postcode":"02481",
    "addr:street":"Cleveland Rd",
    "iso:country":"US",
    "sg:address":"55 Cleveland Rd",
    "sg:city":"Wellesley",
    "sg:classifiers":[
        {
            "category":"Health Services",
            "subcategory":"Doctor",
            "type":"Services"
        }
    ],
    "sg:phone":"+1 781 235 1546",
    "sg:postcode":"02481",
    "sg:province":"MA",
    "sg:tags":[
        "physician",
        "surgeon"
    ],
    "wof:name":"Jerome S Gans MD",
    "wof:placetype":"venue"
},
  "geometry": {"coordinates":[-71.308395,42.307246],"type":"Point"}
}