{
  "type": "Feature",
  "properties": {
    "iso:country":"US",
    "sg:address":"83 Longwood Ave",
    "sg:city":"Brookline",
    "sg:classifiers":[
        {
            "category":"Travel",
            "subcategory":"Bed & Breakfast",
            "type":"Entertainment"
        }
    ],
    "sg:phone":"+1 617 277 1620",
    "sg:postcode":"02446",
    "sg:province":"MA",
    "sg:website":"www.thebeechtreeinn.com",
    "wof:name":"The Beech Tree Inn",
    "wof:placetype":"venue"
},
  "geometry": {"coordinates":[-71.116756,42.340845],"type":"Point"}
}