{
  "type": "Feature",
  "properties": {
    "addr:full":"56 W Foster St Melrose MA 02176",
    "addr:housenumber":"56",
    "addr:postcode":"02176",
    "addr:street":"W Foster St",
    "iso:country":"US",
    "sg:address":"56 W Foster St",
    "sg:city":"Melrose",
    "sg:classifiers":[
        {
            "category":"Government",
            "subcategory":"Police Station",
            "type":"Public Place"
        }
    ],
    "sg:phone":"+1 781 665 1212",
    "sg:postcode":"02176",
    "sg:province":"MA",
    "sg:tags":[
        "department"
    ],
    "sg:website":"www.melrosepolice.com",
    "wof:name":"Police Department",
    "wof:placetype":"venue"
},
  "geometry": {"coordinates":[-71.066669,42.454902],"type":"Point"}
}