{
  "type": "Feature",
  "properties": {
    "addr:full": "199 South St Pittsfield MA 01201",
    "addr:housenumber": "199",
    "addr:postcode": "01201",
    "addr:street": "South St",
    "iso:country": "US",
    "sg:address": "199 South St",
    "sg:city": "Pittsfield",
    "sg:classifiers": [
      {
        "category": "Education",
        "subcategory": "School",
        "type": "Public Place"
      }
    ],
    "sg:phone": "+1 413 499 4167",
    "sg:postcode": "01201",
    "sg:province": "MA",
    "wof:name": "Sinai Academy-The Berkshires",
    "wof:placetype": "venue"
  },
  "geometry": {"coordinates":[-73.255046,42.443694],"type":"Point"}
}
