{
  "type": "Feature",
  "properties": {
    "addr:full": "1 Kiddie Dr Avon MA 02322",
    "addr:housenumber": "1",
    "addr:postcode": "02322",
    "addr:street": "Kiddie Dr",
    "iso:country": "US",
    "sg:address": "1 Kiddie Dr",
    "sg:city": "Avon",
    "sg:classifiers": [
      {
        "category": "Wholesale",
        "subcategory": "Office Equipment",
        "type": "Manufacturing \u0026 Wholesale Goods"
      },
      {
        "category": "Manufacturing",
        "subcategory": "Leather Goods",
        "type": "Manufacturing \u0026 Wholesale Goods"
      },
      {
        "category": "Home \u0026 Garden",
        "subcategory": "Home Furnishings",
        "type": "Retail Goods"
      },
      {
        "category": "Food \u0026 Beverages",
        "subcategory": "Dairy",
        "type": "Retail Goods"
      },
      {
        "category": "Home \u0026 Garden",
        "subcategory": "Furniture",
        "type": "Retail Goods"
      }
    ],
    "sg:phone": "+1 508 436 2518",
    "sg:postcode": "02322",
    "sg:province": "MA",
    "sg:tags": [
      "bedroom",
      "set",
      "store",
      "bed",
      "futon"
    ],
    "sg:website": "http://www.loganfurniture.com",
    "wof:name": "Logan Furniture",
    "wof:placetype": "venue"
  },
  "geometry": {"coordinates":[-71.056038,42.129978],"type":"Point"}
}
