{
  "type": "Feature",
  "properties": {
    "addr:full": "256 S Common St Lynn MA 01905",
    "addr:housenumber": "256",
    "addr:postcode": "01905",
    "addr:street": "S Common St",
    "iso:country": "US",
    "sg:address": "256 S Common St",
    "sg:city": "Lynn",
    "sg:classifiers": [
      {
        "category": "Professional",
        "type": "Services"
      }
    ],
    "sg:phone": "+1   ",
    "sg:postcode": "01905",
    "sg:province": "MA",
    "wof:name": "Q \u0026 D Inc",
    "wof:placetype": "venue"
  },
  "geometry": {"coordinates":[-70.964518,42.461471],"type":"Point"}
}
