{
  "type": "Feature",
  "properties": {
    "addr:full": "695 Hillside St Milton MA 02186",
    "addr:housenumber": "695",
    "addr:postcode": "02186",
    "addr:street": "Hillside St",
    "iso:country": "US",
    "sg:address": "695 Hillside St",
    "sg:city": "Milton",
    "sg:classifiers": [
      {
        "category": "Government",
        "subcategory": "Office",
        "type": "Public Place"
      }
    ],
    "sg:phone": "+1 617 727 4573",
    "sg:postcode": "02186",
    "sg:province": "MA",
    "sg:website": "www.ma.gov/dcr",
    "wof:name": "Dept Of Cnsrvation \u0026 Rcration",
    "wof:placetype": "venue"
  },
  "geometry": {"coordinates":[-71.097183,42.20966],"type":"Point"}
}
