{
  "type": "Feature",
  "properties": {
    "iso:country":"US",
    "sg:address":"18 Tremont St",
    "sg:city":"Boston",
    "sg:classifiers":[
        {
            "category":"Professional",
            "subcategory":"Lawyer & Legal Services",
            "type":"Services"
        }
    ],
    "sg:phone":"+1 617 399 6720",
    "sg:postcode":"02108",
    "sg:province":"MA",
    "sg:tags":[
        "attorney"
    ],
    "wof:name":"Victim Rights Law Ctr Inc",
    "wof:placetype":"venue"
},
  "geometry": {"coordinates":[-71.05975599999999,42.359046],"type":"Point"}
}