{
  "type": "Feature",
  "properties": {
    "iso:country":"US",
    "sg:address":"5 Sycamore Street",
    "sg:city":"Everett",
    "sg:classifiers":[
        {
            "category":"Restaurant",
            "type":"Food & Drink"
        }
    ],
    "sg:phone":"+1 781 321 3335",
    "sg:postcode":"02149",
    "sg:province":"MA",
    "sg:tags":[
        "pizza",
        "italian"
    ],
    "sg:website":"www.pizzahut.com",
    "wof:name":"Pizza Hut",
    "wof:placetype":"venue"
},
  "geometry": {"coordinates":[-71.04710300000001,42.414432],"type":"Point"}
}