{
  "type": "Feature",
  "properties": {
    "addr:full": "5 Sycamore Street Everett MA 02149",
    "addr:housenumber": "5",
    "addr:postcode": "02149",
    "addr:street": "Sycamore Street",
    "iso:country": "US",
    "sg:address": "5 Sycamore Street",
    "sg:city": "Everett",
    "sg:classifiers": [
      {
        "category": "Restaurant",
        "type": "Food \u0026 Drink"
      }
    ],
    "sg:phone": "+1 781 321 3335",
    "sg:postcode": "02149",
    "sg:province": "MA",
    "sg:tags": [
      "pizza",
      "italian"
    ],
    "sg:website": "www.pizzahut.com",
    "wof:name": "Pizza Hut",
    "wof:placetype": "venue"
  },
  "geometry": {"coordinates":[-71.047103,42.414432],"type":"Point"}
}
