{
  "type": "Feature",
  "properties": {
    "addr:full":"444 Appleton St Holyoke MA 01040",
    "addr:housenumber":"444",
    "addr:postcode":"01040",
    "addr:street":"Appleton St",
    "iso:country":"US",
    "sg:address":"444 Appleton St",
    "sg:city":"Holyoke",
    "sg:classifiers":[
        {
            "category":"Personal",
            "subcategory":"Barber",
            "type":"Services"
        }
    ],
    "sg:phone":"+1 413 534 1820",
    "sg:postcode":"01040",
    "sg:province":"MA",
    "sg:tags":[
        "shop"
    ],
    "wof:name":"Jose's Barber Shop",
    "wof:placetype":"venue"
},
  "geometry": {"coordinates":[-72.61547400000001,42.207816],"type":"Point"}
}