{
  "type": "Feature",
  "properties": {
    "addr:full":"319 E 8th St Boston MA 02127",
    "addr:housenumber":"319",
    "addr:postcode":"02127",
    "addr:street":"E 8Th St",
    "iso:country":"US",
    "sg:address":"319 E 8th St",
    "sg:city":"Boston",
    "sg:classifiers":[
        {
            "category":"Building & Trades",
            "subcategory":"Plumbing",
            "type":"Services"
        }
    ],
    "sg:phone":"+1   ",
    "sg:postcode":"02127",
    "sg:province":"MA",
    "sg:tags":[
        "plumbing",
        "heating",
        "contractor"
    ],
    "wof:name":"Mc Carthy Joseph M Plbg & Htg",
    "wof:placetype":"venue"
},
  "geometry": {"coordinates":[-71.048357,42.331148],"type":"Point"}
}