{
  "type": "Feature",
  "properties": {
    "iso:country":"US",
    "sg:address":"500 Front St",
    "sg:city":"Chicopee",
    "sg:classifiers":[
        {
            "category":"Shopping",
            "type":"Retail Goods"
        }
    ],
    "sg:phone":"+1 413 592 4400",
    "sg:postcode":"01013",
    "sg:province":"MA",
    "sg:tags":[
        "hearing",
        "equipment",
        "supply",
        "impaired"
    ],
    "wof:name":"Chicopee Hearing Ctr-Pioneer",
    "wof:placetype":"venue"
},
  "geometry": {"coordinates":[-72.59747400000001,42.147995],"type":"Point"}
}