{
  "type": "Feature",
  "properties": {
    "addr:full": "500 Front St Chicopee MA 01013",
    "addr:housenumber": "500",
    "addr:postcode": "01013",
    "addr:street": "Front St",
    "iso:country": "US",
    "sg:address": "500 Front St",
    "sg:city": "Chicopee",
    "sg:classifiers": [
      {
        "category": "Shopping",
        "type": "Retail Goods"
      }
    ],
    "sg:phone": "+1 413 592 4400",
    "sg:postcode": "01013",
    "sg:province": "MA",
    "sg:tags": [
      "hearing",
      "equipment",
      "supply",
      "impaired"
    ],
    "wof:name": "Chicopee Hearing Ctr-Pioneer",
    "wof:placetype": "venue"
  },
  "geometry": {"coordinates":[-72.597474,42.147995],"type":"Point"}
}
