{
  "type": "Feature",
  "properties": {
    "iso:country":"US",
    "sg:address":"1 Union St",
    "sg:city":"Scituate",
    "sg:classifiers":[
        {
            "category":"Shopping",
            "type":"Retail Goods"
        }
    ],
    "sg:phone":"+1 781 545 1311",
    "sg:postcode":"02066",
    "sg:province":"MA",
    "sg:tags":[
        "pet",
        "food",
        "supply"
    ],
    "wof:name":"Fitts Mill",
    "wof:placetype":"venue"
},
  "geometry": {"coordinates":[-70.744743,42.182508],"type":"Point"}
}