{
  "type": "Feature",
  "properties": {
    "iso:country":"US",
    "sg:address":"3 School St Ste 302",
    "sg:city":"Boston",
    "sg:classifiers":[
        {
            "category":"Professional",
            "subcategory":"Management & Consulting",
            "type":"Services"
        },
        {
            "category":"Professional",
            "subcategory":"Business Services",
            "type":"Services"
        }
    ],
    "sg:phone":"+1 617 742 2412",
    "sg:postcode":"02108",
    "sg:province":"MA",
    "sg:tags":[
        "consultant",
        "coach"
    ],
    "wof:name":"The Windsor Group Inc",
    "wof:placetype":"venue"
},
  "geometry": {"coordinates":[-71.058492,42.357413],"type":"Point"}
}