{
  "type": "Feature",
  "properties": {
    "addr:full": "37 Cushman St Taunton MA 02780",
    "addr:housenumber": "37",
    "addr:postcode": "02780",
    "addr:street": "Cushman St",
    "iso:country": "US",
    "sg:address": "37 Cushman St",
    "sg:city": "Taunton",
    "sg:classifiers": [
      {
        "category": "Professional",
        "type": "Services"
      }
    ],
    "sg:phone": "+1 508 996 0165",
    "sg:postcode": "02780",
    "sg:province": "MA",
    "sg:tags": [
      "establishment"
    ],
    "wof:name": "Zelenda Metric",
    "wof:placetype": "venue"
  },
  "geometry": {"coordinates":[-71.087652,41.893422],"type":"Point"}
}
