{
  "type": "Feature",
  "properties": {
    "addr:full": "86 Cottage St Boston MA 02128",
    "addr:housenumber": "86",
    "addr:postcode": "02128",
    "addr:street": "Cottage St",
    "iso:country": "US",
    "sg:address": "86 Cottage St",
    "sg:city": "Boston",
    "sg:classifiers": [
      {
        "category": "Food \u0026 Beverages",
        "subcategory": "Groceries \u0026 Convenience Stores",
        "type": "Retail Goods"
      }
    ],
    "sg:phone": "+1 617 567 6373",
    "sg:postcode": "02128",
    "sg:province": "MA",
    "sg:tags": [
      "product",
      "grocer"
    ],
    "wof:name": "Gloria Food Stores",
    "wof:placetype": "venue"
  },
  "geometry": {"coordinates":[-71.035004,42.368],"type":"Point"}
}
