{
  "type": "Feature",
  "properties": {
    "iso:country":"US",
    "sg:address":"86 Cottage St",
    "sg:city":"Boston",
    "sg:classifiers":[
        {
            "category":"Food & Beverages",
            "subcategory":"Groceries & Convenience Stores",
            "type":"Retail Goods"
        }
    ],
    "sg:phone":"+1 617 567 6373",
    "sg:postcode":"02128",
    "sg:province":"MA",
    "sg:tags":[
        "product",
        "grocer"
    ],
    "wof:name":"Gloria Food Stores",
    "wof:placetype":"venue"
},
  "geometry": {"coordinates":[-71.035004,42.368],"type":"Point"}
}