{
  "type": "Feature",
  "properties": {
    "addr:full":"450 Huntington Ave Boston MA 02108",
    "addr:housenumber":"450",
    "addr:postcode":"02108",
    "addr:street":"Huntington Ave",
    "iso:country":"US",
    "sg:address":"450 Huntington Ave",
    "sg:city":"Boston",
    "sg:classifiers":[
        {
            "category":"Bars & Pubs",
            "type":"Food & Drink"
        },
        {
            "category":"Bars & Pubs",
            "subcategory":"Dive Bar",
            "type":"Food & Drink"
        }
    ],
    "sg:phone":"+1 617 472 2330",
    "sg:postcode":"02108",
    "sg:province":"MA",
    "wof:name":"Punter's Pub",
    "wof:placetype":"venue"
},
  "geometry": {"coordinates":[-71.09286400000001,42.338697],"type":"Point"}
}