{
  "type": "Feature",
  "properties": {
    "addr:full": "450 Huntington Ave Boston MA 02108",
    "addr:housenumber": "450",
    "addr:postcode": "02108",
    "addr:street": "Huntington Ave",
    "iso:country": "US",
    "sg:address": "450 Huntington Ave",
    "sg:city": "Boston",
    "sg:classifiers": [
      {
        "category": "Bars \u0026 Pubs",
        "type": "Food \u0026 Drink"
      },
      {
        "category": "Bars \u0026 Pubs",
        "subcategory": "Dive Bar",
        "type": "Food \u0026 Drink"
      }
    ],
    "sg:phone": "+1 617 472 2330",
    "sg:postcode": "02108",
    "sg:province": "MA",
    "wof:name": "Punter's Pub",
    "wof:placetype": "venue"
  },
  "geometry": {"coordinates":[-71.092864,42.338697],"type":"Point"}
}
