{
  "type": "Feature",
  "properties": {
    "iso:country":"US",
    "sg:address":"21 Main St",
    "sg:city":"Harwich",
    "sg:classifiers":[
        {
            "category":"Restaurant",
            "type":"Food & Drink"
        }
    ],
    "sg:phone":"+1 508 432 8855",
    "sg:postcode":"02645",
    "sg:province":"MA",
    "wof:name":"China Lighthouse Cuisine",
    "wof:placetype":"venue"
},
  "geometry": {"coordinates":[-70.13127,41.700053],"type":"Point"}
}