{
  "type": "Feature",
  "properties": {
    "addr:full": "21 Main St Harwich MA 02645",
    "addr:housenumber": "21",
    "addr:postcode": "02645",
    "addr:street": "Main St",
    "iso:country": "US",
    "sg:address": "21 Main St",
    "sg:city": "Harwich",
    "sg:classifiers": [
      {
        "category": "Restaurant",
        "type": "Food \u0026 Drink"
      }
    ],
    "sg:phone": "+1 508 432 8855",
    "sg:postcode": "02645",
    "sg:province": "MA",
    "wof:name": "China Lighthouse Cuisine",
    "wof:placetype": "venue"
  },
  "geometry": {"coordinates":[-70.13127,41.700053],"type":"Point"}
}
