{
  "type": "Feature",
  "properties": {
    "addr:full": "438 Main St Woburn MA 01801",
    "addr:housenumber": "438",
    "addr:postcode": "01801",
    "addr:street": "Main St",
    "iso:country": "US",
    "ovtr:label": "Hot Breads, 438 Main St Woburn MA US",
    "ovtr:similarity": 2.08274507522583,
    "sg:address": "438 Main St",
    "sg:city": "Woburn",
    "sg:classifiers": [
      {
        "category": "Restaurant",
        "type": "Food \u0026 Drink"
      },
      {
        "category": "Bakery",
        "type": "Food \u0026 Drink"
      }
    ],
    "sg:phone": "+1 781 933 7557",
    "sg:postcode": "01801",
    "sg:province": "MA",
    "sg:tags": [
      "indian"
    ],
    "sg:website": "www.hotbreads-woburn.com/",
    "wof:name": "Hot Breads",
    "wof:placetype": "venue"
  },
  "geometry": {"coordinates":[-71.151039,42.480949],"type":"Point"}
}
