{
  "type": "Feature",
  "properties": {
    "iso:country":"US",
    "sg:address":"25 Ellison Rd",
    "sg:city":"Newton",
    "sg:classifiers":[
        {
            "category":"Professional",
            "subcategory":"Management & Consulting",
            "type":"Services"
        }
    ],
    "sg:phone":"+1 617 332 3496",
    "sg:postcode":"02459",
    "sg:province":"MA",
    "sg:tags":[
        "consultant",
        "business"
    ],
    "sg:website":"www.disaster-help.com",
    "wof:name":"Systems Audit Group",
    "wof:placetype":"venue"
},
  "geometry": {"coordinates":[-71.20619499999999,42.336585],"type":"Point"}
}