{
  "type": "Feature",
  "properties": {
    "iso:country":"US",
    "sg:address":"394 Main St Ste B",
    "sg:city":"Medford",
    "sg:classifiers":[
        {
            "category":"Coffee & Tea",
            "type":"Food & Drink"
        },
        {
            "category":"Restaurant",
            "type":"Food & Drink"
        },
        {
            "category":"Internet Cafe",
            "subcategory":"None",
            "type":"Food & Drink"
        }
    ],
    "sg:phone":"+1 781 219 4929",
    "sg:postcode":"02155",
    "sg:province":"MA",
    "sg:tags":[
        "shop",
        "brunch",
        "breakfast"
    ],
    "sg:website":"www.cafedeia.net/",
    "wof:name":"Cafe Deia",
    "wof:placetype":"venue"
},
  "geometry": {"coordinates":[-71.107568,42.404666],"type":"Point"}
}