{
  "type": "Feature",
  "properties": {
    "addr:full": "394 Main St Ste B Medford MA 02155",
    "addr:housenumber": "394",
    "addr:postcode": "02155",
    "addr:street": "Main St Ste B",
    "iso:country": "US",
    "sg:address": "394 Main St Ste B",
    "sg:city": "Medford",
    "sg:classifiers": [
      {
        "category": "Coffee \u0026 Tea",
        "type": "Food \u0026 Drink"
      },
      {
        "category": "Restaurant",
        "type": "Food \u0026 Drink"
      },
      {
        "category": "Internet Cafe",
        "subcategory": "None",
        "type": "Food \u0026 Drink"
      }
    ],
    "sg:phone": "+1 781 219 4929",
    "sg:postcode": "02155",
    "sg:province": "MA",
    "sg:tags": [
      "shop",
      "brunch",
      "breakfast"
    ],
    "sg:website": "www.cafedeia.net/",
    "wof:name": "Cafe Deia",
    "wof:placetype": "venue"
  },
  "geometry": {"coordinates":[-71.107568,42.404666],"type":"Point"}
}
