{
  "type": "Feature",
  "properties": {
    "iso:country":"US",
    "sg:address":"790 Southbridge St",
    "sg:city":"Auburn",
    "sg:classifiers":[
        {
            "category":"Recreation",
            "type":"Entertainment"
        }
    ],
    "sg:phone":"+1 508 832 0559",
    "sg:postcode":"01501",
    "sg:province":"MA",
    "sg:tags":[
        "range",
        "practice",
        "golf"
    ],
    "wof:name":"Auburn Golf Range",
    "wof:placetype":"venue"
},
  "geometry": {"coordinates":[-71.86809599999999,42.181818],"type":"Point"}
}