{
  "type": "Feature",
  "properties": {
    "iso:country":"US",
    "sg:address":"11 Mark St",
    "sg:city":"Burlington",
    "sg:classifiers":[
        {
            "category":"Professional",
            "type":"Services"
        }
    ],
    "sg:phone":"+1   ",
    "sg:postcode":"01803",
    "sg:province":"MA",
    "wof:name":"Alison Conliffe",
    "wof:placetype":"venue"
},
  "geometry": {"coordinates":[-71.212642,42.490791],"type":"Point"}
}