{
  "type": "Feature",
  "properties": {
    "addr:full":"164 Main St Watertown MA 02472",
    "addr:housenumber":"164",
    "addr:postcode":"02472",
    "addr:street":"Main St",
    "iso:country":"US",
    "sg:address":"164 Main St",
    "sg:city":"Watertown",
    "sg:classifiers":[
        {
            "category":"Food & Beverages",
            "subcategory":"Groceries & Convenience Stores",
            "type":"Retail Goods"
        }
    ],
    "sg:phone":"+1 617 926 8018",
    "sg:postcode":"02472",
    "sg:province":"MA",
    "wof:name":"Store 24",
    "wof:placetype":"venue"
},
  "geometry": {"coordinates":[-71.188608,42.368075],"type":"Point"}
}