{
  "type": "Feature",
  "properties": {
    "iso:country":"US",
    "sg:address":"165 F New Boston St",
    "sg:city":"Woburn",
    "sg:classifiers":[
        {
            "category":"Building & Trades",
            "subcategory":"Cleaning & Sanitation",
            "type":"Services"
        }
    ],
    "sg:phone":"+1 781 938 6688",
    "sg:postcode":"01801",
    "sg:province":"MA",
    "sg:tags":[
        "carpet"
    ],
    "sg:website":"www.bostoncleaningcompanyinc.com",
    "wof:name":"Boston Cleaning Company, Inc",
    "wof:placetype":"venue"
},
  "geometry": {"coordinates":[-71.143784,42.510062],"type":"Point"}
}