{
  "type": "Feature",
  "properties": {
    "addr:full": "665 Liberty St Ste 1 Springfield MA 01104",
    "addr:housenumber": "665",
    "addr:postcode": "01104",
    "addr:street": "Liberty St Ste 1",
    "iso:country": "US",
    "sg:address": "665 Liberty St Ste 1",
    "sg:city": "Springfield",
    "sg:classifiers": [
      {
        "category": "Shopping",
        "subcategory": "Thrift Store",
        "type": "Retail Goods"
      },
      {
        "category": "Banks \u0026 Credit Unions",
        "subcategory": "Bank",
        "type": "Services"
      }
    ],
    "sg:phone": "+1 413 732 9259",
    "sg:postcode": "01104",
    "sg:province": "MA",
    "sg:tags": [
      "shop",
      "second",
      "hand"
    ],
    "wof:name": "Salvation Army Thrift Store",
    "wof:placetype": "venue"
  },
  "geometry": {"coordinates":[-72.584222,42.121446],"type":"Point"}
}
