{
  "type": "Feature",
  "properties": {
    "addr:full":"24 Pocahontas Dr Peabody MA 01960",
    "addr:housenumber":"24",
    "addr:postcode":"01960",
    "addr:street":"Pocahontas Dr",
    "iso:country":"US",
    "sg:address":"24 Pocahontas Dr",
    "sg:city":"Peabody",
    "sg:classifiers":[
        {
            "category":"Building & Trades",
            "subcategory":"Construction",
            "type":"Services"
        }
    ],
    "sg:phone":"+1 781 451 3086",
    "sg:postcode":"01960",
    "sg:province":"MA",
    "sg:tags":[
        "roofing",
        "contractor"
    ],
    "wof:name":"Robbins Roofing & Contracting",
    "wof:placetype":"venue"
},
  "geometry": {"coordinates":[-71.02699699999999,42.556045],"type":"Point"}
}