{
  "type": "Feature",
  "properties": {
    "addr:full": "24 Province St Boston MA 02108",
    "addr:housenumber": "24",
    "addr:postcode": "02108",
    "addr:street": "Province St",
    "iso:country": "US",
    "sg:address": "24 Province St",
    "sg:city": "Boston",
    "sg:classifiers": [
      {
        "category": "Professional",
        "subcategory": "Research",
        "type": "Services"
      },
      {
        "category": "Professional",
        "subcategory": "Employment Agencies",
        "type": "Services"
      },
      {
        "category": "Organizations",
        "subcategory": "Professional Association",
        "type": "Services"
      },
      {
        "category": "Professional",
        "subcategory": "Business Services",
        "type": "Services"
      },
      {
        "category": "Organizations",
        "subcategory": "Community Association",
        "type": "Services"
      },
      {
        "category": "Education",
        "subcategory": "Library",
        "type": "Public Place"
      }
    ],
    "sg:phone": "+1 617 720 1000",
    "sg:postcode": "02108",
    "sg:province": "MA",
    "sg:tags": [
      "trade",
      "lobbyist",
      "employer"
    ],
    "sg:website": "http://www.masstaxpayers.org",
    "wof:name": "Massachusetts Taxpayers Fndtn",
    "wof:placetype": "venue"
  },
  "geometry": {"coordinates":[-71.059779,42.357157],"type":"Point"}
}
