{
  "type": "Feature",
  "properties": {
    "addr:full": "21 Broad St Nantucket MA 02554",
    "addr:housenumber": "21",
    "addr:postcode": "02554",
    "addr:street": "Broad St",
    "iso:country": "US",
    "sg:address": "21 Broad St",
    "sg:city": "Nantucket",
    "sg:classifiers": [
      {
        "category": "Travel",
        "subcategory": "Hotels \u0026 Motels",
        "type": "Entertainment"
      }
    ],
    "sg:phone": "+1 508 228 0156",
    "sg:postcode": "02554",
    "sg:province": "MA",
    "wof:name": "Nesbitt Inn",
    "wof:placetype": "venue"
  },
  "geometry": {"coordinates":[-70.099474,41.28524],"type":"Point"}
}
