{
  "type": "Feature",
  "properties": {
    "iso:country":"US",
    "sg:address":"21 Broad St",
    "sg:city":"Nantucket",
    "sg:classifiers":[
        {
            "category":"Travel",
            "subcategory":"Hotels & Motels",
            "type":"Entertainment"
        }
    ],
    "sg:phone":"+1 508 228 0156",
    "sg:postcode":"02554",
    "sg:province":"MA",
    "wof:name":"Nesbitt Inn",
    "wof:placetype":"venue"
},
  "geometry": {"coordinates":[-70.099474,41.28524],"type":"Point"}
}