{
  "type": "Feature",
  "properties": {
    "addr:full":"333 Washington St Ste 335 Boston MA 02108",
    "addr:housenumber":"333",
    "addr:postcode":"02108",
    "addr:street":"Washington St Ste 335",
    "iso:country":"US",
    "sg:address":"333 Washington St Ste 335",
    "sg:city":"Boston",
    "sg:classifiers":[
        {
            "category":"Manufacturing",
            "subcategory":"Jewelry",
            "type":"Manufacturing & Wholesale Goods"
        },
        {
            "category":"Retail",
            "subcategory":"Repair Shop",
            "type":"Services"
        }
    ],
    "sg:phone":"+1 617 227 8575",
    "sg:postcode":"02108",
    "sg:province":"MA",
    "sg:tags":[
        "repairing",
        "clock"
    ],
    "wof:name":"Michel Hamoui",
    "wof:placetype":"venue"
},
  "geometry": {"coordinates":[-71.059012,42.356777],"type":"Point"}
}