{
  "type": "Feature",
  "properties": {
    "iso:country":"US",
    "sg:address":"45 Walker St",
    "sg:city":"Lenox",
    "sg:classifiers":[
        {
            "category":"Personal",
            "type":"Services"
        }
    ],
    "sg:phone":"+1 413 637 0106",
    "sg:postcode":"01240",
    "sg:province":"MA",
    "sg:tags":[
        "program",
        "physical",
        "exercise",
        "fitness"
    ],
    "wof:name":"Kinephere Gyrotonic",
    "wof:placetype":"venue"
},
  "geometry": {"coordinates":[-73.283345,42.356028],"type":"Point"}
}