{
  "type": "Feature",
  "properties": {
    "addr:full": "875 Main St Worcester MA 01610",
    "addr:housenumber": "875",
    "addr:postcode": "01610",
    "addr:street": "Main St",
    "iso:country": "US",
    "sg:address": "875 Main St",
    "sg:city": "Worcester",
    "sg:classifiers": [
      {
        "category": "Social Services",
        "subcategory": "Child Care",
        "type": "Services"
      }
    ],
    "sg:phone": "+1 508 752 0675",
    "sg:postcode": "01610",
    "sg:province": "MA",
    "wof:name": "Worcester Comp Childcare",
    "wof:placetype": "venue"
  },
  "geometry": {"coordinates":[-71.821,42.250808],"type":"Point"}
}
