{
  "type": "Feature",
  "properties": {
    "addr:full": "363 River St Winchendon MA 01475",
    "addr:housenumber": "363",
    "addr:postcode": "01475",
    "addr:street": "River St",
    "iso:country": "US",
    "sg:address": "363 River St",
    "sg:city": "Winchendon",
    "sg:classifiers": [
      {
        "category": "Manufacturing",
        "subcategory": "Wood Products",
        "type": "Manufacturing \u0026 Wholesale Goods"
      }
    ],
    "sg:phone": "+1 978 297 2310",
    "sg:postcode": "01475",
    "sg:province": "MA",
    "wof:name": "M Kamenstein Inc",
    "wof:placetype": "venue"
  },
  "geometry": {"coordinates":[-72.061991,42.677505],"type":"Point"}
}
