{
  "type": "Feature",
  "properties": {
    "iso:country":"US",
    "sg:address":"363 River St",
    "sg:city":"Winchendon",
    "sg:classifiers":[
        {
            "category":"Manufacturing",
            "subcategory":"Wood Products",
            "type":"Manufacturing & Wholesale Goods"
        }
    ],
    "sg:phone":"+1 978 297 2310",
    "sg:postcode":"01475",
    "sg:province":"MA",
    "wof:name":"M Kamenstein Inc",
    "wof:placetype":"venue"
},
  "geometry": {"coordinates":[-72.06199100000001,42.677505],"type":"Point"}
}