{
  "type": "Feature",
  "properties": {
    "iso:country":"US",
    "sg:address":"475 E Main St",
    "sg:city":"Southbridge",
    "sg:classifiers":[
        {
            "category":"Wholesale",
            "subcategory":"Auto Parts",
            "type":"Manufacturing & Wholesale Goods"
        }
    ],
    "sg:phone":"+1 508 764 2773",
    "sg:postcode":"01550",
    "sg:province":"MA",
    "sg:tags":[
        "automobile",
        "rebuilt"
    ],
    "wof:name":"Plaza Used Auto Parts",
    "wof:placetype":"venue"
},
  "geometry": {"coordinates":[-72.012224,42.070363],"type":"Point"}
}