{
  "type": "Feature",
  "properties": {
    "addr:full": "475 E Main St Southbridge MA 01550",
    "addr:housenumber": "475",
    "addr:postcode": "01550",
    "addr:street": "E Main St",
    "iso:country": "US",
    "ovtr:label": "Plaza Used Auto Parts, 475 E Main St Southbridge MA US",
    "ovtr:similarity": 1.9665440320968628,
    "sg:address": "475 E Main St",
    "sg:city": "Southbridge",
    "sg:classifiers": [
      {
        "category": "Wholesale",
        "subcategory": "Auto Parts",
        "type": "Manufacturing \u0026 Wholesale Goods"
      }
    ],
    "sg:phone": "+1 508 764 2773",
    "sg:postcode": "01550",
    "sg:province": "MA",
    "sg:tags": [
      "automobile",
      "rebuilt"
    ],
    "wof:name": "Plaza Used Auto Parts",
    "wof:placetype": "venue"
  },
  "geometry": {"coordinates":[-72.012224,42.070363],"type":"Point"}
}
