{
  "type": "Feature",
  "properties": {
    "addr:full": "184 Morton Rd South Chatham MA 02659",
    "addr:housenumber": "184",
    "addr:postcode": "02659",
    "addr:street": "Morton Rd",
    "iso:country": "US",
    "sg:address": "184 Morton Rd",
    "sg:city": "South Chatham",
    "sg:classifiers": [
      {
        "category": "Real Estate",
        "subcategory": "Real Estate Agent",
        "type": "Services"
      }
    ],
    "sg:phone": "+1   ",
    "sg:postcode": "02659",
    "sg:province": "MA",
    "wof:name": "Prestige Properties",
    "wof:placetype": "venue"
  },
  "geometry": {"coordinates":[-70.024613,41.683242],"type":"Point"}
}
