{
  "type": "Feature",
  "properties": {
    "iso:country":"US",
    "sg:address":"98 Newbury St",
    "sg:city":"Danvers",
    "sg:classifiers":[
        {
            "category":"Home & Garden",
            "subcategory":"Household Appliances",
            "type":"Retail Goods"
        }
    ],
    "sg:phone":"+1 978 283 0770",
    "sg:postcode":"01923",
    "sg:province":"MA",
    "sg:tags":[
        "machine",
        "sewing"
    ],
    "wof:name":"Ed's North Shore Sew & Vac",
    "wof:placetype":"venue"
},
  "geometry": {"coordinates":[-70.974733,42.567131],"type":"Point"}
}