{
  "type": "Feature",
  "properties": {
    "iso:country":"US",
    "sg:address":"575 Boylston St",
    "sg:city":"Newton",
    "sg:classifiers":[
        {
            "category":"Health Services",
            "subcategory":"Doctor",
            "type":"Services"
        }
    ],
    "sg:phone":"+1 617 332 8280",
    "sg:postcode":"02459",
    "sg:province":"MA",
    "sg:tags":[
        "physician",
        "surgeon"
    ],
    "wof:name":"Boston Cosmetic Ctr",
    "wof:placetype":"venue"
},
  "geometry": {"coordinates":[-71.19273200000001,42.318878],"type":"Point"}
}