{
  "type": "Feature",
  "properties": {
    "addr:full": "33 Cranberry Meadow Rd Bellingham MA 02019",
    "addr:housenumber": "33",
    "addr:postcode": "02019",
    "addr:street": "Cranberry Meadow Rd",
    "iso:country": "US",
    "sg:address": "33 Cranberry Meadow Rd",
    "sg:city": "Bellingham",
    "sg:classifiers": [
      {
        "category": "Building \u0026 Trades",
        "subcategory": "Plumbing",
        "type": "Services"
      }
    ],
    "sg:phone": "+1 508 883 8375",
    "sg:postcode": "02019",
    "sg:province": "MA",
    "sg:tags": [
      "plumbing",
      "contractor"
    ],
    "wof:name": "A Custom Co Plumbing",
    "wof:placetype": "venue"
  },
  "geometry": {"coordinates":[-71.494713,42.050828],"type":"Point"}
}
