{
  "type": "Feature",
  "properties": {
    "iso:country":"US",
    "sg:address":"33 Cranberry Meadow Rd",
    "sg:city":"Bellingham",
    "sg:classifiers":[
        {
            "category":"Building & Trades",
            "subcategory":"Plumbing",
            "type":"Services"
        }
    ],
    "sg:phone":"+1 508 883 8375",
    "sg:postcode":"02019",
    "sg:province":"MA",
    "sg:tags":[
        "plumbing",
        "contractor"
    ],
    "wof:name":"A Custom Co Plumbing",
    "wof:placetype":"venue"
},
  "geometry": {"coordinates":[-71.494713,42.050828],"type":"Point"}
}