{
  "type": "Feature",
  "properties": {
    "addr:full": "885 Waverly St Framingham MA 01702",
    "addr:housenumber": "885",
    "addr:postcode": "01702",
    "addr:street": "Waverly St",
    "iso:country": "US",
    "sg:address": "885 Waverly St",
    "sg:city": "Framingham",
    "sg:classifiers": [
      {
        "category": "Home \u0026 Garden",
        "subcategory": "Household Appliances",
        "type": "Retail Goods"
      },
      {
        "category": "Building \u0026 Trades",
        "subcategory": "Construction",
        "type": "Services"
      }
    ],
    "sg:phone": "+1 508 875 3182",
    "sg:postcode": "01702",
    "sg:province": "MA",
    "sg:tags": [
      "dishwashing",
      "system",
      "contractor",
      "machine",
      "air conditioning"
    ],
    "sg:website": "http://www.bonazzolihvac.com",
    "wof:name": "The Bonazzoli Corporation",
    "wof:placetype": "venue"
  },
  "geometry": {"coordinates":[-71.434354,42.27379],"type":"Point"}
}
