{
  "type": "Feature",
  "properties": {
    "addr:full": "316 Main St North Easton MA 02356",
    "addr:housenumber": "316",
    "addr:postcode": "02356",
    "addr:street": "Main St",
    "iso:country": "US",
    "sg:address": "316 Main St",
    "sg:city": "North Easton",
    "sg:classifiers": [
      {
        "category": "Food \u0026 Beverages",
        "subcategory": "Candy",
        "type": "Retail Goods"
      }
    ],
    "sg:phone": "+1 508 238 6231",
    "sg:postcode": "02356",
    "sg:province": "MA",
    "sg:tags": [
      "confectionery"
    ],
    "wof:name": "Hillard's House Of Candy",
    "wof:placetype": "venue"
  },
  "geometry": {"coordinates":[-71.083809,42.067341],"type":"Point"}
}
