{
  "type": "Feature",
  "properties": {
    "addr:full": "562 Cambridge St Allston MA 02134",
    "addr:housenumber": "562",
    "addr:postcode": "02134",
    "addr:street": "Cambridge St",
    "iso:country": "US",
    "ovtr:label": "Cheema Supermarket, 562 Cambridge St Allston MA US",
    "ovtr:similarity": 2.1076018810272217,
    "sg:address": "562 Cambridge St",
    "sg:city": "Allston",
    "sg:classifiers": [
      {
        "category": "Food \u0026 Beverages",
        "subcategory": "Meat \u0026 Fish",
        "type": "Retail Goods"
      }
    ],
    "sg:phone": "+1 617 783 9800",
    "sg:postcode": "02134",
    "sg:province": "MA",
    "sg:tags": [
      "shop"
    ],
    "wof:name": "Cheema Supermarket",
    "wof:placetype": "venue"
  },
  "geometry": {"coordinates":[-71.1404,42.3523],"type":"Point"}
}
