{
  "type": "Feature",
  "properties": {
    "iso:country":"US",
    "sg:address":"562 Cambridge St",
    "sg:city":"Allston",
    "sg:classifiers":[
        {
            "category":"Food & Beverages",
            "subcategory":"Meat & Fish",
            "type":"Retail Goods"
        }
    ],
    "sg:phone":"+1 617 783 9800",
    "sg:postcode":"02134",
    "sg:province":"MA",
    "sg:tags":[
        "shop"
    ],
    "wof:name":"Cheema Supermarket",
    "wof:placetype":"venue"
},
  "geometry": {"coordinates":[-71.1404,42.3523],"type":"Point"}
}