{
  "type": "Feature",
  "properties": {
    "iso:country":"US",
    "sg:address":"449 Boston Post Rd E",
    "sg:city":"Marlborough",
    "sg:classifiers":[
        {
            "category":"Building & Trades",
            "subcategory":"Plumbing",
            "type":"Services"
        }
    ],
    "sg:phone":"+1 508 481 2349",
    "sg:postcode":"01752",
    "sg:province":"MA",
    "sg:tags":[
        "refrigeration",
        "contractor"
    ],
    "wof:name":"O'Donnell's Air Conditioning",
    "wof:placetype":"venue"
},
  "geometry": {"coordinates":[-71.51531199999999,42.348115],"type":"Point"}
}