{
  "type": "Feature",
  "properties": {
    "iso:country":"US",
    "sg:address":"96 Camp Opechee Rd",
    "sg:city":"Centerville",
    "sg:classifiers":[
        {
            "category":"Building & Trades",
            "subcategory":"Landscaping Services",
            "type":"Services"
        }
    ],
    "sg:phone":"+1 508 775 8062",
    "sg:postcode":"02632",
    "sg:province":"MA",
    "sg:tags":[
        "landscape",
        "contractor"
    ],
    "wof:name":"Leonard Yard & Tree",
    "wof:placetype":"venue"
},
  "geometry": {"coordinates":[-70.348748,41.66064],"type":"Point"}
}