{
  "type": "Feature",
  "properties": {
    "iso:country":"US",
    "sg:address":"136 Bond Rd",
    "sg:city":"Charlton",
    "sg:classifiers":[
        {
            "category":"Retail",
            "subcategory":"Repair Shop",
            "type":"Services"
        }
    ],
    "sg:phone":"+1   ",
    "sg:postcode":"01507",
    "sg:province":"MA",
    "wof:name":"Worcester Boiler Repair",
    "wof:placetype":"venue"
},
  "geometry": {"coordinates":[-71.945826,42.113154],"type":"Point"}
}