{
  "type": "Feature",
  "properties": {
    "addr:full":"34 Bridge St Chelmsford MA 01824",
    "addr:housenumber":"34",
    "addr:postcode":"01824",
    "addr:street":"Bridge St",
    "iso:country":"US",
    "sg:address":"34 Bridge St",
    "sg:city":"Chelmsford",
    "sg:classifiers":[
        {
            "category":"Building & Trades",
            "subcategory":"Construction",
            "type":"Services"
        }
    ],
    "sg:phone":"+1 978 256 2086",
    "sg:postcode":"01824",
    "sg:province":"MA",
    "sg:tags":[
        "contractor"
    ],
    "wof:name":"Gagnon Construction",
    "wof:placetype":"venue"
},
  "geometry": {"coordinates":[-71.358774,42.596669],"type":"Point"}
}