{
  "type": "Feature",
  "properties": {
    "addr:full": "379 Cambridge St Allston MA 02134",
    "addr:housenumber": "379",
    "addr:postcode": "02134",
    "addr:street": "Cambridge St",
    "iso:country": "US",
    "sg:address": "379 Cambridge St",
    "sg:city": "Allston",
    "sg:classifiers": [
      {
        "category": "Shopping",
        "subcategory": "Used Merchandise",
        "type": "Retail Goods"
      }
    ],
    "sg:phone": "+1 617 787 2428",
    "sg:postcode": "02134",
    "sg:province": "MA",
    "sg:tags": [
      "antique"
    ],
    "wof:name": "Boston Rug Co",
    "wof:placetype": "venue"
  },
  "geometry": {"coordinates":[-71.133142,42.35548],"type":"Point"}
}
