{
  "type": "Feature",
  "properties": {
    "addr:full":"47 Vernon St Waltham MA 02453",
    "addr:housenumber":"47",
    "addr:postcode":"02453",
    "addr:street":"Vernon St",
    "iso:country":"US",
    "sg:address":"47 Vernon St",
    "sg:city":"Waltham",
    "sg:classifiers":[
        {
            "category":"Manufacturing",
            "subcategory":"Signs",
            "type":"Manufacturing & Wholesale Goods"
        }
    ],
    "sg:phone":"+1 781 444 4658",
    "sg:postcode":"02453",
    "sg:province":"MA",
    "sg:tags":[
        "animation",
        "mechanism"
    ],
    "sg:website":"www.temah.com",
    "wof:name":"T Time Animation",
    "wof:placetype":"venue"
},
  "geometry": {"coordinates":[-71.250041,42.374376],"type":"Point"}
}