{
  "type": "Feature",
  "properties": {
    "addr:full": "550 Worcester Rd Framingham MA 01702",
    "addr:housenumber": "550",
    "addr:postcode": "01702",
    "addr:street": "Worcester Rd",
    "iso:country": "US",
    "sg:address": "550 Worcester Rd",
    "sg:city": "Framingham",
    "sg:classifiers": [
      {
        "category": "Professional",
        "subcategory": "Lawyer \u0026 Legal Services",
        "type": "Services"
      }
    ],
    "sg:phone": "+1 508 875 9595",
    "sg:postcode": "01702",
    "sg:province": "MA",
    "sg:tags": [
      "attorney"
    ],
    "wof:name": "Rubin \u0026 Oriel",
    "wof:placetype": "venue"
  },
  "geometry": {"coordinates":[-71.419071,42.297636],"type":"Point"}
}
