{
  "type": "Feature",
  "properties": {
    "iso:country":"US",
    "sg:address":"2 Westgate Ln",
    "sg:city":"East Freetown",
    "sg:classifiers":[
        {
            "category":"Retail",
            "subcategory":"Repair Shop",
            "type":"Services"
        }
    ],
    "sg:phone":"+1   ",
    "sg:postcode":"02717",
    "sg:province":"MA",
    "wof:name":"Toms Sharpening Service",
    "wof:placetype":"venue"
},
  "geometry": {"coordinates":[-70.97543899999999,41.737598],"type":"Point"}
}