{
  "type": "Feature",
  "properties": {
    "addr:full": "4 Westdale Rd Canton MA 02021",
    "addr:housenumber": "4",
    "addr:postcode": "02021",
    "addr:street": "Westdale Rd",
    "iso:country": "US",
    "sg:address": "4 Westdale Rd",
    "sg:city": "Canton",
    "sg:classifiers": [
      {
        "category": "Professional",
        "subcategory": "Business Services",
        "type": "Services"
      }
    ],
    "sg:phone": "+1   ",
    "sg:postcode": "02021",
    "sg:province": "MA",
    "wof:name": "Hughes Enterprise",
    "wof:placetype": "venue"
  },
  "geometry": {"coordinates":[-71.09353,42.18506],"type":"Point"}
}
