{
  "type": "Feature",
  "properties": {
    "addr:full": "86A Sherman St Cambridge MA 02140",
    "addr:housenumber": "86a",
    "addr:postcode": "02140",
    "addr:street": "Sherman St",
    "iso:country": "US",
    "sg:address": "86A Sherman St",
    "sg:city": "Cambridge",
    "sg:classifiers": [
      {
        "category": "Building \u0026 Trades",
        "subcategory": "Equipment Rental",
        "type": "Services"
      }
    ],
    "sg:phone": "+1 617 497 6941",
    "sg:postcode": "02140",
    "sg:province": "MA",
    "sg:tags": [
      "bedding",
      "supply",
      "manufacturer"
    ],
    "wof:name": "Ascion",
    "wof:placetype": "venue"
  },
  "geometry": {"coordinates":[-71.132118,42.387841],"type":"Point"}
}
