{
  "type": "Feature",
  "properties": {
    "iso:country":"US",
    "sg:address":"165 Belgrade Ave",
    "sg:city":"Roslindale",
    "sg:classifiers":[
        {
            "category":"Food & Beverages",
            "subcategory":"Groceries & Convenience Stores",
            "type":"Retail Goods"
        }
    ],
    "sg:phone":"+1 617 325 5272",
    "sg:postcode":"02131",
    "sg:province":"MA",
    "wof:name":"Home Mkt",
    "wof:placetype":"venue"
},
  "geometry": {"coordinates":[-71.138603,42.286301],"type":"Point"}
}