{
  "type": "Feature",
  "properties": {
    "iso:country":"US",
    "sg:address":"1360 S Washington St",
    "sg:city":"North Attleboro",
    "sg:classifiers":[
        {
            "category":"Shopping",
            "subcategory":"Crafts & Fabrics",
            "type":"Retail Goods"
        }
    ],
    "sg:phone":"+1 508 643 1911",
    "sg:postcode":"02760",
    "sg:province":"MA",
    "sg:tags":[
        "art"
    ],
    "sg:website":"www.joann.com",
    "wof:name":"Jo-Ann Fabric and Crafts Superstore",
    "wof:placetype":"venue"
},
  "geometry": {"coordinates":[-71.34603199999999,41.937654],"type":"Point"}
}