{
  "type": "Feature",
  "properties": {
    "addr:full": "1360 S Washington St North Attleboro MA 02760",
    "addr:housenumber": "1360",
    "addr:postcode": "02760",
    "addr:street": "S Washington St",
    "iso:country": "US",
    "sg:address": "1360 S Washington St",
    "sg:city": "North Attleboro",
    "sg:classifiers": [
      {
        "category": "Shopping",
        "subcategory": "Crafts \u0026 Fabrics",
        "type": "Retail Goods"
      }
    ],
    "sg:phone": "+1 508 643 1911",
    "sg:postcode": "02760",
    "sg:province": "MA",
    "sg:tags": [
      "art"
    ],
    "sg:website": "www.joann.com",
    "wof:name": "Jo-Ann Fabric and Crafts Superstore",
    "wof:placetype": "venue"
  },
  "geometry": {"coordinates":[-71.346032,41.937654],"type":"Point"}
}
