{
  "type": "Feature",
  "properties": {
    "iso:country":"US",
    "sg:address":"486 Chandler St",
    "sg:city":"Tewksbury",
    "sg:classifiers":[
        {
            "category":"Health Services",
            "subcategory":"Nursing And Care Facility",
            "type":"Services"
        }
    ],
    "sg:phone":"+1 978 851 7258",
    "sg:postcode":"01876",
    "sg:province":"MA",
    "sg:tags":[
        "home",
        "convalescent"
    ],
    "wof:name":"Retirement Home",
    "wof:placetype":"venue"
},
  "geometry": {"coordinates":[-71.227608,42.604203],"type":"Point"}
}