{
  "type": "Feature",
  "properties": {
    "addr:full":"121 Creeper Hill Rd North Grafton MA 01536",
    "addr:housenumber":"121",
    "addr:postcode":"01536",
    "addr:street":"Creeper Hill Rd",
    "iso:country":"US",
    "sg:address":"121 Creeper Hill Rd",
    "sg:city":"North Grafton",
    "sg:classifiers":[
        {
            "category":"Manufacturing",
            "subcategory":"Tools & Machinery",
            "type":"Manufacturing & Wholesale Goods"
        }
    ],
    "sg:phone":"+1 508 839 2175",
    "sg:postcode":"01536",
    "sg:province":"MA",
    "sg:tags":[
        "machine",
        "shop"
    ],
    "wof:name":"Lincoln Precision Machining Co",
    "wof:placetype":"venue"
},
  "geometry": {"coordinates":[-71.733018,42.23635],"type":"Point"}
}