{
  "type": "Feature",
  "properties": {
    "iso:country":"US",
    "sg:address":"250 Hammond Pond Pkwy",
    "sg:city":"Chestnut Hill",
    "sg:classifiers":[
        {
            "category":"Professional",
            "subcategory":"Lawyer & Legal Services",
            "type":"Services"
        }
    ],
    "sg:phone":"+1 617 558 9800",
    "sg:postcode":"02467",
    "sg:province":"MA",
    "sg:tags":[
        "attorney"
    ],
    "wof:name":"Ring Jordan Lewis & Assoc",
    "wof:placetype":"venue"
},
  "geometry": {"coordinates":[-71.172431,42.321229],"type":"Point"}
}