{
  "type": "Feature",
  "properties": {
    "addr:full":"Canton Center 635 Washington St Canton MA 02021",
    "addr:housenumber":"635",
    "addr:postcode":"02021",
    "addr:street":"Canton;Washington St",
    "iso:country":"US",
    "sg:address":"Canton Center 635 Washington St",
    "sg:city":"Canton",
    "sg:classifiers":[
        {
            "category":"Coffee & Tea",
            "type":"Food & Drink"
        },
        {
            "category":"Restaurant",
            "type":"Food & Drink"
        }
    ],
    "sg:phone":"+1 339 237 3925",
    "sg:postcode":"02021",
    "sg:province":"MA",
    "sg:tags":[
        "traditional",
        "american",
        "espresso"
    ],
    "wof:name":"Amber Road Cafe",
    "wof:placetype":"venue"
},
  "geometry": {"coordinates":[-71.145803,42.154219],"type":"Point"}
}