{
  "type": "Feature",
  "properties": {
    "addr:full":"117 Marginal St Lowell MA 01851",
    "addr:housenumber":"117",
    "addr:postcode":"01851",
    "addr:street":"Marginal St",
    "iso:country":"US",
    "sg:address":"117 Marginal St",
    "sg:city":"Lowell",
    "sg:classifiers":[
        {
            "category":"Shopping",
            "subcategory":"Used Merchandise",
            "type":"Retail Goods"
        }
    ],
    "sg:phone":"+1 978 275 6465",
    "sg:postcode":"01851",
    "sg:province":"MA",
    "sg:tags":[
        "furniture"
    ],
    "wof:name":"Fi Office Inc",
    "wof:placetype":"venue"
},
  "geometry": {"coordinates":[-71.335686,42.639625],"type":"Point"}
}