{
  "type": "Feature",
  "properties": {
    "addr:full": "195 Whiting St Hingham MA 02043",
    "addr:housenumber": "195",
    "addr:postcode": "02043",
    "addr:street": "Whiting St",
    "iso:country": "US",
    "sg:address": "195 Whiting St",
    "sg:city": "Hingham",
    "sg:classifiers": [
      {
        "category": "Personal",
        "subcategory": "Beauty Salon",
        "type": "Services"
      }
    ],
    "sg:phone": "+1 781 749 9077",
    "sg:postcode": "02043",
    "sg:province": "MA",
    "wof:name": "Nailary",
    "wof:placetype": "venue"
  },
  "geometry": {"coordinates":[-70.898251,42.179723],"type":"Point"}
}
