{
  "type": "Feature",
  "properties": {
    "addr:full":"17 Hampshire Rd Methuen MA 01844",
    "addr:housenumber":"17",
    "addr:postcode":"01844",
    "addr:street":"Hampshire Rd",
    "iso:country":"US",
    "sg:address":"17 Hampshire Rd",
    "sg:city":"Methuen",
    "sg:classifiers":[
        {
            "category":"Real Estate",
            "subcategory":"Real Estate Operator",
            "type":"Services"
        }
    ],
    "sg:phone":"+1 978 682 8883",
    "sg:postcode":"01844",
    "sg:province":"MA",
    "sg:tags":[
        "apartment"
    ],
    "sg:website":"http://www.pavilionsapartments.com",
    "wof:name":"Spicket Commons",
    "wof:placetype":"venue"
},
  "geometry": {"coordinates":[-71.204002,42.741852],"type":"Point"}
}