{
  "type": "Feature",
  "properties": {
    "addr:full":"14 Hadley St North Billerica MA 01862",
    "addr:housenumber":"14",
    "addr:postcode":"01862",
    "addr:street":"Hadley St",
    "iso:country":"US",
    "sg:address":"14 Hadley St",
    "sg:city":"North Billerica",
    "sg:classifiers":[
        {
            "category":"Manufacturing",
            "subcategory":"Tools & Machinery",
            "type":"Manufacturing & Wholesale Goods"
        }
    ],
    "sg:phone":"+1 978 667 9793",
    "sg:postcode":"01862",
    "sg:province":"MA",
    "sg:tags":[
        "machine",
        "shop"
    ],
    "wof:name":"Mike's Precision Machine",
    "wof:placetype":"venue"
},
  "geometry": {"coordinates":[-71.27875,42.572212],"type":"Point"}
}