{
  "type": "Feature",
  "properties": {
    "addr:full":"23 Rocky Hill Rd Oxford MA 01540",
    "addr:housenumber":"23",
    "addr:postcode":"01540",
    "addr:street":"Rocky Hill Rd",
    "iso:country":"US",
    "sg:address":"23 Rocky Hill Rd",
    "sg:city":"Oxford",
    "sg:classifiers":[
        {
            "category":"Building & Trades",
            "subcategory":"Construction",
            "type":"Services"
        }
    ],
    "sg:phone":"+1 508 987 1346",
    "sg:postcode":"01540",
    "sg:province":"MA",
    "sg:tags":[
        "wallcoverings-installation",
        "wallpaper",
        "painting",
        "contractor"
    ],
    "wof:name":"Beardsley Painting",
    "wof:placetype":"venue"
},
  "geometry": {"coordinates":[-71.869179,42.13232],"type":"Point"}
}