{
  "type": "Feature",
  "properties": {
    "addr:full": "146 Boston St Lynn MA 01904",
    "addr:housenumber": "146",
    "addr:postcode": "01904",
    "addr:street": "Boston St",
    "iso:country": "US",
    "ovtr:label": "Pro Laundromat \u0026 Dry Cleaning, 146 Boston St Lynn MA US",
    "ovtr:similarity": 2.051774024963379,
    "sg:address": "146 Boston St",
    "sg:city": "Lynn",
    "sg:classifiers": [
      {
        "category": "Retail",
        "subcategory": "Self-service Laundry",
        "type": "Services"
      }
    ],
    "sg:phone": "+1 781 592 1146",
    "sg:postcode": "01904",
    "sg:province": "MA",
    "wof:name": "Pro Laundromat \u0026 Dry Cleaning",
    "wof:placetype": "venue"
  },
  "geometry": {"coordinates":[-70.95888,42.471259],"type":"Point"}
}
