{
  "type": "Feature",
  "properties": {
    "iso:country":"US",
    "sg:address":"146 Boston St",
    "sg:city":"Lynn",
    "sg:classifiers":[
        {
            "category":"Retail",
            "subcategory":"Self-service Laundry",
            "type":"Services"
        }
    ],
    "sg:phone":"+1 781 592 1146",
    "sg:postcode":"01904",
    "sg:province":"MA",
    "wof:name":"Pro Laundromat & Dry Cleaning",
    "wof:placetype":"venue"
},
  "geometry": {"coordinates":[-70.95887999999999,42.471259],"type":"Point"}
}