{
  "type": "Feature",
  "properties": {
    "addr:full": "80 Jefferson Street Winthrop MA 02152",
    "addr:housenumber": "80",
    "addr:postcode": "02152",
    "addr:street": "Jefferson Street",
    "iso:country": "US",
    "sg:address": "80 Jefferson Street",
    "sg:city": "Winthrop",
    "sg:classifiers": [
      {
        "category": "Professional",
        "subcategory": "Lawyer \u0026 Legal Services",
        "type": "Services"
      }
    ],
    "sg:phone": "+1 617 846 3433",
    "sg:postcode": "02152",
    "sg:province": "MA",
    "sg:tags": [
      "personal",
      "injury"
    ],
    "wof:name": "Tick William Lwyr",
    "wof:placetype": "venue"
  },
  "geometry": {"coordinates":[-70.986037,42.375],"type":"Point"}
}
