{
  "type": "Feature",
  "properties": {
    "addr:full":"210 Waverly St Framingham MA 01702",
    "addr:housenumber":"210",
    "addr:postcode":"01702",
    "addr:street":"Waverly St",
    "iso:country":"US",
    "sg:address":"210 Waverly St",
    "sg:city":"Framingham",
    "sg:classifiers":[
        {
            "category":"Restaurant",
            "type":"Food & Drink"
        }
    ],
    "sg:menulink":"http://www.allmenus.com/ma/framingham/69886-papa-ginos/menu/",
    "sg:phone":"+1 508 626 1677",
    "sg:postcode":"01702",
    "sg:province":"MA",
    "sg:tags":[
        "american",
        "pizza"
    ],
    "wof:name":"Papa Gino's",
    "wof:placetype":"venue"
},
  "geometry": {"coordinates":[-71.40844800000001,42.278421],"type":"Point"}
}