{
  "type": "Feature",
  "properties": {
    "addr:full": "40 Depot St Brewster MA 02631",
    "addr:housenumber": "40",
    "addr:postcode": "02631",
    "addr:street": "Depot St",
    "iso:country": "US",
    "sg:address": "40 Depot St",
    "sg:city": "Brewster",
    "sg:classifiers": [
      {
        "category": "Recreation",
        "type": "Entertainment"
      }
    ],
    "sg:phone": "+1 508 896 4601",
    "sg:postcode": "02631",
    "sg:province": "MA",
    "sg:tags": [
      "stable"
    ],
    "wof:name": "Olde Orchard Farms",
    "wof:placetype": "venue"
  },
  "geometry": {"coordinates":[-70.071974,41.751943],"type":"Point"}
}
