{
  "type": "Feature",
  "properties": {
    "addr:full": "268 Newbury St Boston MA 02116",
    "addr:housenumber": "268",
    "addr:postcode": "02116",
    "addr:street": "Newbury St",
    "iso:country": "US",
    "sg:address": "268 Newbury St",
    "sg:city": "Boston",
    "sg:classifiers": [
      {
        "category": "Real Estate",
        "subcategory": "Real Estate Agent",
        "type": "Services"
      }
    ],
    "sg:phone": "+1 617 262 5353",
    "sg:postcode": "02116",
    "sg:province": "MA",
    "wof:name": "Olde Boston Realty Co",
    "wof:placetype": "venue"
  },
  "geometry": {"coordinates":[-71.083067,42.349416],"type":"Point"}
}
