{
  "type": "Feature",
  "properties": {
    "addr:full":"853 N Main St Leominster MA 01453",
    "addr:housenumber":"853",
    "addr:postcode":"01453",
    "addr:street":"N Main St",
    "iso:country":"US",
    "sg:address":"853 N Main St",
    "sg:city":"Leominster",
    "sg:classifiers":[
        {
            "category":"Shopping",
            "subcategory":"Jewelry",
            "type":"Retail Goods"
        }
    ],
    "sg:phone":"+1   ",
    "sg:postcode":"01453",
    "sg:province":"MA",
    "wof:name":"Cutco Cutlery",
    "wof:placetype":"venue"
},
  "geometry": {"coordinates":[-71.771303,42.556915],"type":"Point"}
}