{
  "type": "Feature",
  "properties": {
    "addr:full": "159 Samoset St Plymouth MA 02360",
    "addr:housenumber": "159",
    "addr:postcode": "02360",
    "addr:street": "Samoset St",
    "iso:country": "US",
    "sg:address": "159 Samoset St",
    "sg:city": "Plymouth",
    "sg:classifiers": [
      {
        "category": "Health Services",
        "subcategory": "Doctor",
        "type": "Services"
      }
    ],
    "sg:phone": "+1 508 746 1990",
    "sg:postcode": "02360",
    "sg:province": "MA",
    "sg:tags": [
      "physician",
      "surgeon"
    ],
    "wof:name": "Joseph J Grant Optometrist",
    "wof:placetype": "venue"
  },
  "geometry": {"coordinates":[-70.688683,41.95116],"type":"Point"}
}
