{
  "type": "Feature",
  "properties": {
    "addr:full": "183 Franklin St Boston MA 02110",
    "addr:housenumber": "183",
    "addr:postcode": "02110",
    "addr:street": "Franklin St",
    "iso:country": "US",
    "sg:address": "183 Franklin St",
    "sg:city": "Boston",
    "sg:classifiers": [
      {
        "category": "Shopping",
        "subcategory": "Crafts \u0026 Fabrics",
        "type": "Retail Goods"
      }
    ],
    "sg:phone": "+1 617 574 9261",
    "sg:postcode": "02110",
    "sg:province": "MA",
    "sg:tags": [
      "store"
    ],
    "wof:name": "Scalamandre",
    "wof:placetype": "venue"
  },
  "geometry": {"coordinates":[-71.055801,42.355801],"type":"Point"}
}
