{
  "type": "Feature",
  "properties": {
    "addr:full": "430 N Canal St Ste 2 Lawrence MA 01840",
    "addr:housenumber": "430",
    "addr:postcode": "01840",
    "addr:street": "N Canal St Ste 2",
    "iso:country": "US",
    "sg:address": "430 N Canal St Ste 2",
    "sg:city": "Lawrence",
    "sg:classifiers": [
      {
        "category": "Social Services",
        "type": "Services"
      }
    ],
    "sg:phone": "+1 978 685 6609",
    "sg:postcode": "01840",
    "sg:province": "MA",
    "sg:tags": [
      "program",
      "services-information",
      "referral"
    ],
    "wof:name": "Garden Street Apartment Inc",
    "wof:placetype": "venue"
  },
  "geometry": {"coordinates":[-71.163667,42.705131],"type":"Point"}
}
