{
  "type": "Feature",
  "properties": {
    "iso:country":"US",
    "sg:address":"73 Russell Rd",
    "sg:city":"Westfield",
    "sg:classifiers":[
        {
            "category":"Retail",
            "subcategory":"Repair Shop",
            "type":"Services"
        }
    ],
    "sg:phone":"+1   ",
    "sg:postcode":"01085",
    "sg:province":"MA",
    "sg:tags":[
        "stationery",
        "equipment",
        "electrical"
    ],
    "wof:name":"Taylor Office Machine",
    "wof:placetype":"venue"
},
  "geometry": {"coordinates":[-72.76675899999999,42.128233],"type":"Point"}
}