{
  "type": "Feature",
  "properties": {
    "addr:full": "16 Sparks Ave Nantucket MA 02554",
    "addr:housenumber": "16",
    "addr:postcode": "02554",
    "addr:street": "Sparks Ave",
    "iso:country": "US",
    "ovtr:label": "Nantucket Housefitters, Inc, 16 Sparks Ave Nantucket MA US",
    "ovtr:similarity": 2.879357099533081,
    "sg:address": "16 Sparks Ave",
    "sg:city": "Nantucket",
    "sg:classifiers": [
      {
        "category": "Building \u0026 Trades",
        "subcategory": "Construction",
        "type": "Services"
      }
    ],
    "sg:phone": "+1 508 228 2815",
    "sg:postcode": "02554",
    "sg:province": "MA",
    "sg:tags": [
      "general",
      "contractor"
    ],
    "wof:name": "Nantucket Housefitters Inc",
    "wof:placetype": "venue"
  },
  "geometry": {"coordinates":[-70.090586,41.27117],"type":"Point"}
}
