{
  "type": "Feature",
  "properties": {
    "iso:country":"US",
    "sg:address":"16 Sparks Ave",
    "sg:city":"Nantucket",
    "sg:classifiers":[
        {
            "category":"Building & Trades",
            "subcategory":"Construction",
            "type":"Services"
        }
    ],
    "sg:phone":"+1 508 228 2815",
    "sg:postcode":"02554",
    "sg:province":"MA",
    "sg:tags":[
        "general",
        "contractor"
    ],
    "wof:name":"Nantucket Housefitters Inc",
    "wof:placetype":"venue"
},
  "geometry": {"coordinates":[-70.090586,41.27117],"type":"Point"}
}