{
  "type": "Feature",
  "properties": {
    "addr:full":"45 Robbins Rd Walpole MA 02081",
    "addr:housenumber":"45",
    "addr:postcode":"02081",
    "addr:street":"Robbins Rd",
    "iso:country":"US",
    "sg:address":"45 Robbins Rd",
    "sg:city":"Walpole",
    "sg:classifiers":[
        {
            "category":"Shopping",
            "subcategory":"Gifts & Souvenirs",
            "type":"Retail Goods"
        }
    ],
    "sg:phone":"+1   ",
    "sg:postcode":"02081",
    "sg:province":"MA",
    "wof:name":"West Indies Trading Co",
    "wof:placetype":"venue"
},
  "geometry": {"coordinates":[-71.251941,42.153483],"type":"Point"}
}