{
  "type": "Feature",
  "properties": {
    "iso:country":"US",
    "sg:address":"85 Forge Rd",
    "sg:city":"Westport",
    "sg:classifiers":[
        {
            "category":"Autos & Motor Vehicles",
            "subcategory":"Automobile Sales",
            "type":"Retail Goods"
        },
        {
            "category":"Retail",
            "subcategory":"Auto Repair",
            "type":"Services"
        }
    ],
    "sg:phone":"+1 508 636 3906",
    "sg:postcode":"02790",
    "sg:province":"MA",
    "sg:tags":[
        "body",
        "used",
        "car",
        "painting",
        "dealers-used",
        "new",
        "cars-wholesale",
        "repairing"
    ],
    "wof:name":"Ferreira's Auto Body & Auto Sales",
    "wof:placetype":"venue"
},
  "geometry": {"coordinates":[-71.053862,41.640901],"type":"Point"}
}