{
  "type": "Feature",
  "properties": {
    "addr:full": "7 Bearskin Neck Rockport MA 01966",
    "addr:housenumber": "7",
    "addr:postcode": "01966",
    "addr:street": "Bearskin Neck",
    "iso:country": "US",
    "sg:address": "7 Bearskin Neck",
    "sg:city": "Rockport",
    "sg:classifiers": [
      {
        "category": "Shopping",
        "subcategory": "Jewelry",
        "type": "Retail Goods"
      }
    ],
    "sg:phone": "+1 978 546 0028",
    "sg:postcode": "01966",
    "sg:province": "MA",
    "sg:tags": [
      "jeweler"
    ],
    "wof:name": "Evans \u0026 Hughes",
    "wof:placetype": "venue"
  },
  "geometry": {"coordinates":[-70.616617,42.659023],"type":"Point"}
}
