{
  "type": "Feature",
  "properties": {
    "iso:country":"US",
    "sg:address":"7 Bearskin Neck",
    "sg:city":"Rockport",
    "sg:classifiers":[
        {
            "category":"Shopping",
            "subcategory":"Jewelry",
            "type":"Retail Goods"
        }
    ],
    "sg:phone":"+1 978 546 0028",
    "sg:postcode":"01966",
    "sg:province":"MA",
    "sg:tags":[
        "jeweler"
    ],
    "wof:name":"Evans & Hughes",
    "wof:placetype":"venue"
},
  "geometry": {"coordinates":[-70.61661700000001,42.659023],"type":"Point"}
}