{
  "type": "Feature",
  "properties": {
    "addr:full": "15 Lovett Ln North Chelmsford MA 01863",
    "addr:housenumber": "15",
    "addr:postcode": "01863",
    "addr:street": "Lovett Ln",
    "iso:country": "US",
    "sg:address": "15 Lovett Ln",
    "sg:city": "North Chelmsford",
    "sg:classifiers": [
      {
        "category": "Shopping",
        "subcategory": "Musical Instruments",
        "type": "Retail Goods"
      }
    ],
    "sg:phone": "+1   ",
    "sg:postcode": "01863",
    "sg:province": "MA",
    "wof:name": "Percussion Specialists",
    "wof:placetype": "venue"
  },
  "geometry": {"coordinates":[-71.40817,42.628005],"type":"Point"}
}
