{
  "type": "Feature",
  "properties": {
    "iso:country":"US",
    "sg:address":"26 Simmons Dr",
    "sg:city":"Milford",
    "sg:classifiers":[
        {
            "category":"Professional",
            "subcategory":"Business Services",
            "type":"Services"
        }
    ],
    "sg:phone":"+1   ",
    "sg:postcode":"01757",
    "sg:province":"MA",
    "wof:name":"Compassionate Friends",
    "wof:placetype":"venue"
},
  "geometry": {"coordinates":[-71.55032,42.157334],"type":"Point"}
}