{
  "type": "Feature",
  "properties": {
    "iso:country":"US",
    "sg:address":"9 Harrington St",
    "sg:city":"Watertown",
    "sg:classifiers":[
        {
            "category":"Building & Trades",
            "subcategory":"Plumbing",
            "type":"Services"
        }
    ],
    "sg:phone":"+1 617 484 5388",
    "sg:postcode":"02472",
    "sg:province":"MA",
    "sg:tags":[
        "plumbing",
        "contractor"
    ],
    "wof:name":"De Simone Plumbing",
    "wof:placetype":"venue"
},
  "geometry": {"coordinates":[-71.196043,42.382601],"type":"Point"}
}