{
  "type": "Feature",
  "properties": {
    "addr:full": "91 Union St Attleboro MA 02703",
    "addr:housenumber": "91",
    "addr:postcode": "02703",
    "addr:street": "Union St",
    "iso:country": "US",
    "sg:address": "91 Union St",
    "sg:city": "Attleboro",
    "sg:classifiers": [
      {
        "category": "Real Estate",
        "subcategory": "Real Estate Services",
        "type": "Services"
      },
      {
        "category": "Building \u0026 Trades",
        "subcategory": "Cleaning \u0026 Sanitation",
        "type": "Services"
      },
      {
        "category": "Building \u0026 Trades",
        "subcategory": "Construction",
        "type": "Services"
      }
    ],
    "sg:phone": "+1 508 223 2990",
    "sg:postcode": "02703",
    "sg:province": "MA",
    "sg:tags": [
      "industrial",
      "contractors-commercial",
      "maintenance",
      "cleaners-interior"
    ],
    "wof:name": "Chain Store Maintenance, Inc.",
    "wof:placetype": "venue"
  },
  "geometry": {"coordinates":[-71.282969,41.941283],"type":"Point"}
}
