{
  "type": "Feature",
  "properties": {
    "iso:country":"US",
    "sg:address":"91 Union St",
    "sg:city":"Attleboro",
    "sg:classifiers":[
        {
            "category":"Real Estate",
            "subcategory":"Real Estate Services",
            "type":"Services"
        },
        {
            "category":"Building & Trades",
            "subcategory":"Cleaning & Sanitation",
            "type":"Services"
        },
        {
            "category":"Building & Trades",
            "subcategory":"Construction",
            "type":"Services"
        }
    ],
    "sg:phone":"+1 508 223 2990",
    "sg:postcode":"02703",
    "sg:province":"MA",
    "sg:tags":[
        "industrial",
        "contractors-commercial",
        "maintenance",
        "cleaners-interior"
    ],
    "wof:name":"Chain Store Maintenance, Inc.",
    "wof:placetype":"venue"
},
  "geometry": {"coordinates":[-71.28296899999999,41.941283],"type":"Point"}
}