{
  "type": "Feature",
  "properties": {
    "addr:full": "54 Mount Auburn St Watertown MA 02472",
    "addr:housenumber": "54",
    "addr:postcode": "02472",
    "addr:street": "Mount Auburn St",
    "iso:country": "US",
    "sg:address": "54 Mount Auburn St",
    "sg:city": "Watertown",
    "sg:classifiers": [
      {
        "category": "Restaurant",
        "type": "Food \u0026 Drink"
      }
    ],
    "sg:menulink": "http://www.allmenus.com/ma/watertown/283307-super-fusion-cuisine/menu/",
    "sg:phone": "+1 617 926 4164",
    "sg:postcode": "02472",
    "sg:province": "MA",
    "sg:tags": [
      "sushi",
      "asian"
    ],
    "wof:name": "Super Fusion Cuisine",
    "wof:placetype": "venue"
  },
  "geometry": {"coordinates":[-71.182664,42.366064],"type":"Point"}
}
