{
  "type": "Feature",
  "properties": {
    "iso:country":"US",
    "sg:address":"96 Swampscott Rd",
    "sg:city":"Salem",
    "sg:classifiers":[
        {
            "category":"Manufacturing",
            "subcategory":"Rubber & Plastics",
            "type":"Manufacturing & Wholesale Goods"
        }
    ],
    "sg:phone":"+1 978 744 8000",
    "sg:postcode":"01970",
    "sg:province":"MA",
    "wof:name":"Atlantic Extrusions Corp",
    "wof:placetype":"venue"
},
  "geometry": {"coordinates":[-70.918966,42.491936],"type":"Point"}
}