{
  "type": "Feature",
  "properties": {
    "addr:full":"42 Nonset Path Acton MA 01720",
    "addr:housenumber":"42",
    "addr:postcode":"01720",
    "addr:street":"Nonset Path",
    "iso:country":"US",
    "sg:address":"42 Nonset Path",
    "sg:city":"Acton",
    "sg:classifiers":[
        {
            "category":"Banks & Credit Unions",
            "subcategory":"Bank",
            "type":"Services"
        }
    ],
    "sg:phone":"+1 978 635 0136",
    "sg:postcode":"01720",
    "sg:province":"MA",
    "sg:tags":[
        "loan",
        "real estate"
    ],
    "sg:website":"www.bill-bowen.com",
    "wof:name":"Bill Bowen Assoc",
    "wof:placetype":"venue"
},
  "geometry": {"coordinates":[-71.43158099999999,42.519562],"type":"Point"}
}