{
  "type": "Feature",
  "properties": {
    "addr:full":"109 Randolph St South Weymouth MA 02190",
    "addr:housenumber":"109",
    "addr:postcode":"02190",
    "addr:street":"Randolph St",
    "iso:country":"US",
    "sg:address":"109 Randolph St",
    "sg:city":"South Weymouth",
    "sg:classifiers":[
        {
            "category":"Wholesale",
            "subcategory":"Beer",
            "type":"Manufacturing & Wholesale Goods"
        }
    ],
    "sg:phone":"+1 781 340 6466",
    "sg:postcode":"02190",
    "sg:province":"MA",
    "sg:tags":[
        "import"
    ],
    "wof:name":"Ace Import & Export Corp",
    "wof:placetype":"venue"
},
  "geometry": {"coordinates":[-70.96372599999999,42.170808],"type":"Point"}
}