{
  "type": "Feature",
  "properties": {
    "addr:full": "4 Ashmont St Shrewsbury MA 01545",
    "addr:housenumber": "4",
    "addr:postcode": "01545",
    "addr:street": "Ashmont St",
    "iso:country": "US",
    "sg:address": "4 Ashmont St",
    "sg:city": "Shrewsbury",
    "sg:classifiers": [
      {
        "category": "Education",
        "subcategory": "Special Training",
        "type": "Public Place"
      }
    ],
    "sg:phone": "+1   ",
    "sg:postcode": "01545",
    "sg:province": "MA",
    "wof:name": "Musical Creations",
    "wof:placetype": "venue"
  },
  "geometry": {"coordinates":[-71.695955,42.289755],"type":"Point"}
}
