{
  "type": "Feature",
  "properties": {
    "addr:full": "47 Salt Island Rd Gloucester MA 01930",
    "addr:housenumber": "47",
    "addr:postcode": "01930",
    "addr:street": "Salt Island Rd",
    "iso:country": "US",
    "sg:address": "47 Salt Island Rd",
    "sg:city": "Gloucester",
    "sg:classifiers": [
      {
        "category": "Real Estate",
        "subcategory": "Real Estate Agent",
        "type": "Services"
      }
    ],
    "sg:phone": "+1   ",
    "sg:postcode": "01930",
    "sg:province": "MA",
    "wof:name": "Roedder Enterprises Inc",
    "wof:placetype": "venue"
  },
  "geometry": {"coordinates":[-70.621609,42.623457],"type":"Point"}
}
