{
  "type": "Feature",
  "properties": {
    "iso:country":"US",
    "sg:address":"47 Salt Island Rd",
    "sg:city":"Gloucester",
    "sg:classifiers":[
        {
            "category":"Real Estate",
            "subcategory":"Real Estate Agent",
            "type":"Services"
        }
    ],
    "sg:phone":"+1   ",
    "sg:postcode":"01930",
    "sg:province":"MA",
    "wof:name":"Roedder Enterprises Inc",
    "wof:placetype":"venue"
},
  "geometry": {"coordinates":[-70.62160900000001,42.623457],"type":"Point"}
}