{
  "type": "Feature",
  "properties": {
    "addr:full":"719 Park Hill Rd Florence MA 01062",
    "addr:housenumber":"719",
    "addr:postcode":"01062",
    "addr:street":"Park Hill Rd",
    "iso:country":"US",
    "sg:address":"719 Park Hill Rd",
    "sg:city":"Florence",
    "sg:classifiers":[
        {
            "category":"Manufacturing",
            "subcategory":"Toys & Sporting Goods",
            "type":"Manufacturing & Wholesale Goods"
        }
    ],
    "sg:phone":"+1 413 478 7356",
    "sg:postcode":"01062",
    "sg:province":"MA",
    "sg:tags":[
        "goods-wholesale",
        "manufacturer"
    ],
    "wof:name":"Psi91, Inc.",
    "wof:placetype":"venue"
},
  "geometry": {"coordinates":[-72.703338,42.290159],"type":"Point"}
}