{
  "type": "Feature",
  "properties": {
    "iso:country":"US",
    "sg:address":"234 Washington St",
    "sg:city":"Hudson",
    "sg:classifiers":[
        {
            "category":"Shopping",
            "subcategory":"Pharmacy",
            "type":"Retail Goods"
        }
    ],
    "sg:phone":"+1 978 562 2663",
    "sg:postcode":"01749",
    "sg:province":"MA",
    "wof:name":"CVS Pharmacy",
    "wof:placetype":"venue"
},
  "geometry": {"coordinates":[-71.56876,42.382698],"type":"Point"}
}