{
  "type": "Feature",
  "properties": {
    "addr:full": "454 Broadway Hanover MA 02339",
    "addr:housenumber": "454",
    "addr:postcode": "02339",
    "addr:street": "Broadway",
    "iso:country": "US",
    "sg:address": "454 Broadway",
    "sg:city": "Hanover",
    "sg:classifiers": [
      {
        "category": "Professional",
        "type": "Services"
      }
    ],
    "sg:phone": "+1   ",
    "sg:postcode": "02339",
    "sg:province": "MA",
    "wof:name": "Ridder Building",
    "wof:placetype": "venue"
  },
  "geometry": {"coordinates":[-70.824614,42.108483],"type":"Point"}
}
