{
  "type": "Feature",
  "properties": {
    "addr:full": "100 Hawthorn St Newton MA 02458",
    "addr:housenumber": "100",
    "addr:postcode": "02458",
    "addr:street": "Hawthorn St",
    "iso:country": "US",
    "sg:address": "100 Hawthorn St",
    "sg:city": "Newton",
    "sg:classifiers": [
      {
        "category": "Insurance",
        "subcategory": "Insurance Agent",
        "type": "Services"
      }
    ],
    "sg:phone": "+1 617 969 9350",
    "sg:postcode": "02458",
    "sg:province": "MA",
    "wof:name": "Gerald Leone Insurance",
    "wof:placetype": "venue"
  },
  "geometry": {"coordinates":[-71.200381,42.356888],"type":"Point"}
}
