{
  "type": "Feature",
  "properties": {
    "iso:country":"US",
    "sg:address":"265 S Meadow Rd",
    "sg:city":"Plymouth",
    "sg:classifiers":[
        {
            "category":"Bakery",
            "type":"Food & Drink"
        },
        {
            "category":"Coffee & Tea",
            "type":"Food & Drink"
        },
        {
            "category":"Bagels",
            "type":"Food & Drink"
        },
        {
            "category":"Donuts",
            "type":"Food & Drink"
        }
    ],
    "sg:menulink":"http://www.allmenus.com/ma/plymouth/143259-dunkin-donuts/menu/",
    "sg:phone":"+1 508 747 4929",
    "sg:postcode":"02360",
    "sg:province":"MA",
    "sg:tags":[
        "american",
        "diner",
        "pastry"
    ],
    "wof:name":"Dunkin' Donuts",
    "wof:placetype":"venue"
},
  "geometry": {"coordinates":[-70.73742300000001,41.912299],"type":"Point"}
}