{
  "type": "Feature",
  "properties": {
    "iso:country":"US",
    "sg:address":"485 Westgate Dr Fl 2",
    "sg:city":"Brockton",
    "sg:classifiers":[
        {
            "category":"Professional",
            "subcategory":"Accounting & Tax Preparation",
            "type":"Services"
        }
    ],
    "sg:phone":"+1 508 588 1750",
    "sg:postcode":"02301",
    "sg:province":"MA",
    "sg:tags":[
        "accountant"
    ],
    "wof:name":"Sullivan Paul E CPA",
    "wof:placetype":"venue"
},
  "geometry": {"coordinates":[-71.054298,42.092602],"type":"Point"}
}