{
  "type": "Feature",
  "properties": {
    "addr:full":"47 Mount Auburn St Cambridge MA 02138",
    "addr:housenumber":"47",
    "addr:postcode":"02138",
    "addr:street":"Mount Auburn St",
    "iso:country":"US",
    "sg:address":"47 Mount Auburn St",
    "sg:city":"Cambridge",
    "sg:classifiers":[
        {
            "category":"Food & Beverages",
            "subcategory":"Groceries & Convenience Stores",
            "type":"Retail Goods"
        }
    ],
    "sg:phone":"+1 617 234 0048",
    "sg:postcode":"02138",
    "sg:province":"MA",
    "wof:name":"Tommy's Value",
    "wof:placetype":"venue"
},
  "geometry": {"coordinates":[-71.11644099999999,42.371202],"type":"Point"}
}