{
  "type": "Feature",
  "properties": {
    "addr:full": "125 Summer St Boston MA 02110",
    "addr:housenumber": "125",
    "addr:postcode": "02110",
    "addr:street": "Summer St",
    "iso:country": "US",
    "sg:address": "125 Summer St",
    "sg:city": "Boston",
    "sg:classifiers": [
      {
        "category": "Real Estate",
        "subcategory": "Real Estate Agent",
        "type": "Services"
      }
    ],
    "sg:phone": "+1 617 330 6900",
    "sg:postcode": "02110",
    "sg:province": "MA",
    "sg:website": "www.gvaboston.com",
    "wof:name": "GVA Thompson Doyle Hennessey",
    "wof:placetype": "venue"
  },
  "geometry": {"coordinates":[-71.05757,42.353354],"type":"Point"}
}
