{
  "type": "Feature",
  "properties": {
    "addr:full": "203 Bechan Rd Oakham MA 01068",
    "addr:housenumber": "203",
    "addr:postcode": "01068",
    "addr:street": "Bechan Rd",
    "iso:country": "US",
    "sg:address": "203 Bechan Rd",
    "sg:city": "Oakham",
    "sg:classifiers": [
      {
        "category": "Travel",
        "subcategory": "Campground",
        "type": "Entertainment"
      }
    ],
    "sg:phone": "+1 508 882 9509",
    "sg:postcode": "01068",
    "sg:province": "MA",
    "sg:website": "www.pineacresresort.com",
    "wof:name": "Pine Acres Family Camping",
    "wof:placetype": "venue"
  },
  "geometry": {"coordinates":[-72.026296,42.34075],"type":"Point"}
}
