{
  "type": "Feature",
  "properties": {
    "addr:full":"1364 Beacon St Brookline MA 02446",
    "addr:housenumber":"1364",
    "addr:postcode":"02446",
    "addr:street":"Beacon St",
    "iso:country":"US",
    "sg:address":"1364 Beacon St",
    "sg:city":"Brookline",
    "sg:classifiers":[
        {
            "category":"Shopping",
            "subcategory":"Clothing, Apparel, & Fashions",
            "type":"Retail Goods"
        }
    ],
    "sg:phone":"+1 781 848 6188",
    "sg:postcode":"02446",
    "sg:province":"MA",
    "sg:tags":[
        "clothing",
        "women's"
    ],
    "sg:website":"www.ladygrace.com",
    "wof:name":"Lady Grace",
    "wof:placetype":"venue"
},
  "geometry": {"coordinates":[-71.12299299999999,42.341766],"type":"Point"}
}