{
  "type": "Feature",
  "properties": {
    "iso:country":"US",
    "sg:address":"81 Prospect St",
    "sg:city":"Gloucester",
    "sg:classifiers":[
        {
            "category":"Real Estate",
            "subcategory":"Architect",
            "type":"Services"
        }
    ],
    "sg:phone":"+1 978 281 7264",
    "sg:postcode":"01930",
    "sg:province":"MA",
    "wof:name":"Taormina Architects & Builders",
    "wof:placetype":"venue"
},
  "geometry": {"coordinates":[-70.661896,42.615325],"type":"Point"}
}