{
  "type": "Feature",
  "properties": {
    "addr:full":"14 Morgan Way Tyngsboro MA 01879",
    "addr:housenumber":"14",
    "addr:postcode":"01879",
    "addr:street":"Morgan Way",
    "iso:country":"US",
    "sg:address":"14 Morgan Way",
    "sg:city":"Tyngsboro",
    "sg:classifiers":[
        {
            "category":"Health Services",
            "subcategory":"Clinic",
            "type":"Services"
        }
    ],
    "sg:phone":"+1 978 649 7517",
    "sg:postcode":"01879",
    "sg:province":"MA",
    "sg:tags":[
        "education"
    ],
    "sg:website":"www.mahima.org",
    "wof:name":"Mass Health Information Mgmt",
    "wof:placetype":"venue"
},
  "geometry": {"coordinates":[-71.45355600000001,42.653316],"type":"Point"}
}