{
  "type": "Feature",
  "properties": {
    "iso:country":"US",
    "sg:address":"34 Old Grafton Rd",
    "sg:city":"North Grafton",
    "sg:classifiers":[
        {
            "category":"Real Estate",
            "subcategory":"Real Estate Agent",
            "type":"Services"
        }
    ],
    "sg:phone":"+1 508 839 0228",
    "sg:postcode":"01568",
    "sg:province":"MA",
    "wof:name":"Coldwell Banker",
    "wof:placetype":"venue"
},
  "geometry": {"coordinates":[-71.63616,42.177994],"type":"Point"}
}