{
  "type": "Feature",
  "properties": {
    "addr:full":"201 Alewife Brook Pkwy Cambridge MA 02138",
    "addr:housenumber":"201",
    "addr:postcode":"02138",
    "addr:street":"Alewife Brook Pkwy",
    "iso:country":"US",
    "sg:address":"201 Alewife Brook Pkwy",
    "sg:city":"Cambridge",
    "sg:classifiers":[
        {
            "category":"Restaurant",
            "type":"Food & Drink"
        }
    ],
    "sg:phone":"+1 617 661 3366",
    "sg:postcode":"02138",
    "sg:province":"MA",
    "sg:tags":[
        "pizza"
    ],
    "sg:website":"cheddarspizzeria.com",
    "wof:name":"Cheddars Pizzeria",
    "wof:placetype":"venue"
},
  "geometry": {"coordinates":[-71.142077,42.390194],"type":"Point"}
}