{
  "type": "Feature",
  "properties": {
    "addr:full": "61 Medford Street Somerville MA 02143",
    "addr:housenumber": "61",
    "addr:postcode": "02143",
    "addr:street": "Medford Street",
    "iso:country": "US",
    "ovtr:label": "Somerville-Cambridge Elder Services, 61 Medford St Somerville MA US",
    "ovtr:similarity": 3.029038906097412,
    "sg:address": "61 Medford Street",
    "sg:city": "Somerville",
    "sg:classifiers": [
      {
        "category": "Sports \u0026 Exercise",
        "subcategory": "Gym",
        "type": "Entertainment"
      }
    ],
    "sg:phone": "+1 617 628 2601",
    "sg:postcode": "02143",
    "sg:province": "MA",
    "sg:tags": [
      "trainer"
    ],
    "sg:website": "www.eldercare.org",
    "wof:name": "Somerville-Cambridge Elder Services",
    "wof:placetype": "venue"
  },
  "geometry": {"coordinates":[-71.102377,42.385075],"type":"Point"}
}
