{
  "type": "Feature",
  "properties": {
    "iso:country":"US",
    "sg:address":"61 Medford Street",
    "sg:city":"Somerville",
    "sg:classifiers":[
        {
            "category":"Sports & Exercise",
            "subcategory":"Gym",
            "type":"Entertainment"
        }
    ],
    "sg:phone":"+1 617 628 2601",
    "sg:postcode":"02143",
    "sg:province":"MA",
    "sg:tags":[
        "trainer"
    ],
    "sg:website":"www.eldercare.org",
    "wof:name":"Somerville-Cambridge Elder Services",
    "wof:placetype":"venue"
},
  "geometry": {"coordinates":[-71.102377,42.385075],"type":"Point"}
}