{
  "type": "Feature",
  "properties": {
    "addr:full": "153 Mount Auburn St Watertown MA 02472",
    "addr:housenumber": "153",
    "addr:postcode": "02472",
    "addr:street": "Mount Auburn St",
    "iso:country": "US",
    "sg:address": "153 Mount Auburn St",
    "sg:city": "Watertown",
    "sg:classifiers": [
      {
        "category": "Shopping",
        "subcategory": "Computers \u0026 Home Electronics",
        "type": "Retail Goods"
      }
    ],
    "sg:phone": "+1 617 923 0735",
    "sg:postcode": "02472",
    "sg:province": "MA",
    "sg:tags": [
      "equipment",
      "metal",
      "locating"
    ],
    "wof:name": "Whites Metal Detectors",
    "wof:placetype": "venue"
  },
  "geometry": {"coordinates":[-71.17789,42.368162],"type":"Point"}
}
