{
  "type": "Feature",
  "properties": {
    "addr:full":"31 Franklin St Fall River MA 02720",
    "addr:housenumber":"31",
    "addr:postcode":"02720",
    "addr:street":"Franklin St",
    "iso:country":"US",
    "sg:address":"31 Franklin St",
    "sg:city":"Fall River",
    "sg:classifiers":[
        {
            "category":"Social Services",
            "type":"Services"
        }
    ],
    "sg:phone":"+1 508 672 9197",
    "sg:postcode":"02720",
    "sg:province":"MA",
    "sg:tags":[
        "organization",
        "welfare"
    ],
    "wof:name":"Police Athletic League",
    "wof:placetype":"venue"
},
  "geometry": {"coordinates":[-71.154308,41.70332],"type":"Point"}
}