{
  "type": "Feature",
  "properties": {
    "addr:full":"1254 S Main St Palmer MA 01069",
    "addr:housenumber":"1254",
    "addr:postcode":"01069",
    "addr:street":"S Main St",
    "iso:country":"US",
    "sg:address":"1254 S Main St",
    "sg:city":"Palmer",
    "sg:classifiers":[
        {
            "category":"Manufacturing",
            "subcategory":"Apparel",
            "type":"Manufacturing & Wholesale Goods"
        }
    ],
    "sg:phone":"+1 413 283 8731",
    "sg:postcode":"01069",
    "sg:province":"MA",
    "sg:tags":[
        "emblem"
    ],
    "wof:name":"Palmer Emblem Co",
    "wof:placetype":"venue"
},
  "geometry": {"coordinates":[-72.325872,42.154186],"type":"Point"}
}