{
  "type": "Feature",
  "properties": {
    "iso:country":"US",
    "sg:address":"357 Boylston St",
    "sg:city":"Brookline",
    "sg:classifiers":[
        {
            "category":"Personal",
            "type":"Services"
        }
    ],
    "sg:phone":"+1 617 232 7997",
    "sg:postcode":"02445",
    "sg:province":"MA",
    "sg:tags":[
        "wear",
        "formal"
    ],
    "wof:name":"Mr Tux",
    "wof:placetype":"venue"
},
  "geometry": {"coordinates":[-71.127054,42.330012],"type":"Point"}
}