{
  "type": "Feature",
  "properties": {
    "iso:country":"US",
    "sg:address":"240 Longwood Ave",
    "sg:city":"Boston",
    "sg:classifiers":[
        {
            "category":"Organizations",
            "subcategory":"Professional Association",
            "type":"Services"
        }
    ],
    "sg:phone":"+1 617 432 6171",
    "sg:postcode":"02115",
    "sg:province":"MA",
    "wof:name":"Dale N Larson",
    "wof:placetype":"venue"
},
  "geometry": {"coordinates":[-71.10343899999999,42.33712],"type":"Point"}
}