{
  "type": "Feature",
  "properties": {
    "addr:full":"1 Faneuil Hall Sq Ste 1 Boston MA 02109",
    "addr:housenumber":"1",
    "addr:postcode":"02109",
    "addr:street":"Faneuil Hall Sq Ste 1",
    "iso:country":"US",
    "sg:address":"1 Faneuil Hall Sq Ste 1",
    "sg:city":"Boston",
    "sg:classifiers":[
        {
            "category":"Professional",
            "subcategory":"Business Services",
            "type":"Services"
        },
        {
            "category":"Government",
            "subcategory":"Post Office",
            "type":"Public Place"
        }
    ],
    "sg:phone":"+1 800 275 8777",
    "sg:postcode":"02109",
    "sg:province":"MA",
    "sg:tags":[
        "mail",
        "shipping"
    ],
    "sg:website":"http://www.usps.com",
    "wof:name":"USPS - United States Post Office - Faneuil Hall Retail Unit",
    "wof:placetype":"venue"
},
  "geometry": {"coordinates":[-71.05579400000001,42.359959],"type":"Point"}
}