{
  "type": "Feature",
  "properties": {
    "addr:full": "1956 Purchase St New Bedford MA 02740",
    "addr:housenumber": "1956",
    "addr:postcode": "02740",
    "addr:street": "Purchase St",
    "iso:country": "US",
    "sg:address": "1956 Purchase St",
    "sg:city": "New Bedford",
    "sg:classifiers": [
      {
        "category": "Shopping",
        "subcategory": "Used Merchandise",
        "type": "Retail Goods"
      }
    ],
    "sg:phone": "+1 508 984 5810",
    "sg:postcode": "02740",
    "sg:province": "MA",
    "sg:tags": [
      "pawnbroker"
    ],
    "wof:name": "Benjys Pawn Shop",
    "wof:placetype": "venue"
  },
  "geometry": {"coordinates":[-70.929302,41.651303],"type":"Point"}
}
