{
  "type": "Feature",
  "properties": {
    "iso:country":"US",
    "sg:address":"37 1/2 Forrester St The Professional Bldg",
    "sg:city":"Newburyport",
    "sg:classifiers":[
        {
            "category":"Health Services",
            "subcategory":"Dentist",
            "type":"Services"
        }
    ],
    "sg:phone":"+1 978 462 9611",
    "sg:postcode":"01950",
    "sg:province":"MA",
    "sg:website":"www.newburyportdental.com",
    "wof:name":"Newburyport Dental Associates",
    "wof:placetype":"venue"
},
  "geometry": {"coordinates":[-70.877275,42.812591],"type":"Point"}
}