{
  "type": "Feature",
  "properties": {
    "iso:country":"US",
    "sg:address":"27 Mattakeesett St",
    "sg:city":"Pembroke",
    "sg:classifiers":[
        {
            "category":"Home & Garden",
            "subcategory":"Building Materials",
            "type":"Retail Goods"
        }
    ],
    "sg:phone":"+1 781 293 1010",
    "sg:postcode":"02359",
    "sg:province":"MA",
    "sg:tags":[
        "modular"
    ],
    "wof:name":"JLK & Assoc Inc",
    "wof:placetype":"venue"
},
  "geometry": {"coordinates":[-70.81340299999999,42.067457],"type":"Point"}
}