{
  "type": "Feature",
  "properties": {
    "addr:full": "27 Mattakeesett St Pembroke MA 02359",
    "addr:housenumber": "27",
    "addr:postcode": "02359",
    "addr:street": "Mattakeesett St",
    "iso:country": "US",
    "sg:address": "27 Mattakeesett St",
    "sg:city": "Pembroke",
    "sg:classifiers": [
      {
        "category": "Home \u0026 Garden",
        "subcategory": "Building Materials",
        "type": "Retail Goods"
      }
    ],
    "sg:phone": "+1 781 293 1010",
    "sg:postcode": "02359",
    "sg:province": "MA",
    "sg:tags": [
      "modular"
    ],
    "wof:name": "JLK \u0026 Assoc Inc",
    "wof:placetype": "venue"
  },
  "geometry": {"coordinates":[-70.813403,42.067457],"type":"Point"}
}
