{
  "type": "Feature",
  "properties": {
    "iso:country":"US",
    "sg:address":"74 Cushing St",
    "sg:city":"Hingham",
    "sg:classifiers":[
        {
            "category":"Freight",
            "type":"Transportation"
        }
    ],
    "sg:phone":"+1 781 749 2199",
    "sg:postcode":"02043",
    "sg:province":"MA",
    "sg:tags":[
        "building",
        "house",
        "mover"
    ],
    "wof:name":"James J Gordon Inc",
    "wof:placetype":"venue"
},
  "geometry": {"coordinates":[-70.890642,42.204495],"type":"Point"}
}