{
  "type": "Feature",
  "properties": {
    "iso:country":"US",
    "sg:address":"1 Boston Pl",
    "sg:city":"Boston",
    "sg:classifiers":[
        {
            "category":"Professional",
            "subcategory":"Lawyer & Legal Services",
            "type":"Services"
        }
    ],
    "sg:phone":"+1 617 367 2501",
    "sg:postcode":"02108",
    "sg:province":"MA",
    "wof:name":"Griffin Wm F Jr Atty",
    "wof:placetype":"venue"
},
  "geometry": {"coordinates":[-71.065102,42.3577],"type":"Point"}
}