{
  "type": "Feature",
  "properties": {
    "iso:country":"US",
    "sg:address":"372 Stevens St",
    "sg:city":"Fall River",
    "sg:classifiers":[
        {
            "category":"Manufacturing",
            "subcategory":"Textiles",
            "type":"Manufacturing & Wholesale Goods"
        }
    ],
    "sg:phone":"+1 508 674 4611",
    "sg:postcode":"02721",
    "sg:province":"MA",
    "sg:tags":[
        "finishing"
    ],
    "wof:name":"Swan Dyeing Print Corp",
    "wof:placetype":"venue"
},
  "geometry": {"coordinates":[-71.144775,41.676332],"type":"Point"}
}