{
  "type": "Feature",
  "properties": {
    "addr:full": "372 Stevens St Fall River MA 02721",
    "addr:housenumber": "372",
    "addr:postcode": "02721",
    "addr:street": "Stevens St",
    "iso:country": "US",
    "ovtr:label": "Swan Dyeing \u0026 Printing Corporation, 372 Stevens St Fall River MA US",
    "ovtr:similarity": 3.4567959308624268,
    "sg:address": "372 Stevens St",
    "sg:city": "Fall River",
    "sg:classifiers": [
      {
        "category": "Manufacturing",
        "subcategory": "Textiles",
        "type": "Manufacturing \u0026 Wholesale Goods"
      }
    ],
    "sg:phone": "+1 508 674 4611",
    "sg:postcode": "02721",
    "sg:province": "MA",
    "sg:tags": [
      "finishing"
    ],
    "wof:name": "Swan Dyeing Print Corp",
    "wof:placetype": "venue"
  },
  "geometry": {"coordinates":[-71.144775,41.676332],"type":"Point"}
}
