{
  "type": "Feature",
  "properties": {
    "iso:country":"US",
    "sg:address":"53 State St",
    "sg:city":"Boston",
    "sg:classifiers":[
        {
            "category":"Professional",
            "subcategory":"Lawyer & Legal Services",
            "type":"Services"
        }
    ],
    "sg:phone":"+1 617 439 3113",
    "sg:postcode":"02109",
    "sg:province":"MA",
    "sg:tags":[
        "attorney"
    ],
    "wof:name":"Richards Barry Joyce & Partner",
    "wof:placetype":"venue"
},
  "geometry": {"coordinates":[-71.05614300000001,42.358905],"type":"Point"}
}