{
  "type": "Feature",
  "properties": {
    "iso:country":"US",
    "sg:address":"40 Franklin St",
    "sg:city":"Danvers",
    "sg:classifiers":[
        {
            "category":"Personal",
            "subcategory":"Beauty Salon",
            "type":"Services"
        }
    ],
    "sg:phone":"+1 978 777 0068",
    "sg:postcode":"01923",
    "sg:province":"MA",
    "sg:tags":[
        "shop"
    ],
    "wof:name":"Town & Country Coiffures",
    "wof:placetype":"venue"
},
  "geometry": {"coordinates":[-70.933792,42.567184],"type":"Point"}
}