{
  "type": "Feature",
  "properties": {
    "iso:country":"US",
    "sg:address":"5 Broadway",
    "sg:city":"Beverly",
    "sg:classifiers":[
        {
            "category":"Real Estate",
            "subcategory":"Real Estate Agent",
            "type":"Services"
        }
    ],
    "sg:phone":"+1 978 922 4850",
    "sg:postcode":"01915",
    "sg:province":"MA",
    "sg:tags":[
        "management"
    ],
    "wof:name":"Cabot Co",
    "wof:placetype":"venue"
},
  "geometry": {"coordinates":[-70.88003999999999,42.547815],"type":"Point"}
}