{
  "type": "Feature",
  "properties": {
    "addr:full":"60 Center Sq East Longmeadow MA 01028",
    "addr:housenumber":"60",
    "addr:postcode":"01028",
    "addr:street":"Center Sq",
    "iso:country":"US",
    "sg:address":"60 Center Sq",
    "sg:city":"East Longmeadow",
    "sg:classifiers":[
        {
            "category":"Government",
            "subcategory":"Office",
            "type":"Public Place"
        }
    ],
    "sg:phone":"+1 413 525 5420",
    "sg:postcode":"01028",
    "sg:province":"MA",
    "sg:tags":[
        "village"
    ],
    "wof:name":"East Longmeadow Planning",
    "wof:placetype":"venue"
},
  "geometry": {"coordinates":[-72.513175,42.064559],"type":"Point"}
}