{
  "type": "Feature",
  "properties": {
    "addr:full": "103 Center St Bridgewater MA 02324",
    "addr:housenumber": "103",
    "addr:postcode": "02324",
    "addr:street": "Center St",
    "iso:country": "US",
    "ovtr:label": "St Thomas Aquinas Church, 103 Center St Bridgewater MA US",
    "ovtr:similarity": 2.6982710361480713,
    "sg:address": "103 Center St",
    "sg:city": "Bridgewater",
    "sg:classifiers": [
      {
        "category": "Organizations",
        "subcategory": "Religious Organization",
        "type": "Services"
      }
    ],
    "sg:phone": "+1 508 697 9528",
    "sg:postcode": "02324",
    "sg:province": "MA",
    "sg:tags": [
      "church"
    ],
    "wof:name": "St Thomas Aquinas Church",
    "wof:placetype": "venue"
  },
  "geometry": {"coordinates":[-70.988452,41.996944],"type":"Point"}
}
