{
  "type": "Feature",
  "properties": {
    "iso:country":"US",
    "sg:address":"103 Center St",
    "sg:city":"Bridgewater",
    "sg:classifiers":[
        {
            "category":"Organizations",
            "subcategory":"Religious Organization",
            "type":"Services"
        }
    ],
    "sg:phone":"+1 508 697 9528",
    "sg:postcode":"02324",
    "sg:province":"MA",
    "sg:tags":[
        "church"
    ],
    "wof:name":"St Thomas Aquinas Church",
    "wof:placetype":"venue"
},
  "geometry": {"coordinates":[-70.988452,41.996944],"type":"Point"}
}