{
  "type": "Feature",
  "properties": {
    "addr:full":"22 Central Sq Cambridge MA 02139",
    "addr:housenumber":"22",
    "addr:postcode":"02139",
    "addr:street":"Central Sq",
    "iso:country":"US",
    "sg:address":"22 Central Sq",
    "sg:city":"Cambridge",
    "sg:classifiers":[
        {
            "category":"Restaurant",
            "type":"Food & Drink"
        }
    ],
    "sg:menulink":"http://www.allmenus.com/ma/cambridge/229507-sonny-notos-restaurant/menu/",
    "sg:phone":"+1 617 569 2003",
    "sg:postcode":"02139",
    "sg:province":"MA",
    "sg:tags":[
        "american",
        "italian"
    ],
    "wof:name":"Sonny Noto's Restaurant",
    "wof:placetype":"venue"
},
  "geometry": {"coordinates":[-71.107174,42.365138],"type":"Point"}
}