{
  "type": "Feature",
  "properties": {
    "addr:full": "69 River St West Newton MA 02465",
    "addr:housenumber": "69",
    "addr:postcode": "02465",
    "addr:street": "River St",
    "iso:country": "US",
    "sg:address": "69 River St",
    "sg:city": "West Newton",
    "sg:classifiers": [
      {
        "category": "Retail",
        "subcategory": "Repair Shop",
        "type": "Services"
      }
    ],
    "sg:phone": "+1 617 477 0279",
    "sg:postcode": "02465",
    "sg:province": "MA",
    "sg:tags": [
      "lock",
      "locksmith"
    ],
    "wof:name": "24 7 Emergency Locksmith",
    "wof:placetype": "venue"
  },
  "geometry": {"coordinates":[-71.228182,42.352151],"type":"Point"}
}
