{
  "type": "Feature",
  "properties": {
    "addr:full":"59 Surrey St Brighton MA 02135",
    "addr:housenumber":"59",
    "addr:postcode":"02135",
    "addr:street":"Surrey St",
    "iso:country":"US",
    "sg:address":"59 Surrey St",
    "sg:city":"Brighton",
    "sg:classifiers":[
        {
            "category":"Professional",
            "subcategory":"Business Services",
            "type":"Services"
        }
    ],
    "sg:phone":"+1   ",
    "sg:postcode":"02135",
    "sg:province":"MA",
    "wof:name":"Global Busines Group Inc",
    "wof:placetype":"venue"
},
  "geometry": {"coordinates":[-71.15642099999999,42.350851],"type":"Point"}
}