{
  "type": "Feature",
  "properties": {
    "iso:country":"US",
    "sg:address":"19 W Cedar St",
    "sg:city":"Norfolk",
    "sg:classifiers":[
        {
            "category":"Building & Trades",
            "subcategory":"Electrical",
            "type":"Services"
        }
    ],
    "sg:phone":"+1 508 989 8195",
    "sg:postcode":"02056",
    "sg:province":"MA",
    "sg:tags":[
        "electrician",
        "contractor"
    ],
    "wof:name":"Aronne Electric",
    "wof:placetype":"venue"
},
  "geometry": {"coordinates":[-71.320762,42.091818],"type":"Point"}
}