{
  "type": "Feature",
  "properties": {
    "iso:country":"US",
    "sg:address":"7 Westford Rd",
    "sg:city":"Tyngsboro",
    "sg:classifiers":[
        {
            "category":"Real Estate",
            "subcategory":"Real Estate Agent",
            "type":"Services"
        }
    ],
    "sg:phone":"+1 978 649 6030",
    "sg:postcode":"01879",
    "sg:province":"MA",
    "wof:name":"Century 21",
    "wof:placetype":"venue"
},
  "geometry": {"coordinates":[-71.420878,42.671206],"type":"Point"}
}