{
  "type": "Feature",
  "properties": {
    "addr:full": "Burlington Mall 75 Middlesex Turnpike Burlington MA 01803",
    "addr:housenumber": "75",
    "addr:postcode": "01803",
    "addr:street": "Middlesex Turnpike",
    "iso:country": "US",
    "sg:address": "Burlington Mall 75 Middlesex Turnpike",
    "sg:city": "Burlington",
    "sg:classifiers": [
      {
        "category": "Restaurant",
        "type": "Food \u0026 Drink"
      },
      {
        "category": "Food \u0026 Beverages",
        "subcategory": "Meat \u0026 Fish",
        "type": "Retail Goods"
      }
    ],
    "sg:phone": "+1 781 270 9700",
    "sg:postcode": "01803",
    "sg:province": "MA",
    "sg:tags": [
      "seafood",
      "market"
    ],
    "sg:website": "www.legalseafoods.com/",
    "wof:name": "Legal Sea Foods",
    "wof:placetype": "venue"
  },
  "geometry": {"coordinates":[-71.214389,42.482111],"type":"Point"}
}
