{
  "type": "Feature",
  "properties": {
    "iso:country":"US",
    "sg:address":"1095 Great Plain Ave",
    "sg:city":"Needham",
    "sg:classifiers":[
        {
            "category":"Utilities",
            "subcategory":"Mobile Phone",
            "type":"Services"
        }
    ],
    "sg:phone":"+1 781 444 2534",
    "sg:postcode":"02492",
    "sg:province":"MA",
    "sg:tags":[
        "telephone",
        "cellular"
    ],
    "wof:name":"Nextel K Communications",
    "wof:placetype":"venue"
},
  "geometry": {"coordinates":[-71.238647,42.280294],"type":"Point"}
}