{
  "type": "Feature",
  "properties": {
    "addr:full":"396 Brockton Ave Abington MA 02351",
    "addr:housenumber":"396",
    "addr:postcode":"02351",
    "addr:street":"Brockton Ave",
    "iso:country":"US",
    "sg:address":"396 Brockton Ave",
    "sg:city":"Abington",
    "sg:classifiers":[
        {
            "category":"Restaurant",
            "type":"Food & Drink"
        }
    ],
    "sg:phone":"+1 781 878 7774",
    "sg:postcode":"02351",
    "sg:province":"MA",
    "wof:name":"Ming Fang Garden",
    "wof:placetype":"venue"
},
  "geometry": {"coordinates":[-70.959394,42.10067],"type":"Point"}
}