{
  "type": "Feature",
  "properties": {
    "addr:full":"82 Tarbell Spring Rd Concord MA 01742",
    "addr:housenumber":"82",
    "addr:postcode":"01742",
    "addr:street":"Tarbell Spring Rd",
    "iso:country":"US",
    "sg:address":"82 Tarbell Spring Rd",
    "sg:city":"Concord",
    "sg:classifiers":[
        {
            "category":"Building & Trades",
            "subcategory":"Construction",
            "type":"Services"
        }
    ],
    "sg:phone":"+1 508 759 2076",
    "sg:postcode":"01742",
    "sg:province":"MA",
    "sg:tags":[
        "concrete",
        "contractor"
    ],
    "wof:name":"National Concrete Tanks LLC",
    "wof:placetype":"venue"
},
  "geometry": {"coordinates":[-71.39735,42.447942],"type":"Point"}
}