{
  "type": "Feature",
  "properties": {
    "addr:full": "996 Blue Hill Ave Dorchester Ctr MA 02124",
    "addr:housenumber": "996",
    "addr:postcode": "02124",
    "addr:street": "Blue Hill Ave Dorchester Ctr",
    "iso:country": "US",
    "sg:address": "996 Blue Hill Ave",
    "sg:city": "Dorchester Ctr",
    "sg:classifiers": [
      {
        "category": "Personal",
        "subcategory": "Beauty Salon",
        "type": "Services"
      }
    ],
    "sg:phone": "+1 617 265 7778",
    "sg:postcode": "02124",
    "sg:province": "MA",
    "wof:name": "Complex Hair Design Inc",
    "wof:placetype": "venue"
  },
  "geometry": {"coordinates":[-71.08934,42.289982],"type":"Point"}
}
