{
  "type": "Feature",
  "properties": {
    "iso:country":"US",
    "sg:address":"996 Blue Hill Ave",
    "sg:city":"Dorchester Ctr",
    "sg:classifiers":[
        {
            "category":"Personal",
            "subcategory":"Beauty Salon",
            "type":"Services"
        }
    ],
    "sg:phone":"+1 617 265 7778",
    "sg:postcode":"02124",
    "sg:province":"MA",
    "wof:name":"Complex Hair Design Inc",
    "wof:placetype":"venue"
},
  "geometry": {"coordinates":[-71.08934000000001,42.289982],"type":"Point"}
}