{
  "type": "Feature",
  "properties": {
    "addr:full":"229 Berkeley St Boston MA 02116",
    "addr:housenumber":"229",
    "addr:postcode":"02116",
    "addr:street":"Berkeley St",
    "iso:country":"US",
    "sg:address":"229 Berkeley St",
    "sg:city":"Boston",
    "sg:classifiers":[
        {
            "category":"Building & Trades",
            "subcategory":"Locksmith",
            "type":"Services"
        }
    ],
    "sg:phone":"+1 617 895 3412",
    "sg:postcode":"02116",
    "sg:province":"MA",
    "sg:tags":[
        "key"
    ],
    "wof:name":"24 Hours A Locksmith",
    "wof:placetype":"venue"
},
  "geometry": {"coordinates":[-71.072982,42.351479],"type":"Point"}
}