{
  "type": "Feature",
  "properties": {
    "iso:country":"US",
    "sg:address":"50 Williams St",
    "sg:city":"Taunton",
    "sg:classifiers":[
        {
            "category":"Education",
            "subcategory":"School",
            "type":"Public Place"
        }
    ],
    "sg:phone":"+1 508 821 1111",
    "sg:postcode":"02780",
    "sg:province":"MA",
    "sg:website":"www.tauntonschools.org",
    "wof:name":"John F Parker Middle School",
    "wof:placetype":"venue"
},
  "geometry": {"coordinates":[-71.07117700000001,41.898652],"type":"Point"}
}