{
  "type": "Feature",
  "properties": {
    "addr:full": "97 Cove St New Bedford MA 02744",
    "addr:housenumber": "97",
    "addr:postcode": "02744",
    "addr:street": "Cove St",
    "iso:country": "US",
    "sg:address": "97 Cove St",
    "sg:city": "New Bedford",
    "sg:classifiers": [
      {
        "category": "Professional",
        "type": "Services"
      }
    ],
    "sg:phone": "+1 508 990 8403",
    "sg:postcode": "02744",
    "sg:province": "MA",
    "sg:tags": [
      "establishment"
    ],
    "wof:name": "J B \u0026 D Co",
    "wof:placetype": "venue"
  },
  "geometry": {"coordinates":[-70.91742,41.61627],"type":"Point"}
}
