{
  "type": "Feature",
  "properties": {
    "iso:country":"US",
    "sg:address":"5 Poplar St",
    "sg:city":"Ipswich",
    "sg:classifiers":[
        {
            "category":"Building & Trades",
            "subcategory":"Landscaping Services",
            "type":"Services"
        }
    ],
    "sg:phone":"+1 978 356 8816",
    "sg:postcode":"01938",
    "sg:province":"MA",
    "wof:name":"Prime Landscape Contractors",
    "wof:placetype":"venue"
},
  "geometry": {"coordinates":[-70.83340699999999,42.676463],"type":"Point"}
}