{
  "type": "Feature",
  "properties": {
    "iso:country":"US",
    "sg:address":"348 Hancock St",
    "sg:city":"Braintree",
    "sg:classifiers":[
        {
            "category":"Professional",
            "subcategory":"Management & Consulting",
            "type":"Services"
        }
    ],
    "sg:phone":"+1   ",
    "sg:postcode":"02184",
    "sg:province":"MA",
    "wof:name":"Matthew J Mullen Management",
    "wof:placetype":"venue"
},
  "geometry": {"coordinates":[-71.006745,42.191139],"type":"Point"}
}