{
  "type": "Feature",
  "properties": {
    "iso:country":"US",
    "sg:address":"850 Pleasant St",
    "sg:city":"New Bedford",
    "sg:classifiers":[
        {
            "category":"Health Services",
            "subcategory":"Health Practitioner",
            "type":"Services"
        }
    ],
    "sg:phone":"+1 508 997 2991",
    "sg:postcode":"02740",
    "sg:province":"MA",
    "sg:tags":[
        "nutritionist"
    ],
    "wof:name":"Coastline Nutrition Program",
    "wof:placetype":"venue"
},
  "geometry": {"coordinates":[-70.927601,41.639211],"type":"Point"}
}