{
  "type": "Feature",
  "properties": {
    "addr:full":"36 Avery Rd Holden MA 01520",
    "addr:housenumber":"36",
    "addr:postcode":"01520",
    "addr:street":"Avery Rd",
    "iso:country":"US",
    "sg:address":"36 Avery Rd",
    "sg:city":"Holden",
    "sg:classifiers":[
        {
            "category":"Professional",
            "subcategory":"Business Services",
            "type":"Services"
        }
    ],
    "sg:phone":"+1 508 798 0861",
    "sg:postcode":"01520",
    "sg:province":"MA",
    "sg:tags":[
        "holding"
    ],
    "wof:name":"Octagon Corp",
    "wof:placetype":"venue"
},
  "geometry": {"coordinates":[-71.86592400000001,42.344643],"type":"Point"}
}