{
  "type": "Feature",
  "properties": {
    "iso:country":"US",
    "sg:address":"650 Washington St",
    "sg:city":"Dedham",
    "sg:classifiers":[
        {
            "category":"Personal",
            "subcategory":"Beauty Salon",
            "type":"Services"
        }
    ],
    "sg:phone":"+1 781 251 6600",
    "sg:postcode":"02026",
    "sg:province":"MA",
    "sg:website":"www.keldara.com",
    "wof:name":"Keldara The Day Spa",
    "wof:placetype":"venue"
},
  "geometry": {"coordinates":[-71.17838399999999,42.241862],"type":"Point"}
}