{
  "type": "Feature",
  "properties": {
    "addr:full":"210 Charlton Rd Sturbridge MA 01566",
    "addr:housenumber":"210",
    "addr:postcode":"01566",
    "addr:street":"Charlton Rd",
    "iso:country":"US",
    "sg:address":"210 Charlton Rd",
    "sg:city":"Sturbridge",
    "sg:classifiers":[
        {
            "category":"Retail",
            "subcategory":"Auto Repair",
            "type":"Services"
        }
    ],
    "sg:phone":"+1 508 347 9116",
    "sg:postcode":"01566",
    "sg:province":"MA",
    "wof:name":"Steve's Collision Center",
    "wof:placetype":"venue"
},
  "geometry": {"coordinates":[-72.066498,42.114899],"type":"Point"}
}