{
  "type": "Feature",
  "properties": {
    "addr:full": "75 Garfield St Quincy MA 02169",
    "addr:housenumber": "75",
    "addr:postcode": "02169",
    "addr:street": "Garfield St",
    "iso:country": "US",
    "sg:address": "75 Garfield St",
    "sg:city": "Quincy",
    "sg:classifiers": [
      {
        "category": "Building \u0026 Trades",
        "subcategory": "Plumbing",
        "type": "Services"
      }
    ],
    "sg:phone": "+1 617 472 8158",
    "sg:postcode": "02169",
    "sg:province": "MA",
    "sg:tags": [
      "plumber",
      "industrial",
      "contractors-commercial"
    ],
    "wof:name": "Albert L Lewis Jr Plumber",
    "wof:placetype": "venue"
  },
  "geometry": {"coordinates":[-71.014462,42.243494],"type":"Point"}
}
