{
  "type": "Feature",
  "properties": {
    "iso:country":"US",
    "sg:address":"100 Eliot Street",
    "sg:city":"Chestnut Hill",
    "sg:classifiers":[
        {
            "category":"Education",
            "subcategory":"School",
            "type":"Public Place"
        }
    ],
    "sg:phone":"+1 617 879 4314",
    "sg:postcode":"02467",
    "sg:province":"MA",
    "sg:tags":[
        "high",
        "middle",
        "elementary"
    ],
    "wof:name":"Brookline Town of",
    "wof:placetype":"venue"
},
  "geometry": {"coordinates":[-71.146428,42.32804],"type":"Point"}
}