{
  "type": "Feature",
  "properties": {
    "addr:full":"20 Pease Point Way Edgartown MA 02539",
    "addr:housenumber":"20",
    "addr:postcode":"02539",
    "addr:street":"Pease Point Way",
    "iso:country":"US",
    "sg:address":"20 Pease Point Way",
    "sg:city":"Edgartown",
    "sg:classifiers":[
        {
            "category":"Travel",
            "subcategory":"Hotels & Motels",
            "type":"Entertainment"
        }
    ],
    "sg:phone":"+1 508 627 4671",
    "sg:postcode":"02539",
    "sg:province":"MA",
    "wof:name":"Edgartown Commons",
    "wof:placetype":"venue"
},
  "geometry": {"coordinates":[-70.514791,41.391748],"type":"Point"}
}