{
  "type": "Feature",
  "properties": {
    "addr:full":"11 Westech Dr Tyngsboro MA 01879",
    "addr:housenumber":"11",
    "addr:postcode":"01879",
    "addr:street":"Westech Dr",
    "iso:country":"US",
    "sg:address":"11 Westech Dr",
    "sg:city":"Tyngsboro",
    "sg:classifiers":[
        {
            "category":"Real Estate",
            "subcategory":"Real Estate Services",
            "type":"Services"
        },
        {
            "category":"Building & Trades",
            "subcategory":"Cleaning & Sanitation",
            "type":"Services"
        }
    ],
    "sg:phone":"+1 978 392 1135",
    "sg:postcode":"01879",
    "sg:province":"MA",
    "sg:tags":[
        "maintenance",
        "cleaners-interior"
    ],
    "wof:name":"Mobile Maids Janitorial Svcs",
    "wof:placetype":"venue"
},
  "geometry": {"coordinates":[-71.423863,42.656053],"type":"Point"}
}