{
  "type": "Feature",
  "properties": {
    "iso:country":"US",
    "sg:address":"46 Franklin St",
    "sg:city":"Northampton",
    "sg:classifiers":[
        {
            "category":"Shopping",
            "subcategory":"Books",
            "type":"Retail Goods"
        }
    ],
    "sg:phone":"+1   ",
    "sg:postcode":"01060",
    "sg:province":"MA",
    "wof:name":"Cumberland Rare Book",
    "wof:placetype":"venue"
},
  "geometry": {"coordinates":[-72.64357099999999,42.325401],"type":"Point"}
}