{
  "type": "Feature",
  "properties": {
    "addr:full":"429 Cherry Street West Newton MA 02465",
    "addr:housenumber":"429",
    "addr:postcode":"02465",
    "addr:street":"Cherry Street",
    "iso:country":"US",
    "sg:address":"429 Cherry Street",
    "sg:city":"West Newton",
    "sg:classifiers":[
        {
            "category":"Professional",
            "subcategory":"Computer Services",
            "type":"Services"
        }
    ],
    "sg:phone":"+1 617 332 9588",
    "sg:postcode":"02465",
    "sg:province":"MA",
    "sg:tags":[
        "web-design",
        "web-development",
        "web-site",
        "website",
        "boston",
        "web-designer",
        "boston-web-design-firm"
    ],
    "sg:website":"http://www.getverve.com",
    "wof:name":"Verve Creative",
    "wof:placetype":"venue"
},
  "geometry": {"coordinates":[-71.22857,42.349703],"type":"Point"}
}