{
  "type": "Feature",
  "properties": {
    "addr:full": "32 Clinton Rd Weymouth MA 02189",
    "addr:housenumber": "32",
    "addr:postcode": "02189",
    "addr:street": "Clinton Rd",
    "iso:country": "US",
    "sg:address": "32 Clinton Rd",
    "sg:city": "Weymouth",
    "sg:classifiers": [
      {
        "category": "Professional",
        "type": "Services"
      }
    ],
    "sg:phone": "+1 781 335 2231",
    "sg:postcode": "02189",
    "sg:province": "MA",
    "sg:tags": [
      "establishment"
    ],
    "wof:name": "Paul J Smith Assoc",
    "wof:placetype": "venue"
  },
  "geometry": {"coordinates":[-70.918797,42.225371],"type":"Point"}
}
