{
  "type": "Feature",
  "properties": {
    "addr:full":"5 Hoyle St Norwood MA 02062",
    "addr:housenumber":"5",
    "addr:postcode":"02062",
    "addr:street":"Hoyle St",
    "iso:country":"US",
    "sg:address":"5 Hoyle St",
    "sg:city":"Norwood",
    "sg:classifiers":[
        {
            "category":"Wholesale",
            "subcategory":"Home Furnishings",
            "type":"Manufacturing & Wholesale Goods"
        }
    ],
    "sg:phone":"+1   ",
    "sg:postcode":"02062",
    "sg:province":"MA",
    "wof:name":"Ms Sheryl A Stcroix",
    "wof:placetype":"venue"
},
  "geometry": {"coordinates":[-71.20514799999999,42.188302],"type":"Point"}
}