{
  "type": "Feature",
  "properties": {
    "addr:full": "40 Central Ave Salisbury MA 01952",
    "addr:housenumber": "40",
    "addr:postcode": "01952",
    "addr:street": "Central Ave",
    "iso:country": "US",
    "sg:address": "40 Central Ave",
    "sg:city": "Salisbury",
    "sg:classifiers": [
      {
        "category": "Travel",
        "subcategory": "Hotels \u0026 Motels",
        "type": "Entertainment"
      }
    ],
    "sg:phone": "+1 978 499 0260",
    "sg:postcode": "01952",
    "sg:province": "MA",
    "wof:name": "Michael's Oceanfront Motel",
    "wof:placetype": "venue"
  },
  "geometry": {"coordinates":[-70.817349,42.844798],"type":"Point"}
}
