{
  "type": "Feature",
  "properties": {
    "iso:country":"US",
    "sg:address":"44 Milford St",
    "sg:city":"Medway",
    "sg:classifiers":[
        {
            "category":"Government",
            "subcategory":"Fire Station",
            "type":"Public Place"
        }
    ],
    "sg:phone":"+1 508 533 3211",
    "sg:postcode":"02053",
    "sg:province":"MA",
    "sg:tags":[
        "department"
    ],
    "wof:name":"Medway Fire Dept",
    "wof:placetype":"venue"
},
  "geometry": {"coordinates":[-71.4406,42.14429],"type":"Point"}
}