{
  "type": "Feature",
  "properties": {
    "addr:full": "44 Milford St Medway MA 02053",
    "addr:housenumber": "44",
    "addr:postcode": "02053",
    "addr:street": "Milford St",
    "iso:country": "US",
    "ovtr:label": "Medway Fire Department, 44 Milford St Medway MA US",
    "ovtr:similarity": 2.8168320655822754,
    "sg:address": "44 Milford St",
    "sg:city": "Medway",
    "sg:classifiers": [
      {
        "category": "Government",
        "subcategory": "Fire Station",
        "type": "Public Place"
      }
    ],
    "sg:phone": "+1 508 533 3211",
    "sg:postcode": "02053",
    "sg:province": "MA",
    "sg:tags": [
      "department"
    ],
    "wof:name": "Medway Fire Dept",
    "wof:placetype": "venue"
  },
  "geometry": {"coordinates":[-71.4406,42.14429],"type":"Point"}
}
