{
  "type": "Feature",
  "properties": {
    "addr:full":"51 Davis St Greenfield MA 01301",
    "addr:housenumber":"51",
    "addr:postcode":"01301",
    "addr:street":"Davis St",
    "iso:country":"US",
    "sg:address":"51 Davis St",
    "sg:city":"Greenfield",
    "sg:classifiers":[
        {
            "category":"Social Services",
            "type":"Services"
        }
    ],
    "sg:phone":"+1 413 772 2168",
    "sg:postcode":"01301",
    "sg:province":"MA",
    "sg:tags":[
        "organization",
        "welfare"
    ],
    "wof:name":"United Way",
    "wof:placetype":"venue"
},
  "geometry": {"coordinates":[-72.60218999999999,42.591026],"type":"Point"}
}