{
  "type": "Feature",
  "properties": {
    "iso:country":"US",
    "sg:address":"39 Parkvale Ave",
    "sg:city":"Allston",
    "sg:classifiers":[
        {
            "category":"Professional",
            "subcategory":"Engineering",
            "type":"Services"
        }
    ],
    "sg:phone":"+1 617 787 2385",
    "sg:postcode":"02134",
    "sg:province":"MA",
    "sg:tags":[
        "engineer"
    ],
    "wof:name":"Arbat Engineering",
    "wof:placetype":"venue"
},
  "geometry": {"coordinates":[-71.13316399999999,42.352121],"type":"Point"}
}