{
  "type": "Feature",
  "properties": {
    "addr:full": "111 Bucknam St Everett MA 02149",
    "addr:housenumber": "111",
    "addr:postcode": "02149",
    "addr:street": "Bucknam St",
    "iso:country": "US",
    "sg:address": "111 Bucknam St",
    "sg:city": "Everett",
    "sg:classifiers": [
      {
        "category": "Social Services",
        "subcategory": "Adult Care",
        "type": "Services"
      }
    ],
    "sg:phone": "+1 617 389 7494",
    "sg:postcode": "02149",
    "sg:province": "MA",
    "sg:tags": [
      "home",
      "facility",
      "residential"
    ],
    "wof:name": "Everett Place",
    "wof:placetype": "venue"
  },
  "geometry": {"coordinates":[-71.060783,42.411819],"type":"Point"}
}
