{
  "type": "Feature",
  "properties": {
    "addr:full": "55 Main St Wareham MA 02571",
    "addr:housenumber": "55",
    "addr:postcode": "02571",
    "addr:street": "Main St",
    "iso:country": "US",
    "sg:address": "55 Main St",
    "sg:city": "Wareham",
    "sg:classifiers": [
      {
        "category": "Real Estate",
        "subcategory": "Real Estate Agent",
        "type": "Services"
      }
    ],
    "sg:phone": "+1 508 295 6440",
    "sg:postcode": "02571",
    "sg:province": "MA",
    "wof:name": "Wareham River Realty Trust",
    "wof:placetype": "venue"
  },
  "geometry": {"coordinates":[-70.711429,41.754682],"type":"Point"}
}
