{
  "type": "Feature",
  "properties": {
    "addr:full": "64 Wealthy Ave Pittsfield MA 01201",
    "addr:housenumber": "64",
    "addr:postcode": "01201",
    "addr:street": "Wealthy Ave",
    "iso:country": "US",
    "sg:address": "64 Wealthy Ave",
    "sg:city": "Pittsfield",
    "sg:classifiers": [
      {
        "category": "Manufacturing",
        "subcategory": "Printing",
        "type": "Manufacturing \u0026 Wholesale Goods"
      }
    ],
    "sg:phone": "+1 413 496 9638",
    "sg:postcode": "01201",
    "sg:province": "MA",
    "sg:tags": [
      "newspaper"
    ],
    "wof:name": "Animal Life Publications",
    "wof:placetype": "venue"
  },
  "geometry": {"coordinates":[-73.197199,42.452417],"type":"Point"}
}
