{
  "type": "Feature",
  "properties": {
    "iso:country":"US",
    "sg:address":"64 Wealthy Ave",
    "sg:city":"Pittsfield",
    "sg:classifiers":[
        {
            "category":"Manufacturing",
            "subcategory":"Printing",
            "type":"Manufacturing & Wholesale Goods"
        }
    ],
    "sg:phone":"+1 413 496 9638",
    "sg:postcode":"01201",
    "sg:province":"MA",
    "sg:tags":[
        "newspaper"
    ],
    "wof:name":"Animal Life Publications",
    "wof:placetype":"venue"
},
  "geometry": {"coordinates":[-73.197199,42.452417],"type":"Point"}
}