{
  "type": "Feature",
  "properties": {
    "iso:country":"US",
    "sg:address":"120 Tremont St",
    "sg:city":"Boston",
    "sg:classifiers":[
        {
            "category":"Education",
            "subcategory":"University",
            "type":"Public Place"
        }
    ],
    "sg:phone":"+1 617 573 8000",
    "sg:postcode":"02108",
    "sg:province":"MA",
    "sg:tags":[
        "college"
    ],
    "sg:website":"www.law.suffolk.edu/",
    "wof:name":"Suffolk University Law School",
    "wof:placetype":"venue"
},
  "geometry": {"coordinates":[-71.061491,42.35697],"type":"Point"}
}