{
  "type": "Feature",
  "properties": {
    "iso:country":"US",
    "sg:address":"526 Washington St",
    "sg:city":"Norwood",
    "sg:classifiers":[
        {
            "category":"Food & Beverages",
            "subcategory":"Meat & Fish",
            "type":"Retail Goods"
        }
    ],
    "sg:phone":"+1 781 769 6111",
    "sg:postcode":"02062",
    "sg:province":"MA",
    "sg:tags":[
        "seafood",
        "market"
    ],
    "wof:name":"Seagroup International Ltd",
    "wof:placetype":"venue"
},
  "geometry": {"coordinates":[-71.198645,42.197377],"type":"Point"}
}