{
  "type": "Feature",
  "properties": {
    "addr:full": "39 Orchard St Marblehead MA 01945",
    "addr:housenumber": "39",
    "addr:postcode": "01945",
    "addr:street": "Orchard St",
    "iso:country": "US",
    "sg:address": "39 Orchard St",
    "sg:city": "Marblehead",
    "sg:classifiers": [
      {
        "category": "Real Estate",
        "subcategory": "Developer",
        "type": "Services"
      }
    ],
    "sg:phone": "+1   ",
    "sg:postcode": "01945",
    "sg:province": "MA",
    "wof:name": "Young Development Corp",
    "wof:placetype": "venue"
  },
  "geometry": {"coordinates":[-70.862028,42.490969],"type":"Point"}
}
