{
  "type": "Feature",
  "properties": {
    "iso:country":"US",
    "sg:address":"8 Calumet Ave",
    "sg:city":"Worcester",
    "sg:classifiers":[
        {
            "category":"Professional",
            "type":"Services"
        }
    ],
    "sg:phone":"+1 508 852 5243",
    "sg:postcode":"01606",
    "sg:province":"MA",
    "sg:tags":[
        "establishment"
    ],
    "wof:name":"Feecon Corp",
    "wof:placetype":"venue"
},
  "geometry": {"coordinates":[-71.78493899999999,42.306666],"type":"Point"}
}