{
  "type": "Feature",
  "properties": {
    "addr:full": "38 Chauncy St 600 Boston MA 02111",
    "addr:housenumber": "38;600",
    "addr:postcode": "02111",
    "addr:street": "Chauncy St",
    "iso:country": "US",
    "sg:address": "38 Chauncy St 600",
    "sg:city": "Boston",
    "sg:classifiers": [
      {
        "category": "Professional",
        "subcategory": "Management \u0026 Consulting",
        "type": "Services"
      },
      {
        "category": "Government",
        "subcategory": "Office",
        "type": "Public Place"
      }
    ],
    "sg:phone": "+1 617 423 3114",
    "sg:postcode": "02111",
    "sg:province": "MA",
    "sg:tags": [
      "consultant",
      "resource",
      "human"
    ],
    "wof:name": "Affordable Housing",
    "wof:placetype": "venue"
  },
  "geometry": {"coordinates":[-71.060103,42.353698],"type":"Point"}
}
