{
  "type": "Feature",
  "properties": {
    "addr:full":"1826-1830 Washington St Boston MA 02118",
    "addr:housenumber":"1826-1830",
    "addr:postcode":"02118",
    "addr:street":"Washington St",
    "iso:country":"US",
    "sg:address":"1826-1830 Washington St",
    "sg:city":"Boston",
    "sg:classifiers":[
        {
            "category":"Shopping",
            "subcategory":"Beauty & Cosmetics",
            "type":"Retail Goods"
        }
    ],
    "sg:phone":"+1 617 442 1600",
    "sg:postcode":"02118",
    "sg:province":"MA",
    "sg:tags":[
        "supply"
    ],
    "wof:name":"Hair Stop Roxbury",
    "wof:placetype":"venue"
},
  "geometry": {"coordinates":[-71.078193,42.335576],"type":"Point"}
}