{
  "type": "Feature",
  "properties": {
    "addr:full": "33 West St Northampton MA 01060",
    "addr:housenumber": "33",
    "addr:postcode": "01060",
    "addr:street": "West St",
    "iso:country": "US",
    "sg:address": "33 West St",
    "sg:city": "Northampton",
    "sg:classifiers": [
      {
        "category": "Personal",
        "subcategory": "Massage",
        "type": "Services"
      }
    ],
    "sg:phone": "+1 413 587 0000",
    "sg:postcode": "01060",
    "sg:province": "MA",
    "sg:tags": [
      "therapist"
    ],
    "wof:name": "Paradise Spa",
    "wof:placetype": "venue"
  },
  "geometry": {"coordinates":[-72.63658,42.316108],"type":"Point"}
}
