{
  "type": "Feature",
  "properties": {
    "iso:country":"US",
    "sg:address":"1600 Beacon Street",
    "sg:city":"Brookline",
    "sg:classifiers":[
        {
            "category":"Professional",
            "subcategory":"Computer Services",
            "type":"Services"
        }
    ],
    "sg:phone":"+1   ",
    "sg:postcode":"02446",
    "sg:province":"MA",
    "wof:name":"Jumbo Solutions Inc",
    "wof:placetype":"venue"
},
  "geometry": {"coordinates":[-71.13448,42.33982],"type":"Point"}
}