{
  "type": "Feature",
  "properties": {
    "iso:country":"US",
    "sg:address":"52 Central Sq",
    "sg:city":"Lynn",
    "sg:classifiers":[
        {
            "category":"Shopping",
            "subcategory":"Books",
            "type":"Retail Goods"
        }
    ],
    "sg:phone":"+1 781 477 0444",
    "sg:postcode":"01901",
    "sg:province":"MA",
    "sg:tags":[
        "dealer"
    ],
    "wof:name":"Ex Libris Inc",
    "wof:placetype":"venue"
},
  "geometry": {"coordinates":[-70.945148,42.463924],"type":"Point"}
}