{
  "type": "Feature",
  "properties": {
    "addr:full": "18 Boutin Ct Chicopee MA 01020",
    "addr:housenumber": "18",
    "addr:postcode": "01020",
    "addr:street": "Boutin Ct",
    "iso:country": "US",
    "sg:address": "18 Boutin Ct",
    "sg:city": "Chicopee",
    "sg:classifiers": [
      {
        "category": "Local Transit",
        "type": "Transportation"
      }
    ],
    "sg:phone": "+1   ",
    "sg:postcode": "01020",
    "sg:province": "MA",
    "sg:tags": [
      "passenger",
      "transport"
    ],
    "wof:name": "Ajc Limousine Service",
    "wof:placetype": "venue"
  },
  "geometry": {"coordinates":[-72.571885,42.19018],"type":"Point"}
}
