{
  "type": "Feature",
  "properties": {
    "addr:full":"101 University Dr Amherst MA 01002",
    "addr:housenumber":"101",
    "addr:postcode":"01002",
    "addr:street":"University Dr",
    "iso:country":"US",
    "sg:address":"101 University Dr",
    "sg:city":"Amherst",
    "sg:classifiers":[
        {
            "category":"Health Services",
            "subcategory":"Optometrist",
            "type":"Services"
        }
    ],
    "sg:phone":"+1 413 549 2614",
    "sg:postcode":"01002",
    "sg:province":"MA",
    "wof:name":"Robert E Delany OD",
    "wof:placetype":"venue"
},
  "geometry": {"coordinates":[-72.532031,42.378867],"type":"Point"}
}