{
  "type": "Feature",
  "properties": {
    "iso:country":"US",
    "sg:address":"100 Shore Dr",
    "sg:city":"Worcester",
    "sg:classifiers":[
        {
            "category":"Social Services",
            "subcategory":"Child Care",
            "type":"Services"
        }
    ],
    "sg:phone":"+1 508 856 0400",
    "sg:postcode":"01605",
    "sg:province":"MA",
    "wof:name":"YMCA",
    "wof:placetype":"venue"
},
  "geometry": {"coordinates":[-71.81387100000001,42.30382],"type":"Point"}
}