{
  "type": "Feature",
  "properties": {
    "iso:country":"US",
    "sg:address":"58 Bowen St",
    "sg:city":"Newton",
    "sg:classifiers":[
        {
            "category":"Wholesale",
            "subcategory":"Non-durable Goods",
            "type":"Manufacturing & Wholesale Goods"
        }
    ],
    "sg:phone":"+1   ",
    "sg:postcode":"02459",
    "sg:province":"MA",
    "sg:tags":[
        "premium",
        "advertising",
        "specialty"
    ],
    "wof:name":"Pioneer Premium Promotions",
    "wof:placetype":"venue"
},
  "geometry": {"coordinates":[-71.19550099999999,42.334159],"type":"Point"}
}