{
  "type": "Feature",
  "properties": {
    "addr:full": "50 Bourne Rd Plymouth MA 02360",
    "addr:housenumber": "50",
    "addr:postcode": "02360",
    "addr:street": "Bourne Rd",
    "iso:country": "US",
    "sg:address": "50 Bourne Rd",
    "sg:city": "Plymouth",
    "sg:classifiers": [
      {
        "category": "Wholesale",
        "subcategory": "Seafood",
        "type": "Manufacturing \u0026 Wholesale Goods"
      }
    ],
    "sg:phone": "+1 508 224 0981",
    "sg:postcode": "02360",
    "sg:province": "MA",
    "wof:name": "Royal Greenland East Coast",
    "wof:placetype": "venue"
  },
  "geometry": {"coordinates":[-70.603082,41.844668],"type":"Point"}
}
