{
  "type": "Feature",
  "properties": {
    "addr:full": "897 Dalton Ave Pittsfield MA 01201",
    "addr:housenumber": "897",
    "addr:postcode": "01201",
    "addr:street": "Dalton Ave",
    "iso:country": "US",
    "sg:address": "897 Dalton Ave",
    "sg:city": "Pittsfield",
    "sg:classifiers": [
      {
        "category": "Shopping",
        "subcategory": "Clothing, Apparel, \u0026 Fashions",
        "type": "Retail Goods"
      }
    ],
    "sg:phone": "+1 413 445 4050",
    "sg:postcode": "01201",
    "sg:province": "MA",
    "sg:tags": [
      "t"
    ],
    "wof:name": "Tee Shirts To Go",
    "wof:placetype": "venue"
  },
  "geometry": {"coordinates":[-73.201762,42.468645],"type":"Point"}
}
