{
  "type": "Feature",
  "properties": {
    "iso:country":"US",
    "sg:address":"897 Dalton Ave",
    "sg:city":"Pittsfield",
    "sg:classifiers":[
        {
            "category":"Shopping",
            "subcategory":"Clothing, Apparel, & Fashions",
            "type":"Retail Goods"
        }
    ],
    "sg:phone":"+1 413 445 4050",
    "sg:postcode":"01201",
    "sg:province":"MA",
    "sg:tags":[
        "t"
    ],
    "wof:name":"Tee Shirts To Go",
    "wof:placetype":"venue"
},
  "geometry": {"coordinates":[-73.201762,42.468645],"type":"Point"}
}