{
  "type": "Feature",
  "properties": {
    "iso:country":"US",
    "sg:address":"107 Pond St",
    "sg:city":"Waltham",
    "sg:classifiers":[
        {
            "category":"Retail",
            "subcategory":"Repair Shop",
            "type":"Services"
        }
    ],
    "sg:phone":"+1   ",
    "sg:postcode":"02451",
    "sg:province":"MA",
    "sg:tags":[
        "refrigeration"
    ],
    "wof:name":"Boulos Mechanical",
    "wof:placetype":"venue"
},
  "geometry": {"coordinates":[-71.24176799999999,42.37962],"type":"Point"}
}