{
  "type": "Feature",
  "properties": {
    "addr:full":"1539 County St Somerset MA 02726",
    "addr:housenumber":"1539",
    "addr:postcode":"02726",
    "addr:street":"County St",
    "iso:country":"US",
    "sg:address":"1539 County St",
    "sg:city":"Somerset",
    "sg:classifiers":[
        {
            "category":"Building & Trades",
            "subcategory":"Electrical",
            "type":"Services"
        }
    ],
    "sg:phone":"+1 508 676 6545",
    "sg:postcode":"02726",
    "sg:province":"MA",
    "sg:tags":[
        "electric",
        "contractor"
    ],
    "wof:name":"Forbus Electrical Svc",
    "wof:placetype":"venue"
},
  "geometry": {"coordinates":[-71.140236,41.7558],"type":"Point"}
}