{
  "type": "Feature",
  "properties": {
    "addr:full": "175 West St Ware MA 01082",
    "addr:housenumber": "175",
    "addr:postcode": "01082",
    "addr:street": "West St",
    "iso:country": "US",
    "sg:address": "175 West St",
    "sg:city": "Ware",
    "sg:classifiers": [
      {
        "category": "Autos \u0026 Motor Vehicles",
        "subcategory": "Auto Supplies",
        "type": "Retail Goods"
      }
    ],
    "sg:phone": "+1 413 967 5121",
    "sg:postcode": "01082",
    "sg:province": "MA",
    "sg:tags": [
      "automobile",
      "parts"
    ],
    "wof:name": "NAPA Auto Parts",
    "wof:placetype": "venue"
  },
  "geometry": {"coordinates":[-72.254476,42.254232],"type":"Point"}
}
