{
  "type": "Feature",
  "properties": {
    "addr:full":"27 Glen St Stoughton MA 02072",
    "addr:housenumber":"27",
    "addr:postcode":"02072",
    "addr:street":"Glen St",
    "iso:country":"US",
    "sg:address":"27 Glen St",
    "sg:city":"Stoughton",
    "sg:classifiers":[
        {
            "category":"Wholesale",
            "subcategory":"Machinery & Supplies",
            "type":"Manufacturing & Wholesale Goods"
        }
    ],
    "sg:phone":"+1 781 341 1771",
    "sg:postcode":"02072",
    "sg:province":"MA",
    "sg:tags":[
        "equipment",
        "industrial"
    ],
    "wof:name":"Michael Silbert",
    "wof:placetype":"venue"
},
  "geometry": {"coordinates":[-71.10318700000001,42.130797],"type":"Point"}
}