{
  "type": "Feature",
  "properties": {
    "iso:country":"US",
    "sg:address":"59 Temple Pl",
    "sg:city":"Boston",
    "sg:classifiers":[
        {
            "category":"Wholesale",
            "subcategory":"Machinery & Supplies",
            "type":"Manufacturing & Wholesale Goods"
        }
    ],
    "sg:phone":"+1 617 426 0921",
    "sg:postcode":"02111",
    "sg:province":"MA",
    "sg:tags":[
        "salon",
        "beauty"
    ],
    "wof:name":"Boston Beauty Supply",
    "wof:placetype":"venue"
},
  "geometry": {"coordinates":[-71.061424,42.354883],"type":"Point"}
}