{
  "type": "Feature",
  "properties": {
    "iso:country":"US",
    "sg:address":"29 Dean St",
    "sg:city":"Mansfield",
    "sg:classifiers":[
        {
            "category":"Education",
            "subcategory":"School",
            "type":"Public Place"
        }
    ],
    "sg:phone":"+1 508 261 7507",
    "sg:postcode":"02048",
    "sg:province":"MA",
    "wof:name":"Mansfield Special Education",
    "wof:placetype":"venue"
},
  "geometry": {"coordinates":[-71.220972,42.024058],"type":"Point"}
}