{
  "type": "Feature",
  "properties": {
    "iso:country":"US",
    "sg:address":"653 Church St",
    "sg:city":"Whitinsville",
    "sg:classifiers":[
        {
            "category":"Professional",
            "type":"Services"
        }
    ],
    "sg:phone":"+1 508 234 5148",
    "sg:postcode":"01588",
    "sg:province":"MA",
    "sg:tags":[
        "establishment"
    ],
    "wof:name":"Schotanus & Schotanus",
    "wof:placetype":"venue"
},
  "geometry": {"coordinates":[-71.64707199999999,42.122708],"type":"Point"}
}