{
  "type": "Feature",
  "properties": {
    "iso:country":"US",
    "sg:address":"131 Bunker Hill Ln",
    "sg:city":"Quincy",
    "sg:classifiers":[
        {
            "category":"Real Estate",
            "subcategory":"Real Estate Agent",
            "type":"Services"
        }
    ],
    "sg:phone":"+1 617 773 7010",
    "sg:postcode":"02169",
    "sg:province":"MA",
    "wof:name":"Fantucchio Realty Co",
    "wof:placetype":"venue"
},
  "geometry": {"coordinates":[-71.031194,42.236917],"type":"Point"}
}