{
  "type": "Feature",
  "properties": {
    "addr:full":"699 Boylston St Boston MA 02116",
    "addr:housenumber":"699",
    "addr:postcode":"02116",
    "addr:street":"Boylston St",
    "iso:country":"US",
    "sg:address":"699 Boylston St",
    "sg:city":"Boston",
    "sg:classifiers":[
        {
            "category":"Banks & Credit Unions",
            "subcategory":"Investment Brokerage",
            "type":"Services"
        },
        {
            "category":"Banks & Credit Unions",
            "subcategory":"Financial Services",
            "type":"Services"
        }
    ],
    "sg:phone":"+1 617 927 6699",
    "sg:postcode":"02116",
    "sg:province":"MA",
    "sg:tags":[
        "security",
        "planner"
    ],
    "sg:website":"http://www.wachoviasec.com",
    "wof:name":"Wells Fargo Advisors",
    "wof:placetype":"venue"
},
  "geometry": {"coordinates":[-71.079483,42.349499],"type":"Point"}
}