{
  "type": "Feature",
  "properties": {
    "iso:country":"US",
    "sg:address":"11 Fowle St",
    "sg:city":"Woburn",
    "sg:classifiers":[
        {
            "category":"Building & Trades",
            "subcategory":"Landscaping Services",
            "type":"Services"
        }
    ],
    "sg:phone":"+1 781 729 0478",
    "sg:postcode":"01801",
    "sg:province":"MA",
    "sg:tags":[
        "tree"
    ],
    "sg:website":"www.arborcaretree.com",
    "wof:name":"Arborcare Tree Svc",
    "wof:placetype":"venue"
},
  "geometry": {"coordinates":[-71.148105,42.472629],"type":"Point"}
}