{
  "type": "Feature",
  "properties": {
    "addr:full": "182 Parker St Lawrence MA 01843",
    "addr:housenumber": "182",
    "addr:postcode": "01843",
    "addr:street": "Parker St",
    "iso:country": "US",
    "sg:address": "182 Parker St",
    "sg:city": "Lawrence",
    "sg:classifiers": [
      {
        "category": "Insurance",
        "subcategory": "Insurance Agent",
        "type": "Services"
      }
    ],
    "sg:phone": "+1 978 681 1112",
    "sg:postcode": "01843",
    "sg:province": "MA",
    "wof:name": "Matthews Insurance",
    "wof:placetype": "venue"
  },
  "geometry": {"coordinates":[-71.157561,42.695444],"type":"Point"}
}
