{
  "type": "Feature",
  "properties": {
    "iso:country":"US",
    "sg:address":"294 6th St",
    "sg:city":"Leominster",
    "sg:classifiers":[
        {
            "category":"Building & Trades",
            "subcategory":"Landscaping Services",
            "type":"Services"
        }
    ],
    "sg:phone":"+1 978 537 4345",
    "sg:postcode":"01453",
    "sg:province":"MA",
    "sg:tags":[
        "landscape",
        "contractor"
    ],
    "wof:name":"DNA Quality Svc",
    "wof:placetype":"venue"
},
  "geometry": {"coordinates":[-71.75247299999999,42.518694],"type":"Point"}
}