{
  "type": "Feature",
  "properties": {
    "addr:full":"58 Macy St Amesbury MA 01913",
    "addr:housenumber":"58",
    "addr:postcode":"01913",
    "addr:street":"Macy St",
    "iso:country":"US",
    "sg:address":"58 Macy St",
    "sg:city":"Amesbury",
    "sg:classifiers":[
        {
            "category":"Organizations",
            "subcategory":"Religious Organization",
            "type":"Services"
        }
    ],
    "sg:phone":"+1 978 834 7830",
    "sg:postcode":"01913",
    "sg:province":"MA",
    "sg:tags":[
        "church"
    ],
    "wof:name":"Unity On The River",
    "wof:placetype":"venue"
},
  "geometry": {"coordinates":[-70.92126,42.846702],"type":"Point"}
}