{
  "type": "Feature",
  "properties": {
    "addr:full":"1097 Lexington St Waltham MA 02452",
    "addr:housenumber":"1097",
    "addr:postcode":"02452",
    "addr:street":"Lexington St",
    "iso:country":"US",
    "sg:address":"1097 Lexington St",
    "sg:city":"Waltham",
    "sg:classifiers":[
        {
            "category":"Retail",
            "subcategory":"Photofinishing",
            "type":"Services"
        }
    ],
    "sg:phone":"+1 781 899 7624",
    "sg:postcode":"02452",
    "sg:province":"MA",
    "sg:tags":[
        "photo",
        "finishing"
    ],
    "wof:name":"Photo Quick",
    "wof:placetype":"venue"
},
  "geometry": {"coordinates":[-71.233588,42.411177],"type":"Point"}
}