{
  "type": "Feature",
  "properties": {
    "addr:full":"52 S Quinsigamond Ave Shrewsbury MA 01545",
    "addr:housenumber":"52",
    "addr:postcode":"01545",
    "addr:street":"S Quinsigamond Ave",
    "iso:country":"US",
    "sg:address":"52 S Quinsigamond Ave",
    "sg:city":"Shrewsbury",
    "sg:classifiers":[
        {
            "category":"Restaurant",
            "type":"Food & Drink"
        }
    ],
    "sg:phone":"+1 508 755 0040",
    "sg:postcode":"01545",
    "sg:province":"MA",
    "sg:tags":[
        "banquet",
        "rooms"
    ],
    "sg:website":"www.maironis.com",
    "wof:name":"Maironis Park",
    "wof:placetype":"venue"
},
  "geometry": {"coordinates":[-71.750822,42.271029],"type":"Point"}
}