{
  "type": "Feature",
  "properties": {
    "addr:full": "15 Warwick Rd Northfield MA 01360",
    "addr:housenumber": "15",
    "addr:postcode": "01360",
    "addr:street": "Warwick Rd",
    "iso:country": "US",
    "sg:address": "15 Warwick Rd",
    "sg:city": "Northfield",
    "sg:classifiers": [
      {
        "category": "Manufacturing",
        "subcategory": "Printing",
        "type": "Manufacturing \u0026 Wholesale Goods"
      }
    ],
    "sg:phone": "+1   ",
    "sg:postcode": "01360",
    "sg:province": "MA",
    "sg:tags": [
      "lithographic",
      "book",
      "commercial"
    ],
    "wof:name": "Swamp Press",
    "wof:placetype": "venue"
  },
  "geometry": {"coordinates":[-72.454996,42.693967],"type":"Point"}
}
