{
  "type": "Feature",
  "properties": {
    "addr:full": "1 Heritage Dr Bedford MA 01730",
    "addr:housenumber": "1",
    "addr:postcode": "01730",
    "addr:street": "Heritage Dr",
    "iso:country": "US",
    "sg:address": "1 Heritage Dr",
    "sg:city": "Bedford",
    "sg:classifiers": [
      {
        "category": "Professional",
        "subcategory": "Accounting \u0026 Tax Preparation",
        "type": "Services"
      }
    ],
    "sg:phone": "+1 781 271 0177",
    "sg:postcode": "01730",
    "sg:province": "MA",
    "sg:tags": [
      "accountant"
    ],
    "wof:name": "Dave M Theresa CPA",
    "wof:placetype": "venue"
  },
  "geometry": {"coordinates":[-71.282402,42.503899],"type":"Point"}
}
