{
  "type": "Feature",
  "properties": {
    "addr:full": "295 Main St North Easton MA 02356",
    "addr:housenumber": "295",
    "addr:postcode": "02356",
    "addr:street": "Main St",
    "iso:country": "US",
    "ovtr:label": "North Easton Savings Bank, 295 Main St North Easton MA US",
    "ovtr:similarity": 3.0488789081573486,
    "sg:address": "295 Main St",
    "sg:city": "North Easton",
    "sg:classifiers": [
      {
        "category": "Banks \u0026 Credit Unions",
        "subcategory": "Bank",
        "type": "Services"
      }
    ],
    "sg:phone": "+1 508 238 2007",
    "sg:postcode": "02356",
    "sg:province": "MA",
    "sg:website": "www.northeastonsavingsbank.com",
    "wof:name": "North Easton Savings Bank",
    "wof:placetype": "venue"
  },
  "geometry": {"coordinates":[-71.091952,42.066554],"type":"Point"}
}
