{
  "type": "Feature",
  "properties": {
    "iso:country":"US",
    "sg:address":"295 Main St",
    "sg:city":"North Easton",
    "sg:classifiers":[
        {
            "category":"Banks & Credit Unions",
            "subcategory":"Bank",
            "type":"Services"
        }
    ],
    "sg:phone":"+1 508 238 2007",
    "sg:postcode":"02356",
    "sg:province":"MA",
    "sg:website":"www.northeastonsavingsbank.com",
    "wof:name":"North Easton Savings Bank",
    "wof:placetype":"venue"
},
  "geometry": {"coordinates":[-71.09195200000001,42.066554],"type":"Point"}
}