{
  "type": "Feature",
  "properties": {
    "iso:country":"US",
    "sg:address":"143 Millard Rd",
    "sg:city":"North Attleboro",
    "sg:classifiers":[
        {
            "category":"Retail",
            "subcategory":"Pet Boarding",
            "type":"Services"
        }
    ],
    "sg:phone":"+1 508 695 0210",
    "sg:postcode":"02760",
    "sg:province":"MA",
    "sg:tags":[
        "boarding/pet",
        "sitting"
    ],
    "wof:name":"Taramanor Kennel",
    "wof:placetype":"venue"
},
  "geometry": {"coordinates":[-71.373001,41.961498],"type":"Point"}
}