{
  "type": "Feature",
  "properties": {
    "iso:country":"US",
    "sg:address":"220 Commercial St",
    "sg:city":"Provincetown",
    "sg:classifiers":[
        {
            "category":"Shopping",
            "subcategory":"Gifts & Souvenirs",
            "type":"Retail Goods"
        }
    ],
    "sg:phone":"+1 508 487 3434",
    "sg:postcode":"02657",
    "sg:province":"MA",
    "sg:tags":[
        "shop"
    ],
    "wof:name":"I D",
    "wof:placetype":"venue"
},
  "geometry": {"coordinates":[-70.188992,42.048983],"type":"Point"}
}