{
  "type": "Feature",
  "properties": {
    "iso:country":"US",
    "sg:address":"101 Fayette St",
    "sg:city":"Lynn",
    "sg:classifiers":[
        {
            "category":"Organizations",
            "subcategory":"Labor Organization",
            "type":"Services"
        }
    ],
    "sg:phone":"+1 781 599 1085",
    "sg:postcode":"01902",
    "sg:province":"MA",
    "wof:name":"Lynn Firefighters Union",
    "wof:placetype":"venue"
},
  "geometry": {"coordinates":[-70.936801,42.470438],"type":"Point"}
}