{
  "type": "Feature",
  "properties": {
    "addr:full": "59 Temple Pl Boston MA 02111",
    "addr:housenumber": "59",
    "addr:postcode": "02111",
    "addr:street": "Temple Pl",
    "iso:country": "US",
    "sg:address": "59 Temple Pl",
    "sg:city": "Boston",
    "sg:classifiers": [
      {
        "category": "Professional",
        "subcategory": "Lawyer \u0026 Legal Services",
        "type": "Services"
      }
    ],
    "sg:phone": "+1 617 542 5111",
    "sg:postcode": "02111",
    "sg:province": "MA",
    "sg:tags": [
      "personal",
      "injury"
    ],
    "wof:name": "Sexton Patricia M",
    "wof:placetype": "venue"
  },
  "geometry": {"coordinates":[-71.061699,42.355099],"type":"Point"}
}
