{
  "type": "Feature",
  "properties": {
    "addr:full": "161 New Lombard Rd Chicopee MA 01020",
    "addr:housenumber": "161",
    "addr:postcode": "01020",
    "addr:street": "New Lombard Rd",
    "iso:country": "US",
    "sg:address": "161 New Lombard Rd",
    "sg:city": "Chicopee",
    "sg:classifiers": [
      {
        "category": "Utilities",
        "subcategory": "Refuse",
        "type": "Services"
      }
    ],
    "sg:phone": "+1   ",
    "sg:postcode": "01020",
    "sg:province": "MA",
    "sg:tags": [
      "landfill",
      "sanitary",
      "operation"
    ],
    "wof:name": "Connecticut Valy Wast Dispos",
    "wof:placetype": "venue"
  },
  "geometry": {"coordinates":[-72.542288,42.16706],"type":"Point"}
}
