{
  "type": "Feature",
  "properties": {
    "iso:country":"US",
    "sg:address":"17 Main St",
    "sg:city":"Brimfield",
    "sg:classifiers":[
        {
            "category":"Restaurant",
            "type":"Food & Drink"
        }
    ],
    "sg:phone":"+1 413 245 9437",
    "sg:postcode":"01010",
    "sg:province":"MA",
    "wof:name":"Athen's Pizza",
    "wof:placetype":"venue"
},
  "geometry": {"coordinates":[-72.203262,42.122089],"type":"Point"}
}