{
  "type": "Feature",
  "properties": {
    "addr:full":"495 Broadway Lynnfield MA 01940",
    "addr:housenumber":"495",
    "addr:postcode":"01940",
    "addr:street":"Broadway",
    "iso:country":"US",
    "sg:address":"495 Broadway",
    "sg:city":"Lynnfield",
    "sg:classifiers":[
        {
            "category":"Building & Trades",
            "subcategory":"Construction",
            "type":"Services"
        }
    ],
    "sg:phone":"+1 781 596 0022",
    "sg:postcode":"01940",
    "sg:province":"MA",
    "sg:tags":[
        "excavating",
        "contractor"
    ],
    "wof:name":"P T Corp",
    "wof:placetype":"venue"
},
  "geometry": {"coordinates":[-71.001976,42.515887],"type":"Point"}
}