{
  "type": "Feature",
  "properties": {
    "addr:full":"207 Bussey St Dedham MA 02026",
    "addr:housenumber":"207",
    "addr:postcode":"02026",
    "addr:street":"Bussey St",
    "iso:country":"US",
    "sg:address":"207 Bussey St",
    "sg:city":"Dedham",
    "sg:classifiers":[
        {
            "category":"Personal",
            "subcategory":"Beauty Salon",
            "type":"Services"
        }
    ],
    "sg:phone":"+1 781 329 1922",
    "sg:postcode":"02026",
    "sg:province":"MA",
    "wof:name":"Carol's Beauty Salon",
    "wof:placetype":"venue"
},
  "geometry": {"coordinates":[-71.15562,42.249759],"type":"Point"}
}