{
  "type": "Feature",
  "properties": {
    "iso:country":"US",
    "sg:address":"7 Echo Hill Rd",
    "sg:city":"Wilbraham",
    "sg:classifiers":[
        {
            "category":"Manufacturing",
            "subcategory":"Printing",
            "type":"Manufacturing & Wholesale Goods"
        }
    ],
    "sg:phone":"+1   ",
    "sg:postcode":"01095",
    "sg:province":"MA",
    "sg:tags":[
        "book"
    ],
    "wof:name":"Motor Manuals",
    "wof:placetype":"venue"
},
  "geometry": {"coordinates":[-72.431597,42.105988],"type":"Point"}
}