{
  "type": "Feature",
  "properties": {
    "addr:full": "35 Commercial Dr Wrentham MA 02093",
    "addr:housenumber": "35",
    "addr:postcode": "02093",
    "addr:street": "Commercial Dr",
    "iso:country": "US",
    "sg:address": "35 Commercial Dr",
    "sg:city": "Wrentham",
    "sg:classifiers": [
      {
        "category": "Building \u0026 Trades",
        "subcategory": "Construction",
        "type": "Services"
      }
    ],
    "sg:phone": "+1 508 384 4434",
    "sg:postcode": "02093",
    "sg:province": "MA",
    "sg:tags": [
      "boring",
      "drilling",
      "contractor"
    ],
    "wof:name": "Geo Logic Inc",
    "wof:placetype": "venue"
  },
  "geometry": {"coordinates":[-71.30164,42.051548],"type":"Point"}
}
