{
  "type": "Feature",
  "properties": {
    "addr:full": "90 Bolt St Lowell MA 01852",
    "addr:housenumber": "90",
    "addr:postcode": "01852",
    "addr:street": "Bolt St",
    "iso:country": "US",
    "sg:address": "90 Bolt St",
    "sg:city": "Lowell",
    "sg:classifiers": [
      {
        "category": "Professional",
        "subcategory": "Business Services",
        "type": "Services"
      }
    ],
    "sg:phone": "+1 978 446 0104",
    "sg:postcode": "01852",
    "sg:province": "MA",
    "sg:tags": [
      "fire",
      "protection"
    ],
    "wof:name": "Eastern Mass Fire Protection",
    "wof:placetype": "venue"
  },
  "geometry": {"coordinates":[-71.29963,42.625255],"type":"Point"}
}
