{
  "type": "Feature",
  "properties": {
    "iso:country":"US",
    "sg:address":"5 W Main St",
    "sg:city":"Northborough",
    "sg:classifiers":[
        {
            "category":"Shopping",
            "subcategory":"Gifts & Souvenirs",
            "type":"Retail Goods"
        }
    ],
    "sg:phone":"+1 508 393 6665",
    "sg:postcode":"01532",
    "sg:province":"MA",
    "sg:tags":[
        "basket",
        "parcel"
    ],
    "wof:name":"Wicked Good Cookies",
    "wof:placetype":"venue"
},
  "geometry": {"coordinates":[-71.642456,42.31972],"type":"Point"}
}