{
  "type": "Feature",
  "properties": {
    "iso:country":"US",
    "sg:address":"211 Congress St Ste 700",
    "sg:city":"Boston",
    "sg:classifiers":[
        {
            "category":"Health Services",
            "subcategory":"Dentist",
            "type":"Services"
        }
    ],
    "sg:phone":"+1 617 574 8700",
    "sg:postcode":"02110",
    "sg:province":"MA",
    "sg:website":"www.congressdentalgroup.com",
    "wof:name":"Congress Dental Group",
    "wof:placetype":"venue"
},
  "geometry": {"coordinates":[-71.054838,42.354728],"type":"Point"}
}