{
  "type": "Feature",
  "properties": {
    "iso:country":"US",
    "sg:address":"34 Wasilla Dr",
    "sg:city":"Worcester",
    "sg:classifiers":[
        {
            "category":"Professional",
            "subcategory":"Computer Services",
            "type":"Services"
        }
    ],
    "sg:phone":"+1 508 757 5502",
    "sg:postcode":"01604",
    "sg:province":"MA",
    "sg:website":"www.westmarkinc.com",
    "wof:name":"Westmark Consulting Inc",
    "wof:placetype":"venue"
},
  "geometry": {"coordinates":[-71.76735600000001,42.246277],"type":"Point"}
}