{
  "type": "Feature",
  "properties": {
    "iso:country":"US",
    "sg:address":"391 E Central St",
    "sg:city":"Franklin",
    "sg:classifiers":[
        {
            "category":"Restaurant",
            "type":"Food & Drink"
        }
    ],
    "sg:phone":"+1 508 528 5590",
    "sg:postcode":"02038",
    "sg:province":"MA",
    "sg:tags":[
        "delicatessen"
    ],
    "wof:name":"Best Deli",
    "wof:placetype":"venue"
},
  "geometry": {"coordinates":[-71.381191,42.080072],"type":"Point"}
}