{
  "type": "Feature",
  "properties": {
    "iso:country":"US",
    "sg:address":"165 Main St",
    "sg:city":"Medway",
    "sg:classifiers":[
        {
            "category":"Professional",
            "subcategory":"Management & Consulting",
            "type":"Services"
        }
    ],
    "sg:phone":"+1 508 533 6533",
    "sg:postcode":"02053",
    "sg:province":"MA",
    "sg:tags":[
        "consultant",
        "hygiene",
        "industrial"
    ],
    "wof:name":"Cannon Hygiene",
    "wof:placetype":"venue"
},
  "geometry": {"coordinates":[-71.42837900000001,42.146319],"type":"Point"}
}