{
  "type": "Feature",
  "properties": {
    "addr:full": "165 Main St Medway MA 02053",
    "addr:housenumber": "165",
    "addr:postcode": "02053",
    "addr:street": "Main St",
    "iso:country": "US",
    "sg:address": "165 Main St",
    "sg:city": "Medway",
    "sg:classifiers": [
      {
        "category": "Professional",
        "subcategory": "Management \u0026 Consulting",
        "type": "Services"
      }
    ],
    "sg:phone": "+1 508 533 6533",
    "sg:postcode": "02053",
    "sg:province": "MA",
    "sg:tags": [
      "consultant",
      "hygiene",
      "industrial"
    ],
    "wof:name": "Cannon Hygiene",
    "wof:placetype": "venue"
  },
  "geometry": {"coordinates":[-71.428379,42.146319],"type":"Point"}
}
