{
  "type": "Feature",
  "properties": {
    "addr:full": "230 Holland St Somerville MA 02144",
    "addr:housenumber": "230",
    "addr:postcode": "02144",
    "addr:street": "Holland St",
    "iso:country": "US",
    "sg:address": "230 Holland St",
    "sg:city": "Somerville",
    "sg:classifiers": [
      {
        "category": "Retail",
        "subcategory": "Repair Shop",
        "type": "Services"
      }
    ],
    "sg:phone": "+1 617 453 5187",
    "sg:postcode": "02144",
    "sg:province": "MA",
    "sg:tags": [
      "lock",
      "locksmith"
    ],
    "wof:name": "All Day Emergency Locksmith",
    "wof:placetype": "venue"
  },
  "geometry": {"coordinates":[-71.126503,42.401773],"type":"Point"}
}
