{
  "type": "Feature",
  "properties": {
    "iso:country":"US",
    "sg:address":"45 Blodgett Ave",
    "sg:city":"Swampscott",
    "sg:classifiers":[
        {
            "category":"Professional",
            "type":"Services"
        }
    ],
    "sg:phone":"+1   ",
    "sg:postcode":"01907",
    "sg:province":"MA",
    "wof:name":"Old Neighborhood Foods",
    "wof:placetype":"venue"
},
  "geometry": {"coordinates":[-70.88403700000001,42.474449],"type":"Point"}
}