{
  "type": "Feature",
  "properties": {
    "addr:full":"270 Broadway Revere MA 02151",
    "addr:housenumber":"270",
    "addr:postcode":"02151",
    "addr:street":"Broadway",
    "iso:country":"US",
    "sg:address":"270 Broadway",
    "sg:city":"Revere",
    "sg:classifiers":[
        {
            "category":"Professional",
            "subcategory":"Business Services",
            "type":"Services"
        }
    ],
    "sg:phone":"+1 781 485 1619",
    "sg:postcode":"02151",
    "sg:province":"MA",
    "sg:tags":[
        "appraiser"
    ],
    "wof:name":"United Appraisal Assoc",
    "wof:placetype":"venue"
},
  "geometry": {"coordinates":[-71.013819,42.407672],"type":"Point"}
}