{
  "type": "Feature",
  "properties": {
    "addr:full":"689 Somerville Ave Somerville MA 02143",
    "addr:housenumber":"689",
    "addr:postcode":"02143",
    "addr:street":"Somerville Ave",
    "iso:country":"US",
    "sg:address":"689 Somerville Ave",
    "sg:city":"Somerville",
    "sg:classifiers":[
        {
            "category":"Real Estate",
            "subcategory":"Real Estate Services",
            "type":"Services"
        },
        {
            "category":"Real Estate",
            "subcategory":"Real Estate Agent",
            "type":"Services"
        }
    ],
    "sg:phone":"+1 617 440 7347",
    "sg:postcode":"02143",
    "sg:province":"MA",
    "sg:tags":[
        "buyer",
        "broker"
    ],
    "wof:name":"Bridge Realty Group",
    "wof:placetype":"venue"
},
  "geometry": {"coordinates":[-71.113055,42.385288],"type":"Point"}
}