{
  "type": "Feature",
  "properties": {
    "addr:full": "19 Volkmar Rd Worcester MA 01606",
    "addr:housenumber": "19",
    "addr:postcode": "01606",
    "addr:street": "Volkmar Rd",
    "iso:country": "US",
    "sg:address": "19 Volkmar Rd",
    "sg:city": "Worcester",
    "sg:classifiers": [
      {
        "category": "Building \u0026 Trades",
        "subcategory": "Cleaning \u0026 Sanitation",
        "type": "Services"
      }
    ],
    "sg:phone": "+1 508 767 1610",
    "sg:postcode": "01606",
    "sg:province": "MA",
    "sg:tags": [
      "cleaning-industrial",
      "contractor"
    ],
    "wof:name": "Bay State Cleaning",
    "wof:placetype": "venue"
  },
  "geometry": {"coordinates":[-71.793904,42.319757],"type":"Point"}
}
