{
  "type": "Feature",
  "properties": {
    "addr:full": "119 Hardy St Dunstable MA 01827",
    "addr:housenumber": "119",
    "addr:postcode": "01827",
    "addr:street": "Hardy St",
    "iso:country": "US",
    "sg:address": "119 Hardy St",
    "sg:city": "Dunstable",
    "sg:classifiers": [
      {
        "category": "Real Estate",
        "subcategory": "Real Estate Services",
        "type": "Services"
      },
      {
        "category": "Real Estate",
        "subcategory": "Real Estate Agent",
        "type": "Services"
      }
    ],
    "sg:phone": "+1 978 649 4562",
    "sg:postcode": "01827",
    "sg:province": "MA",
    "sg:tags": [
      "buyer",
      "broker"
    ],
    "wof:name": "Dc Wotton Realty",
    "wof:placetype": "venue"
  },
  "geometry": {"coordinates":[-71.465689,42.693107],"type":"Point"}
}
