{
  "type": "Feature",
  "properties": {
    "addr:full":"5 Winslow Ave Scituate MA 02066",
    "addr:housenumber":"5",
    "addr:postcode":"02066",
    "addr:street":"Winslow Ave",
    "iso:country":"US",
    "sg:address":"5 Winslow Ave",
    "sg:city":"Scituate",
    "sg:classifiers":[
        {
            "category":"Social Services",
            "type":"Services"
        }
    ],
    "sg:phone":"+1 781 545 0041",
    "sg:postcode":"02066",
    "sg:province":"MA",
    "sg:tags":[
        "counselor",
        "marriage",
        "family"
    ],
    "wof:name":"Personal Counseling Svc",
    "wof:placetype":"venue"
},
  "geometry": {"coordinates":[-70.74194300000001,42.216974],"type":"Point"}
}