{
  "type": "Feature",
  "properties": {
    "iso:country":"US",
    "sg:address":"75 Columbia St",
    "sg:city":"Cambridge",
    "sg:classifiers":[
        {
            "category":"Building & Trades",
            "subcategory":"Locksmith",
            "type":"Services"
        }
    ],
    "sg:phone":"+1 617 299 2098",
    "sg:postcode":"02139",
    "sg:province":"MA",
    "sg:tags":[
        "key"
    ],
    "wof:name":"A Locksmith Service",
    "wof:placetype":"venue"
},
  "geometry": {"coordinates":[-71.099075,42.365243],"type":"Point"}
}