{
  "type": "Feature",
  "properties": {
    "iso:country":"US",
    "sg:address":"55 Franklin St",
    "sg:city":"Needham",
    "sg:classifiers":[
        {
            "category":"Wholesale",
            "subcategory":"Hardware",
            "type":"Manufacturing & Wholesale Goods"
        }
    ],
    "sg:phone":"+1 781 449 5972",
    "sg:postcode":"02494",
    "sg:province":"MA",
    "sg:tags":[
        "water",
        "cooler",
        "fountain",
        "filter"
    ],
    "wof:name":"Nature Springs Water Co",
    "wof:placetype":"venue"
},
  "geometry": {"coordinates":[-71.224441,42.30538],"type":"Point"}
}