{
  "type": "Feature",
  "properties": {
    "iso:country":"US",
    "sg:address":"110 State St",
    "sg:city":"Boston",
    "sg:classifiers":[
        {
            "category":"Food & Beverages",
            "subcategory":"Bakery",
            "type":"Retail Goods"
        }
    ],
    "sg:phone":"+1 617 720 5555",
    "sg:postcode":"02109",
    "sg:province":"MA",
    "sg:tags":[
        "sandwich"
    ],
    "sg:website":"www.alsstatestreetcafe.com",
    "wof:name":"Al's State Street Cafe",
    "wof:placetype":"venue"
},
  "geometry": {"coordinates":[-71.0549,42.359183],"type":"Point"}
}