{
  "type": "Feature",
  "properties": {
    "addr:full":"118 Old Colony Ave Quincy MA 02170",
    "addr:housenumber":"118",
    "addr:postcode":"02170",
    "addr:street":"Old Colony Ave",
    "iso:country":"US",
    "sg:address":"118 Old Colony Ave",
    "sg:city":"Quincy",
    "sg:classifiers":[
        {
            "category":"Wholesale",
            "subcategory":"Hardware",
            "type":"Manufacturing & Wholesale Goods"
        }
    ],
    "sg:phone":"+1 617 328 7070",
    "sg:postcode":"02170",
    "sg:province":"MA",
    "sg:tags":[
        "plumbing",
        "fixture",
        "supply"
    ],
    "wof:name":"Stratford Associates",
    "wof:placetype":"venue"
},
  "geometry": {"coordinates":[-71.01343199999999,42.260788],"type":"Point"}
}