{
  "type": "Feature",
  "properties": {
    "addr:full": "350 Hanover St Boston MA 02113",
    "addr:housenumber": "350",
    "addr:postcode": "02113",
    "addr:street": "Hanover St",
    "iso:country": "US",
    "sg:address": "350 Hanover St",
    "sg:city": "Boston",
    "sg:classifiers": [
      {
        "category": "Personal",
        "subcategory": "Barber",
        "type": "Services"
      }
    ],
    "sg:phone": "+1 617 742 6643",
    "sg:postcode": "02113",
    "sg:province": "MA",
    "wof:name": "Guy's Men Salon",
    "wof:placetype": "venue"
  },
  "geometry": {"coordinates":[-71.053393,42.365065],"type":"Point"}
}
