{
  "type": "Feature",
  "properties": {
    "addr:full":"168 Shaker Rd East Longmeadow MA 01028",
    "addr:housenumber":"168",
    "addr:postcode":"01028",
    "addr:street":"Shaker Rd",
    "iso:country":"US",
    "sg:address":"168 Shaker Rd",
    "sg:city":"East Longmeadow",
    "sg:classifiers":[
        {
            "category":"Sports & Exercise",
            "subcategory":"Bowling",
            "type":"Entertainment"
        }
    ],
    "sg:phone":"+1 413 525 7198",
    "sg:postcode":"01028",
    "sg:province":"MA",
    "sg:tags":[
        "center"
    ],
    "wof:name":"Shaker Bowl",
    "wof:placetype":"venue"
},
  "geometry": {"coordinates":[-72.518023,42.056029],"type":"Point"}
}