{
  "type": "Feature",
  "properties": {
    "iso:country":"US",
    "sg:address":"17 Tudor Street",
    "sg:city":"Cambridge",
    "sg:classifiers":[
        {
            "category":"Building & Trades",
            "subcategory":"Construction",
            "type":"Services"
        }
    ],
    "sg:phone":"+1 617 547 4546",
    "sg:postcode":"02139",
    "sg:province":"MA",
    "sg:tags":[
        "contractor"
    ],
    "wof:name":"Siena Construction Corporation",
    "wof:placetype":"venue"
},
  "geometry": {"coordinates":[-71.10329299999999,42.359991],"type":"Point"}
}