{
  "type": "Feature",
  "properties": {
    "iso:country":"US",
    "sg:address":"Redstone Plaza",
    "sg:city":"Stoneham",
    "sg:classifiers":[
        {
            "category":"Shopping",
            "subcategory":"Hobbies, Toys, & Games",
            "type":"Retail Goods"
        }
    ],
    "sg:phone":"+1 781 438 7986",
    "sg:postcode":"02180",
    "sg:province":"MA",
    "sg:tags":[
        "toy",
        "store"
    ],
    "wof:name":"K B Toys - CLOSED",
    "wof:placetype":"venue"
},
  "geometry": {"coordinates":[-71.100174,42.483734],"type":"Point"}
}