{
  "type": "Feature",
  "properties": {
    "iso:country":"US",
    "sg:address":"1 George St",
    "sg:city":"Plainville",
    "sg:classifiers":[
        {
            "category":"Building & Trades",
            "subcategory":"Cleaning & Sanitation",
            "type":"Services"
        }
    ],
    "sg:phone":"+1 508 643 7114",
    "sg:postcode":"02762",
    "sg:province":"MA",
    "sg:tags":[
        "janitor"
    ],
    "wof:name":"New Dimension Cleaning",
    "wof:placetype":"venue"
},
  "geometry": {"coordinates":[-71.31268,42.00866],"type":"Point"}
}