{
  "type": "Feature",
  "properties": {
    "addr:full": "1 George St Plainville MA 02762",
    "addr:housenumber": "1",
    "addr:postcode": "02762",
    "addr:street": "George St",
    "iso:country": "US",
    "sg:address": "1 George St",
    "sg:city": "Plainville",
    "sg:classifiers": [
      {
        "category": "Building \u0026 Trades",
        "subcategory": "Cleaning \u0026 Sanitation",
        "type": "Services"
      }
    ],
    "sg:phone": "+1 508 643 7114",
    "sg:postcode": "02762",
    "sg:province": "MA",
    "sg:tags": [
      "janitor"
    ],
    "wof:name": "New Dimension Cleaning",
    "wof:placetype": "venue"
  },
  "geometry": {"coordinates":[-71.31268,42.00866],"type":"Point"}
}
