{
  "type": "Feature",
  "properties": {
    "addr:full":"110 Fox Hill Rd Nahant MA 01908",
    "addr:housenumber":"110",
    "addr:postcode":"01908",
    "addr:street":"Fox Hill Rd",
    "iso:country":"US",
    "sg:address":"110 Fox Hill Rd",
    "sg:city":"Nahant",
    "sg:classifiers":[
        {
            "category":"Building & Trades",
            "subcategory":"Construction",
            "type":"Services"
        }
    ],
    "sg:phone":"+1   ",
    "sg:postcode":"01908",
    "sg:province":"MA",
    "sg:tags":[
        "carpentry",
        "contractor"
    ],
    "wof:name":"Rex Antrim Carpentry",
    "wof:placetype":"venue"
},
  "geometry": {"coordinates":[-70.932706,42.424143],"type":"Point"}
}