{
  "type": "Feature",
  "properties": {
    "iso:country":"US",
    "sg:address":"15 Old Ferry Rd",
    "sg:city":"Methuen",
    "sg:classifiers":[
        {
            "category":"Building & Trades",
            "subcategory":"Construction",
            "type":"Services"
        }
    ],
    "sg:phone":"+1 978 686 4867",
    "sg:postcode":"01844",
    "sg:province":"MA",
    "sg:tags":[
        "utility",
        "contractor"
    ],
    "wof:name":"Power Shot Utility Construct",
    "wof:placetype":"venue"
},
  "geometry": {"coordinates":[-71.140283,42.751742],"type":"Point"}
}