{
  "type": "Feature",
  "properties": {
    "addr:full": "121 Marlborough Rd Waltham MA 02452",
    "addr:housenumber": "121",
    "addr:postcode": "02452",
    "addr:street": "Marlborough Rd",
    "iso:country": "US",
    "sg:address": "121 Marlborough Rd",
    "sg:city": "Waltham",
    "sg:classifiers": [
      {
        "category": "Education",
        "subcategory": "Special Training",
        "type": "Public Place"
      }
    ],
    "sg:phone": "+1   ",
    "sg:postcode": "02452",
    "sg:province": "MA",
    "wof:name": "Center For Complex Systems",
    "wof:placetype": "venue"
  },
  "geometry": {"coordinates":[-71.201523,42.396828],"type":"Point"}
}
