{
  "type": "Feature",
  "properties": {
    "addr:full": "294 Taunton Ave Seekonk MA 02771",
    "addr:housenumber": "294",
    "addr:postcode": "02771",
    "addr:street": "Taunton Ave",
    "iso:country": "US",
    "sg:address": "294 Taunton Ave",
    "sg:city": "Seekonk",
    "sg:classifiers": [
      {
        "category": "Wholesale",
        "subcategory": "Non-durable Goods",
        "type": "Manufacturing \u0026 Wholesale Goods"
      }
    ],
    "sg:phone": "+1 508 336 9555",
    "sg:postcode": "02771",
    "sg:province": "MA",
    "sg:tags": [
      "advertising"
    ],
    "wof:name": "Lasergram",
    "wof:placetype": "venue"
  },
  "geometry": {"coordinates":[-71.337901,41.824815],"type":"Point"}
}
