{
  "type": "Feature",
  "properties": {
    "addr:full": "26 Jefferson St Milford MA 01757",
    "addr:housenumber": "26",
    "addr:postcode": "01757",
    "addr:street": "Jefferson St",
    "iso:country": "US",
    "sg:address": "26 Jefferson St",
    "sg:city": "Milford",
    "sg:classifiers": [
      {
        "category": "Real Estate",
        "subcategory": "Real Estate Agent",
        "type": "Services"
      }
    ],
    "sg:phone": "+1 508 473 2007",
    "sg:postcode": "01757",
    "sg:province": "MA",
    "wof:name": "Castle \u0026 Cottage Realty",
    "wof:placetype": "venue"
  },
  "geometry": {"coordinates":[-71.518571,42.141242],"type":"Point"}
}
