{
  "type": "Feature",
  "properties": {
    "iso:country":"US",
    "sg:address":"45 River St",
    "sg:city":"Millbury",
    "sg:classifiers":[
        {
            "category":"Shopping",
            "subcategory":"Gifts & Souvenirs",
            "type":"Retail Goods"
        }
    ],
    "sg:phone":"+1 508 865 1203",
    "sg:postcode":"01527",
    "sg:province":"MA",
    "sg:tags":[
        "shop"
    ],
    "wof:name":"Dandelions",
    "wof:placetype":"venue"
},
  "geometry": {"coordinates":[-71.765699,42.192516],"type":"Point"}
}