{
  "type": "Feature",
  "properties": {
    "addr:full":"465 Atherton St Milton MA 02186",
    "addr:housenumber":"465",
    "addr:postcode":"02186",
    "addr:street":"Atherton St",
    "iso:country":"US",
    "sg:address":"465 Atherton St",
    "sg:city":"Milton",
    "sg:classifiers":[
        {
            "category":"Professional",
            "type":"Services"
        }
    ],
    "sg:phone":"+1   ",
    "sg:postcode":"02186",
    "sg:province":"MA",
    "sg:tags":[
        "consultant",
        "physics"
    ],
    "wof:name":"Robert A Cormack",
    "wof:placetype":"venue"
},
  "geometry": {"coordinates":[-71.09600500000001,42.239316],"type":"Point"}
}