{
  "type": "Feature",
  "properties": {
    "iso:country":"US",
    "sg:address":"480 Lincoln Ave",
    "sg:city":"Saugus",
    "sg:classifiers":[
        {
            "category":"Insurance",
            "subcategory":"Insurance Agent",
            "type":"Services"
        }
    ],
    "sg:phone":"+1 781 592 1900",
    "sg:postcode":"01906",
    "sg:province":"MA",
    "wof:name":"Tarpey Insurance Group Inc",
    "wof:placetype":"venue"
},
  "geometry": {"coordinates":[-71.00892399999999,42.448577],"type":"Point"}
}