{
  "type": "Feature",
  "properties": {
    "addr:full": "14 Pine St Taunton MA 02780",
    "addr:housenumber": "14",
    "addr:postcode": "02780",
    "addr:street": "Pine St",
    "iso:country": "US",
    "sg:address": "14 Pine St",
    "sg:city": "Taunton",
    "sg:classifiers": [
      {
        "category": "Building \u0026 Trades",
        "subcategory": "Cleaning \u0026 Sanitation",
        "type": "Services"
      }
    ],
    "sg:phone": "+1 508 823 3506",
    "sg:postcode": "02780",
    "sg:province": "MA",
    "sg:tags": [
      "janitorial"
    ],
    "wof:name": "Costa Cleaning",
    "wof:placetype": "venue"
  },
  "geometry": {"coordinates":[-71.103661,41.901878],"type":"Point"}
}
