{
  "type": "Feature",
  "properties": {
    "iso:country":"US",
    "sg:address":"171 Harvard Ave",
    "sg:city":"Allston",
    "sg:classifiers":[
        {
            "category":"Health Services",
            "subcategory":"Doctor",
            "type":"Services"
        },
        {
            "category":"Health Services",
            "subcategory":"Health Practitioner",
            "type":"Services"
        }
    ],
    "sg:phone":"+1 617 787 4503",
    "sg:postcode":"02134",
    "sg:province":"MA",
    "sg:tags":[
        "medicine",
        "acupuncture",
        "internal"
    ],
    "sg:website":"www.eshantang.com",
    "wof:name":"E Shan Tang",
    "wof:placetype":"venue"
},
  "geometry": {"coordinates":[-71.131623,42.351307],"type":"Point"}
}