{
  "type": "Feature",
  "properties": {
    "iso:country":"US",
    "sg:address":"561 Boylston St",
    "sg:city":"Boston",
    "sg:classifiers":[
        {
            "category":"Professional",
            "subcategory":"Art Services",
            "type":"Services"
        }
    ],
    "sg:phone":"+1 617 236 1858",
    "sg:postcode":"02116",
    "sg:province":"MA",
    "sg:tags":[
        "designer",
        "display",
        "producer"
    ],
    "wof:name":"Sean Mckinney Design Incorporated",
    "wof:placetype":"venue"
},
  "geometry": {"coordinates":[-71.07634400000001,42.350358],"type":"Point"}
}