{
  "type": "Feature",
  "properties": {
    "addr:full":"511 State Hwy 28 West Yarmouth MA 02673",
    "addr:housenumber":"511",
    "addr:postcode":"02673",
    "addr:street":"State Hwy 28",
    "iso:country":"US",
    "sg:address":"511 State Hwy 28",
    "sg:city":"West Yarmouth",
    "sg:classifiers":[
        {
            "category":"Food & Beverages",
            "subcategory":"Liquor & Beverages",
            "type":"Retail Goods"
        }
    ],
    "sg:phone":"+1 508 775 2979",
    "sg:postcode":"02673",
    "sg:province":"MA",
    "wof:name":"Lukes Liquors",
    "wof:placetype":"venue"
},
  "geometry": {"coordinates":[-70.228071,41.681535],"type":"Point"}
}