{
  "type": "Feature",
  "properties": {
    "iso:country":"US",
    "sg:address":"58 E Main St",
    "sg:city":"Southbridge",
    "sg:classifiers":[
        {
            "category":"Food & Beverages",
            "subcategory":"Groceries & Convenience Stores",
            "type":"Retail Goods"
        }
    ],
    "sg:phone":"+1 508 764 9999",
    "sg:postcode":"01550",
    "sg:province":"MA",
    "wof:name":"Thomas Variety Convenience",
    "wof:placetype":"venue"
},
  "geometry": {"coordinates":[-72.025002,42.0723],"type":"Point"}
}