{
  "type": "Feature",
  "properties": {
    "iso:country":"US",
    "sg:address":"228 Park Ave",
    "sg:city":"Worcester",
    "sg:classifiers":[
        {
            "category":"Insurance",
            "subcategory":"Hazard Insurance",
            "type":"Services"
        }
    ],
    "sg:phone":"+1 508 755 4155",
    "sg:postcode":"01609",
    "sg:province":"MA",
    "wof:name":"Whitman Agency",
    "wof:placetype":"venue"
},
  "geometry": {"coordinates":[-71.816012,42.271009],"type":"Point"}
}