{
  "type": "Feature",
  "properties": {
    "iso:country":"US",
    "sg:address":"12 Hyde Park Avenue",
    "sg:city":"Jamaica Plain",
    "sg:classifiers":[
        {
            "category":"Sports & Exercise",
            "subcategory":"Gym",
            "type":"Entertainment"
        },
        {
            "category":"Health Services",
            "subcategory":"Health Practitioner",
            "type":"Services"
        }
    ],
    "sg:phone":"+1 617 983 0788",
    "sg:postcode":"02130",
    "sg:province":"MA",
    "sg:tags":[
        "trainer",
        "therapy",
        "physical"
    ],
    "wof:name":"Brown & Brown Associates",
    "wof:placetype":"venue"
},
  "geometry": {"coordinates":[-71.113939,42.299613],"type":"Point"}
}