{
  "type": "Feature",
  "properties": {
    "addr:full": "12 Hyde Park Avenue Jamaica Plain MA 02130",
    "addr:housenumber": "12",
    "addr:postcode": "02130",
    "addr:street": "Hyde Park Avenue",
    "iso:country": "US",
    "sg:address": "12 Hyde Park Avenue",
    "sg:city": "Jamaica Plain",
    "sg:classifiers": [
      {
        "category": "Sports \u0026 Exercise",
        "subcategory": "Gym",
        "type": "Entertainment"
      },
      {
        "category": "Health Services",
        "subcategory": "Health Practitioner",
        "type": "Services"
      }
    ],
    "sg:phone": "+1 617 983 0788",
    "sg:postcode": "02130",
    "sg:province": "MA",
    "sg:tags": [
      "trainer",
      "therapy",
      "physical"
    ],
    "wof:name": "Brown \u0026 Brown Associates",
    "wof:placetype": "venue"
  },
  "geometry": {"coordinates":[-71.113939,42.299613],"type":"Point"}
}
