{
  "type": "Feature",
  "properties": {
    "iso:country":"US",
    "sg:address":"248 Columbia St",
    "sg:city":"Adams",
    "sg:classifiers":[
        {
            "category":"Professional",
            "subcategory":"Business Services",
            "type":"Services"
        }
    ],
    "sg:phone":"+1   ",
    "sg:postcode":"01220",
    "sg:province":"MA",
    "wof:name":"Lesure Enterprises",
    "wof:placetype":"venue"
},
  "geometry": {"coordinates":[-73.11242900000001,42.641349],"type":"Point"}
}