{
  "type": "Feature",
  "properties": {
    "addr:full": "248 Columbia St Adams MA 01220",
    "addr:housenumber": "248",
    "addr:postcode": "01220",
    "addr:street": "Columbia St",
    "iso:country": "US",
    "sg:address": "248 Columbia St",
    "sg:city": "Adams",
    "sg:classifiers": [
      {
        "category": "Professional",
        "subcategory": "Business Services",
        "type": "Services"
      }
    ],
    "sg:phone": "+1   ",
    "sg:postcode": "01220",
    "sg:province": "MA",
    "wof:name": "Lesure Enterprises",
    "wof:placetype": "venue"
  },
  "geometry": {"coordinates":[-73.112429,42.641349],"type":"Point"}
}
