{
  "type": "Feature",
  "properties": {
    "addr:full":"263 Central St Foxboro MA 02035",
    "addr:housenumber":"263",
    "addr:postcode":"02035",
    "addr:street":"Central St",
    "iso:country":"US",
    "sg:address":"263 Central St",
    "sg:city":"Foxboro",
    "sg:classifiers":[
        {
            "category":"Shopping",
            "subcategory":"Optical Goods",
            "type":"Retail Goods"
        }
    ],
    "sg:phone":"+1 508 543 0880",
    "sg:postcode":"02035",
    "sg:province":"MA",
    "sg:tags":[
        "sun",
        "goggles",
        "sunglasses"
    ],
    "wof:name":"Jim Maui Sunglasses",
    "wof:placetype":"venue"
},
  "geometry": {"coordinates":[-71.236405,42.050371],"type":"Point"}
}