{
  "type": "Feature",
  "properties": {
    "addr:full":"262 Groton Rd Westford MA 01886",
    "addr:housenumber":"262",
    "addr:postcode":"01886",
    "addr:street":"Groton Rd",
    "iso:country":"US",
    "sg:address":"262 Groton Rd",
    "sg:city":"Westford",
    "sg:classifiers":[
        {
            "category":"Autos & Motor Vehicles",
            "subcategory":"Fuel & Gas Station",
            "type":"Retail Goods"
        }
    ],
    "sg:phone":"+1 978 692 8719",
    "sg:postcode":"01886",
    "sg:province":"MA",
    "sg:tags":[
        "oil"
    ],
    "wof:name":"Westford Getty",
    "wof:placetype":"venue"
},
  "geometry": {"coordinates":[-71.45079699999999,42.616063],"type":"Point"}
}