{
  "type": "Feature",
  "properties": {
    "iso:country":"US",
    "sg:address":"24 State St",
    "sg:city":"Leominster",
    "sg:classifiers":[
        {
            "category":"Real Estate",
            "subcategory":"Real Estate Operator",
            "type":"Services"
        }
    ],
    "sg:phone":"+1 978 534 4522",
    "sg:postcode":"01453",
    "sg:province":"MA",
    "sg:tags":[
        "apartment"
    ],
    "wof:name":"Riverside Village Apartments",
    "wof:placetype":"venue"
},
  "geometry": {"coordinates":[-71.767117,42.556158],"type":"Point"}
}