{
  "type": "Feature",
  "properties": {
    "addr:full": "59 Temple Place Boston MA 02111",
    "addr:housenumber": "59",
    "addr:postcode": "02111",
    "addr:street": "Temple Place",
    "iso:country": "US",
    "sg:address": "59 Temple Place",
    "sg:city": "Boston",
    "sg:classifiers": [
      {
        "category": "Professional",
        "subcategory": "Lawyer \u0026 Legal Services",
        "type": "Services"
      }
    ],
    "sg:phone": "+1 617 338 9433",
    "sg:postcode": "02111",
    "sg:province": "MA",
    "wof:name": "Vaughan Harold L Lwyr",
    "wof:placetype": "venue"
  },
  "geometry": {"coordinates":[-71.061701,42.355084],"type":"Point"}
}
