{
  "type": "Feature",
  "properties": {
    "addr:full": "401 Middle Rd Chilmark MA 02535",
    "addr:housenumber": "401",
    "addr:postcode": "02535",
    "addr:street": "Middle Rd",
    "iso:country": "US",
    "sg:address": "401 Middle Rd",
    "sg:city": "Chilmark",
    "sg:classifiers": [
      {
        "category": "Government",
        "subcategory": "Office",
        "type": "Public Place"
      }
    ],
    "sg:phone": "+1 508 645 2114",
    "sg:postcode": "02535",
    "sg:province": "MA",
    "sg:tags": [
      "city",
      "planning",
      "dev"
    ],
    "wof:name": "Chilmark Zoning Board-Appeals",
    "wof:placetype": "venue"
  },
  "geometry": {"coordinates":[-70.742678,41.345013],"type":"Point"}
}
