{
  "type": "Feature",
  "properties": {
    "iso:country":"US",
    "sg:address":"18 Wyman St",
    "sg:city":"Stoughton",
    "sg:classifiers":[
        {
            "category":"Shopping",
            "subcategory":"Jewelry",
            "type":"Retail Goods"
        }
    ],
    "sg:phone":"+1 781 344 5000",
    "sg:postcode":"02072",
    "sg:province":"MA",
    "wof:name":"Work of Art",
    "wof:placetype":"venue"
},
  "geometry": {"coordinates":[-71.10216200000001,42.124247],"type":"Point"}
}