{
  "type": "Feature",
  "properties": {
    "addr:full":"89 Main St Bridgewater MA 02324",
    "addr:housenumber":"89",
    "addr:postcode":"02324",
    "addr:street":"Main St",
    "iso:country":"US",
    "sg:address":"89 Main St",
    "sg:city":"Bridgewater",
    "sg:classifiers":[
        {
            "category":"Government",
            "subcategory":"Office",
            "type":"Public Place"
        }
    ],
    "sg:phone":"+1   ",
    "sg:postcode":"02324",
    "sg:province":"MA",
    "sg:tags":[
        "congressman"
    ],
    "wof:name":"Barney Frank Congressman",
    "wof:placetype":"venue"
},
  "geometry": {"coordinates":[-70.97774099999999,41.992028],"type":"Point"}
}