{
  "type": "Feature",
  "properties": {
    "iso:country":"US",
    "sg:address":"55 Middlesex St",
    "sg:city":"North Chelmsford",
    "sg:classifiers":[
        {
            "category":"Professional",
            "subcategory":"Employment Agencies",
            "type":"Services"
        }
    ],
    "sg:phone":"+1 978 251 7272",
    "sg:postcode":"01863",
    "sg:province":"MA",
    "sg:tags":[
        "help",
        "contractor"
    ],
    "sg:website":"www.net-temps.com",
    "wof:name":"Net Temps",
    "wof:placetype":"venue"
},
  "geometry": {"coordinates":[-71.37887000000001,42.637984],"type":"Point"}
}