{
  "type": "Feature",
  "properties": {
    "iso:country":"US",
    "sg:address":"28 Falmouth Rd",
    "sg:city":"Mashpee",
    "sg:classifiers":[
        {
            "category":"Shopping",
            "subcategory":"Pharmacy",
            "type":"Retail Goods"
        }
    ],
    "sg:phone":"+1 508 477 1535",
    "sg:postcode":"02649",
    "sg:province":"MA",
    "sg:website":"www.cvs.com",
    "wof:name":"CVS Pharmacy",
    "wof:placetype":"venue"
},
  "geometry": {"coordinates":[-70.457764,41.634379],"type":"Point"}
}