{
  "type": "Feature",
  "properties": {
    "iso:country":"US",
    "sg:address":"191 W Pomeroy Ln",
    "sg:city":"Amherst",
    "sg:classifiers":[
        {
            "category":"Restaurant",
            "type":"Food & Drink"
        }
    ],
    "sg:phone":"+1 413 253 7094",
    "sg:postcode":"01002",
    "sg:province":"MA",
    "sg:tags":[
        "caterer"
    ],
    "wof:name":"J & L Caters At Hickory Ridge",
    "wof:placetype":"venue"
},
  "geometry": {"coordinates":[-72.53027899999999,42.340373],"type":"Point"}
}