{
  "type": "Feature",
  "properties": {
    "addr:full": "191 W Pomeroy Ln Amherst MA 01002",
    "addr:housenumber": "191",
    "addr:postcode": "01002",
    "addr:street": "W Pomeroy Ln",
    "iso:country": "US",
    "sg:address": "191 W Pomeroy Ln",
    "sg:city": "Amherst",
    "sg:classifiers": [
      {
        "category": "Restaurant",
        "type": "Food \u0026 Drink"
      }
    ],
    "sg:phone": "+1 413 253 7094",
    "sg:postcode": "01002",
    "sg:province": "MA",
    "sg:tags": [
      "caterer"
    ],
    "wof:name": "J \u0026 L Caters At Hickory Ridge",
    "wof:placetype": "venue"
  },
  "geometry": {"coordinates":[-72.530279,42.340373],"type":"Point"}
}
