{
  "type": "Feature",
  "properties": {
    "addr:full":"1385 Berkshire Ave Indian Orchard MA 01151",
    "addr:housenumber":"1385",
    "addr:postcode":"01151",
    "addr:street":"Berkshire Ave",
    "iso:country":"US",
    "sg:address":"1385 Berkshire Ave",
    "sg:city":"Indian Orchard",
    "sg:classifiers":[
        {
            "category":"Education",
            "subcategory":"School",
            "type":"Public Place"
        }
    ],
    "sg:phone":"+1 413 787 7510",
    "sg:postcode":"01151",
    "sg:province":"MA",
    "wof:name":"John F Kennedy Middle School",
    "wof:placetype":"venue"
},
  "geometry": {"coordinates":[-72.51233000000001,42.154827],"type":"Point"}
}