{
  "type": "Feature",
  "properties": {
    "addr:full":"12 Kimbrough Rd Billerica MA 01821",
    "addr:housenumber":"12",
    "addr:postcode":"01821",
    "addr:street":"Kimbrough Rd",
    "iso:country":"US",
    "sg:address":"12 Kimbrough Rd",
    "sg:city":"Billerica",
    "sg:classifiers":[
        {
            "category":"Professional",
            "type":"Services"
        }
    ],
    "sg:phone":"+1 978 663 1865",
    "sg:postcode":"01821",
    "sg:province":"MA",
    "sg:tags":[
        "establishment"
    ],
    "wof:name":"GBC Automated Finishings",
    "wof:placetype":"venue"
},
  "geometry": {"coordinates":[-71.228955,42.565248],"type":"Point"}
}