{
  "type": "Feature",
  "properties": {
    "addr:full":"127 Augustus St Revere MA 02151",
    "addr:housenumber":"127",
    "addr:postcode":"02151",
    "addr:street":"Augustus St",
    "iso:country":"US",
    "sg:address":"127 Augustus St",
    "sg:city":"Revere",
    "sg:classifiers":[
        {
            "category":"Building & Trades",
            "subcategory":"Construction",
            "type":"Services"
        }
    ],
    "sg:phone":"+1 617 884 6858",
    "sg:postcode":"02151",
    "sg:province":"MA",
    "sg:tags":[
        "resurfacing",
        "refinishing",
        "floor"
    ],
    "wof:name":"Michael Floor Sanding",
    "wof:placetype":"venue"
},
  "geometry": {"coordinates":[-71.014931,42.426612],"type":"Point"}
}