{
  "type": "Feature",
  "properties": {
    "iso:country":"US",
    "sg:address":"689 Massachusetts Ave",
    "sg:city":"Cambridge",
    "sg:classifiers":[
        {
            "category":"Professional",
            "subcategory":"Lawyer & Legal Services",
            "type":"Services"
        }
    ],
    "sg:phone":"+1 617 871 6335",
    "sg:postcode":"02139",
    "sg:province":"MA",
    "wof:name":"Heinlein & Beeler PC",
    "wof:placetype":"venue"
},
  "geometry": {"coordinates":[-71.104316,42.365944],"type":"Point"}
}