{
  "type": "Feature",
  "properties": {
    "addr:full": "63 Rotch St New Bedford MA 02740",
    "addr:housenumber": "63",
    "addr:postcode": "02740",
    "addr:street": "Rotch St",
    "iso:country": "US",
    "sg:address": "63 Rotch St",
    "sg:city": "New Bedford",
    "sg:classifiers": [
      {
        "category": "Professional",
        "subcategory": "Lawyer \u0026 Legal Services",
        "type": "Services"
      }
    ],
    "sg:phone": "+1   ",
    "sg:postcode": "02740",
    "sg:province": "MA",
    "wof:name": "Federal Post Conviction",
    "wof:placetype": "venue"
  },
  "geometry": {"coordinates":[-70.942592,41.630444],"type":"Point"}
}
