{
  "type": "Feature",
  "properties": {
    "iso:country":"US",
    "sg:address":"24 John St Unit 1",
    "sg:city":"Brookline",
    "sg:classifiers":[
        {
            "category":"Building & Trades",
            "subcategory":"Construction",
            "type":"Services"
        }
    ],
    "sg:phone":"+1 617 739 7223",
    "sg:postcode":"02446",
    "sg:province":"MA",
    "sg:tags":[
        "tile-contractors"
    ],
    "wof:name":"Team Tile",
    "wof:placetype":"venue"
},
  "geometry": {"coordinates":[-71.12106799999999,42.343692],"type":"Point"}
}