{
  "type": "Feature",
  "properties": {
    "addr:full":"125 Lawrence St Malden MA 02148",
    "addr:housenumber":"125",
    "addr:postcode":"02148",
    "addr:street":"Lawrence St",
    "iso:country":"US",
    "sg:address":"125 Lawrence St",
    "sg:city":"Malden",
    "sg:classifiers":[
        {
            "category":"Building & Trades",
            "subcategory":"Construction",
            "type":"Services"
        }
    ],
    "sg:phone":"+1 781 388 3739",
    "sg:postcode":"02148",
    "sg:province":"MA",
    "sg:tags":[
        "painting",
        "contractor"
    ],
    "wof:name":"Spadaro Painting",
    "wof:placetype":"venue"
},
  "geometry": {"coordinates":[-71.027338,42.433176],"type":"Point"}
}