{
  "type": "Feature",
  "properties": {
    "addr:full":"206 Breeds Hill Rd Hyannis MA 02601",
    "addr:housenumber":"206",
    "addr:postcode":"02601",
    "addr:street":"Breeds Hill Rd",
    "iso:country":"US",
    "sg:address":"206 Breeds Hill Rd",
    "sg:city":"Hyannis",
    "sg:classifiers":[
        {
            "category":"Social Services",
            "type":"Services"
        }
    ],
    "sg:phone":"+1 508 775 0275",
    "sg:postcode":"02601",
    "sg:province":"MA",
    "sg:tags":[
        "organization",
        "welfare"
    ],
    "wof:name":"MSPCC",
    "wof:placetype":"venue"
},
  "geometry": {"coordinates":[-70.290221,41.681989],"type":"Point"}
}