{
  "type": "Feature",
  "properties": {
    "addr:full":"81 Spring St Watertown MA 02472",
    "addr:housenumber":"81",
    "addr:postcode":"02472",
    "addr:street":"Spring St",
    "iso:country":"US",
    "sg:address":"81 Spring St",
    "sg:city":"Watertown",
    "sg:classifiers":[
        {
            "category":"Professional",
            "subcategory":"Art Services",
            "type":"Services"
        }
    ],
    "sg:phone":"+1   ",
    "sg:postcode":"02472",
    "sg:province":"MA",
    "sg:tags":[
        "photography",
        "commercial"
    ],
    "wof:name":"David Caras Photographer",
    "wof:placetype":"venue"
},
  "geometry": {"coordinates":[-71.181697,42.368084],"type":"Point"}
}