{
  "type": "Feature",
  "properties": {
    "addr:full":"100 Tower Office Park Woburn MA 01801",
    "addr:housenumber":"100",
    "addr:postcode":"01801",
    "addr:street":"Office Park",
    "iso:country":"US",
    "sg:address":"100 Tower Office Park",
    "sg:city":"Woburn",
    "sg:classifiers":[
        {
            "category":"Organizations",
            "subcategory":"Labor Organization",
            "type":"Services"
        }
    ],
    "sg:phone":"+1 781 937 9600",
    "sg:postcode":"01801",
    "sg:province":"MA",
    "wof:name":"Communications Workers-America",
    "wof:placetype":"venue"
},
  "geometry": {"coordinates":[-71.123653,42.497697],"type":"Point"}
}