{
  "type": "Feature",
  "properties": {
    "iso:country":"US",
    "sg:address":"1068 Main St",
    "sg:city":"Walpole",
    "sg:classifiers":[
        {
            "category":"Professional",
            "subcategory":"Lawyer & Legal Services",
            "type":"Services"
        }
    ],
    "sg:phone":"+1 508 668 5595",
    "sg:postcode":"02081",
    "sg:province":"MA",
    "sg:tags":[
        "attorney"
    ],
    "wof:name":"Robert Fennessy Law Offices",
    "wof:placetype":"venue"
},
  "geometry": {"coordinates":[-71.25409999999999,42.1443],"type":"Point"}
}