{
  "type": "Feature",
  "properties": {
    "iso:country":"US",
    "sg:address":"104 Gold St",
    "sg:city":"Agawam",
    "sg:classifiers":[
        {
            "category":"Manufacturing",
            "subcategory":"Tools & Machinery",
            "type":"Manufacturing & Wholesale Goods"
        }
    ],
    "sg:phone":"+1 413 786 1680",
    "sg:postcode":"01001",
    "sg:province":"MA",
    "sg:tags":[
        "physician",
        "surgeon"
    ],
    "wof:name":"Microtest Internet Svc",
    "wof:placetype":"venue"
},
  "geometry": {"coordinates":[-72.63681699999999,42.052489],"type":"Point"}
}