{
  "type": "Feature",
  "properties": {
    "addr:full": "127 Rodney French Blvd New Bedford MA 02744",
    "addr:housenumber": "127",
    "addr:postcode": "02744",
    "addr:street": "Rodney French Blvd",
    "iso:country": "US",
    "sg:address": "127 Rodney French Blvd",
    "sg:city": "New Bedford",
    "sg:classifiers": [
      {
        "category": "Home \u0026 Garden",
        "subcategory": "Furniture",
        "type": "Retail Goods"
      }
    ],
    "sg:phone": "+1 508 999 4414",
    "sg:postcode": "02744",
    "sg:province": "MA",
    "sg:website": "www.furniturecity.org",
    "wof:name": "Furniture City/Mattress City",
    "wof:placetype": "venue"
  },
  "geometry": {"coordinates":[-70.917412,41.610714],"type":"Point"}
}
