{
  "type": "Feature",
  "properties": {
    "iso:country":"US",
    "sg:address":"85 Broadway",
    "sg:city":"Somerville",
    "sg:classifiers":[
        {
            "category":"Professional",
            "subcategory":"Accounting & Tax Preparation",
            "type":"Services"
        }
    ],
    "sg:phone":"+1 617 627 6644",
    "sg:postcode":"02145",
    "sg:province":"MA",
    "sg:tags":[
        "bookkeeping"
    ],
    "wof:name":"Alpha Pro Tax",
    "wof:placetype":"venue"
},
  "geometry": {"coordinates":[-71.082283,42.38728],"type":"Point"}
}