{
  "type": "Feature",
  "properties": {
    "addr:full": "85 Broadway Somerville MA 02145",
    "addr:housenumber": "85",
    "addr:postcode": "02145",
    "addr:street": "Broadway",
    "iso:country": "US",
    "sg:address": "85 Broadway",
    "sg:city": "Somerville",
    "sg:classifiers": [
      {
        "category": "Professional",
        "subcategory": "Accounting \u0026 Tax Preparation",
        "type": "Services"
      }
    ],
    "sg:phone": "+1 617 627 6644",
    "sg:postcode": "02145",
    "sg:province": "MA",
    "sg:tags": [
      "bookkeeping"
    ],
    "wof:name": "Alpha Pro Tax",
    "wof:placetype": "venue"
  },
  "geometry": {"coordinates":[-71.082283,42.38728],"type":"Point"}
}
