{
  "type": "Feature",
  "properties": {
    "addr:full":"721 Main St Mashpee MA 02649",
    "addr:housenumber":"721",
    "addr:postcode":"02649",
    "addr:street":"Main St",
    "iso:country":"US",
    "sg:address":"721 Main St",
    "sg:city":"Mashpee",
    "sg:classifiers":[
        {
            "category":"Building & Trades",
            "subcategory":"Cleaning & Sanitation",
            "type":"Services"
        }
    ],
    "sg:phone":"+1 508 539 4944",
    "sg:postcode":"02649",
    "sg:province":"MA",
    "sg:tags":[
        "window"
    ],
    "wof:name":"Mark Lee Window Cleaning Inc",
    "wof:placetype":"venue"
},
  "geometry": {"coordinates":[-70.507448,41.67056],"type":"Point"}
}