{
  "type": "Feature",
  "properties": {
    "iso:country":"US",
    "sg:address":"354 Congress St",
    "sg:city":"Boston",
    "sg:classifiers":[
        {
            "category":"Museum",
            "type":"Entertainment"
        }
    ],
    "sg:phone":"+1 617 422 5822",
    "sg:postcode":"02210",
    "sg:province":"MA",
    "sg:tags":[
        "organization",
        "arts",
        "information"
    ],
    "wof:name":"Artery Creative Inc",
    "wof:placetype":"venue"
},
  "geometry": {"coordinates":[-71.048208,42.350197],"type":"Point"}
}