{
  "type": "Feature",
  "properties": {
    "addr:full":"8 E Falmouth Hwy East Falmouth MA 02536",
    "addr:housenumber":"8",
    "addr:postcode":"02536",
    "addr:street":"E Falmouth Hwy",
    "iso:country":"US",
    "sg:address":"8 E Falmouth Hwy",
    "sg:city":"East Falmouth",
    "sg:classifiers":[
        {
            "category":"Real Estate",
            "subcategory":"Real Estate Agent",
            "type":"Services"
        }
    ],
    "sg:phone":"+1   ",
    "sg:postcode":"02536",
    "sg:province":"MA",
    "wof:name":"Monteiro Real Estate",
    "wof:placetype":"venue"
},
  "geometry": {"coordinates":[-70.57183499999999,41.578364],"type":"Point"}
}