{
  "type": "Feature",
  "properties": {
    "iso:country":"US",
    "sg:address":"178 Lowell St",
    "sg:city":"Lexington",
    "sg:classifiers":[
        {
            "category":"Health Services",
            "subcategory":"Nursing And Care Facility",
            "type":"Services"
        }
    ],
    "sg:phone":"+1 781 862 7400",
    "sg:postcode":"02420",
    "sg:province":"MA",
    "sg:tags":[
        "home",
        "convalescent"
    ],
    "sg:website":"www.kone.com",
    "wof:name":"Lexington Health Care",
    "wof:placetype":"venue"
},
  "geometry": {"coordinates":[-71.19244500000001,42.440194],"type":"Point"}
}