{
  "type": "Feature",
  "properties": {
    "addr:full": "178 Lowell St Lexington MA 02420",
    "addr:housenumber": "178",
    "addr:postcode": "02420",
    "addr:street": "Lowell St",
    "iso:country": "US",
    "ovtr:label": "Lexington Health Care, 178 Lowell St Lexington MA US",
    "ovtr:similarity": 2.497713088989258,
    "sg:address": "178 Lowell St",
    "sg:city": "Lexington",
    "sg:classifiers": [
      {
        "category": "Health Services",
        "subcategory": "Nursing And Care Facility",
        "type": "Services"
      }
    ],
    "sg:phone": "+1 781 862 7400",
    "sg:postcode": "02420",
    "sg:province": "MA",
    "sg:tags": [
      "home",
      "convalescent"
    ],
    "sg:website": "www.kone.com",
    "wof:name": "Lexington Health Care",
    "wof:placetype": "venue"
  },
  "geometry": {"coordinates":[-71.192445,42.440194],"type":"Point"}
}
