{
  "type": "Feature",
  "properties": {
    "iso:country":"US",
    "sg:address":"98 Boylston St",
    "sg:city":"Boston",
    "sg:classifiers":[
        {
            "category":"Building & Trades",
            "subcategory":"Equipment Rental",
            "type":"Services"
        }
    ],
    "sg:phone":"+1 617 542 8383",
    "sg:postcode":"02116",
    "sg:province":"MA",
    "sg:tags":[
        "leasing",
        "furniture"
    ],
    "wof:name":"Cort Furniture Rental",
    "wof:placetype":"venue"
},
  "geometry": {"coordinates":[-71.065439,42.352341],"type":"Point"}
}