{
  "type": "Feature",
  "properties": {
    "iso:country":"US",
    "sg:address":"40 Old Center",
    "sg:city":"Winchendon",
    "sg:classifiers":[
        {
            "category":"Social Services",
            "type":"Services"
        }
    ],
    "sg:phone":"+1 978 297 3313",
    "sg:postcode":"01475",
    "sg:province":"MA",
    "sg:tags":[
        "counselor",
        "marriage",
        "family"
    ],
    "wof:name":"Yvonne G Harrington Cslng Svc",
    "wof:placetype":"venue"
},
  "geometry": {"coordinates":[-72.04094600000001,42.660636],"type":"Point"}
}