{
  "type": "Feature",
  "properties": {
    "iso:country":"US",
    "sg:address":"55 Market St",
    "sg:city":"Ipswich",
    "sg:classifiers":[
        {
            "category":"Personal",
            "subcategory":"Beauty Salon",
            "type":"Services"
        }
    ],
    "sg:phone":"+1 978 356 7800",
    "sg:postcode":"01938",
    "sg:province":"MA",
    "wof:name":"Salon Patrice",
    "wof:placetype":"venue"
},
  "geometry": {"coordinates":[-70.839106,42.679231],"type":"Point"}
}