{
  "type": "Feature",
  "properties": {
    "addr:full":"234 Essex St Middleton MA 01949",
    "addr:housenumber":"234",
    "addr:postcode":"01949",
    "addr:street":"Essex St",
    "iso:country":"US",
    "sg:address":"234 Essex St",
    "sg:city":"Middleton",
    "sg:classifiers":[
        {
            "category":"Health Services",
            "subcategory":"Podiatrist",
            "type":"Services"
        }
    ],
    "sg:phone":"+1 508 364 9739",
    "sg:postcode":"01949",
    "sg:province":"MA",
    "sg:tags":[
        "equipment",
        "supply"
    ],
    "wof:name":"Axess Medical",
    "wof:placetype":"venue"
},
  "geometry": {"coordinates":[-71.04038300000001,42.628104],"type":"Point"}
}