{
  "type": "Feature",
  "properties": {
    "addr:full": "21 Walden Square Rd Cambridge MA 02140",
    "addr:housenumber": "21",
    "addr:postcode": "02140",
    "addr:street": "Walden Square Rd",
    "iso:country": "US",
    "sg:address": "21 Walden Square Rd",
    "sg:city": "Cambridge",
    "sg:classifiers": [
      {
        "category": "Professional",
        "subcategory": "Business Services",
        "type": "Services"
      }
    ],
    "sg:phone": "+1 617 497 4913",
    "sg:postcode": "02140",
    "sg:province": "MA",
    "wof:name": "Pic Disc 1",
    "wof:placetype": "venue"
  },
  "geometry": {"coordinates":[-71.132611,42.389195],"type":"Point"}
}
