{
  "type": "Feature",
  "properties": {
    "addr:full":"102 Pakachoag St Auburn MA 01501",
    "addr:housenumber":"102",
    "addr:postcode":"01501",
    "addr:street":"Pakachoag St",
    "iso:country":"US",
    "sg:address":"102 Pakachoag St",
    "sg:city":"Auburn",
    "sg:classifiers":[
        {
            "category":"Social Services",
            "subcategory":"Child Care",
            "type":"Services"
        }
    ],
    "sg:phone":"+1 508 767 1214",
    "sg:postcode":"01501",
    "sg:province":"MA",
    "sg:website":"www.simplyput.net",
    "wof:name":"A Step Ahead",
    "wof:placetype":"venue"
},
  "geometry": {"coordinates":[-71.814046,42.224493],"type":"Point"}
}