{
  "type": "Feature",
  "properties": {
    "iso:country":"US",
    "sg:address":"322 West Ave",
    "sg:city":"Ludlow",
    "sg:classifiers":[
        {
            "category":"Personal",
            "subcategory":"Beauty Salon",
            "type":"Services"
        }
    ],
    "sg:phone":"+1 413 547 8600",
    "sg:postcode":"01056",
    "sg:province":"MA",
    "sg:tags":[
        "hair",
        "stylist"
    ],
    "wof:name":"Hair West",
    "wof:placetype":"venue"
},
  "geometry": {"coordinates":[-72.48617400000001,42.165427],"type":"Point"}
}