{
  "type": "Feature",
  "properties": {
    "addr:full": "7 E Central St Franklin MA 02038",
    "addr:housenumber": "7",
    "addr:postcode": "02038",
    "addr:street": "E Central St",
    "iso:country": "US",
    "ovtr:label": "H\u0026R Block, 7 E Central St Franklin MA US",
    "ovtr:similarity": 2.8380188941955566,
    "sg:address": "7 E Central St",
    "sg:city": "Franklin",
    "sg:classifiers": [
      {
        "category": "Professional",
        "subcategory": "Accounting \u0026 Tax Preparation",
        "type": "Services"
      },
      {
        "category": "Banks \u0026 Credit Unions",
        "subcategory": "Financial Services",
        "type": "Services"
      }
    ],
    "sg:phone": "+1 508 528 6012",
    "sg:postcode": "02038",
    "sg:province": "MA",
    "sg:tags": [
      "return",
      "preparation-business",
      "taxes-consultants",
      "loan",
      "reporting",
      "representative",
      "alternative",
      "bookkeeping"
    ],
    "sg:website": "http://www.hrblock.com",
    "wof:name": "H\u0026R Block",
    "wof:placetype": "venue"
  },
  "geometry": {"coordinates":[-71.396698,42.082432],"type":"Point"}
}
