{
  "type": "Feature",
  "properties": {
    "iso:country":"US",
    "sg:address":"51 Winthrop St",
    "sg:city":"Kingston",
    "sg:classifiers":[
        {
            "category":"Building & Trades",
            "subcategory":"Construction",
            "type":"Services"
        }
    ],
    "sg:phone":"+1   ",
    "sg:postcode":"02364",
    "sg:province":"MA",
    "sg:tags":[
        "house"
    ],
    "wof:name":"Omalleys Construction",
    "wof:placetype":"venue"
},
  "geometry": {"coordinates":[-70.732022,42.005868],"type":"Point"}
}