{
  "type": "Feature",
  "properties": {
    "addr:full": "52 Perkins St Brockton MA 02302",
    "addr:housenumber": "52",
    "addr:postcode": "02302",
    "addr:street": "Perkins St",
    "iso:country": "US",
    "sg:address": "52 Perkins St",
    "sg:city": "Brockton",
    "sg:classifiers": [
      {
        "category": "Manufacturing",
        "subcategory": "Metals",
        "type": "Manufacturing \u0026 Wholesale Goods"
      }
    ],
    "sg:phone": "+1 508 588 0186",
    "sg:postcode": "02302",
    "sg:province": "MA",
    "sg:tags": [
      "transfer",
      "heat",
      "material"
    ],
    "sg:website": "www.heatpress.com",
    "wof:name": "George Knight Co",
    "wof:placetype": "venue"
  },
  "geometry": {"coordinates":[-71.015538,42.079685],"type":"Point"}
}
