{
  "type": "Feature",
  "properties": {
    "addr:full":"1059 Main St Worcester MA 01603",
    "addr:housenumber":"1059",
    "addr:postcode":"01603",
    "addr:street":"Main St",
    "iso:country":"US",
    "sg:address":"1059 Main St",
    "sg:city":"Worcester",
    "sg:classifiers":[
        {
            "category":"Social Services",
            "type":"Services"
        }
    ],
    "sg:phone":"+1 508 755 6403",
    "sg:postcode":"01603",
    "sg:province":"MA",
    "sg:tags":[
        "organization",
        "welfare"
    ],
    "sg:website":"www.jeremiahsinn.org",
    "wof:name":"Jeremiah's Inn",
    "wof:placetype":"venue"
},
  "geometry": {"coordinates":[-71.831605,42.24534],"type":"Point"}
}