{
  "type": "Feature",
  "properties": {
    "addr:full":"266 Border St East Boston MA 02128",
    "addr:housenumber":"266",
    "addr:postcode":"02128",
    "addr:street":"Border St",
    "iso:country":"US",
    "sg:address":"266 Border St",
    "sg:city":"East Boston",
    "sg:classifiers":[
        {
            "category":"Wholesale",
            "subcategory":"Stationery",
            "type":"Manufacturing & Wholesale Goods"
        }
    ],
    "sg:phone":"+1 617 567 6200",
    "sg:postcode":"02128",
    "sg:province":"MA",
    "sg:tags":[
        "product",
        "paper"
    ],
    "wof:name":"A & M Paper Converting & Sales",
    "wof:placetype":"venue"
},
  "geometry": {"coordinates":[-71.03989199999999,42.375816],"type":"Point"}
}