{
  "type": "Feature",
  "properties": {
    "addr:full": "266 Border St East Boston MA 02128",
    "addr:housenumber": "266",
    "addr:postcode": "02128",
    "addr:street": "Border St",
    "iso:country": "US",
    "sg:address": "266 Border St",
    "sg:city": "East Boston",
    "sg:classifiers": [
      {
        "category": "Wholesale",
        "subcategory": "Stationery",
        "type": "Manufacturing \u0026 Wholesale Goods"
      }
    ],
    "sg:phone": "+1 617 567 6200",
    "sg:postcode": "02128",
    "sg:province": "MA",
    "sg:tags": [
      "product",
      "paper"
    ],
    "wof:name": "A \u0026 M Paper Converting \u0026 Sales",
    "wof:placetype": "venue"
  },
  "geometry": {"coordinates":[-71.039892,42.375816],"type":"Point"}
}
