{
  "type": "Feature",
  "properties": {
    "iso:country":"US",
    "sg:address":"30 Florence Rd",
    "sg:city":"Easthampton",
    "sg:classifiers":[
        {
            "category":"Wholesale",
            "subcategory":"Farm Supplies",
            "type":"Manufacturing & Wholesale Goods"
        }
    ],
    "sg:phone":"+1 413 527 1612",
    "sg:postcode":"01027",
    "sg:province":"MA",
    "sg:tags":[
        "horse",
        "dealer"
    ],
    "wof:name":"Heritage Farm",
    "wof:placetype":"venue"
},
  "geometry": {"coordinates":[-72.672299,42.287232],"type":"Point"}
}