{
  "type": "Feature",
  "properties": {
    "addr:full":"112 Burlington Mall Rd Burlington MA 01803",
    "addr:housenumber":"112",
    "addr:postcode":"01803",
    "addr:street":"Burlington Mall Rd",
    "iso:country":"US",
    "sg:address":"112 Burlington Mall Rd",
    "sg:city":"Burlington",
    "sg:classifiers":[
        {
            "category":"Home & Garden",
            "subcategory":"Furniture",
            "type":"Retail Goods"
        }
    ],
    "sg:phone":"+1 781 270 6633",
    "sg:postcode":"01803",
    "sg:province":"MA",
    "sg:tags":[
        "mattress"
    ],
    "wof:name":"Mattress Discounters",
    "wof:placetype":"venue"
},
  "geometry": {"coordinates":[-71.21157599999999,42.485957],"type":"Point"}
}