{
  "type": "Feature",
  "properties": {
    "addr:full": "6 Woodlawn Cir East Bridgewater MA 02382",
    "addr:housenumber": "6",
    "addr:postcode": "02382",
    "addr:street": "Woodlawn Cir",
    "iso:country": "US",
    "sg:address": "6 Woodlawn Cir",
    "sg:city": "East Bridgewater",
    "sg:classifiers": [
      {
        "category": "Building \u0026 Trades",
        "subcategory": "Construction",
        "type": "Services"
      }
    ],
    "sg:phone": "+1 508 690 1900",
    "sg:postcode": "02382",
    "sg:province": "MA",
    "sg:tags": [
      "contractor"
    ],
    "wof:name": "Rhoman Roofing Co",
    "wof:placetype": "venue"
  },
  "geometry": {"coordinates":[-70.94531,42.068314],"type":"Point"}
}
