{
  "type": "Feature",
  "properties": {
    "iso:country":"US",
    "sg:address":"6 Woodlawn Cir",
    "sg:city":"East Bridgewater",
    "sg:classifiers":[
        {
            "category":"Building & Trades",
            "subcategory":"Construction",
            "type":"Services"
        }
    ],
    "sg:phone":"+1 508 690 1900",
    "sg:postcode":"02382",
    "sg:province":"MA",
    "sg:tags":[
        "contractor"
    ],
    "wof:name":"Rhoman Roofing Co",
    "wof:placetype":"venue"
},
  "geometry": {"coordinates":[-70.94531000000001,42.068314],"type":"Point"}
}