{
  "type": "Feature",
  "properties": {
    "iso:country":"US",
    "sg:address":"15 Joshua Rd",
    "sg:city":"Wrentham",
    "sg:classifiers":[
        {
            "category":"Home & Garden",
            "subcategory":"Hardware",
            "type":"Retail Goods"
        }
    ],
    "sg:phone":"+1   ",
    "sg:postcode":"02093",
    "sg:province":"MA",
    "wof:name":"Snap-On Tools",
    "wof:placetype":"venue"
},
  "geometry": {"coordinates":[-71.34351599999999,42.088991],"type":"Point"}
}