{
  "type": "Feature",
  "properties": {
    "addr:full": "15 Joshua Rd Wrentham MA 02093",
    "addr:housenumber": "15",
    "addr:postcode": "02093",
    "addr:street": "Joshua Rd",
    "iso:country": "US",
    "sg:address": "15 Joshua Rd",
    "sg:city": "Wrentham",
    "sg:classifiers": [
      {
        "category": "Home \u0026 Garden",
        "subcategory": "Hardware",
        "type": "Retail Goods"
      }
    ],
    "sg:phone": "+1   ",
    "sg:postcode": "02093",
    "sg:province": "MA",
    "wof:name": "Snap-On Tools",
    "wof:placetype": "venue"
  },
  "geometry": {"coordinates":[-71.343516,42.088991],"type":"Point"}
}
