{
  "type": "Feature",
  "properties": {
    "addr:full": "186 Union Ave Framingham MA 01702",
    "addr:housenumber": "186",
    "addr:postcode": "01702",
    "addr:street": "Union Ave",
    "iso:country": "US",
    "sg:address": "186 Union Ave",
    "sg:city": "Framingham",
    "sg:classifiers": [
      {
        "category": "Professional",
        "subcategory": "Business Services",
        "type": "Services"
      }
    ],
    "sg:phone": "+1 508 875 5630",
    "sg:postcode": "01702",
    "sg:province": "MA",
    "sg:tags": [
      "appraiser"
    ],
    "wof:name": "Advanced Appraisal Svc",
    "wof:placetype": "venue"
  },
  "geometry": {"coordinates":[-71.419706,42.282475],"type":"Point"}
}
