{
  "type": "Feature",
  "properties": {
    "addr:full":"1916 Wilbraham Rd Springfield MA 01129",
    "addr:housenumber":"1916",
    "addr:postcode":"01129",
    "addr:street":"Wilbraham Rd",
    "iso:country":"US",
    "sg:address":"1916 Wilbraham Rd",
    "sg:city":"Springfield",
    "sg:classifiers":[
        {
            "category":"Sports & Exercise",
            "subcategory":"Gym",
            "type":"Entertainment"
        }
    ],
    "sg:phone":"+1 413 782 7100",
    "sg:postcode":"01129",
    "sg:province":"MA",
    "sg:tags":[
        "club",
        "health",
        "studio",
        "gymnasium"
    ],
    "wof:name":"Curves For Women",
    "wof:placetype":"venue"
},
  "geometry": {"coordinates":[-72.496441,42.114593],"type":"Point"}
}