{
  "type": "Feature",
  "properties": {
    "addr:full":"274 French King Hwy Gill MA 01354",
    "addr:housenumber":"274",
    "addr:postcode":"01354",
    "addr:street":"French King Hwy",
    "iso:country":"US",
    "sg:address":"274 French King Hwy",
    "sg:city":"Gill",
    "sg:classifiers":[
        {
            "category":"Autos & Motor Vehicles",
            "subcategory":"Motorcycle Sales",
            "type":"Retail Goods"
        }
    ],
    "sg:phone":"+1 413 863 9543",
    "sg:postcode":"01354",
    "sg:province":"MA",
    "sg:tags":[
        "scooter"
    ],
    "wof:name":"A-J Cycle SHOP Bmw",
    "wof:placetype":"venue"
},
  "geometry": {"coordinates":[-72.50235600000001,42.60234],"type":"Point"}
}