{
  "type": "Feature",
  "properties": {
    "iso:country":"US",
    "sg:address":"71 Mossdale Rd",
    "sg:city":"Jamaica Plain",
    "sg:classifiers":[
        {
            "category":"Government",
            "subcategory":"Office",
            "type":"Public Place"
        }
    ],
    "sg:phone":"+1 617 524 9370",
    "sg:postcode":"02130",
    "sg:province":"MA",
    "wof:name":"Kevin Fitzgerald Committee",
    "wof:placetype":"venue"
},
  "geometry": {"coordinates":[-71.12748999999999,42.307888],"type":"Point"}
}