{
  "type": "Feature",
  "properties": {
    "addr:full": "8 N Main St Attleboro MA 02703",
    "addr:housenumber": "8",
    "addr:postcode": "02703",
    "addr:street": "N Main St",
    "iso:country": "US",
    "sg:address": "8 N Main St",
    "sg:city": "Attleboro",
    "sg:classifiers": [
      {
        "category": "Professional",
        "subcategory": "Lawyer \u0026 Legal Services",
        "type": "Services"
      }
    ],
    "sg:phone": "+1 508 222 6400",
    "sg:postcode": "02703",
    "sg:province": "MA",
    "wof:name": "Hatch Brian Atty",
    "wof:placetype": "venue"
  },
  "geometry": {"coordinates":[-71.284401,41.944698],"type":"Point"}
}
