{
  "type": "Feature",
  "properties": {
    "addr:full": "20 Arnold St Ste 1 Westfield MA 01085",
    "addr:housenumber": "20",
    "addr:postcode": "01085",
    "addr:street": "Arnold St Ste 1",
    "iso:country": "US",
    "sg:address": "20 Arnold St Ste 1",
    "sg:city": "Westfield",
    "sg:classifiers": [
      {
        "category": "Deli",
        "type": "Food \u0026 Drink"
      },
      {
        "category": "Restaurant",
        "type": "Food \u0026 Drink"
      }
    ],
    "sg:phone": "+1 413 568 8334",
    "sg:postcode": "01085",
    "sg:province": "MA",
    "sg:tags": [
      "delicatessen"
    ],
    "wof:name": "Westfield Variety \u0026 Deli",
    "wof:placetype": "venue"
  },
  "geometry": {"coordinates":[-72.749165,42.122863],"type":"Point"}
}
