{
  "type": "Feature",
  "properties": {
    "iso:country":"US",
    "sg:address":"20 Arnold St Ste 1",
    "sg:city":"Westfield",
    "sg:classifiers":[
        {
            "category":"Deli",
            "type":"Food & Drink"
        },
        {
            "category":"Restaurant",
            "type":"Food & Drink"
        }
    ],
    "sg:phone":"+1 413 568 8334",
    "sg:postcode":"01085",
    "sg:province":"MA",
    "sg:tags":[
        "delicatessen"
    ],
    "wof:name":"Westfield Variety & Deli",
    "wof:placetype":"venue"
},
  "geometry": {"coordinates":[-72.749165,42.122863],"type":"Point"}
}