{
  "type": "Feature",
  "properties": {
    "iso:country":"US",
    "sg:address":"30 Resnik Rd",
    "sg:city":"Plymouth",
    "sg:classifiers":[
        {
            "category":"Health Services",
            "subcategory":"Dentist",
            "type":"Services"
        }
    ],
    "sg:phone":"+1 508 746 8700",
    "sg:postcode":"02360",
    "sg:province":"MA",
    "wof:name":"Gill Jasjit S DMD",
    "wof:placetype":"venue"
},
  "geometry": {"coordinates":[-70.708,41.950802],"type":"Point"}
}