{
  "type": "Feature",
  "properties": {
    "addr:full":"18 Allen Pl Scituate MA 02066",
    "addr:housenumber":"18",
    "addr:postcode":"02066",
    "addr:street":"Allen Pl",
    "iso:country":"US",
    "sg:address":"18 Allen Pl",
    "sg:city":"Scituate",
    "sg:classifiers":[
        {
            "category":"Travel",
            "subcategory":"Hotels & Motels",
            "type":"Entertainment"
        }
    ],
    "sg:phone":"+1 781 545 8221",
    "sg:postcode":"02066",
    "sg:province":"MA",
    "sg:tags":[
        "breakfast",
        "accommodation",
        "bed"
    ],
    "sg:website":"www.allenhousebnb.com",
    "wof:name":"Allen House",
    "wof:placetype":"venue"
},
  "geometry": {"coordinates":[-70.72985799999999,42.196038],"type":"Point"}
}