{
  "type": "Feature",
  "properties": {
    "iso:country":"US",
    "sg:address":"20 Joanne Dr",
    "sg:city":"Ashland",
    "sg:classifiers":[
        {
            "category":"Building & Trades",
            "subcategory":"Cleaning & Sanitation",
            "type":"Services"
        }
    ],
    "sg:phone":"+1 508 875 3874",
    "sg:postcode":"01721",
    "sg:province":"MA",
    "sg:tags":[
        "fireplace",
        "chimney"
    ],
    "wof:name":"Chim Chimney Sweep",
    "wof:placetype":"venue"
},
  "geometry": {"coordinates":[-71.455535,42.246679],"type":"Point"}
}