{
  "type": "Feature",
  "properties": {
    "addr:full": "4 Middleton Rd Boxford MA 01921",
    "addr:housenumber": "4",
    "addr:postcode": "01921",
    "addr:street": "Middleton Rd",
    "iso:country": "US",
    "sg:address": "4 Middleton Rd",
    "sg:city": "Boxford",
    "sg:classifiers": [
      {
        "category": "Government",
        "subcategory": "Office",
        "type": "Public Place"
      }
    ],
    "sg:phone": "+1 978 887 3591",
    "sg:postcode": "01921",
    "sg:province": "MA",
    "sg:tags": [
      "city",
      "resource",
      "human"
    ],
    "wof:name": "Council On Aging",
    "wof:placetype": "venue"
  },
  "geometry": {"coordinates":[-70.998031,42.663371],"type":"Point"}
}
