{
  "type": "Feature",
  "properties": {
    "iso:country":"US",
    "sg:address":"131 Elm St",
    "sg:city":"Millbury",
    "sg:classifiers":[
        {
            "category":"Real Estate",
            "subcategory":"Real Estate Agent",
            "type":"Services"
        }
    ],
    "sg:phone":"+1 508 865 9900",
    "sg:postcode":"01527",
    "sg:province":"MA",
    "wof:name":"Gateway Realty Assoc Inc",
    "wof:placetype":"venue"
},
  "geometry": {"coordinates":[-71.764618,42.188888],"type":"Point"}
}