{
  "type": "Feature",
  "properties": {
    "iso:country":"US",
    "sg:address":"3 N Brookfield Rd",
    "sg:city":"North Brookfield",
    "sg:classifiers":[
        {
            "category":"Building & Trades",
            "subcategory":"Plumbing",
            "type":"Services"
        }
    ],
    "sg:phone":"+1 508 867 5466",
    "sg:postcode":"01535",
    "sg:province":"MA",
    "sg:tags":[
        "plumbing",
        "contractor"
    ],
    "wof:name":"Nye Plumbing Co",
    "wof:placetype":"venue"
},
  "geometry": {"coordinates":[-72.09018399999999,42.253796],"type":"Point"}
}