{
  "type": "Feature",
  "properties": {
    "addr:full": "45 Felton St Waltham MA 02453",
    "addr:housenumber": "45",
    "addr:postcode": "02453",
    "addr:street": "Felton St",
    "iso:country": "US",
    "sg:address": "45 Felton St",
    "sg:city": "Waltham",
    "sg:classifiers": [
      {
        "category": "Professional",
        "type": "Services"
      }
    ],
    "sg:phone": "+1 781 891 3348",
    "sg:postcode": "02453",
    "sg:province": "MA",
    "sg:tags": [
      "establishment"
    ],
    "wof:name": "Preferred Customers",
    "wof:placetype": "venue"
  },
  "geometry": {"coordinates":[-71.238271,42.374321],"type":"Point"}
}
