{
  "type": "Feature",
  "properties": {
    "iso:country":"US",
    "sg:address":"13 Margate Ln",
    "sg:city":"Mashpee",
    "sg:classifiers":[
        {
            "category":"Home & Garden",
            "subcategory":"Furniture",
            "type":"Retail Goods"
        }
    ],
    "sg:phone":"+1 508 539 8995",
    "sg:postcode":"02660",
    "sg:province":"MA",
    "sg:website":"www.eldredwheeler.com",
    "wof:name":"Eldred Wheeler",
    "wof:placetype":"venue"
},
  "geometry": {"coordinates":[-70.170299,41.709596],"type":"Point"}
}