{
  "type": "Feature",
  "properties": {
    "addr:full": "210 Jones Rd Falmouth MA 02540",
    "addr:housenumber": "210",
    "addr:postcode": "02540",
    "addr:street": "Jones Rd",
    "iso:country": "US",
    "ovtr:label": "Falmouth Dental Associates, 210 Jones Rd Falmouth MA US",
    "ovtr:similarity": 2.6292619705200195,
    "sg:address": "210 Jones Rd",
    "sg:city": "Falmouth",
    "sg:classifiers": [
      {
        "category": "Health Services",
        "subcategory": "Dentist",
        "type": "Services"
      }
    ],
    "sg:phone": "+1 508 540 0303",
    "sg:postcode": "02540",
    "sg:province": "MA",
    "sg:tags": [
      "dentists-cosmetic",
      "denture",
      "dental",
      "dentists-periodontists",
      "clinic",
      "dentistry",
      "dentists-prosthodontists"
    ],
    "sg:website": "http://www.falmouthdental.com",
    "wof:name": "Falmouth Dental Associates",
    "wof:placetype": "venue"
  },
  "geometry": {"coordinates":[-70.611588,41.561111],"type":"Point"}
}
