{
  "type": "Feature",
  "properties": {
    "iso:country":"US",
    "sg:address":"1304 Massachusetts Ave",
    "sg:city":"Cambridge",
    "sg:classifiers":[
        {
            "category":"Personal",
            "subcategory":"Shoe Repair & Shine",
            "type":"Services"
        }
    ],
    "sg:postcode":"02138",
    "sg:province":"MA",
    "wof:name":"Felix Shoe Repair",
    "wof:placetype":"venue"
},
  "geometry": {"coordinates":[-71.11725800000001,42.372922],"type":"Point"}
}