{
  "type": "Feature",
  "properties": {
    "addr:full": "1304 Massachusetts Ave Cambridge MA 02138",
    "addr:housenumber": "1304",
    "addr:postcode": "02138",
    "addr:street": "Massachusetts Ave",
    "iso:country": "US",
    "ovtr:label": "Felix Shoe Repair, 1304 Massachusetts Ave Cambridge MA US",
    "ovtr:similarity": 1.9711250066757202,
    "sg:address": "1304 Massachusetts Ave",
    "sg:city": "Cambridge",
    "sg:classifiers": [
      {
        "category": "Personal",
        "subcategory": "Shoe Repair \u0026 Shine",
        "type": "Services"
      }
    ],
    "sg:postcode": "02138",
    "sg:province": "MA",
    "wof:name": "Felix Shoe Repair",
    "wof:placetype": "venue"
  },
  "geometry": {"coordinates":[-71.117258,42.372922],"type":"Point"}
}
