{
  "type": "Feature",
  "properties": {
    "addr:full":"41 Locksley Rd Lynnfield MA 01940",
    "addr:housenumber":"41",
    "addr:postcode":"01940",
    "addr:street":"Locksley Rd",
    "iso:country":"US",
    "sg:address":"41 Locksley Rd",
    "sg:city":"Lynnfield",
    "sg:classifiers":[
        {
            "category":"Home & Garden",
            "subcategory":"Home Furnishings",
            "type":"Retail Goods"
        }
    ],
    "sg:phone":"+1   ",
    "sg:postcode":"01940",
    "sg:province":"MA",
    "wof:name":"Top It Off",
    "wof:placetype":"venue"
},
  "geometry": {"coordinates":[-71.010093,42.518622],"type":"Point"}
}