{
  "type": "Feature",
  "properties": {
    "iso:country":"US",
    "sg:address":"20 Brewster Rd",
    "sg:city":"Mashpee",
    "sg:classifiers":[
        {
            "category":"Landmark",
            "subcategory":"Tourist Information",
            "type":"Public Place"
        }
    ],
    "sg:phone":"+1 508 328 7064",
    "sg:postcode":"02649",
    "sg:province":"MA",
    "sg:tags":[
        "promoter",
        "tours-operators"
    ],
    "wof:name":"Great Marsh Kyak Tours Inc",
    "wof:placetype":"venue"
},
  "geometry": {"coordinates":[-70.476913,41.62196],"type":"Point"}
}