{
  "type": "Feature",
  "properties": {
    "iso:country":"US",
    "sg:address":"28 Pine St",
    "sg:city":"Stoneham",
    "sg:classifiers":[
        {
            "category":"Retail",
            "subcategory":"Auto Repair",
            "type":"Services"
        }
    ],
    "sg:phone":"+1 781 438 3838",
    "sg:postcode":"02180",
    "sg:province":"MA",
    "sg:tags":[
        "oil",
        "change"
    ],
    "wof:name":"Onsite Automotive Services",
    "wof:placetype":"venue"
},
  "geometry": {"coordinates":[-71.096959,42.479128],"type":"Point"}
}