{
  "type": "Feature",
  "properties": {
    "iso:country":"US",
    "sg:address":"103 Main St",
    "sg:city":"Lakeville",
    "sg:classifiers":[
        {
            "category":"Wholesale",
            "subcategory":"Construction Materials",
            "type":"Manufacturing & Wholesale Goods"
        }
    ],
    "sg:phone":"+1 508 947 6013",
    "sg:postcode":"02347",
    "sg:province":"MA",
    "sg:tags":[
        "concrete",
        "form"
    ],
    "wof:name":"J & L Concrete Forms Inc",
    "wof:placetype":"venue"
},
  "geometry": {"coordinates":[-70.93478399999999,41.865824],"type":"Point"}
}