{
  "type": "Feature",
  "properties": {
    "addr:full": "103 Main St Lakeville MA 02347",
    "addr:housenumber": "103",
    "addr:postcode": "02347",
    "addr:street": "Main St",
    "iso:country": "US",
    "sg:address": "103 Main St",
    "sg:city": "Lakeville",
    "sg:classifiers": [
      {
        "category": "Wholesale",
        "subcategory": "Construction Materials",
        "type": "Manufacturing \u0026 Wholesale Goods"
      }
    ],
    "sg:phone": "+1 508 947 6013",
    "sg:postcode": "02347",
    "sg:province": "MA",
    "sg:tags": [
      "concrete",
      "form"
    ],
    "wof:name": "J \u0026 L Concrete Forms Inc",
    "wof:placetype": "venue"
  },
  "geometry": {"coordinates":[-70.934784,41.865824],"type":"Point"}
}
