{
  "type": "Feature",
  "properties": {
    "addr:full": "151 State Rd Westport MA 02790",
    "addr:housenumber": "151",
    "addr:postcode": "02790",
    "addr:street": "State Rd",
    "iso:country": "US",
    "sg:address": "151 State Rd",
    "sg:city": "Westport",
    "sg:classifiers": [
      {
        "category": "Building \u0026 Trades",
        "subcategory": "Construction",
        "type": "Services"
      }
    ],
    "sg:phone": "+1 508 674 4297",
    "sg:postcode": "02790",
    "sg:province": "MA",
    "sg:tags": [
      "painter"
    ],
    "wof:name": "JTS Painting Svc",
    "wof:placetype": "venue"
  },
  "geometry": {"coordinates":[-71.10969,41.675915],"type":"Point"}
}
