{
  "type": "Feature",
  "properties": {
    "addr:full":"2 Thatcher Rd Middleboro MA 02360",
    "addr:housenumber":"2",
    "addr:postcode":"02360",
    "addr:street":"Thatcher Rd",
    "iso:country":"US",
    "sg:address":"2 Thatcher Rd",
    "sg:city":"Middleboro",
    "sg:classifiers":[
        {
            "category":"Social Services",
            "subcategory":"Job Training",
            "type":"Services"
        }
    ],
    "sg:phone":"+1 508 947 6000",
    "sg:postcode":"02360",
    "sg:province":"MA",
    "sg:tags":[
        "career",
        "counseling",
        "vocational"
    ],
    "wof:name":"Triangle",
    "wof:placetype":"venue"
},
  "geometry": {"coordinates":[-70.607827,41.870956],"type":"Point"}
}