{
  "type": "Feature",
  "properties": {
    "iso:country":"US",
    "sg:address":"15 Dennis Ave",
    "sg:city":"Brockton",
    "sg:classifiers":[
        {
            "category":"Professional",
            "subcategory":"Business Services",
            "type":"Services"
        }
    ],
    "sg:phone":"+1   ",
    "sg:postcode":"02301",
    "sg:province":"MA",
    "wof:name":"H Cardosa",
    "wof:placetype":"venue"
},
  "geometry": {"coordinates":[-71.04806600000001,42.072461],"type":"Point"}
}