{
  "type": "Feature",
  "properties": {
    "iso:country":"US",
    "sg:address":"28 Exeter St",
    "sg:city":"Boston",
    "sg:classifiers":[
        {
            "category":"Professional",
            "subcategory":"Management & Consulting",
            "type":"Services"
        }
    ],
    "sg:phone":"+1 617 426 9099",
    "sg:postcode":"02116",
    "sg:province":"MA",
    "sg:tags":[
        "consultant"
    ],
    "wof:name":"H A Consulting",
    "wof:placetype":"venue"
},
  "geometry": {"coordinates":[-71.07968099999999,42.349914],"type":"Point"}
}