{
  "type": "Feature",
  "properties": {
    "addr:full":"186 Walnut St Watertown MA 02472",
    "addr:housenumber":"186",
    "addr:postcode":"02472",
    "addr:street":"Walnut St",
    "iso:country":"US",
    "sg:address":"186 Walnut St",
    "sg:city":"Watertown",
    "sg:classifiers":[
        {
            "category":"Wholesale",
            "subcategory":"Construction Materials",
            "type":"Manufacturing & Wholesale Goods"
        }
    ],
    "sg:phone":"+1 617 924 6652",
    "sg:postcode":"02472",
    "sg:province":"MA",
    "sg:tags":[
        "fence"
    ],
    "wof:name":"Patriot Fence Crafters",
    "wof:placetype":"venue"
},
  "geometry": {"coordinates":[-71.16804,42.36499],"type":"Point"}
}