{
  "type": "Feature",
  "properties": {
    "iso:country":"US",
    "sg:address":"446 Moody St",
    "sg:city":"Waltham",
    "sg:classifiers":[
        {
            "category":"Health Services",
            "subcategory":"Optometrist",
            "type":"Services"
        }
    ],
    "sg:phone":"+1 781 899 3200",
    "sg:postcode":"02453",
    "sg:province":"MA",
    "wof:name":"Bay State Eye Assoc",
    "wof:placetype":"venue"
},
  "geometry": {"coordinates":[-71.237425,42.367763],"type":"Point"}
}