{
  "type": "Feature",
  "properties": {
    "addr:full":"117 Business St Hyde Park MA 02136",
    "addr:housenumber":"117",
    "addr:postcode":"02136",
    "addr:street":"Business St",
    "iso:country":"US",
    "sg:address":"117 Business St",
    "sg:city":"Hyde Park",
    "sg:classifiers":[
        {
            "category":"Retail",
            "subcategory":"Auto Repair",
            "type":"Services"
        }
    ],
    "sg:phone":"+1 617 361 2030",
    "sg:postcode":"02136",
    "sg:province":"MA",
    "sg:tags":[
        "transmission"
    ],
    "wof:name":"Savon Transmission Co",
    "wof:placetype":"venue"
},
  "geometry": {"coordinates":[-71.128604,42.252043],"type":"Point"}
}