{
  "type": "Feature",
  "properties": {
    "iso:country":"US",
    "sg:address":"92 Main St",
    "sg:city":"Hopkinton",
    "sg:classifiers":[
        {
            "category":"Personal",
            "subcategory":"Beauty Salon",
            "type":"Services"
        }
    ],
    "sg:phone":"+1 508 497 5073",
    "sg:postcode":"01748",
    "sg:province":"MA",
    "sg:tags":[
        "hair",
        "stylist"
    ],
    "wof:name":"Hair That Works",
    "wof:placetype":"venue"
},
  "geometry": {"coordinates":[-71.525879,42.22699],"type":"Point"}
}