{
  "type": "Feature",
  "properties": {
    "iso:country":"US",
    "sg:address":"74 Hawksnest Rd",
    "sg:city":"Harwich",
    "sg:classifiers":[
        {
            "category":"Insurance",
            "subcategory":"Insurance Agent",
            "type":"Services"
        }
    ],
    "sg:phone":"+1 508 430 7466",
    "sg:postcode":"02645",
    "sg:province":"MA",
    "wof:name":"Dubuque Insurance",
    "wof:placetype":"venue"
},
  "geometry": {"coordinates":[-70.03695399999999,41.70594],"type":"Point"}
}