{
  "type": "Feature",
  "properties": {
    "addr:full": "101 Federal St Boston MA 02110",
    "addr:housenumber": "101",
    "addr:postcode": "02110",
    "addr:street": "Federal St",
    "iso:country": "US",
    "sg:address": "101 Federal St",
    "sg:city": "Boston",
    "sg:classifiers": [
      {
        "category": "Professional",
        "subcategory": "Lawyer \u0026 Legal Services",
        "type": "Services"
      }
    ],
    "sg:phone": "+1 617 428 0900",
    "sg:postcode": "02110",
    "sg:province": "MA",
    "sg:tags": [
      "attorney"
    ],
    "sg:website": "www.clarkelbing.com",
    "wof:name": "Clark \u0026 Elbing",
    "wof:placetype": "venue"
  },
  "geometry": {"coordinates":[-71.056297,42.355099],"type":"Point"}
}
