{
  "type": "Feature",
  "properties": {
    "iso:country":"US",
    "sg:address":"218 Pearl St",
    "sg:city":"Malden",
    "sg:classifiers":[
        {
            "category":"Shopping",
            "subcategory":"Hobbies, Toys, & Games",
            "type":"Retail Goods"
        }
    ],
    "sg:phone":"+1 781 321 8796",
    "sg:postcode":"02148",
    "sg:province":"MA",
    "sg:tags":[
        "sport",
        "card",
        "memorabilia"
    ],
    "wof:name":"Krazy Jimz",
    "wof:placetype":"venue"
},
  "geometry": {"coordinates":[-71.077243,42.421162],"type":"Point"}
}