{
  "type": "Feature",
  "properties": {
    "addr:full":"42 Bancroft Park Hopedale MA 01747",
    "addr:housenumber":"42",
    "addr:postcode":"01747",
    "addr:street":"Bancroft Park",
    "iso:country":"US",
    "sg:address":"42 Bancroft Park",
    "sg:city":"Hopedale",
    "sg:classifiers":[
        {
            "category":"Professional",
            "subcategory":"Business Services",
            "type":"Services"
        }
    ],
    "sg:phone":"+1   ",
    "sg:postcode":"01747",
    "sg:province":"MA",
    "wof:name":"New England Fine Art Inc",
    "wof:placetype":"venue"
},
  "geometry": {"coordinates":[-71.547042,42.129872],"type":"Point"}
}