{
  "type": "Feature",
  "properties": {
    "iso:country":"US",
    "sg:address":"2 Main St",
    "sg:city":"Southborough",
    "sg:classifiers":[
        {
            "category":"Restaurant",
            "type":"Food & Drink"
        }
    ],
    "sg:phone":"+1 508 485 8730",
    "sg:postcode":"01772",
    "sg:province":"MA",
    "wof:name":"Mc Carthy's Restaurant",
    "wof:placetype":"venue"
},
  "geometry": {"coordinates":[-71.52396299999999,42.305991],"type":"Point"}
}