{
  "type": "Feature",
  "properties": {
    "iso:country":"US",
    "sg:address":"19 Church St",
    "sg:city":"Leominster",
    "sg:classifiers":[
        {
            "category":"Government",
            "subcategory":"Fire Station",
            "type":"Public Place"
        }
    ],
    "sg:phone":"+1 978 534 7541",
    "sg:postcode":"01453",
    "sg:province":"MA",
    "sg:tags":[
        "department"
    ],
    "wof:name":"Leominster Fire Dept",
    "wof:placetype":"venue"
},
  "geometry": {"coordinates":[-71.760845,42.527604],"type":"Point"}
}