{
  "type": "Feature",
  "properties": {
    "addr:full": "496 Bridge St Springfield MA 01103",
    "addr:housenumber": "496",
    "addr:postcode": "01103",
    "addr:street": "Bridge St",
    "iso:country": "US",
    "sg:address": "496 Bridge St",
    "sg:city": "Springfield",
    "sg:classifiers": [
      {
        "category": "Real Estate",
        "subcategory": "Real Estate Agent",
        "type": "Services"
      }
    ],
    "sg:phone": "+1 413 747 8057",
    "sg:postcode": "01103",
    "sg:province": "MA",
    "sg:tags": [
      "management"
    ],
    "wof:name": "Baystate Group",
    "wof:placetype": "venue"
  },
  "geometry": {"coordinates":[-72.589005,42.105613],"type":"Point"}
}
