{
  "type": "Feature",
  "properties": {
    "addr:full":"496 Massachusetts Ave Cambridge MA 02139",
    "addr:housenumber":"496",
    "addr:postcode":"02139",
    "addr:street":"Massachusetts Ave",
    "iso:country":"US",
    "sg:address":"496 Massachusetts Ave",
    "sg:city":"Cambridge",
    "sg:classifiers":[
        {
            "category":"Retail",
            "subcategory":"Repair Shop",
            "type":"Services"
        }
    ],
    "sg:phone":"+1 617 453 5151",
    "sg:postcode":"02139",
    "sg:province":"MA",
    "sg:tags":[
        "lock",
        "locksmith"
    ],
    "wof:name":"24 All Day Emergency Locksmith",
    "wof:placetype":"venue"
},
  "geometry": {"coordinates":[-71.101955,42.364267],"type":"Point"}
}