{
  "type": "Feature",
  "properties": {
    "addr:full": "99 Scotland Rd Newbury MA 01951",
    "addr:housenumber": "99",
    "addr:postcode": "01951",
    "addr:street": "Scotland Rd",
    "iso:country": "US",
    "sg:address": "99 Scotland Rd",
    "sg:city": "Newbury",
    "sg:classifiers": [
      {
        "category": "Utilities",
        "subcategory": "Refuse",
        "type": "Services"
      }
    ],
    "sg:phone": "+1 978 465 0053",
    "sg:postcode": "01951",
    "sg:province": "MA",
    "sg:tags": [
      "garbage",
      "collection"
    ],
    "wof:name": "BRC Recycling \u0026 Disposal",
    "wof:placetype": "venue"
  },
  "geometry": {"coordinates":[-70.908085,42.788578],"type":"Point"}
}
