{
  "type": "Feature",
  "properties": {
    "iso:country":"US",
    "sg:address":"1 Pearl St",
    "sg:city":"Brockton",
    "sg:classifiers":[
        {
            "category":"Health Services",
            "subcategory":"Doctor",
            "type":"Services"
        }
    ],
    "sg:phone":"+1 508 894 5100",
    "sg:postcode":"02301",
    "sg:province":"MA",
    "sg:tags":[
        "dermatologist"
    ],
    "wof:name":"Speigel Joan H Dermatologist",
    "wof:placetype":"venue"
},
  "geometry": {"coordinates":[-71.064555,42.08924],"type":"Point"}
}