{
  "type": "Feature",
  "properties": {
    "iso:country":"US",
    "sg:address":"2 Ipswich River Rd",
    "sg:city":"Danvers",
    "sg:classifiers":[
        {
            "category":"Professional",
            "subcategory":"Lawyer & Legal Services",
            "type":"Services"
        }
    ],
    "sg:phone":"+1 978 777 2800",
    "sg:postcode":"01923",
    "sg:province":"MA",
    "sg:tags":[
        "attorney"
    ],
    "wof:name":"Tanya P Millett",
    "wof:placetype":"venue"
},
  "geometry": {"coordinates":[-70.991551,42.575748],"type":"Point"}
}