{
  "type": "Feature",
  "properties": {
    "iso:country":"US",
    "sg:address":"17 Keeler St",
    "sg:city":"Pittsfield",
    "sg:classifiers":[
        {
            "category":"Professional",
            "subcategory":"Business Services",
            "type":"Services"
        }
    ],
    "sg:phone":"+1 413 499 4467",
    "sg:postcode":"01201",
    "sg:province":"MA",
    "sg:tags":[
        "painter",
        "sign"
    ],
    "wof:name":"Showcase Sign",
    "wof:placetype":"venue"
},
  "geometry": {"coordinates":[-73.24773999999999,42.481457],"type":"Point"}
}