{
  "type": "Feature",
  "properties": {
    "addr:full":"57 Wharf St Salem MA 01970",
    "addr:housenumber":"57",
    "addr:postcode":"01970",
    "addr:street":"Wharf St",
    "iso:country":"US",
    "sg:address":"57 Wharf St",
    "sg:city":"Salem",
    "sg:classifiers":[
        {
            "category":"Banks & Credit Unions",
            "subcategory":"Investment Brokerage",
            "type":"Services"
        }
    ],
    "sg:phone":"+1 978 741 4933",
    "sg:postcode":"01970",
    "sg:province":"MA",
    "sg:tags":[
        "advisory",
        "financial"
    ],
    "wof:name":"W B Smith & Co",
    "wof:placetype":"venue"
},
  "geometry": {"coordinates":[-70.88785799999999,42.519867],"type":"Point"}
}