{
  "type": "Feature",
  "properties": {
    "addr:full":"1350 Main St Ste 1508 Springfield MA 01103",
    "addr:housenumber":"1350",
    "addr:postcode":"01103",
    "addr:street":"Main St Ste 1508",
    "iso:country":"US",
    "sg:address":"1350 Main St Ste 1508",
    "sg:city":"Springfield",
    "sg:classifiers":[
        {
            "category":"Professional",
            "subcategory":"Management & Consulting",
            "type":"Services"
        }
    ],
    "sg:phone":"+1 413 686 9199",
    "sg:postcode":"01103",
    "sg:province":"MA",
    "sg:tags":[
        "consultant"
    ],
    "wof:name":"The Markens Group",
    "wof:placetype":"venue"
},
  "geometry": {"coordinates":[-72.58913099999999,42.102035],"type":"Point"}
}