{
  "type": "Feature",
  "properties": {
    "addr:full":"11 Plain St Norton MA 02766",
    "addr:housenumber":"11",
    "addr:postcode":"02766",
    "addr:street":"Plain St",
    "iso:country":"US",
    "sg:address":"11 Plain St",
    "sg:city":"Norton",
    "sg:classifiers":[
        {
            "category":"Building & Trades",
            "subcategory":"Plumbing",
            "type":"Services"
        }
    ],
    "sg:phone":"+1 508 285 5700",
    "sg:postcode":"02766",
    "sg:province":"MA",
    "wof:name":"Geoghegan Owen Plumbing & Heating",
    "wof:placetype":"venue"
},
  "geometry": {"coordinates":[-71.17420199999999,41.965599],"type":"Point"}
}