{
  "type": "Feature",
  "properties": {
    "iso:country":"US",
    "sg:address":"28 School St",
    "sg:city":"Manchester",
    "sg:classifiers":[
        {
            "category":"Professional",
            "subcategory":"Computer Services",
            "type":"Services"
        }
    ],
    "sg:phone":"+1 978 526 9953",
    "sg:postcode":"01944",
    "sg:province":"MA",
    "sg:tags":[
        "website",
        "design"
    ],
    "sg:website":"www.swanzey.com",
    "wof:name":"Swanzey Internet Group",
    "wof:placetype":"venue"
},
  "geometry": {"coordinates":[-70.770585,42.577248],"type":"Point"}
}