{
  "type": "Feature",
  "properties": {
    "iso:country":"US",
    "sg:address":"739 State Rd",
    "sg:city":"Plymouth",
    "sg:classifiers":[
        {
            "category":"Restaurant",
            "type":"Food & Drink"
        }
    ],
    "sg:phone":"+1 508 224 2620",
    "sg:postcode":"02360",
    "sg:province":"MA",
    "wof:name":"Checkers Pizza & Subs",
    "wof:placetype":"venue"
},
  "geometry": {"coordinates":[-70.554147,41.914601],"type":"Point"}
}