{
  "type": "Feature",
  "properties": {
    "addr:full": "739 State Rd Plymouth MA 02360",
    "addr:housenumber": "739",
    "addr:postcode": "02360",
    "addr:street": "State Rd",
    "iso:country": "US",
    "sg:address": "739 State Rd",
    "sg:city": "Plymouth",
    "sg:classifiers": [
      {
        "category": "Restaurant",
        "type": "Food \u0026 Drink"
      }
    ],
    "sg:phone": "+1 508 224 2620",
    "sg:postcode": "02360",
    "sg:province": "MA",
    "wof:name": "Checkers Pizza \u0026 Subs",
    "wof:placetype": "venue"
  },
  "geometry": {"coordinates":[-70.554147,41.914601],"type":"Point"}
}
