{
  "type": "Feature",
  "properties": {
    "iso:country":"US",
    "sg:address":"333 Washington St Ste 204",
    "sg:city":"Boston",
    "sg:classifiers":[
        {
            "category":"Manufacturing",
            "subcategory":"Metals",
            "type":"Manufacturing & Wholesale Goods"
        },
        {
            "category":"Retail",
            "subcategory":"Repair Shop",
            "type":"Services"
        },
        {
            "category":"Manufacturing",
            "subcategory":"Jewelry",
            "type":"Manufacturing & Wholesale Goods"
        },
        {
            "category":"Professional",
            "subcategory":"Business Services",
            "type":"Services"
        },
        {
            "category":"Shopping",
            "subcategory":"Jewelry",
            "type":"Retail Goods"
        }
    ],
    "sg:phone":"+1 617 542 3836",
    "sg:postcode":"02108",
    "sg:province":"MA",
    "sg:tags":[
        "repairing",
        "stone",
        "industrial",
        "jewelers-wholesale",
        "clock",
        "metals-precious",
        "commercial",
        "appraisers-business",
        "precious",
        "semi-precious",
        "appraiser",
        "manufacturer"
    ],
    "wof:name":"Paul S Calantropo & Co",
    "wof:placetype":"venue"
},
  "geometry": {"coordinates":[-71.059012,42.356777],"type":"Point"}
}