{
  "type": "Feature",
  "properties": {
    "addr:full": "39 Hurd Ave Saugus MA 01906",
    "addr:housenumber": "39",
    "addr:postcode": "01906",
    "addr:street": "Hurd Ave",
    "iso:country": "US",
    "ovtr:label": "Veterans Memorial Elementary School, 39 Hurd Ave Saugus MA US",
    "ovtr:similarity": 3.4128971099853516,
    "sg:address": "39 Hurd Ave",
    "sg:city": "Saugus",
    "sg:classifiers": [
      {
        "category": "Education",
        "subcategory": "School",
        "type": "Public Place"
      }
    ],
    "sg:phone": "+1 781 231 8568",
    "sg:postcode": "01906",
    "sg:province": "MA",
    "wof:name": "Veterans Memorial Elementary",
    "wof:placetype": "venue"
  },
  "geometry": {"coordinates":[-71.00564,42.454178],"type":"Point"}
}
