{
  "type": "Feature",
  "properties": {
    "iso:country":"US",
    "sg:address":"39 Hurd Ave",
    "sg:city":"Saugus",
    "sg:classifiers":[
        {
            "category":"Education",
            "subcategory":"School",
            "type":"Public Place"
        }
    ],
    "sg:phone":"+1 781 231 8568",
    "sg:postcode":"01906",
    "sg:province":"MA",
    "wof:name":"Veterans Memorial Elementary",
    "wof:placetype":"venue"
},
  "geometry": {"coordinates":[-71.00564,42.454178],"type":"Point"}
}