{
  "type": "Feature",
  "properties": {
    "addr:full": "56 Chestnut St Cambridge MA 02139",
    "addr:housenumber": "56",
    "addr:postcode": "02139",
    "addr:street": "Chestnut St",
    "iso:country": "US",
    "sg:address": "56 Chestnut St",
    "sg:city": "Cambridge",
    "sg:classifiers": [
      {
        "category": "Communications",
        "subcategory": "Film \u0026 Video Production",
        "type": "Services"
      }
    ],
    "sg:phone": "+1 617 492 5200",
    "sg:postcode": "02139",
    "sg:province": "MA",
    "sg:tags": [
      "tape"
    ],
    "sg:website": "www.iamedia.com",
    "wof:name": "Intersection Associates",
    "wof:placetype": "venue"
  },
  "geometry": {"coordinates":[-71.108399,42.356218],"type":"Point"}
}
