{
  "type": "Feature",
  "properties": {
    "addr:full":"11 Meridian St Boston MA 02128",
    "addr:housenumber":"11",
    "addr:postcode":"02128",
    "addr:street":"Meridian St",
    "iso:country":"US",
    "sg:address":"11 Meridian St",
    "sg:city":"Boston",
    "sg:classifiers":[
        {
            "category":"Food & Beverages",
            "subcategory":"Specialty",
            "type":"Retail Goods"
        },
        {
            "category":"Food & Beverages",
            "subcategory":"Groceries & Convenience Stores",
            "type":"Retail Goods"
        }
    ],
    "sg:phone":"+1 617 569 6320",
    "sg:postcode":"02128",
    "sg:province":"MA",
    "sg:tags":[
        "grocers-specialty"
    ],
    "wof:name":"Los Paisanos Market Llc",
    "wof:placetype":"venue"
},
  "geometry": {"coordinates":[-71.038768,42.370441],"type":"Point"}
}