{
  "type": "Feature",
  "properties": {
    "iso:country":"US",
    "sg:address":"1 Westledge Rd",
    "sg:city":"Marblehead",
    "sg:classifiers":[
        {
            "category":"Professional",
            "subcategory":"Business Services",
            "type":"Services"
        }
    ],
    "sg:phone":"+1 781 639 7900",
    "sg:postcode":"01945",
    "sg:province":"MA",
    "sg:tags":[
        "interior",
        "consultant",
        "design",
        "decorator"
    ],
    "wof:name":"East Coast Design",
    "wof:placetype":"venue"
},
  "geometry": {"coordinates":[-70.871928,42.50325],"type":"Point"}
}