{
  "type": "Feature",
  "properties": {
    "iso:country":"US",
    "sg:address":"390 Main St Ste 206",
    "sg:city":"Woburn",
    "sg:classifiers":[
        {
            "category":"Professional",
            "subcategory":"Lawyer & Legal Services",
            "type":"Services"
        }
    ],
    "sg:phone":"+1 781 933 9800",
    "sg:postcode":"01801",
    "sg:province":"MA",
    "wof:name":"Diana Corinne Atty",
    "wof:placetype":"venue"
},
  "geometry": {"coordinates":[-71.15070299999999,42.482101],"type":"Point"}
}