{
  "type": "Feature",
  "properties": {
    "addr:full":"70 Court St Plymouth MA 02360",
    "addr:housenumber":"70",
    "addr:postcode":"02360",
    "addr:street":"Court St",
    "iso:country":"US",
    "sg:address":"70 Court St",
    "sg:city":"Plymouth",
    "sg:classifiers":[
        {
            "category":"Health Services",
            "subcategory":"Doctor",
            "type":"Services"
        },
        {
            "category":"Health Services",
            "subcategory":"Dentist",
            "type":"Services"
        }
    ],
    "sg:phone":"+1 508 746 1666",
    "sg:postcode":"02360",
    "sg:province":"MA",
    "sg:tags":[
        "dentists-oral",
        "physician",
        "maxillofacial",
        "surgeons",
        "surgery",
        "oral"
    ],
    "wof:name":"Boynton Matthew T DMD",
    "wof:placetype":"venue"
},
  "geometry": {"coordinates":[-70.66838300000001,41.9588],"type":"Point"}
}