{
  "type": "Feature",
  "properties": {
    "iso:country":"US",
    "sg:address":"13 Pleasant St",
    "sg:city":"Taunton",
    "sg:classifiers":[
        {
            "category":"Retail",
            "subcategory":"Auto Rental",
            "type":"Services"
        },
        {
            "category":"Building & Trades",
            "subcategory":"Equipment Rental",
            "type":"Services"
        },
        {
            "category":"Retail",
            "subcategory":"Storage",
            "type":"Services"
        }
    ],
    "sg:phone":"+1 508 880 0001",
    "sg:postcode":"02780",
    "sg:province":"MA",
    "sg:tags":[
        "renting",
        "moving-self",
        "leasing",
        "moving",
        "truck",
        "trailer"
    ],
    "sg:website":"http://www.pensketruckrental.com/",
    "wof:name":"Penske Truck Rental",
    "wof:placetype":"venue"
},
  "geometry": {"coordinates":[-71.093822,41.903866],"type":"Point"}
}