{
  "type": "Feature",
  "properties": {
    "iso:country":"US",
    "sg:address":"1 Trajanowski Ave",
    "sg:city":"Northbridge",
    "sg:classifiers":[
        {
            "category":"Building & Trades",
            "subcategory":"Landscaping Services",
            "type":"Services"
        }
    ],
    "sg:phone":"+1 508 266 0135",
    "sg:postcode":"01534",
    "sg:province":"MA",
    "sg:tags":[
        "tree"
    ],
    "wof:name":"Union Tree Inc",
    "wof:placetype":"venue"
},
  "geometry": {"coordinates":[-71.655762,42.130852],"type":"Point"}
}