{
  "type": "Feature",
  "properties": {
    "iso:country":"US",
    "sg:address":"10 Main St",
    "sg:city":"Stoneham",
    "sg:classifiers":[
        {
            "category":"Restaurant",
            "type":"Food & Drink"
        }
    ],
    "sg:menulink":"http://www.allmenus.com/ma/stoneham/222714-99-restaurant/menu/",
    "sg:phone":"+1 781 279 0399",
    "sg:postcode":"02180",
    "sg:province":"MA",
    "sg:tags":[
        "salad",
        "burger",
        "pub",
        "soup",
        "american",
        "tex-mex"
    ],
    "wof:name":"99 Restaurant",
    "wof:placetype":"venue"
},
  "geometry": {"coordinates":[-71.100827,42.50092],"type":"Point"}
}