{
  "type": "Feature",
  "properties": {
    "iso:country":"US",
    "sg:address":"99 W Main St",
    "sg:city":"Spencer",
    "sg:classifiers":[
        {
            "category":"Personal",
            "subcategory":"Beauty Salon",
            "type":"Services"
        }
    ],
    "sg:phone":"+1 508 885 4477",
    "sg:postcode":"01562",
    "sg:province":"MA",
    "wof:name":"Sheena's Salon",
    "wof:placetype":"venue"
},
  "geometry": {"coordinates":[-72.018676,42.231504],"type":"Point"}
}