{
  "type": "Feature",
  "properties": {
    "addr:full":"144 Wildwood Ave Braintree MA 02184",
    "addr:housenumber":"144",
    "addr:postcode":"02184",
    "addr:street":"Wildwood Ave",
    "iso:country":"US",
    "sg:address":"144 Wildwood Ave",
    "sg:city":"Braintree",
    "sg:classifiers":[
        {
            "category":"Education",
            "subcategory":"School",
            "type":"Public Place"
        }
    ],
    "sg:phone":"+1 781 380 0190",
    "sg:postcode":"02184",
    "sg:province":"MA",
    "sg:tags":[
        "elementary",
        "high"
    ],
    "wof:name":"Highlands Elementary School",
    "wof:placetype":"venue"
},
  "geometry": {"coordinates":[-71.00434300000001,42.177034],"type":"Point"}
}