{
  "type": "Feature",
  "properties": {
    "addr:full":"12 High St Cambridge MA 02138",
    "addr:housenumber":"12",
    "addr:postcode":"02138",
    "addr:street":"High St",
    "iso:country":"US",
    "sg:address":"12 High St",
    "sg:city":"Cambridge",
    "sg:classifiers":[
        {
            "category":"Arts & Performance",
            "subcategory":"Theater",
            "type":"Entertainment"
        }
    ],
    "sg:phone":"+1 617 320 1937",
    "sg:postcode":"02138",
    "sg:province":"MA",
    "sg:tags":[
        "musician"
    ],
    "wof:name":"Liber Unusualis",
    "wof:placetype":"venue"
},
  "geometry": {"coordinates":[-71.150599,42.378028],"type":"Point"}
}