{
  "type": "Feature",
  "properties": {
    "iso:country":"US",
    "sg:address":"1037A Beacon Street",
    "sg:city":"Brookline",
    "sg:classifiers":[
        {
            "category":"Health Services",
            "subcategory":"Dentist",
            "type":"Services"
        }
    ],
    "sg:phone":"+1 617 232 1515",
    "sg:postcode":"02446",
    "sg:province":"MA",
    "sg:website":"http://gentledental.com",
    "wof:name":"Prosthodontic Associates",
    "wof:placetype":"venue"
},
  "geometry": {"coordinates":[-71.108783,42.345341],"type":"Point"}
}