{
  "type": "Feature",
  "properties": {
    "addr:full":"17 Center St Watertown MA 02472",
    "addr:housenumber":"17",
    "addr:postcode":"02472",
    "addr:street":"Center St",
    "iso:country":"US",
    "sg:address":"17 Center St",
    "sg:city":"Watertown",
    "sg:classifiers":[
        {
            "category":"Manufacturing",
            "subcategory":"Printing",
            "type":"Manufacturing & Wholesale Goods"
        }
    ],
    "sg:phone":"+1 617 924 2270",
    "sg:postcode":"02472",
    "sg:province":"MA",
    "sg:tags":[
        "multimedia"
    ],
    "sg:website":"www.odyssee-interactive.net",
    "wof:name":"Odyssee",
    "wof:placetype":"venue"
},
  "geometry": {"coordinates":[-71.17358,42.367992],"type":"Point"}
}