{
  "type": "Feature",
  "properties": {
    "addr:full": "20 Gedick Rd Burlington MA 01803",
    "addr:housenumber": "20",
    "addr:postcode": "01803",
    "addr:street": "Gedick Rd",
    "iso:country": "US",
    "sg:address": "20 Gedick Rd",
    "sg:city": "Burlington",
    "sg:classifiers": [
      {
        "category": "Building \u0026 Trades",
        "subcategory": "Locksmith",
        "type": "Services"
      }
    ],
    "sg:phone": "+1 781 203 6184",
    "sg:postcode": "01803",
    "sg:province": "MA",
    "sg:tags": [
      "key"
    ],
    "wof:name": "Emergency Locksmith 123 Always 24 Hour",
    "wof:placetype": "venue"
  },
  "geometry": {"coordinates":[-71.207212,42.535081],"type":"Point"}
}
