{
  "type": "Feature",
  "properties": {
    "addr:full": "896 Beacon St Boston MA 02215",
    "addr:housenumber": "896",
    "addr:postcode": "02215",
    "addr:street": "Beacon St",
    "iso:country": "US",
    "sg:address": "896 Beacon St",
    "sg:city": "Boston",
    "sg:classifiers": [
      {
        "category": "Professional",
        "subcategory": "Lawyer \u0026 Legal Services",
        "type": "Services"
      }
    ],
    "sg:phone": "+1 617 247 3800",
    "sg:postcode": "02215",
    "sg:province": "MA",
    "sg:tags": [
      "attorney"
    ],
    "wof:name": "Corrigan \u0026 Levy",
    "wof:placetype": "venue"
  },
  "geometry": {"coordinates":[-71.106072,42.346531],"type":"Point"}
}
