{
  "type": "Feature",
  "properties": {
    "addr:full":"355 Main St Plympton MA 02367",
    "addr:housenumber":"355",
    "addr:postcode":"02367",
    "addr:street":"Main St",
    "iso:country":"US",
    "sg:address":"355 Main St",
    "sg:city":"Plympton",
    "sg:classifiers":[
        {
            "category":"Arena",
            "subcategory":"Sports Club",
            "type":"Entertainment"
        }
    ],
    "sg:phone":"+1 781 582 3911",
    "sg:postcode":"02367",
    "sg:province":"MA",
    "sg:tags":[
        "martial art"
    ],
    "wof:name":"Neves Karate Academy",
    "wof:placetype":"venue"
},
  "geometry": {"coordinates":[-70.812039,41.942584],"type":"Point"}
}