{
  "type": "Feature",
  "properties": {
    "addr:full":"101 Tremont St Ste 1100 Boston MA 02108",
    "addr:housenumber":"101",
    "addr:postcode":"02108",
    "addr:street":"Tremont St Ste 1100",
    "iso:country":"US",
    "sg:address":"101 Tremont St Ste 1100",
    "sg:city":"Boston",
    "sg:classifiers":[
        {
            "category":"Professional",
            "subcategory":"Lawyer & Legal Services",
            "type":"Services"
        }
    ],
    "sg:phone":"+1 617 367 7111",
    "sg:postcode":"02108",
    "sg:province":"MA",
    "wof:name":"Griffin Law Office",
    "wof:placetype":"venue"
},
  "geometry": {"coordinates":[-71.061137,42.357078],"type":"Point"}
}