{
  "type": "Feature",
  "properties": {
    "addr:full":"117 Mount Vernon St Winchester MA 01890",
    "addr:housenumber":"117",
    "addr:postcode":"01890",
    "addr:street":"Mount Vernon St",
    "iso:country":"US",
    "sg:address":"117 Mount Vernon St",
    "sg:city":"Winchester",
    "sg:classifiers":[
        {
            "category":"Utilities",
            "subcategory":"Refuse",
            "type":"Services"
        }
    ],
    "sg:phone":"+1 781 729 8526",
    "sg:postcode":"01890",
    "sg:province":"MA",
    "sg:tags":[
        "disposal",
        "waste"
    ],
    "wof:name":"Vitale Environmental Svc",
    "wof:placetype":"venue"
},
  "geometry": {"coordinates":[-71.13264100000001,42.453002],"type":"Point"}
}