{
  "type": "Feature",
  "properties": {
    "iso:country":"US",
    "sg:address":"118 Forest Ave",
    "sg:city":"Hudson",
    "sg:classifiers":[
        {
            "category":"Autos & Motor Vehicles",
            "subcategory":"Automobile Sales",
            "type":"Retail Goods"
        }
    ],
    "sg:phone":"+1 978 562 1797",
    "sg:postcode":"01749",
    "sg:province":"MA",
    "sg:tags":[
        "dealers-used",
        "car",
        "used",
        "cars-wholesale",
        "new"
    ],
    "wof:name":"Reis Auto Sales",
    "wof:placetype":"venue"
},
  "geometry": {"coordinates":[-71.54924,42.387772],"type":"Point"}
}