{
  "type": "Feature",
  "properties": {
    "iso:country":"US",
    "sg:address":"21 Fottler Rd",
    "sg:city":"Hingham",
    "sg:classifiers":[
        {
            "category":"Building & Trades",
            "subcategory":"Electrical",
            "type":"Services"
        }
    ],
    "sg:phone":"+1 781 740 8334",
    "sg:postcode":"02043",
    "sg:province":"MA",
    "sg:tags":[
        "electric",
        "contractor"
    ],
    "wof:name":"Dartmouth Electrical Constr Co",
    "wof:placetype":"venue"
},
  "geometry": {"coordinates":[-70.91266,42.248829],"type":"Point"}
}