{
  "type": "Feature",
  "properties": {
    "addr:full": "295 Elm St Braintree MA 02184",
    "addr:housenumber": "295",
    "addr:postcode": "02184",
    "addr:street": "Elm St",
    "iso:country": "US",
    "sg:address": "295 Elm St",
    "sg:city": "Braintree",
    "sg:classifiers": [
      {
        "category": "Retail",
        "subcategory": "Laundry \u0026 Dry Cleaning",
        "type": "Services"
      }
    ],
    "sg:phone": "+1 617 696 7047",
    "sg:postcode": "02184",
    "sg:province": "MA",
    "sg:tags": [
      "curtain",
      "drapery",
      "cleaner"
    ],
    "sg:website": "http://www.dannysdrycleaners.com",
    "wof:name": "Danny's Cleaners \u0026 Tailors Inc",
    "wof:placetype": "venue"
  },
  "geometry": {"coordinates":[-70.996499,42.224649],"type":"Point"}
}
