{
  "type": "Feature",
  "properties": {
    "addr:full":"617 Chandler St Worcester MA 01602",
    "addr:housenumber":"617",
    "addr:postcode":"01602",
    "addr:street":"Chandler St",
    "iso:country":"US",
    "sg:address":"617 Chandler St",
    "sg:city":"Worcester",
    "sg:classifiers":[
        {
            "category":"Health Services",
            "subcategory":"Doctor",
            "type":"Services"
        }
    ],
    "sg:phone":"+1 508 791 7370",
    "sg:postcode":"01602",
    "sg:province":"MA",
    "sg:tags":[
        "dentist"
    ],
    "wof:name":"James W Vuona DDS",
    "wof:placetype":"venue"
},
  "geometry": {"coordinates":[-71.852705,42.276603],"type":"Point"}
}