{
  "type": "Feature",
  "properties": {
    "iso:country":"US",
    "sg:address":"1120 Long Pond Rd",
    "sg:city":"Plymouth",
    "sg:classifiers":[
        {
            "category":"Education",
            "subcategory":"School",
            "type":"Public Place"
        }
    ],
    "sg:phone":"+1 508 888 1889",
    "sg:postcode":"02360",
    "sg:province":"MA",
    "wof:name":"New Testament Christian School",
    "wof:placetype":"venue"
},
  "geometry": {"coordinates":[-70.560337,41.813419],"type":"Point"}
}