{
  "type": "Feature",
  "properties": {
    "addr:full": "40 West Ave Brockton MA 02301",
    "addr:housenumber": "40",
    "addr:postcode": "02301",
    "addr:street": "West Ave",
    "iso:country": "US",
    "sg:address": "40 West Ave",
    "sg:city": "Brockton",
    "sg:classifiers": [
      {
        "category": "Professional",
        "subcategory": "Lawyer \u0026 Legal Services",
        "type": "Services"
      }
    ],
    "sg:phone": "+1 508 586 4761",
    "sg:postcode": "02301",
    "sg:province": "MA",
    "wof:name": "Lederman Robin Lwyr - CLOSED",
    "wof:placetype": "venue"
  },
  "geometry": {"coordinates":[-71.046799,42.0844],"type":"Point"}
}
