{
  "type": "Feature",
  "properties": {
    "iso:country":"US",
    "sg:address":"40 West Ave",
    "sg:city":"Brockton",
    "sg:classifiers":[
        {
            "category":"Professional",
            "subcategory":"Lawyer & Legal Services",
            "type":"Services"
        }
    ],
    "sg:phone":"+1 508 586 4761",
    "sg:postcode":"02301",
    "sg:province":"MA",
    "wof:name":"Lederman Robin Lwyr - CLOSED",
    "wof:placetype":"venue"
},
  "geometry": {"coordinates":[-71.04679899999999,42.0844],"type":"Point"}
}