{
  "type": "Feature",
  "properties": {
    "iso:country":"US",
    "sg:address":"8 Arlington St",
    "sg:city":"Middleboro",
    "sg:classifiers":[
        {
            "category":"Shopping",
            "subcategory":"Used Merchandise",
            "type":"Retail Goods"
        }
    ],
    "sg:phone":"+1   ",
    "sg:postcode":"02346",
    "sg:province":"MA",
    "wof:name":"Lochthyme Antiques",
    "wof:placetype":"venue"
},
  "geometry": {"coordinates":[-70.920958,41.895219],"type":"Point"}
}