{
  "type": "Feature",
  "properties": {
    "addr:full": "196 N Main St Mansfield MA 02048",
    "addr:housenumber": "196",
    "addr:postcode": "02048",
    "addr:street": "N Main St",
    "iso:country": "US",
    "sg:address": "196 N Main St",
    "sg:city": "Mansfield",
    "sg:classifiers": [
      {
        "category": "Personal",
        "subcategory": "Barber",
        "type": "Services"
      }
    ],
    "sg:phone": "+1 508 339 7190",
    "sg:postcode": "02048",
    "sg:province": "MA",
    "sg:tags": [
      "shop"
    ],
    "wof:name": "Stan S Barber Shoppe",
    "wof:placetype": "venue"
  },
  "geometry": {"coordinates":[-71.218171,42.028781],"type":"Point"}
}
