{
  "type": "Feature",
  "properties": {
    "iso:country":"US",
    "sg:address":"199 Phillips Ave",
    "sg:city":"New Bedford",
    "sg:classifiers":[
        {
            "category":"Insurance",
            "subcategory":"Insurance Agent",
            "type":"Services"
        }
    ],
    "sg:phone":"+1 508 997 7849",
    "sg:postcode":"02746",
    "sg:province":"MA",
    "sg:website":"www.bergeroninsurance.com",
    "wof:name":"Bergeron Insurance",
    "wof:placetype":"venue"
},
  "geometry": {"coordinates":[-70.926942,41.663031],"type":"Point"}
}