{
  "type": "Feature",
  "properties": {
    "iso:country":"US",
    "sg:address":"138 Ipswich St",
    "sg:city":"Boston",
    "sg:classifiers":[
        {
            "category":"Wholesale",
            "subcategory":"Music Publishers",
            "type":"Manufacturing & Wholesale Goods"
        }
    ],
    "sg:phone":"+1 617 236 1935",
    "sg:postcode":"02215",
    "sg:province":"MA",
    "sg:tags":[
        "distribution"
    ],
    "sg:website":"http://www.ecspublishing.com",
    "wof:name":"Ione Press Inc",
    "wof:placetype":"venue"
},
  "geometry": {"coordinates":[-71.093857,42.347519],"type":"Point"}
}