{
  "type": "Feature",
  "properties": {
    "iso:country":"US",
    "sg:address":"221 Boston Rd Suite 4",
    "sg:city":"Billerica",
    "sg:classifiers":[
        {
            "category":"Health Services",
            "subcategory":"Doctor",
            "type":"Services"
        }
    ],
    "sg:phone":"+1 978 670 1300",
    "sg:postcode":"01862",
    "sg:province":"MA",
    "sg:tags":[
        "medicine",
        "practice",
        "internal",
        "family"
    ],
    "sg:website":"www.billericamedicalhealth.com",
    "wof:name":"Joshi Ashok K MD",
    "wof:placetype":"venue"
},
  "geometry": {"coordinates":[-71.286258,42.579174],"type":"Point"}
}