{
  "type": "Feature",
  "properties": {
    "addr:full":"268 Great Rd Acton MA 01720",
    "addr:housenumber":"268",
    "addr:postcode":"01720",
    "addr:street":"Great Rd",
    "iso:country":"US",
    "sg:address":"268 Great Rd",
    "sg:city":"Acton",
    "sg:classifiers":[
        {
            "category":"Shopping",
            "type":"Retail Goods"
        }
    ],
    "sg:phone":"+1 978 263 0574",
    "sg:postcode":"01720",
    "sg:province":"MA",
    "sg:tags":[
        "picture",
        "frame"
    ],
    "wof:name":"Acton Framers",
    "wof:placetype":"venue"
},
  "geometry": {"coordinates":[-71.41678899999999,42.495719],"type":"Point"}
}