{
  "type": "Feature",
  "properties": {
    "iso:country":"US",
    "sg:address":"90 Pleasant Valley St",
    "sg:city":"Methuen",
    "sg:classifiers":[
        {
            "category":"Restaurant",
            "type":"Food & Drink"
        }
    ],
    "sg:phone":"+1 978 974 0015",
    "sg:postcode":"01844",
    "sg:province":"MA",
    "sg:tags":[
        "eating"
    ],
    "wof:name":"Not Your Average Joe's",
    "wof:placetype":"venue"
},
  "geometry": {"coordinates":[-71.180126,42.732532],"type":"Point"}
}