{
  "type": "Feature",
  "properties": {
    "addr:full": "908 Main St Acton MA 01720",
    "addr:housenumber": "908",
    "addr:postcode": "01720",
    "addr:street": "Main St",
    "iso:country": "US",
    "ovtr:label": "Nashoba Sportsmens Club, 908 Main St Acton MA US",
    "ovtr:similarity": 2.193113088607788,
    "sg:address": "908 Main St",
    "sg:city": "Acton",
    "sg:classifiers": [
      {
        "category": "Recreation",
        "type": "Entertainment"
      }
    ],
    "sg:phone": "+1 978 635 0573",
    "sg:postcode": "01720",
    "sg:province": "MA",
    "sg:tags": [
      "sport",
      "amateur",
      "center",
      "team"
    ],
    "wof:name": "Nashoba Sportsmens Club",
    "wof:placetype": "venue"
  },
  "geometry": {"coordinates":[-71.403503,42.522099],"type":"Point"}
}
