{
  "type": "Feature",
  "properties": {
    "iso:country":"US",
    "sg:address":"1041 Pearl St",
    "sg:city":"Brockton",
    "sg:classifiers":[
        {
            "category":"Freight",
            "type":"Transportation"
        }
    ],
    "sg:phone":"+1 508 436 6766",
    "sg:postcode":"02301",
    "sg:province":"MA",
    "sg:tags":[
        "delivery"
    ],
    "wof:name":"Transportech",
    "wof:placetype":"venue"
},
  "geometry": {"coordinates":[-71.06678700000001,42.054314],"type":"Point"}
}