{
  "type": "Feature",
  "properties": {
    "addr:full": "1041 Pearl St Brockton MA 02301",
    "addr:housenumber": "1041",
    "addr:postcode": "02301",
    "addr:street": "Pearl St",
    "iso:country": "US",
    "sg:address": "1041 Pearl St",
    "sg:city": "Brockton",
    "sg:classifiers": [
      {
        "category": "Freight",
        "type": "Transportation"
      }
    ],
    "sg:phone": "+1 508 436 6766",
    "sg:postcode": "02301",
    "sg:province": "MA",
    "sg:tags": [
      "delivery"
    ],
    "wof:name": "Transportech",
    "wof:placetype": "venue"
  },
  "geometry": {"coordinates":[-71.066787,42.054314],"type":"Point"}
}
