{
  "type": "Feature",
  "properties": {
    "addr:full":"188 Gore Rd Webster MA 01570",
    "addr:housenumber":"188",
    "addr:postcode":"01570",
    "addr:street":"Gore Rd",
    "iso:country":"US",
    "sg:address":"188 Gore Rd",
    "sg:city":"Webster",
    "sg:classifiers":[
        {
            "category":"Fast Food",
            "type":"Food & Drink"
        },
        {
            "category":"Restaurant",
            "type":"Food & Drink"
        },
        {
            "category":"Food & Beverages",
            "subcategory":"Groceries & Convenience Stores",
            "type":"Retail Goods"
        }
    ],
    "sg:phone":"+1 508 943 3833",
    "sg:postcode":"01570",
    "sg:province":"MA",
    "sg:tags":[
        "shop",
        "american",
        "sandwich",
        "take"
    ],
    "sg:website":"http://www.subway.com",
    "wof:name":"Subway",
    "wof:placetype":"venue"
},
  "geometry": {"coordinates":[-71.83944099999999,42.053702],"type":"Point"}
}