{
  "type": "Feature",
  "properties": {
    "addr:full": "188 Gore Rd Webster MA 01570",
    "addr:housenumber": "188",
    "addr:postcode": "01570",
    "addr:street": "Gore Rd",
    "iso:country": "US",
    "ovtr:label": "Subway, 188 Gore Rd Webster MA US",
    "ovtr:similarity": 2.606605052947998,
    "sg:address": "188 Gore Rd",
    "sg:city": "Webster",
    "sg:classifiers": [
      {
        "category": "Fast Food",
        "type": "Food \u0026 Drink"
      },
      {
        "category": "Restaurant",
        "type": "Food \u0026 Drink"
      },
      {
        "category": "Food \u0026 Beverages",
        "subcategory": "Groceries \u0026 Convenience Stores",
        "type": "Retail Goods"
      }
    ],
    "sg:phone": "+1 508 943 3833",
    "sg:postcode": "01570",
    "sg:province": "MA",
    "sg:tags": [
      "shop",
      "american",
      "sandwich",
      "take"
    ],
    "sg:website": "http://www.subway.com",
    "wof:name": "Subway",
    "wof:placetype": "venue"
  },
  "geometry": {"coordinates":[-71.839441,42.053702],"type":"Point"}
}
