{
  "type": "Feature",
  "properties": {
    "addr:full": "80 New Salem St Wakefield MA 01880",
    "addr:housenumber": "80",
    "addr:postcode": "01880",
    "addr:street": "New Salem St",
    "iso:country": "US",
    "sg:address": "80 New Salem St",
    "sg:city": "Wakefield",
    "sg:classifiers": [
      {
        "category": "Freight",
        "type": "Transportation"
      },
      {
        "category": "Building \u0026 Trades",
        "subcategory": "Construction",
        "type": "Services"
      }
    ],
    "sg:phone": "+1 781 245 0307",
    "sg:postcode": "01880",
    "sg:province": "MA",
    "sg:tags": [
      "excavating",
      "contractor",
      "trucking"
    ],
    "wof:name": "Taibbi Equipment Corp",
    "wof:placetype": "venue"
  },
  "geometry": {"coordinates":[-71.065015,42.505268],"type":"Point"}
}
