{
  "type": "Feature",
  "properties": {
    "addr:full": "130 Baker Ave Concord MA 01742",
    "addr:housenumber": "130",
    "addr:postcode": "01742",
    "addr:street": "Baker Ave",
    "iso:country": "US",
    "sg:address": "130 Baker Ave",
    "sg:city": "Concord",
    "sg:classifiers": [
      {
        "category": "Manufacturing",
        "subcategory": "Tools \u0026 Machinery",
        "type": "Manufacturing \u0026 Wholesale Goods"
      }
    ],
    "sg:phone": "+1   ",
    "sg:postcode": "01742",
    "sg:province": "MA",
    "sg:tags": [
      "analytical",
      "optical",
      "mfg"
    ],
    "wof:name": "Oxford Diffraction",
    "wof:placetype": "venue"
  },
  "geometry": {"coordinates":[-71.383407,42.461589],"type":"Point"}
}
