{
  "type": "Feature",
  "properties": {
    "addr:full":"1316 Massachusetts Ave Cambridge MA 02138",
    "addr:housenumber":"1316",
    "addr:postcode":"02138",
    "addr:street":"Massachusetts Ave",
    "iso:country":"US",
    "sg:address":"1316 Massachusetts Ave",
    "sg:city":"Cambridge",
    "sg:classifiers":[
        {
            "category":"Shopping",
            "subcategory":"Jewelry",
            "type":"Retail Goods"
        }
    ],
    "sg:phone":"+1 617 491 6991",
    "sg:postcode":"02138",
    "sg:province":"MA",
    "sg:website":"www.zipajewelry.com",
    "wof:name":"Zipa Jewelry",
    "wof:placetype":"venue"
},
  "geometry": {"coordinates":[-71.117699,42.373199],"type":"Point"}
}