{
  "type": "Feature",
  "properties": {
    "iso:country":"US",
    "sg:address":"109 Highland Ave",
    "sg:city":"Needham",
    "sg:classifiers":[
        {
            "category":"Professional",
            "subcategory":"Computer Services",
            "type":"Services"
        }
    ],
    "sg:phone":"+1 781 449 5077",
    "sg:postcode":"02494",
    "sg:province":"MA",
    "sg:tags":[
        "consultant",
        "designer"
    ],
    "sg:website":"www.arrowheadsolutions.com",
    "wof:name":"Arrowhead Solutions",
    "wof:placetype":"venue"
},
  "geometry": {"coordinates":[-71.218571,42.305345],"type":"Point"}
}