{
  "type": "Feature",
  "properties": {
    "iso:country":"US",
    "sg:address":"3 N St",
    "sg:city":"Boston",
    "sg:classifiers":[
        {
            "category":"Restaurant",
            "type":"Food & Drink"
        }
    ],
    "sg:phone":"+1 617 523 0077",
    "sg:postcode":"02127",
    "sg:province":"MA",
    "sg:website":"www.mammamaria.com/",
    "wof:name":"Mamma Maria Restaurant",
    "wof:placetype":"venue"
},
  "geometry": {"coordinates":[-71.03119700000001,42.337299],"type":"Point"}
}