{
  "type": "Feature",
  "properties": {
    "iso:country":"US",
    "sg:address":"421 N Main St",
    "sg:city":"Leeds",
    "sg:classifiers":[
        {
            "category":"Health Services",
            "subcategory":"Hospital",
            "type":"Services"
        }
    ],
    "sg:phone":"+1   ",
    "sg:postcode":"01053",
    "sg:province":"MA",
    "sg:tags":[
        "specialty"
    ],
    "wof:name":"VA Medical Center 631",
    "wof:placetype":"venue"
},
  "geometry": {"coordinates":[-72.682895,42.345026],"type":"Point"}
}