{
  "type": "Feature",
  "properties": {
    "iso:country":"US",
    "sg:address":"258 Park Ave",
    "sg:city":"Worcester",
    "sg:classifiers":[
        {
            "category":"Arts & Performance",
            "subcategory":"Theater",
            "type":"Entertainment"
        }
    ],
    "sg:phone":"+1 508 755 7373",
    "sg:postcode":"01609",
    "sg:province":"MA",
    "sg:tags":[
        "musician"
    ],
    "sg:website":"www.royalacademyarts.com",
    "wof:name":"Royal Academy-Performing Arts",
    "wof:placetype":"venue"
},
  "geometry": {"coordinates":[-71.81938,42.264444],"type":"Point"}
}