{
  "type": "Feature",
  "properties": {
    "addr:full": "62 Forge River Pkwy Raynham MA 02767",
    "addr:housenumber": "62",
    "addr:postcode": "02767",
    "addr:street": "Forge River Pkwy",
    "iso:country": "US",
    "sg:address": "62 Forge River Pkwy",
    "sg:city": "Raynham",
    "sg:classifiers": [
      {
        "category": "Real Estate",
        "subcategory": "Real Estate Agent",
        "type": "Services"
      }
    ],
    "sg:phone": "+1 508 823 0349",
    "sg:postcode": "02767",
    "sg:province": "MA",
    "sg:tags": [
      "appraiser"
    ],
    "wof:name": "Appraisal Resource",
    "wof:placetype": "venue"
  },
  "geometry": {"coordinates":[-71.062898,41.909305],"type":"Point"}
}
