{
  "type": "Feature",
  "properties": {
    "addr:full": "214 Maple St Holyoke MA 01040",
    "addr:housenumber": "214",
    "addr:postcode": "01040",
    "addr:street": "Maple St",
    "iso:country": "US",
    "sg:address": "214 Maple St",
    "sg:city": "Holyoke",
    "sg:classifiers": [
      {
        "category": "Manufacturing",
        "subcategory": "Printing",
        "type": "Manufacturing \u0026 Wholesale Goods"
      }
    ],
    "sg:phone": "+1 413 533 2600",
    "sg:postcode": "01040",
    "sg:province": "MA",
    "sg:tags": [
      "label"
    ],
    "wof:name": "Label Group",
    "wof:placetype": "venue"
  },
  "geometry": {"coordinates":[-72.607714,42.20837],"type":"Point"}
}
