{
  "type": "Feature",
  "properties": {
    "iso:country":"US",
    "sg:address":"9 Sabino Farm Rd R",
    "sg:city":"Peabody",
    "sg:classifiers":[
        {
            "category":"Retail",
            "subcategory":"Funeral Services",
            "type":"Services"
        }
    ],
    "sg:phone":"+1 978 531 3336",
    "sg:postcode":"01960",
    "sg:province":"MA",
    "sg:tags":[
        "burial",
        "vault"
    ],
    "wof:name":"North Shore Vault Co Inc",
    "wof:placetype":"venue"
},
  "geometry": {"coordinates":[-70.93159799999999,42.539445],"type":"Point"}
}