{
  "type": "Feature",
  "properties": {
    "addr:full":"1313 Washington St Roxbury MA 02118",
    "addr:housenumber":"1313",
    "addr:postcode":"02118",
    "addr:street":"Washington St",
    "iso:country":"US",
    "sg:address":"1313 Washington St",
    "sg:city":"Roxbury",
    "sg:classifiers":[
        {
            "category":"Home & Garden",
            "subcategory":"Furniture",
            "type":"Retail Goods"
        }
    ],
    "sg:phone":"+1 617 423 7632",
    "sg:postcode":"02118",
    "sg:province":"MA",
    "sg:tags":[
        "store"
    ],
    "wof:name":"Biltmore Furniture",
    "wof:placetype":"venue"
},
  "geometry": {"coordinates":[-71.068398,42.3419],"type":"Point"}
}