{
  "type": "Feature",
  "properties": {
    "addr:full": "15 Market St Northampton MA 01060",
    "addr:housenumber": "15",
    "addr:postcode": "01060",
    "addr:street": "Market St",
    "iso:country": "US",
    "sg:address": "15 Market St",
    "sg:city": "Northampton",
    "sg:classifiers": [
      {
        "category": "Shopping",
        "subcategory": "Used Merchandise",
        "type": "Retail Goods"
      }
    ],
    "sg:phone": "+1 413 584 3978",
    "sg:postcode": "01060",
    "sg:province": "MA",
    "wof:name": "Better Yet",
    "wof:placetype": "venue"
  },
  "geometry": {"coordinates":[-72.628672,42.32112],"type":"Point"}
}
