{
  "type": "Feature",
  "properties": {
    "addr:full":"157 High St Greenfield MA 01301",
    "addr:housenumber":"157",
    "addr:postcode":"01301",
    "addr:street":"High St",
    "iso:country":"US",
    "sg:address":"157 High St",
    "sg:city":"Greenfield",
    "sg:classifiers":[
        {
            "category":"Health Services",
            "subcategory":"Doctor",
            "type":"Services"
        }
    ],
    "sg:phone":"+1 413 772 0172",
    "sg:postcode":"01301",
    "sg:province":"MA",
    "sg:tags":[
        "physician",
        "surgeon"
    ],
    "wof:name":"Associated Surgeons-Greenfield",
    "wof:placetype":"venue"
},
  "geometry": {"coordinates":[-72.591207,42.595531],"type":"Point"}
}