{
  "type": "Feature",
  "properties": {
    "iso:country":"US",
    "sg:address":"287 Grove St",
    "sg:city":"Worcester",
    "sg:classifiers":[
        {
            "category":"Freight",
            "type":"Transportation"
        }
    ],
    "sg:phone":"+1 508 791 9782",
    "sg:postcode":"01605",
    "sg:province":"MA",
    "wof:name":"Worcester Area Transportation",
    "wof:placetype":"venue"
},
  "geometry": {"coordinates":[-71.80683999999999,42.282947],"type":"Point"}
}