{
  "type": "Feature",
  "properties": {
    "iso:country":"US",
    "sg:address":"58 Roundwood Rd",
    "sg:city":"Newton",
    "sg:classifiers":[
        {
            "category":"Professional",
            "subcategory":"Art Services",
            "type":"Services"
        }
    ],
    "sg:phone":"+1 617 244 9504",
    "sg:postcode":"02464",
    "sg:province":"MA",
    "sg:tags":[
        "photographer"
    ],
    "wof:name":"Silver Vision Publishing Co",
    "wof:placetype":"venue"
},
  "geometry": {"coordinates":[-71.217538,42.31671],"type":"Point"}
}