{
  "type": "Feature",
  "properties": {
    "addr:full":"89 Wanamaker Rd Northfield MA 01360",
    "addr:housenumber":"89",
    "addr:postcode":"01360",
    "addr:street":"Wanamaker Rd",
    "iso:country":"US",
    "sg:address":"89 Wanamaker Rd",
    "sg:city":"Northfield",
    "sg:classifiers":[
        {
            "category":"Shopping",
            "subcategory":"Used Merchandise",
            "type":"Retail Goods"
        }
    ],
    "sg:phone":"+1 413 498 5574",
    "sg:postcode":"01360",
    "sg:province":"MA",
    "sg:tags":[
        "antique"
    ],
    "wof:name":"Mulberry Farm Antiques & Herbs",
    "wof:placetype":"venue"
},
  "geometry": {"coordinates":[-72.437996,42.72607],"type":"Point"}
}