{
  "type": "Feature",
  "properties": {
    "iso:country":"US",
    "sg:address":"1235 River St",
    "sg:city":"Hyde Park",
    "sg:classifiers":[
        {
            "category":"Personal",
            "subcategory":"Beauty Salon",
            "type":"Services"
        }
    ],
    "sg:phone":"+1 617 364 0838",
    "sg:postcode":"02136",
    "sg:province":"MA",
    "wof:name":"Maria's Hair Salon",
    "wof:placetype":"venue"
},
  "geometry": {"coordinates":[-71.123555,42.255963],"type":"Point"}
}