{
  "type": "Feature",
  "properties": {
    "iso:country":"US",
    "sg:address":"26 S Water St",
    "sg:city":"New Bedford",
    "sg:classifiers":[
        {
            "category":"Health Services",
            "subcategory":"Chiropractor",
            "type":"Services"
        }
    ],
    "sg:phone":"+1 508 993 5663",
    "sg:postcode":"02740",
    "sg:province":"MA",
    "wof:name":"Douglas D Gagnon DC",
    "wof:placetype":"venue"
},
  "geometry": {"coordinates":[-70.923226,41.632965],"type":"Point"}
}