{
  "type": "Feature",
  "properties": {
    "addr:full":"1 South St Southbridge MA 01550",
    "addr:housenumber":"1",
    "addr:postcode":"01550",
    "addr:street":"South St",
    "iso:country":"US",
    "sg:address":"1 South St",
    "sg:city":"Southbridge",
    "sg:classifiers":[
        {
            "category":"Travel",
            "subcategory":"Hotels & Motels",
            "type":"Entertainment"
        }
    ],
    "sg:phone":"+1   ",
    "sg:postcode":"01550",
    "sg:province":"MA",
    "sg:tags":[
        "personal",
        "operation",
        "s",
        "business"
    ],
    "wof:name":"Aramark",
    "wof:placetype":"venue"
},
  "geometry": {"coordinates":[-72.03816999999999,42.07766],"type":"Point"}
}