{
  "type": "Feature",
  "properties": {
    "addr:full":"7 Pheasant Hill Rd Granby MA 01033",
    "addr:housenumber":"7",
    "addr:postcode":"01033",
    "addr:street":"Pheasant Hill Rd",
    "iso:country":"US",
    "sg:address":"7 Pheasant Hill Rd",
    "sg:city":"Granby",
    "sg:classifiers":[
        {
            "category":"Professional",
            "subcategory":"Business Services",
            "type":"Services"
        }
    ],
    "sg:phone":"+1 413 467 1598",
    "sg:postcode":"01033",
    "sg:province":"MA",
    "sg:tags":[
        "water",
        "treatment"
    ],
    "wof:name":"ADK Water Management",
    "wof:placetype":"venue"
},
  "geometry": {"coordinates":[-72.53430299999999,42.24443],"type":"Point"}
}