{
  "type": "Feature",
  "properties": {
    "iso:country":"US",
    "sg:address":"106 High St",
    "sg:city":"Clinton",
    "sg:classifiers":[
        {
            "category":"Shopping",
            "subcategory":"Florist",
            "type":"Retail Goods"
        }
    ],
    "sg:phone":"+1 978 368 8600",
    "sg:postcode":"01510",
    "sg:province":"MA",
    "wof:name":"Country Garden Florist",
    "wof:placetype":"venue"
},
  "geometry": {"coordinates":[-71.684634,42.418397],"type":"Point"}
}