{
  "type": "Feature",
  "properties": {
    "addr:full": "643 Brayton Ave Fall River MA 02721",
    "addr:housenumber": "643",
    "addr:postcode": "02721",
    "addr:street": "Brayton Ave",
    "iso:country": "US",
    "ovtr:label": "Bob Luongo's Auto Sales, 643 Brayton Ave Fall River MA US",
    "ovtr:similarity": 2.121628999710083,
    "sg:address": "643 Brayton Ave",
    "sg:city": "Fall River",
    "sg:classifiers": [
      {
        "category": "Autos \u0026 Motor Vehicles",
        "subcategory": "Automobile Sales",
        "type": "Retail Goods"
      }
    ],
    "sg:phone": "+1 508 675 1303",
    "sg:postcode": "02721",
    "sg:province": "MA",
    "sg:tags": [
      "car",
      "dealer"
    ],
    "wof:name": "Bob Luongo's Auto Sales",
    "wof:placetype": "venue"
  },
  "geometry": {"coordinates":[-71.146502,41.6826],"type":"Point"}
}
