{
  "type": "Feature",
  "properties": {
    "iso:country":"US",
    "sg:address":"643 Brayton Ave",
    "sg:city":"Fall River",
    "sg:classifiers":[
        {
            "category":"Autos & Motor Vehicles",
            "subcategory":"Automobile Sales",
            "type":"Retail Goods"
        }
    ],
    "sg:phone":"+1 508 675 1303",
    "sg:postcode":"02721",
    "sg:province":"MA",
    "sg:tags":[
        "car",
        "dealer"
    ],
    "wof:name":"Bob Luongo's Auto Sales",
    "wof:placetype":"venue"
},
  "geometry": {"coordinates":[-71.146502,41.6826],"type":"Point"}
}