{
  "type": "Feature",
  "properties": {
    "addr:full": "1457 Dorchester Ave Dorchester MA 02122",
    "addr:housenumber": "1457",
    "addr:postcode": "02122",
    "addr:street": "Dorchester Ave",
    "iso:country": "US",
    "sg:address": "1457 Dorchester Ave",
    "sg:city": "Dorchester",
    "sg:classifiers": [
      {
        "category": "Insurance",
        "subcategory": "Insurance Agent",
        "type": "Services"
      }
    ],
    "sg:phone": "+1 617 825 5788",
    "sg:postcode": "02122",
    "sg:province": "MA",
    "wof:name": "Karlene A Valnete",
    "wof:placetype": "venue"
  },
  "geometry": {"coordinates":[-71.059924,42.301401],"type":"Point"}
}
