{
  "type": "Feature",
  "properties": {
    "addr:full": "353 Providence Rd South Grafton MA 01560",
    "addr:housenumber": "353",
    "addr:postcode": "01560",
    "addr:street": "Providence Rd",
    "iso:country": "US",
    "sg:address": "353 Providence Rd",
    "sg:city": "South Grafton",
    "sg:classifiers": [
      {
        "category": "Sports \u0026 Exercise",
        "subcategory": "Gym",
        "type": "Entertainment"
      }
    ],
    "sg:phone": "+1 508 839 0011",
    "sg:postcode": "01560",
    "sg:province": "MA",
    "sg:tags": [
      "club",
      "health",
      "studio",
      "gymnasium"
    ],
    "wof:name": "Omega Fitness Ctr",
    "wof:placetype": "venue"
  },
  "geometry": {"coordinates":[-71.672101,42.170595],"type":"Point"}
}
