{
  "type": "Feature",
  "properties": {
    "addr:full": "94 King St Northampton MA 01060",
    "addr:housenumber": "94",
    "addr:postcode": "01060",
    "addr:street": "King St",
    "iso:country": "US",
    "sg:address": "94 King St",
    "sg:city": "Northampton",
    "sg:classifiers": [
      {
        "category": "Health Services",
        "subcategory": "Doctor",
        "type": "Services"
      }
    ],
    "sg:phone": "+1 413 585 8880",
    "sg:postcode": "01060",
    "sg:province": "MA",
    "sg:tags": [
      "physician",
      "surgeon"
    ],
    "wof:name": "Charles K Brummer MD",
    "wof:placetype": "venue"
  },
  "geometry": {"coordinates":[-72.63215,42.322246],"type":"Point"}
}
