{
  "type": "Feature",
  "properties": {
    "addr:full": "52 Juniper Rd Fitchburg MA 01420",
    "addr:housenumber": "52",
    "addr:postcode": "01420",
    "addr:street": "Juniper Rd",
    "iso:country": "US",
    "sg:address": "52 Juniper Rd",
    "sg:city": "Fitchburg",
    "sg:classifiers": [
      {
        "category": "Real Estate",
        "subcategory": "Real Estate Agent",
        "type": "Services"
      }
    ],
    "sg:phone": "+1 978 345 6400",
    "sg:postcode": "01420",
    "sg:province": "MA",
    "sg:tags": [
      "inspection"
    ],
    "wof:name": "Allmac Home Inspections Inc",
    "wof:placetype": "venue"
  },
  "geometry": {"coordinates":[-71.789346,42.602565],"type":"Point"}
}
