{
  "type": "Feature",
  "properties": {
    "addr:full": "15 Wheeler Ave Framingham MA 01702",
    "addr:housenumber": "15",
    "addr:postcode": "01702",
    "addr:street": "Wheeler Ave",
    "iso:country": "US",
    "sg:address": "15 Wheeler Ave",
    "sg:city": "Framingham",
    "sg:classifiers": [
      {
        "category": "Organizations",
        "subcategory": "Religious Organization",
        "type": "Services"
      }
    ],
    "sg:phone": "+1 508 879 4271",
    "sg:postcode": "01702",
    "sg:province": "MA",
    "wof:name": "St Bridget's Ccd Religious",
    "wof:placetype": "venue"
  },
  "geometry": {"coordinates":[-71.430853,42.299043],"type":"Point"}
}
