{
  "type": "Feature",
  "properties": {
    "addr:full":"1432 Main St Palmer MA 01069",
    "addr:housenumber":"1432",
    "addr:postcode":"01069",
    "addr:street":"Main St",
    "iso:country":"US",
    "sg:address":"1432 Main St",
    "sg:city":"Palmer",
    "sg:classifiers":[
        {
            "category":"Home & Garden",
            "subcategory":"Furniture",
            "type":"Retail Goods"
        }
    ],
    "sg:phone":"+1 413 283 7040",
    "sg:postcode":"01069",
    "sg:province":"MA",
    "sg:tags":[
        "equipment",
        "kitchen",
        "cabinet"
    ],
    "wof:name":"Ideal Kitchen Cabinet Fronts",
    "wof:placetype":"venue"
},
  "geometry": {"coordinates":[-72.329949,42.157301],"type":"Point"}
}