{
  "type": "Feature",
  "properties": {
    "addr:full": "25 Nevada Ave Malden MA 02148",
    "addr:housenumber": "25",
    "addr:postcode": "02148",
    "addr:street": "Nevada Ave",
    "iso:country": "US",
    "sg:address": "25 Nevada Ave",
    "sg:city": "Malden",
    "sg:classifiers": [
      {
        "category": "Professional",
        "subcategory": "Computer Services",
        "type": "Services"
      }
    ],
    "sg:phone": "+1 781 397 8713",
    "sg:postcode": "02148",
    "sg:province": "MA",
    "sg:tags": [
      "programing",
      "custom"
    ],
    "sg:website": "www.msz.com",
    "wof:name": "MSZ Computing Inc",
    "wof:placetype": "venue"
  },
  "geometry": {"coordinates":[-71.060078,42.436603],"type":"Point"}
}
