{
  "type": "Feature",
  "properties": {
    "addr:full": "3217 Main St Barnstable MA 02630",
    "addr:housenumber": "3217",
    "addr:postcode": "02630",
    "addr:street": "Main St",
    "iso:country": "US",
    "sg:address": "3217 Main St",
    "sg:city": "Barnstable",
    "sg:classifiers": [
      {
        "category": "Professional",
        "subcategory": "Lawyer \u0026 Legal Services",
        "type": "Services"
      }
    ],
    "sg:phone": "+1 508 362 0166",
    "sg:postcode": "02630",
    "sg:province": "MA",
    "wof:name": "Psomos Penelope",
    "wof:placetype": "venue"
  },
  "geometry": {"coordinates":[-70.305102,41.701905],"type":"Point"}
}
