{
  "type": "Feature",
  "properties": {
    "iso:country":"US",
    "sg:address":"200 Dartmouth St",
    "sg:city":"New Bedford",
    "sg:classifiers":[
        {
            "category":"Shopping",
            "subcategory":"Discount & Variety Stores",
            "type":"Retail Goods"
        }
    ],
    "sg:phone":"+1 508 996 9798",
    "sg:postcode":"02740",
    "sg:province":"MA",
    "wof:name":"Scents 4 Cents",
    "wof:placetype":"venue"
},
  "geometry": {"coordinates":[-70.934147,41.622456],"type":"Point"}
}