{
  "type": "Feature",
  "properties": {
    "iso:country":"US",
    "sg:address":"439 White St",
    "sg:city":"Springfield",
    "sg:classifiers":[
        {
            "category":"Shopping",
            "subcategory":"Clothing, Apparel, & Fashions",
            "type":"Retail Goods"
        }
    ],
    "sg:phone":"+1 413 731 1944",
    "sg:postcode":"01108",
    "sg:province":"MA",
    "sg:tags":[
        "hat"
    ],
    "wof:name":"Brim & Crown Shop",
    "wof:placetype":"venue"
},
  "geometry": {"coordinates":[-72.549892,42.088312],"type":"Point"}
}