{
  "type": "Feature",
  "properties": {
    "iso:country":"US",
    "sg:address":"410 Lakeside Ave",
    "sg:city":"Marlborough",
    "sg:classifiers":[
        {
            "category":"Autos & Motor Vehicles",
            "subcategory":"Fuel & Gas Station",
            "type":"Retail Goods"
        }
    ],
    "sg:phone":"+1 508 480 0431",
    "sg:postcode":"01752",
    "sg:province":"MA",
    "sg:tags":[
        "oil"
    ],
    "wof:name":"Lakeside Exxon",
    "wof:placetype":"venue"
},
  "geometry": {"coordinates":[-71.579522,42.34123],"type":"Point"}
}