{
  "type": "Feature",
  "properties": {
    "addr:full":"140 N Dartmouth Mall North Dartmouth MA 02747",
    "addr:housenumber":"140",
    "addr:postcode":"02747",
    "addr:street":"N Dartmouth Mall",
    "iso:country":"US",
    "sg:address":"140 N Dartmouth Mall",
    "sg:city":"North Dartmouth",
    "sg:classifiers":[
        {
            "category":"Cinema",
            "subcategory":"Movie Theater",
            "type":"Entertainment"
        }
    ],
    "sg:phone":"+1 508 999 3142",
    "sg:postcode":"02747",
    "sg:province":"MA",
    "wof:name":"NORTH Dartmouth Mall Cinema",
    "wof:placetype":"venue"
},
  "geometry": {"coordinates":[-70.99244899999999,41.642865],"type":"Point"}
}