{
  "type": "Feature",
  "properties": {
    "addr:full": "59 Linden St Taunton MA 02780",
    "addr:housenumber": "59",
    "addr:postcode": "02780",
    "addr:street": "Linden St",
    "iso:country": "US",
    "sg:address": "59 Linden St",
    "sg:city": "Taunton",
    "sg:classifiers": [
      {
        "category": "Freight",
        "type": "Transportation"
      }
    ],
    "sg:phone": "+1   ",
    "sg:postcode": "02780",
    "sg:province": "MA",
    "wof:name": "Guillemette Brothers Inc",
    "wof:placetype": "venue"
  },
  "geometry": {"coordinates":[-71.076373,41.886721],"type":"Point"}
}
