{
  "type": "Feature",
  "properties": {
    "iso:country":"US",
    "sg:address":"59 Linden St",
    "sg:city":"Taunton",
    "sg:classifiers":[
        {
            "category":"Freight",
            "type":"Transportation"
        }
    ],
    "sg:phone":"+1   ",
    "sg:postcode":"02780",
    "sg:province":"MA",
    "wof:name":"Guillemette Brothers Inc",
    "wof:placetype":"venue"
},
  "geometry": {"coordinates":[-71.076373,41.886721],"type":"Point"}
}