{
  "type": "Feature",
  "properties": {
    "addr:full": "19 Bay State Ct Brewster MA 02631",
    "addr:housenumber": "19",
    "addr:postcode": "02631",
    "addr:street": "Bay State Ct",
    "iso:country": "US",
    "sg:address": "19 Bay State Ct",
    "sg:city": "Brewster",
    "sg:classifiers": [
      {
        "category": "Health Services",
        "subcategory": "Doctor",
        "type": "Services"
      }
    ],
    "sg:phone": "+1 508 255 2325",
    "sg:postcode": "02631",
    "sg:province": "MA",
    "sg:tags": [
      "gynecology",
      "physician",
      "surgeon",
      "surgeons",
      "obstetrics"
    ],
    "sg:website": "http://www.capegynecology.com",
    "wof:name": "Cape Gynecology LLC",
    "wof:placetype": "venue"
  },
  "geometry": {"coordinates":[-70.008913,41.774681],"type":"Point"}
}
