{
  "type": "Feature",
  "properties": {
    "iso:country":"US",
    "sg:address":"186 Groveland St",
    "sg:city":"Haverhill",
    "sg:classifiers":[
        {
            "category":"Building & Trades",
            "subcategory":"Construction",
            "type":"Services"
        }
    ],
    "sg:phone":"+1   ",
    "sg:postcode":"01830",
    "sg:province":"MA",
    "sg:tags":[
        "house"
    ],
    "wof:name":"Archambault Const",
    "wof:placetype":"venue"
},
  "geometry": {"coordinates":[-71.05140900000001,42.768141],"type":"Point"}
}