{
  "type": "Feature",
  "properties": {
    "addr:full":"117 Mott St New Bedford MA 02744",
    "addr:housenumber":"117",
    "addr:postcode":"02744",
    "addr:street":"Mott St",
    "iso:country":"US",
    "sg:address":"117 Mott St",
    "sg:city":"New Bedford",
    "sg:classifiers":[
        {
            "category":"Freight",
            "type":"Transportation"
        }
    ],
    "sg:phone":"+1   ",
    "sg:postcode":"02744",
    "sg:province":"MA",
    "sg:tags":[
        "operator",
        "local",
        "trucking"
    ],
    "wof:name":"S&W Trucking",
    "wof:placetype":"venue"
},
  "geometry": {"coordinates":[-70.91297,41.611538],"type":"Point"}
}