{
  "type": "Feature",
  "properties": {
    "iso:country":"US",
    "sg:address":"92 Newton St",
    "sg:city":"Brookline",
    "sg:classifiers":[
        {
            "category":"Professional",
            "subcategory":"Lawyer & Legal Services",
            "type":"Services"
        }
    ],
    "sg:phone":"+1 617 523 7070",
    "sg:postcode":"02445",
    "sg:province":"MA",
    "sg:tags":[
        "attorney"
    ],
    "wof:name":"Joseph S Dow",
    "wof:placetype":"venue"
},
  "geometry": {"coordinates":[-71.136743,42.309583],"type":"Point"}
}