{
  "type": "Feature",
  "properties": {
    "iso:country":"US",
    "sg:address":"390 West St",
    "sg:city":"Mansfield",
    "sg:classifiers":[
        {
            "category":"Wholesale",
            "subcategory":"Groceries",
            "type":"Manufacturing & Wholesale Goods"
        }
    ],
    "sg:phone":"+1 508 339 4845",
    "sg:postcode":"02048",
    "sg:province":"MA",
    "sg:tags":[
        "baker"
    ],
    "wof:name":"Honey Dew Donuts",
    "wof:placetype":"venue"
},
  "geometry": {"coordinates":[-71.23272900000001,42.026407],"type":"Point"}
}