{
  "type": "Feature",
  "properties": {
    "addr:full": "318 Southbridge Rd Charlton MA 01507",
    "addr:housenumber": "318",
    "addr:postcode": "01507",
    "addr:street": "Southbridge Rd",
    "iso:country": "US",
    "sg:address": "318 Southbridge Rd",
    "sg:city": "Charlton",
    "sg:classifiers": [
      {
        "category": "Home \u0026 Garden",
        "subcategory": "Furniture",
        "type": "Retail Goods"
      }
    ],
    "sg:phone": "+1 508 764 6012",
    "sg:postcode": "01507",
    "sg:province": "MA",
    "wof:name": "Debron Furniture",
    "wof:placetype": "venue"
  },
  "geometry": {"coordinates":[-72.014743,42.107357],"type":"Point"}
}
