{
  "type": "Feature",
  "properties": {
    "addr:full": "167 Sidney St Cambridge MA 02139",
    "addr:housenumber": "167",
    "addr:postcode": "02139",
    "addr:street": "Sidney St",
    "iso:country": "US",
    "sg:address": "167 Sidney St",
    "sg:city": "Cambridge",
    "sg:classifiers": [
      {
        "category": "Shopping",
        "subcategory": "Pharmacy",
        "type": "Retail Goods"
      }
    ],
    "sg:phone": "+1 617 225 0078",
    "sg:postcode": "02139",
    "sg:province": "MA",
    "sg:tags": [
      "drugstore"
    ],
    "wof:name": "Ideara Pharm",
    "wof:placetype": "venue"
  },
  "geometry": {"coordinates":[-71.104622,42.358779],"type":"Point"}
}
