{
  "type": "Feature",
  "properties": {
    "iso:country":"US",
    "sg:address":"39 Kilby St",
    "sg:city":"Woburn",
    "sg:classifiers":[
        {
            "category":"Professional",
            "subcategory":"Business Services",
            "type":"Services"
        }
    ],
    "sg:phone":"+1 781 368 7459",
    "sg:postcode":"01801",
    "sg:province":"MA",
    "sg:tags":[
        "food",
        "delivery"
    ],
    "sg:website":"www.clickandmeal.com",
    "wof:name":"Click & Meal",
    "wof:placetype":"venue"
},
  "geometry": {"coordinates":[-71.132969,42.488462],"type":"Point"}
}