{
  "type": "Feature",
  "properties": {
    "addr:full":"12 Clarendon Ave Somerville MA 02144",
    "addr:housenumber":"12",
    "addr:postcode":"02144",
    "addr:street":"Clarendon Ave",
    "iso:country":"US",
    "sg:address":"12 Clarendon Ave",
    "sg:city":"Somerville",
    "sg:classifiers":[
        {
            "category":"Shopping",
            "subcategory":"Computers & Home Electronics",
            "type":"Retail Goods"
        }
    ],
    "sg:phone":"+1 617 718 0173",
    "sg:postcode":"02144",
    "sg:province":"MA",
    "sg:tags":[
        "software"
    ],
    "wof:name":"Nombas Inc",
    "wof:placetype":"venue"
},
  "geometry": {"coordinates":[-71.128485,42.402746],"type":"Point"}
}