{
  "type": "Feature",
  "properties": {
    "iso:country":"US",
    "sg:address":"17 Alexander Rd",
    "sg:city":"Hopkinton",
    "sg:classifiers":[
        {
            "category":"Health Services",
            "subcategory":"Clinic",
            "type":"Services"
        }
    ],
    "sg:phone":"+1 508 435 9142",
    "sg:postcode":"01748",
    "sg:province":"MA",
    "sg:tags":[
        "welfare"
    ],
    "wof:name":"Biotricity Medical Inc",
    "wof:placetype":"venue"
},
  "geometry": {"coordinates":[-71.527069,42.205261],"type":"Point"}
}