{
  "type": "Feature",
  "properties": {
    "iso:country":"US",
    "sg:address":"859 Massachusetts Ave",
    "sg:city":"Cambridge",
    "sg:classifiers":[
        {
            "category":"Professional",
            "subcategory":"Accounting & Tax Preparation",
            "type":"Services"
        }
    ],
    "sg:phone":"+1 617 871 6602",
    "sg:postcode":"02139",
    "sg:province":"MA",
    "sg:tags":[
        "accountant"
    ],
    "sg:website":"www.cpadp.com",
    "wof:name":"David Prothero, CPA",
    "wof:placetype":"venue"
},
  "geometry": {"coordinates":[-71.10719,42.36755],"type":"Point"}
}