{
  "type": "Feature",
  "properties": {
    "iso:country":"US",
    "sg:address":"2040 Boston Rd",
    "sg:city":"Wilbraham",
    "sg:classifiers":[
        {
            "category":"Health Services",
            "subcategory":"Hospital",
            "type":"Services"
        }
    ],
    "sg:phone":"+1 413 543 1132",
    "sg:postcode":"01095",
    "sg:province":"MA",
    "sg:tags":[
        "treatment",
        "psychiatric",
        "facility"
    ],
    "wof:name":"Psycmatrix For Child",
    "wof:placetype":"venue"
},
  "geometry": {"coordinates":[-72.46292099999999,42.15167],"type":"Point"}
}