{
  "type": "Feature",
  "properties": {
    "iso:country":"US",
    "sg:address":"2449 Main St",
    "sg:city":"Brewster",
    "sg:classifiers":[
        {
            "category":"Restaurant",
            "type":"Food & Drink"
        }
    ],
    "sg:phone":"+1 508 896 3640",
    "sg:postcode":"02631",
    "sg:province":"MA",
    "sg:tags":[
        "lounge",
        "american",
        "cocktail"
    ],
    "sg:website":"http://www.chillingsworth.com",
    "wof:name":"Chillingsworth",
    "wof:placetype":"venue"
},
  "geometry": {"coordinates":[-70.065764,41.765387],"type":"Point"}
}