{
  "type": "Feature",
  "properties": {
    "addr:full": "340 May St Worcester MA 01602",
    "addr:housenumber": "340",
    "addr:postcode": "01602",
    "addr:street": "May St",
    "iso:country": "US",
    "ovtr:label": "Tatnuck Park at Worcester, 340 May St Worcester MA US",
    "ovtr:similarity": 2.8480288982391357,
    "sg:address": "340 May St",
    "sg:city": "Worcester",
    "sg:classifiers": [
      {
        "category": "Social Services",
        "type": "Services"
      }
    ],
    "sg:phone": "+1 508 755 7277",
    "sg:postcode": "01602",
    "sg:province": "MA",
    "sg:tags": [
      "senior",
      "citizen"
    ],
    "sg:website": "www.benchmarkquality.com",
    "wof:name": "Tatnuck Park At Worcester",
    "wof:placetype": "venue"
  },
  "geometry": {"coordinates":[-71.841675,42.27072],"type":"Point"}
}
