{
  "type": "Feature",
  "properties": {
    "addr:full": "23 Alton Dr Dudley MA 01571",
    "addr:housenumber": "23",
    "addr:postcode": "01571",
    "addr:street": "Alton Dr",
    "iso:country": "US",
    "sg:address": "23 Alton Dr",
    "sg:city": "Dudley",
    "sg:classifiers": [
      {
        "category": "Building \u0026 Trades",
        "subcategory": "Construction",
        "type": "Services"
      }
    ],
    "sg:phone": "+1 508 943 6319",
    "sg:postcode": "01571",
    "sg:province": "MA",
    "sg:tags": [
      "painter"
    ],
    "wof:name": "Dave's Painting",
    "wof:placetype": "venue"
  },
  "geometry": {"coordinates":[-71.910621,42.04455],"type":"Point"}
}
