{
  "type": "Feature",
  "properties": {
    "addr:full":"22 Briarwood Dr Westford MA 01886",
    "addr:housenumber":"22",
    "addr:postcode":"01886",
    "addr:street":"Briarwood Dr",
    "iso:country":"US",
    "sg:address":"22 Briarwood Dr",
    "sg:city":"Westford",
    "sg:classifiers":[
        {
            "category":"Professional",
            "subcategory":"Detective & Security Services",
            "type":"Services"
        }
    ],
    "sg:phone":"+1 978 392 9471",
    "sg:postcode":"01886",
    "sg:province":"MA",
    "sg:tags":[
        "control",
        "monitoring",
        "system"
    ],
    "wof:name":"Nightwatch Protection Inc",
    "wof:placetype":"venue"
},
  "geometry": {"coordinates":[-71.43171700000001,42.629613],"type":"Point"}
}