{
  "type": "Feature",
  "properties": {
    "addr:full": "20 Lantern Ln Arlington MA 02474",
    "addr:housenumber": "20",
    "addr:postcode": "02474",
    "addr:street": "Lantern Ln",
    "iso:country": "US",
    "sg:address": "20 Lantern Ln",
    "sg:city": "Arlington",
    "sg:classifiers": [
      {
        "category": "Building \u0026 Trades",
        "subcategory": "Locksmith",
        "type": "Services"
      }
    ],
    "sg:phone": "+1 617 714 1096",
    "sg:postcode": "02474",
    "sg:province": "MA",
    "sg:tags": [
      "key"
    ],
    "wof:name": "Locksmith Factory",
    "wof:placetype": "venue"
  },
  "geometry": {"coordinates":[-71.166432,42.435082],"type":"Point"}
}
