{
  "type": "Feature",
  "properties": {
    "addr:full": "836 Western Ave Lynn MA 01905",
    "addr:housenumber": "836",
    "addr:postcode": "01905",
    "addr:street": "Western Ave",
    "iso:country": "US",
    "sg:address": "836 Western Ave",
    "sg:city": "Lynn",
    "sg:classifiers": [
      {
        "category": "Personal",
        "subcategory": "Barber",
        "type": "Services"
      }
    ],
    "sg:phone": "+1 781 595 9640",
    "sg:postcode": "01905",
    "sg:province": "MA",
    "wof:name": "Avenue Barber Stylist",
    "wof:placetype": "venue"
  },
  "geometry": {"coordinates":[-70.970216,42.458464],"type":"Point"}
}
