{
  "type": "Feature",
  "properties": {
    "iso:country":"US",
    "sg:address":"836 Western Ave",
    "sg:city":"Lynn",
    "sg:classifiers":[
        {
            "category":"Personal",
            "subcategory":"Barber",
            "type":"Services"
        }
    ],
    "sg:phone":"+1 781 595 9640",
    "sg:postcode":"01905",
    "sg:province":"MA",
    "wof:name":"Avenue Barber Stylist",
    "wof:placetype":"venue"
},
  "geometry": {"coordinates":[-70.97021599999999,42.458464],"type":"Point"}
}