{
  "type": "Feature",
  "properties": {
    "addr:full":"26 Howland St Plymouth MA 02360",
    "addr:housenumber":"26",
    "addr:postcode":"02360",
    "addr:street":"Howland St",
    "iso:country":"US",
    "sg:address":"26 Howland St",
    "sg:city":"Plymouth",
    "sg:classifiers":[
        {
            "category":"Professional",
            "subcategory":"Art Services",
            "type":"Services"
        }
    ],
    "sg:phone":"+1 508 732 9903",
    "sg:postcode":"02360",
    "sg:province":"MA",
    "sg:tags":[
        "graphic",
        "commercial",
        "designer",
        "artist"
    ],
    "wof:name":"Shields Design",
    "wof:placetype":"venue"
},
  "geometry": {"coordinates":[-70.666128,41.959034],"type":"Point"}
}