{
  "type": "Feature",
  "properties": {
    "iso:country":"US",
    "sg:address":"62 Main St",
    "sg:city":"Upton",
    "sg:classifiers":[
        {
            "category":"Health Services",
            "subcategory":"Chiropractor",
            "type":"Services"
        }
    ],
    "sg:phone":"+1 508 529 2700",
    "sg:postcode":"01568",
    "sg:province":"MA",
    "wof:name":"Upton Chiropractic",
    "wof:placetype":"venue"
},
  "geometry": {"coordinates":[-71.610882,42.169719],"type":"Point"}
}