{
  "type": "Feature",
  "properties": {
    "iso:country":"US",
    "sg:address":"9 Peoples Way",
    "sg:city":"Fairhaven",
    "sg:classifiers":[
        {
            "category":"Autos & Motor Vehicles",
            "subcategory":"Auto Supplies",
            "type":"Retail Goods"
        }
    ],
    "sg:phone":"+1 508 992 8665",
    "sg:postcode":"02719",
    "sg:province":"MA",
    "sg:tags":[
        "tire"
    ],
    "wof:name":"Benny's",
    "wof:placetype":"venue"
},
  "geometry": {"coordinates":[-70.891822,41.643315],"type":"Point"}
}