{
  "type": "Feature",
  "properties": {
    "iso:country":"US",
    "sg:address":"22 Fales Rd",
    "sg:city":"Plainville",
    "sg:classifiers":[
        {
            "category":"Building & Trades",
            "subcategory":"Landscaping Services",
            "type":"Services"
        }
    ],
    "sg:phone":"+1 508 643 1087",
    "sg:postcode":"02762",
    "sg:province":"MA",
    "sg:tags":[
        "landscape",
        "contractor"
    ],
    "wof:name":"Mustard Seed Landscaping Co",
    "wof:placetype":"venue"
},
  "geometry": {"coordinates":[-71.377599,41.98957],"type":"Point"}
}