{
  "type": "Feature",
  "properties": {
    "iso:country":"US",
    "sg:address":"12 Overbrook Ter",
    "sg:city":"Natick",
    "sg:classifiers":[
        {
            "category":"Retail",
            "subcategory":"Portrait Studio",
            "type":"Services"
        }
    ],
    "sg:phone":"+1   ",
    "sg:postcode":"01760",
    "sg:province":"MA",
    "sg:tags":[
        "photo"
    ],
    "wof:name":"Unforgettable Photography",
    "wof:placetype":"venue"
},
  "geometry": {"coordinates":[-71.327674,42.305761],"type":"Point"}
}