{
  "type": "Feature",
  "properties": {
    "addr:full":"312 Millbury Ave Millbury MA 01527",
    "addr:housenumber":"312",
    "addr:postcode":"01527",
    "addr:street":"Millbury Ave",
    "iso:country":"US",
    "sg:address":"312 Millbury Ave",
    "sg:city":"Millbury",
    "sg:classifiers":[
        {
            "category":"Health Services",
            "subcategory":"Nursing And Care Facility",
            "type":"Services"
        }
    ],
    "sg:phone":"+1 508 793 0088",
    "sg:postcode":"01527",
    "sg:province":"MA",
    "sg:tags":[
        "home",
        "convalescent"
    ],
    "wof:name":"Millbury Heathcare Ctr",
    "wof:placetype":"venue"
},
  "geometry": {"coordinates":[-71.76003799999999,42.222547],"type":"Point"}
}