{
  "type": "Feature",
  "properties": {
    "addr:full": "352 Main St Ste 352 Clinton MA 01510",
    "addr:housenumber": "352",
    "addr:postcode": "01510",
    "addr:street": "Main St Ste 352",
    "iso:country": "US",
    "sg:address": "352 Main St Ste 352",
    "sg:city": "Clinton",
    "sg:classifiers": [
      {
        "category": "Personal",
        "subcategory": "Beauty Salon",
        "type": "Services"
      }
    ],
    "sg:phone": "+1 978 365 9200",
    "sg:postcode": "01510",
    "sg:province": "MA",
    "wof:name": "Shear Madness",
    "wof:placetype": "venue"
  },
  "geometry": {"coordinates":[-71.691582,42.413647],"type":"Point"}
}
