{
  "type": "Feature",
  "properties": {
    "iso:country":"US",
    "sg:address":"145 Tremont St Ste 202",
    "sg:city":"Boston",
    "sg:classifiers":[
        {
            "category":"Insurance",
            "subcategory":"Health Insurance",
            "type":"Services"
        }
    ],
    "sg:phone":"+1 617 482 4471",
    "sg:postcode":"02111",
    "sg:province":"MA",
    "sg:tags":[
        "employee",
        "benefit"
    ],
    "sg:website":"http://www.seiu105.org",
    "wof:name":"Service Employees Intl Un Ea",
    "wof:placetype":"venue"
},
  "geometry": {"coordinates":[-71.063283,42.355184],"type":"Point"}
}