{
  "type": "Feature",
  "properties": {
    "iso:country":"US",
    "sg:address":"37 Dexter Ave",
    "sg:city":"Sandwich",
    "sg:classifiers":[
        {
            "category":"Food & Beverages",
            "subcategory":"Candy",
            "type":"Retail Goods"
        }
    ],
    "sg:phone":"+1 508 280 9012",
    "sg:postcode":"02563",
    "sg:province":"MA",
    "sg:tags":[
        "confectionery"
    ],
    "wof:name":"Candy's Creations",
    "wof:placetype":"venue"
},
  "geometry": {"coordinates":[-70.496651,41.767639],"type":"Point"}
}