{
  "type": "Feature",
  "properties": {
    "addr:full": "37 Dexter Ave Sandwich MA 02563",
    "addr:housenumber": "37",
    "addr:postcode": "02563",
    "addr:street": "Dexter Ave",
    "iso:country": "US",
    "sg:address": "37 Dexter Ave",
    "sg:city": "Sandwich",
    "sg:classifiers": [
      {
        "category": "Food \u0026 Beverages",
        "subcategory": "Candy",
        "type": "Retail Goods"
      }
    ],
    "sg:phone": "+1 508 280 9012",
    "sg:postcode": "02563",
    "sg:province": "MA",
    "sg:tags": [
      "confectionery"
    ],
    "wof:name": "Candy's Creations",
    "wof:placetype": "venue"
  },
  "geometry": {"coordinates":[-70.496651,41.767639],"type":"Point"}
}
