{
  "type": "Feature",
  "properties": {
    "addr:full": "33 Bridge St Lakeville MA 02347",
    "addr:housenumber": "33",
    "addr:postcode": "02347",
    "addr:street": "Bridge St",
    "iso:country": "US",
    "sg:address": "33 Bridge St",
    "sg:city": "Lakeville",
    "sg:classifiers": [
      {
        "category": "Professional",
        "subcategory": "Management \u0026 Consulting",
        "type": "Services"
      }
    ],
    "sg:phone": "+1 508 947 7807",
    "sg:postcode": "02347",
    "sg:province": "MA",
    "sg:tags": [
      "consultant"
    ],
    "wof:name": "Standish Enterprise",
    "wof:placetype": "venue"
  },
  "geometry": {"coordinates":[-70.91803,41.870869],"type":"Point"}
}
