{
  "type": "Feature",
  "properties": {
    "addr:full":"82 Boardman St Norfolk MA 02056",
    "addr:housenumber":"82",
    "addr:postcode":"02056",
    "addr:street":"Boardman St",
    "iso:country":"US",
    "sg:address":"82 Boardman St",
    "sg:city":"Norfolk",
    "sg:classifiers":[
        {
            "category":"Wholesale",
            "subcategory":"Electrical",
            "type":"Manufacturing & Wholesale Goods"
        }
    ],
    "sg:phone":"+1 508 528 2239",
    "sg:postcode":"02056",
    "sg:province":"MA",
    "sg:tags":[
        "communication",
        "radio",
        "system"
    ],
    "wof:name":"Capone Communications",
    "wof:placetype":"venue"
},
  "geometry": {"coordinates":[-71.323251,42.125558],"type":"Point"}
}