{
  "type": "Feature",
  "properties": {
    "addr:full":"492 High St Medford MA 02155",
    "addr:housenumber":"492",
    "addr:postcode":"02155",
    "addr:street":"High St",
    "iso:country":"US",
    "sg:address":"492 High St",
    "sg:city":"Medford",
    "sg:classifiers":[
        {
            "category":"Bus Charters",
            "type":"Transportation"
        }
    ],
    "sg:phone":"+1 781 483 3339",
    "sg:postcode":"02155",
    "sg:province":"MA",
    "sg:tags":[
        "rental"
    ],
    "sg:website":"www.njltransportation.com",
    "wof:name":"NJL Transportation",
    "wof:placetype":"venue"
},
  "geometry": {"coordinates":[-71.13467,42.421488],"type":"Point"}
}