{
  "type": "Feature",
  "properties": {
    "addr:full": "295 Devonshire Street Boston MA 02110",
    "addr:housenumber": "295",
    "addr:postcode": "02110",
    "addr:street": "Devonshire Street",
    "iso:country": "US",
    "sg:address": "295 Devonshire Street",
    "sg:city": "Boston",
    "sg:classifiers": [
      {
        "category": "Professional",
        "subcategory": "Lawyer \u0026 Legal Services",
        "type": "Services"
      }
    ],
    "sg:phone": "+1 617 423 2450",
    "sg:postcode": "02110",
    "sg:province": "MA",
    "wof:name": "Jordan Harris Atty",
    "wof:placetype": "venue"
  },
  "geometry": {"coordinates":[-71.058057,42.353755],"type":"Point"}
}
