{
  "type": "Feature",
  "properties": {
    "iso:country":"US",
    "sg:address":"295 Devonshire Street",
    "sg:city":"Boston",
    "sg:classifiers":[
        {
            "category":"Professional",
            "subcategory":"Lawyer & Legal Services",
            "type":"Services"
        }
    ],
    "sg:phone":"+1 617 423 2450",
    "sg:postcode":"02110",
    "sg:province":"MA",
    "wof:name":"Jordan Harris Atty",
    "wof:placetype":"venue"
},
  "geometry": {"coordinates":[-71.05805700000001,42.353755],"type":"Point"}
}