{
  "type": "Feature",
  "properties": {
    "addr:full": "69 Lincoln St Gardner MA 01440",
    "addr:housenumber": "69",
    "addr:postcode": "01440",
    "addr:street": "Lincoln St",
    "iso:country": "US",
    "sg:address": "69 Lincoln St",
    "sg:city": "Gardner",
    "sg:classifiers": [
      {
        "category": "Building \u0026 Trades",
        "subcategory": "Construction",
        "type": "Services"
      }
    ],
    "sg:phone": "+1 978 630 3442",
    "sg:postcode": "01440",
    "sg:province": "MA",
    "sg:tags": [
      "general",
      "contractor"
    ],
    "wof:name": "A Francis Contracting Inc",
    "wof:placetype": "venue"
  },
  "geometry": {"coordinates":[-71.990404,42.576876],"type":"Point"}
}
