{
  "type": "Feature",
  "properties": {
    "addr:full":"5 New Whitney St Boston MA 02115",
    "addr:housenumber":"5",
    "addr:postcode":"02115",
    "addr:street":"New Whitney St",
    "iso:country":"US",
    "sg:address":"5 New Whitney St",
    "sg:city":"Boston",
    "sg:classifiers":[
        {
            "category":"Social Services",
            "type":"Services"
        }
    ],
    "sg:phone":"+1 617 277 8033",
    "sg:postcode":"02115",
    "sg:province":"MA",
    "sg:tags":[
        "product",
        "developmentally",
        "disabled",
        "need",
        "special"
    ],
    "sg:website":"http://www.darefamilyservices.com",
    "wof:name":"Dare Family Services, Inc",
    "wof:placetype":"venue"
},
  "geometry": {"coordinates":[-71.10893299999999,42.334115],"type":"Point"}
}