{
  "type": "Feature",
  "properties": {
    "addr:full":"377 Washington St Brighton MA 02135",
    "addr:housenumber":"377",
    "addr:postcode":"02135",
    "addr:street":"Washington St",
    "iso:country":"US",
    "sg:address":"377 Washington St",
    "sg:city":"Brighton",
    "sg:classifiers":[
        {
            "category":"Restaurant",
            "type":"Food & Drink"
        }
    ],
    "sg:phone":"+1 617 787 0293",
    "sg:postcode":"02135",
    "sg:province":"MA",
    "sg:tags":[
        "chinese"
    ],
    "sg:website":"HappyGardenChinese.com",
    "wof:name":"Happy Garden",
    "wof:placetype":"venue"
},
  "geometry": {"coordinates":[-71.154281,42.349139],"type":"Point"}
}