{
  "type": "Feature",
  "properties": {
    "addr:full": "3 Belcher St Plainville MA 02762",
    "addr:housenumber": "3",
    "addr:postcode": "02762",
    "addr:street": "Belcher St",
    "iso:country": "US",
    "sg:address": "3 Belcher St",
    "sg:city": "Plainville",
    "sg:classifiers": [
      {
        "category": "Manufacturing",
        "subcategory": "Glass \u0026 Minerals",
        "type": "Manufacturing \u0026 Wholesale Goods"
      }
    ],
    "sg:phone": "+1 508 695 3252",
    "sg:postcode": "02762",
    "sg:province": "MA",
    "sg:tags": [
      "stone",
      "cut",
      "product"
    ],
    "sg:website": "www.lorussocorp.com",
    "wof:name": "Lorusso Corp",
    "wof:placetype": "venue"
  },
  "geometry": {"coordinates":[-71.300103,42.039297],"type":"Point"}
}
