{
  "type": "Feature",
  "properties": {
    "iso:country":"US",
    "sg:address":"3 Belcher St",
    "sg:city":"Plainville",
    "sg:classifiers":[
        {
            "category":"Manufacturing",
            "subcategory":"Glass & Minerals",
            "type":"Manufacturing & Wholesale Goods"
        }
    ],
    "sg:phone":"+1 508 695 3252",
    "sg:postcode":"02762",
    "sg:province":"MA",
    "sg:tags":[
        "stone",
        "cut",
        "product"
    ],
    "sg:website":"www.lorussocorp.com",
    "wof:name":"Lorusso Corp",
    "wof:placetype":"venue"
},
  "geometry": {"coordinates":[-71.30010299999999,42.039297],"type":"Point"}
}