{
  "type": "Feature",
  "properties": {
    "addr:full": "36 School St Leominster MA 01453",
    "addr:housenumber": "36",
    "addr:postcode": "01453",
    "addr:street": "School St",
    "iso:country": "US",
    "sg:address": "36 School St",
    "sg:city": "Leominster",
    "sg:classifiers": [
      {
        "category": "Professional",
        "subcategory": "Lawyer \u0026 Legal Services",
        "type": "Services"
      }
    ],
    "sg:phone": "+1 978 840 1020",
    "sg:postcode": "01453",
    "sg:province": "MA",
    "sg:tags": [
      "arbitration",
      "attorney",
      "mediation"
    ],
    "sg:website": "http://www.depasqualelaw.com/",
    "wof:name": "Carolyn G De Pasquale",
    "wof:placetype": "venue"
  },
  "geometry": {"coordinates":[-71.762075,42.527254],"type":"Point"}
}
