{
  "type": "Feature",
  "properties": {
    "addr:full": "34 Gold St Shrewsbury MA 01545",
    "addr:housenumber": "34",
    "addr:postcode": "01545",
    "addr:street": "Gold St",
    "iso:country": "US",
    "sg:address": "34 Gold St",
    "sg:city": "Shrewsbury",
    "sg:classifiers": [
      {
        "category": "Organizations",
        "subcategory": "Religious Organization",
        "type": "Services"
      }
    ],
    "sg:phone": "+1 508 845 0088",
    "sg:postcode": "01545",
    "sg:province": "MA",
    "sg:tags": [
      "church"
    ],
    "wof:name": "St Nicholas Orthodox Church",
    "wof:placetype": "venue"
  },
  "geometry": {"coordinates":[-71.709645,42.267949],"type":"Point"}
}
