{
  "type": "Feature",
  "properties": {
    "iso:country":"US",
    "sg:address":"34 Gold St",
    "sg:city":"Shrewsbury",
    "sg:classifiers":[
        {
            "category":"Organizations",
            "subcategory":"Religious Organization",
            "type":"Services"
        }
    ],
    "sg:phone":"+1 508 845 0088",
    "sg:postcode":"01545",
    "sg:province":"MA",
    "sg:tags":[
        "church"
    ],
    "wof:name":"St Nicholas Orthodox Church",
    "wof:placetype":"venue"
},
  "geometry": {"coordinates":[-71.70964499999999,42.267949],"type":"Point"}
}