{
  "type": "Feature",
  "properties": {
    "iso:country":"US",
    "sg:address":"1 Wesley St",
    "sg:city":"Malden",
    "sg:classifiers":[
        {
            "category":"Freight",
            "type":"Transportation"
        }
    ],
    "sg:phone":"+1 781 324 4858",
    "sg:postcode":"02150",
    "sg:province":"MA",
    "sg:tags":[
        "commercial",
        "storage"
    ],
    "wof:name":"Wayside Compartments Inc",
    "wof:placetype":"venue"
},
  "geometry": {"coordinates":[-71.029741,42.405673],"type":"Point"}
}