{
  "type": "Feature",
  "properties": {
    "addr:full": "74 Woodside Ave Winthrop MA 02152",
    "addr:housenumber": "74",
    "addr:postcode": "02152",
    "addr:street": "Woodside Ave",
    "iso:country": "US",
    "sg:address": "74 Woodside Ave",
    "sg:city": "Winthrop",
    "sg:classifiers": [
      {
        "category": "Real Estate",
        "subcategory": "Real Estate Agent",
        "type": "Services"
      }
    ],
    "sg:phone": "+1 617 846 7773",
    "sg:postcode": "02152",
    "sg:province": "MA",
    "wof:name": "Re Max All Stars",
    "wof:placetype": "venue"
  },
  "geometry": {"coordinates":[-70.98572,42.372789],"type":"Point"}
}
