{
  "type": "Feature",
  "properties": {
    "iso:country":"US",
    "sg:address":"7 Commerce Dr",
    "sg:city":"Orleans",
    "sg:classifiers":[
        {
            "category":"Recreation",
            "subcategory":"Marina",
            "type":"Entertainment"
        }
    ],
    "sg:phone":"+1 508 240 0058",
    "sg:postcode":"02653",
    "sg:province":"MA",
    "sg:tags":[
        "repairing",
        "boat"
    ],
    "sg:website":"www.marinerestoration.com",
    "wof:name":"Marine Restoration & Salvage",
    "wof:placetype":"venue"
},
  "geometry": {"coordinates":[-69.996877,41.776671],"type":"Point"}
}