{
  "type": "Feature",
  "properties": {
    "addr:full": "7 Commerce Dr Orleans MA 02653",
    "addr:housenumber": "7",
    "addr:postcode": "02653",
    "addr:street": "Commerce Dr",
    "iso:country": "US",
    "sg:address": "7 Commerce Dr",
    "sg:city": "Orleans",
    "sg:classifiers": [
      {
        "category": "Recreation",
        "subcategory": "Marina",
        "type": "Entertainment"
      }
    ],
    "sg:phone": "+1 508 240 0058",
    "sg:postcode": "02653",
    "sg:province": "MA",
    "sg:tags": [
      "repairing",
      "boat"
    ],
    "sg:website": "www.marinerestoration.com",
    "wof:name": "Marine Restoration \u0026 Salvage",
    "wof:placetype": "venue"
  },
  "geometry": {"coordinates":[-69.996877,41.776671],"type":"Point"}
}
