{
  "type": "Feature",
  "properties": {
    "addr:full": "242 Northern Ave Boston MA 02210",
    "addr:housenumber": "242",
    "addr:postcode": "02210",
    "addr:street": "Northern Ave",
    "iso:country": "US",
    "sg:address": "242 Northern Ave",
    "sg:city": "Boston",
    "sg:classifiers": [
      {
        "category": "Restaurant",
        "type": "Food \u0026 Drink"
      },
      {
        "category": "Food \u0026 Beverages",
        "subcategory": "Groceries \u0026 Convenience Stores",
        "type": "Retail Goods"
      }
    ],
    "sg:phone": "+1 617 423 1000",
    "sg:postcode": "02210",
    "sg:province": "MA",
    "sg:tags": [
      "shop",
      "seafood",
      "sandwich",
      "health",
      "american"
    ],
    "wof:name": "Jimmy's Harborside Restaurant",
    "wof:placetype": "venue"
  },
  "geometry": {"coordinates":[-71.03876,42.348787],"type":"Point"}
}
