{
  "type": "Feature",
  "properties": {
    "iso:country":"US",
    "sg:address":"12 Kendall Ave",
    "sg:city":"Framingham",
    "sg:classifiers":[
        {
            "category":"Personal",
            "type":"Services"
        },
        {
            "category":"Building & Trades",
            "subcategory":"Cleaning & Sanitation",
            "type":"Services"
        }
    ],
    "sg:phone":"+1 617 449 9329",
    "sg:postcode":"01702",
    "sg:province":"MA",
    "sg:tags":[
        "house",
        "butlers'",
        "maids'"
    ],
    "wof:name":"MS Cleaning",
    "wof:placetype":"venue"
},
  "geometry": {"coordinates":[-71.397583,42.272236],"type":"Point"}
}