{
  "type": "Feature",
  "properties": {
    "iso:country":"US",
    "sg:address":"75 Getchell St",
    "sg:city":"Randolph",
    "sg:classifiers":[
        {
            "category":"Manufacturing",
            "subcategory":"Metals",
            "type":"Manufacturing & Wholesale Goods"
        }
    ],
    "sg:phone":"+1 781 961 2000",
    "sg:postcode":"02368",
    "sg:province":"MA",
    "sg:tags":[
        "engraver"
    ],
    "wof:name":"ID Graphics Group",
    "wof:placetype":"venue"
},
  "geometry": {"coordinates":[-71.070069,42.165894],"type":"Point"}
}