{
  "type": "Feature",
  "properties": {
    "addr:full":"51 Eastern Point Rd Gloucester MA 01930",
    "addr:housenumber":"51",
    "addr:postcode":"01930",
    "addr:street":"Eastern Point Rd",
    "iso:country":"US",
    "sg:address":"51 Eastern Point Rd",
    "sg:city":"Gloucester",
    "sg:classifiers":[
        {
            "category":"Professional",
            "subcategory":"Business Services",
            "type":"Services"
        }
    ],
    "sg:phone":"+1   ",
    "sg:postcode":"01930",
    "sg:province":"MA",
    "wof:name":"Gofer Time Services",
    "wof:placetype":"venue"
},
  "geometry": {"coordinates":[-70.65516100000001,42.600707],"type":"Point"}
}