{
  "type": "Feature",
  "properties": {
    "addr:full": "8 Prospect St Greenfield MA 01301",
    "addr:housenumber": "8",
    "addr:postcode": "01301",
    "addr:street": "Prospect St",
    "iso:country": "US",
    "sg:address": "8 Prospect St",
    "sg:city": "Greenfield",
    "sg:classifiers": [
      {
        "category": "Government",
        "subcategory": "Police Station",
        "type": "Public Place"
      }
    ],
    "sg:phone": "+1 413 773 1846",
    "sg:postcode": "01301",
    "sg:province": "MA",
    "sg:tags": [
      "sheriff"
    ],
    "wof:name": "Franklin County Sheriffs Comm",
    "wof:placetype": "venue"
  },
  "geometry": {"coordinates":[-72.598687,42.585306],"type":"Point"}
}
