{
  "type": "Feature",
  "properties": {
    "addr:full":"23 E Hoyle St Norwood MA 02062",
    "addr:housenumber":"23",
    "addr:postcode":"02062",
    "addr:street":"E Hoyle St",
    "iso:country":"US",
    "sg:address":"23 E Hoyle St",
    "sg:city":"Norwood",
    "sg:classifiers":[
        {
            "category":"Retail",
            "subcategory":"Auto Repair",
            "type":"Services"
        }
    ],
    "sg:phone":"+1 781 762 6624",
    "sg:postcode":"02062",
    "sg:province":"MA",
    "sg:tags":[
        "repairing",
        "automobile"
    ],
    "wof:name":"Auto Doctor",
    "wof:placetype":"venue"
},
  "geometry": {"coordinates":[-71.201024,42.187712],"type":"Point"}
}