{
  "type": "Feature",
  "properties": {
    "iso:country":"US",
    "sg:address":"2 N Main St",
    "sg:city":"Sherborn",
    "sg:classifiers":[
        {
            "category":"Education",
            "subcategory":"School",
            "type":"Public Place"
        }
    ],
    "sg:phone":"+1 508 655 2143",
    "sg:postcode":"01770",
    "sg:province":"MA",
    "wof:name":"Life Experience School",
    "wof:placetype":"venue"
},
  "geometry": {"coordinates":[-71.369963,42.243941],"type":"Point"}
}