{
  "type": "Feature",
  "properties": {
    "addr:full": "147 Plymouth Ave Fall River MA 02721",
    "addr:housenumber": "147",
    "addr:postcode": "02721",
    "addr:street": "Plymouth Ave",
    "iso:country": "US",
    "sg:address": "147 Plymouth Ave",
    "sg:city": "Fall River",
    "sg:classifiers": [
      {
        "category": "Wholesale",
        "subcategory": "Home Furnishings",
        "type": "Manufacturing \u0026 Wholesale Goods"
      }
    ],
    "sg:phone": "+1 508 678 5550",
    "sg:postcode": "02721",
    "sg:province": "MA",
    "sg:tags": [
      "blanket"
    ],
    "wof:name": "New England Fleece Co",
    "wof:placetype": "venue"
  },
  "geometry": {"coordinates":[-71.148561,41.697489],"type":"Point"}
}
