{
  "type": "Feature",
  "properties": {
    "iso:country":"US",
    "sg:address":"4 Tarbell St",
    "sg:city":"Pepperell",
    "sg:classifiers":[
        {
            "category":"Building & Trades",
            "subcategory":"Plumbing",
            "type":"Services"
        }
    ],
    "sg:phone":"+1 978 433 8713",
    "sg:postcode":"01463",
    "sg:province":"MA",
    "sg:tags":[
        "heating",
        "contractor"
    ],
    "wof:name":"Buckley Plumbing & Heating",
    "wof:placetype":"venue"
},
  "geometry": {"coordinates":[-71.569975,42.66679],"type":"Point"}
}