{
  "type": "Feature",
  "properties": {
    "addr:full": "9 Peacevale Road Dorchester Center MA 02124",
    "addr:housenumber": "9",
    "addr:postcode": "02124",
    "addr:street": "Peacevale Road",
    "iso:country": "US",
    "sg:address": "9 Peacevale Road",
    "sg:city": "Dorchester Center",
    "sg:classifiers": [
      {
        "category": "Education",
        "subcategory": "School",
        "type": "Public Place"
      }
    ],
    "sg:phone": "+1 617 282 6330",
    "sg:postcode": "02124",
    "sg:province": "MA",
    "sg:tags": [
      "high",
      "middle",
      "elementary"
    ],
    "sg:website": "www.dorchesterhighschool.com",
    "wof:name": "Dorchester High School Clinic",
    "wof:placetype": "venue"
  },
  "geometry": {"coordinates":[-71.076554,42.288012],"type":"Point"}
}
