{
  "type": "Feature",
  "properties": {
    "addr:full":"6 Milford St Medway MA 02053",
    "addr:housenumber":"6",
    "addr:postcode":"02053",
    "addr:street":"Milford St",
    "iso:country":"US",
    "sg:address":"6 Milford St",
    "sg:city":"Medway",
    "sg:classifiers":[
        {
            "category":"Professional",
            "subcategory":"Business Services",
            "type":"Services"
        }
    ],
    "sg:phone":"+1 508 533 7673",
    "sg:postcode":"02053",
    "sg:province":"MA",
    "sg:tags":[
        "auctioneer"
    ],
    "wof:name":"As Time Goes By Auctions",
    "wof:placetype":"venue"
},
  "geometry": {"coordinates":[-71.435739,42.143988],"type":"Point"}
}