{
  "type": "Feature",
  "properties": {
    "iso:country":"US",
    "sg:address":"117 Drum Hill Rd",
    "sg:city":"Chelmsford",
    "sg:classifiers":[
        {
            "category":"Health Services",
            "subcategory":"Doctor",
            "type":"Services"
        }
    ],
    "sg:phone":"+1 978 454 5656",
    "sg:postcode":"01824",
    "sg:province":"MA",
    "sg:tags":[
        "dentist"
    ],
    "wof:name":"Drum Hill Dental Care",
    "wof:placetype":"venue"
},
  "geometry": {"coordinates":[-71.363383,42.623836],"type":"Point"}
}