{
  "type": "Feature",
  "properties": {
    "addr:full": "473 Main St Ste 1 Greenfield MA 01301",
    "addr:housenumber": "473",
    "addr:postcode": "01301",
    "addr:street": "Main St Ste 1",
    "iso:country": "US",
    "sg:address": "473 Main St Ste 1",
    "sg:city": "Greenfield",
    "sg:classifiers": [
      {
        "category": "Professional",
        "subcategory": "Lawyer \u0026 Legal Services",
        "type": "Services"
      }
    ],
    "sg:phone": "+1 413 774 2217",
    "sg:postcode": "01301",
    "sg:province": "MA",
    "sg:tags": [
      "attorney",
      "practice"
    ],
    "wof:name": "Gregory M Olchowski",
    "wof:placetype": "venue"
  },
  "geometry": {"coordinates":[-72.597643,42.587457],"type":"Point"}
}
