{
  "type": "Feature",
  "properties": {
    "addr:full":"260 Mill Valley Rd Belchertown MA 01007",
    "addr:housenumber":"260",
    "addr:postcode":"01007",
    "addr:street":"Mill Valley Rd",
    "iso:country":"US",
    "sg:address":"260 Mill Valley Rd",
    "sg:city":"Belchertown",
    "sg:classifiers":[
        {
            "category":"Manufacturing",
            "subcategory":"Lumber",
            "type":"Manufacturing & Wholesale Goods"
        }
    ],
    "sg:phone":"+1 413 323 4831",
    "sg:postcode":"01007",
    "sg:province":"MA",
    "wof:name":"Native Lumber Co",
    "wof:placetype":"venue"
},
  "geometry": {"coordinates":[-72.379927,42.266304],"type":"Point"}
}