{
  "type": "Feature",
  "properties": {
    "iso:country":"US",
    "sg:address":"490 Chapman St",
    "sg:city":"Canton",
    "sg:classifiers":[
        {
            "category":"Professional",
            "subcategory":"Business Services",
            "type":"Services"
        }
    ],
    "sg:phone":"+1 781 830 6040",
    "sg:postcode":"02021",
    "sg:province":"MA",
    "sg:tags":[
        "inventory"
    ],
    "wof:name":"Hilco Appraisal Svc",
    "wof:placetype":"venue"
},
  "geometry": {"coordinates":[-71.15487899999999,42.16515],"type":"Point"}
}