{
  "type": "Feature",
  "properties": {
    "addr:full": "2 Middleboro Rd East Freetown MA 02717",
    "addr:housenumber": "2",
    "addr:postcode": "02717",
    "addr:street": "Middleboro Rd",
    "iso:country": "US",
    "sg:address": "2 Middleboro Rd",
    "sg:city": "East Freetown",
    "sg:classifiers": [
      {
        "category": "Retail",
        "subcategory": "Veterinary Services",
        "type": "Services"
      }
    ],
    "sg:phone": "+1 508 763 2212",
    "sg:postcode": "02717",
    "sg:province": "MA",
    "sg:tags": [
      "veterinarian"
    ],
    "wof:name": "Woodland Pet Lodge",
    "wof:placetype": "venue"
  },
  "geometry": {"coordinates":[-70.944223,41.750794],"type":"Point"}
}
