{
  "type": "Feature",
  "properties": {
    "addr:full":"330 Mt. Auburn St Fifth Floor Cambridge MA 02138",
    "addr:housenumber":"330",
    "addr:postcode":"02138",
    "addr:street":"Mt. Auburn St;Floor",
    "iso:country":"US",
    "sg:address":"330 Mt. Auburn St Fifth Floor",
    "sg:city":"Cambridge",
    "sg:classifiers":[
        {
            "category":"Health Services",
            "subcategory":"Clinic",
            "type":"Services"
        }
    ],
    "sg:postcode":"02138",
    "sg:province":"MA",
    "sg:tags":[
        "medical"
    ],
    "sg:website":"www.mountauburnhospital.org/body...",
    "wof:name":"Bain Birthing Center at Mt. Auburn Hospital",
    "wof:placetype":"venue"
},
  "geometry": {"coordinates":[-71.134186,42.374923],"type":"Point"}
}