{
  "type": "Feature",
  "properties": {
    "iso:country":"US",
    "sg:address":"1 Beacon St",
    "sg:city":"Boston",
    "sg:classifiers":[
        {
            "category":"Professional",
            "type":"Services"
        },
        {
            "category":"Coffee & Tea",
            "type":"Food & Drink"
        },
        {
            "category":"Restaurant",
            "type":"Food & Drink"
        }
    ],
    "sg:phone":"+1 617 482 0066",
    "sg:postcode":"02108",
    "sg:province":"MA",
    "sg:tags":[
        "espresso",
        "caterer"
    ],
    "wof:name":"Rebecca's Cafe & Catering",
    "wof:placetype":"venue"
},
  "geometry": {"coordinates":[-71.060562,42.358021],"type":"Point"}
}