{
  "type": "Feature",
  "properties": {
    "iso:country":"US",
    "sg:address":"26 Jacob St",
    "sg:city":"Malden",
    "sg:classifiers":[
        {
            "category":"Professional",
            "type":"Services"
        }
    ],
    "sg:phone":"+1   ",
    "sg:postcode":"02148",
    "sg:province":"MA",
    "wof:name":"Folder Service",
    "wof:placetype":"venue"
},
  "geometry": {"coordinates":[-71.04383799999999,42.435654],"type":"Point"}
}