{
  "type": "Feature",
  "properties": {
    "iso:country":"US",
    "sg:address":"63 Rzasa Dr",
    "sg:city":"Chicopee",
    "sg:classifiers":[
        {
            "category":"Retail",
            "subcategory":"Repair Shop",
            "type":"Services"
        }
    ],
    "sg:phone":"+1   ",
    "sg:postcode":"01013",
    "sg:province":"MA",
    "sg:tags":[
        "miscellaneous"
    ],
    "wof:name":"Chicopee Machine Tool Svcs Inc",
    "wof:placetype":"venue"
},
  "geometry": {"coordinates":[-72.59218199999999,42.141687],"type":"Point"}
}