{
  "type": "Feature",
  "properties": {
    "addr:full": "80 Hadley Rd Merrimac MA 01860",
    "addr:housenumber": "80",
    "addr:postcode": "01860",
    "addr:street": "Hadley Rd",
    "iso:country": "US",
    "sg:address": "80 Hadley Rd",
    "sg:city": "Merrimac",
    "sg:classifiers": [
      {
        "category": "Autos \u0026 Motor Vehicles",
        "subcategory": "Auto Supplies",
        "type": "Retail Goods"
      },
      {
        "category": "Wholesale",
        "subcategory": "Auto Parts",
        "type": "Manufacturing \u0026 Wholesale Goods"
      }
    ],
    "sg:phone": "+1 978 346 4786",
    "sg:postcode": "01860",
    "sg:province": "MA",
    "sg:tags": [
      "alternator",
      "generator"
    ],
    "wof:name": "Bill's Generator \u0026 Starter Svc",
    "wof:placetype": "venue"
  },
  "geometry": {"coordinates":[-71.039431,42.849394],"type":"Point"}
}
