{
  "type": "Feature",
  "properties": {
    "iso:country":"US",
    "sg:address":"80 Hadley Rd",
    "sg:city":"Merrimac",
    "sg:classifiers":[
        {
            "category":"Autos & Motor Vehicles",
            "subcategory":"Auto Supplies",
            "type":"Retail Goods"
        },
        {
            "category":"Wholesale",
            "subcategory":"Auto Parts",
            "type":"Manufacturing & Wholesale Goods"
        }
    ],
    "sg:phone":"+1 978 346 4786",
    "sg:postcode":"01860",
    "sg:province":"MA",
    "sg:tags":[
        "alternator",
        "generator"
    ],
    "wof:name":"Bill's Generator & Starter Svc",
    "wof:placetype":"venue"
},
  "geometry": {"coordinates":[-71.03943099999999,42.849394],"type":"Point"}
}