{
  "type": "Feature",
  "properties": {
    "iso:country":"US",
    "sg:address":"18 Chester Ave",
    "sg:city":"Waltham",
    "sg:classifiers":[
        {
            "category":"Building & Trades",
            "subcategory":"Construction",
            "type":"Services"
        }
    ],
    "sg:phone":"+1   ",
    "sg:postcode":"02453",
    "sg:province":"MA",
    "sg:tags":[
        "hanging",
        "contractor"
    ],
    "wof:name":"Stephen Navarro Painters",
    "wof:placetype":"venue"
},
  "geometry": {"coordinates":[-71.23893700000001,42.362573],"type":"Point"}
}