{
  "type": "Feature",
  "properties": {
    "addr:full": "18 Chester Ave Waltham MA 02453",
    "addr:housenumber": "18",
    "addr:postcode": "02453",
    "addr:street": "Chester Ave",
    "iso:country": "US",
    "sg:address": "18 Chester Ave",
    "sg:city": "Waltham",
    "sg:classifiers": [
      {
        "category": "Building \u0026 Trades",
        "subcategory": "Construction",
        "type": "Services"
      }
    ],
    "sg:phone": "+1   ",
    "sg:postcode": "02453",
    "sg:province": "MA",
    "sg:tags": [
      "hanging",
      "contractor"
    ],
    "wof:name": "Stephen Navarro Painters",
    "wof:placetype": "venue"
  },
  "geometry": {"coordinates":[-71.238937,42.362573],"type":"Point"}
}
