{
  "type": "Feature",
  "properties": {
    "iso:country":"US",
    "sg:address":"129 Elm St",
    "sg:city":"Hatfield",
    "sg:classifiers":[
        {
            "category":"Utilities",
            "subcategory":"Refuse",
            "type":"Services"
        }
    ],
    "sg:phone":"+1 413 586 4101",
    "sg:postcode":"01038",
    "sg:province":"MA",
    "sg:tags":[
        "garbage",
        "collection"
    ],
    "sg:website":"www.duseautrucking.com",
    "wof:name":"Duseau Trucking",
    "wof:placetype":"venue"
},
  "geometry": {"coordinates":[-72.626176,42.36015],"type":"Point"}
}