{
  "type": "Feature",
  "properties": {
    "addr:full":"154 N Franklin St Holbrook MA 02343",
    "addr:housenumber":"154",
    "addr:postcode":"02343",
    "addr:street":"N Franklin St",
    "iso:country":"US",
    "sg:address":"154 N Franklin St",
    "sg:city":"Holbrook",
    "sg:classifiers":[
        {
            "category":"Banks & Credit Unions",
            "subcategory":"Bank",
            "type":"Services"
        }
    ],
    "sg:phone":"+1 781 767 0041",
    "sg:postcode":"02343",
    "sg:province":"MA",
    "sg:tags":[
        "loan",
        "real estate"
    ],
    "wof:name":"GTM Mortgage",
    "wof:placetype":"venue"
},
  "geometry": {"coordinates":[-71.007673,42.157269],"type":"Point"}
}