{
  "type": "Feature",
  "properties": {
    "iso:country":"US",
    "sg:address":"807 Boylston Street",
    "sg:city":"Chestnut Hill",
    "sg:classifiers":[
        {
            "category":"Shopping",
            "subcategory":"Used Merchandise",
            "type":"Retail Goods"
        }
    ],
    "sg:phone":"+1 617 277 3006",
    "sg:postcode":"02467",
    "sg:province":"MA",
    "sg:tags":[
        "vintage",
        "consignment"
    ],
    "wof:name":"Children's Orchard-Resale & New",
    "wof:placetype":"venue"
},
  "geometry": {"coordinates":[-71.14692599999999,42.326412],"type":"Point"}
}