{
  "type": "Feature",
  "properties": {
    "addr:full":"30 Aetna St Worcester MA 01604",
    "addr:housenumber":"30",
    "addr:postcode":"01604",
    "addr:street":"Aetna St",
    "iso:country":"US",
    "sg:address":"30 Aetna St",
    "sg:city":"Worcester",
    "sg:classifiers":[
        {
            "category":"Organizations",
            "subcategory":"Community Association",
            "type":"Services"
        }
    ],
    "sg:phone":"+1 508 757 7506",
    "sg:postcode":"01604",
    "sg:province":"MA",
    "wof:name":"Foundations",
    "wof:placetype":"venue"
},
  "geometry": {"coordinates":[-71.789282,42.253501],"type":"Point"}
}