{
  "type": "Feature",
  "properties": {
    "iso:country":"US",
    "sg:address":"850 Broadway",
    "sg:city":"Somerville",
    "sg:classifiers":[
        {
            "category":"Food & Beverages",
            "subcategory":"Groceries & Convenience Stores",
            "type":"Retail Goods"
        }
    ],
    "sg:postcode":"02144",
    "sg:province":"MA",
    "wof:name":"Five Corner Convenience Store",
    "wof:placetype":"venue"
},
  "geometry": {"coordinates":[-71.117649,42.400833],"type":"Point"}
}