{
  "type": "Feature",
  "properties": {
    "iso:country":"US",
    "sg:address":"536 Massachusetts Ave",
    "sg:city":"Acton",
    "sg:classifiers":[
        {
            "category":"Personal",
            "type":"Services"
        }
    ],
    "sg:phone":"+1 978 266 1981",
    "sg:postcode":"01720",
    "sg:province":"MA",
    "sg:tags":[
        "consultant",
        "program",
        "health",
        "fitness"
    ],
    "sg:website":"www.personalgains.net",
    "wof:name":"Personal Gains Inc",
    "wof:placetype":"venue"
},
  "geometry": {"coordinates":[-71.47024399999999,42.475941],"type":"Point"}
}