{
  "type": "Feature",
  "properties": {
    "addr:full": "2 Charlesgate W Boston MA 02215",
    "addr:housenumber": "2",
    "addr:postcode": "02215",
    "addr:street": "Charlesgate W",
    "iso:country": "US",
    "sg:address": "2 Charlesgate W",
    "sg:city": "Boston",
    "sg:classifiers": [
      {
        "category": "Farming",
        "subcategory": "Farm \u0026 Veterinary Services",
        "type": "Manufacturing \u0026 Wholesale Goods"
      },
      {
        "category": "Retail",
        "subcategory": "Animal Services",
        "type": "Services"
      }
    ],
    "sg:phone": "+1 617 638 3312",
    "sg:postcode": "02215",
    "sg:province": "MA",
    "sg:tags": [
      "breeder",
      "pet",
      "livestock"
    ],
    "wof:name": "Be Stables Inc",
    "wof:placetype": "venue"
  },
  "geometry": {"coordinates":[-71.091614,42.350262],"type":"Point"}
}
