{
  "type": "Feature",
  "properties": {
    "iso:country":"US",
    "sg:address":"497 Freemans Way",
    "sg:city":"Brewster",
    "sg:classifiers":[
        {
            "category":"Retail",
            "subcategory":"Portrait Studio",
            "type":"Services"
        }
    ],
    "sg:phone":"+1   ",
    "sg:postcode":"02631",
    "sg:province":"MA",
    "sg:tags":[
        "photo"
    ],
    "wof:name":"Amy Dykens Photography",
    "wof:placetype":"venue"
},
  "geometry": {"coordinates":[-70.030439,41.739176],"type":"Point"}
}