{
  "type": "Feature",
  "properties": {
    "iso:country":"US",
    "sg:address":"59 Temple Pl",
    "sg:city":"Boston",
    "sg:classifiers":[
        {
            "category":"Health Services",
            "subcategory":"Clinic",
            "type":"Services"
        }
    ],
    "sg:phone":"+1 617 357 9876",
    "sg:postcode":"02111",
    "sg:province":"MA",
    "sg:website":"www.hmrboston.com",
    "wof:name":"Health Management Resources",
    "wof:placetype":"venue"
},
  "geometry": {"coordinates":[-71.061424,42.354883],"type":"Point"}
}