{
  "type": "Feature",
  "properties": {
    "addr:full": "41 Federal St Reading MA 01867",
    "addr:housenumber": "41",
    "addr:postcode": "01867",
    "addr:street": "Federal St",
    "iso:country": "US",
    "sg:address": "41 Federal St",
    "sg:city": "Reading",
    "sg:classifiers": [
      {
        "category": "Home \u0026 Garden",
        "subcategory": "Home Furnishings",
        "type": "Retail Goods"
      }
    ],
    "sg:phone": "+1 781 944 1539",
    "sg:postcode": "01867",
    "sg:province": "MA",
    "sg:tags": [
      "draperies",
      "curtain",
      "window",
      "treatment"
    ],
    "wof:name": "Shades On Wheels",
    "wof:placetype": "venue"
  },
  "geometry": {"coordinates":[-71.105023,42.529537],"type":"Point"}
}
