{
  "type": "Feature",
  "properties": {
    "iso:country":"US",
    "sg:address":"123 Muller Rd",
    "sg:city":"Burlington",
    "sg:classifiers":[
        {
            "category":"Building & Trades",
            "subcategory":"Construction",
            "type":"Services"
        }
    ],
    "sg:phone":"+1 781 229 0700",
    "sg:postcode":"01803",
    "sg:province":"MA",
    "sg:tags":[
        "contractor"
    ],
    "wof:name":"Hunter David Builders",
    "wof:placetype":"venue"
},
  "geometry": {"coordinates":[-71.20639799999999,42.473598],"type":"Point"}
}