{
  "type": "Feature",
  "properties": {
    "addr:full": "28 Franklin St Worcester MA 01608",
    "addr:housenumber": "28",
    "addr:postcode": "01608",
    "addr:street": "Franklin St",
    "iso:country": "US",
    "ovtr:label": "Bay State Savings Bank, 28 Franklin St Worcester MA US",
    "ovtr:similarity": 2.8309481143951416,
    "sg:address": "28 Franklin St",
    "sg:city": "Worcester",
    "sg:classifiers": [
      {
        "category": "Banks \u0026 Credit Unions",
        "subcategory": "Bank",
        "type": "Services"
      }
    ],
    "sg:phone": "+1 508 890 9000",
    "sg:postcode": "01608",
    "sg:province": "MA",
    "sg:website": "www.baystatesavingsbank.com",
    "wof:name": "Bay State Savings Bank",
    "wof:placetype": "venue"
  },
  "geometry": {"coordinates":[-71.801558,42.261772],"type":"Point"}
}
