{
  "type": "Feature",
  "properties": {
    "addr:full":"195 Main St Groton MA 01450",
    "addr:housenumber":"195",
    "addr:postcode":"01450",
    "addr:street":"Main St",
    "iso:country":"US",
    "sg:address":"195 Main St",
    "sg:city":"Groton",
    "sg:classifiers":[
        {
            "category":"Real Estate",
            "subcategory":"Real Estate Agent",
            "type":"Services"
        }
    ],
    "sg:phone":"+1 978 448 0500",
    "sg:postcode":"01450",
    "sg:province":"MA",
    "sg:website":"www.applecountryrealty.com",
    "wof:name":"Apple Country Realty Inc",
    "wof:placetype":"venue"
},
  "geometry": {"coordinates":[-71.57239199999999,42.608929],"type":"Point"}
}