{
  "type": "Feature",
  "properties": {
    "iso:country":"US",
    "sg:address":"320 Libbey Industrial Pkwy",
    "sg:city":"Weymouth",
    "sg:classifiers":[
        {
            "category":"Real Estate",
            "subcategory":"Architect",
            "type":"Services"
        }
    ],
    "sg:phone":"+1 781 682 9888",
    "sg:postcode":"02189",
    "sg:province":"MA",
    "sg:website":"www.jacaarchitects.com",
    "wof:name":"JACA Architects",
    "wof:placetype":"venue"
},
  "geometry": {"coordinates":[-70.932327,42.189449],"type":"Point"}
}