{
  "type": "Feature",
  "properties": {
    "iso:country":"US",
    "sg:address":"160 University Ave",
    "sg:city":"Westwood",
    "sg:classifiers":[
        {
            "category":"Professional",
            "type":"Services"
        }
    ],
    "sg:phone":"+1 781 329 9960",
    "sg:postcode":"02090",
    "sg:province":"MA",
    "sg:tags":[
        "establishment"
    ],
    "wof:name":"MIB Inc",
    "wof:placetype":"venue"
},
  "geometry": {"coordinates":[-71.149552,42.211531],"type":"Point"}
}