{
  "type": "Feature",
  "properties": {
    "addr:full": "67 Millbrook St Worcester MA 01606",
    "addr:housenumber": "67",
    "addr:postcode": "01606",
    "addr:street": "Millbrook St",
    "iso:country": "US",
    "sg:address": "67 Millbrook St",
    "sg:city": "Worcester",
    "sg:classifiers": [
      {
        "category": "Professional",
        "subcategory": "Management \u0026 Consulting",
        "type": "Services"
      }
    ],
    "sg:phone": "+1 508 421 8002",
    "sg:postcode": "01606",
    "sg:province": "MA",
    "sg:tags": [
      "consultant",
      "business"
    ],
    "wof:name": "Anderson Maddocks",
    "wof:placetype": "venue"
  },
  "geometry": {"coordinates":[-71.800304,42.287317],"type":"Point"}
}
