{
  "type": "Feature",
  "properties": {
    "addr:full": "64 Green St Northampton MA 01060",
    "addr:housenumber": "64",
    "addr:postcode": "01060",
    "addr:street": "Green St",
    "iso:country": "US",
    "sg:address": "64 Green St",
    "sg:city": "Northampton",
    "sg:classifiers": [
      {
        "category": "Restaurant",
        "type": "Food \u0026 Drink"
      }
    ],
    "sg:phone": "+1 413 586 5650",
    "sg:postcode": "01060",
    "sg:province": "MA",
    "wof:name": "Green Street Cafe",
    "wof:placetype": "venue"
  },
  "geometry": {"coordinates":[-72.637053,42.316667],"type":"Point"}
}
