{
  "type": "Feature",
  "properties": {
    "addr:full": "196 Beach St Revere MA 02151",
    "addr:housenumber": "196",
    "addr:postcode": "02151",
    "addr:street": "Beach St",
    "iso:country": "US",
    "sg:address": "196 Beach St",
    "sg:city": "Revere",
    "sg:classifiers": [
      {
        "category": "Personal",
        "subcategory": "Beauty Salon",
        "type": "Services"
      }
    ],
    "sg:phone": "+1 781 662 6252",
    "sg:postcode": "02151",
    "sg:province": "MA",
    "wof:name": "A Cut Above",
    "wof:placetype": "venue"
  },
  "geometry": {"coordinates":[-71.009558,42.408057],"type":"Point"}
}
