{
  "type": "Feature",
  "properties": {
    "iso:country":"US",
    "sg:address":"196 Beach St",
    "sg:city":"Revere",
    "sg:classifiers":[
        {
            "category":"Personal",
            "subcategory":"Beauty Salon",
            "type":"Services"
        }
    ],
    "sg:phone":"+1 781 662 6252",
    "sg:postcode":"02151",
    "sg:province":"MA",
    "wof:name":"A Cut Above",
    "wof:placetype":"venue"
},
  "geometry": {"coordinates":[-71.009558,42.408057],"type":"Point"}
}