{
  "type": "Feature",
  "properties": {
    "iso:country":"US",
    "sg:address":"437 Franklin St",
    "sg:city":"Mansfield",
    "sg:classifiers":[
        {
            "category":"Professional",
            "subcategory":"Management & Consulting",
            "type":"Services"
        }
    ],
    "sg:phone":"+1   ",
    "sg:postcode":"02048",
    "sg:province":"MA",
    "wof:name":"Plan International",
    "wof:placetype":"venue"
},
  "geometry": {"coordinates":[-71.191385,42.049771],"type":"Point"}
}