{
  "type": "Feature",
  "properties": {
    "addr:full":"813 Beacon St Newton MA 02459",
    "addr:housenumber":"813",
    "addr:postcode":"02459",
    "addr:street":"Beacon St",
    "iso:country":"US",
    "sg:address":"813 Beacon St",
    "sg:city":"Newton",
    "sg:classifiers":[
        {
            "category":"Professional",
            "subcategory":"Management & Consulting",
            "type":"Services"
        }
    ],
    "sg:phone":"+1 617 247 1055",
    "sg:postcode":"02459",
    "sg:province":"MA",
    "sg:tags":[
        "counselor",
        "public",
        "relations"
    ],
    "wof:name":"Jackson & Co Public Relations",
    "wof:placetype":"venue"
},
  "geometry": {"coordinates":[-71.19802199999999,42.330461],"type":"Point"}
}