{
  "type": "Feature",
  "properties": {
    "addr:full":"189 Access Rd Norwood MA 02062",
    "addr:housenumber":"189",
    "addr:postcode":"02062",
    "addr:street":"Access Rd",
    "iso:country":"US",
    "sg:address":"189 Access Rd",
    "sg:city":"Norwood",
    "sg:classifiers":[
        {
            "category":"Professional",
            "type":"Services"
        }
    ],
    "sg:phone":"+1 781 278 0088",
    "sg:postcode":"02062",
    "sg:province":"MA",
    "sg:tags":[
        "establishment"
    ],
    "wof:name":"Robinson Ted Bulldog Trust",
    "wof:placetype":"venue"
},
  "geometry": {"coordinates":[-71.179835,42.188982],"type":"Point"}
}