{
  "type": "Feature",
  "properties": {
    "iso:country":"US",
    "sg:address":"20 Exchange St",
    "sg:city":"Waltham",
    "sg:classifiers":[
        {
            "category":"Organizations",
            "subcategory":"Community Association",
            "type":"Services"
        }
    ],
    "sg:phone":"+1 781 893 6620",
    "sg:postcode":"02451",
    "sg:province":"MA",
    "sg:tags":[
        "club"
    ],
    "sg:website":"www.walthambgc.org",
    "wof:name":"Waltham Boys & Girls Club Inc",
    "wof:placetype":"venue"
},
  "geometry": {"coordinates":[-71.24002299999999,42.376276],"type":"Point"}
}