{
  "type": "Feature",
  "properties": {
    "addr:full": "113 Spencer Ave Chelsea MA 02150",
    "addr:housenumber": "113",
    "addr:postcode": "02150",
    "addr:street": "Spencer Ave",
    "iso:country": "US",
    "sg:address": "113 Spencer Ave",
    "sg:city": "Chelsea",
    "sg:classifiers": [
      {
        "category": "Government",
        "subcategory": "Office",
        "type": "Public Place"
      }
    ],
    "sg:phone": "+1 617 884 5175",
    "sg:postcode": "02150",
    "sg:province": "MA",
    "sg:tags": [
      "state",
      "security"
    ],
    "wof:name": "National Guard",
    "wof:placetype": "venue"
  },
  "geometry": {"coordinates":[-71.023304,42.397913],"type":"Point"}
}
