{
  "type": "Feature",
  "properties": {
    "addr:full": "100 Grandview Rd Ste 108 Braintree MA 02184",
    "addr:housenumber": "100",
    "addr:postcode": "02184",
    "addr:street": "Grandview Rd Ste 108",
    "iso:country": "US",
    "sg:address": "100 Grandview Rd Ste 108",
    "sg:city": "Braintree",
    "sg:classifiers": [
      {
        "category": "Professional",
        "subcategory": "Advertising",
        "type": "Services"
      }
    ],
    "sg:phone": "+1 800 266 2278",
    "sg:postcode": "02184",
    "sg:province": "MA",
    "sg:tags": [
      "agency",
      "specialty"
    ],
    "wof:name": "Comcast",
    "wof:placetype": "venue"
  },
  "geometry": {"coordinates":[-71.033249,42.220132],"type":"Point"}
}
