{
  "type": "Feature",
  "properties": {
    "iso:country":"US",
    "sg:address":"351 Pleasant Lake Ave",
    "sg:city":"Harwich",
    "sg:classifiers":[
        {
            "category":"Education",
            "subcategory":"Junior College",
            "type":"Public Place"
        }
    ],
    "sg:phone":"+1 508 771 2600",
    "sg:postcode":"02645",
    "sg:province":"MA",
    "sg:tags":[
        "technical",
        "institute"
    ],
    "sg:website":"www.capetech.us",
    "wof:name":"Cape Cod Reg Tech High School",
    "wof:placetype":"venue"
},
  "geometry": {"coordinates":[-70.07744099999999,41.707027],"type":"Point"}
}