{
  "type": "Feature",
  "properties": {
    "addr:full": "211 Essex St Swampscott MA 01907",
    "addr:housenumber": "211",
    "addr:postcode": "01907",
    "addr:street": "Essex St",
    "iso:country": "US",
    "sg:address": "211 Essex St",
    "sg:city": "Swampscott",
    "sg:classifiers": [
      {
        "category": "Personal",
        "type": "Services"
      },
      {
        "category": "Sports \u0026 Exercise",
        "subcategory": "Gym",
        "type": "Entertainment"
      },
      {
        "category": "Health Services",
        "subcategory": "Health Practitioner",
        "type": "Services"
      },
      {
        "category": "Arena",
        "subcategory": "Sports Club",
        "type": "Entertainment"
      }
    ],
    "sg:phone": "+1 800 615 7352",
    "sg:postcode": "01907",
    "sg:province": "MA",
    "sg:tags": [
      "trainer",
      "control",
      "weight",
      "consultant",
      "program",
      "fitness",
      "physical"
    ],
    "sg:website": "http://national.citysearch.com/profile/external/41175566/swampscott_ma/curves.html?publisher=yellowpages\u0026reference_id=1\u0026placement=ypwebsitemip",
    "wof:name": "Curves",
    "wof:placetype": "venue"
  },
  "geometry": {"coordinates":[-70.917564,42.478655],"type":"Point"}
}
