{
  "type": "Feature",
  "properties": {
    "addr:full":"51 Lorna Ave Pembroke MA 02359",
    "addr:housenumber":"51",
    "addr:postcode":"02359",
    "addr:street":"Lorna Ave",
    "iso:country":"US",
    "sg:address":"51 Lorna Ave",
    "sg:city":"Pembroke",
    "sg:classifiers":[
        {
            "category":"Building & Trades",
            "subcategory":"Construction",
            "type":"Services"
        }
    ],
    "sg:phone":"+1 781 826 5789",
    "sg:postcode":"02359",
    "sg:province":"MA",
    "sg:tags":[
        "painter"
    ],
    "wof:name":"CRB Painting Inc",
    "wof:placetype":"venue"
},
  "geometry": {"coordinates":[-70.788751,42.104113],"type":"Point"}
}