{
  "type": "Feature",
  "properties": {
    "iso:country":"US",
    "sg:address":"507 Southampton Rd",
    "sg:city":"Westfield",
    "sg:phone":"+1 413 568 4443",
    "sg:postcode":"01085",
    "sg:province":"MA",
    "sg:tags":[
        "oil"
    ],
    "wof:name":"Pioneer Valley Oil Inc",
    "wof:placetype":"venue"
},
  "geometry": {"coordinates":[-72.72545700000001,42.153545],"type":"Point"}
}