{
  "type": "Feature",
  "properties": {
    "iso:country":"US",
    "sg:address":"164 N Main St",
    "sg:city":"Natick",
    "sg:classifiers":[
        {
            "category":"Professional",
            "subcategory":"Employment Agencies",
            "type":"Services"
        }
    ],
    "sg:phone":"+1 508 652 1940",
    "sg:postcode":"01760",
    "sg:province":"MA",
    "sg:tags":[
        "opportunity"
    ],
    "wof:name":"Bernard Group",
    "wof:placetype":"venue"
},
  "geometry": {"coordinates":[-71.358921,42.296599],"type":"Point"}
}