{
  "type": "Feature",
  "properties": {
    "iso:country":"US",
    "sg:address":"11 Marconi Ln",
    "sg:city":"Marion",
    "sg:classifiers":[
        {
            "category":"Building & Trades",
            "subcategory":"Equipment Rental",
            "type":"Services"
        }
    ],
    "sg:phone":"+1 508 748 1792",
    "sg:postcode":"02738",
    "sg:province":"MA",
    "sg:tags":[
        "camping"
    ],
    "wof:name":"Sperry Tents",
    "wof:placetype":"venue"
},
  "geometry": {"coordinates":[-70.77337900000001,41.714083],"type":"Point"}
}