{
  "type": "Feature",
  "properties": {
    "addr:full": "435 Newbury St Danvers MA 01923",
    "addr:housenumber": "435",
    "addr:postcode": "01923",
    "addr:street": "Newbury St",
    "iso:country": "US",
    "sg:address": "435 Newbury St",
    "sg:city": "Danvers",
    "sg:classifiers": [
      {
        "category": "Building \u0026 Trades",
        "subcategory": "Construction",
        "type": "Services"
      }
    ],
    "sg:phone": "+1 978 774 2700",
    "sg:postcode": "01923",
    "sg:province": "MA",
    "sg:tags": [
      "general",
      "contractor"
    ],
    "wof:name": "Hawthorne North Realty Trust",
    "wof:placetype": "venue"
  },
  "geometry": {"coordinates":[-70.960507,42.598532],"type":"Point"}
}
