{
  "type": "Feature",
  "properties": {
    "addr:full":"51 Harborview Rd Hull MA 02045",
    "addr:housenumber":"51",
    "addr:postcode":"02045",
    "addr:street":"Harborview Rd",
    "iso:country":"US",
    "sg:address":"51 Harborview Rd",
    "sg:city":"Hull",
    "sg:classifiers":[
        {
            "category":"Professional",
            "type":"Services"
        }
    ],
    "sg:phone":"+1   ",
    "sg:postcode":"02045",
    "sg:province":"MA",
    "sg:tags":[
        "seminar",
        "software"
    ],
    "wof:name":"Pro/User Inc",
    "wof:placetype":"venue"
},
  "geometry": {"coordinates":[-70.90626,42.307164],"type":"Point"}
}