{
  "type": "Feature",
  "properties": {
    "addr:full": "1 Mill St Amesbury MA 01913",
    "addr:housenumber": "1",
    "addr:postcode": "01913",
    "addr:street": "Mill St",
    "iso:country": "US",
    "sg:address": "1 Mill St",
    "sg:city": "Amesbury",
    "sg:classifiers": [
      {
        "category": "Organizations",
        "subcategory": "Community Association",
        "type": "Services"
      }
    ],
    "sg:phone": "+1 978 388 9921",
    "sg:postcode": "01913",
    "sg:province": "MA",
    "sg:tags": [
      "club"
    ],
    "wof:name": "Polish National Alliance",
    "wof:placetype": "venue"
  },
  "geometry": {"coordinates":[-70.930551,42.857084],"type":"Point"}
}
