{
  "type": "Feature",
  "properties": {
    "iso:country":"US",
    "sg:address":"82 Sandwich Rd # 84",
    "sg:city":"Buzzards Bay",
    "sg:classifiers":[
        {
            "category":"Real Estate",
            "subcategory":"Real Estate Operator",
            "type":"Services"
        }
    ],
    "sg:phone":"+1 508 743 9100",
    "sg:postcode":"02532",
    "sg:province":"MA",
    "sg:tags":[
        "apartment"
    ],
    "wof:name":"Tudor House Apartments",
    "wof:placetype":"venue"
},
  "geometry": {"coordinates":[-70.593102,41.743401],"type":"Point"}
}