{
  "type": "Feature",
  "properties": {
    "iso:country":"US",
    "sg:address":"263 Milton St",
    "sg:city":"Dedham",
    "sg:classifiers":[
        {
            "category":"Professional",
            "type":"Services"
        }
    ],
    "sg:phone":"+1 781 251 9645",
    "sg:postcode":"02026",
    "sg:province":"MA",
    "sg:tags":[
        "establishment"
    ],
    "wof:name":"Agbar Technologies",
    "wof:placetype":"venue"
},
  "geometry": {"coordinates":[-71.145375,42.241329],"type":"Point"}
}