{
  "type": "Feature",
  "properties": {
    "iso:country":"US",
    "sg:address":"201 Coburn St",
    "sg:city":"Lowell",
    "sg:classifiers":[
        {
            "category":"Social Services",
            "type":"Services"
        },
        {
            "category":"Professional",
            "subcategory":"Employment Agencies",
            "type":"Services"
        },
        {
            "category":"Organizations",
            "subcategory":"Community Association",
            "type":"Services"
        }
    ],
    "sg:phone":"+1 978 452 8190",
    "sg:postcode":"01850",
    "sg:province":"MA",
    "sg:tags":[
        "club",
        "workers'",
        "placement",
        "volunteer"
    ],
    "wof:name":"Polish Amer Veterans Of Lowell Inc",
    "wof:placetype":"venue"
},
  "geometry": {"coordinates":[-71.305986,42.655899],"type":"Point"}
}