{
  "type": "Feature",
  "properties": {
    "iso:country":"US",
    "sg:address":"80 Shingle Mill Ln",
    "sg:city":"Hanover",
    "sg:classifiers":[
        {
            "category":"Mining & Drilling",
            "type":"Manufacturing & Wholesale Goods"
        }
    ],
    "sg:phone":"+1   ",
    "sg:postcode":"02339",
    "sg:province":"MA",
    "sg:tags":[
        "field"
    ],
    "wof:name":"Servicing Opthalmic Systems",
    "wof:placetype":"venue"
},
  "geometry": {"coordinates":[-70.876645,42.143819],"type":"Point"}
}