{
  "type": "Feature",
  "properties": {
    "addr:full":"98 Captains Row Chelsea MA 02150",
    "addr:housenumber":"98",
    "addr:postcode":"02150",
    "addr:street":"Captains Row",
    "iso:country":"US",
    "sg:address":"98 Captains Row",
    "sg:city":"Chelsea",
    "sg:classifiers":[
        {
            "category":"Banks & Credit Unions",
            "subcategory":"Bank",
            "type":"Services"
        }
    ],
    "sg:phone":"+1 617 889 1700",
    "sg:postcode":"02150",
    "sg:province":"MA",
    "sg:tags":[
        "other",
        "plan",
        "card"
    ],
    "wof:name":"Card Service New England",
    "wof:placetype":"venue"
},
  "geometry": {"coordinates":[-71.044849,42.388967],"type":"Point"}
}