{
  "type": "Feature",
  "properties": {
    "addr:full":"27 Sever St Worcester MA 01609",
    "addr:housenumber":"27",
    "addr:postcode":"01609",
    "addr:street":"Sever St",
    "iso:country":"US",
    "sg:address":"27 Sever St",
    "sg:city":"Worcester",
    "sg:classifiers":[
        {
            "category":"Education",
            "subcategory":"School",
            "type":"Public Place"
        }
    ],
    "sg:phone":"+1 508 755 2571",
    "sg:postcode":"01609",
    "sg:province":"MA",
    "sg:website":"www.dynamy.org",
    "wof:name":"Dynamy Program",
    "wof:placetype":"venue"
},
  "geometry": {"coordinates":[-71.812044,42.265977],"type":"Point"}
}