{
  "type": "Feature",
  "properties": {
    "iso:country":"US",
    "sg:address":"75 Lindall St",
    "sg:city":"Danvers",
    "sg:classifiers":[
        {
            "category":"Health Services",
            "subcategory":"Doctor",
            "type":"Services"
        }
    ],
    "sg:phone":"+1 978 777 4266",
    "sg:postcode":"01923",
    "sg:province":"MA",
    "sg:tags":[
        "physician",
        "surgeon"
    ],
    "wof:name":"Occupational Health",
    "wof:placetype":"venue"
},
  "geometry": {"coordinates":[-70.944258,42.575155],"type":"Point"}
}