{
  "type": "Feature",
  "properties": {
    "iso:country":"US",
    "sg:address":"1441 Iyannough Rd",
    "sg:city":"Hyannis",
    "sg:classifiers":[
        {
            "category":"Professional",
            "subcategory":"Lawyer & Legal Services",
            "type":"Services"
        }
    ],
    "sg:phone":"+1 508 775 2900",
    "sg:postcode":"02601",
    "sg:province":"MA",
    "wof:name":"Libbey Gordon Mark Atty",
    "wof:placetype":"venue"
},
  "geometry": {"coordinates":[-70.310501,41.6754],"type":"Point"}
}