{
  "type": "Feature",
  "properties": {
    "addr:full": "35 Ellsworth St Worcester MA 01610",
    "addr:housenumber": "35",
    "addr:postcode": "01610",
    "addr:street": "Ellsworth St",
    "iso:country": "US",
    "sg:address": "35 Ellsworth St",
    "sg:city": "Worcester",
    "sg:classifiers": [
      {
        "category": "Freight",
        "type": "Transportation"
      }
    ],
    "sg:phone": "+1 508 798 8301",
    "sg:postcode": "01610",
    "sg:province": "MA",
    "sg:tags": [
      "delivery"
    ],
    "wof:name": "Time Express Delivery Svc",
    "wof:placetype": "venue"
  },
  "geometry": {"coordinates":[-71.800759,42.252031],"type":"Point"}
}
