{
  "type": "Feature",
  "properties": {
    "iso:country":"US",
    "sg:address":"110 Canal St",
    "sg:city":"Boston",
    "sg:classifiers":[
        {
            "category":"Manufacturing",
            "subcategory":"Food",
            "type":"Manufacturing & Wholesale Goods"
        }
    ],
    "sg:phone":"+1 617 896 2300",
    "sg:postcode":"02114",
    "sg:province":"MA",
    "sg:tags":[
        "brewer"
    ],
    "wof:name":"Slesar Brothers Brewing Co",
    "wof:placetype":"venue"
},
  "geometry": {"coordinates":[-71.061222,42.365413],"type":"Point"}
}