{
  "type": "Feature",
  "properties": {
    "addr:full": "487 Chapin Rd Hampden MA 01036",
    "addr:housenumber": "487",
    "addr:postcode": "01036",
    "addr:street": "Chapin Rd",
    "iso:country": "US",
    "sg:address": "487 Chapin Rd",
    "sg:city": "Hampden",
    "sg:classifiers": [
      {
        "category": "Wholesale",
        "subcategory": "Books, Periodicals, \u0026 Newspapers",
        "type": "Manufacturing \u0026 Wholesale Goods"
      }
    ],
    "sg:phone": "+1   ",
    "sg:postcode": "01036",
    "sg:province": "MA",
    "wof:name": "Spfld News Dist 1",
    "wof:placetype": "venue"
  },
  "geometry": {"coordinates":[-72.392973,42.0349],"type":"Point"}
}
