{
  "type": "Feature",
  "properties": {
    "iso:country":"US",
    "sg:address":"487 Chapin Rd",
    "sg:city":"Hampden",
    "sg:classifiers":[
        {
            "category":"Wholesale",
            "subcategory":"Books, Periodicals, & Newspapers",
            "type":"Manufacturing & Wholesale Goods"
        }
    ],
    "sg:phone":"+1   ",
    "sg:postcode":"01036",
    "sg:province":"MA",
    "wof:name":"Spfld News Dist 1",
    "wof:placetype":"venue"
},
  "geometry": {"coordinates":[-72.392973,42.0349],"type":"Point"}
}