{
  "type": "Feature",
  "properties": {
    "addr:full": "9 Russell Rd Westfield MA 01085",
    "addr:housenumber": "9",
    "addr:postcode": "01085",
    "addr:street": "Russell Rd",
    "iso:country": "US",
    "ovtr:label": "Country Clipper, 9 Russell Rd Westfield MA US",
    "ovtr:similarity": 2.273693084716797,
    "sg:address": "9 Russell Rd",
    "sg:city": "Westfield",
    "sg:classifiers": [
      {
        "category": "Retail",
        "subcategory": "Animal Services",
        "type": "Services"
      }
    ],
    "sg:phone": "+1 413 568 0556",
    "sg:postcode": "01085",
    "sg:province": "MA",
    "sg:tags": [
      "pet",
      "grooming",
      "washing"
    ],
    "wof:name": "Country Clipper",
    "wof:placetype": "venue"
  },
  "geometry": {"coordinates":[-72.764051,42.128484],"type":"Point"}
}
