{
  "type": "Feature",
  "properties": {
    "addr:full": "327 Center St Bridgewater MA 02324",
    "addr:housenumber": "327",
    "addr:postcode": "02324",
    "addr:street": "Center St",
    "iso:country": "US",
    "sg:address": "327 Center St",
    "sg:city": "Bridgewater",
    "sg:classifiers": [
      {
        "category": "Retail",
        "subcategory": "Repair Shop",
        "type": "Services"
      }
    ],
    "sg:phone": "+1   ",
    "sg:postcode": "02324",
    "sg:province": "MA",
    "wof:name": "Miniature Services",
    "wof:placetype": "venue"
  },
  "geometry": {"coordinates":[-70.987396,41.991806],"type":"Point"}
}
