{
  "type": "Feature",
  "properties": {
    "addr:full":"1197 Centre St Newton MA 02459",
    "addr:housenumber":"1197",
    "addr:postcode":"02459",
    "addr:street":"Centre St",
    "iso:country":"US",
    "sg:address":"1197 Centre St",
    "sg:city":"Newton",
    "sg:classifiers":[
        {
            "category":"Banks & Credit Unions",
            "subcategory":"Bank",
            "type":"Services"
        }
    ],
    "sg:phone":"+1 617 244 0559",
    "sg:postcode":"02459",
    "sg:province":"MA",
    "wof:name":"Boston Federal Savings Bank",
    "wof:placetype":"venue"
},
  "geometry": {"coordinates":[-71.19436899999999,42.332145],"type":"Point"}
}