{
  "type": "Feature",
  "properties": {
    "iso:country":"US",
    "sg:address":"1 Winthrop St",
    "sg:city":"Provincetown",
    "sg:classifiers":[
        {
            "category":"Real Estate",
            "subcategory":"Real Estate Services",
            "type":"Services"
        },
        {
            "category":"Real Estate",
            "subcategory":"Real Estate Agent",
            "type":"Services"
        }
    ],
    "sg:phone":"+1 508 487 8887",
    "sg:postcode":"02657",
    "sg:province":"MA",
    "sg:tags":[
        "management"
    ],
    "sg:website":"http://www.ptownproperties.com",
    "wof:name":"Peter Karl & Associates Real Estate Inc",
    "wof:placetype":"venue"
},
  "geometry": {"coordinates":[-70.189819,42.047779],"type":"Point"}
}