{
  "type": "Feature",
  "properties": {
    "iso:country":"US",
    "sg:address":"60 Moulton St",
    "sg:city":"Cambridge",
    "sg:classifiers":[
        {
            "category":"Professional",
            "type":"Services"
        }
    ],
    "sg:phone":"+1 617 864 6080",
    "sg:postcode":"02138",
    "sg:province":"MA",
    "sg:tags":[
        "establishment"
    ],
    "wof:name":"Smith-Erie Co",
    "wof:placetype":"venue"
},
  "geometry": {"coordinates":[-71.147706,42.390539],"type":"Point"}
}