{
  "type": "Feature",
  "properties": {
    "addr:full":"21 Maebeth St Springfield MA 01119",
    "addr:housenumber":"21",
    "addr:postcode":"01119",
    "addr:street":"Maebeth St",
    "iso:country":"US",
    "sg:address":"21 Maebeth St",
    "sg:city":"Springfield",
    "sg:classifiers":[
        {
            "category":"Freight",
            "type":"Transportation"
        }
    ],
    "sg:phone":"+1   ",
    "sg:postcode":"01119",
    "sg:province":"MA",
    "sg:tags":[
        "carrier",
        "interstate"
    ],
    "wof:name":"Hood Jack Transportation Inc",
    "wof:placetype":"venue"
},
  "geometry": {"coordinates":[-72.512214,42.119227],"type":"Point"}
}