{
  "type": "Feature",
  "properties": {
    "iso:country":"US",
    "sg:address":"308 Central St",
    "sg:city":"Saugus",
    "sg:classifiers":[
        {
            "category":"Organizations",
            "subcategory":"Religious Organization",
            "type":"Services"
        }
    ],
    "sg:phone":"+1 781 941 2004",
    "sg:postcode":"01906",
    "sg:province":"MA",
    "sg:tags":[
        "church"
    ],
    "wof:name":"Greater Grace World Outreach",
    "wof:placetype":"venue"
},
  "geometry": {"coordinates":[-71.00972899999999,42.463634],"type":"Point"}
}