{
  "type": "Feature",
  "properties": {
    "iso:country":"US",
    "sg:address":"31 State St 7th Fl",
    "sg:city":"Boston",
    "sg:classifiers":[
        {
            "category":"Health Services",
            "subcategory":"Dentist",
            "type":"Services"
        }
    ],
    "sg:phone":"+1 617 742 1350",
    "sg:postcode":"02109",
    "sg:province":"MA",
    "sg:website":"www.ShareThatSmile.com",
    "wof:name":"Dr. Jack B. Share, DDS",
    "wof:placetype":"venue"
},
  "geometry": {"coordinates":[-71.056884,42.358589],"type":"Point"}
}