{
  "type": "Feature",
  "properties": {
    "addr:full":"700 Beacon St Newton MA 02459",
    "addr:housenumber":"700",
    "addr:postcode":"02459",
    "addr:street":"Beacon St",
    "iso:country":"US",
    "sg:address":"700 Beacon St",
    "sg:city":"Newton",
    "sg:classifiers":[
        {
            "category":"Real Estate",
            "subcategory":"Real Estate Agent",
            "type":"Services"
        }
    ],
    "sg:phone":"+1 617 527 2675",
    "sg:postcode":"02459",
    "sg:province":"MA",
    "wof:name":"Town & Country Properties",
    "wof:placetype":"venue"
},
  "geometry": {"coordinates":[-71.190535,42.330722],"type":"Point"}
}