{
  "type": "Feature",
  "properties": {
    "addr:full": "31 Stony Brook Rd Great Barrington MA 01230",
    "addr:housenumber": "31",
    "addr:postcode": "01230",
    "addr:street": "Stony Brook Rd",
    "iso:country": "US",
    "sg:address": "31 Stony Brook Rd",
    "sg:city": "Great Barrington",
    "sg:classifiers": [
      {
        "category": "Professional",
        "subcategory": "Employment Agencies",
        "type": "Services"
      }
    ],
    "sg:phone": "+1 413 528 4769",
    "sg:postcode": "01230",
    "sg:province": "MA",
    "sg:tags": [
      "consultant",
      "search",
      "executive"
    ],
    "wof:name": "Search \u0026 Placement Svc",
    "wof:placetype": "venue"
  },
  "geometry": {"coordinates":[-73.318148,42.220423],"type":"Point"}
}
