{
  "type": "Feature",
  "properties": {
    "iso:country":"US",
    "sg:address":"31 Stony Brook Rd",
    "sg:city":"Great Barrington",
    "sg:classifiers":[
        {
            "category":"Professional",
            "subcategory":"Employment Agencies",
            "type":"Services"
        }
    ],
    "sg:phone":"+1 413 528 4769",
    "sg:postcode":"01230",
    "sg:province":"MA",
    "sg:tags":[
        "consultant",
        "search",
        "executive"
    ],
    "wof:name":"Search & Placement Svc",
    "wof:placetype":"venue"
},
  "geometry": {"coordinates":[-73.31814799999999,42.220423],"type":"Point"}
}