{
  "type": "Feature",
  "properties": {
    "addr:full":"79 Sunnyside Avenue Arlington MA 02474",
    "addr:housenumber":"79",
    "addr:postcode":"02474",
    "addr:street":"Sunnyside Avenue",
    "iso:country":"US",
    "sg:address":"79 Sunnyside Avenue",
    "sg:city":"Arlington",
    "sg:classifiers":[
        {
            "category":"Professional",
            "subcategory":"Accounting & Tax Preparation",
            "type":"Services"
        }
    ],
    "sg:phone":"+1 781 648 7737",
    "sg:postcode":"02474",
    "sg:province":"MA",
    "sg:tags":[
        "accountant"
    ],
    "wof:name":"Bolduc Charlotte CPA",
    "wof:placetype":"venue"
},
  "geometry": {"coordinates":[-71.133347,42.410402],"type":"Point"}
}