{
  "type": "Feature",
  "properties": {
    "addr:full":"660 Washington St Canton MA 02021",
    "addr:housenumber":"660",
    "addr:postcode":"02021",
    "addr:street":"Washington St",
    "iso:country":"US",
    "sg:address":"660 Washington St",
    "sg:city":"Canton",
    "sg:classifiers":[
        {
            "category":"Health Services",
            "subcategory":"Health Practitioner",
            "type":"Services"
        }
    ],
    "sg:phone":"+1 781 821 0093",
    "sg:postcode":"02021",
    "sg:province":"MA",
    "sg:tags":[
        "nutritionist"
    ],
    "wof:name":"Hessco Nutrition Dept",
    "wof:placetype":"venue"
},
  "geometry": {"coordinates":[-71.127701,42.164101],"type":"Point"}
}