{
  "type": "Feature",
  "properties": {
    "addr:full":"760 Main St Holden MA 01520",
    "addr:housenumber":"760",
    "addr:postcode":"01520",
    "addr:street":"Main St",
    "iso:country":"US",
    "sg:address":"760 Main St",
    "sg:city":"Holden",
    "sg:classifiers":[
        {
            "category":"Wholesale",
            "subcategory":"Medical Equipment & Supplies",
            "type":"Manufacturing & Wholesale Goods"
        }
    ],
    "sg:phone":"+1 508 829 2012",
    "sg:postcode":"01520",
    "sg:province":"MA",
    "sg:tags":[
        "hospital"
    ],
    "wof:name":"Apple Homecare Assoc Inc",
    "wof:placetype":"venue"
},
  "geometry": {"coordinates":[-71.838948,42.340261],"type":"Point"}
}