{
  "type": "Feature",
  "properties": {
    "addr:full":"866 Washington St Canton MA 02021",
    "addr:housenumber":"866",
    "addr:postcode":"02021",
    "addr:street":"Washington St",
    "iso:country":"US",
    "sg:address":"866 Washington St",
    "sg:city":"Canton",
    "sg:classifiers":[
        {
            "category":"Communications",
            "subcategory":"Newspaper",
            "type":"Services"
        }
    ],
    "sg:phone":"+1 781 821 4418",
    "sg:postcode":"02021",
    "sg:province":"MA",
    "sg:tags":[
        "print",
        "medium"
    ],
    "wof:name":"Canton Citizen Inc",
    "wof:placetype":"venue"
},
  "geometry": {"coordinates":[-71.1437,42.160702],"type":"Point"}
}