{
  "type": "Feature",
  "properties": {
    "addr:full":"46 Auburn St Auburn MA 01501",
    "addr:housenumber":"46",
    "addr:postcode":"01501",
    "addr:street":"Auburn St",
    "iso:country":"US",
    "sg:address":"46 Auburn St",
    "sg:city":"Auburn",
    "sg:classifiers":[
        {
            "category":"Cinema",
            "subcategory":"Movie Rental",
            "type":"Entertainment"
        }
    ],
    "sg:phone":"+1 508 721 9915",
    "sg:postcode":"01501",
    "sg:province":"MA",
    "sg:tags":[
        "leasing",
        "video",
        "disc",
        "tape"
    ],
    "sg:website":"www.hollywoodvideo.com",
    "wof:name":"Hollywood Video",
    "wof:placetype":"venue"
},
  "geometry": {"coordinates":[-71.83333399999999,42.205895],"type":"Point"}
}