{
  "type": "Feature",
  "properties": {
    "addr:full":"44 Round Top Rd Framingham MA 01701",
    "addr:housenumber":"44",
    "addr:postcode":"01701",
    "addr:street":"Round Top Rd",
    "iso:country":"US",
    "sg:address":"44 Round Top Rd",
    "sg:city":"Framingham",
    "sg:classifiers":[
        {
            "category":"Professional",
            "subcategory":"Lawyer & Legal Services",
            "type":"Services"
        }
    ],
    "sg:phone":"+1 508 877 2728",
    "sg:postcode":"01701",
    "sg:province":"MA",
    "wof:name":"Alan Joel Finkel",
    "wof:placetype":"venue"
},
  "geometry": {"coordinates":[-71.43222799999999,42.337575],"type":"Point"}
}