{
  "type": "Feature",
  "properties": {
    "addr:full":"239 Fuller St Boston MA 02124",
    "addr:housenumber":"239",
    "addr:postcode":"02124",
    "addr:street":"Fuller St",
    "iso:country":"US",
    "sg:address":"239 Fuller St",
    "sg:city":"Boston",
    "sg:classifiers":[
        {
            "category":"Building & Trades",
            "subcategory":"Construction",
            "type":"Services"
        }
    ],
    "sg:phone":"+1   ",
    "sg:postcode":"02124",
    "sg:province":"MA",
    "sg:tags":[
        "contractor",
        "co",
        "hanging"
    ],
    "wof:name":"Frank Harris Jr",
    "wof:placetype":"venue"
},
  "geometry": {"coordinates":[-71.07798699999999,42.280659],"type":"Point"}
}