{
  "type": "Feature",
  "properties": {
    "iso:country":"US",
    "sg:address":"167 E Main St",
    "sg:city":"Hopkinton",
    "sg:classifiers":[
        {
            "category":"Building & Trades",
            "subcategory":"Electrical",
            "type":"Services"
        }
    ],
    "sg:phone":"+1 508 435 7733",
    "sg:postcode":"01748",
    "sg:province":"MA",
    "sg:tags":[
        "installation"
    ],
    "wof:name":"Apollo Installation Svc",
    "wof:placetype":"venue"
},
  "geometry": {"coordinates":[-71.48586299999999,42.241446],"type":"Point"}
}