{
  "type": "Feature",
  "properties": {
    "iso:country":"US",
    "sg:address":"54 Salem St",
    "sg:city":"Andover",
    "sg:classifiers":[
        {
            "category":"Banks & Credit Unions",
            "subcategory":"Investment Brokerage",
            "type":"Services"
        }
    ],
    "sg:phone":"+1 978 474 5034",
    "sg:postcode":"01810",
    "sg:province":"MA",
    "sg:tags":[
        "consultant",
        "planning",
        "financial"
    ],
    "wof:name":"Saunders & Assoc",
    "wof:placetype":"venue"
},
  "geometry": {"coordinates":[-71.125641,42.644862],"type":"Point"}
}