{
  "type": "Feature",
  "properties": {
    "addr:full":"89 Leno Rd Holland MA 01521",
    "addr:housenumber":"89",
    "addr:postcode":"01521",
    "addr:street":"Leno Rd",
    "iso:country":"US",
    "sg:address":"89 Leno Rd",
    "sg:city":"Holland",
    "sg:classifiers":[
        {
            "category":"Professional",
            "subcategory":"Accounting & Tax Preparation",
            "type":"Services"
        }
    ],
    "sg:phone":"+1   ",
    "sg:postcode":"01521",
    "sg:province":"MA",
    "sg:tags":[
        "return"
    ],
    "wof:name":"Roman/Roman Consulting",
    "wof:placetype":"venue"
},
  "geometry": {"coordinates":[-72.15150199999999,42.066891],"type":"Point"}
}