{
  "type": "Feature",
  "properties": {
    "iso:country":"US",
    "sg:address":"89 N Main St",
    "sg:city":"Andover",
    "sg:classifiers":[
        {
            "category":"Shopping",
            "subcategory":"Computers & Home Electronics",
            "type":"Retail Goods"
        }
    ],
    "sg:phone":"+1 978 475 2366",
    "sg:postcode":"01810",
    "sg:province":"MA",
    "sg:tags":[
        "software"
    ],
    "wof:name":"Intelic Software Solutions",
    "wof:placetype":"venue"
},
  "geometry": {"coordinates":[-71.143655,42.660703],"type":"Point"}
}