{
  "type": "Feature",
  "properties": {
    "iso:country":"US",
    "sg:address":"313 Washington St",
    "sg:city":"Newton",
    "sg:classifiers":[
        {
            "category":"Health Services",
            "subcategory":"Health Practitioner",
            "type":"Services"
        }
    ],
    "sg:phone":"+1 617 332 0911",
    "sg:postcode":"02458",
    "sg:province":"MA",
    "sg:tags":[
        "therapist",
        "physical"
    ],
    "wof:name":"Wellesley Therapeutic Svc",
    "wof:placetype":"venue"
},
  "geometry": {"coordinates":[-71.18653,42.357029],"type":"Point"}
}