{
  "type": "Feature",
  "properties": {
    "addr:full": "120 Germano Dr Tewksbury MA 01876",
    "addr:housenumber": "120",
    "addr:postcode": "01876",
    "addr:street": "Germano Dr",
    "iso:country": "US",
    "sg:address": "120 Germano Dr",
    "sg:city": "Tewksbury",
    "sg:classifiers": [
      {
        "category": "Government",
        "subcategory": "Office",
        "type": "Public Place"
      }
    ],
    "sg:phone": "+1 978 851 5807",
    "sg:postcode": "01876",
    "sg:province": "MA",
    "sg:tags": [
      "village"
    ],
    "wof:name": "Tewksbury Town Office",
    "wof:placetype": "venue"
  },
  "geometry": {"coordinates":[-71.237239,42.633583],"type":"Point"}
}
