{
  "type": "Feature",
  "properties": {
    "iso:country":"US",
    "sg:address":"40 Thorndike St",
    "sg:city":"Cambridge",
    "sg:classifiers":[
        {
            "category":"Professional",
            "subcategory":"Business Services",
            "type":"Services"
        }
    ],
    "sg:phone":"+1   ",
    "sg:postcode":"02141",
    "sg:province":"MA",
    "wof:name":"Middlsex Multi Door Courthouse",
    "wof:placetype":"venue"
},
  "geometry": {"coordinates":[-71.079898,42.369514],"type":"Point"}
}