{
  "type": "Feature",
  "properties": {
    "iso:country":"US",
    "sg:address":"1452 Dorchester Ave",
    "sg:city":"Dorchester",
    "sg:classifiers":[
        {
            "category":"Organizations",
            "subcategory":"Non-profit Organization",
            "type":"Services"
        }
    ],
    "sg:phone":"+1 617 825 1917",
    "sg:postcode":"02122",
    "sg:province":"MA",
    "sg:tags":[
        "educational",
        "research"
    ],
    "wof:name":"Peace Institute",
    "wof:placetype":"venue"
},
  "geometry": {"coordinates":[-71.059884,42.301237],"type":"Point"}
}