{
  "type": "Feature",
  "properties": {
    "addr:full":"94 Garden St Needham MA 02492",
    "addr:housenumber":"94",
    "addr:postcode":"02492",
    "addr:street":"Garden St",
    "iso:country":"US",
    "sg:address":"94 Garden St",
    "sg:city":"Needham",
    "sg:classifiers":[
        {
            "category":"Professional",
            "subcategory":"Computer Services",
            "type":"Services"
        }
    ],
    "sg:phone":"+1   ",
    "sg:postcode":"02492",
    "sg:province":"MA",
    "sg:tags":[
        "related"
    ],
    "wof:name":"Interactive Automation Inc",
    "wof:placetype":"venue"
},
  "geometry": {"coordinates":[-71.23706900000001,42.285956],"type":"Point"}
}