{
  "type": "Feature",
  "properties": {
    "iso:country":"US",
    "sg:address":"4 School House Rd",
    "sg:city":"Gloucester",
    "sg:classifiers":[
        {
            "category":"Social Services",
            "subcategory":"Child Care",
            "type":"Services"
        }
    ],
    "sg:phone":"+1 978 281 6920",
    "sg:postcode":"01930",
    "sg:province":"MA",
    "wof:name":"Gloucester Integrated Preschl",
    "wof:placetype":"venue"
},
  "geometry": {"coordinates":[-70.661424,42.623293],"type":"Point"}
}