{
  "type": "Feature",
  "properties": {
    "addr:full":"128 School St Walpole MA 02081",
    "addr:housenumber":"128",
    "addr:postcode":"02081",
    "addr:street":"School St",
    "iso:country":"US",
    "sg:address":"128 School St",
    "sg:city":"Walpole",
    "sg:classifiers":[
        {
            "category":"Professional",
            "subcategory":"Lawyer & Legal Services",
            "type":"Services"
        }
    ],
    "sg:phone":"+1 508 660 2004",
    "sg:postcode":"02081",
    "sg:province":"MA",
    "sg:tags":[
        "attorney"
    ],
    "wof:name":"Van Tine & Assoc",
    "wof:placetype":"venue"
},
  "geometry": {"coordinates":[-71.24914099999999,42.146141],"type":"Point"}
}