{
  "type": "Feature",
  "properties": {
    "iso:country":"US",
    "sg:address":"7 Kensington Rd",
    "sg:city":"Arlington",
    "sg:classifiers":[
        {
            "category":"Retail",
            "subcategory":"Auto Repair",
            "type":"Services"
        }
    ],
    "sg:phone":"+1 978 256 2312",
    "sg:postcode":"02476",
    "sg:province":"MA",
    "sg:tags":[
        "body",
        "automobile",
        "painting"
    ],
    "wof:name":"Mike Fender Design",
    "wof:placetype":"venue"
},
  "geometry": {"coordinates":[-71.163062,42.408908],"type":"Point"}
}