{
  "type": "Feature",
  "properties": {
    "iso:country":"US",
    "sg:address":"160 Boylston St",
    "sg:city":"Boston",
    "sg:classifiers":[
        {
            "category":"Real Estate",
            "subcategory":"Architect",
            "type":"Services"
        }
    ],
    "sg:phone":"+1 617 426 6200",
    "sg:postcode":"02116",
    "sg:province":"MA",
    "wof:name":"Signer Harris Architects",
    "wof:placetype":"venue"
},
  "geometry": {"coordinates":[-71.066362,42.35238],"type":"Point"}
}