{
  "type": "Feature",
  "properties": {
    "iso:country":"US",
    "sg:address":"3 Apple Hill Dr",
    "sg:city":"Natick",
    "sg:classifiers":[
        {
            "category":"Travel",
            "subcategory":"Travel Agent",
            "type":"Entertainment"
        }
    ],
    "sg:phone":"+1 508 650 0400",
    "sg:postcode":"01760",
    "sg:province":"MA",
    "sg:tags":[
        "agency",
        "bureau"
    ],
    "wof:name":"Global Express Travel Systems",
    "wof:placetype":"venue"
},
  "geometry": {"coordinates":[-71.349631,42.300575],"type":"Point"}
}