{
  "type": "Feature",
  "properties": {
    "iso:country":"US",
    "sg:address":"22 Bridge St",
    "sg:city":"Chelmsford",
    "sg:classifiers":[
        {
            "category":"Building & Trades",
            "subcategory":"Construction",
            "type":"Services"
        }
    ],
    "sg:phone":"+1 978 256 4177",
    "sg:postcode":"01824",
    "sg:province":"MA",
    "sg:tags":[
        "contractor"
    ],
    "wof:name":"Emerson Stephen",
    "wof:placetype":"venue"
},
  "geometry": {"coordinates":[-71.3554,42.598],"type":"Point"}
}