{
  "type": "Feature",
  "properties": {
    "iso:country":"US",
    "sg:address":"47 Spring St",
    "sg:city":"Williamstown",
    "sg:classifiers":[
        {
            "category":"Restaurant",
            "type":"Food & Drink"
        }
    ],
    "sg:phone":"+1 413 458 5010",
    "sg:postcode":"01267",
    "sg:province":"MA",
    "sg:tags":[
        "shop",
        "coffee"
    ],
    "wof:name":"Cold Springs Coffee Roasters",
    "wof:placetype":"venue"
},
  "geometry": {"coordinates":[-73.204167,42.710837],"type":"Point"}
}