{
  "type": "Feature",
  "properties": {
    "addr:full": "132 Great Rd Stow MA 01775",
    "addr:housenumber": "132",
    "addr:postcode": "01775",
    "addr:street": "Great Rd",
    "iso:country": "US",
    "sg:address": "132 Great Rd",
    "sg:city": "Stow",
    "sg:classifiers": [
      {
        "category": "Retail",
        "subcategory": "Laundry \u0026 Dry Cleaning",
        "type": "Services"
      }
    ],
    "sg:phone": "+1 978 897 5100",
    "sg:postcode": "01775",
    "sg:province": "MA",
    "sg:tags": [
      "cleaners"
    ],
    "wof:name": "Alpha Alterations \u0026 Cleaners",
    "wof:placetype": "venue"
  },
  "geometry": {"coordinates":[-71.487817,42.433834],"type":"Point"}
}
