{
  "type": "Feature",
  "properties": {
    "addr:full": "43 Witt Hill Rd Worthington MA 01098",
    "addr:housenumber": "43",
    "addr:postcode": "01098",
    "addr:street": "Witt Hill Rd",
    "iso:country": "US",
    "sg:address": "43 Witt Hill Rd",
    "sg:city": "Worthington",
    "sg:classifiers": [
      {
        "category": "Professional",
        "subcategory": "Computer Services",
        "type": "Services"
      }
    ],
    "sg:phone": "+1 413 238 7730",
    "sg:postcode": "01098",
    "sg:province": "MA",
    "wof:name": "B \u0026 H Computer Svc",
    "wof:placetype": "venue"
  },
  "geometry": {"coordinates":[-72.923061,42.378702],"type":"Point"}
}
