{
  "type": "Feature",
  "properties": {
    "addr:full":"29 Caroline Park Waban MA 02468",
    "addr:housenumber":"29",
    "addr:postcode":"02468",
    "addr:street":"Caroline Park",
    "iso:country":"US",
    "sg:address":"29 Caroline Park",
    "sg:city":"Waban",
    "sg:classifiers":[
        {
            "category":"Shopping",
            "subcategory":"Computers & Home Electronics",
            "type":"Retail Goods"
        }
    ],
    "sg:phone":"+1 617 641 0072",
    "sg:postcode":"02468",
    "sg:province":"MA",
    "sg:tags":[
        "software"
    ],
    "wof:name":"RSH Software Inc",
    "wof:placetype":"venue"
},
  "geometry": {"coordinates":[-71.226535,42.332814],"type":"Point"}
}