{
  "type": "Feature",
  "properties": {
    "addr:full": "560 Harrison Ave Boston MA 02118",
    "addr:housenumber": "560",
    "addr:postcode": "02118",
    "addr:street": "Harrison Ave",
    "iso:country": "US",
    "sg:address": "560 Harrison Ave",
    "sg:city": "Boston",
    "sg:classifiers": [
      {
        "category": "Professional",
        "type": "Services"
      }
    ],
    "sg:phone": "+1 617 451 5113",
    "sg:postcode": "02118",
    "sg:province": "MA",
    "sg:tags": [
      "writer"
    ],
    "wof:name": "Libretto",
    "wof:placetype": "venue"
  },
  "geometry": {"coordinates":[-71.067615,42.341087],"type":"Point"}
}
