{
  "type": "Feature",
  "properties": {
    "addr:full":"96 Worcester St North Grafton MA 01536",
    "addr:housenumber":"96",
    "addr:postcode":"01536",
    "addr:street":"Worcester St",
    "iso:country":"US",
    "sg:address":"96 Worcester St",
    "sg:city":"North Grafton",
    "sg:classifiers":[
        {
            "category":"Banks & Credit Unions",
            "subcategory":"Bank",
            "type":"Services"
        }
    ],
    "sg:phone":"+1 508 839 6901",
    "sg:postcode":"01536",
    "sg:province":"MA",
    "wof:name":"Savers Co-Operative Bank",
    "wof:placetype":"venue"
},
  "geometry": {"coordinates":[-71.697069,42.218454],"type":"Point"}
}