{
  "type": "Feature",
  "properties": {
    "addr:full":"27 Naugus Ave Marblehead MA 01945",
    "addr:housenumber":"27",
    "addr:postcode":"01945",
    "addr:street":"Naugus Ave",
    "iso:country":"US",
    "sg:address":"27 Naugus Ave",
    "sg:city":"Marblehead",
    "sg:classifiers":[
        {
            "category":"Communications",
            "subcategory":"Radio Station",
            "type":"Services"
        }
    ],
    "sg:phone":"+1 978 744 1230",
    "sg:postcode":"01945",
    "sg:province":"MA",
    "sg:tags":[
        "company",
        "broadcasting"
    ],
    "wof:name":"North Shore Broadcasting",
    "wof:placetype":"venue"
},
  "geometry": {"coordinates":[-70.86197199999999,42.518528],"type":"Point"}
}