{
  "type": "Feature",
  "properties": {
    "addr:full":"31 Tyngsboro Rd Westford MA 01886",
    "addr:housenumber":"31",
    "addr:postcode":"01886",
    "addr:street":"Tyngsboro Rd",
    "iso:country":"US",
    "sg:address":"31 Tyngsboro Rd",
    "sg:city":"Westford",
    "sg:classifiers":[
        {
            "category":"Professional",
            "subcategory":"Business Services",
            "type":"Services"
        }
    ],
    "sg:phone":"+1   ",
    "sg:postcode":"01886",
    "sg:province":"MA",
    "wof:name":"Budlong Associates",
    "wof:placetype":"venue"
},
  "geometry": {"coordinates":[-71.44234899999999,42.625793],"type":"Point"}
}