{
  "type": "Feature",
  "properties": {
    "addr:full":"165 N Falmouth Hwy North Falmouth MA 02556",
    "addr:housenumber":"165",
    "addr:postcode":"02556",
    "addr:street":"N Falmouth Hwy North",
    "iso:country":"US",
    "sg:address":"165 N Falmouth Hwy",
    "sg:city":"North Falmouth",
    "sg:classifiers":[
        {
            "category":"Retail",
            "subcategory":"Portrait Studio",
            "type":"Services"
        }
    ],
    "sg:phone":"+1 508 548 7032",
    "sg:postcode":"02556",
    "sg:province":"MA",
    "sg:tags":[
        "photography",
        "store"
    ],
    "wof:name":"Green Chris & Elizabeth",
    "wof:placetype":"venue"
},
  "geometry": {"coordinates":[-70.621768,41.62578],"type":"Point"}
}