{
  "type": "Feature",
  "properties": {
    "addr:full": "8 Piedmont Rd Medford MA 02155",
    "addr:housenumber": "8",
    "addr:postcode": "02155",
    "addr:street": "Piedmont Rd",
    "iso:country": "US",
    "sg:address": "8 Piedmont Rd",
    "sg:city": "Medford",
    "sg:classifiers": [
      {
        "category": "Professional",
        "subcategory": "Research",
        "type": "Services"
      }
    ],
    "sg:phone": "+1   ",
    "sg:postcode": "02155",
    "sg:province": "MA",
    "sg:tags": [
      "field",
      "reader"
    ],
    "wof:name": "Lucille Matrascia",
    "wof:placetype": "venue"
  },
  "geometry": {"coordinates":[-71.126027,42.422494],"type":"Point"}
}
