{
  "type": "Feature",
  "properties": {
    "iso:country":"US",
    "sg:address":"928 Park St",
    "sg:city":"Stoughton",
    "sg:classifiers":[
        {
            "category":"Shopping",
            "subcategory":"Florist",
            "type":"Retail Goods"
        }
    ],
    "sg:phone":"+1 781 344 2804",
    "sg:postcode":"02072",
    "sg:province":"MA",
    "sg:website":"www.ftd.com/centralflorist",
    "wof:name":"Central Florist and Nursery",
    "wof:placetype":"venue"
},
  "geometry": {"coordinates":[-71.07399700000001,42.111801],"type":"Point"}
}