{
  "type": "Feature",
  "properties": {
    "addr:full": "928 Park St Stoughton MA 02072",
    "addr:housenumber": "928",
    "addr:postcode": "02072",
    "addr:street": "Park St",
    "iso:country": "US",
    "ovtr:label": "Central Florist \u0026 Nursery, 928 Park St Stoughton MA US",
    "ovtr:similarity": 2.701411008834839,
    "sg:address": "928 Park St",
    "sg:city": "Stoughton",
    "sg:classifiers": [
      {
        "category": "Shopping",
        "subcategory": "Florist",
        "type": "Retail Goods"
      }
    ],
    "sg:phone": "+1 781 344 2804",
    "sg:postcode": "02072",
    "sg:province": "MA",
    "sg:website": "www.ftd.com/centralflorist",
    "wof:name": "Central Florist and Nursery",
    "wof:placetype": "venue"
  },
  "geometry": {"coordinates":[-71.073997,42.111801],"type":"Point"}
}
