{
  "type": "Feature",
  "properties": {
    "iso:country":"US",
    "sg:address":"24 Sleepy Hollow Dr",
    "sg:city":"Plymouth",
    "sg:classifiers":[
        {
            "category":"Shopping",
            "subcategory":"Used Merchandise",
            "type":"Retail Goods"
        }
    ],
    "sg:phone":"+1   ",
    "sg:postcode":"02360",
    "sg:province":"MA",
    "wof:name":"Short Takes Antique",
    "wof:placetype":"venue"
},
  "geometry": {"coordinates":[-70.691819,41.942581],"type":"Point"}
}