{
  "type": "Feature",
  "properties": {
    "iso:country":"US",
    "sg:address":"126 Central Ave",
    "sg:city":"Seekonk",
    "sg:classifiers":[
        {
            "category":"Building & Trades",
            "subcategory":"Construction",
            "type":"Services"
        }
    ],
    "sg:phone":"+1   ",
    "sg:postcode":"02771",
    "sg:province":"MA",
    "sg:tags":[
        "carpentry",
        "contractor"
    ],
    "wof:name":"Lustre Aluminum Products",
    "wof:placetype":"venue"
},
  "geometry": {"coordinates":[-71.334137,41.889168],"type":"Point"}
}