{
  "type": "Feature",
  "properties": {
    "iso:country":"US",
    "sg:address":"175 High St",
    "sg:city":"Waltham",
    "sg:classifiers":[
        {
            "category":"Taxi",
            "type":"Transportation"
        }
    ],
    "sg:phone":"+1 617 527 0300",
    "sg:postcode":"02453",
    "sg:province":"MA",
    "sg:tags":[
        "taxicab",
        "airport"
    ],
    "sg:website":"http://www.veteranstaxi.com",
    "wof:name":"Veterans Taxi",
    "wof:placetype":"venue"
},
  "geometry": {"coordinates":[-71.22956499999999,42.366074],"type":"Point"}
}