{
  "type": "Feature",
  "properties": {
    "iso:country":"US",
    "sg:address":"793 Iyannough Rd",
    "sg:city":"Hyannis",
    "sg:classifiers":[
        {
            "category":"Shopping",
            "subcategory":"Clothing, Apparel, & Fashions",
            "type":"Retail Goods"
        }
    ],
    "sg:phone":"+1 508 778 2750",
    "sg:postcode":"02601",
    "sg:province":"MA",
    "sg:website":"www.wetseal.com",
    "wof:name":"Wet Seal",
    "wof:placetype":"venue"
},
  "geometry": {"coordinates":[-70.297163,41.66935],"type":"Point"}
}