{
  "type": "Feature",
  "properties": {
    "iso:country":"US",
    "sg:address":"607 Franklin St",
    "sg:city":"Cambridge",
    "sg:classifiers":[
        {
            "category":"Retail",
            "subcategory":"Portrait Studio",
            "type":"Services"
        },
        {
            "category":"Professional",
            "subcategory":"Art Services",
            "type":"Services"
        }
    ],
    "sg:phone":"+1 617 876 6416",
    "sg:postcode":"02139",
    "sg:province":"MA",
    "sg:tags":[
        "photographer",
        "photography",
        "store"
    ],
    "wof:name":"Dorfman Elsa Photography",
    "wof:placetype":"venue"
},
  "geometry": {"coordinates":[-71.111099,42.367599],"type":"Point"}
}