{
  "type": "Feature",
  "properties": {
    "addr:full":"283 Bay Rd Hadley MA 01035",
    "addr:housenumber":"283",
    "addr:postcode":"01035",
    "addr:street":"Bay Rd",
    "iso:country":"US",
    "sg:address":"283 Bay Rd",
    "sg:city":"Hadley",
    "sg:classifiers":[
        {
            "category":"Retail",
            "subcategory":"Animal Services",
            "type":"Services"
        }
    ],
    "sg:phone":"+1 413 584 6479",
    "sg:postcode":"01035",
    "sg:province":"MA",
    "wof:name":"Hampshire Stables",
    "wof:placetype":"venue"
},
  "geometry": {"coordinates":[-72.544586,42.31998],"type":"Point"}
}