{
  "type": "Feature",
  "properties": {
    "iso:country":"US",
    "sg:address":"5 Fillmore Dr",
    "sg:city":"Billerica",
    "sg:classifiers":[
        {
            "category":"Building & Trades",
            "subcategory":"Electrical",
            "type":"Services"
        }
    ],
    "sg:phone":"+1 978 670 1372",
    "sg:postcode":"01821",
    "sg:province":"MA",
    "sg:tags":[
        "electrician"
    ],
    "wof:name":"Michael Cataldo Electric",
    "wof:placetype":"venue"
},
  "geometry": {"coordinates":[-71.222802,42.5721],"type":"Point"}
}