{
  "type": "Feature",
  "properties": {
    "addr:full":"48 Rte 130 Sandwich MA 02563",
    "addr:housenumber":"48",
    "addr:postcode":"02563",
    "addr:street":"Rte 130",
    "iso:country":"US",
    "sg:address":"48 Rte 130",
    "sg:city":"Sandwich",
    "sg:classifiers":[
        {
            "category":"Shopping",
            "subcategory":"Bicycles & Sporting Goods",
            "type":"Retail Goods"
        }
    ],
    "sg:phone":"+1 508 539 8952",
    "sg:postcode":"02563",
    "sg:province":"MA",
    "wof:name":"Forestdale Bait & Tackle",
    "wof:placetype":"venue"
},
  "geometry": {"coordinates":[-70.51639,41.761953],"type":"Point"}
}