{
  "type": "Feature",
  "properties": {
    "iso:country":"US",
    "sg:address":"492 Cabot St",
    "sg:city":"Beverly",
    "sg:classifiers":[
        {
            "category":"Shopping",
            "subcategory":"Clothing, Apparel, & Fashions",
            "type":"Retail Goods"
        }
    ],
    "sg:phone":"+1 978 927 1516",
    "sg:postcode":"01915",
    "sg:province":"MA",
    "sg:tags":[
        "tailor"
    ],
    "wof:name":"Zeke's Tailoring",
    "wof:placetype":"venue"
},
  "geometry": {"coordinates":[-70.88535299999999,42.564748],"type":"Point"}
}