{
  "type": "Feature",
  "properties": {
    "addr:full": "492 Cabot St Beverly MA 01915",
    "addr:housenumber": "492",
    "addr:postcode": "01915",
    "addr:street": "Cabot St",
    "iso:country": "US",
    "sg:address": "492 Cabot St",
    "sg:city": "Beverly",
    "sg:classifiers": [
      {
        "category": "Shopping",
        "subcategory": "Clothing, Apparel, \u0026 Fashions",
        "type": "Retail Goods"
      }
    ],
    "sg:phone": "+1 978 927 1516",
    "sg:postcode": "01915",
    "sg:province": "MA",
    "sg:tags": [
      "tailor"
    ],
    "wof:name": "Zeke's Tailoring",
    "wof:placetype": "venue"
  },
  "geometry": {"coordinates":[-70.885353,42.564748],"type":"Point"}
}
