{
  "type": "Feature",
  "properties": {
    "iso:country":"US",
    "sg:address":"24 Presidential Dr",
    "sg:city":"Quincy",
    "sg:classifiers":[
        {
            "category":"Home & Garden",
            "subcategory":"Household Appliances",
            "type":"Retail Goods"
        },
        {
            "category":"Retail",
            "subcategory":"Repair Shop",
            "type":"Services"
        }
    ],
    "sg:phone":"+1 617 479 3400",
    "sg:postcode":"02169",
    "sg:province":"MA",
    "sg:tags":[
        "small",
        "major",
        "refinishing",
        "appliances-small"
    ],
    "wof:name":"Allied Appliance Service",
    "wof:placetype":"venue"
},
  "geometry": {"coordinates":[-70.982646,42.240316],"type":"Point"}
}