{
  "type": "Feature",
  "properties": {
    "iso:country":"US",
    "sg:address":"3 Patterson Rd",
    "sg:city":"Shirley",
    "sg:classifiers":[
        {
            "category":"Manufacturing",
            "subcategory":"Buildings",
            "type":"Manufacturing & Wholesale Goods"
        },
        {
            "category":"Building & Trades",
            "subcategory":"Construction",
            "type":"Services"
        }
    ],
    "sg:phone":"+1 978 425 3100",
    "sg:postcode":"01464",
    "sg:province":"MA",
    "sg:tags":[
        "home",
        "builder",
        "contractor"
    ],
    "wof:name":"Home Locator Network",
    "wof:placetype":"venue"
},
  "geometry": {"coordinates":[-71.625247,42.551588],"type":"Point"}
}