{
  "type": "Feature",
  "properties": {
    "addr:full":"125 Cross Neck Rd Marion MA 02738",
    "addr:housenumber":"125",
    "addr:postcode":"02738",
    "addr:street":"Cross Neck Rd",
    "iso:country":"US",
    "sg:address":"125 Cross Neck Rd",
    "sg:city":"Marion",
    "sg:classifiers":[
        {
            "category":"Marine",
            "type":"Transportation"
        }
    ],
    "sg:phone":"+1   ",
    "sg:postcode":"02738",
    "sg:province":"MA",
    "sg:tags":[
        "water",
        "transport"
    ],
    "wof:name":"Xanadu Yacht Corporation",
    "wof:placetype":"venue"
},
  "geometry": {"coordinates":[-70.742076,41.714629],"type":"Point"}
}