{
  "type": "Feature",
  "properties": {
    "iso:country":"US",
    "sg:address":"7 Witchcraft Rd",
    "sg:city":"Salem",
    "sg:classifiers":[
        {
            "category":"Building & Trades",
            "subcategory":"Construction",
            "type":"Services"
        }
    ],
    "sg:phone":"+1 978 531 7283",
    "sg:postcode":"01970",
    "sg:province":"MA",
    "sg:tags":[
        "house",
        "general",
        "contractor"
    ],
    "wof:name":"George Glynos & Construction",
    "wof:placetype":"venue"
},
  "geometry": {"coordinates":[-70.918496,42.518149],"type":"Point"}
}