{
  "type": "Feature",
  "properties": {
    "addr:full":"54 Clemente St Holyoke MA 01040",
    "addr:housenumber":"54",
    "addr:postcode":"01040",
    "addr:street":"Clemente St",
    "iso:country":"US",
    "sg:address":"54 Clemente St",
    "sg:city":"Holyoke",
    "sg:classifiers":[
        {
            "category":"Retail",
            "subcategory":"Auto Repair",
            "type":"Services"
        }
    ],
    "sg:phone":"+1 413 533 7813",
    "sg:postcode":"01040",
    "sg:province":"MA",
    "sg:tags":[
        "wrecker"
    ],
    "wof:name":"L & M Towing & Auto",
    "wof:placetype":"venue"
},
  "geometry": {"coordinates":[-72.605868,42.199849],"type":"Point"}
}