{
  "type": "Feature",
  "properties": {
    "addr:full": "129 Concord St Framingham MA 01702",
    "addr:housenumber": "129",
    "addr:postcode": "01702",
    "addr:street": "Concord St",
    "iso:country": "US",
    "sg:address": "129 Concord St",
    "sg:city": "Framingham",
    "sg:classifiers": [
      {
        "category": "Shopping",
        "subcategory": "Clothing, Apparel, \u0026 Fashions",
        "type": "Retail Goods"
      }
    ],
    "sg:phone": "+1 508 879 0057",
    "sg:postcode": "01702",
    "sg:province": "MA",
    "wof:name": "Karen Fashion",
    "wof:placetype": "venue"
  },
  "geometry": {"coordinates":[-71.416675,42.278866],"type":"Point"}
}
