{
  "type": "Feature",
  "properties": {
    "addr:full": "105 Huntington Ave Boston MA 02199",
    "addr:housenumber": "105",
    "addr:postcode": "02199",
    "addr:street": "Huntington Ave",
    "iso:country": "US",
    "sg:address": "105 Huntington Ave",
    "sg:city": "Boston",
    "sg:classifiers": [
      {
        "category": "Restaurant",
        "type": "Food \u0026 Drink"
      }
    ],
    "sg:menulink": "http://www.allmenus.com/ma/boston/53-applebees/menu/",
    "sg:phone": "+1 617 424 7780",
    "sg:postcode": "02199",
    "sg:province": "MA",
    "sg:tags": [
      "american"
    ],
    "wof:name": "Applebee's",
    "wof:placetype": "venue"
  },
  "geometry": {"coordinates":[-71.080764,42.34634],"type":"Point"}
}
