{
  "type": "Feature",
  "properties": {
    "addr:full":"599 Centre St Brockton MA 02302",
    "addr:housenumber":"599",
    "addr:postcode":"02302",
    "addr:street":"Centre St",
    "iso:country":"US",
    "sg:address":"599 Centre St",
    "sg:city":"Brockton",
    "sg:classifiers":[
        {
            "category":"Manufacturing",
            "subcategory":"Printing",
            "type":"Manufacturing & Wholesale Goods"
        }
    ],
    "sg:phone":"+1 508 587 6200",
    "sg:postcode":"02302",
    "sg:province":"MA",
    "sg:tags":[
        "printer"
    ],
    "wof:name":"Minuteman Press",
    "wof:placetype":"venue"
},
  "geometry": {"coordinates":[-70.995153,42.085649],"type":"Point"}
}