{
  "type": "Feature",
  "properties": {
    "iso:country":"US",
    "sg:address":"38 Gerrish Rd",
    "sg:city":"Rochester",
    "sg:classifiers":[
        {
            "category":"Professional",
            "type":"Services"
        }
    ],
    "sg:phone":"+1 508 763 9333",
    "sg:postcode":"02770",
    "sg:province":"MA",
    "sg:tags":[
        "establishment"
    ],
    "wof:name":"Jet Expediting Inc",
    "wof:placetype":"venue"
},
  "geometry": {"coordinates":[-70.86574899999999,41.787335],"type":"Point"}
}