{
  "type": "Feature",
  "properties": {
    "iso:country":"US",
    "sg:address":"192 Bennington St",
    "sg:city":"Boston",
    "sg:classifiers":[
        {
            "category":"Retail",
            "subcategory":"Repair Shop",
            "type":"Services"
        }
    ],
    "sg:phone":"+1 617 567 8108",
    "sg:postcode":"02128",
    "sg:province":"MA",
    "sg:tags":[
        "equipment",
        "electronic",
        "supply"
    ],
    "wof:name":"Malu Solutions",
    "wof:placetype":"venue"
},
  "geometry": {"coordinates":[-71.032899,42.377022],"type":"Point"}
}