{
  "type": "Feature",
  "properties": {
    "addr:full": "129 High St Jefferson MA 01522",
    "addr:housenumber": "129",
    "addr:postcode": "01522",
    "addr:street": "High St",
    "iso:country": "US",
    "sg:address": "129 High St",
    "sg:city": "Jefferson",
    "sg:classifiers": [
      {
        "category": "Shopping",
        "subcategory": "Gifts \u0026 Souvenirs",
        "type": "Retail Goods"
      }
    ],
    "sg:phone": "+1   ",
    "sg:postcode": "01522",
    "sg:province": "MA",
    "wof:name": "Autographs Collectibles Etc",
    "wof:placetype": "venue"
  },
  "geometry": {"coordinates":[-71.876326,42.356324],"type":"Point"}
}
