{
  "type": "Feature",
  "properties": {
    "iso:country":"US",
    "sg:address":"129 High St",
    "sg:city":"Jefferson",
    "sg:classifiers":[
        {
            "category":"Shopping",
            "subcategory":"Gifts & Souvenirs",
            "type":"Retail Goods"
        }
    ],
    "sg:phone":"+1   ",
    "sg:postcode":"01522",
    "sg:province":"MA",
    "wof:name":"Autographs Collectibles Etc",
    "wof:placetype":"venue"
},
  "geometry": {"coordinates":[-71.87632600000001,42.356324],"type":"Point"}
}