{
  "type": "Feature",
  "properties": {
    "addr:full": "32 Maple St Danvers MA 01923",
    "addr:housenumber": "32",
    "addr:postcode": "01923",
    "addr:street": "Maple St",
    "iso:country": "US",
    "sg:address": "32 Maple St",
    "sg:city": "Danvers",
    "sg:classifiers": [
      {
        "category": "Health Services",
        "subcategory": "Chiropractor",
        "type": "Services"
      }
    ],
    "sg:phone": "+1 978 774 8844",
    "sg:postcode": "01923",
    "sg:province": "MA",
    "wof:name": "Danvers Chiropractic Ctr",
    "wof:placetype": "venue"
  },
  "geometry": {"coordinates":[-70.936413,42.566319],"type":"Point"}
}
