{
  "type": "Feature",
  "properties": {
    "addr:full":"407 US Hwy 44 Raynham MA 02767",
    "addr:housenumber":"407",
    "addr:postcode":"02767",
    "addr:street":"Us Hwy 44",
    "iso:country":"US",
    "sg:address":"407 US Hwy 44",
    "sg:city":"Raynham",
    "sg:classifiers":[
        {
            "category":"Personal",
            "type":"Services"
        }
    ],
    "sg:phone":"+1   ",
    "sg:postcode":"02767",
    "sg:province":"MA",
    "wof:name":"Tux Town Tuxedos By Roberts",
    "wof:placetype":"venue"
},
  "geometry": {"coordinates":[-71.048912,41.906121],"type":"Point"}
}