{
  "type": "Feature",
  "properties": {
    "addr:full": "10 Village Green Ln Natick MA 01760",
    "addr:housenumber": "10",
    "addr:postcode": "01760",
    "addr:street": "Village Green Ln",
    "iso:country": "US",
    "sg:address": "10 Village Green Ln",
    "sg:city": "Natick",
    "sg:classifiers": [
      {
        "category": "Professional",
        "subcategory": "Business Services",
        "type": "Services"
      }
    ],
    "sg:phone": "+1 508 655 3949",
    "sg:postcode": "01760",
    "sg:province": "MA",
    "sg:tags": [
      "organizing"
    ],
    "sg:website": "www.sortitoutnow.com",
    "wof:name": "Sort It Out",
    "wof:placetype": "venue"
  },
  "geometry": {"coordinates":[-71.391637,42.281231],"type":"Point"}
}
