{
  "type": "Feature",
  "properties": {
    "addr:full":"121 Beach St Boston MA 02111",
    "addr:housenumber":"121",
    "addr:postcode":"02111",
    "addr:street":"Beach St",
    "iso:country":"US",
    "sg:address":"121 Beach St",
    "sg:city":"Boston",
    "sg:classifiers":[
        {
            "category":"Wholesale",
            "subcategory":"Chemicals & Plastics",
            "type":"Manufacturing & Wholesale Goods"
        }
    ],
    "sg:phone":"+1 617 423 6260",
    "sg:postcode":"02111",
    "sg:province":"MA",
    "wof:name":"Crown Plastics Corp",
    "wof:placetype":"venue"
},
  "geometry": {"coordinates":[-71.057588,42.350649],"type":"Point"}
}