{
  "type": "Feature",
  "properties": {
    "iso:country":"US",
    "sg:address":"132 Mirick Rd",
    "sg:city":"Princeton",
    "sg:classifiers":[
        {
            "category":"Real Estate",
            "subcategory":"Architect",
            "type":"Services"
        }
    ],
    "sg:phone":"+1 978 464 2360",
    "sg:postcode":"01541",
    "sg:province":"MA",
    "wof:name":"Russell Swinton Oatman Design",
    "wof:placetype":"venue"
},
  "geometry": {"coordinates":[-71.873609,42.472479],"type":"Point"}
}