{
  "type": "Feature",
  "properties": {
    "addr:full":"40 Congress St Springfield MA 01104",
    "addr:housenumber":"40",
    "addr:postcode":"01104",
    "addr:street":"Congress St",
    "iso:country":"US",
    "sg:address":"40 Congress St",
    "sg:city":"Springfield",
    "sg:classifiers":[
        {
            "category":"Personal",
            "type":"Services"
        },
        {
            "category":"Retail",
            "subcategory":"Storage",
            "type":"Services"
        }
    ],
    "sg:phone":"+1 866 320 6309",
    "sg:postcode":"01104",
    "sg:province":"MA",
    "sg:tags":[
        "self",
        "full",
        "commercial",
        "mover",
        "household"
    ],
    "sg:website":"http://www.unclebobs.com/stores/UB280/?source=Yellowpages.com&howheard=ISM",
    "wof:name":"Uncle Bob's Self Storage",
    "wof:placetype":"venue"
},
  "geometry": {"coordinates":[-72.596386,42.107422],"type":"Point"}
}