{
  "type": "Feature",
  "properties": {
    "iso:country":"US",
    "sg:address":"9 Eleanor Rd",
    "sg:city":"Walpole",
    "sg:classifiers":[
        {
            "category":"Building & Trades",
            "subcategory":"Construction",
            "type":"Services"
        }
    ],
    "sg:phone":"+1   ",
    "sg:postcode":"02081",
    "sg:province":"MA",
    "sg:tags":[
        "carpentry",
        "contractor"
    ],
    "wof:name":"Paul F Doolan Carpentry Inc",
    "wof:placetype":"venue"
},
  "geometry": {"coordinates":[-71.239942,42.127068],"type":"Point"}
}