{
  "type": "Feature",
  "properties": {
    "addr:full": "22 Chestnut Pl Apt 612 Brookline MA 02445",
    "addr:housenumber": "22;612",
    "addr:postcode": "02445",
    "addr:street": "Chestnut Pl Apt",
    "iso:country": "US",
    "sg:address": "22 Chestnut Pl Apt 612",
    "sg:city": "Brookline",
    "sg:classifiers": [
      {
        "category": "Professional",
        "subcategory": "Business Services",
        "type": "Services"
      }
    ],
    "sg:phone": "+1 617 232 7469",
    "sg:postcode": "02445",
    "sg:province": "MA",
    "sg:tags": [
      "holding"
    ],
    "wof:name": "Petra Holdings Intl",
    "wof:placetype": "venue"
  },
  "geometry": {"coordinates":[-71.126715,42.326539],"type":"Point"}
}
