{
  "type": "Feature",
  "properties": {
    "iso:country":"US",
    "sg:address":"22 Chestnut Pl Apt 612",
    "sg:city":"Brookline",
    "sg:classifiers":[
        {
            "category":"Professional",
            "subcategory":"Business Services",
            "type":"Services"
        }
    ],
    "sg:phone":"+1 617 232 7469",
    "sg:postcode":"02445",
    "sg:province":"MA",
    "sg:tags":[
        "holding"
    ],
    "wof:name":"Petra Holdings Intl",
    "wof:placetype":"venue"
},
  "geometry": {"coordinates":[-71.126715,42.326539],"type":"Point"}
}