{
  "type": "Feature",
  "properties": {
    "addr:full": "189 Russell St Hadley MA 01035",
    "addr:housenumber": "189",
    "addr:postcode": "01035",
    "addr:street": "Russell St",
    "iso:country": "US",
    "sg:address": "189 Russell St",
    "sg:city": "Hadley",
    "sg:classifiers": [
      {
        "category": "Restaurant",
        "type": "Food \u0026 Drink"
      }
    ],
    "sg:phone": "+1 413 586 9800",
    "sg:postcode": "01035",
    "sg:province": "MA",
    "sg:tags": [
      "eating"
    ],
    "wof:name": "Olde Hadleigh Grille Inc",
    "wof:placetype": "venue"
  },
  "geometry": {"coordinates":[-72.575684,42.345396],"type":"Point"}
}
