{
  "type": "Feature",
  "properties": {
    "addr:full": "27 Cambridge St Ste 200 Burlington MA 01803",
    "addr:housenumber": "27",
    "addr:postcode": "01803",
    "addr:street": "Cambridge St Ste 200",
    "iso:country": "US",
    "sg:address": "27 Cambridge St Ste 200",
    "sg:city": "Burlington",
    "sg:classifiers": [
      {
        "category": "Real Estate",
        "subcategory": "Real Estate Services",
        "type": "Services"
      }
    ],
    "sg:phone": "+1 781 273 1000",
    "sg:postcode": "01803",
    "sg:province": "MA",
    "sg:tags": [
      "management",
      "property"
    ],
    "wof:name": "Murray's Real Estate - CLOSED",
    "wof:placetype": "venue"
  },
  "geometry": {"coordinates":[-71.188599,42.483101],"type":"Point"}
}
