{
  "type": "Feature",
  "properties": {
    "iso:country":"US",
    "sg:address":"524 W Central St",
    "sg:city":"Franklin",
    "sg:classifiers":[
        {
            "category":"Shopping",
            "subcategory":"Stationery & Office Supplies",
            "type":"Retail Goods"
        },
        {
            "category":"Shopping",
            "subcategory":"Gifts & Souvenirs",
            "type":"Retail Goods"
        }
    ],
    "sg:phone":"+1 508 528 0977",
    "sg:postcode":"02038",
    "sg:province":"MA",
    "sg:tags":[
        "shop",
        "store"
    ],
    "wof:name":"Terrazza",
    "wof:placetype":"venue"
},
  "geometry": {"coordinates":[-71.42122500000001,42.09056],"type":"Point"}
}