{
  "type": "Feature",
  "properties": {
    "addr:full": "407 Mystic Ave Medford MA 02155",
    "addr:housenumber": "407",
    "addr:postcode": "02155",
    "addr:street": "Mystic Ave",
    "iso:country": "US",
    "sg:address": "407 Mystic Ave",
    "sg:city": "Medford",
    "sg:classifiers": [
      {
        "category": "Professional",
        "subcategory": "Engineering",
        "type": "Services"
      }
    ],
    "sg:phone": "+1 781 391 5757",
    "sg:postcode": "02155",
    "sg:province": "MA",
    "sg:tags": [
      "engineer"
    ],
    "sg:website": "www.greenintl.com",
    "wof:name": "Green International Affiliates",
    "wof:placetype": "venue"
  },
  "geometry": {"coordinates":[-71.09793,42.401701],"type":"Point"}
}
