{
  "type": "Feature",
  "properties": {
    "iso:country":"US",
    "sg:address":"6 Royal Cir",
    "sg:city":"Lexington",
    "sg:classifiers":[
        {
            "category":"Professional",
            "type":"Services"
        }
    ],
    "sg:phone":"+1   ",
    "sg:postcode":"02420",
    "sg:province":"MA",
    "sg:tags":[
        "recording",
        "consulting",
        "production",
        "business"
    ],
    "wof:name":"Ongaku Records",
    "wof:placetype":"venue"
},
  "geometry": {"coordinates":[-71.238533,42.474992],"type":"Point"}
}