{
  "type": "Feature",
  "properties": {
    "iso:country":"US",
    "sg:address":"218 Lumber St",
    "sg:city":"Hopkinton",
    "sg:classifiers":[
        {
            "category":"Building & Trades",
            "subcategory":"Construction",
            "type":"Services"
        }
    ],
    "sg:phone":"+1 508 435 8552",
    "sg:postcode":"01748",
    "sg:province":"MA",
    "sg:tags":[
        "concrete",
        "contractor"
    ],
    "wof:name":"Eastern Concrete Co",
    "wof:placetype":"venue"
},
  "geometry": {"coordinates":[-71.524621,42.196985],"type":"Point"}
}