{
  "type": "Feature",
  "properties": {
    "addr:full": "55 Amy Ln Holliston MA 01746",
    "addr:housenumber": "55",
    "addr:postcode": "01746",
    "addr:street": "Amy Ln",
    "iso:country": "US",
    "sg:address": "55 Amy Ln",
    "sg:city": "Holliston",
    "sg:classifiers": [
      {
        "category": "Professional",
        "subcategory": "Business Services",
        "type": "Services"
      }
    ],
    "sg:phone": "+1 508 429 3151",
    "sg:postcode": "01746",
    "sg:province": "MA",
    "sg:tags": [
      "commercial",
      "real estate"
    ],
    "wof:name": "Harmony Enterprises",
    "wof:placetype": "venue"
  },
  "geometry": {"coordinates":[-71.462346,42.178988],"type":"Point"}
}
