{
  "type": "Feature",
  "properties": {
    "iso:country":"US",
    "sg:address":"8 Pepper Ln",
    "sg:city":"Harwich",
    "sg:classifiers":[
        {
            "category":"Building & Trades",
            "subcategory":"Landscaping Services",
            "type":"Services"
        }
    ],
    "sg:phone":"+1 508 432 4166",
    "sg:postcode":"02645",
    "sg:province":"MA",
    "sg:tags":[
        "landscape",
        "contractor"
    ],
    "wof:name":"Gregory Small Landscaping",
    "wof:placetype":"venue"
},
  "geometry": {"coordinates":[-70.119332,41.696795],"type":"Point"}
}