{
  "type": "Feature",
  "properties": {
    "addr:full":"32 Northern Ave Northampton MA 01060",
    "addr:housenumber":"32",
    "addr:postcode":"01060",
    "addr:street":"Northern Ave",
    "iso:country":"US",
    "sg:address":"32 Northern Ave",
    "sg:city":"Northampton",
    "sg:classifiers":[
        {
            "category":"Professional",
            "subcategory":"Computer Services",
            "type":"Services"
        }
    ],
    "sg:phone":"+1   ",
    "sg:postcode":"01060",
    "sg:province":"MA",
    "sg:tags":[
        "related"
    ],
    "wof:name":"Micro Computer Consulting",
    "wof:placetype":"venue"
},
  "geometry": {"coordinates":[-72.629274,42.329802],"type":"Point"}
}