{
  "type": "Feature",
  "properties": {
    "addr:full": "309 Rantoul St Beverly MA 01915",
    "addr:housenumber": "309",
    "addr:postcode": "01915",
    "addr:street": "Rantoul St",
    "iso:country": "US",
    "sg:address": "309 Rantoul St",
    "sg:city": "Beverly",
    "sg:classifiers": [
      {
        "category": "Home \u0026 Garden",
        "subcategory": "Building Materials",
        "type": "Retail Goods"
      }
    ],
    "sg:phone": "+1 978 922 5579",
    "sg:postcode": "01915",
    "sg:province": "MA",
    "sg:tags": [
      "windows"
    ],
    "wof:name": "Laughlin Contracting Inc",
    "wof:placetype": "venue"
  },
  "geometry": {"coordinates":[-70.882708,42.551747],"type":"Point"}
}
