{
  "type": "Feature",
  "properties": {
    "iso:country":"US",
    "sg:address":"3 Swampscott Ave",
    "sg:city":"Peabody",
    "sg:classifiers":[
        {
            "category":"Education",
            "subcategory":"School",
            "type":"Public Place"
        }
    ],
    "sg:phone":"+1 978 531 1600",
    "sg:postcode":"01960",
    "sg:province":"MA",
    "wof:name":"William E Welch Senior School",
    "wof:placetype":"venue"
},
  "geometry": {"coordinates":[-70.933099,42.520575],"type":"Point"}
}