{
  "type": "Feature",
  "properties": {
    "iso:country":"US",
    "sg:address":"82 Burlington Mall Rd",
    "sg:city":"Burlington",
    "sg:classifiers":[
        {
            "category":"Shopping",
            "subcategory":"Bicycles & Sporting Goods",
            "type":"Retail Goods"
        }
    ],
    "sg:phone":"+1 781 272 4083",
    "sg:postcode":"01803",
    "sg:province":"MA",
    "sg:tags":[
        "equipment",
        "exercise"
    ],
    "wof:name":"Omni Fitness Equip Specialists",
    "wof:placetype":"venue"
},
  "geometry": {"coordinates":[-71.210838,42.486001],"type":"Point"}
}