{
  "type": "Feature",
  "properties": {
    "iso:country":"US",
    "sg:address":"432 Hildreth St Unit 4",
    "sg:city":"Lowell",
    "sg:classifiers":[
        {
            "category":"Real Estate",
            "subcategory":"Real Estate Operator",
            "type":"Services"
        }
    ],
    "sg:phone":"+1 978 455 6293",
    "sg:postcode":"01850",
    "sg:province":"MA",
    "sg:tags":[
        "apartment"
    ],
    "wof:name":"Hildreth Street Townhouses",
    "wof:placetype":"venue"
},
  "geometry": {"coordinates":[-71.307652,42.658295],"type":"Point"}
}