{
  "type": "Feature",
  "properties": {
    "addr:full":"177 Lake View Ave Cambridge MA 02138",
    "addr:housenumber":"177",
    "addr:postcode":"02138",
    "addr:street":"Lake View Ave",
    "iso:country":"US",
    "sg:address":"177 Lake View Ave",
    "sg:city":"Cambridge",
    "sg:classifiers":[
        {
            "category":"Education",
            "subcategory":"Special Training",
            "type":"Public Place"
        }
    ],
    "sg:phone":"+1   ",
    "sg:postcode":"02138",
    "sg:province":"MA",
    "sg:tags":[
        "educational"
    ],
    "wof:name":"Paula Leoni-Bacchus",
    "wof:placetype":"venue"
},
  "geometry": {"coordinates":[-71.140007,42.380935],"type":"Point"}
}