{
  "type": "Feature",
  "properties": {
    "iso:country":"US",
    "sg:address":"7 Clapboardtree St",
    "sg:city":"Westwood",
    "sg:classifiers":[
        {
            "category":"Organizations",
            "subcategory":"Religious Organization",
            "type":"Services"
        }
    ],
    "sg:phone":"+1 781 769 5270",
    "sg:postcode":"02090",
    "sg:province":"MA",
    "sg:tags":[
        "synagogue"
    ],
    "sg:website":"www.templebethdavid.homestead.com",
    "wof:name":"Temple Beth David",
    "wof:placetype":"venue"
},
  "geometry": {"coordinates":[-71.226097,42.2085],"type":"Point"}
}