{
  "type": "Feature",
  "properties": {
    "addr:full":"1199 W Central St Franklin MA 02038",
    "addr:housenumber":"1199",
    "addr:postcode":"02038",
    "addr:street":"W Central St",
    "iso:country":"US",
    "sg:address":"1199 W Central St",
    "sg:city":"Franklin",
    "sg:classifiers":[
        {
            "category":"Retail",
            "subcategory":"Auto Rental",
            "type":"Services"
        }
    ],
    "sg:phone":"+1 508 520 3327",
    "sg:postcode":"02038",
    "sg:province":"MA",
    "sg:tags":[
        "renting",
        "truck",
        "leasing"
    ],
    "wof:name":"Budget Truck Rental",
    "wof:placetype":"venue"
},
  "geometry": {"coordinates":[-71.444536,42.086474],"type":"Point"}
}