{
  "type": "Feature",
  "properties": {
    "addr:full":"44 Green River Way Watertown MA 02472",
    "addr:housenumber":"44",
    "addr:postcode":"02472",
    "addr:street":"Green River Way",
    "iso:country":"US",
    "sg:address":"44 Green River Way",
    "sg:city":"Watertown",
    "sg:classifiers":[
        {
            "category":"Home & Garden",
            "subcategory":"Building Materials",
            "type":"Retail Goods"
        }
    ],
    "sg:phone":"+1 617 923 9700",
    "sg:postcode":"02472",
    "sg:province":"MA",
    "sg:tags":[
        "door"
    ],
    "sg:website":"www.wdiinc.com",
    "wof:name":"Wholesale Doors Inc",
    "wof:placetype":"venue"
},
  "geometry": {"coordinates":[-71.207672,42.367967],"type":"Point"}
}