{
  "type": "Feature",
  "properties": {
    "addr:full":"8 Chatham Rd Andover MA 01810",
    "addr:housenumber":"8",
    "addr:postcode":"01810",
    "addr:street":"Chatham Rd",
    "iso:country":"US",
    "sg:address":"8 Chatham Rd",
    "sg:city":"Andover",
    "sg:classifiers":[
        {
            "category":"Building & Trades",
            "subcategory":"Construction",
            "type":"Services"
        }
    ],
    "sg:phone":"+1   ",
    "sg:postcode":"01810",
    "sg:province":"MA",
    "sg:tags":[
        "contractor"
    ],
    "wof:name":"Metal Installations Inc",
    "wof:placetype":"venue"
},
  "geometry": {"coordinates":[-71.117452,42.624427],"type":"Point"}
}