{
  "type": "Feature",
  "properties": {
    "addr:full": "39 Bellevue St Newton MA 02458",
    "addr:housenumber": "39",
    "addr:postcode": "02458",
    "addr:street": "Bellevue St",
    "iso:country": "US",
    "sg:address": "39 Bellevue St",
    "sg:city": "Newton",
    "sg:classifiers": [
      {
        "category": "Place Of Worship",
        "type": "Public Place"
      }
    ],
    "sg:phone": "+1 617 285 8860",
    "sg:postcode": "02458",
    "sg:province": "MA",
    "sg:tags": [
      "church"
    ],
    "wof:name": "Charles Chu",
    "wof:placetype": "venue"
  },
  "geometry": {"coordinates":[-71.189888,42.3512],"type":"Point"}
}
