{
  "type": "Feature",
  "properties": {
    "iso:country":"US",
    "sg:address":"17 John St",
    "sg:city":"East Longmeadow",
    "sg:classifiers":[
        {
            "category":"Insurance",
            "subcategory":"Life Insurance",
            "type":"Services"
        }
    ],
    "sg:phone":"+1   ",
    "sg:postcode":"01028",
    "sg:province":"MA",
    "sg:tags":[
        "carrier",
        "association"
    ],
    "wof:name":"Polish National Alliance",
    "wof:placetype":"venue"
},
  "geometry": {"coordinates":[-72.516366,42.073176],"type":"Point"}
}