{
  "type": "Feature",
  "properties": {
    "addr:full":"85 Bald Mountain Rd Bernardston MA 01337",
    "addr:housenumber":"85",
    "addr:postcode":"01337",
    "addr:street":"Bald Mountain Rd",
    "iso:country":"US",
    "sg:address":"85 Bald Mountain Rd",
    "sg:city":"Bernardston",
    "sg:classifiers":[
        {
            "category":"Building & Trades",
            "subcategory":"Landscaping Services",
            "type":"Services"
        }
    ],
    "sg:phone":"+1 413 648 5458",
    "sg:postcode":"01337",
    "sg:province":"MA",
    "sg:tags":[
        "landscape",
        "contractor"
    ],
    "wof:name":"Berkshire Landscapes Company",
    "wof:placetype":"venue"
},
  "geometry": {"coordinates":[-72.541267,42.675251],"type":"Point"}
}