{
  "type": "Feature",
  "properties": {
    "addr:full":"21 Saint Clare Road Medford MA 02155",
    "addr:housenumber":"21",
    "addr:postcode":"02155",
    "addr:street":"Saint Clare Road",
    "iso:country":"US",
    "sg:address":"21 Saint Clare Road",
    "sg:city":"Medford",
    "sg:classifiers":[
        {
            "category":"Organizations",
            "subcategory":"Religious Organization",
            "type":"Services"
        }
    ],
    "sg:phone":"+1 781 395 4042",
    "sg:postcode":"02155",
    "sg:province":"MA",
    "wof:name":"St Francis of Assisi",
    "wof:placetype":"venue"
},
  "geometry": {"coordinates":[-71.102346,42.427303],"type":"Point"}
}