{
  "type": "Feature",
  "properties": {
    "iso:country":"US",
    "sg:address":"101 Amesbury St",
    "sg:city":"Lawrence",
    "sg:classifiers":[
        {
            "category":"Home & Garden",
            "subcategory":"Home Furnishings",
            "type":"Retail Goods"
        }
    ],
    "sg:phone":"+1 978 683 3553",
    "sg:postcode":"01841",
    "sg:province":"MA",
    "sg:tags":[
        "utensil",
        "cooking"
    ],
    "wof:name":"Royal Prestige",
    "wof:placetype":"venue"
},
  "geometry": {"coordinates":[-71.16386799999999,42.708627],"type":"Point"}
}