{
  "type": "Feature",
  "properties": {
    "addr:full": "912 Main St Waltham MA 02451",
    "addr:housenumber": "912",
    "addr:postcode": "02451",
    "addr:street": "Main St",
    "iso:country": "US",
    "sg:address": "912 Main St",
    "sg:city": "Waltham",
    "sg:classifiers": [
      {
        "category": "Restaurant",
        "type": "Food \u0026 Drink"
      }
    ],
    "sg:menulink": "http://www.allmenus.com/ma/waltham/151097-petes-pizza--wings/menu/",
    "sg:phone": "+1 781 647 0234",
    "sg:postcode": "02451",
    "sg:province": "MA",
    "sg:tags": [
      "american",
      "pizza"
    ],
    "wof:name": "Pete's Pizza \u0026 Wings",
    "wof:placetype": "venue"
  },
  "geometry": {"coordinates":[-71.24776,42.376289],"type":"Point"}
}
