{
  "type": "Feature",
  "properties": {
    "iso:country":"US",
    "sg:address":"95 Morse St",
    "sg:city":"Norwood",
    "sg:classifiers":[
        {
            "category":"Insurance",
            "subcategory":"Insurance Agent",
            "type":"Services"
        }
    ],
    "sg:phone":"+1 781 769 3982",
    "sg:postcode":"02062",
    "sg:province":"MA",
    "wof:name":"Northeast Dealer Svc",
    "wof:placetype":"venue"
},
  "geometry": {"coordinates":[-71.205381,42.172891],"type":"Point"}
}