{
  "type": "Feature",
  "properties": {
    "addr:full":"64 Ames St Brockton MA 02302",
    "addr:housenumber":"64",
    "addr:postcode":"02302",
    "addr:street":"Ames St",
    "iso:country":"US",
    "sg:address":"64 Ames St",
    "sg:city":"Brockton",
    "sg:classifiers":[
        {
            "category":"Building & Trades",
            "subcategory":"Electrical",
            "type":"Services"
        }
    ],
    "sg:phone":"+1 508 588 1700",
    "sg:postcode":"02302",
    "sg:province":"MA",
    "sg:tags":[
        "electric",
        "contractor"
    ],
    "wof:name":"Southgate Electric Corp",
    "wof:placetype":"venue"
},
  "geometry": {"coordinates":[-71.018736,42.102141],"type":"Point"}
}