{
  "type": "Feature",
  "properties": {
    "iso:country":"US",
    "sg:address":"31 Jackson Cir",
    "sg:city":"Franklin",
    "sg:classifiers":[
        {
            "category":"Professional",
            "subcategory":"Art Services",
            "type":"Services"
        }
    ],
    "sg:phone":"+1   ",
    "sg:postcode":"02038",
    "sg:province":"MA",
    "sg:tags":[
        "commercial",
        "design"
    ],
    "wof:name":"Wahlberg Studio",
    "wof:placetype":"venue"
},
  "geometry": {"coordinates":[-71.42206899999999,42.04808],"type":"Point"}
}