{
  "type": "Feature",
  "properties": {
    "iso:country":"US",
    "sg:address":"9 Sand Hill Rd",
    "sg:city":"Monson",
    "sg:classifiers":[
        {
            "category":"Manufacturing",
            "subcategory":"Retail Goods",
            "type":"Manufacturing & Wholesale Goods"
        }
    ],
    "sg:phone":"+1 413 267 0500",
    "sg:postcode":"01057",
    "sg:province":"MA",
    "sg:tags":[
        "product",
        "mfg"
    ],
    "wof:name":"Visual Creations",
    "wof:placetype":"venue"
},
  "geometry": {"coordinates":[-72.354761,42.109171],"type":"Point"}
}