{
  "type": "Feature",
  "properties": {
    "iso:country":"US",
    "sg:address":"225 High St",
    "sg:city":"Randolph",
    "sg:classifiers":[
        {
            "category":"Education",
            "subcategory":"School",
            "type":"Public Place"
        }
    ],
    "sg:phone":"+1   ",
    "sg:postcode":"02368",
    "sg:province":"MA",
    "sg:tags":[
        "elementary",
        "secondary"
    ],
    "wof:name":"Randolph Cmnty Middle Schl Pto",
    "wof:placetype":"venue"
},
  "geometry": {"coordinates":[-71.066818,42.18185],"type":"Point"}
}