{
  "type": "Feature",
  "properties": {
    "addr:full":"1001 Main St South Weymouth MA 02190",
    "addr:housenumber":"1001",
    "addr:postcode":"02190",
    "addr:street":"Main St",
    "iso:country":"US",
    "sg:address":"1001 Main St",
    "sg:city":"South Weymouth",
    "sg:classifiers":[
        {
            "category":"Personal",
            "subcategory":"Beauty Salon",
            "type":"Services"
        }
    ],
    "sg:phone":"+1 781 331 7009",
    "sg:postcode":"02190",
    "sg:province":"MA",
    "sg:tags":[
        "manicuring"
    ],
    "wof:name":"Lavender Nail & Waxing",
    "wof:placetype":"venue"
},
  "geometry": {"coordinates":[-70.955321,42.169657],"type":"Point"}
}