{
  "type": "Feature",
  "properties": {
    "addr:full":"73 Water St Newburyport MA 01950",
    "addr:housenumber":"73",
    "addr:postcode":"01950",
    "addr:street":"Water St",
    "iso:country":"US",
    "sg:address":"73 Water St",
    "sg:city":"Newburyport",
    "sg:classifiers":[
        {
            "category":"Building & Trades",
            "subcategory":"Construction",
            "type":"Services"
        }
    ],
    "sg:phone":"+1 978 462 7207",
    "sg:postcode":"01950",
    "sg:province":"MA",
    "sg:tags":[
        "excavating",
        "contractor"
    ],
    "wof:name":"Wickson Constructions Corp",
    "wof:placetype":"venue"
},
  "geometry": {"coordinates":[-70.865617,42.810726],"type":"Point"}
}