{
  "type": "Feature",
  "properties": {
    "addr:full": "79 E Alvord St Springfield MA 01108",
    "addr:housenumber": "79",
    "addr:postcode": "01108",
    "addr:street": "E Alvord St",
    "iso:country": "US",
    "sg:address": "79 E Alvord St",
    "sg:city": "Springfield",
    "sg:classifiers": [
      {
        "category": "Retail",
        "subcategory": "Portrait Studio",
        "type": "Services"
      }
    ],
    "sg:phone": "+1 413 781 1398",
    "sg:postcode": "01108",
    "sg:province": "MA",
    "sg:tags": [
      "photography"
    ],
    "wof:name": "Sunray Photography",
    "wof:placetype": "venue"
  },
  "geometry": {"coordinates":[-72.548783,42.090672],"type":"Point"}
}
