{
  "type": "Feature",
  "properties": {
    "iso:country":"US",
    "sg:address":"765 State St",
    "sg:city":"Springfield",
    "sg:classifiers":[
        {
            "category":"Government",
            "subcategory":"Office",
            "type":"Public Place"
        }
    ],
    "sg:phone":"+1   ",
    "sg:postcode":"01109",
    "sg:province":"ME",
    "sg:tags":[
        "library"
    ],
    "wof:name":"Public Library - Mason Sq",
    "wof:placetype":"venue"
},
  "geometry": {"coordinates":[-72.564315,42.111419],"type":"Point"}
}