{
  "type": "Feature",
  "properties": {
    "addr:full":"3 Arrow St Cambridge MA 02138",
    "addr:housenumber":"3",
    "addr:postcode":"02138",
    "addr:street":"Arrow St",
    "iso:country":"US",
    "sg:address":"3 Arrow St",
    "sg:city":"Cambridge",
    "sg:classifiers":[
        {
            "category":"Ice Cream",
            "type":"Food & Drink"
        }
    ],
    "sg:phone":"+1 617 868 3500",
    "sg:postcode":"02138",
    "sg:province":"MA",
    "sg:tags":[
        "frozen",
        "yogurt"
    ],
    "sg:website":"www.berryline.com",
    "wof:name":"BerryLine",
    "wof:placetype":"venue"
},
  "geometry": {"coordinates":[-71.114091,42.370954],"type":"Point"}
}