{
  "type": "Feature",
  "properties": {
    "addr:full": "460 Fuller St Ludlow MA 01056",
    "addr:housenumber": "460",
    "addr:postcode": "01056",
    "addr:street": "Fuller St",
    "iso:country": "US",
    "sg:address": "460 Fuller St",
    "sg:city": "Ludlow",
    "sg:classifiers": [
      {
        "category": "Building \u0026 Trades",
        "subcategory": "Construction",
        "type": "Services"
      }
    ],
    "sg:phone": "+1 413 547 8059",
    "sg:postcode": "01056",
    "sg:province": "MA",
    "sg:tags": [
      "concrete",
      "contractor"
    ],
    "wof:name": "LA Roche Concrete",
    "wof:placetype": "venue"
  },
  "geometry": {"coordinates":[-72.482615,42.194188],"type":"Point"}
}
