{
  "type": "Feature",
  "properties": {
    "iso:country":"US",
    "sg:address":"460 Fuller St",
    "sg:city":"Ludlow",
    "sg:classifiers":[
        {
            "category":"Building & Trades",
            "subcategory":"Construction",
            "type":"Services"
        }
    ],
    "sg:phone":"+1 413 547 8059",
    "sg:postcode":"01056",
    "sg:province":"MA",
    "sg:tags":[
        "concrete",
        "contractor"
    ],
    "wof:name":"LA Roche Concrete",
    "wof:placetype":"venue"
},
  "geometry": {"coordinates":[-72.482615,42.194188],"type":"Point"}
}