{
  "type": "Feature",
  "properties": {
    "addr:full":"28 State St Fl 13 Boston MA 02109",
    "addr:housenumber":"28;13",
    "addr:postcode":"02109",
    "addr:street":"State St Fl",
    "iso:country":"US",
    "sg:address":"28 State St Fl 13",
    "sg:city":"Boston",
    "sg:classifiers":[
        {
            "category":"Banks & Credit Unions",
            "subcategory":"Bank",
            "type":"Services"
        }
    ],
    "sg:phone":"+1 617 725 5901",
    "sg:postcode":"02109",
    "sg:province":"MA",
    "sg:website":"www.citizensbank.com",
    "wof:name":"Citizens Bank Retail Office",
    "wof:placetype":"venue"
},
  "geometry": {"coordinates":[-71.05711100000001,42.359015],"type":"Point"}
}