{
  "type": "Feature",
  "properties": {
    "iso:country":"US",
    "sg:address":"55 Captain Simmons Rd",
    "sg:city":"South Yarmouth",
    "sg:classifiers":[
        {
            "category":"Wholesale",
            "subcategory":"Electrical",
            "type":"Manufacturing & Wholesale Goods"
        }
    ],
    "sg:phone":"+1   ",
    "sg:postcode":"02664",
    "sg:province":"MA",
    "sg:tags":[
        "equipment"
    ],
    "wof:name":"Eastrep",
    "wof:placetype":"venue"
},
  "geometry": {"coordinates":[-70.21362499999999,41.672022],"type":"Point"}
}