{
  "type": "Feature",
  "properties": {
    "iso:country":"US",
    "sg:address":"128 Upton Rd",
    "sg:city":"Westborough",
    "sg:classifiers":[
        {
            "category":"Professional",
            "type":"Services"
        }
    ],
    "sg:phone":"+1   ",
    "sg:postcode":"01581",
    "sg:province":"MA",
    "wof:name":"Hicgo Corp",
    "wof:placetype":"venue"
},
  "geometry": {"coordinates":[-71.60581500000001,42.233434],"type":"Point"}
}