{
  "type": "Feature",
  "properties": {
    "iso:country":"US",
    "sg:address":"287 Appleton St",
    "sg:city":"Lowell",
    "sg:classifiers":[
        {
            "category":"Manufacturing",
            "subcategory":"Printing",
            "type":"Manufacturing & Wholesale Goods"
        }
    ],
    "sg:phone":"+1 978 459 2109",
    "sg:postcode":"01852",
    "sg:province":"MA",
    "sg:tags":[
        "printer"
    ],
    "wof:name":"Sir Speedy Printing Ctr",
    "wof:placetype":"venue"
},
  "geometry": {"coordinates":[-71.315209,42.639052],"type":"Point"}
}