{
  "type": "Feature",
  "properties": {
    "addr:full": "65 Windsor Ln Marshfield MA 02050",
    "addr:housenumber": "65",
    "addr:postcode": "02050",
    "addr:street": "Windsor Ln",
    "iso:country": "US",
    "sg:address": "65 Windsor Ln",
    "sg:city": "Marshfield",
    "sg:classifiers": [
      {
        "category": "Manufacturing",
        "subcategory": "Paper Products",
        "type": "Manufacturing \u0026 Wholesale Goods"
      }
    ],
    "sg:phone": "+1 781 837 5507",
    "sg:postcode": "02050",
    "sg:province": "MA",
    "sg:tags": [
      "bookbinder"
    ],
    "wof:name": "Superior Bindery",
    "wof:placetype": "venue"
  },
  "geometry": {"coordinates":[-70.756067,42.136087],"type":"Point"}
}
