{
  "type": "Feature",
  "properties": {
    "addr:full": "145 Falmouth Heights Rd Falmouth MA 02540",
    "addr:housenumber": "145",
    "addr:postcode": "02540",
    "addr:street": "Falmouth Heights Rd",
    "iso:country": "US",
    "sg:address": "145 Falmouth Heights Rd",
    "sg:city": "Falmouth",
    "sg:classifiers": [
      {
        "category": "Autos \u0026 Motor Vehicles",
        "subcategory": "Boat Sales",
        "type": "Retail Goods"
      }
    ],
    "sg:phone": "+1 508 495 4078",
    "sg:postcode": "02540",
    "sg:province": "MA",
    "sg:tags": [
      "dealer",
      "sales"
    ],
    "wof:name": "Boston Yacht Sales",
    "wof:placetype": "venue"
  },
  "geometry": {"coordinates":[-70.600199,41.547459],"type":"Point"}
}
