{
  "type": "Feature",
  "properties": {
    "addr:full":"3 Wheeler Rd West Townsend MA 01474",
    "addr:housenumber":"3",
    "addr:postcode":"01474",
    "addr:street":"Wheeler Rd West",
    "iso:country":"US",
    "sg:address":"3 Wheeler Rd",
    "sg:city":"West Townsend",
    "sg:classifiers":[
        {
            "category":"School Buses",
            "type":"Transportation"
        }
    ],
    "sg:phone":"+1   ",
    "sg:postcode":"01474",
    "sg:province":"MA",
    "wof:name":"Brookside of Townsend Inc",
    "wof:placetype":"venue"
},
  "geometry": {"coordinates":[-71.76442,42.674344],"type":"Point"}
}