{
  "type": "Feature",
  "properties": {
    "iso:country":"US",
    "sg:address":"90 Corey Rd",
    "sg:city":"Brighton",
    "sg:classifiers":[
        {
            "category":"Manufacturing",
            "subcategory":"Apparel",
            "type":"Manufacturing & Wholesale Goods"
        }
    ],
    "sg:phone":"+1   ",
    "sg:postcode":"02135",
    "sg:province":"MA",
    "sg:tags":[
        "accessory",
        "mfg"
    ],
    "wof:name":"Hadley Pollet LLC",
    "wof:placetype":"venue"
},
  "geometry": {"coordinates":[-71.141555,42.341516],"type":"Point"}
}