{
  "type": "Feature",
  "properties": {
    "addr:full": "90 Corey Rd Brighton MA 02135",
    "addr:housenumber": "90",
    "addr:postcode": "02135",
    "addr:street": "Corey Rd",
    "iso:country": "US",
    "sg:address": "90 Corey Rd",
    "sg:city": "Brighton",
    "sg:classifiers": [
      {
        "category": "Manufacturing",
        "subcategory": "Apparel",
        "type": "Manufacturing \u0026 Wholesale Goods"
      }
    ],
    "sg:phone": "+1   ",
    "sg:postcode": "02135",
    "sg:province": "MA",
    "sg:tags": [
      "accessory",
      "mfg"
    ],
    "wof:name": "Hadley Pollet LLC",
    "wof:placetype": "venue"
  },
  "geometry": {"coordinates":[-71.141555,42.341516],"type":"Point"}
}
