{
  "type": "Feature",
  "properties": {
    "iso:country":"US",
    "sg:address":"35 Porter Rd",
    "sg:city":"Waltham",
    "sg:classifiers":[
        {
            "category":"Retail",
            "subcategory":"Auto Repair",
            "type":"Services"
        }
    ],
    "sg:phone":"+1   ",
    "sg:postcode":"02452",
    "sg:province":"MA",
    "sg:tags":[
        "body"
    ],
    "wof:name":"Stewarts Collision Repair Ctr",
    "wof:placetype":"venue"
},
  "geometry": {"coordinates":[-71.20609399999999,42.396222],"type":"Point"}
}