{
  "type": "Feature",
  "properties": {
    "addr:full": "61 Everett Avenue Chelsea MA 02150",
    "addr:housenumber": "61",
    "addr:postcode": "02150",
    "addr:street": "Everett Avenue",
    "iso:country": "US",
    "sg:address": "61 Everett Avenue",
    "sg:city": "Chelsea",
    "sg:classifiers": [
      {
        "category": "Health Services",
        "subcategory": "Dentist",
        "type": "Services"
      }
    ],
    "sg:phone": "+1 617 887 9944",
    "sg:postcode": "02150",
    "sg:province": "MA",
    "wof:name": "Chelsea Dental Care",
    "wof:placetype": "venue"
  },
  "geometry": {"coordinates":[-71.039042,42.392852],"type":"Point"}
}
