{
  "type": "Feature",
  "properties": {
    "addr:full": "10 Forbes St Jamaica Plain MA 02130",
    "addr:housenumber": "10",
    "addr:postcode": "02130",
    "addr:street": "Forbes St",
    "iso:country": "US",
    "sg:address": "10 Forbes St",
    "sg:city": "Jamaica Plain",
    "sg:classifiers": [
      {
        "category": "Professional",
        "subcategory": "Research",
        "type": "Services"
      }
    ],
    "sg:phone": "+1 617 946 0755",
    "sg:postcode": "02130",
    "sg:province": "MA",
    "sg:tags": [
      "market",
      "analysis"
    ],
    "sg:website": "www.focusonboston.com",
    "wof:name": "Focus On Boston",
    "wof:placetype": "venue"
  },
  "geometry": {"coordinates":[-71.105242,42.319426],"type":"Point"}
}
