{
  "type": "Feature",
  "properties": {
    "addr:full":"75 Arlington St Boston MA 02116",
    "addr:housenumber":"75",
    "addr:postcode":"02116",
    "addr:street":"Arlington St",
    "iso:country":"US",
    "sg:address":"75 Arlington St",
    "sg:city":"Boston",
    "sg:classifiers":[
        {
            "category":"Personal",
            "subcategory":"Beauty Salon",
            "type":"Services"
        },
        {
            "category":"Personal",
            "type":"Services"
        }
    ],
    "sg:phone":"+1 857 241 3862",
    "sg:postcode":"02116",
    "sg:province":"MA",
    "sg:tags":[
        "planning",
        "party",
        "makeup",
        "event",
        "artist"
    ],
    "sg:website":"www.gaudeandgold.com",
    "wof:name":"Gaude and Gold",
    "wof:placetype":"venue"
},
  "geometry": {"coordinates":[-71.07020300000001,42.350379],"type":"Point"}
}