{
  "type": "Feature",
  "properties": {
    "addr:full":"1200 Washington St # 213 Boston MA 02118",
    "addr:housenumber":"1200",
    "addr:postcode":"02118",
    "addr:street":"Washington St # 213",
    "iso:country":"US",
    "sg:address":"1200 Washington St # 213",
    "sg:city":"Boston",
    "sg:classifiers":[
        {
            "category":"Home & Garden",
            "subcategory":"Home Furnishings",
            "type":"Retail Goods"
        }
    ],
    "sg:phone":"+1 617 542 0575",
    "sg:postcode":"02118",
    "sg:province":"MA",
    "sg:tags":[
        "draperies",
        "window",
        "treatment",
        "curtain",
        "drapery",
        "trimming"
    ],
    "wof:name":"Dreamscapes Of Boston",
    "wof:placetype":"venue"
},
  "geometry": {"coordinates":[-71.066801,42.343061],"type":"Point"}
}