{
  "type": "Feature",
  "properties": {
    "iso:country":"US",
    "sg:address":"4 Park Sq",
    "sg:city":"Dracut",
    "sg:classifiers":[
        {
            "category":"Real Estate",
            "subcategory":"Real Estate Agent",
            "type":"Services"
        }
    ],
    "sg:phone":"+1 978 275 3838",
    "sg:postcode":"01826",
    "sg:province":"MA",
    "wof:name":"United Estates Realty",
    "wof:placetype":"venue"
},
  "geometry": {"coordinates":[-71.298153,42.671395],"type":"Point"}
}