{
  "type": "Feature",
  "properties": {
    "iso:country":"US",
    "sg:address":"313 Main St",
    "sg:city":"Great Barrington",
    "sg:classifiers":[
        {
            "category":"Shopping",
            "subcategory":"Gifts & Souvenirs",
            "type":"Retail Goods"
        }
    ],
    "sg:phone":"+1 413 528 1888",
    "sg:postcode":"01230",
    "sg:province":"MA",
    "sg:tags":[
        "shop"
    ],
    "sg:website":"www.lapaceinc.com",
    "wof:name":"LA Pace Inc",
    "wof:placetype":"venue"
},
  "geometry": {"coordinates":[-73.364356,42.188413],"type":"Point"}
}