{
  "type": "Feature",
  "properties": {
    "iso:country":"US",
    "sg:address":"795 Plymouth Ave",
    "sg:city":"Fall River",
    "sg:classifiers":[
        {
            "category":"Autos & Motor Vehicles",
            "subcategory":"Auto Supplies",
            "type":"Retail Goods"
        }
    ],
    "sg:phone":"+1 508 677 0569",
    "sg:postcode":"02721",
    "sg:province":"MA",
    "sg:tags":[
        "automobile",
        "accessory"
    ],
    "wof:name":"Lethal Wheelz Auto Accessories",
    "wof:placetype":"venue"
},
  "geometry": {"coordinates":[-71.15807,41.69164],"type":"Point"}
}