{
  "type": "Feature",
  "properties": {
    "iso:country":"US",
    "sg:address":"300 Foxboro Blvd",
    "sg:city":"Foxboro",
    "sg:classifiers":[
        {
            "category":"Wholesale",
            "subcategory":"Groceries",
            "type":"Manufacturing & Wholesale Goods"
        }
    ],
    "sg:phone":"+1 508 698 5700",
    "sg:postcode":"02035",
    "sg:province":"MA",
    "sg:tags":[
        "food",
        "broker"
    ],
    "sg:website":"www.asmnet.com",
    "wof:name":"ADVANTAGE Sales & Marketing",
    "wof:placetype":"venue"
},
  "geometry": {"coordinates":[-71.23644299999999,42.042999],"type":"Point"}
}