{
  "type": "Feature",
  "properties": {
    "addr:full": "300 Foxboro Blvd Foxboro MA 02035",
    "addr:housenumber": "300",
    "addr:postcode": "02035",
    "addr:street": "Foxboro Blvd",
    "iso:country": "US",
    "sg:address": "300 Foxboro Blvd",
    "sg:city": "Foxboro",
    "sg:classifiers": [
      {
        "category": "Wholesale",
        "subcategory": "Groceries",
        "type": "Manufacturing \u0026 Wholesale Goods"
      }
    ],
    "sg:phone": "+1 508 698 5700",
    "sg:postcode": "02035",
    "sg:province": "MA",
    "sg:tags": [
      "food",
      "broker"
    ],
    "sg:website": "www.asmnet.com",
    "wof:name": "ADVANTAGE Sales \u0026 Marketing",
    "wof:placetype": "venue"
  },
  "geometry": {"coordinates":[-71.236443,42.042999],"type":"Point"}
}
