{
  "type": "Feature",
  "properties": {
    "iso:country":"US",
    "sg:address":"11 Oakland St",
    "sg:city":"Amesbury",
    "sg:classifiers":[
        {
            "category":"Manufacturing",
            "subcategory":"Metals",
            "type":"Manufacturing & Wholesale Goods"
        }
    ],
    "sg:phone":"+1 978 388 9491",
    "sg:postcode":"01913",
    "sg:province":"MA",
    "sg:tags":[
        "fabricator",
        "sheet"
    ],
    "wof:name":"Oakland Industries Inc",
    "wof:placetype":"venue"
},
  "geometry": {"coordinates":[-70.924559,42.857029],"type":"Point"}
}