{
  "type": "Feature",
  "properties": {
    "addr:full":"29 Union Sq Gardner MA 01440",
    "addr:housenumber":"29",
    "addr:postcode":"01440",
    "addr:street":"Union Sq",
    "iso:country":"US",
    "sg:address":"29 Union Sq",
    "sg:city":"Gardner",
    "sg:classifiers":[
        {
            "category":"Health Services",
            "subcategory":"Doctor",
            "type":"Services"
        }
    ],
    "sg:phone":"+1 978 632 7383",
    "sg:postcode":"01440",
    "sg:province":"MA",
    "sg:tags":[
        "physician",
        "surgeon"
    ],
    "wof:name":"Wachusett Radiology Inc",
    "wof:placetype":"venue"
},
  "geometry": {"coordinates":[-71.981853,42.566471],"type":"Point"}
}