{
  "type": "Feature",
  "properties": {
    "iso:country":"US",
    "sg:address":"87 Pearl St",
    "sg:city":"Cambridge",
    "sg:classifiers":[
        {
            "category":"Food & Beverages",
            "subcategory":"Groceries & Convenience Stores",
            "type":"Retail Goods"
        }
    ],
    "sg:phone":"+1 617 492 2157",
    "sg:postcode":"02139",
    "sg:province":"MA",
    "sg:tags":[
        "grocer"
    ],
    "wof:name":"Pearl Street Market",
    "wof:placetype":"venue"
},
  "geometry": {"coordinates":[-71.105103,42.3624],"type":"Point"}
}