{
  "type": "Feature",
  "properties": {
    "addr:full": "87 Pearl St Cambridge MA 02139",
    "addr:housenumber": "87",
    "addr:postcode": "02139",
    "addr:street": "Pearl St",
    "iso:country": "US",
    "sg:address": "87 Pearl St",
    "sg:city": "Cambridge",
    "sg:classifiers": [
      {
        "category": "Food \u0026 Beverages",
        "subcategory": "Groceries \u0026 Convenience Stores",
        "type": "Retail Goods"
      }
    ],
    "sg:phone": "+1 617 492 2157",
    "sg:postcode": "02139",
    "sg:province": "MA",
    "sg:tags": [
      "grocer"
    ],
    "wof:name": "Pearl Street Market",
    "wof:placetype": "venue"
  },
  "geometry": {"coordinates":[-71.105103,42.3624],"type":"Point"}
}
