{
  "type": "Feature",
  "properties": {
    "addr:full":"20 Meacham Rd Cambridge MA 02140",
    "addr:housenumber":"20",
    "addr:postcode":"02140",
    "addr:street":"Meacham Rd",
    "iso:country":"US",
    "sg:address":"20 Meacham Rd",
    "sg:city":"Cambridge",
    "sg:classifiers":[
        {
            "category":"Organizations",
            "subcategory":"Religious Organization",
            "type":"Services"
        }
    ],
    "sg:phone":"+1   ",
    "sg:postcode":"02140",
    "sg:province":"MA",
    "wof:name":"SRI Prmananda Ctr of Untd Stat",
    "wof:placetype":"venue"
},
  "geometry": {"coordinates":[-71.12700599999999,42.395245],"type":"Point"}
}