{
  "type": "Feature",
  "properties": {
    "iso:country":"US",
    "sg:address":"64 Westbourne Ter",
    "sg:city":"Brookline",
    "sg:classifiers":[
        {
            "category":"Education",
            "subcategory":"School",
            "type":"Public Place"
        }
    ],
    "sg:phone":"+1 617 879 4266",
    "sg:postcode":"02446",
    "sg:province":"MA",
    "sg:tags":[
        "high",
        "middle",
        "elementary"
    ],
    "wof:name":"Brookline Town of",
    "wof:placetype":"venue"
},
  "geometry": {"coordinates":[-71.135814,42.341054],"type":"Point"}
}