{
  "type": "Feature",
  "properties": {
    "addr:full": "3 Doane St Wilmington MA 01887",
    "addr:housenumber": "3",
    "addr:postcode": "01887",
    "addr:street": "Doane St",
    "iso:country": "US",
    "sg:address": "3 Doane St",
    "sg:city": "Wilmington",
    "sg:classifiers": [
      {
        "category": "Building \u0026 Trades",
        "subcategory": "Plumbing",
        "type": "Services"
      }
    ],
    "sg:phone": "+1 978 988 3889",
    "sg:postcode": "01887",
    "sg:province": "MA",
    "wof:name": "D \u0026 D Services",
    "wof:placetype": "venue"
  },
  "geometry": {"coordinates":[-71.17335,42.567534],"type":"Point"}
}
