{
  "type": "Feature",
  "properties": {
    "iso:country":"US",
    "sg:address":"3 Doane St",
    "sg:city":"Wilmington",
    "sg:classifiers":[
        {
            "category":"Building & Trades",
            "subcategory":"Plumbing",
            "type":"Services"
        }
    ],
    "sg:phone":"+1 978 988 3889",
    "sg:postcode":"01887",
    "sg:province":"MA",
    "wof:name":"D & D Services",
    "wof:placetype":"venue"
},
  "geometry": {"coordinates":[-71.17335,42.567534],"type":"Point"}
}