{
  "type": "Feature",
  "properties": {
    "addr:full":"365 Boston Rd Billerica MA 01821",
    "addr:housenumber":"365",
    "addr:postcode":"01821",
    "addr:street":"Boston Rd",
    "iso:country":"US",
    "sg:address":"365 Boston Rd",
    "sg:city":"Billerica",
    "sg:classifiers":[
        {
            "category":"Banks & Credit Unions",
            "subcategory":"Bank",
            "type":"Services"
        }
    ],
    "sg:phone":"+1 978 667 2434",
    "sg:postcode":"01821",
    "sg:province":"MA",
    "wof:name":"Billerica Municipal Employees Credit Union",
    "wof:placetype":"venue"
},
  "geometry": {"coordinates":[-71.271896,42.5644],"type":"Point"}
}