{
  "type": "Feature",
  "properties": {
    "addr:full": "2 Clementi Ln Methuen MA 01844",
    "addr:housenumber": "2",
    "addr:postcode": "01844",
    "addr:street": "Clementi Ln",
    "iso:country": "US",
    "sg:address": "2 Clementi Ln",
    "sg:city": "Methuen",
    "sg:classifiers": [
      {
        "category": "Home \u0026 Garden",
        "subcategory": "Garden Supply",
        "type": "Retail Goods"
      }
    ],
    "sg:phone": "+1 978 975 2255",
    "sg:postcode": "01844",
    "sg:province": "MA",
    "sg:tags": [
      "sprinkler"
    ],
    "wof:name": "Wain's Irrigation",
    "wof:placetype": "venue"
  },
  "geometry": {"coordinates":[-71.123578,42.741489],"type":"Point"}
}
