{
  "type": "Feature",
  "properties": {
    "iso:country":"US",
    "sg:address":"2 Clementi Ln",
    "sg:city":"Methuen",
    "sg:classifiers":[
        {
            "category":"Home & Garden",
            "subcategory":"Garden Supply",
            "type":"Retail Goods"
        }
    ],
    "sg:phone":"+1 978 975 2255",
    "sg:postcode":"01844",
    "sg:province":"MA",
    "sg:tags":[
        "sprinkler"
    ],
    "wof:name":"Wain's Irrigation",
    "wof:placetype":"venue"
},
  "geometry": {"coordinates":[-71.12357799999999,42.741489],"type":"Point"}
}