{
  "type": "Feature",
  "properties": {
    "addr:full":"769 Iyannough Rd Hyannis MA 02601",
    "addr:housenumber":"769",
    "addr:postcode":"02601",
    "addr:street":"Iyannough Rd",
    "iso:country":"US",
    "sg:address":"769 Iyannough Rd",
    "sg:city":"Hyannis",
    "sg:classifiers":[
        {
            "category":"Shopping",
            "subcategory":"Clothing, Apparel, & Fashions",
            "type":"Retail Goods"
        }
    ],
    "sg:phone":"+1 508 771 1376",
    "sg:postcode":"02601",
    "sg:province":"MA",
    "sg:tags":[
        "maternity",
        "wear"
    ],
    "sg:website":"www.motherhood.com",
    "wof:name":"Motherhood Maternity",
    "wof:placetype":"venue"
},
  "geometry": {"coordinates":[-70.294899,41.668598],"type":"Point"}
}