{
  "type": "Feature",
  "properties": {
    "addr:full": "86 High St Wareham MA 02571",
    "addr:housenumber": "86",
    "addr:postcode": "02571",
    "addr:street": "High St",
    "iso:country": "US",
    "sg:address": "86 High St",
    "sg:city": "Wareham",
    "sg:classifiers": [
      {
        "category": "Organizations",
        "subcategory": "Religious Organization",
        "type": "Services"
      }
    ],
    "sg:phone": "+1 508 295 0780",
    "sg:postcode": "02571",
    "sg:province": "MA",
    "wof:name": "St Patrick's Rectory",
    "wof:placetype": "venue"
  },
  "geometry": {"coordinates":[-70.717003,41.757363],"type":"Point"}
}
