{
  "type": "Feature",
  "properties": {
    "addr:full": "8 Broadway Westford MA 01886",
    "addr:housenumber": "8",
    "addr:postcode": "01886",
    "addr:street": "Broadway",
    "iso:country": "US",
    "sg:address": "8 Broadway",
    "sg:city": "Westford",
    "sg:classifiers": [
      {
        "category": "Organizations",
        "subcategory": "Community Association",
        "type": "Services"
      }
    ],
    "sg:phone": "+1 978 692 5494",
    "sg:postcode": "01886",
    "sg:province": "MA",
    "sg:tags": [
      "support",
      "business"
    ],
    "wof:name": "Business Support Svc",
    "wof:placetype": "venue"
  },
  "geometry": {"coordinates":[-71.460557,42.592261],"type":"Point"}
}
