{
  "type": "Feature",
  "properties": {
    "addr:full": "216 Chandler St Ste B Worcester MA 01609",
    "addr:housenumber": "216",
    "addr:postcode": "01609",
    "addr:street": "Chandler St Ste B",
    "iso:country": "US",
    "sg:address": "216 Chandler St Ste B",
    "sg:city": "Worcester",
    "sg:classifiers": [
      {
        "category": "Bars \u0026 Pubs",
        "type": "Food \u0026 Drink"
      },
      {
        "category": "Restaurant",
        "type": "Food \u0026 Drink"
      },
      {
        "category": "Bars \u0026 Pubs",
        "subcategory": "Lounge",
        "type": "Food \u0026 Drink"
      }
    ],
    "sg:phone": "+1 508 753 9072",
    "sg:postcode": "01609",
    "sg:province": "MA",
    "sg:tags": [
      "tavern",
      "seafood",
      "cocktail"
    ],
    "sg:website": "http://www.georgescafebrockton.com",
    "wof:name": "Suney's Pub \u0026 Restaurant",
    "wof:placetype": "venue"
  },
  "geometry": {"coordinates":[-71.81842,42.26088],"type":"Point"}
}
