{
  "type": "Feature",
  "properties": {
    "iso:country":"US",
    "sg:address":"150 Boston St",
    "sg:city":"East Boston",
    "sg:classifiers":[
        {
            "category":"Airline",
            "type":"Transportation"
        }
    ],
    "sg:phone":"+1 617 569 2216",
    "sg:postcode":"02125",
    "sg:province":"MA",
    "sg:tags":[
        "company"
    ],
    "wof:name":"TAP Air Portugal",
    "wof:placetype":"venue"
},
  "geometry": {"coordinates":[-71.0596,42.324423],"type":"Point"}
}