{
  "type": "Feature",
  "properties": {
    "addr:full": "150 Boston St East Boston MA 02125",
    "addr:housenumber": "150",
    "addr:postcode": "02125",
    "addr:street": "Boston St",
    "iso:country": "US",
    "sg:address": "150 Boston St",
    "sg:city": "East Boston",
    "sg:classifiers": [
      {
        "category": "Airline",
        "type": "Transportation"
      }
    ],
    "sg:phone": "+1 617 569 2216",
    "sg:postcode": "02125",
    "sg:province": "MA",
    "sg:tags": [
      "company"
    ],
    "wof:name": "TAP Air Portugal",
    "wof:placetype": "venue"
  },
  "geometry": {"coordinates":[-71.0596,42.324423],"type":"Point"}
}
