{
  "type": "Feature",
  "properties": {
    "iso:country":"US",
    "sg:address":"106 Lowell St",
    "sg:city":"Methuen",
    "sg:classifiers":[
        {
            "category":"Restaurant",
            "type":"Food & Drink"
        }
    ],
    "sg:phone":"+1 978 682 5542",
    "sg:postcode":"01844",
    "sg:province":"MA",
    "sg:website":"www.jimmysii.com",
    "wof:name":"Jimmy's Restaurant II",
    "wof:placetype":"venue"
},
  "geometry": {"coordinates":[-71.19549000000001,42.721042],"type":"Point"}
}