{
  "type": "Feature",
  "properties": {
    "addr:full": "106 Lowell St Methuen MA 01844",
    "addr:housenumber": "106",
    "addr:postcode": "01844",
    "addr:street": "Lowell St",
    "iso:country": "US",
    "sg:address": "106 Lowell St",
    "sg:city": "Methuen",
    "sg:classifiers": [
      {
        "category": "Restaurant",
        "type": "Food \u0026 Drink"
      }
    ],
    "sg:phone": "+1 978 682 5542",
    "sg:postcode": "01844",
    "sg:province": "MA",
    "sg:website": "www.jimmysii.com",
    "wof:name": "Jimmy's Restaurant II",
    "wof:placetype": "venue"
  },
  "geometry": {"coordinates":[-71.19549,42.721042],"type":"Point"}
}
