{
  "type": "Feature",
  "properties": {
    "iso:country":"US",
    "sg:address":"36 Grant Ave",
    "sg:city":"Burlington",
    "sg:classifiers":[
        {
            "category":"Building & Trades",
            "subcategory":"Electrical",
            "type":"Services"
        }
    ],
    "sg:phone":"+1 781 270 9520",
    "sg:postcode":"01803",
    "sg:province":"MA",
    "sg:tags":[
        "electrician"
    ],
    "wof:name":"Schuler Electric Inc - CLOSED",
    "wof:placetype":"venue"
},
  "geometry": {"coordinates":[-71.200699,42.512798],"type":"Point"}
}