{
  "type": "Feature",
  "properties": {
    "addr:full":"33 E Main St West Brookfield MA 01585",
    "addr:housenumber":"33",
    "addr:postcode":"01585",
    "addr:street":"E Main St West",
    "iso:country":"US",
    "sg:address":"33 E Main St",
    "sg:city":"West Brookfield",
    "sg:classifiers":[
        {
            "category":"Professional",
            "subcategory":"Lawyer & Legal Services",
            "type":"Services"
        }
    ],
    "sg:phone":"+1 508 867 2441",
    "sg:postcode":"01585",
    "sg:province":"MA",
    "sg:tags":[
        "attorney"
    ],
    "wof:name":"James F Baird",
    "wof:placetype":"venue"
},
  "geometry": {"coordinates":[-72.14198,42.23494],"type":"Point"}
}