{
  "type": "Feature",
  "properties": {
    "addr:full": "47 Florence Rd Easthampton MA 01027",
    "addr:housenumber": "47",
    "addr:postcode": "01027",
    "addr:street": "Florence Rd",
    "iso:country": "US",
    "sg:address": "47 Florence Rd",
    "sg:city": "Easthampton",
    "sg:classifiers": [
      {
        "category": "Home \u0026 Garden",
        "subcategory": "Household Appliances",
        "type": "Retail Goods"
      }
    ],
    "sg:phone": "+1 413 527 2244",
    "sg:postcode": "01027",
    "sg:province": "MA",
    "wof:name": "Cooper Appliance Svc",
    "wof:placetype": "venue"
  },
  "geometry": {"coordinates":[-72.671213,42.285126],"type":"Point"}
}
