{
  "type": "Feature",
  "properties": {
    "iso:country":"US",
    "sg:address":"47 Florence Rd",
    "sg:city":"Easthampton",
    "sg:classifiers":[
        {
            "category":"Home & Garden",
            "subcategory":"Household Appliances",
            "type":"Retail Goods"
        }
    ],
    "sg:phone":"+1 413 527 2244",
    "sg:postcode":"01027",
    "sg:province":"MA",
    "wof:name":"Cooper Appliance Svc",
    "wof:placetype":"venue"
},
  "geometry": {"coordinates":[-72.67121299999999,42.285126],"type":"Point"}
}