{
  "type": "Feature",
  "properties": {
    "iso:country":"US",
    "sg:address":"45 William T Morrissey",
    "sg:city":"Dorchester",
    "sg:classifiers":[
        {
            "category":"Retail",
            "subcategory":"Laundry & Dry Cleaning",
            "type":"Services"
        }
    ],
    "sg:phone":"+1 617 287 8881",
    "sg:postcode":"02125",
    "sg:province":"MA",
    "wof:name":"Sparkle One-Hour Cleaners",
    "wof:placetype":"venue"
},
  "geometry": {"coordinates":[-71.04960699999999,42.317737],"type":"Point"}
}