{
  "type": "Feature",
  "properties": {
    "addr:full": "45 William T Morrissey Dorchester MA 02125",
    "addr:housenumber": "45",
    "addr:postcode": "02125",
    "addr:street": "William T Morrissey",
    "iso:country": "US",
    "sg:address": "45 William T Morrissey",
    "sg:city": "Dorchester",
    "sg:classifiers": [
      {
        "category": "Retail",
        "subcategory": "Laundry \u0026 Dry Cleaning",
        "type": "Services"
      }
    ],
    "sg:phone": "+1 617 287 8881",
    "sg:postcode": "02125",
    "sg:province": "MA",
    "wof:name": "Sparkle One-Hour Cleaners",
    "wof:placetype": "venue"
  },
  "geometry": {"coordinates":[-71.049607,42.317737],"type":"Point"}
}
