{
  "type": "Feature",
  "properties": {
    "addr:full": "18 Lancelot Dr Paxton MA 01612",
    "addr:housenumber": "18",
    "addr:postcode": "01612",
    "addr:street": "Lancelot Dr",
    "iso:country": "US",
    "sg:address": "18 Lancelot Dr",
    "sg:city": "Paxton",
    "sg:classifiers": [
      {
        "category": "Recreation",
        "type": "Entertainment"
      }
    ],
    "sg:phone": "+1   ",
    "sg:postcode": "01612",
    "sg:province": "MA",
    "wof:name": "Deep Sea Divers",
    "wof:placetype": "venue"
  },
  "geometry": {"coordinates":[-71.928358,42.304166],"type":"Point"}
}
