{
  "type": "Feature",
  "properties": {
    "addr:full":"8 Deerfield Dr Walpole MA 02081",
    "addr:housenumber":"8",
    "addr:postcode":"02081",
    "addr:street":"Deerfield Dr",
    "iso:country":"US",
    "sg:address":"8 Deerfield Dr",
    "sg:city":"Walpole",
    "sg:classifiers":[
        {
            "category":"Building & Trades",
            "subcategory":"Electrical",
            "type":"Services"
        }
    ],
    "sg:phone":"+1   ",
    "sg:postcode":"02081",
    "sg:province":"MA",
    "sg:tags":[
        "electrical",
        "contractor"
    ],
    "wof:name":"Alan Soundworks Co Inc",
    "wof:placetype":"venue"
},
  "geometry": {"coordinates":[-71.29816599999999,42.133161],"type":"Point"}
}