{
  "type": "Feature",
  "properties": {
    "addr:full": "150 Shrewsbury St Boylston MA 01505",
    "addr:housenumber": "150",
    "addr:postcode": "01505",
    "addr:street": "Shrewsbury St",
    "iso:country": "US",
    "sg:address": "150 Shrewsbury St",
    "sg:city": "Boylston",
    "sg:classifiers": [
      {
        "category": "Bus Charters",
        "type": "Transportation"
      }
    ],
    "sg:phone": "+1 508 869 2696",
    "sg:postcode": "01505",
    "sg:province": "MA",
    "sg:tags": [
      "rental"
    ],
    "wof:name": "First Student Inc",
    "wof:placetype": "venue"
  },
  "geometry": {"coordinates":[-71.729849,42.334311],"type":"Point"}
}
