{
  "type": "Feature",
  "properties": {
    "addr:full":"1373 Washington St Weymouth MA 02189",
    "addr:housenumber":"1373",
    "addr:postcode":"02189",
    "addr:street":"Washington St",
    "iso:country":"US",
    "sg:address":"1373 Washington St",
    "sg:city":"Weymouth",
    "sg:classifiers":[
        {
            "category":"Retail",
            "subcategory":"Auto Rental",
            "type":"Services"
        }
    ],
    "sg:phone":"+1 781 340 7513",
    "sg:postcode":"02189",
    "sg:province":"MA",
    "sg:tags":[
        "renting",
        "truck",
        "leasing"
    ],
    "sg:website":"www.budgettruck.com",
    "wof:name":"Budget Truck Rental",
    "wof:placetype":"venue"
},
  "geometry": {"coordinates":[-70.919301,42.193589],"type":"Point"}
}