{
  "type": "Feature",
  "properties": {
    "iso:country":"US",
    "sg:address":"6 Park St",
    "sg:city":"Rehoboth",
    "sg:classifiers":[
        {
            "category":"Building & Trades",
            "subcategory":"Construction",
            "type":"Services"
        }
    ],
    "sg:phone":"+1   ",
    "sg:postcode":"02769",
    "sg:province":"MA",
    "sg:tags":[
        "excavation",
        "concrete",
        "contractor"
    ],
    "wof:name":"Donnelly Concrete",
    "wof:placetype":"venue"
},
  "geometry": {"coordinates":[-71.253863,41.906654],"type":"Point"}
}