{
  "type": "Feature",
  "properties": {
    "addr:full": "12 E Main St Westborough MA 01581",
    "addr:housenumber": "12",
    "addr:postcode": "01581",
    "addr:street": "E Main St",
    "iso:country": "US",
    "sg:address": "12 E Main St",
    "sg:city": "Westborough",
    "sg:classifiers": [
      {
        "category": "Retail",
        "subcategory": "Laundry \u0026 Dry Cleaning",
        "type": "Services"
      }
    ],
    "sg:phone": "+1 508 366 6463",
    "sg:postcode": "01581",
    "sg:province": "MA",
    "sg:tags": [
      "cleaner",
      "tailoring",
      "alteration",
      "wedding"
    ],
    "wof:name": "Best Cleaners \u0026 Tailors",
    "wof:placetype": "venue"
  },
  "geometry": {"coordinates":[-71.612836,42.27006],"type":"Point"}
}
