{
  "type": "Feature",
  "properties": {
    "iso:country":"US",
    "sg:address":"12 E Main St",
    "sg:city":"Westborough",
    "sg:classifiers":[
        {
            "category":"Retail",
            "subcategory":"Laundry & Dry Cleaning",
            "type":"Services"
        }
    ],
    "sg:phone":"+1 508 366 6463",
    "sg:postcode":"01581",
    "sg:province":"MA",
    "sg:tags":[
        "cleaner",
        "tailoring",
        "alteration",
        "wedding"
    ],
    "wof:name":"Best Cleaners & Tailors",
    "wof:placetype":"venue"
},
  "geometry": {"coordinates":[-71.612836,42.27006],"type":"Point"}
}