{
  "type": "Feature",
  "properties": {
    "iso:country":"US",
    "sg:address":"2 Oakland Ter",
    "sg:city":"Natick",
    "sg:classifiers":[
        {
            "category":"Wholesale",
            "subcategory":"Toys & Hobbies",
            "type":"Manufacturing & Wholesale Goods"
        }
    ],
    "sg:phone":"+1 508 647 9645",
    "sg:postcode":"01760",
    "sg:province":"MA",
    "sg:tags":[
        "firework"
    ],
    "sg:website":"www.magicfire.com",
    "wof:name":"Magic Fire Inc",
    "wof:placetype":"venue"
},
  "geometry": {"coordinates":[-71.358728,42.274789],"type":"Point"}
}