{
  "type": "Feature",
  "properties": {
    "iso:country":"US",
    "sg:address":"12 Sherman Pl",
    "sg:city":"Woburn",
    "sg:classifiers":[
        {
            "category":"Health Services",
            "subcategory":"Medical Lab",
            "type":"Services"
        }
    ],
    "sg:phone":"+1   ",
    "sg:postcode":"01801",
    "sg:province":"MA",
    "sg:tags":[
        "laboratory",
        "dental"
    ],
    "wof:name":"Dinardi Dental Lab",
    "wof:placetype":"venue"
},
  "geometry": {"coordinates":[-71.139544,42.482414],"type":"Point"}
}