{
  "type": "Feature",
  "properties": {
    "addr:full": "181 Charles St North Attleboro MA 02760",
    "addr:housenumber": "181",
    "addr:postcode": "02760",
    "addr:street": "Charles St",
    "iso:country": "US",
    "sg:address": "181 Charles St",
    "sg:city": "North Attleboro",
    "sg:classifiers": [
      {
        "category": "Building \u0026 Trades",
        "subcategory": "Construction",
        "type": "Services"
      }
    ],
    "sg:phone": "+1 508 643 2601",
    "sg:postcode": "02760",
    "sg:province": "MA",
    "sg:tags": [
      "contractor"
    ],
    "wof:name": "Grimaldi Construction Garage",
    "wof:placetype": "venue"
  },
  "geometry": {"coordinates":[-71.326897,41.9725],"type":"Point"}
}
