{
  "type": "Feature",
  "properties": {
    "addr:full": "45 Storey Ave Newburyport MA 01950",
    "addr:housenumber": "45",
    "addr:postcode": "01950",
    "addr:street": "Storey Ave",
    "iso:country": "US",
    "sg:address": "45 Storey Ave",
    "sg:city": "Newburyport",
    "sg:classifiers": [
      {
        "category": "Shopping",
        "subcategory": "Mobile Phones",
        "type": "Retail Goods"
      }
    ],
    "sg:phone": "+1 978 465 5007",
    "sg:postcode": "01950",
    "sg:province": "MA",
    "wof:name": "Freedom Communication",
    "wof:placetype": "venue"
  },
  "geometry": {"coordinates":[-70.906663,42.820872],"type":"Point"}
}
