{
  "type": "Feature",
  "properties": {
    "addr:full": "33 Laxfield Rd Weston MA 02493",
    "addr:housenumber": "33",
    "addr:postcode": "02493",
    "addr:street": "Laxfield Rd",
    "iso:country": "US",
    "sg:address": "33 Laxfield Rd",
    "sg:city": "Weston",
    "sg:classifiers": [
      {
        "category": "Professional",
        "subcategory": "Management \u0026 Consulting",
        "type": "Services"
      }
    ],
    "sg:phone": "+1   ",
    "sg:postcode": "02493",
    "sg:province": "MA",
    "wof:name": "Martin Duhms \u0026 Associates",
    "wof:placetype": "venue"
  },
  "geometry": {"coordinates":[-71.305326,42.374559],"type":"Point"}
}
