{
  "type": "Feature",
  "properties": {
    "iso:country":"US",
    "sg:address":"33 Laxfield Rd",
    "sg:city":"Weston",
    "sg:classifiers":[
        {
            "category":"Professional",
            "subcategory":"Management & Consulting",
            "type":"Services"
        }
    ],
    "sg:phone":"+1   ",
    "sg:postcode":"02493",
    "sg:province":"MA",
    "wof:name":"Martin Duhms & Associates",
    "wof:placetype":"venue"
},
  "geometry": {"coordinates":[-71.30532599999999,42.374559],"type":"Point"}
}