{
  "type": "Feature",
  "properties": {
    "iso:country":"US",
    "sg:address":"289 Commercial St",
    "sg:city":"Provincetown",
    "sg:classifiers":[
        {
            "category":"Shopping",
            "subcategory":"Music",
            "type":"Retail Goods"
        }
    ],
    "sg:phone":"+1 508 487 4416",
    "sg:postcode":"02657",
    "sg:province":"MA",
    "sg:tags":[
        "compact",
        "record",
        "disc",
        "tape"
    ],
    "wof:name":"Strangeways",
    "wof:placetype":"venue"
},
  "geometry": {"coordinates":[-70.18576899999999,42.051808],"type":"Point"}
}