{
  "type": "Feature",
  "properties": {
    "addr:full": "24 Beck Rd Arlington MA 02476",
    "addr:housenumber": "24",
    "addr:postcode": "02476",
    "addr:street": "Beck Rd",
    "iso:country": "US",
    "sg:address": "24 Beck Rd",
    "sg:city": "Arlington",
    "sg:classifiers": [
      {
        "category": "Building \u0026 Trades",
        "subcategory": "Plumbing",
        "type": "Services"
      }
    ],
    "sg:phone": "+1 781 674 2600",
    "sg:postcode": "02476",
    "sg:province": "MA",
    "sg:tags": [
      "plumbing",
      "contractor"
    ],
    "wof:name": "Puopolo E \u0026 Son",
    "wof:placetype": "venue"
  },
  "geometry": {"coordinates":[-71.17441,42.425187],"type":"Point"}
}
