{
  "type": "Feature",
  "properties": {
    "addr:full": "595 Ashmont St Apt 4 Dorchester MA 02122",
    "addr:housenumber": "595;4",
    "addr:postcode": "02122",
    "addr:street": "Ashmont St Apt",
    "iso:country": "US",
    "sg:address": "595 Ashmont St Apt 4",
    "sg:city": "Dorchester",
    "sg:classifiers": [
      {
        "category": "Real Estate",
        "subcategory": "Real Estate Operator",
        "type": "Services"
      }
    ],
    "sg:phone": "+1 617 265 3249",
    "sg:postcode": "02122",
    "sg:province": "MA",
    "sg:tags": [
      "apartment"
    ],
    "wof:name": "Driscoll Management Inc",
    "wof:placetype": "venue"
  },
  "geometry": {"coordinates":[-71.04866,42.290031],"type":"Point"}
}
