{
  "type": "Feature",
  "properties": {
    "addr:full":"101 Nash Rd New Bedford MA 02746",
    "addr:housenumber":"101",
    "addr:postcode":"02746",
    "addr:street":"Nash Rd",
    "iso:country":"US",
    "sg:address":"101 Nash Rd",
    "sg:city":"New Bedford",
    "sg:classifiers":[
        {
            "category":"Autos & Motor Vehicles",
            "subcategory":"Auto Supplies",
            "type":"Retail Goods"
        }
    ],
    "sg:phone":"+1 508 992 4999",
    "sg:postcode":"02746",
    "sg:province":"MA",
    "sg:tags":[
        "automobile",
        "alarm"
    ],
    "wof:name":"Auto Alarms & Accessories",
    "wof:placetype":"venue"
},
  "geometry": {"coordinates":[-70.92277799999999,41.667294],"type":"Point"}
}