{
  "type": "Feature",
  "properties": {
    "iso:country":"US",
    "sg:address":"301 Old Stevens Rd",
    "sg:city":"Swansea",
    "sg:classifiers":[
        {
            "category":"Manufacturing",
            "subcategory":"Signs",
            "type":"Manufacturing & Wholesale Goods"
        }
    ],
    "sg:phone":"+1 508 676 0711",
    "sg:postcode":"02777",
    "sg:province":"MA",
    "wof:name":"Lee Sign Rental",
    "wof:placetype":"venue"
},
  "geometry": {"coordinates":[-71.170216,41.751377],"type":"Point"}
}