{
  "type": "Feature",
  "properties": {
    "iso:country":"US",
    "sg:address":"615 Nantasket Ave",
    "sg:city":"Hull",
    "sg:classifiers":[
        {
            "category":"Building & Trades",
            "subcategory":"Landscaping Services",
            "type":"Services"
        }
    ],
    "sg:phone":"+1 781 925 3009",
    "sg:postcode":"02045",
    "sg:province":"MA",
    "sg:tags":[
        "lawn"
    ],
    "wof:name":"Marquez Landscape",
    "wof:placetype":"venue"
},
  "geometry": {"coordinates":[-70.87700700000001,42.288059],"type":"Point"}
}