{
  "type": "Feature",
  "properties": {
    "addr:full": "25 Mansfield Rd Wellesley MA 02481",
    "addr:housenumber": "25",
    "addr:postcode": "02481",
    "addr:street": "Mansfield Rd",
    "iso:country": "US",
    "sg:address": "25 Mansfield Rd",
    "sg:city": "Wellesley",
    "sg:classifiers": [
      {
        "category": "Professional",
        "type": "Services"
      }
    ],
    "sg:phone": "+1   ",
    "sg:postcode": "02481",
    "sg:province": "MA",
    "wof:name": "Julio Medeiros",
    "wof:placetype": "venue"
  },
  "geometry": {"coordinates":[-71.305074,42.307616],"type":"Point"}
}
