{
  "type": "Feature",
  "properties": {
    "addr:full": "1549 Acushnet Ave New Bedford MA 02746",
    "addr:housenumber": "1549",
    "addr:postcode": "02746",
    "addr:street": "Acushnet Ave",
    "iso:country": "US",
    "sg:address": "1549 Acushnet Ave",
    "sg:city": "New Bedford",
    "sg:classifiers": [
      {
        "category": "Education",
        "subcategory": "Special Training",
        "type": "Public Place"
      }
    ],
    "sg:phone": "+1   ",
    "sg:postcode": "02746",
    "sg:province": "MA",
    "sg:tags": [
      "school",
      "driving"
    ],
    "wof:name": "A1 Driving School Inc",
    "wof:placetype": "venue"
  },
  "geometry": {"coordinates":[-70.928575,41.663217],"type":"Point"}
}
