{
  "type": "Feature",
  "properties": {
    "iso:country":"US",
    "sg:address":"34 Fisher St",
    "sg:city":"Westborough",
    "sg:classifiers":[
        {
            "category":"Building & Trades",
            "subcategory":"Construction",
            "type":"Services"
        }
    ],
    "sg:phone":"+1   ",
    "sg:postcode":"01581",
    "sg:province":"MA",
    "sg:tags":[
        "painting",
        "contractor"
    ],
    "wof:name":"Capital Painting",
    "wof:placetype":"venue"
},
  "geometry": {"coordinates":[-71.62842999999999,42.270962],"type":"Point"}
}