{
  "type": "Feature",
  "properties": {
    "addr:full": "34 Fisher St Westborough MA 01581",
    "addr:housenumber": "34",
    "addr:postcode": "01581",
    "addr:street": "Fisher St",
    "iso:country": "US",
    "sg:address": "34 Fisher St",
    "sg:city": "Westborough",
    "sg:classifiers": [
      {
        "category": "Building \u0026 Trades",
        "subcategory": "Construction",
        "type": "Services"
      }
    ],
    "sg:phone": "+1   ",
    "sg:postcode": "01581",
    "sg:province": "MA",
    "sg:tags": [
      "painting",
      "contractor"
    ],
    "wof:name": "Capital Painting",
    "wof:placetype": "venue"
  },
  "geometry": {"coordinates":[-71.62843,42.270962],"type":"Point"}
}
