{
  "type": "Feature",
  "properties": {
    "addr:full":"700 E Broadway Boston MA 02127",
    "addr:housenumber":"700",
    "addr:postcode":"02127",
    "addr:street":"E Broadway",
    "iso:country":"US",
    "sg:address":"700 E Broadway",
    "sg:city":"Boston",
    "sg:classifiers":[
        {
            "category":"Real Estate",
            "subcategory":"Real Estate Services",
            "type":"Services"
        },
        {
            "category":"Real Estate",
            "subcategory":"Real Estate Agent",
            "type":"Services"
        }
    ],
    "sg:phone":"+1 617 269 1000",
    "sg:postcode":"02127",
    "sg:province":"MA",
    "sg:tags":[
        "buyer",
        "management",
        "broker"
    ],
    "sg:website":"http://www.southboston.net",
    "wof:name":"Rooney Real Estate",
    "wof:placetype":"venue"
},
  "geometry": {"coordinates":[-71.03730299999999,42.33575],"type":"Point"}
}