{
  "type": "Feature",
  "properties": {
    "iso:country":"US",
    "sg:address":"366 Huron Ave",
    "sg:city":"Cambridge",
    "sg:classifiers":[
        {
            "category":"Personal",
            "subcategory":"Beauty Salon",
            "type":"Services"
        }
    ],
    "sg:phone":"+1 617 354 1311",
    "sg:postcode":"02138",
    "sg:province":"MA",
    "sg:tags":[
        "hair"
    ],
    "wof:name":"The Salon @ Huron Village",
    "wof:placetype":"venue"
},
  "geometry": {"coordinates":[-71.138824,42.381144],"type":"Point"}
}