{
  "type": "Feature",
  "properties": {
    "iso:country":"US",
    "sg:address":"11 Cushing Pl",
    "sg:city":"Chelmsford",
    "sg:classifiers":[
        {
            "category":"Home & Garden",
            "subcategory":"Garden Supply",
            "type":"Retail Goods"
        }
    ],
    "sg:phone":"+1 978 256 1123",
    "sg:postcode":"01824",
    "sg:province":"MA",
    "sg:tags":[
        "landscaping",
        "equipment"
    ],
    "wof:name":"Green Industry Distributors",
    "wof:placetype":"venue"
},
  "geometry": {"coordinates":[-71.35263,42.596196],"type":"Point"}
}