{
  "type": "Feature",
  "properties": {
    "iso:country":"US",
    "sg:address":"40 School St",
    "sg:city":"Greenfield",
    "sg:classifiers":[
        {
            "category":"Real Estate",
            "subcategory":"Real Estate Agent",
            "type":"Services"
        }
    ],
    "sg:phone":"+1 413 774 6447",
    "sg:postcode":"01301",
    "sg:province":"MA",
    "wof:name":"Virgilio Dahna Real Estate",
    "wof:placetype":"venue"
},
  "geometry": {"coordinates":[-72.60095200000001,42.589605],"type":"Point"}
}