{
  "type": "Feature",
  "properties": {
    "iso:country":"US",
    "sg:address":"199 Church St",
    "sg:city":"Harwich",
    "sg:classifiers":[
        {
            "category":"Retail",
            "subcategory":"Repair Shop",
            "type":"Services"
        }
    ],
    "sg:phone":"+1   ",
    "sg:postcode":"02645",
    "sg:province":"MA",
    "wof:name":"Bosetti Septic Systems",
    "wof:placetype":"venue"
},
  "geometry": {"coordinates":[-70.01063499999999,41.710423],"type":"Point"}
}