{
  "type": "Feature",
  "properties": {
    "addr:full":"149 Main St Watertown MA 02472",
    "addr:housenumber":"149",
    "addr:postcode":"02472",
    "addr:street":"Main St",
    "iso:country":"US",
    "sg:address":"149 Main St",
    "sg:city":"Watertown",
    "sg:classifiers":[
        {
            "category":"Government",
            "subcategory":"Court House",
            "type":"Public Place"
        }
    ],
    "sg:phone":"+1 617 972 6464",
    "sg:postcode":"02472",
    "sg:province":"MA",
    "sg:tags":[
        "city",
        "counsel"
    ],
    "wof:name":"Watertown Town Attorney",
    "wof:placetype":"venue"
},
  "geometry": {"coordinates":[-71.18791899999999,42.367658],"type":"Point"}
}