{
  "type": "Feature",
  "properties": {
    "iso:country":"US",
    "sg:address":"2 Barry Dr",
    "sg:city":"Framingham",
    "sg:classifiers":[
        {
            "category":"Professional",
            "subcategory":"Management & Consulting",
            "type":"Services"
        }
    ],
    "sg:phone":"+1   ",
    "sg:postcode":"01702",
    "sg:province":"MA",
    "sg:tags":[
        "business"
    ],
    "wof:name":"S Finn & Co Inc",
    "wof:placetype":"venue"
},
  "geometry": {"coordinates":[-71.45433800000001,42.279833],"type":"Point"}
}