{
  "type": "Feature",
  "properties": {
    "iso:country":"US",
    "sg:address":"61 Union St",
    "sg:city":"Brighton",
    "sg:classifiers":[
        {
            "category":"Retail",
            "subcategory":"Animal Services",
            "type":"Services"
        }
    ],
    "sg:phone":"+1 617 787 1386",
    "sg:postcode":"02135",
    "sg:province":"MA",
    "sg:tags":[
        "pet",
        "boarding",
        "sitting"
    ],
    "wof:name":"Ms Paws",
    "wof:placetype":"venue"
},
  "geometry": {"coordinates":[-71.14970599999999,42.345459],"type":"Point"}
}