{
  "type": "Feature",
  "properties": {
    "addr:full": "123 South Street Boston MA 02111",
    "addr:housenumber": "123",
    "addr:postcode": "02111",
    "addr:street": "South Street",
    "iso:country": "US",
    "sg:address": "123 South Street",
    "sg:city": "Boston",
    "sg:classifiers": [
      {
        "category": "Personal",
        "subcategory": "Beauty Salon",
        "type": "Services"
      }
    ],
    "sg:phone": "+1 617 451 3516",
    "sg:postcode": "02111",
    "sg:province": "MA",
    "sg:tags": [
      "hair"
    ],
    "wof:name": "Niki South Street Salon",
    "wof:placetype": "venue"
  },
  "geometry": {"coordinates":[-71.057394,42.351392],"type":"Point"}
}
