{
  "type": "Feature",
  "properties": {
    "addr:full": "1 N Beacon Street Boston MA 02134",
    "addr:housenumber": "1",
    "addr:postcode": "02134",
    "addr:street": "N Beacon Street",
    "iso:country": "US",
    "sg:address": "1 N Beacon Street",
    "sg:city": "Boston",
    "sg:classifiers": [
      {
        "category": "Professional",
        "subcategory": "Lawyer \u0026 Legal Services",
        "type": "Services"
      }
    ],
    "sg:phone": "+1 617 523 8400",
    "sg:postcode": "02134",
    "sg:province": "MA",
    "wof:name": "Wolkon \u0026 Pascucci Llp",
    "wof:placetype": "venue"
  },
  "geometry": {"coordinates":[-71.137529,42.3535],"type":"Point"}
}
