{
  "type": "Feature",
  "properties": {
    "addr:full": "1207 Acushnet Ave New Bedford MA 02746",
    "addr:housenumber": "1207",
    "addr:postcode": "02746",
    "addr:street": "Acushnet Ave",
    "iso:country": "US",
    "sg:address": "1207 Acushnet Ave",
    "sg:city": "New Bedford",
    "sg:classifiers": [
      {
        "category": "Shopping",
        "subcategory": "Pharmacy",
        "type": "Retail Goods"
      }
    ],
    "sg:phone": "+1 508 994 7298",
    "sg:postcode": "02746",
    "sg:province": "MA",
    "wof:name": "Brooks Pharmacy",
    "wof:placetype": "venue"
  },
  "geometry": {"coordinates":[-70.927358,41.65837],"type":"Point"}
}
