{
  "type": "Feature",
  "properties": {
    "iso:country":"US",
    "sg:address":"209 Shrewsbury St",
    "sg:city":"Worcester",
    "sg:classifiers":[
        {
            "category":"Wholesale",
            "subcategory":"Auto Parts",
            "type":"Manufacturing & Wholesale Goods"
        }
    ],
    "sg:phone":"+1 508 752 0960",
    "sg:postcode":"01604",
    "sg:province":"MA",
    "sg:tags":[
        "body",
        "automobile",
        "shop"
    ],
    "wof:name":"R M Suppliers Inc",
    "wof:placetype":"venue"
},
  "geometry": {"coordinates":[-71.784538,42.266214],"type":"Point"}
}