{
  "type": "Feature",
  "properties": {
    "addr:full": "89 Middleboro Rd East Freetown MA 02717",
    "addr:housenumber": "89",
    "addr:postcode": "02717",
    "addr:street": "Middleboro Rd",
    "iso:country": "US",
    "sg:address": "89 Middleboro Rd",
    "sg:city": "East Freetown",
    "sg:classifiers": [
      {
        "category": "Organizations",
        "subcategory": "Community Association",
        "type": "Services"
      }
    ],
    "sg:phone": "+1 508 763 8885",
    "sg:postcode": "02717",
    "sg:province": "MA",
    "sg:tags": [
      "club"
    ],
    "wof:name": "Veterans Of Foreign Wars",
    "wof:placetype": "venue"
  },
  "geometry": {"coordinates":[-70.942285,41.765712],"type":"Point"}
}
