{
  "type": "Feature",
  "properties": {
    "iso:country":"US",
    "sg:address":"89 Middleboro Rd",
    "sg:city":"East Freetown",
    "sg:classifiers":[
        {
            "category":"Organizations",
            "subcategory":"Community Association",
            "type":"Services"
        }
    ],
    "sg:phone":"+1 508 763 8885",
    "sg:postcode":"02717",
    "sg:province":"MA",
    "sg:tags":[
        "club"
    ],
    "wof:name":"Veterans Of Foreign Wars",
    "wof:placetype":"venue"
},
  "geometry": {"coordinates":[-70.942285,41.765712],"type":"Point"}
}