{
  "type": "Feature",
  "properties": {
    "iso:country":"US",
    "sg:address":"61 Lincoln St",
    "sg:city":"Framingham",
    "sg:classifiers":[
        {
            "category":"Health Services",
            "subcategory":"Doctor",
            "type":"Services"
        }
    ],
    "sg:phone":"+1 508 628 0205",
    "sg:postcode":"01702",
    "sg:province":"MA",
    "sg:tags":[
        "clinic"
    ],
    "wof:name":"Outpatient Clinic Va Hlthcr",
    "wof:placetype":"venue"
},
  "geometry": {"coordinates":[-71.41774599999999,42.283028],"type":"Point"}
}