{
  "type": "Feature",
  "properties": {
    "addr:full": "400 Mystic Avenue Somerville MA 02145",
    "addr:housenumber": "400",
    "addr:postcode": "02145",
    "addr:street": "Mystic Avenue",
    "iso:country": "US",
    "sg:address": "400 Mystic Avenue",
    "sg:city": "Somerville",
    "sg:classifiers": [
      {
        "category": "Building \u0026 Trades",
        "subcategory": "Plumbing",
        "type": "Services"
      }
    ],
    "sg:phone": "+1 617 623 6609",
    "sg:postcode": "02145",
    "sg:province": "MA",
    "wof:name": "CJ Doherty Inc",
    "wof:placetype": "venue"
  },
  "geometry": {"coordinates":[-71.088009,42.39472],"type":"Point"}
}
