{
  "type": "Feature",
  "properties": {
    "addr:full":"3 Margaret Dr Norton MA 02766",
    "addr:housenumber":"3",
    "addr:postcode":"02766",
    "addr:street":"Margaret Dr",
    "iso:country":"US",
    "sg:address":"3 Margaret Dr",
    "sg:city":"Norton",
    "sg:classifiers":[
        {
            "category":"Professional",
            "type":"Services"
        }
    ],
    "sg:phone":"+1 508 285 8558",
    "sg:postcode":"02766",
    "sg:province":"MA",
    "sg:tags":[
        "sporting",
        "good"
    ],
    "wof:name":"Reach the Beach Inc",
    "wof:placetype":"venue"
},
  "geometry": {"coordinates":[-71.19528699999999,41.94651],"type":"Point"}
}