{
  "type": "Feature",
  "properties": {
    "addr:full":"71 S Nelson Rd Sterling MA 01564",
    "addr:housenumber":"71",
    "addr:postcode":"01564",
    "addr:street":"S Nelson Rd",
    "iso:country":"US",
    "sg:address":"71 S Nelson Rd",
    "sg:city":"Sterling",
    "sg:classifiers":[
        {
            "category":"Professional",
            "subcategory":"Detective & Security Services",
            "type":"Services"
        }
    ],
    "sg:phone":"+1 978 422 7395",
    "sg:postcode":"01564",
    "sg:province":"MA",
    "sg:tags":[
        "information",
        "bureau"
    ],
    "wof:name":"Horse Services Inc",
    "wof:placetype":"venue"
},
  "geometry": {"coordinates":[-71.79540900000001,42.454845],"type":"Point"}
}