{
  "type": "Feature",
  "properties": {
    "addr:full":"218 South St Waltham MA 02453",
    "addr:housenumber":"218",
    "addr:postcode":"02453",
    "addr:street":"South St",
    "iso:country":"US",
    "sg:address":"218 South St",
    "sg:city":"Waltham",
    "sg:classifiers":[
        {
            "category":"Social Services",
            "subcategory":"Child Care",
            "type":"Services"
        }
    ],
    "sg:phone":"+1 781 647 6564",
    "sg:postcode":"02453",
    "sg:province":"MA",
    "sg:tags":[
        "nursery",
        "day"
    ],
    "wof:name":"Charles River Early Interv Ctr",
    "wof:placetype":"venue"
},
  "geometry": {"coordinates":[-71.25102200000001,42.368481],"type":"Point"}
}