{
  "type": "Feature",
  "properties": {
    "iso:country":"US",
    "sg:address":"8 Old Town Rd",
    "sg:city":"Beverly",
    "sg:classifiers":[
        {
            "category":"Professional",
            "subcategory":"Business Services",
            "type":"Services"
        }
    ],
    "sg:phone":"+1   ",
    "sg:postcode":"01915",
    "sg:province":"MA",
    "sg:tags":[
        "printing",
        "broker"
    ],
    "wof:name":"RC Sheedy & Associates",
    "wof:placetype":"venue"
},
  "geometry": {"coordinates":[-70.837986,42.590317],"type":"Point"}
}