{
  "type": "Feature",
  "properties": {
    "addr:full": "33 Old Elm St North Billerica MA 01862",
    "addr:housenumber": "33",
    "addr:postcode": "01862",
    "addr:street": "Old Elm St",
    "iso:country": "US",
    "sg:address": "33 Old Elm St",
    "sg:city": "North Billerica",
    "sg:classifiers": [
      {
        "category": "Real Estate",
        "subcategory": "Real Estate Agent",
        "type": "Services"
      }
    ],
    "sg:phone": "+1   ",
    "sg:postcode": "01862",
    "sg:province": "MA",
    "wof:name": "Rl Hillson Inc",
    "wof:placetype": "venue"
  },
  "geometry": {"coordinates":[-71.28738,42.589983],"type":"Point"}
}
