{
  "type": "Feature",
  "properties": {
    "addr:full": "40 Grafton Cir Shrewsbury MA 01545",
    "addr:housenumber": "40",
    "addr:postcode": "01545",
    "addr:street": "Grafton Cir",
    "iso:country": "US",
    "sg:address": "40 Grafton Cir",
    "sg:city": "Shrewsbury",
    "sg:classifiers": [
      {
        "category": "Shopping",
        "subcategory": "Used Merchandise",
        "type": "Retail Goods"
      }
    ],
    "sg:phone": "+1 508 842 4472",
    "sg:postcode": "01545",
    "sg:province": "MA",
    "sg:tags": [
      "furniture"
    ],
    "wof:name": "Specialty Shoppe",
    "wof:placetype": "venue"
  },
  "geometry": {"coordinates":[-71.71109,42.27486],"type":"Point"}
}
