{
  "type": "Feature",
  "properties": {
    "addr:full":"873 Main St Ashby MA 01431",
    "addr:housenumber":"873",
    "addr:postcode":"01431",
    "addr:street":"Main St",
    "iso:country":"US",
    "sg:address":"873 Main St",
    "sg:city":"Ashby",
    "sg:classifiers":[
        {
            "category":"Insurance",
            "subcategory":"Insurance Agent",
            "type":"Services"
        }
    ],
    "sg:phone":"+1 978 386 7050",
    "sg:postcode":"01431",
    "sg:province":"MA",
    "wof:name":"Choice Insurance Inc",
    "wof:placetype":"venue"
},
  "geometry": {"coordinates":[-71.829899,42.68044],"type":"Point"}
}