{
  "type": "Feature",
  "properties": {
    "addr:full":"150 Coolidge St Hudson MA 01749",
    "addr:housenumber":"150",
    "addr:postcode":"01749",
    "addr:street":"Coolidge St",
    "iso:country":"US",
    "sg:address":"150 Coolidge St",
    "sg:city":"Hudson",
    "sg:classifiers":[
        {
            "category":"Personal",
            "subcategory":"Beauty Salon",
            "type":"Services"
        }
    ],
    "sg:phone":"+1 978 562 7697",
    "sg:postcode":"01749",
    "sg:province":"MA",
    "sg:tags":[
        "manicuring"
    ],
    "sg:website":"www.thefragrantpath.com",
    "wof:name":"Fragrant Path",
    "wof:placetype":"venue"
},
  "geometry": {"coordinates":[-71.593022,42.396731],"type":"Point"}
}