{
  "type": "Feature",
  "properties": {
    "addr:full":"119 Chapin Rd Hudson MA 01749",
    "addr:housenumber":"119",
    "addr:postcode":"01749",
    "addr:street":"Chapin Rd",
    "iso:country":"US",
    "sg:address":"119 Chapin Rd",
    "sg:city":"Hudson",
    "sg:classifiers":[
        {
            "category":"Social Services",
            "type":"Services"
        }
    ],
    "sg:phone":"+1 978 562 6199",
    "sg:postcode":"01749",
    "sg:province":"MA",
    "sg:tags":[
        "youth",
        "organization",
        "center"
    ],
    "wof:name":"Hudson Youth Baseball",
    "wof:placetype":"venue"
},
  "geometry": {"coordinates":[-71.584925,42.379596],"type":"Point"}
}