{
  "type": "Feature",
  "properties": {
    "iso:country":"US",
    "sg:address":"735 Broadway",
    "sg:city":"Everett",
    "sg:classifiers":[
        {
            "category":"Autos & Motor Vehicles",
            "subcategory":"Automobile Sales",
            "type":"Retail Goods"
        }
    ],
    "sg:phone":"+1 617 389 2991",
    "sg:postcode":"02149",
    "sg:province":"MA",
    "sg:tags":[
        "car",
        "dealer"
    ],
    "wof:name":"Glendale Auto Sales",
    "wof:placetype":"venue"
},
  "geometry": {"coordinates":[-71.04767699999999,42.415631],"type":"Point"}
}