{
  "type": "Feature",
  "properties": {
    "addr:full":"6 Taunton St Plainville MA 02762",
    "addr:housenumber":"6",
    "addr:postcode":"02762",
    "addr:street":"Taunton St",
    "iso:country":"US",
    "sg:address":"6 Taunton St",
    "sg:city":"Plainville",
    "sg:classifiers":[
        {
            "category":"Fast Food",
            "type":"Food & Drink"
        },
        {
            "category":"Food & Beverages",
            "subcategory":"Meat & Fish",
            "type":"Retail Goods"
        }
    ],
    "sg:phone":"+1 508 695 1664",
    "sg:postcode":"02762",
    "sg:province":"MA",
    "sg:tags":[
        "burger",
        "hot",
        "dog"
    ],
    "sg:website":"www.burgerking.com",
    "wof:name":"Burger King Family Restaurants",
    "wof:placetype":"venue"
},
  "geometry": {"coordinates":[-71.30500000000001,42.009998],"type":"Point"}
}