{
  "type": "Feature",
  "properties": {
    "iso:country":"US",
    "sg:address":"1 Russell St",
    "sg:city":"Peabody",
    "sg:classifiers":[
        {
            "category":"Building & Trades",
            "subcategory":"Construction",
            "type":"Services"
        }
    ],
    "sg:phone":"+1   ",
    "sg:postcode":"01960",
    "sg:province":"MA",
    "sg:tags":[
        "equipment",
        "installation"
    ],
    "wof:name":"Malcolm Ent",
    "wof:placetype":"venue"
},
  "geometry": {"coordinates":[-71.000523,42.551279],"type":"Point"}
}