{
  "type": "Feature",
  "properties": {
    "iso:country":"US",
    "sg:address":"317 Main St",
    "sg:city":"Falmouth",
    "sg:classifiers":[
        {
            "category":"Shopping",
            "type":"Retail Goods"
        }
    ],
    "sg:phone":"+1 508 457 5533",
    "sg:postcode":"02540",
    "sg:province":"MA",
    "sg:tags":[
        "art",
        "gallery",
        "merchandise",
        "dealer"
    ],
    "sg:website":"www.jancollinsselman.com",
    "wof:name":"Jan Collins Selman Fine Art",
    "wof:placetype":"venue"
},
  "geometry": {"coordinates":[-70.613732,41.552053],"type":"Point"}
}