{
  "type": "Feature",
  "properties": {
    "addr:full": "154 Broadway Hanover MA 02339",
    "addr:housenumber": "154",
    "addr:postcode": "02339",
    "addr:street": "Broadway",
    "iso:country": "US",
    "sg:address": "154 Broadway",
    "sg:city": "Hanover",
    "sg:classifiers": [
      {
        "category": "Insurance",
        "subcategory": "Insurance Agent",
        "type": "Services"
      }
    ],
    "sg:phone": "+1 781 829 0247",
    "sg:postcode": "02339",
    "sg:province": "MA",
    "wof:name": "David W Luce Insurance",
    "wof:placetype": "venue"
  },
  "geometry": {"coordinates":[-70.812879,42.113335],"type":"Point"}
}
