{
  "type": "Feature",
  "properties": {
    "iso:country":"US",
    "sg:address":"1 Canal St",
    "sg:city":"Salem",
    "sg:classifiers":[
        {
            "category":"Retail",
            "subcategory":"Car Wash",
            "type":"Services"
        }
    ],
    "sg:phone":"+1 978 740 2962",
    "sg:postcode":"01970",
    "sg:province":"MA",
    "sg:tags":[
        "automobile",
        "detail",
        "clean"
    ],
    "wof:name":"Price Auto Detailing",
    "wof:placetype":"venue"
},
  "geometry": {"coordinates":[-70.89573300000001,42.516858],"type":"Point"}
}