{
  "type": "Feature",
  "properties": {
    "iso:country":"US",
    "sg:address":"962 Carew St",
    "sg:city":"Springfield",
    "sg:classifiers":[
        {
            "category":"Education",
            "subcategory":"School",
            "type":"Public Place"
        }
    ],
    "sg:phone":"+1 413 787 7299",
    "sg:postcode":"01104",
    "sg:province":"MA",
    "wof:name":"Liberty Elementary School",
    "wof:placetype":"venue"
},
  "geometry": {"coordinates":[-72.579337,42.129137],"type":"Point"}
}