{
  "type": "Feature",
  "properties": {
    "addr:full": "18 Arnold St New Bedford MA 02740",
    "addr:housenumber": "18",
    "addr:postcode": "02740",
    "addr:street": "Arnold St",
    "iso:country": "US",
    "sg:address": "18 Arnold St",
    "sg:city": "New Bedford",
    "sg:classifiers": [
      {
        "category": "Professional",
        "subcategory": "Advertising",
        "type": "Services"
      }
    ],
    "sg:phone": "+1 508 990 2154",
    "sg:postcode": "02740",
    "sg:province": "MA",
    "sg:tags": [
      "counselor"
    ],
    "wof:name": "Out Of The Box Creative",
    "wof:placetype": "venue"
  },
  "geometry": {"coordinates":[-70.930638,41.631934],"type":"Point"}
}
