{
  "type": "Feature",
  "properties": {
    "iso:country":"US",
    "sg:address":"257 W Main St",
    "sg:city":"Dudley",
    "sg:classifiers":[
        {
            "category":"Shopping",
            "type":"Retail Goods"
        }
    ],
    "sg:phone":"+1   ",
    "sg:postcode":"01571",
    "sg:province":"MA",
    "sg:tags":[
        "merchandise"
    ],
    "wof:name":"Jmro Enterprise",
    "wof:placetype":"venue"
},
  "geometry": {"coordinates":[-71.91875400000001,42.037058],"type":"Point"}
}