{
  "type": "Feature",
  "properties": {
    "addr:full": "257 W Main St Dudley MA 01571",
    "addr:housenumber": "257",
    "addr:postcode": "01571",
    "addr:street": "W Main St",
    "iso:country": "US",
    "sg:address": "257 W Main St",
    "sg:city": "Dudley",
    "sg:classifiers": [
      {
        "category": "Shopping",
        "type": "Retail Goods"
      }
    ],
    "sg:phone": "+1   ",
    "sg:postcode": "01571",
    "sg:province": "MA",
    "sg:tags": [
      "merchandise"
    ],
    "wof:name": "Jmro Enterprise",
    "wof:placetype": "venue"
  },
  "geometry": {"coordinates":[-71.918754,42.037058],"type":"Point"}
}
