{
  "type": "Feature",
  "properties": {
    "iso:country":"US",
    "sg:address":"128 Garden St",
    "sg:city":"Cambridge",
    "sg:classifiers":[
        {
            "category":"Professional",
            "type":"Services"
        }
    ],
    "sg:phone":"+1 617 497 5335",
    "sg:postcode":"02138",
    "sg:province":"MA",
    "sg:tags":[
        "arts",
        "artist"
    ],
    "sg:website":"www.joywaldman.com",
    "wof:name":"Garden Street Studio",
    "wof:placetype":"venue"
},
  "geometry": {"coordinates":[-71.131162,42.384758],"type":"Point"}
}