{
  "type": "Feature",
  "properties": {
    "iso:country":"US",
    "sg:address":"467 Cheshire Rd",
    "sg:city":"Pittsfield",
    "sg:classifiers":[
        {
            "category":"Government",
            "subcategory":"Jail",
            "type":"Public Place"
        }
    ],
    "sg:phone":"+1   ",
    "sg:postcode":"01201",
    "sg:province":"MA",
    "sg:tags":[
        "correctional",
        "institution"
    ],
    "wof:name":"House of Correction",
    "wof:placetype":"venue"
},
  "geometry": {"coordinates":[-73.202816,42.482509],"type":"Point"}
}