{
  "type": "Feature",
  "properties": {
    "addr:full":"336 Adams St Dorchester MA 02122",
    "addr:housenumber":"336",
    "addr:postcode":"02122",
    "addr:street":"Adams St",
    "iso:country":"US",
    "sg:address":"336 Adams St",
    "sg:city":"Dorchester",
    "sg:classifiers":[
        {
            "category":"Building & Trades",
            "subcategory":"Construction",
            "type":"Services"
        }
    ],
    "sg:phone":"+1 617 287 8919",
    "sg:postcode":"02122",
    "sg:province":"MA",
    "sg:tags":[
        "resurfacing",
        "laying",
        "refinishing",
        "floor"
    ],
    "wof:name":"Vincent's Hardwood Floors",
    "wof:placetype":"venue"
},
  "geometry": {"coordinates":[-71.056849,42.298136],"type":"Point"}
}