{
  "type": "Feature",
  "properties": {
    "iso:country":"US",
    "sg:address":"89 Falmouth Heights Rd",
    "sg:city":"Falmouth",
    "sg:classifiers":[
        {
            "category":"Recreation",
            "subcategory":"Marina",
            "type":"Entertainment"
        }
    ],
    "sg:phone":"+1 508 540 3611",
    "sg:postcode":"02540",
    "sg:province":"MA",
    "sg:tags":[
        "yard",
        "boat"
    ],
    "sg:website":"www.eastmarine.com",
    "wof:name":"East Marine Falmouth LLC",
    "wof:placetype":"venue"
},
  "geometry": {"coordinates":[-70.600128,41.55004],"type":"Point"}
}