{
  "type": "Feature",
  "properties": {
    "addr:full":"10 Pearl St Dedham MA 02026",
    "addr:housenumber":"10",
    "addr:postcode":"02026",
    "addr:street":"Pearl St",
    "iso:country":"US",
    "sg:address":"10 Pearl St",
    "sg:city":"Dedham",
    "sg:classifiers":[
        {
            "category":"Professional",
            "subcategory":"Lawyer & Legal Services",
            "type":"Services"
        }
    ],
    "sg:phone":"+1 781 326 8585",
    "sg:postcode":"02026",
    "sg:province":"MA",
    "sg:tags":[
        "attorney"
    ],
    "wof:name":"Puopolo & Carr",
    "wof:placetype":"venue"
},
  "geometry": {"coordinates":[-71.175862,42.24829],"type":"Point"}
}