{
  "type": "Feature",
  "properties": {
    "addr:full":"112 Westfield St West Springfield MA 01089",
    "addr:housenumber":"112",
    "addr:postcode":"01089",
    "addr:street":"Westfield St",
    "iso:country":"US",
    "sg:address":"112 Westfield St",
    "sg:city":"West Springfield",
    "sg:classifiers":[
        {
            "category":"Banks & Credit Unions",
            "subcategory":"Bank",
            "type":"Services"
        }
    ],
    "sg:phone":"+1 413 734 1600",
    "sg:postcode":"01089",
    "sg:province":"MA",
    "sg:tags":[
        "loan",
        "real estate"
    ],
    "wof:name":"H & R Block Mortgage Corp",
    "wof:placetype":"venue"
},
  "geometry": {"coordinates":[-72.625288,42.10642],"type":"Point"}
}