{
  "type": "Feature",
  "properties": {
    "addr:full": "20 Park Plz Ste 479 Boston MA 02116",
    "addr:housenumber": "20",
    "addr:postcode": "02116",
    "addr:street": "Park Plz Ste 479",
    "iso:country": "US",
    "sg:address": "20 Park Plz Ste 479",
    "sg:city": "Boston",
    "sg:classifiers": [
      {
        "category": "Professional",
        "subcategory": "Lawyer \u0026 Legal Services",
        "type": "Services"
      }
    ],
    "sg:phone": "+1 617 948 2516",
    "sg:postcode": "02116",
    "sg:province": "MA",
    "wof:name": "Moynihan Partners",
    "wof:placetype": "venue"
  },
  "geometry": {"coordinates":[-71.069091,42.351543],"type":"Point"}
}
