{
  "type": "Feature",
  "properties": {
    "addr:full":"1330 Washington St Norwood MA 02062",
    "addr:housenumber":"1330",
    "addr:postcode":"02062",
    "addr:street":"Washington St",
    "iso:country":"US",
    "sg:address":"1330 Washington St",
    "sg:city":"Norwood",
    "sg:classifiers":[
        {
            "category":"Personal",
            "type":"Services"
        }
    ],
    "sg:phone":"+1   ",
    "sg:postcode":"02062",
    "sg:province":"MA",
    "wof:name":"Germino Consulting",
    "wof:placetype":"venue"
},
  "geometry": {"coordinates":[-71.211026,42.168953],"type":"Point"}
}