{
  "type": "Feature",
  "properties": {
    "addr:full":"1 India St Boston MA 02109",
    "addr:housenumber":"1",
    "addr:postcode":"02109",
    "addr:street":"India St",
    "iso:country":"US",
    "sg:address":"1 India St",
    "sg:city":"Boston",
    "sg:classifiers":[
        {
            "category":"Real Estate",
            "subcategory":"Real Estate Operator",
            "type":"Services"
        }
    ],
    "sg:phone":"+1 310 444 2204",
    "sg:postcode":"02109",
    "sg:province":"MA",
    "sg:tags":[
        "hotel",
        "apartment"
    ],
    "wof:name":"Oakwood Corporate Housing",
    "wof:placetype":"venue"
},
  "geometry": {"coordinates":[-71.05407,42.35928],"type":"Point"}
}