{
  "type": "Feature",
  "properties": {
    "addr:full": "112 Spruce St Leominster MA 01453",
    "addr:housenumber": "112",
    "addr:postcode": "01453",
    "addr:street": "Spruce St",
    "iso:country": "US",
    "sg:address": "112 Spruce St",
    "sg:city": "Leominster",
    "sg:classifiers": [
      {
        "category": "Social Services",
        "type": "Services"
      }
    ],
    "sg:phone": "+1 978 534 3145",
    "sg:postcode": "01453",
    "sg:province": "MA",
    "sg:tags": [
      "organization",
      "welfare"
    ],
    "wof:name": "Spanish American Ctr",
    "wof:placetype": "venue"
  },
  "geometry": {"coordinates":[-71.751727,42.526163],"type":"Point"}
}
