{
  "type": "Feature",
  "properties": {
    "addr:full": "305 Union St Holbrook MA 02343",
    "addr:housenumber": "305",
    "addr:postcode": "02343",
    "addr:street": "Union St",
    "iso:country": "US",
    "ovtr:label": "Auto Clinic, 305 Union St Holbrook MA US",
    "ovtr:similarity": 2.450390100479126,
    "sg:address": "305 Union St",
    "sg:city": "Holbrook",
    "sg:classifiers": [
      {
        "category": "Retail",
        "subcategory": "Auto Repair",
        "type": "Services"
      }
    ],
    "sg:phone": "+1 781 767 4471",
    "sg:postcode": "02343",
    "sg:province": "MA",
    "sg:tags": [
      "repairing",
      "automobile"
    ],
    "wof:name": "Auto Clinic",
    "wof:placetype": "venue"
  },
  "geometry": {"coordinates":[-71.02319,42.15522],"type":"Point"}
}
