{
  "type": "Feature",
  "properties": {
    "addr:full": "28 Chester Rd Belmont MA 02478",
    "addr:housenumber": "28",
    "addr:postcode": "02478",
    "addr:street": "Chester Rd",
    "iso:country": "US",
    "sg:address": "28 Chester Rd",
    "sg:city": "Belmont",
    "sg:classifiers": [
      {
        "category": "Professional",
        "subcategory": "Business Services",
        "type": "Services"
      }
    ],
    "sg:phone": "+1   ",
    "sg:postcode": "02478",
    "sg:province": "MA",
    "sg:tags": [
      "group"
    ],
    "wof:name": "Meg Recording Co",
    "wof:placetype": "venue"
  },
  "geometry": {"coordinates":[-71.173821,42.383607],"type":"Point"}
}
