{
  "type": "Feature",
  "properties": {
    "iso:country":"US",
    "sg:address":"462 Boston St",
    "sg:city":"Topsfield",
    "sg:classifiers":[
        {
            "category":"Professional",
            "subcategory":"Lawyer & Legal Services",
            "type":"Services"
        }
    ],
    "sg:phone":"+1 978 887 9100",
    "sg:postcode":"01983",
    "sg:province":"MA",
    "sg:tags":[
        "attorney"
    ],
    "wof:name":"Mangos & Stone",
    "wof:placetype":"venue"
},
  "geometry": {"coordinates":[-70.93008399999999,42.662328],"type":"Point"}
}