{
  "type": "Feature",
  "properties": {
    "addr:full": "462 Boston St Topsfield MA 01983",
    "addr:housenumber": "462",
    "addr:postcode": "01983",
    "addr:street": "Boston St",
    "iso:country": "US",
    "sg:address": "462 Boston St",
    "sg:city": "Topsfield",
    "sg:classifiers": [
      {
        "category": "Professional",
        "subcategory": "Lawyer \u0026 Legal Services",
        "type": "Services"
      }
    ],
    "sg:phone": "+1 978 887 9100",
    "sg:postcode": "01983",
    "sg:province": "MA",
    "sg:tags": [
      "attorney"
    ],
    "wof:name": "Mangos \u0026 Stone",
    "wof:placetype": "venue"
  },
  "geometry": {"coordinates":[-70.930084,42.662328],"type":"Point"}
}
