{
  "type": "Feature",
  "properties": {
    "addr:full":"29 Gay Rd Brookfield MA 01506",
    "addr:housenumber":"29",
    "addr:postcode":"01506",
    "addr:street":"Gay Rd",
    "iso:country":"US",
    "sg:address":"29 Gay Rd",
    "sg:city":"Brookfield",
    "sg:classifiers":[
        {
            "category":"Travel",
            "subcategory":"Travel Agent",
            "type":"Entertainment"
        }
    ],
    "sg:phone":"+1   ",
    "sg:postcode":"01506",
    "sg:province":"MA",
    "sg:tags":[
        "agency"
    ],
    "wof:name":"JM Travel Resources",
    "wof:placetype":"venue"
},
  "geometry": {"coordinates":[-72.089727,42.168479],"type":"Point"}
}