{
  "type": "Feature",
  "properties": {
    "addr:full": "1060 Main St Hanson MA 02341",
    "addr:housenumber": "1060",
    "addr:postcode": "02341",
    "addr:street": "Main St",
    "iso:country": "US",
    "sg:address": "1060 Main St",
    "sg:city": "Hanson",
    "sg:classifiers": [
      {
        "category": "Professional",
        "subcategory": "Detective \u0026 Security Services",
        "type": "Services"
      }
    ],
    "sg:phone": "+1 781 293 4777",
    "sg:postcode": "02341",
    "sg:province": "MA",
    "sg:tags": [
      "investigator"
    ],
    "sg:website": "www.d-i-g.com",
    "wof:name": "Defense Investigators Group",
    "wof:placetype": "venue"
  },
  "geometry": {"coordinates":[-70.87922,42.042934],"type":"Point"}
}
