{
  "type": "Feature",
  "properties": {
    "iso:country":"US",
    "sg:address":"270 Main St",
    "sg:city":"Hanson",
    "sg:classifiers":[
        {
            "category":"Insurance",
            "subcategory":"Insurance Agent",
            "type":"Services"
        }
    ],
    "sg:phone":"+1 781 293 3551",
    "sg:postcode":"02341",
    "sg:province":"MA",
    "wof:name":"Passaro Leverone & Buckley Ins",
    "wof:placetype":"venue"
},
  "geometry": {"coordinates":[-70.84539599999999,42.042809],"type":"Point"}
}