{
  "type": "Feature",
  "properties": {
    "addr:full": "15 Washington Street Brighton MA 02135",
    "addr:housenumber": "15",
    "addr:postcode": "02135",
    "addr:street": "Washington Street",
    "iso:country": "US",
    "sg:address": "15 Washington Street",
    "sg:city": "Brighton",
    "sg:classifiers": [
      {
        "category": "Building \u0026 Trades",
        "subcategory": "Locksmith",
        "type": "Services"
      }
    ],
    "sg:phone": "+1 617 370 0428",
    "sg:postcode": "02135",
    "sg:province": "MA",
    "sg:tags": [
      "key"
    ],
    "wof:name": "1 Emerg 7 Day Locksmith",
    "wof:placetype": "venue"
  },
  "geometry": {"coordinates":[-71.141714,42.342926],"type":"Point"}
}
