{
  "type": "Feature",
  "properties": {
    "iso:country":"US",
    "sg:address":"653 E Broadway Apt 1",
    "sg:city":"Boston",
    "sg:classifiers":[
        {
            "category":"Insurance",
            "subcategory":"Hazard Insurance",
            "type":"Services"
        }
    ],
    "sg:phone":"+1 617 268 4703",
    "sg:postcode":"02127",
    "sg:province":"MA",
    "wof:name":"Front Page Insurance",
    "wof:placetype":"venue"
},
  "geometry": {"coordinates":[-71.03876,42.335433],"type":"Point"}
}