{
  "type": "Feature",
  "properties": {
    "addr:full": "35 Washington St Marblehead MA 01945",
    "addr:housenumber": "35",
    "addr:postcode": "01945",
    "addr:street": "Washington St",
    "iso:country": "US",
    "sg:address": "35 Washington St",
    "sg:city": "Marblehead",
    "sg:classifiers": [
      {
        "category": "Organizations",
        "subcategory": "Religious Organization",
        "type": "Services"
      }
    ],
    "sg:phone": "+1 781 631 1244",
    "sg:postcode": "01945",
    "sg:province": "MA",
    "sg:tags": [
      "church"
    ],
    "sg:website": "www.onchurch.org",
    "wof:name": "First Church Of Christ",
    "wof:placetype": "venue"
  },
  "geometry": {"coordinates":[-70.848289,42.506364],"type":"Point"}
}
