{
  "type": "Feature",
  "properties": {
    "iso:country":"US",
    "sg:address":"16 Merchant's Way",
    "sg:city":"Middleboro",
    "sg:classifiers":[
        {
            "category":"Shopping",
            "subcategory":"Optical Goods",
            "type":"Retail Goods"
        }
    ],
    "sg:phone":"+1 508 947 6300",
    "sg:postcode":"02346",
    "sg:province":"MA",
    "sg:tags":[
        "optician"
    ],
    "wof:name":"Optique Limited",
    "wof:placetype":"venue"
},
  "geometry": {"coordinates":[-70.909064,41.882916],"type":"Point"}
}