{
  "type": "Feature",
  "properties": {
    "iso:country":"US",
    "sg:address":"251 Heath St",
    "sg:city":"Jamaica Plain",
    "sg:classifiers":[
        {
            "category":"Building & Trades",
            "subcategory":"Construction",
            "type":"Services"
        }
    ],
    "sg:phone":"+1 617 445 6723",
    "sg:postcode":"02130",
    "sg:province":"MA",
    "sg:tags":[
        "general",
        "contractor"
    ],
    "wof:name":"Consigli Construction Co",
    "wof:placetype":"venue"
},
  "geometry": {"coordinates":[-71.108779,42.327583],"type":"Point"}
}