{
  "type": "Feature",
  "properties": {
    "iso:country":"US",
    "sg:address":"364 Ocean Ave",
    "sg:city":"Revere",
    "sg:classifiers":[
        {
            "category":"Building & Trades",
            "subcategory":"Cleaning & Sanitation",
            "type":"Services"
        }
    ],
    "sg:phone":"+1 781 289 4912",
    "sg:postcode":"02151",
    "sg:province":"MA",
    "sg:tags":[
        "janitor"
    ],
    "wof:name":"Smile Cleaning Svc",
    "wof:placetype":"venue"
},
  "geometry": {"coordinates":[-70.99169999999999,42.409467],"type":"Point"}
}