{
  "type": "Feature",
  "properties": {
    "iso:country":"US",
    "sg:address":"2211 Northampton St",
    "sg:city":"Holyoke",
    "sg:classifiers":[
        {
            "category":"Autos & Motor Vehicles",
            "subcategory":"Auto Supplies",
            "type":"Retail Goods"
        }
    ],
    "sg:phone":"+1 413 535 1382",
    "sg:postcode":"01040",
    "sg:province":"MA",
    "sg:tags":[
        "automobile",
        "parts"
    ],
    "wof:name":"Advance Auto Parts Inc",
    "wof:placetype":"venue"
},
  "geometry": {"coordinates":[-72.630172,42.187878],"type":"Point"}
}