{
  "type": "Feature",
  "properties": {
    "addr:full": "17 Salem St Medford MA 02155",
    "addr:housenumber": "17",
    "addr:postcode": "02155",
    "addr:street": "Salem St",
    "iso:country": "US",
    "sg:address": "17 Salem St",
    "sg:city": "Medford",
    "sg:classifiers": [
      {
        "category": "Personal",
        "subcategory": "Beauty Salon",
        "type": "Services"
      }
    ],
    "sg:phone": "+1 781 396 1066",
    "sg:postcode": "02155",
    "sg:province": "MA",
    "sg:tags": [
      "hair"
    ],
    "sg:website": "www.salonfabianoltd.com",
    "wof:name": "Salon Fabiano Ltd",
    "wof:placetype": "venue"
  },
  "geometry": {"coordinates":[-71.108139,42.418303],"type":"Point"}
}
