{
  "type": "Feature",
  "properties": {
    "iso:country":"US",
    "sg:address":"17 Salem St",
    "sg:city":"Medford",
    "sg:classifiers":[
        {
            "category":"Personal",
            "subcategory":"Beauty Salon",
            "type":"Services"
        }
    ],
    "sg:phone":"+1 781 396 1066",
    "sg:postcode":"02155",
    "sg:province":"MA",
    "sg:tags":[
        "hair"
    ],
    "sg:website":"www.salonfabianoltd.com",
    "wof:name":"Salon Fabiano Ltd",
    "wof:placetype":"venue"
},
  "geometry": {"coordinates":[-71.10813899999999,42.418303],"type":"Point"}
}