{
  "type": "Feature",
  "properties": {
    "addr:full": "27 W Mountain St Worcester MA 01606",
    "addr:housenumber": "27",
    "addr:postcode": "01606",
    "addr:street": "W Mountain St",
    "iso:country": "US",
    "sg:address": "27 W Mountain St",
    "sg:city": "Worcester",
    "sg:classifiers": [
      {
        "category": "Professional",
        "subcategory": "Advertising",
        "type": "Services"
      }
    ],
    "sg:phone": "+1 508 856 7477",
    "sg:postcode": "01606",
    "sg:province": "MA",
    "sg:tags": [
      "designer",
      "display",
      "producer"
    ],
    "wof:name": "Admore Exhibits",
    "wof:placetype": "venue"
  },
  "geometry": {"coordinates":[-71.794411,42.324064],"type":"Point"}
}
