{
  "type": "Feature",
  "properties": {
    "iso:country":"US",
    "sg:address":"17 T Hall Rd",
    "sg:city":"Charlton",
    "sg:classifiers":[
        {
            "category":"Professional",
            "type":"Services"
        }
    ],
    "sg:phone":"+1 508 248 9500",
    "sg:postcode":"01507",
    "sg:province":"MA",
    "sg:tags":[
        "establishment"
    ],
    "wof:name":"Advanced Sensor Tech Inc",
    "wof:placetype":"venue"
},
  "geometry": {"coordinates":[-71.985432,42.121084],"type":"Point"}
}