{
  "type": "Feature",
  "properties": {
    "iso:country":"US",
    "sg:address":"488 Pleasant St",
    "sg:city":"Worcester",
    "sg:classifiers":[
        {
            "category":"Health Services",
            "subcategory":"Optometrist",
            "type":"Services"
        }
    ],
    "sg:phone":"+1 508 756 6832",
    "sg:postcode":"01609",
    "sg:province":"MA",
    "wof:name":"Optometry Associates",
    "wof:placetype":"venue"
},
  "geometry": {"coordinates":[-71.81827199999999,42.263293],"type":"Point"}
}