{
  "type": "Feature",
  "properties": {
    "iso:country":"US",
    "sg:address":"127 Chestnut St",
    "sg:city":"New Bedford",
    "sg:classifiers":[
        {
            "category":"Insurance",
            "subcategory":"Insurance Agent",
            "type":"Services"
        }
    ],
    "sg:phone":"+1 508 999 0111",
    "sg:postcode":"02740",
    "sg:province":"MA",
    "wof:name":"Raymond E Gramlich III Ins",
    "wof:placetype":"venue"
},
  "geometry": {"coordinates":[-70.933694,41.641585],"type":"Point"}
}