{
  "type": "Feature",
  "properties": {
    "addr:full":"10 Jefferson Ave Woburn MA 01801",
    "addr:housenumber":"10",
    "addr:postcode":"01801",
    "addr:street":"Jefferson Ave",
    "iso:country":"US",
    "sg:address":"10 Jefferson Ave",
    "sg:city":"Woburn",
    "sg:classifiers":[
        {
            "category":"Professional",
            "type":"Services"
        }
    ],
    "sg:phone":"+1 781 935 9585",
    "sg:postcode":"01801",
    "sg:province":"MA",
    "sg:tags":[
        "establishment"
    ],
    "wof:name":"Plasco Inc",
    "wof:placetype":"venue"
},
  "geometry": {"coordinates":[-71.14577300000001,42.477971],"type":"Point"}
}