{
  "type": "Feature",
  "properties": {
    "addr:full":"31 Marshall St Watertown MA 02472",
    "addr:housenumber":"31",
    "addr:postcode":"02472",
    "addr:street":"Marshall St",
    "iso:country":"US",
    "sg:address":"31 Marshall St",
    "sg:city":"Watertown",
    "sg:classifiers":[
        {
            "category":"Government",
            "subcategory":"Office",
            "type":"Public Place"
        }
    ],
    "sg:phone":"+1 617 972 6490",
    "sg:postcode":"02472",
    "sg:province":"MA",
    "sg:tags":[
        "city",
        "resource",
        "human"
    ],
    "wof:name":"Watertown Council On Aging",
    "wof:placetype":"venue"
},
  "geometry": {"coordinates":[-71.17975300000001,42.368439],"type":"Point"}
}