{
  "type": "Feature",
  "properties": {
    "iso:country":"US",
    "sg:address":"1215 Wilbraham Rd",
    "sg:city":"Springfield",
    "sg:classifiers":[
        {
            "category":"Education",
            "subcategory":"Library",
            "type":"Public Place"
        }
    ],
    "sg:phone":"+1 413 782 1535",
    "sg:postcode":"01119",
    "sg:province":"MA",
    "wof:name":"D'Amour Library",
    "wof:placetype":"venue"
},
  "geometry": {"coordinates":[-72.52200999999999,42.11632],"type":"Point"}
}