{
  "type": "Feature",
  "properties": {
    "addr:full": "1215 Wilbraham Rd Springfield MA 01119",
    "addr:housenumber": "1215",
    "addr:postcode": "01119",
    "addr:street": "Wilbraham Rd",
    "iso:country": "US",
    "ovtr:label": "D'Amour Library, 1215 Wilbraham Rd Springfield MA US",
    "ovtr:similarity": 2.363394021987915,
    "sg:address": "1215 Wilbraham Rd",
    "sg:city": "Springfield",
    "sg:classifiers": [
      {
        "category": "Education",
        "subcategory": "Library",
        "type": "Public Place"
      }
    ],
    "sg:phone": "+1 413 782 1535",
    "sg:postcode": "01119",
    "sg:province": "MA",
    "wof:name": "D'Amour Library",
    "wof:placetype": "venue"
  },
  "geometry": {"coordinates":[-72.52201,42.11632],"type":"Point"}
}
