{
  "type": "Feature",
  "properties": {
    "addr:full": "3 Saint Marys Rd Milton MA 02186",
    "addr:housenumber": "3",
    "addr:postcode": "02186",
    "addr:street": "Saint Marys Rd",
    "iso:country": "US",
    "sg:address": "3 Saint Marys Rd",
    "sg:city": "Milton",
    "sg:classifiers": [
      {
        "category": "Shopping",
        "type": "Retail Goods"
      },
      {
        "category": "Organizations",
        "subcategory": "Non-profit Organization",
        "type": "Services"
      }
    ],
    "sg:phone": "+1 617 296 8806",
    "sg:postcode": "02186",
    "sg:province": "MA",
    "sg:tags": [
      "supply",
      "fund",
      "games",
      "merchandise",
      "raising"
    ],
    "wof:name": "Liz Page Associates",
    "wof:placetype": "venue"
  },
  "geometry": {"coordinates":[-71.089989,42.262375],"type":"Point"}
}
