{
  "type": "Feature",
  "properties": {
    "iso:country":"US",
    "sg:address":"89 Front St",
    "sg:city":"Marblehead",
    "sg:classifiers":[
        {
            "category":"Autos & Motor Vehicles",
            "subcategory":"Boat Sales",
            "type":"Retail Goods"
        }
    ],
    "sg:phone":"+1 781 639 1490",
    "sg:postcode":"01945",
    "sg:province":"MA",
    "sg:tags":[
        "equipment",
        "marine",
        "supply"
    ],
    "sg:website":"www.doylesails.com",
    "wof:name":"Doyle Sailmakers Inc",
    "wof:placetype":"venue"
},
  "geometry": {"coordinates":[-70.846503,42.504706],"type":"Point"}
}