{
  "type": "Feature",
  "properties": {
    "iso:country":"US",
    "sg:address":"389 Cabot St",
    "sg:city":"Beverly",
    "sg:classifiers":[
        {
            "category":"Food & Beverages",
            "subcategory":"Groceries & Convenience Stores",
            "type":"Retail Goods"
        }
    ],
    "sg:phone":"+1 978 927 9059",
    "sg:postcode":"01915",
    "sg:province":"MA",
    "wof:name":"7-Eleven",
    "wof:placetype":"venue"
},
  "geometry": {"coordinates":[-70.88182999999999,42.558622],"type":"Point"}
}