{
  "type": "Feature",
  "properties": {
    "addr:full": "389 Cabot St Beverly MA 01915",
    "addr:housenumber": "389",
    "addr:postcode": "01915",
    "addr:street": "Cabot St",
    "iso:country": "US",
    "sg:address": "389 Cabot St",
    "sg:city": "Beverly",
    "sg:classifiers": [
      {
        "category": "Food \u0026 Beverages",
        "subcategory": "Groceries \u0026 Convenience Stores",
        "type": "Retail Goods"
      }
    ],
    "sg:phone": "+1 978 927 9059",
    "sg:postcode": "01915",
    "sg:province": "MA",
    "wof:name": "7-Eleven",
    "wof:placetype": "venue"
  },
  "geometry": {"coordinates":[-70.88183,42.558622],"type":"Point"}
}
