{
  "type": "Feature",
  "properties": {
    "addr:full": "31 Preston St Wakefield MA 01880",
    "addr:housenumber": "31",
    "addr:postcode": "01880",
    "addr:street": "Preston St",
    "iso:country": "US",
    "sg:address": "31 Preston St",
    "sg:city": "Wakefield",
    "sg:classifiers": [
      {
        "category": "Building \u0026 Trades",
        "subcategory": "Construction",
        "type": "Services"
      }
    ],
    "sg:phone": "+1   ",
    "sg:postcode": "01880",
    "sg:province": "MA",
    "sg:tags": [
      "floor",
      "laying",
      "contractor"
    ],
    "wof:name": "Montrose Flooring Inc",
    "wof:placetype": "venue"
  },
  "geometry": {"coordinates":[-71.059397,42.507212],"type":"Point"}
}
