{
  "type": "Feature",
  "properties": {
    "iso:country":"US",
    "sg:address":"31 Preston St",
    "sg:city":"Wakefield",
    "sg:classifiers":[
        {
            "category":"Building & Trades",
            "subcategory":"Construction",
            "type":"Services"
        }
    ],
    "sg:phone":"+1   ",
    "sg:postcode":"01880",
    "sg:province":"MA",
    "sg:tags":[
        "floor",
        "laying",
        "contractor"
    ],
    "wof:name":"Montrose Flooring Inc",
    "wof:placetype":"venue"
},
  "geometry": {"coordinates":[-71.059397,42.507212],"type":"Point"}
}