{
  "type": "Feature",
  "properties": {
    "addr:full":"39 Larcridge Ln Ashland MA 01721",
    "addr:housenumber":"39",
    "addr:postcode":"01721",
    "addr:street":"Larcridge Ln",
    "iso:country":"US",
    "sg:address":"39 Larcridge Ln",
    "sg:city":"Ashland",
    "sg:classifiers":[
        {
            "category":"Professional",
            "subcategory":"Lawyer & Legal Services",
            "type":"Services"
        }
    ],
    "sg:phone":"+1   ",
    "sg:postcode":"01721",
    "sg:province":"MA",
    "wof:name":"Gren M Bresnick Atty At Law",
    "wof:placetype":"venue"
},
  "geometry": {"coordinates":[-71.455167,42.243378],"type":"Point"}
}