{
  "type": "Feature",
  "properties": {
    "addr:full": "420 Common St Lawrence MA 01840",
    "addr:housenumber": "420",
    "addr:postcode": "01840",
    "addr:street": "Common",
    "iso:country": "US",
    "sg:address": "420 Common St",
    "sg:city": "Lawrence",
    "sg:classifiers": [
      {
        "category": "Freight",
        "type": "Transportation"
      }
    ],
    "sg:phone": "+1 978 682 1461",
    "sg:postcode": "01840",
    "sg:province": "MA",
    "wof:name": "Transpro LLC",
    "wof:placetype": "venue"
  },
  "geometry": {"coordinates":[-71.163958,42.70764],"type":"Point"}
}
