{
  "type": "Feature",
  "properties": {
    "iso:country":"US",
    "sg:address":"340 Turnpike St",
    "sg:city":"Canton",
    "sg:classifiers":[
        {
            "category":"Restaurant",
            "type":"Food & Drink"
        }
    ],
    "sg:phone":"+1 781 784 8239",
    "sg:postcode":"02021",
    "sg:province":"MA",
    "wof:name":"Mirob Management",
    "wof:placetype":"venue"
},
  "geometry": {"coordinates":[-71.11185999999999,42.174379],"type":"Point"}
}