{
  "type": "Feature",
  "properties": {
    "iso:country":"US",
    "sg:address":"63 Circuit Ave",
    "sg:city":"Hyannis",
    "sg:classifiers":[
        {
            "category":"Retail",
            "subcategory":"Auto Repair",
            "type":"Services"
        }
    ],
    "sg:phone":"+1   ",
    "sg:postcode":"02601",
    "sg:province":"MA",
    "sg:tags":[
        "body"
    ],
    "wof:name":"European Car Service",
    "wof:placetype":"venue"
},
  "geometry": {"coordinates":[-70.281447,41.638881],"type":"Point"}
}