{
  "type": "Feature",
  "properties": {
    "iso:country":"US",
    "sg:address":"66 Chester Rd",
    "sg:city":"Belmont",
    "sg:classifiers":[
        {
            "category":"Professional",
            "subcategory":"Art Services",
            "type":"Services"
        }
    ],
    "sg:phone":"+1 617 923 8300",
    "sg:postcode":"02478",
    "sg:province":"MA",
    "sg:tags":[
        "sculptor"
    ],
    "wof:name":"David Larocca Sculptor",
    "wof:placetype":"venue"
},
  "geometry": {"coordinates":[-71.17198500000001,42.383873],"type":"Point"}
}