{
  "type": "Feature",
  "properties": {
    "iso:country":"US",
    "sg:address":"101 Thomas St",
    "sg:city":"Ashland",
    "sg:classifiers":[
        {
            "category":"Building & Trades",
            "subcategory":"Landscaping Services",
            "type":"Services"
        }
    ],
    "sg:phone":"+1 508 881 2475",
    "sg:postcode":"01721",
    "sg:province":"MA",
    "sg:tags":[
        "tree"
    ],
    "wof:name":"Jerry Mc Millan Tree Svc",
    "wof:placetype":"venue"
},
  "geometry": {"coordinates":[-71.505518,42.273013],"type":"Point"}
}