{
  "type": "Feature",
  "properties": {
    "iso:country":"US",
    "sg:address":"33 Mount Vernon St",
    "sg:city":"Lawrence",
    "sg:classifiers":[
        {
            "category":"Government",
            "subcategory":"Court House",
            "type":"Public Place"
        }
    ],
    "sg:phone":"+1 978 689 3486",
    "sg:postcode":"01843",
    "sg:province":"MA",
    "sg:tags":[
        "justice",
        "peace"
    ],
    "wof:name":"Elaine C Costello",
    "wof:placetype":"venue"
},
  "geometry": {"coordinates":[-71.15734999999999,42.685645],"type":"Point"}
}