{
  "type": "Feature",
  "properties": {
    "addr:full":"405 W Broadway Boston MA 02127",
    "addr:housenumber":"405",
    "addr:postcode":"02127",
    "addr:street":"W Broadway",
    "iso:country":"US",
    "sg:address":"405 W Broadway",
    "sg:city":"Boston",
    "sg:classifiers":[
        {
            "category":"Food & Beverages",
            "subcategory":"Groceries & Convenience Stores",
            "type":"Retail Goods"
        }
    ],
    "sg:phone":"+1 617 269 1652",
    "sg:postcode":"02127",
    "sg:province":"MA",
    "wof:name":"Store 24 Inc the",
    "wof:placetype":"venue"
},
  "geometry": {"coordinates":[-71.048698,42.337601],"type":"Point"}
}