{
  "type": "Feature",
  "properties": {
    "addr:full": "107 Main St Sheffield MA 01257",
    "addr:housenumber": "107",
    "addr:postcode": "01257",
    "addr:street": "Main St",
    "iso:country": "US",
    "sg:address": "107 Main St",
    "sg:city": "Sheffield",
    "sg:classifiers": [
      {
        "category": "Shopping",
        "subcategory": "Department Store",
        "type": "Retail Goods"
      }
    ],
    "sg:phone": "+1 413 229 8702",
    "sg:postcode": "01257",
    "sg:province": "MA",
    "sg:tags": [
      "variety"
    ],
    "wof:name": "Silk's Variety Inc",
    "wof:placetype": "venue"
  },
  "geometry": {"coordinates":[-73.353695,42.109798],"type":"Point"}
}
