{
  "type": "Feature",
  "properties": {
    "addr:full": "1022 State Hwy 6 Alt West Barnstable MA 02668",
    "addr:housenumber": "1022",
    "addr:postcode": "02668",
    "addr:street": "State Hwy 6;West",
    "iso:country": "US",
    "sg:address": "1022 State Hwy 6 Alt",
    "sg:city": "West Barnstable",
    "sg:classifiers": [
      {
        "category": "Shopping",
        "subcategory": "Stationery \u0026 Office Supplies",
        "type": "Retail Goods"
      }
    ],
    "sg:phone": "+1 508 790 1111",
    "sg:postcode": "02668",
    "sg:province": "MA",
    "sg:tags": [
      "map"
    ],
    "wof:name": "Butterworth Map Co Inc",
    "wof:placetype": "venue"
  },
  "geometry": {"coordinates":[-70.370712,41.707902],"type":"Point"}
}
