{
  "type": "Feature",
  "properties": {
    "addr:full":"351 Amherst Rd Amherst MA 01002",
    "addr:housenumber":"351",
    "addr:postcode":"01002",
    "addr:street":"Amherst Rd",
    "iso:country":"US",
    "sg:address":"351 Amherst Rd",
    "sg:city":"Amherst",
    "sg:classifiers":[
        {
            "category":"Government",
            "subcategory":"Office",
            "type":"Public Place"
        }
    ],
    "sg:phone":"+1   ",
    "sg:postcode":"01002",
    "sg:province":"MA",
    "wof:name":"Pelham Treasurers Office",
    "wof:placetype":"venue"
},
  "geometry": {"coordinates":[-72.408513,42.391385],"type":"Point"}
}