{
  "type": "Feature",
  "properties": {
    "iso:country":"US",
    "sg:address":"156 N West St",
    "sg:city":"Feeding Hills",
    "sg:classifiers":[
        {
            "category":"Social Services",
            "subcategory":"Child Care",
            "type":"Services"
        }
    ],
    "sg:phone":"+1   ",
    "sg:postcode":"01030",
    "sg:province":"MA",
    "sg:tags":[
        "day"
    ],
    "wof:name":"Moon & Stars Daycare",
    "wof:placetype":"venue"
},
  "geometry": {"coordinates":[-72.693586,42.066535],"type":"Point"}
}