{
  "type": "Feature",
  "properties": {
    "addr:full": "1819 Washington Street Boston MA 02118",
    "addr:housenumber": "1819",
    "addr:postcode": "02118",
    "addr:street": "Washington Street",
    "iso:country": "US",
    "sg:address": "1819 Washington Street",
    "sg:city": "Boston",
    "sg:classifiers": [
      {
        "category": "Sports \u0026 Exercise",
        "subcategory": "Sports Center",
        "type": "Entertainment"
      },
      {
        "category": "Social Services",
        "subcategory": "Child Care",
        "type": "Services"
      },
      {
        "category": "Sports \u0026 Exercise",
        "subcategory": "Gym",
        "type": "Entertainment"
      }
    ],
    "sg:phone": "+1 617 445 1813",
    "sg:postcode": "02118",
    "sg:province": "MA",
    "sg:tags": [
      "trainer",
      "amateur",
      "day",
      "team"
    ],
    "wof:name": "Cooper Day Nursery",
    "wof:placetype": "venue"
  },
  "geometry": {"coordinates":[-71.078549,42.335125],"type":"Point"}
}
