{
  "type": "Feature",
  "properties": {
    "addr:full": "153 Industrial Blvd Turners Falls MA 01376",
    "addr:housenumber": "153",
    "addr:postcode": "01376",
    "addr:street": "Industrial Blvd",
    "iso:country": "US",
    "sg:address": "153 Industrial Blvd",
    "sg:city": "Turners Falls",
    "sg:classifiers": [
      {
        "category": "Food \u0026 Beverages",
        "subcategory": "Groceries \u0026 Convenience Stores",
        "type": "Retail Goods"
      }
    ],
    "sg:phone": "+1 413 863 8500",
    "sg:postcode": "01376",
    "sg:province": "MA",
    "sg:tags": [
      "product"
    ],
    "sg:website": "www.lightlife.com",
    "wof:name": "Lightlife Foods Inc",
    "wof:placetype": "venue"
  },
  "geometry": {"coordinates":[-72.521403,42.599947],"type":"Point"}
}
