{
  "type": "Feature",
  "properties": {
    "iso:country":"US",
    "sg:address":"153 Industrial Blvd",
    "sg:city":"Turners Falls",
    "sg:classifiers":[
        {
            "category":"Food & Beverages",
            "subcategory":"Groceries & Convenience Stores",
            "type":"Retail Goods"
        }
    ],
    "sg:phone":"+1 413 863 8500",
    "sg:postcode":"01376",
    "sg:province":"MA",
    "sg:tags":[
        "product"
    ],
    "sg:website":"www.lightlife.com",
    "wof:name":"Lightlife Foods Inc",
    "wof:placetype":"venue"
},
  "geometry": {"coordinates":[-72.52140300000001,42.599947],"type":"Point"}
}