{
  "type": "Feature",
  "properties": {
    "addr:full": "1600 N Main St Fall River MA 02720",
    "addr:housenumber": "1600",
    "addr:postcode": "02720",
    "addr:street": "N Main St",
    "iso:country": "US",
    "ovtr:label": "Republican Club, 1600 N Main St Fall River MA US",
    "ovtr:similarity": 1.9650030136108398,
    "sg:address": "1600 N Main St",
    "sg:city": "Fall River",
    "sg:classifiers": [
      {
        "category": "Organizations",
        "subcategory": "Community Association",
        "type": "Services"
      }
    ],
    "sg:phone": "+1 508 676 3420",
    "sg:postcode": "02720",
    "sg:province": "MA",
    "sg:tags": [
      "club"
    ],
    "wof:name": "Republican Club",
    "wof:placetype": "venue"
  },
  "geometry": {"coordinates":[-71.144697,41.72259],"type":"Point"}
}
