{
  "type": "Feature",
  "properties": {
    "iso:country":"US",
    "sg:address":"1600 N Main St",
    "sg:city":"Fall River",
    "sg:classifiers":[
        {
            "category":"Organizations",
            "subcategory":"Community Association",
            "type":"Services"
        }
    ],
    "sg:phone":"+1 508 676 3420",
    "sg:postcode":"02720",
    "sg:province":"MA",
    "sg:tags":[
        "club"
    ],
    "wof:name":"Republican Club",
    "wof:placetype":"venue"
},
  "geometry": {"coordinates":[-71.14469699999999,41.72259],"type":"Point"}
}