{
  "type": "Feature",
  "properties": {
    "iso:country":"US",
    "sg:address":"73 North St",
    "sg:city":"Salem",
    "sg:classifiers":[
        {
            "category":"Manufacturing",
            "subcategory":"Glass & Minerals",
            "type":"Manufacturing & Wholesale Goods"
        }
    ],
    "sg:phone":"+1 978 744 0871",
    "sg:postcode":"01970",
    "sg:province":"MA",
    "sg:tags":[
        "stone",
        "cut",
        "product",
        "monument"
    ],
    "sg:website":"http://www.cemetery-services.com",
    "wof:name":"O'Rourke Bros Memorials",
    "wof:placetype":"venue"
},
  "geometry": {"coordinates":[-70.89965100000001,42.524872],"type":"Point"}
}