{
  "type": "Feature",
  "properties": {
    "addr:full": "73 North St Salem MA 01970",
    "addr:housenumber": "73",
    "addr:postcode": "01970",
    "addr:street": "North St",
    "iso:country": "US",
    "ovtr:label": "O'Rourke Bros. Memorials, 73 North St Salem MA US",
    "ovtr:similarity": 3.0166430473327637,
    "sg:address": "73 North St",
    "sg:city": "Salem",
    "sg:classifiers": [
      {
        "category": "Manufacturing",
        "subcategory": "Glass \u0026 Minerals",
        "type": "Manufacturing \u0026 Wholesale Goods"
      }
    ],
    "sg:phone": "+1 978 744 0871",
    "sg:postcode": "01970",
    "sg:province": "MA",
    "sg:tags": [
      "stone",
      "cut",
      "product",
      "monument"
    ],
    "sg:website": "http://www.cemetery-services.com",
    "wof:name": "O'Rourke Bros Memorials",
    "wof:placetype": "venue"
  },
  "geometry": {"coordinates":[-70.899651,42.524872],"type":"Point"}
}
