{
  "type": "Feature",
  "properties": {
    "iso:country":"US",
    "sg:address":"6 Colonial Dr",
    "sg:city":"Westborough",
    "sg:classifiers":[
        {
            "category":"Personal",
            "type":"Services"
        }
    ],
    "sg:phone":"+1 508 366 0930",
    "sg:postcode":"01581",
    "sg:province":"MA",
    "sg:tags":[
        "therapist",
        "massage"
    ],
    "wof:name":"Starseed Massage Assoc",
    "wof:placetype":"venue"
},
  "geometry": {"coordinates":[-71.609236,42.272408],"type":"Point"}
}