{
  "type": "Feature",
  "properties": {
    "iso:country":"US",
    "sg:address":"1 Sampson Rd",
    "sg:city":"Charlton",
    "sg:classifiers":[
        {
            "category":"Sports & Exercise",
            "subcategory":"Golf",
            "type":"Entertainment"
        }
    ],
    "sg:phone":"+1 508 248 5111",
    "sg:postcode":"01507",
    "sg:province":"MA",
    "sg:tags":[
        "course"
    ],
    "wof:name":"Heritage Country Club",
    "wof:placetype":"venue"
},
  "geometry": {"coordinates":[-72.019672,42.13874],"type":"Point"}
}