{
  "type": "Feature",
  "properties": {
    "addr:full": "1 Sampson Rd Charlton MA 01507",
    "addr:housenumber": "1",
    "addr:postcode": "01507",
    "addr:street": "Sampson Rd",
    "iso:country": "US",
    "ovtr:label": "Heritage Country Club, 85 Sampson Rd Charlton MA US",
    "ovtr:similarity": 3.5382750034332275,
    "sg:address": "1 Sampson Rd",
    "sg:city": "Charlton",
    "sg:classifiers": [
      {
        "category": "Sports \u0026 Exercise",
        "subcategory": "Golf",
        "type": "Entertainment"
      }
    ],
    "sg:phone": "+1 508 248 5111",
    "sg:postcode": "01507",
    "sg:province": "MA",
    "sg:tags": [
      "course"
    ],
    "wof:name": "Heritage Country Club",
    "wof:placetype": "venue"
  },
  "geometry": {"coordinates":[-72.019672,42.13874],"type":"Point"}
}
