{
  "type": "Feature",
  "properties": {
    "addr:full": "93 S Main St Orange MA 01364",
    "addr:housenumber": "93",
    "addr:postcode": "01364",
    "addr:street": "S Main St",
    "iso:country": "US",
    "ovtr:label": "Central Congregational Church, 93 S Main St Orange MA US",
    "ovtr:similarity": 2.7789769172668457,
    "sg:address": "93 S Main St",
    "sg:city": "Orange",
    "sg:classifiers": [
      {
        "category": "Organizations",
        "subcategory": "Religious Organization",
        "type": "Services"
      }
    ],
    "sg:phone": "+1 978 544 6895",
    "sg:postcode": "01364",
    "sg:province": "MA",
    "sg:tags": [
      "church"
    ],
    "wof:name": "Central Congregational Church",
    "wof:placetype": "venue"
  },
  "geometry": {"coordinates":[-72.309483,42.588672],"type":"Point"}
}
