{
  "type": "Feature",
  "properties": {
    "iso:country":"US",
    "sg:address":"93 S Main St",
    "sg:city":"Orange",
    "sg:classifiers":[
        {
            "category":"Organizations",
            "subcategory":"Religious Organization",
            "type":"Services"
        }
    ],
    "sg:phone":"+1 978 544 6895",
    "sg:postcode":"01364",
    "sg:province":"MA",
    "sg:tags":[
        "church"
    ],
    "wof:name":"Central Congregational Church",
    "wof:placetype":"venue"
},
  "geometry": {"coordinates":[-72.309483,42.588672],"type":"Point"}
}