{
  "type": "Feature",
  "properties": {
    "iso:country":"US",
    "sg:address":"215 Dutton St",
    "sg:city":"Lowell",
    "sg:classifiers":[
        {
            "category":"Manufacturing",
            "subcategory":"Petroleum Products",
            "type":"Manufacturing & Wholesale Goods"
        }
    ],
    "sg:phone":"+1 978 452 8413",
    "sg:postcode":"01852",
    "sg:province":"MA",
    "sg:tags":[
        "oil"
    ],
    "wof:name":"Haffner's Service Stations",
    "wof:placetype":"venue"
},
  "geometry": {"coordinates":[-71.314667,42.643864],"type":"Point"}
}