{
  "type": "Feature",
  "properties": {
    "addr:full": "197 Ave A Turners Falls MA 01376",
    "addr:housenumber": "197",
    "addr:postcode": "01376",
    "addr:street": "Ave A",
    "iso:country": "US",
    "sg:address": "197 Ave A",
    "sg:city": "Turners Falls",
    "sg:classifiers": [
      {
        "category": "Organizations",
        "subcategory": "Community Association",
        "type": "Services"
      }
    ],
    "sg:phone": "+1 413 863 4361",
    "sg:postcode": "01376",
    "sg:province": "MA",
    "sg:tags": [
      "club"
    ],
    "wof:name": "St Kaziemerz Society",
    "wof:placetype": "venue"
  },
  "geometry": {"coordinates":[-72.559415,42.605631],"type":"Point"}
}
