{
  "type": "Feature",
  "properties": {
    "iso:country":"US",
    "sg:address":"197 Ave A",
    "sg:city":"Turners Falls",
    "sg:classifiers":[
        {
            "category":"Organizations",
            "subcategory":"Community Association",
            "type":"Services"
        }
    ],
    "sg:phone":"+1 413 863 4361",
    "sg:postcode":"01376",
    "sg:province":"MA",
    "sg:tags":[
        "club"
    ],
    "wof:name":"St Kaziemerz Society",
    "wof:placetype":"venue"
},
  "geometry": {"coordinates":[-72.559415,42.605631],"type":"Point"}
}