{
  "type": "Feature",
  "properties": {
    "iso:country":"US",
    "sg:address":"635 Riverside Ave",
    "sg:city":"Haverhill",
    "sg:classifiers":[
        {
            "category":"Building & Trades",
            "subcategory":"Construction",
            "type":"Services"
        }
    ],
    "sg:phone":"+1   ",
    "sg:postcode":"01830",
    "sg:province":"MA",
    "sg:tags":[
        "masonry",
        "restoration"
    ],
    "wof:name":"Stone-Tek",
    "wof:placetype":"venue"
},
  "geometry": {"coordinates":[-71.037046,42.762636],"type":"Point"}
}