{
  "type": "Feature",
  "properties": {
    "addr:full": "97 N Worcester St Norton MA 02766",
    "addr:housenumber": "97",
    "addr:postcode": "02766",
    "addr:street": "N Worcester St",
    "iso:country": "US",
    "sg:address": "97 N Worcester St",
    "sg:city": "Norton",
    "sg:classifiers": [
      {
        "category": "Real Estate",
        "subcategory": "Real Estate Agent",
        "type": "Services"
      }
    ],
    "sg:phone": "+1 508 222 5004",
    "sg:postcode": "02766",
    "sg:province": "MA",
    "wof:name": "Bramwell Realty Inc",
    "wof:placetype": "venue"
  },
  "geometry": {"coordinates":[-71.237219,41.960708],"type":"Point"}
}
