{
  "type": "Feature",
  "properties": {
    "addr:full":"2720 Boston Rd Wilbraham MA 01095",
    "addr:housenumber":"2720",
    "addr:postcode":"01095",
    "addr:street":"Boston Rd",
    "iso:country":"US",
    "sg:address":"2720 Boston Rd",
    "sg:city":"Wilbraham",
    "sg:classifiers":[
        {
            "category":"Wholesale",
            "subcategory":"Scrap",
            "type":"Manufacturing & Wholesale Goods"
        }
    ],
    "sg:phone":"+1 413 596 2814",
    "sg:postcode":"01095",
    "sg:province":"MA",
    "sg:tags":[
        "recycling",
        "center"
    ],
    "wof:name":"Wilbraham Recycling",
    "wof:placetype":"venue"
},
  "geometry": {"coordinates":[-72.42779899999999,42.151444],"type":"Point"}
}