{
  "type": "Feature",
  "properties": {
    "addr:full":"12 Clover Hill Rd Sutton MA 01590",
    "addr:housenumber":"12",
    "addr:postcode":"01590",
    "addr:street":"Clover Hill Rd",
    "iso:country":"US",
    "sg:address":"12 Clover Hill Rd",
    "sg:city":"Sutton",
    "sg:classifiers":[
        {
            "category":"Education",
            "subcategory":"School",
            "type":"Public Place"
        }
    ],
    "sg:phone":"+1 508 234 8609",
    "sg:postcode":"01590",
    "sg:province":"MA",
    "sg:website":"www.integritasacademy.org",
    "wof:name":"Integritas Academy",
    "wof:placetype":"venue"
},
  "geometry": {"coordinates":[-71.68129999999999,42.102263],"type":"Point"}
}