{
  "type": "Feature",
  "properties": {
    "addr:full": "23 Whites Path South Yarmouth MA 02664",
    "addr:housenumber": "23",
    "addr:postcode": "02664",
    "addr:street": "Whites Path",
    "iso:country": "US",
    "sg:address": "23 Whites Path",
    "sg:city": "South Yarmouth",
    "sg:classifiers": [
      {
        "category": "Health Services",
        "subcategory": "Chiropractor",
        "type": "Services"
      }
    ],
    "sg:phone": "+1 508 394 1112",
    "sg:postcode": "02664",
    "sg:province": "MA",
    "wof:name": "Drown Chiropractic",
    "wof:placetype": "venue"
  },
  "geometry": {"coordinates":[-70.208906,41.689098],"type":"Point"}
}
