{
  "type": "Feature",
  "properties": {
    "iso:country":"US",
    "sg:address":"39 Olympia Ave",
    "sg:city":"Woburn",
    "sg:classifiers":[
        {
            "category":"Professional",
            "subcategory":"Research",
            "type":"Services"
        }
    ],
    "sg:phone":"+1 781 935 9050",
    "sg:postcode":"01801",
    "sg:province":"MA",
    "sg:tags":[
        "development",
        "laboratory"
    ],
    "sg:website":"www.conceptsnrec.com",
    "wof:name":"Northern Research & Engineerng",
    "wof:placetype":"venue"
},
  "geometry": {"coordinates":[-71.13352,42.499083],"type":"Point"}
}