{
  "type": "Feature",
  "properties": {
    "addr:full": "15 Everard Ave Revere MA 02151",
    "addr:housenumber": "15",
    "addr:postcode": "02151",
    "addr:street": "Everard Ave",
    "iso:country": "US",
    "sg:address": "15 Everard Ave",
    "sg:city": "Revere",
    "sg:classifiers": [
      {
        "category": "Building \u0026 Trades",
        "subcategory": "Locksmith",
        "type": "Services"
      }
    ],
    "sg:phone": "+1 781 922 4062",
    "sg:postcode": "02151",
    "sg:province": "MA",
    "sg:tags": [
      "key"
    ],
    "wof:name": "Real Time Locksmith",
    "wof:placetype": "venue"
  },
  "geometry": {"coordinates":[-70.992026,42.395562],"type":"Point"}
}
