{
  "type": "Feature",
  "properties": {
    "addr:full": "150 Main St Lee MA 01238",
    "addr:housenumber": "150",
    "addr:postcode": "01238",
    "addr:street": "Main St",
    "iso:country": "US",
    "sg:address": "150 Main St",
    "sg:city": "Lee",
    "sg:classifiers": [
      {
        "category": "Restaurant",
        "type": "Food \u0026 Drink"
      }
    ],
    "sg:phone": "+1   ",
    "sg:postcode": "01238",
    "sg:province": "MA",
    "sg:tags": [
      "eating"
    ],
    "wof:name": "From Ketchup To Caviar Inc",
    "wof:placetype": "venue"
  },
  "geometry": {"coordinates":[-73.250428,42.307342],"type":"Point"}
}
