{
  "type": "Feature",
  "properties": {
    "addr:full":"24 Normac Rd. Woburn MA 01801",
    "addr:housenumber":"24",
    "addr:postcode":"01801",
    "addr:street":"Normac Rd.",
    "iso:country":"US",
    "sg:address":"24 Normac Rd.",
    "sg:city":"Woburn",
    "sg:classifiers":[
        {
            "category":"Building & Trades",
            "subcategory":"Plumbing",
            "type":"Services"
        },
        {
            "category":"Building & Trades",
            "subcategory":"Construction",
            "type":"Services"
        }
    ],
    "sg:phone":"+1 978 372 2232",
    "sg:postcode":"01801",
    "sg:province":"MA",
    "sg:tags":[
        "air",
        "heating",
        "conditioning/hvac"
    ],
    "sg:website":"ars.com/home.aspx",
    "wof:name":"ARS - Climate Zone",
    "wof:placetype":"venue"
},
  "geometry": {"coordinates":[-71.132587,42.500086],"type":"Point"}
}