{
  "type": "Feature",
  "properties": {
    "addr:full": "30 Pond Park Rd Hingham MA 02043",
    "addr:housenumber": "30",
    "addr:postcode": "02043",
    "addr:street": "Pond Park Rd",
    "iso:country": "US",
    "sg:address": "30 Pond Park Rd",
    "sg:city": "Hingham",
    "sg:classifiers": [
      {
        "category": "Wholesale",
        "subcategory": "Stationery",
        "type": "Manufacturing \u0026 Wholesale Goods"
      }
    ],
    "sg:phone": "+1 781 741 5101",
    "sg:postcode": "02043",
    "sg:province": "MA",
    "sg:tags": [
      "packaging",
      "material"
    ],
    "wof:name": "Road To Responsibility",
    "wof:placetype": "venue"
  },
  "geometry": {"coordinates":[-70.919356,42.174085],"type":"Point"}
}
