{
  "type": "Feature",
  "properties": {
    "iso:country":"US",
    "sg:address":"137 Dorchester St",
    "sg:city":"South Boston",
    "sg:classifiers":[
        {
            "category":"Building & Trades",
            "subcategory":"Locksmith",
            "type":"Services"
        }
    ],
    "sg:phone":"+1 617 303 2617",
    "sg:postcode":"02127",
    "sg:province":"MA",
    "sg:tags":[
        "key"
    ],
    "wof:name":"On Call Locksmith",
    "wof:placetype":"venue"
},
  "geometry": {"coordinates":[-71.047318,42.334855],"type":"Point"}
}