{
  "type": "Feature",
  "properties": {
    "addr:full":"116 Main St #118 Pepperell MA 01463",
    "addr:housenumber":"116",
    "addr:postcode":"01463",
    "addr:street":"Main St # 118",
    "iso:country":"US",
    "sg:address":"116 Main St #118",
    "sg:city":"Pepperell",
    "sg:classifiers":[
        {
            "category":"Donuts",
            "subcategory":"None",
            "type":"Food & Drink"
        }
    ],
    "sg:phone":"+1 978 433 9042",
    "sg:postcode":"01463",
    "sg:province":"MA",
    "sg:tags":[
        "shop"
    ],
    "sg:website":"http://www.dunkindonuts.com",
    "wof:name":"Dunkin Donuts",
    "wof:placetype":"venue"
},
  "geometry": {"coordinates":[-71.577986,42.664895],"type":"Point"}
}