{
  "type": "Feature",
  "properties": {
    "iso:country":"US",
    "sg:address":"5 Bedford St",
    "sg:city":"Quincy",
    "sg:classifiers":[
        {
            "category":"Building & Trades",
            "subcategory":"Equipment Rental",
            "type":"Services"
        }
    ],
    "sg:phone":"+1 617 479 2100",
    "sg:postcode":"02169",
    "sg:province":"MA",
    "sg:tags":[
        "contractors'"
    ],
    "wof:name":"Downtown Johnny",
    "wof:placetype":"venue"
},
  "geometry": {"coordinates":[-71.01183899999999,42.250291],"type":"Point"}
}