{
  "type": "Feature",
  "properties": {
    "iso:country":"US",
    "sg:address":"119 Great Rd",
    "sg:city":"Bedford",
    "sg:classifiers":[
        {
            "category":"Building & Trades",
            "subcategory":"Locksmith",
            "type":"Services"
        }
    ],
    "sg:phone":"+1 617 895 3663",
    "sg:postcode":"01730",
    "sg:province":"MA",
    "sg:tags":[
        "key"
    ],
    "wof:name":"All Day Emergency A Locksmith",
    "wof:placetype":"venue"
},
  "geometry": {"coordinates":[-71.27775800000001,42.491192],"type":"Point"}
}