{
  "type": "Feature",
  "properties": {
    "iso:country":"US",
    "sg:address":"475 Quincy Ave",
    "sg:city":"Braintree",
    "sg:classifiers":[
        {
            "category":"Building & Trades",
            "subcategory":"Construction",
            "type":"Services"
        }
    ],
    "sg:phone":"+1 781 848 0524",
    "sg:postcode":"02184",
    "sg:province":"MA",
    "sg:tags":[
        "railing"
    ],
    "wof:name":"Diaute Brothers",
    "wof:placetype":"venue"
},
  "geometry": {"coordinates":[-70.98330199999999,42.238664],"type":"Point"}
}