{
  "type": "Feature",
  "properties": {
    "addr:full": "475 Quincy Ave Braintree MA 02184",
    "addr:housenumber": "475",
    "addr:postcode": "02184",
    "addr:street": "Quincy Ave",
    "iso:country": "US",
    "ovtr:label": "Diaute Bros, 475 Quincy Ave Braintree MA US",
    "ovtr:similarity": 3.778968095779419,
    "sg:address": "475 Quincy Ave",
    "sg:city": "Braintree",
    "sg:classifiers": [
      {
        "category": "Building \u0026 Trades",
        "subcategory": "Construction",
        "type": "Services"
      }
    ],
    "sg:phone": "+1 781 848 0524",
    "sg:postcode": "02184",
    "sg:province": "MA",
    "sg:tags": [
      "railing"
    ],
    "wof:name": "Diaute Brothers",
    "wof:placetype": "venue"
  },
  "geometry": {"coordinates":[-70.983302,42.238664],"type":"Point"}
}
