{
  "type": "Feature",
  "properties": {
    "iso:country":"US",
    "sg:address":"21 Colborne Rd",
    "sg:city":"Brighton",
    "sg:classifiers":[
        {
            "category":"Building & Trades",
            "subcategory":"Construction",
            "type":"Services"
        }
    ],
    "sg:phone":"+1 617 783 0259",
    "sg:postcode":"02135",
    "sg:province":"MA",
    "sg:tags":[
        "painter"
    ],
    "wof:name":"James J Lacey Painting Contractors",
    "wof:placetype":"venue"
},
  "geometry": {"coordinates":[-71.14630099999999,42.342602],"type":"Point"}
}