{
  "type": "Feature",
  "properties": {
    "addr:full": "21 Colborne Rd Brighton MA 02135",
    "addr:housenumber": "21",
    "addr:postcode": "02135",
    "addr:street": "Colborne Rd",
    "iso:country": "US",
    "sg:address": "21 Colborne Rd",
    "sg:city": "Brighton",
    "sg:classifiers": [
      {
        "category": "Building \u0026 Trades",
        "subcategory": "Construction",
        "type": "Services"
      }
    ],
    "sg:phone": "+1 617 783 0259",
    "sg:postcode": "02135",
    "sg:province": "MA",
    "sg:tags": [
      "painter"
    ],
    "wof:name": "James J Lacey Painting Contractors",
    "wof:placetype": "venue"
  },
  "geometry": {"coordinates":[-71.146301,42.342602],"type":"Point"}
}
