{
  "type": "Feature",
  "properties": {
    "addr:full":"353 Washington St Stoughton MA 02072",
    "addr:housenumber":"353",
    "addr:postcode":"02072",
    "addr:street":"Washington St",
    "iso:country":"US",
    "sg:address":"353 Washington St",
    "sg:city":"Stoughton",
    "sg:classifiers":[
        {
            "category":"Professional",
            "subcategory":"Business Services",
            "type":"Services"
        }
    ],
    "sg:phone":"+1   ",
    "sg:postcode":"02072",
    "sg:province":"MA",
    "sg:tags":[
        "specialty",
        "mfg"
    ],
    "wof:name":"Sign Depot Inc",
    "wof:placetype":"venue"
},
  "geometry": {"coordinates":[-71.101991,42.13688],"type":"Point"}
}