{
  "type": "Feature",
  "properties": {
    "addr:full": "448 Turnpike St South Easton MA 02375",
    "addr:housenumber": "448",
    "addr:postcode": "02375",
    "addr:street": "Turnpike St",
    "iso:country": "US",
    "sg:address": "448 Turnpike St",
    "sg:city": "South Easton",
    "sg:classifiers": [
      {
        "category": "Professional",
        "subcategory": "Engineering",
        "type": "Services"
      }
    ],
    "sg:phone": "+1 508 238 0760",
    "sg:postcode": "02375",
    "sg:province": "MA",
    "sg:tags": [
      "engineer"
    ],
    "wof:name": "Everett \u0026 Gerrish Engineering",
    "wof:placetype": "venue"
  },
  "geometry": {"coordinates":[-71.066676,42.012431],"type":"Point"}
}
