{
  "type": "Feature",
  "properties": {
    "iso:country":"US",
    "sg:address":"448 Turnpike St",
    "sg:city":"South Easton",
    "sg:classifiers":[
        {
            "category":"Professional",
            "subcategory":"Engineering",
            "type":"Services"
        }
    ],
    "sg:phone":"+1 508 238 0760",
    "sg:postcode":"02375",
    "sg:province":"MA",
    "sg:tags":[
        "engineer"
    ],
    "wof:name":"Everett & Gerrish Engineering",
    "wof:placetype":"venue"
},
  "geometry": {"coordinates":[-71.066676,42.012431],"type":"Point"}
}