{
  "type": "Feature",
  "properties": {
    "addr:full": "199 N Pleasant St Amherst MA 01002",
    "addr:housenumber": "199",
    "addr:postcode": "01002",
    "addr:street": "N Pleasant St",
    "iso:country": "US",
    "sg:address": "199 N Pleasant St",
    "sg:city": "Amherst",
    "sg:classifiers": [
      {
        "category": "Shopping",
        "subcategory": "Used Merchandise",
        "type": "Retail Goods"
      }
    ],
    "sg:phone": "+1 413 256 1508",
    "sg:postcode": "01002",
    "sg:province": "MA",
    "sg:tags": [
      "book",
      "rare",
      "dealer"
    ],
    "sg:website": "www.valleybooks.com",
    "wof:name": "Valley Books",
    "wof:placetype": "venue"
  },
  "geometry": {"coordinates":[-72.520023,42.379264],"type":"Point"}
}
