{
  "type": "Feature",
  "properties": {
    "addr:full": "22 Crandall St Adams MA 01220",
    "addr:housenumber": "22",
    "addr:postcode": "01220",
    "addr:street": "Crandall St",
    "iso:country": "US",
    "sg:address": "22 Crandall St",
    "sg:city": "Adams",
    "sg:classifiers": [
      {
        "category": "Building \u0026 Trades",
        "subcategory": "Construction",
        "type": "Services"
      }
    ],
    "sg:phone": "+1 413 743 3031",
    "sg:postcode": "01220",
    "sg:province": "MA",
    "sg:tags": [
      "hanging",
      "contractor"
    ],
    "wof:name": "Wellington Design",
    "wof:placetype": "venue"
  },
  "geometry": {"coordinates":[-73.118734,42.616342],"type":"Point"}
}
