{
  "type": "Feature",
  "properties": {
    "addr:full": "501 Cordwainer Dr Norwell MA 02061",
    "addr:housenumber": "501",
    "addr:postcode": "02061",
    "addr:street": "Cordwainer Dr",
    "iso:country": "US",
    "ovtr:label": "Southwood At Norwell Nursing, 501 Cordwainer Dr Norwell MA US",
    "ovtr:similarity": 2.289691925048828,
    "sg:address": "501 Cordwainer Dr",
    "sg:city": "Norwell",
    "sg:classifiers": [
      {
        "category": "Health Services",
        "subcategory": "Nursing And Care Facility",
        "type": "Services"
      }
    ],
    "sg:phone": "+1 781 982 7450",
    "sg:postcode": "02061",
    "sg:province": "MA",
    "sg:tags": [
      "home",
      "convalescent"
    ],
    "sg:website": "www.southwoodatnorwell.com",
    "wof:name": "Southwood At Norwell Nursing",
    "wof:placetype": "venue"
  },
  "geometry": {"coordinates":[-70.883498,42.16473],"type":"Point"}
}
