{
  "type": "Feature",
  "properties": {
    "iso:country":"US",
    "sg:address":"501 Cordwainer Dr",
    "sg:city":"Norwell",
    "sg:classifiers":[
        {
            "category":"Health Services",
            "subcategory":"Nursing And Care Facility",
            "type":"Services"
        }
    ],
    "sg:phone":"+1 781 982 7450",
    "sg:postcode":"02061",
    "sg:province":"MA",
    "sg:tags":[
        "home",
        "convalescent"
    ],
    "sg:website":"www.southwoodatnorwell.com",
    "wof:name":"Southwood At Norwell Nursing",
    "wof:placetype":"venue"
},
  "geometry": {"coordinates":[-70.883498,42.16473],"type":"Point"}
}