{
  "type": "Feature",
  "properties": {
    "iso:country":"US",
    "sg:address":"301 Harvard St",
    "sg:city":"Dorchester Ctr",
    "sg:classifiers":[
        {
            "category":"Professional",
            "type":"Services"
        }
    ],
    "sg:phone":"+1 617 822 2914",
    "sg:postcode":"02124",
    "sg:province":"MA",
    "sg:tags":[
        "establishment"
    ],
    "wof:name":"Torres Abreu",
    "wof:placetype":"venue"
},
  "geometry": {"coordinates":[-71.08921100000001,42.294086],"type":"Point"}
}