{
  "type": "Feature",
  "properties": {
    "addr:full":"77 Fayerweather St Cambridge MA 02138",
    "addr:housenumber":"77",
    "addr:postcode":"02138",
    "addr:street":"Fayerweather St",
    "iso:country":"US",
    "sg:address":"77 Fayerweather St",
    "sg:city":"Cambridge",
    "sg:classifiers":[
        {
            "category":"Banks & Credit Unions",
            "subcategory":"Financial Services",
            "type":"Services"
        }
    ],
    "sg:phone":"+1 617 661 1654",
    "sg:postcode":"02138",
    "sg:province":"MA",
    "sg:tags":[
        "broker",
        "mortgage"
    ],
    "wof:name":"Income Property Finance",
    "wof:placetype":"venue"
},
  "geometry": {"coordinates":[-71.137497,42.381199],"type":"Point"}
}