{
  "type": "Feature",
  "properties": {
    "iso:country":"US",
    "sg:address":"790 Turnpike St",
    "sg:city":"North Andover",
    "sg:classifiers":[
        {
            "category":"Shopping",
            "type":"Retail Goods"
        }
    ],
    "sg:phone":"+1 978 794 5528",
    "sg:postcode":"01845",
    "sg:province":"MA",
    "sg:tags":[
        "orthopedic",
        "appliance"
    ],
    "wof:name":"Patriot Orthotic Products",
    "wof:placetype":"venue"
},
  "geometry": {"coordinates":[-71.109233,42.661559],"type":"Point"}
}