{
  "type": "Feature",
  "properties": {
    "iso:country":"US",
    "sg:address":"319 Littleton Rd",
    "sg:city":"Westford",
    "sg:classifiers":[
        {
            "category":"Professional",
            "subcategory":"Engineering",
            "type":"Services"
        },
        {
            "category":"Professional",
            "subcategory":"Computer Services",
            "type":"Services"
        }
    ],
    "sg:phone":"+1 978 692 4200",
    "sg:postcode":"01886",
    "sg:province":"MA",
    "sg:tags":[
        "repair",
        "designer",
        "consultant",
        "integration",
        "system",
        "engineer"
    ],
    "sg:website":"www.ekaru.com",
    "wof:name":"Ekaru",
    "wof:placetype":"venue"
},
  "geometry": {"coordinates":[-71.445256,42.555225],"type":"Point"}
}