{
  "type": "Feature",
  "properties": {
    "addr:full":"1 Ashburton Pl Boston MA 02108",
    "addr:housenumber":"1",
    "addr:postcode":"02108",
    "addr:street":"Ashburton Pl",
    "iso:country":"US",
    "sg:address":"1 Ashburton Pl",
    "sg:city":"Boston",
    "sg:classifiers":[
        {
            "category":"Government",
            "subcategory":"Office",
            "type":"Public Place"
        }
    ],
    "sg:phone":"+1 617 727 9640",
    "sg:postcode":"02108",
    "sg:province":"MA",
    "sg:tags":[
        "building",
        "executive",
        "park"
    ],
    "sg:website":"http://www.salemdeeds.com",
    "wof:name":"Secretary Of The Commonwealth/",
    "wof:placetype":"venue"
},
  "geometry": {"coordinates":[-71.06179,42.35915],"type":"Point"}
}