{
  "type": "Feature",
  "properties": {
    "addr:full": "20 Woodward St Everett MA 02149",
    "addr:housenumber": "20",
    "addr:postcode": "02149",
    "addr:street": "Woodward St",
    "iso:country": "US",
    "sg:address": "20 Woodward St",
    "sg:city": "Everett",
    "sg:classifiers": [
      {
        "category": "Building \u0026 Trades",
        "subcategory": "Construction",
        "type": "Services"
      }
    ],
    "sg:phone": "+1 617 547 3011",
    "sg:postcode": "02149",
    "sg:province": "MA",
    "sg:tags": [
      "painter"
    ],
    "wof:name": "Cambridge Paint Co",
    "wof:placetype": "venue"
  },
  "geometry": {"coordinates":[-71.049895,42.419667],"type":"Point"}
}
