{
  "type": "Feature",
  "properties": {
    "iso:country":"US",
    "sg:address":"20 Woodward St",
    "sg:city":"Everett",
    "sg:classifiers":[
        {
            "category":"Building & Trades",
            "subcategory":"Construction",
            "type":"Services"
        }
    ],
    "sg:phone":"+1 617 547 3011",
    "sg:postcode":"02149",
    "sg:province":"MA",
    "sg:tags":[
        "painter"
    ],
    "wof:name":"Cambridge Paint Co",
    "wof:placetype":"venue"
},
  "geometry": {"coordinates":[-71.04989500000001,42.419667],"type":"Point"}
}