{
  "type": "Feature",
  "properties": {
    "iso:country":"US",
    "sg:address":"31 Lewis Rd",
    "sg:city":"Swampscott",
    "sg:classifiers":[
        {
            "category":"Building & Trades",
            "subcategory":"Construction",
            "type":"Services"
        }
    ],
    "sg:phone":"+1 781 598 1843",
    "sg:postcode":"01907",
    "sg:province":"MA",
    "sg:tags":[
        "general",
        "contractor"
    ],
    "wof:name":"D'Alelio Construction Co",
    "wof:placetype":"venue"
},
  "geometry": {"coordinates":[-70.90090600000001,42.47149],"type":"Point"}
}