{
  "type": "Feature",
  "properties": {
    "addr:full": "21 Bishop Rd Rochester MA 02770",
    "addr:housenumber": "21",
    "addr:postcode": "02770",
    "addr:street": "Bishop Rd",
    "iso:country": "US",
    "sg:address": "21 Bishop Rd",
    "sg:city": "Rochester",
    "sg:classifiers": [
      {
        "category": "Manufacturing",
        "subcategory": "Tools \u0026 Machinery",
        "type": "Manufacturing \u0026 Wholesale Goods"
      }
    ],
    "sg:phone": "+1   ",
    "sg:postcode": "02770",
    "sg:province": "MA",
    "sg:tags": [
      "lab",
      "mfg"
    ],
    "wof:name": "Microautomation Inc",
    "wof:placetype": "venue"
  },
  "geometry": {"coordinates":[-70.866155,41.782224],"type":"Point"}
}
