{
  "type": "Feature",
  "properties": {
    "addr:full":"21 Bishop Rd Rochester MA 02770",
    "addr:housenumber":"21",
    "addr:postcode":"02770",
    "addr:street":"Bishop Rd",
    "iso:country":"US",
    "sg:address":"21 Bishop Rd",
    "sg:city":"Rochester",
    "sg:classifiers":[
        {
            "category":"Manufacturing",
            "subcategory":"Tools & Machinery",
            "type":"Manufacturing & Wholesale Goods"
        }
    ],
    "sg:phone":"+1   ",
    "sg:postcode":"02770",
    "sg:province":"MA",
    "sg:tags":[
        "lab",
        "mfg"
    ],
    "wof:name":"Microautomation Inc",
    "wof:placetype":"venue"
},
  "geometry": {"coordinates":[-70.86615500000001,41.782224],"type":"Point"}
}