{
  "type": "Feature",
  "properties": {
    "addr:full": "560 Washington St Stoughton MA 02072",
    "addr:housenumber": "560",
    "addr:postcode": "02072",
    "addr:street": "Washington St",
    "iso:country": "US",
    "sg:address": "560 Washington St",
    "sg:city": "Stoughton",
    "sg:classifiers": [
      {
        "category": "Organizations",
        "subcategory": "Community Association",
        "type": "Services"
      }
    ],
    "sg:phone": "+1   ",
    "sg:postcode": "02072",
    "sg:province": "MA",
    "wof:name": "Sons of Italy of Stoughton Inc",
    "wof:placetype": "venue"
  },
  "geometry": {"coordinates":[-71.1018,42.13007],"type":"Point"}
}
