{
  "type": "Feature",
  "properties": {
    "addr:full": "766 Falmouth Rd Mashpee MA 02649",
    "addr:housenumber": "766",
    "addr:postcode": "02649",
    "addr:street": "Falmouth Rd",
    "iso:country": "US",
    "sg:address": "766 Falmouth Rd",
    "sg:city": "Mashpee",
    "sg:classifiers": [
      {
        "category": "Professional",
        "subcategory": "Art Services",
        "type": "Services"
      }
    ],
    "sg:phone": "+1 508 477 7482",
    "sg:postcode": "02649",
    "sg:province": "MA",
    "sg:tags": [
      "graphic",
      "designer"
    ],
    "sg:website": "www.carolmcleoddesign.com",
    "wof:name": "Carol Mc Leod Design",
    "wof:placetype": "venue"
  },
  "geometry": {"coordinates":[-70.496837,41.604044],"type":"Point"}
}
