{
  "type": "Feature",
  "properties": {
    "addr:full": "10 Jericho Rd Scituate MA 02066",
    "addr:housenumber": "10",
    "addr:postcode": "02066",
    "addr:street": "Jericho Rd",
    "iso:country": "US",
    "sg:address": "10 Jericho Rd",
    "sg:city": "Scituate",
    "sg:classifiers": [
      {
        "category": "Travel",
        "subcategory": "Hotels \u0026 Motels",
        "type": "Entertainment"
      }
    ],
    "sg:phone": "+1 781 545 4377",
    "sg:postcode": "02066",
    "sg:province": "MA",
    "sg:tags": [
      "operation"
    ],
    "wof:name": "Harborside Inn Of Scituate",
    "wof:placetype": "venue"
  },
  "geometry": {"coordinates":[-70.727336,42.199221],"type":"Point"}
}
