{
  "type": "Feature",
  "properties": {
    "iso:country":"US",
    "sg:address":"637 Broadway",
    "sg:city":"Lawrence",
    "sg:classifiers":[
        {
            "category":"Personal",
            "subcategory":"Beauty Salon",
            "type":"Services"
        }
    ],
    "sg:phone":"+1 978 681 0099",
    "sg:postcode":"01841",
    "sg:province":"MA",
    "sg:tags":[
        "manicuring"
    ],
    "wof:name":"Professional Nails",
    "wof:placetype":"venue"
},
  "geometry": {"coordinates":[-71.177976,42.716676],"type":"Point"}
}