{
  "type": "Feature",
  "properties": {
    "addr:full": "555 Pleasant St Ste 206 Attleboro MA 02703",
    "addr:housenumber": "555",
    "addr:postcode": "02703",
    "addr:street": "Pleasant St Ste 206",
    "iso:country": "US",
    "sg:address": "555 Pleasant St Ste 206",
    "sg:city": "Attleboro",
    "sg:classifiers": [
      {
        "category": "Health Services",
        "subcategory": "Doctor",
        "type": "Services"
      }
    ],
    "sg:phone": "+1 508 431 5900",
    "sg:postcode": "02703",
    "sg:province": "MA",
    "sg:tags": [
      "dermatologist"
    ],
    "wof:name": "Hines Dermatology Associates Inc.",
    "wof:placetype": "venue"
  },
  "geometry": {"coordinates":[-71.268922,41.952758],"type":"Point"}
}
