{
  "type": "Feature",
  "properties": {
    "addr:full": "8 Gages Way South Dennis MA 02660",
    "addr:housenumber": "8",
    "addr:postcode": "02660",
    "addr:street": "Gages Way",
    "iso:country": "US",
    "sg:address": "8 Gages Way",
    "sg:city": "South Dennis",
    "sg:classifiers": [
      {
        "category": "Shopping",
        "subcategory": "Bicycles \u0026 Sporting Goods",
        "type": "Retail Goods"
      }
    ],
    "sg:phone": "+1 508 398 5926",
    "sg:postcode": "02660",
    "sg:province": "MA",
    "wof:name": "Moon's Skate Shop",
    "wof:placetype": "venue"
  },
  "geometry": {"coordinates":[-70.149182,41.707467],"type":"Point"}
}
