{
  "type": "Feature",
  "properties": {
    "iso:country":"US",
    "sg:address":"11 Appleton St",
    "sg:city":"Danvers",
    "sg:classifiers":[
        {
            "category":"Professional",
            "subcategory":"Management & Consulting",
            "type":"Services"
        }
    ],
    "sg:phone":"+1   ",
    "sg:postcode":"01923",
    "sg:province":"MA",
    "sg:tags":[
        "business"
    ],
    "wof:name":"Dagley Consultants",
    "wof:placetype":"venue"
},
  "geometry": {"coordinates":[-70.924272,42.549684],"type":"Point"}
}