{
  "type": "Feature",
  "properties": {
    "addr:full": "102 Elm St Westfield MA 01085",
    "addr:housenumber": "102",
    "addr:postcode": "01085",
    "addr:street": "Elm St",
    "iso:country": "US",
    "sg:address": "102 Elm St",
    "sg:city": "Westfield",
    "sg:classifiers": [
      {
        "category": "Wholesale",
        "subcategory": "Petroleum",
        "type": "Manufacturing \u0026 Wholesale Goods"
      }
    ],
    "sg:phone": "+1   ",
    "sg:postcode": "01085",
    "sg:province": "MA",
    "sg:tags": [
      "bulk",
      "station"
    ],
    "wof:name": "Valero Energy",
    "wof:placetype": "venue"
  },
  "geometry": {"coordinates":[-72.74838,42.123381],"type":"Point"}
}
