{
  "type": "Feature",
  "properties": {
    "addr:full": "101 Munson St Greenfield MA 01301",
    "addr:housenumber": "101",
    "addr:postcode": "01301",
    "addr:street": "Munson St",
    "iso:country": "US",
    "sg:address": "101 Munson St",
    "sg:city": "Greenfield",
    "sg:classifiers": [
      {
        "category": "Professional",
        "subcategory": "Computer Services",
        "type": "Services"
      }
    ],
    "sg:phone": "+1 413 772 5555",
    "sg:postcode": "01301",
    "sg:province": "MA",
    "sg:tags": [
      "internet"
    ],
    "sg:website": "www.crocker.com",
    "wof:name": "Crocker Communications",
    "wof:placetype": "venue"
  },
  "geometry": {"coordinates":[-72.624665,42.579253],"type":"Point"}
}
