{
  "type": "Feature",
  "properties": {
    "addr:full":"1 Olde North Rd Chelmsford MA 01824",
    "addr:housenumber":"1",
    "addr:postcode":"01824",
    "addr:street":"Olde North Rd",
    "iso:country":"US",
    "sg:address":"1 Olde North Rd",
    "sg:city":"Chelmsford",
    "sg:classifiers":[
        {
            "category":"Wholesale",
            "subcategory":"Electrical",
            "type":"Manufacturing & Wholesale Goods"
        }
    ],
    "sg:phone":"+1 978 256 7100",
    "sg:postcode":"01824",
    "sg:province":"MA",
    "sg:tags":[
        "electronic",
        "representative"
    ],
    "sg:website":"www.dbmsales.com",
    "wof:name":"DBM Technical Sales Inc",
    "wof:placetype":"venue"
},
  "geometry": {"coordinates":[-71.366491,42.620014],"type":"Point"}
}