{
  "type": "Feature",
  "properties": {
    "addr:full": "350 3rd St Cambridge MA 02143",
    "addr:housenumber": "350",
    "addr:postcode": "02143",
    "addr:street": "3Rd St",
    "iso:country": "US",
    "sg:address": "350 3rd St",
    "sg:city": "Cambridge",
    "sg:classifiers": [
      {
        "category": "Restaurant",
        "type": "Food \u0026 Drink"
      }
    ],
    "sg:phone": "+1 617 661 3866",
    "sg:postcode": "02143",
    "sg:province": "MA",
    "sg:tags": [
      "new",
      "american"
    ],
    "sg:website": "www.evoorestaurant.com",
    "wof:name": "EVOO",
    "wof:placetype": "venue"
  },
  "geometry": {"coordinates":[-71.083378,42.363744],"type":"Point"}
}
