{
  "type": "Feature",
  "properties": {
    "addr:full":"17 Pond Meadow Dr Marstons Mills MA 02648",
    "addr:housenumber":"17",
    "addr:postcode":"02648",
    "addr:street":"Pond Meadow Dr",
    "iso:country":"US",
    "sg:address":"17 Pond Meadow Dr",
    "sg:city":"Marstons Mills",
    "sg:classifiers":[
        {
            "category":"Wholesale",
            "subcategory":"Stationery",
            "type":"Manufacturing & Wholesale Goods"
        }
    ],
    "sg:phone":"+1 508 420 5301",
    "sg:postcode":"02648",
    "sg:province":"MA",
    "sg:tags":[
        "card"
    ],
    "wof:name":"Spirithaven of Cape Cod - CLOSED",
    "wof:placetype":"venue"
},
  "geometry": {"coordinates":[-70.43609600000001,41.6716],"type":"Point"}
}