{
  "type": "Feature",
  "properties": {
    "iso:country":"US",
    "sg:address":"65 S Main St",
    "sg:city":"Attleboro",
    "sg:classifiers":[
        {
            "category":"Shopping",
            "type":"Retail Goods"
        }
    ],
    "sg:phone":"+1 508 222 0234",
    "sg:postcode":"02703",
    "sg:province":"MA",
    "sg:tags":[
        "food",
        "pet",
        "store",
        "supply"
    ],
    "wof:name":"Attleboro's Old Barn",
    "wof:placetype":"venue"
},
  "geometry": {"coordinates":[-71.284554,41.942181],"type":"Point"}
}