{
  "type": "Feature",
  "properties": {
    "iso:country":"US",
    "sg:address":"8 Park St",
    "sg:city":"Rehoboth",
    "sg:classifiers":[
        {
            "category":"Building & Trades",
            "subcategory":"Construction",
            "type":"Services"
        }
    ],
    "sg:phone":"+1   ",
    "sg:postcode":"02769",
    "sg:province":"MA",
    "sg:tags":[
        "welding",
        "contractor"
    ],
    "wof:name":"Town Line Welding",
    "wof:placetype":"venue"
},
  "geometry": {"coordinates":[-71.253992,41.906816],"type":"Point"}
}