{
  "type": "Feature",
  "properties": {
    "addr:full": "333 W 1st St Boston MA 02127",
    "addr:housenumber": "333",
    "addr:postcode": "02127",
    "addr:street": "W 1St St",
    "iso:country": "US",
    "sg:address": "333 W 1st St",
    "sg:city": "Boston",
    "sg:classifiers": [
      {
        "category": "Restaurant",
        "type": "Food \u0026 Drink"
      }
    ],
    "sg:phone": "+1 617 464 1993",
    "sg:postcode": "02127",
    "sg:province": "MA",
    "sg:tags": [
      "seafood"
    ],
    "wof:name": "Sunnys Seafood",
    "wof:placetype": "venue"
  },
  "geometry": {"coordinates":[-71.046074,42.33909],"type":"Point"}
}
