{
  "type": "Feature",
  "properties": {
    "addr:full": "7 Island Rd Worcester MA 01603",
    "addr:housenumber": "7",
    "addr:postcode": "01603",
    "addr:street": "Island Rd",
    "iso:country": "US",
    "sg:address": "7 Island Rd",
    "sg:city": "Worcester",
    "sg:classifiers": [
      {
        "category": "Real Estate",
        "subcategory": "Developer",
        "type": "Services"
      }
    ],
    "sg:phone": "+1 508 753 8842",
    "sg:postcode": "01603",
    "sg:province": "MA",
    "sg:tags": [
      "cemetery"
    ],
    "sg:website": "www.allfaithscem.org",
    "wof:name": "All Faiths Cemetery \u0026 Crmtry",
    "wof:placetype": "venue"
  },
  "geometry": {"coordinates":[-71.83336,42.230098],"type":"Point"}
}
