{
  "type": "Feature",
  "properties": {
    "iso:country":"US",
    "sg:address":"250 Arbor St",
    "sg:city":"Lunenburg",
    "sg:classifiers":[
        {
            "category":"Professional",
            "subcategory":"Lawyer & Legal Services",
            "type":"Services"
        }
    ],
    "sg:phone":"+1   ",
    "sg:postcode":"01462",
    "sg:province":"MA",
    "wof:name":"Law Office of Louis J Fra",
    "wof:placetype":"venue"
},
  "geometry": {"coordinates":[-71.695706,42.589527],"type":"Point"}
}