{
  "type": "Feature",
  "properties": {
    "addr:full":"42 Highland Ave Greenfield MA 01301",
    "addr:housenumber":"42",
    "addr:postcode":"01301",
    "addr:street":"Highland Ave",
    "iso:country":"US",
    "sg:address":"42 Highland Ave",
    "sg:city":"Greenfield",
    "sg:classifiers":[
        {
            "category":"Professional",
            "subcategory":"Management & Consulting",
            "type":"Services"
        }
    ],
    "sg:phone":"+1   ",
    "sg:postcode":"01301",
    "sg:province":"MA",
    "wof:name":"Networking Marketing",
    "wof:placetype":"venue"
},
  "geometry": {"coordinates":[-72.59277899999999,42.5842],"type":"Point"}
}