{
  "type": "Feature",
  "properties": {
    "addr:full": "24 Beaver Dam Rd Carver MA 02330",
    "addr:housenumber": "24",
    "addr:postcode": "02330",
    "addr:street": "Beaver Dam Rd",
    "iso:country": "US",
    "sg:address": "24 Beaver Dam Rd",
    "sg:city": "Carver",
    "sg:classifiers": [
      {
        "category": "Personal",
        "subcategory": "Beauty Salon",
        "type": "Services"
      }
    ],
    "sg:phone": "+1 508 866 3573",
    "sg:postcode": "02330",
    "sg:province": "MA",
    "wof:name": "Maureen's Beauty Salon",
    "wof:placetype": "venue"
  },
  "geometry": {"coordinates":[-70.794584,41.884891],"type":"Point"}
}
