{
  "type": "Feature",
  "properties": {
    "iso:country":"US",
    "sg:address":"48 Middlesex Ave",
    "sg:city":"Worcester",
    "sg:classifiers":[
        {
            "category":"Building & Trades",
            "subcategory":"Construction",
            "type":"Services"
        }
    ],
    "sg:phone":"+1 508 798 0325",
    "sg:postcode":"01604",
    "sg:province":"MA",
    "sg:tags":[
        "masonry",
        "contractor"
    ],
    "wof:name":"Laudone Natale Masonry",
    "wof:placetype":"venue"
},
  "geometry": {"coordinates":[-71.762792,42.256957],"type":"Point"}
}