{
  "type": "Feature",
  "properties": {
    "iso:country":"US",
    "sg:address":"437 Wrentham Rd",
    "sg:city":"Bellingham",
    "sg:classifiers":[
        {
            "category":"Retail",
            "subcategory":"Auto Repair",
            "type":"Services"
        }
    ],
    "sg:phone":"+1 508 883 2999",
    "sg:postcode":"02019",
    "sg:province":"MA",
    "sg:tags":[
        "repairing",
        "automobile"
    ],
    "wof:name":"Mike Mc Alister Automotive Rpr",
    "wof:placetype":"venue"
},
  "geometry": {"coordinates":[-71.46948,42.025335],"type":"Point"}
}