{
  "type": "Feature",
  "properties": {
    "iso:country":"US",
    "sg:address":"12 Madison St",
    "sg:city":"Haverhill",
    "sg:classifiers":[
        {
            "category":"Professional",
            "type":"Services"
        }
    ],
    "sg:phone":"+1 978 373 4428",
    "sg:postcode":"01830",
    "sg:province":"MA",
    "sg:tags":[
        "technical",
        "preparation",
        "manual"
    ],
    "wof:name":"Katherine Pinard",
    "wof:placetype":"venue"
},
  "geometry": {"coordinates":[-71.0502,42.761983],"type":"Point"}
}