{
  "type": "Feature",
  "properties": {
    "addr:full": "601 Congress St Fl 2 Boston MA 02210",
    "addr:housenumber": "601;2",
    "addr:postcode": "02210",
    "addr:street": "Congress St",
    "iso:country": "US",
    "sg:address": "601 Congress St Fl 2",
    "sg:city": "Boston",
    "sg:classifiers": [
      {
        "category": "Banks \u0026 Credit Unions",
        "subcategory": "Investment Brokerage",
        "type": "Services"
      },
      {
        "category": "Insurance",
        "subcategory": "Hazard Insurance",
        "type": "Services"
      },
      {
        "category": "Banks \u0026 Credit Unions",
        "subcategory": "Financial Services",
        "type": "Services"
      }
    ],
    "sg:phone": "+1 617 663 1000",
    "sg:postcode": "02210",
    "sg:province": "MA",
    "sg:tags": [
      "advisory",
      "planner"
    ],
    "wof:name": "Manulife Financial North Amer",
    "wof:placetype": "venue"
  },
  "geometry": {"coordinates":[-71.0401,42.347889],"type":"Point"}
}
