{
  "type": "Feature",
  "properties": {
    "addr:full":"321 Manley St West Bridgewater MA 02379",
    "addr:housenumber":"321",
    "addr:postcode":"02379",
    "addr:street":"Manley St",
    "iso:country":"US",
    "sg:address":"321 Manley St",
    "sg:city":"West Bridgewater",
    "sg:classifiers":[
        {
            "category":"Professional",
            "subcategory":"Advertising",
            "type":"Services"
        }
    ],
    "sg:phone":"+1 508 586 2455",
    "sg:postcode":"02379",
    "sg:province":"MA",
    "sg:tags":[
        "mailing",
        "shipping"
    ],
    "wof:name":"VIP Mailing Svc",
    "wof:placetype":"venue"
},
  "geometry": {"coordinates":[-71.056337,42.034675],"type":"Point"}
}