{
  "type": "Feature",
  "properties": {
    "addr:full": "362 Commonwealth Ave Boston MA 02115",
    "addr:housenumber": "362",
    "addr:postcode": "02115",
    "addr:street": "Commonwealth Ave",
    "iso:country": "US",
    "ovtr:label": "Orpheus Performing Arts, 362 Commonwealth Ave Boston MA US",
    "ovtr:similarity": 2.223686933517456,
    "sg:address": "362 Commonwealth Ave",
    "sg:city": "Boston",
    "sg:classifiers": [
      {
        "category": "Shopping",
        "subcategory": "Music",
        "type": "Retail Goods"
      }
    ],
    "sg:phone": "+1 617 247 7200",
    "sg:postcode": "02115",
    "sg:province": "MA",
    "sg:tags": [
      "dvd's"
    ],
    "wof:name": "Orpheus Performing Arts",
    "wof:placetype": "venue"
  },
  "geometry": {"coordinates":[-71.088402,42.3489],"type":"Point"}
}
