{
  "type": "Feature",
  "properties": {
    "addr:full": "970 South St Fitchburg MA 01420",
    "addr:housenumber": "970",
    "addr:postcode": "01420",
    "addr:street": "South St",
    "iso:country": "US",
    "ovtr:label": "Partner's Pub, 970 South St Fitchburg MA US",
    "ovtr:similarity": 2.0666520595550537,
    "sg:address": "970 South St",
    "sg:city": "Fitchburg",
    "sg:classifiers": [
      {
        "category": "Bars \u0026 Pubs",
        "type": "Food \u0026 Drink"
      }
    ],
    "sg:phone": "+1 978 345 5051",
    "sg:postcode": "01420",
    "sg:province": "MA",
    "sg:tags": [
      "lounge",
      "cocktail"
    ],
    "wof:name": "Partner's Pub",
    "wof:placetype": "venue"
  },
  "geometry": {"coordinates":[-71.786734,42.556642],"type":"Point"}
}
