{
  "type": "Feature",
  "properties": {
    "iso:country":"US",
    "sg:address":"8 Freight House Rd",
    "sg:city":"Wareham",
    "sg:classifiers":[
        {
            "category":"Railroad",
            "type":"Transportation"
        }
    ],
    "sg:phone":"+1 508 291 7432",
    "sg:postcode":"02571",
    "sg:province":"MA",
    "wof:name":"Bay Colony RR Corp",
    "wof:placetype":"venue"
},
  "geometry": {"coordinates":[-70.696946,41.756074],"type":"Point"}
}