{
  "type": "Feature",
  "properties": {
    "iso:country":"US",
    "sg:address":"7 Bryant St",
    "sg:city":"Lynnfield",
    "sg:classifiers":[
        {
            "category":"Mining & Drilling",
            "type":"Manufacturing & Wholesale Goods"
        },
        {
            "category":"Shopping",
            "subcategory":"Jewelry",
            "type":"Retail Goods"
        },
        {
            "category":"Utilities",
            "type":"Services"
        }
    ],
    "sg:phone":"+1 781 334 3147",
    "sg:postcode":"01940",
    "sg:province":"MA",
    "sg:tags":[
        "stone",
        "semi-precious",
        "precious",
        "gemologists"
    ],
    "wof:name":"Gemological Evaluation And Marketing Services Inc",
    "wof:placetype":"venue"
},
  "geometry": {"coordinates":[-71.061857,42.535195],"type":"Point"}
}