{
  "type": "Feature",
  "properties": {
    "addr:full": "7 Bryant St Lynnfield MA 01940",
    "addr:housenumber": "7",
    "addr:postcode": "01940",
    "addr:street": "Bryant St",
    "iso:country": "US",
    "sg:address": "7 Bryant St",
    "sg:city": "Lynnfield",
    "sg:classifiers": [
      {
        "category": "Mining \u0026 Drilling",
        "type": "Manufacturing \u0026 Wholesale Goods"
      },
      {
        "category": "Shopping",
        "subcategory": "Jewelry",
        "type": "Retail Goods"
      },
      {
        "category": "Utilities",
        "type": "Services"
      }
    ],
    "sg:phone": "+1 781 334 3147",
    "sg:postcode": "01940",
    "sg:province": "MA",
    "sg:tags": [
      "stone",
      "semi-precious",
      "precious",
      "gemologists"
    ],
    "wof:name": "Gemological Evaluation And Marketing Services Inc",
    "wof:placetype": "venue"
  },
  "geometry": {"coordinates":[-71.061857,42.535195],"type":"Point"}
}
