{
  "type": "Feature",
  "properties": {
    "addr:full":"765 W Boylston St Worcester MA 01606",
    "addr:housenumber":"765",
    "addr:postcode":"01606",
    "addr:street":"W Boylston St",
    "iso:country":"US",
    "sg:address":"765 W Boylston St",
    "sg:city":"Worcester",
    "sg:classifiers":[
        {
            "category":"Real Estate",
            "subcategory":"Real Estate Services",
            "type":"Services"
        },
        {
            "category":"Banks & Credit Unions",
            "subcategory":"Financial Services",
            "type":"Services"
        }
    ],
    "sg:phone":"+1 508 853 6649",
    "sg:postcode":"01606",
    "sg:province":"MA",
    "sg:tags":[
        "loan",
        "processing"
    ],
    "wof:name":"Pmi Removal Inc",
    "wof:placetype":"venue"
},
  "geometry": {"coordinates":[-71.79577500000001,42.318754],"type":"Point"}
}