{
  "type": "Feature",
  "properties": {
    "addr:full":"45 Danforth St Boston MA 02131",
    "addr:housenumber":"45",
    "addr:postcode":"02131",
    "addr:street":"Danforth St",
    "iso:country":"US",
    "sg:address":"45 Danforth St",
    "sg:city":"Boston",
    "sg:classifiers":[
        {
            "category":"Arts & Performance",
            "subcategory":"Dance",
            "type":"Entertainment"
        }
    ],
    "sg:phone":"+1 617 942 1130",
    "sg:postcode":"02131",
    "sg:province":"MA",
    "sg:tags":[
        "school"
    ],
    "sg:website":"www.zapataentertainment.com/",
    "wof:name":"Zapata Entertainment",
    "wof:placetype":"venue"
},
  "geometry": {"coordinates":[-71.1057,42.3175],"type":"Point"}
}