{
  "type": "Feature",
  "properties": {
    "iso:country":"US",
    "sg:address":"696 Crescent St",
    "sg:city":"Brockton",
    "sg:classifiers":[
        {
            "category":"Restaurant",
            "type":"Food & Drink"
        }
    ],
    "sg:phone":"+1 508 588 6665",
    "sg:postcode":"02302",
    "sg:province":"MA",
    "sg:tags":[
        "grill",
        "bar"
    ],
    "wof:name":"Brazil On Grill Inc",
    "wof:placetype":"venue"
},
  "geometry": {"coordinates":[-70.99124500000001,42.081095],"type":"Point"}
}