{
  "type": "Feature",
  "properties": {
    "addr:full": "696 Crescent St Brockton MA 02302",
    "addr:housenumber": "696",
    "addr:postcode": "02302",
    "addr:street": "Crescent St",
    "iso:country": "US",
    "sg:address": "696 Crescent St",
    "sg:city": "Brockton",
    "sg:classifiers": [
      {
        "category": "Restaurant",
        "type": "Food \u0026 Drink"
      }
    ],
    "sg:phone": "+1 508 588 6665",
    "sg:postcode": "02302",
    "sg:province": "MA",
    "sg:tags": [
      "grill",
      "bar"
    ],
    "wof:name": "Brazil On Grill Inc",
    "wof:placetype": "venue"
  },
  "geometry": {"coordinates":[-70.991245,42.081095],"type":"Point"}
}
