{
  "type": "Feature",
  "properties": {
    "addr:full":"89 Intervale Ave Athol MA 01331",
    "addr:housenumber":"89",
    "addr:postcode":"01331",
    "addr:street":"Intervale Ave",
    "iso:country":"US",
    "sg:address":"89 Intervale Ave",
    "sg:city":"Athol",
    "sg:classifiers":[
        {
            "category":"Education",
            "subcategory":"Special Training",
            "type":"Public Place"
        }
    ],
    "sg:phone":"+1   ",
    "sg:postcode":"01331",
    "sg:province":"MA",
    "wof:name":"This Bloomin Place",
    "wof:placetype":"venue"
},
  "geometry": {"coordinates":[-72.23638699999999,42.602254],"type":"Point"}
}