{
  "type": "Feature",
  "properties": {
    "iso:country":"US",
    "sg:address":"8 Whittier Pl",
    "sg:city":"Boston",
    "sg:classifiers":[
        {
            "category":"Personal",
            "subcategory":"Beauty Salon",
            "type":"Services"
        }
    ],
    "sg:phone":"+1 617 263 0031",
    "sg:postcode":"02114",
    "sg:province":"MA",
    "wof:name":"Charles River Day Spa",
    "wof:placetype":"venue"
},
  "geometry": {"coordinates":[-71.066924,42.365813],"type":"Point"}
}