{
  "type": "Feature",
  "properties": {
    "iso:country":"US",
    "sg:address":"117 Chandler St",
    "sg:city":"Boston",
    "sg:classifiers":[
        {
            "category":"Professional",
            "subcategory":"Management & Consulting",
            "type":"Services"
        },
        {
            "category":"Professional",
            "subcategory":"Advertising",
            "type":"Services"
        }
    ],
    "sg:phone":"+1 617 877 9405",
    "sg:postcode":"02116",
    "sg:province":"MA",
    "sg:tags":[
        "marketing",
        "program",
        "consultant"
    ],
    "wof:name":"Mti Marketing Services",
    "wof:placetype":"venue"
},
  "geometry": {"coordinates":[-71.074729,42.345938],"type":"Point"}
}