{
  "type": "Feature",
  "properties": {
    "addr:full": "160 Sylvan Ter Leominster MA 01453",
    "addr:housenumber": "160",
    "addr:postcode": "01453",
    "addr:street": "Sylvan Ter",
    "iso:country": "US",
    "sg:address": "160 Sylvan Ter",
    "sg:city": "Leominster",
    "sg:classifiers": [
      {
        "category": "Home \u0026 Garden",
        "subcategory": "Building Materials",
        "type": "Retail Goods"
      }
    ],
    "sg:phone": "+1 978 534 0700",
    "sg:postcode": "01453",
    "sg:province": "MA",
    "sg:tags": [
      "siding"
    ],
    "wof:name": "Thebeau Siding",
    "wof:placetype": "venue"
  },
  "geometry": {"coordinates":[-71.768051,42.513809],"type":"Point"}
}
