{
  "type": "Feature",
  "properties": {
    "addr:full":"95 North Washington Street Boston MA 02113",
    "addr:housenumber":"95",
    "addr:postcode":"02113",
    "addr:street":"North Washington Street",
    "iso:country":"US",
    "sg:address":"95 North Washington Street",
    "sg:city":"Boston",
    "sg:classifiers":[
        {
            "category":"Personal",
            "subcategory":"Nail Salon",
            "type":"Services"
        }
    ],
    "sg:phone":"+1 857 445 0185",
    "sg:postcode":"02113",
    "sg:province":"MA",
    "wof:name":"Supreme Nails & Spa",
    "wof:placetype":"venue"
},
  "geometry": {"coordinates":[-71.05835500000001,42.365366],"type":"Point"}
}