{
  "type": "Feature",
  "properties": {
    "addr:full": "19 Almeida Rd Rehoboth MA 02769",
    "addr:housenumber": "19",
    "addr:postcode": "02769",
    "addr:street": "Almeida Rd",
    "iso:country": "US",
    "sg:address": "19 Almeida Rd",
    "sg:city": "Rehoboth",
    "sg:classifiers": [
      {
        "category": "Retail",
        "subcategory": "Repair Shop",
        "type": "Services"
      }
    ],
    "sg:phone": "+1 508 336 3222",
    "sg:postcode": "02769",
    "sg:province": "MA",
    "sg:tags": [
      "pumps-service"
    ],
    "wof:name": "Fernco Pump Service Inc",
    "wof:placetype": "venue"
  },
  "geometry": {"coordinates":[-71.287896,41.786485],"type":"Point"}
}
