{
  "type": "Feature",
  "properties": {
    "iso:country":"US",
    "sg:address":"219 Charles St",
    "sg:city":"Fitchburg",
    "sg:classifiers":[
        {
            "category":"Professional",
            "subcategory":"Accounting & Tax Preparation",
            "type":"Services"
        }
    ],
    "sg:phone":"+1 978 343 6877",
    "sg:postcode":"01420",
    "sg:province":"MA",
    "sg:tags":[
        "return",
        "filing"
    ],
    "wof:name":"Stanley B Mac Phadden Acctg",
    "wof:placetype":"venue"
},
  "geometry": {"coordinates":[-71.805527,42.579679],"type":"Point"}
}