{
  "type": "Feature",
  "properties": {
    "addr:full":"505 Middlesex Tpke Billerica MA 01821",
    "addr:housenumber":"505",
    "addr:postcode":"01821",
    "addr:street":"Middlesex Tpke",
    "iso:country":"US",
    "sg:address":"505 Middlesex Tpke",
    "sg:city":"Billerica",
    "sg:classifiers":[
        {
            "category":"Health Services",
            "subcategory":"Clinic",
            "type":"Services"
        }
    ],
    "sg:phone":"+1 978 663 7077",
    "sg:postcode":"01821",
    "sg:province":"MA",
    "sg:tags":[
        "counseling",
        "mental"
    ],
    "wof:name":"Sandler Paul S Dr",
    "wof:placetype":"venue"
},
  "geometry": {"coordinates":[-71.252197,42.551701],"type":"Point"}
}