{
  "type": "Feature",
  "properties": {
    "iso:country":"US",
    "sg:address":"37 Gove Street",
    "sg:city":"Boston",
    "sg:classifiers":[
        {
            "category":"Education",
            "subcategory":"School",
            "type":"Public Place"
        }
    ],
    "sg:phone":"+1 617 635 8529",
    "sg:postcode":"02128",
    "sg:province":"MA",
    "sg:tags":[
        "high",
        "middle",
        "elementary"
    ],
    "wof:name":"Boston City of",
    "wof:placetype":"venue"
},
  "geometry": {"coordinates":[-71.03731399999999,42.371517],"type":"Point"}
}