{
  "type": "Feature",
  "properties": {
    "iso:country":"US",
    "sg:address":"15 Titcomb St",
    "sg:city":"Newburyport",
    "sg:classifiers":[
        {
            "category":"Health Services",
            "subcategory":"Clinic",
            "type":"Services"
        }
    ],
    "sg:phone":"+1 978 462 5646",
    "sg:postcode":"01950",
    "sg:province":"MA",
    "sg:tags":[
        "counseling",
        "mental"
    ],
    "wof:name":"Newburyport Counseling Group",
    "wof:placetype":"venue"
},
  "geometry": {"coordinates":[-70.87390000000001,42.8106],"type":"Point"}
}