{
  "type": "Feature",
  "properties": {
    "addr:full": "15 Titcomb St Newburyport MA 01950",
    "addr:housenumber": "15",
    "addr:postcode": "01950",
    "addr:street": "Titcomb St",
    "iso:country": "US",
    "sg:address": "15 Titcomb St",
    "sg:city": "Newburyport",
    "sg:classifiers": [
      {
        "category": "Health Services",
        "subcategory": "Clinic",
        "type": "Services"
      }
    ],
    "sg:phone": "+1 978 462 5646",
    "sg:postcode": "01950",
    "sg:province": "MA",
    "sg:tags": [
      "counseling",
      "mental"
    ],
    "wof:name": "Newburyport Counseling Group",
    "wof:placetype": "venue"
  },
  "geometry": {"coordinates":[-70.8739,42.8106],"type":"Point"}
}
