{
  "type": "Feature",
  "properties": {
    "iso:country":"US",
    "sg:address":"1140 Blue Hill Avenue",
    "sg:city":"Dorchester Center",
    "sg:classifiers":[
        {
            "category":"Retail",
            "subcategory":"Laundry & Dry Cleaning",
            "type":"Services"
        }
    ],
    "sg:phone":"+1 617 265 9995",
    "sg:postcode":"02124",
    "sg:province":"MA",
    "wof:name":"Kay Dry Cleaner",
    "wof:placetype":"venue"
},
  "geometry": {"coordinates":[-71.091161,42.285264],"type":"Point"}
}