{
  "type": "Feature",
  "properties": {
    "addr:full":"318 Harvard St Ste 41 Brookline MA 02446",
    "addr:housenumber":"318",
    "addr:postcode":"02446",
    "addr:street":"Harvard St Ste 41",
    "iso:country":"US",
    "sg:address":"318 Harvard St Ste 41",
    "sg:city":"Brookline",
    "sg:classifiers":[
        {
            "category":"Retail",
            "subcategory":"Funeral Services",
            "type":"Services"
        },
        {
            "category":"Cemetery",
            "type":"Public Place"
        }
    ],
    "sg:phone":"+1 617 232 1472",
    "sg:postcode":"02446",
    "sg:province":"MA",
    "sg:tags":[
        "crematory"
    ],
    "wof:name":"Lindwood Memorial Park Inc",
    "wof:placetype":"venue"
},
  "geometry": {"coordinates":[-71.123358,42.343428],"type":"Point"}
}