{
  "type": "Feature",
  "properties": {
    "addr:full":"83 Shank Painter Rd Provincetown MA 02657",
    "addr:housenumber":"83",
    "addr:postcode":"02657",
    "addr:street":"Shank Painter Rd",
    "iso:country":"US",
    "sg:address":"83 Shank Painter Rd",
    "sg:city":"Provincetown",
    "sg:classifiers":[
        {
            "category":"Restaurant",
            "type":"Food & Drink"
        }
    ],
    "sg:phone":"+1 508 487 4327",
    "sg:postcode":"02657",
    "sg:province":"MA",
    "sg:tags":[
        "caterer"
    ],
    "wof:name":"Clem & Ursie's Catering",
    "wof:placetype":"venue"
},
  "geometry": {"coordinates":[-70.19556,42.053009],"type":"Point"}
}