{
  "type": "Feature",
  "properties": {
    "addr:full": "896 Main St Springfield MA 01103",
    "addr:housenumber": "896",
    "addr:postcode": "01103",
    "addr:street": "Main St",
    "iso:country": "US",
    "sg:address": "896 Main St",
    "sg:city": "Springfield",
    "sg:classifiers": [
      {
        "category": "Shopping",
        "subcategory": "Clothing, Apparel, \u0026 Fashions",
        "type": "Retail Goods"
      }
    ],
    "sg:phone": "+1 413 731 8203",
    "sg:postcode": "01103",
    "sg:province": "MA",
    "sg:tags": [
      "tailor"
    ],
    "wof:name": "Ben's Tailor Shop",
    "wof:placetype": "venue"
  },
  "geometry": {"coordinates":[-72.583128,42.097864],"type":"Point"}
}
