{
  "type": "Feature",
  "properties": {
    "iso:country":"US",
    "sg:address":"417 Blue Hill Ave",
    "sg:city":"Boston",
    "sg:classifiers":[
        {
            "category":"Home & Garden",
            "subcategory":"Carpets & Floor Coverings",
            "type":"Retail Goods"
        }
    ],
    "sg:phone":"+1   ",
    "sg:postcode":"02121",
    "sg:province":"MA",
    "wof:name":"All of Boston Carpet",
    "wof:placetype":"venue"
},
  "geometry": {"coordinates":[-71.08199500000001,42.310436],"type":"Point"}
}