{
  "type": "Feature",
  "properties": {
    "addr:full": "417 Blue Hill Ave Boston MA 02121",
    "addr:housenumber": "417",
    "addr:postcode": "02121",
    "addr:street": "Blue Hill Ave",
    "iso:country": "US",
    "sg:address": "417 Blue Hill Ave",
    "sg:city": "Boston",
    "sg:classifiers": [
      {
        "category": "Home \u0026 Garden",
        "subcategory": "Carpets \u0026 Floor Coverings",
        "type": "Retail Goods"
      }
    ],
    "sg:phone": "+1   ",
    "sg:postcode": "02121",
    "sg:province": "MA",
    "wof:name": "All of Boston Carpet",
    "wof:placetype": "venue"
  },
  "geometry": {"coordinates":[-71.081995,42.310436],"type":"Point"}
}
