{
  "type": "Feature",
  "properties": {
    "iso:country":"US",
    "sg:address":"12 Mulliken Way",
    "sg:city":"Newburyport",
    "sg:classifiers":[
        {
            "category":"Professional",
            "subcategory":"Research",
            "type":"Services"
        }
    ],
    "sg:phone":"+1 978 465 1595",
    "sg:postcode":"01950",
    "sg:province":"MA",
    "sg:tags":[
        "environmental",
        "ecological"
    ],
    "sg:website":"www.enpro.com",
    "wof:name":"Enpro Services Inc",
    "wof:placetype":"venue"
},
  "geometry": {"coordinates":[-70.890311,42.799738],"type":"Point"}
}