{
  "type": "Feature",
  "properties": {
    "addr:full":"41 Blantyre Ave Centerville MA 02632",
    "addr:housenumber":"41",
    "addr:postcode":"02632",
    "addr:street":"Blantyre Ave",
    "iso:country":"US",
    "sg:address":"41 Blantyre Ave",
    "sg:city":"Centerville",
    "sg:classifiers":[
        {
            "category":"Real Estate",
            "subcategory":"Real Estate Services",
            "type":"Services"
        },
        {
            "category":"Real Estate",
            "subcategory":"Real Estate Agent",
            "type":"Services"
        }
    ],
    "sg:phone":"+1 508 775 0200",
    "sg:postcode":"02632",
    "sg:province":"MA",
    "sg:tags":[
        "buyer",
        "management",
        "broker"
    ],
    "wof:name":"Bayview Corp",
    "wof:placetype":"venue"
},
  "geometry": {"coordinates":[-70.33599100000001,41.65261],"type":"Point"}
}