{
  "type": "Feature",
  "properties": {
    "iso:country":"US",
    "sg:address":"3353 Washington St",
    "sg:city":"Jamaica Plain",
    "sg:classifiers":[
        {
            "category":"Organizations",
            "subcategory":"Labor Organization",
            "type":"Services"
        }
    ],
    "sg:phone":"+1 617 524 8778",
    "sg:postcode":"02130",
    "sg:province":"MA",
    "wof:name":"Jobs With Justice",
    "wof:placetype":"venue"
},
  "geometry": {"coordinates":[-71.10623200000001,42.307846],"type":"Point"}
}