{
  "type": "Feature",
  "properties": {
    "addr:full": "121 Bay Rd North Easton MA 02356",
    "addr:housenumber": "121",
    "addr:postcode": "02356",
    "addr:street": "Bay Rd",
    "iso:country": "US",
    "sg:address": "121 Bay Rd",
    "sg:city": "North Easton",
    "sg:classifiers": [
      {
        "category": "Home \u0026 Garden",
        "subcategory": "Garden Supply",
        "type": "Retail Goods"
      }
    ],
    "sg:phone": "+1 508 238 1910",
    "sg:postcode": "02356",
    "sg:province": "MA",
    "sg:tags": [
      "sprinkler"
    ],
    "wof:name": "Affordable Lawn Sprinklers",
    "wof:placetype": "venue"
  },
  "geometry": {"coordinates":[-71.131819,42.059287],"type":"Point"}
}
