{
  "type": "Feature",
  "properties": {
    "iso:country":"US",
    "sg:address":"36 Adams St",
    "sg:city":"North Adams",
    "sg:classifiers":[
        {
            "category":"Restaurant",
            "type":"Food & Drink"
        }
    ],
    "sg:phone":"+1 413 664 7811",
    "sg:postcode":"01247",
    "sg:province":"MA",
    "wof:name":"Papa Gino's",
    "wof:placetype":"venue"
},
  "geometry": {"coordinates":[-73.122985,42.704161],"type":"Point"}
}