{
  "type": "Feature",
  "properties": {
    "addr:full":"115 Newbury St Lawrence MA 01841",
    "addr:housenumber":"115",
    "addr:postcode":"01841",
    "addr:street":"Newbury St",
    "iso:country":"US",
    "sg:address":"115 Newbury St",
    "sg:city":"Lawrence",
    "sg:classifiers":[
        {
            "category":"Food & Beverages",
            "subcategory":"Liquor & Beverages",
            "type":"Retail Goods"
        }
    ],
    "sg:phone":"+1 978 685 6699",
    "sg:postcode":"01841",
    "sg:province":"MA",
    "wof:name":"Tony's Liquor",
    "wof:placetype":"venue"
},
  "geometry": {"coordinates":[-71.155563,42.711809],"type":"Point"}
}