{
  "type": "Feature",
  "properties": {
    "iso:country":"US",
    "sg:address":"65 Mathewson Dr",
    "sg:city":"Weymouth",
    "sg:classifiers":[
        {
            "category":"Restaurant",
            "type":"Food & Drink"
        }
    ],
    "sg:phone":"+1 781 337 2283",
    "sg:postcode":"02189",
    "sg:province":"MA",
    "sg:tags":[
        "caterer"
    ],
    "wof:name":"Z-Chef",
    "wof:placetype":"venue"
},
  "geometry": {"coordinates":[-70.933243,42.192723],"type":"Point"}
}