{
  "type": "Feature",
  "properties": {
    "addr:full": "227 Navajo Rd Springfield MA 01109",
    "addr:housenumber": "227",
    "addr:postcode": "01109",
    "addr:street": "Navajo Rd",
    "iso:country": "US",
    "sg:address": "227 Navajo Rd",
    "sg:city": "Springfield",
    "sg:classifiers": [
      {
        "category": "Social Services",
        "subcategory": "Child Care",
        "type": "Services"
      }
    ],
    "sg:phone": "+1   ",
    "sg:postcode": "01109",
    "sg:province": "MA",
    "sg:tags": [
      "day"
    ],
    "wof:name": "Honey Comb Child Day Care",
    "wof:placetype": "venue"
  },
  "geometry": {"coordinates":[-72.521658,42.10701],"type":"Point"}
}
