{
  "type": "Feature",
  "properties": {
    "addr:full": "60 Dix St Lowell MA 01852",
    "addr:housenumber": "60",
    "addr:postcode": "01852",
    "addr:street": "Dix St",
    "iso:country": "US",
    "sg:address": "60 Dix St",
    "sg:city": "Lowell",
    "sg:phone": "+1 978 454 0600",
    "sg:postcode": "01852",
    "sg:province": "MA",
    "sg:tags": [
      "equipment",
      "supply"
    ],
    "wof:name": "H \u0026 H Restaurant Equipment",
    "wof:placetype": "venue"
  },
  "geometry": {"coordinates":[-71.309652,42.630156],"type":"Point"}
}
