{
  "type": "Feature",
  "properties": {
    "iso:country":"US",
    "sg:address":"328 Washington Street",
    "sg:city":"Boston",
    "sg:classifiers":[
        {
            "category":"Health Services",
            "subcategory":"Optometrist",
            "type":"Services"
        },
        {
            "category":"Shopping",
            "subcategory":"Optician",
            "type":"Retail Goods"
        }
    ],
    "sg:phone":"+1 617 542 9221",
    "sg:postcode":"02108",
    "sg:province":"MA",
    "sg:tags":[
        "eyewear"
    ],
    "sg:website":"www.cohensfashionoptical.com/",
    "wof:name":"Cohen's Fashion Optical",
    "wof:placetype":"venue"
},
  "geometry": {"coordinates":[-71.059076,42.356863],"type":"Point"}
}