{
  "type": "Feature",
  "properties": {
    "iso:country":"US",
    "sg:address":"10 Pleasant Harbour Rd",
    "sg:city":"Plymouth",
    "sg:classifiers":[
        {
            "category":"Building & Trades",
            "subcategory":"Electrical",
            "type":"Services"
        },
        {
            "category":"Wholesale",
            "subcategory":"Home Furnishings",
            "type":"Manufacturing & Wholesale Goods"
        }
    ],
    "sg:phone":"+1 508 224 4811",
    "sg:postcode":"02360",
    "sg:province":"MA",
    "sg:tags":[
        "lighting",
        "fixtures-wholesale",
        "electrician",
        "manufacturer"
    ],
    "wof:name":"Douglas Grey Jr",
    "wof:placetype":"venue"
},
  "geometry": {"coordinates":[-70.540285,41.863692],"type":"Point"}
}