{
  "type": "Feature",
  "properties": {
    "addr:full": "58 Commercial St Holyoke MA 01040",
    "addr:housenumber": "58",
    "addr:postcode": "01040",
    "addr:street": "Commercial St",
    "iso:country": "US",
    "ovtr:label": "G \u0026 H Landscaping, Inc., 58 Commercial St Holyoke MA US",
    "ovtr:similarity": 3.981861114501953,
    "sg:address": "58 Commercial St",
    "sg:city": "Holyoke",
    "sg:classifiers": [
      {
        "category": "Building \u0026 Trades",
        "subcategory": "Landscaping Services",
        "type": "Services"
      }
    ],
    "sg:phone": "+1 413 532 4888",
    "sg:postcode": "01040",
    "sg:province": "MA",
    "sg:tags": [
      "landscape",
      "contractor"
    ],
    "wof:name": "G \u0026 H Landscaping",
    "wof:placetype": "venue"
  },
  "geometry": {"coordinates":[-72.613956,42.198827],"type":"Point"}
}
