{
  "type": "Feature",
  "properties": {
    "iso:country":"US",
    "sg:address":"58 Commercial St",
    "sg:city":"Holyoke",
    "sg:classifiers":[
        {
            "category":"Building & Trades",
            "subcategory":"Landscaping Services",
            "type":"Services"
        }
    ],
    "sg:phone":"+1 413 532 4888",
    "sg:postcode":"01040",
    "sg:province":"MA",
    "sg:tags":[
        "landscape",
        "contractor"
    ],
    "wof:name":"G & H Landscaping",
    "wof:placetype":"venue"
},
  "geometry": {"coordinates":[-72.613956,42.198827],"type":"Point"}
}