{
  "type": "Feature",
  "properties": {
    "iso:country":"US",
    "sg:address":"17 Accord Park Dr",
    "sg:city":"Norwell",
    "sg:classifiers":[
        {
            "category":"Health Services",
            "subcategory":"Doctor",
            "type":"Services"
        }
    ],
    "sg:phone":"+1 781 681 7088",
    "sg:postcode":"02061",
    "sg:province":"MA",
    "sg:tags":[
        "physician",
        "surgeon"
    ],
    "wof:name":"Practice First",
    "wof:placetype":"venue"
},
  "geometry": {"coordinates":[-70.889242,42.167132],"type":"Point"}
}