{
  "type": "Feature",
  "properties": {
    "iso:country":"US",
    "sg:address":"230 Maple St",
    "sg:city":"Holyoke",
    "sg:classifiers":[
        {
            "category":"Health Services",
            "subcategory":"Doctor",
            "type":"Services"
        }
    ],
    "sg:phone":"+1 413 420 2200",
    "sg:postcode":"01040",
    "sg:province":"MA",
    "sg:tags":[
        "clinic"
    ],
    "wof:name":"Holyoke Health Ctr",
    "wof:placetype":"venue"
},
  "geometry": {"coordinates":[-72.609494,42.206426],"type":"Point"}
}