{
  "type": "Feature",
  "properties": {
    "addr:full":"13 Shirley Rd Andover MA 01810",
    "addr:housenumber":"13",
    "addr:postcode":"01810",
    "addr:street":"Shirley Rd",
    "iso:country":"US",
    "sg:address":"13 Shirley Rd",
    "sg:city":"Andover",
    "sg:classifiers":[
        {
            "category":"Professional",
            "subcategory":"Management & Consulting",
            "type":"Services"
        }
    ],
    "sg:phone":"+1 978 749 0044",
    "sg:postcode":"01810",
    "sg:province":"MA",
    "sg:tags":[
        "conference",
        "consultant",
        "meeting"
    ],
    "wof:name":"Event Management Group Inc",
    "wof:placetype":"venue"
},
  "geometry": {"coordinates":[-71.167951,42.660284],"type":"Point"}
}