{
  "type": "Feature",
  "properties": {
    "iso:country":"US",
    "sg:address":"51 Sawyer Rd",
    "sg:city":"Waltham",
    "sg:classifiers":[
        {
            "category":"Wholesale",
            "subcategory":"Drugs",
            "type":"Manufacturing & Wholesale Goods"
        }
    ],
    "sg:phone":"+1 781 647 3900",
    "sg:postcode":"02453",
    "sg:province":"MA",
    "sg:tags":[
        "pharmaceutical",
        "product"
    ],
    "sg:website":"www.invernessmedical.com",
    "wof:name":"Inverness Medical Innovations",
    "wof:placetype":"venue"
},
  "geometry": {"coordinates":[-71.258518,42.361822],"type":"Point"}
}