{
  "type": "Feature",
  "properties": {
    "addr:full":"155 Pine St Amherst MA 01002",
    "addr:housenumber":"155",
    "addr:postcode":"01002",
    "addr:street":"Pine St",
    "iso:country":"US",
    "sg:address":"155 Pine St",
    "sg:city":"Amherst",
    "sg:classifiers":[
        {
            "category":"Real Estate",
            "subcategory":"Architect",
            "type":"Services"
        }
    ],
    "sg:phone":"+1 413 549 3616",
    "sg:postcode":"01002",
    "sg:province":"MA",
    "sg:website":"www.coldhamarchitects.com",
    "wof:name":"Coldham Architects",
    "wof:placetype":"venue"
},
  "geometry": {"coordinates":[-72.514983,42.412435],"type":"Point"}
}