{
  "type": "Feature",
  "properties": {
    "iso:country":"US",
    "sg:address":"72 Turnpike Rd",
    "sg:city":"Ipswich",
    "sg:classifiers":[
        {
            "category":"Food & Beverages",
            "subcategory":"Groceries & Convenience Stores",
            "type":"Retail Goods"
        }
    ],
    "sg:phone":"+1 978 356 8487",
    "sg:postcode":"01938",
    "sg:province":"MA",
    "sg:website":"www.cumberlandfarms.com",
    "wof:name":"Cumberland Farms",
    "wof:placetype":"venue"
},
  "geometry": {"coordinates":[-70.918297,42.685398],"type":"Point"}
}