{
  "type": "Feature",
  "properties": {
    "iso:country":"US",
    "sg:address":"258 Willard St",
    "sg:city":"Quincy",
    "sg:classifiers":[
        {
            "category":"Retail",
            "subcategory":"Auto Repair",
            "type":"Services"
        }
    ],
    "sg:phone":"+1 617 696 6450",
    "sg:postcode":"02169",
    "sg:province":"MA",
    "sg:tags":[
        "wrecker"
    ],
    "sg:website":"www.bluehillstowing.com",
    "wof:name":"Blue Hills Towing",
    "wof:placetype":"venue"
},
  "geometry": {"coordinates":[-71.033224,42.24733],"type":"Point"}
}