{
  "type": "Feature",
  "properties": {
    "addr:full": "130 Concord Ln Osterville MA 02655",
    "addr:housenumber": "130",
    "addr:postcode": "02655",
    "addr:street": "Concord Ln",
    "iso:country": "US",
    "sg:address": "130 Concord Ln",
    "sg:city": "Osterville",
    "sg:classifiers": [
      {
        "category": "Building \u0026 Trades",
        "subcategory": "Construction",
        "type": "Services"
      }
    ],
    "sg:phone": "+1 508 428 0599",
    "sg:postcode": "02655",
    "sg:province": "MA",
    "sg:tags": [
      "painter"
    ],
    "wof:name": "Alpha \u0026 Omega Painters",
    "wof:placetype": "venue"
  },
  "geometry": {"coordinates":[-70.38597,41.656223],"type":"Point"}
}
