{
  "type": "Feature",
  "properties": {
    "iso:country":"US",
    "sg:address":"114 Union St",
    "sg:city":"Lynn",
    "sg:classifiers":[
        {
            "category":"Food & Beverages",
            "subcategory":"Groceries & Convenience Stores",
            "type":"Retail Goods"
        }
    ],
    "sg:phone":"+1 781 477 7878",
    "sg:postcode":"01902",
    "sg:province":"MA",
    "wof:name":"Quisqueya Market",
    "wof:placetype":"venue"
},
  "geometry": {"coordinates":[-70.94096500000001,42.467295],"type":"Point"}
}