{
  "type": "Feature",
  "properties": {
    "iso:country":"US",
    "sg:address":"100 Summer St Ste 3200",
    "sg:city":"Boston",
    "sg:classifiers":[
        {
            "category":"Professional",
            "subcategory":"Engineering",
            "type":"Services"
        }
    ],
    "sg:phone":"+1 617 737 0262",
    "sg:postcode":"02110",
    "sg:province":"MA",
    "sg:tags":[
        "consultant",
        "energy",
        "conservation"
    ],
    "sg:website":"http://www.levitan.com",
    "wof:name":"Lai",
    "wof:placetype":"venue"
},
  "geometry": {"coordinates":[-71.057388,42.353359],"type":"Point"}
}