{
  "type": "Feature",
  "properties": {
    "addr:full": "300 Brickstone Sq Ste 203 Andover MA 01810",
    "addr:housenumber": "300",
    "addr:postcode": "01810",
    "addr:street": "Brickstone Sq Ste 203",
    "iso:country": "US",
    "sg:address": "300 Brickstone Sq Ste 203",
    "sg:city": "Andover",
    "sg:classifiers": [
      {
        "category": "Health Services",
        "subcategory": "Hospital",
        "type": "Services"
      }
    ],
    "sg:phone": "+1 978 482 2300",
    "sg:postcode": "01810",
    "sg:province": "MA",
    "sg:tags": [
      "equipment",
      "supply"
    ],
    "wof:name": "Capsuletech, Inc.",
    "wof:placetype": "venue"
  },
  "geometry": {"coordinates":[-71.146307,42.675234],"type":"Point"}
}
