{
  "type": "Feature",
  "properties": {
    "iso:country":"US",
    "sg:address":"222 Eastern Ave",
    "sg:city":"Gloucester",
    "sg:classifiers":[
        {
            "category":"Health Services",
            "subcategory":"Clinic",
            "type":"Services"
        }
    ],
    "sg:phone":"+1 978 282 4842",
    "sg:postcode":"01930",
    "sg:province":"MA",
    "sg:tags":[
        "holistic",
        "practitioner"
    ],
    "wof:name":"222 Arts & Wellness Ctr",
    "wof:placetype":"venue"
},
  "geometry": {"coordinates":[-70.69613699999999,42.615575],"type":"Point"}
}