{
  "type": "Feature",
  "properties": {
    "addr:full":"120 Westbourne Ter Brookline MA 02446",
    "addr:housenumber":"120",
    "addr:postcode":"02446",
    "addr:street":"Westbourne Ter",
    "iso:country":"US",
    "sg:address":"120 Westbourne Ter",
    "sg:city":"Brookline",
    "sg:classifiers":[
        {
            "category":"Professional",
            "subcategory":"Computer Services",
            "type":"Services"
        }
    ],
    "sg:phone":"+1 617 739 9925",
    "sg:postcode":"02446",
    "sg:province":"MA",
    "sg:tags":[
        "consultant",
        "product",
        "designer",
        "internet"
    ],
    "sg:website":"www.dataleverage.com",
    "wof:name":"Data-Lev-Erage",
    "wof:placetype":"venue"
},
  "geometry": {"coordinates":[-71.136987,42.341877],"type":"Point"}
}