{
  "type": "Feature",
  "properties": {
    "iso:country":"US",
    "sg:address":"220 Alewife Brook Pkwy",
    "sg:city":"Cambridge",
    "sg:classifiers":[
        {
            "category":"Coffee & Tea",
            "type":"Food & Drink"
        }
    ],
    "sg:phone":"+1 617 876 1070",
    "sg:postcode":"02138",
    "sg:province":"MA",
    "sg:website":"www.starbucks.com",
    "wof:name":"Starbucks",
    "wof:placetype":"venue"
},
  "geometry": {"coordinates":[-71.14241800000001,42.38852],"type":"Point"}
}