{
  "type": "Feature",
  "properties": {
    "addr:full": "220 Alewife Brook Pkwy Cambridge MA 02138",
    "addr:housenumber": "220",
    "addr:postcode": "02138",
    "addr:street": "Alewife Brook Pkwy",
    "iso:country": "US",
    "ovtr:label": "Starbucks, 222 Alewife Brook Pkwy Cambridge MA US",
    "ovtr:similarity": 3.3122410774230957,
    "sg:address": "220 Alewife Brook Pkwy",
    "sg:city": "Cambridge",
    "sg:classifiers": [
      {
        "category": "Coffee \u0026 Tea",
        "type": "Food \u0026 Drink"
      }
    ],
    "sg:phone": "+1 617 876 1070",
    "sg:postcode": "02138",
    "sg:province": "MA",
    "sg:website": "www.starbucks.com",
    "wof:name": "Starbucks",
    "wof:placetype": "venue"
  },
  "geometry": {"coordinates":[-71.142418,42.38852],"type":"Point"}
}
