{
  "type": "Feature",
  "properties": {
    "addr:full":"147 Nonotuck St Florence MA 01062",
    "addr:housenumber":"147",
    "addr:postcode":"01062",
    "addr:street":"Nonotuck St",
    "iso:country":"US",
    "sg:address":"147 Nonotuck St",
    "sg:city":"Florence",
    "sg:classifiers":[
        {
            "category":"Farming",
            "subcategory":"Nursery",
            "type":"Manufacturing & Wholesale Goods"
        }
    ],
    "sg:phone":"+1 413 587 9213",
    "sg:postcode":"01062",
    "sg:province":"MA",
    "sg:tags":[
        "greenhouse"
    ],
    "wof:name":"Cavicchio Greenhouses Inc",
    "wof:placetype":"venue"
},
  "geometry": {"coordinates":[-72.668603,42.330717],"type":"Point"}
}