{
  "type": "Feature",
  "properties": {
    "iso:country":"US",
    "sg:address":"262 Swansea Mall Dr",
    "sg:city":"Swansea",
    "sg:classifiers":[
        {
            "category":"Wholesale",
            "subcategory":"Stationery",
            "type":"Manufacturing & Wholesale Goods"
        }
    ],
    "sg:phone":"+1 508 676 3349",
    "sg:postcode":"02777",
    "sg:province":"MA",
    "sg:tags":[
        "container",
        "plastic"
    ],
    "wof:name":"Tupperware",
    "wof:placetype":"venue"
},
  "geometry": {"coordinates":[-71.220046,41.760038],"type":"Point"}
}