{
  "type": "Feature",
  "properties": {
    "addr:full":"125 Greenleaf St Quincy MA 02169",
    "addr:housenumber":"125",
    "addr:postcode":"02169",
    "addr:street":"Greenleaf St",
    "iso:country":"US",
    "sg:address":"125 Greenleaf St",
    "sg:city":"Quincy",
    "sg:classifiers":[
        {
            "category":"Insurance",
            "subcategory":"Insurance Agent",
            "type":"Services"
        },
        {
            "category":"Insurance",
            "subcategory":"Hazard Insurance",
            "type":"Services"
        }
    ],
    "sg:phone":"+1 617 328 8138",
    "sg:postcode":"02169",
    "sg:province":"MA",
    "sg:tags":[
        "business",
        "commercial",
        "fidelity",
        "surety",
        "bond"
    ],
    "wof:name":"Bradley Insurance & Bonding Agency Inc",
    "wof:placetype":"venue"
},
  "geometry": {"coordinates":[-71.00259200000001,42.257581],"type":"Point"}
}