{
  "type": "Feature",
  "properties": {
    "addr:full":"119 Webb St Salem MA 01970",
    "addr:housenumber":"119",
    "addr:postcode":"01970",
    "addr:street":"Webb St",
    "iso:country":"US",
    "sg:address":"119 Webb St",
    "sg:city":"Salem",
    "sg:classifiers":[
        {
            "category":"Retail",
            "subcategory":"Repair Shop",
            "type":"Services"
        }
    ],
    "sg:phone":"+1 978 744 0988",
    "sg:postcode":"01970",
    "sg:province":"MA",
    "sg:tags":[
        "lock",
        "locksmith"
    ],
    "wof:name":"Hayden Systems",
    "wof:placetype":"venue"
},
  "geometry": {"coordinates":[-70.89009,42.528104],"type":"Point"}
}