{
  "type": "Feature",
  "properties": {
    "addr:full": "430 Albemarle Rd Newton MA 02460",
    "addr:housenumber": "430",
    "addr:postcode": "02460",
    "addr:street": "Albemarle Rd",
    "iso:country": "US",
    "sg:address": "430 Albemarle Rd",
    "sg:city": "Newton",
    "sg:classifiers": [
      {
        "category": "Building \u0026 Trades",
        "subcategory": "Cleaning \u0026 Sanitation",
        "type": "Services"
      }
    ],
    "sg:phone": "+1 617 244 7776",
    "sg:postcode": "02460",
    "sg:province": "MA",
    "sg:tags": [
      "janitor"
    ],
    "wof:name": "In A Pinch Cleaning Svc",
    "wof:placetype": "venue"
  },
  "geometry": {"coordinates":[-71.214407,42.352691],"type":"Point"}
}
