{
  "type": "Feature",
  "properties": {
    "addr:full": "33 Middle St Lowell MA 01852",
    "addr:housenumber": "33",
    "addr:postcode": "01852",
    "addr:street": "Middle St",
    "iso:country": "US",
    "ovtr:label": "EYEFUL Beauty, 33 Middle St Lowell MA US",
    "ovtr:similarity": 2.452052116394043,
    "sg:address": "33 Middle St",
    "sg:city": "Lowell",
    "sg:phone": "+1 617 899 0781",
    "sg:postcode": "01852",
    "sg:province": "MA",
    "wof:name": "Eyeful Beauty",
    "wof:placetype": "venue"
  },
  "geometry": {"coordinates":[-71.311947,42.645264],"type":"Point"}
}
