{
  "type": "Feature",
  "properties": {
    "addr:full":"600 Page St Avon MA 02322",
    "addr:housenumber":"600",
    "addr:postcode":"02322",
    "addr:street":"Page St",
    "iso:country":"US",
    "sg:address":"600 Page St",
    "sg:city":"Avon",
    "sg:classifiers":[
        {
            "category":"Restaurant",
            "type":"Food & Drink"
        }
    ],
    "sg:phone":"+1 508 580 8338",
    "sg:postcode":"02322",
    "sg:province":"MA",
    "wof:name":"D'angelo's Sandwich Shops",
    "wof:placetype":"venue"
},
  "geometry": {"coordinates":[-71.046997,42.126598],"type":"Point"}
}