{
  "type": "Feature",
  "properties": {
    "iso:country":"US",
    "sg:address":"100 Danton Dr",
    "sg:city":"Methuen",
    "sg:classifiers":[
        {
            "category":"Freight",
            "type":"Transportation"
        }
    ],
    "sg:phone":"+1 978 794 9477",
    "sg:postcode":"01844",
    "sg:province":"MA",
    "sg:tags":[
        "warehouse"
    ],
    "wof:name":"Shaw's Methuen Warehouse",
    "wof:placetype":"venue"
},
  "geometry": {"coordinates":[-71.212413,42.719665],"type":"Point"}
}