{
  "type": "Feature",
  "properties": {
    "iso:country":"US",
    "sg:address":"PO Box 52137",
    "sg:city":"Boston",
    "sg:classifiers":[
        {
            "category":"Communications",
            "subcategory":"Newspaper",
            "type":"Services"
        }
    ],
    "sg:phone":"+1 617 275 4249",
    "sg:postcode":"02205",
    "sg:province":"MA",
    "sg:tags":[
        "print",
        "medium"
    ],
    "sg:website":"www.asianboston.com",
    "wof:name":"AsianBoston Media Group ABMG",
    "wof:placetype":"venue"
},
  "geometry": {"coordinates":[-71.0536,42.3512],"type":"Point"}
}