{
  "type": "Feature",
  "properties": {
    "iso:country":"US",
    "sg:address":"34 Church St",
    "sg:city":"Spencer",
    "sg:classifiers":[
        {
            "category":"Communications",
            "type":"Services"
        }
    ],
    "sg:phone":"+1 508 885 9406",
    "sg:postcode":"01562",
    "sg:province":"MA",
    "wof:name":"DKS Communications",
    "wof:placetype":"venue"
},
  "geometry": {"coordinates":[-71.99427900000001,42.240482],"type":"Point"}
}