{
  "type": "Feature",
  "properties": {
    "addr:full": "34 Church St Spencer MA 01562",
    "addr:housenumber": "34",
    "addr:postcode": "01562",
    "addr:street": "Church St",
    "iso:country": "US",
    "sg:address": "34 Church St",
    "sg:city": "Spencer",
    "sg:classifiers": [
      {
        "category": "Communications",
        "type": "Services"
      }
    ],
    "sg:phone": "+1 508 885 9406",
    "sg:postcode": "01562",
    "sg:province": "MA",
    "wof:name": "DKS Communications",
    "wof:placetype": "venue"
  },
  "geometry": {"coordinates":[-71.994279,42.240482],"type":"Point"}
}
