{
  "type": "Feature",
  "properties": {
    "addr:full":"269 Main St Greenfield MA 01301",
    "addr:housenumber":"269",
    "addr:postcode":"01301",
    "addr:street":"Main St",
    "iso:country":"US",
    "sg:address":"269 Main St",
    "sg:city":"Greenfield",
    "sg:classifiers":[
        {
            "category":"Food & Beverages",
            "subcategory":"Candy",
            "type":"Retail Goods"
        }
    ],
    "sg:phone":"+1 413 772 2263",
    "sg:postcode":"01301",
    "sg:province":"MA",
    "sg:tags":[
        "confectionery"
    ],
    "wof:name":"Candylicious",
    "wof:placetype":"venue"
},
  "geometry": {"coordinates":[-72.21093399999999,42.306171],"type":"Point"}
}