{
  "type": "Feature",
  "properties": {
    "addr:full": "250 S Main St Middleton MA 01949",
    "addr:housenumber": "250",
    "addr:postcode": "01949",
    "addr:street": "S Main St",
    "atp:label": "Dairy Queen, 250 S Main St Middleton MA US",
    "atp:similarity": 3.1906790733337402,
    "iso:country": "US",
    "sg:address": "250 S Main St",
    "sg:city": "Middleton",
    "sg:classifiers": [
      {
        "category": "Ice Cream",
        "type": "Food \u0026 Drink"
      }
    ],
    "sg:menulink": "http://www.allmenus.com/ma/middleton/168423-dairy-queen/menu/",
    "sg:phone": "+1 978 777 3663",
    "sg:postcode": "01949",
    "sg:province": "MA",
    "sg:tags": [
      "burger",
      "american"
    ],
    "wof:name": "Dairy Queen",
    "wof:placetype": "venue"
  },
  "geometry": {"coordinates":[-71.001001,42.579842],"type":"Point"}
}
