{
  "type": "Feature",
  "properties": {
    "iso:country":"US",
    "sg:address":"250 S Main St",
    "sg:city":"Middleton",
    "sg:classifiers":[
        {
            "category":"Ice Cream",
            "type":"Food & Drink"
        }
    ],
    "sg:menulink":"http://www.allmenus.com/ma/middleton/168423-dairy-queen/menu/",
    "sg:phone":"+1 978 777 3663",
    "sg:postcode":"01949",
    "sg:province":"MA",
    "sg:tags":[
        "burger",
        "american"
    ],
    "wof:name":"Dairy Queen",
    "wof:placetype":"venue"
},
  "geometry": {"coordinates":[-71.001001,42.579842],"type":"Point"}
}