{
  "type": "Feature",
  "properties": {
    "iso:country":"US",
    "sg:address":"10 W Central St",
    "sg:city":"Natick",
    "sg:classifiers":[
        {
            "category":"Building & Trades",
            "subcategory":"Construction",
            "type":"Services"
        }
    ],
    "sg:phone":"+1 508 655 7910",
    "sg:postcode":"01760",
    "sg:province":"MA",
    "sg:tags":[
        "painter"
    ],
    "wof:name":"Cobb Brothers Co",
    "wof:placetype":"venue"
},
  "geometry": {"coordinates":[-71.34958399999999,42.283435],"type":"Point"}
}