{
  "type": "Feature",
  "properties": {
    "addr:full": "27 Pleasant St Ware MA 01082",
    "addr:housenumber": "27",
    "addr:postcode": "01082",
    "addr:street": "Pleasant St",
    "iso:country": "US",
    "sg:address": "27 Pleasant St",
    "sg:city": "Ware",
    "sg:classifiers": [
      {
        "category": "Organizations",
        "subcategory": "Religious Organization",
        "type": "Services"
      }
    ],
    "sg:phone": "+1 413 967 8307",
    "sg:postcode": "01082",
    "sg:province": "MA",
    "sg:tags": [
      "monastery",
      "convent"
    ],
    "wof:name": "Sisters Of St Joseph",
    "wof:placetype": "venue"
  },
  "geometry": {"coordinates":[-72.239961,42.261509],"type":"Point"}
}
