{
  "type": "Feature",
  "properties": {
    "addr:full":"167 Melrose St Auburndale MA 02466",
    "addr:housenumber":"167",
    "addr:postcode":"02466",
    "addr:street":"Melrose St",
    "iso:country":"US",
    "sg:address":"167 Melrose St",
    "sg:city":"Auburndale",
    "sg:classifiers":[
        {
            "category":"Professional",
            "subcategory":"Art Services",
            "type":"Services"
        }
    ],
    "sg:phone":"+1   ",
    "sg:postcode":"02466",
    "sg:province":"MA",
    "sg:tags":[
        "commercial",
        "design"
    ],
    "wof:name":"Steinberg Miller Design",
    "wof:placetype":"venue"
},
  "geometry": {"coordinates":[-71.24921500000001,42.349932],"type":"Point"}
}