{
  "type": "Feature",
  "properties": {
    "iso:country":"US",
    "sg:address":"19 Uncle Ezra's Path",
    "sg:city":"Dennis Port",
    "sg:classifiers":[
        {
            "category":"Building & Trades",
            "subcategory":"Plumbing",
            "type":"Services"
        }
    ],
    "sg:phone":"+1   ",
    "sg:postcode":"02639",
    "sg:province":"MA",
    "sg:tags":[
        "contractor"
    ],
    "wof:name":"Michael Rylander",
    "wof:placetype":"venue"
},
  "geometry": {"coordinates":[-70.14021099999999,41.662196],"type":"Point"}
}