{
  "type": "Feature",
  "properties": {
    "addr:full": "19 Uncle Ezra's Path Dennis Port MA 02639",
    "addr:housenumber": "19",
    "addr:postcode": "02639",
    "addr:street": "Uncle Ezra'S Path",
    "iso:country": "US",
    "sg:address": "19 Uncle Ezra's Path",
    "sg:city": "Dennis Port",
    "sg:classifiers": [
      {
        "category": "Building \u0026 Trades",
        "subcategory": "Plumbing",
        "type": "Services"
      }
    ],
    "sg:phone": "+1   ",
    "sg:postcode": "02639",
    "sg:province": "MA",
    "sg:tags": [
      "contractor"
    ],
    "wof:name": "Michael Rylander",
    "wof:placetype": "venue"
  },
  "geometry": {"coordinates":[-70.140211,41.662196],"type":"Point"}
}
