{
  "type": "Feature",
  "properties": {
    "addr:full":"162 Queen Anne Rd Harwich MA 02645",
    "addr:housenumber":"162",
    "addr:postcode":"02645",
    "addr:street":"Queen Anne Rd",
    "iso:country":"US",
    "sg:address":"162 Queen Anne Rd",
    "sg:city":"Harwich",
    "sg:classifiers":[
        {
            "category":"Manufacturing",
            "subcategory":"Tools & Machinery",
            "type":"Manufacturing & Wholesale Goods"
        }
    ],
    "sg:phone":"+1 508 432 1830",
    "sg:postcode":"02645",
    "sg:province":"MA",
    "sg:tags":[
        "machine",
        "shop"
    ],
    "wof:name":"Phipps Machinery & Welding",
    "wof:placetype":"venue"
},
  "geometry": {"coordinates":[-70.097244,41.6984],"type":"Point"}
}