{
  "type": "Feature",
  "properties": {
    "addr:full":"720 Atlantic Ave Boston MA 02111",
    "addr:housenumber":"720",
    "addr:postcode":"02111",
    "addr:street":"Atlantic Ave",
    "iso:country":"US",
    "sg:address":"720 Atlantic Ave",
    "sg:city":"Boston",
    "sg:phone":"+1 617 345 0427",
    "sg:postcode":"02111",
    "sg:province":"MA",
    "sg:website":"http://www.aubonpain.com",
    "wof:name":"Au Bon Pain",
    "wof:placetype":"venue"
},
  "geometry": {"coordinates":[-71.056602,42.350422],"type":"Point"}
}