{
  "type": "Feature",
  "properties": {
    "addr:full":"18 N Meadows Rd Medfield MA 02052",
    "addr:housenumber":"18",
    "addr:postcode":"02052",
    "addr:street":"N Meadows Rd",
    "iso:country":"US",
    "sg:address":"18 N Meadows Rd",
    "sg:city":"Medfield",
    "sg:classifiers":[
        {
            "category":"Building & Trades",
            "subcategory":"Plumbing",
            "type":"Services"
        }
    ],
    "sg:phone":"+1 508 359 1085",
    "sg:postcode":"02052",
    "sg:province":"MA",
    "sg:tags":[
        "tank",
        "installation"
    ],
    "wof:name":"Sea-Land Environmental",
    "wof:placetype":"venue"
},
  "geometry": {"coordinates":[-71.31406,42.18884],"type":"Point"}
}