{
  "type": "Feature",
  "properties": {
    "iso:country":"US",
    "sg:address":"33 Locust St",
    "sg:city":"Dorchester",
    "sg:classifiers":[
        {
            "category":"Wholesale",
            "subcategory":"Machinery & Supplies",
            "type":"Manufacturing & Wholesale Goods"
        }
    ],
    "sg:phone":"+1 617 825 3800",
    "sg:postcode":"02125",
    "sg:province":"MA",
    "sg:tags":[
        "renting",
        "equipment",
        "lawn",
        "garden",
        "contractor"
    ],
    "sg:website":"http://www.stihldealer.net/default-dealer-043469.aspx",
    "wof:name":"ATS Equipment Inc",
    "wof:placetype":"venue"
},
  "geometry": {"coordinates":[-71.055708,42.323391],"type":"Point"}
}