{
  "type": "Feature",
  "properties": {
    "addr:full": "286 Summer St Boston MA 02210",
    "addr:housenumber": "286",
    "addr:postcode": "02210",
    "addr:street": "Summer St",
    "iso:country": "US",
    "sg:address": "286 Summer St",
    "sg:city": "Boston",
    "sg:classifiers": [
      {
        "category": "Real Estate",
        "subcategory": "Real Estate Services",
        "type": "Services"
      },
      {
        "category": "Real Estate",
        "subcategory": "Developer",
        "type": "Services"
      },
      {
        "category": "Real Estate",
        "subcategory": "Real Estate Agent",
        "type": "Services"
      }
    ],
    "sg:phone": "+1 617 423 1174",
    "sg:postcode": "02210",
    "sg:province": "MA",
    "sg:tags": [
      "buyer",
      "broker"
    ],
    "sg:website": "http://www.teelrealty.com",
    "wof:name": "Teel Realty",
    "wof:placetype": "venue"
  },
  "geometry": {"coordinates":[-71.049287,42.349805],"type":"Point"}
}
