{
  "type": "Feature",
  "properties": {
    "iso:country":"US",
    "sg:address":"1730 Massachusetts Avenue",
    "sg:city":"Cambridge",
    "sg:classifiers":[
        {
            "category":"Real Estate",
            "subcategory":"Real Estate Agent",
            "type":"Services"
        }
    ],
    "sg:phone":"+1 617 864 4430",
    "sg:postcode":"02138",
    "sg:province":"MA",
    "sg:website":"www.newenglandmoves.com/officeSe...",
    "wof:name":"Coldwell Banker Residential Brokerage",
    "wof:placetype":"venue"
},
  "geometry": {"coordinates":[-71.119502,42.384678],"type":"Point"}
}