{
  "type": "Feature",
  "properties": {
    "iso:country":"US",
    "sg:address":"78 Summer St",
    "sg:city":"Boston",
    "sg:classifiers":[
        {
            "category":"Personal",
            "subcategory":"Beauty Salon",
            "type":"Services"
        }
    ],
    "sg:phone":"+1 617 350 7868",
    "sg:postcode":"02110",
    "sg:province":"MA",
    "sg:tags":[
        "hair"
    ],
    "sg:website":"www.dellaria.com",
    "wof:name":"Dellaria Salon",
    "wof:placetype":"venue"
},
  "geometry": {"coordinates":[-71.058215,42.354073],"type":"Point"}
}