{
  "type": "Feature",
  "properties": {
    "addr:full": "84 Westech Dr Tyngsboro MA 01879",
    "addr:housenumber": "84",
    "addr:postcode": "01879",
    "addr:street": "Westech Dr",
    "iso:country": "US",
    "sg:address": "84 Westech Dr",
    "sg:city": "Tyngsboro",
    "sg:classifiers": [
      {
        "category": "Building \u0026 Trades",
        "subcategory": "Electrical",
        "type": "Services"
      }
    ],
    "sg:phone": "+1 978 649 4046",
    "sg:postcode": "01879",
    "sg:province": "MA",
    "sg:tags": [
      "electric",
      "contractor"
    ],
    "wof:name": "RFB Electrical",
    "wof:placetype": "venue"
  },
  "geometry": {"coordinates":[-71.425218,42.659022],"type":"Point"}
}
