{
  "type": "Feature",
  "properties": {
    "addr:full": "1590 Concord St Framingham MA 01701",
    "addr:housenumber": "1590",
    "addr:postcode": "01701",
    "addr:street": "Concord St",
    "iso:country": "US",
    "sg:address": "1590 Concord St",
    "sg:city": "Framingham",
    "sg:classifiers": [
      {
        "category": "Freight",
        "type": "Transportation"
      }
    ],
    "sg:phone": "+1 508 877 5566",
    "sg:postcode": "01701",
    "sg:province": "MA",
    "sg:tags": [
      "warehouse",
      "self",
      "storage"
    ],
    "wof:name": "Storage USA",
    "wof:placetype": "venue"
  },
  "geometry": {"coordinates":[-71.399371,42.324067],"type":"Point"}
}
