{
  "type": "Feature",
  "properties": {
    "addr:full":"21 Clark St North Andover MA 01845",
    "addr:housenumber":"21",
    "addr:postcode":"01845",
    "addr:street":"Clark St",
    "iso:country":"US",
    "sg:address":"21 Clark St",
    "sg:city":"North Andover",
    "sg:classifiers":[
        {
            "category":"Wholesale",
            "subcategory":"Scrap",
            "type":"Manufacturing & Wholesale Goods"
        }
    ],
    "sg:phone":"+1 978 688 9009",
    "sg:postcode":"01845",
    "sg:province":"MA",
    "sg:tags":[
        "recycling",
        "center"
    ],
    "wof:name":"Derosa Landfill Management",
    "wof:placetype":"venue"
},
  "geometry": {"coordinates":[-71.115988,42.71798],"type":"Point"}
}