{
  "type": "Feature",
  "properties": {
    "addr:full": "97 Jarvis Cir Needham MA 02492",
    "addr:housenumber": "97",
    "addr:postcode": "02492",
    "addr:street": "Jarvis Cir",
    "iso:country": "US",
    "sg:address": "97 Jarvis Cir",
    "sg:city": "Needham",
    "sg:classifiers": [
      {
        "category": "Building \u0026 Trades",
        "subcategory": "Electrical",
        "type": "Services"
      }
    ],
    "sg:phone": "+1 781 801 0565",
    "sg:postcode": "02492",
    "sg:province": "MA",
    "sg:tags": [
      "electrician"
    ],
    "wof:name": "John Mcaward Electrical Contr",
    "wof:placetype": "venue"
  },
  "geometry": {"coordinates":[-71.248738,42.29029],"type":"Point"}
}
