{
  "type": "Feature",
  "properties": {
    "addr:full": "10 Saint James Ave Boston MA 02116",
    "addr:housenumber": "10",
    "addr:postcode": "02116",
    "addr:street": "Saint James Ave",
    "iso:country": "US",
    "sg:address": "10 Saint James Ave",
    "sg:city": "Boston",
    "sg:classifiers": [
      {
        "category": "Professional",
        "type": "Services"
      },
      {
        "category": "Personal",
        "type": "Services"
      }
    ],
    "sg:phone": "+1 617 357 9777",
    "sg:postcode": "02116",
    "sg:province": "MA",
    "sg:tags": [
      "home"
    ],
    "sg:website": "www.arclineaboston.com",
    "wof:name": "Arclinea Boston",
    "wof:placetype": "venue"
  },
  "geometry": {"coordinates":[-71.070852,42.350902],"type":"Point"}
}
