{
  "type": "Feature",
  "properties": {
    "addr:full": "722 Huntington Ave Boston MA 02115",
    "addr:housenumber": "722",
    "addr:postcode": "02115",
    "addr:street": "Huntington Ave",
    "iso:country": "US",
    "sg:address": "722 Huntington Ave",
    "sg:city": "Boston",
    "sg:classifiers": [
      {
        "category": "Building \u0026 Trades",
        "subcategory": "Locksmith",
        "type": "Services"
      }
    ],
    "sg:phone": "+1 617 303 2714",
    "sg:postcode": "02115",
    "sg:province": "MA",
    "sg:tags": [
      "key"
    ],
    "wof:name": "Go Smart Locksmith",
    "wof:placetype": "venue"
  },
  "geometry": {"coordinates":[-71.104994,42.333853],"type":"Point"}
}
