{
  "type": "Feature",
  "properties": {
    "addr:full": "6 Canterbury Dr Plymouth MA 02360",
    "addr:housenumber": "6",
    "addr:postcode": "02360",
    "addr:street": "Canterbury Dr",
    "iso:country": "US",
    "sg:address": "6 Canterbury Dr",
    "sg:city": "Plymouth",
    "sg:classifiers": [
      {
        "category": "Building \u0026 Trades",
        "subcategory": "Electrical",
        "type": "Services"
      }
    ],
    "sg:phone": "+1 508 747 2330",
    "sg:postcode": "02360",
    "sg:province": "MA",
    "sg:tags": [
      "electrician"
    ],
    "wof:name": "Decesar Electric",
    "wof:placetype": "venue"
  },
  "geometry": {"coordinates":[-70.709333,41.905014],"type":"Point"}
}
