{
  "type": "Feature",
  "properties": {
    "addr:full":"910 Broadway Saugus MA 01906",
    "addr:housenumber":"910",
    "addr:postcode":"01906",
    "addr:street":"Broadway",
    "iso:country":"US",
    "sg:address":"910 Broadway",
    "sg:city":"Saugus",
    "sg:classifiers":[
        {
            "category":"Shopping",
            "subcategory":"Clothing, Apparel, & Fashions",
            "type":"Retail Goods"
        }
    ],
    "sg:phone":"+1 781 231 9060",
    "sg:postcode":"01906",
    "sg:province":"MA",
    "sg:tags":[
        "clothing",
        "boys'",
        "store"
    ],
    "wof:name":"Hajjar's Big & Tall",
    "wof:placetype":"venue"
},
  "geometry": {"coordinates":[-71.025398,42.467995],"type":"Point"}
}