{
  "type": "Feature",
  "properties": {
    "iso:country":"US",
    "sg:address":"33 Electric Ave",
    "sg:city":"Fitchburg",
    "sg:classifiers":[
        {
            "category":"Health Services",
            "subcategory":"Optometrist",
            "type":"Services"
        }
    ],
    "sg:phone":"+1   ",
    "sg:postcode":"01420",
    "sg:province":"MA",
    "wof:name":"Anesthesia Center For Pain",
    "wof:placetype":"venue"
},
  "geometry": {"coordinates":[-71.798393,42.568399],"type":"Point"}
}