{
  "type": "Feature",
  "properties": {
    "addr:full": "37 Buena Vista Rd Arlington MA 02476",
    "addr:housenumber": "37",
    "addr:postcode": "02476",
    "addr:street": "Buena Vista Rd",
    "iso:country": "US",
    "sg:address": "37 Buena Vista Rd",
    "sg:city": "Arlington",
    "sg:classifiers": [
      {
        "category": "Health Services",
        "subcategory": "Hospital",
        "type": "Services"
      }
    ],
    "sg:phone": "+1 781 643 7783",
    "sg:postcode": "02476",
    "sg:province": "MA",
    "sg:tags": [
      "equipment",
      "supply"
    ],
    "wof:name": "Clarence E Smith Co Inc",
    "wof:placetype": "venue"
  },
  "geometry": {"coordinates":[-71.177794,42.418195],"type":"Point"}
}
