{
  "type": "Feature",
  "properties": {
    "iso:country":"US",
    "sg:address":"30 Hamilton Rd",
    "sg:city":"Arlington",
    "sg:classifiers":[
        {
            "category":"Professional",
            "subcategory":"Computer Services",
            "type":"Services"
        }
    ],
    "sg:phone":"+1 781 641 4423",
    "sg:postcode":"02474",
    "sg:province":"MA",
    "sg:tags":[
        "consultant",
        "designer"
    ],
    "wof:name":"DAO Design Inc",
    "wof:placetype":"venue"
},
  "geometry": {"coordinates":[-71.14839600000001,42.406832],"type":"Point"}
}