{
  "type": "Feature",
  "properties": {
    "addr:full":"15 State St Newburyport MA 01950",
    "addr:housenumber":"15",
    "addr:postcode":"01950",
    "addr:street":"State St",
    "iso:country":"US",
    "sg:address":"15 State St",
    "sg:city":"Newburyport",
    "sg:classifiers":[
        {
            "category":"Shopping",
            "subcategory":"Clothing, Apparel, & Fashions",
            "type":"Retail Goods"
        }
    ],
    "sg:phone":"+1 978 465 7650",
    "sg:postcode":"01950",
    "sg:province":"MA",
    "sg:tags":[
        "children's",
        "clothing"
    ],
    "sg:website":"www.livelykid.com",
    "wof:name":"Lively Kids",
    "wof:placetype":"venue"
},
  "geometry": {"coordinates":[-70.869911,42.810616],"type":"Point"}
}