{
  "type": "Feature",
  "properties": {
    "addr:full":"34 Coolidge St Lawrence MA 01843",
    "addr:housenumber":"34",
    "addr:postcode":"01843",
    "addr:street":"Coolidge St",
    "iso:country":"US",
    "sg:address":"34 Coolidge St",
    "sg:city":"Lawrence",
    "sg:classifiers":[
        {
            "category":"Building & Trades",
            "subcategory":"Plumbing",
            "type":"Services"
        }
    ],
    "sg:phone":"+1 978 681 1979",
    "sg:postcode":"01843",
    "sg:province":"MA",
    "sg:tags":[
        "plumbing",
        "contractor"
    ],
    "wof:name":"David Field Plumbing & Heating",
    "wof:placetype":"venue"
},
  "geometry": {"coordinates":[-71.168663,42.693495],"type":"Point"}
}