{
  "type": "Feature",
  "properties": {
    "iso:country":"US",
    "sg:address":"57 Mcdonald St",
    "sg:city":"Dedham",
    "sg:classifiers":[
        {
            "category":"Building & Trades",
            "subcategory":"Landscaping Services",
            "type":"Services"
        },
        {
            "category":"Home & Garden",
            "subcategory":"Garden Supply",
            "type":"Retail Goods"
        }
    ],
    "sg:phone":"+1 781 329 8494",
    "sg:postcode":"02026",
    "sg:province":"MA",
    "sg:tags":[
        "horticulture",
        "product",
        "stump",
        "tree",
        "grinding",
        "removal",
        "arborist"
    ],
    "sg:website":"http://www.royertreeservice.com",
    "wof:name":"Royer Tree Service Inc",
    "wof:placetype":"venue"
},
  "geometry": {"coordinates":[-71.138395,42.232322],"type":"Point"}
}