{
  "type": "Feature",
  "properties": {
    "addr:full": "57 Mcdonald St Dedham MA 02026",
    "addr:housenumber": "57",
    "addr:postcode": "02026",
    "addr:street": "Mcdonald St",
    "iso:country": "US",
    "ovtr:label": "Royer Tree Service, 57 McDonald St Dedham MA US",
    "ovtr:similarity": 3.3819870948791504,
    "sg:address": "57 Mcdonald St",
    "sg:city": "Dedham",
    "sg:classifiers": [
      {
        "category": "Building \u0026 Trades",
        "subcategory": "Landscaping Services",
        "type": "Services"
      },
      {
        "category": "Home \u0026 Garden",
        "subcategory": "Garden Supply",
        "type": "Retail Goods"
      }
    ],
    "sg:phone": "+1 781 329 8494",
    "sg:postcode": "02026",
    "sg:province": "MA",
    "sg:tags": [
      "horticulture",
      "product",
      "stump",
      "tree",
      "grinding",
      "removal",
      "arborist"
    ],
    "sg:website": "http://www.royertreeservice.com",
    "wof:name": "Royer Tree Service Inc",
    "wof:placetype": "venue"
  },
  "geometry": {"coordinates":[-71.138395,42.232322],"type":"Point"}
}
