{
  "type": "Feature",
  "properties": {
    "addr:full":"80 Washington St Norwell MA 02061",
    "addr:housenumber":"80",
    "addr:postcode":"02061",
    "addr:street":"Washington St",
    "iso:country":"US",
    "sg:address":"80 Washington St",
    "sg:city":"Norwell",
    "sg:classifiers":[
        {
            "category":"Banks & Credit Unions",
            "subcategory":"Bank",
            "type":"Services"
        }
    ],
    "sg:phone":"+1 781 871 8650",
    "sg:postcode":"02061",
    "sg:province":"MA",
    "wof:name":"Eastern Bank",
    "wof:placetype":"venue"
},
  "geometry": {"coordinates":[-70.880346,42.172979],"type":"Point"}
}