{
  "type": "Feature",
  "properties": {
    "iso:country":"US",
    "sg:address":"75 Pine St",
    "sg:city":"West Springfield",
    "sg:classifiers":[
        {
            "category":"Education",
            "subcategory":"School",
            "type":"Public Place"
        }
    ],
    "sg:phone":"+1 413 739 4131",
    "sg:postcode":"01089",
    "sg:province":"MA",
    "wof:name":"St Thomas School",
    "wof:placetype":"venue"
},
  "geometry": {"coordinates":[-72.64048099999999,42.108255],"type":"Point"}
}