{
  "type": "Feature",
  "properties": {
    "addr:full": "9 Myers Ln Milton MA 02186",
    "addr:housenumber": "9",
    "addr:postcode": "02186",
    "addr:street": "Myers Ln",
    "iso:country": "US",
    "sg:address": "9 Myers Ln",
    "sg:city": "Milton",
    "sg:classifiers": [
      {
        "category": "Wholesale",
        "subcategory": "Non-durable Goods",
        "type": "Manufacturing \u0026 Wholesale Goods"
      }
    ],
    "sg:phone": "+1 617 696 1783",
    "sg:postcode": "02186",
    "sg:province": "MA",
    "sg:tags": [
      "merchandise-wholesale",
      "mfg"
    ],
    "wof:name": "Cam Enterprise",
    "wof:placetype": "venue"
  },
  "geometry": {"coordinates":[-71.096643,42.243606],"type":"Point"}
}
