{
  "type": "Feature",
  "properties": {
    "addr:full":"17 Nashua Rd Pepperell MA 01463",
    "addr:housenumber":"17",
    "addr:postcode":"01463",
    "addr:street":"Nashua Rd",
    "iso:country":"US",
    "sg:address":"17 Nashua Rd",
    "sg:city":"Pepperell",
    "sg:classifiers":[
        {
            "category":"Retail",
            "subcategory":"Auto Repair",
            "type":"Services"
        }
    ],
    "sg:phone":"+1 978 433 8200",
    "sg:postcode":"01463",
    "sg:province":"MA",
    "sg:tags":[
        "repairing",
        "automobile"
    ],
    "wof:name":"Auto Clinic",
    "wof:placetype":"venue"
},
  "geometry": {"coordinates":[-71.577487,42.673916],"type":"Point"}
}