{
  "type": "Feature",
  "properties": {
    "addr:full": "660 Cheshire Rd Lanesboro MA 01237",
    "addr:housenumber": "660",
    "addr:postcode": "01237",
    "addr:street": "Cheshire Rd",
    "iso:country": "US",
    "sg:address": "660 Cheshire Rd",
    "sg:city": "Lanesboro",
    "sg:classifiers": [
      {
        "category": "Restaurant",
        "type": "Food \u0026 Drink"
      }
    ],
    "sg:phone": "+1 413 499 5562",
    "sg:postcode": "01237",
    "sg:province": "MA",
    "sg:tags": [
      "italian",
      "pizza"
    ],
    "sg:website": "http://www.arizonapizza.com",
    "wof:name": "Pasta's Arizona Pizza Co",
    "wof:placetype": "venue"
  },
  "geometry": {"coordinates":[-73.202959,42.527686],"type":"Point"}
}
