{
  "type": "Feature",
  "properties": {
    "iso:country":"US",
    "sg:address":"55 Mead St",
    "sg:city":"Seekonk",
    "sg:classifiers":[
        {
            "category":"Professional",
            "type":"Services"
        },
        {
            "category":"Personal",
            "type":"Services"
        },
        {
            "category":"Freight",
            "type":"Transportation"
        },
        {
            "category":"Retail",
            "subcategory":"Storage",
            "type":"Services"
        }
    ],
    "sg:phone":"+1 508 336 7766",
    "sg:postcode":"02771",
    "sg:province":"MA",
    "sg:tags":[
        "full",
        "household",
        "material",
        "commercial",
        "trucking",
        "moving",
        "services-labor",
        "mover",
        "local"
    ],
    "sg:website":"http://www.conlonmoving.com",
    "wof:name":"Conlon Moving & Storage Inc",
    "wof:placetype":"venue"
},
  "geometry": {"coordinates":[-71.32804299999999,41.790283],"type":"Point"}
}