{
  "type": "Feature",
  "properties": {
    "addr:full": "55 Mead St Seekonk MA 02771",
    "addr:housenumber": "55",
    "addr:postcode": "02771",
    "addr:street": "Mead St",
    "iso:country": "US",
    "sg:address": "55 Mead St",
    "sg:city": "Seekonk",
    "sg:classifiers": [
      {
        "category": "Professional",
        "type": "Services"
      },
      {
        "category": "Personal",
        "type": "Services"
      },
      {
        "category": "Freight",
        "type": "Transportation"
      },
      {
        "category": "Retail",
        "subcategory": "Storage",
        "type": "Services"
      }
    ],
    "sg:phone": "+1 508 336 7766",
    "sg:postcode": "02771",
    "sg:province": "MA",
    "sg:tags": [
      "full",
      "household",
      "material",
      "commercial",
      "trucking",
      "moving",
      "services-labor",
      "mover",
      "local"
    ],
    "sg:website": "http://www.conlonmoving.com",
    "wof:name": "Conlon Moving \u0026 Storage Inc",
    "wof:placetype": "venue"
  },
  "geometry": {"coordinates":[-71.328043,41.790283],"type":"Point"}
}
