{
  "type": "Feature",
  "properties": {
    "addr:full": "95 Newbury St Lawrence MA 01841",
    "addr:housenumber": "95",
    "addr:postcode": "01841",
    "addr:street": "Newbury St",
    "iso:country": "US",
    "sg:address": "95 Newbury St",
    "sg:city": "Lawrence",
    "sg:classifiers": [
      {
        "category": "Restaurant",
        "type": "Food \u0026 Drink"
      }
    ],
    "sg:phone": "+1 978 682 8111",
    "sg:postcode": "01841",
    "sg:province": "MA",
    "wof:name": "Zuny Restaurant",
    "wof:placetype": "venue"
  },
  "geometry": {"coordinates":[-71.155556,42.712328],"type":"Point"}
}
