{
  "type": "Feature",
  "properties": {
    "iso:country":"US",
    "sg:address":"1 Ave A",
    "sg:city":"Turners Falls",
    "sg:classifiers":[
        {
            "category":"Government",
            "subcategory":"Office",
            "type":"Public Place"
        }
    ],
    "sg:phone":"+1 413 863 3201",
    "sg:postcode":"01376",
    "sg:province":"MA",
    "sg:tags":[
        "village"
    ],
    "wof:name":"Administrative Assistant",
    "wof:placetype":"venue"
},
  "geometry": {"coordinates":[-72.555041,42.609852],"type":"Point"}
}