{
  "type": "Feature",
  "properties": {
    "addr:full": "45 Partridge Way Centerville MA 02632",
    "addr:housenumber": "45",
    "addr:postcode": "02632",
    "addr:street": "Partridge Way",
    "iso:country": "US",
    "sg:address": "45 Partridge Way",
    "sg:city": "Centerville",
    "sg:classifiers": [
      {
        "category": "Building \u0026 Trades",
        "subcategory": "Landscaping Services",
        "type": "Services"
      }
    ],
    "sg:phone": "+1 508 775 6255",
    "sg:postcode": "02632",
    "sg:province": "MA",
    "sg:tags": [
      "tree"
    ],
    "wof:name": "Arborscapes",
    "wof:placetype": "venue"
  },
  "geometry": {"coordinates":[-70.340503,41.648325],"type":"Point"}
}
