{
  "type": "Feature",
  "properties": {
    "iso:country":"US",
    "sg:address":"100 Hano St",
    "sg:city":"Allston",
    "sg:classifiers":[
        {
            "category":"Freight",
            "type":"Transportation"
        }
    ],
    "sg:phone":"+1 617 787 3881",
    "sg:postcode":"02134",
    "sg:province":"MA",
    "sg:tags":[
        "delivery"
    ],
    "wof:name":"Sunrise Trucking",
    "wof:placetype":"venue"
},
  "geometry": {"coordinates":[-71.136228,42.354094],"type":"Point"}
}