{
  "type": "Feature",
  "properties": {
    "addr:full":"235 White St Lowell MA 01854",
    "addr:housenumber":"235",
    "addr:postcode":"01854",
    "addr:street":"White St",
    "iso:country":"US",
    "sg:address":"235 White St",
    "sg:city":"Lowell",
    "sg:classifiers":[
        {
            "category":"Insurance",
            "subcategory":"Insurance Agent",
            "type":"Services"
        }
    ],
    "sg:phone":"+1 978 453 7391",
    "sg:postcode":"01854",
    "sg:province":"MA",
    "wof:name":"Albert EJ Bergeron Insurance",
    "wof:placetype":"venue"
},
  "geometry": {"coordinates":[-71.32866,42.655842],"type":"Point"}
}