{
  "type": "Feature",
  "properties": {
    "iso:country":"US",
    "sg:address":"230 North St",
    "sg:city":"Medfield",
    "sg:classifiers":[
        {
            "category":"Farming",
            "subcategory":"Farm",
            "type":"Manufacturing & Wholesale Goods"
        }
    ],
    "sg:phone":"+1 508 359 0081",
    "sg:postcode":"02052",
    "sg:province":"MA",
    "wof:name":"Long Grove Farm",
    "wof:placetype":"venue"
},
  "geometry": {"coordinates":[-71.31098,42.204425],"type":"Point"}
}