{
  "type": "Feature",
  "properties": {
    "addr:full": "15 Creek Rd Marion MA 02738",
    "addr:housenumber": "15",
    "addr:postcode": "02738",
    "addr:street": "Creek Rd",
    "iso:country": "US",
    "sg:address": "15 Creek Rd",
    "sg:city": "Marion",
    "sg:classifiers": [
      {
        "category": "Professional",
        "subcategory": "Advertising",
        "type": "Services"
      }
    ],
    "sg:phone": "+1 508 748 1600",
    "sg:postcode": "02738",
    "sg:province": "MA",
    "sg:tags": [
      "counselor"
    ],
    "sg:website": "www.jkurgan.com",
    "wof:name": "John Kurgan Assoc Inc",
    "wof:placetype": "venue"
  },
  "geometry": {"coordinates":[-70.759086,41.72277],"type":"Point"}
}
