{
  "type": "Feature",
  "properties": {
    "iso:country":"US",
    "sg:address":"1168 Highland Ave",
    "sg:city":"Fall River",
    "sg:classifiers":[
        {
            "category":"Health Services",
            "subcategory":"Nursing And Care Facility",
            "type":"Services"
        }
    ],
    "sg:phone":"+1 508 679 0144",
    "sg:postcode":"02720",
    "sg:province":"MA",
    "sg:tags":[
        "home",
        "convalescent"
    ],
    "wof:name":"Home For Aged People",
    "wof:placetype":"venue"
},
  "geometry": {"coordinates":[-71.13929899999999,41.721706],"type":"Point"}
}