{
  "type": "Feature",
  "properties": {
    "addr:full":"142 Albee Rd Uxbridge MA 01569",
    "addr:housenumber":"142",
    "addr:postcode":"01569",
    "addr:street":"Albee Rd",
    "iso:country":"US",
    "sg:address":"142 Albee Rd",
    "sg:city":"Uxbridge",
    "sg:classifiers":[
        {
            "category":"Arts & Performance",
            "subcategory":"Art Gallery",
            "type":"Entertainment"
        }
    ],
    "sg:phone":"+1 508 278 7193",
    "sg:postcode":"01569",
    "sg:province":"MA",
    "sg:tags":[
        "consultant",
        "galleries"
    ],
    "wof:name":"Rainbow Palette",
    "wof:placetype":"venue"
},
  "geometry": {"coordinates":[-71.598839,42.042381],"type":"Point"}
}