{
  "type": "Feature",
  "properties": {
    "iso:country":"US",
    "sg:address":"606 Main St",
    "sg:city":"Hyannis",
    "sg:classifiers":[
        {
            "category":"Shopping",
            "type":"Retail Goods"
        }
    ],
    "sg:phone":"+1 508 775 7035",
    "sg:postcode":"02601",
    "sg:province":"MA",
    "sg:tags":[
        "wedding",
        "supply"
    ],
    "wof:name":"Loving Touches Calligraphy",
    "wof:placetype":"venue"
},
  "geometry": {"coordinates":[-70.290796,41.649296],"type":"Point"}
}