{
  "type": "Feature",
  "properties": {
    "iso:country":"US",
    "sg:address":"31 Central Sq",
    "sg:city":"Lynn",
    "sg:classifiers":[
        {
            "category":"Insurance",
            "subcategory":"Insurance Agent",
            "type":"Services"
        }
    ],
    "sg:phone":"+1 781 598 5000",
    "sg:postcode":"01901",
    "sg:province":"MA",
    "wof:name":"Columbia Insurance Inc",
    "wof:placetype":"venue"
},
  "geometry": {"coordinates":[-70.945081,42.464087],"type":"Point"}
}