{
  "type": "Feature",
  "properties": {
    "addr:full": "68 Cranberry Meadow Rd Spencer MA 01562",
    "addr:housenumber": "68",
    "addr:postcode": "01562",
    "addr:street": "Cranberry Meadow Rd",
    "iso:country": "US",
    "sg:address": "68 Cranberry Meadow Rd",
    "sg:city": "Spencer",
    "sg:classifiers": [
      {
        "category": "Professional",
        "subcategory": "Management \u0026 Consulting",
        "type": "Services"
      }
    ],
    "sg:phone": "+1 774 239 1051",
    "sg:postcode": "01562",
    "sg:province": "MA",
    "sg:tags": [
      "consultant",
      "product"
    ],
    "wof:name": "Piucci Design \u0026 Development",
    "wof:placetype": "venue"
  },
  "geometry": {"coordinates":[-72.003413,42.197979],"type":"Point"}
}
