{
  "type": "Feature",
  "properties": {
    "iso:country":"US",
    "sg:address":"68 Cranberry Meadow Rd",
    "sg:city":"Spencer",
    "sg:classifiers":[
        {
            "category":"Professional",
            "subcategory":"Management & Consulting",
            "type":"Services"
        }
    ],
    "sg:phone":"+1 774 239 1051",
    "sg:postcode":"01562",
    "sg:province":"MA",
    "sg:tags":[
        "consultant",
        "product"
    ],
    "wof:name":"Piucci Design & Development",
    "wof:placetype":"venue"
},
  "geometry": {"coordinates":[-72.00341299999999,42.197979],"type":"Point"}
}