{
  "type": "Feature",
  "properties": {
    "iso:country":"US",
    "sg:address":"515 E Main St",
    "sg:city":"Southbridge",
    "sg:classifiers":[
        {
            "category":"Restaurant",
            "type":"Food & Drink"
        }
    ],
    "sg:menulink":"http://www.allmenus.com/ma/southbridge/188720-mcdonalds/menu/",
    "sg:postcode":"01550",
    "sg:province":"MA",
    "sg:tags":[
        "burger",
        "american"
    ],
    "wof:name":"McDonald's",
    "wof:placetype":"venue"
},
  "geometry": {"coordinates":[-72.01221099999999,42.070287],"type":"Point"}
}