{
  "type": "Feature",
  "properties": {
    "addr:full":"22 Bridge St Dedham MA 02026",
    "addr:housenumber":"22",
    "addr:postcode":"02026",
    "addr:street":"Bridge St",
    "iso:country":"US",
    "sg:address":"22 Bridge St",
    "sg:city":"Dedham",
    "sg:classifiers":[
        {
            "category":"Autos & Motor Vehicles",
            "subcategory":"Fuel & Gas Station",
            "type":"Retail Goods"
        }
    ],
    "sg:phone":"+1 781 326 0789",
    "sg:postcode":"02026",
    "sg:province":"MA",
    "sg:tags":[
        "oil"
    ],
    "wof:name":"Dedham Getty",
    "wof:placetype":"venue"
},
  "geometry": {"coordinates":[-71.17371900000001,42.270377],"type":"Point"}
}