{
  "type": "Feature",
  "properties": {
    "iso:country":"US",
    "sg:address":"38 Main St",
    "sg:city":"Andover",
    "sg:classifiers":[
        {
            "category":"Professional",
            "subcategory":"Management & Consulting",
            "type":"Services"
        }
    ],
    "sg:phone":"+1 978 749 6700",
    "sg:postcode":"01810",
    "sg:province":"MA",
    "sg:tags":[
        "marketing",
        "consultant"
    ],
    "sg:website":"www.meetthepros.com",
    "wof:name":"Celebrity Marketing Inc",
    "wof:placetype":"venue"
},
  "geometry": {"coordinates":[-71.14001500000001,42.655906],"type":"Point"}
}