{
  "type": "Feature",
  "properties": {
    "addr:full": "131 Magazine St Cambridge MA 02139",
    "addr:housenumber": "131",
    "addr:postcode": "02139",
    "addr:street": "Magazine St",
    "iso:country": "US",
    "sg:address": "131 Magazine St",
    "sg:city": "Cambridge",
    "sg:classifiers": [
      {
        "category": "Wholesale",
        "subcategory": "Durable Goods \u0026 Equipment",
        "type": "Manufacturing \u0026 Wholesale Goods"
      }
    ],
    "sg:phone": "+1 617 576 0167",
    "sg:postcode": "02139",
    "sg:province": "MA",
    "sg:tags": [
      "importer"
    ],
    "wof:name": "Avo Imports",
    "wof:placetype": "venue"
  },
  "geometry": {"coordinates":[-71.11182,42.358578],"type":"Point"}
}
