{
  "type": "Feature",
  "properties": {
    "iso:country":"US",
    "sg:address":"131 Magazine St",
    "sg:city":"Cambridge",
    "sg:classifiers":[
        {
            "category":"Wholesale",
            "subcategory":"Durable Goods & Equipment",
            "type":"Manufacturing & Wholesale Goods"
        }
    ],
    "sg:phone":"+1 617 576 0167",
    "sg:postcode":"02139",
    "sg:province":"MA",
    "sg:tags":[
        "importer"
    ],
    "wof:name":"Avo Imports",
    "wof:placetype":"venue"
},
  "geometry": {"coordinates":[-71.11181999999999,42.358578],"type":"Point"}
}