{
  "type": "Feature",
  "properties": {
    "addr:full": "699 Boylston St Boston MA 02116",
    "addr:housenumber": "699",
    "addr:postcode": "02116",
    "addr:street": "Boylston St",
    "iso:country": "US",
    "sg:address": "699 Boylston St",
    "sg:city": "Boston",
    "sg:classifiers": [
      {
        "category": "Professional",
        "subcategory": "Lawyer \u0026 Legal Services",
        "type": "Services"
      }
    ],
    "sg:phone": "+1 617 880 7100",
    "sg:postcode": "02116",
    "sg:province": "MA",
    "wof:name": "Hardoon Laurence E",
    "wof:placetype": "venue"
  },
  "geometry": {"coordinates":[-71.079498,42.349499],"type":"Point"}
}
