{
  "type": "Feature",
  "properties": {
    "iso:country":"US",
    "sg:address":"37 Brattle St",
    "sg:city":"Cambridge",
    "sg:classifiers":[
        {
            "category":"Professional",
            "type":"Services"
        }
    ],
    "sg:phone":"+1 617 547 3173",
    "sg:postcode":"02138",
    "sg:province":"MA",
    "sg:tags":[
        "establishment"
    ],
    "sg:website":"www.jasminesola.com",
    "wof:name":"Jasmine Co Inc",
    "wof:placetype":"venue"
},
  "geometry": {"coordinates":[-71.12111299999999,42.373613],"type":"Point"}
}