{
  "type": "Feature",
  "properties": {
    "addr:full":"735 American Legion Hwy Roslindale MA 02131",
    "addr:housenumber":"735",
    "addr:postcode":"02131",
    "addr:street":"American Legion Hwy",
    "iso:country":"US",
    "sg:address":"735 American Legion Hwy",
    "sg:city":"Roslindale",
    "sg:classifiers":[
        {
            "category":"Building & Trades",
            "subcategory":"Locksmith",
            "type":"Services"
        }
    ],
    "sg:phone":"+1 617 390 9015",
    "sg:postcode":"02131",
    "sg:province":"MA",
    "sg:tags":[
        "key"
    ],
    "wof:name":"Locksmith 24 Hour Emergency",
    "wof:placetype":"venue"
},
  "geometry": {"coordinates":[-71.114676,42.282835],"type":"Point"}
}