{
  "type": "Feature",
  "properties": {
    "addr:full":"175 Paramount Dr Raynham MA 02767",
    "addr:housenumber":"175",
    "addr:postcode":"02767",
    "addr:street":"Paramount Dr",
    "iso:country":"US",
    "sg:address":"175 Paramount Dr",
    "sg:city":"Raynham",
    "sg:classifiers":[
        {
            "category":"Professional",
            "subcategory":"Research",
            "type":"Services"
        }
    ],
    "sg:phone":"+1 508 880 2446",
    "sg:postcode":"02767",
    "sg:province":"MA",
    "sg:tags":[
        "environmental",
        "ecological"
    ],
    "wof:name":"National Environmental",
    "wof:placetype":"venue"
},
  "geometry": {"coordinates":[-71.033705,41.901963],"type":"Point"}
}