{
  "type": "Feature",
  "properties": {
    "addr:full":"25 Mount Auburn St Cambridge MA 02138",
    "addr:housenumber":"25",
    "addr:postcode":"02138",
    "addr:street":"Mount Auburn St",
    "iso:country":"US",
    "sg:address":"25 Mount Auburn St",
    "sg:city":"Cambridge",
    "sg:classifiers":[
        {
            "category":"Organizations",
            "subcategory":"Non-profit Organization",
            "type":"Services"
        }
    ],
    "sg:phone":"+1 617 495 5255",
    "sg:postcode":"02138",
    "sg:province":"MA",
    "wof:name":"Laspau",
    "wof:placetype":"venue"
},
  "geometry": {"coordinates":[-71.114482,42.370495],"type":"Point"}
}