{
  "type": "Feature",
  "properties": {
    "addr:full": "224 Washington Street Brookline MA 02445",
    "addr:housenumber": "224",
    "addr:postcode": "02445",
    "addr:street": "Washington Street",
    "iso:country": "US",
    "ovtr:label": "E C Florist \u0026 Gifts, 224 Washington St Brookline MA US",
    "ovtr:similarity": 3.935724973678589,
    "sg:address": "224 Washington Street",
    "sg:city": "Brookline",
    "sg:classifiers": [
      {
        "category": "Shopping",
        "subcategory": "Florist",
        "type": "Retail Goods"
      }
    ],
    "sg:phone": "+1 617 232 3693",
    "sg:postcode": "02445",
    "sg:province": "MA",
    "wof:name": "E C Florist",
    "wof:placetype": "venue"
  },
  "geometry": {"coordinates":[-71.11845,42.332601],"type":"Point"}
}
