{
  "type": "Feature",
  "properties": {
    "iso:country":"US",
    "sg:address":"95 Rockdale Ave",
    "sg:city":"New Bedford",
    "sg:classifiers":[
        {
            "category":"Home & Garden",
            "subcategory":"Home Furnishings",
            "type":"Retail Goods"
        }
    ],
    "sg:phone":"+1   ",
    "sg:postcode":"02740",
    "sg:province":"MA",
    "sg:tags":[
        "household"
    ],
    "wof:name":"M & G Imports",
    "wof:placetype":"venue"
},
  "geometry": {"coordinates":[-70.934832,41.614213],"type":"Point"}
}