{
  "type": "Feature",
  "properties": {
    "iso:country":"US",
    "sg:address":"445 Concord Ave",
    "sg:city":"Cambridge",
    "sg:classifiers":[
        {
            "category":"Freight",
            "type":"Transportation"
        }
    ],
    "sg:phone":"+1 617 661 2958",
    "sg:postcode":"02138",
    "sg:province":"MA",
    "sg:tags":[
        "mover"
    ],
    "wof:name":"Julian Wright & Moving Inc",
    "wof:placetype":"venue"
},
  "geometry": {"coordinates":[-71.13887,42.385962],"type":"Point"}
}