{
  "type": "Feature",
  "properties": {
    "iso:country":"US",
    "sg:address":"359 Main St",
    "sg:city":"Harwich",
    "sg:classifiers":[
        {
            "category":"Food & Beverages",
            "subcategory":"Farmers Market",
            "type":"Retail Goods"
        }
    ],
    "sg:phone":"+1 508 432 2931",
    "sg:postcode":"02645",
    "sg:province":"MA",
    "sg:tags":[
        "vegetable",
        "fruit",
        "shipper",
        "grower"
    ],
    "wof:name":"Raymond L & Beverly R Thacher",
    "wof:placetype":"venue"
},
  "geometry": {"coordinates":[-70.101761,41.689128],"type":"Point"}
}