{
  "type": "Feature",
  "properties": {
    "addr:full": "249 Washington St Leominster MA 01453",
    "addr:housenumber": "249",
    "addr:postcode": "01453",
    "addr:street": "Washington St",
    "iso:country": "US",
    "sg:address": "249 Washington St",
    "sg:city": "Leominster",
    "sg:classifiers": [
      {
        "category": "Building \u0026 Trades",
        "subcategory": "Construction",
        "type": "Services"
      }
    ],
    "sg:phone": "+1 978 537 2033",
    "sg:postcode": "01453",
    "sg:province": "MA",
    "sg:tags": [
      "home",
      "improvement"
    ],
    "wof:name": "Gregory's Carpentry",
    "wof:placetype": "venue"
  },
  "geometry": {"coordinates":[-71.760072,42.539262],"type":"Point"}
}
