{
  "type": "Feature",
  "properties": {
    "iso:country":"US",
    "sg:address":"249 Washington St",
    "sg:city":"Leominster",
    "sg:classifiers":[
        {
            "category":"Building & Trades",
            "subcategory":"Construction",
            "type":"Services"
        }
    ],
    "sg:phone":"+1 978 537 2033",
    "sg:postcode":"01453",
    "sg:province":"MA",
    "sg:tags":[
        "home",
        "improvement"
    ],
    "wof:name":"Gregory's Carpentry",
    "wof:placetype":"venue"
},
  "geometry": {"coordinates":[-71.76007199999999,42.539262],"type":"Point"}
}