{
  "type": "Feature",
  "properties": {
    "iso:country":"US",
    "sg:address":"24 Terrane Ave",
    "sg:city":"Natick",
    "sg:classifiers":[
        {
            "category":"Shopping",
            "subcategory":"Computers & Home Electronics",
            "type":"Retail Goods"
        }
    ],
    "sg:phone":"+1 508 647 4999",
    "sg:postcode":"01760",
    "sg:province":"MA",
    "sg:tags":[
        "software"
    ],
    "wof:name":"Norman R Mancuso Assoc",
    "wof:placetype":"venue"
},
  "geometry": {"coordinates":[-71.352924,42.306135],"type":"Point"}
}