{
  "type": "Feature",
  "properties": {
    "addr:full": "24 Terrane Ave Natick MA 01760",
    "addr:housenumber": "24",
    "addr:postcode": "01760",
    "addr:street": "Terrane Ave",
    "iso:country": "US",
    "sg:address": "24 Terrane Ave",
    "sg:city": "Natick",
    "sg:classifiers": [
      {
        "category": "Shopping",
        "subcategory": "Computers \u0026 Home Electronics",
        "type": "Retail Goods"
      }
    ],
    "sg:phone": "+1 508 647 4999",
    "sg:postcode": "01760",
    "sg:province": "MA",
    "sg:tags": [
      "software"
    ],
    "wof:name": "Norman R Mancuso Assoc",
    "wof:placetype": "venue"
  },
  "geometry": {"coordinates":[-71.352924,42.306135],"type":"Point"}
}
