{
  "type": "Feature",
  "properties": {
    "iso:country":"US",
    "sg:address":"24 Summer Hill Rd",
    "sg:city":"Medway",
    "sg:classifiers":[
        {
            "category":"Building & Trades",
            "subcategory":"Landscaping Services",
            "type":"Services"
        }
    ],
    "sg:phone":"+1   ",
    "sg:postcode":"02053",
    "sg:province":"MA",
    "sg:tags":[
        "tree",
        "care"
    ],
    "wof:name":"Wind River Tree Care",
    "wof:placetype":"venue"
},
  "geometry": {"coordinates":[-71.45477,42.15987],"type":"Point"}
}