{
  "type": "Feature",
  "properties": {
    "addr:full":"950 Massachusetts Ave Cambridge MA 02139",
    "addr:housenumber":"950",
    "addr:postcode":"02139",
    "addr:street":"Massachusetts Ave",
    "iso:country":"US",
    "sg:address":"950 Massachusetts Ave",
    "sg:city":"Cambridge",
    "sg:classifiers":[
        {
            "category":"Real Estate",
            "subcategory":"Real Estate Operator",
            "type":"Services"
        }
    ],
    "sg:phone":"+1 617 547 7722",
    "sg:postcode":"02139",
    "sg:province":"MA",
    "sg:tags":[
        "condominium"
    ],
    "wof:name":"Bay Square Condominium Lobby",
    "wof:placetype":"venue"
},
  "geometry": {"coordinates":[-71.11002999999999,42.368796],"type":"Point"}
}