{
  "type": "Feature",
  "properties": {
    "addr:full": "129 S Main St Cohasset MA 02025",
    "addr:housenumber": "129",
    "addr:postcode": "02025",
    "addr:street": "S Main St",
    "iso:country": "US",
    "sg:address": "129 S Main St",
    "sg:city": "Cohasset",
    "sg:classifiers": [
      {
        "category": "Organizations",
        "subcategory": "Religious Organization",
        "type": "Services"
      }
    ],
    "sg:phone": "+1 781 383 0219",
    "sg:postcode": "02025",
    "sg:province": "MA",
    "sg:tags": [
      "church"
    ],
    "wof:name": "St Anthony Catholic Church",
    "wof:placetype": "venue"
  },
  "geometry": {"coordinates":[-70.799324,42.237584],"type":"Point"}
}
