{
  "type": "Feature",
  "properties": {
    "addr:full": "385 Main St Woburn MA 01801",
    "addr:housenumber": "385",
    "addr:postcode": "01801",
    "addr:street": "Main St",
    "iso:country": "US",
    "sg:address": "385 Main St",
    "sg:city": "Woburn",
    "sg:classifiers": [
      {
        "category": "Coffee \u0026 Tea",
        "type": "Food \u0026 Drink"
      },
      {
        "category": "Restaurant",
        "type": "Food \u0026 Drink"
      }
    ],
    "sg:phone": "+1 781 721 4545",
    "sg:postcode": "01801",
    "sg:province": "MA",
    "sg:tags": [
      "espresso"
    ],
    "wof:name": "Woburn Cafe",
    "wof:placetype": "venue"
  },
  "geometry": {"coordinates":[-71.151868,42.479875],"type":"Point"}
}
