{
  "type": "Feature",
  "properties": {
    "iso:country":"US",
    "sg:address":"385 Main St",
    "sg:city":"Woburn",
    "sg:classifiers":[
        {
            "category":"Coffee & Tea",
            "type":"Food & Drink"
        },
        {
            "category":"Restaurant",
            "type":"Food & Drink"
        }
    ],
    "sg:phone":"+1 781 721 4545",
    "sg:postcode":"01801",
    "sg:province":"MA",
    "sg:tags":[
        "espresso"
    ],
    "wof:name":"Woburn Cafe",
    "wof:placetype":"venue"
},
  "geometry": {"coordinates":[-71.15186799999999,42.479875],"type":"Point"}
}