{
  "type": "Feature",
  "properties": {
    "iso:country":"US",
    "sg:address":"750 Washington Street",
    "sg:city":"Boston",
    "sg:classifiers":[
        {
            "category":"Health Services",
            "subcategory":"Doctor",
            "type":"Services"
        },
        {
            "category":"Health Services",
            "subcategory":"Hospital",
            "type":"Services"
        },
        {
            "category":"Sports & Exercise",
            "subcategory":"Gym",
            "type":"Entertainment"
        }
    ],
    "sg:phone":"+1 617 636 7242",
    "sg:postcode":"02111",
    "sg:province":"MA",
    "sg:tags":[
        "trainer"
    ],
    "wof:name":"Center For Children With Special Needs",
    "wof:placetype":"venue"
},
  "geometry": {"coordinates":[-71.06331,42.350296],"type":"Point"}
}