{
  "type": "Feature",
  "properties": {
    "addr:full": "750 Washington Street Boston MA 02111",
    "addr:housenumber": "750",
    "addr:postcode": "02111",
    "addr:street": "Washington Street",
    "iso:country": "US",
    "ovtr:label": "Center for Children with Special Needs, 755 Washington St Boston MA US",
    "ovtr:similarity": 3.3242599964141846,
    "sg:address": "750 Washington Street",
    "sg:city": "Boston",
    "sg:classifiers": [
      {
        "category": "Health Services",
        "subcategory": "Doctor",
        "type": "Services"
      },
      {
        "category": "Health Services",
        "subcategory": "Hospital",
        "type": "Services"
      },
      {
        "category": "Sports \u0026 Exercise",
        "subcategory": "Gym",
        "type": "Entertainment"
      }
    ],
    "sg:phone": "+1 617 636 7242",
    "sg:postcode": "02111",
    "sg:province": "MA",
    "sg:tags": [
      "trainer"
    ],
    "wof:name": "Center For Children With Special Needs",
    "wof:placetype": "venue"
  },
  "geometry": {"coordinates":[-71.06331,42.350296],"type":"Point"}
}
