{
  "type": "Feature",
  "properties": {
    "iso:country":"US",
    "sg:address":"284 Union Ave",
    "sg:city":"Framingham",
    "sg:classifiers":[
        {
            "category":"Professional",
            "subcategory":"Lawyer & Legal Services",
            "type":"Services"
        }
    ],
    "sg:phone":"+1 508 370 7600",
    "sg:postcode":"01702",
    "sg:province":"MA",
    "sg:tags":[
        "attorney"
    ],
    "wof:name":"Freeley & Freeley",
    "wof:placetype":"venue"
},
  "geometry": {"coordinates":[-71.422391,42.285947],"type":"Point"}
}