{
  "type": "Feature",
  "properties": {
    "addr:full": "17 Humphrey St Great Barrington MA 01230",
    "addr:housenumber": "17",
    "addr:postcode": "01230",
    "addr:street": "Humphrey St",
    "iso:country": "US",
    "sg:address": "17 Humphrey St",
    "sg:city": "Great Barrington",
    "sg:classifiers": [
      {
        "category": "Building \u0026 Trades",
        "subcategory": "Equipment Rental",
        "type": "Services"
      }
    ],
    "sg:phone": "+1 413 528 5945",
    "sg:postcode": "01230",
    "sg:province": "MA",
    "sg:tags": [
      "yard"
    ],
    "sg:website": "www.mahaiwetent.com",
    "wof:name": "Mahaiwe Tent Inc",
    "wof:placetype": "venue"
  },
  "geometry": {"coordinates":[-73.356744,42.193619],"type":"Point"}
}
