{
  "type": "Feature",
  "properties": {
    "addr:full":"1699 Shawsheen St Tewksbury MA 01876",
    "addr:housenumber":"1699",
    "addr:postcode":"01876",
    "addr:street":"Shawsheen St",
    "iso:country":"US",
    "sg:address":"1699 Shawsheen St",
    "sg:city":"Tewksbury",
    "sg:classifiers":[
        {
            "category":"Food & Beverages",
            "subcategory":"Groceries & Convenience Stores",
            "type":"Retail Goods"
        }
    ],
    "sg:phone":"+1 978 851 8986",
    "sg:postcode":"01876",
    "sg:province":"MA",
    "wof:name":"White Hen Pantry Inc",
    "wof:placetype":"venue"
},
  "geometry": {"coordinates":[-71.18394000000001,42.620696],"type":"Point"}
}