{
  "type": "Feature",
  "properties": {
    "addr:full":"156 Chamberlain St Holliston MA 01746",
    "addr:housenumber":"156",
    "addr:postcode":"01746",
    "addr:street":"Chamberlain St",
    "iso:country":"US",
    "sg:address":"156 Chamberlain St",
    "sg:city":"Holliston",
    "sg:classifiers":[
        {
            "category":"Shopping",
            "subcategory":"Books",
            "type":"Retail Goods"
        }
    ],
    "sg:phone":"+1 508 429 6121",
    "sg:postcode":"01746",
    "sg:province":"MA",
    "sg:tags":[
        "comic"
    ],
    "wof:name":"Paper Heroes Inc",
    "wof:placetype":"venue"
},
  "geometry": {"coordinates":[-71.46355,42.196482],"type":"Point"}
}