{
  "type": "Feature",
  "properties": {
    "addr:full": "1055 Main St Springfield MA 01103",
    "addr:housenumber": "1055",
    "addr:postcode": "01103",
    "addr:street": "Main St",
    "iso:country": "US",
    "sg:address": "1055 Main St",
    "sg:city": "Springfield",
    "sg:classifiers": [
      {
        "category": "Home \u0026 Garden",
        "subcategory": "Furniture",
        "type": "Retail Goods"
      }
    ],
    "sg:phone": "+1 413 732 2945",
    "sg:postcode": "01103",
    "sg:province": "MA",
    "wof:name": "Hampden Furniture Showcase",
    "wof:placetype": "venue"
  },
  "geometry": {"coordinates":[-72.584962,42.099602],"type":"Point"}
}
