{
  "type": "Feature",
  "properties": {
    "iso:country":"US",
    "sg:address":"31 East St",
    "sg:city":"Plainfield",
    "sg:classifiers":[
        {
            "category":"Manufacturing",
            "subcategory":"Pottery",
            "type":"Manufacturing & Wholesale Goods"
        }
    ],
    "sg:phone":"+1 413 634 8844",
    "sg:postcode":"01070",
    "sg:province":"MA",
    "sg:tags":[
        "pottery-wholesale",
        "manufacturer"
    ],
    "wof:name":"Andrassche Handbuilt Stoneware",
    "wof:placetype":"venue"
},
  "geometry": {"coordinates":[-72.88590600000001,42.513821],"type":"Point"}
}