{
  "type": "Feature",
  "properties": {
    "addr:full":"142 Old Colony Ave Boston MA 02127",
    "addr:housenumber":"142",
    "addr:postcode":"02127",
    "addr:street":"Old Colony Ave",
    "iso:country":"US",
    "sg:address":"142 Old Colony Ave",
    "sg:city":"Boston",
    "sg:classifiers":[
        {
            "category":"Building & Trades",
            "subcategory":"Cleaning & Sanitation",
            "type":"Services"
        }
    ],
    "sg:phone":"+1 617 268 6993",
    "sg:postcode":"02127",
    "sg:province":"MA",
    "sg:tags":[
        "window"
    ],
    "wof:name":"Sunshine Windows Company Inc",
    "wof:placetype":"venue"
},
  "geometry": {"coordinates":[-71.055151,42.334949],"type":"Point"}
}