{
  "type": "Feature",
  "properties": {
    "iso:country":"US",
    "sg:address":"66 Wolcott Rd",
    "sg:city":"Southampton",
    "sg:classifiers":[
        {
            "category":"Farming",
            "subcategory":"Farm",
            "type":"Manufacturing & Wholesale Goods"
        }
    ],
    "sg:phone":"+1 413 527 4310",
    "sg:postcode":"01073",
    "sg:province":"MA",
    "wof:name":"Maple Hollow Farm",
    "wof:placetype":"venue"
},
  "geometry": {"coordinates":[-72.73762600000001,42.246546],"type":"Point"}
}