{
  "type": "Feature",
  "properties": {
    "addr:full": "9 Bennett St Manchester MA 01944",
    "addr:housenumber": "9",
    "addr:postcode": "01944",
    "addr:street": "Bennett St",
    "iso:country": "US",
    "sg:address": "9 Bennett St",
    "sg:city": "Manchester",
    "sg:classifiers": [
      {
        "category": "Real Estate",
        "subcategory": "Real Estate Services",
        "type": "Services"
      },
      {
        "category": "Real Estate",
        "subcategory": "Real Estate Agent",
        "type": "Services"
      }
    ],
    "sg:phone": "+1 617 365 9473",
    "sg:postcode": "01944",
    "sg:province": "MA",
    "sg:tags": [
      "buyer",
      "broker"
    ],
    "wof:name": "Beacon Real Estate Advisors",
    "wof:placetype": "venue"
  },
  "geometry": {"coordinates":[-70.775441,42.57414],"type":"Point"}
}
