{
  "type": "Feature",
  "properties": {
    "addr:full": "152 East St Petersham MA 01366",
    "addr:housenumber": "152",
    "addr:postcode": "01366",
    "addr:street": "East St",
    "iso:country": "US",
    "sg:address": "152 East St",
    "sg:city": "Petersham",
    "sg:classifiers": [
      {
        "category": "Freight",
        "type": "Transportation"
      }
    ],
    "sg:phone": "+1 978 249 0303",
    "sg:postcode": "01366",
    "sg:province": "MA",
    "sg:tags": [
      "broker",
      "agent"
    ],
    "wof:name": "Kenneth Miller Assoc Inc",
    "wof:placetype": "venue"
  },
  "geometry": {"coordinates":[-72.159988,42.490139],"type":"Point"}
}
