{
  "type": "Feature",
  "properties": {
    "iso:country":"US",
    "sg:address":"20 G And S Dr",
    "sg:city":"Dudley",
    "sg:classifiers":[
        {
            "category":"Wholesale",
            "subcategory":"Medical Equipment & Supplies",
            "type":"Manufacturing & Wholesale Goods"
        }
    ],
    "sg:phone":"+1 508 949 0492",
    "sg:postcode":"01571",
    "sg:province":"MA",
    "sg:tags":[
        "instrument",
        "surgical"
    ],
    "wof:name":"Nicolay",
    "wof:placetype":"venue"
},
  "geometry": {"coordinates":[-71.920486,42.062939],"type":"Point"}
}