{
  "type": "Feature",
  "properties": {
    "addr:full":"43 Snow St Brighton MA 02135",
    "addr:housenumber":"43",
    "addr:postcode":"02135",
    "addr:street":"Snow St",
    "iso:country":"US",
    "sg:address":"43 Snow St",
    "sg:city":"Brighton",
    "sg:classifiers":[
        {
            "category":"Arts & Performance",
            "subcategory":"Theater",
            "type":"Entertainment"
        }
    ],
    "sg:phone":"+1   ",
    "sg:postcode":"02135",
    "sg:province":"MA",
    "sg:tags":[
        "group"
    ],
    "wof:name":"Kilombo Mambo",
    "wof:placetype":"venue"
},
  "geometry": {"coordinates":[-71.149103,42.346099],"type":"Point"}
}