{
  "type": "Feature",
  "properties": {
    "iso:country":"US",
    "sg:address":"130 Spring St",
    "sg:city":"Hull",
    "sg:classifiers":[
        {
            "category":"Organizations",
            "subcategory":"Religious Organization",
            "type":"Services"
        }
    ],
    "sg:phone":"+1 781 925 9101",
    "sg:postcode":"02045",
    "sg:province":"MA",
    "sg:tags":[
        "church"
    ],
    "wof:name":"Hull United Methodist Church",
    "wof:placetype":"venue"
},
  "geometry": {"coordinates":[-70.906648,42.303171],"type":"Point"}
}