{
  "type": "Feature",
  "properties": {
    "iso:country":"US",
    "sg:address":"401 N Hemlock Ln",
    "sg:city":"Williamstown",
    "sg:classifiers":[
        {
            "category":"Professional",
            "subcategory":"Management & Consulting",
            "type":"Services"
        }
    ],
    "sg:phone":"+1   ",
    "sg:postcode":"01267",
    "sg:province":"MA",
    "sg:tags":[
        "business"
    ],
    "wof:name":"Legend Interests Inc",
    "wof:placetype":"venue"
},
  "geometry": {"coordinates":[-73.206406,42.726708],"type":"Point"}
}