{
  "type": "Feature",
  "properties": {
    "iso:country":"US",
    "sg:address":"4 Fairhaven Rd",
    "sg:city":"Mattapoisett",
    "sg:phone":"+1 508 758 4338",
    "sg:postcode":"02739",
    "sg:province":"MA",
    "sg:tags":[
        "gas"
    ],
    "wof:name":"Sea Gas",
    "wof:placetype":"venue"
},
  "geometry": {"coordinates":[-70.82028200000001,41.661584],"type":"Point"}
}