{
  "type": "Feature",
  "properties": {
    "addr:full":"30 Lakeshore Dr Wayland MA 01778",
    "addr:housenumber":"30",
    "addr:postcode":"01778",
    "addr:street":"Lakeshore Dr",
    "iso:country":"US",
    "sg:address":"30 Lakeshore Dr",
    "sg:city":"Wayland",
    "sg:classifiers":[
        {
            "category":"Building & Trades",
            "subcategory":"Landscaping Services",
            "type":"Services"
        }
    ],
    "sg:phone":"+1   ",
    "sg:postcode":"01778",
    "sg:province":"MA",
    "wof:name":"Hanlon Lawn and Landscaping",
    "wof:placetype":"venue"
},
  "geometry": {"coordinates":[-71.370717,42.333414],"type":"Point"}
}