{
  "type": "Feature",
  "properties": {
    "addr:full": "260 Franklin St Boston MA 02110",
    "addr:housenumber": "260",
    "addr:postcode": "02110",
    "addr:street": "Franklin St",
    "iso:country": "US",
    "sg:address": "260 Franklin St",
    "sg:city": "Boston",
    "sg:classifiers": [
      {
        "category": "Professional",
        "subcategory": "Lawyer \u0026 Legal Services",
        "type": "Services"
      }
    ],
    "sg:phone": "+1 617 737 9045",
    "sg:postcode": "02110",
    "sg:province": "MA",
    "sg:tags": [
      "environment",
      "resource",
      "attorney",
      "law",
      "natural"
    ],
    "sg:website": "www.governo.com",
    "wof:name": "Governo Law Firm",
    "wof:placetype": "venue"
  },
  "geometry": {"coordinates":[-71.053879,42.35659],"type":"Point"}
}
