{
  "type": "Feature",
  "properties": {
    "iso:country":"US",
    "sg:address":"260 Franklin St",
    "sg:city":"Boston",
    "sg:classifiers":[
        {
            "category":"Professional",
            "subcategory":"Lawyer & Legal Services",
            "type":"Services"
        }
    ],
    "sg:phone":"+1 617 737 9045",
    "sg:postcode":"02110",
    "sg:province":"MA",
    "sg:tags":[
        "environment",
        "resource",
        "attorney",
        "law",
        "natural"
    ],
    "sg:website":"www.governo.com",
    "wof:name":"Governo Law Firm",
    "wof:placetype":"venue"
},
  "geometry": {"coordinates":[-71.05387899999999,42.35659],"type":"Point"}
}