{
  "type": "Feature",
  "properties": {
    "addr:full":"179 Great Rd Acton MA 01720",
    "addr:housenumber":"179",
    "addr:postcode":"01720",
    "addr:street":"Great Rd",
    "iso:country":"US",
    "sg:address":"179 Great Rd",
    "sg:city":"Acton",
    "sg:classifiers":[
        {
            "category":"Education",
            "subcategory":"Special Training",
            "type":"Public Place"
        }
    ],
    "sg:phone":"+1 978 263 3187",
    "sg:postcode":"01720",
    "sg:province":"MA",
    "sg:tags":[
        "tutoring"
    ],
    "sg:website":"tutoring.sylvanlearning.com",
    "wof:name":"Sylvan Learning Center",
    "wof:placetype":"venue"
},
  "geometry": {"coordinates":[-71.41680100000001,42.487],"type":"Point"}
}