{
  "type": "Feature",
  "properties": {
    "iso:country":"US",
    "sg:address":"113 Clay St",
    "sg:city":"Cambridge",
    "sg:classifiers":[
        {
            "category":"Professional",
            "subcategory":"Business Services",
            "type":"Services"
        }
    ],
    "sg:phone":"+1   ",
    "sg:postcode":"02140",
    "sg:province":"MA",
    "wof:name":"Solo & Associates Inc",
    "wof:placetype":"venue"
},
  "geometry": {"coordinates":[-71.13420499999999,42.397374],"type":"Point"}
}