{
  "type": "Feature",
  "properties": {
    "iso:country":"US",
    "sg:address":"224 Littleton Rd",
    "sg:city":"Westford",
    "sg:classifiers":[
        {
            "category":"Professional",
            "type":"Services"
        },
        {
            "category":"Deli",
            "type":"Food & Drink"
        }
    ],
    "sg:phone":"+1 978 692 1819",
    "sg:postcode":"01886",
    "sg:province":"MA",
    "sg:tags":[
        "caterer"
    ],
    "sg:website":"www.metrodeliandcatering.com",
    "wof:name":"Metropolitan Deli & Catering Co Inc",
    "wof:placetype":"venue"
},
  "geometry": {"coordinates":[-71.430488,42.561716],"type":"Point"}
}