{
  "type": "Feature",
  "properties": {
    "addr:full": "224 Littleton Rd Westford MA 01886",
    "addr:housenumber": "224",
    "addr:postcode": "01886",
    "addr:street": "Littleton Rd",
    "iso:country": "US",
    "sg:address": "224 Littleton Rd",
    "sg:city": "Westford",
    "sg:classifiers": [
      {
        "category": "Professional",
        "type": "Services"
      },
      {
        "category": "Deli",
        "type": "Food \u0026 Drink"
      }
    ],
    "sg:phone": "+1 978 692 1819",
    "sg:postcode": "01886",
    "sg:province": "MA",
    "sg:tags": [
      "caterer"
    ],
    "sg:website": "www.metrodeliandcatering.com",
    "wof:name": "Metropolitan Deli \u0026 Catering Co Inc",
    "wof:placetype": "venue"
  },
  "geometry": {"coordinates":[-71.430488,42.561716],"type":"Point"}
}
