{
  "type": "Feature",
  "properties": {
    "addr:full":"161 Ferry Rd Haverhill MA 01835",
    "addr:housenumber":"161",
    "addr:postcode":"01835",
    "addr:street":"Ferry Rd",
    "iso:country":"US",
    "sg:address":"161 Ferry Rd",
    "sg:city":"Haverhill",
    "sg:classifiers":[
        {
            "category":"Utilities",
            "subcategory":"Refuse",
            "type":"Services"
        }
    ],
    "sg:phone":"+1 978 521 3388",
    "sg:postcode":"01835",
    "sg:province":"MA",
    "sg:tags":[
        "disposal",
        "waste"
    ],
    "wof:name":"Biosystems",
    "wof:placetype":"venue"
},
  "geometry": {"coordinates":[-71.10932,42.751442],"type":"Point"}
}