{
  "type": "Feature",
  "properties": {
    "addr:full": "36 Gloucester St Boston MA 02115",
    "addr:housenumber": "36",
    "addr:postcode": "02115",
    "addr:street": "Gloucester St",
    "iso:country": "US",
    "ovtr:label": "Rainbow Health Center, 36 Gloucester St Boston MA US",
    "ovtr:similarity": 2.4991579055786133,
    "sg:address": "36 Gloucester St",
    "sg:city": "Boston",
    "sg:classifiers": [
      {
        "category": "Personal",
        "subcategory": "Massage",
        "type": "Services"
      },
      {
        "category": "Health Services",
        "subcategory": "Clinic",
        "type": "Services"
      }
    ],
    "sg:phone": "+1 617 859 5858",
    "sg:postcode": "02115",
    "sg:province": "MA",
    "sg:tags": [
      "welfare"
    ],
    "sg:website": "www.backbayrainbow.com",
    "wof:name": "Rainbow Health Center",
    "wof:placetype": "venue"
  },
  "geometry": {"coordinates":[-71.084343,42.3492],"type":"Point"}
}
