{
  "type": "Feature",
  "properties": {
    "iso:country":"US",
    "sg:address":"36 Gloucester St",
    "sg:city":"Boston",
    "sg:classifiers":[
        {
            "category":"Personal",
            "subcategory":"Massage",
            "type":"Services"
        },
        {
            "category":"Health Services",
            "subcategory":"Clinic",
            "type":"Services"
        }
    ],
    "sg:phone":"+1 617 859 5858",
    "sg:postcode":"02115",
    "sg:province":"MA",
    "sg:tags":[
        "welfare"
    ],
    "sg:website":"www.backbayrainbow.com",
    "wof:name":"Rainbow Health Center",
    "wof:placetype":"venue"
},
  "geometry": {"coordinates":[-71.084343,42.3492],"type":"Point"}
}