{
  "type": "Feature",
  "properties": {
    "addr:full": "24 Norfolk Ave South Easton MA 02375",
    "addr:housenumber": "24",
    "addr:postcode": "02375",
    "addr:street": "Norfolk Ave",
    "iso:country": "US",
    "sg:address": "24 Norfolk Ave",
    "sg:city": "South Easton",
    "sg:classifiers": [
      {
        "category": "Manufacturing",
        "subcategory": "Retail Goods",
        "type": "Manufacturing \u0026 Wholesale Goods"
      }
    ],
    "sg:phone": "+1 508 238 7982",
    "sg:postcode": "02375",
    "sg:province": "MA",
    "sg:tags": [
      "manufacturer"
    ],
    "wof:name": "Brighton-Best Socket Screw Mfg",
    "wof:placetype": "venue"
  },
  "geometry": {"coordinates":[-71.077162,42.049205],"type":"Point"}
}
