{
  "type": "Feature",
  "properties": {
    "addr:full":"47 Pine Grove St Fairhaven MA 02719",
    "addr:housenumber":"47",
    "addr:postcode":"02719",
    "addr:street":"Pine Grove St",
    "iso:country":"US",
    "sg:address":"47 Pine Grove St",
    "sg:city":"Fairhaven",
    "sg:classifiers":[
        {
            "category":"Building & Trades",
            "subcategory":"Plumbing",
            "type":"Services"
        }
    ],
    "sg:phone":"+1 508 993 4197",
    "sg:postcode":"02719",
    "sg:province":"MA",
    "sg:tags":[
        "septic"
    ],
    "wof:name":"Dennis Borges Septic Tank Svc",
    "wof:placetype":"venue"
},
  "geometry": {"coordinates":[-70.850008,41.655773],"type":"Point"}
}