{
  "type": "Feature",
  "properties": {
    "iso:country":"US",
    "sg:address":"491 Maple St",
    "sg:city":"Danvers",
    "sg:classifiers":[
        {
            "category":"Health Services",
            "subcategory":"Health Practitioner",
            "type":"Services"
        }
    ],
    "sg:phone":"+1 978 739 4500",
    "sg:postcode":"01923",
    "sg:province":"MA",
    "sg:tags":[
        "nurse",
        "registry"
    ],
    "wof:name":"Medtech",
    "wof:placetype":"venue"
},
  "geometry": {"coordinates":[-70.97230999999999,42.586977],"type":"Point"}
}