{
  "type": "Feature",
  "properties": {
    "addr:full": "12 Farnsworth St Boston MA 02210",
    "addr:housenumber": "12",
    "addr:postcode": "02210",
    "addr:street": "Farnsworth St",
    "iso:country": "US",
    "sg:address": "12 Farnsworth St",
    "sg:city": "Boston",
    "sg:classifiers": [
      {
        "category": "Communications",
        "subcategory": "Film \u0026 Video Production",
        "type": "Services"
      }
    ],
    "sg:phone": "+1 617 422 0003",
    "sg:postcode": "02210",
    "sg:province": "MA",
    "sg:tags": [
      "signs-erectors",
      "hanger",
      "taping"
    ],
    "wof:name": "Allen Roche Group",
    "wof:placetype": "venue"
  },
  "geometry": {"coordinates":[-71.048919,42.350902],"type":"Point"}
}
