{
  "type": "Feature",
  "properties": {
    "addr:full": "19 High Street Medford MA 02155",
    "addr:housenumber": "19",
    "addr:postcode": "02155",
    "addr:street": "High Street",
    "iso:country": "US",
    "sg:address": "19 High Street",
    "sg:city": "Medford",
    "sg:classifiers": [
      {
        "category": "Banks \u0026 Credit Unions",
        "subcategory": "Financial Services",
        "type": "Services"
      }
    ],
    "sg:phone": "+1 781 391 0145",
    "sg:postcode": "02155",
    "sg:province": "MA",
    "sg:tags": [
      "broker",
      "mortgage"
    ],
    "sg:website": "financial.wellsfargo.com",
    "wof:name": "Wells Fargo Financial",
    "wof:placetype": "venue"
  },
  "geometry": {"coordinates":[-71.110005,42.418191],"type":"Point"}
}
