{
  "type": "Feature",
  "properties": {
    "iso:country":"US",
    "sg:address":"22 Amherst Rd",
    "sg:city":"Pelham",
    "sg:classifiers":[
        {
            "category":"Manufacturing",
            "subcategory":"Printing",
            "type":"Manufacturing & Wholesale Goods"
        }
    ],
    "sg:phone":"+1 413 362 3502",
    "sg:postcode":"01002",
    "sg:province":"MA",
    "sg:tags":[
        "periodical"
    ],
    "wof:name":"Human Development Press Inc",
    "wof:placetype":"venue"
},
  "geometry": {"coordinates":[-72.47407,42.378227],"type":"Point"}
}