{
  "type": "Feature",
  "properties": {
    "addr:full": "22 Amherst Rd Pelham MA 01002",
    "addr:housenumber": "22",
    "addr:postcode": "01002",
    "addr:street": "Amherst Rd",
    "iso:country": "US",
    "sg:address": "22 Amherst Rd",
    "sg:city": "Pelham",
    "sg:classifiers": [
      {
        "category": "Manufacturing",
        "subcategory": "Printing",
        "type": "Manufacturing \u0026 Wholesale Goods"
      }
    ],
    "sg:phone": "+1 413 362 3502",
    "sg:postcode": "01002",
    "sg:province": "MA",
    "sg:tags": [
      "periodical"
    ],
    "wof:name": "Human Development Press Inc",
    "wof:placetype": "venue"
  },
  "geometry": {"coordinates":[-72.47407,42.378227],"type":"Point"}
}
