{
  "type": "Feature",
  "properties": {
    "addr:full":"16 High Street Medford MA 02155",
    "addr:housenumber":"16",
    "addr:postcode":"02155",
    "addr:street":"High Street",
    "iso:country":"US",
    "sg:address":"16 High Street",
    "sg:city":"Medford",
    "sg:classifiers":[
        {
            "category":"Health Services",
            "subcategory":"Optometrist",
            "type":"Services"
        },
        {
            "category":"Shopping",
            "subcategory":"Optician",
            "type":"Retail Goods"
        }
    ],
    "sg:phone":"+1 781 391 8222",
    "sg:postcode":"02155",
    "sg:province":"MA",
    "sg:tags":[
        "eyewear"
    ],
    "sg:website":"www.kidsoptical.com",
    "wof:name":"Medford Optical",
    "wof:placetype":"venue"
},
  "geometry": {"coordinates":[-71.110337,42.418524],"type":"Point"}
}