{
  "type": "Feature",
  "properties": {
    "addr:full": "10 Industrial Pkwy Woburn MA 01801",
    "addr:housenumber": "10",
    "addr:postcode": "01801",
    "addr:street": "Industrial Pkwy",
    "iso:country": "US",
    "sg:address": "10 Industrial Pkwy",
    "sg:city": "Woburn",
    "sg:classifiers": [
      {
        "category": "Wholesale",
        "subcategory": "Hardware",
        "type": "Manufacturing \u0026 Wholesale Goods"
      }
    ],
    "sg:phone": "+1 781 721 0303",
    "sg:postcode": "01801",
    "sg:province": "MA",
    "sg:tags": [
      "equipment",
      "heating",
      "system"
    ],
    "wof:name": "Capco Energy Supply",
    "wof:placetype": "venue"
  },
  "geometry": {"coordinates":[-71.1415,42.505114],"type":"Point"}
}
