{
  "type": "Feature",
  "properties": {
    "iso:country":"US",
    "sg:address":"10 Industrial Pkwy",
    "sg:city":"Woburn",
    "sg:classifiers":[
        {
            "category":"Wholesale",
            "subcategory":"Hardware",
            "type":"Manufacturing & Wholesale Goods"
        }
    ],
    "sg:phone":"+1 781 721 0303",
    "sg:postcode":"01801",
    "sg:province":"MA",
    "sg:tags":[
        "equipment",
        "heating",
        "system"
    ],
    "wof:name":"Capco Energy Supply",
    "wof:placetype":"venue"
},
  "geometry": {"coordinates":[-71.14149999999999,42.505114],"type":"Point"}
}