{
  "type": "Feature",
  "properties": {
    "iso:country":"US",
    "sg:address":"250 North St",
    "sg:city":"Danvers",
    "sg:classifiers":[
        {
            "category":"Manufacturing",
            "subcategory":"Electronics",
            "type":"Manufacturing & Wholesale Goods"
        }
    ],
    "sg:phone":"+1 978 774 5412",
    "sg:postcode":"01923",
    "sg:province":"MA",
    "sg:tags":[
        "semiconductor",
        "devices"
    ],
    "wof:name":"Centrotherm",
    "wof:placetype":"venue"
},
  "geometry": {"coordinates":[-70.962926,42.600297],"type":"Point"}
}