{
  "type": "Feature",
  "properties": {
    "addr:full": "250 North St Danvers MA 01923",
    "addr:housenumber": "250",
    "addr:postcode": "01923",
    "addr:street": "North St",
    "iso:country": "US",
    "sg:address": "250 North St",
    "sg:city": "Danvers",
    "sg:classifiers": [
      {
        "category": "Manufacturing",
        "subcategory": "Electronics",
        "type": "Manufacturing \u0026 Wholesale Goods"
      }
    ],
    "sg:phone": "+1 978 774 5412",
    "sg:postcode": "01923",
    "sg:province": "MA",
    "sg:tags": [
      "semiconductor",
      "devices"
    ],
    "wof:name": "Centrotherm",
    "wof:placetype": "venue"
  },
  "geometry": {"coordinates":[-70.962926,42.600297],"type":"Point"}
}
