{
  "type": "Feature",
  "properties": {
    "iso:country":"US",
    "sg:address":"1263 Hyde Park Ave",
    "sg:city":"Hyde Park",
    "sg:classifiers":[
        {
            "category":"Shopping",
            "subcategory":"Clothing, Apparel, & Fashions",
            "type":"Retail Goods"
        }
    ],
    "sg:phone":"+1   ",
    "sg:postcode":"02136",
    "sg:province":"MA",
    "wof:name":"Just For Girls",
    "wof:placetype":"venue"
},
  "geometry": {"coordinates":[-71.124122,42.256194],"type":"Point"}
}