{
  "type": "Feature",
  "properties": {
    "iso:country":"US",
    "sg:address":"96 Washington St",
    "sg:city":"Marblehead",
    "sg:classifiers":[
        {
            "category":"Banks & Credit Unions",
            "subcategory":"Bank",
            "type":"Services"
        },
        {
            "category":"Shopping",
            "subcategory":"Used Merchandise",
            "type":"Retail Goods"
        }
    ],
    "sg:phone":"+1 781 639 0676",
    "sg:postcode":"01945",
    "sg:province":"MA",
    "sg:tags":[
        "second",
        "furniture",
        "hand"
    ],
    "wof:name":"Surroundings",
    "wof:placetype":"venue"
},
  "geometry": {"coordinates":[-70.84981500000001,42.504953],"type":"Point"}
}