{
  "type": "Feature",
  "properties": {
    "addr:full": "96 Washington St Marblehead MA 01945",
    "addr:housenumber": "96",
    "addr:postcode": "01945",
    "addr:street": "Washington St",
    "iso:country": "US",
    "ovtr:label": "Surroundings, 96 Washington St Marblehead MA US",
    "ovtr:similarity": 2.83964204788208,
    "sg:address": "96 Washington St",
    "sg:city": "Marblehead",
    "sg:classifiers": [
      {
        "category": "Banks \u0026 Credit Unions",
        "subcategory": "Bank",
        "type": "Services"
      },
      {
        "category": "Shopping",
        "subcategory": "Used Merchandise",
        "type": "Retail Goods"
      }
    ],
    "sg:phone": "+1 781 639 0676",
    "sg:postcode": "01945",
    "sg:province": "MA",
    "sg:tags": [
      "second",
      "furniture",
      "hand"
    ],
    "wof:name": "Surroundings",
    "wof:placetype": "venue"
  },
  "geometry": {"coordinates":[-70.849815,42.504953],"type":"Point"}
}
