{
  "type": "Feature",
  "properties": {
    "addr:full": "31 Turkey Hill Rd Lunenburg MA 01462",
    "addr:housenumber": "31",
    "addr:postcode": "01462",
    "addr:street": "Turkey Hill Rd",
    "iso:country": "US",
    "sg:address": "31 Turkey Hill Rd",
    "sg:city": "Lunenburg",
    "sg:classifiers": [
      {
        "category": "Professional",
        "subcategory": "Lawyer \u0026 Legal Services",
        "type": "Services"
      }
    ],
    "sg:phone": "+1 978 582 0700",
    "sg:postcode": "01462",
    "sg:province": "MA",
    "sg:tags": [
      "attorney"
    ],
    "wof:name": "Daniel W Cronin Law Offices",
    "wof:placetype": "venue"
  },
  "geometry": {"coordinates":[-71.723114,42.60256],"type":"Point"}
}
