{
  "type": "Feature",
  "properties": {
    "iso:country":"US",
    "sg:address":"64 Main St",
    "sg:city":"Southbridge",
    "sg:classifiers":[
        {
            "category":"Personal",
            "type":"Services"
        }
    ],
    "sg:phone":"+1 508 765 3806",
    "sg:postcode":"01550",
    "sg:province":"MA",
    "sg:tags":[
        "mover"
    ],
    "wof:name":"A Class Moving Service",
    "wof:placetype":"venue"
},
  "geometry": {"coordinates":[-72.028503,42.073399],"type":"Point"}
}