{
  "type": "Feature",
  "properties": {
    "addr:full":"22 Hilliard Street Cambridge MA 02138",
    "addr:housenumber":"22",
    "addr:postcode":"02138",
    "addr:street":"Hilliard Street",
    "iso:country":"US",
    "sg:address":"22 Hilliard Street",
    "sg:city":"Cambridge",
    "sg:classifiers":[
        {
            "category":"Sports & Exercise",
            "subcategory":"Gym",
            "type":"Entertainment"
        }
    ],
    "sg:phone":"+1 617 492 0750",
    "sg:postcode":"02138",
    "sg:province":"MA",
    "sg:tags":[
        "trainer"
    ],
    "wof:name":"McNally Abigail PHD Psychlgst",
    "wof:placetype":"venue"
},
  "geometry": {"coordinates":[-71.12374,42.374077],"type":"Point"}
}