{
  "type": "Feature",
  "properties": {
    "addr:full": "364 South St Agawam MA 01001",
    "addr:housenumber": "364",
    "addr:postcode": "01001",
    "addr:street": "South St",
    "iso:country": "US",
    "sg:address": "364 South St",
    "sg:city": "Agawam",
    "sg:classifiers": [
      {
        "category": "Building \u0026 Trades",
        "subcategory": "Cleaning \u0026 Sanitation",
        "type": "Services"
      }
    ],
    "sg:phone": "+1 413 786 5047",
    "sg:postcode": "01001",
    "sg:province": "MA",
    "sg:tags": [
      "janitorial"
    ],
    "sg:website": "http://www.viewtec.com",
    "wof:name": "Imperial Janitorial Service",
    "wof:placetype": "venue"
  },
  "geometry": {"coordinates":[-72.633048,42.043137],"type":"Point"}
}
