{
  "type": "Feature",
  "properties": {
    "addr:full":"457 Main St Amherst MA 01002",
    "addr:housenumber":"457",
    "addr:postcode":"01002",
    "addr:street":"Main St",
    "iso:country":"US",
    "sg:address":"457 Main St",
    "sg:city":"Amherst",
    "sg:classifiers":[
        {
            "category":"Organizations",
            "subcategory":"Community Association",
            "type":"Services"
        }
    ],
    "sg:phone":"+1 413 253 9286",
    "sg:postcode":"01002",
    "sg:province":"MA",
    "sg:tags":[
        "club"
    ],
    "wof:name":"Veterans Of Foreign Wars",
    "wof:placetype":"venue"
},
  "geometry": {"coordinates":[-72.511241,42.375785],"type":"Point"}
}