{
  "type": "Feature",
  "properties": {
    "iso:country":"US",
    "sg:address":"152 Bailey St",
    "sg:city":"Canton",
    "sg:classifiers":[
        {
            "category":"Building & Trades",
            "subcategory":"Construction",
            "type":"Services"
        }
    ],
    "sg:phone":"+1 781 575 1244",
    "sg:postcode":"02021",
    "sg:province":"MA",
    "sg:tags":[
        "contractor"
    ],
    "wof:name":"Cig Construction Inc - CLOSED",
    "wof:placetype":"venue"
},
  "geometry": {"coordinates":[-71.141098,42.144501],"type":"Point"}
}