{
  "type": "Feature",
  "properties": {
    "iso:country":"US",
    "sg:address":"375 Yarmouth Rd",
    "sg:city":"Hyannis",
    "sg:classifiers":[
        {
            "category":"Retail",
            "subcategory":"Auto Repair",
            "type":"Services"
        }
    ],
    "sg:phone":"+1 508 775 4151",
    "sg:postcode":"02601",
    "sg:province":"MA",
    "sg:tags":[
        "automobile",
        "top",
        "upholstery"
    ],
    "wof:name":"Carnu Co",
    "wof:placetype":"venue"
},
  "geometry": {"coordinates":[-70.271733,41.665952],"type":"Point"}
}