{
  "type": "Feature",
  "properties": {
    "addr:full": "590 Main St Hampden MA 01036",
    "addr:housenumber": "590",
    "addr:postcode": "01036",
    "addr:street": "Main St",
    "iso:country": "US",
    "ovtr:label": "Federated Community Church, 590 Main St Hampden MA US",
    "ovtr:similarity": 2.460176944732666,
    "sg:address": "590 Main St",
    "sg:city": "Hampden",
    "sg:classifiers": [
      {
        "category": "Organizations",
        "subcategory": "Religious Organization",
        "type": "Services"
      }
    ],
    "sg:phone": "+1 413 566 3711",
    "sg:postcode": "01036",
    "sg:province": "MA",
    "sg:tags": [
      "church"
    ],
    "wof:name": "Federated Community Church",
    "wof:placetype": "venue"
  },
  "geometry": {"coordinates":[-72.415693,42.063641],"type":"Point"}
}
