{
  "type": "Feature",
  "properties": {
    "iso:country":"US",
    "sg:address":"590 Main St",
    "sg:city":"Hampden",
    "sg:classifiers":[
        {
            "category":"Organizations",
            "subcategory":"Religious Organization",
            "type":"Services"
        }
    ],
    "sg:phone":"+1 413 566 3711",
    "sg:postcode":"01036",
    "sg:province":"MA",
    "sg:tags":[
        "church"
    ],
    "wof:name":"Federated Community Church",
    "wof:placetype":"venue"
},
  "geometry": {"coordinates":[-72.415693,42.063641],"type":"Point"}
}