{
  "type": "Feature",
  "properties": {
    "iso:country":"US",
    "sg:address":"9 Mallard Ave",
    "sg:city":"Dorchester Ctr",
    "sg:classifiers":[
        {
            "category":"Autos & Motor Vehicles",
            "subcategory":"Automobile Sales",
            "type":"Retail Goods"
        }
    ],
    "sg:phone":"+1 617 825 7520",
    "sg:postcode":"02124",
    "sg:province":"MA",
    "sg:tags":[
        "car",
        "dealer"
    ],
    "wof:name":"Levedo Motors",
    "wof:placetype":"venue"
},
  "geometry": {"coordinates":[-71.077873,42.29092],"type":"Point"}
}