{
  "type": "Feature",
  "properties": {
    "iso:country":"US",
    "sg:address":"73 Lexington St Ste B1",
    "sg:city":"Auburndale",
    "sg:classifiers":[
        {
            "category":"Real Estate",
            "subcategory":"Real Estate Services",
            "type":"Services"
        },
        {
            "category":"Real Estate",
            "subcategory":"Real Estate Agent",
            "type":"Services"
        }
    ],
    "sg:phone":"+1 617 965 8600",
    "sg:postcode":"02466",
    "sg:province":"MA",
    "sg:tags":[
        "buyer",
        "management",
        "broker"
    ],
    "sg:website":"http://www.century21.com",
    "wof:name":"Century 21 Shawmut Properties",
    "wof:placetype":"venue"
},
  "geometry": {"coordinates":[-71.239817,42.357303],"type":"Point"}
}