{
  "type": "Feature",
  "properties": {
    "iso:country":"US",
    "sg:address":"24 Wilson Way",
    "sg:city":"Westwood",
    "sg:classifiers":[
        {
            "category":"Professional",
            "type":"Services"
        }
    ],
    "sg:phone":"+1 508 668 8137",
    "sg:postcode":"02090",
    "sg:province":"MA",
    "sg:tags":[
        "establishment"
    ],
    "wof:name":"ADI",
    "wof:placetype":"venue"
},
  "geometry": {"coordinates":[-71.183976,42.215535],"type":"Point"}
}