{
  "type": "Feature",
  "properties": {
    "addr:full":"14 Medford St Arlington MA 02474",
    "addr:housenumber":"14",
    "addr:postcode":"02474",
    "addr:street":"Medford St",
    "iso:country":"US",
    "sg:address":"14 Medford St",
    "sg:city":"Arlington",
    "sg:classifiers":[
        {
            "category":"Restaurant",
            "type":"Food & Drink"
        }
    ],
    "sg:phone":"+1 781 648 8828",
    "sg:postcode":"02474",
    "sg:province":"MA",
    "sg:tags":[
        "chinese"
    ],
    "sg:website":"www.chefcosarlington.com/",
    "wof:name":"Chef Co's Arlington",
    "wof:placetype":"venue"
},
  "geometry": {"coordinates":[-71.15051800000001,42.415299],"type":"Point"}
}