{
  "type": "Feature",
  "properties": {
    "addr:full": "26 Queen St Worcester MA 01610",
    "addr:housenumber": "26",
    "addr:postcode": "01610",
    "addr:street": "Queen St",
    "iso:country": "US",
    "sg:address": "26 Queen St",
    "sg:city": "Worcester",
    "sg:classifiers": [
      {
        "category": "Health Services",
        "subcategory": "Doctor",
        "type": "Services"
      }
    ],
    "sg:phone": "+1 508 797 1300",
    "sg:postcode": "01610",
    "sg:province": "MA",
    "sg:tags": [
      "physician",
      "surgeon"
    ],
    "wof:name": "Diabetes Research",
    "wof:placetype": "venue"
  },
  "geometry": {"coordinates":[-71.813617,42.258425],"type":"Point"}
}
