{
  "type": "Feature",
  "properties": {
    "addr:full": "411A Highland Ave Ste 312 Somerville MA 02144",
    "addr:housenumber": "411a",
    "addr:postcode": "02144",
    "addr:street": "Highland Ave Ste 312",
    "iso:country": "US",
    "sg:address": "411A Highland Ave Ste 312",
    "sg:city": "Somerville",
    "sg:classifiers": [
      {
        "category": "Wholesale",
        "subcategory": "Construction Materials",
        "type": "Manufacturing \u0026 Wholesale Goods"
      }
    ],
    "sg:phone": "+1 617 500 3938",
    "sg:postcode": "02144",
    "sg:province": "MA",
    "sg:tags": [
      "coatings-protective"
    ],
    "wof:name": "Sunbug Solar",
    "wof:placetype": "venue"
  },
  "geometry": {"coordinates":[-71.121294,42.396063],"type":"Point"}
}
