{
  "type": "Feature",
  "properties": {
    "addr:full":"77 Avenue Louis Pasteur Boston MA 02115",
    "addr:housenumber":"77",
    "addr:postcode":"02115",
    "addr:street":"Avenue Louis Pasteur",
    "iso:country":"US",
    "sg:address":"77 Avenue Louis Pasteur",
    "sg:city":"Boston",
    "sg:classifiers":[
        {
            "category":"Organizations",
            "subcategory":"Professional Association",
            "type":"Services"
        }
    ],
    "sg:phone":"+1 617 667 2699",
    "sg:postcode":"02115",
    "sg:province":"MA",
    "wof:name":"David K Simon",
    "wof:placetype":"venue"
},
  "geometry": {"coordinates":[-71.102654,42.337879],"type":"Point"}
}