{
  "type": "Feature",
  "properties": {
    "addr:full": "171 Chase Rd North Dartmouth MA 02747",
    "addr:housenumber": "171",
    "addr:postcode": "02747",
    "addr:street": "Chase Rd",
    "iso:country": "US",
    "sg:address": "171 Chase Rd",
    "sg:city": "North Dartmouth",
    "sg:classifiers": [
      {
        "category": "Professional",
        "subcategory": "Accounting \u0026 Tax Preparation",
        "type": "Services"
      }
    ],
    "sg:phone": "+1 508 990 2116",
    "sg:postcode": "02747",
    "sg:province": "MA",
    "sg:tags": [
      "bookkeeping",
      "general"
    ],
    "wof:name": "Check'n Balance",
    "wof:placetype": "venue"
  },
  "geometry": {"coordinates":[-70.997408,41.622674],"type":"Point"}
}
