{
  "type": "Feature",
  "properties": {
    "iso:country":"US",
    "sg:address":"171 Chase Rd",
    "sg:city":"North Dartmouth",
    "sg:classifiers":[
        {
            "category":"Professional",
            "subcategory":"Accounting & Tax Preparation",
            "type":"Services"
        }
    ],
    "sg:phone":"+1 508 990 2116",
    "sg:postcode":"02747",
    "sg:province":"MA",
    "sg:tags":[
        "bookkeeping",
        "general"
    ],
    "wof:name":"Check'n Balance",
    "wof:placetype":"venue"
},
  "geometry": {"coordinates":[-70.99740799999999,41.622674],"type":"Point"}
}