{
  "type": "Feature",
  "properties": {
    "iso:country":"US",
    "sg:address":"1755 Parker St",
    "sg:city":"Springfield",
    "sg:classifiers":[
        {
            "category":"Home & Garden",
            "subcategory":"Home Furnishings",
            "type":"Retail Goods"
        }
    ],
    "sg:phone":"+1   ",
    "sg:postcode":"01128",
    "sg:province":"MA",
    "wof:name":"Creative Wndows Finshg Touches",
    "wof:placetype":"venue"
},
  "geometry": {"coordinates":[-72.49397,42.099084],"type":"Point"}
}