{
  "type": "Feature",
  "properties": {
    "iso:country":"US",
    "sg:address":"100 Inman Street Suite 200",
    "sg:city":"Cambridge",
    "sg:classifiers":[
        {
            "category":"Sports & Exercise",
            "subcategory":"Gym",
            "type":"Entertainment"
        }
    ],
    "sg:phone":"+1 617 868 2399",
    "sg:postcode":"02139",
    "sg:province":"MA",
    "sg:tags":[
        "trainer"
    ],
    "wof:name":"One Cell Systems",
    "wof:placetype":"venue"
},
  "geometry": {"coordinates":[-71.101574,42.371986],"type":"Point"}
}