{
  "type": "Feature",
  "properties": {
    "iso:country":"US",
    "sg:address":"30 Wildewood Dr",
    "sg:city":"Canton",
    "sg:classifiers":[
        {
            "category":"Wholesale",
            "subcategory":"Vending Machines",
            "type":"Manufacturing & Wholesale Goods"
        }
    ],
    "sg:phone":"+1 781 828 6988",
    "sg:postcode":"02021",
    "sg:province":"MA",
    "sg:tags":[
        "operator",
        "restaurant"
    ],
    "wof:name":"H & R Canteen",
    "wof:placetype":"venue"
},
  "geometry": {"coordinates":[-71.146075,42.167358],"type":"Point"}
}