{
  "type": "Feature",
  "properties": {
    "addr:full": "30 Wildewood Dr Canton MA 02021",
    "addr:housenumber": "30",
    "addr:postcode": "02021",
    "addr:street": "Wildewood Dr",
    "iso:country": "US",
    "sg:address": "30 Wildewood Dr",
    "sg:city": "Canton",
    "sg:classifiers": [
      {
        "category": "Wholesale",
        "subcategory": "Vending Machines",
        "type": "Manufacturing \u0026 Wholesale Goods"
      }
    ],
    "sg:phone": "+1 781 828 6988",
    "sg:postcode": "02021",
    "sg:province": "MA",
    "sg:tags": [
      "operator",
      "restaurant"
    ],
    "wof:name": "H \u0026 R Canteen",
    "wof:placetype": "venue"
  },
  "geometry": {"coordinates":[-71.146075,42.167358],"type":"Point"}
}
