{
  "type": "Feature",
  "properties": {
    "iso:country":"US",
    "sg:address":"1 N Main St",
    "sg:city":"Fall River",
    "sg:classifiers":[
        {
            "category":"Social Services",
            "type":"Services"
        }
    ],
    "sg:phone":"+1 508 679 4333",
    "sg:postcode":"02720",
    "sg:province":"MA",
    "sg:tags":[
        "counselor",
        "marriage",
        "family"
    ],
    "wof:name":"Solid Ground Psychotherapy",
    "wof:placetype":"venue"
},
  "geometry": {"coordinates":[-71.155354,41.701398],"type":"Point"}
}