{
  "type": "Feature",
  "properties": {
    "iso:country":"US",
    "sg:address":"187 Florence St",
    "sg:city":"Brockton",
    "sg:classifiers":[
        {
            "category":"Transit Center",
            "subcategory":"Freight",
            "type":"Transportation"
        },
        {
            "category":"Freight",
            "type":"Transportation"
        }
    ],
    "sg:phone":"+1 857 919 6560",
    "sg:postcode":"02301",
    "sg:province":"MA",
    "sg:tags":[
        "local",
        "trucking-motor",
        "trucking"
    ],
    "wof:name":"Netco Express Co",
    "wof:placetype":"venue"
},
  "geometry": {"coordinates":[-71.027074,42.070971],"type":"Point"}
}