{
  "type": "Feature",
  "properties": {
    "iso:country":"US",
    "sg:address":"100 Wotton St",
    "sg:city":"North Chelmsford",
    "sg:classifiers":[
        {
            "category":"Professional",
            "type":"Services"
        }
    ],
    "sg:phone":"+1 978 251 1900",
    "sg:postcode":"01863",
    "sg:province":"MA",
    "sg:tags":[
        "establishment"
    ],
    "wof:name":"Blaiseconsulting",
    "wof:placetype":"venue"
},
  "geometry": {"coordinates":[-71.38261,42.64167],"type":"Point"}
}