{
  "type": "Feature",
  "properties": {
    "iso:country":"US",
    "sg:address":"6 Bancroft Ln",
    "sg:city":"Merrimac",
    "sg:classifiers":[
        {
            "category":"Professional",
            "subcategory":"Management & Consulting",
            "type":"Services"
        }
    ],
    "sg:phone":"+1   ",
    "sg:postcode":"01860",
    "sg:province":"MA",
    "wof:name":"Sightseen",
    "wof:placetype":"venue"
},
  "geometry": {"coordinates":[-70.98175500000001,42.825797],"type":"Point"}
}