{
  "type": "Feature",
  "properties": {
    "addr:full": "207 Porter St Boston MA 02128",
    "addr:housenumber": "207",
    "addr:postcode": "02128",
    "addr:street": "Porter St",
    "iso:country": "US",
    "sg:address": "207 Porter St",
    "sg:city": "Boston",
    "sg:classifiers": [
      {
        "category": "Travel",
        "subcategory": "Hotels \u0026 Motels",
        "type": "Entertainment"
      }
    ],
    "sg:phone": "+1 617 567 5000",
    "sg:postcode": "02128",
    "sg:province": "MA",
    "wof:name": "Embassy Suites Boston",
    "wof:placetype": "venue"
  },
  "geometry": {"coordinates":[-71.031888,42.370645],"type":"Point"}
}
