{
  "type": "Feature",
  "properties": {
    "iso:country":"US",
    "sg:address":"207 Porter St",
    "sg:city":"Boston",
    "sg:classifiers":[
        {
            "category":"Travel",
            "subcategory":"Hotels & Motels",
            "type":"Entertainment"
        }
    ],
    "sg:phone":"+1 617 567 5000",
    "sg:postcode":"02128",
    "sg:province":"MA",
    "wof:name":"Embassy Suites Boston",
    "wof:placetype":"venue"
},
  "geometry": {"coordinates":[-71.031888,42.370645],"type":"Point"}
}