{
  "type": "Feature",
  "properties": {
    "iso:country":"US",
    "sg:address":"56 Southbridge Rd",
    "sg:city":"Dudley",
    "sg:classifiers":[
        {
            "category":"Manufacturing",
            "subcategory":"Metals",
            "type":"Manufacturing & Wholesale Goods"
        }
    ],
    "sg:phone":"+1 508 949 3000",
    "sg:postcode":"01571",
    "sg:province":"MA",
    "sg:tags":[
        "fiber",
        "optics",
        "system"
    ],
    "sg:website":"www.myriadfiber.com",
    "wof:name":"Myriad Fiber Imaging",
    "wof:placetype":"venue"
},
  "geometry": {"coordinates":[-71.964659,42.03144],"type":"Point"}
}