{
  "type": "Feature",
  "properties": {
    "addr:full": "56 Southbridge Rd Dudley MA 01571",
    "addr:housenumber": "56",
    "addr:postcode": "01571",
    "addr:street": "Southbridge Rd",
    "iso:country": "US",
    "sg:address": "56 Southbridge Rd",
    "sg:city": "Dudley",
    "sg:classifiers": [
      {
        "category": "Manufacturing",
        "subcategory": "Metals",
        "type": "Manufacturing \u0026 Wholesale Goods"
      }
    ],
    "sg:phone": "+1 508 949 3000",
    "sg:postcode": "01571",
    "sg:province": "MA",
    "sg:tags": [
      "fiber",
      "optics",
      "system"
    ],
    "sg:website": "www.myriadfiber.com",
    "wof:name": "Myriad Fiber Imaging",
    "wof:placetype": "venue"
  },
  "geometry": {"coordinates":[-71.964659,42.03144],"type":"Point"}
}
