{
  "type": "Feature",
  "properties": {
    "addr:full": "205 Lexington St Waltham MA 02452",
    "addr:housenumber": "205",
    "addr:postcode": "02452",
    "addr:street": "Lexington St",
    "atp:label": "Domino's Pizza, 205 Lexington Street Waltham MA US",
    "atp:similarity": 3.336353063583374,
    "iso:country": "US",
    "ovtr:label": "Domino's Pizza, 205 Lexington St Waltham MA US",
    "ovtr:similarity": 2.771920919418335,
    "sg:address": "205 Lexington St",
    "sg:city": "Waltham",
    "sg:classifiers": [
      {
        "category": "Restaurant",
        "type": "Food \u0026 Drink"
      }
    ],
    "sg:menulink": "http://www.allmenus.com/ma/waltham/84586-dominos-pizza/menu/",
    "sg:phone": "+1 781 894 4848",
    "sg:postcode": "02452",
    "sg:province": "MA",
    "sg:tags": [
      "american",
      "wing",
      "pizza"
    ],
    "wof:name": "Domino's Pizza",
    "wof:placetype": "venue"
  },
  "geometry": {"coordinates":[-71.236759,42.383264],"type":"Point"}
}
