{
  "type": "Feature",
  "properties": {
    "iso:country":"US",
    "sg:address":"205 Lexington St",
    "sg:city":"Waltham",
    "sg:classifiers":[
        {
            "category":"Restaurant",
            "type":"Food & Drink"
        }
    ],
    "sg:menulink":"http://www.allmenus.com/ma/waltham/84586-dominos-pizza/menu/",
    "sg:phone":"+1 781 894 4848",
    "sg:postcode":"02452",
    "sg:province":"MA",
    "sg:tags":[
        "american",
        "wing",
        "pizza"
    ],
    "wof:name":"Domino's Pizza",
    "wof:placetype":"venue"
},
  "geometry": {"coordinates":[-71.23675900000001,42.383264],"type":"Point"}
}