{
  "type": "Feature",
  "properties": {
    "iso:country":"US",
    "sg:address":"60 Amory St",
    "sg:city":"Roxbury",
    "sg:classifiers":[
        {
            "category":"Home & Garden",
            "subcategory":"Furniture",
            "type":"Retail Goods"
        }
    ],
    "sg:phone":"+1 617 427 6006",
    "sg:postcode":"02119",
    "sg:province":"MA",
    "wof:name":"Frugal Mc Doogal's",
    "wof:placetype":"venue"
},
  "geometry": {"coordinates":[-71.09916200000001,42.321642],"type":"Point"}
}