{
  "type": "Feature",
  "properties": {
    "addr:full": "60 Amory St Roxbury MA 02119",
    "addr:housenumber": "60",
    "addr:postcode": "02119",
    "addr:street": "Amory St",
    "iso:country": "US",
    "sg:address": "60 Amory St",
    "sg:city": "Roxbury",
    "sg:classifiers": [
      {
        "category": "Home \u0026 Garden",
        "subcategory": "Furniture",
        "type": "Retail Goods"
      }
    ],
    "sg:phone": "+1 617 427 6006",
    "sg:postcode": "02119",
    "sg:province": "MA",
    "wof:name": "Frugal Mc Doogal's",
    "wof:placetype": "venue"
  },
  "geometry": {"coordinates":[-71.099162,42.321642],"type":"Point"}
}
