{
  "type": "Feature",
  "properties": {
    "addr:full":"2 Park Plz Boston MA 02116",
    "addr:housenumber":"2",
    "addr:postcode":"02116",
    "addr:street":"Park Plz",
    "iso:country":"US",
    "sg:address":"2 Park Plz",
    "sg:city":"Boston",
    "sg:classifiers":[
        {
            "category":"Banks & Credit Unions",
            "subcategory":"Investment Brokerage",
            "type":"Services"
        }
    ],
    "sg:phone":"+1 617 426 4455",
    "sg:postcode":"02116",
    "sg:province":"MA",
    "sg:tags":[
        "consultant",
        "financing"
    ],
    "sg:website":"www.michel-shaked.com",
    "wof:name":"Michel Shaked Group",
    "wof:placetype":"venue"
},
  "geometry": {"coordinates":[-71.067469,42.352495],"type":"Point"}
}