{
  "type": "Feature",
  "properties": {
    "addr:full": "452 Ash St Brockton MA 02301",
    "addr:housenumber": "452",
    "addr:postcode": "02301",
    "addr:street": "Ash St",
    "iso:country": "US",
    "sg:address": "452 Ash St",
    "sg:city": "Brockton",
    "sg:classifiers": [
      {
        "category": "Professional",
        "subcategory": "Engineering",
        "type": "Services"
      }
    ],
    "sg:phone": "+1   ",
    "sg:postcode": "02301",
    "sg:province": "MA",
    "wof:name": "Mirtech Inc",
    "wof:placetype": "venue"
  },
  "geometry": {"coordinates":[-71.034516,42.072914],"type":"Point"}
}
