{
  "type": "Feature",
  "properties": {
    "addr:full": "115 Palmer Ave Falmouth MA 02540",
    "addr:housenumber": "115",
    "addr:postcode": "02540",
    "addr:street": "Palmer Ave",
    "iso:country": "US",
    "sg:address": "115 Palmer Ave",
    "sg:city": "Falmouth",
    "sg:classifiers": [
      {
        "category": "Shopping",
        "subcategory": "Bicycles \u0026 Sporting Goods",
        "type": "Retail Goods"
      },
      {
        "category": "Sports \u0026 Exercise",
        "subcategory": "Bicycle Rental",
        "type": "Entertainment"
      },
      {
        "category": "Parking",
        "subcategory": "Bicycle",
        "type": "Transportation"
      }
    ],
    "sg:phone": "+1 508 540 4195",
    "sg:postcode": "02540",
    "sg:province": "MA",
    "sg:tags": [
      "shop",
      "system",
      "bicycles-repair",
      "security",
      "rack",
      "bicycles-renting"
    ],
    "sg:website": "http://www.cornercycle.com",
    "wof:name": "Corner Cycle Cape Cod",
    "wof:placetype": "venue"
  },
  "geometry": {"coordinates":[-70.620529,41.555703],"type":"Point"}
}
