{
  "type": "Feature",
  "properties": {
    "addr:full": "1079 Main St Fitchburg MA 01420",
    "addr:housenumber": "1079",
    "addr:postcode": "01420",
    "addr:street": "Main St",
    "iso:country": "US",
    "sg:address": "1079 Main St",
    "sg:city": "Fitchburg",
    "sg:classifiers": [
      {
        "category": "Retail",
        "subcategory": "Repair Shop",
        "type": "Services"
      },
      {
        "category": "Wholesale",
        "subcategory": "Construction Materials",
        "type": "Manufacturing \u0026 Wholesale Goods"
      }
    ],
    "sg:phone": "+1 978 345 2802",
    "sg:postcode": "01420",
    "sg:province": "MA",
    "sg:tags": [
      "refinish",
      "furniture",
      "caning",
      "supply"
    ],
    "wof:name": "The Right Corner",
    "wof:placetype": "venue"
  },
  "geometry": {"coordinates":[-71.80848,42.587202],"type":"Point"}
}
