{
  "type": "Feature",
  "properties": {
    "addr:full":"12 Grace Ln Marshfield MA 02050",
    "addr:housenumber":"12",
    "addr:postcode":"02050",
    "addr:street":"Grace Ln",
    "iso:country":"US",
    "sg:address":"12 Grace Ln",
    "sg:city":"Marshfield",
    "sg:classifiers":[
        {
            "category":"Professional",
            "subcategory":"Business Services",
            "type":"Services"
        }
    ],
    "sg:phone":"+1   ",
    "sg:postcode":"02050",
    "sg:province":"MA",
    "wof:name":"Interior Creations By Penny",
    "wof:placetype":"venue"
},
  "geometry": {"coordinates":[-70.684713,42.074452],"type":"Point"}
}