{
  "type": "Feature",
  "properties": {
    "addr:full": "1329 Riverdale St West Springfield MA 01089",
    "addr:housenumber": "1329",
    "addr:postcode": "01089",
    "addr:street": "Riverdale St",
    "iso:country": "US",
    "ovtr:label": "Subway, 1329 Riverdale St West Springfield MA US",
    "ovtr:similarity": 2.671431064605713,
    "sg:address": "1329 Riverdale St",
    "sg:city": "West Springfield",
    "sg:classifiers": [
      {
        "category": "Restaurant",
        "type": "Food \u0026 Drink"
      }
    ],
    "sg:menulink": "http://www.allmenus.com/ma/west-springfield/131753-subway/menu/",
    "sg:phone": "+1 413 781 0092",
    "sg:postcode": "01089",
    "sg:province": "MA",
    "sg:tags": [
      "american",
      "sandwich"
    ],
    "wof:name": "Subway",
    "wof:placetype": "venue"
  },
  "geometry": {"coordinates":[-72.62676,42.140074],"type":"Point"}
}
