{
  "type": "Feature",
  "properties": {
    "iso:country":"US",
    "sg:address":"2 Man Mar Dr Unit 4",
    "sg:city":"Plainville",
    "sg:classifiers":[
        {
            "category":"Restaurant",
            "type":"Food & Drink"
        }
    ],
    "sg:phone":"+1 508 695 7865",
    "sg:postcode":"02762",
    "sg:province":"MA",
    "wof:name":"D & D Breakfast and Luncheon Shoppe",
    "wof:placetype":"venue"
},
  "geometry": {"coordinates":[-71.305099,42.009899],"type":"Point"}
}