{
  "type": "Feature",
  "properties": {
    "addr:full": "43 Bullock Rd East Freetown MA 02717",
    "addr:housenumber": "43",
    "addr:postcode": "02717",
    "addr:street": "Bullock Rd",
    "iso:country": "US",
    "sg:address": "43 Bullock Rd",
    "sg:city": "East Freetown",
    "sg:classifiers": [
      {
        "category": "Building \u0026 Trades",
        "subcategory": "Construction",
        "type": "Services"
      }
    ],
    "sg:phone": "+1 508 763 5091",
    "sg:postcode": "02717",
    "sg:province": "MA",
    "sg:tags": [
      "company"
    ],
    "wof:name": "AMG Construction Co",
    "wof:placetype": "venue"
  },
  "geometry": {"coordinates":[-71.016353,41.760718],"type":"Point"}
}
