{
  "type": "Feature",
  "properties": {
    "iso:country":"US",
    "sg:address":"166 Norfolk St",
    "sg:city":"Boston",
    "sg:classifiers":[
        {
            "category":"Shopping",
            "subcategory":"Discount & Variety Stores",
            "type":"Retail Goods"
        }
    ],
    "sg:phone":"+1 617 288 7488",
    "sg:postcode":"02124",
    "sg:province":"MA",
    "wof:name":"Scott's Variety",
    "wof:placetype":"venue"
},
  "geometry": {"coordinates":[-71.078198,42.287713],"type":"Point"}
}