{
  "type": "Feature",
  "properties": {
    "addr:full": "166 Norfolk St Boston MA 02124",
    "addr:housenumber": "166",
    "addr:postcode": "02124",
    "addr:street": "Norfolk St",
    "iso:country": "US",
    "sg:address": "166 Norfolk St",
    "sg:city": "Boston",
    "sg:classifiers": [
      {
        "category": "Shopping",
        "subcategory": "Discount \u0026 Variety Stores",
        "type": "Retail Goods"
      }
    ],
    "sg:phone": "+1 617 288 7488",
    "sg:postcode": "02124",
    "sg:province": "MA",
    "wof:name": "Scott's Variety",
    "wof:placetype": "venue"
  },
  "geometry": {"coordinates":[-71.078198,42.287713],"type":"Point"}
}
