{
  "type": "Feature",
  "properties": {
    "addr:full": "9 Jerome St Medford MA 02155",
    "addr:housenumber": "9",
    "addr:postcode": "02155",
    "addr:street": "Jerome St",
    "iso:country": "US",
    "sg:address": "9 Jerome St",
    "sg:city": "Medford",
    "sg:classifiers": [
      {
        "category": "Retail",
        "subcategory": "Photofinishing",
        "type": "Services"
      },
      {
        "category": "Professional",
        "subcategory": "Printing \u0026 Photocopies",
        "type": "Services"
      }
    ],
    "sg:phone": "+1 781 488 3100",
    "sg:postcode": "02155",
    "sg:province": "MA",
    "sg:tags": [
      "photo",
      "laboratories-commercial",
      "finishing-custom",
      "laboratory"
    ],
    "wof:name": "New England Coloreze, Inc",
    "wof:placetype": "venue"
  },
  "geometry": {"coordinates":[-71.14157,42.420511],"type":"Point"}
}
