{
  "type": "Feature",
  "properties": {
    "iso:country":"US",
    "sg:address":"52 Hagen Rd",
    "sg:city":"Newton",
    "sg:classifiers":[
        {
            "category":"Professional",
            "subcategory":"Lawyer & Legal Services",
            "type":"Services"
        }
    ],
    "sg:phone":"+1   ",
    "sg:postcode":"02459",
    "sg:province":"MA",
    "wof:name":"Frank Wolpe Esq",
    "wof:placetype":"venue"
},
  "geometry": {"coordinates":[-71.192859,42.316889],"type":"Point"}
}