{
  "type": "Feature",
  "properties": {
    "iso:country":"US",
    "sg:address":"69 Main St",
    "sg:city":"Essex",
    "sg:classifiers":[
        {
            "category":"Shopping",
            "subcategory":"Used Merchandise",
            "type":"Retail Goods"
        }
    ],
    "sg:phone":"+1 978 768 3322",
    "sg:postcode":"01929",
    "sg:province":"MA",
    "sg:tags":[
        "antique"
    ],
    "wof:name":"Ro-Dan Antiques",
    "wof:placetype":"venue"
},
  "geometry": {"coordinates":[-70.77940700000001,42.632079],"type":"Point"}
}