{
  "type": "Feature",
  "properties": {
    "addr:full":"389 Main St Holyoke MA 01040",
    "addr:housenumber":"389",
    "addr:postcode":"01040",
    "addr:street":"Main St",
    "iso:country":"US",
    "sg:address":"389 Main St",
    "sg:city":"Holyoke",
    "sg:classifiers":[
        {
            "category":"Food & Beverages",
            "subcategory":"Meat & Fish",
            "type":"Retail Goods"
        }
    ],
    "sg:phone":"+1 413 533 5253",
    "sg:postcode":"01040",
    "sg:province":"MA",
    "sg:tags":[
        "seafood"
    ],
    "wof:name":"LA Pescaderia Restaurant",
    "wof:placetype":"venue"
},
  "geometry": {"coordinates":[-72.60751399999999,42.199859],"type":"Point"}
}