{
  "type": "Feature",
  "properties": {
    "addr:full": "389 Main St Holyoke MA 01040",
    "addr:housenumber": "389",
    "addr:postcode": "01040",
    "addr:street": "Main St",
    "iso:country": "US",
    "ovtr:label": "La Pescaderia Restaurant, 389 Main St Holyoke MA US",
    "ovtr:similarity": 1.7695759534835815,
    "sg:address": "389 Main St",
    "sg:city": "Holyoke",
    "sg:classifiers": [
      {
        "category": "Food \u0026 Beverages",
        "subcategory": "Meat \u0026 Fish",
        "type": "Retail Goods"
      }
    ],
    "sg:phone": "+1 413 533 5253",
    "sg:postcode": "01040",
    "sg:province": "MA",
    "sg:tags": [
      "seafood"
    ],
    "wof:name": "LA Pescaderia Restaurant",
    "wof:placetype": "venue"
  },
  "geometry": {"coordinates":[-72.607514,42.199859],"type":"Point"}
}
