{
  "type": "Feature",
  "properties": {
    "iso:country":"US",
    "sg:address":"1 Crescent Hill",
    "sg:city":"Springfield",
    "sg:classifiers":[
        {
            "category":"Professional",
            "subcategory":"Business Services",
            "type":"Services"
        }
    ],
    "sg:phone":"+1 413 733 1169",
    "sg:postcode":"01105",
    "sg:province":"MA",
    "sg:tags":[
        "recording",
        "studio"
    ],
    "wof:name":"S B Productions",
    "wof:placetype":"venue"
},
  "geometry": {"coordinates":[-72.574781,42.096168],"type":"Point"}
}