{
  "type": "Feature",
  "properties": {
    "addr:full": "75 David G Mugar Way Boston MA 02114",
    "addr:housenumber": "75",
    "addr:postcode": "02114",
    "addr:street": "David G Mugar Way",
    "iso:country": "US",
    "sg:address": "75 David G Mugar Way",
    "sg:city": "Boston",
    "sg:classifiers": [
      {
        "category": "Communications",
        "subcategory": "Radio Station",
        "type": "Services"
      }
    ],
    "sg:phone": "+1 617 367 5893",
    "sg:postcode": "02114",
    "sg:province": "MA",
    "wof:name": "W Ods",
    "wof:placetype": "venue"
  },
  "geometry": {"coordinates":[-71.07228,42.359819],"type":"Point"}
}
