{
  "type": "Feature",
  "properties": {
    "addr:full":"99 Brattle St Cambridge MA 02138",
    "addr:housenumber":"99",
    "addr:postcode":"02138",
    "addr:street":"Brattle St",
    "iso:country":"US",
    "sg:address":"99 Brattle St",
    "sg:city":"Cambridge",
    "sg:classifiers":[
        {
            "category":"Education",
            "subcategory":"Library",
            "type":"Public Place"
        }
    ],
    "sg:phone":"+1 617 349 3602",
    "sg:postcode":"02138",
    "sg:province":"MA",
    "sg:tags":[
        "special",
        "interest"
    ],
    "wof:name":"Weston Jesuit Theology Library",
    "wof:placetype":"venue"
},
  "geometry": {"coordinates":[-71.124492,42.375965],"type":"Point"}
}