{
  "type": "Feature",
  "properties": {
    "iso:country":"US",
    "sg:address":"44 Lincoln St",
    "sg:city":"Greenfield",
    "sg:classifiers":[
        {
            "category":"Professional",
            "subcategory":"Computer Services",
            "type":"Services"
        }
    ],
    "sg:phone":"+1   ",
    "sg:postcode":"01301",
    "sg:province":"MA",
    "sg:tags":[
        "related"
    ],
    "wof:name":"Lincoln Computer",
    "wof:placetype":"venue"
},
  "geometry": {"coordinates":[-72.590045,42.601129],"type":"Point"}
}