{
  "type": "Feature",
  "properties": {
    "addr:full": "44 Lincoln St Greenfield MA 01301",
    "addr:housenumber": "44",
    "addr:postcode": "01301",
    "addr:street": "Lincoln St",
    "iso:country": "US",
    "sg:address": "44 Lincoln St",
    "sg:city": "Greenfield",
    "sg:classifiers": [
      {
        "category": "Professional",
        "subcategory": "Computer Services",
        "type": "Services"
      }
    ],
    "sg:phone": "+1   ",
    "sg:postcode": "01301",
    "sg:province": "MA",
    "sg:tags": [
      "related"
    ],
    "wof:name": "Lincoln Computer",
    "wof:placetype": "venue"
  },
  "geometry": {"coordinates":[-72.590045,42.601129],"type":"Point"}
}
