{
  "type": "Feature",
  "properties": {
    "addr:full": "1138 Main St Brockton MA 02301",
    "addr:housenumber": "1138",
    "addr:postcode": "02301",
    "addr:street": "Main St",
    "iso:country": "US",
    "sg:address": "1138 Main St",
    "sg:city": "Brockton",
    "sg:classifiers": [
      {
        "category": "Utilities",
        "subcategory": "Water",
        "type": "Services"
      }
    ],
    "sg:phone": "+1 800 749 7093",
    "sg:postcode": "02301",
    "sg:province": "MA",
    "sg:tags": [
      "damage",
      "emergency"
    ],
    "sg:website": "http://floodsquad.com",
    "wof:name": "Flood Squad-Commercial Water Damage Extraction Sewage Clean Up Co Serve \u0026 Mold Cleanup Pro In Home Basement \u0026 Building",
    "wof:placetype": "venue"
  },
  "geometry": {"coordinates":[-71.015151,42.062723],"type":"Point"}
}
