{
  "type": "Feature",
  "properties": {
    "addr:full":"1615 Shawsheen St Tewksbury MA 01876",
    "addr:housenumber":"1615",
    "addr:postcode":"01876",
    "addr:street":"Shawsheen St",
    "iso:country":"US",
    "sg:address":"1615 Shawsheen St",
    "sg:city":"Tewksbury",
    "sg:classifiers":[
        {
            "category":"Retail",
            "subcategory":"Auto Rental",
            "type":"Services"
        }
    ],
    "sg:phone":"+1 978 640 9432",
    "sg:postcode":"01876",
    "sg:province":"MA",
    "sg:tags":[
        "renting",
        "truck",
        "leasing"
    ],
    "wof:name":"U-Haul Co",
    "wof:placetype":"venue"
},
  "geometry": {"coordinates":[-71.184822,42.617679],"type":"Point"}
}