{
  "type": "Feature",
  "properties": {
    "iso:country":"US",
    "sg:address":"420 East Rd",
    "sg:city":"Richmond",
    "sg:classifiers":[
        {
            "category":"Manufacturing",
            "subcategory":"Printing",
            "type":"Manufacturing & Wholesale Goods"
        }
    ],
    "sg:phone":"+1 413 698 2142",
    "sg:postcode":"01254",
    "sg:province":"MA",
    "sg:tags":[
        "newspaper",
        "publishing"
    ],
    "wof:name":"Richmond Record Inc",
    "wof:placetype":"venue"
},
  "geometry": {"coordinates":[-73.33259099999999,42.388382],"type":"Point"}
}