{
  "type": "Feature",
  "properties": {
    "addr:full": "420 East Rd Richmond MA 01254",
    "addr:housenumber": "420",
    "addr:postcode": "01254",
    "addr:street": "East Rd",
    "iso:country": "US",
    "sg:address": "420 East Rd",
    "sg:city": "Richmond",
    "sg:classifiers": [
      {
        "category": "Manufacturing",
        "subcategory": "Printing",
        "type": "Manufacturing \u0026 Wholesale Goods"
      }
    ],
    "sg:phone": "+1 413 698 2142",
    "sg:postcode": "01254",
    "sg:province": "MA",
    "sg:tags": [
      "newspaper",
      "publishing"
    ],
    "wof:name": "Richmond Record Inc",
    "wof:placetype": "venue"
  },
  "geometry": {"coordinates":[-73.332591,42.388382],"type":"Point"}
}
