{
  "type": "Feature",
  "properties": {
    "addr:full": "111 Huntington Ave Boston MA 02115",
    "addr:housenumber": "111",
    "addr:postcode": "02115",
    "addr:street": "Huntington Ave",
    "iso:country": "US",
    "sg:address": "111 Huntington Ave",
    "sg:city": "Boston",
    "sg:classifiers": [
      {
        "category": "Shopping",
        "type": "Retail Goods"
      }
    ],
    "sg:phone": "+1 617 262 8557",
    "sg:postcode": "02115",
    "sg:province": "MA",
    "sg:tags": [
      "candle"
    ],
    "wof:name": "Luna Candle LLC",
    "wof:placetype": "venue"
  },
  "geometry": {"coordinates":[-71.081382,42.345837],"type":"Point"}
}
