{
  "type": "Feature",
  "properties": {
    "addr:full": "36 Woburn St Reading MA 01867",
    "addr:housenumber": "36",
    "addr:postcode": "01867",
    "addr:street": "Woburn St",
    "iso:country": "US",
    "sg:address": "36 Woburn St",
    "sg:city": "Reading",
    "sg:classifiers": [
      {
        "category": "Personal",
        "subcategory": "Beauty Salon",
        "type": "Services"
      }
    ],
    "sg:phone": "+1 781 944 2822",
    "sg:postcode": "01867",
    "sg:province": "MA",
    "wof:name": "Blush",
    "wof:placetype": "venue"
  },
  "geometry": {"coordinates":[-71.104744,42.524713],"type":"Point"}
}
