{
  "type": "Feature",
  "properties": {
    "iso:country":"US",
    "sg:address":"153 Prichard St",
    "sg:city":"Fitchburg",
    "sg:classifiers":[
        {
            "category":"Health Services",
            "subcategory":"Health Practitioner",
            "type":"Services"
        }
    ],
    "sg:phone":"+1 978 342 3826",
    "sg:postcode":"01420",
    "sg:province":"MA",
    "sg:tags":[
        "psychologist"
    ],
    "wof:name":"Psychologist Office",
    "wof:placetype":"venue"
},
  "geometry": {"coordinates":[-71.801024,42.585729],"type":"Point"}
}