{
  "type": "Feature",
  "properties": {
    "addr:full":"104 High St Danvers MA 01923",
    "addr:housenumber":"104",
    "addr:postcode":"01923",
    "addr:street":"High St",
    "iso:country":"US",
    "sg:address":"104 High St",
    "sg:city":"Danvers",
    "sg:classifiers":[
        {
            "category":"Real Estate",
            "subcategory":"Real Estate Agent",
            "type":"Services"
        }
    ],
    "sg:phone":"+1 978 774 5545",
    "sg:postcode":"01923",
    "sg:province":"MA",
    "sg:website":"www.delrealty.com",
    "wof:name":"Del Realty",
    "wof:placetype":"venue"
},
  "geometry": {"coordinates":[-70.93028700000001,42.558894],"type":"Point"}
}