{
  "type": "Feature",
  "properties": {
    "addr:full": "25 Harvard St Brookline MA 02446",
    "addr:housenumber": "25",
    "addr:postcode": "02446",
    "addr:street": "Harvard St",
    "iso:country": "US",
    "ovtr:label": "Baptiste Power Yoga Boston, 25 Harvard St Brookline MA US",
    "ovtr:similarity": 2.587585926055908,
    "sg:address": "25 Harvard St",
    "sg:city": "Brookline",
    "sg:classifiers": [
      {
        "category": "Sports \u0026 Exercise",
        "subcategory": "Gym",
        "type": "Entertainment"
      }
    ],
    "sg:phone": "+1 617 232 9642",
    "sg:postcode": "02446",
    "sg:province": "MA",
    "sg:tags": [
      "yoga"
    ],
    "sg:website": "www.baronbaptiste.com",
    "wof:name": "Baptiste Power Yoga",
    "wof:placetype": "venue"
  },
  "geometry": {"coordinates":[-71.122255,42.336319],"type":"Point"}
}
