{
  "type": "Feature",
  "properties": {
    "iso:country":"US",
    "sg:address":"697 Cambridge St",
    "sg:city":"Brighton",
    "sg:classifiers":[
        {
            "category":"Health Services",
            "subcategory":"Doctor",
            "type":"Services"
        }
    ],
    "sg:phone":"+1 617 782 5700",
    "sg:postcode":"02135",
    "sg:province":"MA",
    "sg:tags":[
        "physician",
        "surgeon"
    ],
    "sg:website":"www.stantonmed.com",
    "wof:name":"Stanton Medical Assoc Inc",
    "wof:placetype":"venue"
},
  "geometry": {"coordinates":[-71.146511,42.350417],"type":"Point"}
}