{
  "type": "Feature",
  "properties": {
    "iso:country":"US",
    "sg:address":"85 Andover St",
    "sg:city":"North Andover",
    "sg:classifiers":[
        {
            "category":"Health Services",
            "subcategory":"Clinic",
            "type":"Services"
        }
    ],
    "sg:phone":"+1 978 794 8366",
    "sg:postcode":"01845",
    "sg:province":"MA",
    "sg:tags":[
        "education"
    ],
    "sg:website":"www.fhea.com",
    "wof:name":"Fitzgerald Health Education",
    "wof:placetype":"venue"
},
  "geometry": {"coordinates":[-71.116924,42.682207],"type":"Point"}
}