{
  "type": "Feature",
  "properties": {
    "iso:country":"US",
    "sg:address":"141 Church St",
    "sg:city":"Whitinsville",
    "sg:classifiers":[
        {
            "category":"Restaurant",
            "type":"Food & Drink"
        },
        {
            "category":"Ice Cream",
            "type":"Food & Drink"
        }
    ],
    "sg:menulink":"http://www.allmenus.com/ma/northbridge/99183-friendlys/menu/",
    "sg:phone":"+1 508 234 3170",
    "sg:postcode":"01588",
    "sg:province":"MA",
    "sg:tags":[
        "burger",
        "american",
        "ice",
        "cream"
    ],
    "wof:name":"Friendly's",
    "wof:placetype":"venue"
},
  "geometry": {"coordinates":[-71.659288,42.112354],"type":"Point"}
}