{
  "type": "Feature",
  "properties": {
    "addr:full": "141 Church St Whitinsville MA 01588",
    "addr:housenumber": "141",
    "addr:postcode": "01588",
    "addr:street": "Church St",
    "iso:country": "US",
    "sg:address": "141 Church St",
    "sg:city": "Whitinsville",
    "sg:classifiers": [
      {
        "category": "Restaurant",
        "type": "Food \u0026 Drink"
      },
      {
        "category": "Ice Cream",
        "type": "Food \u0026 Drink"
      }
    ],
    "sg:menulink": "http://www.allmenus.com/ma/northbridge/99183-friendlys/menu/",
    "sg:phone": "+1 508 234 3170",
    "sg:postcode": "01588",
    "sg:province": "MA",
    "sg:tags": [
      "burger",
      "american",
      "ice",
      "cream"
    ],
    "wof:name": "Friendly's",
    "wof:placetype": "venue"
  },
  "geometry": {"coordinates":[-71.659288,42.112354],"type":"Point"}
}
