{
  "type": "Feature",
  "properties": {
    "addr:full":"225 High St Holyoke MA 01040",
    "addr:housenumber":"225",
    "addr:postcode":"01040",
    "addr:street":"High St",
    "iso:country":"US",
    "sg:address":"225 High St",
    "sg:city":"Holyoke",
    "sg:classifiers":[
        {
            "category":"Professional",
            "subcategory":"Lawyer & Legal Services",
            "type":"Services"
        }
    ],
    "sg:phone":"+1 413 533 1115",
    "sg:postcode":"01040",
    "sg:province":"MA",
    "sg:tags":[
        "attorney"
    ],
    "wof:name":"Joseph J D'Amour Attorney",
    "wof:placetype":"venue"
},
  "geometry": {"coordinates":[-72.60727799999999,42.207636],"type":"Point"}
}