{
  "type": "Feature",
  "properties": {
    "addr:full":"56 Sam West Rd Southwick MA 01077",
    "addr:housenumber":"56",
    "addr:postcode":"01077",
    "addr:street":"Sam West Rd",
    "iso:country":"US",
    "sg:address":"56 Sam West Rd",
    "sg:city":"Southwick",
    "sg:classifiers":[
        {
            "category":"Wholesale",
            "subcategory":"Auto Parts",
            "type":"Manufacturing & Wholesale Goods"
        }
    ],
    "sg:phone":"+1 413 569 1266",
    "sg:postcode":"01077",
    "sg:province":"MA",
    "sg:tags":[
        "automobile",
        "rebuilt"
    ],
    "wof:name":"R E Humason Inc",
    "wof:placetype":"venue"
},
  "geometry": {"coordinates":[-72.756675,42.076301],"type":"Point"}
}