{
  "type": "Feature",
  "properties": {
    "addr:full":"55 Water St Hingham MA 02043",
    "addr:housenumber":"55",
    "addr:postcode":"02043",
    "addr:street":"Water St",
    "iso:country":"US",
    "sg:address":"55 Water St",
    "sg:city":"Hingham",
    "sg:classifiers":[
        {
            "category":"Shopping",
            "subcategory":"Bicycles & Sporting Goods",
            "type":"Retail Goods"
        }
    ],
    "sg:phone":"+1   ",
    "sg:postcode":"02043",
    "sg:province":"MA",
    "sg:tags":[
        "retailer"
    ],
    "wof:name":"Hingham Motor Parts",
    "wof:placetype":"venue"
},
  "geometry": {"coordinates":[-70.88360900000001,42.243736],"type":"Point"}
}