{
  "type": "Feature",
  "properties": {
    "addr:full": "1 Innis Dr Billerica MA 01821",
    "addr:housenumber": "1",
    "addr:postcode": "01821",
    "addr:street": "Innis Dr",
    "iso:country": "US",
    "sg:address": "1 Innis Dr",
    "sg:city": "Billerica",
    "sg:classifiers": [
      {
        "category": "Retail",
        "subcategory": "Auto Repair",
        "type": "Services"
      }
    ],
    "sg:phone": "+1 978 670 5222",
    "sg:postcode": "01821",
    "sg:province": "MA",
    "wof:name": "R \u0026 D Custom Exhaust",
    "wof:placetype": "venue"
  },
  "geometry": {"coordinates":[-71.263901,42.551498],"type":"Point"}
}
