{
  "type": "Feature",
  "properties": {
    "iso:country":"US",
    "sg:address":"1 Innis Dr",
    "sg:city":"Billerica",
    "sg:classifiers":[
        {
            "category":"Retail",
            "subcategory":"Auto Repair",
            "type":"Services"
        }
    ],
    "sg:phone":"+1 978 670 5222",
    "sg:postcode":"01821",
    "sg:province":"MA",
    "wof:name":"R & D Custom Exhaust",
    "wof:placetype":"venue"
},
  "geometry": {"coordinates":[-71.263901,42.551498],"type":"Point"}
}