{
  "type": "Feature",
  "properties": {
    "addr:full": "360 Merrimack St Lawrence MA 01843",
    "addr:housenumber": "360",
    "addr:postcode": "01843",
    "addr:street": "Merrimack St",
    "iso:country": "US",
    "sg:address": "360 Merrimack St",
    "sg:city": "Lawrence",
    "sg:classifiers": [
      {
        "category": "Professional",
        "type": "Services"
      }
    ],
    "sg:phone": "+1 978 689 3200",
    "sg:postcode": "01843",
    "sg:province": "MA",
    "sg:tags": [
      "establishment"
    ],
    "sg:website": "www.tekpad.com",
    "wof:name": "Broleco Inc",
    "wof:placetype": "venue"
  },
  "geometry": {"coordinates":[-71.141516,42.703553],"type":"Point"}
}
