{
  "type": "Feature",
  "properties": {
    "iso:country":"US",
    "sg:address":"519 Washington St",
    "sg:city":"Gloucester",
    "sg:classifiers":[
        {
            "category":"Utilities",
            "subcategory":"Telephone",
            "type":"Services"
        }
    ],
    "sg:phone":"+1   ",
    "sg:postcode":"01930",
    "sg:province":"MA",
    "sg:tags":[
        "communications"
    ],
    "wof:name":"Rtj Products",
    "wof:placetype":"venue"
},
  "geometry": {"coordinates":[-70.672753,42.639247],"type":"Point"}
}