{
  "type": "Feature",
  "properties": {
    "addr:full": "641 Belmont St Brockton MA 02301",
    "addr:housenumber": "641",
    "addr:postcode": "02301",
    "addr:street": "Belmont St",
    "iso:country": "US",
    "sg:address": "641 Belmont St",
    "sg:city": "Brockton",
    "sg:classifiers": [
      {
        "category": "Banks \u0026 Credit Unions",
        "subcategory": "Bank",
        "type": "Services"
      }
    ],
    "sg:phone": "+1 508 000 1111",
    "sg:postcode": "02301",
    "sg:province": "MA",
    "wof:name": "Sovereign Bank",
    "wof:placetype": "venue"
  },
  "geometry": {"coordinates":[-71.044057,42.07183],"type":"Point"}
}
