{
  "type": "Feature",
  "properties": {
    "iso:country":"US",
    "sg:address":"104 Pine St",
    "sg:city":"Chicopee",
    "sg:classifiers":[
        {
            "category":"Manufacturing",
            "subcategory":"Food",
            "type":"Manufacturing & Wholesale Goods"
        }
    ],
    "sg:phone":"+1   ",
    "sg:postcode":"01020",
    "sg:province":"MA",
    "sg:tags":[
        "product",
        "mfg"
    ],
    "wof:name":"Freihofer",
    "wof:placetype":"venue"
},
  "geometry": {"coordinates":[-72.580592,42.152591],"type":"Point"}
}