{
  "type": "Feature",
  "properties": {
    "addr:full":"211 Mountain Ave Unit 1 Revere MA 02151",
    "addr:housenumber":"211;1",
    "addr:postcode":"02151",
    "addr:street":"Mountain Ave Unit",
    "iso:country":"US",
    "sg:address":"211 Mountain Ave Unit 1",
    "sg:city":"Revere",
    "sg:classifiers":[
        {
            "category":"Real Estate",
            "subcategory":"Real Estate Services",
            "type":"Services"
        },
        {
            "category":"Real Estate",
            "subcategory":"Surveying",
            "type":"Services"
        }
    ],
    "sg:phone":"+1 781 286 1847",
    "sg:postcode":"02151",
    "sg:province":"MA",
    "sg:tags":[
        "industrial",
        "appraisers-commercial",
        "appraiser"
    ],
    "wof:name":"Real Estate Appraisal Services",
    "wof:placetype":"venue"
},
  "geometry": {"coordinates":[-71.016634,42.413263],"type":"Point"}
}