{
  "type": "Feature",
  "properties": {
    "addr:full": "301 W Center St West Bridgewater MA 02379",
    "addr:housenumber": "301",
    "addr:postcode": "02379",
    "addr:street": "W Center St",
    "iso:country": "US",
    "sg:address": "301 W Center St",
    "sg:city": "West Bridgewater",
    "sg:classifiers": [
      {
        "category": "Real Estate",
        "subcategory": "Surveying",
        "type": "Services"
      }
    ],
    "sg:phone": "+1 508 559 8047",
    "sg:postcode": "02379",
    "sg:province": "MA",
    "sg:tags": [
      "surveyor"
    ],
    "wof:name": "Ribelin Land Surveyors Inc",
    "wof:placetype": "venue"
  },
  "geometry": {"coordinates":[-71.025875,42.016641],"type":"Point"}
}
