{
  "type": "Feature",
  "properties": {
    "addr:full":"101 Cambridge St Burlington MA 01803",
    "addr:housenumber":"101",
    "addr:postcode":"01803",
    "addr:street":"Cambridge St",
    "iso:country":"US",
    "sg:address":"101 Cambridge St",
    "sg:city":"Burlington",
    "sg:classifiers":[
        {
            "category":"Health Services",
            "subcategory":"Hospital",
            "type":"Services"
        },
        {
            "category":"Health Services",
            "subcategory":"Health Practitioner",
            "type":"Services"
        }
    ],
    "sg:phone":"+1 781 229 9353",
    "sg:postcode":"01803",
    "sg:province":"MA",
    "sg:tags":[
        "therapy",
        "physical"
    ],
    "wof:name":"Institute of Orthopedic Manual Therapy",
    "wof:placetype":"venue"
},
  "geometry": {"coordinates":[-71.194603,42.495499],"type":"Point"}
}