{
  "type": "Feature",
  "properties": {
    "iso:country":"US",
    "sg:address":"79 Brook St",
    "sg:city":"New Bedford",
    "sg:classifiers":[
        {
            "category":"Real Estate",
            "subcategory":"Real Estate Agent",
            "type":"Services"
        }
    ],
    "sg:phone":"+1 508 992 0358",
    "sg:postcode":"02746",
    "sg:province":"MA",
    "wof:name":"RBV Realty",
    "wof:placetype":"venue"
},
  "geometry": {"coordinates":[-70.93142899999999,41.659547],"type":"Point"}
}