{
  "type": "Feature",
  "properties": {
    "addr:full": "79 Brook St New Bedford MA 02746",
    "addr:housenumber": "79",
    "addr:postcode": "02746",
    "addr:street": "Brook St",
    "iso:country": "US",
    "sg:address": "79 Brook St",
    "sg:city": "New Bedford",
    "sg:classifiers": [
      {
        "category": "Real Estate",
        "subcategory": "Real Estate Agent",
        "type": "Services"
      }
    ],
    "sg:phone": "+1 508 992 0358",
    "sg:postcode": "02746",
    "sg:province": "MA",
    "wof:name": "RBV Realty",
    "wof:placetype": "venue"
  },
  "geometry": {"coordinates":[-70.931429,41.659547],"type":"Point"}
}
