{
  "type": "Feature",
  "properties": {
    "addr:full": "1145 Hancock St Quincy MA 02169",
    "addr:housenumber": "1145",
    "addr:postcode": "02169",
    "addr:street": "Hancock St",
    "iso:country": "US",
    "sg:address": "1145 Hancock St",
    "sg:city": "Quincy",
    "sg:classifiers": [
      {
        "category": "Real Estate",
        "subcategory": "Real Estate Agent",
        "type": "Services"
      }
    ],
    "sg:phone": "+1 617 328 5588",
    "sg:postcode": "02169",
    "sg:province": "MA",
    "wof:name": "Norfolk Real Estate Group",
    "wof:placetype": "venue"
  },
  "geometry": {"coordinates":[-71.004938,42.253265],"type":"Point"}
}
