{
  "type": "Feature",
  "properties": {
    "iso:country":"US",
    "sg:address":"Boston Marriott Burlington 1 Burlington Mall Rd",
    "sg:city":"Burlington",
    "sg:classifiers":[
        {
            "category":"Bars & Pubs",
            "type":"Food & Drink"
        }
    ],
    "sg:postcode":"01803",
    "sg:province":"MA",
    "sg:website":"www.marriott.com/hotels/photo-to...",
    "wof:name":"Fitzwilliams Irish Pub",
    "wof:placetype":"venue"
},
  "geometry": {"coordinates":[-71.193443,42.491423],"type":"Point"}
}