{
  "type": "Feature",
  "properties": {
    "addr:full":"14 S Russell St Boston MA 02114",
    "addr:housenumber":"14",
    "addr:postcode":"02114",
    "addr:street":"S Russell St",
    "iso:country":"US",
    "sg:address":"14 S Russell St",
    "sg:city":"Boston",
    "sg:classifiers":[
        {
            "category":"Real Estate",
            "subcategory":"Architect",
            "type":"Services"
        }
    ],
    "sg:phone":"+1 617 227 5364",
    "sg:postcode":"02114",
    "sg:province":"MA",
    "wof:name":"Michael Lesburg",
    "wof:placetype":"venue"
},
  "geometry": {"coordinates":[-71.065905,42.36103],"type":"Point"}
}