{
  "type": "Feature",
  "properties": {
    "addr:full": "418 Highland Avenue Somerville MA 02144",
    "addr:housenumber": "418",
    "addr:postcode": "02144",
    "addr:street": "Highland Avenue",
    "iso:country": "US",
    "ovtr:label": "Davis Square Nails \u0026 Spa, 418 Highland Ave Somerville MA US",
    "ovtr:similarity": 3.517029047012329,
    "sg:address": "418 Highland Avenue",
    "sg:city": "Somerville",
    "sg:classifiers": [
      {
        "category": "Personal",
        "subcategory": "Nail Salon",
        "type": "Services"
      }
    ],
    "sg:phone": "+1 617 666 3332",
    "sg:postcode": "02144",
    "sg:province": "MA",
    "wof:name": "Davis Sq Nails \u0026 Spa",
    "wof:placetype": "venue"
  },
  "geometry": {"coordinates":[-71.121886,42.396437],"type":"Point"}
}
