{
  "type": "Feature",
  "properties": {
    "addr:full":"1420 Pleasant St Bridgewater MA 02324",
    "addr:housenumber":"1420",
    "addr:postcode":"02324",
    "addr:street":"Pleasant St",
    "iso:country":"US",
    "sg:address":"1420 Pleasant St",
    "sg:city":"Bridgewater",
    "sg:phone":"+1 508 697 8815",
    "sg:postcode":"02324",
    "sg:province":"MA",
    "wof:name":"Emma's Pub & Pizza",
    "wof:placetype":"venue"
},
  "geometry": {"coordinates":[-71.018844,41.969318],"type":"Point"}
}