{
  "type": "Feature",
  "properties": {
    "iso:country":"US",
    "sg:address":"70 North St",
    "sg:city":"Somerset",
    "sg:classifiers":[
        {
            "category":"Building & Trades",
            "subcategory":"Construction",
            "type":"Services"
        }
    ],
    "sg:phone":"+1 508 673 7811",
    "sg:postcode":"02726",
    "sg:province":"MA",
    "sg:tags":[
        "roofing",
        "contractor"
    ],
    "wof:name":"Richard Miranda Construction",
    "wof:placetype":"venue"
},
  "geometry": {"coordinates":[-71.12499200000001,41.783963],"type":"Point"}
}