{
  "type": "Feature",
  "properties": {
    "iso:country":"US",
    "sg:address":"441 Main St",
    "sg:city":"Woburn",
    "sg:classifiers":[
        {
            "category":"Cinema",
            "subcategory":"Movie Rental",
            "type":"Entertainment"
        }
    ],
    "sg:phone":"+1 781 938 5777",
    "sg:postcode":"01801",
    "sg:province":"MA",
    "sg:tags":[
        "game",
        "video"
    ],
    "sg:website":"www.blockbuster.com",
    "wof:name":"Blockbuster Video",
    "wof:placetype":"venue"
},
  "geometry": {"coordinates":[-71.151398,42.483501],"type":"Point"}
}