{
  "type": "Feature",
  "properties": {
    "iso:country":"US",
    "sg:address":"460 Yarmouth Rd",
    "sg:city":"Hyannis",
    "sg:classifiers":[
        {
            "category":"Autos & Motor Vehicles",
            "subcategory":"Automobile Sales",
            "type":"Retail Goods"
        },
        {
            "category":"Retail",
            "subcategory":"Auto Repair",
            "type":"Services"
        }
    ],
    "sg:phone":"+1 508 790 4455",
    "sg:postcode":"02601",
    "sg:province":"MA",
    "sg:tags":[
        "car"
    ],
    "wof:name":"Miskinis Motors Hyundai",
    "wof:placetype":"venue"
},
  "geometry": {"coordinates":[-70.275299,41.6609],"type":"Point"}
}