{
  "type": "Feature",
  "properties": {
    "iso:country":"US",
    "sg:address":"30 Memorial Rd",
    "sg:city":"Somerville",
    "sg:classifiers":[
        {
            "category":"Building & Trades",
            "subcategory":"Locksmith",
            "type":"Services"
        }
    ],
    "sg:phone":"+1 617 440 4992",
    "sg:postcode":"02145",
    "sg:province":"MA",
    "sg:tags":[
        "key"
    ],
    "wof:name":"A Locksmith 24 Hours",
    "wof:placetype":"venue"
},
  "geometry": {"coordinates":[-71.092584,42.396119],"type":"Point"}
}