{
  "type": "Feature",
  "properties": {
    "addr:full": "55 Knox Trl Acton MA 01720",
    "addr:housenumber": "55",
    "addr:postcode": "01720",
    "addr:street": "Knox Trl",
    "iso:country": "US",
    "sg:address": "55 Knox Trl",
    "sg:city": "Acton",
    "sg:classifiers": [
      {
        "category": "Building \u0026 Trades",
        "subcategory": "Construction",
        "type": "Services"
      }
    ],
    "sg:phone": "+1 978 897 1150",
    "sg:postcode": "01720",
    "sg:province": "MA",
    "sg:tags": [
      "resurfacing",
      "laying",
      "refinishing",
      "floor"
    ],
    "wof:name": "J J Hardwood Floors Inc",
    "wof:placetype": "venue"
  },
  "geometry": {"coordinates":[-71.425793,42.445362],"type":"Point"}
}
