{
  "type": "Feature",
  "properties": {
    "addr:full":"67 Main St Boylston MA 01505",
    "addr:housenumber":"67",
    "addr:postcode":"01505",
    "addr:street":"Main St",
    "iso:country":"US",
    "sg:address":"67 Main St",
    "sg:city":"Boylston",
    "sg:classifiers":[
        {
            "category":"Autos & Motor Vehicles",
            "subcategory":"Automobile Sales",
            "type":"Retail Goods"
        }
    ],
    "sg:phone":"+1 508 869 6767",
    "sg:postcode":"01505",
    "sg:province":"MA",
    "sg:tags":[
        "car",
        "dealer"
    ],
    "wof:name":"Wangner Audi Of Boyston",
    "wof:placetype":"venue"
},
  "geometry": {"coordinates":[-71.756781,42.317184],"type":"Point"}
}