{
  "type": "Feature",
  "properties": {
    "addr:full": "5 Dalbeck Ln Ashburnham MA 01430",
    "addr:housenumber": "5",
    "addr:postcode": "01430",
    "addr:street": "Dalbeck Ln",
    "iso:country": "US",
    "sg:address": "5 Dalbeck Ln",
    "sg:city": "Ashburnham",
    "sg:classifiers": [
      {
        "category": "Food \u0026 Beverages",
        "subcategory": "Liquor \u0026 Beverages",
        "type": "Retail Goods"
      }
    ],
    "sg:phone": "+1 978 537 1178",
    "sg:postcode": "01430",
    "sg:province": "MA",
    "wof:name": "Leominster Beer Mart",
    "wof:placetype": "venue"
  },
  "geometry": {"coordinates":[-71.90656,42.662559],"type":"Point"}
}
