{
  "type": "Feature",
  "properties": {
    "iso:country":"US",
    "sg:address":"492 E Merrimack St",
    "sg:city":"Lowell",
    "sg:classifiers":[
        {
            "category":"Professional",
            "type":"Services"
        }
    ],
    "sg:phone":"+1   ",
    "sg:postcode":"01852",
    "sg:province":"MA",
    "wof:name":"Cambodia Immigration Conslt",
    "wof:placetype":"venue"
},
  "geometry": {"coordinates":[-71.296592,42.643781],"type":"Point"}
}