{
  "type": "Feature",
  "properties": {
    "iso:country":"US",
    "sg:address":"25 Dry Dock Ave",
    "sg:city":"Boston",
    "sg:classifiers":[
        {
            "category":"Professional",
            "subcategory":"Advertising",
            "type":"Services"
        }
    ],
    "sg:phone":"+1 617 330 9393",
    "sg:postcode":"02210",
    "sg:province":"MA",
    "sg:tags":[
        "counselor"
    ],
    "sg:website":"www.partnersandsimons.com",
    "wof:name":"Partners & Simons Inc",
    "wof:placetype":"venue"
},
  "geometry": {"coordinates":[-71.027452,42.344715],"type":"Point"}
}