{
  "type": "Feature",
  "properties": {
    "addr:full": "25 Dry Dock Ave Boston MA 02210",
    "addr:housenumber": "25",
    "addr:postcode": "02210",
    "addr:street": "Dry Dock Ave",
    "iso:country": "US",
    "sg:address": "25 Dry Dock Ave",
    "sg:city": "Boston",
    "sg:classifiers": [
      {
        "category": "Professional",
        "subcategory": "Advertising",
        "type": "Services"
      }
    ],
    "sg:phone": "+1 617 330 9393",
    "sg:postcode": "02210",
    "sg:province": "MA",
    "sg:tags": [
      "counselor"
    ],
    "sg:website": "www.partnersandsimons.com",
    "wof:name": "Partners \u0026 Simons Inc",
    "wof:placetype": "venue"
  },
  "geometry": {"coordinates":[-71.027452,42.344715],"type":"Point"}
}
