{
  "type": "Feature",
  "properties": {
    "addr:full": "800 S Franklin St Holbrook MA 02343",
    "addr:housenumber": "800",
    "addr:postcode": "02343",
    "addr:street": "S Franklin St",
    "iso:country": "US",
    "sg:address": "800 S Franklin St",
    "sg:city": "Holbrook",
    "sg:classifiers": [
      {
        "category": "Health Services",
        "subcategory": "Clinic",
        "type": "Services"
      }
    ],
    "sg:phone": "+1 339 987 4856",
    "sg:postcode": "02343",
    "sg:province": "MA",
    "sg:tags": [
      "information",
      "alcoholism",
      "treatment"
    ],
    "wof:name": "Js Therapy Associates",
    "wof:placetype": "venue"
  },
  "geometry": {"coordinates":[-71.008957,42.128811],"type":"Point"}
}
