{
  "type": "Feature",
  "properties": {
    "addr:full": "85 Rangeway Rd North Billerica MA 01862",
    "addr:housenumber": "85",
    "addr:postcode": "01862",
    "addr:street": "Rangeway Rd",
    "iso:country": "US",
    "sg:address": "85 Rangeway Rd",
    "sg:city": "North Billerica",
    "sg:classifiers": [
      {
        "category": "Professional",
        "subcategory": "Research",
        "type": "Services"
      }
    ],
    "sg:phone": "+1 978 670 5610",
    "sg:postcode": "01862",
    "sg:province": "MA",
    "sg:tags": [
      "development",
      "laboratory"
    ],
    "sg:website": "www.apcc.com",
    "wof:name": "American Power Conversion Corp",
    "wof:placetype": "venue"
  },
  "geometry": {"coordinates":[-71.303118,42.57766],"type":"Point"}
}
