{
  "type": "Feature",
  "properties": {
    "addr:full":"41 N Brookfield Rd North Brookfield MA 01535",
    "addr:housenumber":"41",
    "addr:postcode":"01535",
    "addr:street":"N Brookfield Rd",
    "iso:country":"US",
    "sg:address":"41 N Brookfield Rd",
    "sg:city":"North Brookfield",
    "sg:classifiers":[
        {
            "category":"Professional",
            "subcategory":"Management & Consulting",
            "type":"Services"
        }
    ],
    "sg:phone":"+1 508 867 2100",
    "sg:postcode":"01535",
    "sg:province":"MA",
    "sg:tags":[
        "consultant",
        "training"
    ],
    "wof:name":"New England Center",
    "wof:placetype":"venue"
},
  "geometry": {"coordinates":[-72.092297,42.245394],"type":"Point"}
}