{
  "type": "Feature",
  "properties": {
    "iso:country":"US",
    "sg:address":"136 Fountain St",
    "sg:city":"Ashland",
    "sg:classifiers":[
        {
            "category":"Manufacturing",
            "subcategory":"Furniture",
            "type":"Manufacturing & Wholesale Goods"
        }
    ],
    "sg:phone":"+1 508 881 7000",
    "sg:postcode":"01721",
    "sg:province":"MA",
    "sg:tags":[
        "mfg",
        "wood",
        "cabinet"
    ],
    "wof:name":"KARP Woodworks Corp",
    "wof:placetype":"venue"
},
  "geometry": {"coordinates":[-71.44986400000001,42.268125],"type":"Point"}
}