{
  "type": "Feature",
  "properties": {
    "addr:full": "2077 Centre St West Roxbury MA 02132",
    "addr:housenumber": "2077",
    "addr:postcode": "02132",
    "addr:street": "Centre St",
    "iso:country": "US",
    "sg:address": "2077 Centre St",
    "sg:city": "West Roxbury",
    "sg:classifiers": [
      {
        "category": "Real Estate",
        "subcategory": "Real Estate Agent",
        "type": "Services"
      }
    ],
    "sg:phone": "+1 617 323 5050",
    "sg:postcode": "02132",
    "sg:province": "MA",
    "wof:name": "Re/Max Affiliates",
    "wof:placetype": "venue"
  },
  "geometry": {"coordinates":[-71.159108,42.279396],"type":"Point"}
}
