{
  "type": "Feature",
  "properties": {
    "iso:country":"US",
    "sg:address":"2298 State Rd",
    "sg:city":"Plymouth",
    "sg:classifiers":[
        {
            "category":"Restaurant",
            "type":"Food & Drink"
        }
    ],
    "sg:phone":"+1 508 833 0442",
    "sg:postcode":"02360",
    "sg:province":"MA",
    "sg:tags":[
        "out"
    ],
    "wof:name":"Rock Bottom Gally",
    "wof:placetype":"venue"
},
  "geometry": {"coordinates":[-70.552252,41.818428],"type":"Point"}
}