{
  "type": "Feature",
  "properties": {
    "addr:full": "18 Main St Northampton MA 01060",
    "addr:housenumber": "18",
    "addr:postcode": "01060",
    "addr:street": "Main St",
    "iso:country": "US",
    "sg:address": "18 Main St",
    "sg:city": "Northampton",
    "sg:classifiers": [
      {
        "category": "Restaurant",
        "type": "Food \u0026 Drink"
      }
    ],
    "sg:phone": "+1 413 582 1888",
    "sg:postcode": "01060",
    "sg:province": "MA",
    "wof:name": "Taipei \u0026 Tokyo",
    "wof:placetype": "venue"
  },
  "geometry": {"coordinates":[-72.629067,42.319958],"type":"Point"}
}
