{
  "type": "Feature",
  "properties": {
    "iso:country":"US",
    "sg:address":"18 Main St",
    "sg:city":"Northampton",
    "sg:classifiers":[
        {
            "category":"Restaurant",
            "type":"Food & Drink"
        }
    ],
    "sg:phone":"+1 413 582 1888",
    "sg:postcode":"01060",
    "sg:province":"MA",
    "wof:name":"Taipei & Tokyo",
    "wof:placetype":"venue"
},
  "geometry": {"coordinates":[-72.62906700000001,42.319958],"type":"Point"}
}