{
  "type": "Feature",
  "properties": {
    "iso:country":"US",
    "sg:address":"699 Main St",
    "sg:city":"Brewster",
    "sg:classifiers":[
        {
            "category":"Travel",
            "subcategory":"Hotels & Motels",
            "type":"Entertainment"
        }
    ],
    "sg:phone":"+1 508 896 4353",
    "sg:postcode":"02631",
    "sg:province":"MA",
    "sg:tags":[
        "breakfast",
        "accommodation",
        "bed"
    ],
    "wof:name":"Blue Cedar Bed & Breakfast",
    "wof:placetype":"venue"
},
  "geometry": {"coordinates":[-70.122535,41.749812],"type":"Point"}
}