{
  "type": "Feature",
  "properties": {
    "iso:country":"US",
    "sg:address":"200 Newton St",
    "sg:city":"Waltham",
    "sg:classifiers":[
        {
            "category":"Building & Trades",
            "subcategory":"Electrical",
            "type":"Services"
        }
    ],
    "sg:phone":"+1 781 647 8897",
    "sg:postcode":"02453",
    "sg:province":"MA",
    "sg:tags":[
        "electric",
        "contractor"
    ],
    "sg:website":"www.republicelectric.com",
    "wof:name":"Republic Electric",
    "wof:placetype":"venue"
},
  "geometry": {"coordinates":[-71.229691,42.370631],"type":"Point"}
}