{
  "type": "Feature",
  "properties": {
    "iso:country":"US",
    "sg:address":"26 Center St",
    "sg:city":"Chicopee",
    "sg:classifiers":[
        {
            "category":"Personal",
            "subcategory":"Beauty Salon",
            "type":"Services"
        }
    ],
    "sg:phone":"+1   ",
    "sg:postcode":"01013",
    "sg:province":"MA",
    "sg:tags":[
        "shop"
    ],
    "wof:name":"Diamond Nail",
    "wof:placetype":"venue"
},
  "geometry": {"coordinates":[-72.60729000000001,42.147026],"type":"Point"}
}