{
  "type": "Feature",
  "properties": {
    "addr:full": "49 Prospect St Waltham MA 02453",
    "addr:housenumber": "49",
    "addr:postcode": "02453",
    "addr:street": "Prospect St",
    "iso:country": "US",
    "ovtr:label": "Auto Systems, 49 Prospect St Waltham MA US",
    "ovtr:similarity": 2.3994429111480713,
    "sg:address": "49 Prospect St",
    "sg:city": "Waltham",
    "sg:classifiers": [
      {
        "category": "Retail",
        "subcategory": "Auto Repair",
        "type": "Services"
      }
    ],
    "sg:phone": "+1 781 899 8544",
    "sg:postcode": "02453",
    "sg:province": "MA",
    "sg:tags": [
      "muffler",
      "exhaust",
      "system"
    ],
    "wof:name": "Auto Systems",
    "wof:placetype": "venue"
  },
  "geometry": {"coordinates":[-71.246589,42.373826],"type":"Point"}
}
