{
  "type": "Feature",
  "properties": {
    "addr:full":"265 Willard St Quincy MA 02169",
    "addr:housenumber":"265",
    "addr:postcode":"02169",
    "addr:street":"Willard St",
    "iso:country":"US",
    "sg:address":"265 Willard St",
    "sg:city":"Quincy",
    "sg:classifiers":[
        {
            "category":"Building & Trades",
            "subcategory":"Construction",
            "type":"Services"
        }
    ],
    "sg:phone":"+1 617 770 0050",
    "sg:postcode":"02169",
    "sg:province":"MA",
    "sg:tags":[
        "home",
        "builder",
        "contractor"
    ],
    "sg:website":"www.combuild.com",
    "wof:name":"Commonwealth Building",
    "wof:placetype":"venue"
},
  "geometry": {"coordinates":[-71.032931,42.246794],"type":"Point"}
}