{
  "type": "Feature",
  "properties": {
    "addr:full":"111 Old Road To 9 Acre Cor Concord MA 01742",
    "addr:housenumber":"111",
    "addr:postcode":"01742",
    "addr:street":"Old Road To 9 Acre Cor",
    "iso:country":"US",
    "sg:address":"111 Old Road To 9 Acre Cor",
    "sg:city":"Concord",
    "sg:classifiers":[
        {
            "category":"Social Services",
            "subcategory":"Child Care",
            "type":"Services"
        }
    ],
    "sg:phone":"+1 978 369 3524",
    "sg:postcode":"01742",
    "sg:province":"MA",
    "sg:tags":[
        "nursery",
        "day"
    ],
    "wof:name":"Earyl Intervention Services",
    "wof:placetype":"venue"
},
  "geometry": {"coordinates":[-71.37629699999999,42.453623],"type":"Point"}
}