{
  "type": "Feature",
  "properties": {
    "addr:full":"552 Broadway Methuen MA 01844",
    "addr:housenumber":"552",
    "addr:postcode":"01844",
    "addr:street":"Broadway",
    "iso:country":"US",
    "sg:address":"552 Broadway",
    "sg:city":"Methuen",
    "sg:classifiers":[
        {
            "category":"Restaurant",
            "type":"Food & Drink"
        }
    ],
    "sg:phone":"+1 978 794 0908",
    "sg:postcode":"01844",
    "sg:province":"MA",
    "sg:tags":[
        "mexican"
    ],
    "sg:website":"http://methuen.plazaaztecanewengland.com/",
    "wof:name":"Plaza Azteca",
    "wof:placetype":"venue"
},
  "geometry": {"coordinates":[-71.19667,42.739791],"type":"Point"}
}