{
  "type": "Feature",
  "properties": {
    "iso:country":"US",
    "sg:address":"292 Western Ave",
    "sg:city":"Allston",
    "sg:classifiers":[
        {
            "category":"Building & Trades",
            "subcategory":"Locksmith",
            "type":"Services"
        }
    ],
    "sg:phone":"+1 617 782 5159",
    "sg:postcode":"02134",
    "sg:province":"MA",
    "sg:tags":[
        "key"
    ],
    "wof:name":"1 A 1 Emerg A Locks & Locksmith",
    "wof:placetype":"venue"
},
  "geometry": {"coordinates":[-71.134804,42.363201],"type":"Point"}
}