{
  "type": "Feature",
  "properties": {
    "iso:country":"US",
    "sg:address":"129 Camelot Dr",
    "sg:city":"Plymouth",
    "sg:classifiers":[
        {
            "category":"Wholesale",
            "subcategory":"Construction Materials",
            "type":"Manufacturing & Wholesale Goods"
        }
    ],
    "sg:phone":"+1 508 747 5485",
    "sg:postcode":"02360",
    "sg:province":"MA",
    "sg:tags":[
        "concrete",
        "product"
    ],
    "wof:name":"South Eastern Precast Steps",
    "wof:placetype":"venue"
},
  "geometry": {"coordinates":[-70.648573,41.925857],"type":"Point"}
}