{
  "type": "Feature",
  "properties": {
    "addr:full": "129 Camelot Dr Plymouth MA 02360",
    "addr:housenumber": "129",
    "addr:postcode": "02360",
    "addr:street": "Camelot Dr",
    "iso:country": "US",
    "sg:address": "129 Camelot Dr",
    "sg:city": "Plymouth",
    "sg:classifiers": [
      {
        "category": "Wholesale",
        "subcategory": "Construction Materials",
        "type": "Manufacturing \u0026 Wholesale Goods"
      }
    ],
    "sg:phone": "+1 508 747 5485",
    "sg:postcode": "02360",
    "sg:province": "MA",
    "sg:tags": [
      "concrete",
      "product"
    ],
    "wof:name": "South Eastern Precast Steps",
    "wof:placetype": "venue"
  },
  "geometry": {"coordinates":[-70.648573,41.925857],"type":"Point"}
}
