{
  "type": "Feature",
  "properties": {
    "iso:country":"US",
    "sg:address":"11 Tech Cir",
    "sg:city":"Natick",
    "sg:classifiers":[
        {
            "category":"Professional",
            "subcategory":"Management & Consulting",
            "type":"Services"
        }
    ],
    "sg:phone":"+1 508 655 5565",
    "sg:postcode":"01760",
    "sg:province":"MA",
    "sg:tags":[
        "consultant",
        "energy",
        "conservation"
    ],
    "sg:website":"www.busek.com",
    "wof:name":"Busek Inc",
    "wof:placetype":"venue"
},
  "geometry": {"coordinates":[-71.336119,42.314981],"type":"Point"}
}