{
  "type": "Feature",
  "properties": {
    "addr:full":"42 Main St Amesbury MA 01913",
    "addr:housenumber":"42",
    "addr:postcode":"01913",
    "addr:street":"Main St",
    "iso:country":"US",
    "sg:address":"42 Main St",
    "sg:city":"Amesbury",
    "sg:classifiers":[
        {
            "category":"Shopping",
            "subcategory":"Jewelry",
            "type":"Retail Goods"
        },
        {
            "category":"Shopping",
            "subcategory":"Gifts & Souvenirs",
            "type":"Retail Goods"
        }
    ],
    "sg:phone":"+1 978 388 2124",
    "sg:postcode":"01913",
    "sg:province":"MA",
    "sg:tags":[
        "shop",
        "stone",
        "semi-precious",
        "precious"
    ],
    "wof:name":"Maxwell Jewelers",
    "wof:placetype":"venue"
},
  "geometry": {"coordinates":[-70.930862,42.857182],"type":"Point"}
}