{
  "type": "Feature",
  "properties": {
    "addr:full":"18 Phoenix St Shirley MA 01464",
    "addr:housenumber":"18",
    "addr:postcode":"01464",
    "addr:street":"Phoenix St",
    "iso:country":"US",
    "sg:address":"18 Phoenix St",
    "sg:city":"Shirley",
    "sg:classifiers":[
        {
            "category":"Building & Trades",
            "subcategory":"Construction",
            "type":"Services"
        }
    ],
    "sg:phone":"+1 978 425 9635",
    "sg:postcode":"01464",
    "sg:province":"MA",
    "sg:tags":[
        "altering",
        "remodeling",
        "contractor"
    ],
    "wof:name":"Chesbroughs Remodeling",
    "wof:placetype":"venue"
},
  "geometry": {"coordinates":[-71.647789,42.542938],"type":"Point"}
}