{
  "type": "Feature",
  "properties": {
    "iso:country":"US",
    "sg:address":"17 Yetten Ter",
    "sg:city":"Waltham",
    "sg:classifiers":[
        {
            "category":"Home & Garden",
            "subcategory":"Carpets & Floor Coverings",
            "type":"Retail Goods"
        }
    ],
    "sg:phone":"+1 781 642 9776",
    "sg:postcode":"02453",
    "sg:province":"MA",
    "sg:tags":[
        "material"
    ],
    "wof:name":"Atlantis Flooring Co Inc",
    "wof:placetype":"venue"
},
  "geometry": {"coordinates":[-71.229181,42.369704],"type":"Point"}
}