{
  "type": "Feature",
  "properties": {
    "iso:country":"US",
    "sg:address":"292 Union St",
    "sg:city":"New Bedford",
    "sg:classifiers":[
        {
            "category":"Insurance",
            "subcategory":"Insurance Agent",
            "type":"Services"
        }
    ],
    "sg:phone":"+1   ",
    "sg:postcode":"02740",
    "sg:province":"MA",
    "sg:tags":[
        "security"
    ],
    "wof:name":"Barton Financial Ser",
    "wof:placetype":"venue"
},
  "geometry": {"coordinates":[-70.930122,41.633725],"type":"Point"}
}