{
  "type": "Feature",
  "properties": {
    "addr:full":"57 Plymouth St Holbrook MA 02343",
    "addr:housenumber":"57",
    "addr:postcode":"02343",
    "addr:street":"Plymouth St",
    "iso:country":"US",
    "sg:address":"57 Plymouth St",
    "sg:city":"Holbrook",
    "sg:classifiers":[
        {
            "category":"Retail",
            "subcategory":"Auto Rental",
            "type":"Services"
        }
    ],
    "sg:phone":"+1 781 767 1414",
    "sg:postcode":"02343",
    "sg:province":"MA",
    "sg:tags":[
        "renting",
        "automobile"
    ],
    "wof:name":"Basic Auto Rental",
    "wof:placetype":"venue"
},
  "geometry": {"coordinates":[-71.007184,42.154699],"type":"Point"}
}