{
  "type": "Feature",
  "properties": {
    "addr:full": "154 South St Pittsfield MA 01201",
    "addr:housenumber": "154",
    "addr:postcode": "01201",
    "addr:street": "South St",
    "iso:country": "US",
    "sg:address": "154 South St",
    "sg:city": "Pittsfield",
    "sg:classifiers": [
      {
        "category": "Wholesale",
        "subcategory": "Hardware",
        "type": "Manufacturing \u0026 Wholesale Goods"
      }
    ],
    "sg:phone": "+1 413 684 0808",
    "sg:postcode": "01201",
    "sg:province": "MA",
    "sg:tags": [
      "furnace"
    ],
    "wof:name": "Roland J Down Heating \u0026Cooling",
    "wof:placetype": "venue"
  },
  "geometry": {"coordinates":[-73.255123,42.444212],"type":"Point"}
}
