{
  "type": "Feature",
  "properties": {
    "iso:country":"US",
    "sg:address":"57 Merrill St",
    "sg:city":"Amesbury",
    "sg:classifiers":[
        {
            "category":"Professional",
            "subcategory":"Research",
            "type":"Services"
        }
    ],
    "sg:phone":"+1 978 388 6566",
    "sg:postcode":"01913",
    "sg:province":"MA",
    "sg:tags":[
        "environmental",
        "ecological"
    ],
    "wof:name":"Kairos Environmental",
    "wof:placetype":"venue"
},
  "geometry": {"coordinates":[-70.903555,42.841025],"type":"Point"}
}