{
  "type": "Feature",
  "properties": {
    "addr:full":"113 Great Rd Bedford MA 01730",
    "addr:housenumber":"113",
    "addr:postcode":"01730",
    "addr:street":"Great Rd",
    "iso:country":"US",
    "sg:address":"113 Great Rd",
    "sg:city":"Bedford",
    "sg:classifiers":[
        {
            "category":"Professional",
            "subcategory":"Lawyer & Legal Services",
            "type":"Services"
        }
    ],
    "sg:phone":"+1 781 271 9020",
    "sg:postcode":"01730",
    "sg:province":"MA",
    "wof:name":"Wall Robert Atty",
    "wof:placetype":"venue"
},
  "geometry": {"coordinates":[-71.27629899999999,42.490898],"type":"Point"}
}