{
  "type": "Feature",
  "properties": {
    "addr:full":"98 Taft Ave Swansea MA 02777",
    "addr:housenumber":"98",
    "addr:postcode":"02777",
    "addr:street":"Taft Ave",
    "iso:country":"US",
    "sg:address":"98 Taft Ave",
    "sg:city":"Swansea",
    "sg:classifiers":[
        {
            "category":"Personal",
            "subcategory":"Beauty Salon",
            "type":"Services"
        }
    ],
    "sg:phone":"+1   ",
    "sg:postcode":"02777",
    "sg:province":"MA",
    "sg:tags":[
        "shop"
    ],
    "wof:name":"Everythings Hair",
    "wof:placetype":"venue"
},
  "geometry": {"coordinates":[-71.21072599999999,41.752179],"type":"Point"}
}