{
  "type": "Feature",
  "properties": {
    "iso:country":"US",
    "sg:address":"40 Cottage St",
    "sg:city":"Easthampton",
    "sg:classifiers":[
        {
            "category":"Shopping",
            "type":"Retail Goods"
        }
    ],
    "sg:phone":"+1 413 529 9393",
    "sg:postcode":"01027",
    "sg:province":"MA",
    "sg:tags":[
        "art",
        "gallery",
        "dealer"
    ],
    "wof:name":"Nashawannuck Gallery",
    "wof:placetype":"venue"
},
  "geometry": {"coordinates":[-72.667984,42.265083],"type":"Point"}
}