{
  "type": "Feature",
  "properties": {
    "iso:country":"US",
    "sg:address":"424 Tyler St",
    "sg:city":"Pittsfield",
    "sg:classifiers":[
        {
            "category":"Wholesale",
            "subcategory":"Auto Parts",
            "type":"Manufacturing & Wholesale Goods"
        }
    ],
    "sg:phone":"+1 413 442 6060",
    "sg:postcode":"01201",
    "sg:province":"MA",
    "sg:tags":[
        "automobile",
        "supply"
    ],
    "wof:name":"Jacks Billards",
    "wof:placetype":"venue"
},
  "geometry": {"coordinates":[-73.241038,42.457337],"type":"Point"}
}