{
  "type": "Feature",
  "properties": {
    "iso:country":"US",
    "sg:address":"15 Jan Sebastian Dr",
    "sg:city":"Sandwich",
    "sg:classifiers":[
        {
            "category":"Building & Trades",
            "subcategory":"Landscaping Services",
            "type":"Services"
        }
    ],
    "sg:phone":"+1 508 888 6260",
    "sg:postcode":"02563",
    "sg:province":"MA",
    "sg:tags":[
        "tree"
    ],
    "wof:name":"Childs Arborists",
    "wof:placetype":"venue"
},
  "geometry": {"coordinates":[-70.48438299999999,41.71827],"type":"Point"}
}