{
  "type": "Feature",
  "properties": {
    "addr:full": "15 Jan Sebastian Dr Sandwich MA 02563",
    "addr:housenumber": "15",
    "addr:postcode": "02563",
    "addr:street": "Jan Sebastian Dr",
    "iso:country": "US",
    "sg:address": "15 Jan Sebastian Dr",
    "sg:city": "Sandwich",
    "sg:classifiers": [
      {
        "category": "Building \u0026 Trades",
        "subcategory": "Landscaping Services",
        "type": "Services"
      }
    ],
    "sg:phone": "+1 508 888 6260",
    "sg:postcode": "02563",
    "sg:province": "MA",
    "sg:tags": [
      "tree"
    ],
    "wof:name": "Childs Arborists",
    "wof:placetype": "venue"
  },
  "geometry": {"coordinates":[-70.484383,41.71827],"type":"Point"}
}
