{
  "type": "Feature",
  "properties": {
    "addr:full": "732 Crescent St Brockton MA 02302",
    "addr:housenumber": "732",
    "addr:postcode": "02302",
    "addr:street": "Crescent St",
    "iso:country": "US",
    "sg:address": "732 Crescent St",
    "sg:city": "Brockton",
    "sg:classifiers": [
      {
        "category": "Food \u0026 Beverages",
        "subcategory": "Meat \u0026 Fish",
        "type": "Retail Goods"
      }
    ],
    "sg:phone": "+1 508 588 8882",
    "sg:postcode": "02302",
    "sg:province": "MA",
    "wof:name": "Crossroad's Country Store",
    "wof:placetype": "venue"
  },
  "geometry": {"coordinates":[-70.989601,42.081297],"type":"Point"}
}
