{
  "type": "Feature",
  "properties": {
    "iso:country":"US",
    "sg:address":"One Jewel Dr Unit 1R",
    "sg:city":"Wilmington",
    "sg:classifiers":[
        {
            "category":"Sports & Exercise",
            "subcategory":"Playing Field",
            "type":"Entertainment"
        }
    ],
    "sg:phone":"+1 978 694 9678",
    "sg:postcode":"01887",
    "sg:province":"MA",
    "sg:tags":[
        "instruction",
        "fitness"
    ],
    "sg:website":"www.gymstreetusa.com/index.htm",
    "wof:name":"GymStreet USA",
    "wof:placetype":"venue"
},
  "geometry": {"coordinates":[-71.15661900000001,42.526428],"type":"Point"}
}