{
  "type": "Feature",
  "properties": {
    "iso:country":"US",
    "sg:address":"68 Bearskin Neck",
    "sg:city":"Rockport",
    "sg:classifiers":[
        {
            "category":"Restaurant",
            "type":"Food & Drink"
        }
    ],
    "sg:phone":"+1 978 546 9667",
    "sg:postcode":"01966",
    "sg:province":"MA",
    "sg:tags":[
        "banquet",
        "rooms"
    ],
    "wof:name":"My Place By The Sea",
    "wof:placetype":"venue"
},
  "geometry": {"coordinates":[-70.614521,42.660651],"type":"Point"}
}