{
  "type": "Feature",
  "properties": {
    "addr:full": "26 Ellis Rd Southbridge MA 01550",
    "addr:housenumber": "26",
    "addr:postcode": "01550",
    "addr:street": "Ellis Rd",
    "iso:country": "US",
    "sg:address": "26 Ellis Rd",
    "sg:city": "Southbridge",
    "sg:classifiers": [
      {
        "category": "Organizations",
        "subcategory": "Religious Organization",
        "type": "Services"
      }
    ],
    "sg:phone": "+1 508 764 2219",
    "sg:postcode": "01550",
    "sg:province": "MA",
    "sg:tags": [
      "church"
    ],
    "wof:name": "Full Gospel Ctr",
    "wof:placetype": "venue"
  },
  "geometry": {"coordinates":[-72.000194,42.089073],"type":"Point"}
}
