{
  "type": "Feature",
  "properties": {
    "iso:country":"US",
    "sg:address":"274 Hudson Rd",
    "sg:city":"Stow",
    "sg:classifiers":[
        {
            "category":"Real Estate",
            "subcategory":"Real Estate Agent",
            "type":"Services"
        }
    ],
    "sg:phone":"+1   ",
    "sg:postcode":"01775",
    "sg:province":"MA",
    "wof:name":"Tom Baccei",
    "wof:placetype":"venue"
},
  "geometry": {"coordinates":[-71.53928399999999,42.420513],"type":"Point"}
}