{
  "type": "Feature",
  "properties": {
    "addr:full":"67 Parker St Maynard MA 01754",
    "addr:housenumber":"67",
    "addr:postcode":"01754",
    "addr:street":"Parker St",
    "iso:country":"US",
    "sg:address":"67 Parker St",
    "sg:city":"Maynard",
    "sg:classifiers":[
        {
            "category":"Wholesale",
            "subcategory":"Metals & Minerals",
            "type":"Manufacturing & Wholesale Goods"
        }
    ],
    "sg:phone":"+1 978 897 7271",
    "sg:postcode":"01754",
    "sg:province":"MA",
    "sg:tags":[
        "pipe"
    ],
    "wof:name":"Butler Pipe",
    "wof:placetype":"venue"
},
  "geometry": {"coordinates":[-71.44956500000001,42.425892],"type":"Point"}
}