{
  "type": "Feature",
  "properties": {
    "iso:country":"US",
    "sg:address":"446 Boston Rd",
    "sg:city":"Billerica",
    "sg:classifiers":[
        {
            "category":"Personal",
            "subcategory":"Beauty Salon",
            "type":"Services"
        }
    ],
    "sg:phone":"+1 978 667 4690",
    "sg:postcode":"01821",
    "sg:province":"MA",
    "sg:tags":[
        "hair"
    ],
    "sg:website":"bellamiahairsalon.com",
    "wof:name":"Bella Mia",
    "wof:placetype":"venue"
},
  "geometry": {"coordinates":[-71.2677,42.557098],"type":"Point"}
}