{
  "type": "Feature",
  "properties": {
    "iso:country":"US",
    "sg:address":"335 Main St",
    "sg:city":"Reading",
    "sg:classifiers":[
        {
            "category":"Building & Trades",
            "subcategory":"Construction",
            "type":"Services"
        }
    ],
    "sg:phone":"+1 781 942 8880",
    "sg:postcode":"01867",
    "sg:province":"MA",
    "sg:tags":[
        "contractor"
    ],
    "wof:name":"Mottl Builders & Cabinetry Inc",
    "wof:placetype":"venue"
},
  "geometry": {"coordinates":[-71.10369900000001,42.516998],"type":"Point"}
}