{
  "type": "Feature",
  "properties": {
    "addr:full": "335 Main St Reading MA 01867",
    "addr:housenumber": "335",
    "addr:postcode": "01867",
    "addr:street": "Main St",
    "iso:country": "US",
    "sg:address": "335 Main St",
    "sg:city": "Reading",
    "sg:classifiers": [
      {
        "category": "Building \u0026 Trades",
        "subcategory": "Construction",
        "type": "Services"
      }
    ],
    "sg:phone": "+1 781 942 8880",
    "sg:postcode": "01867",
    "sg:province": "MA",
    "sg:tags": [
      "contractor"
    ],
    "wof:name": "Mottl Builders \u0026 Cabinetry Inc",
    "wof:placetype": "venue"
  },
  "geometry": {"coordinates":[-71.103699,42.516998],"type":"Point"}
}
