{
  "type": "Feature",
  "properties": {
    "addr:full":"58 Cummings Park Woburn MA 01801",
    "addr:housenumber":"58",
    "addr:postcode":"01801",
    "addr:street":"Cummings Park",
    "iso:country":"US",
    "sg:address":"58 Cummings Park",
    "sg:city":"Woburn",
    "sg:classifiers":[
        {
            "category":"Wholesale",
            "subcategory":"Farm Supplies",
            "type":"Manufacturing & Wholesale Goods"
        }
    ],
    "sg:phone":"+1 781 939 3147",
    "sg:postcode":"01801",
    "sg:province":"MA",
    "sg:tags":[
        "control",
        "equipment",
        "pest"
    ],
    "wof:name":"Univar USA",
    "wof:placetype":"venue"
},
  "geometry": {"coordinates":[-71.124251,42.497278],"type":"Point"}
}