{
  "type": "Feature",
  "properties": {
    "addr:full":"489 Broadway Cambridge MA 02138",
    "addr:housenumber":"489",
    "addr:postcode":"02138",
    "addr:street":"Broadway",
    "iso:country":"US",
    "sg:address":"489 Broadway",
    "sg:city":"Cambridge",
    "sg:classifiers":[
        {
            "category":"Government",
            "subcategory":"Police Station",
            "type":"Public Place"
        }
    ],
    "sg:phone":"+1 617 349 3300",
    "sg:postcode":"02138",
    "sg:province":"MA",
    "sg:tags":[
        "department"
    ],
    "wof:name":"Police Dept-Communications Ctr",
    "wof:placetype":"venue"
},
  "geometry": {"coordinates":[-71.115948,42.375598],"type":"Point"}
}