{
  "type": "Feature",
  "properties": {
    "addr:full": "907 Boylston St Boston MA 02115",
    "addr:housenumber": "907",
    "addr:postcode": "02115",
    "addr:street": "Boylston St",
    "iso:country": "US",
    "sg:address": "907 Boylston St",
    "sg:city": "Boston",
    "sg:classifiers": [
      {
        "category": "Bars \u0026 Pubs",
        "type": "Food \u0026 Drink"
      },
      {
        "category": "Restaurant",
        "type": "Food \u0026 Drink"
      }
    ],
    "sg:phone": "+1 617 236 1767",
    "sg:postcode": "02115",
    "sg:province": "MA",
    "sg:tags": [
      "traditional",
      "american"
    ],
    "sg:website": "www.pourhouseboston.com",
    "wof:name": "The Pour House",
    "wof:placetype": "venue"
  },
  "geometry": {"coordinates":[-71.084209,42.348232],"type":"Point"}
}
