{
  "type": "Feature",
  "properties": {
    "iso:country":"US",
    "sg:address":"907 Boylston St",
    "sg:city":"Boston",
    "sg:classifiers":[
        {
            "category":"Bars & Pubs",
            "type":"Food & Drink"
        },
        {
            "category":"Restaurant",
            "type":"Food & Drink"
        }
    ],
    "sg:phone":"+1 617 236 1767",
    "sg:postcode":"02115",
    "sg:province":"MA",
    "sg:tags":[
        "traditional",
        "american"
    ],
    "sg:website":"www.pourhouseboston.com",
    "wof:name":"The Pour House",
    "wof:placetype":"venue"
},
  "geometry": {"coordinates":[-71.084209,42.348232],"type":"Point"}
}