{
  "type": "Feature",
  "properties": {
    "iso:country":"US",
    "sg:address":"1740 Massachusetts Ave",
    "sg:city":"Lexington",
    "sg:classifiers":[
        {
            "category":"Personal",
            "subcategory":"Beauty Salon",
            "type":"Services"
        }
    ],
    "sg:phone":"+1 781 862 0300",
    "sg:postcode":"02421",
    "sg:province":"MA",
    "sg:tags":[
        "hair"
    ],
    "sg:website":"www.stephanielouissalon.com",
    "wof:name":"Stephanie Louis Salon",
    "wof:placetype":"venue"
},
  "geometry": {"coordinates":[-71.226896,42.447231],"type":"Point"}
}