{
  "type": "Feature",
  "properties": {
    "addr:full": "1740 Massachusetts Ave Lexington MA 02421",
    "addr:housenumber": "1740",
    "addr:postcode": "02421",
    "addr:street": "Massachusetts Ave",
    "iso:country": "US",
    "ovtr:label": "Stephanie Louis Salon, 1740 Massachusetts Ave Lexington MA US",
    "ovtr:similarity": 2.437359094619751,
    "sg:address": "1740 Massachusetts Ave",
    "sg:city": "Lexington",
    "sg:classifiers": [
      {
        "category": "Personal",
        "subcategory": "Beauty Salon",
        "type": "Services"
      }
    ],
    "sg:phone": "+1 781 862 0300",
    "sg:postcode": "02421",
    "sg:province": "MA",
    "sg:tags": [
      "hair"
    ],
    "sg:website": "www.stephanielouissalon.com",
    "wof:name": "Stephanie Louis Salon",
    "wof:placetype": "venue"
  },
  "geometry": {"coordinates":[-71.226896,42.447231],"type":"Point"}
}
