{
  "type": "Feature",
  "properties": {
    "addr:full": "8 S Deerfield Byp South Deerfield MA 01373",
    "addr:housenumber": "8",
    "addr:postcode": "01373",
    "addr:street": "S Deerfield Byp",
    "iso:country": "US",
    "sg:address": "8 S Deerfield Byp",
    "sg:city": "South Deerfield",
    "sg:classifiers": [
      {
        "category": "Personal",
        "subcategory": "Beauty Salon",
        "type": "Services"
      }
    ],
    "sg:phone": "+1 413 665 8707",
    "sg:postcode": "01373",
    "sg:province": "MA",
    "sg:tags": [
      "manicuring"
    ],
    "wof:name": "Get Nailed",
    "wof:placetype": "venue"
  },
  "geometry": {"coordinates":[-72.614489,42.471664],"type":"Point"}
}
