{
  "type": "Feature",
  "properties": {
    "iso:country":"US",
    "sg:address":"792 Parker St",
    "sg:city":"East Longmeadow",
    "sg:classifiers":[
        {
            "category":"Building & Trades",
            "subcategory":"Landscaping Services",
            "type":"Services"
        }
    ],
    "sg:phone":"+1 413 525 2624",
    "sg:postcode":"01028",
    "sg:province":"MA",
    "sg:tags":[
        "landscape",
        "contractor"
    ],
    "wof:name":"Clean Cut Landscaping",
    "wof:placetype":"venue"
},
  "geometry": {"coordinates":[-72.490977,42.086552],"type":"Point"}
}