{
  "type": "Feature",
  "properties": {
    "addr:full":"780 Boylston Street Suite 1 Boston MA 02199",
    "addr:housenumber":"780",
    "addr:postcode":"02199",
    "addr:street":"Boylston Street Suite 1",
    "iso:country":"US",
    "sg:address":"780 Boylston Street Suite 1",
    "sg:city":"Boston",
    "sg:classifiers":[
        {
            "category":"Health Services",
            "subcategory":"Doctor",
            "type":"Services"
        },
        {
            "category":"Sports & Exercise",
            "subcategory":"Gym",
            "type":"Entertainment"
        }
    ],
    "sg:phone":"+1 617 262 1500",
    "sg:postcode":"02199",
    "sg:province":"MA",
    "sg:tags":[
        "trainer"
    ],
    "wof:name":"Thomas H Emerson Phys",
    "wof:placetype":"venue"
},
  "geometry": {"coordinates":[-71.081626,42.348924],"type":"Point"}
}