{
  "type": "Feature",
  "properties": {
    "iso:country":"US",
    "sg:address":"9 Ashland Pl",
    "sg:city":"Taunton",
    "sg:classifiers":[
        {
            "category":"Education",
            "subcategory":"School",
            "type":"Public Place"
        }
    ],
    "sg:phone":"+1 508 822 2364",
    "sg:postcode":"02780",
    "sg:province":"MA",
    "wof:name":"Brick House School Inc",
    "wof:placetype":"venue"
},
  "geometry": {"coordinates":[-71.083516,41.905884],"type":"Point"}
}