{
  "type": "Feature",
  "properties": {
    "iso:country":"US",
    "sg:address":"4196 Washington St",
    "sg:city":"Roslindale",
    "sg:classifiers":[
        {
            "category":"Food & Beverages",
            "subcategory":"Groceries & Convenience Stores",
            "type":"Retail Goods"
        }
    ],
    "sg:phone":"+1 617 323 3163",
    "sg:postcode":"02131",
    "sg:province":"MA",
    "wof:name":"Li'l Peach",
    "wof:placetype":"venue"
},
  "geometry": {"coordinates":[-71.12683699999999,42.287644],"type":"Point"}
}