{
  "type": "Feature",
  "properties": {
    "addr:full": "219 Lewis Wharf Boston MA 02110",
    "addr:housenumber": "219",
    "addr:postcode": "02110",
    "addr:street": "Lewis Wharf",
    "iso:country": "US",
    "sg:address": "219 Lewis Wharf",
    "sg:city": "Boston",
    "sg:classifiers": [
      {
        "category": "Professional",
        "subcategory": "Lawyer \u0026 Legal Services",
        "type": "Services"
      }
    ],
    "sg:phone": "+1 617 723 5200",
    "sg:postcode": "02110",
    "sg:province": "MA",
    "wof:name": "McCarthy James P Atty",
    "wof:placetype": "venue"
  },
  "geometry": {"coordinates":[-71.050697,42.363701],"type":"Point"}
}
