{
  "type": "Feature",
  "properties": {
    "addr:full": "1112 Blue Hill Ave Dorchester Center MA 02124",
    "addr:housenumber": "1112",
    "addr:postcode": "02124",
    "addr:street": "Blue Hill Ave",
    "iso:country": "US",
    "sg:address": "1112 Blue Hill Ave",
    "sg:city": "Dorchester Center",
    "sg:classifiers": [
      {
        "category": "Building \u0026 Trades",
        "subcategory": "Locksmith",
        "type": "Services"
      }
    ],
    "sg:phone": "+1 617 514 9531",
    "sg:postcode": "02124",
    "sg:province": "MA",
    "sg:tags": [
      "key"
    ],
    "wof:name": "AAA Anytime Locksmith",
    "wof:placetype": "venue"
  },
  "geometry": {"coordinates":[-71.090467,42.28633],"type":"Point"}
}
