{
  "type": "Feature",
  "properties": {
    "iso:country":"US",
    "sg:address":"79 Old Mayfair Rd",
    "sg:city":"South Dennis",
    "sg:classifiers":[
        {
            "category":"Building & Trades",
            "subcategory":"Construction",
            "type":"Services"
        }
    ],
    "sg:phone":"+1 508 398 1511",
    "sg:postcode":"02660",
    "sg:province":"MA",
    "sg:tags":[
        "carpentry",
        "carpenter",
        "contractor"
    ],
    "wof:name":"Nunez Vasco Carpentry",
    "wof:placetype":"venue"
},
  "geometry": {"coordinates":[-70.17238999999999,41.69942],"type":"Point"}
}