{
  "type": "Feature",
  "properties": {
    "addr:full": "61 Water St Woburn MA 01801",
    "addr:housenumber": "61",
    "addr:postcode": "01801",
    "addr:street": "Water St",
    "iso:country": "US",
    "sg:address": "61 Water St",
    "sg:city": "Woburn",
    "sg:classifiers": [
      {
        "category": "Education",
        "subcategory": "School",
        "type": "Public Place"
      }
    ],
    "sg:phone": "+1   ",
    "sg:postcode": "01801",
    "sg:province": "MA",
    "wof:name": "Mother Natures Classroom",
    "wof:placetype": "venue"
  },
  "geometry": {"coordinates":[-71.161293,42.473565],"type":"Point"}
}
