{
  "type": "Feature",
  "properties": {
    "addr:full":"34 Paine St Worcester MA 01605",
    "addr:housenumber":"34",
    "addr:postcode":"01605",
    "addr:street":"Paine St",
    "iso:country":"US",
    "sg:address":"34 Paine St",
    "sg:city":"Worcester",
    "sg:classifiers":[
        {
            "category":"Manufacturing",
            "subcategory":"Motor Vehicles & Parts",
            "type":"Manufacturing & Wholesale Goods"
        }
    ],
    "sg:phone":"+1 508 799 5650",
    "sg:postcode":"01605",
    "sg:province":"MA",
    "sg:tags":[
        "car",
        "electric"
    ],
    "sg:website":"www.electricvehiclesystems.com",
    "wof:name":"Electric Vehicle Systems",
    "wof:placetype":"venue"
},
  "geometry": {"coordinates":[-71.79465500000001,42.279812],"type":"Point"}
}