{
  "type": "Feature",
  "properties": {
    "iso:country":"US",
    "sg:address":"59 S Pine St",
    "sg:city":"Haverhill",
    "sg:classifiers":[
        {
            "category":"Building & Trades",
            "subcategory":"Plumbing",
            "type":"Services"
        }
    ],
    "sg:phone":"+1 978 372 6139",
    "sg:postcode":"01835",
    "sg:province":"MA",
    "sg:tags":[
        "plumber",
        "industrial",
        "contractors-commercial"
    ],
    "wof:name":"P H D",
    "wof:placetype":"venue"
},
  "geometry": {"coordinates":[-71.073982,42.767804],"type":"Point"}
}