{
  "type": "Feature",
  "properties": {
    "addr:full": "140 Central St Auburn MA 01501",
    "addr:housenumber": "140",
    "addr:postcode": "01501",
    "addr:street": "Central St",
    "iso:country": "US",
    "sg:address": "140 Central St",
    "sg:city": "Auburn",
    "sg:classifiers": [
      {
        "category": "Education",
        "subcategory": "Library",
        "type": "Public Place"
      }
    ],
    "sg:phone": "+1 508 832 3977",
    "sg:postcode": "01501",
    "sg:province": "MA",
    "sg:tags": [
      "research"
    ],
    "wof:name": "LMS",
    "wof:placetype": "venue"
  },
  "geometry": {"coordinates":[-71.836024,42.194189],"type":"Point"}
}
