{
  "type": "Feature",
  "properties": {
    "iso:country":"US",
    "sg:address":"140 Central St",
    "sg:city":"Auburn",
    "sg:classifiers":[
        {
            "category":"Education",
            "subcategory":"Library",
            "type":"Public Place"
        }
    ],
    "sg:phone":"+1 508 832 3977",
    "sg:postcode":"01501",
    "sg:province":"MA",
    "sg:tags":[
        "research"
    ],
    "wof:name":"LMS",
    "wof:placetype":"venue"
},
  "geometry": {"coordinates":[-71.83602399999999,42.194189],"type":"Point"}
}