{
  "type": "Feature",
  "properties": {
    "iso:country":"US",
    "sg:address":"99 Lorna Rd",
    "sg:city":"Mattapan",
    "sg:classifiers":[
        {
            "category":"Organizations",
            "subcategory":"Membership Organization",
            "type":"Services"
        }
    ],
    "sg:phone":"+1   ",
    "sg:postcode":"02126",
    "sg:province":"MA",
    "wof:name":"Class of 61 Inc",
    "wof:placetype":"venue"
},
  "geometry": {"coordinates":[-71.086028,42.275946],"type":"Point"}
}