{
  "type": "Feature",
  "properties": {
    "iso:country":"US",
    "sg:address":"15 Robert St",
    "sg:city":"North Dartmouth",
    "sg:classifiers":[
        {
            "category":"Building & Trades",
            "subcategory":"Electrical",
            "type":"Services"
        }
    ],
    "sg:phone":"+1 508 997 2185",
    "sg:postcode":"02747",
    "sg:province":"MA",
    "sg:tags":[
        "electric",
        "contractor"
    ],
    "wof:name":"David Gonsalves Electric Inc",
    "wof:placetype":"venue"
},
  "geometry": {"coordinates":[-70.97185,41.637621],"type":"Point"}
}