{
  "type": "Feature",
  "properties": {
    "addr:full":"One Harborside Drive Terminal E, Logan Airport East Boston MA 02128",
    "addr:postcode":"02128",
    "addr:street":"Harborside Drive;E;East Boston",
    "iso:country":"US",
    "sg:address":"One Harborside Drive Terminal E, Logan Airport",
    "sg:city":"East Boston",
    "sg:classifiers":[
        {
            "category":"Restaurant",
            "type":"Food & Drink"
        }
    ],
    "sg:postcode":"02128",
    "sg:province":"MA",
    "wof:name":"Ozone",
    "wof:placetype":"venue"
},
  "geometry": {"coordinates":[-71.02770200000001,42.366901],"type":"Point"}
}