{
  "type": "Feature",
  "properties": {
    "iso:country":"US",
    "sg:address":"19 Walnut Rd",
    "sg:city":"Swampscott",
    "sg:classifiers":[
        {
            "category":"Professional",
            "type":"Services"
        }
    ],
    "sg:phone":"+1   ",
    "sg:postcode":"01907",
    "sg:province":"MA",
    "sg:tags":[
        "chemical",
        "consultant"
    ],
    "wof:name":"John Stemnishi Dr",
    "wof:placetype":"venue"
},
  "geometry": {"coordinates":[-70.903245,42.471404],"type":"Point"}
}