{
  "type": "Feature",
  "properties": {
    "iso:country":"US",
    "sg:address":"9 Snyder Rd",
    "sg:city":"Medfield",
    "sg:classifiers":[
        {
            "category":"Restaurant",
            "type":"Food & Drink"
        }
    ],
    "sg:phone":"+1 508 359 6893",
    "sg:postcode":"02052",
    "sg:province":"MA",
    "wof:name":"Sum & Harrington Associates Inc",
    "wof:placetype":"venue"
},
  "geometry": {"coordinates":[-71.301361,42.153259],"type":"Point"}
}