{
  "type": "Feature",
  "properties": {
    "addr:full": "66 Park Ave Three Rivers MA 01080",
    "addr:housenumber": "66",
    "addr:postcode": "01080",
    "addr:street": "Park Ave",
    "iso:country": "US",
    "sg:address": "66 Park Ave",
    "sg:city": "Three Rivers",
    "sg:classifiers": [
      {
        "category": "Building \u0026 Trades",
        "subcategory": "Construction",
        "type": "Services"
      }
    ],
    "sg:phone": "+1 413 283 4438",
    "sg:postcode": "01080",
    "sg:province": "MA",
    "sg:tags": [
      "resurfacing",
      "laying",
      "refinishing",
      "floor"
    ],
    "wof:name": "Custom Wood Floors",
    "wof:placetype": "venue"
  },
  "geometry": {"coordinates":[-72.366352,42.178742],"type":"Point"}
}
