{
  "type": "Feature",
  "properties": {
    "iso:country":"US",
    "sg:address":"66 Park Ave",
    "sg:city":"Three Rivers",
    "sg:classifiers":[
        {
            "category":"Building & Trades",
            "subcategory":"Construction",
            "type":"Services"
        }
    ],
    "sg:phone":"+1 413 283 4438",
    "sg:postcode":"01080",
    "sg:province":"MA",
    "sg:tags":[
        "resurfacing",
        "laying",
        "refinishing",
        "floor"
    ],
    "wof:name":"Custom Wood Floors",
    "wof:placetype":"venue"
},
  "geometry": {"coordinates":[-72.36635200000001,42.178742],"type":"Point"}
}