{
  "type": "Feature",
  "properties": {
    "addr:full":"21 Beacon St Boston MA 02108",
    "addr:housenumber":"21",
    "addr:postcode":"02108",
    "addr:street":"Beacon St",
    "iso:country":"US",
    "sg:address":"21 Beacon St",
    "sg:city":"Boston",
    "sg:classifiers":[
        {
            "category":"Professional",
            "type":"Services"
        }
    ],
    "sg:phone":"+1 617 720 2454",
    "sg:postcode":"02108",
    "sg:province":"MA",
    "sg:tags":[
        "establishment"
    ],
    "wof:name":"KNOX V",
    "wof:placetype":"venue"
},
  "geometry": {"coordinates":[-71.061663,42.3584],"type":"Point"}
}