{
  "type": "Feature",
  "properties": {
    "iso:country":"US",
    "sg:address":"17 Hamilton Ave",
    "sg:city":"South Hamilton",
    "sg:classifiers":[
        {
            "category":"Professional",
            "subcategory":"Business Services",
            "type":"Services"
        }
    ],
    "sg:phone":"+1   ",
    "sg:postcode":"01982",
    "sg:province":"MA",
    "wof:name":"K J Donovan & Co Inc",
    "wof:placetype":"venue"
},
  "geometry": {"coordinates":[-70.875631,42.612958],"type":"Point"}
}