{
  "type": "Feature",
  "properties": {
    "addr:full": "17 Hamilton Ave South Hamilton MA 01982",
    "addr:housenumber": "17",
    "addr:postcode": "01982",
    "addr:street": "Hamilton Ave South",
    "iso:country": "US",
    "sg:address": "17 Hamilton Ave",
    "sg:city": "South Hamilton",
    "sg:classifiers": [
      {
        "category": "Professional",
        "subcategory": "Business Services",
        "type": "Services"
      }
    ],
    "sg:phone": "+1   ",
    "sg:postcode": "01982",
    "sg:province": "MA",
    "wof:name": "K J Donovan \u0026 Co Inc",
    "wof:placetype": "venue"
  },
  "geometry": {"coordinates":[-70.875631,42.612958],"type":"Point"}
}
