{
  "type": "Feature",
  "properties": {
    "addr:full":"31 Germania St Jamaica Plain MA 02130",
    "addr:housenumber":"31",
    "addr:postcode":"02130",
    "addr:street":"Germania St",
    "iso:country":"US",
    "sg:address":"31 Germania St",
    "sg:city":"Jamaica Plain",
    "sg:classifiers":[
        {
            "category":"Retail",
            "subcategory":"Repair Shop",
            "type":"Services"
        }
    ],
    "sg:phone":"+1 617 326 0801",
    "sg:postcode":"02130",
    "sg:province":"MA",
    "sg:tags":[
        "lock",
        "locksmith"
    ],
    "wof:name":"24 Hr Emergency Locksmith",
    "wof:placetype":"venue"
},
  "geometry": {"coordinates":[-71.102238,42.314091],"type":"Point"}
}