{
  "type": "Feature",
  "properties": {
    "addr:full":"99 Huntoon Memorial Hwy Rochdale MA 01542",
    "addr:housenumber":"99",
    "addr:postcode":"01542",
    "addr:street":"Huntoon Memorial Hwy",
    "iso:country":"US",
    "sg:address":"99 Huntoon Memorial Hwy",
    "sg:city":"Rochdale",
    "sg:classifiers":[
        {
            "category":"Freight",
            "type":"Transportation"
        }
    ],
    "sg:phone":"+1 508 791 1490",
    "sg:postcode":"01542",
    "sg:province":"MA",
    "sg:tags":[
        "mover"
    ],
    "sg:website":"www.libertymovers.com",
    "wof:name":"Liberty Movers Inc",
    "wof:placetype":"venue"
},
  "geometry": {"coordinates":[-71.907366,42.210377],"type":"Point"}
}