{
  "type": "Feature",
  "properties": {
    "iso:country":"US",
    "sg:address":"60 Cedar Ln",
    "sg:city":"Orleans",
    "sg:classifiers":[
        {
            "category":"Retail",
            "subcategory":"Repair Shop",
            "type":"Services"
        }
    ],
    "sg:phone":"+1 508 255 1863",
    "sg:postcode":"02642",
    "sg:province":"MA",
    "wof:name":"Town Cove Heating",
    "wof:placetype":"venue"
},
  "geometry": {"coordinates":[-69.975802,41.805589],"type":"Point"}
}