{
  "type": "Feature",
  "properties": {
    "addr:full": "4 Fernwood Dr Rutland MA 01543",
    "addr:housenumber": "4",
    "addr:postcode": "01543",
    "addr:street": "Fernwood Dr",
    "iso:country": "US",
    "sg:address": "4 Fernwood Dr",
    "sg:city": "Rutland",
    "sg:classifiers": [
      {
        "category": "Home \u0026 Garden",
        "subcategory": "Building Materials",
        "type": "Retail Goods"
      }
    ],
    "sg:phone": "+1 508 886 6943",
    "sg:postcode": "01543",
    "sg:province": "MA",
    "sg:tags": [
      "siding"
    ],
    "wof:name": "Dkat Siding",
    "wof:placetype": "venue"
  },
  "geometry": {"coordinates":[-71.936978,42.36879],"type":"Point"}
}
