{
  "type": "Feature",
  "properties": {
    "addr:full": "45 Boston St Lynn MA 01904",
    "addr:housenumber": "45",
    "addr:postcode": "01904",
    "addr:street": "Boston St",
    "iso:country": "US",
    "sg:address": "45 Boston St",
    "sg:city": "Lynn",
    "sg:classifiers": [
      {
        "category": "Wholesale",
        "subcategory": "Auto Parts",
        "type": "Manufacturing \u0026 Wholesale Goods"
      }
    ],
    "sg:phone": "+1 781 599 3792",
    "sg:postcode": "01904",
    "sg:province": "MA",
    "sg:tags": [
      "automobile",
      "supply"
    ],
    "wof:name": "Mahan's",
    "wof:placetype": "venue"
  },
  "geometry": {"coordinates":[-70.956888,42.477821],"type":"Point"}
}
