{
  "type": "Feature",
  "properties": {
    "iso:country":"US",
    "sg:address":"45 Boston St",
    "sg:city":"Lynn",
    "sg:classifiers":[
        {
            "category":"Wholesale",
            "subcategory":"Auto Parts",
            "type":"Manufacturing & Wholesale Goods"
        }
    ],
    "sg:phone":"+1 781 599 3792",
    "sg:postcode":"01904",
    "sg:province":"MA",
    "sg:tags":[
        "automobile",
        "supply"
    ],
    "wof:name":"Mahan's",
    "wof:placetype":"venue"
},
  "geometry": {"coordinates":[-70.95688800000001,42.477821],"type":"Point"}
}