{
  "type": "Feature",
  "properties": {
    "addr:full": "411 North St Walpole MA 02081",
    "addr:housenumber": "411",
    "addr:postcode": "02081",
    "addr:street": "North St",
    "iso:country": "US",
    "sg:address": "411 North St",
    "sg:city": "Walpole",
    "sg:classifiers": [
      {
        "category": "Building \u0026 Trades",
        "subcategory": "Construction",
        "type": "Services"
      }
    ],
    "sg:phone": "+1   ",
    "sg:postcode": "02081",
    "sg:province": "MA",
    "sg:tags": [
      "house"
    ],
    "wof:name": "Hunter Homes Corp",
    "wof:placetype": "venue"
  },
  "geometry": {"coordinates":[-71.252149,42.168301],"type":"Point"}
}
