{
  "type": "Feature",
  "properties": {
    "addr:full":"330 Union St New Bedford MA 02740",
    "addr:housenumber":"330",
    "addr:postcode":"02740",
    "addr:street":"Union St",
    "iso:country":"US",
    "sg:address":"330 Union St",
    "sg:city":"New Bedford",
    "sg:classifiers":[
        {
            "category":"Health Services",
            "subcategory":"Health Practitioner",
            "type":"Services"
        }
    ],
    "sg:phone":"+1 508 991 7488",
    "sg:postcode":"02740",
    "sg:province":"MA",
    "sg:tags":[
        "acupuncture"
    ],
    "wof:name":"Acupuncture Associates-E Mass",
    "wof:placetype":"venue"
},
  "geometry": {"coordinates":[-70.932912,41.633448],"type":"Point"}
}