{
  "type": "Feature",
  "properties": {
    "addr:full":"299 Hartford Pike Shrewsbury MA 01545",
    "addr:housenumber":"299",
    "addr:postcode":"01545",
    "addr:street":"Hartford Pike",
    "iso:country":"US",
    "sg:address":"299 Hartford Pike",
    "sg:city":"Shrewsbury",
    "sg:classifiers":[
        {
            "category":"Utilities",
            "subcategory":"Telephone",
            "type":"Services"
        }
    ],
    "sg:phone":"+1 508 798 9920",
    "sg:postcode":"01545",
    "sg:province":"MA",
    "sg:tags":[
        "company"
    ],
    "wof:name":"Pyramid Telecommunication Svc",
    "wof:placetype":"venue"
},
  "geometry": {"coordinates":[-71.71641099999999,42.249356],"type":"Point"}
}