{
  "type": "Feature",
  "properties": {
    "iso:country":"US",
    "sg:address":"1 Union Pl",
    "sg:city":"Braintree",
    "sg:classifiers":[
        {
            "category":"Government",
            "subcategory":"Fire Station",
            "type":"Public Place"
        }
    ],
    "sg:phone":"+1 781 843 3600",
    "sg:postcode":"02184",
    "sg:province":"MA",
    "sg:tags":[
        "department"
    ],
    "wof:name":"Braintree Fire Dept",
    "wof:placetype":"venue"
},
  "geometry": {"coordinates":[-71.0042,42.207119],"type":"Point"}
}