{
  "type": "Feature",
  "properties": {
    "addr:full":"375 Common St Lawrence MA 01840",
    "addr:housenumber":"375",
    "addr:postcode":"01840",
    "addr:street":"Common",
    "iso:country":"US",
    "sg:address":"375 Common St",
    "sg:city":"Lawrence",
    "sg:classifiers":[
        {
            "category":"Professional",
            "subcategory":"Engineering",
            "type":"Services"
        }
    ],
    "sg:phone":"+1   ",
    "sg:postcode":"01840",
    "sg:province":"MA",
    "wof:name":"Hajec Assoc",
    "wof:placetype":"venue"
},
  "geometry": {"coordinates":[-71.164649,42.7074],"type":"Point"}
}