{
  "type": "Feature",
  "properties": {
    "addr:full": "5 Tidd Cir Lexington MA 02420",
    "addr:housenumber": "5",
    "addr:postcode": "02420",
    "addr:street": "Tidd Cir",
    "iso:country": "US",
    "sg:address": "5 Tidd Cir",
    "sg:city": "Lexington",
    "sg:classifiers": [
      {
        "category": "Social Services",
        "subcategory": "Child Care",
        "type": "Services"
      }
    ],
    "sg:phone": "+1 781 863 5390",
    "sg:postcode": "02420",
    "sg:province": "MA",
    "sg:tags": [
      "school",
      "program",
      "after"
    ],
    "wof:name": "Lexington Kumon Math \u0026 Reading",
    "wof:placetype": "venue"
  },
  "geometry": {"coordinates":[-71.233842,42.472225],"type":"Point"}
}
