{
  "type": "Feature",
  "properties": {
    "iso:country":"US",
    "sg:address":"19 Lincoln St",
    "sg:city":"Newton",
    "sg:classifiers":[
        {
            "category":"Personal",
            "subcategory":"Beauty Salon",
            "type":"Services"
        }
    ],
    "sg:phone":"+1 617 527 8753",
    "sg:postcode":"02461",
    "sg:province":"MA",
    "wof:name":"Angelo's Barber Shop",
    "wof:placetype":"venue"
},
  "geometry": {"coordinates":[-71.20719200000001,42.321638],"type":"Point"}
}