{
  "type": "Feature",
  "properties": {
    "addr:full": "254 Turnpike Rd Westborough MA 01581",
    "addr:housenumber": "254",
    "addr:postcode": "01581",
    "addr:street": "Turnpike Rd",
    "iso:country": "US",
    "sg:address": "254 Turnpike Rd",
    "sg:city": "Westborough",
    "sg:classifiers": [
      {
        "category": "Home \u0026 Garden",
        "subcategory": "Garden Supply",
        "type": "Retail Goods"
      }
    ],
    "sg:phone": "+1 508 366 5478",
    "sg:postcode": "01581",
    "sg:province": "MA",
    "sg:tags": [
      "center"
    ],
    "wof:name": "Hardwicke Gardens Statuary",
    "wof:placetype": "venue"
  },
  "geometry": {"coordinates":[-71.646215,42.283091],"type":"Point"}
}
