{
  "type": "Feature",
  "properties": {
    "addr:full":"21 June St Worcester MA 01602",
    "addr:housenumber":"21",
    "addr:postcode":"01602",
    "addr:street":"June St",
    "iso:country":"US",
    "sg:address":"21 June St",
    "sg:city":"Worcester",
    "sg:classifiers":[
        {
            "category":"Education",
            "subcategory":"Special Training",
            "type":"Public Place"
        }
    ],
    "sg:phone":"+1   ",
    "sg:postcode":"01602",
    "sg:province":"MA",
    "wof:name":"Learning Skills Institute Inc",
    "wof:placetype":"venue"
},
  "geometry": {"coordinates":[-71.827493,42.268555],"type":"Point"}
}