{
  "type": "Feature",
  "properties": {
    "iso:country":"US",
    "sg:address":"1261 Hyde Park Ave",
    "sg:city":"Hyde Park",
    "sg:classifiers":[
        {
            "category":"Manufacturing",
            "subcategory":"Printing",
            "type":"Manufacturing & Wholesale Goods"
        }
    ],
    "sg:phone":"+1 617 361 6500",
    "sg:postcode":"02136",
    "sg:province":"MA",
    "sg:tags":[
        "newspaper"
    ],
    "wof:name":"Tribune Publishing Co",
    "wof:placetype":"venue"
},
  "geometry": {"coordinates":[-71.124139,42.256122],"type":"Point"}
}