{
  "type": "Feature",
  "properties": {
    "addr:full": "223 Newbury St Boston MA 02116",
    "addr:housenumber": "223",
    "addr:postcode": "02116",
    "addr:street": "Newbury St",
    "iso:country": "US",
    "sg:address": "223 Newbury St",
    "sg:city": "Boston",
    "sg:classifiers": [
      {
        "category": "Shopping",
        "subcategory": "Clothing, Apparel, \u0026 Fashions",
        "type": "Retail Goods"
      },
      {
        "category": "Shopping",
        "subcategory": "Jewelry",
        "type": "Retail Goods"
      }
    ],
    "sg:phone": "+1 617 421 8637",
    "sg:postcode": "02116",
    "sg:province": "MA",
    "sg:tags": [
      "clothing",
      "women's"
    ],
    "sg:website": "www.litboutique.com",
    "wof:name": "LIT on Newbury",
    "wof:placetype": "venue"
  },
  "geometry": {"coordinates":[-71.0816,42.3501],"type":"Point"}
}
