{
  "type": "Feature",
  "properties": {
    "addr:full":"90 Orne St North Attleboro MA 02760",
    "addr:housenumber":"90",
    "addr:postcode":"02760",
    "addr:street":"Orne St",
    "iso:country":"US",
    "sg:address":"90 Orne St",
    "sg:city":"North Attleboro",
    "sg:classifiers":[
        {
            "category":"Personal",
            "subcategory":"Hair Removal",
            "type":"Services"
        }
    ],
    "sg:phone":"+1 508 643 8100",
    "sg:postcode":"02760",
    "sg:province":"MA",
    "sg:tags":[
        "removing"
    ],
    "wof:name":"Laser Connection",
    "wof:placetype":"venue"
},
  "geometry": {"coordinates":[-71.330924,41.983098],"type":"Point"}
}