{
  "type": "Feature",
  "properties": {
    "addr:full": "51 Fox Meadow Rd Leominster MA 01453",
    "addr:housenumber": "51",
    "addr:postcode": "01453",
    "addr:street": "Fox Meadow Rd",
    "iso:country": "US",
    "sg:address": "51 Fox Meadow Rd",
    "sg:city": "Leominster",
    "sg:classifiers": [
      {
        "category": "Government",
        "subcategory": "Office",
        "type": "Public Place"
      }
    ],
    "sg:phone": "+1   ",
    "sg:postcode": "01453",
    "sg:province": "MA",
    "sg:tags": [
      "safety",
      "order"
    ],
    "wof:name": "Ahmed PHD Fazal",
    "wof:placetype": "venue"
  },
  "geometry": {"coordinates":[-71.747293,42.553718],"type":"Point"}
}
