{
  "type": "Feature",
  "properties": {
    "iso:country":"US",
    "sg:address":"51 Fox Meadow Rd",
    "sg:city":"Leominster",
    "sg:classifiers":[
        {
            "category":"Government",
            "subcategory":"Office",
            "type":"Public Place"
        }
    ],
    "sg:phone":"+1   ",
    "sg:postcode":"01453",
    "sg:province":"MA",
    "sg:tags":[
        "safety",
        "order"
    ],
    "wof:name":"Ahmed PHD Fazal",
    "wof:placetype":"venue"
},
  "geometry": {"coordinates":[-71.747293,42.553718],"type":"Point"}
}