{
  "type": "Feature",
  "properties": {
    "addr:full": "97 Webster Ct Worcester MA 01603",
    "addr:housenumber": "97",
    "addr:postcode": "01603",
    "addr:street": "Webster Ct",
    "iso:country": "US",
    "sg:address": "97 Webster Ct",
    "sg:city": "Worcester",
    "sg:classifiers": [
      {
        "category": "Professional",
        "type": "Services"
      }
    ],
    "sg:phone": "+1 508 757 6197",
    "sg:postcode": "01603",
    "sg:province": "MA",
    "sg:tags": [
      "establishment"
    ],
    "wof:name": "Blindsight Sculpture",
    "wof:placetype": "venue"
  },
  "geometry": {"coordinates":[-71.833064,42.24266],"type":"Point"}
}
