{
  "type": "Feature",
  "properties": {
    "iso:country":"US",
    "sg:address":"1837 Columbus Ave",
    "sg:city":"Boston",
    "sg:classifiers":[
        {
            "category":"Autos & Motor Vehicles",
            "subcategory":"Auto Supplies",
            "type":"Retail Goods"
        }
    ],
    "sg:phone":"+1 617 442 7711",
    "sg:postcode":"02119",
    "sg:province":"MA",
    "sg:tags":[
        "equipment",
        "racing",
        "car",
        "automobile"
    ],
    "wof:name":"Motion Motor Sports Inc",
    "wof:placetype":"venue"
},
  "geometry": {"coordinates":[-71.0985,42.320336],"type":"Point"}
}