{
  "type": "Feature",
  "properties": {
    "addr:full": "27 Bronson Ter Springfield MA 01108",
    "addr:housenumber": "27",
    "addr:postcode": "01108",
    "addr:street": "Bronson Ter",
    "iso:country": "US",
    "sg:address": "27 Bronson Ter",
    "sg:city": "Springfield",
    "sg:classifiers": [
      {
        "category": "Professional",
        "subcategory": "Management \u0026 Consulting",
        "type": "Services"
      }
    ],
    "sg:phone": "+1 413 732 2922",
    "sg:postcode": "01108",
    "sg:province": "MA",
    "sg:tags": [
      "marketing",
      "consultant"
    ],
    "wof:name": "Marketrend Interactive",
    "wof:placetype": "venue"
  },
  "geometry": {"coordinates":[-72.556014,42.078372],"type":"Point"}
}
