{
  "type": "Feature",
  "properties": {
    "addr:full":"52 Glendale Ave Northampton MA 01060",
    "addr:housenumber":"52",
    "addr:postcode":"01060",
    "addr:street":"Glendale Ave",
    "iso:country":"US",
    "sg:address":"52 Glendale Ave",
    "sg:city":"Northampton",
    "sg:classifiers":[
        {
            "category":"Freight",
            "type":"Transportation"
        }
    ],
    "sg:phone":"+1   ",
    "sg:postcode":"01060",
    "sg:province":"MA",
    "sg:tags":[
        "operator",
        "local",
        "trucking"
    ],
    "wof:name":"B N B Waste Services",
    "wof:placetype":"venue"
},
  "geometry": {"coordinates":[-72.639831,42.32747],"type":"Point"}
}