{
  "type": "Feature",
  "properties": {
    "addr:full": "44 Broadway Salisbury MA 01952",
    "addr:housenumber": "44",
    "addr:postcode": "01952",
    "addr:street": "Broadway",
    "iso:country": "US",
    "sg:address": "44 Broadway",
    "sg:city": "Salisbury",
    "sg:classifiers": [
      {
        "category": "Bars \u0026 Pubs",
        "type": "Food \u0026 Drink"
      }
    ],
    "sg:phone": "+1   ",
    "sg:postcode": "01952",
    "sg:province": "MA",
    "sg:tags": [
      "drinking"
    ],
    "wof:name": "Normandy Lounge",
    "wof:placetype": "venue"
  },
  "geometry": {"coordinates":[-70.81685,42.842518],"type":"Point"}
}
