{
  "type": "Feature",
  "properties": {
    "iso:country":"US",
    "sg:address":"44 Broadway",
    "sg:city":"Salisbury",
    "sg:classifiers":[
        {
            "category":"Bars & Pubs",
            "type":"Food & Drink"
        }
    ],
    "sg:phone":"+1   ",
    "sg:postcode":"01952",
    "sg:province":"MA",
    "sg:tags":[
        "drinking"
    ],
    "wof:name":"Normandy Lounge",
    "wof:placetype":"venue"
},
  "geometry": {"coordinates":[-70.81685,42.842518],"type":"Point"}
}