{
  "type": "Feature",
  "properties": {
    "iso:country":"US",
    "sg:address":"20 Lillypond Ln",
    "sg:city":"Halifax",
    "sg:classifiers":[
        {
            "category":"Building & Trades",
            "subcategory":"Construction",
            "type":"Services"
        }
    ],
    "sg:phone":"+1 781 294 1367",
    "sg:postcode":"02338",
    "sg:province":"MA",
    "sg:tags":[
        "general",
        "contractor"
    ],
    "wof:name":"Top Notch Building & Remodelng",
    "wof:placetype":"venue"
},
  "geometry": {"coordinates":[-70.885588,41.985419],"type":"Point"}
}