{
  "type": "Feature",
  "properties": {
    "addr:full":"156 Church St Pembroke MA 02359",
    "addr:housenumber":"156",
    "addr:postcode":"02359",
    "addr:street":"Church St",
    "iso:country":"US",
    "sg:address":"156 Church St",
    "sg:city":"Pembroke",
    "sg:classifiers":[
        {
            "category":"Shopping",
            "type":"Retail Goods"
        }
    ],
    "sg:phone":"+1   ",
    "sg:postcode":"02359",
    "sg:province":"MA",
    "sg:tags":[
        "merchandise"
    ],
    "wof:name":"Mas Audiology",
    "wof:placetype":"venue"
},
  "geometry": {"coordinates":[-70.770078,42.107828],"type":"Point"}
}