{
  "type": "Feature",
  "properties": {
    "iso:country":"US",
    "sg:address":"378 Pleasant St",
    "sg:city":"East Bridgewater",
    "sg:classifiers":[
        {
            "category":"Wholesale",
            "subcategory":"Meat",
            "type":"Manufacturing & Wholesale Goods"
        }
    ],
    "sg:phone":"+1 508 580 5646",
    "sg:postcode":"02333",
    "sg:province":"MA",
    "wof:name":"D'Andrea Foods Inc",
    "wof:placetype":"venue"
},
  "geometry": {"coordinates":[-70.983097,42.040741],"type":"Point"}
}