{
  "type": "Feature",
  "properties": {
    "addr:full":"69 Main St Lakeville MA 02347",
    "addr:housenumber":"69",
    "addr:postcode":"02347",
    "addr:street":"Main St",
    "iso:country":"US",
    "sg:address":"69 Main St",
    "sg:city":"Lakeville",
    "sg:classifiers":[
        {
            "category":"Health Services",
            "subcategory":"Clinic",
            "type":"Services"
        }
    ],
    "sg:phone":"+1 508 245 8618",
    "sg:postcode":"02347",
    "sg:province":"MA",
    "sg:tags":[
        "holistic",
        "practitioner"
    ],
    "wof:name":"Reiki Associates",
    "wof:placetype":"venue"
},
  "geometry": {"coordinates":[-70.931181,41.870656],"type":"Point"}
}