{
  "type": "Feature",
  "properties": {
    "addr:full":"260 Elm St Somerville MA 02144",
    "addr:housenumber":"260",
    "addr:postcode":"02144",
    "addr:street":"Elm St",
    "iso:country":"US",
    "sg:address":"260 Elm St",
    "sg:city":"Somerville",
    "sg:classifiers":[
        {
            "category":"Professional",
            "type":"Services"
        }
    ],
    "sg:phone":"+1 617 623 4156",
    "sg:postcode":"02144",
    "sg:province":"MA",
    "sg:tags":[
        "establishment"
    ],
    "wof:name":"Tsao Yo Fang Refinances",
    "wof:placetype":"venue"
},
  "geometry": {"coordinates":[-71.12142299999999,42.394734],"type":"Point"}
}