{
  "type": "Feature",
  "properties": {
    "iso:country":"US",
    "sg:address":"698 Eastern Ave",
    "sg:city":"Malden",
    "sg:classifiers":[
        {
            "category":"Freight",
            "type":"Transportation"
        }
    ],
    "sg:phone":"+1 781 321 0956",
    "sg:postcode":"02148",
    "sg:province":"MA",
    "sg:tags":[
        "mover"
    ],
    "wof:name":"ABC Moving Svc Inc",
    "wof:placetype":"venue"
},
  "geometry": {"coordinates":[-71.048072,42.429794],"type":"Point"}
}