{
  "type": "Feature",
  "properties": {
    "addr:full": "2 Auburn Sq Charlestown MA 02129",
    "addr:housenumber": "2",
    "addr:postcode": "02129",
    "addr:street": "Auburn Sq",
    "iso:country": "US",
    "sg:address": "2 Auburn Sq",
    "sg:city": "Charlestown",
    "sg:classifiers": [
      {
        "category": "Banks \u0026 Credit Unions",
        "subcategory": "Bank",
        "type": "Services"
      }
    ],
    "sg:phone": "+1 617 242 1851",
    "sg:postcode": "02129",
    "sg:province": "MA",
    "sg:tags": [
      "mortgage",
      "loan",
      "broker",
      "real estate"
    ],
    "wof:name": "Charlestown Mortgage",
    "wof:placetype": "venue"
  },
  "geometry": {"coordinates":[-71.069168,42.381347],"type":"Point"}
}
