{
  "type": "Feature",
  "properties": {
    "iso:country":"US",
    "sg:address":"1539 Blue Hill Ave",
    "sg:city":"Mattapan",
    "sg:classifiers":[
        {
            "category":"Professional",
            "subcategory":"Lawyer & Legal Services",
            "type":"Services"
        }
    ],
    "sg:phone":"+1 617 296 0900",
    "sg:postcode":"02126",
    "sg:province":"MA",
    "sg:tags":[
        "attorney"
    ],
    "wof:name":"Nunotte Zama Law Offices",
    "wof:placetype":"venue"
},
  "geometry": {"coordinates":[-71.09378100000001,42.269917],"type":"Point"}
}