{
  "type": "Feature",
  "properties": {
    "addr:full": "63 Union Sq Somerville MA 02143",
    "addr:housenumber": "63",
    "addr:postcode": "02143",
    "addr:street": "Union Sq",
    "iso:country": "US",
    "sg:address": "63 Union Sq",
    "sg:city": "Somerville",
    "sg:classifiers": [
      {
        "category": "Retail",
        "subcategory": "Repair Shop",
        "type": "Services"
      }
    ],
    "sg:phone": "+1 617 453 5178",
    "sg:postcode": "02143",
    "sg:province": "MA",
    "sg:tags": [
      "lock",
      "locksmith"
    ],
    "wof:name": "1 Hour 7 Day Emerge Locksmith",
    "wof:placetype": "venue"
  },
  "geometry": {"coordinates":[-71.096303,42.379724],"type":"Point"}
}
