{
  "type": "Feature",
  "properties": {
    "addr:full": "252 Wachusett Ave Arlington MA 02476",
    "addr:housenumber": "252",
    "addr:postcode": "02476",
    "addr:street": "Wachusett Ave",
    "iso:country": "US",
    "sg:address": "252 Wachusett Ave",
    "sg:city": "Arlington",
    "sg:classifiers": [
      {
        "category": "Place Of Worship",
        "type": "Public Place"
      }
    ],
    "sg:phone": "+1 781 646 2389",
    "sg:postcode": "02476",
    "sg:province": "MA",
    "sg:tags": [
      "church"
    ],
    "wof:name": "Gospel Reach Out Inc",
    "wof:placetype": "venue"
  },
  "geometry": {"coordinates":[-71.182734,42.414585],"type":"Point"}
}
