{
  "type": "Feature",
  "properties": {
    "iso:country":"US",
    "sg:address":"12 Harding St",
    "sg:city":"Lakeville",
    "sg:classifiers":[
        {
            "category":"Shopping",
            "type":"Retail Goods"
        }
    ],
    "sg:phone":"+1 508 822 1887",
    "sg:postcode":"02347",
    "sg:province":"MA",
    "sg:tags":[
        "telephone",
        "cellular"
    ],
    "wof:name":"Digi Com Cellular Phones",
    "wof:placetype":"venue"
},
  "geometry": {"coordinates":[-70.97877699999999,41.901834],"type":"Point"}
}