{
  "type": "Feature",
  "properties": {
    "addr:full": "1 S Main St Gardner MA 01440",
    "addr:housenumber": "1",
    "addr:postcode": "01440",
    "addr:street": "S Main St",
    "iso:country": "US",
    "sg:address": "1 S Main St",
    "sg:city": "Gardner",
    "sg:classifiers": [
      {
        "category": "Wholesale",
        "subcategory": "Furniture",
        "type": "Manufacturing \u0026 Wholesale Goods"
      }
    ],
    "sg:phone": "+1 978 632 1301",
    "sg:postcode": "01440",
    "sg:province": "MA",
    "sg:tags": [
      "furniture-wholesale",
      "manufacturer"
    ],
    "sg:website": "http://www.gardnerchair.com",
    "wof:name": "Royal Furniture Mfg Co Inc",
    "wof:placetype": "venue"
  },
  "geometry": {"coordinates":[-71.980629,42.557701],"type":"Point"}
}
