{
  "type": "Feature",
  "properties": {
    "addr:full": "272 County St Attleboro MA 02703",
    "addr:housenumber": "272",
    "addr:postcode": "02703",
    "addr:street": "County St",
    "iso:country": "US",
    "sg:address": "272 County St",
    "sg:city": "Attleboro",
    "sg:classifiers": [
      {
        "category": "Health Services",
        "subcategory": "Chiropractor",
        "type": "Services"
      }
    ],
    "sg:phone": "+1 508 222 2299",
    "sg:postcode": "02703",
    "sg:province": "MA",
    "wof:name": "Almeida Robert S DC",
    "wof:placetype": "venue"
  },
  "geometry": {"coordinates":[-71.299202,41.9347],"type":"Point"}
}
