{
  "type": "Feature",
  "properties": {
    "addr:full":"15 Union St Lawrence MA 01840",
    "addr:housenumber":"15",
    "addr:postcode":"01840",
    "addr:street":"Union St",
    "iso:country":"US",
    "sg:address":"15 Union St",
    "sg:city":"Lawrence",
    "sg:classifiers":[
        {
            "category":"Communications",
            "type":"Services"
        }
    ],
    "sg:phone":"+1 978 794 3878",
    "sg:postcode":"01840",
    "sg:province":"MA",
    "wof:name":"Newfound Communications Inc",
    "wof:placetype":"venue"
},
  "geometry": {"coordinates":[-71.153401,42.706478],"type":"Point"}
}