{
  "type": "Feature",
  "properties": {
    "iso:country":"US",
    "sg:address":"20 Sun Valley Dr",
    "sg:city":"Framingham",
    "sg:classifiers":[
        {
            "category":"Building & Trades",
            "subcategory":"Construction",
            "type":"Services"
        }
    ],
    "sg:phone":"+1   ",
    "sg:postcode":"01701",
    "sg:province":"MA",
    "sg:tags":[
        "contractor"
    ],
    "wof:name":"Bevilcqua Tile MBL Instllation",
    "wof:placetype":"venue"
},
  "geometry": {"coordinates":[-71.446353,42.303143],"type":"Point"}
}