{
  "type": "Feature",
  "properties": {
    "iso:country":"US",
    "sg:address":"200 University Ave",
    "sg:city":"Westwood",
    "sg:classifiers":[
        {
            "category":"Shopping",
            "type":"Retail Goods"
        }
    ],
    "sg:phone":"+1 781 329 9966",
    "sg:postcode":"02090",
    "sg:province":"MA",
    "sg:tags":[
        "equipment",
        "telephone",
        "supply"
    ],
    "wof:name":"Shared Technologies Fairchild",
    "wof:placetype":"venue"
},
  "geometry": {"coordinates":[-71.150983,42.20896],"type":"Point"}
}