{
  "type": "Feature",
  "properties": {
    "iso:country":"US",
    "sg:address":"176 Federal Street",
    "sg:city":"Boston",
    "sg:classifiers":[
        {
            "category":"Professional",
            "subcategory":"Computer Services",
            "type":"Services"
        }
    ],
    "sg:phone":"+1 617 896 4000",
    "sg:postcode":"02110",
    "sg:province":"MA",
    "sg:tags":[
        "point-of-care",
        "charge-capture"
    ],
    "sg:website":"http://medaptus.com/",
    "wof:name":"MedAptus",
    "wof:placetype":"venue"
},
  "geometry": {"coordinates":[-71.056416,42.353364],"type":"Point"}
}