{
  "type": "Feature",
  "properties": {
    "iso:country":"US",
    "sg:address":"57 Eliot St",
    "sg:city":"Natick",
    "sg:classifiers":[
        {
            "category":"Restaurant",
            "type":"Food & Drink"
        }
    ],
    "sg:phone":"+1 508 655 4628",
    "sg:postcode":"01760",
    "sg:province":"MA",
    "sg:tags":[
        "shop",
        "coffee"
    ],
    "wof:name":"Clever Monk Coffee Co",
    "wof:placetype":"venue"
},
  "geometry": {"coordinates":[-71.316079,42.272819],"type":"Point"}
}