{
  "type": "Feature",
  "properties": {
    "addr:full": "57 Eliot St Natick MA 01760",
    "addr:housenumber": "57",
    "addr:postcode": "01760",
    "addr:street": "Eliot St",
    "iso:country": "US",
    "sg:address": "57 Eliot St",
    "sg:city": "Natick",
    "sg:classifiers": [
      {
        "category": "Restaurant",
        "type": "Food \u0026 Drink"
      }
    ],
    "sg:phone": "+1 508 655 4628",
    "sg:postcode": "01760",
    "sg:province": "MA",
    "sg:tags": [
      "shop",
      "coffee"
    ],
    "wof:name": "Clever Monk Coffee Co",
    "wof:placetype": "venue"
  },
  "geometry": {"coordinates":[-71.316079,42.272819],"type":"Point"}
}
