{
  "type": "Feature",
  "properties": {
    "addr:full": "448 Washington St Wellesley MA 02482",
    "addr:housenumber": "448",
    "addr:postcode": "02482",
    "addr:street": "Washington St",
    "iso:country": "US",
    "sg:address": "448 Washington St",
    "sg:city": "Wellesley",
    "sg:classifiers": [
      {
        "category": "Professional",
        "subcategory": "Management \u0026 Consulting",
        "type": "Services"
      }
    ],
    "sg:phone": "+1 781 237 0547",
    "sg:postcode": "02482",
    "sg:province": "MA",
    "sg:tags": [
      "marketing",
      "program"
    ],
    "wof:name": "Catalina Marketing Corp",
    "wof:placetype": "venue"
  },
  "geometry": {"coordinates":[-71.28059,42.30686],"type":"Point"}
}
