{
  "type": "Feature",
  "properties": {
    "iso:country":"US",
    "sg:address":"250 Washington St",
    "sg:city":"Attleboro",
    "sg:classifiers":[
        {
            "category":"Restaurant",
            "type":"Food & Drink"
        }
    ],
    "sg:phone":"+1 508 399 6677",
    "sg:postcode":"02703",
    "sg:province":"MA",
    "sg:website":"www.hearthnkettle.com",
    "wof:name":"Hearth 'n Kettle",
    "wof:placetype":"venue"
},
  "geometry": {"coordinates":[-71.3573,41.923],"type":"Point"}
}