{
  "type": "Feature",
  "properties": {
    "iso:country":"US",
    "sg:address":"245 High St",
    "sg:city":"Waltham",
    "sg:classifiers":[
        {
            "category":"Retail",
            "subcategory":"Auto Repair",
            "type":"Services"
        }
    ],
    "sg:phone":"+1 781 899 6607",
    "sg:postcode":"02453",
    "sg:province":"MA",
    "sg:tags":[
        "automobile",
        "electric"
    ],
    "wof:name":"Tele Ignition",
    "wof:placetype":"venue"
},
  "geometry": {"coordinates":[-71.22823200000001,42.3654],"type":"Point"}
}