{
  "type": "Feature",
  "properties": {
    "addr:full": "245 High St Waltham MA 02453",
    "addr:housenumber": "245",
    "addr:postcode": "02453",
    "addr:street": "High St",
    "iso:country": "US",
    "sg:address": "245 High St",
    "sg:city": "Waltham",
    "sg:classifiers": [
      {
        "category": "Retail",
        "subcategory": "Auto Repair",
        "type": "Services"
      }
    ],
    "sg:phone": "+1 781 899 6607",
    "sg:postcode": "02453",
    "sg:province": "MA",
    "sg:tags": [
      "automobile",
      "electric"
    ],
    "wof:name": "Tele Ignition",
    "wof:placetype": "venue"
  },
  "geometry": {"coordinates":[-71.228232,42.3654],"type":"Point"}
}
