{
  "type": "Feature",
  "properties": {
    "addr:full":"1 Edgell Rd Framingham MA 01701",
    "addr:housenumber":"1",
    "addr:postcode":"01701",
    "addr:street":"Edgell Rd",
    "iso:country":"US",
    "sg:address":"1 Edgell Rd",
    "sg:city":"Framingham",
    "sg:classifiers":[
        {
            "category":"Professional",
            "subcategory":"Employment Agencies",
            "type":"Services"
        }
    ],
    "sg:phone":"+1 508 875 6025",
    "sg:postcode":"01701",
    "sg:province":"MA",
    "sg:tags":[
        "consultant",
        "search",
        "executive"
    ],
    "wof:name":"Moran & Assoc",
    "wof:placetype":"venue"
},
  "geometry": {"coordinates":[-71.434524,42.30023],"type":"Point"}
}