{
  "type": "Feature",
  "properties": {
    "addr:full": "169 Elm St Waltham MA 02453",
    "addr:housenumber": "169",
    "addr:postcode": "02453",
    "addr:street": "Elm St",
    "iso:country": "US",
    "sg:address": "169 Elm St",
    "sg:city": "Waltham",
    "sg:classifiers": [
      {
        "category": "Building \u0026 Trades",
        "subcategory": "Construction",
        "type": "Services"
      }
    ],
    "sg:phone": "+1 781 647 1711",
    "sg:postcode": "02453",
    "sg:province": "MA",
    "sg:tags": [
      "excavating",
      "contractor"
    ],
    "sg:website": "www.environic.com",
    "wof:name": "Environic Solutions Inc",
    "wof:placetype": "venue"
  },
  "geometry": {"coordinates":[-71.232109,42.372437],"type":"Point"}
}
