{
  "type": "Feature",
  "properties": {
    "iso:country":"US",
    "sg:address":"1663 Falmouth Rd",
    "sg:city":"Centerville",
    "sg:classifiers":[
        {
            "category":"Health Services",
            "subcategory":"Health Practitioner",
            "type":"Services"
        }
    ],
    "sg:phone":"+1 508 775 3848",
    "sg:postcode":"02632",
    "sg:province":"MA",
    "sg:tags":[
        "therapist",
        "physical"
    ],
    "wof:name":"Physiotherapy Assoc",
    "wof:placetype":"venue"
},
  "geometry": {"coordinates":[-70.348535,41.6569],"type":"Point"}
}