{
  "type": "Feature",
  "properties": {
    "iso:country":"US",
    "sg:address":"475 Hillside Ave",
    "sg:city":"Needham",
    "sg:classifiers":[
        {
            "category":"Manufacturing",
            "subcategory":"Retail Goods",
            "type":"Manufacturing & Wholesale Goods"
        }
    ],
    "sg:phone":"+1 781 444 2426",
    "sg:postcode":"02494",
    "sg:province":"MA",
    "sg:tags":[
        "marking",
        "devices"
    ],
    "wof:name":"Esselte Meto/Kimball Systems",
    "wof:placetype":"venue"
},
  "geometry": {"coordinates":[-71.237759,42.290754],"type":"Point"}
}