{
  "type": "Feature",
  "properties": {
    "iso:country":"US",
    "sg:address":"41 Joslin Rd",
    "sg:city":"Winchendon",
    "sg:classifiers":[
        {
            "category":"Retail",
            "subcategory":"Auto Repair",
            "type":"Services"
        }
    ],
    "sg:phone":"+1 978 297 4015",
    "sg:postcode":"01475",
    "sg:province":"MA",
    "sg:tags":[
        "body",
        "shop",
        "painting",
        "automobile"
    ],
    "wof:name":"Kinner's Auto Body",
    "wof:placetype":"venue"
},
  "geometry": {"coordinates":[-72.062434,42.646695],"type":"Point"}
}