{
  "type": "Feature",
  "properties": {
    "addr:full": "395 Columbia Rd Dorchester MA 02125",
    "addr:housenumber": "395",
    "addr:postcode": "02125",
    "addr:street": "Columbia Rd",
    "iso:country": "US",
    "sg:address": "395 Columbia Rd",
    "sg:city": "Dorchester",
    "sg:classifiers": [
      {
        "category": "Building \u0026 Trades",
        "subcategory": "Construction",
        "type": "Services"
      }
    ],
    "sg:phone": "+1 617 288 3000",
    "sg:postcode": "02125",
    "sg:province": "MA",
    "sg:tags": [
      "restoration",
      "preservation"
    ],
    "sg:website": "http://www.chapmanwaterproofing.com",
    "wof:name": "Calhess Restoration \u0026 Weather",
    "wof:placetype": "venue"
  },
  "geometry": {"coordinates":[-71.07003,42.311272],"type":"Point"}
}
