{
  "type": "Feature",
  "properties": {
    "iso:country":"US",
    "sg:address":"8 Park Plz",
    "sg:city":"Boston",
    "sg:classifiers":[
        {
            "category":"Restaurant",
            "type":"Food & Drink"
        }
    ],
    "sg:phone":"+1 617 573 0821",
    "sg:postcode":"02116",
    "sg:province":"MA",
    "sg:website":"www.pfchangs.com",
    "wof:name":"P F Chang's China Bistro",
    "wof:placetype":"venue"
},
  "geometry": {"coordinates":[-71.067336,42.352258],"type":"Point"}
}