{
  "type": "Feature",
  "properties": {
    "iso:country":"US",
    "sg:address":"15 Pleasant St",
    "sg:city":"Wakefield",
    "sg:classifiers":[
        {
            "category":"Social Services",
            "subcategory":"Adult Care",
            "type":"Services"
        }
    ],
    "sg:phone":"+1 781 245 6008",
    "sg:postcode":"01880",
    "sg:province":"MA",
    "sg:tags":[
        "home",
        "residential"
    ],
    "wof:name":"Pleasant Street",
    "wof:placetype":"venue"
},
  "geometry": {"coordinates":[-71.06744399999999,42.506008],"type":"Point"}
}