{
  "type": "Feature",
  "properties": {
    "iso:country":"US",
    "sg:address":"79 Warren St",
    "sg:city":"Brookline",
    "sg:classifiers":[
        {
            "category":"Health Services",
            "subcategory":"Nursing And Care Facility",
            "type":"Services"
        }
    ],
    "sg:phone":"+1 617 232 5344",
    "sg:postcode":"02445",
    "sg:province":"MA",
    "sg:tags":[
        "nurse",
        "practice-arnp",
        "nurses-advanced"
    ],
    "wof:name":"Newborn Support Service",
    "wof:placetype":"venue"
},
  "geometry": {"coordinates":[-71.131953,42.325932],"type":"Point"}
}