{
  "type": "Feature",
  "properties": {
    "iso:country":"US",
    "sg:address":"15 Drake St",
    "sg:city":"South Easton",
    "sg:classifiers":[
        {
            "category":"Manufacturing",
            "subcategory":"Printing",
            "type":"Manufacturing & Wholesale Goods"
        }
    ],
    "sg:phone":"+1 508 230 5905",
    "sg:postcode":"02375",
    "sg:province":"MA",
    "sg:tags":[
        "printer"
    ],
    "wof:name":"Fremont Printing Inc",
    "wof:placetype":"venue"
},
  "geometry": {"coordinates":[-71.084564,42.040143],"type":"Point"}
}