{
  "type": "Feature",
  "properties": {
    "iso:country":"US",
    "sg:address":"777 Main St",
    "sg:city":"Great Barrington",
    "sg:classifiers":[
        {
            "category":"Retail",
            "subcategory":"Photofinishing",
            "type":"Services"
        }
    ],
    "sg:phone":"+1   ",
    "sg:postcode":"01230",
    "sg:province":"MA",
    "sg:tags":[
        "laboratory"
    ],
    "wof:name":"Vermont Color Photo Labs",
    "wof:placetype":"venue"
},
  "geometry": {"coordinates":[-73.36318,42.17918],"type":"Point"}
}