{
  "type": "Feature",
  "properties": {
    "addr:full":"7 Craig Rd Acton MA 01720",
    "addr:housenumber":"7",
    "addr:postcode":"01720",
    "addr:street":"Craig Rd",
    "iso:country":"US",
    "sg:address":"7 Craig Rd",
    "sg:city":"Acton",
    "sg:classifiers":[
        {
            "category":"Personal",
            "type":"Services"
        }
    ],
    "sg:phone":"+1 800 442 6683",
    "sg:postcode":"01720",
    "sg:province":"MA",
    "sg:tags":[
        "mover"
    ],
    "wof:name":"ABC Relocation Services",
    "wof:placetype":"venue"
},
  "geometry": {"coordinates":[-71.418875,42.46688],"type":"Point"}
}