{
  "type": "Feature",
  "properties": {
    "addr:full": "116 Mechanic St Bellingham MA 02019",
    "addr:housenumber": "116",
    "addr:postcode": "02019",
    "addr:street": "Mechanic St",
    "iso:country": "US",
    "sg:address": "116 Mechanic St",
    "sg:city": "Bellingham",
    "sg:classifiers": [
      {
        "category": "Professional",
        "subcategory": "Employment Agencies",
        "type": "Services"
      }
    ],
    "sg:phone": "+1 508 966 5227",
    "sg:postcode": "02019",
    "sg:province": "MA",
    "wof:name": "Bartending Academy-New England",
    "wof:placetype": "venue"
  },
  "geometry": {"coordinates":[-71.465293,42.081919],"type":"Point"}
}
