{
  "type": "Feature",
  "properties": {
    "iso:country":"US",
    "sg:address":"417 Rock St",
    "sg:city":"Fall River",
    "sg:classifiers":[
        {
            "category":"Education",
            "subcategory":"School",
            "type":"Public Place"
        }
    ],
    "sg:phone":"+1 508 675 8420",
    "sg:postcode":"02720",
    "sg:province":"MA",
    "wof:name":"Fall River School Adm Building",
    "wof:placetype":"venue"
},
  "geometry": {"coordinates":[-71.151572,41.707574],"type":"Point"}
}