{
  "type": "Feature",
  "properties": {
    "addr:full": "7 Franklin St Salem MA 01970",
    "addr:housenumber": "7",
    "addr:postcode": "01970",
    "addr:street": "Franklin St",
    "iso:country": "US",
    "sg:address": "7 Franklin St",
    "sg:city": "Salem",
    "sg:classifiers": [
      {
        "category": "Building \u0026 Trades",
        "subcategory": "Electrical",
        "type": "Services"
      }
    ],
    "sg:phone": "+1 978 815 9122",
    "sg:postcode": "01970",
    "sg:province": "MA",
    "sg:tags": [
      "electrician"
    ],
    "wof:name": "Davis Digregorio Electric",
    "wof:placetype": "venue"
  },
  "geometry": {"coordinates":[-70.899239,42.525909],"type":"Point"}
}
