{
  "type": "Feature",
  "properties": {
    "iso:country":"US",
    "sg:address":"7 Franklin St",
    "sg:city":"Salem",
    "sg:classifiers":[
        {
            "category":"Building & Trades",
            "subcategory":"Electrical",
            "type":"Services"
        }
    ],
    "sg:phone":"+1 978 815 9122",
    "sg:postcode":"01970",
    "sg:province":"MA",
    "sg:tags":[
        "electrician"
    ],
    "wof:name":"Davis Digregorio Electric",
    "wof:placetype":"venue"
},
  "geometry": {"coordinates":[-70.89923899999999,42.525909],"type":"Point"}
}