{
  "type": "Feature",
  "properties": {
    "addr:full":"105 N Bridge St Holyoke MA 01040",
    "addr:housenumber":"105",
    "addr:postcode":"01040",
    "addr:street":"N Bridge St",
    "iso:country":"US",
    "sg:address":"105 N Bridge St",
    "sg:city":"Holyoke",
    "sg:classifiers":[
        {
            "category":"Autos & Motor Vehicles",
            "subcategory":"Automobile Sales",
            "type":"Retail Goods"
        }
    ],
    "sg:phone":"+1 413 534 9144",
    "sg:postcode":"01040",
    "sg:province":"MA",
    "sg:tags":[
        "car",
        "dealer"
    ],
    "wof:name":"Reyes Auto Sales",
    "wof:placetype":"venue"
},
  "geometry": {"coordinates":[-72.59732099999999,42.203421],"type":"Point"}
}