{
  "type": "Feature",
  "properties": {
    "addr:full": "72 Broad Street Boston MA 02110",
    "addr:housenumber": "72",
    "addr:postcode": "02110",
    "addr:street": "Broad Street",
    "iso:country": "US",
    "sg:address": "72 Broad Street",
    "sg:city": "Boston",
    "sg:classifiers": [
      {
        "category": "Bars \u0026 Pubs",
        "type": "Food \u0026 Drink"
      },
      {
        "category": "Restaurant",
        "type": "Food \u0026 Drink"
      },
      {
        "category": "Bars \u0026 Pubs",
        "subcategory": "Lounge",
        "type": "Food \u0026 Drink"
      }
    ],
    "sg:phone": "+1 617 482 1900",
    "sg:postcode": "02110",
    "sg:province": "MA",
    "sg:tags": [
      "new",
      "american",
      "cocktail"
    ],
    "sg:website": "www.vlboston.com",
    "wof:name": "Vintage Lounge",
    "wof:placetype": "venue"
  },
  "geometry": {"coordinates":[-71.052902,42.3577],"type":"Point"}
}
