{
  "type": "Feature",
  "properties": {
    "iso:country":"US",
    "sg:address":"72 Broad Street",
    "sg:city":"Boston",
    "sg:classifiers":[
        {
            "category":"Bars & Pubs",
            "type":"Food & Drink"
        },
        {
            "category":"Restaurant",
            "type":"Food & Drink"
        },
        {
            "category":"Bars & Pubs",
            "subcategory":"Lounge",
            "type":"Food & Drink"
        }
    ],
    "sg:phone":"+1 617 482 1900",
    "sg:postcode":"02110",
    "sg:province":"MA",
    "sg:tags":[
        "new",
        "american",
        "cocktail"
    ],
    "sg:website":"www.vlboston.com",
    "wof:name":"Vintage Lounge",
    "wof:placetype":"venue"
},
  "geometry": {"coordinates":[-71.052902,42.3577],"type":"Point"}
}