{
  "type": "Feature",
  "properties": {
    "iso:country":"US",
    "sg:address":"24 River St",
    "sg:city":"Danvers",
    "sg:classifiers":[
        {
            "category":"Building & Trades",
            "subcategory":"Landscaping Services",
            "type":"Services"
        }
    ],
    "sg:phone":"+1 978 777 1621",
    "sg:postcode":"01923",
    "sg:province":"MA",
    "sg:tags":[
        "landscape",
        "contractor"
    ],
    "wof:name":"K L Svc",
    "wof:placetype":"venue"
},
  "geometry": {"coordinates":[-70.921374,42.554645],"type":"Point"}
}