{
  "type": "Feature",
  "properties": {
    "iso:country":"US",
    "sg:address":"1141 Beacon Street",
    "sg:city":"Brookline",
    "sg:classifiers":[
        {
            "category":"Sports & Exercise",
            "subcategory":"Gym",
            "type":"Entertainment"
        }
    ],
    "sg:phone":"+1 617 277 9400",
    "sg:postcode":"02446",
    "sg:province":"MA",
    "sg:tags":[
        "trainer"
    ],
    "wof:name":"Fajnzylber Marcel Psychlogst",
    "wof:placetype":"venue"
},
  "geometry": {"coordinates":[-71.113027,42.344251],"type":"Point"}
}