{
  "type": "Feature",
  "properties": {
    "addr:full": "76 Cedar St Malden MA 02148",
    "addr:housenumber": "76",
    "addr:postcode": "02148",
    "addr:street": "Cedar St",
    "iso:country": "US",
    "sg:address": "76 Cedar St",
    "sg:city": "Malden",
    "sg:classifiers": [
      {
        "category": "Travel",
        "subcategory": "Travel Agent",
        "type": "Entertainment"
      }
    ],
    "sg:phone": "+1 781 870 1998",
    "sg:postcode": "02148",
    "sg:province": "MA",
    "sg:tags": [
      "tours",
      "promoter"
    ],
    "wof:name": "New England Poker Tour",
    "wof:placetype": "venue"
  },
  "geometry": {"coordinates":[-71.076415,42.429231],"type":"Point"}
}
