{
  "type": "Feature",
  "properties": {
    "iso:country":"US",
    "sg:address":"Hobbs Brk",
    "sg:city":"Sturbridge",
    "sg:classifiers":[
        {
            "category":"Shopping",
            "subcategory":"Clothing, Apparel, & Fashions",
            "type":"Retail Goods"
        }
    ],
    "sg:phone":"+1 508 347 5409",
    "sg:postcode":"01566",
    "sg:province":"MA",
    "sg:tags":[
        "men's",
        "clothing",
        "women's"
    ],
    "sg:website":"www.oldnavy.com",
    "wof:name":"Old Navy",
    "wof:placetype":"venue"
},
  "geometry": {"coordinates":[-72.058431,42.125635],"type":"Point"}
}