{
  "type": "Feature",
  "properties": {
    "addr:full":"200 Valley Path Marshfield MA 02050",
    "addr:housenumber":"200",
    "addr:postcode":"02050",
    "addr:street":"Valley Path",
    "iso:country":"US",
    "sg:address":"200 Valley Path",
    "sg:city":"Marshfield",
    "sg:classifiers":[
        {
            "category":"Autos & Motor Vehicles",
            "subcategory":"Auto Supplies",
            "type":"Retail Goods"
        }
    ],
    "sg:phone":"+1 781 834 9396",
    "sg:postcode":"02050",
    "sg:province":"MA",
    "sg:tags":[
        "automobile",
        "part"
    ],
    "wof:name":"Ardee Spray Supply",
    "wof:placetype":"venue"
},
  "geometry": {"coordinates":[-70.75248000000001,42.139839],"type":"Point"}
}