{
  "type": "Feature",
  "properties": {
    "addr:full":"279 Elm St North Attleboro MA 02760",
    "addr:housenumber":"279",
    "addr:postcode":"02760",
    "addr:street":"Elm St",
    "iso:country":"US",
    "sg:address":"279 Elm St",
    "sg:city":"North Attleboro",
    "sg:classifiers":[
        {
            "category":"Building & Trades",
            "subcategory":"Construction",
            "type":"Services"
        }
    ],
    "sg:phone":"+1 508 695 2626",
    "sg:postcode":"02760",
    "sg:province":"MA",
    "sg:tags":[
        "contractor"
    ],
    "wof:name":"Cavalieri Patsy & Sons Contrs",
    "wof:placetype":"venue"
},
  "geometry": {"coordinates":[-71.323898,41.976101],"type":"Point"}
}