{
  "type": "Feature",
  "properties": {
    "iso:country":"US",
    "sg:address":"344 Commonwealth Rd",
    "sg:city":"Wayland",
    "sg:classifiers":[
        {
            "category":"Home & Garden",
            "subcategory":"Building Materials",
            "type":"Retail Goods"
        }
    ],
    "sg:phone":"+1 508 655 5495",
    "sg:postcode":"01778",
    "sg:province":"MA",
    "sg:tags":[
        "modular"
    ],
    "wof:name":"Millbrook",
    "wof:placetype":"venue"
},
  "geometry": {"coordinates":[-71.351963,42.323299],"type":"Point"}
}