{
  "type": "Feature",
  "properties": {
    "addr:full": "344 Commonwealth Rd Wayland MA 01778",
    "addr:housenumber": "344",
    "addr:postcode": "01778",
    "addr:street": "Commonwealth Rd",
    "iso:country": "US",
    "sg:address": "344 Commonwealth Rd",
    "sg:city": "Wayland",
    "sg:classifiers": [
      {
        "category": "Home \u0026 Garden",
        "subcategory": "Building Materials",
        "type": "Retail Goods"
      }
    ],
    "sg:phone": "+1 508 655 5495",
    "sg:postcode": "01778",
    "sg:province": "MA",
    "sg:tags": [
      "modular"
    ],
    "wof:name": "Millbrook",
    "wof:placetype": "venue"
  },
  "geometry": {"coordinates":[-71.351963,42.323299],"type":"Point"}
}
