{
  "type": "Feature",
  "properties": {
    "iso:country":"US",
    "sg:address":"12 Inwood Rd",
    "sg:city":"Worcester",
    "sg:classifiers":[
        {
            "category":"Professional",
            "subcategory":"Detective & Security Services",
            "type":"Services"
        },
        {
            "category":"Professional",
            "subcategory":"Business Services",
            "type":"Services"
        }
    ],
    "sg:phone":"+1 508 856 7350",
    "sg:postcode":"01606",
    "sg:province":"MA",
    "wof:name":"Secure Stream Technologies Inc",
    "wof:placetype":"venue"
},
  "geometry": {"coordinates":[-71.78831700000001,42.312975],"type":"Point"}
}