{
  "type": "Feature",
  "properties": {
    "iso:country":"US",
    "sg:address":"13 Centre St",
    "sg:city":"New Bedford",
    "sg:classifiers":[
        {
            "category":"Wholesale",
            "subcategory":"Seafood",
            "type":"Manufacturing & Wholesale Goods"
        }
    ],
    "sg:phone":"+1 508 994 8600",
    "sg:postcode":"02740",
    "sg:province":"MA",
    "sg:tags":[
        "fish"
    ],
    "wof:name":"Sea Born Products",
    "wof:placetype":"venue"
},
  "geometry": {"coordinates":[-70.922629,41.635333],"type":"Point"}
}