{
  "type": "Feature",
  "properties": {
    "iso:country":"US",
    "sg:address":"85 Industrial Dr",
    "sg:city":"Holden",
    "sg:classifiers":[
        {
            "category":"Manufacturing",
            "subcategory":"Chemicals & Compounds",
            "type":"Manufacturing & Wholesale Goods"
        }
    ],
    "sg:phone":"+1 508 829 6321",
    "sg:postcode":"01520",
    "sg:province":"MA",
    "sg:tags":[
        "plastic"
    ],
    "sg:website":"www.clariant.com",
    "wof:name":"Clariant Corp",
    "wof:placetype":"venue"
},
  "geometry": {"coordinates":[-71.84357199999999,42.337458],"type":"Point"}
}