{
  "type": "Feature",
  "properties": {
    "iso:country":"US",
    "sg:address":"20 Florence St",
    "sg:city":"Marlborough",
    "sg:classifiers":[
        {
            "category":"Government",
            "subcategory":"Post Office",
            "type":"Public Place"
        }
    ],
    "sg:phone":"+1 508 000 1111",
    "sg:postcode":"01752",
    "sg:province":"MA",
    "wof:name":"US Post Office",
    "wof:placetype":"venue"
},
  "geometry": {"coordinates":[-71.548638,42.346222],"type":"Point"}
}