{
  "type": "Feature",
  "properties": {
    "iso:country":"US",
    "sg:address":"29 Concord Ave",
    "sg:city":"Cambridge",
    "sg:classifiers":[
        {
            "category":"Professional",
            "subcategory":"Computer Services",
            "type":"Services"
        }
    ],
    "sg:phone":"+1   ",
    "sg:postcode":"02138",
    "sg:province":"MA",
    "sg:tags":[
        "programing",
        "custom"
    ],
    "wof:name":"Charles Volkstorf",
    "wof:placetype":"venue"
},
  "geometry": {"coordinates":[-71.127285,42.380285],"type":"Point"}
}