{
  "type": "Feature",
  "properties": {
    "addr:full": "31 Legate Hill Rd Sterling MA 01564",
    "addr:housenumber": "31",
    "addr:postcode": "01564",
    "addr:street": "Legate Hill Rd",
    "iso:country": "US",
    "sg:address": "31 Legate Hill Rd",
    "sg:city": "Sterling",
    "sg:classifiers": [
      {
        "category": "Building \u0026 Trades",
        "subcategory": "Landscaping Services",
        "type": "Services"
      }
    ],
    "sg:phone": "+1 978 422 6882",
    "sg:postcode": "01564",
    "sg:province": "MA",
    "sg:tags": [
      "tree",
      "landscape",
      "contractor"
    ],
    "wof:name": "K G M Tree \u0026 Landscaping",
    "wof:placetype": "venue"
  },
  "geometry": {"coordinates":[-71.743637,42.47506],"type":"Point"}
}
