{
  "type": "Feature",
  "properties": {
    "addr:full": "55 Wensley St Boston MA 02120",
    "addr:housenumber": "55",
    "addr:postcode": "02120",
    "addr:street": "Wensley St",
    "iso:country": "US",
    "sg:address": "55 Wensley St",
    "sg:city": "Boston",
    "sg:classifiers": [
      {
        "category": "Organizations",
        "subcategory": "Community Association",
        "type": "Services"
      }
    ],
    "sg:phone": "+1   ",
    "sg:postcode": "02120",
    "sg:province": "MA",
    "wof:name": "55 Wensley Street Condo Assn",
    "wof:placetype": "venue"
  },
  "geometry": {"coordinates":[-71.100113,42.326418],"type":"Point"}
}
