{
  "type": "Feature",
  "properties": {
    "addr:full": "150 Industrial Dr Halifax MA 02338",
    "addr:housenumber": "150",
    "addr:postcode": "02338",
    "addr:street": "Industrial Dr",
    "iso:country": "US",
    "sg:address": "150 Industrial Dr",
    "sg:city": "Halifax",
    "sg:classifiers": [
      {
        "category": "Education",
        "subcategory": "Dance Studio",
        "type": "Public Place"
      }
    ],
    "sg:phone": "+1 781 294 8706",
    "sg:postcode": "02338",
    "sg:province": "MA",
    "sg:tags": [
      "instruction",
      "dancing"
    ],
    "wof:name": "A Dancer's World",
    "wof:placetype": "venue"
  },
  "geometry": {"coordinates":[-70.897233,41.998331],"type":"Point"}
}
