{
  "type": "Feature",
  "properties": {
    "iso:country":"US",
    "sg:address":"1105 Blue Hill Ave",
    "sg:city":"Dorchester Ctr",
    "sg:classifiers":[
        {
            "category":"Social Services",
            "subcategory":"Child Care",
            "type":"Services"
        }
    ],
    "sg:phone":"+1 617 825 7661",
    "sg:postcode":"02124",
    "sg:province":"MA",
    "wof:name":"ABC 123",
    "wof:placetype":"venue"
},
  "geometry": {"coordinates":[-71.090701,42.287149],"type":"Point"}
}