{
  "type": "Feature",
  "properties": {
    "addr:full":"69 Ware Rd West Warren MA 01092",
    "addr:housenumber":"69",
    "addr:postcode":"01092",
    "addr:street":"Ware Rd",
    "iso:country":"US",
    "sg:address":"69 Ware Rd",
    "sg:city":"West Warren",
    "sg:classifiers":[
        {
            "category":"Building & Trades",
            "subcategory":"Construction",
            "type":"Services"
        }
    ],
    "sg:phone":"+1 413 436 5279",
    "sg:postcode":"01092",
    "sg:province":"MA",
    "sg:tags":[
        "roofing",
        "contractor"
    ],
    "wof:name":"Warren Roofers Inc",
    "wof:placetype":"venue"
},
  "geometry": {"coordinates":[-72.245254,42.212109],"type":"Point"}
}