{
  "type": "Feature",
  "properties": {
    "addr:full":"2 Prospect St Stockbridge MA 01226",
    "addr:housenumber":"2",
    "addr:postcode":"01226",
    "addr:street":"Prospect St",
    "iso:country":"US",
    "sg:address":"2 Prospect St",
    "sg:city":"Stockbridge",
    "sg:classifiers":[
        {
            "category":"Organizations",
            "subcategory":"Professional Association",
            "type":"Services"
        }
    ],
    "sg:phone":"+1 413 298 3691",
    "sg:postcode":"01226",
    "sg:province":"MA",
    "sg:website":"www.marian.org",
    "wof:name":"Marian Helpers Ctr",
    "wof:placetype":"venue"
},
  "geometry": {"coordinates":[-73.161053,42.481254],"type":"Point"}
}