{
  "type": "Feature",
  "properties": {
    "addr:full": "150 Prospect St Framingham MA 01701",
    "addr:housenumber": "150",
    "addr:postcode": "01701",
    "addr:street": "Prospect St",
    "iso:country": "US",
    "sg:address": "150 Prospect St",
    "sg:city": "Framingham",
    "sg:classifiers": [
      {
        "category": "Real Estate",
        "subcategory": "Real Estate Agent",
        "type": "Services"
      }
    ],
    "sg:phone": "+1 508 875 5757",
    "sg:postcode": "01701",
    "sg:province": "MA",
    "sg:tags": [
      "appraiser"
    ],
    "wof:name": "Handverger \u0026 Assoc",
    "wof:placetype": "venue"
  },
  "geometry": {"coordinates":[-71.42542,42.30495],"type":"Point"}
}
