{
  "type": "Feature",
  "properties": {
    "iso:country":"US",
    "sg:address":"150 Prospect St",
    "sg:city":"Framingham",
    "sg:classifiers":[
        {
            "category":"Real Estate",
            "subcategory":"Real Estate Agent",
            "type":"Services"
        }
    ],
    "sg:phone":"+1 508 875 5757",
    "sg:postcode":"01701",
    "sg:province":"MA",
    "sg:tags":[
        "appraiser"
    ],
    "wof:name":"Handverger & Assoc",
    "wof:placetype":"venue"
},
  "geometry": {"coordinates":[-71.42542,42.30495],"type":"Point"}
}