{
  "type": "Feature",
  "properties": {
    "addr:full": "67 Mechanic St Attleboro MA 02703",
    "addr:housenumber": "67",
    "addr:postcode": "02703",
    "addr:street": "Mechanic St",
    "iso:country": "US",
    "sg:address": "67 Mechanic St",
    "sg:city": "Attleboro",
    "sg:classifiers": [
      {
        "category": "Real Estate",
        "subcategory": "Real Estate Agent",
        "type": "Services"
      }
    ],
    "sg:phone": "+1 508 226 6911",
    "sg:postcode": "02703",
    "sg:province": "MA",
    "sg:tags": [
      "cooperative"
    ],
    "wof:name": "Ocean State Cooperative",
    "wof:placetype": "venue"
  },
  "geometry": {"coordinates":[-71.292853,41.94395],"type":"Point"}
}
