{
  "type": "Feature",
  "properties": {
    "iso:country":"US",
    "sg:address":"67 Mechanic St",
    "sg:city":"Attleboro",
    "sg:classifiers":[
        {
            "category":"Real Estate",
            "subcategory":"Real Estate Agent",
            "type":"Services"
        }
    ],
    "sg:phone":"+1 508 226 6911",
    "sg:postcode":"02703",
    "sg:province":"MA",
    "sg:tags":[
        "cooperative"
    ],
    "wof:name":"Ocean State Cooperative",
    "wof:placetype":"venue"
},
  "geometry": {"coordinates":[-71.29285299999999,41.94395],"type":"Point"}
}