{
  "type": "Feature",
  "properties": {
    "addr:full": "11 Boynton St Jamaica Plain MA 02130",
    "addr:housenumber": "11",
    "addr:postcode": "02130",
    "addr:street": "Boynton St",
    "iso:country": "US",
    "sg:address": "11 Boynton St",
    "sg:city": "Jamaica Plain",
    "sg:classifiers": [
      {
        "category": "Building \u0026 Trades",
        "subcategory": "Locksmith",
        "type": "Services"
      }
    ],
    "sg:phone": "+1 617 390 9038",
    "sg:postcode": "02130",
    "sg:province": "MA",
    "sg:tags": [
      "key"
    ],
    "wof:name": "Service All Emergencies Locksmith",
    "wof:placetype": "venue"
  },
  "geometry": {"coordinates":[-71.114156,42.305283],"type":"Point"}
}
