{
  "type": "Feature",
  "properties": {
    "addr:full":"251 W Central St Natick MA 01760",
    "addr:housenumber":"251",
    "addr:postcode":"01760",
    "addr:street":"W Central St",
    "iso:country":"US",
    "sg:address":"251 W Central St",
    "sg:city":"Natick",
    "sg:classifiers":[
        {
            "category":"Food & Beverages",
            "subcategory":"Groceries & Convenience Stores",
            "type":"Retail Goods"
        }
    ],
    "sg:phone":"+1 508 651 0046",
    "sg:postcode":"01760",
    "sg:province":"MA",
    "wof:name":"Day & Nite Convenience Stores",
    "wof:placetype":"venue"
},
  "geometry": {"coordinates":[-71.39222700000001,42.281865],"type":"Point"}
}