{
  "type": "Feature",
  "properties": {
    "addr:full": "119 Downey Rd Brockton MA 02302",
    "addr:housenumber": "119",
    "addr:postcode": "02302",
    "addr:street": "Downey Rd",
    "iso:country": "US",
    "sg:address": "119 Downey Rd",
    "sg:city": "Brockton",
    "sg:classifiers": [
      {
        "category": "Personal",
        "subcategory": "Beauty Salon",
        "type": "Services"
      }
    ],
    "sg:phone": "+1 508 583 6476",
    "sg:postcode": "02302",
    "sg:province": "MA",
    "wof:name": "It Is A Home",
    "wof:placetype": "venue"
  },
  "geometry": {"coordinates":[-70.993018,42.104342],"type":"Point"}
}
