{
  "type": "Feature",
  "properties": {
    "iso:country":"US",
    "sg:address":"550 N Main St",
    "sg:city":"Attleboro",
    "sg:classifiers":[
        {
            "category":"Health Services",
            "subcategory":"Doctor",
            "type":"Services"
        }
    ],
    "sg:phone":"+1 508 695 8351",
    "sg:postcode":"02703",
    "sg:province":"MA",
    "wof:name":"Snyder H Dennis Phys - CLOSED",
    "wof:placetype":"venue"
},
  "geometry": {"coordinates":[-71.28800200000001,41.956799],"type":"Point"}
}