{
  "type": "Feature",
  "properties": {
    "addr:full":"553 Newport Ave Attleboro MA 02703",
    "addr:housenumber":"553",
    "addr:postcode":"02703",
    "addr:street":"Newport Ave",
    "iso:country":"US",
    "sg:address":"553 Newport Ave",
    "sg:city":"Attleboro",
    "sg:classifiers":[
        {
            "category":"Manufacturing",
            "subcategory":"Petroleum Products",
            "type":"Manufacturing & Wholesale Goods"
        },
        {
            "category":"Utilities",
            "subcategory":"Fuel Oil & Lpg",
            "type":"Services"
        }
    ],
    "sg:phone":"+1 508 399 5300",
    "sg:postcode":"02703",
    "sg:province":"MA",
    "sg:tags":[
        "oils-fuel",
        "marketer",
        "oils-petroleum"
    ],
    "wof:name":"Buy Rite Oil Inc",
    "wof:placetype":"venue"
},
  "geometry": {"coordinates":[-71.353504,41.922841],"type":"Point"}
}