{
  "type": "Feature",
  "properties": {
    "addr:full": "294 Main St Springfield MA 01105",
    "addr:housenumber": "294",
    "addr:postcode": "01105",
    "addr:street": "Main St",
    "iso:country": "US",
    "sg:address": "294 Main St",
    "sg:city": "Springfield",
    "sg:classifiers": [
      {
        "category": "Health Services",
        "subcategory": "Doctor",
        "type": "Services"
      }
    ],
    "sg:phone": "+1 413 525 5244",
    "sg:postcode": "01105",
    "sg:province": "MA",
    "sg:tags": [
      "physician",
      "surgeon"
    ],
    "wof:name": "Jodi Goh MD",
    "wof:placetype": "venue"
  },
  "geometry": {"coordinates":[-72.579476,42.090274],"type":"Point"}
}
