{
  "type": "Feature",
  "properties": {
    "addr:full":"74 Sunset Dr Northborough MA 01532",
    "addr:housenumber":"74",
    "addr:postcode":"01532",
    "addr:street":"Sunset Dr",
    "iso:country":"US",
    "sg:address":"74 Sunset Dr",
    "sg:city":"Northborough",
    "sg:classifiers":[
        {
            "category":"Wholesale",
            "subcategory":"Durable Goods & Equipment",
            "type":"Manufacturing & Wholesale Goods"
        }
    ],
    "sg:phone":"+1 508 393 2895",
    "sg:postcode":"01532",
    "sg:province":"MA",
    "sg:tags":[
        "representative",
        "manufacturer"
    ],
    "wof:name":"Woods Marketing Group Inc",
    "wof:placetype":"venue"
},
  "geometry": {"coordinates":[-71.63363099999999,42.302099],"type":"Point"}
}