{
  "type": "Feature",
  "properties": {
    "iso:country":"US",
    "sg:address":"10 Roessler Rd",
    "sg:city":"Woburn",
    "sg:classifiers":[
        {
            "category":"Shopping",
            "subcategory":"Pharmacy",
            "type":"Retail Goods"
        },
        {
            "category":"Professional",
            "subcategory":"Research",
            "type":"Services"
        }
    ],
    "sg:phone":"+1 781 937 0110",
    "sg:postcode":"01801",
    "sg:province":"MA",
    "sg:tags":[
        "firm"
    ],
    "sg:website":"www.aeristherapeutics.com",
    "wof:name":"Aeris Therapeutics Inc",
    "wof:placetype":"venue"
},
  "geometry": {"coordinates":[-71.143593,42.510209],"type":"Point"}
}