{
  "type": "Feature",
  "properties": {
    "addr:full":"34 Victoria St Springfield MA 01104",
    "addr:housenumber":"34",
    "addr:postcode":"01104",
    "addr:street":"Victoria St",
    "iso:country":"US",
    "sg:address":"34 Victoria St",
    "sg:city":"Springfield",
    "sg:classifiers":[
        {
            "category":"Wholesale",
            "subcategory":"Non-durable Goods",
            "type":"Manufacturing & Wholesale Goods"
        }
    ],
    "sg:phone":"+1 413 733 4329",
    "sg:postcode":"01104",
    "sg:province":"MA",
    "sg:tags":[
        "merchandise-wholesale"
    ],
    "wof:name":"Import Speed",
    "wof:placetype":"venue"
},
  "geometry": {"coordinates":[-72.567971,42.131439],"type":"Point"}
}