{
  "type": "Feature",
  "properties": {
    "addr:full":"16 Boston Rd Chelmsford MA 01824",
    "addr:housenumber":"16",
    "addr:postcode":"01824",
    "addr:street":"Boston Rd",
    "iso:country":"US",
    "sg:address":"16 Boston Rd",
    "sg:city":"Chelmsford",
    "sg:classifiers":[
        {
            "category":"Retail",
            "subcategory":"Photofinishing",
            "type":"Services"
        }
    ],
    "sg:phone":"+1 978 256 8380",
    "sg:postcode":"01824",
    "sg:province":"MA",
    "sg:tags":[
        "photo",
        "finishing"
    ],
    "wof:name":"Ritz Camera Ctr",
    "wof:placetype":"venue"
},
  "geometry": {"coordinates":[-71.350979,42.592949],"type":"Point"}
}