{
  "type": "Feature",
  "properties": {
    "addr:full":"166 Main St Rutland MA 01543",
    "addr:housenumber":"166",
    "addr:postcode":"01543",
    "addr:street":"Main St",
    "iso:country":"US",
    "sg:address":"166 Main St",
    "sg:city":"Rutland",
    "sg:classifiers":[
        {
            "category":"Real Estate",
            "subcategory":"Real Estate Agent",
            "type":"Services"
        }
    ],
    "sg:phone":"+1 508 886 4700",
    "sg:postcode":"01543",
    "sg:province":"MA",
    "wof:name":"A Peace Of Health",
    "wof:placetype":"venue"
},
  "geometry": {"coordinates":[-71.94799,42.37883],"type":"Point"}
}