{
  "type": "Feature",
  "properties": {
    "addr:full": "259 Loring Ave West Dennis MA 02670",
    "addr:housenumber": "259",
    "addr:postcode": "02670",
    "addr:street": "Loring Ave",
    "iso:country": "US",
    "sg:address": "259 Loring Ave",
    "sg:city": "West Dennis",
    "sg:classifiers": [
      {
        "category": "Recreation",
        "subcategory": "Marina",
        "type": "Entertainment"
      }
    ],
    "sg:phone": "+1 508 398 9757",
    "sg:postcode": "02670",
    "sg:province": "MA",
    "sg:tags": [
      "club",
      "boat"
    ],
    "sg:website": "www.wdyc.org",
    "wof:name": "West Dennis Yacht Club Inc",
    "wof:placetype": "venue"
  },
  "geometry": {"coordinates":[-70.173804,41.653145],"type":"Point"}
}
