{
  "type": "Feature",
  "properties": {
    "addr:full":"36 White Cambridge MA 02140",
    "addr:housenumber":"36",
    "addr:postcode":"02140",
    "addr:street":"White",
    "iso:country":"US",
    "sg:address":"36 White",
    "sg:city":"Cambridge",
    "sg:classifiers":[
        {
            "category":"Shopping",
            "subcategory":"Crafts & Fabrics",
            "type":"Retail Goods"
        }
    ],
    "sg:phone":"+1 617 491 4646",
    "sg:postcode":"02140",
    "sg:province":"MA",
    "sg:tags":[
        "art",
        "supply"
    ],
    "wof:name":"Sign of the Dove Artist Company-Op",
    "wof:placetype":"venue"
},
  "geometry": {"coordinates":[-71.119759,42.389546],"type":"Point"}
}