{
  "type": "Feature",
  "properties": {
    "iso:country":"US",
    "sg:address":"116 Bank Rd",
    "sg:city":"Haverhill",
    "sg:classifiers":[
        {
            "category":"Autos & Motor Vehicles",
            "subcategory":"Automobile Sales",
            "type":"Retail Goods"
        }
    ],
    "sg:phone":"+1 978 374 9000",
    "sg:postcode":"01832",
    "sg:province":"MA",
    "sg:tags":[
        "car",
        "dealer"
    ],
    "wof:name":"Bill Deluca Buick GMC Truck",
    "wof:placetype":"venue"
},
  "geometry": {"coordinates":[-71.112177,42.769222],"type":"Point"}
}