{
  "type": "Feature",
  "properties": {
    "iso:country":"US",
    "sg:address":"300 Main St",
    "sg:city":"Buzzards Bay",
    "sg:classifiers":[
        {
            "category":"Restaurant",
            "type":"Food & Drink"
        }
    ],
    "sg:phone":"+1 508 759 3888",
    "sg:postcode":"02532",
    "sg:province":"MA",
    "wof:name":"Way Ho Szechuan & Mandarin Cuisines",
    "wof:placetype":"venue"
},
  "geometry": {"coordinates":[-70.602501,41.75],"type":"Point"}
}