{
  "type": "Feature",
  "properties": {
    "addr:full": "300 Main St Buzzards Bay MA 02532",
    "addr:housenumber": "300",
    "addr:postcode": "02532",
    "addr:street": "Main St",
    "iso:country": "US",
    "sg:address": "300 Main St",
    "sg:city": "Buzzards Bay",
    "sg:classifiers": [
      {
        "category": "Restaurant",
        "type": "Food \u0026 Drink"
      }
    ],
    "sg:phone": "+1 508 759 3888",
    "sg:postcode": "02532",
    "sg:province": "MA",
    "wof:name": "Way Ho Szechuan \u0026 Mandarin Cuisines",
    "wof:placetype": "venue"
  },
  "geometry": {"coordinates":[-70.602501,41.75],"type":"Point"}
}
