{
  "type": "Feature",
  "properties": {
    "iso:country":"US",
    "sg:address":"529 Main Street Suite 1",
    "sg:city":"Boston",
    "sg:classifiers":[
        {
            "category":"Sports & Exercise",
            "subcategory":"Gym",
            "type":"Entertainment"
        }
    ],
    "sg:phone":"+1 617 242 4872",
    "sg:postcode":"02129",
    "sg:province":"MA",
    "sg:tags":[
        "trainer"
    ],
    "sg:website":"www.hospicefed.org",
    "wof:name":"Beacon Hospice",
    "wof:placetype":"venue"
},
  "geometry": {"coordinates":[-71.072219,42.38373],"type":"Point"}
}