{
  "type": "Feature",
  "properties": {
    "addr:full": "1179 N Main St Randolph MA 02368",
    "addr:housenumber": "1179",
    "addr:postcode": "02368",
    "addr:street": "N Main St",
    "iso:country": "US",
    "sg:address": "1179 N Main St",
    "sg:city": "Randolph",
    "sg:classifiers": [
      {
        "category": "Restaurant",
        "type": "Food \u0026 Drink"
      }
    ],
    "sg:phone": "+1 781 986 2323",
    "sg:postcode": "02368",
    "sg:province": "MA",
    "wof:name": "Wong's Kitchen",
    "wof:placetype": "venue"
  },
  "geometry": {"coordinates":[-71.060997,42.195801],"type":"Point"}
}
