{
  "type": "Feature",
  "properties": {
    "addr:full":"4021 Washington St Roslindale MA 02131",
    "addr:housenumber":"4021",
    "addr:postcode":"02131",
    "addr:street":"Washington St",
    "iso:country":"US",
    "sg:address":"4021 Washington St",
    "sg:city":"Roslindale",
    "sg:classifiers":[
        {
            "category":"Personal",
            "subcategory":"Beauty Salon",
            "type":"Services"
        }
    ],
    "sg:phone":"+1 617 323 1982",
    "sg:postcode":"02131",
    "sg:province":"MA",
    "wof:name":"Creations Beauty Salon",
    "wof:placetype":"venue"
},
  "geometry": {"coordinates":[-71.121914,42.292263],"type":"Point"}
}