{
  "type": "Feature",
  "properties": {
    "iso:country":"US",
    "sg:address":"1487 Main St",
    "sg:city":"Tewksbury",
    "sg:classifiers":[
        {
            "category":"Health Services",
            "subcategory":"Health Practitioner",
            "type":"Services"
        }
    ],
    "sg:phone":"+1 978 858 0002",
    "sg:postcode":"01876",
    "sg:province":"MA",
    "sg:tags":[
        "therapist",
        "physical"
    ],
    "wof:name":"Therafit-Tewksbury",
    "wof:placetype":"venue"
},
  "geometry": {"coordinates":[-71.221006,42.599213],"type":"Point"}
}