{
  "type": "Feature",
  "properties": {
    "iso:country":"US",
    "sg:address":"36 Stella Rd",
    "sg:city":"Belmont",
    "sg:classifiers":[
        {
            "category":"Building & Trades",
            "subcategory":"Construction",
            "type":"Services"
        }
    ],
    "sg:phone":"+1 617 489 3740",
    "sg:postcode":"02478",
    "sg:province":"MA",
    "sg:tags":[
        "carpenter"
    ],
    "wof:name":"Jacoby Carpentry",
    "wof:placetype":"venue"
},
  "geometry": {"coordinates":[-71.17204700000001,42.402753],"type":"Point"}
}