{
  "type": "Feature",
  "properties": {
    "iso:country":"US",
    "sg:address":"136 Pond St",
    "sg:city":"Leominster",
    "sg:classifiers":[
        {
            "category":"Professional",
            "subcategory":"Business Services",
            "type":"Services"
        }
    ],
    "sg:phone":"+1 978 466 9000",
    "sg:postcode":"01453",
    "sg:province":"MA",
    "sg:tags":[
        "painter",
        "sign"
    ],
    "wof:name":"Add-A-Sign",
    "wof:placetype":"venue"
},
  "geometry": {"coordinates":[-71.76784499999999,42.524108],"type":"Point"}
}