{
  "type": "Feature",
  "properties": {
    "iso:country":"US",
    "sg:address":"111 Oak St",
    "sg:city":"Florence",
    "sg:classifiers":[
        {
            "category":"Professional",
            "type":"Services"
        }
    ],
    "sg:phone":"+1   ",
    "sg:postcode":"01062",
    "sg:province":"MA",
    "wof:name":"Jan Stensons Painting Conserv",
    "wof:placetype":"venue"
},
  "geometry": {"coordinates":[-72.674925,42.343241],"type":"Point"}
}