{
  "type": "Feature",
  "properties": {
    "addr:full": "26 Foundry Rd Sharon MA 02067",
    "addr:housenumber": "26",
    "addr:postcode": "02067",
    "addr:street": "Foundry Rd",
    "iso:country": "US",
    "sg:address": "26 Foundry Rd",
    "sg:city": "Sharon",
    "sg:classifiers": [
      {
        "category": "Retail",
        "subcategory": "Laundry \u0026 Dry Cleaning",
        "type": "Services"
      }
    ],
    "sg:phone": "+1 781 793 0202",
    "sg:postcode": "02067",
    "sg:province": "MA",
    "sg:tags": [
      "cleaners",
      "rug",
      "carpet"
    ],
    "wof:name": "Absolute Chem Dry",
    "wof:placetype": "venue"
  },
  "geometry": {"coordinates":[-71.204423,42.077434],"type":"Point"}
}
