{
  "type": "Feature",
  "properties": {
    "iso:country":"US",
    "sg:address":"26 Foundry Rd",
    "sg:city":"Sharon",
    "sg:classifiers":[
        {
            "category":"Retail",
            "subcategory":"Laundry & Dry Cleaning",
            "type":"Services"
        }
    ],
    "sg:phone":"+1 781 793 0202",
    "sg:postcode":"02067",
    "sg:province":"MA",
    "sg:tags":[
        "cleaners",
        "rug",
        "carpet"
    ],
    "wof:name":"Absolute Chem Dry",
    "wof:placetype":"venue"
},
  "geometry": {"coordinates":[-71.20442300000001,42.077434],"type":"Point"}
}