{
  "type": "Feature",
  "properties": {
    "addr:full":"364 Prospect St Leominster MA 01453",
    "addr:housenumber":"364",
    "addr:postcode":"01453",
    "addr:street":"Prospect St",
    "iso:country":"US",
    "sg:address":"364 Prospect St",
    "sg:city":"Leominster",
    "sg:classifiers":[
        {
            "category":"Wholesale",
            "subcategory":"Medical Equipment & Supplies",
            "type":"Manufacturing & Wholesale Goods"
        }
    ],
    "sg:phone":"+1 800 743 5545",
    "sg:postcode":"01453",
    "sg:province":"MA",
    "sg:tags":[
        "wheelchair"
    ],
    "sg:website":"http://www.sourceequipment.com",
    "wof:name":"Source Equipment Co Inc Toll Free-Dial '1' & Then",
    "wof:placetype":"venue"
},
  "geometry": {"coordinates":[-71.725967,42.533649],"type":"Point"}
}