{
  "type": "Feature",
  "properties": {
    "iso:country":"US",
    "sg:address":"15 Harvard St",
    "sg:city":"Quincy",
    "sg:classifiers":[
        {
            "category":"Government",
            "subcategory":"Office",
            "type":"Public Place"
        }
    ],
    "sg:phone":"+1   ",
    "sg:postcode":"02171",
    "sg:province":"MA",
    "sg:tags":[
        "program",
        "administrative"
    ],
    "wof:name":"Atlantic Nighborhood Cmnty Ctr",
    "wof:placetype":"venue"
},
  "geometry": {"coordinates":[-71.03751,42.26854],"type":"Point"}
}