{
  "type": "Feature",
  "properties": {
    "iso:country":"US",
    "sg:address":"23 Walnut St",
    "sg:city":"Whitman",
    "sg:classifiers":[
        {
            "category":"Real Estate",
            "subcategory":"Real Estate Services",
            "type":"Services"
        },
        {
            "category":"Real Estate",
            "subcategory":"Real Estate Agent",
            "type":"Services"
        }
    ],
    "sg:phone":"+1 781 293 9800",
    "sg:postcode":"02382",
    "sg:province":"MA",
    "sg:tags":[
        "buyer",
        "broker"
    ],
    "wof:name":"Celebration Real Estate",
    "wof:placetype":"venue"
},
  "geometry": {"coordinates":[-70.944969,42.094231],"type":"Point"}
}