{
  "type": "Feature",
  "properties": {
    "addr:full":"705 Alger St Winchendon MA 01475",
    "addr:housenumber":"705",
    "addr:postcode":"01475",
    "addr:street":"Alger St",
    "iso:country":"US",
    "sg:address":"705 Alger St",
    "sg:city":"Winchendon",
    "sg:classifiers":[
        {
            "category":"Recreation",
            "type":"Entertainment"
        }
    ],
    "sg:phone":"+1 978 297 5435",
    "sg:postcode":"01475",
    "sg:province":"MA",
    "sg:tags":[
        "riding",
        "academy"
    ],
    "wof:name":"Hyridge Stables",
    "wof:placetype":"venue"
},
  "geometry": {"coordinates":[-72.079885,42.640802],"type":"Point"}
}