{
  "type": "Feature",
  "properties": {
    "addr:full":"450 N Main St Sharon MA 02067",
    "addr:housenumber":"450",
    "addr:postcode":"02067",
    "addr:street":"N Main St",
    "iso:country":"US",
    "sg:address":"450 N Main St",
    "sg:city":"Sharon",
    "sg:classifiers":[
        {
            "category":"Health Services",
            "subcategory":"Doctor",
            "type":"Services"
        }
    ],
    "sg:phone":"+1 781 784 5402",
    "sg:postcode":"02067",
    "sg:province":"MA",
    "sg:tags":[
        "psychologist"
    ],
    "wof:name":"Sprague Rick Ph.D.",
    "wof:placetype":"venue"
},
  "geometry": {"coordinates":[-71.15120400000001,42.138045],"type":"Point"}
}