{
  "type": "Feature",
  "properties": {
    "iso:country":"US",
    "sg:address":"268 Summer St Lower Level",
    "sg:city":"Boston",
    "sg:classifiers":[
        {
            "category":"Shopping",
            "subcategory":"Clothing, Apparel, & Fashions",
            "type":"Retail Goods"
        }
    ],
    "sg:phone":"+1 617 807 0530",
    "sg:postcode":"02210",
    "sg:province":"MA",
    "sg:tags":[
        "men's",
        "clothing"
    ],
    "sg:website":"www.astorandblack.com",
    "wof:name":"Astor & Black Custom Clothiers",
    "wof:placetype":"venue"
},
  "geometry": {"coordinates":[-71.050383,42.350352],"type":"Point"}
}