{
  "type": "Feature",
  "properties": {
    "iso:country":"US",
    "sg:address":"434 Russell St",
    "sg:city":"Hadley",
    "sg:classifiers":[
        {
            "category":"Food & Beverages",
            "subcategory":"Groceries & Convenience Stores",
            "type":"Retail Goods"
        }
    ],
    "sg:phone":"+1 413 253 5257",
    "sg:postcode":"01035",
    "sg:province":"MA",
    "wof:name":"O'Connell's Convenience Plus",
    "wof:placetype":"venue"
},
  "geometry": {"coordinates":[-72.538293,42.364201],"type":"Point"}
}