{
  "type": "Feature",
  "properties": {
    "addr:full": "63 Albion St Wakefield MA 01880",
    "addr:housenumber": "63",
    "addr:postcode": "01880",
    "addr:street": "Albion St",
    "iso:country": "US",
    "sg:address": "63 Albion St",
    "sg:city": "Wakefield",
    "sg:classifiers": [
      {
        "category": "Personal",
        "subcategory": "Beauty Salon",
        "type": "Services"
      }
    ],
    "sg:phone": "+1   ",
    "sg:postcode": "01880",
    "sg:province": "MA",
    "sg:tags": [
      "shop"
    ],
    "wof:name": "Donna Procaccini",
    "wof:placetype": "venue"
  },
  "geometry": {"coordinates":[-71.074013,42.502596],"type":"Point"}
}
