{
  "type": "Feature",
  "properties": {
    "iso:country":"US",
    "sg:address":"507 Main St",
    "sg:city":"Hyannis",
    "sg:classifiers":[
        {
            "category":"Real Estate",
            "subcategory":"Real Estate Agent",
            "type":"Services"
        }
    ],
    "sg:phone":"+1   ",
    "sg:postcode":"02601",
    "sg:province":"MA",
    "wof:name":"John Lemos Real Estate",
    "wof:placetype":"venue"
},
  "geometry": {"coordinates":[-70.287791,41.650742],"type":"Point"}
}