{
  "type": "Feature",
  "properties": {
    "iso:country":"US",
    "sg:address":"89 South St",
    "sg:city":"Boston",
    "sg:classifiers":[
        {
            "category":"Professional",
            "subcategory":"Computer Services",
            "type":"Services"
        }
    ],
    "sg:phone":"+1 617 531 3803",
    "sg:postcode":"02111",
    "sg:province":"MA",
    "sg:tags":[
        "isp",
        "provider",
        "internet"
    ],
    "wof:name":"Silicon Valley Internet Partne",
    "wof:placetype":"venue"
},
  "geometry": {"coordinates":[-71.05719999999999,42.351639],"type":"Point"}
}