{
  "type": "Feature",
  "properties": {
    "addr:full": "22 Tucker Dr Leominster MA 01453",
    "addr:housenumber": "22",
    "addr:postcode": "01453",
    "addr:street": "Tucker Dr",
    "iso:country": "US",
    "sg:address": "22 Tucker Dr",
    "sg:city": "Leominster",
    "sg:classifiers": [
      {
        "category": "Manufacturing",
        "subcategory": "Rubber \u0026 Plastics",
        "type": "Manufacturing \u0026 Wholesale Goods"
      }
    ],
    "sg:phone": "+1 978 537 2570",
    "sg:postcode": "01453",
    "sg:province": "MA",
    "sg:website": "www.jam-plastics.com",
    "wof:name": "JAM Plastics Inc",
    "wof:placetype": "venue"
  },
  "geometry": {"coordinates":[-71.745147,42.551392],"type":"Point"}
}
