{
  "type": "Feature",
  "properties": {
    "iso:country":"US",
    "sg:address":"22 Tucker Dr",
    "sg:city":"Leominster",
    "sg:classifiers":[
        {
            "category":"Manufacturing",
            "subcategory":"Rubber & Plastics",
            "type":"Manufacturing & Wholesale Goods"
        }
    ],
    "sg:phone":"+1 978 537 2570",
    "sg:postcode":"01453",
    "sg:province":"MA",
    "sg:website":"www.jam-plastics.com",
    "wof:name":"JAM Plastics Inc",
    "wof:placetype":"venue"
},
  "geometry": {"coordinates":[-71.745147,42.551392],"type":"Point"}
}