{
  "type": "Feature",
  "properties": {
    "addr:full":"16 Powderhouse Ln Boxford MA 01921",
    "addr:housenumber":"16",
    "addr:postcode":"01921",
    "addr:street":"Powderhouse Ln",
    "iso:country":"US",
    "sg:address":"16 Powderhouse Ln",
    "sg:city":"Boxford",
    "sg:classifiers":[
        {
            "category":"Health Services",
            "subcategory":"Doctor",
            "type":"Services"
        }
    ],
    "sg:phone":"+1   ",
    "sg:postcode":"01921",
    "sg:province":"MA",
    "sg:tags":[
        "medical"
    ],
    "wof:name":"Elmi Saeid M D P C",
    "wof:placetype":"venue"
},
  "geometry": {"coordinates":[-71.009546,42.694733],"type":"Point"}
}