{
  "type": "Feature",
  "properties": {
    "addr:full": "107 Millbury St Worcester MA 01610",
    "addr:housenumber": "107",
    "addr:postcode": "01610",
    "addr:street": "Millbury St",
    "iso:country": "US",
    "sg:address": "107 Millbury St",
    "sg:city": "Worcester",
    "sg:classifiers": [
      {
        "category": "Restaurant",
        "type": "Food \u0026 Drink"
      }
    ],
    "sg:phone": "+1 508 752 9979",
    "sg:postcode": "01610",
    "sg:province": "MA",
    "sg:tags": [
      "eating"
    ],
    "wof:name": "Grand Island Deli \u0026 Pub",
    "wof:placetype": "venue"
  },
  "geometry": {"coordinates":[-71.799218,42.252512],"type":"Point"}
}
