{
  "type": "Feature",
  "properties": {
    "iso:country":"US",
    "sg:address":"107 Millbury St",
    "sg:city":"Worcester",
    "sg:classifiers":[
        {
            "category":"Restaurant",
            "type":"Food & Drink"
        }
    ],
    "sg:phone":"+1 508 752 9979",
    "sg:postcode":"01610",
    "sg:province":"MA",
    "sg:tags":[
        "eating"
    ],
    "wof:name":"Grand Island Deli & Pub",
    "wof:placetype":"venue"
},
  "geometry": {"coordinates":[-71.799218,42.252512],"type":"Point"}
}