{
  "type": "Feature",
  "properties": {
    "addr:full":"680 Chequessett Neck Rd Wellfleet MA 02667",
    "addr:housenumber":"680",
    "addr:postcode":"02667",
    "addr:street":"Chequessett Neck Rd",
    "iso:country":"US",
    "sg:address":"680 Chequessett Neck Rd",
    "sg:city":"Wellfleet",
    "sg:classifiers":[
        {
            "category":"Organizations",
            "subcategory":"Membership Organization",
            "type":"Services"
        },
        {
            "category":"Sports & Exercise",
            "subcategory":"Golf",
            "type":"Entertainment"
        }
    ],
    "sg:phone":"+1 508 349 3704",
    "sg:postcode":"02667",
    "sg:province":"MA",
    "sg:tags":[
        "club",
        "course",
        "private"
    ],
    "sg:website":"http://www.cycc.net",
    "wof:name":"Chequessett Yacht & Country Club Inc",
    "wof:placetype":"venue"
},
  "geometry": {"coordinates":[-70.05285600000001,41.929291],"type":"Point"}
}