{
  "type": "Feature",
  "properties": {
    "addr:full": "7 Stearns Rd Bedford MA 01730",
    "addr:housenumber": "7",
    "addr:postcode": "01730",
    "addr:street": "Stearns Rd",
    "iso:country": "US",
    "sg:address": "7 Stearns Rd",
    "sg:city": "Bedford",
    "sg:classifiers": [
      {
        "category": "Professional",
        "subcategory": "Management \u0026 Consulting",
        "type": "Services"
      }
    ],
    "sg:phone": "+1 781 271 9000",
    "sg:postcode": "01730",
    "sg:province": "MA",
    "sg:tags": [
      "consultant",
      "business"
    ],
    "wof:name": "ROIC",
    "wof:placetype": "venue"
  },
  "geometry": {"coordinates":[-71.294966,42.511263],"type":"Point"}
}
