{
  "type": "Feature",
  "properties": {
    "iso:country":"US",
    "sg:address":"7 Stearns Rd",
    "sg:city":"Bedford",
    "sg:classifiers":[
        {
            "category":"Professional",
            "subcategory":"Management & Consulting",
            "type":"Services"
        }
    ],
    "sg:phone":"+1 781 271 9000",
    "sg:postcode":"01730",
    "sg:province":"MA",
    "sg:tags":[
        "consultant",
        "business"
    ],
    "wof:name":"ROIC",
    "wof:placetype":"venue"
},
  "geometry": {"coordinates":[-71.294966,42.511263],"type":"Point"}
}