{
  "type": "Feature",
  "properties": {
    "addr:full":"36 Cambridgepark Dr Cambridge MA 02140",
    "addr:housenumber":"36",
    "addr:postcode":"02140",
    "addr:street":"Cambridgepark Dr",
    "iso:country":"US",
    "sg:address":"36 Cambridgepark Dr",
    "sg:city":"Cambridge",
    "sg:classifiers":[
        {
            "category":"Internet Cafe",
            "subcategory":"None",
            "type":"Food & Drink"
        },
        {
            "category":"Professional",
            "subcategory":"Computer Services",
            "type":"Services"
        }
    ],
    "sg:phone":"+1 617 864 0636",
    "sg:postcode":"02140",
    "sg:province":"MA",
    "sg:tags":[
        "product",
        "designer",
        "network",
        "consultant",
        "system",
        "design",
        "software"
    ],
    "sg:website":"http://www.vecnatech.com",
    "wof:name":"Vecna Medical",
    "wof:placetype":"venue"
},
  "geometry": {"coordinates":[-71.142308,42.39462],"type":"Point"}
}