{
  "type": "Feature",
  "properties": {
    "addr:full": "65 Sawmill Rd Marstons Mills MA 02648",
    "addr:housenumber": "65",
    "addr:postcode": "02648",
    "addr:street": "Sawmill Rd",
    "iso:country": "US",
    "sg:address": "65 Sawmill Rd",
    "sg:city": "Marstons Mills",
    "sg:classifiers": [
      {
        "category": "Building \u0026 Trades",
        "subcategory": "Construction",
        "type": "Services"
      }
    ],
    "sg:phone": "+1 508 771 8604",
    "sg:postcode": "02648",
    "sg:province": "MA",
    "sg:tags": [
      "contractor"
    ],
    "sg:website": "www.schulzebuildingco.com",
    "wof:name": "Schulze Building Co",
    "wof:placetype": "venue"
  },
  "geometry": {"coordinates":[-70.4207,41.6772],"type":"Point"}
}
