{
  "type": "Feature",
  "properties": {
    "addr:full": "25 Butterhill Rd Pelham MA 01002",
    "addr:housenumber": "25",
    "addr:postcode": "01002",
    "addr:street": "Butterhill Rd",
    "iso:country": "US",
    "sg:address": "25 Butterhill Rd",
    "sg:city": "Pelham",
    "sg:classifiers": [
      {
        "category": "Building \u0026 Trades",
        "subcategory": "Construction",
        "type": "Services"
      }
    ],
    "sg:phone": "+1 413 253 4800",
    "sg:postcode": "01002",
    "sg:province": "MA",
    "sg:tags": [
      "contractor"
    ],
    "sg:website": "http://www.msmbuilders.com",
    "wof:name": "M S M Builders",
    "wof:placetype": "venue"
  },
  "geometry": {"coordinates":[-72.44771,42.367762],"type":"Point"}
}
