{
  "type": "Feature",
  "properties": {
    "iso:country":"US",
    "sg:address":"78 Northside Rd",
    "sg:city":"Charlton",
    "sg:classifiers":[
        {
            "category":"Communications",
            "type":"Services"
        }
    ],
    "sg:phone":"+1 603 870 9849",
    "sg:postcode":"01507",
    "sg:province":"MA",
    "wof:name":"Usn Communications Inc",
    "wof:placetype":"venue"
},
  "geometry": {"coordinates":[-71.95902100000001,42.152514],"type":"Point"}
}