{
  "type": "Feature",
  "properties": {
    "addr:full":"225 Waverley Oak Rd Waltham MA 02452",
    "addr:housenumber":"225",
    "addr:postcode":"02452",
    "addr:street":"Waverley Oak Rd",
    "iso:country":"US",
    "sg:address":"225 Waverley Oak Rd",
    "sg:city":"Waltham",
    "sg:classifiers":[
        {
            "category":"Food & Beverages",
            "subcategory":"Groceries & Convenience Stores",
            "type":"Retail Goods"
        }
    ],
    "sg:phone":"+1 781 893 1540",
    "sg:postcode":"02452",
    "sg:province":"MA",
    "wof:name":"Waverly Oaks Shell",
    "wof:placetype":"venue"
},
  "geometry": {"coordinates":[-71.214921,42.381574],"type":"Point"}
}