{
  "type": "Feature",
  "properties": {
    "iso:country":"US",
    "sg:address":"14 Maverick Sq",
    "sg:city":"Boston",
    "sg:classifiers":[
        {
            "category":"Food & Beverages",
            "subcategory":"Groceries & Convenience Stores",
            "type":"Retail Goods"
        }
    ],
    "sg:phone":"+1 617 567 6025",
    "sg:postcode":"02128",
    "sg:province":"MA",
    "wof:name":"Store 24 Inc the",
    "wof:placetype":"venue"
},
  "geometry": {"coordinates":[-71.039902,42.3689],"type":"Point"}
}