{
  "type": "Feature",
  "properties": {
    "addr:full": "14 Maverick Sq Boston MA 02128",
    "addr:housenumber": "14",
    "addr:postcode": "02128",
    "addr:street": "Maverick Sq",
    "iso:country": "US",
    "sg:address": "14 Maverick Sq",
    "sg:city": "Boston",
    "sg:classifiers": [
      {
        "category": "Food \u0026 Beverages",
        "subcategory": "Groceries \u0026 Convenience Stores",
        "type": "Retail Goods"
      }
    ],
    "sg:phone": "+1 617 567 6025",
    "sg:postcode": "02128",
    "sg:province": "MA",
    "wof:name": "Store 24 Inc the",
    "wof:placetype": "venue"
  },
  "geometry": {"coordinates":[-71.039902,42.3689],"type":"Point"}
}
