{
  "type": "Feature",
  "properties": {
    "iso:country":"US",
    "sg:address":"408 Cabot St",
    "sg:city":"Beverly",
    "sg:classifiers":[
        {
            "category":"Personal",
            "subcategory":"Beauty Salon",
            "type":"Services"
        }
    ],
    "sg:phone":"+1 978 927 2560",
    "sg:postcode":"01915",
    "sg:province":"MA",
    "sg:tags":[
        "manicuring"
    ],
    "wof:name":"Emily Nails",
    "wof:placetype":"venue"
},
  "geometry": {"coordinates":[-70.883033,42.559839],"type":"Point"}
}