{
  "type": "Feature",
  "properties": {
    "addr:full": "285 Washington St Norwell MA 02061",
    "addr:housenumber": "285",
    "addr:postcode": "02061",
    "addr:street": "Washington St",
    "iso:country": "US",
    "sg:address": "285 Washington St",
    "sg:city": "Norwell",
    "sg:classifiers": [
      {
        "category": "Fast Food",
        "type": "Food \u0026 Drink"
      },
      {
        "category": "Personal",
        "type": "Services"
      },
      {
        "category": "Restaurant",
        "type": "Food \u0026 Drink"
      },
      {
        "category": "Retail",
        "subcategory": "Event Space",
        "type": "Services"
      },
      {
        "category": "Professional",
        "type": "Services"
      }
    ],
    "sg:phone": "+1 781 651 0135",
    "sg:postcode": "02061",
    "sg:province": "MA",
    "sg:tags": [
      "grill",
      "bar",
      "facility",
      "hall",
      "delivery",
      "planning",
      "take",
      "reception",
      "party",
      "banquet"
    ],
    "sg:website": "http://www.thefours.com",
    "wof:name": "The Fours",
    "wof:placetype": "venue"
  },
  "geometry": {"coordinates":[-70.867691,42.164181],"type":"Point"}
}
