{
  "type": "Feature",
  "properties": {
    "iso:country":"US",
    "sg:address":"431 Lincoln St",
    "sg:city":"Marlborough",
    "sg:classifiers":[
        {
            "category":"Autos & Motor Vehicles",
            "subcategory":"Fuel & Gas Station",
            "type":"Retail Goods"
        }
    ],
    "sg:phone":"+1 508 485 9772",
    "sg:postcode":"01752",
    "sg:province":"MA",
    "sg:tags":[
        "oil"
    ],
    "wof:name":"Shell Food Mart",
    "wof:placetype":"venue"
},
  "geometry": {"coordinates":[-71.559282,42.346146],"type":"Point"}
}