{
  "type": "Feature",
  "properties": {
    "iso:country":"US",
    "sg:address":"70 High St",
    "sg:city":"West Barnstable",
    "sg:classifiers":[
        {
            "category":"Travel",
            "subcategory":"Hotels & Motels",
            "type":"Entertainment"
        },
        {
            "category":"Travel",
            "subcategory":"Bed & Breakfast",
            "type":"Entertainment"
        }
    ],
    "sg:phone":"+1 508 362 4441",
    "sg:postcode":"02668",
    "sg:province":"MA",
    "sg:tags":[
        "house",
        "guest"
    ],
    "sg:website":"www.thehighpointeinn.com",
    "wof:name":"High Pointe Inn",
    "wof:placetype":"venue"
},
  "geometry": {"coordinates":[-70.3907,41.7175],"type":"Point"}
}