{
  "type": "Feature",
  "properties": {
    "addr:full": "70 High St West Barnstable MA 02668",
    "addr:housenumber": "70",
    "addr:postcode": "02668",
    "addr:street": "High St",
    "iso:country": "US",
    "sg:address": "70 High St",
    "sg:city": "West Barnstable",
    "sg:classifiers": [
      {
        "category": "Travel",
        "subcategory": "Hotels \u0026 Motels",
        "type": "Entertainment"
      },
      {
        "category": "Travel",
        "subcategory": "Bed \u0026 Breakfast",
        "type": "Entertainment"
      }
    ],
    "sg:phone": "+1 508 362 4441",
    "sg:postcode": "02668",
    "sg:province": "MA",
    "sg:tags": [
      "house",
      "guest"
    ],
    "sg:website": "www.thehighpointeinn.com",
    "wof:name": "High Pointe Inn",
    "wof:placetype": "venue"
  },
  "geometry": {"coordinates":[-70.3907,41.7175],"type":"Point"}
}
