{
  "type": "Feature",
  "properties": {
    "iso:country":"US",
    "sg:address":"179 Main St",
    "sg:city":"Ashland",
    "sg:classifiers":[
        {
            "category":"Restaurant",
            "type":"Food & Drink"
        }
    ],
    "sg:phone":"+1 508 881 1778",
    "sg:postcode":"01721",
    "sg:province":"MA",
    "sg:website":"www.stonespublichouse.com",
    "wof:name":"Stones Public House",
    "wof:placetype":"venue"
},
  "geometry": {"coordinates":[-71.464873,42.260408],"type":"Point"}
}