{
  "type": "Feature",
  "properties": {
    "iso:country":"US",
    "sg:address":"772 Purchase St",
    "sg:city":"New Bedford",
    "sg:classifiers":[
        {
            "category":"Shopping",
            "subcategory":"Clothing, Apparel, & Fashions",
            "type":"Retail Goods"
        }
    ],
    "sg:phone":"+1 508 999 2166",
    "sg:postcode":"02740",
    "sg:province":"MA",
    "sg:tags":[
        "t"
    ],
    "sg:website":"www.theblackwhale.com",
    "wof:name":"Elaine's T-Shirts & Costumes",
    "wof:placetype":"venue"
},
  "geometry": {"coordinates":[-70.92579499999999,41.634352],"type":"Point"}
}