{
  "type": "Feature",
  "properties": {
    "iso:country":"US",
    "sg:address":"45 School St Apt 507",
    "sg:city":"Quincy",
    "sg:classifiers":[
        {
            "category":"Real Estate",
            "subcategory":"Real Estate Operator",
            "type":"Services"
        }
    ],
    "sg:phone":"+1 617 847 1818",
    "sg:postcode":"02169",
    "sg:province":"MA",
    "sg:tags":[
        "apartment"
    ],
    "wof:name":"Granite Place Apts",
    "wof:placetype":"venue"
},
  "geometry": {"coordinates":[-71.00195600000001,42.244582],"type":"Point"}
}