{
  "type": "Feature",
  "properties": {
    "addr:full": "11 Patterson Brook Rd Wareham MA 02576",
    "addr:housenumber": "11",
    "addr:postcode": "02576",
    "addr:street": "Patterson Brook Rd",
    "iso:country": "US",
    "sg:address": "11 Patterson Brook Rd",
    "sg:city": "Wareham",
    "sg:classifiers": [
      {
        "category": "Professional",
        "subcategory": "Engineering",
        "type": "Services"
      }
    ],
    "sg:phone": "+1 508 291 2727",
    "sg:postcode": "02576",
    "sg:province": "MA",
    "sg:tags": [
      "general",
      "contractor"
    ],
    "wof:name": "Hydro Engineering Group Inc",
    "wof:placetype": "venue"
  },
  "geometry": {"coordinates":[-70.748518,41.783086],"type":"Point"}
}
