{
  "type": "Feature",
  "properties": {
    "iso:country":"US",
    "sg:address":"121 Precinct St",
    "sg:city":"Middleboro",
    "sg:classifiers":[
        {
            "category":"Building & Trades",
            "subcategory":"Construction",
            "type":"Services"
        }
    ],
    "sg:phone":"+1 508 947 4500",
    "sg:postcode":"02346",
    "sg:province":"MA",
    "sg:tags":[
        "home",
        "improvement"
    ],
    "wof:name":"Highlite Construction Co",
    "wof:placetype":"venue"
},
  "geometry": {"coordinates":[-70.905186,41.916867],"type":"Point"}
}