{
  "type": "Feature",
  "properties": {
    "addr:full": "365 Gannett Rd Scituate MA 02066",
    "addr:housenumber": "365",
    "addr:postcode": "02066",
    "addr:street": "Gannett Rd",
    "iso:country": "US",
    "sg:address": "365 Gannett Rd",
    "sg:city": "Scituate",
    "sg:classifiers": [
      {
        "category": "Professional",
        "subcategory": "Management \u0026 Consulting",
        "type": "Services"
      }
    ],
    "sg:phone": "+1 781 545 3381",
    "sg:postcode": "02066",
    "sg:province": "MA",
    "sg:tags": [
      "business"
    ],
    "wof:name": "C T Outfitters",
    "wof:placetype": "venue"
  },
  "geometry": {"coordinates":[-70.785131,42.219248],"type":"Point"}
}
