{
  "type": "Feature",
  "properties": {
    "addr:full":"48 Revere St Winthrop MA 02152",
    "addr:housenumber":"48",
    "addr:postcode":"02152",
    "addr:street":"Revere St",
    "iso:country":"US",
    "sg:address":"48 Revere St",
    "sg:city":"Winthrop",
    "sg:classifiers":[
        {
            "category":"Building & Trades",
            "subcategory":"Locksmith",
            "type":"Services"
        }
    ],
    "sg:phone":"+1 617 329 6038",
    "sg:postcode":"02152",
    "sg:province":"MA",
    "sg:tags":[
        "key"
    ],
    "wof:name":"Anytime Anywhere Emergency Locksmith",
    "wof:placetype":"venue"
},
  "geometry": {"coordinates":[-70.98078599999999,42.382395],"type":"Point"}
}