{
  "type": "Feature",
  "properties": {
    "addr:full":"16 Ridgeway Rd North Reading MA 01864",
    "addr:housenumber":"16",
    "addr:postcode":"01864",
    "addr:street":"Ridgeway Rd",
    "iso:country":"US",
    "sg:address":"16 Ridgeway Rd",
    "sg:city":"North Reading",
    "sg:classifiers":[
        {
            "category":"Recreation",
            "type":"Entertainment"
        }
    ],
    "sg:phone":"+1   ",
    "sg:postcode":"01864",
    "sg:province":"MA",
    "sg:tags":[
        "club",
        "membership"
    ],
    "wof:name":"Little League Baseball In",
    "wof:placetype":"venue"
},
  "geometry": {"coordinates":[-71.10319,42.583248],"type":"Point"}
}