{
  "type": "Feature",
  "properties": {
    "addr:full": "18 Glen Rd Jamaica Plain MA 02130",
    "addr:housenumber": "18",
    "addr:postcode": "02130",
    "addr:street": "Glen Rd",
    "iso:country": "US",
    "sg:address": "18 Glen Rd",
    "sg:city": "Jamaica Plain",
    "sg:classifiers": [
      {
        "category": "Organizations",
        "subcategory": "Community Association",
        "type": "Services"
      }
    ],
    "sg:phone": "+1 617 522 6127",
    "sg:postcode": "02130",
    "sg:province": "MA",
    "sg:tags": [
      "club"
    ],
    "wof:name": "Trinidad \u0026 Tobago Social Club",
    "wof:placetype": "venue"
  },
  "geometry": {"coordinates":[-71.10329,42.309205],"type":"Point"}
}
