{
  "type": "Feature",
  "properties": {
    "iso:country":"US",
    "sg:address":"18 Glen Rd",
    "sg:city":"Jamaica Plain",
    "sg:classifiers":[
        {
            "category":"Organizations",
            "subcategory":"Community Association",
            "type":"Services"
        }
    ],
    "sg:phone":"+1 617 522 6127",
    "sg:postcode":"02130",
    "sg:province":"MA",
    "sg:tags":[
        "club"
    ],
    "wof:name":"Trinidad & Tobago Social Club",
    "wof:placetype":"venue"
},
  "geometry": {"coordinates":[-71.10329,42.309205],"type":"Point"}
}