{
  "type": "Feature",
  "properties": {
    "iso:country":"US",
    "sg:address":"417 Adams St",
    "sg:city":"Dorchester",
    "sg:classifiers":[
        {
            "category":"Building & Trades",
            "subcategory":"Locksmith",
            "type":"Services"
        }
    ],
    "sg:phone":"+1 617 895 3430",
    "sg:postcode":"02122",
    "sg:province":"MA",
    "sg:tags":[
        "key"
    ],
    "wof:name":"24 Hours A Locksmith",
    "wof:placetype":"venue"
},
  "geometry": {"coordinates":[-71.056426,42.295071],"type":"Point"}
}