{
  "type": "Feature",
  "properties": {
    "addr:full":"39 Union Ave Sudbury MA 01776",
    "addr:housenumber":"39",
    "addr:postcode":"01776",
    "addr:street":"Union Ave",
    "iso:country":"US",
    "sg:address":"39 Union Ave",
    "sg:city":"Sudbury",
    "sg:classifiers":[
        {
            "category":"Home & Garden",
            "subcategory":"Carpets & Floor Coverings",
            "type":"Retail Goods"
        }
    ],
    "sg:phone":"+1 508 788 0464",
    "sg:postcode":"01776",
    "sg:province":"MA",
    "sg:tags":[
        "material",
        "rug"
    ],
    "wof:name":"Original Saxonville Carpet Store",
    "wof:placetype":"venue"
},
  "geometry": {"coordinates":[-71.421898,42.363392],"type":"Point"}
}