{
  "type": "Feature",
  "properties": {
    "addr:full":"235 Newbury St Danvers MA 01923",
    "addr:housenumber":"235",
    "addr:postcode":"01923",
    "addr:street":"Newbury St",
    "iso:country":"US",
    "sg:address":"235 Newbury St",
    "sg:city":"Danvers",
    "sg:classifiers":[
        {
            "category":"Real Estate",
            "subcategory":"Surveying",
            "type":"Services"
        }
    ],
    "sg:phone":"+1 781 592 8386",
    "sg:postcode":"01923",
    "sg:province":"MA",
    "sg:tags":[
        "surveyor"
    ],
    "wof:name":"Carter & Towers Engineering",
    "wof:placetype":"venue"
},
  "geometry": {"coordinates":[-70.970652,42.57563],"type":"Point"}
}