{
  "type": "Feature",
  "properties": {
    "addr:full":"161 Copeland St Quincy MA 02169",
    "addr:housenumber":"161",
    "addr:postcode":"02169",
    "addr:street":"Copeland St",
    "iso:country":"US",
    "sg:address":"161 Copeland St",
    "sg:city":"Quincy",
    "sg:classifiers":[
        {
            "category":"Professional",
            "type":"Services"
        }
    ],
    "sg:phone":"+1 617 471 2345",
    "sg:postcode":"02169",
    "sg:province":"MA",
    "sg:tags":[
        "establishment"
    ],
    "wof:name":"PC Direct",
    "wof:placetype":"venue"
},
  "geometry": {"coordinates":[-71.022132,42.24314],"type":"Point"}
}