{
  "type": "Feature",
  "properties": {
    "iso:country":"US",
    "sg:address":"345 Neponset St",
    "sg:city":"Canton",
    "sg:classifiers":[
        {
            "category":"Professional",
            "subcategory":"Lawyer & Legal Services",
            "type":"Services"
        }
    ],
    "sg:phone":"+1 781 828 7771",
    "sg:postcode":"02021",
    "sg:province":"MA",
    "wof:name":"Titlebaum Joseph E Attorney and Counslr At Lw Atty",
    "wof:placetype":"venue"
},
  "geometry": {"coordinates":[-71.154999,42.158901],"type":"Point"}
}