{
  "type": "Feature",
  "properties": {
    "addr:full": "10 Holden Street Malden MA 02148",
    "addr:housenumber": "10",
    "addr:postcode": "02148",
    "addr:street": "Holden Street",
    "iso:country": "US",
    "ovtr:label": "Eastern Acupuncture Center, 10 Holden St Malden MA US",
    "ovtr:similarity": 2.9931349754333496,
    "sg:address": "10 Holden Street",
    "sg:city": "Malden",
    "sg:classifiers": [
      {
        "category": "Health Services",
        "subcategory": "Health Practitioner",
        "type": "Services"
      }
    ],
    "sg:phone": "+1 781 324 4300",
    "sg:postcode": "02148",
    "sg:province": "MA",
    "sg:tags": [
      "acupuncture"
    ],
    "wof:name": "Eastern Acupuncture Center",
    "wof:placetype": "venue"
  },
  "geometry": {"coordinates":[-71.063911,42.427802],"type":"Point"}
}
