{
  "type": "Feature",
  "properties": {
    "iso:country":"US",
    "sg:address":"216 Water St",
    "sg:city":"Fitchburg",
    "sg:classifiers":[
        {
            "category":"Building & Trades",
            "subcategory":"Plumbing",
            "type":"Services"
        }
    ],
    "sg:phone":"+1 978 345 4444",
    "sg:postcode":"01420",
    "sg:province":"MA",
    "sg:tags":[
        "contractor"
    ],
    "sg:website":"www.advancedenergyconcepts.com",
    "wof:name":"Fitchburg Heating & AC CO",
    "wof:placetype":"venue"
},
  "geometry": {"coordinates":[-71.793195,42.578345],"type":"Point"}
}