{
  "type": "Feature",
  "properties": {
    "addr:full":"8 Cambridge Center Cambridge MA 02142",
    "addr:housenumber":"8",
    "addr:postcode":"02142",
    "addr:street":"Cambridge Center",
    "iso:country":"US",
    "sg:address":"8 Cambridge Center",
    "sg:city":"Cambridge",
    "sg:classifiers":[
        {
            "category":"Professional",
            "subcategory":"Computer Services",
            "type":"Services"
        }
    ],
    "sg:phone":"+1 617 444 3000",
    "sg:postcode":"02142",
    "sg:province":"MA",
    "sg:tags":[
        "internet"
    ],
    "wof:name":"Akamai Technologies Inc",
    "wof:placetype":"venue"
},
  "geometry": {"coordinates":[-71.085724,42.36262],"type":"Point"}
}