{
  "type": "Feature",
  "properties": {
    "addr:full": "19 Jan Sebastian Dr Sandwich MA 02563",
    "addr:housenumber": "19",
    "addr:postcode": "02563",
    "addr:street": "Jan Sebastian Dr",
    "iso:country": "US",
    "sg:address": "19 Jan Sebastian Dr",
    "sg:city": "Sandwich",
    "sg:classifiers": [
      {
        "category": "Freight",
        "type": "Transportation"
      }
    ],
    "sg:phone": "+1 508 888 1255",
    "sg:postcode": "02563",
    "sg:province": "MA",
    "sg:tags": [
      "broker",
      "trucking"
    ],
    "sg:website": "www.jctransportation.com",
    "wof:name": "J C Assoc",
    "wof:placetype": "venue"
  },
  "geometry": {"coordinates":[-70.483015,41.71838],"type":"Point"}
}
