{
  "type": "Feature",
  "properties": {
    "iso:country":"US",
    "sg:address":"19 Jan Sebastian Dr",
    "sg:city":"Sandwich",
    "sg:classifiers":[
        {
            "category":"Freight",
            "type":"Transportation"
        }
    ],
    "sg:phone":"+1 508 888 1255",
    "sg:postcode":"02563",
    "sg:province":"MA",
    "sg:tags":[
        "broker",
        "trucking"
    ],
    "sg:website":"www.jctransportation.com",
    "wof:name":"J C Assoc",
    "wof:placetype":"venue"
},
  "geometry": {"coordinates":[-70.48301499999999,41.71838],"type":"Point"}
}