{
  "type": "Feature",
  "properties": {
    "addr:full":"78 Pine St Attleboro MA 02703",
    "addr:housenumber":"78",
    "addr:postcode":"02703",
    "addr:street":"Pine St",
    "iso:country":"US",
    "sg:address":"78 Pine St",
    "sg:city":"Attleboro",
    "sg:classifiers":[
        {
            "category":"Food & Beverages",
            "subcategory":"Groceries & Convenience Stores",
            "type":"Retail Goods"
        }
    ],
    "sg:phone":"+1 508 222 8721",
    "sg:postcode":"02703",
    "sg:province":"MA",
    "sg:tags":[
        "grocer"
    ],
    "wof:name":"International Market",
    "wof:placetype":"venue"
},
  "geometry": {"coordinates":[-71.281171,41.941095],"type":"Point"}
}