{
  "type": "Feature",
  "properties": {
    "iso:country":"US",
    "sg:address":"76 Tonawanda St",
    "sg:city":"Dorchester Center",
    "sg:classifiers":[
        {
            "category":"Home & Garden",
            "subcategory":"Household Appliances",
            "type":"Retail Goods"
        }
    ],
    "sg:phone":"+1 617 288 3028",
    "sg:postcode":"02124",
    "sg:province":"MA",
    "sg:tags":[
        "repair"
    ],
    "wof:name":"Peerless Heating Cooling & Appliance Repair",
    "wof:placetype":"venue"
},
  "geometry": {"coordinates":[-71.0682,42.2982],"type":"Point"}
}