{
  "type": "Feature",
  "properties": {
    "addr:full":"1475 Mohawk Trl Charlemont MA 01339",
    "addr:housenumber":"1475",
    "addr:postcode":"01339",
    "addr:street":"Mohawk Trl",
    "iso:country":"US",
    "sg:address":"1475 Mohawk Trl",
    "sg:city":"Charlemont",
    "sg:classifiers":[
        {
            "category":"Shopping",
            "subcategory":"Gifts & Souvenirs",
            "type":"Retail Goods"
        }
    ],
    "sg:phone":"+1 413 339 4096",
    "sg:postcode":"01339",
    "sg:province":"MA",
    "sg:tags":[
        "shop"
    ],
    "wof:name":"Indian Plaza Gift Shop",
    "wof:placetype":"venue"
},
  "geometry": {"coordinates":[-72.82921399999999,42.617774],"type":"Point"}
}