{
  "type": "Feature",
  "properties": {
    "iso:country":"US",
    "sg:address":"4 Welby Rd",
    "sg:city":"New Bedford",
    "sg:classifiers":[
        {
            "category":"Building & Trades",
            "subcategory":"Construction",
            "type":"Services"
        }
    ],
    "sg:phone":"+1 508 998 9700",
    "sg:postcode":"02745",
    "sg:province":"MA",
    "sg:tags":[
        "home",
        "builder"
    ],
    "wof:name":"Morency Custom Homes",
    "wof:placetype":"venue"
},
  "geometry": {"coordinates":[-70.948615,41.705417],"type":"Point"}
}