{
  "type": "Feature",
  "properties": {
    "addr:full":"70 Bow St Arlington MA 02474",
    "addr:housenumber":"70",
    "addr:postcode":"02474",
    "addr:street":"Bow St",
    "iso:country":"US",
    "sg:address":"70 Bow St",
    "sg:city":"Arlington",
    "sg:classifiers":[
        {
            "category":"Manufacturing",
            "subcategory":"Metals",
            "type":"Manufacturing & Wholesale Goods"
        }
    ],
    "sg:phone":"+1 781 646 8800",
    "sg:postcode":"02474",
    "sg:province":"MA",
    "sg:tags":[
        "fence"
    ],
    "sg:website":"www.securityfenceco.com",
    "wof:name":"Security Fence Co Inc",
    "wof:placetype":"venue"
},
  "geometry": {"coordinates":[-71.17976,42.426257],"type":"Point"}
}