{
  "type": "Feature",
  "properties": {
    "iso:country":"US",
    "sg:address":"1 Walnut Hill Park",
    "sg:city":"Woburn",
    "sg:classifiers":[
        {
            "category":"Professional",
            "subcategory":"Lawyer & Legal Services",
            "type":"Services"
        }
    ],
    "sg:phone":"+1 781 933 0357",
    "sg:postcode":"01801",
    "sg:province":"MA",
    "wof:name":"Lapierre Neil R Atty",
    "wof:placetype":"venue"
},
  "geometry": {"coordinates":[-71.13200399999999,42.489101],"type":"Point"}
}