{
  "type": "Feature",
  "properties": {
    "addr:full":"258 Beech St Fitchburg MA 01420",
    "addr:housenumber":"258",
    "addr:postcode":"01420",
    "addr:street":"Beech St",
    "iso:country":"US",
    "sg:address":"258 Beech St",
    "sg:city":"Fitchburg",
    "sg:classifiers":[
        {
            "category":"Freight",
            "type":"Transportation"
        }
    ],
    "sg:phone":"+1   ",
    "sg:postcode":"01420",
    "sg:province":"MA",
    "sg:tags":[
        "operator",
        "local",
        "trucking"
    ],
    "wof:name":"M&M Trans Lease Co",
    "wof:placetype":"venue"
},
  "geometry": {"coordinates":[-71.816547,42.577104],"type":"Point"}
}