{
  "type": "Feature",
  "properties": {
    "iso:country":"US",
    "sg:address":"33 Cheriton Rd",
    "sg:city":"Quincy",
    "sg:classifiers":[
        {
            "category":"Manufacturing",
            "subcategory":"Buildings",
            "type":"Manufacturing & Wholesale Goods"
        },
        {
            "category":"Building & Trades",
            "subcategory":"Construction",
            "type":"Services"
        }
    ],
    "sg:phone":"+1 617 479 5948",
    "sg:postcode":"02170",
    "sg:province":"MA",
    "sg:tags":[
        "home",
        "builder",
        "contractor"
    ],
    "wof:name":"Absolute Construction Co",
    "wof:placetype":"venue"
},
  "geometry": {"coordinates":[-71.02033,42.271648],"type":"Point"}
}