{
  "type": "Feature",
  "properties": {
    "addr:full":"53 Nash Hill Rd Williamsburg MA 01096",
    "addr:housenumber":"53",
    "addr:postcode":"01096",
    "addr:street":"Nash Hill Rd",
    "iso:country":"US",
    "sg:address":"53 Nash Hill Rd",
    "sg:city":"Williamsburg",
    "sg:classifiers":[
        {
            "category":"Professional",
            "subcategory":"Management & Consulting",
            "type":"Services"
        }
    ],
    "sg:phone":"+1   ",
    "sg:postcode":"01096",
    "sg:province":"MA",
    "sg:tags":[
        "sub"
    ],
    "wof:name":"Rtm Enterprises",
    "wof:placetype":"venue"
},
  "geometry": {"coordinates":[-72.728252,42.40143],"type":"Point"}
}