{
  "type": "Feature",
  "properties": {
    "iso:country":"US",
    "sg:address":"34 Spruce Cir",
    "sg:city":"Hanover",
    "sg:classifiers":[
        {
            "category":"Food & Beverages",
            "subcategory":"Meat & Fish",
            "type":"Retail Goods"
        }
    ],
    "sg:phone":"+1 781 871 2173",
    "sg:postcode":"02339",
    "sg:province":"MA",
    "sg:tags":[
        "seafood",
        "seafood-wholesale",
        "market"
    ],
    "wof:name":"Michael P O'connell Sea Food",
    "wof:placetype":"venue"
},
  "geometry": {"coordinates":[-70.851737,42.145339],"type":"Point"}
}