{
  "type": "Feature",
  "properties": {
    "addr:full": "34 Spruce Cir Hanover MA 02339",
    "addr:housenumber": "34",
    "addr:postcode": "02339",
    "addr:street": "Spruce Cir",
    "iso:country": "US",
    "sg:address": "34 Spruce Cir",
    "sg:city": "Hanover",
    "sg:classifiers": [
      {
        "category": "Food \u0026 Beverages",
        "subcategory": "Meat \u0026 Fish",
        "type": "Retail Goods"
      }
    ],
    "sg:phone": "+1 781 871 2173",
    "sg:postcode": "02339",
    "sg:province": "MA",
    "sg:tags": [
      "seafood",
      "seafood-wholesale",
      "market"
    ],
    "wof:name": "Michael P O'connell Sea Food",
    "wof:placetype": "venue"
  },
  "geometry": {"coordinates":[-70.851737,42.145339],"type":"Point"}
}
