{
  "type": "Feature",
  "properties": {
    "addr:full": "49 Hawthorne St Cambridge MA 02138",
    "addr:housenumber": "49",
    "addr:postcode": "02138",
    "addr:street": "Hawthorne St",
    "iso:country": "US",
    "sg:address": "49 Hawthorne St",
    "sg:city": "Cambridge",
    "sg:classifiers": [
      {
        "category": "Airline",
        "type": "Transportation"
      }
    ],
    "sg:phone": "+1 617 876 2025",
    "sg:postcode": "02138",
    "sg:province": "MA",
    "sg:tags": [
      "airport"
    ],
    "sg:website": "www.bettina-network.com",
    "wof:name": "Bettina Network Inc",
    "wof:placetype": "venue"
  },
  "geometry": {"coordinates":[-71.126515,42.374649],"type":"Point"}
}
