{
  "type": "Feature",
  "properties": {
    "addr:full": "407 Cabot St Beverly MA 01915",
    "addr:housenumber": "407",
    "addr:postcode": "01915",
    "addr:street": "Cabot St",
    "iso:country": "US",
    "sg:address": "407 Cabot St",
    "sg:city": "Beverly",
    "sg:classifiers": [
      {
        "category": "Retail",
        "subcategory": "Self-service Laundry",
        "type": "Services"
      }
    ],
    "sg:phone": "+1 978 927 9903",
    "sg:postcode": "01915",
    "sg:province": "MA",
    "sg:tags": [
      "coin"
    ],
    "wof:name": "Laundry Basket",
    "wof:placetype": "venue"
  },
  "geometry": {"coordinates":[-70.882039,42.558834],"type":"Point"}
}
