{
  "type": "Feature",
  "properties": {
    "addr:full": "166 Worcester Rd Charlton MA 01507",
    "addr:housenumber": "166",
    "addr:postcode": "01507",
    "addr:street": "Worcester Rd",
    "iso:country": "US",
    "sg:address": "166 Worcester Rd",
    "sg:city": "Charlton",
    "sg:classifiers": [
      {
        "category": "Personal",
        "type": "Services"
      },
      {
        "category": "Sports \u0026 Exercise",
        "subcategory": "Gym",
        "type": "Entertainment"
      },
      {
        "category": "Health Services",
        "subcategory": "Health Practitioner",
        "type": "Services"
      },
      {
        "category": "Arena",
        "subcategory": "Sports Club",
        "type": "Entertainment"
      }
    ],
    "sg:phone": "+1 508 248 2700",
    "sg:postcode": "01507",
    "sg:province": "MA",
    "sg:tags": [
      "control",
      "weight",
      "consultant",
      "program",
      "fitness",
      "physical"
    ],
    "sg:website": "http://www.curves.com",
    "wof:name": "Curves",
    "wof:placetype": "venue"
  },
  "geometry": {"coordinates":[-71.963518,42.144304],"type":"Point"}
}
