{
  "type": "Feature",
  "properties": {
    "iso:country":"US",
    "sg:address":"23 Dedham Ave",
    "sg:city":"Needham",
    "sg:classifiers":[
        {
            "category":"Organizations",
            "subcategory":"Religious Organization",
            "type":"Services"
        }
    ],
    "sg:phone":"+1 781 444 0823",
    "sg:postcode":"02492",
    "sg:province":"MA",
    "sg:tags":[
        "church"
    ],
    "sg:website":"www.uuneedham.org",
    "wof:name":"First Parish In Needham",
    "wof:placetype":"venue"
},
  "geometry": {"coordinates":[-71.235585,42.279885],"type":"Point"}
}