{
  "type": "Feature",
  "properties": {
    "addr:full": "23 Dedham Ave Needham MA 02492",
    "addr:housenumber": "23",
    "addr:postcode": "02492",
    "addr:street": "Dedham Ave",
    "iso:country": "US",
    "ovtr:label": "First Parish In Needham, 23 Dedham Ave Needham MA US",
    "ovtr:similarity": 2.5749270915985107,
    "sg:address": "23 Dedham Ave",
    "sg:city": "Needham",
    "sg:classifiers": [
      {
        "category": "Organizations",
        "subcategory": "Religious Organization",
        "type": "Services"
      }
    ],
    "sg:phone": "+1 781 444 0823",
    "sg:postcode": "02492",
    "sg:province": "MA",
    "sg:tags": [
      "church"
    ],
    "sg:website": "www.uuneedham.org",
    "wof:name": "First Parish In Needham",
    "wof:placetype": "venue"
  },
  "geometry": {"coordinates":[-71.235585,42.279885],"type":"Point"}
}
