{
  "type": "Feature",
  "properties": {
    "addr:full": "30 Central Sq Chelmsford MA 01824",
    "addr:housenumber": "30",
    "addr:postcode": "01824",
    "addr:street": "Central Sq",
    "iso:country": "US",
    "sg:address": "30 Central Sq",
    "sg:city": "Chelmsford",
    "sg:classifiers": [
      {
        "category": "Autos \u0026 Motor Vehicles",
        "subcategory": "Fuel \u0026 Gas Station",
        "type": "Retail Goods"
      }
    ],
    "sg:phone": "+1 978 250 1452",
    "sg:postcode": "01824",
    "sg:province": "MA",
    "wof:name": "Rudy's Fuel \u0026 Auto Service Inc",
    "wof:placetype": "venue"
  },
  "geometry": {"coordinates":[-71.3526,42.597401],"type":"Point"}
}
