{
  "type": "Feature",
  "properties": {
    "iso:country":"US",
    "sg:address":"30 Central Sq",
    "sg:city":"Chelmsford",
    "sg:classifiers":[
        {
            "category":"Autos & Motor Vehicles",
            "subcategory":"Fuel & Gas Station",
            "type":"Retail Goods"
        }
    ],
    "sg:phone":"+1 978 250 1452",
    "sg:postcode":"01824",
    "sg:province":"MA",
    "wof:name":"Rudy's Fuel & Auto Service Inc",
    "wof:placetype":"venue"
},
  "geometry": {"coordinates":[-71.3526,42.597401],"type":"Point"}
}