{
  "type": "Feature",
  "properties": {
    "addr:full": "80 Mill St Apt 4 Woburn MA 01801",
    "addr:housenumber": "80;4",
    "addr:postcode": "01801",
    "addr:street": "Mill St Apt",
    "iso:country": "US",
    "sg:address": "80 Mill St Apt 4",
    "sg:city": "Woburn",
    "sg:classifiers": [
      {
        "category": "Building \u0026 Trades",
        "subcategory": "Electrical",
        "type": "Services"
      }
    ],
    "sg:phone": "+1 781 932 1045",
    "sg:postcode": "01801",
    "sg:province": "MA",
    "sg:tags": [
      "electrician"
    ],
    "wof:name": "American Eagle Electric",
    "wof:placetype": "venue"
  },
  "geometry": {"coordinates":[-71.116402,42.490627],"type":"Point"}
}
