{
  "type": "Feature",
  "properties": {
    "addr:full": "3 Endicott St Norwood MA 02062",
    "addr:housenumber": "3",
    "addr:postcode": "02062",
    "addr:street": "Endicott St",
    "iso:country": "US",
    "sg:address": "3 Endicott St",
    "sg:city": "Norwood",
    "sg:classifiers": [
      {
        "category": "Retail",
        "subcategory": "Repair Shop",
        "type": "Services"
      }
    ],
    "sg:phone": "+1 781 762 8321",
    "sg:postcode": "02062",
    "sg:province": "MA",
    "sg:tags": [
      "vinyl"
    ],
    "wof:name": "Scholz Specialty Products Co",
    "wof:placetype": "venue"
  },
  "geometry": {"coordinates":[-71.217813,42.179197],"type":"Point"}
}
