{
  "type": "Feature",
  "properties": {
    "addr:full": "400 Lowell Ave Haverhill MA 01832",
    "addr:housenumber": "400",
    "addr:postcode": "01832",
    "addr:street": "Lowell Ave",
    "iso:country": "US",
    "sg:address": "400 Lowell Ave",
    "sg:city": "Haverhill",
    "sg:classifiers": [
      {
        "category": "Cinema",
        "subcategory": "Movie Rental",
        "type": "Entertainment"
      }
    ],
    "sg:phone": "+1 978 521 1334",
    "sg:postcode": "01832",
    "sg:province": "MA",
    "sg:tags": [
      "leasing",
      "video",
      "disc",
      "tape"
    ],
    "wof:name": "West Gate Video",
    "wof:placetype": "venue"
  },
  "geometry": {"coordinates":[-71.115745,42.774769],"type":"Point"}
}
