{
  "type": "Feature",
  "properties": {
    "addr:full": "55 Highfield Dr Brockton MA 02301",
    "addr:housenumber": "55",
    "addr:postcode": "02301",
    "addr:street": "Highfield Dr",
    "iso:country": "US",
    "sg:address": "55 Highfield Dr",
    "sg:city": "Brockton",
    "sg:classifiers": [
      {
        "category": "Real Estate",
        "subcategory": "Real Estate Services",
        "type": "Services"
      },
      {
        "category": "Building \u0026 Trades",
        "subcategory": "Cleaning \u0026 Sanitation",
        "type": "Services"
      }
    ],
    "sg:phone": "+1 508 587 2287",
    "sg:postcode": "02301",
    "sg:province": "MA",
    "sg:tags": [
      "cleaning-industrial",
      "janitorial",
      "maintenance",
      "contractor"
    ],
    "wof:name": "Kinsella Robert",
    "wof:placetype": "venue"
  },
  "geometry": {"coordinates":[-71.045461,42.061199],"type":"Point"}
}
