{
  "type": "Feature",
  "properties": {
    "addr:full": "47 Main St Lee MA 01238",
    "addr:housenumber": "47",
    "addr:postcode": "01238",
    "addr:street": "Main St",
    "iso:country": "US",
    "ovtr:label": "Greylock Federal Credit Union, 47 Main St Lee MA US",
    "ovtr:similarity": 2.256347894668579,
    "sg:address": "47 Main St",
    "sg:city": "Lee",
    "sg:classifiers": [
      {
        "category": "Banks \u0026 Credit Unions",
        "subcategory": "Bank",
        "type": "Services"
      }
    ],
    "sg:phone": "+1 413 243 2121",
    "sg:postcode": "01238",
    "sg:province": "MA",
    "wof:name": "Greylock Federal Credit Union",
    "wof:placetype": "venue"
  },
  "geometry": {"coordinates":[-73.249489,42.30569],"type":"Point"}
}
