{
  "type": "Feature",
  "properties": {
    "iso:country":"US",
    "sg:address":"505 Tremont Street Unit 605",
    "sg:city":"Boston",
    "sg:classifiers":[
        {
            "category":"Shopping",
            "subcategory":"Clothing, Apparel, & Fashions",
            "type":"Retail Goods"
        }
    ],
    "sg:phone":"+1 617 536 0809",
    "sg:postcode":"02116",
    "sg:province":"MA",
    "sg:tags":[
        "clothing",
        "women's"
    ],
    "wof:name":"Sooki",
    "wof:placetype":"venue"
},
  "geometry": {"coordinates":[-71.07021899999999,42.344872],"type":"Point"}
}