{
  "type": "Feature",
  "properties": {
    "iso:country":"US",
    "sg:address":"800 Boylston St",
    "sg:city":"Chestnut Hill",
    "sg:classifiers":[
        {
            "category":"Health Services",
            "subcategory":"Dentist",
            "type":"Services"
        }
    ],
    "sg:phone":"+1 617 259 1100",
    "sg:postcode":"02467",
    "sg:province":"MA",
    "sg:website":"www.dentalpartnersofboston.com",
    "wof:name":"Cardenas Maria E",
    "wof:placetype":"venue"
},
  "geometry": {"coordinates":[-71.146112,42.326253],"type":"Point"}
}