{
  "type": "Feature",
  "properties": {
    "iso:country":"US",
    "sg:address":"201 Southbridge St",
    "sg:city":"Auburn",
    "sg:classifiers":[
        {
            "category":"Building & Trades",
            "subcategory":"Construction",
            "type":"Services"
        }
    ],
    "sg:phone":"+1 508 832 5090",
    "sg:postcode":"01501",
    "sg:province":"MA",
    "sg:tags":[
        "general",
        "contractor"
    ],
    "wof:name":"Kronoff & Assoc",
    "wof:placetype":"venue"
},
  "geometry": {"coordinates":[-71.827797,42.216257],"type":"Point"}
}