{
  "type": "Feature",
  "properties": {
    "iso:country":"US",
    "sg:address":"41 Corey St Apt 689",
    "sg:city":"Charlestown",
    "sg:classifiers":[
        {
            "category":"Professional",
            "subcategory":"Advertising",
            "type":"Services"
        }
    ],
    "sg:phone":"+1 617 242 1862",
    "sg:postcode":"02129",
    "sg:province":"MA",
    "sg:tags":[
        "promotion",
        "sale"
    ],
    "wof:name":"Beanz Promotions",
    "wof:placetype":"venue"
},
  "geometry": {"coordinates":[-71.056129,42.378391],"type":"Point"}
}