{
  "type": "Feature",
  "properties": {
    "addr:full":"35 Cross St Chatham MA 02633",
    "addr:housenumber":"35",
    "addr:postcode":"02633",
    "addr:street":"Cross St",
    "iso:country":"US",
    "sg:address":"35 Cross St",
    "sg:city":"Chatham",
    "sg:classifiers":[
        {
            "category":"Shopping",
            "subcategory":"Antiques",
            "type":"Retail Goods"
        }
    ],
    "sg:phone":"+1 508 945 9746",
    "sg:postcode":"02633",
    "sg:province":"MA",
    "wof:name":"Aquitain Antiques - CLOSED",
    "wof:placetype":"venue"
},
  "geometry": {"coordinates":[-69.95880099999999,41.680901],"type":"Point"}
}