{
  "type": "Feature",
  "properties": {
    "addr:full": "201 Indian Pipe Ln Concord MA 01742",
    "addr:housenumber": "201",
    "addr:postcode": "01742",
    "addr:street": "Indian Pipe Ln",
    "iso:country": "US",
    "sg:address": "201 Indian Pipe Ln",
    "sg:city": "Concord",
    "sg:classifiers": [
      {
        "category": "Professional",
        "subcategory": "Engineering",
        "type": "Services"
      }
    ],
    "sg:phone": "+1 978 369 8266",
    "sg:postcode": "01742",
    "sg:province": "MA",
    "sg:tags": [
      "engineer"
    ],
    "wof:name": "Dynamic Analysis",
    "wof:placetype": "venue"
  },
  "geometry": {"coordinates":[-71.396256,42.4282],"type":"Point"}
}
