{
  "type": "Feature",
  "properties": {
    "addr:full": "9 Marien Ln Marlborough MA 01752",
    "addr:housenumber": "9",
    "addr:postcode": "01752",
    "addr:street": "Marien Ln",
    "iso:country": "US",
    "sg:address": "9 Marien Ln",
    "sg:city": "Marlborough",
    "sg:classifiers": [
      {
        "category": "Education",
        "subcategory": "Special Training",
        "type": "Public Place"
      }
    ],
    "sg:phone": "+1 508 786 5844",
    "sg:postcode": "01752",
    "sg:province": "MA",
    "sg:tags": [
      "instruction",
      "music"
    ],
    "wof:name": "Chi Wu Piano Studio",
    "wof:placetype": "venue"
  },
  "geometry": {"coordinates":[-71.558332,42.35746],"type":"Point"}
}
