{
  "type": "Feature",
  "properties": {
    "iso:country":"US",
    "sg:address":"9 Marien Ln",
    "sg:city":"Marlborough",
    "sg:classifiers":[
        {
            "category":"Education",
            "subcategory":"Special Training",
            "type":"Public Place"
        }
    ],
    "sg:phone":"+1 508 786 5844",
    "sg:postcode":"01752",
    "sg:province":"MA",
    "sg:tags":[
        "instruction",
        "music"
    ],
    "wof:name":"Chi Wu Piano Studio",
    "wof:placetype":"venue"
},
  "geometry": {"coordinates":[-71.55833199999999,42.35746],"type":"Point"}
}