{
  "type": "Feature",
  "properties": {
    "addr:full": "28 Revere Beach Pkwy Medford MA 02155",
    "addr:housenumber": "28",
    "addr:postcode": "02155",
    "addr:street": "Revere Beach Pkwy",
    "iso:country": "US",
    "sg:address": "28 Revere Beach Pkwy",
    "sg:city": "Medford",
    "sg:classifiers": [
      {
        "category": "Building \u0026 Trades",
        "subcategory": "Construction",
        "type": "Services"
      }
    ],
    "sg:phone": "+1 781 393 4343",
    "sg:postcode": "02155",
    "sg:province": "MA",
    "sg:tags": [
      "general",
      "contractor"
    ],
    "wof:name": "Cranshaw Construction-New",
    "wof:placetype": "venue"
  },
  "geometry": {"coordinates":[-71.080672,42.404523],"type":"Point"}
}
