{
  "type": "Feature",
  "properties": {
    "addr:full": "262 Swansea Mall Dr Swansea MA 02777",
    "addr:housenumber": "262",
    "addr:postcode": "02777",
    "addr:street": "Swansea Mall Dr",
    "iso:country": "US",
    "sg:address": "262 Swansea Mall Dr",
    "sg:city": "Swansea",
    "sg:classifiers": [
      {
        "category": "Shopping",
        "subcategory": "Bicycles \u0026 Sporting Goods",
        "type": "Retail Goods"
      }
    ],
    "sg:phone": "+1 508 676 8393",
    "sg:postcode": "02777",
    "sg:province": "MA",
    "sg:website": "www.olympiasports.net",
    "wof:name": "Olympia Sports",
    "wof:placetype": "venue"
  },
  "geometry": {"coordinates":[-71.220046,41.760038],"type":"Point"}
}
