{
  "type": "Feature",
  "properties": {
    "iso:country":"US",
    "sg:address":"15 Bicknell St",
    "sg:city":"Boston",
    "sg:classifiers":[
        {
            "category":"Restaurant",
            "type":"Food & Drink"
        }
    ],
    "sg:phone":"+1   ",
    "sg:postcode":"02121",
    "sg:province":"MA",
    "sg:tags":[
        "eating"
    ],
    "wof:name":"J & C Kenan Restaurant",
    "wof:placetype":"venue"
},
  "geometry": {"coordinates":[-71.083026,42.2983],"type":"Point"}
}