{
  "type": "Feature",
  "properties": {
    "addr:full": "15 Bicknell St Boston MA 02121",
    "addr:housenumber": "15",
    "addr:postcode": "02121",
    "addr:street": "Bicknell St",
    "iso:country": "US",
    "sg:address": "15 Bicknell St",
    "sg:city": "Boston",
    "sg:classifiers": [
      {
        "category": "Restaurant",
        "type": "Food \u0026 Drink"
      }
    ],
    "sg:phone": "+1   ",
    "sg:postcode": "02121",
    "sg:province": "MA",
    "sg:tags": [
      "eating"
    ],
    "wof:name": "J \u0026 C Kenan Restaurant",
    "wof:placetype": "venue"
  },
  "geometry": {"coordinates":[-71.083026,42.2983],"type":"Point"}
}
