{
  "type": "Feature",
  "properties": {
    "iso:country":"US",
    "sg:address":"551 Main St.",
    "sg:city":"Hyannis",
    "sg:classifiers":[
        {
            "category":"Bakery",
            "type":"Food & Drink"
        }
    ],
    "sg:phone":"+1 508 778 5853",
    "sg:postcode":"02601",
    "sg:province":"MA",
    "sg:website":"www.krazykakes.citymaker.com/Hom...",
    "wof:name":"Krazy Kakes",
    "wof:placetype":"venue"
},
  "geometry": {"coordinates":[-70.289165,41.650116],"type":"Point"}
}