{
  "type": "Feature",
  "properties": {
    "addr:full":"194 Centre St Danvers MA 01923",
    "addr:housenumber":"194",
    "addr:postcode":"01923",
    "addr:street":"Centre St",
    "iso:country":"US",
    "sg:address":"194 Centre St",
    "sg:city":"Danvers",
    "sg:classifiers":[
        {
            "category":"Building & Trades",
            "subcategory":"Construction",
            "type":"Services"
        }
    ],
    "sg:phone":"+1 978 502 2323",
    "sg:postcode":"01923",
    "sg:province":"MA",
    "sg:tags":[
        "contractor"
    ],
    "wof:name":"DCAM Corp",
    "wof:placetype":"venue"
},
  "geometry": {"coordinates":[-70.979895,42.567935],"type":"Point"}
}