{
  "type": "Feature",
  "properties": {
    "addr:full": "90 Kirkland Dr Stow MA 01775",
    "addr:housenumber": "90",
    "addr:postcode": "01775",
    "addr:street": "Kirkland Dr",
    "iso:country": "US",
    "sg:address": "90 Kirkland Dr",
    "sg:city": "Stow",
    "sg:classifiers": [
      {
        "category": "Professional",
        "type": "Services"
      }
    ],
    "sg:phone": "+1   ",
    "sg:postcode": "01775",
    "sg:province": "MA",
    "wof:name": "Meow Inc",
    "wof:placetype": "venue"
  },
  "geometry": {"coordinates":[-71.536374,42.453971],"type":"Point"}
}
