{
  "type": "Feature",
  "properties": {
    "addr:full":"86A Sherman St. Cambridge MA 02140",
    "addr:housenumber":"86a",
    "addr:postcode":"02140",
    "addr:street":"Sherman St.",
    "iso:country":"US",
    "sg:address":"86A Sherman St.",
    "sg:city":"Cambridge",
    "sg:classifiers":[
        {
            "category":"Professional",
            "subcategory":"Computer Services",
            "type":"Services"
        }
    ],
    "sg:phone":"+1 917 573 8747",
    "sg:postcode":"02140",
    "sg:province":"MA",
    "sg:tags":[
        "mobile",
        "scanner",
        "whiteboard",
        "pdf",
        "mobile-scanning",
        "document",
        "iphone",
        "android"
    ],
    "sg:website":"http://jotnot.com/",
    "wof:name":"JotNot",
    "wof:placetype":"venue"
},
  "geometry": {"coordinates":[-71.131995,42.387669],"type":"Point"}
}