{
  "type": "Feature",
  "properties": {
    "iso:country":"US",
    "sg:address":"300 Brookside Dr",
    "sg:city":"Andover",
    "sg:classifiers":[
        {
            "category":"Banks & Credit Unions",
            "subcategory":"Investment Brokerage",
            "type":"Services"
        }
    ],
    "sg:phone":"+1 978 470 2500",
    "sg:postcode":"01810",
    "sg:province":"MA",
    "sg:tags":[
        "advisory",
        "financial"
    ],
    "wof:name":"Salix Ventures",
    "wof:placetype":"venue"
},
  "geometry": {"coordinates":[-71.19518600000001,42.687032],"type":"Point"}
}