{
  "type": "Feature",
  "properties": {
    "iso:country":"US",
    "sg:address":"45 Harland Ave",
    "sg:city":"Lowell",
    "sg:classifiers":[
        {
            "category":"Health Services",
            "subcategory":"Clinic",
            "type":"Services"
        }
    ],
    "sg:phone":"+1   ",
    "sg:postcode":"01852",
    "sg:province":"MA",
    "sg:tags":[
        "home",
        "agency",
        "employment",
        "care"
    ],
    "wof:name":"Lowell Registry For Private Du",
    "wof:placetype":"venue"
},
  "geometry": {"coordinates":[-71.275311,42.647339],"type":"Point"}
}