{
  "type": "Feature",
  "properties": {
    "addr:full":"38 Railroad St Bradford MA 01835",
    "addr:housenumber":"38",
    "addr:postcode":"01835",
    "addr:street":"Railroad St",
    "iso:country":"US",
    "sg:address":"38 Railroad St",
    "sg:city":"Bradford",
    "sg:classifiers":[
        {
            "category":"Retail",
            "subcategory":"Repair Shop",
            "type":"Services"
        }
    ],
    "sg:phone":"+1 978 470 8320",
    "sg:postcode":"01835",
    "sg:province":"MA",
    "sg:tags":[
        "plumbing",
        "drain",
        "cleaning",
        "sewer"
    ],
    "wof:name":"Drain King",
    "wof:placetype":"venue"
},
  "geometry": {"coordinates":[-71.069987,42.771106],"type":"Point"}
}