{
  "type": "Feature",
  "properties": {
    "addr:full":"2 Orchid Cir Burlington MA 01803",
    "addr:housenumber":"2",
    "addr:postcode":"01803",
    "addr:street":"Orchid Cir",
    "iso:country":"US",
    "sg:address":"2 Orchid Cir",
    "sg:city":"Burlington",
    "sg:classifiers":[
        {
            "category":"Building & Trades",
            "subcategory":"Construction",
            "type":"Services"
        }
    ],
    "sg:phone":"+1 781 750 8041",
    "sg:postcode":"01803",
    "sg:province":"MA",
    "sg:tags":[
        "handyman"
    ],
    "wof:name":"Case Handyman Svc",
    "wof:placetype":"venue"
},
  "geometry": {"coordinates":[-71.216662,42.504479],"type":"Point"}
}