{
  "type": "Feature",
  "properties": {
    "addr:full":"28 S Main St Milford MA 01757",
    "addr:housenumber":"28",
    "addr:postcode":"01757",
    "addr:street":"S Main St",
    "iso:country":"US",
    "sg:address":"28 S Main St",
    "sg:city":"Milford",
    "sg:classifiers":[
        {
            "category":"Banks & Credit Unions",
            "subcategory":"Investment Brokerage",
            "type":"Services"
        }
    ],
    "sg:phone":"+1 508 478 8124",
    "sg:postcode":"01757",
    "sg:province":"MA",
    "wof:name":"Anes Investment, Inc.",
    "wof:placetype":"venue"
},
  "geometry": {"coordinates":[-71.52152599999999,42.136491],"type":"Point"}
}