{
  "type": "Feature",
  "properties": {
    "addr:full": "44 Peter Salem Rd Leicester MA 01524",
    "addr:housenumber": "44",
    "addr:postcode": "01524",
    "addr:street": "Peter Salem Rd",
    "iso:country": "US",
    "sg:address": "44 Peter Salem Rd",
    "sg:city": "Leicester",
    "sg:classifiers": [
      {
        "category": "Building \u0026 Trades",
        "subcategory": "Electrical",
        "type": "Services"
      }
    ],
    "sg:phone": "+1 508 892 3300",
    "sg:postcode": "01524",
    "sg:province": "MA",
    "sg:tags": [
      "electrician"
    ],
    "wof:name": "Pete's Electrical Service",
    "wof:placetype": "venue"
  },
  "geometry": {"coordinates":[-71.9095,42.227299],"type":"Point"}
}
