{
  "type": "Feature",
  "properties": {
    "iso:country":"US",
    "sg:address":"44 Peter Salem Rd",
    "sg:city":"Leicester",
    "sg:classifiers":[
        {
            "category":"Building & Trades",
            "subcategory":"Electrical",
            "type":"Services"
        }
    ],
    "sg:phone":"+1 508 892 3300",
    "sg:postcode":"01524",
    "sg:province":"MA",
    "sg:tags":[
        "electrician"
    ],
    "wof:name":"Pete's Electrical Service",
    "wof:placetype":"venue"
},
  "geometry": {"coordinates":[-71.90949999999999,42.227299],"type":"Point"}
}