{
  "type": "Feature",
  "properties": {
    "iso:country":"US",
    "sg:address":"16 Temple Pl",
    "sg:city":"Fairhaven",
    "sg:classifiers":[
        {
            "category":"Place Of Worship",
            "subcategory":"Church",
            "type":"Public Place"
        },
        {
            "category":"Place Of Worship",
            "type":"Public Place"
        }
    ],
    "sg:phone":"+1 508 993 6351",
    "sg:postcode":"02719",
    "sg:province":"MA",
    "sg:tags":[
        "lutheran",
        "america",
        "churches-lutheran",
        "churches-lutheran-evangelical"
    ],
    "sg:website":"http://www.trinitylutheranchurch.com",
    "wof:name":"Trinity Lutheran Church Inc",
    "wof:placetype":"venue"
},
  "geometry": {"coordinates":[-70.89084,41.640734],"type":"Point"}
}