{
  "type": "Feature",
  "properties": {
    "addr:full":"125 Kingston St Boston MA 02111",
    "addr:housenumber":"125",
    "addr:postcode":"02111",
    "addr:street":"Kingston St",
    "iso:country":"US",
    "sg:address":"125 Kingston St",
    "sg:city":"Boston",
    "sg:classifiers":[
        {
            "category":"Professional",
            "type":"Services"
        }
    ],
    "sg:phone":"+1 617 753 9333",
    "sg:postcode":"02111",
    "sg:province":"MA",
    "sg:tags":[
        "establishment"
    ],
    "wof:name":"Swyst Tracy",
    "wof:placetype":"venue"
},
  "geometry": {"coordinates":[-71.05936199999999,42.35203],"type":"Point"}
}