{
  "type": "Feature",
  "properties": {
    "iso:country":"US",
    "sg:address":"13 Howe St",
    "sg:city":"Dorchester",
    "sg:classifiers":[
        {
            "category":"Building & Trades",
            "subcategory":"Construction",
            "type":"Services"
        }
    ],
    "sg:phone":"+1 617 828 2733",
    "sg:postcode":"02125",
    "sg:province":"MA",
    "sg:tags":[
        "paving",
        "contractor"
    ],
    "wof:name":"A J General Contractors",
    "wof:placetype":"venue"
},
  "geometry": {"coordinates":[-71.06524400000001,42.310947],"type":"Point"}
}