{
  "type": "Feature",
  "properties": {
    "iso:country":"US",
    "sg:address":"388 Commonwealth Ave",
    "sg:city":"Boston",
    "sg:classifiers":[
        {
            "category":"Health Services",
            "subcategory":"Dentist",
            "type":"Services"
        }
    ],
    "sg:phone":"+1 617 266 8770",
    "sg:postcode":"02215",
    "sg:province":"MA",
    "wof:name":"Haller Leslie DMD",
    "wof:placetype":"venue"
},
  "geometry": {"coordinates":[-71.089203,42.348801],"type":"Point"}
}