{
  "type": "Feature",
  "properties": {
    "iso:country":"US",
    "sg:address":"41 Charles St",
    "sg:city":"Boston",
    "sg:classifiers":[
        {
            "category":"Retail",
            "subcategory":"Repair Shop",
            "type":"Services"
        }
    ],
    "sg:phone":"+1 617 208 1169",
    "sg:postcode":"02114",
    "sg:province":"MA",
    "sg:tags":[
        "lock",
        "locksmith"
    ],
    "wof:name":"7 Day Always Emergency Lcksmth",
    "wof:placetype":"venue"
},
  "geometry": {"coordinates":[-71.070089,42.357519],"type":"Point"}
}