{
  "type": "Feature",
  "properties": {
    "addr:full": "80 Foley Rd Marlborough MA 01752",
    "addr:housenumber": "80",
    "addr:postcode": "01752",
    "addr:street": "Foley Rd",
    "iso:country": "US",
    "ovtr:label": "Richer Elementary School, 80 Foley Rd Marlborough MA US",
    "ovtr:similarity": 2.559597969055176,
    "sg:address": "80 Foley Rd",
    "sg:city": "Marlborough",
    "sg:classifiers": [
      {
        "category": "Education",
        "subcategory": "School",
        "type": "Public Place"
      }
    ],
    "sg:phone": "+1 508 460 3504",
    "sg:postcode": "01752",
    "sg:province": "MA",
    "wof:name": "Richer Elementary School",
    "wof:placetype": "venue"
  },
  "geometry": {"coordinates":[-71.578609,42.338444],"type":"Point"}
}
