{
  "type": "Feature",
  "properties": {
    "iso:country":"US",
    "sg:address":"452 Great Rd Ste 4",
    "sg:city":"Acton",
    "sg:classifiers":[
        {
            "category":"Banks & Credit Unions",
            "subcategory":"Bank",
            "type":"Services"
        },
        {
            "category":"Banks & Credit Unions",
            "subcategory":"Financial Services",
            "type":"Services"
        }
    ],
    "sg:phone":"+1 800 221 4020",
    "sg:postcode":"01720",
    "sg:province":"MA",
    "sg:tags":[
        "broker",
        "mortgage"
    ],
    "sg:website":"www.wcu.com",
    "wof:name":"Workers Credit Union",
    "wof:placetype":"venue"
},
  "geometry": {"coordinates":[-71.424154,42.51287],"type":"Point"}
}