{
  "type": "Feature",
  "properties": {
    "addr:full":"239 Cross Rd North Dartmouth MA 02747",
    "addr:housenumber":"239",
    "addr:postcode":"02747",
    "addr:street":"Cross Rd",
    "iso:country":"US",
    "sg:address":"239 Cross Rd",
    "sg:city":"North Dartmouth",
    "sg:classifiers":[
        {
            "category":"Social Services",
            "subcategory":"Adult Care",
            "type":"Services"
        }
    ],
    "sg:phone":"+1 508 992 8880",
    "sg:postcode":"02747",
    "sg:province":"MA",
    "sg:tags":[
        "home",
        "residential"
    ],
    "wof:name":"Heritage At Dartmouth",
    "wof:placetype":"venue"
},
  "geometry": {"coordinates":[-71.007475,41.648472],"type":"Point"}
}