{
  "type": "Feature",
  "properties": {
    "addr:full": "30 Hemenway Street Boston MA 02115",
    "addr:housenumber": "30",
    "addr:postcode": "02115",
    "addr:street": "Hemenway Street",
    "iso:country": "US",
    "sg:address": "30 Hemenway Street",
    "sg:city": "Boston",
    "sg:classifiers": [
      {
        "category": "Real Estate",
        "subcategory": "Real Estate Operator",
        "type": "Services"
      }
    ],
    "sg:phone": "+1 617 266 7917",
    "sg:postcode": "02115",
    "sg:province": "MA",
    "sg:tags": [
      "apartment"
    ],
    "wof:name": "Continental Wingate Company",
    "wof:placetype": "venue"
  },
  "geometry": {"coordinates":[-71.089422,42.34579],"type":"Point"}
}
