{
  "type": "Feature",
  "properties": {
    "iso:country":"US",
    "sg:address":"43 High St",
    "sg:city":"Wareham",
    "sg:classifiers":[
        {
            "category":"Health Services",
            "subcategory":"Doctor",
            "type":"Services"
        }
    ],
    "sg:phone":"+1 508 291 4359",
    "sg:postcode":"02571",
    "sg:province":"MA",
    "sg:tags":[
        "practice",
        "family"
    ],
    "wof:name":"Fitzpatrick Brian",
    "wof:placetype":"venue"
},
  "geometry": {"coordinates":[-70.714679,41.755953],"type":"Point"}
}