{
  "type": "Feature",
  "properties": {
    "iso:country":"US",
    "sg:address":"49 Hawthorn St",
    "sg:city":"New Bedford",
    "sg:classifiers":[
        {
            "category":"Health Services",
            "subcategory":"Doctor",
            "type":"Services"
        }
    ],
    "sg:phone":"+1 508 992 3838",
    "sg:postcode":"02740",
    "sg:province":"MA",
    "sg:tags":[
        "physician",
        "surgeon"
    ],
    "wof:name":"New Bedford Surgical Assoc",
    "wof:placetype":"venue"
},
  "geometry": {"coordinates":[-70.93065199999999,41.629515],"type":"Point"}
}