{
  "type": "Feature",
  "properties": {
    "iso:country":"US",
    "sg:address":"1374 Cambridge St",
    "sg:city":"Cambridge",
    "sg:classifiers":[
        {
            "category":"Banks & Credit Unions",
            "subcategory":"Bank",
            "type":"Services"
        }
    ],
    "sg:phone":"+1 617 864 8700",
    "sg:postcode":"02139",
    "sg:province":"MA",
    "wof:name":"Cambridge Savings Bank",
    "wof:placetype":"venue"
},
  "geometry": {"coordinates":[-71.100621,42.37363],"type":"Point"}
}