{
  "type": "Feature",
  "properties": {
    "addr:full": "4 Scott Hollow Dr Holyoke MA 01040",
    "addr:housenumber": "4",
    "addr:postcode": "01040",
    "addr:street": "Scott Hollow Dr",
    "iso:country": "US",
    "sg:address": "4 Scott Hollow Dr",
    "sg:city": "Holyoke",
    "sg:classifiers": [
      {
        "category": "Personal",
        "subcategory": "Beauty Salon",
        "type": "Services"
      }
    ],
    "sg:phone": "+1   ",
    "sg:postcode": "01040",
    "sg:province": "MA",
    "sg:tags": [
      "shop",
      "hanging",
      "contractor"
    ],
    "wof:name": "A Brush Above",
    "wof:placetype": "venue"
  },
  "geometry": {"coordinates":[-72.640236,42.214094],"type":"Point"}
}
