{
  "type": "Feature",
  "properties": {
    "addr:full":"1 Coolidge Ave Greenfield MA 01301",
    "addr:housenumber":"1",
    "addr:postcode":"01301",
    "addr:street":"Coolidge Ave",
    "iso:country":"US",
    "sg:address":"1 Coolidge Ave",
    "sg:city":"Greenfield",
    "sg:classifiers":[
        {
            "category":"Restaurant",
            "type":"Food & Drink"
        }
    ],
    "sg:phone":"+1   ",
    "sg:postcode":"01301",
    "sg:province":"MA",
    "sg:tags":[
        "eating"
    ],
    "wof:name":"Bell Cafeteria Services",
    "wof:placetype":"venue"
},
  "geometry": {"coordinates":[-72.58008100000001,42.610369],"type":"Point"}
}