{
  "type": "Feature",
  "properties": {
    "addr:full":"40 Lee Burbank Highway Boston Logan Airport Revere MA 02128",
    "addr:housenumber":"40",
    "addr:postcode":"02128",
    "addr:street":"Lee Burbank Highway",
    "iso:country":"US",
    "sg:address":"40 Lee Burbank Highway Boston Logan Airport",
    "sg:city":"Revere",
    "sg:classifiers":[
        {
            "category":"Retail",
            "subcategory":"Auto Rental",
            "type":"Services"
        }
    ],
    "sg:phone":"+1 877 283 0898",
    "sg:postcode":"02128",
    "sg:province":"MA",
    "sg:tags":[
        "car"
    ],
    "sg:website":"www.thrifty.com",
    "wof:name":"Thrifty Car Rental",
    "wof:placetype":"venue"
},
  "geometry": {"coordinates":[-71.03016599999999,42.370056],"type":"Point"}
}