{
  "type": "Feature",
  "properties": {
    "addr:full":"62 Elm St Worcester MA 01609",
    "addr:housenumber":"62",
    "addr:postcode":"01609",
    "addr:street":"Elm St",
    "iso:country":"US",
    "sg:address":"62 Elm St",
    "sg:city":"Worcester",
    "sg:classifiers":[
        {
            "category":"Social Services",
            "type":"Services"
        }
    ],
    "sg:phone":"+1 508 752 5128",
    "sg:postcode":"01609",
    "sg:province":"MA",
    "sg:tags":[
        "organization",
        "welfare"
    ],
    "wof:name":"Alternatives",
    "wof:placetype":"venue"
},
  "geometry": {"coordinates":[-71.80906299999999,42.265522],"type":"Point"}
}