{
  "type": "Feature",
  "properties": {
    "addr:full":"64 Hartford St Framingham MA 01702",
    "addr:housenumber":"64",
    "addr:postcode":"01702",
    "addr:street":"Hartford St",
    "iso:country":"US",
    "sg:address":"64 Hartford St",
    "sg:city":"Framingham",
    "sg:classifiers":[
        {
            "category":"Professional",
            "subcategory":"Management & Consulting",
            "type":"Services"
        }
    ],
    "sg:phone":"+1   ",
    "sg:postcode":"01702",
    "sg:province":"MA",
    "sg:tags":[
        "engineering",
        "system",
        "analysis"
    ],
    "wof:name":"ISS",
    "wof:placetype":"venue"
},
  "geometry": {"coordinates":[-71.405821,42.290144],"type":"Point"}
}