{
  "type": "Feature",
  "properties": {
    "addr:full": "1430 Main St Palmer MA 01069",
    "addr:housenumber": "1430",
    "addr:postcode": "01069",
    "addr:street": "Main St",
    "iso:country": "US",
    "sg:address": "1430 Main St",
    "sg:city": "Palmer",
    "sg:classifiers": [
      {
        "category": "Building \u0026 Trades",
        "subcategory": "Construction",
        "type": "Services"
      }
    ],
    "sg:phone": "+1 413 283 7899",
    "sg:postcode": "01069",
    "sg:province": "MA",
    "sg:tags": [
      "concrete",
      "driveway",
      "contractor"
    ],
    "wof:name": "JKL Liquid Asphalt Inc",
    "wof:placetype": "venue"
  },
  "geometry": {"coordinates":[-72.329874,42.157281],"type":"Point"}
}
