{
  "type": "Feature",
  "properties": {
    "addr:full":"350 Rantoul St Beverly MA 01915",
    "addr:housenumber":"350",
    "addr:postcode":"01915",
    "addr:street":"Rantoul St",
    "iso:country":"US",
    "sg:address":"350 Rantoul St",
    "sg:city":"Beverly",
    "sg:classifiers":[
        {
            "category":"Restaurant",
            "type":"Food & Drink"
        }
    ],
    "sg:phone":"+1 978 524 0511",
    "sg:postcode":"01915",
    "sg:province":"MA",
    "sg:tags":[
        "caterer"
    ],
    "wof:name":"Bittersweet Kitchen",
    "wof:placetype":"venue"
},
  "geometry": {"coordinates":[-70.88251,42.552733],"type":"Point"}
}