{
  "type": "Feature",
  "properties": {
    "addr:full": "12 Kensington Ave Methuen MA 01844",
    "addr:housenumber": "12",
    "addr:postcode": "01844",
    "addr:street": "Kensington Ave",
    "iso:country": "US",
    "sg:address": "12 Kensington Ave",
    "sg:city": "Methuen",
    "sg:classifiers": [
      {
        "category": "Building \u0026 Trades",
        "subcategory": "Construction",
        "type": "Services"
      }
    ],
    "sg:phone": "+1 978 688 6398",
    "sg:postcode": "01844",
    "sg:province": "MA",
    "sg:tags": [
      "carpentry",
      "contractor"
    ],
    "wof:name": "Rino Enterprises",
    "wof:placetype": "venue"
  },
  "geometry": {"coordinates":[-71.173993,42.746431],"type":"Point"}
}
