{
  "type": "Feature",
  "properties": {
    "iso:country":"US",
    "sg:address":"12 Kensington Ave",
    "sg:city":"Methuen",
    "sg:classifiers":[
        {
            "category":"Building & Trades",
            "subcategory":"Construction",
            "type":"Services"
        }
    ],
    "sg:phone":"+1 978 688 6398",
    "sg:postcode":"01844",
    "sg:province":"MA",
    "sg:tags":[
        "carpentry",
        "contractor"
    ],
    "wof:name":"Rino Enterprises",
    "wof:placetype":"venue"
},
  "geometry": {"coordinates":[-71.173993,42.746431],"type":"Point"}
}