{
  "type": "Feature",
  "properties": {
    "addr:full": "2 Oakmont Ave Westminster MA 01473",
    "addr:housenumber": "2",
    "addr:postcode": "01473",
    "addr:street": "Oakmont Ave",
    "iso:country": "US",
    "sg:address": "2 Oakmont Ave",
    "sg:city": "Westminster",
    "sg:classifiers": [
      {
        "category": "Utilities",
        "subcategory": "Water",
        "type": "Services"
      }
    ],
    "sg:phone": "+1 978 874 5572",
    "sg:postcode": "01473",
    "sg:province": "MA",
    "sg:tags": [
      "company",
      "sewage"
    ],
    "wof:name": "Westminster Water Dept",
    "wof:placetype": "venue"
  },
  "geometry": {"coordinates":[-71.907776,42.570657],"type":"Point"}
}
