{
  "type": "Feature",
  "properties": {
    "iso:country":"US",
    "sg:address":"1 Court St",
    "sg:city":"Boston",
    "sg:classifiers":[
        {
            "category":"Professional",
            "subcategory":"Lawyer & Legal Services",
            "type":"Services"
        }
    ],
    "sg:phone":"+1 617 578 0033",
    "sg:postcode":"02108",
    "sg:province":"MA",
    "sg:tags":[
        "attorney"
    ],
    "wof:name":"Lumsden & Inge",
    "wof:placetype":"venue"
},
  "geometry": {"coordinates":[-71.058216,42.358951],"type":"Point"}
}