{
  "type": "Feature",
  "properties": {
    "addr:full":"62 Warren St W Raynham MA 02767",
    "addr:housenumber":"62",
    "addr:postcode":"02767",
    "addr:street":"Warren St W",
    "iso:country":"US",
    "sg:address":"62 Warren St W",
    "sg:city":"Raynham",
    "sg:classifiers":[
        {
            "category":"Retail",
            "subcategory":"Laundry & Dry Cleaning",
            "type":"Services"
        }
    ],
    "sg:phone":"+1 508 823 8600",
    "sg:postcode":"02767",
    "sg:province":"MA",
    "sg:tags":[
        "cleaners",
        "rug",
        "carpet"
    ],
    "wof:name":"Clean Carpet Systems",
    "wof:placetype":"venue"
},
  "geometry": {"coordinates":[-71.053952,41.912089],"type":"Point"}
}