{
  "type": "Feature",
  "properties": {
    "iso:country":"US",
    "sg:address":"976 Bernardston Rd",
    "sg:city":"Greenfield",
    "sg:classifiers":[
        {
            "category":"Retail",
            "subcategory":"Auto Repair",
            "type":"Services"
        }
    ],
    "sg:phone":"+1 413 772 0759",
    "sg:postcode":"01301",
    "sg:province":"MA",
    "sg:tags":[
        "body",
        "painting",
        "repairing",
        "automobile"
    ],
    "wof:name":"North Greenfield Autobody An",
    "wof:placetype":"venue"
},
  "geometry": {"coordinates":[-72.586094,42.609764],"type":"Point"}
}