{
  "type": "Feature",
  "properties": {
    "addr:full":"302 Summer St Rehoboth MA 02769",
    "addr:housenumber":"302",
    "addr:postcode":"02769",
    "addr:street":"Summer St",
    "iso:country":"US",
    "sg:address":"302 Summer St",
    "sg:city":"Rehoboth",
    "sg:classifiers":[
        {
            "category":"Autos & Motor Vehicles",
            "subcategory":"Auto Supplies",
            "type":"Retail Goods"
        }
    ],
    "sg:phone":"+1   ",
    "sg:postcode":"02769",
    "sg:province":"MA",
    "wof:name":"Veaders Equipment Plus Inc",
    "wof:placetype":"venue"
},
  "geometry": {"coordinates":[-71.290873,41.829065],"type":"Point"}
}