{
  "type": "Feature",
  "properties": {
    "addr:full": "218 Causeway St Medfield MA 02052",
    "addr:housenumber": "218",
    "addr:postcode": "02052",
    "addr:street": "Causeway St",
    "iso:country": "US",
    "sg:address": "218 Causeway St",
    "sg:city": "Medfield",
    "sg:classifiers": [
      {
        "category": "Professional",
        "subcategory": "Advertising",
        "type": "Services"
      }
    ],
    "sg:phone": "+1   ",
    "sg:postcode": "02052",
    "sg:province": "MA",
    "sg:tags": [
      "agency",
      "public",
      "relations"
    ],
    "wof:name": "Wirsig Design",
    "wof:placetype": "venue"
  },
  "geometry": {"coordinates":[-71.326376,42.160887],"type":"Point"}
}
