{
  "type": "Feature",
  "properties": {
    "addr:full":"9 Damonmill Sq Suite 4D Concord MA 01742",
    "addr:housenumber":"9",
    "addr:postcode":"01742",
    "addr:street":"Damonmill Sq Suite 4D",
    "iso:country":"US",
    "sg:address":"9 Damonmill Sq Suite 4D",
    "sg:city":"Concord",
    "sg:classifiers":[
        {
            "category":"Professional",
            "subcategory":"Lawyer & Legal Services",
            "type":"Services"
        }
    ],
    "sg:phone":"+1 978 341 0222",
    "sg:postcode":"01742",
    "sg:province":"MA",
    "sg:tags":[
        "attorney",
        "business",
        "administrative",
        "labor",
        "governmental",
        "planning",
        "real estate",
        "law",
        "employment"
    ],
    "wof:name":"Hicks , Edward E. - Edward E. Hicks",
    "wof:placetype":"venue"
},
  "geometry": {"coordinates":[-71.404796,42.453822],"type":"Point"}
}