{
  "type": "Feature",
  "properties": {
    "addr:full":"23 Liberty Dr North Billerica MA 01862",
    "addr:housenumber":"23",
    "addr:postcode":"01862",
    "addr:street":"Liberty Dr North",
    "iso:country":"US",
    "sg:address":"23 Liberty Dr",
    "sg:city":"North Billerica",
    "sg:classifiers":[
        {
            "category":"Professional",
            "type":"Services"
        }
    ],
    "sg:phone":"+1 781 229 0066",
    "sg:postcode":"01862",
    "sg:province":"MA",
    "sg:tags":[
        "establishment"
    ],
    "wof:name":"Pioneer Inc",
    "wof:placetype":"venue"
},
  "geometry": {"coordinates":[-71.30297400000001,42.539823],"type":"Point"}
}