{
  "type": "Feature",
  "properties": {
    "iso:country":"US",
    "sg:address":"625 Main St",
    "sg:city":"Wilbraham",
    "sg:classifiers":[
        {
            "category":"Education",
            "subcategory":"School",
            "type":"Public Place"
        }
    ],
    "sg:phone":"+1 413 596 6921",
    "sg:postcode":"01095",
    "sg:province":"MA",
    "wof:name":"Mile Tree School",
    "wof:placetype":"venue"
},
  "geometry": {"coordinates":[-72.434905,42.112176],"type":"Point"}
}