{
  "type": "Feature",
  "properties": {
    "addr:full":"19 Norman St West Springfield MA 01089",
    "addr:housenumber":"19",
    "addr:postcode":"01089",
    "addr:street":"Norman St",
    "iso:country":"US",
    "sg:address":"19 Norman St",
    "sg:city":"West Springfield",
    "sg:classifiers":[
        {
            "category":"Home & Garden",
            "subcategory":"Garden Supply",
            "type":"Retail Goods"
        }
    ],
    "sg:phone":"+1 413 732 5335",
    "sg:postcode":"01089",
    "sg:province":"MA",
    "sg:tags":[
        "sprinkler"
    ],
    "wof:name":"John Deere Landscapes",
    "wof:placetype":"venue"
},
  "geometry": {"coordinates":[-72.62362400000001,42.0959],"type":"Point"}
}