{
  "type": "Feature",
  "properties": {
    "iso:country":"US",
    "sg:address":"78 Powell St",
    "sg:city":"Brookline",
    "sg:classifiers":[
        {
            "category":"Professional",
            "subcategory":"Lawyer & Legal Services",
            "type":"Services"
        }
    ],
    "sg:phone":"+1 617 264 9500",
    "sg:postcode":"02446",
    "sg:province":"MA",
    "sg:tags":[
        "attorney"
    ],
    "wof:name":"Britton & Douglass",
    "wof:placetype":"venue"
},
  "geometry": {"coordinates":[-71.115578,42.345907],"type":"Point"}
}