{
  "type": "Feature",
  "properties": {
    "iso:country":"US",
    "sg:address":"121 Eastern Ave",
    "sg:city":"Chelsea",
    "sg:classifiers":[
        {
            "category":"Retail",
            "subcategory":"Auto Rental",
            "type":"Services"
        }
    ],
    "sg:phone":"+1 617 887 1628",
    "sg:postcode":"02150",
    "sg:province":"MA",
    "sg:tags":[
        "car"
    ],
    "sg:website":"www.enterprise.com",
    "wof:name":"Enterprise Rent-A-Car",
    "wof:placetype":"venue"
},
  "geometry": {"coordinates":[-71.02286700000001,42.390185],"type":"Point"}
}