{
  "type": "Feature",
  "properties": {
    "iso:country":"US",
    "sg:address":"407 W Grove St",
    "sg:city":"Middleboro",
    "sg:classifiers":[
        {
            "category":"Restaurant",
            "type":"Food & Drink"
        }
    ],
    "sg:phone":"+1 508 947 9297",
    "sg:postcode":"02346",
    "sg:province":"MA",
    "wof:name":"Harry's Bar & Grille",
    "wof:placetype":"venue"
},
  "geometry": {"coordinates":[-70.947901,41.896479],"type":"Point"}
}