{
  "type": "Feature",
  "properties": {
    "addr:full": "407 W Grove St Middleboro MA 02346",
    "addr:housenumber": "407",
    "addr:postcode": "02346",
    "addr:street": "W Grove St",
    "iso:country": "US",
    "ovtr:label": "Harry's Bar \u0026 Grille, 407 W Grove St Middleboro MA US",
    "ovtr:similarity": 2.4622600078582764,
    "sg:address": "407 W Grove St",
    "sg:city": "Middleboro",
    "sg:classifiers": [
      {
        "category": "Restaurant",
        "type": "Food \u0026 Drink"
      }
    ],
    "sg:phone": "+1 508 947 9297",
    "sg:postcode": "02346",
    "sg:province": "MA",
    "wof:name": "Harry's Bar \u0026 Grille",
    "wof:placetype": "venue"
  },
  "geometry": {"coordinates":[-70.947901,41.896479],"type":"Point"}
}
