{
  "type": "Feature",
  "properties": {
    "addr:full": "118 N Washington St North Attleboro MA 02760",
    "addr:housenumber": "118",
    "addr:postcode": "02760",
    "addr:street": "N Washington St",
    "iso:country": "US",
    "ovtr:label": "Richards Memorial Library, 118 N Washington St North Attleboro MA US",
    "ovtr:similarity": 2.345263957977295,
    "sg:address": "118 N Washington St",
    "sg:city": "North Attleboro",
    "sg:classifiers": [
      {
        "category": "Education",
        "subcategory": "Library",
        "type": "Public Place"
      }
    ],
    "sg:phone": "+1 508 699 0122",
    "sg:postcode": "02760",
    "sg:province": "MA",
    "sg:website": "www.rmlonline.org",
    "wof:name": "Richards Memorial Library",
    "wof:placetype": "venue"
  },
  "geometry": {"coordinates":[-71.332147,41.985261],"type":"Point"}
}
