{
  "type": "Feature",
  "properties": {
    "iso:country":"US",
    "sg:address":"118 N Washington St",
    "sg:city":"North Attleboro",
    "sg:classifiers":[
        {
            "category":"Education",
            "subcategory":"Library",
            "type":"Public Place"
        }
    ],
    "sg:phone":"+1 508 699 0122",
    "sg:postcode":"02760",
    "sg:province":"MA",
    "sg:website":"www.rmlonline.org",
    "wof:name":"Richards Memorial Library",
    "wof:placetype":"venue"
},
  "geometry": {"coordinates":[-71.33214700000001,41.985261],"type":"Point"}
}