{
  "type": "Feature",
  "properties": {
    "iso:country":"US",
    "sg:address":"214 Andover St",
    "sg:city":"Wilmington",
    "sg:classifiers":[
        {
            "category":"Professional",
            "subcategory":"Business Services",
            "type":"Services"
        }
    ],
    "sg:phone":"+1 978 658 4444",
    "sg:postcode":"01887",
    "sg:province":"MA",
    "wof:name":"United Rug Binding & Fringing",
    "wof:placetype":"venue"
},
  "geometry": {"coordinates":[-71.147013,42.58755],"type":"Point"}
}