{
  "type": "Feature",
  "properties": {
    "iso:country":"US",
    "sg:address":"52 Westland Ave",
    "sg:city":"Boston",
    "sg:classifiers":[
        {
            "category":"Manufacturing",
            "subcategory":"Musical Instruments",
            "type":"Manufacturing & Wholesale Goods"
        }
    ],
    "sg:phone":"+1   ",
    "sg:postcode":"02115",
    "sg:province":"MA",
    "sg:tags":[
        "mfg"
    ],
    "wof:name":"Two Steps of Infinity Inc",
    "wof:placetype":"venue"
},
  "geometry": {"coordinates":[-71.087666,42.343489],"type":"Point"}
}