{
  "type": "Feature",
  "properties": {
    "iso:country":"US",
    "sg:address":"203 Crescent St. Suite 106",
    "sg:city":"Waltham ",
    "sg:classifiers":[
        {
            "category":"Professional",
            "subcategory":"Computer Services",
            "type":"Services"
        }
    ],
    "sg:phone":"+1 866 929 9177",
    "sg:postcode":"02453",
    "sg:province":"MA",
    "sg:tags":[
        "web-design",
        "web-app-design",
        "rapid-prototyping",
        "user-interface-design",
        "ui",
        "ui-web-design",
        "ux",
        "user-interface-web-design"
    ],
    "sg:website":"http://www.freshtilledsoil.com",
    "wof:name":"Fresh Tilled Soil",
    "wof:placetype":"venue"
},
  "geometry": {"coordinates":[-71.242777,42.368133],"type":"Point"}
}