{
  "type": "Feature",
  "properties": {
    "iso:country":"US",
    "sg:address":"1 Fall St",
    "sg:city":"Fall River",
    "sg:classifiers":[
        {
            "category":"Government",
            "subcategory":"Office",
            "type":"Public Place"
        }
    ],
    "sg:phone":"+1 508 324 2620",
    "sg:postcode":"02769",
    "sg:province":"MA",
    "sg:tags":[
        "city",
        "program",
        "adm"
    ],
    "wof:name":"Fall River Economic Dev Office",
    "wof:placetype":"venue"
},
  "geometry": {"coordinates":[-71.290869,41.779416],"type":"Point"}
}