{
  "type": "Feature",
  "properties": {
    "addr:full":"233 Bacon St Waltham MA 02451",
    "addr:housenumber":"233",
    "addr:postcode":"02451",
    "addr:street":"Bacon St",
    "iso:country":"US",
    "sg:address":"233 Bacon St",
    "sg:city":"Waltham",
    "sg:classifiers":[
        {
            "category":"Retail",
            "subcategory":"Auto Repair",
            "type":"Services"
        }
    ],
    "sg:phone":"+1 781 899 8970",
    "sg:postcode":"02451",
    "sg:province":"MA",
    "sg:tags":[
        "repairing",
        "automobile"
    ],
    "wof:name":"Di Giorgio Automotive",
    "wof:placetype":"venue"
},
  "geometry": {"coordinates":[-71.241241,42.384228],"type":"Point"}
}