{
  "type": "Feature",
  "properties": {
    "iso:country":"US",
    "sg:address":"35 Independence Way",
    "sg:city":"Danvers",
    "sg:classifiers":[
        {
            "category":"Shopping",
            "type":"Retail Goods"
        }
    ],
    "sg:phone":"+1 978 777 4795",
    "sg:postcode":"01923",
    "sg:province":"MA",
    "sg:tags":[
        "cosmetic",
        "perfume"
    ],
    "wof:name":"Boston Beauty Supply",
    "wof:placetype":"venue"
},
  "geometry": {"coordinates":[-70.939937,42.55046],"type":"Point"}
}