{
  "type": "Feature",
  "properties": {
    "addr:full":"3 Bailey St Foxboro MA 02035",
    "addr:housenumber":"3",
    "addr:postcode":"02035",
    "addr:street":"Bailey St",
    "iso:country":"US",
    "sg:address":"3 Bailey St",
    "sg:city":"Foxboro",
    "sg:classifiers":[
        {
            "category":"Health Services",
            "subcategory":"Health Practitioner",
            "type":"Services"
        }
    ],
    "sg:phone":"+1 508 543 9416",
    "sg:postcode":"02035",
    "sg:province":"MA",
    "sg:tags":[
        "therapist",
        "physical"
    ],
    "wof:name":"Howard Rehabilitation Svc",
    "wof:placetype":"venue"
},
  "geometry": {"coordinates":[-71.24490299999999,42.035099],"type":"Point"}
}