{
  "type": "Feature",
  "properties": {
    "addr:full": "1193 Memorial Dr Chicopee MA 01020",
    "addr:housenumber": "1193",
    "addr:postcode": "01020",
    "addr:street": "Memorial Dr",
    "iso:country": "US",
    "ovtr:label": "A Cut Above Florist, 1193 Memorial Dr Chicopee MA US",
    "ovtr:similarity": 2.2710180282592773,
    "sg:address": "1193 Memorial Dr",
    "sg:city": "Chicopee",
    "sg:classifiers": [
      {
        "category": "Shopping",
        "subcategory": "Florist",
        "type": "Retail Goods"
      }
    ],
    "sg:phone": "+1 413 593 3344",
    "sg:postcode": "01020",
    "sg:province": "MA",
    "wof:name": "A Cut Above Florist",
    "wof:placetype": "venue"
  },
  "geometry": {"coordinates":[-72.576957,42.190267],"type":"Point"}
}
