{
  "type": "Feature",
  "properties": {
    "iso:country":"US",
    "sg:address":"1193 Memorial Dr",
    "sg:city":"Chicopee",
    "sg:classifiers":[
        {
            "category":"Shopping",
            "subcategory":"Florist",
            "type":"Retail Goods"
        }
    ],
    "sg:phone":"+1 413 593 3344",
    "sg:postcode":"01020",
    "sg:province":"MA",
    "wof:name":"A Cut Above Florist",
    "wof:placetype":"venue"
},
  "geometry": {"coordinates":[-72.57695699999999,42.190267],"type":"Point"}
}