{
  "type": "Feature",
  "properties": {
    "addr:full":"318 Montvale Ave. Woburn MA 01801",
    "addr:housenumber":"318",
    "addr:postcode":"01801",
    "addr:street":"Montvale Ave.",
    "iso:country":"US",
    "sg:address":"318 Montvale Ave.",
    "sg:city":"Woburn",
    "sg:classifiers":[
        {
            "category":"Donuts",
            "subcategory":"None",
            "type":"Food & Drink"
        }
    ],
    "sg:phone":"+1 781 935 3873",
    "sg:postcode":"01801",
    "sg:province":"MA",
    "sg:website":"www.dunkindonuts.com",
    "wof:name":"Dunkin Donuts",
    "wof:placetype":"venue"
},
  "geometry": {"coordinates":[-71.120045,42.479888],"type":"Point"}
}