{
  "type": "Feature",
  "properties": {
    "addr:full":"1520 East St Pittsfield MA 01201",
    "addr:housenumber":"1520",
    "addr:postcode":"01201",
    "addr:street":"East St",
    "iso:country":"US",
    "sg:address":"1520 East St",
    "sg:city":"Pittsfield",
    "sg:classifiers":[
        {
            "category":"Health Services",
            "subcategory":"Hospital",
            "type":"Services"
        }
    ],
    "sg:phone":"+1 413 447 8051",
    "sg:postcode":"01201",
    "sg:province":"MA",
    "sg:tags":[
        "equipment",
        "supply"
    ],
    "sg:website":"http://www.pst-corp.com",
    "wof:name":"P S T",
    "wof:placetype":"venue"
},
  "geometry": {"coordinates":[-73.209941,42.45465],"type":"Point"}
}