{
  "type": "Feature",
  "properties": {
    "iso:country":"US",
    "sg:address":"22 Podunk Pike",
    "sg:city":"Spencer",
    "sg:classifiers":[
        {
            "category":"Transit Center",
            "subcategory":"Freight",
            "type":"Transportation"
        },
        {
            "category":"Freight",
            "type":"Transportation"
        }
    ],
    "sg:phone":"+1 508 885 6601",
    "sg:postcode":"01562",
    "sg:province":"MA",
    "sg:tags":[
        "trucking-motor",
        "trucking"
    ],
    "wof:name":"Swift Transportation",
    "wof:placetype":"venue"
},
  "geometry": {"coordinates":[-72.022942,42.218444],"type":"Point"}
}