{
  "type": "Feature",
  "properties": {
    "addr:full":"1019 Trapelo Rd Waltham MA 02452",
    "addr:housenumber":"1019",
    "addr:postcode":"02452",
    "addr:street":"Trapelo Rd",
    "iso:country":"US",
    "sg:address":"1019 Trapelo Rd",
    "sg:city":"Waltham",
    "sg:classifiers":[
        {
            "category":"Autos & Motor Vehicles",
            "subcategory":"Fuel & Gas Station",
            "type":"Retail Goods"
        }
    ],
    "sg:phone":"+1 781 894 8600",
    "sg:postcode":"02452",
    "sg:province":"MA",
    "sg:tags":[
        "oil"
    ],
    "wof:name":"Trapelo Road Shell",
    "wof:placetype":"venue"
},
  "geometry": {"coordinates":[-71.232555,42.41057],"type":"Point"}
}