{
  "type": "Feature",
  "properties": {
    "iso:country":"US",
    "sg:address":"1188 Parker St",
    "sg:city":"Springfield",
    "sg:classifiers":[
        {
            "category":"Professional",
            "subcategory":"Accounting & Tax Preparation",
            "type":"Services"
        }
    ],
    "sg:phone":"+1 413 796 1215",
    "sg:postcode":"01129",
    "sg:province":"MA",
    "sg:tags":[
        "accountant"
    ],
    "wof:name":"Baxter Accounting",
    "wof:placetype":"venue"
},
  "geometry": {"coordinates":[-72.498971,42.117452],"type":"Point"}
}