{
  "type": "Feature",
  "properties": {
    "addr:full": "110 Stergis Way Dedham MA 02026",
    "addr:housenumber": "110",
    "addr:postcode": "02026",
    "addr:street": "Stergis Way",
    "iso:country": "US",
    "sg:address": "110 Stergis Way",
    "sg:city": "Dedham",
    "sg:classifiers": [
      {
        "category": "Health Services",
        "subcategory": "Health Practitioner",
        "type": "Services"
      }
    ],
    "sg:phone": "+1 800 364 3306",
    "sg:postcode": "02026",
    "sg:province": "MA",
    "sg:tags": [
      "home"
    ],
    "sg:website": "http://www.bostonhomeinfusion.com",
    "wof:name": "Boston Home Infusion Toll Free-Dial '1' \u0026 Then",
    "wof:placetype": "venue"
  },
  "geometry": {"coordinates":[-71.176667,42.234527],"type":"Point"}
}
