{
  "type": "Feature",
  "properties": {
    "addr:full": "2 Springfield St Three Rivers MA 01080",
    "addr:housenumber": "2",
    "addr:postcode": "01080",
    "addr:street": "Springfield St",
    "iso:country": "US",
    "sg:address": "2 Springfield St",
    "sg:city": "Three Rivers",
    "sg:classifiers": [
      {
        "category": "Manufacturing",
        "subcategory": "Printing",
        "type": "Manufacturing \u0026 Wholesale Goods"
      }
    ],
    "sg:phone": "+1 413 283 8556",
    "sg:postcode": "01080",
    "sg:province": "MA",
    "sg:tags": [
      "printer"
    ],
    "sg:website": "www.vanvolumes.com",
    "wof:name": "Van Volumes Book Printing",
    "wof:placetype": "venue"
  },
  "geometry": {"coordinates":[-72.365417,42.179795],"type":"Point"}
}
