{
  "type": "Feature",
  "properties": {
    "addr:full": "1278 Dorchester Ave Dorchester MA 02122",
    "addr:housenumber": "1278",
    "addr:postcode": "02122",
    "addr:street": "Dorchester Ave",
    "iso:country": "US",
    "sg:address": "1278 Dorchester Ave",
    "sg:city": "Dorchester",
    "sg:classifiers": [
      {
        "category": "Wholesale",
        "subcategory": "Scrap",
        "type": "Manufacturing \u0026 Wholesale Goods"
      }
    ],
    "sg:phone": "+1 617 265 1034",
    "sg:postcode": "02122",
    "sg:province": "MA",
    "sg:tags": [
      "recycling",
      "center"
    ],
    "wof:name": "Dorchester Bottle \u0026 Cans",
    "wof:placetype": "venue"
  },
  "geometry": {"coordinates":[-71.058338,42.307609],"type":"Point"}
}
