{
  "type": "Feature",
  "properties": {
    "iso:country":"US",
    "sg:address":"1278 Dorchester Ave",
    "sg:city":"Dorchester",
    "sg:classifiers":[
        {
            "category":"Wholesale",
            "subcategory":"Scrap",
            "type":"Manufacturing & Wholesale Goods"
        }
    ],
    "sg:phone":"+1 617 265 1034",
    "sg:postcode":"02122",
    "sg:province":"MA",
    "sg:tags":[
        "recycling",
        "center"
    ],
    "wof:name":"Dorchester Bottle & Cans",
    "wof:placetype":"venue"
},
  "geometry": {"coordinates":[-71.05833800000001,42.307609],"type":"Point"}
}