{
  "type": "Feature",
  "properties": {
    "addr:full":"85 Sam Fonzo Dr Beverly MA 01915",
    "addr:housenumber":"85",
    "addr:postcode":"01915",
    "addr:street":"Sam Fonzo Dr",
    "iso:country":"US",
    "sg:address":"85 Sam Fonzo Dr",
    "sg:city":"Beverly",
    "sg:classifiers":[
        {
            "category":"Manufacturing",
            "subcategory":"Printing",
            "type":"Manufacturing & Wholesale Goods"
        }
    ],
    "sg:phone":"+1 978 777 8200",
    "sg:postcode":"01915",
    "sg:province":"MA",
    "sg:tags":[
        "publisher"
    ],
    "sg:website":"www.libertyink.com",
    "wof:name":"Liberty Publishing Inc",
    "wof:placetype":"venue"
},
  "geometry": {"coordinates":[-70.90541,42.581708],"type":"Point"}
}