{
  "type": "Feature",
  "properties": {
    "addr:full": "79 Humphrey St Marblehead MA 01945",
    "addr:housenumber": "79",
    "addr:postcode": "01945",
    "addr:street": "Humphrey St",
    "iso:country": "US",
    "sg:address": "79 Humphrey St",
    "sg:city": "Marblehead",
    "sg:classifiers": [
      {
        "category": "Building \u0026 Trades",
        "subcategory": "Construction",
        "type": "Services"
      }
    ],
    "sg:phone": "+1 781 631 0441",
    "sg:postcode": "01945",
    "sg:province": "MA",
    "sg:tags": [
      "painter"
    ],
    "wof:name": "Juan In A Million",
    "wof:placetype": "venue"
  },
  "geometry": {"coordinates":[-70.876625,42.490913],"type":"Point"}
}
