{
  "type": "Feature",
  "properties": {
    "iso:country":"US",
    "sg:address":"500 W Cummings Park Ste 6050",
    "sg:city":"Woburn",
    "sg:classifiers":[
        {
            "category":"Real Estate",
            "subcategory":"Real Estate Services",
            "type":"Services"
        }
    ],
    "sg:phone":"+1 781 932 9229",
    "sg:postcode":"01801",
    "sg:province":"MA",
    "sg:tags":[
        "management",
        "property"
    ],
    "sg:website":"www.aptcondoteam.com",
    "wof:name":"American Properties Team Inc",
    "wof:placetype":"venue"
},
  "geometry": {"coordinates":[-71.128732,42.495415],"type":"Point"}
}