{
  "type": "Feature",
  "properties": {
    "addr:full": "10 N Dartmouth Mall North Dartmouth MA 02747",
    "addr:housenumber": "10",
    "addr:postcode": "02747",
    "addr:street": "N Dartmouth Mall",
    "iso:country": "US",
    "sg:address": "10 N Dartmouth Mall",
    "sg:city": "North Dartmouth",
    "sg:classifiers": [
      {
        "category": "Communications",
        "subcategory": "Film \u0026 Video Production",
        "type": "Services"
      }
    ],
    "sg:phone": "+1 508 985 9000",
    "sg:postcode": "02747",
    "sg:province": "MA",
    "sg:tags": [
      "taping"
    ],
    "wof:name": "B-Sharp Video Productions",
    "wof:placetype": "venue"
  },
  "geometry": {"coordinates":[-70.994162,41.64132],"type":"Point"}
}
