{
  "type": "Feature",
  "properties": {
    "addr:full": "6 Town Hall Dr Princeton MA 01541",
    "addr:housenumber": "6",
    "addr:postcode": "01541",
    "addr:street": "Town Hall Dr",
    "iso:country": "US",
    "sg:address": "6 Town Hall Dr",
    "sg:city": "Princeton",
    "sg:classifiers": [
      {
        "category": "Government",
        "subcategory": "Office",
        "type": "Public Place"
      }
    ],
    "sg:phone": "+1 978 464 2102",
    "sg:postcode": "01541",
    "sg:province": "MA",
    "sg:tags": [
      "village"
    ],
    "wof:name": "Board Of Selectmen",
    "wof:placetype": "venue"
  },
  "geometry": {"coordinates":[-71.87751,42.448666],"type":"Point"}
}
