{
  "type": "Feature",
  "properties": {
    "addr:full": "49 Rose St Stoughton MA 02072",
    "addr:housenumber": "49",
    "addr:postcode": "02072",
    "addr:street": "Rose St",
    "iso:country": "US",
    "sg:address": "49 Rose St",
    "sg:city": "Stoughton",
    "sg:classifiers": [
      {
        "category": "Education",
        "subcategory": "Music School",
        "type": "Public Place"
      }
    ],
    "sg:phone": "+1 781 341 0776",
    "sg:postcode": "02072",
    "sg:province": "MA",
    "sg:tags": [
      "instrument",
      "teacher",
      "musical"
    ],
    "wof:name": "Harris Musical Products",
    "wof:placetype": "venue"
  },
  "geometry": {"coordinates":[-71.104062,42.125766],"type":"Point"}
}
