{
  "type": "Feature",
  "properties": {
    "iso:country":"US",
    "sg:address":"15 Liberty St",
    "sg:city":"Merrimac",
    "sg:classifiers":[
        {
            "category":"Wholesale",
            "subcategory":"Scrap",
            "type":"Manufacturing & Wholesale Goods"
        }
    ],
    "sg:phone":"+1 978 346 8300",
    "sg:postcode":"01860",
    "sg:province":"MA",
    "sg:tags":[
        "material",
        "metal",
        "iron"
    ],
    "wof:name":"Blue Recycling",
    "wof:placetype":"venue"
},
  "geometry": {"coordinates":[-71.002606,42.835708],"type":"Point"}
}