{
  "type": "Feature",
  "properties": {
    "addr:full": "15 Liberty St Merrimac MA 01860",
    "addr:housenumber": "15",
    "addr:postcode": "01860",
    "addr:street": "Liberty St",
    "iso:country": "US",
    "sg:address": "15 Liberty St",
    "sg:city": "Merrimac",
    "sg:classifiers": [
      {
        "category": "Wholesale",
        "subcategory": "Scrap",
        "type": "Manufacturing \u0026 Wholesale Goods"
      }
    ],
    "sg:phone": "+1 978 346 8300",
    "sg:postcode": "01860",
    "sg:province": "MA",
    "sg:tags": [
      "material",
      "metal",
      "iron"
    ],
    "wof:name": "Blue Recycling",
    "wof:placetype": "venue"
  },
  "geometry": {"coordinates":[-71.002606,42.835708],"type":"Point"}
}
