{
  "type": "Feature",
  "properties": {
    "addr:full": "525 Canton Ave Milton MA 02186",
    "addr:housenumber": "525",
    "addr:postcode": "02186",
    "addr:street": "Canton Ave",
    "iso:country": "US",
    "sg:address": "525 Canton Ave",
    "sg:city": "Milton",
    "sg:classifiers": [
      {
        "category": "Government",
        "subcategory": "Office",
        "type": "Public Place"
      }
    ],
    "sg:phone": "+1 617 696 5812",
    "sg:postcode": "02186",
    "sg:province": "MA",
    "sg:tags": [
      "city",
      "program",
      "health"
    ],
    "sg:website": "www.townofmilton.org",
    "wof:name": "Health Dept",
    "wof:placetype": "venue"
  },
  "geometry": {"coordinates":[-71.08218,42.2519],"type":"Point"}
}
