{
  "type": "Feature",
  "properties": {
    "addr:full":"45 North St Dalton MA 01226",
    "addr:housenumber":"45",
    "addr:postcode":"01226",
    "addr:street":"North St",
    "iso:country":"US",
    "sg:address":"45 North St",
    "sg:city":"Dalton",
    "sg:classifiers":[
        {
            "category":"Social Services",
            "type":"Services"
        }
    ],
    "sg:phone":"+1 413 684 0631",
    "sg:postcode":"01226",
    "sg:province":"MA",
    "sg:tags":[
        "organization",
        "welfare"
    ],
    "wof:name":"Unity Lodge",
    "wof:placetype":"venue"
},
  "geometry": {"coordinates":[-73.15931399999999,42.474792],"type":"Point"}
}