{
  "type": "Feature",
  "properties": {
    "addr:full":"174 Hampden St Roxbury MA 02119",
    "addr:housenumber":"174",
    "addr:postcode":"02119",
    "addr:street":"Hampden St",
    "iso:country":"US",
    "sg:address":"174 Hampden St",
    "sg:city":"Roxbury",
    "sg:classifiers":[
        {
            "category":"Wholesale",
            "subcategory":"Hardware",
            "type":"Manufacturing & Wholesale Goods"
        }
    ],
    "sg:phone":"+1 617 318 1012",
    "sg:postcode":"02119",
    "sg:province":"MA",
    "sg:tags":[
        "hardware-wholesale",
        "manufacturer"
    ],
    "wof:name":"Flood Square Hardware",
    "wof:placetype":"venue"
},
  "geometry": {"coordinates":[-71.075216,42.327191],"type":"Point"}
}