{
  "type": "Feature",
  "properties": {
    "iso:country":"US",
    "sg:address":"120 School St",
    "sg:city":"Lexington",
    "sg:classifiers":[
        {
            "category":"Health Services",
            "subcategory":"Dentist",
            "type":"Services"
        }
    ],
    "sg:phone":"+1 781 862 6433",
    "sg:postcode":"02421",
    "sg:province":"MA",
    "wof:name":"Davis Sarah Haven DMD LLC",
    "wof:placetype":"venue"
},
  "geometry": {"coordinates":[-71.250998,42.440729],"type":"Point"}
}