{
  "type": "Feature",
  "properties": {
    "iso:country":"US",
    "sg:address":"180 Eastern Ave",
    "sg:city":"Springfield",
    "sg:classifiers":[
        {
            "category":"Restaurant",
            "type":"Food & Drink"
        }
    ],
    "sg:phone":"+1 413 214 7619",
    "sg:postcode":"01109",
    "sg:province":"MA",
    "wof:name":"Collosal Soul Food",
    "wof:placetype":"venue"
},
  "geometry": {"coordinates":[-72.56310000000001,42.106279],"type":"Point"}
}