{
  "type": "Feature",
  "properties": {
    "addr:full": "13 Railroad Sq Haverhill MA 01832",
    "addr:housenumber": "13",
    "addr:postcode": "01832",
    "addr:street": "Railroad Sq",
    "iso:country": "US",
    "sg:address": "13 Railroad Sq",
    "sg:city": "Haverhill",
    "sg:classifiers": [
      {
        "category": "Personal",
        "subcategory": "Beauty Salon",
        "type": "Services"
      }
    ],
    "sg:phone": "+1 978 373 1433",
    "sg:postcode": "01832",
    "sg:province": "MA",
    "wof:name": "Studio At 13",
    "wof:placetype": "venue"
  },
  "geometry": {"coordinates":[-71.085898,42.77316],"type":"Point"}
}
