{
  "type": "Feature",
  "properties": {
    "addr:full": "9 Valley St Hatfield MA 01038",
    "addr:housenumber": "9",
    "addr:postcode": "01038",
    "addr:street": "Valley St",
    "iso:country": "US",
    "sg:address": "9 Valley St",
    "sg:city": "Hatfield",
    "sg:classifiers": [
      {
        "category": "Food \u0026 Beverages",
        "subcategory": "Bakery",
        "type": "Retail Goods"
      },
      {
        "category": "Bakery",
        "type": "Food \u0026 Drink"
      }
    ],
    "sg:phone": "+1 413 247 9799",
    "sg:postcode": "01038",
    "sg:province": "MA",
    "sg:tags": [
      "bakers-wholesale"
    ],
    "wof:name": "Lickety Splitz",
    "wof:placetype": "venue"
  },
  "geometry": {"coordinates":[-72.599674,42.364931],"type":"Point"}
}
