{
  "type": "Feature",
  "properties": {
    "addr:full":"367 Russell St Hadley MA 01035",
    "addr:housenumber":"367",
    "addr:postcode":"01035",
    "addr:street":"Russell St",
    "iso:country":"US",
    "sg:address":"367 Russell St",
    "sg:city":"Hadley",
    "sg:classifiers":[
        {
            "category":"Ice Cream",
            "type":"Food & Drink"
        }
    ],
    "sg:menulink":"http://www.allmenus.com/ma/hadley/168413-dairy-queen/menu/",
    "sg:phone":"+1 413 582 0009",
    "sg:postcode":"01035",
    "sg:province":"MA",
    "sg:tags":[
        "burger",
        "american"
    ],
    "wof:name":"Dairy Queen",
    "wof:placetype":"venue"
},
  "geometry": {"coordinates":[-72.54866,42.35732],"type":"Point"}
}