{
  "type": "Feature",
  "properties": {
    "addr:full":"1 Milford St Ste C Upton MA 01568",
    "addr:housenumber":"1",
    "addr:postcode":"01568",
    "addr:street":"Milford St Ste C",
    "iso:country":"US",
    "sg:address":"1 Milford St Ste C",
    "sg:city":"Upton",
    "sg:classifiers":[
        {
            "category":"Real Estate",
            "subcategory":"Real Estate Services",
            "type":"Services"
        },
        {
            "category":"Real Estate",
            "subcategory":"Real Estate Agent",
            "type":"Services"
        }
    ],
    "sg:phone":"+1 508 529 7653",
    "sg:postcode":"01568",
    "sg:province":"MA",
    "sg:tags":[
        "buyer",
        "broker"
    ],
    "wof:name":"Cbl Realty",
    "wof:placetype":"venue"
},
  "geometry": {"coordinates":[-71.603172,42.173721],"type":"Point"}
}