{
  "type": "Feature",
  "properties": {
    "iso:country":"US",
    "sg:address":"114 Main St",
    "sg:city":"Gloucester",
    "sg:classifiers":[
        {
            "category":"Retail",
            "subcategory":"Auto Repair",
            "type":"Services"
        }
    ],
    "sg:phone":"+1 978 283 4217",
    "sg:postcode":"01930",
    "sg:province":"MA",
    "sg:tags":[
        "automobile",
        "lubrication"
    ],
    "sg:website":"www.myradistributing.com",
    "wof:name":"Myra Distributing Inc",
    "wof:placetype":"venue"
},
  "geometry": {"coordinates":[-70.663702,42.612569],"type":"Point"}
}