{
  "type": "Feature",
  "properties": {
    "addr:full": "14 Mayberry Dr Westborough MA 01581",
    "addr:housenumber": "14",
    "addr:postcode": "01581",
    "addr:street": "Mayberry Dr",
    "iso:country": "US",
    "sg:address": "14 Mayberry Dr",
    "sg:city": "Westborough",
    "sg:classifiers": [
      {
        "category": "Real Estate",
        "subcategory": "Real Estate Operator",
        "type": "Services"
      }
    ],
    "sg:phone": "+1 508 366 9664",
    "sg:postcode": "01581",
    "sg:province": "MA",
    "sg:tags": [
      "condominium"
    ],
    "wof:name": "Heritage Hall Condominiums",
    "wof:placetype": "venue"
  },
  "geometry": {"coordinates":[-71.61521,42.276209],"type":"Point"}
}
