{
  "type": "Feature",
  "properties": {
    "iso:country":"US",
    "sg:address":"143 Palmer Ave",
    "sg:city":"Falmouth",
    "sg:classifiers":[
        {
            "category":"Health Services",
            "subcategory":"Chiropractor",
            "type":"Services"
        }
    ],
    "sg:phone":"+1 508 457 1515",
    "sg:postcode":"02540",
    "sg:province":"MA",
    "wof:name":"Steven D Jacobs DC",
    "wof:placetype":"venue"
},
  "geometry": {"coordinates":[-70.620833,41.556759],"type":"Point"}
}