{
  "type": "Feature",
  "properties": {
    "addr:full":"15 Commonwealth Ave Suite 202 Woburn MA 01801",
    "addr:housenumber":"15",
    "addr:postcode":"01801",
    "addr:street":"Commonwealth Ave Suite 202",
    "iso:country":"US",
    "sg:address":"15 Commonwealth Ave Suite 202",
    "sg:city":"Woburn",
    "sg:phone":"+1 781 569 6047",
    "sg:postcode":"01801",
    "sg:province":"MA",
    "wof:name":"College Pro Painters",
    "wof:placetype":"venue"
},
  "geometry": {"coordinates":[-71.13203,42.513235],"type":"Point"}
}