{
  "type": "Feature",
  "properties": {
    "iso:country":"US",
    "sg:address":"847 Washington St",
    "sg:city":"Canton",
    "sg:classifiers":[
        {
            "category":"Professional",
            "subcategory":"Lawyer & Legal Services",
            "type":"Services"
        }
    ],
    "sg:phone":"+1 781 828 0696",
    "sg:postcode":"02021",
    "sg:province":"MA",
    "wof:name":"Carroll Paul B Lwyr",
    "wof:placetype":"venue"
},
  "geometry": {"coordinates":[-71.144203,42.160301],"type":"Point"}
}