{
  "type": "Feature",
  "properties": {
    "addr:full":"inside the CambridgeSide Galleria 100 CambridgeSide Place Cambridge MA 02141",
    "addr:housenumber":"100",
    "addr:postcode":"02141",
    "addr:street":"Galleria;Place",
    "iso:country":"US",
    "sg:address":"inside the CambridgeSide Galleria 100 CambridgeSide Place",
    "sg:city":"Cambridge",
    "sg:classifiers":[
        {
            "category":"Shopping",
            "subcategory":"Clothing, Apparel, & Fashions",
            "type":"Retail Goods"
        }
    ],
    "sg:phone":"+1 617 577 0070",
    "sg:postcode":"02141",
    "sg:province":"MA",
    "sg:website":"www.oldnavy.com",
    "wof:name":"Old Navy",
    "wof:placetype":"venue"
},
  "geometry": {"coordinates":[-71.07576299999999,42.36784],"type":"Point"}
}