{
  "type": "Feature",
  "properties": {
    "iso:country":"US",
    "sg:address":"118 Bowdoin St",
    "sg:city":"Dorchester Ctr",
    "sg:classifiers":[
        {
            "category":"Organizations",
            "subcategory":"Religious Organization",
            "type":"Services"
        }
    ],
    "sg:phone":"+1 617 282 0243",
    "sg:postcode":"02124",
    "sg:province":"MA",
    "sg:tags":[
        "church"
    ],
    "wof:name":"Chief Cornerstone Church-God",
    "wof:placetype":"venue"
},
  "geometry": {"coordinates":[-71.07155400000001,42.302979],"type":"Point"}
}