{
  "type": "Feature",
  "properties": {
    "addr:full":"525 York St Canton MA 02021",
    "addr:housenumber":"525",
    "addr:postcode":"02021",
    "addr:street":"York St",
    "iso:country":"US",
    "sg:address":"525 York St",
    "sg:city":"Canton",
    "sg:classifiers":[
        {
            "category":"Retail",
            "subcategory":"Laundry & Dry Cleaning",
            "type":"Services"
        }
    ],
    "sg:phone":"+1 781 821 0898",
    "sg:postcode":"02021",
    "sg:province":"MA",
    "sg:tags":[
        "cleaner",
        "rug",
        "carpet"
    ],
    "wof:name":"Chem Shl",
    "wof:placetype":"venue"
},
  "geometry": {"coordinates":[-71.08081799999999,42.156818],"type":"Point"}
}