{
  "type": "Feature",
  "properties": {
    "addr:full": "195 Hanover St Hanover MA 02339",
    "addr:housenumber": "195",
    "addr:postcode": "02339",
    "addr:street": "Hanover St",
    "iso:country": "US",
    "sg:address": "195 Hanover St",
    "sg:city": "Hanover",
    "sg:classifiers": [
      {
        "category": "Building \u0026 Trades",
        "subcategory": "Plumbing",
        "type": "Services"
      }
    ],
    "sg:phone": "+1 781 826 4651",
    "sg:postcode": "02339",
    "sg:province": "MA",
    "sg:tags": [
      "fittings-electric",
      "conduit"
    ],
    "wof:name": "East Coast Distributors",
    "wof:placetype": "venue"
  },
  "geometry": {"coordinates":[-70.829662,42.115196],"type":"Point"}
}
