{
  "type": "Feature",
  "properties": {
    "addr:full":"972 Main St Walpole MA 02081",
    "addr:housenumber":"972",
    "addr:postcode":"02081",
    "addr:street":"Main St",
    "iso:country":"US",
    "sg:address":"972 Main St",
    "sg:city":"Walpole",
    "sg:classifiers":[
        {
            "category":"Government",
            "subcategory":"Police Station",
            "type":"Public Place"
        }
    ],
    "sg:phone":"+1 508 668 1095",
    "sg:postcode":"02081",
    "sg:province":"MA",
    "sg:tags":[
        "department"
    ],
    "sg:website":"www.walpolepd.com",
    "wof:name":"Walpole Police Dept",
    "wof:placetype":"venue"
},
  "geometry": {"coordinates":[-71.25290800000001,42.145826],"type":"Point"}
}