{
  "type": "Feature",
  "properties": {
    "addr:full":"70 Pleasant St Winchendon MA 01475",
    "addr:housenumber":"70",
    "addr:postcode":"01475",
    "addr:street":"Pleasant St",
    "iso:country":"US",
    "sg:address":"70 Pleasant St",
    "sg:city":"Winchendon",
    "sg:classifiers":[
        {
            "category":"Retail",
            "subcategory":"Funeral Services",
            "type":"Services"
        }
    ],
    "sg:phone":"+1 978 297 1234",
    "sg:postcode":"01475",
    "sg:province":"MA",
    "sg:tags":[
        "director"
    ],
    "wof:name":"Fletcher-Hebert Funeral Home",
    "wof:placetype":"venue"
},
  "geometry": {"coordinates":[-72.049412,42.681802],"type":"Point"}
}