{
  "type": "Feature",
  "properties": {
    "addr:full": "25 Westford Rd Ayer MA 01432",
    "addr:housenumber": "25",
    "addr:postcode": "01432",
    "addr:street": "Westford Rd",
    "iso:country": "US",
    "sg:address": "25 Westford Rd",
    "sg:city": "Ayer",
    "sg:phone": "+1 978 772 2031",
    "sg:postcode": "01432",
    "sg:province": "MA",
    "sg:tags": [
      "oil"
    ],
    "wof:name": "Ayer Oil Co",
    "wof:placetype": "venue"
  },
  "geometry": {"coordinates":[-71.538752,42.561546],"type":"Point"}
}
