{
  "type": "Feature",
  "properties": {
    "addr:full":"1037 Main St Winchester MA 01890",
    "addr:housenumber":"1037",
    "addr:postcode":"01890",
    "addr:street":"Main St",
    "iso:country":"US",
    "sg:address":"1037 Main St",
    "sg:city":"Winchester",
    "sg:classifiers":[
        {
            "category":"Building & Trades",
            "subcategory":"Locksmith",
            "type":"Services"
        }
    ],
    "sg:phone":"+1 617 925 3739",
    "sg:postcode":"01890",
    "sg:province":"MA",
    "sg:tags":[
        "key"
    ],
    "wof:name":"Boston A Locksmith",
    "wof:placetype":"venue"
},
  "geometry": {"coordinates":[-71.14570500000001,42.465624],"type":"Point"}
}