{
  "type": "Feature",
  "properties": {
    "iso:country":"US",
    "sg:address":"217 Washington St",
    "sg:city":"Fairhaven",
    "sg:classifiers":[
        {
            "category":"Restaurant",
            "type":"Food & Drink"
        }
    ],
    "sg:phone":"+1 508 994 3055",
    "sg:postcode":"02719",
    "sg:province":"MA",
    "wof:name":"Mc Donald's",
    "wof:placetype":"venue"
},
  "geometry": {"coordinates":[-70.888752,41.641299],"type":"Point"}
}