{
  "type": "Feature",
  "properties": {
    "iso:country":"US",
    "sg:address":"163 Shears St",
    "sg:city":"Wrentham",
    "sg:classifiers":[
        {
            "category":"Professional",
            "subcategory":"Testing Lab",
            "type":"Services"
        }
    ],
    "sg:phone":"+1 508 384 7097",
    "sg:postcode":"02093",
    "sg:province":"MA",
    "sg:tags":[
        "chemist"
    ],
    "wof:name":"Shipps Inc",
    "wof:placetype":"venue"
},
  "geometry": {"coordinates":[-71.329948,42.078553],"type":"Point"}
}