{
  "type": "Feature",
  "properties": {
    "addr:full":"237 W Center St West Bridgewater MA 02379",
    "addr:housenumber":"237",
    "addr:postcode":"02379",
    "addr:street":"W Center St",
    "iso:country":"US",
    "sg:address":"237 W Center St",
    "sg:city":"West Bridgewater",
    "sg:classifiers":[
        {
            "category":"Shopping",
            "subcategory":"Florist",
            "type":"Retail Goods"
        }
    ],
    "sg:phone":"+1 508 586 1690",
    "sg:postcode":"02379",
    "sg:province":"MA",
    "wof:name":"Farley's Flowers",
    "wof:placetype":"venue"
},
  "geometry": {"coordinates":[-71.021383,42.016883],"type":"Point"}
}