{
  "type": "Feature",
  "properties": {
    "addr:full":"58 Chapin St West Springfield MA 01089",
    "addr:housenumber":"58",
    "addr:postcode":"01089",
    "addr:street":"Chapin St",
    "iso:country":"US",
    "sg:address":"58 Chapin St",
    "sg:city":"West Springfield",
    "sg:classifiers":[
        {
            "category":"Organizations",
            "subcategory":"Community Association",
            "type":"Services"
        }
    ],
    "sg:phone":"+1   ",
    "sg:postcode":"01089",
    "sg:province":"MA",
    "sg:tags":[
        "membership",
        "cl"
    ],
    "wof:name":"Verdi Club Inc",
    "wof:placetype":"venue"
},
  "geometry": {"coordinates":[-72.603093,42.099627],"type":"Point"}
}