{
  "type": "Feature",
  "properties": {
    "addr:full": "1565 Main St Tewksbury MA 01876",
    "addr:housenumber": "1565",
    "addr:postcode": "01876",
    "addr:street": "Main St",
    "iso:country": "US",
    "sg:address": "1565 Main St",
    "sg:city": "Tewksbury",
    "sg:classifiers": [
      {
        "category": "Health Services",
        "subcategory": "Health Practitioner",
        "type": "Services"
      }
    ],
    "sg:phone": "+1 978 851 8768",
    "sg:postcode": "01876",
    "sg:province": "MA",
    "sg:tags": [
      "therapist",
      "physical"
    ],
    "wof:name": "Tewksbury Physical Therapy",
    "wof:placetype": "venue"
  },
  "geometry": {"coordinates":[-71.218241,42.598061],"type":"Point"}
}
