{
  "type": "Feature",
  "properties": {
    "addr:full": "55 Walker St Newtonville MA 02460",
    "addr:housenumber": "55",
    "addr:postcode": "02460",
    "addr:street": "Walker St",
    "iso:country": "US",
    "sg:address": "55 Walker St",
    "sg:city": "Newtonville",
    "sg:classifiers": [
      {
        "category": "Personal",
        "type": "Services"
      }
    ],
    "sg:phone": "+1 617 527 9473",
    "sg:postcode": "02460",
    "sg:province": "MA",
    "sg:tags": [
      "party",
      "planning",
      "event"
    ],
    "wof:name": "Up Wise Marketing",
    "wof:placetype": "venue"
  },
  "geometry": {"coordinates":[-71.212531,42.352744],"type":"Point"}
}
