{
  "type": "Feature",
  "properties": {
    "addr:full": "450 Massapoag Ave Sharon MA 02067",
    "addr:housenumber": "450",
    "addr:postcode": "02067",
    "addr:street": "Massapoag Ave",
    "iso:country": "US",
    "sg:address": "450 Massapoag Ave",
    "sg:city": "Sharon",
    "sg:classifiers": [
      {
        "category": "Professional",
        "subcategory": "Management \u0026 Consulting",
        "type": "Services"
      }
    ],
    "sg:phone": "+1 781 784 0200",
    "sg:postcode": "02067",
    "sg:province": "MA",
    "sg:tags": [
      "international",
      "consultant"
    ],
    "wof:name": "AJM Group",
    "wof:placetype": "venue"
  },
  "geometry": {"coordinates":[-71.172547,42.079142],"type":"Point"}
}
