{
  "type": "Feature",
  "properties": {
    "iso:country":"US",
    "sg:address":"3280 County St",
    "sg:city":"Somerset",
    "sg:classifiers":[
        {
            "category":"Retail",
            "subcategory":"Auto Repair",
            "type":"Services"
        }
    ],
    "sg:phone":"+1 508 672 0096",
    "sg:postcode":"02726",
    "sg:province":"MA",
    "sg:tags":[
        "repairing",
        "automobile"
    ],
    "wof:name":"Nelson's Auto Repair",
    "wof:placetype":"venue"
},
  "geometry": {"coordinates":[-71.13507,41.777207],"type":"Point"}
}