{
  "type": "Feature",
  "properties": {
    "iso:country":"US",
    "sg:address":"169 S Spencer Rd",
    "sg:city":"Spencer",
    "sg:classifiers":[
        {
            "category":"Building & Trades",
            "subcategory":"Construction",
            "type":"Services"
        }
    ],
    "sg:phone":"+1 508 885 5151",
    "sg:postcode":"01562",
    "sg:province":"MA",
    "sg:tags":[
        "excavating",
        "contractor"
    ],
    "wof:name":"Bercume Equipment",
    "wof:placetype":"venue"
},
  "geometry": {"coordinates":[-72.014625,42.197458],"type":"Point"}
}