{
  "type": "Feature",
  "properties": {
    "addr:full": "603 Main St Wilbraham MA 01095",
    "addr:housenumber": "603",
    "addr:postcode": "01095",
    "addr:street": "Main St",
    "iso:country": "US",
    "sg:address": "603 Main St",
    "sg:city": "Wilbraham",
    "sg:classifiers": [
      {
        "category": "Wholesale",
        "subcategory": "Meat",
        "type": "Manufacturing \u0026 Wholesale Goods"
      }
    ],
    "sg:phone": "+1 413 596 3135",
    "sg:postcode": "01095",
    "sg:province": "MA",
    "sg:tags": [
      "poultry",
      "plant",
      "processing"
    ],
    "wof:name": "Bennett Turkey Farms Inc",
    "wof:placetype": "venue"
  },
  "geometry": {"coordinates":[-72.4339,42.114772],"type":"Point"}
}
