{
  "type": "Feature",
  "properties": {
    "iso:country":"US",
    "sg:address":"657 College Hwy",
    "sg:city":"Southwick",
    "sg:classifiers":[
        {
            "category":"Retail",
            "subcategory":"Car Wash",
            "type":"Services"
        }
    ],
    "sg:phone":"+1 413 569 3459",
    "sg:postcode":"01077",
    "sg:province":"MA",
    "sg:tags":[
        "polishing",
        "washing"
    ],
    "wof:name":"Valvoline Express Care",
    "wof:placetype":"venue"
},
  "geometry": {"coordinates":[-72.764242,42.068799],"type":"Point"}
}