{
  "type": "Feature",
  "properties": {
    "addr:full": "657 College Hwy Southwick MA 01077",
    "addr:housenumber": "657",
    "addr:postcode": "01077",
    "addr:street": "College Hwy",
    "iso:country": "US",
    "ovtr:label": "Valvoline Express Care, 657 College Hwy Southwick MA US",
    "ovtr:similarity": 2.1104629039764404,
    "sg:address": "657 College Hwy",
    "sg:city": "Southwick",
    "sg:classifiers": [
      {
        "category": "Retail",
        "subcategory": "Car Wash",
        "type": "Services"
      }
    ],
    "sg:phone": "+1 413 569 3459",
    "sg:postcode": "01077",
    "sg:province": "MA",
    "sg:tags": [
      "polishing",
      "washing"
    ],
    "wof:name": "Valvoline Express Care",
    "wof:placetype": "venue"
  },
  "geometry": {"coordinates":[-72.764242,42.068799],"type":"Point"}
}
