{
  "type": "Feature",
  "properties": {
    "addr:full": "1 Bartlett St Lowell MA 01852",
    "addr:housenumber": "1",
    "addr:postcode": "01852",
    "addr:street": "Bartlett St",
    "iso:country": "US",
    "sg:address": "1 Bartlett St",
    "sg:city": "Lowell",
    "sg:classifiers": [
      {
        "category": "Organizations",
        "subcategory": "Religious Organization",
        "type": "Services"
      }
    ],
    "sg:phone": "+1 978 459 9631",
    "sg:postcode": "01852",
    "sg:province": "MA",
    "sg:tags": [
      "church"
    ],
    "sg:website": "www.cculowell.org",
    "wof:name": "Christ Church United In Lowell",
    "wof:placetype": "venue"
  },
  "geometry": {"coordinates":[-71.302,42.645331],"type":"Point"}
}
