{
  "type": "Feature",
  "properties": {
    "iso:country":"US",
    "sg:address":"85 Maple Street",
    "sg:city":"Stoneham",
    "sg:classifiers":[
        {
            "category":"Health Services",
            "subcategory":"Dentist",
            "type":"Services"
        }
    ],
    "sg:phone":"+1 781 438 6110",
    "sg:postcode":"02180",
    "sg:province":"MA",
    "wof:name":"Advanced Dental Technologies",
    "wof:placetype":"venue"
},
  "geometry": {"coordinates":[-71.108368,42.478719],"type":"Point"}
}