{
  "type": "Feature",
  "properties": {
    "addr:full": "192 W Main St West Brookfield MA 01585",
    "addr:housenumber": "192",
    "addr:postcode": "01585",
    "addr:street": "W Main St West",
    "iso:country": "US",
    "sg:address": "192 W Main St",
    "sg:city": "West Brookfield",
    "sg:classifiers": [
      {
        "category": "Wholesale",
        "subcategory": "Machinery \u0026 Supplies",
        "type": "Manufacturing \u0026 Wholesale Goods"
      }
    ],
    "sg:phone": "+1 508 867 5083",
    "sg:postcode": "01585",
    "sg:province": "MA",
    "sg:tags": [
      "machine",
      "tool"
    ],
    "wof:name": "MRSE Inc",
    "wof:placetype": "venue"
  },
  "geometry": {"coordinates":[-72.164594,42.238731],"type":"Point"}
}
