{
  "type": "Feature",
  "properties": {
    "addr:full": "75 York Ave Ste A Randolph MA 02368",
    "addr:housenumber": "75",
    "addr:postcode": "02368",
    "addr:street": "York Ave Ste A",
    "iso:country": "US",
    "sg:address": "75 York Ave Ste A",
    "sg:city": "Randolph",
    "sg:classifiers": [
      {
        "category": "Communications",
        "subcategory": "Newspaper",
        "type": "Services"
      }
    ],
    "sg:phone": "+1 781 963 8169",
    "sg:postcode": "02368",
    "sg:province": "MA",
    "sg:tags": [
      "print",
      "medium"
    ],
    "wof:name": "Retail Sales Inc",
    "wof:placetype": "venue"
  },
  "geometry": {"coordinates":[-71.068261,42.181782],"type":"Point"}
}
