{
  "type": "Feature",
  "properties": {
    "addr:full":"19 Alexander St Billerica MA 01821",
    "addr:housenumber":"19",
    "addr:postcode":"01821",
    "addr:street":"Alexander St",
    "iso:country":"US",
    "sg:address":"19 Alexander St",
    "sg:city":"Billerica",
    "sg:classifiers":[
        {
            "category":"Freight",
            "type":"Transportation"
        }
    ],
    "sg:phone":"+1   ",
    "sg:postcode":"01821",
    "sg:province":"MA",
    "sg:tags":[
        "operator",
        "trucking"
    ],
    "wof:name":"Nieroda Transport Inc",
    "wof:placetype":"venue"
},
  "geometry": {"coordinates":[-71.295998,42.56256],"type":"Point"}
}