{
  "type": "Feature",
  "properties": {
    "iso:country":"US",
    "sg:address":"444 Humphrey St",
    "sg:city":"Swampscott",
    "sg:classifiers":[
        {
            "category":"Food & Beverages",
            "subcategory":"Bakery",
            "type":"Retail Goods"
        }
    ],
    "sg:phone":"+1 781 477 9100",
    "sg:postcode":"01907",
    "sg:province":"MA",
    "sg:tags":[
        "cookie",
        "cracker"
    ],
    "wof:name":"Jacqui Senns Cookies",
    "wof:placetype":"venue"
},
  "geometry": {"coordinates":[-70.90818400000001,42.467844],"type":"Point"}
}