{
  "type": "Feature",
  "properties": {
    "iso:country":"US",
    "sg:address":"29 Kensington St",
    "sg:city":"Newton",
    "sg:classifiers":[
        {
            "category":"Building & Trades",
            "subcategory":"Construction",
            "type":"Services"
        }
    ],
    "sg:phone":"+1 617 244 1415",
    "sg:postcode":"02460",
    "sg:province":"MA",
    "sg:tags":[
        "asphalt",
        "general",
        "paving",
        "contractor",
        "road",
        "driveway"
    ],
    "wof:name":"Quinn Lawrence P Co",
    "wof:placetype":"venue"
},
  "geometry": {"coordinates":[-71.215762,42.354064],"type":"Point"}
}