{
  "type": "Feature",
  "properties": {
    "addr:full": "29 Kensington St Newton MA 02460",
    "addr:housenumber": "29",
    "addr:postcode": "02460",
    "addr:street": "Kensington St",
    "iso:country": "US",
    "sg:address": "29 Kensington St",
    "sg:city": "Newton",
    "sg:classifiers": [
      {
        "category": "Building \u0026 Trades",
        "subcategory": "Construction",
        "type": "Services"
      }
    ],
    "sg:phone": "+1 617 244 1415",
    "sg:postcode": "02460",
    "sg:province": "MA",
    "sg:tags": [
      "asphalt",
      "general",
      "paving",
      "contractor",
      "road",
      "driveway"
    ],
    "wof:name": "Quinn Lawrence P Co",
    "wof:placetype": "venue"
  },
  "geometry": {"coordinates":[-71.215762,42.354064],"type":"Point"}
}
