{
  "type": "Feature",
  "properties": {
    "addr:full":"1181 Broadway Saugus MA 01906",
    "addr:housenumber":"1181",
    "addr:postcode":"01906",
    "addr:street":"Broadway",
    "iso:country":"US",
    "sg:address":"1181 Broadway",
    "sg:city":"Saugus",
    "sg:classifiers":[
        {
            "category":"Shopping",
            "subcategory":"Clothing, Apparel, & Fashions",
            "type":"Retail Goods"
        }
    ],
    "sg:phone":"+1   ",
    "sg:postcode":"01906",
    "sg:province":"MA",
    "sg:tags":[
        "personal"
    ],
    "wof:name":"Denises Fashions",
    "wof:placetype":"venue"
},
  "geometry": {"coordinates":[-71.024067,42.45984],"type":"Point"}
}