{
  "type": "Feature",
  "properties": {
    "addr:full": "607 Middlesex St Lowell MA 01851",
    "addr:housenumber": "607",
    "addr:postcode": "01851",
    "addr:street": "Middlesex St",
    "iso:country": "US",
    "sg:address": "607 Middlesex St",
    "sg:city": "Lowell",
    "sg:classifiers": [
      {
        "category": "Autos \u0026 Motor Vehicles",
        "subcategory": "Automobile Sales",
        "type": "Retail Goods"
      }
    ],
    "sg:phone": "+1 978 453 7433",
    "sg:postcode": "01851",
    "sg:province": "MA",
    "sg:tags": [
      "new",
      "used",
      "dealer",
      "car"
    ],
    "wof:name": "Deals On Wheels Inc",
    "wof:placetype": "venue"
  },
  "geometry": {"coordinates":[-71.319493,42.638587],"type":"Point"}
}
