{
  "type": "Feature",
  "properties": {
    "addr:full":"52 Summit Hill Rd Washington MA 01223",
    "addr:housenumber":"52",
    "addr:postcode":"01223",
    "addr:street":"Summit Hill Rd",
    "iso:country":"US",
    "sg:address":"52 Summit Hill Rd",
    "sg:city":"Washington",
    "sg:classifiers":[
        {
            "category":"Building & Trades",
            "subcategory":"Landscaping Services",
            "type":"Services"
        }
    ],
    "sg:phone":"+1 413 623 8989",
    "sg:postcode":"01223",
    "sg:province":"MA",
    "sg:tags":[
        "landscape",
        "contractor"
    ],
    "wof:name":"Always Growing Landscaping",
    "wof:placetype":"venue"
},
  "geometry": {"coordinates":[-73.116294,42.373315],"type":"Point"}
}