{
  "type": "Feature",
  "properties": {
    "addr:full": "16 Juniper St Ipswich MA 01938",
    "addr:housenumber": "16",
    "addr:postcode": "01938",
    "addr:street": "Juniper St",
    "iso:country": "US",
    "sg:address": "16 Juniper St",
    "sg:city": "Ipswich",
    "sg:classifiers": [
      {
        "category": "Organizations",
        "subcategory": "Membership Organization",
        "type": "Services"
      }
    ],
    "sg:phone": "+1   ",
    "sg:postcode": "01938",
    "sg:province": "MA",
    "wof:name": "Ipswich Partnership",
    "wof:placetype": "venue"
  },
  "geometry": {"coordinates":[-70.856261,42.673832],"type":"Point"}
}
