{
  "type": "Feature",
  "properties": {
    "addr:full":"46 Brentwood Cir Needham MA 02492",
    "addr:housenumber":"46",
    "addr:postcode":"02492",
    "addr:street":"Brentwood Cir",
    "iso:country":"US",
    "sg:address":"46 Brentwood Cir",
    "sg:city":"Needham",
    "sg:classifiers":[
        {
            "category":"Professional",
            "subcategory":"Management & Consulting",
            "type":"Services"
        }
    ],
    "sg:phone":"+1 781 453 0504",
    "sg:postcode":"02492",
    "sg:province":"MA",
    "sg:tags":[
        "consultant"
    ],
    "wof:name":"Rabin & Associates Corporate Consulting",
    "wof:placetype":"venue"
},
  "geometry": {"coordinates":[-71.24231,42.282046],"type":"Point"}
}