{
  "type": "Feature",
  "properties": {
    "addr:full": "155 Federal St Ste 1202 Boston MA 02110",
    "addr:housenumber": "155;1202",
    "addr:postcode": "02110",
    "addr:street": "Federal St Ste",
    "iso:country": "US",
    "sg:address": "155 Federal St Ste 1202",
    "sg:city": "Boston",
    "sg:classifiers": [
      {
        "category": "Professional",
        "subcategory": "Lawyer \u0026 Legal Services",
        "type": "Services"
      }
    ],
    "sg:phone": "+1 617 449 6020",
    "sg:postcode": "02110",
    "sg:province": "MA",
    "wof:name": "Adorno and Yoss Llc",
    "wof:placetype": "venue"
  },
  "geometry": {"coordinates":[-71.056407,42.354091],"type":"Point"}
}
