{
  "type": "Feature",
  "properties": {
    "iso:country":"US",
    "sg:address":"155 Federal St Ste 1202",
    "sg:city":"Boston",
    "sg:classifiers":[
        {
            "category":"Professional",
            "subcategory":"Lawyer & Legal Services",
            "type":"Services"
        }
    ],
    "sg:phone":"+1 617 449 6020",
    "sg:postcode":"02110",
    "sg:province":"MA",
    "wof:name":"Adorno and Yoss Llc",
    "wof:placetype":"venue"
},
  "geometry": {"coordinates":[-71.05640699999999,42.354091],"type":"Point"}
}