{
  "type": "Feature",
  "properties": {
    "iso:country":"US",
    "sg:address":"385 Geneva Ave",
    "sg:city":"Dorchester",
    "sg:classifiers":[
        {
            "category":"Food & Beverages",
            "subcategory":"Groceries & Convenience Stores",
            "type":"Retail Goods"
        }
    ],
    "sg:phone":"+1 617 436 8451",
    "sg:postcode":"02122",
    "sg:province":"MA",
    "sg:tags":[
        "grocer"
    ],
    "wof:name":"Fernandes Market",
    "wof:placetype":"venue"
},
  "geometry": {"coordinates":[-71.067497,42.301102],"type":"Point"}
}