{
  "type": "Feature",
  "properties": {
    "addr:full": "27 Henry Ave Pittsfield MA 01201",
    "addr:housenumber": "27",
    "addr:postcode": "01201",
    "addr:street": "Henry Ave",
    "iso:country": "US",
    "sg:address": "27 Henry Ave",
    "sg:city": "Pittsfield",
    "sg:classifiers": [
      {
        "category": "Professional",
        "subcategory": "Lawyer \u0026 Legal Services",
        "type": "Services"
      }
    ],
    "sg:phone": "+1 413 445 7750",
    "sg:postcode": "01201",
    "sg:province": "MA",
    "sg:tags": [
      "attorney"
    ],
    "wof:name": "Pellegrini Seeley Ryan",
    "wof:placetype": "venue"
  },
  "geometry": {"coordinates":[-73.256833,42.442968],"type":"Point"}
}
