{
  "type": "Feature",
  "properties": {
    "addr:full": "503 Waltham St Lexington MA 02421",
    "addr:housenumber": "503",
    "addr:postcode": "02421",
    "addr:street": "Waltham St",
    "iso:country": "US",
    "sg:address": "503 Waltham St",
    "sg:city": "Lexington",
    "sg:classifiers": [
      {
        "category": "Building \u0026 Trades",
        "subcategory": "Construction",
        "type": "Services"
      }
    ],
    "sg:phone": "+1 617 206 4231",
    "sg:postcode": "02421",
    "sg:province": "MA",
    "sg:tags": [
      "roofing",
      "contractor",
      "industrial",
      "contractors-commercial",
      "consultant"
    ],
    "sg:website": "http://baystateroofingcarpe.rtrk.com/?scid=1963713",
    "wof:name": "Local Roofing Contractors",
    "wof:placetype": "venue"
  },
  "geometry": {"coordinates":[-71.233451,42.432217],"type":"Point"}
}
