{
  "type": "Feature",
  "properties": {
    "iso:country":"US",
    "sg:address":"1 North St",
    "sg:city":"Southbridge",
    "sg:classifiers":[
        {
            "category":"Manufacturing",
            "subcategory":"Tools & Machinery",
            "type":"Manufacturing & Wholesale Goods"
        }
    ],
    "sg:phone":"+1 508 764 6011",
    "sg:postcode":"01550",
    "sg:province":"MA",
    "sg:tags":[
        "machine",
        "shop"
    ],
    "wof:name":"L & M Machine",
    "wof:placetype":"venue"
},
  "geometry": {"coordinates":[-72.03188299999999,42.076861],"type":"Point"}
}