{
  "type": "Feature",
  "properties": {
    "addr:full": "1 North St Southbridge MA 01550",
    "addr:housenumber": "1",
    "addr:postcode": "01550",
    "addr:street": "North St",
    "iso:country": "US",
    "sg:address": "1 North St",
    "sg:city": "Southbridge",
    "sg:classifiers": [
      {
        "category": "Manufacturing",
        "subcategory": "Tools \u0026 Machinery",
        "type": "Manufacturing \u0026 Wholesale Goods"
      }
    ],
    "sg:phone": "+1 508 764 6011",
    "sg:postcode": "01550",
    "sg:province": "MA",
    "sg:tags": [
      "machine",
      "shop"
    ],
    "wof:name": "L \u0026 M Machine",
    "wof:placetype": "venue"
  },
  "geometry": {"coordinates":[-72.031883,42.076861],"type":"Point"}
}
