{
  "type": "Feature",
  "properties": {
    "iso:country":"US",
    "sg:address":"425 Broadway",
    "sg:city":"Somerville",
    "sg:classifiers":[
        {
            "category":"Real Estate",
            "subcategory":"Real Estate Agent",
            "type":"Services"
        }
    ],
    "sg:phone":"+1 617 628 6449",
    "sg:postcode":"02145",
    "sg:province":"MA",
    "wof:name":"B F Realty",
    "wof:placetype":"venue"
},
  "geometry": {"coordinates":[-71.09993299999999,42.395891],"type":"Point"}
}