{
  "type": "Feature",
  "properties": {
    "iso:country":"US",
    "sg:address":"451 Quincy Ave",
    "sg:city":"Quincy",
    "sg:classifiers":[
        {
            "category":"Autos & Motor Vehicles",
            "subcategory":"Automobile Sales",
            "type":"Retail Goods"
        }
    ],
    "sg:phone":"+1 617 847 0077",
    "sg:postcode":"02169",
    "sg:province":"MA",
    "sg:tags":[
        "car",
        "dealer"
    ],
    "wof:name":"Quincy Auto Sales Inc",
    "wof:placetype":"venue"
},
  "geometry": {"coordinates":[-70.983784,42.238745],"type":"Point"}
}