{
  "type": "Feature",
  "properties": {
    "addr:full": "1295 Boylston St Boston MA 02215",
    "addr:housenumber": "1295",
    "addr:postcode": "02215",
    "addr:street": "Boylston St",
    "iso:country": "US",
    "sg:address": "1295 Boylston St",
    "sg:city": "Boston",
    "sg:classifiers": [
      {
        "category": "Professional",
        "type": "Services"
      }
    ],
    "sg:phone": "+1 617 536 0046",
    "sg:postcode": "02215",
    "sg:province": "MA",
    "sg:tags": [
      "establishment"
    ],
    "wof:name": "M \u0026 P Partners",
    "wof:placetype": "venue"
  },
  "geometry": {"coordinates":[-71.095588,42.345243],"type":"Point"}
}
