{
  "type": "Feature",
  "properties": {
    "iso:country":"US",
    "sg:address":"37 Cottage St",
    "sg:city":"Amherst",
    "sg:classifiers":[
        {
            "category":"Professional",
            "subcategory":"Management & Consulting",
            "type":"Services"
        }
    ],
    "sg:phone":"+1 413 549 1635",
    "sg:postcode":"01002",
    "sg:province":"MA",
    "sg:tags":[
        "consultant",
        "educational"
    ],
    "wof:name":"Alden & Assoc",
    "wof:placetype":"venue"
},
  "geometry": {"coordinates":[-72.517584,42.380517],"type":"Point"}
}