{
  "type": "Feature",
  "properties": {
    "addr:full":"50 Mill St Burlington MA 01803",
    "addr:housenumber":"50",
    "addr:postcode":"01803",
    "addr:street":"Mill St",
    "iso:country":"US",
    "sg:address":"50 Mill St",
    "sg:city":"Burlington",
    "sg:classifiers":[
        {
            "category":"Professional",
            "subcategory":"Management & Consulting",
            "type":"Services"
        }
    ],
    "sg:phone":"+1 781 272 2929",
    "sg:postcode":"01803",
    "sg:province":"MA",
    "sg:tags":[
        "consultant"
    ],
    "wof:name":"Bancrealty Advisors LLC",
    "wof:placetype":"venue"
},
  "geometry": {"coordinates":[-71.18882499999999,42.513456],"type":"Point"}
}