{
  "type": "Feature",
  "properties": {
    "addr:full":"542 Boston St Lynn MA 01905",
    "addr:housenumber":"542",
    "addr:postcode":"01905",
    "addr:street":"Boston St",
    "iso:country":"US",
    "sg:address":"542 Boston St",
    "sg:city":"Lynn",
    "sg:classifiers":[
        {
            "category":"Organizations",
            "subcategory":"Professional Association",
            "type":"Services"
        }
    ],
    "sg:phone":"+1 781 593 7815",
    "sg:postcode":"01905",
    "sg:province":"MA",
    "sg:tags":[
        "sales"
    ],
    "wof:name":"World Commerce",
    "wof:placetype":"venue"
},
  "geometry": {"coordinates":[-70.972904,42.464223],"type":"Point"}
}