{
  "type": "Feature",
  "properties": {
    "iso:country":"US",
    "sg:address":"37 Myrtle Ave",
    "sg:city":"Holyoke",
    "sg:classifiers":[
        {
            "category":"Restaurant",
            "type":"Food & Drink"
        }
    ],
    "sg:menulink":"http://www.allmenus.com/ma/holyoke/261540-tramore-chip-shop/menu/",
    "sg:phone":"+1 413 533 4319",
    "sg:postcode":"01040",
    "sg:province":"MA",
    "wof:name":"Tramore Chip Shop",
    "wof:placetype":"venue"
},
  "geometry": {"coordinates":[-72.628624,42.19368],"type":"Point"}
}