{
  "type": "Feature",
  "properties": {
    "iso:country":"US",
    "sg:address":"95 Congress St",
    "sg:city":"Salem",
    "sg:classifiers":[
        {
            "category":"Retail",
            "subcategory":"Laundry & Dry Cleaning",
            "type":"Services"
        }
    ],
    "sg:phone":"+1 978 744 3472",
    "sg:postcode":"01970",
    "sg:province":"MA",
    "wof:name":"B R Laundry",
    "wof:placetype":"venue"
},
  "geometry": {"coordinates":[-70.889269,42.516412],"type":"Point"}
}