{
  "type": "Feature",
  "properties": {
    "addr:full":"1449 State Hwy 132 Hyannis MA 02601",
    "addr:housenumber":"1449",
    "addr:postcode":"02601",
    "addr:street":"State Hwy 132",
    "iso:country":"US",
    "sg:address":"1449 State Hwy 132",
    "sg:city":"Hyannis",
    "sg:classifiers":[
        {
            "category":"Autos & Motor Vehicles",
            "subcategory":"Fuel & Gas Station",
            "type":"Retail Goods"
        }
    ],
    "sg:phone":"+1 508 362 5581",
    "sg:postcode":"02601",
    "sg:province":"MA",
    "sg:tags":[
        "oil"
    ],
    "wof:name":"Hyannis Mobil",
    "wof:placetype":"venue"
},
  "geometry": {"coordinates":[-70.31788,41.678488],"type":"Point"}
}