{
  "type": "Feature",
  "properties": {
    "iso:country":"US",
    "sg:address":"12 Garfield St",
    "sg:city":"South Dartmouth",
    "sg:classifiers":[
        {
            "category":"Building & Trades",
            "subcategory":"Construction",
            "type":"Services"
        }
    ],
    "sg:phone":"+1 508 997 7098",
    "sg:postcode":"02748",
    "sg:province":"MA",
    "sg:tags":[
        "painter"
    ],
    "wof:name":"Martins Painting & Home",
    "wof:placetype":"venue"
},
  "geometry": {"coordinates":[-70.941379,41.610238],"type":"Point"}
}