{
  "type": "Feature",
  "properties": {
    "addr:full":"100 High St Fl 15 Boston MA 02110",
    "addr:housenumber":"100;15",
    "addr:postcode":"02110",
    "addr:street":"High St Fl",
    "iso:country":"US",
    "sg:address":"100 High St Fl 15",
    "sg:city":"Boston",
    "sg:classifiers":[
        {
            "category":"Professional",
            "subcategory":"Lawyer & Legal Services",
            "type":"Services"
        }
    ],
    "sg:phone":"+1 617 951 8000",
    "sg:postcode":"02110",
    "sg:province":"MA",
    "sg:tags":[
        "attorney",
        "practice"
    ],
    "wof:name":"Bingham Sports Consulting",
    "wof:placetype":"venue"
},
  "geometry": {"coordinates":[-71.054581,42.354641],"type":"Point"}
}