{
  "type": "Feature",
  "properties": {
    "iso:country":"US",
    "sg:address":"6 Nehemiah Rd",
    "sg:city":"Shirley",
    "sg:classifiers":[
        {
            "category":"Personal",
            "subcategory":"Beauty Salon",
            "type":"Services"
        }
    ],
    "sg:phone":"+1 978 256 8038",
    "sg:postcode":"01464",
    "sg:province":"MA",
    "wof:name":"Hairs To You",
    "wof:placetype":"venue"
},
  "geometry": {"coordinates":[-71.638204,42.610083],"type":"Point"}
}