{
  "type": "Feature",
  "properties": {
    "addr:full": "6 Lakeville Business Park Lakeville MA 02347",
    "addr:housenumber": "6",
    "addr:postcode": "02347",
    "addr:street": "Business Park",
    "iso:country": "US",
    "sg:address": "6 Lakeville Business Park",
    "sg:city": "Lakeville",
    "sg:classifiers": [
      {
        "category": "Health Services",
        "subcategory": "Doctor",
        "type": "Services"
      },
      {
        "category": "Professional",
        "type": "Services"
      }
    ],
    "sg:phone": "+1 508 947 7558",
    "sg:postcode": "02347",
    "sg:province": "MA",
    "sg:tags": [
      "physician",
      "surgeon",
      "processing",
      "data"
    ],
    "sg:website": "http://www.healthcareadministrativeservices.com",
    "wof:name": "Healthcare Administrative Services",
    "wof:placetype": "venue"
  },
  "geometry": {"coordinates":[-70.955137,41.882754],"type":"Point"}
}
