{
  "type": "Feature",
  "properties": {
    "iso:country":"US",
    "sg:address":"270 Littleton Rd",
    "sg:city":"Westford",
    "sg:classifiers":[
        {
            "category":"Health Services",
            "subcategory":"Doctor",
            "type":"Services"
        }
    ],
    "sg:phone":"+1 978 392 9095",
    "sg:postcode":"01886",
    "sg:province":"MA",
    "sg:tags":[
        "surgeon",
        "oral"
    ],
    "wof:name":"Friedman Allen Oral Surg",
    "wof:placetype":"venue"
},
  "geometry": {"coordinates":[-71.42849699999999,42.586601],"type":"Point"}
}