{
  "type": "Feature",
  "properties": {
    "addr:full":"24 Billings Rd Quincy MA 02171",
    "addr:housenumber":"24",
    "addr:postcode":"02171",
    "addr:street":"Billings Rd",
    "iso:country":"US",
    "sg:address":"24 Billings Rd",
    "sg:city":"Quincy",
    "sg:classifiers":[
        {
            "category":"Restaurant",
            "type":"Food & Drink"
        }
    ],
    "sg:phone":"+1 617 770 9333",
    "sg:postcode":"02171",
    "sg:province":"MA",
    "sg:tags":[
        "delicatessen"
    ],
    "wof:name":"Saigon Corner",
    "wof:placetype":"venue"
},
  "geometry": {"coordinates":[-71.02583799999999,42.273238],"type":"Point"}
}