{
  "type": "Feature",
  "properties": {
    "addr:full":"2 Park St Dorchester MA 02122",
    "addr:housenumber":"2",
    "addr:postcode":"02122",
    "addr:street":"Park St",
    "iso:country":"US",
    "sg:address":"2 Park St",
    "sg:city":"Dorchester",
    "sg:classifiers":[
        {
            "category":"Professional",
            "subcategory":"Engineering",
            "type":"Services"
        }
    ],
    "sg:phone":"+1 617 288 3969",
    "sg:postcode":"02122",
    "sg:province":"MA",
    "sg:tags":[
        "engineer"
    ],
    "wof:name":"Engineering Advantage Inc",
    "wof:placetype":"venue"
},
  "geometry": {"coordinates":[-71.053528,42.302029],"type":"Point"}
}