{
  "type": "Feature",
  "properties": {
    "addr:full":"101 Binney St Cambridge MA 02142",
    "addr:housenumber":"101",
    "addr:postcode":"02142",
    "addr:street":"Binney St",
    "iso:country":"US",
    "sg:address":"101 Binney St",
    "sg:city":"Cambridge",
    "sg:classifiers":[
        {
            "category":"Wholesale",
            "subcategory":"Drugs",
            "type":"Manufacturing & Wholesale Goods"
        }
    ],
    "sg:phone":"+1 617 491 0771",
    "sg:postcode":"02142",
    "sg:province":"MA",
    "sg:tags":[
        "pharmaceutical",
        "product"
    ],
    "sg:website":"www.merrimackpharma.com",
    "wof:name":"Merrimack Pharmaceuticals",
    "wof:placetype":"venue"
},
  "geometry": {"coordinates":[-71.081459,42.36572],"type":"Point"}
}