{
  "type": "Feature",
  "properties": {
    "iso:country":"US",
    "sg:address":"6 Barstow Ln",
    "sg:city":"Rockland",
    "sg:phone":"+1 781 982 5554",
    "sg:postcode":"02370",
    "sg:province":"MA",
    "sg:tags":[
        "oil"
    ],
    "wof:name":"De Palma Oil",
    "wof:placetype":"venue"
},
  "geometry": {"coordinates":[-70.904618,42.096989],"type":"Point"}
}