{
  "type": "Feature",
  "properties": {
    "addr:full": "30 Western Ave Gloucester MA 01930",
    "addr:housenumber": "30",
    "addr:postcode": "01930",
    "addr:street": "Western Ave",
    "iso:country": "US",
    "sg:address": "30 Western Ave",
    "sg:city": "Gloucester",
    "sg:classifiers": [
      {
        "category": "Banks \u0026 Credit Unions",
        "subcategory": "Investment Brokerage",
        "type": "Services"
      }
    ],
    "sg:phone": "+1 978 281 5555",
    "sg:postcode": "01930",
    "sg:province": "MA",
    "sg:tags": [
      "security"
    ],
    "wof:name": "American Investment Svc",
    "wof:placetype": "venue"
  },
  "geometry": {"coordinates":[-70.66823,42.610303],"type":"Point"}
}
