{
  "type": "Feature",
  "properties": {
    "addr:full": "9 Norton Rd West Yarmouth MA 02673",
    "addr:housenumber": "9",
    "addr:postcode": "02673",
    "addr:street": "Norton Rd",
    "iso:country": "US",
    "sg:address": "9 Norton Rd",
    "sg:city": "West Yarmouth",
    "sg:classifiers": [
      {
        "category": "Building \u0026 Trades",
        "subcategory": "Cleaning \u0026 Sanitation",
        "type": "Services"
      }
    ],
    "sg:phone": "+1   ",
    "sg:postcode": "02673",
    "sg:province": "MA",
    "sg:tags": [
      "maintenance"
    ],
    "wof:name": "TLC Cleaning Service",
    "wof:placetype": "venue"
  },
  "geometry": {"coordinates":[-70.233499,41.660102],"type":"Point"}
}
