{
  "type": "Feature",
  "properties": {
    "iso:country":"US",
    "sg:address":"9 Norton Rd",
    "sg:city":"West Yarmouth",
    "sg:classifiers":[
        {
            "category":"Building & Trades",
            "subcategory":"Cleaning & Sanitation",
            "type":"Services"
        }
    ],
    "sg:phone":"+1   ",
    "sg:postcode":"02673",
    "sg:province":"MA",
    "sg:tags":[
        "maintenance"
    ],
    "wof:name":"TLC Cleaning Service",
    "wof:placetype":"venue"
},
  "geometry": {"coordinates":[-70.23349899999999,41.660102],"type":"Point"}
}