{
  "type": "Feature",
  "properties": {
    "iso:country":"US",
    "sg:address":"720 Atlantic Ave",
    "sg:city":"Boston",
    "sg:classifiers":[
        {
            "category":"Shopping",
            "subcategory":"Jewelry",
            "type":"Retail Goods"
        }
    ],
    "sg:phone":"+1 617 345 8015",
    "sg:postcode":"02111",
    "sg:province":"MA",
    "wof:name":"Boston Ring & Gem",
    "wof:placetype":"venue"
},
  "geometry": {"coordinates":[-71.056297,42.350399],"type":"Point"}
}