{
  "type": "Feature",
  "properties": {
    "addr:full": "31 Michael Rd Dedham MA 02026",
    "addr:housenumber": "31",
    "addr:postcode": "02026",
    "addr:street": "Michael Rd",
    "iso:country": "US",
    "sg:address": "31 Michael Rd",
    "sg:city": "Dedham",
    "sg:classifiers": [
      {
        "category": "Banks \u0026 Credit Unions",
        "subcategory": "Bank",
        "type": "Services"
      }
    ],
    "sg:phone": "+1 781 329 6025",
    "sg:postcode": "02026",
    "sg:province": "MA",
    "sg:tags": [
      "loan",
      "real estate"
    ],
    "wof:name": "Accessible Funding Group",
    "wof:placetype": "venue"
  },
  "geometry": {"coordinates":[-71.166958,42.240478],"type":"Point"}
}
