{
  "type": "Feature",
  "properties": {
    "addr:full": "138 Franklin St Quincy MA 02169",
    "addr:housenumber": "138",
    "addr:postcode": "02169",
    "addr:street": "Franklin St",
    "iso:country": "US",
    "sg:address": "138 Franklin St",
    "sg:city": "Quincy",
    "sg:classifiers": [
      {
        "category": "Banks \u0026 Credit Unions",
        "subcategory": "Bank",
        "type": "Services"
      }
    ],
    "sg:phone": "+1 781 337 3000",
    "sg:postcode": "02169",
    "sg:province": "MA",
    "wof:name": "South Shore Savings Bank",
    "wof:placetype": "venue"
  },
  "geometry": {"coordinates":[-71.003183,42.239233],"type":"Point"}
}
