{
  "type": "Feature",
  "properties": {
    "iso:country":"US",
    "sg:address":"138 Franklin St",
    "sg:city":"Quincy",
    "sg:classifiers":[
        {
            "category":"Banks & Credit Unions",
            "subcategory":"Bank",
            "type":"Services"
        }
    ],
    "sg:phone":"+1 781 337 3000",
    "sg:postcode":"02169",
    "sg:province":"MA",
    "wof:name":"South Shore Savings Bank",
    "wof:placetype":"venue"
},
  "geometry": {"coordinates":[-71.00318300000001,42.239233],"type":"Point"}
}