{
  "type": "Feature",
  "properties": {
    "iso:country":"US",
    "sg:address":"175 Mansfield Ave Ste B",
    "sg:city":"Norton",
    "sg:classifiers":[
        {
            "category":"Professional",
            "subcategory":"Lawyer & Legal Services",
            "type":"Services"
        }
    ],
    "sg:phone":"+1 508 285 1930",
    "sg:postcode":"02766",
    "sg:province":"MA",
    "sg:tags":[
        "notary"
    ],
    "sg:website":"www.postalcenterusa.com",
    "wof:name":"Postal Center USA",
    "wof:placetype":"venue"
},
  "geometry": {"coordinates":[-71.20927,41.981005],"type":"Point"}
}