{
  "type": "Feature",
  "properties": {
    "iso:country":"US",
    "sg:address":"1453 Dorchester Ave",
    "sg:city":"Boston",
    "sg:classifiers":[
        {
            "category":"Professional",
            "subcategory":"Management & Consulting",
            "type":"Services"
        }
    ],
    "sg:phone":"+1   ",
    "sg:postcode":"02122",
    "sg:province":"MA",
    "sg:tags":[
        "real estate"
    ],
    "wof:name":"Avenue Realty",
    "wof:placetype":"venue"
},
  "geometry": {"coordinates":[-71.059997,42.301242],"type":"Point"}
}