{
  "type": "Feature",
  "properties": {
    "addr:full": "1111 Federal St Belchertown MA 01007",
    "addr:housenumber": "1111",
    "addr:postcode": "01007",
    "addr:street": "Federal St",
    "iso:country": "US",
    "sg:address": "1111 Federal St",
    "sg:city": "Belchertown",
    "sg:classifiers": [
      {
        "category": "Professional",
        "subcategory": "Engineering",
        "type": "Services"
      }
    ],
    "sg:phone": "+1 413 256 3400",
    "sg:postcode": "01007",
    "sg:province": "MA",
    "sg:tags": [
      "engineer"
    ],
    "wof:name": "Amherst Civil Engineering",
    "wof:placetype": "venue"
  },
  "geometry": {"coordinates":[-72.458664,42.340748],"type":"Point"}
}
