{
  "type": "Feature",
  "properties": {
    "addr:full": "182 Massachusetts Ave Cambridge MA 02139",
    "addr:housenumber": "182",
    "addr:postcode": "02139",
    "addr:street": "Massachusetts Ave",
    "iso:country": "US",
    "sg:address": "182 Massachusetts Ave",
    "sg:city": "Cambridge",
    "sg:classifiers": [
      {
        "category": "Shopping",
        "subcategory": "Used Merchandise",
        "type": "Retail Goods"
      }
    ],
    "sg:phone": "+1 617 547 4424",
    "sg:postcode": "02139",
    "sg:province": "MA",
    "sg:tags": [
      "antique"
    ],
    "wof:name": "Sadye \u0026 Co",
    "wof:placetype": "venue"
  },
  "geometry": {"coordinates":[-71.0965,42.361012],"type":"Point"}
}
