{
  "type": "Feature",
  "properties": {
    "addr:full": "44 Binney St Boston MA 02115",
    "addr:housenumber": "44",
    "addr:postcode": "02115",
    "addr:street": "Binney St",
    "iso:country": "US",
    "sg:address": "44 Binney St",
    "sg:city": "Boston",
    "sg:classifiers": [
      {
        "category": "Health Services",
        "subcategory": "Doctor",
        "type": "Services"
      }
    ],
    "sg:phone": "+1 617 632 3000",
    "sg:postcode": "02115",
    "sg:province": "MA",
    "sg:tags": [
      "traditional",
      "physician",
      "american",
      "surgeon",
      "hospital"
    ],
    "sg:website": "www.dana-farber.org",
    "wof:name": "Dana-Farber Cancer Institute",
    "wof:placetype": "venue"
  },
  "geometry": {"coordinates":[-71.107249,42.337896],"type":"Point"}
}
