{
  "type": "Feature",
  "properties": {
    "addr:full":"109 Tosca Dr Stoughton MA 02072",
    "addr:housenumber":"109",
    "addr:postcode":"02072",
    "addr:street":"Tosca Dr",
    "iso:country":"US",
    "sg:address":"109 Tosca Dr",
    "sg:city":"Stoughton",
    "sg:classifiers":[
        {
            "category":"Wholesale",
            "subcategory":"Apparel",
            "type":"Manufacturing & Wholesale Goods"
        }
    ],
    "sg:phone":"+1 781 297 2088",
    "sg:postcode":"02072",
    "sg:province":"MA",
    "sg:tags":[
        "shoes"
    ],
    "wof:name":"East Coast Athletics",
    "wof:placetype":"venue"
},
  "geometry": {"coordinates":[-71.125242,42.133606],"type":"Point"}
}