{
  "type": "Feature",
  "properties": {
    "addr:full": "40 Broad St Boston MA 02109",
    "addr:housenumber": "40",
    "addr:postcode": "02109",
    "addr:street": "Broad St",
    "iso:country": "US",
    "sg:address": "40 Broad St",
    "sg:city": "Boston",
    "sg:classifiers": [
      {
        "category": "Professional",
        "subcategory": "Lawyer \u0026 Legal Services",
        "type": "Services"
      }
    ],
    "sg:phone": "+1 617 350 6800",
    "sg:postcode": "02109",
    "sg:province": "MA",
    "wof:name": "Sachs Jeffrey",
    "wof:placetype": "venue"
  },
  "geometry": {"coordinates":[-71.054199,42.358398],"type":"Point"}
}
