{
  "type": "Feature",
  "properties": {
    "addr:full": "36 Winn St Burlington MA 01803",
    "addr:housenumber": "36",
    "addr:postcode": "01803",
    "addr:street": "Winn St",
    "iso:country": "US",
    "sg:address": "36 Winn St",
    "sg:city": "Burlington",
    "sg:classifiers": [
      {
        "category": "Personal",
        "subcategory": "Beauty Salon",
        "type": "Services"
      }
    ],
    "sg:phone": "+1 781 229 1608",
    "sg:postcode": "01803",
    "sg:province": "MA",
    "wof:name": "Sharper Image Hairstylist",
    "wof:placetype": "venue"
  },
  "geometry": {"coordinates":[-71.172859,42.49028],"type":"Point"}
}
