{
  "type": "Feature",
  "properties": {
    "addr:full": "186 Alewife Brook Pkwy Cambridge MA 02138",
    "addr:housenumber": "186",
    "addr:postcode": "02138",
    "addr:street": "Alewife Brook Pkwy",
    "iso:country": "US",
    "sg:address": "186 Alewife Brook Pkwy",
    "sg:city": "Cambridge",
    "sg:classifiers": [
      {
        "category": "Professional",
        "subcategory": "Lawyer \u0026 Legal Services",
        "type": "Services"
      }
    ],
    "sg:phone": "+1 617 492 4242",
    "sg:postcode": "02138",
    "sg:province": "MA",
    "wof:name": "Walsh Richard D Lwyr",
    "wof:placetype": "venue"
  },
  "geometry": {"coordinates":[-71.141098,42.391701],"type":"Point"}
}
