{
  "type": "Feature",
  "properties": {
    "addr:full": "260 Beacon Street Somerville MA 02143",
    "addr:housenumber": "260",
    "addr:postcode": "02143",
    "addr:street": "Beacon Street",
    "iso:country": "US",
    "sg:address": "260 Beacon Street",
    "sg:city": "Somerville",
    "sg:classifiers": [
      {
        "category": "Sports \u0026 Exercise",
        "subcategory": "Gym",
        "type": "Entertainment"
      }
    ],
    "sg:phone": "+1 617 864 0941",
    "sg:postcode": "02143",
    "sg:province": "MA",
    "sg:tags": [
      "trainer"
    ],
    "wof:name": "North Charles Foundation",
    "wof:placetype": "venue"
  },
  "geometry": {"coordinates":[-71.112041,42.383004],"type":"Point"}
}
