{
  "type": "Feature",
  "properties": {
    "addr:full": "115 Pilgrim Rd Braintree MA 02184",
    "addr:housenumber": "115",
    "addr:postcode": "02184",
    "addr:street": "Pilgrim Rd",
    "iso:country": "US",
    "sg:address": "115 Pilgrim Rd",
    "sg:city": "Braintree",
    "sg:classifiers": [
      {
        "category": "Professional",
        "type": "Services"
      }
    ],
    "sg:phone": "+1 781 849 0006",
    "sg:postcode": "02184",
    "sg:province": "MA",
    "sg:tags": [
      "establishment"
    ],
    "wof:name": "Arundel Associates",
    "wof:placetype": "venue"
  },
  "geometry": {"coordinates":[-70.975203,42.212831],"type":"Point"}
}
