{
  "type": "Feature",
  "properties": {
    "iso:country":"US",
    "sg:address":"1 International Place",
    "sg:city":"Boston",
    "sg:classifiers":[
        {
            "category":"Banks & Credit Unions",
            "subcategory":"Investment Brokerage",
            "type":"Services"
        }
    ],
    "sg:phone":"+1 617 261 9981",
    "sg:postcode":"02110",
    "sg:province":"MA",
    "sg:tags":[
        "investing"
    ],
    "wof:name":"Singapore Economic Development Board",
    "wof:placetype":"venue"
},
  "geometry": {"coordinates":[-71.05258000000001,42.35628],"type":"Point"}
}