{
  "type": "Feature",
  "properties": {
    "iso:country":"US",
    "sg:address":"3 Belcher St",
    "sg:city":"Plainville",
    "sg:classifiers":[
        {
            "category":"Professional",
            "type":"Services"
        }
    ],
    "sg:phone":"+1 508 643 2920",
    "sg:postcode":"02762",
    "sg:province":"MA",
    "sg:tags":[
        "establishment"
    ],
    "wof:name":"Edgewood Development Co LLC",
    "wof:placetype":"venue"
},
  "geometry": {"coordinates":[-71.30010299999999,42.039297],"type":"Point"}
}