{
  "type": "Feature",
  "properties": {
    "addr:full": "33 Richdale Ave Cambridge MA 02140",
    "addr:housenumber": "33",
    "addr:postcode": "02140",
    "addr:street": "Richdale Ave",
    "iso:country": "US",
    "sg:address": "33 Richdale Ave",
    "sg:city": "Cambridge",
    "sg:classifiers": [
      {
        "category": "Organizations",
        "subcategory": "Professional Association",
        "type": "Services"
      }
    ],
    "sg:phone": "+1 617 497 8366",
    "sg:postcode": "02140",
    "sg:province": "MA",
    "sg:tags": [
      "agency",
      "bureau",
      "entertainment"
    ],
    "sg:website": "http://www.developingartist.com",
    "wof:name": "Developing Artist",
    "wof:placetype": "venue"
  },
  "geometry": {"coordinates":[-71.122299,42.388371],"type":"Point"}
}
