{
  "type": "Feature",
  "properties": {
    "iso:country":"US",
    "sg:address":"11 Robert St",
    "sg:city":"Attleboro",
    "sg:classifiers":[
        {
            "category":"Health Services",
            "subcategory":"Chiropractor",
            "type":"Services"
        }
    ],
    "sg:phone":"+1 508 226 2333",
    "sg:postcode":"02703",
    "sg:province":"MA",
    "sg:website":"www.millerchiro.net",
    "wof:name":"Miller Chiropractic Health Center",
    "wof:placetype":"venue"
},
  "geometry": {"coordinates":[-71.291067,41.938406],"type":"Point"}
}