{
  "type": "Feature",
  "properties": {
    "iso:country":"US",
    "sg:address":"100 Highland Ave",
    "sg:city":"Salem",
    "sg:phone":"+1 978 607 0093",
    "sg:postcode":"01970",
    "sg:province":"MA",
    "sg:website":"http://www.highlanddentalgroup.com",
    "wof:name":"Highland Dental Group",
    "wof:placetype":"venue"
},
  "geometry": {"coordinates":[-70.909538,42.511015],"type":"Point"}
}