{
  "type": "Feature",
  "properties": {
    "addr:full": "100 Highland Ave Salem MA 01970",
    "addr:housenumber": "100",
    "addr:postcode": "01970",
    "addr:street": "Highland Ave",
    "iso:country": "US",
    "ovtr:label": "Highland Dental Group, 100 Highland Ave Salem MA US",
    "ovtr:similarity": 2.599216938018799,
    "sg:address": "100 Highland Ave",
    "sg:city": "Salem",
    "sg:phone": "+1 978 607 0093",
    "sg:postcode": "01970",
    "sg:province": "MA",
    "sg:website": "http://www.highlanddentalgroup.com",
    "wof:name": "Highland Dental Group",
    "wof:placetype": "venue"
  },
  "geometry": {"coordinates":[-70.909538,42.511015],"type":"Point"}
}
