{
  "type": "Feature",
  "properties": {
    "addr:full": "14 Marshfield Ave Humarock MA 02047",
    "addr:housenumber": "14",
    "addr:postcode": "02047",
    "addr:street": "Marshfield Ave",
    "iso:country": "US",
    "sg:address": "14 Marshfield Ave",
    "sg:city": "Humarock",
    "sg:classifiers": [
      {
        "category": "Restaurant",
        "type": "Food \u0026 Drink"
      }
    ],
    "sg:phone": "+1 781 319 0430",
    "sg:postcode": "02047",
    "sg:province": "MA",
    "sg:tags": [
      "cafe"
    ],
    "wof:name": "Sands End Cafe",
    "wof:placetype": "venue"
  },
  "geometry": {"coordinates":[-70.690142,42.138759],"type":"Point"}
}
