{
  "type": "Feature",
  "properties": {
    "iso:country":"US",
    "sg:address":"14 Marshfield Ave",
    "sg:city":"Humarock",
    "sg:classifiers":[
        {
            "category":"Restaurant",
            "type":"Food & Drink"
        }
    ],
    "sg:phone":"+1 781 319 0430",
    "sg:postcode":"02047",
    "sg:province":"MA",
    "sg:tags":[
        "cafe"
    ],
    "wof:name":"Sands End Cafe",
    "wof:placetype":"venue"
},
  "geometry": {"coordinates":[-70.69014199999999,42.138759],"type":"Point"}
}