{
  "type": "Feature",
  "properties": {
    "addr:full": "967 Saratoga Street Boston MA 02128",
    "addr:housenumber": "967",
    "addr:postcode": "02128",
    "addr:street": "Saratoga Street",
    "iso:country": "US",
    "sg:address": "967 Saratoga Street",
    "sg:city": "Boston",
    "sg:classifiers": [
      {
        "category": "Sports \u0026 Exercise",
        "subcategory": "Gym",
        "type": "Entertainment"
      },
      {
        "category": "Health Services",
        "subcategory": "Dentist",
        "type": "Services"
      }
    ],
    "sg:phone": "+1 617 569 2761",
    "sg:postcode": "02128",
    "sg:province": "MA",
    "sg:tags": [
      "trainer"
    ],
    "wof:name": "Khrkhryan Aleksander Dent",
    "wof:placetype": "venue"
  },
  "geometry": {"coordinates":[-71.008168,42.386902],"type":"Point"}
}
