{
  "type": "Feature",
  "properties": {
    "addr:full":"15 Garfield Ave Somerville MA 02145",
    "addr:housenumber":"15",
    "addr:postcode":"02145",
    "addr:street":"Garfield Ave",
    "iso:country":"US",
    "sg:address":"15 Garfield Ave",
    "sg:city":"Somerville",
    "sg:classifiers":[
        {
            "category":"Food & Beverages",
            "subcategory":"Chocolate",
            "type":"Retail Goods"
        }
    ],
    "sg:phone":"+1 617 625 3721",
    "sg:postcode":"02145",
    "sg:province":"MA",
    "sg:tags":[
        "processor",
        "canners"
    ],
    "sg:website":"http://www.pillsbury.com",
    "wof:name":"Pillsbury",
    "wof:placetype":"venue"
},
  "geometry": {"coordinates":[-71.08650900000001,42.389239],"type":"Point"}
}