{
  "type": "Feature",
  "properties": {
    "iso:country":"US",
    "sg:address":"62 Main St",
    "sg:city":"Lakeville",
    "sg:classifiers":[
        {
            "category":"Insurance",
            "subcategory":"Insurance Agent",
            "type":"Services"
        }
    ],
    "sg:phone":"+1 508 946 1166",
    "sg:postcode":"02347",
    "sg:province":"MA",
    "wof:name":"Piasecki & Assoc",
    "wof:placetype":"venue"
},
  "geometry": {"coordinates":[-70.93012,41.87166],"type":"Point"}
}