{
  "type": "Feature",
  "properties": {
    "addr:full": "77 Elizabeth Rd Belmont MA 02478",
    "addr:housenumber": "77",
    "addr:postcode": "02478",
    "addr:street": "Elizabeth Rd",
    "iso:country": "US",
    "sg:address": "77 Elizabeth Rd",
    "sg:city": "Belmont",
    "sg:classifiers": [
      {
        "category": "Professional",
        "type": "Services"
      }
    ],
    "sg:phone": "+1   ",
    "sg:postcode": "02478",
    "sg:province": "MA",
    "wof:name": "Citeline Inc",
    "wof:placetype": "venue"
  },
  "geometry": {"coordinates":[-71.165293,42.382884],"type":"Point"}
}
