{
  "type": "Feature",
  "properties": {
    "addr:full": "10 Ballard Rd Lawrence MA 01843",
    "addr:housenumber": "10",
    "addr:postcode": "01843",
    "addr:street": "Ballard Rd",
    "iso:country": "US",
    "sg:address": "10 Ballard Rd",
    "sg:city": "Lawrence",
    "sg:classifiers": [
      {
        "category": "Manufacturing",
        "subcategory": "Tools \u0026 Machinery",
        "type": "Manufacturing \u0026 Wholesale Goods"
      }
    ],
    "sg:phone": "+1 978 682 6300",
    "sg:postcode": "01843",
    "sg:province": "MA",
    "sg:tags": [
      "industrial",
      "truck"
    ],
    "wof:name": "Brodie Toyota-Lift",
    "wof:placetype": "venue"
  },
  "geometry": {"coordinates":[-71.185853,42.686405],"type":"Point"}
}
