{
  "type": "Feature",
  "properties": {
    "iso:country":"US",
    "sg:address":"10 Ballard Rd",
    "sg:city":"Lawrence",
    "sg:classifiers":[
        {
            "category":"Manufacturing",
            "subcategory":"Tools & Machinery",
            "type":"Manufacturing & Wholesale Goods"
        }
    ],
    "sg:phone":"+1 978 682 6300",
    "sg:postcode":"01843",
    "sg:province":"MA",
    "sg:tags":[
        "industrial",
        "truck"
    ],
    "wof:name":"Brodie Toyota-Lift",
    "wof:placetype":"venue"
},
  "geometry": {"coordinates":[-71.18585299999999,42.686405],"type":"Point"}
}