{
  "type": "Feature",
  "properties": {
    "addr:full":"1353 Dwight St Holyoke MA 01040",
    "addr:housenumber":"1353",
    "addr:postcode":"01040",
    "addr:street":"Dwight St",
    "iso:country":"US",
    "sg:address":"1353 Dwight St",
    "sg:city":"Holyoke",
    "sg:classifiers":[
        {
            "category":"Personal",
            "subcategory":"Beauty Salon",
            "type":"Services"
        }
    ],
    "sg:phone":"+1 413 533 0307",
    "sg:postcode":"01040",
    "sg:province":"MA",
    "wof:name":"Margot's Hair Fashions",
    "wof:placetype":"venue"
},
  "geometry": {"coordinates":[-72.624546,42.210985],"type":"Point"}
}