{
  "type": "Feature",
  "properties": {
    "iso:country":"US",
    "sg:address":"200 Wheeler Rd Ste 2",
    "sg:city":"Burlington",
    "sg:classifiers":[
        {
            "category":"Banks & Credit Unions",
            "subcategory":"Investment Brokerage",
            "type":"Services"
        }
    ],
    "sg:phone":"+1 781 494 4000",
    "sg:postcode":"01803",
    "sg:province":"MA",
    "sg:tags":[
        "investing"
    ],
    "wof:name":"Tambone Investment Group",
    "wof:placetype":"venue"
},
  "geometry": {"coordinates":[-71.215642,42.476406],"type":"Point"}
}