{
  "type": "Feature",
  "properties": {
    "addr:full":"146 Lowell St Wakefield MA 01880",
    "addr:housenumber":"146",
    "addr:postcode":"01880",
    "addr:street":"Lowell St",
    "iso:country":"US",
    "sg:address":"146 Lowell St",
    "sg:city":"Wakefield",
    "sg:classifiers":[
        {
            "category":"Personal",
            "subcategory":"Beauty Salon",
            "type":"Services"
        }
    ],
    "sg:phone":"+1 781 245 0455",
    "sg:postcode":"01880",
    "sg:province":"MA",
    "wof:name":"AJA The Art & Sci-Hair Dsgn",
    "wof:placetype":"venue"
},
  "geometry": {"coordinates":[-71.079554,42.523883],"type":"Point"}
}