{
  "type": "Feature",
  "properties": {
    "iso:country":"US",
    "sg:address":"32 E Falmouth Hwy",
    "sg:city":"East Falmouth",
    "sg:classifiers":[
        {
            "category":"Professional",
            "type":"Services"
        }
    ],
    "sg:phone":"+1   ",
    "sg:postcode":"02536",
    "sg:province":"MA",
    "wof:name":"George Bronstein",
    "wof:placetype":"venue"
},
  "geometry": {"coordinates":[-70.572524,41.578335],"type":"Point"}
}