{
  "type": "Feature",
  "properties": {
    "addr:full": "191 Main St Ste 106 Wareham MA 02571",
    "addr:housenumber": "191",
    "addr:postcode": "02571",
    "addr:street": "Main St Ste 106",
    "iso:country": "US",
    "sg:address": "191 Main St Ste 106",
    "sg:city": "Wareham",
    "sg:classifiers": [
      {
        "category": "Professional",
        "type": "Services"
      }
    ],
    "sg:phone": "+1 508 295 0005",
    "sg:postcode": "02571",
    "sg:province": "MA",
    "sg:website": "www.ghdunn.com",
    "wof:name": "Dunn G H Insurance Agcy Inc",
    "wof:placetype": "venue"
  },
  "geometry": {"coordinates":[-70.716797,41.759399],"type":"Point"}
}
