{
  "type": "Feature",
  "properties": {
    "addr:full": "4286 Washington St Roslindale MA 02131",
    "addr:housenumber": "4286",
    "addr:postcode": "02131",
    "addr:street": "Washington St",
    "iso:country": "US",
    "sg:address": "4286 Washington St",
    "sg:city": "Roslindale",
    "sg:classifiers": [
      {
        "category": "Shopping",
        "subcategory": "Books",
        "type": "Retail Goods"
      }
    ],
    "sg:phone": "+1 617 325 3580",
    "sg:postcode": "02131",
    "sg:province": "MA",
    "sg:tags": [
      "dealer"
    ],
    "wof:name": "Christian Science Reading",
    "wof:placetype": "venue"
  },
  "geometry": {"coordinates":[-71.130178,42.284487],"type":"Point"}
}
