{
  "type": "Feature",
  "properties": {
    "iso:country":"US",
    "sg:address":"2 Gill St",
    "sg:city":"Woburn",
    "sg:classifiers":[
        {
            "category":"Professional",
            "subcategory":"Management & Consulting",
            "type":"Services"
        }
    ],
    "sg:phone":"+1 781 935 3888",
    "sg:postcode":"01801",
    "sg:province":"MA",
    "sg:tags":[
        "marketing",
        "consultant"
    ],
    "sg:website":"www.gqimports.com",
    "wof:name":"G Q Imports",
    "wof:placetype":"venue"
},
  "geometry": {"coordinates":[-71.146967,42.509679],"type":"Point"}
}