{
  "type": "Feature",
  "properties": {
    "addr:full": "2 Gill St Woburn MA 01801",
    "addr:housenumber": "2",
    "addr:postcode": "01801",
    "addr:street": "Gill St",
    "iso:country": "US",
    "sg:address": "2 Gill St",
    "sg:city": "Woburn",
    "sg:classifiers": [
      {
        "category": "Professional",
        "subcategory": "Management \u0026 Consulting",
        "type": "Services"
      }
    ],
    "sg:phone": "+1 781 935 3888",
    "sg:postcode": "01801",
    "sg:province": "MA",
    "sg:tags": [
      "marketing",
      "consultant"
    ],
    "sg:website": "www.gqimports.com",
    "wof:name": "G Q Imports",
    "wof:placetype": "venue"
  },
  "geometry": {"coordinates":[-71.146967,42.509679],"type":"Point"}
}
