{
  "type": "Feature",
  "properties": {
    "addr:full":"535 State Hwy 6 Alt North Truro MA 02652",
    "addr:housenumber":"535",
    "addr:postcode":"02652",
    "addr:street":"State Hwy 6",
    "iso:country":"US",
    "sg:address":"535 State Hwy 6 Alt",
    "sg:city":"North Truro",
    "sg:classifiers":[
        {
            "category":"Restaurant",
            "type":"Food & Drink"
        }
    ],
    "sg:phone":"+1 508 487 4360",
    "sg:postcode":"02652",
    "sg:province":"MA",
    "wof:name":"Adrian's Restaurant",
    "wof:placetype":"venue"
},
  "geometry": {"coordinates":[-70.08866999999999,42.040219],"type":"Point"}
}