{
  "type": "Feature",
  "properties": {
    "iso:country":"US",
    "sg:address":"221 N Main St",
    "sg:city":"North Brookfield",
    "sg:classifiers":[
        {
            "category":"Food & Beverages",
            "subcategory":"Liquor & Beverages",
            "type":"Retail Goods"
        }
    ],
    "sg:phone":"+1 508 867 6709",
    "sg:postcode":"01535",
    "sg:province":"MA",
    "wof:name":"Algoo's Package Store Inc",
    "wof:placetype":"venue"
},
  "geometry": {"coordinates":[-72.08561400000001,42.270045],"type":"Point"}
}