{
  "type": "Feature",
  "properties": {
    "iso:country":"US",
    "sg:address":"1264 Parker St",
    "sg:city":"Springfield",
    "sg:classifiers":[
        {
            "category":"Social Services",
            "subcategory":"Child Care",
            "type":"Services"
        }
    ],
    "sg:phone":"+1 413 782 0409",
    "sg:postcode":"01129",
    "sg:province":"MA",
    "wof:name":"Quality Time Child Care",
    "wof:placetype":"venue"
},
  "geometry": {"coordinates":[-72.49914,42.11244],"type":"Point"}
}