{
  "type": "Feature",
  "properties": {
    "iso:country":"US",
    "sg:address":"155 Bay State Dr",
    "sg:city":"Braintree",
    "sg:classifiers":[
        {
            "category":"Home & Garden",
            "subcategory":"Furniture",
            "type":"Retail Goods"
        },
        {
            "category":"Building & Trades",
            "subcategory":"Construction",
            "type":"Services"
        },
        {
            "category":"Manufacturing",
            "subcategory":"Building Materials",
            "type":"Manufacturing & Wholesale Goods"
        },
        {
            "category":"Wholesale",
            "subcategory":"Home Furnishings",
            "type":"Manufacturing & Wholesale Goods"
        }
    ],
    "sg:phone":"+1 781 843 8882",
    "sg:postcode":"02184",
    "sg:province":"MA",
    "sg:tags":[
        "industrial",
        "equipment-wholesale",
        "cabinetmakers-commercial",
        "kitchen",
        "equipment-household",
        "cabinet",
        "maker",
        "manufacturer"
    ],
    "wof:name":"Aisen Cabinetry",
    "wof:placetype":"venue"
},
  "geometry": {"coordinates":[-71.027112,42.19996],"type":"Point"}
}