{
  "type": "Feature",
  "properties": {
    "addr:full": "155 Bay State Dr Braintree MA 02184",
    "addr:housenumber": "155",
    "addr:postcode": "02184",
    "addr:street": "Bay State Dr",
    "iso:country": "US",
    "sg:address": "155 Bay State Dr",
    "sg:city": "Braintree",
    "sg:classifiers": [
      {
        "category": "Home \u0026 Garden",
        "subcategory": "Furniture",
        "type": "Retail Goods"
      },
      {
        "category": "Building \u0026 Trades",
        "subcategory": "Construction",
        "type": "Services"
      },
      {
        "category": "Manufacturing",
        "subcategory": "Building Materials",
        "type": "Manufacturing \u0026 Wholesale Goods"
      },
      {
        "category": "Wholesale",
        "subcategory": "Home Furnishings",
        "type": "Manufacturing \u0026 Wholesale Goods"
      }
    ],
    "sg:phone": "+1 781 843 8882",
    "sg:postcode": "02184",
    "sg:province": "MA",
    "sg:tags": [
      "industrial",
      "equipment-wholesale",
      "cabinetmakers-commercial",
      "kitchen",
      "equipment-household",
      "cabinet",
      "maker",
      "manufacturer"
    ],
    "wof:name": "Aisen Cabinetry",
    "wof:placetype": "venue"
  },
  "geometry": {"coordinates":[-71.027112,42.19996],"type":"Point"}
}
