{
  "type": "Feature",
  "properties": {
    "addr:full": "672 Main St Holden MA 01520",
    "addr:housenumber": "672",
    "addr:postcode": "01520",
    "addr:street": "Main St",
    "iso:country": "US",
    "sg:address": "672 Main St",
    "sg:city": "Holden",
    "sg:classifiers": [
      {
        "category": "Shopping",
        "type": "Retail Goods"
      },
      {
        "category": "Arts \u0026 Performance",
        "subcategory": "Theater",
        "type": "Entertainment"
      }
    ],
    "sg:phone": "+1 508 829 2151",
    "sg:postcode": "01520",
    "sg:province": "MA",
    "sg:tags": [
      "wedding",
      "group",
      "supply"
    ],
    "wof:name": "American Mobile Sound",
    "wof:placetype": "venue"
  },
  "geometry": {"coordinates":[-71.841775,42.341487],"type":"Point"}
}
