{
  "type": "Feature",
  "properties": {
    "iso:country":"US",
    "sg:address":"220 Greenacre Ave",
    "sg:city":"Longmeadow",
    "sg:classifiers":[
        {
            "category":"Utilities",
            "subcategory":"Telephone",
            "type":"Services"
        }
    ],
    "sg:phone":"+1   ",
    "sg:postcode":"01106",
    "sg:province":"MA",
    "sg:tags":[
        "communications"
    ],
    "wof:name":"Jake Shore-Suslowitz",
    "wof:placetype":"venue"
},
  "geometry": {"coordinates":[-72.57262299999999,42.054357],"type":"Point"}
}