{
  "type": "Feature",
  "properties": {
    "addr:full": "303 Bridge St Weymouth MA 02191",
    "addr:housenumber": "303",
    "addr:postcode": "02191",
    "addr:street": "Bridge St",
    "iso:country": "US",
    "sg:address": "303 Bridge St",
    "sg:city": "Weymouth",
    "sg:classifiers": [
      {
        "category": "Retail",
        "subcategory": "Auto Repair",
        "type": "Services"
      }
    ],
    "sg:phone": "+1 781 335 9680",
    "sg:postcode": "02191",
    "sg:province": "MA",
    "sg:tags": [
      "repairing",
      "automobile"
    ],
    "wof:name": "T \u0026 S Auto \u0026 Truck Repair",
    "wof:placetype": "venue"
  },
  "geometry": {"coordinates":[-70.953089,42.242743],"type":"Point"}
}
