{
  "type": "Feature",
  "properties": {
    "addr:full":"42 Woods Ave Somerville MA 02144",
    "addr:housenumber":"42",
    "addr:postcode":"02144",
    "addr:street":"Woods Ave",
    "iso:country":"US",
    "sg:address":"42 Woods Ave",
    "sg:city":"Somerville",
    "sg:classifiers":[
        {
            "category":"Building & Trades",
            "subcategory":"Plumbing",
            "type":"Services"
        }
    ],
    "sg:phone":"+1 617 776 9650",
    "sg:postcode":"02144",
    "sg:province":"MA",
    "sg:tags":[
        "plumber"
    ],
    "wof:name":"Mitrano Mario A & Sillari Anthony R",
    "wof:placetype":"venue"
},
  "geometry": {"coordinates":[-71.128078,42.411399],"type":"Point"}
}