{
  "type": "Feature",
  "properties": {
    "addr:full": "6 Broadway Lawrence MA 01840",
    "addr:housenumber": "6",
    "addr:postcode": "01840",
    "addr:street": "Broadway",
    "iso:country": "US",
    "sg:address": "6 Broadway",
    "sg:city": "Lawrence",
    "sg:classifiers": [
      {
        "category": "Travel",
        "subcategory": "Travel Agent",
        "type": "Entertainment"
      }
    ],
    "sg:phone": "+1 978 685 1041",
    "sg:postcode": "01840",
    "sg:province": "MA",
    "sg:tags": [
      "information",
      "tourist"
    ],
    "wof:name": "Lawrence Hydroelectric Tourism",
    "wof:placetype": "venue"
  },
  "geometry": {"coordinates":[-71.167486,42.703737],"type":"Point"}
}
