{
  "type": "Feature",
  "properties": {
    "iso:country":"US",
    "sg:address":"1181 Main St",
    "sg:city":"Leicester",
    "sg:classifiers":[
        {
            "category":"Donuts",
            "subcategory":"None",
            "type":"Food & Drink"
        }
    ],
    "sg:phone":"+1 508 892 8748",
    "sg:postcode":"01524",
    "sg:province":"MA",
    "wof:name":"Mike's Donut Shoppe",
    "wof:placetype":"venue"
},
  "geometry": {"coordinates":[-71.914001,42.2453],"type":"Point"}
}