{
  "type": "Feature",
  "properties": {
    "iso:country":"US",
    "sg:address":"162 W Hill Rd",
    "sg:city":"Marlborough",
    "sg:classifiers":[
        {
            "category":"Banks & Credit Unions",
            "subcategory":"Bank",
            "type":"Services"
        },
        {
            "category":"Banks & Credit Unions",
            "subcategory":"Financial Services",
            "type":"Services"
        }
    ],
    "sg:phone":"+1 508 733 1410",
    "sg:postcode":"01752",
    "sg:province":"MA",
    "sg:tags":[
        "loan",
        "saving"
    ],
    "wof:name":"Community First Bank",
    "wof:placetype":"venue"
},
  "geometry": {"coordinates":[-71.57573499999999,42.359612],"type":"Point"}
}