{
  "type": "Feature",
  "properties": {
    "addr:full": "162 W Hill Rd Marlborough MA 01752",
    "addr:housenumber": "162",
    "addr:postcode": "01752",
    "addr:street": "W Hill Rd",
    "iso:country": "US",
    "sg:address": "162 W Hill Rd",
    "sg:city": "Marlborough",
    "sg:classifiers": [
      {
        "category": "Banks \u0026 Credit Unions",
        "subcategory": "Bank",
        "type": "Services"
      },
      {
        "category": "Banks \u0026 Credit Unions",
        "subcategory": "Financial Services",
        "type": "Services"
      }
    ],
    "sg:phone": "+1 508 733 1410",
    "sg:postcode": "01752",
    "sg:province": "MA",
    "sg:tags": [
      "loan",
      "saving"
    ],
    "wof:name": "Community First Bank",
    "wof:placetype": "venue"
  },
  "geometry": {"coordinates":[-71.575735,42.359612],"type":"Point"}
}
