{
  "type": "Feature",
  "properties": {
    "iso:country":"US",
    "sg:address":"106 River St",
    "sg:city":"West Newton",
    "sg:classifiers":[
        {
            "category":"Organizations",
            "subcategory":"Non-profit Organization",
            "type":"Services"
        }
    ],
    "sg:phone":"+1 617 969 2521",
    "sg:postcode":"02465",
    "sg:province":"MA",
    "sg:website":"www.bostonneca.org",
    "wof:name":"Electrical Contractors Assn",
    "wof:placetype":"venue"
},
  "geometry": {"coordinates":[-71.229472,42.352292],"type":"Point"}
}