{
  "type": "Feature",
  "properties": {
    "addr:full": "25 Prospect St Ste 2 Framingham MA 01701",
    "addr:housenumber": "25",
    "addr:postcode": "01701",
    "addr:street": "Prospect St Ste 2",
    "iso:country": "US",
    "sg:address": "25 Prospect St Ste 2",
    "sg:city": "Framingham",
    "sg:classifiers": [
      {
        "category": "Shopping",
        "subcategory": "Clothing, Apparel, \u0026 Fashions",
        "type": "Retail Goods"
      }
    ],
    "sg:phone": "+1 508 620 5900",
    "sg:postcode": "01701",
    "sg:province": "MA",
    "sg:tags": [
      "suits-custom",
      "men's",
      "made"
    ],
    "wof:name": "Mr Tux",
    "wof:placetype": "venue"
  },
  "geometry": {"coordinates":[-71.422394,42.29845],"type":"Point"}
}
