{
  "type": "Feature",
  "properties": {
    "addr:full":"8 Faneuil Hall Market Pl Floor Boston MA 02109",
    "addr:housenumber":"8",
    "addr:postcode":"02109",
    "addr:street":"Faneuil Hall Market Pl Floor",
    "iso:country":"US",
    "sg:address":"8 Faneuil Hall Market Pl Floor",
    "sg:city":"Boston",
    "sg:classifiers":[
        {
            "category":"Structure",
            "subcategory":"Office Building",
            "type":"Public Place"
        }
    ],
    "sg:phone":"+1 617 973 6400",
    "sg:postcode":"02109",
    "sg:province":"MA",
    "sg:tags":[
        "rental",
        "desk",
        "park",
        "space"
    ],
    "wof:name":"Regus/ HQ",
    "wof:placetype":"venue"
},
  "geometry": {"coordinates":[-71.055764,42.359961],"type":"Point"}
}