{
  "type": "Feature",
  "properties": {
    "addr:full": "381 Medford Street Malden MA 02148",
    "addr:housenumber": "381",
    "addr:postcode": "02148",
    "addr:street": "Medford Street",
    "iso:country": "US",
    "sg:address": "381 Medford Street",
    "sg:city": "Malden",
    "sg:classifiers": [
      {
        "category": "Food \u0026 Beverages",
        "subcategory": "Liquor \u0026 Beverages",
        "type": "Retail Goods"
      }
    ],
    "sg:phone": "+1 781 322 8355",
    "sg:postcode": "02148",
    "sg:province": "MA",
    "sg:tags": [
      "beer",
      "spirit",
      "wine"
    ],
    "wof:name": "Edgeworth Liquor Store",
    "wof:placetype": "venue"
  },
  "geometry": {"coordinates":[-71.080013,42.417538],"type":"Point"}
}
