{
  "type": "Feature",
  "properties": {
    "iso:country":"US",
    "sg:address":"381 Medford Street",
    "sg:city":"Malden",
    "sg:classifiers":[
        {
            "category":"Food & Beverages",
            "subcategory":"Liquor & Beverages",
            "type":"Retail Goods"
        }
    ],
    "sg:phone":"+1 781 322 8355",
    "sg:postcode":"02148",
    "sg:province":"MA",
    "sg:tags":[
        "beer",
        "spirit",
        "wine"
    ],
    "wof:name":"Edgeworth Liquor Store",
    "wof:placetype":"venue"
},
  "geometry": {"coordinates":[-71.08001299999999,42.417538],"type":"Point"}
}