{
  "type": "Feature",
  "properties": {
    "iso:country":"US",
    "sg:address":"6 Snow Rd",
    "sg:city":"Marshfield",
    "sg:classifiers":[
        {
            "category":"Professional",
            "type":"Services"
        }
    ],
    "sg:phone":"+1 781 834 9788",
    "sg:postcode":"02050",
    "sg:province":"MA",
    "sg:tags":[
        "establishment"
    ],
    "wof:name":"Mug'n Muffin",
    "wof:placetype":"venue"
},
  "geometry": {"coordinates":[-70.70472700000001,42.091354],"type":"Point"}
}