{
  "type": "Feature",
  "properties": {
    "iso:country":"US",
    "sg:address":"63 Howard St",
    "sg:city":"Norwood",
    "sg:classifiers":[
        {
            "category":"Home & Garden",
            "subcategory":"Carpets & Floor Coverings",
            "type":"Retail Goods"
        }
    ],
    "sg:phone":"+1 781 255 0546",
    "sg:postcode":"02062",
    "sg:province":"MA",
    "sg:tags":[
        "material"
    ],
    "wof:name":"Shearing Shed, The",
    "wof:placetype":"venue"
},
  "geometry": {"coordinates":[-71.200639,42.198919],"type":"Point"}
}