{
  "type": "Feature",
  "properties": {
    "iso:country":"US",
    "sg:address":"1219 Providence Rd",
    "sg:city":"Whitinsville",
    "sg:classifiers":[
        {
            "category":"Education",
            "subcategory":"Library",
            "type":"Public Place"
        }
    ],
    "sg:phone":"+1 508 234 5975",
    "sg:postcode":"01588",
    "sg:province":"MA",
    "sg:tags":[
        "reading",
        "instruction"
    ],
    "sg:website":"http://www.kumon.com",
    "wof:name":"Kumon Math & Reading Center Of Whitinsville",
    "wof:placetype":"venue"
},
  "geometry": {"coordinates":[-71.64653,42.126167],"type":"Point"}
}