{
  "type": "Feature",
  "properties": {
    "addr:full": "32 Federal Furnace Rd Plymouth MA 02360",
    "addr:housenumber": "32",
    "addr:postcode": "02360",
    "addr:street": "Federal Furnace Rd",
    "iso:country": "US",
    "sg:address": "32 Federal Furnace Rd",
    "sg:city": "Plymouth",
    "sg:classifiers": [
      {
        "category": "Professional",
        "subcategory": "Computer Services",
        "type": "Services"
      }
    ],
    "sg:phone": "+1 508 747 6888",
    "sg:postcode": "02360",
    "sg:province": "MA",
    "sg:tags": [
      "repair"
    ],
    "wof:name": "Computer Trouble Shooters",
    "wof:placetype": "venue"
  },
  "geometry": {"coordinates":[-70.69652,41.941513],"type":"Point"}
}
