{
  "type": "Feature",
  "properties": {
    "iso:country":"US",
    "sg:address":"32 Federal Furnace Rd",
    "sg:city":"Plymouth",
    "sg:classifiers":[
        {
            "category":"Professional",
            "subcategory":"Computer Services",
            "type":"Services"
        }
    ],
    "sg:phone":"+1 508 747 6888",
    "sg:postcode":"02360",
    "sg:province":"MA",
    "sg:tags":[
        "repair"
    ],
    "wof:name":"Computer Trouble Shooters",
    "wof:placetype":"venue"
},
  "geometry": {"coordinates":[-70.69652000000001,41.941513],"type":"Point"}
}