{
  "type": "Feature",
  "properties": {
    "iso:country":"US",
    "sg:address":"22 Pratts Mill Rd",
    "sg:city":"Sudbury",
    "sg:classifiers":[
        {
            "category":"Social Services",
            "subcategory":"Child Care",
            "type":"Services"
        },
        {
            "category":"Government",
            "subcategory":"Office",
            "type":"Public Place"
        }
    ],
    "sg:phone":"+1 978 443 6964",
    "sg:postcode":"01776",
    "sg:province":"MA",
    "sg:tags":[
        "nursery",
        "day"
    ],
    "wof:name":"Sudbury Extended Day Curtis",
    "wof:placetype":"venue"
},
  "geometry": {"coordinates":[-71.435013,42.378521],"type":"Point"}
}