{
  "type": "Feature",
  "properties": {
    "addr:full":"1 Exchange St Gloucester MA 01930",
    "addr:housenumber":"1",
    "addr:postcode":"01930",
    "addr:street":"Exchange St",
    "iso:country":"US",
    "sg:address":"1 Exchange St",
    "sg:city":"Gloucester",
    "sg:classifiers":[
        {
            "category":"Professional",
            "type":"Services"
        }
    ],
    "sg:phone":"+1 978 283 4339",
    "sg:postcode":"01930",
    "sg:province":"MA",
    "sg:tags":[
        "establishment"
    ],
    "wof:name":"Braga Management Team",
    "wof:placetype":"venue"
},
  "geometry": {"coordinates":[-70.66945200000001,42.616918],"type":"Point"}
}