{
  "type": "Feature",
  "properties": {
    "addr:full":"131 Harvard St Brookline MA 02446",
    "addr:housenumber":"131",
    "addr:postcode":"02446",
    "addr:street":"Harvard St",
    "iso:country":"US",
    "sg:address":"131 Harvard St",
    "sg:city":"Brookline",
    "sg:classifiers":[
        {
            "category":"Health Services",
            "subcategory":"Clinic",
            "type":"Services"
        }
    ],
    "sg:phone":"+1 617 277 1367",
    "sg:postcode":"02446",
    "sg:province":"MA",
    "sg:tags":[
        "home"
    ],
    "wof:name":"TLC Staff Builders",
    "wof:placetype":"venue"
},
  "geometry": {"coordinates":[-71.12146199999999,42.3377],"type":"Point"}
}