{
  "type": "Feature",
  "properties": {
    "addr:full":"37 Bennett St Lynn MA 01905",
    "addr:housenumber":"37",
    "addr:postcode":"01905",
    "addr:street":"Bennett St",
    "iso:country":"US",
    "sg:address":"37 Bennett St",
    "sg:city":"Lynn",
    "sg:classifiers":[
        {
            "category":"Retail",
            "subcategory":"Auto Repair",
            "type":"Services"
        }
    ],
    "sg:phone":"+1 781 581 1216",
    "sg:postcode":"01905",
    "sg:province":"MA",
    "sg:tags":[
        "repairing",
        "automobile"
    ],
    "wof:name":"Brickyard Auto Repair",
    "wof:placetype":"venue"
},
  "geometry": {"coordinates":[-70.962279,42.456624],"type":"Point"}
}