{
  "type": "Feature",
  "properties": {
    "iso:country":"US",
    "sg:address":"164 Pauline St",
    "sg:city":"Winthrop",
    "sg:classifiers":[
        {
            "category":"Travel",
            "subcategory":"Travel Agent",
            "type":"Entertainment"
        }
    ],
    "sg:phone":"+1 617 539 0937",
    "sg:postcode":"02152",
    "sg:province":"MA",
    "sg:tags":[
        "agency",
        "services-commercial"
    ],
    "wof:name":"Tft Travel",
    "wof:placetype":"venue"
},
  "geometry": {"coordinates":[-70.989098,42.375185],"type":"Point"}
}