{
  "type": "Feature",
  "properties": {
    "addr:full":"153 Northboro Rd Southborough MA 01772",
    "addr:housenumber":"153",
    "addr:postcode":"01772",
    "addr:street":"Northboro Rd",
    "iso:country":"US",
    "sg:address":"153 Northboro Rd",
    "sg:city":"Southborough",
    "sg:classifiers":[
        {
            "category":"Wholesale",
            "subcategory":"Wine & Distilled Alcoholic Beverages",
            "type":"Manufacturing & Wholesale Goods"
        }
    ],
    "sg:phone":"+1 508 229 0014",
    "sg:postcode":"01772",
    "sg:province":"MA",
    "wof:name":"Atlantic Importing Co",
    "wof:placetype":"venue"
},
  "geometry": {"coordinates":[-71.577414,42.315255],"type":"Point"}
}