{
  "type": "Feature",
  "properties": {
    "addr:full": "89 Access Rd Norwood MA 02062",
    "addr:housenumber": "89",
    "addr:postcode": "02062",
    "addr:street": "Access Rd",
    "iso:country": "US",
    "sg:address": "89 Access Rd",
    "sg:city": "Norwood",
    "sg:classifiers": [
      {
        "category": "Professional",
        "subcategory": "Engineering",
        "type": "Services"
      }
    ],
    "sg:phone": "+1 781 255 0796",
    "sg:postcode": "02062",
    "sg:province": "MA",
    "sg:tags": [
      "engineer"
    ],
    "wof:name": "Innovative Engineering",
    "wof:placetype": "venue"
  },
  "geometry": {"coordinates":[-71.1795,42.18475],"type":"Point"}
}
