{
  "type": "Feature",
  "properties": {
    "iso:country":"US",
    "sg:address":"320 New Boston Rd",
    "sg:city":"Fairhaven",
    "sg:classifiers":[
        {
            "category":"Professional",
            "subcategory":"Computer Services",
            "type":"Services"
        }
    ],
    "sg:phone":"+1 508 997 9507",
    "sg:postcode":"02719",
    "sg:province":"MA",
    "sg:tags":[
        "website",
        "design"
    ],
    "wof:name":"Cyber Systems Inc",
    "wof:placetype":"venue"
},
  "geometry": {"coordinates":[-70.866052,41.672935],"type":"Point"}
}