{
  "type": "Feature",
  "properties": {
    "iso:country":"US",
    "sg:address":"460 South St",
    "sg:city":"Athol",
    "sg:classifiers":[
        {
            "category":"Restaurant",
            "type":"Food & Drink"
        }
    ],
    "sg:phone":"+1 978 249 3236",
    "sg:postcode":"01331",
    "sg:province":"MA",
    "wof:name":"Eddie's",
    "wof:placetype":"venue"
},
  "geometry": {"coordinates":[-72.231872,42.592153],"type":"Point"}
}