{
  "type": "Feature",
  "properties": {
    "addr:full": "460 South St Athol MA 01331",
    "addr:housenumber": "460",
    "addr:postcode": "01331",
    "addr:street": "South St",
    "iso:country": "US",
    "sg:address": "460 South St",
    "sg:city": "Athol",
    "sg:classifiers": [
      {
        "category": "Restaurant",
        "type": "Food \u0026 Drink"
      }
    ],
    "sg:phone": "+1 978 249 3236",
    "sg:postcode": "01331",
    "sg:province": "MA",
    "wof:name": "Eddie's",
    "wof:placetype": "venue"
  },
  "geometry": {"coordinates":[-72.231872,42.592153],"type":"Point"}
}
