{
  "type": "Feature",
  "properties": {
    "addr:full": "1 Harris St West Stockbridge MA 01266",
    "addr:housenumber": "1",
    "addr:postcode": "01266",
    "addr:street": "Harris St",
    "iso:country": "US",
    "sg:address": "1 Harris St",
    "sg:city": "West Stockbridge",
    "sg:classifiers": [
      {
        "category": "Restaurant",
        "type": "Food \u0026 Drink"
      }
    ],
    "sg:phone": "+1 413 232 7277",
    "sg:postcode": "01266",
    "sg:province": "MA",
    "wof:name": "Oeno Restaurant",
    "wof:placetype": "venue"
  },
  "geometry": {"coordinates":[-73.368183,42.333137],"type":"Point"}
}
