{
  "type": "Feature",
  "properties": {
    "iso:country":"US",
    "sg:address":"34 Priscilla Ln",
    "sg:city":"Charlton",
    "sg:classifiers":[
        {
            "category":"Professional",
            "type":"Services"
        }
    ],
    "sg:phone":"+1   ",
    "sg:postcode":"01507",
    "sg:province":"MA",
    "wof:name":"Dale Barsamian",
    "wof:placetype":"venue"
},
  "geometry": {"coordinates":[-71.911275,42.159204],"type":"Point"}
}