{
  "type": "Feature",
  "properties": {
    "addr:full":"697 Cambridge St Ste 206 Brighton MA 02135",
    "addr:housenumber":"697",
    "addr:postcode":"02135",
    "addr:street":"Cambridge St Ste 206",
    "iso:country":"US",
    "sg:address":"697 Cambridge St Ste 206",
    "sg:city":"Brighton",
    "sg:classifiers":[
        {
            "category":"Health Services",
            "subcategory":"Clinic",
            "type":"Services"
        },
        {
            "category":"Health Services",
            "subcategory":"Chiropractor",
            "type":"Services"
        }
    ],
    "sg:phone":"+1 617 206 3250",
    "sg:postcode":"02135",
    "sg:province":"MA",
    "sg:tags":[
        "loss",
        "weight"
    ],
    "sg:website":"drsimon.net/",
    "wof:name":"Simon Chiropractic Healthcare",
    "wof:placetype":"venue"
},
  "geometry": {"coordinates":[-71.146249,42.351033],"type":"Point"}
}