{
  "type": "Feature",
  "properties": {
    "addr:full": "38 Main St Gloucester MA 01930",
    "addr:housenumber": "38",
    "addr:postcode": "01930",
    "addr:street": "Main St",
    "iso:country": "US",
    "sg:address": "38 Main St",
    "sg:city": "Gloucester",
    "sg:classifiers": [
      {
        "category": "Restaurant",
        "type": "Food \u0026 Drink"
      }
    ],
    "sg:phone": "+1 978 283 6186",
    "sg:postcode": "01930",
    "sg:province": "MA",
    "wof:name": "Valentino's",
    "wof:placetype": "venue"
  },
  "geometry": {"coordinates":[-70.665384,42.611964],"type":"Point"}
}
