{
  "type": "Feature",
  "properties": {
    "addr:full": "174 High St Ipswich MA 01938",
    "addr:housenumber": "174",
    "addr:postcode": "01938",
    "addr:street": "High St",
    "iso:country": "US",
    "sg:address": "174 High St",
    "sg:city": "Ipswich",
    "sg:classifiers": [
      {
        "category": "Personal",
        "type": "Services"
      }
    ],
    "sg:phone": "+1 978 356 2939",
    "sg:postcode": "01938",
    "sg:province": "MA",
    "sg:tags": [
      "therapist",
      "massage"
    ],
    "wof:name": "Be Well",
    "wof:placetype": "venue"
  },
  "geometry": {"coordinates":[-70.860129,42.693705],"type":"Point"}
}
