{
  "type": "Feature",
  "properties": {
    "addr:full":"21 Fruean Ave South Yarmouth MA 02664",
    "addr:housenumber":"21",
    "addr:postcode":"02664",
    "addr:street":"Fruean Ave",
    "iso:country":"US",
    "sg:address":"21 Fruean Ave",
    "sg:city":"South Yarmouth",
    "sg:classifiers":[
        {
            "category":"Food & Beverages",
            "subcategory":"Bakery",
            "type":"Retail Goods"
        }
    ],
    "sg:phone":"+1 508 945 5080",
    "sg:postcode":"02664",
    "sg:province":"MA",
    "sg:tags":[
        "doughnut"
    ],
    "wof:name":"Dunkin Donuts",
    "wof:placetype":"venue"
},
  "geometry": {"coordinates":[-70.214466,41.685294],"type":"Point"}
}