{
  "type": "Feature",
  "properties": {
    "addr:full": "66 Bremen St # 03 Boston MA 02128",
    "addr:housenumber": "66",
    "addr:postcode": "02128",
    "addr:street": "Bremen St # 03",
    "iso:country": "US",
    "sg:address": "66 Bremen St # 03",
    "sg:city": "Boston",
    "sg:classifiers": [
      {
        "category": "Retail",
        "subcategory": "Laundry \u0026 Dry Cleaning",
        "type": "Services"
      },
      {
        "category": "Building \u0026 Trades",
        "subcategory": "Cleaning \u0026 Sanitation",
        "type": "Services"
      }
    ],
    "sg:phone": "+1 857 277 7618",
    "sg:postcode": "02128",
    "sg:province": "MA",
    "sg:tags": [
      "cleaner",
      "upholstery",
      "rug",
      "contractor",
      "carpet"
    ],
    "sg:website": "http://boston.citysearch.com/profile/604376432/east_boston_ma/friends_carpet_cleaning_inc_.html?publisher=yellowpages\u0026reference_id=1\u0026placement=ypwebsitemip",
    "wof:name": "Friends Carpet Cleaning Inc.",
    "wof:placetype": "venue"
  },
  "geometry": {"coordinates":[-71.037312,42.370187],"type":"Point"}
}
