{
  "type": "Feature",
  "properties": {
    "iso:country":"US",
    "sg:address":"609 Main St",
    "sg:city":"Leominster",
    "sg:phone":"+1 978 537 5831",
    "sg:postcode":"01453",
    "sg:province":"MA",
    "sg:tags":[
        "equipment",
        "supply"
    ],
    "wof:name":"Twin City Bar & Restaurant",
    "wof:placetype":"venue"
},
  "geometry": {"coordinates":[-71.73871200000001,42.542813],"type":"Point"}
}