{
  "type": "Feature",
  "properties": {
    "addr:full": "150 Washington St Haverhill MA 01832",
    "addr:housenumber": "150",
    "addr:postcode": "01832",
    "addr:street": "Washington St",
    "iso:country": "US",
    "sg:address": "150 Washington St",
    "sg:city": "Haverhill",
    "sg:classifiers": [
      {
        "category": "Restaurant",
        "type": "Food \u0026 Drink"
      }
    ],
    "sg:phone": "+1 978 374 1111",
    "sg:postcode": "01832",
    "sg:province": "MA",
    "sg:tags": [
      "pizza"
    ],
    "sg:website": "http://www.bostonpizza.com",
    "wof:name": "Boston Pizza",
    "wof:placetype": "venue"
  },
  "geometry": {"coordinates":[-71.086319,42.772526],"type":"Point"}
}
