{
  "type": "Feature",
  "properties": {
    "addr:full": "400 Rte 15 Sturbridge MA 01566",
    "addr:housenumber": "400",
    "addr:postcode": "01566",
    "addr:street": "Rte 15",
    "iso:country": "US",
    "sg:address": "400 Rte 15",
    "sg:city": "Sturbridge",
    "sg:classifiers": [
      {
        "category": "Restaurant",
        "type": "Food \u0026 Drink"
      }
    ],
    "sg:phone": "+1 774 490 0045",
    "sg:postcode": "01566",
    "sg:province": "MA",
    "wof:name": "Field Stone Grill \u0026 Bar",
    "wof:placetype": "venue"
  },
  "geometry": {"coordinates":[-72.114133,42.061181],"type":"Point"}
}
