{
  "type": "Feature",
  "properties": {
    "iso:country":"US",
    "sg:address":"400 Rte 15",
    "sg:city":"Sturbridge",
    "sg:classifiers":[
        {
            "category":"Restaurant",
            "type":"Food & Drink"
        }
    ],
    "sg:phone":"+1 774 490 0045",
    "sg:postcode":"01566",
    "sg:province":"MA",
    "wof:name":"Field Stone Grill & Bar",
    "wof:placetype":"venue"
},
  "geometry": {"coordinates":[-72.114133,42.061181],"type":"Point"}
}