{
  "type": "Feature",
  "properties": {
    "addr:full": "10 Laurel Ave Wellesley MA 02481",
    "addr:housenumber": "10",
    "addr:postcode": "02481",
    "addr:street": "Laurel Ave",
    "iso:country": "US",
    "sg:address": "10 Laurel Ave",
    "sg:city": "Wellesley",
    "sg:classifiers": [
      {
        "category": "Professional",
        "subcategory": "Accounting \u0026 Tax Preparation",
        "type": "Services"
      }
    ],
    "sg:phone": "+1 781 237 3077",
    "sg:postcode": "02481",
    "sg:province": "MA",
    "sg:tags": [
      "accountant"
    ],
    "wof:name": "De Bairos \u0026 Mathias",
    "wof:placetype": "venue"
  },
  "geometry": {"coordinates":[-71.277726,42.308483],"type":"Point"}
}
