{
  "type": "Feature",
  "properties": {
    "addr:full": "3050 Washington St Roxbury MA 02119",
    "addr:housenumber": "3050",
    "addr:postcode": "02119",
    "addr:street": "Washington St",
    "iso:country": "US",
    "sg:address": "3050 Washington St",
    "sg:city": "Roxbury",
    "sg:classifiers": [
      {
        "category": "Professional",
        "type": "Services"
      }
    ],
    "sg:phone": "+1 617 442 0505",
    "sg:postcode": "02119",
    "sg:province": "MA",
    "sg:tags": [
      "establishment"
    ],
    "wof:name": "Tuesday's Child",
    "wof:placetype": "venue"
  },
  "geometry": {"coordinates":[-71.098066,42.315969],"type":"Point"}
}
