{
  "type": "Feature",
  "properties": {
    "addr:full": "73 Main St Easthampton MA 01027",
    "addr:housenumber": "73",
    "addr:postcode": "01027",
    "addr:street": "Main St",
    "iso:country": "US",
    "sg:address": "73 Main St",
    "sg:city": "Easthampton",
    "sg:classifiers": [
      {
        "category": "Restaurant",
        "type": "Food \u0026 Drink"
      }
    ],
    "sg:phone": "+1 413 527 3363",
    "sg:postcode": "01027",
    "sg:province": "MA",
    "wof:name": "Silver Spoon Restaurant",
    "wof:placetype": "venue"
  },
  "geometry": {"coordinates":[-72.672296,42.27081],"type":"Point"}
}
