{
  "type": "Feature",
  "properties": {
    "iso:country":"US",
    "sg:address":"1295 Broadway",
    "sg:city":"Somerville",
    "sg:classifiers":[
        {
            "category":"Fast Food",
            "type":"Food & Drink"
        },
        {
            "category":"Restaurant",
            "type":"Food & Drink"
        },
        {
            "category":"Professional",
            "type":"Services"
        }
    ],
    "sg:phone":"+1 617 628 0018",
    "sg:postcode":"02144",
    "sg:province":"MA",
    "sg:tags":[
        "delivery",
        "take",
        "chinese"
    ],
    "wof:name":"Szechuan Bay",
    "wof:placetype":"venue"
},
  "geometry": {"coordinates":[-71.13100799999999,42.405651],"type":"Point"}
}