{
  "type": "Feature",
  "properties": {
    "addr:full": "1295 Broadway Somerville MA 02144",
    "addr:housenumber": "1295",
    "addr:postcode": "02144",
    "addr:street": "Broadway",
    "iso:country": "US",
    "sg:address": "1295 Broadway",
    "sg:city": "Somerville",
    "sg:classifiers": [
      {
        "category": "Fast Food",
        "type": "Food \u0026 Drink"
      },
      {
        "category": "Restaurant",
        "type": "Food \u0026 Drink"
      },
      {
        "category": "Professional",
        "type": "Services"
      }
    ],
    "sg:phone": "+1 617 628 0018",
    "sg:postcode": "02144",
    "sg:province": "MA",
    "sg:tags": [
      "delivery",
      "take",
      "chinese"
    ],
    "wof:name": "Szechuan Bay",
    "wof:placetype": "venue"
  },
  "geometry": {"coordinates":[-71.131008,42.405651],"type":"Point"}
}
