{
  "type": "Feature",
  "properties": {
    "addr:full":"132 High St Newburyport MA 01950",
    "addr:housenumber":"132",
    "addr:postcode":"01950",
    "addr:street":"High St",
    "iso:country":"US",
    "sg:address":"132 High St",
    "sg:city":"Newburyport",
    "sg:classifiers":[
        {
            "category":"Health Services",
            "subcategory":"Podiatrist",
            "type":"Services"
        }
    ],
    "sg:phone":"+1 978 462 7011",
    "sg:postcode":"01950",
    "sg:province":"MA",
    "wof:name":"Arthur J Hewett DPM",
    "wof:placetype":"venue"
},
  "geometry": {"coordinates":[-70.873127,42.808054],"type":"Point"}
}