{
  "type": "Feature",
  "properties": {
    "addr:full": "9 Digby Ln Gloucester MA 01930",
    "addr:housenumber": "9",
    "addr:postcode": "01930",
    "addr:street": "Digby Ln",
    "iso:country": "US",
    "sg:address": "9 Digby Ln",
    "sg:city": "Gloucester",
    "sg:classifiers": [
      {
        "category": "Professional",
        "subcategory": "Lawyer \u0026 Legal Services",
        "type": "Services"
      }
    ],
    "sg:phone": "+1 978 283 1919",
    "sg:postcode": "01930",
    "sg:province": "MA",
    "sg:tags": [
      "attorney"
    ],
    "wof:name": "Michael E Mc Mahon",
    "wof:placetype": "venue"
  },
  "geometry": {"coordinates":[-70.700938,42.65508],"type":"Point"}
}
