{
  "type": "Feature",
  "properties": {
    "iso:country":"US",
    "sg:address":"9 Digby Ln",
    "sg:city":"Gloucester",
    "sg:classifiers":[
        {
            "category":"Professional",
            "subcategory":"Lawyer & Legal Services",
            "type":"Services"
        }
    ],
    "sg:phone":"+1 978 283 1919",
    "sg:postcode":"01930",
    "sg:province":"MA",
    "sg:tags":[
        "attorney"
    ],
    "wof:name":"Michael E Mc Mahon",
    "wof:placetype":"venue"
},
  "geometry": {"coordinates":[-70.70093799999999,42.65508],"type":"Point"}
}