{
  "type": "Feature",
  "properties": {
    "addr:full":"1 Bowdoin Sq Boston MA 02114",
    "addr:housenumber":"1",
    "addr:postcode":"02114",
    "addr:street":"Bowdoin Sq",
    "iso:country":"US",
    "sg:address":"1 Bowdoin Sq",
    "sg:city":"Boston",
    "sg:classifiers":[
        {
            "category":"Professional",
            "subcategory":"Lawyer & Legal Services",
            "type":"Services"
        }
    ],
    "sg:phone":"+1 617 227 7031",
    "sg:postcode":"02114",
    "sg:province":"MA",
    "sg:tags":[
        "attorney",
        "practice"
    ],
    "wof:name":"Bailey Elizabeth J Lwyr",
    "wof:placetype":"venue"
},
  "geometry": {"coordinates":[-71.06285099999999,42.361279],"type":"Point"}
}