{
  "type": "Feature",
  "properties": {
    "addr:full": "22 Woburn St Reading MA 01867",
    "addr:housenumber": "22",
    "addr:postcode": "01867",
    "addr:street": "Woburn St",
    "iso:country": "US",
    "sg:address": "22 Woburn St",
    "sg:city": "Reading",
    "sg:classifiers": [
      {
        "category": "Personal",
        "type": "Services"
      }
    ],
    "sg:phone": "+1 781 944 7431",
    "sg:postcode": "01867",
    "sg:province": "MA",
    "sg:tags": [
      "therapist",
      "massage"
    ],
    "sg:website": "www.chap.com",
    "wof:name": "Center For Health \u0026 Athletic",
    "wof:placetype": "venue"
  },
  "geometry": {"coordinates":[-71.103964,42.524842],"type":"Point"}
}
