{
  "type": "Feature",
  "properties": {
    "iso:country":"US",
    "sg:address":"55 Woronco Rd",
    "sg:city":"Blandford",
    "sg:classifiers":[
        {
            "category":"Farming",
            "subcategory":"Nursery",
            "type":"Manufacturing & Wholesale Goods"
        }
    ],
    "sg:phone":"+1 413 568 8665",
    "sg:postcode":"01008",
    "sg:province":"MA",
    "sg:tags":[
        "greenhouse"
    ],
    "wof:name":"Pine Acres Greenhouse",
    "wof:placetype":"venue"
},
  "geometry": {"coordinates":[-72.91589399999999,42.174867],"type":"Point"}
}