{
  "type": "Feature",
  "properties": {
    "iso:country":"US",
    "sg:address":"1 S Main St",
    "sg:city":"Assonet",
    "sg:classifiers":[
        {
            "category":"Professional",
            "subcategory":"Lawyer & Legal Services",
            "type":"Services"
        }
    ],
    "sg:phone":"+1 508 644 2116",
    "sg:postcode":"02702",
    "sg:province":"MA",
    "sg:tags":[
        "attorney"
    ],
    "wof:name":"Commonwealth Police Svc",
    "wof:placetype":"venue"
},
  "geometry": {"coordinates":[-71.06767000000001,41.79499],"type":"Point"}
}