{
  "type": "Feature",
  "properties": {
    "addr:full": "1 S Main St Assonet MA 02702",
    "addr:housenumber": "1",
    "addr:postcode": "02702",
    "addr:street": "S Main St",
    "iso:country": "US",
    "sg:address": "1 S Main St",
    "sg:city": "Assonet",
    "sg:classifiers": [
      {
        "category": "Professional",
        "subcategory": "Lawyer \u0026 Legal Services",
        "type": "Services"
      }
    ],
    "sg:phone": "+1 508 644 2116",
    "sg:postcode": "02702",
    "sg:province": "MA",
    "sg:tags": [
      "attorney"
    ],
    "wof:name": "Commonwealth Police Svc",
    "wof:placetype": "venue"
  },
  "geometry": {"coordinates":[-71.06767,41.79499],"type":"Point"}
}
