{
  "type": "Feature",
  "properties": {
    "addr:full":"4 Cranberry Cir Pittsfield MA 01201",
    "addr:housenumber":"4",
    "addr:postcode":"01201",
    "addr:street":"Cranberry Cir",
    "iso:country":"US",
    "sg:address":"4 Cranberry Cir",
    "sg:city":"Pittsfield",
    "sg:classifiers":[
        {
            "category":"Building & Trades",
            "subcategory":"Plumbing",
            "type":"Services"
        }
    ],
    "sg:phone":"+1 413 499 7975",
    "sg:postcode":"01201",
    "sg:province":"MA",
    "wof:name":"Girona Plumbing Heating & Cooling - CLOSED",
    "wof:placetype":"venue"
},
  "geometry": {"coordinates":[-73.372398,42.448502],"type":"Point"}
}