{
  "type": "Feature",
  "properties": {
    "iso:country":"US",
    "sg:address":"79 1/2 Newbury Ave",
    "sg:city":"Quincy",
    "sg:classifiers":[
        {
            "category":"Personal",
            "type":"Services"
        }
    ],
    "sg:phone":"+1 617 773 5823",
    "sg:postcode":"02171",
    "sg:province":"MA",
    "sg:tags":[
        "image",
        "consultants-personal"
    ],
    "wof:name":"Image Connection",
    "wof:placetype":"venue"
},
  "geometry": {"coordinates":[-71.029004,42.28092],"type":"Point"}
}