{
  "type": "Feature",
  "properties": {
    "addr:full": "761 Washington St Stoughton MA 02072",
    "addr:housenumber": "761",
    "addr:postcode": "02072",
    "addr:street": "Washington St",
    "iso:country": "US",
    "sg:address": "761 Washington St",
    "sg:city": "Stoughton",
    "sg:classifiers": [
      {
        "category": "Shopping",
        "type": "Retail Goods"
      }
    ],
    "sg:phone": "+1   ",
    "sg:postcode": "02072",
    "sg:province": "MA",
    "sg:tags": [
      "communication",
      "radiotelephone"
    ],
    "wof:name": "Pagecom Wireless Inc",
    "wof:placetype": "venue"
  },
  "geometry": {"coordinates":[-71.102142,42.12505],"type":"Point"}
}
