{
  "type": "Feature",
  "properties": {
    "iso:country":"US",
    "sg:address":"350 Summer St",
    "sg:city":"Abington",
    "sg:classifiers":[
        {
            "category":"Government",
            "subcategory":"Office",
            "type":"Public Place"
        }
    ],
    "sg:phone":"+1 781 982 2122",
    "sg:postcode":"02351",
    "sg:province":"MA",
    "sg:tags":[
        "village"
    ],
    "wof:name":"Abington Sewer Dept",
    "wof:placetype":"venue"
},
  "geometry": {"coordinates":[-70.938174,42.10329],"type":"Point"}
}