{
  "type": "Feature",
  "properties": {
    "iso:country":"US",
    "sg:address":"242 Mammoth Rd",
    "sg:city":"Lowell",
    "sg:classifiers":[
        {
            "category":"Retail",
            "subcategory":"Auto Repair",
            "type":"Services"
        }
    ],
    "sg:phone":"+1 978 458 7406",
    "sg:postcode":"01854",
    "sg:province":"MA",
    "sg:tags":[
        "wrecker"
    ],
    "wof:name":"Scott's Towing",
    "wof:placetype":"venue"
},
  "geometry": {"coordinates":[-71.338286,42.654205],"type":"Point"}
}