{
  "type": "Feature",
  "properties": {
    "iso:country":"US",
    "sg:address":"94 Park Ave",
    "sg:city":"Belmont",
    "sg:classifiers":[
        {
            "category":"Shopping",
            "subcategory":"Clothing, Apparel, & Fashions",
            "type":"Retail Goods"
        }
    ],
    "sg:phone":"+1 617 489 2355",
    "sg:postcode":"02478",
    "sg:province":"MA",
    "sg:tags":[
        "tailor"
    ],
    "wof:name":"Park Place Clothiers",
    "wof:placetype":"venue"
},
  "geometry": {"coordinates":[-71.181518,42.410689],"type":"Point"}
}