{
  "type": "Feature",
  "properties": {
    "addr:full":"628 Dartmouth St South Dartmouth MA 02748",
    "addr:housenumber":"628",
    "addr:postcode":"02748",
    "addr:street":"Dartmouth St",
    "iso:country":"US",
    "sg:address":"628 Dartmouth St",
    "sg:city":"South Dartmouth",
    "sg:classifiers":[
        {
            "category":"Social Services",
            "type":"Services"
        }
    ],
    "sg:phone":"+1 508 991 6018",
    "sg:postcode":"02748",
    "sg:province":"MA",
    "sg:tags":[
        "care",
        "center",
        "day"
    ],
    "wof:name":"Dartmouth Senior Social Day",
    "wof:placetype":"venue"
},
  "geometry": {"coordinates":[-70.94052600000001,41.606945],"type":"Point"}
}