{
  "type": "Feature",
  "properties": {
    "addr:full":"440 E Squantum Street Quincy MA 02171",
    "addr:housenumber":"440",
    "addr:postcode":"02171",
    "addr:street":"E Squantum Street",
    "iso:country":"US",
    "sg:address":"440 E Squantum Street",
    "sg:city":"Quincy",
    "sg:classifiers":[
        {
            "category":"Social Services",
            "subcategory":"Child Care",
            "type":"Services"
        },
        {
            "category":"Sports & Exercise",
            "subcategory":"Gym",
            "type":"Entertainment"
        }
    ],
    "sg:phone":"+1 617 471 5712",
    "sg:postcode":"02171",
    "sg:province":"MA",
    "sg:tags":[
        "trainer",
        "day"
    ],
    "wof:name":"Beechwood Community Life Center",
    "wof:placetype":"venue"
},
  "geometry": {"coordinates":[-71.02248,42.28992],"type":"Point"}
}