{
  "type": "Feature",
  "properties": {
    "iso:country":"US",
    "sg:address":"129 Main St",
    "sg:city":"Byfield",
    "sg:classifiers":[
        {
            "category":"Building & Trades",
            "subcategory":"Construction",
            "type":"Services"
        }
    ],
    "sg:phone":"+1 978 463 6274",
    "sg:postcode":"01922",
    "sg:province":"MA",
    "sg:tags":[
        "excavating",
        "contractor"
    ],
    "wof:name":"S J Blair Excavation",
    "wof:placetype":"venue"
},
  "geometry": {"coordinates":[-70.94337299999999,42.767776],"type":"Point"}
}