{
  "type": "Feature",
  "properties": {
    "iso:country":"US",
    "sg:address":"15 Franklin St",
    "sg:city":"Quincy",
    "sg:classifiers":[
        {
            "category":"Real Estate",
            "subcategory":"Real Estate Agent",
            "type":"Services"
        }
    ],
    "sg:phone":"+1 617 471 3337",
    "sg:postcode":"02169",
    "sg:province":"MA",
    "wof:name":"Coastal Realty Group Inc",
    "wof:placetype":"venue"
},
  "geometry": {"coordinates":[-71.003489,42.242836],"type":"Point"}
}