{
  "type": "Feature",
  "properties": {
    "iso:country":"US",
    "sg:address":"Tower Point 27-43 Wormwood St., Suite 520",
    "sg:city":"Boston",
    "sg:classifiers":[
        {
            "category":"Professional",
            "subcategory":"Computer Services",
            "type":"Services"
        }
    ],
    "sg:phone":"+1 800 862 0511",
    "sg:postcode":"02210",
    "sg:province":"MA",
    "sg:tags":[
        "mobile",
        "iphone",
        "ipad",
        "ios",
        "enterprise",
        "app-store"
    ],
    "sg:website":"http://www.apperian.com",
    "wof:name":"Apperian",
    "wof:placetype":"venue"
},
  "geometry": {"coordinates":[-71.05056399999999,42.347545],"type":"Point"}
}