{
  "type": "Feature",
  "properties": {
    "iso:country":"US",
    "sg:address":"14 Bell Rd",
    "sg:city":"North Brookfield",
    "sg:classifiers":[
        {
            "category":"Government",
            "subcategory":"Office",
            "type":"Public Place"
        }
    ],
    "sg:phone":"+1 508 867 0205",
    "sg:postcode":"01535",
    "sg:province":"MA",
    "sg:tags":[
        "village"
    ],
    "wof:name":"N Brookfield Veterans Svc Ctr",
    "wof:placetype":"venue"
},
  "geometry": {"coordinates":[-72.089292,42.280814],"type":"Point"}
}