{
  "type": "Feature",
  "properties": {
    "iso:country":"US",
    "sg:address":"93 Wyman St",
    "sg:city":"Medford",
    "sg:classifiers":[
        {
            "category":"Travel",
            "subcategory":"Hotels & Motels",
            "type":"Entertainment"
        }
    ],
    "sg:phone":"+1 781 396 7688",
    "sg:postcode":"02155",
    "sg:province":"MA",
    "sg:tags":[
        "cottage"
    ],
    "wof:name":"Pilgrims Haven Cottages",
    "wof:placetype":"venue"
},
  "geometry": {"coordinates":[-71.12362400000001,42.42365],"type":"Point"}
}