{
  "type": "Feature",
  "properties": {
    "iso:country":"US",
    "sg:address":"672 Lowell St",
    "sg:city":"Peabody",
    "sg:classifiers":[
        {
            "category":"Personal",
            "subcategory":"Beauty Salon",
            "type":"Services"
        }
    ],
    "sg:phone":"+1 978 535 9750",
    "sg:postcode":"01960",
    "sg:province":"MA",
    "wof:name":"Gatsby Hair Design",
    "wof:placetype":"venue"
},
  "geometry": {"coordinates":[-71.007248,42.549809],"type":"Point"}
}