{
  "type": "Feature",
  "properties": {
    "addr:full":"468 John Fitch Hwy Fitchburg MA 01420",
    "addr:housenumber":"468",
    "addr:postcode":"01420",
    "addr:street":"John Fitch Hwy",
    "iso:country":"US",
    "sg:address":"468 John Fitch Hwy",
    "sg:city":"Fitchburg",
    "sg:classifiers":[
        {
            "category":"Real Estate",
            "subcategory":"Real Estate Agent",
            "type":"Services"
        }
    ],
    "sg:phone":"+1 978 345 2184",
    "sg:postcode":"01420",
    "sg:province":"MA",
    "sg:tags":[
        "agency",
        "rental"
    ],
    "wof:name":"Rent-A-Center",
    "wof:placetype":"venue"
},
  "geometry": {"coordinates":[-71.774508,42.582204],"type":"Point"}
}