{
  "type": "Feature",
  "properties": {
    "addr:full": "10 California Rd Tewksbury MA 01876",
    "addr:housenumber": "10",
    "addr:postcode": "01876",
    "addr:street": "California Rd",
    "iso:country": "US",
    "sg:address": "10 California Rd",
    "sg:city": "Tewksbury",
    "sg:classifiers": [
      {
        "category": "Arts \u0026 Performance",
        "subcategory": "Theater",
        "type": "Entertainment"
      }
    ],
    "sg:phone": "+1 978 468 5463",
    "sg:postcode": "01876",
    "sg:province": "MA",
    "sg:tags": [
      "band",
      "orchestra"
    ],
    "wof:name": "Hot Line Band",
    "wof:placetype": "venue"
  },
  "geometry": {"coordinates":[-71.207844,42.576352],"type":"Point"}
}
