{
  "type": "Feature",
  "properties": {
    "iso:country":"US",
    "sg:address":"10 California Rd",
    "sg:city":"Tewksbury",
    "sg:classifiers":[
        {
            "category":"Arts & Performance",
            "subcategory":"Theater",
            "type":"Entertainment"
        }
    ],
    "sg:phone":"+1 978 468 5463",
    "sg:postcode":"01876",
    "sg:province":"MA",
    "sg:tags":[
        "band",
        "orchestra"
    ],
    "wof:name":"Hot Line Band",
    "wof:placetype":"venue"
},
  "geometry": {"coordinates":[-71.20784399999999,42.576352],"type":"Point"}
}