{
  "type": "Feature",
  "properties": {
    "iso:country":"US",
    "sg:address":"185 Church St",
    "sg:city":"Whitinsville",
    "sg:classifiers":[
        {
            "category":"Restaurant",
            "type":"Food & Drink"
        }
    ],
    "sg:phone":"+1 508 234 7269",
    "sg:postcode":"01588",
    "sg:province":"MA",
    "sg:tags":[
        "pizza"
    ],
    "wof:name":"Harry's Famous Pizza",
    "wof:placetype":"venue"
},
  "geometry": {"coordinates":[-71.658297,42.11299],"type":"Point"}
}