{
  "type": "Feature",
  "properties": {
    "addr:full": "185 Church St Whitinsville MA 01588",
    "addr:housenumber": "185",
    "addr:postcode": "01588",
    "addr:street": "Church St",
    "iso:country": "US",
    "ovtr:label": "Harry's Famous Pizza, 185 Church St Whitinsville MA US",
    "ovtr:similarity": 2.8969171047210693,
    "sg:address": "185 Church St",
    "sg:city": "Whitinsville",
    "sg:classifiers": [
      {
        "category": "Restaurant",
        "type": "Food \u0026 Drink"
      }
    ],
    "sg:phone": "+1 508 234 7269",
    "sg:postcode": "01588",
    "sg:province": "MA",
    "sg:tags": [
      "pizza"
    ],
    "wof:name": "Harry's Famous Pizza",
    "wof:placetype": "venue"
  },
  "geometry": {"coordinates":[-71.658297,42.11299],"type":"Point"}
}
