{
  "type": "Feature",
  "properties": {
    "addr:full": "42 Davis St Rutland MA 01543",
    "addr:housenumber": "42",
    "addr:postcode": "01543",
    "addr:street": "Davis St",
    "iso:country": "US",
    "sg:address": "42 Davis St",
    "sg:city": "Rutland",
    "sg:classifiers": [
      {
        "category": "Shopping",
        "subcategory": "Discount \u0026 Variety Stores",
        "type": "Retail Goods"
      }
    ],
    "sg:phone": "+1 508 886 0211",
    "sg:postcode": "01543",
    "sg:province": "MA",
    "wof:name": "Town Line Variety",
    "wof:placetype": "venue"
  },
  "geometry": {"coordinates":[-71.970077,42.426977],"type":"Point"}
}
