{
  "type": "Feature",
  "properties": {
    "addr:full": "669 Winthrop Avenue Revere MA 02151",
    "addr:housenumber": "669",
    "addr:postcode": "02151",
    "addr:street": "Winthrop Avenue",
    "iso:country": "US",
    "ovtr:label": "Beachmont Liquors, 669 Winthrop Ave Revere MA US",
    "ovtr:similarity": 2.5471370220184326,
    "sg:address": "669 Winthrop Avenue",
    "sg:city": "Revere",
    "sg:classifiers": [
      {
        "category": "Food \u0026 Beverages",
        "subcategory": "Liquor \u0026 Beverages",
        "type": "Retail Goods"
      }
    ],
    "sg:phone": "+1 781 289 2838",
    "sg:postcode": "02151",
    "sg:province": "MA",
    "sg:tags": [
      "beer",
      "spirit",
      "store",
      "wine"
    ],
    "wof:name": "Beachmont Liquors",
    "wof:placetype": "venue"
  },
  "geometry": {"coordinates":[-70.991426,42.397295],"type":"Point"}
}
