{
  "type": "Feature",
  "properties": {
    "addr:full": "503 Medford St Somerville MA 02145",
    "addr:housenumber": "503",
    "addr:postcode": "02145",
    "addr:street": "Medford St",
    "iso:country": "US",
    "sg:address": "503 Medford St",
    "sg:city": "Somerville",
    "sg:classifiers": [
      {
        "category": "Real Estate",
        "subcategory": "Real Estate Agent",
        "type": "Services"
      }
    ],
    "sg:phone": "+1 617 666 8500",
    "sg:postcode": "02145",
    "sg:province": "MA",
    "wof:name": "Commonwealth Realty Management",
    "wof:placetype": "venue"
  },
  "geometry": {"coordinates":[-71.103386,42.39609],"type":"Point"}
}
