{
  "type": "Feature",
  "properties": {
    "addr:full":"60 Congress St Springfield MA 01104",
    "addr:housenumber":"60",
    "addr:postcode":"01104",
    "addr:street":"Congress St",
    "iso:country":"US",
    "sg:address":"60 Congress St",
    "sg:city":"Springfield",
    "sg:classifiers":[
        {
            "category":"Restaurant",
            "type":"Food & Drink"
        }
    ],
    "sg:menulink":"http://www.allmenus.com/ma/springfield/9036-hooters/menu/",
    "sg:phone":"+1 413 732 7600",
    "sg:postcode":"01104",
    "sg:province":"MA",
    "sg:tags":[
        "american",
        "wing"
    ],
    "wof:name":"Hooters",
    "wof:placetype":"venue"
},
  "geometry": {"coordinates":[-72.59615700000001,42.107642],"type":"Point"}
}