{
  "type": "Feature",
  "properties": {
    "addr:full":"211 North St Northampton MA 01060",
    "addr:housenumber":"211",
    "addr:postcode":"01060",
    "addr:street":"North St",
    "iso:country":"US",
    "sg:address":"211 North St",
    "sg:city":"Northampton",
    "sg:classifiers":[
        {
            "category":"Wholesale",
            "subcategory":"Durable Goods & Equipment",
            "type":"Manufacturing & Wholesale Goods"
        }
    ],
    "sg:phone":"+1 413 585 9855",
    "sg:postcode":"01060",
    "sg:province":"MA",
    "sg:tags":[
        "importer"
    ],
    "wof:name":"Erich Husemoller Import/Export",
    "wof:placetype":"venue"
},
  "geometry": {"coordinates":[-72.62711299999999,42.329689],"type":"Point"}
}