{
  "type": "Feature",
  "properties": {
    "iso:country":"US",
    "sg:address":"656 Summer St",
    "sg:city":"Brockton",
    "sg:classifiers":[
        {
            "category":"Shopping",
            "subcategory":"Computers & Home Electronics",
            "type":"Retail Goods"
        }
    ],
    "sg:phone":"+1 508 588 5405",
    "sg:postcode":"02302",
    "sg:province":"MA",
    "sg:tags":[
        "equipment",
        "electronic",
        "supply"
    ],
    "wof:name":"Carlo Gavazzi Inc",
    "wof:placetype":"venue"
},
  "geometry": {"coordinates":[-71.00550699999999,42.060147],"type":"Point"}
}