{
  "type": "Feature",
  "properties": {
    "addr:full": "66 Jessica Way Plymouth MA 02360",
    "addr:housenumber": "66",
    "addr:postcode": "02360",
    "addr:street": "Jessica Way",
    "iso:country": "US",
    "sg:address": "66 Jessica Way",
    "sg:city": "Plymouth",
    "sg:classifiers": [
      {
        "category": "Building \u0026 Trades",
        "subcategory": "Construction",
        "type": "Services"
      }
    ],
    "sg:phone": "+1 508 224 5156",
    "sg:postcode": "02360",
    "sg:province": "MA",
    "sg:tags": [
      "painter"
    ],
    "wof:name": "Cutting Edge Painting",
    "wof:placetype": "venue"
  },
  "geometry": {"coordinates":[-70.541271,41.854263],"type":"Point"}
}
