{
  "type": "Feature",
  "properties": {
    "iso:country":"US",
    "sg:address":"66 Jessica Way",
    "sg:city":"Plymouth",
    "sg:classifiers":[
        {
            "category":"Building & Trades",
            "subcategory":"Construction",
            "type":"Services"
        }
    ],
    "sg:phone":"+1 508 224 5156",
    "sg:postcode":"02360",
    "sg:province":"MA",
    "sg:tags":[
        "painter"
    ],
    "wof:name":"Cutting Edge Painting",
    "wof:placetype":"venue"
},
  "geometry": {"coordinates":[-70.54127099999999,41.854263],"type":"Point"}
}