{
  "type": "Feature",
  "properties": {
    "addr:full": "101 Main St Ste 116 Medford MA 02155",
    "addr:housenumber": "101",
    "addr:postcode": "02155",
    "addr:street": "Main St Ste 116",
    "iso:country": "US",
    "sg:address": "101 Main St Ste 116",
    "sg:city": "Medford",
    "sg:classifiers": [
      {
        "category": "Home \u0026 Garden",
        "subcategory": "Furniture",
        "type": "Retail Goods"
      }
    ],
    "sg:phone": "+1 781 391 2939",
    "sg:postcode": "02155",
    "sg:province": "MA",
    "sg:tags": [
      "store"
    ],
    "wof:name": "Lmh Medical Svcs",
    "wof:placetype": "venue"
  },
  "geometry": {"coordinates":[-71.110616,42.415821],"type":"Point"}
}
