{
  "type": "Feature",
  "properties": {
    "iso:country":"US",
    "sg:address":"42 W Grove St",
    "sg:city":"Middleboro",
    "sg:classifiers":[
        {
            "category":"Building & Trades",
            "subcategory":"Plumbing",
            "type":"Services"
        }
    ],
    "sg:phone":"+1 508 946 4243",
    "sg:postcode":"02346",
    "sg:province":"MA",
    "sg:tags":[
        "tank",
        "septic"
    ],
    "wof:name":"TNT Excavating",
    "wof:placetype":"venue"
},
  "geometry": {"coordinates":[-70.920192,41.887139],"type":"Point"}
}