{
  "type": "Feature",
  "properties": {
    "addr:full": "42 W Grove St Middleboro MA 02346",
    "addr:housenumber": "42",
    "addr:postcode": "02346",
    "addr:street": "W Grove St",
    "iso:country": "US",
    "sg:address": "42 W Grove St",
    "sg:city": "Middleboro",
    "sg:classifiers": [
      {
        "category": "Building \u0026 Trades",
        "subcategory": "Plumbing",
        "type": "Services"
      }
    ],
    "sg:phone": "+1 508 946 4243",
    "sg:postcode": "02346",
    "sg:province": "MA",
    "sg:tags": [
      "tank",
      "septic"
    ],
    "wof:name": "TNT Excavating",
    "wof:placetype": "venue"
  },
  "geometry": {"coordinates":[-70.920192,41.887139],"type":"Point"}
}
