{
  "type": "Feature",
  "properties": {
    "iso:country":"US",
    "sg:address":"20 Highland Rd",
    "sg:city":"Groton",
    "sg:classifiers":[
        {
            "category":"Retail",
            "subcategory":"Animal Services",
            "type":"Services"
        }
    ],
    "sg:phone":"+1 978 448 5371",
    "sg:postcode":"01450",
    "sg:province":"MA",
    "sg:tags":[
        "pet",
        "boarding",
        "sitting"
    ],
    "wof:name":"Moore Happy Tails",
    "wof:placetype":"venue"
},
  "geometry": {"coordinates":[-71.525567,42.593564],"type":"Point"}
}