{
  "type": "Feature",
  "properties": {
    "addr:full":"137 Bradford St Needham MA 02492",
    "addr:housenumber":"137",
    "addr:postcode":"02492",
    "addr:street":"Bradford St",
    "iso:country":"US",
    "sg:address":"137 Bradford St",
    "sg:city":"Needham",
    "sg:classifiers":[
        {
            "category":"Insurance",
            "subcategory":"Insurance Agent",
            "type":"Services"
        }
    ],
    "sg:phone":"+1   ",
    "sg:postcode":"02492",
    "sg:province":"MA",
    "wof:name":"Camberg Consultants",
    "wof:placetype":"venue"
},
  "geometry": {"coordinates":[-71.229569,42.276021],"type":"Point"}
}