{
  "type": "Feature",
  "properties": {
    "iso:country":"US",
    "sg:address":"3 Ward Rd",
    "sg:city":"Nahant",
    "sg:classifiers":[
        {
            "category":"Building & Trades",
            "subcategory":"Construction",
            "type":"Services"
        }
    ],
    "sg:phone":"+1   ",
    "sg:postcode":"01908",
    "sg:province":"MA",
    "sg:tags":[
        "residential"
    ],
    "wof:name":"Leon Bartletta Construction",
    "wof:placetype":"venue"
},
  "geometry": {"coordinates":[-70.93358000000001,42.428542],"type":"Point"}
}