{
  "type": "Feature",
  "properties": {
    "addr:full": "458 Russell St Hadley MA 01035",
    "addr:housenumber": "458",
    "addr:postcode": "01035",
    "addr:street": "Russell St",
    "iso:country": "US",
    "sg:address": "458 Russell St",
    "sg:city": "Hadley",
    "sg:classifiers": [
      {
        "category": "Personal",
        "subcategory": "Beauty Salon",
        "type": "Services"
      }
    ],
    "sg:phone": "+1 413 253 0100",
    "sg:postcode": "01035",
    "sg:province": "MA",
    "sg:tags": [
      "shop",
      "manicuring"
    ],
    "wof:name": "Peter's Nails",
    "wof:placetype": "venue"
  },
  "geometry": {"coordinates":[-72.536496,42.365137],"type":"Point"}
}
