{
  "type": "Feature",
  "properties": {
    "iso:country":"US",
    "sg:address":"7 McLean Rd",
    "sg:city":"Saugus",
    "sg:classifiers":[
        {
            "category":"Professional",
            "type":"Services"
        }
    ],
    "sg:phone":"+1   ",
    "sg:postcode":"01906",
    "sg:province":"MA",
    "wof:name":"Alan D Soroko",
    "wof:placetype":"venue"
},
  "geometry": {"coordinates":[-71.02986300000001,42.476387],"type":"Point"}
}