{
  "type": "Feature",
  "properties": {
    "addr:full": "11 Irvington St Waban MA 02468",
    "addr:housenumber": "11",
    "addr:postcode": "02468",
    "addr:street": "Irvington St",
    "iso:country": "US",
    "sg:address": "11 Irvington St",
    "sg:city": "Waban",
    "sg:classifiers": [
      {
        "category": "Professional",
        "subcategory": "Business Services",
        "type": "Services"
      }
    ],
    "sg:phone": "+1   ",
    "sg:postcode": "02468",
    "sg:province": "MA",
    "wof:name": "Neurofeedback Group Inc",
    "wof:placetype": "venue"
  },
  "geometry": {"coordinates":[-71.236508,42.325844],"type":"Point"}
}
