{
  "type": "Feature",
  "properties": {
    "addr:full":"185 Spring St Hyannis MA 02601",
    "addr:housenumber":"185",
    "addr:postcode":"02601",
    "addr:street":"Spring St",
    "iso:country":"US",
    "sg:address":"185 Spring St",
    "sg:city":"Hyannis",
    "sg:classifiers":[
        {
            "category":"Education",
            "subcategory":"Special Training",
            "type":"Public Place"
        }
    ],
    "sg:phone":"+1 508 862 0555",
    "sg:postcode":"02601",
    "sg:province":"MA",
    "sg:tags":[
        "educational"
    ],
    "wof:name":"Sculpture Center",
    "wof:placetype":"venue"
},
  "geometry": {"coordinates":[-70.281368,41.66193],"type":"Point"}
}