{
  "type": "Feature",
  "properties": {
    "iso:country":"US",
    "sg:address":"212 Chandler St",
    "sg:city":"Worcester",
    "sg:classifiers":[
        {
            "category":"Personal",
            "subcategory":"Beauty Salon",
            "type":"Services"
        }
    ],
    "sg:phone":"+1 508 798 5100",
    "sg:postcode":"01609",
    "sg:province":"MA",
    "wof:name":"Hair Creation-Belkis",
    "wof:placetype":"venue"
},
  "geometry": {"coordinates":[-71.817916,42.26065],"type":"Point"}
}