{
  "type": "Feature",
  "properties": {
    "iso:country":"US",
    "sg:address":"84 Congress St",
    "sg:city":"Salem",
    "sg:phone":"+1 978 744 4258",
    "sg:postcode":"01970",
    "sg:province":"MA",
    "sg:tags":[
        "oil"
    ],
    "wof:name":"Michaud & Raymond",
    "wof:placetype":"venue"
},
  "geometry": {"coordinates":[-70.889415,42.515823],"type":"Point"}
}