{
  "type": "Feature",
  "properties": {
    "addr:full": "84 Congress St Salem MA 01970",
    "addr:housenumber": "84",
    "addr:postcode": "01970",
    "addr:street": "Congress St",
    "iso:country": "US",
    "sg:address": "84 Congress St",
    "sg:city": "Salem",
    "sg:phone": "+1 978 744 4258",
    "sg:postcode": "01970",
    "sg:province": "MA",
    "sg:tags": [
      "oil"
    ],
    "wof:name": "Michaud \u0026 Raymond",
    "wof:placetype": "venue"
  },
  "geometry": {"coordinates":[-70.889415,42.515823],"type":"Point"}
}
