{
  "type": "Feature",
  "properties": {
    "addr:full":"110 Winn St Woburn MA 01801",
    "addr:housenumber":"110",
    "addr:postcode":"01801",
    "addr:street":"Winn St",
    "iso:country":"US",
    "sg:address":"110 Winn St",
    "sg:city":"Woburn",
    "sg:classifiers":[
        {
            "category":"Health Services",
            "subcategory":"Dentist",
            "type":"Services"
        }
    ],
    "sg:phone":"+1 781 933 5023",
    "sg:postcode":"01801",
    "sg:province":"MA",
    "wof:name":"Wang Jenny",
    "wof:placetype":"venue"
},
  "geometry": {"coordinates":[-71.15772,42.483698],"type":"Point"}
}