{
  "type": "Feature",
  "properties": {
    "iso:country":"US",
    "sg:address":"791 Boston Rd",
    "sg:city":"Billerica",
    "sg:classifiers":[
        {
            "category":"Personal",
            "subcategory":"Beauty Salon",
            "type":"Services"
        }
    ],
    "sg:phone":"+1   ",
    "sg:postcode":"01821",
    "sg:province":"MA",
    "sg:tags":[
        "shop"
    ],
    "wof:name":"Concepts In Hair & Skin",
    "wof:placetype":"venue"
},
  "geometry": {"coordinates":[-71.228262,42.52996],"type":"Point"}
}