{
  "type": "Feature",
  "properties": {
    "addr:full":"339 Squire Rd Revere MA 02151",
    "addr:housenumber":"339",
    "addr:postcode":"02151",
    "addr:street":"Squire Rd",
    "iso:country":"US",
    "sg:address":"339 Squire Rd",
    "sg:city":"Revere",
    "sg:classifiers":[
        {
            "category":"Building & Trades",
            "subcategory":"Equipment Rental",
            "type":"Services"
        }
    ],
    "sg:phone":"+1 781 284 7747",
    "sg:postcode":"02151",
    "sg:province":"MA",
    "sg:tags":[
        "leasing",
        "television",
        "radio-renting",
        "yard"
    ],
    "sg:website":"http://www.rentacenter.com/",
    "wof:name":"Rent-A-Center",
    "wof:placetype":"venue"
},
  "geometry": {"coordinates":[-71.01379799999999,42.427156],"type":"Point"}
}