{
  "type": "Feature",
  "properties": {
    "addr:full":"40 Poplar St Danvers MA 01923",
    "addr:housenumber":"40",
    "addr:postcode":"01923",
    "addr:street":"Poplar St",
    "iso:country":"US",
    "sg:address":"40 Poplar St",
    "sg:city":"Danvers",
    "sg:classifiers":[
        {
            "category":"Organizations",
            "subcategory":"Labor Organization",
            "type":"Services"
        }
    ],
    "sg:phone":"+1 978 750 9794",
    "sg:postcode":"01923",
    "sg:province":"MA",
    "wof:name":"U A Plumbers",
    "wof:placetype":"venue"
},
  "geometry": {"coordinates":[-70.937347,42.570257],"type":"Point"}
}