{
  "type": "Feature",
  "properties": {
    "iso:country":"US",
    "sg:address":"57 Thompson Rd",
    "sg:city":"Webster",
    "sg:classifiers":[
        {
            "category":"Government",
            "subcategory":"Police Station",
            "type":"Public Place"
        }
    ],
    "sg:phone":"+1 508 943 1212",
    "sg:postcode":"01570",
    "sg:province":"MA",
    "sg:tags":[
        "department"
    ],
    "sg:website":"www.websterpolice.com",
    "wof:name":"Webster Police Dept",
    "wof:placetype":"venue"
},
  "geometry": {"coordinates":[-71.86279399999999,42.055496],"type":"Point"}
}