{
  "type": "Feature",
  "properties": {
    "addr:full": "59 Windsor Park Rd Lowell MA 01852",
    "addr:housenumber": "59",
    "addr:postcode": "01852",
    "addr:street": "Windsor Park Rd",
    "iso:country": "US",
    "sg:address": "59 Windsor Park Rd",
    "sg:city": "Lowell",
    "sg:classifiers": [
      {
        "category": "Building \u0026 Trades",
        "subcategory": "Construction",
        "type": "Services"
      }
    ],
    "sg:phone": "+1 978 453 8019",
    "sg:postcode": "01852",
    "sg:province": "MA",
    "sg:tags": [
      "painter"
    ],
    "wof:name": "Dave Errico's Quality Painting",
    "wof:placetype": "venue"
  },
  "geometry": {"coordinates":[-71.284534,42.645072],"type":"Point"}
}
