{
  "type": "Feature",
  "properties": {
    "iso:country":"US",
    "sg:address":"1122 Bay St",
    "sg:city":"Springfield",
    "sg:classifiers":[
        {
            "category":"Coffee & Tea",
            "type":"Food & Drink"
        },
        {
            "category":"Donuts",
            "subcategory":"None",
            "type":"Food & Drink"
        }
    ],
    "sg:phone":"+1 413 733 7485",
    "sg:postcode":"01109",
    "sg:province":"MA",
    "sg:tags":[
        "shop",
        "espresso",
        "restaurant"
    ],
    "sg:website":"http://www.dunkindonuts.com",
    "wof:name":"Dunkin' Donuts",
    "wof:placetype":"venue"
},
  "geometry": {"coordinates":[-72.547032,42.132334],"type":"Point"}
}