{
  "type": "Feature",
  "properties": {
    "addr:full": "133 W Boylston St Worcester MA 01606",
    "addr:housenumber": "133",
    "addr:postcode": "01606",
    "addr:street": "W Boylston St",
    "iso:country": "US",
    "sg:address": "133 W Boylston St",
    "sg:city": "Worcester",
    "sg:classifiers": [
      {
        "category": "Autos \u0026 Motor Vehicles",
        "subcategory": "Fuel \u0026 Gas Station",
        "type": "Retail Goods"
      }
    ],
    "sg:phone": "+1 508 853 6606",
    "sg:postcode": "01606",
    "sg:province": "MA",
    "sg:tags": [
      "oil"
    ],
    "wof:name": "Ramstrom's Service Ctr",
    "wof:placetype": "venue"
  },
  "geometry": {"coordinates":[-71.804802,42.29259],"type":"Point"}
}
