{
  "type": "Feature",
  "properties": {
    "iso:country":"US",
    "sg:address":"133 W Boylston St",
    "sg:city":"Worcester",
    "sg:classifiers":[
        {
            "category":"Autos & Motor Vehicles",
            "subcategory":"Fuel & Gas Station",
            "type":"Retail Goods"
        }
    ],
    "sg:phone":"+1 508 853 6606",
    "sg:postcode":"01606",
    "sg:province":"MA",
    "sg:tags":[
        "oil"
    ],
    "wof:name":"Ramstrom's Service Ctr",
    "wof:placetype":"venue"
},
  "geometry": {"coordinates":[-71.804802,42.29259],"type":"Point"}
}