{
  "type": "Feature",
  "properties": {
    "addr:full": "167 Bow St Everett MA 02149",
    "addr:housenumber": "167",
    "addr:postcode": "02149",
    "addr:street": "Bow St",
    "iso:country": "US",
    "sg:address": "167 Bow St",
    "sg:city": "Everett",
    "sg:classifiers": [
      {
        "category": "Building \u0026 Trades",
        "subcategory": "Plumbing",
        "type": "Services"
      }
    ],
    "sg:phone": "+1 617 389 9483",
    "sg:postcode": "02149",
    "sg:province": "MA",
    "sg:tags": [
      "metal",
      "worker",
      "sheet"
    ],
    "wof:name": "LMM Inc",
    "wof:placetype": "venue"
  },
  "geometry": {"coordinates":[-71.061445,42.399274],"type":"Point"}
}
