{
  "type": "Feature",
  "properties": {
    "iso:country":"US",
    "sg:address":"167 Bow St",
    "sg:city":"Everett",
    "sg:classifiers":[
        {
            "category":"Building & Trades",
            "subcategory":"Plumbing",
            "type":"Services"
        }
    ],
    "sg:phone":"+1 617 389 9483",
    "sg:postcode":"02149",
    "sg:province":"MA",
    "sg:tags":[
        "metal",
        "worker",
        "sheet"
    ],
    "wof:name":"LMM Inc",
    "wof:placetype":"venue"
},
  "geometry": {"coordinates":[-71.06144500000001,42.399274],"type":"Point"}
}