{
  "type": "Feature",
  "properties": {
    "addr:full":"20 Andover St North Andover MA 01845",
    "addr:housenumber":"20",
    "addr:postcode":"01845",
    "addr:street":"Andover St",
    "iso:country":"US",
    "sg:address":"20 Andover St",
    "sg:city":"North Andover",
    "sg:classifiers":[
        {
            "category":"Building & Trades",
            "subcategory":"Construction",
            "type":"Services"
        }
    ],
    "sg:phone":"+1   ",
    "sg:postcode":"01845",
    "sg:province":"MA",
    "sg:tags":[
        "contractor"
    ],
    "wof:name":"McEvoy Construction",
    "wof:placetype":"venue"
},
  "geometry": {"coordinates":[-71.115039,42.683174],"type":"Point"}
}