{
  "type": "Feature",
  "properties": {
    "addr:full": "517 Washington St Duxbury MA 02332",
    "addr:housenumber": "517",
    "addr:postcode": "02332",
    "addr:street": "Washington St",
    "iso:country": "US",
    "sg:address": "517 Washington St",
    "sg:city": "Duxbury",
    "sg:classifiers": [
      {
        "category": "Wholesale",
        "subcategory": "Medical Equipment \u0026 Supplies",
        "type": "Manufacturing \u0026 Wholesale Goods"
      }
    ],
    "sg:phone": "+1 781 934 9055",
    "sg:postcode": "02332",
    "sg:province": "MA",
    "sg:tags": [
      "podiatrist"
    ],
    "wof:name": "Kinetic Technologies",
    "wof:placetype": "venue"
  },
  "geometry": {"coordinates":[-70.671742,42.040144],"type":"Point"}
}
