{
  "type": "Feature",
  "properties": {
    "iso:country":"US",
    "sg:address":"517 Washington St",
    "sg:city":"Duxbury",
    "sg:classifiers":[
        {
            "category":"Wholesale",
            "subcategory":"Medical Equipment & Supplies",
            "type":"Manufacturing & Wholesale Goods"
        }
    ],
    "sg:phone":"+1 781 934 9055",
    "sg:postcode":"02332",
    "sg:province":"MA",
    "sg:tags":[
        "podiatrist"
    ],
    "wof:name":"Kinetic Technologies",
    "wof:placetype":"venue"
},
  "geometry": {"coordinates":[-70.67174199999999,42.040144],"type":"Point"}
}