{
  "type": "Feature",
  "properties": {
    "iso:country":"US",
    "sg:address":"4 Cambridge Ctr",
    "sg:city":"Cambridge",
    "sg:classifiers":[
        {
            "category":"Health Services",
            "subcategory":"Doctor",
            "type":"Services"
        }
    ],
    "sg:phone":"+1 617 252 0003",
    "sg:postcode":"02142",
    "sg:province":"MA",
    "wof:name":"Albright Tenley E",
    "wof:placetype":"venue"
},
  "geometry": {"coordinates":[-71.087459,42.363187],"type":"Point"}
}