{
  "type": "Feature",
  "properties": {
    "addr:full": "161 High St Holyoke MA 01040",
    "addr:housenumber": "161",
    "addr:postcode": "01040",
    "addr:street": "High St",
    "iso:country": "US",
    "sg:address": "161 High St",
    "sg:city": "Holyoke",
    "sg:classifiers": [
      {
        "category": "Restaurant",
        "type": "Food \u0026 Drink"
      }
    ],
    "sg:phone": "+1 413 532 1139",
    "sg:postcode": "01040",
    "sg:province": "MA",
    "wof:name": "Fernandez Family Restaurant",
    "wof:placetype": "venue"
  },
  "geometry": {"coordinates":[-72.606499,42.208221],"type":"Point"}
}
