{
  "type": "Feature",
  "properties": {
    "iso:country":"US",
    "sg:address":"7 Thompson St",
    "sg:city":"Winchester",
    "sg:classifiers":[
        {
            "category":"Shopping",
            "subcategory":"Clothing, Apparel, & Fashions",
            "type":"Retail Goods"
        }
    ],
    "sg:phone":"+1 781 729 0456",
    "sg:postcode":"01890",
    "sg:province":"MA",
    "sg:tags":[
        "accessory",
        "clothing",
        "women's"
    ],
    "wof:name":"French Lessons Boutique",
    "wof:placetype":"venue"
},
  "geometry": {"coordinates":[-71.13702600000001,42.452222],"type":"Point"}
}