{
  "type": "Feature",
  "properties": {
    "addr:full": "58 Hancock St Braintree MA 02184",
    "addr:housenumber": "58",
    "addr:postcode": "02184",
    "addr:street": "Hancock St",
    "iso:country": "US",
    "sg:address": "58 Hancock St",
    "sg:city": "Braintree",
    "sg:classifiers": [
      {
        "category": "Professional",
        "subcategory": "Management \u0026 Consulting",
        "type": "Services"
      }
    ],
    "sg:phone": "+1 781 706 2497",
    "sg:postcode": "02184",
    "sg:province": "MA",
    "sg:tags": [
      "party",
      "planning"
    ],
    "wof:name": "Active Event Production",
    "wof:placetype": "venue"
  },
  "geometry": {"coordinates":[-71.00502,42.201254],"type":"Point"}
}
