{
  "type": "Feature",
  "properties": {
    "iso:country":"US",
    "sg:address":"58 Hancock St",
    "sg:city":"Braintree",
    "sg:classifiers":[
        {
            "category":"Professional",
            "subcategory":"Management & Consulting",
            "type":"Services"
        }
    ],
    "sg:phone":"+1 781 706 2497",
    "sg:postcode":"02184",
    "sg:province":"MA",
    "sg:tags":[
        "party",
        "planning"
    ],
    "wof:name":"Active Event Production",
    "wof:placetype":"venue"
},
  "geometry": {"coordinates":[-71.00502,42.201254],"type":"Point"}
}