{
  "type": "Feature",
  "properties": {
    "iso:country":"US",
    "sg:address":"601 Locust St",
    "sg:city":"Fall River",
    "sg:classifiers":[
        {
            "category":"Social Services",
            "type":"Services"
        }
    ],
    "sg:phone":"+1 508 673 2963",
    "sg:postcode":"02720",
    "sg:province":"MA",
    "sg:tags":[
        "organization",
        "welfare"
    ],
    "wof:name":"Fall River Community Ctr",
    "wof:placetype":"venue"
},
  "geometry": {"coordinates":[-71.14806,41.70533],"type":"Point"}
}