{
  "type": "Feature",
  "properties": {
    "addr:full": "36 Cummings Park Woburn MA 01801",
    "addr:housenumber": "36",
    "addr:postcode": "01801",
    "addr:street": "Cummings Park",
    "iso:country": "US",
    "sg:address": "36 Cummings Park",
    "sg:city": "Woburn",
    "sg:classifiers": [
      {
        "category": "Insurance",
        "subcategory": "Insurance Agent",
        "type": "Services"
      }
    ],
    "sg:phone": "+1 781 935 8480",
    "sg:postcode": "01801",
    "sg:province": "MA",
    "sg:website": "www.desanctisins.com",
    "wof:name": "Robert L Desanctis Insurance",
    "wof:placetype": "venue"
  },
  "geometry": {"coordinates":[-71.124249,42.497374],"type":"Point"}
}
