{
  "type": "Feature",
  "properties": {
    "iso:country":"US",
    "sg:address":"219 Quincy Ave",
    "sg:city":"Quincy",
    "sg:classifiers":[
        {
            "category":"Shopping",
            "subcategory":"Pharmacy",
            "type":"Retail Goods"
        }
    ],
    "sg:phone":"+1 617 376 9595",
    "sg:postcode":"02169",
    "sg:province":"MA",
    "wof:name":"Kam Ma Shopping Court",
    "wof:placetype":"venue"
},
  "geometry": {"coordinates":[-70.990341,42.241132],"type":"Point"}
}