{
  "type": "Feature",
  "properties": {
    "iso:country":"US",
    "sg:address":"8 Port View Rd",
    "sg:city":"South Chatham",
    "sg:classifiers":[
        {
            "category":"Retail",
            "subcategory":"Portrait Studio",
            "type":"Services"
        }
    ],
    "sg:phone":"+1 508 432 2218",
    "sg:postcode":"02659",
    "sg:province":"MA",
    "sg:tags":[
        "photography"
    ],
    "wof:name":"Casual Shots Photography",
    "wof:placetype":"venue"
},
  "geometry": {"coordinates":[-70.019003,41.676134],"type":"Point"}
}