{
  "type": "Feature",
  "properties": {
    "iso:country":"US",
    "sg:address":"158 Caroline Dr",
    "sg:city":"Bellingham",
    "sg:classifiers":[
        {
            "category":"Health Services",
            "subcategory":"Medical Lab",
            "type":"Services"
        }
    ],
    "sg:phone":"+1   ",
    "sg:postcode":"02019",
    "sg:province":"MA",
    "sg:tags":[
        "laboratory",
        "dental"
    ],
    "wof:name":"Norfolk Dental Lab",
    "wof:placetype":"venue"
},
  "geometry": {"coordinates":[-71.478223,42.102567],"type":"Point"}
}