{
  "type": "Feature",
  "properties": {
    "addr:full": "158 Caroline Dr Bellingham MA 02019",
    "addr:housenumber": "158",
    "addr:postcode": "02019",
    "addr:street": "Caroline Dr",
    "iso:country": "US",
    "sg:address": "158 Caroline Dr",
    "sg:city": "Bellingham",
    "sg:classifiers": [
      {
        "category": "Health Services",
        "subcategory": "Medical Lab",
        "type": "Services"
      }
    ],
    "sg:phone": "+1   ",
    "sg:postcode": "02019",
    "sg:province": "MA",
    "sg:tags": [
      "laboratory",
      "dental"
    ],
    "wof:name": "Norfolk Dental Lab",
    "wof:placetype": "venue"
  },
  "geometry": {"coordinates":[-71.478223,42.102567],"type":"Point"}
}
