{
  "type": "Feature",
  "properties": {
    "iso:country":"US",
    "sg:address":"1365 Liberty St",
    "sg:city":"Springfield",
    "sg:classifiers":[
        {
            "category":"Banks & Credit Unions",
            "subcategory":"Investment Brokerage",
            "type":"Services"
        }
    ],
    "sg:phone":"+1 413 732 5898",
    "sg:postcode":"01104",
    "sg:province":"MA",
    "sg:tags":[
        "tape",
        "video",
        "sale",
        "dvds-rental"
    ],
    "wof:name":"Hollywood Video",
    "wof:placetype":"venue"
},
  "geometry": {"coordinates":[-72.583743,42.136729],"type":"Point"}
}