{
  "type": "Feature",
  "properties": {
    "addr:full": "14 Hanover St Hanover MA 02339",
    "addr:housenumber": "14",
    "addr:postcode": "02339",
    "addr:street": "Hanover St",
    "iso:country": "US",
    "sg:address": "14 Hanover St",
    "sg:city": "Hanover",
    "sg:classifiers": [
      {
        "category": "Home \u0026 Garden",
        "subcategory": "Household Appliances",
        "type": "Retail Goods"
      },
      {
        "category": "Building \u0026 Trades",
        "subcategory": "Construction",
        "type": "Services"
      }
    ],
    "sg:phone": "+1 781 829 9600",
    "sg:postcode": "02339",
    "sg:province": "MA",
    "sg:tags": [
      "major",
      "dishwashing",
      "system",
      "machine",
      "contractor",
      "air conditioning"
    ],
    "wof:name": "Heating And Cooling Comfort Systems",
    "wof:placetype": "venue"
  },
  "geometry": {"coordinates":[-70.824249,42.119671],"type":"Point"}
}
