{
  "type": "Feature",
  "properties": {
    "iso:country":"US",
    "sg:address":"14 Hanover St",
    "sg:city":"Hanover",
    "sg:classifiers":[
        {
            "category":"Home & Garden",
            "subcategory":"Household Appliances",
            "type":"Retail Goods"
        },
        {
            "category":"Building & Trades",
            "subcategory":"Construction",
            "type":"Services"
        }
    ],
    "sg:phone":"+1 781 829 9600",
    "sg:postcode":"02339",
    "sg:province":"MA",
    "sg:tags":[
        "major",
        "dishwashing",
        "system",
        "machine",
        "contractor",
        "air conditioning"
    ],
    "wof:name":"Heating And Cooling Comfort Systems",
    "wof:placetype":"venue"
},
  "geometry": {"coordinates":[-70.82424899999999,42.119671],"type":"Point"}
}