{
  "type": "Feature",
  "properties": {
    "addr:full":"519 Columbia Rd Dorchester MA 02125",
    "addr:housenumber":"519",
    "addr:postcode":"02125",
    "addr:street":"Columbia Rd",
    "iso:country":"US",
    "sg:address":"519 Columbia Rd",
    "sg:city":"Dorchester",
    "sg:classifiers":[
        {
            "category":"Retail",
            "subcategory":"Laundry & Dry Cleaning",
            "type":"Services"
        }
    ],
    "sg:phone":"+1 617 929 1100",
    "sg:postcode":"02125",
    "sg:province":"MA",
    "sg:tags":[
        "cleaner",
        "operated",
        "dryer",
        "laundries-self",
        "washer",
        "coin"
    ],
    "wof:name":"Granite Laundry",
    "wof:placetype":"venue"
},
  "geometry": {"coordinates":[-71.06643699999999,42.315571],"type":"Point"}
}