{
  "type": "Feature",
  "properties": {
    "addr:full":"36 Cottage St Medway MA 02053",
    "addr:housenumber":"36",
    "addr:postcode":"02053",
    "addr:street":"Cottage St",
    "iso:country":"US",
    "sg:address":"36 Cottage St",
    "sg:city":"Medway",
    "sg:classifiers":[
        {
            "category":"Real Estate",
            "subcategory":"Architect",
            "type":"Services"
        }
    ],
    "sg:phone":"+1   ",
    "sg:postcode":"02053",
    "sg:province":"MA",
    "sg:tags":[
        "architectural"
    ],
    "wof:name":"Moores Charles Design Assoc",
    "wof:placetype":"venue"
},
  "geometry": {"coordinates":[-71.42144999999999,42.14194],"type":"Point"}
}