{
  "type": "Feature",
  "properties": {
    "addr:full": "72 Rogers St Gloucester MA 01930",
    "addr:housenumber": "72",
    "addr:postcode": "01930",
    "addr:street": "Rogers St",
    "iso:country": "US",
    "sg:address": "72 Rogers St",
    "sg:city": "Gloucester",
    "sg:classifiers": [
      {
        "category": "Shopping",
        "subcategory": "Jewelry",
        "type": "Retail Goods"
      }
    ],
    "sg:phone": "+1 978 283 0007",
    "sg:postcode": "01930",
    "sg:province": "MA",
    "sg:tags": [
      "jeweler"
    ],
    "wof:name": "Dobbs Meadow Jewelry",
    "wof:placetype": "venue"
  },
  "geometry": {"coordinates":[-70.661463,42.612137],"type":"Point"}
}
