{
  "type": "Feature",
  "properties": {
    "addr:full": "1079 Main St Housatonic MA 01236",
    "addr:housenumber": "1079",
    "addr:postcode": "01236",
    "addr:street": "Main St",
    "iso:country": "US",
    "sg:address": "1079 Main St",
    "sg:city": "Housatonic",
    "sg:classifiers": [
      {
        "category": "Food \u0026 Beverages",
        "subcategory": "Bakery",
        "type": "Retail Goods"
      }
    ],
    "sg:phone": "+1 413 274 0044",
    "sg:postcode": "01236",
    "sg:province": "MA",
    "sg:tags": [
      "bakers-wholesale"
    ],
    "wof:name": "Lisa Newmanncooks Inc",
    "wof:placetype": "venue"
  },
  "geometry": {"coordinates":[-73.366386,42.257508],"type":"Point"}
}
