{
  "type": "Feature",
  "properties": {
    "iso:country":"US",
    "sg:address":"1079 Main St",
    "sg:city":"Housatonic",
    "sg:classifiers":[
        {
            "category":"Food & Beverages",
            "subcategory":"Bakery",
            "type":"Retail Goods"
        }
    ],
    "sg:phone":"+1 413 274 0044",
    "sg:postcode":"01236",
    "sg:province":"MA",
    "sg:tags":[
        "bakers-wholesale"
    ],
    "wof:name":"Lisa Newmanncooks Inc",
    "wof:placetype":"venue"
},
  "geometry": {"coordinates":[-73.36638600000001,42.257508],"type":"Point"}
}