{
  "type": "Feature",
  "properties": {
    "addr:full":"151 Federal St Boston MA 02110",
    "addr:housenumber":"151",
    "addr:postcode":"02110",
    "addr:street":"Federal St",
    "iso:country":"US",
    "sg:address":"151 Federal St",
    "sg:city":"Boston",
    "sg:classifiers":[
        {
            "category":"Professional",
            "type":"Services"
        }
    ],
    "sg:phone":"+1 617 342 7302",
    "sg:postcode":"02110",
    "sg:province":"MA",
    "sg:tags":[
        "establishment"
    ],
    "wof:name":"A H Davonport Corp",
    "wof:placetype":"venue"
},
  "geometry": {"coordinates":[-71.05614799999999,42.35374],"type":"Point"}
}