{
  "type": "Feature",
  "properties": {
    "iso:country":"US",
    "sg:address":"145 Rockland St",
    "sg:city":"Abington",
    "sg:classifiers":[
        {
            "category":"Taxi",
            "type":"Transportation"
        }
    ],
    "sg:phone":"+1 781 982 0100",
    "sg:postcode":"02351",
    "sg:province":"MA",
    "wof:name":"Abington Checker Cab",
    "wof:placetype":"venue"
},
  "geometry": {"coordinates":[-70.953778,42.107716],"type":"Point"}
}