{
  "type": "Feature",
  "properties": {
    "addr:full": "303 State Rd Westport MA 02790",
    "addr:housenumber": "303",
    "addr:postcode": "02790",
    "addr:street": "State Rd",
    "iso:country": "US",
    "sg:address": "303 State Rd",
    "sg:city": "Westport",
    "sg:classifiers": [
      {
        "category": "Shopping",
        "type": "Retail Goods"
      }
    ],
    "sg:phone": "+1 508 678 7801",
    "sg:postcode": "02790",
    "sg:province": "MA",
    "sg:tags": [
      "monument"
    ],
    "wof:name": "Albanese Monument Co",
    "wof:placetype": "venue"
  },
  "geometry": {"coordinates":[-71.101639,41.670991],"type":"Point"}
}
