{
  "type": "Feature",
  "properties": {
    "iso:country":"US",
    "sg:address":"33 Southwick St",
    "sg:city":"Feeding Hills",
    "sg:classifiers":[
        {
            "category":"Health Services",
            "subcategory":"Doctor",
            "type":"Services"
        }
    ],
    "sg:phone":"+1 413 786 7555",
    "sg:postcode":"01030",
    "sg:province":"MA",
    "sg:tags":[
        "dentist"
    ],
    "wof:name":"Donald H Willett DDS",
    "wof:placetype":"venue"
},
  "geometry": {"coordinates":[-72.681241,42.066789],"type":"Point"}
}