{
  "type": "Feature",
  "properties": {
    "addr:full":"196 Franklin St Stoneham MA 02180",
    "addr:housenumber":"196",
    "addr:postcode":"02180",
    "addr:street":"Franklin St",
    "iso:country":"US",
    "sg:address":"196 Franklin St",
    "sg:city":"Stoneham",
    "sg:classifiers":[
        {
            "category":"Professional",
            "subcategory":"Engineering",
            "type":"Services"
        }
    ],
    "sg:phone":"+1 781 665 0165",
    "sg:postcode":"02180",
    "sg:province":"MA",
    "sg:tags":[
        "engineer"
    ],
    "wof:name":"Kevin Gregory Engineering Inc",
    "wof:placetype":"venue"
},
  "geometry": {"coordinates":[-71.083674,42.472516],"type":"Point"}
}