{
  "type": "Feature",
  "properties": {
    "addr:full": "14 North St Hingham MA 02043",
    "addr:housenumber": "14",
    "addr:postcode": "02043",
    "addr:street": "North St",
    "iso:country": "US",
    "sg:address": "14 North St",
    "sg:city": "Hingham",
    "sg:classifiers": [
      {
        "category": "Restaurant",
        "type": "Food \u0026 Drink"
      }
    ],
    "sg:menulink": "http://www.allmenus.com/ma/hingham/267819-tosca/menu/",
    "sg:phone": "+1 781 740 0080",
    "sg:postcode": "02043",
    "sg:province": "MA",
    "sg:tags": [
      "italian"
    ],
    "wof:name": "Tosca",
    "wof:placetype": "venue"
  },
  "geometry": {"coordinates":[-70.884902,42.244557],"type":"Point"}
}
