{
  "type": "Feature",
  "properties": {
    "iso:country":"US",
    "sg:address":"14 North St",
    "sg:city":"Hingham",
    "sg:classifiers":[
        {
            "category":"Restaurant",
            "type":"Food & Drink"
        }
    ],
    "sg:menulink":"http://www.allmenus.com/ma/hingham/267819-tosca/menu/",
    "sg:phone":"+1 781 740 0080",
    "sg:postcode":"02043",
    "sg:province":"MA",
    "sg:tags":[
        "italian"
    ],
    "wof:name":"Tosca",
    "wof:placetype":"venue"
},
  "geometry": {"coordinates":[-70.884902,42.244557],"type":"Point"}
}