{
  "type": "Feature",
  "properties": {
    "addr:full": "32 Fairview Rd Weston MA 02493",
    "addr:housenumber": "32",
    "addr:postcode": "02493",
    "addr:street": "Fairview Rd",
    "iso:country": "US",
    "sg:address": "32 Fairview Rd",
    "sg:city": "Weston",
    "sg:classifiers": [
      {
        "category": "Real Estate",
        "subcategory": "Real Estate Agent",
        "type": "Services"
      }
    ],
    "sg:phone": "+1 781 899 7434",
    "sg:postcode": "02493",
    "sg:province": "MA",
    "wof:name": "Carol Realty Co",
    "wof:placetype": "venue"
  },
  "geometry": {"coordinates":[-71.295392,42.379591],"type":"Point"}
}
