{
  "type": "Feature",
  "properties": {
    "addr:full":"51 School St Pembroke MA 02359",
    "addr:housenumber":"51",
    "addr:postcode":"02359",
    "addr:street":"School St",
    "iso:country":"US",
    "sg:address":"51 School St",
    "sg:city":"Pembroke",
    "sg:classifiers":[
        {
            "category":"Manufacturing",
            "subcategory":"Tools & Machinery",
            "type":"Manufacturing & Wholesale Goods"
        }
    ],
    "sg:phone":"+1 781 294 8031",
    "sg:postcode":"02359",
    "sg:province":"MA",
    "sg:tags":[
        "machine",
        "shop"
    ],
    "wof:name":"Ab-Wey Machine & Die Co",
    "wof:placetype":"venue"
},
  "geometry": {"coordinates":[-70.838033,42.042285],"type":"Point"}
}