{
  "type": "Feature",
  "properties": {
    "iso:country":"US",
    "sg:address":"25 Harvard Street",
    "sg:city":"Brookline",
    "sg:classifiers":[
        {
            "category":"Health Services",
            "subcategory":"Doctor",
            "type":"Services"
        },
        {
            "category":"Sports & Exercise",
            "subcategory":"Gym",
            "type":"Entertainment"
        }
    ],
    "sg:phone":"+1 617 754 0350",
    "sg:postcode":"02445",
    "sg:province":"MA",
    "sg:tags":[
        "medicine",
        "trainer",
        "internal",
        "dermatologist"
    ],
    "wof:name":"Beth Israel Deaconess Medical",
    "wof:placetype":"venue"
},
  "geometry": {"coordinates":[-71.119066,42.333981],"type":"Point"}
}