{
  "type": "Feature",
  "properties": {
    "iso:country":"US",
    "sg:address":"27 Blackmer Rd",
    "sg:city":"Sudbury",
    "sg:classifiers":[
        {
            "category":"Real Estate",
            "subcategory":"Real Estate Services",
            "type":"Services"
        },
        {
            "category":"Real Estate",
            "subcategory":"Real Estate Agent",
            "type":"Services"
        }
    ],
    "sg:phone":"+1 978 443 5169",
    "sg:postcode":"01776",
    "sg:province":"MA",
    "sg:tags":[
        "buyer",
        "broker"
    ],
    "wof:name":"Charlesbridge Realty Co",
    "wof:placetype":"venue"
},
  "geometry": {"coordinates":[-71.40011,42.350867],"type":"Point"}
}