{
  "type": "Feature",
  "properties": {
    "iso:country":"US",
    "sg:address":"186 South St",
    "sg:city":"Boston",
    "sg:classifiers":[
        {
            "category":"Professional",
            "type":"Services"
        }
    ],
    "sg:phone":"+1 617 425 7300",
    "sg:postcode":"02111",
    "sg:province":"MA",
    "sg:tags":[
        "establishment"
    ],
    "sg:website":"www.onetooneinteractive.com",
    "wof:name":"One To One Interactive",
    "wof:placetype":"venue"
},
  "geometry": {"coordinates":[-71.057514,42.34991],"type":"Point"}
}