{
  "type": "Feature",
  "properties": {
    "iso:country":"US",
    "sg:address":"45 Linden St",
    "sg:city":"Worcester",
    "sg:classifiers":[
        {
            "category":"Professional",
            "subcategory":"Lawyer & Legal Services",
            "type":"Services"
        }
    ],
    "sg:phone":"+1 508 799 7997",
    "sg:postcode":"01609",
    "sg:province":"MA",
    "sg:tags":[
        "attorney"
    ],
    "wof:name":"John M Gerard Attorney",
    "wof:placetype":"venue"
},
  "geometry": {"coordinates":[-71.805927,42.264577],"type":"Point"}
}