{
  "type": "Feature",
  "properties": {
    "addr:full": "8 Warren Rd Buzzards Bay MA 02532",
    "addr:housenumber": "8",
    "addr:postcode": "02532",
    "addr:street": "Warren Rd",
    "iso:country": "US",
    "sg:address": "8 Warren Rd",
    "sg:city": "Buzzards Bay",
    "sg:classifiers": [
      {
        "category": "Professional",
        "subcategory": "Business Services",
        "type": "Services"
      }
    ],
    "sg:phone": "+1   ",
    "sg:postcode": "02532",
    "sg:province": "MA",
    "wof:name": "Mackenzie Associates Cons",
    "wof:placetype": "venue"
  },
  "geometry": {"coordinates":[-70.620252,41.730914],"type":"Point"}
}
