{
  "type": "Feature",
  "properties": {
    "addr:full": "534 Main St Chatham MA 02633",
    "addr:housenumber": "534",
    "addr:postcode": "02633",
    "addr:street": "Main St",
    "iso:country": "US",
    "sg:address": "534 Main St",
    "sg:city": "Chatham",
    "sg:classifiers": [
      {
        "category": "Food \u0026 Beverages",
        "subcategory": "Liquor \u0026 Beverages",
        "type": "Retail Goods"
      }
    ],
    "sg:phone": "+1 508 945 0047",
    "sg:postcode": "02633",
    "sg:province": "MA",
    "sg:tags": [
      "beer",
      "spirit",
      "wine"
    ],
    "wof:name": "Epicure of Chatham Inc",
    "wof:placetype": "venue"
  },
  "geometry": {"coordinates":[-69.956398,41.679699],"type":"Point"}
}
