{
  "type": "Feature",
  "properties": {
    "addr:full":"19 Moose Hill Pkwy Sharon MA 02067",
    "addr:housenumber":"19",
    "addr:postcode":"02067",
    "addr:street":"Moose Hill Pkwy",
    "iso:country":"US",
    "sg:address":"19 Moose Hill Pkwy",
    "sg:city":"Sharon",
    "sg:classifiers":[
        {
            "category":"Restaurant",
            "type":"Food & Drink"
        }
    ],
    "sg:phone":"+1 781 784 1690",
    "sg:postcode":"02067",
    "sg:province":"MA",
    "wof:name":"Jeffrey Seul Esther Whitfield",
    "wof:placetype":"venue"
},
  "geometry": {"coordinates":[-71.18791899999999,42.12479],"type":"Point"}
}