{
  "type": "Feature",
  "properties": {
    "addr:full": "88 Pine St Medfield MA 02052",
    "addr:housenumber": "88",
    "addr:postcode": "02052",
    "addr:street": "Pine St",
    "iso:country": "US",
    "sg:address": "88 Pine St",
    "sg:city": "Medfield",
    "sg:classifiers": [
      {
        "category": "Arts \u0026 Performance",
        "subcategory": "Art Gallery",
        "type": "Entertainment"
      }
    ],
    "sg:phone": "+1 508 359 9565",
    "sg:postcode": "02052",
    "sg:province": "MA",
    "sg:tags": [
      "consultant",
      "galleries"
    ],
    "wof:name": "Full Moon Fine Arts",
    "wof:placetype": "venue"
  },
  "geometry": {"coordinates":[-71.303126,42.203983],"type":"Point"}
}
