{
  "type": "Feature",
  "properties": {
    "iso:country":"US",
    "sg:address":"88 Pine St",
    "sg:city":"Medfield",
    "sg:classifiers":[
        {
            "category":"Arts & Performance",
            "subcategory":"Art Gallery",
            "type":"Entertainment"
        }
    ],
    "sg:phone":"+1 508 359 9565",
    "sg:postcode":"02052",
    "sg:province":"MA",
    "sg:tags":[
        "consultant",
        "galleries"
    ],
    "wof:name":"Full Moon Fine Arts",
    "wof:placetype":"venue"
},
  "geometry": {"coordinates":[-71.30312600000001,42.203983],"type":"Point"}
}