{
  "type": "Feature",
  "properties": {
    "iso:country":"US",
    "sg:address":"970 County St",
    "sg:city":"Somerset",
    "sg:classifiers":[
        {
            "category":"Restaurant",
            "type":"Food & Drink"
        }
    ],
    "sg:phone":"+1   ",
    "sg:postcode":"02726",
    "sg:province":"MA",
    "sg:tags":[
        "eating"
    ],
    "wof:name":"Chads Chowder House",
    "wof:placetype":"venue"
},
  "geometry": {"coordinates":[-71.145039,41.746258],"type":"Point"}
}