{
  "type": "Feature",
  "properties": {
    "addr:full":"14 Exchange St Barre MA 01005",
    "addr:housenumber":"14",
    "addr:postcode":"01005",
    "addr:street":"Exchange St",
    "iso:country":"US",
    "sg:address":"14 Exchange St",
    "sg:city":"Barre",
    "sg:classifiers":[
        {
            "category":"Real Estate",
            "subcategory":"Real Estate Agent",
            "type":"Services"
        }
    ],
    "sg:phone":"+1 978 355 2154",
    "sg:postcode":"01005",
    "sg:province":"MA",
    "wof:name":"Neylon Real Estate",
    "wof:placetype":"venue"
},
  "geometry": {"coordinates":[-72.104696,42.423069],"type":"Point"}
}