{
  "type": "Feature",
  "properties": {
    "addr:full":"1721 Washington St Boston MA 02118",
    "addr:housenumber":"1721",
    "addr:postcode":"02118",
    "addr:street":"Washington St",
    "iso:country":"US",
    "sg:address":"1721 Washington St",
    "sg:city":"Boston",
    "sg:classifiers":[
        {
            "category":"Restaurant",
            "type":"Food & Drink"
        }
    ],
    "sg:phone":"+1 617 536 6386",
    "sg:postcode":"02118",
    "sg:province":"MA",
    "sg:tags":[
        "thai",
        "take"
    ],
    "sg:website":"www.equatorrestaurantma.com",
    "wof:name":"Equator",
    "wof:placetype":"venue"
},
  "geometry": {"coordinates":[-71.076611,42.337059],"type":"Point"}
}