{
  "type": "Feature",
  "properties": {
    "iso:country":"US",
    "sg:address":"786 Washington St",
    "sg:city":"Braintree",
    "sg:classifiers":[
        {
            "category":"Recreation",
            "type":"Entertainment"
        }
    ],
    "sg:phone":"+1 781 848 1640",
    "sg:postcode":"02184",
    "sg:province":"MA",
    "sg:tags":[
        "historical"
    ],
    "wof:name":"Braintree Historical Society",
    "wof:placetype":"venue"
},
  "geometry": {"coordinates":[-71.00435299999999,42.206325],"type":"Point"}
}