{
  "type": "Feature",
  "properties": {
    "addr:full": "786 Washington St Braintree MA 02184",
    "addr:housenumber": "786",
    "addr:postcode": "02184",
    "addr:street": "Washington St",
    "iso:country": "US",
    "ovtr:label": "Braintree Historical Society, 786 Washington St Braintree MA US",
    "ovtr:similarity": 2.718998908996582,
    "sg:address": "786 Washington St",
    "sg:city": "Braintree",
    "sg:classifiers": [
      {
        "category": "Recreation",
        "type": "Entertainment"
      }
    ],
    "sg:phone": "+1 781 848 1640",
    "sg:postcode": "02184",
    "sg:province": "MA",
    "sg:tags": [
      "historical"
    ],
    "wof:name": "Braintree Historical Society",
    "wof:placetype": "venue"
  },
  "geometry": {"coordinates":[-71.004353,42.206325],"type":"Point"}
}
