{
  "type": "Feature",
  "properties": {
    "addr:full":"62 Canal St Athol MA 01331",
    "addr:housenumber":"62",
    "addr:postcode":"01331",
    "addr:street":"Canal St",
    "iso:country":"US",
    "sg:address":"62 Canal St",
    "sg:city":"Athol",
    "sg:classifiers":[
        {
            "category":"Building & Trades",
            "subcategory":"Construction",
            "type":"Services"
        }
    ],
    "sg:phone":"+1 978 249 3730",
    "sg:postcode":"01331",
    "sg:province":"MA",
    "sg:tags":[
        "sandblasting"
    ],
    "wof:name":"John's Sandblasting",
    "wof:placetype":"venue"
},
  "geometry": {"coordinates":[-72.23660599999999,42.591635],"type":"Point"}
}