{
  "type": "Feature",
  "properties": {
    "iso:country":"US",
    "sg:address":"19 Jefferey Ln",
    "sg:city":"Haverhill",
    "sg:classifiers":[
        {
            "category":"Travel",
            "subcategory":"Travel Agent",
            "type":"Entertainment"
        }
    ],
    "sg:phone":"+1 978 372 8080",
    "sg:postcode":"01832",
    "sg:province":"MA",
    "sg:tags":[
        "tours",
        "promoter"
    ],
    "wof:name":"Groups Inc",
    "wof:placetype":"venue"
},
  "geometry": {"coordinates":[-71.093683,42.788037],"type":"Point"}
}