{
  "type": "Feature",
  "properties": {
    "iso:country":"US",
    "sg:address":"171 S Royalston Rd",
    "sg:city":"Athol",
    "sg:classifiers":[
        {
            "category":"Health Services",
            "subcategory":"Nursing And Care Facility",
            "type":"Services"
        }
    ],
    "sg:phone":"+1 978 249 5110",
    "sg:postcode":"01331",
    "sg:province":"MA",
    "sg:tags":[
        "home",
        "convalescent"
    ],
    "wof:name":"Applewood Home For Elders",
    "wof:placetype":"venue"
},
  "geometry": {"coordinates":[-72.17798000000001,42.585115],"type":"Point"}
}