{
  "type": "Feature",
  "properties": {
    "addr:full": "171 S Royalston Rd Athol MA 01331",
    "addr:housenumber": "171",
    "addr:postcode": "01331",
    "addr:street": "S Royalston Rd",
    "iso:country": "US",
    "ovtr:label": "Applewood Home For Elders, 171 S Royalston Rd Athol MA US",
    "ovtr:similarity": 2.0808749198913574,
    "sg:address": "171 S Royalston Rd",
    "sg:city": "Athol",
    "sg:classifiers": [
      {
        "category": "Health Services",
        "subcategory": "Nursing And Care Facility",
        "type": "Services"
      }
    ],
    "sg:phone": "+1 978 249 5110",
    "sg:postcode": "01331",
    "sg:province": "MA",
    "sg:tags": [
      "home",
      "convalescent"
    ],
    "wof:name": "Applewood Home For Elders",
    "wof:placetype": "venue"
  },
  "geometry": {"coordinates":[-72.17798,42.585115],"type":"Point"}
}
