{
  "type": "Feature",
  "properties": {
    "addr:full":"600 Massachusetts Ave Arlington MA 02476",
    "addr:housenumber":"600",
    "addr:postcode":"02476",
    "addr:street":"Massachusetts Ave",
    "iso:country":"US",
    "sg:address":"600 Massachusetts Ave",
    "sg:city":"Arlington",
    "sg:classifiers":[
        {
            "category":"Organizations",
            "subcategory":"Professional Association",
            "type":"Services"
        }
    ],
    "sg:phone":"+1 781 648 9832",
    "sg:postcode":"02476",
    "sg:province":"MA",
    "wof:name":"Veterans Of Foreign Wars",
    "wof:placetype":"venue"
},
  "geometry": {"coordinates":[-71.15216599999999,42.415031],"type":"Point"}
}