{
  "type": "Feature",
  "properties": {
    "iso:country":"US",
    "sg:address":"38 Oakes Ave",
    "sg:city":"Southbridge",
    "sg:classifiers":[
        {
            "category":"Health Services",
            "subcategory":"Doctor",
            "type":"Services"
        }
    ],
    "sg:phone":"+1 508 765 9522",
    "sg:postcode":"01550",
    "sg:province":"MA",
    "wof:name":"Lebow Robert MD",
    "wof:placetype":"venue"
},
  "geometry": {"coordinates":[-72.041496,42.077499],"type":"Point"}
}