{
  "type": "Feature",
  "properties": {
    "iso:country":"US",
    "sg:address":"1325 Belmont St",
    "sg:city":"Brockton",
    "sg:classifiers":[
        {
            "category":"Professional",
            "subcategory":"Lawyer & Legal Services",
            "type":"Services"
        }
    ],
    "sg:phone":"+1 508 587 1800",
    "sg:postcode":"02301",
    "sg:province":"MA",
    "sg:tags":[
        "attorney"
    ],
    "wof:name":"REED Adami & Kaiser",
    "wof:placetype":"venue"
},
  "geometry": {"coordinates":[-71.069304,42.057897],"type":"Point"}
}