{
  "type": "Feature",
  "properties": {
    "addr:full": "1325 Belmont St Brockton MA 02301",
    "addr:housenumber": "1325",
    "addr:postcode": "02301",
    "addr:street": "Belmont St",
    "iso:country": "US",
    "sg:address": "1325 Belmont St",
    "sg:city": "Brockton",
    "sg:classifiers": [
      {
        "category": "Professional",
        "subcategory": "Lawyer \u0026 Legal Services",
        "type": "Services"
      }
    ],
    "sg:phone": "+1 508 587 1800",
    "sg:postcode": "02301",
    "sg:province": "MA",
    "sg:tags": [
      "attorney"
    ],
    "wof:name": "REED Adami \u0026 Kaiser",
    "wof:placetype": "venue"
  },
  "geometry": {"coordinates":[-71.069304,42.057897],"type":"Point"}
}
