{
  "type": "Feature",
  "properties": {
    "addr:full":"62 Dexter St Medford MA 02155",
    "addr:housenumber":"62",
    "addr:postcode":"02155",
    "addr:street":"Dexter St",
    "iso:country":"US",
    "sg:address":"62 Dexter St",
    "sg:city":"Medford",
    "sg:classifiers":[
        {
            "category":"Place Of Worship",
            "subcategory":"Church",
            "type":"Public Place"
        },
        {
            "category":"Place Of Worship",
            "type":"Public Place"
        }
    ],
    "sg:phone":"+1 781 391 2908",
    "sg:postcode":"02155",
    "sg:province":"MA",
    "sg:tags":[
        "churches-seventh-day",
        "adventist",
        "christian",
        "churches-advent"
    ],
    "sg:website":"http://www.cambridgesda.org",
    "wof:name":"Cambridge Seventh Day Adventist Church",
    "wof:placetype":"venue"
},
  "geometry": {"coordinates":[-71.101395,42.399436],"type":"Point"}
}