{
  "type": "Feature",
  "properties": {
    "addr:full": "Harvard Square 5 Jfk St Cambridge MA 02138",
    "addr:housenumber": "5",
    "addr:postcode": "02138",
    "addr:street": "Jfk St",
    "iso:country": "US",
    "sg:address": "Harvard Square 5 Jfk St",
    "sg:city": "Cambridge",
    "sg:classifiers": [
      {
        "category": "Shopping",
        "subcategory": "Optician",
        "type": "Retail Goods"
      },
      {
        "category": "Professional",
        "type": "Services"
      }
    ],
    "sg:phone": "+1 617 497 6753",
    "sg:postcode": "02138",
    "sg:province": "MA",
    "sg:tags": [
      "eyewear"
    ],
    "wof:name": "Cambridge Vision Specialists",
    "wof:placetype": "venue"
  },
  "geometry": {"coordinates":[-71.119499,42.37333],"type":"Point"}
}
