{
  "type": "Feature",
  "properties": {
    "addr:full":"36 Williamstown Rd Lanesboro MA 01237",
    "addr:housenumber":"36",
    "addr:postcode":"01237",
    "addr:street":"Williamstown Rd",
    "iso:country":"US",
    "sg:address":"36 Williamstown Rd",
    "sg:city":"Lanesboro",
    "sg:classifiers":[
        {
            "category":"Travel",
            "subcategory":"Hotels & Motels",
            "type":"Entertainment"
        }
    ],
    "sg:phone":"+1 413 443 4752",
    "sg:postcode":"01237",
    "sg:province":"MA",
    "sg:tags":[
        "resort",
        "operation",
        "center",
        "skiing"
    ],
    "wof:name":"Brodie Mountain Ski Area",
    "wof:placetype":"venue"
},
  "geometry": {"coordinates":[-73.231013,42.539774],"type":"Point"}
}