{
  "type": "Feature",
  "properties": {
    "addr:full": "236 Swains Pond Ave Melrose MA 02176",
    "addr:housenumber": "236",
    "addr:postcode": "02176",
    "addr:street": "Swains Pond Ave",
    "iso:country": "US",
    "sg:address": "236 Swains Pond Ave",
    "sg:city": "Melrose",
    "sg:classifiers": [
      {
        "category": "Building \u0026 Trades",
        "subcategory": "Construction",
        "type": "Services"
      },
      {
        "category": "Building \u0026 Trades",
        "subcategory": "Landfill",
        "type": "Services"
      }
    ],
    "sg:phone": "+1 781 324 4668",
    "sg:postcode": "02176",
    "sg:province": "MA",
    "sg:tags": [
      "farm",
      "contractor"
    ],
    "wof:name": "Curly Customs Inc",
    "wof:placetype": "venue"
  },
  "geometry": {"coordinates":[-71.043159,42.447281],"type":"Point"}
}
