{
  "type": "Feature",
  "properties": {
    "iso:country":"US",
    "sg:address":"112 Main St",
    "sg:city":"Medway",
    "sg:classifiers":[
        {
            "category":"Restaurant",
            "type":"Food & Drink"
        }
    ],
    "sg:phone":"+1 508 533 2255",
    "sg:postcode":"02053",
    "sg:province":"MA",
    "wof:name":"Medway Famous Pizza",
    "wof:placetype":"venue"
},
  "geometry": {"coordinates":[-71.416172,42.150186],"type":"Point"}
}