{
  "type": "Feature",
  "properties": {
    "addr:full": "10 High St Boston MA 02110",
    "addr:housenumber": "10",
    "addr:postcode": "02110",
    "addr:street": "High St",
    "iso:country": "US",
    "sg:address": "10 High St",
    "sg:city": "Boston",
    "sg:classifiers": [
      {
        "category": "Professional",
        "subcategory": "Management \u0026 Consulting",
        "type": "Services"
      }
    ],
    "sg:phone": "+1 617 278 9600",
    "sg:postcode": "02110",
    "sg:province": "MA",
    "sg:tags": [
      "marketing",
      "consultant"
    ],
    "wof:name": "Chartic LLC",
    "wof:placetype": "venue"
  },
  "geometry": {"coordinates":[-71.056378,42.353587],"type":"Point"}
}
