{
  "type": "Feature",
  "properties": {
    "iso:country":"US",
    "sg:address":"148 Main St",
    "sg:city":"Great Barrington",
    "sg:classifiers":[
        {
            "category":"Restaurant",
            "type":"Food & Drink"
        }
    ],
    "sg:phone":"+1 413 528 4500",
    "sg:postcode":"01230",
    "sg:province":"MA",
    "sg:tags":[
        "caterer"
    ],
    "wof:name":"Moore Fine Food Inc",
    "wof:placetype":"venue"
},
  "geometry": {"coordinates":[-73.360968,42.198752],"type":"Point"}
}