{
  "type": "Feature",
  "properties": {
    "iso:country":"US",
    "sg:address":"16 Roundwood Rd",
    "sg:city":"Natick",
    "sg:classifiers":[
        {
            "category":"Building & Trades",
            "subcategory":"Landscaping Services",
            "type":"Services"
        }
    ],
    "sg:phone":"+1 508 655 1413",
    "sg:postcode":"01760",
    "sg:province":"MA",
    "sg:tags":[
        "landscape",
        "contractor"
    ],
    "wof:name":"Joe Indresano",
    "wof:placetype":"venue"
},
  "geometry": {"coordinates":[-71.344984,42.295963],"type":"Point"}
}