{
  "type": "Feature",
  "properties": {
    "iso:country":"US",
    "sg:address":"257 Middlesex Ave",
    "sg:city":"Wilmington",
    "sg:classifiers":[
        {
            "category":"Retail",
            "subcategory":"Pet Boarding",
            "type":"Services"
        }
    ],
    "sg:phone":"+1 978 657 5665",
    "sg:postcode":"01887",
    "sg:province":"MA",
    "sg:tags":[
        "boarding/pet",
        "sitting"
    ],
    "wof:name":"Shear Delight",
    "wof:placetype":"venue"
},
  "geometry": {"coordinates":[-71.1604,42.561401],"type":"Point"}
}