{
  "type": "Feature",
  "properties": {
    "addr:full": "Huntington Ave Boston MA 02115",
    "addr:postcode": "02115",
    "addr:street": "Huntington Ave",
    "iso:country": "US",
    "sg:address": "Huntington Ave",
    "sg:city": "Boston",
    "sg:classifiers": [
      {
        "category": "Personal",
        "subcategory": "Shoe Repair \u0026 Shine",
        "type": "Services"
      }
    ],
    "sg:phone": "+1 617 421 1930",
    "sg:postcode": "02115",
    "sg:province": "MA",
    "sg:tags": [
      "sunglass"
    ],
    "sg:website": "http://www.sunglasshut.com",
    "wof:name": "Sunglass Hut",
    "wof:placetype": "venue"
  },
  "geometry": {"coordinates":[-71.09708,42.337194],"type":"Point"}
}
