{
  "type": "Feature",
  "properties": {
    "iso:country":"US",
    "sg:address":"4 Business Way",
    "sg:city":"Hopedale",
    "sg:classifiers":[
        {
            "category":"Manufacturing",
            "subcategory":"Tools & Machinery",
            "type":"Manufacturing & Wholesale Goods"
        }
    ],
    "sg:phone":"+1 508 478 0111",
    "sg:postcode":"01747",
    "sg:province":"MA",
    "sg:tags":[
        "machine",
        "shop"
    ],
    "sg:website":"www.iso-tech.com",
    "wof:name":"Isolation Technologies Inc",
    "wof:placetype":"venue"
},
  "geometry": {"coordinates":[-71.505501,42.103701],"type":"Point"}
}