{
  "type": "Feature",
  "properties": {
    "iso:country":"US",
    "sg:address":"73 Center St",
    "sg:city":"Hyannis",
    "sg:classifiers":[
        {
            "category":"Insurance",
            "subcategory":"Health Insurance",
            "type":"Services"
        }
    ],
    "sg:phone":"+1 508 775 2905",
    "sg:postcode":"02601",
    "sg:province":"MA",
    "sg:tags":[
        "market"
    ],
    "wof:name":"Consumer Nutrition",
    "wof:placetype":"venue"
},
  "geometry": {"coordinates":[-70.281747,41.655889],"type":"Point"}
}