{
  "type": "Feature",
  "properties": {
    "addr:full":"59 N Main St Middleboro MA 02346",
    "addr:housenumber":"59",
    "addr:postcode":"02346",
    "addr:street":"N Main St",
    "iso:country":"US",
    "sg:address":"59 N Main St",
    "sg:city":"Middleboro",
    "sg:classifiers":[
        {
            "category":"Personal",
            "subcategory":"Beauty Salon",
            "type":"Services"
        }
    ],
    "sg:phone":"+1 508 947 1500",
    "sg:postcode":"02346",
    "sg:province":"MA",
    "wof:name":"Otto's Hair Styles",
    "wof:placetype":"venue"
},
  "geometry": {"coordinates":[-70.907967,41.893269],"type":"Point"}
}