{
  "type": "Feature",
  "properties": {
    "addr:full":"436 Washington St Gloucester MA 01930",
    "addr:housenumber":"436",
    "addr:postcode":"01930",
    "addr:street":"Washington St",
    "iso:country":"US",
    "sg:address":"436 Washington St",
    "sg:city":"Gloucester",
    "sg:classifiers":[
        {
            "category":"Place Of Worship",
            "subcategory":"Church",
            "type":"Public Place"
        },
        {
            "category":"Place Of Worship",
            "type":"Public Place"
        }
    ],
    "sg:phone":"+1 978 281 1040",
    "sg:postcode":"01930",
    "sg:province":"MA",
    "sg:tags":[
        "churches-methodist"
    ],
    "wof:name":"Gloucester United Mthdst Chr",
    "wof:placetype":"venue"
},
  "geometry": {"coordinates":[-70.67532,42.634109],"type":"Point"}
}