{
  "type": "Feature",
  "properties": {
    "iso:country":"US",
    "sg:address":"21 Old Orchard Rd",
    "sg:city":"Shutesbury",
    "sg:classifiers":[
        {
            "category":"Manufacturing",
            "subcategory":"Printing",
            "type":"Manufacturing & Wholesale Goods"
        }
    ],
    "sg:phone":"+1 413 259 2070",
    "sg:postcode":"01072",
    "sg:province":"MA",
    "sg:tags":[
        "printer"
    ],
    "wof:name":"Print Associates",
    "wof:placetype":"venue"
},
  "geometry": {"coordinates":[-72.421891,42.481654],"type":"Point"}
}