{
  "type": "Feature",
  "properties": {
    "iso:country":"US",
    "sg:address":"32 Rayber Rd",
    "sg:city":"Orleans",
    "sg:classifiers":[
        {
            "category":"Building & Trades",
            "subcategory":"Construction",
            "type":"Services"
        }
    ],
    "sg:phone":"+1 508 240 0668",
    "sg:postcode":"02653",
    "sg:province":"MA",
    "sg:tags":[
        "general",
        "contractor"
    ],
    "wof:name":"John D Martin Excavating",
    "wof:placetype":"venue"
},
  "geometry": {"coordinates":[-69.99152599999999,41.774257],"type":"Point"}
}