{
  "type": "Feature",
  "properties": {
    "iso:country":"US",
    "sg:address":"28 Roxbury Dr",
    "sg:city":"Littleton",
    "sg:classifiers":[
        {
            "category":"Professional",
            "subcategory":"Management & Consulting",
            "type":"Services"
        }
    ],
    "sg:phone":"+1 978 486 4646",
    "sg:postcode":"01460",
    "sg:province":"MA",
    "sg:tags":[
        "marketing",
        "program"
    ],
    "wof:name":"Bob Hill Marketing Writer",
    "wof:placetype":"venue"
},
  "geometry": {"coordinates":[-71.465074,42.529844],"type":"Point"}
}