{
  "type": "Feature",
  "properties": {
    "iso:country":"US",
    "sg:address":"373 Winchester St",
    "sg:city":"Newton",
    "sg:classifiers":[
        {
            "category":"Building & Trades",
            "subcategory":"Equipment Rental",
            "type":"Services"
        }
    ],
    "sg:phone":"+1 617 969 6464",
    "sg:postcode":"02461",
    "sg:province":"MA",
    "sg:tags":[
        "crane"
    ],
    "wof:name":"Pick Crane Svc",
    "wof:placetype":"venue"
},
  "geometry": {"coordinates":[-71.206216,42.30716],"type":"Point"}
}