{
  "type": "Feature",
  "properties": {
    "iso:country":"US",
    "sg:address":"59 Court St",
    "sg:city":"Plymouth",
    "sg:classifiers":[
        {
            "category":"Banks & Credit Unions",
            "subcategory":"Financial Services",
            "type":"Services"
        }
    ],
    "sg:phone":"+1 508 747 5780",
    "sg:postcode":"02360",
    "sg:province":"MA",
    "sg:tags":[
        "educational",
        "plan",
        "scholarship"
    ],
    "wof:name":"College Funding & Sport Schlr",
    "wof:placetype":"venue"
},
  "geometry": {"coordinates":[-70.667429,41.958532],"type":"Point"}
}