{
  "type": "Feature",
  "properties": {
    "iso:country":"US",
    "sg:address":"30 Rowes Wharf",
    "sg:city":"Boston",
    "sg:classifiers":[
        {
            "category":"Professional",
            "subcategory":"Lawyer & Legal Services",
            "type":"Services"
        }
    ],
    "sg:phone":"+1 617 737 3000",
    "sg:postcode":"02110",
    "sg:province":"MA",
    "sg:tags":[
        "attorney"
    ],
    "wof:name":"Arthur Levine Assoc",
    "wof:placetype":"venue"
},
  "geometry": {"coordinates":[-71.049859,42.357149],"type":"Point"}
}