{
  "type": "Feature",
  "properties": {
    "addr:full":"15 Page Ter Stoughton MA 02072",
    "addr:housenumber":"15",
    "addr:postcode":"02072",
    "addr:street":"Page Ter",
    "iso:country":"US",
    "sg:address":"15 Page Ter",
    "sg:city":"Stoughton",
    "sg:classifiers":[
        {
            "category":"Banks & Credit Unions",
            "subcategory":"Bank",
            "type":"Services"
        }
    ],
    "sg:phone":"+1 781 344 0329",
    "sg:postcode":"02072",
    "sg:province":"MA",
    "sg:tags":[
        "loan",
        "real estate"
    ],
    "wof:name":"Patriot Closing",
    "wof:placetype":"venue"
},
  "geometry": {"coordinates":[-71.076095,42.151156],"type":"Point"}
}