{
  "type": "Feature",
  "properties": {
    "addr:full": "44 Staten Rd Braintree MA 02184",
    "addr:housenumber": "44",
    "addr:postcode": "02184",
    "addr:street": "Staten Rd",
    "iso:country": "US",
    "sg:address": "44 Staten Rd",
    "sg:city": "Braintree",
    "sg:classifiers": [
      {
        "category": "Building \u0026 Trades",
        "subcategory": "Construction",
        "type": "Services"
      }
    ],
    "sg:phone": "+1 781 843 2702",
    "sg:postcode": "02184",
    "sg:province": "MA",
    "sg:tags": [
      "resurfacing",
      "refinishing",
      "floor"
    ],
    "wof:name": "Dan's Floor Svc",
    "wof:placetype": "venue"
  },
  "geometry": {"coordinates":[-71.006025,42.223862],"type":"Point"}
}
