{
  "type": "Feature",
  "properties": {
    "iso:country":"US",
    "sg:address":"44 Staten Rd",
    "sg:city":"Braintree",
    "sg:classifiers":[
        {
            "category":"Building & Trades",
            "subcategory":"Construction",
            "type":"Services"
        }
    ],
    "sg:phone":"+1 781 843 2702",
    "sg:postcode":"02184",
    "sg:province":"MA",
    "sg:tags":[
        "resurfacing",
        "refinishing",
        "floor"
    ],
    "wof:name":"Dan's Floor Svc",
    "wof:placetype":"venue"
},
  "geometry": {"coordinates":[-71.00602499999999,42.223862],"type":"Point"}
}