{
  "type": "Feature",
  "properties": {
    "addr:full": "707 Broadway Somerville MA 02144",
    "addr:housenumber": "707",
    "addr:postcode": "02144",
    "addr:street": "Broadway",
    "iso:country": "US",
    "sg:address": "707 Broadway",
    "sg:city": "Somerville",
    "sg:classifiers": [
      {
        "category": "Building \u0026 Trades",
        "subcategory": "Locksmith",
        "type": "Services"
      }
    ],
    "sg:phone": "+1 617 625 5625",
    "sg:postcode": "02144",
    "sg:province": "MA",
    "sg:tags": [
      "key"
    ],
    "wof:name": "Cambridge Lock",
    "wof:placetype": "venue"
  },
  "geometry": {"coordinates":[-71.112311,42.399834],"type":"Point"}
}
