{
  "type": "Feature",
  "properties": {
    "iso:country":"US",
    "sg:address":"707 Broadway",
    "sg:city":"Somerville",
    "sg:classifiers":[
        {
            "category":"Building & Trades",
            "subcategory":"Locksmith",
            "type":"Services"
        }
    ],
    "sg:phone":"+1 617 625 5625",
    "sg:postcode":"02144",
    "sg:province":"MA",
    "sg:tags":[
        "key"
    ],
    "wof:name":"Cambridge Lock",
    "wof:placetype":"venue"
},
  "geometry": {"coordinates":[-71.11231100000001,42.399834],"type":"Point"}
}