{
  "type": "Feature",
  "properties": {
    "iso:country":"US",
    "sg:address":"390 Cooley St",
    "sg:city":"Springfield",
    "sg:classifiers":[
        {
            "category":"Shopping",
            "subcategory":"Department Store",
            "type":"Retail Goods"
        },
        {
            "category":"Shopping",
            "subcategory":"Clothing, Apparel, & Fashions",
            "type":"Retail Goods"
        }
    ],
    "sg:phone":"+1 413 426 9527",
    "sg:postcode":"01128",
    "sg:province":"MA",
    "sg:tags":[
        "clothing"
    ],
    "sg:website":"http://www.burlingtoncoatfactory.com",
    "wof:name":"Burlington Coat Factory",
    "wof:placetype":"venue"
},
  "geometry": {"coordinates":[-72.499262,42.093125],"type":"Point"}
}