{
  "type": "Feature",
  "properties": {
    "addr:full": "161 State St Newburyport MA 01950",
    "addr:housenumber": "161",
    "addr:postcode": "01950",
    "addr:street": "State St",
    "iso:country": "US",
    "sg:address": "161 State St",
    "sg:city": "Newburyport",
    "sg:classifiers": [
      {
        "category": "Building \u0026 Trades",
        "subcategory": "Construction",
        "type": "Services"
      }
    ],
    "sg:phone": "+1 978 465 4154",
    "sg:postcode": "01950",
    "sg:province": "MA",
    "sg:tags": [
      "interior",
      "design"
    ],
    "wof:name": "Matisse Interiors",
    "wof:placetype": "venue"
  },
  "geometry": {"coordinates":[-70.8742,42.8003],"type":"Point"}
}
