{
  "type": "Feature",
  "properties": {
    "addr:full": "248 Cottage St Chelsea MA 02150",
    "addr:housenumber": "248",
    "addr:postcode": "02150",
    "addr:street": "Cottage St",
    "iso:country": "US",
    "sg:address": "248 Cottage St",
    "sg:city": "Chelsea",
    "sg:classifiers": [
      {
        "category": "Building \u0026 Trades",
        "subcategory": "Locksmith",
        "type": "Services"
      }
    ],
    "sg:phone": "+1 617 819 3418",
    "sg:postcode": "02150",
    "sg:province": "MA",
    "sg:tags": [
      "key"
    ],
    "wof:name": "Locksmith On Cottage 123 24 A Day Emergency",
    "wof:placetype": "venue"
  },
  "geometry": {"coordinates":[-71.024168,42.389825],"type":"Point"}
}
