{
  "type": "Feature",
  "properties": {
    "iso:country":"US",
    "sg:address":"248 Cottage St",
    "sg:city":"Chelsea",
    "sg:classifiers":[
        {
            "category":"Building & Trades",
            "subcategory":"Locksmith",
            "type":"Services"
        }
    ],
    "sg:phone":"+1 617 819 3418",
    "sg:postcode":"02150",
    "sg:province":"MA",
    "sg:tags":[
        "key"
    ],
    "wof:name":"Locksmith On Cottage 123 24 A Day Emergency",
    "wof:placetype":"venue"
},
  "geometry": {"coordinates":[-71.024168,42.389825],"type":"Point"}
}