{
  "type": "Feature",
  "properties": {
    "addr:full":"8 Cedar Rd Andover MA 01810",
    "addr:housenumber":"8",
    "addr:postcode":"01810",
    "addr:street":"Cedar Rd",
    "iso:country":"US",
    "sg:address":"8 Cedar Rd",
    "sg:city":"Andover",
    "sg:classifiers":[
        {
            "category":"Building & Trades",
            "subcategory":"Construction",
            "type":"Services"
        }
    ],
    "sg:phone":"+1 978 470 0492",
    "sg:postcode":"01810",
    "sg:province":"MA",
    "sg:tags":[
        "general",
        "contractor"
    ],
    "wof:name":"Lasting Impressions Design",
    "wof:placetype":"venue"
},
  "geometry": {"coordinates":[-71.137083,42.66437],"type":"Point"}
}