{
  "type": "Feature",
  "properties": {
    "addr:full":"635 Main St Great Barrington MA 01230",
    "addr:housenumber":"635",
    "addr:postcode":"01230",
    "addr:street":"Main St",
    "iso:country":"US",
    "sg:address":"635 Main St",
    "sg:city":"Great Barrington",
    "sg:classifiers":[
        {
            "category":"Shopping",
            "subcategory":"Gifts & Souvenirs",
            "type":"Retail Goods"
        }
    ],
    "sg:phone":"+1 413 528 9327",
    "sg:postcode":"01230",
    "sg:province":"MA",
    "sg:tags":[
        "shop"
    ],
    "wof:name":"Urban Country",
    "wof:placetype":"venue"
},
  "geometry": {"coordinates":[-73.364496,42.182359],"type":"Point"}
}