{
  "type": "Feature",
  "properties": {
    "addr:full": "4 Holcomb St Westfield MA 01085",
    "addr:housenumber": "4",
    "addr:postcode": "01085",
    "addr:street": "Holcomb St",
    "iso:country": "US",
    "sg:address": "4 Holcomb St",
    "sg:city": "Westfield",
    "sg:classifiers": [
      {
        "category": "Recreation",
        "type": "Entertainment"
      }
    ],
    "sg:phone": "+1 413 572 6263",
    "sg:postcode": "01085",
    "sg:province": "MA",
    "sg:tags": [
      "parks"
    ],
    "wof:name": "Westfield Park \u0026 Recreation",
    "wof:placetype": "venue"
  },
  "geometry": {"coordinates":[-72.756875,42.119012],"type":"Point"}
}
