{
  "type": "Feature",
  "properties": {
    "iso:country":"US",
    "sg:address":"4 Holcomb St",
    "sg:city":"Westfield",
    "sg:classifiers":[
        {
            "category":"Recreation",
            "type":"Entertainment"
        }
    ],
    "sg:phone":"+1 413 572 6263",
    "sg:postcode":"01085",
    "sg:province":"MA",
    "sg:tags":[
        "parks"
    ],
    "wof:name":"Westfield Park & Recreation",
    "wof:placetype":"venue"
},
  "geometry": {"coordinates":[-72.75687499999999,42.119012],"type":"Point"}
}