{
  "type": "Feature",
  "properties": {
    "iso:country":"US",
    "sg:address":"20 Harrington St",
    "sg:city":"Teaticket",
    "sg:classifiers":[
        {
            "category":"Manufacturing",
            "subcategory":"Buildings",
            "type":"Manufacturing & Wholesale Goods"
        },
        {
            "category":"Structure",
            "subcategory":"Warehouse",
            "type":"Public Place"
        },
        {
            "category":"Building & Trades",
            "subcategory":"Construction",
            "type":"Services"
        }
    ],
    "sg:phone":"+1 508 548 1399",
    "sg:postcode":"02536",
    "sg:province":"MA",
    "sg:tags":[
        "warehouses-merchandise",
        "warehouses-public-commercial",
        "builder",
        "carpenter",
        "contractor",
        "home"
    ],
    "wof:name":"Bilodea Stephen Carpentary",
    "wof:placetype":"venue"
},
  "geometry": {"coordinates":[-70.59041999999999,41.55978],"type":"Point"}
}