{
  "type": "Feature",
  "properties": {
    "addr:full":"488 Northfield Rd Bernardston MA 01337",
    "addr:housenumber":"488",
    "addr:postcode":"01337",
    "addr:street":"Northfield Rd",
    "iso:country":"US",
    "sg:address":"488 Northfield Rd",
    "sg:city":"Bernardston",
    "sg:classifiers":[
        {
            "category":"Wholesale",
            "subcategory":"Farm Supplies",
            "type":"Manufacturing & Wholesale Goods"
        }
    ],
    "sg:phone":"+1 413 648 9254",
    "sg:postcode":"01337",
    "sg:province":"MA",
    "sg:website":"www.feedcommodities.com",
    "wof:name":"Feed Commodities Intl Inc",
    "wof:placetype":"venue"
},
  "geometry": {"coordinates":[-72.496138,42.676428],"type":"Point"}
}