{
  "type": "Feature",
  "properties": {
    "addr:full":"266 Cambridge St Burlington MA 01803",
    "addr:housenumber":"266",
    "addr:postcode":"01803",
    "addr:street":"Cambridge St",
    "iso:country":"US",
    "sg:address":"266 Cambridge St",
    "sg:city":"Burlington",
    "sg:classifiers":[
        {
            "category":"Shopping",
            "subcategory":"Jewelry",
            "type":"Retail Goods"
        },
        {
            "category":"Retail",
            "subcategory":"Repair Shop",
            "type":"Services"
        }
    ],
    "sg:phone":"+1 781 272 7702",
    "sg:postcode":"01803",
    "sg:province":"MA",
    "sg:tags":[
        "watch"
    ],
    "sg:website":"brahimsjewelry.googlepages.com",
    "wof:name":"Brahim's Jewelry",
    "wof:placetype":"venue"
},
  "geometry": {"coordinates":[-71.20364499999999,42.514416],"type":"Point"}
}