{
  "type": "Feature",
  "properties": {
    "iso:country":"US",
    "sg:address":"7 Pleasant St",
    "sg:city":"Marblehead",
    "sg:classifiers":[
        {
            "category":"Professional",
            "type":"Services"
        }
    ],
    "sg:phone":"+1 781 639 4900",
    "sg:postcode":"01945",
    "sg:province":"MA",
    "sg:tags":[
        "establishment"
    ],
    "wof:name":"Babe",
    "wof:placetype":"venue"
},
  "geometry": {"coordinates":[-70.852796,42.504399],"type":"Point"}
}