{
  "type": "Feature",
  "properties": {
    "iso:country":"US",
    "sg:address":"45 Junction Square Dr",
    "sg:city":"Concord",
    "sg:classifiers":[
        {
            "category":"Professional",
            "subcategory":"Accounting & Tax Preparation",
            "type":"Services"
        }
    ],
    "sg:phone":"+1 978 369 4830",
    "sg:postcode":"01742",
    "sg:province":"MA",
    "sg:tags":[
        "accountant"
    ],
    "wof:name":"Dickson Lisa M CPA",
    "wof:placetype":"venue"
},
  "geometry": {"coordinates":[-71.39589700000001,42.456299],"type":"Point"}
}