{
  "type": "Feature",
  "properties": {
    "addr:full":"82 Broad St Suite 103 Westfield MA 01085",
    "addr:housenumber":"82;103",
    "addr:postcode":"01085",
    "addr:street":"Broad St Suite",
    "iso:country":"US",
    "sg:address":"82 Broad St Suite 103",
    "sg:city":"Westfield",
    "sg:classifiers":[
        {
            "category":"Professional",
            "subcategory":"Lawyer & Legal Services",
            "type":"Services"
        }
    ],
    "sg:phone":"+1 413 485 7666",
    "sg:postcode":"01085",
    "sg:province":"MA",
    "sg:tags":[
        "attorney",
        "practice",
        "business",
        "law"
    ],
    "sg:website":"http://www.murphyslaw3.com",
    "wof:name":"Law Offices of David M. Murphy",
    "wof:placetype":"venue"
},
  "geometry": {"coordinates":[-72.74751999999999,42.11515],"type":"Point"}
}