{
  "type": "Feature",
  "properties": {
    "addr:full": "350 Park St North Reading MA 01864",
    "addr:housenumber": "350",
    "addr:postcode": "01864",
    "addr:street": "Park St",
    "iso:country": "US",
    "sg:address": "350 Park St",
    "sg:city": "North Reading",
    "sg:classifiers": [
      {
        "category": "Banks \u0026 Credit Unions",
        "subcategory": "Bank",
        "type": "Services"
      }
    ],
    "sg:phone": "+1 978 664 6480",
    "sg:postcode": "01864",
    "sg:province": "MA",
    "sg:tags": [
      "loan",
      "real estate"
    ],
    "wof:name": "WFP Mortgage Inc",
    "wof:placetype": "venue"
  },
  "geometry": {"coordinates":[-71.10979,42.564724],"type":"Point"}
}
