{
  "type": "Feature",
  "properties": {
    "iso:country":"US",
    "sg:address":"25 Stow Rd",
    "sg:city":"Acton",
    "sg:classifiers":[
        {
            "category":"Health Services",
            "subcategory":"Health Practitioner",
            "type":"Services"
        },
        {
            "category":"Health Services",
            "subcategory":"Doctor",
            "type":"Services"
        }
    ],
    "sg:phone":"+1 978 263 4026",
    "sg:postcode":"01719",
    "sg:province":"MA",
    "sg:tags":[
        "acupuncture",
        "medical"
    ],
    "wof:name":"Boxboro Acupuncture",
    "wof:placetype":"venue"
},
  "geometry": {"coordinates":[-71.516108,42.472951],"type":"Point"}
}