{
  "type": "Feature",
  "properties": {
    "addr:full":"71 Whitney St Holliston MA 01746",
    "addr:housenumber":"71",
    "addr:postcode":"01746",
    "addr:street":"Whitney St",
    "iso:country":"US",
    "sg:address":"71 Whitney St",
    "sg:city":"Holliston",
    "sg:classifiers":[
        {
            "category":"Building & Trades",
            "subcategory":"Plumbing",
            "type":"Services"
        }
    ],
    "sg:phone":"+1 508 429 9589",
    "sg:postcode":"01746",
    "sg:province":"MA",
    "sg:tags":[
        "plumbing",
        "contractor"
    ],
    "wof:name":"Rodenheiser Co Plumbing",
    "wof:placetype":"venue"
},
  "geometry": {"coordinates":[-71.406577,42.215536],"type":"Point"}
}