{
  "type": "Feature",
  "properties": {
    "iso:country":"US",
    "sg:address":"63 Fairbanks Ave",
    "sg:city":"Wellesley Hills",
    "sg:classifiers":[
        {
            "category":"Professional",
            "subcategory":"Research",
            "type":"Services"
        }
    ],
    "sg:phone":"+1 781 431 8509",
    "sg:postcode":"02481",
    "sg:province":"MA",
    "sg:website":"www.roiexpert.com",
    "wof:name":"Nucleus Research Inc",
    "wof:placetype":"venue"
},
  "geometry": {"coordinates":[-71.258476,42.318964],"type":"Point"}
}