{
  "type": "Feature",
  "properties": {
    "addr:full": "378 Maple Ave Shrewsbury MA 01545",
    "addr:housenumber": "378",
    "addr:postcode": "01545",
    "addr:street": "Maple Ave",
    "iso:country": "US",
    "sg:address": "378 Maple Ave",
    "sg:city": "Shrewsbury",
    "sg:classifiers": [
      {
        "category": "Restaurant",
        "type": "Food \u0026 Drink"
      }
    ],
    "sg:phone": "+1 508 799 2255",
    "sg:postcode": "01545",
    "sg:province": "MA",
    "sg:tags": [
      "eating"
    ],
    "wof:name": "Star India",
    "wof:placetype": "venue"
  },
  "geometry": {"coordinates":[-71.737576,42.276018],"type":"Point"}
}
