{
  "type": "Feature",
  "properties": {
    "addr:full":"34 Hurd St Lowell MA 01852",
    "addr:housenumber":"34",
    "addr:postcode":"01852",
    "addr:street":"Hurd St",
    "iso:country":"US",
    "sg:address":"34 Hurd St",
    "sg:city":"Lowell",
    "sg:classifiers":[
        {
            "category":"Organizations",
            "subcategory":"Religious Organization",
            "type":"Services"
        }
    ],
    "sg:phone":"+1   ",
    "sg:postcode":"01852",
    "sg:province":"MA",
    "wof:name":"Saint Puls Untd Methdst Church",
    "wof:placetype":"venue"
},
  "geometry": {"coordinates":[-71.30643499999999,42.642793],"type":"Point"}
}