{
  "type": "Feature",
  "properties": {
    "iso:country":"US",
    "sg:address":"15 Pleasant St Con",
    "sg:city":"Framingham",
    "sg:classifiers":[
        {
            "category":"Professional",
            "subcategory":"Management & Consulting",
            "type":"Services"
        }
    ],
    "sg:phone":"+1 508 370 3147",
    "sg:postcode":"01701",
    "sg:province":"MA",
    "sg:tags":[
        "marketing",
        "program"
    ],
    "sg:website":"www.genzymetreatmentcenters.com",
    "wof:name":"Genzyme Molecular Oncology",
    "wof:placetype":"venue"
},
  "geometry": {"coordinates":[-71.49032200000001,42.297625],"type":"Point"}
}