{
  "type": "Feature",
  "properties": {
    "addr:full": "183 Cambridge St Allston MA 02134",
    "addr:housenumber": "183",
    "addr:postcode": "02134",
    "addr:street": "Cambridge St",
    "iso:country": "US",
    "sg:address": "183 Cambridge St",
    "sg:city": "Allston",
    "sg:classifiers": [
      {
        "category": "Professional",
        "subcategory": "Advertising",
        "type": "Services"
      }
    ],
    "sg:phone": "+1 617 783 2244",
    "sg:postcode": "02134",
    "sg:province": "MA",
    "sg:tags": [
      "distribution"
    ],
    "wof:name": "S \u0026 A Distribution",
    "wof:placetype": "venue"
  },
  "geometry": {"coordinates":[-71.12433,42.358724],"type":"Point"}
}
