{
  "type": "Feature",
  "properties": {
    "iso:country":"US",
    "sg:address":"183 Cambridge St",
    "sg:city":"Allston",
    "sg:classifiers":[
        {
            "category":"Professional",
            "subcategory":"Advertising",
            "type":"Services"
        }
    ],
    "sg:phone":"+1 617 783 2244",
    "sg:postcode":"02134",
    "sg:province":"MA",
    "sg:tags":[
        "distribution"
    ],
    "wof:name":"S & A Distribution",
    "wof:placetype":"venue"
},
  "geometry": {"coordinates":[-71.12433,42.358724],"type":"Point"}
}