{
  "type": "Feature",
  "properties": {
    "addr:full":"23 Pineview Trl Auburn MA 01501",
    "addr:housenumber":"23",
    "addr:postcode":"01501",
    "addr:street":"Pineview Trl",
    "iso:country":"US",
    "sg:address":"23 Pineview Trl",
    "sg:city":"Auburn",
    "sg:classifiers":[
        {
            "category":"Professional",
            "subcategory":"Business Services",
            "type":"Services"
        }
    ],
    "sg:phone":"+1   ",
    "sg:postcode":"01501",
    "sg:province":"MA",
    "sg:tags":[
        "fire",
        "inspector"
    ],
    "wof:name":"John F Callio Inc",
    "wof:placetype":"venue"
},
  "geometry": {"coordinates":[-71.83153900000001,42.225501],"type":"Point"}
}