{
  "type": "Feature",
  "properties": {
    "iso:country":"US",
    "sg:address":"45 Riverside Ave",
    "sg:city":"Medford",
    "sg:classifiers":[
        {
            "category":"Banks & Credit Unions",
            "subcategory":"Bank",
            "type":"Services"
        }
    ],
    "sg:phone":"+1 617 666 4700",
    "sg:postcode":"02155",
    "sg:province":"MA",
    "wof:name":"Middlesex Federal Savings FA",
    "wof:placetype":"venue"
},
  "geometry": {"coordinates":[-71.107671,42.417588],"type":"Point"}
}