{
  "type": "Feature",
  "properties": {
    "addr:full": "163 Bay State Dr Braintree MA 02184",
    "addr:housenumber": "163",
    "addr:postcode": "02184",
    "addr:street": "Bay State Dr",
    "iso:country": "US",
    "sg:address": "163 Bay State Dr",
    "sg:city": "Braintree",
    "sg:classifiers": [
      {
        "category": "Shopping",
        "type": "Retail Goods"
      }
    ],
    "sg:phone": "+1 781 380 4800",
    "sg:postcode": "02184",
    "sg:province": "MA",
    "sg:tags": [
      "equipment",
      "telephone",
      "supply"
    ],
    "sg:website": "www.compel.com",
    "wof:name": "Mahon Communications Corp",
    "wof:placetype": "venue"
  },
  "geometry": {"coordinates":[-71.027898,42.200244],"type":"Point"}
}
