{
  "type": "Feature",
  "properties": {
    "iso:country":"US",
    "sg:address":"163 Bay State Dr",
    "sg:city":"Braintree",
    "sg:classifiers":[
        {
            "category":"Shopping",
            "type":"Retail Goods"
        }
    ],
    "sg:phone":"+1 781 380 4800",
    "sg:postcode":"02184",
    "sg:province":"MA",
    "sg:tags":[
        "equipment",
        "telephone",
        "supply"
    ],
    "sg:website":"www.compel.com",
    "wof:name":"Mahon Communications Corp",
    "wof:placetype":"venue"
},
  "geometry": {"coordinates":[-71.02789799999999,42.200244],"type":"Point"}
}