{
  "type": "Feature",
  "properties": {
    "iso:country":"US",
    "sg:address":"195 Westgate Dr",
    "sg:city":"Brockton",
    "sg:classifiers":[
        {
            "category":"Restaurant",
            "type":"Food & Drink"
        }
    ],
    "sg:phone":"+1 508 559 0008",
    "sg:postcode":"02301",
    "sg:province":"MA",
    "sg:tags":[
        "seafood"
    ],
    "wof:name":"The Grill",
    "wof:placetype":"venue"
},
  "geometry": {"coordinates":[-71.04958000000001,42.094492],"type":"Point"}
}