{
  "type": "Feature",
  "properties": {
    "iso:country":"US",
    "sg:address":"91 Newman Rd",
    "sg:city":"Malden",
    "sg:classifiers":[
        {
            "category":"Building & Trades",
            "subcategory":"Locksmith",
            "type":"Services"
        }
    ],
    "sg:phone":"+1 617 714 1100",
    "sg:postcode":"02148",
    "sg:province":"MA",
    "sg:tags":[
        "key"
    ],
    "wof:name":"George Locksmith",
    "wof:placetype":"venue"
},
  "geometry": {"coordinates":[-71.070582,42.415961],"type":"Point"}
}