{
  "type": "Feature",
  "properties": {
    "iso:country":"US",
    "sg:address":"6 Lewis Ct",
    "sg:city":"Gloucester",
    "sg:classifiers":[
        {
            "category":"Government",
            "subcategory":"Office",
            "type":"Public Place"
        }
    ],
    "sg:phone":"+1 978 281 9765",
    "sg:postcode":"01930",
    "sg:province":"MA",
    "sg:tags":[
        "city",
        "resource",
        "human"
    ],
    "wof:name":"Gloucester Council On Aging",
    "wof:placetype":"venue"
},
  "geometry": {"coordinates":[-70.66934000000001,42.610667],"type":"Point"}
}