{
  "type": "Feature",
  "properties": {
    "addr:full": "6 Lewis Ct Gloucester MA 01930",
    "addr:housenumber": "6",
    "addr:postcode": "01930",
    "addr:street": "Lewis Ct",
    "iso:country": "US",
    "sg:address": "6 Lewis Ct",
    "sg:city": "Gloucester",
    "sg:classifiers": [
      {
        "category": "Government",
        "subcategory": "Office",
        "type": "Public Place"
      }
    ],
    "sg:phone": "+1 978 281 9765",
    "sg:postcode": "01930",
    "sg:province": "MA",
    "sg:tags": [
      "city",
      "resource",
      "human"
    ],
    "wof:name": "Gloucester Council On Aging",
    "wof:placetype": "venue"
  },
  "geometry": {"coordinates":[-70.66934,42.610667],"type":"Point"}
}
