{
  "type": "Feature",
  "properties": {
    "addr:full":"49 Forest St Manchester MA 01944",
    "addr:housenumber":"49",
    "addr:postcode":"01944",
    "addr:street":"Forest St",
    "iso:country":"US",
    "sg:address":"49 Forest St",
    "sg:city":"Manchester",
    "sg:classifiers":[
        {
            "category":"Shopping",
            "subcategory":"Computers & Home Electronics",
            "type":"Retail Goods"
        }
    ],
    "sg:phone":"+1 978 526 7785",
    "sg:postcode":"01944",
    "sg:province":"MA",
    "sg:tags":[
        "parts",
        "supply"
    ],
    "wof:name":"Laser Recycle",
    "wof:placetype":"venue"
},
  "geometry": {"coordinates":[-70.754435,42.583228],"type":"Point"}
}