{
  "type": "Feature",
  "properties": {
    "addr:full":"207 Swansea Mall Dr Swansea MA 02777",
    "addr:housenumber":"207",
    "addr:postcode":"02777",
    "addr:street":"Swansea Mall Dr",
    "iso:country":"US",
    "sg:address":"207 Swansea Mall Dr",
    "sg:city":"Swansea",
    "sg:classifiers":[
        {
            "category":"Restaurant",
            "type":"Food & Drink"
        }
    ],
    "sg:phone":"+1 508 676 8767",
    "sg:postcode":"02777",
    "sg:province":"MA",
    "sg:tags":[
        "eating"
    ],
    "wof:name":"Ping's Swansea Chinese Restaurant",
    "wof:placetype":"venue"
},
  "geometry": {"coordinates":[-71.21526,41.755492],"type":"Point"}
}