{
  "type": "Feature",
  "properties": {
    "iso:country":"US",
    "sg:address":"1183 Walnut St",
    "sg:city":"Newton Highlands",
    "sg:classifiers":[
        {
            "category":"Shopping",
            "subcategory":"Clothing, Apparel, & Fashions",
            "type":"Retail Goods"
        }
    ],
    "sg:phone":"+1 617 581 6530",
    "sg:postcode":"02461",
    "sg:province":"MA",
    "wof:name":"X Hale",
    "wof:placetype":"venue"
},
  "geometry": {"coordinates":[-71.206142,42.321672],"type":"Point"}
}