{
  "type": "Feature",
  "properties": {
    "addr:full":"1428 Dorchester Avenue Dorchester MA 02122",
    "addr:housenumber":"1428",
    "addr:postcode":"02122",
    "addr:street":"Dorchester Avenue",
    "iso:country":"US",
    "sg:address":"1428 Dorchester Avenue",
    "sg:city":"Dorchester",
    "sg:classifiers":[
        {
            "category":"Professional",
            "subcategory":"Lawyer & Legal Services",
            "type":"Services"
        }
    ],
    "sg:phone":"+1 617 265 0025",
    "sg:postcode":"02122",
    "sg:province":"MA",
    "sg:tags":[
        "notary"
    ],
    "wof:name":"Comzer Insurance Agency",
    "wof:placetype":"venue"
},
  "geometry": {"coordinates":[-71.059753,42.302377],"type":"Point"}
}