{
  "type": "Feature",
  "properties": {
    "addr:full": "35 Tripp St Framingham MA 01702",
    "addr:housenumber": "35",
    "addr:postcode": "01702",
    "addr:street": "Tripp St",
    "iso:country": "US",
    "sg:address": "35 Tripp St",
    "sg:city": "Framingham",
    "sg:classifiers": [
      {
        "category": "Real Estate",
        "subcategory": "Real Estate Agent",
        "type": "Services"
      }
    ],
    "sg:phone": "+1 508 872 4864",
    "sg:postcode": "01702",
    "sg:province": "MA",
    "wof:name": "LRT Realty Corp",
    "wof:placetype": "venue"
  },
  "geometry": {"coordinates":[-71.412216,42.268455],"type":"Point"}
}
