{
  "type": "Feature",
  "properties": {
    "iso:country":"US",
    "sg:address":"793 Iyannough Rd",
    "sg:city":"Hyannis",
    "sg:classifiers":[
        {
            "category":"Personal",
            "subcategory":"Beauty Salon",
            "type":"Services"
        }
    ],
    "sg:phone":"+1 508 771 1213",
    "sg:postcode":"02601",
    "sg:province":"MA",
    "wof:name":"Dellaria Salon",
    "wof:placetype":"venue"
},
  "geometry": {"coordinates":[-70.297163,41.66935],"type":"Point"}
}