{
  "type": "Feature",
  "properties": {
    "addr:full": "2306 Washington St Roxbury MA 02119",
    "addr:housenumber": "2306",
    "addr:postcode": "02119",
    "addr:street": "Washington St",
    "iso:country": "US",
    "sg:address": "2306 Washington St",
    "sg:city": "Roxbury",
    "sg:classifiers": [
      {
        "category": "Restaurant",
        "type": "Food \u0026 Drink"
      }
    ],
    "sg:phone": "+1 617 427 7333",
    "sg:postcode": "02119",
    "sg:province": "MA",
    "sg:tags": [
      "mexican",
      "tex-mex"
    ],
    "wof:name": "Tex-Mex Mexican Restaurant",
    "wof:placetype": "venue"
  },
  "geometry": {"coordinates":[-71.083955,42.330166],"type":"Point"}
}
