{
  "type": "Feature",
  "properties": {
    "iso:country":"US",
    "sg:address":"2306 Washington St",
    "sg:city":"Roxbury",
    "sg:classifiers":[
        {
            "category":"Restaurant",
            "type":"Food & Drink"
        }
    ],
    "sg:phone":"+1 617 427 7333",
    "sg:postcode":"02119",
    "sg:province":"MA",
    "sg:tags":[
        "mexican",
        "tex-mex"
    ],
    "wof:name":"Tex-Mex Mexican Restaurant",
    "wof:placetype":"venue"
},
  "geometry": {"coordinates":[-71.083955,42.330166],"type":"Point"}
}