{
  "type": "Feature",
  "properties": {
    "addr:full": "4 Front St Indian Orchard MA 01151",
    "addr:housenumber": "4",
    "addr:postcode": "01151",
    "addr:street": "Front St",
    "iso:country": "US",
    "sg:address": "4 Front St",
    "sg:city": "Indian Orchard",
    "sg:classifiers": [
      {
        "category": "Retail",
        "subcategory": "Auto Repair",
        "type": "Services"
      }
    ],
    "sg:phone": "+1 413 543 5910",
    "sg:postcode": "01151",
    "sg:province": "MA",
    "sg:tags": [
      "repairing",
      "automobile",
      "general"
    ],
    "wof:name": "Little Work Shop",
    "wof:placetype": "venue"
  },
  "geometry": {"coordinates":[-72.50792,42.159879],"type":"Point"}
}
