{
  "type": "Feature",
  "properties": {
    "iso:country":"US",
    "sg:address":"94 Jerusalem Rd",
    "sg:city":"Tyringham",
    "sg:classifiers":[
        {
            "category":"Building & Trades",
            "subcategory":"Landscaping Services",
            "type":"Services"
        }
    ],
    "sg:phone":"+1 413 243 4287",
    "sg:postcode":"01264",
    "sg:province":"MA",
    "sg:tags":[
        "lawn",
        "maintenance",
        "grounds"
    ],
    "wof:name":"Weed Busters",
    "wof:placetype":"venue"
},
  "geometry": {"coordinates":[-73.204634,42.244795],"type":"Point"}
}