{
  "type": "Feature",
  "properties": {
    "addr:full":"67 Bakers Pond Rd Orleans MA 02653",
    "addr:housenumber":"67",
    "addr:postcode":"02653",
    "addr:street":"Bakers Pond Rd",
    "iso:country":"US",
    "sg:address":"67 Bakers Pond Rd",
    "sg:city":"Orleans",
    "sg:classifiers":[
        {
            "category":"Shopping",
            "subcategory":"Pets & Pet Supplies",
            "type":"Retail Goods"
        },
        {
            "category":"Retail",
            "subcategory":"Veterinary Services",
            "type":"Services"
        }
    ],
    "sg:phone":"+1 508 255 2227",
    "sg:postcode":"02653",
    "sg:province":"MA",
    "sg:tags":[
        "specialty"
    ],
    "wof:name":"Anything For Animals",
    "wof:placetype":"venue"
},
  "geometry": {"coordinates":[-70.002763,41.770025],"type":"Point"}
}