{
  "type": "Feature",
  "properties": {
    "addr:full":"15 Oakland St Newburyport MA 01950",
    "addr:housenumber":"15",
    "addr:postcode":"01950",
    "addr:street":"Oakland St",
    "iso:country":"US",
    "sg:address":"15 Oakland St",
    "sg:city":"Newburyport",
    "sg:classifiers":[
        {
            "category":"Professional",
            "subcategory":"Business Services",
            "type":"Services"
        }
    ],
    "sg:phone":"+1   ",
    "sg:postcode":"01950",
    "sg:province":"MA",
    "sg:tags":[
        "translator"
    ],
    "wof:name":"Claudia Dutra",
    "wof:placetype":"venue"
},
  "geometry": {"coordinates":[-70.88443700000001,42.817303],"type":"Point"}
}