{
  "type": "Feature",
  "properties": {
    "iso:country":"US",
    "sg:address":"212 Andover Rd",
    "sg:city":"Billerica",
    "sg:classifiers":[
        {
            "category":"Manufacturing",
            "subcategory":"Metals",
            "type":"Manufacturing & Wholesale Goods"
        }
    ],
    "sg:phone":"+1 978 667 3251",
    "sg:postcode":"01821",
    "sg:province":"MA",
    "sg:tags":[
        "tool"
    ],
    "wof:name":"Metek Tool",
    "wof:placetype":"venue"
},
  "geometry": {"coordinates":[-71.24183499999999,42.573651],"type":"Point"}
}