{
  "type": "Feature",
  "properties": {
    "addr:full": "340 Woodland St Holliston MA 01746",
    "addr:housenumber": "340",
    "addr:postcode": "01746",
    "addr:street": "Woodland St",
    "iso:country": "US",
    "sg:address": "340 Woodland St",
    "sg:city": "Holliston",
    "sg:classifiers": [
      {
        "category": "Professional",
        "subcategory": "Research",
        "type": "Services"
      }
    ],
    "sg:phone": "+1 508 655 4951",
    "sg:postcode": "01746",
    "sg:province": "MA",
    "sg:tags": [
      "environmental",
      "ecological"
    ],
    "wof:name": "Merritt Communications Inc",
    "wof:placetype": "venue"
  },
  "geometry": {"coordinates":[-71.422177,42.204027],"type":"Point"}
}
