{
  "type": "Feature",
  "properties": {
    "addr:full": "319 Main St Great Barrington MA 01230",
    "addr:housenumber": "319",
    "addr:postcode": "01230",
    "addr:street": "Main St",
    "iso:country": "US",
    "sg:address": "319 Main St",
    "sg:city": "Great Barrington",
    "sg:classifiers": [
      {
        "category": "Home \u0026 Garden",
        "subcategory": "Furniture",
        "type": "Retail Goods"
      }
    ],
    "sg:phone": "+1 413 528 3005",
    "sg:postcode": "01230",
    "sg:province": "MA",
    "sg:tags": [
      "equipment",
      "patio",
      "supply"
    ],
    "wof:name": "Deckline Teak",
    "wof:placetype": "venue"
  },
  "geometry": {"coordinates":[-73.362675,42.193766],"type":"Point"}
}
