{
  "type": "Feature",
  "properties": {
    "addr:full": "40 Cummings Park Woburn MA 01801",
    "addr:housenumber": "40",
    "addr:postcode": "01801",
    "addr:street": "Cummings Park",
    "iso:country": "US",
    "sg:address": "40 Cummings Park",
    "sg:city": "Woburn",
    "sg:classifiers": [
      {
        "category": "Restaurant",
        "type": "Food \u0026 Drink"
      }
    ],
    "sg:phone": "+1 781 935 7663",
    "sg:postcode": "01801",
    "sg:province": "MA",
    "wof:name": "Far East Cafe",
    "wof:placetype": "venue"
  },
  "geometry": {"coordinates":[-71.124603,42.4977],"type":"Point"}
}
