{
  "type": "Feature",
  "properties": {
    "addr:full":"208 College Hwy Southwick MA 01077",
    "addr:housenumber":"208",
    "addr:postcode":"01077",
    "addr:street":"College Hwy",
    "iso:country":"US",
    "sg:address":"208 College Hwy",
    "sg:city":"Southwick",
    "sg:classifiers":[
        {
            "category":"Travel",
            "subcategory":"Travel Agent",
            "type":"Entertainment"
        }
    ],
    "sg:phone":"+1 413 569 1500",
    "sg:postcode":"01077",
    "sg:province":"MA",
    "sg:tags":[
        "cruise"
    ],
    "wof:name":"Landmark Tours",
    "wof:placetype":"venue"
},
  "geometry": {"coordinates":[-72.78596400000001,42.026084],"type":"Point"}
}