{
  "type": "Feature",
  "properties": {
    "addr:full": "67 Lowell St Lynn MA 01905",
    "addr:housenumber": "67",
    "addr:postcode": "01905",
    "addr:street": "Lowell St",
    "iso:country": "US",
    "sg:address": "67 Lowell St",
    "sg:city": "Lynn",
    "sg:classifiers": [
      {
        "category": "Autos \u0026 Motor Vehicles",
        "subcategory": "Automobile Sales",
        "type": "Retail Goods"
      }
    ],
    "sg:phone": "+1 781 599 7075",
    "sg:postcode": "01905",
    "sg:province": "MA",
    "sg:tags": [
      "new",
      "car"
    ],
    "wof:name": "Robert L Ford Elementary",
    "wof:placetype": "venue"
  },
  "geometry": {"coordinates":[-70.962522,42.457864],"type":"Point"}
}
