{
  "type": "Feature",
  "properties": {
    "iso:country":"US",
    "sg:address":"67 Lowell St",
    "sg:city":"Lynn",
    "sg:classifiers":[
        {
            "category":"Autos & Motor Vehicles",
            "subcategory":"Automobile Sales",
            "type":"Retail Goods"
        }
    ],
    "sg:phone":"+1 781 599 7075",
    "sg:postcode":"01905",
    "sg:province":"MA",
    "sg:tags":[
        "new",
        "car"
    ],
    "wof:name":"Robert L Ford Elementary",
    "wof:placetype":"venue"
},
  "geometry": {"coordinates":[-70.96252200000001,42.457864],"type":"Point"}
}