{
  "type": "Feature",
  "properties": {
    "addr:full":"528 Main St Wareham MA 02571",
    "addr:housenumber":"528",
    "addr:postcode":"02571",
    "addr:street":"Main St",
    "iso:country":"US",
    "sg:address":"528 Main St",
    "sg:city":"Wareham",
    "sg:classifiers":[
        {
            "category":"Building & Trades",
            "subcategory":"Construction",
            "type":"Services"
        }
    ],
    "sg:phone":"+1 508 295 6318",
    "sg:postcode":"02571",
    "sg:province":"MA",
    "sg:tags":[
        "contractor"
    ],
    "wof:name":"Main Street Builders",
    "wof:placetype":"venue"
},
  "geometry": {"coordinates":[-70.72877,41.76671],"type":"Point"}
}