{
  "type": "Feature",
  "properties": {
    "addr:full":"99 Summer Street Boston MA 02110",
    "addr:housenumber":"99",
    "addr:postcode":"02110",
    "addr:street":"Summer Street",
    "iso:country":"US",
    "sg:address":"99 Summer Street",
    "sg:city":"Boston",
    "sg:classifiers":[
        {
            "category":"Professional",
            "subcategory":"Lawyer & Legal Services",
            "type":"Services"
        }
    ],
    "sg:phone":"+1 617 737 8222",
    "sg:postcode":"02110",
    "sg:province":"MA",
    "wof:name":"Egbert Richard M Atty",
    "wof:placetype":"venue"
},
  "geometry": {"coordinates":[-71.058138,42.353847],"type":"Point"}
}