{
  "type": "Feature",
  "properties": {
    "addr:full":"47 Industrial Dr Uxbridge MA 01569",
    "addr:housenumber":"47",
    "addr:postcode":"01569",
    "addr:street":"Industrial Dr",
    "iso:country":"US",
    "sg:address":"47 Industrial Dr",
    "sg:city":"Uxbridge",
    "sg:classifiers":[
        {
            "category":"Wholesale",
            "subcategory":"Construction Materials",
            "type":"Manufacturing & Wholesale Goods"
        }
    ],
    "sg:phone":"+1 508 278 4243",
    "sg:postcode":"01569",
    "sg:province":"MA",
    "sg:tags":[
        "glass"
    ],
    "wof:name":"Thermal Seal Insulating Glass",
    "wof:placetype":"venue"
},
  "geometry": {"coordinates":[-71.613404,42.038774],"type":"Point"}
}