{
  "type": "Feature",
  "properties": {
    "addr:full":"10 Louis Ave Tyngsboro MA 01879",
    "addr:housenumber":"10",
    "addr:postcode":"01879",
    "addr:street":"Louis Ave",
    "iso:country":"US",
    "sg:address":"10 Louis Ave",
    "sg:city":"Tyngsboro",
    "sg:classifiers":[
        {
            "category":"Building & Trades",
            "subcategory":"Construction",
            "type":"Services"
        }
    ],
    "sg:phone":"+1   ",
    "sg:postcode":"01879",
    "sg:province":"MA",
    "sg:tags":[
        "house"
    ],
    "wof:name":"MMR Builder Inc",
    "wof:placetype":"venue"
},
  "geometry": {"coordinates":[-71.375739,42.673499],"type":"Point"}
}