{
  "type": "Feature",
  "properties": {
    "addr:full": "112 Wapping Rd Kingston MA 02364",
    "addr:housenumber": "112",
    "addr:postcode": "02364",
    "addr:street": "Wapping Rd",
    "iso:country": "US",
    "sg:address": "112 Wapping Rd",
    "sg:city": "Kingston",
    "sg:classifiers": [
      {
        "category": "Restaurant",
        "type": "Food \u0026 Drink"
      }
    ],
    "sg:phone": "+1 781 585 8875",
    "sg:postcode": "02364",
    "sg:province": "MA",
    "wof:name": "Marksie's Mighty Dogs",
    "wof:placetype": "venue"
  },
  "geometry": {"coordinates":[-70.783712,41.989017],"type":"Point"}
}
