{
  "type": "Feature",
  "properties": {
    "iso:country":"US",
    "sg:address":"112 Wapping Rd",
    "sg:city":"Kingston",
    "sg:classifiers":[
        {
            "category":"Restaurant",
            "type":"Food & Drink"
        }
    ],
    "sg:phone":"+1 781 585 8875",
    "sg:postcode":"02364",
    "sg:province":"MA",
    "wof:name":"Marksie's Mighty Dogs",
    "wof:placetype":"venue"
},
  "geometry": {"coordinates":[-70.78371199999999,41.989017],"type":"Point"}
}