{
  "type": "Feature",
  "properties": {
    "addr:full":"280 Washington St Hudson MA 01749",
    "addr:housenumber":"280",
    "addr:postcode":"01749",
    "addr:street":"Washington St",
    "iso:country":"US",
    "sg:address":"280 Washington St",
    "sg:city":"Hudson",
    "sg:classifiers":[
        {
            "category":"Professional",
            "subcategory":"Accounting & Tax Preparation",
            "type":"Services"
        }
    ],
    "sg:phone":"+1 978 562 0837",
    "sg:postcode":"01749",
    "sg:province":"MA",
    "sg:tags":[
        "return",
        "filing"
    ],
    "wof:name":"H & R Block Tax Svc",
    "wof:placetype":"venue"
},
  "geometry": {"coordinates":[-71.562427,42.373171],"type":"Point"}
}