{
  "type": "Feature",
  "properties": {
    "addr:full":"89 Central St Norwood MA 02062",
    "addr:housenumber":"89",
    "addr:postcode":"02062",
    "addr:street":"Central St",
    "iso:country":"US",
    "sg:address":"89 Central St",
    "sg:city":"Norwood",
    "sg:classifiers":[
        {
            "category":"Restaurant",
            "type":"Food & Drink"
        }
    ],
    "sg:phone":"+1 781 255 5895",
    "sg:postcode":"02062",
    "sg:province":"MA",
    "sg:tags":[
        "caterer"
    ],
    "sg:website":"www.dianascatering.com",
    "wof:name":"Diana's Catering Inc",
    "wof:placetype":"venue"
},
  "geometry": {"coordinates":[-71.20050000000001,42.1926],"type":"Point"}
}