{
  "type": "Feature",
  "properties": {
    "iso:country":"US",
    "sg:address":"75 Newbury St",
    "sg:city":"Danvers",
    "sg:classifiers":[
        {
            "category":"Home & Garden",
            "subcategory":"Furniture",
            "type":"Retail Goods"
        }
    ],
    "sg:phone":"+1 978 762 7395",
    "sg:postcode":"01923",
    "sg:province":"MA",
    "sg:tags":[
        "equipment",
        "kitchen",
        "cabinet"
    ],
    "wof:name":"Heartwood Custom Kitchens",
    "wof:placetype":"venue"
},
  "geometry": {"coordinates":[-70.97513600000001,42.565393],"type":"Point"}
}