{
  "type": "Feature",
  "properties": {
    "addr:full":"40 Industrial Park Rd Plymouth MA 02360",
    "addr:housenumber":"40",
    "addr:postcode":"02360",
    "addr:street":"Industrial Park Rd",
    "iso:country":"US",
    "sg:address":"40 Industrial Park Rd",
    "sg:city":"Plymouth",
    "sg:classifiers":[
        {
            "category":"Insurance",
            "subcategory":"Insurance Agent",
            "type":"Services"
        },
        {
            "category":"Insurance",
            "subcategory":"Hazard Insurance",
            "type":"Services"
        },
        {
            "category":"Insurance",
            "subcategory":"Title Insurance",
            "type":"Services"
        }
    ],
    "sg:phone":"+1 508 746 7990",
    "sg:postcode":"02360",
    "sg:province":"MA",
    "sg:tags":[
        "business",
        "auto",
        "commercial",
        "homeowner",
        "motorcycle",
        "renter"
    ],
    "sg:website":"http://www.safeharbourinsurance.com",
    "wof:name":"Safe Harbour Insurance Management Inc",
    "wof:placetype":"venue"
},
  "geometry": {"coordinates":[-70.699529,41.96105],"type":"Point"}
}