{
  "type": "Feature",
  "properties": {
    "iso:country":"US",
    "sg:address":"88 Union St",
    "sg:city":"South Weymouth",
    "sg:classifiers":[
        {
            "category":"Shopping",
            "subcategory":"Used Merchandise",
            "type":"Retail Goods"
        }
    ],
    "sg:phone":"+1   ",
    "sg:postcode":"02190",
    "sg:province":"MA",
    "wof:name":"Doing Antiques",
    "wof:placetype":"venue"
},
  "geometry": {"coordinates":[-70.94654300000001,42.172898],"type":"Point"}
}