{
  "type": "Feature",
  "properties": {
    "addr:full":"132 Fuller St Middleboro MA 02346",
    "addr:housenumber":"132",
    "addr:postcode":"02346",
    "addr:street":"Fuller St",
    "iso:country":"US",
    "sg:address":"132 Fuller St",
    "sg:city":"Middleboro",
    "sg:classifiers":[
        {
            "category":"Organizations",
            "subcategory":"Community Association",
            "type":"Services"
        }
    ],
    "sg:phone":"+1 508 947 6600",
    "sg:postcode":"02346",
    "sg:province":"MA",
    "sg:tags":[
        "club",
        "automobile"
    ],
    "wof:name":"South Shore Antique Auto Club",
    "wof:placetype":"venue"
},
  "geometry": {"coordinates":[-70.858375,41.936069],"type":"Point"}
}