{
  "type": "Feature",
  "properties": {
    "iso:country":"US",
    "sg:address":"485 South St Apt 514",
    "sg:city":"Holyoke",
    "sg:classifiers":[
        {
            "category":"Personal",
            "subcategory":"Beauty Salon",
            "type":"Services"
        },
        {
            "category":"Personal",
            "subcategory":"Barber",
            "type":"Services"
        }
    ],
    "sg:phone":"+1 413 532 8220",
    "sg:postcode":"01040",
    "sg:province":"MA",
    "wof:name":"I Haircut",
    "wof:placetype":"venue"
},
  "geometry": {"coordinates":[-72.625981,42.194778],"type":"Point"}
}