{
  "type": "Feature",
  "properties": {
    "addr:full":"15 Elm St Monson MA 01057",
    "addr:housenumber":"15",
    "addr:postcode":"01057",
    "addr:street":"Elm St",
    "iso:country":"US",
    "sg:address":"15 Elm St",
    "sg:city":"Monson",
    "sg:classifiers":[
        {
            "category":"Social Services",
            "subcategory":"Child Care",
            "type":"Services"
        }
    ],
    "sg:phone":"+1   ",
    "sg:postcode":"01057",
    "sg:province":"MA",
    "sg:tags":[
        "day"
    ],
    "wof:name":"Jean M Valley",
    "wof:placetype":"venue"
},
  "geometry": {"coordinates":[-72.316078,42.087464],"type":"Point"}
}