{
  "type": "Feature",
  "properties": {
    "addr:full":"25 Boylston Pl Newton MA 02445",
    "addr:housenumber":"25",
    "addr:postcode":"02445",
    "addr:street":"Boylston Pl",
    "iso:country":"US",
    "sg:address":"25 Boylston Pl",
    "sg:city":"Newton",
    "sg:classifiers":[
        {
            "category":"Professional",
            "type":"Services"
        }
    ],
    "sg:phone":"+1 617 232 3239",
    "sg:postcode":"02445",
    "sg:province":"MA",
    "wof:name":"American Osteoporosis Svc",
    "wof:placetype":"venue"
},
  "geometry": {"coordinates":[-71.12530599999999,42.330442],"type":"Point"}
}