{
  "type": "Feature",
  "properties": {
    "addr:full": "683 S West St Feeding Hills MA 01030",
    "addr:housenumber": "683",
    "addr:postcode": "west st;01030",
    "addr:street": "S",
    "iso:country": "US",
    "sg:address": "683 S West St",
    "sg:city": "Feeding Hills",
    "sg:classifiers": [
      {
        "category": "Home \u0026 Garden",
        "subcategory": "Garden Supply",
        "type": "Retail Goods"
      }
    ],
    "sg:phone": "+1 413 789 3203",
    "sg:postcode": "01030",
    "sg:province": "MA",
    "sg:tags": [
      "nurseryman"
    ],
    "wof:name": "Oak Ridge Nursery",
    "wof:placetype": "venue"
  },
  "geometry": {"coordinates":[-72.700152,42.042502],"type":"Point"}
}
