{
  "type": "Feature",
  "properties": {
    "addr:full": "590 Boston Rd Springfield MA 01119",
    "addr:housenumber": "590",
    "addr:postcode": "01119",
    "addr:street": "Boston Rd",
    "iso:country": "US",
    "sg:address": "590 Boston Rd",
    "sg:city": "Springfield",
    "sg:classifiers": [
      {
        "category": "Shopping",
        "subcategory": "Department Store",
        "type": "Retail Goods"
      }
    ],
    "sg:phone": "+1 413 796 7804",
    "sg:postcode": "01119",
    "sg:province": "MA",
    "sg:tags": [
      "shop"
    ],
    "wof:name": "Dezi's Jewelry Exchange \u0026 Pawn",
    "wof:placetype": "venue"
  },
  "geometry": {"coordinates":[-72.52497,42.13414],"type":"Point"}
}
