{
  "type": "Feature",
  "properties": {
    "addr:full":"288 Norfolk St 3rd Fl Cambridge MA 02139",
    "addr:housenumber":"288;3rd",
    "addr:postcode":"02139",
    "addr:street":"Norfolk St;Fl",
    "iso:country":"US",
    "sg:address":"288 Norfolk St 3rd Fl",
    "sg:city":"Cambridge",
    "sg:classifiers":[
        {
            "category":"Education",
            "subcategory":"Dance Studio",
            "type":"Public Place"
        },
        {
            "category":"Arts & Performance",
            "subcategory":"Dance",
            "type":"Entertainment"
        }
    ],
    "sg:phone":"+1 617 492 2122",
    "sg:postcode":"02139",
    "sg:province":"MA",
    "sg:tags":[
        "instruction",
        "dancing"
    ],
    "sg:website":"www.extremedancesport.com",
    "wof:name":"Extreme Dancesport",
    "wof:placetype":"venue"
},
  "geometry": {"coordinates":[-71.09726999999999,42.371435],"type":"Point"}
}