{
  "type": "Feature",
  "properties": {
    "iso:country":"US",
    "sg:address":"10 South St",
    "sg:city":"Hudson",
    "sg:classifiers":[
        {
            "category":"Shopping",
            "subcategory":"Used Merchandise",
            "type":"Retail Goods"
        }
    ],
    "sg:phone":"+1 978 568 1494",
    "sg:postcode":"01749",
    "sg:province":"MA",
    "sg:tags":[
        "second",
        "store",
        "hand"
    ],
    "wof:name":"Sleeper's Second-Hand Shoppe",
    "wof:placetype":"venue"
},
  "geometry": {"coordinates":[-71.569395,42.390663],"type":"Point"}
}