{
  "type": "Feature",
  "properties": {
    "addr:full":"4 Kansas St Natick MA 01760",
    "addr:housenumber":"4",
    "addr:postcode":"01760",
    "addr:street":"Kansas St",
    "iso:country":"US",
    "sg:address":"4 Kansas St",
    "sg:city":"Natick",
    "sg:classifiers":[
        {
            "category":"Building & Trades",
            "subcategory":"Cleaning & Sanitation",
            "type":"Services"
        }
    ],
    "sg:phone":"+1 508 820 0668",
    "sg:postcode":"01760",
    "sg:province":"MA",
    "sg:tags":[
        "janitor"
    ],
    "wof:name":"Rayben Enterprises Inc",
    "wof:placetype":"venue"
},
  "geometry": {"coordinates":[-71.357114,42.291306],"type":"Point"}
}