{
  "type": "Feature",
  "properties": {
    "iso:country":"US",
    "sg:address":"185 Central St",
    "sg:city":"Winchendon",
    "sg:classifiers":[
        {
            "category":"Banks & Credit Unions",
            "subcategory":"Bank",
            "type":"Services"
        }
    ],
    "sg:phone":"+1 978 297 4161",
    "sg:postcode":"01475",
    "sg:province":"MA",
    "wof:name":"GFA Federal Credit Union",
    "wof:placetype":"venue"
},
  "geometry": {"coordinates":[-72.045237,42.685336],"type":"Point"}
}