{
  "type": "Feature",
  "properties": {
    "addr:full": "185 Central St Winchendon MA 01475",
    "addr:housenumber": "185",
    "addr:postcode": "01475",
    "addr:street": "Central St",
    "iso:country": "US",
    "ovtr:label": "GFA Federal Credit Union, 185 Central St Winchendon MA US",
    "ovtr:similarity": 2.197258949279785,
    "sg:address": "185 Central St",
    "sg:city": "Winchendon",
    "sg:classifiers": [
      {
        "category": "Banks \u0026 Credit Unions",
        "subcategory": "Bank",
        "type": "Services"
      }
    ],
    "sg:phone": "+1 978 297 4161",
    "sg:postcode": "01475",
    "sg:province": "MA",
    "wof:name": "GFA Federal Credit Union",
    "wof:placetype": "venue"
  },
  "geometry": {"coordinates":[-72.045237,42.685336],"type":"Point"}
}
