{
  "type": "Feature",
  "properties": {
    "iso:country":"US",
    "sg:address":"227 Prospect St",
    "sg:city":"Housatonic",
    "sg:classifiers":[
        {
            "category":"Wholesale",
            "subcategory":"Books, Periodicals, & Newspapers",
            "type":"Manufacturing & Wholesale Goods"
        }
    ],
    "sg:phone":"+1 413 274 1323",
    "sg:postcode":"01236",
    "sg:province":"MA",
    "sg:tags":[
        "publisher",
        "book"
    ],
    "wof:name":"Storytellers",
    "wof:placetype":"venue"
},
  "geometry": {"coordinates":[-73.371972,42.255742],"type":"Point"}
}