{
  "type": "Feature",
  "properties": {
    "addr:full": "227 Prospect St Housatonic MA 01236",
    "addr:housenumber": "227",
    "addr:postcode": "01236",
    "addr:street": "Prospect St",
    "iso:country": "US",
    "sg:address": "227 Prospect St",
    "sg:city": "Housatonic",
    "sg:classifiers": [
      {
        "category": "Wholesale",
        "subcategory": "Books, Periodicals, \u0026 Newspapers",
        "type": "Manufacturing \u0026 Wholesale Goods"
      }
    ],
    "sg:phone": "+1 413 274 1323",
    "sg:postcode": "01236",
    "sg:province": "MA",
    "sg:tags": [
      "publisher",
      "book"
    ],
    "wof:name": "Storytellers",
    "wof:placetype": "venue"
  },
  "geometry": {"coordinates":[-73.371972,42.255742],"type":"Point"}
}
