{
  "type": "Feature",
  "properties": {
    "iso:country":"US",
    "sg:address":"1898 Centre St",
    "sg:city":"West Roxbury",
    "sg:classifiers":[
        {
            "category":"Shopping",
            "subcategory":"Gifts & Souvenirs",
            "type":"Retail Goods"
        }
    ],
    "sg:phone":"+1 617 323 4644",
    "sg:postcode":"02132",
    "sg:province":"MA",
    "sg:tags":[
        "shop"
    ],
    "sg:website":"www.irish-cottage.com",
    "wof:name":"Irish Cottage Inc",
    "wof:placetype":"venue"
},
  "geometry": {"coordinates":[-71.156099,42.285399],"type":"Point"}
}