{
  "type": "Feature",
  "properties": {
    "addr:full": "20 Hope Ave Ste 204 Waltham MA 02453",
    "addr:housenumber": "20",
    "addr:postcode": "02453",
    "addr:street": "Hope Ave Ste 204",
    "iso:country": "US",
    "sg:address": "20 Hope Ave Ste 204",
    "sg:city": "Waltham",
    "sg:classifiers": [
      {
        "category": "Health Services",
        "subcategory": "Doctor",
        "type": "Services"
      }
    ],
    "sg:phone": "+1 781 899 2525",
    "sg:postcode": "02453",
    "sg:province": "MA",
    "sg:tags": [
      "physician",
      "surgeon",
      "urology",
      "surgeons"
    ],
    "wof:name": "New England Urology Associates",
    "wof:placetype": "venue"
  },
  "geometry": {"coordinates":[-71.24855,42.369751],"type":"Point"}
}
