{
  "type": "Feature",
  "properties": {
    "iso:country":"US",
    "sg:address":"20 Park Plz",
    "sg:city":"Boston",
    "sg:classifiers":[
        {
            "category":"Real Estate",
            "subcategory":"Real Estate Services",
            "type":"Services"
        },
        {
            "category":"Real Estate",
            "subcategory":"Real Estate Agent",
            "type":"Services"
        }
    ],
    "sg:phone":"+1 617 338 6102",
    "sg:postcode":"02116",
    "sg:province":"MA",
    "sg:tags":[
        "management",
        "property"
    ],
    "sg:website":"www.backbayproperties.com",
    "wof:name":"Back Bay Properties Corporation",
    "wof:placetype":"venue"
},
  "geometry": {"coordinates":[-71.069012,42.351554],"type":"Point"}
}