{
  "type": "Feature",
  "properties": {
    "addr:full": "575 Boylston St Newton MA 02459",
    "addr:housenumber": "575",
    "addr:postcode": "02459",
    "addr:street": "Boylston St",
    "iso:country": "US",
    "ovtr:label": "Joseph A Russo MD, 575 Boylston St Newton Center MA US",
    "ovtr:similarity": 2.896233081817627,
    "sg:address": "575 Boylston St",
    "sg:city": "Newton",
    "sg:classifiers": [
      {
        "category": "Health Services",
        "subcategory": "Doctor",
        "type": "Services"
      }
    ],
    "sg:phone": "+1 617 964 1440",
    "sg:postcode": "02459",
    "sg:province": "MA",
    "sg:tags": [
      "physician",
      "surgeon"
    ],
    "wof:name": "Joseph A Russo MD",
    "wof:placetype": "venue"
  },
  "geometry": {"coordinates":[-71.192732,42.318878],"type":"Point"}
}
