{
  "type": "Feature",
  "properties": {
    "addr:full": "185 Central St Leominster MA 01453",
    "addr:housenumber": "185",
    "addr:postcode": "01453",
    "addr:street": "Central St",
    "iso:country": "US",
    "sg:address": "185 Central St",
    "sg:city": "Leominster",
    "sg:classifiers": [
      {
        "category": "Food \u0026 Beverages",
        "subcategory": "Groceries \u0026 Convenience Stores",
        "type": "Retail Goods"
      }
    ],
    "sg:phone": "+1 978 466 6260",
    "sg:postcode": "01453",
    "sg:province": "MA",
    "sg:tags": [
      "product"
    ],
    "wof:name": "Cariocas Food",
    "wof:placetype": "venue"
  },
  "geometry": {"coordinates":[-71.758606,42.519794],"type":"Point"}
}
