{
  "type": "Feature",
  "properties": {
    "iso:country":"US",
    "sg:address":"185 Central St",
    "sg:city":"Leominster",
    "sg:classifiers":[
        {
            "category":"Food & Beverages",
            "subcategory":"Groceries & Convenience Stores",
            "type":"Retail Goods"
        }
    ],
    "sg:phone":"+1 978 466 6260",
    "sg:postcode":"01453",
    "sg:province":"MA",
    "sg:tags":[
        "product"
    ],
    "wof:name":"Cariocas Food",
    "wof:placetype":"venue"
},
  "geometry": {"coordinates":[-71.758606,42.519794],"type":"Point"}
}