{
  "type": "Feature",
  "properties": {
    "iso:country":"US",
    "sg:address":"622R Main St",
    "sg:city":"Reading",
    "sg:classifiers":[
        {
            "category":"Personal",
            "subcategory":"Barber",
            "type":"Services"
        }
    ],
    "sg:phone":"+1 781 942 2887",
    "sg:postcode":"01867",
    "sg:province":"MA",
    "wof:name":"Mr Glenn's Barbershop",
    "wof:placetype":"venue"
},
  "geometry": {"coordinates":[-71.102892,42.523879],"type":"Point"}
}