{
  "type": "Feature",
  "properties": {
    "addr:full": "453 Newburyport Tpke Rowley MA 01969",
    "addr:housenumber": "453",
    "addr:postcode": "01969",
    "addr:street": "Newburyport Tpke",
    "iso:country": "US",
    "sg:address": "453 Newburyport Tpke",
    "sg:city": "Rowley",
    "sg:classifiers": [
      {
        "category": "Building \u0026 Trades",
        "subcategory": "Construction",
        "type": "Services"
      }
    ],
    "sg:phone": "+1 978 948 7171",
    "sg:postcode": "01969",
    "sg:province": "MA",
    "sg:tags": [
      "contractor"
    ],
    "wof:name": "North Atlantic Constructors",
    "wof:placetype": "venue"
  },
  "geometry": {"coordinates":[-70.903425,42.724187],"type":"Point"}
}
