{
  "type": "Feature",
  "properties": {
    "addr:full":"610 Wareham St Middleboro MA 02346",
    "addr:housenumber":"610",
    "addr:postcode":"02346",
    "addr:street":"Wareham St",
    "iso:country":"US",
    "sg:address":"610 Wareham St",
    "sg:city":"Middleboro",
    "sg:classifiers":[
        {
            "category":"Building & Trades",
            "subcategory":"Construction",
            "type":"Services"
        }
    ],
    "sg:phone":"+1 508 830 9444",
    "sg:postcode":"02346",
    "sg:province":"MA",
    "sg:tags":[
        "utility",
        "contractor"
    ],
    "wof:name":"Cps Inc",
    "wof:placetype":"venue"
},
  "geometry": {"coordinates":[-70.80695299999999,41.814186],"type":"Point"}
}