{
  "type": "Feature",
  "properties": {
    "addr:full": "7 Andover St North Andover MA 01845",
    "addr:housenumber": "7",
    "addr:postcode": "01845",
    "addr:street": "Andover St",
    "iso:country": "US",
    "sg:address": "7 Andover St",
    "sg:city": "North Andover",
    "sg:classifiers": [
      {
        "category": "Social Services",
        "subcategory": "Child Care",
        "type": "Services"
      }
    ],
    "sg:phone": "+1 978 686 5215",
    "sg:postcode": "01845",
    "sg:province": "MA",
    "sg:website": "www.lilpro.com",
    "wof:name": "Little Professionals Inc",
    "wof:placetype": "venue"
  },
  "geometry": {"coordinates":[-71.117881,42.681328],"type":"Point"}
}
