{
  "type": "Feature",
  "properties": {
    "addr:full": "199 State St Ste 7 Boston MA 02109",
    "addr:housenumber": "199",
    "addr:postcode": "02109",
    "addr:street": "State St Ste 7",
    "iso:country": "US",
    "sg:address": "199 State St Ste 7",
    "sg:city": "Boston",
    "sg:classifiers": [
      {
        "category": "Banks \u0026 Credit Unions",
        "subcategory": "Investment Brokerage",
        "type": "Services"
      },
      {
        "category": "Banks \u0026 Credit Unions",
        "subcategory": "Financial Services",
        "type": "Services"
      }
    ],
    "sg:phone": "+1 617 723 8200",
    "sg:postcode": "02109",
    "sg:province": "MA",
    "sg:tags": [
      "advisory",
      "planner"
    ],
    "wof:name": "The Colony Group Inc",
    "wof:placetype": "venue"
  },
  "geometry": {"coordinates":[-71.052437,42.35955],"type":"Point"}
}
