{
  "type": "Feature",
  "properties": {
    "iso:country":"US",
    "sg:address":"55 Elm St",
    "sg:city":"Dedham",
    "sg:classifiers":[
        {
            "category":"Banks & Credit Unions",
            "subcategory":"Bank",
            "type":"Services"
        }
    ],
    "sg:phone":"+1 781 329 6700",
    "sg:postcode":"02026",
    "sg:province":"MA",
    "sg:tags":[
        "loan",
        "saving"
    ],
    "sg:website":"www.dedhamsavings.com/",
    "wof:name":"Dedham Institution for Savings",
    "wof:placetype":"venue"
},
  "geometry": {"coordinates":[-71.18150300000001,42.233002],"type":"Point"}
}