{
  "type": "Feature",
  "properties": {
    "addr:full": "290 Canal St Salem MA 01970",
    "addr:housenumber": "290",
    "addr:postcode": "01970",
    "addr:street": "Canal St",
    "iso:country": "US",
    "sg:address": "290 Canal St",
    "sg:city": "Salem",
    "sg:classifiers": [
      {
        "category": "Autos \u0026 Motor Vehicles",
        "subcategory": "Fuel \u0026 Gas Station",
        "type": "Retail Goods"
      }
    ],
    "sg:phone": "+1 978 740 5115",
    "sg:postcode": "01970",
    "sg:province": "MA",
    "sg:tags": [
      "oil"
    ],
    "wof:name": "Salem Citgo",
    "wof:placetype": "venue"
  },
  "geometry": {"coordinates":[-70.895984,42.501042],"type":"Point"}
}
