{
  "type": "Feature",
  "properties": {
    "iso:country":"US",
    "sg:address":"435 High St",
    "sg:city":"Westwood",
    "sg:classifiers":[
        {
            "category":"Real Estate",
            "subcategory":"Real Estate Services",
            "type":"Services"
        },
        {
            "category":"Real Estate",
            "subcategory":"Real Estate Agent",
            "type":"Services"
        }
    ],
    "sg:phone":"+1 781 329 7174",
    "sg:postcode":"02090",
    "sg:province":"MA",
    "sg:tags":[
        "management"
    ],
    "wof:name":"Evergreen Ventures",
    "wof:placetype":"venue"
},
  "geometry": {"coordinates":[-71.219368,42.232922],"type":"Point"}
}