{
  "type": "Feature",
  "properties": {
    "iso:country":"US",
    "sg:address":"19 Rawson Rd",
    "sg:city":"Hanover",
    "sg:classifiers":[
        {
            "category":"Retail",
            "subcategory":"Laundry & Dry Cleaning",
            "type":"Services"
        },
        {
            "category":"Building & Trades",
            "subcategory":"Cleaning & Sanitation",
            "type":"Services"
        }
    ],
    "sg:phone":"+1 781 826 9444",
    "sg:postcode":"02339",
    "sg:province":"MA",
    "sg:tags":[
        "cleaner",
        "house"
    ],
    "wof:name":"Air Cleaning Services",
    "wof:placetype":"venue"
},
  "geometry": {"coordinates":[-70.83155499999999,42.128782],"type":"Point"}
}