{
  "type": "Feature",
  "properties": {
    "addr:full": "19 Rawson Rd Hanover MA 02339",
    "addr:housenumber": "19",
    "addr:postcode": "02339",
    "addr:street": "Rawson Rd",
    "iso:country": "US",
    "sg:address": "19 Rawson Rd",
    "sg:city": "Hanover",
    "sg:classifiers": [
      {
        "category": "Retail",
        "subcategory": "Laundry \u0026 Dry Cleaning",
        "type": "Services"
      },
      {
        "category": "Building \u0026 Trades",
        "subcategory": "Cleaning \u0026 Sanitation",
        "type": "Services"
      }
    ],
    "sg:phone": "+1 781 826 9444",
    "sg:postcode": "02339",
    "sg:province": "MA",
    "sg:tags": [
      "cleaner",
      "house"
    ],
    "wof:name": "Air Cleaning Services",
    "wof:placetype": "venue"
  },
  "geometry": {"coordinates":[-70.831555,42.128782],"type":"Point"}
}
