{
  "type": "Feature",
  "properties": {
    "iso:country":"US",
    "sg:address":"133 Washington St",
    "sg:city":"Salem",
    "sg:classifiers":[
        {
            "category":"Professional",
            "subcategory":"Lawyer & Legal Services",
            "type":"Services"
        }
    ],
    "sg:phone":"+1 978 744 9591",
    "sg:postcode":"01970",
    "sg:province":"MA",
    "sg:tags":[
        "attorney"
    ],
    "sg:website":"www.gaydivorce.com",
    "wof:name":"Anthony C Adamopoulos",
    "wof:placetype":"venue"
},
  "geometry": {"coordinates":[-70.895442,42.52073],"type":"Point"}
}