{
  "type": "Feature",
  "properties": {
    "iso:country":"US",
    "sg:address":"7 Alfred Street Suite 300A",
    "sg:city":"Woburn",
    "sg:classifiers":[
        {
            "category":"Health Services",
            "subcategory":"Doctor",
            "type":"Services"
        }
    ],
    "sg:phone":"+1 781 933 9993",
    "sg:postcode":"01801",
    "sg:province":"MA",
    "sg:tags":[
        "obstetrician",
        "gynecologist"
    ],
    "wof:name":"Winchester Women's Health Care",
    "wof:placetype":"venue"
},
  "geometry": {"coordinates":[-71.155991,42.501503],"type":"Point"}
}