{
  "type": "Feature",
  "properties": {
    "iso:country":"US",
    "sg:address":"97 Booth Hill Rd",
    "sg:city":"Scituate",
    "sg:classifiers":[
        {
            "category":"Manufacturing",
            "subcategory":"Glass & Minerals",
            "type":"Manufacturing & Wholesale Goods"
        }
    ],
    "sg:phone":"+1 781 545 4447",
    "sg:postcode":"02066",
    "sg:province":"MA",
    "sg:tags":[
        "glass-wholesale",
        "shape",
        "circle",
        "special",
        "manufacturer"
    ],
    "wof:name":"South Coast Glass & Aluminum",
    "wof:placetype":"venue"
},
  "geometry": {"coordinates":[-70.78997099999999,42.210715],"type":"Point"}
}