{
  "type": "Feature",
  "properties": {
    "addr:full": "97 Booth Hill Rd Scituate MA 02066",
    "addr:housenumber": "97",
    "addr:postcode": "02066",
    "addr:street": "Booth Hill Rd",
    "iso:country": "US",
    "sg:address": "97 Booth Hill Rd",
    "sg:city": "Scituate",
    "sg:classifiers": [
      {
        "category": "Manufacturing",
        "subcategory": "Glass \u0026 Minerals",
        "type": "Manufacturing \u0026 Wholesale Goods"
      }
    ],
    "sg:phone": "+1 781 545 4447",
    "sg:postcode": "02066",
    "sg:province": "MA",
    "sg:tags": [
      "glass-wholesale",
      "shape",
      "circle",
      "special",
      "manufacturer"
    ],
    "wof:name": "South Coast Glass \u0026 Aluminum",
    "wof:placetype": "venue"
  },
  "geometry": {"coordinates":[-70.789971,42.210715],"type":"Point"}
}
