{
  "type": "Feature",
  "properties": {
    "addr:full": "208 Main St Weymouth MA 02188",
    "addr:housenumber": "208",
    "addr:postcode": "02188",
    "addr:street": "Main St",
    "iso:country": "US",
    "sg:address": "208 Main St",
    "sg:city": "Weymouth",
    "sg:classifiers": [
      {
        "category": "Professional",
        "type": "Services"
      },
      {
        "category": "Restaurant",
        "type": "Food \u0026 Drink"
      },
      {
        "category": "Fast Food",
        "type": "Food \u0026 Drink"
      }
    ],
    "sg:phone": "+1 781 331 4777",
    "sg:postcode": "02188",
    "sg:province": "MA",
    "sg:tags": [
      "delivery",
      "take",
      "pizza"
    ],
    "sg:website": "http://www.pizzahut.com",
    "wof:name": "Pizza Hut",
    "wof:placetype": "venue"
  },
  "geometry": {"coordinates":[-70.955862,42.200634],"type":"Point"}
}
