{
  "type": "Feature",
  "properties": {
    "iso:country":"US",
    "sg:address":"208 Main St",
    "sg:city":"Weymouth",
    "sg:classifiers":[
        {
            "category":"Professional",
            "type":"Services"
        },
        {
            "category":"Restaurant",
            "type":"Food & Drink"
        },
        {
            "category":"Fast Food",
            "type":"Food & Drink"
        }
    ],
    "sg:phone":"+1 781 331 4777",
    "sg:postcode":"02188",
    "sg:province":"MA",
    "sg:tags":[
        "delivery",
        "take",
        "pizza"
    ],
    "sg:website":"http://www.pizzahut.com",
    "wof:name":"Pizza Hut",
    "wof:placetype":"venue"
},
  "geometry": {"coordinates":[-70.955862,42.200634],"type":"Point"}
}