{
  "type": "Feature",
  "properties": {
    "iso:country":"US",
    "sg:address":"65 Samoset Rd",
    "sg:city":"Duxbury",
    "sg:classifiers":[
        {
            "category":"Professional",
            "subcategory":"Advertising",
            "type":"Services"
        }
    ],
    "sg:phone":"+1 781 934 7400",
    "sg:postcode":"02332",
    "sg:province":"MA",
    "sg:tags":[
        "agency"
    ],
    "wof:name":"Nichols Creative Enterprises",
    "wof:placetype":"venue"
},
  "geometry": {"coordinates":[-70.669836,42.009948],"type":"Point"}
}