{
  "type": "Feature",
  "properties": {
    "iso:country":"US",
    "sg:address":"72 Maple St",
    "sg:city":"South Hamilton",
    "sg:classifiers":[
        {
            "category":"Building & Trades",
            "subcategory":"Construction",
            "type":"Services"
        }
    ],
    "sg:phone":"+1 978 468 2980",
    "sg:postcode":"01982",
    "sg:province":"MA",
    "sg:tags":[
        "painter"
    ],
    "wof:name":"David C Parker Inc",
    "wof:placetype":"venue"
},
  "geometry": {"coordinates":[-70.869344,42.625002],"type":"Point"}
}