{
  "type": "Feature",
  "properties": {
    "addr:full": "72 Maple St South Hamilton MA 01982",
    "addr:housenumber": "72",
    "addr:postcode": "01982",
    "addr:street": "Maple St South",
    "iso:country": "US",
    "sg:address": "72 Maple St",
    "sg:city": "South Hamilton",
    "sg:classifiers": [
      {
        "category": "Building \u0026 Trades",
        "subcategory": "Construction",
        "type": "Services"
      }
    ],
    "sg:phone": "+1 978 468 2980",
    "sg:postcode": "01982",
    "sg:province": "MA",
    "sg:tags": [
      "painter"
    ],
    "wof:name": "David C Parker Inc",
    "wof:placetype": "venue"
  },
  "geometry": {"coordinates":[-70.869344,42.625002],"type":"Point"}
}
