{
  "type": "Feature",
  "properties": {
    "addr:full":"1576 Blue Hill Ave Mattapan MA 02126",
    "addr:housenumber":"1576",
    "addr:postcode":"02126",
    "addr:street":"Blue Hill Ave",
    "iso:country":"US",
    "sg:address":"1576 Blue Hill Ave",
    "sg:city":"Mattapan",
    "sg:classifiers":[
        {
            "category":"Retail",
            "subcategory":"Auto Repair",
            "type":"Services"
        }
    ],
    "sg:phone":"+1 617 296 0400",
    "sg:postcode":"02126",
    "sg:province":"MA",
    "sg:tags":[
        "repairing",
        "automobile"
    ],
    "wof:name":"Monro Muffler Brake & Svc",
    "wof:placetype":"venue"
},
  "geometry": {"coordinates":[-71.09361,42.269507],"type":"Point"}
}