{
  "type": "Feature",
  "properties": {
    "addr:full":"971 Commonwealth Ave # 35 Boston MA 02215",
    "addr:housenumber":"971",
    "addr:postcode":"02215",
    "addr:street":"Commonwealth Ave # 35",
    "iso:country":"US",
    "sg:address":"971 Commonwealth Ave # 35",
    "sg:city":"Boston",
    "sg:classifiers":[
        {
            "category":"Sports & Exercise",
            "subcategory":"Sports Center",
            "type":"Entertainment"
        }
    ],
    "sg:phone":"+1 617 779 8900",
    "sg:postcode":"02215",
    "sg:province":"MA",
    "sg:tags":[
        "athletic"
    ],
    "wof:name":"Omnibiosystems, Inc.",
    "wof:placetype":"venue"
},
  "geometry": {"coordinates":[-71.11938000000001,42.351646],"type":"Point"}
}