{
  "type": "Feature",
  "properties": {
    "addr:full":"111 Washington St Plainville MA 02762",
    "addr:housenumber":"111",
    "addr:postcode":"02762",
    "addr:street":"Washington St",
    "iso:country":"US",
    "sg:address":"111 Washington St",
    "sg:city":"Plainville",
    "sg:classifiers":[
        {
            "category":"Real Estate",
            "subcategory":"Real Estate Agent",
            "type":"Services"
        }
    ],
    "sg:phone":"+1 508 699 5777",
    "sg:postcode":"02762",
    "sg:province":"MA",
    "sg:tags":[
        "appraiser"
    ],
    "wof:name":"Schofield Appraisers & Conslnt",
    "wof:placetype":"venue"
},
  "geometry": {"coordinates":[-71.31791699999999,42.016133],"type":"Point"}
}