{
  "type": "Feature",
  "properties": {
    "iso:country":"US",
    "sg:address":"489 Summer St",
    "sg:city":"Franklin",
    "sg:classifiers":[
        {
            "category":"Shopping",
            "type":"Retail Goods"
        }
    ],
    "sg:phone":"+1 508 553 8863",
    "sg:postcode":"02038",
    "sg:province":"MA",
    "sg:tags":[
        "merchandise"
    ],
    "wof:name":"Mb Contracting Incorporated",
    "wof:placetype":"venue"
},
  "geometry": {"coordinates":[-71.386954,42.069941],"type":"Point"}
}