{
  "type": "Feature",
  "properties": {
    "addr:full": "178 E Main St Gloucester MA 01930",
    "addr:housenumber": "178",
    "addr:postcode": "01930",
    "addr:street": "E Main St",
    "iso:country": "US",
    "sg:address": "178 E Main St",
    "sg:city": "Gloucester",
    "sg:classifiers": [
      {
        "category": "Shopping",
        "type": "Retail Goods"
      }
    ],
    "sg:phone": "+1 978 281 8584",
    "sg:postcode": "01930",
    "sg:province": "MA",
    "sg:tags": [
      "art",
      "gallery",
      "dealer"
    ],
    "wof:name": "Sacred Cod",
    "wof:placetype": "venue"
  },
  "geometry": {"coordinates":[-70.650599,42.610583],"type":"Point"}
}
