{
  "type": "Feature",
  "properties": {
    "addr:full": "331 Hanover St Boston MA 02113",
    "addr:housenumber": "331",
    "addr:postcode": "02113",
    "addr:street": "Hanover St",
    "iso:country": "US",
    "sg:address": "331 Hanover St",
    "sg:city": "Boston",
    "sg:classifiers": [
      {
        "category": "Restaurant",
        "type": "Food \u0026 Drink"
      }
    ],
    "sg:menulink": "http://www.allmenus.com/ma/boston/371-china-house-restaurant/menu/",
    "sg:phone": "+1 617 723 9888",
    "sg:postcode": "02113",
    "sg:province": "MA",
    "sg:tags": [
      "asian",
      "chinese"
    ],
    "wof:name": "China House Restaurant",
    "wof:placetype": "venue"
  },
  "geometry": {"coordinates":[-71.053918,42.364314],"type":"Point"}
}
