{
  "type": "Feature",
  "properties": {
    "addr:full":"1156 Ashley Falls Rd Sheffield MA 01257",
    "addr:housenumber":"1156",
    "addr:postcode":"01257",
    "addr:street":"Ashley Falls Rd",
    "iso:country":"US",
    "sg:address":"1156 Ashley Falls Rd",
    "sg:city":"Sheffield",
    "sg:classifiers":[
        {
            "category":"Organizations",
            "subcategory":"Religious Organization",
            "type":"Services"
        }
    ],
    "sg:phone":"+1   ",
    "sg:postcode":"01257",
    "sg:province":"MA",
    "wof:name":"Trinity United Methdst Church",
    "wof:placetype":"venue"
},
  "geometry": {"coordinates":[-73.335594,42.056758],"type":"Point"}
}