{
  "type": "Feature",
  "properties": {
    "addr:full": "11 Carlson Ln West Barnstable MA 02668",
    "addr:housenumber": "11",
    "addr:postcode": "02668",
    "addr:street": "Carlson Ln",
    "iso:country": "US",
    "sg:address": "11 Carlson Ln",
    "sg:city": "West Barnstable",
    "sg:classifiers": [
      {
        "category": "Wholesale",
        "subcategory": "Durable Goods \u0026 Equipment",
        "type": "Manufacturing \u0026 Wholesale Goods"
      }
    ],
    "sg:phone": "+1 508 362 9874",
    "sg:postcode": "02668",
    "sg:province": "MA",
    "sg:tags": [
      "representative",
      "manufacturer"
    ],
    "wof:name": "Northeast Equipment Sales Co",
    "wof:placetype": "venue"
  },
  "geometry": {"coordinates":[-70.390648,41.716832],"type":"Point"}
}
