{
  "type": "Feature",
  "properties": {
    "addr:full":"1612A Blue Hill Ave Mattapan MA 02126",
    "addr:housenumber":"1612a",
    "addr:postcode":"02126",
    "addr:street":"Blue Hill Ave",
    "iso:country":"US",
    "sg:address":"1612A Blue Hill Ave",
    "sg:city":"Mattapan",
    "sg:classifiers":[
        {
            "category":"Shopping",
            "type":"Retail Goods"
        }
    ],
    "sg:phone":"+1 617 298 2077",
    "sg:postcode":"02126",
    "sg:province":"MA",
    "sg:tags":[
        "item",
        "boutique"
    ],
    "wof:name":"Ketou Boutique",
    "wof:placetype":"venue"
},
  "geometry": {"coordinates":[-71.093678,42.268892],"type":"Point"}
}