{
  "type": "Feature",
  "properties": {
    "iso:country":"US",
    "sg:address":"95 Uxbridge Rd",
    "sg:city":"Mendon",
    "sg:classifiers":[
        {
            "category":"Restaurant",
            "type":"Food & Drink"
        }
    ],
    "sg:phone":"+1 508 478 0600",
    "sg:postcode":"01756",
    "sg:province":"MA",
    "sg:tags":[
        "pizza"
    ],
    "wof:name":"Hide-A-Way Pizza",
    "wof:placetype":"venue"
},
  "geometry": {"coordinates":[-71.57759900000001,42.096809],"type":"Point"}
}