{
  "type": "Feature",
  "properties": {
    "addr:full": "95 Uxbridge Rd Mendon MA 01756",
    "addr:housenumber": "95",
    "addr:postcode": "01756",
    "addr:street": "Uxbridge Rd",
    "iso:country": "US",
    "ovtr:label": "Hide-A-Way Pizza, 95 Uxbridge Rd Mendon MA US",
    "ovtr:similarity": 2.017508029937744,
    "sg:address": "95 Uxbridge Rd",
    "sg:city": "Mendon",
    "sg:classifiers": [
      {
        "category": "Restaurant",
        "type": "Food \u0026 Drink"
      }
    ],
    "sg:phone": "+1 508 478 0600",
    "sg:postcode": "01756",
    "sg:province": "MA",
    "sg:tags": [
      "pizza"
    ],
    "wof:name": "Hide-A-Way Pizza",
    "wof:placetype": "venue"
  },
  "geometry": {"coordinates":[-71.577599,42.096809],"type":"Point"}
}
