{
  "type": "Feature",
  "properties": {
    "addr:full": "1201 Broadway Saugus MA 01906",
    "addr:housenumber": "1201",
    "addr:postcode": "01906",
    "addr:street": "Broadway",
    "iso:country": "US",
    "sg:address": "1201 Broadway",
    "sg:city": "Saugus",
    "sg:classifiers": [
      {
        "category": "Bakery",
        "type": "Food \u0026 Drink"
      },
      {
        "category": "Coffee \u0026 Tea",
        "type": "Food \u0026 Drink"
      },
      {
        "category": "Bagels",
        "type": "Food \u0026 Drink"
      },
      {
        "category": "Donuts",
        "type": "Food \u0026 Drink"
      }
    ],
    "sg:menulink": "http://www.allmenus.com/ma/saugus/143340-dunkin-donuts/menu/",
    "sg:phone": "+1 781 231 6825",
    "sg:postcode": "01906",
    "sg:province": "MA",
    "sg:tags": [
      "american",
      "diner",
      "pastry"
    ],
    "wof:name": "Dunkin' Donuts",
    "wof:placetype": "venue"
  },
  "geometry": {"coordinates":[-71.025921,42.46087],"type":"Point"}
}
