{
  "type": "Feature",
  "properties": {
    "addr:full": "44 N Main St Webster MA 01570",
    "addr:housenumber": "44",
    "addr:postcode": "01570",
    "addr:street": "N Main St",
    "iso:country": "US",
    "sg:address": "44 N Main St",
    "sg:city": "Webster",
    "sg:classifiers": [
      {
        "category": "Personal",
        "subcategory": "Beauty Salon",
        "type": "Services"
      }
    ],
    "sg:phone": "+1 508 943 1437",
    "sg:postcode": "01570",
    "sg:province": "MA",
    "wof:name": "Roni's Beauty Boutique",
    "wof:placetype": "venue"
  },
  "geometry": {"coordinates":[-71.878325,42.055312],"type":"Point"}
}
