{
  "type": "Feature",
  "properties": {
    "iso:country":"US",
    "sg:address":"188 Park Ave",
    "sg:city":"Worcester",
    "sg:classifiers":[
        {
            "category":"Shopping",
            "subcategory":"Optical Goods",
            "type":"Retail Goods"
        }
    ],
    "sg:phone":"+1 508 799 5256",
    "sg:postcode":"01609",
    "sg:province":"MA",
    "sg:tags":[
        "optician"
    ],
    "wof:name":"Metz Opticians Inc",
    "wof:placetype":"venue"
},
  "geometry": {"coordinates":[-71.81309899999999,42.273742],"type":"Point"}
}