{
  "type": "Feature",
  "properties": {
    "iso:country":"US",
    "sg:address":"68 Rome Blvd",
    "sg:city":"Attleboro",
    "sg:classifiers":[
        {
            "category":"Travel",
            "subcategory":"Travel Agent",
            "type":"Entertainment"
        }
    ],
    "sg:phone":"+1 508 223 2893",
    "sg:postcode":"02703",
    "sg:province":"MA",
    "sg:tags":[
        "agency"
    ],
    "wof:name":"Cruise Navigators",
    "wof:placetype":"venue"
},
  "geometry": {"coordinates":[-71.30800000000001,41.941927],"type":"Point"}
}