{
  "type": "Feature",
  "properties": {
    "iso:country":"US",
    "sg:address":"55 Lowell St",
    "sg:city":"Woburn",
    "sg:classifiers":[
        {
            "category":"Building & Trades",
            "subcategory":"Locksmith",
            "type":"Services"
        }
    ],
    "sg:phone":"+1 781 404 4608",
    "sg:postcode":"01801",
    "sg:province":"MA",
    "sg:tags":[
        "key"
    ],
    "wof:name":"Complete Locksmith",
    "wof:placetype":"venue"
},
  "geometry": {"coordinates":[-71.16004599999999,42.493837],"type":"Point"}
}