{
  "type": "Feature",
  "properties": {
    "addr:full":"12 Depot Sq Sheffield MA 01257",
    "addr:housenumber":"12",
    "addr:postcode":"01257",
    "addr:street":"Depot Sq",
    "iso:country":"US",
    "sg:address":"12 Depot Sq",
    "sg:city":"Sheffield",
    "sg:classifiers":[
        {
            "category":"Government",
            "subcategory":"Office",
            "type":"Public Place"
        }
    ],
    "sg:phone":"+1 413 229 7001",
    "sg:postcode":"01257",
    "sg:province":"MA",
    "sg:tags":[
        "city",
        "taxation"
    ],
    "wof:name":"Sheffield Town Assessors",
    "wof:placetype":"venue"
},
  "geometry": {"coordinates":[-73.353403,42.110972],"type":"Point"}
}