{
  "type": "Feature",
  "properties": {
    "iso:country":"US",
    "sg:address":"2 Michaels Mall",
    "sg:city":"Winthrop",
    "sg:classifiers":[
        {
            "category":"Sports & Exercise",
            "subcategory":"Gym",
            "type":"Entertainment"
        }
    ],
    "sg:phone":"+1 617 846 4949",
    "sg:postcode":"02152",
    "sg:province":"MA",
    "sg:tags":[
        "club",
        "health",
        "studio",
        "gymnasium"
    ],
    "wof:name":"Curves For Women",
    "wof:placetype":"venue"
},
  "geometry": {"coordinates":[-70.98580699999999,42.375108],"type":"Point"}
}