{
  "type": "Feature",
  "properties": {
    "addr:full":"1637 Massachusetts Ave Cambridge MA 02138",
    "addr:housenumber":"1637",
    "addr:postcode":"02138",
    "addr:street":"Massachusetts Ave",
    "iso:country":"US",
    "sg:address":"1637 Massachusetts Ave",
    "sg:city":"Cambridge",
    "sg:classifiers":[
        {
            "category":"Building & Trades",
            "subcategory":"Locksmith",
            "type":"Services"
        }
    ],
    "sg:phone":"+1 617 299 2148",
    "sg:postcode":"02138",
    "sg:province":"MA",
    "sg:tags":[
        "key"
    ],
    "wof:name":"Emergency Locksmith Available 24 7",
    "wof:placetype":"venue"
},
  "geometry": {"coordinates":[-71.119558,42.381011],"type":"Point"}
}