{
  "type": "Feature",
  "properties": {
    "addr:full":"457 Washington St Duxbury MA 02332",
    "addr:housenumber":"457",
    "addr:postcode":"02332",
    "addr:street":"Washington St",
    "iso:country":"US",
    "sg:address":"457 Washington St",
    "sg:city":"Duxbury",
    "sg:classifiers":[
        {
            "category":"Education",
            "subcategory":"School",
            "type":"Public Place"
        }
    ],
    "sg:phone":"+1 781 934 7555",
    "sg:postcode":"02332",
    "sg:province":"MA",
    "sg:website":"www.duxbayms.com",
    "wof:name":"Duxbury Bay Maritime School",
    "wof:placetype":"venue"
},
  "geometry": {"coordinates":[-70.67155700000001,42.038858],"type":"Point"}
}