{
  "type": "Feature",
  "properties": {
    "iso:country":"US",
    "sg:address":"25 Spring St",
    "sg:city":"Webster",
    "sg:classifiers":[
        {
            "category":"Building & Trades",
            "subcategory":"Plumbing",
            "type":"Services"
        }
    ],
    "sg:phone":"+1 508 943 3852",
    "sg:postcode":"01570",
    "sg:province":"MA",
    "sg:tags":[
        "plumbing",
        "contractor"
    ],
    "wof:name":"JCP Plumbing & Heating Inc",
    "wof:placetype":"venue"
},
  "geometry": {"coordinates":[-71.87488999999999,42.046817],"type":"Point"}
}