{
  "type": "Feature",
  "properties": {
    "addr:full": "25 Spring St Webster MA 01570",
    "addr:housenumber": "25",
    "addr:postcode": "01570",
    "addr:street": "Spring St",
    "iso:country": "US",
    "sg:address": "25 Spring St",
    "sg:city": "Webster",
    "sg:classifiers": [
      {
        "category": "Building \u0026 Trades",
        "subcategory": "Plumbing",
        "type": "Services"
      }
    ],
    "sg:phone": "+1 508 943 3852",
    "sg:postcode": "01570",
    "sg:province": "MA",
    "sg:tags": [
      "plumbing",
      "contractor"
    ],
    "wof:name": "JCP Plumbing \u0026 Heating Inc",
    "wof:placetype": "venue"
  },
  "geometry": {"coordinates":[-71.87489,42.046817],"type":"Point"}
}
