{
  "type": "Feature",
  "properties": {
    "iso:country":"US",
    "sg:address":"276 W Main St",
    "sg:city":"Northborough",
    "sg:classifiers":[
        {
            "category":"Shopping",
            "subcategory":"Clothing, Apparel, & Fashions",
            "type":"Retail Goods"
        }
    ],
    "sg:phone":"+1 508 393 6101",
    "sg:postcode":"01532",
    "sg:province":"MA",
    "wof:name":"Strut Of Northborough",
    "wof:placetype":"venue"
},
  "geometry": {"coordinates":[-71.65648,42.308785],"type":"Point"}
}