{
  "type": "Feature",
  "properties": {
    "addr:full":"11 Granville Rd Southwick MA 01077",
    "addr:housenumber":"11",
    "addr:postcode":"01077",
    "addr:street":"Granville Rd",
    "iso:country":"US",
    "sg:address":"11 Granville Rd",
    "sg:city":"Southwick",
    "sg:classifiers":[
        {
            "category":"Professional",
            "subcategory":"Management & Consulting",
            "type":"Services"
        }
    ],
    "sg:phone":"+1 413 569 6270",
    "sg:postcode":"01077",
    "sg:province":"MA",
    "sg:tags":[
        "home",
        "demonstration"
    ],
    "wof:name":"Amway Distributors",
    "wof:placetype":"venue"
},
  "geometry": {"coordinates":[-72.77144,42.05511],"type":"Point"}
}