{
  "type": "Feature",
  "properties": {
    "addr:full": "161 Main St Groton MA 01450",
    "addr:housenumber": "161",
    "addr:postcode": "01450",
    "addr:street": "Main St",
    "iso:country": "US",
    "sg:address": "161 Main St",
    "sg:city": "Groton",
    "sg:classifiers": [
      {
        "category": "Freight",
        "type": "Transportation"
      }
    ],
    "sg:phone": "+1 978 448 0048",
    "sg:postcode": "01450",
    "sg:province": "MA",
    "sg:tags": [
      "broker",
      "trucking"
    ],
    "sg:website": "www.amtransportation.com",
    "wof:name": "A M Transportation Svc",
    "wof:placetype": "venue"
  },
  "geometry": {"coordinates":[-71.570775,42.607646],"type":"Point"}
}
