{
  "type": "Feature",
  "properties": {
    "iso:country":"US",
    "sg:address":"52 Centre St",
    "sg:city":"Middleboro",
    "sg:classifiers":[
        {
            "category":"Personal",
            "subcategory":"Tanning Parlor",
            "type":"Services"
        },
        {
            "category":"Personal",
            "type":"Services"
        }
    ],
    "sg:phone":"+1 508 946 0600",
    "sg:postcode":"02346",
    "sg:province":"MA",
    "sg:tags":[
        "salon"
    ],
    "wof:name":"Sun Rays Tanning Salon",
    "wof:placetype":"venue"
},
  "geometry": {"coordinates":[-70.910768,41.892903],"type":"Point"}
}