{
  "type": "Feature",
  "properties": {
    "addr:full": "248 Evergreen Ave Braintree MA 02184",
    "addr:housenumber": "248",
    "addr:postcode": "02184",
    "addr:street": "Evergreen Ave",
    "iso:country": "US",
    "sg:address": "248 Evergreen Ave",
    "sg:city": "Braintree",
    "sg:classifiers": [
      {
        "category": "Building \u0026 Trades",
        "subcategory": "Plumbing",
        "type": "Services"
      }
    ],
    "sg:phone": "+1 781 848 2629",
    "sg:postcode": "02184",
    "sg:province": "MA",
    "sg:tags": [
      "plumber",
      "industrial",
      "contractors-commercial"
    ],
    "wof:name": "Frank Riley Plumbing",
    "wof:placetype": "venue"
  },
  "geometry": {"coordinates":[-70.996574,42.188129],"type":"Point"}
}
