{
  "type": "Feature",
  "properties": {
    "iso:country":"US",
    "sg:address":"7 Forest Park Dr",
    "sg:city":"Waltham",
    "sg:classifiers":[
        {
            "category":"Building & Trades",
            "subcategory":"Electrical",
            "type":"Services"
        }
    ],
    "sg:phone":"+1   ",
    "sg:postcode":"02452",
    "sg:province":"MA",
    "sg:tags":[
        "electrical",
        "contractor"
    ],
    "wof:name":"Master Electrician",
    "wof:placetype":"venue"
},
  "geometry": {"coordinates":[-71.224926,42.396601],"type":"Point"}
}