{
  "type": "Feature",
  "properties": {
    "iso:country":"US",
    "sg:address":"241 Edgewater Dr",
    "sg:city":"Wakefield",
    "sg:classifiers":[
        {
            "category":"Professional",
            "subcategory":"Computer Services",
            "type":"Services"
        }
    ],
    "sg:phone":"+1 781 246 5525",
    "sg:postcode":"01880",
    "sg:province":"MA",
    "sg:tags":[
        "consultant",
        "designer"
    ],
    "wof:name":"Total Tec Systems Inc",
    "wof:placetype":"venue"
},
  "geometry": {"coordinates":[-71.044718,42.51929],"type":"Point"}
}