{
  "type": "Feature",
  "properties": {
    "addr:full": "386 W Boylston St Worcester MA 01606",
    "addr:housenumber": "386",
    "addr:postcode": "01606",
    "addr:street": "W Boylston St",
    "iso:country": "US",
    "sg:address": "386 W Boylston St",
    "sg:city": "Worcester",
    "sg:classifiers": [
      {
        "category": "Shopping",
        "subcategory": "Clothing, Apparel, \u0026 Fashions",
        "type": "Retail Goods"
      }
    ],
    "sg:phone": "+1 508 852 5200",
    "sg:postcode": "01606",
    "sg:province": "MA",
    "wof:name": "Thredz",
    "wof:placetype": "venue"
  },
  "geometry": {"coordinates":[-71.8006,42.304862],"type":"Point"}
}
