{
  "type": "Feature",
  "properties": {
    "iso:country":"US",
    "sg:address":"10 High Street",
    "sg:city":"Boston",
    "sg:classifiers":[
        {
            "category":"Professional",
            "subcategory":"Lawyer & Legal Services",
            "type":"Services"
        }
    ],
    "sg:phone":"+1 617 720 5900",
    "sg:postcode":"02110",
    "sg:province":"MA",
    "wof:name":"Veznaian Mary PC",
    "wof:placetype":"venue"
},
  "geometry": {"coordinates":[-71.056797,42.353363],"type":"Point"}
}