{
  "type": "Feature",
  "properties": {
    "addr:full": "43 Federal St Newburyport MA 01950",
    "addr:housenumber": "43",
    "addr:postcode": "01950",
    "addr:street": "Federal St",
    "iso:country": "US",
    "sg:address": "43 Federal St",
    "sg:city": "Newburyport",
    "sg:classifiers": [
      {
        "category": "Professional",
        "type": "Services"
      }
    ],
    "sg:phone": "+1 978 463 7820",
    "sg:postcode": "01950",
    "sg:province": "MA",
    "sg:tags": [
      "establishment"
    ],
    "wof:name": "Grafton Technologies Inc",
    "wof:placetype": "venue"
  },
  "geometry": {"coordinates":[-70.866974,42.807128],"type":"Point"}
}
