{
  "type": "Feature",
  "properties": {
    "addr:full": "1 Joslin Pl Fitchburg MA 01420",
    "addr:housenumber": "1",
    "addr:postcode": "01420",
    "addr:street": "Joslin Pl",
    "iso:country": "US",
    "sg:address": "1 Joslin Pl",
    "sg:city": "Fitchburg",
    "sg:classifiers": [
      {
        "category": "Building \u0026 Trades",
        "subcategory": "Construction",
        "type": "Services"
      }
    ],
    "sg:phone": "+1 978 342 1428",
    "sg:postcode": "01420",
    "sg:province": "MA",
    "sg:tags": [
      "downspouts",
      "gutter"
    ],
    "wof:name": "Frank Gordon \u0026 Sons",
    "wof:placetype": "venue"
  },
  "geometry": {"coordinates":[-71.788575,42.581299],"type":"Point"}
}
