{
  "type": "Feature",
  "properties": {
    "addr:full": "77 Mulberry St Leicester MA 01524",
    "addr:housenumber": "77",
    "addr:postcode": "01524",
    "addr:street": "Mulberry St",
    "iso:country": "US",
    "sg:address": "77 Mulberry St",
    "sg:city": "Leicester",
    "sg:classifiers": [
      {
        "category": "Professional",
        "type": "Services"
      }
    ],
    "sg:phone": "+1   ",
    "sg:postcode": "01524",
    "sg:province": "MA",
    "wof:name": "Crozier Inc",
    "wof:placetype": "venue"
  },
  "geometry": {"coordinates":[-71.888588,42.258982],"type":"Point"}
}
