{
  "type": "Feature",
  "properties": {
    "iso:country":"US",
    "sg:address":"600 W Cummings Park Ste 1000",
    "sg:city":"Woburn",
    "sg:classifiers":[
        {
            "category":"Professional",
            "subcategory":"Lawyer & Legal Services",
            "type":"Services"
        }
    ],
    "sg:phone":"+1 781 933 2122",
    "sg:postcode":"01801",
    "sg:province":"MA",
    "wof:name":"Crest Group",
    "wof:placetype":"venue"
},
  "geometry": {"coordinates":[-71.127014,42.496135],"type":"Point"}
}