{
  "type": "Feature",
  "properties": {
    "addr:full":"120 W Boylston St West Boylston MA 01583",
    "addr:housenumber":"120",
    "addr:postcode":"01583",
    "addr:street":"W Boylston St",
    "iso:country":"US",
    "sg:address":"120 W Boylston St",
    "sg:city":"West Boylston",
    "sg:classifiers":[
        {
            "category":"Government",
            "subcategory":"Office",
            "type":"Public Place"
        }
    ],
    "sg:phone":"+1 508 835 6916",
    "sg:postcode":"01583",
    "sg:province":"MA",
    "sg:tags":[
        "city",
        "resource",
        "human"
    ],
    "wof:name":"West Boylston Council On Aging",
    "wof:placetype":"venue"
},
  "geometry": {"coordinates":[-71.784441,42.357349],"type":"Point"}
}