{
  "type": "Feature",
  "properties": {
    "addr:full": "1588 S Main St Athol MA 01331",
    "addr:housenumber": "1588",
    "addr:postcode": "01331",
    "addr:street": "S Main St",
    "iso:country": "US",
    "ovtr:label": "Advance Auto Parts, 1588 S Main St Athol MA US",
    "ovtr:similarity": 3.567241907119751,
    "sg:address": "1588 S Main St",
    "sg:city": "Athol",
    "sg:classifiers": [
      {
        "category": "Autos \u0026 Motor Vehicles",
        "subcategory": "Auto Supplies",
        "type": "Retail Goods"
      }
    ],
    "sg:phone": "+1 978 575 0060",
    "sg:postcode": "01331",
    "sg:province": "MA",
    "sg:tags": [
      "automobile",
      "parts"
    ],
    "sg:website": "www.advanceautoparts.com",
    "wof:name": "Advance Auto Parts Inc",
    "wof:placetype": "venue"
  },
  "geometry": {"coordinates":[-72.261386,42.582871],"type":"Point"}
}
