{
  "type": "Feature",
  "properties": {
    "iso:country":"US",
    "sg:address":"1588 S Main St",
    "sg:city":"Athol",
    "sg:classifiers":[
        {
            "category":"Autos & Motor Vehicles",
            "subcategory":"Auto Supplies",
            "type":"Retail Goods"
        }
    ],
    "sg:phone":"+1 978 575 0060",
    "sg:postcode":"01331",
    "sg:province":"MA",
    "sg:tags":[
        "automobile",
        "parts"
    ],
    "sg:website":"www.advanceautoparts.com",
    "wof:name":"Advance Auto Parts Inc",
    "wof:placetype":"venue"
},
  "geometry": {"coordinates":[-72.261386,42.582871],"type":"Point"}
}