{
  "type": "Feature",
  "properties": {
    "iso:country":"US",
    "sg:address":"39 Mansfield St",
    "sg:city":"Gloucester",
    "sg:classifiers":[
        {
            "category":"Farming",
            "subcategory":"Livestock Farm",
            "type":"Manufacturing & Wholesale Goods"
        }
    ],
    "sg:phone":"+1   ",
    "sg:postcode":"01930",
    "sg:province":"MA",
    "sg:tags":[
        "specialty",
        "animal"
    ],
    "wof:name":"Exotic Flights Aviary",
    "wof:placetype":"venue"
},
  "geometry": {"coordinates":[-70.66916500000001,42.611284],"type":"Point"}
}