{
  "type": "Feature",
  "properties": {
    "addr:full":"124 School St Granby MA 01033",
    "addr:housenumber":"124",
    "addr:postcode":"01033",
    "addr:street":"School St",
    "iso:country":"US",
    "sg:address":"124 School St",
    "sg:city":"Granby",
    "sg:classifiers":[
        {
            "category":"Real Estate",
            "subcategory":"Developer",
            "type":"Services"
        }
    ],
    "sg:phone":"+1 413 467 7329",
    "sg:postcode":"01033",
    "sg:province":"MA",
    "wof:name":"Casino Valley Development Inc",
    "wof:placetype":"venue"
},
  "geometry": {"coordinates":[-72.47238,42.261894],"type":"Point"}
}