{
  "type": "Feature",
  "properties": {
    "addr:full": "14 Mcgrath Hwy # 195 Twin City Plaza Somerville MA 02143",
    "addr:housenumber": "14",
    "addr:postcode": "02143",
    "addr:street": "Mcgrath Hwy # 195 Twin",
    "iso:country": "US",
    "sg:address": "14 Mcgrath Hwy # 195 Twin City Plaza",
    "sg:city": "Somerville",
    "sg:classifiers": [
      {
        "category": "Restaurant",
        "type": "Food \u0026 Drink"
      }
    ],
    "sg:phone": "+1 617 628 1820",
    "sg:postcode": "02143",
    "sg:province": "MA",
    "sg:tags": [
      "pizza"
    ],
    "sg:website": "www.papaginos.com",
    "wof:name": "Papa Gino's",
    "wof:placetype": "venue"
  },
  "geometry": {"coordinates":[-71.083267,42.374397],"type":"Point"}
}
