{
  "type": "Feature",
  "properties": {
    "addr:full": "56 Peter Bulkeley Rd Concord MA 01742",
    "addr:housenumber": "56",
    "addr:postcode": "01742",
    "addr:street": "Peter Bulkeley Rd",
    "iso:country": "US",
    "sg:address": "56 Peter Bulkeley Rd",
    "sg:city": "Concord",
    "sg:classifiers": [
      {
        "category": "Building \u0026 Trades",
        "subcategory": "Construction",
        "type": "Services"
      }
    ],
    "sg:phone": "+1 978 369 0307",
    "sg:postcode": "01742",
    "sg:province": "MA",
    "sg:tags": [
      "contractor"
    ],
    "wof:name": "Building Solutions",
    "wof:placetype": "venue"
  },
  "geometry": {"coordinates":[-71.383421,42.4332],"type":"Point"}
}
