{
  "type": "Feature",
  "properties": {
    "iso:country":"US",
    "sg:address":"56 Peter Bulkeley Rd",
    "sg:city":"Concord",
    "sg:classifiers":[
        {
            "category":"Building & Trades",
            "subcategory":"Construction",
            "type":"Services"
        }
    ],
    "sg:phone":"+1 978 369 0307",
    "sg:postcode":"01742",
    "sg:province":"MA",
    "sg:tags":[
        "contractor"
    ],
    "wof:name":"Building Solutions",
    "wof:placetype":"venue"
},
  "geometry": {"coordinates":[-71.383421,42.4332],"type":"Point"}
}