{
  "type": "Feature",
  "properties": {
    "iso:country":"US",
    "sg:address":"25 Thompson Rd",
    "sg:city":"Webster",
    "sg:classifiers":[
        {
            "category":"Professional",
            "subcategory":"Business Services",
            "type":"Services"
        }
    ],
    "sg:phone":"+1 508 949 1515",
    "sg:postcode":"01570",
    "sg:province":"MA",
    "wof:name":"Webster Day Reporting",
    "wof:placetype":"venue"
},
  "geometry": {"coordinates":[-71.863045,42.057576],"type":"Point"}
}