{
  "type": "Feature",
  "properties": {
    "iso:country":"US",
    "sg:address":"54 Main St",
    "sg:city":"Marlborough",
    "sg:classifiers":[
        {
            "category":"Bakery",
            "type":"Food & Drink"
        },
        {
            "category":"Coffee & Tea",
            "type":"Food & Drink"
        },
        {
            "category":"Bagels",
            "type":"Food & Drink"
        },
        {
            "category":"Donuts",
            "type":"Food & Drink"
        }
    ],
    "sg:menulink":"http://www.allmenus.com/ma/marlborough/143077-dunkin-donuts/menu/",
    "sg:phone":"+1 508 485 6286",
    "sg:postcode":"01752",
    "sg:province":"MA",
    "sg:tags":[
        "american",
        "diner",
        "pastry"
    ],
    "wof:name":"Dunkin' Donuts",
    "wof:placetype":"venue"
},
  "geometry": {"coordinates":[-71.54510500000001,42.347038],"type":"Point"}
}