{
  "type": "Feature",
  "properties": {
    "addr:full": "54 Main St Marlborough MA 01752",
    "addr:housenumber": "54",
    "addr:postcode": "01752",
    "addr:street": "Main St",
    "iso:country": "US",
    "sg:address": "54 Main St",
    "sg:city": "Marlborough",
    "sg:classifiers": [
      {
        "category": "Bakery",
        "type": "Food \u0026 Drink"
      },
      {
        "category": "Coffee \u0026 Tea",
        "type": "Food \u0026 Drink"
      },
      {
        "category": "Bagels",
        "type": "Food \u0026 Drink"
      },
      {
        "category": "Donuts",
        "type": "Food \u0026 Drink"
      }
    ],
    "sg:menulink": "http://www.allmenus.com/ma/marlborough/143077-dunkin-donuts/menu/",
    "sg:phone": "+1 508 485 6286",
    "sg:postcode": "01752",
    "sg:province": "MA",
    "sg:tags": [
      "american",
      "diner",
      "pastry"
    ],
    "wof:name": "Dunkin' Donuts",
    "wof:placetype": "venue"
  },
  "geometry": {"coordinates":[-71.545105,42.347038],"type":"Point"}
}
