{
  "type": "Feature",
  "properties": {
    "addr:full":"199 Rosewood Dr Danvers MA 01923",
    "addr:housenumber":"199",
    "addr:postcode":"01923",
    "addr:street":"Rosewood Dr",
    "iso:country":"US",
    "sg:address":"199 Rosewood Dr",
    "sg:city":"Danvers",
    "sg:classifiers":[
        {
            "category":"Insurance",
            "subcategory":"Insurance Agent",
            "type":"Services"
        }
    ],
    "sg:phone":"+1 978 740 8777",
    "sg:postcode":"01923",
    "sg:province":"MA",
    "wof:name":"Innovative Risk Svc",
    "wof:placetype":"venue"
},
  "geometry": {"coordinates":[-70.98834100000001,42.565126],"type":"Point"}
}