{
  "type": "Feature",
  "properties": {
    "iso:country":"US",
    "sg:address":"20 Keeler St Ste 1",
    "sg:city":"Pittsfield",
    "sg:classifiers":[
        {
            "category":"Manufacturing",
            "subcategory":"Metals",
            "type":"Manufacturing & Wholesale Goods"
        }
    ],
    "sg:phone":"+1 413 442 1557",
    "sg:postcode":"01201",
    "sg:province":"MA",
    "sg:tags":[
        "foundry"
    ],
    "wof:name":"Berkshire Fine Arts Foundry",
    "wof:placetype":"venue"
},
  "geometry": {"coordinates":[-73.24786400000001,42.481491],"type":"Point"}
}