{
  "type": "Feature",
  "properties": {
    "addr:full": "20 N Main St Bellingham MA 02019",
    "addr:housenumber": "20",
    "addr:postcode": "02019",
    "addr:street": "N Main St",
    "iso:country": "US",
    "sg:address": "20 N Main St",
    "sg:city": "Bellingham",
    "sg:classifiers": [
      {
        "category": "Utilities",
        "subcategory": "Mobile Phone",
        "type": "Services"
      }
    ],
    "sg:phone": "+1 508 966 3939",
    "sg:postcode": "02019",
    "sg:province": "MA",
    "sg:tags": [
      "telephone",
      "cellular"
    ],
    "wof:name": "Freedom Communications",
    "wof:placetype": "venue"
  },
  "geometry": {"coordinates":[-71.476343,42.090058],"type":"Point"}
}
