{
  "type": "Feature",
  "properties": {
    "iso:country":"US",
    "sg:address":"10A Birch Ln",
    "sg:city":"Byfield",
    "sg:classifiers":[
        {
            "category":"Professional",
            "subcategory":"Computer Services",
            "type":"Services"
        }
    ],
    "sg:phone":"+1 978 361 5914",
    "sg:postcode":"01922",
    "sg:province":"MA",
    "sg:tags":[
        "design",
        "system",
        "network"
    ],
    "wof:name":"Stephen Whitmore - It Consultant",
    "wof:placetype":"venue"
},
  "geometry": {"coordinates":[-70.927672,42.743263],"type":"Point"}
}