{
  "type": "Feature",
  "properties": {
    "addr:full":"100 Cambridgeside Pl Ste 228 Cambridge MA 02141",
    "addr:housenumber":"100",
    "addr:postcode":"02141",
    "addr:street":"Cambridgeside Pl Ste 228",
    "iso:country":"US",
    "sg:address":"100 Cambridgeside Pl Ste 228",
    "sg:city":"Cambridge",
    "sg:classifiers":[
        {
            "category":"Shopping",
            "subcategory":"Clothing, Apparel, & Fashions",
            "type":"Retail Goods"
        },
        {
            "category":"Shopping",
            "subcategory":"Shoes",
            "type":"Retail Goods"
        }
    ],
    "sg:phone":"+1 617 225 2245",
    "sg:postcode":"02141",
    "sg:province":"MA",
    "sg:tags":[
        "apparel",
        "sportswear",
        "store",
        "women's"
    ],
    "sg:website":"http://www.ladyfootlocker.com/",
    "wof:name":"Lady Foot Locker",
    "wof:placetype":"venue"
},
  "geometry": {"coordinates":[-71.07567,42.36694],"type":"Point"}
}