{
  "type": "Feature",
  "properties": {
    "addr:full": "186 Atlantic Ave Marblehead MA 01945",
    "addr:housenumber": "186",
    "addr:postcode": "01945",
    "addr:street": "Atlantic Ave",
    "iso:country": "US",
    "sg:address": "186 Atlantic Ave",
    "sg:city": "Marblehead",
    "sg:classifiers": [
      {
        "category": "Professional",
        "subcategory": "Art Services",
        "type": "Services"
      }
    ],
    "sg:phone": "+1   ",
    "sg:postcode": "01945",
    "sg:province": "MA",
    "sg:tags": [
      "photo",
      "photography",
      "commercial",
      "studio"
    ],
    "wof:name": "Beebe Photo",
    "wof:placetype": "venue"
  },
  "geometry": {"coordinates":[-70.86424,42.491197],"type":"Point"}
}
