{
  "type": "Feature",
  "properties": {
    "iso:country":"US",
    "sg:address":"40 Friend St",
    "sg:city":"Amesbury",
    "sg:classifiers":[
        {
            "category":"Banks & Credit Unions",
            "subcategory":"Bank",
            "type":"Services"
        }
    ],
    "sg:phone":"+1 978 000 1111",
    "sg:postcode":"01913",
    "sg:province":"MA",
    "wof:name":"Sovereign Bank",
    "wof:placetype":"venue"
},
  "geometry": {"coordinates":[-70.933184,42.856535],"type":"Point"}
}