{
  "type": "Feature",
  "properties": {
    "addr:full":"488 Boston Rd Sutton MA 01590",
    "addr:housenumber":"488",
    "addr:postcode":"01590",
    "addr:street":"Boston Rd",
    "iso:country":"US",
    "sg:address":"488 Boston Rd",
    "sg:city":"Sutton",
    "sg:classifiers":[
        {
            "category":"Farming",
            "subcategory":"Farm",
            "type":"Manufacturing & Wholesale Goods"
        }
    ],
    "sg:phone":"+1 508 581 8755",
    "sg:postcode":"01590",
    "sg:province":"MA",
    "wof:name":"Pembury House Farm",
    "wof:placetype":"venue"
},
  "geometry": {"coordinates":[-71.786805,42.134911],"type":"Point"}
}