{
  "type": "Feature",
  "properties": {
    "addr:full": "88 Two Ponds Rd Falmouth MA 02540",
    "addr:housenumber": "88",
    "addr:postcode": "02540",
    "addr:street": "Two Ponds Rd",
    "iso:country": "US",
    "sg:address": "88 Two Ponds Rd",
    "sg:city": "Falmouth",
    "sg:classifiers": [
      {
        "category": "Health Services",
        "subcategory": "Doctor",
        "type": "Services"
      }
    ],
    "sg:phone": "+1 508 548 7528",
    "sg:postcode": "02540",
    "sg:province": "MA",
    "sg:tags": [
      "physician",
      "surgeon"
    ],
    "wof:name": "Kazuyoshi Sato MD",
    "wof:placetype": "venue"
  },
  "geometry": {"coordinates":[-70.635248,41.556748],"type":"Point"}
}
