{
  "type": "Feature",
  "properties": {
    "iso:country":"US",
    "sg:address":"2 Thatcher Rd",
    "sg:city":"Middleboro",
    "sg:classifiers":[
        {
            "category":"Professional",
            "subcategory":"Employment Agencies",
            "type":"Services"
        }
    ],
    "sg:phone":"+1 508 947 9520",
    "sg:postcode":"02360",
    "sg:province":"MA",
    "wof:name":"Professional Bartending Svc",
    "wof:placetype":"venue"
},
  "geometry": {"coordinates":[-70.607827,41.870956],"type":"Point"}
}