{
  "type": "Feature",
  "properties": {
    "iso:country":"US",
    "sg:address":"677 Massachusetts Avenue",
    "sg:city":"Arlington",
    "sg:classifiers":[
        {
            "category":"Sports & Exercise",
            "subcategory":"Gym",
            "type":"Entertainment"
        }
    ],
    "sg:phone":"+1 781 641 0107",
    "sg:postcode":"02476",
    "sg:province":"MA",
    "sg:tags":[
        "trainer"
    ],
    "wof:name":"Gimbel Jos B Dr Podiatrist",
    "wof:placetype":"venue"
},
  "geometry": {"coordinates":[-71.155081,42.415932],"type":"Point"}
}