{
  "type": "Feature",
  "properties": {
    "addr:full": "28 Webster St Rockland MA 02370",
    "addr:housenumber": "28",
    "addr:postcode": "02370",
    "addr:street": "Webster St",
    "iso:country": "US",
    "sg:address": "28 Webster St",
    "sg:city": "Rockland",
    "sg:classifiers": [
      {
        "category": "Shopping",
        "subcategory": "Books",
        "type": "Retail Goods"
      },
      {
        "category": "Education",
        "subcategory": "School",
        "type": "Public Place"
      }
    ],
    "sg:phone": "+1 781 982 2665",
    "sg:postcode": "02370",
    "sg:province": "MA",
    "sg:tags": [
      "educational",
      "material",
      "supply"
    ],
    "wof:name": "Teachers Rule",
    "wof:placetype": "venue"
  },
  "geometry": {"coordinates":[-70.915613,42.131674],"type":"Point"}
}
