{
  "type": "Feature",
  "properties": {
    "iso:country":"US",
    "sg:address":"28 Webster St",
    "sg:city":"Rockland",
    "sg:classifiers":[
        {
            "category":"Shopping",
            "subcategory":"Books",
            "type":"Retail Goods"
        },
        {
            "category":"Education",
            "subcategory":"School",
            "type":"Public Place"
        }
    ],
    "sg:phone":"+1 781 982 2665",
    "sg:postcode":"02370",
    "sg:province":"MA",
    "sg:tags":[
        "educational",
        "material",
        "supply"
    ],
    "wof:name":"Teachers Rule",
    "wof:placetype":"venue"
},
  "geometry": {"coordinates":[-70.91561299999999,42.131674],"type":"Point"}
}