{
  "type": "Feature",
  "properties": {
    "addr:full": "125 Parker Hill Avenue Roxbury Crossing MA 02120",
    "addr:housenumber": "125",
    "addr:postcode": "02120",
    "addr:street": "Parker Hill Avenue",
    "iso:country": "US",
    "sg:address": "125 Parker Hill Avenue",
    "sg:city": "Roxbury Crossing",
    "sg:classifiers": [
      {
        "category": "Health Services",
        "subcategory": "Doctor",
        "type": "Services"
      },
      {
        "category": "Sports \u0026 Exercise",
        "subcategory": "Gym",
        "type": "Entertainment"
      }
    ],
    "sg:phone": "+1 617 735 9200",
    "sg:postcode": "02120",
    "sg:province": "MA",
    "sg:tags": [
      "trainer"
    ],
    "wof:name": "Gomolin David MD",
    "wof:placetype": "venue"
  },
  "geometry": {"coordinates":[-71.107104,42.330355],"type":"Point"}
}
