{
  "type": "Feature",
  "properties": {
    "addr:full":"61 Alden Rd Holliston MA 01746",
    "addr:housenumber":"61",
    "addr:postcode":"01746",
    "addr:street":"Alden Rd",
    "iso:country":"US",
    "sg:address":"61 Alden Rd",
    "sg:city":"Holliston",
    "sg:classifiers":[
        {
            "category":"Home & Garden",
            "subcategory":"Building Materials",
            "type":"Retail Goods"
        }
    ],
    "sg:phone":"+1 508 429 7325",
    "sg:postcode":"01746",
    "sg:province":"MA",
    "sg:tags":[
        "insulation",
        "heat"
    ],
    "wof:name":"Knauf Fiber Glass",
    "wof:placetype":"venue"
},
  "geometry": {"coordinates":[-71.40674,42.183104],"type":"Point"}
}