{
  "type": "Feature",
  "properties": {
    "iso:country":"US",
    "sg:address":"50 Congress St Ste 1040",
    "sg:city":"Boston",
    "sg:classifiers":[
        {
            "category":"Banks & Credit Unions",
            "subcategory":"Investment Brokerage",
            "type":"Services"
        }
    ],
    "sg:phone":"+1 617 742 6666",
    "sg:postcode":"02109",
    "sg:province":"MA",
    "sg:tags":[
        "investing"
    ],
    "sg:website":"www.zevin.com",
    "wof:name":"Zevin Asset Management",
    "wof:placetype":"venue"
},
  "geometry": {"coordinates":[-71.056382,42.357517],"type":"Point"}
}