{
  "type": "Feature",
  "properties": {
    "addr:full": "204 Pinehurst Ave Swansea MA 02777",
    "addr:housenumber": "204",
    "addr:postcode": "02777",
    "addr:street": "Pinehurst Ave",
    "iso:country": "US",
    "ovtr:label": "Thrill City Cycle, 204 Pinehurst Ave Swansea MA US",
    "ovtr:similarity": 2.2874929904937744,
    "sg:address": "204 Pinehurst Ave",
    "sg:city": "Swansea",
    "sg:classifiers": [
      {
        "category": "Retail",
        "subcategory": "Repair Shop",
        "type": "Services"
      }
    ],
    "sg:phone": "+1 508 324 1717",
    "sg:postcode": "02777",
    "sg:province": "MA",
    "sg:tags": [
      "scooter",
      "motorcycle",
      "motor"
    ],
    "wof:name": "Thrill City Cycle",
    "wof:placetype": "venue"
  },
  "geometry": {"coordinates":[-71.209316,41.727094],"type":"Point"}
}
