{
  "type": "Feature",
  "properties": {
    "iso:country":"US",
    "sg:address":"204 Pinehurst Ave",
    "sg:city":"Swansea",
    "sg:classifiers":[
        {
            "category":"Retail",
            "subcategory":"Repair Shop",
            "type":"Services"
        }
    ],
    "sg:phone":"+1 508 324 1717",
    "sg:postcode":"02777",
    "sg:province":"MA",
    "sg:tags":[
        "scooter",
        "motorcycle",
        "motor"
    ],
    "wof:name":"Thrill City Cycle",
    "wof:placetype":"venue"
},
  "geometry": {"coordinates":[-71.209316,41.727094],"type":"Point"}
}