{
  "type": "Feature",
  "properties": {
    "iso:country":"US",
    "sg:address":"195 Winchester St",
    "sg:city":"Brookline",
    "sg:classifiers":[
        {
            "category":"Building & Trades",
            "subcategory":"Locksmith",
            "type":"Services"
        }
    ],
    "sg:phone":"+1 617 714 1192",
    "sg:postcode":"02446",
    "sg:province":"MA",
    "sg:tags":[
        "key"
    ],
    "wof:name":"Affordable Locksmith",
    "wof:placetype":"venue"
},
  "geometry": {"coordinates":[-71.13215700000001,42.345249],"type":"Point"}
}