{
  "type": "Feature",
  "properties": {
    "addr:full":"109 Canton St North Easton MA 02356",
    "addr:housenumber":"109",
    "addr:postcode":"02356",
    "addr:street":"Canton St",
    "iso:country":"US",
    "sg:address":"109 Canton St",
    "sg:city":"North Easton",
    "sg:classifiers":[
        {
            "category":"Real Estate",
            "subcategory":"Real Estate Agent",
            "type":"Services"
        }
    ],
    "sg:phone":"+1 508 238 7979",
    "sg:postcode":"02356",
    "sg:province":"MA",
    "sg:tags":[
        "buyer",
        "broker"
    ],
    "wof:name":"Realty Search",
    "wof:placetype":"venue"
},
  "geometry": {"coordinates":[-71.115939,42.075985],"type":"Point"}
}