{
  "type": "Feature",
  "properties": {
    "iso:country":"US",
    "sg:address":"247 Mountain Dr",
    "sg:city":"Pittsfield",
    "sg:classifiers":[
        {
            "category":"Professional",
            "subcategory":"Management & Consulting",
            "type":"Services"
        }
    ],
    "sg:phone":"+1   ",
    "sg:postcode":"01201",
    "sg:province":"MA",
    "wof:name":"Dovetail Racing",
    "wof:placetype":"venue"
},
  "geometry": {"coordinates":[-73.20048300000001,42.421657],"type":"Point"}
}