{
  "type": "Feature",
  "properties": {
    "addr:full": "392 Chelmsford St Lowell MA 01851",
    "addr:housenumber": "392",
    "addr:postcode": "01851",
    "addr:street": "Chelmsford St",
    "atp:label": "Burger King, 392 Chelmsford Street LOWELL MA US",
    "atp:similarity": 3.193614959716797,
    "iso:country": "US",
    "ovtr:label": "Burger King, 392 Chelmsford St Lowell MA US",
    "ovtr:similarity": 2.6528079509735107,
    "sg:address": "392 Chelmsford St",
    "sg:city": "Lowell",
    "sg:classifiers": [
      {
        "category": "Restaurant",
        "type": "Food \u0026 Drink"
      }
    ],
    "sg:menulink": "http://www.allmenus.com/ma/lowell/197616-burger-king/menu/",
    "sg:phone": "+1 978 459 6542",
    "sg:postcode": "01851",
    "sg:province": "MA",
    "sg:tags": [
      "burger",
      "american"
    ],
    "wof:name": "Burger King",
    "wof:placetype": "venue"
  },
  "geometry": {"coordinates":[-71.321594,42.629348],"type":"Point"}
}
