{
  "type": "Feature",
  "properties": {
    "addr:full":"146 Burncoat St Worcester MA 01606",
    "addr:housenumber":"146",
    "addr:postcode":"01606",
    "addr:street":"Burncoat St",
    "iso:country":"US",
    "sg:address":"146 Burncoat St",
    "sg:city":"Worcester",
    "sg:classifiers":[
        {
            "category":"Organizations",
            "subcategory":"Religious Organization",
            "type":"Services"
        }
    ],
    "sg:phone":"+1 508 853 4843",
    "sg:postcode":"01606",
    "sg:province":"MA",
    "sg:tags":[
        "church"
    ],
    "sg:website":"www.worcesternevarene.chweb.org",
    "wof:name":"Church Of The Nazarene",
    "wof:placetype":"venue"
},
  "geometry": {"coordinates":[-71.789874,42.296651],"type":"Point"}
}