{
  "type": "Feature",
  "properties": {
    "addr:full": "95 Washington St Foxboro MA 02035",
    "addr:housenumber": "95",
    "addr:postcode": "02035",
    "addr:street": "Washington St",
    "iso:country": "US",
    "sg:address": "95 Washington St",
    "sg:city": "Foxboro",
    "sg:phone": "+1 508 543 5200",
    "sg:postcode": "02035",
    "sg:province": "MA",
    "sg:tags": [
      "oil"
    ],
    "wof:name": "Star Petroleum Co",
    "wof:placetype": "venue"
  },
  "geometry": {"coordinates":[-71.271103,42.09048],"type":"Point"}
}
