{
  "type": "Feature",
  "properties": {
    "iso:country":"US",
    "sg:address":"98 Cambridge St",
    "sg:city":"Middleboro",
    "sg:classifiers":[
        {
            "category":"Building & Trades",
            "subcategory":"Construction",
            "type":"Services"
        }
    ],
    "sg:phone":"+1 508 923 1111",
    "sg:postcode":"02346",
    "sg:province":"MA",
    "sg:tags":[
        "asbestos",
        "removal"
    ],
    "wof:name":"Environmental Response Svc",
    "wof:placetype":"venue"
},
  "geometry": {"coordinates":[-70.91986199999999,41.897709],"type":"Point"}
}