{
  "type": "Feature",
  "properties": {
    "iso:country":"US",
    "sg:address":"44 Winthrop St",
    "sg:city":"Newton",
    "sg:classifiers":[
        {
            "category":"Wholesale",
            "subcategory":"Apparel",
            "type":"Manufacturing & Wholesale Goods"
        }
    ],
    "sg:phone":"+1 617 244 3638",
    "sg:postcode":"02465",
    "sg:province":"MA",
    "sg:tags":[
        "clothing"
    ],
    "wof:name":"Silk Scapes",
    "wof:placetype":"venue"
},
  "geometry": {"coordinates":[-71.23035299999999,42.345044],"type":"Point"}
}