{
  "type": "Feature",
  "properties": {
    "addr:full": "31 Lukes Way Plymouth MA 02360",
    "addr:housenumber": "31",
    "addr:postcode": "02360",
    "addr:street": "Lukes Way",
    "iso:country": "US",
    "sg:address": "31 Lukes Way",
    "sg:city": "Plymouth",
    "sg:classifiers": [
      {
        "category": "Shopping",
        "subcategory": "Gifts \u0026 Souvenirs",
        "type": "Retail Goods"
      }
    ],
    "sg:phone": "+1 781 585 7619",
    "sg:postcode": "02360",
    "sg:province": "MA",
    "sg:tags": [
      "shop"
    ],
    "wof:name": "Lucky Leprechaun Inc",
    "wof:placetype": "venue"
  },
  "geometry": {"coordinates":[-70.714161,41.921023],"type":"Point"}
}
