{
  "type": "Feature",
  "properties": {
    "iso:country":"US",
    "sg:address":"31 Lukes Way",
    "sg:city":"Plymouth",
    "sg:classifiers":[
        {
            "category":"Shopping",
            "subcategory":"Gifts & Souvenirs",
            "type":"Retail Goods"
        }
    ],
    "sg:phone":"+1 781 585 7619",
    "sg:postcode":"02360",
    "sg:province":"MA",
    "sg:tags":[
        "shop"
    ],
    "wof:name":"Lucky Leprechaun Inc",
    "wof:placetype":"venue"
},
  "geometry": {"coordinates":[-70.714161,41.921023],"type":"Point"}
}