{
  "type": "Feature",
  "properties": {
    "iso:country":"US",
    "sg:address":"723 Falmouth Rd",
    "sg:city":"Mashpee",
    "sg:classifiers":[
        {
            "category":"Autos & Motor Vehicles",
            "subcategory":"Fuel & Gas Station",
            "type":"Retail Goods"
        }
    ],
    "sg:phone":"+1 508 477 9100",
    "sg:postcode":"02649",
    "sg:province":"MA",
    "sg:tags":[
        "oil"
    ],
    "wof:name":"Johnny's Tune & Lube Mashpee",
    "wof:placetype":"venue"
},
  "geometry": {"coordinates":[-70.490994,41.609393],"type":"Point"}
}