{
  "type": "Feature",
  "properties": {
    "addr:full": "723 Falmouth Rd Mashpee MA 02649",
    "addr:housenumber": "723",
    "addr:postcode": "02649",
    "addr:street": "Falmouth Rd",
    "iso:country": "US",
    "sg:address": "723 Falmouth Rd",
    "sg:city": "Mashpee",
    "sg:classifiers": [
      {
        "category": "Autos \u0026 Motor Vehicles",
        "subcategory": "Fuel \u0026 Gas Station",
        "type": "Retail Goods"
      }
    ],
    "sg:phone": "+1 508 477 9100",
    "sg:postcode": "02649",
    "sg:province": "MA",
    "sg:tags": [
      "oil"
    ],
    "wof:name": "Johnny's Tune \u0026 Lube Mashpee",
    "wof:placetype": "venue"
  },
  "geometry": {"coordinates":[-70.490994,41.609393],"type":"Point"}
}
