{
  "type": "Feature",
  "properties": {
    "iso:country":"US",
    "sg:address":"2 Piedmont St",
    "sg:city":"Methuen",
    "sg:classifiers":[
        {
            "category":"Recreation",
            "type":"Entertainment"
        }
    ],
    "sg:phone":"+1 978 857 2856",
    "sg:postcode":"01844",
    "sg:province":"MA",
    "sg:tags":[
        "entertainers-family",
        "business"
    ],
    "wof:name":"Great Times Entertainment",
    "wof:placetype":"venue"
},
  "geometry": {"coordinates":[-71.215042,42.72905],"type":"Point"}
}