{
  "type": "Feature",
  "properties": {
    "iso:country":"US",
    "sg:address":"1 Factory St",
    "sg:city":"Sagamore",
    "sg:classifiers":[
        {
            "category":"Home & Garden",
            "subcategory":"Home Furnishings",
            "type":"Retail Goods"
        }
    ],
    "sg:phone":"+1 508 833 0663",
    "sg:postcode":"02563",
    "sg:province":"MA",
    "sg:tags":[
        "curtain",
        "made",
        "drapery"
    ],
    "wof:name":"Home Decor Outlet",
    "wof:placetype":"venue"
},
  "geometry": {"coordinates":[-70.489406,41.757937],"type":"Point"}
}