{
  "type": "Feature",
  "properties": {
    "addr:full":"1 Pennock Rd Chelmsford MA 01824",
    "addr:housenumber":"1",
    "addr:postcode":"01824",
    "addr:street":"Pennock Rd",
    "iso:country":"US",
    "sg:address":"1 Pennock Rd",
    "sg:city":"Chelmsford",
    "sg:classifiers":[
        {
            "category":"Professional",
            "type":"Services"
        }
    ],
    "sg:phone":"+1 978 256 5884",
    "sg:postcode":"01824",
    "sg:province":"MA",
    "sg:tags":[
        "establishment"
    ],
    "wof:name":"At & T Cits",
    "wof:placetype":"venue"
},
  "geometry": {"coordinates":[-71.381816,42.598855],"type":"Point"}
}