{
  "type": "Feature",
  "properties": {
    "iso:country":"US",
    "sg:address":"6 Gardner Ln",
    "sg:city":"Westford",
    "sg:classifiers":[
        {
            "category":"Professional",
            "subcategory":"Management & Consulting",
            "type":"Services"
        }
    ],
    "sg:phone":"+1   ",
    "sg:postcode":"01886",
    "sg:province":"MA",
    "sg:tags":[
        "financial"
    ],
    "wof:name":"Churchill Consulting Group",
    "wof:placetype":"venue"
},
  "geometry": {"coordinates":[-71.445087,42.584547],"type":"Point"}
}