{
  "type": "Feature",
  "properties": {
    "addr:full":"7 Park St Attleboro MA 02703",
    "addr:housenumber":"7",
    "addr:postcode":"02703",
    "addr:street":"Park St",
    "iso:country":"US",
    "sg:address":"7 Park St",
    "sg:city":"Attleboro",
    "sg:classifiers":[
        {
            "category":"Professional",
            "subcategory":"Secretarial Services",
            "type":"Services"
        }
    ],
    "sg:phone":"+1 508 222 3572",
    "sg:postcode":"02703",
    "sg:province":"MA",
    "sg:tags":[
        "mail",
        "reporting",
        "direct",
        "manuscript",
        "advertising"
    ],
    "wof:name":"Lettercraft Service",
    "wof:placetype":"venue"
},
  "geometry": {"coordinates":[-71.283856,41.944536],"type":"Point"}
}