{
  "type": "Feature",
  "properties": {
    "iso:country":"US",
    "sg:address":"6 N Washington St",
    "sg:city":"North Attleboro",
    "sg:classifiers":[
        {
            "category":"Banks & Credit Unions",
            "subcategory":"Financial Services",
            "type":"Services"
        }
    ],
    "sg:phone":"+1   ",
    "sg:postcode":"02760",
    "sg:province":"MA",
    "sg:tags":[
        "residential",
        "trust",
        "including",
        "investment",
        "unit"
    ],
    "wof:name":"Chang Real Estate Trust",
    "wof:placetype":"venue"
},
  "geometry": {"coordinates":[-71.332686,41.982164],"type":"Point"}
}