{
  "type": "Feature",
  "properties": {
    "addr:full": "1132 Hancock St Quincy MA 02169",
    "addr:housenumber": "1132",
    "addr:postcode": "02169",
    "addr:street": "Hancock St",
    "iso:country": "US",
    "sg:address": "1132 Hancock St",
    "sg:city": "Quincy",
    "sg:classifiers": [
      {
        "category": "Autos \u0026 Motor Vehicles",
        "subcategory": "Auto Supplies",
        "type": "Retail Goods"
      }
    ],
    "sg:phone": "+1 617 773 1088",
    "sg:postcode": "02169",
    "sg:province": "MA",
    "sg:tags": [
      "tire"
    ],
    "sg:website": "www.sullivantire.com",
    "wof:name": "Sullivan Tire \u0026 Auto Svc Co",
    "wof:placetype": "venue"
  },
  "geometry": {"coordinates":[-71.005719,42.25429],"type":"Point"}
}
