{
  "type": "Feature",
  "properties": {
    "addr:full": "1475 Memorial Dr Chicopee MA 01020",
    "addr:housenumber": "1475",
    "addr:postcode": "01020",
    "addr:street": "Memorial Dr",
    "iso:country": "US",
    "ovtr:label": "H\u0026R Block, 1487 Memorial Dr Chicopee MA US",
    "ovtr:similarity": 2.6602869033813477,
    "sg:address": "1475 Memorial Dr",
    "sg:city": "Chicopee",
    "sg:classifiers": [
      {
        "category": "Professional",
        "subcategory": "Accounting \u0026 Tax Preparation",
        "type": "Services"
      },
      {
        "category": "Banks \u0026 Credit Unions",
        "subcategory": "Financial Services",
        "type": "Services"
      }
    ],
    "sg:phone": "+1 413 532 9991",
    "sg:postcode": "01020",
    "sg:province": "MA",
    "sg:tags": [
      "return",
      "preparation-business",
      "taxes-consultants",
      "loan",
      "reporting",
      "representative",
      "alternative",
      "bookkeeping"
    ],
    "sg:website": "http://www.hrblock.com",
    "wof:name": "H\u0026R Block",
    "wof:placetype": "venue"
  },
  "geometry": {"coordinates":[-72.573819,42.1978],"type":"Point"}
}
