{
  "type": "Feature",
  "properties": {
    "addr:full": "166 Meadow St Westfield MA 01085",
    "addr:housenumber": "166",
    "addr:postcode": "01085",
    "addr:street": "Meadow St",
    "iso:country": "US",
    "sg:address": "166 Meadow St",
    "sg:city": "Westfield",
    "sg:classifiers": [
      {
        "category": "Shopping",
        "subcategory": "Used Merchandise",
        "type": "Retail Goods"
      }
    ],
    "sg:phone": "+1 413 562 4434",
    "sg:postcode": "01085",
    "sg:province": "MA",
    "wof:name": "Shutters \u0026 Vines",
    "wof:placetype": "venue"
  },
  "geometry": {"coordinates":[-72.739338,42.120194],"type":"Point"}
}
