{
  "type": "Feature",
  "properties": {
    "addr:full":"285 Third St. #412 (Cambridge Innovation Center) Cambridge MA 02142",
    "addr:housenumber":"285",
    "addr:postcode":"02142",
    "addr:street":"Third St. # 412",
    "iso:country":"US",
    "sg:address":"285 Third St. #412 (Cambridge Innovation Center)",
    "sg:city":"Cambridge",
    "sg:classifiers":[
        {
            "category":"Professional",
            "subcategory":"Computer Services",
            "type":"Services"
        }
    ],
    "sg:phone":"+1 415 297 2614",
    "sg:postcode":"02142",
    "sg:province":"MA",
    "sg:tags":[
        "venture-capital",
        "incubator",
        "accelerator",
        "international",
        "network"
    ],
    "sg:website":"http://www.opinno.com",
    "wof:name":"Opinno",
    "wof:placetype":"venue"
},
  "geometry": {"coordinates":[-71.087959,42.363276],"type":"Point"}
}