{
  "type": "Feature",
  "properties": {
    "addr:full": "22 Densmore St North Quincy MA 02171",
    "addr:housenumber": "22",
    "addr:postcode": "02171",
    "addr:street": "Densmore St",
    "iso:country": "US",
    "sg:address": "22 Densmore St",
    "sg:city": "North Quincy",
    "sg:classifiers": [
      {
        "category": "Manufacturing",
        "subcategory": "Metals",
        "type": "Manufacturing \u0026 Wholesale Goods"
      }
    ],
    "sg:phone": "+1 617 328 1010",
    "sg:postcode": "02171",
    "sg:province": "MA",
    "sg:tags": [
      "treating",
      "heat"
    ],
    "sg:website": "www.indht.com",
    "wof:name": "Industrial Heat Treating Inc",
    "wof:placetype": "venue"
  },
  "geometry": {"coordinates":[-71.038436,42.281285],"type":"Point"}
}
