{
  "type": "Feature",
  "properties": {
    "iso:country":"US",
    "sg:address":"22 Densmore St",
    "sg:city":"North Quincy",
    "sg:classifiers":[
        {
            "category":"Manufacturing",
            "subcategory":"Metals",
            "type":"Manufacturing & Wholesale Goods"
        }
    ],
    "sg:phone":"+1 617 328 1010",
    "sg:postcode":"02171",
    "sg:province":"MA",
    "sg:tags":[
        "treating",
        "heat"
    ],
    "sg:website":"www.indht.com",
    "wof:name":"Industrial Heat Treating Inc",
    "wof:placetype":"venue"
},
  "geometry": {"coordinates":[-71.038436,42.281285],"type":"Point"}
}