{
  "type": "Feature",
  "properties": {
    "iso:country":"US",
    "sg:address":"9 Edna Dr",
    "sg:city":"East Freetown",
    "sg:classifiers":[
        {
            "category":"Building & Trades",
            "subcategory":"Construction",
            "type":"Services"
        }
    ],
    "sg:phone":"+1 508 763 1950",
    "sg:postcode":"02703",
    "sg:province":"MA",
    "sg:tags":[
        "coping",
        "plastering",
        "tiling",
        "pool",
        "swimming"
    ],
    "wof:name":"Narciso Enterprises Inc",
    "wof:placetype":"venue"
},
  "geometry": {"coordinates":[-71.305116,41.945818],"type":"Point"}
}