{
  "type": "Feature",
  "properties": {
    "addr:full": "1513 Iyannough Rd Hyannis MA 02601",
    "addr:housenumber": "1513",
    "addr:postcode": "02601",
    "addr:street": "Iyannough Rd",
    "iso:country": "US",
    "sg:address": "1513 Iyannough Rd",
    "sg:city": "Hyannis",
    "sg:classifiers": [
      {
        "category": "Professional",
        "subcategory": "Lawyer \u0026 Legal Services",
        "type": "Services"
      }
    ],
    "sg:phone": "+1 508 790 5400",
    "sg:postcode": "02601",
    "sg:province": "MA",
    "sg:tags": [
      "attorney"
    ],
    "sg:website": "www.nutter.com",
    "wof:name": "Nutter Mc Clennan \u0026 Fish",
    "wof:placetype": "venue"
  },
  "geometry": {"coordinates":[-70.317994,41.678639],"type":"Point"}
}
