{
  "type": "Feature",
  "properties": {
    "iso:country":"US",
    "sg:address":"1513 Iyannough Rd",
    "sg:city":"Hyannis",
    "sg:classifiers":[
        {
            "category":"Professional",
            "subcategory":"Lawyer & Legal Services",
            "type":"Services"
        }
    ],
    "sg:phone":"+1 508 790 5400",
    "sg:postcode":"02601",
    "sg:province":"MA",
    "sg:tags":[
        "attorney"
    ],
    "sg:website":"www.nutter.com",
    "wof:name":"Nutter Mc Clennan & Fish",
    "wof:placetype":"venue"
},
  "geometry": {"coordinates":[-70.317994,41.678639],"type":"Point"}
}