{
  "type": "Feature",
  "properties": {
    "addr:full":"36 Lantz Ave Whitman MA 02382",
    "addr:housenumber":"36",
    "addr:postcode":"02382",
    "addr:street":"Lantz Ave",
    "iso:country":"US",
    "sg:address":"36 Lantz Ave",
    "sg:city":"Whitman",
    "sg:classifiers":[
        {
            "category":"Local Transit",
            "type":"Transportation"
        }
    ],
    "sg:phone":"+1 781 447 6495",
    "sg:postcode":"02382",
    "sg:province":"MA",
    "sg:tags":[
        "airport"
    ],
    "wof:name":"Hanson Livery",
    "wof:placetype":"venue"
},
  "geometry": {"coordinates":[-70.944222,42.073603],"type":"Point"}
}