{
  "type": "Feature",
  "properties": {
    "iso:country":"US",
    "sg:address":"114 Turnpike Rd",
    "sg:city":"Westborough",
    "sg:classifiers":[
        {
            "category":"Banks & Credit Unions",
            "subcategory":"Bank",
            "type":"Services"
        }
    ],
    "sg:phone":"+1 508 366 4515",
    "sg:postcode":"01581",
    "sg:province":"MA",
    "sg:tags":[
        "loan"
    ],
    "wof:name":"Centex Home Equity",
    "wof:placetype":"venue"
},
  "geometry": {"coordinates":[-71.603762,42.284925],"type":"Point"}
}