{
  "type": "Feature",
  "properties": {
    "addr:full":"33 Waldo St Worcester MA 01608",
    "addr:housenumber":"33",
    "addr:postcode":"01608",
    "addr:street":"Waldo St",
    "iso:country":"US",
    "sg:address":"33 Waldo St",
    "sg:city":"Worcester",
    "sg:classifiers":[
        {
            "category":"Government",
            "subcategory":"Office",
            "type":"Public Place"
        }
    ],
    "sg:phone":"+1 508 753 2929",
    "sg:postcode":"01608",
    "sg:province":"MA",
    "sg:tags":[
        "federal",
        "program",
        "adm"
    ],
    "wof:name":"US Small Business Adm",
    "wof:placetype":"venue"
},
  "geometry": {"coordinates":[-71.80021499999999,42.264908],"type":"Point"}
}