{
  "type": "Feature",
  "properties": {
    "addr:full": "385 Broadway Revere MA 02151",
    "addr:housenumber": "385",
    "addr:postcode": "02151",
    "addr:street": "Broadway",
    "iso:country": "US",
    "sg:address": "385 Broadway",
    "sg:city": "Revere",
    "sg:classifiers": [
      {
        "category": "Communications",
        "subcategory": "Newspaper",
        "type": "Services"
      }
    ],
    "sg:phone": "+1 781 485 0588",
    "sg:postcode": "02151",
    "sg:province": "MA",
    "sg:tags": [
      "print",
      "medium"
    ],
    "wof:name": "Winthrop Independent Newspaper",
    "wof:placetype": "venue"
  },
  "geometry": {"coordinates":[-71.012229,42.41012],"type":"Point"}
}
