{
  "type": "Feature",
  "properties": {
    "addr:full":"408 State Rd North Dartmouth MA 02747",
    "addr:housenumber":"408",
    "addr:postcode":"02747",
    "addr:street":"State Rd",
    "iso:country":"US",
    "sg:address":"408 State Rd",
    "sg:city":"North Dartmouth",
    "sg:classifiers":[
        {
            "category":"Health Services",
            "subcategory":"Doctor",
            "type":"Services"
        }
    ],
    "sg:phone":"+1 508 990 3000",
    "sg:postcode":"02747",
    "sg:province":"MA",
    "sg:tags":[
        "dentist"
    ],
    "wof:name":"Orthodonic Centers Of New Engl",
    "wof:placetype":"venue"
},
  "geometry": {"coordinates":[-70.997665,41.640366],"type":"Point"}
}