{
  "type": "Feature",
  "properties": {
    "addr:full":"577 Main St Hudson MA 01749",
    "addr:housenumber":"577",
    "addr:postcode":"01749",
    "addr:street":"Main St",
    "iso:country":"US",
    "sg:address":"577 Main St",
    "sg:city":"Hudson",
    "sg:classifiers":[
        {
            "category":"Shopping",
            "subcategory":"Catalog Store",
            "type":"Retail Goods"
        }
    ],
    "sg:phone":"+1 978 562 1289",
    "sg:postcode":"01749",
    "sg:province":"MA",
    "sg:tags":[
        "mail",
        "order"
    ],
    "wof:name":"FSP Books",
    "wof:placetype":"venue"
},
  "geometry": {"coordinates":[-71.50491100000001,42.391431],"type":"Point"}
}