{
  "type": "Feature",
  "properties": {
    "addr:full":"77 Franklin St Boston MA 02110",
    "addr:housenumber":"77",
    "addr:postcode":"02110",
    "addr:street":"Franklin St",
    "iso:country":"US",
    "sg:address":"77 Franklin St",
    "sg:city":"Boston",
    "sg:classifiers":[
        {
            "category":"Sports & Exercise",
            "subcategory":"Sports Center",
            "type":"Entertainment"
        }
    ],
    "sg:phone":"+1 617 695 3200",
    "sg:postcode":"02110",
    "sg:province":"MA",
    "sg:tags":[
        "manager",
        "promoter"
    ],
    "wof:name":"Orpheus Sports & Entertainment Consulting Company",
    "wof:placetype":"venue"
},
  "geometry": {"coordinates":[-71.058037,42.355412],"type":"Point"}
}