{
  "type": "Feature",
  "properties": {
    "addr:full":"3 Joyce St West Townsend MA 01474",
    "addr:housenumber":"3",
    "addr:postcode":"01474",
    "addr:street":"Joyce St",
    "iso:country":"US",
    "sg:address":"3 Joyce St",
    "sg:city":"West Townsend",
    "sg:classifiers":[
        {
            "category":"Shopping",
            "subcategory":"Computers & Home Electronics",
            "type":"Retail Goods"
        }
    ],
    "sg:phone":"+1 978 597 5559",
    "sg:postcode":"01474",
    "sg:province":"MA",
    "sg:tags":[
        "equipment",
        "satellite",
        "system"
    ],
    "sg:website":"www.astec.tv",
    "wof:name":"Astrovision Technologies-Astec",
    "wof:placetype":"venue"
},
  "geometry": {"coordinates":[-71.73891999999999,42.682107],"type":"Point"}
}