{
  "type": "Feature",
  "properties": {
    "addr:full":"18 Railroad Ave Andover MA 01810",
    "addr:housenumber":"18",
    "addr:postcode":"01810",
    "addr:street":"Railroad Ave",
    "iso:country":"US",
    "sg:address":"18 Railroad Ave",
    "sg:city":"Andover",
    "sg:classifiers":[
        {
            "category":"Professional",
            "subcategory":"Employment Agencies",
            "type":"Services"
        }
    ],
    "sg:phone":"+1 978 623 3344",
    "sg:postcode":"01810",
    "sg:province":"MA",
    "sg:tags":[
        "help",
        "contractor"
    ],
    "wof:name":"Quality Works",
    "wof:placetype":"venue"
},
  "geometry": {"coordinates":[-71.144116,42.661017],"type":"Point"}
}