{
  "type": "Feature",
  "properties": {
    "addr:full":"100 Properzi Way Somerville MA 02143",
    "addr:housenumber":"100",
    "addr:postcode":"02143",
    "addr:street":"Properzi Way",
    "iso:country":"US",
    "sg:address":"100 Properzi Way",
    "sg:city":"Somerville",
    "sg:classifiers":[
        {
            "category":"Real Estate",
            "subcategory":"Architect",
            "type":"Services"
        }
    ],
    "sg:phone":"+1 617 629 2100",
    "sg:postcode":"02143",
    "sg:province":"MA",
    "sg:website":"www.msafdie.com",
    "wof:name":"Moshe Safdie Assoc",
    "wof:placetype":"venue"
},
  "geometry": {"coordinates":[-71.10724,42.379965],"type":"Point"}
}