{
  "type": "Feature",
  "properties": {
    "iso:country":"US",
    "sg:address":"2393 Main St",
    "sg:city":"Lancaster",
    "sg:classifiers":[
        {
            "category":"Professional",
            "subcategory":"Business Services",
            "type":"Services"
        }
    ],
    "sg:phone":"+1   ",
    "sg:postcode":"01523",
    "sg:province":"MA",
    "wof:name":"Apple Lane Group LLC",
    "wof:placetype":"venue"
},
  "geometry": {"coordinates":[-71.70943200000001,42.487353],"type":"Point"}
}