{
  "type": "Feature",
  "properties": {
    "iso:country":"US",
    "sg:address":"24 Cross St",
    "sg:city":"Somerville",
    "sg:classifiers":[
        {
            "category":"Home & Garden",
            "subcategory":"Building Materials",
            "type":"Retail Goods"
        },
        {
            "category":"Building & Trades",
            "subcategory":"Construction",
            "type":"Services"
        }
    ],
    "sg:phone":"+1 617 666 8029",
    "sg:postcode":"02145",
    "sg:province":"MA",
    "sg:tags":[
        "insulation",
        "contractor"
    ],
    "wof:name":"General Insulabtion Co",
    "wof:placetype":"venue"
},
  "geometry": {"coordinates":[-71.086647,42.387589],"type":"Point"}
}