{
  "type": "Feature",
  "properties": {
    "addr:full": "24 Cross St Somerville MA 02145",
    "addr:housenumber": "24",
    "addr:postcode": "02145",
    "addr:street": "Cross St",
    "iso:country": "US",
    "sg:address": "24 Cross St",
    "sg:city": "Somerville",
    "sg:classifiers": [
      {
        "category": "Home \u0026 Garden",
        "subcategory": "Building Materials",
        "type": "Retail Goods"
      },
      {
        "category": "Building \u0026 Trades",
        "subcategory": "Construction",
        "type": "Services"
      }
    ],
    "sg:phone": "+1 617 666 8029",
    "sg:postcode": "02145",
    "sg:province": "MA",
    "sg:tags": [
      "insulation",
      "contractor"
    ],
    "wof:name": "General Insulabtion Co",
    "wof:placetype": "venue"
  },
  "geometry": {"coordinates":[-71.086647,42.387589],"type":"Point"}
}
