{
  "type": "Feature",
  "properties": {
    "addr:full": "100 Green St Fairhaven MA 02719",
    "addr:housenumber": "100",
    "addr:postcode": "02719",
    "addr:street": "Green St",
    "iso:country": "US",
    "sg:address": "100 Green St",
    "sg:city": "Fairhaven",
    "sg:classifiers": [
      {
        "category": "Government",
        "subcategory": "Office",
        "type": "Public Place"
      }
    ],
    "sg:phone": "+1 508 992 4524",
    "sg:postcode": "02719",
    "sg:province": "MA",
    "wof:name": "Fort Phoenix",
    "wof:placetype": "venue"
  },
  "geometry": {"coordinates":[-70.901969,41.63751],"type":"Point"}
}
