{
  "type": "Feature",
  "properties": {
    "iso:country":"US",
    "sg:address":"100 Green St",
    "sg:city":"Fairhaven",
    "sg:classifiers":[
        {
            "category":"Government",
            "subcategory":"Office",
            "type":"Public Place"
        }
    ],
    "sg:phone":"+1 508 992 4524",
    "sg:postcode":"02719",
    "sg:province":"MA",
    "wof:name":"Fort Phoenix",
    "wof:placetype":"venue"
},
  "geometry": {"coordinates":[-70.90196899999999,41.63751],"type":"Point"}
}