{
  "type": "Feature",
  "properties": {
    "iso:country":"US",
    "sg:address":"31 N Pleasant St",
    "sg:city":"Amherst",
    "sg:classifiers":[
        {
            "category":"Restaurant",
            "type":"Food & Drink"
        }
    ],
    "sg:menulink":"http://www.allmenus.com/ma/amherst/31534-antonios-pizza/menu/",
    "sg:phone":"+1 413 549 0077",
    "sg:postcode":"01002",
    "sg:province":"MA",
    "sg:tags":[
        "american",
        "pizza"
    ],
    "wof:name":"Antonio's Pizza",
    "wof:placetype":"venue"
},
  "geometry": {"coordinates":[-72.519885,42.376323],"type":"Point"}
}