{
  "type": "Feature",
  "properties": {
    "iso:country":"US",
    "sg:address":"1245 Hancock St",
    "sg:city":"Quincy",
    "sg:classifiers":[
        {
            "category":"Professional",
            "type":"Services"
        }
    ],
    "sg:phone":"+1 617 773 8338",
    "sg:postcode":"02169",
    "sg:province":"MA",
    "sg:tags":[
        "establishment"
    ],
    "wof:name":"Presidents Place Assoc",
    "wof:placetype":"venue"
},
  "geometry": {"coordinates":[-71.004035,42.251973],"type":"Point"}
}