{
  "type": "Feature",
  "properties": {
    "iso:country":"US",
    "sg:address":"59 S Meadow Rd",
    "sg:city":"Carver",
    "sg:classifiers":[
        {
            "category":"Freight",
            "type":"Transportation"
        }
    ],
    "sg:phone":"+1 508 866 9039",
    "sg:postcode":"02330",
    "sg:province":"MA",
    "sg:tags":[
        "operator",
        "trucking"
    ],
    "wof:name":"Hurley Trans",
    "wof:placetype":"venue"
},
  "geometry": {"coordinates":[-70.75369999999999,41.891571],"type":"Point"}
}