{
  "type": "Feature",
  "properties": {
    "iso:country":"US",
    "sg:address":"10 Old Harbor Rd",
    "sg:city":"Rockport",
    "sg:classifiers":[
        {
            "category":"Restaurant",
            "type":"Food & Drink"
        }
    ],
    "sg:phone":"+1   ",
    "sg:postcode":"01966",
    "sg:province":"MA",
    "wof:name":"Fresh Ketch Restaurant",
    "wof:placetype":"venue"
},
  "geometry": {"coordinates":[-70.616456,42.659866],"type":"Point"}
}