{
  "type": "Feature",
  "properties": {
    "addr:full": "10 Old Harbor Rd Rockport MA 01966",
    "addr:housenumber": "10",
    "addr:postcode": "01966",
    "addr:street": "Old Harbor Rd",
    "iso:country": "US",
    "sg:address": "10 Old Harbor Rd",
    "sg:city": "Rockport",
    "sg:classifiers": [
      {
        "category": "Restaurant",
        "type": "Food \u0026 Drink"
      }
    ],
    "sg:phone": "+1   ",
    "sg:postcode": "01966",
    "sg:province": "MA",
    "wof:name": "Fresh Ketch Restaurant",
    "wof:placetype": "venue"
  },
  "geometry": {"coordinates":[-70.616456,42.659866],"type":"Point"}
}
