{
  "type": "Feature",
  "properties": {
    "iso:country":"US",
    "sg:address":"79 Main St",
    "sg:city":"Framingham",
    "sg:classifiers":[
        {
            "category":"Sports & Exercise",
            "subcategory":"Gym",
            "type":"Entertainment"
        }
    ],
    "sg:phone":"+1 508 370 8171",
    "sg:postcode":"01702",
    "sg:province":"MA",
    "sg:tags":[
        "club",
        "health",
        "studio",
        "gymnasium"
    ],
    "wof:name":"My Fitness Trainer",
    "wof:placetype":"venue"
},
  "geometry": {"coordinates":[-71.427088,42.297032],"type":"Point"}
}