{
  "type": "Feature",
  "properties": {
    "iso:country":"US",
    "sg:address":"139 Brighton Ave",
    "sg:city":"Allston",
    "sg:classifiers":[
        {
            "category":"Building & Trades",
            "subcategory":"Cleaning & Sanitation",
            "type":"Services"
        }
    ],
    "sg:phone":"+1 617 783 2700",
    "sg:postcode":"02134",
    "sg:province":"MA",
    "wof:name":"PCC Inc",
    "wof:placetype":"venue"
},
  "geometry": {"coordinates":[-71.130842,42.35296],"type":"Point"}
}