{
  "type": "Feature",
  "properties": {
    "addr:full": "139 Brighton Ave Allston MA 02134",
    "addr:housenumber": "139",
    "addr:postcode": "02134",
    "addr:street": "Brighton Ave",
    "iso:country": "US",
    "sg:address": "139 Brighton Ave",
    "sg:city": "Allston",
    "sg:classifiers": [
      {
        "category": "Building \u0026 Trades",
        "subcategory": "Cleaning \u0026 Sanitation",
        "type": "Services"
      }
    ],
    "sg:phone": "+1 617 783 2700",
    "sg:postcode": "02134",
    "sg:province": "MA",
    "wof:name": "PCC Inc",
    "wof:placetype": "venue"
  },
  "geometry": {"coordinates":[-71.130842,42.35296],"type":"Point"}
}
