{
  "type": "Feature",
  "properties": {
    "iso:country":"US",
    "sg:address":"230 Pond St",
    "sg:city":"Natick",
    "sg:classifiers":[
        {
            "category":"Health Services",
            "subcategory":"Doctor",
            "type":"Services"
        }
    ],
    "sg:phone":"+1 508 653 2417",
    "sg:postcode":"01760",
    "sg:province":"MA",
    "sg:tags":[
        "dentist"
    ],
    "wof:name":"Fabian Ody Gonzalez DDS",
    "wof:placetype":"venue"
},
  "geometry": {"coordinates":[-71.374438,42.278093],"type":"Point"}
}