{
  "type": "Feature",
  "properties": {
    "addr:full": "27 Winn St Burlington MA 01803",
    "addr:housenumber": "27",
    "addr:postcode": "01803",
    "addr:street": "Winn St",
    "iso:country": "US",
    "sg:address": "27 Winn St",
    "sg:city": "Burlington",
    "sg:classifiers": [
      {
        "category": "Personal",
        "subcategory": "Tanning Parlor",
        "type": "Services"
      }
    ],
    "sg:phone": "+1 781 229 9700",
    "sg:postcode": "01803",
    "sg:province": "MA",
    "wof:name": "Bare Bottom Tanning Salon",
    "wof:placetype": "venue"
  },
  "geometry": {"coordinates":[-71.171799,42.489498],"type":"Point"}
}
