{
  "type": "Feature",
  "properties": {
    "addr:full":"1330 Beacon St Ste 324 Brookline MA 02446",
    "addr:housenumber":"1330",
    "addr:postcode":"02446",
    "addr:street":"Beacon St Ste 324",
    "iso:country":"US",
    "sg:address":"1330 Beacon St Ste 324",
    "sg:city":"Brookline",
    "sg:classifiers":[
        {
            "category":"Professional",
            "subcategory":"Computer Services",
            "type":"Services"
        }
    ],
    "sg:phone":"+1 617 232 8300",
    "sg:postcode":"02446",
    "sg:province":"MA",
    "sg:tags":[
        "publisher",
        "designer",
        "consultant",
        "system",
        "software",
        "developer"
    ],
    "wof:name":"C I S",
    "wof:placetype":"venue"
},
  "geometry": {"coordinates":[-71.12133,42.342239],"type":"Point"}
}