{
  "type": "Feature",
  "properties": {
    "iso:country":"US",
    "sg:address":"343 Wilbraham Rd",
    "sg:city":"Springfield",
    "sg:classifiers":[
        {
            "category":"Food & Beverages",
            "subcategory":"Specialty",
            "type":"Retail Goods"
        },
        {
            "category":"Food & Beverages",
            "subcategory":"Groceries & Convenience Stores",
            "type":"Retail Goods"
        }
    ],
    "sg:phone":"+1 413 783 7456",
    "sg:postcode":"01109",
    "sg:province":"MA",
    "sg:tags":[
        "grocers-specialty"
    ],
    "wof:name":"V J's Coin Operated Laundry",
    "wof:placetype":"venue"
},
  "geometry": {"coordinates":[-72.551649,42.11289],"type":"Point"}
}