{
  "type": "Feature",
  "properties": {
    "addr:full": "820 Washington St Gloucester MA 01930",
    "addr:housenumber": "820",
    "addr:postcode": "01930",
    "addr:street": "Washington St",
    "iso:country": "US",
    "ovtr:label": "Annisquam Village Church, 820 Washington St Gloucester MA US",
    "ovtr:similarity": 2.246284008026123,
    "sg:address": "820 Washington St",
    "sg:city": "Gloucester",
    "sg:classifiers": [
      {
        "category": "Organizations",
        "subcategory": "Religious Organization",
        "type": "Services"
      }
    ],
    "sg:phone": "+1 978 281 0376",
    "sg:postcode": "01930",
    "sg:province": "MA",
    "sg:tags": [
      "church"
    ],
    "wof:name": "Annisquam Village Church",
    "wof:placetype": "venue"
  },
  "geometry": {"coordinates":[-70.673441,42.656538],"type":"Point"}
}
