{
  "type": "Feature",
  "properties": {
    "iso:country":"US",
    "sg:address":"10 Federal St",
    "sg:city":"Salem",
    "sg:classifiers":[
        {
            "category":"Social Services",
            "subcategory":"Job Training",
            "type":"Services"
        }
    ],
    "sg:phone":"+1 978 744 2417",
    "sg:postcode":"01970",
    "sg:province":"MA",
    "sg:tags":[
        "employment"
    ],
    "wof:name":"Mass Job Training",
    "wof:placetype":"venue"
},
  "geometry": {"coordinates":[-70.894066,42.523329],"type":"Point"}
}