{
  "type": "Feature",
  "properties": {
    "addr:full":"135 Hadley St South Hadley MA 01075",
    "addr:housenumber":"135",
    "addr:postcode":"01075",
    "addr:street":"Hadley St",
    "iso:country":"US",
    "sg:address":"135 Hadley St",
    "sg:city":"South Hadley",
    "sg:classifiers":[
        {
            "category":"Personal",
            "subcategory":"Beauty Salon",
            "type":"Services"
        }
    ],
    "sg:phone":"+1 413 533 0999",
    "sg:postcode":"01075",
    "sg:province":"MA",
    "wof:name":"Jeri Lynn's Haircare",
    "wof:placetype":"venue"
},
  "geometry": {"coordinates":[-72.58842199999999,42.272761],"type":"Point"}
}