{
  "type": "Feature",
  "properties": {
    "addr:full":"17 Indian Ln Webster MA 01570",
    "addr:housenumber":"17",
    "addr:postcode":"01570",
    "addr:street":"Indian Ln",
    "iso:country":"US",
    "sg:address":"17 Indian Ln",
    "sg:city":"Webster",
    "sg:classifiers":[
        {
            "category":"Professional",
            "subcategory":"Engineering",
            "type":"Services"
        }
    ],
    "sg:phone":"+1 508 943 9889",
    "sg:postcode":"01570",
    "sg:province":"MA",
    "sg:tags":[
        "engineer"
    ],
    "wof:name":"Arion Engineers Inc",
    "wof:placetype":"venue"
},
  "geometry": {"coordinates":[-71.833319,42.024302],"type":"Point"}
}