{
  "type": "Feature",
  "properties": {
    "addr:full": "218 Union St West Springfield MA 01089",
    "addr:housenumber": "218",
    "addr:postcode": "01089",
    "addr:street": "Union St",
    "iso:country": "US",
    "ovtr:label": "Charlie's Diner, 218 Union St West Springfield MA US",
    "ovtr:similarity": 3.2963080406188965,
    "sg:address": "218 Union St",
    "sg:city": "West Springfield",
    "sg:classifiers": [
      {
        "category": "Restaurant",
        "type": "Food \u0026 Drink"
      }
    ],
    "sg:phone": "+1 413 733 8551",
    "sg:postcode": "01089",
    "sg:province": "MA",
    "wof:name": "Charlie's Diner",
    "wof:placetype": "venue"
  },
  "geometry": {"coordinates":[-72.616681,42.102498],"type":"Point"}
}
