{
  "type": "Feature",
  "properties": {
    "iso:country":"US",
    "sg:address":"150 Mount Vernon St Ste 5",
    "sg:city":"Dorchester",
    "sg:classifiers":[
        {
            "category":"Real Estate",
            "subcategory":"Real Estate Operator",
            "type":"Services"
        }
    ],
    "sg:phone":"+1 781 599 7295",
    "sg:postcode":"02125",
    "sg:province":"MA",
    "sg:tags":[
        "apartment"
    ],
    "wof:name":"Quaker Meadows Apartments Company",
    "wof:placetype":"venue"
},
  "geometry": {"coordinates":[-71.05152099999999,42.321098],"type":"Point"}
}