{
  "type": "Feature",
  "properties": {
    "addr:full": "150 Mount Vernon St Ste 5 Dorchester MA 02125",
    "addr:housenumber": "150",
    "addr:postcode": "02125",
    "addr:street": "Mount Vernon St Ste 5",
    "iso:country": "US",
    "sg:address": "150 Mount Vernon St Ste 5",
    "sg:city": "Dorchester",
    "sg:classifiers": [
      {
        "category": "Real Estate",
        "subcategory": "Real Estate Operator",
        "type": "Services"
      }
    ],
    "sg:phone": "+1 781 599 7295",
    "sg:postcode": "02125",
    "sg:province": "MA",
    "sg:tags": [
      "apartment"
    ],
    "wof:name": "Quaker Meadows Apartments Company",
    "wof:placetype": "venue"
  },
  "geometry": {"coordinates":[-71.051521,42.321098],"type":"Point"}
}
