{
  "type": "Feature",
  "properties": {
    "iso:country":"US",
    "sg:address":"78 Glover St",
    "sg:city":"Southbridge",
    "sg:classifiers":[
        {
            "category":"Building & Trades",
            "subcategory":"Construction",
            "type":"Services"
        }
    ],
    "sg:phone":"+1 508 764 0777",
    "sg:postcode":"01550",
    "sg:province":"MA",
    "sg:tags":[
        "wallcoverings-installation",
        "wallpaper",
        "painting",
        "contractor"
    ],
    "wof:name":"Donoghue Painting",
    "wof:placetype":"venue"
},
  "geometry": {"coordinates":[-72.046181,42.07515],"type":"Point"}
}