{
  "type": "Feature",
  "properties": {
    "addr:full":"15 Mansfield St Gloucester MA 01930",
    "addr:housenumber":"15",
    "addr:postcode":"01930",
    "addr:street":"Mansfield St",
    "iso:country":"US",
    "sg:address":"15 Mansfield St",
    "sg:city":"Gloucester",
    "sg:classifiers":[
        {
            "category":"Retail",
            "subcategory":"Auto Repair",
            "type":"Services"
        }
    ],
    "sg:phone":"+1 978 281 0159",
    "sg:postcode":"01930",
    "sg:province":"MA",
    "sg:tags":[
        "body",
        "automobile",
        "painting"
    ],
    "wof:name":"V & T Autobody",
    "wof:placetype":"venue"
},
  "geometry": {"coordinates":[-70.668296,42.612279],"type":"Point"}
}