{
  "type": "Feature",
  "properties": {
    "iso:country":"US",
    "sg:address":"75 Priest St",
    "sg:city":"Hudson",
    "sg:classifiers":[
        {
            "category":"Professional",
            "type":"Services"
        }
    ],
    "sg:phone":"+1 978 568 8633",
    "sg:postcode":"01749",
    "sg:province":"MA",
    "sg:tags":[
        "establishment"
    ],
    "wof:name":"Danaruma Fiberglass & Porcelin",
    "wof:placetype":"venue"
},
  "geometry": {"coordinates":[-71.553575,42.402298],"type":"Point"}
}