{
  "type": "Feature",
  "properties": {
    "addr:full": "17 Holyoke St Cambridge MA 02138",
    "addr:housenumber": "17",
    "addr:postcode": "02138",
    "addr:street": "Holyoke St",
    "iso:country": "US",
    "sg:address": "17 Holyoke St",
    "sg:city": "Cambridge",
    "sg:classifiers": [
      {
        "category": "Education",
        "subcategory": "University",
        "type": "Public Place"
      }
    ],
    "sg:phone": "+1 617 495 9649",
    "sg:postcode": "02138",
    "sg:province": "MA",
    "sg:tags": [
      "college"
    ],
    "wof:name": "Let's Go Travel",
    "wof:placetype": "venue"
  },
  "geometry": {"coordinates":[-71.118301,42.3722],"type":"Point"}
}
