{
  "type": "Feature",
  "properties": {
    "iso:country":"US",
    "sg:address":"246 Memorial Ave",
    "sg:city":"West Springfield",
    "sg:classifiers":[
        {
            "category":"Shopping",
            "subcategory":"Stationery & Office Supplies",
            "type":"Retail Goods"
        }
    ],
    "sg:phone":"+1 413 827 0500",
    "sg:postcode":"01089",
    "sg:province":"MA",
    "wof:name":"Paperworks",
    "wof:placetype":"venue"
},
  "geometry": {"coordinates":[-72.600182,42.096791],"type":"Point"}
}