{
  "type": "Feature",
  "properties": {
    "addr:full":"170 Legge St Bridgewater MA 02324",
    "addr:housenumber":"170",
    "addr:postcode":"02324",
    "addr:street":"Legge St",
    "iso:country":"US",
    "sg:address":"170 Legge St",
    "sg:city":"Bridgewater",
    "sg:classifiers":[
        {
            "category":"Building & Trades",
            "subcategory":"Cleaning & Sanitation",
            "type":"Services"
        }
    ],
    "sg:phone":"+1 508 279 0717",
    "sg:postcode":"02324",
    "sg:province":"MA",
    "sg:tags":[
        "window",
        "maintenance"
    ],
    "wof:name":"Crystal Clear Window Cleaning",
    "wof:placetype":"venue"
},
  "geometry": {"coordinates":[-70.98746300000001,41.95586],"type":"Point"}
}