{
  "type": "Feature",
  "properties": {
    "iso:country":"US",
    "sg:address":"26 Central St Fl 3",
    "sg:city":"Somerville",
    "sg:classifiers":[
        {
            "category":"Health Services",
            "subcategory":"Doctor",
            "type":"Services"
        }
    ],
    "sg:phone":"+1 617 591 6408",
    "sg:postcode":"02143",
    "sg:province":"MA",
    "sg:tags":[
        "psychiatry",
        "physician",
        "surgeon",
        "surgeons"
    ],
    "wof:name":"Regina Kelly Licsw",
    "wof:placetype":"venue"
},
  "geometry": {"coordinates":[-71.105957,42.38475],"type":"Point"}
}