{
  "type": "Feature",
  "properties": {
    "iso:country":"US",
    "sg:address":"100 Hammond St",
    "sg:city":"Waltham",
    "sg:classifiers":[
        {
            "category":"Insurance",
            "subcategory":"Hazard Insurance",
            "type":"Services"
        }
    ],
    "sg:phone":"+1 781 893 1181",
    "sg:postcode":"02451",
    "sg:province":"MA",
    "wof:name":"Regan Real Estate & Insurance",
    "wof:placetype":"venue"
},
  "geometry": {"coordinates":[-71.246628,42.380058],"type":"Point"}
}