{
  "type": "Feature",
  "properties": {
    "addr:full":"8 Drum Ln Harwich MA 02645",
    "addr:housenumber":"8",
    "addr:postcode":"02645",
    "addr:street":"Drum Ln",
    "iso:country":"US",
    "sg:address":"8 Drum Ln",
    "sg:city":"Harwich",
    "sg:classifiers":[
        {
            "category":"Retail",
            "subcategory":"Auto Repair",
            "type":"Services"
        }
    ],
    "sg:phone":"+1 508 432 0873",
    "sg:postcode":"02645",
    "sg:province":"MA",
    "sg:tags":[
        "repairing",
        "automobile"
    ],
    "wof:name":"Auto Center Of Cape Cod",
    "wof:placetype":"venue"
},
  "geometry": {"coordinates":[-70.074973,41.688508],"type":"Point"}
}