{
  "type": "Feature",
  "properties": {
    "iso:country":"US",
    "sg:address":"615 Quarry St",
    "sg:city":"Quincy",
    "sg:classifiers":[
        {
            "category":"Professional",
            "subcategory":"Business Services",
            "type":"Services"
        }
    ],
    "sg:phone":"+1 617 984 0405",
    "sg:postcode":"02169",
    "sg:province":"MA",
    "sg:tags":[
        "broker"
    ],
    "wof:name":"Centrix Group",
    "wof:placetype":"venue"
},
  "geometry": {"coordinates":[-71.03711,42.252559],"type":"Point"}
}