{
  "type": "Feature",
  "properties": {
    "iso:country":"US",
    "sg:address":"145 Tremont St",
    "sg:city":"Boston",
    "sg:classifiers":[
        {
            "category":"Retail",
            "subcategory":"Repair Shop",
            "type":"Services"
        }
    ],
    "sg:phone":"+1 617 208 1113",
    "sg:postcode":"02111",
    "sg:province":"MA",
    "sg:tags":[
        "lock",
        "locksmith"
    ],
    "wof:name":"7 Day Always Emergency Lcksmth",
    "wof:placetype":"venue"
},
  "geometry": {"coordinates":[-71.062946,42.355516],"type":"Point"}
}