{
  "type": "Feature",
  "properties": {
    "addr:full": "145 Tremont St Boston MA 02111",
    "addr:housenumber": "145",
    "addr:postcode": "02111",
    "addr:street": "Tremont St",
    "iso:country": "US",
    "sg:address": "145 Tremont St",
    "sg:city": "Boston",
    "sg:classifiers": [
      {
        "category": "Retail",
        "subcategory": "Repair Shop",
        "type": "Services"
      }
    ],
    "sg:phone": "+1 617 208 1113",
    "sg:postcode": "02111",
    "sg:province": "MA",
    "sg:tags": [
      "lock",
      "locksmith"
    ],
    "wof:name": "7 Day Always Emergency Lcksmth",
    "wof:placetype": "venue"
  },
  "geometry": {"coordinates":[-71.062946,42.355516],"type":"Point"}
}
