{
  "type": "Feature",
  "properties": {
    "iso:country":"US",
    "sg:address":"1150 Baker Ave",
    "sg:city":"Concord",
    "sg:classifiers":[
        {
            "category":"Taxi",
            "type":"Transportation"
        }
    ],
    "sg:phone":"+1 978 369 1752",
    "sg:postcode":"01742",
    "sg:province":"MA",
    "wof:name":"Sunshine Taxi Cab",
    "wof:placetype":"venue"
},
  "geometry": {"coordinates":[-71.386276,42.46022],"type":"Point"}
}