{
  "type": "Feature",
  "properties": {
    "iso:country":"US",
    "sg:address":"800 College Hwy",
    "sg:city":"Southwick",
    "sg:classifiers":[
        {
            "category":"Health Services",
            "subcategory":"Doctor",
            "type":"Services"
        }
    ],
    "sg:phone":"+1 800 433 3243",
    "sg:postcode":"01077",
    "sg:province":"MA",
    "sg:tags":[
        "medicine",
        "physician",
        "surgeon",
        "internal",
        "surgeons"
    ],
    "wof:name":"College Highway Medical Associates",
    "wof:placetype":"venue"
},
  "geometry": {"coordinates":[-72.764381,42.08736],"type":"Point"}
}