{
  "type": "Feature",
  "properties": {
    "iso:country":"US",
    "sg:address":"9 Reservoir Rd",
    "sg:city":"Southwick",
    "sg:classifiers":[
        {
            "category":"Building & Trades",
            "subcategory":"Construction",
            "type":"Services"
        }
    ],
    "sg:phone":"+1   ",
    "sg:postcode":"01077",
    "sg:province":"MA",
    "sg:tags":[
        "house"
    ],
    "wof:name":"Walter Kruzynski Construction",
    "wof:placetype":"venue"
},
  "geometry": {"coordinates":[-72.79820100000001,42.094584],"type":"Point"}
}