{
  "type": "Feature",
  "properties": {
    "addr:full": "9 Reservoir Rd Southwick MA 01077",
    "addr:housenumber": "9",
    "addr:postcode": "01077",
    "addr:street": "Reservoir Rd",
    "iso:country": "US",
    "sg:address": "9 Reservoir Rd",
    "sg:city": "Southwick",
    "sg:classifiers": [
      {
        "category": "Building \u0026 Trades",
        "subcategory": "Construction",
        "type": "Services"
      }
    ],
    "sg:phone": "+1   ",
    "sg:postcode": "01077",
    "sg:province": "MA",
    "sg:tags": [
      "house"
    ],
    "wof:name": "Walter Kruzynski Construction",
    "wof:placetype": "venue"
  },
  "geometry": {"coordinates":[-72.798201,42.094584],"type":"Point"}
}
