{
  "type": "Feature",
  "properties": {
    "iso:country":"US",
    "sg:address":"17 Capital St",
    "sg:city":"Newton",
    "sg:classifiers":[
        {
            "category":"Place Of Worship",
            "type":"Public Place"
        }
    ],
    "sg:phone":"+1 617 630 1998",
    "sg:postcode":"02458",
    "sg:province":"MA",
    "sg:tags":[
        "church"
    ],
    "wof:name":"Franciscan Missionary",
    "wof:placetype":"venue"
},
  "geometry": {"coordinates":[-71.19558000000001,42.360531],"type":"Point"}
}