{
  "type": "Feature",
  "properties": {
    "iso:country":"US",
    "sg:address":"550 Kimball St",
    "sg:city":"Fitchburg",
    "sg:classifiers":[
        {
            "category":"Restaurant",
            "type":"Food & Drink"
        }
    ],
    "sg:menulink":"http://www.allmenus.com/ma/fitchburg/188573-mcdonalds/menu/",
    "sg:postcode":"01420",
    "sg:province":"MA",
    "sg:tags":[
        "burger",
        "american"
    ],
    "wof:name":"McDonald's",
    "wof:placetype":"venue"
},
  "geometry": {"coordinates":[-71.817966,42.583026],"type":"Point"}
}