{
  "type": "Feature",
  "properties": {
    "addr:full": "550 Kimball St Fitchburg MA 01420",
    "addr:housenumber": "550",
    "addr:postcode": "01420",
    "addr:street": "Kimball St",
    "iso:country": "US",
    "sg:address": "550 Kimball St",
    "sg:city": "Fitchburg",
    "sg:classifiers": [
      {
        "category": "Restaurant",
        "type": "Food \u0026 Drink"
      }
    ],
    "sg:menulink": "http://www.allmenus.com/ma/fitchburg/188573-mcdonalds/menu/",
    "sg:postcode": "01420",
    "sg:province": "MA",
    "sg:tags": [
      "burger",
      "american"
    ],
    "wof:name": "McDonald's",
    "wof:placetype": "venue"
  },
  "geometry": {"coordinates":[-71.817966,42.583026],"type":"Point"}
}
