{
  "type": "Feature",
  "properties": {
    "addr:full":"50 Charles River Dr Franklin MA 02038",
    "addr:housenumber":"50",
    "addr:postcode":"02038",
    "addr:street":"Charles River Dr",
    "iso:country":"US",
    "sg:address":"50 Charles River Dr",
    "sg:city":"Franklin",
    "sg:classifiers":[
        {
            "category":"Utilities",
            "subcategory":"Telephone",
            "type":"Services"
        }
    ],
    "sg:phone":"+1   ",
    "sg:postcode":"02038",
    "sg:province":"MA",
    "sg:tags":[
        "communications"
    ],
    "wof:name":"AT&T",
    "wof:placetype":"venue"
},
  "geometry": {"coordinates":[-71.412189,42.102547],"type":"Point"}
}