{
  "type": "Feature",
  "properties": {
    "addr:full":"523 Main St Woburn MA 01801",
    "addr:housenumber":"523",
    "addr:postcode":"01801",
    "addr:street":"Main St",
    "iso:country":"US",
    "sg:address":"523 Main St",
    "sg:city":"Woburn",
    "sg:classifiers":[
        {
            "category":"Social Services",
            "subcategory":"Child Care",
            "type":"Services"
        },
        {
            "category":"Education",
            "subcategory":"Preschool",
            "type":"Public Place"
        },
        {
            "category":"Education",
            "subcategory":"School",
            "type":"Public Place"
        }
    ],
    "sg:phone":"+1 781 938 1025",
    "sg:postcode":"01801",
    "sg:province":"MA",
    "sg:tags":[
        "elementary",
        "day"
    ],
    "wof:name":"YMCA Youth Center",
    "wof:placetype":"venue"
},
  "geometry": {"coordinates":[-71.15129899999999,42.483898],"type":"Point"}
}