{
  "type": "Feature",
  "properties": {
    "addr:full": "40 Schofield Ave Dudley MA 01571",
    "addr:housenumber": "40",
    "addr:postcode": "01571",
    "addr:street": "Schofield Ave",
    "iso:country": "US",
    "sg:address": "40 Schofield Ave",
    "sg:city": "Dudley",
    "sg:classifiers": [
      {
        "category": "Government",
        "subcategory": "Office",
        "type": "Public Place"
      }
    ],
    "sg:phone": "+1 508 949 8008",
    "sg:postcode": "01571",
    "sg:province": "MA",
    "sg:tags": [
      "village"
    ],
    "wof:name": "Dudley Sewage Dept",
    "wof:placetype": "venue"
  },
  "geometry": {"coordinates":[-71.890942,42.043901],"type":"Point"}
}
