{
  "type": "Feature",
  "properties": {
    "addr:full":"4 California Ave Framingham MA 01701",
    "addr:housenumber":"4",
    "addr:postcode":"01701",
    "addr:street":"California Ave",
    "iso:country":"US",
    "sg:address":"4 California Ave",
    "sg:city":"Framingham",
    "sg:classifiers":[
        {
            "category":"Professional",
            "subcategory":"Business Services",
            "type":"Services"
        }
    ],
    "sg:phone":"+1 508 875 2557",
    "sg:postcode":"01701",
    "sg:province":"MA",
    "sg:tags":[
        "statistical"
    ],
    "sg:website":"www.averioninc.com",
    "wof:name":"Averion",
    "wof:placetype":"venue"
},
  "geometry": {"coordinates":[-71.48217,42.298711],"type":"Point"}
}