{
  "type": "Feature",
  "properties": {
    "addr:full":"250 Granite St Braintree MA 02184",
    "addr:housenumber":"250",
    "addr:postcode":"02184",
    "addr:street":"Granite St",
    "iso:country":"US",
    "sg:address":"250 Granite St",
    "sg:city":"Braintree",
    "sg:classifiers":[
        {
            "category":"Shopping",
            "subcategory":"Shoes",
            "type":"Retail Goods"
        }
    ],
    "sg:phone":"+1 781 849 9255",
    "sg:postcode":"02184",
    "sg:province":"MA",
    "wof:name":"Walking Co",
    "wof:placetype":"venue"
},
  "geometry": {"coordinates":[-71.028615,42.221083],"type":"Point"}
}