{
  "type": "Feature",
  "properties": {
    "addr:full": "231 Cabot St Beverly MA 01915",
    "addr:housenumber": "231",
    "addr:postcode": "01915",
    "addr:street": "Cabot St",
    "iso:country": "US",
    "sg:address": "231 Cabot St",
    "sg:city": "Beverly",
    "sg:classifiers": [
      {
        "category": "Shopping",
        "subcategory": "Used Merchandise",
        "type": "Retail Goods"
      }
    ],
    "sg:phone": "+1 978 922 5777",
    "sg:postcode": "01915",
    "sg:province": "MA",
    "wof:name": "Golden Hanger",
    "wof:placetype": "venue"
  },
  "geometry": {"coordinates":[-70.877954,42.550565],"type":"Point"}
}
