{
  "type": "Feature",
  "properties": {
    "addr:full": "73 Chandler St Worcester MA 01609",
    "addr:housenumber": "73",
    "addr:postcode": "01609",
    "addr:street": "Chandler St",
    "iso:country": "US",
    "sg:address": "73 Chandler St",
    "sg:city": "Worcester",
    "sg:classifiers": [
      {
        "category": "Manufacturing",
        "subcategory": "Rubber \u0026 Plastics",
        "type": "Manufacturing \u0026 Wholesale Goods"
      },
      {
        "category": "Autos \u0026 Motor Vehicles",
        "subcategory": "Auto Supplies",
        "type": "Retail Goods"
      }
    ],
    "sg:phone": "+1 508 755 5255",
    "sg:postcode": "01609",
    "sg:province": "MA",
    "sg:tags": [
      "tires-wholesale",
      "tire",
      "manufacturer"
    ],
    "sg:website": "http://www.coopertire.com",
    "wof:name": "Ken Jones Inc",
    "wof:placetype": "venue"
  },
  "geometry": {"coordinates":[-71.808901,42.26053],"type":"Point"}
}
