{
  "type": "Feature",
  "properties": {
    "iso:country":"US",
    "sg:address":"23 Brookledge St",
    "sg:city":"Boston",
    "sg:classifiers":[
        {
            "category":"Arts & Performance",
            "subcategory":"Theater",
            "type":"Entertainment"
        }
    ],
    "sg:phone":"+1   ",
    "sg:postcode":"02121",
    "sg:province":"MA",
    "sg:tags":[
        "group"
    ],
    "wof:name":"Attack Entertainment",
    "wof:placetype":"venue"
},
  "geometry": {"coordinates":[-71.088928,42.308874],"type":"Point"}
}