{
  "type": "Feature",
  "properties": {
    "addr:full": "23 Brookledge St Boston MA 02121",
    "addr:housenumber": "23",
    "addr:postcode": "02121",
    "addr:street": "Brookledge St",
    "iso:country": "US",
    "sg:address": "23 Brookledge St",
    "sg:city": "Boston",
    "sg:classifiers": [
      {
        "category": "Arts \u0026 Performance",
        "subcategory": "Theater",
        "type": "Entertainment"
      }
    ],
    "sg:phone": "+1   ",
    "sg:postcode": "02121",
    "sg:province": "MA",
    "sg:tags": [
      "group"
    ],
    "wof:name": "Attack Entertainment",
    "wof:placetype": "venue"
  },
  "geometry": {"coordinates":[-71.088928,42.308874],"type":"Point"}
}
