{
  "type": "Feature",
  "properties": {
    "addr:full":"61 Bromfield Street Boston MA 02108",
    "addr:housenumber":"61",
    "addr:postcode":"02108",
    "addr:street":"Bromfield Street",
    "iso:country":"US",
    "sg:address":"61 Bromfield Street",
    "sg:city":"Boston",
    "sg:classifiers":[
        {
            "category":"Personal",
            "subcategory":"Nail Salon",
            "type":"Services"
        }
    ],
    "sg:phone":"+1 617 292 7117",
    "sg:postcode":"02108",
    "sg:province":"MA",
    "wof:name":"Nail Time",
    "wof:placetype":"venue"
},
  "geometry": {"coordinates":[-71.06072500000001,42.356996],"type":"Point"}
}