{
  "type": "Feature",
  "properties": {
    "addr:full": "90 Tremont St Everett MA 02149",
    "addr:housenumber": "90",
    "addr:postcode": "02149",
    "addr:street": "Tremont St",
    "iso:country": "US",
    "sg:address": "90 Tremont St",
    "sg:city": "Everett",
    "sg:classifiers": [
      {
        "category": "Retail",
        "subcategory": "Auto Repair",
        "type": "Services"
      }
    ],
    "sg:phone": "+1 617 387 2150",
    "sg:postcode": "02149",
    "sg:province": "MA",
    "sg:tags": [
      "body",
      "automobile",
      "painting"
    ],
    "wof:name": "Tremont Auto Body",
    "wof:placetype": "venue"
  },
  "geometry": {"coordinates":[-71.066902,42.41092],"type":"Point"}
}
