{
  "type": "Feature",
  "properties": {
    "addr:full": "54 Peters St North Andover MA 01845",
    "addr:housenumber": "54",
    "addr:postcode": "01845",
    "addr:street": "Peters St",
    "iso:country": "US",
    "sg:address": "54 Peters St",
    "sg:city": "North Andover",
    "sg:classifiers": [
      {
        "category": "Food \u0026 Beverages",
        "subcategory": "Liquor \u0026 Beverages",
        "type": "Retail Goods"
      }
    ],
    "sg:phone": "+1 978 683 2216",
    "sg:postcode": "01845",
    "sg:province": "MA",
    "wof:name": "Den Rock Liquor Mart",
    "wof:placetype": "venue"
  },
  "geometry": {"coordinates":[-71.126903,42.675693],"type":"Point"}
}
