{
  "type": "Feature",
  "properties": {
    "iso:country":"US",
    "sg:address":"54 Peters St",
    "sg:city":"North Andover",
    "sg:classifiers":[
        {
            "category":"Food & Beverages",
            "subcategory":"Liquor & Beverages",
            "type":"Retail Goods"
        }
    ],
    "sg:phone":"+1 978 683 2216",
    "sg:postcode":"01845",
    "sg:province":"MA",
    "wof:name":"Den Rock Liquor Mart",
    "wof:placetype":"venue"
},
  "geometry": {"coordinates":[-71.126903,42.675693],"type":"Point"}
}