{
  "type": "Feature",
  "properties": {
    "iso:country":"US",
    "sg:address":"1942 Centre St",
    "sg:city":"West Roxbury",
    "sg:classifiers":[
        {
            "category":"Autos & Motor Vehicles",
            "subcategory":"Fuel & Gas Station",
            "type":"Retail Goods"
        }
    ],
    "sg:phone":"+1 617 323 9691",
    "sg:postcode":"02132",
    "sg:province":"MA",
    "sg:tags":[
        "oil"
    ],
    "wof:name":"West Roxbury Shell",
    "wof:placetype":"venue"
},
  "geometry": {"coordinates":[-71.1571,42.283178],"type":"Point"}
}