{
  "type": "Feature",
  "properties": {
    "addr:full": "1942 Centre St West Roxbury MA 02132",
    "addr:housenumber": "1942",
    "addr:postcode": "02132",
    "addr:street": "Centre St",
    "iso:country": "US",
    "sg:address": "1942 Centre St",
    "sg:city": "West Roxbury",
    "sg:classifiers": [
      {
        "category": "Autos \u0026 Motor Vehicles",
        "subcategory": "Fuel \u0026 Gas Station",
        "type": "Retail Goods"
      }
    ],
    "sg:phone": "+1 617 323 9691",
    "sg:postcode": "02132",
    "sg:province": "MA",
    "sg:tags": [
      "oil"
    ],
    "wof:name": "West Roxbury Shell",
    "wof:placetype": "venue"
  },
  "geometry": {"coordinates":[-71.1571,42.283178],"type":"Point"}
}
