{
  "type": "Feature",
  "properties": {
    "iso:country":"US",
    "sg:address":"79 Morton Pl",
    "sg:city":"East Boston",
    "sg:classifiers":[
        {
            "category":"Health Services",
            "subcategory":"Doctor",
            "type":"Services"
        }
    ],
    "sg:phone":"+1 617 569 6321",
    "sg:postcode":"02128",
    "sg:province":"MA",
    "sg:tags":[
        "physician",
        "surgeon"
    ],
    "wof:name":"Leo X Callahan MD",
    "wof:placetype":"venue"
},
  "geometry": {"coordinates":[-71.03781499999999,42.376146],"type":"Point"}
}