{
  "type": "Feature",
  "properties": {
    "addr:full":"1256 Methuen St Dracut MA 01826",
    "addr:housenumber":"1256",
    "addr:postcode":"01826",
    "addr:street":"Methuen St",
    "iso:country":"US",
    "sg:address":"1256 Methuen St",
    "sg:city":"Dracut",
    "sg:classifiers":[
        {
            "category":"Real Estate",
            "subcategory":"Real Estate Agent",
            "type":"Services"
        }
    ],
    "sg:phone":"+1 978 458 0767",
    "sg:postcode":"01826",
    "sg:province":"MA",
    "wof:name":"Wilkins Real Estate",
    "wof:placetype":"venue"
},
  "geometry": {"coordinates":[-71.25530500000001,42.668766],"type":"Point"}
}