{
  "type": "Feature",
  "properties": {
    "iso:country":"US",
    "sg:address":"339 Sawyer St",
    "sg:city":"New Bedford",
    "sg:classifiers":[
        {
            "category":"Utilities",
            "subcategory":"Mobile Phone",
            "type":"Services"
        }
    ],
    "sg:phone":"+1 508 999 2099",
    "sg:postcode":"02746",
    "sg:province":"MA",
    "sg:tags":[
        "communication",
        "r",
        "radiotelephone",
        "merchandise"
    ],
    "wof:name":"Car Tunes",
    "wof:placetype":"venue"
},
  "geometry": {"coordinates":[-70.931484,41.65712],"type":"Point"}
}