{
  "type": "Feature",
  "properties": {
    "addr:full":"1342 Main St Walpole MA 02081",
    "addr:housenumber":"1342",
    "addr:postcode":"02081",
    "addr:street":"Main St",
    "iso:country":"US",
    "sg:address":"1342 Main St",
    "sg:city":"Walpole",
    "sg:classifiers":[
        {
            "category":"Retail",
            "subcategory":"Veterinary Services",
            "type":"Services"
        }
    ],
    "sg:phone":"+1 508 668 5088",
    "sg:postcode":"02081",
    "sg:province":"MA",
    "sg:tags":[
        "veterinarian",
        "specialty"
    ],
    "sg:website":"http://www.norfolkvet.net",
    "wof:name":"Christina M. Poor",
    "wof:placetype":"venue"
},
  "geometry": {"coordinates":[-71.261487,42.133875],"type":"Point"}
}