{
  "type": "Feature",
  "properties": {
    "addr:full":"4 Ladyslipper Ln Forestdale MA 02644",
    "addr:housenumber":"4",
    "addr:postcode":"02644",
    "addr:street":"Ladyslipper Ln",
    "iso:country":"US",
    "sg:address":"4 Ladyslipper Ln",
    "sg:city":"Forestdale",
    "sg:classifiers":[
        {
            "category":"Home & Garden",
            "subcategory":"Garden Supply",
            "type":"Retail Goods"
        },
        {
            "category":"Building & Trades",
            "subcategory":"Construction",
            "type":"Services"
        }
    ],
    "sg:phone":"+1 508 737 5149",
    "sg:postcode":"02644",
    "sg:province":"MA",
    "sg:tags":[
        "equipment",
        "contractor",
        "pressure",
        "cleaning",
        "painting"
    ],
    "wof:name":"Joshua Painting",
    "wof:placetype":"venue"
},
  "geometry": {"coordinates":[-70.508855,41.689354],"type":"Point"}
}