{
  "type": "Feature",
  "properties": {
    "iso:country":"US",
    "sg:address":"21 Mohawk Trl",
    "sg:city":"Greenfield",
    "sg:classifiers":[
        {
            "category":"Personal",
            "subcategory":"Beauty Salon",
            "type":"Services"
        }
    ],
    "sg:phone":"+1 413 774 6467",
    "sg:postcode":"01301",
    "sg:province":"MA",
    "wof:name":"Chris & Co",
    "wof:placetype":"venue"
},
  "geometry": {"coordinates":[-72.61124599999999,42.586121],"type":"Point"}
}