{
  "type": "Feature",
  "properties": {
    "iso:country":"US",
    "sg:address":"12 10th Ave",
    "sg:city":"Haverhill",
    "sg:classifiers":[
        {
            "category":"Organizations",
            "subcategory":"Non-profit Organization",
            "type":"Services"
        }
    ],
    "sg:phone":"+1   ",
    "sg:postcode":"01830",
    "sg:province":"MA",
    "sg:tags":[
        "consulting",
        "business",
        "social"
    ],
    "wof:name":"Laleche Leag Greater Haverhill",
    "wof:placetype":"venue"
},
  "geometry": {"coordinates":[-71.08358800000001,42.787322],"type":"Point"}
}