{
  "type": "Feature",
  "properties": {
    "addr:full":"273 Water St Wakefield MA 01880",
    "addr:housenumber":"273",
    "addr:postcode":"01880",
    "addr:street":"Water St",
    "iso:country":"US",
    "sg:address":"273 Water St",
    "sg:city":"Wakefield",
    "sg:classifiers":[
        {
            "category":"Professional",
            "subcategory":"Business Services",
            "type":"Services"
        }
    ],
    "sg:phone":"+1   ",
    "sg:postcode":"01880",
    "sg:province":"MA",
    "wof:name":"John H Hawkes Production",
    "wof:placetype":"venue"
},
  "geometry": {"coordinates":[-71.05962100000001,42.503111],"type":"Point"}
}