{
  "type": "Feature",
  "properties": {
    "iso:country":"US",
    "sg:address":"435 Riverside Ave",
    "sg:city":"Medford",
    "sg:classifiers":[
        {
            "category":"Home & Garden",
            "subcategory":"Building Materials",
            "type":"Retail Goods"
        }
    ],
    "sg:phone":"+1 781 391 2332",
    "sg:postcode":"02155",
    "sg:province":"MA",
    "sg:tags":[
        "glass",
        "window",
        "plate"
    ],
    "wof:name":"Superior Auto Body",
    "wof:placetype":"venue"
},
  "geometry": {"coordinates":[-71.088757,42.410994],"type":"Point"}
}