{
  "type": "Feature",
  "properties": {
    "addr:full": "435 Riverside Ave Medford MA 02155",
    "addr:housenumber": "435",
    "addr:postcode": "02155",
    "addr:street": "Riverside Ave",
    "iso:country": "US",
    "ovtr:label": "Superior Auto Body, 435 Riverside Ave Medford MA US",
    "ovtr:similarity": 1.9585340023040771,
    "sg:address": "435 Riverside Ave",
    "sg:city": "Medford",
    "sg:classifiers": [
      {
        "category": "Home \u0026 Garden",
        "subcategory": "Building Materials",
        "type": "Retail Goods"
      }
    ],
    "sg:phone": "+1 781 391 2332",
    "sg:postcode": "02155",
    "sg:province": "MA",
    "sg:tags": [
      "glass",
      "window",
      "plate"
    ],
    "wof:name": "Superior Auto Body",
    "wof:placetype": "venue"
  },
  "geometry": {"coordinates":[-71.088757,42.410994],"type":"Point"}
}
