{
  "type": "Feature",
  "properties": {
    "iso:country":"US",
    "sg:address":"2 Skura Ln",
    "sg:city":"Three Rivers",
    "sg:classifiers":[
        {
            "category":"Retail",
            "subcategory":"Repair Shop",
            "type":"Services"
        }
    ],
    "sg:phone":"+1 413 283 5564",
    "sg:postcode":"01080",
    "sg:province":"MA",
    "sg:tags":[
        "welding"
    ],
    "wof:name":"Construction Welding Service",
    "wof:placetype":"venue"
},
  "geometry": {"coordinates":[-72.369376,42.183735],"type":"Point"}
}