{
  "type": "Feature",
  "properties": {
    "addr:full": "16 French St Hingham MA 02043",
    "addr:housenumber": "16",
    "addr:postcode": "02043",
    "addr:street": "French St",
    "iso:country": "US",
    "sg:address": "16 French St",
    "sg:city": "Hingham",
    "sg:phone": "+1 781 749 6104",
    "sg:postcode": "02043",
    "sg:province": "MA",
    "sg:tags": [
      "oil"
    ],
    "wof:name": "Mallard Oil",
    "wof:placetype": "venue"
  },
  "geometry": {"coordinates":[-70.91178,42.216509],"type":"Point"}
}
