{
  "type": "Feature",
  "properties": {
    "iso:country":"US",
    "sg:address":"58 Walnut St",
    "sg:city":"Arlington",
    "sg:classifiers":[
        {
            "category":"Professional",
            "subcategory":"Computer Services",
            "type":"Services"
        }
    ],
    "sg:phone":"+1   ",
    "sg:postcode":"02476",
    "sg:province":"MA",
    "sg:tags":[
        "web",
        "design",
        "page"
    ],
    "wof:name":"Alteon Websystems Inc",
    "wof:placetype":"venue"
},
  "geometry": {"coordinates":[-71.17110599999999,42.417725],"type":"Point"}
}