{
  "type": "Feature",
  "properties": {
    "iso:country":"US",
    "sg:address":"1125 Commonwealth Ave",
    "sg:city":"Boston",
    "sg:classifiers":[
        {
            "category":"Real Estate",
            "subcategory":"Real Estate Services",
            "type":"Services"
        },
        {
            "category":"Real Estate",
            "subcategory":"Real Estate Operator",
            "type":"Services"
        }
    ],
    "sg:phone":"+1 617 787 2777",
    "sg:postcode":"02134",
    "sg:province":"MA",
    "sg:tags":[
        "apartment",
        "property",
        "management"
    ],
    "sg:website":"www.rollsrealtyinc.com",
    "wof:name":"Rolls Realty",
    "wof:placetype":"venue"
},
  "geometry": {"coordinates":[-71.1262,42.3515],"type":"Point"}
}