{
  "type": "Feature",
  "properties": {
    "iso:country":"US",
    "sg:address":"39 Melody Ln",
    "sg:city":"Waltham",
    "sg:classifiers":[
        {
            "category":"Professional",
            "subcategory":"Computer Services",
            "type":"Services"
        }
    ],
    "sg:phone":"+1   ",
    "sg:postcode":"02451",
    "sg:province":"MA",
    "sg:tags":[
        "datum"
    ],
    "wof:name":"Wayne Crichlow",
    "wof:placetype":"venue"
},
  "geometry": {"coordinates":[-71.263074,42.416311],"type":"Point"}
}