{
  "type": "Feature",
  "properties": {
    "addr:full":"20 Oak St Beverly MA 01915",
    "addr:housenumber":"20",
    "addr:postcode":"01915",
    "addr:street":"Oak St",
    "iso:country":"US",
    "sg:address":"20 Oak St",
    "sg:city":"Beverly",
    "sg:classifiers":[
        {
            "category":"Real Estate",
            "subcategory":"Real Estate Agent",
            "type":"Services"
        }
    ],
    "sg:phone":"+1 978 927 9229",
    "sg:postcode":"01915",
    "sg:province":"MA",
    "sg:tags":[
        "desk",
        "space"
    ],
    "sg:website":"www.twentyoak.com",
    "wof:name":"Twenty Oak Street",
    "wof:placetype":"venue"
},
  "geometry": {"coordinates":[-70.81056,42.562543],"type":"Point"}
}