{
  "type": "Feature",
  "properties": {
    "iso:country":"US",
    "sg:address":"500 Harvard St",
    "sg:city":"Brookline",
    "sg:classifiers":[
        {
            "category":"Deli",
            "type":"Food & Drink"
        },
        {
            "category":"Restaurant",
            "type":"Food & Drink"
        }
    ],
    "sg:phone":"+1 617 731 8787",
    "sg:postcode":"02446",
    "sg:province":"MA",
    "sg:tags":[
        "kosher"
    ],
    "sg:website":"www.rubinskosher.com",
    "wof:name":"Rubin's Kosher Restaurant",
    "wof:placetype":"venue"
},
  "geometry": {"coordinates":[-71.129176,42.347944],"type":"Point"}
}