{
  "type": "Feature",
  "properties": {
    "addr:full": "4 Dock Sq Rockport MA 01966",
    "addr:housenumber": "4",
    "addr:postcode": "01966",
    "addr:street": "Dock Sq",
    "iso:country": "US",
    "sg:address": "4 Dock Sq",
    "sg:city": "Rockport",
    "sg:classifiers": [
      {
        "category": "Shopping",
        "subcategory": "Gifts \u0026 Souvenirs",
        "type": "Retail Goods"
      }
    ],
    "sg:phone": "+1 978 546 3155",
    "sg:postcode": "01966",
    "sg:province": "MA",
    "sg:tags": [
      "shop"
    ],
    "wof:name": "Spa Fina Boutique",
    "wof:placetype": "venue"
  },
  "geometry": {"coordinates":[-70.616794,42.658563],"type":"Point"}
}
