{
  "type": "Feature",
  "properties": {
    "addr:full":"10 Holden St Malden MA 02148",
    "addr:housenumber":"10",
    "addr:postcode":"02148",
    "addr:street":"Holden St",
    "iso:country":"US",
    "sg:address":"10 Holden St",
    "sg:city":"Malden",
    "sg:classifiers":[
        {
            "category":"Health Services",
            "subcategory":"Dentist",
            "type":"Services"
        }
    ],
    "sg:phone":"+1 781 322 9060",
    "sg:postcode":"02148",
    "sg:province":"MA",
    "wof:name":"Ho Tom Dr",
    "wof:placetype":"venue"
},
  "geometry": {"coordinates":[-71.063738,42.427833],"type":"Point"}
}