{
  "type": "Feature",
  "properties": {
    "iso:country":"US",
    "sg:address":"1200 Commonwealth Ave",
    "sg:city":"Allston",
    "sg:classifiers":[
        {
            "category":"Utilities",
            "subcategory":"Water",
            "type":"Services"
        }
    ],
    "sg:phone":"+1 617 731 6124",
    "sg:postcode":"02134",
    "sg:province":"MA",
    "sg:tags":[
        "bulk",
        "companies-bottled"
    ],
    "wof:name":"Sandra B Waters",
    "wof:placetype":"venue"
},
  "geometry": {"coordinates":[-71.129829,42.35038],"type":"Point"}
}