{
  "type": "Feature",
  "properties": {
    "iso:country":"US",
    "sg:address":"145 Donovans Ln",
    "sg:city":"Westport",
    "sg:classifiers":[
        {
            "category":"Real Estate",
            "subcategory":"Real Estate Agent",
            "type":"Services"
        }
    ],
    "sg:phone":"+1   ",
    "sg:postcode":"02790",
    "sg:province":"MA",
    "wof:name":"Noquochoke Investment",
    "wof:placetype":"venue"
},
  "geometry": {"coordinates":[-71.06426999999999,41.594221],"type":"Point"}
}