{
  "type": "Feature",
  "properties": {
    "addr:full":"20 Thurber Ave Seekonk MA 02771",
    "addr:housenumber":"20",
    "addr:postcode":"02771",
    "addr:street":"Thurber Ave",
    "iso:country":"US",
    "sg:address":"20 Thurber Ave",
    "sg:city":"Seekonk",
    "sg:classifiers":[
        {
            "category":"Professional",
            "type":"Services"
        }
    ],
    "sg:phone":"+1   ",
    "sg:postcode":"02771",
    "sg:province":"MA",
    "wof:name":"Anorexia Blimia Support Svcs I",
    "wof:placetype":"venue"
},
  "geometry": {"coordinates":[-71.33571000000001,41.891555],"type":"Point"}
}