{
  "type": "Feature",
  "properties": {
    "addr:full":"12 Hampton St Auburn MA 01501",
    "addr:housenumber":"12",
    "addr:postcode":"01501",
    "addr:street":"Hampton St",
    "iso:country":"US",
    "sg:address":"12 Hampton St",
    "sg:city":"Auburn",
    "sg:classifiers":[
        {
            "category":"Professional",
            "subcategory":"Management & Consulting",
            "type":"Services"
        }
    ],
    "sg:phone":"+1   ",
    "sg:postcode":"01501",
    "sg:province":"MA",
    "wof:name":"J&B Enterprises",
    "wof:placetype":"venue"
},
  "geometry": {"coordinates":[-71.81483,42.22883],"type":"Point"}
}