{
  "type": "Feature",
  "properties": {
    "addr:full": "1045 Boston Rd Springfield MA 01119",
    "addr:housenumber": "1045",
    "addr:postcode": "01119",
    "addr:street": "Boston Rd",
    "iso:country": "US",
    "sg:address": "1045 Boston Rd",
    "sg:city": "Springfield",
    "sg:classifiers": [
      {
        "category": "Retail",
        "subcategory": "Auto Rental",
        "type": "Services"
      }
    ],
    "sg:phone": "+1 413 783 8900",
    "sg:postcode": "01119",
    "sg:province": "MA",
    "sg:tags": [
      "renting",
      "automobile"
    ],
    "wof:name": "Enterprise Rent-A-Car",
    "wof:placetype": "venue"
  },
  "geometry": {"coordinates":[-72.510827,42.138583],"type":"Point"}
}
