{
  "type": "Feature",
  "properties": {
    "iso:country":"US",
    "sg:address":"1045 Boston Rd",
    "sg:city":"Springfield",
    "sg:classifiers":[
        {
            "category":"Retail",
            "subcategory":"Auto Rental",
            "type":"Services"
        }
    ],
    "sg:phone":"+1 413 783 8900",
    "sg:postcode":"01119",
    "sg:province":"MA",
    "sg:tags":[
        "renting",
        "automobile"
    ],
    "wof:name":"Enterprise Rent-A-Car",
    "wof:placetype":"venue"
},
  "geometry": {"coordinates":[-72.51082700000001,42.138583],"type":"Point"}
}