{
  "type": "Feature",
  "properties": {
    "iso:country":"US",
    "sg:address":"20 Spring St",
    "sg:city":"Saugus",
    "sg:classifiers":[
        {
            "category":"Wholesale",
            "subcategory":"Electrical",
            "type":"Manufacturing & Wholesale Goods"
        }
    ],
    "sg:phone":"+1 781 233 1717",
    "sg:postcode":"01906",
    "sg:province":"MA",
    "sg:tags":[
        "testing",
        "apparatus"
    ],
    "sg:website":"www.lasercomp.com",
    "wof:name":"Laser Comp",
    "wof:placetype":"venue"
},
  "geometry": {"coordinates":[-71.01637100000001,42.494775],"type":"Point"}
}