{
  "type": "Feature",
  "properties": {
    "addr:full": "30 Madison Ave Springfield MA 01105",
    "addr:housenumber": "30",
    "addr:postcode": "01105",
    "addr:street": "Madison Ave",
    "iso:country": "US",
    "sg:address": "30 Madison Ave",
    "sg:city": "Springfield",
    "sg:classifiers": [
      {
        "category": "Social Services",
        "subcategory": "Child Care",
        "type": "Services"
      }
    ],
    "sg:phone": "+1 413 788 6522",
    "sg:postcode": "01105",
    "sg:province": "MA",
    "wof:name": "Springfield Holyoke Chicopee",
    "wof:placetype": "venue"
  },
  "geometry": {"coordinates":[-72.575441,42.1005],"type":"Point"}
}
