{
  "type": "Feature",
  "properties": {
    "iso:country":"US",
    "sg:address":"31 Kidder Ave",
    "sg:city":"Somerville",
    "sg:classifiers":[
        {
            "category":"Professional",
            "subcategory":"Management & Consulting",
            "type":"Services"
        }
    ],
    "sg:phone":"+1 617 628 9297",
    "sg:postcode":"02144",
    "sg:province":"MA",
    "wof:name":"Madsen Marketing Strategies",
    "wof:placetype":"venue"
},
  "geometry": {"coordinates":[-71.116671,42.398593],"type":"Point"}
}