{
  "type": "Feature",
  "properties": {
    "addr:full": "1820 Old Turnpike Rd Oakham MA 01068",
    "addr:housenumber": "1820",
    "addr:postcode": "01068",
    "addr:street": "Old Turnpike Rd",
    "iso:country": "US",
    "sg:address": "1820 Old Turnpike Rd",
    "sg:city": "Oakham",
    "sg:classifiers": [
      {
        "category": "Sports \u0026 Exercise",
        "subcategory": "Golf",
        "type": "Entertainment"
      }
    ],
    "sg:phone": "+1 508 882 5516",
    "sg:postcode": "01068",
    "sg:province": "MA",
    "sg:tags": [
      "course"
    ],
    "wof:name": "Quail Hollow Golf \u0026 Country",
    "wof:placetype": "venue"
  },
  "geometry": {"coordinates":[-72.089388,42.360563],"type":"Point"}
}
