{
  "type": "Feature",
  "properties": {
    "iso:country":"US",
    "sg:address":"383 Whalom Rd",
    "sg:city":"Lunenburg",
    "sg:classifiers":[
        {
            "category":"Personal",
            "subcategory":"Beauty Salon",
            "type":"Services"
        }
    ],
    "sg:phone":"+1 978 345 7474",
    "sg:postcode":"01462",
    "sg:province":"MA",
    "wof:name":"Bellissima Capelli's",
    "wof:placetype":"venue"
},
  "geometry": {"coordinates":[-71.748339,42.576218],"type":"Point"}
}