{
  "type": "Feature",
  "properties": {
    "iso:country":"US",
    "sg:address":"35 Pleasant St",
    "sg:city":"Worcester",
    "sg:classifiers":[
        {
            "category":"Shopping",
            "subcategory":"Clothing, Apparel, & Fashions",
            "type":"Retail Goods"
        }
    ],
    "sg:phone":"+1 508 752 3289",
    "sg:postcode":"01609",
    "sg:province":"MA",
    "wof:name":"Lujon Men's Clothes Inc",
    "wof:placetype":"venue"
},
  "geometry": {"coordinates":[-71.803431,42.263654],"type":"Point"}
}