{
  "type": "Feature",
  "properties": {
    "addr:full": "48 Hawes St Brookline MA 02446",
    "addr:housenumber": "48",
    "addr:postcode": "02446",
    "addr:street": "Hawes St",
    "iso:country": "US",
    "sg:address": "48 Hawes St",
    "sg:city": "Brookline",
    "sg:classifiers": [
      {
        "category": "Manufacturing",
        "subcategory": "Food",
        "type": "Manufacturing \u0026 Wholesale Goods"
      }
    ],
    "sg:phone": "+1 617 731 3645",
    "sg:postcode": "02446",
    "sg:province": "MA",
    "sg:tags": [
      "olive",
      "oil"
    ],
    "wof:name": "Maghi Florea Imports",
    "wof:placetype": "venue"
  },
  "geometry": {"coordinates":[-71.110449,42.344063],"type":"Point"}
}
