{
  "type": "Feature",
  "properties": {
    "addr:full":"105 Cotuit Rd Marstons Mills MA 02648",
    "addr:housenumber":"105",
    "addr:postcode":"02648",
    "addr:street":"Cotuit Rd",
    "iso:country":"US",
    "sg:address":"105 Cotuit Rd",
    "sg:city":"Marstons Mills",
    "sg:classifiers":[
        {
            "category":"Restaurant",
            "type":"Food & Drink"
        }
    ],
    "sg:phone":"+1 508 419 7151",
    "sg:postcode":"02648",
    "sg:province":"MA",
    "sg:tags":[
        "pizza"
    ],
    "wof:name":"Good To Go",
    "wof:placetype":"venue"
},
  "geometry": {"coordinates":[-70.413577,41.653106],"type":"Point"}
}