{
  "type": "Feature",
  "properties": {
    "addr:full":"3 Bridge St Haydenville MA 01039",
    "addr:housenumber":"3",
    "addr:postcode":"01039",
    "addr:street":"Bridge St",
    "iso:country":"US",
    "sg:address":"3 Bridge St",
    "sg:city":"Haydenville",
    "sg:classifiers":[
        {
            "category":"Personal",
            "subcategory":"Beauty Salon",
            "type":"Services"
        }
    ],
    "sg:phone":"+1 413 268 7847",
    "sg:postcode":"01039",
    "sg:province":"MA",
    "wof:name":"Tilly's Hair Design",
    "wof:placetype":"venue"
},
  "geometry": {"coordinates":[-72.702549,42.3733],"type":"Point"}
}