{
  "type": "Feature",
  "properties": {
    "addr:full":"2122 Main St Tewksbury MA 01876",
    "addr:housenumber":"2122",
    "addr:postcode":"01876",
    "addr:street":"Main St",
    "iso:country":"US",
    "sg:address":"2122 Main St",
    "sg:city":"Tewksbury",
    "sg:classifiers":[
        {
            "category":"Personal",
            "subcategory":"Beauty Salon",
            "type":"Services"
        }
    ],
    "sg:phone":"+1 978 658 9333",
    "sg:postcode":"01876",
    "sg:province":"MA",
    "wof:name":"Jean's Curl & Swirl",
    "wof:placetype":"venue"
},
  "geometry": {"coordinates":[-71.199158,42.586511],"type":"Point"}
}