{
  "type": "Feature",
  "properties": {
    "addr:full":"340 Marshall Rd Fitchburg MA 01420",
    "addr:housenumber":"340",
    "addr:postcode":"01420",
    "addr:street":"Marshall Rd",
    "iso:country":"US",
    "sg:address":"340 Marshall Rd",
    "sg:city":"Fitchburg",
    "sg:classifiers":[
        {
            "category":"Food & Beverages",
            "subcategory":"Fruits & Vegetables",
            "type":"Retail Goods"
        }
    ],
    "sg:phone":"+1 978 343 6255",
    "sg:postcode":"01420",
    "sg:province":"MA",
    "sg:tags":[
        "produce"
    ],
    "wof:name":"Marshall Farm",
    "wof:placetype":"venue"
},
  "geometry": {"coordinates":[-71.77898999999999,42.60024],"type":"Point"}
}