{
  "type": "Feature",
  "properties": {
    "addr:full":"54 R Jones Rd Spencer MA 01562",
    "addr:housenumber":"54",
    "addr:postcode":"01562",
    "addr:street":"R Jones Rd",
    "iso:country":"US",
    "sg:address":"54 R Jones Rd",
    "sg:city":"Spencer",
    "sg:classifiers":[
        {
            "category":"Home & Garden",
            "subcategory":"Building Materials",
            "type":"Retail Goods"
        }
    ],
    "sg:phone":"+1 508 885 5331",
    "sg:postcode":"01562",
    "sg:province":"MA",
    "sg:tags":[
        "modular"
    ],
    "wof:name":"Prime Property Developers",
    "wof:placetype":"venue"
},
  "geometry": {"coordinates":[-71.959543,42.231231],"type":"Point"}
}