{
  "type": "Feature",
  "properties": {
    "addr:full": "136 Damon Rd Northampton MA 01060",
    "addr:housenumber": "136",
    "addr:postcode": "01060",
    "addr:street": "Damon Rd",
    "iso:country": "US",
    "sg:address": "136 Damon Rd",
    "sg:city": "Northampton",
    "sg:classifiers": [
      {
        "category": "Government",
        "subcategory": "Office",
        "type": "Public Place"
      }
    ],
    "sg:phone": "+1 413 586 8706",
    "sg:postcode": "01060",
    "sg:province": "MA",
    "wof:name": "Planning \u0026 Development",
    "wof:placetype": "venue"
  },
  "geometry": {"coordinates":[-72.623943,42.336037],"type":"Point"}
}
