{
  "type": "Feature",
  "properties": {
    "addr:full":"16 Miles Standish Rd Marblehead MA 01945",
    "addr:housenumber":"16",
    "addr:postcode":"01945",
    "addr:street":"Miles Standish Rd",
    "iso:country":"US",
    "sg:address":"16 Miles Standish Rd",
    "sg:city":"Marblehead",
    "sg:classifiers":[
        {
            "category":"Professional",
            "subcategory":"Employment Agencies",
            "type":"Services"
        }
    ],
    "sg:phone":"+1 781 631 1495",
    "sg:postcode":"01945",
    "sg:province":"MA",
    "sg:tags":[
        "consultant",
        "search",
        "executive"
    ],
    "wof:name":"F-O-R-T-U-N-E Personnel CNSLTS",
    "wof:placetype":"venue"
},
  "geometry": {"coordinates":[-70.88771,42.488246],"type":"Point"}
}