{
  "type": "Feature",
  "properties": {
    "addr:full":"60 Glen Rd Brookline MA 02445",
    "addr:housenumber":"60",
    "addr:postcode":"02445",
    "addr:street":"Glen Rd",
    "iso:country":"US",
    "sg:address":"60 Glen Rd",
    "sg:city":"Brookline",
    "sg:classifiers":[
        {
            "category":"Professional",
            "subcategory":"Management & Consulting",
            "type":"Services"
        }
    ],
    "sg:phone":"+1   ",
    "sg:postcode":"02445",
    "sg:province":"MA",
    "wof:name":"Jfs Design Studios",
    "wof:placetype":"venue"
},
  "geometry": {"coordinates":[-71.117034,42.327076],"type":"Point"}
}