{
  "type": "Feature",
  "properties": {
    "addr:full":"22 Revere Rd East Weymouth MA 02189",
    "addr:housenumber":"22",
    "addr:postcode":"02189",
    "addr:street":"Revere Rd",
    "iso:country":"US",
    "sg:address":"22 Revere Rd",
    "sg:city":"East Weymouth",
    "sg:classifiers":[
        {
            "category":"Building & Trades",
            "subcategory":"Plumbing",
            "type":"Services"
        }
    ],
    "sg:phone":"+1 781 337 9068",
    "sg:postcode":"02189",
    "sg:province":"MA",
    "sg:tags":[
        "conditioning",
        "air",
        "system",
        "contractor"
    ],
    "wof:name":"Warrens Heating & AC",
    "wof:placetype":"venue"
},
  "geometry": {"coordinates":[-70.930868,42.207945],"type":"Point"}
}