{
  "type": "Feature",
  "properties": {
    "addr:full": "50 King Philip Dr Longmeadow MA 01106",
    "addr:housenumber": "50",
    "addr:postcode": "01106",
    "addr:street": "King Philip Dr",
    "iso:country": "US",
    "sg:address": "50 King Philip Dr",
    "sg:city": "Longmeadow",
    "sg:classifiers": [
      {
        "category": "Professional",
        "type": "Services"
      }
    ],
    "sg:phone": "+1 413 567 9964",
    "sg:postcode": "01106",
    "sg:province": "MA",
    "sg:tags": [
      "establishment"
    ],
    "wof:name": "J Brookmeyer",
    "wof:placetype": "venue"
  },
  "geometry": {"coordinates":[-72.546526,42.034749],"type":"Point"}
}
