{
  "type": "Feature",
  "properties": {
    "iso:country":"US",
    "sg:address":"139 Jackson St",
    "sg:city":"Lawrence",
    "sg:classifiers":[
        {
            "category":"Retail",
            "subcategory":"Auto Repair",
            "type":"Services"
        }
    ],
    "sg:phone":"+1 978 687 3049",
    "sg:postcode":"01841",
    "sg:province":"MA",
    "sg:tags":[
        "repairing",
        "automobile"
    ],
    "wof:name":"Independent Import Specialists",
    "wof:placetype":"venue"
},
  "geometry": {"coordinates":[-71.157871,42.712267],"type":"Point"}
}