{
  "type": "Feature",
  "properties": {
    "iso:country":"US",
    "sg:address":"7 Banbury Dr",
    "sg:city":"Westford",
    "sg:classifiers":[
        {
            "category":"Professional",
            "subcategory":"Advertising",
            "type":"Services"
        }
    ],
    "sg:phone":"+1 978 392 0864",
    "sg:postcode":"01886",
    "sg:province":"MA",
    "sg:tags":[
        "agency"
    ],
    "wof:name":"Lab Rat Communications",
    "wof:placetype":"venue"
},
  "geometry": {"coordinates":[-71.433932,42.553201],"type":"Point"}
}