{
  "type": "Feature",
  "properties": {
    "iso:country":"US",
    "sg:address":"1025 Washington St",
    "sg:city":"Braintree",
    "sg:classifiers":[
        {
            "category":"Autos & Motor Vehicles",
            "subcategory":"Automobile Sales",
            "type":"Retail Goods"
        }
    ],
    "sg:phone":"+1 781 843 0345",
    "sg:postcode":"02184",
    "sg:province":"MA",
    "sg:tags":[
        "new",
        "car"
    ],
    "wof:name":"Sunset Auto Sales",
    "wof:placetype":"venue"
},
  "geometry": {"coordinates":[-71.00726,42.201603],"type":"Point"}
}