{
  "type": "Feature",
  "properties": {
    "iso:country":"US",
    "sg:address":"312 North St",
    "sg:city":"Pittsfield",
    "sg:classifiers":[
        {
            "category":"Retail",
            "subcategory":"Repair Shop",
            "type":"Services"
        },
        {
            "category":"Personal",
            "subcategory":"Shoe Repair & Shine",
            "type":"Services"
        }
    ],
    "sg:phone":"+1 413 442 7522",
    "sg:postcode":"01201",
    "sg:province":"MA",
    "sg:tags":[
        "leather",
        "parlor",
        "good"
    ],
    "wof:name":"George's Shoe Repair",
    "wof:placetype":"venue"
},
  "geometry": {"coordinates":[-73.252459,42.453197],"type":"Point"}
}