{
  "type": "Feature",
  "properties": {
    "addr:full": "312 North St Pittsfield MA 01201",
    "addr:housenumber": "312",
    "addr:postcode": "01201",
    "addr:street": "North St",
    "iso:country": "US",
    "ovtr:label": "George's Shoe Repair, 312 North St Pittsfield MA US",
    "ovtr:similarity": 1.9924730062484741,
    "sg:address": "312 North St",
    "sg:city": "Pittsfield",
    "sg:classifiers": [
      {
        "category": "Retail",
        "subcategory": "Repair Shop",
        "type": "Services"
      },
      {
        "category": "Personal",
        "subcategory": "Shoe Repair \u0026 Shine",
        "type": "Services"
      }
    ],
    "sg:phone": "+1 413 442 7522",
    "sg:postcode": "01201",
    "sg:province": "MA",
    "sg:tags": [
      "leather",
      "parlor",
      "good"
    ],
    "wof:name": "George's Shoe Repair",
    "wof:placetype": "venue"
  },
  "geometry": {"coordinates":[-73.252459,42.453197],"type":"Point"}
}
