{
  "type": "Feature",
  "properties": {
    "addr:full":"1916 Beacon St Brighton MA 02135",
    "addr:housenumber":"1916",
    "addr:postcode":"02135",
    "addr:street":"Beacon St",
    "iso:country":"US",
    "sg:address":"1916 Beacon St",
    "sg:city":"Brighton",
    "sg:classifiers":[
        {
            "category":"Cinema",
            "subcategory":"Movie Rental",
            "type":"Entertainment"
        }
    ],
    "sg:phone":"+1 617 738 6225",
    "sg:postcode":"02135",
    "sg:province":"MA",
    "sg:tags":[
        "leasing",
        "video",
        "disc",
        "tape"
    ],
    "wof:name":"Book & Movie Review",
    "wof:placetype":"venue"
},
  "geometry": {"coordinates":[-71.14990899999999,42.336256],"type":"Point"}
}