{
  "type": "Feature",
  "properties": {
    "iso:country":"US",
    "sg:address":"7 Park Ave",
    "sg:city":"Revere",
    "sg:classifiers":[
        {
            "category":"Real Estate",
            "subcategory":"Real Estate Operator",
            "type":"Services"
        }
    ],
    "sg:phone":"+1 781 286 3755",
    "sg:postcode":"02151",
    "sg:province":"MA",
    "sg:tags":[
        "condominium"
    ],
    "wof:name":"Broadway Park Condo",
    "wof:placetype":"venue"
},
  "geometry": {"coordinates":[-71.01241400000001,42.409955],"type":"Point"}
}