{
  "type": "Feature",
  "properties": {
    "addr:full": "1109 Park St Palmer MA 01069",
    "addr:housenumber": "1109",
    "addr:postcode": "01069",
    "addr:street": "Park St",
    "iso:country": "US",
    "sg:address": "1109 Park St",
    "sg:city": "Palmer",
    "sg:classifiers": [
      {
        "category": "Shopping",
        "type": "Retail Goods"
      }
    ],
    "sg:phone": "+1 413 283 8369",
    "sg:postcode": "01069",
    "sg:province": "MA",
    "sg:tags": [
      "pet",
      "food",
      "supply"
    ],
    "wof:name": "Haley's Grain Store Inc",
    "wof:placetype": "venue"
  },
  "geometry": {"coordinates":[-72.313493,42.151159],"type":"Point"}
}
