{
  "type": "Feature",
  "properties": {
    "addr:full":"33 Hamlet St Lawrence MA 01843",
    "addr:housenumber":"33",
    "addr:postcode":"01843",
    "addr:street":"Hamlet St",
    "iso:country":"US",
    "sg:address":"33 Hamlet St",
    "sg:city":"Lawrence",
    "sg:classifiers":[
        {
            "category":"Education",
            "subcategory":"School",
            "type":"Public Place"
        }
    ],
    "sg:phone":"+1   ",
    "sg:postcode":"01843",
    "sg:province":"MA",
    "wof:name":"Lawrence Public School Dst",
    "wof:placetype":"venue"
},
  "geometry": {"coordinates":[-71.164323,42.686008],"type":"Point"}
}