{
  "type": "Feature",
  "properties": {
    "addr:full": "1200 Auburn St Whitman MA 02382",
    "addr:housenumber": "1200",
    "addr:postcode": "02382",
    "addr:street": "Auburn St",
    "iso:country": "US",
    "sg:address": "1200 Auburn St",
    "sg:city": "Whitman",
    "sg:classifiers": [
      {
        "category": "Professional",
        "subcategory": "Engineering",
        "type": "Services"
      }
    ],
    "sg:phone": "+1 781 857 2555",
    "sg:postcode": "02382",
    "sg:province": "MA",
    "sg:tags": [
      "general",
      "contractor"
    ],
    "wof:name": "Watertown Engineering Corp",
    "wof:placetype": "venue"
  },
  "geometry": {"coordinates":[-70.968818,42.071903],"type":"Point"}
}
