{
  "type": "Feature",
  "properties": {
    "addr:full": "32 Lake Ave Worcester MA 01604",
    "addr:housenumber": "32",
    "addr:postcode": "01604",
    "addr:street": "Lake Ave",
    "iso:country": "US",
    "sg:address": "32 Lake Ave",
    "sg:city": "Worcester",
    "sg:classifiers": [
      {
        "category": "Building \u0026 Trades",
        "subcategory": "Pest Control",
        "type": "Services"
      }
    ],
    "sg:phone": "+1 508 792 9000",
    "sg:postcode": "01604",
    "sg:province": "MA",
    "sg:website": "www.colonialpest.com",
    "wof:name": "Colonial Pest Control",
    "wof:placetype": "venue"
  },
  "geometry": {"coordinates":[-71.759126,42.273297],"type":"Point"}
}
