{
  "type": "Feature",
  "properties": {
    "addr:full": "1 Driftwood Dr Woburn MA 01801",
    "addr:housenumber": "1",
    "addr:postcode": "01801",
    "addr:street": "Driftwood Dr",
    "iso:country": "US",
    "sg:address": "1 Driftwood Dr",
    "sg:city": "Woburn",
    "sg:classifiers": [
      {
        "category": "Building \u0026 Trades",
        "subcategory": "Construction",
        "type": "Services"
      }
    ],
    "sg:phone": "+1   ",
    "sg:postcode": "01801",
    "sg:province": "MA",
    "sg:tags": [
      "house"
    ],
    "wof:name": "Santullo Construciton",
    "wof:placetype": "venue"
  },
  "geometry": {"coordinates":[-71.163144,42.517348],"type":"Point"}
}
