{
  "type": "Feature",
  "properties": {
    "iso:country":"US",
    "sg:address":"23 Battle Green Rd",
    "sg:city":"Lexington",
    "sg:classifiers":[
        {
            "category":"Professional",
            "type":"Services"
        }
    ],
    "sg:phone":"+1   ",
    "sg:postcode":"02421",
    "sg:province":"MA",
    "wof:name":"Sakura Japan Inc",
    "wof:placetype":"venue"
},
  "geometry": {"coordinates":[-71.248221,42.448173],"type":"Point"}
}