{
  "type": "Feature",
  "properties": {
    "addr:full": "657 Pleasant St Fall River MA 02721",
    "addr:housenumber": "657",
    "addr:postcode": "02721",
    "addr:street": "Pleasant St",
    "iso:country": "US",
    "ovtr:label": "Best Nails, 657 Pleasant St Fall River MA US",
    "ovtr:similarity": 2.4311060905456543,
    "sg:address": "657 Pleasant St",
    "sg:city": "Fall River",
    "sg:classifiers": [
      {
        "category": "Personal",
        "subcategory": "Beauty Salon",
        "type": "Services"
      }
    ],
    "sg:phone": "+1 508 674 6220",
    "sg:postcode": "02721",
    "sg:province": "MA",
    "sg:tags": [
      "manicuring"
    ],
    "wof:name": "Best Nails",
    "wof:placetype": "venue"
  },
  "geometry": {"coordinates":[-71.144223,41.697565],"type":"Point"}
}
