{
  "type": "Feature",
  "properties": {
    "addr:full":"462 Worcester Rd Charlton MA 01507",
    "addr:housenumber":"462",
    "addr:postcode":"01507",
    "addr:street":"Worcester Rd",
    "iso:country":"US",
    "sg:address":"462 Worcester Rd",
    "sg:city":"Charlton",
    "sg:classifiers":[
        {
            "category":"Retail",
            "subcategory":"Pet Boarding",
            "type":"Services"
        }
    ],
    "sg:phone":"+1 508 248 7474",
    "sg:postcode":"01507",
    "sg:province":"MA",
    "sg:tags":[
        "boarding/pet",
        "sitting"
    ],
    "sg:website":"www.thebarkwoodinn.com",
    "wof:name":"Barkwood Inn the",
    "wof:placetype":"venue"
},
  "geometry": {"coordinates":[-71.911722,42.154411],"type":"Point"}
}