{
  "type": "Feature",
  "properties": {
    "addr:full":"216 Main St Harwich MA 02645",
    "addr:housenumber":"216",
    "addr:postcode":"02645",
    "addr:street":"Main St",
    "iso:country":"US",
    "sg:address":"216 Main St",
    "sg:city":"Harwich",
    "sg:classifiers":[
        {
            "category":"Shopping",
            "type":"Retail Goods"
        }
    ],
    "sg:phone":"+1 508 430 7773",
    "sg:postcode":"02645",
    "sg:province":"MA",
    "sg:tags":[
        "hearing",
        "equipment",
        "supply",
        "impaired"
    ],
    "wof:name":"Benchmark Hearing Svc",
    "wof:placetype":"venue"
},
  "geometry": {"coordinates":[-70.114991,41.695215],"type":"Point"}
}