{
  "type": "Feature",
  "properties": {
    "iso:country":"US",
    "sg:address":"715 Broadway",
    "sg:city":"Revere",
    "sg:classifiers":[
        {
            "category":"Taxi",
            "type":"Transportation"
        }
    ],
    "sg:phone":"+1 781 284 5800",
    "sg:postcode":"02151",
    "sg:province":"MA",
    "wof:name":"Revere Taxi",
    "wof:placetype":"venue"
},
  "geometry": {"coordinates":[-71.00847899999999,42.415981],"type":"Point"}
}