{
  "type": "Feature",
  "properties": {
    "addr:full": "715 Broadway Revere MA 02151",
    "addr:housenumber": "715",
    "addr:postcode": "02151",
    "addr:street": "Broadway",
    "iso:country": "US",
    "sg:address": "715 Broadway",
    "sg:city": "Revere",
    "sg:classifiers": [
      {
        "category": "Taxi",
        "type": "Transportation"
      }
    ],
    "sg:phone": "+1 781 284 5800",
    "sg:postcode": "02151",
    "sg:province": "MA",
    "wof:name": "Revere Taxi",
    "wof:placetype": "venue"
  },
  "geometry": {"coordinates":[-71.008479,42.415981],"type":"Point"}
}
