{
  "type": "Feature",
  "properties": {
    "iso:country":"US",
    "sg:address":"97 Main St",
    "sg:city":"North Easton",
    "sg:classifiers":[
        {
            "category":"Restaurant",
            "type":"Food & Drink"
        }
    ],
    "sg:phone":"+1 508 230 2444",
    "sg:postcode":"02356",
    "sg:province":"MA",
    "wof:name":"Bill's House Of Pizza",
    "wof:placetype":"venue"
},
  "geometry": {"coordinates":[-71.102661,42.066119],"type":"Point"}
}