{
  "type": "Feature",
  "properties": {
    "addr:full": "97 Main St North Easton MA 02356",
    "addr:housenumber": "97",
    "addr:postcode": "02356",
    "addr:street": "Main St",
    "iso:country": "US",
    "ovtr:label": "Bill's House of Pizza, 97 Main St North Easton MA US",
    "ovtr:similarity": 2.499824047088623,
    "sg:address": "97 Main St",
    "sg:city": "North Easton",
    "sg:classifiers": [
      {
        "category": "Restaurant",
        "type": "Food \u0026 Drink"
      }
    ],
    "sg:phone": "+1 508 230 2444",
    "sg:postcode": "02356",
    "sg:province": "MA",
    "wof:name": "Bill's House Of Pizza",
    "wof:placetype": "venue"
  },
  "geometry": {"coordinates":[-71.102661,42.066119],"type":"Point"}
}
