{
  "type": "Feature",
  "properties": {
    "addr:full": "14 Mechanic St Spencer MA 01562",
    "addr:housenumber": "14",
    "addr:postcode": "01562",
    "addr:street": "Mechanic St",
    "iso:country": "US",
    "sg:address": "14 Mechanic St",
    "sg:city": "Spencer",
    "sg:classifiers": [
      {
        "category": "Bars \u0026 Pubs",
        "subcategory": "Nightclub",
        "type": "Food \u0026 Drink"
      }
    ],
    "sg:phone": "+1 508 885 5928",
    "sg:postcode": "01562",
    "sg:province": "MA",
    "sg:tags": [
      "nightlife"
    ],
    "wof:name": "Paradis Cafe - CLOSED",
    "wof:placetype": "venue"
  },
  "geometry": {"coordinates":[-71.993599,42.243198],"type":"Point"}
}
