{
  "type": "Feature",
  "properties": {
    "addr:full": "244 Bodwell St Avon MA 02322",
    "addr:housenumber": "244",
    "addr:postcode": "02322",
    "addr:street": "Bodwell St",
    "iso:country": "US",
    "sg:address": "244 Bodwell St",
    "sg:city": "Avon",
    "sg:classifiers": [
      {
        "category": "Personal",
        "type": "Services"
      }
    ],
    "sg:phone": "+1 617 277 8311",
    "sg:postcode": "02322",
    "sg:province": "MA",
    "sg:tags": [
      "mover"
    ],
    "sg:website": "www.deathwishpiano.com",
    "wof:name": "Deathwish Piano Movers",
    "wof:placetype": "venue"
  },
  "geometry": {"coordinates":[-71.060552,42.136253],"type":"Point"}
}
