{
  "type": "Feature",
  "properties": {
    "addr:full":"54 Kathy Ann Ln Falmouth MA 02540",
    "addr:housenumber":"54",
    "addr:postcode":"02540",
    "addr:street":"Kathy Ann Ln",
    "iso:country":"US",
    "sg:address":"54 Kathy Ann Ln",
    "sg:city":"Falmouth",
    "sg:classifiers":[
        {
            "category":"Building & Trades",
            "subcategory":"Landscaping Services",
            "type":"Services"
        }
    ],
    "sg:phone":"+1 508 548 2099",
    "sg:postcode":"02540",
    "sg:province":"MA",
    "sg:tags":[
        "landscape",
        "contractor"
    ],
    "wof:name":"Majesty Landscape & Constr",
    "wof:placetype":"venue"
},
  "geometry": {"coordinates":[-70.60072700000001,41.561259],"type":"Point"}
}