{
  "type": "Feature",
  "properties": {
    "iso:country":"US",
    "sg:address":"14 Kimball Rd",
    "sg:city":"Amesbury",
    "sg:classifiers":[
        {
            "category":"Personal",
            "subcategory":"Beauty Salon",
            "type":"Services"
        }
    ],
    "sg:phone":"+1 978 388 0056",
    "sg:postcode":"01913",
    "sg:province":"MA",
    "wof:name":"Margaret Bisson Hair Stylist",
    "wof:placetype":"venue"
},
  "geometry": {"coordinates":[-70.959688,42.846853],"type":"Point"}
}