{
  "type": "Feature",
  "properties": {
    "iso:country":"US",
    "sg:address":"83 Oak St",
    "sg:city":"Natick",
    "sg:classifiers":[
        {
            "category":"Professional",
            "subcategory":"Business Services",
            "type":"Services"
        }
    ],
    "sg:phone":"+1 508 652 1988",
    "sg:postcode":"01760",
    "sg:province":"MA",
    "sg:tags":[
        "interior",
        "consultant",
        "design",
        "decorator"
    ],
    "wof:name":"Zarrin Interiors",
    "wof:placetype":"venue"
},
  "geometry": {"coordinates":[-71.332139,42.302839],"type":"Point"}
}