{
  "type": "Feature",
  "properties": {
    "addr:full":"338 Park Ave Worcester MA 01610",
    "addr:housenumber":"338",
    "addr:postcode":"01610",
    "addr:street":"Park Ave",
    "iso:country":"US",
    "sg:address":"338 Park Ave",
    "sg:city":"Worcester",
    "sg:classifiers":[
        {
            "category":"Food & Beverages",
            "subcategory":"Bakery",
            "type":"Retail Goods"
        }
    ],
    "sg:phone":"+1 508 753 4600",
    "sg:postcode":"01610",
    "sg:province":"MA",
    "sg:tags":[
        "doughnut"
    ],
    "wof:name":"Gourmet Donuts",
    "wof:placetype":"venue"
},
  "geometry": {"coordinates":[-71.82067499999999,42.261493],"type":"Point"}
}