{
  "type": "Feature",
  "properties": {
    "addr:full": "305 Newbury St Ste 32 Boston MA 02115",
    "addr:housenumber": "305",
    "addr:postcode": "02115",
    "addr:street": "Newbury St Ste 32",
    "iso:country": "US",
    "sg:address": "305 Newbury St Ste 32",
    "sg:city": "Boston",
    "sg:classifiers": [
      {
        "category": "Personal",
        "subcategory": "Beauty Salon",
        "type": "Services"
      }
    ],
    "sg:phone": "+1 617 236 0025",
    "sg:postcode": "02115",
    "sg:province": "MA",
    "sg:tags": [
      "hair"
    ],
    "wof:name": "Salon 350",
    "wof:placetype": "venue"
  },
  "geometry": {"coordinates":[-71.085477,42.348804],"type":"Point"}
}
