{
  "type": "Feature",
  "properties": {
    "iso:country":"US",
    "sg:address":"50 Gold St",
    "sg:city":"South Boston",
    "sg:classifiers":[
        {
            "category":"Wholesale",
            "subcategory":"Apparel",
            "type":"Manufacturing & Wholesale Goods"
        }
    ],
    "sg:phone":"+1 617 268 8401",
    "sg:postcode":"02127",
    "sg:province":"MA",
    "sg:tags":[
        "button"
    ],
    "wof:name":"Harve Button",
    "wof:placetype":"venue"
},
  "geometry": {"coordinates":[-71.05569199999999,42.340103],"type":"Point"}
}