{
  "type": "Feature",
  "properties": {
    "addr:full": "50 Gold St South Boston MA 02127",
    "addr:housenumber": "50",
    "addr:postcode": "02127",
    "addr:street": "Gold St",
    "iso:country": "US",
    "sg:address": "50 Gold St",
    "sg:city": "South Boston",
    "sg:classifiers": [
      {
        "category": "Wholesale",
        "subcategory": "Apparel",
        "type": "Manufacturing \u0026 Wholesale Goods"
      }
    ],
    "sg:phone": "+1 617 268 8401",
    "sg:postcode": "02127",
    "sg:province": "MA",
    "sg:tags": [
      "button"
    ],
    "wof:name": "Harve Button",
    "wof:placetype": "venue"
  },
  "geometry": {"coordinates":[-71.055692,42.340103],"type":"Point"}
}
