{
  "type": "Feature",
  "properties": {
    "iso:country":"US",
    "sg:address":"44 Washington Street",
    "sg:city":"Brookline",
    "sg:classifiers":[
        {
            "category":"Health Services",
            "subcategory":"Optometrist",
            "type":"Services"
        },
        {
            "category":"Sports & Exercise",
            "subcategory":"Gym",
            "type":"Entertainment"
        }
    ],
    "sg:phone":"+1 617 232 9600",
    "sg:postcode":"02445",
    "sg:province":"MA",
    "sg:tags":[
        "trainer"
    ],
    "wof:name":"Pavlo Irving Phys",
    "wof:placetype":"venue"
},
  "geometry": {"coordinates":[-71.118037,42.331839],"type":"Point"}
}