{
  "type": "Feature",
  "properties": {
    "iso:country":"US",
    "sg:address":"118 W Main St",
    "sg:city":"Spencer",
    "sg:classifiers":[
        {
            "category":"Banks & Credit Unions",
            "subcategory":"Bank",
            "type":"Services"
        }
    ],
    "sg:phone":"+1 508 885 1700",
    "sg:postcode":"01562",
    "sg:province":"MA",
    "wof:name":"Webster First Federal Credit Union",
    "wof:placetype":"venue"
},
  "geometry": {"coordinates":[-72.018097,42.231701],"type":"Point"}
}