{
  "type": "Feature",
  "properties": {
    "addr:full": "118 W Main St Spencer MA 01562",
    "addr:housenumber": "118",
    "addr:postcode": "01562",
    "addr:street": "W Main St",
    "iso:country": "US",
    "ovtr:label": "Webster First Federal Credit Union – Spencer MA, 118 W Main St Spencer MA US",
    "ovtr:similarity": 3.893017053604126,
    "sg:address": "118 W Main St",
    "sg:city": "Spencer",
    "sg:classifiers": [
      {
        "category": "Banks \u0026 Credit Unions",
        "subcategory": "Bank",
        "type": "Services"
      }
    ],
    "sg:phone": "+1 508 885 1700",
    "sg:postcode": "01562",
    "sg:province": "MA",
    "wof:name": "Webster First Federal Credit Union",
    "wof:placetype": "venue"
  },
  "geometry": {"coordinates":[-72.018097,42.231701],"type":"Point"}
}
