{
  "type": "Feature",
  "properties": {
    "iso:country":"US",
    "sg:address":"1 Kelseys Way",
    "sg:city":"Westport",
    "sg:classifiers":[
        {
            "category":"Home & Garden",
            "subcategory":"Building Materials",
            "type":"Retail Goods"
        },
        {
            "category":"Building & Trades",
            "subcategory":"Construction",
            "type":"Services"
        }
    ],
    "sg:phone":"+1 508 673 1476",
    "sg:postcode":"02790",
    "sg:province":"MA",
    "sg:tags":[
        "concrete",
        "foundation",
        "staining",
        "contractor"
    ],
    "wof:name":"Forms-R-Us Inc",
    "wof:placetype":"venue"
},
  "geometry": {"coordinates":[-71.086426,41.609344],"type":"Point"}
}