{
  "type": "Feature",
  "properties": {
    "addr:full": "1 Kelseys Way Westport MA 02790",
    "addr:housenumber": "1",
    "addr:postcode": "02790",
    "addr:street": "Kelseys Way",
    "iso:country": "US",
    "sg:address": "1 Kelseys Way",
    "sg:city": "Westport",
    "sg:classifiers": [
      {
        "category": "Home \u0026 Garden",
        "subcategory": "Building Materials",
        "type": "Retail Goods"
      },
      {
        "category": "Building \u0026 Trades",
        "subcategory": "Construction",
        "type": "Services"
      }
    ],
    "sg:phone": "+1 508 673 1476",
    "sg:postcode": "02790",
    "sg:province": "MA",
    "sg:tags": [
      "concrete",
      "foundation",
      "staining",
      "contractor"
    ],
    "wof:name": "Forms-R-Us Inc",
    "wof:placetype": "venue"
  },
  "geometry": {"coordinates":[-71.086426,41.609344],"type":"Point"}
}
