{
  "type": "Feature",
  "properties": {
    "iso:country":"US",
    "sg:address":"2071 Riverdale St",
    "sg:city":"West Springfield",
    "sg:classifiers":[
        {
            "category":"Real Estate",
            "subcategory":"Real Estate Operator",
            "type":"Services"
        }
    ],
    "sg:phone":"+1 413 739 9596",
    "sg:postcode":"01089",
    "sg:province":"MA",
    "sg:tags":[
        "apartment"
    ],
    "wof:name":"Olympia Manor Apartments",
    "wof:placetype":"venue"
},
  "geometry": {"coordinates":[-72.63266299999999,42.156659],"type":"Point"}
}