{
  "type": "Feature",
  "properties": {
    "iso:country":"US",
    "sg:address":"76 Bedford St Ste 33",
    "sg:city":"Lexington",
    "sg:classifiers":[
        {
            "category":"Professional",
            "subcategory":"Management & Consulting",
            "type":"Services"
        }
    ],
    "sg:phone":"+1 781 274 8400",
    "sg:postcode":"02420",
    "sg:province":"MA",
    "sg:tags":[
        "consultant",
        "educational"
    ],
    "wof:name":"Campus Bound",
    "wof:placetype":"venue"
},
  "geometry": {"coordinates":[-71.233559,42.454319],"type":"Point"}
}