{
  "type": "Feature",
  "properties": {
    "addr:full":"446 Pelham Rd Dracut MA 01826",
    "addr:housenumber":"446",
    "addr:postcode":"01826",
    "addr:street":"Pelham Rd",
    "iso:country":"US",
    "sg:address":"446 Pelham Rd",
    "sg:city":"Dracut",
    "sg:classifiers":[
        {
            "category":"Real Estate",
            "subcategory":"Real Estate Services",
            "type":"Services"
        },
        {
            "category":"Real Estate",
            "subcategory":"Real Estate Agent",
            "type":"Services"
        }
    ],
    "sg:phone":"+1 978 459 9085",
    "sg:postcode":"01826",
    "sg:province":"MA",
    "sg:tags":[
        "buyer",
        "broker"
    ],
    "wof:name":"Leo Ouellette Realtor",
    "wof:placetype":"venue"
},
  "geometry": {"coordinates":[-71.267211,42.713489],"type":"Point"}
}