{
  "type": "Feature",
  "properties": {
    "addr:full":"136 Main St Haydenville MA 01039",
    "addr:housenumber":"136",
    "addr:postcode":"01039",
    "addr:street":"Main St",
    "iso:country":"US",
    "sg:address":"136 Main St",
    "sg:city":"Haydenville",
    "sg:classifiers":[
        {
            "category":"Education",
            "subcategory":"Library",
            "type":"Public Place"
        }
    ],
    "sg:phone":"+1 413 268 8406",
    "sg:postcode":"01039",
    "sg:province":"MA",
    "wof:name":"Haydenville Public Library",
    "wof:placetype":"venue"
},
  "geometry": {"coordinates":[-72.702242,42.374366],"type":"Point"}
}