{
  "type": "Feature",
  "properties": {
    "iso:country":"US",
    "sg:address":"10 Park Plz",
    "sg:city":"Boston",
    "sg:classifiers":[
        {
            "category":"Recreation",
            "type":"Entertainment"
        }
    ],
    "sg:phone":"+1 617 727 3201",
    "sg:postcode":"02116",
    "sg:province":"MA",
    "sg:tags":[
        "attraction",
        "tourist"
    ],
    "sg:website":"www.massvacation.com",
    "wof:name":"Department-Travel & Tourism",
    "wof:placetype":"venue"
},
  "geometry": {"coordinates":[-71.06731600000001,42.352173],"type":"Point"}
}