{
  "type": "Feature",
  "properties": {
    "addr:full": "10 Park Plz Boston MA 02116",
    "addr:housenumber": "10",
    "addr:postcode": "02116",
    "addr:street": "Park Plz",
    "iso:country": "US",
    "sg:address": "10 Park Plz",
    "sg:city": "Boston",
    "sg:classifiers": [
      {
        "category": "Recreation",
        "type": "Entertainment"
      }
    ],
    "sg:phone": "+1 617 727 3201",
    "sg:postcode": "02116",
    "sg:province": "MA",
    "sg:tags": [
      "attraction",
      "tourist"
    ],
    "sg:website": "www.massvacation.com",
    "wof:name": "Department-Travel \u0026 Tourism",
    "wof:placetype": "venue"
  },
  "geometry": {"coordinates":[-71.067316,42.352173],"type":"Point"}
}
