{
  "type": "Feature",
  "properties": {
    "iso:country":"US",
    "sg:address":"57 Gothic St",
    "sg:city":"Northampton",
    "sg:classifiers":[
        {
            "category":"Health Services",
            "subcategory":"Health Practitioner",
            "type":"Services"
        }
    ],
    "sg:phone":"+1   ",
    "sg:postcode":"01060",
    "sg:province":"MA",
    "wof:name":"Miller Davina",
    "wof:placetype":"venue"
},
  "geometry": {"coordinates":[-72.631103,42.319629],"type":"Point"}
}