{
  "type": "Feature",
  "properties": {
    "addr:full": "137 Brighton Ave Allston MA 02134",
    "addr:housenumber": "137",
    "addr:postcode": "02134",
    "addr:street": "Brighton Ave",
    "iso:country": "US",
    "sg:address": "137 Brighton Ave",
    "sg:city": "Allston",
    "sg:classifiers": [
      {
        "category": "Restaurant",
        "type": "Food \u0026 Drink"
      }
    ],
    "sg:menulink": "http://www.allmenus.com/ma/boston/1016-pho-pasteur/menu/",
    "sg:phone": "+1 617 783 2340",
    "sg:postcode": "02134",
    "sg:province": "MA",
    "sg:tags": [
      "asian",
      "vietnamese"
    ],
    "wof:name": "Pho Pasteur",
    "wof:placetype": "venue"
  },
  "geometry": {"coordinates":[-71.131427,42.352966],"type":"Point"}
}
