{
  "type": "Feature",
  "properties": {
    "addr:full": "38 Temple St Reading MA 01867",
    "addr:housenumber": "38",
    "addr:postcode": "01867",
    "addr:street": "Temple St",
    "iso:country": "US",
    "sg:address": "38 Temple St",
    "sg:city": "Reading",
    "sg:classifiers": [
      {
        "category": "Building \u0026 Trades",
        "subcategory": "Plumbing",
        "type": "Services"
      }
    ],
    "sg:phone": "+1 781 944 1503",
    "sg:postcode": "01867",
    "sg:province": "MA",
    "sg:tags": [
      "plumbing",
      "contractor"
    ],
    "wof:name": "William Gibson Plumbing",
    "wof:placetype": "venue"
  },
  "geometry": {"coordinates":[-71.114216,42.521859],"type":"Point"}
}
