{
  "type": "Feature",
  "properties": {
    "iso:country":"US",
    "sg:address":"38 Temple St",
    "sg:city":"Reading",
    "sg:classifiers":[
        {
            "category":"Building & Trades",
            "subcategory":"Plumbing",
            "type":"Services"
        }
    ],
    "sg:phone":"+1 781 944 1503",
    "sg:postcode":"01867",
    "sg:province":"MA",
    "sg:tags":[
        "plumbing",
        "contractor"
    ],
    "wof:name":"William Gibson Plumbing",
    "wof:placetype":"venue"
},
  "geometry": {"coordinates":[-71.114216,42.521859],"type":"Point"}
}