{
  "type": "Feature",
  "properties": {
    "addr:full":"1 Sandra Ln N Boston MA 02188",
    "addr:housenumber":"1",
    "addr:postcode":"02188",
    "addr:street":"Sandra Ln N",
    "iso:country":"US",
    "sg:address":"1 Sandra Ln N",
    "sg:city":"Boston",
    "sg:classifiers":[
        {
            "category":"Banks & Credit Unions",
            "subcategory":"Investment Brokerage",
            "type":"Services"
        }
    ],
    "sg:phone":"+1 617 426 3750",
    "sg:postcode":"02188",
    "sg:province":"MA",
    "sg:tags":[
        "advisory",
        "financial"
    ],
    "sg:website":"www.colonial.com",
    "wof:name":"Columbia Funds Group",
    "wof:placetype":"venue"
},
  "geometry": {"coordinates":[-70.95107899999999,42.192519],"type":"Point"}
}