{
  "type": "Feature",
  "properties": {
    "addr:full":"658 Bay Ln Centerville MA 02632",
    "addr:housenumber":"658",
    "addr:postcode":"02632",
    "addr:street":"Bay Ln",
    "iso:country":"US",
    "sg:address":"658 Bay Ln",
    "sg:city":"Centerville",
    "sg:classifiers":[
        {
            "category":"Education",
            "subcategory":"School",
            "type":"Public Place"
        }
    ],
    "sg:phone":"+1 508 775 2770",
    "sg:postcode":"02632",
    "sg:province":"MA",
    "wof:name":"Centerville Early Learning Center",
    "wof:placetype":"venue"
},
  "geometry": {"coordinates":[-70.353302,41.6474],"type":"Point"}
}