{
  "type": "Feature",
  "properties": {
    "addr:full": "135 Highland Rd Somerville MA 02144",
    "addr:housenumber": "135",
    "addr:postcode": "02144",
    "addr:street": "Highland Rd",
    "iso:country": "US",
    "sg:address": "135 Highland Rd",
    "sg:city": "Somerville",
    "sg:classifiers": [
      {
        "category": "Building \u0026 Trades",
        "subcategory": "Locksmith",
        "type": "Services"
      }
    ],
    "sg:phone": "+1 617 702 1033",
    "sg:postcode": "02144",
    "sg:province": "MA",
    "sg:tags": [
      "key"
    ],
    "wof:name": "All Emergencys Locksmith Service On Hig",
    "wof:placetype": "venue"
  },
  "geometry": {"coordinates":[-71.111427,42.397843],"type":"Point"}
}
