{
  "type": "Feature",
  "properties": {
    "iso:country":"US",
    "sg:address":"135 Highland Rd",
    "sg:city":"Somerville",
    "sg:classifiers":[
        {
            "category":"Building & Trades",
            "subcategory":"Locksmith",
            "type":"Services"
        }
    ],
    "sg:phone":"+1 617 702 1033",
    "sg:postcode":"02144",
    "sg:province":"MA",
    "sg:tags":[
        "key"
    ],
    "wof:name":"All Emergencys Locksmith Service On Hig",
    "wof:placetype":"venue"
},
  "geometry": {"coordinates":[-71.11142700000001,42.397843],"type":"Point"}
}