{
  "type": "Feature",
  "properties": {
    "iso:country":"US",
    "sg:address":"50 Grove St",
    "sg:city":"Salem",
    "sg:classifiers":[
        {
            "category":"Shopping",
            "subcategory":"Hobbies, Toys, & Games",
            "type":"Retail Goods"
        }
    ],
    "sg:phone":"+1 978 741 3231",
    "sg:postcode":"01970",
    "sg:province":"MA",
    "sg:tags":[
        "product",
        "ceramic"
    ],
    "wof:name":"Droll Designs",
    "wof:placetype":"venue"
},
  "geometry": {"coordinates":[-70.91059799999999,42.522386],"type":"Point"}
}