{
  "type": "Feature",
  "properties": {
    "iso:country":"US",
    "sg:address":"358 Great Rd",
    "sg:city":"Acton",
    "sg:classifiers":[
        {
            "category":"Restaurant",
            "type":"Food & Drink"
        }
    ],
    "sg:phone":"+1 978 263 2969",
    "sg:postcode":"01720",
    "sg:province":"MA",
    "wof:name":"Gourmet Bagel",
    "wof:placetype":"venue"
},
  "geometry": {"coordinates":[-71.42054,42.504429],"type":"Point"}
}