{
  "type": "Feature",
  "properties": {
    "addr:full": "117 Elm St Millbury MA 01527",
    "addr:housenumber": "117",
    "addr:postcode": "01527",
    "addr:street": "Elm St",
    "iso:country": "US",
    "sg:address": "117 Elm St",
    "sg:city": "Millbury",
    "sg:classifiers": [
      {
        "category": "Professional",
        "subcategory": "Accounting \u0026 Tax Preparation",
        "type": "Services"
      }
    ],
    "sg:phone": "+1 508 865 5553",
    "sg:postcode": "01527",
    "sg:province": "MA",
    "sg:tags": [
      "return",
      "filing"
    ],
    "wof:name": "James M Beauregard",
    "wof:placetype": "venue"
  },
  "geometry": {"coordinates":[-71.762177,42.190574],"type":"Point"}
}
