{
  "type": "Feature",
  "properties": {
    "addr:full": "491 Petersham Rd Athol MA 01331",
    "addr:housenumber": "491",
    "addr:postcode": "01331",
    "addr:street": "Petersham Rd",
    "iso:country": "US",
    "sg:address": "491 Petersham Rd",
    "sg:city": "Athol",
    "sg:classifiers": [
      {
        "category": "Building \u0026 Trades",
        "subcategory": "Construction",
        "type": "Services"
      }
    ],
    "sg:phone": "+1   ",
    "sg:postcode": "01331",
    "sg:province": "MA",
    "sg:tags": [
      "house"
    ],
    "wof:name": "Bd Homes Inc",
    "wof:placetype": "venue"
  },
  "geometry": {"coordinates":[-72.199669,42.575053],"type":"Point"}
}
