{
  "type": "Feature",
  "properties": {
    "iso:country":"US",
    "sg:address":"255 Interstate Dr",
    "sg:city":"West Springfield",
    "sg:classifiers":[
        {
            "category":"Home & Garden",
            "subcategory":"Building Materials",
            "type":"Retail Goods"
        }
    ],
    "sg:phone":"+1 413 733 1111",
    "sg:postcode":"01089",
    "sg:province":"MA",
    "sg:tags":[
        "windows"
    ],
    "wof:name":"Chandler Architectural Prods",
    "wof:placetype":"venue"
},
  "geometry": {"coordinates":[-72.65066,42.15686],"type":"Point"}
}