{
  "type": "Feature",
  "properties": {
    "addr:full": "3018 Cranberry Hwy East Wareham MA 02538",
    "addr:housenumber": "3018",
    "addr:postcode": "02538",
    "addr:street": "Cranberry Hwy",
    "iso:country": "US",
    "sg:address": "3018 Cranberry Hwy",
    "sg:city": "East Wareham",
    "sg:classifiers": [
      {
        "category": "Restaurant",
        "type": "Food \u0026 Drink"
      }
    ],
    "sg:phone": "+1 508 273 0135",
    "sg:postcode": "02538",
    "sg:province": "MA",
    "sg:website": "www.dangelo.com",
    "wof:name": "D'Angelo Sandwich Shop",
    "wof:placetype": "venue"
  },
  "geometry": {"coordinates":[-70.665397,41.759733],"type":"Point"}
}
