{
  "type": "Feature",
  "properties": {
    "iso:country":"US",
    "sg:address":"3018 Cranberry Hwy",
    "sg:city":"East Wareham",
    "sg:classifiers":[
        {
            "category":"Restaurant",
            "type":"Food & Drink"
        }
    ],
    "sg:phone":"+1 508 273 0135",
    "sg:postcode":"02538",
    "sg:province":"MA",
    "sg:website":"www.dangelo.com",
    "wof:name":"D'Angelo Sandwich Shop",
    "wof:placetype":"venue"
},
  "geometry": {"coordinates":[-70.665397,41.759733],"type":"Point"}
}