{
  "type": "Feature",
  "properties": {
    "addr:full":"21 Parker Ct Gilbertville MA 01037",
    "addr:housenumber":"21",
    "addr:postcode":"01037",
    "addr:street":"Parker Ct",
    "iso:country":"US",
    "sg:address":"21 Parker Ct",
    "sg:city":"Gilbertville",
    "sg:classifiers":[
        {
            "category":"Organizations",
            "subcategory":"Community Association",
            "type":"Services"
        }
    ],
    "sg:phone":"+1 413 477 8256",
    "sg:postcode":"01037",
    "sg:province":"MA",
    "sg:tags":[
        "club"
    ],
    "wof:name":"Veterans Of Foreign Wars",
    "wof:placetype":"venue"
},
  "geometry": {"coordinates":[-72.20623399999999,42.312695],"type":"Point"}
}