{
  "type": "Feature",
  "properties": {
    "iso:country":"US",
    "sg:address":"51 Pleasant St",
    "sg:city":"Marblehead",
    "sg:classifiers":[
        {
            "category":"Recreation",
            "type":"Entertainment"
        },
        {
            "category":"Organizations",
            "subcategory":"Community Association",
            "type":"Services"
        }
    ],
    "sg:phone":"+1 781 631 9810",
    "sg:postcode":"01945",
    "sg:province":"MA",
    "sg:tags":[
        "club",
        "membership"
    ],
    "wof:name":"Gut'n Feathers Club",
    "wof:placetype":"venue"
},
  "geometry": {"coordinates":[-70.85393500000001,42.503909],"type":"Point"}
}