{
  "type": "Feature",
  "properties": {
    "iso:country":"US",
    "sg:address":"1291 Dorchester Ave",
    "sg:city":"Dorchester",
    "sg:classifiers":[
        {
            "category":"Wholesale",
            "subcategory":"Machinery & Supplies",
            "type":"Manufacturing & Wholesale Goods"
        }
    ],
    "sg:phone":"+1 617 288 6077",
    "sg:postcode":"02122",
    "sg:province":"MA",
    "sg:tags":[
        "salon",
        "beauty"
    ],
    "wof:name":"Tulip Supply",
    "wof:placetype":"venue"
},
  "geometry": {"coordinates":[-71.058791,42.306008],"type":"Point"}
}