{
  "type": "Feature",
  "properties": {
    "iso:country":"US",
    "sg:address":"229 Commercial St",
    "sg:city":"Provincetown",
    "sg:classifiers":[
        {
            "category":"Shopping",
            "subcategory":"Clothing, Apparel, & Fashions",
            "type":"Retail Goods"
        }
    ],
    "sg:phone":"+1 508 487 2542",
    "sg:postcode":"02657",
    "sg:province":"MA",
    "wof:name":"Pennsylvania Co",
    "wof:placetype":"venue"
},
  "geometry": {"coordinates":[-70.188138,42.050114],"type":"Point"}
}