{
  "type": "Feature",
  "properties": {
    "iso:country":"US",
    "sg:address":"35 Central St",
    "sg:city":"Manchester",
    "sg:classifiers":[
        {
            "category":"Professional",
            "subcategory":"Lawyer & Legal Services",
            "type":"Services"
        }
    ],
    "sg:phone":"+1 978 526 8000",
    "sg:postcode":"01944",
    "sg:province":"MA",
    "sg:tags":[
        "attorney"
    ],
    "wof:name":"Don Halgren Attorney",
    "wof:placetype":"venue"
},
  "geometry": {"coordinates":[-70.773842,42.575119],"type":"Point"}
}