{
  "type": "Feature",
  "properties": {
    "iso:country":"US",
    "sg:address":"180 Summit St",
    "sg:city":"Belchertown",
    "sg:classifiers":[
        {
            "category":"Building & Trades",
            "subcategory":"Construction",
            "type":"Services"
        }
    ],
    "sg:phone":"+1 413 323 6947",
    "sg:postcode":"01007",
    "sg:province":"MA",
    "sg:tags":[
        "coping",
        "plastering",
        "tiling",
        "pool",
        "swimming"
    ],
    "wof:name":"Pioneer Pool Svc Co",
    "wof:placetype":"venue"
},
  "geometry": {"coordinates":[-72.42639,42.256248],"type":"Point"}
}