{
  "type": "Feature",
  "properties": {
    "addr:full": "180 Summit St Belchertown MA 01007",
    "addr:housenumber": "180",
    "addr:postcode": "01007",
    "addr:street": "Summit St",
    "iso:country": "US",
    "sg:address": "180 Summit St",
    "sg:city": "Belchertown",
    "sg:classifiers": [
      {
        "category": "Building \u0026 Trades",
        "subcategory": "Construction",
        "type": "Services"
      }
    ],
    "sg:phone": "+1 413 323 6947",
    "sg:postcode": "01007",
    "sg:province": "MA",
    "sg:tags": [
      "coping",
      "plastering",
      "tiling",
      "pool",
      "swimming"
    ],
    "wof:name": "Pioneer Pool Svc Co",
    "wof:placetype": "venue"
  },
  "geometry": {"coordinates":[-72.42639,42.256248],"type":"Point"}
}
