{
  "type": "Feature",
  "properties": {
    "iso:country":"US",
    "sg:address":"27 Park St",
    "sg:city":"Adams",
    "sg:classifiers":[
        {
            "category":"Restaurant",
            "type":"Food & Drink"
        }
    ],
    "sg:phone":"+1 413 743 9600",
    "sg:postcode":"01220",
    "sg:province":"MA",
    "wof:name":"Topia Theater & Cafe",
    "wof:placetype":"venue"
},
  "geometry": {"coordinates":[-73.120301,42.621202],"type":"Point"}
}