{
  "type": "Feature",
  "properties": {
    "addr:full": "27 Park St Adams MA 01220",
    "addr:housenumber": "27",
    "addr:postcode": "01220",
    "addr:street": "Park St",
    "iso:country": "US",
    "sg:address": "27 Park St",
    "sg:city": "Adams",
    "sg:classifiers": [
      {
        "category": "Restaurant",
        "type": "Food \u0026 Drink"
      }
    ],
    "sg:phone": "+1 413 743 9600",
    "sg:postcode": "01220",
    "sg:province": "MA",
    "wof:name": "Topia Theater \u0026 Cafe",
    "wof:placetype": "venue"
  },
  "geometry": {"coordinates":[-73.120301,42.621202],"type":"Point"}
}
