{
  "type": "Feature",
  "properties": {
    "iso:country":"US",
    "sg:address":"431 Old Chatham Rd",
    "sg:city":"South Dennis",
    "sg:classifiers":[
        {
            "category":"Home & Garden",
            "subcategory":"Building Materials",
            "type":"Retail Goods"
        }
    ],
    "sg:phone":"+1 508 385 2235",
    "sg:postcode":"02660",
    "sg:province":"MA",
    "sg:tags":[
        "glass",
        "window",
        "plate"
    ],
    "wof:name":"Central Cape Glass",
    "wof:placetype":"venue"
},
  "geometry": {"coordinates":[-70.137743,41.703362],"type":"Point"}
}