{
  "type": "Feature",
  "properties": {
    "addr:full": "431 Old Chatham Rd South Dennis MA 02660",
    "addr:housenumber": "431",
    "addr:postcode": "02660",
    "addr:street": "Old Chatham Rd",
    "iso:country": "US",
    "ovtr:label": "Central Cape Glass, 431 Old Chatham Rd South Dennis MA US",
    "ovtr:similarity": 1.9349759817123413,
    "sg:address": "431 Old Chatham Rd",
    "sg:city": "South Dennis",
    "sg:classifiers": [
      {
        "category": "Home \u0026 Garden",
        "subcategory": "Building Materials",
        "type": "Retail Goods"
      }
    ],
    "sg:phone": "+1 508 385 2235",
    "sg:postcode": "02660",
    "sg:province": "MA",
    "sg:tags": [
      "glass",
      "window",
      "plate"
    ],
    "wof:name": "Central Cape Glass",
    "wof:placetype": "venue"
  },
  "geometry": {"coordinates":[-70.137743,41.703362],"type":"Point"}
}
