{
  "type": "Feature",
  "properties": {
    "addr:full":"30 Grove St Kingston MA 02364",
    "addr:housenumber":"30",
    "addr:postcode":"02364",
    "addr:street":"Grove St",
    "iso:country":"US",
    "sg:address":"30 Grove St",
    "sg:city":"Kingston",
    "sg:classifiers":[
        {
            "category":"Manufacturing",
            "subcategory":"Tools & Machinery",
            "type":"Manufacturing & Wholesale Goods"
        }
    ],
    "sg:phone":"+1   ",
    "sg:postcode":"02364",
    "sg:province":"MA",
    "sg:tags":[
        "devices",
        "mfg"
    ],
    "wof:name":"Rotec Engineered Sales",
    "wof:placetype":"venue"
},
  "geometry": {"coordinates":[-70.75197199999999,41.999662],"type":"Point"}
}