{
  "type": "Feature",
  "properties": {
    "addr:full": "387 Harvard Street Brookline MA 02446",
    "addr:housenumber": "387",
    "addr:postcode": "02446",
    "addr:street": "Harvard Street",
    "iso:country": "US",
    "sg:address": "387 Harvard Street",
    "sg:city": "Brookline",
    "sg:classifiers": [
      {
        "category": "Communications",
        "subcategory": "Newspaper",
        "type": "Services"
      }
    ],
    "sg:phone": "+1 617 734 7400",
    "sg:postcode": "02446",
    "sg:province": "MA",
    "sg:tags": [
      "print",
      "medium"
    ],
    "wof:name": "Boston Courier Russian Newspaper",
    "wof:placetype": "venue"
  },
  "geometry": {"coordinates":[-71.126065,42.344824],"type":"Point"}
}
