{
  "type": "Feature",
  "properties": {
    "iso:country":"US",
    "sg:address":"540 Meadow St",
    "sg:city":"Agawam",
    "sg:classifiers":[
        {
            "category":"Real Estate",
            "subcategory":"Real Estate Agent",
            "type":"Services"
        }
    ],
    "sg:phone":"+1 413 789 3030",
    "sg:postcode":"01001",
    "sg:province":"MA",
    "wof:name":"East West Realty",
    "wof:placetype":"venue"
},
  "geometry": {"coordinates":[-72.588212,42.081374],"type":"Point"}
}