{
  "type": "Feature",
  "properties": {
    "addr:full": "399 Southbridge St Worcester MA 01610",
    "addr:housenumber": "399",
    "addr:postcode": "01610",
    "addr:street": "Southbridge St",
    "iso:country": "US",
    "sg:address": "399 Southbridge St",
    "sg:city": "Worcester",
    "sg:classifiers": [
      {
        "category": "Restaurant",
        "type": "Food \u0026 Drink"
      }
    ],
    "sg:phone": "+1   ",
    "sg:postcode": "01610",
    "sg:province": "MA",
    "sg:tags": [
      "eating"
    ],
    "wof:name": "Subway 30964",
    "wof:placetype": "venue"
  },
  "geometry": {"coordinates":[-71.808022,42.252333],"type":"Point"}
}
