{
  "type": "Feature",
  "properties": {
    "iso:country":"US",
    "sg:address":"399 Southbridge St",
    "sg:city":"Worcester",
    "sg:classifiers":[
        {
            "category":"Restaurant",
            "type":"Food & Drink"
        }
    ],
    "sg:phone":"+1   ",
    "sg:postcode":"01610",
    "sg:province":"MA",
    "sg:tags":[
        "eating"
    ],
    "wof:name":"Subway 30964",
    "wof:placetype":"venue"
},
  "geometry": {"coordinates":[-71.80802199999999,42.252333],"type":"Point"}
}