{
  "type": "Feature",
  "properties": {
    "addr:full": "28 Pleasant St Medfield MA 02052",
    "addr:housenumber": "28",
    "addr:postcode": "02052",
    "addr:street": "Pleasant St",
    "iso:country": "US",
    "sg:address": "28 Pleasant St",
    "sg:city": "Medfield",
    "sg:classifiers": [
      {
        "category": "Social Services",
        "subcategory": "Child Care",
        "type": "Services"
      }
    ],
    "sg:phone": "+1 508 359 3667",
    "sg:postcode": "02052",
    "sg:province": "MA",
    "sg:tags": [
      "kindergarten",
      "academic",
      "school"
    ],
    "wof:name": "Medfield Children's Ctr Inc",
    "wof:placetype": "venue"
  },
  "geometry": {"coordinates":[-71.303785,42.185428],"type":"Point"}
}
