{
  "type": "Feature",
  "properties": {
    "iso:country":"US",
    "sg:address":"17 Blueberry Ln",
    "sg:city":"Lexington",
    "sg:classifiers":[
        {
            "category":"Real Estate",
            "subcategory":"Real Estate Services",
            "type":"Services"
        },
        {
            "category":"Real Estate",
            "subcategory":"Real Estate Agent",
            "type":"Services"
        }
    ],
    "sg:phone":"+1 781 861 9000",
    "sg:postcode":"02420",
    "sg:province":"MA",
    "sg:tags":[
        "buyer",
        "broker"
    ],
    "wof:name":"Malin Realty Inc",
    "wof:placetype":"venue"
},
  "geometry": {"coordinates":[-71.19261,42.447988],"type":"Point"}
}