{
  "type": "Feature",
  "properties": {
    "addr:full": "16 Telegraph Rd Dennis Port MA 02639",
    "addr:housenumber": "16",
    "addr:postcode": "02639",
    "addr:street": "Telegraph Rd",
    "iso:country": "US",
    "sg:address": "16 Telegraph Rd",
    "sg:city": "Dennis Port",
    "sg:classifiers": [
      {
        "category": "Manufacturing",
        "subcategory": "Printing",
        "type": "Manufacturing \u0026 Wholesale Goods"
      }
    ],
    "sg:phone": "+1 508 394 8301",
    "sg:postcode": "02639",
    "sg:province": "MA",
    "sg:tags": [
      "printer"
    ],
    "wof:name": "Mid Cape Printing \u0026 Copy Ctr",
    "wof:placetype": "venue"
  },
  "geometry": {"coordinates":[-70.124343,41.668202],"type":"Point"}
}
