{
  "type": "Feature",
  "properties": {
    "iso:country":"US",
    "sg:address":"410 Bridge St",
    "sg:city":"North Weymouth",
    "sg:classifiers":[
        {
            "category":"Retail",
            "subcategory":"Repair Shop",
            "type":"Services"
        }
    ],
    "sg:phone":"+1 781 782 0337",
    "sg:postcode":"02191",
    "sg:province":"MA",
    "sg:tags":[
        "lock",
        "locksmith"
    ],
    "wof:name":"Emergency 7 Day Locksmith",
    "wof:placetype":"venue"
},
  "geometry": {"coordinates":[-70.949941,42.243101],"type":"Point"}
}