{
  "type": "Feature",
  "properties": {
    "addr:full":"41 Thomas St Fitchburg MA 01420",
    "addr:housenumber":"41",
    "addr:postcode":"01420",
    "addr:street":"Thomas St",
    "iso:country":"US",
    "sg:address":"41 Thomas St",
    "sg:city":"Fitchburg",
    "sg:classifiers":[
        {
            "category":"Building & Trades",
            "subcategory":"Landscaping Services",
            "type":"Services"
        }
    ],
    "sg:phone":"+1   ",
    "sg:postcode":"01420",
    "sg:province":"MA",
    "sg:tags":[
        "landscape"
    ],
    "wof:name":"D & J Landscaping",
    "wof:placetype":"venue"
},
  "geometry": {"coordinates":[-71.79728,42.576239],"type":"Point"}
}