{
  "type": "Feature",
  "properties": {
    "iso:country":"US",
    "sg:address":"1434 Main St",
    "sg:city":"Palmer",
    "sg:classifiers":[
        {
            "category":"Recreation",
            "type":"Entertainment"
        }
    ],
    "sg:phone":"+1 413 283 4822",
    "sg:postcode":"01069",
    "sg:province":"MA",
    "sg:tags":[
        "martial",
        "arts",
        "instruction"
    ],
    "wof:name":"Fred Villari's Studio",
    "wof:placetype":"venue"
},
  "geometry": {"coordinates":[-72.32996799999999,42.157322],"type":"Point"}
}