{
  "type": "Feature",
  "properties": {
    "addr:full": "700 Pleasant St New Bedford MA 02740",
    "addr:housenumber": "700",
    "addr:postcode": "02740",
    "addr:street": "Pleasant St",
    "iso:country": "US",
    "sg:address": "700 Pleasant St",
    "sg:city": "New Bedford",
    "sg:classifiers": [
      {
        "category": "Professional",
        "subcategory": "Management \u0026 Consulting",
        "type": "Services"
      }
    ],
    "sg:phone": "+1   ",
    "sg:postcode": "02740",
    "sg:province": "MA",
    "wof:name": "Clare Cole",
    "wof:placetype": "venue"
  },
  "geometry": {"coordinates":[-70.927107,41.636394],"type":"Point"}
}
