{
  "type": "Feature",
  "properties": {
    "addr:full": "1421 Granby Rd Chicopee MA 01020",
    "addr:housenumber": "1421",
    "addr:postcode": "01020",
    "addr:street": "Granby Rd",
    "iso:country": "US",
    "sg:address": "1421 Granby Rd",
    "sg:city": "Chicopee",
    "sg:classifiers": [
      {
        "category": "Personal",
        "subcategory": "Beauty Salon",
        "type": "Services"
      }
    ],
    "sg:phone": "+1 413 593 9011",
    "sg:postcode": "01020",
    "sg:province": "MA",
    "wof:name": "Bocage Hair Design",
    "wof:placetype": "venue"
  },
  "geometry": {"coordinates":[-72.580801,42.179217],"type":"Point"}
}
