{
  "type": "Feature",
  "properties": {
    "iso:country":"US",
    "sg:address":"1421 Granby Rd",
    "sg:city":"Chicopee",
    "sg:classifiers":[
        {
            "category":"Personal",
            "subcategory":"Beauty Salon",
            "type":"Services"
        }
    ],
    "sg:phone":"+1 413 593 9011",
    "sg:postcode":"01020",
    "sg:province":"MA",
    "wof:name":"Bocage Hair Design",
    "wof:placetype":"venue"
},
  "geometry": {"coordinates":[-72.58080099999999,42.179217],"type":"Point"}
}