{
  "type": "Feature",
  "properties": {
    "iso:country":"US",
    "sg:address":"155 Crowell Rd Ofc",
    "sg:city":"Chatham",
    "sg:classifiers":[
        {
            "category":"Building & Trades",
            "subcategory":"Construction",
            "type":"Services"
        }
    ],
    "sg:phone":"+1 508 945 2300",
    "sg:postcode":"02633",
    "sg:province":"MA",
    "sg:tags":[
        "contractor"
    ],
    "wof:name":"Eastward Companies Inc",
    "wof:placetype":"venue"
},
  "geometry": {"coordinates":[-69.966202,41.689098],"type":"Point"}
}