{
  "type": "Feature",
  "properties": {
    "addr:full":"49 W Wyoming Avenue Melrose MA 02176",
    "addr:housenumber":"49",
    "addr:postcode":"02176",
    "addr:street":"W Wyoming Avenue",
    "iso:country":"US",
    "sg:address":"49 W Wyoming Avenue",
    "sg:city":"Melrose",
    "sg:classifiers":[
        {
            "category":"Food & Beverages",
            "subcategory":"Groceries & Convenience Stores",
            "type":"Retail Goods"
        }
    ],
    "sg:phone":"+1 781 662 0801",
    "sg:postcode":"02176",
    "sg:province":"MA",
    "wof:name":"West Wyoming Market",
    "wof:placetype":"venue"
},
  "geometry": {"coordinates":[-71.06947599999999,42.452196],"type":"Point"}
}