{
  "type": "Feature",
  "properties": {
    "addr:full": "49 W Wyoming Avenue Melrose MA 02176",
    "addr:housenumber": "49",
    "addr:postcode": "02176",
    "addr:street": "W Wyoming Avenue",
    "iso:country": "US",
    "ovtr:label": "West Wyoming Market, 49 W Wyoming Ave Melrose MA US",
    "ovtr:similarity": 2.8137168884277344,
    "sg:address": "49 W Wyoming Avenue",
    "sg:city": "Melrose",
    "sg:classifiers": [
      {
        "category": "Food \u0026 Beverages",
        "subcategory": "Groceries \u0026 Convenience Stores",
        "type": "Retail Goods"
      }
    ],
    "sg:phone": "+1 781 662 0801",
    "sg:postcode": "02176",
    "sg:province": "MA",
    "wof:name": "West Wyoming Market",
    "wof:placetype": "venue"
  },
  "geometry": {"coordinates":[-71.069476,42.452196],"type":"Point"}
}
