{
  "type": "Feature",
  "properties": {
    "iso:country":"US",
    "sg:address":"21 Church St",
    "sg:city":"Hudson",
    "sg:classifiers":[
        {
            "category":"Organizations",
            "subcategory":"Community Association",
            "type":"Services"
        }
    ],
    "sg:phone":"+1 978 568 0408",
    "sg:postcode":"01749",
    "sg:province":"MA",
    "sg:tags":[
        "club"
    ],
    "wof:name":"Boys & Girls Clubs-Metro",
    "wof:placetype":"venue"
},
  "geometry": {"coordinates":[-71.56694899999999,42.392763],"type":"Point"}
}