{
  "type": "Feature",
  "properties": {
    "iso:country":"US",
    "sg:address":"9 Little John Cir",
    "sg:city":"Oxford",
    "sg:classifiers":[
        {
            "category":"Retail",
            "subcategory":"Portrait Studio",
            "type":"Services"
        },
        {
            "category":"Professional",
            "subcategory":"Art Services",
            "type":"Services"
        }
    ],
    "sg:phone":"+1 508 987 5171",
    "sg:postcode":"01540",
    "sg:province":"MA",
    "sg:tags":[
        "photographer",
        "photography",
        "store"
    ],
    "wof:name":"Lasting Images Photography",
    "wof:placetype":"venue"
},
  "geometry": {"coordinates":[-71.873322,42.102691],"type":"Point"}
}