{
  "type": "Feature",
  "properties": {
    "iso:country":"US",
    "sg:address":"77 Alden St",
    "sg:city":"Plymouth",
    "sg:classifiers":[
        {
            "category":"Sports & Exercise",
            "subcategory":"Golf",
            "type":"Entertainment"
        }
    ],
    "sg:phone":"+1 508 295 7010",
    "sg:postcode":"02360",
    "sg:province":"MA",
    "sg:tags":[
        "course"
    ],
    "wof:name":"Golf Course Turf Management",
    "wof:placetype":"venue"
},
  "geometry": {"coordinates":[-70.68203,41.9613],"type":"Point"}
}