{
  "type": "Feature",
  "properties": {
    "addr:full": "77 Alden St Plymouth MA 02360",
    "addr:housenumber": "77",
    "addr:postcode": "02360",
    "addr:street": "Alden St",
    "iso:country": "US",
    "sg:address": "77 Alden St",
    "sg:city": "Plymouth",
    "sg:classifiers": [
      {
        "category": "Sports \u0026 Exercise",
        "subcategory": "Golf",
        "type": "Entertainment"
      }
    ],
    "sg:phone": "+1 508 295 7010",
    "sg:postcode": "02360",
    "sg:province": "MA",
    "sg:tags": [
      "course"
    ],
    "wof:name": "Golf Course Turf Management",
    "wof:placetype": "venue"
  },
  "geometry": {"coordinates":[-70.68203,41.9613],"type":"Point"}
}
