{
  "type": "Feature",
  "properties": {
    "iso:country":"US",
    "sg:address":"8 Park St",
    "sg:city":"Boston",
    "sg:classifiers":[
        {
            "category":"Organizations",
            "subcategory":"Community Association",
            "type":"Services"
        }
    ],
    "sg:phone":"+1 617 227 0589",
    "sg:postcode":"02108",
    "sg:province":"MA",
    "sg:tags":[
        "club"
    ],
    "sg:website":"www.unionclub.org",
    "wof:name":"Union Club",
    "wof:placetype":"venue"
},
  "geometry": {"coordinates":[-71.062944,42.357459],"type":"Point"}
}