{
  "type": "Feature",
  "properties": {
    "iso:country":"US",
    "sg:address":"4 Clarence St",
    "sg:city":"Worcester",
    "sg:classifiers":[
        {
            "category":"Building & Trades",
            "subcategory":"Electrical",
            "type":"Services"
        }
    ],
    "sg:phone":"+1 508 450 1164",
    "sg:postcode":"01605",
    "sg:province":"MA",
    "sg:tags":[
        "electrician"
    ],
    "wof:name":"Flynn Electrical",
    "wof:placetype":"venue"
},
  "geometry": {"coordinates":[-71.808937,42.287979],"type":"Point"}
}