{
  "type": "Feature",
  "properties": {
    "addr:full": "31 Upton St Cambridge MA 02139",
    "addr:housenumber": "31",
    "addr:postcode": "02139",
    "addr:street": "Upton St",
    "iso:country": "US",
    "sg:address": "31 Upton St",
    "sg:city": "Cambridge",
    "sg:classifiers": [
      {
        "category": "Government",
        "subcategory": "Court House",
        "type": "Public Place"
      }
    ],
    "sg:phone": "+1 617 236 4809",
    "sg:postcode": "02139",
    "sg:province": "MA",
    "sg:tags": [
      "justice",
      "peace"
    ],
    "wof:name": "As Good As It Gets Weddings",
    "wof:placetype": "venue"
  },
  "geometry": {"coordinates":[-71.108767,42.36299],"type":"Point"}
}
