{
  "type": "Feature",
  "properties": {
    "addr:full": "915 Commonwealth Ave Boston MA 02215",
    "addr:housenumber": "915",
    "addr:postcode": "02215",
    "addr:street": "Commonwealth Ave",
    "iso:country": "US",
    "sg:address": "915 Commonwealth Ave",
    "sg:city": "Boston",
    "sg:classifiers": [
      {
        "category": "Sports \u0026 Exercise",
        "subcategory": "Gym",
        "type": "Entertainment"
      },
      {
        "category": "Sports \u0026 Exercise",
        "subcategory": "Swimming Pool",
        "type": "Entertainment"
      }
    ],
    "sg:postcode": "02215",
    "sg:province": "MA",
    "sg:website": "bu.edu/fitrec",
    "wof:name": "BU Fitness and Recreation Center",
    "wof:placetype": "venue"
  },
  "geometry": {"coordinates":[-71.117335,42.351409],"type":"Point"}
}
