{
  "type": "Feature",
  "properties": {
    "iso:country":"US",
    "sg:address":"915 Commonwealth Ave",
    "sg:city":"Boston",
    "sg:classifiers":[
        {
            "category":"Sports & Exercise",
            "subcategory":"Gym",
            "type":"Entertainment"
        },
        {
            "category":"Sports & Exercise",
            "subcategory":"Swimming Pool",
            "type":"Entertainment"
        }
    ],
    "sg:postcode":"02215",
    "sg:province":"MA",
    "sg:website":"bu.edu/fitrec",
    "wof:name":"BU Fitness and Recreation Center",
    "wof:placetype":"venue"
},
  "geometry": {"coordinates":[-71.117335,42.351409],"type":"Point"}
}