{
  "type": "Feature",
  "properties": {
    "addr:full":"10 Oakhurst Rd Hopkinton MA 01748",
    "addr:housenumber":"10",
    "addr:postcode":"01748",
    "addr:street":"Oakhurst Rd",
    "iso:country":"US",
    "sg:address":"10 Oakhurst Rd",
    "sg:city":"Hopkinton",
    "sg:classifiers":[
        {
            "category":"Shopping",
            "subcategory":"Musical Instruments",
            "type":"Retail Goods"
        }
    ],
    "sg:phone":"+1 508 435 5191",
    "sg:postcode":"01748",
    "sg:province":"MA",
    "sg:tags":[
        "piano"
    ],
    "wof:name":"Charlie The Tuner",
    "wof:placetype":"venue"
},
  "geometry": {"coordinates":[-71.562473,42.202934],"type":"Point"}
}