{
  "type": "Feature",
  "properties": {
    "iso:country":"US",
    "sg:address":"1101 Beacon St Ste 403W",
    "sg:city":"Brookline",
    "sg:classifiers":[
        {
            "category":"Sports & Exercise",
            "subcategory":"Gym",
            "type":"Entertainment"
        }
    ],
    "sg:phone":"+1 617 332 2777",
    "sg:postcode":"02446",
    "sg:province":"MA",
    "sg:tags":[
        "trainer"
    ],
    "wof:name":"Snap Smart Nutrition Application & Practice",
    "wof:placetype":"venue"
},
  "geometry": {"coordinates":[-71.110917,42.344851],"type":"Point"}
}