{
  "type": "Feature",
  "properties": {
    "addr:full": "1101 Beacon St Ste 403W Brookline MA 02446",
    "addr:housenumber": "1101",
    "addr:postcode": "02446",
    "addr:street": "Beacon St Ste 403W",
    "iso:country": "US",
    "sg:address": "1101 Beacon St Ste 403W",
    "sg:city": "Brookline",
    "sg:classifiers": [
      {
        "category": "Sports \u0026 Exercise",
        "subcategory": "Gym",
        "type": "Entertainment"
      }
    ],
    "sg:phone": "+1 617 332 2777",
    "sg:postcode": "02446",
    "sg:province": "MA",
    "sg:tags": [
      "trainer"
    ],
    "wof:name": "Snap Smart Nutrition Application \u0026 Practice",
    "wof:placetype": "venue"
  },
  "geometry": {"coordinates":[-71.110917,42.344851],"type":"Point"}
}
