{
  "type": "Feature",
  "properties": {
    "iso:country":"US",
    "sg:address":"12 E Border Rd",
    "sg:city":"Malden",
    "sg:classifiers":[
        {
            "category":"Building & Trades",
            "subcategory":"Cleaning & Sanitation",
            "type":"Services"
        }
    ],
    "sg:phone":"+1 781 395 4219",
    "sg:postcode":"02148",
    "sg:province":"MA",
    "sg:tags":[
        "house"
    ],
    "wof:name":"L A Cleaning Co",
    "wof:placetype":"venue"
},
  "geometry": {"coordinates":[-71.077558,42.436831],"type":"Point"}
}