{
  "type": "Feature",
  "properties": {
    "addr:full": "20 Park Plaza Suite 905 Boston MA 02116",
    "addr:housenumber": "20",
    "addr:postcode": "02116",
    "addr:street": "Park Plaza Suite 905",
    "iso:country": "US",
    "sg:address": "20 Park Plaza Suite 905",
    "sg:city": "Boston",
    "sg:classifiers": [
      {
        "category": "Professional",
        "subcategory": "Lawyer \u0026 Legal Services",
        "type": "Services"
      }
    ],
    "sg:phone": "+1 617 227 3700",
    "sg:postcode": "02116",
    "sg:province": "MA",
    "wof:name": "Budreau James H Atty",
    "wof:placetype": "venue"
  },
  "geometry": {"coordinates":[-71.077621,42.348863],"type":"Point"}
}
