{
  "type": "Feature",
  "properties": {
    "iso:country":"US",
    "sg:address":"1585 Hancock St",
    "sg:city":"Quincy",
    "sg:classifiers":[
        {
            "category":"Recreation",
            "type":"Entertainment"
        }
    ],
    "sg:phone":"+1 617 847 3959",
    "sg:postcode":"02169",
    "sg:province":"MA",
    "sg:tags":[
        "parlor",
        "billiard"
    ],
    "wof:name":"Renaissance Billiard Club",
    "wof:placetype":"venue"
},
  "geometry": {"coordinates":[-71.001153,42.247335],"type":"Point"}
}