{
  "type": "Feature",
  "properties": {
    "iso:country":"US",
    "sg:address":"60 State St Ste 700",
    "sg:city":"Boston",
    "sg:classifiers":[
        {
            "category":"Banks & Credit Unions",
            "subcategory":"Bank",
            "type":"Services"
        }
    ],
    "sg:phone":"+1 617 878 2009",
    "sg:postcode":"02109",
    "sg:province":"MA",
    "wof:name":"Bank Leumi NE Business Development",
    "wof:placetype":"venue"
},
  "geometry": {"coordinates":[-71.055919,42.359027],"type":"Point"}
}