{
  "type": "Feature",
  "properties": {
    "iso:country":"US",
    "sg:address":"109 Locksley Rd",
    "sg:city":"Lynnfield",
    "sg:classifiers":[
        {
            "category":"Personal",
            "subcategory":"Beauty Salon",
            "type":"Services"
        }
    ],
    "sg:phone":"+1 781 334 3707",
    "sg:postcode":"01940",
    "sg:province":"MA",
    "wof:name":"Frank Michael's Hair Salon Inc",
    "wof:placetype":"venue"
},
  "geometry": {"coordinates":[-71.009496,42.523051],"type":"Point"}
}