{
  "type": "Feature",
  "properties": {
    "iso:country":"US",
    "sg:address":"244 Boston Post Rd",
    "sg:city":"Wayland",
    "sg:classifiers":[
        {
            "category":"Taxi",
            "type":"Transportation"
        }
    ],
    "sg:phone":"+1 508 358 0099",
    "sg:postcode":"01778",
    "sg:province":"MA",
    "wof:name":"Town Taxi Co",
    "wof:placetype":"venue"
},
  "geometry": {"coordinates":[-71.36174200000001,42.363071],"type":"Point"}
}