{
  "type": "Feature",
  "properties": {
    "addr:full":"929 Dalton Ave Pittsfield MA 01201",
    "addr:housenumber":"929",
    "addr:postcode":"01201",
    "addr:street":"Dalton Ave",
    "iso:country":"US",
    "sg:address":"929 Dalton Ave",
    "sg:city":"Pittsfield",
    "sg:classifiers":[
        {
            "category":"Home & Garden",
            "subcategory":"Building Materials",
            "type":"Retail Goods"
        }
    ],
    "sg:phone":"+1 413 443 6042",
    "sg:postcode":"01201",
    "sg:province":"MA",
    "sg:tags":[
        "paint"
    ],
    "wof:name":"Sherwin-Williams Paints",
    "wof:placetype":"venue"
},
  "geometry": {"coordinates":[-73.196984,42.469896],"type":"Point"}
}