{
  "type": "Feature",
  "properties": {
    "addr:full":"342 Centre Street Jamaica Plain MA 02130",
    "addr:housenumber":"342",
    "addr:postcode":"02130",
    "addr:street":"Centre Street",
    "iso:country":"US",
    "sg:address":"342 Centre Street",
    "sg:city":"Jamaica Plain",
    "sg:classifiers":[
        {
            "category":"Food & Beverages",
            "subcategory":"Groceries & Convenience Stores",
            "type":"Retail Goods"
        }
    ],
    "sg:phone":"+1 617 522 3033",
    "sg:postcode":"02130",
    "sg:province":"MA",
    "wof:name":"Mr V Auto Parts",
    "wof:placetype":"venue"
},
  "geometry": {"coordinates":[-71.10736300000001,42.322594],"type":"Point"}
}