{
  "type": "Feature",
  "properties": {
    "addr:full": "112 W Main St Hyannis MA 02601",
    "addr:housenumber": "112",
    "addr:postcode": "02601",
    "addr:street": "W Main St",
    "iso:country": "US",
    "sg:address": "112 W Main St",
    "sg:city": "Hyannis",
    "sg:classifiers": [
      {
        "category": "Shopping",
        "subcategory": "Clothing, Apparel, \u0026 Fashions",
        "type": "Retail Goods"
      }
    ],
    "sg:phone": "+1 508 771 6615",
    "sg:postcode": "02601",
    "sg:province": "MA",
    "sg:tags": [
      "shop",
      "bridal"
    ],
    "wof:name": "Louise Starr Bridals",
    "wof:placetype": "venue"
  },
  "geometry": {"coordinates":[-70.301003,41.647781],"type":"Point"}
}
