{
  "type": "Feature",
  "properties": {
    "iso:country":"US",
    "sg:address":"112 W Main St",
    "sg:city":"Hyannis",
    "sg:classifiers":[
        {
            "category":"Shopping",
            "subcategory":"Clothing, Apparel, & Fashions",
            "type":"Retail Goods"
        }
    ],
    "sg:phone":"+1 508 771 6615",
    "sg:postcode":"02601",
    "sg:province":"MA",
    "sg:tags":[
        "shop",
        "bridal"
    ],
    "wof:name":"Louise Starr Bridals",
    "wof:placetype":"venue"
},
  "geometry": {"coordinates":[-70.30100299999999,41.647781],"type":"Point"}
}