{
  "type": "Feature",
  "properties": {
    "iso:country":"US",
    "sg:address":"16 Mystic Ave",
    "sg:city":"Medford",
    "sg:classifiers":[
        {
            "category":"Autos & Motor Vehicles",
            "subcategory":"Auto Supplies",
            "type":"Retail Goods"
        }
    ],
    "sg:phone":"+1 781 396 6040",
    "sg:postcode":"02155",
    "sg:province":"MA",
    "sg:tags":[
        "automobile",
        "parts"
    ],
    "wof:name":"Mystic Auto Supply Inc",
    "wof:placetype":"venue"
},
  "geometry": {"coordinates":[-71.109522,42.414179],"type":"Point"}
}