{
  "type": "Feature",
  "properties": {
    "addr:full":"162 Cross Rd Clarksburg MA 01247",
    "addr:housenumber":"162",
    "addr:postcode":"01247",
    "addr:street":"Cross Rd",
    "iso:country":"US",
    "sg:address":"162 Cross Rd",
    "sg:city":"Clarksburg",
    "sg:classifiers":[
        {
            "category":"Professional",
            "subcategory":"Advertising",
            "type":"Services"
        }
    ],
    "sg:phone":"+1 413 664 7832",
    "sg:postcode":"01247",
    "sg:province":"MA",
    "sg:tags":[
        "counselor"
    ],
    "wof:name":"Berkshire Advertising & Office",
    "wof:placetype":"venue"
},
  "geometry": {"coordinates":[-73.08565299999999,42.718097],"type":"Point"}
}