{
  "type": "Feature",
  "properties": {
    "iso:country":"US",
    "sg:address":"32 Crescent Hill Ave",
    "sg:city":"Arlington",
    "sg:classifiers":[
        {
            "category":"Building & Trades",
            "subcategory":"Construction",
            "type":"Services"
        }
    ],
    "sg:phone":"+1 781 641 1144",
    "sg:postcode":"02474",
    "sg:province":"MA",
    "sg:tags":[
        "roofing",
        "contractor"
    ],
    "wof:name":"Top Notch Roofing & Sheetmetal",
    "wof:placetype":"venue"
},
  "geometry": {"coordinates":[-71.18356,42.428564],"type":"Point"}
}