{
  "type": "Feature",
  "properties": {
    "addr:full":"PO Box 67523 Suite 204 Chestnut Hill MA 02467",
    "addr:housenumber":"po box 67523 suite 204",
    "addr:postcode":"02467",
    "addr:street":"Hill",
    "iso:country":"US",
    "sg:address":"PO Box 67523 Suite 204",
    "sg:city":"Chestnut Hill",
    "sg:classifiers":[
        {
            "category":"Banks & Credit Unions",
            "subcategory":"Financial Services",
            "type":"Services"
        }
    ],
    "sg:phone":"+1 617 965 3555",
    "sg:postcode":"02467",
    "sg:province":"MA",
    "sg:tags":[
        "broker",
        "mortgage"
    ],
    "wof:name":"Bankers Mutual Trust",
    "wof:placetype":"venue"
},
  "geometry": {"coordinates":[-71.161737,42.329348],"type":"Point"}
}