{
  "type": "Feature",
  "properties": {
    "addr:full": "282 Winthrop St Taunton MA 02780",
    "addr:housenumber": "282",
    "addr:postcode": "02780",
    "addr:street": "Winthrop St",
    "iso:country": "US",
    "ovtr:label": "Vault Liquors, 280 Winthrop St Taunton MA US",
    "ovtr:similarity": 2.5906269550323486,
    "sg:address": "282 Winthrop St",
    "sg:city": "Taunton",
    "sg:classifiers": [
      {
        "category": "Food \u0026 Beverages",
        "subcategory": "Liquor \u0026 Beverages",
        "type": "Retail Goods"
      }
    ],
    "sg:phone": "+1 508 821 2718",
    "sg:postcode": "02780",
    "sg:province": "MA",
    "wof:name": "Vault Liquors",
    "wof:placetype": "venue"
  },
  "geometry": {"coordinates":[-71.120009,41.889126],"type":"Point"}
}
