{
  "type": "Feature",
  "properties": {
    "addr:full": "385 Southbridge St Auburn MA 01501",
    "addr:housenumber": "385",
    "addr:postcode": "01501",
    "addr:street": "Southbridge St",
    "iso:country": "US",
    "sg:address": "385 Southbridge St",
    "sg:city": "Auburn",
    "sg:classifiers": [
      {
        "category": "Restaurant",
        "type": "Food \u0026 Drink"
      }
    ],
    "sg:menulink": "http://www.allmenus.com/ma/auburn/131882-subway/menu/",
    "sg:phone": "+1 508 832 4290",
    "sg:postcode": "01501",
    "sg:province": "MA",
    "sg:tags": [
      "american",
      "sandwich"
    ],
    "wof:name": "Subway",
    "wof:placetype": "venue"
  },
  "geometry": {"coordinates":[-71.835735,42.20287],"type":"Point"}
}
