{
  "type": "Feature",
  "properties": {
    "iso:country":"US",
    "sg:address":"5 Riverside Dr",
    "sg:city":"Berkley",
    "sg:classifiers":[
        {
            "category":"Retail",
            "subcategory":"Repair Shop",
            "type":"Services"
        }
    ],
    "sg:phone":"+1 508 821 9663",
    "sg:postcode":"02779",
    "sg:province":"MA",
    "sg:tags":[
        "trade",
        "welding",
        "contractor"
    ],
    "wof:name":"De Rosa Welding",
    "wof:placetype":"venue"
},
  "geometry": {"coordinates":[-71.113302,41.783892],"type":"Point"}
}