{
  "type": "Feature",
  "properties": {
    "addr:full": "581 Bridge St Lowell MA 01850",
    "addr:housenumber": "581",
    "addr:postcode": "01850",
    "addr:street": "Bridge St",
    "iso:country": "US",
    "sg:address": "581 Bridge St",
    "sg:city": "Lowell",
    "sg:classifiers": [
      {
        "category": "Shopping",
        "subcategory": "Gifts \u0026 Souvenirs",
        "type": "Retail Goods"
      }
    ],
    "sg:phone": "+1 978 458 1076",
    "sg:postcode": "01850",
    "sg:province": "MA",
    "sg:tags": [
      "shop"
    ],
    "wof:name": "Jenny Gift Shop",
    "wof:placetype": "venue"
  },
  "geometry": {"coordinates":[-71.302551,42.652895],"type":"Point"}
}
