{
  "type": "Feature",
  "properties": {
    "iso:country":"US",
    "sg:address":"581 Bridge St",
    "sg:city":"Lowell",
    "sg:classifiers":[
        {
            "category":"Shopping",
            "subcategory":"Gifts & Souvenirs",
            "type":"Retail Goods"
        }
    ],
    "sg:phone":"+1 978 458 1076",
    "sg:postcode":"01850",
    "sg:province":"MA",
    "sg:tags":[
        "shop"
    ],
    "wof:name":"Jenny Gift Shop",
    "wof:placetype":"venue"
},
  "geometry": {"coordinates":[-71.30255099999999,42.652895],"type":"Point"}
}