{
  "type": "Feature",
  "properties": {
    "addr:full": "130 N Main St Leominster MA 01453",
    "addr:housenumber": "130",
    "addr:postcode": "01453",
    "addr:street": "N Main St",
    "iso:country": "US",
    "sg:address": "130 N Main St",
    "sg:city": "Leominster",
    "sg:classifiers": [
      {
        "category": "Health Services",
        "subcategory": "Doctor",
        "type": "Services"
      }
    ],
    "sg:phone": "+1 978 534 4853",
    "sg:postcode": "01453",
    "sg:province": "MA",
    "sg:tags": [
      "dentist"
    ],
    "wof:name": "Joseph F P Cronin DDS",
    "wof:placetype": "venue"
  },
  "geometry": {"coordinates":[-71.757396,42.53656],"type":"Point"}
}
