{
  "type": "Feature",
  "properties": {
    "iso:country":"US",
    "sg:address":"41 Meetinghouse Ln",
    "sg:city":"Sagamore Beach",
    "sg:classifiers":[
        {
            "category":"Shopping",
            "subcategory":"Bicycles & Sporting Goods",
            "type":"Retail Goods"
        }
    ],
    "sg:phone":"+1 508 833 3500",
    "sg:postcode":"02562",
    "sg:province":"MA",
    "sg:tags":[
        "tackle",
        "fishing"
    ],
    "wof:name":"One Shot Outdoor Sports Inc",
    "wof:placetype":"venue"
},
  "geometry": {"coordinates":[-70.536564,41.780809],"type":"Point"}
}