{
  "type": "Feature",
  "properties": {
    "addr:full": "75 Providence Hwy Norwood MA 02062",
    "addr:housenumber": "75",
    "addr:postcode": "02062",
    "addr:street": "Providence Hwy",
    "iso:country": "US",
    "sg:address": "75 Providence Hwy",
    "sg:city": "Norwood",
    "sg:classifiers": [
      {
        "category": "Shopping",
        "type": "Retail Goods"
      }
    ],
    "sg:phone": "+1 781 551 9092",
    "sg:postcode": "02062",
    "sg:province": "MA",
    "sg:tags": [
      "religious"
    ],
    "sg:website": "www.saintmichelarts.com",
    "wof:name": "St Michel Liturgical Arts Inc",
    "wof:placetype": "venue"
  },
  "geometry": {"coordinates":[-71.184561,42.209562],"type":"Point"}
}
