{
  "type": "Feature",
  "properties": {
    "addr:full": "8 Mortimer Pl # 3 Somerville MA 02145",
    "addr:housenumber": "8",
    "addr:postcode": "02145",
    "addr:street": "Mortimer Pl # 3",
    "iso:country": "US",
    "sg:address": "8 Mortimer Pl # 3",
    "sg:city": "Somerville",
    "sg:classifiers": [
      {
        "category": "Building \u0026 Trades",
        "subcategory": "Cleaning \u0026 Sanitation",
        "type": "Services"
      }
    ],
    "sg:phone": "+1 857 231 6262",
    "sg:postcode": "02145",
    "sg:province": "MA",
    "sg:tags": [
      "site-clean-up",
      "house",
      "construction",
      "janitorial",
      "cleaners-interior"
    ],
    "wof:name": "Ara Cleaning Company",
    "wof:placetype": "venue"
  },
  "geometry": {"coordinates":[-71.094198,42.390527],"type":"Point"}
}
