{
  "type": "Feature",
  "properties": {
    "iso:country":"US",
    "sg:address":"8 Mortimer Pl # 3",
    "sg:city":"Somerville",
    "sg:classifiers":[
        {
            "category":"Building & Trades",
            "subcategory":"Cleaning & Sanitation",
            "type":"Services"
        }
    ],
    "sg:phone":"+1 857 231 6262",
    "sg:postcode":"02145",
    "sg:province":"MA",
    "sg:tags":[
        "site-clean-up",
        "house",
        "construction",
        "janitorial",
        "cleaners-interior"
    ],
    "wof:name":"Ara Cleaning Company",
    "wof:placetype":"venue"
},
  "geometry": {"coordinates":[-71.09419800000001,42.390527],"type":"Point"}
}