{
  "type": "Feature",
  "properties": {
    "addr:full": "36 Harlow St Worcester MA 01605",
    "addr:housenumber": "36",
    "addr:postcode": "01605",
    "addr:street": "Harlow St",
    "iso:country": "US",
    "sg:address": "36 Harlow St",
    "sg:city": "Worcester",
    "sg:classifiers": [
      {
        "category": "Wholesale",
        "subcategory": "Hardware",
        "type": "Manufacturing \u0026 Wholesale Goods"
      }
    ],
    "sg:phone": "+1 508 755 2237",
    "sg:postcode": "01605",
    "sg:province": "MA",
    "sg:tags": [
      "oil",
      "burner"
    ],
    "wof:name": "Johnson \u0026 Bouvier Co",
    "wof:placetype": "venue"
  },
  "geometry": {"coordinates":[-71.793219,42.283457],"type":"Point"}
}
