{
  "type": "Feature",
  "properties": {
    "addr:full": "271 Western Ave Lynn MA 01904",
    "addr:housenumber": "271",
    "addr:postcode": "01904",
    "addr:street": "Western Ave",
    "iso:country": "US",
    "sg:address": "271 Western Ave",
    "sg:city": "Lynn",
    "sg:classifiers": [
      {
        "category": "Real Estate",
        "subcategory": "Real Estate Agent",
        "type": "Services"
      }
    ],
    "sg:phone": "+1 781 599 8001",
    "sg:postcode": "01904",
    "sg:province": "MA",
    "wof:name": "Joe Wilson \u0026 Co Realty",
    "wof:placetype": "venue"
  },
  "geometry": {"coordinates":[-70.94984,42.476459],"type":"Point"}
}
