{
  "type": "Feature",
  "properties": {
    "iso:country":"US",
    "sg:address":"290 Baker Ave Exd",
    "sg:city":"Concord",
    "sg:classifiers":[
        {
            "category":"Health Services",
            "subcategory":"Doctor",
            "type":"Services"
        }
    ],
    "sg:phone":"+1 978 369 7770",
    "sg:postcode":"01742",
    "sg:province":"MA",
    "sg:tags":[
        "dentist"
    ],
    "wof:name":"John T Prehn DDS",
    "wof:placetype":"venue"
},
  "geometry": {"coordinates":[-71.386657,42.460522],"type":"Point"}
}