{
  "type": "Feature",
  "properties": {
    "addr:full": "55 Elm St Millbury MA 01527",
    "addr:housenumber": "55",
    "addr:postcode": "01527",
    "addr:street": "Elm St",
    "iso:country": "US",
    "sg:address": "55 Elm St",
    "sg:city": "Millbury",
    "sg:classifiers": [
      {
        "category": "Building \u0026 Trades",
        "subcategory": "Construction",
        "type": "Services"
      }
    ],
    "sg:phone": "+1 508 865 3227",
    "sg:postcode": "01527",
    "sg:province": "MA",
    "sg:tags": [
      "paving",
      "contractor"
    ],
    "wof:name": "S Casey",
    "wof:placetype": "venue"
  },
  "geometry": {"coordinates":[-71.758796,42.191851],"type":"Point"}
}
