{
  "type": "Feature",
  "properties": {
    "addr:full": "1776 Main St Springfield MA 01103",
    "addr:housenumber": "1776",
    "addr:postcode": "01103",
    "addr:street": "Main St",
    "iso:country": "US",
    "sg:address": "1776 Main St",
    "sg:city": "Springfield",
    "sg:classifiers": [
      {
        "category": "Local Transit",
        "type": "Transportation"
      }
    ],
    "sg:phone": "+1 413 781 7882",
    "sg:postcode": "01103",
    "sg:province": "MA",
    "sg:tags": [
      "bus",
      "line"
    ],
    "wof:name": "Pioneer Valley Transit Athrty",
    "wof:placetype": "venue"
  },
  "geometry": {"coordinates":[-72.595991,42.105182],"type":"Point"}
}
