{
  "type": "Feature",
  "properties": {
    "iso:country":"US",
    "sg:address":"19 N Spencer Rd",
    "sg:city":"Spencer",
    "sg:classifiers":[
        {
            "category":"Wholesale",
            "subcategory":"Auto Parts",
            "type":"Manufacturing & Wholesale Goods"
        }
    ],
    "sg:phone":"+1 508 885 7205",
    "sg:postcode":"01562",
    "sg:province":"MA",
    "sg:tags":[
        "automobile",
        "rebuilt"
    ],
    "wof:name":"Paul's Ford Barn & Towing",
    "wof:placetype":"venue"
},
  "geometry": {"coordinates":[-72.009242,42.257639],"type":"Point"}
}