{
  "type": "Feature",
  "properties": {
    "addr:full": "19 N Spencer Rd Spencer MA 01562",
    "addr:housenumber": "19",
    "addr:postcode": "01562",
    "addr:street": "N Spencer Rd",
    "iso:country": "US",
    "sg:address": "19 N Spencer Rd",
    "sg:city": "Spencer",
    "sg:classifiers": [
      {
        "category": "Wholesale",
        "subcategory": "Auto Parts",
        "type": "Manufacturing \u0026 Wholesale Goods"
      }
    ],
    "sg:phone": "+1 508 885 7205",
    "sg:postcode": "01562",
    "sg:province": "MA",
    "sg:tags": [
      "automobile",
      "rebuilt"
    ],
    "wof:name": "Paul's Ford Barn \u0026 Towing",
    "wof:placetype": "venue"
  },
  "geometry": {"coordinates":[-72.009242,42.257639],"type":"Point"}
}
