{
  "type": "Feature",
  "properties": {
    "addr:full": "200 Captains Row Chelsea MA 02150",
    "addr:housenumber": "200",
    "addr:postcode": "02150",
    "addr:street": "Captains Row",
    "iso:country": "US",
    "sg:address": "200 Captains Row",
    "sg:city": "Chelsea",
    "sg:classifiers": [
      {
        "category": "Professional",
        "type": "Services"
      }
    ],
    "sg:phone": "+1   ",
    "sg:postcode": "02150",
    "sg:province": "MA",
    "wof:name": "JRS Constrction Serviceinc",
    "wof:placetype": "venue"
  },
  "geometry": {"coordinates":[-71.044284,42.389765],"type":"Point"}
}
