{
  "type": "Feature",
  "properties": {
    "iso:country":"US",
    "sg:address":"2 Winn St",
    "sg:city":"Burlington",
    "sg:classifiers":[
        {
            "category":"Education",
            "subcategory":"School",
            "type":"Public Place"
        }
    ],
    "sg:phone":"+1 781 272 2074",
    "sg:postcode":"01803",
    "sg:province":"MA",
    "sg:website":"www.cobma.org",
    "wof:name":"Open Bible",
    "wof:placetype":"venue"
},
  "geometry": {"coordinates":[-71.170197,42.488998],"type":"Point"}
}