{
  "type": "Feature",
  "properties": {
    "iso:country":"US",
    "sg:address":"52 Dragon Ct",
    "sg:city":"Woburn",
    "sg:classifiers":[
        {
            "category":"Wholesale",
            "subcategory":"Electrical",
            "type":"Manufacturing & Wholesale Goods"
        }
    ],
    "sg:phone":"+1 781 933 2466",
    "sg:postcode":"01801",
    "sg:province":"MA",
    "sg:tags":[
        "equipment",
        "ultrasonic",
        "supply"
    ],
    "wof:name":"Advanced Devices",
    "wof:placetype":"venue"
},
  "geometry": {"coordinates":[-71.130066,42.513975],"type":"Point"}
}