{
  "type": "Feature",
  "properties": {
    "addr:full": "1 Mifflin Pl Ste 400 Cambridge MA 02138",
    "addr:housenumber": "1",
    "addr:postcode": "02138",
    "addr:street": "Mifflin Pl Ste 400",
    "iso:country": "US",
    "sg:address": "1 Mifflin Pl Ste 400",
    "sg:city": "Cambridge",
    "sg:classifiers": [
      {
        "category": "Professional",
        "subcategory": "Lawyer \u0026 Legal Services",
        "type": "Services"
      }
    ],
    "sg:phone": "+1 339 221 1077",
    "sg:postcode": "02138",
    "sg:province": "MA",
    "sg:website": "www.immigrationado.com",
    "wof:name": "Albrecht Immigration Strategies, PC",
    "wof:placetype": "venue"
  },
  "geometry": {"coordinates":[-71.122474,42.373431],"type":"Point"}
}
