{
  "type": "Feature",
  "properties": {
    "addr:full":"69 Bridge St Salem MA 01970",
    "addr:housenumber":"69",
    "addr:postcode":"01970",
    "addr:street":"Bridge St",
    "iso:country":"US",
    "sg:address":"69 Bridge St",
    "sg:city":"Salem",
    "sg:classifiers":[
        {
            "category":"Wholesale",
            "subcategory":"Hardware",
            "type":"Manufacturing & Wholesale Goods"
        },
        {
            "category":"Professional",
            "type":"Services"
        },
        {
            "category":"Retail",
            "subcategory":"Repair Shop",
            "type":"Services"
        }
    ],
    "sg:phone":"+1 978 745 1248",
    "sg:postcode":"01970",
    "sg:province":"MA",
    "sg:tags":[
        "sharpening",
        "saw",
        "saws-sharpen"
    ],
    "wof:name":"Ceramaloy Carbide Sharpening",
    "wof:placetype":"venue"
},
  "geometry": {"coordinates":[-70.88915299999999,42.530819],"type":"Point"}
}