{
  "type": "Feature",
  "properties": {
    "addr:full":"200 SW Cutoff Worcester MA 01604",
    "addr:housenumber":"200",
    "addr:postcode":"01604",
    "addr:street":"Sw Cutoff",
    "iso:country":"US",
    "sg:address":"200 SW Cutoff",
    "sg:city":"Worcester",
    "sg:classifiers":[
        {
            "category":"Autos & Motor Vehicles",
            "subcategory":"Boat Sales",
            "type":"Retail Goods"
        }
    ],
    "sg:phone":"+1 508 791 7116",
    "sg:postcode":"01604",
    "sg:province":"MA",
    "sg:tags":[
        "dealer",
        "sales"
    ],
    "sg:website":"www.marineusainc.com",
    "wof:name":"Marine USA Inc",
    "wof:placetype":"venue"
},
  "geometry": {"coordinates":[-71.75877699999999,42.227503],"type":"Point"}
}