{
  "type": "Feature",
  "properties": {
    "iso:country":"US",
    "sg:address":"13 Joy St",
    "sg:city":"Somerville",
    "sg:classifiers":[
        {
            "category":"Real Estate",
            "subcategory":"Real Estate Agent",
            "type":"Services"
        }
    ],
    "sg:phone":"+1 617 776 0838",
    "sg:postcode":"02143",
    "sg:province":"MA",
    "wof:name":"Union Square Auto Inc",
    "wof:placetype":"venue"
},
  "geometry": {"coordinates":[-71.088444,42.380299],"type":"Point"}
}