{
  "type": "Feature",
  "properties": {
    "addr:full":"61 Squire Road Revere MA 02151",
    "addr:housenumber":"61",
    "addr:postcode":"02151",
    "addr:street":"Squire Road",
    "iso:country":"US",
    "sg:address":"61 Squire Road",
    "sg:city":"Revere",
    "sg:classifiers":[
        {
            "category":"Home & Garden",
            "subcategory":"Household Appliances",
            "type":"Retail Goods"
        }
    ],
    "sg:phone":"+1 781 284 4363",
    "sg:postcode":"02151",
    "sg:province":"MA",
    "wof:name":"Sozio Night Lighting & Searchlight Service",
    "wof:placetype":"venue"
},
  "geometry": {"coordinates":[-71.00694,42.422143],"type":"Point"}
}