{
  "type": "Feature",
  "properties": {
    "addr:full":"40 Depot St Duxbury MA 02332",
    "addr:housenumber":"40",
    "addr:postcode":"02332",
    "addr:street":"Depot St",
    "iso:country":"US",
    "sg:address":"40 Depot St",
    "sg:city":"Duxbury",
    "sg:classifiers":[
        {
            "category":"Professional",
            "subcategory":"Business Services",
            "type":"Services"
        }
    ],
    "sg:phone":"+1 781 934 0334",
    "sg:postcode":"02332",
    "sg:province":"MA",
    "sg:tags":[
        "interior",
        "consultant",
        "design",
        "decorator"
    ],
    "wof:name":"Ejaba Interiors",
    "wof:placetype":"venue"
},
  "geometry": {"coordinates":[-70.683857,42.025599],"type":"Point"}
}