{
  "type": "Feature",
  "properties": {
    "addr:full":"20 Lincoln St Wakefield MA 01880",
    "addr:housenumber":"20",
    "addr:postcode":"01880",
    "addr:street":"Lincoln St",
    "iso:country":"US",
    "sg:address":"20 Lincoln St",
    "sg:city":"Wakefield",
    "sg:classifiers":[
        {
            "category":"Autos & Motor Vehicles",
            "subcategory":"Auto Supplies",
            "type":"Retail Goods"
        }
    ],
    "sg:phone":"+1 781 245 5548",
    "sg:postcode":"01880",
    "sg:province":"MA",
    "sg:tags":[
        "tire"
    ],
    "wof:name":"Wakefield Tire Ctr",
    "wof:placetype":"venue"
},
  "geometry": {"coordinates":[-71.068517,42.503108],"type":"Point"}
}