{
  "type": "Feature",
  "properties": {
    "addr:full": "76 Mountain Rd Waltham MA 02451",
    "addr:housenumber": "76",
    "addr:postcode": "02451",
    "addr:street": "Mountain Rd",
    "iso:country": "US",
    "sg:address": "76 Mountain Rd",
    "sg:city": "Waltham",
    "sg:classifiers": [
      {
        "category": "Building \u0026 Trades",
        "subcategory": "Construction",
        "type": "Services"
      }
    ],
    "sg:phone": "+1 781 890 6522",
    "sg:postcode": "02451",
    "sg:province": "MA",
    "sg:tags": [
      "house",
      "general",
      "contractor"
    ],
    "wof:name": "Apex Builders Inc",
    "wof:placetype": "venue"
  },
  "geometry": {"coordinates":[-71.26359,42.419326],"type":"Point"}
}
