{
  "type": "Feature",
  "properties": {
    "iso:country":"US",
    "sg:address":"76 Mountain Rd",
    "sg:city":"Waltham",
    "sg:classifiers":[
        {
            "category":"Building & Trades",
            "subcategory":"Construction",
            "type":"Services"
        }
    ],
    "sg:phone":"+1 781 890 6522",
    "sg:postcode":"02451",
    "sg:province":"MA",
    "sg:tags":[
        "house",
        "general",
        "contractor"
    ],
    "wof:name":"Apex Builders Inc",
    "wof:placetype":"venue"
},
  "geometry": {"coordinates":[-71.26358999999999,42.419326],"type":"Point"}
}