{
  "type": "Feature",
  "properties": {
    "iso:country":"US",
    "sg:address":"45 Haskell Cir",
    "sg:city":"Lakeville",
    "sg:classifiers":[
        {
            "category":"Professional",
            "subcategory":"Engineering",
            "type":"Services"
        }
    ],
    "sg:phone":"+1   ",
    "sg:postcode":"02347",
    "sg:province":"MA",
    "sg:tags":[
        "civil",
        "consultant",
        "land",
        "engineer",
        "surveying"
    ],
    "wof:name":"Donald P Mac Neill",
    "wof:placetype":"venue"
},
  "geometry": {"coordinates":[-70.93113,41.881274],"type":"Point"}
}