{
  "type": "Feature",
  "properties": {
    "addr:full":"197 8th St Charlestown MA 02129",
    "addr:housenumber":"197",
    "addr:postcode":"02129",
    "addr:street":"8Th St",
    "iso:country":"US",
    "sg:address":"197 8th St",
    "sg:city":"Charlestown",
    "sg:classifiers":[
        {
            "category":"Real Estate",
            "subcategory":"Real Estate Agent",
            "type":"Services"
        }
    ],
    "sg:phone":"+1 617 242 0025",
    "sg:postcode":"02129",
    "sg:province":"MA",
    "sg:website":"www.newenglandmoves.com",
    "wof:name":"Coldwell Banker",
    "wof:placetype":"venue"
},
  "geometry": {"coordinates":[-71.051661,42.373752],"type":"Point"}
}