{
  "type": "Feature",
  "properties": {
    "addr:full":"495 Main St Stoneham MA 02180",
    "addr:housenumber":"495",
    "addr:postcode":"02180",
    "addr:street":"Main St",
    "iso:country":"US",
    "sg:address":"495 Main St",
    "sg:city":"Stoneham",
    "sg:classifiers":[
        {
            "category":"Personal",
            "subcategory":"Massage",
            "type":"Services"
        }
    ],
    "sg:phone":"+1 781 438 1040",
    "sg:postcode":"02180",
    "sg:province":"MA",
    "wof:name":"Pearl Massage",
    "wof:placetype":"venue"
},
  "geometry": {"coordinates":[-71.100765,42.474331],"type":"Point"}
}