{
  "type": "Feature",
  "properties": {
    "iso:country":"US",
    "sg:address":"961 Dorchester Ave",
    "sg:city":"Dorchester",
    "sg:classifiers":[
        {
            "category":"Shopping",
            "subcategory":"Shoes",
            "type":"Retail Goods"
        }
    ],
    "sg:phone":"+1 617 287 8282",
    "sg:postcode":"02125",
    "sg:province":"MA",
    "wof:name":"Sonny Cins",
    "wof:placetype":"venue"
},
  "geometry": {"coordinates":[-71.05680099999999,42.318361],"type":"Point"}
}