{
  "type": "Feature",
  "properties": {
    "iso:country":"US",
    "sg:address":"1120 W Chestnut St",
    "sg:city":"Brockton",
    "sg:classifiers":[
        {
            "category":"Home & Garden",
            "subcategory":"Building Materials",
            "type":"Retail Goods"
        }
    ],
    "sg:phone":"+1 508 580 8802",
    "sg:postcode":"02301",
    "sg:province":"MA",
    "sg:tags":[
        "roofing"
    ],
    "sg:website":"www.beaconsales.com",
    "wof:name":"Beacon Sales Co",
    "wof:placetype":"venue"
},
  "geometry": {"coordinates":[-71.066317,42.053212],"type":"Point"}
}