{
  "type": "Feature",
  "properties": {
    "addr:full": "3 Rodney French Blvd New Bedford MA 02744",
    "addr:housenumber": "3",
    "addr:postcode": "02744",
    "addr:street": "Rodney French Blvd",
    "iso:country": "US",
    "sg:address": "3 Rodney French Blvd",
    "sg:city": "New Bedford",
    "sg:classifiers": [
      {
        "category": "Education",
        "subcategory": "Library",
        "type": "Public Place"
      }
    ],
    "sg:phone": "+1 508 991 6212",
    "sg:postcode": "02744",
    "sg:province": "MA",
    "wof:name": "Howland Green Library",
    "wof:placetype": "venue"
  },
  "geometry": {"coordinates":[-70.919403,41.615624],"type":"Point"}
}
