{
  "type": "Feature",
  "properties": {
    "addr:full":"13 Osprey Dr Berkley MA 02779",
    "addr:housenumber":"13",
    "addr:postcode":"02779",
    "addr:street":"Osprey Dr",
    "iso:country":"US",
    "sg:address":"13 Osprey Dr",
    "sg:city":"Berkley",
    "sg:classifiers":[
        {
            "category":"Professional",
            "subcategory":"Computer Services",
            "type":"Services"
        }
    ],
    "sg:phone":"+1   ",
    "sg:postcode":"02779",
    "sg:province":"MA",
    "sg:tags":[
        "design",
        "system"
    ],
    "wof:name":"Osprey Software & Systems Inc",
    "wof:placetype":"venue"
},
  "geometry": {"coordinates":[-71.10841000000001,41.793561],"type":"Point"}
}