{
  "type": "Feature",
  "properties": {
    "addr:full":"4110 Mystic Valley Pkwy Medford MA 02155",
    "addr:housenumber":"4110",
    "addr:postcode":"02155",
    "addr:street":"Mystic Valley Pkwy",
    "iso:country":"US",
    "sg:address":"4110 Mystic Valley Pkwy",
    "sg:city":"Medford",
    "sg:classifiers":[
        {
            "category":"Restaurant",
            "type":"Food & Drink"
        }
    ],
    "sg:menulink":"http://www.allmenus.com/ma/medford/131890-subway/menu/",
    "sg:phone":"+1 781 396 9966",
    "sg:postcode":"02155",
    "sg:province":"MA",
    "sg:tags":[
        "american",
        "sandwich"
    ],
    "wof:name":"Subway",
    "wof:placetype":"venue"
},
  "geometry": {"coordinates":[-71.084611,42.404961],"type":"Point"}
}