{
  "type": "Feature",
  "properties": {
    "addr:full":"5 Coles Ln Plymouth MA 02360",
    "addr:housenumber":"5",
    "addr:postcode":"02360",
    "addr:street":"Coles Ln",
    "iso:country":"US",
    "sg:address":"5 Coles Ln",
    "sg:city":"Plymouth",
    "sg:classifiers":[
        {
            "category":"Banks & Credit Unions",
            "subcategory":"Investment Brokerage",
            "type":"Services"
        }
    ],
    "sg:phone":"+1   ",
    "sg:postcode":"02360",
    "sg:province":"MA",
    "sg:tags":[
        "advisory"
    ],
    "wof:name":"Brookstone Equipment Services",
    "wof:placetype":"venue"
},
  "geometry": {"coordinates":[-70.646496,41.942789],"type":"Point"}
}