{
  "type": "Feature",
  "properties": {
    "iso:country":"US",
    "sg:address":"102 Jaques St",
    "sg:city":"Somerville",
    "sg:classifiers":[
        {
            "category":"Local Transit",
            "type":"Transportation"
        }
    ],
    "sg:phone":"+1   ",
    "sg:postcode":"02145",
    "sg:province":"MA",
    "sg:tags":[
        "passenger"
    ],
    "wof:name":"Marcs Executive Limo Svs",
    "wof:placetype":"venue"
},
  "geometry": {"coordinates":[-71.093203,42.394926],"type":"Point"}
}