{
  "type": "Feature",
  "properties": {
    "iso:country":"US",
    "sg:address":"Howe Vlg",
    "sg:city":"Spencer",
    "sg:classifiers":[
        {
            "category":"Real Estate",
            "subcategory":"Real Estate Services",
            "type":"Services"
        }
    ],
    "sg:phone":"+1 508 885 3904",
    "sg:postcode":"01562",
    "sg:province":"MA",
    "sg:tags":[
        "management",
        "property"
    ],
    "wof:name":"Spencer Housing Authority",
    "wof:placetype":"venue"
},
  "geometry": {"coordinates":[-71.991798,42.241402],"type":"Point"}
}