{
  "type": "Feature",
  "properties": {
    "addr:full":"65 Pleasant St Cambridge MA 02139",
    "addr:housenumber":"65",
    "addr:postcode":"02139",
    "addr:street":"Pleasant St",
    "iso:country":"US",
    "sg:address":"65 Pleasant St",
    "sg:city":"Cambridge",
    "sg:classifiers":[
        {
            "category":"Professional",
            "subcategory":"Art Services",
            "type":"Services"
        }
    ],
    "sg:phone":"+1   ",
    "sg:postcode":"02139",
    "sg:province":"MA",
    "sg:tags":[
        "photography",
        "commercial"
    ],
    "wof:name":"Angier Roswell",
    "wof:placetype":"venue"
},
  "geometry": {"coordinates":[-71.109593,42.36301],"type":"Point"}
}