{
  "type": "Feature",
  "properties": {
    "iso:country":"US",
    "sg:address":"51 Church St",
    "sg:city":"Lenox",
    "sg:classifiers":[
        {
            "category":"Shopping",
            "subcategory":"Used Merchandise",
            "type":"Retail Goods"
        }
    ],
    "sg:phone":"+1 413 637 2733",
    "sg:postcode":"01240",
    "sg:province":"MA",
    "sg:tags":[
        "antique"
    ],
    "wof:name":"Stone's Throw Antiques",
    "wof:placetype":"venue"
},
  "geometry": {"coordinates":[-73.28364000000001,42.356403],"type":"Point"}
}