{
  "type": "Feature",
  "properties": {
    "addr:full": "51 Church St Lenox MA 01240",
    "addr:housenumber": "51",
    "addr:postcode": "01240",
    "addr:street": "Church St",
    "iso:country": "US",
    "sg:address": "51 Church St",
    "sg:city": "Lenox",
    "sg:classifiers": [
      {
        "category": "Shopping",
        "subcategory": "Used Merchandise",
        "type": "Retail Goods"
      }
    ],
    "sg:phone": "+1 413 637 2733",
    "sg:postcode": "01240",
    "sg:province": "MA",
    "sg:tags": [
      "antique"
    ],
    "wof:name": "Stone's Throw Antiques",
    "wof:placetype": "venue"
  },
  "geometry": {"coordinates":[-73.28364,42.356403],"type":"Point"}
}
