{
  "type": "Feature",
  "properties": {
    "addr:full":"262 Swansea Mall Dr # 624 Swansea MA 02777",
    "addr:housenumber":"262",
    "addr:postcode":"02777",
    "addr:street":"Swansea Mall Dr # 624",
    "iso:country":"US",
    "sg:address":"262 Swansea Mall Dr # 624",
    "sg:city":"Swansea",
    "sg:classifiers":[
        {
            "category":"Wholesale",
            "subcategory":"Apparel",
            "type":"Manufacturing & Wholesale Goods"
        },
        {
            "category":"Shopping",
            "subcategory":"Shoes",
            "type":"Retail Goods"
        }
    ],
    "sg:phone":"+1 508 673 6722",
    "sg:postcode":"02777",
    "sg:province":"MA",
    "sg:tags":[
        "shoes-wholesale",
        "store",
        "manufacturer"
    ],
    "sg:website":"http://www.shoeshow.com",
    "wof:name":"Shoe Dept 668",
    "wof:placetype":"venue"
},
  "geometry": {"coordinates":[-71.219016,41.758917],"type":"Point"}
}