{
  "type": "Feature",
  "properties": {
    "addr:full":"69 Cedar St Dedham MA 02026",
    "addr:housenumber":"69",
    "addr:postcode":"02026",
    "addr:street":"Cedar St",
    "iso:country":"US",
    "sg:address":"69 Cedar St",
    "sg:city":"Dedham",
    "sg:classifiers":[
        {
            "category":"Food & Beverages",
            "subcategory":"Groceries & Convenience Stores",
            "type":"Retail Goods"
        }
    ],
    "sg:phone":"+1 781 326 9959",
    "sg:postcode":"02026",
    "sg:province":"MA",
    "wof:name":"Dedham Convenience Store",
    "wof:placetype":"venue"
},
  "geometry": {"coordinates":[-71.155441,42.241135],"type":"Point"}
}