{
  "type": "Feature",
  "properties": {
    "addr:full": "21 Exchange St Milford MA 01757",
    "addr:housenumber": "21",
    "addr:postcode": "01757",
    "addr:street": "Exchange St",
    "iso:country": "US",
    "sg:address": "21 Exchange St",
    "sg:city": "Milford",
    "sg:classifiers": [
      {
        "category": "Professional",
        "subcategory": "Business Services",
        "type": "Services"
      }
    ],
    "sg:phone": "+1 508 478 7199",
    "sg:postcode": "01757",
    "sg:province": "MA",
    "wof:name": "Business Integrated Svc Inc",
    "wof:placetype": "venue"
  },
  "geometry": {"coordinates":[-71.520802,42.140364],"type":"Point"}
}
