{
  "type": "Feature",
  "properties": {
    "addr:full": "21 Allen Ln Ipswich MA 01938",
    "addr:housenumber": "21",
    "addr:postcode": "01938",
    "addr:street": "Allen Ln",
    "iso:country": "US",
    "sg:address": "21 Allen Ln",
    "sg:city": "Ipswich",
    "sg:classifiers": [
      {
        "category": "Professional",
        "subcategory": "Management \u0026 Consulting",
        "type": "Services"
      }
    ],
    "sg:phone": "+1 978 356 5947",
    "sg:postcode": "01938",
    "sg:province": "MA",
    "sg:tags": [
      "business"
    ],
    "wof:name": "E W Contracting Inc",
    "wof:placetype": "venue"
  },
  "geometry": {"coordinates":[-70.902936,42.689545],"type":"Point"}
}
