{
  "type": "Feature",
  "properties": {
    "addr:full":"3 Sunset Ln Spencer MA 01562",
    "addr:housenumber":"3",
    "addr:postcode":"01562",
    "addr:street":"Sunset Ln",
    "iso:country":"US",
    "sg:address":"3 Sunset Ln",
    "sg:city":"Spencer",
    "sg:classifiers":[
        {
            "category":"Utilities",
            "subcategory":"Refuse",
            "type":"Services"
        }
    ],
    "sg:phone":"+1 508 885 4499",
    "sg:postcode":"01562",
    "sg:province":"MA",
    "sg:tags":[
        "garbage",
        "collection"
    ],
    "wof:name":"Durkin & Sons Trucking Co",
    "wof:placetype":"venue"
},
  "geometry": {"coordinates":[-71.981542,42.243865],"type":"Point"}
}