{
  "type": "Feature",
  "properties": {
    "iso:country":"US",
    "sg:address":"50 Brook St",
    "sg:city":"Manchester",
    "sg:classifiers":[
        {
            "category":"Professional",
            "subcategory":"Employment Agencies",
            "type":"Services"
        }
    ],
    "sg:phone":"+1 978 526 8771",
    "sg:postcode":"01944",
    "sg:province":"MA",
    "sg:tags":[
        "consultant",
        "search",
        "executive"
    ],
    "wof:name":"Gilreath Consultantcy",
    "wof:placetype":"venue"
},
  "geometry": {"coordinates":[-70.76467599999999,42.577595],"type":"Point"}
}