{
  "type": "Feature",
  "properties": {
    "addr:full":"8 Elm St Hubbardston MA 01452",
    "addr:housenumber":"8",
    "addr:postcode":"01452",
    "addr:street":"Elm St",
    "iso:country":"US",
    "sg:address":"8 Elm St",
    "sg:city":"Hubbardston",
    "sg:classifiers":[
        {
            "category":"Education",
            "subcategory":"School",
            "type":"Public Place"
        }
    ],
    "sg:phone":"+1 978 928 4487",
    "sg:postcode":"01452",
    "sg:province":"MA",
    "wof:name":"Hubbardston Center School",
    "wof:placetype":"venue"
},
  "geometry": {"coordinates":[-72.00671,42.474115],"type":"Point"}
}