{
  "type": "Feature",
  "properties": {
    "addr:full": "34 Searles Pl Brockton MA 02301",
    "addr:housenumber": "34",
    "addr:postcode": "02301",
    "addr:street": "Searles Pl",
    "iso:country": "US",
    "sg:address": "34 Searles Pl",
    "sg:city": "Brockton",
    "sg:classifiers": [
      {
        "category": "Wholesale",
        "subcategory": "Drugs",
        "type": "Manufacturing \u0026 Wholesale Goods"
      }
    ],
    "sg:phone": "+1   ",
    "sg:postcode": "02301",
    "sg:province": "MA",
    "wof:name": "Soapy Topia",
    "wof:placetype": "venue"
  },
  "geometry": {"coordinates":[-71.028127,42.106245],"type":"Point"}
}
