{
  "type": "Feature",
  "properties": {
    "addr:full": "65 E India Row Boston MA 02110",
    "addr:housenumber": "65",
    "addr:postcode": "02110",
    "addr:street": "E India Row",
    "iso:country": "US",
    "sg:address": "65 E India Row",
    "sg:city": "Boston",
    "sg:classifiers": [
      {
        "category": "Building \u0026 Trades",
        "subcategory": "Construction",
        "type": "Services"
      }
    ],
    "sg:phone": "+1 617 722 9940",
    "sg:postcode": "02110",
    "sg:province": "MA",
    "sg:tags": [
      "interior",
      "design"
    ],
    "wof:name": "Redecorators the",
    "wof:placetype": "venue"
  },
  "geometry": {"coordinates":[-71.050201,42.358002],"type":"Point"}
}
