{
  "type": "Feature",
  "properties": {
    "addr:full":"1021 Concord Ave Belmont MA 02478",
    "addr:housenumber":"1021",
    "addr:postcode":"02478",
    "addr:street":"Concord Ave",
    "iso:country":"US",
    "sg:address":"1021 Concord Ave",
    "sg:city":"Belmont",
    "sg:classifiers":[
        {
            "category":"Building & Trades",
            "subcategory":"Construction",
            "type":"Services"
        }
    ],
    "sg:phone":"+1   ",
    "sg:postcode":"02478",
    "sg:province":"MA",
    "sg:tags":[
        "floor",
        "laying",
        "contractor"
    ],
    "wof:name":"Kershaw Floors",
    "wof:placetype":"venue"
},
  "geometry": {"coordinates":[-71.19973899999999,42.405373],"type":"Point"}
}