{
  "type": "Feature",
  "properties": {
    "addr:full":"1 Southville Rd Southborough MA 01772",
    "addr:housenumber":"1",
    "addr:postcode":"01772",
    "addr:street":"Southville Rd",
    "iso:country":"US",
    "sg:address":"1 Southville Rd",
    "sg:city":"Southborough",
    "sg:classifiers":[
        {
            "category":"Restaurant",
            "type":"Food & Drink"
        }
    ],
    "sg:phone":"+1 508 786 5665",
    "sg:postcode":"01772",
    "sg:province":"MA",
    "sg:tags":[
        "asian",
        "chinese",
        "pan"
    ],
    "wof:name":"Rose Garden",
    "wof:placetype":"venue"
},
  "geometry": {"coordinates":[-71.505859,42.266571],"type":"Point"}
}