{
  "type": "Feature",
  "properties": {
    "addr:full": "27 Harbor Loop Gloucester MA 01930",
    "addr:housenumber": "27",
    "addr:postcode": "01930",
    "addr:street": "Harbor Loop",
    "iso:country": "US",
    "sg:address": "27 Harbor Loop",
    "sg:city": "Gloucester",
    "sg:classifiers": [
      {
        "category": "Wholesale",
        "subcategory": "Seafood",
        "type": "Manufacturing \u0026 Wholesale Goods"
      }
    ],
    "sg:phone": "+1 978 281 6900",
    "sg:postcode": "01930",
    "sg:province": "MA",
    "wof:name": "Zeus Packing Inc",
    "wof:placetype": "venue"
  },
  "geometry": {"coordinates":[-70.659236,42.611599],"type":"Point"}
}
