{
  "type": "Feature",
  "properties": {
    "addr:full": "45 Depot St Duxbury MA 02332",
    "addr:housenumber": "45",
    "addr:postcode": "02332",
    "addr:street": "Depot St",
    "iso:country": "US",
    "sg:address": "45 Depot St",
    "sg:city": "Duxbury",
    "sg:classifiers": [
      {
        "category": "Home \u0026 Garden",
        "subcategory": "Carpets \u0026 Floor Coverings",
        "type": "Retail Goods"
      }
    ],
    "sg:phone": "+1 781 934 5100",
    "sg:postcode": "02332",
    "sg:province": "MA",
    "wof:name": "Oriental Express",
    "wof:placetype": "venue"
  },
  "geometry": {"coordinates":[-70.683311,42.023125],"type":"Point"}
}
