{
  "type": "Feature",
  "properties": {
    "addr:full":"50 Holyoke St Holyoke MA 01040",
    "addr:housenumber":"50",
    "addr:postcode":"01040",
    "addr:street":"Holyoke St",
    "iso:country":"US",
    "sg:address":"50 Holyoke St",
    "sg:city":"Holyoke",
    "sg:classifiers":[
        {
            "category":"Shopping",
            "subcategory":"Clothing, Apparel, & Fashions",
            "type":"Retail Goods"
        }
    ],
    "sg:phone":"+1 413 534 5265",
    "sg:postcode":"01040",
    "sg:province":"MA",
    "sg:tags":[
        "infant",
        "wear"
    ],
    "sg:website":"www.limitedtoo.com",
    "wof:name":"Limited Too",
    "wof:placetype":"venue"
},
  "geometry": {"coordinates":[-72.640165,42.172916],"type":"Point"}
}