{
  "type": "Feature",
  "properties": {
    "iso:country":"US",
    "sg:address":"158 Grove St",
    "sg:city":"Franklin",
    "sg:classifiers":[
        {
            "category":"Building & Trades",
            "subcategory":"Construction",
            "type":"Services"
        }
    ],
    "sg:phone":"+1 508 541 4488",
    "sg:postcode":"02038",
    "sg:province":"MA",
    "sg:tags":[
        "contractor",
        "paving",
        "asphalt",
        "sealcoating"
    ],
    "sg:website":"http://www.firehouseinfrared.com",
    "wof:name":"Firehouse Infrared Asphalt Repair",
    "wof:placetype":"venue"
},
  "geometry": {"coordinates":[-71.4235,42.072189],"type":"Point"}
}