{
  "type": "Feature",
  "properties": {
    "addr:full": "165 E Main St Westborough MA 01581",
    "addr:housenumber": "165",
    "addr:postcode": "01581",
    "addr:street": "E Main St",
    "iso:country": "US",
    "sg:address": "165 E Main St",
    "sg:city": "Westborough",
    "sg:classifiers": [
      {
        "category": "Professional",
        "subcategory": "Computer Services",
        "type": "Services"
      }
    ],
    "sg:phone": "+1 508 870 9993",
    "sg:postcode": "01581",
    "sg:province": "MA",
    "sg:tags": [
      "design",
      "electrical",
      "system",
      "contractor"
    ],
    "wof:name": "D H Data Com",
    "wof:placetype": "venue"
  },
  "geometry": {"coordinates":[-71.591956,42.289932],"type":"Point"}
}
