{
  "type": "Feature",
  "properties": {
    "addr:full":"15 Court Sq Ste 450 Boston MA 02108",
    "addr:housenumber":"15",
    "addr:postcode":"02108",
    "addr:street":"Court Sq Ste 450",
    "iso:country":"US",
    "sg:address":"15 Court Sq Ste 450",
    "sg:city":"Boston",
    "sg:classifiers":[
        {
            "category":"Government",
            "subcategory":"Court House",
            "type":"Public Place"
        }
    ],
    "sg:phone":"+1 800 244 3593",
    "sg:postcode":"02108",
    "sg:province":"MA",
    "sg:tags":[
        "justice"
    ],
    "wof:name":"Bedugnis & Associates Inc",
    "wof:placetype":"venue"
},
  "geometry": {"coordinates":[-71.058228,42.358817],"type":"Point"}
}