{
  "type": "Feature",
  "properties": {
    "addr:full": "86 Boston Dr Shrewsbury MA 01545",
    "addr:housenumber": "86",
    "addr:postcode": "01545",
    "addr:street": "Boston Dr",
    "iso:country": "US",
    "sg:address": "86 Boston Dr",
    "sg:city": "Shrewsbury",
    "sg:classifiers": [
      {
        "category": "Travel",
        "subcategory": "Travel Agent",
        "type": "Entertainment"
      }
    ],
    "sg:phone": "+1 508 755 8731",
    "sg:postcode": "01545",
    "sg:province": "MA",
    "sg:tags": [
      "agency",
      "bureau"
    ],
    "wof:name": "Liberty Travel",
    "wof:placetype": "venue"
  },
  "geometry": {"coordinates":[-71.694763,42.287497],"type":"Point"}
}
