{
  "type": "Feature",
  "properties": {
    "iso:country":"US",
    "sg:address":"3049 County St",
    "sg:city":"Somerset",
    "sg:classifiers":[
        {
            "category":"Restaurant",
            "type":"Food & Drink"
        }
    ],
    "sg:phone":"+1 508 730 2326",
    "sg:postcode":"02726",
    "sg:province":"MA",
    "wof:name":"Wilkie's Restaurant & Catering",
    "wof:placetype":"venue"
},
  "geometry": {"coordinates":[-71.136717,41.774086],"type":"Point"}
}