{
  "type": "Feature",
  "properties": {
    "iso:country":"US",
    "sg:address":"573 Northampton St",
    "sg:city":"Holyoke",
    "sg:classifiers":[
        {
            "category":"Professional",
            "subcategory":"Lawyer & Legal Services",
            "type":"Services"
        }
    ],
    "sg:phone":"+1 413 532 1200",
    "sg:postcode":"01040",
    "sg:province":"MA",
    "sg:tags":[
        "attorney",
        "family",
        "divorce",
        "elder",
        "real estate",
        "law",
        "bankruptcy"
    ],
    "sg:website":"http://www.jackson-torrone.com",
    "wof:name":"Jackson & Torrone Attys At Law",
    "wof:placetype":"venue"
},
  "geometry": {"coordinates":[-72.611037,42.260133],"type":"Point"}
}