{
  "type": "Feature",
  "properties": {
    "addr:full": "10 Capen Way Leominster MA 01453",
    "addr:housenumber": "10",
    "addr:postcode": "01453",
    "addr:street": "Capen Way",
    "iso:country": "US",
    "sg:address": "10 Capen Way",
    "sg:city": "Leominster",
    "sg:classifiers": [
      {
        "category": "Wholesale",
        "subcategory": "Sporting Goods",
        "type": "Manufacturing \u0026 Wholesale Goods"
      }
    ],
    "sg:phone": "+1   ",
    "sg:postcode": "01453",
    "sg:province": "MA",
    "wof:name": "Case Catchers",
    "wof:placetype": "venue"
  },
  "geometry": {"coordinates":[-71.751089,42.501684],"type":"Point"}
}
