{
  "type": "Feature",
  "properties": {
    "addr:full": "31 State St Boston MA 02109",
    "addr:housenumber": "31",
    "addr:postcode": "02109",
    "addr:street": "State St",
    "iso:country": "US",
    "sg:address": "31 State St",
    "sg:city": "Boston",
    "sg:classifiers": [
      {
        "category": "Professional",
        "subcategory": "Accounting \u0026 Tax Preparation",
        "type": "Services"
      }
    ],
    "sg:phone": "+1 617 720 0182",
    "sg:postcode": "02109",
    "sg:province": "MA",
    "sg:tags": [
      "consultant"
    ],
    "wof:name": "Marvin F Poer \u0026 Co",
    "wof:placetype": "venue"
  },
  "geometry": {"coordinates":[-71.056825,42.358875],"type":"Point"}
}
