{
  "type": "Feature",
  "properties": {
    "iso:country":"US",
    "sg:address":"31 Tremont St",
    "sg:city":"Cambridge",
    "sg:classifiers":[
        {
            "category":"Building & Trades",
            "subcategory":"Construction",
            "type":"Services"
        }
    ],
    "sg:phone":"+1   ",
    "sg:postcode":"02139",
    "sg:province":"MA",
    "sg:tags":[
        "hanging",
        "contractor"
    ],
    "wof:name":"Mannis Painting Co",
    "wof:placetype":"venue"
},
  "geometry": {"coordinates":[-71.09996099999999,42.368902],"type":"Point"}
}