{
  "type": "Feature",
  "properties": {
    "iso:country":"US",
    "sg:address":"8 Peabody Ter",
    "sg:city":"Cambridge",
    "sg:classifiers":[
        {
            "category":"Professional",
            "subcategory":"Secretarial Services",
            "type":"Services"
        }
    ],
    "sg:phone":"+1   ",
    "sg:postcode":"02138",
    "sg:province":"MA",
    "sg:tags":[
        "editing",
        "presentation",
        "document",
        "power",
        "point"
    ],
    "wof:name":"Vivek Chadaga",
    "wof:placetype":"venue"
},
  "geometry": {"coordinates":[-71.114684,42.366563],"type":"Point"}
}