{
  "type": "Feature",
  "properties": {
    "addr:full": "25 Montvale Ave Woburn MA 01801",
    "addr:housenumber": "25",
    "addr:postcode": "01801",
    "addr:street": "Montvale Ave",
    "iso:country": "US",
    "ovtr:label": "The Peterson School, 25 Montvale Ave Woburn MA US",
    "ovtr:similarity": 3.4727859497070312,
    "sg:address": "25 Montvale Ave",
    "sg:city": "Woburn",
    "sg:classifiers": [
      {
        "category": "Education",
        "subcategory": "Vocational School",
        "type": "Public Place"
      }
    ],
    "sg:phone": "+1 781 938 5656",
    "sg:postcode": "01801",
    "sg:province": "MA",
    "sg:tags": [
      "technical",
      "adult",
      "trade"
    ],
    "sg:website": "www.petersonschool.com",
    "wof:name": "Peterson School the",
    "wof:placetype": "venue"
  },
  "geometry": {"coordinates":[-71.149803,42.479401],"type":"Point"}
}
