{
  "type": "Feature",
  "properties": {
    "iso:country":"US",
    "sg:address":"25 Montvale Ave",
    "sg:city":"Woburn",
    "sg:classifiers":[
        {
            "category":"Education",
            "subcategory":"Vocational School",
            "type":"Public Place"
        }
    ],
    "sg:phone":"+1 781 938 5656",
    "sg:postcode":"01801",
    "sg:province":"MA",
    "sg:tags":[
        "technical",
        "adult",
        "trade"
    ],
    "sg:website":"www.petersonschool.com",
    "wof:name":"Peterson School the",
    "wof:placetype":"venue"
},
  "geometry": {"coordinates":[-71.14980300000001,42.479401],"type":"Point"}
}