{
  "type": "Feature",
  "properties": {
    "addr:full":"44 Bodick Rd Hyannis MA 02601",
    "addr:housenumber":"44",
    "addr:postcode":"02601",
    "addr:street":"Bodick Rd",
    "iso:country":"US",
    "sg:address":"44 Bodick Rd",
    "sg:city":"Hyannis",
    "sg:classifiers":[
        {
            "category":"Wholesale",
            "subcategory":"Dairy",
            "type":"Manufacturing & Wholesale Goods"
        }
    ],
    "sg:phone":"+1 508 771 4700",
    "sg:postcode":"02601",
    "sg:province":"MA",
    "sg:tags":[
        "product"
    ],
    "wof:name":"Cape Dairy Products Inc",
    "wof:placetype":"venue"
},
  "geometry": {"coordinates":[-70.270922,41.663951],"type":"Point"}
}