{
  "type": "Feature",
  "properties": {
    "iso:country":"US",
    "sg:address":"95 Helvetia St",
    "sg:city":"Tewksbury",
    "sg:classifiers":[
        {
            "category":"Building & Trades",
            "subcategory":"Plumbing",
            "type":"Services"
        }
    ],
    "sg:phone":"+1 978 851 9084",
    "sg:postcode":"01876",
    "sg:province":"MA",
    "sg:tags":[
        "plumbing",
        "contractor"
    ],
    "wof:name":"Tewksbury Sewer Svc",
    "wof:placetype":"venue"
},
  "geometry": {"coordinates":[-71.231942,42.607971],"type":"Point"}
}