{
  "type": "Feature",
  "properties": {
    "addr:full": "264 Cordaville Rd Southborough MA 01772",
    "addr:housenumber": "264",
    "addr:postcode": "01772",
    "addr:street": "Cordaville Rd",
    "iso:country": "US",
    "sg:address": "264 Cordaville Rd",
    "sg:city": "Southborough",
    "sg:classifiers": [
      {
        "category": "Autos \u0026 Motor Vehicles",
        "subcategory": "Fuel \u0026 Gas Station",
        "type": "Retail Goods"
      }
    ],
    "sg:phone": "+1 508 481 9070",
    "sg:postcode": "01772",
    "sg:province": "MA",
    "sg:tags": [
      "oil"
    ],
    "wof:name": "Custom Automotive",
    "wof:placetype": "venue"
  },
  "geometry": {"coordinates":[-71.523096,42.271992],"type":"Point"}
}
