{
  "type": "Feature",
  "properties": {
    "iso:country":"US",
    "sg:address":"195 Main St",
    "sg:city":"Great Barrington",
    "sg:classifiers":[
        {
            "category":"Communications",
            "subcategory":"Radio Station",
            "type":"Services"
        }
    ],
    "sg:phone":"+1 413 644 9797",
    "sg:postcode":"01230",
    "sg:province":"MA",
    "sg:tags":[
        "company",
        "broadcasting"
    ],
    "wof:name":"WBCRLP 97.7 FM",
    "wof:placetype":"venue"
},
  "geometry": {"coordinates":[-73.36113899999999,42.197487],"type":"Point"}
}