{
  "type": "Feature",
  "properties": {
    "addr:full": "195 Main St Great Barrington MA 01230",
    "addr:housenumber": "195",
    "addr:postcode": "01230",
    "addr:street": "Main St",
    "iso:country": "US",
    "sg:address": "195 Main St",
    "sg:city": "Great Barrington",
    "sg:classifiers": [
      {
        "category": "Communications",
        "subcategory": "Radio Station",
        "type": "Services"
      }
    ],
    "sg:phone": "+1 413 644 9797",
    "sg:postcode": "01230",
    "sg:province": "MA",
    "sg:tags": [
      "company",
      "broadcasting"
    ],
    "wof:name": "WBCRLP 97.7 FM",
    "wof:placetype": "venue"
  },
  "geometry": {"coordinates":[-73.361139,42.197487],"type":"Point"}
}
