{
  "type": "Feature",
  "properties": {
    "addr:full": "300 Oak St Exd Pembroke MA 02359",
    "addr:housenumber": "300",
    "addr:postcode": "02359",
    "addr:street": "Oak St Exd",
    "iso:country": "US",
    "sg:address": "300 Oak St Exd",
    "sg:city": "Pembroke",
    "sg:classifiers": [
      {
        "category": "Mining \u0026 Drilling",
        "type": "Manufacturing \u0026 Wholesale Goods"
      }
    ],
    "sg:phone": "+1 781 826 1522",
    "sg:postcode": "02359",
    "sg:province": "MA",
    "sg:tags": [
      "stone"
    ],
    "wof:name": "Globe Granite",
    "wof:placetype": "venue"
  },
  "geometry": {"coordinates":[-70.765322,42.105293],"type":"Point"}
}
