{
  "type": "Feature",
  "properties": {
    "addr:full":"100 Independence Way Danvers MA 01923",
    "addr:housenumber":"100",
    "addr:postcode":"01923",
    "addr:street":"Independence Way",
    "iso:country":"US",
    "sg:address":"100 Independence Way",
    "sg:city":"Danvers",
    "sg:classifiers":[
        {
            "category":"Retail",
            "subcategory":"Repair Shop",
            "type":"Services"
        }
    ],
    "sg:phone":"+1 978 646 8884",
    "sg:postcode":"01923",
    "sg:province":"MA",
    "wof:name":"Barats Jewelry Repair",
    "wof:placetype":"venue"
},
  "geometry": {"coordinates":[-70.938069,42.550814],"type":"Point"}
}