{
  "type": "Feature",
  "properties": {
    "iso:country":"US",
    "sg:address":"3 Elm St",
    "sg:city":"South Deerfield",
    "sg:classifiers":[
        {
            "category":"Restaurant",
            "type":"Food & Drink"
        }
    ],
    "sg:phone":"+1 413 665 8195",
    "sg:postcode":"01373",
    "sg:province":"MA",
    "wof:name":"Holiday Pizza",
    "wof:placetype":"venue"
},
  "geometry": {"coordinates":[-72.610315,42.477487],"type":"Point"}
}