{
  "type": "Feature",
  "properties": {
    "addr:full": "3 Elm St South Deerfield MA 01373",
    "addr:housenumber": "3",
    "addr:postcode": "01373",
    "addr:street": "Elm St",
    "iso:country": "US",
    "ovtr:label": "Holiday Pizza, 3 Elm St South Deerfield MA US",
    "ovtr:similarity": 2.1737499237060547,
    "sg:address": "3 Elm St",
    "sg:city": "South Deerfield",
    "sg:classifiers": [
      {
        "category": "Restaurant",
        "type": "Food \u0026 Drink"
      }
    ],
    "sg:phone": "+1 413 665 8195",
    "sg:postcode": "01373",
    "sg:province": "MA",
    "wof:name": "Holiday Pizza",
    "wof:placetype": "venue"
  },
  "geometry": {"coordinates":[-72.610315,42.477487],"type":"Point"}
}
