{
  "type": "Feature",
  "properties": {
    "iso:country":"US",
    "sg:address":"623 Main St Ste 27",
    "sg:city":"Woburn",
    "sg:classifiers":[
        {
            "category":"Real Estate",
            "subcategory":"Real Estate Services",
            "type":"Services"
        }
    ],
    "sg:phone":"+1 781 933 0107",
    "sg:postcode":"01801",
    "sg:province":"MA",
    "sg:tags":[
        "home",
        "inspector"
    ],
    "wof:name":"Vista Home Inspections - CLOSED",
    "wof:placetype":"venue"
},
  "geometry": {"coordinates":[-71.152298,42.4883],"type":"Point"}
}