{
  "type": "Feature",
  "properties": {
    "addr:full": "44 Melendy Ave Watertown MA 02472",
    "addr:housenumber": "44",
    "addr:postcode": "02472",
    "addr:street": "Melendy Ave",
    "iso:country": "US",
    "sg:address": "44 Melendy Ave",
    "sg:city": "Watertown",
    "sg:classifiers": [
      {
        "category": "Professional",
        "type": "Services"
      }
    ],
    "sg:phone": "+1   ",
    "sg:postcode": "02472",
    "sg:province": "MA",
    "wof:name": "Breen Corporation",
    "wof:placetype": "venue"
  },
  "geometry": {"coordinates":[-71.159281,42.369713],"type":"Point"}
}
