{
  "type": "Feature",
  "properties": {
    "iso:country":"US",
    "sg:address":"44 Melendy Ave",
    "sg:city":"Watertown",
    "sg:classifiers":[
        {
            "category":"Professional",
            "type":"Services"
        }
    ],
    "sg:phone":"+1   ",
    "sg:postcode":"02472",
    "sg:province":"MA",
    "wof:name":"Breen Corporation",
    "wof:placetype":"venue"
},
  "geometry": {"coordinates":[-71.15928099999999,42.369713],"type":"Point"}
}