{
  "type": "Feature",
  "properties": {
    "addr:full":"442 King St Littleton MA 01460",
    "addr:housenumber":"442",
    "addr:postcode":"01460",
    "addr:street":"King St",
    "iso:country":"US",
    "sg:address":"442 King St",
    "sg:city":"Littleton",
    "sg:classifiers":[
        {
            "category":"Social Services",
            "type":"Services"
        }
    ],
    "sg:phone":"+1 978 952 0151",
    "sg:postcode":"01460",
    "sg:province":"MA",
    "sg:tags":[
        "worker"
    ],
    "wof:name":"Gabouri Michele Licsw",
    "wof:placetype":"venue"
},
  "geometry": {"coordinates":[-71.475719,42.545323],"type":"Point"}
}