{
  "type": "Feature",
  "properties": {
    "iso:country":"US",
    "sg:address":"424 Long Pond Rd",
    "sg:city":"Plymouth",
    "sg:classifiers":[
        {
            "category":"Building & Trades",
            "subcategory":"Construction",
            "type":"Services"
        }
    ],
    "sg:phone":"+1 508 830 6788",
    "sg:postcode":"02360",
    "sg:province":"MA",
    "sg:tags":[
        "general",
        "contractor"
    ],
    "wof:name":"International Golf Constr",
    "wof:placetype":"venue"
},
  "geometry": {"coordinates":[-70.624044,41.88419],"type":"Point"}
}