{
  "type": "Feature",
  "properties": {
    "addr:full": "424 Long Pond Rd Plymouth MA 02360",
    "addr:housenumber": "424",
    "addr:postcode": "02360",
    "addr:street": "Long Pond Rd",
    "iso:country": "US",
    "sg:address": "424 Long Pond Rd",
    "sg:city": "Plymouth",
    "sg:classifiers": [
      {
        "category": "Building \u0026 Trades",
        "subcategory": "Construction",
        "type": "Services"
      }
    ],
    "sg:phone": "+1 508 830 6788",
    "sg:postcode": "02360",
    "sg:province": "MA",
    "sg:tags": [
      "general",
      "contractor"
    ],
    "wof:name": "International Golf Constr",
    "wof:placetype": "venue"
  },
  "geometry": {"coordinates":[-70.624044,41.88419],"type":"Point"}
}
