{
  "type": "Feature",
  "properties": {
    "iso:country":"US",
    "sg:address":"152 Central St",
    "sg:city":"Auburn",
    "sg:classifiers":[
        {
            "category":"Arts & Performance",
            "subcategory":"Theater",
            "type":"Entertainment"
        }
    ],
    "sg:phone":"+1 508 248 9044",
    "sg:postcode":"01501",
    "sg:province":"MA",
    "sg:tags":[
        "live",
        "music"
    ],
    "wof:name":"Greg Vangel Wedding DJ",
    "wof:placetype":"venue"
},
  "geometry": {"coordinates":[-71.83873,42.192289],"type":"Point"}
}