{
  "type": "Feature",
  "properties": {
    "addr:full":"15 Paul Gore St Jamaica Plain MA 02130",
    "addr:housenumber":"15",
    "addr:postcode":"02130",
    "addr:street":"Paul Gore St",
    "iso:country":"US",
    "sg:address":"15 Paul Gore St",
    "sg:city":"Jamaica Plain",
    "sg:classifiers":[
        {
            "category":"Professional",
            "subcategory":"Management & Consulting",
            "type":"Services"
        }
    ],
    "sg:phone":"+1   ",
    "sg:postcode":"02130",
    "sg:province":"MA",
    "wof:name":"Cec International Inc",
    "wof:placetype":"venue"
},
  "geometry": {"coordinates":[-71.10929899999999,42.320145],"type":"Point"}
}