{
  "type": "Feature",
  "properties": {
    "addr:full": "179 Littleton Rd Westford MA 01886",
    "addr:housenumber": "179",
    "addr:postcode": "01886",
    "addr:street": "Littleton Rd",
    "iso:country": "US",
    "sg:address": "179 Littleton Rd",
    "sg:city": "Westford",
    "sg:classifiers": [
      {
        "category": "Food \u0026 Beverages",
        "subcategory": "Groceries \u0026 Convenience Stores",
        "type": "Retail Goods"
      }
    ],
    "sg:phone": "+1 978 692 0969",
    "sg:postcode": "01886",
    "sg:province": "MA",
    "sg:website": "www.exxon.com",
    "wof:name": "Westford Exxon",
    "wof:placetype": "venue"
  },
  "geometry": {"coordinates":[-71.418198,42.569801],"type":"Point"}
}
