{
  "type": "Feature",
  "properties": {
    "addr:full": "900 Broadway Saugus MA 01906",
    "addr:housenumber": "900",
    "addr:postcode": "01906",
    "addr:street": "Broadway",
    "iso:country": "US",
    "sg:address": "900 Broadway",
    "sg:city": "Saugus",
    "sg:classifiers": [
      {
        "category": "Bars \u0026 Pubs",
        "type": "Food \u0026 Drink"
      },
      {
        "category": "Restaurant",
        "type": "Food \u0026 Drink"
      },
      {
        "category": "Bars \u0026 Pubs",
        "subcategory": "Lounge",
        "type": "Food \u0026 Drink"
      }
    ],
    "sg:phone": "+1 781 231 2221",
    "sg:postcode": "01906",
    "sg:province": "MA",
    "sg:tags": [
      "grill",
      "latin",
      "cocktail",
      "house",
      "vegetarian",
      "american",
      "barbecue",
      "steak"
    ],
    "sg:website": "http://www.MidwestGrillRestaurant.com",
    "wof:name": "Midwest Grill",
    "wof:placetype": "venue"
  },
  "geometry": {"coordinates":[-71.025398,42.468011],"type":"Point"}
}
