{
  "type": "Feature",
  "properties": {
    "addr:full":"578 Tremont St Boston MA 02118",
    "addr:housenumber":"578",
    "addr:postcode":"02118",
    "addr:street":"Tremont St",
    "iso:country":"US",
    "sg:address":"578 Tremont St",
    "sg:city":"Boston",
    "sg:classifiers":[
        {
            "category":"Restaurant",
            "type":"Food & Drink"
        }
    ],
    "sg:phone":"+1 617 236 5658",
    "sg:postcode":"02118",
    "sg:province":"MA",
    "wof:name":"Nightingale",
    "wof:placetype":"venue"
},
  "geometry": {"coordinates":[-71.07245399999999,42.343508],"type":"Point"}
}