{
  "type": "Feature",
  "properties": {
    "iso:country":"US",
    "sg:address":"27 Mystic View Rd",
    "sg:city":"Everett",
    "sg:classifiers":[
        {
            "category":"Restaurant",
            "type":"Food & Drink"
        },
        {
            "category":"Bakery",
            "type":"Food & Drink"
        }
    ],
    "sg:menulink":"http://www.allmenus.com/ma/everett/103083-panera-bread/menu/",
    "sg:phone":"+1 617 387 8135",
    "sg:postcode":"02149",
    "sg:province":"MA",
    "sg:tags":[
        "american",
        "sandwich",
        "bakery",
        "pastry"
    ],
    "wof:name":"Panera Bread",
    "wof:placetype":"venue"
},
  "geometry": {"coordinates":[-71.07147999999999,42.400477],"type":"Point"}
}