{
  "type": "Feature",
  "properties": {
    "addr:full": "27 Mystic View Rd Everett MA 02149",
    "addr:housenumber": "27",
    "addr:postcode": "02149",
    "addr:street": "Mystic View Rd",
    "iso:country": "US",
    "ovtr:label": "Panera Bread, 25 Mystic View Rd Everett MA US",
    "ovtr:similarity": 3.253973960876465,
    "sg:address": "27 Mystic View Rd",
    "sg:city": "Everett",
    "sg:classifiers": [
      {
        "category": "Restaurant",
        "type": "Food \u0026 Drink"
      },
      {
        "category": "Bakery",
        "type": "Food \u0026 Drink"
      }
    ],
    "sg:menulink": "http://www.allmenus.com/ma/everett/103083-panera-bread/menu/",
    "sg:phone": "+1 617 387 8135",
    "sg:postcode": "02149",
    "sg:province": "MA",
    "sg:tags": [
      "american",
      "sandwich",
      "bakery",
      "pastry"
    ],
    "wof:name": "Panera Bread",
    "wof:placetype": "venue"
  },
  "geometry": {"coordinates":[-71.07148,42.400477],"type":"Point"}
}
