{
  "type": "Feature",
  "properties": {
    "addr:full": "185 Libbey Industrial Pkwy Weymouth MA 02189",
    "addr:housenumber": "185",
    "addr:postcode": "02189",
    "addr:street": "Libbey Industrial Pkwy",
    "iso:country": "US",
    "sg:address": "185 Libbey Industrial Pkwy",
    "sg:city": "Weymouth",
    "sg:classifiers": [
      {
        "category": "Manufacturing",
        "subcategory": "Leather Goods",
        "type": "Manufacturing \u0026 Wholesale Goods"
      }
    ],
    "sg:phone": "+1 781 331 9004",
    "sg:postcode": "02189",
    "sg:province": "MA",
    "sg:tags": [
      "shoes",
      "supply"
    ],
    "sg:website": "www.faytex.com",
    "wof:name": "Faytex Corp",
    "wof:placetype": "venue"
  },
  "geometry": {"coordinates":[-70.941223,42.19152],"type":"Point"}
}
