{
  "type": "Feature",
  "properties": {
    "addr:full": "950 Kings Hwy New Bedford MA 02745",
    "addr:housenumber": "950",
    "addr:postcode": "02745",
    "addr:street": "Kings Hwy",
    "iso:country": "US",
    "sg:address": "950 Kings Hwy",
    "sg:city": "New Bedford",
    "sg:classifiers": [
      {
        "category": "Restaurant",
        "type": "Food \u0026 Drink"
      }
    ],
    "sg:phone": "+1 508 998 3313",
    "sg:postcode": "02745",
    "sg:province": "MA",
    "wof:name": "Papa Gino's",
    "wof:placetype": "venue"
  },
  "geometry": {"coordinates":[-70.943636,41.676282],"type":"Point"}
}
