{
  "type": "Feature",
  "properties": {
    "addr:full": "215 Hayden Rowe St Hopkinton MA 01748",
    "addr:housenumber": "215",
    "addr:postcode": "01748",
    "addr:street": "Hayden Rowe St",
    "iso:country": "US",
    "sg:address": "215 Hayden Rowe St",
    "sg:city": "Hopkinton",
    "sg:classifiers": [
      {
        "category": "Building \u0026 Trades",
        "subcategory": "Landscaping Services",
        "type": "Services"
      }
    ],
    "sg:phone": "+1 508 435 4016",
    "sg:postcode": "01748",
    "sg:province": "MA",
    "sg:tags": [
      "landscape",
      "contractor"
    ],
    "sg:website": "www.rlstevenslandscape.com",
    "wof:name": "R L Stevens Construction Inc",
    "wof:placetype": "venue"
  },
  "geometry": {"coordinates":[-71.507944,42.200521],"type":"Point"}
}
