{
  "type": "Feature",
  "properties": {
    "iso:country":"US",
    "sg:address":"63 Longfellow Rd",
    "sg:city":"Wellesley",
    "sg:classifiers":[
        {
            "category":"Health Services",
            "subcategory":"Clinic",
            "type":"Services"
        }
    ],
    "sg:phone":"+1 781 522 0547",
    "sg:postcode":"02481",
    "sg:province":"MA",
    "sg:tags":[
        "organization",
        "medical",
        "surgical"
    ],
    "wof:name":"Simon Medical Svc Inc",
    "wof:placetype":"venue"
},
  "geometry": {"coordinates":[-71.25948,42.31422],"type":"Point"}
}