{
  "type": "Feature",
  "properties": {
    "iso:country":"US",
    "sg:address":"98 N Washington St",
    "sg:city":"Boston",
    "sg:classifiers":[
        {
            "category":"Professional",
            "subcategory":"Lawyer & Legal Services",
            "type":"Services"
        }
    ],
    "sg:phone":"+1 617 523 0200",
    "sg:postcode":"02114",
    "sg:province":"MA",
    "sg:tags":[
        "attorney",
        "law",
        "business",
        "bankruptcy"
    ],
    "wof:name":"Donald H Alder",
    "wof:placetype":"venue"
},
  "geometry": {"coordinates":[-71.05837200000001,42.365528],"type":"Point"}
}