{
  "type": "Feature",
  "properties": {
    "addr:full": "200 Smith St Waltham MA 02451",
    "addr:housenumber": "200",
    "addr:postcode": "02451",
    "addr:street": "Smith St",
    "iso:country": "US",
    "sg:address": "200 Smith St",
    "sg:city": "Waltham",
    "sg:classifiers": [
      {
        "category": "Organizations",
        "subcategory": "Labor Organization",
        "type": "Services"
      }
    ],
    "sg:phone": "+1 781 684 9215",
    "sg:postcode": "02451",
    "sg:province": "MA",
    "wof:name": "Mail Handlers Union-New Englnd",
    "wof:placetype": "venue"
  },
  "geometry": {"coordinates":[-71.252953,42.41609],"type":"Point"}
}
