{
  "type": "Feature",
  "properties": {
    "iso:country":"US",
    "sg:address":"200 Smith St",
    "sg:city":"Waltham",
    "sg:classifiers":[
        {
            "category":"Organizations",
            "subcategory":"Labor Organization",
            "type":"Services"
        }
    ],
    "sg:phone":"+1 781 684 9215",
    "sg:postcode":"02451",
    "sg:province":"MA",
    "wof:name":"Mail Handlers Union-New Englnd",
    "wof:placetype":"venue"
},
  "geometry": {"coordinates":[-71.25295300000001,42.41609],"type":"Point"}
}