{
  "type": "Feature",
  "properties": {
    "iso:country":"US",
    "sg:address":"156 Rodman St",
    "sg:city":"Fall River",
    "sg:classifiers":[
        {
            "category":"Education",
            "subcategory":"Special Training",
            "type":"Public Place"
        }
    ],
    "sg:phone":"+1 508 646 0459",
    "sg:postcode":"02721",
    "sg:province":"MA",
    "sg:tags":[
        "instruction",
        "driving"
    ],
    "wof:name":"J & A Driving School",
    "wof:placetype":"venue"
},
  "geometry": {"coordinates":[-71.15619700000001,41.697459],"type":"Point"}
}