{
  "type": "Feature",
  "properties": {
    "addr:full": "2 Park St Attleboro MA 02703",
    "addr:housenumber": "2",
    "addr:postcode": "02703",
    "addr:street": "Park St",
    "iso:country": "US",
    "sg:address": "2 Park St",
    "sg:city": "Attleboro",
    "sg:classifiers": [
      {
        "category": "Retail",
        "subcategory": "Portrait Studio",
        "type": "Services"
      },
      {
        "category": "Professional",
        "subcategory": "Art Services",
        "type": "Services"
      }
    ],
    "sg:phone": "+1 508 223 3021",
    "sg:postcode": "02703",
    "sg:province": "MA",
    "sg:tags": [
      "photographer",
      "photography",
      "store"
    ],
    "wof:name": "Miller Laurie J Custom Framing",
    "wof:placetype": "venue"
  },
  "geometry": {"coordinates":[-71.283997,41.944401],"type":"Point"}
}
