{
  "type": "Feature",
  "properties": {
    "addr:full": "54 Canal St Boston MA 02114",
    "addr:housenumber": "54",
    "addr:postcode": "02114",
    "addr:street": "Canal St",
    "iso:country": "US",
    "sg:address": "54 Canal St",
    "sg:city": "Boston",
    "sg:classifiers": [
      {
        "category": "Professional",
        "subcategory": "Business Services",
        "type": "Services"
      }
    ],
    "sg:phone": "+1   ",
    "sg:postcode": "02114",
    "sg:province": "MA",
    "wof:name": "Ghk Associates",
    "wof:placetype": "venue"
  },
  "geometry": {"coordinates":[-71.059947,42.364324],"type":"Point"}
}
