{
  "type": "Feature",
  "properties": {
    "iso:country":"US",
    "sg:address":"16 Central Sq",
    "sg:city":"Bridgewater",
    "sg:classifiers":[
        {
            "category":"Professional",
            "subcategory":"Computer Services",
            "type":"Services"
        }
    ],
    "sg:phone":"+1 508 279 6562",
    "sg:postcode":"02324",
    "sg:province":"MA",
    "sg:tags":[
        "website",
        "design"
    ],
    "sg:website":"www.webject.com",
    "wof:name":"Webject Systems Inc",
    "wof:placetype":"venue"
},
  "geometry": {"coordinates":[-70.97629499999999,41.988979],"type":"Point"}
}