{
  "type": "Feature",
  "properties": {
    "addr:full": "248 Washington St Fall River MA 02721",
    "addr:housenumber": "248",
    "addr:postcode": "02721",
    "addr:street": "Washington St",
    "iso:country": "US",
    "sg:address": "248 Washington St",
    "sg:city": "Fall River",
    "sg:classifiers": [
      {
        "category": "Personal",
        "subcategory": "Beauty Salon",
        "type": "Services"
      }
    ],
    "sg:phone": "+1 508 679 0677",
    "sg:postcode": "02721",
    "sg:province": "MA",
    "wof:name": "Julio's Hair Stylists",
    "wof:placetype": "venue"
  },
  "geometry": {"coordinates":[-71.1607,41.698753],"type":"Point"}
}
