{
  "type": "Feature",
  "properties": {
    "iso:country":"US",
    "sg:address":"248 Washington St",
    "sg:city":"Fall River",
    "sg:classifiers":[
        {
            "category":"Personal",
            "subcategory":"Beauty Salon",
            "type":"Services"
        }
    ],
    "sg:phone":"+1 508 679 0677",
    "sg:postcode":"02721",
    "sg:province":"MA",
    "wof:name":"Julio's Hair Stylists",
    "wof:placetype":"venue"
},
  "geometry": {"coordinates":[-71.16070000000001,41.698753],"type":"Point"}
}