{
  "type": "Feature",
  "properties": {
    "iso:country":"US",
    "sg:address":"4 Brooks Rd",
    "sg:city":"Monument Beach",
    "sg:classifiers":[
        {
            "category":"Professional",
            "subcategory":"Accounting & Tax Preparation",
            "type":"Services"
        }
    ],
    "sg:phone":"+1 508 759 4110",
    "sg:postcode":"02553",
    "sg:province":"MA",
    "sg:tags":[
        "accountant"
    ],
    "wof:name":"Marzelli Linda CPA - CLOSED",
    "wof:placetype":"venue"
},
  "geometry": {"coordinates":[-70.617897,41.698002],"type":"Point"}
}