{
  "type": "Feature",
  "properties": {
    "iso:country":"US",
    "sg:address":"2 Kemble St",
    "sg:city":"Lenox",
    "sg:classifiers":[
        {
            "category":"Travel",
            "subcategory":"Hotels & Motels",
            "type":"Entertainment"
        }
    ],
    "sg:phone":"+1 413 637 4113",
    "sg:postcode":"01240",
    "sg:province":"MA",
    "sg:tags":[
        "breakfast",
        "accommodation",
        "bed"
    ],
    "sg:website":"www.kembleinn.com",
    "wof:name":"Kemble Inn",
    "wof:placetype":"venue"
},
  "geometry": {"coordinates":[-73.28234999999999,42.355367],"type":"Point"}
}