{
  "type": "Feature",
  "properties": {
    "iso:country":"US",
    "sg:address":"186 W Boylston St",
    "sg:city":"West Boylston",
    "sg:classifiers":[
        {
            "category":"Education",
            "subcategory":"Special Training",
            "type":"Public Place"
        }
    ],
    "sg:phone":"+1 508 835 2333",
    "sg:postcode":"01583",
    "sg:province":"MA",
    "sg:tags":[
        "instruction",
        "driving"
    ],
    "wof:name":"Central Mass Safety Auto Schl",
    "wof:placetype":"venue"
},
  "geometry": {"coordinates":[-71.785389,42.350407],"type":"Point"}
}