{
  "type": "Feature",
  "properties": {
    "addr:full":"195 Cranberry Hwy Orleans MA 02653",
    "addr:housenumber":"195",
    "addr:postcode":"02653",
    "addr:street":"Cranberry Hwy",
    "iso:country":"US",
    "sg:address":"195 Cranberry Hwy",
    "sg:city":"Orleans",
    "sg:classifiers":[
        {
            "category":"Personal",
            "type":"Services"
        }
    ],
    "sg:phone":"+1 508 240 1139",
    "sg:postcode":"02653",
    "sg:province":"MA",
    "sg:tags":[
        "therapist",
        "massage"
    ],
    "wof:name":"Transitions",
    "wof:placetype":"venue"
},
  "geometry": {"coordinates":[-69.99937,41.78062],"type":"Point"}
}