{
  "type": "Feature",
  "properties": {
    "addr:full":"100 Broadway Rd Dracut MA 01826",
    "addr:housenumber":"100",
    "addr:postcode":"01826",
    "addr:street":"Broadway Rd",
    "iso:country":"US",
    "sg:address":"100 Broadway Rd",
    "sg:city":"Dracut",
    "sg:classifiers":[
        {
            "category":"Banks & Credit Unions",
            "subcategory":"Bank",
            "type":"Services"
        }
    ],
    "sg:phone":"+1 978 275 6003",
    "sg:postcode":"01826",
    "sg:province":"MA",
    "wof:name":"Washington Savings Bank",
    "wof:placetype":"venue"
},
  "geometry": {"coordinates":[-71.29473900000001,42.674384],"type":"Point"}
}