{
  "type": "Feature",
  "properties": {
    "addr:full": "100 Broadway Rd Dracut MA 01826",
    "addr:housenumber": "100",
    "addr:postcode": "01826",
    "addr:street": "Broadway Rd",
    "iso:country": "US",
    "ovtr:label": "Washington Savings Bank, 100 Broadway Rd Dracut MA US",
    "ovtr:similarity": 2.2813029289245605,
    "sg:address": "100 Broadway Rd",
    "sg:city": "Dracut",
    "sg:classifiers": [
      {
        "category": "Banks \u0026 Credit Unions",
        "subcategory": "Bank",
        "type": "Services"
      }
    ],
    "sg:phone": "+1 978 275 6003",
    "sg:postcode": "01826",
    "sg:province": "MA",
    "wof:name": "Washington Savings Bank",
    "wof:placetype": "venue"
  },
  "geometry": {"coordinates":[-71.294739,42.674384],"type":"Point"}
}
