{
  "type": "Feature",
  "properties": {
    "addr:full": "11 Tracy Cir Amherst MA 01002",
    "addr:housenumber": "11",
    "addr:postcode": "01002",
    "addr:street": "Tracy Cir",
    "iso:country": "US",
    "sg:address": "11 Tracy Cir",
    "sg:city": "Amherst",
    "sg:classifiers": [
      {
        "category": "Professional",
        "subcategory": "Management \u0026 Consulting",
        "type": "Services"
      }
    ],
    "sg:phone": "+1 413 582 1480",
    "sg:postcode": "01002",
    "sg:province": "MA",
    "sg:tags": [
      "consultant"
    ],
    "wof:name": "Amherst Management Cnsltng Grp",
    "wof:placetype": "venue"
  },
  "geometry": {"coordinates":[-72.523641,42.337801],"type":"Point"}
}
