{
  "type": "Feature",
  "properties": {
    "addr:full":"691 Washington St Attleboro MA 02703",
    "addr:housenumber":"691",
    "addr:postcode":"02703",
    "addr:street":"Washington St",
    "iso:country":"US",
    "sg:address":"691 Washington St",
    "sg:city":"Attleboro",
    "sg:classifiers":[
        {
            "category":"Manufacturing",
            "subcategory":"Lumber",
            "type":"Manufacturing & Wholesale Goods"
        }
    ],
    "sg:phone":"+1 508 399 6280",
    "sg:postcode":"02703",
    "sg:province":"MA",
    "wof:name":"Tradewood Lumber Corp",
    "wof:placetype":"venue"
},
  "geometry": {"coordinates":[-71.36405999999999,41.90858],"type":"Point"}
}