{
  "type": "Feature",
  "properties": {
    "addr:full": "139 Newbury St Framingham MA 01701",
    "addr:housenumber": "139",
    "addr:postcode": "01701",
    "addr:street": "Newbury St",
    "iso:country": "US",
    "sg:address": "139 Newbury St",
    "sg:city": "Framingham",
    "sg:classifiers": [
      {
        "category": "Manufacturing",
        "subcategory": "Printing",
        "type": "Manufacturing \u0026 Wholesale Goods"
      }
    ],
    "sg:phone": "+1 508 270 8484",
    "sg:postcode": "01701",
    "sg:province": "MA",
    "sg:tags": [
      "printer"
    ],
    "wof:name": "Freedom Digital Printing LLC",
    "wof:placetype": "venue"
  },
  "geometry": {"coordinates":[-71.393166,42.309691],"type":"Point"}
}
