{
  "type": "Feature",
  "properties": {
    "iso:country":"US",
    "sg:address":"139 Newbury St",
    "sg:city":"Framingham",
    "sg:classifiers":[
        {
            "category":"Manufacturing",
            "subcategory":"Printing",
            "type":"Manufacturing & Wholesale Goods"
        }
    ],
    "sg:phone":"+1 508 270 8484",
    "sg:postcode":"01701",
    "sg:province":"MA",
    "sg:tags":[
        "printer"
    ],
    "wof:name":"Freedom Digital Printing LLC",
    "wof:placetype":"venue"
},
  "geometry": {"coordinates":[-71.39316599999999,42.309691],"type":"Point"}
}