{
  "type": "Feature",
  "properties": {
    "iso:country":"US",
    "sg:address":"8 High St",
    "sg:city":"Andover",
    "sg:classifiers":[
        {
            "category":"Health Services",
            "subcategory":"Doctor",
            "type":"Services"
        }
    ],
    "sg:phone":"+1 978 475 3997",
    "sg:postcode":"01810",
    "sg:province":"MA",
    "sg:tags":[
        "dentist"
    ],
    "wof:name":"Kevin T Bagnall DDS",
    "wof:placetype":"venue"
},
  "geometry": {"coordinates":[-71.141451,42.659492],"type":"Point"}
}