{
  "type": "Feature",
  "properties": {
    "addr:full": "18 Forrest Rd Topsfield MA 01983",
    "addr:housenumber": "18",
    "addr:postcode": "01983",
    "addr:street": "Forrest Rd",
    "iso:country": "US",
    "sg:address": "18 Forrest Rd",
    "sg:city": "Topsfield",
    "sg:classifiers": [
      {
        "category": "Professional",
        "subcategory": "Management \u0026 Consulting",
        "type": "Services"
      }
    ],
    "sg:phone": "+1   ",
    "sg:postcode": "01983",
    "sg:province": "MA",
    "wof:name": "Paul F Jackman",
    "wof:placetype": "venue"
  },
  "geometry": {"coordinates":[-70.966031,42.639548],"type":"Point"}
}
