{
  "type": "Feature",
  "properties": {
    "iso:country":"US",
    "sg:address":"8 Hawthorne Pl Ste 102",
    "sg:city":"Boston",
    "sg:classifiers":[
        {
            "category":"Health Services",
            "subcategory":"Doctor",
            "type":"Services"
        }
    ],
    "sg:phone":"+1 617 742 8336",
    "sg:postcode":"02114",
    "sg:province":"MA",
    "sg:tags":[
        "physician",
        "surgeon"
    ],
    "sg:website":"http://www.jamescgroves.com",
    "wof:name":"James E Groves",
    "wof:placetype":"venue"
},
  "geometry": {"coordinates":[-71.066462,42.363429],"type":"Point"}
}