{
  "type": "Feature",
  "properties": {
    "addr:full":"24 Newton St Southborough MA 01772",
    "addr:housenumber":"24",
    "addr:postcode":"01772",
    "addr:street":"Newton St",
    "iso:country":"US",
    "sg:address":"24 Newton St",
    "sg:city":"Southborough",
    "sg:classifiers":[
        {
            "category":"Health Services",
            "subcategory":"Health Practitioner",
            "type":"Services"
        }
    ],
    "sg:phone":"+1 508 481 2996",
    "sg:postcode":"01772",
    "sg:province":"MA",
    "sg:tags":[
        "therapist",
        "physical"
    ],
    "wof:name":"Hardy Physical Therapy Rehab",
    "wof:placetype":"venue"
},
  "geometry": {"coordinates":[-71.525626,42.3119],"type":"Point"}
}