{
  "type": "Feature",
  "properties": {
    "iso:country":"US",
    "sg:address":"24 Tamarack Dr",
    "sg:city":"Amherst",
    "sg:classifiers":[
        {
            "category":"Education",
            "subcategory":"Special Training",
            "type":"Public Place"
        }
    ],
    "sg:phone":"+1 413 256 8623",
    "sg:postcode":"01002",
    "sg:province":"MA",
    "sg:tags":[
        "tutoring"
    ],
    "wof:name":"High Quality Teaching Inst Inc",
    "wof:placetype":"venue"
},
  "geometry": {"coordinates":[-72.496663,42.364017],"type":"Point"}
}