{
  "type": "Feature",
  "properties": {
    "iso:country":"US",
    "sg:address":"207 Mammoth Rd",
    "sg:city":"Lowell",
    "sg:classifiers":[
        {
            "category":"Manufacturing",
            "subcategory":"Toys & Sporting Goods",
            "type":"Manufacturing & Wholesale Goods"
        }
    ],
    "sg:phone":"+1   ",
    "sg:postcode":"01854",
    "sg:province":"MA",
    "sg:tags":[
        "mfg"
    ],
    "wof:name":"Dave S Custom Clubs",
    "wof:placetype":"venue"
},
  "geometry": {"coordinates":[-71.337585,42.653956],"type":"Point"}
}