{
  "type": "Feature",
  "properties": {
    "iso:country":"US",
    "sg:address":"10 Minuteman Rd",
    "sg:city":"Hingham",
    "sg:classifiers":[
        {
            "category":"Building & Trades",
            "subcategory":"Construction",
            "type":"Services"
        }
    ],
    "sg:phone":"+1   ",
    "sg:postcode":"02043",
    "sg:province":"MA",
    "sg:tags":[
        "house"
    ],
    "wof:name":"Crowley Builders Edmond P",
    "wof:placetype":"venue"
},
  "geometry": {"coordinates":[-70.89243,42.199494],"type":"Point"}
}