{
  "type": "Feature",
  "properties": {
    "addr:full": "1195 Beacon St Ste 3 Brookline MA 02446",
    "addr:housenumber": "1195",
    "addr:postcode": "02446",
    "addr:street": "Beacon St Ste 3",
    "iso:country": "US",
    "sg:address": "1195 Beacon St Ste 3",
    "sg:city": "Brookline",
    "sg:classifiers": [
      {
        "category": "Home \u0026 Garden",
        "subcategory": "Home Furnishings",
        "type": "Retail Goods"
      }
    ],
    "sg:phone": "+1 800 403 7086",
    "sg:postcode": "02446",
    "sg:province": "MA",
    "sg:tags": [
      "decor"
    ],
    "sg:website": "www.laccento.com",
    "wof:name": "Laccento",
    "wof:placetype": "venue"
  },
  "geometry": {"coordinates":[-71.115591,42.343553],"type":"Point"}
}
