{
  "type": "Feature",
  "properties": {
    "addr:full":"65 Begley St Agawam MA 01001",
    "addr:housenumber":"65",
    "addr:postcode":"01001",
    "addr:street":"Begley St",
    "iso:country":"US",
    "sg:address":"65 Begley St",
    "sg:city":"Agawam",
    "sg:classifiers":[
        {
            "category":"Organizations",
            "subcategory":"Professional Association",
            "type":"Services"
        }
    ],
    "sg:phone":"+1 413 821 0473",
    "sg:postcode":"01001",
    "sg:province":"MA",
    "wof:name":"Agawam Educational Assn",
    "wof:placetype":"venue"
},
  "geometry": {"coordinates":[-72.63979399999999,42.089573],"type":"Point"}
}