{
  "type": "Feature",
  "properties": {
    "iso:country":"US",
    "sg:address":"834 Blue Hill Ave",
    "sg:city":"Dorchester Ctr",
    "sg:classifiers":[
        {
            "category":"Health Services",
            "subcategory":"Health Practitioner",
            "type":"Services"
        }
    ],
    "sg:phone":"+1 617 929 1000",
    "sg:postcode":"02124",
    "sg:province":"MA",
    "sg:tags":[
        "therapist",
        "physical"
    ],
    "wof:name":"Atlantis Physical Therapy",
    "wof:placetype":"venue"
},
  "geometry": {"coordinates":[-71.087351,42.296229],"type":"Point"}
}