{
  "type": "Feature",
  "properties": {
    "iso:country":"US",
    "sg:address":"442 Marrett Rd",
    "sg:city":"Lexington",
    "sg:classifiers":[
        {
            "category":"Health Services",
            "subcategory":"Chiropractor",
            "type":"Services"
        }
    ],
    "sg:phone":"+1 781 863 0583",
    "sg:postcode":"02421",
    "sg:province":"MA",
    "wof:name":"Conley Susan E",
    "wof:placetype":"venue"
},
  "geometry": {"coordinates":[-71.24299600000001,42.434463],"type":"Point"}
}