{
  "type": "Feature",
  "properties": {
    "addr:full": "442 Marrett Rd Lexington MA 02421",
    "addr:housenumber": "442",
    "addr:postcode": "02421",
    "addr:street": "Marrett Rd",
    "iso:country": "US",
    "sg:address": "442 Marrett Rd",
    "sg:city": "Lexington",
    "sg:classifiers": [
      {
        "category": "Health Services",
        "subcategory": "Chiropractor",
        "type": "Services"
      }
    ],
    "sg:phone": "+1 781 863 0583",
    "sg:postcode": "02421",
    "sg:province": "MA",
    "wof:name": "Conley Susan E",
    "wof:placetype": "venue"
  },
  "geometry": {"coordinates":[-71.242996,42.434463],"type":"Point"}
}
