{
  "type": "Feature",
  "properties": {
    "addr:full":"109 South St Hopkinton MA 01748",
    "addr:housenumber":"109",
    "addr:postcode":"01748",
    "addr:street":"South St",
    "iso:country":"US",
    "sg:address":"109 South St",
    "sg:city":"Hopkinton",
    "sg:classifiers":[
        {
            "category":"Wholesale",
            "subcategory":"Electrical",
            "type":"Manufacturing & Wholesale Goods"
        }
    ],
    "sg:phone":"+1 781 449 1750",
    "sg:postcode":"01748",
    "sg:province":"MA",
    "sg:tags":[
        "transmission",
        "equipment",
        "power"
    ],
    "wof:name":"Warren Pike Assoc",
    "wof:placetype":"venue"
},
  "geometry": {"coordinates":[-71.54397,42.202058],"type":"Point"}
}