{
  "type": "Feature",
  "properties": {
    "addr:full":"47 North St Lexington MA 02420",
    "addr:housenumber":"47",
    "addr:postcode":"02420",
    "addr:street":"North St",
    "iso:country":"US",
    "sg:address":"47 North St",
    "sg:city":"Lexington",
    "sg:classifiers":[
        {
            "category":"Education",
            "subcategory":"Junior College",
            "type":"Public Place"
        }
    ],
    "sg:phone":"+1 781 863 9907",
    "sg:postcode":"02420",
    "sg:province":"MA",
    "sg:tags":[
        "doll"
    ],
    "wof:name":"Tinker Minds Inc",
    "wof:placetype":"venue"
},
  "geometry": {"coordinates":[-71.21690599999999,42.468765],"type":"Point"}
}