{
  "type": "Feature",
  "properties": {
    "addr:full": "63 E Main St Westborough MA 01581",
    "addr:housenumber": "63",
    "addr:postcode": "01581",
    "addr:street": "E Main St",
    "iso:country": "US",
    "sg:address": "63 E Main St",
    "sg:city": "Westborough",
    "sg:classifiers": [
      {
        "category": "Food \u0026 Beverages",
        "subcategory": "Bakery",
        "type": "Retail Goods"
      }
    ],
    "sg:phone": "+1 508 898 2333",
    "sg:postcode": "01581",
    "sg:province": "MA",
    "sg:tags": [
      "doughnut"
    ],
    "wof:name": "Donut Maker",
    "wof:placetype": "venue"
  },
  "geometry": {"coordinates":[-71.609521,42.275461],"type":"Point"}
}
