{
  "type": "Feature",
  "properties": {
    "addr:full": "1245 South St Needham MA 02492",
    "addr:housenumber": "1245",
    "addr:postcode": "02492",
    "addr:street": "South St",
    "iso:country": "US",
    "sg:address": "1245 South St",
    "sg:city": "Needham",
    "sg:classifiers": [
      {
        "category": "Professional",
        "subcategory": "Lawyer \u0026 Legal Services",
        "type": "Services"
      }
    ],
    "sg:phone": "+1 781 449 3012",
    "sg:postcode": "02492",
    "sg:province": "MA",
    "sg:tags": [
      "attorney"
    ],
    "wof:name": "James R Burke",
    "wof:placetype": "venue"
  },
  "geometry": {"coordinates":[-71.256959,42.261303],"type":"Point"}
}
