{
  "type": "Feature",
  "properties": {
    "iso:country":"US",
    "sg:address":"1245 South St",
    "sg:city":"Needham",
    "sg:classifiers":[
        {
            "category":"Professional",
            "subcategory":"Lawyer & Legal Services",
            "type":"Services"
        }
    ],
    "sg:phone":"+1 781 449 3012",
    "sg:postcode":"02492",
    "sg:province":"MA",
    "sg:tags":[
        "attorney"
    ],
    "wof:name":"James R Burke",
    "wof:placetype":"venue"
},
  "geometry": {"coordinates":[-71.25695899999999,42.261303],"type":"Point"}
}