{
  "type": "Feature",
  "properties": {
    "addr:full": "140 1st St Medford MA 02155",
    "addr:housenumber": "140",
    "addr:postcode": "02155",
    "addr:street": "1St St",
    "iso:country": "US",
    "sg:address": "140 1st St",
    "sg:city": "Medford",
    "sg:classifiers": [
      {
        "category": "Local Transit",
        "type": "Transportation"
      }
    ],
    "sg:phone": "+1 781 306 0303",
    "sg:postcode": "02155",
    "sg:province": "MA",
    "sg:tags": [
      "car"
    ],
    "wof:name": "Capital Intasia",
    "wof:placetype": "venue"
  },
  "geometry": {"coordinates":[-71.082533,42.412196],"type":"Point"}
}
