{
  "type": "Feature",
  "properties": {
    "addr:full":"1768A Massachusetts Ave Cambridge MA 02140",
    "addr:housenumber":"1768a",
    "addr:postcode":"02140",
    "addr:street":"Massachusetts Ave",
    "iso:country":"US",
    "sg:address":"1768A Massachusetts Ave",
    "sg:city":"Cambridge",
    "sg:classifiers":[
        {
            "category":"Personal",
            "subcategory":"Beauty Salon",
            "type":"Services"
        }
    ],
    "sg:phone":"+1 617 354 9133",
    "sg:postcode":"02140",
    "sg:province":"MA",
    "sg:tags":[
        "hair"
    ],
    "wof:name":"Hair Connection",
    "wof:placetype":"venue"
},
  "geometry": {"coordinates":[-71.11939700000001,42.385518],"type":"Point"}
}