{
  "type": "Feature",
  "properties": {
    "addr:full": "55 Kimball Rd Chelsea MA 02150",
    "addr:housenumber": "55",
    "addr:postcode": "02150",
    "addr:street": "Kimball Rd",
    "iso:country": "US",
    "sg:address": "55 Kimball Rd",
    "sg:city": "Chelsea",
    "sg:classifiers": [
      {
        "category": "Professional",
        "subcategory": "Business Services",
        "type": "Services"
      }
    ],
    "sg:phone": "+1 617 884 1105",
    "sg:postcode": "02150",
    "sg:province": "MA",
    "sg:tags": [
      "embroidery"
    ],
    "sg:website": "www.krazykatsembroidery.com",
    "wof:name": "Krazy Kat's",
    "wof:placetype": "venue"
  },
  "geometry": {"coordinates":[-71.033326,42.4075],"type":"Point"}
}
