{
  "type": "Feature",
  "properties": {
    "addr:full":"420 Main St Ste 2 Walpole MA 02081",
    "addr:housenumber":"420",
    "addr:postcode":"02081",
    "addr:street":"Main St Ste 2",
    "iso:country":"US",
    "sg:address":"420 Main St Ste 2",
    "sg:city":"Walpole",
    "sg:classifiers":[
        {
            "category":"Professional",
            "subcategory":"Lawyer & Legal Services",
            "type":"Services"
        }
    ],
    "sg:phone":"+1 508 668 3360",
    "sg:postcode":"02081",
    "sg:province":"MA",
    "wof:name":"Riley James Jr Attorney",
    "wof:placetype":"venue"
},
  "geometry": {"coordinates":[-71.237999,42.1619],"type":"Point"}
}