{
  "type": "Feature",
  "properties": {
    "addr:full": "28 State St Boston MA 02109",
    "addr:housenumber": "28",
    "addr:postcode": "02109",
    "addr:street": "State St",
    "iso:country": "US",
    "sg:address": "28 State St",
    "sg:city": "Boston",
    "sg:classifiers": [
      {
        "category": "Professional",
        "subcategory": "Lawyer \u0026 Legal Services",
        "type": "Services"
      }
    ],
    "sg:phone": "+1 617 535 4023",
    "sg:postcode": "02109",
    "sg:province": "MA",
    "wof:name": "Ploszaj Stephen Atty",
    "wof:placetype": "venue"
  },
  "geometry": {"coordinates":[-71.057404,42.358898],"type":"Point"}
}
