{
  "type": "Feature",
  "properties": {
    "addr:full": "334 Washington St Haverhill MA 01832",
    "addr:housenumber": "334",
    "addr:postcode": "01832",
    "addr:street": "Washington St",
    "iso:country": "US",
    "sg:address": "334 Washington St",
    "sg:city": "Haverhill",
    "sg:classifiers": [
      {
        "category": "Food \u0026 Beverages",
        "subcategory": "Bakery",
        "type": "Retail Goods"
      }
    ],
    "sg:phone": "+1 978 372 4308",
    "sg:postcode": "01832",
    "sg:province": "MA",
    "sg:tags": [
      "baker"
    ],
    "wof:name": "Bread Of Life Bakery Sales",
    "wof:placetype": "venue"
  },
  "geometry": {"coordinates":[-71.091259,42.771249],"type":"Point"}
}
