{
  "type": "Feature",
  "properties": {
    "iso:country":"US",
    "sg:address":"334 Washington St",
    "sg:city":"Haverhill",
    "sg:classifiers":[
        {
            "category":"Food & Beverages",
            "subcategory":"Bakery",
            "type":"Retail Goods"
        }
    ],
    "sg:phone":"+1 978 372 4308",
    "sg:postcode":"01832",
    "sg:province":"MA",
    "sg:tags":[
        "baker"
    ],
    "wof:name":"Bread Of Life Bakery Sales",
    "wof:placetype":"venue"
},
  "geometry": {"coordinates":[-71.09125899999999,42.771249],"type":"Point"}
}