{
  "type": "Feature",
  "properties": {
    "iso:country":"US",
    "sg:address":"33 Bedford Street",
    "sg:city":"Lexington",
    "sg:classifiers":[
        {
            "category":"Professional",
            "subcategory":"Lawyer & Legal Services",
            "type":"Services"
        }
    ],
    "sg:phone":"+1 781 862 7050",
    "sg:postcode":"02420",
    "sg:province":"MA",
    "sg:website":"www.shapiroelderlaw.com",
    "wof:name":"Shapiro Elder Law & Estate Planning",
    "wof:placetype":"venue"
},
  "geometry": {"coordinates":[-71.219464,42.456866],"type":"Point"}
}