{
  "type": "Feature",
  "properties": {
    "addr:full": "10 Winthrop Sq Fl 2 Boston MA 02110",
    "addr:housenumber": "10;2",
    "addr:postcode": "02110",
    "addr:street": "Winthrop Sq Fl",
    "iso:country": "US",
    "sg:address": "10 Winthrop Sq Fl 2",
    "sg:city": "Boston",
    "sg:classifiers": [
      {
        "category": "Professional",
        "subcategory": "Lawyer \u0026 Legal Services",
        "type": "Services"
      }
    ],
    "sg:phone": "+1 617 350 0100",
    "sg:postcode": "02110",
    "sg:province": "MA",
    "wof:name": "Lewinger Sheila Lwyr",
    "wof:placetype": "venue"
  },
  "geometry": {"coordinates":[-71.058098,42.353802],"type":"Point"}
}
