{
  "type": "Feature",
  "properties": {
    "addr:full": "8 Bow St Beverly MA 01915",
    "addr:housenumber": "8",
    "addr:postcode": "01915",
    "addr:street": "Bow St",
    "iso:country": "US",
    "sg:address": "8 Bow St",
    "sg:city": "Beverly",
    "sg:classifiers": [
      {
        "category": "Home \u0026 Garden",
        "subcategory": "Building Materials",
        "type": "Retail Goods"
      }
    ],
    "sg:phone": "+1 978 927 7592",
    "sg:postcode": "01915",
    "sg:province": "MA",
    "sg:tags": [
      "door"
    ],
    "wof:name": "Sihpol Overhead Garage Door",
    "wof:placetype": "venue"
  },
  "geometry": {"coordinates":[-70.879537,42.548338],"type":"Point"}
}
