{
  "type": "Feature",
  "properties": {
    "addr:full": "568 Dartmouth St South Dartmouth MA 02748",
    "addr:housenumber": "568",
    "addr:postcode": "02748",
    "addr:street": "Dartmouth St",
    "iso:country": "US",
    "sg:address": "568 Dartmouth St",
    "sg:city": "South Dartmouth",
    "sg:classifiers": [
      {
        "category": "Retail",
        "subcategory": "Auto Repair",
        "type": "Services"
      }
    ],
    "sg:phone": "+1 508 991 3620",
    "sg:postcode": "02748",
    "sg:province": "MA",
    "sg:tags": [
      "recreational",
      "general",
      "vehicle"
    ],
    "sg:website": "www.rvdr.net",
    "wof:name": "R V Doctor We Make House Calls",
    "wof:placetype": "venue"
  },
  "geometry": {"coordinates":[-70.939149,41.611371],"type":"Point"}
}
