{
  "type": "Feature",
  "properties": {
    "addr:full": "600 E Ashland St Brockton MA 02302",
    "addr:housenumber": "600",
    "addr:postcode": "02302",
    "addr:street": "E Ashland St",
    "iso:country": "US",
    "ovtr:label": "La Belle Day School, 600 E Ashland St Brockton MA US",
    "ovtr:similarity": 2.6009650230407715,
    "sg:address": "600 E Ashland St",
    "sg:city": "Brockton",
    "sg:classifiers": [
      {
        "category": "Social Services",
        "subcategory": "Child Care",
        "type": "Services"
      }
    ],
    "sg:phone": "+1 508 586 9143",
    "sg:postcode": "02302",
    "sg:province": "MA",
    "sg:tags": [
      "kindergarten",
      "academic",
      "school"
    ],
    "wof:name": "LA Belle Day School",
    "wof:placetype": "venue"
  },
  "geometry": {"coordinates":[-70.993684,42.098341],"type":"Point"}
}
