{
  "type": "Feature",
  "properties": {
    "iso:country":"US",
    "sg:address":"600 E Ashland St",
    "sg:city":"Brockton",
    "sg:classifiers":[
        {
            "category":"Social Services",
            "subcategory":"Child Care",
            "type":"Services"
        }
    ],
    "sg:phone":"+1 508 586 9143",
    "sg:postcode":"02302",
    "sg:province":"MA",
    "sg:tags":[
        "kindergarten",
        "academic",
        "school"
    ],
    "wof:name":"LA Belle Day School",
    "wof:placetype":"venue"
},
  "geometry": {"coordinates":[-70.993684,42.098341],"type":"Point"}
}