{
  "type": "Feature",
  "properties": {
    "addr:full":"873 Concord St Framingham MA 01701",
    "addr:housenumber":"873",
    "addr:postcode":"01701",
    "addr:street":"Concord St",
    "iso:country":"US",
    "sg:address":"873 Concord St",
    "sg:city":"Framingham",
    "sg:classifiers":[
        {
            "category":"Professional",
            "subcategory":"Computer Services",
            "type":"Services"
        }
    ],
    "sg:phone":"+1 508 589 4486",
    "sg:postcode":"01701",
    "sg:province":"MA",
    "sg:tags":[
        "invite",
        "events",
        "evite",
        "invitations",
        "party"
    ],
    "sg:website":"http://www.punchbowl.com/",
    "wof:name":"Punchbowl",
    "wof:placetype":"venue"
},
  "geometry": {"coordinates":[-71.40574599999999,42.301997],"type":"Point"}
}