{
  "type": "Feature",
  "properties": {
    "iso:country":"US",
    "sg:address":"11 Story St",
    "sg:city":"Cambridge",
    "sg:classifiers":[
        {
            "category":"Professional",
            "type":"Services"
        }
    ],
    "sg:phone":"+1 617 876 5050",
    "sg:postcode":"02138",
    "sg:province":"MA",
    "sg:tags":[
        "establishment"
    ],
    "wof:name":"Hire Minds",
    "wof:placetype":"venue"
},
  "geometry": {"coordinates":[-71.123293,42.373655],"type":"Point"}
}