{
  "type": "Feature",
  "properties": {
    "addr:full": "20 Deforest Rd Newton MA 02462",
    "addr:housenumber": "20",
    "addr:postcode": "02462",
    "addr:street": "Deforest Rd",
    "iso:country": "US",
    "sg:address": "20 Deforest Rd",
    "sg:city": "Newton",
    "sg:classifiers": [
      {
        "category": "Health Services",
        "subcategory": "Medical Lab",
        "type": "Services"
      }
    ],
    "sg:phone": "+1 617 244 8265",
    "sg:postcode": "02462",
    "sg:province": "MA",
    "sg:tags": [
      "laboratory"
    ],
    "wof:name": "Dental Engineering",
    "wof:placetype": "venue"
  },
  "geometry": {"coordinates":[-71.257703,42.334185],"type":"Point"}
}
