{
  "type": "Feature",
  "properties": {
    "addr:full": "253 Acton St Carlisle MA 01741",
    "addr:housenumber": "253",
    "addr:postcode": "01741",
    "addr:street": "Acton St",
    "iso:country": "US",
    "sg:address": "253 Acton St",
    "sg:city": "Carlisle",
    "sg:classifiers": [
      {
        "category": "Professional",
        "subcategory": "Research",
        "type": "Services"
      }
    ],
    "sg:phone": "+1 978 287 5882",
    "sg:postcode": "01741",
    "sg:province": "MA",
    "sg:tags": [
      "development",
      "laboratory"
    ],
    "wof:name": "MRC Materials Research Corp",
    "wof:placetype": "venue"
  },
  "geometry": {"coordinates":[-71.386643,42.529915],"type":"Point"}
}
