{
  "type": "Feature",
  "properties": {
    "addr:full":"71 Mill St Mansfield MA 02048",
    "addr:housenumber":"71",
    "addr:postcode":"02048",
    "addr:street":"Mill St",
    "iso:country":"US",
    "sg:address":"71 Mill St",
    "sg:city":"Mansfield",
    "sg:classifiers":[
        {
            "category":"Community Center",
            "subcategory":"Youth",
            "type":"Public Place"
        }
    ],
    "sg:phone":"+1 508 339 0037",
    "sg:postcode":"02048",
    "sg:province":"MA",
    "wof:name":"Un Common Theatre Co",
    "wof:placetype":"venue"
},
  "geometry": {"coordinates":[-71.178459,42.021671],"type":"Point"}
}