{
  "type": "Feature",
  "properties": {
    "iso:country":"US",
    "sg:address":"221 Essex St",
    "sg:city":"Haverhill",
    "sg:classifiers":[
        {
            "category":"Retail",
            "subcategory":"Auto Repair",
            "type":"Services"
        }
    ],
    "sg:phone":"+1 978 374 0311",
    "sg:postcode":"01832",
    "sg:province":"MA",
    "sg:tags":[
        "repairing",
        "automobile"
    ],
    "wof:name":"Bradford Towing Co",
    "wof:placetype":"venue"
},
  "geometry": {"coordinates":[-71.087222,42.775741],"type":"Point"}
}