{
  "type": "Feature",
  "properties": {
    "iso:country":"US",
    "sg:address":"71 Central St",
    "sg:city":"West Boylston",
    "sg:classifiers":[
        {
            "category":"Health Services",
            "subcategory":"Doctor",
            "type":"Services"
        }
    ],
    "sg:phone":"+1 508 835 3146",
    "sg:postcode":"01583",
    "sg:province":"MA",
    "sg:tags":[
        "dentist"
    ],
    "wof:name":"Michael S Casey DDS",
    "wof:placetype":"venue"
},
  "geometry": {"coordinates":[-71.78424099999999,42.369195],"type":"Point"}
}