{
  "type": "Feature",
  "properties": {
    "addr:full": "71 Central St West Boylston MA 01583",
    "addr:housenumber": "71",
    "addr:postcode": "01583",
    "addr:street": "Central St",
    "iso:country": "US",
    "sg:address": "71 Central St",
    "sg:city": "West Boylston",
    "sg:classifiers": [
      {
        "category": "Health Services",
        "subcategory": "Doctor",
        "type": "Services"
      }
    ],
    "sg:phone": "+1 508 835 3146",
    "sg:postcode": "01583",
    "sg:province": "MA",
    "sg:tags": [
      "dentist"
    ],
    "wof:name": "Michael S Casey DDS",
    "wof:placetype": "venue"
  },
  "geometry": {"coordinates":[-71.784241,42.369195],"type":"Point"}
}
