{
  "type": "Feature",
  "properties": {
    "iso:country":"US",
    "sg:address":"28 Hastings St",
    "sg:city":"Mendon",
    "sg:classifiers":[
        {
            "category":"Building & Trades",
            "subcategory":"Cleaning & Sanitation",
            "type":"Services"
        }
    ],
    "sg:phone":"+1 508 634 8377",
    "sg:postcode":"01756",
    "sg:province":"MA",
    "sg:tags":[
        "ventilating",
        "duct",
        "system",
        "air"
    ],
    "wof:name":"Mighty Duct",
    "wof:placetype":"venue"
},
  "geometry": {"coordinates":[-71.557227,42.104441],"type":"Point"}
}