{
  "type": "Feature",
  "properties": {
    "iso:country":"US",
    "sg:address":"690 American Legion Hwy",
    "sg:city":"Roslindale",
    "sg:phone":"+1 617 522 1140",
    "sg:postcode":"02131",
    "sg:province":"MA",
    "wof:name":"Designer Outlet",
    "wof:placetype":"venue"
},
  "geometry": {"coordinates":[-71.11252899999999,42.284008],"type":"Point"}
}