{
  "type": "Feature",
  "properties": {
    "addr:full": "39 Arnold St Quincy MA 02169",
    "addr:housenumber": "39",
    "addr:postcode": "02169",
    "addr:street": "Arnold St",
    "iso:country": "US",
    "sg:address": "39 Arnold St",
    "sg:city": "Quincy",
    "sg:classifiers": [
      {
        "category": "Building \u0026 Trades",
        "subcategory": "Construction",
        "type": "Services"
      }
    ],
    "sg:phone": "+1   ",
    "sg:postcode": "02169",
    "sg:province": "MA",
    "sg:tags": [
      "residential"
    ],
    "wof:name": "Nor East Building Inc",
    "wof:placetype": "venue"
  },
  "geometry": {"coordinates":[-70.985484,42.244348],"type":"Point"}
}
