{
  "type": "Feature",
  "properties": {
    "iso:country":"US",
    "sg:address":"406 Washington St",
    "sg:city":"Holliston",
    "sg:classifiers":[
        {
            "category":"Shopping",
            "type":"Retail Goods"
        }
    ],
    "sg:phone":"+1 508 429 6040",
    "sg:postcode":"01746",
    "sg:province":"MA",
    "sg:tags":[
        "picture",
        "frame"
    ],
    "wof:name":"That's My Ticket",
    "wof:placetype":"venue"
},
  "geometry": {"coordinates":[-71.426614,42.210398],"type":"Point"}
}