{
  "type": "Feature",
  "properties": {
    "iso:country":"US",
    "sg:address":"215 Forest Hills Street",
    "sg:city":"Jamaica Plain",
    "sg:classifiers":[
        {
            "category":"Education",
            "subcategory":"Preschool",
            "type":"Public Place"
        },
        {
            "category":"Education",
            "subcategory":"School",
            "type":"Public Place"
        }
    ],
    "sg:phone":"+1 617 522 1841",
    "sg:postcode":"02130",
    "sg:province":"MA",
    "sg:tags":[
        "elementary"
    ],
    "wof:name":"Parkside Christian Academy",
    "wof:placetype":"venue"
},
  "geometry": {"coordinates":[-71.102555,42.306744],"type":"Point"}
}