{
  "type": "Feature",
  "properties": {
    "addr:full":"248 Main St Wareham MA 02571",
    "addr:housenumber":"248",
    "addr:postcode":"02571",
    "addr:street":"Main St",
    "iso:country":"US",
    "sg:address":"248 Main St",
    "sg:city":"Wareham",
    "sg:classifiers":[
        {
            "category":"Professional",
            "subcategory":"Business Services",
            "type":"Services"
        },
        {
            "category":"Government",
            "subcategory":"Post Office",
            "type":"Public Place"
        }
    ],
    "sg:phone":"+1 800 275 8777",
    "sg:postcode":"02571",
    "sg:province":"MA",
    "sg:tags":[
        "mail",
        "shipping"
    ],
    "sg:website":"http://www.usps.com",
    "wof:name":"United States Postal Service",
    "wof:placetype":"venue"
},
  "geometry": {"coordinates":[-70.716397,41.758983],"type":"Point"}
}