{
  "type": "Feature",
  "properties": {
    "iso:country":"US",
    "sg:address":"1700 Middlesex St",
    "sg:city":"Lowell",
    "sg:classifiers":[
        {
            "category":"Retail",
            "subcategory":"Car Wash",
            "type":"Services"
        }
    ],
    "sg:phone":"+1 978 458 2801",
    "sg:postcode":"01851",
    "sg:province":"MA",
    "sg:tags":[
        "polishing",
        "automobile",
        "washing",
        "detailing"
    ],
    "sg:website":"http://www.carwashandlaundry.com",
    "wof:name":"St Hilaire Car Wash",
    "wof:placetype":"venue"
},
  "geometry": {"coordinates":[-71.352341,42.635488],"type":"Point"}
}