{
  "type": "Feature",
  "properties": {
    "addr:full": "11 Legion Rd Weston MA 02493",
    "addr:housenumber": "11",
    "addr:postcode": "02493",
    "addr:street": "Legion Rd",
    "iso:country": "US",
    "sg:address": "11 Legion Rd",
    "sg:city": "Weston",
    "sg:classifiers": [
      {
        "category": "Building \u0026 Trades",
        "subcategory": "Construction",
        "type": "Services"
      }
    ],
    "sg:phone": "+1   ",
    "sg:postcode": "02493",
    "sg:province": "MA",
    "sg:tags": [
      "hanging",
      "contractor"
    ],
    "wof:name": "Dennis Schmiz",
    "wof:placetype": "venue"
  },
  "geometry": {"coordinates":[-71.269416,42.388045],"type":"Point"}
}
