{
  "type": "Feature",
  "properties": {
    "addr:full":"2 Concord Rd Lincoln MA 01773",
    "addr:housenumber":"2",
    "addr:postcode":"01773",
    "addr:street":"Concord Rd",
    "iso:country":"US",
    "sg:address":"2 Concord Rd",
    "sg:city":"Lincoln",
    "sg:classifiers":[
        {
            "category":"Travel",
            "subcategory":"Hotels & Motels",
            "type":"Entertainment"
        }
    ],
    "sg:phone":"+1 781 259 1899",
    "sg:postcode":"01773",
    "sg:province":"MA",
    "sg:tags":[
        "breakfast",
        "accommodation",
        "bed"
    ],
    "wof:name":"Walden Thoreau's Bed & Brkfs",
    "wof:placetype":"venue"
},
  "geometry": {"coordinates":[-71.33587,42.434118],"type":"Point"}
}