{
  "type": "Feature",
  "properties": {
    "addr:full": "32 19th St Lowell MA 01850",
    "addr:housenumber": "32",
    "addr:postcode": "01850",
    "addr:street": "19Th St",
    "iso:country": "US",
    "sg:address": "32 19th St",
    "sg:city": "Lowell",
    "sg:phone": "+1 781 218 3985",
    "sg:postcode": "01850",
    "sg:province": "MA",
    "sg:website": "http://national.citysearch.com/profile/external/604235792/lowell_ma/dual_state_electric_services_llc.html?publisher=yellowpages\u0026reference_id=1\u0026placement=ypwebsitemip",
    "wof:name": "Dual State Electric Services LLC",
    "wof:placetype": "venue"
  },
  "geometry": {"coordinates":[-71.302065,42.66224],"type":"Point"}
}
