{
  "type": "Feature",
  "properties": {
    "iso:country":"US",
    "sg:address":"91 Forest St",
    "sg:city":"Brockton",
    "sg:classifiers":[
        {
            "category":"Manufacturing",
            "subcategory":"Metals",
            "type":"Manufacturing & Wholesale Goods"
        }
    ],
    "sg:phone":"+1 508 580 5004",
    "sg:postcode":"02302",
    "sg:province":"MA",
    "sg:tags":[
        "steel"
    ],
    "wof:name":"Newcorp Steel Fabricators",
    "wof:placetype":"venue"
},
  "geometry": {"coordinates":[-71.009637,42.061899],"type":"Point"}
}