{
  "type": "Feature",
  "properties": {
    "addr:full": "91 Forest St Brockton MA 02302",
    "addr:housenumber": "91",
    "addr:postcode": "02302",
    "addr:street": "Forest St",
    "iso:country": "US",
    "sg:address": "91 Forest St",
    "sg:city": "Brockton",
    "sg:classifiers": [
      {
        "category": "Manufacturing",
        "subcategory": "Metals",
        "type": "Manufacturing \u0026 Wholesale Goods"
      }
    ],
    "sg:phone": "+1 508 580 5004",
    "sg:postcode": "02302",
    "sg:province": "MA",
    "sg:tags": [
      "steel"
    ],
    "wof:name": "Newcorp Steel Fabricators",
    "wof:placetype": "venue"
  },
  "geometry": {"coordinates":[-71.009637,42.061899],"type":"Point"}
}
