{
  "type": "Feature",
  "properties": {
    "addr:full":"289 Columbia St Cambridge MA 02141",
    "addr:housenumber":"289",
    "addr:postcode":"02141",
    "addr:street":"Columbia St",
    "iso:country":"US",
    "sg:address":"289 Columbia St",
    "sg:city":"Cambridge",
    "sg:classifiers":[
        {
            "category":"Personal",
            "subcategory":"Beauty Salon",
            "type":"Services"
        }
    ],
    "sg:phone":"+1 617 864 3473",
    "sg:postcode":"02141",
    "sg:province":"MA",
    "sg:tags":[
        "hair",
        "stylist"
    ],
    "wof:name":"Aicha African Hair Braiding by Factou",
    "wof:placetype":"venue"
},
  "geometry": {"coordinates":[-71.096183,42.369957],"type":"Point"}
}