{
  "type": "Feature",
  "properties": {
    "addr:full":"40 Wainwright Rd Winchester MA 01890",
    "addr:housenumber":"40",
    "addr:postcode":"01890",
    "addr:street":"Wainwright Rd",
    "iso:country":"US",
    "sg:address":"40 Wainwright Rd",
    "sg:city":"Winchester",
    "sg:classifiers":[
        {
            "category":"Professional",
            "subcategory":"Business Services",
            "type":"Services"
        }
    ],
    "sg:phone":"+1   ",
    "sg:postcode":"01890",
    "sg:province":"MA",
    "wof:name":"Vaeth Associates Inc",
    "wof:placetype":"venue"
},
  "geometry": {"coordinates":[-71.164851,42.458329],"type":"Point"}
}