{
  "type": "Feature",
  "properties": {
    "iso:country":"US",
    "sg:address":"490 N Main St",
    "sg:city":"Randolph",
    "sg:classifiers":[
        {
            "category":"Health Services",
            "subcategory":"Doctor",
            "type":"Services"
        }
    ],
    "sg:phone":"+1 781 963 7204",
    "sg:postcode":"02368",
    "sg:province":"MA",
    "sg:tags":[
        "surgeon",
        "oral"
    ],
    "wof:name":"Rossman Richard S DDS",
    "wof:placetype":"venue"
},
  "geometry": {"coordinates":[-71.048599,42.174999],"type":"Point"}
}