{
  "type": "Feature",
  "properties": {
    "iso:country":"US",
    "sg:address":"98 Central St",
    "sg:city":"Holliston",
    "sg:classifiers":[
        {
            "category":"Restaurant",
            "type":"Food & Drink"
        }
    ],
    "sg:phone":"+1 508 429 7275",
    "sg:postcode":"01746",
    "sg:province":"MA",
    "sg:tags":[
        "shop",
        "coffee"
    ],
    "wof:name":"Central Cafe",
    "wof:placetype":"venue"
},
  "geometry": {"coordinates":[-71.42603699999999,42.200024],"type":"Point"}
}