{
  "type": "Feature",
  "properties": {
    "iso:country":"US",
    "sg:address":"6 Federal St Ste 1",
    "sg:city":"Haverhill",
    "sg:classifiers":[
        {
            "category":"Retail",
            "subcategory":"Auto Rental",
            "type":"Services"
        },
        {
            "category":"Local Transit",
            "type":"Transportation"
        }
    ],
    "sg:phone":"+1 978 373 4852",
    "sg:postcode":"01832",
    "sg:province":"MA",
    "sg:tags":[
        "shuttle",
        "limousine"
    ],
    "wof:name":"American Livery Systems",
    "wof:placetype":"venue"
},
  "geometry": {"coordinates":[-71.09163700000001,42.779469],"type":"Point"}
}