{
  "type": "Feature",
  "properties": {
    "addr:full": "6 Federal St Ste 1 Haverhill MA 01832",
    "addr:housenumber": "6",
    "addr:postcode": "01832",
    "addr:street": "Federal St Ste 1",
    "iso:country": "US",
    "sg:address": "6 Federal St Ste 1",
    "sg:city": "Haverhill",
    "sg:classifiers": [
      {
        "category": "Retail",
        "subcategory": "Auto Rental",
        "type": "Services"
      },
      {
        "category": "Local Transit",
        "type": "Transportation"
      }
    ],
    "sg:phone": "+1 978 373 4852",
    "sg:postcode": "01832",
    "sg:province": "MA",
    "sg:tags": [
      "shuttle",
      "limousine"
    ],
    "wof:name": "American Livery Systems",
    "wof:placetype": "venue"
  },
  "geometry": {"coordinates":[-71.091637,42.779469],"type":"Point"}
}
