{
  "type": "Feature",
  "properties": {
    "addr:full": "266 Old Oaken Bucket Rd Scituate MA 02066",
    "addr:housenumber": "266",
    "addr:postcode": "02066",
    "addr:street": "Old Oaken Bucket Rd",
    "iso:country": "US",
    "sg:address": "266 Old Oaken Bucket Rd",
    "sg:city": "Scituate",
    "sg:classifiers": [
      {
        "category": "Social Services",
        "subcategory": "Child Care",
        "type": "Services"
      }
    ],
    "sg:phone": "+1 781 545 4525",
    "sg:postcode": "02066",
    "sg:province": "MA",
    "sg:tags": [
      "kindergarten",
      "academic",
      "school"
    ],
    "wof:name": "Berryblue Preschool",
    "wof:placetype": "venue"
  },
  "geometry": {"coordinates":[-70.773484,42.184038],"type":"Point"}
}
