{
  "type": "Feature",
  "properties": {
    "addr:full": "5 Admirals Way Chelsea MA 02150",
    "addr:housenumber": "5",
    "addr:postcode": "02150",
    "addr:street": "Admirals Way",
    "iso:country": "US",
    "sg:address": "5 Admirals Way",
    "sg:city": "Chelsea",
    "sg:classifiers": [
      {
        "category": "Real Estate",
        "subcategory": "Real Estate Agent",
        "type": "Services"
      }
    ],
    "sg:phone": "+1 617 884 4532",
    "sg:postcode": "02150",
    "sg:province": "MA",
    "wof:name": "Peabody Properties",
    "wof:placetype": "venue"
  },
  "geometry": {"coordinates":[-71.045535,42.390743],"type":"Point"}
}
