{
  "type": "Feature",
  "properties": {
    "addr:full":"340 Fordham Rd Wilmington MA 01887",
    "addr:housenumber":"340",
    "addr:postcode":"01887",
    "addr:street":"Fordham Rd",
    "iso:country":"US",
    "sg:address":"340 Fordham Rd",
    "sg:city":"Wilmington",
    "sg:classifiers":[
        {
            "category":"Education",
            "subcategory":"Special Training",
            "type":"Public Place"
        }
    ],
    "sg:phone":"+1 978 988 9199",
    "sg:postcode":"01887",
    "sg:province":"MA",
    "sg:tags":[
        "instruction",
        "music"
    ],
    "sg:website":"www.fishman.com",
    "wof:name":"Fishman Transducers Inc",
    "wof:placetype":"venue"
},
  "geometry": {"coordinates":[-71.137162,42.567202],"type":"Point"}
}