{
  "type": "Feature",
  "properties": {
    "addr:full": "200 Greenwood St Worcester MA 01607",
    "addr:housenumber": "200",
    "addr:postcode": "01607",
    "addr:street": "Greenwood St",
    "iso:country": "US",
    "ovtr:label": "Emanuel Lutheran Church, 200 Greenwood St Worcester MA US",
    "ovtr:similarity": 2.942852020263672,
    "sg:address": "200 Greenwood St",
    "sg:city": "Worcester",
    "sg:classifiers": [
      {
        "category": "Organizations",
        "subcategory": "Religious Organization",
        "type": "Services"
      }
    ],
    "sg:phone": "+1 508 756 6620",
    "sg:postcode": "01607",
    "sg:province": "MA",
    "sg:tags": [
      "church"
    ],
    "wof:name": "Emanuel Lutheran Church",
    "wof:placetype": "venue"
  },
  "geometry": {"coordinates":[-71.796068,42.223906],"type":"Point"}
}
