{
  "type": "Feature",
  "properties": {
    "iso:country":"US",
    "sg:address":"200 Greenwood St",
    "sg:city":"Worcester",
    "sg:classifiers":[
        {
            "category":"Organizations",
            "subcategory":"Religious Organization",
            "type":"Services"
        }
    ],
    "sg:phone":"+1 508 756 6620",
    "sg:postcode":"01607",
    "sg:province":"MA",
    "sg:tags":[
        "church"
    ],
    "wof:name":"Emanuel Lutheran Church",
    "wof:placetype":"venue"
},
  "geometry": {"coordinates":[-71.79606800000001,42.223906],"type":"Point"}
}