{
  "type": "Feature",
  "properties": {
    "iso:country":"US",
    "sg:address":"50 Church St",
    "sg:city":"Concord",
    "sg:classifiers":[
        {
            "category":"Professional",
            "subcategory":"Lawyer & Legal Services",
            "type":"Services"
        }
    ],
    "sg:phone":"+1 978 369 7720",
    "sg:postcode":"01742",
    "sg:province":"MA",
    "wof:name":"Bander David Atty - CLOSED",
    "wof:placetype":"venue"
},
  "geometry": {"coordinates":[-71.39540100000001,42.456402],"type":"Point"}
}