{
  "type": "Feature",
  "properties": {
    "addr:full": "50 Church St Concord MA 01742",
    "addr:housenumber": "50",
    "addr:postcode": "01742",
    "addr:street": "Church St",
    "iso:country": "US",
    "sg:address": "50 Church St",
    "sg:city": "Concord",
    "sg:classifiers": [
      {
        "category": "Professional",
        "subcategory": "Lawyer \u0026 Legal Services",
        "type": "Services"
      }
    ],
    "sg:phone": "+1 978 369 7720",
    "sg:postcode": "01742",
    "sg:province": "MA",
    "wof:name": "Bander David Atty - CLOSED",
    "wof:placetype": "venue"
  },
  "geometry": {"coordinates":[-71.395401,42.456402],"type":"Point"}
}
