{
  "type": "Feature",
  "properties": {
    "iso:country":"US",
    "sg:address":"360 Newbury St",
    "sg:city":"Boston",
    "sg:phone":"+1 617 375 7412",
    "sg:postcode":"02115",
    "sg:province":"MA",
    "sg:website":"http://www.geeksquad.com",
    "wof:name":"Geek Squad",
    "wof:placetype":"venue"
},
  "geometry": {"coordinates":[-71.087817,42.348151],"type":"Point"}
}