{
  "type": "Feature",
  "properties": {
    "iso:country":"US",
    "sg:address":"240 Sykes St",
    "sg:city":"Palmer",
    "sg:classifiers":[
        {
            "category":"Education",
            "subcategory":"Vocational School",
            "type":"Public Place"
        }
    ],
    "sg:phone":"+1 413 283 9701",
    "sg:postcode":"01069",
    "sg:province":"MA",
    "sg:tags":[
        "technical",
        "trade"
    ],
    "wof:name":"Pathfinder Regional Tech High",
    "wof:placetype":"venue"
},
  "geometry": {"coordinates":[-72.348446,42.18687],"type":"Point"}
}