{
  "type": "Feature",
  "properties": {
    "addr:full": "150 Highland St Townsend MA 01469",
    "addr:housenumber": "150",
    "addr:postcode": "01469",
    "addr:street": "Highland St",
    "iso:country": "US",
    "sg:address": "150 Highland St",
    "sg:city": "Townsend",
    "sg:classifiers": [
      {
        "category": "Real Estate",
        "subcategory": "Real Estate Agent",
        "type": "Services"
      }
    ],
    "sg:phone": "+1 978 597 1300",
    "sg:postcode": "01469",
    "sg:province": "MA",
    "sg:tags": [
      "inspection"
    ],
    "wof:name": "Galeota Associates Inc",
    "wof:placetype": "venue"
  },
  "geometry": {"coordinates":[-71.682176,42.671165],"type":"Point"}
}
