{
  "type": "Feature",
  "properties": {
    "iso:country":"US",
    "sg:address":"174 Union St",
    "sg:city":"Rockland",
    "sg:classifiers":[
        {
            "category":"Professional",
            "subcategory":"Business Services",
            "type":"Services"
        }
    ],
    "sg:phone":"+1   ",
    "sg:postcode":"02370",
    "sg:province":"MA",
    "wof:name":"Lexington Reclosers",
    "wof:placetype":"venue"
},
  "geometry": {"coordinates":[-70.91495399999999,42.127403],"type":"Point"}
}