{
  "type": "Feature",
  "properties": {
    "iso:country":"US",
    "sg:address":"53 Nicholas Rd",
    "sg:city":"Framingham",
    "sg:classifiers":[
        {
            "category":"Personal",
            "subcategory":"Tanning Parlor",
            "type":"Services"
        },
        {
            "category":"Personal",
            "type":"Services"
        }
    ],
    "sg:phone":"+1 508 788 5050",
    "sg:postcode":"01701",
    "sg:province":"MA",
    "sg:tags":[
        "salon"
    ],
    "wof:name":"Tanning Studio The",
    "wof:placetype":"venue"
},
  "geometry": {"coordinates":[-71.40326399999999,42.326354],"type":"Point"}
}