{
  "type": "Feature",
  "properties": {
    "addr:full": "21 Elm St Great Barrington MA 01230",
    "addr:housenumber": "21",
    "addr:postcode": "01230",
    "addr:street": "Elm St",
    "iso:country": "US",
    "sg:address": "21 Elm St",
    "sg:city": "Great Barrington",
    "sg:classifiers": [
      {
        "category": "Manufacturing",
        "subcategory": "Printing",
        "type": "Manufacturing \u0026 Wholesale Goods"
      }
    ],
    "sg:phone": "+1 413 528 5380",
    "sg:postcode": "01230",
    "sg:province": "MA",
    "sg:tags": [
      "newspaper"
    ],
    "wof:name": "Berkshire Record",
    "wof:placetype": "venue"
  },
  "geometry": {"coordinates":[-73.362179,42.195688],"type":"Point"}
}
