{
  "type": "Feature",
  "properties": {
    "iso:country":"US",
    "sg:address":"19 Mount Pleasant St",
    "sg:city":"Rockport",
    "sg:classifiers":[
        {
            "category":"Shopping",
            "type":"Retail Goods"
        }
    ],
    "sg:phone":"+1 978 546 8116",
    "sg:postcode":"01966",
    "sg:province":"MA",
    "sg:tags":[
        "art",
        "gallery",
        "dealer"
    ],
    "sg:website":"www.wennigergallery.com",
    "wof:name":"Wenniger Gallery",
    "wof:placetype":"venue"
},
  "geometry": {"coordinates":[-70.614131,42.6566],"type":"Point"}
}