{
  "type": "Feature",
  "properties": {
    "iso:country":"US",
    "sg:address":"284 Winthrop St",
    "sg:city":"Taunton",
    "sg:classifiers":[
        {
            "category":"Retail",
            "subcategory":"Auto Repair",
            "type":"Services"
        }
    ],
    "sg:phone":"+1 508 821 3033",
    "sg:postcode":"02780",
    "sg:province":"MA",
    "sg:tags":[
        "automobile",
        "lubrication"
    ],
    "wof:name":"Pro/Team Quick Oil Change",
    "wof:placetype":"venue"
},
  "geometry": {"coordinates":[-71.120009,41.889126],"type":"Point"}
}