{
  "type": "Feature",
  "properties": {
    "addr:full": "98 Reservation Rd Milton MA 02186",
    "addr:housenumber": "98",
    "addr:postcode": "02186",
    "addr:street": "Reservation Rd",
    "iso:country": "US",
    "sg:address": "98 Reservation Rd",
    "sg:city": "Milton",
    "sg:classifiers": [
      {
        "category": "Real Estate",
        "subcategory": "Surveying",
        "type": "Services"
      }
    ],
    "sg:phone": "+1 617 696 5550",
    "sg:postcode": "02186",
    "sg:province": "MA",
    "sg:tags": [
      "surveyor"
    ],
    "wof:name": "Milton Survey Assn",
    "wof:placetype": "venue"
  },
  "geometry": {"coordinates":[-71.046267,42.256985],"type":"Point"}
}
