{
  "type": "Feature",
  "properties": {
    "addr:full":"85 Merrimac St Boston MA 02114",
    "addr:housenumber":"85",
    "addr:postcode":"02114",
    "addr:street":"Merrimac St",
    "iso:country":"US",
    "sg:address":"85 Merrimac St",
    "sg:city":"Boston",
    "sg:classifiers":[
        {
            "category":"Professional",
            "subcategory":"Lawyer & Legal Services",
            "type":"Services"
        }
    ],
    "sg:phone":"+1 617 742 1760",
    "sg:postcode":"02114",
    "sg:province":"MA",
    "sg:tags":[
        "attorney"
    ],
    "wof:name":"Kathleen Keville",
    "wof:placetype":"venue"
},
  "geometry": {"coordinates":[-71.06182699999999,42.363649],"type":"Point"}
}