{
  "type": "Feature",
  "properties": {
    "addr:full": "46 Washington St Haverhill MA 01832",
    "addr:housenumber": "46",
    "addr:postcode": "01832",
    "addr:street": "Washington St",
    "iso:country": "US",
    "sg:address": "46 Washington St",
    "sg:city": "Haverhill",
    "sg:classifiers": [
      {
        "category": "Bars \u0026 Pubs",
        "type": "Food \u0026 Drink"
      }
    ],
    "sg:phone": "+1 978 521 2097",
    "sg:postcode": "01832",
    "sg:province": "MA",
    "wof:name": "Cheerleaders Sports Bar",
    "wof:placetype": "venue"
  },
  "geometry": {"coordinates":[-71.085208,42.77282],"type":"Point"}
}
