{
  "type": "Feature",
  "properties": {
    "iso:country":"US",
    "sg:address":"235 Columbia St",
    "sg:city":"Fall River",
    "sg:classifiers":[
        {
            "category":"Food & Beverages",
            "subcategory":"Groceries & Convenience Stores",
            "type":"Retail Goods"
        }
    ],
    "sg:phone":"+1 508 678 8652",
    "sg:postcode":"02721",
    "sg:province":"MA",
    "sg:tags":[
        "market"
    ],
    "wof:name":"Nobrega's Superette",
    "wof:placetype":"venue"
},
  "geometry": {"coordinates":[-71.162755,41.699011],"type":"Point"}
}