{
  "type": "Feature",
  "properties": {
    "addr:full": "235 Columbia St Fall River MA 02721",
    "addr:housenumber": "235",
    "addr:postcode": "02721",
    "addr:street": "Columbia St",
    "iso:country": "US",
    "ovtr:label": "Nobrega's Superette, 235 Columbia St Fall River MA US",
    "ovtr:similarity": 2.201781988143921,
    "sg:address": "235 Columbia St",
    "sg:city": "Fall River",
    "sg:classifiers": [
      {
        "category": "Food \u0026 Beverages",
        "subcategory": "Groceries \u0026 Convenience Stores",
        "type": "Retail Goods"
      }
    ],
    "sg:phone": "+1 508 678 8652",
    "sg:postcode": "02721",
    "sg:province": "MA",
    "sg:tags": [
      "market"
    ],
    "wof:name": "Nobrega's Superette",
    "wof:placetype": "venue"
  },
  "geometry": {"coordinates":[-71.162755,41.699011],"type":"Point"}
}
