{
  "type": "Feature",
  "properties": {
    "addr:full": "13 Pearl St Brockton MA 02301",
    "addr:housenumber": "13",
    "addr:postcode": "02301",
    "addr:street": "Pearl St",
    "iso:country": "US",
    "sg:address": "13 Pearl St",
    "sg:city": "Brockton",
    "sg:classifiers": [
      {
        "category": "Food \u0026 Beverages",
        "subcategory": "Liquor \u0026 Beverages",
        "type": "Retail Goods"
      }
    ],
    "sg:phone": "+1 508 583 0756",
    "sg:postcode": "02301",
    "sg:province": "MA",
    "sg:tags": [
      "beer",
      "spirit",
      "wine"
    ],
    "wof:name": "Winebasket Inc",
    "wof:placetype": "venue"
  },
  "geometry": {"coordinates":[-71.064499,42.089199],"type":"Point"}
}
