{
  "type": "Feature",
  "properties": {
    "iso:country":"US",
    "sg:address":"444 Humphrey St Ste 1",
    "sg:city":"Swampscott",
    "sg:classifiers":[
        {
            "category":"Food & Beverages",
            "subcategory":"Supermarket",
            "type":"Retail Goods"
        },
        {
            "category":"Food & Beverages",
            "subcategory":"Groceries & Convenience Stores",
            "type":"Retail Goods"
        }
    ],
    "sg:phone":"+1 781 581 5487",
    "sg:postcode":"01907",
    "sg:province":"MA",
    "sg:tags":[
        "super"
    ],
    "wof:name":"White Hen Pantry",
    "wof:placetype":"venue"
},
  "geometry": {"coordinates":[-70.909176,42.467783],"type":"Point"}
}