{
  "type": "Feature",
  "properties": {
    "addr:full": "444 Humphrey St Ste 1 Swampscott MA 01907",
    "addr:housenumber": "444",
    "addr:postcode": "01907",
    "addr:street": "Humphrey St Ste 1",
    "iso:country": "US",
    "sg:address": "444 Humphrey St Ste 1",
    "sg:city": "Swampscott",
    "sg:classifiers": [
      {
        "category": "Food \u0026 Beverages",
        "subcategory": "Supermarket",
        "type": "Retail Goods"
      },
      {
        "category": "Food \u0026 Beverages",
        "subcategory": "Groceries \u0026 Convenience Stores",
        "type": "Retail Goods"
      }
    ],
    "sg:phone": "+1 781 581 5487",
    "sg:postcode": "01907",
    "sg:province": "MA",
    "sg:tags": [
      "super"
    ],
    "wof:name": "White Hen Pantry",
    "wof:placetype": "venue"
  },
  "geometry": {"coordinates":[-70.909176,42.467783],"type":"Point"}
}
