{
  "type": "Feature",
  "properties": {
    "iso:country":"US",
    "sg:address":"800 Boston Rd",
    "sg:city":"Billerica",
    "sg:classifiers":[
        {
            "category":"Insurance",
            "subcategory":"Insurance Agent",
            "type":"Services"
        }
    ],
    "sg:phone":"+1 978 667 3265",
    "sg:postcode":"01821",
    "sg:province":"MA",
    "wof:name":"Triple L Insurance",
    "wof:placetype":"venue"
},
  "geometry": {"coordinates":[-71.230361,42.532334],"type":"Point"}
}