{
  "type": "Feature",
  "properties": {
    "addr:full": "184 Mill St Springfield MA 01108",
    "addr:housenumber": "184",
    "addr:postcode": "01108",
    "addr:street": "Mill St",
    "iso:country": "US",
    "sg:address": "184 Mill St",
    "sg:city": "Springfield",
    "sg:classifiers": [
      {
        "category": "Social Services",
        "type": "Services"
      }
    ],
    "sg:phone": "+1   ",
    "sg:postcode": "01108",
    "sg:province": "MA",
    "wof:name": "First Call",
    "wof:placetype": "venue"
  },
  "geometry": {"coordinates":[-72.573366,42.093664],"type":"Point"}
}
