{
  "type": "Feature",
  "properties": {
    "addr:full": "201A Highland Avenue Somerville MA 02143",
    "addr:housenumber": "201a",
    "addr:postcode": "02143",
    "addr:street": "Highland Avenue",
    "iso:country": "US",
    "sg:address": "201A Highland Avenue",
    "sg:city": "Somerville",
    "sg:classifiers": [
      {
        "category": "Personal",
        "subcategory": "Nail Salon",
        "type": "Services"
      }
    ],
    "sg:phone": "+1 617 591 2022",
    "sg:postcode": "02143",
    "sg:province": "MA",
    "wof:name": "Natural Touch",
    "wof:placetype": "venue"
  },
  "geometry": {"coordinates":[-71.107,42.38964],"type":"Point"}
}
