{
  "type": "Feature",
  "properties": {
    "addr:full": "486 Main St Greenfield MA 01301",
    "addr:housenumber": "486",
    "addr:postcode": "01301",
    "addr:street": "Main St",
    "iso:country": "US",
    "sg:address": "486 Main St",
    "sg:city": "Greenfield",
    "sg:classifiers": [
      {
        "category": "Health Services",
        "subcategory": "Health Practitioner",
        "type": "Services"
      }
    ],
    "sg:phone": "+1 413 773 8696",
    "sg:postcode": "01301",
    "sg:province": "MA",
    "sg:tags": [
      "psychologist"
    ],
    "wof:name": "Richard Schuetz PHD",
    "wof:placetype": "venue"
  },
  "geometry": {"coordinates":[-72.59669,42.587399],"type":"Point"}
}
