{
  "type": "Feature",
  "properties": {
    "iso:country":"US",
    "sg:address":"1622 Grand Army Hwy",
    "sg:city":"Somerset",
    "sg:classifiers":[
        {
            "category":"Personal",
            "subcategory":"Beauty Salon",
            "type":"Services"
        }
    ],
    "sg:phone":"+1 508 672 2277",
    "sg:postcode":"02726",
    "sg:province":"MA",
    "sg:tags":[
        "hair",
        "shop",
        "stylist"
    ],
    "sg:website":"http://www.hairaffair.org",
    "wof:name":"Swansea Hair Affair Ltd",
    "wof:placetype":"venue"
},
  "geometry": {"coordinates":[-71.18237499999999,41.737903],"type":"Point"}
}