{
  "type": "Feature",
  "properties": {
    "iso:country":"US",
    "sg:address":"14 Progress Rd",
    "sg:city":"Billerica",
    "sg:classifiers":[
        {
            "category":"Shopping",
            "subcategory":"Computers & Home Electronics",
            "type":"Retail Goods"
        }
    ],
    "sg:phone":"+1 978 671 9473",
    "sg:postcode":"01821",
    "sg:province":"MA",
    "sg:tags":[
        "consumer"
    ],
    "sg:website":"http://www.qplwire.com",
    "wof:name":"Q P L Electronic Distributors, Inc.",
    "wof:placetype":"venue"
},
  "geometry": {"coordinates":[-71.231368,42.521153],"type":"Point"}
}