{
  "type": "Feature",
  "properties": {
    "addr:full": "1 Constitution Plz Ste 3 Charlestown MA 02129",
    "addr:housenumber": "1",
    "addr:postcode": "02129",
    "addr:street": "Constitution Plz Ste 3",
    "iso:country": "US",
    "sg:address": "1 Constitution Plz Ste 3",
    "sg:city": "Charlestown",
    "sg:classifiers": [
      {
        "category": "Professional",
        "subcategory": "Lawyer \u0026 Legal Services",
        "type": "Services"
      }
    ],
    "sg:phone": "+1 617 241 3000",
    "sg:postcode": "02129",
    "sg:province": "MA",
    "wof:name": "Grunert John A K",
    "wof:placetype": "venue"
  },
  "geometry": {"coordinates":[-71.060995,42.370869],"type":"Point"}
}
