{
  "type": "Feature",
  "properties": {
    "iso:country":"US",
    "sg:address":"325 Mount Vernon Street",
    "sg:city":"Dorchester",
    "sg:classifiers":[
        {
            "category":"Education",
            "subcategory":"School",
            "type":"Public Place"
        }
    ],
    "sg:phone":"+1 617 635 8694",
    "sg:postcode":"02125",
    "sg:province":"MA",
    "sg:tags":[
        "high",
        "middle",
        "elementary"
    ],
    "wof:name":"Boston City of",
    "wof:placetype":"venue"
},
  "geometry": {"coordinates":[-71.04306200000001,42.318229],"type":"Point"}
}