{
  "type": "Feature",
  "properties": {
    "iso:country":"US",
    "sg:address":"119 Howard St",
    "sg:city":"Ludlow",
    "sg:classifiers":[
        {
            "category":"Retail",
            "subcategory":"Repair Shop",
            "type":"Services"
        }
    ],
    "sg:phone":"+1 413 592 8377",
    "sg:postcode":"01056",
    "sg:province":"MA",
    "sg:tags":[
        "welding"
    ],
    "wof:name":"United Welding Inc",
    "wof:placetype":"venue"
},
  "geometry": {"coordinates":[-72.480046,42.162407],"type":"Point"}
}