{
  "type": "Feature",
  "properties": {
    "addr:full":"18 Rutledge Rd Peabody MA 01960",
    "addr:housenumber":"18",
    "addr:postcode":"01960",
    "addr:street":"Rutledge Rd",
    "iso:country":"US",
    "sg:address":"18 Rutledge Rd",
    "sg:city":"Peabody",
    "sg:phone":"+1 978 536 9955",
    "sg:postcode":"01960",
    "sg:province":"MA",
    "sg:tags":[
        "oil"
    ],
    "wof:name":"Direct Fuel",
    "wof:placetype":"venue"
},
  "geometry": {"coordinates":[-71.02785900000001,42.548057],"type":"Point"}
}