{
  "type": "Feature",
  "properties": {
    "iso:country":"US",
    "sg:address":"232 Newbury St",
    "sg:city":"Boston",
    "sg:classifiers":[
        {
            "category":"Shopping",
            "type":"Retail Goods"
        }
    ],
    "sg:phone":"+1 617 536 5992",
    "sg:postcode":"02116",
    "sg:province":"MA",
    "sg:tags":[
        "picture",
        "frame"
    ],
    "sg:website":"www.posterexpress.com",
    "wof:name":"Wall",
    "wof:placetype":"venue"
},
  "geometry": {"coordinates":[-71.08055299999999,42.35012],"type":"Point"}
}