{
  "type": "Feature",
  "properties": {
    "addr:full":"218 Old Sudbury Rd Sudbury MA 01776",
    "addr:housenumber":"218",
    "addr:postcode":"01776",
    "addr:street":"Old Sudbury Rd",
    "iso:country":"US",
    "sg:address":"218 Old Sudbury Rd",
    "sg:city":"Sudbury",
    "sg:classifiers":[
        {
            "category":"Professional",
            "subcategory":"Business Services",
            "type":"Services"
        }
    ],
    "sg:phone":"+1 978 443 5255",
    "sg:postcode":"01776",
    "sg:province":"MA",
    "sg:tags":[
        "nonphysical",
        "commercial",
        "market",
        "analysis",
        "research"
    ],
    "sg:website":"http://www.mkt-insights.com",
    "wof:name":"Market Insights",
    "wof:placetype":"venue"
},
  "geometry": {"coordinates":[-71.40848200000001,42.380128],"type":"Point"}
}