{
  "type": "Feature",
  "properties": {
    "addr:full":"18 S Water St New Bedford MA 02740",
    "addr:housenumber":"18",
    "addr:postcode":"02740",
    "addr:street":"S Water St",
    "iso:country":"US",
    "sg:address":"18 S Water St",
    "sg:city":"New Bedford",
    "sg:classifiers":[
        {
            "category":"Wholesale",
            "subcategory":"Seafood",
            "type":"Manufacturing & Wholesale Goods"
        }
    ],
    "sg:phone":"+1   ",
    "sg:postcode":"02740",
    "sg:province":"MA",
    "wof:name":"Canyon Seafood International",
    "wof:placetype":"venue"
},
  "geometry": {"coordinates":[-70.922657,41.634467],"type":"Point"}
}