{
  "type": "Feature",
  "properties": {
    "iso:country":"US",
    "sg:address":"1495 Washington St",
    "sg:city":"East Bridgewater",
    "sg:classifiers":[
        {
            "category":"Professional",
            "type":"Services"
        }
    ],
    "sg:phone":"+1 508 378 7752",
    "sg:postcode":"02333",
    "sg:province":"MA",
    "sg:tags":[
        "establishment"
    ],
    "wof:name":"S & S Assoc",
    "wof:placetype":"venue"
},
  "geometry": {"coordinates":[-70.91842,42.029756],"type":"Point"}
}