{
  "type": "Feature",
  "properties": {
    "iso:country":"US",
    "sg:address":"165 Concord St",
    "sg:city":"Framingham",
    "sg:classifiers":[
        {
            "category":"Food & Beverages",
            "subcategory":"Bakery",
            "type":"Retail Goods"
        }
    ],
    "sg:phone":"+1 508 872 8698",
    "sg:postcode":"01702",
    "sg:province":"MA",
    "sg:tags":[
        "baker"
    ],
    "wof:name":"Padaria Brasil Bakery",
    "wof:placetype":"venue"
},
  "geometry": {"coordinates":[-71.416684,42.27854],"type":"Point"}
}