{
  "type": "Feature",
  "properties": {
    "addr:full": "194 North St Danvers MA 01923",
    "addr:housenumber": "194",
    "addr:postcode": "01923",
    "addr:street": "North St",
    "iso:country": "US",
    "sg:address": "194 North St",
    "sg:city": "Danvers",
    "sg:classifiers": [
      {
        "category": "Health Services",
        "subcategory": "Clinic",
        "type": "Services"
      }
    ],
    "sg:phone": "+1 978 745 5245",
    "sg:postcode": "01923",
    "sg:province": "MA",
    "sg:tags": [
      "holistic",
      "practitioner"
    ],
    "wof:name": "Reiki Wellness Group",
    "wof:placetype": "venue"
  },
  "geometry": {"coordinates":[-70.959144,42.59576],"type":"Point"}
}
