{
  "type": "Feature",
  "properties": {
    "addr:full": "70 Pleasant St Gloucester MA 01930",
    "addr:housenumber": "70",
    "addr:postcode": "01930",
    "addr:street": "Pleasant St",
    "iso:country": "US",
    "sg:address": "70 Pleasant St",
    "sg:city": "Gloucester",
    "sg:classifiers": [
      {
        "category": "Professional",
        "type": "Services"
      }
    ],
    "sg:phone": "+1 978 281 2471",
    "sg:postcode": "01930",
    "sg:province": "MA",
    "sg:tags": [
      "place",
      "worship",
      "church"
    ],
    "wof:name": "Monsignor Sullivan Hall",
    "wof:placetype": "venue"
  },
  "geometry": {"coordinates":[-70.662761,42.615918],"type":"Point"}
}
