{
  "type": "Feature",
  "properties": {
    "addr:full": "11 Davis St New Bedford MA 02746",
    "addr:housenumber": "11",
    "addr:postcode": "02746",
    "addr:street": "Davis St",
    "iso:country": "US",
    "sg:address": "11 Davis St",
    "sg:city": "New Bedford",
    "sg:classifiers": [
      {
        "category": "Building \u0026 Trades",
        "subcategory": "Landscaping Services",
        "type": "Services"
      }
    ],
    "sg:phone": "+1 508 979 8100",
    "sg:postcode": "02746",
    "sg:province": "MA",
    "sg:tags": [
      "landscape",
      "contractor"
    ],
    "wof:name": "Raindance Irrigation \u0026 Svc",
    "wof:placetype": "venue"
  },
  "geometry": {"coordinates":[-70.92275,41.664729],"type":"Point"}
}
