{
  "type": "Feature",
  "properties": {
    "iso:country":"US",
    "sg:address":"11 Davis St",
    "sg:city":"New Bedford",
    "sg:classifiers":[
        {
            "category":"Building & Trades",
            "subcategory":"Landscaping Services",
            "type":"Services"
        }
    ],
    "sg:phone":"+1 508 979 8100",
    "sg:postcode":"02746",
    "sg:province":"MA",
    "sg:tags":[
        "landscape",
        "contractor"
    ],
    "wof:name":"Raindance Irrigation & Svc",
    "wof:placetype":"venue"
},
  "geometry": {"coordinates":[-70.92274999999999,41.664729],"type":"Point"}
}