{
  "type": "Feature",
  "properties": {
    "addr:full": "33 Francesca Ave Somerville MA 02144",
    "addr:housenumber": "33",
    "addr:postcode": "02144",
    "addr:street": "Francesca Ave",
    "iso:country": "US",
    "sg:address": "33 Francesca Ave",
    "sg:city": "Somerville",
    "sg:classifiers": [
      {
        "category": "Arts \u0026 Performance",
        "subcategory": "Arts Center",
        "type": "Entertainment"
      },
      {
        "category": "Building \u0026 Trades",
        "subcategory": "Construction",
        "type": "Services"
      }
    ],
    "sg:phone": "+1 617 776 5003",
    "sg:postcode": "02144",
    "sg:province": "MA",
    "sg:tags": [
      "wallcoverings-installation",
      "wallpaper",
      "contractor",
      "decorating",
      "hand",
      "painting"
    ],
    "wof:name": "Othonia Painting Co",
    "wof:placetype": "venue"
  },
  "geometry": {"coordinates":[-71.119589,42.39897],"type":"Point"}
}
