{
  "type": "Feature",
  "properties": {
    "addr:full": "220 Main St Townsend MA 01469",
    "addr:housenumber": "220",
    "addr:postcode": "01469",
    "addr:street": "Main St",
    "iso:country": "US",
    "sg:address": "220 Main St",
    "sg:city": "Townsend",
    "sg:classifiers": [
      {
        "category": "Restaurant",
        "type": "Food \u0026 Drink"
      }
    ],
    "sg:phone": "+1 978 597 2331",
    "sg:postcode": "01469",
    "sg:province": "MA",
    "sg:tags": [
      "pizza"
    ],
    "wof:name": "Central Plaza Pizza",
    "wof:placetype": "venue"
  },
  "geometry": {"coordinates":[-71.701679,42.664806],"type":"Point"}
}
