{
  "type": "Feature",
  "properties": {
    "iso:country":"US",
    "sg:address":"220 Main St",
    "sg:city":"Townsend",
    "sg:classifiers":[
        {
            "category":"Restaurant",
            "type":"Food & Drink"
        }
    ],
    "sg:phone":"+1 978 597 2331",
    "sg:postcode":"01469",
    "sg:province":"MA",
    "sg:tags":[
        "pizza"
    ],
    "wof:name":"Central Plaza Pizza",
    "wof:placetype":"venue"
},
  "geometry": {"coordinates":[-71.701679,42.664806],"type":"Point"}
}