{
  "type": "Feature",
  "properties": {
    "iso:country":"US",
    "sg:address":"35 Day St",
    "sg:city":"Fitchburg",
    "sg:classifiers":[
        {
            "category":"Real Estate",
            "subcategory":"Real Estate Operator",
            "type":"Services"
        }
    ],
    "sg:phone":"+1 978 345 7143",
    "sg:postcode":"01420",
    "sg:province":"MA",
    "sg:tags":[
        "apartment"
    ],
    "wof:name":"Hotel Raymond Apartments",
    "wof:placetype":"venue"
},
  "geometry": {"coordinates":[-71.795733,42.581923],"type":"Point"}
}