{
  "type": "Feature",
  "properties": {
    "addr:full": "One Moody Street Waltham MA 02453",
    "addr:postcode": "02453",
    "addr:street": "Moody Street",
    "iso:country": "US",
    "sg:address": "One Moody Street",
    "sg:city": "Waltham",
    "sg:classifiers": [
      {
        "category": "Professional",
        "subcategory": "Research",
        "type": "Services"
      }
    ],
    "sg:phone": "+1 781 891 3750",
    "sg:postcode": "02453",
    "sg:province": "MA",
    "sg:website": "http://www.energyclimatesolutions.com/",
    "wof:name": "EnergyClimate Solutions",
    "wof:placetype": "venue"
  },
  "geometry": {"coordinates":[-71.237073,42.376185],"type":"Point"}
}
