{
  "type": "Feature",
  "properties": {
    "addr:full": "223 Barnstable Rd Hyannis MA 02601",
    "addr:housenumber": "223",
    "addr:postcode": "02601",
    "addr:street": "Barnstable Rd",
    "iso:country": "US",
    "sg:address": "223 Barnstable Rd",
    "sg:city": "Hyannis",
    "sg:classifiers": [
      {
        "category": "Shopping",
        "subcategory": "Bicycles \u0026 Sporting Goods",
        "type": "Retail Goods"
      }
    ],
    "sg:phone": "+1 508 775 7756",
    "sg:postcode": "02601",
    "sg:province": "MA",
    "wof:name": "Wind Snow \u0026 H2o",
    "wof:placetype": "venue"
  },
  "geometry": {"coordinates":[-70.285043,41.659787],"type":"Point"}
}
