{
  "type": "Feature",
  "properties": {
    "iso:country":"US",
    "sg:address":"223 Barnstable Rd",
    "sg:city":"Hyannis",
    "sg:classifiers":[
        {
            "category":"Shopping",
            "subcategory":"Bicycles & Sporting Goods",
            "type":"Retail Goods"
        }
    ],
    "sg:phone":"+1 508 775 7756",
    "sg:postcode":"02601",
    "sg:province":"MA",
    "wof:name":"Wind Snow & H2o",
    "wof:placetype":"venue"
},
  "geometry": {"coordinates":[-70.285043,41.659787],"type":"Point"}
}