{
  "type": "Feature",
  "properties": {
    "addr:full": "324 Deerfield St Greenfield MA 01301",
    "addr:housenumber": "324",
    "addr:postcode": "01301",
    "addr:street": "Deerfield St",
    "iso:country": "US",
    "sg:address": "324 Deerfield St",
    "sg:city": "Greenfield",
    "sg:classifiers": [
      {
        "category": "Home \u0026 Garden",
        "subcategory": "Garden Supply",
        "type": "Retail Goods"
      },
      {
        "category": "Shopping",
        "subcategory": "Gifts \u0026 Souvenirs",
        "type": "Retail Goods"
      },
      {
        "category": "Shopping",
        "subcategory": "Crafts \u0026 Fabrics",
        "type": "Retail Goods"
      },
      {
        "category": "Shopping",
        "subcategory": "Florist",
        "type": "Retail Goods"
      }
    ],
    "sg:phone": "+1 413 376 4233",
    "sg:postcode": "01301",
    "sg:province": "MA",
    "sg:tags": [
      "plant",
      "etc-retail",
      "dried",
      "basket",
      "trees-silk",
      "flowers"
    ],
    "sg:website": "http://www.floralaffairsgreenfield.com",
    "wof:name": "Floral Affairs",
    "wof:placetype": "venue"
  },
  "geometry": {"coordinates":[-72.596903,42.574561],"type":"Point"}
}
