{
  "type": "Feature",
  "properties": {
    "iso:country":"US",
    "sg:address":"3103 Cranberry Hwy",
    "sg:city":"East Wareham",
    "sg:classifiers":[
        {
            "category":"Home & Garden",
            "subcategory":"Home Furnishings",
            "type":"Retail Goods"
        }
    ],
    "sg:phone":"+1 508 759 2529",
    "sg:postcode":"02538",
    "sg:province":"MA",
    "sg:tags":[
        "housewares"
    ],
    "wof:name":"Not So General Store",
    "wof:placetype":"venue"
},
  "geometry": {"coordinates":[-70.64277,41.755964],"type":"Point"}
}