{
  "type": "Feature",
  "properties": {
    "iso:country":"US",
    "sg:address":"34R Chelmsford St",
    "sg:city":"Chelmsford",
    "sg:classifiers":[
        {
            "category":"Professional",
            "subcategory":"Lawyer & Legal Services",
            "type":"Services"
        }
    ],
    "sg:phone":"+1 978 250 2777",
    "sg:postcode":"01824",
    "sg:province":"MA",
    "sg:tags":[
        "personal",
        "injury"
    ],
    "sg:website":"www.kevinsullivanlaw.com",
    "wof:name":"Sullivan Kevin S Law Offices of",
    "wof:placetype":"venue"
},
  "geometry": {"coordinates":[-71.350195,42.598235],"type":"Point"}
}