{
  "type": "Feature",
  "properties": {
    "addr:full": "111 Canal St Salem MA 01970",
    "addr:housenumber": "111",
    "addr:postcode": "01970",
    "addr:street": "Canal St",
    "iso:country": "US",
    "ovtr:label": "Salem Laundry Co, 111 Canal St Salem MA US",
    "ovtr:similarity": 2.716865062713623,
    "sg:address": "111 Canal St",
    "sg:city": "Salem",
    "sg:classifiers": [
      {
        "category": "Retail",
        "subcategory": "Self-service Laundry",
        "type": "Services"
      }
    ],
    "sg:phone": "+1 978 745 4892",
    "sg:postcode": "01970",
    "sg:province": "MA",
    "wof:name": "Salem Laundry Co",
    "wof:placetype": "venue"
  },
  "geometry": {"coordinates":[-70.895989,42.509696],"type":"Point"}
}
