{
  "type": "Feature",
  "properties": {
    "iso:country":"US",
    "sg:address":"1627 Tremont Street",
    "sg:city":"Roxbury Crossing",
    "sg:classifiers":[
        {
            "category":"Bakery",
            "type":"Food & Drink"
        }
    ],
    "sg:phone":"+1 617 232 9974",
    "sg:postcode":"02120",
    "sg:province":"MA",
    "wof:name":"Athena's Donut",
    "wof:placetype":"venue"
},
  "geometry": {"coordinates":[-71.10372599999999,42.333694],"type":"Point"}
}