{
  "type": "Feature",
  "properties": {
    "iso:country":"US",
    "sg:address":"287 Essex St",
    "sg:city":"Lynn",
    "sg:classifiers":[
        {
            "category":"Retail",
            "subcategory":"Auto Repair",
            "type":"Services"
        }
    ],
    "sg:phone":"+1 781 592 0490",
    "sg:postcode":"01902",
    "sg:province":"MA",
    "sg:tags":[
        "repairing",
        "automobile"
    ],
    "wof:name":"Essex Auto Repair",
    "wof:placetype":"venue"
},
  "geometry": {"coordinates":[-70.93695,42.470555],"type":"Point"}
}