{
  "type": "Feature",
  "properties": {
    "iso:country":"US",
    "sg:address":"499 Essex St",
    "sg:city":"Lawrence",
    "sg:classifiers":[
        {
            "category":"Social Services",
            "type":"Services"
        }
    ],
    "sg:phone":"+1 978 689 3653",
    "sg:postcode":"01840",
    "sg:province":"MA",
    "sg:tags":[
        "probation"
    ],
    "wof:name":"Us Probation Office",
    "wof:placetype":"venue"
},
  "geometry": {"coordinates":[-71.16601799999999,42.705944],"type":"Point"}
}