{
  "type": "Feature",
  "properties": {
    "iso:country":"US",
    "sg:address":"65 Middle St",
    "sg:city":"Gloucester",
    "sg:classifiers":[
        {
            "category":"Manufacturing",
            "subcategory":"Printing",
            "type":"Manufacturing & Wholesale Goods"
        }
    ],
    "sg:phone":"+1   ",
    "sg:postcode":"01930",
    "sg:province":"MA",
    "sg:tags":[
        "newspaper"
    ],
    "wof:name":"Journal of Postmodern Mat",
    "wof:placetype":"venue"
},
  "geometry": {"coordinates":[-70.66304100000001,42.613316],"type":"Point"}
}