{
  "type": "Feature",
  "properties": {
    "addr:full": "65 Middle St Gloucester MA 01930",
    "addr:housenumber": "65",
    "addr:postcode": "01930",
    "addr:street": "Middle St",
    "iso:country": "US",
    "sg:address": "65 Middle St",
    "sg:city": "Gloucester",
    "sg:classifiers": [
      {
        "category": "Manufacturing",
        "subcategory": "Printing",
        "type": "Manufacturing \u0026 Wholesale Goods"
      }
    ],
    "sg:phone": "+1   ",
    "sg:postcode": "01930",
    "sg:province": "MA",
    "sg:tags": [
      "newspaper"
    ],
    "wof:name": "Journal of Postmodern Mat",
    "wof:placetype": "venue"
  },
  "geometry": {"coordinates":[-70.663041,42.613316],"type":"Point"}
}
