{
  "type": "Feature",
  "properties": {
    "addr:full": "314 Boston Rd North Billerica MA 01862",
    "addr:housenumber": "314",
    "addr:postcode": "01862",
    "addr:street": "Boston Rd",
    "atp:label": "7-ELEVEN #32481, 314 Boston Rd North Billerica MA US",
    "atp:similarity": 3.662853956222534,
    "iso:country": "US",
    "ovtr:label": "7-Eleven, 314 Boston Rd North Billerica MA US",
    "ovtr:similarity": 2.3948020935058594,
    "sg:address": "314 Boston Rd",
    "sg:city": "North Billerica",
    "sg:classifiers": [
      {
        "category": "Food \u0026 Beverages",
        "subcategory": "Groceries \u0026 Convenience Stores",
        "type": "Retail Goods"
      }
    ],
    "sg:phone": "+1 978 667 8124",
    "sg:postcode": "01862",
    "sg:province": "MA",
    "sg:website": "www.7-eleven.com",
    "wof:name": "7-Eleven",
    "wof:placetype": "venue"
  },
  "geometry": {"coordinates":[-71.276978,42.57139],"type":"Point"}
}
