{
  "type": "Feature",
  "properties": {
    "addr:full":"407 Hartford Pike Shrewsbury MA 01545",
    "addr:housenumber":"407",
    "addr:postcode":"01545",
    "addr:street":"Hartford Pike",
    "iso:country":"US",
    "sg:address":"407 Hartford Pike",
    "sg:city":"Shrewsbury",
    "sg:classifiers":[
        {
            "category":"Autos & Motor Vehicles",
            "subcategory":"Auto Supplies",
            "type":"Retail Goods"
        }
    ],
    "sg:phone":"+1 508 754 9876",
    "sg:postcode":"01545",
    "sg:province":"MA",
    "sg:tags":[
        "tire"
    ],
    "sg:website":"www.tirebarn.com",
    "wof:name":"Pete's Tire Barn Inc",
    "wof:placetype":"venue"
},
  "geometry": {"coordinates":[-71.711347,42.250289],"type":"Point"}
}