{
  "type": "Feature",
  "properties": {
    "addr:full":"1 Sunset Ct Amherst MA 01002",
    "addr:housenumber":"1",
    "addr:postcode":"01002",
    "addr:street":"Sunset Ct",
    "iso:country":"US",
    "sg:address":"1 Sunset Ct",
    "sg:city":"Amherst",
    "sg:classifiers":[
        {
            "category":"Travel",
            "subcategory":"Hotels & Motels",
            "type":"Entertainment"
        }
    ],
    "sg:phone":"+1 413 549 7554",
    "sg:postcode":"01002",
    "sg:province":"MA",
    "sg:tags":[
        "operation"
    ],
    "wof:name":"Ivy House Bed & Breakfast",
    "wof:placetype":"venue"
},
  "geometry": {"coordinates":[-72.527287,42.382796],"type":"Point"}
}