{
  "type": "Feature",
  "properties": {
    "iso:country":"US",
    "sg:address":"1620 Massachusetts Avenue",
    "sg:city":"Lexington",
    "sg:classifiers":[
        {
            "category":"Professional",
            "subcategory":"Lawyer & Legal Services",
            "type":"Services"
        }
    ],
    "sg:phone":"+1 781 862 1099",
    "sg:postcode":"02420",
    "sg:province":"MA",
    "wof:name":"Wallerstein Les Atty",
    "wof:placetype":"venue"
},
  "geometry": {"coordinates":[-71.224424,42.446448],"type":"Point"}
}