{
  "type": "Feature",
  "properties": {
    "addr:full": "542 Cambridge St Allston MA 02134",
    "addr:housenumber": "542",
    "addr:postcode": "02134",
    "addr:street": "Cambridge St",
    "iso:country": "US",
    "sg:address": "542 Cambridge St",
    "sg:city": "Allston",
    "sg:classifiers": [
      {
        "category": "Retail",
        "subcategory": "Veterinary Services",
        "type": "Services"
      }
    ],
    "sg:phone": "+1 617 782 5420",
    "sg:postcode": "02134",
    "sg:province": "MA",
    "sg:tags": [
      "veterinarian"
    ],
    "wof:name": "Merwin Memorial Free Clinic For Animals",
    "wof:placetype": "venue"
  },
  "geometry": {"coordinates":[-71.1393,42.3526],"type":"Point"}
}
