{
  "type": "Feature",
  "properties": {
    "addr:full": "520 Nantasket Ave Hull MA 02045",
    "addr:housenumber": "520",
    "addr:postcode": "02045",
    "addr:street": "Nantasket Ave",
    "iso:country": "US",
    "sg:address": "520 Nantasket Ave",
    "sg:city": "Hull",
    "sg:classifiers": [
      {
        "category": "Personal",
        "subcategory": "Beauty Salon",
        "type": "Services"
      }
    ],
    "sg:phone": "+1 781 925 2141",
    "sg:postcode": "02045",
    "sg:province": "MA",
    "wof:name": "Linda's Beachside Hair Salon",
    "wof:placetype": "venue"
  },
  "geometry": {"coordinates":[-70.873648,42.282877],"type":"Point"}
}
