{
  "type": "Feature",
  "properties": {
    "addr:full": "14 Storrs Ave Braintree MA 02184",
    "addr:housenumber": "14",
    "addr:postcode": "02184",
    "addr:street": "Storrs Ave",
    "iso:country": "US",
    "sg:address": "14 Storrs Ave",
    "sg:city": "Braintree",
    "sg:classifiers": [
      {
        "category": "Shopping",
        "subcategory": "Computers \u0026 Home Electronics",
        "type": "Retail Goods"
      }
    ],
    "sg:phone": "+1 781 849 9977",
    "sg:postcode": "02184",
    "sg:province": "MA",
    "sg:tags": [
      "software"
    ],
    "wof:name": "Bang Zoom Software",
    "wof:placetype": "venue"
  },
  "geometry": {"coordinates":[-71.004249,42.220629],"type":"Point"}
}
