{
  "type": "Feature",
  "properties": {
    "iso:country":"US",
    "sg:address":"14 Storrs Ave",
    "sg:city":"Braintree",
    "sg:classifiers":[
        {
            "category":"Shopping",
            "subcategory":"Computers & Home Electronics",
            "type":"Retail Goods"
        }
    ],
    "sg:phone":"+1 781 849 9977",
    "sg:postcode":"02184",
    "sg:province":"MA",
    "sg:tags":[
        "software"
    ],
    "wof:name":"Bang Zoom Software",
    "wof:placetype":"venue"
},
  "geometry": {"coordinates":[-71.004249,42.220629],"type":"Point"}
}