{
  "type": "Feature",
  "properties": {
    "iso:country":"US",
    "sg:address":"71 Plymouth Rd",
    "sg:city":"Bellingham",
    "sg:classifiers":[
        {
            "category":"Professional",
            "subcategory":"Business Services",
            "type":"Services"
        }
    ],
    "sg:phone":"+1   ",
    "sg:postcode":"02019",
    "sg:province":"MA",
    "wof:name":"Mike Morrison Scholarship",
    "wof:placetype":"venue"
},
  "geometry": {"coordinates":[-71.44902,42.123524],"type":"Point"}
}