{
  "type": "Feature",
  "properties": {
    "addr:full": "20 Donna Rd Newton MA 02459",
    "addr:housenumber": "20",
    "addr:postcode": "02459",
    "addr:street": "Donna Rd",
    "iso:country": "US",
    "sg:address": "20 Donna Rd",
    "sg:city": "Newton",
    "sg:classifiers": [
      {
        "category": "Building \u0026 Trades",
        "subcategory": "Equipment Rental",
        "type": "Services"
      }
    ],
    "sg:phone": "+1   ",
    "sg:postcode": "02459",
    "sg:province": "MA",
    "sg:tags": [
      "lessor"
    ],
    "wof:name": "All Equiped Leasing Inc",
    "wof:placetype": "venue"
  },
  "geometry": {"coordinates":[-71.178098,42.308304],"type":"Point"}
}
