{
  "type": "Feature",
  "properties": {
    "addr:full":"11 New Whitney St Boston MA 02115",
    "addr:housenumber":"11",
    "addr:postcode":"02115",
    "addr:street":"New Whitney St",
    "iso:country":"US",
    "sg:address":"11 New Whitney St",
    "sg:city":"Boston",
    "sg:classifiers":[
        {
            "category":"Organizations",
            "subcategory":"Non-profit Organization",
            "type":"Services"
        }
    ],
    "sg:phone":"+1 617 232 4306",
    "sg:postcode":"02115",
    "sg:province":"MA",
    "sg:tags":[
        "service/non-profit",
        "community"
    ],
    "wof:name":"Roxbury Tenants of Harvard",
    "wof:placetype":"venue"
},
  "geometry": {"coordinates":[-71.108902,42.3344],"type":"Point"}
}