{
  "type": "Feature",
  "properties": {
    "addr:full": "RR 28 Hyannis MA 02601",
    "addr:housenumber": "28",
    "addr:postcode": "02601",
    "addr:street": "Rr",
    "iso:country": "US",
    "sg:address": "RR 28",
    "sg:city": "Hyannis",
    "sg:classifiers": [
      {
        "category": "Banks \u0026 Credit Unions",
        "subcategory": "Bank",
        "type": "Services"
      },
      {
        "category": "Banks \u0026 Credit Unions",
        "subcategory": "Financial Services",
        "type": "Services"
      }
    ],
    "sg:phone": "+1 508 255 3052",
    "sg:postcode": "02601",
    "sg:province": "MA",
    "sg:tags": [
      "broker",
      "mortgage"
    ],
    "wof:name": "Cape Cod Five Cents Savings Bank",
    "wof:placetype": "venue"
  },
  "geometry": {"coordinates":[-70.299103,41.656502],"type":"Point"}
}
