{
  "type": "Feature",
  "properties": {
    "iso:country":"US",
    "sg:address":"56 Kearney Road",
    "sg:city":"Needham",
    "sg:classifiers":[
        {
            "category":"Professional",
            "subcategory":"Computer Services",
            "type":"Services"
        }
    ],
    "sg:phone":"+1 617 266 2555",
    "sg:postcode":"02494",
    "sg:province":"MA",
    "sg:tags":[
        "identity",
        "information-cards",
        "i-cards",
        "openid",
        "higgins"
    ],
    "sg:website":"http://www.azigo.com",
    "wof:name":"Azigo (formerly Parity)",
    "wof:placetype":"venue"
},
  "geometry": {"coordinates":[-71.229776,42.305712],"type":"Point"}
}