{
  "type": "Feature",
  "properties": {
    "iso:country":"US",
    "sg:address":"57 South Rd",
    "sg:city":"Pepperell",
    "sg:classifiers":[
        {
            "category":"Building & Trades",
            "subcategory":"Electrical",
            "type":"Services"
        }
    ],
    "sg:phone":"+1 978 433 1881",
    "sg:postcode":"01463",
    "sg:province":"MA",
    "sg:tags":[
        "electric",
        "contractor"
    ],
    "wof:name":"Mcgrath Electric",
    "wof:placetype":"venue"
},
  "geometry": {"coordinates":[-71.606683,42.634165],"type":"Point"}
}