{
  "type": "Feature",
  "properties": {
    "addr:full": "188 Bulrush Farm Rd Scituate MA 02066",
    "addr:housenumber": "188",
    "addr:postcode": "02066",
    "addr:street": "Bulrush Farm Rd",
    "iso:country": "US",
    "sg:address": "188 Bulrush Farm Rd",
    "sg:city": "Scituate",
    "sg:classifiers": [
      {
        "category": "Professional",
        "subcategory": "Engineering",
        "type": "Services"
      }
    ],
    "sg:phone": "+1 781 545 5522",
    "sg:postcode": "02066",
    "sg:province": "MA",
    "sg:tags": [
      "engineer"
    ],
    "wof:name": "Litzinger \u0026 Co Engineers",
    "wof:placetype": "venue"
  },
  "geometry": {"coordinates":[-70.770417,42.219526],"type":"Point"}
}
