{
  "type": "Feature",
  "properties": {
    "addr:full":"4 Lillian Rd Framingham MA 01701",
    "addr:housenumber":"4",
    "addr:postcode":"01701",
    "addr:street":"Lillian Rd",
    "iso:country":"US",
    "sg:address":"4 Lillian Rd",
    "sg:city":"Framingham",
    "sg:classifiers":[
        {
            "category":"Building & Trades",
            "subcategory":"Electrical",
            "type":"Services"
        }
    ],
    "sg:phone":"+1 508 879 5532",
    "sg:postcode":"01701",
    "sg:province":"MA",
    "sg:tags":[
        "electric",
        "contractor"
    ],
    "wof:name":"Joseph Spataro Master Electric",
    "wof:placetype":"venue"
},
  "geometry": {"coordinates":[-71.428139,42.304735],"type":"Point"}
}