{
  "type": "Feature",
  "properties": {
    "addr:full":"202 Sidney St Cambridge MA 02139",
    "addr:housenumber":"202",
    "addr:postcode":"02139",
    "addr:street":"Sidney St",
    "iso:country":"US",
    "sg:address":"202 Sidney St",
    "sg:city":"Cambridge",
    "sg:classifiers":[
        {
            "category":"Professional",
            "type":"Services"
        }
    ],
    "sg:phone":"+1 617 492 3452",
    "sg:postcode":"02139",
    "sg:province":"MA",
    "sg:tags":[
        "sculptor"
    ],
    "wof:name":"Peter D Haines",
    "wof:placetype":"venue"
},
  "geometry": {"coordinates":[-71.104878,42.358293],"type":"Point"}
}