{
  "type": "Feature",
  "properties": {
    "addr:full": "102 School St Manchester MA 01944",
    "addr:housenumber": "102",
    "addr:postcode": "01944",
    "addr:street": "School St",
    "iso:country": "US",
    "sg:address": "102 School St",
    "sg:city": "Manchester",
    "sg:classifiers": [
      {
        "category": "Wholesale",
        "subcategory": "Seafood",
        "type": "Manufacturing \u0026 Wholesale Goods"
      }
    ],
    "sg:phone": "+1 978 525 3474",
    "sg:postcode": "01944",
    "sg:province": "MA",
    "wof:name": "Sea Trek Enterprises",
    "wof:placetype": "venue"
  },
  "geometry": {"coordinates":[-70.770232,42.582622],"type":"Point"}
}
