{
  "type": "Feature",
  "properties": {
    "iso:country":"US",
    "sg:address":"102 School St",
    "sg:city":"Manchester",
    "sg:classifiers":[
        {
            "category":"Wholesale",
            "subcategory":"Seafood",
            "type":"Manufacturing & Wholesale Goods"
        }
    ],
    "sg:phone":"+1 978 525 3474",
    "sg:postcode":"01944",
    "sg:province":"MA",
    "wof:name":"Sea Trek Enterprises",
    "wof:placetype":"venue"
},
  "geometry": {"coordinates":[-70.77023199999999,42.582622],"type":"Point"}
}