{
  "type": "Feature",
  "properties": {
    "iso:country":"US",
    "sg:address":"54 Forest St",
    "sg:city":"Medford",
    "sg:classifiers":[
        {
            "category":"Professional",
            "subcategory":"Management & Consulting",
            "type":"Services"
        }
    ],
    "sg:phone":"+1   ",
    "sg:postcode":"02155",
    "sg:province":"MA",
    "sg:tags":[
        "business"
    ],
    "wof:name":"Lyn Max Consultant",
    "wof:placetype":"venue"
},
  "geometry": {"coordinates":[-71.109115,42.419269],"type":"Point"}
}