{
  "type": "Feature",
  "properties": {
    "iso:country":"US",
    "sg:address":"2271 Main St",
    "sg:city":"Brewster",
    "sg:classifiers":[
        {
            "category":"Professional",
            "subcategory":"Art Services",
            "type":"Services"
        }
    ],
    "sg:phone":"+1   ",
    "sg:postcode":"02631",
    "sg:province":"MA",
    "sg:tags":[
        "photography",
        "commercial"
    ],
    "wof:name":"Hucklesberrys",
    "wof:placetype":"venue"
},
  "geometry": {"coordinates":[-70.071884,41.76403],"type":"Point"}
}