{
  "type": "Feature",
  "properties": {
    "iso:country":"US",
    "sg:address":"92 Allen St",
    "sg:city":"Gardner",
    "sg:classifiers":[
        {
            "category":"Building & Trades",
            "subcategory":"Construction",
            "type":"Services"
        }
    ],
    "sg:phone":"+1 978 632 0314",
    "sg:postcode":"01440",
    "sg:province":"MA",
    "sg:tags":[
        "roofing",
        "contractor"
    ],
    "wof:name":"Norman Le Blanc Siding Co",
    "wof:placetype":"venue"
},
  "geometry": {"coordinates":[-72.00175,42.583809],"type":"Point"}
}