{
  "type": "Feature",
  "properties": {
    "iso:country":"US",
    "sg:address":"172 Newbury St",
    "sg:city":"Boston",
    "sg:classifiers":[
        {
            "category":"Organizations",
            "subcategory":"Non-profit Organization",
            "type":"Services"
        }
    ],
    "sg:phone":"+1 617 262 2828",
    "sg:postcode":"02116",
    "sg:province":"MA",
    "sg:website":"www.thepartnershipinc.org",
    "wof:name":"Partnership Inc",
    "wof:placetype":"venue"
},
  "geometry": {"coordinates":[-71.079019,42.350541],"type":"Point"}
}