{
  "type": "Feature",
  "properties": {
    "iso:country":"US",
    "sg:address":"50 Church St",
    "sg:city":"Belmont",
    "sg:classifiers":[
        {
            "category":"Professional",
            "subcategory":"Management & Consulting",
            "type":"Services"
        }
    ],
    "sg:phone":"+1 617 489 7800",
    "sg:postcode":"02478",
    "sg:province":"MA",
    "wof:name":"Levitt & Co Inc",
    "wof:placetype":"venue"
},
  "geometry": {"coordinates":[-71.190449,42.387178],"type":"Point"}
}