{
  "type": "Feature",
  "properties": {
    "addr:full": "50 Church St Belmont MA 02478",
    "addr:housenumber": "50",
    "addr:postcode": "02478",
    "addr:street": "Church St",
    "iso:country": "US",
    "sg:address": "50 Church St",
    "sg:city": "Belmont",
    "sg:classifiers": [
      {
        "category": "Professional",
        "subcategory": "Management \u0026 Consulting",
        "type": "Services"
      }
    ],
    "sg:phone": "+1 617 489 7800",
    "sg:postcode": "02478",
    "sg:province": "MA",
    "wof:name": "Levitt \u0026 Co Inc",
    "wof:placetype": "venue"
  },
  "geometry": {"coordinates":[-71.190449,42.387178],"type":"Point"}
}
