{
  "type": "Feature",
  "properties": {
    "addr:full":"12 Otis St Somerville MA 02145",
    "addr:housenumber":"12",
    "addr:postcode":"02145",
    "addr:street":"Otis St",
    "iso:country":"US",
    "sg:address":"12 Otis St",
    "sg:city":"Somerville",
    "sg:classifiers":[
        {
            "category":"Home & Garden",
            "subcategory":"Household Appliances",
            "type":"Retail Goods"
        },
        {
            "category":"Building & Trades",
            "subcategory":"Cleaning & Sanitation",
            "type":"Services"
        }
    ],
    "sg:phone":"+1 617 666 9622",
    "sg:postcode":"02145",
    "sg:province":"MA",
    "sg:tags":[
        "equipment",
        "purifying",
        "filters-cleaning",
        "air"
    ],
    "wof:name":"A-1 Filter Service",
    "wof:placetype":"venue"
},
  "geometry": {"coordinates":[-71.08700399999999,42.387061],"type":"Point"}
}