{
  "type": "Feature",
  "properties": {
    "addr:full": "35 Main St Plymouth MA 02360",
    "addr:housenumber": "35",
    "addr:postcode": "02360",
    "addr:street": "Main St",
    "iso:country": "US",
    "sg:address": "35 Main St",
    "sg:city": "Plymouth",
    "sg:classifiers": [
      {
        "category": "Restaurant",
        "type": "Food \u0026 Drink"
      },
      {
        "category": "Bars \u0026 Pubs",
        "subcategory": "Nightclub",
        "type": "Food \u0026 Drink"
      }
    ],
    "sg:phone": "+1 508 747 8337",
    "sg:postcode": "02360",
    "sg:province": "MA",
    "sg:tags": [
      "nightlife"
    ],
    "wof:name": "Riptides Grill \u0026 Bar - CLOSED",
    "wof:placetype": "venue"
  },
  "geometry": {"coordinates":[-70.662804,41.955002],"type":"Point"}
}
