{
  "type": "Feature",
  "properties": {
    "addr:full":"35 Main St Plymouth MA 02360",
    "addr:housenumber":"35",
    "addr:postcode":"02360",
    "addr:street":"Main St",
    "iso:country":"US",
    "sg:address":"35 Main St",
    "sg:city":"Plymouth",
    "sg:classifiers":[
        {
            "category":"Restaurant",
            "type":"Food & Drink"
        },
        {
            "category":"Bars & Pubs",
            "subcategory":"Nightclub",
            "type":"Food & Drink"
        }
    ],
    "sg:phone":"+1 508 747 8337",
    "sg:postcode":"02360",
    "sg:province":"MA",
    "sg:tags":[
        "nightlife"
    ],
    "wof:name":"Riptides Grill & Bar - CLOSED",
    "wof:placetype":"venue"
},
  "geometry": {"coordinates":[-70.66280399999999,41.955002],"type":"Point"}
}