{
  "type": "Feature",
  "properties": {
    "addr:full": "800 Boylston St Boston MA 02199",
    "addr:housenumber": "800",
    "addr:postcode": "02199",
    "addr:street": "Boylston St",
    "iso:country": "US",
    "sg:address": "800 Boylston St",
    "sg:city": "Boston",
    "sg:classifiers": [
      {
        "category": "Landmark",
        "subcategory": "Historic",
        "type": "Public Place"
      }
    ],
    "sg:phone": "+1 617 236 3100",
    "sg:postcode": "02199",
    "sg:province": "MA",
    "sg:tags": [
      "building",
      "historical"
    ],
    "wof:name": "Prudential Tower",
    "wof:placetype": "venue"
  },
  "geometry": {"coordinates":[-71.081814,42.348883],"type":"Point"}
}
