{
  "type": "Feature",
  "properties": {
    "iso:country":"US",
    "sg:address":"1616 Hyde Park Ave",
    "sg:city":"Hyde Park",
    "sg:classifiers":[
        {
            "category":"Wholesale",
            "subcategory":"Metals & Minerals",
            "type":"Manufacturing & Wholesale Goods"
        }
    ],
    "sg:phone":"+1 617 361 4646",
    "sg:postcode":"02136",
    "sg:province":"MA",
    "sg:tags":[
        "steel",
        "warehouse"
    ],
    "sg:website":"www.noreitech.com",
    "wof:name":"Northeast Industrial Tech Inc",
    "wof:placetype":"venue"
},
  "geometry": {"coordinates":[-71.131012,42.240777],"type":"Point"}
}