{
  "type": "Feature",
  "properties": {
    "iso:country":"US",
    "sg:address":"6 Dodge St",
    "sg:city":"Essex",
    "sg:classifiers":[
        {
            "category":"Home & Garden",
            "subcategory":"Furniture",
            "type":"Retail Goods"
        }
    ],
    "sg:phone":"+1 978 768 7799",
    "sg:postcode":"01929",
    "sg:province":"MA",
    "sg:tags":[
        "cabinet"
    ],
    "wof:name":"Full Circle Cabinetry",
    "wof:placetype":"venue"
},
  "geometry": {"coordinates":[-70.779563,42.634901],"type":"Point"}
}