{
  "type": "Feature",
  "properties": {
    "addr:full": "6 Dodge St Essex MA 01929",
    "addr:housenumber": "6",
    "addr:postcode": "01929",
    "addr:street": "Dodge St",
    "iso:country": "US",
    "sg:address": "6 Dodge St",
    "sg:city": "Essex",
    "sg:classifiers": [
      {
        "category": "Home \u0026 Garden",
        "subcategory": "Furniture",
        "type": "Retail Goods"
      }
    ],
    "sg:phone": "+1 978 768 7799",
    "sg:postcode": "01929",
    "sg:province": "MA",
    "sg:tags": [
      "cabinet"
    ],
    "wof:name": "Full Circle Cabinetry",
    "wof:placetype": "venue"
  },
  "geometry": {"coordinates":[-70.779563,42.634901],"type":"Point"}
}
