{
  "type": "Feature",
  "properties": {
    "addr:full": "62 School St Westfield MA 01085",
    "addr:housenumber": "62",
    "addr:postcode": "01085",
    "addr:street": "School St",
    "iso:country": "US",
    "sg:address": "62 School St",
    "sg:city": "Westfield",
    "sg:classifiers": [
      {
        "category": "Manufacturing",
        "subcategory": "Printing",
        "type": "Manufacturing \u0026 Wholesale Goods"
      }
    ],
    "sg:phone": "+1 413 568 4921",
    "sg:postcode": "01085",
    "sg:province": "MA",
    "sg:tags": [
      "newspaper"
    ],
    "wof:name": "Longmeadow News",
    "wof:placetype": "venue"
  },
  "geometry": {"coordinates":[-72.751589,42.121693],"type":"Point"}
}
