{
  "type": "Feature",
  "properties": {
    "addr:full": "123 Sylvan St Danvers MA 01923",
    "addr:housenumber": "123",
    "addr:postcode": "01923",
    "addr:street": "Sylvan St",
    "iso:country": "US",
    "sg:address": "123 Sylvan St",
    "sg:city": "Danvers",
    "sg:classifiers": [
      {
        "category": "Insurance",
        "subcategory": "Insurance Agent",
        "type": "Services"
      }
    ],
    "sg:phone": "+1 978 774 2463",
    "sg:postcode": "01923",
    "sg:province": "MA",
    "wof:name": "County Insurance",
    "wof:placetype": "venue"
  },
  "geometry": {"coordinates":[-70.944521,42.554518],"type":"Point"}
}
