{
  "type": "Feature",
  "properties": {
    "iso:country":"US",
    "sg:address":"123 Sylvan St",
    "sg:city":"Danvers",
    "sg:classifiers":[
        {
            "category":"Insurance",
            "subcategory":"Insurance Agent",
            "type":"Services"
        }
    ],
    "sg:phone":"+1 978 774 2463",
    "sg:postcode":"01923",
    "sg:province":"MA",
    "wof:name":"County Insurance",
    "wof:placetype":"venue"
},
  "geometry": {"coordinates":[-70.94452099999999,42.554518],"type":"Point"}
}