{
  "type": "Feature",
  "properties": {
    "iso:country":"US",
    "sg:address":"194 Middle St Ste 3R",
    "sg:city":"Lowell",
    "sg:phone":"+1 978 453 1311",
    "sg:postcode":"01852",
    "sg:province":"MA",
    "wof:name":"Life Alive",
    "wof:placetype":"venue"
},
  "geometry": {"coordinates":[-71.309682,42.645084],"type":"Point"}
}