{
  "type": "Feature",
  "properties": {
    "addr:full": "696 Merrill Rd Pittsfield MA 01201",
    "addr:housenumber": "696",
    "addr:postcode": "01201",
    "addr:street": "Merrill Rd",
    "iso:country": "US",
    "ovtr:label": "Pizza Hut, 660 Merrill Rd Pittsfield MA US",
    "ovtr:similarity": 3.4960970878601074,
    "sg:address": "696 Merrill Rd",
    "sg:city": "Pittsfield",
    "sg:classifiers": [
      {
        "category": "Restaurant",
        "type": "Food \u0026 Drink"
      }
    ],
    "sg:menulink": "http://www.allmenus.com/ma/pittsfield/73583-pizza-hut/menu/",
    "sg:phone": "+1 413 443 0288",
    "sg:postcode": "01201",
    "sg:province": "MA",
    "sg:tags": [
      "american",
      "pizza"
    ],
    "wof:name": "Pizza Hut",
    "wof:placetype": "venue"
  },
  "geometry": {"coordinates":[-73.2035,42.467706],"type":"Point"}
}
