{
  "type": "Feature",
  "properties": {
    "addr:full":"696 Merrill Rd Pittsfield MA 01201",
    "addr:housenumber":"696",
    "addr:postcode":"01201",
    "addr:street":"Merrill Rd",
    "iso:country":"US",
    "sg:address":"696 Merrill Rd",
    "sg:city":"Pittsfield",
    "sg:classifiers":[
        {
            "category":"Restaurant",
            "type":"Food & Drink"
        }
    ],
    "sg:menulink":"http://www.allmenus.com/ma/pittsfield/73583-pizza-hut/menu/",
    "sg:phone":"+1 413 443 0288",
    "sg:postcode":"01201",
    "sg:province":"MA",
    "sg:tags":[
        "american",
        "pizza"
    ],
    "wof:name":"Pizza Hut",
    "wof:placetype":"venue"
},
  "geometry": {"coordinates":[-73.20350000000001,42.467706],"type":"Point"}
}