{
  "type": "Feature",
  "properties": {
    "iso:country":"US",
    "sg:address":"25 South St",
    "sg:city":"Taunton",
    "sg:classifiers":[
        {
            "category":"Shopping",
            "subcategory":"Music",
            "type":"Retail Goods"
        }
    ],
    "sg:phone":"+1 508 222 2858",
    "sg:postcode":"02780",
    "sg:province":"MA",
    "sg:tags":[
        "compact",
        "record",
        "disc",
        "tape"
    ],
    "wof:name":"Cd Auto & Truck Repair",
    "wof:placetype":"venue"
},
  "geometry": {"coordinates":[-71.118707,41.863963],"type":"Point"}
}