{
  "type": "Feature",
  "properties": {
    "iso:country":"US",
    "sg:address":"192 W Main St",
    "sg:city":"Orange",
    "sg:classifiers":[
        {
            "category":"Arts & Performance",
            "subcategory":"Theater",
            "type":"Entertainment"
        }
    ],
    "sg:phone":"+1 978 544 8092",
    "sg:postcode":"01364",
    "sg:province":"MA",
    "sg:tags":[
        "magician"
    ],
    "wof:name":"Ed The Wizard",
    "wof:placetype":"venue"
},
  "geometry": {"coordinates":[-72.317189,42.592614],"type":"Point"}
}