{
  "type": "Feature",
  "properties": {
    "addr:full": "33 Commercial Dr Hampden MA 01036",
    "addr:housenumber": "33",
    "addr:postcode": "01036",
    "addr:street": "Commercial Dr",
    "iso:country": "US",
    "sg:address": "33 Commercial Dr",
    "sg:city": "Hampden",
    "sg:classifiers": [
      {
        "category": "Building \u0026 Trades",
        "subcategory": "Construction",
        "type": "Services"
      }
    ],
    "sg:phone": "+1 413 566 3629",
    "sg:postcode": "01036",
    "sg:province": "MA",
    "sg:tags": [
      "general",
      "contractor"
    ],
    "wof:name": "Netco Construction Corp",
    "wof:placetype": "venue"
  },
  "geometry": {"coordinates":[-72.450743,42.060451],"type":"Point"}
}
