{
  "type": "Feature",
  "properties": {
    "addr:full": "5 Williams Way Bellingham MA 02019",
    "addr:housenumber": "5",
    "addr:postcode": "02019",
    "addr:street": "Williams Way",
    "iso:country": "US",
    "sg:address": "5 Williams Way",
    "sg:city": "Bellingham",
    "sg:classifiers": [
      {
        "category": "Building \u0026 Trades",
        "subcategory": "Construction",
        "type": "Services"
      }
    ],
    "sg:phone": "+1 508 966 4800",
    "sg:postcode": "02019",
    "sg:province": "MA",
    "sg:tags": [
      "spray",
      "painting",
      "finishing"
    ],
    "sg:website": "www.consolidatedcoating.com",
    "wof:name": "Consolidated Coatings Corp",
    "wof:placetype": "venue"
  },
  "geometry": {"coordinates":[-71.496482,42.087393],"type":"Point"}
}
