{
  "type": "Feature",
  "properties": {
    "iso:country":"US",
    "sg:address":"15 Knight Rd",
    "sg:city":"Framingham",
    "sg:classifiers":[
        {
            "category":"Retail",
            "subcategory":"Repair Shop",
            "type":"Services"
        }
    ],
    "sg:phone":"+1   ",
    "sg:postcode":"01701",
    "sg:province":"MA",
    "sg:tags":[
        "industrial",
        "electrical"
    ],
    "wof:name":"Computer Electronics Unlimited",
    "wof:placetype":"venue"
},
  "geometry": {"coordinates":[-71.453694,42.305776],"type":"Point"}
}