{
  "type": "Feature",
  "properties": {
    "addr:full":"1205 Hyde Park Ave Hyde Park MA 02136",
    "addr:housenumber":"1205",
    "addr:postcode":"02136",
    "addr:street":"Hyde Park Ave",
    "iso:country":"US",
    "sg:address":"1205 Hyde Park Ave",
    "sg:city":"Hyde Park",
    "sg:classifiers":[
        {
            "category":"Health Services",
            "subcategory":"Health Practitioner",
            "type":"Services"
        }
    ],
    "sg:phone":"+1 617 361 9700",
    "sg:postcode":"02136",
    "sg:province":"MA",
    "sg:tags":[
        "therapist",
        "physical"
    ],
    "wof:name":"Procare Physical Therapy",
    "wof:placetype":"venue"
},
  "geometry": {"coordinates":[-71.12379799999999,42.257501],"type":"Point"}
}