{
  "type": "Feature",
  "properties": {
    "addr:full": "184 Spring St Florence MA 01062",
    "addr:housenumber": "184",
    "addr:postcode": "01062",
    "addr:street": "Spring St",
    "iso:country": "US",
    "sg:address": "184 Spring St",
    "sg:city": "Florence",
    "sg:classifiers": [
      {
        "category": "Building \u0026 Trades",
        "subcategory": "Construction",
        "type": "Services"
      }
    ],
    "sg:phone": "+1   ",
    "sg:postcode": "01062",
    "sg:province": "MA",
    "sg:tags": [
      "contractor"
    ],
    "wof:name": "Chimney Saver",
    "wof:placetype": "venue"
  },
  "geometry": {"coordinates":[-72.687547,42.335304],"type":"Point"}
}
