{
  "type": "Feature",
  "properties": {
    "iso:country":"US",
    "sg:address":"184 Spring St",
    "sg:city":"Florence",
    "sg:classifiers":[
        {
            "category":"Building & Trades",
            "subcategory":"Construction",
            "type":"Services"
        }
    ],
    "sg:phone":"+1   ",
    "sg:postcode":"01062",
    "sg:province":"MA",
    "sg:tags":[
        "contractor"
    ],
    "wof:name":"Chimney Saver",
    "wof:placetype":"venue"
},
  "geometry": {"coordinates":[-72.687547,42.335304],"type":"Point"}
}