{
  "type": "Feature",
  "properties": {
    "iso:country":"US",
    "sg:address":"600 Turnpike St",
    "sg:city":"South Easton",
    "sg:classifiers":[
        {
            "category":"Freight",
            "type":"Transportation"
        }
    ],
    "sg:phone":"+1 508 238 1236",
    "sg:postcode":"02375",
    "sg:province":"MA",
    "wof:name":"Lilly Transportation",
    "wof:placetype":"venue"
},
  "geometry": {"coordinates":[-71.067269,41.997965],"type":"Point"}
}