{
  "type": "Feature",
  "properties": {
    "addr:full": "600 Turnpike St South Easton MA 02375",
    "addr:housenumber": "600",
    "addr:postcode": "02375",
    "addr:street": "Turnpike St",
    "iso:country": "US",
    "sg:address": "600 Turnpike St",
    "sg:city": "South Easton",
    "sg:classifiers": [
      {
        "category": "Freight",
        "type": "Transportation"
      }
    ],
    "sg:phone": "+1 508 238 1236",
    "sg:postcode": "02375",
    "sg:province": "MA",
    "wof:name": "Lilly Transportation",
    "wof:placetype": "venue"
  },
  "geometry": {"coordinates":[-71.067269,41.997965],"type":"Point"}
}
