{
  "type": "Feature",
  "properties": {
    "iso:country":"US",
    "sg:address":"44 Francis Dr",
    "sg:city":"Reading",
    "sg:classifiers":[
        {
            "category":"Organizations",
            "subcategory":"Religious Organization",
            "type":"Services"
        }
    ],
    "sg:phone":"+1   ",
    "sg:postcode":"01867",
    "sg:province":"MA",
    "wof:name":"Embroiderers Guild of AME",
    "wof:placetype":"venue"
},
  "geometry": {"coordinates":[-71.102383,42.531704],"type":"Point"}
}