{
  "type": "Feature",
  "properties": {
    "addr:full":"37 Thelma Rd Framingham MA 01702",
    "addr:housenumber":"37",
    "addr:postcode":"01702",
    "addr:street":"Thelma Rd",
    "iso:country":"US",
    "sg:address":"37 Thelma Rd",
    "sg:city":"Framingham",
    "sg:classifiers":[
        {
            "category":"Freight",
            "type":"Transportation"
        }
    ],
    "sg:phone":"+1   ",
    "sg:postcode":"01702",
    "sg:province":"MA",
    "sg:tags":[
        "local",
        "trucking"
    ],
    "wof:name":"World One Logistics",
    "wof:placetype":"venue"
},
  "geometry": {"coordinates":[-71.40702,42.291289],"type":"Point"}
}