{
  "type": "Feature",
  "properties": {
    "addr:full":"1923 Massachusetts Ave Cambridge MA 02140",
    "addr:housenumber":"1923",
    "addr:postcode":"02140",
    "addr:street":"Massachusetts Ave",
    "iso:country":"US",
    "sg:address":"1923 Massachusetts Ave",
    "sg:city":"Cambridge",
    "sg:classifiers":[
        {
            "category":"Restaurant",
            "type":"Food & Drink"
        }
    ],
    "sg:phone":"+1 617 354 0670",
    "sg:postcode":"02140",
    "sg:province":"MA",
    "sg:tags":[
        "italian"
    ],
    "wof:name":"Falzones",
    "wof:placetype":"venue"
},
  "geometry": {"coordinates":[-71.11986899999999,42.389323],"type":"Point"}
}