{
  "type": "Feature",
  "properties": {
    "addr:full":"60 Nicholas Rd Framingham MA 01701",
    "addr:housenumber":"60",
    "addr:postcode":"01701",
    "addr:street":"Nicholas Rd",
    "iso:country":"US",
    "sg:address":"60 Nicholas Rd",
    "sg:city":"Framingham",
    "sg:classifiers":[
        {
            "category":"Manufacturing",
            "subcategory":"Printing",
            "type":"Manufacturing & Wholesale Goods"
        }
    ],
    "sg:phone":"+1 508 405 2296",
    "sg:postcode":"01701",
    "sg:province":"MA",
    "sg:tags":[
        "printer"
    ],
    "wof:name":"Boston Print Solutions",
    "wof:placetype":"venue"
},
  "geometry": {"coordinates":[-71.40571799999999,42.328863],"type":"Point"}
}