{
  "type": "Feature",
  "properties": {
    "iso:country":"US",
    "sg:address":"15 New England Executive Park",
    "sg:city":"Burlington",
    "sg:classifiers":[
        {
            "category":"Real Estate",
            "subcategory":"Real Estate Services",
            "type":"Services"
        }
    ],
    "sg:phone":"+1 781 685 4600",
    "sg:postcode":"01803",
    "sg:province":"MA",
    "sg:website":"www.regus.com",
    "wof:name":"Regus Business Center",
    "wof:placetype":"venue"
},
  "geometry": {"coordinates":[-71.2092,42.4852],"type":"Point"}
}