{
  "type": "Feature",
  "properties": {
    "iso:country":"US",
    "sg:address":"251 Main St",
    "sg:city":"Great Barrington",
    "sg:classifiers":[
        {
            "category":"Social Services",
            "subcategory":"Child Care",
            "type":"Services"
        }
    ],
    "sg:phone":"+1 413 528 2127",
    "sg:postcode":"01230",
    "sg:province":"MA",
    "sg:tags":[
        "kindergarten",
        "academic",
        "school"
    ],
    "wof:name":"Great Barrington Co-Op Nursery",
    "wof:placetype":"venue"
},
  "geometry": {"coordinates":[-73.36122,42.19562],"type":"Point"}
}