{
  "type": "Feature",
  "properties": {
    "addr:full": "6 Walker St Lenox MA 01240",
    "addr:housenumber": "6",
    "addr:postcode": "01240",
    "addr:street": "Walker St",
    "iso:country": "US",
    "sg:address": "6 Walker St",
    "sg:city": "Lenox",
    "sg:classifiers": [
      {
        "category": "Government",
        "subcategory": "Office",
        "type": "Public Place"
      }
    ],
    "sg:phone": "+1 413 637 5502",
    "sg:postcode": "01240",
    "sg:province": "MA",
    "sg:tags": [
      "city",
      "taxation"
    ],
    "wof:name": "Lenox Town Assessors Office",
    "wof:placetype": "venue"
  },
  "geometry": {"coordinates":[-73.284889,42.356836],"type":"Point"}
}
