{
  "type": "Feature",
  "properties": {
    "addr:full": "421 S Broadway Lawrence MA 01843",
    "addr:housenumber": "421",
    "addr:postcode": "01843",
    "addr:street": "S Broadway",
    "iso:country": "US",
    "sg:address": "421 S Broadway",
    "sg:city": "Lawrence",
    "sg:classifiers": [
      {
        "category": "Food \u0026 Beverages",
        "subcategory": "Liquor \u0026 Beverages",
        "type": "Retail Goods"
      }
    ],
    "sg:phone": "+1 978 683 8031",
    "sg:postcode": "01843",
    "sg:province": "MA",
    "wof:name": "Mt Vernon Liquors",
    "wof:placetype": "venue"
  },
  "geometry": {"coordinates":[-71.156228,42.685665],"type":"Point"}
}
