{
  "type": "Feature",
  "properties": {
    "addr:full": "1573 Main St Brewster MA 02631",
    "addr:housenumber": "1573",
    "addr:postcode": "02631",
    "addr:street": "Main St",
    "iso:country": "US",
    "sg:address": "1573 Main St",
    "sg:city": "Brewster",
    "sg:classifiers": [
      {
        "category": "Organizations",
        "subcategory": "Religious Organization",
        "type": "Services"
      }
    ],
    "sg:phone": "+1 508 896 2550",
    "sg:postcode": "02631",
    "sg:province": "MA",
    "sg:tags": [
      "church"
    ],
    "wof:name": "Anglican Church-The Rsrrctn",
    "wof:placetype": "venue"
  },
  "geometry": {"coordinates":[-70.092294,41.75545],"type":"Point"}
}
