{
  "type": "Feature",
  "properties": {
    "addr:full": "39 Puritan Rd Buzzards Bay MA 02532",
    "addr:housenumber": "39",
    "addr:postcode": "02532",
    "addr:street": "Puritan Rd",
    "iso:country": "US",
    "sg:address": "39 Puritan Rd",
    "sg:city": "Buzzards Bay",
    "sg:classifiers": [
      {
        "category": "Building \u0026 Trades",
        "subcategory": "Construction",
        "type": "Services"
      }
    ],
    "sg:phone": "+1 508 759 5132",
    "sg:postcode": "02532",
    "sg:province": "MA",
    "sg:tags": [
      "home",
      "improvement"
    ],
    "wof:name": "Bruce Wenzel's General Contr",
    "wof:placetype": "venue"
  },
  "geometry": {"coordinates":[-70.614123,41.75136],"type":"Point"}
}
