{
  "type": "Feature",
  "properties": {
    "iso:country":"US",
    "sg:address":"39 Puritan Rd",
    "sg:city":"Buzzards Bay",
    "sg:classifiers":[
        {
            "category":"Building & Trades",
            "subcategory":"Construction",
            "type":"Services"
        }
    ],
    "sg:phone":"+1 508 759 5132",
    "sg:postcode":"02532",
    "sg:province":"MA",
    "sg:tags":[
        "home",
        "improvement"
    ],
    "wof:name":"Bruce Wenzel's General Contr",
    "wof:placetype":"venue"
},
  "geometry": {"coordinates":[-70.61412300000001,41.75136],"type":"Point"}
}