{
  "type": "Feature",
  "properties": {
    "addr:full":"295 Huntington Ave Ste 209 Boston MA 02115",
    "addr:housenumber":"295",
    "addr:postcode":"02115",
    "addr:street":"Huntington Ave Ste 209",
    "iso:country":"US",
    "sg:address":"295 Huntington Ave Ste 209",
    "sg:city":"Boston",
    "sg:classifiers":[
        {
            "category":"Communications",
            "type":"Services"
        }
    ],
    "sg:phone":"+1 617 652 0545",
    "sg:postcode":"02115",
    "sg:province":"MA",
    "sg:tags":[
        "web",
        "design"
    ],
    "sg:website":"www.williamgrand.com/",
    "wof:name":"William Grand Associates - Interactive Application Development",
    "wof:placetype":"venue"
},
  "geometry": {"coordinates":[-71.08680200000001,42.341373],"type":"Point"}
}