{
  "type": "Feature",
  "properties": {
    "addr:full":"704 E Broadway Boston MA 02127",
    "addr:housenumber":"704",
    "addr:postcode":"02127",
    "addr:street":"E Broadway",
    "iso:country":"US",
    "sg:address":"704 E Broadway",
    "sg:city":"Boston",
    "sg:classifiers":[
        {
            "category":"Restaurant",
            "type":"Food & Drink"
        }
    ],
    "sg:phone":"+1 617 268 3553",
    "sg:postcode":"02127",
    "sg:province":"MA",
    "sg:tags":[
        "breakfast",
        "eating",
        "brunch"
    ],
    "wof:name":"Cranberry Cafe",
    "wof:placetype":"venue"
},
  "geometry": {"coordinates":[-71.037003,42.335499],"type":"Point"}
}