{
  "type": "Feature",
  "properties": {
    "iso:country":"US",
    "sg:address":"115 Lafayette St",
    "sg:city":"Salem",
    "sg:classifiers":[
        {
            "category":"Shopping",
            "subcategory":"Books",
            "type":"Retail Goods"
        }
    ],
    "sg:phone":"+1 978 745 0919",
    "sg:postcode":"01970",
    "sg:province":"MA",
    "sg:tags":[
        "store"
    ],
    "wof:name":"Botanica San Miguel",
    "wof:placetype":"venue"
},
  "geometry": {"coordinates":[-70.893112,42.517966],"type":"Point"}
}