{
  "type": "Feature",
  "properties": {
    "iso:country":"US",
    "sg:address":"15 Cottage St",
    "sg:city":"Norwood",
    "sg:classifiers":[
        {
            "category":"Personal",
            "type":"Services"
        }
    ],
    "sg:phone":"+1 781 769 6063",
    "sg:postcode":"02062",
    "sg:province":"MA",
    "sg:tags":[
        "electrolysis"
    ],
    "wof:name":"Louise A Devin",
    "wof:placetype":"venue"
},
  "geometry": {"coordinates":[-71.201948,42.19412],"type":"Point"}
}