{
  "type": "Feature",
  "properties": {
    "addr:full": "76 Powder Mill Rd Maynard MA 01754",
    "addr:housenumber": "76",
    "addr:postcode": "01754",
    "addr:street": "Powder Mill Rd",
    "iso:country": "US",
    "sg:address": "76 Powder Mill Rd",
    "sg:city": "Maynard",
    "sg:classifiers": [
      {
        "category": "Retail",
        "subcategory": "Auto Repair",
        "type": "Services"
      }
    ],
    "sg:phone": "+1 978 897 8168",
    "sg:postcode": "01754",
    "sg:province": "MA",
    "sg:tags": [
      "body",
      "automobile",
      "painting"
    ],
    "wof:name": "Quinns Auto Body",
    "wof:placetype": "venue"
  },
  "geometry": {"coordinates":[-71.443012,42.437076],"type":"Point"}
}
