{
  "type": "Feature",
  "properties": {
    "addr:full": "22 Beacon St Marblehead MA 01945",
    "addr:housenumber": "22",
    "addr:postcode": "01945",
    "addr:street": "Beacon St",
    "iso:country": "US",
    "sg:address": "22 Beacon St",
    "sg:city": "Marblehead",
    "sg:classifiers": [
      {
        "category": "Professional",
        "subcategory": "Art Services",
        "type": "Services"
      }
    ],
    "sg:phone": "+1 781 639 7801",
    "sg:postcode": "01945",
    "sg:province": "MA",
    "sg:tags": [
      "graphic",
      "designer"
    ],
    "wof:name": "Nimbus Creatif",
    "wof:placetype": "venue"
  },
  "geometry": {"coordinates":[-70.846329,42.512823],"type":"Point"}
}
