{
  "type": "Feature",
  "properties": {
    "iso:country":"US",
    "sg:address":"19 Rock Brook Way",
    "sg:city":"Boxford",
    "sg:classifiers":[
        {
            "category":"Banks & Credit Unions",
            "subcategory":"Bank",
            "type":"Services"
        }
    ],
    "sg:phone":"+1 978 621 6171",
    "sg:postcode":"01921",
    "sg:province":"MA",
    "sg:tags":[
        "loan",
        "real estate"
    ],
    "wof:name":"Allied Home Mortgage Capital",
    "wof:placetype":"venue"
},
  "geometry": {"coordinates":[-71.04055099999999,42.709483],"type":"Point"}
}