{
  "type": "Feature",
  "properties": {
    "addr:full": "183 South St Southbridge MA 01550",
    "addr:housenumber": "183",
    "addr:postcode": "01550",
    "addr:street": "South St",
    "iso:country": "US",
    "sg:address": "183 South St",
    "sg:city": "Southbridge",
    "sg:classifiers": [
      {
        "category": "Organizations",
        "subcategory": "Religious Organization",
        "type": "Services"
      }
    ],
    "sg:phone": "+1 508 764 3073",
    "sg:postcode": "01550",
    "sg:province": "MA",
    "sg:tags": [
      "church"
    ],
    "wof:name": "Recotry Holy Trinity",
    "wof:placetype": "venue"
  },
  "geometry": {"coordinates":[-72.044666,42.076635],"type":"Point"}
}
