{
  "type": "Feature",
  "properties": {
    "iso:country":"US",
    "sg:address":"739 Central St",
    "sg:city":"Leominster",
    "sg:classifiers":[
        {
            "category":"Food & Beverages",
            "subcategory":"Meat & Fish",
            "type":"Retail Goods"
        }
    ],
    "sg:phone":"+1 978 534 9998",
    "sg:postcode":"01453",
    "sg:province":"MA",
    "wof:name":"Central Street Meats & Deli",
    "wof:placetype":"venue"
},
  "geometry": {"coordinates":[-71.7465,42.502581],"type":"Point"}
}