{
  "type": "Feature",
  "properties": {
    "addr:full": "349 Trapelo Rd Belmont MA 02478",
    "addr:housenumber": "349",
    "addr:postcode": "02478",
    "addr:street": "Trapelo Rd",
    "iso:country": "US",
    "sg:address": "349 Trapelo Rd",
    "sg:city": "Belmont",
    "sg:classifiers": [
      {
        "category": "Real Estate",
        "subcategory": "Real Estate Agent",
        "type": "Services"
      }
    ],
    "sg:phone": "+1 617 489 1133",
    "sg:postcode": "02478",
    "sg:province": "MA",
    "wof:name": "Gardner Realty",
    "wof:placetype": "venue"
  },
  "geometry": {"coordinates":[-71.183146,42.385194],"type":"Point"}
}
