{
  "type": "Feature",
  "properties": {
    "addr:full": "1238 Chestnut St Newton MA 02464",
    "addr:housenumber": "1238",
    "addr:postcode": "02464",
    "addr:street": "Chestnut St",
    "iso:country": "US",
    "sg:address": "1238 Chestnut St",
    "sg:city": "Newton",
    "sg:classifiers": [
      {
        "category": "Home \u0026 Garden",
        "subcategory": "Building Materials",
        "type": "Retail Goods"
      }
    ],
    "sg:phone": "+1 617 244 0141",
    "sg:postcode": "02464",
    "sg:province": "MA",
    "sg:tags": [
      "glass",
      "leaded"
    ],
    "wof:name": "Artigiano Stained Glass",
    "wof:placetype": "venue"
  },
  "geometry": {"coordinates":[-71.219506,42.309895],"type":"Point"}
}
