{
  "type": "Feature",
  "properties": {
    "iso:country":"US",
    "sg:address":"1407 Boston Providence Tpke",
    "sg:city":"Norwood",
    "sg:classifiers":[
        {
            "category":"Autos & Motor Vehicles",
            "subcategory":"Fuel & Gas Station",
            "type":"Retail Goods"
        }
    ],
    "sg:phone":"+1 781 762 9537",
    "sg:postcode":"02062",
    "sg:province":"MA",
    "wof:name":"Best Petroleum Co Inc",
    "wof:placetype":"venue"
},
  "geometry": {"coordinates":[-71.19928899999999,42.163779],"type":"Point"}
}