{
  "type": "Feature",
  "properties": {
    "addr:full": "1407 Boston Providence Tpke Norwood MA 02062",
    "addr:housenumber": "1407",
    "addr:postcode": "02062",
    "addr:street": "Boston Providence Tpke",
    "iso:country": "US",
    "sg:address": "1407 Boston Providence Tpke",
    "sg:city": "Norwood",
    "sg:classifiers": [
      {
        "category": "Autos \u0026 Motor Vehicles",
        "subcategory": "Fuel \u0026 Gas Station",
        "type": "Retail Goods"
      }
    ],
    "sg:phone": "+1 781 762 9537",
    "sg:postcode": "02062",
    "sg:province": "MA",
    "wof:name": "Best Petroleum Co Inc",
    "wof:placetype": "venue"
  },
  "geometry": {"coordinates":[-71.199289,42.163779],"type":"Point"}
}
