{
  "type": "Feature",
  "properties": {
    "iso:country":"US",
    "sg:address":"116 Pleasant Valley St",
    "sg:city":"Methuen",
    "sg:classifiers":[
        {
            "category":"Personal",
            "type":"Services"
        }
    ],
    "sg:phone":"+1 978 975 0660",
    "sg:postcode":"01844",
    "sg:province":"MA",
    "sg:tags":[
        "program",
        "physical",
        "exercise",
        "fitness"
    ],
    "wof:name":"Gold's Gym",
    "wof:placetype":"venue"
},
  "geometry": {"coordinates":[-71.145573,42.744339],"type":"Point"}
}