{
  "type": "Feature",
  "properties": {
    "addr:full":"470 Atlantic Ave Ste Chelsea MA 02150",
    "addr:housenumber":"470",
    "addr:postcode":"02150",
    "addr:street":"Atlantic Ave Ste",
    "iso:country":"US",
    "sg:address":"470 Atlantic Ave Ste",
    "sg:city":"Chelsea",
    "sg:classifiers":[
        {
            "category":"Professional",
            "subcategory":"Lawyer & Legal Services",
            "type":"Services"
        }
    ],
    "sg:phone":"+1 617 289 9200",
    "sg:postcode":"02150",
    "sg:province":"MA",
    "wof:name":"Duane Morris Llp",
    "wof:placetype":"venue"
},
  "geometry": {"coordinates":[-71.03449999999999,42.398102],"type":"Point"}
}