{
  "type": "Feature",
  "properties": {
    "iso:country":"US",
    "sg:address":"320 W Main St",
    "sg:city":"Norton",
    "sg:classifiers":[
        {
            "category":"Personal",
            "type":"Services"
        }
    ],
    "sg:phone":"+1 508 222 4622",
    "sg:postcode":"02766",
    "sg:province":"MA",
    "sg:tags":[
        "hair",
        "electrolysis",
        "removal"
    ],
    "wof:name":"Adonis Electrolysis",
    "wof:placetype":"venue"
},
  "geometry": {"coordinates":[-71.22615999999999,41.950908],"type":"Point"}
}