{
  "type": "Feature",
  "properties": {
    "addr:full": "730 Main St Boylston MA 01505",
    "addr:housenumber": "730",
    "addr:postcode": "01505",
    "addr:street": "Main St",
    "iso:country": "US",
    "ovtr:label": "Jazziak's Dance School, 730 Main St Boylston MA US",
    "ovtr:similarity": 2.2417359352111816,
    "sg:address": "730 Main St",
    "sg:city": "Boylston",
    "sg:classifiers": [
      {
        "category": "Education",
        "subcategory": "Dance Studio",
        "type": "Public Place"
      }
    ],
    "sg:phone": "+1 508 869 0026",
    "sg:postcode": "01505",
    "sg:province": "MA",
    "sg:tags": [
      "instruction",
      "dancing"
    ],
    "wof:name": "Jazziak's Dance School",
    "wof:placetype": "venue"
  },
  "geometry": {"coordinates":[-71.73256,42.357353],"type":"Point"}
}
