{
  "type": "Feature",
  "properties": {
    "iso:country":"US",
    "sg:address":"730 Main St",
    "sg:city":"Boylston",
    "sg:classifiers":[
        {
            "category":"Education",
            "subcategory":"Dance Studio",
            "type":"Public Place"
        }
    ],
    "sg:phone":"+1 508 869 0026",
    "sg:postcode":"01505",
    "sg:province":"MA",
    "sg:tags":[
        "instruction",
        "dancing"
    ],
    "wof:name":"Jazziak's Dance School",
    "wof:placetype":"venue"
},
  "geometry": {"coordinates":[-71.73256000000001,42.357353],"type":"Point"}
}