{
  "type": "Feature",
  "properties": {
    "iso:country":"US",
    "sg:address":"2041 Riverdale St",
    "sg:city":"West Springfield",
    "sg:classifiers":[
        {
            "category":"Travel",
            "subcategory":"Hotels & Motels",
            "type":"Entertainment"
        }
    ],
    "sg:phone":"+1 413 736 5773",
    "sg:postcode":"01089",
    "sg:province":"MA",
    "wof:name":"Welcome Inn",
    "wof:placetype":"venue"
},
  "geometry": {"coordinates":[-72.633026,42.159034],"type":"Point"}
}