{
  "type": "Feature",
  "properties": {
    "addr:full": "2041 Riverdale St West Springfield MA 01089",
    "addr:housenumber": "2041",
    "addr:postcode": "01089",
    "addr:street": "Riverdale St",
    "iso:country": "US",
    "ovtr:label": "Welcome Inn, 2041 Riverdale St West Springfield MA US",
    "ovtr:similarity": 2.7103960514068604,
    "sg:address": "2041 Riverdale St",
    "sg:city": "West Springfield",
    "sg:classifiers": [
      {
        "category": "Travel",
        "subcategory": "Hotels \u0026 Motels",
        "type": "Entertainment"
      }
    ],
    "sg:phone": "+1 413 736 5773",
    "sg:postcode": "01089",
    "sg:province": "MA",
    "wof:name": "Welcome Inn",
    "wof:placetype": "venue"
  },
  "geometry": {"coordinates":[-72.633026,42.159034],"type":"Point"}
}
