{
  "type": "Feature",
  "properties": {
    "addr:full": "21 Hunters Rd Boxford MA 01921",
    "addr:housenumber": "21",
    "addr:postcode": "01921",
    "addr:street": "Hunters Rd",
    "iso:country": "US",
    "sg:address": "21 Hunters Rd",
    "sg:city": "Boxford",
    "sg:classifiers": [
      {
        "category": "Building \u0026 Trades",
        "subcategory": "Construction",
        "type": "Services"
      }
    ],
    "sg:phone": "+1 781 937 5666",
    "sg:postcode": "01921",
    "sg:province": "MA",
    "sg:tags": [
      "concrete",
      "contractor"
    ],
    "wof:name": "Accurate Concrete Cutting Inc",
    "wof:placetype": "venue"
  },
  "geometry": {"coordinates":[-70.968263,42.66525],"type":"Point"}
}
