{
  "type": "Feature",
  "properties": {
    "iso:country":"US",
    "sg:address":"21 Hunters Rd",
    "sg:city":"Boxford",
    "sg:classifiers":[
        {
            "category":"Building & Trades",
            "subcategory":"Construction",
            "type":"Services"
        }
    ],
    "sg:phone":"+1 781 937 5666",
    "sg:postcode":"01921",
    "sg:province":"MA",
    "sg:tags":[
        "concrete",
        "contractor"
    ],
    "wof:name":"Accurate Concrete Cutting Inc",
    "wof:placetype":"venue"
},
  "geometry": {"coordinates":[-70.96826299999999,42.66525],"type":"Point"}
}