{
  "type": "Feature",
  "properties": {
    "addr:full": "10 Elm St Salisbury MA 01952",
    "addr:housenumber": "10",
    "addr:postcode": "01952",
    "addr:street": "Elm St",
    "iso:country": "US",
    "sg:address": "10 Elm St",
    "sg:city": "Salisbury",
    "sg:classifiers": [
      {
        "category": "Insurance",
        "subcategory": "Insurance Agent",
        "type": "Services"
      }
    ],
    "sg:phone": "+1 978 462 4822",
    "sg:postcode": "01952",
    "sg:province": "MA",
    "wof:name": "Salisbury Insurance Inc",
    "wof:placetype": "venue"
  },
  "geometry": {"coordinates":[-70.862704,42.839515],"type":"Point"}
}
