{
  "type": "Feature",
  "properties": {
    "iso:country":"US",
    "sg:address":"10 Elm St",
    "sg:city":"Salisbury",
    "sg:classifiers":[
        {
            "category":"Insurance",
            "subcategory":"Insurance Agent",
            "type":"Services"
        }
    ],
    "sg:phone":"+1 978 462 4822",
    "sg:postcode":"01952",
    "sg:province":"MA",
    "wof:name":"Salisbury Insurance Inc",
    "wof:placetype":"venue"
},
  "geometry": {"coordinates":[-70.86270399999999,42.839515],"type":"Point"}
}