{
  "type": "Feature",
  "properties": {
    "iso:country":"US",
    "sg:address":"100 East St",
    "sg:city":"Hadley",
    "sg:classifiers":[
        {
            "category":"Banks & Credit Unions",
            "subcategory":"Bank",
            "type":"Services"
        }
    ],
    "sg:phone":"+1 413 527 4111",
    "sg:postcode":"01035",
    "sg:province":"MA",
    "wof:name":"Easthampton Savings Bank",
    "wof:placetype":"venue"
},
  "geometry": {"coordinates":[-72.581779,42.341976],"type":"Point"}
}