{
  "type": "Feature",
  "properties": {
    "addr:full": "252 Humphrey St Swampscott MA 01907",
    "addr:housenumber": "252",
    "addr:postcode": "01907",
    "addr:street": "Humphrey St",
    "iso:country": "US",
    "sg:address": "252 Humphrey St",
    "sg:city": "Swampscott",
    "sg:classifiers": [
      {
        "category": "Retail",
        "subcategory": "Repair Shop",
        "type": "Services"
      }
    ],
    "sg:phone": "+1 781 346 6754",
    "sg:postcode": "01907",
    "sg:province": "MA",
    "sg:tags": [
      "lock",
      "locksmith"
    ],
    "wof:name": "7 Day Always Locksmith",
    "wof:placetype": "venue"
  },
  "geometry": {"coordinates":[-70.913524,42.467227],"type":"Point"}
}
