{
  "type": "Feature",
  "properties": {
    "addr:full": "296 N Beacon Street Brighton MA 02135",
    "addr:housenumber": "296",
    "addr:postcode": "02135",
    "addr:street": "N Beacon Street",
    "iso:country": "US",
    "sg:address": "296 N Beacon Street",
    "sg:city": "Brighton",
    "sg:classifiers": [
      {
        "category": "Retail",
        "subcategory": "Auto Repair",
        "type": "Services"
      }
    ],
    "sg:phone": "+1 617 787 1187",
    "sg:postcode": "02135",
    "sg:province": "MA",
    "wof:name": "Samuels Jaguar Motor Ltd",
    "wof:placetype": "venue"
  },
  "geometry": {"coordinates":[-71.157652,42.358432],"type":"Point"}
}
