{
  "type": "Feature",
  "properties": {
    "addr:full": "32 Woodland Rd Malden MA 02148",
    "addr:housenumber": "32",
    "addr:postcode": "02148",
    "addr:street": "Woodland Rd",
    "iso:country": "US",
    "sg:address": "32 Woodland Rd",
    "sg:city": "Malden",
    "sg:classifiers": [
      {
        "category": "Utilities",
        "subcategory": "Fuel Oil \u0026 Lpg",
        "type": "Services"
      }
    ],
    "sg:phone": "+1 781 322 4505",
    "sg:postcode": "02148",
    "sg:province": "MA",
    "sg:tags": [
      "oils-fuel"
    ],
    "wof:name": "Walter Hurley Oil Co",
    "wof:placetype": "venue"
  },
  "geometry": {"coordinates":[-71.080161,42.433042],"type":"Point"}
}
