{
  "type": "Feature",
  "properties": {
    "addr:full":"68 Main St Falmouth MA 02540",
    "addr:housenumber":"68",
    "addr:postcode":"02540",
    "addr:street":"Main St",
    "iso:country":"US",
    "sg:address":"68 Main St",
    "sg:city":"Falmouth",
    "sg:classifiers":[
        {
            "category":"Place Of Worship",
            "subcategory":"Church",
            "type":"Public Place"
        },
        {
            "category":"Place Of Worship",
            "type":"Public Place"
        },
        {
            "category":"Organizations",
            "subcategory":"Religious Organization",
            "type":"Services"
        }
    ],
    "sg:phone":"+1 508 548 3700",
    "sg:postcode":"02540",
    "sg:province":"MA",
    "sg:tags":[
        "churches-interdenominational",
        "churches-various",
        "denomination"
    ],
    "wof:name":"First Congregstional Church",
    "wof:placetype":"venue"
},
  "geometry": {"coordinates":[-70.617001,41.552474],"type":"Point"}
}