{
  "type": "Feature",
  "properties": {
    "iso:country":"US",
    "sg:address":"114 Potter Pond",
    "sg:city":"Lexington",
    "sg:classifiers":[
        {
            "category":"Health Services",
            "subcategory":"Clinic",
            "type":"Services"
        }
    ],
    "sg:phone":"+1 781 862 7495",
    "sg:postcode":"02421",
    "sg:province":"MA",
    "sg:tags":[
        "welfare"
    ],
    "wof:name":"U Mass Correctional Health",
    "wof:placetype":"venue"
},
  "geometry": {"coordinates":[-71.215557,42.41179],"type":"Point"}
}