{
  "type": "Feature",
  "properties": {
    "addr:full":"189 Winthrop St Medford MA 02155",
    "addr:housenumber":"189",
    "addr:postcode":"02155",
    "addr:street":"Winthrop St",
    "iso:country":"US",
    "sg:address":"189 Winthrop St",
    "sg:city":"Medford",
    "sg:classifiers":[
        {
            "category":"Building & Trades",
            "subcategory":"Landscaping Services",
            "type":"Services"
        }
    ],
    "sg:phone":"+1   ",
    "sg:postcode":"02155",
    "sg:province":"MA",
    "wof:name":"Total Landscape Care",
    "wof:placetype":"venue"
},
  "geometry": {"coordinates":[-71.117924,42.41739],"type":"Point"}
}