{
  "type": "Feature",
  "properties": {
    "iso:country":"US",
    "sg:address":"18 Mcintosh Dr",
    "sg:city":"Taunton",
    "sg:classifiers":[
        {
            "category":"Travel",
            "subcategory":"Travel Agent",
            "type":"Entertainment"
        }
    ],
    "sg:phone":"+1 508 822 0849",
    "sg:postcode":"02780",
    "sg:province":"MA",
    "sg:tags":[
        "agency",
        "services-commercial"
    ],
    "wof:name":"Best Escape With Us Travel",
    "wof:placetype":"venue"
},
  "geometry": {"coordinates":[-71.12647200000001,41.893419],"type":"Point"}
}