{
  "type": "Feature",
  "properties": {
    "addr:full": "2760 Main St Springfield MA 01107",
    "addr:housenumber": "2760",
    "addr:postcode": "01107",
    "addr:street": "Main St",
    "iso:country": "US",
    "sg:address": "2760 Main St",
    "sg:city": "Springfield",
    "sg:classifiers": [
      {
        "category": "Wholesale",
        "subcategory": "Groceries",
        "type": "Manufacturing \u0026 Wholesale Goods"
      }
    ],
    "sg:phone": "+1 413 788 2932",
    "sg:postcode": "01107",
    "sg:province": "MA",
    "sg:tags": [
      "grocer"
    ],
    "wof:name": "Bobegon Supermarket",
    "wof:placetype": "venue"
  },
  "geometry": {"coordinates":[-72.60676,42.116098],"type":"Point"}
}
