{
  "type": "Feature",
  "properties": {
    "iso:country":"US",
    "sg:address":"2760 Main St",
    "sg:city":"Springfield",
    "sg:classifiers":[
        {
            "category":"Wholesale",
            "subcategory":"Groceries",
            "type":"Manufacturing & Wholesale Goods"
        }
    ],
    "sg:phone":"+1 413 788 2932",
    "sg:postcode":"01107",
    "sg:province":"MA",
    "sg:tags":[
        "grocer"
    ],
    "wof:name":"Bobegon Supermarket",
    "wof:placetype":"venue"
},
  "geometry": {"coordinates":[-72.60675999999999,42.116098],"type":"Point"}
}