{
  "type": "Feature",
  "properties": {
    "iso:country":"US",
    "sg:address":"36 Gainsville Rd",
    "sg:city":"Dedham",
    "sg:classifiers":[
        {
            "category":"Building & Trades",
            "subcategory":"Landscaping Services",
            "type":"Services"
        }
    ],
    "sg:phone":"+1   ",
    "sg:postcode":"02026",
    "sg:province":"MA",
    "sg:tags":[
        "landscape"
    ],
    "wof:name":"Tynne Landscape Design",
    "wof:placetype":"venue"
},
  "geometry": {"coordinates":[-71.149063,42.226762],"type":"Point"}
}