{
  "type": "Feature",
  "properties": {
    "iso:country":"US",
    "sg:address":"241 Broadway",
    "sg:city":"Saugus",
    "sg:classifiers":[
        {
            "category":"Restaurant",
            "type":"Food & Drink"
        }
    ],
    "sg:phone":"+1 781 231 0137",
    "sg:postcode":"01906",
    "sg:province":"MA",
    "sg:website":"www.applebees.com",
    "wof:name":"Applebee's Neighborhood Grill",
    "wof:placetype":"venue"
},
  "geometry": {"coordinates":[-71.01513199999999,42.500539],"type":"Point"}
}