{
  "type": "Feature",
  "properties": {
    "addr:full": "3071 Boston Rd Wilbraham MA 01095",
    "addr:housenumber": "3071",
    "addr:postcode": "01095",
    "addr:street": "Boston Rd",
    "iso:country": "US",
    "sg:address": "3071 Boston Rd",
    "sg:city": "Wilbraham",
    "sg:classifiers": [
      {
        "category": "Building \u0026 Trades",
        "subcategory": "Landscaping Services",
        "type": "Services"
      }
    ],
    "sg:phone": "+1 413 596 2799",
    "sg:postcode": "01095",
    "sg:province": "MA",
    "sg:tags": [
      "landscape",
      "contractor"
    ],
    "wof:name": "Mountain Landscape Inc",
    "wof:placetype": "venue"
  },
  "geometry": {"coordinates":[-72.404991,42.152549],"type":"Point"}
}
