{
  "type": "Feature",
  "properties": {
    "addr:full": "6 Whitman Rd Waltham MA 02453",
    "addr:housenumber": "6",
    "addr:postcode": "02453",
    "addr:street": "Whitman Rd",
    "iso:country": "US",
    "sg:address": "6 Whitman Rd",
    "sg:city": "Waltham",
    "sg:classifiers": [
      {
        "category": "Real Estate",
        "subcategory": "Real Estate Services",
        "type": "Services"
      },
      {
        "category": "Real Estate",
        "subcategory": "Real Estate Operator",
        "type": "Services"
      }
    ],
    "sg:phone": "+1 781 893 3537",
    "sg:postcode": "02453",
    "sg:province": "MA",
    "sg:tags": [
      "management",
      "apartment",
      "condominium"
    ],
    "wof:name": "Garden Grove Condominium Trust",
    "wof:placetype": "venue"
  },
  "geometry": {"coordinates":[-71.207654,42.374512],"type":"Point"}
}
