{
  "type": "Feature",
  "properties": {
    "addr:full": "36 Main St Plymouth MA 02360",
    "addr:housenumber": "36",
    "addr:postcode": "02360",
    "addr:street": "Main St",
    "iso:country": "US",
    "sg:address": "36 Main St",
    "sg:city": "Plymouth",
    "sg:classifiers": [
      {
        "category": "Banks \u0026 Credit Unions",
        "subcategory": "Bank",
        "type": "Services"
      }
    ],
    "sg:phone": "+1 508 746 3300",
    "sg:postcode": "02360",
    "sg:province": "MA",
    "wof:name": "Plymouth Savings Bank",
    "wof:placetype": "venue"
  },
  "geometry": {"coordinates":[-70.662903,41.9548],"type":"Point"}
}
