{
  "type": "Feature",
  "properties": {
    "addr:full": "129 Hathaway Blvd New Bedford MA 02740",
    "addr:housenumber": "129",
    "addr:postcode": "02740",
    "addr:street": "Hathaway Blvd",
    "iso:country": "US",
    "sg:address": "129 Hathaway Blvd",
    "sg:city": "New Bedford",
    "sg:classifiers": [
      {
        "category": "Organizations",
        "subcategory": "Religious Organization",
        "type": "Services"
      }
    ],
    "sg:phone": "+1 508 993 0800",
    "sg:postcode": "02740",
    "sg:province": "MA",
    "sg:tags": [
      "church"
    ],
    "wof:name": "Evangelical Pentecostal Church",
    "wof:placetype": "venue"
  },
  "geometry": {"coordinates":[-70.949181,41.640555],"type":"Point"}
}
