{
  "type": "Feature",
  "properties": {
    "addr:full":"6 Wood St Southborough MA 01772",
    "addr:housenumber":"6",
    "addr:postcode":"01772",
    "addr:street":"Wood St",
    "iso:country":"US",
    "sg:address":"6 Wood St",
    "sg:city":"Southborough",
    "sg:classifiers":[
        {
            "category":"Professional",
            "type":"Services"
        }
    ],
    "sg:phone":"+1   ",
    "sg:postcode":"01772",
    "sg:province":"MA",
    "sg:tags":[
        "entertainment",
        "artist",
        "puppeteer"
    ],
    "wof:name":"Deborah McAdow Costine",
    "wof:placetype":"venue"
},
  "geometry": {"coordinates":[-71.53643,42.265332],"type":"Point"}
}