{
  "type": "Feature",
  "properties": {
    "addr:full":"10 Post Office Sq Boston MA 02109",
    "addr:housenumber":"10",
    "addr:postcode":"02109",
    "addr:street":"Post Office Sq",
    "iso:country":"US",
    "sg:address":"10 Post Office Sq",
    "sg:city":"Boston",
    "sg:classifiers":[
        {
            "category":"Banks & Credit Unions",
            "subcategory":"Investment Brokerage",
            "type":"Services"
        }
    ],
    "sg:phone":"+1 617 988 2780",
    "sg:postcode":"02109",
    "sg:province":"MA",
    "wof:name":"Bayfield Investment Mngt Co",
    "wof:placetype":"venue"
},
  "geometry": {"coordinates":[-71.055745,42.357013],"type":"Point"}
}