{
  "type": "Feature",
  "properties": {
    "addr:full":"132 Main St Spencer MA 01562",
    "addr:housenumber":"132",
    "addr:postcode":"01562",
    "addr:street":"Main St",
    "iso:country":"US",
    "sg:address":"132 Main St",
    "sg:city":"Spencer",
    "sg:classifiers":[
        {
            "category":"Home & Garden",
            "subcategory":"Hardware",
            "type":"Retail Goods"
        }
    ],
    "sg:phone":"+1 508 885 3200",
    "sg:postcode":"01562",
    "sg:province":"MA",
    "sg:tags":[
        "store"
    ],
    "sg:website":"www.hardwarestore.com",
    "wof:name":"Aubuchon Hardware",
    "wof:placetype":"venue"
},
  "geometry": {"coordinates":[-71.996101,42.2435],"type":"Point"}
}