{
  "type": "Feature",
  "properties": {
    "addr:full":"76 Olympia Rd Marshfield MA 02050",
    "addr:housenumber":"76",
    "addr:postcode":"02050",
    "addr:street":"Olympia Rd",
    "iso:country":"US",
    "sg:address":"76 Olympia Rd",
    "sg:city":"Marshfield",
    "sg:classifiers":[
        {
            "category":"Building & Trades",
            "subcategory":"Construction",
            "type":"Services"
        }
    ],
    "sg:phone":"+1 781 319 0472",
    "sg:postcode":"02050",
    "sg:province":"MA",
    "sg:tags":[
        "general",
        "contractor"
    ],
    "wof:name":"RTM & Sons",
    "wof:placetype":"venue"
},
  "geometry": {"coordinates":[-70.667331,42.106725],"type":"Point"}
}