{
  "type": "Feature",
  "properties": {
    "addr:full":"2100 Dorchester Ave Dorchester Ctr MA 02124",
    "addr:housenumber":"2100",
    "addr:postcode":"02124",
    "addr:street":"Dorchester Ave Dorchester Ctr",
    "iso:country":"US",
    "sg:address":"2100 Dorchester Ave",
    "sg:city":"Dorchester Ctr",
    "sg:classifiers":[
        {
            "category":"Health Services",
            "subcategory":"Hospital",
            "type":"Services"
        }
    ],
    "sg:phone":"+1 617 296 4000",
    "sg:postcode":"02124",
    "sg:province":"MA",
    "wof:name":"Carney Hospital",
    "wof:placetype":"venue"
},
  "geometry": {"coordinates":[-71.06640899999999,42.277984],"type":"Point"}
}