{
  "type": "Feature",
  "properties": {
    "addr:full": "102 NEWBURY ST DANVERS MA 01923",
    "addr:housenumber": "102",
    "addr:postcode": "01923",
    "addr:street": "Newbury St",
    "iso:country": "US",
    "sg:address": "102 NEWBURY ST",
    "sg:city": "DANVERS",
    "sg:classifiers": [
      {
        "category": "Travel",
        "subcategory": "Hotels \u0026 Motels",
        "type": "Entertainment"
      }
    ],
    "sg:phone": "+1 978 762 7414",
    "sg:postcode": "01923",
    "sg:province": "MA",
    "sg:tags": [
      "corporate",
      "lodging"
    ],
    "sg:website": "http://redirect.searchignite.com/si/cm/tracking/DGTrackingRedirect.aspx?siclientid=2918\u0026siredirect=http%3A%2F%2Fwww%2Eextendedstayamerica%2Ecom%2FDAN\u0026sisearchengine=155\u0026siproduct=ESA+Boston+%2D+Danvers\u0026clearppc=1",
    "wof:name": "Extended Stay America Boston - Danvers",
    "wof:placetype": "venue"
  },
  "geometry": {"coordinates":[-70.975588,42.5652],"type":"Point"}
}
