{
  "type": "Feature",
  "properties": {
    "iso:country":"US",
    "sg:address":"102 NEWBURY ST",
    "sg:city":"DANVERS",
    "sg:classifiers":[
        {
            "category":"Travel",
            "subcategory":"Hotels & Motels",
            "type":"Entertainment"
        }
    ],
    "sg:phone":"+1 978 762 7414",
    "sg:postcode":"01923",
    "sg:province":"MA",
    "sg:tags":[
        "corporate",
        "lodging"
    ],
    "sg:website":"http://redirect.searchignite.com/si/cm/tracking/DGTrackingRedirect.aspx?siclientid=2918&siredirect=http%3A%2F%2Fwww%2Eextendedstayamerica%2Ecom%2FDAN&sisearchengine=155&siproduct=ESA+Boston+%2D+Danvers&clearppc=1",
    "wof:name":"Extended Stay America Boston - Danvers",
    "wof:placetype":"venue"
},
  "geometry": {"coordinates":[-70.975588,42.5652],"type":"Point"}
}