{
  "type": "Feature",
  "properties": {
    "addr:full":"28 State Street Boston MA 02109",
    "addr:housenumber":"28",
    "addr:postcode":"02109",
    "addr:street":"State Street",
    "iso:country":"US",
    "sg:address":"28 State Street",
    "sg:city":"Boston",
    "sg:classifiers":[
        {
            "category":"Professional",
            "subcategory":"Lawyer & Legal Services",
            "type":"Services"
        }
    ],
    "sg:phone":"+1 617 573 5188",
    "sg:postcode":"02109",
    "sg:province":"MA",
    "wof:name":"Tourse & Associates",
    "wof:placetype":"venue"
},
  "geometry": {"coordinates":[-71.05709400000001,42.358901],"type":"Point"}
}