{
  "type": "Feature",
  "properties": {
    "addr:full": "84 Moreau St Stoughton MA 02072",
    "addr:housenumber": "84",
    "addr:postcode": "02072",
    "addr:street": "Moreau St",
    "iso:country": "US",
    "sg:address": "84 Moreau St",
    "sg:city": "Stoughton",
    "sg:classifiers": [
      {
        "category": "Wholesale",
        "subcategory": "Photographic Equipment",
        "type": "Manufacturing \u0026 Wholesale Goods"
      }
    ],
    "sg:phone": "+1 781 344 4897",
    "sg:postcode": "02072",
    "sg:province": "MA",
    "sg:tags": [
      "supplies-wholesale",
      "manufacturer"
    ],
    "wof:name": "Ernie Wolf Sales Co Inc",
    "wof:placetype": "venue"
  },
  "geometry": {"coordinates":[-71.119173,42.141871],"type":"Point"}
}
