{
  "type": "Feature",
  "properties": {
    "iso:country":"US",
    "sg:address":"84 Moreau St",
    "sg:city":"Stoughton",
    "sg:classifiers":[
        {
            "category":"Wholesale",
            "subcategory":"Photographic Equipment",
            "type":"Manufacturing & Wholesale Goods"
        }
    ],
    "sg:phone":"+1 781 344 4897",
    "sg:postcode":"02072",
    "sg:province":"MA",
    "sg:tags":[
        "supplies-wholesale",
        "manufacturer"
    ],
    "wof:name":"Ernie Wolf Sales Co Inc",
    "wof:placetype":"venue"
},
  "geometry": {"coordinates":[-71.119173,42.141871],"type":"Point"}
}