{
  "type": "Feature",
  "properties": {
    "addr:full": "189 Circuit St Hanover MA 02339",
    "addr:housenumber": "189",
    "addr:postcode": "02339",
    "addr:street": "Circuit",
    "iso:country": "US",
    "sg:address": "189 Circuit St",
    "sg:city": "Hanover",
    "sg:classifiers": [
      {
        "category": "Building \u0026 Trades",
        "subcategory": "Construction",
        "type": "Services"
      }
    ],
    "sg:phone": "+1 781 878 3606",
    "sg:postcode": "02339",
    "sg:province": "MA",
    "sg:tags": [
      "runway",
      "dog",
      "enclosure"
    ],
    "wof:name": "Fence-A-Pet Petsafe Radio",
    "wof:placetype": "venue"
  },
  "geometry": {"coordinates":[-70.864067,42.113086],"type":"Point"}
}
