{
  "type": "Feature",
  "properties": {
    "addr:full":"12 Bay St Wilmington MA 01887",
    "addr:housenumber":"12",
    "addr:postcode":"01887",
    "addr:street":"Bay St",
    "iso:country":"US",
    "sg:address":"12 Bay St",
    "sg:city":"Wilmington",
    "sg:classifiers":[
        {
            "category":"Manufacturing",
            "subcategory":"Building Materials",
            "type":"Manufacturing & Wholesale Goods"
        }
    ],
    "sg:phone":"+1 978 658 4562",
    "sg:postcode":"01887",
    "sg:province":"MA",
    "wof:name":"Griffin Interiors Inc",
    "wof:placetype":"venue"
},
  "geometry": {"coordinates":[-71.153092,42.542105],"type":"Point"}
}