{
  "type": "Feature",
  "properties": {
    "addr:full":"173 Whitmar Rd Cotuit MA 02635",
    "addr:housenumber":"173",
    "addr:postcode":"02635",
    "addr:street":"Whitmar Rd",
    "iso:country":"US",
    "sg:address":"173 Whitmar Rd",
    "sg:city":"Cotuit",
    "sg:classifiers":[
        {
            "category":"Winery",
            "type":"Food & Drink"
        }
    ],
    "sg:phone":"+1 508 420 2009",
    "sg:postcode":"02635",
    "sg:province":"MA",
    "wof:name":"C K Mondavi - CLOSED",
    "wof:placetype":"venue"
},
  "geometry": {"coordinates":[-70.424599,41.640598],"type":"Point"}
}