{
  "type": "Feature",
  "properties": {
    "iso:country":"US",
    "sg:address":"150 Gordon Owen Pkwy",
    "sg:city":"Taunton",
    "sg:classifiers":[
        {
            "category":"Shopping",
            "subcategory":"Bicycles & Sporting Goods",
            "type":"Retail Goods"
        }
    ],
    "sg:phone":"+1 508 823 0350",
    "sg:postcode":"02780",
    "sg:province":"MA",
    "wof:name":"J & B Hockey Inc",
    "wof:placetype":"venue"
},
  "geometry": {"coordinates":[-71.075524,41.90028],"type":"Point"}
}