{
  "type": "Feature",
  "properties": {
    "addr:full": "70 Randolph St Springfield MA 01108",
    "addr:housenumber": "70",
    "addr:postcode": "01108",
    "addr:street": "Randolph St",
    "iso:country": "US",
    "sg:address": "70 Randolph St",
    "sg:city": "Springfield",
    "sg:classifiers": [
      {
        "category": "Professional",
        "subcategory": "Lawyer \u0026 Legal Services",
        "type": "Services"
      }
    ],
    "sg:phone": "+1 413 788 4859",
    "sg:postcode": "01108",
    "sg:province": "MA",
    "sg:tags": [
      "attorney"
    ],
    "wof:name": "William F Howard III",
    "wof:placetype": "venue"
  },
  "geometry": {"coordinates":[-72.570691,42.085423],"type":"Point"}
}
