{
  "type": "Feature",
  "properties": {
    "iso:country":"US",
    "sg:address":"245 N Washington St",
    "sg:city":"North Attleboro",
    "sg:classifiers":[
        {
            "category":"Restaurant",
            "type":"Food & Drink"
        }
    ],
    "sg:phone":"+1 508 699 5055",
    "sg:postcode":"02760",
    "sg:province":"MA",
    "wof:name":"Jeffrey's Pizza",
    "wof:placetype":"venue"
},
  "geometry": {"coordinates":[-71.330901,41.989293],"type":"Point"}
}