{
  "type": "Feature",
  "properties": {
    "addr:full": "245 N Washington St North Attleboro MA 02760",
    "addr:housenumber": "245",
    "addr:postcode": "02760",
    "addr:street": "N Washington St",
    "iso:country": "US",
    "sg:address": "245 N Washington St",
    "sg:city": "North Attleboro",
    "sg:classifiers": [
      {
        "category": "Restaurant",
        "type": "Food \u0026 Drink"
      }
    ],
    "sg:phone": "+1 508 699 5055",
    "sg:postcode": "02760",
    "sg:province": "MA",
    "wof:name": "Jeffrey's Pizza",
    "wof:placetype": "venue"
  },
  "geometry": {"coordinates":[-71.330901,41.989293],"type":"Point"}
}
