{
  "type": "Feature",
  "properties": {
    "addr:full": "262 Essex St Salem MA 01970",
    "addr:housenumber": "262",
    "addr:postcode": "01970",
    "addr:street": "Essex St",
    "iso:country": "US",
    "sg:address": "262 Essex St",
    "sg:city": "Salem",
    "sg:classifiers": [
      {
        "category": "Real Estate",
        "subcategory": "Architect",
        "type": "Services"
      }
    ],
    "sg:phone": "+1 978 741 5777",
    "sg:postcode": "01970",
    "sg:province": "MA",
    "sg:website": "www.nsaarch.com",
    "wof:name": "Nilsson \u0026 Siden Assoc Inc",
    "wof:placetype": "venue"
  },
  "geometry": {"coordinates":[-70.897414,42.521514],"type":"Point"}
}
