{
  "type": "Feature",
  "properties": {
    "addr:full": "140 Winter St Weymouth MA 02188",
    "addr:housenumber": "140",
    "addr:postcode": "02188",
    "addr:street": "Winter St",
    "iso:country": "US",
    "sg:address": "140 Winter St",
    "sg:city": "Weymouth",
    "sg:classifiers": [
      {
        "category": "Government",
        "subcategory": "Police Station",
        "type": "Public Place"
      }
    ],
    "sg:phone": "+1 781 335 1212",
    "sg:postcode": "02188",
    "sg:province": "MA",
    "sg:tags": [
      "department"
    ],
    "wof:name": "Police Dept Communications",
    "wof:placetype": "venue"
  },
  "geometry": {"coordinates":[-70.950119,42.200602],"type":"Point"}
}
