{
  "type": "Feature",
  "properties": {
    "addr:full": "106 Access Rd Norwood MA 02062",
    "addr:housenumber": "106",
    "addr:postcode": "02062",
    "addr:street": "Access Rd",
    "iso:country": "US",
    "sg:address": "106 Access Rd",
    "sg:city": "Norwood",
    "sg:classifiers": [
      {
        "category": "Building \u0026 Trades",
        "subcategory": "Electrical",
        "type": "Services"
      }
    ],
    "sg:phone": "+1 781 762 4004",
    "sg:postcode": "02062",
    "sg:province": "MA",
    "sg:tags": [
      "electrician",
      "electric",
      "contractor"
    ],
    "wof:name": "Guzovsky Electric Co",
    "wof:placetype": "venue"
  },
  "geometry": {"coordinates":[-71.177902,42.185501],"type":"Point"}
}
