{
  "type": "Feature",
  "properties": {
    "addr:full":"133 Holland St Somerville MA 02144",
    "addr:housenumber":"133",
    "addr:postcode":"02144",
    "addr:street":"Holland St",
    "iso:country":"US",
    "sg:address":"133 Holland St",
    "sg:city":"Somerville",
    "sg:classifiers":[
        {
            "category":"Government",
            "subcategory":"City Hall",
            "type":"Public Place"
        }
    ],
    "sg:phone":"+1 617 666 3311",
    "sg:postcode":"02144",
    "sg:province":"MA",
    "sg:website":"www.somervillema.gov/Department....",
    "wof:name":"City of Somerville Office of the Parking Clerk",
    "wof:placetype":"venue"
},
  "geometry": {"coordinates":[-71.12543700000001,42.400068],"type":"Point"}
}