{
  "type": "Feature",
  "properties": {
    "iso:country":"US",
    "sg:address":"85 L St",
    "sg:city":"Boston",
    "sg:classifiers":[
        {
            "category":"Retail",
            "subcategory":"Laundry & Dry Cleaning",
            "type":"Services"
        }
    ],
    "sg:phone":"+1 617 269 3464",
    "sg:postcode":"02127",
    "sg:province":"MA",
    "sg:tags":[
        "cleaner"
    ],
    "wof:name":"Executive Cleaners",
    "wof:placetype":"venue"
},
  "geometry": {"coordinates":[-71.035202,42.334599],"type":"Point"}
}