{
  "type": "Feature",
  "properties": {
    "addr:full": "35 Lowell St Wilmington MA 01887",
    "addr:housenumber": "35",
    "addr:postcode": "01887",
    "addr:street": "Lowell St",
    "iso:country": "US",
    "sg:address": "35 Lowell St",
    "sg:city": "Wilmington",
    "sg:classifiers": [
      {
        "category": "Shopping",
        "subcategory": "Discount \u0026 Variety Stores",
        "type": "Retail Goods"
      }
    ],
    "sg:phone": "+1 978 657 9652",
    "sg:postcode": "01887",
    "sg:province": "MA",
    "sg:tags": [
      "merchandise",
      "general"
    ],
    "wof:name": "Pp Mart Discount LLC",
    "wof:placetype": "venue"
  },
  "geometry": {"coordinates":[-71.164071,42.54172],"type":"Point"}
}
