{
  "type": "Feature",
  "properties": {
    "addr:full": "2 Center Plz Ste 510 Boston MA 02108",
    "addr:housenumber": "2",
    "addr:postcode": "02108",
    "addr:street": "Center Plz Ste 510",
    "iso:country": "US",
    "sg:address": "2 Center Plz Ste 510",
    "sg:city": "Boston",
    "sg:classifiers": [
      {
        "category": "Professional",
        "subcategory": "Lawyer \u0026 Legal Services",
        "type": "Services"
      }
    ],
    "sg:phone": "+1 617 412 4291",
    "sg:postcode": "02108",
    "sg:province": "MA",
    "sg:tags": [
      "attorney",
      "practice",
      "plan"
    ],
    "wof:name": "Bottone Dennis Attorney",
    "wof:placetype": "venue"
  },
  "geometry": {"coordinates":[-71.060951,42.36012],"type":"Point"}
}
