{
  "type": "Feature",
  "properties": {
    "addr:full":"52 Second Avenue Burlington MA 01803",
    "addr:housenumber":"52",
    "addr:postcode":"01803",
    "addr:street":"Second Avenue",
    "iso:country":"US",
    "sg:address":"52 Second Avenue",
    "sg:city":"Burlington",
    "sg:classifiers":[
        {
            "category":"Professional",
            "subcategory":"Computer Services",
            "type":"Services"
        }
    ],
    "sg:phone":"+1 781 328 0888",
    "sg:postcode":"01803",
    "sg:province":"MA",
    "sg:website":"http://www.bluesocket.com/",
    "wof:name":"Bluesocket",
    "wof:placetype":"venue"
},
  "geometry": {"coordinates":[-71.224958,42.487228],"type":"Point"}
}