{
  "type": "Feature",
  "properties": {
    "addr:full": "20 Willis St New Bedford MA 02740",
    "addr:housenumber": "20",
    "addr:postcode": "02740",
    "addr:street": "Willis St",
    "iso:country": "US",
    "sg:address": "20 Willis St",
    "sg:city": "New Bedford",
    "sg:classifiers": [
      {
        "category": "Social Services",
        "type": "Services"
      }
    ],
    "sg:phone": "+1 508 990 3458",
    "sg:postcode": "02740",
    "sg:province": "MA",
    "sg:tags": [
      "organization",
      "welfare"
    ],
    "wof:name": "Veterans Transition House",
    "wof:placetype": "venue"
  },
  "geometry": {"coordinates":[-70.927813,41.643179],"type":"Point"}
}
