{
  "type": "Feature",
  "properties": {
    "addr:full":"14 Porter Street Boston MA 02128",
    "addr:housenumber":"14",
    "addr:postcode":"02128",
    "addr:street":"Porter Street",
    "iso:country":"US",
    "sg:address":"14 Porter Street",
    "sg:city":"Boston",
    "sg:classifiers":[
        {
            "category":"Health Services",
            "subcategory":"Clinic",
            "type":"Services"
        },
        {
            "category":"Sports & Exercise",
            "subcategory":"Gym",
            "type":"Entertainment"
        }
    ],
    "sg:phone":"+1 617 569 3189",
    "sg:postcode":"02128",
    "sg:province":"MA",
    "sg:tags":[
        "information",
        "mental",
        "trainer",
        "welfare"
    ],
    "wof:name":"North Suffolk Mental Health Association",
    "wof:placetype":"venue"
},
  "geometry": {"coordinates":[-71.038481,42.374599],"type":"Point"}
}