{
  "type": "Feature",
  "properties": {
    "addr:full":"4 Longfellow Pl Boston MA 02114",
    "addr:housenumber":"4",
    "addr:postcode":"02114",
    "addr:street":"Longfellow Pl",
    "iso:country":"US",
    "sg:address":"4 Longfellow Pl",
    "sg:city":"Boston",
    "sg:classifiers":[
        {
            "category":"Banks & Credit Unions",
            "subcategory":"Investment Brokerage",
            "type":"Services"
        }
    ],
    "sg:phone":"+1 617 523 4441",
    "sg:postcode":"02114",
    "sg:province":"MA",
    "wof:name":"Investment Network Of America",
    "wof:placetype":"venue"
},
  "geometry": {"coordinates":[-71.06405700000001,42.363271],"type":"Point"}
}