{
  "type": "Feature",
  "properties": {
    "iso:country":"US",
    "sg:address":"107 Fairhaven Rd",
    "sg:city":"Mattapoisett",
    "sg:classifiers":[
        {
            "category":"Health Services",
            "subcategory":"Doctor",
            "type":"Services"
        }
    ],
    "sg:phone":"+1 508 997 2200",
    "sg:postcode":"02739",
    "sg:province":"MA",
    "sg:tags":[
        "physician",
        "surgeon"
    ],
    "wof:name":"Healthcare For Women Inc",
    "wof:placetype":"venue"
},
  "geometry": {"coordinates":[-70.836484,41.656033],"type":"Point"}
}