{
  "type": "Feature",
  "properties": {
    "addr:full": "107 Fairhaven Rd Mattapoisett MA 02739",
    "addr:housenumber": "107",
    "addr:postcode": "02739",
    "addr:street": "Fairhaven Rd",
    "iso:country": "US",
    "sg:address": "107 Fairhaven Rd",
    "sg:city": "Mattapoisett",
    "sg:classifiers": [
      {
        "category": "Health Services",
        "subcategory": "Doctor",
        "type": "Services"
      }
    ],
    "sg:phone": "+1 508 997 2200",
    "sg:postcode": "02739",
    "sg:province": "MA",
    "sg:tags": [
      "physician",
      "surgeon"
    ],
    "wof:name": "Healthcare For Women Inc",
    "wof:placetype": "venue"
  },
  "geometry": {"coordinates":[-70.836484,41.656033],"type":"Point"}
}
