{
  "type": "Feature",
  "properties": {
    "addr:full":"1193 River St Hyde Park MA 02136",
    "addr:housenumber":"1193",
    "addr:postcode":"02136",
    "addr:street":"River St",
    "iso:country":"US",
    "sg:address":"1193 River St",
    "sg:city":"Hyde Park",
    "sg:classifiers":[
        {
            "category":"Manufacturing",
            "subcategory":"Printing",
            "type":"Manufacturing & Wholesale Goods"
        }
    ],
    "sg:phone":"+1 617 364 5050",
    "sg:postcode":"02136",
    "sg:province":"MA",
    "sg:tags":[
        "printer"
    ],
    "wof:name":"Union Printworks",
    "wof:placetype":"venue"
},
  "geometry": {"coordinates":[-71.122004,42.256103],"type":"Point"}
}