{
  "type": "Feature",
  "properties": {
    "addr:full": "25 Centre St Roxbury MA 02119",
    "addr:housenumber": "25",
    "addr:postcode": "02119",
    "addr:street": "Centre St",
    "iso:country": "US",
    "sg:address": "25 Centre St",
    "sg:city": "Roxbury",
    "sg:classifiers": [
      {
        "category": "Manufacturing",
        "subcategory": "Buildings",
        "type": "Manufacturing \u0026 Wholesale Goods"
      },
      {
        "category": "Building \u0026 Trades",
        "subcategory": "Construction",
        "type": "Services"
      }
    ],
    "sg:phone": "+1 617 442 3761",
    "sg:postcode": "02119",
    "sg:province": "MA",
    "sg:tags": [
      "home",
      "builder",
      "management",
      "contractor"
    ],
    "wof:name": "Ilama Construction \u0026 Construction Management Inc",
    "wof:placetype": "venue"
  },
  "geometry": {"coordinates":[-71.093201,42.329689],"type":"Point"}
}
