{
  "type": "Feature",
  "properties": {
    "iso:country":"US",
    "sg:address":"25 Centre St",
    "sg:city":"Roxbury",
    "sg:classifiers":[
        {
            "category":"Manufacturing",
            "subcategory":"Buildings",
            "type":"Manufacturing & Wholesale Goods"
        },
        {
            "category":"Building & Trades",
            "subcategory":"Construction",
            "type":"Services"
        }
    ],
    "sg:phone":"+1 617 442 3761",
    "sg:postcode":"02119",
    "sg:province":"MA",
    "sg:tags":[
        "home",
        "builder",
        "management",
        "contractor"
    ],
    "wof:name":"Ilama Construction & Construction Management Inc",
    "wof:placetype":"venue"
},
  "geometry": {"coordinates":[-71.09320099999999,42.329689],"type":"Point"}
}