{
  "type": "Feature",
  "properties": {
    "addr:full": "20 Bridge St Northampton MA 01060",
    "addr:housenumber": "20",
    "addr:postcode": "01060",
    "addr:street": "Bridge St",
    "iso:country": "US",
    "sg:address": "20 Bridge St",
    "sg:city": "Northampton",
    "sg:classifiers": [
      {
        "category": "Home \u0026 Garden",
        "subcategory": "Household Appliances",
        "type": "Retail Goods"
      }
    ],
    "sg:phone": "+1 413 584 2000",
    "sg:postcode": "01060",
    "sg:province": "MA",
    "wof:name": "L \u0026 H TV \u0026 Appliance Inc",
    "wof:placetype": "venue"
  },
  "geometry": {"coordinates":[-72.626066,42.3223],"type":"Point"}
}
