{
  "type": "Feature",
  "properties": {
    "iso:country":"US",
    "sg:address":"20 Bridge St",
    "sg:city":"Northampton",
    "sg:classifiers":[
        {
            "category":"Home & Garden",
            "subcategory":"Household Appliances",
            "type":"Retail Goods"
        }
    ],
    "sg:phone":"+1 413 584 2000",
    "sg:postcode":"01060",
    "sg:province":"MA",
    "wof:name":"L & H TV & Appliance Inc",
    "wof:placetype":"venue"
},
  "geometry": {"coordinates":[-72.62606599999999,42.3223],"type":"Point"}
}