{
  "type": "Feature",
  "properties": {
    "addr:full":"1001 Kings Hwy New Bedford MA 02745",
    "addr:housenumber":"1001",
    "addr:postcode":"02745",
    "addr:street":"Kings Hwy",
    "iso:country":"US",
    "sg:address":"1001 Kings Hwy",
    "sg:city":"New Bedford",
    "sg:classifiers":[
        {
            "category":"Restaurant",
            "type":"Food & Drink"
        }
    ],
    "sg:phone":"+1   ",
    "sg:postcode":"02745",
    "sg:province":"MA",
    "sg:tags":[
        "eating"
    ],
    "wof:name":"Wendys",
    "wof:placetype":"venue"
},
  "geometry": {"coordinates":[-70.942059,41.677979],"type":"Point"}
}