{
  "type": "Feature",
  "properties": {
    "addr:full": "1001 Kings Hwy New Bedford MA 02745",
    "addr:housenumber": "1001",
    "addr:postcode": "02745",
    "addr:street": "Kings Hwy",
    "iso:country": "US",
    "ovtr:label": "Wendy's, 1095 Kings Hwy New Bedford MA US",
    "ovtr:similarity": 3.849699020385742,
    "sg:address": "1001 Kings Hwy",
    "sg:city": "New Bedford",
    "sg:classifiers": [
      {
        "category": "Restaurant",
        "type": "Food \u0026 Drink"
      }
    ],
    "sg:phone": "+1   ",
    "sg:postcode": "02745",
    "sg:province": "MA",
    "sg:tags": [
      "eating"
    ],
    "wof:name": "Wendys",
    "wof:placetype": "venue"
  },
  "geometry": {"coordinates":[-70.942059,41.677979],"type":"Point"}
}
