{
  "type": "Feature",
  "properties": {
    "addr:full": "211 W Newton St Apt 5 Boston MA 02116",
    "addr:housenumber": "211;5",
    "addr:postcode": "02116",
    "addr:street": "W Newton St Apt",
    "iso:country": "US",
    "sg:address": "211 W Newton St Apt 5",
    "sg:city": "Boston",
    "sg:classifiers": [
      {
        "category": "Cinema",
        "subcategory": "Movie Rental",
        "type": "Entertainment"
      }
    ],
    "sg:phone": "+1 617 966 5554",
    "sg:postcode": "02116",
    "sg:province": "MA",
    "sg:tags": [
      "picture",
      "exchange",
      "motion",
      "distributor",
      "film"
    ],
    "wof:name": "Debdee Productions",
    "wof:placetype": "venue"
  },
  "geometry": {"coordinates":[-71.079597,42.343899],"type":"Point"}
}
