{
  "type": "Feature",
  "properties": {
    "iso:country":"US",
    "sg:address":"108 Waite Rd",
    "sg:city":"Acton",
    "sg:classifiers":[
        {
            "category":"Education",
            "subcategory":"Special Training",
            "type":"Public Place"
        }
    ],
    "sg:phone":"+1   ",
    "sg:postcode":"01719",
    "sg:province":"MA",
    "wof:name":"Susan Destefano",
    "wof:placetype":"venue"
},
  "geometry": {"coordinates":[-71.503857,42.503611],"type":"Point"}
}