{
  "type": "Feature",
  "properties": {
    "iso:country":"US",
    "sg:address":"63 Summer St",
    "sg:city":"Maynard",
    "sg:classifiers":[
        {
            "category":"Education",
            "subcategory":"Special Training",
            "type":"Public Place"
        }
    ],
    "sg:phone":"+1 978 897 4339",
    "sg:postcode":"01754",
    "sg:province":"MA",
    "sg:tags":[
        "school",
        "instruction",
        "art"
    ],
    "wof:name":"Moonscape Design",
    "wof:placetype":"venue"
},
  "geometry": {"coordinates":[-71.455883,42.434368],"type":"Point"}
}