{
  "type": "Feature",
  "properties": {
    "iso:country":"US",
    "sg:address":"70 Rindge Ave",
    "sg:city":"Cambridge",
    "sg:classifiers":[
        {
            "category":"Education",
            "subcategory":"Library",
            "type":"Public Place"
        }
    ],
    "sg:phone":"+1 617 349 4023",
    "sg:postcode":"02140",
    "sg:province":"MA",
    "sg:website":"www.cambridgema.gov/CPL/hours/on...",
    "wof:name":"O'Neill Branch Library",
    "wof:placetype":"venue"
},
  "geometry": {"coordinates":[-71.12809799999999,42.392717],"type":"Point"}
}