{
  "type": "Feature",
  "properties": {
    "iso:country":"US",
    "sg:address":"151 Stoughton St",
    "sg:city":"Dorchester",
    "sg:classifiers":[
        {
            "category":"Shopping",
            "subcategory":"Clothing, Apparel, & Fashions",
            "type":"Retail Goods"
        }
    ],
    "sg:phone":"+1 617 282 5613",
    "sg:postcode":"02125",
    "sg:province":"MA",
    "wof:name":"Euro Style",
    "wof:placetype":"venue"
},
  "geometry": {"coordinates":[-71.060259,42.314793],"type":"Point"}
}