{
  "type": "Feature",
  "properties": {
    "iso:country":"US",
    "sg:address":"417 Meridian St",
    "sg:city":"Boston",
    "sg:classifiers":[
        {
            "category":"Professional",
            "subcategory":"Advertising",
            "type":"Services"
        }
    ],
    "sg:phone":"+1 617 561 0033",
    "sg:postcode":"02128",
    "sg:province":"MA",
    "sg:tags":[
        "mail",
        "direct"
    ],
    "wof:name":"Diversi Inc",
    "wof:placetype":"venue"
},
  "geometry": {"coordinates":[-71.03919,42.380916],"type":"Point"}
}