{
  "type": "Feature",
  "properties": {
    "addr:full": "417 Meridian St Boston MA 02128",
    "addr:housenumber": "417",
    "addr:postcode": "02128",
    "addr:street": "Meridian St",
    "iso:country": "US",
    "sg:address": "417 Meridian St",
    "sg:city": "Boston",
    "sg:classifiers": [
      {
        "category": "Professional",
        "subcategory": "Advertising",
        "type": "Services"
      }
    ],
    "sg:phone": "+1 617 561 0033",
    "sg:postcode": "02128",
    "sg:province": "MA",
    "sg:tags": [
      "mail",
      "direct"
    ],
    "wof:name": "Diversi Inc",
    "wof:placetype": "venue"
  },
  "geometry": {"coordinates":[-71.03919,42.380916],"type":"Point"}
}
