{
  "type": "Feature",
  "properties": {
    "iso:country":"US",
    "sg:address":"24 May St",
    "sg:city":"Peabody",
    "sg:classifiers":[
        {
            "category":"Building & Trades",
            "subcategory":"Construction",
            "type":"Services"
        }
    ],
    "sg:phone":"+1   ",
    "sg:postcode":"01960",
    "sg:province":"MA",
    "sg:tags":[
        "house"
    ],
    "wof:name":"Santos Greenhouse Construction",
    "wof:placetype":"venue"
},
  "geometry": {"coordinates":[-70.94053599999999,42.514566],"type":"Point"}
}