{
  "type": "Feature",
  "properties": {
    "addr:full": "24 May St Peabody MA 01960",
    "addr:housenumber": "24",
    "addr:postcode": "01960",
    "addr:street": "May St",
    "iso:country": "US",
    "sg:address": "24 May St",
    "sg:city": "Peabody",
    "sg:classifiers": [
      {
        "category": "Building \u0026 Trades",
        "subcategory": "Construction",
        "type": "Services"
      }
    ],
    "sg:phone": "+1   ",
    "sg:postcode": "01960",
    "sg:province": "MA",
    "sg:tags": [
      "house"
    ],
    "wof:name": "Santos Greenhouse Construction",
    "wof:placetype": "venue"
  },
  "geometry": {"coordinates":[-70.940536,42.514566],"type":"Point"}
}
