{
  "type": "Feature",
  "properties": {
    "addr:full": "26 Locke St Cambridge MA 02140",
    "addr:housenumber": "26",
    "addr:postcode": "02140",
    "addr:street": "Locke St",
    "iso:country": "US",
    "sg:address": "26 Locke St",
    "sg:city": "Cambridge",
    "sg:classifiers": [
      {
        "category": "Professional",
        "type": "Services"
      }
    ],
    "sg:phone": "+1   ",
    "sg:postcode": "02140",
    "sg:province": "MA",
    "wof:name": "K L Thibodeau Corporation",
    "wof:placetype": "venue"
  },
  "geometry": {"coordinates":[-71.127322,42.396738],"type":"Point"}
}
