{
  "type": "Feature",
  "properties": {
    "iso:country":"US",
    "sg:address":"26 Locke St",
    "sg:city":"Cambridge",
    "sg:classifiers":[
        {
            "category":"Professional",
            "type":"Services"
        }
    ],
    "sg:phone":"+1   ",
    "sg:postcode":"02140",
    "sg:province":"MA",
    "wof:name":"K L Thibodeau Corporation",
    "wof:placetype":"venue"
},
  "geometry": {"coordinates":[-71.12732200000001,42.396738],"type":"Point"}
}