{
  "type": "Feature",
  "properties": {
    "addr:full": "110 Winn Street Suite 208 Woburn MA 01801",
    "addr:housenumber": "110",
    "addr:postcode": "01801",
    "addr:street": "Winn Street Suite 208",
    "iso:country": "US",
    "sg:address": "110 Winn Street Suite 208",
    "sg:city": "Woburn",
    "sg:classifiers": [
      {
        "category": "Personal",
        "subcategory": "Tanning Parlor",
        "type": "Services"
      }
    ],
    "sg:phone": "+1 781 933 7100",
    "sg:postcode": "01801",
    "sg:province": "MA",
    "sg:website": "www.advancedairbrushtanning.com",
    "wof:name": "Advanced Airbrush Tanning",
    "wof:placetype": "venue"
  },
  "geometry": {"coordinates":[-71.158041,42.483614],"type":"Point"}
}
