{
  "type": "Feature",
  "properties": {
    "iso:country":"US",
    "sg:address":"200 Sherwood Ln",
    "sg:city":"Raynham",
    "sg:classifiers":[
        {
            "category":"Personal",
            "type":"Services"
        }
    ],
    "sg:phone":"+1 508 813 8996",
    "sg:postcode":"02767",
    "sg:province":"MA",
    "sg:tags":[
        "therapist",
        "massage"
    ],
    "wof:name":"Brian Clifford",
    "wof:placetype":"venue"
},
  "geometry": {"coordinates":[-71.04603299999999,41.929285],"type":"Point"}
}