{
  "type": "Feature",
  "properties": {
    "addr:full": "67 Mill Street Revere MA 02151",
    "addr:housenumber": "67",
    "addr:postcode": "02151",
    "addr:street": "Mill Street",
    "iso:country": "US",
    "sg:address": "67 Mill Street",
    "sg:city": "Revere",
    "sg:classifiers": [
      {
        "category": "Professional",
        "subcategory": "Lawyer \u0026 Legal Services",
        "type": "Services"
      }
    ],
    "sg:phone": "+1 781 284 1664",
    "sg:postcode": "02151",
    "sg:province": "MA",
    "wof:name": "Duffy George J Lwyr",
    "wof:placetype": "venue"
  },
  "geometry": {"coordinates":[-71.010933,42.404711],"type":"Point"}
}
