{
  "type": "Feature",
  "properties": {
    "iso:country":"US",
    "sg:address":"47 Kemble Pl",
    "sg:city":"Boston",
    "sg:classifiers":[
        {
            "category":"Utilities",
            "subcategory":"Refuse",
            "type":"Services"
        },
        {
            "category":"Utilities",
            "subcategory":"Recycling",
            "type":"Services"
        }
    ],
    "sg:phone":"+1 617 541 4000",
    "sg:postcode":"02127",
    "sg:province":"MA",
    "sg:tags":[
        "container",
        "garbage",
        "disposal",
        "collection",
        "removal",
        "equipment",
        "rubbish",
        "waste"
    ],
    "sg:website":"http://www.jet-a-way.com",
    "wof:name":"Jet-A-Way",
    "wof:placetype":"venue"
},
  "geometry": {"coordinates":[-71.02748,42.337752],"type":"Point"}
}