{
  "type": "Feature",
  "properties": {
    "iso:country":"US",
    "sg:address":"35 Pomeworth St",
    "sg:city":"Stoneham",
    "sg:classifiers":[
        {
            "category":"Retail",
            "subcategory":"Car Wash",
            "type":"Services"
        }
    ],
    "sg:phone":"+1 781 438 9090",
    "sg:postcode":"02180",
    "sg:province":"MA",
    "sg:tags":[
        "automobile",
        "detail",
        "clean"
    ],
    "wof:name":"Auto Spa",
    "wof:placetype":"venue"
},
  "geometry": {"coordinates":[-71.09670199999999,42.483266],"type":"Point"}
}