{
  "type": "Feature",
  "properties": {
    "addr:full": "35 Pomeworth St Stoneham MA 02180",
    "addr:housenumber": "35",
    "addr:postcode": "02180",
    "addr:street": "Pomeworth St",
    "iso:country": "US",
    "sg:address": "35 Pomeworth St",
    "sg:city": "Stoneham",
    "sg:classifiers": [
      {
        "category": "Retail",
        "subcategory": "Car Wash",
        "type": "Services"
      }
    ],
    "sg:phone": "+1 781 438 9090",
    "sg:postcode": "02180",
    "sg:province": "MA",
    "sg:tags": [
      "automobile",
      "detail",
      "clean"
    ],
    "wof:name": "Auto Spa",
    "wof:placetype": "venue"
  },
  "geometry": {"coordinates":[-71.096702,42.483266],"type":"Point"}
}
