{
  "type": "Feature",
  "properties": {
    "iso:country":"US",
    "sg:address":"32 Main St",
    "sg:city":"West Stockbridge",
    "sg:classifiers":[
        {
            "category":"Arts & Performance",
            "subcategory":"Art Gallery",
            "type":"Entertainment"
        }
    ],
    "sg:phone":"+1 413 232 7997",
    "sg:postcode":"01266",
    "sg:province":"MA",
    "wof:name":"Waterside Gallery - CLOSED",
    "wof:placetype":"venue"
},
  "geometry": {"coordinates":[-73.367104,42.3395],"type":"Point"}
}