{
  "type": "Feature",
  "properties": {
    "iso:country":"US",
    "sg:address":"95 State St",
    "sg:city":"Springfield",
    "sg:classifiers":[
        {
            "category":"Professional",
            "subcategory":"Lawyer & Legal Services",
            "type":"Services"
        }
    ],
    "sg:phone":"+1 413 781 4931",
    "sg:postcode":"01103",
    "sg:province":"MA",
    "sg:tags":[
        "attorney"
    ],
    "wof:name":"Carrie Robinson Law Office",
    "wof:placetype":"venue"
},
  "geometry": {"coordinates":[-72.587304,42.100553],"type":"Point"}
}