{
  "type": "Feature",
  "properties": {
    "addr:full": "92 Industrial Dr Mashpee MA 02649",
    "addr:housenumber": "92",
    "addr:postcode": "02649",
    "addr:street": "Industrial Dr",
    "iso:country": "US",
    "sg:address": "92 Industrial Dr",
    "sg:city": "Mashpee",
    "sg:classifiers": [
      {
        "category": "Home \u0026 Garden",
        "subcategory": "Furniture",
        "type": "Retail Goods"
      }
    ],
    "sg:phone": "+1 508 539 9901",
    "sg:postcode": "02649",
    "sg:province": "MA",
    "sg:tags": [
      "top",
      "counter"
    ],
    "wof:name": "Coastal N Counters",
    "wof:placetype": "venue"
  },
  "geometry": {"coordinates":[-70.491076,41.603247],"type":"Point"}
}
