{
  "type": "Feature",
  "properties": {
    "addr:full": "346 School St Winchendon MA 01475",
    "addr:housenumber": "346",
    "addr:postcode": "01475",
    "addr:street": "School St",
    "iso:country": "US",
    "sg:address": "346 School St",
    "sg:city": "Winchendon",
    "sg:classifiers": [
      {
        "category": "Utilities",
        "subcategory": "Natural Gas",
        "type": "Services"
      }
    ],
    "sg:phone": "+1 978 297 9939",
    "sg:postcode": "01475",
    "sg:province": "MA",
    "sg:tags": [
      "company"
    ],
    "wof:name": "Whitey's Gas",
    "wof:placetype": "venue"
  },
  "geometry": {"coordinates":[-72.061057,42.695613],"type":"Point"}
}
