{
  "type": "Feature",
  "properties": {
    "addr:full":"110 Chapin Rd Hudson MA 01749",
    "addr:housenumber":"110",
    "addr:postcode":"01749",
    "addr:street":"Chapin Rd",
    "iso:country":"US",
    "sg:address":"110 Chapin Rd",
    "sg:city":"Hudson",
    "sg:classifiers":[
        {
            "category":"Retail",
            "subcategory":"Animal Services",
            "type":"Services"
        }
    ],
    "sg:phone":"+1 978 568 9700",
    "sg:postcode":"01749",
    "sg:province":"MA",
    "sg:tags":[
        "shelter"
    ],
    "sg:website":"www.ygrr.org",
    "wof:name":"Yankee Golden Retriever Rescue",
    "wof:placetype":"venue"
},
  "geometry": {"coordinates":[-71.586274,42.380711],"type":"Point"}
}