{
  "type": "Feature",
  "properties": {
    "iso:country":"US",
    "sg:address":"80 Worcester St",
    "sg:city":"North Grafton",
    "sg:classifiers":[
        {
            "category":"Personal",
            "subcategory":"Tanning Parlor",
            "type":"Services"
        }
    ],
    "sg:phone":"+1 508 887 8600",
    "sg:postcode":"01536",
    "sg:province":"MA",
    "sg:tags":[
        "salon"
    ],
    "wof:name":"Caribbean Tanning Inc",
    "wof:placetype":"venue"
},
  "geometry": {"coordinates":[-71.69366599999999,42.21631],"type":"Point"}
}