{
  "type": "Feature",
  "properties": {
    "iso:country":"US",
    "sg:address":"31 S Westfield St",
    "sg:city":"Feeding Hills",
    "sg:classifiers":[
        {
            "category":"Professional",
            "type":"Services"
        }
    ],
    "sg:phone":"+1 413 789 1723",
    "sg:postcode":"01030",
    "sg:province":"MA",
    "sg:tags":[
        "establishment"
    ],
    "wof:name":"Lower Pioneer Valley Edctnl",
    "wof:placetype":"venue"
},
  "geometry": {"coordinates":[-72.678707,42.06695],"type":"Point"}
}