{
  "type": "Feature",
  "properties": {
    "addr:full": "71 Emerson Rd East Walpole MA 02032",
    "addr:housenumber": "71",
    "addr:postcode": "02032",
    "addr:street": "Emerson Rd",
    "iso:country": "US",
    "sg:address": "71 Emerson Rd",
    "sg:city": "East Walpole",
    "sg:classifiers": [
      {
        "category": "Insurance",
        "subcategory": "Insurance Agent",
        "type": "Services"
      }
    ],
    "sg:phone": "+1 508 668 8025",
    "sg:postcode": "02032",
    "sg:province": "MA",
    "sg:website": "www.lifehealth.com",
    "wof:name": "Life \u0026 Health Advisor",
    "wof:placetype": "venue"
  },
  "geometry": {"coordinates":[-71.219958,42.150925],"type":"Point"}
}
