{
  "type": "Feature",
  "properties": {
    "addr:full": "1436 Main St Palmer MA 01069",
    "addr:housenumber": "1436",
    "addr:postcode": "01069",
    "addr:street": "Main St",
    "iso:country": "US",
    "sg:address": "1436 Main St",
    "sg:city": "Palmer",
    "sg:classifiers": [
      {
        "category": "Health Services",
        "subcategory": "Doctor",
        "type": "Services"
      }
    ],
    "sg:phone": "+1 413 283 3360",
    "sg:postcode": "01069",
    "sg:province": "MA",
    "sg:tags": [
      "dentist"
    ],
    "wof:name": "General Dentistry",
    "wof:placetype": "venue"
  },
  "geometry": {"coordinates":[-72.329987,42.157344],"type":"Point"}
}
