{
  "type": "Feature",
  "properties": {
    "addr:full":"945 Great Plain Ave # 17 Needham MA 02492",
    "addr:housenumber":"945",
    "addr:postcode":"02492",
    "addr:street":"Great Plain Ave # 17",
    "iso:country":"US",
    "sg:address":"945 Great Plain Ave # 17",
    "sg:city":"Needham",
    "sg:classifiers":[
        {
            "category":"Manufacturing",
            "subcategory":"Chemicals & Compounds",
            "type":"Manufacturing & Wholesale Goods"
        },
        {
            "category":"Building & Trades",
            "subcategory":"Pest Control",
            "type":"Services"
        }
    ],
    "sg:phone":"+1 781 449 6776",
    "sg:postcode":"02492",
    "sg:province":"MA",
    "sg:tags":[
        "equipment",
        "insecticide",
        "supply"
    ],
    "wof:name":"Shoofly",
    "wof:placetype":"venue"
},
  "geometry": {"coordinates":[-71.235876,42.28027],"type":"Point"}
}