{
  "type": "Feature",
  "properties": {
    "addr:full": "111 Fitchburg Rd Ayer MA 01432",
    "addr:housenumber": "111",
    "addr:postcode": "01432",
    "addr:street": "Fitchburg Rd",
    "iso:country": "US",
    "sg:address": "111 Fitchburg Rd",
    "sg:city": "Ayer",
    "sg:classifiers": [
      {
        "category": "Real Estate",
        "subcategory": "Surveying",
        "type": "Services"
      }
    ],
    "sg:phone": "+1 978 772 6232",
    "sg:postcode": "01432",
    "sg:province": "MA",
    "sg:tags": [
      "surveyor"
    ],
    "sg:website": "www.davideross.com",
    "wof:name": "David E Ross Assoc Inc",
    "wof:placetype": "venue"
  },
  "geometry": {"coordinates":[-71.60777,42.578004],"type":"Point"}
}
