{
  "type": "Feature",
  "properties": {
    "iso:country":"US",
    "sg:address":"72 Valleyview Dr",
    "sg:city":"Fitchburg",
    "sg:classifiers":[
        {
            "category":"Building & Trades",
            "subcategory":"Construction",
            "type":"Services"
        }
    ],
    "sg:phone":"+1 978 342 5800",
    "sg:postcode":"01420",
    "sg:province":"MA",
    "sg:tags":[
        "siding",
        "contractor"
    ],
    "wof:name":"Fred's Aluminum & Vinyl Siding",
    "wof:placetype":"venue"
},
  "geometry": {"coordinates":[-71.819339,42.588536],"type":"Point"}
}