{
  "type": "Feature",
  "properties": {
    "addr:full": "89 Elm Street Cambridge MA 02139",
    "addr:housenumber": "89",
    "addr:postcode": "02139",
    "addr:street": "Elm Street",
    "iso:country": "US",
    "sg:address": "89 Elm Street",
    "sg:city": "Cambridge",
    "sg:classifiers": [
      {
        "category": "Education",
        "subcategory": "School",
        "type": "Public Place"
      }
    ],
    "sg:phone": "+1 617 497 0063",
    "sg:postcode": "02139",
    "sg:province": "MA",
    "sg:tags": [
      "high",
      "middle",
      "elementary"
    ],
    "wof:name": "Cambridgeport Afterschool Programs",
    "wof:placetype": "venue"
  },
  "geometry": {"coordinates":[-71.097778,42.369185],"type":"Point"}
}
