{
  "type": "Feature",
  "properties": {
    "iso:country":"US",
    "sg:address":"25 Christina St",
    "sg:city":"Newton",
    "sg:classifiers":[
        {
            "category":"Professional",
            "subcategory":"Accounting & Tax Preparation",
            "type":"Services"
        }
    ],
    "sg:phone":"+1 617 969 3300",
    "sg:postcode":"02461",
    "sg:province":"MA",
    "sg:tags":[
        "accountant"
    ],
    "wof:name":"Braver & Co PC",
    "wof:placetype":"venue"
},
  "geometry": {"coordinates":[-71.21371600000001,42.306787],"type":"Point"}
}