{
  "type": "Feature",
  "properties": {
    "iso:country":"US",
    "sg:address":"535 College Hwy",
    "sg:city":"Southwick",
    "sg:classifiers":[
        {
            "category":"Personal",
            "subcategory":"Beauty Salon",
            "type":"Services"
        }
    ],
    "sg:phone":"+1 413 569 2100",
    "sg:postcode":"01077",
    "sg:province":"MA",
    "wof:name":"Nail Tique",
    "wof:placetype":"venue"
},
  "geometry": {"coordinates":[-72.767555,42.058412],"type":"Point"}
}