{
  "type": "Feature",
  "properties": {
    "iso:country":"US",
    "sg:address":"8 Main St",
    "sg:city":"Nantucket",
    "sg:classifiers":[
        {
            "category":"Food & Beverages",
            "subcategory":"Liquor & Beverages",
            "type":"Retail Goods"
        }
    ],
    "sg:phone":"+1 508 257 6365",
    "sg:postcode":"02554",
    "sg:province":"MA",
    "sg:tags":[
        "wine"
    ],
    "wof:name":"Siasconset Bookstore",
    "wof:placetype":"venue"
},
  "geometry": {"coordinates":[-70.097325,41.283685],"type":"Point"}
}