{
  "type": "Feature",
  "properties": {
    "addr:full": "8 Main St Nantucket MA 02554",
    "addr:housenumber": "8",
    "addr:postcode": "02554",
    "addr:street": "Main St",
    "iso:country": "US",
    "sg:address": "8 Main St",
    "sg:city": "Nantucket",
    "sg:classifiers": [
      {
        "category": "Food \u0026 Beverages",
        "subcategory": "Liquor \u0026 Beverages",
        "type": "Retail Goods"
      }
    ],
    "sg:phone": "+1 508 257 6365",
    "sg:postcode": "02554",
    "sg:province": "MA",
    "sg:tags": [
      "wine"
    ],
    "wof:name": "Siasconset Bookstore",
    "wof:placetype": "venue"
  },
  "geometry": {"coordinates":[-70.097325,41.283685],"type":"Point"}
}
