{
  "type": "Feature",
  "properties": {
    "addr:full": "955 Main St Winchester MA 01890",
    "addr:housenumber": "955",
    "addr:postcode": "01890",
    "addr:street": "Main St",
    "iso:country": "US",
    "ovtr:label": "Russell Hill Dental, 955 Main St Winchester MA US",
    "ovtr:similarity": 2.021656036376953,
    "sg:address": "955 Main St",
    "sg:city": "Winchester",
    "sg:classifiers": [
      {
        "category": "Health Services",
        "subcategory": "Doctor",
        "type": "Services"
      }
    ],
    "sg:phone": "+1 781 729 5041",
    "sg:postcode": "01890",
    "sg:province": "MA",
    "sg:tags": [
      "dentist"
    ],
    "wof:name": "Russell Hill Dental",
    "wof:placetype": "venue"
  },
  "geometry": {"coordinates":[-71.144068,42.463174],"type":"Point"}
}
