{
  "type": "Feature",
  "properties": {
    "addr:full":"160 E Main St Westborough MA 01581",
    "addr:housenumber":"160",
    "addr:postcode":"01581",
    "addr:street":"E Main St",
    "iso:country":"US",
    "sg:address":"160 E Main St",
    "sg:city":"Westborough",
    "sg:classifiers":[
        {
            "category":"Banks & Credit Unions",
            "subcategory":"Investment Brokerage",
            "type":"Services"
        }
    ],
    "sg:phone":"+1 508 366 1202",
    "sg:postcode":"01581",
    "sg:province":"MA",
    "sg:tags":[
        "consultant",
        "planning",
        "financial"
    ],
    "wof:name":"Papaz Financial Svc",
    "wof:placetype":"venue"
},
  "geometry": {"coordinates":[-71.59859299999999,42.284651],"type":"Point"}
}