{
  "type": "Feature",
  "properties": {
    "addr:full":"314 Central St Gardner MA 01440",
    "addr:housenumber":"314",
    "addr:postcode":"01440",
    "addr:street":"Central St",
    "iso:country":"US",
    "sg:address":"314 Central St",
    "sg:city":"Gardner",
    "sg:classifiers":[
        {
            "category":"Shopping",
            "subcategory":"Hobbies, Toys, & Games",
            "type":"Retail Goods"
        }
    ],
    "sg:phone":"+1 978 630 2355",
    "sg:postcode":"01440",
    "sg:province":"MA",
    "sg:tags":[
        "model",
        "supply"
    ],
    "wof:name":"B C Enterprises",
    "wof:placetype":"venue"
},
  "geometry": {"coordinates":[-71.994423,42.576599],"type":"Point"}
}