{
  "type": "Feature",
  "properties": {
    "iso:country":"US",
    "sg:address":"11 Dexter Mill Dr",
    "sg:city":"Teaticket",
    "sg:classifiers":[
        {
            "category":"Building & Trades",
            "subcategory":"Construction",
            "type":"Services"
        }
    ],
    "sg:phone":"+1 508 540 4154",
    "sg:postcode":"02536",
    "sg:province":"MA",
    "sg:tags":[
        "contractor"
    ],
    "wof:name":"Sullivan, Dr Builders",
    "wof:placetype":"venue"
},
  "geometry": {"coordinates":[-70.57984399999999,41.571071],"type":"Point"}
}