{
  "type": "Feature",
  "properties": {
    "addr:full": "16 Lambeth Park Rd Fairhaven MA 02719",
    "addr:housenumber": "16",
    "addr:postcode": "02719",
    "addr:street": "Lambeth Park Rd",
    "iso:country": "US",
    "sg:address": "16 Lambeth Park Rd",
    "sg:city": "Fairhaven",
    "sg:classifiers": [
      {
        "category": "Home \u0026 Garden",
        "subcategory": "Furniture",
        "type": "Retail Goods"
      }
    ],
    "sg:phone": "+1 508 994 1818",
    "sg:postcode": "02719",
    "sg:province": "MA",
    "wof:name": "Alex's Furniture \u0026 Bedding",
    "wof:placetype": "venue"
  },
  "geometry": {"coordinates":[-70.887843,41.65039],"type":"Point"}
}
