{
  "type": "Feature",
  "properties": {
    "addr:full": "428 Sanford Rd Westport MA 02790",
    "addr:housenumber": "428",
    "addr:postcode": "02790",
    "addr:street": "Sanford Rd",
    "iso:country": "US",
    "sg:address": "428 Sanford Rd",
    "sg:city": "Westport",
    "sg:classifiers": [
      {
        "category": "Building \u0026 Trades",
        "subcategory": "Construction",
        "type": "Services"
      }
    ],
    "sg:phone": "+1   ",
    "sg:postcode": "02790",
    "sg:province": "MA",
    "sg:tags": [
      "contractor"
    ],
    "wof:name": "F C Installations Inc",
    "wof:placetype": "venue"
  },
  "geometry": {"coordinates":[-71.107237,41.656719],"type":"Point"}
}
