{
  "type": "Feature",
  "properties": {
    "iso:country":"US",
    "sg:address":"7 Kilby St",
    "sg:city":"Woburn",
    "sg:classifiers":[
        {
            "category":"Personal",
            "subcategory":"Nail Salon",
            "type":"Services"
        }
    ],
    "sg:phone":"+1 781 937 3141",
    "sg:postcode":"01801",
    "sg:province":"MA",
    "wof:name":"Nail Studio the",
    "wof:placetype":"venue"
},
  "geometry": {"coordinates":[-71.15270200000001,42.486],"type":"Point"}
}