{
  "type": "Feature",
  "properties": {
    "iso:country":"US",
    "sg:address":"980 Salem St",
    "sg:city":"Lynnfield",
    "sg:classifiers":[
        {
            "category":"Building & Trades",
            "subcategory":"Construction",
            "type":"Services"
        }
    ],
    "sg:phone":"+1 781 595 0194",
    "sg:postcode":"01940",
    "sg:province":"MA",
    "sg:tags":[
        "house"
    ],
    "wof:name":"JNJ Enterprises",
    "wof:placetype":"venue"
},
  "geometry": {"coordinates":[-70.99260099999999,42.512383],"type":"Point"}
}