{
  "type": "Feature",
  "properties": {
    "addr:full": "980 Salem St Lynnfield MA 01940",
    "addr:housenumber": "980",
    "addr:postcode": "01940",
    "addr:street": "Salem St",
    "iso:country": "US",
    "sg:address": "980 Salem St",
    "sg:city": "Lynnfield",
    "sg:classifiers": [
      {
        "category": "Building \u0026 Trades",
        "subcategory": "Construction",
        "type": "Services"
      }
    ],
    "sg:phone": "+1 781 595 0194",
    "sg:postcode": "01940",
    "sg:province": "MA",
    "sg:tags": [
      "house"
    ],
    "wof:name": "JNJ Enterprises",
    "wof:placetype": "venue"
  },
  "geometry": {"coordinates":[-70.992601,42.512383],"type":"Point"}
}
