{
  "type": "Feature",
  "properties": {
    "iso:country":"US",
    "sg:address":"430 Liberty St",
    "sg:city":"Hanson",
    "sg:classifiers":[
        {
            "category":"Shopping",
            "subcategory":"Hobbies, Toys, & Games",
            "type":"Retail Goods"
        }
    ],
    "sg:phone":"+1 781 294 1447",
    "sg:postcode":"02341",
    "sg:province":"MA",
    "wof:name":"Rhyme 'n Reason",
    "wof:placetype":"venue"
},
  "geometry": {"coordinates":[-70.876734,42.071107],"type":"Point"}
}