{
  "type": "Feature",
  "properties": {
    "addr:full": "36 McGeoch St Abington MA 02351",
    "addr:housenumber": "36",
    "addr:postcode": "02351",
    "addr:street": "Mcgeoch St",
    "iso:country": "US",
    "sg:address": "36 McGeoch St",
    "sg:city": "Abington",
    "sg:classifiers": [
      {
        "category": "Freight",
        "type": "Transportation"
      }
    ],
    "sg:phone": "+1 781 871 6997",
    "sg:postcode": "02351",
    "sg:province": "MA",
    "sg:tags": [
      "trucking"
    ],
    "wof:name": "Chisholm \u0026 Son Trucking",
    "wof:placetype": "venue"
  },
  "geometry": {"coordinates":[-70.971899,42.138598],"type":"Point"}
}
