{
  "type": "Feature",
  "properties": {
    "iso:country":"US",
    "sg:address":"36 McGeoch St",
    "sg:city":"Abington",
    "sg:classifiers":[
        {
            "category":"Freight",
            "type":"Transportation"
        }
    ],
    "sg:phone":"+1 781 871 6997",
    "sg:postcode":"02351",
    "sg:province":"MA",
    "sg:tags":[
        "trucking"
    ],
    "wof:name":"Chisholm & Son Trucking",
    "wof:placetype":"venue"
},
  "geometry": {"coordinates":[-70.97189899999999,42.138598],"type":"Point"}
}