{
  "type": "Feature",
  "properties": {
    "addr:full":"25 Ridge Way North Andover MA 01845",
    "addr:housenumber":"25",
    "addr:postcode":"01845",
    "addr:street":"Ridge Way",
    "iso:country":"US",
    "sg:address":"25 Ridge Way",
    "sg:city":"North Andover",
    "sg:classifiers":[
        {
            "category":"Airline",
            "type":"Transportation"
        }
    ],
    "sg:phone":"+1   ",
    "sg:postcode":"01845",
    "sg:province":"MA",
    "sg:tags":[
        "scheduled",
        "air"
    ],
    "wof:name":"Jet Cab LLC",
    "wof:placetype":"venue"
},
  "geometry": {"coordinates":[-71.101827,42.661326],"type":"Point"}
}