{
  "type": "Feature",
  "properties": {
    "addr:full":"39 Fairmont St Cambridge MA 02139",
    "addr:housenumber":"39",
    "addr:postcode":"02139",
    "addr:street":"Fairmont St",
    "iso:country":"US",
    "sg:address":"39 Fairmont St",
    "sg:city":"Cambridge",
    "sg:classifiers":[
        {
            "category":"Building & Trades",
            "subcategory":"Locksmith",
            "type":"Services"
        }
    ],
    "sg:phone":"+1 617 299 2090",
    "sg:postcode":"02139",
    "sg:province":"MA",
    "sg:tags":[
        "key"
    ],
    "wof:name":"Fair Emergency Locksmith",
    "wof:placetype":"venue"
},
  "geometry": {"coordinates":[-71.111014,42.361966],"type":"Point"}
}