{
  "type": "Feature",
  "properties": {
    "addr:full":"63 Winthrop St Taunton MA 02780",
    "addr:housenumber":"63",
    "addr:postcode":"02780",
    "addr:street":"Winthrop St",
    "iso:country":"US",
    "sg:address":"63 Winthrop St",
    "sg:city":"Taunton",
    "sg:classifiers":[
        {
            "category":"Banks & Credit Unions",
            "subcategory":"Investment Brokerage",
            "type":"Services"
        }
    ],
    "sg:phone":"+1 508 823 4500",
    "sg:postcode":"02780",
    "sg:province":"MA",
    "sg:tags":[
        "advisory",
        "financial"
    ],
    "wof:name":"UBS Financial Svc",
    "wof:placetype":"venue"
},
  "geometry": {"coordinates":[-71.096569,41.897929],"type":"Point"}
}