{
  "type": "Feature",
  "properties": {
    "iso:country":"US",
    "sg:address":"13 Franklin St",
    "sg:city":"Salem",
    "sg:classifiers":[
        {
            "category":"Wholesale",
            "subcategory":"Fruits & Vegetables",
            "type":"Manufacturing & Wholesale Goods"
        }
    ],
    "sg:phone":"+1 978 741 1668",
    "sg:postcode":"01970",
    "sg:province":"MA",
    "wof:name":"Garden Gate",
    "wof:placetype":"venue"
},
  "geometry": {"coordinates":[-70.899547,42.525728],"type":"Point"}
}