{
  "type": "Feature",
  "properties": {
    "addr:full": "29 Hale Rd Stow MA 01775",
    "addr:housenumber": "29",
    "addr:postcode": "01775",
    "addr:street": "Hale Rd",
    "iso:country": "US",
    "sg:address": "29 Hale Rd",
    "sg:city": "Stow",
    "sg:classifiers": [
      {
        "category": "Professional",
        "subcategory": "Management \u0026 Consulting",
        "type": "Services"
      }
    ],
    "sg:phone": "+1 978 562 9084",
    "sg:postcode": "01775",
    "sg:province": "MA",
    "sg:tags": [
      "construction"
    ],
    "wof:name": "Maxton Technology Inc",
    "wof:placetype": "venue"
  },
  "geometry": {"coordinates":[-71.491381,42.397381],"type":"Point"}
}
