{
  "type": "Feature",
  "properties": {
    "iso:country":"US",
    "sg:address":"29 Hale Rd",
    "sg:city":"Stow",
    "sg:classifiers":[
        {
            "category":"Professional",
            "subcategory":"Management & Consulting",
            "type":"Services"
        }
    ],
    "sg:phone":"+1 978 562 9084",
    "sg:postcode":"01775",
    "sg:province":"MA",
    "sg:tags":[
        "construction"
    ],
    "wof:name":"Maxton Technology Inc",
    "wof:placetype":"venue"
},
  "geometry": {"coordinates":[-71.491381,42.397381],"type":"Point"}
}