{
  "type": "Feature",
  "properties": {
    "iso:country":"US",
    "sg:address":"2460 Boston Rd",
    "sg:city":"Wilbraham",
    "sg:classifiers":[
        {
            "category":"Wholesale",
            "subcategory":"Vending Machines",
            "type":"Manufacturing & Wholesale Goods"
        }
    ],
    "sg:phone":"+1 413 596 9482",
    "sg:postcode":"01095",
    "sg:province":"MA",
    "wof:name":"Fun Stop Cigarette & Amusement",
    "wof:placetype":"venue"
},
  "geometry": {"coordinates":[-72.444836,42.148928],"type":"Point"}
}