{
  "type": "Feature",
  "properties": {
    "iso:country":"US",
    "sg:address":"10 Waban St",
    "sg:city":"Wellesley",
    "sg:classifiers":[
        {
            "category":"Health Services",
            "subcategory":"Clinic",
            "type":"Services"
        }
    ],
    "sg:phone":"+1 781 235 1769",
    "sg:postcode":"02482",
    "sg:province":"MA",
    "sg:tags":[
        "wellness",
        "program"
    ],
    "wof:name":"Institute For Wellness Edctn",
    "wof:placetype":"venue"
},
  "geometry": {"coordinates":[-71.296226,42.294149],"type":"Point"}
}