{
  "type": "Feature",
  "properties": {
    "addr:full": "34 Pratt St Fitchburg MA 01420",
    "addr:housenumber": "34",
    "addr:postcode": "01420",
    "addr:street": "Pratt St",
    "iso:country": "US",
    "sg:address": "34 Pratt St",
    "sg:city": "Fitchburg",
    "sg:classifiers": [
      {
        "category": "Building \u0026 Trades",
        "subcategory": "Construction",
        "type": "Services"
      }
    ],
    "sg:phone": "+1 978 345 0444",
    "sg:postcode": "01420",
    "sg:province": "MA",
    "sg:tags": [
      "general",
      "contractor"
    ],
    "wof:name": "A \u0026 R Construction",
    "wof:placetype": "venue"
  },
  "geometry": {"coordinates":[-71.818012,42.576639],"type":"Point"}
}
