{
  "type": "Feature",
  "properties": {
    "addr:full": "4 Hartley Rd Rochester MA 02770",
    "addr:housenumber": "4",
    "addr:postcode": "02770",
    "addr:street": "Hartley Rd",
    "iso:country": "US",
    "ovtr:label": "Lloyd's Market, 4 Hartley Rd Rochester MA US",
    "ovtr:similarity": 2.610940933227539,
    "sg:address": "4 Hartley Rd",
    "sg:city": "Rochester",
    "sg:classifiers": [
      {
        "category": "Food \u0026 Beverages",
        "subcategory": "Groceries \u0026 Convenience Stores",
        "type": "Retail Goods"
      }
    ],
    "sg:phone": "+1 508 763 5673",
    "sg:postcode": "02770",
    "sg:province": "MA",
    "sg:tags": [
      "grocer"
    ],
    "wof:name": "Lloyd's Market",
    "wof:placetype": "venue"
  },
  "geometry": {"coordinates":[-70.867279,41.744139],"type":"Point"}
}
