{
  "type": "Feature",
  "properties": {
    "iso:country":"US",
    "sg:address":"648 Harvard St",
    "sg:city":"East Bridgewater",
    "sg:classifiers":[
        {
            "category":"Building & Trades",
            "subcategory":"Construction",
            "type":"Services"
        }
    ],
    "sg:phone":"+1 508 690 1205",
    "sg:postcode":"02333",
    "sg:province":"MA",
    "sg:tags":[
        "excavating",
        "contractor"
    ],
    "wof:name":"Coots Brothers Inc",
    "wof:placetype":"venue"
},
  "geometry": {"coordinates":[-70.940676,42.05825],"type":"Point"}
}