{
  "type": "Feature",
  "properties": {
    "addr:full":"5 Morton Ter Milton MA 02186",
    "addr:housenumber":"5",
    "addr:postcode":"02186",
    "addr:street":"Morton Ter",
    "iso:country":"US",
    "sg:address":"5 Morton Ter",
    "sg:city":"Milton",
    "sg:classifiers":[
        {
            "category":"Professional",
            "subcategory":"Management & Consulting",
            "type":"Services"
        }
    ],
    "sg:phone":"+1 617 696 7430",
    "sg:postcode":"02186",
    "sg:province":"MA",
    "wof:name":"Community Consultation",
    "wof:placetype":"venue"
},
  "geometry": {"coordinates":[-71.070813,42.269564],"type":"Point"}
}