{
  "type": "Feature",
  "properties": {
    "iso:country":"US",
    "sg:address":"15 Higgins Rd",
    "sg:city":"Marblehead",
    "sg:classifiers":[
        {
            "category":"Building & Trades",
            "subcategory":"Construction",
            "type":"Services"
        }
    ],
    "sg:phone":"+1 781 631 2207",
    "sg:postcode":"01945",
    "sg:province":"MA",
    "sg:tags":[
        "repairing",
        "remodeling",
        "contractor"
    ],
    "wof:name":"Nova Construction & Remodeling",
    "wof:placetype":"venue"
},
  "geometry": {"coordinates":[-70.86850099999999,42.495499],"type":"Point"}
}