{
  "type": "Feature",
  "properties": {
    "addr:full":"681 Falmouth Rd Mashpee MA 02649",
    "addr:housenumber":"681",
    "addr:postcode":"02649",
    "addr:street":"Falmouth Rd",
    "iso:country":"US",
    "sg:address":"681 Falmouth Rd",
    "sg:city":"Mashpee",
    "sg:classifiers":[
        {
            "category":"Building & Trades",
            "subcategory":"Construction",
            "type":"Services"
        }
    ],
    "sg:phone":"+1 508 477 6549",
    "sg:postcode":"02649",
    "sg:province":"MA",
    "sg:tags":[
        "contractor"
    ],
    "wof:name":"Agricola Construction",
    "wof:placetype":"venue"
},
  "geometry": {"coordinates":[-70.490617,41.611179],"type":"Point"}
}