{
  "type": "Feature",
  "properties": {
    "addr:full":"14 Payson St Lexington MA 02421",
    "addr:housenumber":"14",
    "addr:postcode":"02421",
    "addr:street":"Payson St",
    "iso:country":"US",
    "sg:address":"14 Payson St",
    "sg:city":"Lexington",
    "sg:classifiers":[
        {
            "category":"Building & Trades",
            "subcategory":"Plumbing",
            "type":"Services"
        }
    ],
    "sg:phone":"+1 781 652 8610",
    "sg:postcode":"02421",
    "sg:province":"MA",
    "sg:tags":[
        "heating",
        "specialty"
    ],
    "wof:name":"J D Heating & Air Conditioning",
    "wof:placetype":"venue"
},
  "geometry": {"coordinates":[-71.239751,42.43281],"type":"Point"}
}