{
  "type": "Feature",
  "properties": {
    "addr:full": "537 Gray Ter Swansea MA 02764",
    "addr:housenumber": "537",
    "addr:postcode": "02764",
    "addr:street": "Gray Ter",
    "iso:country": "US",
    "sg:address": "537 Gray Ter",
    "sg:city": "Swansea",
    "sg:classifiers": [
      {
        "category": "Retail",
        "subcategory": "Car Wash",
        "type": "Services"
      }
    ],
    "sg:phone": "+1 508 676 3237",
    "sg:postcode": "02764",
    "sg:province": "MA",
    "sg:tags": [
      "polishing",
      "washing"
    ],
    "wof:name": "KWIK Lube N Tune Inc",
    "wof:placetype": "venue"
  },
  "geometry": {"coordinates":[-71.124572,41.854583],"type":"Point"}
}
