{
  "type": "Feature",
  "properties": {
    "iso:country":"US",
    "sg:address":"561 Moody St",
    "sg:city":"Waltham",
    "sg:classifiers":[
        {
            "category":"Home & Garden",
            "subcategory":"Furniture",
            "type":"Retail Goods"
        }
    ],
    "sg:phone":"+1 781 891 9598",
    "sg:postcode":"02453",
    "sg:province":"MA",
    "sg:tags":[
        "cabinet"
    ],
    "wof:name":"Penny Pincher",
    "wof:placetype":"venue"
},
  "geometry": {"coordinates":[-71.237972,42.366335],"type":"Point"}
}