{
  "type": "Feature",
  "properties": {
    "addr:full": "561 Moody St Waltham MA 02453",
    "addr:housenumber": "561",
    "addr:postcode": "02453",
    "addr:street": "Moody St",
    "iso:country": "US",
    "sg:address": "561 Moody St",
    "sg:city": "Waltham",
    "sg:classifiers": [
      {
        "category": "Home \u0026 Garden",
        "subcategory": "Furniture",
        "type": "Retail Goods"
      }
    ],
    "sg:phone": "+1 781 891 9598",
    "sg:postcode": "02453",
    "sg:province": "MA",
    "sg:tags": [
      "cabinet"
    ],
    "wof:name": "Penny Pincher",
    "wof:placetype": "venue"
  },
  "geometry": {"coordinates":[-71.237972,42.366335],"type":"Point"}
}
