{
  "type": "Feature",
  "properties": {
    "addr:full": "130 Endicott St Boston MA 02113",
    "addr:housenumber": "130",
    "addr:postcode": "02113",
    "addr:street": "Endicott St",
    "iso:country": "US",
    "sg:address": "130 Endicott St",
    "sg:city": "Boston",
    "sg:classifiers": [
      {
        "category": "Building \u0026 Trades",
        "subcategory": "Locksmith",
        "type": "Services"
      }
    ],
    "sg:phone": "+1 617 517 5766",
    "sg:postcode": "02113",
    "sg:province": "MA",
    "sg:tags": [
      "key"
    ],
    "wof:name": "Emergency A Locksmith",
    "wof:placetype": "venue"
  },
  "geometry": {"coordinates":[-71.057365,42.364769],"type":"Point"}
}
