{
  "type": "Feature",
  "properties": {
    "addr:full":"79 Newell Pond Rd Greenfield MA 01301",
    "addr:housenumber":"79",
    "addr:postcode":"01301",
    "addr:street":"Newell Pond Rd",
    "iso:country":"US",
    "sg:address":"79 Newell Pond Rd",
    "sg:city":"Greenfield",
    "sg:classifiers":[
        {
            "category":"Building & Trades",
            "subcategory":"Construction",
            "type":"Services"
        }
    ],
    "sg:phone":"+1   ",
    "sg:postcode":"01301",
    "sg:province":"MA",
    "sg:tags":[
        "house"
    ],
    "wof:name":"Gilman Roofing & Home Remodeli",
    "wof:placetype":"venue"
},
  "geometry": {"coordinates":[-72.576132,42.63859],"type":"Point"}
}