{
  "type": "Feature",
  "properties": {
    "iso:country":"US",
    "sg:address":"407 Sumner St",
    "sg:city":"Stoughton",
    "sg:classifiers":[
        {
            "category":"Building & Trades",
            "subcategory":"Plumbing",
            "type":"Services"
        }
    ],
    "sg:phone":"+1   ",
    "sg:postcode":"02072",
    "sg:province":"MA",
    "sg:tags":[
        "contractor"
    ],
    "wof:name":"DAndrea Plumbing Co",
    "wof:placetype":"venue"
},
  "geometry": {"coordinates":[-71.091026,42.114423],"type":"Point"}
}