{
  "type": "Feature",
  "properties": {
    "addr:full":"225 Water St Plymouth MA 02360",
    "addr:housenumber":"225",
    "addr:postcode":"02360",
    "addr:street":"Water St",
    "iso:country":"US",
    "sg:address":"225 Water St",
    "sg:city":"Plymouth",
    "sg:classifiers":[
        {
            "category":"Shopping",
            "subcategory":"Computers & Home Electronics",
            "type":"Retail Goods"
        }
    ],
    "sg:phone":"+1 508 830 9417",
    "sg:postcode":"02360",
    "sg:province":"MA",
    "sg:tags":[
        "equipment",
        "satellite",
        "system"
    ],
    "wof:name":"Plymouth Network Satellite Ofc",
    "wof:placetype":"venue"
},
  "geometry": {"coordinates":[-70.67147199999999,41.965306],"type":"Point"}
}