{
  "type": "Feature",
  "properties": {
    "addr:full":"267 Boston Ave Medford MA 02155",
    "addr:housenumber":"267",
    "addr:postcode":"02155",
    "addr:street":"Boston Ave",
    "iso:country":"US",
    "sg:address":"267 Boston Ave",
    "sg:city":"Medford",
    "sg:classifiers":[
        {
            "category":"Home & Garden",
            "subcategory":"Household Appliances",
            "type":"Retail Goods"
        }
    ],
    "sg:phone":"+1 781 396 0290",
    "sg:postcode":"02155",
    "sg:province":"MA",
    "sg:tags":[
        "machine",
        "washing"
    ],
    "wof:name":"RCA Svc Co",
    "wof:placetype":"venue"
},
  "geometry": {"coordinates":[-71.12476599999999,42.413475],"type":"Point"}
}