{
  "type": "Feature",
  "properties": {
    "addr:full": "1 Pemberton Sq Boston MA 02108",
    "addr:housenumber": "1",
    "addr:postcode": "02108",
    "addr:street": "Pemberton Sq",
    "iso:country": "US",
    "sg:address": "1 Pemberton Sq",
    "sg:city": "Boston",
    "sg:classifiers": [
      {
        "category": "Government",
        "subcategory": "Police Station",
        "type": "Public Place"
      }
    ],
    "sg:phone": "+1   ",
    "sg:postcode": "02108",
    "sg:province": "MA",
    "sg:tags": [
      "protection"
    ],
    "wof:name": "Sheriffs Office",
    "wof:placetype": "venue"
  },
  "geometry": {"coordinates":[-71.060313,42.358672],"type":"Point"}
}
