{
  "type": "Feature",
  "properties": {
    "addr:full":"189 Hadley St South Hadley MA 01075",
    "addr:housenumber":"189",
    "addr:postcode":"01075",
    "addr:street":"Hadley St",
    "iso:country":"US",
    "sg:address":"189 Hadley St",
    "sg:city":"South Hadley",
    "sg:classifiers":[
        {
            "category":"Building & Trades",
            "subcategory":"Electrical",
            "type":"Services"
        }
    ],
    "sg:phone":"+1 413 535 0370",
    "sg:postcode":"01075",
    "sg:province":"MA",
    "sg:tags":[
        "electric",
        "contractor"
    ],
    "wof:name":"LA Pierre Electric Co",
    "wof:placetype":"venue"
},
  "geometry": {"coordinates":[-72.588786,42.279077],"type":"Point"}
}