{
  "type": "Feature",
  "properties": {
    "addr:full": "301 Newbury St Danvers MA 01923",
    "addr:housenumber": "301",
    "addr:postcode": "01923",
    "addr:street": "Newbury St",
    "iso:country": "US",
    "sg:address": "301 Newbury St",
    "sg:city": "Danvers",
    "sg:classifiers": [
      {
        "category": "Bakery",
        "type": "Food \u0026 Drink"
      },
      {
        "category": "Coffee \u0026 Tea",
        "type": "Food \u0026 Drink"
      },
      {
        "category": "Bagels",
        "type": "Food \u0026 Drink"
      },
      {
        "category": "Donuts",
        "type": "Food \u0026 Drink"
      }
    ],
    "sg:menulink": "http://www.allmenus.com/ma/danvers/142831-dunkin-donuts/menu/",
    "sg:phone": "+1 978 762 4444",
    "sg:postcode": "01923",
    "sg:province": "MA",
    "sg:tags": [
      "american",
      "diner",
      "pastry"
    ],
    "wof:name": "Dunkin' Donuts",
    "wof:placetype": "venue"
  },
  "geometry": {"coordinates":[-70.964693,42.584764],"type":"Point"}
}
