{
  "type": "Feature",
  "properties": {
    "addr:full":"224 Clarendon Street Boston MA 02116",
    "addr:housenumber":"224",
    "addr:postcode":"02116",
    "addr:street":"Clarendon Street",
    "iso:country":"US",
    "sg:address":"224 Clarendon Street",
    "sg:city":"Boston",
    "sg:classifiers":[
        {
            "category":"Professional",
            "subcategory":"Lawyer & Legal Services",
            "type":"Services"
        }
    ],
    "sg:phone":"+1 617 859 1814",
    "sg:postcode":"02116",
    "sg:province":"MA",
    "wof:name":"Yorra Hubert I Lwyr",
    "wof:placetype":"venue"
},
  "geometry": {"coordinates":[-71.07555600000001,42.351328],"type":"Point"}
}