{
  "type": "Feature",
  "properties": {
    "addr:full":"100 Maple Ave Sheffield MA 01257",
    "addr:housenumber":"100",
    "addr:postcode":"01257",
    "addr:street":"Maple Ave",
    "iso:country":"US",
    "sg:address":"100 Maple Ave",
    "sg:city":"Sheffield",
    "sg:classifiers":[
        {
            "category":"Building & Trades",
            "subcategory":"Construction",
            "type":"Services"
        }
    ],
    "sg:phone":"+1 413 229 2346",
    "sg:postcode":"01257",
    "sg:province":"MA",
    "sg:tags":[
        "general",
        "contractor"
    ],
    "wof:name":"J W Woodworking",
    "wof:placetype":"venue"
},
  "geometry": {"coordinates":[-73.348382,42.110532],"type":"Point"}
}