{
  "type": "Feature",
  "properties": {
    "addr:full": "269 Page Blvd Springfield MA 01104",
    "addr:housenumber": "269",
    "addr:postcode": "01104",
    "addr:street": "Page Blvd",
    "iso:country": "US",
    "sg:address": "269 Page Blvd",
    "sg:city": "Springfield",
    "sg:classifiers": [
      {
        "category": "Autos \u0026 Motor Vehicles",
        "subcategory": "Auto Supplies",
        "type": "Retail Goods"
      }
    ],
    "sg:phone": "+1 413 739 5369",
    "sg:postcode": "01104",
    "sg:province": "MA",
    "sg:tags": [
      "tire"
    ],
    "wof:name": "American Tire",
    "wof:placetype": "venue"
  },
  "geometry": {"coordinates":[-72.561317,42.13392],"type":"Point"}
}
