{
  "type": "Feature",
  "properties": {
    "addr:full": "16 Pillsbury Ln Georgetown MA 01833",
    "addr:housenumber": "16",
    "addr:postcode": "01833",
    "addr:street": "Pillsbury Ln",
    "iso:country": "US",
    "sg:address": "16 Pillsbury Ln",
    "sg:city": "Georgetown",
    "sg:classifiers": [
      {
        "category": "Professional",
        "subcategory": "Business Services",
        "type": "Services"
      }
    ],
    "sg:phone": "+1 978 352 4530",
    "sg:postcode": "01833",
    "sg:province": "MA",
    "sg:tags": [
      "plant",
      "design",
      "maintenance"
    ],
    "wof:name": "Belle's Blossoms",
    "wof:placetype": "venue"
  },
  "geometry": {"coordinates":[-70.981124,42.721476],"type":"Point"}
}
