{
  "type": "Feature",
  "properties": {
    "addr:full": "143 Hamilton St Worcester MA 01604",
    "addr:housenumber": "143",
    "addr:postcode": "01604",
    "addr:street": "Hamilton St",
    "iso:country": "US",
    "sg:address": "143 Hamilton St",
    "sg:city": "Worcester",
    "sg:classifiers": [
      {
        "category": "Retail",
        "subcategory": "Auto Repair",
        "type": "Services"
      }
    ],
    "sg:phone": "+1 508 752 2272",
    "sg:postcode": "01604",
    "sg:province": "MA",
    "sg:tags": [
      "repairing",
      "automobile"
    ],
    "wof:name": "All Make Auto \u0026 Diesel",
    "wof:placetype": "venue"
  },
  "geometry": {"coordinates":[-71.777428,42.256284],"type":"Point"}
}
