{
  "type": "Feature",
  "properties": {
    "addr:full":"1212 Kempton St New Bedford MA 02740",
    "addr:housenumber":"1212",
    "addr:postcode":"02740",
    "addr:street":"Kempton St",
    "iso:country":"US",
    "sg:address":"1212 Kempton St",
    "sg:city":"New Bedford",
    "sg:classifiers":[
        {
            "category":"Health Services",
            "subcategory":"Doctor",
            "type":"Services"
        }
    ],
    "sg:phone":"+1 508 999 2727",
    "sg:postcode":"02740",
    "sg:province":"MA",
    "sg:tags":[
        "dentist"
    ],
    "wof:name":"Buttonwood Dental Assoc",
    "wof:placetype":"venue"
},
  "geometry": {"coordinates":[-70.957764,41.636359],"type":"Point"}
}