{
  "type": "Feature",
  "properties": {
    "iso:country":"US",
    "sg:address":"746 Chief Justice Cushing Hwy",
    "sg:city":"Cohasset",
    "sg:classifiers":[
        {
            "category":"Home & Garden",
            "subcategory":"Furniture",
            "type":"Retail Goods"
        }
    ],
    "sg:phone":"+1 781 383 0012",
    "sg:postcode":"02025",
    "sg:province":"MA",
    "sg:tags":[
        "solid",
        "top",
        "material",
        "surface",
        "counter"
    ],
    "wof:name":"B C Tops",
    "wof:placetype":"venue"
},
  "geometry": {"coordinates":[-70.80394699999999,42.222821],"type":"Point"}
}