{
  "type": "Feature",
  "properties": {
    "addr:full":"63 Moore St Boston MA 02128",
    "addr:housenumber":"63",
    "addr:postcode":"02128",
    "addr:street":"Moore St",
    "iso:country":"US",
    "sg:address":"63 Moore St",
    "sg:city":"Boston",
    "sg:classifiers":[
        {
            "category":"Organizations",
            "subcategory":"Religious Organization",
            "type":"Services"
        }
    ],
    "sg:phone":"+1 617 569 8070",
    "sg:postcode":"02128",
    "sg:province":"MA",
    "wof:name":"Universal Church",
    "wof:placetype":"venue"
},
  "geometry": {"coordinates":[-71.018272,42.382702],"type":"Point"}
}