{
  "type": "Feature",
  "properties": {
    "addr:full":"4 Longfellow Way Boylston MA 01505",
    "addr:housenumber":"4",
    "addr:postcode":"01505",
    "addr:street":"Longfellow Way",
    "iso:country":"US",
    "sg:address":"4 Longfellow Way",
    "sg:city":"Boylston",
    "sg:classifiers":[
        {
            "category":"Professional",
            "subcategory":"Computer Services",
            "type":"Services"
        }
    ],
    "sg:phone":"+1   ",
    "sg:postcode":"01505",
    "sg:province":"MA",
    "sg:tags":[
        "related"
    ],
    "wof:name":"Sevier Systems Group",
    "wof:placetype":"venue"
},
  "geometry": {"coordinates":[-71.713044,42.337714],"type":"Point"}
}