{
  "type": "Feature",
  "properties": {
    "iso:country":"US",
    "sg:address":"321 Allen St",
    "sg:city":"Springfield",
    "sg:classifiers":[
        {
            "category":"Autos & Motor Vehicles",
            "subcategory":"Automobile Sales",
            "type":"Retail Goods"
        }
    ],
    "sg:phone":"+1 413 736 4506",
    "sg:postcode":"01108",
    "sg:province":"MA",
    "sg:tags":[
        "used"
    ],
    "wof:name":"Bailey Motors",
    "wof:placetype":"venue"
},
  "geometry": {"coordinates":[-72.55149900000001,42.093435],"type":"Point"}
}