{
  "type": "Feature",
  "properties": {
    "iso:country":"US",
    "sg:address":"Who's On First 19 Yawkey Way",
    "sg:city":"Boston",
    "sg:classifiers":[
        {
            "category":"Bars & Pubs",
            "subcategory":"Nightclub",
            "type":"Food & Drink"
        }
    ],
    "sg:phone":"+1 866 400 6253",
    "sg:postcode":"01906",
    "sg:province":"MA",
    "sg:tags":[
        "nightlife"
    ],
    "sg:website":"www.maleencounterboston.com",
    "wof:name":"The Male Encounter",
    "wof:placetype":"venue"
},
  "geometry": {"coordinates":[-71.09889200000001,42.346089],"type":"Point"}
}