{
  "type": "Feature",
  "properties": {
    "addr:full": "Who's On First 19 Yawkey Way Boston MA 01906",
    "addr:housenumber": "19",
    "addr:postcode": "01906",
    "addr:street": "Yawkey Way",
    "iso:country": "US",
    "sg:address": "Who's On First 19 Yawkey Way",
    "sg:city": "Boston",
    "sg:classifiers": [
      {
        "category": "Bars \u0026 Pubs",
        "subcategory": "Nightclub",
        "type": "Food \u0026 Drink"
      }
    ],
    "sg:phone": "+1 866 400 6253",
    "sg:postcode": "01906",
    "sg:province": "MA",
    "sg:tags": [
      "nightlife"
    ],
    "sg:website": "www.maleencounterboston.com",
    "wof:name": "The Male Encounter",
    "wof:placetype": "venue"
  },
  "geometry": {"coordinates":[-71.098892,42.346089],"type":"Point"}
}
