{
  "type": "Feature",
  "properties": {
    "addr:full":"18 Fenno Dr Westminster MA 01473",
    "addr:housenumber":"18",
    "addr:postcode":"01473",
    "addr:street":"Fenno Dr",
    "iso:country":"US",
    "sg:address":"18 Fenno Dr",
    "sg:city":"Westminster",
    "sg:classifiers":[
        {
            "category":"Social Services",
            "subcategory":"Child Care",
            "type":"Services"
        }
    ],
    "sg:phone":"+1 978 874 2570",
    "sg:postcode":"01473",
    "sg:province":"MA",
    "wof:name":"Three Bears Day Care",
    "wof:placetype":"venue"
},
  "geometry": {"coordinates":[-71.931676,42.553889],"type":"Point"}
}