{
  "type": "Feature",
  "properties": {
    "iso:country":"US",
    "sg:address":"968 Reed Rd",
    "sg:city":"North Dartmouth",
    "sg:classifiers":[
        {
            "category":"Recreation",
            "type":"Entertainment"
        }
    ],
    "sg:phone":"+1 508 991 3663",
    "sg:postcode":"02747",
    "sg:province":"MA",
    "sg:tags":[
        "range",
        "practice",
        "golf"
    ],
    "wof:name":"Dartmouth Sports Dome",
    "wof:placetype":"venue"
},
  "geometry": {"coordinates":[-71.0351,41.665084],"type":"Point"}
}