{
  "type": "Feature",
  "properties": {
    "iso:country":"US",
    "sg:address":"30 Faulkner St",
    "sg:city":"Ayer",
    "sg:classifiers":[
        {
            "category":"Manufacturing",
            "subcategory":"Rubber & Plastics",
            "type":"Manufacturing & Wholesale Goods"
        }
    ],
    "sg:phone":"+1 978 772 6900",
    "sg:postcode":"01432",
    "sg:province":"MA",
    "wof:name":"Micron Plastics Inc",
    "wof:placetype":"venue"
},
  "geometry": {"coordinates":[-71.588172,42.557337],"type":"Point"}
}