{
  "type": "Feature",
  "properties": {
    "addr:full": "236 Bay State Rd Boston MA 02215",
    "addr:housenumber": "236",
    "addr:postcode": "02215",
    "addr:street": "Bay State Rd",
    "iso:country": "US",
    "sg:address": "236 Bay State Rd",
    "sg:city": "Boston",
    "sg:classifiers": [
      {
        "category": "Manufacturing",
        "subcategory": "Printing",
        "type": "Manufacturing \u0026 Wholesale Goods"
      }
    ],
    "sg:phone": "+1 617 353 4260",
    "sg:postcode": "02215",
    "sg:province": "MA",
    "sg:tags": [
      "publisher"
    ],
    "wof:name": "Partisan Review",
    "wof:placetype": "venue"
  },
  "geometry": {"coordinates":[-71.109234,42.35138],"type":"Point"}
}
