{
  "type": "Feature",
  "properties": {
    "addr:full": "11 Temple Pl Boston MA 02111",
    "addr:housenumber": "11",
    "addr:postcode": "02111",
    "addr:street": "Temple Pl",
    "iso:country": "US",
    "ovtr:label": "Herrera's Mexican Grill, 11 Temple Pl Boston MA US",
    "ovtr:similarity": 2.768557071685791,
    "sg:address": "11 Temple Pl",
    "sg:city": "Boston",
    "sg:classifiers": [
      {
        "category": "Restaurant",
        "type": "Food \u0026 Drink"
      }
    ],
    "sg:menulink": "http://www.allmenus.com/ma/boston/662-herreras-mexican-grill/menu/",
    "sg:phone": "+1 617 426 2350",
    "sg:postcode": "02111",
    "sg:province": "MA",
    "sg:tags": [
      "mexican"
    ],
    "wof:name": "Herrera's Mexican Grill",
    "wof:placetype": "venue"
  },
  "geometry": {"coordinates":[-71.062685,42.355579],"type":"Point"}
}
