{
  "type": "Feature",
  "properties": {
    "addr:full":"236 Vine St Everett MA 02149",
    "addr:housenumber":"236",
    "addr:postcode":"02149",
    "addr:street":"Vine St",
    "iso:country":"US",
    "sg:address":"236 Vine St",
    "sg:city":"Everett",
    "sg:classifiers":[
        {
            "category":"Building & Trades",
            "subcategory":"Cleaning & Sanitation",
            "type":"Services"
        }
    ],
    "sg:phone":"+1 617 417 2242",
    "sg:postcode":"02149",
    "sg:province":"MA",
    "sg:tags":[
        "home"
    ],
    "wof:name":"A & B Cleaning",
    "wof:placetype":"venue"
},
  "geometry": {"coordinates":[-71.045621,42.407379],"type":"Point"}
}