{
  "type": "Feature",
  "properties": {
    "iso:country":"US",
    "sg:address":"54 High St",
    "sg:city":"Clinton",
    "sg:classifiers":[
        {
            "category":"Wholesale",
            "subcategory":"Durable Goods & Equipment",
            "type":"Manufacturing & Wholesale Goods"
        }
    ],
    "sg:phone":"+1 978 368 8313",
    "sg:postcode":"01510",
    "sg:province":"MA",
    "sg:tags":[
        "importer"
    ],
    "wof:name":"Brazil Popular",
    "wof:placetype":"venue"
},
  "geometry": {"coordinates":[-71.684792,42.417332],"type":"Point"}
}