{
  "type": "Feature",
  "properties": {
    "iso:country":"US",
    "sg:address":"90 Main St",
    "sg:city":"North Reading",
    "sg:classifiers":[
        {
            "category":"Shopping",
            "subcategory":"Department Store",
            "type":"Retail Goods"
        }
    ],
    "sg:phone":"+1 978 276 0087",
    "sg:postcode":"01864",
    "sg:province":"MA",
    "wof:name":"Dollar Sense",
    "wof:placetype":"venue"
},
  "geometry": {"coordinates":[-71.110719,42.574812],"type":"Point"}
}