{
  "type": "Feature",
  "properties": {
    "addr:full": "33 McKenney Cir Andover MA 01810",
    "addr:housenumber": "33",
    "addr:postcode": "01810",
    "addr:street": "Mckenney Cir",
    "iso:country": "US",
    "sg:address": "33 McKenney Cir",
    "sg:city": "Andover",
    "sg:classifiers": [
      {
        "category": "Local Transit",
        "type": "Transportation"
      }
    ],
    "sg:phone": "+1   ",
    "sg:postcode": "01810",
    "sg:province": "MA",
    "sg:tags": [
      "passenger"
    ],
    "wof:name": "All American Limousine Inc",
    "wof:placetype": "venue"
  },
  "geometry": {"coordinates":[-71.156908,42.679896],"type":"Point"}
}
