{
  "type": "Feature",
  "properties": {
    "iso:country":"US",
    "sg:address":"30 Upland Rd",
    "sg:city":"Dedham",
    "sg:classifiers":[
        {
            "category":"Building & Trades",
            "subcategory":"Locksmith",
            "type":"Services"
        }
    ],
    "sg:phone":"+1 781 410 9028",
    "sg:postcode":"02026",
    "sg:province":"MA",
    "sg:tags":[
        "key"
    ],
    "wof:name":"Locksmith Service All Week 24 Emergency",
    "wof:placetype":"venue"
},
  "geometry": {"coordinates":[-71.159133,42.229926],"type":"Point"}
}