{
  "type": "Feature",
  "properties": {
    "addr:full":"5 Middlesex Ave Somerville MA 02145",
    "addr:housenumber":"5",
    "addr:postcode":"02145",
    "addr:street":"Middlesex Ave",
    "iso:country":"US",
    "sg:address":"5 Middlesex Ave",
    "sg:city":"Somerville",
    "sg:classifiers":[
        {
            "category":"Education",
            "subcategory":"Special Training",
            "type":"Public Place"
        }
    ],
    "sg:phone":"+1 617 779 0367",
    "sg:postcode":"02145",
    "sg:province":"MA",
    "sg:tags":[
        "adult"
    ],
    "sg:website":"www.targetschool.com",
    "wof:name":"Target International Student Center",
    "wof:placetype":"venue"
},
  "geometry": {"coordinates":[-71.08223700000001,42.39076],"type":"Point"}
}