{
  "type": "Feature",
  "properties": {
    "iso:country":"US",
    "sg:address":"261 Neck Rd",
    "sg:city":"Haverhill",
    "sg:classifiers":[
        {
            "category":"Wholesale",
            "subcategory":"Groceries",
            "type":"Manufacturing & Wholesale Goods"
        }
    ],
    "sg:phone":"+1 978 521 3923",
    "sg:postcode":"01835",
    "sg:province":"MA",
    "sg:tags":[
        "beverage"
    ],
    "sg:website":"www.pepsimv.com",
    "wof:name":"Pepsi-Cola Bottling Co",
    "wof:placetype":"venue"
},
  "geometry": {"coordinates":[-71.12196900000001,42.756332],"type":"Point"}
}