{
  "type": "Feature",
  "properties": {
    "iso:country":"US",
    "sg:address":"43 Hillcrest St",
    "sg:city":"Dunstable",
    "sg:classifiers":[
        {
            "category":"Building & Trades",
            "subcategory":"Construction",
            "type":"Services"
        }
    ],
    "sg:phone":"+1 978 649 9535",
    "sg:postcode":"01827",
    "sg:province":"MA",
    "sg:tags":[
        "general",
        "contractor"
    ],
    "wof:name":"Drew Masonry Inc",
    "wof:placetype":"venue"
},
  "geometry": {"coordinates":[-71.478814,42.671742],"type":"Point"}
}