{
  "type": "Feature",
  "properties": {
    "addr:full":"10 Porter St Stoughton MA 02072",
    "addr:housenumber":"10",
    "addr:postcode":"02072",
    "addr:street":"Porter St",
    "iso:country":"US",
    "sg:address":"10 Porter St",
    "sg:city":"Stoughton",
    "sg:classifiers":[
        {
            "category":"Restaurant",
            "type":"Food & Drink"
        }
    ],
    "sg:phone":"+1 781 341 9882",
    "sg:postcode":"02072",
    "sg:province":"MA",
    "wof:name":"Centerfields Bar & Grill",
    "wof:placetype":"venue"
},
  "geometry": {"coordinates":[-71.103887,42.124786],"type":"Point"}
}