{
  "type": "Feature",
  "properties": {
    "addr:full":"95 Grew Ave Roslindale MA 02131",
    "addr:housenumber":"95",
    "addr:postcode":"02131",
    "addr:street":"Grew Ave",
    "iso:country":"US",
    "sg:address":"95 Grew Ave",
    "sg:city":"Roslindale",
    "sg:classifiers":[
        {
            "category":"Organizations",
            "subcategory":"Professional Association",
            "type":"Services"
        }
    ],
    "sg:phone":"+1 617 469 8121",
    "sg:postcode":"02131",
    "sg:province":"MA",
    "sg:tags":[
        "business",
        "trade"
    ],
    "wof:name":"Mvp Commerce Co",
    "wof:placetype":"venue"
},
  "geometry": {"coordinates":[-71.121236,42.27426],"type":"Point"}
}