{
  "type": "Feature",
  "properties": {
    "addr:full": "57 Pearl St Amesbury MA 01913",
    "addr:housenumber": "57",
    "addr:postcode": "01913",
    "addr:street": "Pearl St",
    "iso:country": "US",
    "sg:address": "57 Pearl St",
    "sg:city": "Amesbury",
    "sg:classifiers": [
      {
        "category": "Professional",
        "type": "Services"
      }
    ],
    "sg:phone": "+1   ",
    "sg:postcode": "01913",
    "sg:province": "MA",
    "wof:name": "Bruce M Georgian Corp",
    "wof:placetype": "venue"
  },
  "geometry": {"coordinates":[-70.919595,42.858857],"type":"Point"}
}
