{
  "type": "Feature",
  "properties": {
    "iso:country":"US",
    "sg:address":"57 Pearl St",
    "sg:city":"Amesbury",
    "sg:classifiers":[
        {
            "category":"Professional",
            "type":"Services"
        }
    ],
    "sg:phone":"+1   ",
    "sg:postcode":"01913",
    "sg:province":"MA",
    "wof:name":"Bruce M Georgian Corp",
    "wof:placetype":"venue"
},
  "geometry": {"coordinates":[-70.919595,42.858857],"type":"Point"}
}