{
  "type": "Feature",
  "properties": {
    "addr:full":"1 State Street Boston MA 02109",
    "addr:housenumber":"1",
    "addr:postcode":"02109",
    "addr:street":"State Street",
    "iso:country":"US",
    "sg:address":"1 State Street",
    "sg:city":"Boston",
    "sg:classifiers":[
        {
            "category":"Professional",
            "type":"Services"
        }
    ],
    "sg:phone":"+1 617 723 4751",
    "sg:postcode":"02109",
    "sg:province":"MA",
    "sg:website":"www.amextravelresources.com/spec...",
    "wof:name":"American Express Travel",
    "wof:placetype":"venue"
},
  "geometry": {"coordinates":[-71.05781500000001,42.358815],"type":"Point"}
}