{
  "type": "Feature",
  "properties": {
    "iso:country":"US",
    "sg:address":"13 Maple Ave",
    "sg:city":"Ashburnham",
    "sg:classifiers":[
        {
            "category":"Building & Trades",
            "subcategory":"Construction",
            "type":"Services"
        }
    ],
    "sg:phone":"+1 978 827 5420",
    "sg:postcode":"01430",
    "sg:province":"MA",
    "sg:tags":[
        "residential"
    ],
    "wof:name":"John Boucher Construction",
    "wof:placetype":"venue"
},
  "geometry": {"coordinates":[-71.923717,42.605433],"type":"Point"}
}