{
  "type": "Feature",
  "properties": {
    "iso:country":"US",
    "sg:address":"581 E Broadway",
    "sg:city":"Boston",
    "sg:classifiers":[
        {
            "category":"Building & Trades",
            "subcategory":"Construction",
            "type":"Services"
        }
    ],
    "sg:phone":"+1   ",
    "sg:postcode":"02127",
    "sg:province":"MA",
    "sg:tags":[
        "house"
    ],
    "wof:name":"Blackthorn Construction LLC",
    "wof:placetype":"venue"
},
  "geometry": {"coordinates":[-71.040239,42.335465],"type":"Point"}
}