{
  "type": "Feature",
  "properties": {
    "addr:full": "422 Worcester St Wellesley MA 02481",
    "addr:housenumber": "422",
    "addr:postcode": "02481",
    "addr:street": "Worcester St",
    "iso:country": "US",
    "sg:address": "422 Worcester St",
    "sg:city": "Wellesley",
    "sg:classifiers": [
      {
        "category": "Health Services",
        "subcategory": "Clinic",
        "type": "Services"
      }
    ],
    "sg:phone": "+1 781 235 8366",
    "sg:postcode": "02481",
    "sg:province": "MA",
    "sg:tags": [
      "medical",
      "group"
    ],
    "wof:name": "Robert C Nardone",
    "wof:placetype": "venue"
  },
  "geometry": {"coordinates":[-71.273473,42.313835],"type":"Point"}
}
