{
  "type": "Feature",
  "properties": {
    "addr:full": "95 Washington St Taunton MA 02780",
    "addr:housenumber": "95",
    "addr:postcode": "02780",
    "addr:street": "Washington St",
    "iso:country": "US",
    "sg:address": "95 Washington St",
    "sg:city": "Taunton",
    "sg:classifiers": [
      {
        "category": "Health Services",
        "subcategory": "Doctor",
        "type": "Services"
      }
    ],
    "sg:phone": "+1 508 824 4075",
    "sg:postcode": "02780",
    "sg:province": "MA",
    "sg:tags": [
      "physician",
      "surgeon"
    ],
    "wof:name": "Thoracic Associates Inc",
    "wof:placetype": "venue"
  },
  "geometry": {"coordinates":[-71.096789,41.903673],"type":"Point"}
}
