{
  "type": "Feature",
  "properties": {
    "addr:full": "1243 Washington St Norwood MA 02062",
    "addr:housenumber": "1243",
    "addr:postcode": "02062",
    "addr:street": "Washington St",
    "iso:country": "US",
    "sg:address": "1243 Washington St",
    "sg:city": "Norwood",
    "sg:classifiers": [
      {
        "category": "Restaurant",
        "type": "Food \u0026 Drink"
      }
    ],
    "sg:phone": "+1 781 762 1099",
    "sg:postcode": "02062",
    "sg:province": "MA",
    "sg:tags": [
      "pizza"
    ],
    "wof:name": "Olympic Pizza",
    "wof:placetype": "venue"
  },
  "geometry": {"coordinates":[-71.207199,42.1754],"type":"Point"}
}
