{
  "type": "Feature",
  "properties": {
    "iso:country":"US",
    "sg:address":"103 Olde Knoll Rd",
    "sg:city":"Marion",
    "sg:classifiers":[
        {
            "category":"Professional",
            "subcategory":"Management & Consulting",
            "type":"Services"
        }
    ],
    "sg:phone":"+1 508 748 6662",
    "sg:postcode":"02738",
    "sg:province":"MA",
    "sg:tags":[
        "consultant",
        "business"
    ],
    "wof:name":"R C Assoc",
    "wof:placetype":"venue"
},
  "geometry": {"coordinates":[-70.766938,41.686498],"type":"Point"}
}