{
  "type": "Feature",
  "properties": {
    "addr:full": "8 Ward Ave Millbury MA 01527",
    "addr:housenumber": "8",
    "addr:postcode": "01527",
    "addr:street": "Ward Ave",
    "iso:country": "US",
    "sg:address": "8 Ward Ave",
    "sg:city": "Millbury",
    "sg:classifiers": [
      {
        "category": "Professional",
        "type": "Services"
      }
    ],
    "sg:phone": "+1 508 798 7800",
    "sg:postcode": "01527",
    "sg:province": "MA",
    "wof:name": "Service Solutions",
    "wof:placetype": "venue"
  },
  "geometry": {"coordinates":[-71.745898,42.231818],"type":"Point"}
}
