{
  "type": "Feature",
  "properties": {
    "addr:full":"355 Main St Charlestown MA 02129",
    "addr:housenumber":"355",
    "addr:postcode":"02129",
    "addr:street":"Main St",
    "iso:country":"US",
    "sg:address":"355 Main St",
    "sg:city":"Charlestown",
    "sg:classifiers":[
        {
            "category":"Building & Trades",
            "subcategory":"Locksmith",
            "type":"Services"
        }
    ],
    "sg:phone":"+1 617 714 1294",
    "sg:postcode":"02129",
    "sg:province":"MA",
    "sg:tags":[
        "key"
    ],
    "wof:name":"Community Locksmith",
    "wof:placetype":"venue"
},
  "geometry": {"coordinates":[-71.068614,42.379141],"type":"Point"}
}