{
  "type": "Feature",
  "properties": {
    "iso:country":"US",
    "sg:address":"520 Tremont St",
    "sg:city":"Boston",
    "sg:classifiers":[
        {
            "category":"Bars & Pubs",
            "type":"Food & Drink"
        }
    ],
    "sg:phone":"+1 617 542 4494",
    "sg:postcode":"02116",
    "sg:province":"MA",
    "sg:tags":[
        "gay"
    ],
    "wof:name":"The Boston Eagle",
    "wof:placetype":"venue"
},
  "geometry": {"coordinates":[-71.07021899999999,42.344814],"type":"Point"}
}