{
  "type": "Feature",
  "properties": {
    "addr:full":"396 Willow St Mansfield MA 02048",
    "addr:housenumber":"396",
    "addr:postcode":"02048",
    "addr:street":"Willow St",
    "iso:country":"US",
    "sg:address":"396 Willow St",
    "sg:city":"Mansfield",
    "sg:classifiers":[
        {
            "category":"Professional",
            "subcategory":"Lawyer & Legal Services",
            "type":"Services"
        }
    ],
    "sg:phone":"+1 508 339 2122",
    "sg:postcode":"02048",
    "sg:province":"MA",
    "sg:tags":[
        "divorce",
        "law",
        "family"
    ],
    "wof:name":"Pickhover Lyn A Atty",
    "wof:placetype":"venue"
},
  "geometry": {"coordinates":[-71.212502,42.011002],"type":"Point"}
}