{
  "type": "Feature",
  "properties": {
    "iso:country":"US",
    "sg:address":"186 Forbes Rd",
    "sg:city":"Braintree",
    "sg:classifiers":[
        {
            "category":"Professional",
            "subcategory":"Lawyer & Legal Services",
            "type":"Services"
        }
    ],
    "sg:phone":"+1 781 356 5555",
    "sg:postcode":"02184",
    "sg:province":"MA",
    "sg:tags":[
        "attorney"
    ],
    "wof:name":"Fein Law Office",
    "wof:placetype":"venue"
},
  "geometry": {"coordinates":[-71.035394,42.21978],"type":"Point"}
}