{
  "type": "Feature",
  "properties": {
    "addr:full":"10 Moore St East Boston MA 02128",
    "addr:housenumber":"10",
    "addr:postcode":"02128",
    "addr:street":"Moore St",
    "iso:country":"US",
    "sg:address":"10 Moore St",
    "sg:city":"East Boston",
    "sg:classifiers":[
        {
            "category":"Health Services",
            "subcategory":"Hospital",
            "type":"Services"
        }
    ],
    "sg:phone":"+1 617 567 4669",
    "sg:postcode":"02128",
    "sg:province":"MA",
    "wof:name":"East Boston Neighborhood Health Center",
    "wof:placetype":"venue"
},
  "geometry": {"coordinates":[-71.019966,42.383903],"type":"Point"}
}