{
  "type": "Feature",
  "properties": {
    "addr:full":"77 E Merrimack St Lowell MA 01852",
    "addr:housenumber":"77",
    "addr:postcode":"01852",
    "addr:street":"E Merrimack St",
    "iso:country":"US",
    "sg:address":"77 E Merrimack St",
    "sg:city":"Lowell",
    "sg:classifiers":[
        {
            "category":"Health Services",
            "subcategory":"Doctor",
            "type":"Services"
        }
    ],
    "sg:phone":"+1   ",
    "sg:postcode":"01852",
    "sg:province":"MA",
    "sg:tags":[
        "medical"
    ],
    "wof:name":"Kaplan Leonard W",
    "wof:placetype":"venue"
},
  "geometry": {"coordinates":[-71.304168,42.644585],"type":"Point"}
}