{
  "type": "Feature",
  "properties": {
    "iso:country":"US",
    "sg:address":"793 Iyannough Rd",
    "sg:city":"Hyannis",
    "sg:classifiers":[
        {
            "category":"Shopping",
            "subcategory":"Discount & Variety Stores",
            "type":"Retail Goods"
        }
    ],
    "sg:phone":"+1 508 775 7080",
    "sg:postcode":"02601",
    "sg:province":"MA",
    "sg:tags":[
        "merchandise",
        "general"
    ],
    "wof:name":"Decor Inc",
    "wof:placetype":"venue"
},
  "geometry": {"coordinates":[-70.297163,41.66935],"type":"Point"}
}