{
  "type": "Feature",
  "properties": {
    "addr:full": "517 Broadway Saugus MA 01906",
    "addr:housenumber": "517",
    "addr:postcode": "01906",
    "addr:street": "Broadway",
    "iso:country": "US",
    "ovtr:label": "Prince Pizzeria, 517 Broadway Saugus MA US",
    "ovtr:similarity": 2.9893229007720947,
    "sg:address": "517 Broadway",
    "sg:city": "Saugus",
    "sg:classifiers": [
      {
        "category": "Restaurant",
        "type": "Food \u0026 Drink"
      }
    ],
    "sg:phone": "+1 781 233 9950",
    "sg:postcode": "01906",
    "sg:province": "MA",
    "sg:tags": [
      "pizza"
    ],
    "wof:name": "Prince Pizzeria \u0026 Bar",
    "wof:placetype": "venue"
  },
  "geometry": {"coordinates":[-71.019963,42.483632],"type":"Point"}
}
