{
  "type": "Feature",
  "properties": {
    "iso:country":"US",
    "sg:address":"517 Broadway",
    "sg:city":"Saugus",
    "sg:classifiers":[
        {
            "category":"Restaurant",
            "type":"Food & Drink"
        }
    ],
    "sg:phone":"+1 781 233 9950",
    "sg:postcode":"01906",
    "sg:province":"MA",
    "sg:tags":[
        "pizza"
    ],
    "wof:name":"Prince Pizzeria & Bar",
    "wof:placetype":"venue"
},
  "geometry": {"coordinates":[-71.019963,42.483632],"type":"Point"}
}