{
  "type": "Feature",
  "properties": {
    "iso:country":"US",
    "sg:address":"6 Barnard St",
    "sg:city":"Marblehead",
    "sg:classifiers":[
        {
            "category":"Shopping",
            "subcategory":"Hobbies, Toys, & Games",
            "type":"Retail Goods"
        }
    ],
    "sg:phone":"+1 781 639 1835",
    "sg:postcode":"01945",
    "sg:province":"MA",
    "sg:website":"www.worthmarine.com",
    "wof:name":"Worth Marine Inc",
    "wof:placetype":"venue"
},
  "geometry": {"coordinates":[-70.855931,42.499417],"type":"Point"}
}