{
  "type": "Feature",
  "properties": {
    "iso:country":"US",
    "sg:address":"18 Main St",
    "sg:city":"Concord",
    "sg:classifiers":[
        {
            "category":"Local Transit",
            "type":"Transportation"
        }
    ],
    "sg:phone":"+1 978 371 5600",
    "sg:postcode":"01742",
    "sg:province":"MA",
    "sg:tags":[
        "shuttle",
        "airport",
        "limousine"
    ],
    "wof:name":"Lincoln Concord Coach",
    "wof:placetype":"venue"
},
  "geometry": {"coordinates":[-71.349197,42.460201],"type":"Point"}
}