{
  "type": "Feature",
  "properties": {
    "addr:full": "669 Tremont St Apartment #5 Boston MA 02118",
    "addr:housenumber": "669",
    "addr:postcode": "02118",
    "addr:street": "Tremont St",
    "iso:country": "US",
    "sg:address": "669 Tremont St Apartment #5",
    "sg:city": "Boston",
    "sg:classifiers": [
      {
        "category": "Banks \u0026 Credit Unions",
        "subcategory": "Financial Services",
        "type": "Services"
      }
    ],
    "sg:phone": "+1 617 694 3190",
    "sg:postcode": "02118",
    "sg:province": "MA",
    "sg:website": "http://www.MichaelRRomano.com",
    "wof:name": "Michael Romano",
    "wof:placetype": "venue"
  },
  "geometry": {"coordinates":[-71.075951,42.341648],"type":"Point"}
}
