{
  "type": "Feature",
  "properties": {
    "addr:full": "1620 Turnpike St North Andover MA 01845",
    "addr:housenumber": "1620",
    "addr:postcode": "01845",
    "addr:street": "Turnpike St",
    "iso:country": "US",
    "sg:address": "1620 Turnpike St",
    "sg:city": "North Andover",
    "sg:classifiers": [
      {
        "category": "Shopping",
        "subcategory": "Computers \u0026 Home Electronics",
        "type": "Retail Goods"
      }
    ],
    "sg:phone": "+1 978 794 1400",
    "sg:postcode": "01845",
    "sg:province": "MA",
    "sg:tags": [
      "software"
    ],
    "wof:name": "Systems Distributors",
    "wof:placetype": "venue"
  },
  "geometry": {"coordinates":[-71.080919,42.640073],"type":"Point"}
}
