{
  "type": "Feature",
  "properties": {
    "iso:country":"US",
    "sg:address":"1620 Turnpike St",
    "sg:city":"North Andover",
    "sg:classifiers":[
        {
            "category":"Shopping",
            "subcategory":"Computers & Home Electronics",
            "type":"Retail Goods"
        }
    ],
    "sg:phone":"+1 978 794 1400",
    "sg:postcode":"01845",
    "sg:province":"MA",
    "sg:tags":[
        "software"
    ],
    "wof:name":"Systems Distributors",
    "wof:placetype":"venue"
},
  "geometry": {"coordinates":[-71.08091899999999,42.640073],"type":"Point"}
}