{
  "type": "Feature",
  "properties": {
    "addr:full": "239 Littleton Rd Westford MA 01886",
    "addr:housenumber": "239",
    "addr:postcode": "01886",
    "addr:street": "Littleton Rd",
    "iso:country": "US",
    "sg:address": "239 Littleton Rd",
    "sg:city": "Westford",
    "sg:classifiers": [
      {
        "category": "Professional",
        "subcategory": "Management \u0026 Consulting",
        "type": "Services"
      }
    ],
    "sg:phone": "+1 781 438 3397",
    "sg:postcode": "01886",
    "sg:province": "MA",
    "sg:tags": [
      "personnel",
      "consultant"
    ],
    "wof:name": "Opis Education",
    "wof:placetype": "venue"
  },
  "geometry": {"coordinates":[-71.436428,42.558636],"type":"Point"}
}
