{
  "type": "Feature",
  "properties": {
    "addr:full": "51 Middle St Amherst MA 01002",
    "addr:housenumber": "51",
    "addr:postcode": "01002",
    "addr:street": "Middle St",
    "iso:country": "US",
    "sg:address": "51 Middle St",
    "sg:city": "Amherst",
    "sg:classifiers": [
      {
        "category": "Professional",
        "type": "Services"
      }
    ],
    "sg:phone": "+1   ",
    "sg:postcode": "01002",
    "sg:province": "MA",
    "wof:name": "Environmental Pollution",
    "wof:placetype": "venue"
  },
  "geometry": {"coordinates":[-72.504854,42.33704],"type":"Point"}
}
