{
  "type": "Feature",
  "properties": {
    "iso:country":"US",
    "sg:address":"51 Middle St",
    "sg:city":"Amherst",
    "sg:classifiers":[
        {
            "category":"Professional",
            "type":"Services"
        }
    ],
    "sg:phone":"+1   ",
    "sg:postcode":"01002",
    "sg:province":"MA",
    "wof:name":"Environmental Pollution",
    "wof:placetype":"venue"
},
  "geometry": {"coordinates":[-72.50485399999999,42.33704],"type":"Point"}
}