{
  "type": "Feature",
  "properties": {
    "addr:full": "245 State Rd Edgartown MA 02575",
    "addr:housenumber": "245",
    "addr:postcode": "02575",
    "addr:street": "State Rd",
    "iso:country": "US",
    "sg:address": "245 State Rd",
    "sg:city": "Edgartown",
    "sg:classifiers": [
      {
        "category": "Restaurant",
        "type": "Food \u0026 Drink"
      }
    ],
    "sg:phone": "+1 508 627 9910",
    "sg:postcode": "02575",
    "sg:province": "MA",
    "wof:name": "Ken's Island Pizza Inc",
    "wof:placetype": "venue"
  },
  "geometry": {"coordinates":[-70.639197,41.430681],"type":"Point"}
}
