{
  "type": "Feature",
  "properties": {
    "iso:country":"US",
    "sg:address":"245 State Rd",
    "sg:city":"Edgartown",
    "sg:classifiers":[
        {
            "category":"Restaurant",
            "type":"Food & Drink"
        }
    ],
    "sg:phone":"+1 508 627 9910",
    "sg:postcode":"02575",
    "sg:province":"MA",
    "wof:name":"Ken's Island Pizza Inc",
    "wof:placetype":"venue"
},
  "geometry": {"coordinates":[-70.639197,41.430681],"type":"Point"}
}