{
  "type": "Feature",
  "properties": {
    "iso:country":"US",
    "sg:address":"55 Foster St",
    "sg:city":"Peabody",
    "sg:classifiers":[
        {
            "category":"Sports & Exercise",
            "subcategory":"Bowling",
            "type":"Entertainment"
        }
    ],
    "sg:phone":"+1 978 531 3555",
    "sg:postcode":"01960",
    "sg:province":"MA",
    "wof:name":"The Dog Bowl",
    "wof:placetype":"venue"
},
  "geometry": {"coordinates":[-70.928617,42.524256],"type":"Point"}
}