{
  "type": "Feature",
  "properties": {
    "iso:country":"US",
    "sg:address":"5 Hollis Ave",
    "sg:city":"Quincy",
    "sg:classifiers":[
        {
            "category":"Social Services",
            "type":"Services"
        }
    ],
    "sg:phone":"+1 617 773 9280",
    "sg:postcode":"02171",
    "sg:province":"MA",
    "sg:tags":[
        "senior",
        "citizen"
    ],
    "wof:name":"South Shore Senior Citizens",
    "wof:placetype":"venue"
},
  "geometry": {"coordinates":[-71.02644600000001,42.27588],"type":"Point"}
}