{
  "type": "Feature",
  "properties": {
    "addr:full":"41 State Rd North Dartmouth MA 02747",
    "addr:housenumber":"41",
    "addr:postcode":"02747",
    "addr:street":"State Rd",
    "iso:country":"US",
    "sg:address":"41 State Rd",
    "sg:city":"North Dartmouth",
    "sg:classifiers":[
        {
            "category":"Banks & Credit Unions",
            "subcategory":"Investment Brokerage",
            "type":"Services"
        }
    ],
    "sg:phone":"+1 508 994 1311",
    "sg:postcode":"02747",
    "sg:province":"MA",
    "sg:tags":[
        "security"
    ],
    "wof:name":"A G Edwards & Sons Inc",
    "wof:placetype":"venue"
},
  "geometry": {"coordinates":[-70.962683,41.637046],"type":"Point"}
}