{
  "type": "Feature",
  "properties": {
    "iso:country":"US",
    "sg:address":"108 Mechanic St",
    "sg:city":"Bellingham",
    "sg:classifiers":[
        {
            "category":"Home & Garden",
            "subcategory":"Carpets & Floor Coverings",
            "type":"Retail Goods"
        }
    ],
    "sg:phone":"+1 508 966 2648",
    "sg:postcode":"02019",
    "sg:province":"MA",
    "sg:tags":[
        "dealer",
        "rug"
    ],
    "wof:name":"K & D Flooring",
    "wof:placetype":"venue"
},
  "geometry": {"coordinates":[-71.464787,42.081812],"type":"Point"}
}