{
  "type": "Feature",
  "properties": {
    "addr:full": "24 Sharp St Dorchester Ctr MA 02124",
    "addr:housenumber": "24",
    "addr:postcode": "02124",
    "addr:street": "Sharp St",
    "iso:country": "US",
    "sg:address": "24 Sharp St",
    "sg:city": "Dorchester Ctr",
    "sg:classifiers": [
      {
        "category": "Education",
        "subcategory": "School",
        "type": "Public Place"
      }
    ],
    "sg:phone": "+1 617 822 9225",
    "sg:postcode": "02124",
    "sg:province": "MA",
    "wof:name": "Epiphany Middle School",
    "wof:placetype": "venue"
  },
  "geometry": {"coordinates":[-71.066622,42.292619],"type":"Point"}
}
