{
  "type": "Feature",
  "properties": {
    "iso:country":"US",
    "sg:address":"770 Grafton St",
    "sg:city":"Shrewsbury",
    "sg:classifiers":[
        {
            "category":"Social Services",
            "subcategory":"Child Care",
            "type":"Services"
        }
    ],
    "sg:phone":"+1 508 757 1900",
    "sg:postcode":"01545",
    "sg:province":"MA",
    "sg:tags":[
        "kindergarten",
        "academic",
        "school"
    ],
    "wof:name":"Lilliput Two",
    "wof:placetype":"venue"
},
  "geometry": {"coordinates":[-71.712433,42.245315],"type":"Point"}
}