{
  "type": "Feature",
  "properties": {
    "iso:country":"US",
    "sg:address":"5 Charlesview Rd",
    "sg:city":"Hopedale",
    "sg:classifiers":[
        {
            "category":"Autos & Motor Vehicles",
            "subcategory":"Motorcycle Sales",
            "type":"Retail Goods"
        }
    ],
    "sg:phone":"+1 508 422 9555",
    "sg:postcode":"01747",
    "sg:province":"MA",
    "sg:tags":[
        "scooter"
    ],
    "wof:name":"Mass Mini Choppers",
    "wof:placetype":"venue"
},
  "geometry": {"coordinates":[-71.502932,42.104761],"type":"Point"}
}