{
  "type": "Feature",
  "properties": {
    "iso:country":"US",
    "sg:address":"350 Fenn St",
    "sg:city":"Pittsfield",
    "sg:classifiers":[
        {
            "category":"Organizations",
            "subcategory":"Community Association",
            "type":"Services"
        }
    ],
    "sg:phone":"+1 413 448 2827",
    "sg:postcode":"01201",
    "sg:province":"MA",
    "sg:tags":[
        "club"
    ],
    "wof:name":"UNICO",
    "wof:placetype":"venue"
},
  "geometry": {"coordinates":[-73.24760999999999,42.449248],"type":"Point"}
}