{
  "type": "Feature",
  "properties": {
    "addr:full": "19 Elm St Pittsfield MA 01201",
    "addr:housenumber": "19",
    "addr:postcode": "01201",
    "addr:street": "Elm St",
    "iso:country": "US",
    "ovtr:label": "George's Liquors, 19 Elm St Pittsfield MA US",
    "ovtr:similarity": 3.4969658851623535,
    "sg:address": "19 Elm St",
    "sg:city": "Pittsfield",
    "sg:classifiers": [
      {
        "category": "Food \u0026 Beverages",
        "subcategory": "Liquor \u0026 Beverages",
        "type": "Retail Goods"
      }
    ],
    "sg:phone": "+1 413 448 8989",
    "sg:postcode": "01201",
    "sg:province": "MA",
    "wof:name": "George's Liquor Store",
    "wof:placetype": "venue"
  },
  "geometry": {"coordinates":[-73.244563,42.446329],"type":"Point"}
}
