{
  "type": "Feature",
  "properties": {
    "addr:full": "1 Industrial Park Rd W Oxford MA 01540",
    "addr:housenumber": "1",
    "addr:postcode": "01540",
    "addr:street": "Industrial Park Rd W",
    "iso:country": "US",
    "sg:address": "1 Industrial Park Rd W",
    "sg:city": "Oxford",
    "sg:classifiers": [
      {
        "category": "Manufacturing",
        "subcategory": "Printing",
        "type": "Manufacturing \u0026 Wholesale Goods"
      }
    ],
    "sg:phone": "+1 508 987 2363",
    "sg:postcode": "01540",
    "sg:province": "MA",
    "sg:tags": [
      "newspaper"
    ],
    "wof:name": "Community Browser Newspaper",
    "wof:placetype": "venue"
  },
  "geometry": {"coordinates":[-71.869626,42.08708],"type":"Point"}
}
