{
  "type": "Feature",
  "properties": {
    "iso:country":"US",
    "sg:address":"1 Industrial Park Rd W",
    "sg:city":"Oxford",
    "sg:classifiers":[
        {
            "category":"Manufacturing",
            "subcategory":"Printing",
            "type":"Manufacturing & Wholesale Goods"
        }
    ],
    "sg:phone":"+1 508 987 2363",
    "sg:postcode":"01540",
    "sg:province":"MA",
    "sg:tags":[
        "newspaper"
    ],
    "wof:name":"Community Browser Newspaper",
    "wof:placetype":"venue"
},
  "geometry": {"coordinates":[-71.869626,42.08708],"type":"Point"}
}