{
  "type": "Feature",
  "properties": {
    "iso:country":"US",
    "sg:address":"1600 Providence Hwy",
    "sg:city":"Walpole",
    "sg:classifiers":[
        {
            "category":"Wholesale",
            "subcategory":"Chemicals & Plastics",
            "type":"Manufacturing & Wholesale Goods"
        }
    ],
    "sg:phone":"+1 781 551 3335",
    "sg:postcode":"02081",
    "sg:province":"MA",
    "sg:tags":[
        "oxygen"
    ],
    "wof:name":"Reliable Respiratory",
    "wof:placetype":"venue"
},
  "geometry": {"coordinates":[-71.237831,42.116063],"type":"Point"}
}