{
  "type": "Feature",
  "properties": {
    "iso:country":"US",
    "sg:address":"650 Worcester Rd",
    "sg:city":"Framingham",
    "sg:classifiers":[
        {
            "category":"Health Services",
            "subcategory":"Chiropractor",
            "type":"Services"
        }
    ],
    "sg:phone":"+1 508 879 8882",
    "sg:postcode":"01702",
    "sg:province":"MA",
    "wof:name":"Wexler Chiropractic Office",
    "wof:placetype":"venue"
},
  "geometry": {"coordinates":[-71.422833,42.298033],"type":"Point"}
}