{
  "type": "Feature",
  "properties": {
    "iso:country":"US",
    "sg:address":"40 Arsenal St",
    "sg:city":"Watertown",
    "sg:phone":"+1 617 924 3989",
    "sg:postcode":"02472",
    "sg:province":"MA",
    "sg:website":"http://www.firestonecompleteautocare.com/?s_kwcid=IYP_NTL",
    "wof:name":"Firestone Complete Auto Care Store",
    "wof:placetype":"venue"
},
  "geometry": {"coordinates":[-71.18232,42.365059],"type":"Point"}
}