{
  "type": "Feature",
  "properties": {
    "addr:full":"6 Abbott Rd Lexington MA 02420",
    "addr:housenumber":"6",
    "addr:postcode":"02420",
    "addr:street":"Abbott Rd",
    "iso:country":"US",
    "sg:address":"6 Abbott Rd",
    "sg:city":"Lexington",
    "sg:classifiers":[
        {
            "category":"Manufacturing",
            "subcategory":"Electronics",
            "type":"Manufacturing & Wholesale Goods"
        }
    ],
    "sg:phone":"+1   ",
    "sg:postcode":"02420",
    "sg:province":"MA",
    "sg:tags":[
        "equipment",
        "mfg",
        "communication"
    ],
    "wof:name":"Three-Five Systems Inc",
    "wof:placetype":"venue"
},
  "geometry": {"coordinates":[-71.223091,42.452013],"type":"Point"}
}