{
  "type": "Feature",
  "properties": {
    "addr:full":"141 Pleasant St Malden MA 02148",
    "addr:housenumber":"141",
    "addr:postcode":"02148",
    "addr:street":"Pleasant St",
    "iso:country":"US",
    "sg:address":"141 Pleasant St",
    "sg:city":"Malden",
    "sg:classifiers":[
        {
            "category":"Retail",
            "subcategory":"Repair Shop",
            "type":"Services"
        }
    ],
    "sg:phone":"+1 781 413 0226",
    "sg:postcode":"02148",
    "sg:province":"MA",
    "sg:tags":[
        "lock",
        "locksmith"
    ],
    "wof:name":"All Day Emergency Locksmith",
    "wof:placetype":"venue"
},
  "geometry": {"coordinates":[-71.07171,42.427245],"type":"Point"}
}