{
  "type": "Feature",
  "properties": {
    "iso:country":"US",
    "sg:address":"106 Main St",
    "sg:city":"Greenfield",
    "sg:classifiers":[
        {
            "category":"Government",
            "subcategory":"Court House",
            "type":"Public Place"
        }
    ],
    "sg:phone":"+1 413 774 7011",
    "sg:postcode":"01301",
    "sg:province":"MA",
    "sg:tags":[
        "county"
    ],
    "wof:name":"Franklin County Family Court",
    "wof:placetype":"venue"
},
  "geometry": {"coordinates":[-72.604969,42.587674],"type":"Point"}
}