{
  "type": "Feature",
  "properties": {
    "addr:full": "19 Waterline Dr S Mashpee MA 02649",
    "addr:housenumber": "19",
    "addr:postcode": "02649",
    "addr:street": "Waterline Dr S",
    "iso:country": "US",
    "sg:address": "19 Waterline Dr S",
    "sg:city": "Mashpee",
    "sg:classifiers": [
      {
        "category": "Wholesale",
        "subcategory": "Vending Machines",
        "type": "Manufacturing \u0026 Wholesale Goods"
      }
    ],
    "sg:phone": "+1   ",
    "sg:postcode": "02649",
    "sg:province": "MA",
    "sg:tags": [
      "operator"
    ],
    "wof:name": "Star Vending Inc",
    "wof:placetype": "venue"
  },
  "geometry": {"coordinates":[-70.501513,41.567291],"type":"Point"}
}
