{
  "type": "Feature",
  "properties": {
    "addr:full": "7 Brookside Ct Housatonic MA 01230",
    "addr:housenumber": "7",
    "addr:postcode": "01230",
    "addr:street": "Brookside Ct",
    "iso:country": "US",
    "sg:address": "7 Brookside Ct",
    "sg:city": "Housatonic",
    "sg:classifiers": [
      {
        "category": "Manufacturing",
        "subcategory": "Pottery",
        "type": "Manufacturing \u0026 Wholesale Goods"
      }
    ],
    "sg:phone": "+1 413 274 3879",
    "sg:postcode": "01230",
    "sg:province": "MA",
    "wof:name": "Masako Graphics",
    "wof:placetype": "venue"
  },
  "geometry": {"coordinates":[-73.374868,42.241755],"type":"Point"}
}
