{
  "type": "Feature",
  "properties": {
    "addr:full":"1142 Acushnet Ave New Bedford MA 02746",
    "addr:housenumber":"1142",
    "addr:postcode":"02746",
    "addr:street":"Acushnet Ave",
    "iso:country":"US",
    "sg:address":"1142 Acushnet Ave",
    "sg:city":"New Bedford",
    "sg:classifiers":[
        {
            "category":"Shopping",
            "subcategory":"Bicycles & Sporting Goods",
            "type":"Retail Goods"
        }
    ],
    "sg:phone":"+1 508 999 2988",
    "sg:postcode":"02746",
    "sg:province":"MA",
    "sg:tags":[
        "tackle",
        "fishing"
    ],
    "wof:name":"Never Home Bait & Tackle",
    "wof:placetype":"venue"
},
  "geometry": {"coordinates":[-70.92704500000001,41.656584],"type":"Point"}
}