{
  "type": "Feature",
  "properties": {
    "iso:country":"US",
    "sg:address":"1349 Washington St",
    "sg:city":"West Newton",
    "sg:classifiers":[
        {
            "category":"Restaurant",
            "type":"Food & Drink"
        }
    ],
    "sg:menulink":"http://www.allmenus.com/ma/newton/150969-the-cherry-tree/menu/",
    "sg:phone":"+1 617 965 9796",
    "sg:postcode":"02465",
    "sg:province":"MA",
    "sg:tags":[
        "american",
        "pub"
    ],
    "wof:name":"The Cherry Tree",
    "wof:placetype":"venue"
},
  "geometry": {"coordinates":[-71.228386,42.34891],"type":"Point"}
}