{
  "type": "Feature",
  "properties": {
    "addr:full":"106 Kenney Ln Concord MA 01742",
    "addr:housenumber":"106",
    "addr:postcode":"01742",
    "addr:street":"Kenney Ln",
    "iso:country":"US",
    "sg:address":"106 Kenney Ln",
    "sg:city":"Concord",
    "sg:classifiers":[
        {
            "category":"Communications",
            "subcategory":"Radio Station",
            "type":"Services"
        }
    ],
    "sg:phone":"+1   ",
    "sg:postcode":"01742",
    "sg:province":"MA",
    "sg:tags":[
        "broadcast"
    ],
    "wof:name":"Inter Act",
    "wof:placetype":"venue"
},
  "geometry": {"coordinates":[-71.319287,42.466257],"type":"Point"}
}