{
  "type": "Feature",
  "properties": {
    "addr:full":"237 Oakwood Ave Revere MA 02151",
    "addr:housenumber":"237",
    "addr:postcode":"02151",
    "addr:street":"Oakwood Ave",
    "iso:country":"US",
    "sg:address":"237 Oakwood Ave",
    "sg:city":"Revere",
    "sg:classifiers":[
        {
            "category":"Professional",
            "subcategory":"Business Services",
            "type":"Services"
        }
    ],
    "sg:phone":"+1   ",
    "sg:postcode":"02151",
    "sg:province":"MA",
    "sg:tags":[
        "cheese",
        "confectionery",
        "advertising",
        "candy",
        "specialty"
    ],
    "wof:name":"Melpa Enterprises Inc",
    "wof:placetype":"venue"
},
  "geometry": {"coordinates":[-71.022828,42.417357],"type":"Point"}
}