{
  "type": "Feature",
  "properties": {
    "addr:full": "103 Commonwealth Ave Attleboro Falls MA 02763",
    "addr:housenumber": "103",
    "addr:postcode": "02763",
    "addr:street": "Commonwealth Ave",
    "iso:country": "US",
    "sg:address": "103 Commonwealth Ave",
    "sg:city": "Attleboro Falls",
    "sg:classifiers": [
      {
        "category": "Health Services",
        "subcategory": "Doctor",
        "type": "Services"
      }
    ],
    "sg:phone": "+1 508 699 0449",
    "sg:postcode": "02763",
    "sg:province": "MA",
    "sg:tags": [
      "surgeon",
      "oral"
    ],
    "wof:name": "Biernacki John F Oral Surg",
    "wof:placetype": "venue"
  },
  "geometry": {"coordinates":[-71.314697,41.971401],"type":"Point"}
}
