{
  "type": "Feature",
  "properties": {
    "iso:country":"US",
    "sg:address":"180 Rawson Rd",
    "sg:city":"Brookline",
    "sg:classifiers":[
        {
            "category":"Professional",
            "subcategory":"Engineering",
            "type":"Services"
        }
    ],
    "sg:phone":"+1   ",
    "sg:postcode":"02445",
    "sg:province":"MA",
    "wof:name":"Gabriel E Padawer",
    "wof:placetype":"venue"
},
  "geometry": {"coordinates":[-71.13677,42.33638],"type":"Point"}
}