{
  "type": "Feature",
  "properties": {
    "addr:full": "115 Newbury St Ste 201 Boston MA 02116",
    "addr:housenumber": "115",
    "addr:postcode": "02116",
    "addr:street": "Newbury St Ste 201",
    "iso:country": "US",
    "sg:address": "115 Newbury St Ste 201",
    "sg:city": "Boston",
    "sg:classifiers": [
      {
        "category": "Personal",
        "subcategory": "Beauty Salon",
        "type": "Services"
      },
      {
        "category": "Personal",
        "subcategory": "Hair Removal",
        "type": "Services"
      },
      {
        "category": "Personal",
        "subcategory": "Day Spa",
        "type": "Services"
      }
    ],
    "sg:phone": "+1 617 266 4017",
    "sg:postcode": "02116",
    "sg:province": "MA",
    "wof:name": "Austen's",
    "wof:placetype": "venue"
  },
  "geometry": {"coordinates":[-71.076024,42.351331],"type":"Point"}
}
