{
  "type": "Feature",
  "properties": {
    "iso:country":"US",
    "sg:address":"33 Pond Ave",
    "sg:city":"Brookline",
    "sg:classifiers":[
        {
            "category":"Health Services",
            "subcategory":"Doctor",
            "type":"Services"
        }
    ],
    "sg:phone":"+1 617 739 7061",
    "sg:postcode":"02445",
    "sg:province":"MA",
    "wof:name":"Personal MD",
    "wof:placetype":"venue"
},
  "geometry": {"coordinates":[-71.11421,42.331182],"type":"Point"}
}