{
  "type": "Feature",
  "properties": {
    "addr:full":"49 Coolidge Rd Worcester MA 01602",
    "addr:housenumber":"49",
    "addr:postcode":"01602",
    "addr:street":"Coolidge Rd",
    "iso:country":"US",
    "sg:address":"49 Coolidge Rd",
    "sg:city":"Worcester",
    "sg:classifiers":[
        {
            "category":"Professional",
            "subcategory":"Accounting & Tax Preparation",
            "type":"Services"
        }
    ],
    "sg:phone":"+1 508 752 3994",
    "sg:postcode":"01602",
    "sg:province":"MA",
    "sg:tags":[
        "bookkeeping",
        "general"
    ],
    "wof:name":"Books On A Budget",
    "wof:placetype":"venue"
},
  "geometry": {"coordinates":[-71.82442399999999,42.26439],"type":"Point"}
}