{
  "type": "Feature",
  "properties": {
    "addr:full": "267 Lake St Arlington MA 02474",
    "addr:housenumber": "267",
    "addr:postcode": "02474",
    "addr:street": "Lake St",
    "iso:country": "US",
    "sg:address": "267 Lake St",
    "sg:city": "Arlington",
    "sg:classifiers": [
      {
        "category": "Restaurant",
        "type": "Food \u0026 Drink"
      }
    ],
    "sg:phone": "+1 781 316 2908",
    "sg:postcode": "02474",
    "sg:province": "MA",
    "sg:tags": [
      "thai",
      "asian",
      "pan"
    ],
    "wof:name": "Snk Siam Inc",
    "wof:placetype": "venue"
  },
  "geometry": {"coordinates":[-71.158595,42.402877],"type":"Point"}
}
