{
  "type": "Feature",
  "properties": {
    "iso:country":"US",
    "sg:address":"267 Lake St",
    "sg:city":"Arlington",
    "sg:classifiers":[
        {
            "category":"Restaurant",
            "type":"Food & Drink"
        }
    ],
    "sg:phone":"+1 781 316 2908",
    "sg:postcode":"02474",
    "sg:province":"MA",
    "sg:tags":[
        "thai",
        "asian",
        "pan"
    ],
    "wof:name":"Snk Siam Inc",
    "wof:placetype":"venue"
},
  "geometry": {"coordinates":[-71.15859500000001,42.402877],"type":"Point"}
}