{
  "type": "Feature",
  "properties": {
    "addr:full":"16 Knollwood Rd Paxton MA 01612",
    "addr:housenumber":"16",
    "addr:postcode":"01612",
    "addr:street":"Knollwood Rd",
    "iso:country":"US",
    "sg:address":"16 Knollwood Rd",
    "sg:city":"Paxton",
    "sg:classifiers":[
        {
            "category":"Insurance",
            "subcategory":"Insurance Agent",
            "type":"Services"
        }
    ],
    "sg:phone":"+1 508 754 7578",
    "sg:postcode":"01612",
    "sg:province":"MA",
    "wof:name":"Peter J Lombardo",
    "wof:placetype":"venue"
},
  "geometry": {"coordinates":[-71.902816,42.302769],"type":"Point"}
}