{
  "type": "Feature",
  "properties": {
    "iso:country":"US",
    "sg:address":"22 Emerson St",
    "sg:city":"Haverhill",
    "sg:classifiers":[
        {
            "category":"Restaurant",
            "type":"Food & Drink"
        }
    ],
    "sg:phone":"+1 978 372 0193",
    "sg:postcode":"01830",
    "sg:province":"MA",
    "wof:name":"Neiborhood Pizzeria",
    "wof:placetype":"venue"
},
  "geometry": {"coordinates":[-71.082273,42.774816],"type":"Point"}
}