{
  "type": "Feature",
  "properties": {
    "addr:full": "764 S Athol Rd Athol MA 01331",
    "addr:housenumber": "764",
    "addr:postcode": "01331",
    "addr:street": "S Athol Rd",
    "iso:country": "US",
    "sg:address": "764 S Athol Rd",
    "sg:city": "Athol",
    "sg:classifiers": [
      {
        "category": "Manufacturing",
        "subcategory": "Rubber \u0026 Plastics",
        "type": "Manufacturing \u0026 Wholesale Goods"
      }
    ],
    "sg:phone": "+1 978 249 5343",
    "sg:postcode": "01331",
    "sg:province": "MA",
    "wof:name": "Bunzl Extrusion",
    "wof:placetype": "venue"
  },
  "geometry": {"coordinates":[-72.242134,42.585307],"type":"Point"}
}
