{
  "type": "Feature",
  "properties": {
    "addr:full":"5 Oxford St Lawrence MA 01841",
    "addr:housenumber":"5",
    "addr:postcode":"01841",
    "addr:street":"Oxford St",
    "iso:country":"US",
    "sg:address":"5 Oxford St",
    "sg:city":"Lawrence",
    "sg:classifiers":[
        {
            "category":"Retail",
            "subcategory":"Auto Repair",
            "type":"Services"
        }
    ],
    "sg:phone":"+1 978 683 2401",
    "sg:postcode":"01841",
    "sg:province":"MA",
    "sg:tags":[
        "muffler",
        "exhaust",
        "system"
    ],
    "wof:name":"Gil Muffler",
    "wof:placetype":"venue"
},
  "geometry": {"coordinates":[-71.171532,42.703177],"type":"Point"}
}