{
  "type": "Feature",
  "properties": {
    "addr:full":"51 Union St Suite 208 Worcester MA 01608",
    "addr:housenumber":"51",
    "addr:postcode":"01608",
    "addr:street":"Union St Suite 208",
    "iso:country":"US",
    "sg:address":"51 Union St Suite 208",
    "sg:city":"Worcester",
    "sg:classifiers":[
        {
            "category":"Professional",
            "subcategory":"Lawyer & Legal Services",
            "type":"Services"
        }
    ],
    "sg:phone":"+1 866 204 3662",
    "sg:postcode":"01608",
    "sg:province":"MA",
    "sg:tags":[
        "attorney",
        "practice",
        "clinic"
    ],
    "sg:website":"http://local.ingenio.com/Listings/Details.aspx?NUM=a%3a10076865%3a13%3a4859924%3a14%3a0%3a7",
    "wof:name":"Ornell Law Office PC",
    "wof:placetype":"venue"
},
  "geometry": {"coordinates":[-71.798303,42.269444],"type":"Point"}
}