{
  "type": "Feature",
  "properties": {
    "addr:full": "88 Lewis St Lynn MA 01902",
    "addr:housenumber": "88",
    "addr:postcode": "01902",
    "addr:street": "Lewis St",
    "iso:country": "US",
    "sg:address": "88 Lewis St",
    "sg:city": "Lynn",
    "sg:classifiers": [
      {
        "category": "Personal",
        "subcategory": "Beauty Salon",
        "type": "Services"
      }
    ],
    "sg:phone": "+1 781 596 0010",
    "sg:postcode": "01902",
    "sg:province": "MA",
    "sg:tags": [
      "manicuring"
    ],
    "wof:name": "A \u0026 T Nails Salon",
    "wof:placetype": "venue"
  },
  "geometry": {"coordinates":[-70.92923,42.466179],"type":"Point"}
}
