{
  "type": "Feature",
  "properties": {
    "iso:country":"US",
    "sg:address":"140 Newmarket Sq",
    "sg:city":"Roxbury",
    "sg:classifiers":[
        {
            "category":"Food & Beverages",
            "subcategory":"Meat & Fish",
            "type":"Retail Goods"
        }
    ],
    "sg:phone":"+1 617 442 1400",
    "sg:postcode":"02118",
    "sg:province":"MA",
    "sg:tags":[
        "shop"
    ],
    "wof:name":"B & B Trading Corporation",
    "wof:placetype":"venue"
},
  "geometry": {"coordinates":[-71.06834000000001,42.330525],"type":"Point"}
}