{
  "type": "Feature",
  "properties": {
    "addr:full":"255 Worcester Rd Framingham MA 01701",
    "addr:housenumber":"255",
    "addr:postcode":"01701",
    "addr:street":"Worcester Rd",
    "iso:country":"US",
    "sg:address":"255 Worcester Rd",
    "sg:city":"Framingham",
    "sg:classifiers":[
        {
            "category":"Manufacturing",
            "subcategory":"Furniture",
            "type":"Manufacturing & Wholesale Goods"
        }
    ],
    "sg:phone":"+1 508 872 1104",
    "sg:postcode":"01701",
    "sg:province":"MA",
    "sg:website":"www.leatherfurniturestore.com",
    "wof:name":"Design Center West",
    "wof:placetype":"venue"
},
  "geometry": {"coordinates":[-71.406271,42.298308],"type":"Point"}
}