{
  "type": "Feature",
  "properties": {
    "addr:full": "363 Beach St Wrentham MA 02093",
    "addr:housenumber": "363",
    "addr:postcode": "02093",
    "addr:street": "Beach St",
    "iso:country": "US",
    "sg:address": "363 Beach St",
    "sg:city": "Wrentham",
    "sg:classifiers": [
      {
        "category": "Shopping",
        "subcategory": "Florist",
        "type": "Retail Goods"
      }
    ],
    "sg:phone": "+1   ",
    "sg:postcode": "02093",
    "sg:province": "MA",
    "wof:name": "Robins Florals",
    "wof:placetype": "venue"
  },
  "geometry": {"coordinates":[-71.329122,42.048108],"type":"Point"}
}
