{
  "type": "Feature",
  "properties": {
    "iso:country":"US",
    "sg:address":"505 Washington St",
    "sg:city":"Auburn",
    "sg:classifiers":[
        {
            "category":"Professional",
            "subcategory":"Management & Consulting",
            "type":"Services"
        }
    ],
    "sg:phone":"+1 508 832 9910",
    "sg:postcode":"01501",
    "sg:province":"MA",
    "sg:tags":[
        "communications",
        "consultant"
    ],
    "wof:name":"Charter Contract Svc",
    "wof:placetype":"venue"
},
  "geometry": {"coordinates":[-71.83673,42.186472],"type":"Point"}
}