{
  "type": "Feature",
  "properties": {
    "addr:full": "505 Washington St Auburn MA 01501",
    "addr:housenumber": "505",
    "addr:postcode": "01501",
    "addr:street": "Washington St",
    "iso:country": "US",
    "sg:address": "505 Washington St",
    "sg:city": "Auburn",
    "sg:classifiers": [
      {
        "category": "Professional",
        "subcategory": "Management \u0026 Consulting",
        "type": "Services"
      }
    ],
    "sg:phone": "+1 508 832 9910",
    "sg:postcode": "01501",
    "sg:province": "MA",
    "sg:tags": [
      "communications",
      "consultant"
    ],
    "wof:name": "Charter Contract Svc",
    "wof:placetype": "venue"
  },
  "geometry": {"coordinates":[-71.83673,42.186472],"type":"Point"}
}
