{
  "type": "Feature",
  "properties": {
    "iso:country":"US",
    "sg:address":"304 Washington St",
    "sg:city":"Dorchester",
    "sg:classifiers":[
        {
            "category":"Retail",
            "subcategory":"Auto Repair",
            "type":"Services"
        }
    ],
    "sg:phone":"+1 617 822 9975",
    "sg:postcode":"02121",
    "sg:province":"MA",
    "sg:tags":[
        "body",
        "automobile",
        "painting",
        "repairing"
    ],
    "wof:name":"Edwards Auto Body",
    "wof:placetype":"venue"
},
  "geometry": {"coordinates":[-71.07490199999999,42.300354],"type":"Point"}
}