{
  "type": "Feature",
  "properties": {
    "addr:full": "333 Washington St Ste 707 Boston MA 02108",
    "addr:housenumber": "333",
    "addr:postcode": "02108",
    "addr:street": "Washington St Ste 707",
    "iso:country": "US",
    "sg:address": "333 Washington St Ste 707",
    "sg:city": "Boston",
    "sg:classifiers": [
      {
        "category": "Shopping",
        "subcategory": "Jewelry",
        "type": "Retail Goods"
      }
    ],
    "sg:phone": "+1 617 720 0752",
    "sg:postcode": "02108",
    "sg:province": "MA",
    "sg:website": "www.adcodiamond.com",
    "wof:name": "ADCO Diamond Corporation",
    "wof:placetype": "venue"
  },
  "geometry": {"coordinates":[-71.059193,42.356916],"type":"Point"}
}
