{
  "type": "Feature",
  "properties": {
    "addr:full": "36 Hope Ln Dennis MA 02638",
    "addr:housenumber": "36",
    "addr:postcode": "02638",
    "addr:street": "Hope Ln",
    "iso:country": "US",
    "sg:address": "36 Hope Ln",
    "sg:city": "Dennis",
    "sg:classifiers": [
      {
        "category": "Restaurant",
        "type": "Food \u0026 Drink"
      }
    ],
    "sg:phone": "+1 508 385 7737",
    "sg:postcode": "02638",
    "sg:province": "MA",
    "sg:website": "www.centerstagedennis.com",
    "wof:name": "Center Stage Cafe",
    "wof:placetype": "venue"
  },
  "geometry": {"coordinates":[-70.193536,41.738963],"type":"Point"}
}
