{
  "type": "Feature",
  "properties": {
    "addr:full":"1076 Main St South Weymouth MA 02190",
    "addr:housenumber":"1076",
    "addr:postcode":"02190",
    "addr:street":"Main St",
    "iso:country":"US",
    "sg:address":"1076 Main St",
    "sg:city":"South Weymouth",
    "sg:classifiers":[
        {
            "category":"Autos & Motor Vehicles",
            "subcategory":"Automobile Sales",
            "type":"Retail Goods"
        }
    ],
    "sg:phone":"+1 781 335 3921",
    "sg:postcode":"02190",
    "sg:province":"MA",
    "sg:tags":[
        "car",
        "dealer"
    ],
    "wof:name":"Jannell Motors Inc",
    "wof:placetype":"venue"
},
  "geometry": {"coordinates":[-70.95520500000001,42.167595],"type":"Point"}
}