{
  "type": "Feature",
  "properties": {
    "iso:country":"US",
    "sg:address":"1 Patrick Clark Dr",
    "sg:city":"Avon",
    "sg:classifiers":[
        {
            "category":"Education",
            "subcategory":"School",
            "type":"Public Place"
        }
    ],
    "sg:phone":"+1 508 588 0230",
    "sg:postcode":"02322",
    "sg:province":"MA",
    "wof:name":"Avon School District",
    "wof:placetype":"venue"
},
  "geometry": {"coordinates":[-71.04523,42.115379],"type":"Point"}
}