{
  "type": "Feature",
  "properties": {
    "addr:full":"142 Crescent St Brockton MA 02302",
    "addr:housenumber":"142",
    "addr:postcode":"02302",
    "addr:street":"Crescent St",
    "iso:country":"US",
    "sg:address":"142 Crescent St",
    "sg:city":"Brockton",
    "sg:classifiers":[
        {
            "category":"Real Estate",
            "subcategory":"Real Estate Agent",
            "type":"Services"
        }
    ],
    "sg:phone":"+1 508 586 1115",
    "sg:postcode":"02302",
    "sg:province":"MA",
    "wof:name":"Corporate Realty Assoc",
    "wof:placetype":"venue"
},
  "geometry": {"coordinates":[-71.01577,42.081077],"type":"Point"}
}