{
  "type": "Feature",
  "properties": {
    "iso:country":"US",
    "sg:address":"391 Main St",
    "sg:city":"Easthampton",
    "sg:classifiers":[
        {
            "category":"Real Estate",
            "subcategory":"Real Estate Operator",
            "type":"Services"
        }
    ],
    "sg:phone":"+1 413 527 6337",
    "sg:postcode":"01027",
    "sg:province":"MA",
    "sg:tags":[
        "apartment"
    ],
    "wof:name":"College Highway Apartments",
    "wof:placetype":"venue"
},
  "geometry": {"coordinates":[-72.692447,42.254891],"type":"Point"}
}