{
  "type": "Feature",
  "properties": {
    "addr:full":"37 Maple St East Longmeadow MA 01028",
    "addr:housenumber":"37",
    "addr:postcode":"01028",
    "addr:street":"Maple St",
    "iso:country":"US",
    "sg:address":"37 Maple St",
    "sg:city":"East Longmeadow",
    "sg:classifiers":[
        {
            "category":"Shopping",
            "subcategory":"Optical Goods",
            "type":"Retail Goods"
        }
    ],
    "sg:phone":"+1 413 525 1533",
    "sg:postcode":"01028",
    "sg:province":"MA",
    "sg:tags":[
        "optician"
    ],
    "wof:name":"Eyewear Specialists Assoc",
    "wof:placetype":"venue"
},
  "geometry": {"coordinates":[-72.515885,42.063776],"type":"Point"}
}