{
  "type": "Feature",
  "properties": {
    "iso:country":"US",
    "sg:address":"14 Muzzey St",
    "sg:city":"Lexington",
    "sg:classifiers":[
        {
            "category":"Personal",
            "subcategory":"Beauty Salon",
            "type":"Services"
        }
    ],
    "sg:phone":"+1 781 862 8100",
    "sg:postcode":"02421",
    "sg:province":"MA",
    "wof:name":"Laser Skin Care Of Lexington I",
    "wof:placetype":"venue"
},
  "geometry": {"coordinates":[-71.22926099999999,42.447163],"type":"Point"}
}