{
  "type": "Feature",
  "properties": {
    "addr:full":"8 Church St Greenfield MA 01301",
    "addr:housenumber":"8",
    "addr:postcode":"01301",
    "addr:street":"Church St",
    "iso:country":"US",
    "sg:address":"8 Church St",
    "sg:city":"Greenfield",
    "sg:classifiers":[
        {
            "category":"Organizations",
            "subcategory":"Religious Organization",
            "type":"Services"
        }
    ],
    "sg:phone":"+1 413 773 3925",
    "sg:postcode":"01301",
    "sg:province":"MA",
    "sg:tags":[
        "church"
    ],
    "sg:website":"www.stjames-gfld.org",
    "wof:name":"St James Episcopal Church",
    "wof:placetype":"venue"
},
  "geometry": {"coordinates":[-72.598624,42.59013],"type":"Point"}
}