{
  "type": "Feature",
  "properties": {
    "iso:country":"US",
    "sg:address":"219 Concord Ave",
    "sg:city":"Cambridge",
    "sg:classifiers":[
        {
            "category":"Communications",
            "subcategory":"Film & Video Production",
            "type":"Services"
        }
    ],
    "sg:phone":"+1 617 629 5999",
    "sg:postcode":"02138",
    "sg:province":"MA",
    "sg:tags":[
        "taping"
    ],
    "wof:name":"Verissima Productions",
    "wof:placetype":"venue"
},
  "geometry": {"coordinates":[-71.131632,42.382744],"type":"Point"}
}