{
  "type": "Feature",
  "properties": {
    "addr:full": "754 Newport Ave Attleboro MA 02703",
    "addr:housenumber": "754",
    "addr:postcode": "02703",
    "addr:street": "Newport Ave",
    "iso:country": "US",
    "sg:address": "754 Newport Ave",
    "sg:city": "Attleboro",
    "sg:classifiers": [
      {
        "category": "Sports \u0026 Exercise",
        "subcategory": "Golf",
        "type": "Entertainment"
      }
    ],
    "sg:phone": "+1 508 761 5484",
    "sg:postcode": "02703",
    "sg:province": "MA",
    "wof:name": "Atlantic Golf Centers Ltd",
    "wof:placetype": "venue"
  },
  "geometry": {"coordinates":[-71.3591,41.9156],"type":"Point"}
}
