{
  "type": "Feature",
  "properties": {
    "addr:full": "1460 John Fitch Hwy Fitchburg MA 01420",
    "addr:housenumber": "1460",
    "addr:postcode": "01420",
    "addr:street": "John Fitch Hwy",
    "iso:country": "US",
    "sg:address": "1460 John Fitch Hwy",
    "sg:city": "Fitchburg",
    "sg:classifiers": [
      {
        "category": "Restaurant",
        "type": "Food \u0026 Drink"
      }
    ],
    "sg:phone": "+1 978 345 6999",
    "sg:postcode": "01420",
    "sg:province": "MA",
    "wof:name": "LA Bella Ristorante",
    "wof:placetype": "venue"
  },
  "geometry": {"coordinates":[-71.792731,42.598658],"type":"Point"}
}
