{
  "type": "Feature",
  "properties": {
    "iso:country":"US",
    "sg:address":"44 Hudson St",
    "sg:city":"Northborough",
    "sg:classifiers":[
        {
            "category":"Building & Trades",
            "subcategory":"Construction",
            "type":"Services"
        }
    ],
    "sg:phone":"+1 508 393 8666",
    "sg:postcode":"01532",
    "sg:province":"MA",
    "sg:tags":[
        "general",
        "contractor"
    ],
    "wof:name":"Central Mass Contracting",
    "wof:placetype":"venue"
},
  "geometry": {"coordinates":[-71.63910199999999,42.323066],"type":"Point"}
}