{
  "type": "Feature",
  "properties": {
    "addr:full": "8 New England Executive Park Burlington MA 01803",
    "addr:housenumber": "8",
    "addr:postcode": "01803",
    "addr:street": "New England Executive Park",
    "iso:country": "US",
    "sg:address": "8 New England Executive Park",
    "sg:city": "Burlington",
    "sg:classifiers": [
      {
        "category": "Professional",
        "subcategory": "Engineering",
        "type": "Services"
      }
    ],
    "sg:phone": "+1 781 238 8880",
    "sg:postcode": "01803",
    "sg:province": "MA",
    "sg:tags": [
      "engineer"
    ],
    "wof:name": "Peer Consultants",
    "wof:placetype": "venue"
  },
  "geometry": {"coordinates":[-71.211787,42.485607],"type":"Point"}
}
