{
  "type": "Feature",
  "properties": {
    "addr:full":"18 Lincoln St Natick MA 01760",
    "addr:housenumber":"18",
    "addr:postcode":"01760",
    "addr:street":"Lincoln St",
    "iso:country":"US",
    "sg:address":"18 Lincoln St",
    "sg:city":"Natick",
    "sg:classifiers":[
        {
            "category":"Banks & Credit Unions",
            "subcategory":"Investment Brokerage",
            "type":"Services"
        }
    ],
    "sg:phone":"+1 508 655 2720",
    "sg:postcode":"01760",
    "sg:province":"MA",
    "sg:tags":[
        "advisory",
        "financial"
    ],
    "wof:name":"Leo J Ryan Financial Planner",
    "wof:placetype":"venue"
},
  "geometry": {"coordinates":[-71.34392,42.283951],"type":"Point"}
}