{
  "type": "Feature",
  "properties": {
    "addr:full": "96 Salem St Boston MA 02113",
    "addr:housenumber": "96",
    "addr:postcode": "02113",
    "addr:street": "Salem St",
    "iso:country": "US",
    "sg:address": "96 Salem St",
    "sg:city": "Boston",
    "sg:classifiers": [
      {
        "category": "Food \u0026 Beverages",
        "subcategory": "Liquor \u0026 Beverages",
        "type": "Retail Goods"
      },
      {
        "category": "Food \u0026 Beverages",
        "subcategory": "Groceries \u0026 Convenience Stores",
        "type": "Retail Goods"
      }
    ],
    "sg:phone": "+1 617 248 8893",
    "sg:postcode": "02113",
    "sg:province": "MA",
    "sg:tags": [
      "beer",
      "spirit",
      "wine"
    ],
    "wof:name": "Wild Duck",
    "wof:placetype": "venue"
  },
  "geometry": {"coordinates":[-71.055654,42.364013],"type":"Point"}
}
