{
  "type": "Feature",
  "properties": {
    "iso:country":"US",
    "sg:address":"96 Salem St",
    "sg:city":"Boston",
    "sg:classifiers":[
        {
            "category":"Food & Beverages",
            "subcategory":"Liquor & Beverages",
            "type":"Retail Goods"
        },
        {
            "category":"Food & Beverages",
            "subcategory":"Groceries & Convenience Stores",
            "type":"Retail Goods"
        }
    ],
    "sg:phone":"+1 617 248 8893",
    "sg:postcode":"02113",
    "sg:province":"MA",
    "sg:tags":[
        "beer",
        "spirit",
        "wine"
    ],
    "wof:name":"Wild Duck",
    "wof:placetype":"venue"
},
  "geometry": {"coordinates":[-71.055654,42.364013],"type":"Point"}
}