{
  "type": "Feature",
  "properties": {
    "addr:full":"255 North St Pittsfield MA 01201",
    "addr:housenumber":"255",
    "addr:postcode":"01201",
    "addr:street":"North St",
    "iso:country":"US",
    "sg:address":"255 North St",
    "sg:city":"Pittsfield",
    "sg:classifiers":[
        {
            "category":"Professional",
            "type":"Services"
        }
    ],
    "sg:phone":"+1 413 499 6617",
    "sg:postcode":"01201",
    "sg:province":"MA",
    "wof:name":"State Line Svc",
    "wof:placetype":"venue"
},
  "geometry": {"coordinates":[-73.25311499999999,42.451836],"type":"Point"}
}