{
  "type": "Feature",
  "properties": {
    "addr:full": "42 Davis Rd Acton MA 01720",
    "addr:housenumber": "42",
    "addr:postcode": "01720",
    "addr:street": "Davis Rd",
    "iso:country": "US",
    "sg:address": "42 Davis Rd",
    "sg:city": "Acton",
    "sg:classifiers": [
      {
        "category": "Building \u0026 Trades",
        "subcategory": "Construction",
        "type": "Services"
      }
    ],
    "sg:phone": "+1 978 263 8315",
    "sg:postcode": "01720",
    "sg:province": "MA",
    "sg:tags": [
      "course",
      "golf"
    ],
    "wof:name": "NMP Golf Construction",
    "wof:placetype": "venue"
  },
  "geometry": {"coordinates":[-71.413531,42.502245],"type":"Point"}
}
