{
  "type": "Feature",
  "properties": {
    "iso:country":"US",
    "sg:address":"42 Davis Rd",
    "sg:city":"Acton",
    "sg:classifiers":[
        {
            "category":"Building & Trades",
            "subcategory":"Construction",
            "type":"Services"
        }
    ],
    "sg:phone":"+1 978 263 8315",
    "sg:postcode":"01720",
    "sg:province":"MA",
    "sg:tags":[
        "course",
        "golf"
    ],
    "wof:name":"NMP Golf Construction",
    "wof:placetype":"venue"
},
  "geometry": {"coordinates":[-71.41353100000001,42.502245],"type":"Point"}
}