{
  "type": "Feature",
  "properties": {
    "iso:country":"US",
    "sg:address":"1305 Springfield St",
    "sg:city":"Feeding Hills",
    "sg:classifiers":[
        {
            "category":"Education",
            "subcategory":"Special Training",
            "type":"Public Place"
        }
    ],
    "sg:phone":"+1 413 789 3649",
    "sg:postcode":"01030",
    "sg:province":"MA",
    "sg:tags":[
        "center"
    ],
    "wof:name":"Massachusetts Music Education",
    "wof:placetype":"venue"
},
  "geometry": {"coordinates":[-72.67295300000001,42.067663],"type":"Point"}
}