{
  "type": "Feature",
  "properties": {
    "addr:full":"295 Huntington Ave Boston MA 02115",
    "addr:housenumber":"295",
    "addr:postcode":"02115",
    "addr:street":"Huntington Ave",
    "iso:country":"US",
    "sg:address":"295 Huntington Ave",
    "sg:city":"Boston",
    "sg:classifiers":[
        {
            "category":"Education",
            "subcategory":"Special Training",
            "type":"Public Place"
        }
    ],
    "sg:phone":"+1 617 536 4553",
    "sg:postcode":"02115",
    "sg:province":"MA",
    "sg:tags":[
        "instruction",
        "music"
    ],
    "sg:website":"www.thevoicestudio.com",
    "wof:name":"Jeannie Deva Voice Studio",
    "wof:placetype":"venue"
},
  "geometry": {"coordinates":[-71.08886,42.340592],"type":"Point"}
}