{
  "type": "Feature",
  "properties": {
    "iso:country":"US",
    "sg:address":"102 State Rd",
    "sg:city":"North Dartmouth",
    "sg:classifiers":[
        {
            "category":"Real Estate",
            "subcategory":"Real Estate Agent",
            "type":"Services"
        }
    ],
    "sg:phone":"+1 508 996 9744",
    "sg:postcode":"02747",
    "sg:province":"MA",
    "wof:name":"Jeffery D Antine & Co",
    "wof:placetype":"venue"
},
  "geometry": {"coordinates":[-70.969329,41.638081],"type":"Point"}
}