{
  "type": "Feature",
  "properties": {
    "iso:country":"US",
    "sg:address":"200 Boston Avenue",
    "sg:city":"Medford",
    "sg:classifiers":[
        {
            "category":"Banks & Credit Unions",
            "subcategory":"Bank",
            "type":"Services"
        }
    ],
    "sg:phone":"+1 781 395 7700",
    "sg:postcode":"02155",
    "sg:province":"MA",
    "wof:name":"Ancora Pharmaceuticals",
    "wof:placetype":"venue"
},
  "geometry": {"coordinates":[-71.12767599999999,42.415461],"type":"Point"}
}