{
  "type": "Feature",
  "properties": {
    "iso:country":"US",
    "sg:address":"57 Stonegate Rd",
    "sg:city":"Chelmsford",
    "sg:classifiers":[
        {
            "category":"Health Services",
            "subcategory":"Clinic",
            "type":"Services"
        }
    ],
    "sg:phone":"+1 978 250 3997",
    "sg:postcode":"01824",
    "sg:province":"MA",
    "wof:name":"Tufts Assoc Health",
    "wof:placetype":"venue"
},
  "geometry": {"coordinates":[-71.32571,42.589102],"type":"Point"}
}