{
  "type": "Feature",
  "properties": {
    "iso:country":"US",
    "sg:address":"88 Jackson St",
    "sg:city":"Northampton",
    "sg:classifiers":[
        {
            "category":"Wholesale",
            "subcategory":"Farm Supplies",
            "type":"Manufacturing & Wholesale Goods"
        }
    ],
    "sg:phone":"+1   ",
    "sg:postcode":"01060",
    "sg:province":"MA",
    "wof:name":"Andrew F Paciorek",
    "wof:placetype":"venue"
},
  "geometry": {"coordinates":[-72.64469099999999,42.332856],"type":"Point"}
}