{
  "type": "Feature",
  "properties": {
    "addr:full": "88 Jackson St Northampton MA 01060",
    "addr:housenumber": "88",
    "addr:postcode": "01060",
    "addr:street": "Jackson St",
    "iso:country": "US",
    "sg:address": "88 Jackson St",
    "sg:city": "Northampton",
    "sg:classifiers": [
      {
        "category": "Wholesale",
        "subcategory": "Farm Supplies",
        "type": "Manufacturing \u0026 Wholesale Goods"
      }
    ],
    "sg:phone": "+1   ",
    "sg:postcode": "01060",
    "sg:province": "MA",
    "wof:name": "Andrew F Paciorek",
    "wof:placetype": "venue"
  },
  "geometry": {"coordinates":[-72.644691,42.332856],"type":"Point"}
}
