{
  "type": "Feature",
  "properties": {
    "addr:full":"665 Beacon St Boston MA 02215",
    "addr:housenumber":"665",
    "addr:postcode":"02215",
    "addr:street":"Beacon St",
    "iso:country":"US",
    "sg:address":"665 Beacon St",
    "sg:city":"Boston",
    "sg:classifiers":[
        {
            "category":"Education",
            "subcategory":"Dance Studio",
            "type":"Public Place"
        }
    ],
    "sg:phone":"+1 857 413 7749",
    "sg:postcode":"02215",
    "sg:province":"MA",
    "sg:website":"www.levelupbboy.com",
    "wof:name":"Level Up Bboy Studio",
    "wof:placetype":"venue"
},
  "geometry": {"coordinates":[-71.098527,42.348326],"type":"Point"}
}