{
  "type": "Feature",
  "properties": {
    "addr:full":"350 Woburn St Lowell MA 01852",
    "addr:housenumber":"350",
    "addr:postcode":"01852",
    "addr:street":"Woburn St",
    "iso:country":"US",
    "sg:address":"350 Woburn St",
    "sg:city":"Lowell",
    "sg:classifiers":[
        {
            "category":"Manufacturing",
            "subcategory":"Electronics",
            "type":"Manufacturing & Wholesale Goods"
        }
    ],
    "sg:phone":"+1 978 970 3700",
    "sg:postcode":"01852",
    "sg:province":"MA",
    "sg:tags":[
        "equipment",
        "electronic",
        "supply"
    ],
    "wof:name":"Jabil Circuit Inc",
    "wof:placetype":"venue"
},
  "geometry": {"coordinates":[-71.28752,42.615239],"type":"Point"}
}