{
  "type": "Feature",
  "properties": {
    "addr:full":"85 Main St Byfield MA 01922",
    "addr:housenumber":"85",
    "addr:postcode":"01922",
    "addr:street":"Main St",
    "iso:country":"US",
    "sg:address":"85 Main St",
    "sg:city":"Byfield",
    "sg:classifiers":[
        {
            "category":"Professional",
            "subcategory":"Printing & Photocopies",
            "type":"Services"
        }
    ],
    "sg:phone":"+1 978 255 2139",
    "sg:postcode":"01922",
    "sg:province":"MA",
    "sg:tags":[
        "photographers-commercial"
    ],
    "wof:name":"A Perfect Image",
    "wof:placetype":"venue"
},
  "geometry": {"coordinates":[-70.947388,42.761349],"type":"Point"}
}