{
  "type": "Feature",
  "properties": {
    "addr:full":"7 Nel Bonney Rd Plympton MA 02367",
    "addr:housenumber":"7",
    "addr:postcode":"02367",
    "addr:street":"Nel Bonney Rd",
    "iso:country":"US",
    "sg:address":"7 Nel Bonney Rd",
    "sg:city":"Plympton",
    "sg:classifiers":[
        {
            "category":"Professional",
            "type":"Services"
        }
    ],
    "sg:phone":"+1 781 585 7400",
    "sg:postcode":"02367",
    "sg:province":"MA",
    "sg:tags":[
        "establishment"
    ],
    "wof:name":"Camera Turret",
    "wof:placetype":"venue"
},
  "geometry": {"coordinates":[-70.785236,41.941544],"type":"Point"}
}