{
  "type": "Feature",
  "properties": {
    "addr:full": "544 State Hwy 130 Mashpee MA 02649",
    "addr:housenumber": "544",
    "addr:postcode": "02649",
    "addr:street": "State Hwy 130",
    "iso:country": "US",
    "sg:address": "544 State Hwy 130",
    "sg:city": "Mashpee",
    "sg:classifiers": [
      {
        "category": "Wholesale",
        "subcategory": "Construction Materials",
        "type": "Manufacturing \u0026 Wholesale Goods"
      }
    ],
    "sg:phone": "+1 508 477 4600",
    "sg:postcode": "02649",
    "sg:province": "MA",
    "sg:tags": [
      "concrete",
      "shape",
      "block"
    ],
    "wof:name": "Harwich Concrete Block",
    "wof:placetype": "venue"
  },
  "geometry": {"coordinates":[-70.496021,41.659799],"type":"Point"}
}
