{
  "type": "Feature",
  "properties": {
    "addr:full":"637 N Montello St Brockton MA 02301",
    "addr:housenumber":"637",
    "addr:postcode":"02301",
    "addr:street":"N Montello St",
    "iso:country":"US",
    "sg:address":"637 N Montello St",
    "sg:city":"Brockton",
    "sg:classifiers":[
        {
            "category":"Professional",
            "subcategory":"Business Services",
            "type":"Services"
        }
    ],
    "sg:phone":"+1 508 587 7000",
    "sg:postcode":"02301",
    "sg:province":"MA",
    "sg:tags":[
        "interior",
        "consultant",
        "design",
        "decorator"
    ],
    "wof:name":"Contract Decor Intl",
    "wof:placetype":"venue"
},
  "geometry": {"coordinates":[-71.01897,42.101198],"type":"Point"}
}