{
  "type": "Feature",
  "properties": {
    "addr:full": "364 Whiting Ave Dedham MA 02026",
    "addr:housenumber": "364",
    "addr:postcode": "02026",
    "addr:street": "Whiting Ave",
    "iso:country": "US",
    "sg:address": "364 Whiting Ave",
    "sg:city": "Dedham",
    "sg:classifiers": [
      {
        "category": "Taxi",
        "type": "Transportation"
      }
    ],
    "sg:phone": "+1   ",
    "sg:postcode": "02026",
    "sg:province": "MA",
    "sg:tags": [
      "taxicab"
    ],
    "wof:name": "Farah Cab Inc",
    "wof:placetype": "venue"
  },
  "geometry": {"coordinates":[-71.153044,42.243483],"type":"Point"}
}
