{
  "type": "Feature",
  "properties": {
    "iso:country":"US",
    "sg:address":"632 Washington St",
    "sg:city":"South Easton",
    "sg:classifiers":[
        {
            "category":"Health Services",
            "subcategory":"Chiropractor",
            "type":"Services"
        }
    ],
    "sg:phone":"+1 508 238 7799",
    "sg:postcode":"02375",
    "sg:province":"MA",
    "wof:name":"Easton Chiropractic Offices",
    "wof:placetype":"venue"
},
  "geometry": {"coordinates":[-71.079106,42.044561],"type":"Point"}
}