{
  "type": "Feature",
  "properties": {
    "addr:full": "330 Boston Rd Ste 16 North Billerica MA 01862",
    "addr:housenumber": "330",
    "addr:postcode": "01862",
    "addr:street": "Boston Rd Ste 16 North",
    "iso:country": "US",
    "ovtr:label": "New Concepts Dental Group, 330 Boston Rd North Billerica MA US",
    "ovtr:similarity": 2.807554006576538,
    "sg:address": "330 Boston Rd Ste 16",
    "sg:city": "North Billerica",
    "sg:classifiers": [
      {
        "category": "Health Services",
        "subcategory": "Dentist",
        "type": "Services"
      }
    ],
    "sg:phone": "+1 978 670 1839",
    "sg:postcode": "01862",
    "sg:province": "MA",
    "sg:website": "www.newconceptsdental.com",
    "wof:name": "New Concepts Dental Group",
    "wof:placetype": "venue"
  },
  "geometry": {"coordinates":[-71.275663,42.569036],"type":"Point"}
}
