{
  "type": "Feature",
  "properties": {
    "iso:country":"US",
    "sg:address":"330 Boston Rd Ste 16",
    "sg:city":"North Billerica",
    "sg:classifiers":[
        {
            "category":"Health Services",
            "subcategory":"Dentist",
            "type":"Services"
        }
    ],
    "sg:phone":"+1 978 670 1839",
    "sg:postcode":"01862",
    "sg:province":"MA",
    "sg:website":"www.newconceptsdental.com",
    "wof:name":"New Concepts Dental Group",
    "wof:placetype":"venue"
},
  "geometry": {"coordinates":[-71.27566299999999,42.569036],"type":"Point"}
}