{
  "type": "Feature",
  "properties": {
    "addr:full": "166 County St Lakeville MA 02347",
    "addr:housenumber": "166",
    "addr:postcode": "02347",
    "addr:street": "County St",
    "iso:country": "US",
    "ovtr:label": "The Broken Tee Virtual Golf Club, 166 County St Lakeville MA US",
    "ovtr:similarity": 2.548454999923706,
    "sg:address": "166 County St",
    "sg:city": "Lakeville",
    "sg:classifiers": [
      {
        "category": "Arena",
        "subcategory": "Sports Club",
        "type": "Entertainment"
      },
      {
        "category": "Sports \u0026 Exercise",
        "subcategory": "Sports Center",
        "type": "Entertainment"
      },
      {
        "category": "Sports \u0026 Exercise",
        "subcategory": "Golf",
        "type": "Entertainment"
      }
    ],
    "sg:phone": "+1 508 923 4653",
    "sg:postcode": "02347",
    "sg:province": "MA",
    "sg:tags": [
      "courses-private"
    ],
    "wof:name": "The Broken Tee Virtual Golf Club",
    "wof:placetype": "venue"
  },
  "geometry": {"coordinates":[-70.968658,41.80711],"type":"Point"}
}
