{
  "type": "Feature",
  "properties": {
    "iso:country":"US",
    "sg:address":"166 County St",
    "sg:city":"Lakeville",
    "sg:classifiers":[
        {
            "category":"Arena",
            "subcategory":"Sports Club",
            "type":"Entertainment"
        },
        {
            "category":"Sports & Exercise",
            "subcategory":"Sports Center",
            "type":"Entertainment"
        },
        {
            "category":"Sports & Exercise",
            "subcategory":"Golf",
            "type":"Entertainment"
        }
    ],
    "sg:phone":"+1 508 923 4653",
    "sg:postcode":"02347",
    "sg:province":"MA",
    "sg:tags":[
        "courses-private"
    ],
    "wof:name":"The Broken Tee Virtual Golf Club",
    "wof:placetype":"venue"
},
  "geometry": {"coordinates":[-70.968658,41.80711],"type":"Point"}
}