{
  "type": "Feature",
  "properties": {
    "iso:country":"US",
    "sg:address":"54 Clayton St",
    "sg:city":"Dorchester",
    "sg:classifiers":[
        {
            "category":"Real Estate",
            "subcategory":"Real Estate Agent",
            "type":"Services"
        }
    ],
    "sg:phone":"+1 617 929 0388",
    "sg:postcode":"02122",
    "sg:province":"MA",
    "wof:name":"Liberty Realty",
    "wof:placetype":"venue"
},
  "geometry": {"coordinates":[-71.056248,42.302415],"type":"Point"}
}