{
  "type": "Feature",
  "properties": {
    "addr:full": "93 Snake Hill Rd Ayer MA 01432",
    "addr:housenumber": "93",
    "addr:postcode": "01432",
    "addr:street": "Snake Hill Rd",
    "iso:country": "US",
    "ovtr:label": "B \u0026 J Cycles Mobile Repair, 93 Snake Hill Rd Ayer MA US",
    "ovtr:similarity": 1.8849530220031738,
    "sg:address": "93 Snake Hill Rd",
    "sg:city": "Ayer",
    "sg:classifiers": [
      {
        "category": "Autos \u0026 Motor Vehicles",
        "subcategory": "Motorcycle Sales",
        "type": "Retail Goods"
      }
    ],
    "sg:phone": "+1 978 772 7864",
    "sg:postcode": "01432",
    "sg:province": "MA",
    "sg:tags": [
      "scooter"
    ],
    "wof:name": "B \u0026 J Cycles Mobile Repair",
    "wof:placetype": "venue"
  },
  "geometry": {"coordinates":[-71.558629,42.552579],"type":"Point"}
}
