{
  "type": "Feature",
  "properties": {
    "iso:country":"US",
    "sg:address":"93 Snake Hill Rd",
    "sg:city":"Ayer",
    "sg:classifiers":[
        {
            "category":"Autos & Motor Vehicles",
            "subcategory":"Motorcycle Sales",
            "type":"Retail Goods"
        }
    ],
    "sg:phone":"+1 978 772 7864",
    "sg:postcode":"01432",
    "sg:province":"MA",
    "sg:tags":[
        "scooter"
    ],
    "wof:name":"B & J Cycles Mobile Repair",
    "wof:placetype":"venue"
},
  "geometry": {"coordinates":[-71.558629,42.552579],"type":"Point"}
}