{
  "type": "Feature",
  "properties": {
    "iso:country":"US",
    "sg:address":"118 Washington St",
    "sg:city":"Marblehead",
    "sg:classifiers":[
        {
            "category":"Food & Beverages",
            "subcategory":"Groceries & Convenience Stores",
            "type":"Retail Goods"
        }
    ],
    "sg:phone":"+1 781 631 1741",
    "sg:postcode":"01945",
    "sg:province":"MA",
    "sg:tags":[
        "grocer"
    ],
    "wof:name":"Crosby's Market",
    "wof:placetype":"venue"
},
  "geometry": {"coordinates":[-70.849784,42.504907],"type":"Point"}
}