{
  "type": "Feature",
  "properties": {
    "addr:full": "118 Washington St Marblehead MA 01945",
    "addr:housenumber": "118",
    "addr:postcode": "01945",
    "addr:street": "Washington St",
    "iso:country": "US",
    "sg:address": "118 Washington St",
    "sg:city": "Marblehead",
    "sg:classifiers": [
      {
        "category": "Food \u0026 Beverages",
        "subcategory": "Groceries \u0026 Convenience Stores",
        "type": "Retail Goods"
      }
    ],
    "sg:phone": "+1 781 631 1741",
    "sg:postcode": "01945",
    "sg:province": "MA",
    "sg:tags": [
      "grocer"
    ],
    "wof:name": "Crosby's Market",
    "wof:placetype": "venue"
  },
  "geometry": {"coordinates":[-70.849784,42.504907],"type":"Point"}
}
