{
  "type": "Feature",
  "properties": {
    "addr:full":"333 Lowell St Somerville MA 02145",
    "addr:housenumber":"333",
    "addr:postcode":"02145",
    "addr:street":"Lowell St",
    "iso:country":"US",
    "sg:address":"333 Lowell St",
    "sg:city":"Somerville",
    "sg:classifiers":[
        {
            "category":"Professional",
            "type":"Services"
        }
    ],
    "sg:phone":"+1   ",
    "sg:postcode":"02145",
    "sg:province":"MA",
    "wof:name":"Jfc II Inc",
    "wof:placetype":"venue"
},
  "geometry": {"coordinates":[-71.104945,42.394321],"type":"Point"}
}