{
  "type": "Feature",
  "properties": {
    "iso:country":"US",
    "sg:address":"227 Eisenhower Dr",
    "sg:city":"Cotuit",
    "sg:classifiers":[
        {
            "category":"Wholesale",
            "subcategory":"Painting Supplies",
            "type":"Manufacturing & Wholesale Goods"
        }
    ],
    "sg:phone":"+1 508 420 3575",
    "sg:postcode":"02635",
    "sg:province":"MA",
    "sg:tags":[
        "colors",
        "pigment"
    ],
    "wof:name":"E M Industries",
    "wof:placetype":"venue"
},
  "geometry": {"coordinates":[-70.430695,41.636996],"type":"Point"}
}