{
  "type": "Feature",
  "properties": {
    "iso:country":"US",
    "sg:address":"36 State Hwy 28",
    "sg:city":"West Harwich",
    "sg:classifiers":[
        {
            "category":"Travel",
            "subcategory":"Hotels & Motels",
            "type":"Entertainment"
        }
    ],
    "sg:phone":"+1 508 432 6789",
    "sg:postcode":"02671",
    "sg:province":"MA",
    "sg:tags":[
        "breakfast",
        "accommodation",
        "bed"
    ],
    "sg:website":"www.barnabyinn.com",
    "wof:name":"Barnaby Inn",
    "wof:placetype":"venue"
},
  "geometry": {"coordinates":[-70.119863,41.66914],"type":"Point"}
}