{
  "type": "Feature",
  "properties": {
    "addr:full": "36 State Hwy 28 West Harwich MA 02671",
    "addr:housenumber": "36",
    "addr:postcode": "02671",
    "addr:street": "State Hwy 28",
    "iso:country": "US",
    "ovtr:label": "Barnaby Inn, 36 Route 28 West Harwich MA US",
    "ovtr:similarity": 3.3688700199127197,
    "sg:address": "36 State Hwy 28",
    "sg:city": "West Harwich",
    "sg:classifiers": [
      {
        "category": "Travel",
        "subcategory": "Hotels \u0026 Motels",
        "type": "Entertainment"
      }
    ],
    "sg:phone": "+1 508 432 6789",
    "sg:postcode": "02671",
    "sg:province": "MA",
    "sg:tags": [
      "breakfast",
      "accommodation",
      "bed"
    ],
    "sg:website": "www.barnabyinn.com",
    "wof:name": "Barnaby Inn",
    "wof:placetype": "venue"
  },
  "geometry": {"coordinates":[-70.119863,41.66914],"type":"Point"}
}
