{
  "type": "Feature",
  "properties": {
    "addr:full":"29 Union St North Andover MA 01845",
    "addr:housenumber":"29",
    "addr:postcode":"01845",
    "addr:street":"Union St",
    "iso:country":"US",
    "sg:address":"29 Union St",
    "sg:city":"North Andover",
    "sg:classifiers":[
        {
            "category":"Shopping",
            "subcategory":"Gifts & Souvenirs",
            "type":"Retail Goods"
        }
    ],
    "sg:phone":"+1 978 686 6500",
    "sg:postcode":"01845",
    "sg:province":"MA",
    "sg:tags":[
        "shop"
    ],
    "wof:name":"Mel B's Gifts",
    "wof:placetype":"venue"
},
  "geometry": {"coordinates":[-71.135848,42.700441],"type":"Point"}
}