{
  "type": "Feature",
  "properties": {
    "addr:full":"34 Chestnut St Charlestown MA 02129",
    "addr:housenumber":"34",
    "addr:postcode":"02129",
    "addr:street":"Chestnut St",
    "iso:country":"US",
    "sg:address":"34 Chestnut St",
    "sg:city":"Charlestown",
    "sg:classifiers":[
        {
            "category":"Professional",
            "subcategory":"Business Services",
            "type":"Services"
        }
    ],
    "sg:phone":"+1   ",
    "sg:postcode":"02129",
    "sg:province":"MA",
    "wof:name":"Janet L Shensa Interior Design",
    "wof:placetype":"venue"
},
  "geometry": {"coordinates":[-71.05905,42.374494],"type":"Point"}
}