{
  "type": "Feature",
  "properties": {
    "addr:full": "1050 South St Pittsfield MA 01201",
    "addr:housenumber": "1050",
    "addr:postcode": "01201",
    "addr:street": "South St",
    "iso:country": "US",
    "sg:address": "1050 South St",
    "sg:city": "Pittsfield",
    "sg:classifiers": [
      {
        "category": "Restaurant",
        "type": "Food \u0026 Drink"
      }
    ],
    "sg:phone": "+1 413 236 5699",
    "sg:postcode": "01201",
    "sg:province": "MA",
    "sg:tags": [
      "sandwich"
    ],
    "wof:name": "Coffee Hut",
    "wof:placetype": "venue"
  },
  "geometry": {"coordinates":[-73.263081,42.409824],"type":"Point"}
}
