{
  "type": "Feature",
  "properties": {
    "iso:country":"US",
    "sg:address":"35 Pine St",
    "sg:city":"Stoneham",
    "sg:classifiers":[
        {
            "category":"Professional",
            "subcategory":"Business Services",
            "type":"Services"
        }
    ],
    "sg:phone":"+1   ",
    "sg:postcode":"02180",
    "sg:province":"MA",
    "sg:tags":[
        "graphic"
    ],
    "wof:name":"Jessamyn Bridgland Smith",
    "wof:placetype":"venue"
},
  "geometry": {"coordinates":[-71.09753499999999,42.478825],"type":"Point"}
}