{
  "type": "Feature",
  "properties": {
    "addr:full":"170 Common St Lawrence MA 01840",
    "addr:housenumber":"170",
    "addr:postcode":"01840",
    "addr:street":"Common",
    "iso:country":"US",
    "sg:address":"170 Common St",
    "sg:city":"Lawrence",
    "sg:classifiers":[
        {
            "category":"Real Estate",
            "subcategory":"Real Estate Services",
            "type":"Services"
        },
        {
            "category":"Real Estate",
            "subcategory":"Real Estate Agent",
            "type":"Services"
        }
    ],
    "sg:phone":"+1 978 965 4148",
    "sg:postcode":"01840",
    "sg:province":"MA",
    "sg:tags":[
        "buyer",
        "broker"
    ],
    "wof:name":"E And A Realty",
    "wof:placetype":"venue"
},
  "geometry": {"coordinates":[-71.158362,42.708469],"type":"Point"}
}