{
  "type": "Feature",
  "properties": {
    "iso:country":"US",
    "sg:address":"7 N Vine St",
    "sg:city":"Milford",
    "sg:classifiers":[
        {
            "category":"Professional",
            "subcategory":"Detective & Security Services",
            "type":"Services"
        }
    ],
    "sg:phone":"+1   ",
    "sg:postcode":"01757",
    "sg:province":"MA",
    "sg:tags":[
        "car"
    ],
    "wof:name":"Dan F Niro",
    "wof:placetype":"venue"
},
  "geometry": {"coordinates":[-71.539551,42.159227],"type":"Point"}
}