{
  "type": "Feature",
  "properties": {
    "addr:full":"63 Lowell St Methuen MA 01844",
    "addr:housenumber":"63",
    "addr:postcode":"01844",
    "addr:street":"Lowell St",
    "iso:country":"US",
    "sg:address":"63 Lowell St",
    "sg:city":"Methuen",
    "sg:classifiers":[
        {
            "category":"Shopping",
            "subcategory":"Clothing, Apparel, & Fashions",
            "type":"Retail Goods"
        }
    ],
    "sg:phone":"+1   ",
    "sg:postcode":"01844",
    "sg:province":"MA",
    "sg:tags":[
        "accessory"
    ],
    "wof:name":"Erdemir Tailor Shop",
    "wof:placetype":"venue"
},
  "geometry": {"coordinates":[-71.193697,42.723251],"type":"Point"}
}