{
  "type": "Feature",
  "properties": {
    "iso:country":"US",
    "sg:address":"50 Kitteridge Ave",
    "sg:city":"Tewksbury",
    "sg:classifiers":[
        {
            "category":"Building & Trades",
            "subcategory":"Construction",
            "type":"Services"
        }
    ],
    "sg:phone":"+1 978 640 2935",
    "sg:postcode":"01876",
    "sg:province":"MA",
    "sg:tags":[
        "woodworker"
    ],
    "wof:name":"American Architectural Co Inc",
    "wof:placetype":"venue"
},
  "geometry": {"coordinates":[-71.269307,42.620963],"type":"Point"}
}