{
  "type": "Feature",
  "properties": {
    "iso:country":"US",
    "sg:address":"24 Fox Run Rd",
    "sg:city":"Bedford",
    "sg:classifiers":[
        {
            "category":"Building & Trades",
            "subcategory":"Equipment Rental",
            "type":"Services"
        }
    ],
    "sg:phone":"+1   ",
    "sg:postcode":"01730",
    "sg:province":"MA",
    "wof:name":"Thomas Hirsch",
    "wof:placetype":"venue"
},
  "geometry": {"coordinates":[-71.280872,42.525349],"type":"Point"}
}