{
  "type": "Feature",
  "properties": {
    "iso:country":"US",
    "sg:address":"487 Vale St",
    "sg:city":"Fall River",
    "sg:classifiers":[
        {
            "category":"Real Estate",
            "subcategory":"Real Estate Agent",
            "type":"Services"
        }
    ],
    "sg:phone":"+1   ",
    "sg:postcode":"02724",
    "sg:province":"MA",
    "wof:name":"Amaral & Associates RE",
    "wof:placetype":"venue"
},
  "geometry": {"coordinates":[-71.166448,41.682003],"type":"Point"}
}