{
  "type": "Feature",
  "properties": {
    "addr:full": "67 County St Dover MA 02030",
    "addr:housenumber": "67",
    "addr:postcode": "02030",
    "addr:street": "County St",
    "iso:country": "US",
    "sg:address": "67 County St",
    "sg:city": "Dover",
    "sg:classifiers": [
      {
        "category": "Autos \u0026 Motor Vehicles",
        "subcategory": "Fuel \u0026 Gas Station",
        "type": "Retail Goods"
      }
    ],
    "sg:phone": "+1 508 785 1697",
    "sg:postcode": "02030",
    "sg:province": "MA",
    "sg:tags": [
      "oil"
    ],
    "wof:name": "Dover Citgo",
    "wof:placetype": "venue"
  },
  "geometry": {"coordinates":[-71.2615,42.204168],"type":"Point"}
}
