{
  "type": "Feature",
  "properties": {
    "iso:country":"US",
    "sg:address":"67 County St",
    "sg:city":"Dover",
    "sg:classifiers":[
        {
            "category":"Autos & Motor Vehicles",
            "subcategory":"Fuel & Gas Station",
            "type":"Retail Goods"
        }
    ],
    "sg:phone":"+1 508 785 1697",
    "sg:postcode":"02030",
    "sg:province":"MA",
    "sg:tags":[
        "oil"
    ],
    "wof:name":"Dover Citgo",
    "wof:placetype":"venue"
},
  "geometry": {"coordinates":[-71.2615,42.204168],"type":"Point"}
}