{
  "type": "Feature",
  "properties": {
    "iso:country":"US",
    "sg:address":"231 Highland Ave",
    "sg:city":"Seekonk",
    "sg:classifiers":[
        {
            "category":"Personal",
            "subcategory":"Beauty Salon",
            "type":"Services"
        }
    ],
    "sg:phone":"+1 508 336 2626",
    "sg:postcode":"02771",
    "sg:province":"MA",
    "wof:name":"Snip-Its",
    "wof:placetype":"venue"
},
  "geometry": {"coordinates":[-71.33237699999999,41.79786],"type":"Point"}
}