{
  "type": "Feature",
  "properties": {
    "iso:country":"US",
    "sg:address":"108 Housatonic St",
    "sg:city":"Lenox",
    "sg:classifiers":[
        {
            "category":"Shopping",
            "subcategory":"Florist",
            "type":"Retail Goods"
        }
    ],
    "sg:phone":"+1 413 637 0402",
    "sg:postcode":"01240",
    "sg:province":"MA",
    "wof:name":"Family Flowers",
    "wof:placetype":"venue"
},
  "geometry": {"coordinates":[-73.278813,42.35582],"type":"Point"}
}