{
  "type": "Feature",
  "properties": {
    "addr:full":"601 Pleasant St Brockton MA 02301",
    "addr:housenumber":"601",
    "addr:postcode":"02301",
    "addr:street":"Pleasant St",
    "iso:country":"US",
    "sg:address":"601 Pleasant St",
    "sg:city":"Brockton",
    "sg:classifiers":[
        {
            "category":"Health Services",
            "subcategory":"Doctor",
            "type":"Services"
        }
    ],
    "sg:phone":"+1 508 586 2951",
    "sg:postcode":"02301",
    "sg:province":"MA",
    "sg:tags":[
        "dentist"
    ],
    "wof:name":"David M Finstein DDS",
    "wof:placetype":"venue"
},
  "geometry": {"coordinates":[-71.04604399999999,42.088905],"type":"Point"}
}