{
  "type": "Feature",
  "properties": {
    "addr:full": "151 Endicott St Danvers MA 01923",
    "addr:housenumber": "151",
    "addr:postcode": "01923",
    "addr:street": "Endicott St",
    "iso:country": "US",
    "sg:address": "151 Endicott St",
    "sg:city": "Danvers",
    "sg:classifiers": [
      {
        "category": "Home \u0026 Garden",
        "subcategory": "Building Materials",
        "type": "Retail Goods"
      }
    ],
    "sg:phone": "+1 978 777 2057",
    "sg:postcode": "01923",
    "sg:province": "MA",
    "sg:tags": [
      "paint"
    ],
    "wof:name": "Sherwin-Williams Paints",
    "wof:placetype": "venue"
  },
  "geometry": {"coordinates":[-70.940297,42.548745],"type":"Point"}
}
