{
  "type": "Feature",
  "properties": {
    "addr:full":"56 Cynthia Rd Newton MA 02459",
    "addr:housenumber":"56",
    "addr:postcode":"02459",
    "addr:street":"Cynthia Rd",
    "iso:country":"US",
    "sg:address":"56 Cynthia Rd",
    "sg:city":"Newton",
    "sg:classifiers":[
        {
            "category":"Professional",
            "subcategory":"Business Services",
            "type":"Services"
        }
    ],
    "sg:phone":"+1   ",
    "sg:postcode":"02459",
    "sg:province":"MA",
    "wof:name":"Design Resources S",
    "wof:placetype":"venue"
},
  "geometry": {"coordinates":[-71.183052,42.305726],"type":"Point"}
}