{
  "type": "Feature",
  "properties": {
    "addr:full":"23 Berdon Way Fairhaven MA 02719",
    "addr:housenumber":"23",
    "addr:postcode":"02719",
    "addr:street":"Berdon Way",
    "iso:country":"US",
    "sg:address":"23 Berdon Way",
    "sg:city":"Fairhaven",
    "sg:classifiers":[
        {
            "category":"Autos & Motor Vehicles",
            "subcategory":"Auto Supplies",
            "type":"Retail Goods"
        }
    ],
    "sg:phone":"+1 508 996 3250",
    "sg:postcode":"02719",
    "sg:province":"MA",
    "sg:tags":[
        "tire"
    ],
    "wof:name":"Town Fair Tire",
    "wof:placetype":"venue"
},
  "geometry": {"coordinates":[-70.88405299999999,41.640156],"type":"Point"}
}