{
  "type": "Feature",
  "properties": {
    "iso:country":"US",
    "sg:address":"50 Payson Ave Ste 100",
    "sg:city":"Easthampton",
    "sg:classifiers":[
        {
            "category":"Education",
            "subcategory":"School",
            "type":"Public Place"
        }
    ],
    "sg:phone":"+1 413 529 1500",
    "sg:postcode":"01027",
    "sg:province":"MA",
    "wof:name":"Easthampton Public Schools",
    "wof:placetype":"venue"
},
  "geometry": {"coordinates":[-72.670711,42.265934],"type":"Point"}
}