{
  "type": "Feature",
  "properties": {
    "iso:country":"US",
    "sg:address":"212 Great Rd",
    "sg:city":"Maynard",
    "sg:classifiers":[
        {
            "category":"Organizations",
            "subcategory":"Community Association",
            "type":"Services"
        }
    ],
    "sg:phone":"+1 978 461 2871",
    "sg:postcode":"01754",
    "sg:province":"MA",
    "sg:tags":[
        "club"
    ],
    "wof:name":"Boys & Girls Of Assobet Valley",
    "wof:placetype":"venue"
},
  "geometry": {"coordinates":[-71.45039800000001,42.423546],"type":"Point"}
}