{
  "type": "Feature",
  "properties": {
    "addr:full": "212 Great Rd Maynard MA 01754",
    "addr:housenumber": "212",
    "addr:postcode": "01754",
    "addr:street": "Great Rd",
    "iso:country": "US",
    "sg:address": "212 Great Rd",
    "sg:city": "Maynard",
    "sg:classifiers": [
      {
        "category": "Organizations",
        "subcategory": "Community Association",
        "type": "Services"
      }
    ],
    "sg:phone": "+1 978 461 2871",
    "sg:postcode": "01754",
    "sg:province": "MA",
    "sg:tags": [
      "club"
    ],
    "wof:name": "Boys \u0026 Girls Of Assobet Valley",
    "wof:placetype": "venue"
  },
  "geometry": {"coordinates":[-71.450398,42.423546],"type":"Point"}
}
