{
  "type": "Feature",
  "properties": {
    "iso:country":"US",
    "sg:address":"1381 Boylston St",
    "sg:city":"Boston",
    "sg:classifiers":[
        {
            "category":"Restaurant",
            "type":"Food & Drink"
        }
    ],
    "sg:phone":"+1 617 437 1111",
    "sg:postcode":"02215",
    "sg:province":"MA",
    "sg:tags":[
        "pizza"
    ],
    "sg:website":"cambridge1.us",
    "wof:name":"Cambridge, 1.",
    "wof:placetype":"venue"
},
  "geometry": {"coordinates":[-71.101147,42.343848],"type":"Point"}
}