{
  "type": "Feature",
  "properties": {
    "addr:full": "13 Valley Rd Mashpee MA 02649",
    "addr:housenumber": "13",
    "addr:postcode": "02649",
    "addr:street": "Valley Rd",
    "iso:country": "US",
    "sg:address": "13 Valley Rd",
    "sg:city": "Mashpee",
    "sg:classifiers": [
      {
        "category": "Professional",
        "type": "Services"
      }
    ],
    "sg:phone": "+1   ",
    "sg:postcode": "02649",
    "sg:province": "MA",
    "wof:name": "Edwin Davis Humphrey",
    "wof:placetype": "venue"
  },
  "geometry": {"coordinates":[-70.519468,41.637067],"type":"Point"}
}
