{
  "type": "Feature",
  "properties": {
    "addr:full": "49 South St Grafton MA 01519",
    "addr:housenumber": "49",
    "addr:postcode": "01519",
    "addr:street": "South St",
    "iso:country": "US",
    "sg:address": "49 South St",
    "sg:city": "Grafton",
    "sg:classifiers": [
      {
        "category": "Building \u0026 Trades",
        "subcategory": "Construction",
        "type": "Services"
      }
    ],
    "sg:phone": "+1 508 839 6985",
    "sg:postcode": "01519",
    "sg:province": "MA",
    "sg:tags": [
      "project"
    ],
    "wof:name": "Sjogren Rental \u0026 Construction",
    "wof:placetype": "venue"
  },
  "geometry": {"coordinates":[-71.68494,42.204996],"type":"Point"}
}
