{
  "type": "Feature",
  "properties": {
    "addr:full":"127 Woodcrest Dr Chicopee MA 01020",
    "addr:housenumber":"127",
    "addr:postcode":"01020",
    "addr:street":"Woodcrest Dr",
    "iso:country":"US",
    "sg:address":"127 Woodcrest Dr",
    "sg:city":"Chicopee",
    "sg:classifiers":[
        {
            "category":"Community Center",
            "type":"Public Place"
        }
    ],
    "sg:phone":"+1 413 331 0596",
    "sg:postcode":"01020",
    "sg:province":"MA",
    "sg:tags":[
        "medical"
    ],
    "wof:name":"Adventist Medical Center",
    "wof:placetype":"venue"
},
  "geometry": {"coordinates":[-72.58564699999999,42.181032],"type":"Point"}
}