{
  "type": "Feature",
  "properties": {
    "iso:country":"US",
    "sg:address":"108 Myrtle St",
    "sg:city":"Melrose",
    "sg:classifiers":[
        {
            "category":"Sports & Exercise",
            "subcategory":"Gym",
            "type":"Entertainment"
        }
    ],
    "sg:phone":"+1   ",
    "sg:postcode":"02176",
    "sg:province":"MA",
    "sg:tags":[
        "fitness",
        "physical",
        "facility"
    ],
    "wof:name":"Fitness Strategies By Steven",
    "wof:placetype":"venue"
},
  "geometry": {"coordinates":[-71.066563,42.457306],"type":"Point"}
}