{
  "type": "Feature",
  "properties": {
    "addr:full": "1071 Main St Woburn MA 01801",
    "addr:housenumber": "1071",
    "addr:postcode": "01801",
    "addr:street": "Main St",
    "iso:country": "US",
    "sg:address": "1071 Main St",
    "sg:city": "Woburn",
    "sg:classifiers": [
      {
        "category": "Utilities",
        "subcategory": "Refuse",
        "type": "Services"
      }
    ],
    "sg:phone": "+1 781 935 6339",
    "sg:postcode": "01801",
    "sg:province": "MA",
    "sg:tags": [
      "garbage",
      "collection"
    ],
    "wof:name": "Acme Waste Systems Inc",
    "wof:placetype": "venue"
  },
  "geometry": {"coordinates":[-71.160449,42.5171],"type":"Point"}
}
