{
  "type": "Feature",
  "properties": {
    "iso:country":"US",
    "sg:address":"100 Fessenden St",
    "sg:city":"Newtonville",
    "sg:classifiers":[
        {
            "category":"Health Services",
            "subcategory":"Chiropractor",
            "type":"Services"
        }
    ],
    "sg:phone":"+1 617 965 2510",
    "sg:postcode":"02460",
    "sg:province":"MA",
    "wof:name":"Dr Timothy Knight Chiropractor",
    "wof:placetype":"venue"
},
  "geometry": {"coordinates":[-71.21427799999999,42.361053],"type":"Point"}
}