{
  "type": "Feature",
  "properties": {
    "addr:full": "100 Fessenden St Newtonville MA 02460",
    "addr:housenumber": "100",
    "addr:postcode": "02460",
    "addr:street": "Fessenden St",
    "iso:country": "US",
    "sg:address": "100 Fessenden St",
    "sg:city": "Newtonville",
    "sg:classifiers": [
      {
        "category": "Health Services",
        "subcategory": "Chiropractor",
        "type": "Services"
      }
    ],
    "sg:phone": "+1 617 965 2510",
    "sg:postcode": "02460",
    "sg:province": "MA",
    "wof:name": "Dr Timothy Knight Chiropractor",
    "wof:placetype": "venue"
  },
  "geometry": {"coordinates":[-71.214278,42.361053],"type":"Point"}
}
