{
  "type": "Feature",
  "properties": {
    "iso:country":"US",
    "sg:address":"65 Riverside Rd",
    "sg:city":"Gardner",
    "sg:classifiers":[
        {
            "category":"Autos & Motor Vehicles",
            "subcategory":"Automobile Sales",
            "type":"Retail Goods"
        },
        {
            "category":"Autos & Motor Vehicles",
            "subcategory":"Auto Supplies",
            "type":"Retail Goods"
        }
    ],
    "sg:phone":"+1 978 632 7190",
    "sg:postcode":"01440",
    "sg:province":"MA",
    "sg:tags":[
        "salvage",
        "rebuilt",
        "part",
        "supplies-used"
    ],
    "wof:name":"Riverside Auto Salvage",
    "wof:placetype":"venue"
},
  "geometry": {"coordinates":[-72.022873,42.575291],"type":"Point"}
}