{
  "type": "Feature",
  "properties": {
    "addr:full": "67 Main St Charlestown MA 02129",
    "addr:housenumber": "67",
    "addr:postcode": "02129",
    "addr:street": "Main St",
    "iso:country": "US",
    "sg:address": "67 Main St",
    "sg:city": "Charlestown",
    "sg:classifiers": [
      {
        "category": "Professional",
        "type": "Services"
      },
      {
        "category": "Restaurant",
        "type": "Food \u0026 Drink"
      }
    ],
    "sg:menulink": "http://www.allmenus.com/ma/boston/562-figs/menu/",
    "sg:phone": "+1 617 242 2229",
    "sg:postcode": "02129",
    "sg:province": "MA",
    "sg:tags": [
      "american",
      "italian",
      "pizza"
    ],
    "wof:name": "Figs",
    "wof:placetype": "venue"
  },
  "geometry": {"coordinates":[-71.062547,42.373585],"type":"Point"}
}
