{
  "type": "Feature",
  "properties": {
    "iso:country":"US",
    "sg:address":"4 Court Sq",
    "sg:city":"Greenfield",
    "sg:classifiers":[
        {
            "category":"Insurance",
            "subcategory":"Insurance Agent",
            "type":"Services"
        }
    ],
    "sg:phone":"+1 413 772 0238",
    "sg:postcode":"01301",
    "sg:province":"MA",
    "wof:name":"Northwestern Mutual Financial",
    "wof:placetype":"venue"
},
  "geometry": {"coordinates":[-72.600814,42.587194],"type":"Point"}
}