{
  "type": "Feature",
  "properties": {
    "addr:full": "700 American Legion Hwy Roslindale MA 02131",
    "addr:housenumber": "700",
    "addr:postcode": "02131",
    "addr:street": "American Legion Hwy",
    "iso:country": "US",
    "sg:address": "700 American Legion Hwy",
    "sg:city": "Roslindale",
    "sg:classifiers": [
      {
        "category": "Wholesale",
        "subcategory": "Medical Equipment \u0026 Supplies",
        "type": "Manufacturing \u0026 Wholesale Goods"
      }
    ],
    "sg:phone": "+1 617 323 2439",
    "sg:postcode": "02131",
    "sg:province": "MA",
    "sg:tags": [
      "soundproofing"
    ],
    "wof:name": "Ats Electronics",
    "wof:placetype": "venue"
  },
  "geometry": {"coordinates":[-71.113417,42.283369],"type":"Point"}
}
