{
  "type": "Feature",
  "properties": {
    "iso:country":"US",
    "sg:address":"48 Essex St",
    "sg:city":"Lynnfield",
    "sg:classifiers":[
        {
            "category":"Professional",
            "subcategory":"Computer Services",
            "type":"Services"
        }
    ],
    "sg:phone":"+1 781 248 6734",
    "sg:postcode":"01940",
    "sg:province":"MA",
    "sg:tags":[
        "software",
        "programing",
        "custom"
    ],
    "wof:name":"Northern Light Custom Designs",
    "wof:placetype":"venue"
},
  "geometry": {"coordinates":[-71.042518,42.542161],"type":"Point"}
}