{
  "type": "Feature",
  "properties": {
    "iso:country":"US",
    "sg:address":"10 Schooner Rdg",
    "sg:city":"Marblehead",
    "sg:classifiers":[
        {
            "category":"Building & Trades",
            "subcategory":"Construction",
            "type":"Services"
        }
    ],
    "sg:phone":"+1 781 639 1677",
    "sg:postcode":"01945",
    "sg:province":"MA",
    "sg:tags":[
        "altering",
        "remodeling",
        "contractor"
    ],
    "wof:name":"Hudak Hm Remodeling",
    "wof:placetype":"venue"
},
  "geometry": {"coordinates":[-70.85784099999999,42.515018],"type":"Point"}
}