{
  "type": "Feature",
  "properties": {
    "addr:full": "10 Schooner Rdg Marblehead MA 01945",
    "addr:housenumber": "10",
    "addr:postcode": "01945",
    "addr:street": "Schooner Rdg",
    "iso:country": "US",
    "sg:address": "10 Schooner Rdg",
    "sg:city": "Marblehead",
    "sg:classifiers": [
      {
        "category": "Building \u0026 Trades",
        "subcategory": "Construction",
        "type": "Services"
      }
    ],
    "sg:phone": "+1 781 639 1677",
    "sg:postcode": "01945",
    "sg:province": "MA",
    "sg:tags": [
      "altering",
      "remodeling",
      "contractor"
    ],
    "wof:name": "Hudak Hm Remodeling",
    "wof:placetype": "venue"
  },
  "geometry": {"coordinates":[-70.857841,42.515018],"type":"Point"}
}
