{
  "type": "Feature",
  "properties": {
    "addr:full": "40 Center St Fairhaven MA 02719",
    "addr:housenumber": "40",
    "addr:postcode": "02719",
    "addr:street": "Center St",
    "iso:country": "US",
    "sg:address": "40 Center St",
    "sg:city": "Fairhaven",
    "sg:classifiers": [
      {
        "category": "Government",
        "subcategory": "Office",
        "type": "Public Place"
      }
    ],
    "sg:phone": "+1 508 979 4025",
    "sg:postcode": "02719",
    "sg:province": "MA",
    "sg:tags": [
      "village"
    ],
    "wof:name": "Fairhaven Town Registrars",
    "wof:placetype": "venue"
  },
  "geometry": {"coordinates":[-70.903371,41.636042],"type":"Point"}
}
