{
  "type": "Feature",
  "properties": {
    "iso:country":"US",
    "sg:address":"800 Boylston Street",
    "sg:city":"Boston",
    "sg:classifiers":[
        {
            "category":"Shopping Center",
            "type":"Public Place"
        }
    ],
    "sg:phone":"+1 617 236 3100",
    "sg:postcode":"02199",
    "sg:province":"MA",
    "sg:website":"www.prudentialcenter.com/",
    "wof:name":"The Shops At Prudential Center",
    "wof:placetype":"venue"
},
  "geometry": {"coordinates":[-71.082584,42.347793],"type":"Point"}
}