{
  "type": "Feature",
  "properties": {
    "iso:country":"US",
    "sg:address":"251 Mohawk Trl",
    "sg:city":"Greenfield",
    "sg:classifiers":[
        {
            "category":"Restaurant",
            "type":"Food & Drink"
        }
    ],
    "sg:phone":"+1 413 774 3636",
    "sg:postcode":"01301",
    "sg:province":"MA",
    "wof:name":"Subway Sandwiches & Salads",
    "wof:placetype":"venue"
},
  "geometry": {"coordinates":[-72.627465,42.586715],"type":"Point"}
}