{
  "type": "Feature",
  "properties": {
    "iso:country":"US",
    "sg:address":"411 Waverley Oak Rd",
    "sg:city":"Waltham",
    "sg:classifiers":[
        {
            "category":"Professional",
            "subcategory":"Management & Consulting",
            "type":"Services"
        }
    ],
    "sg:phone":"+1 781 906 6700",
    "sg:postcode":"02452",
    "sg:province":"MA",
    "sg:tags":[
        "consultant",
        "business"
    ],
    "wof:name":"International Quality Systems",
    "wof:placetype":"venue"
},
  "geometry": {"coordinates":[-71.201278,42.38786],"type":"Point"}
}