{
  "type": "Feature",
  "properties": {
    "addr:full": "20 Central Sq Chelmsford MA 01824",
    "addr:housenumber": "20",
    "addr:postcode": "01824",
    "addr:street": "Central Sq",
    "iso:country": "US",
    "sg:address": "20 Central Sq",
    "sg:city": "Chelmsford",
    "sg:classifiers": [
      {
        "category": "Shopping",
        "subcategory": "Used Merchandise",
        "type": "Retail Goods"
      }
    ],
    "sg:phone": "+1   ",
    "sg:postcode": "01824",
    "sg:province": "MA",
    "wof:name": "Antiques \u0026 Collectibles",
    "wof:placetype": "venue"
  },
  "geometry": {"coordinates":[-71.352018,42.596461],"type":"Point"}
}
