{
  "type": "Feature",
  "properties": {
    "addr:full":"790 Chief Justice Cushing Hwy Cohasset MA 02025",
    "addr:housenumber":"790",
    "addr:postcode":"02025",
    "addr:street":"Chief Justice Cushing Hwy",
    "iso:country":"US",
    "sg:address":"790 Chief Justice Cushing Hwy",
    "sg:city":"Cohasset",
    "sg:classifiers":[
        {
            "category":"Arena",
            "subcategory":"Sports Club",
            "type":"Entertainment"
        }
    ],
    "sg:phone":"+1 781 383 8004",
    "sg:postcode":"02025",
    "sg:province":"MA",
    "sg:tags":[
        "health"
    ],
    "wof:name":"Hypertone Personal Fitness",
    "wof:placetype":"venue"
},
  "geometry": {"coordinates":[-70.801113,42.220454],"type":"Point"}
}