{
  "type": "Feature",
  "properties": {
    "addr:full":"15 Savoy St Apt D308 Boston MA 02118",
    "addr:housenumber":"15",
    "addr:postcode":"02118",
    "addr:street":"Savoy St Apt D308",
    "iso:country":"US",
    "sg:address":"15 Savoy St Apt D308",
    "sg:city":"Boston",
    "sg:classifiers":[
        {
            "category":"Shopping",
            "subcategory":"Mobile Phones",
            "type":"Retail Goods"
        }
    ],
    "sg:phone":"+1 617 792 7463",
    "sg:postcode":"02118",
    "sg:province":"MA",
    "sg:website":"www.pompeiidesigngroup.com",
    "wof:name":"Pompeii Design Group Cellular",
    "wof:placetype":"venue"
},
  "geometry": {"coordinates":[-71.067864,42.341907],"type":"Point"}
}