{
  "type": "Feature",
  "properties": {
    "addr:full": "11 Wilbur St Norton MA 02766",
    "addr:housenumber": "11",
    "addr:postcode": "02766",
    "addr:street": "Wilbur St",
    "iso:country": "US",
    "sg:address": "11 Wilbur St",
    "sg:city": "Norton",
    "sg:classifiers": [
      {
        "category": "Professional",
        "subcategory": "Art Services",
        "type": "Services"
      }
    ],
    "sg:phone": "+1 508 285 2099",
    "sg:postcode": "02766",
    "sg:province": "MA",
    "sg:tags": [
      "designer",
      "display",
      "producer"
    ],
    "wof:name": "Anna Gallo Designs Inc",
    "wof:placetype": "venue"
  },
  "geometry": {"coordinates":[-71.165443,41.994049],"type":"Point"}
}
