{
  "type": "Feature",
  "properties": {
    "addr:full":"182 Newbury St Peabody MA 01960",
    "addr:housenumber":"182",
    "addr:postcode":"01960",
    "addr:street":"Newbury St",
    "iso:country":"US",
    "sg:address":"182 Newbury St",
    "sg:city":"Peabody",
    "sg:classifiers":[
        {
            "category":"Professional",
            "subcategory":"Management & Consulting",
            "type":"Services"
        }
    ],
    "sg:phone":"+1 978 777 5555",
    "sg:postcode":"01960",
    "sg:province":"MA",
    "sg:tags":[
        "consultant",
        "business"
    ],
    "wof:name":"Great North Property Mgmt",
    "wof:placetype":"venue"
},
  "geometry": {"coordinates":[-70.986738,42.541222],"type":"Point"}
}