{
  "type": "Feature",
  "properties": {
    "iso:country":"US",
    "sg:address":"14 Dartmouth St",
    "sg:city":"Malden",
    "sg:classifiers":[
        {
            "category":"Education",
            "subcategory":"Special Training",
            "type":"Public Place"
        }
    ],
    "sg:phone":"+1 617 257 3544",
    "sg:postcode":"02148",
    "sg:province":"MA",
    "sg:tags":[
        "tutoring"
    ],
    "sg:website":"www.excelsiorlearningcenter.com",
    "wof:name":"Excelsior Learning Center",
    "wof:placetype":"venue"
},
  "geometry": {"coordinates":[-71.068327,42.427081],"type":"Point"}
}