{
  "type": "Feature",
  "properties": {
    "iso:country":"US",
    "sg:address":"11 Roanoke Avenue",
    "sg:city":"Jamaica Plain",
    "sg:classifiers":[
        {
            "category":"Organizations",
            "subcategory":"Religious Organization",
            "type":"Services"
        }
    ],
    "sg:phone":"+1 617 524 2999",
    "sg:postcode":"02130",
    "sg:province":"MA",
    "wof:name":"St John's Episc Church",
    "wof:placetype":"venue"
},
  "geometry": {"coordinates":[-71.110534,42.31006],"type":"Point"}
}