{
  "type": "Feature",
  "properties": {
    "iso:country":"US",
    "sg:address":"1 Mystic View Rd",
    "sg:city":"Everett",
    "sg:classifiers":[
        {
            "category":"Retail",
            "subcategory":"Portrait Studio",
            "type":"Services"
        }
    ],
    "sg:phone":"+1 617 389 8407",
    "sg:postcode":"02149",
    "sg:province":"MA",
    "sg:tags":[
        "photographer"
    ],
    "wof:name":"Lifetouch",
    "wof:placetype":"venue"
},
  "geometry": {"coordinates":[-71.070013,42.401933],"type":"Point"}
}