{
  "type": "Feature",
  "properties": {
    "iso:country":"US",
    "sg:address":"28 Hill St",
    "sg:city":"Watertown",
    "sg:classifiers":[
        {
            "category":"Building & Trades",
            "subcategory":"Construction",
            "type":"Services"
        }
    ],
    "sg:phone":"+1 617 926 4838",
    "sg:postcode":"02472",
    "sg:province":"MA",
    "sg:tags":[
        "masonry",
        "contractor"
    ],
    "wof:name":"Deangelis & Sons",
    "wof:placetype":"venue"
},
  "geometry": {"coordinates":[-71.184729,42.371078],"type":"Point"}
}