{
  "type": "Feature",
  "properties": {
    "iso:country":"US",
    "sg:address":"41 Belvidere St",
    "sg:city":"Boston",
    "sg:classifiers":[
        {
            "category":"Organizations",
            "subcategory":"Religious Organization",
            "type":"Services"
        }
    ],
    "sg:phone":"+1 617 247 4927",
    "sg:postcode":"02115",
    "sg:province":"MA",
    "wof:name":"Ecclesia Ministries",
    "wof:placetype":"venue"
},
  "geometry": {"coordinates":[-71.085376,42.346036],"type":"Point"}
}