{
  "type": "Feature",
  "properties": {
    "addr:full":"19 Norfolk St Dorchester Ctr MA 02124",
    "addr:housenumber":"19",
    "addr:postcode":"02124",
    "addr:street":"Norfolk St",
    "iso:country":"US",
    "sg:address":"19 Norfolk St",
    "sg:city":"Dorchester Ctr",
    "sg:classifiers":[
        {
            "category":"Personal",
            "subcategory":"Barber",
            "type":"Services"
        }
    ],
    "sg:phone":"+1 617 287 8844",
    "sg:postcode":"02124",
    "sg:province":"MA",
    "wof:name":"Cut To Fit Barber Shop",
    "wof:placetype":"venue"
},
  "geometry": {"coordinates":[-71.07237499999999,42.290037],"type":"Point"}
}