{
  "type": "Feature",
  "properties": {
    "addr:full": "117 E Berkeley St Boston MA 02118",
    "addr:housenumber": "117",
    "addr:postcode": "02118",
    "addr:street": "E Berkeley St",
    "iso:country": "US",
    "sg:address": "117 E Berkeley St",
    "sg:city": "Boston",
    "sg:classifiers": [
      {
        "category": "Bars \u0026 Pubs",
        "type": "Food \u0026 Drink"
      },
      {
        "category": "Restaurant",
        "type": "Food \u0026 Drink"
      }
    ],
    "sg:phone": "+1 617 728 9101",
    "sg:postcode": "02118",
    "sg:province": "MA",
    "sg:tags": [
      "traditional",
      "new",
      "american"
    ],
    "sg:website": "www.jjfoleyscafe.com",
    "wof:name": "J. J. Foley's",
    "wof:placetype": "venue"
  },
  "geometry": {"coordinates":[-71.065645,42.343859],"type":"Point"}
}
