{
  "type": "Feature",
  "properties": {
    "iso:country":"US",
    "sg:address":"117 E Berkeley St",
    "sg:city":"Boston",
    "sg:classifiers":[
        {
            "category":"Bars & Pubs",
            "type":"Food & Drink"
        },
        {
            "category":"Restaurant",
            "type":"Food & Drink"
        }
    ],
    "sg:phone":"+1 617 728 9101",
    "sg:postcode":"02118",
    "sg:province":"MA",
    "sg:tags":[
        "traditional",
        "new",
        "american"
    ],
    "sg:website":"www.jjfoleyscafe.com",
    "wof:name":"J. J. Foley's",
    "wof:placetype":"venue"
},
  "geometry": {"coordinates":[-71.065645,42.343859],"type":"Point"}
}