{
  "type": "Feature",
  "properties": {
    "iso:country":"US",
    "sg:address":"27 Andrew's Way",
    "sg:city":"Plymouth",
    "sg:classifiers":[
        {
            "category":"Building & Trades",
            "subcategory":"Equipment Rental",
            "type":"Services"
        }
    ],
    "sg:phone":"+1 508 224 1884",
    "sg:postcode":"02360",
    "sg:province":"MA",
    "sg:tags":[
        "television"
    ],
    "wof:name":"Telerent Leasing Corp",
    "wof:placetype":"venue"
},
  "geometry": {"coordinates":[-70.55431299999999,41.894645],"type":"Point"}
}