{
  "type": "Feature",
  "properties": {
    "addr:full": "364 N Plain Rd Housatonic MA 01236",
    "addr:housenumber": "364",
    "addr:postcode": "01236",
    "addr:street": "N Plain Rd",
    "iso:country": "US",
    "sg:address": "364 N Plain Rd",
    "sg:city": "Housatonic",
    "sg:classifiers": [
      {
        "category": "Building \u0026 Trades",
        "subcategory": "Plumbing",
        "type": "Services"
      }
    ],
    "sg:phone": "+1   ",
    "sg:postcode": "01236",
    "sg:province": "MA",
    "sg:tags": [
      "contractor"
    ],
    "wof:name": "Brazie \u0026 Son Heating",
    "wof:placetype": "venue"
  },
  "geometry": {"coordinates":[-73.374887,42.250908],"type":"Point"}
}
