{
  "type": "Feature",
  "properties": {
    "addr:full":"156 Dixon Rd Brockton MA 02302",
    "addr:housenumber":"156",
    "addr:postcode":"02302",
    "addr:street":"Dixon Rd",
    "iso:country":"US",
    "sg:address":"156 Dixon Rd",
    "sg:city":"Brockton",
    "sg:classifiers":[
        {
            "category":"Professional",
            "subcategory":"Accounting & Tax Preparation",
            "type":"Services"
        }
    ],
    "sg:phone":"+1 508 583 1353",
    "sg:postcode":"02302",
    "sg:province":"MA",
    "sg:tags":[
        "return"
    ],
    "wof:name":"Brockton Business & Tax Svc",
    "wof:placetype":"venue"
},
  "geometry": {"coordinates":[-70.995059,42.105228],"type":"Point"}
}