{
  "type": "Feature",
  "properties": {
    "iso:country":"US",
    "sg:address":"311 Arsenal St",
    "sg:city":"Watertown",
    "sg:classifiers":[
        {
            "category":"Professional",
            "subcategory":"Computer Services",
            "type":"Services"
        }
    ],
    "sg:phone":"+1 617 926 0504",
    "sg:postcode":"02472",
    "sg:province":"MA",
    "sg:tags":[
        "consultant",
        "designer"
    ],
    "sg:website":"www.examanager.com",
    "wof:name":"Liaison International Inc",
    "wof:placetype":"venue"
},
  "geometry": {"coordinates":[-71.17012699999999,42.364066],"type":"Point"}
}