{
  "type": "Feature",
  "properties": {
    "iso:country":"US",
    "sg:address":"274 Main St",
    "sg:city":"Wareham",
    "sg:classifiers":[
        {
            "category":"Retail",
            "subcategory":"Laundry & Dry Cleaning",
            "type":"Services"
        }
    ],
    "sg:phone":"+1 508 295 0053",
    "sg:postcode":"02571",
    "sg:province":"MA",
    "sg:tags":[
        "cleaners"
    ],
    "wof:name":"Town & Country Cleaners",
    "wof:placetype":"venue"
},
  "geometry": {"coordinates":[-70.717421,41.759644],"type":"Point"}
}