{
  "type": "Feature",
  "properties": {
    "iso:country":"US",
    "sg:address":"284 Myrtle St",
    "sg:city":"New Bedford",
    "sg:classifiers":[
        {
            "category":"Retail",
            "subcategory":"Auto Repair",
            "type":"Services"
        }
    ],
    "sg:phone":"+1 508 997 7896",
    "sg:postcode":"02746",
    "sg:province":"MA",
    "sg:tags":[
        "truck"
    ],
    "wof:name":"Tremblay's Truck Ctr",
    "wof:placetype":"venue"
},
  "geometry": {"coordinates":[-70.93679400000001,41.657694],"type":"Point"}
}