{
  "type": "Feature",
  "properties": {
    "iso:country":"US",
    "sg:address":"9 Main St",
    "sg:city":"Peabody",
    "sg:classifiers":[
        {
            "category":"Health Services",
            "subcategory":"Health Practitioner",
            "type":"Services"
        }
    ],
    "sg:phone":"+1   ",
    "sg:postcode":"01960",
    "sg:province":"MA",
    "wof:name":"Anthony R Marino Dr",
    "wof:placetype":"venue"
},
  "geometry": {"coordinates":[-70.926755,42.525619],"type":"Point"}
}