{
  "type": "Feature",
  "properties": {
    "iso:country":"US",
    "sg:address":"156 Andover St",
    "sg:city":"North Andover",
    "sg:classifiers":[
        {
            "category":"Real Estate",
            "subcategory":"Real Estate Agent",
            "type":"Services"
        }
    ],
    "sg:phone":"+1 978 682 8835",
    "sg:postcode":"01845",
    "sg:province":"MA",
    "wof:name":"Harvest Of Homes",
    "wof:placetype":"venue"
},
  "geometry": {"coordinates":[-71.118381,42.680821],"type":"Point"}
}