{
  "type": "Feature",
  "properties": {
    "iso:country":"US",
    "sg:address":"124 Country Club Rd",
    "sg:city":"Dedham",
    "sg:classifiers":[
        {
            "category":"Organizations",
            "subcategory":"Community Association",
            "type":"Services"
        }
    ],
    "sg:phone":"+1 781 326 3090",
    "sg:postcode":"02026",
    "sg:province":"MA",
    "sg:tags":[
        "club"
    ],
    "wof:name":"Dedham Country & Polo Club",
    "wof:placetype":"venue"
},
  "geometry": {"coordinates":[-71.210438,42.247652],"type":"Point"}
}