{
  "type": "Feature",
  "properties": {
    "iso:country":"US",
    "sg:address":"31 Centennial Dr",
    "sg:city":"Norwood",
    "sg:classifiers":[
        {
            "category":"Professional",
            "type":"Services"
        }
    ],
    "sg:phone":"+1 781 769 2306",
    "sg:postcode":"02062",
    "sg:province":"MA",
    "sg:tags":[
        "establishment"
    ],
    "wof:name":"Nahatan Terrace Assoc",
    "wof:placetype":"venue"
},
  "geometry": {"coordinates":[-71.18780099999999,42.188703],"type":"Point"}
}