{
  "type": "Feature",
  "properties": {
    "iso:country":"US",
    "sg:address":"958 Turnpike St",
    "sg:city":"Canton",
    "sg:classifiers":[
        {
            "category":"Restaurant",
            "type":"Food & Drink"
        }
    ],
    "sg:phone":"+1 781 828 8231",
    "sg:postcode":"02021",
    "sg:province":"MA",
    "wof:name":"Turnpike Cafe",
    "wof:placetype":"venue"
},
  "geometry": {"coordinates":[-71.10610200000001,42.153599],"type":"Point"}
}