{
  "type": "Feature",
  "properties": {
    "addr:full": "63 Liberty St Plymouth MA 02360",
    "addr:housenumber": "63",
    "addr:postcode": "02360",
    "addr:street": "Liberty St",
    "iso:country": "US",
    "sg:address": "63 Liberty St",
    "sg:city": "Plymouth",
    "sg:classifiers": [
      {
        "category": "Retail",
        "subcategory": "Auto Repair",
        "type": "Services"
      }
    ],
    "sg:phone": "+1 508 746 4911",
    "sg:postcode": "02360",
    "sg:province": "MA",
    "sg:tags": [
      "body",
      "automobile",
      "painting"
    ],
    "wof:name": "Sears Auto Body",
    "wof:placetype": "venue"
  },
  "geometry": {"coordinates":[-70.691676,41.963675],"type":"Point"}
}
