{
  "type": "Feature",
  "properties": {
    "iso:country":"US",
    "sg:address":"430 School St",
    "sg:city":"Marshfield",
    "sg:classifiers":[
        {
            "category":"Building & Trades",
            "subcategory":"Electrical",
            "type":"Services"
        }
    ],
    "sg:phone":"+1 781 837 1075",
    "sg:postcode":"02050",
    "sg:province":"MA",
    "sg:tags":[
        "electric",
        "contractor"
    ],
    "wof:name":"Freed Electric",
    "wof:placetype":"venue"
},
  "geometry": {"coordinates":[-70.754637,42.1089],"type":"Point"}
}