{
  "type": "Feature",
  "properties": {
    "addr:full": "310 Franklin St Wrentham MA 02093",
    "addr:housenumber": "310",
    "addr:postcode": "02093",
    "addr:street": "Franklin St",
    "iso:country": "US",
    "sg:address": "310 Franklin St",
    "sg:city": "Wrentham",
    "sg:classifiers": [
      {
        "category": "Shopping",
        "subcategory": "Hobbies, Toys, \u0026 Games",
        "type": "Retail Goods"
      }
    ],
    "sg:phone": "+1 508 384 0847",
    "sg:postcode": "02093",
    "sg:province": "MA",
    "sg:tags": [
      "model",
      "supply"
    ],
    "wof:name": "My Dad's Trains",
    "wof:placetype": "venue"
  },
  "geometry": {"coordinates":[-71.34021,42.073989],"type":"Point"}
}
