{
  "type": "Feature",
  "properties": {
    "iso:country":"US",
    "sg:address":"156 Mountain View Rd",
    "sg:city":"East Longmeadow",
    "sg:classifiers":[
        {
            "category":"Building & Trades",
            "subcategory":"Construction",
            "type":"Services"
        }
    ],
    "sg:phone":"+1 413 525 2522",
    "sg:postcode":"01028",
    "sg:province":"MA",
    "sg:tags":[
        "house"
    ],
    "wof:name":"Goodchild Home Improvement",
    "wof:placetype":"venue"
},
  "geometry": {"coordinates":[-72.49619,42.070995],"type":"Point"}
}