{
  "type": "Feature",
  "properties": {
    "iso:country":"US",
    "sg:address":"40 Church St",
    "sg:city":"Boston",
    "sg:classifiers":[
        {
            "category":"Professional",
            "subcategory":"Employment Agencies",
            "type":"Services"
        }
    ],
    "sg:phone":"+1 617 423 3031",
    "sg:postcode":"02116",
    "sg:province":"MA",
    "sg:tags":[
        "modeling"
    ],
    "wof:name":"Copley Seven",
    "wof:placetype":"venue"
},
  "geometry": {"coordinates":[-71.06836800000001,42.349292],"type":"Point"}
}