{
  "type": "Feature",
  "properties": {
    "addr:full":"219 Winthrop St Taunton MA 02780",
    "addr:housenumber":"219",
    "addr:postcode":"02780",
    "addr:street":"Winthrop St",
    "iso:country":"US",
    "sg:address":"219 Winthrop St",
    "sg:city":"Taunton",
    "sg:classifiers":[
        {
            "category":"Social Services",
            "subcategory":"Job Training",
            "type":"Services"
        },
        {
            "category":"Professional",
            "subcategory":"Employment Agencies",
            "type":"Services"
        }
    ],
    "sg:phone":"+1 508 824 3663",
    "sg:postcode":"02780",
    "sg:province":"MA",
    "sg:tags":[
        "opportunity"
    ],
    "wof:name":"Eap Network Inc",
    "wof:placetype":"venue"
},
  "geometry": {"coordinates":[-71.111453,41.891191],"type":"Point"}
}