{
  "type": "Feature",
  "properties": {
    "iso:country":"US",
    "sg:address":"398 Essex St",
    "sg:city":"Beverly",
    "sg:classifiers":[
        {
            "category":"Sports & Exercise",
            "subcategory":"Golf",
            "type":"Entertainment"
        }
    ],
    "sg:phone":"+1 978 921 7878",
    "sg:postcode":"01915",
    "sg:province":"MA",
    "sg:tags":[
        "course"
    ],
    "wof:name":"All Access Sports",
    "wof:placetype":"venue"
},
  "geometry": {"coordinates":[-70.85617499999999,42.572996],"type":"Point"}
}