{
  "type": "Feature",
  "properties": {
    "addr:full":"106 High St Turners Falls MA 01376",
    "addr:housenumber":"106",
    "addr:postcode":"01376",
    "addr:street":"High St",
    "iso:country":"US",
    "sg:address":"106 High St",
    "sg:city":"Turners Falls",
    "sg:classifiers":[
        {
            "category":"Food & Beverages",
            "subcategory":"Groceries & Convenience Stores",
            "type":"Retail Goods"
        }
    ],
    "sg:phone":"+1 413 863 9634",
    "sg:postcode":"01376",
    "sg:province":"MA",
    "wof:name":"Scotty's Convenience Store",
    "wof:placetype":"venue"
},
  "geometry": {"coordinates":[-72.55179099999999,42.600348],"type":"Point"}
}