{
  "type": "Feature",
  "properties": {
    "addr:full": "106 High St Turners Falls MA 01376",
    "addr:housenumber": "106",
    "addr:postcode": "01376",
    "addr:street": "High St",
    "iso:country": "US",
    "sg:address": "106 High St",
    "sg:city": "Turners Falls",
    "sg:classifiers": [
      {
        "category": "Food \u0026 Beverages",
        "subcategory": "Groceries \u0026 Convenience Stores",
        "type": "Retail Goods"
      }
    ],
    "sg:phone": "+1 413 863 9634",
    "sg:postcode": "01376",
    "sg:province": "MA",
    "wof:name": "Scotty's Convenience Store",
    "wof:placetype": "venue"
  },
  "geometry": {"coordinates":[-72.551791,42.600348],"type":"Point"}
}
