{
  "type": "Feature",
  "properties": {
    "iso:country":"US",
    "sg:address":"413 Bowdoin St",
    "sg:city":"Dorchester",
    "sg:classifiers":[
        {
            "category":"Building & Trades",
            "subcategory":"Electrical",
            "type":"Services"
        }
    ],
    "sg:phone":"+1 617 825 2525",
    "sg:postcode":"02122",
    "sg:province":"MA",
    "sg:tags":[
        "electric",
        "contractor"
    ],
    "wof:name":"Joseph L Mc Keen Inc",
    "wof:placetype":"venue"
},
  "geometry": {"coordinates":[-71.06237299999999,42.31034],"type":"Point"}
}