{
  "type": "Feature",
  "properties": {
    "addr:full": "413 Bowdoin St Dorchester MA 02122",
    "addr:housenumber": "413",
    "addr:postcode": "02122",
    "addr:street": "Bowdoin St",
    "iso:country": "US",
    "sg:address": "413 Bowdoin St",
    "sg:city": "Dorchester",
    "sg:classifiers": [
      {
        "category": "Building \u0026 Trades",
        "subcategory": "Electrical",
        "type": "Services"
      }
    ],
    "sg:phone": "+1 617 825 2525",
    "sg:postcode": "02122",
    "sg:province": "MA",
    "sg:tags": [
      "electric",
      "contractor"
    ],
    "wof:name": "Joseph L Mc Keen Inc",
    "wof:placetype": "venue"
  },
  "geometry": {"coordinates":[-71.062373,42.31034],"type":"Point"}
}
