{
  "type": "Feature",
  "properties": {
    "addr:full": "191 Ward Hill Ave Haverhill MA 01835",
    "addr:housenumber": "191",
    "addr:postcode": "01835",
    "addr:street": "Ward Hill Ave",
    "iso:country": "US",
    "sg:address": "191 Ward Hill Ave",
    "sg:city": "Haverhill",
    "sg:classifiers": [
      {
        "category": "Wholesale",
        "subcategory": "Medical Equipment \u0026 Supplies",
        "type": "Manufacturing \u0026 Wholesale Goods"
      }
    ],
    "sg:phone": "+1 978 373 3589",
    "sg:postcode": "01835",
    "sg:province": "MA",
    "sg:tags": [
      "physician",
      "surgeon"
    ],
    "sg:website": "www.conwayassociates.com",
    "wof:name": "SCBA Inc",
    "wof:placetype": "venue"
  },
  "geometry": {"coordinates":[-71.117286,42.76125],"type":"Point"}
}
