{
  "type": "Feature",
  "properties": {
    "iso:country":"US",
    "sg:address":"191 Ward Hill Ave",
    "sg:city":"Haverhill",
    "sg:classifiers":[
        {
            "category":"Wholesale",
            "subcategory":"Medical Equipment & Supplies",
            "type":"Manufacturing & Wholesale Goods"
        }
    ],
    "sg:phone":"+1 978 373 3589",
    "sg:postcode":"01835",
    "sg:province":"MA",
    "sg:tags":[
        "physician",
        "surgeon"
    ],
    "sg:website":"www.conwayassociates.com",
    "wof:name":"SCBA Inc",
    "wof:placetype":"venue"
},
  "geometry": {"coordinates":[-71.11728599999999,42.76125],"type":"Point"}
}