{
  "type": "Feature",
  "properties": {
    "iso:country":"US",
    "sg:address":"535 Lowell St",
    "sg:city":"Peabody",
    "sg:classifiers":[
        {
            "category":"Restaurant",
            "type":"Food & Drink"
        }
    ],
    "sg:phone":"+1 978 535 8355",
    "sg:postcode":"01960",
    "sg:province":"MA",
    "sg:tags":[
        "pizza"
    ],
    "wof:name":"Bonkers Fun House Pizza",
    "wof:placetype":"venue"
},
  "geometry": {"coordinates":[-70.98195800000001,42.546625],"type":"Point"}
}