{
  "type": "Feature",
  "properties": {
    "iso:country":"US",
    "sg:address":"7 Main St",
    "sg:city":"Whitinsville",
    "sg:classifiers":[
        {
            "category":"Professional",
            "subcategory":"Business Services",
            "type":"Services"
        }
    ],
    "sg:phone":"+1   ",
    "sg:postcode":"01588",
    "sg:province":"MA",
    "sg:tags":[
        "building",
        "inspector"
    ],
    "wof:name":"Northbridge Building Dept",
    "wof:placetype":"venue"
},
  "geometry": {"coordinates":[-71.671815,42.110814],"type":"Point"}
}