{
  "type": "Feature",
  "properties": {
    "addr:full": "40 Fay St Boston MA 02118",
    "addr:housenumber": "40",
    "addr:postcode": "02118",
    "addr:street": "Fay St",
    "iso:country": "US",
    "sg:address": "40 Fay St",
    "sg:city": "Boston",
    "sg:classifiers": [
      {
        "category": "Building \u0026 Trades",
        "subcategory": "Locksmith",
        "type": "Services"
      }
    ],
    "sg:phone": "+1 617 531 1123",
    "sg:postcode": "02118",
    "sg:province": "MA",
    "sg:tags": [
      "key"
    ],
    "wof:name": "Fays Street 24 Hr Locksmith",
    "wof:placetype": "venue"
  },
  "geometry": {"coordinates":[-71.065336,42.343455],"type":"Point"}
}
