{
  "type": "Feature",
  "properties": {
    "iso:country":"US",
    "sg:address":"24 Winston Rd",
    "sg:city":"Dorchester Ctr",
    "sg:classifiers":[
        {
            "category":"Professional",
            "subcategory":"Management & Consulting",
            "type":"Services"
        }
    ],
    "sg:phone":"+1 617 367 4776",
    "sg:postcode":"02124",
    "sg:province":"MA",
    "sg:tags":[
        "consultant"
    ],
    "wof:name":"Logan Communications Intl Inc",
    "wof:placetype":"venue"
},
  "geometry": {"coordinates":[-71.08917,42.284445],"type":"Point"}
}