{
  "type": "Feature",
  "properties": {
    "addr:full": "64 Charme Rd Billerica MA 01821",
    "addr:housenumber": "64",
    "addr:postcode": "01821",
    "addr:street": "Charme Rd",
    "iso:country": "US",
    "sg:address": "64 Charme Rd",
    "sg:city": "Billerica",
    "sg:classifiers": [
      {
        "category": "Retail",
        "subcategory": "Repair Shop",
        "type": "Services"
      }
    ],
    "sg:phone": "+1 781 933 7272",
    "sg:postcode": "01821",
    "sg:province": "MA",
    "sg:tags": [
      "tool",
      "parts"
    ],
    "wof:name": "Red's Tool Repair Inc",
    "wof:placetype": "venue"
  },
  "geometry": {"coordinates":[-71.218781,42.571568],"type":"Point"}
}
