{
  "type": "Feature",
  "properties": {
    "iso:country":"US",
    "sg:address":"37 Main St",
    "sg:city":"Pepperell",
    "sg:classifiers":[
        {
            "category":"Retail",
            "subcategory":"Funeral Services",
            "type":"Services"
        }
    ],
    "sg:phone":"+1 978 433 2100",
    "sg:postcode":"01463",
    "sg:province":"MA",
    "sg:tags":[
        "director"
    ],
    "wof:name":"Hamilton Funeral Home",
    "wof:placetype":"venue"
},
  "geometry": {"coordinates":[-71.58930599999999,42.666397],"type":"Point"}
}