{
  "type": "Feature",
  "properties": {
    "addr:full": "53 Wyllis Ave Malden MA 02148",
    "addr:housenumber": "53",
    "addr:postcode": "02148",
    "addr:street": "Wyllis Ave",
    "iso:country": "US",
    "sg:address": "53 Wyllis Ave",
    "sg:city": "Malden",
    "sg:classifiers": [
      {
        "category": "Education",
        "subcategory": "Music School",
        "type": "Public Place"
      }
    ],
    "sg:phone": "+1 781 388 1960",
    "sg:postcode": "02148",
    "sg:province": "MA",
    "wof:name": "Touch Of Soul Productions",
    "wof:placetype": "venue"
  },
  "geometry": {"coordinates":[-71.066986,42.415102],"type":"Point"}
}
