{
  "type": "Feature",
  "properties": {
    "addr:full": "4 Cranberry Ln Chelmsford MA 01824",
    "addr:housenumber": "4",
    "addr:postcode": "01824",
    "addr:street": "Cranberry Ln",
    "iso:country": "US",
    "sg:address": "4 Cranberry Ln",
    "sg:city": "Chelmsford",
    "sg:classifiers": [
      {
        "category": "Shopping",
        "subcategory": "Florist",
        "type": "Retail Goods"
      }
    ],
    "sg:phone": "+1 978 256 8688",
    "sg:postcode": "01824",
    "sg:province": "MA",
    "wof:name": "Flowers By Joann",
    "wof:placetype": "venue"
  },
  "geometry": {"coordinates":[-71.368068,42.564901],"type":"Point"}
}
