{
  "type": "Feature",
  "properties": {
    "iso:country":"US",
    "sg:address":"4 Cranberry Ln",
    "sg:city":"Chelmsford",
    "sg:classifiers":[
        {
            "category":"Shopping",
            "subcategory":"Florist",
            "type":"Retail Goods"
        }
    ],
    "sg:phone":"+1 978 256 8688",
    "sg:postcode":"01824",
    "sg:province":"MA",
    "wof:name":"Flowers By Joann",
    "wof:placetype":"venue"
},
  "geometry": {"coordinates":[-71.36806799999999,42.564901],"type":"Point"}
}