{
  "type": "Feature",
  "properties": {
    "addr:full": "1 Independence Ave Quincy MA 02169",
    "addr:housenumber": "1",
    "addr:postcode": "02169",
    "addr:street": "Independence Ave",
    "iso:country": "US",
    "ovtr:label": "Sweeney Brothers Home for Funerals, Inc., 1 Independence Ave Quincy MA US",
    "ovtr:similarity": 3.597311019897461,
    "sg:address": "1 Independence Ave",
    "sg:city": "Quincy",
    "sg:classifiers": [
      {
        "category": "Retail",
        "subcategory": "Funeral Services",
        "type": "Services"
      }
    ],
    "sg:phone": "+1 617 472 6344",
    "sg:postcode": "02169",
    "sg:province": "MA",
    "sg:tags": [
      "director"
    ],
    "wof:name": "Sweeney Brothers Home-Funerals",
    "wof:placetype": "venue"
  },
  "geometry": {"coordinates":[-71.003959,42.23788],"type":"Point"}
}
