{
  "type": "Feature",
  "properties": {
    "iso:country":"US",
    "sg:address":"1 Independence Ave",
    "sg:city":"Quincy",
    "sg:classifiers":[
        {
            "category":"Retail",
            "subcategory":"Funeral Services",
            "type":"Services"
        }
    ],
    "sg:phone":"+1 617 472 6344",
    "sg:postcode":"02169",
    "sg:province":"MA",
    "sg:tags":[
        "director"
    ],
    "wof:name":"Sweeney Brothers Home-Funerals",
    "wof:placetype":"venue"
},
  "geometry": {"coordinates":[-71.00395899999999,42.23788],"type":"Point"}
}