{
  "type": "Feature",
  "properties": {
    "addr:full": "9 Broadway Beverly MA 01915",
    "addr:housenumber": "9",
    "addr:postcode": "01915",
    "addr:street": "Broadway",
    "iso:country": "US",
    "sg:address": "9 Broadway",
    "sg:city": "Beverly",
    "sg:classifiers": [
      {
        "category": "Health Services",
        "subcategory": "Doctor",
        "type": "Services"
      },
      {
        "category": "Health Services",
        "subcategory": "Dentist",
        "type": "Services"
      }
    ],
    "sg:phone": "+1 978 922 0778",
    "sg:postcode": "01915",
    "sg:province": "MA",
    "sg:tags": [
      "dentists-oral",
      "physician",
      "maxillofacial",
      "surgeons",
      "surgery",
      "oral"
    ],
    "wof:name": "Eli Davidyan Dmd Pc",
    "wof:placetype": "venue"
  },
  "geometry": {"coordinates":[-70.879758,42.547715],"type":"Point"}
}
