{
  "type": "Feature",
  "properties": {
    "addr:full": "28 Fales St Franklin MA 02038",
    "addr:housenumber": "28",
    "addr:postcode": "02038",
    "addr:street": "Fales St",
    "iso:country": "US",
    "sg:address": "28 Fales St",
    "sg:city": "Franklin",
    "sg:classifiers": [
      {
        "category": "Manufacturing",
        "subcategory": "Buildings",
        "type": "Manufacturing \u0026 Wholesale Goods"
      },
      {
        "category": "Building \u0026 Trades",
        "subcategory": "Construction",
        "type": "Services"
      }
    ],
    "sg:phone": "+1 508 520 3114",
    "sg:postcode": "02038",
    "sg:province": "MA",
    "sg:tags": [
      "home",
      "builder",
      "contractor"
    ],
    "wof:name": "Construction Drilling",
    "wof:placetype": "venue"
  },
  "geometry": {"coordinates":[-71.394715,42.089508],"type":"Point"}
}
