{
  "type": "Feature",
  "properties": {
    "iso:country":"US",
    "sg:address":"28 Fales St",
    "sg:city":"Franklin",
    "sg:classifiers":[
        {
            "category":"Manufacturing",
            "subcategory":"Buildings",
            "type":"Manufacturing & Wholesale Goods"
        },
        {
            "category":"Building & Trades",
            "subcategory":"Construction",
            "type":"Services"
        }
    ],
    "sg:phone":"+1 508 520 3114",
    "sg:postcode":"02038",
    "sg:province":"MA",
    "sg:tags":[
        "home",
        "builder",
        "contractor"
    ],
    "wof:name":"Construction Drilling",
    "wof:placetype":"venue"
},
  "geometry": {"coordinates":[-71.39471500000001,42.089508],"type":"Point"}
}