{
  "type": "Feature",
  "properties": {
    "iso:country":"US",
    "sg:address":"4 Community Rd",
    "sg:city":"Marblehead",
    "sg:classifiers":[
        {
            "category":"Social Services",
            "type":"Services"
        }
    ],
    "sg:phone":"+1 781 631 8330",
    "sg:postcode":"01945",
    "sg:province":"MA",
    "sg:tags":[
        "organization",
        "welfare"
    ],
    "sg:website":"www.jccns.org",
    "wof:name":"Jewish Community Ctr",
    "wof:placetype":"venue"
},
  "geometry": {"coordinates":[-70.874893,42.485171],"type":"Point"}
}