{
  "type": "Feature",
  "properties": {
    "addr:full": "60 Main St Hatfield MA 01038",
    "addr:housenumber": "60",
    "addr:postcode": "01038",
    "addr:street": "Main St",
    "iso:country": "US",
    "sg:address": "60 Main St",
    "sg:city": "Hatfield",
    "sg:classifiers": [
      {
        "category": "Travel",
        "subcategory": "Travel Agent",
        "type": "Entertainment"
      }
    ],
    "sg:phone": "+1 413 247 7678",
    "sg:postcode": "01038",
    "sg:province": "MA",
    "sg:tags": [
      "tours",
      "promoter"
    ],
    "sg:website": "www.sportstravelandtours.com",
    "wof:name": "Sports Travel Inc",
    "wof:placetype": "venue"
  },
  "geometry": {"coordinates":[-72.596204,42.373245],"type":"Point"}
}
