{
  "type": "Feature",
  "properties": {
    "addr:full":"1 April Ln Pittsfield MA 01201",
    "addr:housenumber":"1",
    "addr:postcode":"01201",
    "addr:street":"April Ln",
    "iso:country":"US",
    "sg:address":"1 April Ln",
    "sg:city":"Pittsfield",
    "sg:classifiers":[
        {
            "category":"Real Estate",
            "subcategory":"Real Estate Operator",
            "type":"Services"
        }
    ],
    "sg:phone":"+1 413 447 9809",
    "sg:postcode":"01201",
    "sg:province":"MA",
    "sg:tags":[
        "apartment"
    ],
    "wof:name":"Dalton Apartments",
    "wof:placetype":"venue"
},
  "geometry": {"coordinates":[-73.19888400000001,42.436603],"type":"Point"}
}