{
  "type": "Feature",
  "properties": {
    "iso:country":"US",
    "sg:address":"30 Monument Sq",
    "sg:city":"Concord",
    "sg:classifiers":[
        {
            "category":"Professional",
            "subcategory":"Accounting & Tax Preparation",
            "type":"Services"
        }
    ],
    "sg:phone":"+1 978 369 1773",
    "sg:postcode":"01742",
    "sg:province":"MA",
    "sg:tags":[
        "accountant"
    ],
    "sg:website":"www.sherico.com",
    "wof:name":"Sheridan & Co",
    "wof:placetype":"venue"
},
  "geometry": {"coordinates":[-71.349115,42.461264],"type":"Point"}
}