{
  "type": "Feature",
  "properties": {
    "iso:country":"US",
    "sg:address":"36 N Bedford St",
    "sg:city":"East Bridgewater",
    "sg:classifiers":[
        {
            "category":"Personal",
            "type":"Services"
        },
        {
            "category":"Personal",
            "subcategory":"Beauty Salon",
            "type":"Services"
        }
    ],
    "sg:phone":"+1 508 350 0105",
    "sg:postcode":"02333",
    "sg:province":"MA",
    "sg:tags":[
        "shop",
        "electrolysis"
    ],
    "wof:name":"Maureen T Zuzevich",
    "wof:placetype":"venue"
},
  "geometry": {"coordinates":[-70.95831699999999,42.035025],"type":"Point"}
}