{
  "type": "Feature",
  "properties": {
    "addr:full": "1 Constitution Plaza Boston MA 02129",
    "addr:housenumber": "1",
    "addr:postcode": "02129",
    "addr:street": "Constitution Plaza",
    "iso:country": "US",
    "sg:address": "1 Constitution Plaza",
    "sg:city": "Boston",
    "sg:classifiers": [
      {
        "category": "Real Estate",
        "subcategory": "Real Estate Services",
        "type": "Services"
      }
    ],
    "sg:phone": "+1 781 350 5966",
    "sg:postcode": "02129",
    "sg:province": "MA",
    "sg:website": "www.JosephCampbellRealty.com",
    "wof:name": "Joseph Campbell Realty",
    "wof:placetype": "venue"
  },
  "geometry": {"coordinates":[-71.058506,42.372459],"type":"Point"}
}
