{
  "type": "Feature",
  "properties": {
    "addr:full":"2 Lincoln St Brookfield MA 01506",
    "addr:housenumber":"2",
    "addr:postcode":"01506",
    "addr:street":"Lincoln St",
    "iso:country":"US",
    "sg:address":"2 Lincoln St",
    "sg:city":"Brookfield",
    "sg:classifiers":[
        {
            "category":"Education",
            "subcategory":"Library",
            "type":"Public Place"
        }
    ],
    "sg:phone":"+1 508 867 6339",
    "sg:postcode":"01506",
    "sg:province":"MA",
    "sg:tags":[
        "government"
    ],
    "wof:name":"Merrick Public Library",
    "wof:placetype":"venue"
},
  "geometry": {"coordinates":[-72.102737,42.213581],"type":"Point"}
}