{
  "type": "Feature",
  "properties": {
    "iso:country":"US",
    "sg:address":"2380 Massachusetts Ave",
    "sg:city":"Cambridge",
    "sg:classifiers":[
        {
            "category":"Education",
            "subcategory":"Kindergarten",
            "type":"Public Place"
        }
    ],
    "sg:phone":"+1 617 661 2700",
    "sg:postcode":"02140",
    "sg:province":"MA",
    "sg:tags":[
        "school",
        "driving"
    ],
    "wof:name":"A D Auto School",
    "wof:placetype":"venue"
},
  "geometry": {"coordinates":[-71.129097,42.3923],"type":"Point"}
}