{
  "type": "Feature",
  "properties": {
    "iso:country":"US",
    "sg:address":"45 Perley Ave",
    "sg:city":"Peabody",
    "sg:classifiers":[
        {
            "category":"Building & Trades",
            "subcategory":"Construction",
            "type":"Services"
        }
    ],
    "sg:phone":"+1 978 535 6908",
    "sg:postcode":"01960",
    "sg:province":"MA",
    "sg:tags":[
        "general",
        "contractor"
    ],
    "wof:name":"Markham Roofing",
    "wof:placetype":"venue"
},
  "geometry": {"coordinates":[-71.027973,42.548078],"type":"Point"}
}