{
  "type": "Feature",
  "properties": {
    "addr:full": "178 Bennington St Boston MA 02128",
    "addr:housenumber": "178",
    "addr:postcode": "02128",
    "addr:street": "Bennington St",
    "iso:country": "US",
    "sg:address": "178 Bennington St",
    "sg:city": "Boston",
    "sg:classifiers": [
      {
        "category": "Food \u0026 Beverages",
        "subcategory": "Groceries \u0026 Convenience Stores",
        "type": "Retail Goods"
      }
    ],
    "sg:phone": "+1 617 568 1873",
    "sg:postcode": "02128",
    "sg:province": "MA",
    "wof:name": "Variedades Amy",
    "wof:placetype": "venue"
  },
  "geometry": {"coordinates":[-71.032528,42.377424],"type":"Point"}
}
