{
  "type": "Feature",
  "properties": {
    "addr:full":"5 Howe St Auburn MA 01501",
    "addr:housenumber":"5",
    "addr:postcode":"01501",
    "addr:street":"Howe St",
    "iso:country":"US",
    "sg:address":"5 Howe St",
    "sg:city":"Auburn",
    "sg:classifiers":[
        {
            "category":"Personal",
            "subcategory":"Beauty Salon",
            "type":"Services"
        }
    ],
    "sg:phone":"+1 508 832 8600",
    "sg:postcode":"01501",
    "sg:province":"MA",
    "sg:tags":[
        "treatment",
        "skin"
    ],
    "wof:name":"Skin Perfection Boutique",
    "wof:placetype":"venue"
},
  "geometry": {"coordinates":[-71.83917700000001,42.203816],"type":"Point"}
}