{
  "type": "Feature",
  "properties": {
    "addr:full":"14 Main Street Ext Plymouth MA 02360",
    "addr:housenumber":"14",
    "addr:postcode":"02360",
    "addr:street":"Main Street Ext",
    "iso:country":"US",
    "sg:address":"14 Main Street Ext",
    "sg:city":"Plymouth",
    "sg:classifiers":[
        {
            "category":"Shopping",
            "subcategory":"Clothing, Apparel, & Fashions",
            "type":"Retail Goods"
        },
        {
            "category":"Shopping",
            "subcategory":"Gifts & Souvenirs",
            "type":"Retail Goods"
        }
    ],
    "sg:phone":"+1 508 747 7482",
    "sg:postcode":"02360",
    "sg:province":"MA",
    "sg:tags":[
        "apparel",
        "shop",
        "women's"
    ],
    "wof:name":"Sweet Dreams",
    "wof:placetype":"venue"
},
  "geometry": {"coordinates":[-70.663788,41.955626],"type":"Point"}
}