{
  "type": "Feature",
  "properties": {
    "iso:country":"US",
    "sg:address":"22 Draper Rd",
    "sg:city":"Dover",
    "sg:classifiers":[
        {
            "category":"Health Services",
            "subcategory":"Doctor",
            "type":"Services"
        }
    ],
    "sg:phone":"+1 508 785 2972",
    "sg:postcode":"02030",
    "sg:province":"MA",
    "sg:tags":[
        "physician",
        "surgeon"
    ],
    "wof:name":"Dr N Song",
    "wof:placetype":"venue"
},
  "geometry": {"coordinates":[-71.26714800000001,42.207782],"type":"Point"}
}