{
  "type": "Feature",
  "properties": {
    "iso:country":"US",
    "sg:address":"56 Pulaski St",
    "sg:city":"Peabody",
    "sg:classifiers":[
        {
            "category":"Communications",
            "subcategory":"Film & Video Production",
            "type":"Services"
        }
    ],
    "sg:phone":"+1 978 977 0077",
    "sg:postcode":"01960",
    "sg:province":"MA",
    "sg:tags":[
        "consultant",
        "audio"
    ],
    "wof:name":"American Home Theater",
    "wof:placetype":"venue"
},
  "geometry": {"coordinates":[-70.921677,42.543057],"type":"Point"}
}