{
  "type": "Feature",
  "properties": {
    "iso:country":"US",
    "sg:address":"1130 Main Street",
    "sg:city":"Malden",
    "sg:classifiers":[
        {
            "category":"Animal Shelter",
            "type":"Public Place"
        },
        {
            "category":"Retail",
            "subcategory":"Veterinary Services",
            "type":"Services"
        },
        {
            "category":"Retail",
            "subcategory":"Pet Boarding",
            "type":"Services"
        }
    ],
    "sg:phone":"+1 781 321 1300",
    "sg:postcode":"02148",
    "sg:province":"MA",
    "sg:tags":[
        "sitting",
        "hospital",
        "specialty",
        "clinic",
        "veterinarian",
        "boarding/pet",
        "kennel"
    ],
    "sg:website":"http://www.pinebanksanimalhospital.com/",
    "wof:name":"Pine Banks Animal Hospital & Kennels",
    "wof:placetype":"venue"
},
  "geometry": {"coordinates":[-71.06756900000001,42.440475],"type":"Point"}
}