{
  "type": "Feature",
  "properties": {
    "addr:full": "1130 Main Street Malden MA 02148",
    "addr:housenumber": "1130",
    "addr:postcode": "02148",
    "addr:street": "Main Street",
    "iso:country": "US",
    "ovtr:label": "Pine Banks Animal Hospital, 1130 Main St Malden MA US",
    "ovtr:similarity": 3.945841073989868,
    "sg:address": "1130 Main Street",
    "sg:city": "Malden",
    "sg:classifiers": [
      {
        "category": "Animal Shelter",
        "type": "Public Place"
      },
      {
        "category": "Retail",
        "subcategory": "Veterinary Services",
        "type": "Services"
      },
      {
        "category": "Retail",
        "subcategory": "Pet Boarding",
        "type": "Services"
      }
    ],
    "sg:phone": "+1 781 321 1300",
    "sg:postcode": "02148",
    "sg:province": "MA",
    "sg:tags": [
      "sitting",
      "hospital",
      "specialty",
      "clinic",
      "veterinarian",
      "boarding/pet",
      "kennel"
    ],
    "sg:website": "http://www.pinebanksanimalhospital.com/",
    "wof:name": "Pine Banks Animal Hospital \u0026 Kennels",
    "wof:placetype": "venue"
  },
  "geometry": {"coordinates":[-71.067569,42.440475],"type":"Point"}
}
