{
  "type": "Feature",
  "properties": {
    "addr:full":"325 Chelsea St Everett MA 02149",
    "addr:housenumber":"325",
    "addr:postcode":"02149",
    "addr:street":"Chelsea St",
    "iso:country":"US",
    "sg:address":"325 Chelsea St",
    "sg:city":"Everett",
    "sg:classifiers":[
        {
            "category":"Autos & Motor Vehicles",
            "subcategory":"Automobile Sales",
            "type":"Retail Goods"
        }
    ],
    "sg:phone":"+1 617 389 9900",
    "sg:postcode":"02149",
    "sg:province":"MA",
    "sg:tags":[
        "car",
        "dealer"
    ],
    "wof:name":"Everett Auto Brokers",
    "wof:placetype":"venue"
},
  "geometry": {"coordinates":[-71.042277,42.402784],"type":"Point"}
}