{
  "type": "Feature",
  "properties": {
    "addr:full":"211 Temple St West Boylston MA 01583",
    "addr:housenumber":"211",
    "addr:postcode":"01583",
    "addr:street":"Temple St",
    "iso:country":"US",
    "sg:address":"211 Temple St",
    "sg:city":"West Boylston",
    "sg:classifiers":[
        {
            "category":"Government",
            "subcategory":"Office",
            "type":"Public Place"
        }
    ],
    "sg:phone":"+1 508 835 3607",
    "sg:postcode":"01583",
    "sg:province":"MA",
    "sg:tags":[
        "state"
    ],
    "wof:name":"Fisheries & Game Div",
    "wof:placetype":"venue"
},
  "geometry": {"coordinates":[-71.76530700000001,42.348321],"type":"Point"}
}