{
  "type": "Feature",
  "properties": {
    "addr:full":"740 Elm St Concord MA 01742",
    "addr:housenumber":"740",
    "addr:postcode":"01742",
    "addr:street":"Elm St",
    "iso:country":"US",
    "sg:address":"740 Elm St",
    "sg:city":"Concord",
    "sg:classifiers":[
        {
            "category":"Travel",
            "subcategory":"Hotels & Motels",
            "type":"Entertainment"
        }
    ],
    "sg:phone":"+1 978 369 6100",
    "sg:postcode":"01742",
    "sg:province":"MA",
    "wof:name":"Best Western At Historic Concord",
    "wof:placetype":"venue"
},
  "geometry": {"coordinates":[-71.381401,42.4631],"type":"Point"}
}