{
  "type": "Feature",
  "properties": {
    "addr:full":"139 Walter St Roslindale MA 02131",
    "addr:housenumber":"139",
    "addr:postcode":"02131",
    "addr:street":"Walter St",
    "iso:country":"US",
    "sg:address":"139 Walter St",
    "sg:city":"Roslindale",
    "sg:classifiers":[
        {
            "category":"Shopping",
            "subcategory":"Clothing, Apparel, & Fashions",
            "type":"Retail Goods"
        },
        {
            "category":"Shopping",
            "subcategory":"Crafts & Fabrics",
            "type":"Retail Goods"
        }
    ],
    "sg:phone":"+1 617 327 5981",
    "sg:postcode":"02131",
    "sg:province":"MA",
    "sg:tags":[
        "trim",
        "accessory",
        "costume",
        "fabrics"
    ],
    "wof:name":"Head Game",
    "wof:placetype":"venue"
},
  "geometry": {"coordinates":[-71.13046799999999,42.292934],"type":"Point"}
}