{
  "type": "Feature",
  "properties": {
    "addr:full": "123 Cambridge St Boston MA 02129",
    "addr:housenumber": "123",
    "addr:postcode": "02129",
    "addr:street": "Cambridge St",
    "iso:country": "US",
    "sg:address": "123 Cambridge St",
    "sg:city": "Boston",
    "sg:classifiers": [
      {
        "category": "Autos \u0026 Motor Vehicles",
        "subcategory": "Fuel \u0026 Gas Station",
        "type": "Retail Goods"
      }
    ],
    "sg:postcode": "02129",
    "sg:province": "MA",
    "wof:name": "Hess",
    "wof:placetype": "venue"
  },
  "geometry": {"coordinates":[-71.080475,42.382232],"type":"Point"}
}
