{
  "type": "Feature",
  "properties": {
    "addr:full":"911 East St Tewksbury MA 01876",
    "addr:housenumber":"911",
    "addr:postcode":"01876",
    "addr:street":"East St",
    "iso:country":"US",
    "sg:address":"911 East St",
    "sg:city":"Tewksbury",
    "sg:classifiers":[
        {
            "category":"Retail",
            "subcategory":"Auto Repair",
            "type":"Services"
        }
    ],
    "sg:phone":"+1 978 851 5005",
    "sg:postcode":"01876",
    "sg:province":"MA",
    "sg:tags":[
        "glass",
        "coating",
        "tinting"
    ],
    "wof:name":"Blackout Window Tinting",
    "wof:placetype":"venue"
},
  "geometry": {"coordinates":[-71.192494,42.619171],"type":"Point"}
}