{
  "type": "Feature",
  "properties": {
    "addr:full":"275 Cambridge St Boston MA 02114",
    "addr:housenumber":"275",
    "addr:postcode":"02114",
    "addr:street":"Cambridge St",
    "iso:country":"US",
    "sg:address":"275 Cambridge St",
    "sg:city":"Boston",
    "sg:classifiers":[
        {
            "category":"Health Services",
            "subcategory":"Doctor",
            "type":"Services"
        }
    ],
    "sg:phone":"+1 617 724 6750",
    "sg:postcode":"02114",
    "sg:province":"MA",
    "sg:tags":[
        "physician",
        "surgeon"
    ],
    "wof:name":"Cardiac Unit Assoc",
    "wof:placetype":"venue"
},
  "geometry": {"coordinates":[-71.068202,42.361272],"type":"Point"}
}