{
  "type": "Feature",
  "properties": {
    "addr:full": "15 New England Executive Park Burlington MA 01803",
    "addr:housenumber": "15",
    "addr:postcode": "01803",
    "addr:street": "New England Executive Park",
    "iso:country": "US",
    "sg:address": "15 New England Executive Park",
    "sg:city": "Burlington",
    "sg:classifiers": [
      {
        "category": "Professional",
        "subcategory": "Computer Services",
        "type": "Services"
      }
    ],
    "sg:phone": "+1 781 583 1503",
    "sg:postcode": "01803",
    "sg:province": "MA",
    "sg:tags": [
      "elearning",
      "education"
    ],
    "sg:website": "http://www.qstream.me",
    "wof:name": "Qstream",
    "wof:placetype": "venue"
  },
  "geometry": {"coordinates":[-71.211059,42.484888],"type":"Point"}
}
