{
  "type": "Feature",
  "properties": {
    "addr:full": "20 Church St Dover MA 02030",
    "addr:housenumber": "20",
    "addr:postcode": "02030",
    "addr:street": "Church St",
    "iso:country": "US",
    "sg:address": "20 Church St",
    "sg:city": "Dover",
    "sg:classifiers": [
      {
        "category": "Professional",
        "type": "Services"
      }
    ],
    "sg:phone": "+1   ",
    "sg:postcode": "02030",
    "sg:province": "MA",
    "wof:name": "Assoc Processor Service",
    "wof:placetype": "venue"
  },
  "geometry": {"coordinates":[-71.284579,42.250679],"type":"Point"}
}
