{
  "type": "Feature",
  "properties": {
    "iso:country":"US",
    "sg:address":"99 Huntoon Memorial Hwy",
    "sg:city":"Rochdale",
    "sg:classifiers":[
        {
            "category":"Professional",
            "type":"Services"
        },
        {
            "category":"Personal",
            "type":"Services"
        },
        {
            "category":"Structure",
            "subcategory":"Warehouse",
            "type":"Public Place"
        },
        {
            "category":"Retail",
            "subcategory":"Storage",
            "type":"Services"
        }
    ],
    "sg:phone":"+1 508 892 7241",
    "sg:postcode":"01542",
    "sg:province":"MA",
    "sg:tags":[
        "full",
        "warehouses-public-commercial",
        "household",
        "material",
        "commercial",
        "moving",
        "services-labor",
        "mover"
    ],
    "sg:website":"http://www.libertymovers.com",
    "wof:name":"Liberty Movers Inc Bekins Agent",
    "wof:placetype":"venue"
},
  "geometry": {"coordinates":[-71.90081000000001,42.202389],"type":"Point"}
}