{
  "type": "Feature",
  "properties": {
    "addr:full": "109 Highland St Amesbury MA 01913",
    "addr:housenumber": "109",
    "addr:postcode": "01913",
    "addr:street": "Highland St",
    "iso:country": "US",
    "sg:address": "109 Highland St",
    "sg:city": "Amesbury",
    "sg:classifiers": [
      {
        "category": "Professional",
        "subcategory": "Business Services",
        "type": "Services"
      }
    ],
    "sg:phone": "+1   ",
    "sg:postcode": "01913",
    "sg:province": "MA",
    "wof:name": "NDT Computer Solutions",
    "wof:placetype": "venue"
  },
  "geometry": {"coordinates":[-70.93455,42.848592],"type":"Point"}
}
