{
  "type": "Feature",
  "properties": {
    "addr:full":"142 Elm St Worcester MA 01609",
    "addr:housenumber":"142",
    "addr:postcode":"01609",
    "addr:street":"Elm St",
    "iso:country":"US",
    "sg:address":"142 Elm St",
    "sg:city":"Worcester",
    "sg:classifiers":[
        {
            "category":"Retail",
            "subcategory":"Animal Services",
            "type":"Services"
        }
    ],
    "sg:phone":"+1   ",
    "sg:postcode":"01609",
    "sg:province":"MA",
    "wof:name":"Pet-Serve Plus",
    "wof:placetype":"venue"
},
  "geometry": {"coordinates":[-71.816147,42.266055],"type":"Point"}
}