{
  "type": "Feature",
  "properties": {
    "iso:country":"US",
    "sg:address":"500 Brookline Ave Brigham & Women's Hospital",
    "sg:city":"Boston",
    "sg:classifiers":[
        {
            "category":"Health Services",
            "subcategory":"Doctor",
            "type":"Services"
        }
    ],
    "sg:phone":"+1 617 739 1153",
    "sg:postcode":"02130",
    "sg:province":"MA",
    "sg:tags":[
        "obstetrician",
        "gynecologist"
    ],
    "wof:name":"Amanda French, MD",
    "wof:placetype":"venue"
},
  "geometry": {"coordinates":[-71.10972599999999,42.336622],"type":"Point"}
}