{
  "type": "Feature",
  "properties": {
    "iso:country":"US",
    "sg:address":"315 New Boston St",
    "sg:city":"Woburn",
    "sg:classifiers":[
        {
            "category":"Ice Cream",
            "type":"Food & Drink"
        }
    ],
    "sg:phone":"+1 781 933 0611",
    "sg:postcode":"01801",
    "sg:province":"MA",
    "sg:tags":[
        "frozen",
        "yogurt"
    ],
    "wof:name":"Northeast Ice Cream - CLOSED",
    "wof:placetype":"venue"
},
  "geometry": {"coordinates":[-71.1465,42.519501],"type":"Point"}
}