{
  "type": "Feature",
  "properties": {
    "addr:full": "315 New Boston St Woburn MA 01801",
    "addr:housenumber": "315",
    "addr:postcode": "01801",
    "addr:street": "New Boston St",
    "iso:country": "US",
    "sg:address": "315 New Boston St",
    "sg:city": "Woburn",
    "sg:classifiers": [
      {
        "category": "Ice Cream",
        "type": "Food \u0026 Drink"
      }
    ],
    "sg:phone": "+1 781 933 0611",
    "sg:postcode": "01801",
    "sg:province": "MA",
    "sg:tags": [
      "frozen",
      "yogurt"
    ],
    "wof:name": "Northeast Ice Cream - CLOSED",
    "wof:placetype": "venue"
  },
  "geometry": {"coordinates":[-71.1465,42.519501],"type":"Point"}
}
