{
  "type": "Feature",
  "properties": {
    "iso:country":"US",
    "sg:address":"45 Commerce Way",
    "sg:city":"Woburn",
    "sg:classifiers":[
        {
            "category":"Shopping",
            "subcategory":"Computers & Home Electronics",
            "type":"Retail Goods"
        }
    ],
    "sg:phone":"+1 781 935 8238",
    "sg:postcode":"01801",
    "sg:province":"MA",
    "sg:tags":[
        "publishing"
    ],
    "sg:website":"www.jdpc.net",
    "wof:name":"Jonathan David Printing & Comm",
    "wof:placetype":"venue"
},
  "geometry": {"coordinates":[-71.131334,42.507113],"type":"Point"}
}