{
  "type": "Feature",
  "properties": {
    "addr:full": "45 Commerce Way Woburn MA 01801",
    "addr:housenumber": "45",
    "addr:postcode": "01801",
    "addr:street": "Commerce Way",
    "iso:country": "US",
    "sg:address": "45 Commerce Way",
    "sg:city": "Woburn",
    "sg:classifiers": [
      {
        "category": "Shopping",
        "subcategory": "Computers \u0026 Home Electronics",
        "type": "Retail Goods"
      }
    ],
    "sg:phone": "+1 781 935 8238",
    "sg:postcode": "01801",
    "sg:province": "MA",
    "sg:tags": [
      "publishing"
    ],
    "sg:website": "www.jdpc.net",
    "wof:name": "Jonathan David Printing \u0026 Comm",
    "wof:placetype": "venue"
  },
  "geometry": {"coordinates":[-71.131334,42.507113],"type":"Point"}
}
