{
  "type": "Feature",
  "properties": {
    "iso:country":"US",
    "sg:address":"937 Iyannough Rd",
    "sg:city":"Hyannis",
    "sg:classifiers":[
        {
            "category":"Home & Garden",
            "subcategory":"Carpets & Floor Coverings",
            "type":"Retail Goods"
        }
    ],
    "sg:phone":"+1 508 771 8444",
    "sg:postcode":"02601",
    "sg:province":"MA",
    "sg:tags":[
        "rug"
    ],
    "wof:name":"Atlantic Carpet Inc",
    "wof:placetype":"venue"
},
  "geometry": {"coordinates":[-70.30054199999999,41.671017],"type":"Point"}
}