{
  "type": "Feature",
  "properties": {
    "addr:full": "937 Iyannough Rd Hyannis MA 02601",
    "addr:housenumber": "937",
    "addr:postcode": "02601",
    "addr:street": "Iyannough Rd",
    "iso:country": "US",
    "sg:address": "937 Iyannough Rd",
    "sg:city": "Hyannis",
    "sg:classifiers": [
      {
        "category": "Home \u0026 Garden",
        "subcategory": "Carpets \u0026 Floor Coverings",
        "type": "Retail Goods"
      }
    ],
    "sg:phone": "+1 508 771 8444",
    "sg:postcode": "02601",
    "sg:province": "MA",
    "sg:tags": [
      "rug"
    ],
    "wof:name": "Atlantic Carpet Inc",
    "wof:placetype": "venue"
  },
  "geometry": {"coordinates":[-70.300542,41.671017],"type":"Point"}
}
