{
  "type": "Feature",
  "properties": {
    "iso:country":"US",
    "sg:address":"16 Potter Rd",
    "sg:city":"Charlemont",
    "sg:classifiers":[
        {
            "category":"Wholesale",
            "subcategory":"Metals & Minerals",
            "type":"Manufacturing & Wholesale Goods"
        }
    ],
    "sg:phone":"+1 413 339 4400",
    "sg:postcode":"01339",
    "sg:province":"MA",
    "sg:tags":[
        "steel",
        "warehouse"
    ],
    "wof:name":"Stainless Source New England",
    "wof:placetype":"venue"
},
  "geometry": {"coordinates":[-72.89331799999999,42.648928],"type":"Point"}
}