{
  "type": "Feature",
  "properties": {
    "addr:full": "1000 Main St Hanson MA 02341",
    "addr:housenumber": "1000",
    "addr:postcode": "02341",
    "addr:street": "Main St",
    "iso:country": "US",
    "sg:address": "1000 Main St",
    "sg:city": "Hanson",
    "sg:classifiers": [
      {
        "category": "Professional",
        "subcategory": "Business Services",
        "type": "Services"
      }
    ],
    "sg:phone": "+1 781 293 8601",
    "sg:postcode": "02341",
    "sg:province": "MA",
    "sg:tags": [
      "fund",
      "promotion",
      "raising"
    ],
    "wof:name": "TNT Promotional",
    "wof:placetype": "venue"
  },
  "geometry": {"coordinates":[-70.876693,42.042131],"type":"Point"}
}
