{
  "type": "Feature",
  "properties": {
    "addr:full":"2058 Dorchester Ave Boston MA 02124",
    "addr:housenumber":"2058",
    "addr:postcode":"02124",
    "addr:street":"Dorchester Ave",
    "iso:country":"US",
    "sg:address":"2058 Dorchester Ave",
    "sg:city":"Boston",
    "sg:classifiers":[
        {
            "category":"Building & Trades",
            "subcategory":"Construction",
            "type":"Services"
        }
    ],
    "sg:phone":"+1   ",
    "sg:postcode":"02124",
    "sg:province":"MA",
    "sg:tags":[
        "contractor"
    ],
    "wof:name":"Ledang Gr Contracting",
    "wof:placetype":"venue"
},
  "geometry": {"coordinates":[-71.065794,42.280165],"type":"Point"}
}