{
  "type": "Feature",
  "properties": {
    "addr:full":"1280 Belmont St Brockton MA 02301",
    "addr:housenumber":"1280",
    "addr:postcode":"02301",
    "addr:street":"Belmont St",
    "iso:country":"US",
    "sg:address":"1280 Belmont St",
    "sg:city":"Brockton",
    "sg:classifiers":[
        {
            "category":"Banks & Credit Unions",
            "subcategory":"Bank",
            "type":"Services"
        }
    ],
    "sg:phone":"+1 508 586 8010",
    "sg:postcode":"02301",
    "sg:province":"MA",
    "sg:tags":[
        "financing"
    ],
    "wof:name":"Citi Financial",
    "wof:placetype":"venue"
},
  "geometry": {"coordinates":[-71.067638,42.058915],"type":"Point"}
}