{
  "type": "Feature",
  "properties": {
    "iso:country":"US",
    "sg:address":"84 Water Tower Pl",
    "sg:city":"Leominster",
    "sg:classifiers":[
        {
            "category":"Shopping",
            "subcategory":"Department Store",
            "type":"Retail Goods"
        }
    ],
    "sg:phone":"+1 978 466 9188",
    "sg:postcode":"01453",
    "sg:province":"MA",
    "wof:name":"First Us Dollar",
    "wof:placetype":"venue"
},
  "geometry": {"coordinates":[-71.770145,42.556537],"type":"Point"}
}