{
  "type": "Feature",
  "properties": {
    "iso:country":"US",
    "sg:address":"10 Lincoln St",
    "sg:city":"Medway",
    "sg:classifiers":[
        {
            "category":"Local Transit",
            "type":"Transportation"
        }
    ],
    "sg:phone":"+1 508 879 8970",
    "sg:postcode":"02053",
    "sg:province":"MA",
    "sg:tags":[
        "limousine"
    ],
    "sg:website":"www.lelimo.com",
    "wof:name":"Le Limo",
    "wof:placetype":"venue"
},
  "geometry": {"coordinates":[-71.426524,42.141049],"type":"Point"}
}