{
  "type": "Feature",
  "properties": {
    "addr:full": "230 Cumberland Rd Lowell MA 01850",
    "addr:housenumber": "230",
    "addr:postcode": "01850",
    "addr:street": "Cumberland Rd",
    "iso:country": "US",
    "sg:address": "230 Cumberland Rd",
    "sg:city": "Lowell",
    "sg:classifiers": [
      {
        "category": "Retail",
        "subcategory": "Self-service Laundry",
        "type": "Services"
      }
    ],
    "sg:phone": "+1 978 458 8503",
    "sg:postcode": "01850",
    "sg:province": "MA",
    "wof:name": "Terry's Kids Laundromat",
    "wof:placetype": "venue"
  },
  "geometry": {"coordinates":[-71.311399,42.660065],"type":"Point"}
}
