{
  "type": "Feature",
  "properties": {
    "addr:full": "900 Salem Street Malden MA 02148",
    "addr:housenumber": "900",
    "addr:postcode": "02148",
    "addr:street": "Salem Street",
    "iso:country": "US",
    "sg:address": "900 Salem Street",
    "sg:city": "Malden",
    "sg:classifiers": [
      {
        "category": "Shopping",
        "subcategory": "Florist",
        "type": "Retail Goods"
      }
    ],
    "sg:phone": "+1 781 324 8800",
    "sg:postcode": "02148",
    "sg:province": "MA",
    "wof:name": "Salem Street Florists - CLOSED",
    "wof:placetype": "venue"
  },
  "geometry": {"coordinates":[-71.038646,42.434123],"type":"Point"}
}
