{
  "type": "Feature",
  "properties": {
    "addr:full": "550 Main St Indian Orchard MA 01151",
    "addr:housenumber": "550",
    "addr:postcode": "01151",
    "addr:street": "Main St",
    "iso:country": "US",
    "sg:address": "550 Main St",
    "sg:city": "Indian Orchard",
    "sg:classifiers": [
      {
        "category": "Farming",
        "subcategory": "Orchard",
        "type": "Manufacturing \u0026 Wholesale Goods"
      }
    ],
    "sg:phone": "+1 413 543 8865",
    "sg:postcode": "01151",
    "sg:province": "MA",
    "sg:tags": [
      "grove",
      "management"
    ],
    "wof:name": "Indian Orchard Mobil",
    "wof:placetype": "venue"
  },
  "geometry": {"coordinates":[-72.485381,42.155761],"type":"Point"}
}
