{
  "type": "Feature",
  "properties": {
    "addr:full":"520 Main St Vineyard Haven MA 02568",
    "addr:housenumber":"520",
    "addr:postcode":"02568",
    "addr:street":"Main St",
    "iso:country":"US",
    "sg:address":"520 Main St",
    "sg:city":"Vineyard Haven",
    "sg:classifiers":[
        {
            "category":"Wholesale",
            "subcategory":"Non-durable Goods",
            "type":"Manufacturing & Wholesale Goods"
        }
    ],
    "sg:phone":"+1 508 696 9038",
    "sg:postcode":"02568",
    "sg:province":"MA",
    "wof:name":"Golden Basket",
    "wof:placetype":"venue"
},
  "geometry": {"coordinates":[-70.59979,41.468729],"type":"Point"}
}