{
  "type": "Feature",
  "properties": {
    "addr:full":"131 Great Rd # A Bedford MA 01730",
    "addr:housenumber":"131",
    "addr:postcode":"01730",
    "addr:street":"Great Rd # A",
    "iso:country":"US",
    "sg:address":"131 Great Rd # A",
    "sg:city":"Bedford",
    "sg:classifiers":[
        {
            "category":"Arts & Performance",
            "subcategory":"Arts Center",
            "type":"Entertainment"
        }
    ],
    "sg:phone":"+1 781 275 2655",
    "sg:postcode":"01730",
    "sg:province":"MA",
    "sg:tags":[
        "performing"
    ],
    "wof:name":"Dancetime",
    "wof:placetype":"venue"
},
  "geometry": {"coordinates":[-71.27708800000001,42.491065],"type":"Point"}
}