{
  "type": "Feature",
  "properties": {
    "iso:country":"US",
    "sg:address":"346 Commercial St",
    "sg:city":"Provincetown",
    "sg:classifiers":[
        {
            "category":"Professional",
            "type":"Services"
        }
    ],
    "sg:phone":"+1 508 487 3942",
    "sg:postcode":"02657",
    "sg:province":"MA",
    "sg:tags":[
        "establishment"
    ],
    "wof:name":"Spank The Monkey",
    "wof:placetype":"venue"
},
  "geometry": {"coordinates":[-70.18434000000001,42.053118],"type":"Point"}
}