{
  "type": "Feature",
  "properties": {
    "addr:full":"283 Center St Holbrook MA 02343",
    "addr:housenumber":"283",
    "addr:postcode":"02343",
    "addr:street":"Center St",
    "iso:country":"US",
    "sg:address":"283 Center St",
    "sg:city":"Holbrook",
    "sg:classifiers":[
        {
            "category":"Building & Trades",
            "subcategory":"Electrical",
            "type":"Services"
        }
    ],
    "sg:phone":"+1 781 961 5555",
    "sg:postcode":"02343",
    "sg:province":"MA",
    "sg:tags":[
        "electric",
        "contractor"
    ],
    "wof:name":"Frisoli Electric Inc",
    "wof:placetype":"venue"
},
  "geometry": {"coordinates":[-71.023793,42.162975],"type":"Point"}
}