{
  "type": "Feature",
  "properties": {
    "addr:full": "1 City Hall Ave Boston MA 02108",
    "addr:housenumber": "1",
    "addr:postcode": "02108",
    "addr:street": "City Hall Ave",
    "iso:country": "US",
    "sg:address": "1 City Hall Ave",
    "sg:city": "Boston",
    "sg:classifiers": [
      {
        "category": "Government",
        "subcategory": "Office",
        "type": "Public Place"
      }
    ],
    "sg:phone": "+1 617 635 4600",
    "sg:postcode": "02108",
    "sg:province": "MA",
    "sg:tags": [
      "city"
    ],
    "wof:name": "Boston City Clerk",
    "wof:placetype": "venue"
  },
  "geometry": {"coordinates":[-71.059299,42.357766],"type":"Point"}
}
