{
  "type": "Feature",
  "properties": {
    "addr:full":"318 Main St Marshfield MA 02050",
    "addr:housenumber":"318",
    "addr:postcode":"02050",
    "addr:street":"Main St",
    "iso:country":"US",
    "sg:address":"318 Main St",
    "sg:city":"Marshfield",
    "sg:classifiers":[
        {
            "category":"Manufacturing",
            "subcategory":"Retail Goods",
            "type":"Manufacturing & Wholesale Goods"
        }
    ],
    "sg:phone":"+1   ",
    "sg:postcode":"02050",
    "sg:province":"MA",
    "sg:tags":[
        "carbon",
        "ribbon",
        "mfg"
    ],
    "wof:name":"Canston Cartridge Supplies",
    "wof:placetype":"venue"
},
  "geometry": {"coordinates":[-70.720037,42.103323],"type":"Point"}
}