{
  "type": "Feature",
  "properties": {
    "addr:full": "15 Ledgewood Pl Belmont MA 02478",
    "addr:housenumber": "15",
    "addr:postcode": "02478",
    "addr:street": "Ledgewood Pl",
    "iso:country": "US",
    "sg:address": "15 Ledgewood Pl",
    "sg:city": "Belmont",
    "sg:classifiers": [
      {
        "category": "Organizations",
        "subcategory": "Religious Organization",
        "type": "Services"
      }
    ],
    "sg:phone": "+1   ",
    "sg:postcode": "02478",
    "sg:province": "MA",
    "wof:name": "Morman The",
    "wof:placetype": "venue"
  },
  "geometry": {"coordinates":[-71.189371,42.413073],"type":"Point"}
}
