{
  "type": "Feature",
  "properties": {
    "addr:full":"1 Hill St Woburn MA 01801",
    "addr:housenumber":"1",
    "addr:postcode":"01801",
    "addr:street":"Hill St",
    "iso:country":"US",
    "sg:address":"1 Hill St",
    "sg:city":"Woburn",
    "sg:classifiers":[
        {
            "category":"Manufacturing",
            "subcategory":"Food",
            "type":"Manufacturing & Wholesale Goods"
        }
    ],
    "sg:phone":"+1 781 933 2800",
    "sg:postcode":"01801",
    "sg:province":"MA",
    "sg:tags":[
        "product",
        "manufacturer"
    ],
    "wof:name":"Kraft Foods",
    "wof:placetype":"venue"
},
  "geometry": {"coordinates":[-71.11787,42.479623],"type":"Point"}
}