{
  "type": "Feature",
  "properties": {
    "iso:country":"US",
    "sg:address":"115 Cummings Park",
    "sg:city":"Woburn",
    "sg:classifiers":[
        {
            "category":"Sports & Exercise",
            "subcategory":"Golf",
            "type":"Entertainment"
        }
    ],
    "sg:phone":"+1 781 933 6657",
    "sg:postcode":"01801",
    "sg:province":"MA",
    "sg:website":"www.ironwoodbattingcages.com",
    "wof:name":"Ironwood Golf and Batting Cages",
    "wof:placetype":"venue"
},
  "geometry": {"coordinates":[-71.12370300000001,42.4977],"type":"Point"}
}