{
  "type": "Feature",
  "properties": {
    "addr:full": "115 Cummings Park Woburn MA 01801",
    "addr:housenumber": "115",
    "addr:postcode": "01801",
    "addr:street": "Cummings Park",
    "iso:country": "US",
    "sg:address": "115 Cummings Park",
    "sg:city": "Woburn",
    "sg:classifiers": [
      {
        "category": "Sports \u0026 Exercise",
        "subcategory": "Golf",
        "type": "Entertainment"
      }
    ],
    "sg:phone": "+1 781 933 6657",
    "sg:postcode": "01801",
    "sg:province": "MA",
    "sg:website": "www.ironwoodbattingcages.com",
    "wof:name": "Ironwood Golf and Batting Cages",
    "wof:placetype": "venue"
  },
  "geometry": {"coordinates":[-71.123703,42.4977],"type":"Point"}
}
