{
  "type": "Feature",
  "properties": {
    "iso:country":"US",
    "sg:address":"2991 Cranberry Hwy",
    "sg:city":"East Wareham",
    "sg:classifiers":[
        {
            "category":"Autos & Motor Vehicles",
            "subcategory":"Auto Supplies",
            "type":"Retail Goods"
        }
    ],
    "sg:phone":"+1 508 295 5700",
    "sg:postcode":"02538",
    "sg:province":"MA",
    "sg:tags":[
        "automobile",
        "parts"
    ],
    "sg:website":"www.autozone.com",
    "wof:name":"Autozone",
    "wof:placetype":"venue"
},
  "geometry": {"coordinates":[-70.665031,41.759668],"type":"Point"}
}