{
  "type": "Feature",
  "properties": {
    "addr:full": "2991 Cranberry Hwy East Wareham MA 02538",
    "addr:housenumber": "2991",
    "addr:postcode": "02538",
    "addr:street": "Cranberry Hwy",
    "iso:country": "US",
    "ovtr:label": "AutoZone, 2991 Cranberry Hwy East Wareham MA US",
    "ovtr:similarity": 1.9870599508285522,
    "sg:address": "2991 Cranberry Hwy",
    "sg:city": "East Wareham",
    "sg:classifiers": [
      {
        "category": "Autos \u0026 Motor Vehicles",
        "subcategory": "Auto Supplies",
        "type": "Retail Goods"
      }
    ],
    "sg:phone": "+1 508 295 5700",
    "sg:postcode": "02538",
    "sg:province": "MA",
    "sg:tags": [
      "automobile",
      "parts"
    ],
    "sg:website": "www.autozone.com",
    "wof:name": "Autozone",
    "wof:placetype": "venue"
  },
  "geometry": {"coordinates":[-70.665031,41.759668],"type":"Point"}
}
