{
  "type": "Feature",
  "properties": {
    "addr:full": "49 riley road northborough MA 01532",
    "addr:housenumber": "49",
    "addr:postcode": "01532",
    "addr:street": "Riley Road",
    "iso:country": "US",
    "sg:address": "49 riley road",
    "sg:city": "northborough",
    "sg:classifiers": [
      {
        "category": "Professional",
        "subcategory": "Computer Services",
        "type": "Services"
      }
    ],
    "sg:phone": "+1 508 221 2311",
    "sg:postcode": "01532",
    "sg:province": "MA",
    "sg:tags": [
      "concerts",
      "music",
      "bands",
      "tickets",
      "mapping",
      "apis",
      "mashups"
    ],
    "sg:website": "http://tickets.gruvr.com",
    "wof:name": "Active Interactive",
    "wof:placetype": "venue"
  },
  "geometry": {"coordinates":[-71.646988,42.310878],"type":"Point"}
}
