{
  "type": "Feature",
  "properties": {
    "iso:country":"US",
    "sg:address":"240 Lewis Wharf",
    "sg:city":"Boston",
    "sg:classifiers":[
        {
            "category":"Banks & Credit Unions",
            "subcategory":"Atm",
            "type":"Services"
        }
    ],
    "sg:phone":"+1 617 723 3600",
    "sg:postcode":"02110",
    "sg:province":"MA",
    "sg:tags":[
        "bankruptcy"
    ],
    "wof:name":"Anderson Aquino Llp",
    "wof:placetype":"venue"
},
  "geometry": {"coordinates":[-71.050781,42.363493],"type":"Point"}
}