{
  "type": "Feature",
  "properties": {
    "addr:full": "39 N Main St Randolph MA 02368",
    "addr:housenumber": "39",
    "addr:postcode": "02368",
    "addr:street": "N Main St",
    "iso:country": "US",
    "ovtr:label": "Zorba's Pizza, 39 N Main St Randolph MA US",
    "ovtr:similarity": 2.1296238899230957,
    "sg:address": "39 N Main St",
    "sg:city": "Randolph",
    "sg:classifiers": [
      {
        "category": "Restaurant",
        "type": "Food \u0026 Drink"
      }
    ],
    "sg:phone": "+1 781 986 0120",
    "sg:postcode": "02368",
    "sg:province": "MA",
    "sg:tags": [
      "pizza"
    ],
    "wof:name": "Zorba's Pizza",
    "wof:placetype": "venue"
  },
  "geometry": {"coordinates":[-71.042198,42.163502],"type":"Point"}
}
