{
  "type": "Feature",
  "properties": {
    "addr:full":"15 Hane Rd Mashpee MA 02649",
    "addr:housenumber":"15",
    "addr:postcode":"02649",
    "addr:street":"Hane Rd",
    "iso:country":"US",
    "sg:address":"15 Hane Rd",
    "sg:city":"Mashpee",
    "sg:classifiers":[
        {
            "category":"Building & Trades",
            "subcategory":"Construction",
            "type":"Services"
        }
    ],
    "sg:phone":"+1 508 477 0310",
    "sg:postcode":"02649",
    "sg:province":"MA",
    "sg:tags":[
        "well",
        "drilling"
    ],
    "wof:name":"S J Di Maggio",
    "wof:placetype":"venue"
},
  "geometry": {"coordinates":[-70.489208,41.644187],"type":"Point"}
}