{
  "type": "Feature",
  "properties": {
    "addr:full":"622 Somerville Ave Somerville MA 02143",
    "addr:housenumber":"622",
    "addr:postcode":"02143",
    "addr:street":"Somerville Ave",
    "iso:country":"US",
    "sg:address":"622 Somerville Ave",
    "sg:city":"Somerville",
    "sg:classifiers":[
        {
            "category":"Wholesale",
            "subcategory":"Groceries",
            "type":"Manufacturing & Wholesale Goods"
        }
    ],
    "sg:phone":"+1 617 629 0157",
    "sg:postcode":"02143",
    "sg:province":"MA",
    "sg:tags":[
        "food",
        "product"
    ],
    "wof:name":"Essence Of India",
    "wof:placetype":"venue"
},
  "geometry": {"coordinates":[-71.11021599999999,42.383949],"type":"Point"}
}