{
  "type": "Feature",
  "properties": {
    "addr:full": "5 Clifton St Worcester MA 01610",
    "addr:housenumber": "5",
    "addr:postcode": "01610",
    "addr:street": "Clifton St",
    "iso:country": "US",
    "sg:address": "5 Clifton St",
    "sg:city": "Worcester",
    "sg:classifiers": [
      {
        "category": "Real Estate",
        "subcategory": "Real Estate Agent",
        "type": "Services"
      }
    ],
    "sg:phone": "+1 508 767 0304",
    "sg:postcode": "01610",
    "sg:province": "MA",
    "sg:tags": [
      "management"
    ],
    "wof:name": "New Creative Visions",
    "wof:placetype": "venue"
  },
  "geometry": {"coordinates":[-71.820925,42.254791],"type":"Point"}
}
