{
  "type": "Feature",
  "properties": {
    "iso:country":"US",
    "sg:address":"158 E Central St",
    "sg:city":"Natick",
    "sg:classifiers":[
        {
            "category":"Restaurant",
            "type":"Food & Drink"
        }
    ],
    "sg:phone":"+1 508 647 0200",
    "sg:postcode":"01760",
    "sg:province":"MA",
    "wof:name":"Central Street Grill",
    "wof:placetype":"venue"
},
  "geometry": {"coordinates":[-71.334045,42.287533],"type":"Point"}
}