{
  "type": "Feature",
  "properties": {
    "iso:country":"US",
    "sg:address":"515 E 2nd St",
    "sg:city":"Boston",
    "sg:classifiers":[
        {
            "category":"Shopping",
            "subcategory":"Pets & Pet Supplies",
            "type":"Retail Goods"
        },
        {
            "category":"Retail",
            "subcategory":"Pet Boarding",
            "type":"Services"
        }
    ],
    "sg:phone":"+1 617 464 1688",
    "sg:postcode":"02127",
    "sg:province":"MA",
    "sg:tags":[
        "boarding/pet",
        "store",
        "groomers",
        "sitting"
    ],
    "sg:website":"www.thepawstonian.com",
    "wof:name":"The Pawstonian",
    "wof:placetype":"venue"
},
  "geometry": {"coordinates":[-71.042749,42.337183],"type":"Point"}
}