{
  "type": "Feature",
  "properties": {
    "iso:country":"US",
    "sg:address":"110 Haverhill Rd",
    "sg:city":"Amesbury",
    "sg:classifiers":[
        {
            "category":"Professional",
            "subcategory":"Business Services",
            "type":"Services"
        }
    ],
    "sg:phone":"+1 978 388 8780",
    "sg:postcode":"01913",
    "sg:province":"MA",
    "sg:tags":[
        "recording",
        "studio"
    ],
    "wof:name":"Dark Horse Music",
    "wof:placetype":"venue"
},
  "geometry": {"coordinates":[-70.961073,42.843025],"type":"Point"}
}