{
  "type": "Feature",
  "properties": {
    "addr:full": "113B Davis St Revere MA 02151",
    "addr:housenumber": "113b",
    "addr:postcode": "02151",
    "addr:street": "Davis St",
    "iso:country": "US",
    "sg:address": "113B Davis St",
    "sg:city": "Revere",
    "sg:classifiers": [
      {
        "category": "Building \u0026 Trades",
        "subcategory": "Construction",
        "type": "Services"
      }
    ],
    "sg:phone": "+1 781 629 3202",
    "sg:postcode": "02151",
    "sg:province": "MA",
    "sg:tags": [
      "wallcoverings-installation",
      "wallpaper",
      "painting",
      "contractor"
    ],
    "wof:name": "C \u0026 L Painting",
    "wof:placetype": "venue"
  },
  "geometry": {"coordinates":[-71.010437,42.419476],"type":"Point"}
}
