{
  "type": "Feature",
  "properties": {
    "addr:full": "1575 Massachusetts Ave Cambridge MA 02138",
    "addr:housenumber": "1575",
    "addr:postcode": "02138",
    "addr:street": "Massachusetts Ave",
    "iso:country": "US",
    "sg:address": "1575 Massachusetts Ave",
    "sg:city": "Cambridge",
    "sg:classifiers": [
      {
        "category": "Professional",
        "subcategory": "Management \u0026 Consulting",
        "type": "Services"
      }
    ],
    "sg:phone": "+1 617 496 3341",
    "sg:postcode": "02138",
    "sg:province": "MA",
    "sg:tags": [
      "consultant",
      "business"
    ],
    "wof:name": "Adoption \u0026 Reproduction Conslt",
    "wof:placetype": "venue"
  },
  "geometry": {"coordinates":[-71.119982,42.379982],"type":"Point"}
}
