{
  "type": "Feature",
  "properties": {
    "iso:country":"US",
    "sg:address":"1575 Massachusetts Ave",
    "sg:city":"Cambridge",
    "sg:classifiers":[
        {
            "category":"Professional",
            "subcategory":"Management & Consulting",
            "type":"Services"
        }
    ],
    "sg:phone":"+1 617 496 3341",
    "sg:postcode":"02138",
    "sg:province":"MA",
    "sg:tags":[
        "consultant",
        "business"
    ],
    "wof:name":"Adoption & Reproduction Conslt",
    "wof:placetype":"venue"
},
  "geometry": {"coordinates":[-71.11998199999999,42.379982],"type":"Point"}
}