{
  "type": "Feature",
  "properties": {
    "iso:country":"US",
    "sg:address":"572 Osceola Rd",
    "sg:city":"Richmond",
    "sg:classifiers":[
        {
            "category":"Building & Trades",
            "subcategory":"Construction",
            "type":"Services"
        }
    ],
    "sg:phone":"+1 413 698 2617",
    "sg:postcode":"01254",
    "sg:province":"MA",
    "sg:tags":[
        "home",
        "improvement"
    ],
    "wof:name":"Kingsley Custom Builders",
    "wof:placetype":"venue"
},
  "geometry": {"coordinates":[-73.330338,42.397709],"type":"Point"}
}