{
  "type": "Feature",
  "properties": {
    "iso:country":"US",
    "sg:address":"143 Green St",
    "sg:city":"Foxboro",
    "sg:classifiers":[
        {
            "category":"Social Services",
            "subcategory":"Child Care",
            "type":"Services"
        }
    ],
    "sg:phone":"+1 508 543 7393",
    "sg:postcode":"02035",
    "sg:province":"MA",
    "wof:name":"Bright Horizons Family Solutns",
    "wof:placetype":"venue"
},
  "geometry": {"coordinates":[-71.248195,42.031878],"type":"Point"}
}