{
  "type": "Feature",
  "properties": {
    "iso:country":"US",
    "sg:address":"176 Walker St",
    "sg:city":"Lowell",
    "sg:classifiers":[
        {
            "category":"Wholesale",
            "subcategory":"Electrical",
            "type":"Manufacturing & Wholesale Goods"
        }
    ],
    "sg:phone":"+1 978 459 3344",
    "sg:postcode":"01854",
    "sg:province":"MA",
    "sg:tags":[
        "control",
        "security",
        "system"
    ],
    "wof:name":"Property Protection Monitoring",
    "wof:placetype":"venue"
},
  "geometry": {"coordinates":[-71.330901,42.641854],"type":"Point"}
}