{
  "type": "Feature",
  "properties": {
    "iso:country":"US",
    "sg:address":"144 Lunenburg St",
    "sg:city":"Fitchburg",
    "sg:classifiers":[
        {
            "category":"Shopping",
            "subcategory":"Discount & Variety Stores",
            "type":"Retail Goods"
        }
    ],
    "sg:phone":"+1 978 343 3469",
    "sg:postcode":"01420",
    "sg:province":"MA",
    "wof:name":"Cozy Corner Coffee Shoppe",
    "wof:placetype":"venue"
},
  "geometry": {"coordinates":[-71.784554,42.583851],"type":"Point"}
}