{
  "type": "Feature",
  "properties": {
    "addr:full": "144 Lunenburg St Fitchburg MA 01420",
    "addr:housenumber": "144",
    "addr:postcode": "01420",
    "addr:street": "Lunenburg St",
    "iso:country": "US",
    "ovtr:label": "Cozy Corner Coffee Shoppe, 144 Lunenburg St Fitchburg MA US",
    "ovtr:similarity": 2.024915933609009,
    "sg:address": "144 Lunenburg St",
    "sg:city": "Fitchburg",
    "sg:classifiers": [
      {
        "category": "Shopping",
        "subcategory": "Discount \u0026 Variety Stores",
        "type": "Retail Goods"
      }
    ],
    "sg:phone": "+1 978 343 3469",
    "sg:postcode": "01420",
    "sg:province": "MA",
    "wof:name": "Cozy Corner Coffee Shoppe",
    "wof:placetype": "venue"
  },
  "geometry": {"coordinates":[-71.784554,42.583851],"type":"Point"}
}
