{
  "type": "Feature",
  "properties": {
    "iso:country":"US",
    "sg:address":"659 Western Ave",
    "sg:city":"Lynn",
    "sg:classifiers":[
        {
            "category":"Personal",
            "subcategory":"Beauty Salon",
            "type":"Services"
        }
    ],
    "sg:phone":"+1 781 581 0573",
    "sg:postcode":"01905",
    "sg:province":"MA",
    "wof:name":"Desi's Hair Design",
    "wof:placetype":"venue"
},
  "geometry": {"coordinates":[-70.96312399999999,42.464756],"type":"Point"}
}