{
  "type": "Feature",
  "properties": {
    "addr:full": "2 Park St South Deerfield MA 01373",
    "addr:housenumber": "2",
    "addr:postcode": "01373",
    "addr:street": "Park St",
    "iso:country": "US",
    "sg:address": "2 Park St",
    "sg:city": "South Deerfield",
    "sg:classifiers": [
      {
        "category": "Health Services",
        "subcategory": "Clinic",
        "type": "Services"
      }
    ],
    "sg:phone": "+1 413 397 9933",
    "sg:postcode": "01373",
    "sg:province": "MA",
    "sg:tags": [
      "home"
    ],
    "wof:name": "Collective Home Care Inc",
    "wof:placetype": "venue"
  },
  "geometry": {"coordinates":[-72.607762,42.477644],"type":"Point"}
}
