{
  "type": "Feature",
  "properties": {
    "iso:country":"US",
    "sg:address":"2 Park St",
    "sg:city":"South Deerfield",
    "sg:classifiers":[
        {
            "category":"Health Services",
            "subcategory":"Clinic",
            "type":"Services"
        }
    ],
    "sg:phone":"+1 413 397 9933",
    "sg:postcode":"01373",
    "sg:province":"MA",
    "sg:tags":[
        "home"
    ],
    "wof:name":"Collective Home Care Inc",
    "wof:placetype":"venue"
},
  "geometry": {"coordinates":[-72.60776199999999,42.477644],"type":"Point"}
}