{
  "type": "Feature",
  "properties": {
    "iso:country":"US",
    "sg:address":"291 Newbury St",
    "sg:city":"Boston",
    "sg:classifiers":[
        {
            "category":"Shopping",
            "subcategory":"Hobbies, Toys, & Games",
            "type":"Retail Goods"
        }
    ],
    "sg:phone":"+1 617 266 0050",
    "sg:postcode":"02115",
    "sg:province":"MA",
    "sg:tags":[
        "toy",
        "store"
    ],
    "sg:website":"www.beantowntoys.com",
    "wof:name":"The Boston Baked Bean",
    "wof:placetype":"venue"
},
  "geometry": {"coordinates":[-71.08456700000001,42.349057],"type":"Point"}
}