{
  "type": "Feature",
  "properties": {
    "addr:full":"424 N Main St East Longmeadow MA 01028",
    "addr:housenumber":"424",
    "addr:postcode":"01028",
    "addr:street":"N Main St",
    "iso:country":"US",
    "sg:address":"424 N Main St",
    "sg:city":"East Longmeadow",
    "sg:classifiers":[
        {
            "category":"Insurance",
            "subcategory":"Insurance Agent",
            "type":"Services"
        }
    ],
    "sg:phone":"+1   ",
    "sg:postcode":"01028",
    "sg:province":"MA",
    "wof:name":"Pryor Patricia A Insur Agcy",
    "wof:placetype":"venue"
},
  "geometry": {"coordinates":[-72.53162399999999,42.079242],"type":"Point"}
}