{
  "type": "Feature",
  "properties": {
    "addr:full":"534 US Hwy 44 Raynham MA 02767",
    "addr:housenumber":"534",
    "addr:postcode":"02767",
    "addr:street":"Us Hwy 44",
    "iso:country":"US",
    "sg:address":"534 US Hwy 44",
    "sg:city":"Raynham",
    "sg:classifiers":[
        {
            "category":"Building & Trades",
            "subcategory":"Construction",
            "type":"Services"
        }
    ],
    "sg:phone":"+1 508 823 7761",
    "sg:postcode":"02767",
    "sg:province":"MA",
    "sg:tags":[
        "paving",
        "contractor"
    ],
    "wof:name":"Nevio Catarina Asphalt Paving",
    "wof:placetype":"venue"
},
  "geometry": {"coordinates":[-71.047197,41.906488],"type":"Point"}
}