{
  "type": "Feature",
  "properties": {
    "iso:country":"US",
    "sg:address":"78 Circuit Ave N",
    "sg:city":"Worcester",
    "sg:classifiers":[
        {
            "category":"Home & Garden",
            "subcategory":"Building Materials",
            "type":"Retail Goods"
        },
        {
            "category":"Building & Trades",
            "subcategory":"Construction",
            "type":"Services"
        }
    ],
    "sg:phone":"+1 508 755 8800",
    "sg:postcode":"01603",
    "sg:province":"MA",
    "sg:tags":[
        "insulation",
        "plastering",
        "improvement",
        "drywall",
        "contractor"
    ],
    "sg:website":"http://www.heatsavers.us",
    "wof:name":"Heatsavers",
    "wof:placetype":"venue"
},
  "geometry": {"coordinates":[-71.83931200000001,42.255408],"type":"Point"}
}