{
  "type": "Feature",
  "properties": {
    "addr:full": "604 Columbus Ave Boston MA 02118",
    "addr:housenumber": "604",
    "addr:postcode": "02118",
    "addr:street": "Columbus Ave",
    "iso:country": "US",
    "sg:address": "604 Columbus Ave",
    "sg:city": "Boston",
    "sg:classifiers": [
      {
        "category": "Restaurant",
        "type": "Food \u0026 Drink"
      }
    ],
    "sg:phone": "+1 617 247 2537",
    "sg:postcode": "02118",
    "sg:province": "MA",
    "sg:tags": [
      "french"
    ],
    "sg:website": "http://www.circle-restaurant.com",
    "wof:name": "Circle Plates \u0026 Lounge",
    "wof:placetype": "venue"
  },
  "geometry": {"coordinates":[-71.082564,42.339948],"type":"Point"}
}
