{
  "type": "Feature",
  "properties": {
    "iso:country":"US",
    "sg:address":"122 Bowdoin St",
    "sg:city":"Boston",
    "sg:classifiers":[
        {
            "category":"Professional",
            "type":"Services"
        }
    ],
    "sg:phone":"+1   ",
    "sg:postcode":"02108",
    "sg:province":"MA",
    "wof:name":"Bentonia Music",
    "wof:placetype":"venue"
},
  "geometry": {"coordinates":[-71.06277799999999,42.359076],"type":"Point"}
}