{
  "type": "Feature",
  "properties": {
    "iso:country":"US",
    "sg:address":"167 Dwight Rd",
    "sg:city":"Longmeadow",
    "sg:classifiers":[
        {
            "category":"Professional",
            "subcategory":"Management & Consulting",
            "type":"Services"
        },
        {
            "category":"Professional",
            "subcategory":"Employment Agencies",
            "type":"Services"
        }
    ],
    "sg:phone":"+1 413 565 2466",
    "sg:postcode":"01106",
    "sg:province":"MA",
    "sg:tags":[
        "opportunity",
        "business"
    ],
    "wof:name":"Colen & Associates Inc",
    "wof:placetype":"venue"
},
  "geometry": {"coordinates":[-72.539103,42.062289],"type":"Point"}
}