{
  "type": "Feature",
  "properties": {
    "addr:full": "167 Dwight Rd Longmeadow MA 01106",
    "addr:housenumber": "167",
    "addr:postcode": "01106",
    "addr:street": "Dwight Rd",
    "iso:country": "US",
    "sg:address": "167 Dwight Rd",
    "sg:city": "Longmeadow",
    "sg:classifiers": [
      {
        "category": "Professional",
        "subcategory": "Management \u0026 Consulting",
        "type": "Services"
      },
      {
        "category": "Professional",
        "subcategory": "Employment Agencies",
        "type": "Services"
      }
    ],
    "sg:phone": "+1 413 565 2466",
    "sg:postcode": "01106",
    "sg:province": "MA",
    "sg:tags": [
      "opportunity",
      "business"
    ],
    "wof:name": "Colen \u0026 Associates Inc",
    "wof:placetype": "venue"
  },
  "geometry": {"coordinates":[-72.539103,42.062289],"type":"Point"}
}
