{
  "type": "Feature",
  "properties": {
    "iso:country":"US",
    "sg:address":"1344 Allen St",
    "sg:city":"Springfield",
    "sg:classifiers":[
        {
            "category":"Shopping",
            "subcategory":"Bicycles & Sporting Goods",
            "type":"Retail Goods"
        }
    ],
    "sg:phone":"+1 413 783 4834",
    "sg:postcode":"01118",
    "sg:province":"MA",
    "wof:name":"Pro Bicycle Shop",
    "wof:placetype":"venue"
},
  "geometry": {"coordinates":[-72.51534700000001,42.094171],"type":"Point"}
}