{
  "type": "Feature",
  "properties": {
    "iso:country":"US",
    "sg:address":"65 New Salem St",
    "sg:city":"Wakefield",
    "sg:classifiers":[
        {
            "category":"Retail",
            "subcategory":"Auto Repair",
            "type":"Services"
        }
    ],
    "sg:phone":"+1 781 246 0445",
    "sg:postcode":"01880",
    "sg:province":"MA",
    "sg:tags":[
        "repairing",
        "automobile"
    ],
    "wof:name":"Quality Volvo Repairs",
    "wof:placetype":"venue"
},
  "geometry": {"coordinates":[-71.06460800000001,42.505673],"type":"Point"}
}