{
  "type": "Feature",
  "properties": {
    "addr:full": "123 Ridge Ave Newton MA 02459",
    "addr:housenumber": "123",
    "addr:postcode": "02459",
    "addr:street": "Ridge Ave",
    "iso:country": "US",
    "sg:address": "123 Ridge Ave",
    "sg:city": "Newton",
    "sg:classifiers": [
      {
        "category": "Professional",
        "subcategory": "Business Services",
        "type": "Services"
      }
    ],
    "sg:phone": "+1   ",
    "sg:postcode": "02459",
    "sg:province": "MA",
    "wof:name": "Power Object Group Inc",
    "wof:placetype": "venue"
  },
  "geometry": {"coordinates":[-71.19136,42.322695],"type":"Point"}
}
