{
  "type": "Feature",
  "properties": {
    "iso:country":"US",
    "sg:address":"35 Water St",
    "sg:city":"Amesbury",
    "sg:classifiers":[
        {
            "category":"Manufacturing",
            "subcategory":"Tools & Machinery",
            "type":"Manufacturing & Wholesale Goods"
        }
    ],
    "sg:phone":"+1 978 388 0085",
    "sg:postcode":"01913",
    "sg:province":"MA",
    "sg:tags":[
        "machine",
        "shop"
    ],
    "sg:website":"www.bartleymachine.com",
    "wof:name":"Bartley Machine & Mfg Co",
    "wof:placetype":"venue"
},
  "geometry": {"coordinates":[-70.928952,42.856947],"type":"Point"}
}