{
  "type": "Feature",
  "properties": {
    "addr:full": "35 Water St Amesbury MA 01913",
    "addr:housenumber": "35",
    "addr:postcode": "01913",
    "addr:street": "Water St",
    "iso:country": "US",
    "sg:address": "35 Water St",
    "sg:city": "Amesbury",
    "sg:classifiers": [
      {
        "category": "Manufacturing",
        "subcategory": "Tools \u0026 Machinery",
        "type": "Manufacturing \u0026 Wholesale Goods"
      }
    ],
    "sg:phone": "+1 978 388 0085",
    "sg:postcode": "01913",
    "sg:province": "MA",
    "sg:tags": [
      "machine",
      "shop"
    ],
    "sg:website": "www.bartleymachine.com",
    "wof:name": "Bartley Machine \u0026 Mfg Co",
    "wof:placetype": "venue"
  },
  "geometry": {"coordinates":[-70.928952,42.856947],"type":"Point"}
}
