{
  "type": "Feature",
  "properties": {
    "addr:full": "130 Old Colony Ave Quincy MA 02170",
    "addr:housenumber": "130",
    "addr:postcode": "02170",
    "addr:street": "Old Colony Ave",
    "iso:country": "US",
    "sg:address": "130 Old Colony Ave",
    "sg:city": "Quincy",
    "sg:classifiers": [
      {
        "category": "Professional",
        "type": "Services"
      }
    ],
    "sg:phone": "+1 617 471 2527",
    "sg:postcode": "02170",
    "sg:province": "MA",
    "sg:tags": [
      "establishment"
    ],
    "wof:name": "O P Mannion Inc",
    "wof:placetype": "venue"
  },
  "geometry": {"coordinates":[-71.015308,42.262372],"type":"Point"}
}
