{
  "type": "Feature",
  "properties": {
    "addr:full":"284 Grafton St Worcester MA 01604",
    "addr:housenumber":"284",
    "addr:postcode":"01604",
    "addr:street":"Grafton St",
    "iso:country":"US",
    "sg:address":"284 Grafton St",
    "sg:city":"Worcester",
    "sg:classifiers":[
        {
            "category":"Shopping",
            "subcategory":"Florist",
            "type":"Retail Goods"
        }
    ],
    "sg:phone":"+1 508 755 7744",
    "sg:postcode":"01604",
    "sg:province":"MA",
    "wof:name":"Perro's Flower Shop",
    "wof:placetype":"venue"
},
  "geometry": {"coordinates":[-71.78724099999999,42.256116],"type":"Point"}
}