{
  "type": "Feature",
  "properties": {
    "addr:full": "124 Grove St Franklin MA 02038",
    "addr:housenumber": "124",
    "addr:postcode": "02038",
    "addr:street": "Grove St",
    "iso:country": "US",
    "sg:address": "124 Grove St",
    "sg:city": "Franklin",
    "sg:classifiers": [
      {
        "category": "Insurance",
        "subcategory": "Hazard Insurance",
        "type": "Services"
      }
    ],
    "sg:phone": "+1 508 553 9425",
    "sg:postcode": "02038",
    "sg:province": "MA",
    "sg:tags": [
      "casualty"
    ],
    "sg:website": "www.farmfamily.com",
    "wof:name": "Farm Family Casualty Ins Co",
    "wof:placetype": "venue"
  },
  "geometry": {"coordinates":[-71.422301,42.078804],"type":"Point"}
}
