{
  "type": "Feature",
  "properties": {
    "iso:country":"US",
    "sg:address":"1320 Massachusetts Ave",
    "sg:city":"Arlington",
    "sg:classifiers":[
        {
            "category":"Personal",
            "subcategory":"Beauty Salon",
            "type":"Services"
        }
    ],
    "sg:phone":"+1 781 648 0478",
    "sg:postcode":"02476",
    "sg:province":"MA",
    "sg:website":"http://www.starnail.com",
    "wof:name":"Star Nails",
    "wof:placetype":"venue"
},
  "geometry": {"coordinates":[-71.182478,42.424274],"type":"Point"}
}