{
  "type": "Feature",
  "properties": {
    "iso:country":"US",
    "sg:address":"100 Charlton Rd",
    "sg:city":"Sturbridge",
    "sg:classifiers":[
        {
            "category":"Insurance",
            "subcategory":"Insurance Agent",
            "type":"Services"
        }
    ],
    "sg:phone":"+1 508 347 2616",
    "sg:postcode":"01566",
    "sg:province":"MA",
    "sg:website":"www.insuranceprofessionalsofne.com",
    "wof:name":"Insurance Professionals Of NE",
    "wof:placetype":"venue"
},
  "geometry": {"coordinates":[-72.05617100000001,42.124833],"type":"Point"}
}