{
  "type": "Feature",
  "properties": {
    "iso:country":"US",
    "sg:address":"530 Pochassic Rd",
    "sg:city":"Westfield",
    "sg:classifiers":[
        {
            "category":"Retail",
            "subcategory":"Auto Repair",
            "type":"Services"
        }
    ],
    "sg:phone":"+1 413 568 3284",
    "sg:postcode":"01085",
    "sg:province":"MA",
    "sg:tags":[
        "truck"
    ],
    "wof:name":"Bill's Truck & Equipment Rpr",
    "wof:placetype":"venue"
},
  "geometry": {"coordinates":[-72.786616,42.142335],"type":"Point"}
}