{
  "type": "Feature",
  "properties": {
    "addr:full": "8 Lapham Ct Mendon MA 01756",
    "addr:housenumber": "8",
    "addr:postcode": "01756",
    "addr:street": "Lapham Ct",
    "iso:country": "US",
    "sg:address": "8 Lapham Ct",
    "sg:city": "Mendon",
    "sg:classifiers": [
      {
        "category": "Building \u0026 Trades",
        "subcategory": "Construction",
        "type": "Services"
      }
    ],
    "sg:phone": "+1   ",
    "sg:postcode": "01756",
    "sg:province": "MA",
    "sg:tags": [
      "house"
    ],
    "wof:name": "Castle Maintenance \u0026 Repair",
    "wof:placetype": "venue"
  },
  "geometry": {"coordinates":[-71.535702,42.108421],"type":"Point"}
}
