{
  "type": "Feature",
  "properties": {
    "iso:country":"US",
    "sg:address":"90 Pleasant Valley St",
    "sg:city":"Methuen",
    "sg:classifiers":[
        {
            "category":"Shopping",
            "subcategory":"Clothing, Apparel, & Fashions",
            "type":"Retail Goods"
        }
    ],
    "sg:phone":"+1 978 794 7901",
    "sg:postcode":"01844",
    "sg:province":"MA",
    "sg:tags":[
        "apparel",
        "accessory",
        "clothing",
        "store",
        "women's"
    ],
    "sg:website":"http://www.anntaylor.com",
    "wof:name":"Ann Taylor LOFT Store",
    "wof:placetype":"venue"
},
  "geometry": {"coordinates":[-71.155922,42.742168],"type":"Point"}
}