{
  "type": "Feature",
  "properties": {
    "iso:country":"US",
    "sg:address":"60 School St",
    "sg:city":"Brockton",
    "sg:classifiers":[
        {
            "category":"Professional",
            "type":"Services"
        }
    ],
    "sg:phone":"+1 508 586 5333",
    "sg:postcode":"02301",
    "sg:province":"MA",
    "sg:tags":[
        "establishment"
    ],
    "wof:name":"Nesscom",
    "wof:placetype":"venue"
},
  "geometry": {"coordinates":[-71.01777199999999,42.082611],"type":"Point"}
}