{
  "type": "Feature",
  "properties": {
    "iso:country":"US",
    "sg:address":"9 New Salem St",
    "sg:city":"Wakefield",
    "sg:classifiers":[
        {
            "category":"Retail",
            "subcategory":"Auto Repair",
            "type":"Services"
        }
    ],
    "sg:phone":"+1 781 245 2352",
    "sg:postcode":"01880",
    "sg:province":"MA",
    "sg:tags":[
        "repairing",
        "automobile",
        "general"
    ],
    "wof:name":"Joe's Auto Repair",
    "wof:placetype":"venue"
},
  "geometry": {"coordinates":[-71.063507,42.507304],"type":"Point"}
}