{
  "type": "Feature",
  "properties": {
    "iso:country":"US",
    "sg:address":"179 Summer St",
    "sg:city":"Kingston",
    "sg:classifiers":[
        {
            "category":"Personal",
            "subcategory":"Beauty Salon",
            "type":"Services"
        }
    ],
    "sg:phone":"+1 781 585 3521",
    "sg:postcode":"02364",
    "sg:province":"MA",
    "sg:tags":[
        "manicuring"
    ],
    "wof:name":"Beauty Nail",
    "wof:placetype":"venue"
},
  "geometry": {"coordinates":[-70.731004,42.008522],"type":"Point"}
}