{
  "type": "Feature",
  "properties": {
    "addr:full": "203 Chestnut Hill Ave Brighton MA 02135",
    "addr:housenumber": "203",
    "addr:postcode": "02135",
    "addr:street": "Chestnut Hill Ave",
    "iso:country": "US",
    "sg:address": "203 Chestnut Hill Ave",
    "sg:city": "Brighton",
    "sg:classifiers": [
      {
        "category": "Organizations",
        "subcategory": "Religious Organization",
        "type": "Services"
      },
      {
        "category": "Arena",
        "subcategory": "Sports Club",
        "type": "Entertainment"
      }
    ],
    "sg:phone": "+1 617 787 1506",
    "sg:postcode": "02135",
    "sg:province": "MA",
    "sg:tags": [
      "martial art"
    ],
    "wof:name": "Shim Gum DO Center",
    "wof:placetype": "venue"
  },
  "geometry": {"coordinates":[-71.155296,42.340302],"type":"Point"}
}
