{
  "type": "Feature",
  "properties": {
    "iso:country":"US",
    "sg:address":"203 Chestnut Hill Ave",
    "sg:city":"Brighton",
    "sg:classifiers":[
        {
            "category":"Organizations",
            "subcategory":"Religious Organization",
            "type":"Services"
        },
        {
            "category":"Arena",
            "subcategory":"Sports Club",
            "type":"Entertainment"
        }
    ],
    "sg:phone":"+1 617 787 1506",
    "sg:postcode":"02135",
    "sg:province":"MA",
    "sg:tags":[
        "martial art"
    ],
    "wof:name":"Shim Gum DO Center",
    "wof:placetype":"venue"
},
  "geometry": {"coordinates":[-71.15529600000001,42.340302],"type":"Point"}
}