{
  "type": "Feature",
  "properties": {
    "addr:full":"296 Buffinton St Somerset MA 02726",
    "addr:housenumber":"296",
    "addr:postcode":"02726",
    "addr:street":"Buffinton St",
    "iso:country":"US",
    "sg:address":"296 Buffinton St",
    "sg:city":"Somerset",
    "sg:classifiers":[
        {
            "category":"Home & Garden",
            "subcategory":"Hardware",
            "type":"Retail Goods"
        }
    ],
    "sg:phone":"+1 508 677 4022",
    "sg:postcode":"02726",
    "sg:province":"MA",
    "sg:tags":[
        "tool",
        "used"
    ],
    "wof:name":"Diamcut Tool",
    "wof:placetype":"venue"
},
  "geometry": {"coordinates":[-71.144775,41.747112],"type":"Point"}
}