{
  "type": "Feature",
  "properties": {
    "iso:country":"US",
    "sg:address":"261 Fountain St",
    "sg:city":"Springfield",
    "sg:classifiers":[
        {
            "category":"Building & Trades",
            "subcategory":"Plumbing",
            "type":"Services"
        }
    ],
    "sg:phone":"+1   ",
    "sg:postcode":"01108",
    "sg:province":"MA",
    "sg:tags":[
        "contractor"
    ],
    "wof:name":"McNeish Plumbing and Heating",
    "wof:placetype":"venue"
},
  "geometry": {"coordinates":[-72.544769,42.082561],"type":"Point"}
}