{
  "type": "Feature",
  "properties": {
    "iso:country":"US",
    "sg:address":"1387 Fall River Ave",
    "sg:city":"Seekonk",
    "sg:classifiers":[
        {
            "category":"Shopping",
            "subcategory":"Gifts & Souvenirs",
            "type":"Retail Goods"
        }
    ],
    "sg:phone":"+1 508 336 7868",
    "sg:postcode":"02771",
    "sg:province":"MA",
    "sg:tags":[
        "collectible"
    ],
    "sg:website":"www.cutiesbearsandstuffies.com",
    "wof:name":"Cuties Bears & Stuffies",
    "wof:placetype":"venue"
},
  "geometry": {"coordinates":[-71.319969,41.788493],"type":"Point"}
}