{
  "type": "Feature",
  "properties": {
    "addr:full": "285 Dedham St Wrentham MA 02093",
    "addr:housenumber": "285",
    "addr:postcode": "02093",
    "addr:street": "Dedham St",
    "iso:country": "US",
    "sg:address": "285 Dedham St",
    "sg:city": "Wrentham",
    "sg:classifiers": [
      {
        "category": "Parking",
        "type": "Transportation"
      }
    ],
    "sg:phone": "+1 508 384 0248",
    "sg:postcode": "02093",
    "sg:province": "MA",
    "sg:tags": [
      "garage"
    ],
    "wof:name": "M \u0026 M Garage",
    "wof:placetype": "venue"
  },
  "geometry": {"coordinates":[-71.31858,42.074239],"type":"Point"}
}
