{
  "type": "Feature",
  "properties": {
    "iso:country":"US",
    "sg:address":"140 Wood St",
    "sg:city":"Somerset",
    "sg:classifiers":[
        {
            "category":"Recreation",
            "type":"Entertainment"
        }
    ],
    "sg:phone":"+1 508 646 2808",
    "sg:postcode":"02726",
    "sg:province":"MA",
    "sg:tags":[
        "parks"
    ],
    "wof:name":"Somerset Recreation Dept",
    "wof:placetype":"venue"
},
  "geometry": {"coordinates":[-71.141756,41.751621],"type":"Point"}
}