{
  "type": "Feature",
  "properties": {
    "iso:country":"US",
    "sg:address":"99 Paugus Rd",
    "sg:city":"Holden",
    "sg:classifiers":[
        {
            "category":"Wholesale",
            "subcategory":"Electrical",
            "type":"Manufacturing & Wholesale Goods"
        }
    ],
    "sg:phone":"+1 508 853 1805",
    "sg:postcode":"01520",
    "sg:province":"MA",
    "sg:tags":[
        "fire",
        "equipment",
        "protection"
    ],
    "wof:name":"Fire & Safety Engineering",
    "wof:placetype":"venue"
},
  "geometry": {"coordinates":[-71.82567899999999,42.319609],"type":"Point"}
}