{
  "type": "Feature",
  "properties": {
    "iso:country":"US",
    "sg:address":"28 Lebanon Street",
    "sg:city":"Malden",
    "sg:classifiers":[
        {
            "category":"Banks & Credit Unions",
            "subcategory":"Bank",
            "type":"Services"
        }
    ],
    "sg:phone":"+1 781 321 0093",
    "sg:postcode":"02148",
    "sg:province":"MA",
    "sg:website":"www.citizensbank.com",
    "wof:name":"Citizens Bank",
    "wof:placetype":"venue"
},
  "geometry": {"coordinates":[-71.045778,42.434082],"type":"Point"}
}