{
  "type": "Feature",
  "properties": {
    "addr:full": "52 Lexington Rd Billerica MA 01821",
    "addr:housenumber": "52",
    "addr:postcode": "01821",
    "addr:street": "Lexington Rd",
    "iso:country": "US",
    "sg:address": "52 Lexington Rd",
    "sg:city": "Billerica",
    "sg:classifiers": [
      {
        "category": "Building \u0026 Trades",
        "subcategory": "Landscaping Services",
        "type": "Services"
      }
    ],
    "sg:phone": "+1 978 667 1901",
    "sg:postcode": "01821",
    "sg:province": "MA",
    "sg:tags": [
      "tree"
    ],
    "wof:name": "Muise Tree Service",
    "wof:placetype": "venue"
  },
  "geometry": {"coordinates":[-71.261784,42.540645],"type":"Point"}
}
