{
  "type": "Feature",
  "properties": {
    "addr:full":"301 High St Holyoke MA 01040",
    "addr:housenumber":"301",
    "addr:postcode":"01040",
    "addr:street":"High St",
    "iso:country":"US",
    "sg:address":"301 High St",
    "sg:city":"Holyoke",
    "sg:classifiers":[
        {
            "category":"Professional",
            "subcategory":"Business Services",
            "type":"Services"
        }
    ],
    "sg:phone":"+1 413 536 6300",
    "sg:postcode":"01040",
    "sg:province":"MA",
    "sg:tags":[
        "notary"
    ],
    "wof:name":"Carlos M Gomez Law Office",
    "wof:placetype":"venue"
},
  "geometry": {"coordinates":[-72.609246,42.205408],"type":"Point"}
}