{
  "type": "Feature",
  "properties": {
    "addr:full": "950 Massachusetts Ave Ste 1 Cambridge MA 02139",
    "addr:housenumber": "950",
    "addr:postcode": "02139",
    "addr:street": "Massachusetts Ave Ste 1",
    "iso:country": "US",
    "sg:address": "950 Massachusetts Ave Ste 1",
    "sg:city": "Cambridge",
    "sg:classifiers": [
      {
        "category": "Food \u0026 Beverages",
        "subcategory": "Groceries \u0026 Convenience Stores",
        "type": "Retail Goods"
      }
    ],
    "sg:phone": "+1 617 576 0029",
    "sg:postcode": "02139",
    "sg:province": "MA",
    "wof:name": "Mass Food Market",
    "wof:placetype": "venue"
  },
  "geometry": {"coordinates":[-71.109933,42.36873],"type":"Point"}
}
