{
  "type": "Feature",
  "properties": {
    "iso:country":"US",
    "sg:address":"950 Massachusetts Ave Ste 1",
    "sg:city":"Cambridge",
    "sg:classifiers":[
        {
            "category":"Food & Beverages",
            "subcategory":"Groceries & Convenience Stores",
            "type":"Retail Goods"
        }
    ],
    "sg:phone":"+1 617 576 0029",
    "sg:postcode":"02139",
    "sg:province":"MA",
    "wof:name":"Mass Food Market",
    "wof:placetype":"venue"
},
  "geometry": {"coordinates":[-71.109933,42.36873],"type":"Point"}
}