{
  "type": "Feature",
  "properties": {
    "iso:country":"US",
    "sg:address":"21 Taylor St",
    "sg:city":"Littleton",
    "sg:classifiers":[
        {
            "category":"Social Services",
            "subcategory":"Child Care",
            "type":"Services"
        }
    ],
    "sg:phone":"+1 978 486 4145",
    "sg:postcode":"01460",
    "sg:province":"MA",
    "wof:name":"Peace Of Mind Daycare Ctr Inc",
    "wof:placetype":"venue"
},
  "geometry": {"coordinates":[-71.51160299999999,42.53655],"type":"Point"}
}