{
  "type": "Feature",
  "properties": {
    "iso:country":"US",
    "sg:address":"21 Lisa Ave",
    "sg:city":"Plymouth",
    "sg:classifiers":[
        {
            "category":"Professional",
            "subcategory":"Computer Services",
            "type":"Services"
        }
    ],
    "sg:phone":"+1   ",
    "sg:postcode":"02360",
    "sg:province":"MA",
    "sg:tags":[
        "datum"
    ],
    "wof:name":"Evan Damiano",
    "wof:placetype":"venue"
},
  "geometry": {"coordinates":[-70.73738,41.92891],"type":"Point"}
}