{
  "type": "Feature",
  "properties": {
    "iso:country":"US",
    "sg:address":"590 Iyannough Rd",
    "sg:city":"Hyannis",
    "sg:classifiers":[
        {
            "category":"Autos & Motor Vehicles",
            "subcategory":"Fuel & Gas Station",
            "type":"Retail Goods"
        }
    ],
    "sg:phone":"+1 508 771 3334",
    "sg:postcode":"02601",
    "sg:province":"MA",
    "wof:name":"Point Route 132 Shell Inc",
    "wof:placetype":"venue"
},
  "geometry": {"coordinates":[-70.289299,41.66605],"type":"Point"}
}