{
  "type": "Feature",
  "properties": {
    "addr:full":"186 Hampshire St Cambridge MA 02139",
    "addr:housenumber":"186",
    "addr:postcode":"02139",
    "addr:street":"Hampshire St",
    "iso:country":"US",
    "sg:address":"186 Hampshire St",
    "sg:city":"Cambridge",
    "sg:classifiers":[
        {
            "category":"Personal",
            "subcategory":"Massage",
            "type":"Services"
        },
        {
            "category":"Health Services",
            "subcategory":"Clinic",
            "type":"Services"
        },
        {
            "category":"Health Services",
            "subcategory":"Health Practitioner",
            "type":"Services"
        },
        {
            "category":"Personal",
            "subcategory":"Nail Salon",
            "type":"Services"
        }
    ],
    "sg:phone":"+1 617 714 5478",
    "sg:postcode":"02139",
    "sg:province":"MA",
    "sg:tags":[
        "medicine",
        "alternative",
        "therapist",
        "therapy",
        "physical"
    ],
    "wof:name":"Seasons of Genesis",
    "wof:placetype":"venue"
},
  "geometry": {"coordinates":[-71.09977000000001,42.372849],"type":"Point"}
}