{
  "type": "Feature",
  "properties": {
    "iso:country":"US",
    "sg:address":"24 Puffer St",
    "sg:city":"Ashburnham",
    "sg:classifiers":[
        {
            "category":"Government",
            "subcategory":"Office",
            "type":"Public Place"
        }
    ],
    "sg:phone":"+1 978 827 5805",
    "sg:postcode":"01430",
    "sg:province":"MA",
    "sg:tags":[
        "village"
    ],
    "wof:name":"Danny Marden Memorial Field",
    "wof:placetype":"venue"
},
  "geometry": {"coordinates":[-71.909425,42.633121],"type":"Point"}
}