{
  "type": "Feature",
  "properties": {
    "addr:full": "7 Woodland St Worcester MA 01610",
    "addr:housenumber": "7",
    "addr:postcode": "01610",
    "addr:street": "Woodland St",
    "iso:country": "US",
    "sg:address": "7 Woodland St",
    "sg:city": "Worcester",
    "sg:classifiers": [
      {
        "category": "Organizations",
        "subcategory": "Non-profit Organization",
        "type": "Services"
      }
    ],
    "sg:phone": "+1 508 756 8320",
    "sg:postcode": "01610",
    "sg:province": "MA",
    "sg:tags": [
      "info",
      "addiction",
      "abuse",
      "treatment",
      "drug"
    ],
    "wof:name": "Footsteps Supportive Housing",
    "wof:placetype": "venue"
  },
  "geometry": {"coordinates":[-71.816426,42.258138],"type":"Point"}
}
