{
  "type": "Feature",
  "properties": {
    "iso:country":"US",
    "sg:address":"206 N Washington St",
    "sg:city":"North Attleboro",
    "sg:classifiers":[
        {
            "category":"Restaurant",
            "type":"Food & Drink"
        }
    ],
    "sg:phone":"+1 508 699 8988",
    "sg:postcode":"02760",
    "sg:province":"MA",
    "sg:tags":[
        "eating"
    ],
    "wof:name":"Golden Panda Restaurant",
    "wof:placetype":"venue"
},
  "geometry": {"coordinates":[-71.331452,41.987978],"type":"Point"}
}