{
  "type": "Feature",
  "properties": {
    "addr:full": "65 Turnpike Rd Southborough MA 01772",
    "addr:housenumber": "65",
    "addr:postcode": "01772",
    "addr:street": "Turnpike Rd",
    "iso:country": "US",
    "sg:address": "65 Turnpike Rd",
    "sg:city": "Southborough",
    "sg:classifiers": [
      {
        "category": "Food \u0026 Beverages",
        "subcategory": "Liquor \u0026 Beverages",
        "type": "Retail Goods"
      }
    ],
    "sg:phone": "+1 508 485 1757",
    "sg:postcode": "01772",
    "sg:province": "MA",
    "wof:name": "Turnpike Food \u0026 Liquor Mart",
    "wof:placetype": "venue"
  },
  "geometry": {"coordinates":[-71.504049,42.295093],"type":"Point"}
}
