{
  "type": "Feature",
  "properties": {
    "addr:full":"42 Cross St Boston MA 02113",
    "addr:housenumber":"42",
    "addr:postcode":"02113",
    "addr:street":"Cross St",
    "iso:country":"US",
    "sg:address":"42 Cross St",
    "sg:city":"Boston",
    "sg:classifiers":[
        {
            "category":"Food & Beverages",
            "subcategory":"Groceries & Convenience Stores",
            "type":"Retail Goods"
        }
    ],
    "sg:phone":"+1 617 227 9673",
    "sg:postcode":"02113",
    "sg:province":"MA",
    "wof:name":"J. Pace & Sons",
    "wof:placetype":"venue"
},
  "geometry": {"coordinates":[-71.056754,42.363248],"type":"Point"}
}