{
  "type": "Feature",
  "properties": {
    "addr:full": "434 Salem St Medford MA 02155",
    "addr:housenumber": "434",
    "addr:postcode": "02155",
    "addr:street": "Salem St",
    "iso:country": "US",
    "sg:address": "434 Salem St",
    "sg:city": "Medford",
    "sg:classifiers": [
      {
        "category": "Retail",
        "subcategory": "Self-service Laundry",
        "type": "Services"
      }
    ],
    "sg:phone": "+1 781 393 4347",
    "sg:postcode": "02155",
    "sg:province": "MA",
    "wof:name": "Song's Homestyle Laundry",
    "wof:placetype": "venue"
  },
  "geometry": {"coordinates":[-71.091252,42.42318],"type":"Point"}
}
