{
  "type": "Feature",
  "properties": {
    "addr:full": "375 Main Street Stoneham MA 02180",
    "addr:housenumber": "375",
    "addr:postcode": "02180",
    "addr:street": "Main Street",
    "iso:country": "US",
    "sg:address": "375 Main Street",
    "sg:city": "Stoneham",
    "sg:classifiers": [
      {
        "category": "Building \u0026 Trades",
        "subcategory": "Construction",
        "type": "Services"
      }
    ],
    "sg:phone": "+1 781 438 1266",
    "sg:postcode": "02180",
    "sg:province": "MA",
    "sg:tags": [
      "contractor"
    ],
    "wof:name": "Betterway Corporation",
    "wof:placetype": "venue"
  },
  "geometry": {"coordinates":[-71.100227,42.479438],"type":"Point"}
}
