{
  "type": "Feature",
  "properties": {
    "iso:country":"US",
    "sg:address":"375 Main Street",
    "sg:city":"Stoneham",
    "sg:classifiers":[
        {
            "category":"Building & Trades",
            "subcategory":"Construction",
            "type":"Services"
        }
    ],
    "sg:phone":"+1 781 438 1266",
    "sg:postcode":"02180",
    "sg:province":"MA",
    "sg:tags":[
        "contractor"
    ],
    "wof:name":"Betterway Corporation",
    "wof:placetype":"venue"
},
  "geometry": {"coordinates":[-71.100227,42.479438],"type":"Point"}
}