{
  "type": "Feature",
  "properties": {
    "addr:full": "33 Winter St Haverhill MA 01830",
    "addr:housenumber": "33",
    "addr:postcode": "01830",
    "addr:street": "Winter St",
    "iso:country": "US",
    "sg:address": "33 Winter St",
    "sg:city": "Haverhill",
    "sg:classifiers": [
      {
        "category": "Shopping",
        "subcategory": "Party Supplies",
        "type": "Retail Goods"
      },
      {
        "category": "Retail",
        "subcategory": "Auto Rental",
        "type": "Services"
      },
      {
        "category": "Local Transit",
        "type": "Transportation"
      }
    ],
    "sg:phone": "+1 978 372 8227",
    "sg:postcode": "01830",
    "sg:province": "MA",
    "sg:tags": [
      "shuttle",
      "limousine",
      "wedding"
    ],
    "wof:name": "Linahan Limousine",
    "wof:placetype": "venue"
  },
  "geometry": {"coordinates":[-71.078174,42.777224],"type":"Point"}
}
