{
  "type": "Feature",
  "properties": {
    "addr:full": "165 Tyler St Methuen MA 01844",
    "addr:housenumber": "165",
    "addr:postcode": "01844",
    "addr:street": "Tyler St",
    "iso:country": "US",
    "sg:address": "165 Tyler St",
    "sg:city": "Methuen",
    "sg:classifiers": [
      {
        "category": "Building \u0026 Trades",
        "subcategory": "Electrical",
        "type": "Services"
      }
    ],
    "sg:phone": "+1 978 689 4115",
    "sg:postcode": "01844",
    "sg:province": "MA",
    "sg:tags": [
      "electric",
      "contractor"
    ],
    "wof:name": "Eagle Electrical Corp",
    "wof:placetype": "venue"
  },
  "geometry": {"coordinates":[-71.22819,42.710297],"type":"Point"}
}
