{
  "type": "Feature",
  "properties": {
    "iso:country":"US",
    "sg:address":"165 Tyler St",
    "sg:city":"Methuen",
    "sg:classifiers":[
        {
            "category":"Building & Trades",
            "subcategory":"Electrical",
            "type":"Services"
        }
    ],
    "sg:phone":"+1 978 689 4115",
    "sg:postcode":"01844",
    "sg:province":"MA",
    "sg:tags":[
        "electric",
        "contractor"
    ],
    "wof:name":"Eagle Electrical Corp",
    "wof:placetype":"venue"
},
  "geometry": {"coordinates":[-71.22819,42.710297],"type":"Point"}
}