{
  "type": "Feature",
  "properties": {
    "addr:full": "33 Indian Spring Rd Ashland MA 01721",
    "addr:housenumber": "33",
    "addr:postcode": "01721",
    "addr:street": "Indian Spring Rd",
    "iso:country": "US",
    "sg:address": "33 Indian Spring Rd",
    "sg:city": "Ashland",
    "sg:classifiers": [
      {
        "category": "Building \u0026 Trades",
        "subcategory": "Construction",
        "type": "Services"
      }
    ],
    "sg:phone": "+1 508 881 0067",
    "sg:postcode": "01721",
    "sg:province": "MA",
    "sg:tags": [
      "resurfacing",
      "laying",
      "refinishing",
      "floor"
    ],
    "wof:name": "Classic Floors",
    "wof:placetype": "venue"
  },
  "geometry": {"coordinates":[-71.477955,42.250323],"type":"Point"}
}
