{
  "type": "Feature",
  "properties": {
    "iso:country":"US",
    "sg:address":"90 Haskell Ave",
    "sg:city":"Clinton",
    "sg:classifiers":[
        {
            "category":"Manufacturing",
            "subcategory":"Printing",
            "type":"Manufacturing & Wholesale Goods"
        }
    ],
    "sg:phone":"+1 978 368 1740",
    "sg:postcode":"01510",
    "sg:province":"MA",
    "sg:tags":[
        "publisher"
    ],
    "sg:website":"www.parkinsongroup.com",
    "wof:name":"Parkinson Group Inc",
    "wof:placetype":"venue"
},
  "geometry": {"coordinates":[-71.675645,42.417652],"type":"Point"}
}