{
  "type": "Feature",
  "properties": {
    "iso:country":"US",
    "sg:address":"29 Cottage Ave Ste 5",
    "sg:city":"Quincy",
    "sg:classifiers":[
        {
            "category":"Real Estate",
            "subcategory":"Real Estate Services",
            "type":"Services"
        },
        {
            "category":"Professional",
            "subcategory":"Business Services",
            "type":"Services"
        },
        {
            "category":"Real Estate",
            "subcategory":"Surveying",
            "type":"Services"
        }
    ],
    "sg:phone":"+1 617 770 9170",
    "sg:postcode":"02169",
    "sg:province":"MA",
    "sg:tags":[
        "commercial",
        "appraisers-business",
        "industrial",
        "appraisers-commercial",
        "appraiser"
    ],
    "wof:name":"Mcgovern Appraisal Service Inc",
    "wof:placetype":"venue"
},
  "geometry": {"coordinates":[-71.001609,42.248275],"type":"Point"}
}