{
  "type": "Feature",
  "properties": {
    "addr:full":"171 Nahatan St Norwood MA 02062",
    "addr:housenumber":"171",
    "addr:postcode":"02062",
    "addr:street":"Nahatan St",
    "iso:country":"US",
    "sg:address":"171 Nahatan St",
    "sg:city":"Norwood",
    "sg:classifiers":[
        {
            "category":"Restaurant",
            "type":"Food & Drink"
        }
    ],
    "sg:phone":"+1 781 762 2058",
    "sg:postcode":"02062",
    "sg:province":"MA",
    "sg:tags":[
        "new",
        "american",
        "cafe"
    ],
    "wof:name":"Old Colonial Cafe",
    "wof:placetype":"venue"
},
  "geometry": {"coordinates":[-71.200855,42.195138],"type":"Point"}
}