{
  "type": "Feature",
  "properties": {
    "addr:full":"10 Whipple Ave Roslindale MA 02131",
    "addr:housenumber":"10",
    "addr:postcode":"02131",
    "addr:street":"Whipple Ave",
    "iso:country":"US",
    "sg:address":"10 Whipple Ave",
    "sg:city":"Roslindale",
    "sg:classifiers":[
        {
            "category":"Building & Trades",
            "subcategory":"Construction",
            "type":"Services"
        }
    ],
    "sg:phone":"+1 617 971 9706",
    "sg:postcode":"02131",
    "sg:province":"MA",
    "sg:tags":[
        "general",
        "contractor"
    ],
    "wof:name":"Leeward Environmental Corp",
    "wof:placetype":"venue"
},
  "geometry": {"coordinates":[-71.12099600000001,42.291127],"type":"Point"}
}