{
  "type": "Feature",
  "properties": {
    "addr:full": "373 Russell St Woburn MA 01801",
    "addr:housenumber": "373",
    "addr:postcode": "01801",
    "addr:street": "Russell St",
    "iso:country": "US",
    "sg:address": "373 Russell St",
    "sg:city": "Woburn",
    "sg:classifiers": [
      {
        "category": "Retail",
        "subcategory": "Veterinary Services",
        "type": "Services"
      },
      {
        "category": "Retail",
        "subcategory": "Pet Boarding",
        "type": "Services"
      }
    ],
    "sg:phone": "+1 781 933 0170",
    "sg:postcode": "01801",
    "sg:province": "MA",
    "sg:tags": [
      "sitting",
      "hospital",
      "specialty",
      "clinic",
      "veterinarian",
      "boarding/pet"
    ],
    "wof:name": "Woburn Animal Hospital",
    "wof:placetype": "venue"
  },
  "geometry": {"coordinates":[-71.193199,42.465],"type":"Point"}
}
