{
  "type": "Feature",
  "properties": {
    "iso:country":"US",
    "sg:address":"373 Russell St",
    "sg:city":"Woburn",
    "sg:classifiers":[
        {
            "category":"Retail",
            "subcategory":"Veterinary Services",
            "type":"Services"
        },
        {
            "category":"Retail",
            "subcategory":"Pet Boarding",
            "type":"Services"
        }
    ],
    "sg:phone":"+1 781 933 0170",
    "sg:postcode":"01801",
    "sg:province":"MA",
    "sg:tags":[
        "sitting",
        "hospital",
        "specialty",
        "clinic",
        "veterinarian",
        "boarding/pet"
    ],
    "wof:name":"Woburn Animal Hospital",
    "wof:placetype":"venue"
},
  "geometry": {"coordinates":[-71.19319900000001,42.465],"type":"Point"}
}