{
  "type": "Feature",
  "properties": {
    "addr:full": "14 Sycamore Dr Rutland MA 01543",
    "addr:housenumber": "14",
    "addr:postcode": "01543",
    "addr:street": "Sycamore Dr",
    "iso:country": "US",
    "sg:address": "14 Sycamore Dr",
    "sg:city": "Rutland",
    "sg:classifiers": [
      {
        "category": "Professional",
        "subcategory": "Accounting \u0026 Tax Preparation",
        "type": "Services"
      }
    ],
    "sg:phone": "+1 508 886 4948",
    "sg:postcode": "01543",
    "sg:province": "MA",
    "sg:tags": [
      "return",
      "preparation-business"
    ],
    "wof:name": "The Tax Break",
    "wof:placetype": "venue"
  },
  "geometry": {"coordinates":[-71.934084,42.379232],"type":"Point"}
}
