{
  "type": "Feature",
  "properties": {
    "iso:country":"US",
    "sg:address":"14 Sycamore Dr",
    "sg:city":"Rutland",
    "sg:classifiers":[
        {
            "category":"Professional",
            "subcategory":"Accounting & Tax Preparation",
            "type":"Services"
        }
    ],
    "sg:phone":"+1 508 886 4948",
    "sg:postcode":"01543",
    "sg:province":"MA",
    "sg:tags":[
        "return",
        "preparation-business"
    ],
    "wof:name":"The Tax Break",
    "wof:placetype":"venue"
},
  "geometry": {"coordinates":[-71.934084,42.379232],"type":"Point"}
}