{
  "type": "Feature",
  "properties": {
    "addr:full": "4 Market St Bridgewater MA 02301",
    "addr:housenumber": "4",
    "addr:postcode": "02301",
    "addr:street": "Market St",
    "iso:country": "US",
    "sg:address": "4 Market St",
    "sg:city": "Bridgewater",
    "sg:classifiers": [
      {
        "category": "Building \u0026 Trades",
        "subcategory": "Construction",
        "type": "Services"
      }
    ],
    "sg:phone": "+1 781 294 4837",
    "sg:postcode": "02301",
    "sg:province": "MA",
    "sg:tags": [
      "general",
      "contractor"
    ],
    "wof:name": "Johnson Construction",
    "wof:placetype": "venue"
  },
  "geometry": {"coordinates":[-71.01644,42.062572],"type":"Point"}
}
