{
  "type": "Feature",
  "properties": {
    "iso:country":"US",
    "sg:address":"875 Merriam Ave",
    "sg:city":"Leominster",
    "sg:classifiers":[
        {
            "category":"Health Services",
            "subcategory":"Doctor",
            "type":"Services"
        }
    ],
    "sg:phone":"+1 978 840 9900",
    "sg:postcode":"01453",
    "sg:province":"MA",
    "sg:tags":[
        "dental",
        "clinic",
        "dentist"
    ],
    "sg:website":"http://www.aspendental.com/?utm_source=Yellowpages.com&utm_medium=fixed%2Bplacement&utm_campaign=trade%2Blistings",
    "wof:name":"Aspen Dental",
    "wof:placetype":"venue"
},
  "geometry": {"coordinates":[-71.782583,42.551418],"type":"Point"}
}