{
  "type": "Feature",
  "properties": {
    "iso:country":"US",
    "sg:address":"1 Main St",
    "sg:city":"Lunenburg",
    "sg:classifiers":[
        {
            "category":"Restaurant",
            "type":"Food & Drink"
        }
    ],
    "sg:phone":"+1 978 582 6100",
    "sg:postcode":"01462",
    "sg:province":"MA",
    "wof:name":"Village Grill Pizzaria Rstrnt",
    "wof:placetype":"venue"
},
  "geometry": {"coordinates":[-71.725049,42.594933],"type":"Point"}
}