{
  "type": "Feature",
  "properties": {
    "addr:full":"3 Sunset Dr Randolph MA 02368",
    "addr:housenumber":"3",
    "addr:postcode":"02368",
    "addr:street":"Sunset Dr",
    "iso:country":"US",
    "sg:address":"3 Sunset Dr",
    "sg:city":"Randolph",
    "sg:classifiers":[
        {
            "category":"Building & Trades",
            "subcategory":"Construction",
            "type":"Services"
        }
    ],
    "sg:phone":"+1 781 963 5032",
    "sg:postcode":"02368",
    "sg:province":"MA",
    "sg:tags":[
        "system",
        "contractor",
        "air conditioning"
    ],
    "wof:name":"Kents Air Conditioning",
    "wof:placetype":"venue"
},
  "geometry": {"coordinates":[-71.079187,42.188794],"type":"Point"}
}