{
  "type": "Feature",
  "properties": {
    "iso:country":"US",
    "sg:address":"427 Merrimac St",
    "sg:city":"Newburyport",
    "sg:classifiers":[
        {
            "category":"Personal",
            "subcategory":"Beauty Salon",
            "type":"Services"
        }
    ],
    "sg:phone":"+1 978 465 8880",
    "sg:postcode":"01950",
    "sg:province":"MA",
    "wof:name":"Mindi's",
    "wof:placetype":"venue"
},
  "geometry": {"coordinates":[-70.892042,42.825117],"type":"Point"}
}