{
  "type": "Feature",
  "properties": {
    "addr:full": "61 King Philip Rd Sudbury MA 01776",
    "addr:housenumber": "61",
    "addr:postcode": "01776",
    "addr:street": "King Philip Rd",
    "iso:country": "US",
    "sg:address": "61 King Philip Rd",
    "sg:city": "Sudbury",
    "sg:classifiers": [
      {
        "category": "Travel",
        "subcategory": "Hotels \u0026 Motels",
        "type": "Entertainment"
      }
    ],
    "sg:phone": "+1 978 440 9525",
    "sg:postcode": "01776",
    "sg:province": "MA",
    "sg:tags": [
      "breakfast",
      "accommodation",
      "bed"
    ],
    "wof:name": "Hunt House Bed \u0026 Breakfast",
    "wof:placetype": "venue"
  },
  "geometry": {"coordinates":[-71.412091,42.362821],"type":"Point"}
}
