{
  "type": "Feature",
  "properties": {
    "iso:country":"US",
    "sg:address":"61 King Philip Rd",
    "sg:city":"Sudbury",
    "sg:classifiers":[
        {
            "category":"Travel",
            "subcategory":"Hotels & Motels",
            "type":"Entertainment"
        }
    ],
    "sg:phone":"+1 978 440 9525",
    "sg:postcode":"01776",
    "sg:province":"MA",
    "sg:tags":[
        "breakfast",
        "accommodation",
        "bed"
    ],
    "wof:name":"Hunt House Bed & Breakfast",
    "wof:placetype":"venue"
},
  "geometry": {"coordinates":[-71.412091,42.362821],"type":"Point"}
}