{
  "type": "Feature",
  "properties": {
    "iso:country":"US",
    "sg:address":"85 1st Ave",
    "sg:city":"Waltham",
    "sg:classifiers":[
        {
            "category":"Health Services",
            "subcategory":"Doctor",
            "type":"Services"
        }
    ],
    "sg:phone":"+1 781 894 5522",
    "sg:postcode":"02451",
    "sg:province":"MA",
    "sg:tags":[
        "physician",
        "surgeon",
        "anesthesiology",
        "surgeons"
    ],
    "wof:name":"Greater Boston Anesthesia Associates Inc",
    "wof:placetype":"venue"
},
  "geometry": {"coordinates":[-71.267314,42.395647],"type":"Point"}
}