{
  "type": "Feature",
  "properties": {
    "addr:full":"33 Spoonhill Ave Marlborough MA 01752",
    "addr:housenumber":"33",
    "addr:postcode":"01752",
    "addr:street":"Spoonhill Ave",
    "iso:country":"US",
    "sg:address":"33 Spoonhill Ave",
    "sg:city":"Marlborough",
    "sg:classifiers":[
        {
            "category":"Professional",
            "type":"Services"
        }
    ],
    "sg:phone":"+1   ",
    "sg:postcode":"01752",
    "sg:province":"MA",
    "wof:name":"Mmd Strategic Services Inc",
    "wof:placetype":"venue"
},
  "geometry": {"coordinates":[-71.532325,42.358381],"type":"Point"}
}