{
  "type": "Feature",
  "properties": {
    "addr:full":"449 Springfield St Wilbraham MA 01095",
    "addr:housenumber":"449",
    "addr:postcode":"01095",
    "addr:street":"Springfield St",
    "iso:country":"US",
    "sg:address":"449 Springfield St",
    "sg:city":"Wilbraham",
    "sg:classifiers":[
        {
            "category":"Professional",
            "type":"Services"
        }
    ],
    "sg:phone":"+1 413 596 8431",
    "sg:postcode":"01095",
    "sg:province":"MA",
    "wof:name":"Parallel Information Systems",
    "wof:placetype":"venue"
},
  "geometry": {"coordinates":[-72.462766,42.119823],"type":"Point"}
}