{
  "type": "Feature",
  "properties": {
    "addr:full":"333 Massachusetts Ave Boston MA 02115",
    "addr:housenumber":"333",
    "addr:postcode":"02115",
    "addr:street":"Massachusetts Ave",
    "iso:country":"US",
    "sg:address":"333 Massachusetts Ave",
    "sg:city":"Boston",
    "sg:classifiers":[
        {
            "category":"Personal",
            "subcategory":"Massage",
            "type":"Services"
        }
    ],
    "sg:phone":"+1 617 959 2543",
    "sg:postcode":"02115",
    "sg:province":"MA",
    "wof:name":"Thai Body Work",
    "wof:placetype":"venue"
},
  "geometry": {"coordinates":[-71.08505599999999,42.342819],"type":"Point"}
}