{
  "type": "Feature",
  "properties": {
    "addr:full":"151 Martine St Fall River MA 02723",
    "addr:housenumber":"151",
    "addr:postcode":"02723",
    "addr:street":"Martine St",
    "iso:country":"US",
    "sg:address":"151 Martine St",
    "sg:city":"Fall River",
    "sg:classifiers":[
        {
            "category":"Building & Trades",
            "subcategory":"Construction",
            "type":"Services"
        }
    ],
    "sg:phone":"+1 508 235 0458",
    "sg:postcode":"02723",
    "sg:province":"MA",
    "sg:tags":[
        "general",
        "contractor"
    ],
    "wof:name":"Spec Process Engineering",
    "wof:placetype":"venue"
},
  "geometry": {"coordinates":[-71.12199099999999,41.683804],"type":"Point"}
}