{
  "type": "Feature",
  "properties": {
    "addr:full":"4 Gill St Woburn MA 01801",
    "addr:housenumber":"4",
    "addr:postcode":"01801",
    "addr:street":"Gill St",
    "iso:country":"US",
    "sg:address":"4 Gill St",
    "sg:city":"Woburn",
    "sg:classifiers":[
        {
            "category":"Wholesale",
            "subcategory":"Machinery & Supplies",
            "type":"Manufacturing & Wholesale Goods"
        },
        {
            "category":"Wholesale",
            "subcategory":"Electrical",
            "type":"Manufacturing & Wholesale Goods"
        }
    ],
    "sg:phone":"+1 781 935 7590",
    "sg:postcode":"01801",
    "sg:province":"MA",
    "sg:tags":[
        "transmission",
        "equipment",
        "industrial",
        "power"
    ],
    "sg:website":"www.kamandirect.com",
    "wof:name":"Kaman Industrial Tech Corp",
    "wof:placetype":"venue"
},
  "geometry": {"coordinates":[-71.147076,42.509732],"type":"Point"}
}