{
  "type": "Feature",
  "properties": {
    "iso:country":"US",
    "sg:address":"484 Main St",
    "sg:city":"Worcester",
    "sg:classifiers":[
        {
            "category":"Professional",
            "subcategory":"Lawyer & Legal Services",
            "type":"Services"
        }
    ],
    "sg:phone":"+1 508 754 1970",
    "sg:postcode":"01608",
    "sg:province":"MA",
    "sg:tags":[
        "attorney"
    ],
    "wof:name":"Mary Bermudez Camp Law Ofc",
    "wof:placetype":"venue"
},
  "geometry": {"coordinates":[-71.80237099999999,42.263384],"type":"Point"}
}