{
  "type": "Feature",
  "properties": {
    "addr:full": "1150 Boylston St Newton MA 02464",
    "addr:housenumber": "1150",
    "addr:postcode": "02464",
    "addr:street": "Boylston St",
    "iso:country": "US",
    "sg:address": "1150 Boylston St",
    "sg:city": "Newton",
    "sg:classifiers": [
      {
        "category": "Professional",
        "subcategory": "Accounting \u0026 Tax Preparation",
        "type": "Services"
      }
    ],
    "sg:phone": "+1 617 244 4260",
    "sg:postcode": "02464",
    "sg:province": "MA",
    "sg:tags": [
      "accountant"
    ],
    "sg:website": "www.taxadvice.com",
    "wof:name": "United Revenue Svc",
    "wof:placetype": "venue"
  },
  "geometry": {"coordinates":[-71.216956,42.318163],"type":"Point"}
}
