{
  "type": "Feature",
  "properties": {
    "addr:full":"29 Brennan Way Holden MA 01520",
    "addr:housenumber":"29",
    "addr:postcode":"01520",
    "addr:street":"Brennan Way",
    "iso:country":"US",
    "sg:address":"29 Brennan Way",
    "sg:city":"Holden",
    "sg:classifiers":[
        {
            "category":"Home & Garden",
            "subcategory":"Building Materials",
            "type":"Retail Goods"
        }
    ],
    "sg:phone":"+1 508 829 4488",
    "sg:postcode":"01520",
    "sg:province":"MA",
    "sg:tags":[
        "siding"
    ],
    "wof:name":"Dave's Siding",
    "wof:placetype":"venue"
},
  "geometry": {"coordinates":[-71.872589,42.335369],"type":"Point"}
}