{
  "type": "Feature",
  "properties": {
    "addr:full": "315 W Broadway Boston MA 02127",
    "addr:housenumber": "315",
    "addr:postcode": "02127",
    "addr:street": "W Broadway",
    "iso:country": "US",
    "sg:address": "315 W Broadway",
    "sg:city": "Boston",
    "sg:classifiers": [
      {
        "category": "Shopping",
        "subcategory": "Department Store",
        "type": "Retail Goods"
      }
    ],
    "sg:phone": "+1 617 269 9667",
    "sg:postcode": "02127",
    "sg:province": "MA",
    "sg:tags": [
      "shop"
    ],
    "wof:name": "Boston's Best Bargain Basement",
    "wof:placetype": "venue"
  },
  "geometry": {"coordinates":[-71.050135,42.338349],"type":"Point"}
}
