{
  "type": "Feature",
  "properties": {
    "iso:country":"US",
    "sg:address":"1 Carlisle Rd",
    "sg:city":"Westford",
    "sg:classifiers":[
        {
            "category":"Shopping",
            "subcategory":"Pharmacy",
            "type":"Retail Goods"
        }
    ],
    "sg:phone":"+1 978 392 6995",
    "sg:postcode":"01886",
    "sg:province":"MA",
    "sg:tags":[
        "drugstore"
    ],
    "sg:website":"www.riteaid.com",
    "wof:name":"Rite Aid Pharmacies",
    "wof:placetype":"venue"
},
  "geometry": {"coordinates":[-71.423906,42.565919],"type":"Point"}
}