{
  "type": "Feature",
  "properties": {
    "iso:country":"US",
    "sg:address":"2 Lynn Fells Pkwy",
    "sg:city":"Melrose",
    "sg:classifiers":[
        {
            "category":"Food & Beverages",
            "subcategory":"Groceries & Convenience Stores",
            "type":"Retail Goods"
        }
    ],
    "sg:phone":"+1 781 662 7711",
    "sg:postcode":"02176",
    "sg:province":"MA",
    "wof:name":"Super Petroleum Inc",
    "wof:placetype":"venue"
},
  "geometry": {"coordinates":[-71.07872399999999,42.461453],"type":"Point"}
}