{
  "type": "Feature",
  "properties": {
    "addr:full": "2 Lynn Fells Pkwy Melrose MA 02176",
    "addr:housenumber": "2",
    "addr:postcode": "02176",
    "addr:street": "Lynn Fells Pkwy",
    "iso:country": "US",
    "sg:address": "2 Lynn Fells Pkwy",
    "sg:city": "Melrose",
    "sg:classifiers": [
      {
        "category": "Food \u0026 Beverages",
        "subcategory": "Groceries \u0026 Convenience Stores",
        "type": "Retail Goods"
      }
    ],
    "sg:phone": "+1 781 662 7711",
    "sg:postcode": "02176",
    "sg:province": "MA",
    "wof:name": "Super Petroleum Inc",
    "wof:placetype": "venue"
  },
  "geometry": {"coordinates":[-71.078724,42.461453],"type":"Point"}
}
