{
  "type": "Feature",
  "properties": {
    "iso:country":"US",
    "sg:address":"1 Kelley Sq",
    "sg:city":"Worcester",
    "sg:classifiers":[
        {
            "category":"Professional",
            "subcategory":"Management & Consulting",
            "type":"Services"
        }
    ],
    "sg:phone":"+1 508 798 5220",
    "sg:postcode":"01610",
    "sg:province":"MA",
    "sg:tags":[
        "construction"
    ],
    "wof:name":"Harding Design & Construction",
    "wof:placetype":"venue"
},
  "geometry": {"coordinates":[-71.79755299999999,42.254812],"type":"Point"}
}