{
  "type": "Feature",
  "properties": {
    "addr:full": "1 Kelley Sq Worcester MA 01610",
    "addr:housenumber": "1",
    "addr:postcode": "01610",
    "addr:street": "Kelley Sq",
    "iso:country": "US",
    "sg:address": "1 Kelley Sq",
    "sg:city": "Worcester",
    "sg:classifiers": [
      {
        "category": "Professional",
        "subcategory": "Management \u0026 Consulting",
        "type": "Services"
      }
    ],
    "sg:phone": "+1 508 798 5220",
    "sg:postcode": "01610",
    "sg:province": "MA",
    "sg:tags": [
      "construction"
    ],
    "wof:name": "Harding Design \u0026 Construction",
    "wof:placetype": "venue"
  },
  "geometry": {"coordinates":[-71.797553,42.254812],"type":"Point"}
}
