{
  "type": "Feature",
  "properties": {
    "iso:country":"US",
    "sg:address":"145 Harvest Rd",
    "sg:city":"Eastham",
    "sg:classifiers":[
        {
            "category":"Building & Trades",
            "subcategory":"Construction",
            "type":"Services"
        }
    ],
    "sg:phone":"+1   ",
    "sg:postcode":"02642",
    "sg:province":"MA",
    "sg:tags":[
        "carpentry",
        "contractor"
    ],
    "wof:name":"Kenny Duff Finish Carpent",
    "wof:placetype":"venue"
},
  "geometry": {"coordinates":[-69.992271,41.874678],"type":"Point"}
}