{
  "type": "Feature",
  "properties": {
    "iso:country":"US",
    "sg:address":"22 Reservoir Rd Fl 1",
    "sg:city":"Gloucester",
    "sg:classifiers":[
        {
            "category":"Wholesale",
            "subcategory":"Hardware",
            "type":"Manufacturing & Wholesale Goods"
        }
    ],
    "sg:phone":"+1 978 281 5053",
    "sg:postcode":"01930",
    "sg:province":"MA",
    "sg:tags":[
        "hardware-wholesale",
        "manufacturer"
    ],
    "wof:name":"Bradley Robertson",
    "wof:placetype":"venue"
},
  "geometry": {"coordinates":[-70.67046499999999,42.62802],"type":"Point"}
}