{
  "type": "Feature",
  "properties": {
    "addr:full":"83 Bennett Cir Billerica MA 01821",
    "addr:housenumber":"83",
    "addr:postcode":"01821",
    "addr:street":"Bennett Cir",
    "iso:country":"US",
    "sg:address":"83 Bennett Cir",
    "sg:city":"Billerica",
    "sg:classifiers":[
        {
            "category":"Building & Trades",
            "subcategory":"Locksmith",
            "type":"Services"
        }
    ],
    "sg:phone":"+1 978 901 6016",
    "sg:postcode":"01821",
    "sg:province":"MA",
    "sg:tags":[
        "key"
    ],
    "wof:name":"For Locksmith",
    "wof:placetype":"venue"
},
  "geometry": {"coordinates":[-71.243272,42.544546],"type":"Point"}
}