{
  "type": "Feature",
  "properties": {
    "addr:full":"450 Chestnut St Gardner MA 01440",
    "addr:housenumber":"450",
    "addr:postcode":"01440",
    "addr:street":"Chestnut St",
    "iso:country":"US",
    "sg:address":"450 Chestnut St",
    "sg:city":"Gardner",
    "sg:classifiers":[
        {
            "category":"Manufacturing",
            "subcategory":"Metals",
            "type":"Manufacturing & Wholesale Goods"
        }
    ],
    "sg:phone":"+1 978 632 1007",
    "sg:postcode":"01440",
    "sg:province":"MA",
    "sg:tags":[
        "machine",
        "screw",
        "product"
    ],
    "wof:name":"L H Sawin Co",
    "wof:placetype":"venue"
},
  "geometry": {"coordinates":[-71.984177,42.571059],"type":"Point"}
}