{
  "type": "Feature",
  "properties": {
    "addr:full": "210 Commercial St Provincetown MA 02657",
    "addr:housenumber": "210",
    "addr:postcode": "02657",
    "addr:street": "Commercial St",
    "iso:country": "US",
    "sg:address": "210 Commercial St",
    "sg:city": "Provincetown",
    "sg:classifiers": [
      {
        "category": "Shopping",
        "subcategory": "Clothing, Apparel, \u0026 Fashions",
        "type": "Retail Goods"
      }
    ],
    "sg:phone": "+1 508 487 6215",
    "sg:postcode": "02657",
    "sg:province": "MA",
    "wof:name": "All American Boy",
    "wof:placetype": "venue"
  },
  "geometry": {"coordinates":[-70.188785,42.04938],"type":"Point"}
}
