{
  "type": "Feature",
  "properties": {
    "iso:country":"US",
    "sg:address":"1540 Lakeview Ave",
    "sg:city":"Dracut",
    "sg:classifiers":[
        {
            "category":"Education",
            "subcategory":"School",
            "type":"Public Place"
        }
    ],
    "sg:phone":"+1 978 957 1500",
    "sg:postcode":"01826",
    "sg:province":"MA",
    "wof:name":"Dracut Senior High School",
    "wof:placetype":"venue"
},
  "geometry": {"coordinates":[-71.335514,42.675319],"type":"Point"}
}