{
  "type": "Feature",
  "properties": {
    "addr:full":"334 E 8th St Boston MA 02127",
    "addr:housenumber":"334",
    "addr:postcode":"02127",
    "addr:street":"E 8Th St",
    "iso:country":"US",
    "sg:address":"334 E 8th St",
    "sg:city":"Boston",
    "sg:classifiers":[
        {
            "category":"Food & Beverages",
            "subcategory":"Groceries & Convenience Stores",
            "type":"Retail Goods"
        }
    ],
    "sg:phone":"+1 617 269 7222",
    "sg:postcode":"02127",
    "sg:province":"MA",
    "sg:tags":[
        "market"
    ],
    "wof:name":"Family Market",
    "wof:placetype":"venue"
},
  "geometry": {"coordinates":[-71.04789700000001,42.3311],"type":"Point"}
}