{
  "type": "Feature",
  "properties": {
    "addr:full":"107 Eastern Ave Gloucester MA 01930",
    "addr:housenumber":"107",
    "addr:postcode":"01930",
    "addr:street":"Eastern Ave",
    "iso:country":"US",
    "sg:address":"107 Eastern Ave",
    "sg:city":"Gloucester",
    "sg:classifiers":[
        {
            "category":"Autos & Motor Vehicles",
            "subcategory":"Auto Supplies",
            "type":"Retail Goods"
        },
        {
            "category":"Retail",
            "subcategory":"Auto Repair",
            "type":"Services"
        }
    ],
    "sg:phone":"+1 978 381 0261",
    "sg:postcode":"01930",
    "sg:province":"MA",
    "sg:tags":[
        "tire",
        "automobile",
        "retread",
        "part",
        "balancing",
        "wheels-aligning",
        "recap"
    ],
    "sg:website":"http://www.eastcoasttire.com",
    "wof:name":"East Coast Tire",
    "wof:placetype":"venue"
},
  "geometry": {"coordinates":[-70.64315000000001,42.622871],"type":"Point"}
}