{
  "type": "Feature",
  "properties": {
    "iso:country":"US",
    "sg:address":"546 South St",
    "sg:city":"Fitchburg",
    "sg:classifiers":[
        {
            "category":"Retail",
            "subcategory":"Auto Repair",
            "type":"Services"
        }
    ],
    "sg:phone":"+1 978 343 8286",
    "sg:postcode":"01420",
    "sg:province":"MA",
    "sg:tags":[
        "body",
        "automobile",
        "painting"
    ],
    "wof:name":"Pride Auto Svc Ctr",
    "wof:placetype":"venue"
},
  "geometry": {"coordinates":[-71.795266,42.56759],"type":"Point"}
}