{
  "type": "Feature",
  "properties": {
    "addr:full": "44 Old Forge Rd South Weymouth MA 02190",
    "addr:housenumber": "44",
    "addr:postcode": "02190",
    "addr:street": "Old Forge Rd",
    "iso:country": "US",
    "sg:address": "44 Old Forge Rd",
    "sg:city": "South Weymouth",
    "sg:classifiers": [
      {
        "category": "Professional",
        "type": "Services"
      }
    ],
    "sg:phone": "+1   ",
    "sg:postcode": "02190",
    "sg:province": "MA",
    "wof:name": "Douglas Frank",
    "wof:placetype": "venue"
  },
  "geometry": {"coordinates":[-70.968948,42.142918],"type":"Point"}
}
