{
  "type": "Feature",
  "properties": {
    "iso:country":"US",
    "sg:address":"145 Bliss St",
    "sg:city":"New Bedford",
    "sg:classifiers":[
        {
            "category":"Retail",
            "subcategory":"Car Wash",
            "type":"Services"
        }
    ],
    "sg:phone":"+1 508 991 7048",
    "sg:postcode":"02740",
    "sg:province":"MA",
    "sg:tags":[
        "polishing",
        "washing"
    ],
    "wof:name":"Nice N Clean Car Wash",
    "wof:placetype":"venue"
},
  "geometry": {"coordinates":[-70.934,41.610696],"type":"Point"}
}