{
  "type": "Feature",
  "properties": {
    "addr:full":"63 Exchange St Malden MA 02148",
    "addr:housenumber":"63",
    "addr:postcode":"02148",
    "addr:street":"Exchange St",
    "iso:country":"US",
    "sg:address":"63 Exchange St",
    "sg:city":"Malden",
    "sg:classifiers":[
        {
            "category":"Shopping",
            "subcategory":"Clothing, Apparel, & Fashions",
            "type":"Retail Goods"
        }
    ],
    "sg:phone":"+1 781 324 3844",
    "sg:postcode":"02148",
    "sg:province":"MA",
    "wof:name":"Styles",
    "wof:placetype":"venue"
},
  "geometry": {"coordinates":[-71.069456,42.426425],"type":"Point"}
}