{
  "type": "Feature",
  "properties": {
    "iso:country":"US",
    "sg:address":"11 Crosby Rd",
    "sg:city":"Grafton",
    "sg:classifiers":[
        {
            "category":"Professional",
            "subcategory":"Business Services",
            "type":"Services"
        }
    ],
    "sg:phone":"+1   ",
    "sg:postcode":"01519",
    "sg:province":"MA",
    "wof:name":"Maxton Technology Inc",
    "wof:placetype":"venue"
},
  "geometry": {"coordinates":[-71.702129,42.2086],"type":"Point"}
}