{
  "type": "Feature",
  "properties": {
    "addr:full":"683 Main Rd Westport MA 02790",
    "addr:housenumber":"683",
    "addr:postcode":"02790",
    "addr:street":"Main Rd",
    "iso:country":"US",
    "sg:address":"683 Main Rd",
    "sg:city":"Westport",
    "sg:classifiers":[
        {
            "category":"Professional",
            "subcategory":"Lawyer & Legal Services",
            "type":"Services"
        }
    ],
    "sg:phone":"+1 508 636 6992",
    "sg:postcode":"02790",
    "sg:province":"MA",
    "sg:tags":[
        "attorney"
    ],
    "wof:name":"Carlton Realty",
    "wof:placetype":"venue"
},
  "geometry": {"coordinates":[-71.08835999999999,41.585302],"type":"Point"}
}