{
  "type": "Feature",
  "properties": {
    "addr:full": "116 June St Worcester MA 01602",
    "addr:housenumber": "116",
    "addr:postcode": "01602",
    "addr:street": "June St",
    "iso:country": "US",
    "sg:address": "116 June St",
    "sg:city": "Worcester",
    "sg:classifiers": [
      {
        "category": "Personal",
        "subcategory": "Beauty Salon",
        "type": "Services"
      }
    ],
    "sg:phone": "+1 508 752 6414",
    "sg:postcode": "01602",
    "sg:province": "MA",
    "wof:name": "Paul's Hair Design",
    "wof:placetype": "venue"
  },
  "geometry": {"coordinates":[-71.833308,42.264303],"type":"Point"}
}
