{
  "type": "Feature",
  "properties": {
    "addr:full":"209 Worcester Rd Sterling MA 01564",
    "addr:housenumber":"209",
    "addr:postcode":"01564",
    "addr:street":"Worcester Rd",
    "iso:country":"US",
    "sg:address":"209 Worcester Rd",
    "sg:city":"Sterling",
    "sg:classifiers":[
        {
            "category":"Retail",
            "subcategory":"Auto Repair",
            "type":"Services"
        }
    ],
    "sg:phone":"+1 978 422 7222",
    "sg:postcode":"01564",
    "sg:province":"MA",
    "sg:tags":[
        "muffler",
        "exhaust",
        "system"
    ],
    "wof:name":"Worcester Street Garage",
    "wof:placetype":"venue"
},
  "geometry": {"coordinates":[-71.770202,42.426692],"type":"Point"}
}