{
  "type": "Feature",
  "properties": {
    "addr:full": "967 East St Ludlow MA 01056",
    "addr:housenumber": "967",
    "addr:postcode": "01056",
    "addr:street": "East St",
    "iso:country": "US",
    "ovtr:label": "Uncle Bob's General Store, 967 East St Ludlow MA US",
    "ovtr:similarity": 2.2231268882751465,
    "sg:address": "967 East St",
    "sg:city": "Ludlow",
    "sg:classifiers": [
      {
        "category": "Shopping",
        "subcategory": "Discount \u0026 Variety Stores",
        "type": "Retail Goods"
      }
    ],
    "sg:phone": "+1 413 583 6711",
    "sg:postcode": "01056",
    "sg:province": "MA",
    "sg:tags": [
      "merchandise",
      "general"
    ],
    "wof:name": "Uncle Bob's General Store",
    "wof:placetype": "venue"
  },
  "geometry": {"coordinates":[-72.44254,42.171317],"type":"Point"}
}
