{
  "type": "Feature",
  "properties": {
    "addr:full":"967 East St Ludlow MA 01056",
    "addr:housenumber":"967",
    "addr:postcode":"01056",
    "addr:street":"East St",
    "iso:country":"US",
    "sg:address":"967 East St",
    "sg:city":"Ludlow",
    "sg:classifiers":[
        {
            "category":"Shopping",
            "subcategory":"Discount & Variety Stores",
            "type":"Retail Goods"
        }
    ],
    "sg:phone":"+1 413 583 6711",
    "sg:postcode":"01056",
    "sg:province":"MA",
    "sg:tags":[
        "merchandise",
        "general"
    ],
    "wof:name":"Uncle Bob's General Store",
    "wof:placetype":"venue"
},
  "geometry": {"coordinates":[-72.44253999999999,42.171317],"type":"Point"}
}