{
  "type": "Feature",
  "properties": {
    "iso:country":"US",
    "sg:address":"35 Central St",
    "sg:city":"Stoneham",
    "sg:classifiers":[
        {
            "category":"Government",
            "subcategory":"Office",
            "type":"Public Place"
        }
    ],
    "sg:phone":"+1 781 279 2612",
    "sg:postcode":"02180",
    "sg:province":"MA",
    "sg:tags":[
        "village"
    ],
    "wof:name":"Stoneham Health Board",
    "wof:placetype":"venue"
},
  "geometry": {"coordinates":[-71.098884,42.480663],"type":"Point"}
}