{
  "type": "Feature",
  "properties": {
    "addr:full": "Cummings Center 100 Suite 244G Beverly MA 01915",
    "addr:housenumber": "100 suite 244g",
    "addr:postcode": "01915",
    "iso:country": "US",
    "sg:address": "Cummings Center 100 Suite 244G",
    "sg:city": "Beverly",
    "sg:classifiers": [
      {
        "category": "Professional",
        "subcategory": "Computer Services",
        "type": "Services"
      }
    ],
    "sg:phone": "+1 978 922 0684",
    "sg:postcode": "01915",
    "sg:province": "MA",
    "sg:website": "http://www.sionyx.com",
    "wof:name": "SiOnyx",
    "wof:placetype": "venue"
  },
  "geometry": {"coordinates":[-70.874174,42.611305],"type":"Point"}
}
