{
  "type": "Feature",
  "properties": {
    "addr:full": "427 Main St Haverhill MA 01830",
    "addr:housenumber": "427",
    "addr:postcode": "01830",
    "addr:street": "Main St",
    "iso:country": "US",
    "sg:address": "427 Main St",
    "sg:city": "Haverhill",
    "sg:classifiers": [
      {
        "category": "Banks \u0026 Credit Unions",
        "subcategory": "Bank",
        "type": "Services"
      }
    ],
    "sg:phone": "+1 978 373 3840",
    "sg:postcode": "01830",
    "sg:province": "MA",
    "wof:name": "Haverhill Credit Union",
    "wof:placetype": "venue"
  },
  "geometry": {"coordinates":[-71.07944,42.785192],"type":"Point"}
}
