{
  "type": "Feature",
  "properties": {
    "iso:country":"US",
    "sg:address":"301 Moosehill Rd",
    "sg:city":"East Walpole",
    "sg:classifiers":[
        {
            "category":"Building & Trades",
            "subcategory":"Construction",
            "type":"Services"
        }
    ],
    "sg:phone":"+1   ",
    "sg:postcode":"02032",
    "sg:province":"MA",
    "sg:tags":[
        "hanging",
        "contractor"
    ],
    "wof:name":"Endicott Painting",
    "wof:placetype":"venue"
},
  "geometry": {"coordinates":[-71.212354,42.144275],"type":"Point"}
}