{
  "type": "Feature",
  "properties": {
    "iso:country":"US",
    "sg:address":"1637 Main St",
    "sg:city":"Brockton",
    "sg:classifiers":[
        {
            "category":"Autos & Motor Vehicles",
            "subcategory":"Automobile Sales",
            "type":"Retail Goods"
        }
    ],
    "sg:phone":"+1 508 583 5339",
    "sg:postcode":"02301",
    "sg:province":"MA",
    "sg:tags":[
        "car",
        "dealer"
    ],
    "wof:name":"House Of Wheels",
    "wof:placetype":"venue"
},
  "geometry": {"coordinates":[-71.011646,42.05302],"type":"Point"}
}