{
  "type": "Feature",
  "properties": {
    "iso:country":"US",
    "sg:address":"387 Nantasket Ave",
    "sg:city":"Hull",
    "sg:classifiers":[
        {
            "category":"Building & Trades",
            "subcategory":"Construction",
            "type":"Services"
        }
    ],
    "sg:phone":"+1 781 925 5383",
    "sg:postcode":"02045",
    "sg:province":"MA",
    "sg:tags":[
        "hanging",
        "painter",
        "contractor"
    ],
    "wof:name":"Reilly Renovations",
    "wof:placetype":"venue"
},
  "geometry": {"coordinates":[-70.868178,42.278961],"type":"Point"}
}