{
  "type": "Feature",
  "properties": {
    "addr:full":"12 Salem St Ste 6 Lynnfield MA 01940",
    "addr:housenumber":"12",
    "addr:postcode":"01940",
    "addr:street":"Salem St Ste 6",
    "iso:country":"US",
    "sg:address":"12 Salem St Ste 6",
    "sg:city":"Lynnfield",
    "sg:classifiers":[
        {
            "category":"Restaurant",
            "type":"Food & Drink"
        }
    ],
    "sg:phone":"+1 781 213 1133",
    "sg:postcode":"01940",
    "sg:province":"MA",
    "wof:name":"Emerald Dragon",
    "wof:placetype":"venue"
},
  "geometry": {"coordinates":[-71.03639200000001,42.511742],"type":"Point"}
}