{
  "type": "Feature",
  "properties": {
    "iso:country":"US",
    "sg:address":"889 Main St",
    "sg:city":"Waltham",
    "sg:classifiers":[
        {
            "category":"Restaurant",
            "type":"Food & Drink"
        }
    ],
    "sg:menulink":"http://www.allmenus.com/ma/waltham/151098-lenas/menu/",
    "sg:phone":"+1 781 891 1270",
    "sg:postcode":"02451",
    "sg:province":"MA",
    "sg:tags":[
        "american",
        "pizza"
    ],
    "wof:name":"Lena's",
    "wof:placetype":"venue"
},
  "geometry": {"coordinates":[-71.24669900000001,42.376279],"type":"Point"}
}