{
  "type": "Feature",
  "properties": {
    "addr:full": "889 Main St Waltham MA 02451",
    "addr:housenumber": "889",
    "addr:postcode": "02451",
    "addr:street": "Main St",
    "iso:country": "US",
    "ovtr:label": "Lena's, 889 Main St Waltham MA US",
    "ovtr:similarity": 2.141839027404785,
    "sg:address": "889 Main St",
    "sg:city": "Waltham",
    "sg:classifiers": [
      {
        "category": "Restaurant",
        "type": "Food \u0026 Drink"
      }
    ],
    "sg:menulink": "http://www.allmenus.com/ma/waltham/151098-lenas/menu/",
    "sg:phone": "+1 781 891 1270",
    "sg:postcode": "02451",
    "sg:province": "MA",
    "sg:tags": [
      "american",
      "pizza"
    ],
    "wof:name": "Lena's",
    "wof:placetype": "venue"
  },
  "geometry": {"coordinates":[-71.246699,42.376279],"type":"Point"}
}
