{
  "type": "Feature",
  "properties": {
    "addr:full": "150 Main St Buzzards Bay MA 02532",
    "addr:housenumber": "150",
    "addr:postcode": "02532",
    "addr:street": "Main St",
    "iso:country": "US",
    "ovtr:label": "The Liquor Barn, 150 Main St Buzzards Bay MA US",
    "ovtr:similarity": 3.226978063583374,
    "sg:address": "150 Main St",
    "sg:city": "Buzzards Bay",
    "sg:classifiers": [
      {
        "category": "Food \u0026 Beverages",
        "subcategory": "Liquor \u0026 Beverages",
        "type": "Retail Goods"
      }
    ],
    "sg:phone": "+1 508 759 9933",
    "sg:postcode": "02532",
    "sg:province": "MA",
    "sg:tags": [
      "beer",
      "spirit",
      "wine"
    ],
    "wof:name": "Liquor Barn the",
    "wof:placetype": "venue"
  },
  "geometry": {"coordinates":[-70.610298,41.746201],"type":"Point"}
}
