{
  "type": "Feature",
  "properties": {
    "addr:full":"483 Broadway Everett MA 02149",
    "addr:housenumber":"483",
    "addr:postcode":"02149",
    "addr:street":"Broadway",
    "iso:country":"US",
    "sg:address":"483 Broadway",
    "sg:city":"Everett",
    "sg:classifiers":[
        {
            "category":"Government",
            "subcategory":"Fire Station",
            "type":"Public Place"
        }
    ],
    "sg:phone":"+1 617 387 7198",
    "sg:postcode":"02149",
    "sg:province":"MA",
    "sg:tags":[
        "department"
    ],
    "wof:name":"Everett Fire Dept",
    "wof:placetype":"venue"
},
  "geometry": {"coordinates":[-71.05418899999999,42.408496],"type":"Point"}
}