{
  "type": "Feature",
  "properties": {
    "iso:country":"US",
    "sg:address":"1 Oxford St",
    "sg:city":"Cambridge",
    "sg:classifiers":[
        {
            "category":"Education",
            "subcategory":"Library",
            "type":"Public Place"
        }
    ],
    "sg:phone":"+1 617 495 5496",
    "sg:postcode":"02138",
    "sg:province":"MA",
    "sg:tags":[
        "special",
        "interest"
    ],
    "sg:website":"www.stat.harvard.edu",
    "wof:name":"Statistics Dept",
    "wof:placetype":"venue"
},
  "geometry": {"coordinates":[-71.11657599999999,42.379011],"type":"Point"}
}