{
  "type": "Feature",
  "properties": {
    "addr:full": "10 Fairway St Ste 222 Mattapan MA 02126",
    "addr:housenumber": "10",
    "addr:postcode": "02126",
    "addr:street": "Fairway St Ste 222",
    "iso:country": "US",
    "sg:address": "10 Fairway St Ste 222",
    "sg:city": "Mattapan",
    "sg:classifiers": [
      {
        "category": "Communications",
        "subcategory": "Radio Station",
        "type": "Services"
      }
    ],
    "sg:phone": "+1 617 296 8649",
    "sg:postcode": "02126",
    "sg:province": "MA",
    "sg:tags": [
      "broadcast"
    ],
    "sg:website": "http://www.echoevangelique.org",
    "wof:name": "Echo Evangelique Radio",
    "wof:placetype": "venue"
  },
  "geometry": {"coordinates":[-71.095298,42.268428],"type":"Point"}
}
