{
  "type": "Feature",
  "properties": {
    "addr:full": "1 Thompson Sq Charlestown MA 02129",
    "addr:housenumber": "1",
    "addr:postcode": "02129",
    "addr:street": "Thompson Sq",
    "iso:country": "US",
    "sg:address": "1 Thompson Sq",
    "sg:city": "Charlestown",
    "sg:classifiers": [
      {
        "category": "Shopping",
        "subcategory": "Florist",
        "type": "Retail Goods"
      }
    ],
    "sg:phone": "+1 617 242 2124",
    "sg:postcode": "02129",
    "sg:province": "MA",
    "wof:name": "Bunker Hill Florist",
    "wof:placetype": "venue"
  },
  "geometry": {"coordinates":[-71.063111,42.374706],"type":"Point"}
}
