{
  "type": "Feature",
  "properties": {
    "iso:country":"US",
    "sg:address":"1 Thompson Sq",
    "sg:city":"Charlestown",
    "sg:classifiers":[
        {
            "category":"Shopping",
            "subcategory":"Florist",
            "type":"Retail Goods"
        }
    ],
    "sg:phone":"+1 617 242 2124",
    "sg:postcode":"02129",
    "sg:province":"MA",
    "wof:name":"Bunker Hill Florist",
    "wof:placetype":"venue"
},
  "geometry": {"coordinates":[-71.06311100000001,42.374706],"type":"Point"}
}