{
  "type": "Feature",
  "properties": {
    "iso:country":"US",
    "sg:address":"8 Industrial Pkwy",
    "sg:city":"Woburn",
    "sg:classifiers":[
        {
            "category":"Building & Trades",
            "subcategory":"Pest Control",
            "type":"Services"
        }
    ],
    "sg:phone":"+1 978 777 6076",
    "sg:postcode":"01801",
    "sg:province":"MA",
    "wof:name":"Orkin Exterminating Co Inc",
    "wof:placetype":"venue"
},
  "geometry": {"coordinates":[-71.14180500000001,42.505271],"type":"Point"}
}