{
  "type": "Feature",
  "properties": {
    "addr:full": "8 Industrial Pkwy Woburn MA 01801",
    "addr:housenumber": "8",
    "addr:postcode": "01801",
    "addr:street": "Industrial Pkwy",
    "iso:country": "US",
    "sg:address": "8 Industrial Pkwy",
    "sg:city": "Woburn",
    "sg:classifiers": [
      {
        "category": "Building \u0026 Trades",
        "subcategory": "Pest Control",
        "type": "Services"
      }
    ],
    "sg:phone": "+1 978 777 6076",
    "sg:postcode": "01801",
    "sg:province": "MA",
    "wof:name": "Orkin Exterminating Co Inc",
    "wof:placetype": "venue"
  },
  "geometry": {"coordinates":[-71.141805,42.505271],"type":"Point"}
}
