{
  "type": "Feature",
  "properties": {
    "iso:country":"US",
    "sg:address":"125 George St",
    "sg:city":"Somerset",
    "sg:classifiers":[
        {
            "category":"Building & Trades",
            "subcategory":"Construction",
            "type":"Services"
        }
    ],
    "sg:phone":"+1 508 677 2250",
    "sg:postcode":"02726",
    "sg:province":"MA",
    "sg:tags":[
        "painter"
    ],
    "wof:name":"D & D Sandblasting",
    "wof:placetype":"venue"
},
  "geometry": {"coordinates":[-71.15732199999999,41.736373],"type":"Point"}
}