{
  "type": "Feature",
  "properties": {
    "iso:country":"US",
    "sg:address":"433 Springfield St",
    "sg:city":"Agawam",
    "sg:classifiers":[
        {
            "category":"Insurance",
            "subcategory":"Insurance Agent",
            "type":"Services"
        }
    ],
    "sg:phone":"+1 413 786 0797",
    "sg:postcode":"01001",
    "sg:province":"MA",
    "wof:name":"Southwick Insurance Agency",
    "wof:placetype":"venue"
},
  "geometry": {"coordinates":[-72.64375800000001,42.084834],"type":"Point"}
}