{
  "type": "Feature",
  "properties": {
    "addr:full":"25 Main St Stockbridge MA 01262",
    "addr:housenumber":"25",
    "addr:postcode":"01262",
    "addr:street":"Main St",
    "iso:country":"US",
    "sg:address":"25 Main St",
    "sg:city":"Stockbridge",
    "sg:classifiers":[
        {
            "category":"Health Services",
            "subcategory":"Hospital",
            "type":"Services"
        }
    ],
    "sg:phone":"+1 413 298 5511",
    "sg:postcode":"01262",
    "sg:province":"MA",
    "sg:tags":[
        "mental"
    ],
    "sg:website":"www.austenriggs.org",
    "wof:name":"Austen Riggs Ctr",
    "wof:placetype":"venue"
},
  "geometry": {"coordinates":[-73.312527,42.282446],"type":"Point"}
}