{
  "type": "Feature",
  "properties": {
    "iso:country":"US",
    "sg:address":"242 Quincy Shore Dr",
    "sg:city":"Quincy",
    "sg:classifiers":[
        {
            "category":"Shopping",
            "subcategory":"Used Merchandise",
            "type":"Retail Goods"
        }
    ],
    "sg:phone":"+1   ",
    "sg:postcode":"02171",
    "sg:province":"MA",
    "wof:name":"Fair Shops",
    "wof:placetype":"venue"
},
  "geometry": {"coordinates":[-71.030304,42.284745],"type":"Point"}
}