{
  "type": "Feature",
  "properties": {
    "iso:country":"US",
    "sg:address":"10 Tremont Street",
    "sg:city":"Boston",
    "sg:classifiers":[
        {
            "category":"Professional",
            "subcategory":"Lawyer & Legal Services",
            "type":"Services"
        }
    ],
    "sg:phone":"+1 617 720 6040",
    "sg:postcode":"02108",
    "sg:province":"MA",
    "sg:tags":[
        "attorney",
        "practice"
    ],
    "wof:name":"Bove & Langa PC Law Offices of",
    "wof:placetype":"venue"
},
  "geometry": {"coordinates":[-71.05969399999999,42.359064],"type":"Point"}
}