{
  "type": "Feature",
  "properties": {
    "iso:country":"US",
    "sg:address":"980 Washington St",
    "sg:city":"Dedham",
    "sg:classifiers":[
        {
            "category":"Insurance",
            "subcategory":"Insurance Agent",
            "type":"Services"
        }
    ],
    "sg:phone":"+1 781 329 8200",
    "sg:postcode":"02026",
    "sg:province":"MA",
    "wof:name":"Cubell Associates",
    "wof:placetype":"venue"
},
  "geometry": {"coordinates":[-71.18563399999999,42.229879],"type":"Point"}
}