{
  "type": "Feature",
  "properties": {
    "addr:full": "32 Hull St Lynn MA 01984",
    "addr:housenumber": "32",
    "addr:postcode": "01984",
    "addr:street": "Hull St",
    "iso:country": "US",
    "sg:address": "32 Hull St",
    "sg:city": "Lynn",
    "sg:classifiers": [
      {
        "category": "Social Services",
        "subcategory": "Adult Care",
        "type": "Services"
      }
    ],
    "sg:phone": "+1 781 599 0246",
    "sg:postcode": "01984",
    "sg:province": "MA",
    "sg:tags": [
      "home",
      "residential"
    ],
    "wof:name": "St Theresa Home",
    "wof:placetype": "venue"
  },
  "geometry": {"coordinates":[-70.829016,42.585576],"type":"Point"}
}
