{
  "type": "Feature",
  "properties": {
    "addr:full":"37 Washington St Natick MA 01760",
    "addr:housenumber":"37",
    "addr:postcode":"01760",
    "addr:street":"Washington St",
    "iso:country":"US",
    "sg:address":"37 Washington St",
    "sg:city":"Natick",
    "sg:classifiers":[
        {
            "category":"Organizations",
            "subcategory":"Religious Organization",
            "type":"Services"
        }
    ],
    "sg:phone":"+1   ",
    "sg:postcode":"01760",
    "sg:province":"MA",
    "wof:name":"Alban Orthdx CHR Annunctn",
    "wof:placetype":"venue"
},
  "geometry": {"coordinates":[-71.346825,42.287187],"type":"Point"}
}