{
  "type": "Feature",
  "properties": {
    "addr:full": "289 Westford St Lowell MA 01851",
    "addr:housenumber": "289",
    "addr:postcode": "01851",
    "addr:street": "Westford St",
    "iso:country": "US",
    "sg:address": "289 Westford St",
    "sg:city": "Lowell",
    "sg:classifiers": [
      {
        "category": "Food \u0026 Beverages",
        "subcategory": "Groceries \u0026 Convenience Stores",
        "type": "Retail Goods"
      }
    ],
    "sg:phone": "+1 978 452 7391",
    "sg:postcode": "01851",
    "sg:province": "MA",
    "sg:tags": [
      "market"
    ],
    "wof:name": "Hong Kong Market",
    "wof:placetype": "venue"
  },
  "geometry": {"coordinates":[-71.325437,42.635465],"type":"Point"}
}
