{
  "type": "Feature",
  "properties": {
    "iso:country":"US",
    "sg:address":"230 Congress St",
    "sg:city":"Boston",
    "sg:classifiers":[
        {
            "category":"Communications",
            "type":"Services"
        },
        {
            "category":"Professional",
            "subcategory":"Management & Consulting",
            "type":"Services"
        }
    ],
    "sg:phone":"+1 617 532 3200",
    "sg:postcode":"02110",
    "sg:province":"MA",
    "sg:tags":[
        "business"
    ],
    "sg:website":"www.paetec.com",
    "wof:name":"Paetec Communications Inc",
    "wof:placetype":"venue"
},
  "geometry": {"coordinates":[-71.054261,42.354502],"type":"Point"}
}