{
  "type": "Feature",
  "properties": {
    "addr:full":"15 Mendon St Uxbridge MA 01569",
    "addr:housenumber":"15",
    "addr:postcode":"01569",
    "addr:street":"Mendon St",
    "iso:country":"US",
    "sg:address":"15 Mendon St",
    "sg:city":"Uxbridge",
    "sg:classifiers":[
        {
            "category":"Shopping",
            "subcategory":"Computers & Home Electronics",
            "type":"Retail Goods"
        }
    ],
    "sg:phone":"+1 508 278 3505",
    "sg:postcode":"01569",
    "sg:province":"MA",
    "sg:tags":[
        "software"
    ],
    "sg:website":"www.act-networks.com",
    "wof:name":"Applied Computer",
    "wof:placetype":"venue"
},
  "geometry": {"coordinates":[-71.62854799999999,42.076484],"type":"Point"}
}