{
  "type": "Feature",
  "properties": {
    "addr:full":"41 Union Point Rd Webster MA 01570",
    "addr:housenumber":"41",
    "addr:postcode":"01570",
    "addr:street":"Union Point Rd",
    "iso:country":"US",
    "sg:address":"41 Union Point Rd",
    "sg:city":"Webster",
    "sg:classifiers":[
        {
            "category":"Personal",
            "subcategory":"Beauty Salon",
            "type":"Services"
        }
    ],
    "sg:phone":"+1 508 943 1905",
    "sg:postcode":"01570",
    "sg:province":"MA",
    "wof:name":"Barbara's Beauty Salon",
    "wof:placetype":"venue"
},
  "geometry": {"coordinates":[-71.855676,42.039905],"type":"Point"}
}