{
  "type": "Feature",
  "properties": {
    "addr:full": "1211 Washington St Newton MA 02465",
    "addr:housenumber": "1211",
    "addr:postcode": "02465",
    "addr:street": "Washington St",
    "iso:country": "US",
    "sg:address": "1211 Washington St",
    "sg:city": "Newton",
    "sg:phone": "+1 617 964 4430",
    "sg:postcode": "02465",
    "sg:province": "MA",
    "sg:tags": [
      "oil"
    ],
    "wof:name": "Radiant Fuel Plumbing \u0026 Heat",
    "wof:placetype": "venue"
  },
  "geometry": {"coordinates":[-71.22406,42.349329],"type":"Point"}
}
