{
  "type": "Feature",
  "properties": {
    "addr:full":"41 Union St Holbrook MA 02343",
    "addr:housenumber":"41",
    "addr:postcode":"02343",
    "addr:street":"Union St",
    "iso:country":"US",
    "sg:address":"41 Union St",
    "sg:city":"Holbrook",
    "sg:classifiers":[
        {
            "category":"Personal",
            "subcategory":"Beauty Salon",
            "type":"Services"
        }
    ],
    "sg:phone":"+1 781 767 2783",
    "sg:postcode":"02343",
    "sg:province":"MA",
    "sg:tags":[
        "manicuring"
    ],
    "wof:name":"Holbrook Nail Shop",
    "wof:placetype":"venue"
},
  "geometry": {"coordinates":[-71.01049399999999,42.154775],"type":"Point"}
}