{
  "type": "Feature",
  "properties": {
    "addr:full": "2 Etta Rd Billerica MA 01821",
    "addr:housenumber": "2",
    "addr:postcode": "01821",
    "addr:street": "Etta Rd",
    "iso:country": "US",
    "sg:address": "2 Etta Rd",
    "sg:city": "Billerica",
    "sg:classifiers": [
      {
        "category": "Professional",
        "subcategory": "Management \u0026 Consulting",
        "type": "Services"
      }
    ],
    "sg:phone": "+1   ",
    "sg:postcode": "01821",
    "sg:province": "MA",
    "sg:tags": [
      "business"
    ],
    "wof:name": "Automotive Service Analysts",
    "wof:placetype": "venue"
  },
  "geometry": {"coordinates":[-71.278295,42.564168],"type":"Point"}
}
