{
  "type": "Feature",
  "properties": {
    "addr:full": "4 Canal St Danvers MA 01923",
    "addr:housenumber": "4",
    "addr:postcode": "01923",
    "addr:street": "Canal St",
    "iso:country": "US",
    "sg:address": "4 Canal St",
    "sg:city": "Danvers",
    "sg:classifiers": [
      {
        "category": "Manufacturing",
        "subcategory": "Tools \u0026 Machinery",
        "type": "Manufacturing \u0026 Wholesale Goods"
      }
    ],
    "sg:phone": "+1 978 774 1140",
    "sg:postcode": "01923",
    "sg:province": "MA",
    "sg:tags": [
      "machine",
      "shop"
    ],
    "wof:name": "Jones Machine Co",
    "wof:placetype": "venue"
  },
  "geometry": {"coordinates":[-70.93324,42.560197],"type":"Point"}
}
