{
  "type": "Feature",
  "properties": {
    "iso:country":"US",
    "sg:address":"95 Main Street",
    "sg:city":"Everett",
    "sg:classifiers":[
        {
            "category":"Sports & Exercise",
            "subcategory":"Gym",
            "type":"Entertainment"
        },
        {
            "category":"Health Services",
            "subcategory":"Dentist",
            "type":"Services"
        }
    ],
    "sg:phone":"+1 617 387 2233",
    "sg:postcode":"02149",
    "sg:province":"MA",
    "sg:tags":[
        "trainer"
    ],
    "wof:name":"Everett Dental Center DMD",
    "wof:placetype":"venue"
},
  "geometry": {"coordinates":[-71.061336,42.403882],"type":"Point"}
}