{
  "type": "Feature",
  "properties": {
    "addr:full":"89 New Ipswich Rd Ashby MA 01431",
    "addr:housenumber":"89",
    "addr:postcode":"01431",
    "addr:street":"New Ipswich Rd",
    "iso:country":"US",
    "sg:address":"89 New Ipswich Rd",
    "sg:city":"Ashby",
    "sg:classifiers":[
        {
            "category":"Professional",
            "subcategory":"Management & Consulting",
            "type":"Services"
        }
    ],
    "sg:phone":"+1 978 386 7171",
    "sg:postcode":"01431",
    "sg:province":"MA",
    "sg:tags":[
        "consultant",
        "business"
    ],
    "wof:name":"Richard W Mc Carthy & Assoc",
    "wof:placetype":"venue"
},
  "geometry": {"coordinates":[-71.818507,42.679606],"type":"Point"}
}