{
  "type": "Feature",
  "properties": {
    "addr:full":"167 Franklin St Framingham MA 01702",
    "addr:housenumber":"167",
    "addr:postcode":"01702",
    "addr:street":"Franklin St",
    "iso:country":"US",
    "sg:address":"167 Franklin St",
    "sg:city":"Framingham",
    "sg:classifiers":[
        {
            "category":"Taxi",
            "type":"Transportation"
        }
    ],
    "sg:phone":"+1 508 872 3500",
    "sg:postcode":"01702",
    "sg:province":"MA",
    "sg:tags":[
        "taxicab"
    ],
    "sg:website":"www.tommystaxicab.com",
    "wof:name":"Tommy's Taxi Inc",
    "wof:placetype":"venue"
},
  "geometry": {"coordinates":[-71.421299,42.282354],"type":"Point"}
}