{
  "type": "Feature",
  "properties": {
    "addr:full":"221 Essex St Salem MA 01970",
    "addr:housenumber":"221",
    "addr:postcode":"01970",
    "addr:street":"Essex St",
    "iso:country":"US",
    "sg:address":"221 Essex St",
    "sg:city":"Salem",
    "sg:classifiers":[
        {
            "category":"Manufacturing",
            "subcategory":"Printing",
            "type":"Manufacturing & Wholesale Goods"
        }
    ],
    "sg:phone":"+1 978 744 8868",
    "sg:postcode":"01970",
    "sg:province":"MA",
    "sg:tags":[
        "printer"
    ],
    "wof:name":"Digital Imaging Inc",
    "wof:placetype":"venue"
},
  "geometry": {"coordinates":[-70.895679,42.521432],"type":"Point"}
}