{
  "type": "Feature",
  "properties": {
    "addr:full": "347 Bolivar St Canton MA 02021",
    "addr:housenumber": "347",
    "addr:postcode": "02021",
    "addr:street": "Bolivar St",
    "iso:country": "US",
    "sg:address": "347 Bolivar St",
    "sg:city": "Canton",
    "sg:classifiers": [
      {
        "category": "Professional",
        "subcategory": "Advertising",
        "type": "Services"
      }
    ],
    "sg:phone": "+1 781 821 2569",
    "sg:postcode": "02021",
    "sg:province": "MA",
    "sg:tags": [
      "counselor"
    ],
    "sg:website": "www.dmsstrategies.com",
    "wof:name": "DMS Strategies",
    "wof:placetype": "venue"
  },
  "geometry": {"coordinates":[-71.137978,42.151977],"type":"Point"}
}
