{
  "type": "Feature",
  "properties": {
    "iso:country":"US",
    "sg:address":"347 Bolivar St",
    "sg:city":"Canton",
    "sg:classifiers":[
        {
            "category":"Professional",
            "subcategory":"Advertising",
            "type":"Services"
        }
    ],
    "sg:phone":"+1 781 821 2569",
    "sg:postcode":"02021",
    "sg:province":"MA",
    "sg:tags":[
        "counselor"
    ],
    "sg:website":"www.dmsstrategies.com",
    "wof:name":"DMS Strategies",
    "wof:placetype":"venue"
},
  "geometry": {"coordinates":[-71.137978,42.151977],"type":"Point"}
}