{
  "type": "Feature",
  "properties": {
    "iso:country":"US",
    "sg:address":"1089 Main St",
    "sg:city":"Holden",
    "sg:classifiers":[
        {
            "category":"Travel",
            "subcategory":"Travel Agent",
            "type":"Entertainment"
        }
    ],
    "sg:phone":"+1 508 829 7797",
    "sg:postcode":"01520",
    "sg:province":"MA",
    "sg:tags":[
        "agency",
        "bureau"
    ],
    "wof:name":"Global Incentives",
    "wof:placetype":"venue"
},
  "geometry": {"coordinates":[-71.860382,42.349871],"type":"Point"}
}