{
  "type": "Feature",
  "properties": {
    "addr:full":"1630 Hancock St Quincy MA 02169",
    "addr:housenumber":"1630",
    "addr:postcode":"02169",
    "addr:street":"Hancock St",
    "iso:country":"US",
    "sg:address":"1630 Hancock St",
    "sg:city":"Quincy",
    "sg:classifiers":[
        {
            "category":"Cinema",
            "subcategory":"Movie Rental",
            "type":"Entertainment"
        }
    ],
    "sg:phone":"+1 617 471 5055",
    "sg:postcode":"02169",
    "sg:province":"MA",
    "sg:tags":[
        "leasing",
        "video",
        "disc",
        "tape"
    ],
    "sg:website":"www.blockbuster.com",
    "wof:name":"Blockbuster Video",
    "wof:placetype":"venue"
},
  "geometry": {"coordinates":[-71.00069000000001,42.246631],"type":"Point"}
}