{
  "type": "Feature",
  "properties": {
    "iso:country":"US",
    "sg:address":"54 Dwight St",
    "sg:city":"Boston",
    "sg:classifiers":[
        {
            "category":"Arts & Performance",
            "subcategory":"Theater",
            "type":"Entertainment"
        }
    ],
    "sg:phone":"+1   ",
    "sg:postcode":"02118",
    "sg:province":"MA",
    "sg:tags":[
        "theatrical"
    ],
    "wof:name":"Play Ground Childrens Theater",
    "wof:placetype":"venue"
},
  "geometry": {"coordinates":[-71.069621,42.344446],"type":"Point"}
}