{
  "type": "Feature",
  "properties": {
    "addr:full":"26 Dibuono Dr Marlborough MA 01752",
    "addr:housenumber":"26",
    "addr:postcode":"01752",
    "addr:street":"Dibuono Dr",
    "iso:country":"US",
    "sg:address":"26 Dibuono Dr",
    "sg:city":"Marlborough",
    "sg:classifiers":[
        {
            "category":"Wholesale",
            "subcategory":"Apparel",
            "type":"Manufacturing & Wholesale Goods"
        }
    ],
    "sg:phone":"+1 508 303 6544",
    "sg:postcode":"01752",
    "sg:province":"MA",
    "sg:tags":[
        "shoes"
    ],
    "wof:name":"Sun Tec",
    "wof:placetype":"venue"
},
  "geometry": {"coordinates":[-71.583647,42.3434],"type":"Point"}
}