{
  "type": "Feature",
  "properties": {
    "iso:country":"US",
    "sg:address":"10 Marilyn Dr",
    "sg:city":"Wilbraham",
    "sg:classifiers":[
        {
            "category":"Real Estate",
            "subcategory":"Developer",
            "type":"Services"
        }
    ],
    "sg:phone":"+1 413 599 4992",
    "sg:postcode":"01095",
    "sg:province":"MA",
    "wof:name":"Bergeron Developers Inc",
    "wof:placetype":"venue"
},
  "geometry": {"coordinates":[-72.439038,42.139643],"type":"Point"}
}