{
  "type": "Feature",
  "properties": {
    "iso:country":"US",
    "sg:address":"56 Bennett St",
    "sg:city":"Brighton",
    "sg:classifiers":[
        {
            "category":"Personal",
            "subcategory":"Massage",
            "type":"Services"
        }
    ],
    "sg:phone":"+1 617 331 4488",
    "sg:postcode":"02135",
    "sg:province":"MA",
    "sg:website":"www.brightonmedicalmassage.com",
    "wof:name":"Brighton Medical Massage",
    "wof:placetype":"venue"
},
  "geometry": {"coordinates":[-71.15600000000001,42.3515],"type":"Point"}
}