{
  "type": "Feature",
  "properties": {
    "iso:country":"US",
    "sg:address":"710 Waverly St",
    "sg:city":"Framingham",
    "sg:classifiers":[
        {
            "category":"Shopping",
            "subcategory":"Gifts & Souvenirs",
            "type":"Retail Goods"
        }
    ],
    "sg:phone":"+1 508 872 6695",
    "sg:postcode":"01702",
    "sg:province":"MA",
    "sg:tags":[
        "shop"
    ],
    "wof:name":"Perfect Presents",
    "wof:placetype":"venue"
},
  "geometry": {"coordinates":[-71.428844,42.272231],"type":"Point"}
}