{
  "type": "Feature",
  "properties": {
    "addr:full":"134 Magazine St Cambridge MA 02139",
    "addr:housenumber":"134",
    "addr:postcode":"02139",
    "addr:street":"Magazine St",
    "iso:country":"US",
    "sg:address":"134 Magazine St",
    "sg:city":"Cambridge",
    "sg:classifiers":[
        {
            "category":"Museum",
            "type":"Entertainment"
        }
    ],
    "sg:phone":"+1 617 372 4403",
    "sg:postcode":"02139",
    "sg:province":"MA",
    "wof:name":"Science Club For Girls, Inc.",
    "wof:placetype":"venue"
},
  "geometry": {"coordinates":[-71.111383,42.358827],"type":"Point"}
}