{
  "type": "Feature",
  "properties": {
    "addr:full":"5 Vale St Fall River MA 02724",
    "addr:housenumber":"5",
    "addr:postcode":"02724",
    "addr:street":"Vale St",
    "iso:country":"US",
    "sg:address":"5 Vale St",
    "sg:city":"Fall River",
    "sg:classifiers":[
        {
            "category":"Retail",
            "subcategory":"Auto Repair",
            "type":"Services"
        }
    ],
    "sg:phone":"+1 508 672 0840",
    "sg:postcode":"02724",
    "sg:province":"MA",
    "sg:tags":[
        "body",
        "automobile",
        "painting"
    ],
    "wof:name":"Modern Auto Body & Sales",
    "wof:placetype":"venue"
},
  "geometry": {"coordinates":[-71.16476900000001,41.687008],"type":"Point"}
}