{
  "type": "Feature",
  "properties": {
    "iso:country":"US",
    "sg:address":"7 High St",
    "sg:city":"Salem",
    "sg:classifiers":[
        {
            "category":"Building & Trades",
            "subcategory":"Cleaning & Sanitation",
            "type":"Services"
        }
    ],
    "sg:phone":"+1 978 745 2058",
    "sg:postcode":"01970",
    "sg:province":"MA",
    "sg:tags":[
        "cleaners-interior"
    ],
    "wof:name":"Clean All Co",
    "wof:placetype":"venue"
},
  "geometry": {"coordinates":[-70.89672899999999,42.518826],"type":"Point"}
}