{
  "type": "Feature",
  "properties": {
    "iso:country":"US",
    "sg:address":"621 Boston Post Rd",
    "sg:city":"Sudbury",
    "sg:classifiers":[
        {
            "category":"Cafe",
            "type":"Food & Drink"
        },
        {
            "category":"Restaurant",
            "type":"Food & Drink"
        }
    ],
    "sg:menulink":"http://www.allmenus.com/ma/sudbury/43610-fugakyu-cafe/menu/",
    "sg:phone":"+1 978 443 1668",
    "sg:postcode":"01776",
    "sg:province":"MA",
    "sg:tags":[
        "japanese",
        "asian"
    ],
    "wof:name":"Fugakyu Cafe",
    "wof:placetype":"venue"
},
  "geometry": {"coordinates":[-71.439381,42.360433],"type":"Point"}
}