{
  "type": "Feature",
  "properties": {
    "addr:full": "621 Boston Post Rd Sudbury MA 01776",
    "addr:housenumber": "621",
    "addr:postcode": "01776",
    "addr:street": "Boston Post Rd",
    "iso:country": "US",
    "ovtr:label": "Fugakyu Cafe, 621 Boston Post Rd Sudbury MA US",
    "ovtr:similarity": 2.25451397895813,
    "sg:address": "621 Boston Post Rd",
    "sg:city": "Sudbury",
    "sg:classifiers": [
      {
        "category": "Cafe",
        "type": "Food \u0026 Drink"
      },
      {
        "category": "Restaurant",
        "type": "Food \u0026 Drink"
      }
    ],
    "sg:menulink": "http://www.allmenus.com/ma/sudbury/43610-fugakyu-cafe/menu/",
    "sg:phone": "+1 978 443 1668",
    "sg:postcode": "01776",
    "sg:province": "MA",
    "sg:tags": [
      "japanese",
      "asian"
    ],
    "wof:name": "Fugakyu Cafe",
    "wof:placetype": "venue"
  },
  "geometry": {"coordinates":[-71.439381,42.360433],"type":"Point"}
}
