{
  "type": "Feature",
  "properties": {
    "addr:full":"10 Huntington Ave Boston MA 02116",
    "addr:housenumber":"10",
    "addr:postcode":"02116",
    "addr:street":"Huntington Ave",
    "iso:country":"US",
    "sg:address":"10 Huntington Ave",
    "sg:city":"Boston",
    "sg:classifiers":[
        {
            "category":"Travel",
            "subcategory":"Hotels & Motels",
            "type":"Entertainment"
        },
        {
            "category":"Travel",
            "subcategory":"Resort",
            "type":"Entertainment"
        },
        {
            "category":"Sports & Exercise",
            "subcategory":"Ski Resort",
            "type":"Entertainment"
        }
    ],
    "sg:phone":"+1 617 262 9600",
    "sg:postcode":"02116",
    "sg:province":"MA",
    "sg:tags":[
        "corporate",
        "lodging"
    ],
    "sg:website":"www.westincopleyplaceboston.com/",
    "wof:name":"The Westin Copley Place",
    "wof:placetype":"venue"
},
  "geometry": {"coordinates":[-71.07758,42.348809],"type":"Point"}
}