{
  "type": "Feature",
  "properties": {
    "addr:full": "10 N Point Blvd Cambridge MA 02141",
    "addr:housenumber": "10",
    "addr:postcode": "02141",
    "addr:street": "N Point Blvd",
    "iso:country": "US",
    "sg:address": "10 N Point Blvd",
    "sg:city": "Cambridge",
    "sg:classifiers": [
      {
        "category": "Community Center",
        "type": "Public Place"
      }
    ],
    "sg:phone": "+1 617 727 1680",
    "sg:postcode": "02141",
    "sg:province": "MA",
    "sg:tags": [
      "recreation"
    ],
    "wof:name": "Department Of Conservation \u0026 Recreation",
    "wof:placetype": "venue"
  },
  "geometry": {"coordinates":[-71.070099,42.370024],"type":"Point"}
}
