{
  "type": "Feature",
  "properties": {
    "iso:country":"US",
    "sg:address":"10 N Point Blvd",
    "sg:city":"Cambridge",
    "sg:classifiers":[
        {
            "category":"Community Center",
            "type":"Public Place"
        }
    ],
    "sg:phone":"+1 617 727 1680",
    "sg:postcode":"02141",
    "sg:province":"MA",
    "sg:tags":[
        "recreation"
    ],
    "wof:name":"Department Of Conservation & Recreation",
    "wof:placetype":"venue"
},
  "geometry": {"coordinates":[-71.070099,42.370024],"type":"Point"}
}