{
  "type": "Feature",
  "properties": {
    "addr:full":"307 Nantasket Ave Hull MA 02045",
    "addr:housenumber":"307",
    "addr:postcode":"02045",
    "addr:street":"Nantasket Ave",
    "iso:country":"US",
    "sg:address":"307 Nantasket Ave",
    "sg:city":"Hull",
    "sg:classifiers":[
        {
            "category":"Restaurant",
            "type":"Food & Drink"
        }
    ],
    "sg:menulink":"http://www.allmenus.com/ma/hull/131853-subway/menu/",
    "sg:phone":"+1 781 925 3322",
    "sg:postcode":"02045",
    "sg:province":"MA",
    "sg:tags":[
        "american",
        "sandwich"
    ],
    "wof:name":"Subway",
    "wof:placetype":"venue"
},
  "geometry": {"coordinates":[-70.860499,42.273487],"type":"Point"}
}