{
  "type": "Feature",
  "properties": {
    "addr:full":"82 Crescent Ave Dorchester MA 02125",
    "addr:housenumber":"82",
    "addr:postcode":"02125",
    "addr:street":"Crescent Ave",
    "iso:country":"US",
    "sg:address":"82 Crescent Ave",
    "sg:city":"Dorchester",
    "sg:classifiers":[
        {
            "category":"Professional",
            "subcategory":"Business Services",
            "type":"Services"
        }
    ],
    "sg:phone":"+1 617 436 8333",
    "sg:postcode":"02125",
    "sg:province":"MA",
    "sg:tags":[
        "painter",
        "sign"
    ],
    "sg:website":"www.unerectors.com",
    "wof:name":"Unerectors Inc",
    "wof:placetype":"venue"
},
  "geometry": {"coordinates":[-71.052926,42.319264],"type":"Point"}
}