{
  "type": "Feature",
  "properties": {
    "iso:country":"US",
    "sg:address":"59 Dothan St",
    "sg:city":"Arlington",
    "sg:classifiers":[
        {
            "category":"Retail",
            "subcategory":"Repair Shop",
            "type":"Services"
        }
    ],
    "sg:phone":"+1 781 643 4460",
    "sg:postcode":"02474",
    "sg:province":"MA",
    "sg:tags":[
        "welding"
    ],
    "wof:name":"Allard Welding",
    "wof:placetype":"venue"
},
  "geometry": {"coordinates":[-71.178623,42.435867],"type":"Point"}
}