{
  "type": "Feature",
  "properties": {
    "addr:full": "180 Main St Bridgewater MA 02324",
    "addr:housenumber": "180",
    "addr:postcode": "02324",
    "addr:street": "Main St",
    "iso:country": "US",
    "sg:address": "180 Main St",
    "sg:city": "Bridgewater",
    "sg:classifiers": [
      {
        "category": "Personal",
        "subcategory": "Tanning Parlor",
        "type": "Services"
      }
    ],
    "sg:phone": "+1 508 697 9401",
    "sg:postcode": "02324",
    "sg:province": "MA",
    "sg:tags": [
      "salon"
    ],
    "wof:name": "Terri's Tanning \u0026 Boutiques",
    "wof:placetype": "venue"
  },
  "geometry": {"coordinates":[-70.979498,41.993969],"type":"Point"}
}
