{
  "type": "Feature",
  "properties": {
    "addr:full": "40 Oakland Rd Malden MA 02148",
    "addr:housenumber": "40",
    "addr:postcode": "02148",
    "addr:street": "Oakland Rd",
    "iso:country": "US",
    "sg:address": "40 Oakland Rd",
    "sg:city": "Malden",
    "sg:classifiers": [
      {
        "category": "Organizations",
        "subcategory": "Community Association",
        "type": "Services"
      }
    ],
    "sg:phone": "+1 781 321 0859",
    "sg:postcode": "02148",
    "sg:province": "MA",
    "sg:tags": [
      "club"
    ],
    "wof:name": "Italian American WW Veterans",
    "wof:placetype": "venue"
  },
  "geometry": {"coordinates":[-71.061247,42.435121],"type":"Point"}
}
