{
  "type": "Feature",
  "properties": {
    "iso:country":"US",
    "sg:address":"55 Massachusetts Ave",
    "sg:city":"Lexington",
    "sg:classifiers":[
        {
            "category":"Food & Beverages",
            "subcategory":"Liquor & Beverages",
            "type":"Retail Goods"
        },
        {
            "category":"Wholesale",
            "subcategory":"Wine & Distilled Alcoholic Beverages",
            "type":"Manufacturing & Wholesale Goods"
        }
    ],
    "sg:phone":"+1 781 862 0515",
    "sg:postcode":"02420",
    "sg:province":"MA",
    "sg:tags":[
        "broker"
    ],
    "wof:name":"Arborway Imports, Inc.",
    "wof:placetype":"venue"
},
  "geometry": {"coordinates":[-71.19341300000001,42.425522],"type":"Point"}
}