{
  "type": "Feature",
  "properties": {
    "addr:full": "55 Massachusetts Ave Lexington MA 02420",
    "addr:housenumber": "55",
    "addr:postcode": "02420",
    "addr:street": "Massachusetts Ave",
    "iso:country": "US",
    "sg:address": "55 Massachusetts Ave",
    "sg:city": "Lexington",
    "sg:classifiers": [
      {
        "category": "Food \u0026 Beverages",
        "subcategory": "Liquor \u0026 Beverages",
        "type": "Retail Goods"
      },
      {
        "category": "Wholesale",
        "subcategory": "Wine \u0026 Distilled Alcoholic Beverages",
        "type": "Manufacturing \u0026 Wholesale Goods"
      }
    ],
    "sg:phone": "+1 781 862 0515",
    "sg:postcode": "02420",
    "sg:province": "MA",
    "sg:tags": [
      "broker"
    ],
    "wof:name": "Arborway Imports, Inc.",
    "wof:placetype": "venue"
  },
  "geometry": {"coordinates":[-71.193413,42.425522],"type":"Point"}
}
