{
  "type": "Feature",
  "properties": {
    "addr:full": "82 Forest St Medford MA 02155",
    "addr:housenumber": "82",
    "addr:postcode": "02155",
    "addr:street": "Forest St",
    "iso:country": "US",
    "ovtr:label": "The Medford Center for Orthodontics and Pediatric Dentistry, 82 Forest St Medford MA US",
    "ovtr:similarity": 3.5001931190490723,
    "sg:address": "82 Forest St",
    "sg:city": "Medford",
    "sg:classifiers": [
      {
        "category": "Health Services",
        "subcategory": "Dentist",
        "type": "Services"
      }
    ],
    "sg:phone": "+1 781 396 1980",
    "sg:postcode": "02155",
    "sg:province": "MA",
    "sg:tags": [
      "orthodontist",
      "pediatric"
    ],
    "sg:website": "www.themedfordcenter.com",
    "wof:name": "The Medford Center for Orthodontics and Pediatric Dentistry",
    "wof:placetype": "venue"
  },
  "geometry": {"coordinates":[-71.108236,42.421356],"type":"Point"}
}
