{
  "type": "Feature",
  "properties": {
    "addr:full":"39 S Main St Middleton MA 01949",
    "addr:housenumber":"39",
    "addr:postcode":"01949",
    "addr:street":"S Main St",
    "iso:country":"US",
    "sg:address":"39 S Main St",
    "sg:city":"Middleton",
    "sg:classifiers":[
        {
            "category":"Government",
            "subcategory":"Post Office",
            "type":"Public Place"
        }
    ],
    "sg:phone":"+1 978 000 1111",
    "sg:postcode":"01949",
    "sg:province":"MA",
    "wof:name":"US Post Office",
    "wof:placetype":"venue"
},
  "geometry": {"coordinates":[-71.015107,42.593773],"type":"Point"}
}