{
  "type": "Feature",
  "properties": {
    "addr:full": "426 Adams St Dorchester MA 02122",
    "addr:housenumber": "426",
    "addr:postcode": "02122",
    "addr:street": "Adams St",
    "iso:country": "US",
    "sg:address": "426 Adams St",
    "sg:city": "Dorchester",
    "sg:classifiers": [
      {
        "category": "Professional",
        "subcategory": "Lawyer \u0026 Legal Services",
        "type": "Services"
      }
    ],
    "sg:phone": "+1 617 436 1207",
    "sg:postcode": "02122",
    "sg:province": "MA",
    "wof:name": "Nwogu Ezenwa",
    "wof:placetype": "venue"
  },
  "geometry": {"coordinates":[-71.056999,42.294102],"type":"Point"}
}
