{
  "type": "Feature",
  "properties": {
    "iso:country":"US",
    "sg:address":"426 Adams St",
    "sg:city":"Dorchester",
    "sg:classifiers":[
        {
            "category":"Professional",
            "subcategory":"Lawyer & Legal Services",
            "type":"Services"
        }
    ],
    "sg:phone":"+1 617 436 1207",
    "sg:postcode":"02122",
    "sg:province":"MA",
    "wof:name":"Nwogu Ezenwa",
    "wof:placetype":"venue"
},
  "geometry": {"coordinates":[-71.056999,42.294102],"type":"Point"}
}