{
  "type": "Feature",
  "properties": {
    "addr:full": "300 Longwood Avenue Boston MA 02115",
    "addr:housenumber": "300",
    "addr:postcode": "02115",
    "addr:street": "Longwood Avenue",
    "iso:country": "US",
    "sg:address": "300 Longwood Avenue",
    "sg:city": "Boston",
    "sg:classifiers": [
      {
        "category": "Health Services",
        "subcategory": "Doctor",
        "type": "Services"
      }
    ],
    "sg:phone": "+1 617 355 2932",
    "sg:postcode": "02115",
    "sg:province": "MA",
    "wof:name": "Atala Anthony MD",
    "wof:placetype": "venue"
  },
  "geometry": {"coordinates":[-71.104838,42.337778],"type":"Point"}
}
