{
  "type": "Feature",
  "properties": {
    "addr:full": "92 Mercury St Weymouth MA 02188",
    "addr:housenumber": "92",
    "addr:postcode": "02188",
    "addr:street": "Mercury St",
    "iso:country": "US",
    "sg:address": "92 Mercury St",
    "sg:city": "Weymouth",
    "sg:classifiers": [
      {
        "category": "Wholesale",
        "subcategory": "Machinery \u0026 Supplies",
        "type": "Manufacturing \u0026 Wholesale Goods"
      }
    ],
    "sg:phone": "+1 781 337 7263",
    "sg:postcode": "02188",
    "sg:province": "MA",
    "sg:tags": [
      "medical-cylinder",
      "bulk",
      "gas-industrial"
    ],
    "wof:name": "Ad Petro Gas Inc",
    "wof:placetype": "venue"
  },
  "geometry": {"coordinates":[-70.968597,42.184319],"type":"Point"}
}
