{
  "type": "Feature",
  "properties": {
    "iso:country":"US",
    "sg:address":"240 Bear Hill Rd",
    "sg:city":"Waltham",
    "sg:classifiers":[
        {
            "category":"Shopping",
            "subcategory":"Computers & Home Electronics",
            "type":"Retail Goods"
        }
    ],
    "sg:phone":"+1 781 890 4878",
    "sg:postcode":"02451",
    "sg:province":"MA",
    "sg:tags":[
        "software"
    ],
    "sg:website":"www.rcube.com",
    "wof:name":"R-Cube Technologies",
    "wof:placetype":"venue"
},
  "geometry": {"coordinates":[-71.265869,42.38668],"type":"Point"}
}