{
  "type": "Feature",
  "properties": {
    "iso:country":"US",
    "sg:address":"143 Cambridge St",
    "sg:city":"Lowell",
    "sg:classifiers":[
        {
            "category":"Building & Trades",
            "subcategory":"Construction",
            "type":"Services"
        }
    ],
    "sg:phone":"+1 978 452 2333",
    "sg:postcode":"01852",
    "sg:province":"MA",
    "sg:tags":[
        "painter"
    ],
    "wof:name":"Dunn-Rite Painting Co",
    "wof:placetype":"venue"
},
  "geometry": {"coordinates":[-71.314939,42.630197],"type":"Point"}
}