{
  "type": "Feature",
  "properties": {
    "addr:full": "10 Ware Rd Belchertown MA 01007",
    "addr:housenumber": "10",
    "addr:postcode": "01007",
    "addr:street": "Ware Rd",
    "iso:country": "US",
    "ovtr:label": "Devon Lane Power Equipment, 10 Ware Rd Belchertown MA US",
    "ovtr:similarity": 2.0559470653533936,
    "sg:address": "10 Ware Rd",
    "sg:city": "Belchertown",
    "sg:classifiers": [
      {
        "category": "Home \u0026 Garden",
        "subcategory": "Garden Supply",
        "type": "Retail Goods"
      }
    ],
    "sg:phone": "+1 413 323 5435",
    "sg:postcode": "01007",
    "sg:province": "MA",
    "sg:tags": [
      "renting",
      "equipment",
      "lawn",
      "mower"
    ],
    "sg:website": "http://www.stihldealer.net/default-dealer-041020.aspx",
    "wof:name": "Devon Lane Power Equipment",
    "wof:placetype": "venue"
  },
  "geometry": {"coordinates":[-72.389992,42.284359],"type":"Point"}
}
