{
  "type": "Feature",
  "properties": {
    "addr:full": "399 Clifton St Attleboro MA 02703",
    "addr:housenumber": "399",
    "addr:postcode": "02703",
    "addr:street": "Clifton St",
    "iso:country": "US",
    "sg:address": "399 Clifton St",
    "sg:city": "Attleboro",
    "sg:classifiers": [
      {
        "category": "Manufacturing",
        "subcategory": "Jewelry",
        "type": "Manufacturing \u0026 Wholesale Goods"
      }
    ],
    "sg:phone": "+1 508 695 3224",
    "sg:postcode": "02703",
    "sg:province": "MA",
    "sg:tags": [
      "casting"
    ],
    "wof:name": "Comcast-Community Casting Co",
    "wof:placetype": "venue"
  },
  "geometry": {"coordinates":[-71.309243,41.957757],"type":"Point"}
}
