{
  "type": "Feature",
  "properties": {
    "addr:full": "1287 Liberty St Springfield MA 01104",
    "addr:housenumber": "1287",
    "addr:postcode": "01104",
    "addr:street": "Liberty St",
    "iso:country": "US",
    "sg:address": "1287 Liberty St",
    "sg:city": "Springfield",
    "sg:classifiers": [
      {
        "category": "Restaurant",
        "type": "Food \u0026 Drink"
      }
    ],
    "sg:phone": "+1 413 733 5205",
    "sg:postcode": "01104",
    "sg:province": "MA",
    "wof:name": "Mykonos European Restaurant",
    "wof:placetype": "venue"
  },
  "geometry": {"coordinates":[-72.583525,42.136806],"type":"Point"}
}
