{
  "type": "Feature",
  "properties": {
    "addr:full": "60 Lithgow St Boston MA 02124",
    "addr:housenumber": "60",
    "addr:postcode": "02124",
    "addr:street": "Lithgow St",
    "iso:country": "US",
    "sg:address": "60 Lithgow St",
    "sg:city": "Boston",
    "sg:classifiers": [
      {
        "category": "Building \u0026 Trades",
        "subcategory": "Construction",
        "type": "Services"
      }
    ],
    "sg:phone": "+1   ",
    "sg:postcode": "02124",
    "sg:province": "MA",
    "sg:tags": [
      "residential"
    ],
    "wof:name": "Nihen Construction",
    "wof:placetype": "venue"
  },
  "geometry": {"coordinates":[-71.068173,42.290538],"type":"Point"}
}
