{
  "type": "Feature",
  "properties": {
    "iso:country":"US",
    "sg:address":"11 Rabbit Rd",
    "sg:city":"Salisbury",
    "sg:classifiers":[
        {
            "category":"Home & Garden",
            "subcategory":"Building Materials",
            "type":"Retail Goods"
        },
        {
            "category":"Building & Trades",
            "subcategory":"Construction",
            "type":"Services"
        }
    ],
    "sg:phone":"+1 978 465 2611",
    "sg:postcode":"01952",
    "sg:province":"MA",
    "sg:tags":[
        "concrete",
        "staining",
        "contractor"
    ],
    "wof:name":"Coated Concrete Critters",
    "wof:placetype":"venue"
},
  "geometry": {"coordinates":[-70.89910500000001,42.846592],"type":"Point"}
}