{
  "type": "Feature",
  "properties": {
    "iso:country":"US",
    "sg:address":"173 Cambridge St",
    "sg:city":"Boston",
    "sg:classifiers":[
        {
            "category":"Retail",
            "subcategory":"Laundry & Dry Cleaning",
            "type":"Services"
        }
    ],
    "sg:phone":"+1 617 523 8584",
    "sg:postcode":"02114",
    "sg:province":"MA",
    "sg:tags":[
        "cleaners"
    ],
    "sg:website":"www.sarni.com",
    "wof:name":"Sarni Cleaners Of Boston Inc",
    "wof:placetype":"venue"
},
  "geometry": {"coordinates":[-71.06598700000001,42.361188],"type":"Point"}
}