{
  "type": "Feature",
  "properties": {
    "iso:country":"US",
    "sg:address":"1 Secret Lake Rd",
    "sg:city":"Athol",
    "sg:classifiers":[
        {
            "category":"Manufacturing",
            "subcategory":"Metals",
            "type":"Manufacturing & Wholesale Goods"
        }
    ],
    "sg:phone":"+1 978 249 0483",
    "sg:postcode":"01331",
    "sg:province":"MA",
    "sg:tags":[
        "steel"
    ],
    "wof:name":"Braden Manufacturing LLC",
    "wof:placetype":"venue"
},
  "geometry": {"coordinates":[-72.180154,42.569616],"type":"Point"}
}