{
  "type": "Feature",
  "properties": {
    "iso:country":"US",
    "sg:address":"525 Washington St",
    "sg:city":"Auburn",
    "sg:classifiers":[
        {
            "category":"Autos & Motor Vehicles",
            "subcategory":"Auto Supplies",
            "type":"Retail Goods"
        }
    ],
    "sg:phone":"+1 508 832 3860",
    "sg:postcode":"01501",
    "sg:province":"MA",
    "sg:tags":[
        "wheel",
        "cover"
    ],
    "wof:name":"PRIVATEWHEELS.COM",
    "wof:placetype":"venue"
},
  "geometry": {"coordinates":[-71.84016800000001,42.185698],"type":"Point"}
}