{
  "type": "Feature",
  "properties": {
    "addr:full": "422 Washington St Woburn MA 01801",
    "addr:housenumber": "422",
    "addr:postcode": "01801",
    "addr:street": "Washington St",
    "iso:country": "US",
    "sg:address": "422 Washington St",
    "sg:city": "Woburn",
    "sg:classifiers": [
      {
        "category": "Professional",
        "subcategory": "Lawyer \u0026 Legal Services",
        "type": "Services"
      }
    ],
    "sg:phone": "+1 781 935 4080",
    "sg:postcode": "01801",
    "sg:province": "MA",
    "wof:name": "Judex Alternative Dispute Resolutions - CLOSED",
    "wof:placetype": "venue"
  },
  "geometry": {"coordinates":[-71.126404,42.503601],"type":"Point"}
}
