{
  "type": "Feature",
  "properties": {
    "addr:full": "336 Baker Ave Concord MA 01742",
    "addr:housenumber": "336",
    "addr:postcode": "01742",
    "addr:street": "Baker Ave",
    "iso:country": "US",
    "sg:address": "336 Baker Ave",
    "sg:city": "Concord",
    "sg:classifiers": [
      {
        "category": "Professional",
        "subcategory": "Lawyer \u0026 Legal Services",
        "type": "Services"
      }
    ],
    "sg:phone": "+1 978 369 7511",
    "sg:postcode": "01742",
    "sg:province": "MA",
    "wof:name": "Bamford Mark E Law Office of",
    "wof:placetype": "venue"
  },
  "geometry": {"coordinates":[-71.384903,42.459099],"type":"Point"}
}
