{
  "type": "Feature",
  "properties": {
    "addr:full":"1 High St North Andover MA 01845",
    "addr:housenumber":"1",
    "addr:postcode":"01845",
    "addr:street":"High St",
    "iso:country":"US",
    "sg:address":"1 High St",
    "sg:city":"North Andover",
    "sg:classifiers":[
        {
            "category":"Professional",
            "type":"Services"
        }
    ],
    "sg:phone":"+1 978 686 3583",
    "sg:postcode":"01845",
    "sg:province":"MA",
    "sg:tags":[
        "establishment"
    ],
    "wof:name":"Modicon",
    "wof:placetype":"venue"
},
  "geometry": {"coordinates":[-71.125231,42.705393],"type":"Point"}
}