{
  "type": "Feature",
  "properties": {
    "iso:country":"US",
    "sg:address":"14 Leitha Dr",
    "sg:city":"Waltham",
    "sg:classifiers":[
        {
            "category":"Shopping",
            "subcategory":"Shoes",
            "type":"Retail Goods"
        }
    ],
    "sg:phone":"+1 781 893 4858",
    "sg:postcode":"02451",
    "sg:province":"MA",
    "wof:name":"It's Official",
    "wof:placetype":"venue"
},
  "geometry": {"coordinates":[-71.239155,42.412277],"type":"Point"}
}