{
  "type": "Feature",
  "properties": {
    "addr:full":"52 Brattle St Cambridge MA 02138",
    "addr:housenumber":"52",
    "addr:postcode":"02138",
    "addr:street":"Brattle St",
    "iso:country":"US",
    "sg:address":"52 Brattle St",
    "sg:city":"Cambridge",
    "sg:classifiers":[
        {
            "category":"Shopping",
            "subcategory":"Clothing, Apparel, & Fashions",
            "type":"Retail Goods"
        }
    ],
    "sg:phone":"+1 617 661 6441",
    "sg:postcode":"02138",
    "sg:province":"MA",
    "sg:tags":[
        "lingerie",
        "accessory"
    ],
    "sg:website":"www.clothware.com",
    "wof:name":"Clothware",
    "wof:placetype":"venue"
},
  "geometry": {"coordinates":[-71.12200199999999,42.374699],"type":"Point"}
}