{
  "type": "Feature",
  "properties": {
    "iso:country":"US",
    "sg:address":"1 Douglas St",
    "sg:city":"Quincy",
    "sg:classifiers":[
        {
            "category":"Banks & Credit Unions",
            "subcategory":"Investment Brokerage",
            "type":"Services"
        }
    ],
    "sg:phone":"+1 617 472 9600",
    "sg:postcode":"02169",
    "sg:province":"MA",
    "sg:tags":[
        "advisory",
        "financial"
    ],
    "wof:name":"B Donelin Financial Svc Inc",
    "wof:placetype":"venue"
},
  "geometry": {"coordinates":[-71.02946,42.24218],"type":"Point"}
}