{
  "type": "Feature",
  "properties": {
    "iso:country":"US",
    "sg:address":"235 Union St",
    "sg:city":"Lynn",
    "sg:classifiers":[
        {
            "category":"Restaurant",
            "type":"Food & Drink"
        }
    ],
    "sg:menulink":"http://www.allmenus.com/ma/lynn/229462-carusos-/menu/",
    "sg:phone":"+1 781 599 9494",
    "sg:postcode":"01901",
    "sg:province":"MA",
    "sg:tags":[
        "italian"
    ],
    "wof:name":"Caruso's ",
    "wof:placetype":"venue"
},
  "geometry": {"coordinates":[-70.94281599999999,42.465675],"type":"Point"}
}