{
  "type": "Feature",
  "properties": {
    "iso:country":"US",
    "sg:address":"324 Middle Rd",
    "sg:city":"Haverhill",
    "sg:classifiers":[
        {
            "category":"Retail",
            "subcategory":"Laundry & Dry Cleaning",
            "type":"Services"
        }
    ],
    "sg:phone":"+1 978 463 6688",
    "sg:postcode":"01830",
    "sg:province":"MA",
    "sg:tags":[
        "cleaners",
        "rug",
        "carpet"
    ],
    "wof:name":"Judy's Cleaning Svc",
    "wof:placetype":"venue"
},
  "geometry": {"coordinates":[-71.033272,42.802921],"type":"Point"}
}