{
  "type": "Feature",
  "properties": {
    "iso:country":"US",
    "sg:address":"160 Pleasant St",
    "sg:city":"Attleboro",
    "sg:classifiers":[
        {
            "category":"Shopping",
            "subcategory":"Optical Goods",
            "type":"Retail Goods"
        }
    ],
    "sg:phone":"+1 508 222 5400",
    "sg:postcode":"02703",
    "sg:province":"MA",
    "sg:tags":[
        "optician",
        "eyewear"
    ],
    "sg:website":"www.attleboroopticalshoppe.com",
    "wof:name":"Attleboro Optical Shoppe",
    "wof:placetype":"venue"
},
  "geometry": {"coordinates":[-71.275902,41.949699],"type":"Point"}
}