{
  "type": "Feature",
  "properties": {
    "addr:full": "160 Pleasant St Attleboro MA 02703",
    "addr:housenumber": "160",
    "addr:postcode": "02703",
    "addr:street": "Pleasant St",
    "iso:country": "US",
    "ovtr:label": "Attleboro Optical Shoppe, 160 Pleasant St Attleboro MA US",
    "ovtr:similarity": 2.7105350494384766,
    "sg:address": "160 Pleasant St",
    "sg:city": "Attleboro",
    "sg:classifiers": [
      {
        "category": "Shopping",
        "subcategory": "Optical Goods",
        "type": "Retail Goods"
      }
    ],
    "sg:phone": "+1 508 222 5400",
    "sg:postcode": "02703",
    "sg:province": "MA",
    "sg:tags": [
      "optician",
      "eyewear"
    ],
    "sg:website": "www.attleboroopticalshoppe.com",
    "wof:name": "Attleboro Optical Shoppe",
    "wof:placetype": "venue"
  },
  "geometry": {"coordinates":[-71.275902,41.949699],"type":"Point"}
}
