{
  "type": "Feature",
  "properties": {
    "iso:country":"US",
    "sg:address":"111 Washington St",
    "sg:city":"Plainville",
    "sg:classifiers":[
        {
            "category":"Shopping",
            "subcategory":"Florist",
            "type":"Retail Goods"
        }
    ],
    "sg:phone":"+1 508 699 8900",
    "sg:postcode":"02762",
    "sg:province":"MA",
    "wof:name":"A A 1 Trash Removal",
    "wof:placetype":"venue"
},
  "geometry": {"coordinates":[-71.318028,42.015798],"type":"Point"}
}