{
  "type": "Feature",
  "properties": {
    "addr:full":"2 Forbes Rd Woburn MA 01801",
    "addr:housenumber":"2",
    "addr:postcode":"01801",
    "addr:street":"Forbes Rd",
    "iso:country":"US",
    "sg:address":"2 Forbes Rd",
    "sg:city":"Woburn",
    "sg:classifiers":[
        {
            "category":"Travel",
            "subcategory":"Hotels & Motels",
            "type":"Entertainment"
        }
    ],
    "sg:postcode":"01801",
    "sg:province":"MA",
    "sg:website":"www.hilton.com",
    "wof:name":"Hilton Boston-Woburn",
    "wof:placetype":"venue"
},
  "geometry": {"coordinates":[-71.12393400000001,42.495593],"type":"Point"}
}