{
  "type": "Feature",
  "properties": {
    "addr:full": "110 Route 137 Harwich MA 02645",
    "addr:housenumber": "110",
    "addr:postcode": "02645",
    "addr:street": "Route 137",
    "iso:country": "US",
    "sg:address": "110 Route 137",
    "sg:city": "Harwich",
    "sg:classifiers": [
      {
        "category": "Food \u0026 Beverages",
        "subcategory": "Groceries \u0026 Convenience Stores",
        "type": "Retail Goods"
      }
    ],
    "sg:phone": "+1 508 430 1781",
    "sg:postcode": "02645",
    "sg:province": "MA",
    "sg:website": "www.mobil.com",
    "wof:name": "Mobil Route 137",
    "wof:placetype": "venue"
  },
  "geometry": {"coordinates":[-70.0216,41.7062],"type":"Point"}
}
