{
  "type": "Feature",
  "properties": {
    "addr:full": "5 State St Shelburne Falls MA 01370",
    "addr:housenumber": "5",
    "addr:postcode": "01370",
    "addr:street": "State St",
    "iso:country": "US",
    "sg:address": "5 State St",
    "sg:city": "Shelburne Falls",
    "sg:classifiers": [
      {
        "category": "Professional",
        "subcategory": "Accounting \u0026 Tax Preparation",
        "type": "Services"
      }
    ],
    "sg:phone": "+1 413 625 8221",
    "sg:postcode": "01370",
    "sg:province": "MA",
    "sg:tags": [
      "bookkeeping",
      "general"
    ],
    "wof:name": "JPS Computer Svc",
    "wof:placetype": "venue"
  },
  "geometry": {"coordinates":[-72.741414,42.603922],"type":"Point"}
}
