{
  "type": "Feature",
  "properties": {
    "iso:country":"US",
    "sg:address":"5 State St",
    "sg:city":"Shelburne Falls",
    "sg:classifiers":[
        {
            "category":"Professional",
            "subcategory":"Accounting & Tax Preparation",
            "type":"Services"
        }
    ],
    "sg:phone":"+1 413 625 8221",
    "sg:postcode":"01370",
    "sg:province":"MA",
    "sg:tags":[
        "bookkeeping",
        "general"
    ],
    "wof:name":"JPS Computer Svc",
    "wof:placetype":"venue"
},
  "geometry": {"coordinates":[-72.74141400000001,42.603922],"type":"Point"}
}