{
  "type": "Feature",
  "properties": {
    "iso:country":"US",
    "sg:address":"873 Beacon St",
    "sg:city":"Boston",
    "sg:classifiers":[
        {
            "category":"Professional",
            "subcategory":"Lawyer & Legal Services",
            "type":"Services"
        }
    ],
    "sg:phone":"+1 617 375 0006",
    "sg:postcode":"02215",
    "sg:province":"MA",
    "wof:name":"Gold Jonathan Atty",
    "wof:placetype":"venue"
},
  "geometry": {"coordinates":[-71.10430100000001,42.346802],"type":"Point"}
}