{
  "type": "Feature",
  "properties": {
    "addr:full": "873 Beacon St Boston MA 02215",
    "addr:housenumber": "873",
    "addr:postcode": "02215",
    "addr:street": "Beacon St",
    "iso:country": "US",
    "sg:address": "873 Beacon St",
    "sg:city": "Boston",
    "sg:classifiers": [
      {
        "category": "Professional",
        "subcategory": "Lawyer \u0026 Legal Services",
        "type": "Services"
      }
    ],
    "sg:phone": "+1 617 375 0006",
    "sg:postcode": "02215",
    "sg:province": "MA",
    "wof:name": "Gold Jonathan Atty",
    "wof:placetype": "venue"
  },
  "geometry": {"coordinates":[-71.104301,42.346802],"type":"Point"}
}
