{
  "type": "Feature",
  "properties": {
    "addr:full":"896 Main St Tewksbury MA 01876",
    "addr:housenumber":"896",
    "addr:postcode":"01876",
    "addr:street":"Main St",
    "iso:country":"US",
    "sg:address":"896 Main St",
    "sg:city":"Tewksbury",
    "sg:classifiers":[
        {
            "category":"Restaurant",
            "type":"Food & Drink"
        }
    ],
    "sg:phone":"+1 978 851 7271",
    "sg:postcode":"01876",
    "sg:province":"MA",
    "sg:tags":[
        "italian",
        "pizza"
    ],
    "sg:website":"http://www.capellinisrestaurant.com",
    "wof:name":"Capellini's",
    "wof:placetype":"venue"
},
  "geometry": {"coordinates":[-71.237757,42.613603],"type":"Point"}
}