{
  "type": "Feature",
  "properties": {
    "addr:full":"4 Mallard Way Burlington MA 01803",
    "addr:housenumber":"4",
    "addr:postcode":"01803",
    "addr:street":"Mallard Way",
    "iso:country":"US",
    "sg:address":"4 Mallard Way",
    "sg:city":"Burlington",
    "sg:classifiers":[
        {
            "category":"Building & Trades",
            "subcategory":"Locksmith",
            "type":"Services"
        }
    ],
    "sg:phone":"+1 781 203 6137",
    "sg:postcode":"01803",
    "sg:province":"MA",
    "sg:tags":[
        "key"
    ],
    "wof:name":"Locksmith Service ABC Emergency",
    "wof:placetype":"venue"
},
  "geometry": {"coordinates":[-71.182779,42.521946],"type":"Point"}
}