{
  "type": "Feature",
  "properties": {
    "addr:full": "105 William St New Bedford MA 02740",
    "addr:housenumber": "105",
    "addr:postcode": "02740",
    "addr:street": "William St",
    "iso:country": "US",
    "sg:address": "105 William St",
    "sg:city": "New Bedford",
    "sg:classifiers": [
      {
        "category": "Professional",
        "type": "Services"
      }
    ],
    "sg:phone": "+1 508 996 3147",
    "sg:postcode": "02740",
    "sg:province": "MA",
    "sg:tags": [
      "establishment"
    ],
    "wof:name": "Project Care",
    "wof:placetype": "venue"
  },
  "geometry": {"coordinates":[-70.926712,41.635391],"type":"Point"}
}
