{
  "type": "Feature",
  "properties": {
    "iso:country":"US",
    "sg:address":"105 William St",
    "sg:city":"New Bedford",
    "sg:classifiers":[
        {
            "category":"Professional",
            "type":"Services"
        }
    ],
    "sg:phone":"+1 508 996 3147",
    "sg:postcode":"02740",
    "sg:province":"MA",
    "sg:tags":[
        "establishment"
    ],
    "wof:name":"Project Care",
    "wof:placetype":"venue"
},
  "geometry": {"coordinates":[-70.92671199999999,41.635391],"type":"Point"}
}