{
  "type": "Feature",
  "properties": {
    "addr:full":"235 South St Holyoke MA 01040",
    "addr:housenumber":"235",
    "addr:postcode":"01040",
    "addr:street":"South St",
    "iso:country":"US",
    "sg:address":"235 South St",
    "sg:city":"Holyoke",
    "sg:classifiers":[
        {
            "category":"Food & Beverages",
            "subcategory":"Groceries & Convenience Stores",
            "type":"Retail Goods"
        }
    ],
    "sg:phone":"+1 413 532 1700",
    "sg:postcode":"01040",
    "sg:province":"MA",
    "sg:website":"http://www.save-a-lot.com/",
    "wof:name":"Save-A-Lot",
    "wof:placetype":"venue"
},
  "geometry": {"coordinates":[-72.620648,42.195801],"type":"Point"}
}