{
  "type": "Feature",
  "properties": {
    "addr:full":"344 Massachusetts Ave Arlington MA 02474",
    "addr:housenumber":"344",
    "addr:postcode":"02474",
    "addr:street":"Massachusetts Ave",
    "iso:country":"US",
    "sg:address":"344 Massachusetts Ave",
    "sg:city":"Arlington",
    "sg:classifiers":[
        {
            "category":"Real Estate",
            "subcategory":"Real Estate Agent",
            "type":"Services"
        }
    ],
    "sg:phone":"+1 781 648 4900",
    "sg:postcode":"02474",
    "sg:province":"MA",
    "wof:name":"G & G Realty",
    "wof:placetype":"venue"
},
  "geometry": {"coordinates":[-71.14756199999999,42.41016],"type":"Point"}
}