{
  "type": "Feature",
  "properties": {
    "iso:country":"US",
    "sg:address":"65 Lowell St",
    "sg:city":"Lawrence",
    "sg:classifiers":[
        {
            "category":"Government",
            "subcategory":"Office",
            "type":"Public Place"
        }
    ],
    "sg:phone":"+1 978 794 5852",
    "sg:postcode":"01840",
    "sg:province":"MA",
    "sg:tags":[
        "civil",
        "defense",
        "agency"
    ],
    "wof:name":"Lawrence Emergency Management",
    "wof:placetype":"venue"
},
  "geometry": {"coordinates":[-71.165755,42.708313],"type":"Point"}
}