{
  "type": "Feature",
  "properties": {
    "addr:full":"16 Ricker Rd Newton MA 02458",
    "addr:housenumber":"16",
    "addr:postcode":"02458",
    "addr:street":"Ricker Rd",
    "iso:country":"US",
    "sg:address":"16 Ricker Rd",
    "sg:city":"Newton",
    "sg:classifiers":[
        {
            "category":"Building & Trades",
            "subcategory":"Plumbing",
            "type":"Services"
        }
    ],
    "sg:phone":"+1 617 244 6560",
    "sg:postcode":"02458",
    "sg:province":"MA",
    "sg:tags":[
        "plumbing",
        "bidding",
        "contractor"
    ],
    "wof:name":"Robert Fei Plumbing & Heating",
    "wof:placetype":"venue"
},
  "geometry": {"coordinates":[-71.174863,42.35205],"type":"Point"}
}