{
  "type": "Feature",
  "properties": {
    "iso:country":"US",
    "sg:address":"104 Marston St",
    "sg:city":"Lawrence",
    "sg:classifiers":[
        {
            "category":"Building & Trades",
            "subcategory":"Plumbing",
            "type":"Services"
        }
    ],
    "sg:phone":"+1 978 682 8614",
    "sg:postcode":"01841",
    "sg:province":"MA",
    "sg:tags":[
        "plumbing",
        "contractor"
    ],
    "wof:name":"Cheever Mechanical",
    "wof:placetype":"venue"
},
  "geometry": {"coordinates":[-71.141417,42.708787],"type":"Point"}
}