{
  "type": "Feature",
  "properties": {
    "addr:full":"63 Fulton St Peabody MA 01960",
    "addr:housenumber":"63",
    "addr:postcode":"01960",
    "addr:street":"Fulton St",
    "iso:country":"US",
    "sg:address":"63 Fulton St",
    "sg:city":"Peabody",
    "sg:classifiers":[
        {
            "category":"Retail",
            "subcategory":"Laundry & Dry Cleaning",
            "type":"Services"
        }
    ],
    "sg:phone":"+1 978 531 1200",
    "sg:postcode":"01960",
    "sg:province":"MA",
    "sg:tags":[
        "cleaners",
        "rug",
        "carpet"
    ],
    "wof:name":"Fox Cleaning & Restoration",
    "wof:placetype":"venue"
},
  "geometry": {"coordinates":[-70.916738,42.528463],"type":"Point"}
}