{
  "type": "Feature",
  "properties": {
    "iso:country":"US",
    "sg:address":"211 Granite St",
    "sg:city":"Worcester",
    "sg:classifiers":[
        {
            "category":"Autos & Motor Vehicles",
            "subcategory":"Automobile Sales",
            "type":"Retail Goods"
        },
        {
            "category":"Autos & Motor Vehicles",
            "subcategory":"Auto Supplies",
            "type":"Retail Goods"
        }
    ],
    "sg:phone":"+1 857 277 7520",
    "sg:postcode":"01607",
    "sg:province":"MA",
    "sg:tags":[
        "used",
        "car",
        "part",
        "supplies-used",
        "rebuilt",
        "salvage"
    ],
    "sg:website":"http://www.lindersinc.com",
    "wof:name":"Linder's Inc.",
    "wof:placetype":"venue"
},
  "geometry": {"coordinates":[-71.78279999999999,42.237455],"type":"Point"}
}