{
  "type": "Feature",
  "properties": {
    "iso:country":"US",
    "sg:address":"52 Jackbon Rd",
    "sg:city":"Mashpee",
    "sg:classifiers":[
        {
            "category":"Building & Trades",
            "subcategory":"Construction",
            "type":"Services"
        }
    ],
    "sg:phone":"+1 508 477 3383",
    "sg:postcode":"02649",
    "sg:province":"MA",
    "sg:tags":[
        "painter"
    ],
    "wof:name":"Brentwood Custom Painting Inc",
    "wof:placetype":"venue"
},
  "geometry": {"coordinates":[-70.46717,41.606347],"type":"Point"}
}