{
  "type": "Feature",
  "properties": {
    "addr:full":"0 Central St Ipswich MA 01938",
    "addr:housenumber":"0",
    "addr:postcode":"01938",
    "addr:street":"Central St",
    "iso:country":"US",
    "sg:address":"0 Central St",
    "sg:city":"Ipswich",
    "sg:phone":"+1 978 356 4222",
    "sg:postcode":"01938",
    "sg:province":"MA",
    "wof:name":"Stone Soup Cafe",
    "wof:placetype":"venue"
},
  "geometry": {"coordinates":[-70.844238,42.684299],"type":"Point"}
}