{
  "type": "Feature",
  "properties": {
    "addr:full":"491 Springfield St Feeding Hills MA 01030",
    "addr:housenumber":"491",
    "addr:postcode":"01030",
    "addr:street":"Springfield St",
    "iso:country":"US",
    "sg:address":"491 Springfield St",
    "sg:city":"Feeding Hills",
    "sg:classifiers":[
        {
            "category":"Autos & Motor Vehicles",
            "subcategory":"Auto Supplies",
            "type":"Retail Goods"
        }
    ],
    "sg:phone":"+1 413 786 5411",
    "sg:postcode":"01030",
    "sg:province":"MA",
    "sg:tags":[
        "automobile",
        "parts"
    ],
    "wof:name":"NAPA Auto Parts",
    "wof:placetype":"venue"
},
  "geometry": {"coordinates":[-72.64582299999999,42.083114],"type":"Point"}
}