{
  "type": "Feature",
  "properties": {
    "iso:country":"US",
    "sg:address":"175 Shore Rd",
    "sg:city":"Buzzards Bay",
    "sg:classifiers":[
        {
            "category":"Building & Trades",
            "subcategory":"Construction",
            "type":"Services"
        }
    ],
    "sg:phone":"+1 508 759 4832",
    "sg:postcode":"02532",
    "sg:province":"MA",
    "sg:tags":[
        "contractor"
    ],
    "wof:name":"Rose Chas L General Carpentry",
    "wof:placetype":"venue"
},
  "geometry": {"coordinates":[-70.61190000000001,41.736698],"type":"Point"}
}