{
  "type": "Feature",
  "properties": {
    "addr:full":"45 Drum Hill Rd Chelmsford MA 01824",
    "addr:housenumber":"45",
    "addr:postcode":"01824",
    "addr:street":"Drum Hill Rd",
    "iso:country":"US",
    "sg:address":"45 Drum Hill Rd",
    "sg:city":"Chelmsford",
    "sg:classifiers":[
        {
            "category":"Utilities",
            "subcategory":"Mobile Phone",
            "type":"Services"
        },
        {
            "category":"Shopping",
            "subcategory":"Mobile Phones",
            "type":"Retail Goods"
        },
        {
            "category":"Utilities",
            "subcategory":"Telephone",
            "type":"Services"
        },
        {
            "category":"Professional",
            "subcategory":"Computer Services",
            "type":"Services"
        }
    ],
    "sg:phone":"+1 978 937 2355",
    "sg:postcode":"01824",
    "sg:province":"MA",
    "sg:tags":[
        "telecommunication",
        "supply",
        "communication",
        "system",
        "wireless",
        "equipment",
        "cellular"
    ],
    "sg:website":"http://clickserve.dartsearch.net/link/click?lid=43000000308049899",
    "wof:name":"T-Mobile",
    "wof:placetype":"venue"
},
  "geometry": {"coordinates":[-71.361473,42.625118],"type":"Point"}
}