{
  "type": "Feature",
  "properties": {
    "addr:full":"448 Salem St Wakefield MA 01880",
    "addr:housenumber":"448",
    "addr:postcode":"01880",
    "addr:street":"Salem St",
    "iso:country":"US",
    "sg:address":"448 Salem St",
    "sg:city":"Wakefield",
    "sg:classifiers":[
        {
            "category":"Freight",
            "type":"Transportation"
        }
    ],
    "sg:phone":"+1 781 246 1751",
    "sg:postcode":"01880",
    "sg:province":"MA",
    "sg:tags":[
        "trucking"
    ],
    "wof:name":"Puglia Trucking Co",
    "wof:placetype":"venue"
},
  "geometry": {"coordinates":[-71.04201999999999,42.511967],"type":"Point"}
}