{
  "type": "Feature",
  "properties": {
    "addr:full":"195 West St Milford MA 01757",
    "addr:housenumber":"195",
    "addr:postcode":"01757",
    "addr:street":"West St",
    "iso:country":"US",
    "sg:address":"195 West St",
    "sg:city":"Milford",
    "sg:classifiers":[
        {
            "category":"Shopping",
            "subcategory":"Computers & Home Electronics",
            "type":"Retail Goods"
        }
    ],
    "sg:phone":"+1 508 478 5174",
    "sg:postcode":"01757",
    "sg:province":"MA",
    "sg:tags":[
        "equipment",
        "dealer"
    ],
    "sg:website":"www.wca.com",
    "wof:name":"Whalley Computer Assoc",
    "wof:placetype":"venue"
},
  "geometry": {"coordinates":[-71.54015800000001,42.141123],"type":"Point"}
}