{
  "type": "Feature",
  "properties": {
    "addr:full":"720 Edgell Rd Framingham MA 01701",
    "addr:housenumber":"720",
    "addr:postcode":"01701",
    "addr:street":"Edgell Rd",
    "iso:country":"US",
    "sg:address":"720 Edgell Rd",
    "sg:city":"Framingham",
    "sg:classifiers":[
        {
            "category":"Organizations",
            "subcategory":"Religious Organization",
            "type":"Services"
        }
    ],
    "sg:phone":"+1 508 877 2550",
    "sg:postcode":"01701",
    "sg:province":"MA",
    "wof:name":"Lutheran Church Of Framingham",
    "wof:placetype":"venue"
},
  "geometry": {"coordinates":[-71.437123,42.32291],"type":"Point"}
}