{
  "type": "Feature",
  "properties": {
    "addr:full": "11 Jonathan Bourne Dr # 2 Pocasset MA 02559",
    "addr:housenumber": "11",
    "addr:postcode": "02559",
    "addr:street": "Jonathan Bourne Dr # 2",
    "iso:country": "US",
    "sg:address": "11 Jonathan Bourne Dr # 2",
    "sg:city": "Pocasset",
    "sg:classifiers": [
      {
        "category": "Wholesale",
        "subcategory": "Office Equipment",
        "type": "Manufacturing \u0026 Wholesale Goods"
      },
      {
        "category": "Professional",
        "subcategory": "Printing \u0026 Photocopies",
        "type": "Services"
      },
      {
        "category": "Shopping",
        "subcategory": "Computers \u0026 Home Electronics",
        "type": "Retail Goods"
      }
    ],
    "sg:phone": "+1 508 563 5001",
    "sg:postcode": "02559",
    "sg:province": "MA",
    "sg:tags": [
      "scanning",
      "printer",
      "services-commercial",
      "plotting",
      "supply"
    ],
    "wof:name": "Cape Cod National Offset And Bindery Inc",
    "wof:placetype": "venue"
  },
  "geometry": {"coordinates":[-70.584773,41.707758],"type":"Point"}
}
