{
  "type": "Feature",
  "properties": {
    "addr:full": "67 Mechanic St Unit 5 Attleboro MA 02703",
    "addr:housenumber": "67",
    "addr:postcode": "02703",
    "addr:street": "Mechanic St Unit 5",
    "iso:country": "US",
    "sg:address": "67 Mechanic St Unit 5",
    "sg:city": "Attleboro",
    "sg:classifiers": [
      {
        "category": "Science Facility",
        "type": "Public Place"
      }
    ],
    "sg:phone": "+1 508 226 0080",
    "sg:postcode": "02703",
    "sg:province": "MA",
    "sg:tags": [
      "development",
      "laboratories-research"
    ],
    "wof:name": "J T Inman Co Inc",
    "wof:placetype": "venue"
  },
  "geometry": {"coordinates":[-71.292862,41.943958],"type":"Point"}
}
