{
  "type": "Feature",
  "properties": {
    "iso:country":"US",
    "sg:address":"2 Forest Rd",
    "sg:city":"Medway",
    "sg:classifiers":[
        {
            "category":"Shopping",
            "subcategory":"Music",
            "type":"Retail Goods"
        }
    ],
    "sg:phone":"+1 508 533 6016",
    "sg:postcode":"02053",
    "sg:province":"MA",
    "sg:tags":[
        "compact",
        "record",
        "disc",
        "tape"
    ],
    "wof:name":"C D's For Pc's",
    "wof:placetype":"venue"
},
  "geometry": {"coordinates":[-71.416381,42.143643],"type":"Point"}
}