{
  "type": "Feature",
  "properties": {
    "iso:country":"US",
    "sg:address":"60 Court St",
    "sg:city":"Westfield",
    "sg:classifiers":[
        {
            "category":"Health Services",
            "subcategory":"Doctor",
            "type":"Services"
        }
    ],
    "sg:phone":"+1 413 568 5285",
    "sg:postcode":"01085",
    "sg:province":"MA",
    "sg:tags":[
        "dentist"
    ],
    "wof:name":"Jacinthe Giroux DDS",
    "wof:placetype":"venue"
},
  "geometry": {"coordinates":[-72.754856,42.120098],"type":"Point"}
}