{
  "type": "Feature",
  "properties": {
    "iso:country":"US",
    "sg:address":"117 Main St",
    "sg:city":"Greenfield",
    "sg:classifiers":[
        {
            "category":"Insurance",
            "subcategory":"Insurance Agent",
            "type":"Services"
        }
    ],
    "sg:phone":"+1 413 773 9913",
    "sg:postcode":"01301",
    "sg:province":"MA",
    "wof:name":"Massone Insurance",
    "wof:placetype":"venue"
},
  "geometry": {"coordinates":[-72.60589899999999,42.587508],"type":"Point"}
}