{
  "type": "Feature",
  "properties": {
    "addr:full":"43 Franklin St Watertown MA 02472",
    "addr:housenumber":"43",
    "addr:postcode":"02472",
    "addr:street":"Franklin St",
    "iso:country":"US",
    "sg:address":"43 Franklin St",
    "sg:city":"Watertown",
    "sg:classifiers":[
        {
            "category":"Building & Trades",
            "subcategory":"Electrical",
            "type":"Services"
        }
    ],
    "sg:phone":"+1 617 923 0910",
    "sg:postcode":"02472",
    "sg:province":"MA",
    "sg:tags":[
        "electrician"
    ],
    "wof:name":"George Pizzuto Electric",
    "wof:placetype":"venue"
},
  "geometry": {"coordinates":[-71.175033,42.367189],"type":"Point"}
}