{
  "type": "Feature",
  "properties": {
    "addr:full": "235 Albany St Springfield MA 01105",
    "addr:housenumber": "235",
    "addr:postcode": "01105",
    "addr:street": "Albany St",
    "iso:country": "US",
    "sg:address": "235 Albany St",
    "sg:city": "Springfield",
    "sg:classifiers": [
      {
        "category": "Wholesale",
        "subcategory": "Machinery \u0026 Supplies",
        "type": "Manufacturing \u0026 Wholesale Goods"
      }
    ],
    "sg:phone": "+1 413 739 0200",
    "sg:postcode": "01105",
    "sg:province": "MA",
    "sg:tags": [
      "industrial",
      "equipment",
      "used",
      "machinery-new",
      "supplies-wholesale"
    ],
    "wof:name": "Petroleum Solutions, Inc.",
    "wof:placetype": "venue"
  },
  "geometry": {"coordinates":[-72.575202,42.119728],"type":"Point"}
}
