{
  "type": "Feature",
  "properties": {
    "addr:full":"50 Metropolitan Ave Ashland MA 01721",
    "addr:housenumber":"50",
    "addr:postcode":"01721",
    "addr:street":"Metropolitan Ave",
    "iso:country":"US",
    "sg:address":"50 Metropolitan Ave",
    "sg:city":"Ashland",
    "sg:classifiers":[
        {
            "category":"Wholesale",
            "subcategory":"Construction Materials",
            "type":"Manufacturing & Wholesale Goods"
        }
    ],
    "sg:phone":"+1 508 881 0910",
    "sg:postcode":"01721",
    "sg:province":"MA",
    "sg:tags":[
        "fence"
    ],
    "wof:name":"E & D Fence Co",
    "wof:placetype":"venue"
},
  "geometry": {"coordinates":[-71.463566,42.253262],"type":"Point"}
}