{
  "type": "Feature",
  "properties": {
    "addr:full": "3 Tara Ln Sterling MA 01564",
    "addr:housenumber": "3",
    "addr:postcode": "01564",
    "addr:street": "Tara Ln",
    "iso:country": "US",
    "sg:address": "3 Tara Ln",
    "sg:city": "Sterling",
    "sg:classifiers": [
      {
        "category": "Retail",
        "subcategory": "Portrait Studio",
        "type": "Services"
      }
    ],
    "sg:phone": "+1 978 422 3349",
    "sg:postcode": "01564",
    "sg:province": "MA",
    "sg:tags": [
      "photography"
    ],
    "wof:name": "Lauren Studio",
    "wof:placetype": "venue"
  },
  "geometry": {"coordinates":[-71.747342,42.421569],"type":"Point"}
}
