{
  "type": "Feature",
  "properties": {
    "addr:full":"63 Anderson Ave Middleboro MA 02346",
    "addr:housenumber":"63",
    "addr:postcode":"02346",
    "addr:street":"Anderson Ave",
    "iso:country":"US",
    "sg:address":"63 Anderson Ave",
    "sg:city":"Middleboro",
    "sg:classifiers":[
        {
            "category":"Health Services",
            "subcategory":"Doctor",
            "type":"Services"
        }
    ],
    "sg:phone":"+1 508 947 8737",
    "sg:postcode":"02346",
    "sg:province":"MA",
    "sg:tags":[
        "physician",
        "surgeon"
    ],
    "wof:name":"Jiri R Kudliki MD",
    "wof:placetype":"venue"
},
  "geometry": {"coordinates":[-70.94503400000001,41.896031],"type":"Point"}
}