{
  "type": "Feature",
  "properties": {
    "addr:full": "34 Essex St Melrose MA 02176",
    "addr:housenumber": "34",
    "addr:postcode": "02176",
    "addr:street": "Essex St",
    "iso:country": "US",
    "sg:address": "34 Essex St",
    "sg:city": "Melrose",
    "sg:classifiers": [
      {
        "category": "Professional",
        "subcategory": "Management \u0026 Consulting",
        "type": "Services"
      }
    ],
    "sg:phone": "+1 781 665 7469",
    "sg:postcode": "02176",
    "sg:province": "MA",
    "sg:tags": [
      "marketing",
      "program"
    ],
    "wof:name": "Catalina Marketing Corp",
    "wof:placetype": "venue"
  },
  "geometry": {"coordinates":[-71.065218,42.456295],"type":"Point"}
}
