{
  "type": "Feature",
  "properties": {
    "addr:full":"492 Reed Rd North Dartmouth MA 02747",
    "addr:housenumber":"492",
    "addr:postcode":"02747",
    "addr:street":"Reed Rd",
    "iso:country":"US",
    "sg:address":"492 Reed Rd",
    "sg:city":"North Dartmouth",
    "sg:classifiers":[
        {
            "category":"Building & Trades",
            "subcategory":"Construction",
            "type":"Services"
        }
    ],
    "sg:phone":"+1   ",
    "sg:postcode":"02747",
    "sg:province":"MA",
    "sg:tags":[
        "residential"
    ],
    "wof:name":"Galego Construction",
    "wof:placetype":"venue"
},
  "geometry": {"coordinates":[-71.036756,41.63812],"type":"Point"}
}