{
  "type": "Feature",
  "properties": {
    "iso:country":"US",
    "sg:address":"25 Western Way",
    "sg:city":"Duxbury",
    "sg:classifiers":[
        {
            "category":"Shopping",
            "subcategory":"Used Merchandise",
            "type":"Retail Goods"
        }
    ],
    "sg:phone":"+1   ",
    "sg:postcode":"02332",
    "sg:province":"MA",
    "wof:name":"Jean Pannell",
    "wof:placetype":"venue"
},
  "geometry": {"coordinates":[-70.67387600000001,42.036168],"type":"Point"}
}