{
  "type": "Feature",
  "properties": {
    "iso:country":"US",
    "sg:address":"179 Sydney St",
    "sg:city":"Boston",
    "sg:classifiers":[
        {
            "category":"Professional",
            "type":"Services"
        }
    ],
    "sg:phone":"+1   ",
    "sg:postcode":"02125",
    "sg:province":"MA",
    "wof:name":"Tyburn John",
    "wof:placetype":"venue"
},
  "geometry": {"coordinates":[-71.05249999999999,42.317673],"type":"Point"}
}