{
  "type": "Feature",
  "properties": {
    "iso:country":"US",
    "sg:address":"2 Spring St",
    "sg:city":"West Bridgewater",
    "sg:classifiers":[
        {
            "category":"Education",
            "subcategory":"School",
            "type":"Public Place"
        }
    ],
    "sg:phone":"+1 508 894 1235",
    "sg:postcode":"02379",
    "sg:province":"MA",
    "wof:name":"West Bridgewater Public School",
    "wof:placetype":"venue"
},
  "geometry": {"coordinates":[-71.01577,42.023433],"type":"Point"}
}