{
  "type": "Feature",
  "properties": {
    "addr:full":"163 Hobart St Danvers MA 01923",
    "addr:housenumber":"163",
    "addr:postcode":"01923",
    "addr:street":"Hobart St",
    "iso:country":"US",
    "sg:address":"163 Hobart St",
    "sg:city":"Danvers",
    "sg:classifiers":[
        {
            "category":"Farming",
            "subcategory":"Farm & Veterinary Services",
            "type":"Manufacturing & Wholesale Goods"
        }
    ],
    "sg:phone":"+1 978 774 0550",
    "sg:postcode":"01923",
    "sg:province":"MA",
    "sg:tags":[
        "custom"
    ],
    "wof:name":"Clark Farm",
    "wof:placetype":"venue"
},
  "geometry": {"coordinates":[-70.958027,42.565756],"type":"Point"}
}