{
  "type": "Feature",
  "properties": {
    "iso:country":"US",
    "sg:address":"15 Gay St",
    "sg:city":"Westwood",
    "sg:classifiers":[
        {
            "category":"Building & Trades",
            "subcategory":"Landscaping Services",
            "type":"Services"
        }
    ],
    "sg:phone":"+1 781 320 9800",
    "sg:postcode":"02090",
    "sg:province":"MA",
    "sg:tags":[
        "tree"
    ],
    "wof:name":"Bark Busters Tree Svc",
    "wof:placetype":"venue"
},
  "geometry": {"coordinates":[-71.22141000000001,42.224696],"type":"Point"}
}