{
  "type": "Feature",
  "properties": {
    "iso:country":"US",
    "sg:address":"100 Huntington Ave",
    "sg:city":"Boston",
    "sg:classifiers":[
        {
            "category":"Shopping",
            "subcategory":"Beauty & Cosmetics",
            "type":"Retail Goods"
        }
    ],
    "sg:phone":"+1 617 236 7257",
    "sg:postcode":"02116",
    "sg:province":"MA",
    "sg:tags":[
        "supply"
    ],
    "wof:name":"C.O. Bigelow",
    "wof:placetype":"venue"
},
  "geometry": {"coordinates":[-71.079399,42.347],"type":"Point"}
}