{
  "type": "Feature",
  "properties": {
    "addr:full": "100 Huntington Ave Boston MA 02116",
    "addr:housenumber": "100",
    "addr:postcode": "02116",
    "addr:street": "Huntington Ave",
    "iso:country": "US",
    "sg:address": "100 Huntington Ave",
    "sg:city": "Boston",
    "sg:classifiers": [
      {
        "category": "Shopping",
        "subcategory": "Beauty \u0026 Cosmetics",
        "type": "Retail Goods"
      }
    ],
    "sg:phone": "+1 617 236 7257",
    "sg:postcode": "02116",
    "sg:province": "MA",
    "sg:tags": [
      "supply"
    ],
    "wof:name": "C.O. Bigelow",
    "wof:placetype": "venue"
  },
  "geometry": {"coordinates":[-71.079399,42.347],"type":"Point"}
}
