{
  "type": "Feature",
  "properties": {
    "addr:full": "60 Attucks Ln Hyannis MA 02601",
    "addr:housenumber": "60",
    "addr:postcode": "02601",
    "addr:street": "Attucks Ln",
    "iso:country": "US",
    "sg:address": "60 Attucks Ln",
    "sg:city": "Hyannis",
    "sg:classifiers": [
      {
        "category": "Wholesale",
        "subcategory": "Computers",
        "type": "Manufacturing \u0026 Wholesale Goods"
      }
    ],
    "sg:phone": "+1 508 778 8808",
    "sg:postcode": "02601",
    "sg:province": "MA",
    "sg:tags": [
      "equipment"
    ],
    "sg:website": "http://www.tekelec.com",
    "wof:name": "Tekelec",
    "wof:placetype": "venue"
  },
  "geometry": {"coordinates":[-70.322091,41.680727],"type":"Point"}
}
