{
  "type": "Feature",
  "properties": {
    "addr:full":"213 Huttleston Ave Fairhaven MA 02719",
    "addr:housenumber":"213",
    "addr:postcode":"02719",
    "addr:street":"Huttleston Ave",
    "iso:country":"US",
    "sg:address":"213 Huttleston Ave",
    "sg:city":"Fairhaven",
    "sg:classifiers":[
        {
            "category":"Shopping",
            "subcategory":"Clothing, Apparel, & Fashions",
            "type":"Retail Goods"
        }
    ],
    "sg:phone":"+1 508 996 1384",
    "sg:postcode":"02719",
    "sg:province":"MA",
    "sg:website":"www.dressbarn.com",
    "wof:name":"Dress Barn",
    "wof:placetype":"venue"
},
  "geometry": {"coordinates":[-70.880177,41.640966],"type":"Point"}
}