{
  "type": "Feature",
  "properties": {
    "iso:country":"US",
    "sg:address":"1793 Main St",
    "sg:city":"Brewster",
    "sg:classifiers":[
        {
            "category":"Shopping",
            "subcategory":"Used Merchandise",
            "type":"Retail Goods"
        }
    ],
    "sg:phone":"+1 508 896 7198",
    "sg:postcode":"02631",
    "sg:province":"MA",
    "sg:tags":[
        "antique"
    ],
    "wof:name":"Barbara Grant Antiques & Books",
    "wof:placetype":"venue"
},
  "geometry": {"coordinates":[-70.08639100000001,41.758483],"type":"Point"}
}