{
  "type": "Feature",
  "properties": {
    "addr:full": "1793 Main St Brewster MA 02631",
    "addr:housenumber": "1793",
    "addr:postcode": "02631",
    "addr:street": "Main St",
    "iso:country": "US",
    "sg:address": "1793 Main St",
    "sg:city": "Brewster",
    "sg:classifiers": [
      {
        "category": "Shopping",
        "subcategory": "Used Merchandise",
        "type": "Retail Goods"
      }
    ],
    "sg:phone": "+1 508 896 7198",
    "sg:postcode": "02631",
    "sg:province": "MA",
    "sg:tags": [
      "antique"
    ],
    "wof:name": "Barbara Grant Antiques \u0026 Books",
    "wof:placetype": "venue"
  },
  "geometry": {"coordinates":[-70.086391,41.758483],"type":"Point"}
}
