{
  "type": "Feature",
  "properties": {
    "addr:full":"5 Cape Rd Milford MA 01757",
    "addr:housenumber":"5",
    "addr:postcode":"01757",
    "addr:street":"Cape Rd",
    "iso:country":"US",
    "sg:address":"5 Cape Rd",
    "sg:city":"Milford",
    "sg:classifiers":[
        {
            "category":"Autos & Motor Vehicles",
            "subcategory":"Automobile Sales",
            "type":"Retail Goods"
        }
    ],
    "sg:phone":"+1 508 473 2800",
    "sg:postcode":"01757",
    "sg:province":"MA",
    "sg:tags":[
        "car",
        "dealer"
    ],
    "sg:website":"www.imperialford.com",
    "wof:name":"Imperial Ford",
    "wof:placetype":"venue"
},
  "geometry": {"coordinates":[-71.525238,42.130384],"type":"Point"}
}