{
  "type": "Feature",
  "properties": {
    "addr:full":"12 Bittersweet Ln Walpole MA 02081",
    "addr:housenumber":"12",
    "addr:postcode":"02081",
    "addr:street":"Bittersweet Ln",
    "iso:country":"US",
    "sg:address":"12 Bittersweet Ln",
    "sg:city":"Walpole",
    "sg:classifiers":[
        {
            "category":"Education",
            "subcategory":"Dance Studio",
            "type":"Public Place"
        }
    ],
    "sg:phone":"+1 508 660 8858",
    "sg:postcode":"02081",
    "sg:province":"MA",
    "sg:tags":[
        "instruction",
        "dancing"
    ],
    "wof:name":"Rosemaries Dance Studio",
    "wof:placetype":"venue"
},
  "geometry": {"coordinates":[-71.24640100000001,42.181888],"type":"Point"}
}