{
  "type": "Feature",
  "properties": {
    "iso:country":"US",
    "sg:address":"49 Woodside Ave",
    "sg:city":"Brockton",
    "sg:classifiers":[
        {
            "category":"Professional",
            "subcategory":"Management & Consulting",
            "type":"Services"
        }
    ],
    "sg:phone":"+1 508 580 1984",
    "sg:postcode":"02301",
    "sg:province":"MA",
    "sg:tags":[
        "business"
    ],
    "wof:name":"Jostens Publishing",
    "wof:placetype":"venue"
},
  "geometry": {"coordinates":[-71.02018700000001,42.049421],"type":"Point"}
}