{
  "type": "Feature",
  "properties": {
    "addr:full": "49 Woodside Ave Brockton MA 02301",
    "addr:housenumber": "49",
    "addr:postcode": "02301",
    "addr:street": "Woodside Ave",
    "iso:country": "US",
    "sg:address": "49 Woodside Ave",
    "sg:city": "Brockton",
    "sg:classifiers": [
      {
        "category": "Professional",
        "subcategory": "Management \u0026 Consulting",
        "type": "Services"
      }
    ],
    "sg:phone": "+1 508 580 1984",
    "sg:postcode": "02301",
    "sg:province": "MA",
    "sg:tags": [
      "business"
    ],
    "wof:name": "Jostens Publishing",
    "wof:placetype": "venue"
  },
  "geometry": {"coordinates":[-71.020187,42.049421],"type":"Point"}
}
