{
  "type": "Feature",
  "properties": {
    "addr:full":"17 Groton Rd Shirley MA 01464",
    "addr:housenumber":"17",
    "addr:postcode":"01464",
    "addr:street":"Groton Rd",
    "iso:country":"US",
    "sg:address":"17 Groton Rd",
    "sg:city":"Shirley",
    "sg:classifiers":[
        {
            "category":"Retail",
            "subcategory":"Auto Repair",
            "type":"Services"
        }
    ],
    "sg:phone":"+1 978 448 5864",
    "sg:postcode":"01464",
    "sg:province":"MA",
    "sg:tags":[
        "body",
        "automobile",
        "painting"
    ],
    "wof:name":"Bob's Auto Body",
    "wof:placetype":"venue"
},
  "geometry": {"coordinates":[-71.629189,42.600687],"type":"Point"}
}