{
  "type": "Feature",
  "properties": {
    "addr:full": "32 Regent St Cambridge MA 02140",
    "addr:housenumber": "32",
    "addr:postcode": "02140",
    "addr:street": "Regent St",
    "iso:country": "US",
    "sg:address": "32 Regent St",
    "sg:city": "Cambridge",
    "sg:classifiers": [
      {
        "category": "Banks \u0026 Credit Unions",
        "subcategory": "Financial Services",
        "type": "Services"
      }
    ],
    "sg:phone": "+1 617 576 5351",
    "sg:postcode": "02140",
    "sg:province": "MA",
    "sg:tags": [
      "trust"
    ],
    "wof:name": "Regent Court Condominium Trust",
    "wof:placetype": "venue"
  },
  "geometry": {"coordinates":[-71.122638,42.389235],"type":"Point"}
}
