{
  "type": "Feature",
  "properties": {
    "iso:country":"US",
    "sg:address":"32 Regent St",
    "sg:city":"Cambridge",
    "sg:classifiers":[
        {
            "category":"Banks & Credit Unions",
            "subcategory":"Financial Services",
            "type":"Services"
        }
    ],
    "sg:phone":"+1 617 576 5351",
    "sg:postcode":"02140",
    "sg:province":"MA",
    "sg:tags":[
        "trust"
    ],
    "wof:name":"Regent Court Condominium Trust",
    "wof:placetype":"venue"
},
  "geometry": {"coordinates":[-71.12263799999999,42.389235],"type":"Point"}
}