{
  "type": "Feature",
  "properties": {
    "iso:country":"US",
    "sg:address":"300 Mount Auburn St",
    "sg:city":"Cambridge",
    "sg:classifiers":[
        {
            "category":"Health Services",
            "subcategory":"Doctor",
            "type":"Services"
        }
    ],
    "sg:phone":"+1 617 497 0077",
    "sg:postcode":"02138",
    "sg:province":"MA",
    "wof:name":"Holmblad Christian J Phys",
    "wof:placetype":"venue"
},
  "geometry": {"coordinates":[-71.13359800000001,42.374802],"type":"Point"}
}