{
  "type": "Feature",
  "properties": {
    "addr:full":"65 Russell Mills Rd Plymouth MA 02360",
    "addr:housenumber":"65",
    "addr:postcode":"02360",
    "addr:street":"Russell Mills Rd",
    "iso:country":"US",
    "sg:address":"65 Russell Mills Rd",
    "sg:city":"Plymouth",
    "sg:classifiers":[
        {
            "category":"Organizations",
            "subcategory":"Professional Association",
            "type":"Services"
        }
    ],
    "sg:phone":"+1   ",
    "sg:postcode":"02360",
    "sg:province":"MA",
    "wof:name":"Coastal Kayak Educators Inc",
    "wof:placetype":"venue"
},
  "geometry": {"coordinates":[-70.63265,41.920482],"type":"Point"}
}