{
  "type": "Feature",
  "properties": {
    "addr:full": "230 N Main St Randolph MA 02368",
    "addr:housenumber": "230",
    "addr:postcode": "02368",
    "addr:street": "N Main St",
    "iso:country": "US",
    "sg:address": "230 N Main St",
    "sg:city": "Randolph",
    "sg:classifiers": [
      {
        "category": "Shopping",
        "subcategory": "Clothing, Apparel, \u0026 Fashions",
        "type": "Retail Goods"
      }
    ],
    "sg:phone": "+1 781 963 3277",
    "sg:postcode": "02368",
    "sg:province": "MA",
    "sg:tags": [
      "sewing",
      "alteration"
    ],
    "wof:name": "Angelos Custom Tailor",
    "wof:placetype": "venue"
  },
  "geometry": {"coordinates":[-71.043701,42.166599],"type":"Point"}
}
