{
  "type": "Feature",
  "properties": {
    "addr:full": "239 Littleton Rd Westford MA 01886",
    "addr:housenumber": "239",
    "addr:postcode": "01886",
    "addr:street": "Littleton Rd",
    "iso:country": "US",
    "sg:address": "239 Littleton Rd",
    "sg:city": "Westford",
    "sg:classifiers": [
      {
        "category": "Manufacturing",
        "subcategory": "Electronics",
        "type": "Manufacturing \u0026 Wholesale Goods"
      }
    ],
    "sg:phone": "+1 978 589 3850",
    "sg:postcode": "01886",
    "sg:province": "MA",
    "sg:tags": [
      "semiconductor",
      "devices"
    ],
    "wof:name": "Semi Tech",
    "wof:placetype": "venue"
  },
  "geometry": {"coordinates":[-71.436428,42.558636],"type":"Point"}
}
