{
  "type": "Feature",
  "properties": {
    "iso:country":"US",
    "sg:address":"134 Cambridge St",
    "sg:city":"Burlington",
    "sg:classifiers":[
        {
            "category":"Real Estate",
            "subcategory":"Real Estate Services",
            "type":"Services"
        },
        {
            "category":"Banks & Credit Unions",
            "subcategory":"Bank",
            "type":"Services"
        },
        {
            "category":"Banks & Credit Unions",
            "subcategory":"Financial Services",
            "type":"Services"
        }
    ],
    "sg:phone":"+1 781 238 8700",
    "sg:postcode":"01803",
    "sg:province":"MA",
    "sg:tags":[
        "saving",
        "mortgage",
        "loan",
        "commercial",
        "broker"
    ],
    "wof:name":"Century Bank",
    "wof:placetype":"venue"
},
  "geometry": {"coordinates":[-71.19499999999999,42.5019],"type":"Point"}
}