{
  "type": "Feature",
  "properties": {
    "iso:country":"US",
    "sg:address":"5 Cherry Hill Dr",
    "sg:city":"Danvers",
    "sg:classifiers":[
        {
            "category":"Restaurant",
            "type":"Food & Drink"
        }
    ],
    "sg:phone":"+1 978 774 5856",
    "sg:postcode":"01923",
    "sg:province":"MA",
    "wof:name":"Cherry Hill Cafe",
    "wof:placetype":"venue"
},
  "geometry": {"coordinates":[-70.914817,42.572527],"type":"Point"}
}