{
  "type": "Feature",
  "properties": {
    "iso:country":"US",
    "sg:address":"33 Faculty St",
    "sg:city":"Wilbraham",
    "sg:classifiers":[
        {
            "category":"Recreation",
            "type":"Entertainment"
        }
    ],
    "sg:phone":"+1 413 596 4046",
    "sg:postcode":"01095",
    "sg:province":"MA",
    "sg:tags":[
        "ticket"
    ],
    "wof:name":"Tickets For Groups",
    "wof:placetype":"venue"
},
  "geometry": {"coordinates":[-72.440658,42.1236],"type":"Point"}
}