{
  "type": "Feature",
  "properties": {
    "addr:full": "92 High St Medford MA 02155",
    "addr:housenumber": "92",
    "addr:postcode": "02155",
    "addr:street": "High St",
    "iso:country": "US",
    "sg:address": "92 High St",
    "sg:city": "Medford",
    "sg:classifiers": [
      {
        "category": "Health Services",
        "subcategory": "Doctor",
        "type": "Services"
      }
    ],
    "sg:phone": "+1 781 388 4100",
    "sg:postcode": "02155",
    "sg:province": "MA",
    "sg:tags": [
      "physician",
      "surgeon"
    ],
    "wof:name": "Family Healthcare Assoc",
    "wof:placetype": "venue"
  },
  "geometry": {"coordinates":[-71.112752,42.4189],"type":"Point"}
}
