{
  "type": "Feature",
  "properties": {
    "addr:full":"841 E Broadway Boston MA 02127",
    "addr:housenumber":"841",
    "addr:postcode":"02127",
    "addr:street":"E Broadway",
    "iso:country":"US",
    "sg:address":"841 E Broadway",
    "sg:city":"Boston",
    "sg:classifiers":[
        {
            "category":"Education",
            "subcategory":"School",
            "type":"Public Place"
        },
        {
            "category":"Organizations",
            "subcategory":"Religious Organization",
            "type":"Services"
        }
    ],
    "sg:phone":"+1 617 268 2122",
    "sg:postcode":"02127",
    "sg:province":"MA",
    "wof:name":"St Brigid's Rectory",
    "wof:placetype":"venue"
},
  "geometry": {"coordinates":[-71.030968,42.335813],"type":"Point"}
}