{
  "type": "Feature",
  "properties": {
    "iso:country":"US",
    "sg:address":"3860 Falmouth Rd",
    "sg:city":"Marstons Mills",
    "sg:classifiers":[
        {
            "category":"Banks & Credit Unions",
            "subcategory":"Bank",
            "type":"Services"
        }
    ],
    "sg:phone":"+1 508 428 6750",
    "sg:postcode":"02648",
    "sg:province":"MA",
    "sg:tags":[
        "loan",
        "real estate"
    ],
    "wof:name":"American Home Mortgage",
    "wof:placetype":"venue"
},
  "geometry": {"coordinates":[-70.42276699999999,41.648399],"type":"Point"}
}