{
  "type": "Feature",
  "properties": {
    "iso:country":"US",
    "sg:address":"20 Roseland St",
    "sg:city":"Dorchester Ctr",
    "sg:classifiers":[
        {
            "category":"Shopping",
            "type":"Retail Goods"
        }
    ],
    "sg:phone":"+1 617 822 0679",
    "sg:postcode":"02124",
    "sg:province":"MA",
    "sg:tags":[
        "religious"
    ],
    "wof:name":"Irish Pastoral Ctr",
    "wof:placetype":"venue"
},
  "geometry": {"coordinates":[-71.06286900000001,42.291212],"type":"Point"}
}