{
  "type": "Feature",
  "properties": {
    "addr:full":"535 Boylston St Boston MA 02116",
    "addr:housenumber":"535",
    "addr:postcode":"02116",
    "addr:street":"Boylston St",
    "iso:country":"US",
    "sg:address":"535 Boylston St",
    "sg:city":"Boston",
    "sg:classifiers":[
        {
            "category":"Professional",
            "subcategory":"Lawyer & Legal Services",
            "type":"Services"
        }
    ],
    "sg:phone":"+1 617 859 0500",
    "sg:postcode":"02116",
    "sg:province":"MA",
    "sg:tags":[
        "attorney"
    ],
    "wof:name":"Core Legal",
    "wof:placetype":"venue"
},
  "geometry": {"coordinates":[-71.077359,42.350159],"type":"Point"}
}