{
  "type": "Feature",
  "properties": {
    "iso:country":"US",
    "sg:address":"521 Tremont Street",
    "sg:city":"Boston",
    "sg:classifiers":[
        {
            "category":"Banks & Credit Unions",
            "subcategory":"Bank",
            "type":"Services"
        }
    ],
    "sg:phone":"+1 617 236 1333",
    "sg:postcode":"02116",
    "sg:province":"MA",
    "sg:website":"www.sovereignbank.com",
    "wof:name":"Sovereign Bank",
    "wof:placetype":"venue"
},
  "geometry": {"coordinates":[-71.07068599999999,42.34433],"type":"Point"}
}