{
  "type": "Feature",
  "properties": {
    "addr:full": "521 Tremont Street Boston MA 02116",
    "addr:housenumber": "521",
    "addr:postcode": "02116",
    "addr:street": "Tremont Street",
    "iso:country": "US",
    "sg:address": "521 Tremont Street",
    "sg:city": "Boston",
    "sg:classifiers": [
      {
        "category": "Banks \u0026 Credit Unions",
        "subcategory": "Bank",
        "type": "Services"
      }
    ],
    "sg:phone": "+1 617 236 1333",
    "sg:postcode": "02116",
    "sg:province": "MA",
    "sg:website": "www.sovereignbank.com",
    "wof:name": "Sovereign Bank",
    "wof:placetype": "venue"
  },
  "geometry": {"coordinates":[-71.070686,42.34433],"type":"Point"}
}
