{
  "type": "Feature",
  "properties": {
    "iso:country":"US",
    "sg:address":"47 Winthrop Ave",
    "sg:city":"Lowell",
    "sg:classifiers":[
        {
            "category":"Building & Trades",
            "subcategory":"Construction",
            "type":"Services"
        }
    ],
    "sg:phone":"+1 978 452 7321",
    "sg:postcode":"01851",
    "sg:province":"MA",
    "sg:tags":[
        "contractor"
    ],
    "wof:name":"Cunha Construction Co",
    "wof:placetype":"venue"
},
  "geometry": {"coordinates":[-71.32410400000001,42.627716],"type":"Point"}
}