{
  "type": "Feature",
  "properties": {
    "addr:full": "47 Winthrop Ave Lowell MA 01851",
    "addr:housenumber": "47",
    "addr:postcode": "01851",
    "addr:street": "Winthrop Ave",
    "iso:country": "US",
    "sg:address": "47 Winthrop Ave",
    "sg:city": "Lowell",
    "sg:classifiers": [
      {
        "category": "Building \u0026 Trades",
        "subcategory": "Construction",
        "type": "Services"
      }
    ],
    "sg:phone": "+1 978 452 7321",
    "sg:postcode": "01851",
    "sg:province": "MA",
    "sg:tags": [
      "contractor"
    ],
    "wof:name": "Cunha Construction Co",
    "wof:placetype": "venue"
  },
  "geometry": {"coordinates":[-71.324104,42.627716],"type":"Point"}
}
