{
  "type": "Feature",
  "properties": {
    "iso:country":"US",
    "sg:address":"70 Industrial Ave E",
    "sg:city":"Lowell",
    "sg:classifiers":[
        {
            "category":"Manufacturing",
            "subcategory":"Electronics",
            "type":"Manufacturing & Wholesale Goods"
        }
    ],
    "sg:phone":"+1 978 458 4624",
    "sg:postcode":"01852",
    "sg:province":"MA",
    "sg:tags":[
        "printed",
        "circuit",
        "etched"
    ],
    "wof:name":"Foresight Imaging",
    "wof:placetype":"venue"
},
  "geometry": {"coordinates":[-71.316457,42.615488],"type":"Point"}
}