{
  "type": "Feature",
  "properties": {
    "addr:full": "69 Brigham St Hudson MA 01749",
    "addr:housenumber": "69",
    "addr:postcode": "01749",
    "addr:street": "Brigham St",
    "iso:country": "US",
    "ovtr:label": "Hudson High School, 69 Brigham St Hudson MA US",
    "ovtr:similarity": 3.6742570400238037,
    "sg:address": "69 Brigham St",
    "sg:city": "Hudson",
    "sg:classifiers": [
      {
        "category": "Education",
        "subcategory": "School",
        "type": "Public Place"
      }
    ],
    "sg:phone": "+1 978 567 6250",
    "sg:postcode": "01749",
    "sg:province": "MA",
    "sg:tags": [
      "high"
    ],
    "sg:website": "http://www.hudson.k12.ma.us",
    "wof:name": "Hudson High School",
    "wof:placetype": "venue"
  },
  "geometry": {"coordinates":[-71.579356,42.377365],"type":"Point"}
}
