{
  "type": "Feature",
  "properties": {
    "iso:country":"US",
    "sg:address":"69 Brigham St",
    "sg:city":"Hudson",
    "sg:classifiers":[
        {
            "category":"Education",
            "subcategory":"School",
            "type":"Public Place"
        }
    ],
    "sg:phone":"+1 978 567 6250",
    "sg:postcode":"01749",
    "sg:province":"MA",
    "sg:tags":[
        "high"
    ],
    "sg:website":"http://www.hudson.k12.ma.us",
    "wof:name":"Hudson High School",
    "wof:placetype":"venue"
},
  "geometry": {"coordinates":[-71.579356,42.377365],"type":"Point"}
}