{
  "type": "Feature",
  "properties": {
    "addr:full":"16 Joyce Rd Peabody MA 01960",
    "addr:housenumber":"16",
    "addr:postcode":"01960",
    "addr:street":"Joyce Rd",
    "iso:country":"US",
    "sg:address":"16 Joyce Rd",
    "sg:city":"Peabody",
    "sg:classifiers":[
        {
            "category":"Shopping",
            "subcategory":"Gifts & Souvenirs",
            "type":"Retail Goods"
        }
    ],
    "sg:phone":"+1   ",
    "sg:postcode":"01960",
    "sg:province":"MA",
    "sg:tags":[
        "shop",
        "novelty"
    ],
    "wof:name":"Jean Jackson",
    "wof:placetype":"venue"
},
  "geometry": {"coordinates":[-70.982783,42.515902],"type":"Point"}
}