{
  "type": "Feature",
  "properties": {
    "addr:full": "138 Ocean St Hyannis MA 02601",
    "addr:housenumber": "138",
    "addr:postcode": "02601",
    "addr:street": "Ocean St",
    "iso:country": "US",
    "sg:address": "138 Ocean St",
    "sg:city": "Hyannis",
    "sg:classifiers": [
      {
        "category": "Recreation",
        "type": "Entertainment"
      }
    ],
    "sg:phone": "+1 508 790 0696",
    "sg:postcode": "02601",
    "sg:province": "MA",
    "sg:tags": [
      "party",
      "fishing"
    ],
    "wof:name": "Hy Line Cruises",
    "wof:placetype": "venue"
  },
  "geometry": {"coordinates":[-70.279951,41.649991],"type":"Point"}
}
