{
  "type": "Feature",
  "properties": {
    "addr:full":"2 Brewer St Cambridge MA 02138",
    "addr:housenumber":"2",
    "addr:postcode":"02138",
    "addr:street":"Brewer St",
    "iso:country":"US",
    "sg:address":"2 Brewer St",
    "sg:city":"Cambridge",
    "sg:classifiers":[
        {
            "category":"Professional",
            "subcategory":"Management & Consulting",
            "type":"Services"
        }
    ],
    "sg:phone":"+1   ",
    "sg:postcode":"02138",
    "sg:province":"MA",
    "sg:tags":[
        "personal",
        "development",
        "school"
    ],
    "wof:name":"Expedtonary Lrng Outward Bound",
    "wof:placetype":"venue"
},
  "geometry": {"coordinates":[-71.125069,42.373822],"type":"Point"}
}