{
  "type": "Feature",
  "properties": {
    "addr:full":"392 W Broadway Boston MA 02127",
    "addr:housenumber":"392",
    "addr:postcode":"02127",
    "addr:street":"W Broadway",
    "iso:country":"US",
    "sg:address":"392 W Broadway",
    "sg:city":"Boston",
    "sg:classifiers":[
        {
            "category":"Real Estate",
            "subcategory":"Real Estate Agent",
            "type":"Services"
        }
    ],
    "sg:phone":"+1 617 269 3999",
    "sg:postcode":"02127",
    "sg:province":"MA",
    "sg:tags":[
        "management"
    ],
    "wof:name":"Doyle Realty",
    "wof:placetype":"venue"
},
  "geometry": {"coordinates":[-71.048303,42.337385],"type":"Point"}
}