{
  "type": "Feature",
  "properties": {
    "iso:country":"US",
    "sg:address":"817 Main St",
    "sg:city":"Worcester",
    "sg:classifiers":[
        {
            "category":"Food & Beverages",
            "subcategory":"Liquor & Beverages",
            "type":"Retail Goods"
        }
    ],
    "sg:phone":"+1 508 752 0661",
    "sg:postcode":"01610",
    "sg:province":"MA",
    "wof:name":"Faucher & Masson Inc",
    "wof:placetype":"venue"
},
  "geometry": {"coordinates":[-71.81967899999999,42.251594],"type":"Point"}
}