{
  "type": "Feature",
  "properties": {
    "addr:full": "817 Main St Worcester MA 01610",
    "addr:housenumber": "817",
    "addr:postcode": "01610",
    "addr:street": "Main St",
    "iso:country": "US",
    "sg:address": "817 Main St",
    "sg:city": "Worcester",
    "sg:classifiers": [
      {
        "category": "Food \u0026 Beverages",
        "subcategory": "Liquor \u0026 Beverages",
        "type": "Retail Goods"
      }
    ],
    "sg:phone": "+1 508 752 0661",
    "sg:postcode": "01610",
    "sg:province": "MA",
    "wof:name": "Faucher \u0026 Masson Inc",
    "wof:placetype": "venue"
  },
  "geometry": {"coordinates":[-71.819679,42.251594],"type":"Point"}
}
