{
  "type": "Feature",
  "properties": {
    "iso:country":"US",
    "sg:address":"757 Boston Rd",
    "sg:city":"Springfield",
    "sg:classifiers":[
        {
            "category":"Restaurant",
            "type":"Food & Drink"
        }
    ],
    "sg:menulink":"http://www.allmenus.com/ma/springfield/173258-wendys/menu/",
    "sg:phone":"+1 413 783 7286",
    "sg:postcode":"01119",
    "sg:province":"MA",
    "sg:tags":[
        "burger",
        "american",
        "soup"
    ],
    "wof:name":"Wendy's",
    "wof:placetype":"venue"
},
  "geometry": {"coordinates":[-72.519473,42.136737],"type":"Point"}
}