{
  "type": "Feature",
  "properties": {
    "addr:full":"216 Boston Rd Southborough MA 01772",
    "addr:housenumber":"216",
    "addr:postcode":"01772",
    "addr:street":"Boston Rd",
    "iso:country":"US",
    "sg:address":"216 Boston Rd",
    "sg:city":"Southborough",
    "sg:classifiers":[
        {
            "category":"Manufacturing",
            "subcategory":"Printing",
            "type":"Manufacturing & Wholesale Goods"
        }
    ],
    "sg:phone":"+1 508 481 7709",
    "sg:postcode":"01772",
    "sg:province":"MA",
    "sg:tags":[
        "printer"
    ],
    "wof:name":"Quik Print",
    "wof:placetype":"venue"
},
  "geometry": {"coordinates":[-71.496104,42.298442],"type":"Point"}
}