{
  "type": "Feature",
  "properties": {
    "addr:full":"12 Driscoll Ln Beverly MA 01915",
    "addr:housenumber":"12",
    "addr:postcode":"01915",
    "addr:street":"Driscoll Ln",
    "iso:country":"US",
    "sg:address":"12 Driscoll Ln",
    "sg:city":"Beverly",
    "sg:classifiers":[
        {
            "category":"Professional",
            "subcategory":"Testing Lab",
            "type":"Services"
        }
    ],
    "sg:phone":"+1 978 500 9502",
    "sg:postcode":"01915",
    "sg:province":"MA",
    "sg:tags":[
        "laboratory"
    ],
    "wof:name":"Douglas Laboratories",
    "wof:placetype":"venue"
},
  "geometry": {"coordinates":[-70.83431899999999,42.582172],"type":"Point"}
}