{
  "type": "Feature",
  "properties": {
    "iso:country":"US",
    "sg:address":"67 Sharp St",
    "sg:city":"Hingham",
    "sg:classifiers":[
        {
            "category":"Wholesale",
            "subcategory":"Machinery & Supplies",
            "type":"Manufacturing & Wholesale Goods"
        }
    ],
    "sg:phone":"+1 781 331 4280",
    "sg:postcode":"02043",
    "sg:province":"MA",
    "sg:tags":[
        "equipment",
        "system",
        "vacuum"
    ],
    "sg:website":"www.alcatelvacuumus.com",
    "wof:name":"Alcatel Vacuum Products",
    "wof:placetype":"venue"
},
  "geometry": {"coordinates":[-70.921725,42.162794],"type":"Point"}
}