{
  "type": "Feature",
  "properties": {
    "addr:full": "381 Main St West Newbury MA 01985",
    "addr:housenumber": "381",
    "addr:postcode": "01985",
    "addr:street": "Main St",
    "iso:country": "US",
    "sg:address": "381 Main St",
    "sg:city": "West Newbury",
    "sg:classifiers": [
      {
        "category": "Government",
        "subcategory": "Office",
        "type": "Public Place"
      }
    ],
    "sg:phone": "+1 978 363 1100",
    "sg:postcode": "01985",
    "sg:province": "MA",
    "sg:tags": [
      "village"
    ],
    "wof:name": "Selectman's Office",
    "wof:placetype": "venue"
  },
  "geometry": {"coordinates":[-70.995337,42.796817],"type":"Point"}
}
