{
  "type": "Feature",
  "properties": {
    "iso:country":"US",
    "sg:address":"16 Bennington St",
    "sg:city":"East Boston",
    "sg:classifiers":[
        {
            "category":"Restaurant",
            "type":"Food & Drink"
        }
    ],
    "sg:phone":"+1 617 569 7770",
    "sg:postcode":"02128",
    "sg:province":"MA",
    "sg:tags":[
        "american",
        "latin"
    ],
    "wof:name":"Punto Rojo",
    "wof:placetype":"venue"
},
  "geometry": {"coordinates":[-70.99199299999999,42.397201],"type":"Point"}
}