{
  "type": "Feature",
  "properties": {
    "addr:full":"34 Main St Amherst MA 01002",
    "addr:housenumber":"34",
    "addr:postcode":"01002",
    "addr:street":"Main St",
    "iso:country":"US",
    "sg:address":"34 Main St",
    "sg:city":"Amherst",
    "sg:classifiers":[
        {
            "category":"Personal",
            "type":"Services"
        }
    ],
    "sg:phone":"+1 413 256 4991",
    "sg:postcode":"01002",
    "sg:province":"MA",
    "sg:tags":[
        "electrolysis"
    ],
    "wof:name":"Barbieri & Barbieri",
    "wof:placetype":"venue"
},
  "geometry": {"coordinates":[-72.519509,42.375745],"type":"Point"}
}