{
  "type": "Feature",
  "properties": {
    "iso:country":"US",
    "sg:address":"25 Rochdale St",
    "sg:city":"Auburn",
    "sg:classifiers":[
        {
            "category":"Personal",
            "subcategory":"Beauty Salon",
            "type":"Services"
        }
    ],
    "sg:phone":"+1 508 832 0544",
    "sg:postcode":"01501",
    "sg:province":"MA",
    "wof:name":"Karen's Corner Cuts",
    "wof:placetype":"venue"
},
  "geometry": {"coordinates":[-71.846007,42.217825],"type":"Point"}
}