{
  "type": "Feature",
  "properties": {
    "iso:country":"US",
    "sg:address":"206 Haverhill St",
    "sg:city":"Lawrence",
    "sg:classifiers":[
        {
            "category":"Professional",
            "subcategory":"Lawyer & Legal Services",
            "type":"Services"
        }
    ],
    "sg:phone":"+1 978 687 1777",
    "sg:postcode":"01840",
    "sg:province":"MA",
    "sg:tags":[
        "attorney"
    ],
    "wof:name":"Kara Difruscia",
    "wof:placetype":"venue"
},
  "geometry": {"coordinates":[-71.160861,42.710351],"type":"Point"}
}