{
  "type": "Feature",
  "properties": {
    "iso:country":"US",
    "sg:address":"438 Massachusetts Ave",
    "sg:city":"Arlington",
    "sg:classifiers":[
        {
            "category":"Shopping",
            "subcategory":"Computers & Home Electronics",
            "type":"Retail Goods"
        }
    ],
    "sg:phone":"+1 781 316 2651",
    "sg:postcode":"02474",
    "sg:province":"MA",
    "sg:tags":[
        "software"
    ],
    "wof:name":"Business Software Systems",
    "wof:placetype":"venue"
},
  "geometry": {"coordinates":[-71.15068100000001,42.413969],"type":"Point"}
}