{
  "type": "Feature",
  "properties": {
    "iso:country":"US",
    "sg:address":"252 County St",
    "sg:city":"New Bedford",
    "sg:classifiers":[
        {
            "category":"Social Services",
            "type":"Services"
        }
    ],
    "sg:phone":"+1 508 996 3343",
    "sg:postcode":"02740",
    "sg:province":"MA",
    "sg:tags":[
        "organization",
        "welfare"
    ],
    "wof:name":"Greater New Bedford Women's",
    "wof:placetype":"venue"
},
  "geometry": {"coordinates":[-70.924961,41.624283],"type":"Point"}
}