{
  "type": "Feature",
  "properties": {
    "addr:full": "151 E Central St Natick MA 01760",
    "addr:housenumber": "151",
    "addr:postcode": "01760",
    "addr:street": "E Central St",
    "iso:country": "US",
    "sg:address": "151 E Central St",
    "sg:city": "Natick",
    "sg:classifiers": [
      {
        "category": "Retail",
        "subcategory": "Auto Repair",
        "type": "Services"
      }
    ],
    "sg:phone": "+1 508 653 9074",
    "sg:postcode": "01760",
    "sg:province": "MA",
    "sg:tags": [
      "repairing",
      "automobile"
    ],
    "wof:name": "Frazee Automotive",
    "wof:placetype": "venue"
  },
  "geometry": {"coordinates":[-71.333486,42.287592],"type":"Point"}
}
