{
  "type": "Feature",
  "properties": {
    "addr:full": "1 Van de Graaff Dr Burlington MA 01803",
    "addr:housenumber": "1",
    "addr:postcode": "01803",
    "addr:street": "Van;Graaff Dr",
    "iso:country": "US",
    "sg:address": "1 Van de Graaff Dr",
    "sg:city": "Burlington",
    "sg:classifiers": [
      {
        "category": "Banks \u0026 Credit Unions",
        "subcategory": "Bank",
        "type": "Services"
      }
    ],
    "sg:phone": "+1 781 272 3825",
    "sg:postcode": "01803",
    "sg:province": "MA",
    "sg:tags": [
      "machine",
      "teller",
      "automated"
    ],
    "wof:name": "Corporate Atm Svc",
    "wof:placetype": "venue"
  },
  "geometry": {"coordinates":[-71.195521,42.483601],"type":"Point"}
}
