{
  "type": "Feature",
  "properties": {
    "addr:full":"700 Boston Rd Ste 9 Billerica MA 01821",
    "addr:housenumber":"700",
    "addr:postcode":"01821",
    "addr:street":"Boston Rd Ste 9",
    "iso:country":"US",
    "sg:address":"700 Boston Rd Ste 9",
    "sg:city":"Billerica",
    "sg:classifiers":[
        {
            "category":"Shopping",
            "subcategory":"Clothing, Apparel, & Fashions",
            "type":"Retail Goods"
        }
    ],
    "sg:phone":"+1 978 667 3488",
    "sg:postcode":"01821",
    "sg:province":"MA",
    "sg:tags":[
        "accessory"
    ],
    "sg:website":"fashionbug.charmingshoppes.com",
    "wof:name":"Fashion Bug the",
    "wof:placetype":"venue"
},
  "geometry": {"coordinates":[-71.245255,42.539015],"type":"Point"}
}