{
  "type": "Feature",
  "properties": {
    "iso:country":"US",
    "sg:address":"99 Summer Street",
    "sg:city":"Boston",
    "sg:classifiers":[
        {
            "category":"Professional",
            "subcategory":"Lawyer & Legal Services",
            "type":"Services"
        }
    ],
    "sg:phone":"+1 617 951 2300",
    "sg:postcode":"02110",
    "sg:province":"MA",
    "wof:name":"Puleo Nancy J Atty",
    "wof:placetype":"venue"
},
  "geometry": {"coordinates":[-71.058138,42.353847],"type":"Point"}
}