{
  "type": "Feature",
  "properties": {
    "iso:country":"US",
    "sg:address":"508 Harvard Rd",
    "sg:city":"Lancaster",
    "sg:classifiers":[
        {
            "category":"Building & Trades",
            "subcategory":"Cleaning & Sanitation",
            "type":"Services"
        }
    ],
    "sg:phone":"+1 978 343 2755",
    "sg:postcode":"01523",
    "sg:province":"MA",
    "sg:tags":[
        "fireplace",
        "chimney"
    ],
    "wof:name":"Patriot Chimney Svc",
    "wof:placetype":"venue"
},
  "geometry": {"coordinates":[-71.664905,42.467192],"type":"Point"}
}