{
  "type": "Feature",
  "properties": {
    "iso:country":"US",
    "sg:address":"1000 Franklin Village Dr",
    "sg:city":"Franklin",
    "sg:classifiers":[
        {
            "category":"Real Estate",
            "subcategory":"Developer",
            "type":"Services"
        }
    ],
    "sg:phone":"+1 508 528 3700",
    "sg:postcode":"02038",
    "sg:province":"MA",
    "sg:website":"www.caldevel.com",
    "wof:name":"Calarese Development Corp",
    "wof:placetype":"venue"
},
  "geometry": {"coordinates":[-71.422454,42.090735],"type":"Point"}
}