{
  "type": "Feature",
  "properties": {
    "addr:full": "291 Montvale Ave Woburn MA 01801",
    "addr:housenumber": "291",
    "addr:postcode": "01801",
    "addr:street": "Montvale Ave",
    "iso:country": "US",
    "sg:address": "291 Montvale Ave",
    "sg:city": "Woburn",
    "sg:classifiers": [
      {
        "category": "Home \u0026 Garden",
        "subcategory": "Household Appliances",
        "type": "Retail Goods"
      },
      {
        "category": "Building \u0026 Trades",
        "subcategory": "Cleaning \u0026 Sanitation",
        "type": "Services"
      }
    ],
    "sg:phone": "+1 781 935 2704",
    "sg:postcode": "01801",
    "sg:province": "MA",
    "sg:tags": [
      "repair"
    ],
    "wof:name": "Easy Housekeeping Shops",
    "wof:placetype": "venue"
  },
  "geometry": {"coordinates":[-71.121696,42.479801],"type":"Point"}
}
