{
  "type": "Feature",
  "properties": {
    "iso:country":"US",
    "sg:address":"291 Montvale Ave",
    "sg:city":"Woburn",
    "sg:classifiers":[
        {
            "category":"Home & Garden",
            "subcategory":"Household Appliances",
            "type":"Retail Goods"
        },
        {
            "category":"Building & Trades",
            "subcategory":"Cleaning & Sanitation",
            "type":"Services"
        }
    ],
    "sg:phone":"+1 781 935 2704",
    "sg:postcode":"01801",
    "sg:province":"MA",
    "sg:tags":[
        "repair"
    ],
    "wof:name":"Easy Housekeeping Shops",
    "wof:placetype":"venue"
},
  "geometry": {"coordinates":[-71.121696,42.479801],"type":"Point"}
}