{
  "type": "Feature",
  "properties": {
    "iso:country":"US",
    "sg:address":"308 Hartford Pike",
    "sg:city":"Shrewsbury",
    "sg:classifiers":[
        {
            "category":"Restaurant",
            "type":"Food & Drink"
        }
    ],
    "sg:phone":"+1 508 754 2117",
    "sg:postcode":"01545",
    "sg:province":"MA",
    "wof:name":"Dianna's Family Restaurant",
    "wof:placetype":"venue"
},
  "geometry": {"coordinates":[-71.714433,42.249611],"type":"Point"}
}