{
  "type": "Feature",
  "properties": {
    "addr:full": "223 Charlton Rd Spencer MA 01562",
    "addr:housenumber": "223",
    "addr:postcode": "01562",
    "addr:street": "Charlton Rd",
    "iso:country": "US",
    "sg:address": "223 Charlton Rd",
    "sg:city": "Spencer",
    "sg:classifiers": [
      {
        "category": "Building \u0026 Trades",
        "subcategory": "Construction",
        "type": "Services"
      }
    ],
    "sg:phone": "+1   ",
    "sg:postcode": "01562",
    "sg:province": "MA",
    "sg:tags": [
      "contractor"
    ],
    "wof:name": "Schrader Plastering",
    "wof:placetype": "venue"
  },
  "geometry": {"coordinates":[-71.987244,42.200631],"type":"Point"}
}
