{
  "type": "Feature",
  "properties": {
    "addr:full": "30 Scout Ln North Attleboro MA 02760",
    "addr:housenumber": "30",
    "addr:postcode": "02760",
    "addr:street": "Scout Ln",
    "iso:country": "US",
    "sg:address": "30 Scout Ln",
    "sg:city": "North Attleboro",
    "sg:classifiers": [
      {
        "category": "Building \u0026 Trades",
        "subcategory": "Construction",
        "type": "Services"
      }
    ],
    "sg:phone": "+1 508 695 6401",
    "sg:postcode": "02760",
    "sg:province": "MA",
    "sg:tags": [
      "contractor"
    ],
    "wof:name": "Bryson J M Custom Building \u0026 Repair - CLOSED",
    "wof:placetype": "venue"
  },
  "geometry": {"coordinates":[-71.289902,41.9804],"type":"Point"}
}
