{
  "type": "Feature",
  "properties": {
    "addr:full": "45 Lakeside Ave Marlborough MA 01752",
    "addr:housenumber": "45",
    "addr:postcode": "01752",
    "addr:street": "Lakeside Ave",
    "iso:country": "US",
    "sg:address": "45 Lakeside Ave",
    "sg:city": "Marlborough",
    "sg:classifiers": [
      {
        "category": "Professional",
        "subcategory": "Computer Services",
        "type": "Services"
      }
    ],
    "sg:phone": "+1 508 481 6776",
    "sg:postcode": "01752",
    "sg:province": "MA",
    "sg:tags": [
      "website",
      "design"
    ],
    "sg:website": "www.wonderspace.com",
    "wof:name": "Alice's Enterprises",
    "wof:placetype": "venue"
  },
  "geometry": {"coordinates":[-71.56298,42.340358],"type":"Point"}
}
