{
  "type": "Feature",
  "properties": {
    "addr:full":"375 Totten Pond Road Suite 400 Waltham MA 02451",
    "addr:housenumber":"375",
    "addr:postcode":"02451",
    "addr:street":"Totten Pond Road Suite 400",
    "iso:country":"US",
    "sg:address":"375 Totten Pond Road Suite 400",
    "sg:city":"Waltham",
    "sg:classifiers":[
        {
            "category":"Professional",
            "subcategory":"Computer Services",
            "type":"Services"
        }
    ],
    "sg:phone":"+1 781 810 2700",
    "sg:postcode":"02451",
    "sg:province":"MA",
    "sg:tags":[
        "mobile-research",
        "online-research",
        "engage"
    ],
    "sg:website":"http://www.invoke.com",
    "wof:name":"Invoke Solutions",
    "wof:placetype":"venue"
},
  "geometry": {"coordinates":[-71.256784,42.397141],"type":"Point"}
}