{
  "type": "Feature",
  "properties": {
    "addr:full":"8 North Ave Natick MA 01760",
    "addr:housenumber":"8",
    "addr:postcode":"01760",
    "addr:street":"North Ave",
    "iso:country":"US",
    "sg:address":"8 North Ave",
    "sg:city":"Natick",
    "sg:classifiers":[
        {
            "category":"Shopping",
            "type":"Retail Goods"
        }
    ],
    "sg:phone":"+1   ",
    "sg:postcode":"01760",
    "sg:province":"MA",
    "sg:tags":[
        "merchandise"
    ],
    "wof:name":"Hanna Hearing Aids Service",
    "wof:placetype":"venue"
},
  "geometry": {"coordinates":[-71.348254,42.285772],"type":"Point"}
}