{
  "type": "Feature",
  "properties": {
    "addr:full": "595 Pawtucket Blvd Lowell MA 01854",
    "addr:housenumber": "595",
    "addr:postcode": "01854",
    "addr:street": "Pawtucket Blvd",
    "iso:country": "US",
    "sg:address": "595 Pawtucket Blvd",
    "sg:city": "Lowell",
    "sg:classifiers": [
      {
        "category": "Social Services",
        "type": "Services"
      }
    ],
    "sg:phone": "+1 978 454 4234",
    "sg:postcode": "01854",
    "sg:province": "MA",
    "sg:tags": [
      "organization",
      "welfare"
    ],
    "wof:name": "Institute At Lowell",
    "wof:placetype": "venue"
  },
  "geometry": {"coordinates":[-71.355467,42.640765],"type":"Point"}
}
