{
  "type": "Feature",
  "properties": {
    "addr:full":"124 Elm St Westfield MA 01085",
    "addr:housenumber":"124",
    "addr:postcode":"01085",
    "addr:street":"Elm St",
    "iso:country":"US",
    "sg:address":"124 Elm St",
    "sg:city":"Westfield",
    "sg:classifiers":[
        {
            "category":"Real Estate",
            "subcategory":"Real Estate Agent",
            "type":"Services"
        }
    ],
    "sg:phone":"+1 413 485 0187",
    "sg:postcode":"01085",
    "sg:province":"MA",
    "wof:name":"Whip City Real Estate",
    "wof:placetype":"venue"
},
  "geometry": {"coordinates":[-72.748159,42.124163],"type":"Point"}
}