{
  "type": "Feature",
  "properties": {
    "iso:country":"US",
    "sg:address":"24 Scranton Ave",
    "sg:city":"Falmouth",
    "sg:classifiers":[
        {
            "category":"Travel",
            "subcategory":"Hotels & Motels",
            "type":"Entertainment"
        }
    ],
    "sg:phone":"+1 508 548 1110",
    "sg:postcode":"02540",
    "sg:province":"MA",
    "wof:name":"Motel 7 Seas",
    "wof:placetype":"venue"
},
  "geometry": {"coordinates":[-70.602361,41.552903],"type":"Point"}
}