{
  "type": "Feature",
  "properties": {
    "addr:full": "508 Medford St Somerville MA 02145",
    "addr:housenumber": "508",
    "addr:postcode": "02145",
    "addr:street": "Medford St",
    "iso:country": "US",
    "sg:address": "508 Medford St",
    "sg:city": "Somerville",
    "sg:classifiers": [
      {
        "category": "Food \u0026 Beverages",
        "subcategory": "Bakery",
        "type": "Retail Goods"
      }
    ],
    "sg:phone": "+1 617 625 5047",
    "sg:postcode": "02145",
    "sg:province": "MA",
    "sg:tags": [
      "baker"
    ],
    "sg:website": "www.gcasebakingco.com",
    "wof:name": "G Case Baking Co",
    "wof:placetype": "venue"
  },
  "geometry": {"coordinates":[-71.103096,42.395705],"type":"Point"}
}
