{
  "type": "Feature",
  "properties": {
    "addr:full": "707 Moody St Waltham MA 02453",
    "addr:housenumber": "707",
    "addr:postcode": "02453",
    "addr:street": "Moody St",
    "iso:country": "US",
    "sg:address": "707 Moody St",
    "sg:city": "Waltham",
    "sg:classifiers": [
      {
        "category": "Shopping",
        "type": "Retail Goods"
      }
    ],
    "sg:phone": "+1 781 647 0425",
    "sg:postcode": "02453",
    "sg:province": "MA",
    "sg:tags": [
      "religious"
    ],
    "wof:name": "Botanica San Miguel",
    "wof:placetype": "venue"
  },
  "geometry": {"coordinates":[-71.238826,42.363901],"type":"Point"}
}
