{
  "type": "Feature",
  "properties": {
    "iso:country":"US",
    "sg:address":"707 Moody St",
    "sg:city":"Waltham",
    "sg:classifiers":[
        {
            "category":"Shopping",
            "type":"Retail Goods"
        }
    ],
    "sg:phone":"+1 781 647 0425",
    "sg:postcode":"02453",
    "sg:province":"MA",
    "sg:tags":[
        "religious"
    ],
    "wof:name":"Botanica San Miguel",
    "wof:placetype":"venue"
},
  "geometry": {"coordinates":[-71.238826,42.363901],"type":"Point"}
}