{
  "type": "Feature",
  "properties": {
    "iso:country":"US",
    "sg:address":"142 Worcester Rd",
    "sg:city":"Framingham",
    "sg:classifiers":[
        {
            "category":"Shopping",
            "subcategory":"Jewelry",
            "type":"Retail Goods"
        }
    ],
    "sg:phone":"+1   ",
    "sg:postcode":"01702",
    "sg:province":"MA",
    "sg:tags":[
        "store"
    ],
    "wof:name":"Stardust Jewelers Framingham",
    "wof:placetype":"venue"
},
  "geometry": {"coordinates":[-71.403615,42.29848],"type":"Point"}
}