{
  "type": "Feature",
  "properties": {
    "addr:full": "22 Evergreen Dr Taunton MA 02780",
    "addr:housenumber": "22",
    "addr:postcode": "02780",
    "addr:street": "Evergreen Dr",
    "iso:country": "US",
    "sg:address": "22 Evergreen Dr",
    "sg:city": "Taunton",
    "sg:classifiers": [
      {
        "category": "Arena",
        "subcategory": "Sports Club",
        "type": "Entertainment"
      }
    ],
    "sg:phone": "+1 508 880 6228",
    "sg:postcode": "02780",
    "sg:province": "MA",
    "sg:tags": [
      "martial art",
      "instruction"
    ],
    "wof:name": "Gracie Noble Sampson",
    "wof:placetype": "venue"
  },
  "geometry": {"coordinates":[-71.140608,41.923937],"type":"Point"}
}
