{
  "type": "Feature",
  "properties": {
    "addr:full":"1131 Sandwich Rd Sagamore MA 02561",
    "addr:housenumber":"1131",
    "addr:postcode":"02561",
    "addr:street":"Sandwich Rd",
    "iso:country":"US",
    "sg:address":"1131 Sandwich Rd",
    "sg:city":"Sagamore",
    "sg:classifiers":[
        {
            "category":"Restaurant",
            "type":"Food & Drink"
        }
    ],
    "sg:phone":"+1 508 888 9707",
    "sg:postcode":"02561",
    "sg:province":"MA",
    "sg:website":"www.sagamoreinn.com",
    "wof:name":"Sagamore Inn",
    "wof:placetype":"venue"
},
  "geometry": {"coordinates":[-70.52348600000001,41.768386],"type":"Point"}
}