{
  "type": "Feature",
  "properties": {
    "iso:country":"US",
    "sg:address":"26 Lelandville Rd",
    "sg:city":"Charlton",
    "sg:classifiers":[
        {
            "category":"Building & Trades",
            "subcategory":"Construction",
            "type":"Services"
        }
    ],
    "sg:phone":"+1 508 248 6020",
    "sg:postcode":"01507",
    "sg:province":"MA",
    "sg:tags":[
        "contractor"
    ],
    "wof:name":"Bostonian Restorations Inc",
    "wof:placetype":"venue"
},
  "geometry": {"coordinates":[-71.92520500000001,42.098434],"type":"Point"}
}