{
  "type": "Feature",
  "properties": {
    "addr:full": "26 Lelandville Rd Charlton MA 01507",
    "addr:housenumber": "26",
    "addr:postcode": "01507",
    "addr:street": "Lelandville Rd",
    "iso:country": "US",
    "sg:address": "26 Lelandville Rd",
    "sg:city": "Charlton",
    "sg:classifiers": [
      {
        "category": "Building \u0026 Trades",
        "subcategory": "Construction",
        "type": "Services"
      }
    ],
    "sg:phone": "+1 508 248 6020",
    "sg:postcode": "01507",
    "sg:province": "MA",
    "sg:tags": [
      "contractor"
    ],
    "wof:name": "Bostonian Restorations Inc",
    "wof:placetype": "venue"
  },
  "geometry": {"coordinates":[-71.925205,42.098434],"type":"Point"}
}
