{
  "type": "Feature",
  "properties": {
    "addr:full":"101 Independence Mall Way Kingston MA 02364",
    "addr:housenumber":"101",
    "addr:postcode":"02364",
    "addr:street":"Independence Mall Way",
    "iso:country":"US",
    "sg:address":"101 Independence Mall Way",
    "sg:city":"Kingston",
    "sg:classifiers":[
        {
            "category":"Shopping",
            "subcategory":"Department Store",
            "type":"Retail Goods"
        }
    ],
    "sg:phone":"+1 781 585 1400",
    "sg:postcode":"02364",
    "sg:province":"MA",
    "sg:website":"http://www.macys.com",
    "wof:name":"Macy's",
    "wof:placetype":"venue"
},
  "geometry": {"coordinates":[-70.71363100000001,41.969269],"type":"Point"}
}