{
  "type": "Feature",
  "properties": {
    "addr:full": "19 Harbor Loop Gloucester MA 01930",
    "addr:housenumber": "19",
    "addr:postcode": "01930",
    "addr:street": "Harbor Loop",
    "iso:country": "US",
    "sg:address": "19 Harbor Loop",
    "sg:city": "Gloucester",
    "sg:classifiers": [
      {
        "category": "Manufacturing",
        "subcategory": "Printing",
        "type": "Manufacturing \u0026 Wholesale Goods"
      }
    ],
    "sg:phone": "+1 978 281 3222",
    "sg:postcode": "01930",
    "sg:province": "MA",
    "sg:tags": [
      "publisher"
    ],
    "wof:name": "Fran Jurga",
    "wof:placetype": "venue"
  },
  "geometry": {"coordinates":[-70.659799,42.611194],"type":"Point"}
}
