{
  "type": "Feature",
  "properties": {
    "addr:full": "101 Tremont Street Boston MA 02108",
    "addr:housenumber": "101",
    "addr:postcode": "02108",
    "addr:street": "Tremont Street",
    "iso:country": "US",
    "sg:address": "101 Tremont Street",
    "sg:city": "Boston",
    "sg:classifiers": [
      {
        "category": "Professional",
        "subcategory": "Lawyer \u0026 Legal Services",
        "type": "Services"
      }
    ],
    "sg:phone": "+1 617 423 1501",
    "sg:postcode": "02108",
    "sg:province": "MA",
    "wof:name": "Barnicle Nugent PA",
    "wof:placetype": "venue"
  },
  "geometry": {"coordinates":[-71.060946,42.357498],"type":"Point"}
}
