{
  "type": "Feature",
  "properties": {
    "addr:full": "407 Pleasant St Fall River MA 02721",
    "addr:housenumber": "407",
    "addr:postcode": "02721",
    "addr:street": "Pleasant St",
    "iso:country": "US",
    "sg:address": "407 Pleasant St",
    "sg:city": "Fall River",
    "sg:classifiers": [
      {
        "category": "Manufacturing",
        "subcategory": "Paper Products",
        "type": "Manufacturing \u0026 Wholesale Goods"
      }
    ],
    "sg:phone": "+1 508 673 3241",
    "sg:postcode": "02721",
    "sg:province": "MA",
    "sg:tags": [
      "converted",
      "prod"
    ],
    "sg:website": "www.lincolnpress.com",
    "wof:name": "Lincoln Press Co",
    "wof:placetype": "venue"
  },
  "geometry": {"coordinates":[-71.148568,41.69911],"type":"Point"}
}
