{
  "type": "Feature",
  "properties": {
    "addr:full": "10 Mount Auburn St Watertown MA 02472",
    "addr:housenumber": "10",
    "addr:postcode": "02472",
    "addr:street": "Mount Auburn St",
    "iso:country": "US",
    "sg:address": "10 Mount Auburn St",
    "sg:city": "Watertown",
    "sg:classifiers": [
      {
        "category": "Wholesale",
        "subcategory": "Stationery",
        "type": "Manufacturing \u0026 Wholesale Goods"
      }
    ],
    "sg:phone": "+1 617 972 6140",
    "sg:postcode": "02472",
    "sg:province": "MA",
    "sg:tags": [
      "school",
      "supply"
    ],
    "wof:name": "S'Cool Etc",
    "wof:placetype": "venue"
  },
  "geometry": {"coordinates":[-71.184668,42.365201],"type":"Point"}
}
