{
  "type": "Feature",
  "properties": {
    "iso:country":"US",
    "sg:address":"646 Broadway St",
    "sg:city":"Raynham",
    "sg:classifiers":[
        {
            "category":"Insurance",
            "subcategory":"Insurance Agent",
            "type":"Services"
        }
    ],
    "sg:phone":"+1 508 822 2799",
    "sg:postcode":"02767",
    "sg:province":"MA",
    "sg:website":"www.afmacedoinsurance.com",
    "wof:name":"A F Macedo Insurance",
    "wof:placetype":"venue"
},
  "geometry": {"coordinates":[-71.075245,41.945239],"type":"Point"}
}