{
  "type": "Feature",
  "properties": {
    "iso:country":"US",
    "sg:address":"50 Marion Rd",
    "sg:city":"Watertown",
    "sg:classifiers":[
        {
            "category":"Professional",
            "subcategory":"Management & Consulting",
            "type":"Services"
        }
    ],
    "sg:phone":"+1   ",
    "sg:postcode":"02472",
    "sg:province":"MA",
    "wof:name":"Aurora Enterprises",
    "wof:placetype":"venue"
},
  "geometry": {"coordinates":[-71.181472,42.371702],"type":"Point"}
}