{
  "type": "Feature",
  "properties": {
    "iso:country":"US",
    "sg:address":"106 E Main St",
    "sg:city":"Westborough",
    "sg:classifiers":[
        {
            "category":"Health Services",
            "subcategory":"Doctor",
            "type":"Services"
        }
    ],
    "sg:phone":"+1 508 871 0765",
    "sg:postcode":"01581",
    "sg:province":"MA",
    "sg:tags":[
        "physician",
        "surgeon"
    ],
    "sg:website":"www.fallonclinic.com",
    "wof:name":"Fallon Medical Ctr",
    "wof:placetype":"venue"
},
  "geometry": {"coordinates":[-71.607682,42.278374],"type":"Point"}
}