{
  "type": "Feature",
  "properties": {
    "addr:full":"776 Westfield St West Springfield MA 01089",
    "addr:housenumber":"776",
    "addr:postcode":"01089",
    "addr:street":"Westfield St",
    "iso:country":"US",
    "sg:address":"776 Westfield St",
    "sg:city":"West Springfield",
    "sg:classifiers":[
        {
            "category":"Real Estate",
            "subcategory":"Real Estate Agent",
            "type":"Services"
        }
    ],
    "sg:phone":"+1 413 737 7356",
    "sg:postcode":"01089",
    "sg:province":"MA",
    "sg:website":"www.c21a1nolan.com",
    "wof:name":"Century 21",
    "wof:placetype":"venue"
},
  "geometry": {"coordinates":[-72.636127,42.103572],"type":"Point"}
}