{
  "type": "Feature",
  "properties": {
    "addr:full": "150 Cross St The Ferryway School Malden MA 02148",
    "addr:housenumber": "150",
    "addr:postcode": "02148",
    "addr:street": "Cross St",
    "iso:country": "US",
    "sg:address": "150 Cross St The Ferryway School",
    "sg:city": "Malden",
    "sg:classifiers": [
      {
        "category": "Personal",
        "type": "Services"
      }
    ],
    "sg:phone": "+1 978 664 6555",
    "sg:postcode": "02148",
    "sg:province": "MA",
    "sg:tags": [
      "local"
    ],
    "sg:website": "www.gotbooks.com",
    "wof:name": "Got Books Donation Container",
    "wof:placetype": "venue"
  },
  "geometry": {"coordinates":[-71.059446,42.421217],"type":"Point"}
}
