{
  "type": "Feature",
  "properties": {
    "addr:full":"101 Kathleen Dr Plymouth MA 02360",
    "addr:housenumber":"101",
    "addr:postcode":"02360",
    "addr:street":"Kathleen Dr",
    "iso:country":"US",
    "sg:address":"101 Kathleen Dr",
    "sg:city":"Plymouth",
    "sg:classifiers":[
        {
            "category":"Arts & Performance",
            "subcategory":"Theater",
            "type":"Entertainment"
        }
    ],
    "sg:phone":"+1 508 224 5942",
    "sg:postcode":"02360",
    "sg:province":"MA",
    "sg:tags":[
        "bureau"
    ],
    "wof:name":"Sea Coast Entertainment Inc",
    "wof:placetype":"venue"
},
  "geometry": {"coordinates":[-70.553065,41.893057],"type":"Point"}
}