{
  "type": "Feature",
  "properties": {
    "addr:full":"10 Park Plz Boston MA 02116",
    "addr:housenumber":"10",
    "addr:postcode":"02116",
    "addr:street":"Park Plz",
    "iso:country":"US",
    "sg:address":"10 Park Plz",
    "sg:city":"Boston",
    "sg:classifiers":[
        {
            "category":"Government",
            "subcategory":"Office",
            "type":"Public Place"
        }
    ],
    "sg:phone":"+1 617 973 7189",
    "sg:postcode":"02116",
    "sg:province":"MA",
    "sg:website":"www.bostonmpo.org",
    "wof:name":"Transportation & Construction",
    "wof:placetype":"venue"
},
  "geometry": {"coordinates":[-71.06731600000001,42.352173],"type":"Point"}
}