{
  "type": "Feature",
  "properties": {
    "iso:country":"US",
    "sg:address":"887 Main St",
    "sg:city":"Waltham",
    "sg:classifiers":[
        {
            "category":"Shopping",
            "subcategory":"Bicycles & Sporting Goods",
            "type":"Retail Goods"
        }
    ],
    "sg:phone":"+1 781 894 2768",
    "sg:postcode":"02451",
    "sg:province":"MA",
    "wof:name":"Spoke N Wheel Inc",
    "wof:placetype":"venue"
},
  "geometry": {"coordinates":[-71.246691,42.376356],"type":"Point"}
}