{
  "type": "Feature",
  "properties": {
    "addr:full": "329 Broadway Everett MA 02149",
    "addr:housenumber": "329",
    "addr:postcode": "02149",
    "addr:street": "Broadway",
    "iso:country": "US",
    "sg:address": "329 Broadway",
    "sg:city": "Everett",
    "sg:classifiers": [
      {
        "category": "Education",
        "subcategory": "School",
        "type": "Public Place"
      }
    ],
    "sg:phone": "+1 617 394 2410",
    "sg:postcode": "02149",
    "sg:province": "MA",
    "sg:tags": [
      "high",
      "middle",
      "elementary"
    ],
    "wof:name": "Everett City of",
    "wof:placetype": "venue"
  },
  "geometry": {"coordinates":[-71.058401,42.404124],"type":"Point"}
}
