{
  "type": "Feature",
  "properties": {
    "addr:full": "44 Pond St Douglas MA 01516",
    "addr:housenumber": "44",
    "addr:postcode": "01516",
    "addr:street": "Pond St",
    "iso:country": "US",
    "sg:address": "44 Pond St",
    "sg:city": "Douglas",
    "sg:classifiers": [
      {
        "category": "Professional",
        "subcategory": "Accounting \u0026 Tax Preparation",
        "type": "Services"
      }
    ],
    "sg:phone": "+1 508 476 3236",
    "sg:postcode": "01516",
    "sg:province": "MA",
    "sg:tags": [
      "accountant"
    ],
    "wof:name": "Blatchford Public Accounting",
    "wof:placetype": "venue"
  },
  "geometry": {"coordinates":[-71.716204,42.082975],"type":"Point"}
}
