{
  "type": "Feature",
  "properties": {
    "addr:full":"20 Joseph E Warner Blvd North Dighton MA 02764",
    "addr:housenumber":"20",
    "addr:postcode":"02764",
    "addr:street":"Joseph E Warner Blvd",
    "iso:country":"US",
    "sg:address":"20 Joseph E Warner Blvd",
    "sg:city":"North Dighton",
    "sg:classifiers":[
        {
            "category":"Manufacturing",
            "subcategory":"Metals",
            "type":"Manufacturing & Wholesale Goods"
        }
    ],
    "sg:phone":"+1 508 822 5444",
    "sg:postcode":"02764",
    "sg:province":"MA",
    "sg:tags":[
        "product",
        "wire",
        "fabricated"
    ],
    "wof:name":"BIW Cable Systems",
    "wof:placetype":"venue"
},
  "geometry": {"coordinates":[-71.125626,41.865481],"type":"Point"}
}