{
  "type": "Feature",
  "properties": {
    "addr:full":"851 Main St South Weymouth MA 02190",
    "addr:housenumber":"851",
    "addr:postcode":"02190",
    "addr:street":"Main St",
    "iso:country":"US",
    "sg:address":"851 Main St",
    "sg:city":"South Weymouth",
    "sg:classifiers":[
        {
            "category":"Health Services",
            "subcategory":"Doctor",
            "type":"Services"
        }
    ],
    "sg:phone":"+1 781 337 6500",
    "sg:postcode":"02190",
    "sg:province":"MA",
    "sg:tags":[
        "physician",
        "surgeon"
    ],
    "wof:name":"Hypertension & Kidney Ctr",
    "wof:placetype":"venue"
},
  "geometry": {"coordinates":[-70.95547000000001,42.176301],"type":"Point"}
}