{
  "type": "Feature",
  "properties": {
    "addr:full": "206 Rogers St Lowell MA 01852",
    "addr:housenumber": "206",
    "addr:postcode": "01852",
    "addr:street": "Rogers St",
    "iso:country": "US",
    "sg:address": "206 Rogers St",
    "sg:city": "Lowell",
    "sg:classifiers": [
      {
        "category": "Social Services",
        "type": "Services"
      }
    ],
    "sg:phone": "+1 978 454 5405",
    "sg:postcode": "01852",
    "sg:province": "MA",
    "sg:tags": [
      "workers'",
      "volunteer",
      "placement",
      "welfare"
    ],
    "sg:website": "http://www.ywca.org",
    "wof:name": "Ywca",
    "wof:placetype": "venue"
  },
  "geometry": {"coordinates":[-71.2948,42.636292],"type":"Point"}
}
