{
  "type": "Feature",
  "properties": {
    "iso:country":"US",
    "sg:address":"28 State Street",
    "sg:city":"Boston",
    "sg:classifiers":[
        {
            "category":"Banks & Credit Unions",
            "subcategory":"Investment Brokerage",
            "type":"Services"
        }
    ],
    "sg:phone":"+1 617 747 5800",
    "sg:postcode":"02109",
    "sg:province":"MA",
    "sg:tags":[
        "investing"
    ],
    "wof:name":"High Rock Asset Management",
    "wof:placetype":"venue"
},
  "geometry": {"coordinates":[-71.05709400000001,42.358901],"type":"Point"}
}