{
  "type": "Feature",
  "properties": {
    "addr:full": "28 State Street Boston MA 02109",
    "addr:housenumber": "28",
    "addr:postcode": "02109",
    "addr:street": "State Street",
    "iso:country": "US",
    "sg:address": "28 State Street",
    "sg:city": "Boston",
    "sg:classifiers": [
      {
        "category": "Banks \u0026 Credit Unions",
        "subcategory": "Investment Brokerage",
        "type": "Services"
      }
    ],
    "sg:phone": "+1 617 747 5800",
    "sg:postcode": "02109",
    "sg:province": "MA",
    "sg:tags": [
      "investing"
    ],
    "wof:name": "High Rock Asset Management",
    "wof:placetype": "venue"
  },
  "geometry": {"coordinates":[-71.057094,42.358901],"type":"Point"}
}
