{
  "type": "Feature",
  "properties": {
    "addr:full": "18 Ballard Ct Southbridge MA 01550",
    "addr:housenumber": "18",
    "addr:postcode": "01550",
    "addr:street": "Ballard Ct",
    "iso:country": "US",
    "sg:address": "18 Ballard Ct",
    "sg:city": "Southbridge",
    "sg:classifiers": [
      {
        "category": "Organizations",
        "subcategory": "Community Association",
        "type": "Services"
      }
    ],
    "sg:phone": "+1 508 764 8940",
    "sg:postcode": "01550",
    "sg:province": "MA",
    "sg:tags": [
      "club"
    ],
    "wof:name": "Polish Club",
    "wof:placetype": "venue"
  },
  "geometry": {"coordinates":[-72.049017,42.081792],"type":"Point"}
}
