{
  "type": "Feature",
  "properties": {
    "addr:full": "66 Mall Rd Burlington MA 01803",
    "addr:housenumber": "66",
    "addr:postcode": "01803",
    "addr:street": "Mall Rd",
    "iso:country": "US",
    "sg:address": "66 Mall Rd",
    "sg:city": "Burlington",
    "sg:classifiers": [
      {
        "category": "Home \u0026 Garden",
        "subcategory": "Furniture",
        "type": "Retail Goods"
      }
    ],
    "sg:phone": "+1 781 273 2600",
    "sg:postcode": "01803",
    "sg:province": "MA",
    "sg:tags": [
      "store"
    ],
    "sg:website": "www.cabothouse.com",
    "wof:name": "Cabot House",
    "wof:placetype": "venue"
  },
  "geometry": {"coordinates":[-71.199799,42.4897],"type":"Point"}
}
