{
  "type": "Feature",
  "properties": {
    "addr:full":"35 Rockland St Quincy MA 02169",
    "addr:housenumber":"35",
    "addr:postcode":"02169",
    "addr:street":"Rockland St",
    "iso:country":"US",
    "sg:address":"35 Rockland St",
    "sg:city":"Quincy",
    "sg:classifiers":[
        {
            "category":"Recreation",
            "type":"Entertainment"
        }
    ],
    "sg:phone":"+1   ",
    "sg:postcode":"02169",
    "sg:province":"MA",
    "wof:name":"Quiet Storm Ocean Ventures",
    "wof:placetype":"venue"
},
  "geometry": {"coordinates":[-70.9601,42.26488],"type":"Point"}
}