{
  "type": "Feature",
  "properties": {
    "addr:full":"18 Breck St Milton MA 02186",
    "addr:housenumber":"18",
    "addr:postcode":"02186",
    "addr:street":"Breck St",
    "iso:country":"US",
    "sg:address":"18 Breck St",
    "sg:city":"Milton",
    "sg:classifiers":[
        {
            "category":"Building & Trades",
            "subcategory":"Construction",
            "type":"Services"
        }
    ],
    "sg:phone":"+1 617 696 6276",
    "sg:postcode":"02186",
    "sg:province":"MA",
    "sg:tags":[
        "company"
    ],
    "wof:name":"D & D Construction",
    "wof:placetype":"venue"
},
  "geometry": {"coordinates":[-71.085025,42.2576],"type":"Point"}
}