{
  "type": "Feature",
  "properties": {
    "addr:full":"Ocean Street HyLine Landing 230 Ocean St Hyannis MA 02601",
    "addr:housenumber":"230",
    "addr:postcode":"02601",
    "addr:street":"Ocean Street;Ocean St",
    "iso:country":"US",
    "sg:address":"Ocean Street HyLine Landing 230 Ocean St",
    "sg:city":"Hyannis",
    "sg:classifiers":[
        {
            "category":"Food & Beverages",
            "subcategory":"Specialty",
            "type":"Retail Goods"
        },
        {
            "category":"Restaurant",
            "type":"Food & Drink"
        }
    ],
    "sg:phone":"+1 508 775 8800",
    "sg:postcode":"02601",
    "sg:province":"MA",
    "sg:tags":[
        "seafood",
        "live/raw"
    ],
    "sg:website":"www.therawbar.com",
    "wof:name":"The Raw Bar",
    "wof:placetype":"venue"
},
  "geometry": {"coordinates":[-70.28014,41.647364],"type":"Point"}
}