{
  "type": "Feature",
  "properties": {
    "iso:country":"US",
    "sg:address":"38 Brunswick St",
    "sg:city":"Springfield",
    "sg:classifiers":[
        {
            "category":"Shopping",
            "subcategory":"Clothing, Apparel, & Fashions",
            "type":"Retail Goods"
        }
    ],
    "sg:phone":"+1   ",
    "sg:postcode":"01108",
    "sg:province":"MA",
    "wof:name":"Santas Socks",
    "wof:placetype":"venue"
},
  "geometry": {"coordinates":[-72.54366,42.087354],"type":"Point"}
}