{
  "type": "Feature",
  "properties": {
    "addr:full":"25 Bridge St Billerica MA 01821",
    "addr:housenumber":"25",
    "addr:postcode":"01821",
    "addr:street":"Bridge St",
    "iso:country":"US",
    "sg:address":"25 Bridge St",
    "sg:city":"Billerica",
    "sg:classifiers":[
        {
            "category":"Building & Trades",
            "subcategory":"Construction",
            "type":"Services"
        }
    ],
    "sg:phone":"+1 978 667 9736",
    "sg:postcode":"01821",
    "sg:province":"MA",
    "sg:tags":[
        "contractor"
    ],
    "wof:name":"Delsie-Mc Dowell Construction",
    "wof:placetype":"venue"
},
  "geometry": {"coordinates":[-71.286203,42.573632],"type":"Point"}
}