{
  "type": "Feature",
  "properties": {
    "iso:country":"US",
    "sg:address":"22 Laurel Ln",
    "sg:city":"Forestdale",
    "sg:classifiers":[
        {
            "category":"Professional",
            "subcategory":"Accounting & Tax Preparation",
            "type":"Services"
        }
    ],
    "sg:phone":"+1 508 539 0544",
    "sg:postcode":"02644",
    "sg:province":"MA",
    "sg:tags":[
        "return",
        "filing"
    ],
    "wof:name":"White's Tax & Financial Svc",
    "wof:placetype":"venue"
},
  "geometry": {"coordinates":[-70.51896600000001,41.676614],"type":"Point"}
}