{
  "type": "Feature",
  "properties": {
    "addr:full": "22 Laurel Ln Forestdale MA 02644",
    "addr:housenumber": "22",
    "addr:postcode": "02644",
    "addr:street": "Laurel Ln",
    "iso:country": "US",
    "sg:address": "22 Laurel Ln",
    "sg:city": "Forestdale",
    "sg:classifiers": [
      {
        "category": "Professional",
        "subcategory": "Accounting \u0026 Tax Preparation",
        "type": "Services"
      }
    ],
    "sg:phone": "+1 508 539 0544",
    "sg:postcode": "02644",
    "sg:province": "MA",
    "sg:tags": [
      "return",
      "filing"
    ],
    "wof:name": "White's Tax \u0026 Financial Svc",
    "wof:placetype": "venue"
  },
  "geometry": {"coordinates":[-70.518966,41.676614],"type":"Point"}
}
