{
  "type": "Feature",
  "properties": {
    "addr:full": "76 Shirley Ave Revere MA 02151",
    "addr:housenumber": "76",
    "addr:postcode": "02151",
    "addr:street": "Shirley Ave",
    "iso:country": "US",
    "sg:address": "76 Shirley Ave",
    "sg:city": "Revere",
    "sg:classifiers": [
      {
        "category": "Health Services",
        "subcategory": "Health Practitioner",
        "type": "Services"
      }
    ],
    "sg:phone": "+1 781 284 8277",
    "sg:postcode": "02151",
    "sg:province": "MA",
    "sg:tags": [
      "therapy",
      "physical"
    ],
    "wof:name": "Revere Physical Therapy",
    "wof:placetype": "venue"
  },
  "geometry": {"coordinates":[-70.997628,42.408349],"type":"Point"}
}
