{
  "type": "Feature",
  "properties": {
    "iso:country":"US",
    "sg:address":"76 Summer St",
    "sg:city":"Fitchburg",
    "sg:classifiers":[
        {
            "category":"Health Services",
            "subcategory":"Health Practitioner",
            "type":"Services"
        }
    ],
    "sg:phone":"+1   ",
    "sg:postcode":"01420",
    "sg:province":"MA",
    "wof:name":"Judith Kneen",
    "wof:placetype":"venue"
},
  "geometry": {"coordinates":[-71.787622,42.579836],"type":"Point"}
}