{
  "type": "Feature",
  "properties": {
    "iso:country":"US",
    "sg:address":"14 Pond St",
    "sg:city":"Canton",
    "sg:classifiers":[
        {
            "category":"Personal",
            "subcategory":"Beauty Salon",
            "type":"Services"
        }
    ],
    "sg:phone":"+1 781 821 1868",
    "sg:postcode":"02021",
    "sg:province":"MA",
    "wof:name":"Helen's Hair Styling",
    "wof:placetype":"venue"
},
  "geometry": {"coordinates":[-71.149957,42.145032],"type":"Point"}
}