{
  "type": "Feature",
  "properties": {
    "iso:country":"US",
    "sg:address":"27 Huntington Rd",
    "sg:city":"Plymouth",
    "sg:classifiers":[
        {
            "category":"Social Services",
            "subcategory":"Job Training",
            "type":"Services"
        }
    ],
    "sg:phone":"+1 508 732 0109",
    "sg:postcode":"02360",
    "sg:province":"MA",
    "sg:tags":[
        "rehabilitation"
    ],
    "wof:name":"Speech Pathology Assoc",
    "wof:placetype":"venue"
},
  "geometry": {"coordinates":[-70.704826,41.926199],"type":"Point"}
}