{
  "type": "Feature",
  "properties": {
    "iso:country":"US",
    "sg:address":"179 Main St",
    "sg:city":"Millville",
    "sg:classifiers":[
        {
            "category":"Utilities",
            "subcategory":"Refuse",
            "type":"Services"
        },
        {
            "category":"Utilities",
            "subcategory":"Recycling",
            "type":"Services"
        }
    ],
    "sg:phone":"+1 508 883 2980",
    "sg:postcode":"01529",
    "sg:province":"MA",
    "sg:tags":[
        "container",
        "garbage",
        "disposal",
        "collection",
        "removal",
        "equipment",
        "rubbish",
        "waste"
    ],
    "wof:name":"Lakeview Ent Inc",
    "wof:placetype":"venue"
},
  "geometry": {"coordinates":[-71.57730100000001,42.026779],"type":"Point"}
}