{
  "type": "Feature",
  "properties": {
    "iso:country":"US",
    "sg:address":"32 Driftway",
    "sg:city":"Scituate",
    "sg:classifiers":[
        {
            "category":"Autos & Motor Vehicles",
            "subcategory":"Automobile Sales",
            "type":"Retail Goods"
        }
    ],
    "sg:phone":"+1 781 544 3300",
    "sg:postcode":"02066",
    "sg:province":"MA",
    "sg:tags":[
        "car",
        "dealer"
    ],
    "wof:name":"Conway Auto Works",
    "wof:placetype":"venue"
},
  "geometry": {"coordinates":[-70.71746899999999,42.176496],"type":"Point"}
}