{
  "type": "Feature",
  "properties": {
    "iso:country":"US",
    "sg:address":"10 Jefferson Ave",
    "sg:city":"Salem",
    "sg:classifiers":[
        {
            "category":"Education",
            "subcategory":"School",
            "type":"Public Place"
        }
    ],
    "sg:phone":"+1 978 740 0044",
    "sg:postcode":"01970",
    "sg:province":"MA",
    "sg:website":"www.palmerinstitute.com",
    "wof:name":"Palmer Institute Of Massage",
    "wof:placetype":"venue"
},
  "geometry": {"coordinates":[-70.899011,42.51501],"type":"Point"}
}