{
  "type": "Feature",
  "properties": {
    "iso:country":"US",
    "sg:address":"93 Dyer St",
    "sg:city":"Fall River",
    "sg:classifiers":[
        {
            "category":"Retail",
            "subcategory":"Auto Repair",
            "type":"Services"
        }
    ],
    "sg:phone":"+1 508 678 8458",
    "sg:postcode":"02720",
    "sg:province":"MA",
    "sg:tags":[
        "repairing",
        "automobile"
    ],
    "wof:name":"Executive Auto Body",
    "wof:placetype":"venue"
},
  "geometry": {"coordinates":[-71.152415,41.715752],"type":"Point"}
}