{
  "type": "Feature",
  "properties": {
    "addr:full": "553 Washington St Duxbury MA 02332",
    "addr:housenumber": "553",
    "addr:postcode": "02332",
    "addr:street": "Washington St",
    "iso:country": "US",
    "sg:address": "553 Washington St",
    "sg:city": "Duxbury",
    "sg:classifiers": [
      {
        "category": "Recreation",
        "subcategory": "Marina",
        "type": "Entertainment"
      }
    ],
    "sg:phone": "+1 781 934 5302",
    "sg:postcode": "02332",
    "sg:province": "MA",
    "sg:tags": [
      "repairing",
      "equipment",
      "marine",
      "boat",
      "supply"
    ],
    "sg:website": "http://www.longpointmarine.com",
    "wof:name": "Long Point Marine Inc",
    "wof:placetype": "venue"
  },
  "geometry": {"coordinates":[-70.671889,42.042162],"type":"Point"}
}
