{
  "type": "Feature",
  "properties": {
    "iso:country":"US",
    "sg:address":"140 Main St",
    "sg:city":"Brockton",
    "sg:classifiers":[
        {
            "category":"Shopping",
            "subcategory":"Discount & Variety Stores",
            "type":"Retail Goods"
        }
    ],
    "sg:phone":"+1 508 583 1008",
    "sg:postcode":"02301",
    "sg:province":"MA",
    "wof:name":"Main Street Variety",
    "wof:placetype":"venue"
},
  "geometry": {"coordinates":[-71.01988,42.082553],"type":"Point"}
}