{
  "type": "Feature",
  "properties": {
    "addr:full": "5 Stockbridge Ave Dalton MA 01226",
    "addr:housenumber": "5",
    "addr:postcode": "01226",
    "addr:street": "Stockbridge Ave",
    "iso:country": "US",
    "sg:address": "5 Stockbridge Ave",
    "sg:city": "Dalton",
    "sg:classifiers": [
      {
        "category": "Professional",
        "type": "Services"
      }
    ],
    "sg:phone": "+1   ",
    "sg:postcode": "01226",
    "sg:province": "MA",
    "wof:name": "Linda Fellmann",
    "wof:placetype": "venue"
  },
  "geometry": {"coordinates":[-73.166823,42.474219],"type":"Point"}
}
