{
  "type": "Feature",
  "properties": {
    "iso:country":"US",
    "sg:address":"5 Stockbridge Ave",
    "sg:city":"Dalton",
    "sg:classifiers":[
        {
            "category":"Professional",
            "type":"Services"
        }
    ],
    "sg:phone":"+1   ",
    "sg:postcode":"01226",
    "sg:province":"MA",
    "wof:name":"Linda Fellmann",
    "wof:placetype":"venue"
},
  "geometry": {"coordinates":[-73.16682299999999,42.474219],"type":"Point"}
}