{
  "type": "Feature",
  "properties": {
    "iso:country":"US",
    "sg:address":"75 Fitzpatrick Rd",
    "sg:city":"Grafton",
    "sg:classifiers":[
        {
            "category":"Building & Trades",
            "subcategory":"Construction",
            "type":"Services"
        }
    ],
    "sg:phone":"+1 508 839 7756",
    "sg:postcode":"01519",
    "sg:province":"MA",
    "sg:tags":[
        "general",
        "contractor"
    ],
    "sg:website":"www.leclairebuilders.com",
    "wof:name":"Jon R Le Claire Builders Inc",
    "wof:placetype":"venue"
},
  "geometry": {"coordinates":[-71.71177400000001,42.189914],"type":"Point"}
}