{
  "type": "Feature",
  "properties": {
    "addr:full": "4 Arapaho Rd Worcester MA 01606",
    "addr:housenumber": "4",
    "addr:postcode": "01606",
    "addr:street": "Arapaho Rd",
    "iso:country": "US",
    "sg:address": "4 Arapaho Rd",
    "sg:city": "Worcester",
    "sg:classifiers": [
      {
        "category": "Professional",
        "subcategory": "Computer Services",
        "type": "Services"
      }
    ],
    "sg:phone": "+1   ",
    "sg:postcode": "01606",
    "sg:province": "MA",
    "sg:tags": [
      "build"
    ],
    "wof:name": "Hoovers Computer Services",
    "wof:placetype": "venue"
  },
  "geometry": {"coordinates":[-71.812887,42.309132],"type":"Point"}
}
