{
  "type": "Feature",
  "properties": {
    "addr:full":"331 Russell St Hadley MA 01035",
    "addr:housenumber":"331",
    "addr:postcode":"01035",
    "addr:street":"Russell St",
    "iso:country":"US",
    "sg:address":"331 Russell St",
    "sg:city":"Hadley",
    "sg:classifiers":[
        {
            "category":"Shopping",
            "subcategory":"Bicycles & Sporting Goods",
            "type":"Retail Goods"
        }
    ],
    "sg:phone":"+1 413 585 8854",
    "sg:postcode":"01035",
    "sg:province":"MA",
    "wof:name":"Jonathan's Sports World",
    "wof:placetype":"venue"
},
  "geometry": {"coordinates":[-72.55678399999999,42.354811],"type":"Point"}
}