{
  "type": "Feature",
  "properties": {
    "addr:full":"325 Kennedy Rd Leeds MA 01053",
    "addr:housenumber":"325",
    "addr:postcode":"01053",
    "addr:street":"Kennedy Rd",
    "iso:country":"US",
    "sg:address":"325 Kennedy Rd",
    "sg:city":"Leeds",
    "sg:classifiers":[
        {
            "category":"Manufacturing",
            "subcategory":"Signs",
            "type":"Manufacturing & Wholesale Goods"
        }
    ],
    "sg:phone":"+1 413 584 5327",
    "sg:postcode":"01053",
    "sg:province":"MA",
    "wof:name":"Adams Signs",
    "wof:placetype":"venue"
},
  "geometry": {"coordinates":[-72.71987,42.356184],"type":"Point"}
}