{
  "type": "Feature",
  "properties": {
    "addr:full": "5 Saint Lukes Rd Allston MA 02134",
    "addr:housenumber": "5",
    "addr:postcode": "02134",
    "addr:street": "Saint Lukes Rd",
    "iso:country": "US",
    "sg:address": "5 Saint Lukes Rd",
    "sg:city": "Allston",
    "sg:classifiers": [
      {
        "category": "Place Of Worship",
        "subcategory": "Church",
        "type": "Public Place"
      }
    ],
    "sg:phone": "+1 617 782 2029",
    "sg:postcode": "02134",
    "sg:province": "MA",
    "sg:website": "www.forministry.com/USMAECUSASLASE",
    "wof:name": "Saint Luke's and Saint Margaret's Episcopal Church",
    "wof:placetype": "venue"
  },
  "geometry": {"coordinates":[-71.127002,42.352046],"type":"Point"}
}
