{
  "type": "Feature",
  "properties": {
    "addr:full": "722 Churchill St Pittsfield MA 01201",
    "addr:housenumber": "722",
    "addr:postcode": "01201",
    "addr:street": "Churchill St",
    "iso:country": "US",
    "sg:address": "722 Churchill St",
    "sg:city": "Pittsfield",
    "sg:classifiers": [
      {
        "category": "Travel",
        "subcategory": "Campground",
        "type": "Entertainment"
      }
    ],
    "sg:phone": "+1 413 443 3298",
    "sg:postcode": "01201",
    "sg:province": "MA",
    "sg:tags": [
      "camp"
    ],
    "wof:name": "Camp Winadu Operating Co",
    "wof:placetype": "venue"
  },
  "geometry": {"coordinates":[-73.28224,42.489852],"type":"Point"}
}
