{
  "type": "Feature",
  "properties": {
    "iso:country":"US",
    "sg:address":"800 Hingham St",
    "sg:city":"Rockland",
    "sg:classifiers":[
        {
            "category":"Manufacturing",
            "subcategory":"Paper Products",
            "type":"Manufacturing & Wholesale Goods"
        }
    ],
    "sg:phone":"+1 781 878 7708",
    "sg:postcode":"02370",
    "sg:province":"MA",
    "sg:tags":[
        "mill",
        "paperboard"
    ],
    "wof:name":"Lamitech",
    "wof:placetype":"venue"
},
  "geometry": {"coordinates":[-70.90353,42.159099],"type":"Point"}
}