{
  "type": "Feature",
  "properties": {
    "addr:full": "800 Hingham St Rockland MA 02370",
    "addr:housenumber": "800",
    "addr:postcode": "02370",
    "addr:street": "Hingham St",
    "iso:country": "US",
    "sg:address": "800 Hingham St",
    "sg:city": "Rockland",
    "sg:classifiers": [
      {
        "category": "Manufacturing",
        "subcategory": "Paper Products",
        "type": "Manufacturing \u0026 Wholesale Goods"
      }
    ],
    "sg:phone": "+1 781 878 7708",
    "sg:postcode": "02370",
    "sg:province": "MA",
    "sg:tags": [
      "mill",
      "paperboard"
    ],
    "wof:name": "Lamitech",
    "wof:placetype": "venue"
  },
  "geometry": {"coordinates":[-70.90353,42.159099],"type":"Point"}
}
