{
  "type": "Feature",
  "properties": {
    "iso:country":"US",
    "sg:address":"55 Hospital Dr",
    "sg:city":"Winchendon",
    "sg:classifiers":[
        {
            "category":"Health Services",
            "subcategory":"Doctor",
            "type":"Services"
        }
    ],
    "sg:phone":"+1 978 297 2311",
    "sg:postcode":"01475",
    "sg:province":"MA",
    "sg:tags":[
        "physician",
        "surgeon"
    ],
    "wof:name":"Winchendon Health Ctr",
    "wof:placetype":"venue"
},
  "geometry": {"coordinates":[-72.042424,42.664645],"type":"Point"}
}