{
  "type": "Feature",
  "properties": {
    "addr:full": "3 Hampden St Worcester MA 01609",
    "addr:housenumber": "3",
    "addr:postcode": "01609",
    "addr:street": "Hampden St",
    "iso:country": "US",
    "sg:address": "3 Hampden St",
    "sg:city": "Worcester",
    "sg:classifiers": [
      {
        "category": "Building \u0026 Trades",
        "subcategory": "Cleaning \u0026 Sanitation",
        "type": "Services"
      }
    ],
    "sg:phone": "+1 508 767 0014",
    "sg:postcode": "01609",
    "sg:province": "MA",
    "sg:tags": [
      "house"
    ],
    "wof:name": "Nooks \u0026 Crannies Commercial",
    "wof:placetype": "venue"
  },
  "geometry": {"coordinates":[-71.808545,42.269361],"type":"Point"}
}
