{
  "type": "Feature",
  "properties": {
    "addr:full":"1791 Boston Rd Springfield MA 01129",
    "addr:housenumber":"1791",
    "addr:postcode":"01129",
    "addr:street":"Boston Rd",
    "iso:country":"US",
    "sg:address":"1791 Boston Rd",
    "sg:city":"Springfield",
    "sg:classifiers":[
        {
            "category":"Shopping",
            "type":"Retail Goods"
        }
    ],
    "sg:phone":"+1 413 543 9200",
    "sg:postcode":"01129",
    "sg:province":"MA",
    "sg:tags":[
        "telephone",
        "cellular"
    ],
    "wof:name":"Digital Connection",
    "wof:placetype":"venue"
},
  "geometry": {"coordinates":[-72.483694,42.145524],"type":"Point"}
}