{
  "type": "Feature",
  "properties": {
    "addr:full": "1309 Commonwealth Avenue Allston MA 02134",
    "addr:housenumber": "1309",
    "addr:postcode": "02134",
    "addr:street": "Commonwealth Avenue",
    "iso:country": "US",
    "sg:address": "1309 Commonwealth Avenue",
    "sg:city": "Allston",
    "sg:classifiers": [
      {
        "category": "Building \u0026 Trades",
        "subcategory": "Locksmith",
        "type": "Services"
      }
    ],
    "sg:phone": "+1 617 287 2907",
    "sg:postcode": "02134",
    "sg:province": "MA",
    "sg:tags": [
      "key"
    ],
    "wof:name": "AA 1 Discount Locksmith",
    "wof:placetype": "venue"
  },
  "geometry": {"coordinates":[-71.134638,42.348803],"type":"Point"}
}
