{
  "type": "Feature",
  "properties": {
    "addr:full": "75 Williams St Jamaica Plain MA 02130",
    "addr:housenumber": "75",
    "addr:postcode": "02130",
    "addr:street": "Williams St",
    "iso:country": "US",
    "sg:address": "75 Williams St",
    "sg:city": "Jamaica Plain",
    "sg:classifiers": [
      {
        "category": "Professional",
        "subcategory": "Management \u0026 Consulting",
        "type": "Services"
      },
      {
        "category": "Professional",
        "subcategory": "Computer Services",
        "type": "Services"
      }
    ],
    "sg:phone": "+1 617 983 9611",
    "sg:postcode": "02130",
    "sg:province": "MA",
    "sg:tags": [
      "consultant",
      "business"
    ],
    "wof:name": "Gropp Consulting",
    "wof:placetype": "venue"
  },
  "geometry": {"coordinates":[-71.106785,42.30581],"type":"Point"}
}
