{
  "type": "Feature",
  "properties": {
    "addr:full":"6 Beacon St Ste 800 Boston MA 02108",
    "addr:housenumber":"6",
    "addr:postcode":"02108",
    "addr:street":"Beacon St Ste 800",
    "iso:country":"US",
    "sg:address":"6 Beacon St Ste 800",
    "sg:city":"Boston",
    "sg:classifiers":[
        {
            "category":"Professional",
            "subcategory":"Lawyer & Legal Services",
            "type":"Services"
        }
    ],
    "sg:phone":"+1 617 720 4529",
    "sg:postcode":"02108",
    "sg:province":"MA",
    "wof:name":"Schneiders Robert",
    "wof:placetype":"venue"
},
  "geometry": {"coordinates":[-71.061442,42.35821],"type":"Point"}
}