{
  "type": "Feature",
  "properties": {
    "iso:country":"US",
    "sg:address":"100 Huntington Ave.",
    "sg:city":"Boston",
    "sg:classifiers":[
        {
            "category":"Shopping",
            "subcategory":"Shoes",
            "type":"Retail Goods"
        }
    ],
    "sg:phone":"+1 617 536 9255",
    "sg:postcode":"02116",
    "sg:province":"MA",
    "sg:tags":[
        "store"
    ],
    "sg:website":"www.TheWalkingCompany.com",
    "wof:name":"The Walking Company",
    "wof:placetype":"venue"
},
  "geometry": {"coordinates":[-71.077828,42.347042],"type":"Point"}
}