{
  "type": "Feature",
  "properties": {
    "addr:full": "328 Bank St Harwich MA 02645",
    "addr:housenumber": "328",
    "addr:postcode": "02645",
    "addr:street": "Bank St",
    "iso:country": "US",
    "sg:address": "328 Bank St",
    "sg:city": "Harwich",
    "sg:classifiers": [
      {
        "category": "Social Services",
        "subcategory": "Adult Care",
        "type": "Services"
      }
    ],
    "sg:phone": "+1 508 430 7067",
    "sg:postcode": "02645",
    "sg:province": "MA",
    "sg:tags": [
      "home",
      "residential"
    ],
    "wof:name": "Royal Assisted Living",
    "wof:placetype": "venue"
  },
  "geometry": {"coordinates":[-70.071833,41.685029],"type":"Point"}
}
