{
  "type": "Feature",
  "properties": {
    "iso:country":"US",
    "sg:address":"328 Bank St",
    "sg:city":"Harwich",
    "sg:classifiers":[
        {
            "category":"Social Services",
            "subcategory":"Adult Care",
            "type":"Services"
        }
    ],
    "sg:phone":"+1 508 430 7067",
    "sg:postcode":"02645",
    "sg:province":"MA",
    "sg:tags":[
        "home",
        "residential"
    ],
    "wof:name":"Royal Assisted Living",
    "wof:placetype":"venue"
},
  "geometry": {"coordinates":[-70.071833,41.685029],"type":"Point"}
}