{
  "type": "Feature",
  "properties": {
    "iso:country":"US",
    "sg:address":"50 Main St Ste 201",
    "sg:city":"North Reading",
    "sg:classifiers":[
        {
            "category":"Professional",
            "subcategory":"Accounting & Tax Preparation",
            "type":"Services"
        }
    ],
    "sg:phone":"+1 978 276 1495",
    "sg:postcode":"01864",
    "sg:province":"MA",
    "sg:tags":[
        "accountant"
    ],
    "wof:name":"Hughes Gregory CPA",
    "wof:placetype":"venue"
},
  "geometry": {"coordinates":[-71.1092,42.5695],"type":"Point"}
}