{
  "type": "Feature",
  "properties": {
    "iso:country":"US",
    "sg:address":"91 W Main St",
    "sg:city":"West Brookfield",
    "sg:classifiers":[
        {
            "category":"Professional",
            "subcategory":"Lawyer & Legal Services",
            "type":"Services"
        }
    ],
    "sg:phone":"+1 508 867 7380",
    "sg:postcode":"01585",
    "sg:province":"MA",
    "sg:tags":[
        "attorney"
    ],
    "wof:name":"Bruce R Beard",
    "wof:placetype":"venue"
},
  "geometry": {"coordinates":[-72.150459,42.233536],"type":"Point"}
}