{
  "type": "Feature",
  "properties": {
    "addr:full": "40 Essex Rd Ipswich MA 01938",
    "addr:housenumber": "40",
    "addr:postcode": "01938",
    "addr:street": "Essex Rd",
    "iso:country": "US",
    "sg:address": "40 Essex Rd",
    "sg:city": "Ipswich",
    "sg:classifiers": [
      {
        "category": "Shopping",
        "type": "Retail Goods"
      }
    ],
    "sg:phone": "+1 978 356 0115",
    "sg:postcode": "01938",
    "sg:province": "MA",
    "sg:tags": [
      "picture",
      "frame"
    ],
    "wof:name": "Norris Gallery \u0026 Frame Shop",
    "wof:placetype": "venue"
  },
  "geometry": {"coordinates":[-70.833181,42.66381],"type":"Point"}
}
