{
  "type": "Feature",
  "properties": {
    "addr:full":"1476 Centre St Roslindale MA 02131",
    "addr:housenumber":"1476",
    "addr:postcode":"02131",
    "addr:street":"Centre St",
    "iso:country":"US",
    "sg:address":"1476 Centre St",
    "sg:city":"Roslindale",
    "sg:classifiers":[
        {
            "category":"Organizations",
            "subcategory":"Religious Organization",
            "type":"Services"
        }
    ],
    "sg:phone":"+1 617 323 6379",
    "sg:postcode":"02131",
    "sg:province":"MA",
    "wof:name":"Holy Orthodox Metropolis-Bos",
    "wof:placetype":"venue"
},
  "geometry": {"coordinates":[-71.138604,42.292174],"type":"Point"}
}