{
  "type": "Feature",
  "properties": {
    "iso:country":"US",
    "sg:address":"80 Billerica Ave",
    "sg:city":"North Billerica",
    "sg:classifiers":[
        {
            "category":"Food & Beverages",
            "subcategory":"Bakery",
            "type":"Retail Goods"
        }
    ],
    "sg:phone":"+1 978 667 8588",
    "sg:postcode":"01862",
    "sg:province":"MA",
    "sg:tags":[
        "doughnut"
    ],
    "wof:name":"Dunkin Donuts",
    "wof:placetype":"venue"
},
  "geometry": {"coordinates":[-71.282201,42.598822],"type":"Point"}
}