{
  "type": "Feature",
  "properties": {
    "addr:full": "80 Billerica Ave North Billerica MA 01862",
    "addr:housenumber": "80",
    "addr:postcode": "01862",
    "addr:street": "Billerica Ave North",
    "iso:country": "US",
    "sg:address": "80 Billerica Ave",
    "sg:city": "North Billerica",
    "sg:classifiers": [
      {
        "category": "Food \u0026 Beverages",
        "subcategory": "Bakery",
        "type": "Retail Goods"
      }
    ],
    "sg:phone": "+1 978 667 8588",
    "sg:postcode": "01862",
    "sg:province": "MA",
    "sg:tags": [
      "doughnut"
    ],
    "wof:name": "Dunkin Donuts",
    "wof:placetype": "venue"
  },
  "geometry": {"coordinates":[-71.282201,42.598822],"type":"Point"}
}
