{
  "type": "Feature",
  "properties": {
    "iso:country":"US",
    "sg:address":"1539 Broadway",
    "sg:city":"Saugus",
    "sg:classifiers":[
        {
            "category":"Restaurant",
            "type":"Food & Drink"
        }
    ],
    "sg:menulink":"http://www.allmenus.com/ma/saugus/131767-subway/menu/",
    "sg:phone":"+1 781 941 8055",
    "sg:postcode":"01906",
    "sg:province":"MA",
    "sg:tags":[
        "american",
        "sandwich"
    ],
    "wof:name":"Subway",
    "wof:placetype":"venue"
},
  "geometry": {"coordinates":[-71.023878,42.45451],"type":"Point"}
}