{
  "type": "Feature",
  "properties": {
    "addr:full": "1 Thayer St Methuen MA 01844",
    "addr:housenumber": "1",
    "addr:postcode": "01844",
    "addr:street": "Thayer St",
    "iso:country": "US",
    "sg:address": "1 Thayer St",
    "sg:city": "Methuen",
    "sg:classifiers": [
      {
        "category": "Building \u0026 Trades",
        "subcategory": "Construction",
        "type": "Services"
      }
    ],
    "sg:phone": "+1 978 688 3219",
    "sg:postcode": "01844",
    "sg:province": "MA",
    "sg:tags": [
      "contractor"
    ],
    "wof:name": "A J Zinno Construction Co",
    "wof:placetype": "venue"
  },
  "geometry": {"coordinates":[-71.163587,42.762716],"type":"Point"}
}
