{
  "type": "Feature",
  "properties": {
    "addr:full": "184 White St Belmont MA 02478",
    "addr:housenumber": "184",
    "addr:postcode": "02478",
    "addr:street": "White St",
    "iso:country": "US",
    "sg:address": "184 White St",
    "sg:city": "Belmont",
    "sg:classifiers": [
      {
        "category": "Building \u0026 Trades",
        "subcategory": "Construction",
        "type": "Services"
      }
    ],
    "sg:phone": "+1 617 484 2599",
    "sg:postcode": "02478",
    "sg:province": "MA",
    "sg:tags": [
      "contractor"
    ],
    "wof:name": "Doyle Construction",
    "wof:placetype": "venue"
  },
  "geometry": {"coordinates":[-71.187358,42.38232],"type":"Point"}
}
