{
  "type": "Feature",
  "properties": {
    "addr:full": "4 Meadowview Rd Wayland MA 01778",
    "addr:housenumber": "4",
    "addr:postcode": "01778",
    "addr:street": "Meadowview Rd",
    "iso:country": "US",
    "sg:address": "4 Meadowview Rd",
    "sg:city": "Wayland",
    "sg:classifiers": [
      {
        "category": "Recreation",
        "type": "Entertainment"
      }
    ],
    "sg:phone": "+1 508 877 2108",
    "sg:postcode": "01778",
    "sg:province": "MA",
    "sg:tags": [
      "club",
      "membership",
      "sporting"
    ],
    "wof:name": "Wayland Rod \u0026 Gun Club",
    "wof:placetype": "venue"
  },
  "geometry": {"coordinates":[-71.3893,42.340154],"type":"Point"}
}
