{
  "type": "Feature",
  "properties": {
    "iso:country":"US",
    "sg:address":"4 Meadowview Rd",
    "sg:city":"Wayland",
    "sg:classifiers":[
        {
            "category":"Recreation",
            "type":"Entertainment"
        }
    ],
    "sg:phone":"+1 508 877 2108",
    "sg:postcode":"01778",
    "sg:province":"MA",
    "sg:tags":[
        "club",
        "membership",
        "sporting"
    ],
    "wof:name":"Wayland Rod & Gun Club",
    "wof:placetype":"venue"
},
  "geometry": {"coordinates":[-71.38930000000001,42.340154],"type":"Point"}
}