{
  "type": "Feature",
  "properties": {
    "addr:full":"33 Fairview St Fitchburg MA 01420",
    "addr:housenumber":"33",
    "addr:postcode":"01420",
    "addr:street":"Fairview St",
    "iso:country":"US",
    "sg:address":"33 Fairview St",
    "sg:city":"Fitchburg",
    "sg:classifiers":[
        {
            "category":"Building & Trades",
            "subcategory":"Cleaning & Sanitation",
            "type":"Services"
        }
    ],
    "sg:phone":"+1 978 345 4111",
    "sg:postcode":"01420",
    "sg:province":"MA",
    "sg:tags":[
        "janitor"
    ],
    "wof:name":"Albert's Complete Cleaning Svc",
    "wof:placetype":"venue"
},
  "geometry": {"coordinates":[-71.83633399999999,42.576011],"type":"Point"}
}