{
  "type": "Feature",
  "properties": {
    "addr:full":"167 Bedford St Middleboro MA 02346",
    "addr:housenumber":"167",
    "addr:postcode":"02346",
    "addr:street":"Bedford St",
    "iso:country":"US",
    "sg:address":"167 Bedford St",
    "sg:city":"Middleboro",
    "sg:classifiers":[
        {
            "category":"Retail",
            "subcategory":"Auto Repair",
            "type":"Services"
        }
    ],
    "sg:phone":"+1 508 946 9570",
    "sg:postcode":"02346",
    "sg:province":"MA",
    "sg:tags":[
        "automotive"
    ],
    "wof:name":"A To Z Towing",
    "wof:placetype":"venue"
},
  "geometry": {"coordinates":[-70.963263,41.9241],"type":"Point"}
}