{
  "type": "Feature",
  "properties": {
    "iso:country":"US",
    "sg:address":"39 Central St",
    "sg:city":"Rowley",
    "sg:classifiers":[
        {
            "category":"Government",
            "subcategory":"Office",
            "type":"Public Place"
        }
    ],
    "sg:phone":"+1 978 948 7637",
    "sg:postcode":"01969",
    "sg:province":"MA",
    "sg:tags":[
        "city",
        "resource",
        "human"
    ],
    "wof:name":"Rowley Council On Aging",
    "wof:placetype":"venue"
},
  "geometry": {"coordinates":[-70.88022100000001,42.718105],"type":"Point"}
}