{
  "type": "Feature",
  "properties": {
    "iso:country":"US",
    "sg:address":"655 Haverhill St",
    "sg:city":"Lawrence",
    "sg:classifiers":[
        {
            "category":"Home & Garden",
            "subcategory":"Building Materials",
            "type":"Retail Goods"
        }
    ],
    "sg:phone":"+1 978 682 1199",
    "sg:postcode":"01841",
    "sg:province":"MA",
    "sg:tags":[
        "glass",
        "window",
        "plate"
    ],
    "wof:name":"Sentry Glass Co",
    "wof:placetype":"venue"
},
  "geometry": {"coordinates":[-71.18932599999999,42.704882],"type":"Point"}
}