{
  "type": "Feature",
  "properties": {
    "addr:full": "655 Haverhill St Lawrence MA 01841",
    "addr:housenumber": "655",
    "addr:postcode": "01841",
    "addr:street": "Haverhill St",
    "iso:country": "US",
    "ovtr:label": "Sentry Glass Co, 655 Haverhill St Lawrence MA US",
    "ovtr:similarity": 2.3030829429626465,
    "sg:address": "655 Haverhill St",
    "sg:city": "Lawrence",
    "sg:classifiers": [
      {
        "category": "Home \u0026 Garden",
        "subcategory": "Building Materials",
        "type": "Retail Goods"
      }
    ],
    "sg:phone": "+1 978 682 1199",
    "sg:postcode": "01841",
    "sg:province": "MA",
    "sg:tags": [
      "glass",
      "window",
      "plate"
    ],
    "wof:name": "Sentry Glass Co",
    "wof:placetype": "venue"
  },
  "geometry": {"coordinates":[-71.189326,42.704882],"type":"Point"}
}
