{
  "type": "Feature",
  "properties": {
    "iso:country":"US",
    "sg:address":"40 Railroad Ave",
    "sg:city":"Swansea",
    "sg:classifiers":[
        {
            "category":"Personal",
            "subcategory":"Beauty Salon",
            "type":"Services"
        }
    ],
    "sg:phone":"+1   ",
    "sg:postcode":"02777",
    "sg:province":"MA",
    "sg:tags":[
        "shop"
    ],
    "wof:name":"Nail Designs",
    "wof:placetype":"venue"
},
  "geometry": {"coordinates":[-71.20869,41.723375],"type":"Point"}
}