{
  "type": "Feature",
  "properties": {
    "iso:country":"US",
    "sg:address":"41 Winter St",
    "sg:city":"Boston",
    "sg:classifiers":[
        {
            "category":"Shopping",
            "subcategory":"Clothing, Apparel, & Fashions",
            "type":"Retail Goods"
        }
    ],
    "sg:phone":"+1 617 482 9631",
    "sg:postcode":"02108",
    "sg:province":"MA",
    "sg:tags":[
        "dressmaker"
    ],
    "wof:name":"Naomi Bain",
    "wof:placetype":"venue"
},
  "geometry": {"coordinates":[-71.06208599999999,42.356256],"type":"Point"}
}