{
  "type": "Feature",
  "properties": {
    "addr:full": "41 Winter St Boston MA 02108",
    "addr:housenumber": "41",
    "addr:postcode": "02108",
    "addr:street": "Winter St",
    "iso:country": "US",
    "sg:address": "41 Winter St",
    "sg:city": "Boston",
    "sg:classifiers": [
      {
        "category": "Shopping",
        "subcategory": "Clothing, Apparel, \u0026 Fashions",
        "type": "Retail Goods"
      }
    ],
    "sg:phone": "+1 617 482 9631",
    "sg:postcode": "02108",
    "sg:province": "MA",
    "sg:tags": [
      "dressmaker"
    ],
    "wof:name": "Naomi Bain",
    "wof:placetype": "venue"
  },
  "geometry": {"coordinates":[-71.062086,42.356256],"type":"Point"}
}
