{
  "type": "Feature",
  "properties": {
    "addr:full":"55 Union St Lawrence MA 01840",
    "addr:housenumber":"55",
    "addr:postcode":"01840",
    "addr:street":"Union St",
    "iso:country":"US",
    "sg:address":"55 Union St",
    "sg:city":"Lawrence",
    "sg:classifiers":[
        {
            "category":"Food & Beverages",
            "subcategory":"Bakery",
            "type":"Retail Goods"
        }
    ],
    "sg:phone":"+1 978 682 7774",
    "sg:postcode":"01840",
    "sg:province":"MA",
    "sg:tags":[
        "baker"
    ],
    "wof:name":"Fisichelli's Pastry Shop",
    "wof:placetype":"venue"
},
  "geometry": {"coordinates":[-71.153392,42.70986],"type":"Point"}
}