{
  "type": "Feature",
  "properties": {
    "iso:country":"US",
    "sg:address":"40 Joan Dr",
    "sg:city":"Pittsfield",
    "sg:classifiers":[
        {
            "category":"Building & Trades",
            "subcategory":"Construction",
            "type":"Services"
        }
    ],
    "sg:phone":"+1 413 443 7679",
    "sg:postcode":"01201",
    "sg:province":"MA",
    "sg:tags":[
        "carpentry",
        "contractor"
    ],
    "wof:name":"Northstar Window & Door",
    "wof:placetype":"venue"
},
  "geometry": {"coordinates":[-73.209616,42.427513],"type":"Point"}
}