{
  "type": "Feature",
  "properties": {
    "iso:country":"US",
    "sg:address":"55 Columbus Ave",
    "sg:city":"Somerville",
    "sg:classifiers":[
        {
            "category":"Building & Trades",
            "subcategory":"Locksmith",
            "type":"Services"
        }
    ],
    "sg:phone":"+1 617 714 1363",
    "sg:postcode":"02143",
    "sg:province":"MA",
    "sg:tags":[
        "key"
    ],
    "wof:name":"Vip Locksmith",
    "wof:placetype":"venue"
},
  "geometry": {"coordinates":[-71.09437200000001,42.381551],"type":"Point"}
}