{
  "type": "Feature",
  "properties": {
    "addr:full": "55 Columbus Ave Somerville MA 02143",
    "addr:housenumber": "55",
    "addr:postcode": "02143",
    "addr:street": "Columbus Ave",
    "iso:country": "US",
    "sg:address": "55 Columbus Ave",
    "sg:city": "Somerville",
    "sg:classifiers": [
      {
        "category": "Building \u0026 Trades",
        "subcategory": "Locksmith",
        "type": "Services"
      }
    ],
    "sg:phone": "+1 617 714 1363",
    "sg:postcode": "02143",
    "sg:province": "MA",
    "sg:tags": [
      "key"
    ],
    "wof:name": "Vip Locksmith",
    "wof:placetype": "venue"
  },
  "geometry": {"coordinates":[-71.094372,42.381551],"type":"Point"}
}
