{
  "type": "Feature",
  "properties": {
    "addr:full":"300 Constitution Dr Taunton MA 02780",
    "addr:housenumber":"300",
    "addr:postcode":"02780",
    "addr:street":"Constitution Dr",
    "iso:country":"US",
    "sg:address":"300 Constitution Dr",
    "sg:city":"Taunton",
    "sg:classifiers":[
        {
            "category":"Shopping",
            "subcategory":"Catalog Store",
            "type":"Retail Goods"
        }
    ],
    "sg:phone":"+1 508 895 4183",
    "sg:postcode":"02780",
    "sg:province":"MA",
    "sg:tags":[
        "mail",
        "order"
    ],
    "wof:name":"Redcats USA Fulfillment Ctr",
    "wof:placetype":"venue"
},
  "geometry": {"coordinates":[-71.12599,41.948172],"type":"Point"}
}