{
  "type": "Feature",
  "properties": {
    "addr:full": "36 Mount Auburn St Watertown MA 02472",
    "addr:housenumber": "36",
    "addr:postcode": "02472",
    "addr:street": "Mount Auburn St",
    "iso:country": "US",
    "sg:address": "36 Mount Auburn St",
    "sg:city": "Watertown",
    "sg:classifiers": [
      {
        "category": "Retail",
        "subcategory": "Portrait Studio",
        "type": "Services"
      }
    ],
    "sg:phone": "+1 617 924 6664",
    "sg:postcode": "02472",
    "sg:province": "MA",
    "sg:tags": [
      "photography"
    ],
    "wof:name": "Natural Exposures",
    "wof:placetype": "venue"
  },
  "geometry": {"coordinates":[-71.182991,42.366014],"type":"Point"}
}
