{
  "type": "Feature",
  "properties": {
    "iso:country":"US",
    "sg:address":"2 Hubbard Park Rd",
    "sg:city":"Cambridge",
    "sg:classifiers":[
        {
            "category":"Professional",
            "subcategory":"Management & Consulting",
            "type":"Services"
        }
    ],
    "sg:phone":"+1 617 491 8952",
    "sg:postcode":"02138",
    "sg:province":"MA",
    "sg:tags":[
        "town",
        "city",
        "regional",
        "planner"
    ],
    "wof:name":"Ronald L Fleming",
    "wof:placetype":"venue"
},
  "geometry": {"coordinates":[-71.13238200000001,42.376815],"type":"Point"}
}