{
  "type": "Feature",
  "properties": {
    "addr:full": "2 Hubbard Park Rd Cambridge MA 02138",
    "addr:housenumber": "2",
    "addr:postcode": "02138",
    "addr:street": "Hubbard Park Rd",
    "iso:country": "US",
    "sg:address": "2 Hubbard Park Rd",
    "sg:city": "Cambridge",
    "sg:classifiers": [
      {
        "category": "Professional",
        "subcategory": "Management \u0026 Consulting",
        "type": "Services"
      }
    ],
    "sg:phone": "+1 617 491 8952",
    "sg:postcode": "02138",
    "sg:province": "MA",
    "sg:tags": [
      "town",
      "city",
      "regional",
      "planner"
    ],
    "wof:name": "Ronald L Fleming",
    "wof:placetype": "venue"
  },
  "geometry": {"coordinates":[-71.132382,42.376815],"type":"Point"}
}
