{
  "type": "Feature",
  "properties": {
    "addr:full": "2 Bert Dr West Bridgewater MA 02379",
    "addr:housenumber": "2",
    "addr:postcode": "02379",
    "addr:street": "Bert Dr",
    "iso:country": "US",
    "sg:address": "2 Bert Dr",
    "sg:city": "West Bridgewater",
    "sg:classifiers": [
      {
        "category": "Communications",
        "subcategory": "Television Station",
        "type": "Services"
      }
    ],
    "sg:phone": "+1 508 586 4677",
    "sg:postcode": "02379",
    "sg:province": "MA",
    "sg:tags": [
      "broadcasting",
      "co"
    ],
    "wof:name": "WWDP",
    "wof:placetype": "venue"
  },
  "geometry": {"coordinates":[-71.059615,42.035854],"type":"Point"}
}
