{
  "type": "Feature",
  "properties": {
    "addr:full":"21 N Main St Florence MA 01062",
    "addr:housenumber":"21",
    "addr:postcode":"01062",
    "addr:street":"N Main St",
    "iso:country":"US",
    "sg:address":"21 N Main St",
    "sg:city":"Florence",
    "sg:classifiers":[
        {
            "category":"Professional",
            "subcategory":"Business Services",
            "type":"Services"
        }
    ],
    "sg:phone":"+1 413 585 9787",
    "sg:postcode":"01062",
    "sg:province":"MA",
    "sg:tags":[
        "auctioneer"
    ],
    "wof:name":"Northampton Auction Co",
    "wof:placetype":"venue"
},
  "geometry": {"coordinates":[-72.672269,42.335586],"type":"Point"}
}