{
  "type": "Feature",
  "properties": {
    "addr:full": "60 E Main St Erving MA 01344",
    "addr:housenumber": "60",
    "addr:postcode": "01344",
    "addr:street": "E Main St",
    "iso:country": "US",
    "ovtr:label": "Freight House Antiques, 11 E Main St Erving MA US",
    "ovtr:similarity": 3.9280340671539307,
    "sg:address": "60 E Main St",
    "sg:city": "Erving",
    "sg:classifiers": [
      {
        "category": "Shopping",
        "subcategory": "Used Merchandise",
        "type": "Retail Goods"
      }
    ],
    "sg:phone": "+1 413 422 2828",
    "sg:postcode": "01344",
    "sg:province": "MA",
    "sg:tags": [
      "antique"
    ],
    "wof:name": "Freight House Antiques",
    "wof:placetype": "venue"
  },
  "geometry": {"coordinates":[-72.392763,42.599173],"type":"Point"}
}
