{
  "type": "Feature",
  "properties": {
    "addr:full":"1463 Hyde Park Ave Hyde Park MA 02136",
    "addr:housenumber":"1463",
    "addr:postcode":"02136",
    "addr:street":"Hyde Park Ave",
    "iso:country":"US",
    "sg:address":"1463 Hyde Park Ave",
    "sg:city":"Hyde Park",
    "sg:classifiers":[
        {
            "category":"Banks & Credit Unions",
            "subcategory":"Bank",
            "type":"Services"
        }
    ],
    "sg:phone":"+1 617 333 9797",
    "sg:postcode":"02136",
    "sg:province":"MA",
    "sg:tags":[
        "loan",
        "real estate"
    ],
    "wof:name":"Home Run Mortgage",
    "wof:placetype":"venue"
},
  "geometry": {"coordinates":[-71.12663499999999,42.249159],"type":"Point"}
}