{
  "type": "Feature",
  "properties": {
    "iso:country":"US",
    "sg:address":"416 Pond St",
    "sg:city":"Franklin",
    "sg:classifiers":[
        {
            "category":"Retail",
            "subcategory":"Auto Repair",
            "type":"Services"
        }
    ],
    "sg:phone":"+1 508 528 9534",
    "sg:postcode":"02038",
    "sg:province":"MA",
    "sg:tags":[
        "wrecker"
    ],
    "wof:name":"Robert Papp Towing",
    "wof:placetype":"venue"
},
  "geometry": {"coordinates":[-71.42851899999999,42.10478],"type":"Point"}
}