{
  "type": "Feature",
  "properties": {
    "iso:country":"US",
    "sg:address":"1 Orange St",
    "sg:city":"Salem",
    "sg:classifiers":[
        {
            "category":"Wholesale",
            "subcategory":"Jewelry",
            "type":"Manufacturing & Wholesale Goods"
        }
    ],
    "sg:phone":"+1   ",
    "sg:postcode":"01970",
    "sg:province":"MA",
    "sg:tags":[
        "detergent",
        "stone",
        "mfg"
    ],
    "wof:name":"Crystal Grove The",
    "wof:placetype":"venue"
},
  "geometry": {"coordinates":[-70.887636,42.521968],"type":"Point"}
}