{
  "type": "Feature",
  "properties": {
    "iso:country":"US",
    "sg:address":"8 Mohawk Ave",
    "sg:city":"Webster",
    "sg:classifiers":[
        {
            "category":"Arts & Performance",
            "subcategory":"Theater",
            "type":"Entertainment"
        }
    ],
    "sg:phone":"+1   ",
    "sg:postcode":"01570",
    "sg:province":"MA",
    "sg:tags":[
        "group"
    ],
    "wof:name":"Chip Hoffman Disc Jockey",
    "wof:placetype":"venue"
},
  "geometry": {"coordinates":[-71.82494699999999,42.028805],"type":"Point"}
}