{
  "type": "Feature",
  "properties": {
    "addr:full": "8 Mohawk Ave Webster MA 01570",
    "addr:housenumber": "8",
    "addr:postcode": "01570",
    "addr:street": "Mohawk Ave",
    "iso:country": "US",
    "sg:address": "8 Mohawk Ave",
    "sg:city": "Webster",
    "sg:classifiers": [
      {
        "category": "Arts \u0026 Performance",
        "subcategory": "Theater",
        "type": "Entertainment"
      }
    ],
    "sg:phone": "+1   ",
    "sg:postcode": "01570",
    "sg:province": "MA",
    "sg:tags": [
      "group"
    ],
    "wof:name": "Chip Hoffman Disc Jockey",
    "wof:placetype": "venue"
  },
  "geometry": {"coordinates":[-71.824947,42.028805],"type":"Point"}
}
