{
  "type": "Feature",
  "properties": {
    "iso:country":"US",
    "sg:address":"101 Industrial Dr",
    "sg:city":"Amherst",
    "sg:classifiers":[
        {
            "category":"Manufacturing",
            "subcategory":"Printing",
            "type":"Manufacturing & Wholesale Goods"
        }
    ],
    "sg:phone":"+1 413 584 1817",
    "sg:postcode":"01060",
    "sg:province":"MA",
    "sg:tags":[
        "commercial"
    ],
    "wof:name":"Metcalf Printing Co",
    "wof:placetype":"venue"
},
  "geometry": {"coordinates":[-72.62989,42.334609],"type":"Point"}
}