{
  "type": "Feature",
  "properties": {
    "addr:full": "12 Chestnut St Peabody MA 01960",
    "addr:housenumber": "12",
    "addr:postcode": "01960",
    "addr:street": "Chestnut St",
    "iso:country": "US",
    "sg:address": "12 Chestnut St",
    "sg:city": "Peabody",
    "sg:classifiers": [
      {
        "category": "Retail",
        "subcategory": "Funeral Services",
        "type": "Services"
      }
    ],
    "sg:phone": "+1 978 531 0398",
    "sg:postcode": "01960",
    "sg:province": "MA",
    "sg:tags": [
      "director"
    ],
    "sg:website": "www.ccbfuneral.com",
    "wof:name": "Conway Funeral Home",
    "wof:placetype": "venue"
  },
  "geometry": {"coordinates":[-70.928222,42.526115],"type":"Point"}
}
