{
  "type": "Feature",
  "properties": {
    "addr:full": "35 Fuller St Canton MA 02021",
    "addr:housenumber": "35",
    "addr:postcode": "02021",
    "addr:street": "Fuller St",
    "iso:country": "US",
    "sg:address": "35 Fuller St",
    "sg:city": "Canton",
    "sg:classifiers": [
      {
        "category": "Professional",
        "subcategory": "Management \u0026 Consulting",
        "type": "Services"
      }
    ],
    "sg:phone": "+1 781 575 1600",
    "sg:postcode": "02021",
    "sg:province": "MA",
    "sg:tags": [
      "communications",
      "consultant"
    ],
    "sg:website": "www.webbconsult.com",
    "wof:name": "WEBB \u0026 Assoc",
    "wof:placetype": "venue"
  },
  "geometry": {"coordinates":[-71.156893,42.160535],"type":"Point"}
}
