{
  "type": "Feature",
  "properties": {
    "addr:full":"257 Main St Medford MA 02155",
    "addr:housenumber":"257",
    "addr:postcode":"02155",
    "addr:street":"Main St",
    "iso:country":"US",
    "sg:address":"257 Main St",
    "sg:city":"Medford",
    "sg:classifiers":[
        {
            "category":"Building & Trades",
            "subcategory":"Locksmith",
            "type":"Services"
        }
    ],
    "sg:phone":"+1 781 658 3152",
    "sg:postcode":"02155",
    "sg:province":"MA",
    "sg:tags":[
        "key"
    ],
    "wof:name":"All Day All Night Emergency Locksmith",
    "wof:placetype":"venue"
},
  "geometry": {"coordinates":[-71.110152,42.409891],"type":"Point"}
}