{
  "type": "Feature",
  "properties": {
    "iso:country":"US",
    "sg:address":"6 Park Row",
    "sg:city":"Mansfield",
    "sg:classifiers":[
        {
            "category":"Government",
            "subcategory":"Office",
            "type":"Public Place"
        }
    ],
    "sg:phone":"+1 508 261 7350",
    "sg:postcode":"02048",
    "sg:province":"MA",
    "sg:tags":[
        "city",
        "taxation"
    ],
    "wof:name":"Mansfield Town Assessors",
    "wof:placetype":"venue"
},
  "geometry": {"coordinates":[-71.215929,42.023808],"type":"Point"}
}