{
  "type": "Feature",
  "properties": {
    "iso:country":"US",
    "sg:address":"18 Locke Rd",
    "sg:city":"Billerica",
    "sg:classifiers":[
        {
            "category":"Retail",
            "subcategory":"Repair Shop",
            "type":"Services"
        }
    ],
    "sg:phone":"+1   ",
    "sg:postcode":"01821",
    "sg:province":"MA",
    "wof:name":"M & D Respiratory Repair Svc",
    "wof:placetype":"venue"
},
  "geometry": {"coordinates":[-71.257158,42.544524],"type":"Point"}
}