{
  "type": "Feature",
  "properties": {
    "addr:full":"649 Lawrence St Lowell MA 01852",
    "addr:housenumber":"649",
    "addr:postcode":"01852",
    "addr:street":"Lawrence St",
    "iso:country":"US",
    "sg:address":"649 Lawrence St",
    "sg:city":"Lowell",
    "sg:classifiers":[
        {
            "category":"School Buses",
            "type":"Transportation"
        },
        {
            "category":"Arts & Performance",
            "subcategory":"Dance",
            "type":"Entertainment"
        }
    ],
    "sg:phone":"+1 978 446 1450",
    "sg:postcode":"01852",
    "sg:province":"MA",
    "sg:tags":[
        "workshop",
        "acting",
        "instruction",
        "dancing"
    ],
    "wof:name":"Donna Miceli Dance Center",
    "wof:placetype":"venue"
},
  "geometry": {"coordinates":[-71.301783,42.63232],"type":"Point"}
}