{
  "type": "Feature",
  "properties": {
    "addr:full": "2 Andrews Point Rd Carver MA 02330",
    "addr:housenumber": "2",
    "addr:postcode": "02330",
    "addr:street": "Andrews Point Rd",
    "iso:country": "US",
    "sg:address": "2 Andrews Point Rd",
    "sg:city": "Carver",
    "sg:classifiers": [
      {
        "category": "Professional",
        "subcategory": "Computer Services",
        "type": "Services"
      }
    ],
    "sg:phone": "+1 508 866 2891",
    "sg:postcode": "02330",
    "sg:province": "MA",
    "wof:name": "Boston PC Networking",
    "wof:placetype": "venue"
  },
  "geometry": {"coordinates":[-70.752089,41.846311],"type":"Point"}
}
