{
  "type": "Feature",
  "properties": {
    "iso:country":"US",
    "sg:address":"72 Mill St",
    "sg:city":"Westfield",
    "sg:classifiers":[
        {
            "category":"Health Services",
            "subcategory":"Doctor",
            "type":"Services"
        }
    ],
    "sg:phone":"+1 413 562 5201",
    "sg:postcode":"01085",
    "sg:province":"MA",
    "sg:tags":[
        "physician",
        "surgeon"
    ],
    "wof:name":"Richard M Kane MD",
    "wof:placetype":"venue"
},
  "geometry": {"coordinates":[-72.76469299999999,42.111771],"type":"Point"}
}