{
  "type": "Feature",
  "properties": {
    "addr:full":"1 Union Sq Somerville MA 02143",
    "addr:housenumber":"1",
    "addr:postcode":"02143",
    "addr:street":"Union Sq",
    "iso:country":"US",
    "sg:address":"1 Union Sq",
    "sg:city":"Somerville",
    "sg:classifiers":[
        {
            "category":"Retail",
            "subcategory":"Auto Repair",
            "type":"Services"
        }
    ],
    "sg:phone":"+1 617 623 1009",
    "sg:postcode":"02143",
    "sg:province":"MA",
    "sg:website":"www.mikesauto.com/",
    "wof:name":"Mike's Auto Service",
    "wof:placetype":"venue"
},
  "geometry": {"coordinates":[-71.09493999999999,42.379389],"type":"Point"}
}