{
  "type": "Feature",
  "properties": {
    "iso:country":"US",
    "sg:address":"400 Crown Colony Dr Ste 500",
    "sg:city":"Quincy",
    "sg:classifiers":[
        {
            "category":"Insurance",
            "subcategory":"Hazard Insurance",
            "type":"Services"
        }
    ],
    "sg:phone":"+1 617 847 5200",
    "sg:postcode":"02169",
    "sg:province":"MA",
    "sg:tags":[
        "commercial",
        "business"
    ],
    "wof:name":"Greater New York Mutual Insurance",
    "wof:placetype":"venue"
},
  "geometry": {"coordinates":[-71.013901,42.232319],"type":"Point"}
}