{
  "type": "Feature",
  "properties": {
    "iso:country":"US",
    "sg:address":"3 Giddiah Hill Rd",
    "sg:city":"Orleans",
    "sg:classifiers":[
        {
            "category":"Professional",
            "subcategory":"Engineering",
            "type":"Services"
        }
    ],
    "sg:phone":"+1 508 255 8312",
    "sg:postcode":"02653",
    "sg:province":"MA",
    "sg:tags":[
        "civil",
        "engineer"
    ],
    "sg:website":"http://www.ryder-wilcox.com",
    "wof:name":"Ryder And Wilcox, Inc.",
    "wof:placetype":"venue"
},
  "geometry": {"coordinates":[-69.991372,41.776803],"type":"Point"}
}