{
  "type": "Feature",
  "properties": {
    "iso:country":"US",
    "sg:address":"43 Virginia Ln",
    "sg:city":"Newburyport",
    "sg:classifiers":[
        {
            "category":"Insurance",
            "subcategory":"Insurance Agent",
            "type":"Services"
        }
    ],
    "sg:phone":"+1 978 499 4343",
    "sg:postcode":"01950",
    "sg:province":"MA",
    "wof:name":"Baystate Financial Svc",
    "wof:placetype":"venue"
},
  "geometry": {"coordinates":[-70.91885600000001,42.811479],"type":"Point"}
}