{
  "type": "Feature",
  "properties": {
    "iso:country":"US",
    "sg:address":"2 Flume Rd",
    "sg:city":"Gloucester",
    "sg:classifiers":[
        {
            "category":"Professional",
            "type":"Services"
        }
    ],
    "sg:phone":"+1 978 525 2298",
    "sg:postcode":"01930",
    "sg:province":"MA",
    "sg:tags":[
        "establishment"
    ],
    "wof:name":"Fwf Inc",
    "wof:placetype":"venue"
},
  "geometry": {"coordinates":[-70.71301099999999,42.576006],"type":"Point"}
}