{
  "type": "Feature",
  "properties": {
    "addr:full":"165 Cambridge St Boston MA 02114",
    "addr:housenumber":"165",
    "addr:postcode":"02114",
    "addr:street":"Cambridge St",
    "iso:country":"US",
    "sg:address":"165 Cambridge St",
    "sg:city":"Boston",
    "sg:classifiers":[
        {
            "category":"Health Services",
            "subcategory":"Doctor",
            "type":"Services"
        }
    ],
    "sg:phone":"+1 617 726 4900",
    "sg:postcode":"02114",
    "sg:province":"MA",
    "sg:tags":[
        "physician",
        "surgeon"
    ],
    "wof:name":"Garner Haupert MD",
    "wof:placetype":"venue"
},
  "geometry": {"coordinates":[-71.06483799999999,42.361295],"type":"Point"}
}