{
  "type": "Feature",
  "properties": {
    "addr:full":"448 Southbridge St Worcester MA 01610",
    "addr:housenumber":"448",
    "addr:postcode":"01610",
    "addr:street":"Southbridge St",
    "iso:country":"US",
    "sg:address":"448 Southbridge St",
    "sg:city":"Worcester",
    "sg:classifiers":[
        {
            "category":"Freight",
            "type":"Transportation"
        }
    ],
    "sg:phone":"+1 508 798 3603",
    "sg:postcode":"01610",
    "sg:province":"MA",
    "sg:tags":[
        "cargo",
        "containerized"
    ],
    "wof:name":"Intransit Container",
    "wof:placetype":"venue"
},
  "geometry": {"coordinates":[-71.80923799999999,42.250269],"type":"Point"}
}