{
  "type": "Feature",
  "properties": {
    "iso:country":"US",
    "sg:address":"453 S Main St",
    "sg:city":"Attleboro",
    "sg:classifiers":[
        {
            "category":"Manufacturing",
            "subcategory":"Rubber & Plastics",
            "type":"Manufacturing & Wholesale Goods"
        }
    ],
    "sg:phone":"+1 508 226 2708",
    "sg:postcode":"02703",
    "sg:province":"MA",
    "sg:tags":[
        "product"
    ],
    "wof:name":"Chardan Limited",
    "wof:placetype":"venue"
},
  "geometry": {"coordinates":[-71.293083,41.922373],"type":"Point"}
}