{
  "type": "Feature",
  "properties": {
    "addr:full": "15 Davis Rd Acton MA 01720",
    "addr:housenumber": "15",
    "addr:postcode": "01720",
    "addr:street": "Davis Rd",
    "iso:country": "US",
    "sg:address": "15 Davis Rd",
    "sg:city": "Acton",
    "sg:classifiers": [
      {
        "category": "Real Estate",
        "subcategory": "Real Estate Operator",
        "type": "Services"
      }
    ],
    "sg:phone": "+1 978 263 0479",
    "sg:postcode": "01720",
    "sg:province": "MA",
    "sg:tags": [
      "apartment"
    ],
    "wof:name": "Briarbrook Village Apartments",
    "wof:placetype": "venue"
  },
  "geometry": {"coordinates":[-71.416235,42.498981],"type":"Point"}
}
