{
  "type": "Feature",
  "properties": {
    "addr:full":"50 Arcand Dr Lowell MA 01852",
    "addr:housenumber":"50",
    "addr:postcode":"01852",
    "addr:street":"Arcand Dr",
    "iso:country":"US",
    "sg:address":"50 Arcand Dr",
    "sg:city":"Lowell",
    "sg:classifiers":[
        {
            "category":"Government",
            "subcategory":"Office",
            "type":"Public Place"
        }
    ],
    "sg:phone":"+1 978 970 4264",
    "sg:postcode":"01852",
    "sg:province":"MA",
    "sg:tags":[
        "village"
    ],
    "wof:name":"Lowell Traffic Engineering",
    "wof:placetype":"venue"
},
  "geometry": {"coordinates":[-71.313188,42.648209],"type":"Point"}
}