{
  "type": "Feature",
  "properties": {
    "iso:country":"US",
    "sg:address":"112 Andover St",
    "sg:city":"North Andover",
    "sg:classifiers":[
        {
            "category":"Professional",
            "subcategory":"Business Services",
            "type":"Services"
        }
    ],
    "sg:phone":"+1   ",
    "sg:postcode":"01845",
    "sg:province":"MA",
    "wof:name":"Andover Technology Partners",
    "wof:placetype":"venue"
},
  "geometry": {"coordinates":[-71.116947,42.68198],"type":"Point"}
}