{
  "type": "Feature",
  "properties": {
    "iso:country":"US",
    "sg:address":"35 Concord Ave",
    "sg:city":"Cambridge",
    "sg:classifiers":[
        {
            "category":"Professional",
            "subcategory":"Management & Consulting",
            "type":"Services"
        }
    ],
    "sg:phone":"+1 617 492 1543",
    "sg:postcode":"02138",
    "sg:province":"MA",
    "sg:tags":[
        "consultant",
        "business"
    ],
    "wof:name":"Seven29",
    "wof:placetype":"venue"
},
  "geometry": {"coordinates":[-71.12666299999999,42.379922],"type":"Point"}
}