{
  "type": "Feature",
  "properties": {
    "addr:full": "27 Millstone Way Centerville MA 02632",
    "addr:housenumber": "27",
    "addr:postcode": "02632",
    "addr:street": "Millstone Way",
    "iso:country": "US",
    "sg:address": "27 Millstone Way",
    "sg:city": "Centerville",
    "sg:classifiers": [
      {
        "category": "Professional",
        "subcategory": "Computer Services",
        "type": "Services"
      }
    ],
    "sg:phone": "+1   ",
    "sg:postcode": "02632",
    "sg:province": "MA",
    "sg:tags": [
      "related"
    ],
    "wof:name": "Charif Associates",
    "wof:placetype": "venue"
  },
  "geometry": {"coordinates":[-70.326055,41.664066],"type":"Point"}
}
