{
  "type": "Feature",
  "properties": {
    "addr:full": "41 Old Mill Rd Concord MA 01742",
    "addr:housenumber": "41",
    "addr:postcode": "01742",
    "addr:street": "Old Mill Rd",
    "iso:country": "US",
    "sg:address": "41 Old Mill Rd",
    "sg:city": "Concord",
    "sg:classifiers": [
      {
        "category": "Shopping",
        "subcategory": "Bicycles \u0026 Sporting Goods",
        "type": "Retail Goods"
      }
    ],
    "sg:phone": "+1 978 369 3390",
    "sg:postcode": "01742",
    "sg:province": "MA",
    "wof:name": "Athletic Supply Group Inc",
    "wof:placetype": "venue"
  },
  "geometry": {"coordinates":[-71.408184,42.447946],"type":"Point"}
}
