{
  "type": "Feature",
  "properties": {
    "iso:country":"US",
    "sg:address":"41 Old Mill Rd",
    "sg:city":"Concord",
    "sg:classifiers":[
        {
            "category":"Shopping",
            "subcategory":"Bicycles & Sporting Goods",
            "type":"Retail Goods"
        }
    ],
    "sg:phone":"+1 978 369 3390",
    "sg:postcode":"01742",
    "sg:province":"MA",
    "wof:name":"Athletic Supply Group Inc",
    "wof:placetype":"venue"
},
  "geometry": {"coordinates":[-71.40818400000001,42.447946],"type":"Point"}
}