{
  "type": "Feature",
  "properties": {
    "addr:full": "222 Forbes Rd Braintree MA 02184",
    "addr:housenumber": "222",
    "addr:postcode": "02184",
    "addr:street": "Forbes Rd",
    "iso:country": "US",
    "sg:address": "222 Forbes Rd",
    "sg:city": "Braintree",
    "sg:classifiers": [
      {
        "category": "Health Services",
        "subcategory": "Clinic",
        "type": "Services"
      }
    ],
    "sg:phone": "+1 781 356 2696",
    "sg:postcode": "02184",
    "sg:province": "MA",
    "sg:tags": [
      "medical",
      "examination"
    ],
    "wof:name": "Portamedic",
    "wof:placetype": "venue"
  },
  "geometry": {"coordinates":[-71.034779,42.22027],"type":"Point"}
}
