{
  "type": "Feature",
  "properties": {
    "addr:full":"28 Central St Lowell MA 01852",
    "addr:housenumber":"28",
    "addr:postcode":"01852",
    "addr:street":"Central St",
    "iso:country":"US",
    "sg:address":"28 Central St",
    "sg:city":"Lowell",
    "sg:classifiers":[
        {
            "category":"Professional",
            "subcategory":"Management & Consulting",
            "type":"Services"
        }
    ],
    "sg:phone":"+1 978 453 3777",
    "sg:postcode":"01852",
    "sg:province":"MA",
    "sg:tags":[
        "consultant",
        "business"
    ],
    "wof:name":"Latin Multi Svc",
    "wof:placetype":"venue"
},
  "geometry": {"coordinates":[-71.308286,42.645439],"type":"Point"}
}