{
  "type": "Feature",
  "properties": {
    "addr:full":"19 Bishop Ln Rockland MA 02370",
    "addr:housenumber":"19",
    "addr:postcode":"02370",
    "addr:street":"Bishop Ln",
    "iso:country":"US",
    "sg:address":"19 Bishop Ln",
    "sg:city":"Rockland",
    "sg:classifiers":[
        {
            "category":"Sports & Exercise",
            "subcategory":"Race Track",
            "type":"Entertainment"
        }
    ],
    "sg:phone":"+1 781 982 2550",
    "sg:postcode":"02370",
    "sg:province":"MA",
    "wof:name":"Motzof Racing",
    "wof:placetype":"venue"
},
  "geometry": {"coordinates":[-70.89122,42.119147],"type":"Point"}
}