{
  "type": "Feature",
  "properties": {
    "iso:country":"US",
    "sg:address":"391 Totten Pond Rd",
    "sg:city":"Waltham",
    "sg:classifiers":[
        {
            "category":"Professional",
            "subcategory":"Business Services",
            "type":"Services"
        }
    ],
    "sg:phone":"+1 781 487 0500",
    "sg:postcode":"02451",
    "sg:province":"MA",
    "sg:website":"www.bestboston.com",
    "wof:name":"Best Of Boston LTD",
    "wof:placetype":"venue"
},
  "geometry": {"coordinates":[-71.25625100000001,42.397243],"type":"Point"}
}