{
  "type": "Feature",
  "properties": {
    "addr:full": "421 Hanover St Boston MA 02113",
    "addr:housenumber": "421",
    "addr:postcode": "02113",
    "addr:street": "Hanover St",
    "iso:country": "US",
    "sg:address": "421 Hanover St",
    "sg:city": "Boston",
    "sg:classifiers": [
      {
        "category": "Real Estate",
        "subcategory": "Real Estate Services",
        "type": "Services"
      }
    ],
    "sg:phone": "+1 617 523 2333",
    "sg:postcode": "02113",
    "sg:province": "MA",
    "sg:website": "www.citysuitesboston.com",
    "wof:name": "City Suites Boston",
    "wof:placetype": "venue"
  },
  "geometry": {"coordinates":[-71.052675,42.365714],"type":"Point"}
}
