{
  "type": "Feature",
  "properties": {
    "iso:country":"US",
    "sg:address":"421 Hanover St",
    "sg:city":"Boston",
    "sg:classifiers":[
        {
            "category":"Real Estate",
            "subcategory":"Real Estate Services",
            "type":"Services"
        }
    ],
    "sg:phone":"+1 617 523 2333",
    "sg:postcode":"02113",
    "sg:province":"MA",
    "sg:website":"www.citysuitesboston.com",
    "wof:name":"City Suites Boston",
    "wof:placetype":"venue"
},
  "geometry": {"coordinates":[-71.05267499999999,42.365714],"type":"Point"}
}