{
  "type": "Feature",
  "properties": {
    "addr:full": "79 Canton St Stoughton MA 02072",
    "addr:housenumber": "79",
    "addr:postcode": "02072",
    "addr:street": "Canton St",
    "iso:country": "US",
    "sg:address": "79 Canton St",
    "sg:city": "Stoughton",
    "sg:classifiers": [
      {
        "category": "Shopping",
        "subcategory": "Discount \u0026 Variety Stores",
        "type": "Retail Goods"
      }
    ],
    "sg:phone": "+1 781 344 1752",
    "sg:postcode": "02072",
    "sg:province": "MA",
    "wof:name": "Stoughton Coffee House",
    "wof:placetype": "venue"
  },
  "geometry": {"coordinates":[-71.104359,42.124689],"type":"Point"}
}
