{
  "type": "Feature",
  "properties": {
    "iso:country":"US",
    "sg:address":"79 Canton St",
    "sg:city":"Stoughton",
    "sg:classifiers":[
        {
            "category":"Shopping",
            "subcategory":"Discount & Variety Stores",
            "type":"Retail Goods"
        }
    ],
    "sg:phone":"+1 781 344 1752",
    "sg:postcode":"02072",
    "sg:province":"MA",
    "wof:name":"Stoughton Coffee House",
    "wof:placetype":"venue"
},
  "geometry": {"coordinates":[-71.104359,42.124689],"type":"Point"}
}