{
  "type": "Feature",
  "properties": {
    "iso:country":"US",
    "sg:address":"90 Everett Ave",
    "sg:city":"Chelsea",
    "sg:classifiers":[
        {
            "category":"Manufacturing",
            "subcategory":"Food",
            "type":"Manufacturing & Wholesale Goods"
        },
        {
            "category":"Wholesale",
            "subcategory":"Dairy",
            "type":"Manufacturing & Wholesale Goods"
        }
    ],
    "sg:phone":"+1 617 887 3000",
    "sg:postcode":"02150",
    "sg:province":"MA",
    "sg:tags":[
        "process",
        "product",
        "distributes",
        "milk",
        "cream"
    ],
    "sg:website":"www.hphood.com",
    "wof:name":"HP Hood LLC",
    "wof:placetype":"venue"
},
  "geometry": {"coordinates":[-71.039395,42.394723],"type":"Point"}
}