{
  "type": "Feature",
  "properties": {
    "addr:full":"489 Lincoln St Marlborough MA 01752",
    "addr:housenumber":"489",
    "addr:postcode":"01752",
    "addr:street":"Lincoln St",
    "iso:country":"US",
    "sg:address":"489 Lincoln St",
    "sg:city":"Marlborough",
    "sg:classifiers":[
        {
            "category":"Building & Trades",
            "subcategory":"Construction",
            "type":"Services"
        }
    ],
    "sg:phone":"+1 508 303 8045",
    "sg:postcode":"01752",
    "sg:province":"MA",
    "sg:tags":[
        "windows"
    ],
    "wof:name":"Alternative Glass Solutions",
    "wof:placetype":"venue"
},
  "geometry": {"coordinates":[-71.561635,42.344987],"type":"Point"}
}