{
  "type": "Feature",
  "properties": {
    "addr:full":"7 Winslow Ave Scituate MA 02066",
    "addr:housenumber":"7",
    "addr:postcode":"02066",
    "addr:street":"Winslow Ave",
    "iso:country":"US",
    "sg:address":"7 Winslow Ave",
    "sg:city":"Scituate",
    "sg:classifiers":[
        {
            "category":"Cinema",
            "subcategory":"Movie Theater",
            "type":"Entertainment"
        }
    ],
    "sg:phone":"+1   ",
    "sg:postcode":"02066",
    "sg:province":"MA",
    "sg:tags":[
        "motion",
        "picture"
    ],
    "wof:name":"All Theaters Inc",
    "wof:placetype":"venue"
},
  "geometry": {"coordinates":[-70.741998,42.216922],"type":"Point"}
}