{
  "type": "Feature",
  "properties": {
    "addr:full":"72 Stockbridge Rd Great Barrington MA 01230",
    "addr:housenumber":"72",
    "addr:postcode":"01230",
    "addr:street":"Stockbridge Rd",
    "iso:country":"US",
    "sg:address":"72 Stockbridge Rd",
    "sg:city":"Great Barrington",
    "sg:classifiers":[
        {
            "category":"Home & Garden",
            "subcategory":"Furniture",
            "type":"Retail Goods"
        }
    ],
    "sg:phone":"+1 413 528 0023",
    "sg:postcode":"01230",
    "sg:province":"MA",
    "sg:tags":[
        "mattress"
    ],
    "wof:name":"Gans Bedding",
    "wof:placetype":"venue"
},
  "geometry": {"coordinates":[-73.346754,42.203598],"type":"Point"}
}