{
  "type": "Feature",
  "properties": {
    "iso:country":"US",
    "sg:address":"985 Homestead Ave",
    "sg:city":"Holyoke",
    "sg:classifiers":[
        {
            "category":"Farming",
            "subcategory":"Orchard",
            "type":"Manufacturing & Wholesale Goods"
        }
    ],
    "sg:phone":"+1   ",
    "sg:postcode":"01040",
    "sg:province":"MA",
    "sg:tags":[
        "fruit",
        "tree"
    ],
    "wof:name":"Henry Seidel",
    "wof:placetype":"venue"
},
  "geometry": {"coordinates":[-72.64866600000001,42.17727],"type":"Point"}
}