{
  "type": "Feature",
  "properties": {
    "addr:full": "71 Weld Hill St Jamaica Plain MA 02130",
    "addr:housenumber": "71",
    "addr:postcode": "02130",
    "addr:street": "Weld Hill St",
    "iso:country": "US",
    "sg:address": "71 Weld Hill St",
    "sg:city": "Jamaica Plain",
    "sg:classifiers": [
      {
        "category": "Professional",
        "subcategory": "Business Services",
        "type": "Services"
      }
    ],
    "sg:phone": "+1   ",
    "sg:postcode": "02130",
    "sg:province": "MA",
    "wof:name": "Es Marvel Enterprises Inc",
    "wof:placetype": "venue"
  },
  "geometry": {"coordinates":[-71.111411,42.297127],"type":"Point"}
}
