{
  "type": "Feature",
  "properties": {
    "iso:country":"US",
    "sg:address":"99 Summer St",
    "sg:city":"Boston",
    "sg:classifiers":[
        {
            "category":"Banks & Credit Unions",
            "subcategory":"Investment Brokerage",
            "type":"Services"
        }
    ],
    "sg:phone":"+1 617 951 0871",
    "sg:postcode":"02110",
    "sg:province":"MA",
    "sg:tags":[
        "funds",
        "mutual",
        "advisory"
    ],
    "wof:name":"Harbor Capital Advisors Inc",
    "wof:placetype":"venue"
},
  "geometry": {"coordinates":[-71.057991,42.353743],"type":"Point"}
}