{
  "type": "Feature",
  "properties": {
    "addr:full": "190 School St Groveland MA 01834",
    "addr:housenumber": "190",
    "addr:postcode": "01834",
    "addr:street": "School St",
    "iso:country": "US",
    "sg:address": "190 School St",
    "sg:city": "Groveland",
    "sg:classifiers": [
      {
        "category": "Professional",
        "subcategory": "Art Services",
        "type": "Services"
      }
    ],
    "sg:phone": "+1 978 374 5075",
    "sg:postcode": "01834",
    "sg:province": "MA",
    "sg:tags": [
      "consultant",
      "designer",
      "lighting"
    ],
    "wof:name": "Sean P. O'connor",
    "wof:placetype": "venue"
  },
  "geometry": {"coordinates":[-71.024597,42.74913],"type":"Point"}
}
