{
  "type": "Feature",
  "properties": {
    "addr:full":"84 State St Boston MA 02109",
    "addr:housenumber":"84",
    "addr:postcode":"02109",
    "addr:street":"State St",
    "iso:country":"US",
    "sg:address":"84 State St",
    "sg:city":"Boston",
    "sg:classifiers":[
        {
            "category":"Building & Trades",
            "subcategory":"Construction",
            "type":"Services"
        }
    ],
    "sg:phone":"+1 617 723 2050",
    "sg:postcode":"02109",
    "sg:province":"MA",
    "sg:tags":[
        "company"
    ],
    "sg:website":"www.tishman.com",
    "wof:name":"Tishman Construction Corp",
    "wof:placetype":"venue"
},
  "geometry": {"coordinates":[-71.056825,42.358875],"type":"Point"}
}