{
  "type": "Feature",
  "properties": {
    "iso:country":"US",
    "sg:address":"69 Moody Bridge Rd",
    "sg:city":"Hadley",
    "sg:classifiers":[
        {
            "category":"Recreation",
            "type":"Entertainment"
        }
    ],
    "sg:phone":"+1 413 586 3717",
    "sg:postcode":"01035",
    "sg:province":"MA",
    "sg:tags":[
        "stable"
    ],
    "wof:name":"Bri-Mar Stable",
    "wof:placetype":"venue"
},
  "geometry": {"coordinates":[-72.563084,42.339745],"type":"Point"}
}