{
  "type": "Feature",
  "properties": {
    "addr:full": "15 Blaisdell Ter Ipswich MA 01938",
    "addr:housenumber": "15",
    "addr:postcode": "01938",
    "addr:street": "Blaisdell Ter",
    "iso:country": "US",
    "sg:address": "15 Blaisdell Ter",
    "sg:city": "Ipswich",
    "sg:classifiers": [
      {
        "category": "Organizations",
        "subcategory": "Religious Organization",
        "type": "Services"
      }
    ],
    "sg:phone": "+1 978 356 0404",
    "sg:postcode": "01938",
    "sg:province": "MA",
    "wof:name": "Redeemed Lives",
    "wof:placetype": "venue"
  },
  "geometry": {"coordinates":[-70.847879,42.680636],"type":"Point"}
}
