{
  "type": "Feature",
  "properties": {
    "addr:full": "178 Congress Ave Chelsea MA 02150",
    "addr:housenumber": "178",
    "addr:postcode": "02150",
    "addr:street": "Congress Ave",
    "iso:country": "US",
    "sg:address": "178 Congress Ave",
    "sg:city": "Chelsea",
    "sg:classifiers": [
      {
        "category": "Social Services",
        "subcategory": "Child Care",
        "type": "Services"
      }
    ],
    "sg:phone": "+1   ",
    "sg:postcode": "02150",
    "sg:province": "MA",
    "sg:tags": [
      "day"
    ],
    "wof:name": "Nancy Hebert Child Care",
    "wof:placetype": "venue"
  },
  "geometry": {"coordinates":[-71.030937,42.38791],"type":"Point"}
}
