{
  "type": "Feature",
  "properties": {
    "iso:country":"US",
    "sg:address":"178 Congress Ave",
    "sg:city":"Chelsea",
    "sg:classifiers":[
        {
            "category":"Social Services",
            "subcategory":"Child Care",
            "type":"Services"
        }
    ],
    "sg:phone":"+1   ",
    "sg:postcode":"02150",
    "sg:province":"MA",
    "sg:tags":[
        "day"
    ],
    "wof:name":"Nancy Hebert Child Care",
    "wof:placetype":"venue"
},
  "geometry": {"coordinates":[-71.03093699999999,42.38791],"type":"Point"}
}