{
  "type": "Feature",
  "properties": {
    "addr:full":"1156 Massachusetts Ave Cambridge MA 02138",
    "addr:housenumber":"1156",
    "addr:postcode":"02138",
    "addr:street":"Massachusetts Ave",
    "iso:country":"US",
    "sg:address":"1156 Massachusetts Ave",
    "sg:city":"Cambridge",
    "sg:classifiers":[
        {
            "category":"Shopping",
            "subcategory":"Books",
            "type":"Retail Goods"
        }
    ],
    "sg:phone":"+1 617 492 5443",
    "sg:postcode":"02138",
    "sg:province":"MA",
    "sg:tags":[
        "bookstore"
    ],
    "wof:name":"Revolution Books",
    "wof:placetype":"venue"
},
  "geometry": {"coordinates":[-71.114998,42.371899],"type":"Point"}
}