{
  "type": "Feature",
  "properties": {
    "addr:full":"496 Newtown Rd Littleton MA 01460",
    "addr:housenumber":"496",
    "addr:postcode":"01460",
    "addr:street":"Newtown Rd",
    "iso:country":"US",
    "sg:address":"496 Newtown Rd",
    "sg:city":"Littleton",
    "sg:classifiers":[
        {
            "category":"Building & Trades",
            "subcategory":"Construction",
            "type":"Services"
        }
    ],
    "sg:phone":"+1   ",
    "sg:postcode":"01460",
    "sg:province":"MA",
    "sg:tags":[
        "excavation",
        "contractor"
    ],
    "wof:name":"M H Whitcomb Excavating Co",
    "wof:placetype":"venue"
},
  "geometry": {"coordinates":[-71.463105,42.521339],"type":"Point"}
}