{
  "type": "Feature",
  "properties": {
    "addr:full":"242 Baker Ave Concord MA 01742",
    "addr:housenumber":"242",
    "addr:postcode":"01742",
    "addr:street":"Baker Ave",
    "iso:country":"US",
    "sg:address":"242 Baker Ave",
    "sg:city":"Concord",
    "sg:classifiers":[
        {
            "category":"Health Services",
            "subcategory":"Optometrist",
            "type":"Services"
        }
    ],
    "sg:phone":"+1 978 287 9552",
    "sg:postcode":"01742",
    "sg:province":"MA",
    "wof:name":"Wesson & Niro Eyecare PC",
    "wof:placetype":"venue"
},
  "geometry": {"coordinates":[-71.385593,42.458758],"type":"Point"}
}