{
  "type": "Feature",
  "properties": {
    "iso:country":"US",
    "sg:address":"677 Huntington Avenue",
    "sg:city":"Boston",
    "sg:classifiers":[
        {
            "category":"Restaurant",
            "type":"Food & Drink"
        }
    ],
    "sg:phone":"+1 617 432 1045",
    "sg:postcode":"02115",
    "sg:province":"MA",
    "wof:name":"Sebastian's Cafe",
    "wof:placetype":"venue"
},
  "geometry": {"coordinates":[-71.102148,42.335228],"type":"Point"}
}