{
  "type": "Feature",
  "properties": {
    "iso:country":"US",
    "sg:address":"4 Revere Rd",
    "sg:city":"Southwick",
    "sg:classifiers":[
        {
            "category":"Building & Trades",
            "subcategory":"Electrical",
            "type":"Services"
        }
    ],
    "sg:phone":"+1   ",
    "sg:postcode":"01077",
    "sg:province":"MA",
    "sg:tags":[
        "electrical",
        "contractor"
    ],
    "wof:name":"Poulo Electric Co",
    "wof:placetype":"venue"
},
  "geometry": {"coordinates":[-72.756987,42.083723],"type":"Point"}
}