{
  "type": "Feature",
  "properties": {
    "addr:full": "96 Sweetwater Ave Bedford MA 01730",
    "addr:housenumber": "96",
    "addr:postcode": "01730",
    "addr:street": "Sweetwater Ave",
    "iso:country": "US",
    "sg:address": "96 Sweetwater Ave",
    "sg:city": "Bedford",
    "sg:classifiers": [
      {
        "category": "Professional",
        "subcategory": "Business Services",
        "type": "Services"
      }
    ],
    "sg:phone": "+1   ",
    "sg:postcode": "01730",
    "sg:province": "MA",
    "wof:name": "Bela Cosmetics Corp",
    "wof:placetype": "venue"
  },
  "geometry": {"coordinates":[-71.275374,42.514958],"type":"Point"}
}
