{
  "type": "Feature",
  "properties": {
    "iso:country":"US",
    "sg:address":"4 Eastside St",
    "sg:city":"Lawrence",
    "sg:classifiers":[
        {
            "category":"Insurance",
            "subcategory":"Hazard Insurance",
            "type":"Services"
        }
    ],
    "sg:phone":"+1 978 688 5011",
    "sg:postcode":"01841",
    "sg:province":"MA",
    "sg:tags":[
        "commercial",
        "business"
    ],
    "wof:name":"Hassey Insurance Agency",
    "wof:placetype":"venue"
},
  "geometry": {"coordinates":[-71.14078000000001,42.713814],"type":"Point"}
}