{
  "type": "Feature",
  "properties": {
    "iso:country":"US",
    "sg:address":"3132 Lexington Ridge Dr",
    "sg:city":"Lexington",
    "sg:classifiers":[
        {
            "category":"Professional",
            "subcategory":"Management & Consulting",
            "type":"Services"
        }
    ],
    "sg:phone":"+1 781 676 0770",
    "sg:postcode":"02421",
    "sg:province":"MA",
    "sg:tags":[
        "fuel"
    ],
    "wof:name":"Sterling Foundation Mgmt LLC",
    "wof:placetype":"venue"
},
  "geometry": {"coordinates":[-71.23443,42.41396],"type":"Point"}
}