{
  "type": "Feature",
  "properties": {
    "iso:country":"US",
    "sg:address":"17 Meriam St",
    "sg:city":"Lexington",
    "sg:classifiers":[
        {
            "category":"Place Of Worship",
            "subcategory":"Church",
            "type":"Public Place"
        },
        {
            "category":"Place Of Worship",
            "type":"Public Place"
        }
    ],
    "sg:phone":"+1 781 862 6453",
    "sg:postcode":"02420",
    "sg:province":"MA",
    "sg:tags":[
        "churches-greek",
        "churches-eastern",
        "orthodox"
    ],
    "sg:website":"http://www.archangelmichaelchurch.org",
    "wof:name":"St Nicholas Greek Orthodox Ch",
    "wof:placetype":"venue"
},
  "geometry": {"coordinates":[-71.227867,42.449749],"type":"Point"}
}