{
  "type": "Feature",
  "properties": {
    "iso:country":"US",
    "sg:address":"300 Unicorn Park Dr",
    "sg:city":"Woburn",
    "sg:classifiers":[
        {
            "category":"Sports & Exercise",
            "subcategory":"Gym",
            "type":"Entertainment"
        }
    ],
    "sg:phone":"+1 781 935 1604",
    "sg:postcode":"01801",
    "sg:province":"MA",
    "wof:name":"Unicorn Park",
    "wof:placetype":"venue"
},
  "geometry": {"coordinates":[-71.114502,42.482899],"type":"Point"}
}