{
  "type": "Feature",
  "properties": {
    "iso:country":"US",
    "sg:address":"9 Francis Ave",
    "sg:city":"Mansfield",
    "sg:classifiers":[
        {
            "category":"Real Estate",
            "subcategory":"Real Estate Operator",
            "type":"Services"
        }
    ],
    "sg:phone":"+1 508 339 4178",
    "sg:postcode":"02048",
    "sg:province":"MA",
    "sg:tags":[
        "apartment"
    ],
    "wof:name":"Village At Mansfield Depot",
    "wof:placetype":"venue"
},
  "geometry": {"coordinates":[-71.211889,42.04011],"type":"Point"}
}