{
  "type": "Feature",
  "properties": {
    "iso:country":"US",
    "sg:address":"189 Market St",
    "sg:city":"Lowell",
    "sg:classifiers":[
        {
            "category":"Wholesale",
            "subcategory":"Apparel",
            "type":"Manufacturing & Wholesale Goods"
        },
        {
            "category":"Shopping",
            "subcategory":"Shoes",
            "type":"Retail Goods"
        }
    ],
    "sg:phone":"+1 978 934 0762",
    "sg:postcode":"01852",
    "sg:province":"MA",
    "sg:tags":[
        "shoes-wholesale",
        "store",
        "manufacturer"
    ],
    "wof:name":"Kenners Shoes Store Major League Sports",
    "wof:placetype":"venue"
},
  "geometry": {"coordinates":[-71.31202500000001,42.644564],"type":"Point"}
}