{
  "type": "Feature",
  "properties": {
    "iso:country":"US",
    "sg:address":"18 Holly Rd",
    "sg:city":"Holbrook",
    "sg:classifiers":[
        {
            "category":"Building & Trades",
            "subcategory":"Electrical",
            "type":"Services"
        }
    ],
    "sg:phone":"+1 781 767 0183",
    "sg:postcode":"02343",
    "sg:province":"MA",
    "sg:tags":[
        "electrician",
        "electric",
        "contractor"
    ],
    "wof:name":"A & B Electric",
    "wof:placetype":"venue"
},
  "geometry": {"coordinates":[-71.014689,42.139507],"type":"Point"}
}