{
  "type": "Feature",
  "properties": {
    "addr:full": "18 Holly Rd Holbrook MA 02343",
    "addr:housenumber": "18",
    "addr:postcode": "02343",
    "addr:street": "Holly Rd",
    "iso:country": "US",
    "sg:address": "18 Holly Rd",
    "sg:city": "Holbrook",
    "sg:classifiers": [
      {
        "category": "Building \u0026 Trades",
        "subcategory": "Electrical",
        "type": "Services"
      }
    ],
    "sg:phone": "+1 781 767 0183",
    "sg:postcode": "02343",
    "sg:province": "MA",
    "sg:tags": [
      "electrician",
      "electric",
      "contractor"
    ],
    "wof:name": "A \u0026 B Electric",
    "wof:placetype": "venue"
  },
  "geometry": {"coordinates":[-71.014689,42.139507],"type":"Point"}
}
