{
  "type": "Feature",
  "properties": {
    "iso:country":"US",
    "sg:address":"9A Hamilton Pl 1st Fl",
    "sg:city":"Boston",
    "sg:classifiers":[
        {
            "category":"Landmark",
            "subcategory":"Tourist Information",
            "type":"Public Place"
        }
    ],
    "sg:phone":"+1 866 668 4345",
    "sg:postcode":"02108",
    "sg:province":"MA",
    "sg:tags":[
        "tour"
    ],
    "sg:website":"www.bostonmovietours.net",
    "wof:name":"Boston Movie Tours",
    "wof:placetype":"venue"
},
  "geometry": {"coordinates":[-71.061193,42.356399],"type":"Point"}
}