{
  "type": "Feature",
  "properties": {
    "addr:full":"1197 State Rd Plymouth MA 02360",
    "addr:housenumber":"1197",
    "addr:postcode":"02360",
    "addr:street":"State Rd",
    "iso:country":"US",
    "sg:address":"1197 State Rd",
    "sg:city":"Plymouth",
    "sg:classifiers":[
        {
            "category":"Recreation",
            "type":"Entertainment"
        }
    ],
    "sg:phone":"+1 508 224 0216",
    "sg:postcode":"02360",
    "sg:province":"MA",
    "sg:tags":[
        "center"
    ],
    "wof:name":"South Plymouth Little League",
    "wof:placetype":"venue"
},
  "geometry": {"coordinates":[-70.539484,41.888905],"type":"Point"}
}