{
  "type": "Feature",
  "properties": {
    "addr:full":"20 Rice St Newton MA 02459",
    "addr:housenumber":"20",
    "addr:postcode":"02459",
    "addr:street":"Rice St",
    "iso:country":"US",
    "sg:address":"20 Rice St",
    "sg:city":"Newton",
    "sg:classifiers":[
        {
            "category":"Manufacturing",
            "subcategory":"Musical Instruments",
            "type":"Manufacturing & Wholesale Goods"
        }
    ],
    "sg:phone":"+1   ",
    "sg:postcode":"02459",
    "sg:province":"MA",
    "sg:tags":[
        "mfg"
    ],
    "wof:name":"David Polstein Violin Maker",
    "wof:placetype":"venue"
},
  "geometry": {"coordinates":[-71.124107,42.327338],"type":"Point"}
}