{
  "type": "Feature",
  "properties": {
    "addr:full":"10 Southwick Hill Southwick MA 01077",
    "addr:housenumber":"10",
    "addr:postcode":"01077",
    "addr:street":"Southwick Hill",
    "iso:country":"US",
    "sg:address":"10 Southwick Hill",
    "sg:city":"Southwick",
    "sg:classifiers":[
        {
            "category":"Real Estate",
            "subcategory":"Real Estate Agent",
            "type":"Services"
        }
    ],
    "sg:phone":"+1   ",
    "sg:postcode":"01077",
    "sg:province":"MA",
    "wof:name":"N & W Associates",
    "wof:placetype":"venue"
},
  "geometry": {"coordinates":[-72.765204,42.058737],"type":"Point"}
}