{
  "type": "Feature",
  "properties": {
    "addr:full":"13 Orient St Worcester MA 01604",
    "addr:housenumber":"13",
    "addr:postcode":"01604",
    "addr:street":"Orient St",
    "iso:country":"US",
    "sg:address":"13 Orient St",
    "sg:city":"Worcester",
    "sg:classifiers":[
        {
            "category":"Personal",
            "subcategory":"Beauty Salon",
            "type":"Services"
        }
    ],
    "sg:phone":"+1 508 755 9598",
    "sg:postcode":"01604",
    "sg:province":"MA",
    "sg:tags":[
        "shop"
    ],
    "wof:name":"Estetica Hair Design",
    "wof:placetype":"venue"
},
  "geometry": {"coordinates":[-71.784707,42.257049],"type":"Point"}
}