{
  "type": "Feature",
  "properties": {
    "iso:country":"US",
    "sg:address":"11 Ballard Way",
    "sg:city":"Lawrence",
    "sg:classifiers":[
        {
            "category":"Organizations",
            "subcategory":"Non-profit Organization",
            "type":"Services"
        }
    ],
    "sg:phone":"+1 978 682 9360",
    "sg:postcode":"01843",
    "sg:province":"MA",
    "sg:tags":[
        "human"
    ],
    "wof:name":"Community Initatives",
    "wof:placetype":"venue"
},
  "geometry": {"coordinates":[-71.185807,42.683243],"type":"Point"}
}