{
  "type": "Feature",
  "properties": {
    "iso:country":"US",
    "sg:address":"8 Roberts Ln",
    "sg:city":"Nantucket",
    "sg:classifiers":[
        {
            "category":"Building & Trades",
            "subcategory":"Construction",
            "type":"Services"
        }
    ],
    "sg:phone":"+1   ",
    "sg:postcode":"02554",
    "sg:province":"MA",
    "sg:tags":[
        "house"
    ],
    "wof:name":"Kendall Snfrd Old Hs Rsto & Ds",
    "wof:placetype":"venue"
},
  "geometry": {"coordinates":[-70.10647,41.274081],"type":"Point"}
}