{
  "type": "Feature",
  "properties": {
    "addr:full": "8 Roberts Ln Nantucket MA 02554",
    "addr:housenumber": "8",
    "addr:postcode": "02554",
    "addr:street": "Roberts Ln",
    "iso:country": "US",
    "sg:address": "8 Roberts Ln",
    "sg:city": "Nantucket",
    "sg:classifiers": [
      {
        "category": "Building \u0026 Trades",
        "subcategory": "Construction",
        "type": "Services"
      }
    ],
    "sg:phone": "+1   ",
    "sg:postcode": "02554",
    "sg:province": "MA",
    "sg:tags": [
      "house"
    ],
    "wof:name": "Kendall Snfrd Old Hs Rsto \u0026 Ds",
    "wof:placetype": "venue"
  },
  "geometry": {"coordinates":[-70.10647,41.274081],"type":"Point"}
}
