{
  "type": "Feature",
  "properties": {
    "addr:full": "690 Canton St Westwood MA 02090",
    "addr:housenumber": "690",
    "addr:postcode": "02090",
    "addr:street": "Canton St",
    "iso:country": "US",
    "sg:address": "690 Canton St",
    "sg:city": "Westwood",
    "sg:classifiers": [
      {
        "category": "Real Estate",
        "subcategory": "Real Estate Services",
        "type": "Services"
      }
    ],
    "sg:phone": "+1 781 326 1566",
    "sg:postcode": "02090",
    "sg:province": "MA",
    "sg:tags": [
      "management",
      "property"
    ],
    "wof:name": "Nordblom Management Co",
    "wof:placetype": "venue"
  },
  "geometry": {"coordinates":[-71.205101,42.224098],"type":"Point"}
}
