{
  "type": "Feature",
  "properties": {
    "addr:full": "4 Colton Rd Millbury MA 01527",
    "addr:housenumber": "4",
    "addr:postcode": "01527",
    "addr:street": "Colton Rd",
    "iso:country": "US",
    "sg:address": "4 Colton Rd",
    "sg:city": "Millbury",
    "sg:classifiers": [
      {
        "category": "Building \u0026 Trades",
        "subcategory": "Plumbing",
        "type": "Services"
      }
    ],
    "sg:phone": "+1 508 436 4507",
    "sg:postcode": "01527",
    "sg:province": "MA",
    "sg:tags": [
      "plumbing-drain",
      "plumber",
      "sewer",
      "cleaning"
    ],
    "sg:website": "http://worcester.citysearch.com/profile/external/652068820/millbury_ma/r_gustafson_sewer_and_drain.html?publisher=yellowpages\u0026reference_id=7\u0026placement=ypwebsitemip",
    "wof:name": "R. Gustafson Sewer and Drain",
    "wof:placetype": "venue"
  },
  "geometry": {"coordinates":[-71.745045,42.205252],"type":"Point"}
}
