{
  "type": "Feature",
  "properties": {
    "iso:country":"US",
    "sg:address":"125 Walnut St",
    "sg:city":"Watertown",
    "sg:classifiers":[
        {
            "category":"Social Services",
            "type":"Services"
        }
    ],
    "sg:phone":"+1 617 926 1113",
    "sg:postcode":"02472",
    "sg:province":"MA",
    "sg:tags":[
        "organization",
        "welfare"
    ],
    "wof:name":"Beaver Brook Step",
    "wof:placetype":"venue"
},
  "geometry": {"coordinates":[-71.17019000000001,42.365593],"type":"Point"}
}