{
  "type": "Feature",
  "properties": {
    "addr:full": "107 Curtis St Reading MA 01867",
    "addr:housenumber": "107",
    "addr:postcode": "01867",
    "addr:street": "Curtis St",
    "iso:country": "US",
    "sg:address": "107 Curtis St",
    "sg:city": "Reading",
    "sg:classifiers": [
      {
        "category": "Utilities",
        "subcategory": "Fuel Oil \u0026 Lpg",
        "type": "Services"
      }
    ],
    "sg:phone": "+1   ",
    "sg:postcode": "01867",
    "sg:province": "MA",
    "sg:tags": [
      "dealer"
    ],
    "wof:name": "Firewood Co",
    "wof:placetype": "venue"
  },
  "geometry": {"coordinates":[-71.11071,42.502831],"type":"Point"}
}
