{
  "type": "Feature",
  "properties": {
    "iso:country":"US",
    "sg:address":"107 Curtis St",
    "sg:city":"Reading",
    "sg:classifiers":[
        {
            "category":"Utilities",
            "subcategory":"Fuel Oil & Lpg",
            "type":"Services"
        }
    ],
    "sg:phone":"+1   ",
    "sg:postcode":"01867",
    "sg:province":"MA",
    "sg:tags":[
        "dealer"
    ],
    "wof:name":"Firewood Co",
    "wof:placetype":"venue"
},
  "geometry": {"coordinates":[-71.11071,42.502831],"type":"Point"}
}