{
  "type": "Feature",
  "properties": {
    "iso:country":"US",
    "sg:address":"1 Financial Ctr Fl 34",
    "sg:city":"Boston",
    "sg:classifiers":[
        {
            "category":"Banks & Credit Unions",
            "subcategory":"Investment Brokerage",
            "type":"Services"
        }
    ],
    "sg:phone":"+1 617 482 2450",
    "sg:postcode":"02111",
    "sg:province":"MA",
    "sg:tags":[
        "investing"
    ],
    "wof:name":"Loomis Sayles & Company",
    "wof:placetype":"venue"
},
  "geometry": {"coordinates":[-71.056186,42.352482],"type":"Point"}
}