{
  "type": "Feature",
  "properties": {
    "addr:full": "1 Financial Ctr Fl 34 Boston MA 02111",
    "addr:housenumber": "1;34",
    "addr:postcode": "02111",
    "addr:street": "Financial Ctr Fl",
    "iso:country": "US",
    "sg:address": "1 Financial Ctr Fl 34",
    "sg:city": "Boston",
    "sg:classifiers": [
      {
        "category": "Banks \u0026 Credit Unions",
        "subcategory": "Investment Brokerage",
        "type": "Services"
      }
    ],
    "sg:phone": "+1 617 482 2450",
    "sg:postcode": "02111",
    "sg:province": "MA",
    "sg:tags": [
      "investing"
    ],
    "wof:name": "Loomis Sayles \u0026 Company",
    "wof:placetype": "venue"
  },
  "geometry": {"coordinates":[-71.056186,42.352482],"type":"Point"}
}
