{
  "type": "Feature",
  "properties": {
    "addr:full": "92 High St Medford MA 02155",
    "addr:housenumber": "92",
    "addr:postcode": "02155",
    "addr:street": "High St",
    "iso:country": "US",
    "sg:address": "92 High St",
    "sg:city": "Medford",
    "sg:classifiers": [
      {
        "category": "Shopping",
        "type": "Retail Goods"
      }
    ],
    "sg:phone": "+1 781 396 3048",
    "sg:postcode": "02155",
    "sg:province": "MA",
    "sg:tags": [
      "hearing",
      "equipment",
      "supply",
      "impaired"
    ],
    "wof:name": "Diagnostic Hearing \u0026 Language",
    "wof:placetype": "venue"
  },
  "geometry": {"coordinates":[-71.112752,42.4189],"type":"Point"}
}
