{
  "type": "Feature",
  "properties": {
    "iso:country":"US",
    "sg:address":"308 Congress St",
    "sg:city":"Boston",
    "sg:classifiers":[
        {
            "category":"Education",
            "subcategory":"Special Training",
            "type":"Public Place"
        },
        {
            "category":"Education",
            "subcategory":"School",
            "type":"Public Place"
        }
    ],
    "sg:phone":"+1 617 695 2300",
    "sg:postcode":"02210",
    "sg:province":"MA",
    "sg:tags":[
        "high",
        "educational",
        "elementary",
        "middle"
    ],
    "sg:website":"www.citizenschools.org",
    "wof:name":"Citizens Schools Inc",
    "wof:placetype":"venue"
},
  "geometry": {"coordinates":[-71.050059,42.351565],"type":"Point"}
}