{
  "type": "Feature",
  "properties": {
    "addr:full": "16 Chapman St Oak Bluffs MA 02557",
    "addr:housenumber": "16",
    "addr:postcode": "02557",
    "addr:street": "Chapman St",
    "iso:country": "US",
    "sg:address": "16 Chapman St",
    "sg:city": "Oak Bluffs",
    "sg:classifiers": [
      {
        "category": "Restaurant",
        "type": "Food \u0026 Drink"
      }
    ],
    "sg:phone": "+1 508 693 2207",
    "sg:postcode": "02557",
    "sg:province": "MA",
    "wof:name": "Ocean View Restaurant",
    "wof:placetype": "venue"
  },
  "geometry": {"coordinates":[-70.563445,41.458917],"type":"Point"}
}
