{
  "type": "Feature",
  "properties": {
    "iso:country":"US",
    "sg:address":"119 Newmarket Sq",
    "sg:city":"Roxbury",
    "sg:classifiers":[
        {
            "category":"Wholesale",
            "subcategory":"Meat",
            "type":"Manufacturing & Wholesale Goods"
        }
    ],
    "sg:phone":"+1 617 442 4096",
    "sg:postcode":"02118",
    "sg:province":"MA",
    "sg:tags":[
        "shop",
        "packer"
    ],
    "wof:name":"Pyramid Foods Inc",
    "wof:placetype":"venue"
},
  "geometry": {"coordinates":[-71.0681,42.330502],"type":"Point"}
}