{
  "type": "Feature",
  "properties": {
    "iso:country":"US",
    "sg:address":"95 Washington Street",
    "sg:city":"Canton",
    "sg:classifiers":[
        {
            "category":"Health Services",
            "subcategory":"Dentist",
            "type":"Services"
        }
    ],
    "sg:phone":"+1 781 828 1090",
    "sg:postcode":"02021",
    "sg:province":"MA",
    "sg:website":"www.smiledesigninc.com",
    "wof:name":"Smile Design, Inc.",
    "wof:placetype":"venue"
},
  "geometry": {"coordinates":[-71.148926,42.141891],"type":"Point"}
}