{
  "type": "Feature",
  "properties": {
    "addr:full": "1 Dundee Park Dr Andover MA 01810",
    "addr:housenumber": "1",
    "addr:postcode": "01810",
    "addr:street": "Dundee Park Dr",
    "iso:country": "US",
    "sg:address": "1 Dundee Park Dr",
    "sg:city": "Andover",
    "sg:classifiers": [
      {
        "category": "Professional",
        "subcategory": "Management \u0026 Consulting",
        "type": "Services"
      }
    ],
    "sg:phone": "+1   ",
    "sg:postcode": "01810",
    "sg:province": "MA",
    "wof:name": "Closet Classic",
    "wof:placetype": "venue"
  },
  "geometry": {"coordinates":[-71.145868,42.655128],"type":"Point"}
}
