{
  "type": "Feature",
  "properties": {
    "iso:country":"US",
    "sg:address":"1 Dundee Park Dr",
    "sg:city":"Andover",
    "sg:classifiers":[
        {
            "category":"Professional",
            "subcategory":"Management & Consulting",
            "type":"Services"
        }
    ],
    "sg:phone":"+1   ",
    "sg:postcode":"01810",
    "sg:province":"MA",
    "wof:name":"Closet Classic",
    "wof:placetype":"venue"
},
  "geometry": {"coordinates":[-71.14586799999999,42.655128],"type":"Point"}
}