{
  "type": "Feature",
  "properties": {
    "iso:country":"US",
    "sg:address":"168 Ayer Rd",
    "sg:city":"Littleton",
    "sg:classifiers":[
        {
            "category":"Manufacturing",
            "subcategory":"Tools & Machinery",
            "type":"Manufacturing & Wholesale Goods"
        }
    ],
    "sg:phone":"+1 978 486 9626",
    "sg:postcode":"01460",
    "sg:province":"MA",
    "sg:tags":[
        "machine",
        "shop"
    ],
    "wof:name":"P & L Machine Co",
    "wof:placetype":"venue"
},
  "geometry": {"coordinates":[-71.526945,42.550819],"type":"Point"}
}