{
  "type": "Feature",
  "properties": {
    "addr:full":"97 Washington St Weymouth MA 02188",
    "addr:housenumber":"97",
    "addr:postcode":"02188",
    "addr:street":"Washington St",
    "iso:country":"US",
    "sg:address":"97 Washington St",
    "sg:city":"Weymouth",
    "sg:classifiers":[
        {
            "category":"Shopping",
            "subcategory":"Used Merchandise",
            "type":"Retail Goods"
        }
    ],
    "sg:phone":"+1 781 337 3111",
    "sg:postcode":"02188",
    "sg:province":"MA",
    "sg:tags":[
        "book",
        "rare",
        "dealer"
    ],
    "wof:name":"Weymouth Book",
    "wof:placetype":"venue"
},
  "geometry": {"coordinates":[-70.965677,42.217763],"type":"Point"}
}