{
  "type": "Feature",
  "properties": {
    "iso:country":"US",
    "sg:address":"59 Loring Ave",
    "sg:city":"Salem",
    "sg:classifiers":[
        {
            "category":"Restaurant",
            "type":"Food & Drink"
        }
    ],
    "sg:phone":"+1 978 744 3143",
    "sg:postcode":"01970",
    "sg:province":"MA",
    "sg:tags":[
        "grill",
        "bar"
    ],
    "wof:name":"White Dove Market & Grill",
    "wof:placetype":"venue"
},
  "geometry": {"coordinates":[-70.894092,42.502345],"type":"Point"}
}