{
  "type": "Feature",
  "properties": {
    "addr:full":"68 Main St Andover MA 01810",
    "addr:housenumber":"68",
    "addr:postcode":"01810",
    "addr:street":"Main St",
    "iso:country":"US",
    "sg:address":"68 Main St",
    "sg:city":"Andover",
    "sg:classifiers":[
        {
            "category":"Health Services",
            "subcategory":"Doctor",
            "type":"Services"
        }
    ],
    "sg:phone":"+1 978 475 1800",
    "sg:postcode":"01810",
    "sg:province":"MA",
    "sg:tags":[
        "physician",
        "surgeon"
    ],
    "wof:name":"Joseph Gendlerman MD",
    "wof:placetype":"venue"
},
  "geometry": {"coordinates":[-71.138704,42.653963],"type":"Point"}
}