{
  "type": "Feature",
  "properties": {
    "iso:country":"US",
    "sg:address":"64 Central St",
    "sg:city":"Holliston",
    "sg:classifiers":[
        {
            "category":"Retail",
            "subcategory":"Laundry & Dry Cleaning",
            "type":"Services"
        }
    ],
    "sg:phone":"+1 508 429 2671",
    "sg:postcode":"01746",
    "sg:province":"MA",
    "sg:tags":[
        "cleaners"
    ],
    "wof:name":"Holliston Cleaners",
    "wof:placetype":"venue"
},
  "geometry": {"coordinates":[-71.427254,42.199958],"type":"Point"}
}