{
  "type": "Feature",
  "properties": {
    "addr:full": "61 Church St Cambridge MA 02138",
    "addr:housenumber": "61",
    "addr:postcode": "02138",
    "addr:street": "Church St",
    "iso:country": "US",
    "sg:address": "61 Church St",
    "sg:city": "Cambridge",
    "sg:classifiers": [
      {
        "category": "Restaurant",
        "type": "Food \u0026 Drink"
      }
    ],
    "sg:phone": "+1 617 876 4090",
    "sg:postcode": "02138",
    "sg:province": "MA",
    "sg:tags": [
      "traditional",
      "american"
    ],
    "wof:name": "Harvard Cafe",
    "wof:placetype": "venue"
  },
  "geometry": {"coordinates":[-71.121229,42.374263],"type":"Point"}
}
