{
  "type": "Feature",
  "properties": {
    "iso:country":"US",
    "sg:address":"4105 Main St",
    "sg:city":"Palmer",
    "sg:classifiers":[
        {
            "category":"Education",
            "subcategory":"School",
            "type":"Public Place"
        }
    ],
    "sg:phone":"+1 413 283 2626",
    "sg:postcode":"01069",
    "sg:province":"MA",
    "wof:name":"Library High School",
    "wof:placetype":"venue"
},
  "geometry": {"coordinates":[-72.34407299999999,42.187615],"type":"Point"}
}