{
  "type": "Feature",
  "properties": {
    "addr:full": "73 Main St Peabody MA 01960",
    "addr:housenumber": "73",
    "addr:postcode": "01960",
    "addr:street": "Main St",
    "iso:country": "US",
    "sg:address": "73 Main St",
    "sg:city": "Peabody",
    "sg:classifiers": [
      {
        "category": "Retail",
        "subcategory": "Portrait Studio",
        "type": "Services"
      },
      {
        "category": "Professional",
        "subcategory": "Art Services",
        "type": "Services"
      }
    ],
    "sg:phone": "+1 978 532 0077",
    "sg:postcode": "01960",
    "sg:province": "MA",
    "sg:tags": [
      "rental",
      "photographers-portrait",
      "photographic",
      "darkroom"
    ],
    "wof:name": "Century Studios",
    "wof:placetype": "venue"
  },
  "geometry": {"coordinates":[-70.924229,42.524547],"type":"Point"}
}
