{
  "type": "Feature",
  "properties": {
    "iso:country":"US",
    "sg:address":"26 Howley St",
    "sg:city":"Peabody",
    "sg:classifiers":[
        {
            "category":"Banks & Credit Unions",
            "subcategory":"Bank",
            "type":"Services"
        },
        {
            "category":"Shopping",
            "subcategory":"Used Merchandise",
            "type":"Retail Goods"
        }
    ],
    "sg:phone":"+1 978 854 5282",
    "sg:postcode":"01960",
    "sg:province":"MA",
    "sg:tags":[
        "resale",
        "shop",
        "second",
        "hand"
    ],
    "wof:name":"Recylce For Hunger Thrift Shop",
    "wof:placetype":"venue"
},
  "geometry": {"coordinates":[-70.91873200000001,42.524399],"type":"Point"}
}