{
  "type": "Feature",
  "properties": {
    "iso:country":"US",
    "sg:address":"52 Sumner Ave",
    "sg:city":"Springfield",
    "sg:classifiers":[
        {
            "category":"Social Services",
            "subcategory":"Child Care",
            "type":"Services"
        }
    ],
    "sg:phone":"+1 413 739 4618",
    "sg:postcode":"01108",
    "sg:province":"MA",
    "sg:website":"www.sdn.org",
    "wof:name":"Springfield Day Nursery Corp",
    "wof:placetype":"venue"
},
  "geometry": {"coordinates":[-72.57512199999999,42.082811],"type":"Point"}
}