{
  "type": "Feature",
  "properties": {
    "addr:full": "76 East St Pittsfield MA 01201",
    "addr:housenumber": "76",
    "addr:postcode": "01201",
    "addr:street": "East St",
    "iso:country": "US",
    "sg:address": "76 East St",
    "sg:city": "Pittsfield",
    "sg:classifiers": [
      {
        "category": "Government",
        "subcategory": "Office",
        "type": "Public Place"
      }
    ],
    "sg:phone": "+1 413 448 5325",
    "sg:postcode": "01201",
    "sg:province": "MA",
    "wof:name": "Superintendent Of Buildings",
    "wof:placetype": "venue"
  },
  "geometry": {"coordinates":[-73.252602,42.44804],"type":"Point"}
}
