{
  "type": "Feature",
  "properties": {
    "addr:full": "526 Boston Post Rd Wayland MA 01778",
    "addr:housenumber": "526",
    "addr:postcode": "01778",
    "addr:street": "Boston Post Rd",
    "iso:country": "US",
    "sg:address": "526 Boston Post Rd",
    "sg:city": "Wayland",
    "sg:classifiers": [
      {
        "category": "Health Services",
        "subcategory": "Clinic",
        "type": "Services"
      }
    ],
    "sg:phone": "+1 508 358 7353",
    "sg:postcode": "01778",
    "sg:province": "MA",
    "sg:tags": [
      "home"
    ],
    "wof:name": "Christopher House Fund Inc",
    "wof:placetype": "venue"
  },
  "geometry": {"coordinates":[-71.389244,42.363101],"type":"Point"}
}
