{
  "type": "Feature",
  "properties": {
    "iso:country":"US",
    "sg:address":"377 Main St",
    "sg:city":"Wakefield",
    "sg:classifiers":[
        {
            "category":"Banks & Credit Unions",
            "subcategory":"Bank",
            "type":"Services"
        }
    ],
    "sg:phone":"+1 781 245 5500",
    "sg:postcode":"01880",
    "sg:province":"MA",
    "sg:tags":[
        "loan"
    ],
    "wof:name":"Affiliated Mortgages Svc",
    "wof:placetype":"venue"
},
  "geometry": {"coordinates":[-71.07060799999999,42.503857],"type":"Point"}
}