{
  "type": "Feature",
  "properties": {
    "addr:full": "377 Main St Wakefield MA 01880",
    "addr:housenumber": "377",
    "addr:postcode": "01880",
    "addr:street": "Main St",
    "iso:country": "US",
    "sg:address": "377 Main St",
    "sg:city": "Wakefield",
    "sg:classifiers": [
      {
        "category": "Banks \u0026 Credit Unions",
        "subcategory": "Bank",
        "type": "Services"
      }
    ],
    "sg:phone": "+1 781 245 5500",
    "sg:postcode": "01880",
    "sg:province": "MA",
    "sg:tags": [
      "loan"
    ],
    "wof:name": "Affiliated Mortgages Svc",
    "wof:placetype": "venue"
  },
  "geometry": {"coordinates":[-71.070608,42.503857],"type":"Point"}
}
