{
  "type": "Feature",
  "properties": {
    "addr:full": "186 Main St Harwich MA 02645",
    "addr:housenumber": "186",
    "addr:postcode": "02645",
    "addr:street": "Main St",
    "iso:country": "US",
    "sg:address": "186 Main St",
    "sg:city": "Harwich",
    "sg:classifiers": [
      {
        "category": "Building \u0026 Trades",
        "subcategory": "Landscaping Services",
        "type": "Services"
      }
    ],
    "sg:phone": "+1 508 432 5227",
    "sg:postcode": "02645",
    "sg:province": "MA",
    "sg:tags": [
      "landscape",
      "contractor"
    ],
    "wof:name": "Blue Sky Landscape Svc",
    "wof:placetype": "venue"
  },
  "geometry": {"coordinates":[-70.11764,41.69516],"type":"Point"}
}
