{
  "type": "Feature",
  "properties": {
    "iso:country":"US",
    "sg:address":"400 W Cummings Park # 6650",
    "sg:city":"Woburn",
    "sg:classifiers":[
        {
            "category":"Health Services",
            "subcategory":"Clinic",
            "type":"Services"
        }
    ],
    "sg:phone":"+1 781 938 4048",
    "sg:postcode":"01801",
    "sg:province":"MA",
    "sg:tags":[
        "information",
        "mental"
    ],
    "wof:name":"Nami",
    "wof:placetype":"venue"
},
  "geometry": {"coordinates":[-71.12651,42.496385],"type":"Point"}
}