{
  "type": "Feature",
  "properties": {
    "addr:full": "32 Lake St Webster MA 01570",
    "addr:housenumber": "32",
    "addr:postcode": "01570",
    "addr:street": "Lake St",
    "iso:country": "US",
    "ovtr:label": "Sunnyside Farms, 25 Lake St Webster MA US",
    "ovtr:similarity": 3.3903160095214844,
    "sg:address": "32 Lake St",
    "sg:city": "Webster",
    "sg:classifiers": [
      {
        "category": "Food \u0026 Beverages",
        "subcategory": "Groceries \u0026 Convenience Stores",
        "type": "Retail Goods"
      }
    ],
    "sg:phone": "+1 508 943 7224",
    "sg:postcode": "01570",
    "sg:province": "MA",
    "wof:name": "Sunnyside Farms",
    "wof:placetype": "venue"
  },
  "geometry": {"coordinates":[-71.878739,42.04995],"type":"Point"}
}
