{
  "type": "Feature",
  "properties": {
    "addr:full":"32 Lake St Webster MA 01570",
    "addr:housenumber":"32",
    "addr:postcode":"01570",
    "addr:street":"Lake St",
    "iso:country":"US",
    "sg:address":"32 Lake St",
    "sg:city":"Webster",
    "sg:classifiers":[
        {
            "category":"Food & Beverages",
            "subcategory":"Groceries & Convenience Stores",
            "type":"Retail Goods"
        }
    ],
    "sg:phone":"+1 508 943 7224",
    "sg:postcode":"01570",
    "sg:province":"MA",
    "wof:name":"Sunnyside Farms",
    "wof:placetype":"venue"
},
  "geometry": {"coordinates":[-71.878739,42.04995],"type":"Point"}
}