{
  "type": "Feature",
  "properties": {
    "iso:country":"US",
    "sg:address":"334 Union St",
    "sg:city":"New Bedford",
    "sg:classifiers":[
        {
            "category":"Health Services",
            "subcategory":"Doctor",
            "type":"Services"
        }
    ],
    "sg:phone":"+1 508 997 0121",
    "sg:postcode":"02740",
    "sg:province":"MA",
    "sg:tags":[
        "physician",
        "surgeon"
    ],
    "wof:name":"Dermatology & Allergy Assoc PC",
    "wof:placetype":"venue"
},
  "geometry": {"coordinates":[-70.93274,41.633471],"type":"Point"}
}