{
  "type": "Feature",
  "properties": {
    "iso:country":"US",
    "sg:address":"29 Center St",
    "sg:city":"Andover",
    "sg:classifiers":[
        {
            "category":"Professional",
            "subcategory":"Art Services",
            "type":"Services"
        }
    ],
    "sg:phone":"+1   ",
    "sg:postcode":"01810",
    "sg:province":"MA",
    "sg:tags":[
        "commercial",
        "design"
    ],
    "wof:name":"Studio Boudreau",
    "wof:placetype":"venue"
},
  "geometry": {"coordinates":[-71.16136400000001,42.626867],"type":"Point"}
}