{
  "type": "Feature",
  "properties": {
    "addr:full": "29 Center St Andover MA 01810",
    "addr:housenumber": "29",
    "addr:postcode": "01810",
    "addr:street": "Center St",
    "iso:country": "US",
    "sg:address": "29 Center St",
    "sg:city": "Andover",
    "sg:classifiers": [
      {
        "category": "Professional",
        "subcategory": "Art Services",
        "type": "Services"
      }
    ],
    "sg:phone": "+1   ",
    "sg:postcode": "01810",
    "sg:province": "MA",
    "sg:tags": [
      "commercial",
      "design"
    ],
    "wof:name": "Studio Boudreau",
    "wof:placetype": "venue"
  },
  "geometry": {"coordinates":[-71.161364,42.626867],"type":"Point"}
}
