{
  "type": "Feature",
  "properties": {
    "iso:country":"US",
    "sg:address":"1714 Worcester Rd",
    "sg:city":"Framingham",
    "sg:classifiers":[
        {
            "category":"Restaurant",
            "type":"Food & Drink"
        }
    ],
    "sg:menulink":"http://www.allmenus.com/ma/framingham/42503-acapulco/menu/",
    "sg:phone":"+1 508 875 1188",
    "sg:postcode":"01702",
    "sg:province":"MA",
    "sg:tags":[
        "american",
        "mexican",
        "tex-mex"
    ],
    "wof:name":"Acapulco",
    "wof:placetype":"venue"
},
  "geometry": {"coordinates":[-71.478934,42.296768],"type":"Point"}
}