{
  "type": "Feature",
  "properties": {
    "iso:country":"US",
    "sg:address":"228 Sturbridge Rd",
    "sg:city":"Brimfield",
    "sg:classifiers":[
        {
            "category":"Travel",
            "subcategory":"Campground",
            "type":"Entertainment"
        }
    ],
    "sg:phone":"+1 413 245 3504",
    "sg:postcode":"01010",
    "sg:province":"MA",
    "sg:website":"www.villagegreencampground.com",
    "wof:name":"Village Green Campground",
    "wof:placetype":"venue"
},
  "geometry": {"coordinates":[-72.16712099999999,42.110984],"type":"Point"}
}