{
  "type": "Feature",
  "properties": {
    "addr:full": "55 Highland Rock Dr Stoughton MA 02072",
    "addr:housenumber": "55",
    "addr:postcode": "02072",
    "addr:street": "Highland Rock Dr",
    "iso:country": "US",
    "sg:address": "55 Highland Rock Dr",
    "sg:city": "Stoughton",
    "sg:classifiers": [
      {
        "category": "Wholesale",
        "subcategory": "Apparel",
        "type": "Manufacturing \u0026 Wholesale Goods"
      }
    ],
    "sg:phone": "+1 781 344 5281",
    "sg:postcode": "02072",
    "sg:province": "MA",
    "sg:tags": [
      "sportswear"
    ],
    "wof:name": "Ni Pro Co",
    "wof:placetype": "venue"
  },
  "geometry": {"coordinates":[-71.119811,42.084166],"type":"Point"}
}
