{
  "type": "Feature",
  "properties": {
    "iso:country":"US",
    "sg:address":"55 Highland Rock Dr",
    "sg:city":"Stoughton",
    "sg:classifiers":[
        {
            "category":"Wholesale",
            "subcategory":"Apparel",
            "type":"Manufacturing & Wholesale Goods"
        }
    ],
    "sg:phone":"+1 781 344 5281",
    "sg:postcode":"02072",
    "sg:province":"MA",
    "sg:tags":[
        "sportswear"
    ],
    "wof:name":"Ni Pro Co",
    "wof:placetype":"venue"
},
  "geometry": {"coordinates":[-71.119811,42.084166],"type":"Point"}
}