{
  "type": "Feature",
  "properties": {
    "iso:country":"US",
    "sg:address":"359 Hartford Ave",
    "sg:city":"Bellingham",
    "sg:classifiers":[
        {
            "category":"Professional",
            "type":"Services"
        }
    ],
    "sg:phone":"+1   ",
    "sg:postcode":"02019",
    "sg:province":"MA",
    "wof:name":"Chives Inc",
    "wof:placetype":"venue"
},
  "geometry": {"coordinates":[-71.45555400000001,42.122638],"type":"Point"}
}