{
  "type": "Feature",
  "properties": {
    "addr:full": "359 Hartford Ave Bellingham MA 02019",
    "addr:housenumber": "359",
    "addr:postcode": "02019",
    "addr:street": "Hartford Ave",
    "iso:country": "US",
    "sg:address": "359 Hartford Ave",
    "sg:city": "Bellingham",
    "sg:classifiers": [
      {
        "category": "Professional",
        "type": "Services"
      }
    ],
    "sg:phone": "+1   ",
    "sg:postcode": "02019",
    "sg:province": "MA",
    "wof:name": "Chives Inc",
    "wof:placetype": "venue"
  },
  "geometry": {"coordinates":[-71.455554,42.122638],"type":"Point"}
}
