{
  "type": "Feature",
  "properties": {
    "addr:full":"10 Union St Natick MA 01760",
    "addr:housenumber":"10",
    "addr:postcode":"01760",
    "addr:street":"Union St",
    "iso:country":"US",
    "sg:address":"10 Union St",
    "sg:city":"Natick",
    "sg:classifiers":[
        {
            "category":"Health Services",
            "subcategory":"Doctor",
            "type":"Services"
        }
    ],
    "sg:phone":"+1 508 650 1022",
    "sg:postcode":"01760",
    "sg:province":"MA",
    "sg:tags":[
        "physician",
        "surgeon"
    ],
    "wof:name":"Nirmel Krisha",
    "wof:placetype":"venue"
},
  "geometry": {"coordinates":[-71.339172,42.283947],"type":"Point"}
}