{
  "type": "Feature",
  "properties": {
    "addr:full": "10 Presidential Way Woburn MA 01801",
    "addr:housenumber": "10",
    "addr:postcode": "01801",
    "addr:street": "Presidential Way",
    "iso:country": "US",
    "sg:address": "10 Presidential Way",
    "sg:city": "Woburn",
    "sg:classifiers": [
      {
        "category": "Professional",
        "subcategory": "Computer Services",
        "type": "Services"
      }
    ],
    "sg:phone": "+1 888 553 9216",
    "sg:postcode": "01801",
    "sg:province": "MA",
    "sg:website": "http://www.demandware.com",
    "wof:name": "Demandware",
    "wof:placetype": "venue"
  },
  "geometry": {"coordinates":[-71.147803,42.524757],"type":"Point"}
}
