{
  "type": "Feature",
  "properties": {
    "iso:country":"US",
    "sg:address":"1050 Commonwealth Ave",
    "sg:city":"Newton Center",
    "sg:classifiers":[
        {
            "category":"Health Services",
            "subcategory":"Hospital",
            "type":"Services"
        }
    ],
    "sg:phone":"+1 617 277 9799",
    "sg:postcode":"02459",
    "sg:province":"MA",
    "sg:tags":[
        "mental"
    ],
    "wof:name":"Peer Educators Project",
    "wof:placetype":"venue"
},
  "geometry": {"coordinates":[-71.21113200000001,42.337901],"type":"Point"}
}