{
  "type": "Feature",
  "properties": {
    "iso:country":"US",
    "sg:address":"355 May St",
    "sg:city":"Worcester",
    "sg:classifiers":[
        {
            "category":"Building & Trades",
            "subcategory":"Landscaping Services",
            "type":"Services"
        }
    ],
    "sg:phone":"+1 508 799 9414",
    "sg:postcode":"01602",
    "sg:province":"MA",
    "sg:tags":[
        "landscape",
        "contractor"
    ],
    "wof:name":"Tormey Landscaping",
    "wof:placetype":"venue"
},
  "geometry": {"coordinates":[-71.84164699999999,42.26943],"type":"Point"}
}