{
  "type": "Feature",
  "properties": {
    "addr:full": "355 May St Worcester MA 01602",
    "addr:housenumber": "355",
    "addr:postcode": "01602",
    "addr:street": "May St",
    "iso:country": "US",
    "sg:address": "355 May St",
    "sg:city": "Worcester",
    "sg:classifiers": [
      {
        "category": "Building \u0026 Trades",
        "subcategory": "Landscaping Services",
        "type": "Services"
      }
    ],
    "sg:phone": "+1 508 799 9414",
    "sg:postcode": "01602",
    "sg:province": "MA",
    "sg:tags": [
      "landscape",
      "contractor"
    ],
    "wof:name": "Tormey Landscaping",
    "wof:placetype": "venue"
  },
  "geometry": {"coordinates":[-71.841647,42.26943],"type":"Point"}
}
