{
  "type": "Feature",
  "properties": {
    "iso:country":"US",
    "sg:address":"5 Lan Dr Ste 300",
    "sg:city":"Westford",
    "sg:classifiers":[
        {
            "category":"Professional",
            "subcategory":"Engineering",
            "type":"Services"
        }
    ],
    "sg:phone":"+1 978 692 1913",
    "sg:postcode":"01886",
    "sg:province":"MA",
    "sg:tags":[
        "consulting",
        "engineer"
    ],
    "sg:website":"http://www.zande.com",
    "wof:name":"Stantec Consulting Services Inc.",
    "wof:placetype":"venue"
},
  "geometry": {"coordinates":[-71.431314,42.561242],"type":"Point"}
}