{
  "type": "Feature",
  "properties": {
    "addr:full":"253 S Main St Fall River MA 02721",
    "addr:housenumber":"253",
    "addr:postcode":"02721",
    "addr:street":"S Main St",
    "iso:country":"US",
    "sg:address":"253 S Main St",
    "sg:city":"Fall River",
    "sg:classifiers":[
        {
            "category":"Shopping",
            "subcategory":"Discount & Variety Stores",
            "type":"Retail Goods"
        }
    ],
    "sg:phone":"+1 508 678 6683",
    "sg:postcode":"02721",
    "sg:province":"MA",
    "wof:name":"Dollar Fun",
    "wof:placetype":"venue"
},
  "geometry": {"coordinates":[-71.158664,41.698475],"type":"Point"}
}