{
  "type": "Feature",
  "properties": {
    "addr:full": "5 E Main St Merrimac MA 01860",
    "addr:housenumber": "5",
    "addr:postcode": "01860",
    "addr:street": "E Main St",
    "iso:country": "US",
    "sg:address": "5 E Main St",
    "sg:city": "Merrimac",
    "sg:classifiers": [
      {
        "category": "Shopping",
        "subcategory": "Gifts \u0026 Souvenirs",
        "type": "Retail Goods"
      }
    ],
    "sg:phone": "+1   ",
    "sg:postcode": "01860",
    "sg:province": "MA",
    "wof:name": "Lilys",
    "wof:placetype": "venue"
  },
  "geometry": {"coordinates":[-71.001787,42.834044],"type":"Point"}
}
