{
  "type": "Feature",
  "properties": {
    "addr:full":"15 Exchange St Brockton MA 02301",
    "addr:housenumber":"15",
    "addr:postcode":"02301",
    "addr:street":"Exchange St",
    "iso:country":"US",
    "sg:address":"15 Exchange St",
    "sg:city":"Brockton",
    "sg:classifiers":[
        {
            "category":"Professional",
            "type":"Services"
        }
    ],
    "sg:phone":"+1   ",
    "sg:postcode":"02301",
    "sg:province":"MA",
    "wof:name":"Arteamas",
    "wof:placetype":"venue"
},
  "geometry": {"coordinates":[-71.017684,42.075557],"type":"Point"}
}