{
  "type": "Feature",
  "properties": {
    "iso:country":"US",
    "sg:address":"95 High School Road Ext",
    "sg:city":"Hyannis",
    "sg:classifiers":[
        {
            "category":"Organizations",
            "subcategory":"Labor Organization",
            "type":"Services"
        }
    ],
    "sg:phone":"+1 508 775 1454",
    "sg:postcode":"02601",
    "sg:province":"MA",
    "wof:name":"Hyannis Fire Fighters Union Lo",
    "wof:placetype":"venue"
},
  "geometry": {"coordinates":[-70.288816,41.653326],"type":"Point"}
}