{
  "type": "Feature",
  "properties": {
    "iso:country":"US",
    "sg:address":"45 Slocum Rd",
    "sg:city":"North Dartmouth",
    "sg:classifiers":[
        {
            "category":"Real Estate",
            "subcategory":"Real Estate Agent",
            "type":"Services"
        }
    ],
    "sg:phone":"+1 508 996 6562",
    "sg:postcode":"02747",
    "sg:province":"MA",
    "wof:name":"Olde Darthmouth Realty Inc",
    "wof:placetype":"venue"
},
  "geometry": {"coordinates":[-70.958344,41.607251],"type":"Point"}
}