{
  "type": "Feature",
  "properties": {
    "iso:country":"US",
    "sg:address":"563 Great Rd",
    "sg:city":"Bolton",
    "sg:classifiers":[
        {
            "category":"Health Services",
            "subcategory":"Health Practitioner",
            "type":"Services"
        }
    ],
    "sg:phone":"+1 978 779 2888",
    "sg:postcode":"01720",
    "sg:province":"MA",
    "sg:tags":[
        "dental",
        "hygienist"
    ],
    "sg:website":"www.connellyandconnelly.com",
    "wof:name":"Connelly & Connelly",
    "wof:placetype":"venue"
},
  "geometry": {"coordinates":[-71.43306200000001,42.521258],"type":"Point"}
}