{
  "type": "Feature",
  "properties": {
    "iso:country":"US",
    "sg:address":"261 Mossman Rd",
    "sg:city":"Sudbury",
    "sg:classifiers":[
        {
            "category":"Organizations",
            "subcategory":"Community Association",
            "type":"Services"
        }
    ],
    "sg:phone":"+1 978 443 0712",
    "sg:postcode":"01776",
    "sg:province":"MA",
    "sg:tags":[
        "club"
    ],
    "wof:name":"Greenwood Tennis Club",
    "wof:placetype":"venue"
},
  "geometry": {"coordinates":[-71.42462,42.420803],"type":"Point"}
}