{
  "type": "Feature",
  "properties": {
    "iso:country":"US",
    "sg:address":"444 Lower County Rd",
    "sg:city":"Dennis Port",
    "sg:classifiers":[
        {
            "category":"Shopping",
            "subcategory":"Gifts & Souvenirs",
            "type":"Retail Goods"
        }
    ],
    "sg:phone":"+1 508 394 3373",
    "sg:postcode":"02639",
    "sg:province":"MA",
    "sg:tags":[
        "shop"
    ],
    "wof:name":"Grandma Daisy's Inc",
    "wof:placetype":"venue"
},
  "geometry": {"coordinates":[-70.12252100000001,41.66045],"type":"Point"}
}