{
  "type": "Feature",
  "properties": {
    "addr:full": "52 Glenwood Ave Hyde Park MA 02136",
    "addr:housenumber": "52",
    "addr:postcode": "02136",
    "addr:street": "Glenwood Ave",
    "iso:country": "US",
    "sg:address": "52 Glenwood Ave",
    "sg:city": "Hyde Park",
    "sg:classifiers": [
      {
        "category": "Building \u0026 Trades",
        "subcategory": "Cleaning \u0026 Sanitation",
        "type": "Services"
      }
    ],
    "sg:phone": "+1 617 361 3878",
    "sg:postcode": "02136",
    "sg:province": "MA",
    "sg:tags": [
      "janitor"
    ],
    "wof:name": "Luna Cleaning Svc",
    "wof:placetype": "venue"
  },
  "geometry": {"coordinates":[-71.127511,42.248886],"type":"Point"}
}
