{
  "type": "Feature",
  "properties": {
    "addr:full": "340 River St Cambridge MA 02139",
    "addr:housenumber": "340",
    "addr:postcode": "02139",
    "addr:street": "River St",
    "iso:country": "US",
    "ovtr:label": "Whole Foods Market, 340 River St Cambridge MA US",
    "ovtr:similarity": 2.707350015640259,
    "sg:address": "340 River St",
    "sg:city": "Cambridge",
    "sg:classifiers": [
      {
        "category": "Food \u0026 Beverages",
        "subcategory": "Groceries \u0026 Convenience Stores",
        "type": "Retail Goods"
      }
    ],
    "sg:phone": "+1 617 876 6990",
    "sg:postcode": "02139",
    "sg:province": "MA",
    "sg:tags": [
      "grocer"
    ],
    "sg:website": "www.wholefoods.com",
    "wof:name": "Whole Foods Market",
    "wof:placetype": "venue"
  },
  "geometry": {"coordinates":[-71.114006,42.362093],"type":"Point"}
}
