{
  "type": "Feature",
  "properties": {
    "iso:country":"US",
    "sg:address":"30 Gove St",
    "sg:city":"Boston",
    "sg:classifiers":[
        {
            "category":"Building & Trades",
            "subcategory":"Locksmith",
            "type":"Services"
        }
    ],
    "sg:phone":"+1 617 895 3437",
    "sg:postcode":"02128",
    "sg:province":"MA",
    "sg:tags":[
        "key"
    ],
    "wof:name":"24 Hours A Locksmith",
    "wof:placetype":"venue"
},
  "geometry": {"coordinates":[-71.037491,42.37167],"type":"Point"}
}