{
  "type": "Feature",
  "properties": {
    "addr:full": "305 Revere St Winthrop MA 02152",
    "addr:housenumber": "305",
    "addr:postcode": "02152",
    "addr:street": "Revere St",
    "iso:country": "US",
    "sg:address": "305 Revere St",
    "sg:city": "Winthrop",
    "sg:classifiers": [
      {
        "category": "Wholesale",
        "subcategory": "Sporting Goods",
        "type": "Manufacturing \u0026 Wholesale Goods"
      }
    ],
    "sg:phone": "+1 617 846 9555",
    "sg:postcode": "02152",
    "sg:province": "MA",
    "wof:name": "Promounds",
    "wof:placetype": "venue"
  },
  "geometry": {"coordinates":[-70.976813,42.387302],"type":"Point"}
}
