{
  "type": "Feature",
  "properties": {
    "addr:full": "148 Everett Avenue Chelsea MA 02150",
    "addr:housenumber": "148",
    "addr:postcode": "02150",
    "addr:street": "Everett Avenue",
    "iso:country": "US",
    "sg:address": "148 Everett Avenue",
    "sg:city": "Chelsea",
    "sg:classifiers": [
      {
        "category": "Banks \u0026 Credit Unions",
        "subcategory": "Bank",
        "type": "Services"
      }
    ],
    "sg:phone": "+1 877 768 2265",
    "sg:postcode": "02150",
    "sg:province": "MA",
    "sg:website": "www.sovereignbank.com",
    "wof:name": "Sovereign Bank",
    "wof:placetype": "venue"
  },
  "geometry": {"coordinates":[-71.03954,42.39526],"type":"Point"}
}
