{
  "type": "Feature",
  "properties": {
    "iso:country":"US",
    "sg:address":"173 Chestnut St",
    "sg:city":"East Longmeadow",
    "sg:classifiers":[
        {
            "category":"Professional",
            "subcategory":"Accounting & Tax Preparation",
            "type":"Services"
        }
    ],
    "sg:phone":"+1 413 525 9445",
    "sg:postcode":"01028",
    "sg:province":"MA",
    "sg:tags":[
        "billing"
    ],
    "wof:name":"PDQ Billing Svc",
    "wof:placetype":"venue"
},
  "geometry": {"coordinates":[-72.518407,42.053632],"type":"Point"}
}