{
  "type": "Feature",
  "properties": {
    "addr:full":"156 Milk St Ste 2 Boston MA 02109",
    "addr:housenumber":"156",
    "addr:postcode":"02109",
    "addr:street":"Milk St Ste 2",
    "iso:country":"US",
    "sg:address":"156 Milk St Ste 2",
    "sg:city":"Boston",
    "sg:classifiers":[
        {
            "category":"Landmark",
            "subcategory":"Historic",
            "type":"Public Place"
        },
        {
            "category":"Professional",
            "subcategory":"Employment Agencies",
            "type":"Services"
        }
    ],
    "sg:phone":"+1 617 426 9375",
    "sg:postcode":"02109",
    "sg:province":"MA",
    "sg:tags":[
        "historical",
        "employer"
    ],
    "wof:name":"Marshall Street Historical Society Inc",
    "wof:placetype":"venue"
},
  "geometry": {"coordinates":[-71.053247,42.358461],"type":"Point"}
}