{
  "type": "Feature",
  "properties": {
    "addr:full": "41 Cleveland St Springfield MA 01104",
    "addr:housenumber": "41",
    "addr:postcode": "01104",
    "addr:street": "Cleveland St",
    "iso:country": "US",
    "sg:address": "41 Cleveland St",
    "sg:city": "Springfield",
    "sg:classifiers": [
      {
        "category": "Home \u0026 Garden",
        "subcategory": "Home Furnishings",
        "type": "Retail Goods"
      }
    ],
    "sg:phone": "+1 413 737 5374",
    "sg:postcode": "01104",
    "sg:province": "MA",
    "sg:tags": [
      "window",
      "treatment"
    ],
    "wof:name": "Pioneer Shade \u0026 Awning",
    "wof:placetype": "venue"
  },
  "geometry": {"coordinates":[-72.585134,42.12246],"type":"Point"}
}
