{
  "type": "Feature",
  "properties": {
    "iso:country":"US",
    "sg:address":"100 Lowell St",
    "sg:city":"Peabody",
    "sg:classifiers":[
        {
            "category":"Professional",
            "subcategory":"Lawyer & Legal Services",
            "type":"Services"
        }
    ],
    "sg:phone":"+1 978 546 5131",
    "sg:postcode":"01960",
    "sg:province":"MA",
    "sg:tags":[
        "attorney"
    ],
    "wof:name":"Feinestein Affliates",
    "wof:placetype":"venue"
},
  "geometry": {"coordinates":[-70.93238599999999,42.527716],"type":"Point"}
}