{
  "type": "Feature",
  "properties": {
    "iso:country":"US",
    "sg:address":"205 Bedford St",
    "sg:city":"Whitman",
    "sg:classifiers":[
        {
            "category":"Retail",
            "subcategory":"Auto Repair",
            "type":"Services"
        }
    ],
    "sg:phone":"+1   ",
    "sg:postcode":"02382",
    "sg:province":"MA",
    "sg:tags":[
        "general"
    ],
    "wof:name":"Km Auto",
    "wof:placetype":"venue"
},
  "geometry": {"coordinates":[-70.94858600000001,42.067393],"type":"Point"}
}