{
  "type": "Feature",
  "properties": {
    "addr:full": "11 Jan Sebastian Dr Sandwich MA 02563",
    "addr:housenumber": "11",
    "addr:postcode": "02563",
    "addr:street": "Jan Sebastian Dr",
    "iso:country": "US",
    "sg:address": "11 Jan Sebastian Dr",
    "sg:city": "Sandwich",
    "sg:classifiers": [
      {
        "category": "Building \u0026 Trades",
        "subcategory": "Electrical",
        "type": "Services"
      }
    ],
    "sg:phone": "+1 508 888 5731",
    "sg:postcode": "02563",
    "sg:province": "MA",
    "sg:tags": [
      "electric",
      "contractor"
    ],
    "wof:name": "Shadan Electrical Contractors",
    "wof:placetype": "venue"
  },
  "geometry": {"coordinates":[-70.486014,41.718176],"type":"Point"}
}
