{
  "type": "Feature",
  "properties": {
    "addr:full": "123 Spring St Shrewsbury MA 01545",
    "addr:housenumber": "123",
    "addr:postcode": "01545",
    "addr:street": "Spring St",
    "iso:country": "US",
    "sg:address": "123 Spring St",
    "sg:city": "Shrewsbury",
    "sg:classifiers": [
      {
        "category": "Education",
        "subcategory": "School",
        "type": "Public Place"
      }
    ],
    "sg:phone": "+1   ",
    "sg:postcode": "01545",
    "sg:province": "MA",
    "wof:name": "Sg Street Elementary Sch",
    "wof:placetype": "venue"
  },
  "geometry": {"coordinates":[-71.701632,42.30368],"type":"Point"}
}
