{
  "type": "Feature",
  "properties": {
    "iso:country":"US",
    "sg:address":"148 Montague City Rd",
    "sg:city":"Greenfield",
    "sg:classifiers":[
        {
            "category":"Health Services",
            "subcategory":"Nursing And Care Facility",
            "type":"Services"
        }
    ],
    "sg:phone":"+1 413 773 8589",
    "sg:postcode":"01301",
    "sg:province":"MA",
    "sg:tags":[
        "home",
        "convalescent"
    ],
    "wof:name":"Pioneer Valley Manor Rest Home",
    "wof:placetype":"venue"
},
  "geometry": {"coordinates":[-72.579989,42.578404],"type":"Point"}
}