{
  "type": "Feature",
  "properties": {
    "addr:full":"22 Lonergan Rd Middleton MA 01949",
    "addr:housenumber":"22",
    "addr:postcode":"01949",
    "addr:street":"Lonergan Rd",
    "iso:country":"US",
    "sg:address":"22 Lonergan Rd",
    "sg:city":"Middleton",
    "sg:classifiers":[
        {
            "category":"Professional",
            "subcategory":"Management & Consulting",
            "type":"Services"
        }
    ],
    "sg:phone":"+1 978 646 0074",
    "sg:postcode":"01949",
    "sg:province":"MA",
    "sg:tags":[
        "business"
    ],
    "wof:name":"Wild Meadow Equipment Corp",
    "wof:placetype":"venue"
},
  "geometry": {"coordinates":[-70.99965400000001,42.569662],"type":"Point"}
}