{
  "type": "Feature",
  "properties": {
    "addr:full": "74 Willow St Lawrence MA 01841",
    "addr:housenumber": "74",
    "addr:postcode": "01841",
    "addr:street": "Willow St",
    "iso:country": "US",
    "sg:address": "74 Willow St",
    "sg:city": "Lawrence",
    "sg:classifiers": [
      {
        "category": "Retail",
        "subcategory": "Self-service Laundry",
        "type": "Services"
      }
    ],
    "sg:phone": "+1 978 688 4656",
    "sg:postcode": "01841",
    "sg:province": "MA",
    "wof:name": "Super Laundry Mat",
    "wof:placetype": "venue"
  },
  "geometry": {"coordinates":[-71.173043,42.71735],"type":"Point"}
}
