{
  "type": "Feature",
  "properties": {
    "iso:country":"US",
    "sg:address":"74 Willow St",
    "sg:city":"Lawrence",
    "sg:classifiers":[
        {
            "category":"Retail",
            "subcategory":"Self-service Laundry",
            "type":"Services"
        }
    ],
    "sg:phone":"+1 978 688 4656",
    "sg:postcode":"01841",
    "sg:province":"MA",
    "wof:name":"Super Laundry Mat",
    "wof:placetype":"venue"
},
  "geometry": {"coordinates":[-71.17304300000001,42.71735],"type":"Point"}
}