{
  "type": "Feature",
  "properties": {
    "iso:country":"US",
    "sg:address":"41 South St 1",
    "sg:city":"Westborough",
    "sg:classifiers":[
        {
            "category":"Building & Trades",
            "subcategory":"Landscaping Services",
            "type":"Services"
        }
    ],
    "sg:phone":"+1 508 366 4884",
    "sg:postcode":"01581",
    "sg:province":"MA",
    "sg:tags":[
        "lawn"
    ],
    "wof:name":"Four Seasons Landscaping",
    "wof:placetype":"venue"
},
  "geometry": {"coordinates":[-71.612297,42.268009],"type":"Point"}
}