{
  "type": "Feature",
  "properties": {
    "addr:full":"615 Main St West Springfield MA 01089",
    "addr:housenumber":"615",
    "addr:postcode":"01089",
    "addr:street":"Main St",
    "iso:country":"US",
    "sg:address":"615 Main St",
    "sg:city":"West Springfield",
    "sg:classifiers":[
        {
            "category":"Organizations",
            "subcategory":"Community Association",
            "type":"Services"
        }
    ],
    "sg:phone":"+1 413 736 1831",
    "sg:postcode":"01089",
    "sg:province":"MA",
    "sg:tags":[
        "club"
    ],
    "wof:name":"West Springfield Boys Club",
    "wof:placetype":"venue"
},
  "geometry": {"coordinates":[-72.608237,42.101681],"type":"Point"}
}