{
  "type": "Feature",
  "properties": {
    "iso:country":"US",
    "sg:address":"11 South Ave",
    "sg:city":"Natick",
    "sg:classifiers":[
        {
            "category":"Shopping",
            "subcategory":"Florist",
            "type":"Retail Goods"
        }
    ],
    "sg:phone":"+1 508 651 3931",
    "sg:postcode":"01760",
    "sg:province":"MA",
    "wof:name":"Flower Depot",
    "wof:placetype":"venue"
},
  "geometry": {"coordinates":[-71.347172,42.285278],"type":"Point"}
}