{
  "type": "Feature",
  "properties": {
    "iso:country":"US",
    "sg:address":"66 Winn St",
    "sg:city":"Burlington",
    "sg:classifiers":[
        {
            "category":"Retail",
            "subcategory":"Auto Repair",
            "type":"Services"
        }
    ],
    "sg:phone":"+1   ",
    "sg:postcode":"01803",
    "sg:province":"MA",
    "sg:tags":[
        "body"
    ],
    "wof:name":"Ironman Trailer Repair",
    "wof:placetype":"venue"
},
  "geometry": {"coordinates":[-71.176391,42.493639],"type":"Point"}
}