{
  "type": "Feature",
  "properties": {
    "iso:country":"US",
    "sg:address":"85 Eastern Ave",
    "sg:city":"Gloucester",
    "sg:classifiers":[
        {
            "category":"Health Services",
            "subcategory":"Chiropractor",
            "type":"Services"
        }
    ],
    "sg:phone":"+1 978 282 4994",
    "sg:postcode":"01930",
    "sg:province":"MA",
    "sg:tags":[
        "chiropractic"
    ],
    "wof:name":"Atlantic Family Chiropractic PC",
    "wof:placetype":"venue"
},
  "geometry": {"coordinates":[-70.645326,42.621136],"type":"Point"}
}