{
  "type": "Feature",
  "properties": {
    "iso:country":"US",
    "sg:address":"365 W Main St",
    "sg:city":"Hyannis",
    "sg:classifiers":[
        {
            "category":"Autos & Motor Vehicles",
            "subcategory":"Automobile Sales",
            "type":"Retail Goods"
        }
    ],
    "sg:phone":"+1 508 280 7945",
    "sg:postcode":"02601",
    "sg:province":"MA",
    "sg:tags":[
        "car",
        "dealer"
    ],
    "wof:name":"Automotive Resources",
    "wof:placetype":"venue"
},
  "geometry": {"coordinates":[-70.310163,41.64873],"type":"Point"}
}