{
  "type": "Feature",
  "properties": {
    "addr:full": "41 Top Hill Ave Dedham MA 02026",
    "addr:housenumber": "41",
    "addr:postcode": "02026",
    "addr:street": "Top Hill Ave",
    "iso:country": "US",
    "sg:address": "41 Top Hill Ave",
    "sg:city": "Dedham",
    "sg:classifiers": [
      {
        "category": "Real Estate",
        "subcategory": "Real Estate Agent",
        "type": "Services"
      }
    ],
    "sg:phone": "+1   ",
    "sg:postcode": "02026",
    "sg:province": "MA",
    "sg:tags": [
      "appraisal"
    ],
    "wof:name": "Peckham Appraisals Services",
    "wof:placetype": "venue"
  },
  "geometry": {"coordinates":[-71.158912,42.231098],"type":"Point"}
}
