{
  "type": "Feature",
  "properties": {
    "addr:full": "30 Clyde St Needham MA 02492",
    "addr:housenumber": "30",
    "addr:postcode": "02492",
    "addr:street": "Clyde St",
    "iso:country": "US",
    "sg:address": "30 Clyde St",
    "sg:city": "Needham",
    "sg:classifiers": [
      {
        "category": "Professional",
        "subcategory": "Management \u0026 Consulting",
        "type": "Services"
      }
    ],
    "sg:phone": "+1   ",
    "sg:postcode": "02492",
    "sg:province": "MA",
    "sg:tags": [
      "business"
    ],
    "wof:name": "Feinberg Consulting",
    "wof:placetype": "venue"
  },
  "geometry": {"coordinates":[-71.238375,42.275234],"type":"Point"}
}
