{
  "type": "Feature",
  "properties": {
    "iso:country":"US",
    "sg:address":"69 N Common St",
    "sg:city":"Lynn",
    "sg:classifiers":[
        {
            "category":"Real Estate",
            "subcategory":"Real Estate Operator",
            "type":"Services"
        }
    ],
    "sg:phone":"+1 781 599 8386",
    "sg:postcode":"01902",
    "sg:province":"MA",
    "sg:tags":[
        "boarding",
        "house"
    ],
    "wof:name":"Kensington House",
    "wof:placetype":"venue"
},
  "geometry": {"coordinates":[-70.956188,42.463726],"type":"Point"}
}