{
  "type": "Feature",
  "properties": {
    "iso:country":"US",
    "sg:address":"194 Central St",
    "sg:city":"Saugus",
    "sg:classifiers":[
        {
            "category":"Health Services",
            "subcategory":"Health Practitioner",
            "type":"Services"
        }
    ],
    "sg:phone":"+1 781 231 3475",
    "sg:postcode":"01906",
    "sg:province":"MA",
    "sg:tags":[
        "therapist",
        "physical"
    ],
    "wof:name":"Saugus Physical Therapy",
    "wof:placetype":"venue"
},
  "geometry": {"coordinates":[-71.007756,42.471488],"type":"Point"}
}