{
  "type": "Feature",
  "properties": {
    "addr:full": "27 Eagle Hill Dr Plymouth MA 02360",
    "addr:housenumber": "27",
    "addr:postcode": "02360",
    "addr:street": "Eagle Hill Dr",
    "iso:country": "US",
    "sg:address": "27 Eagle Hill Dr",
    "sg:city": "Plymouth",
    "sg:classifiers": [
      {
        "category": "Building \u0026 Trades",
        "subcategory": "Construction",
        "type": "Services"
      }
    ],
    "sg:phone": "+1 508 888 0354",
    "sg:postcode": "02360",
    "sg:province": "MA",
    "sg:tags": [
      "home",
      "improvement"
    ],
    "wof:name": "Winship \u0026 Sons Construction Co",
    "wof:placetype": "venue"
  },
  "geometry": {"coordinates":[-70.56201,41.802303],"type":"Point"}
}
