{
  "type": "Feature",
  "properties": {
    "iso:country":"US",
    "sg:address":"124 Mount Auburn St",
    "sg:city":"Cambridge",
    "sg:classifiers":[
        {
            "category":"Building & Trades",
            "subcategory":"Locksmith",
            "type":"Services"
        }
    ],
    "sg:phone":"+1 617 895 3653",
    "sg:postcode":"02138",
    "sg:province":"MA",
    "sg:tags":[
        "key"
    ],
    "wof:name":"All Day Emergency A Locksmith",
    "wof:placetype":"venue"
},
  "geometry": {"coordinates":[-71.12347,42.373403],"type":"Point"}
}