{
  "type": "Feature",
  "properties": {
    "iso:country":"US",
    "sg:address":"314 Somerset Ave",
    "sg:city":"Taunton",
    "sg:classifiers":[
        {
            "category":"Social Services",
            "type":"Services"
        }
    ],
    "sg:phone":"+1 508 822 6524",
    "sg:postcode":"02780",
    "sg:province":"MA",
    "sg:tags":[
        "counseling"
    ],
    "wof:name":"Community Counseling-Bristol",
    "wof:placetype":"venue"
},
  "geometry": {"coordinates":[-71.093622,41.887677],"type":"Point"}
}