{
  "type": "Feature",
  "properties": {
    "addr:full": "1485 N Shore Rd Revere MA 02151",
    "addr:housenumber": "1485",
    "addr:postcode": "02151",
    "addr:street": "N Shore Rd",
    "iso:country": "US",
    "sg:address": "1485 N Shore Rd",
    "sg:city": "Revere",
    "sg:classifiers": [
      {
        "category": "Deli",
        "type": "Food \u0026 Drink"
      },
      {
        "category": "Restaurant",
        "type": "Food \u0026 Drink"
      }
    ],
    "sg:menulink": "http://www.allmenus.com/ma/revere/229493-peters-super-beef/menu/",
    "sg:phone": "+1 781 286 5610",
    "sg:postcode": "02151",
    "sg:province": "MA",
    "sg:tags": [
      "deli",
      "american"
    ],
    "wof:name": "Peter's Super Beef",
    "wof:placetype": "venue"
  },
  "geometry": {"coordinates":[-70.993499,42.408759],"type":"Point"}
}
