{
  "type": "Feature",
  "properties": {
    "addr:full": "25 West St Fl 4 Boston MA 02111",
    "addr:housenumber": "25;4",
    "addr:postcode": "02111",
    "addr:street": "West St",
    "iso:country": "US",
    "sg:address": "25 West St Fl 4",
    "sg:city": "Boston",
    "sg:classifiers": [
      {
        "category": "Building \u0026 Trades",
        "subcategory": "Landscaping Services",
        "type": "Services"
      }
    ],
    "sg:phone": "+1 617 457 8142",
    "sg:postcode": "02111",
    "sg:province": "MA",
    "sg:tags": [
      "aged",
      "homes-institutional"
    ],
    "wof:name": "Assisted Living Program",
    "wof:placetype": "venue"
  },
  "geometry": {"coordinates":[-71.062397,42.354686],"type":"Point"}
}
