{
  "type": "Feature",
  "properties": {
    "addr:full":"927 Millbury St Worcester MA 01607",
    "addr:housenumber":"927",
    "addr:postcode":"01607",
    "addr:street":"Millbury St",
    "iso:country":"US",
    "sg:address":"927 Millbury St",
    "sg:city":"Worcester",
    "sg:classifiers":[
        {
            "category":"Retail",
            "subcategory":"Auto Repair",
            "type":"Services"
        }
    ],
    "sg:phone":"+1 508 791 1155",
    "sg:postcode":"01607",
    "sg:province":"MA",
    "sg:tags":[
        "repairing",
        "automobile"
    ],
    "wof:name":"K D Automotive",
    "wof:placetype":"venue"
},
  "geometry": {"coordinates":[-71.79172699999999,42.230541],"type":"Point"}
}