{
  "type": "Feature",
  "properties": {
    "addr:full":"619 Essex St Lawrence MA 01840",
    "addr:housenumber":"619",
    "addr:postcode":"01840",
    "addr:street":"Essex St",
    "iso:country":"US",
    "sg:address":"619 Essex St",
    "sg:city":"Lawrence",
    "sg:classifiers":[
        {
            "category":"Home & Garden",
            "subcategory":"Carpets & Floor Coverings",
            "type":"Retail Goods"
        }
    ],
    "sg:phone":"+1 978 688 7142",
    "sg:postcode":"01840",
    "sg:province":"MA",
    "sg:tags":[
        "dealer",
        "rug"
    ],
    "wof:name":"Arrow Floor Carpet One",
    "wof:placetype":"venue"
},
  "geometry": {"coordinates":[-71.168161,42.70481],"type":"Point"}
}