{
  "type": "Feature",
  "properties": {
    "addr:full": "4 Paine St Winthrop MA 02152",
    "addr:housenumber": "4",
    "addr:postcode": "02152",
    "addr:street": "Paine St",
    "iso:country": "US",
    "sg:address": "4 Paine St",
    "sg:city": "Winthrop",
    "sg:classifiers": [
      {
        "category": "Organizations",
        "subcategory": "Labor Organization",
        "type": "Services"
      }
    ],
    "sg:phone": "+1   ",
    "sg:postcode": "02152",
    "sg:province": "MA",
    "wof:name": "Local 1066",
    "wof:placetype": "venue"
  },
  "geometry": {"coordinates":[-70.983297,42.381765],"type":"Point"}
}
