{
  "type": "Feature",
  "properties": {
    "addr:full": "1530 Pleasant St Fall River MA 02723",
    "addr:housenumber": "1530",
    "addr:postcode": "02723",
    "addr:street": "Pleasant St",
    "iso:country": "US",
    "sg:address": "1530 Pleasant St",
    "sg:city": "Fall River",
    "sg:classifiers": [
      {
        "category": "Personal",
        "subcategory": "Barber",
        "type": "Services"
      }
    ],
    "sg:phone": "+1   ",
    "sg:postcode": "02723",
    "sg:province": "MA",
    "sg:tags": [
      "shop"
    ],
    "wof:name": "Teixeiras Bill Barber Shop",
    "wof:placetype": "venue"
  },
  "geometry": {"coordinates":[-71.132505,41.689278],"type":"Point"}
}
