{
  "type": "Feature",
  "properties": {
    "addr:full":"11 Peter Rd Weymouth MA 02191",
    "addr:housenumber":"11",
    "addr:postcode":"02191",
    "addr:street":"Peter Rd",
    "iso:country":"US",
    "sg:address":"11 Peter Rd",
    "sg:city":"Weymouth",
    "sg:phone":"+1 781 337 0800",
    "sg:postcode":"02191",
    "sg:province":"MA",
    "sg:tags":[
        "oil"
    ],
    "wof:name":"Weymouth Burner Svc Inc",
    "wof:placetype":"venue"
},
  "geometry": {"coordinates":[-70.938895,42.232464],"type":"Point"}
}