{
  "type": "Feature",
  "properties": {
    "addr:full": "99 Walnut St Saugus MA 01906",
    "addr:housenumber": "99",
    "addr:postcode": "01906",
    "addr:street": "Walnut St",
    "iso:country": "US",
    "sg:address": "99 Walnut St",
    "sg:city": "Saugus",
    "sg:classifiers": [
      {
        "category": "Professional",
        "subcategory": "Lawyer \u0026 Legal Services",
        "type": "Services"
      }
    ],
    "sg:phone": "+1 781 231 4900",
    "sg:postcode": "01906",
    "sg:province": "MA",
    "sg:tags": [
      "attorney"
    ],
    "wof:name": "Colonna \u0026 Doyle Law Offices",
    "wof:placetype": "venue"
  },
  "geometry": {"coordinates":[-71.020229,42.494861],"type":"Point"}
}
