{
  "type": "Feature",
  "properties": {
    "addr:full":"31 North St Blandford MA 01008",
    "addr:housenumber":"31",
    "addr:postcode":"01008",
    "addr:street":"North St",
    "iso:country":"US",
    "sg:address":"31 North St",
    "sg:city":"Blandford",
    "sg:classifiers":[
        {
            "category":"Manufacturing",
            "subcategory":"Buildings",
            "type":"Manufacturing & Wholesale Goods"
        },
        {
            "category":"Building & Trades",
            "subcategory":"Construction",
            "type":"Services"
        }
    ],
    "sg:phone":"+1 413 848 2752",
    "sg:postcode":"01008",
    "sg:province":"MA",
    "sg:tags":[
        "home",
        "builder",
        "contractor"
    ],
    "wof:name":"Zayac Builders Inc",
    "wof:placetype":"venue"
},
  "geometry": {"coordinates":[-73.035999,42.159759],"type":"Point"}
}