{
  "type": "Feature",
  "properties": {
    "iso:country":"US",
    "sg:address":"6 W Lynde St",
    "sg:city":"Gardner",
    "sg:classifiers":[
        {
            "category":"Retail",
            "subcategory":"Repair Shop",
            "type":"Services"
        },
        {
            "category":"Shopping",
            "subcategory":"Jewelry",
            "type":"Retail Goods"
        }
    ],
    "sg:phone":"+1 978 632 5715",
    "sg:postcode":"01440",
    "sg:province":"MA",
    "sg:tags":[
        "jeweler"
    ],
    "wof:name":"Bruce's Watch & Jewelry",
    "wof:placetype":"venue"
},
  "geometry": {"coordinates":[-71.99453099999999,42.57612],"type":"Point"}
}