{
  "type": "Feature",
  "properties": {
    "addr:full": "6 W Lynde St Gardner MA 01440",
    "addr:housenumber": "6",
    "addr:postcode": "01440",
    "addr:street": "W Lynde St",
    "iso:country": "US",
    "ovtr:label": "Bruce's Watch \u0026 Jewelry, 6 W Lynde St Gardner MA US",
    "ovtr:similarity": 2.2513060569763184,
    "sg:address": "6 W Lynde St",
    "sg:city": "Gardner",
    "sg:classifiers": [
      {
        "category": "Retail",
        "subcategory": "Repair Shop",
        "type": "Services"
      },
      {
        "category": "Shopping",
        "subcategory": "Jewelry",
        "type": "Retail Goods"
      }
    ],
    "sg:phone": "+1 978 632 5715",
    "sg:postcode": "01440",
    "sg:province": "MA",
    "sg:tags": [
      "jeweler"
    ],
    "wof:name": "Bruce's Watch \u0026 Jewelry",
    "wof:placetype": "venue"
  },
  "geometry": {"coordinates":[-71.994531,42.57612],"type":"Point"}
}
