{
  "type": "Feature",
  "properties": {
    "addr:full": "261 Union St New Bedford MA 02740",
    "addr:housenumber": "261",
    "addr:postcode": "02740",
    "addr:street": "Union St",
    "iso:country": "US",
    "sg:address": "261 Union St",
    "sg:city": "New Bedford",
    "sg:classifiers": [
      {
        "category": "Professional",
        "subcategory": "Lawyer \u0026 Legal Services",
        "type": "Services"
      }
    ],
    "sg:phone": "+1   ",
    "sg:postcode": "02740",
    "sg:province": "MA",
    "wof:name": "Jane F Warren",
    "wof:placetype": "venue"
  },
  "geometry": {"coordinates":[-70.928025,41.634107],"type":"Point"}
}
