{
  "type": "Feature",
  "properties": {
    "addr:full": "Brickbottom Artist Building 1 Fitchburg Street B453 Somerville MA 02143",
    "addr:postcode": "02143",
    "addr:street": "Fitchburg Street",
    "iso:country": "US",
    "sg:address": "Brickbottom Artist Building 1 Fitchburg Street B453",
    "sg:city": "Somerville",
    "sg:classifiers": [
      {
        "category": "Arts \u0026 Performance",
        "subcategory": "Arts Center",
        "type": "Entertainment"
      },
      {
        "category": "Professional",
        "type": "Services"
      }
    ],
    "sg:phone": "+1 617 625 1991",
    "sg:postcode": "02143",
    "sg:province": "MA",
    "sg:tags": [
      "planning",
      "performing",
      "event"
    ],
    "sg:website": "www.hippocketorchestra.com",
    "wof:name": "Hip Pocket Orchestra",
    "wof:placetype": "venue"
  },
  "geometry": {"coordinates":[-71.085084,42.375515],"type":"Point"}
}
