{
  "type": "Feature",
  "properties": {
    "iso:country":"US",
    "sg:address":"Brickbottom Artist Building 1 Fitchburg Street B453",
    "sg:city":"Somerville",
    "sg:classifiers":[
        {
            "category":"Arts & Performance",
            "subcategory":"Arts Center",
            "type":"Entertainment"
        },
        {
            "category":"Professional",
            "type":"Services"
        }
    ],
    "sg:phone":"+1 617 625 1991",
    "sg:postcode":"02143",
    "sg:province":"MA",
    "sg:tags":[
        "planning",
        "performing",
        "event"
    ],
    "sg:website":"www.hippocketorchestra.com",
    "wof:name":"Hip Pocket Orchestra",
    "wof:placetype":"venue"
},
  "geometry": {"coordinates":[-71.08508399999999,42.375515],"type":"Point"}
}