{
  "type": "Feature",
  "properties": {
    "addr:full": "522 Pinewood Dr Longmeadow MA 01106",
    "addr:housenumber": "522",
    "addr:postcode": "01106",
    "addr:street": "Pinewood Dr",
    "iso:country": "US",
    "sg:address": "522 Pinewood Dr",
    "sg:city": "Longmeadow",
    "sg:classifiers": [
      {
        "category": "Real Estate",
        "subcategory": "Real Estate Agent",
        "type": "Services"
      }
    ],
    "sg:phone": "+1 413 567 2183",
    "sg:postcode": "01106",
    "sg:province": "MA",
    "wof:name": "Max Winkler Business Line",
    "wof:placetype": "venue"
  },
  "geometry": {"coordinates":[-72.552208,42.057772],"type":"Point"}
}
