{
  "type": "Feature",
  "properties": {
    "iso:country":"US",
    "sg:address":"77 Pond Ave",
    "sg:city":"Brookline",
    "sg:classifiers":[
        {
            "category":"Professional",
            "subcategory":"Management & Consulting",
            "type":"Services"
        }
    ],
    "sg:phone":"+1   ",
    "sg:postcode":"02445",
    "sg:province":"MA",
    "sg:tags":[
        "organizational",
        "development"
    ],
    "wof:name":"Mit Group",
    "wof:placetype":"venue"
},
  "geometry": {"coordinates":[-71.114839,42.330187],"type":"Point"}
}