{
  "type": "Feature",
  "properties": {
    "addr:full": "98 Union St Norfolk MA 02056",
    "addr:housenumber": "98",
    "addr:postcode": "02056",
    "addr:street": "Union St",
    "iso:country": "US",
    "sg:address": "98 Union St",
    "sg:city": "Norfolk",
    "sg:classifiers": [
      {
        "category": "Home \u0026 Garden",
        "subcategory": "Household Appliances",
        "type": "Retail Goods"
      }
    ],
    "sg:phone": "+1 508 528 8359",
    "sg:postcode": "02056",
    "sg:province": "MA",
    "wof:name": "Burow Appliance Svc",
    "wof:placetype": "venue"
  },
  "geometry": {"coordinates":[-71.328674,42.106803],"type":"Point"}
}
