{
  "type": "Feature",
  "properties": {
    "iso:country":"US",
    "sg:address":"98 Union St",
    "sg:city":"Norfolk",
    "sg:classifiers":[
        {
            "category":"Home & Garden",
            "subcategory":"Household Appliances",
            "type":"Retail Goods"
        }
    ],
    "sg:phone":"+1 508 528 8359",
    "sg:postcode":"02056",
    "sg:province":"MA",
    "wof:name":"Burow Appliance Svc",
    "wof:placetype":"venue"
},
  "geometry": {"coordinates":[-71.32867400000001,42.106803],"type":"Point"}
}