{
  "type": "Feature",
  "properties": {
    "addr:full": "43 Tremont St Taunton MA 02780",
    "addr:housenumber": "43",
    "addr:postcode": "02780",
    "addr:street": "Tremont St",
    "iso:country": "US",
    "sg:address": "43 Tremont St",
    "sg:city": "Taunton",
    "sg:classifiers": [
      {
        "category": "Food \u0026 Beverages",
        "subcategory": "Liquor \u0026 Beverages",
        "type": "Retail Goods"
      }
    ],
    "sg:phone": "+1 508 823 3541",
    "sg:postcode": "02780",
    "sg:province": "MA",
    "wof:name": "Tremont St Package Store",
    "wof:placetype": "venue"
  },
  "geometry": {"coordinates":[-71.104504,41.904728],"type":"Point"}
}
