{
  "type": "Feature",
  "properties": {
    "iso:country":"US",
    "sg:address":"43 Tremont St",
    "sg:city":"Taunton",
    "sg:classifiers":[
        {
            "category":"Food & Beverages",
            "subcategory":"Liquor & Beverages",
            "type":"Retail Goods"
        }
    ],
    "sg:phone":"+1 508 823 3541",
    "sg:postcode":"02780",
    "sg:province":"MA",
    "wof:name":"Tremont St Package Store",
    "wof:placetype":"venue"
},
  "geometry": {"coordinates":[-71.10450400000001,41.904728],"type":"Point"}
}