{
  "type": "Feature",
  "properties": {
    "addr:full":"457 Rantoul St Beverly MA 01915",
    "addr:housenumber":"457",
    "addr:postcode":"01915",
    "addr:street":"Rantoul St",
    "iso:country":"US",
    "sg:address":"457 Rantoul St",
    "sg:city":"Beverly",
    "sg:classifiers":[
        {
            "category":"Shopping",
            "subcategory":"Musical Instruments",
            "type":"Retail Goods"
        }
    ],
    "sg:phone":"+1 978 922 0200",
    "sg:postcode":"01915",
    "sg:province":"MA",
    "sg:tags":[
        "drum"
    ],
    "wof:name":"Joe's Drum Shop",
    "wof:placetype":"venue"
},
  "geometry": {"coordinates":[-70.88127900000001,42.555044],"type":"Point"}
}