{
  "type": "Feature",
  "properties": {
    "addr:full":"91 S Broadway Lawrence MA 01843",
    "addr:housenumber":"91",
    "addr:postcode":"01843",
    "addr:street":"S Broadway",
    "iso:country":"US",
    "sg:address":"91 S Broadway",
    "sg:city":"Lawrence",
    "sg:classifiers":[
        {
            "category":"Wholesale",
            "subcategory":"Office Equipment",
            "type":"Manufacturing & Wholesale Goods"
        }
    ],
    "sg:phone":"+1 978 688 7600",
    "sg:postcode":"01843",
    "sg:province":"MA",
    "sg:tags":[
        "machine",
        "duplicating",
        "copying"
    ],
    "wof:name":"Mac Donald Office Equipment",
    "wof:placetype":"venue"
},
  "geometry": {"coordinates":[-71.163526,42.697263],"type":"Point"}
}