{
  "type": "Feature",
  "properties": {
    "iso:country":"US",
    "sg:address":"495 Washington St",
    "sg:city":"Weymouth",
    "sg:classifiers":[
        {
            "category":"Retail",
            "subcategory":"Auto Rental",
            "type":"Services"
        }
    ],
    "sg:phone":"+1 781 331 0175",
    "sg:postcode":"02188",
    "sg:province":"MA",
    "sg:tags":[
        "renting",
        "automobile"
    ],
    "sg:website":"www.hertz.com",
    "wof:name":"Hertz Rent A Car",
    "wof:placetype":"venue"
},
  "geometry": {"coordinates":[-70.957841,42.208457],"type":"Point"}
}