{
  "type": "Feature",
  "properties": {
    "addr:full": "698 Broadway Chelsea MA 02150",
    "addr:housenumber": "698",
    "addr:postcode": "02150",
    "addr:street": "Broadway",
    "iso:country": "US",
    "sg:address": "698 Broadway",
    "sg:city": "Chelsea",
    "sg:classifiers": [
      {
        "category": "Food \u0026 Beverages",
        "subcategory": "Groceries \u0026 Convenience Stores",
        "type": "Retail Goods"
      }
    ],
    "sg:phone": "+1 617 884 2222",
    "sg:postcode": "02150",
    "sg:province": "MA",
    "wof:name": "Nunu Variety Store",
    "wof:placetype": "venue"
  },
  "geometry": {"coordinates":[-71.028586,42.395762],"type":"Point"}
}
