{
  "type": "Feature",
  "properties": {
    "iso:country":"US",
    "sg:address":"698 Broadway",
    "sg:city":"Chelsea",
    "sg:classifiers":[
        {
            "category":"Food & Beverages",
            "subcategory":"Groceries & Convenience Stores",
            "type":"Retail Goods"
        }
    ],
    "sg:phone":"+1 617 884 2222",
    "sg:postcode":"02150",
    "sg:province":"MA",
    "wof:name":"Nunu Variety Store",
    "wof:placetype":"venue"
},
  "geometry": {"coordinates":[-71.028586,42.395762],"type":"Point"}
}