{
  "type": "Feature",
  "properties": {
    "iso:country":"US",
    "sg:address":"175 W Main St",
    "sg:city":"Millbury",
    "sg:classifiers":[
        {
            "category":"Building & Trades",
            "subcategory":"Plumbing",
            "type":"Services"
        }
    ],
    "sg:phone":"+1 508 581 8907",
    "sg:postcode":"01527",
    "sg:province":"MA",
    "sg:tags":[
        "plumbing",
        "contractor"
    ],
    "wof:name":"Chuck Laverty Plumbing & Htg",
    "wof:placetype":"venue"
},
  "geometry": {"coordinates":[-71.77965,42.172366],"type":"Point"}
}