{
  "type": "Feature",
  "properties": {
    "iso:country":"US",
    "sg:address":"231 Alewife Brook Pkwy",
    "sg:city":"Cambridge",
    "sg:classifiers":[
        {
            "category":"Restaurant",
            "type":"Food & Drink"
        }
    ],
    "sg:phone":"+1 617 661 8200",
    "sg:postcode":"02138",
    "sg:province":"MA",
    "sg:tags":[
        "sushi",
        "bar",
        "japanese"
    ],
    "sg:website":"www.genkiyasushi.com",
    "wof:name":"Genki Ya",
    "wof:placetype":"venue"
},
  "geometry": {"coordinates":[-71.142796,42.387907],"type":"Point"}
}