{
  "type": "Feature",
  "properties": {
    "iso:country":"US",
    "sg:address":"710 Albany Street",
    "sg:city":"Boston",
    "sg:classifiers":[
        {
            "category":"Banks & Credit Unions",
            "subcategory":"Financial Services",
            "type":"Services"
        }
    ],
    "sg:phone":"+1 617 638 1900",
    "sg:postcode":"02118",
    "sg:province":"MA",
    "sg:website":"www.universitycu.org",
    "wof:name":"University Credit Union",
    "wof:placetype":"venue"
},
  "geometry": {"coordinates":[-71.068237,42.337232],"type":"Point"}
}