{
  "type": "Feature",
  "properties": {
    "iso:country":"US",
    "sg:address":"261 Little River Rd",
    "sg:city":"Westfield",
    "sg:classifiers":[
        {
            "category":"Professional",
            "type":"Services"
        }
    ],
    "sg:phone":"+1 413 564 5200",
    "sg:postcode":"01085",
    "sg:province":"MA",
    "sg:tags":[
        "arranger",
        "music",
        "composer"
    ],
    "wof:name":"Advertus Media",
    "wof:placetype":"venue"
},
  "geometry": {"coordinates":[-72.71819000000001,42.106337],"type":"Point"}
}