{
  "type": "Feature",
  "properties": {
    "iso:country":"US",
    "sg:address":"26 Keri-Anne Dr",
    "sg:city":"Brockton",
    "sg:classifiers":[
        {
            "category":"Professional",
            "subcategory":"Computer Services",
            "type":"Services"
        }
    ],
    "sg:phone":"+1 508 583 5428",
    "sg:postcode":"02302",
    "sg:province":"MA",
    "sg:tags":[
        "repair"
    ],
    "wof:name":"AC T Technician",
    "wof:placetype":"venue"
},
  "geometry": {"coordinates":[-70.99250000000001,42.062856],"type":"Point"}
}