{
  "type": "Feature",
  "properties": {
    "iso:country":"US",
    "sg:address":"130 Tremont St",
    "sg:city":"Melrose",
    "sg:phone":"+1 781 665 1714",
    "sg:postcode":"02176",
    "sg:province":"MA",
    "sg:tags":[
        "oil"
    ],
    "wof:name":"Knight-Harrison Fuels",
    "wof:placetype":"venue"
},
  "geometry": {"coordinates":[-71.06971299999999,42.462827],"type":"Point"}
}