{
  "type": "Feature",
  "properties": {
    "addr:full":"33 Esty St Ashland MA 01721",
    "addr:housenumber":"33",
    "addr:postcode":"01721",
    "addr:street":"Esty St",
    "iso:country":"US",
    "sg:address":"33 Esty St",
    "sg:city":"Ashland",
    "sg:classifiers":[
        {
            "category":"Professional",
            "subcategory":"Research",
            "type":"Services"
        }
    ],
    "sg:phone":"+1   ",
    "sg:postcode":"01721",
    "sg:province":"MA",
    "sg:tags":[
        "medical"
    ],
    "wof:name":"Eric Lammi",
    "wof:placetype":"venue"
},
  "geometry": {"coordinates":[-71.463532,42.25717],"type":"Point"}
}