{
  "type": "Feature",
  "properties": {
    "addr:full": "6 Federal Way Groveland MA 01834",
    "addr:housenumber": "6",
    "addr:postcode": "01834",
    "addr:street": "Federal",
    "iso:country": "US",
    "sg:address": "6 Federal Way",
    "sg:city": "Groveland",
    "sg:classifiers": [
      {
        "category": "Manufacturing",
        "subcategory": "Aerospace",
        "type": "Manufacturing \u0026 Wholesale Goods"
      }
    ],
    "sg:phone": "+1 978 521 5100",
    "sg:postcode": "01834",
    "sg:province": "MA",
    "sg:tags": [
      "aircraft",
      "component"
    ],
    "wof:name": "Union Machine Co",
    "wof:placetype": "venue"
  },
  "geometry": {"coordinates":[-71.013061,42.734816],"type":"Point"}
}
