{
  "type": "Feature",
  "properties": {
    "iso:country":"US",
    "sg:address":"74 Loomis St",
    "sg:city":"Bedford",
    "sg:classifiers":[
        {
            "category":"Health Services",
            "subcategory":"Doctor",
            "type":"Services"
        }
    ],
    "sg:phone":"+1 781 674 2900",
    "sg:postcode":"01730",
    "sg:province":"MA",
    "wof:name":"Geller David",
    "wof:placetype":"venue"
},
  "geometry": {"coordinates":[-71.275803,42.487099],"type":"Point"}
}