{
  "type": "Feature",
  "properties": {
    "addr:full": "378 Maple St Holyoke MA 01040",
    "addr:housenumber": "378",
    "addr:postcode": "01040",
    "addr:street": "Maple St",
    "iso:country": "US",
    "ovtr:label": "Congregation Sons of Zion, 378 Maple St Holyoke MA US",
    "ovtr:similarity": 2.0431768894195557,
    "sg:address": "378 Maple St",
    "sg:city": "Holyoke",
    "sg:classifiers": [
      {
        "category": "Organizations",
        "subcategory": "Religious Organization",
        "type": "Services"
      }
    ],
    "sg:phone": "+1 413 534 3369",
    "sg:postcode": "01040",
    "sg:province": "MA",
    "sg:tags": [
      "synagogue"
    ],
    "wof:name": "Congregation Sons Of Zion",
    "wof:placetype": "venue"
  },
  "geometry": {"coordinates":[-72.61165,42.204215],"type":"Point"}
}
