{
  "type": "Feature",
  "properties": {
    "addr:full":"800 Lexington St Waltham MA 02452",
    "addr:housenumber":"800",
    "addr:postcode":"02452",
    "addr:street":"Lexington St",
    "iso:country":"US",
    "sg:address":"800 Lexington St",
    "sg:city":"Waltham",
    "sg:classifiers":[
        {
            "category":"Shopping",
            "subcategory":"Computers & Home Electronics",
            "type":"Retail Goods"
        },
        {
            "category":"Wholesale",
            "subcategory":"Office Equipment",
            "type":"Manufacturing & Wholesale Goods"
        },
        {
            "category":"Professional",
            "subcategory":"Printing & Photocopies",
            "type":"Services"
        },
        {
            "category":"Professional",
            "subcategory":"Computer Services",
            "type":"Services"
        },
        {
            "category":"Shopping",
            "subcategory":"Stationery & Office Supplies",
            "type":"Retail Goods"
        },
        {
            "category":"Wholesale",
            "subcategory":"Computers",
            "type":"Manufacturing & Wholesale Goods"
        }
    ],
    "sg:phone":"+1 781 899 4943",
    "sg:postcode":"02452",
    "sg:province":"MA",
    "sg:tags":[
        "printer",
        "register",
        "autographic",
        "duplicating",
        "hardware",
        "copying",
        "software",
        "furniture"
    ],
    "sg:website":"http://www.staples.com/",
    "wof:name":"Staples",
    "wof:placetype":"venue"
},
  "geometry": {"coordinates":[-71.234047,42.402111],"type":"Point"}
}