{
  "type": "Feature",
  "properties": {
    "iso:country":"US",
    "sg:address":"5 Ross Street",
    "sg:city":"Medford",
    "sg:classifiers":[
        {
            "category":"Sports & Exercise",
            "subcategory":"Gym",
            "type":"Entertainment"
        }
    ],
    "sg:phone":"+1 781 393 8144",
    "sg:postcode":"02155",
    "sg:province":"MA",
    "sg:tags":[
        "trainer"
    ],
    "wof:name":"Chenaille Compliance Consulting",
    "wof:placetype":"venue"
},
  "geometry": {"coordinates":[-71.093727,42.412287],"type":"Point"}
}