{
  "type": "Feature",
  "properties": {
    "iso:country":"US",
    "sg:address":"25 Woodhaven Dr",
    "sg:city":"Belchertown",
    "sg:classifiers":[
        {
            "category":"Building & Trades",
            "subcategory":"Electrical",
            "type":"Services"
        }
    ],
    "sg:phone":"+1 413 323 6223",
    "sg:postcode":"01007",
    "sg:province":"MA",
    "sg:tags":[
        "electric",
        "contractor"
    ],
    "wof:name":"Scharff Electric",
    "wof:placetype":"venue"
},
  "geometry": {"coordinates":[-72.402872,42.284487],"type":"Point"}
}