{
  "type": "Feature",
  "properties": {
    "addr:full":"438 Main St Waltham MA 02452",
    "addr:housenumber":"438",
    "addr:postcode":"02452",
    "addr:street":"Main St",
    "iso:country":"US",
    "sg:address":"438 Main St",
    "sg:city":"Waltham",
    "sg:classifiers":[
        {
            "category":"Professional",
            "subcategory":"Accounting & Tax Preparation",
            "type":"Services"
        }
    ],
    "sg:phone":"+1 781 398 0798",
    "sg:postcode":"02452",
    "sg:province":"MA",
    "sg:tags":[
        "accountant"
    ],
    "wof:name":"Mcclary Loretta CPA",
    "wof:placetype":"venue"
},
  "geometry": {"coordinates":[-71.226333,42.377632],"type":"Point"}
}