{
  "type": "Feature",
  "properties": {
    "iso:country":"US",
    "sg:address":"161 Cranberry Hwy",
    "sg:city":"Orleans",
    "sg:classifiers":[
        {
            "category":"Professional",
            "subcategory":"Lawyer & Legal Services",
            "type":"Services"
        }
    ],
    "sg:phone":"+1 508 255 2255",
    "sg:postcode":"02653",
    "sg:province":"MA",
    "sg:tags":[
        "attorney"
    ],
    "wof:name":"D'Elia & Cavanaugh",
    "wof:placetype":"venue"
},
  "geometry": {"coordinates":[-69.99548,41.78296],"type":"Point"}
}