{
  "type": "Feature",
  "properties": {
    "iso:country":"US",
    "sg:address":"33 Ralyn Rd",
    "sg:city":"Cotuit",
    "sg:classifiers":[
        {
            "category":"Education",
            "subcategory":"School",
            "type":"Public Place"
        }
    ],
    "sg:phone":"+1 774 238 8416",
    "sg:postcode":"02635",
    "sg:province":"MA",
    "sg:tags":[
        "elementary"
    ],
    "wof:name":"Elementary School Heads Association",
    "wof:placetype":"venue"
},
  "geometry": {"coordinates":[-70.445836,41.628897],"type":"Point"}
}