{
  "type": "Feature",
  "properties": {
    "iso:country":"US",
    "sg:address":"220 Andover St",
    "sg:city":"North Andover",
    "sg:classifiers":[
        {
            "category":"Shopping",
            "subcategory":"Discount & Variety Stores",
            "type":"Retail Goods"
        },
        {
            "category":"Food & Beverages",
            "subcategory":"Groceries & Convenience Stores",
            "type":"Retail Goods"
        }
    ],
    "sg:phone":"+1 978 682 4400",
    "sg:postcode":"01845",
    "sg:province":"MA",
    "wof:name":"Joe's Variety",
    "wof:placetype":"venue"
},
  "geometry": {"coordinates":[-71.12109100000001,42.678988],"type":"Point"}
}