{
  "type": "Feature",
  "properties": {
    "addr:full": "220 Andover St North Andover MA 01845",
    "addr:housenumber": "220",
    "addr:postcode": "01845",
    "addr:street": "Andover St",
    "iso:country": "US",
    "sg:address": "220 Andover St",
    "sg:city": "North Andover",
    "sg:classifiers": [
      {
        "category": "Shopping",
        "subcategory": "Discount \u0026 Variety Stores",
        "type": "Retail Goods"
      },
      {
        "category": "Food \u0026 Beverages",
        "subcategory": "Groceries \u0026 Convenience Stores",
        "type": "Retail Goods"
      }
    ],
    "sg:phone": "+1 978 682 4400",
    "sg:postcode": "01845",
    "sg:province": "MA",
    "wof:name": "Joe's Variety",
    "wof:placetype": "venue"
  },
  "geometry": {"coordinates":[-71.121091,42.678988],"type":"Point"}
}
