{
  "type": "Feature",
  "properties": {
    "iso:country":"US",
    "sg:address":"12 Pond St",
    "sg:city":"Canton",
    "sg:classifiers":[
        {
            "category":"Professional",
            "subcategory":"Advertising",
            "type":"Services"
        }
    ],
    "sg:phone":"+1 781 821 2277",
    "sg:postcode":"02021",
    "sg:province":"MA",
    "sg:tags":[
        "counselor"
    ],
    "wof:name":"J K Studios",
    "wof:placetype":"venue"
},
  "geometry": {"coordinates":[-71.14981899999999,42.145048],"type":"Point"}
}