{
  "type": "Feature",
  "properties": {
    "addr:full": "12 Pond St Canton MA 02021",
    "addr:housenumber": "12",
    "addr:postcode": "02021",
    "addr:street": "Pond St",
    "iso:country": "US",
    "sg:address": "12 Pond St",
    "sg:city": "Canton",
    "sg:classifiers": [
      {
        "category": "Professional",
        "subcategory": "Advertising",
        "type": "Services"
      }
    ],
    "sg:phone": "+1 781 821 2277",
    "sg:postcode": "02021",
    "sg:province": "MA",
    "sg:tags": [
      "counselor"
    ],
    "wof:name": "J K Studios",
    "wof:placetype": "venue"
  },
  "geometry": {"coordinates":[-71.149819,42.145048],"type":"Point"}
}
