{
  "type": "Feature",
  "properties": {
    "addr:full":"228 Chandler St Worcester MA 01609",
    "addr:housenumber":"228",
    "addr:postcode":"01609",
    "addr:street":"Chandler St",
    "iso:country":"US",
    "sg:address":"228 Chandler St",
    "sg:city":"Worcester",
    "sg:classifiers":[
        {
            "category":"Shopping",
            "subcategory":"Clothing, Apparel, & Fashions",
            "type":"Retail Goods"
        }
    ],
    "sg:phone":"+1 508 791 9522",
    "sg:postcode":"01609",
    "sg:province":"MA",
    "sg:tags":[
        "lingerie"
    ],
    "wof:name":"Lingerie Shoppe",
    "wof:placetype":"venue"
},
  "geometry": {"coordinates":[-71.818878,42.260919],"type":"Point"}
}