{
  "type": "Feature",
  "properties": {
    "addr:full": "162 Old Colony Ave Quincy MA 02170",
    "addr:housenumber": "162",
    "addr:postcode": "02170",
    "addr:street": "Old Colony Ave",
    "iso:country": "US",
    "sg:address": "162 Old Colony Ave",
    "sg:city": "Quincy",
    "sg:classifiers": [
      {
        "category": "Professional",
        "subcategory": "Management \u0026 Consulting",
        "type": "Services"
      }
    ],
    "sg:phone": "+1 617 769 9531",
    "sg:postcode": "02170",
    "sg:province": "MA",
    "sg:tags": [
      "consultant",
      "business"
    ],
    "wof:name": "Rt Robertson Consultants",
    "wof:placetype": "venue"
  },
  "geometry": {"coordinates":[-71.014837,42.262217],"type":"Point"}
}
