{
  "type": "Feature",
  "properties": {
    "iso:country":"US",
    "sg:address":"298 Main St",
    "sg:city":"Saugus",
    "sg:classifiers":[
        {
            "category":"Social Services",
            "type":"Services"
        },
        {
            "category":"Education",
            "subcategory":"Special Training",
            "type":"Public Place"
        },
        {
            "category":"Organizations",
            "subcategory":"Professional Association",
            "type":"Services"
        },
        {
            "category":"Community Center",
            "subcategory":"Youth",
            "type":"Public Place"
        },
        {
            "category":"Exhibition Hall",
            "type":"Public Place"
        },
        {
            "category":"Social Services",
            "subcategory":"Child Care",
            "type":"Services"
        }
    ],
    "sg:phone":"+1 781 233 0443",
    "sg:postcode":"01906",
    "sg:province":"MA",
    "sg:tags":[
        "educational",
        "business",
        "ballroom",
        "services-information",
        "trade",
        "program",
        "referral",
        "halls",
        "auditorium"
    ],
    "sg:website":"http://www.ymca.net",
    "wof:name":"Ymca",
    "wof:placetype":"venue"
},
  "geometry": {"coordinates":[-71.03376299999999,42.471572],"type":"Point"}
}