{
  "type": "Feature",
  "properties": {
    "addr:full": "704 State Rd North Dartmouth MA 02747",
    "addr:housenumber": "704",
    "addr:postcode": "02747",
    "addr:street": "State Rd",
    "iso:country": "US",
    "sg:address": "704 State Rd",
    "sg:city": "North Dartmouth",
    "sg:classifiers": [
      {
        "category": "Autos \u0026 Motor Vehicles",
        "subcategory": "Automobile Sales",
        "type": "Retail Goods"
      }
    ],
    "sg:phone": "+1 508 991 6631",
    "sg:postcode": "02747",
    "sg:province": "MA",
    "sg:tags": [
      "car",
      "dealer"
    ],
    "wof:name": "Leo's Used Cars",
    "wof:placetype": "venue"
  },
  "geometry": {"coordinates":[-71.027848,41.639502],"type":"Point"}
}
