{
  "type": "Feature",
  "properties": {
    "iso:country":"US",
    "sg:address":"704 State Rd",
    "sg:city":"North Dartmouth",
    "sg:classifiers":[
        {
            "category":"Autos & Motor Vehicles",
            "subcategory":"Automobile Sales",
            "type":"Retail Goods"
        }
    ],
    "sg:phone":"+1 508 991 6631",
    "sg:postcode":"02747",
    "sg:province":"MA",
    "sg:tags":[
        "car",
        "dealer"
    ],
    "wof:name":"Leo's Used Cars",
    "wof:placetype":"venue"
},
  "geometry": {"coordinates":[-71.02784800000001,41.639502],"type":"Point"}
}