{
  "type": "Feature",
  "properties": {
    "addr:full":"1040 Main St Clinton MA 01510",
    "addr:housenumber":"1040",
    "addr:postcode":"01510",
    "addr:street":"Main St",
    "iso:country":"US",
    "sg:address":"1040 Main St",
    "sg:city":"Clinton",
    "sg:classifiers":[
        {
            "category":"Restaurant",
            "type":"Food & Drink"
        }
    ],
    "sg:menulink":"http://www.allmenus.com/ma/clinton/188555-mcdonalds/menu/",
    "sg:postcode":"01510",
    "sg:province":"MA",
    "sg:tags":[
        "burger",
        "american"
    ],
    "wof:name":"McDonald's",
    "wof:placetype":"venue"
},
  "geometry": {"coordinates":[-71.687237,42.432234],"type":"Point"}
}