{
  "type": "Feature",
  "properties": {
    "addr:full":"21 Woodwell Cir Amesbury MA 01913",
    "addr:housenumber":"21",
    "addr:postcode":"01913",
    "addr:street":"Woodwell Cir",
    "iso:country":"US",
    "sg:address":"21 Woodwell Cir",
    "sg:city":"Amesbury",
    "sg:classifiers":[
        {
            "category":"Building & Trades",
            "subcategory":"Equipment Rental",
            "type":"Services"
        },
        {
            "category":"Shopping",
            "subcategory":"Computers & Home Electronics",
            "type":"Retail Goods"
        }
    ],
    "sg:phone":"+1 978 388 1301",
    "sg:postcode":"01913",
    "sg:province":"MA",
    "sg:tags":[
        "stereo",
        "leasing",
        "video",
        "audio",
        "equipment-renting",
        "audio-visual"
    ],
    "wof:name":"Magpix, Inc",
    "wof:placetype":"venue"
},
  "geometry": {"coordinates":[-70.947419,42.866879],"type":"Point"}
}