{
  "type": "Feature",
  "properties": {
    "iso:country":"US",
    "sg:address":"253 Williams Street",
    "sg:city":"Chelsea",
    "sg:classifiers":[
        {
            "category":"Food & Beverages",
            "subcategory":"Groceries & Convenience Stores",
            "type":"Retail Goods"
        }
    ],
    "sg:phone":"+1 617 884 4398",
    "sg:postcode":"02150",
    "sg:province":"MA",
    "wof:name":"Jetro Cash & Carry",
    "wof:placetype":"venue"
},
  "geometry": {"coordinates":[-71.04482400000001,42.392581],"type":"Point"}
}