{
  "type": "Feature",
  "properties": {
    "addr:full": "253 Williams Street Chelsea MA 02150",
    "addr:housenumber": "253",
    "addr:postcode": "02150",
    "addr:street": "Williams Street",
    "iso:country": "US",
    "sg:address": "253 Williams Street",
    "sg:city": "Chelsea",
    "sg:classifiers": [
      {
        "category": "Food \u0026 Beverages",
        "subcategory": "Groceries \u0026 Convenience Stores",
        "type": "Retail Goods"
      }
    ],
    "sg:phone": "+1 617 884 4398",
    "sg:postcode": "02150",
    "sg:province": "MA",
    "wof:name": "Jetro Cash \u0026 Carry",
    "wof:placetype": "venue"
  },
  "geometry": {"coordinates":[-71.044824,42.392581],"type":"Point"}
}
