{
  "type": "Feature",
  "properties": {
    "iso:country":"US",
    "sg:address":"51 Main St",
    "sg:city":"Hyannis",
    "sg:classifiers":[
        {
            "category":"Health Services",
            "subcategory":"Doctor",
            "type":"Services"
        }
    ],
    "sg:phone":"+1 508 775 6466",
    "sg:postcode":"02601",
    "sg:province":"MA",
    "sg:tags":[
        "podiatrist"
    ],
    "wof:name":"Murgida Jos DPM - CLOSED",
    "wof:placetype":"venue"
},
  "geometry": {"coordinates":[-70.272499,41.656601],"type":"Point"}
}