{
  "type": "Feature",
  "properties": {
    "addr:full":"652 Newport Ave Attleboro MA 02703",
    "addr:housenumber":"652",
    "addr:postcode":"02703",
    "addr:street":"Newport Ave",
    "iso:country":"US",
    "sg:address":"652 Newport Ave",
    "sg:city":"Attleboro",
    "sg:classifiers":[
        {
            "category":"Home & Garden",
            "subcategory":"Building Materials",
            "type":"Retail Goods"
        }
    ],
    "sg:phone":"+1 508 695 3223",
    "sg:postcode":"02703",
    "sg:province":"MA",
    "sg:tags":[
        "door"
    ],
    "wof:name":"Compton Doors",
    "wof:placetype":"venue"
},
  "geometry": {"coordinates":[-71.356403,41.920447],"type":"Point"}
}