{
  "type": "Feature",
  "properties": {
    "addr:full":"452 Southbridge St Worcester MA 01610",
    "addr:housenumber":"452",
    "addr:postcode":"01610",
    "addr:street":"Southbridge St",
    "iso:country":"US",
    "sg:address":"452 Southbridge St",
    "sg:city":"Worcester",
    "sg:classifiers":[
        {
            "category":"Freight",
            "type":"Transportation"
        }
    ],
    "sg:phone":"+1 508 363 1300",
    "sg:postcode":"01610",
    "sg:province":"MA",
    "wof:name":"MHF-Ls Transload Inc",
    "wof:placetype":"venue"
},
  "geometry": {"coordinates":[-71.809181,42.25041],"type":"Point"}
}