{
  "type": "Feature",
  "properties": {
    "addr:full":"9 New Venture Dr South Dennis MA 02660",
    "addr:housenumber":"9",
    "addr:postcode":"02660",
    "addr:street":"New Venture Dr",
    "iso:country":"US",
    "sg:address":"9 New Venture Dr",
    "sg:city":"South Dennis",
    "sg:classifiers":[
        {
            "category":"Real Estate",
            "subcategory":"Real Estate Agent",
            "type":"Services"
        }
    ],
    "sg:phone":"+1 508 394 4028",
    "sg:postcode":"02660",
    "sg:province":"MA",
    "wof:name":"Titan Realty Corp",
    "wof:placetype":"venue"
},
  "geometry": {"coordinates":[-70.141485,41.690009],"type":"Point"}
}