{
  "type": "Feature",
  "properties": {
    "iso:country":"US",
    "sg:address":"211 Main St",
    "sg:city":"Wilmington",
    "sg:classifiers":[
        {
            "category":"Food & Beverages",
            "subcategory":"Candy",
            "type":"Retail Goods"
        }
    ],
    "sg:phone":"+1 978 658 8825",
    "sg:postcode":"01887",
    "sg:province":"MA",
    "sg:tags":[
        "dessert"
    ],
    "wof:name":"K & A Cones",
    "wof:placetype":"venue"
},
  "geometry": {"coordinates":[-71.181755,42.557432],"type":"Point"}
}