{
  "type": "Feature",
  "properties": {
    "addr:full": "211 Main St Wilmington MA 01887",
    "addr:housenumber": "211",
    "addr:postcode": "01887",
    "addr:street": "Main St",
    "iso:country": "US",
    "sg:address": "211 Main St",
    "sg:city": "Wilmington",
    "sg:classifiers": [
      {
        "category": "Food \u0026 Beverages",
        "subcategory": "Candy",
        "type": "Retail Goods"
      }
    ],
    "sg:phone": "+1 978 658 8825",
    "sg:postcode": "01887",
    "sg:province": "MA",
    "sg:tags": [
      "dessert"
    ],
    "wof:name": "K \u0026 A Cones",
    "wof:placetype": "venue"
  },
  "geometry": {"coordinates":[-71.181755,42.557432],"type":"Point"}
}
