{
  "type": "Feature",
  "properties": {
    "iso:country":"US",
    "sg:address":"85 Main St",
    "sg:city":"Medway",
    "sg:classifiers":[
        {
            "category":"Autos & Motor Vehicles",
            "subcategory":"Auto Supplies",
            "type":"Retail Goods"
        }
    ],
    "sg:phone":"+1 508 533 4200",
    "sg:postcode":"02053",
    "sg:province":"MA",
    "sg:tags":[
        "tire"
    ],
    "sg:website":"www.longdistancetire.com",
    "wof:name":"Long Distance Tire Inc",
    "wof:placetype":"venue"
},
  "geometry": {"coordinates":[-71.410984,42.151217],"type":"Point"}
}