{
  "type": "Feature",
  "properties": {
    "addr:full":"160 Worcester-Providence Tpke Sutton MA 01590",
    "addr:housenumber":"160",
    "addr:postcode":"01590",
    "addr:street":"Worcester-Providence Tpke",
    "iso:country":"US",
    "sg:address":"160 Worcester-Providence Tpke",
    "sg:city":"Sutton",
    "sg:classifiers":[
        {
            "category":"Professional",
            "subcategory":"Business Services",
            "type":"Services"
        }
    ],
    "sg:phone":"+1 508 581 9691",
    "sg:postcode":"01590",
    "sg:province":"MA",
    "sg:tags":[
        "automobile",
        "appraiser"
    ],
    "wof:name":"Property Damage Appraisers Inc",
    "wof:placetype":"venue"
},
  "geometry": {"coordinates":[-71.73698400000001,42.160409],"type":"Point"}
}