{
  "type": "Feature",
  "properties": {
    "iso:country":"US",
    "sg:address":"33 Lloyd Ave",
    "sg:city":"Springfield",
    "sg:classifiers":[
        {
            "category":"Professional",
            "subcategory":"Computer Services",
            "type":"Services"
        }
    ],
    "sg:phone":"+1 413 796 7072",
    "sg:postcode":"01119",
    "sg:province":"MA",
    "sg:tags":[
        "website",
        "design"
    ],
    "wof:name":"Ans Online Connection",
    "wof:placetype":"venue"
},
  "geometry": {"coordinates":[-72.512688,42.137145],"type":"Point"}
}