{
  "type": "Feature",
  "properties": {
    "addr:full":"415 S Main St Randolph MA 02368",
    "addr:housenumber":"415",
    "addr:postcode":"02368",
    "addr:street":"S Main St",
    "iso:country":"US",
    "sg:address":"415 S Main St",
    "sg:city":"Randolph",
    "sg:classifiers":[
        {
            "category":"Wholesale",
            "subcategory":"Computers",
            "type":"Manufacturing & Wholesale Goods"
        }
    ],
    "sg:phone":"+1 781 767 7480",
    "sg:postcode":"02368",
    "sg:province":"MA",
    "wof:name":"Useast Technologies",
    "wof:placetype":"venue"
},
  "geometry": {"coordinates":[-71.043294,42.147958],"type":"Point"}
}