{
  "type": "Feature",
  "properties": {
    "addr:full": "28 Maple Avenue Medford MA 02155",
    "addr:housenumber": "28",
    "addr:postcode": "02155",
    "addr:street": "Maple Avenue",
    "iso:country": "US",
    "sg:address": "28 Maple Avenue",
    "sg:city": "Medford",
    "sg:classifiers": [
      {
        "category": "Sports \u0026 Exercise",
        "subcategory": "Gym",
        "type": "Entertainment"
      }
    ],
    "sg:phone": "+1 781 395 5515",
    "sg:postcode": "02155",
    "sg:province": "MA",
    "sg:tags": [
      "trainer"
    ],
    "wof:name": "Health Watch",
    "wof:placetype": "venue"
  },
  "geometry": {"coordinates":[-71.11675,42.416407],"type":"Point"}
}
