{
  "type": "Feature",
  "properties": {
    "addr:full":"1931 Dorchester Ave Dorchester Ctr MA 02124",
    "addr:housenumber":"1931",
    "addr:postcode":"02124",
    "addr:street":"Dorchester Ave Dorchester Ctr",
    "iso:country":"US",
    "sg:address":"1931 Dorchester Ave",
    "sg:city":"Dorchester Ctr",
    "sg:classifiers":[
        {
            "category":"Food & Beverages",
            "subcategory":"Bakery",
            "type":"Retail Goods"
        }
    ],
    "sg:phone":"+1 617 282 1268",
    "sg:postcode":"02124",
    "sg:province":"MA",
    "sg:tags":[
        "doughnut"
    ],
    "wof:name":"Dunkin Donuts",
    "wof:placetype":"venue"
},
  "geometry": {"coordinates":[-71.06485000000001,42.284066],"type":"Point"}
}