{
  "type": "Feature",
  "properties": {
    "addr:full":"171 Linwood Ave Whitinsville MA 01588",
    "addr:housenumber":"171",
    "addr:postcode":"01588",
    "addr:street":"Linwood Ave",
    "iso:country":"US",
    "sg:address":"171 Linwood Ave",
    "sg:city":"Whitinsville",
    "sg:classifiers":[
        {
            "category":"Education",
            "subcategory":"School",
            "type":"Public Place"
        }
    ],
    "sg:phone":"+1 508 234 8120",
    "sg:postcode":"01588",
    "sg:province":"MA",
    "wof:name":"Public School Administration",
    "wof:placetype":"venue"
},
  "geometry": {"coordinates":[-71.65783399999999,42.108426],"type":"Point"}
}