{
  "type": "Feature",
  "properties": {
    "iso:country":"US",
    "sg:address":"156 Milk St",
    "sg:city":"Boston",
    "sg:classifiers":[
        {
            "category":"Insurance",
            "subcategory":"Insurance Agent",
            "type":"Services"
        }
    ],
    "sg:phone":"+1   ",
    "sg:postcode":"02109",
    "sg:province":"MA",
    "wof:name":"Edmund Morante Insurance Agcy",
    "wof:placetype":"venue"
},
  "geometry": {"coordinates":[-71.052632,42.358652],"type":"Point"}
}