{
  "type": "Feature",
  "properties": {
    "iso:country":"US",
    "sg:address":"108 Newburyport Tpke",
    "sg:city":"Rowley",
    "sg:classifiers":[
        {
            "category":"Personal",
            "type":"Services"
        }
    ],
    "sg:phone":"+1 978 948 2201",
    "sg:postcode":"01969",
    "sg:province":"MA",
    "sg:tags":[
        "sewing",
        "alteration"
    ],
    "wof:name":"Phoenix Monogramming Ent",
    "wof:placetype":"venue"
},
  "geometry": {"coordinates":[-70.910698,42.701099],"type":"Point"}
}