{
  "type": "Feature",
  "properties": {
    "iso:country":"US",
    "sg:address":"935 Summer St",
    "sg:city":"Lynnfield",
    "sg:classifiers":[
        {
            "category":"Building & Trades",
            "subcategory":"Construction",
            "type":"Services"
        }
    ],
    "sg:phone":"+1 781 246 0888",
    "sg:postcode":"01940",
    "sg:province":"MA",
    "sg:tags":[
        "acoustical",
        "material"
    ],
    "wof:name":"Patterson Associates",
    "wof:placetype":"venue"
},
  "geometry": {"coordinates":[-71.01851600000001,42.521674],"type":"Point"}
}