{
  "type": "Feature",
  "properties": {
    "addr:full": "9 Liberty St Newburyport MA 01950",
    "addr:housenumber": "9",
    "addr:postcode": "01950",
    "addr:street": "Liberty St",
    "iso:country": "US",
    "sg:address": "9 Liberty St",
    "sg:city": "Newburyport",
    "sg:classifiers": [
      {
        "category": "Restaurant",
        "type": "Food \u0026 Drink"
      }
    ],
    "sg:phone": "+1 978 499 9393",
    "sg:postcode": "01950",
    "sg:province": "MA",
    "sg:tags": [
      "sandwich"
    ],
    "wof:name": "Moe's Sandwich Shop",
    "wof:placetype": "venue"
  },
  "geometry": {"coordinates":[-70.869095,42.81105],"type":"Point"}
}
