{
  "type": "Feature",
  "properties": {
    "addr:full":"370 Hancock St Quincy MA 02171",
    "addr:housenumber":"370",
    "addr:postcode":"02171",
    "addr:street":"Hancock St",
    "iso:country":"US",
    "sg:address":"370 Hancock St",
    "sg:city":"Quincy",
    "sg:classifiers":[
        {
            "category":"Education",
            "subcategory":"School",
            "type":"Public Place"
        }
    ],
    "sg:phone":"+1 617 328 3830",
    "sg:postcode":"02171",
    "sg:province":"MA",
    "sg:website":"www.shsquincy.org",
    "wof:name":"Sacred Heart School",
    "wof:placetype":"venue"
},
  "geometry": {"coordinates":[-71.026836,42.274935],"type":"Point"}
}