{
  "type": "Feature",
  "properties": {
    "addr:full": "331 Wilbraham Rd Springfield MA 01109",
    "addr:housenumber": "331",
    "addr:postcode": "01109",
    "addr:street": "Wilbraham Rd",
    "iso:country": "US",
    "sg:address": "331 Wilbraham Rd",
    "sg:city": "Springfield",
    "sg:classifiers": [
      {
        "category": "Organizations",
        "subcategory": "Religious Organization",
        "type": "Services"
      }
    ],
    "sg:phone": "+1 413 782 7477",
    "sg:postcode": "01109",
    "sg:province": "MA",
    "sg:tags": [
      "church"
    ],
    "wof:name": "United House Of Prayer",
    "wof:placetype": "venue"
  },
  "geometry": {"coordinates":[-72.551381,42.112845],"type":"Point"}
}
