{
  "type": "Feature",
  "properties": {
    "iso:country":"US",
    "sg:address":"5 Commercial St",
    "sg:city":"Braintree",
    "sg:classifiers":[
        {
            "category":"Personal",
            "type":"Services"
        },
        {
            "category":"Restaurant",
            "type":"Food & Drink"
        },
        {
            "category":"Retail",
            "subcategory":"Event Space",
            "type":"Services"
        }
    ],
    "sg:phone":"+1 781 843 8005",
    "sg:postcode":"02184",
    "sg:province":"MA",
    "sg:tags":[
        "style",
        "mexican",
        "family",
        "facility",
        "hall",
        "planning",
        "reception",
        "party",
        "meeting",
        "banquet"
    ],
    "sg:website":"http://www.elsarape.com",
    "wof:name":"El Sarape",
    "wof:placetype":"venue"
},
  "geometry": {"coordinates":[-70.968672,42.220081],"type":"Point"}
}