{
  "type": "Feature",
  "properties": {
    "addr:full": "5 Commercial St Braintree MA 02184",
    "addr:housenumber": "5",
    "addr:postcode": "02184",
    "addr:street": "Commercial St",
    "iso:country": "US",
    "ovtr:label": "El Sarape, 5 Commercial St Braintree MA US",
    "ovtr:similarity": 2.4745121002197266,
    "sg:address": "5 Commercial St",
    "sg:city": "Braintree",
    "sg:classifiers": [
      {
        "category": "Personal",
        "type": "Services"
      },
      {
        "category": "Restaurant",
        "type": "Food \u0026 Drink"
      },
      {
        "category": "Retail",
        "subcategory": "Event Space",
        "type": "Services"
      }
    ],
    "sg:phone": "+1 781 843 8005",
    "sg:postcode": "02184",
    "sg:province": "MA",
    "sg:tags": [
      "style",
      "mexican",
      "family",
      "facility",
      "hall",
      "planning",
      "reception",
      "party",
      "meeting",
      "banquet"
    ],
    "sg:website": "http://www.elsarape.com",
    "wof:name": "El Sarape",
    "wof:placetype": "venue"
  },
  "geometry": {"coordinates":[-70.968672,42.220081],"type":"Point"}
}
