{
  "type": "Feature",
  "properties": {
    "addr:full": "62 School St Boston MA 02108",
    "addr:housenumber": "62",
    "addr:postcode": "02108",
    "addr:street": "School St",
    "iso:country": "US",
    "sg:address": "62 School St",
    "sg:city": "Boston",
    "sg:classifiers": [
      {
        "category": "Building \u0026 Trades",
        "subcategory": "Locksmith",
        "type": "Services"
      }
    ],
    "sg:phone": "+1 617 303 2676",
    "sg:postcode": "02108",
    "sg:province": "MA",
    "sg:tags": [
      "key"
    ],
    "wof:name": "Top of the Line Locksmith",
    "wof:placetype": "venue"
  },
  "geometry": {"coordinates":[-71.059725,42.357682],"type":"Point"}
}
