{
  "type": "Feature",
  "properties": {
    "addr:full": "167 Bucknam St Everett MA 02149",
    "addr:housenumber": "167",
    "addr:postcode": "02149",
    "addr:street": "Bucknam St",
    "iso:country": "US",
    "sg:address": "167 Bucknam St",
    "sg:city": "Everett",
    "sg:classifiers": [
      {
        "category": "Retail",
        "subcategory": "Self-service Laundry",
        "type": "Services"
      }
    ],
    "sg:phone": "+1 617 381 6850",
    "sg:postcode": "02149",
    "sg:province": "MA",
    "wof:name": "Bright White Laundry Ctr",
    "wof:placetype": "venue"
  },
  "geometry": {"coordinates":[-71.061775,42.414309],"type":"Point"}
}
