{
  "type": "Feature",
  "properties": {
    "iso:country":"US",
    "sg:address":"117 Grove St",
    "sg:city":"Adams",
    "sg:classifiers":[
        {
            "category":"Social Services",
            "subcategory":"Child Care",
            "type":"Services"
        }
    ],
    "sg:phone":"+1 413 743 7902",
    "sg:postcode":"01220",
    "sg:province":"MA",
    "wof:name":"Kiddyland Child Ctr",
    "wof:placetype":"venue"
},
  "geometry": {"coordinates":[-73.13994099999999,42.598094],"type":"Point"}
}