{
  "type": "Feature",
  "properties": {
    "addr:full": "117 Grove St Adams MA 01220",
    "addr:housenumber": "117",
    "addr:postcode": "01220",
    "addr:street": "Grove St",
    "iso:country": "US",
    "sg:address": "117 Grove St",
    "sg:city": "Adams",
    "sg:classifiers": [
      {
        "category": "Social Services",
        "subcategory": "Child Care",
        "type": "Services"
      }
    ],
    "sg:phone": "+1 413 743 7902",
    "sg:postcode": "01220",
    "sg:province": "MA",
    "wof:name": "Kiddyland Child Ctr",
    "wof:placetype": "venue"
  },
  "geometry": {"coordinates":[-73.139941,42.598094],"type":"Point"}
}
