{
  "type": "Feature",
  "properties": {
    "addr:full":"26 Brighton St Belmont MA 02478",
    "addr:housenumber":"26",
    "addr:postcode":"02478",
    "addr:street":"Brighton St",
    "iso:country":"US",
    "sg:address":"26 Brighton St",
    "sg:city":"Belmont",
    "sg:classifiers":[
        {
            "category":"Freight",
            "type":"Transportation"
        }
    ],
    "sg:phone":"+1 617 484 5169",
    "sg:postcode":"02478",
    "sg:province":"MA",
    "sg:tags":[
        "warehouse"
    ],
    "wof:name":"MBO Assoc",
    "wof:placetype":"venue"
},
  "geometry": {"coordinates":[-71.158659,42.395457],"type":"Point"}
}