{
  "type": "Feature",
  "properties": {
    "iso:country":"US",
    "sg:address":"157 Dean St",
    "sg:city":"Taunton",
    "sg:classifiers":[
        {
            "category":"Autos & Motor Vehicles",
            "subcategory":"Automobile Sales",
            "type":"Retail Goods"
        },
        {
            "category":"Retail",
            "subcategory":"Auto Repair",
            "type":"Services"
        }
    ],
    "sg:phone":"+1 508 880 9900",
    "sg:postcode":"02780",
    "sg:province":"MA",
    "sg:tags":[
        "dealers-used",
        "new",
        "used",
        "cars-wholesale",
        "car"
    ],
    "sg:website":"http://www.borgesautocenter.com",
    "wof:name":"Borges Auto Center Inc",
    "wof:placetype":"venue"
},
  "geometry": {"coordinates":[-71.070401,41.905887],"type":"Point"}
}