{
  "type": "Feature",
  "properties": {
    "addr:full":"215 Main St North Reading MA 01864",
    "addr:housenumber":"215",
    "addr:postcode":"01864",
    "addr:street":"Main St",
    "iso:country":"US",
    "sg:address":"215 Main St",
    "sg:city":"North Reading",
    "sg:classifiers":[
        {
            "category":"Personal",
            "subcategory":"Beauty Salon",
            "type":"Services"
        }
    ],
    "sg:phone":"+1 978 664 4489",
    "sg:postcode":"01864",
    "sg:province":"MA",
    "wof:name":"Michael's Cut Above",
    "wof:placetype":"venue"
},
  "geometry": {"coordinates":[-71.115484,42.587491],"type":"Point"}
}