{
  "type": "Feature",
  "properties": {
    "addr:full":"151 Merrimac St Boston MA 02114",
    "addr:housenumber":"151",
    "addr:postcode":"02114",
    "addr:street":"Merrimac St",
    "iso:country":"US",
    "sg:address":"151 Merrimac St",
    "sg:city":"Boston",
    "sg:classifiers":[
        {
            "category":"Professional",
            "subcategory":"Lawyer & Legal Services",
            "type":"Services"
        }
    ],
    "sg:phone":"+1 617 742 2700",
    "sg:postcode":"02114",
    "sg:province":"MA",
    "wof:name":"Fleschner Sara ESQ",
    "wof:placetype":"venue"
},
  "geometry": {"coordinates":[-71.062698,42.363899],"type":"Point"}
}