{
  "type": "Feature",
  "properties": {
    "iso:country":"US",
    "sg:address":"387 Washington Street",
    "sg:city":"Boston",
    "sg:classifiers":[
        {
            "category":"Shopping",
            "subcategory":"Jewelry",
            "type":"Retail Goods"
        }
    ],
    "sg:phone":"+1 617 542 7965",
    "sg:postcode":"02108",
    "sg:province":"MA",
    "wof:name":"Whites Jewelry",
    "wof:placetype":"venue"
},
  "geometry": {"coordinates":[-71.05984599999999,42.356116],"type":"Point"}
}