{
  "type": "Feature",
  "properties": {
    "addr:full": "100 Reservoir Rd Quincy MA 02170",
    "addr:housenumber": "100",
    "addr:postcode": "02170",
    "addr:street": "Reservoir Rd",
    "iso:country": "US",
    "sg:address": "100 Reservoir Rd",
    "sg:city": "Quincy",
    "sg:classifiers": [
      {
        "category": "Real Estate",
        "subcategory": "Real Estate Agent",
        "type": "Services"
      }
    ],
    "sg:phone": "+1 617 302 0000",
    "sg:postcode": "02170",
    "sg:province": "MA",
    "wof:name": "Paul A Wilkie \u0026 Assoc Appraise",
    "wof:placetype": "venue"
  },
  "geometry": {"coordinates":[-71.026429,42.255],"type":"Point"}
}
