{
  "type": "Feature",
  "properties": {
    "iso:country":"US",
    "sg:address":"87 Cameron Rd",
    "sg:city":"Norwood",
    "sg:classifiers":[
        {
            "category":"Retail",
            "subcategory":"Laundry & Dry Cleaning",
            "type":"Services"
        },
        {
            "category":"Home & Garden",
            "subcategory":"Building Materials",
            "type":"Retail Goods"
        },
        {
            "category":"Building & Trades",
            "subcategory":"Construction",
            "type":"Services"
        }
    ],
    "sg:phone":"+1 617 965 2345",
    "sg:postcode":"02062",
    "sg:province":"MA",
    "sg:tags":[
        "chimneys-prefabricated",
        "chimney",
        "contractor"
    ],
    "wof:name":"Downeast Chimney Sweep",
    "wof:placetype":"venue"
},
  "geometry": {"coordinates":[-71.191169,42.208941],"type":"Point"}
}