{
  "type": "Feature",
  "properties": {
    "iso:country":"US",
    "sg:address":"Great Way Wellness Center 278 Elm St Ste 227",
    "sg:city":"Somerville",
    "sg:classifiers":[
        {
            "category":"Health Services",
            "subcategory":"Clinic",
            "type":"Services"
        }
    ],
    "sg:phone":"+1 617 852 0690",
    "sg:postcode":"02144",
    "sg:province":"MA",
    "sg:tags":[
        "medical"
    ],
    "sg:website":"www.greatwaywellness.com",
    "wof:name":"Cathy Thomason",
    "wof:placetype":"venue"
},
  "geometry": {"coordinates":[-71.122299,42.396037],"type":"Point"}
}