{
  "type": "Feature",
  "properties": {
    "iso:country":"US",
    "sg:address":"333 Park St",
    "sg:city":"North Reading",
    "sg:classifiers":[
        {
            "category":"Social Services",
            "subcategory":"Adult Care",
            "type":"Services"
        }
    ],
    "sg:phone":"+1 978 664 9009",
    "sg:postcode":"01864",
    "sg:province":"MA",
    "sg:tags":[
        "home",
        "residential"
    ],
    "wof:name":"Mc Laughlin House",
    "wof:placetype":"venue"
},
  "geometry": {"coordinates":[-71.10775099999999,42.565606],"type":"Point"}
}