{
  "type": "Feature",
  "properties": {
    "addr:full": "87 School Street Brookline MA 02446",
    "addr:housenumber": "87",
    "addr:postcode": "02446",
    "addr:street": "School Street",
    "iso:country": "US",
    "sg:address": "87 School Street",
    "sg:city": "Brookline",
    "sg:classifiers": [
      {
        "category": "Personal",
        "type": "Services"
      },
      {
        "category": "Retail",
        "subcategory": "Laundry \u0026 Dry Cleaning",
        "type": "Services"
      }
    ],
    "sg:phone": "+1 617 566 8740",
    "sg:postcode": "02446",
    "sg:province": "MA",
    "sg:tags": [
      "sewing",
      "alteration"
    ],
    "wof:name": "Brookline Valet Cleaners",
    "wof:placetype": "venue"
  },
  "geometry": {"coordinates":[-71.122835,42.33457],"type":"Point"}
}
