{
  "type": "Feature",
  "properties": {
    "iso:country":"US",
    "sg:address":"45 W Boylston St",
    "sg:city":"West Boylston",
    "sg:classifiers":[
        {
            "category":"Banks & Credit Unions",
            "subcategory":"Investment Brokerage",
            "type":"Services"
        }
    ],
    "sg:phone":"+1 508 829 5891",
    "sg:postcode":"01583",
    "sg:province":"MA",
    "sg:tags":[
        "consultant",
        "planning",
        "financial"
    ],
    "wof:name":"Miller Financial Group",
    "wof:placetype":"venue"
},
  "geometry": {"coordinates":[-71.78426399999999,42.357652],"type":"Point"}
}