{
  "type": "Feature",
  "properties": {
    "addr:full": "45 W Boylston St West Boylston MA 01583",
    "addr:housenumber": "45",
    "addr:postcode": "01583",
    "addr:street": "W Boylston St",
    "iso:country": "US",
    "sg:address": "45 W Boylston St",
    "sg:city": "West Boylston",
    "sg:classifiers": [
      {
        "category": "Banks \u0026 Credit Unions",
        "subcategory": "Investment Brokerage",
        "type": "Services"
      }
    ],
    "sg:phone": "+1 508 829 5891",
    "sg:postcode": "01583",
    "sg:province": "MA",
    "sg:tags": [
      "consultant",
      "planning",
      "financial"
    ],
    "wof:name": "Miller Financial Group",
    "wof:placetype": "venue"
  },
  "geometry": {"coordinates":[-71.784264,42.357652],"type":"Point"}
}
