{
  "type": "Feature",
  "properties": {
    "addr:full": "101 Colonial Dr Andover MA 01810",
    "addr:housenumber": "101",
    "addr:postcode": "01810",
    "addr:street": "Colonial Dr",
    "iso:country": "US",
    "sg:address": "101 Colonial Dr",
    "sg:city": "Andover",
    "sg:classifiers": [
      {
        "category": "Professional",
        "subcategory": "Management \u0026 Consulting",
        "type": "Services"
      }
    ],
    "sg:phone": "+1 978 470 2227",
    "sg:postcode": "01810",
    "sg:province": "MA",
    "sg:tags": [
      "consultant",
      "business"
    ],
    "wof:name": "Red Javeline Communications",
    "wof:placetype": "venue"
  },
  "geometry": {"coordinates":[-71.12159,42.60134],"type":"Point"}
}
