{
  "type": "Feature",
  "properties": {
    "iso:country":"US",
    "sg:address":"101 Colonial Dr",
    "sg:city":"Andover",
    "sg:classifiers":[
        {
            "category":"Professional",
            "subcategory":"Management & Consulting",
            "type":"Services"
        }
    ],
    "sg:phone":"+1 978 470 2227",
    "sg:postcode":"01810",
    "sg:province":"MA",
    "sg:tags":[
        "consultant",
        "business"
    ],
    "wof:name":"Red Javeline Communications",
    "wof:placetype":"venue"
},
  "geometry": {"coordinates":[-71.12159,42.60134],"type":"Point"}
}