{
  "type": "Feature",
  "properties": {
    "addr:full": "682 Lowell St Peabody MA 01960",
    "addr:housenumber": "682",
    "addr:postcode": "01960",
    "addr:street": "Lowell St",
    "iso:country": "US",
    "sg:address": "682 Lowell St",
    "sg:city": "Peabody",
    "sg:classifiers": [
      {
        "category": "Restaurant",
        "type": "Food \u0026 Drink"
      }
    ],
    "sg:phone": "+1 978 535 1207",
    "sg:postcode": "01960",
    "sg:province": "MA",
    "sg:tags": [
      "caterer"
    ],
    "wof:name": "Surf N Turf",
    "wof:placetype": "venue"
  },
  "geometry": {"coordinates":[-71.007543,42.549737],"type":"Point"}
}
