{
  "type": "Feature",
  "properties": {
    "iso:country":"US",
    "sg:address":"45 Harkness Rd",
    "sg:city":"Pelham",
    "sg:classifiers":[
        {
            "category":"Real Estate",
            "subcategory":"Architect",
            "type":"Services"
        }
    ],
    "sg:phone":"+1 413 253 9338",
    "sg:postcode":"01002",
    "sg:province":"MA",
    "sg:tags":[
        "architects'",
        "specification",
        "construction",
        "builders'",
        "architectural"
    ],
    "wof:name":"Gail Kenny",
    "wof:placetype":"venue"
},
  "geometry": {"coordinates":[-72.47368,42.371501],"type":"Point"}
}