{
  "type": "Feature",
  "properties": {
    "iso:country":"US",
    "sg:address":"75 South Rd",
    "sg:city":"Holden",
    "sg:classifiers":[
        {
            "category":"Manufacturing",
            "subcategory":"Tools & Machinery",
            "type":"Manufacturing & Wholesale Goods"
        }
    ],
    "sg:phone":"+1 508 829 6317",
    "sg:postcode":"01520",
    "sg:province":"MA",
    "sg:tags":[
        "machine"
    ],
    "wof:name":"Manufacturing Systems Inc",
    "wof:placetype":"venue"
},
  "geometry": {"coordinates":[-71.877073,42.334917],"type":"Point"}
}