{
  "type": "Feature",
  "properties": {
    "addr:full": "446 Washington St Wellesley MA 02482",
    "addr:housenumber": "446",
    "addr:postcode": "02482",
    "addr:street": "Washington St",
    "iso:country": "US",
    "sg:address": "446 Washington St",
    "sg:city": "Wellesley",
    "sg:classifiers": [
      {
        "category": "Restaurant",
        "type": "Food \u0026 Drink"
      }
    ],
    "sg:menulink": "http://www.allmenus.com/ma/wellesley/23553-tian-fu/menu/",
    "sg:phone": "+1 781 235 1111",
    "sg:postcode": "02482",
    "sg:province": "MA",
    "sg:tags": [
      "asian",
      "chinese"
    ],
    "wof:name": "Tian Fu",
    "wof:placetype": "venue"
  },
  "geometry": {"coordinates":[-71.283884,42.304458],"type":"Point"}
}
