{
  "type": "Feature",
  "properties": {
    "iso:country":"US",
    "sg:address":"446 Washington St",
    "sg:city":"Wellesley",
    "sg:classifiers":[
        {
            "category":"Restaurant",
            "type":"Food & Drink"
        }
    ],
    "sg:menulink":"http://www.allmenus.com/ma/wellesley/23553-tian-fu/menu/",
    "sg:phone":"+1 781 235 1111",
    "sg:postcode":"02482",
    "sg:province":"MA",
    "sg:tags":[
        "asian",
        "chinese"
    ],
    "wof:name":"Tian Fu",
    "wof:placetype":"venue"
},
  "geometry": {"coordinates":[-71.283884,42.304458],"type":"Point"}
}