{
  "type": "Feature",
  "properties": {
    "addr:full":"589 Westfield St West Springfield MA 01089",
    "addr:housenumber":"589",
    "addr:postcode":"01089",
    "addr:street":"Westfield St",
    "iso:country":"US",
    "sg:address":"589 Westfield St",
    "sg:city":"West Springfield",
    "sg:classifiers":[
        {
            "category":"Personal",
            "subcategory":"Beauty Salon",
            "type":"Services"
        }
    ],
    "sg:phone":"+1 413 788 0158",
    "sg:postcode":"01089",
    "sg:province":"MA",
    "sg:tags":[
        "manicuring"
    ],
    "wof:name":"Foxy Nail Salon",
    "wof:placetype":"venue"
},
  "geometry": {"coordinates":[-72.634209,42.103777],"type":"Point"}
}