{
  "type": "Feature",
  "properties": {
    "iso:country":"US",
    "sg:address":"277 Garden St",
    "sg:city":"Feeding Hills",
    "sg:classifiers":[
        {
            "category":"Building & Trades",
            "subcategory":"Construction",
            "type":"Services"
        }
    ],
    "sg:phone":"+1 413 786 4081",
    "sg:postcode":"01030",
    "sg:province":"MA",
    "sg:tags":[
        "roofing",
        "contractor"
    ],
    "wof:name":"C D Roofing Contractor",
    "wof:placetype":"venue"
},
  "geometry": {"coordinates":[-72.65162100000001,42.062182],"type":"Point"}
}