{
  "type": "Feature",
  "properties": {
    "addr:full": "277 Garden St Feeding Hills MA 01030",
    "addr:housenumber": "277",
    "addr:postcode": "01030",
    "addr:street": "Garden St",
    "iso:country": "US",
    "sg:address": "277 Garden St",
    "sg:city": "Feeding Hills",
    "sg:classifiers": [
      {
        "category": "Building \u0026 Trades",
        "subcategory": "Construction",
        "type": "Services"
      }
    ],
    "sg:phone": "+1 413 786 4081",
    "sg:postcode": "01030",
    "sg:province": "MA",
    "sg:tags": [
      "roofing",
      "contractor"
    ],
    "wof:name": "C D Roofing Contractor",
    "wof:placetype": "venue"
  },
  "geometry": {"coordinates":[-72.651621,42.062182],"type":"Point"}
}
