{
  "type": "Feature",
  "properties": {
    "addr:full": "15 Oliver St Fitchburg MA 01420",
    "addr:housenumber": "15",
    "addr:postcode": "01420",
    "addr:street": "Oliver St",
    "iso:country": "US",
    "sg:address": "15 Oliver St",
    "sg:city": "Fitchburg",
    "sg:classifiers": [
      {
        "category": "Real Estate",
        "subcategory": "Architect",
        "type": "Services"
      }
    ],
    "sg:phone": "+1 978 343 9193",
    "sg:postcode": "01420",
    "sg:province": "MA",
    "sg:tags": [
      "specification",
      "architectural"
    ],
    "wof:name": "South Side Designs Inc",
    "wof:placetype": "venue"
  },
  "geometry": {"coordinates":[-71.799568,42.583517],"type":"Point"}
}
