{
  "type": "Feature",
  "properties": {
    "addr:full":"10 Liberty Sq Boston MA 02190",
    "addr:housenumber":"10",
    "addr:postcode":"02190",
    "addr:street":"Liberty Sq",
    "iso:country":"US",
    "sg:address":"10 Liberty Sq",
    "sg:city":"Boston",
    "sg:classifiers":[
        {
            "category":"Building & Trades",
            "subcategory":"Equipment Rental",
            "type":"Services"
        }
    ],
    "sg:phone":"+1 617 426 4116",
    "sg:postcode":"02190",
    "sg:province":"MA",
    "sg:tags":[
        "leasing"
    ],
    "sg:website":"www.ltileasing.com",
    "wof:name":"Lti Ventures Leasing Corp",
    "wof:placetype":"venue"
},
  "geometry": {"coordinates":[-70.929277,42.162969],"type":"Point"}
}