{
  "type": "Feature",
  "properties": {
    "iso:country":"US",
    "sg:address":"374 Trapelo Rd",
    "sg:city":"Belmont",
    "sg:classifiers":[
        {
            "category":"Shopping",
            "subcategory":"Gifts & Souvenirs",
            "type":"Retail Goods"
        }
    ],
    "sg:phone":"+1 617 489 8819",
    "sg:postcode":"02478",
    "sg:province":"MA",
    "sg:tags":[
        "cards",
        "greeting"
    ],
    "wof:name":"J's Discounted Quality Grtng",
    "wof:placetype":"venue"
},
  "geometry": {"coordinates":[-71.18464,42.385702],"type":"Point"}
}