{
  "type": "Feature",
  "properties": {
    "iso:country":"US",
    "sg:address":"159 Washington Cir",
    "sg:city":"Woburn",
    "sg:classifiers":[
        {
            "category":"Wholesale",
            "subcategory":"Machinery & Supplies",
            "type":"Manufacturing & Wholesale Goods"
        }
    ],
    "sg:phone":"+1   ",
    "sg:postcode":"01801",
    "sg:province":"MA",
    "sg:tags":[
        "excavation",
        "equipment",
        "industrial",
        "contractor"
    ],
    "wof:name":"John Novick Clean Out Service",
    "wof:placetype":"venue"
},
  "geometry": {"coordinates":[-71.121331,42.485667],"type":"Point"}
}