{
  "type": "Feature",
  "properties": {
    "addr:full": "159 Washington Cir Woburn MA 01801",
    "addr:housenumber": "159",
    "addr:postcode": "01801",
    "addr:street": "Washington Cir",
    "iso:country": "US",
    "sg:address": "159 Washington Cir",
    "sg:city": "Woburn",
    "sg:classifiers": [
      {
        "category": "Wholesale",
        "subcategory": "Machinery \u0026 Supplies",
        "type": "Manufacturing \u0026 Wholesale Goods"
      }
    ],
    "sg:phone": "+1   ",
    "sg:postcode": "01801",
    "sg:province": "MA",
    "sg:tags": [
      "excavation",
      "equipment",
      "industrial",
      "contractor"
    ],
    "wof:name": "John Novick Clean Out Service",
    "wof:placetype": "venue"
  },
  "geometry": {"coordinates":[-71.121331,42.485667],"type":"Point"}
}
