{
  "type": "Feature",
  "properties": {
    "addr:full": "310 William F McClellan Hwy East Boston MA 02128",
    "addr:housenumber": "310",
    "addr:postcode": "02128",
    "addr:street": "William F Mcclellan Hwy",
    "iso:country": "US",
    "sg:address": "310 William F McClellan Hwy",
    "sg:city": "East Boston",
    "sg:classifiers": [
      {
        "category": "Freight",
        "type": "Transportation"
      }
    ],
    "sg:phone": "+1 617 569 5900",
    "sg:postcode": "02128",
    "sg:province": "MA",
    "sg:website": "www.geo-logistics.com",
    "wof:name": "Geo Logistics America Inc",
    "wof:placetype": "venue"
  },
  "geometry": {"coordinates":[-71.019375,42.38614],"type":"Point"}
}
