{
  "type": "Feature",
  "properties": {
    "addr:full": "63 Concord Ave Milton MA 02186",
    "addr:housenumber": "63",
    "addr:postcode": "02186",
    "addr:street": "Concord Ave",
    "iso:country": "US",
    "sg:address": "63 Concord Ave",
    "sg:city": "Milton",
    "sg:classifiers": [
      {
        "category": "Professional",
        "subcategory": "Business Services",
        "type": "Services"
      }
    ],
    "sg:phone": "+1   ",
    "sg:postcode": "02186",
    "sg:province": "MA",
    "wof:name": "Jaz Design Inc",
    "wof:placetype": "venue"
  },
  "geometry": {"coordinates":[-71.099698,42.25945],"type":"Point"}
}
