{
  "type": "Feature",
  "properties": {
    "iso:country":"US",
    "sg:address":"327 Great Rd",
    "sg:city":"Bedford",
    "sg:classifiers":[
        {
            "category":"Shopping",
            "subcategory":"Hobbies, Toys, & Games",
            "type":"Retail Goods"
        }
    ],
    "sg:phone":"+1 781 271 9033",
    "sg:postcode":"01730",
    "sg:province":"MA",
    "wof:name":"K-B Toy Works",
    "wof:placetype":"venue"
},
  "geometry": {"coordinates":[-71.261942,42.48622],"type":"Point"}
}