{
  "type": "Feature",
  "properties": {
    "addr:full":"1875 Memorial Dr Chicopee MA 01020",
    "addr:housenumber":"1875",
    "addr:postcode":"01020",
    "addr:street":"Memorial Dr",
    "iso:country":"US",
    "sg:address":"1875 Memorial Dr",
    "sg:city":"Chicopee",
    "sg:classifiers":[
        {
            "category":"Food & Beverages",
            "subcategory":"Groceries & Convenience Stores",
            "type":"Retail Goods"
        }
    ],
    "sg:phone":"+1 413 532 3098",
    "sg:postcode":"01020",
    "sg:province":"MA",
    "sg:tags":[
        "grocer"
    ],
    "wof:name":"Neighbor's Variety",
    "wof:placetype":"venue"
},
  "geometry": {"coordinates":[-72.571242,42.209114],"type":"Point"}
}