{
  "type": "Feature",
  "properties": {
    "addr:full":"85 Holland St Somerville MA 02144",
    "addr:housenumber":"85",
    "addr:postcode":"02144",
    "addr:street":"Holland St",
    "iso:country":"US",
    "sg:address":"85 Holland St",
    "sg:city":"Somerville",
    "sg:classifiers":[
        {
            "category":"Retail",
            "subcategory":"Laundry & Dry Cleaning",
            "type":"Services"
        }
    ],
    "sg:phone":"+1   ",
    "sg:postcode":"02144",
    "sg:province":"MA",
    "sg:tags":[
        "drycleaning",
        "plant"
    ],
    "wof:name":"Sams Dry Clg & Alterations",
    "wof:placetype":"venue"
},
  "geometry": {"coordinates":[-71.124392,42.398884],"type":"Point"}
}