{
  "type": "Feature",
  "properties": {
    "addr:full": "30 Snows Ln Provincetown MA 02657",
    "addr:housenumber": "30",
    "addr:postcode": "02657",
    "addr:street": "Snows Ln",
    "iso:country": "US",
    "sg:address": "30 Snows Ln",
    "sg:city": "Provincetown",
    "sg:classifiers": [
      {
        "category": "Wholesale",
        "subcategory": "Seafood",
        "type": "Manufacturing \u0026 Wholesale Goods"
      }
    ],
    "sg:phone": "+1 508 487 4487",
    "sg:postcode": "02657",
    "sg:province": "MA",
    "wof:name": "Rod's Seafood",
    "wof:placetype": "venue"
  },
  "geometry": {"coordinates":[-70.19743,42.047992],"type":"Point"}
}
