{
  "type": "Feature",
  "properties": {
    "iso:country":"US",
    "sg:address":"66 Milton St",
    "sg:city":"Dedham",
    "sg:classifiers":[
        {
            "category":"Education",
            "subcategory":"Dance Studio",
            "type":"Public Place"
        }
    ],
    "sg:phone":"+1 781 251 6662",
    "sg:postcode":"02026",
    "sg:province":"MA",
    "sg:tags":[
        "instruction",
        "dancing"
    ],
    "wof:name":"Dance Explosion School",
    "wof:placetype":"venue"
},
  "geometry": {"coordinates":[-71.152434,42.245709],"type":"Point"}
}