{
  "type": "Feature",
  "properties": {
    "addr:full":"111 Lancaster St Worcester MA 01609",
    "addr:housenumber":"111",
    "addr:postcode":"01609",
    "addr:street":"Lancaster St",
    "iso:country":"US",
    "sg:address":"111 Lancaster St",
    "sg:city":"Worcester",
    "sg:classifiers":[
        {
            "category":"Retail",
            "subcategory":"Funeral Services",
            "type":"Services"
        }
    ],
    "sg:phone":"+1 508 756 4689",
    "sg:postcode":"01609",
    "sg:province":"MA",
    "sg:tags":[
        "director"
    ],
    "wof:name":"Athy Memorial Home",
    "wof:placetype":"venue"
},
  "geometry": {"coordinates":[-71.802171,42.275744],"type":"Point"}
}