{
  "type": "Feature",
  "properties": {
    "addr:full":"142 Marion Cir Ludlow MA 01056",
    "addr:housenumber":"142",
    "addr:postcode":"01056",
    "addr:street":"Marion Cir",
    "iso:country":"US",
    "sg:address":"142 Marion Cir",
    "sg:city":"Ludlow",
    "sg:classifiers":[
        {
            "category":"Building & Trades",
            "subcategory":"Construction",
            "type":"Services"
        }
    ],
    "sg:phone":"+1 413 547 8119",
    "sg:postcode":"01056",
    "sg:province":"MA",
    "sg:tags":[
        "roofing",
        "contractor"
    ],
    "wof:name":"Co-Op Roofing Inc",
    "wof:placetype":"venue"
},
  "geometry": {"coordinates":[-72.435312,42.17446],"type":"Point"}
}