{
  "type": "Feature",
  "properties": {
    "addr:full": "354 Waverly St Framingham MA 01702",
    "addr:housenumber": "354",
    "addr:postcode": "01702",
    "addr:street": "Waverly St",
    "iso:country": "US",
    "sg:address": "354 Waverly St",
    "sg:city": "Framingham",
    "sg:classifiers": [
      {
        "category": "Organizations",
        "subcategory": "Non-profit Organization",
        "type": "Services"
      }
    ],
    "sg:phone": "+1 508 620 1830",
    "sg:postcode": "01702",
    "sg:province": "MA",
    "sg:website": "www.smlegal.org",
    "wof:name": "South Middlesex Legal Svc",
    "wof:placetype": "venue"
  },
  "geometry": {"coordinates":[-71.415093,42.277109],"type":"Point"}
}
