{
  "type": "Feature",
  "properties": {
    "iso:country":"US",
    "sg:address":"101 Turner Rd",
    "sg:city":"Scituate",
    "sg:classifiers":[
        {
            "category":"Professional",
            "subcategory":"Art Services",
            "type":"Services"
        }
    ],
    "sg:phone":"+1   ",
    "sg:postcode":"02066",
    "sg:province":"MA",
    "sg:tags":[
        "commercial",
        "design"
    ],
    "wof:name":"Satuit Studio",
    "wof:placetype":"venue"
},
  "geometry": {"coordinates":[-70.728026,42.209135],"type":"Point"}
}