{
  "type": "Feature",
  "properties": {
    "addr:full":"68 Pleasant St Newburyport MA 01950",
    "addr:housenumber":"68",
    "addr:postcode":"01950",
    "addr:street":"Pleasant St",
    "iso:country":"US",
    "sg:address":"68 Pleasant St",
    "sg:city":"Newburyport",
    "sg:classifiers":[
        {
            "category":"Insurance",
            "subcategory":"Insurance Agent",
            "type":"Services"
        }
    ],
    "sg:phone":"+1 978 465 2700",
    "sg:postcode":"01950",
    "sg:province":"MA",
    "wof:name":"Peter L Chetsas Insurance",
    "wof:placetype":"venue"
},
  "geometry": {"coordinates":[-70.872764,42.811092],"type":"Point"}
}