{
  "type": "Feature",
  "properties": {
    "iso:country":"US",
    "sg:address":"4 Washington Ave",
    "sg:city":"Buzzards Bay",
    "sg:classifiers":[
        {
            "category":"Personal",
            "subcategory":"Shoe Repair & Shine",
            "type":"Services"
        }
    ],
    "sg:phone":"+1   ",
    "sg:postcode":"02532",
    "sg:province":"MA",
    "sg:tags":[
        "parlor"
    ],
    "wof:name":"New York Shoe Repr Bzzards Bay",
    "wof:placetype":"venue"
},
  "geometry": {"coordinates":[-70.616434,41.745744],"type":"Point"}
}