{
  "type": "Feature",
  "properties": {
    "addr:full": "253 E Main St Orange MA 01364",
    "addr:housenumber": "253",
    "addr:postcode": "01364",
    "addr:street": "E Main St",
    "iso:country": "US",
    "ovtr:label": "Hadsel Insurance, 253 E Main St Orange MA US",
    "ovtr:similarity": 2.2587890625,
    "sg:address": "253 E Main St",
    "sg:city": "Orange",
    "sg:classifiers": [
      {
        "category": "Insurance",
        "subcategory": "Insurance Agent",
        "type": "Services"
      }
    ],
    "sg:phone": "+1 978 544 7806",
    "sg:postcode": "01364",
    "sg:province": "MA",
    "wof:name": "Hadsel Insurance",
    "wof:placetype": "venue"
  },
  "geometry": {"coordinates":[-72.298657,42.588534],"type":"Point"}
}
