{
  "type": "Feature",
  "properties": {
    "iso:country":"US",
    "sg:address":"157 Massachusetts Ave Ste A",
    "sg:city":"Boston",
    "sg:classifiers":[
        {
            "category":"Fast Food",
            "type":"Food & Drink"
        }
    ],
    "sg:phone":"+1 617 236 1550",
    "sg:postcode":"02115",
    "sg:province":"MA",
    "sg:website":"www.wendys.com/",
    "wof:name":"Wendy's Old Fashioned Hamburgers",
    "wof:placetype":"venue"
},
  "geometry": {"coordinates":[-71.087341,42.34648],"type":"Point"}
}