{
  "type": "Feature",
  "properties": {
    "iso:country":"US",
    "sg:address":"514 Pearl St",
    "sg:city":"Gardner",
    "sg:classifiers":[
        {
            "category":"Building & Trades",
            "subcategory":"Construction",
            "type":"Services"
        }
    ],
    "sg:phone":"+1 978 632 2990",
    "sg:postcode":"01440",
    "sg:province":"MA",
    "sg:tags":[
        "concrete",
        "contractor"
    ],
    "wof:name":"C & R Concrete Ready Mix",
    "wof:placetype":"venue"
},
  "geometry": {"coordinates":[-71.961956,42.587658],"type":"Point"}
}