{
  "type": "Feature",
  "properties": {
    "addr:full": "170 Main St Tewksbury MA 01876",
    "addr:housenumber": "170",
    "addr:postcode": "01876",
    "addr:street": "Main St",
    "iso:country": "US",
    "sg:address": "170 Main St",
    "sg:city": "Tewksbury",
    "sg:classifiers": [
      {
        "category": "Professional",
        "subcategory": "Engineering",
        "type": "Services"
      }
    ],
    "sg:phone": "+1 978 851 0801",
    "sg:postcode": "01876",
    "sg:province": "MA",
    "sg:tags": [
      "engineer"
    ],
    "sg:website": "www.newtechsolutions.com",
    "wof:name": "New Technology Solutions",
    "wof:placetype": "venue"
  },
  "geometry": {"coordinates":[-71.268423,42.626031],"type":"Point"}
}
