{
  "type": "Feature",
  "properties": {
    "iso:country":"US",
    "sg:address":"47 Middlesex Rd",
    "sg:city":"Tyngsboro",
    "sg:classifiers":[
        {
            "category":"Autos & Motor Vehicles",
            "subcategory":"Auto Supplies",
            "type":"Retail Goods"
        },
        {
            "category":"Manufacturing",
            "subcategory":"Tools & Machinery",
            "type":"Manufacturing & Wholesale Goods"
        }
    ],
    "sg:phone":"+1 978 649 6584",
    "sg:postcode":"01879",
    "sg:province":"MA",
    "sg:tags":[
        "equipment",
        "hydraulic",
        "automotive",
        "repair"
    ],
    "wof:name":"Auto Craft Enterprises Inc",
    "wof:placetype":"venue"
},
  "geometry": {"coordinates":[-71.403143,42.657177],"type":"Point"}
}