{
  "type": "Feature",
  "properties": {
    "addr:full":"11 North Ave Abington MA 02351",
    "addr:housenumber":"11",
    "addr:postcode":"02351",
    "addr:street":"North Ave",
    "iso:country":"US",
    "sg:address":"11 North Ave",
    "sg:city":"Abington",
    "sg:classifiers":[
        {
            "category":"Retail",
            "subcategory":"Repair Shop",
            "type":"Services"
        }
    ],
    "sg:phone":"+1 781 878 5338",
    "sg:postcode":"02351",
    "sg:province":"MA",
    "sg:tags":[
        "television",
        "radio"
    ],
    "wof:name":"Ken's TV",
    "wof:placetype":"venue"
},
  "geometry": {"coordinates":[-70.947489,42.128799],"type":"Point"}
}