{
  "type": "Feature",
  "properties": {
    "addr:full":"12 Erik Rd Medfield MA 02052",
    "addr:housenumber":"12",
    "addr:postcode":"02052",
    "addr:street":"Erik Rd",
    "iso:country":"US",
    "sg:address":"12 Erik Rd",
    "sg:city":"Medfield",
    "sg:classifiers":[
        {
            "category":"Manufacturing",
            "subcategory":"Tools & Machinery",
            "type":"Manufacturing & Wholesale Goods"
        }
    ],
    "sg:phone":"+1 508 359 8688",
    "sg:postcode":"02052",
    "sg:province":"MA",
    "sg:tags":[
        "equipment",
        "hospital",
        "supply"
    ],
    "wof:name":"Bay Medco",
    "wof:placetype":"venue"
},
  "geometry": {"coordinates":[-71.298953,42.199104],"type":"Point"}
}