{
  "type": "Feature",
  "properties": {
    "iso:country":"US",
    "sg:address":"69 Newbury St 2nd Floor",
    "sg:city":"Boston",
    "sg:classifiers":[
        {
            "category":"Real Estate",
            "subcategory":"Real Estate Services",
            "type":"Services"
        },
        {
            "category":"Real Estate",
            "subcategory":"Real Estate Agent",
            "type":"Services"
        }
    ],
    "sg:phone":"+1 617 833 3376",
    "sg:postcode":"02116",
    "sg:province":"MA",
    "sg:website":"www.joeschutt.com",
    "wof:name":"Joe Schutt - Gibson Sotheby's International Realty",
    "wof:placetype":"venue"
},
  "geometry": {"coordinates":[-71.07428299999999,42.352085],"type":"Point"}
}