{
  "type": "Feature",
  "properties": {
    "addr:full":"5 Front St Shirley MA 01464",
    "addr:housenumber":"5",
    "addr:postcode":"01464",
    "addr:street":"Front St",
    "iso:country":"US",
    "sg:address":"5 Front St",
    "sg:city":"Shirley",
    "sg:classifiers":[
        {
            "category":"Retail",
            "subcategory":"Repair Shop",
            "type":"Services"
        }
    ],
    "sg:phone":"+1 978 425 0363",
    "sg:postcode":"01464",
    "sg:province":"MA",
    "sg:tags":[
        "player",
        "recorder",
        "video"
    ],
    "wof:name":"Village Video",
    "wof:placetype":"venue"
},
  "geometry": {"coordinates":[-71.652969,42.544396],"type":"Point"}
}