{
  "type": "Feature",
  "properties": {
    "addr:full": "50 Boston Rd Lowell MA 01852",
    "addr:housenumber": "50",
    "addr:postcode": "01852",
    "addr:street": "Boston Rd",
    "iso:country": "US",
    "sg:address": "50 Boston Rd",
    "sg:city": "Lowell",
    "sg:classifiers": [
      {
        "category": "Building \u0026 Trades",
        "subcategory": "Cleaning \u0026 Sanitation",
        "type": "Services"
      },
      {
        "category": "Home \u0026 Garden",
        "subcategory": "Building Materials",
        "type": "Retail Goods"
      },
      {
        "category": "Building \u0026 Trades",
        "subcategory": "Construction",
        "type": "Services"
      }
    ],
    "sg:phone": "+1 978 256 0092",
    "sg:postcode": "01852",
    "sg:province": "MA",
    "sg:tags": [
      "roofing",
      "gutter",
      "contractor",
      "downspouts",
      "siding",
      "industrial",
      "contractors-commercial"
    ],
    "sg:website": "http://www.negutterkings.com",
    "wof:name": "New England Gutter Kings",
    "wof:placetype": "venue"
  },
  "geometry": {"coordinates":[-71.313431,42.622849],"type":"Point"}
}
