{
  "type": "Feature",
  "properties": {
    "iso:country":"US",
    "sg:address":"50 Boston Rd",
    "sg:city":"Lowell",
    "sg:classifiers":[
        {
            "category":"Building & Trades",
            "subcategory":"Cleaning & Sanitation",
            "type":"Services"
        },
        {
            "category":"Home & Garden",
            "subcategory":"Building Materials",
            "type":"Retail Goods"
        },
        {
            "category":"Building & Trades",
            "subcategory":"Construction",
            "type":"Services"
        }
    ],
    "sg:phone":"+1 978 256 0092",
    "sg:postcode":"01852",
    "sg:province":"MA",
    "sg:tags":[
        "roofing",
        "gutter",
        "contractor",
        "downspouts",
        "siding",
        "industrial",
        "contractors-commercial"
    ],
    "sg:website":"http://www.negutterkings.com",
    "wof:name":"New England Gutter Kings",
    "wof:placetype":"venue"
},
  "geometry": {"coordinates":[-71.31343099999999,42.622849],"type":"Point"}
}