{
  "type": "Feature",
  "properties": {
    "addr:full":"198 Belmont Rd West Harwich MA 02671",
    "addr:housenumber":"198",
    "addr:postcode":"02671",
    "addr:street":"Belmont Rd",
    "iso:country":"US",
    "sg:address":"198 Belmont Rd",
    "sg:city":"West Harwich",
    "sg:classifiers":[
        {
            "category":"Personal",
            "type":"Services"
        }
    ],
    "sg:phone":"+1   ",
    "sg:postcode":"02671",
    "sg:province":"MA",
    "wof:name":"Perennial Parties",
    "wof:placetype":"venue"
},
  "geometry": {"coordinates":[-70.11750600000001,41.669797],"type":"Point"}
}