{
  "type": "Feature",
  "properties": {
    "addr:full": "7 Bartlet St Andover MA 01810",
    "addr:housenumber": "7",
    "addr:postcode": "01810",
    "addr:street": "Bartlet St",
    "iso:country": "US",
    "sg:address": "7 Bartlet St",
    "sg:city": "Andover",
    "sg:classifiers": [
      {
        "category": "Personal",
        "subcategory": "Shoe Repair \u0026 Shine",
        "type": "Services"
      }
    ],
    "sg:phone": "+1 978 474 9320",
    "sg:postcode": "01810",
    "sg:province": "MA",
    "sg:tags": [
      "repairing",
      "parlor",
      "boot"
    ],
    "wof:name": "Paul's Shoe Repair",
    "wof:placetype": "venue"
  },
  "geometry": {"coordinates":[-71.138539,42.656514],"type":"Point"}
}
