{
  "type": "Feature",
  "properties": {
    "iso:country":"US",
    "sg:address":"8 Nashua St",
    "sg:city":"Worcester",
    "sg:classifiers":[
        {
            "category":"Building & Trades",
            "subcategory":"Electrical",
            "type":"Services"
        }
    ],
    "sg:phone":"+1 508 793 1999",
    "sg:postcode":"01605",
    "sg:province":"MA",
    "sg:tags":[
        "electric",
        "contractor"
    ],
    "wof:name":"Wave Optic Communications",
    "wof:placetype":"venue"
},
  "geometry": {"coordinates":[-71.798942,42.283603],"type":"Point"}
}