{
  "type": "Feature",
  "properties": {
    "iso:country":"US",
    "sg:address":"1177 Massachusetts Ave",
    "sg:city":"Arlington",
    "sg:classifiers":[
        {
            "category":"Retail",
            "subcategory":"Laundry & Dry Cleaning",
            "type":"Services"
        }
    ],
    "sg:phone":"+1 781 648 2471",
    "sg:postcode":"02476",
    "sg:province":"MA",
    "wof:name":"Brite Whites Laundromat",
    "wof:placetype":"venue"
},
  "geometry": {"coordinates":[-71.175979,42.423576],"type":"Point"}
}