{
  "type": "Feature",
  "properties": {
    "addr:full": "1177 Massachusetts Ave Arlington MA 02476",
    "addr:housenumber": "1177",
    "addr:postcode": "02476",
    "addr:street": "Massachusetts Ave",
    "iso:country": "US",
    "ovtr:label": "Brite White Laundromat, 1177 Massachusetts Ave Arlington MA US",
    "ovtr:similarity": 3.3928658962249756,
    "sg:address": "1177 Massachusetts Ave",
    "sg:city": "Arlington",
    "sg:classifiers": [
      {
        "category": "Retail",
        "subcategory": "Laundry \u0026 Dry Cleaning",
        "type": "Services"
      }
    ],
    "sg:phone": "+1 781 648 2471",
    "sg:postcode": "02476",
    "sg:province": "MA",
    "wof:name": "Brite Whites Laundromat",
    "wof:placetype": "venue"
  },
  "geometry": {"coordinates":[-71.175979,42.423576],"type":"Point"}
}
