{
  "type": "Feature",
  "properties": {
    "addr:full": "332 Harvard St Dorchester Ctr MA 02124",
    "addr:housenumber": "332",
    "addr:postcode": "02124",
    "addr:street": "Harvard St",
    "iso:country": "US",
    "sg:address": "332 Harvard St",
    "sg:city": "Dorchester Ctr",
    "sg:classifiers": [
      {
        "category": "Building \u0026 Trades",
        "subcategory": "Construction",
        "type": "Services"
      }
    ],
    "sg:phone": "+1 617 282 2753",
    "sg:postcode": "02124",
    "sg:province": "MA",
    "sg:tags": [
      "home",
      "improvement"
    ],
    "wof:name": "Jim's Construction Management",
    "wof:placetype": "venue"
  },
  "geometry": {"coordinates":[-71.089849,42.292589],"type":"Point"}
}
