{
  "type": "Feature",
  "properties": {
    "addr:full":"10 Garfield Ave Somerville MA 02145",
    "addr:housenumber":"10",
    "addr:postcode":"02145",
    "addr:street":"Garfield Ave",
    "iso:country":"US",
    "sg:address":"10 Garfield Ave",
    "sg:city":"Somerville",
    "sg:classifiers":[
        {
            "category":"Retail",
            "subcategory":"Repair Shop",
            "type":"Services"
        }
    ],
    "sg:phone":"+1 617 623 0600",
    "sg:postcode":"02145",
    "sg:province":"MA",
    "sg:tags":[
        "repairing",
        "piano",
        "refinishing"
    ],
    "wof:name":"Acme Piano Sales Co",
    "wof:placetype":"venue"
},
  "geometry": {"coordinates":[-71.085864,42.389878],"type":"Point"}
}