{
  "type": "Feature",
  "properties": {
    "iso:country":"US",
    "sg:address":"100 Doty Cir",
    "sg:city":"West Springfield",
    "sg:classifiers":[
        {
            "category":"Manufacturing",
            "subcategory":"Tools & Machinery",
            "type":"Manufacturing & Wholesale Goods"
        }
    ],
    "sg:phone":"+1 413 739 6627",
    "sg:postcode":"01089",
    "sg:province":"MA",
    "sg:tags":[
        "machine",
        "shop"
    ],
    "sg:website":"www.mutualprecision.com",
    "wof:name":"Mutual Precision Inc",
    "wof:placetype":"venue"
},
  "geometry": {"coordinates":[-72.625857,42.145701],"type":"Point"}
}