{
  "type": "Feature",
  "properties": {
    "addr:full": "67 Main St Medway MA 02053",
    "addr:housenumber": "67",
    "addr:postcode": "02053",
    "addr:street": "Main St",
    "iso:country": "US",
    "sg:address": "67 Main St",
    "sg:city": "Medway",
    "sg:classifiers": [
      {
        "category": "Restaurant",
        "type": "Food \u0026 Drink"
      }
    ],
    "sg:phone": "+1 508 533 5311",
    "sg:postcode": "02053",
    "sg:province": "MA",
    "wof:name": "Primos Italian Restaurant",
    "wof:placetype": "venue"
  },
  "geometry": {"coordinates":[-71.40602,42.152789],"type":"Point"}
}
