{
  "type": "Feature",
  "properties": {
    "addr:full": "192 Maplewood St Watertown MA 02472",
    "addr:housenumber": "192",
    "addr:postcode": "02472",
    "addr:street": "Maplewood St",
    "iso:country": "US",
    "sg:address": "192 Maplewood St",
    "sg:city": "Watertown",
    "sg:classifiers": [
      {
        "category": "Shopping",
        "subcategory": "Optical Goods",
        "type": "Retail Goods"
      }
    ],
    "sg:phone": "+1   ",
    "sg:postcode": "02472",
    "sg:province": "MA",
    "sg:tags": [
      "supply"
    ],
    "wof:name": "Cushing Square Opticians",
    "wof:placetype": "venue"
  },
  "geometry": {"coordinates":[-71.165074,42.373814],"type":"Point"}
}
