{
  "type": "Feature",
  "properties": {
    "addr:full": "297 Boston Post Rd Wayland MA 01778",
    "addr:housenumber": "297",
    "addr:postcode": "01778",
    "addr:street": "Boston Post Rd",
    "iso:country": "US",
    "sg:address": "297 Boston Post Rd",
    "sg:city": "Wayland",
    "sg:classifiers": [
      {
        "category": "Professional",
        "subcategory": "Advertising",
        "type": "Services"
      }
    ],
    "sg:phone": "+1 508 358 0845",
    "sg:postcode": "01778",
    "sg:province": "MA",
    "sg:tags": [
      "mail",
      "direct"
    ],
    "wof:name": "Wayland Pack \u0026 Ship",
    "wof:placetype": "venue"
  },
  "geometry": {"coordinates":[-71.368453,42.363121],"type":"Point"}
}
