{
  "type": "Feature",
  "properties": {
    "iso:country":"US",
    "sg:address":"71 Pleasant St",
    "sg:city":"Worcester",
    "sg:classifiers":[
        {
            "category":"Professional",
            "subcategory":"Management & Consulting",
            "type":"Services"
        }
    ],
    "sg:phone":"+1 508 421 4438",
    "sg:postcode":"01609",
    "sg:province":"MA",
    "sg:tags":[
        "marketing",
        "consultant"
    ],
    "wof:name":"Market Connections",
    "wof:placetype":"venue"
},
  "geometry": {"coordinates":[-71.805024,42.263765],"type":"Point"}
}