{
  "type": "Feature",
  "properties": {
    "addr:full":"173 Fairmount St Boston MA 02124",
    "addr:housenumber":"173",
    "addr:postcode":"02124",
    "addr:street":"Fairmount St",
    "iso:country":"US",
    "sg:address":"173 Fairmount St",
    "sg:city":"Boston",
    "sg:classifiers":[
        {
            "category":"Retail",
            "subcategory":"Repair Shop",
            "type":"Services"
        }
    ],
    "sg:phone":"+1   ",
    "sg:postcode":"02124",
    "sg:province":"MA",
    "wof:name":"Brooks Cleaning",
    "wof:placetype":"venue"
},
  "geometry": {"coordinates":[-71.07997400000001,42.279205],"type":"Point"}
}