{
  "type": "Feature",
  "properties": {
    "iso:country":"US",
    "sg:address":"79 Freeport St # 83",
    "sg:city":"Dorchester",
    "sg:classifiers":[
        {
            "category":"Retail",
            "subcategory":"Auto Rental",
            "type":"Services"
        },
        {
            "category":"Professional",
            "subcategory":"Lawyer & Legal Services",
            "type":"Services"
        }
    ],
    "sg:phone":"+1 617 282 3900",
    "sg:postcode":"02122",
    "sg:province":"MA",
    "sg:tags":[
        "car"
    ],
    "sg:website":"www.enterprise.com",
    "wof:name":"Enterprise Rent-A-Car",
    "wof:placetype":"venue"
},
  "geometry": {"coordinates":[-71.05753300000001,42.305642],"type":"Point"}
}