{
  "type": "Feature",
  "properties": {
    "addr:full": "124 Ashcroft Rd Medford MA 02155",
    "addr:housenumber": "124",
    "addr:postcode": "02155",
    "addr:street": "Ashcroft Rd",
    "iso:country": "US",
    "sg:address": "124 Ashcroft Rd",
    "sg:city": "Medford",
    "sg:classifiers": [
      {
        "category": "Building \u0026 Trades",
        "subcategory": "Construction",
        "type": "Services"
      }
    ],
    "sg:phone": "+1   ",
    "sg:postcode": "02155",
    "sg:province": "MA",
    "sg:tags": [
      "house"
    ],
    "wof:name": "Gautreau \u0026 Sons Construction",
    "wof:placetype": "venue"
  },
  "geometry": {"coordinates":[-71.108689,42.424889],"type":"Point"}
}
