{
  "type": "Feature",
  "properties": {
    "iso:country":"US",
    "sg:address":"124 Ashcroft Rd",
    "sg:city":"Medford",
    "sg:classifiers":[
        {
            "category":"Building & Trades",
            "subcategory":"Construction",
            "type":"Services"
        }
    ],
    "sg:phone":"+1   ",
    "sg:postcode":"02155",
    "sg:province":"MA",
    "sg:tags":[
        "house"
    ],
    "wof:name":"Gautreau & Sons Construction",
    "wof:placetype":"venue"
},
  "geometry": {"coordinates":[-71.108689,42.424889],"type":"Point"}
}