{
  "type": "Feature",
  "properties": {
    "iso:country":"US",
    "sg:address":"15 Carr Rd",
    "sg:city":"Saugus",
    "sg:classifiers":[
        {
            "category":"Building & Trades",
            "subcategory":"Construction",
            "type":"Services"
        },
        {
            "category":"Manufacturing",
            "subcategory":"Building Materials",
            "type":"Manufacturing & Wholesale Goods"
        },
        {
            "category":"Manufacturing",
            "subcategory":"Glass & Minerals",
            "type":"Manufacturing & Wholesale Goods"
        }
    ],
    "sg:phone":"+1 781 233 2929",
    "sg:postcode":"01906",
    "sg:province":"MA",
    "sg:tags":[
        "plate",
        "installation",
        "repair",
        "windows-repair",
        "glazier",
        "window",
        "replacement"
    ],
    "wof:name":"Atlantic Window Co Inc",
    "wof:placetype":"venue"
},
  "geometry": {"coordinates":[-70.990497,42.448974],"type":"Point"}
}