{
  "type": "Feature",
  "properties": {
    "iso:country":"US",
    "sg:address":"7 Lincoln St",
    "sg:city":"Webster",
    "sg:classifiers":[
        {
            "category":"Retail",
            "subcategory":"Auto Repair",
            "type":"Services"
        }
    ],
    "sg:phone":"+1 508 943 3995",
    "sg:postcode":"01570",
    "sg:province":"MA",
    "sg:tags":[
        "repairing",
        "automobile"
    ],
    "wof:name":"Automotive Performance Systems",
    "wof:placetype":"venue"
},
  "geometry": {"coordinates":[-71.87415799999999,42.055312],"type":"Point"}
}