{
  "type": "Feature",
  "properties": {
    "addr:full": "200 Cushing St Stoughton MA 02072",
    "addr:housenumber": "200",
    "addr:postcode": "02072",
    "addr:street": "Cushing St",
    "iso:country": "US",
    "sg:address": "200 Cushing St",
    "sg:city": "Stoughton",
    "sg:classifiers": [
      {
        "category": "Wholesale",
        "subcategory": "Machinery \u0026 Supplies",
        "type": "Manufacturing \u0026 Wholesale Goods"
      }
    ],
    "sg:phone": "+1 781 344 1303",
    "sg:postcode": "02072",
    "sg:province": "MA",
    "sg:tags": [
      "equipment",
      "irrigation",
      "system"
    ],
    "wof:name": "Mass Irrigation Inc",
    "wof:placetype": "venue"
  },
  "geometry": {"coordinates":[-71.114602,42.129581],"type":"Point"}
}
