{
  "type": "Feature",
  "properties": {
    "addr:full": "13 Brookstone Rd Lakeville MA 02347",
    "addr:housenumber": "13",
    "addr:postcode": "02347",
    "addr:street": "Brookstone Rd",
    "iso:country": "US",
    "sg:address": "13 Brookstone Rd",
    "sg:city": "Lakeville",
    "sg:classifiers": [
      {
        "category": "Home \u0026 Garden",
        "subcategory": "Home Furnishings",
        "type": "Retail Goods"
      }
    ],
    "sg:phone": "+1 508 947 6447",
    "sg:postcode": "02347",
    "sg:province": "MA",
    "wof:name": "Darling Window Treatments",
    "wof:placetype": "venue"
  },
  "geometry": {"coordinates":[-70.971246,41.798072],"type":"Point"}
}
