{
  "type": "Feature",
  "properties": {
    "iso:country":"US",
    "sg:address":"13 Brookstone Rd",
    "sg:city":"Lakeville",
    "sg:classifiers":[
        {
            "category":"Home & Garden",
            "subcategory":"Home Furnishings",
            "type":"Retail Goods"
        }
    ],
    "sg:phone":"+1 508 947 6447",
    "sg:postcode":"02347",
    "sg:province":"MA",
    "wof:name":"Darling Window Treatments",
    "wof:placetype":"venue"
},
  "geometry": {"coordinates":[-70.97124599999999,41.798072],"type":"Point"}
}