{
  "type": "Feature",
  "properties": {
    "iso:country":"US",
    "sg:address":"500 Worcester Rd",
    "sg:city":"Framingham",
    "sg:classifiers":[
        {
            "category":"Autos & Motor Vehicles",
            "subcategory":"Automobile Sales",
            "type":"Retail Goods"
        }
    ],
    "sg:phone":"+1 781 239 0888",
    "sg:postcode":"01702",
    "sg:province":"MA",
    "sg:tags":[
        "car",
        "dealer"
    ],
    "wof:name":"Acura Of Framingham",
    "wof:placetype":"venue"
},
  "geometry": {"coordinates":[-71.41693100000001,42.29767],"type":"Point"}
}