{
  "type": "Feature",
  "properties": {
    "iso:country":"US",
    "sg:address":"70 Finnell Dr",
    "sg:city":"Weymouth",
    "sg:classifiers":[
        {
            "category":"Retail",
            "subcategory":"Repair Shop",
            "type":"Services"
        }
    ],
    "sg:phone":"+1 781 335 5557",
    "sg:postcode":"02188",
    "sg:province":"MA",
    "sg:tags":[
        "refrigerating"
    ],
    "sg:website":"www.minuseleven.com",
    "wof:name":"Minus-Eleven Inc",
    "wof:placetype":"venue"
},
  "geometry": {"coordinates":[-70.968036,42.189424],"type":"Point"}
}