{
  "type": "Feature",
  "properties": {
    "iso:country":"US",
    "sg:address":"781 Shoemaker Ln",
    "sg:city":"Feeding Hills",
    "sg:classifiers":[
        {
            "category":"Shopping",
            "subcategory":"Bicycles & Sporting Goods",
            "type":"Retail Goods"
        }
    ],
    "sg:phone":"+1 413 786 2088",
    "sg:postcode":"01030",
    "sg:province":"MA",
    "sg:tags":[
        "equipment",
        "golf",
        "supply"
    ],
    "wof:name":"St Anne Country Club",
    "wof:placetype":"venue"
},
  "geometry": {"coordinates":[-72.66561799999999,42.056868],"type":"Point"}
}