{
  "type": "Feature",
  "properties": {
    "addr:full": "230 S Main St Middleton MA 01949",
    "addr:housenumber": "230",
    "addr:postcode": "01949",
    "addr:street": "S Main St",
    "iso:country": "US",
    "sg:address": "230 S Main St",
    "sg:city": "Middleton",
    "sg:classifiers": [
      {
        "category": "Home \u0026 Garden",
        "subcategory": "Building Materials",
        "type": "Retail Goods"
      },
      {
        "category": "Home \u0026 Garden",
        "subcategory": "Home Furnishings",
        "type": "Retail Goods"
      },
      {
        "category": "Wholesale",
        "subcategory": "Plants",
        "type": "Manufacturing \u0026 Wholesale Goods"
      },
      {
        "category": "Arts \u0026 Performance",
        "subcategory": "Opera",
        "type": "Entertainment"
      }
    ],
    "sg:phone": "+1 888 801 3635",
    "sg:postcode": "01949",
    "sg:province": "MA",
    "sg:tags": [
      "sunroom",
      "builder",
      "equipment",
      "greenhouse",
      "screen",
      "solarium",
      "enclosure"
    ],
    "sg:website": "http://sunspacesma.fourseasonssunrooms.com/default.aspx",
    "wof:name": "Four Seasons Sunrooms",
    "wof:placetype": "venue"
  },
  "geometry": {"coordinates":[-70.997749,42.577229],"type":"Point"}
}
