{
  "type": "Feature",
  "properties": {
    "addr:full": "32 Central St Southbridge MA 01550",
    "addr:housenumber": "32",
    "addr:postcode": "01550",
    "addr:street": "Central St",
    "iso:country": "US",
    "sg:address": "32 Central St",
    "sg:city": "Southbridge",
    "sg:classifiers": [
      {
        "category": "Shopping",
        "subcategory": "Department Store",
        "type": "Retail Goods"
      }
    ],
    "sg:phone": "+1 508 765 0171",
    "sg:postcode": "01550",
    "sg:province": "MA",
    "wof:name": "Crystal's House of Bargains - CLOSED",
    "wof:placetype": "venue"
  },
  "geometry": {"coordinates":[-72.033302,42.0756],"type":"Point"}
}
