{
  "type": "Feature",
  "properties": {
    "addr:full": "56 Underpass Rd Brewster MA 02631",
    "addr:housenumber": "56",
    "addr:postcode": "02631",
    "addr:street": "Underpass Rd",
    "iso:country": "US",
    "ovtr:label": "Brewster Veterinary Hospital, 56 Underpass Rd Brewster MA US",
    "ovtr:similarity": 2.5970449447631836,
    "sg:address": "56 Underpass Rd",
    "sg:city": "Brewster",
    "sg:classifiers": [
      {
        "category": "Retail",
        "subcategory": "Veterinary Services",
        "type": "Services"
      }
    ],
    "sg:phone": "+1 508 896 2540",
    "sg:postcode": "02631",
    "sg:province": "MA",
    "sg:tags": [
      "clinic",
      "veterinarian",
      "hospital"
    ],
    "wof:name": "Brewster Veterinary Hospital",
    "wof:placetype": "venue"
  },
  "geometry": {"coordinates":[-70.066319,41.763919],"type":"Point"}
}
