{
  "type": "Feature",
  "properties": {
    "iso:country":"US",
    "sg:address":"56 Underpass Rd",
    "sg:city":"Brewster",
    "sg:classifiers":[
        {
            "category":"Retail",
            "subcategory":"Veterinary Services",
            "type":"Services"
        }
    ],
    "sg:phone":"+1 508 896 2540",
    "sg:postcode":"02631",
    "sg:province":"MA",
    "sg:tags":[
        "clinic",
        "veterinarian",
        "hospital"
    ],
    "wof:name":"Brewster Veterinary Hospital",
    "wof:placetype":"venue"
},
  "geometry": {"coordinates":[-70.06631899999999,41.763919],"type":"Point"}
}