{
  "type": "Feature",
  "properties": {
    "addr:full":"105 Gidney Rd Orange MA 01364",
    "addr:housenumber":"105",
    "addr:postcode":"01364",
    "addr:street":"Gidney Rd",
    "iso:country":"US",
    "sg:address":"105 Gidney Rd",
    "sg:city":"Orange",
    "sg:classifiers":[
        {
            "category":"Autos & Motor Vehicles",
            "subcategory":"Automobile Sales",
            "type":"Retail Goods"
        }
    ],
    "sg:phone":"+1 978 544 6202",
    "sg:postcode":"01364",
    "sg:province":"MA",
    "sg:tags":[
        "car",
        "dealer"
    ],
    "wof:name":"Bob's Used Car",
    "wof:placetype":"venue"
},
  "geometry": {"coordinates":[-72.34626299999999,42.57981],"type":"Point"}
}