{
  "type": "Feature",
  "properties": {
    "addr:full": "100 Foxboro Blvd Foxboro MA 02035",
    "addr:housenumber": "100",
    "addr:postcode": "02035",
    "addr:street": "Foxboro Blvd",
    "iso:country": "US",
    "sg:address": "100 Foxboro Blvd",
    "sg:city": "Foxboro",
    "sg:classifiers": [
      {
        "category": "Professional",
        "subcategory": "Engineering",
        "type": "Services"
      }
    ],
    "sg:phone": "+1 508 698 3034",
    "sg:postcode": "02035",
    "sg:province": "MA",
    "sg:tags": [
      "engineer"
    ],
    "sg:website": "www.westonandsampson.com",
    "wof:name": "Weston \u0026 Sampson Engineers Inc",
    "wof:placetype": "venue"
  },
  "geometry": {"coordinates":[-71.235325,42.041866],"type":"Point"}
}
