{
  "type": "Feature",
  "properties": {
    "addr:full": "58 Hudson Rd Sudbury MA 01776",
    "addr:housenumber": "58",
    "addr:postcode": "01776",
    "addr:street": "Hudson Rd",
    "iso:country": "US",
    "sg:address": "58 Hudson Rd",
    "sg:city": "Sudbury",
    "sg:classifiers": [
      {
        "category": "Professional",
        "subcategory": "Management \u0026 Consulting",
        "type": "Services"
      }
    ],
    "sg:phone": "+1   ",
    "sg:postcode": "01776",
    "sg:province": "MA",
    "sg:tags": [
      "business"
    ],
    "wof:name": "Lealholm Consulting Corp",
    "wof:placetype": "venue"
  },
  "geometry": {"coordinates":[-71.415458,42.383072],"type":"Point"}
}
