{
  "type": "Feature",
  "properties": {
    "iso:country":"US",
    "sg:address":"58 Hudson Rd",
    "sg:city":"Sudbury",
    "sg:classifiers":[
        {
            "category":"Professional",
            "subcategory":"Management & Consulting",
            "type":"Services"
        }
    ],
    "sg:phone":"+1   ",
    "sg:postcode":"01776",
    "sg:province":"MA",
    "sg:tags":[
        "business"
    ],
    "wof:name":"Lealholm Consulting Corp",
    "wof:placetype":"venue"
},
  "geometry": {"coordinates":[-71.415458,42.383072],"type":"Point"}
}