{
  "type": "Feature",
  "properties": {
    "addr:full": "174 Great Western Rd Harwich MA 02645",
    "addr:housenumber": "174",
    "addr:postcode": "02645",
    "addr:street": "Great Western Rd",
    "iso:country": "US",
    "sg:address": "174 Great Western Rd",
    "sg:city": "Harwich",
    "sg:classifiers": [
      {
        "category": "Health Services",
        "subcategory": "Medical Lab",
        "type": "Services"
      }
    ],
    "sg:phone": "+1 508 430 2553",
    "sg:postcode": "02645",
    "sg:province": "MA",
    "sg:tags": [
      "laboratory"
    ],
    "wof:name": "Seabreeze Dental Ceramics",
    "wof:placetype": "venue"
  },
  "geometry": {"coordinates":[-70.114122,41.687566],"type":"Point"}
}
