{
  "type": "Feature",
  "properties": {
    "iso:country":"US",
    "sg:address":"34 Wigwam Cir",
    "sg:city":"Watertown",
    "sg:classifiers":[
        {
            "category":"Professional",
            "subcategory":"Lawyer & Legal Services",
            "type":"Services"
        }
    ],
    "sg:phone":"+1 617 924 3020",
    "sg:postcode":"02474",
    "sg:province":"MA",
    "sg:tags":[
        "attorney"
    ],
    "wof:name":"Iuliano & Concannon",
    "wof:placetype":"venue"
},
  "geometry": {"coordinates":[-71.171999,42.431549],"type":"Point"}
}