{
  "type": "Feature",
  "properties": {
    "addr:full":"31 Mass Ave Boston MA 02115",
    "addr:housenumber":"31",
    "addr:postcode":"02115",
    "addr:street":"Mass Ave",
    "iso:country":"US",
    "sg:address":"31 Mass Ave",
    "sg:city":"Boston",
    "sg:classifiers":[
        {
            "category":"Shopping",
            "subcategory":"Pets & Pet Supplies",
            "type":"Retail Goods"
        }
    ],
    "sg:phone":"+1 978 302 7867",
    "sg:postcode":"02115",
    "sg:province":"MA",
    "sg:tags":[
        "walker",
        "dog"
    ],
    "wof:name":"City Paws Boston",
    "wof:placetype":"venue"
},
  "geometry": {"coordinates":[-71.089279,42.350367],"type":"Point"}
}