{
  "type": "Feature",
  "properties": {
    "addr:full":"15 Railroad Ave Swampscott MA 01907",
    "addr:housenumber":"15",
    "addr:postcode":"01907",
    "addr:street":"Railroad Ave",
    "iso:country":"US",
    "sg:address":"15 Railroad Ave",
    "sg:city":"Swampscott",
    "sg:classifiers":[
        {
            "category":"Bars & Pubs",
            "subcategory":"Lounge",
            "type":"Food & Drink"
        },
        {
            "category":"Coffee & Tea",
            "type":"Food & Drink"
        },
        {
            "category":"Restaurant",
            "type":"Food & Drink"
        }
    ],
    "sg:phone":"+1 781 581 7552",
    "sg:postcode":"01907",
    "sg:province":"MA",
    "sg:tags":[
        "espresso",
        "cocktail",
        "italian"
    ],
    "wof:name":"Paradise Cafe",
    "wof:placetype":"venue"
},
  "geometry": {"coordinates":[-70.922875,42.473155],"type":"Point"}
}