{
  "type": "Feature",
  "properties": {
    "addr:full": "84 Border St Whitinsville MA 01588",
    "addr:housenumber": "84",
    "addr:postcode": "01588",
    "addr:street": "Border St",
    "iso:country": "US",
    "ovtr:label": "Village variety, 84 Border St Whitinsville MA US",
    "ovtr:similarity": 2.7306020259857178,
    "sg:address": "84 Border St",
    "sg:city": "Whitinsville",
    "sg:classifiers": [
      {
        "category": "Shopping",
        "subcategory": "Discount \u0026 Variety Stores",
        "type": "Retail Goods"
      }
    ],
    "sg:phone": "+1 508 234 3110",
    "sg:postcode": "01588",
    "sg:province": "MA",
    "wof:name": "Village Variety",
    "wof:placetype": "venue"
  },
  "geometry": {"coordinates":[-71.683342,42.114133],"type":"Point"}
}
