{
  "type": "Feature",
  "properties": {
    "addr:full": "5 Worcester Sq Roxbury MA 02118",
    "addr:housenumber": "5",
    "addr:postcode": "02118",
    "addr:street": "Worcester Sq",
    "iso:country": "US",
    "sg:address": "5 Worcester Sq",
    "sg:city": "Roxbury",
    "sg:classifiers": [
      {
        "category": "Retail",
        "subcategory": "Laundry \u0026 Dry Cleaning",
        "type": "Services"
      }
    ],
    "sg:phone": "+1 617 267 6673",
    "sg:postcode": "02118",
    "sg:province": "MA",
    "wof:name": "Andy's Cleaners \u0026 Laundry",
    "wof:placetype": "venue"
  },
  "geometry": {"coordinates":[-71.075286,42.336779],"type":"Point"}
}
