{
  "type": "Feature",
  "properties": {
    "addr:full": "100 N Washington St Boston MA 02114",
    "addr:housenumber": "100",
    "addr:postcode": "02114",
    "addr:street": "N Washington St",
    "iso:country": "US",
    "sg:address": "100 N Washington St",
    "sg:city": "Boston",
    "sg:classifiers": [
      {
        "category": "Professional",
        "type": "Services"
      }
    ],
    "sg:phone": "+1 617 248 9889",
    "sg:postcode": "02114",
    "sg:province": "MA",
    "sg:tags": [
      "establishment"
    ],
    "wof:name": "Fate Foundation USA",
    "wof:placetype": "venue"
  },
  "geometry": {"coordinates":[-71.058465,42.365304],"type":"Point"}
}
