{
  "type": "Feature",
  "properties": {
    "addr:full": "800 W Cummings Park Ste 5000 Woburn MA 01801",
    "addr:housenumber": "800",
    "addr:postcode": "5000;01801",
    "addr:street": "W Cummings Park Ste",
    "iso:country": "US",
    "sg:address": "800 W Cummings Park Ste 5000",
    "sg:city": "Woburn",
    "sg:classifiers": [
      {
        "category": "Banks \u0026 Credit Unions",
        "subcategory": "Financial Services",
        "type": "Services"
      }
    ],
    "sg:phone": "+1 781 376 0089",
    "sg:postcode": "01801",
    "sg:province": "MA",
    "sg:tags": [
      "broker",
      "mortgage"
    ],
    "wof:name": "Ivy Mortgage",
    "wof:placetype": "venue"
  },
  "geometry": {"coordinates":[-71.1269,42.4958],"type":"Point"}
}
