{
  "type": "Feature",
  "properties": {
    "addr:full": "2451 Main St Jefferson MA 01522",
    "addr:housenumber": "2451",
    "addr:postcode": "01522",
    "addr:street": "Main St",
    "iso:country": "US",
    "sg:address": "2451 Main St",
    "sg:city": "Jefferson",
    "sg:classifiers": [
      {
        "category": "Personal",
        "subcategory": "Beauty Salon",
        "type": "Services"
      }
    ],
    "sg:phone": "+1 508 829 4244",
    "sg:postcode": "01522",
    "sg:province": "MA",
    "wof:name": "Tresses Salon",
    "wof:placetype": "venue"
  },
  "geometry": {"coordinates":[-71.918925,42.370986],"type":"Point"}
}
