{
  "type": "Feature",
  "properties": {
    "iso:country":"US",
    "sg:address":"94 Mount Pleasant Ave",
    "sg:city":"Roxbury",
    "sg:classifiers":[
        {
            "category":"Retail",
            "subcategory":"Laundry & Dry Cleaning",
            "type":"Services"
        }
    ],
    "sg:phone":"+1 617 822 9860",
    "sg:postcode":"02119",
    "sg:province":"MA",
    "sg:tags":[
        "cleaners",
        "rug",
        "carpet"
    ],
    "wof:name":"Davis Carpet & Rug Cleaning",
    "wof:placetype":"venue"
},
  "geometry": {"coordinates":[-71.077939,42.32587],"type":"Point"}
}