{
  "type": "Feature",
  "properties": {
    "addr:full": "94 Mount Pleasant Ave Roxbury MA 02119",
    "addr:housenumber": "94",
    "addr:postcode": "02119",
    "addr:street": "Mount Pleasant Ave",
    "iso:country": "US",
    "sg:address": "94 Mount Pleasant Ave",
    "sg:city": "Roxbury",
    "sg:classifiers": [
      {
        "category": "Retail",
        "subcategory": "Laundry \u0026 Dry Cleaning",
        "type": "Services"
      }
    ],
    "sg:phone": "+1 617 822 9860",
    "sg:postcode": "02119",
    "sg:province": "MA",
    "sg:tags": [
      "cleaners",
      "rug",
      "carpet"
    ],
    "wof:name": "Davis Carpet \u0026 Rug Cleaning",
    "wof:placetype": "venue"
  },
  "geometry": {"coordinates":[-71.077939,42.32587],"type":"Point"}
}
