{
  "type": "Feature",
  "properties": {
    "addr:full": "95 Lafayette Rd Salisbury MA 01952",
    "addr:housenumber": "95",
    "addr:postcode": "01952",
    "iso:country": "US",
    "sg:address": "95 Lafayette Rd",
    "sg:city": "Salisbury",
    "sg:classifiers": [
      {
        "category": "Building \u0026 Trades",
        "subcategory": "Construction",
        "type": "Services"
      }
    ],
    "sg:phone": "+1 978 465 7793",
    "sg:postcode": "01952",
    "sg:province": "MA",
    "sg:tags": [
      "demolition",
      "contractor"
    ],
    "wof:name": "Hutchinson Equipment Co Inc",
    "wof:placetype": "venue"
  },
  "geometry": {"coordinates":[-70.868605,42.85263],"type":"Point"}
}
