{
  "type": "Feature",
  "properties": {
    "addr:full": "65 Georgetown Dr Framingham MA 01702",
    "addr:housenumber": "65",
    "addr:postcode": "01702",
    "addr:street": "Georgetown Dr",
    "iso:country": "US",
    "sg:address": "65 Georgetown Dr",
    "sg:city": "Framingham",
    "sg:classifiers": [
      {
        "category": "Building \u0026 Trades",
        "subcategory": "Construction",
        "type": "Services"
      }
    ],
    "sg:phone": "+1 508 886 4851",
    "sg:postcode": "01702",
    "sg:province": "MA",
    "sg:tags": [
      "home",
      "improvement"
    ],
    "wof:name": "D Gutterman",
    "wof:placetype": "venue"
  },
  "geometry": {"coordinates":[-71.425075,42.297422],"type":"Point"}
}
