{
  "type": "Feature",
  "properties": {
    "addr:full":"35 Tomahawk Dr Tewksbury MA 01876",
    "addr:housenumber":"35",
    "addr:postcode":"01876",
    "addr:street":"Tomahawk Dr",
    "iso:country":"US",
    "sg:address":"35 Tomahawk Dr",
    "sg:city":"Tewksbury",
    "sg:classifiers":[
        {
            "category":"Building & Trades",
            "subcategory":"Construction",
            "type":"Services"
        }
    ],
    "sg:phone":"+1 978 455 0741",
    "sg:postcode":"01876",
    "sg:province":"MA",
    "sg:tags":[
        "demolition",
        "contractor"
    ],
    "wof:name":"John's Cleanout & Removal",
    "wof:placetype":"venue"
},
  "geometry": {"coordinates":[-71.234025,42.594977],"type":"Point"}
}