{
  "type": "Feature",
  "properties": {
    "addr:full": "871 Massachusetts Ave Boxborough MA 01719",
    "addr:housenumber": "871",
    "addr:postcode": "01719",
    "addr:street": "Massachusetts Ave",
    "iso:country": "US",
    "sg:address": "871 Massachusetts Ave",
    "sg:city": "Boxborough",
    "sg:classifiers": [
      {
        "category": "Retail",
        "subcategory": "Auto Repair",
        "type": "Services"
      }
    ],
    "sg:phone": "+1 978 929 2590",
    "sg:postcode": "01719",
    "sg:province": "MA",
    "sg:tags": [
      "exchanging",
      "engine"
    ],
    "wof:name": "ENB Small Engine Repair",
    "wof:placetype": "venue"
  },
  "geometry": {"coordinates":[-71.526801,42.483707],"type":"Point"}
}
