{
  "type": "Feature",
  "properties": {
    "iso:country":"US",
    "sg:address":"374 Broadway",
    "sg:city":"Lynn",
    "sg:classifiers":[
        {
            "category":"Social Services",
            "subcategory":"Child Care",
            "type":"Services"
        }
    ],
    "sg:phone":"+1 781 593 3690",
    "sg:postcode":"01904",
    "sg:province":"MA",
    "wof:name":"Program Community Partnership",
    "wof:placetype":"venue"
},
  "geometry": {"coordinates":[-70.958321,42.483754],"type":"Point"}
}