{
  "type": "Feature",
  "properties": {
    "addr:full": "64 Whalon St Fitchburg MA 01420",
    "addr:housenumber": "64",
    "addr:postcode": "01420",
    "addr:street": "Whalon St",
    "iso:country": "US",
    "sg:address": "64 Whalon St",
    "sg:city": "Fitchburg",
    "sg:classifiers": [
      {
        "category": "Real Estate",
        "subcategory": "Real Estate Services",
        "type": "Services"
      },
      {
        "category": "Real Estate",
        "subcategory": "Real Estate Agent",
        "type": "Services"
      }
    ],
    "sg:phone": "+1 978 342 4280",
    "sg:postcode": "01420",
    "sg:province": "MA",
    "sg:tags": [
      "buyer",
      "broker"
    ],
    "wof:name": "Dmc Realty",
    "wof:placetype": "venue"
  },
  "geometry": {"coordinates":[-71.784833,42.554227],"type":"Point"}
}
