{
  "type": "Feature",
  "properties": {
    "addr:full": "1090 Lakeview Ave Dracut MA 01826",
    "addr:housenumber": "1090",
    "addr:postcode": "01826",
    "addr:street": "Lakeview Ave",
    "iso:country": "US",
    "sg:address": "1090 Lakeview Ave",
    "sg:city": "Dracut",
    "sg:classifiers": [
      {
        "category": "Cinema",
        "subcategory": "Movie Rental",
        "type": "Entertainment"
      }
    ],
    "sg:phone": "+1 978 957 5303",
    "sg:postcode": "01826",
    "sg:province": "MA",
    "sg:tags": [
      "leasing",
      "video",
      "disc",
      "tape"
    ],
    "wof:name": "Nason's Video",
    "wof:placetype": "venue"
  },
  "geometry": {"coordinates":[-71.321525,42.66418],"type":"Point"}
}
