{
  "type": "Feature",
  "properties": {
    "iso:country":"US",
    "sg:address":"1090 Lakeview Ave",
    "sg:city":"Dracut",
    "sg:classifiers":[
        {
            "category":"Cinema",
            "subcategory":"Movie Rental",
            "type":"Entertainment"
        }
    ],
    "sg:phone":"+1 978 957 5303",
    "sg:postcode":"01826",
    "sg:province":"MA",
    "sg:tags":[
        "leasing",
        "video",
        "disc",
        "tape"
    ],
    "wof:name":"Nason's Video",
    "wof:placetype":"venue"
},
  "geometry": {"coordinates":[-71.32152499999999,42.66418],"type":"Point"}
}