{
  "type": "Feature",
  "properties": {
    "addr:full":"115 Gardiner St Lynn MA 01905",
    "addr:housenumber":"115",
    "addr:postcode":"01905",
    "addr:street":"Gardiner St",
    "iso:country":"US",
    "sg:address":"115 Gardiner St",
    "sg:city":"Lynn",
    "sg:classifiers":[
        {
            "category":"Organizations",
            "subcategory":"Labor Organization",
            "type":"Services"
        }
    ],
    "sg:phone":"+1 781 581 9486",
    "sg:postcode":"01905",
    "sg:province":"MA",
    "wof:name":"AFSCME",
    "wof:placetype":"venue"
},
  "geometry": {"coordinates":[-70.97764599999999,42.467514],"type":"Point"}
}