{
  "type": "Feature",
  "properties": {
    "addr:full":"2 Brookside Ln Burlington MA 01803",
    "addr:housenumber":"2",
    "addr:postcode":"01803",
    "addr:street":"Brookside Ln",
    "iso:country":"US",
    "sg:address":"2 Brookside Ln",
    "sg:city":"Burlington",
    "sg:classifiers":[
        {
            "category":"Building & Trades",
            "subcategory":"Locksmith",
            "type":"Services"
        }
    ],
    "sg:phone":"+1 781 313 8015",
    "sg:postcode":"01803",
    "sg:province":"MA",
    "sg:tags":[
        "key"
    ],
    "wof:name":"In Burlington MA Locksmith",
    "wof:placetype":"venue"
},
  "geometry": {"coordinates":[-71.206118,42.538368],"type":"Point"}
}