{
  "type": "Feature",
  "properties": {
    "addr:full":"2 Wilshire Dr Sharon MA 02067",
    "addr:housenumber":"2",
    "addr:postcode":"02067",
    "addr:street":"Wilshire Dr",
    "iso:country":"US",
    "sg:address":"2 Wilshire Dr",
    "sg:city":"Sharon",
    "sg:classifiers":[
        {
            "category":"Retail",
            "subcategory":"Repair Shop",
            "type":"Services"
        }
    ],
    "sg:phone":"+1   ",
    "sg:postcode":"02067",
    "sg:province":"MA",
    "wof:name":"Perez Gonzalo Upholstrey",
    "wof:placetype":"venue"
},
  "geometry": {"coordinates":[-71.15407999999999,42.11703],"type":"Point"}
}