{
  "type": "Feature",
  "properties": {
    "addr:full": "91 Bennett Hill Rd Rowley MA 01969",
    "addr:housenumber": "91",
    "addr:postcode": "01969",
    "addr:street": "Bennett Hill Rd",
    "iso:country": "US",
    "sg:address": "91 Bennett Hill Rd",
    "sg:city": "Rowley",
    "sg:classifiers": [
      {
        "category": "Professional",
        "type": "Services"
      }
    ],
    "sg:phone": "+1 978 948 7589",
    "sg:postcode": "01969",
    "sg:province": "MA",
    "sg:tags": [
      "establishment"
    ],
    "wof:name": "MVC Corp",
    "wof:placetype": "venue"
  },
  "geometry": {"coordinates":[-70.887695,42.726359],"type":"Point"}
}
