{
  "type": "Feature",
  "properties": {
    "addr:full":"137 Fort Pleasant Ave Springfield MA 01108",
    "addr:housenumber":"137",
    "addr:postcode":"01108",
    "addr:street":"Fort Pleasant Ave",
    "iso:country":"US",
    "sg:address":"137 Fort Pleasant Ave",
    "sg:city":"Springfield",
    "sg:classifiers":[
        {
            "category":"Real Estate",
            "subcategory":"Real Estate Services",
            "type":"Services"
        },
        {
            "category":"Real Estate",
            "subcategory":"Real Estate Agent",
            "type":"Services"
        }
    ],
    "sg:phone":"+1 413 306 3155",
    "sg:postcode":"01108",
    "sg:province":"MA",
    "sg:tags":[
        "buyer",
        "broker"
    ],
    "wof:name":"Encore Realty Inc",
    "wof:placetype":"venue"
},
  "geometry": {"coordinates":[-72.575236,42.087055],"type":"Point"}
}