{
  "type": "Feature",
  "properties": {
    "addr:full": "320 Golf Club Rd Vineyard Haven MA 02568",
    "addr:housenumber": "320",
    "addr:postcode": "02568",
    "addr:street": "Golf Club Rd",
    "iso:country": "US",
    "ovtr:label": "Mink Meadows Golf Club, 320 Golf Club Rd Vineyard Haven MA US",
    "ovtr:similarity": 2.4960250854492188,
    "sg:address": "320 Golf Club Rd",
    "sg:city": "Vineyard Haven",
    "sg:classifiers": [
      {
        "category": "Shopping",
        "subcategory": "Bicycles \u0026 Sporting Goods",
        "type": "Retail Goods"
      }
    ],
    "sg:phone": "+1 508 693 0600",
    "sg:postcode": "02568",
    "sg:province": "MA",
    "sg:tags": [
      "equipment",
      "golf",
      "supply"
    ],
    "wof:name": "Mink Meadows Golf Club",
    "wof:placetype": "venue"
  },
  "geometry": {"coordinates":[-70.605295,41.4779],"type":"Point"}
}
