{
  "type": "Feature",
  "properties": {
    "iso:country":"US",
    "sg:address":"320 Golf Club Rd",
    "sg:city":"Vineyard Haven",
    "sg:classifiers":[
        {
            "category":"Shopping",
            "subcategory":"Bicycles & Sporting Goods",
            "type":"Retail Goods"
        }
    ],
    "sg:phone":"+1 508 693 0600",
    "sg:postcode":"02568",
    "sg:province":"MA",
    "sg:tags":[
        "equipment",
        "golf",
        "supply"
    ],
    "wof:name":"Mink Meadows Golf Club",
    "wof:placetype":"venue"
},
  "geometry": {"coordinates":[-70.605295,41.4779],"type":"Point"}
}