{
  "type": "Feature",
  "properties": {
    "iso:country":"US",
    "sg:address":"88 W Alvord St",
    "sg:city":"Springfield",
    "sg:classifiers":[
        {
            "category":"Building & Trades",
            "subcategory":"Landscaping Services",
            "type":"Services"
        }
    ],
    "sg:phone":"+1 413 732 2781",
    "sg:postcode":"01108",
    "sg:province":"MA",
    "sg:tags":[
        "tree"
    ],
    "wof:name":"Carl W Delp Iii",
    "wof:placetype":"venue"
},
  "geometry": {"coordinates":[-72.54956300000001,42.088694],"type":"Point"}
}