{
  "type": "Feature",
  "properties": {
    "addr:full": "1166 Worthington St Springfield MA 01109",
    "addr:housenumber": "1166",
    "addr:postcode": "01109",
    "addr:street": "Worthington St",
    "iso:country": "US",
    "sg:address": "1166 Worthington St",
    "sg:city": "Springfield",
    "sg:classifiers": [
      {
        "category": "Professional",
        "type": "Services"
      }
    ],
    "sg:phone": "+1 413 733 6070",
    "sg:postcode": "01109",
    "sg:province": "MA",
    "sg:tags": [
      "art",
      "fine",
      "artist"
    ],
    "wof:name": "Slezak Fine Arts And Design",
    "wof:placetype": "venue"
  },
  "geometry": {"coordinates":[-72.572444,42.116337],"type":"Point"}
}
