{
  "type": "Feature",
  "properties": {
    "addr:full":"41 Belvidere St Boston MA 02115",
    "addr:housenumber":"41",
    "addr:postcode":"02115",
    "addr:street":"Belvidere St",
    "iso:country":"US",
    "sg:address":"41 Belvidere St",
    "sg:city":"Boston",
    "sg:classifiers":[
        {
            "category":"Professional",
            "subcategory":"Management & Consulting",
            "type":"Services"
        }
    ],
    "sg:phone":"+1 617 859 2942",
    "sg:postcode":"02115",
    "sg:province":"MA",
    "sg:tags":[
        "food",
        "consultant",
        "facility"
    ],
    "wof:name":"Berger Food Safety Consulting",
    "wof:placetype":"venue"
},
  "geometry": {"coordinates":[-71.085449,42.346181],"type":"Point"}
}