{
  "type": "Feature",
  "properties": {
    "addr:full": "3 Carriage Rd Chicopee MA 01013",
    "addr:housenumber": "3",
    "addr:postcode": "01013",
    "addr:street": "Carriage Rd",
    "iso:country": "US",
    "sg:address": "3 Carriage Rd",
    "sg:city": "Chicopee",
    "sg:classifiers": [
      {
        "category": "Professional",
        "subcategory": "Business Services",
        "type": "Services"
      }
    ],
    "sg:phone": "+1   ",
    "sg:postcode": "01013",
    "sg:province": "MA",
    "wof:name": "New England Wholsale Tr",
    "wof:placetype": "venue"
  },
  "geometry": {"coordinates":[-72.590353,42.185176],"type":"Point"}
}
