{
  "type": "Feature",
  "properties": {
    "iso:country":"US",
    "sg:address":"3 Carriage Rd",
    "sg:city":"Chicopee",
    "sg:classifiers":[
        {
            "category":"Professional",
            "subcategory":"Business Services",
            "type":"Services"
        }
    ],
    "sg:phone":"+1   ",
    "sg:postcode":"01013",
    "sg:province":"MA",
    "wof:name":"New England Wholsale Tr",
    "wof:placetype":"venue"
},
  "geometry": {"coordinates":[-72.59035299999999,42.185176],"type":"Point"}
}