{
  "type": "Feature",
  "properties": {
    "addr:full":"10 Central St Haverhill MA 01832",
    "addr:housenumber":"10",
    "addr:postcode":"01832",
    "addr:street":"Central St",
    "iso:country":"US",
    "sg:address":"10 Central St",
    "sg:city":"Haverhill",
    "sg:classifiers":[
        {
            "category":"Recreation",
            "type":"Entertainment"
        }
    ],
    "sg:phone":"+1 978 521 4700",
    "sg:postcode":"01832",
    "sg:province":"MA",
    "sg:tags":[
        "martial",
        "arts",
        "instruction"
    ],
    "wof:name":"Tang's Olympic Taekwondo",
    "wof:placetype":"venue"
},
  "geometry": {"coordinates":[-71.08859099999999,42.772826],"type":"Point"}
}