{
  "type": "Feature",
  "properties": {
    "addr:full":"116 Hadley St South Hadley MA 01075",
    "addr:housenumber":"116",
    "addr:postcode":"01075",
    "addr:street":"Hadley St",
    "iso:country":"US",
    "sg:address":"116 Hadley St",
    "sg:city":"South Hadley",
    "sg:classifiers":[
        {
            "category":"Education",
            "subcategory":"School",
            "type":"Public Place"
        }
    ],
    "sg:phone":"+1 413 538 5072",
    "sg:postcode":"01075",
    "sg:province":"MA",
    "wof:name":"Special Education Dept",
    "wof:placetype":"venue"
},
  "geometry": {"coordinates":[-72.585126,42.267248],"type":"Point"}
}