{
  "type": "Feature",
  "properties": {
    "iso:country":"US",
    "sg:address":"316 Court St",
    "sg:city":"Plymouth",
    "sg:classifiers":[
        {
            "category":"Restaurant",
            "type":"Food & Drink"
        }
    ],
    "sg:phone":"+1 508 747 3040",
    "sg:postcode":"02360",
    "sg:province":"MA",
    "wof:name":"Choi King Restaurant",
    "wof:placetype":"venue"
},
  "geometry": {"coordinates":[-70.684271,41.973711],"type":"Point"}
}