{
  "type": "Feature",
  "properties": {
    "addr:full":"37 Teaberry Ln Edgartown MA 02539",
    "addr:housenumber":"37",
    "addr:postcode":"02539",
    "addr:street":"Teaberry Ln",
    "iso:country":"US",
    "sg:address":"37 Teaberry Ln",
    "sg:city":"Edgartown",
    "sg:classifiers":[
        {
            "category":"Building & Trades",
            "subcategory":"Cleaning & Sanitation",
            "type":"Services"
        }
    ],
    "sg:phone":"+1 508 693 4589",
    "sg:postcode":"02539",
    "sg:province":"MA",
    "sg:tags":[
        "janitor"
    ],
    "wof:name":"C & D Janitorial Svc",
    "wof:placetype":"venue"
},
  "geometry": {"coordinates":[-70.55350199999999,41.399479],"type":"Point"}
}