{
  "type": "Feature",
  "properties": {
    "addr:full": "980 Providence Hwy Walpole MA 02081",
    "addr:housenumber": "980",
    "addr:postcode": "02081",
    "addr:street": "Providence Hwy",
    "iso:country": "US",
    "sg:address": "980 Providence Hwy",
    "sg:city": "Walpole",
    "sg:classifiers": [
      {
        "category": "Autos \u0026 Motor Vehicles",
        "subcategory": "Fuel \u0026 Gas Station",
        "type": "Retail Goods"
      }
    ],
    "sg:phone": "+1 508 668 7313",
    "sg:postcode": "02081",
    "sg:province": "MA",
    "sg:tags": [
      "oil"
    ],
    "wof:name": "Walpole Mobil",
    "wof:placetype": "venue"
  },
  "geometry": {"coordinates":[-71.231043,42.12347],"type":"Point"}
}
