{
  "type": "Feature",
  "properties": {
    "iso:country":"US",
    "sg:address":"27 Crane Ave",
    "sg:city":"Westfield",
    "sg:classifiers":[
        {
            "category":"Health Services",
            "subcategory":"Health Practitioner",
            "type":"Services"
        }
    ],
    "sg:phone":"+1   ",
    "sg:postcode":"01085",
    "sg:province":"MA",
    "wof:name":"Self Center",
    "wof:placetype":"venue"
},
  "geometry": {"coordinates":[-72.76732,42.113131],"type":"Point"}
}