{
  "type": "Feature",
  "properties": {
    "addr:full": "234 Iyannough Rd Hyannis MA 02601",
    "addr:housenumber": "234",
    "addr:postcode": "02601",
    "addr:street": "Iyannough Rd",
    "iso:country": "US",
    "ovtr:label": "Cape \u0026 Islands Glass, 234 Iyannough Rd Hyannis MA US",
    "ovtr:similarity": 1.663593053817749,
    "sg:address": "234 Iyannough Rd",
    "sg:city": "Hyannis",
    "sg:classifiers": [
      {
        "category": "Autos \u0026 Motor Vehicles",
        "subcategory": "Auto Supplies",
        "type": "Retail Goods"
      },
      {
        "category": "Building \u0026 Trades",
        "subcategory": "Construction",
        "type": "Services"
      }
    ],
    "sg:phone": "+1 508 775 7742",
    "sg:postcode": "02601",
    "sg:province": "MA",
    "sg:tags": [
      "glass",
      "window",
      "installation"
    ],
    "sg:website": "www.capeandislandsglass.com",
    "wof:name": "Cape \u0026 Islands Glass",
    "wof:placetype": "venue"
  },
  "geometry": {"coordinates":[-70.278268,41.661092],"type":"Point"}
}
