{
  "type": "Feature",
  "properties": {
    "iso:country":"US",
    "sg:address":"234 Iyannough Rd",
    "sg:city":"Hyannis",
    "sg:classifiers":[
        {
            "category":"Autos & Motor Vehicles",
            "subcategory":"Auto Supplies",
            "type":"Retail Goods"
        },
        {
            "category":"Building & Trades",
            "subcategory":"Construction",
            "type":"Services"
        }
    ],
    "sg:phone":"+1 508 775 7742",
    "sg:postcode":"02601",
    "sg:province":"MA",
    "sg:tags":[
        "glass",
        "window",
        "installation"
    ],
    "sg:website":"www.capeandislandsglass.com",
    "wof:name":"Cape & Islands Glass",
    "wof:placetype":"venue"
},
  "geometry": {"coordinates":[-70.278268,41.661092],"type":"Point"}
}