{
  "type": "Feature",
  "properties": {
    "iso:country":"US",
    "sg:address":"1 Bowdoin St",
    "sg:city":"Boston",
    "sg:classifiers":[
        {
            "category":"Professional",
            "subcategory":"Lawyer & Legal Services",
            "type":"Services"
        }
    ],
    "sg:phone":"+1 617 973 4525",
    "sg:postcode":"02114",
    "sg:province":"MA",
    "sg:tags":[
        "attorney"
    ],
    "wof:name":"Koski & Kearns LLP",
    "wof:placetype":"venue"
},
  "geometry": {"coordinates":[-71.06287399999999,42.359483],"type":"Point"}
}