{
  "type": "Feature",
  "properties": {
    "addr:full": "71 E Main St Webster MA 01570",
    "addr:housenumber": "71",
    "addr:postcode": "01570",
    "addr:street": "E Main St",
    "iso:country": "US",
    "ovtr:label": "KFC, 71 E Main St Webster MA US",
    "ovtr:similarity": 2.620398998260498,
    "sg:address": "71 E Main St",
    "sg:city": "Webster",
    "sg:classifiers": [
      {
        "category": "Fast Food",
        "type": "Food \u0026 Drink"
      },
      {
        "category": "Restaurant",
        "type": "Food \u0026 Drink"
      }
    ],
    "sg:phone": "+1 508 671 0134",
    "sg:postcode": "01570",
    "sg:province": "MA",
    "sg:tags": [
      "chicken"
    ],
    "sg:website": "http://www.kfc.com",
    "wof:name": "KFC",
    "wof:placetype": "venue"
  },
  "geometry": {"coordinates":[-71.870804,42.057069],"type":"Point"}
}
