{
  "type": "Feature",
  "properties": {
    "iso:country":"US",
    "sg:address":"71 E Main St",
    "sg:city":"Webster",
    "sg:classifiers":[
        {
            "category":"Fast Food",
            "type":"Food & Drink"
        },
        {
            "category":"Restaurant",
            "type":"Food & Drink"
        }
    ],
    "sg:phone":"+1 508 671 0134",
    "sg:postcode":"01570",
    "sg:province":"MA",
    "sg:tags":[
        "chicken"
    ],
    "sg:website":"http://www.kfc.com",
    "wof:name":"KFC",
    "wof:placetype":"venue"
},
  "geometry": {"coordinates":[-71.87080400000001,42.057069],"type":"Point"}
}