{
  "type": "Feature",
  "properties": {
    "addr:full":"19 Arlington St Boston MA 02116",
    "addr:housenumber":"19",
    "addr:postcode":"02116",
    "addr:street":"Arlington St",
    "iso:country":"US",
    "sg:address":"19 Arlington St",
    "sg:city":"Boston",
    "sg:classifiers":[
        {
            "category":"Building & Trades",
            "subcategory":"Construction",
            "type":"Services"
        }
    ],
    "sg:phone":"+1 508 965 3575",
    "sg:postcode":"02116",
    "sg:province":"MA",
    "sg:tags":[
        "interior",
        "design"
    ],
    "sg:website":"www.bostonstaginganddesign.com",
    "wof:name":"Boston Staging and Design",
    "wof:placetype":"venue"
},
  "geometry": {"coordinates":[-71.071269,42.352286],"type":"Point"}
}