{
  "type": "Feature",
  "properties": {
    "addr:full":"991 Providence Hwy Walpole MA 02081",
    "addr:housenumber":"991",
    "addr:postcode":"02081",
    "addr:street":"Providence Hwy",
    "iso:country":"US",
    "sg:address":"991 Providence Hwy",
    "sg:city":"Walpole",
    "sg:classifiers":[
        {
            "category":"Retail",
            "subcategory":"Portrait Studio",
            "type":"Services"
        },
        {
            "category":"Shopping",
            "subcategory":"Pharmacy",
            "type":"Retail Goods"
        }
    ],
    "sg:phone":"+1 781 762 5005",
    "sg:postcode":"02081",
    "sg:province":"MA",
    "sg:tags":[
        "photography",
        "drugstore",
        "store"
    ],
    "wof:name":"Brooks Pharmacy - CLOSED",
    "wof:placetype":"venue"
},
  "geometry": {"coordinates":[-71.230904,42.123402],"type":"Point"}
}