{
  "type": "Feature",
  "properties": {
    "addr:full": "44 Falmouth Rd Mashpee MA 02649",
    "addr:housenumber": "44",
    "addr:postcode": "02649",
    "addr:street": "Falmouth Rd",
    "iso:country": "US",
    "sg:address": "44 Falmouth Rd",
    "sg:city": "Mashpee",
    "sg:classifiers": [
      {
        "category": "Food \u0026 Beverages",
        "subcategory": "Groceries \u0026 Convenience Stores",
        "type": "Retail Goods"
      }
    ],
    "sg:phone": "+1 508 539 6611",
    "sg:postcode": "02649",
    "sg:province": "MA",
    "wof:name": "Mashpee Mart Inc",
    "wof:placetype": "venue"
  },
  "geometry": {"coordinates":[-70.458925,41.63408],"type":"Point"}
}
