{
  "type": "Feature",
  "properties": {
    "addr:full":"1 International Pl Boston MA 02110",
    "addr:housenumber":"1",
    "addr:postcode":"02110",
    "addr:street":"International Pl",
    "iso:country":"US",
    "sg:address":"1 International Pl",
    "sg:city":"Boston",
    "sg:classifiers":[
        {
            "category":"Coffee & Tea",
            "type":"Food & Drink"
        }
    ],
    "sg:phone":"+1 617 737 4688",
    "sg:postcode":"02110",
    "sg:province":"MA",
    "wof:name":"Starbucks",
    "wof:placetype":"venue"
},
  "geometry": {"coordinates":[-71.052729,42.356072],"type":"Point"}
}