{
  "type": "Feature",
  "properties": {
    "addr:full":"645 Broadway Everett MA 02149",
    "addr:housenumber":"645",
    "addr:postcode":"02149",
    "addr:street":"Broadway",
    "iso:country":"US",
    "sg:address":"645 Broadway",
    "sg:city":"Everett",
    "sg:classifiers":[
        {
            "category":"Shopping",
            "subcategory":"Computers & Home Electronics",
            "type":"Retail Goods"
        }
    ],
    "sg:phone":"+1 617 387 2400",
    "sg:postcode":"02149",
    "sg:province":"MA",
    "wof:name":"A & A Standard Radio & Tv Serv",
    "wof:placetype":"venue"
},
  "geometry": {"coordinates":[-71.050358,42.412836],"type":"Point"}
}