{
  "type": "Feature",
  "properties": {
    "addr:full":"121 Maverick St Boston MA 02128",
    "addr:housenumber":"121",
    "addr:postcode":"02128",
    "addr:street":"Maverick St",
    "iso:country":"US",
    "sg:address":"121 Maverick St",
    "sg:city":"Boston",
    "sg:classifiers":[
        {
            "category":"Personal",
            "subcategory":"Beauty Salon",
            "type":"Services"
        }
    ],
    "sg:phone":"+1 617 561 3283",
    "sg:postcode":"02128",
    "sg:province":"MA",
    "sg:tags":[
        "hair"
    ],
    "wof:name":"First Class",
    "wof:placetype":"venue"
},
  "geometry": {"coordinates":[-71.03939800000001,42.370334],"type":"Point"}
}