{
  "type": "Feature",
  "properties": {
    "addr:full": "49 D St South Boston MA 02127",
    "addr:housenumber": "49",
    "addr:postcode": "02127",
    "addr:street": "D St",
    "iso:country": "US",
    "sg:address": "49 D St",
    "sg:city": "South Boston",
    "sg:classifiers": [
      {
        "category": "Manufacturing",
        "subcategory": "Printing",
        "type": "Manufacturing \u0026 Wholesale Goods"
      }
    ],
    "sg:phone": "+1 617 269 6040",
    "sg:postcode": "02127",
    "sg:province": "MA",
    "sg:tags": [
      "book"
    ],
    "sg:website": "www.jppow.com",
    "wof:name": "John P Pow \u0026 Co",
    "wof:placetype": "venue"
  },
  "geometry": {"coordinates":[-71.056157,42.33405],"type":"Point"}
}
