{
  "type": "Feature",
  "properties": {
    "addr:full": "1653 Dorchester Ave Boston MA 02122",
    "addr:housenumber": "1653",
    "addr:postcode": "02122",
    "addr:street": "Dorchester Ave",
    "iso:country": "US",
    "sg:address": "1653 Dorchester Ave",
    "sg:city": "Boston",
    "sg:classifiers": [
      {
        "category": "Professional",
        "type": "Services"
      }
    ],
    "sg:phone": "+1   ",
    "sg:postcode": "02122",
    "sg:province": "MA",
    "wof:name": "Reliance Service",
    "wof:placetype": "venue"
  },
  "geometry": {"coordinates":[-71.062149,42.293742],"type":"Point"}
}
