{
  "type": "Feature",
  "properties": {
    "iso:country":"US",
    "sg:address":"1653 Dorchester Ave",
    "sg:city":"Boston",
    "sg:classifiers":[
        {
            "category":"Professional",
            "type":"Services"
        }
    ],
    "sg:phone":"+1   ",
    "sg:postcode":"02122",
    "sg:province":"MA",
    "wof:name":"Reliance Service",
    "wof:placetype":"venue"
},
  "geometry": {"coordinates":[-71.06214900000001,42.293742],"type":"Point"}
}