{
  "type": "Feature",
  "properties": {
    "addr:full": "457 Beacon St Boston MA 02115",
    "addr:housenumber": "457",
    "addr:postcode": "02115",
    "addr:street": "Beacon St",
    "iso:country": "US",
    "sg:address": "457 Beacon St",
    "sg:city": "Boston",
    "sg:classifiers": [
      {
        "category": "Education",
        "subcategory": "School",
        "type": "Public Place"
      }
    ],
    "sg:phone": "+1   ",
    "sg:postcode": "02115",
    "sg:province": "MA",
    "sg:tags": [
      "wildlife",
      "primary",
      "pres",
      "secondary"
    ],
    "wof:name": "Virtual Voyage",
    "wof:placetype": "venue"
  },
  "geometry": {"coordinates":[-71.08875,42.35103],"type":"Point"}
}
