{
  "type": "Feature",
  "properties": {
    "iso:country":"US",
    "sg:address":"36 Osceola Ave",
    "sg:city":"Worcester",
    "sg:classifiers":[
        {
            "category":"Building & Trades",
            "subcategory":"Construction",
            "type":"Services"
        }
    ],
    "sg:phone":"+1   ",
    "sg:postcode":"01606",
    "sg:province":"MA",
    "sg:tags":[
        "hanging",
        "contractor"
    ],
    "wof:name":"Kevin M Searl",
    "wof:placetype":"venue"
},
  "geometry": {"coordinates":[-71.78254699999999,42.309222],"type":"Point"}
}