{
  "type": "Feature",
  "properties": {
    "iso:country":"US",
    "sg:address":"92 Pleasant St",
    "sg:city":"Newburyport",
    "sg:classifiers":[
        {
            "category":"Personal",
            "subcategory":"Beauty Salon",
            "type":"Services"
        }
    ],
    "sg:phone":"+1 978 462 3812",
    "sg:postcode":"01950",
    "sg:province":"MA",
    "sg:tags":[
        "spa",
        "day"
    ],
    "wof:name":"Cutting Room At Pleasant Spa the",
    "wof:placetype":"venue"
},
  "geometry": {"coordinates":[-70.873802,42.811199],"type":"Point"}
}