{
  "type": "Feature",
  "properties": {
    "addr:full": "4 Traver Ct Greenfield MA 01301",
    "addr:housenumber": "4",
    "addr:postcode": "01301",
    "addr:street": "Traver Ct",
    "iso:country": "US",
    "sg:address": "4 Traver Ct",
    "sg:city": "Greenfield",
    "sg:classifiers": [
      {
        "category": "Building \u0026 Trades",
        "subcategory": "Construction",
        "type": "Services"
      }
    ],
    "sg:phone": "+1   ",
    "sg:postcode": "01301",
    "sg:province": "MA",
    "sg:tags": [
      "house"
    ],
    "wof:name": "Mr Gary Seldon",
    "wof:placetype": "venue"
  },
  "geometry": {"coordinates":[-72.596821,42.582569],"type":"Point"}
}
