{
  "type": "Feature",
  "properties": {
    "addr:full": "48 Putnam St Beverly MA 01915",
    "addr:housenumber": "48",
    "addr:postcode": "01915",
    "addr:street": "Putnam St",
    "iso:country": "US",
    "sg:address": "48 Putnam St",
    "sg:city": "Beverly",
    "sg:classifiers": [
      {
        "category": "Education",
        "subcategory": "School",
        "type": "Public Place"
      }
    ],
    "sg:phone": "+1 978 921 6130",
    "sg:postcode": "01915",
    "sg:province": "MA",
    "wof:name": "North Beverly School",
    "wof:placetype": "venue"
  },
  "geometry": {"coordinates":[-70.879973,42.580138],"type":"Point"}
}
