{
  "type": "Feature",
  "properties": {
    "iso:country":"US",
    "sg:address":"850 Southbridge St",
    "sg:city":"Auburn",
    "sg:classifiers":[
        {
            "category":"Shopping",
            "subcategory":"Clothing, Apparel, & Fashions",
            "type":"Retail Goods"
        }
    ],
    "sg:phone":"+1 508 721 7800",
    "sg:postcode":"01501",
    "sg:province":"MA",
    "wof:name":"Glamour Boutique",
    "wof:placetype":"venue"
},
  "geometry": {"coordinates":[-71.87372499999999,42.176915],"type":"Point"}
}