{
  "type": "Feature",
  "properties": {
    "addr:full": "850 Southbridge St Auburn MA 01501",
    "addr:housenumber": "850",
    "addr:postcode": "01501",
    "addr:street": "Southbridge St",
    "iso:country": "US",
    "sg:address": "850 Southbridge St",
    "sg:city": "Auburn",
    "sg:classifiers": [
      {
        "category": "Shopping",
        "subcategory": "Clothing, Apparel, \u0026 Fashions",
        "type": "Retail Goods"
      }
    ],
    "sg:phone": "+1 508 721 7800",
    "sg:postcode": "01501",
    "sg:province": "MA",
    "wof:name": "Glamour Boutique",
    "wof:placetype": "venue"
  },
  "geometry": {"coordinates":[-71.873725,42.176915],"type":"Point"}
}
