{
  "type": "Feature",
  "properties": {
    "addr:full": "13 Brook St Ayer MA 01432",
    "addr:housenumber": "13",
    "addr:postcode": "01432",
    "addr:street": "Brook St",
    "iso:country": "US",
    "sg:address": "13 Brook St",
    "sg:city": "Ayer",
    "sg:classifiers": [
      {
        "category": "Retail",
        "subcategory": "Repair Shop",
        "type": "Services"
      }
    ],
    "sg:phone": "+1 978 772 0826",
    "sg:postcode": "01432",
    "sg:province": "MA",
    "sg:tags": [
      "welding"
    ],
    "wof:name": "Mac's Welding \u0026 Fabricating",
    "wof:placetype": "venue"
  },
  "geometry": {"coordinates":[-71.593058,42.563295],"type":"Point"}
}
