{
  "type": "Feature",
  "properties": {
    "iso:country":"US",
    "sg:address":"399 Main St",
    "sg:city":"Holyoke",
    "sg:classifiers":[
        {
            "category":"Food & Beverages",
            "subcategory":"Groceries & Convenience Stores",
            "type":"Retail Goods"
        }
    ],
    "sg:phone":"+1 413 533 5469",
    "sg:postcode":"01040",
    "sg:province":"MA",
    "sg:tags":[
        "grocer"
    ],
    "wof:name":"Main Street Market",
    "wof:placetype":"venue"
},
  "geometry": {"coordinates":[-72.607033,42.199988],"type":"Point"}
}