{
  "type": "Feature",
  "properties": {
    "iso:country":"US",
    "sg:address":"1524 Dorchester Ave",
    "sg:city":"Dorchester",
    "sg:phone":"+1 617 287 1685",
    "sg:postcode":"02122",
    "sg:province":"MA",
    "sg:website":"http://clickserve.dartsearch.net/link/click?lid=43000000308049899",
    "wof:name":"T-Mobile",
    "wof:placetype":"venue"
},
  "geometry": {"coordinates":[-71.060661,42.298599],"type":"Point"}
}