{
  "type": "Feature",
  "properties": {
    "addr:full": "1524 Dorchester Ave Dorchester MA 02122",
    "addr:housenumber": "1524",
    "addr:postcode": "02122",
    "addr:street": "Dorchester Ave",
    "iso:country": "US",
    "ovtr:label": "T-Mobile, 1493 Dorchester Ave Dorchester MA US",
    "ovtr:similarity": 3.7106380462646484,
    "sg:address": "1524 Dorchester Ave",
    "sg:city": "Dorchester",
    "sg:phone": "+1 617 287 1685",
    "sg:postcode": "02122",
    "sg:province": "MA",
    "sg:website": "http://clickserve.dartsearch.net/link/click?lid=43000000308049899",
    "wof:name": "T-Mobile",
    "wof:placetype": "venue"
  },
  "geometry": {"coordinates":[-71.060661,42.298599],"type":"Point"}
}
