{
  "type": "Feature",
  "properties": {
    "addr:full": "26 Galahad Way North Easton MA 02356",
    "addr:housenumber": "26",
    "addr:postcode": "02356",
    "addr:street": "Galahad Way",
    "iso:country": "US",
    "sg:address": "26 Galahad Way",
    "sg:city": "North Easton",
    "sg:classifiers": [
      {
        "category": "Insurance",
        "subcategory": "Insurance Agent",
        "type": "Services"
      }
    ],
    "sg:phone": "+1   ",
    "sg:postcode": "02356",
    "sg:province": "MA",
    "wof:name": "Keepsake",
    "wof:placetype": "venue"
  },
  "geometry": {"coordinates":[-71.129357,42.033832],"type":"Point"}
}
