{
  "type": "Feature",
  "properties": {
    "addr:full":"5 W Central St Natick MA 01760",
    "addr:housenumber":"5",
    "addr:postcode":"01760",
    "addr:street":"W Central St",
    "iso:country":"US",
    "sg:address":"5 W Central St",
    "sg:city":"Natick",
    "sg:classifiers":[
        {
            "category":"Shopping",
            "subcategory":"Jewelry",
            "type":"Retail Goods"
        }
    ],
    "sg:phone":"+1 508 647 9888",
    "sg:postcode":"01760",
    "sg:province":"MA",
    "sg:tags":[
        "jeweler"
    ],
    "wof:name":"GRS Jewelry Inc",
    "wof:placetype":"venue"
},
  "geometry": {"coordinates":[-71.34727599999999,42.283783],"type":"Point"}
}