{
  "type": "Feature",
  "properties": {
    "iso:country":"US",
    "sg:address":"94 Ridgewood Ave",
    "sg:city":"Hyannis",
    "sg:classifiers":[
        {
            "category":"Airline",
            "type":"Transportation"
        }
    ],
    "sg:phone":"+1 508 771 1000",
    "sg:postcode":"02601",
    "sg:province":"MA",
    "sg:tags":[
        "shuttle",
        "airport"
    ],
    "wof:name":"Limos To Logan",
    "wof:placetype":"venue"
},
  "geometry": {"coordinates":[-70.281464,41.657935],"type":"Point"}
}