{
  "type": "Feature",
  "properties": {
    "iso:country":"US",
    "sg:address":"9 Power St",
    "sg:city":"Charlton City",
    "sg:classifiers":[
        {
            "category":"Government",
            "subcategory":"Post Office",
            "type":"Public Place"
        }
    ],
    "sg:phone":"+1 508 000 1111",
    "sg:postcode":"01569",
    "sg:province":"MA",
    "wof:name":"US Post Office",
    "wof:placetype":"venue"
},
  "geometry": {"coordinates":[-71.612872,42.07876],"type":"Point"}
}