{
  "type": "Feature",
  "properties": {
    "addr:full":"95 Tremont St Duxbury MA 02332",
    "addr:housenumber":"95",
    "addr:postcode":"02332",
    "addr:street":"Tremont St",
    "iso:country":"US",
    "sg:address":"95 Tremont St",
    "sg:city":"Duxbury",
    "sg:classifiers":[
        {
            "category":"Health Services",
            "subcategory":"Doctor",
            "type":"Services"
        }
    ],
    "sg:phone":"+1 781 934 7592",
    "sg:postcode":"02332",
    "sg:province":"MA",
    "sg:tags":[
        "physician",
        "surgeon"
    ],
    "wof:name":"Pilgrim Shores Obstetrics",
    "wof:placetype":"venue"
},
  "geometry": {"coordinates":[-70.719825,42.014411],"type":"Point"}
}