{
  "type": "Feature",
  "properties": {
    "addr:full":"113 Neck Rd Haverhill MA 01835",
    "addr:housenumber":"113",
    "addr:postcode":"01835",
    "addr:street":"Neck Rd",
    "iso:country":"US",
    "sg:address":"113 Neck Rd",
    "sg:city":"Haverhill",
    "sg:classifiers":[
        {
            "category":"Wholesale",
            "subcategory":"Hardware",
            "type":"Manufacturing & Wholesale Goods"
        }
    ],
    "sg:phone":"+1 978 373 9378",
    "sg:postcode":"01835",
    "sg:province":"MA",
    "sg:tags":[
        "tool"
    ],
    "wof:name":"Western Tool Supply",
    "wof:placetype":"venue"
},
  "geometry": {"coordinates":[-71.117386,42.753881],"type":"Point"}
}