{
  "type": "Feature",
  "properties": {
    "iso:country":"US",
    "sg:address":"50 Pleasant St",
    "sg:city":"Northampton",
    "sg:classifiers":[
        {
            "category":"Recreation",
            "type":"Entertainment"
        }
    ],
    "sg:phone":"+1 413 527 5240",
    "sg:postcode":"01060",
    "sg:province":"MA",
    "sg:tags":[
        "hall",
        "auditorium"
    ],
    "wof:name":"Easthampton Community Ctr",
    "wof:placetype":"venue"
},
  "geometry": {"coordinates":[-72.62842499999999,42.318757],"type":"Point"}
}