{
  "type": "Feature",
  "properties": {
    "iso:country":"US",
    "sg:address":"64 Vale St",
    "sg:city":"Fall River",
    "sg:classifiers":[
        {
            "category":"Food & Beverages",
            "subcategory":"Bakery",
            "type":"Retail Goods"
        }
    ],
    "sg:phone":"+1 508 676 9955",
    "sg:postcode":"02724",
    "sg:province":"MA",
    "sg:tags":[
        "baker"
    ],
    "wof:name":"Mr Donut",
    "wof:placetype":"venue"
},
  "geometry": {"coordinates":[-71.164457,41.687699],"type":"Point"}
}