{
  "type": "Feature",
  "properties": {
    "addr:full":"382 Huron Ave Cambridge MA 02138",
    "addr:housenumber":"382",
    "addr:postcode":"02138",
    "addr:street":"Huron Ave",
    "iso:country":"US",
    "sg:address":"382 Huron Ave",
    "sg:city":"Cambridge",
    "sg:classifiers":[
        {
            "category":"Professional",
            "subcategory":"Business Services",
            "type":"Services"
        }
    ],
    "sg:phone":"+1 617 576 3878",
    "sg:postcode":"02138",
    "sg:province":"MA",
    "sg:tags":[
        "interior",
        "consultant",
        "design",
        "decorator"
    ],
    "wof:name":"Southerland Design",
    "wof:placetype":"venue"
},
  "geometry": {"coordinates":[-71.139331,42.380984],"type":"Point"}
}