{
  "type": "Feature",
  "properties": {
    "iso:country":"US",
    "sg:address":"6 Morin Dr",
    "sg:city":"Bellingham",
    "sg:classifiers":[
        {
            "category":"Organizations",
            "subcategory":"Community Association",
            "type":"Services"
        }
    ],
    "sg:phone":"+1   ",
    "sg:postcode":"02019",
    "sg:province":"MA",
    "wof:name":"Ancient Mystic Order of S",
    "wof:placetype":"venue"
},
  "geometry": {"coordinates":[-71.477959,42.038601],"type":"Point"}
}