{
  "type": "Feature",
  "properties": {
    "addr:full": "43 Eldridge St Chicopee MA 01013",
    "addr:housenumber": "43",
    "addr:postcode": "01013",
    "addr:street": "Eldridge St",
    "iso:country": "US",
    "sg:address": "43 Eldridge St",
    "sg:city": "Chicopee",
    "sg:classifiers": [
      {
        "category": "Manufacturing",
        "subcategory": "Glass \u0026 Minerals",
        "type": "Manufacturing \u0026 Wholesale Goods"
      }
    ],
    "sg:phone": "+1 413 592 2615",
    "sg:postcode": "01013",
    "sg:province": "MA",
    "sg:tags": [
      "glass-wholesale",
      "shape",
      "circle",
      "special",
      "manufacturer"
    ],
    "wof:name": "Patchwork Glass",
    "wof:placetype": "venue"
  },
  "geometry": {"coordinates":[-72.599471,42.137939],"type":"Point"}
}
