{
  "type": "Feature",
  "properties": {
    "iso:country":"US",
    "sg:address":"326 Union St",
    "sg:city":"Franklin",
    "sg:classifiers":[
        {
            "category":"Food & Beverages",
            "subcategory":"Groceries & Convenience Stores",
            "type":"Retail Goods"
        }
    ],
    "sg:phone":"+1 508 520 0481",
    "sg:postcode":"02038",
    "sg:province":"MA",
    "wof:name":"Jay Gayatri Inc",
    "wof:placetype":"venue"
},
  "geometry": {"coordinates":[-71.403614,42.07732],"type":"Point"}
}