{
  "type": "Feature",
  "properties": {
    "addr:full":"241 Francis Ave Mansfield MA 02048",
    "addr:housenumber":"241",
    "addr:postcode":"02048",
    "addr:street":"Francis Ave",
    "iso:country":"US",
    "sg:address":"241 Francis Ave",
    "sg:city":"Mansfield",
    "sg:classifiers":[
        {
            "category":"Airline",
            "type":"Transportation"
        }
    ],
    "sg:phone":"+1 508 261 1554",
    "sg:postcode":"02048",
    "sg:province":"MA",
    "sg:tags":[
        "cargo",
        "air"
    ],
    "wof:name":"Allstate Air Cargo",
    "wof:placetype":"venue"
},
  "geometry": {"coordinates":[-71.211386,42.04014],"type":"Point"}
}