{
  "type": "Feature",
  "properties": {
    "addr:full": "823 Orange Rd Warwick MA 01378",
    "addr:housenumber": "823",
    "addr:postcode": "01378",
    "addr:street": "Orange Rd",
    "iso:country": "US",
    "sg:address": "823 Orange Rd",
    "sg:city": "Warwick",
    "sg:classifiers": [
      {
        "category": "Farming",
        "subcategory": "Farm",
        "type": "Manufacturing \u0026 Wholesale Goods"
      }
    ],
    "sg:phone": "+1 978 544 1845",
    "sg:postcode": "01378",
    "sg:province": "MA",
    "wof:name": "Old 78 Farm",
    "wof:placetype": "venue"
  },
  "geometry": {"coordinates":[-72.326134,42.630001],"type":"Point"}
}
