{
  "type": "Feature",
  "properties": {
    "addr:full": "109 Crowell Rd Chatham MA 02633",
    "addr:housenumber": "109",
    "addr:postcode": "02633",
    "addr:street": "Crowell Rd",
    "iso:country": "US",
    "sg:address": "109 Crowell Rd",
    "sg:city": "Chatham",
    "sg:classifiers": [
      {
        "category": "Building \u0026 Trades",
        "subcategory": "Construction",
        "type": "Services"
      }
    ],
    "sg:phone": "+1 508 945 4997",
    "sg:postcode": "02633",
    "sg:province": "MA",
    "sg:tags": [
      "woodworker"
    ],
    "wof:name": "Handle Shop",
    "wof:placetype": "venue"
  },
  "geometry": {"coordinates":[-69.966841,41.687727],"type":"Point"}
}
