{
  "type": "Feature",
  "properties": {
    "addr:full": "302 Main Street Malden MA 02148",
    "addr:housenumber": "302",
    "addr:postcode": "02148",
    "addr:street": "Main Street",
    "iso:country": "US",
    "sg:address": "302 Main Street",
    "sg:city": "Malden",
    "sg:classifiers": [
      {
        "category": "Restaurant",
        "type": "Food \u0026 Drink"
      },
      {
        "category": "Food \u0026 Beverages",
        "subcategory": "Specialty",
        "type": "Retail Goods"
      },
      {
        "category": "Food \u0026 Beverages",
        "subcategory": "Bakery",
        "type": "Retail Goods"
      },
      {
        "category": "Wholesale",
        "subcategory": "Groceries",
        "type": "Manufacturing \u0026 Wholesale Goods"
      },
      {
        "category": "Food \u0026 Beverages",
        "subcategory": "Groceries \u0026 Convenience Stores",
        "type": "Retail Goods"
      }
    ],
    "sg:phone": "+1 781 338 9905",
    "sg:postcode": "02148",
    "sg:province": "MA",
    "sg:tags": [
      "grocers-wholesale",
      "sandwich",
      "grocers-specialty",
      "vietnamese"
    ],
    "wof:name": "Vinh Thanh Food Market",
    "wof:placetype": "venue"
  },
  "geometry": {"coordinates":[-71.067574,42.424408],"type":"Point"}
}
