{
  "type": "Feature",
  "properties": {
    "iso:country":"US",
    "sg:address":"302 Main Street",
    "sg:city":"Malden",
    "sg:classifiers":[
        {
            "category":"Restaurant",
            "type":"Food & Drink"
        },
        {
            "category":"Food & Beverages",
            "subcategory":"Specialty",
            "type":"Retail Goods"
        },
        {
            "category":"Food & Beverages",
            "subcategory":"Bakery",
            "type":"Retail Goods"
        },
        {
            "category":"Wholesale",
            "subcategory":"Groceries",
            "type":"Manufacturing & Wholesale Goods"
        },
        {
            "category":"Food & Beverages",
            "subcategory":"Groceries & Convenience Stores",
            "type":"Retail Goods"
        }
    ],
    "sg:phone":"+1 781 338 9905",
    "sg:postcode":"02148",
    "sg:province":"MA",
    "sg:tags":[
        "grocers-wholesale",
        "sandwich",
        "grocers-specialty",
        "vietnamese"
    ],
    "wof:name":"Vinh Thanh Food Market",
    "wof:placetype":"venue"
},
  "geometry": {"coordinates":[-71.06757399999999,42.424408],"type":"Point"}
}