{
  "type": "Feature",
  "properties": {
    "addr:full": "41 Belvidere St Boston MA 02115",
    "addr:housenumber": "41",
    "addr:postcode": "02115",
    "addr:street": "Belvidere St",
    "iso:country": "US",
    "sg:address": "41 Belvidere St",
    "sg:city": "Boston",
    "sg:classifiers": [
      {
        "category": "Building \u0026 Trades",
        "subcategory": "Construction",
        "type": "Services"
      }
    ],
    "sg:phone": "+1 617 450 0022",
    "sg:postcode": "02115",
    "sg:province": "MA",
    "sg:tags": [
      "waterproofing",
      "contractor"
    ],
    "wof:name": "FWT Svc Co",
    "wof:placetype": "venue"
  },
  "geometry": {"coordinates":[-71.085511,42.346165],"type":"Point"}
}
