{
  "type": "Feature",
  "properties": {
    "addr:full":"15 Dorothy Dr Plymouth MA 02360",
    "addr:housenumber":"15",
    "addr:postcode":"02360",
    "addr:street":"Dorothy Dr",
    "iso:country":"US",
    "sg:address":"15 Dorothy Dr",
    "sg:city":"Plymouth",
    "sg:classifiers":[
        {
            "category":"Professional",
            "type":"Services"
        }
    ],
    "sg:phone":"+1   ",
    "sg:postcode":"02360",
    "sg:province":"MA",
    "wof:name":"Community Resources Inc",
    "wof:placetype":"venue"
},
  "geometry": {"coordinates":[-70.59531699999999,41.841628],"type":"Point"}
}