{
  "type": "Feature",
  "properties": {
    "addr:full":"284 Orchard St Watertown MA 02472",
    "addr:housenumber":"284",
    "addr:postcode":"02472",
    "addr:street":"Orchard St",
    "iso:country":"US",
    "sg:address":"284 Orchard St",
    "sg:city":"Watertown",
    "sg:classifiers":[
        {
            "category":"Professional",
            "subcategory":"Engineering",
            "type":"Services"
        }
    ],
    "sg:phone":"+1 617 923 3993",
    "sg:postcode":"02472",
    "sg:province":"MA",
    "sg:tags":[
        "engineer"
    ],
    "wof:name":"GSA",
    "wof:placetype":"venue"
},
  "geometry": {"coordinates":[-71.188812,42.378055],"type":"Point"}
}