{
  "type": "Feature",
  "properties": {
    "addr:full": "579 Boylston St Boston MA 02116",
    "addr:housenumber": "579",
    "addr:postcode": "02116",
    "addr:street": "Boylston St",
    "iso:country": "US",
    "sg:address": "579 Boylston St",
    "sg:city": "Boston",
    "sg:classifiers": [
      {
        "category": "Banks \u0026 Credit Unions",
        "subcategory": "Bank",
        "type": "Services"
      }
    ],
    "sg:phone": "+1 617 266 0740",
    "sg:postcode": "02116",
    "sg:province": "MA",
    "sg:website": "www.tdbanknorth.com",
    "wof:name": "Td Banknorth Na",
    "wof:placetype": "venue"
  },
  "geometry": {"coordinates":[-71.076817,42.350373],"type":"Point"}
}
