{
  "type": "Feature",
  "properties": {
    "iso:country":"US",
    "sg:address":"579 Boylston St",
    "sg:city":"Boston",
    "sg:classifiers":[
        {
            "category":"Banks & Credit Unions",
            "subcategory":"Bank",
            "type":"Services"
        }
    ],
    "sg:phone":"+1 617 266 0740",
    "sg:postcode":"02116",
    "sg:province":"MA",
    "sg:website":"www.tdbanknorth.com",
    "wof:name":"Td Banknorth Na",
    "wof:placetype":"venue"
},
  "geometry": {"coordinates":[-71.07681700000001,42.350373],"type":"Point"}
}