{
  "type": "Feature",
  "properties": {
    "addr:full":"489 Newton St South Hadley MA 01075",
    "addr:housenumber":"489",
    "addr:postcode":"01075",
    "addr:street":"Newton St",
    "iso:country":"US",
    "sg:address":"489 Newton St",
    "sg:city":"South Hadley",
    "sg:classifiers":[
        {
            "category":"Ice Cream",
            "type":"Food & Drink"
        }
    ],
    "sg:menulink":"http://www.allmenus.com/ma/south-hadley/99153-friendlys/menu/",
    "sg:phone":"+1 413 538 8010",
    "sg:postcode":"01075",
    "sg:province":"MA",
    "sg:tags":[
        "burger",
        "american"
    ],
    "wof:name":"Friendly's",
    "wof:placetype":"venue"
},
  "geometry": {"coordinates":[-72.582983,42.236331],"type":"Point"}
}