{
  "type": "Feature",
  "properties": {
    "iso:country":"US",
    "sg:address":"693 Longmeadow St",
    "sg:city":"Longmeadow",
    "sg:classifiers":[
        {
            "category":"Education",
            "subcategory":"School",
            "type":"Public Place"
        }
    ],
    "sg:phone":"+1 413 565 4181",
    "sg:postcode":"01106",
    "sg:province":"MA",
    "wof:name":"Storrs Library",
    "wof:placetype":"venue"
},
  "geometry": {"coordinates":[-72.58219699999999,42.053186],"type":"Point"}
}