{
  "type": "Feature",
  "properties": {
    "addr:full":"41 Summer St Natick MA 01760",
    "addr:housenumber":"41",
    "addr:postcode":"01760",
    "addr:street":"Summer St",
    "iso:country":"US",
    "sg:address":"41 Summer St",
    "sg:city":"Natick",
    "sg:classifiers":[
        {
            "category":"Taxi",
            "type":"Transportation"
        }
    ],
    "sg:phone":"+1 508 653 2300",
    "sg:postcode":"01760",
    "sg:province":"MA",
    "sg:tags":[
        "taxicab"
    ],
    "wof:name":"Natick Cab Co",
    "wof:placetype":"venue"
},
  "geometry": {"coordinates":[-71.34836900000001,42.284585],"type":"Point"}
}