{
  "type": "Feature",
  "properties": {
    "addr:full":"581 Boylston St Boston MA 02116",
    "addr:housenumber":"581",
    "addr:postcode":"02116",
    "addr:street":"Boylston St",
    "iso:country":"US",
    "sg:address":"581 Boylston St",
    "sg:city":"Boston",
    "sg:classifiers":[
        {
            "category":"Real Estate",
            "subcategory":"Real Estate Services",
            "type":"Services"
        },
        {
            "category":"Real Estate",
            "subcategory":"Real Estate Agent",
            "type":"Services"
        },
        {
            "category":"Real Estate",
            "subcategory":"Real Estate Operator",
            "type":"Services"
        }
    ],
    "sg:phone":"+1 617 247 1933",
    "sg:postcode":"02116",
    "sg:province":"MA",
    "sg:tags":[
        "apartment"
    ],
    "sg:website":"www.bostoncityproperties.com/",
    "wof:name":"Boston City Properties",
    "wof:placetype":"venue"
},
  "geometry": {"coordinates":[-71.076725,42.350539],"type":"Point"}
}