{
  "type": "Feature",
  "properties": {
    "addr:full": "60 Madison St Worcester MA 01608",
    "addr:housenumber": "60",
    "addr:postcode": "01608",
    "addr:street": "Madison St",
    "iso:country": "US",
    "sg:address": "60 Madison St",
    "sg:city": "Worcester",
    "sg:classifiers": [
      {
        "category": "Restaurant",
        "type": "Food \u0026 Drink"
      }
    ],
    "sg:phone": "+1 508 791 9577",
    "sg:postcode": "01608",
    "sg:province": "MA",
    "sg:tags": [
      "chinese"
    ],
    "wof:name": "Ping's Garden Restaurant Inc",
    "wof:placetype": "venue"
  },
  "geometry": {"coordinates":[-71.8024,42.257756],"type":"Point"}
}
