{
  "type": "Feature",
  "properties": {
    "iso:country":"US",
    "sg:address":"60 Madison St",
    "sg:city":"Worcester",
    "sg:classifiers":[
        {
            "category":"Restaurant",
            "type":"Food & Drink"
        }
    ],
    "sg:phone":"+1 508 791 9577",
    "sg:postcode":"01608",
    "sg:province":"MA",
    "sg:tags":[
        "chinese"
    ],
    "wof:name":"Ping's Garden Restaurant Inc",
    "wof:placetype":"venue"
},
  "geometry": {"coordinates":[-71.80240000000001,42.257756],"type":"Point"}
}