{
  "type": "Feature",
  "properties": {
    "addr:full":"196 E Main St Milford MA 01757",
    "addr:housenumber":"196",
    "addr:postcode":"01757",
    "addr:street":"E Main St",
    "iso:country":"US",
    "sg:address":"196 E Main St",
    "sg:city":"Milford",
    "sg:classifiers":[
        {
            "category":"Restaurant",
            "type":"Food & Drink"
        }
    ],
    "sg:menulink":"http://www.allmenus.com/ma/milford/49288-town-house-of-pizza/menu/",
    "sg:phone":"+1 508 634 3403",
    "sg:postcode":"01757",
    "sg:province":"MA",
    "sg:tags":[
        "american",
        "pizza"
    ],
    "wof:name":"Town House Of Pizza",
    "wof:placetype":"venue"
},
  "geometry": {"coordinates":[-71.500777,42.15081],"type":"Point"}
}