{
  "type": "Feature",
  "properties": {
    "iso:country":"US",
    "sg:address":"33 Dinsmore Ave",
    "sg:city":"Framingham",
    "sg:classifiers":[
        {
            "category":"Autos & Motor Vehicles",
            "subcategory":"Automobile Sales",
            "type":"Retail Goods"
        }
    ],
    "sg:phone":"+1 508 620 7631",
    "sg:postcode":"01702",
    "sg:province":"MA",
    "sg:tags":[
        "car",
        "dealer"
    ],
    "wof:name":"Framingham Auto City",
    "wof:placetype":"venue"
},
  "geometry": {"coordinates":[-71.40007,42.296256],"type":"Point"}
}