{
  "type": "Feature",
  "properties": {
    "addr:full":"383 Middlesex Ave Wilmington MA 01887",
    "addr:housenumber":"383",
    "addr:postcode":"01887",
    "addr:street":"Middlesex Ave",
    "iso:country":"US",
    "sg:address":"383 Middlesex Ave",
    "sg:city":"Wilmington",
    "sg:classifiers":[
        {
            "category":"Organizations",
            "subcategory":"Community Association",
            "type":"Services"
        }
    ],
    "sg:phone":"+1 978 658 9443",
    "sg:postcode":"01887",
    "sg:province":"MA",
    "sg:tags":[
        "club"
    ],
    "wof:name":"Veterans Of Foreign Wars",
    "wof:placetype":"venue"
},
  "geometry": {"coordinates":[-71.15826300000001,42.569904],"type":"Point"}
}