{
  "type": "Feature",
  "properties": {
    "iso:country":"US",
    "sg:address":"25 Forbes Blvd",
    "sg:city":"Foxboro",
    "sg:classifiers":[
        {
            "category":"Insurance",
            "subcategory":"Insurance Agent",
            "type":"Services"
        },
        {
            "category":"Insurance",
            "subcategory":"Hazard Insurance",
            "type":"Services"
        }
    ],
    "sg:phone":"+1 508 549 9600",
    "sg:postcode":"02035",
    "sg:province":"MA",
    "sg:tags":[
        "insured",
        "property",
        "adjuster",
        "replacement"
    ],
    "sg:website":"http://www.imu.com",
    "wof:name":"Onebeacon Insurance Company",
    "wof:placetype":"venue"
},
  "geometry": {"coordinates":[-71.236735,42.035524],"type":"Point"}
}