{
  "type": "Feature",
  "properties": {
    "iso:country":"US",
    "sg:address":"3607 Washington Street",
    "sg:city":"Jamaica Plain",
    "sg:classifiers":[
        {
            "category":"Banks & Credit Unions",
            "subcategory":"Financial Services",
            "type":"Services"
        }
    ],
    "sg:phone":"+1 617 250 6222",
    "sg:postcode":"02130",
    "sg:province":"MA",
    "sg:tags":[
        "broker",
        "mortgage"
    ],
    "wof:name":"Naca National Office Business Office",
    "wof:placetype":"venue"
},
  "geometry": {"coordinates":[-71.11038000000001,42.303514],"type":"Point"}
}