{
  "type": "Feature",
  "properties": {
    "iso:country":"US",
    "sg:address":"120 Range Heights Rd",
    "sg:city":"Lynn",
    "sg:classifiers":[
        {
            "category":"Shopping",
            "subcategory":"Jewelry",
            "type":"Retail Goods"
        }
    ],
    "sg:phone":"+1 781 598 8007",
    "sg:postcode":"01904",
    "sg:province":"MA",
    "sg:tags":[
        "precious",
        "semi-precious",
        "stone"
    ],
    "wof:name":"Custom Funky Jewelry",
    "wof:placetype":"venue"
},
  "geometry": {"coordinates":[-70.964837,42.499548],"type":"Point"}
}