{
  "type": "Feature",
  "properties": {
    "iso:country":"US",
    "sg:address":"12 N Dartmouth Mall",
    "sg:city":"North Dartmouth",
    "sg:classifiers":[
        {
            "category":"Professional",
            "subcategory":"Research",
            "type":"Services"
        }
    ],
    "sg:phone":"+1 508 999 0634",
    "sg:postcode":"02747",
    "sg:province":"MA",
    "sg:tags":[
        "laboratory"
    ],
    "wof:name":"Aj Dental Lab",
    "wof:placetype":"venue"
},
  "geometry": {"coordinates":[-70.994158,41.641362],"type":"Point"}
}