{
  "type": "Feature",
  "properties": {
    "addr:full": "165 Central St Leominster MA 01453",
    "addr:housenumber": "165",
    "addr:postcode": "01453",
    "addr:street": "Central St",
    "iso:country": "US",
    "sg:address": "165 Central St",
    "sg:city": "Leominster",
    "sg:classifiers": [
      {
        "category": "Home \u0026 Garden",
        "subcategory": "Building Materials",
        "type": "Retail Goods"
      },
      {
        "category": "Building \u0026 Trades",
        "subcategory": "Construction",
        "type": "Services"
      },
      {
        "category": "Military Area",
        "subcategory": "Armory",
        "type": "Public Place"
      }
    ],
    "sg:phone": "+1 978 537 5822",
    "sg:postcode": "01453",
    "sg:province": "MA",
    "sg:tags": [
      "repair",
      "fence-sales",
      "fence",
      "contractor"
    ],
    "wof:name": "Leominster Fence \u0026 Deck Company",
    "wof:placetype": "venue"
  },
  "geometry": {"coordinates":[-71.758556,42.519964],"type":"Point"}
}
