{
  "type": "Feature",
  "properties": {
    "addr:full":"975 Commonwealth Ave Boston MA 02215",
    "addr:housenumber":"975",
    "addr:postcode":"02215",
    "addr:street":"Commonwealth Ave",
    "iso:country":"US",
    "sg:address":"975 Commonwealth Ave",
    "sg:city":"Boston",
    "sg:classifiers":[
        {
            "category":"Retail",
            "subcategory":"Auto Repair",
            "type":"Services"
        }
    ],
    "sg:phone":"+1 617 783 4295",
    "sg:postcode":"02215",
    "sg:province":"MA",
    "sg:tags":[
        "muffler",
        "exhaust",
        "system"
    ],
    "wof:name":"Midas Auto Svc Experts",
    "wof:placetype":"venue"
},
  "geometry": {"coordinates":[-71.118768,42.351628],"type":"Point"}
}