{
  "type": "Feature",
  "properties": {
    "addr:full":"69 Prospect St Amesbury MA 01913",
    "addr:housenumber":"69",
    "addr:postcode":"01913",
    "addr:street":"Prospect St",
    "iso:country":"US",
    "sg:address":"69 Prospect St",
    "sg:city":"Amesbury",
    "sg:classifiers":[
        {
            "category":"Building & Trades",
            "subcategory":"Construction",
            "type":"Services"
        }
    ],
    "sg:phone":"+1 978 388 7919",
    "sg:postcode":"01913",
    "sg:province":"MA",
    "sg:tags":[
        "hanging",
        "painter",
        "contractor"
    ],
    "wof:name":"Details-Details Painting",
    "wof:placetype":"venue"
},
  "geometry": {"coordinates":[-70.93321,42.863115],"type":"Point"}
}