{
  "type": "Feature",
  "properties": {
    "iso:country":"US",
    "sg:address":"14 Pond St",
    "sg:city":"Sharon",
    "sg:classifiers":[
        {
            "category":"Personal",
            "subcategory":"Beauty Salon",
            "type":"Services"
        }
    ],
    "sg:phone":"+1 781 793 0422",
    "sg:postcode":"02067",
    "sg:province":"MA",
    "sg:tags":[
        "nail",
        "manicuring"
    ],
    "wof:name":"True Nails",
    "wof:placetype":"venue"
},
  "geometry": {"coordinates":[-71.178596,42.123299],"type":"Point"}
}