{
  "type": "Feature",
  "properties": {
    "addr:full": "14 Pond St Sharon MA 02067",
    "addr:housenumber": "14",
    "addr:postcode": "02067",
    "addr:street": "Pond St",
    "iso:country": "US",
    "ovtr:label": "True Nails, 14 Pond St Sharon MA US",
    "ovtr:similarity": 2.1041409969329834,
    "sg:address": "14 Pond St",
    "sg:city": "Sharon",
    "sg:classifiers": [
      {
        "category": "Personal",
        "subcategory": "Beauty Salon",
        "type": "Services"
      }
    ],
    "sg:phone": "+1 781 793 0422",
    "sg:postcode": "02067",
    "sg:province": "MA",
    "sg:tags": [
      "nail",
      "manicuring"
    ],
    "wof:name": "True Nails",
    "wof:placetype": "venue"
  },
  "geometry": {"coordinates":[-71.178596,42.123299],"type":"Point"}
}
