{
  "type": "Feature",
  "properties": {
    "addr:full":"500C Mystic Avenue Suite 16 Somerville MA 02145",
    "addr:housenumber":"500c;16",
    "addr:postcode":"02145",
    "addr:street":"Mystic Avenue Suite",
    "iso:country":"US",
    "sg:address":"500C Mystic Avenue Suite 16",
    "sg:city":"Somerville",
    "sg:classifiers":[
        {
            "category":"Social Services",
            "subcategory":"Child Care",
            "type":"Services"
        }
    ],
    "sg:phone":"+1 617 625 8277",
    "sg:postcode":"02145",
    "sg:province":"MA",
    "sg:tags":[
        "day"
    ],
    "wof:name":"Elizabeth Peabody House",
    "wof:placetype":"venue"
},
  "geometry": {"coordinates":[-71.093322,42.398724],"type":"Point"}
}