{
  "type": "Feature",
  "properties": {
    "addr:full":"240 Kittredge St Roslindale MA 02131",
    "addr:housenumber":"240",
    "addr:postcode":"02131",
    "addr:street":"Kittredge St",
    "iso:country":"US",
    "sg:address":"240 Kittredge St",
    "sg:city":"Roslindale",
    "sg:classifiers":[
        {
            "category":"Professional",
            "subcategory":"Research",
            "type":"Services"
        }
    ],
    "sg:phone":"+1   ",
    "sg:postcode":"02131",
    "sg:province":"MA",
    "sg:tags":[
        "medical",
        "contractor"
    ],
    "wof:name":"Kyle Spear",
    "wof:placetype":"venue"
},
  "geometry": {"coordinates":[-71.13291,42.278365],"type":"Point"}
}