{
  "type": "Feature",
  "properties": {
    "addr:full":"172 Mendon St Bellingham MA 02019",
    "addr:housenumber":"172",
    "addr:postcode":"02019",
    "addr:street":"Mendon St",
    "iso:country":"US",
    "sg:address":"172 Mendon St",
    "sg:city":"Bellingham",
    "sg:classifiers":[
        {
            "category":"Retail",
            "subcategory":"Auto Repair",
            "type":"Services"
        }
    ],
    "sg:phone":"+1 508 966 2054",
    "sg:postcode":"02019",
    "sg:province":"MA",
    "sg:tags":[
        "repairing",
        "automobile"
    ],
    "wof:name":"Bellingham Imports, Inc",
    "wof:placetype":"venue"
},
  "geometry": {"coordinates":[-71.496307,42.0877],"type":"Point"}
}