{
  "type": "Feature",
  "properties": {
    "addr:full":"299 Summer St Rehoboth MA 02769",
    "addr:housenumber":"299",
    "addr:postcode":"02769",
    "addr:street":"Summer St",
    "iso:country":"US",
    "sg:address":"299 Summer St",
    "sg:city":"Rehoboth",
    "sg:classifiers":[
        {
            "category":"Professional",
            "subcategory":"Business Services",
            "type":"Services"
        }
    ],
    "sg:phone":"+1   ",
    "sg:postcode":"02769",
    "sg:province":"MA",
    "wof:name":"Edward Kingman",
    "wof:placetype":"venue"
},
  "geometry": {"coordinates":[-71.288954,41.829412],"type":"Point"}
}