{
  "type": "Feature",
  "properties": {
    "addr:full":"334 Main St Easthampton MA 01027",
    "addr:housenumber":"334",
    "addr:postcode":"01027",
    "addr:street":"Main St",
    "iso:country":"US",
    "sg:address":"334 Main St",
    "sg:city":"Easthampton",
    "sg:classifiers":[
        {
            "category":"Shopping",
            "subcategory":"Department Store",
            "type":"Retail Goods"
        },
        {
            "category":"Shopping",
            "subcategory":"Discount & Variety Stores",
            "type":"Retail Goods"
        },
        {
            "category":"Food & Beverages",
            "subcategory":"Groceries & Convenience Stores",
            "type":"Retail Goods"
        }
    ],
    "sg:phone":"+1 413 527 4618",
    "sg:postcode":"01027",
    "sg:province":"MA",
    "wof:name":"College Highway Variety",
    "wof:placetype":"venue"
},
  "geometry": {"coordinates":[-72.685625,42.259951],"type":"Point"}
}