{
  "type": "Feature",
  "properties": {
    "iso:country":"US",
    "sg:address":"528 Federal St",
    "sg:city":"Montague",
    "sg:classifiers":[
        {
            "category":"Farming",
            "subcategory":"Aquatic Farm",
            "type":"Manufacturing & Wholesale Goods"
        }
    ],
    "sg:phone":"+1 413 367 9494",
    "sg:postcode":"01351",
    "sg:province":"MA",
    "sg:tags":[
        "fish"
    ],
    "wof:name":"Red-Wing Meadow Trout Hatchery",
    "wof:placetype":"venue"
},
  "geometry": {"coordinates":[-72.528673,42.521689],"type":"Point"}
}