{
  "type": "Feature",
  "properties": {
    "iso:country":"US",
    "sg:address":"100 Main St",
    "sg:city":"Norfolk",
    "sg:classifiers":[
        {
            "category":"Recreation",
            "type":"Entertainment"
        }
    ],
    "sg:phone":"+1 508 541 3232",
    "sg:postcode":"02056",
    "sg:province":"MA",
    "sg:tags":[
        "hall",
        "auditorium"
    ],
    "wof:name":"Old Town Hall",
    "wof:placetype":"venue"
},
  "geometry": {"coordinates":[-71.320054,42.120449],"type":"Point"}
}