{
  "type": "Feature",
  "properties": {
    "addr:full": "100 Main St Norfolk MA 02056",
    "addr:housenumber": "100",
    "addr:postcode": "02056",
    "addr:street": "Main St",
    "iso:country": "US",
    "sg:address": "100 Main St",
    "sg:city": "Norfolk",
    "sg:classifiers": [
      {
        "category": "Recreation",
        "type": "Entertainment"
      }
    ],
    "sg:phone": "+1 508 541 3232",
    "sg:postcode": "02056",
    "sg:province": "MA",
    "sg:tags": [
      "hall",
      "auditorium"
    ],
    "wof:name": "Old Town Hall",
    "wof:placetype": "venue"
  },
  "geometry": {"coordinates":[-71.320054,42.120449],"type":"Point"}
}
