{
  "type": "Feature",
  "properties": {
    "addr:full": "20 Dailey Ter Fitchburg MA 01420",
    "addr:housenumber": "20",
    "addr:postcode": "01420",
    "addr:street": "Dailey Ter",
    "iso:country": "US",
    "sg:address": "20 Dailey Ter",
    "sg:city": "Fitchburg",
    "sg:classifiers": [
      {
        "category": "Building \u0026 Trades",
        "subcategory": "Landscaping Services",
        "type": "Services"
      }
    ],
    "sg:phone": "+1 978 343 6832",
    "sg:postcode": "01420",
    "sg:province": "MA",
    "sg:tags": [
      "landscape",
      "contractor"
    ],
    "wof:name": "Contemporary Design \u0026 Constr",
    "wof:placetype": "venue"
  },
  "geometry": {"coordinates":[-71.782204,42.557831],"type":"Point"}
}
