{
  "type": "Feature",
  "properties": {
    "addr:full": "17 Main St South Grafton MA 01560",
    "addr:housenumber": "17",
    "addr:postcode": "01560",
    "addr:street": "Main St",
    "iso:country": "US",
    "sg:address": "17 Main St",
    "sg:city": "South Grafton",
    "sg:classifiers": [
      {
        "category": "Shopping",
        "subcategory": "Computers \u0026 Home Electronics",
        "type": "Retail Goods"
      }
    ],
    "sg:phone": "+1 508 839 7277",
    "sg:postcode": "01560",
    "sg:province": "MA",
    "sg:tags": [
      "equipment",
      "electronic",
      "supply"
    ],
    "wof:name": "Elwin Electronic Svc",
    "wof:placetype": "venue"
  },
  "geometry": {"coordinates":[-71.683994,42.177132],"type":"Point"}
}
