{
  "type": "Feature",
  "properties": {
    "iso:country":"US",
    "sg:address":"3771 Main St",
    "sg:city":"Brewster",
    "sg:classifiers":[
        {
            "category":"Building & Trades",
            "subcategory":"Cleaning & Sanitation",
            "type":"Services"
        }
    ],
    "sg:phone":"+1   ",
    "sg:postcode":"02631",
    "sg:province":"MA",
    "sg:tags":[
        "maintenance",
        "architectural"
    ],
    "wof:name":"Wanamaker Cnstr & Design",
    "wof:placetype":"venue"
},
  "geometry": {"coordinates":[-70.023517,41.775783],"type":"Point"}
}