{
  "type": "Feature",
  "properties": {
    "addr:full": "3771 Main St Brewster MA 02631",
    "addr:housenumber": "3771",
    "addr:postcode": "02631",
    "addr:street": "Main St",
    "iso:country": "US",
    "sg:address": "3771 Main St",
    "sg:city": "Brewster",
    "sg:classifiers": [
      {
        "category": "Building \u0026 Trades",
        "subcategory": "Cleaning \u0026 Sanitation",
        "type": "Services"
      }
    ],
    "sg:phone": "+1   ",
    "sg:postcode": "02631",
    "sg:province": "MA",
    "sg:tags": [
      "maintenance",
      "architectural"
    ],
    "wof:name": "Wanamaker Cnstr \u0026 Design",
    "wof:placetype": "venue"
  },
  "geometry": {"coordinates":[-70.023517,41.775783],"type":"Point"}
}
