{
  "type": "Feature",
  "properties": {
    "addr:full":"33 McHugh Ave Billerica MA 01821",
    "addr:housenumber":"33",
    "addr:postcode":"01821",
    "addr:street":"Mchugh Ave",
    "iso:country":"US",
    "sg:address":"33 McHugh Ave",
    "sg:city":"Billerica",
    "sg:classifiers":[
        {
            "category":"Professional",
            "type":"Services"
        }
    ],
    "sg:phone":"+1   ",
    "sg:postcode":"01821",
    "sg:province":"MA",
    "wof:name":"Steve Annese",
    "wof:placetype":"venue"
},
  "geometry": {"coordinates":[-71.22266500000001,42.534874],"type":"Point"}
}