{
  "type": "Feature",
  "properties": {
    "addr:full": "647 Park Ave Revere MA 02151",
    "addr:housenumber": "647",
    "addr:postcode": "02151",
    "addr:street": "Park Ave",
    "iso:country": "US",
    "sg:address": "647 Park Ave",
    "sg:city": "Revere",
    "sg:classifiers": [
      {
        "category": "Building \u0026 Trades",
        "subcategory": "Electrical",
        "type": "Services"
      }
    ],
    "sg:phone": "+1 781 284 4533",
    "sg:postcode": "02151",
    "sg:province": "MA",
    "sg:tags": [
      "electrician"
    ],
    "wof:name": "Frank Iannuzzi Electric",
    "wof:placetype": "venue"
  },
  "geometry": {"coordinates":[-71.029226,42.414583],"type":"Point"}
}
