{
  "type": "Feature",
  "properties": {
    "addr:full":"20 Douglas Ave Wilmington MA 01887",
    "addr:housenumber":"20",
    "addr:postcode":"01887",
    "addr:street":"Douglas Ave",
    "iso:country":"US",
    "sg:address":"20 Douglas Ave",
    "sg:city":"Wilmington",
    "sg:classifiers":[
        {
            "category":"Shopping",
            "subcategory":"Gifts & Souvenirs",
            "type":"Retail Goods"
        }
    ],
    "sg:phone":"+1   ",
    "sg:postcode":"01887",
    "sg:province":"MA",
    "sg:tags":[
        "real estate"
    ],
    "wof:name":"Something Special",
    "wof:placetype":"venue"
},
  "geometry": {"coordinates":[-71.163253,42.563559],"type":"Point"}
}