{
  "type": "Feature",
  "properties": {
    "iso:country":"US",
    "sg:address":"991 Main St",
    "sg:city":"Waltham",
    "sg:classifiers":[
        {
            "category":"Retail",
            "subcategory":"Laundry & Dry Cleaning",
            "type":"Services"
        }
    ],
    "sg:phone":"+1 781 894 8641",
    "sg:postcode":"02451",
    "sg:province":"MA",
    "wof:name":"Bubbles Laundromat",
    "wof:placetype":"venue"
},
  "geometry": {"coordinates":[-71.252149,42.376318],"type":"Point"}
}