{
  "type": "Feature",
  "properties": {
    "iso:country":"US",
    "sg:address":"555 Main St",
    "sg:city":"Harwich",
    "sg:classifiers":[
        {
            "category":"Food & Beverages",
            "subcategory":"Liquor & Beverages",
            "type":"Retail Goods"
        }
    ],
    "sg:phone":"+1 508 432 8250",
    "sg:postcode":"02645",
    "sg:province":"MA",
    "wof:name":"Cranberry Liquors",
    "wof:placetype":"venue"
},
  "geometry": {"coordinates":[-70.089629,41.687309],"type":"Point"}
}