{
  "type": "Feature",
  "properties": {
    "addr:full":"67 Jeffrey Ave Holliston MA 01746",
    "addr:housenumber":"67",
    "addr:postcode":"01746",
    "addr:street":"Jeffrey Ave",
    "iso:country":"US",
    "sg:address":"67 Jeffrey Ave",
    "sg:city":"Holliston",
    "sg:classifiers":[
        {
            "category":"Building & Trades",
            "subcategory":"Landscaping Services",
            "type":"Services"
        }
    ],
    "sg:phone":"+1 508 376 0111",
    "sg:postcode":"01746",
    "sg:province":"MA",
    "sg:tags":[
        "landscape",
        "contractor"
    ],
    "wof:name":"Grasshopper Tree & Landscp Inc",
    "wof:placetype":"venue"
},
  "geometry": {"coordinates":[-71.41125700000001,42.211181],"type":"Point"}
}