{
  "type": "Feature",
  "properties": {
    "iso:country":"US",
    "sg:address":"48 Folly Mill Rd",
    "sg:city":"Salisbury",
    "sg:classifiers":[
        {
            "category":"Professional",
            "subcategory":"Secretarial Services",
            "type":"Services"
        }
    ],
    "sg:phone":"+1   ",
    "sg:postcode":"01952",
    "sg:province":"MA",
    "sg:tags":[
        "reporting"
    ],
    "wof:name":"Roberts Court Reporting",
    "wof:placetype":"venue"
},
  "geometry": {"coordinates":[-70.90110199999999,42.882002],"type":"Point"}
}