{
  "type": "Feature",
  "properties": {
    "addr:full": "50 D'Angelo Dr Marlborough MA 01752",
    "addr:housenumber": "50",
    "addr:postcode": "01752",
    "addr:street": "D'Angelo Dr",
    "iso:country": "US",
    "sg:address": "50 D'Angelo Dr",
    "sg:city": "Marlborough",
    "sg:classifiers": [
      {
        "category": "Professional",
        "subcategory": "Research",
        "type": "Services"
      }
    ],
    "sg:phone": "+1 508 229 2270",
    "sg:postcode": "01752",
    "sg:province": "MA",
    "sg:tags": [
      "environmental",
      "ecological"
    ],
    "sg:website": "www.ecc.net",
    "wof:name": "Environmental Chemical Corp",
    "wof:placetype": "venue"
  },
  "geometry": {"coordinates":[-71.581886,42.314532],"type":"Point"}
}
