{
  "type": "Feature",
  "properties": {
    "iso:country":"US",
    "sg:address":"141 Baldwin Rd",
    "sg:city":"Billerica",
    "sg:classifiers":[
        {
            "category":"Government",
            "subcategory":"Court House",
            "type":"Public Place"
        }
    ],
    "sg:phone":"+1 978 670 5697",
    "sg:postcode":"01821",
    "sg:province":"MA",
    "sg:tags":[
        "justice",
        "peace"
    ],
    "wof:name":"Evelyn M Haines",
    "wof:placetype":"venue"
},
  "geometry": {"coordinates":[-71.22830399999999,42.562779],"type":"Point"}
}