{
  "type": "Feature",
  "properties": {
    "iso:country":"US",
    "sg:address":"75 Valentine Rd",
    "sg:city":"Arlington",
    "sg:classifiers":[
        {
            "category":"Building & Trades",
            "subcategory":"Landscaping Services",
            "type":"Services"
        }
    ],
    "sg:phone":"+1 781 646 5555",
    "sg:postcode":"02476",
    "sg:province":"MA",
    "sg:tags":[
        "lawn",
        "maintenance"
    ],
    "wof:name":"John's Landscape Service",
    "wof:placetype":"venue"
},
  "geometry": {"coordinates":[-71.19047500000001,42.418638],"type":"Point"}
}