{
  "type": "Feature",
  "properties": {
    "iso:country":"US",
    "sg:address":"2 Hancock St",
    "sg:city":"Quincy",
    "sg:classifiers":[
        {
            "category":"Retail",
            "subcategory":"Repair Shop",
            "type":"Services"
        }
    ],
    "sg:phone":"+1 617 471 0459",
    "sg:postcode":"02171",
    "sg:province":"MA",
    "sg:tags":[
        "welding"
    ],
    "wof:name":"E P Wiggins Welding & Mtl Fab",
    "wof:placetype":"venue"
},
  "geometry": {"coordinates":[-71.03838399999999,42.283462],"type":"Point"}
}