{
  "type": "Feature",
  "properties": {
    "iso:country":"US",
    "sg:address":"50 Pearl St",
    "sg:city":"Framingham",
    "sg:classifiers":[
        {
            "category":"Railroad",
            "type":"Transportation"
        }
    ],
    "sg:phone":"+1 508 872 2940",
    "sg:postcode":"01702",
    "sg:province":"MA",
    "wof:name":"Conrail",
    "wof:placetype":"venue"
},
  "geometry": {"coordinates":[-71.420204,42.280035],"type":"Point"}
}