{
  "type": "Feature",
  "properties": {
    "iso:country":"US",
    "sg:address":"10 Church St",
    "sg:city":"Haverhill",
    "sg:classifiers":[
        {
            "category":"Social Services",
            "subcategory":"Child Care",
            "type":"Services"
        }
    ],
    "sg:phone":"+1 978 374 5381",
    "sg:postcode":"01835",
    "sg:province":"MA",
    "wof:name":"Bradford Children's Ctr",
    "wof:placetype":"venue"
},
  "geometry": {"coordinates":[-71.077091,42.766845],"type":"Point"}
}