{
  "type": "Feature",
  "properties": {
    "addr:full":"66 Depot St Westford MA 01886",
    "addr:housenumber":"66",
    "addr:postcode":"01886",
    "addr:street":"Depot St",
    "iso:country":"US",
    "sg:address":"66 Depot St",
    "sg:city":"Westford",
    "sg:classifiers":[
        {
            "category":"Travel",
            "subcategory":"Campground",
            "type":"Entertainment"
        }
    ],
    "sg:phone":"+1 978 692 7076",
    "sg:postcode":"01886",
    "sg:province":"MA",
    "sg:tags":[
        "camp"
    ],
    "wof:name":"East Boston Camps",
    "wof:placetype":"venue"
},
  "geometry": {"coordinates":[-71.436058,42.595689],"type":"Point"}
}