{
  "type": "Feature",
  "properties": {
    "iso:country":"US",
    "sg:address":"111 Salem St Boston",
    "sg:city":"Boston",
    "sg:classifiers":[
        {
            "category":"Restaurant",
            "type":"Food & Drink"
        }
    ],
    "sg:phone":"+1 617 523 4111",
    "sg:postcode":"02113",
    "sg:province":"MA",
    "sg:tags":[
        "pizza",
        "italian"
    ],
    "sg:website":"www.beneventosboston.com/",
    "wof:name":"Benevento's",
    "wof:placetype":"venue"
},
  "geometry": {"coordinates":[-71.055528,42.364308],"type":"Point"}
}