{
  "type": "Feature",
  "properties": {
    "addr:full":"153 Cordaville Rd Southborough MA 01772",
    "addr:housenumber":"153",
    "addr:postcode":"01772",
    "addr:street":"Cordaville Rd",
    "iso:country":"US",
    "sg:address":"153 Cordaville Rd",
    "sg:city":"Southborough",
    "sg:classifiers":[
        {
            "category":"Real Estate",
            "subcategory":"Real Estate Agent",
            "type":"Services"
        }
    ],
    "sg:phone":"+1 508 303 3333",
    "sg:postcode":"01772",
    "sg:province":"MA",
    "wof:name":"Prudential Town & Country Real",
    "wof:placetype":"venue"
},
  "geometry": {"coordinates":[-71.526036,42.286432],"type":"Point"}
}