{
  "type": "Feature",
  "properties": {
    "addr:full": "54 Longmeadow Rd Taunton MA 02780",
    "addr:housenumber": "54",
    "addr:postcode": "02780",
    "addr:street": "Longmeadow Rd",
    "iso:country": "US",
    "sg:address": "54 Longmeadow Rd",
    "sg:city": "Taunton",
    "sg:classifiers": [
      {
        "category": "Banks \u0026 Credit Unions",
        "subcategory": "Investment Brokerage",
        "type": "Services"
      }
    ],
    "sg:phone": "+1   ",
    "sg:postcode": "02780",
    "sg:province": "MA",
    "sg:tags": [
      "security",
      "management",
      "consulting"
    ],
    "wof:name": "Paul F Therrien",
    "wof:placetype": "venue"
  },
  "geometry": {"coordinates":[-71.076761,41.905447],"type":"Point"}
}
