{
  "type": "Feature",
  "properties": {
    "iso:country":"US",
    "sg:address":"54 Longmeadow Rd",
    "sg:city":"Taunton",
    "sg:classifiers":[
        {
            "category":"Banks & Credit Unions",
            "subcategory":"Investment Brokerage",
            "type":"Services"
        }
    ],
    "sg:phone":"+1   ",
    "sg:postcode":"02780",
    "sg:province":"MA",
    "sg:tags":[
        "security",
        "management",
        "consulting"
    ],
    "wof:name":"Paul F Therrien",
    "wof:placetype":"venue"
},
  "geometry": {"coordinates":[-71.076761,41.905447],"type":"Point"}
}