{
  "type": "Feature",
  "properties": {
    "addr:full": "62 Chestnut St Florence MA 01062",
    "addr:housenumber": "62",
    "addr:postcode": "01062",
    "addr:street": "Chestnut St",
    "iso:country": "US",
    "sg:address": "62 Chestnut St",
    "sg:city": "Florence",
    "sg:classifiers": [
      {
        "category": "Travel",
        "subcategory": "Hotels \u0026 Motels",
        "type": "Entertainment"
      }
    ],
    "sg:phone": "+1 413 585 8559",
    "sg:postcode": "01062",
    "sg:province": "MA",
    "sg:tags": [
      "breakfast",
      "accommodation",
      "bed"
    ],
    "wof:name": "Sugar Maple Trailside Inn",
    "wof:placetype": "venue"
  },
  "geometry": {"coordinates":[-72.667069,42.336825],"type":"Point"}
}
