{
  "type": "Feature",
  "properties": {
    "iso:country":"US",
    "sg:address":"62 Chestnut St",
    "sg:city":"Florence",
    "sg:classifiers":[
        {
            "category":"Travel",
            "subcategory":"Hotels & Motels",
            "type":"Entertainment"
        }
    ],
    "sg:phone":"+1 413 585 8559",
    "sg:postcode":"01062",
    "sg:province":"MA",
    "sg:tags":[
        "breakfast",
        "accommodation",
        "bed"
    ],
    "wof:name":"Sugar Maple Trailside Inn",
    "wof:placetype":"venue"
},
  "geometry": {"coordinates":[-72.667069,42.336825],"type":"Point"}
}