{
  "type": "Feature",
  "properties": {
    "addr:full":"46 Bennington St Boston MA 02128",
    "addr:housenumber":"46",
    "addr:postcode":"02128",
    "addr:street":"Bennington St",
    "iso:country":"US",
    "sg:address":"46 Bennington St",
    "sg:city":"Boston",
    "sg:classifiers":[
        {
            "category":"Professional",
            "subcategory":"Lawyer & Legal Services",
            "type":"Services"
        }
    ],
    "sg:phone":"+1 617 567 7750",
    "sg:postcode":"02128",
    "sg:province":"MA",
    "sg:tags":[
        "personal",
        "injury"
    ],
    "wof:name":"Law Office of Alessandra Petruccelli",
    "wof:placetype":"venue"
},
  "geometry": {"coordinates":[-71.037102,42.375599],"type":"Point"}
}