{
  "type": "Feature",
  "properties": {
    "addr:full":"22 Industry Rd Chicopee MA 01020",
    "addr:housenumber":"22",
    "addr:postcode":"01020",
    "addr:street":"Industry Rd",
    "iso:country":"US",
    "sg:address":"22 Industry Rd",
    "sg:city":"Chicopee",
    "sg:classifiers":[
        {
            "category":"Wholesale",
            "subcategory":"Construction Materials",
            "type":"Manufacturing & Wholesale Goods"
        }
    ],
    "sg:phone":"+1 413 594 6300",
    "sg:postcode":"01020",
    "sg:province":"MA",
    "sg:tags":[
        "lumber"
    ],
    "wof:name":"Holden Humphrey Co",
    "wof:placetype":"venue"
},
  "geometry": {"coordinates":[-72.55269800000001,42.15707],"type":"Point"}
}