{
  "type": "Feature",
  "properties": {
    "iso:country":"US",
    "sg:address":"295 S Main St",
    "sg:city":"Sheffield",
    "sg:classifiers":[
        {
            "category":"Professional",
            "type":"Services"
        }
    ],
    "sg:phone":"+1 413 229 2988",
    "sg:postcode":"01257",
    "sg:province":"MA",
    "sg:tags":[
        "landscaping",
        "lawn"
    ],
    "wof:name":"Cross Horticultural Services",
    "wof:placetype":"venue"
},
  "geometry": {"coordinates":[-73.352997,42.098675],"type":"Point"}
}