{
  "type": "Feature",
  "properties": {
    "addr:full": "222 Berkeley St Boston MA 02116",
    "addr:housenumber": "222",
    "addr:postcode": "02116",
    "addr:street": "Berkeley St",
    "iso:country": "US",
    "sg:address": "222 Berkeley St",
    "sg:city": "Boston",
    "sg:classifiers": [
      {
        "category": "Banks \u0026 Credit Unions",
        "subcategory": "Bank",
        "type": "Services"
      }
    ],
    "sg:phone": "+1 617 375 7875",
    "sg:postcode": "02116",
    "sg:province": "MA",
    "wof:name": "CIBC World Markets",
    "wof:placetype": "venue"
  },
  "geometry": {"coordinates":[-71.073029,42.350924],"type":"Point"}
}
