{
  "type": "Feature",
  "properties": {
    "iso:country":"US",
    "sg:address":"300 Hillcrest Rd",
    "sg:city":"Needham",
    "sg:classifiers":[
        {
            "category":"Building & Trades",
            "subcategory":"Construction",
            "type":"Services"
        }
    ],
    "sg:phone":"+1 781 453 0729",
    "sg:postcode":"02492",
    "sg:province":"MA",
    "sg:tags":[
        "contractor",
        "painting",
        "hanging"
    ],
    "sg:website":"http://www.beaconpainters.com",
    "wof:name":"Beacon Painters Inc",
    "wof:placetype":"venue"
},
  "geometry": {"coordinates":[-71.21865,42.286194],"type":"Point"}
}