{
  "type": "Feature",
  "properties": {
    "addr:full":"520 Pleasant St Winthrop MA 02152",
    "addr:housenumber":"520",
    "addr:postcode":"02152",
    "addr:street":"Pleasant St",
    "iso:country":"US",
    "sg:address":"520 Pleasant St",
    "sg:city":"Winthrop",
    "sg:classifiers":[
        {
            "category":"Social Services",
            "subcategory":"Child Care",
            "type":"Services"
        }
    ],
    "sg:phone":"+1 617 846 5813",
    "sg:postcode":"02152",
    "sg:province":"MA",
    "wof:name":"Pleasant Times Daycare",
    "wof:placetype":"venue"
},
  "geometry": {"coordinates":[-70.99196999999999,42.378781],"type":"Point"}
}