{
  "type": "Feature",
  "properties": {
    "iso:country":"US",
    "sg:address":"935 Riverdale St",
    "sg:city":"West Springfield",
    "sg:classifiers":[
        {
            "category":"Shopping",
            "subcategory":"Clothing, Apparel, & Fashions",
            "type":"Retail Goods"
        }
    ],
    "sg:phone":"+1 413 732 5700",
    "sg:postcode":"01089",
    "sg:province":"MA",
    "wof:name":"Dress Barn",
    "wof:placetype":"venue"
},
  "geometry": {"coordinates":[-72.626548,42.128914],"type":"Point"}
}