{
  "type": "Feature",
  "properties": {
    "iso:country":"US",
    "sg:address":"1655 Main St",
    "sg:city":"Springfield",
    "sg:classifiers":[
        {
            "category":"Personal",
            "subcategory":"Beauty Salon",
            "type":"Services"
        }
    ],
    "sg:phone":"+1 413 739 0225",
    "sg:postcode":"01103",
    "sg:province":"MA",
    "wof:name":"Vincent's Beauty Salon",
    "wof:placetype":"venue"
},
  "geometry": {"coordinates":[-72.59391599999999,42.104231],"type":"Point"}
}