{
  "type": "Feature",
  "properties": {
    "iso:country":"US",
    "sg:address":"343 Torrey St",
    "sg:city":"Brockton",
    "sg:classifiers":[
        {
            "category":"Food & Beverages",
            "subcategory":"Groceries & Convenience Stores",
            "type":"Retail Goods"
        }
    ],
    "sg:phone":"+1 508 941 6550",
    "sg:postcode":"02301",
    "sg:province":"MA",
    "wof:name":"Sona's One Stop",
    "wof:placetype":"venue"
},
  "geometry": {"coordinates":[-71.058818,42.071738],"type":"Point"}
}