{
  "type": "Feature",
  "properties": {
    "addr:full": "343 Torrey St Brockton MA 02301",
    "addr:housenumber": "343",
    "addr:postcode": "02301",
    "addr:street": "Torrey St",
    "iso:country": "US",
    "ovtr:label": "Sona's One Stop, 343 Torrey St Brockton MA US",
    "ovtr:similarity": 2.167651891708374,
    "sg:address": "343 Torrey St",
    "sg:city": "Brockton",
    "sg:classifiers": [
      {
        "category": "Food \u0026 Beverages",
        "subcategory": "Groceries \u0026 Convenience Stores",
        "type": "Retail Goods"
      }
    ],
    "sg:phone": "+1 508 941 6550",
    "sg:postcode": "02301",
    "sg:province": "MA",
    "wof:name": "Sona's One Stop",
    "wof:placetype": "venue"
  },
  "geometry": {"coordinates":[-71.058818,42.071738],"type":"Point"}
}
