{
  "type": "Feature",
  "properties": {
    "addr:full": "193 Andover Rd Billerica MA 01821",
    "addr:housenumber": "193",
    "addr:postcode": "01821",
    "addr:street": "Andover Rd",
    "iso:country": "US",
    "sg:address": "193 Andover Rd",
    "sg:city": "Billerica",
    "sg:phone": "+1 978 663 8468",
    "sg:postcode": "01821",
    "sg:province": "MA",
    "wof:name": "Paul Thomas Cdl",
    "wof:placetype": "venue"
  },
  "geometry": {"coordinates":[-71.246439,42.569368],"type":"Point"}
}
