{
  "type": "Feature",
  "properties": {
    "iso:country":"US",
    "sg:address":"12 Stanley Rd",
    "sg:city":"Belmont",
    "sg:classifiers":[
        {
            "category":"Building & Trades",
            "subcategory":"Landscaping Services",
            "type":"Services"
        }
    ],
    "sg:phone":"+1   ",
    "sg:postcode":"02478",
    "sg:province":"MA",
    "sg:tags":[
        "landscape"
    ],
    "wof:name":"Victoria Hibbard Landscaping",
    "wof:placetype":"venue"
},
  "geometry": {"coordinates":[-71.19471900000001,42.397487],"type":"Point"}
}