{
  "type": "Feature",
  "properties": {
    "iso:country":"US",
    "sg:address":"100 State St Lbby",
    "sg:city":"Boston",
    "sg:classifiers":[
        {
            "category":"Professional",
            "subcategory":"Lawyer & Legal Services",
            "type":"Services"
        }
    ],
    "sg:phone":"+1 617 723 4455",
    "sg:postcode":"02109",
    "sg:province":"MA",
    "wof:name":"Phillips Dennis P Atty",
    "wof:placetype":"venue"
},
  "geometry": {"coordinates":[-71.055199,42.3591],"type":"Point"}
}