{
  "type": "Feature",
  "properties": {
    "addr:full":"10 Vinnin Sq Salem MA 01970",
    "addr:housenumber":"10",
    "addr:postcode":"01970",
    "addr:street":"Vinnin Sq",
    "iso:country":"US",
    "sg:address":"10 Vinnin Sq",
    "sg:city":"Salem",
    "sg:classifiers":[
        {
            "category":"Retail",
            "subcategory":"Funeral Services",
            "type":"Services"
        }
    ],
    "sg:phone":"+1 781 581 2300",
    "sg:postcode":"01970",
    "sg:province":"MA",
    "sg:tags":[
        "director"
    ],
    "wof:name":"Stanetsky-Hymanson Meml Chapel",
    "wof:placetype":"venue"
},
  "geometry": {"coordinates":[-70.904068,42.486205],"type":"Point"}
}