{
  "type": "Feature",
  "properties": {
    "iso:country":"US",
    "sg:address":"62 Maple St",
    "sg:city":"Danvers",
    "sg:classifiers":[
        {
            "category":"Manufacturing",
            "subcategory":"Printing",
            "type":"Manufacturing & Wholesale Goods"
        }
    ],
    "sg:phone":"+1 978 774 0564",
    "sg:postcode":"01923",
    "sg:province":"MA",
    "sg:tags":[
        "commercial"
    ],
    "wof:name":"Print One",
    "wof:placetype":"venue"
},
  "geometry": {"coordinates":[-70.936847,42.566795],"type":"Point"}
}