{
  "type": "Feature",
  "properties": {
    "iso:country":"US",
    "sg:address":"900 Main St",
    "sg:city":"Worcester",
    "sg:classifiers":[
        {
            "category":"Health Services",
            "subcategory":"Health Practitioner",
            "type":"Services"
        }
    ],
    "sg:phone":"+1 508 754 7324",
    "sg:postcode":"01610",
    "sg:province":"MA",
    "sg:tags":[
        "nurse",
        "registry"
    ],
    "wof:name":"Seraphic Springs Health Care",
    "wof:placetype":"venue"
},
  "geometry": {"coordinates":[-71.822799,42.249918],"type":"Point"}
}