{
  "type": "Feature",
  "properties": {
    "addr:full": "407 Main St Worcester MA 01608",
    "addr:housenumber": "407",
    "addr:postcode": "01608",
    "addr:street": "Main St",
    "iso:country": "US",
    "ovtr:label": "Woosta Pizza, 407 Main St Worcester MA US",
    "ovtr:similarity": 2.1785550117492676,
    "sg:address": "407 Main St",
    "sg:city": "Worcester",
    "sg:classifiers": [
      {
        "category": "Restaurant",
        "type": "Food \u0026 Drink"
      }
    ],
    "sg:phone": "+1 508 792 0888",
    "sg:postcode": "01608",
    "sg:province": "MA",
    "sg:tags": [
      "pizza"
    ],
    "wof:name": "Woosta Pizza",
    "wof:placetype": "venue"
  },
  "geometry": {"coordinates":[-71.80193,42.26393],"type":"Point"}
}
