{
  "type": "Feature",
  "properties": {
    "addr:full": "713 W Royalston Rd Athol MA 01331",
    "addr:housenumber": "713",
    "addr:postcode": "01331",
    "addr:street": "W Royalston Rd",
    "iso:country": "US",
    "sg:address": "713 W Royalston Rd",
    "sg:city": "Athol",
    "sg:classifiers": [
      {
        "category": "Building \u0026 Trades",
        "subcategory": "Construction",
        "type": "Services"
      }
    ],
    "sg:phone": "+1 978 249 2250",
    "sg:postcode": "01331",
    "sg:province": "MA",
    "sg:tags": [
      "roofing",
      "contractor"
    ],
    "wof:name": "Brockney's Roofing",
    "wof:placetype": "venue"
  },
  "geometry": {"coordinates":[-72.225628,42.620065],"type":"Point"}
}
