{
  "type": "Feature",
  "properties": {
    "iso:country":"US",
    "sg:address":"1030 University Ave",
    "sg:city":"Norwood",
    "sg:classifiers":[
        {
            "category":"Wholesale",
            "subcategory":"Hardware",
            "type":"Manufacturing & Wholesale Goods"
        }
    ],
    "sg:phone":"+1 781 551 4450",
    "sg:postcode":"02062",
    "sg:province":"MA",
    "sg:tags":[
        "ice",
        "freezer",
        "cream"
    ],
    "sg:website":"www.taylornewengland.com",
    "wof:name":"Taylor Freezer Of New England",
    "wof:placetype":"venue"
},
  "geometry": {"coordinates":[-71.17895,42.206277],"type":"Point"}
}