{
  "type": "Feature",
  "properties": {
    "addr:full": "548 Ferry St Everett MA 02149",
    "addr:housenumber": "548",
    "addr:postcode": "02149",
    "addr:street": "Ferry St",
    "iso:country": "US",
    "sg:address": "548 Ferry St",
    "sg:city": "Everett",
    "sg:classifiers": [
      {
        "category": "Personal",
        "subcategory": "Beauty Salon",
        "type": "Services"
      }
    ],
    "sg:phone": "+1 617 387 8040",
    "sg:postcode": "02149",
    "sg:province": "MA",
    "sg:tags": [
      "shop"
    ],
    "wof:name": "Fashions Delight Beauty Salon",
    "wof:placetype": "venue"
  },
  "geometry": {"coordinates":[-71.054757,42.420117],"type":"Point"}
}
