{
  "type": "Feature",
  "properties": {
    "iso:country":"US",
    "sg:address":"695 Atlantic Ave",
    "sg:city":"Boston",
    "sg:classifiers":[
        {
            "category":"Professional",
            "type":"Services"
        }
    ],
    "sg:phone":"+1 617 951 1522",
    "sg:postcode":"02111",
    "sg:province":"MA",
    "sg:tags":[
        "establishment"
    ],
    "wof:name":"SRB Corp",
    "wof:placetype":"venue"
},
  "geometry": {"coordinates":[-71.056082,42.351568],"type":"Point"}
}