{
  "type": "Feature",
  "properties": {
    "iso:country":"US",
    "sg:address":"36 Mill St",
    "sg:city":"Hardwick",
    "sg:classifiers":[
        {
            "category":"Manufacturing",
            "subcategory":"Rubber & Plastics",
            "type":"Manufacturing & Wholesale Goods"
        }
    ],
    "sg:phone":"+1 413 477 6637",
    "sg:postcode":"01057",
    "sg:province":"MA",
    "sg:website":"www.raitto.com",
    "wof:name":"Raitto Engineering & Mfg Co",
    "wof:placetype":"venue"
},
  "geometry": {"coordinates":[-72.322541,42.108346],"type":"Point"}
}