{
  "type": "Feature",
  "properties": {
    "addr:full": "127 Franklin St Reading MA 01867",
    "addr:housenumber": "127",
    "addr:postcode": "01867",
    "addr:street": "Franklin St",
    "iso:country": "US",
    "ovtr:label": "Colonial Manor Realty, 127 Franklin St Reading MA US",
    "ovtr:similarity": 2.6562039852142334,
    "sg:address": "127 Franklin St",
    "sg:city": "Reading",
    "sg:classifiers": [
      {
        "category": "Real Estate",
        "subcategory": "Real Estate Agent",
        "type": "Services"
      }
    ],
    "sg:phone": "+1 781 944 6300",
    "sg:postcode": "01867",
    "sg:province": "MA",
    "sg:website": "www.colonialmanorrealty.com",
    "wof:name": "Colonial Manor Realty",
    "wof:placetype": "venue"
  },
  "geometry": {"coordinates":[-71.104307,42.554218],"type":"Point"}
}
