{
  "type": "Feature",
  "properties": {
    "iso:country":"US",
    "sg:address":"185 New Boston St Ste 1",
    "sg:city":"Woburn",
    "sg:classifiers":[
        {
            "category":"Shopping",
            "subcategory":"Optician",
            "type":"Retail Goods"
        }
    ],
    "sg:phone":"+1 781 933 9243",
    "sg:postcode":"01801",
    "sg:province":"MA",
    "sg:tags":[
        "eyewear"
    ],
    "wof:name":"Morton Advances Materials",
    "wof:placetype":"venue"
},
  "geometry": {"coordinates":[-71.14340199999999,42.511902],"type":"Point"}
}