{
  "type": "Feature",
  "properties": {
    "addr:full": "198 Bourne Rd Plymouth MA 02360",
    "addr:housenumber": "198",
    "addr:postcode": "02360",
    "addr:street": "Bourne Rd",
    "iso:country": "US",
    "sg:address": "198 Bourne Rd",
    "sg:city": "Plymouth",
    "sg:classifiers": [
      {
        "category": "Building \u0026 Trades",
        "subcategory": "Cleaning \u0026 Sanitation",
        "type": "Services"
      }
    ],
    "sg:phone": "+1 508 224 6614",
    "sg:postcode": "02360",
    "sg:province": "MA",
    "sg:tags": [
      "janitor"
    ],
    "wof:name": "A-1 Clean Team Inc",
    "wof:placetype": "venue"
  },
  "geometry": {"coordinates":[-70.607684,41.83394],"type":"Point"}
}
