{
  "type": "Feature",
  "properties": {
    "iso:country":"US",
    "sg:address":"198 Bourne Rd",
    "sg:city":"Plymouth",
    "sg:classifiers":[
        {
            "category":"Building & Trades",
            "subcategory":"Cleaning & Sanitation",
            "type":"Services"
        }
    ],
    "sg:phone":"+1 508 224 6614",
    "sg:postcode":"02360",
    "sg:province":"MA",
    "sg:tags":[
        "janitor"
    ],
    "wof:name":"A-1 Clean Team Inc",
    "wof:placetype":"venue"
},
  "geometry": {"coordinates":[-70.60768400000001,41.83394],"type":"Point"}
}