{
  "type": "Feature",
  "properties": {
    "addr:full":"15 Parker St Gloucester MA 01930",
    "addr:housenumber":"15",
    "addr:postcode":"01930",
    "addr:street":"Parker St",
    "iso:country":"US",
    "sg:address":"15 Parker St",
    "sg:city":"Gloucester",
    "sg:classifiers":[
        {
            "category":"Professional",
            "type":"Services"
        }
    ],
    "sg:phone":"+1 978 282 4847",
    "sg:postcode":"01930",
    "sg:province":"MA",
    "sg:tags":[
        "establishment"
    ],
    "wof:name":"Massachusetts Fishermen's",
    "wof:placetype":"venue"
},
  "geometry": {"coordinates":[-70.650306,42.61569],"type":"Point"}
}