{
  "type": "Feature",
  "properties": {
    "iso:country":"US",
    "sg:address":"88 E Newton St 511D",
    "sg:city":"Boston",
    "sg:classifiers":[
        {
            "category":"Health Services",
            "subcategory":"Doctor",
            "type":"Services"
        }
    ],
    "sg:phone":"+1 617 638 8430",
    "sg:postcode":"02118",
    "sg:province":"MA",
    "sg:tags":[
        "physician",
        "surgeon",
        "surgeons",
        "surgery-general"
    ],
    "wof:name":"Boston Medical Center",
    "wof:placetype":"venue"
},
  "geometry": {"coordinates":[-71.07147999999999,42.337095],"type":"Point"}
}