{
  "type": "Feature",
  "properties": {
    "addr:full":"535 Canton Ave Milton MA 02186",
    "addr:housenumber":"535",
    "addr:postcode":"02186",
    "addr:street":"Canton Ave",
    "iso:country":"US",
    "sg:address":"535 Canton Ave",
    "sg:city":"Milton",
    "sg:classifiers":[
        {
            "category":"Social Services",
            "subcategory":"Child Care",
            "type":"Services"
        }
    ],
    "sg:phone":"+1 617 696 3030",
    "sg:postcode":"02186",
    "sg:province":"MA",
    "sg:tags":[
        "kindergarten",
        "academic",
        "school"
    ],
    "wof:name":"Carriage House Nursery School",
    "wof:placetype":"venue"
},
  "geometry": {"coordinates":[-71.082106,42.252044],"type":"Point"}
}