{
  "type": "Feature",
  "properties": {
    "addr:full": "26 South St Marblehead MA 01945",
    "addr:housenumber": "26",
    "addr:postcode": "01945",
    "addr:street": "South St",
    "iso:country": "US",
    "sg:address": "26 South St",
    "sg:city": "Marblehead",
    "sg:classifiers": [
      {
        "category": "Manufacturing",
        "subcategory": "Chemicals \u0026 Compounds",
        "type": "Manufacturing \u0026 Wholesale Goods"
      }
    ],
    "sg:phone": "+1 617 353 1884",
    "sg:postcode": "01945",
    "sg:province": "MA",
    "sg:tags": [
      "chemicals-wholesale",
      "manufacturer"
    ],
    "wof:name": "Repele International",
    "wof:placetype": "venue"
  },
  "geometry": {"coordinates":[-70.853961,42.501447],"type":"Point"}
}
