{
  "type": "Feature",
  "properties": {
    "iso:country":"US",
    "sg:address":"94 Main St",
    "sg:city":"Hatfield",
    "sg:classifiers":[
        {
            "category":"Banks & Credit Unions",
            "subcategory":"Investment Brokerage",
            "type":"Services"
        }
    ],
    "sg:phone":"+1 413 247 9405",
    "sg:postcode":"01038",
    "sg:province":"MA",
    "sg:tags":[
        "consultant",
        "planning",
        "financial"
    ],
    "wof:name":"Money Concepts Of Hatfield",
    "wof:placetype":"venue"
},
  "geometry": {"coordinates":[-72.595573,42.375758],"type":"Point"}
}