{
  "type": "Feature",
  "properties": {
    "addr:full":"29 Conwell St Somerville MA 02143",
    "addr:housenumber":"29",
    "addr:postcode":"02143",
    "addr:street":"Conwell St",
    "iso:country":"US",
    "sg:address":"29 Conwell St",
    "sg:city":"Somerville",
    "sg:classifiers":[
        {
            "category":"Professional",
            "subcategory":"Management & Consulting",
            "type":"Services"
        }
    ],
    "sg:phone":"+1 617 776 7411",
    "sg:postcode":"02143",
    "sg:province":"MA",
    "sg:tags":[
        "consultant",
        "educational"
    ],
    "wof:name":"Marya Axner Consulting",
    "wof:placetype":"venue"
},
  "geometry": {"coordinates":[-71.111598,42.390643],"type":"Point"}
}