{
  "type": "Feature",
  "properties": {
    "addr:full": "135 Pierce Rd New Braintree MA 01531",
    "addr:housenumber": "135",
    "addr:postcode": "01531",
    "addr:street": "Pierce Rd",
    "iso:country": "US",
    "sg:address": "135 Pierce Rd",
    "sg:city": "New Braintree",
    "sg:classifiers": [
      {
        "category": "Utilities",
        "type": "Services"
      }
    ],
    "sg:phone": "+1 508 867 0099",
    "sg:postcode": "01531",
    "sg:province": "MA",
    "sg:tags": [
      "sweeping"
    ],
    "wof:name": "Great Oak Svc",
    "wof:placetype": "venue"
  },
  "geometry": {"coordinates":[-72.149601,42.293578],"type":"Point"}
}
