{
  "type": "Feature",
  "properties": {
    "addr:full": "775 Centre St Jamaica Plain MA 02130",
    "addr:housenumber": "775",
    "addr:postcode": "02130",
    "addr:street": "Centre St",
    "iso:country": "US",
    "sg:address": "775 Centre St",
    "sg:city": "Jamaica Plain",
    "sg:classifiers": [
      {
        "category": "Restaurant",
        "type": "Food \u0026 Drink"
      }
    ],
    "sg:phone": "+1 617 522 4154",
    "sg:postcode": "02130",
    "sg:province": "MA",
    "sg:tags": [
      "pizza"
    ],
    "sg:website": "www.jphouseofpizza.com",
    "wof:name": "Jamaica Plain House of Pizza",
    "wof:placetype": "venue"
  },
  "geometry": {"coordinates":[-71.115478,42.310063],"type":"Point"}
}
