{
  "type": "Feature",
  "properties": {
    "addr:full": "89 French King Hwy Greenfield MA 01301",
    "addr:housenumber": "89",
    "addr:postcode": "01301",
    "addr:street": "French King Hwy",
    "iso:country": "US",
    "sg:address": "89 French King Hwy",
    "sg:city": "Greenfield",
    "sg:classifiers": [
      {
        "category": "Bakery",
        "type": "Food \u0026 Drink"
      },
      {
        "category": "Coffee \u0026 Tea",
        "type": "Food \u0026 Drink"
      },
      {
        "category": "Bagels",
        "type": "Food \u0026 Drink"
      },
      {
        "category": "Donuts",
        "type": "Food \u0026 Drink"
      }
    ],
    "sg:menulink": "http://www.allmenus.com/ma/greenfield/142946-dunkin-donuts/menu/",
    "sg:phone": "+1 413 774 6096",
    "sg:postcode": "01301",
    "sg:province": "MA",
    "sg:tags": [
      "american",
      "diner",
      "pastry"
    ],
    "wof:name": "Dunkin' Donuts",
    "wof:placetype": "venue"
  },
  "geometry": {"coordinates":[-72.573785,42.607567],"type":"Point"}
}
