{
  "type": "Feature",
  "properties": {
    "addr:full": "60 Hilldale Ave Haverhill MA 01832",
    "addr:housenumber": "60",
    "addr:postcode": "01832",
    "addr:street": "Hilldale Ave",
    "iso:country": "US",
    "sg:address": "60 Hilldale Ave",
    "sg:city": "Haverhill",
    "sg:classifiers": [
      {
        "category": "Restaurant",
        "type": "Food \u0026 Drink"
      }
    ],
    "sg:phone": "+1 978 373 9960",
    "sg:postcode": "01832",
    "sg:province": "MA",
    "wof:name": "Yang's Chinese Specials",
    "wof:placetype": "venue"
  },
  "geometry": {"coordinates":[-71.090989,42.779964],"type":"Point"}
}
