{
  "type": "Feature",
  "properties": {
    "addr:full":"75 Clarendon St Boston MA 02116",
    "addr:housenumber":"75",
    "addr:postcode":"02116",
    "addr:street":"Clarendon St",
    "iso:country":"US",
    "sg:address":"75 Clarendon St",
    "sg:city":"Boston",
    "sg:classifiers":[
        {
            "category":"Real Estate",
            "subcategory":"Real Estate Operator",
            "type":"Services"
        }
    ],
    "sg:phone":"+1 617 482 6800",
    "sg:postcode":"02116",
    "sg:province":"MA",
    "sg:tags":[
        "condominium"
    ],
    "wof:name":"75 Clarendon St Condo Assn",
    "wof:placetype":"venue"
},
  "geometry": {"coordinates":[-71.073106,42.346385],"type":"Point"}
}