{
  "type": "Feature",
  "properties": {
    "addr:full": "125 Summer St Boston MA 02110",
    "addr:housenumber": "125",
    "addr:postcode": "02110",
    "addr:street": "Summer St",
    "iso:country": "US",
    "sg:address": "125 Summer St",
    "sg:city": "Boston",
    "sg:classifiers": [
      {
        "category": "Manufacturing",
        "subcategory": "Chemicals \u0026 Compounds",
        "type": "Manufacturing \u0026 Wholesale Goods"
      }
    ],
    "sg:phone": "+1 617 933 2130",
    "sg:postcode": "02110",
    "sg:province": "MA",
    "sg:tags": [
      "laboratory"
    ],
    "sg:website": "www.pther.com",
    "wof:name": "Point Therapeutics Inc",
    "wof:placetype": "venue"
  },
  "geometry": {"coordinates":[-71.05757,42.353354],"type":"Point"}
}
