{
  "type": "Feature",
  "properties": {
    "addr:full": "14 Denton Rd Wellesley MA 02482",
    "addr:housenumber": "14",
    "addr:postcode": "02482",
    "addr:street": "Denton Rd",
    "iso:country": "US",
    "sg:address": "14 Denton Rd",
    "sg:city": "Wellesley",
    "sg:classifiers": [
      {
        "category": "Health Services",
        "subcategory": "Doctor",
        "type": "Services"
      }
    ],
    "sg:phone": "+1 781 235 1007",
    "sg:postcode": "02482",
    "sg:province": "MA",
    "sg:tags": [
      "physician",
      "surgeon"
    ],
    "wof:name": "O'Sullivan Plastic Surgery",
    "wof:placetype": "venue"
  },
  "geometry": {"coordinates":[-71.293514,42.291881],"type":"Point"}
}
