{
  "type": "Feature",
  "properties": {
    "addr:full":"875 Merriam Ave Leominster MA 01453",
    "addr:housenumber":"875",
    "addr:postcode":"01453",
    "addr:street":"Merriam Ave",
    "iso:country":"US",
    "sg:address":"875 Merriam Ave",
    "sg:city":"Leominster",
    "sg:classifiers":[
        {
            "category":"Autos & Motor Vehicles",
            "subcategory":"Auto Supplies",
            "type":"Retail Goods"
        }
    ],
    "sg:phone":"+1 978 466 8801",
    "sg:postcode":"01453",
    "sg:province":"MA",
    "sg:tags":[
        "tire"
    ],
    "wof:name":"Town Fair Tire",
    "wof:placetype":"venue"
},
  "geometry": {"coordinates":[-71.78287899999999,42.551945],"type":"Point"}
}