{
  "type": "Feature",
  "properties": {
    "addr:full": "875 Merriam Ave Leominster MA 01453",
    "addr:housenumber": "875",
    "addr:postcode": "01453",
    "addr:street": "Merriam Ave",
    "iso:country": "US",
    "ovtr:label": "Town Fair Tire, 875 Merriam Ave Leominster MA US",
    "ovtr:similarity": 2.4467689990997314,
    "sg:address": "875 Merriam Ave",
    "sg:city": "Leominster",
    "sg:classifiers": [
      {
        "category": "Autos \u0026 Motor Vehicles",
        "subcategory": "Auto Supplies",
        "type": "Retail Goods"
      }
    ],
    "sg:phone": "+1 978 466 8801",
    "sg:postcode": "01453",
    "sg:province": "MA",
    "sg:tags": [
      "tire"
    ],
    "wof:name": "Town Fair Tire",
    "wof:placetype": "venue"
  },
  "geometry": {"coordinates":[-71.782879,42.551945],"type":"Point"}
}
