{
  "type": "Feature",
  "properties": {
    "iso:country":"US",
    "sg:address":"26 Vista Dr",
    "sg:city":"Danvers",
    "sg:classifiers":[
        {
            "category":"Building & Trades",
            "subcategory":"Plumbing",
            "type":"Services"
        }
    ],
    "sg:phone":"+1 978 774 4699",
    "sg:postcode":"01923",
    "sg:province":"MA",
    "sg:tags":[
        "conditioning",
        "air",
        "system",
        "contractor"
    ],
    "wof:name":"Guard Mechanical Svc Inc",
    "wof:placetype":"venue"
},
  "geometry": {"coordinates":[-70.90846000000001,42.565529],"type":"Point"}
}