{
  "type": "Feature",
  "properties": {
    "iso:country":"US",
    "sg:address":"4 Northwest Rd",
    "sg:city":"Spencer",
    "sg:classifiers":[
        {
            "category":"Shopping",
            "subcategory":"Gifts & Souvenirs",
            "type":"Retail Goods"
        }
    ],
    "sg:phone":"+1 508 885 4958",
    "sg:postcode":"01562",
    "sg:province":"MA",
    "sg:tags":[
        "shop"
    ],
    "wof:name":"Primitive Thymes",
    "wof:placetype":"venue"
},
  "geometry": {"coordinates":[-72.016502,42.275601],"type":"Point"}
}