{
  "type": "Feature",
  "properties": {
    "addr:full":"222 Paradise Rd Swampscott MA 01907",
    "addr:housenumber":"222",
    "addr:postcode":"01907",
    "addr:street":"Paradise Rd",
    "iso:country":"US",
    "sg:address":"222 Paradise Rd",
    "sg:city":"Swampscott",
    "sg:classifiers":[
        {
            "category":"Autos & Motor Vehicles",
            "subcategory":"Automobile Sales",
            "type":"Retail Goods"
        }
    ],
    "sg:phone":"+1 781 599 0077",
    "sg:postcode":"01907",
    "sg:province":"MA",
    "sg:tags":[
        "car",
        "dealer"
    ],
    "wof:name":"Silver Star Motors",
    "wof:placetype":"venue"
},
  "geometry": {"coordinates":[-70.913849,42.475888],"type":"Point"}
}