{
  "type": "Feature",
  "properties": {
    "iso:country":"US",
    "sg:address":"147 Pelham St",
    "sg:city":"Methuen",
    "sg:classifiers":[
        {
            "category":"Bagels",
            "type":"Food & Drink"
        },
        {
            "category":"Coffee & Tea",
            "type":"Food & Drink"
        },
        {
            "category":"Food & Beverages",
            "subcategory":"Bakery",
            "type":"Retail Goods"
        },
        {
            "category":"Bakery",
            "type":"Food & Drink"
        },
        {
            "category":"Donuts",
            "type":"Food & Drink"
        }
    ],
    "sg:menulink":"http://www.allmenus.com/ma/methuen/143106-dunkin-donuts/menu/",
    "sg:phone":"+1 978 688 1199",
    "sg:postcode":"01844",
    "sg:province":"MA",
    "sg:tags":[
        "coffee",
        "diner",
        "tea",
        "bakery",
        "bagel",
        "american",
        "pastry"
    ],
    "wof:name":"Dunkin' Donuts",
    "wof:placetype":"venue"
},
  "geometry": {"coordinates":[-71.202922,42.728342],"type":"Point"}
}