{
  "type": "Feature",
  "properties": {
    "addr:full": "1144 Blue Hill Ave Dorchester Ctr MA 02124",
    "addr:housenumber": "1144",
    "addr:postcode": "02124",
    "addr:street": "Blue Hill Ave Dorchester Ctr",
    "iso:country": "US",
    "sg:address": "1144 Blue Hill Ave",
    "sg:city": "Dorchester Ctr",
    "sg:classifiers": [
      {
        "category": "Shopping",
        "subcategory": "Music",
        "type": "Retail Goods"
      }
    ],
    "sg:phone": "+1 617 265 0929",
    "sg:postcode": "02124",
    "sg:province": "MA",
    "sg:tags": [
      "compact",
      "record",
      "disc",
      "tape"
    ],
    "wof:name": "Vibes Records",
    "wof:placetype": "venue"
  },
  "geometry": {"coordinates":[-71.090944,42.285191],"type":"Point"}
}
