{
  "type": "Feature",
  "properties": {
    "iso:country":"US",
    "sg:address":"1144 Blue Hill Ave",
    "sg:city":"Dorchester Ctr",
    "sg:classifiers":[
        {
            "category":"Shopping",
            "subcategory":"Music",
            "type":"Retail Goods"
        }
    ],
    "sg:phone":"+1 617 265 0929",
    "sg:postcode":"02124",
    "sg:province":"MA",
    "sg:tags":[
        "compact",
        "record",
        "disc",
        "tape"
    ],
    "wof:name":"Vibes Records",
    "wof:placetype":"venue"
},
  "geometry": {"coordinates":[-71.09094399999999,42.285191],"type":"Point"}
}