{
  "type": "Feature",
  "properties": {
    "addr:full":"55 Pond Ave Brookline MA 02445",
    "addr:housenumber":"55",
    "addr:postcode":"02445",
    "addr:street":"Pond Ave",
    "iso:country":"US",
    "sg:address":"55 Pond Ave",
    "sg:city":"Brookline",
    "sg:classifiers":[
        {
            "category":"Health Services",
            "subcategory":"Doctor",
            "type":"Services"
        }
    ],
    "sg:phone":"+1 617 383 6542",
    "sg:postcode":"02445",
    "sg:province":"MA",
    "sg:tags":[
        "physician",
        "surgeon"
    ],
    "wof:name":"Ch Neurology Foundation Inc",
    "wof:placetype":"venue"
},
  "geometry": {"coordinates":[-71.11525399999999,42.329468],"type":"Point"}
}