{
  "type": "Feature",
  "properties": {
    "addr:full": "158 Reilly St Buzzards Bay MA 02542",
    "addr:housenumber": "158",
    "addr:postcode": "02542",
    "addr:street": "Reilly St",
    "iso:country": "US",
    "sg:address": "158 Reilly St",
    "sg:city": "Buzzards Bay",
    "sg:classifiers": [
      {
        "category": "Government",
        "subcategory": "Office",
        "type": "Public Place"
      }
    ],
    "sg:phone": "+1   ",
    "sg:postcode": "02542",
    "sg:province": "MA",
    "sg:tags": [
      "national",
      "security"
    ],
    "wof:name": "Air National Guard 102 Fighter",
    "wof:placetype": "venue"
  },
  "geometry": {"coordinates":[-70.521618,41.651384],"type":"Point"}
}
