{
  "type": "Feature",
  "properties": {
    "addr:full":"169 Mulberry St Springfield MA 01105",
    "addr:housenumber":"169",
    "addr:postcode":"01105",
    "addr:street":"Mulberry St",
    "iso:country":"US",
    "sg:address":"169 Mulberry St",
    "sg:city":"Springfield",
    "sg:classifiers":[
        {
            "category":"Building & Trades",
            "subcategory":"Construction",
            "type":"Services"
        }
    ],
    "sg:phone":"+1 413 237 1424",
    "sg:postcode":"01105",
    "sg:province":"MA",
    "sg:tags":[
        "acoustical",
        "contractor"
    ],
    "wof:name":"Parker Acoustical Ceilings",
    "wof:placetype":"venue"
},
  "geometry": {"coordinates":[-72.57692900000001,42.10411],"type":"Point"}
}