{
  "type": "Feature",
  "properties": {
    "addr:full": "456 Centre St Jamaica Plain MA 02130",
    "addr:housenumber": "456",
    "addr:postcode": "02130",
    "addr:street": "Centre St",
    "iso:country": "US",
    "sg:address": "456 Centre St",
    "sg:city": "Jamaica Plain",
    "sg:classifiers": [
      {
        "category": "Professional",
        "type": "Services"
      }
    ],
    "sg:phone": "+1 617 522 8452",
    "sg:postcode": "02130",
    "sg:province": "MA",
    "sg:tags": [
      "establishment"
    ],
    "wof:name": "Talca Int",
    "wof:placetype": "venue"
  },
  "geometry": {"coordinates":[-71.111058,42.320326],"type":"Point"}
}
