{
  "type": "Feature",
  "properties": {
    "addr:full": "94 Prince St Boston MA 02113",
    "addr:housenumber": "94",
    "addr:postcode": "02113",
    "addr:street": "Prince St",
    "iso:country": "US",
    "sg:address": "94 Prince St",
    "sg:city": "Boston",
    "sg:classifiers": [
      {
        "category": "Manufacturing",
        "subcategory": "Printing",
        "type": "Manufacturing \u0026 Wholesale Goods"
      }
    ],
    "sg:phone": "+1 617 720 1263",
    "sg:postcode": "02113",
    "sg:province": "MA",
    "sg:tags": [
      "screen",
      "commercial"
    ],
    "wof:name": "Silk Screening U S A",
    "wof:placetype": "venue"
  },
  "geometry": {"coordinates":[-71.056173,42.365578],"type":"Point"}
}
