{
  "type": "Feature",
  "properties": {
    "iso:country":"US",
    "sg:address":"94 Prince St",
    "sg:city":"Boston",
    "sg:classifiers":[
        {
            "category":"Manufacturing",
            "subcategory":"Printing",
            "type":"Manufacturing & Wholesale Goods"
        }
    ],
    "sg:phone":"+1 617 720 1263",
    "sg:postcode":"02113",
    "sg:province":"MA",
    "sg:tags":[
        "screen",
        "commercial"
    ],
    "wof:name":"Silk Screening U S A",
    "wof:placetype":"venue"
},
  "geometry": {"coordinates":[-71.056173,42.365578],"type":"Point"}
}