{
  "type": "Feature",
  "properties": {
    "addr:full":"114 Winthrop St Rehoboth MA 02769",
    "addr:housenumber":"114",
    "addr:postcode":"02769",
    "addr:street":"Winthrop St",
    "iso:country":"US",
    "sg:address":"114 Winthrop St",
    "sg:city":"Rehoboth",
    "sg:classifiers":[
        {
            "category":"Building & Trades",
            "subcategory":"Construction",
            "type":"Services"
        }
    ],
    "sg:phone":"+1 508 252 6188",
    "sg:postcode":"02769",
    "sg:province":"MA",
    "sg:tags":[
        "woodworker"
    ],
    "wof:name":"Heirloom Woodwork",
    "wof:placetype":"venue"
},
  "geometry": {"coordinates":[-71.221615,41.864212],"type":"Point"}
}