{
  "type": "Feature",
  "properties": {
    "iso:country":"US",
    "sg:address":"45 Wyman Street",
    "sg:city":"Stoughton",
    "sg:classifiers":[
        {
            "category":"Local Transit",
            "type":"Transportation"
        }
    ],
    "sg:phone":"+1 401 454 4246",
    "sg:postcode":"02072",
    "sg:province":"MA",
    "sg:tags":[
        "public"
    ],
    "sg:website":"www.mbta.com/schedules_and_maps/...",
    "wof:name":"Stoughton MBTA Commuter Rail Station",
    "wof:placetype":"venue"
},
  "geometry": {"coordinates":[-71.10350200000001,42.124172],"type":"Point"}
}