{
  "type": "Feature",
  "properties": {
    "addr:full": "150 Federal St Fl 3 Boston MA 02110",
    "addr:housenumber": "150;3",
    "addr:postcode": "02110",
    "addr:street": "Federal St",
    "iso:country": "US",
    "sg:address": "150 Federal St Fl 3",
    "sg:city": "Boston",
    "sg:classifiers": [
      {
        "category": "Health Services",
        "subcategory": "Doctor",
        "type": "Services"
      }
    ],
    "sg:phone": "+1 617 790 4000",
    "sg:postcode": "02110",
    "sg:province": "MA",
    "wof:name": "Massachusetts Behavioral Health Partnership",
    "wof:placetype": "venue"
  },
  "geometry": {"coordinates":[-71.05625,42.354043],"type":"Point"}
}
