{
  "type": "Feature",
  "properties": {
    "addr:full": "566 Washington St Canton MA 02021",
    "addr:housenumber": "566",
    "addr:postcode": "02021",
    "addr:street": "Washington St",
    "iso:country": "US",
    "sg:address": "566 Washington St",
    "sg:city": "Canton",
    "sg:classifiers": [
      {
        "category": "Professional",
        "subcategory": "Management \u0026 Consulting",
        "type": "Services"
      }
    ],
    "sg:phone": "+1 781 821 6279",
    "sg:postcode": "02021",
    "sg:province": "MA",
    "sg:tags": [
      "roofing",
      "consultant"
    ],
    "wof:name": "Lydon Roofing",
    "wof:placetype": "venue"
  },
  "geometry": {"coordinates":[-71.146485,42.153618],"type":"Point"}
}
