{
  "type": "Feature",
  "properties": {
    "addr:full": "83 Seaview Ave Oak Bluffs MA 02557",
    "addr:housenumber": "83",
    "addr:postcode": "02557",
    "addr:street": "Seaview Ave",
    "iso:country": "US",
    "sg:address": "83 Seaview Ave",
    "sg:city": "Oak Bluffs",
    "sg:classifiers": [
      {
        "category": "Travel",
        "subcategory": "Hotels \u0026 Motels",
        "type": "Entertainment"
      }
    ],
    "sg:phone": "+1 508 693 3955",
    "sg:postcode": "02557",
    "sg:province": "MA",
    "sg:tags": [
      "breakfast",
      "accommodation",
      "bed"
    ],
    "sg:website": "www.beachhousemv.com",
    "wof:name": "Beach House Bed \u0026 Breakfast",
    "wof:placetype": "venue"
  },
  "geometry": {"coordinates":[-70.554067,41.453075],"type":"Point"}
}
