{
  "type": "Feature",
  "properties": {
    "iso:country":"US",
    "sg:address":"145 Stedman St",
    "sg:city":"Chelmsford",
    "sg:classifiers":[
        {
            "category":"Manufacturing",
            "subcategory":"Furniture",
            "type":"Manufacturing & Wholesale Goods"
        },
        {
            "category":"Wholesale",
            "subcategory":"Home Furnishings",
            "type":"Manufacturing & Wholesale Goods"
        }
    ],
    "sg:phone":"+1 978 458 2028",
    "sg:postcode":"01824",
    "sg:province":"MA",
    "sg:tags":[
        "upholstered",
        "curtain",
        "household",
        "drapery",
        "mfg"
    ],
    "wof:name":"Cornice Designs Unlimited",
    "wof:placetype":"venue"
},
  "geometry": {"coordinates":[-71.351051,42.620864],"type":"Point"}
}