{
  "type": "Feature",
  "properties": {
    "iso:country":"US",
    "sg:address":"5 Plymouth Rd",
    "sg:city":"Wareham",
    "sg:classifiers":[
        {
            "category":"Retail",
            "subcategory":"Repair Shop",
            "type":"Services"
        }
    ],
    "sg:phone":"+1 508 996 6660",
    "sg:postcode":"02571",
    "sg:province":"MA",
    "sg:tags":[
        "lock",
        "locksmith"
    ],
    "wof:name":"Able Locksmith Shop",
    "wof:placetype":"venue"
},
  "geometry": {"coordinates":[-70.681432,41.763862],"type":"Point"}
}