{
  "type": "Feature",
  "properties": {
    "iso:country":"US",
    "sg:address":"295 Union St",
    "sg:city":"East Walpole",
    "sg:classifiers":[
        {
            "category":"Retail",
            "subcategory":"Auto Repair",
            "type":"Services"
        }
    ],
    "sg:phone":"+1 508 660 8900",
    "sg:postcode":"02032",
    "sg:province":"MA",
    "sg:tags":[
        "automobile",
        "co",
        "drive",
        "transporter"
    ],
    "wof:name":"Chip's Transport Svc",
    "wof:placetype":"venue"
},
  "geometry": {"coordinates":[-71.201801,42.159086],"type":"Point"}
}