{
  "type": "Feature",
  "properties": {
    "addr:full":"7 Commerce Dr Orleans MA 02653",
    "addr:housenumber":"7",
    "addr:postcode":"02653",
    "addr:street":"Commerce Dr",
    "iso:country":"US",
    "sg:address":"7 Commerce Dr",
    "sg:city":"Orleans",
    "sg:classifiers":[
        {
            "category":"Building & Trades",
            "subcategory":"Landscaping Services",
            "type":"Services"
        },
        {
            "category":"Manufacturing",
            "subcategory":"Wood Products",
            "type":"Manufacturing & Wholesale Goods"
        }
    ],
    "sg:phone":"+1 508 255 8733",
    "sg:postcode":"02653",
    "sg:province":"MA",
    "sg:tags":[
        "stump",
        "firewood",
        "tree",
        "grinding",
        "removal",
        "arborist"
    ],
    "sg:website":"http://www.atoztreez.com",
    "wof:name":"A to Z Treez",
    "wof:placetype":"venue"
},
  "geometry": {"coordinates":[-69.99654200000001,41.776903],"type":"Point"}
}