{
  "type": "Feature",
  "properties": {
    "addr:full": "933 Pleasant St Fall River MA 02723",
    "addr:housenumber": "933",
    "addr:postcode": "02723",
    "addr:street": "Pleasant St",
    "iso:country": "US",
    "ovtr:label": "K T Nails, 933 Pleasant St Fall River MA US",
    "ovtr:similarity": 2.0858330726623535,
    "sg:address": "933 Pleasant St",
    "sg:city": "Fall River",
    "sg:classifiers": [
      {
        "category": "Personal",
        "subcategory": "Beauty Salon",
        "type": "Services"
      }
    ],
    "sg:phone": "+1 508 676 1937",
    "sg:postcode": "02723",
    "sg:province": "MA",
    "sg:tags": [
      "manicuring"
    ],
    "wof:name": "K T Nails",
    "wof:placetype": "venue"
  },
  "geometry": {"coordinates":[-71.139883,41.695225],"type":"Point"}
}
