{
  "type": "Feature",
  "properties": {
    "iso:country":"US",
    "sg:address":"933 Pleasant St",
    "sg:city":"Fall River",
    "sg:classifiers":[
        {
            "category":"Personal",
            "subcategory":"Beauty Salon",
            "type":"Services"
        }
    ],
    "sg:phone":"+1 508 676 1937",
    "sg:postcode":"02723",
    "sg:province":"MA",
    "sg:tags":[
        "manicuring"
    ],
    "wof:name":"K T Nails",
    "wof:placetype":"venue"
},
  "geometry": {"coordinates":[-71.139883,41.695225],"type":"Point"}
}