{
  "type": "Feature",
  "properties": {
    "addr:full":"50 Topping Rd Andover MA 01810",
    "addr:housenumber":"50",
    "addr:postcode":"01810",
    "addr:street":"Topping Rd",
    "iso:country":"US",
    "sg:address":"50 Topping Rd",
    "sg:city":"Andover",
    "sg:classifiers":[
        {
            "category":"Building & Trades",
            "subcategory":"Landscaping Services",
            "type":"Services"
        }
    ],
    "sg:phone":"+1 978 296 5187",
    "sg:postcode":"01810",
    "sg:province":"MA",
    "sg:tags":[
        "consultant",
        "lawn",
        "designer",
        "landscape",
        "contractor"
    ],
    "sg:website":"http://www.cparks.net",
    "wof:name":"C Parks Landscape",
    "wof:placetype":"venue"
},
  "geometry": {"coordinates":[-71.15602,42.678904],"type":"Point"}
}