{
  "type": "Feature",
  "properties": {
    "addr:full":"99 Glendale St Easthampton MA 01027",
    "addr:housenumber":"99",
    "addr:postcode":"01027",
    "addr:street":"Glendale St",
    "iso:country":"US",
    "sg:address":"99 Glendale St",
    "sg:city":"Easthampton",
    "sg:classifiers":[
        {
            "category":"Professional",
            "subcategory":"Engineering",
            "type":"Services"
        }
    ],
    "sg:phone":"+1   ",
    "sg:postcode":"01027",
    "sg:province":"MA",
    "wof:name":"James A Gracia Pe",
    "wof:placetype":"venue"
},
  "geometry": {"coordinates":[-72.69386299999999,42.268719],"type":"Point"}
}