{
  "type": "Feature",
  "properties": {
    "iso:country":"US",
    "sg:address":"1175 Boylston St",
    "sg:city":"Boston",
    "sg:classifiers":[
        {
            "category":"Professional",
            "subcategory":"Computer Services",
            "type":"Services"
        }
    ],
    "sg:phone":"+1 617 262 2626",
    "sg:postcode":"02215",
    "sg:province":"MA",
    "sg:tags":[
        "repair"
    ],
    "wof:name":"Computer Geeks",
    "wof:placetype":"venue"
},
  "geometry": {"coordinates":[-71.094061,42.345972],"type":"Point"}
}