{
  "type": "Feature",
  "properties": {
    "addr:full":"Burlington Mall 75 Middlesex Tpke Burlington MA 01803",
    "addr:housenumber":"75",
    "addr:postcode":"01803",
    "addr:street":"Middlesex Tpke",
    "iso:country":"US",
    "sg:address":"Burlington Mall 75 Middlesex Tpke",
    "sg:city":"Burlington",
    "sg:classifiers":[
        {
            "category":"Shopping",
            "subcategory":"Used Merchandise",
            "type":"Retail Goods"
        }
    ],
    "sg:phone":"+1 781 221 8440",
    "sg:postcode":"01803",
    "sg:province":"MA",
    "sg:tags":[
        "vintage",
        "consignment"
    ],
    "sg:website":"www.secondtimearound.net",
    "wof:name":"Second Time Around",
    "wof:placetype":"venue"
},
  "geometry": {"coordinates":[-71.21709,42.480741],"type":"Point"}
}