{
  "type": "Feature",
  "properties": {
    "iso:country":"US",
    "sg:address":"45 Day St",
    "sg:city":"Somerville",
    "sg:classifiers":[
        {
            "category":"Restaurant",
            "type":"Food & Drink"
        }
    ],
    "sg:phone":"+1 617 776 0552",
    "sg:postcode":"02144",
    "sg:province":"MA",
    "sg:tags":[
        "pizza"
    ],
    "sg:website":"flatbreadcompany.com",
    "wof:name":"Flatbread Pizza Company",
    "wof:placetype":"venue"
},
  "geometry": {"coordinates":[-71.123627,42.395628],"type":"Point"}
}