{
  "type": "Feature",
  "properties": {
    "addr:full":"4 Delaware St Worcester MA 01603",
    "addr:housenumber":"4",
    "addr:postcode":"01603",
    "addr:street":"Delaware St",
    "iso:country":"US",
    "sg:address":"4 Delaware St",
    "sg:city":"Worcester",
    "sg:classifiers":[
        {
            "category":"Shopping",
            "subcategory":"Bicycles & Sporting Goods",
            "type":"Retail Goods"
        }
    ],
    "sg:phone":"+1 508 795 0677",
    "sg:postcode":"01603",
    "sg:province":"MA",
    "sg:tags":[
        "equipment",
        "exercise"
    ],
    "wof:name":"Gymwalkers",
    "wof:placetype":"venue"
},
  "geometry": {"coordinates":[-71.82982699999999,42.240067],"type":"Point"}
}