{
  "type": "Feature",
  "properties": {
    "addr:full":"636 E Broadway Boston MA 02127",
    "addr:housenumber":"636",
    "addr:postcode":"02127",
    "addr:street":"E Broadway",
    "iso:country":"US",
    "sg:address":"636 E Broadway",
    "sg:city":"Boston",
    "sg:classifiers":[
        {
            "category":"Banks & Credit Unions",
            "subcategory":"Bank",
            "type":"Services"
        }
    ],
    "sg:phone":"+1 617 000 1111",
    "sg:postcode":"02127",
    "sg:province":"MA",
    "wof:name":"Bank Of America",
    "wof:placetype":"venue"
},
  "geometry": {"coordinates":[-71.038095,42.33565],"type":"Point"}
}