{
  "type": "Feature",
  "properties": {
    "iso:country":"US",
    "sg:address":"361 Main St",
    "sg:city":"Malden",
    "sg:classifiers":[
        {
            "category":"Real Estate",
            "subcategory":"Real Estate Agent",
            "type":"Services"
        }
    ],
    "sg:phone":"+1 781 324 3100",
    "sg:postcode":"02148",
    "sg:province":"MA",
    "wof:name":"Era Andrew Realty",
    "wof:placetype":"venue"
},
  "geometry": {"coordinates":[-71.067736,42.425204],"type":"Point"}
}