{
  "type": "Feature",
  "properties": {
    "iso:country":"US",
    "sg:address":"235 Atlantic St",
    "sg:city":"North Quincy",
    "sg:classifiers":[
        {
            "category":"Personal",
            "subcategory":"Skin Care",
            "type":"Services"
        },
        {
            "category":"Personal",
            "subcategory":"Day Spa",
            "type":"Services"
        }
    ],
    "sg:phone":"+1 617 773 5130",
    "sg:postcode":"02171",
    "sg:province":"MA",
    "sg:website":"www.sonomaspa.net",
    "wof:name":"Sonoma Spa & Salon",
    "wof:placetype":"venue"
},
  "geometry": {"coordinates":[-71.02519599999999,42.283833],"type":"Point"}
}