{
  "type": "Feature",
  "properties": {
    "addr:full": "235 Atlantic St North Quincy MA 02171",
    "addr:housenumber": "235",
    "addr:postcode": "02171",
    "addr:street": "Atlantic St",
    "iso:country": "US",
    "sg:address": "235 Atlantic St",
    "sg:city": "North Quincy",
    "sg:classifiers": [
      {
        "category": "Personal",
        "subcategory": "Skin Care",
        "type": "Services"
      },
      {
        "category": "Personal",
        "subcategory": "Day Spa",
        "type": "Services"
      }
    ],
    "sg:phone": "+1 617 773 5130",
    "sg:postcode": "02171",
    "sg:province": "MA",
    "sg:website": "www.sonomaspa.net",
    "wof:name": "Sonoma Spa \u0026 Salon",
    "wof:placetype": "venue"
  },
  "geometry": {"coordinates":[-71.025196,42.283833],"type":"Point"}
}
