{
  "type": "Feature",
  "properties": {
    "addr:full":"20 Salem St Springfield MA 01105",
    "addr:housenumber":"20",
    "addr:postcode":"01105",
    "addr:street":"Salem St",
    "iso:country":"US",
    "sg:address":"20 Salem St",
    "sg:city":"Springfield",
    "sg:classifiers":[
        {
            "category":"Organizations",
            "subcategory":"Religious Organization",
            "type":"Services"
        }
    ],
    "sg:phone":"+1   ",
    "sg:postcode":"01105",
    "sg:province":"MA",
    "wof:name":"Hispanic Baptist Church",
    "wof:placetype":"venue"
},
  "geometry": {"coordinates":[-72.585684,42.106713],"type":"Point"}
}