{
  "type": "Feature",
  "properties": {
    "iso:country":"US",
    "sg:address":"17 S Main St",
    "sg:city":"Millbury",
    "sg:classifiers":[
        {
            "category":"Recreation",
            "subcategory":"Marina",
            "type":"Entertainment"
        }
    ],
    "sg:phone":"+1 508 865 0585",
    "sg:postcode":"01527",
    "sg:province":"MA",
    "wof:name":"Millbury Live Fish Bait Store",
    "wof:placetype":"venue"
},
  "geometry": {"coordinates":[-71.76002099999999,42.189945],"type":"Point"}
}