{
  "type": "Feature",
  "properties": {
    "iso:country":"US",
    "sg:address":"37 Upton Dr",
    "sg:city":"Wilmington",
    "sg:classifiers":[
        {
            "category":"Real Estate",
            "subcategory":"Real Estate Agent",
            "type":"Services"
        }
    ],
    "sg:phone":"+1 978 657 0381",
    "sg:postcode":"01887",
    "sg:province":"MA",
    "wof:name":"PGA Realty Trust",
    "wof:placetype":"venue"
},
  "geometry": {"coordinates":[-71.149118,42.592297],"type":"Point"}
}