{
  "type": "Feature",
  "properties": {
    "addr:full":"88 Shrewsbury St Worcester MA 01604",
    "addr:housenumber":"88",
    "addr:postcode":"01604",
    "addr:street":"Shrewsbury St",
    "iso:country":"US",
    "sg:address":"88 Shrewsbury St",
    "sg:city":"Worcester",
    "sg:classifiers":[
        {
            "category":"Utilities",
            "subcategory":"Mobile Phone",
            "type":"Services"
        }
    ],
    "sg:phone":"+1 508 363 3663",
    "sg:postcode":"01604",
    "sg:province":"MA",
    "sg:tags":[
        "telephone",
        "cellular"
    ],
    "wof:name":"Amcomm Wireless",
    "wof:placetype":"venue"
},
  "geometry": {"coordinates":[-71.789996,42.263611],"type":"Point"}
}