{
  "type": "Feature",
  "properties": {
    "iso:country":"US",
    "sg:address":"60 Carlson St",
    "sg:city":"Everett",
    "sg:classifiers":[
        {
            "category":"Professional",
            "subcategory":"Business Services",
            "type":"Services"
        }
    ],
    "sg:phone":"+1   ",
    "sg:postcode":"02149",
    "sg:province":"MA",
    "wof:name":"Officescapes",
    "wof:placetype":"venue"
},
  "geometry": {"coordinates":[-71.051346,42.419492],"type":"Point"}
}