{
  "type": "Feature",
  "properties": {
    "iso:country":"US",
    "sg:address":"269 Main St",
    "sg:city":"Buzzards Bay",
    "sg:classifiers":[
        {
            "category":"Food & Beverages",
            "subcategory":"Meat & Fish",
            "type":"Retail Goods"
        }
    ],
    "sg:phone":"+1 508 759 8700",
    "sg:postcode":"02532",
    "sg:province":"MA",
    "sg:tags":[
        "lobster"
    ],
    "wof:name":"Buzzards Bay Lobster Pound",
    "wof:placetype":"venue"
},
  "geometry": {"coordinates":[-70.601032,41.750481],"type":"Point"}
}