{
  "type": "Feature",
  "properties": {
    "iso:country":"US",
    "sg:address":"358 Chestnut Hill Ave",
    "sg:city":"Brighton",
    "sg:classifiers":[
        {
            "category":"Travel",
            "subcategory":"Travel Agent",
            "type":"Entertainment"
        }
    ],
    "sg:phone":"+1 617 277 8622",
    "sg:postcode":"02135",
    "sg:province":"MA",
    "sg:tags":[
        "ticket",
        "agency",
        "airline"
    ],
    "wof:name":"Travel Dynamics Inc",
    "wof:placetype":"venue"
},
  "geometry": {"coordinates":[-71.15107999999999,42.336275],"type":"Point"}
}