{
  "type": "Feature",
  "properties": {
    "addr:full": "41 Berkeley St Lawrence MA 01841",
    "addr:housenumber": "41",
    "addr:postcode": "01841",
    "addr:street": "Berkeley St",
    "iso:country": "US",
    "sg:address": "41 Berkeley St",
    "sg:city": "Lawrence",
    "sg:classifiers": [
      {
        "category": "Freight",
        "type": "Transportation"
      }
    ],
    "sg:phone": "+1 978 683 3089",
    "sg:postcode": "01841",
    "sg:province": "MA",
    "sg:tags": [
      "building",
      "house",
      "mover"
    ],
    "wof:name": "Berkley Place Corp",
    "wof:placetype": "venue"
  },
  "geometry": {"coordinates":[-71.157093,42.717661],"type":"Point"}
}
