{
  "type": "Feature",
  "properties": {
    "addr:full": "135 S Main St Middleboro MA 02346",
    "addr:housenumber": "135",
    "addr:postcode": "02346",
    "addr:street": "S Main St",
    "iso:country": "US",
    "sg:address": "135 S Main St",
    "sg:city": "Middleboro",
    "sg:classifiers": [
      {
        "category": "Banks \u0026 Credit Unions",
        "subcategory": "Investment Brokerage",
        "type": "Services"
      },
      {
        "category": "Banks \u0026 Credit Unions",
        "subcategory": "Bank",
        "type": "Services"
      }
    ],
    "sg:phone": "+1 508 946 8350",
    "sg:postcode": "02346",
    "sg:province": "MA",
    "sg:tags": [
      "commercial",
      "trust",
      "saving"
    ],
    "sg:website": "http://www.rocklandtrust.com",
    "wof:name": "Rockland Trust Company",
    "wof:placetype": "venue"
  },
  "geometry": {"coordinates":[-70.917933,41.885276],"type":"Point"}
}
