{
  "type": "Feature",
  "properties": {
    "addr:full":"420 Granite Ave Milton MA 02186",
    "addr:housenumber":"420",
    "addr:postcode":"02186",
    "addr:street":"Granite Ave",
    "iso:country":"US",
    "sg:address":"420 Granite Ave",
    "sg:city":"Milton",
    "sg:classifiers":[
        {
            "category":"Banks & Credit Unions",
            "subcategory":"Bank",
            "type":"Services"
        }
    ],
    "sg:phone":"+1 617 698 0662",
    "sg:postcode":"02186",
    "sg:province":"MA",
    "wof:name":"Citizens Bank",
    "wof:placetype":"venue"
},
  "geometry": {"coordinates":[-71.040494,42.257268],"type":"Point"}
}