{
  "type": "Feature",
  "properties": {
    "addr:full": "800 River St Mattapan MA 02126",
    "addr:housenumber": "800",
    "addr:postcode": "02126",
    "addr:street": "River St",
    "iso:country": "US",
    "sg:address": "800 River St",
    "sg:city": "Mattapan",
    "sg:classifiers": [
      {
        "category": "Freight",
        "type": "Transportation"
      }
    ],
    "sg:phone": "+1 877 258 8230",
    "sg:postcode": "02126",
    "sg:province": "MA",
    "sg:tags": [
      "commercial",
      "household",
      "storage"
    ],
    "sg:website": "http://www.publicstorage.com/?pid=ypcomCPCingenio",
    "wof:name": "Public Storage",
    "wof:placetype": "venue"
  },
  "geometry": {"coordinates":[-71.105278,42.263592],"type":"Point"}
}
