{
  "type": "Feature",
  "properties": {
    "iso:country":"US",
    "sg:address":"36 Melrose St",
    "sg:city":"Boston",
    "sg:classifiers":[
        {
            "category":"Real Estate",
            "subcategory":"Real Estate Agent",
            "type":"Services"
        }
    ],
    "sg:phone":"+1 617 542 5206",
    "sg:postcode":"02116",
    "sg:province":"MA",
    "sg:tags":[
        "management"
    ],
    "wof:name":"Executive Suites",
    "wof:placetype":"venue"
},
  "geometry": {"coordinates":[-71.068628,42.349005],"type":"Point"}
}