{
  "type": "Feature",
  "properties": {
    "addr:full":"120 Sandwich St Plymouth MA 02360",
    "addr:housenumber":"120",
    "addr:postcode":"02360",
    "addr:street":"Sandwich St",
    "iso:country":"US",
    "sg:address":"120 Sandwich St",
    "sg:city":"Plymouth",
    "sg:classifiers":[
        {
            "category":"Autos & Motor Vehicles",
            "subcategory":"Auto Supplies",
            "type":"Retail Goods"
        }
    ],
    "sg:phone":"+1 508 746 3242",
    "sg:postcode":"02360",
    "sg:province":"MA",
    "sg:tags":[
        "automobile",
        "parts"
    ],
    "wof:name":"Carquest Auto Parts",
    "wof:placetype":"venue"
},
  "geometry": {"coordinates":[-70.656682,41.951983],"type":"Point"}
}