{
  "type": "Feature",
  "properties": {
    "iso:country":"US",
    "sg:address":"2071 Washington St",
    "sg:city":"Hanover",
    "sg:classifiers":[
        {
            "category":"Building & Trades",
            "subcategory":"Locksmith",
            "type":"Services"
        }
    ],
    "sg:phone":"+1 781 928 1474",
    "sg:postcode":"02339",
    "sg:province":"MA",
    "sg:tags":[
        "lock",
        "industrial",
        "locksmiths-commercial"
    ],
    "wof:name":"77 Day Emergency A 24 Hour Loc",
    "wof:placetype":"venue"
},
  "geometry": {"coordinates":[-70.84931,42.156049],"type":"Point"}
}