{
  "type": "Feature",
  "properties": {
    "addr:full":"132 Central St Ste 212 Foxboro MA 02035",
    "addr:housenumber":"132",
    "addr:postcode":"02035",
    "addr:street":"Central St Ste 212",
    "iso:country":"US",
    "sg:address":"132 Central St Ste 212",
    "sg:city":"Foxboro",
    "sg:classifiers":[
        {
            "category":"Professional",
            "subcategory":"Printing & Photocopies",
            "type":"Services"
        }
    ],
    "sg:phone":"+1 508 543 9351",
    "sg:postcode":"02035",
    "sg:province":"MA",
    "sg:tags":[
        "lithographer"
    ],
    "wof:name":"Dkr Associates",
    "wof:placetype":"venue"
},
  "geometry": {"coordinates":[-71.242058,42.056429],"type":"Point"}
}