{
  "type": "Feature",
  "properties": {
    "iso:country":"US",
    "sg:address":"Copley Place 110 Huntington Ave",
    "sg:city":"Boston",
    "sg:classifiers":[
        {
            "category":"Bars & Pubs",
            "subcategory":"Lounge",
            "type":"Food & Drink"
        }
    ],
    "sg:phone":"+1 617 236 5800",
    "sg:postcode":"02116",
    "sg:province":"MA",
    "sg:website":"www.marriott.com/hotels/hotel-in...",
    "wof:name":"Connexion Lounge",
    "wof:placetype":"venue"
},
  "geometry": {"coordinates":[-71.079397,42.346175],"type":"Point"}
}