{
  "type": "Feature",
  "properties": {
    "iso:country":"US",
    "sg:address":"72 Highland Ave",
    "sg:city":"Salem",
    "sg:classifiers":[
        {
            "category":"Health Services",
            "subcategory":"Doctor",
            "type":"Services"
        }
    ],
    "sg:phone":"+1 978 745 3050",
    "sg:postcode":"01970",
    "sg:province":"MA",
    "sg:tags":[
        "physician",
        "surgeon"
    ],
    "wof:name":"Pediatric Associates Salem",
    "wof:placetype":"venue"
},
  "geometry": {"coordinates":[-70.90822799999999,42.512375],"type":"Point"}
}