{
  "type": "Feature",
  "properties": {
    "addr:full":"21 Forest Ave Brockton MA 02301",
    "addr:housenumber":"21",
    "addr:postcode":"02301",
    "addr:street":"Forest Ave",
    "iso:country":"US",
    "sg:address":"21 Forest Ave",
    "sg:city":"Brockton",
    "sg:classifiers":[
        {
            "category":"Wholesale",
            "subcategory":"Non-durable Goods",
            "type":"Manufacturing & Wholesale Goods"
        }
    ],
    "sg:phone":"+1   ",
    "sg:postcode":"02301",
    "sg:province":"MA",
    "wof:name":"Tammy O-Kouassi Wholesale",
    "wof:placetype":"venue"
},
  "geometry": {"coordinates":[-71.018866,42.073163],"type":"Point"}
}