{
  "type": "Feature",
  "properties": {
    "iso:country":"US",
    "sg:address":"937 Great Plain Ave",
    "sg:city":"Needham",
    "sg:classifiers":[
        {
            "category":"Retail",
            "subcategory":"Portrait Studio",
            "type":"Services"
        }
    ],
    "sg:phone":"+1 781 444 0042",
    "sg:postcode":"02492",
    "sg:province":"MA",
    "sg:tags":[
        "photography"
    ],
    "wof:name":"Westwood Studios Inc",
    "wof:placetype":"venue"
},
  "geometry": {"coordinates":[-71.235392,42.280352],"type":"Point"}
}