{
  "type": "Feature",
  "properties": {
    "iso:country":"US",
    "sg:address":"11 Waumbeck St",
    "sg:city":"Roxbury",
    "sg:classifiers":[
        {
            "category":"Personal",
            "subcategory":"Adult",
            "type":"Services"
        }
    ],
    "sg:phone":"+1 617 427 9008",
    "sg:postcode":"02121",
    "sg:province":"MA",
    "sg:tags":[
        "escort"
    ],
    "wof:name":"Eye Candy Entertainment",
    "wof:placetype":"venue"
},
  "geometry": {"coordinates":[-71.083724,42.313236],"type":"Point"}
}