{
  "type": "Feature",
  "properties": {
    "addr:full":"16 Raymond St Manchester MA 01944",
    "addr:housenumber":"16",
    "addr:postcode":"01944",
    "addr:street":"Raymond St",
    "iso:country":"US",
    "sg:address":"16 Raymond St",
    "sg:city":"Manchester",
    "sg:classifiers":[
        {
            "category":"Building & Trades",
            "subcategory":"Pest Control",
            "type":"Services"
        }
    ],
    "sg:phone":"+1 978 526 9888",
    "sg:postcode":"01944",
    "sg:province":"MA",
    "wof:name":"Alamo Pest Control",
    "wof:placetype":"venue"
},
  "geometry": {"coordinates":[-70.72170199999999,42.578315],"type":"Point"}
}