{
  "type": "Feature",
  "properties": {
    "iso:country":"US",
    "sg:address":"594 Converse St",
    "sg:city":"Longmeadow",
    "sg:classifiers":[
        {
            "category":"Education",
            "subcategory":"School",
            "type":"Public Place"
        }
    ],
    "sg:phone":"+1 413 567 1517",
    "sg:postcode":"01106",
    "sg:province":"MA",
    "sg:website":"www.heritageacademy.org",
    "wof:name":"Heritage Academy",
    "wof:placetype":"venue"
},
  "geometry": {"coordinates":[-72.55584899999999,42.066474],"type":"Point"}
}