{
  "type": "Feature",
  "properties": {
    "addr:full": "594 Converse St Longmeadow MA 01106",
    "addr:housenumber": "594",
    "addr:postcode": "01106",
    "addr:street": "Converse St",
    "iso:country": "US",
    "sg:address": "594 Converse St",
    "sg:city": "Longmeadow",
    "sg:classifiers": [
      {
        "category": "Education",
        "subcategory": "School",
        "type": "Public Place"
      }
    ],
    "sg:phone": "+1 413 567 1517",
    "sg:postcode": "01106",
    "sg:province": "MA",
    "sg:website": "www.heritageacademy.org",
    "wof:name": "Heritage Academy",
    "wof:placetype": "venue"
  },
  "geometry": {"coordinates":[-72.555849,42.066474],"type":"Point"}
}
