{
  "type": "Feature",
  "properties": {
    "addr:full": "449 Southbridge St Worcester MA 01610",
    "addr:housenumber": "449",
    "addr:postcode": "01610",
    "addr:street": "Southbridge St",
    "iso:country": "US",
    "sg:address": "449 Southbridge St",
    "sg:city": "Worcester",
    "sg:classifiers": [
      {
        "category": "Retail",
        "subcategory": "Auto Repair",
        "type": "Services"
      }
    ],
    "sg:phone": "+1 508 756 2399",
    "sg:postcode": "01610",
    "sg:province": "MA",
    "sg:tags": [
      "body",
      "automobile",
      "painting"
    ],
    "wof:name": "Canterbury Automotive Inc",
    "wof:placetype": "venue"
  },
  "geometry": {"coordinates":[-71.809438,42.250173],"type":"Point"}
}
