{
  "type": "Feature",
  "properties": {
    "addr:full":"Westgate Dr Brockton MA 02301",
    "addr:postcode":"02301",
    "addr:street":"Westgate Dr",
    "iso:country":"US",
    "sg:address":"Westgate Dr",
    "sg:city":"Brockton",
    "sg:classifiers":[
        {
            "category":"Shopping",
            "subcategory":"Gifts & Souvenirs",
            "type":"Retail Goods"
        }
    ],
    "sg:phone":"+1 508 427 7701",
    "sg:postcode":"02301",
    "sg:province":"MA",
    "sg:tags":[
        "shop"
    ],
    "wof:name":"Tatianna's Gift Shop",
    "wof:placetype":"venue"
},
  "geometry": {"coordinates":[-71.052528,42.097515],"type":"Point"}
}