{
  "type": "Feature",
  "properties": {
    "iso:country":"US",
    "sg:address":"9 Patrick Street",
    "sg:city":"Arlington",
    "sg:classifiers":[
        {
            "category":"Building & Trades",
            "subcategory":"Locksmith",
            "type":"Services"
        }
    ],
    "sg:phone":"+1 781 893 8886",
    "sg:postcode":"02474",
    "sg:province":"MA",
    "sg:tags":[
        "key"
    ],
    "wof:name":"Quality Lock Service",
    "wof:placetype":"venue"
},
  "geometry": {"coordinates":[-71.13723299999999,42.412574],"type":"Point"}
}