{
  "type": "Feature",
  "properties": {
    "addr:full": "9 Patrick Street Arlington MA 02474",
    "addr:housenumber": "9",
    "addr:postcode": "02474",
    "addr:street": "Patrick Street",
    "iso:country": "US",
    "sg:address": "9 Patrick Street",
    "sg:city": "Arlington",
    "sg:classifiers": [
      {
        "category": "Building \u0026 Trades",
        "subcategory": "Locksmith",
        "type": "Services"
      }
    ],
    "sg:phone": "+1 781 893 8886",
    "sg:postcode": "02474",
    "sg:province": "MA",
    "sg:tags": [
      "key"
    ],
    "wof:name": "Quality Lock Service",
    "wof:placetype": "venue"
  },
  "geometry": {"coordinates":[-71.137233,42.412574],"type":"Point"}
}
