{
  "type": "Feature",
  "properties": {
    "iso:country":"US",
    "sg:address":"300 Arnold St",
    "sg:city":"Wrentham",
    "sg:classifiers":[
        {
            "category":"Organizations",
            "subcategory":"Religious Organization",
            "type":"Services"
        }
    ],
    "sg:phone":"+1 508 528 1282",
    "sg:postcode":"02093",
    "sg:province":"MA",
    "sg:tags":[
        "monastery",
        "convent"
    ],
    "wof:name":"Mt St Mary's Trappistine Abbey",
    "wof:placetype":"venue"
},
  "geometry": {"coordinates":[-71.394926,42.03442],"type":"Point"}
}