{
  "type": "Feature",
  "properties": {
    "addr:full":"2 Pierce St Framingham MA 01702",
    "addr:housenumber":"2",
    "addr:postcode":"01702",
    "addr:street":"Pierce St",
    "iso:country":"US",
    "sg:address":"2 Pierce St",
    "sg:city":"Framingham",
    "sg:classifiers":[
        {
            "category":"Shopping",
            "subcategory":"Computers & Home Electronics",
            "type":"Retail Goods"
        }
    ],
    "sg:phone":"+1 508 620 1479",
    "sg:postcode":"01702",
    "sg:province":"MA",
    "sg:tags":[
        "equipment",
        "dealer"
    ],
    "wof:name":"Computer Parts",
    "wof:placetype":"venue"
},
  "geometry": {"coordinates":[-71.40452999999999,42.297408],"type":"Point"}
}