{
  "type": "Feature",
  "properties": {
    "iso:country":"US",
    "sg:address":"138 Cooke St",
    "sg:city":"Edgartown",
    "sg:classifiers":[
        {
            "category":"Building & Trades",
            "subcategory":"Plumbing",
            "type":"Services"
        }
    ],
    "sg:phone":"+1 508 627 7300",
    "sg:postcode":"02539",
    "sg:province":"MA",
    "sg:tags":[
        "conditioning",
        "air",
        "system",
        "contractor"
    ],
    "wof:name":"Alexander's Air Cond & Refrig",
    "wof:placetype":"venue"
},
  "geometry": {"coordinates":[-70.522122,41.391644],"type":"Point"}
}