{
  "type": "Feature",
  "properties": {
    "iso:country":"US",
    "sg:address":"452 State Hwy 28",
    "sg:city":"West Yarmouth",
    "sg:classifiers":[
        {
            "category":"Travel",
            "subcategory":"Hotels & Motels",
            "type":"Entertainment"
        }
    ],
    "sg:phone":"+1 508 778 0187",
    "sg:postcode":"02673",
    "sg:province":"MA",
    "wof:name":"Town N Country Motor Lodge",
    "wof:placetype":"venue"
},
  "geometry": {"coordinates":[-70.227137,41.673192],"type":"Point"}
}