{
  "type": "Feature",
  "properties": {
    "iso:country":"US",
    "sg:address":"729 Boylston St",
    "sg:city":"Boston",
    "sg:classifiers":[
        {
            "category":"Professional",
            "subcategory":"Advertising",
            "type":"Services"
        },
        {
            "category":"Internet Cafe",
            "subcategory":"None",
            "type":"Food & Drink"
        },
        {
            "category":"Professional",
            "subcategory":"Computer Services",
            "type":"Services"
        }
    ],
    "sg:phone":"+1 617 603 4949",
    "sg:postcode":"02116",
    "sg:province":"MA",
    "sg:tags":[
        "product",
        "isp",
        "specialty",
        "provider"
    ],
    "wof:name":"Citysearch",
    "wof:placetype":"venue"
},
  "geometry": {"coordinates":[-71.08017700000001,42.349301],"type":"Point"}
}