{
  "type": "Feature",
  "properties": {
    "addr:full":"581 Boston Post Rd E Marlborough MA 01752",
    "addr:housenumber":"581",
    "addr:postcode":"01752",
    "addr:street":"Boston Post Rd E",
    "iso:country":"US",
    "sg:address":"581 Boston Post Rd E",
    "sg:city":"Marlborough",
    "sg:classifiers":[
        {
            "category":"Food & Beverages",
            "subcategory":"Groceries & Convenience Stores",
            "type":"Retail Goods"
        }
    ],
    "sg:phone":"+1 508 624 7524",
    "sg:postcode":"01752",
    "sg:province":"MA",
    "wof:name":"Brasileirnho",
    "wof:placetype":"venue"
},
  "geometry": {"coordinates":[-71.50481600000001,42.349903],"type":"Point"}
}