{
  "type": "Feature",
  "properties": {
    "addr:full":"196 Fountain St Framingham MA 01702",
    "addr:housenumber":"196",
    "addr:postcode":"01702",
    "addr:street":"Fountain St",
    "iso:country":"US",
    "sg:address":"196 Fountain St",
    "sg:city":"Framingham",
    "sg:classifiers":[
        {
            "category":"Autos & Motor Vehicles",
            "subcategory":"Automobile Sales",
            "type":"Retail Goods"
        }
    ],
    "sg:phone":"+1 508 820 9322",
    "sg:postcode":"01702",
    "sg:province":"MA",
    "sg:tags":[
        "car",
        "dealer"
    ],
    "wof:name":"R H Long Motor Sales Co",
    "wof:placetype":"venue"
},
  "geometry": {"coordinates":[-71.436959,42.275291],"type":"Point"}
}