{
  "type": "Feature",
  "properties": {
    "iso:country":"US",
    "sg:address":"9 Central St",
    "sg:city":"Marlborough",
    "sg:classifiers":[
        {
            "category":"Place Of Worship",
            "subcategory":"Church",
            "type":"Public Place"
        },
        {
            "category":"Place Of Worship",
            "type":"Public Place"
        }
    ],
    "sg:phone":"+1 508 485 2575",
    "sg:postcode":"01752",
    "sg:province":"MA",
    "sg:tags":[
        "churches-greek",
        "churches-eastern",
        "orthodox"
    ],
    "wof:name":"Greek Orthodox Church",
    "wof:placetype":"venue"
},
  "geometry": {"coordinates":[-71.55444799999999,42.347369],"type":"Point"}
}