{
  "type": "Feature",
  "properties": {
    "iso:country":"US",
    "sg:address":"37 Washington Street",
    "sg:city":"Melrose",
    "sg:classifiers":[
        {
            "category":"Sports & Exercise",
            "subcategory":"Gym",
            "type":"Entertainment"
        }
    ],
    "sg:phone":"+1 781 662 2222",
    "sg:postcode":"02176",
    "sg:province":"MA",
    "sg:tags":[
        "trainer"
    ],
    "wof:name":"Pioneer Medical Corporation - CLOSED",
    "wof:placetype":"venue"
},
  "geometry": {"coordinates":[-71.071945,42.441839],"type":"Point"}
}