{
  "type": "Feature",
  "properties": {
    "iso:country":"US",
    "sg:address":"702 Main St",
    "sg:city":"Bolton",
    "sg:classifiers":[
        {
            "category":"Professional",
            "type":"Services"
        }
    ],
    "sg:phone":"+1 978 779 0527",
    "sg:postcode":"01740",
    "sg:province":"MA",
    "sg:tags":[
        "establishment"
    ],
    "wof:name":"Bolton Strategic Assoc",
    "wof:placetype":"venue"
},
  "geometry": {"coordinates":[-71.60823000000001,42.433157],"type":"Point"}
}