{
  "type": "Feature",
  "properties": {
    "iso:country":"US",
    "sg:address":"180 Mattakeesett St",
    "sg:city":"Pembroke",
    "sg:classifiers":[
        {
            "category":"Building & Trades",
            "subcategory":"Landscaping Services",
            "type":"Services"
        },
        {
            "category":"Home & Garden",
            "subcategory":"Garden Supply",
            "type":"Retail Goods"
        },
        {
            "category":"Manufacturing",
            "subcategory":"Wood Products",
            "type":"Manufacturing & Wholesale Goods"
        }
    ],
    "sg:phone":"+1 781 294 1520",
    "sg:postcode":"02359",
    "sg:province":"MA",
    "sg:tags":[
        "horticulture",
        "stump",
        "firewood",
        "tree",
        "grinding",
        "removal",
        "arborist"
    ],
    "sg:website":"http://www.newcombstree.com",
    "wof:name":"Newcomb's Tree Service",
    "wof:placetype":"venue"
},
  "geometry": {"coordinates":[-70.82330399999999,42.061803],"type":"Point"}
}