{
  "type": "Feature",
  "properties": {
    "addr:full":"259 Elm Street Somerville MA 02144",
    "addr:housenumber":"259",
    "addr:postcode":"02144",
    "addr:street":"Elm Street",
    "iso:country":"US",
    "sg:address":"259 Elm Street",
    "sg:city":"Somerville",
    "sg:classifiers":[
        {
            "category":"Sports & Exercise",
            "subcategory":"Gym",
            "type":"Entertainment"
        },
        {
            "category":"Health Services",
            "subcategory":"Health Practitioner",
            "type":"Services"
        },
        {
            "category":"Health Services",
            "subcategory":"Chiropractor",
            "type":"Services"
        }
    ],
    "sg:phone":"+1 617 591 9200",
    "sg:postcode":"02144",
    "sg:province":"MA",
    "sg:tags":[
        "trainer",
        "therapy",
        "physical"
    ],
    "wof:name":"Lazarus Felice Pt",
    "wof:placetype":"venue"
},
  "geometry": {"coordinates":[-71.122164,42.395773],"type":"Point"}
}