{
  "type": "Feature",
  "properties": {
    "iso:country":"US",
    "sg:address":"1 Accord Park Dr",
    "sg:city":"Norwell",
    "sg:classifiers":[
        {
            "category":"Shopping",
            "subcategory":"Department Store",
            "type":"Retail Goods"
        }
    ],
    "sg:phone":"+1 781 871 3001",
    "sg:postcode":"02061",
    "sg:province":"MA",
    "wof:name":"Sears Roebuck & Co",
    "wof:placetype":"venue"
},
  "geometry": {"coordinates":[-70.88932699999999,42.167193],"type":"Point"}
}