{
  "type": "Feature",
  "properties": {
    "iso:country":"US",
    "sg:address":"24 Clark Ln",
    "sg:city":"Waltham",
    "sg:classifiers":[
        {
            "category":"Manufacturing",
            "subcategory":"Tools & Machinery",
            "type":"Manufacturing & Wholesale Goods"
        }
    ],
    "sg:phone":"+1   ",
    "sg:postcode":"02451",
    "sg:province":"MA",
    "sg:tags":[
        "computer",
        "storage",
        "devices",
        "mfg"
    ],
    "wof:name":"H A Systems",
    "wof:placetype":"venue"
},
  "geometry": {"coordinates":[-71.24038,42.387838],"type":"Point"}
}