{
  "type": "Feature",
  "properties": {
    "addr:full":"209 Maple St Malden MA 02148",
    "addr:housenumber":"209",
    "addr:postcode":"02148",
    "addr:street":"Maple St",
    "iso:country":"US",
    "sg:address":"209 Maple St",
    "sg:city":"Malden",
    "sg:classifiers":[
        {
            "category":"Retail",
            "subcategory":"Repair Shop",
            "type":"Services"
        }
    ],
    "sg:phone":"+1 781 321 5424",
    "sg:postcode":"02148",
    "sg:province":"MA",
    "sg:tags":[
        "ironwork"
    ],
    "wof:name":"Hammersmith Studios",
    "wof:placetype":"venue"
},
  "geometry": {"coordinates":[-71.08256299999999,42.428763],"type":"Point"}
}