{
  "type": "Feature",
  "properties": {
    "iso:country":"US",
    "sg:address":"51 Summer St",
    "sg:city":"Rehoboth",
    "sg:classifiers":[
        {
            "category":"Professional",
            "subcategory":"Business Services",
            "type":"Services"
        }
    ],
    "sg:phone":"+1   ",
    "sg:postcode":"02769",
    "sg:province":"MA",
    "wof:name":"Willaby Creative Service Inc",
    "wof:placetype":"venue"
},
  "geometry": {"coordinates":[-71.247102,41.835102],"type":"Point"}
}