{
  "type": "Feature",
  "properties": {
    "addr:full":"10 Kensington St Boston MA 02119",
    "addr:housenumber":"10",
    "addr:postcode":"02119",
    "addr:street":"Kensington St",
    "iso:country":"US",
    "sg:address":"10 Kensington St",
    "sg:city":"Boston",
    "sg:classifiers":[
        {
            "category":"Professional",
            "type":"Services"
        }
    ],
    "sg:phone":"+1   ",
    "sg:postcode":"02119",
    "sg:province":"MA",
    "wof:name":"Tanya Brown",
    "wof:placetype":"venue"
},
  "geometry": {"coordinates":[-71.09091600000001,42.320755],"type":"Point"}
}