{
  "type": "Feature",
  "properties": {
    "iso:country":"US",
    "sg:address":"6B Colonel Dr",
    "sg:city":"Buzzards Bay",
    "sg:classifiers":[
        {
            "category":"Building & Trades",
            "subcategory":"Plumbing",
            "type":"Services"
        }
    ],
    "sg:phone":"+1 508 743 9280",
    "sg:postcode":"02532",
    "sg:province":"MA",
    "wof:name":"Blaha Plumbing & Heating",
    "wof:placetype":"venue"
},
  "geometry": {"coordinates":[-70.58928299999999,41.733229],"type":"Point"}
}