{
  "type": "Feature",
  "properties": {
    "iso:country":"US",
    "sg:address":"1855 Beacon Street",
    "sg:city":"Brookline",
    "sg:classifiers":[
        {
            "category":"Sports & Exercise",
            "subcategory":"Gym",
            "type":"Entertainment"
        }
    ],
    "sg:phone":"+1 617 731 2600",
    "sg:postcode":"02445",
    "sg:province":"MA",
    "sg:tags":[
        "trainer"
    ],
    "wof:name":"I Mr Health Economics",
    "wof:placetype":"venue"
},
  "geometry": {"coordinates":[-71.145748,42.336744],"type":"Point"}
}