{
  "type": "Feature",
  "properties": {
    "addr:full": "157 Walnut St Lynn MA 01905",
    "addr:housenumber": "157",
    "addr:postcode": "01905",
    "addr:street": "Walnut St",
    "iso:country": "US",
    "sg:address": "157 Walnut St",
    "sg:city": "Lynn",
    "sg:classifiers": [
      {
        "category": "Shopping",
        "subcategory": "Discount \u0026 Variety Stores",
        "type": "Retail Goods"
      }
    ],
    "sg:phone": "+1 781 596 9392",
    "sg:postcode": "01905",
    "sg:province": "MA",
    "wof:name": "Malam Corp",
    "wof:placetype": "venue"
  },
  "geometry": {"coordinates":[-70.972486,42.469952],"type":"Point"}
}
