{
  "type": "Feature",
  "properties": {
    "addr:full": "19 N Main St Belchertown MA 01007",
    "addr:housenumber": "19",
    "addr:postcode": "01007",
    "addr:street": "N Main St",
    "iso:country": "US",
    "ovtr:label": "Bell \u0026 Hudson Insurance Agency, 19 N Main St Belchertown MA US",
    "ovtr:similarity": 2.436255931854248,
    "sg:address": "19 N Main St",
    "sg:city": "Belchertown",
    "sg:classifiers": [
      {
        "category": "Insurance",
        "subcategory": "Insurance Agent",
        "type": "Services"
      }
    ],
    "sg:phone": "+1 413 323 9611",
    "sg:postcode": "01007",
    "sg:province": "MA",
    "sg:website": "http://www.bellandhudson.com",
    "wof:name": "Bell \u0026 Hudson Insurance Agency Inc",
    "wof:placetype": "venue"
  },
  "geometry": {"coordinates":[-72.403986,42.28082],"type":"Point"}
}
