{
  "type": "Feature",
  "properties": {
    "addr:full":"500 John L Dietsch Blvd North Attleboro MA 02763",
    "addr:housenumber":"500",
    "addr:postcode":"02763",
    "addr:street":"John L Dietsch Blvd",
    "iso:country":"US",
    "sg:address":"500 John L Dietsch Blvd",
    "sg:city":"North Attleboro",
    "sg:classifiers":[
        {
            "category":"Manufacturing",
            "subcategory":"Metals",
            "type":"Manufacturing & Wholesale Goods"
        }
    ],
    "sg:phone":"+1 508 431 2212",
    "sg:postcode":"02763",
    "sg:province":"MA",
    "sg:tags":[
        "coating",
        "powder"
    ],
    "wof:name":"Bell's Powder Coating Inc",
    "wof:placetype":"venue"
},
  "geometry": {"coordinates":[-71.29787399999999,41.986886],"type":"Point"}
}