{
  "type": "Feature",
  "properties": {
    "iso:country":"US",
    "sg:address":"51 Wilson St",
    "sg:city":"Medford",
    "sg:classifiers":[
        {
            "category":"Personal",
            "subcategory":"Beauty Salon",
            "type":"Services"
        }
    ],
    "sg:phone":"+1   ",
    "sg:postcode":"02155",
    "sg:province":"MA",
    "sg:tags":[
        "shop"
    ],
    "wof:name":"Constance M Newell",
    "wof:placetype":"venue"
},
  "geometry": {"coordinates":[-71.09031299999999,42.434427],"type":"Point"}
}