{
  "type": "Feature",
  "properties": {
    "iso:country":"US",
    "sg:address":"50 Watertown St",
    "sg:city":"Watertown",
    "sg:classifiers":[
        {
            "category":"Real Estate",
            "subcategory":"Real Estate Operator",
            "type":"Services"
        }
    ],
    "sg:phone":"+1 617 924 1354",
    "sg:postcode":"02472",
    "sg:province":"MA",
    "sg:tags":[
        "condominium"
    ],
    "wof:name":"Waterbridge Condominium Trust",
    "wof:placetype":"venue"
},
  "geometry": {"coordinates":[-71.188462,42.364207],"type":"Point"}
}