{
  "type": "Feature",
  "properties": {
    "iso:country":"US",
    "sg:address":"928 Commonwealth Ave",
    "sg:city":"Boston",
    "sg:classifiers":[
        {
            "category":"Professional",
            "subcategory":"Management & Consulting",
            "type":"Services"
        }
    ],
    "sg:phone":"+1 617 264 3200",
    "sg:postcode":"02215",
    "sg:province":"MA",
    "sg:tags":[
        "consultant",
        "business"
    ],
    "wof:name":"Work Family Directions Inc",
    "wof:placetype":"venue"
},
  "geometry": {"coordinates":[-71.118105,42.351232],"type":"Point"}
}