{
  "type": "Feature",
  "properties": {
    "iso:country":"US",
    "sg:address":"21 Birchwood Dr",
    "sg:city":"Swansea",
    "sg:classifiers":[
        {
            "category":"Personal",
            "subcategory":"Beauty Salon",
            "type":"Services"
        }
    ],
    "sg:phone":"+1   ",
    "sg:postcode":"02777",
    "sg:province":"MA",
    "sg:tags":[
        "shop"
    ],
    "wof:name":"Cnjs Hair Studio",
    "wof:placetype":"venue"
},
  "geometry": {"coordinates":[-71.213752,41.737788],"type":"Point"}
}