{
  "type": "Feature",
  "properties": {
    "addr:full": "21 Birchwood Dr Swansea MA 02777",
    "addr:housenumber": "21",
    "addr:postcode": "02777",
    "addr:street": "Birchwood Dr",
    "iso:country": "US",
    "sg:address": "21 Birchwood Dr",
    "sg:city": "Swansea",
    "sg:classifiers": [
      {
        "category": "Personal",
        "subcategory": "Beauty Salon",
        "type": "Services"
      }
    ],
    "sg:phone": "+1   ",
    "sg:postcode": "02777",
    "sg:province": "MA",
    "sg:tags": [
      "shop"
    ],
    "wof:name": "Cnjs Hair Studio",
    "wof:placetype": "venue"
  },
  "geometry": {"coordinates":[-71.213752,41.737788],"type":"Point"}
}
