{
  "type": "Feature",
  "properties": {
    "iso:country":"US",
    "sg:address":"11 Sunset Path",
    "sg:city":"Natick",
    "sg:classifiers":[
        {
            "category":"Retail",
            "subcategory":"Repair Shop",
            "type":"Services"
        }
    ],
    "sg:phone":"+1   ",
    "sg:postcode":"01760",
    "sg:province":"MA",
    "wof:name":"J Michael Lonard Woodwind Repr",
    "wof:placetype":"venue"
},
  "geometry": {"coordinates":[-71.36933999999999,42.30646],"type":"Point"}
}