{
  "type": "Feature",
  "properties": {
    "addr:full":"195 New Boston St Woburn MA 01801",
    "addr:housenumber":"195",
    "addr:postcode":"01801",
    "addr:street":"New Boston St",
    "iso:country":"US",
    "sg:address":"195 New Boston St",
    "sg:city":"Woburn",
    "sg:classifiers":[
        {
            "category":"Wholesale",
            "subcategory":"Machinery & Supplies",
            "type":"Manufacturing & Wholesale Goods"
        }
    ],
    "sg:phone":"+1 781 932 0310",
    "sg:postcode":"01801",
    "sg:province":"MA",
    "sg:tags":[
        "contractor"
    ],
    "sg:website":"www.nationsrent.com",
    "wof:name":"Nations Rent",
    "wof:placetype":"venue"
},
  "geometry": {"coordinates":[-71.144705,42.514124],"type":"Point"}
}