{
  "type": "Feature",
  "properties": {
    "addr:full":"1 Parkside Ave Westfield MA 01085",
    "addr:housenumber":"1",
    "addr:postcode":"01085",
    "addr:street":"Parkside Ave",
    "iso:country":"US",
    "sg:address":"1 Parkside Ave",
    "sg:city":"Westfield",
    "sg:classifiers":[
        {
            "category":"Banks & Credit Unions",
            "subcategory":"Bank",
            "type":"Services"
        }
    ],
    "sg:phone":"+1 413 568 9973",
    "sg:postcode":"01085",
    "sg:province":"MA",
    "wof:name":"River Valley School Employ CU",
    "wof:placetype":"venue"
},
  "geometry": {"coordinates":[-72.741934,42.120123],"type":"Point"}
}