{
  "type": "Feature",
  "properties": {
    "addr:full":"16 Maple St Pittsfield MA 01201",
    "addr:housenumber":"16",
    "addr:postcode":"01201",
    "addr:street":"Maple St",
    "iso:country":"US",
    "sg:address":"16 Maple St",
    "sg:city":"Pittsfield",
    "sg:classifiers":[
        {
            "category":"Shopping",
            "subcategory":"Computers & Home Electronics",
            "type":"Retail Goods"
        }
    ],
    "sg:phone":"+1 413 496 8174",
    "sg:postcode":"01201",
    "sg:province":"MA",
    "sg:tags":[
        "software"
    ],
    "wof:name":"C Domain Software",
    "wof:placetype":"venue"
},
  "geometry": {"coordinates":[-73.24263999999999,42.455113],"type":"Point"}
}