{
  "type": "Feature",
  "properties": {
    "iso:country":"US",
    "sg:address":"35 Elm St",
    "sg:city":"Millbury",
    "sg:phone":"+1 508 865 2850",
    "sg:postcode":"01527",
    "sg:province":"MA",
    "wof:name":"Elm Draughthouse Cinema",
    "wof:placetype":"venue"
},
  "geometry": {"coordinates":[-71.759152,42.191737],"type":"Point"}
}