{
  "type": "Feature",
  "properties": {
    "iso:country":"US",
    "sg:address":"378 S Border Rd",
    "sg:city":"Winchester",
    "sg:classifiers":[
        {
            "category":"Professional",
            "subcategory":"Management & Consulting",
            "type":"Services"
        }
    ],
    "sg:phone":"+1   ",
    "sg:postcode":"01890",
    "sg:province":"MA",
    "wof:name":"Richard Clarke",
    "wof:placetype":"venue"
},
  "geometry": {"coordinates":[-71.123728,42.441406],"type":"Point"}
}