{
  "type": "Feature",
  "properties": {
    "addr:full": "300 Tyler St Pittsfield MA 01201",
    "addr:housenumber": "300",
    "addr:postcode": "01201",
    "addr:street": "Tyler St",
    "iso:country": "US",
    "ovtr:label": "Elegant Stitches, 237 1st St Pittsfield MA US",
    "ovtr:similarity": 3.922015905380249,
    "sg:address": "300 Tyler St",
    "sg:city": "Pittsfield",
    "sg:classifiers": [
      {
        "category": "Professional",
        "subcategory": "Business Services",
        "type": "Services"
      }
    ],
    "sg:phone": "+1 413 447 9452",
    "sg:postcode": "01201",
    "sg:province": "MA",
    "sg:tags": [
      "embroidery"
    ],
    "wof:name": "Elegant Stitches",
    "wof:placetype": "venue"
  },
  "geometry": {"coordinates":[-73.243696,42.457751],"type":"Point"}
}
