{
  "type": "Feature",
  "properties": {
    "addr:full":"35 Hewins St 2 Dorchester MA 02121",
    "addr:housenumber":"35;2",
    "addr:postcode":"02121",
    "addr:street":"Hewins St",
    "iso:country":"US",
    "sg:address":"35 Hewins St 2",
    "sg:city":"Dorchester",
    "sg:classifiers":[
        {
            "category":"Education",
            "subcategory":"Preschool",
            "type":"Public Place"
        }
    ],
    "sg:phone":"+1 857 753 5733",
    "sg:postcode":"02121",
    "sg:province":"MA",
    "sg:tags":[
        "kindergarten"
    ],
    "wof:name":"Rafael Hernandez",
    "wof:placetype":"venue"
},
  "geometry": {"coordinates":[-71.081216,42.302598],"type":"Point"}
}