{
  "type": "Feature",
  "properties": {
    "iso:country":"US",
    "sg:address":"319 Main St",
    "sg:city":"Stoneham",
    "sg:classifiers":[
        {
            "category":"Building & Trades",
            "subcategory":"Cleaning & Sanitation",
            "type":"Services"
        }
    ],
    "sg:phone":"+1 781 438 9611",
    "sg:postcode":"02180",
    "sg:province":"MA",
    "sg:tags":[
        "janitor"
    ],
    "wof:name":"Unica Cleaning Svc Inc",
    "wof:placetype":"venue"
},
  "geometry": {"coordinates":[-71.10026000000001,42.481549],"type":"Point"}
}