{
  "type": "Feature",
  "properties": {
    "addr:full": "319 Main St Stoneham MA 02180",
    "addr:housenumber": "319",
    "addr:postcode": "02180",
    "addr:street": "Main St",
    "iso:country": "US",
    "sg:address": "319 Main St",
    "sg:city": "Stoneham",
    "sg:classifiers": [
      {
        "category": "Building \u0026 Trades",
        "subcategory": "Cleaning \u0026 Sanitation",
        "type": "Services"
      }
    ],
    "sg:phone": "+1 781 438 9611",
    "sg:postcode": "02180",
    "sg:province": "MA",
    "sg:tags": [
      "janitor"
    ],
    "wof:name": "Unica Cleaning Svc Inc",
    "wof:placetype": "venue"
  },
  "geometry": {"coordinates":[-71.10026,42.481549],"type":"Point"}
}
