{
  "type": "Feature",
  "properties": {
    "addr:full":"189 Lincoln St Hingham MA 02043",
    "addr:housenumber":"189",
    "addr:postcode":"02043",
    "addr:street":"Lincoln St",
    "iso:country":"US",
    "sg:address":"189 Lincoln St",
    "sg:city":"Hingham",
    "sg:classifiers":[
        {
            "category":"Food & Beverages",
            "subcategory":"Groceries & Convenience Stores",
            "type":"Retail Goods"
        }
    ],
    "sg:phone":"+1 781 740 2824",
    "sg:postcode":"02043",
    "sg:province":"MA",
    "wof:name":"Tedeschi Food Shops",
    "wof:placetype":"venue"
},
  "geometry": {"coordinates":[-70.904269,42.249277],"type":"Point"}
}