{
  "type": "Feature",
  "properties": {
    "iso:country":"US",
    "sg:address":"383 Shrewsbury St",
    "sg:city":"Worcester",
    "sg:classifiers":[
        {
            "category":"Manufacturing",
            "subcategory":"Metals",
            "type":"Manufacturing & Wholesale Goods"
        }
    ],
    "sg:phone":"+1 508 754 7295",
    "sg:postcode":"01604",
    "sg:province":"MA",
    "sg:tags":[
        "machine",
        "screw",
        "product"
    ],
    "wof:name":"United Screw Mach Products Inc",
    "wof:placetype":"venue"
},
  "geometry": {"coordinates":[-71.775595,42.270924],"type":"Point"}
}