{
  "type": "Feature",
  "properties": {
    "addr:full": "383 Shrewsbury St Worcester MA 01604",
    "addr:housenumber": "383",
    "addr:postcode": "01604",
    "addr:street": "Shrewsbury St",
    "iso:country": "US",
    "sg:address": "383 Shrewsbury St",
    "sg:city": "Worcester",
    "sg:classifiers": [
      {
        "category": "Manufacturing",
        "subcategory": "Metals",
        "type": "Manufacturing \u0026 Wholesale Goods"
      }
    ],
    "sg:phone": "+1 508 754 7295",
    "sg:postcode": "01604",
    "sg:province": "MA",
    "sg:tags": [
      "machine",
      "screw",
      "product"
    ],
    "wof:name": "United Screw Mach Products Inc",
    "wof:placetype": "venue"
  },
  "geometry": {"coordinates":[-71.775595,42.270924],"type":"Point"}
}
