{
  "type": "Feature",
  "properties": {
    "iso:country":"US",
    "sg:address":"55 Barnard Rd",
    "sg:city":"Osterville",
    "sg:classifiers":[
        {
            "category":"Banks & Credit Unions",
            "subcategory":"Investment Brokerage",
            "type":"Services"
        }
    ],
    "sg:phone":"+1 508 428 5151",
    "sg:postcode":"02655",
    "sg:province":"MA",
    "sg:tags":[
        "stock",
        "bond"
    ],
    "sg:website":"www.turner-corp.com",
    "wof:name":"Turner Corp",
    "wof:placetype":"venue"
},
  "geometry": {"coordinates":[-70.375719,41.619772],"type":"Point"}
}