{
  "type": "Feature",
  "properties": {
    "iso:country":"US",
    "sg:address":"13 Garland Rd",
    "sg:city":"Concord",
    "sg:classifiers":[
        {
            "category":"Banks & Credit Unions",
            "subcategory":"Financial Services",
            "type":"Services"
        }
    ],
    "sg:phone":"+1 978 287 1470",
    "sg:postcode":"01742",
    "sg:province":"MA",
    "sg:tags":[
        "financing"
    ],
    "wof:name":"Tertiary Inc",
    "wof:placetype":"venue"
},
  "geometry": {"coordinates":[-71.374561,42.459969],"type":"Point"}
}