{
  "type": "Feature",
  "properties": {
    "addr:full": "13 Garland Rd Concord MA 01742",
    "addr:housenumber": "13",
    "addr:postcode": "01742",
    "addr:street": "Garland Rd",
    "iso:country": "US",
    "sg:address": "13 Garland Rd",
    "sg:city": "Concord",
    "sg:classifiers": [
      {
        "category": "Banks \u0026 Credit Unions",
        "subcategory": "Financial Services",
        "type": "Services"
      }
    ],
    "sg:phone": "+1 978 287 1470",
    "sg:postcode": "01742",
    "sg:province": "MA",
    "sg:tags": [
      "financing"
    ],
    "wof:name": "Tertiary Inc",
    "wof:placetype": "venue"
  },
  "geometry": {"coordinates":[-71.374561,42.459969],"type":"Point"}
}
