{
  "type": "Feature",
  "properties": {
    "addr:full":"131 Dartmouth Street Boston MA 02116",
    "addr:housenumber":"131",
    "addr:postcode":"02116",
    "addr:street":"Dartmouth Street",
    "iso:country":"US",
    "sg:address":"131 Dartmouth Street",
    "sg:city":"Boston",
    "sg:classifiers":[
        {
            "category":"Retail",
            "subcategory":"Car Wash",
            "type":"Services"
        }
    ],
    "sg:phone":"+1 617 247 0600",
    "sg:postcode":"02116",
    "sg:province":"MA",
    "sg:website":"www.writetouchpos.com",
    "wof:name":"Magic Touch",
    "wof:placetype":"venue"
},
  "geometry": {"coordinates":[-71.075773,42.346615],"type":"Point"}
}