{
  "type": "Feature",
  "properties": {
    "addr:full": "386 Lindelof Ave Stoughton MA 02072",
    "addr:housenumber": "386",
    "addr:postcode": "02072",
    "addr:street": "Lindelof Ave",
    "iso:country": "US",
    "sg:address": "386 Lindelof Ave",
    "sg:city": "Stoughton",
    "sg:classifiers": [
      {
        "category": "Manufacturing",
        "subcategory": "Signs",
        "type": "Manufacturing \u0026 Wholesale Goods"
      }
    ],
    "sg:phone": "+1 508 427 3662",
    "sg:postcode": "02072",
    "sg:province": "MA",
    "sg:tags": [
      "advertising",
      "specialty"
    ],
    "wof:name": "C T Sign \u0026 Neon",
    "wof:placetype": "venue"
  },
  "geometry": {"coordinates":[-71.063728,42.160915],"type":"Point"}
}
