{
  "type": "Feature",
  "properties": {
    "iso:country":"US",
    "sg:address":"21 Market St",
    "sg:city":"Ipswich",
    "sg:classifiers":[
        {
            "category":"Professional",
            "subcategory":"Management & Consulting",
            "type":"Services"
        }
    ],
    "sg:phone":"+1 978 356 4218",
    "sg:postcode":"01938",
    "sg:province":"MA",
    "sg:tags":[
        "marketing",
        "program"
    ],
    "wof:name":"IMT",
    "wof:placetype":"venue"
},
  "geometry": {"coordinates":[-70.83830500000001,42.679661],"type":"Point"}
}