{
  "type": "Feature",
  "properties": {
    "iso:country":"US",
    "sg:address":"459 Pleasant St",
    "sg:city":"Northampton",
    "sg:classifiers":[
        {
            "category":"Autos & Motor Vehicles",
            "subcategory":"Automobile Sales",
            "type":"Retail Goods"
        }
    ],
    "sg:phone":"+1 413 586 8150",
    "sg:postcode":"01060",
    "sg:province":"MA",
    "sg:tags":[
        "car",
        "dealer"
    ],
    "sg:website":"www.pleasantjourney.com",
    "wof:name":"Pleasant Journey Used Cars Inc",
    "wof:placetype":"venue"
},
  "geometry": {"coordinates":[-72.625212,42.314982],"type":"Point"}
}