{
  "type": "Feature",
  "properties": {
    "addr:full": "190 Commercial Street Malden MA 02148",
    "addr:housenumber": "190",
    "addr:postcode": "02148",
    "addr:street": "Commercial Street",
    "iso:country": "US",
    "sg:address": "190 Commercial Street",
    "sg:city": "Malden",
    "sg:classifiers": [
      {
        "category": "Home \u0026 Garden",
        "subcategory": "Hardware",
        "type": "Retail Goods"
      }
    ],
    "sg:phone": "+1 781 322 8463",
    "sg:postcode": "02148",
    "sg:province": "MA",
    "sg:tags": [
      "store"
    ],
    "wof:name": "Lamson \u0026 Davis Hardware",
    "wof:placetype": "venue"
  },
  "geometry": {"coordinates":[-71.075499,42.420803],"type":"Point"}
}
