{
  "type": "Feature",
  "properties": {
    "iso:country":"US",
    "sg:address":"190 Commercial Street",
    "sg:city":"Malden",
    "sg:classifiers":[
        {
            "category":"Home & Garden",
            "subcategory":"Hardware",
            "type":"Retail Goods"
        }
    ],
    "sg:phone":"+1 781 322 8463",
    "sg:postcode":"02148",
    "sg:province":"MA",
    "sg:tags":[
        "store"
    ],
    "wof:name":"Lamson & Davis Hardware",
    "wof:placetype":"venue"
},
  "geometry": {"coordinates":[-71.07549899999999,42.420803],"type":"Point"}
}