{
  "type": "Feature",
  "properties": {
    "addr:full": "200 Logan Airport Boston MA 02128",
    "addr:housenumber": "200",
    "addr:postcode": "02128",
    "addr:street": "Logan Airport",
    "iso:country": "US",
    "sg:address": "200 Logan Airport",
    "sg:city": "Boston",
    "sg:classifiers": [
      {
        "category": "Shopping",
        "subcategory": "Books",
        "type": "Retail Goods"
      }
    ],
    "sg:phone": "+1 617 567 1554",
    "sg:postcode": "02128",
    "sg:province": "MA",
    "sg:tags": [
      "bookstore"
    ],
    "wof:name": "Virgin Books \u0026 Music",
    "wof:placetype": "venue"
  },
  "geometry": {"coordinates":[-71.007731,42.363425],"type":"Point"}
}
