{
  "type": "Feature",
  "properties": {
    "addr:full": "22 Heritage Path Millis MA 02054",
    "addr:housenumber": "22",
    "addr:postcode": "02054",
    "addr:street": "Heritage Path",
    "iso:country": "US",
    "sg:address": "22 Heritage Path",
    "sg:city": "Millis",
    "sg:classifiers": [
      {
        "category": "Arts \u0026 Performance",
        "subcategory": "Art Gallery",
        "type": "Entertainment"
      }
    ],
    "sg:phone": "+1 508 794 1026",
    "sg:postcode": "02054",
    "sg:province": "MA",
    "sg:tags": [
      "consultant",
      "galleries"
    ],
    "wof:name": "Blink Of An Eye Images",
    "wof:placetype": "venue"
  },
  "geometry": {"coordinates":[-71.346762,42.165613],"type":"Point"}
}
