{
  "type": "Feature",
  "properties": {
    "iso:country":"US",
    "sg:address":"16 Temple Rd",
    "sg:city":"Lynnfield",
    "sg:classifiers":[
        {
            "category":"Professional",
            "subcategory":"Management & Consulting",
            "type":"Services"
        }
    ],
    "sg:phone":"+1   ",
    "sg:postcode":"01940",
    "sg:province":"MA",
    "sg:tags":[
        "environmental"
    ],
    "wof:name":"Colvin Consulting Inc",
    "wof:placetype":"venue"
},
  "geometry": {"coordinates":[-71.031336,42.527034],"type":"Point"}
}