{
  "type": "Feature",
  "properties": {
    "iso:country":"US",
    "sg:address":"4 Marshall Street",
    "sg:city":"North Adams",
    "sg:classifiers":[
        {
            "category":"Professional",
            "subcategory":"Computer Services",
            "type":"Services"
        }
    ],
    "sg:phone":"+1 718 797 0722",
    "sg:postcode":"01247",
    "sg:province":"MA",
    "sg:website":"http://waterfrontmedia.com",
    "wof:name":"Waterfront Media",
    "wof:placetype":"venue"
},
  "geometry": {"coordinates":[-73.113596,42.700844],"type":"Point"}
}