{
  "type": "Feature",
  "properties": {
    "addr:full":"201 Washington St Boston MA 02108",
    "addr:housenumber":"201",
    "addr:postcode":"02108",
    "addr:street":"Washington St",
    "iso:country":"US",
    "sg:address":"201 Washington St",
    "sg:city":"Boston",
    "sg:classifiers":[
        {
            "category":"Shopping",
            "subcategory":"Catalog Store",
            "type":"Retail Goods"
        }
    ],
    "sg:phone":"+1 617 619 3605",
    "sg:postcode":"02108",
    "sg:province":"MA",
    "sg:tags":[
        "e"
    ],
    "wof:name":"Opsware Inc",
    "wof:placetype":"venue"
},
  "geometry": {"coordinates":[-71.05789,42.358731],"type":"Point"}
}