{
  "type": "Feature",
  "properties": {
    "addr:full": "97 Cambridge St Lawrence MA 01843",
    "addr:housenumber": "97",
    "addr:postcode": "01843",
    "addr:street": "Cambridge St",
    "iso:country": "US",
    "sg:address": "97 Cambridge St",
    "sg:city": "Lawrence",
    "sg:classifiers": [
      {
        "category": "Organizations",
        "subcategory": "Religious Organization",
        "type": "Services"
      }
    ],
    "sg:phone": "+1   ",
    "sg:postcode": "01843",
    "sg:province": "MA",
    "wof:name": "Sisters of Charity Halifax",
    "wof:placetype": "venue"
  },
  "geometry": {"coordinates":[-71.151936,42.693962],"type":"Point"}
}
