{
  "type": "Feature",
  "properties": {
    "addr:full":"12 Elm St Agawam MA 01001",
    "addr:housenumber":"12",
    "addr:postcode":"01001",
    "addr:street":"Elm St",
    "iso:country":"US",
    "sg:address":"12 Elm St",
    "sg:city":"Agawam",
    "sg:classifiers":[
        {
            "category":"Real Estate",
            "subcategory":"Real Estate Agent",
            "type":"Services"
        }
    ],
    "sg:phone":"+1 413 786 3317",
    "sg:postcode":"01001",
    "sg:province":"MA",
    "wof:name":"John G Molta Real Estate",
    "wof:placetype":"venue"
},
  "geometry": {"coordinates":[-72.61864799999999,42.067176],"type":"Point"}
}