{
  "type": "Feature",
  "properties": {
    "iso:country":"US",
    "sg:address":"12 N Main St",
    "sg:city":"South Yarmouth",
    "sg:classifiers":[
        {
            "category":"Retail",
            "subcategory":"Laundry & Dry Cleaning",
            "type":"Services"
        }
    ],
    "sg:phone":"+1 508 398 1404",
    "sg:postcode":"02664",
    "sg:province":"MA",
    "sg:tags":[
        "cleaners"
    ],
    "wof:name":"Professional Cleaners Group",
    "wof:placetype":"venue"
},
  "geometry": {"coordinates":[-70.185001,41.666894],"type":"Point"}
}