{
  "type": "Feature",
  "properties": {
    "addr:full": "22 Samoset St Plymouth MA 02360",
    "addr:housenumber": "22",
    "addr:postcode": "02360",
    "addr:street": "Samoset St",
    "iso:country": "US",
    "sg:address": "22 Samoset St",
    "sg:city": "Plymouth",
    "sg:classifiers": [
      {
        "category": "Health Services",
        "subcategory": "Health Practitioner",
        "type": "Services"
      }
    ],
    "sg:phone": "+1 508 747 8283",
    "sg:postcode": "02360",
    "sg:province": "MA",
    "sg:tags": [
      "acupuncture"
    ],
    "wof:name": "Healing Matters",
    "wof:placetype": "venue"
  },
  "geometry": {"coordinates":[-70.672085,41.95874],"type":"Point"}
}
