{
  "type": "Feature",
  "properties": {
    "addr:full": "414 Commercial Street Boston MA 02109",
    "addr:housenumber": "414",
    "addr:postcode": "02109",
    "addr:street": "Commercial Street",
    "iso:country": "US",
    "sg:address": "414 Commercial Street",
    "sg:city": "Boston",
    "sg:classifiers": [
      {
        "category": "Sports \u0026 Exercise",
        "subcategory": "Gym",
        "type": "Entertainment"
      },
      {
        "category": "Health Services",
        "subcategory": "Chiropractor",
        "type": "Services"
      }
    ],
    "sg:phone": "+1 617 742 5797",
    "sg:postcode": "02109",
    "sg:province": "MA",
    "sg:tags": [
      "trainer"
    ],
    "wof:name": "Loughlin Kevin J Chirprctr",
    "wof:placetype": "venue"
  },
  "geometry": {"coordinates":[-71.053326,42.36222],"type":"Point"}
}
