{
  "type": "Feature",
  "properties": {
    "iso:country":"US",
    "sg:address":"1190 Adams St",
    "sg:city":"Dorchester Ctr",
    "sg:classifiers":[
        {
            "category":"Social Services",
            "subcategory":"Adult Care",
            "type":"Services"
        }
    ],
    "sg:phone":"+1 617 298 5656",
    "sg:postcode":"02124",
    "sg:province":"MA",
    "sg:tags":[
        "home",
        "residential"
    ],
    "wof:name":"Standish Village At Lower Mill",
    "wof:placetype":"venue"
},
  "geometry": {"coordinates":[-71.066858,42.272239],"type":"Point"}
}