{
  "type": "Feature",
  "properties": {
    "iso:country":"US",
    "sg:address":"3 Lyons Way",
    "sg:city":"North Attleboro",
    "sg:classifiers":[
        {
            "category":"Insurance",
            "subcategory":"Hazard Insurance",
            "type":"Services"
        }
    ],
    "sg:phone":"+1 508 699 3060",
    "sg:postcode":"02763",
    "sg:province":"MA",
    "sg:tags":[
        "profit",
        "sharing",
        "pension",
        "plan"
    ],
    "wof:name":"Benefit Management Inc",
    "wof:placetype":"venue"
},
  "geometry": {"coordinates":[-71.31188299999999,41.969745],"type":"Point"}
}