{
  "type": "Feature",
  "properties": {
    "addr:full": "438 Dartmouth St New Bedford MA 02740",
    "addr:housenumber": "438",
    "addr:postcode": "02740",
    "addr:street": "Dartmouth St",
    "iso:country": "US",
    "ovtr:label": "Stop \u0026 Shop, 438 Dartmouth St New Bedford MA US",
    "ovtr:similarity": 1.9183299541473389,
    "sg:address": "438 Dartmouth St",
    "sg:city": "New Bedford",
    "sg:classifiers": [
      {
        "category": "Professional",
        "type": "Services"
      }
    ],
    "sg:phone": "+1 508 996 4543",
    "sg:postcode": "02740",
    "sg:province": "MA",
    "sg:tags": [
      "establishment"
    ],
    "wof:name": "Stop \u0026 Shop",
    "wof:placetype": "venue"
  },
  "geometry": {"coordinates":[-70.937131,41.615973],"type":"Point"}
}
