{
  "type": "Feature",
  "properties": {
    "iso:country":"US",
    "sg:address":"438 Dartmouth St",
    "sg:city":"New Bedford",
    "sg:classifiers":[
        {
            "category":"Professional",
            "type":"Services"
        }
    ],
    "sg:phone":"+1 508 996 4543",
    "sg:postcode":"02740",
    "sg:province":"MA",
    "sg:tags":[
        "establishment"
    ],
    "wof:name":"Stop & Shop",
    "wof:placetype":"venue"
},
  "geometry": {"coordinates":[-70.93713099999999,41.615973],"type":"Point"}
}