{
  "type": "Feature",
  "properties": {
    "iso:country":"US",
    "sg:address":"274 Main St",
    "sg:city":"Reading",
    "sg:classifiers":[
        {
            "category":"Communications",
            "subcategory":"Film & Video Production",
            "type":"Services"
        }
    ],
    "sg:phone":"+1 781 944 1799",
    "sg:postcode":"01867",
    "sg:province":"MA",
    "sg:tags":[
        "consultant",
        "audio"
    ],
    "wof:name":"Wideband Solutions",
    "wof:placetype":"venue"
},
  "geometry": {"coordinates":[-71.103741,42.515453],"type":"Point"}
}