{
  "type": "Feature",
  "properties": {
    "addr:full": "3 Main St Lee MA 01238",
    "addr:housenumber": "3",
    "addr:postcode": "01238",
    "addr:street": "Main St",
    "iso:country": "US",
    "ovtr:label": "Kelly Funeral Home, 3 Main St Lee MA US",
    "ovtr:similarity": 2.703326940536499,
    "sg:address": "3 Main St",
    "sg:city": "Lee",
    "sg:classifiers": [
      {
        "category": "Retail",
        "subcategory": "Funeral Services",
        "type": "Services"
      }
    ],
    "sg:phone": "+1 413 243 0204",
    "sg:postcode": "01238",
    "sg:province": "MA",
    "sg:tags": [
      "director"
    ],
    "wof:name": "Kelly Funeral Home",
    "wof:placetype": "venue"
  },
  "geometry": {"coordinates":[-73.249034,42.304686],"type":"Point"}
}
