{
  "type": "Feature",
  "properties": {
    "iso:country":"US",
    "sg:address":"3 Main St",
    "sg:city":"Lee",
    "sg:classifiers":[
        {
            "category":"Retail",
            "subcategory":"Funeral Services",
            "type":"Services"
        }
    ],
    "sg:phone":"+1 413 243 0204",
    "sg:postcode":"01238",
    "sg:province":"MA",
    "sg:tags":[
        "director"
    ],
    "wof:name":"Kelly Funeral Home",
    "wof:placetype":"venue"
},
  "geometry": {"coordinates":[-73.24903399999999,42.304686],"type":"Point"}
}