{
  "type": "Feature",
  "properties": {
    "addr:full":"345 Sumner St Boston MA 02128",
    "addr:housenumber":"345",
    "addr:postcode":"02128",
    "addr:street":"Sumner St",
    "iso:country":"US",
    "sg:address":"345 Sumner St",
    "sg:city":"Boston",
    "sg:classifiers":[
        {
            "category":"Food & Beverages",
            "subcategory":"Groceries & Convenience Stores",
            "type":"Retail Goods"
        }
    ],
    "sg:phone":"+1 617 567 9286",
    "sg:postcode":"02128",
    "sg:province":"MA",
    "wof:name":"Salles Grocery Store",
    "wof:placetype":"venue"
},
  "geometry": {"coordinates":[-71.035572,42.367024],"type":"Point"}
}