{
  "type": "Feature",
  "properties": {
    "iso:country":"US",
    "sg:address":"545 State Rd",
    "sg:city":"Plymouth",
    "sg:classifiers":[
        {
            "category":"Farming",
            "subcategory":"Nursery",
            "type":"Manufacturing & Wholesale Goods"
        }
    ],
    "sg:phone":"+1 508 224 3450",
    "sg:postcode":"02360",
    "sg:province":"MA",
    "sg:tags":[
        "greenhouse"
    ],
    "wof:name":"Dutchies Greenhouses",
    "wof:placetype":"venue"
},
  "geometry": {"coordinates":[-70.567587,41.922231],"type":"Point"}
}