{
  "type": "Feature",
  "properties": {
    "addr:full": "545 State Rd Plymouth MA 02360",
    "addr:housenumber": "545",
    "addr:postcode": "02360",
    "addr:street": "State Rd",
    "iso:country": "US",
    "sg:address": "545 State Rd",
    "sg:city": "Plymouth",
    "sg:classifiers": [
      {
        "category": "Farming",
        "subcategory": "Nursery",
        "type": "Manufacturing \u0026 Wholesale Goods"
      }
    ],
    "sg:phone": "+1 508 224 3450",
    "sg:postcode": "02360",
    "sg:province": "MA",
    "sg:tags": [
      "greenhouse"
    ],
    "wof:name": "Dutchies Greenhouses",
    "wof:placetype": "venue"
  },
  "geometry": {"coordinates":[-70.567587,41.922231],"type":"Point"}
}
