{
  "type": "Feature",
  "properties": {
    "iso:country":"US",
    "sg:address":"61 Lucia Ave",
    "sg:city":"Revere",
    "sg:classifiers":[
        {
            "category":"Organizations",
            "subcategory":"Membership Organization",
            "type":"Services"
        }
    ],
    "sg:phone":"+1 781 284 5445",
    "sg:postcode":"02151",
    "sg:province":"MA",
    "sg:tags":[
        "military",
        "veteran"
    ],
    "wof:name":"Italian American War Veterans Of The United States Inc",
    "wof:placetype":"venue"
},
  "geometry": {"coordinates":[-71.023487,42.425698],"type":"Point"}
}