{
  "type": "Feature",
  "properties": {
    "iso:country":"US",
    "sg:address":"90 Skyline Dr",
    "sg:city":"Nantucket",
    "sg:classifiers":[
        {
            "category":"Travel",
            "subcategory":"Hotels & Motels",
            "type":"Entertainment"
        }
    ],
    "sg:phone":"+1 508 228 8966",
    "sg:postcode":"02554",
    "sg:province":"MA",
    "sg:tags":[
        "breakfast",
        "accommodation",
        "bed"
    ],
    "wof:name":"Claire's Guest House",
    "wof:placetype":"venue"
},
  "geometry": {"coordinates":[-70.070365,41.254931],"type":"Point"}
}