{
  "type": "Feature",
  "properties": {
    "addr:full":"1 Centre St Brockton MA 02346",
    "addr:housenumber":"1",
    "addr:postcode":"02346",
    "addr:street":"Centre St",
    "iso:country":"US",
    "sg:address":"1 Centre St",
    "sg:city":"Brockton",
    "sg:classifiers":[
        {
            "category":"Professional",
            "subcategory":"Lawyer & Legal Services",
            "type":"Services"
        }
    ],
    "sg:phone":"+1 508 587 6670",
    "sg:postcode":"02346",
    "sg:province":"MA",
    "sg:tags":[
        "attorney"
    ],
    "wof:name":"Creedon & Creedon",
    "wof:placetype":"venue"
},
  "geometry": {"coordinates":[-70.91011399999999,41.892799],"type":"Point"}
}