{
  "type": "Feature",
  "properties": {
    "addr:full":"4422 Acushnet Ave New Bedford MA 02745",
    "addr:housenumber":"4422",
    "addr:postcode":"02745",
    "addr:street":"Acushnet Ave",
    "iso:country":"US",
    "sg:address":"4422 Acushnet Ave",
    "sg:city":"New Bedford",
    "sg:classifiers":[
        {
            "category":"Restaurant",
            "type":"Food & Drink"
        }
    ],
    "sg:phone":"+1 508 995 0440",
    "sg:postcode":"02745",
    "sg:province":"MA",
    "wof:name":"Red Dragon Restaurant",
    "wof:placetype":"venue"
},
  "geometry": {"coordinates":[-70.944455,41.737629],"type":"Point"}
}