{
  "type": "Feature",
  "properties": {
    "addr:full":"8 Bell St Danvers MA 01923",
    "addr:housenumber":"8",
    "addr:postcode":"01923",
    "addr:street":"Bell St",
    "iso:country":"US",
    "sg:address":"8 Bell St",
    "sg:city":"Danvers",
    "sg:classifiers":[
        {
            "category":"Shopping",
            "type":"Retail Goods"
        }
    ],
    "sg:phone":"+1   ",
    "sg:postcode":"01923",
    "sg:province":"MA",
    "sg:tags":[
        "merchandise"
    ],
    "wof:name":"C & M Cake Dctg & Candle Sups",
    "wof:placetype":"venue"
},
  "geometry": {"coordinates":[-70.94221400000001,42.567448],"type":"Point"}
}