{
  "type": "Feature",
  "properties": {
    "iso:country":"US",
    "sg:address":"2 Washington St",
    "sg:city":"Foxboro",
    "sg:classifiers":[
        {
            "category":"Building & Trades",
            "subcategory":"Construction",
            "type":"Services"
        }
    ],
    "sg:phone":"+1 508 850 9488",
    "sg:postcode":"02035",
    "sg:province":"MA",
    "sg:tags":[
        "contractor"
    ],
    "wof:name":"Intoccia Construction",
    "wof:placetype":"venue"
},
  "geometry": {"coordinates":[-71.252656,42.105696],"type":"Point"}
}