{
  "type": "Feature",
  "properties": {
    "addr:full":"281 Pleasant St Framingham MA 01701",
    "addr:housenumber":"281",
    "addr:postcode":"01701",
    "addr:street":"Pleasant St",
    "iso:country":"US",
    "sg:address":"281 Pleasant St",
    "sg:city":"Framingham",
    "sg:classifiers":[
        {
            "category":"Professional",
            "type":"Services"
        }
    ],
    "sg:phone":"+1 508 875 1705",
    "sg:postcode":"01701",
    "sg:province":"MA",
    "wof:name":"Lifetree Therapeutic Massage",
    "wof:placetype":"venue"
},
  "geometry": {"coordinates":[-71.449421,42.304417],"type":"Point"}
}