{
  "type": "Feature",
  "properties": {
    "addr:full":"307 Auburn St Cambridge MA 02138",
    "addr:housenumber":"307",
    "addr:postcode":"02138",
    "addr:street":"Auburn St",
    "iso:country":"US",
    "sg:address":"307 Auburn St",
    "sg:city":"Cambridge",
    "sg:classifiers":[
        {
            "category":"Banks & Credit Unions",
            "subcategory":"Bank",
            "type":"Services"
        }
    ],
    "sg:phone":"+1 617 588 7063",
    "sg:postcode":"02138",
    "sg:province":"MA",
    "sg:website":"www.village-bank.com",
    "wof:name":"Village Bank",
    "wof:placetype":"venue"
},
  "geometry": {"coordinates":[-71.107174,42.364878],"type":"Point"}
}