{
  "type": "Feature",
  "properties": {
    "addr:full": "2136 Washington St Roxbury MA 02119",
    "addr:housenumber": "2136",
    "addr:postcode": "02119",
    "addr:street": "Washington St",
    "iso:country": "US",
    "sg:address": "2136 Washington St",
    "sg:city": "Roxbury",
    "sg:classifiers": [
      {
        "category": "Building \u0026 Trades",
        "subcategory": "Locksmith",
        "type": "Services"
      }
    ],
    "sg:phone": "+1 617 602 1123",
    "sg:postcode": "02119",
    "sg:province": "MA",
    "sg:tags": [
      "key"
    ],
    "wof:name": "Rc Locksmith",
    "wof:placetype": "venue"
  },
  "geometry": {"coordinates":[-71.081982,42.331491],"type":"Point"}
}
