{
  "type": "Feature",
  "properties": {
    "iso:country":"US",
    "sg:address":"425 Main St",
    "sg:city":"Greenfield",
    "sg:classifiers":[
        {
            "category":"Government",
            "subcategory":"Office",
            "type":"Public Place"
        }
    ],
    "sg:phone":"+1 413 772 0239",
    "sg:postcode":"01301",
    "sg:province":"MA",
    "wof:name":"Franklin County Register-Deeds",
    "wof:placetype":"venue"
},
  "geometry": {"coordinates":[-72.598181,42.587456],"type":"Point"}
}