{
  "type": "Feature",
  "properties": {
    "iso:country":"US",
    "sg:address":"43 Moulton St",
    "sg:city":"Newburyport",
    "sg:classifiers":[
        {
            "category":"Building & Trades",
            "subcategory":"Cleaning & Sanitation",
            "type":"Services"
        }
    ],
    "sg:phone":"+1 978 454 9735",
    "sg:postcode":"01950",
    "sg:province":"MA",
    "sg:tags":[
        "janitor"
    ],
    "wof:name":"CSM Corp",
    "wof:placetype":"venue"
},
  "geometry": {"coordinates":[-70.900965,42.825052],"type":"Point"}
}