{
  "type": "Feature",
  "properties": {
    "addr:full": "459 Main St Wilbraham MA 01095",
    "addr:housenumber": "459",
    "addr:postcode": "01095",
    "addr:street": "Main St",
    "iso:country": "US",
    "sg:address": "459 Main St",
    "sg:city": "Wilbraham",
    "sg:classifiers": [
      {
        "category": "Shopping",
        "subcategory": "Pharmacy",
        "type": "Retail Goods"
      }
    ],
    "sg:phone": "+1 413 596 6121",
    "sg:postcode": "01095",
    "sg:province": "MA",
    "sg:website": "www.lcdrug.com",
    "wof:name": "Louis \u0026 Clark Drug Stores",
    "wof:placetype": "venue"
  },
  "geometry": {"coordinates":[-72.431201,42.123139],"type":"Point"}
}
