{
  "type": "Feature",
  "properties": {
    "iso:country":"US",
    "sg:address":"227 Newbury Street Bsmt",
    "sg:city":"Boston",
    "sg:classifiers":[
        {
            "category":"Real Estate",
            "subcategory":"Real Estate Services",
            "type":"Services"
        },
        {
            "category":"Real Estate",
            "subcategory":"Real Estate Operator",
            "type":"Services"
        }
    ],
    "sg:phone":"+1 617 375 6900",
    "sg:postcode":"02116",
    "sg:province":"MA",
    "sg:tags":[
        "apartment"
    ],
    "wof:name":"Gibson Domain Domain Real Estate",
    "wof:placetype":"venue"
},
  "geometry": {"coordinates":[-71.08163999999999,42.349944],"type":"Point"}
}