{
  "type": "Feature",
  "properties": {
    "addr:full":"154 Bradstreet Ave Revere MA 02151",
    "addr:housenumber":"154",
    "addr:postcode":"02151",
    "addr:street":"Bradstreet Ave",
    "iso:country":"US",
    "sg:address":"154 Bradstreet Ave",
    "sg:city":"Revere",
    "sg:classifiers":[
        {
            "category":"Building & Trades",
            "subcategory":"Electrical",
            "type":"Services"
        },
        {
            "category":"Retail",
            "subcategory":"Auto Repair",
            "type":"Services"
        }
    ],
    "sg:phone":"+1 781 284 7819",
    "sg:postcode":"02151",
    "sg:province":"MA",
    "sg:tags":[
        "automobile",
        "electrician",
        "electric"
    ],
    "wof:name":"Joe Marasca Electrical",
    "wof:placetype":"venue"
},
  "geometry": {"coordinates":[-70.987106,42.395841],"type":"Point"}
}