{
  "type": "Feature",
  "properties": {
    "iso:country":"US",
    "sg:address":"828 Point Rd",
    "sg:city":"Marion",
    "sg:classifiers":[
        {
            "category":"Retail",
            "subcategory":"Auto Repair",
            "type":"Services"
        }
    ],
    "sg:phone":"+1 508 748 1951",
    "sg:postcode":"02738",
    "sg:province":"MA",
    "sg:tags":[
        "repairing",
        "automobile"
    ],
    "wof:name":"O'Gara's Auto Svc",
    "wof:placetype":"venue"
},
  "geometry": {"coordinates":[-70.751998,41.720019],"type":"Point"}
}