{
  "type": "Feature",
  "properties": {
    "iso:country":"US",
    "sg:address":"243 S Main St",
    "sg:city":"Attleboro",
    "sg:classifiers":[
        {
            "category":"Retail",
            "subcategory":"Repair Shop",
            "type":"Services"
        }
    ],
    "sg:phone":"+1 508 222 1455",
    "sg:postcode":"02703",
    "sg:province":"MA",
    "sg:tags":[
        "petroleum",
        "oil",
        "burner",
        "products-wholesale",
        "manufacturer"
    ],
    "wof:name":"South Main Oil Inc",
    "wof:placetype":"venue"
},
  "geometry": {"coordinates":[-71.284988,41.933521],"type":"Point"}
}