{
  "type": "Feature",
  "properties": {
    "addr:full":"11 N Beacon St Watertown MA 02472",
    "addr:housenumber":"11",
    "addr:postcode":"02472",
    "addr:street":"N Beacon St",
    "iso:country":"US",
    "sg:address":"11 N Beacon St",
    "sg:city":"Watertown",
    "sg:classifiers":[
        {
            "category":"Restaurant",
            "type":"Food & Drink"
        }
    ],
    "sg:phone":"+1 617 923 2369",
    "sg:postcode":"02472",
    "sg:province":"MA",
    "wof:name":"Talk Of The Town Diner",
    "wof:placetype":"venue"
},
  "geometry": {"coordinates":[-71.18289,42.364968],"type":"Point"}
}