{
  "type": "Feature",
  "properties": {
    "addr:full":"30 North St Boston MA 02109",
    "addr:housenumber":"30",
    "addr:postcode":"02109",
    "addr:street":"North St",
    "iso:country":"US",
    "sg:address":"30 North St",
    "sg:city":"Boston",
    "sg:classifiers":[
        {
            "category":"Building & Trades",
            "subcategory":"Locksmith",
            "type":"Services"
        }
    ],
    "sg:phone":"+1 617 531 0460",
    "sg:postcode":"02109",
    "sg:province":"MA",
    "sg:tags":[
        "key"
    ],
    "wof:name":"Locksmith",
    "wof:placetype":"venue"
},
  "geometry": {"coordinates":[-71.05628900000001,42.360644],"type":"Point"}
}