{
  "type": "Feature",
  "properties": {
    "iso:country":"US",
    "sg:address":"365 Summer St",
    "sg:city":"Fitchburg",
    "sg:classifiers":[
        {
            "category":"Recreation",
            "subcategory":"Arcade",
            "type":"Entertainment"
        }
    ],
    "sg:phone":"+1 978 342 0303",
    "sg:postcode":"01420",
    "sg:province":"MA",
    "sg:tags":[
        "amusement",
        "devices"
    ],
    "wof:name":"Viana Distributing",
    "wof:placetype":"venue"
},
  "geometry": {"coordinates":[-71.774998,42.571217],"type":"Point"}
}