{
  "type": "Feature",
  "properties": {
    "addr:full": "7 Surrey Ln Danvers MA 01923",
    "addr:housenumber": "7",
    "addr:postcode": "01923",
    "addr:street": "Surrey Ln",
    "iso:country": "US",
    "sg:address": "7 Surrey Ln",
    "sg:city": "Danvers",
    "sg:classifiers": [
      {
        "category": "Wholesale",
        "subcategory": "Durable Goods \u0026 Equipment",
        "type": "Manufacturing \u0026 Wholesale Goods"
      }
    ],
    "sg:phone": "+1 978 774 7499",
    "sg:postcode": "01923",
    "sg:province": "MA",
    "sg:tags": [
      "representative",
      "manufacturer"
    ],
    "wof:name": "Phillips Engineered Products",
    "wof:placetype": "venue"
  },
  "geometry": {"coordinates":[-70.93453,42.579326],"type":"Point"}
}
