{
  "type": "Feature",
  "properties": {
    "iso:country":"US",
    "sg:address":"904 Sandwich Rd",
    "sg:city":"Sagamore",
    "sg:classifiers":[
        {
            "category":"Building & Trades",
            "subcategory":"Construction",
            "type":"Services"
        }
    ],
    "sg:phone":"+1 508 394 4787",
    "sg:postcode":"02561",
    "sg:province":"MA",
    "sg:tags":[
        "paving",
        "road",
        "contractor"
    ],
    "wof:name":"Sagamore Associates",
    "wof:placetype":"venue"
},
  "geometry": {"coordinates":[-70.53726399999999,41.772726],"type":"Point"}
}