{
  "type": "Feature",
  "properties": {
    "iso:country":"US",
    "sg:address":"152 S Main St",
    "sg:city":"Middleton",
    "sg:classifiers":[
        {
            "category":"Personal",
            "subcategory":"Beauty Salon",
            "type":"Services"
        }
    ],
    "sg:phone":"+1 978 777 1190",
    "sg:postcode":"01949",
    "sg:province":"MA",
    "wof:name":"Julie's Advanced Skin Care Day",
    "wof:placetype":"venue"
},
  "geometry": {"coordinates":[-71.006731,42.584232],"type":"Point"}
}