{
  "type": "Feature",
  "properties": {
    "addr:full":"520 Simonds Rd Ashby MA 01431",
    "addr:housenumber":"520",
    "addr:postcode":"01431",
    "addr:street":"Simonds Rd",
    "iso:country":"US",
    "sg:address":"520 Simonds Rd",
    "sg:city":"Ashby",
    "sg:classifiers":[
        {
            "category":"Building & Trades",
            "subcategory":"Construction",
            "type":"Services"
        }
    ],
    "sg:phone":"+1   ",
    "sg:postcode":"01431",
    "sg:province":"MA",
    "sg:tags":[
        "carpentry",
        "contractor"
    ],
    "wof:name":"Apple Hill Woodworks",
    "wof:placetype":"venue"
},
  "geometry": {"coordinates":[-71.80433499999999,42.697651],"type":"Point"}
}