{
  "type": "Feature",
  "properties": {
    "addr:full":"95 Westminster Rd East Weymouth MA 02189",
    "addr:housenumber":"95",
    "addr:postcode":"02189",
    "addr:street":"Westminster Rd",
    "iso:country":"US",
    "sg:address":"95 Westminster Rd",
    "sg:city":"East Weymouth",
    "sg:classifiers":[
        {
            "category":"Professional",
            "subcategory":"Business Services",
            "type":"Services"
        }
    ],
    "sg:phone":"+1   ",
    "sg:postcode":"02189",
    "sg:province":"MA",
    "wof:name":"Lakeshore Dental Lab",
    "wof:placetype":"venue"
},
  "geometry": {"coordinates":[-70.933964,42.202804],"type":"Point"}
}