{
  "type": "Feature",
  "properties": {
    "iso:country":"US",
    "sg:address":"100 Summer St",
    "sg:city":"Boston",
    "sg:classifiers":[
        {
            "category":"Professional",
            "subcategory":"Lawyer & Legal Services",
            "type":"Services"
        }
    ],
    "sg:phone":"+1 617 720 1333",
    "sg:postcode":"02110",
    "sg:province":"MA",
    "wof:name":"Lesser Michael A Atty",
    "wof:placetype":"venue"
},
  "geometry": {"coordinates":[-71.057999,42.353802],"type":"Point"}
}