{
  "type": "Feature",
  "properties": {
    "addr:full":"125 Summer Street Boston MA 02110",
    "addr:housenumber":"125",
    "addr:postcode":"02110",
    "addr:street":"Summer Street",
    "iso:country":"US",
    "sg:address":"125 Summer Street",
    "sg:city":"Boston",
    "sg:classifiers":[
        {
            "category":"Professional",
            "subcategory":"Lawyer & Legal Services",
            "type":"Services"
        }
    ],
    "sg:phone":"+1 617 345 3000",
    "sg:postcode":"02110",
    "sg:province":"MA",
    "wof:name":"Davidson Shepard C Lwyr",
    "wof:placetype":"venue"
},
  "geometry": {"coordinates":[-71.05764000000001,42.353374],"type":"Point"}
}