{
  "type": "Feature",
  "properties": {
    "iso:country":"US",
    "sg:address":"32 Lake St",
    "sg:city":"Norfolk",
    "sg:classifiers":[
        {
            "category":"Professional",
            "subcategory":"Business Services",
            "type":"Services"
        }
    ],
    "sg:phone":"+1   ",
    "sg:postcode":"02056",
    "sg:province":"MA",
    "wof:name":"Review Video",
    "wof:placetype":"venue"
},
  "geometry": {"coordinates":[-71.346986,42.119289],"type":"Point"}
}