{
  "type": "Feature",
  "properties": {
    "addr:full":"1972 Massachusetts Ave Cambridge MA 02140",
    "addr:housenumber":"1972",
    "addr:postcode":"02140",
    "addr:street":"Massachusetts Ave",
    "iso:country":"US",
    "sg:address":"1972 Massachusetts Ave",
    "sg:city":"Cambridge",
    "sg:classifiers":[
        {
            "category":"Real Estate",
            "subcategory":"Architect",
            "type":"Services"
        }
    ],
    "sg:phone":"+1 617 737 3200",
    "sg:postcode":"02140",
    "sg:province":"MA",
    "wof:name":"Leslie Saul & Assoc Inc",
    "wof:placetype":"venue"
},
  "geometry": {"coordinates":[-71.119202,42.386799],"type":"Point"}
}