{
  "type": "Feature",
  "properties": {
    "iso:country":"US",
    "sg:address":"522 Hancock St",
    "sg:city":"Wollaston",
    "sg:classifiers":[
        {
            "category":"Health Services",
            "subcategory":"Doctor",
            "type":"Services"
        }
    ],
    "sg:phone":"+1 617 773 6605",
    "sg:postcode":"02170",
    "sg:province":"MA",
    "sg:tags":[
        "dentist"
    ],
    "wof:name":"Abraham H Alter DDS",
    "wof:placetype":"venue"
},
  "geometry": {"coordinates":[-71.0219,42.2712],"type":"Point"}
}