{
  "type": "Feature",
  "properties": {
    "iso:country":"US",
    "sg:address":"115 Adams St",
    "sg:city":"North Adams",
    "sg:classifiers":[
        {
            "category":"Shopping",
            "subcategory":"Used Merchandise",
            "type":"Retail Goods"
        }
    ],
    "sg:phone":"+1 413 662 6885",
    "sg:postcode":"01267",
    "sg:province":"MA",
    "sg:tags":[
        "antique"
    ],
    "wof:name":"Heritage Antiques",
    "wof:placetype":"venue"
},
  "geometry": {"coordinates":[-73.19077,42.704773],"type":"Point"}
}