{
  "type": "Feature",
  "properties": {
    "addr:full":"38 Loring St Auburn MA 01501",
    "addr:housenumber":"38",
    "addr:postcode":"01501",
    "addr:street":"Loring St",
    "iso:country":"US",
    "sg:address":"38 Loring St",
    "sg:city":"Auburn",
    "sg:classifiers":[
        {
            "category":"Professional",
            "subcategory":"Business Services",
            "type":"Services"
        }
    ],
    "sg:phone":"+1   ",
    "sg:postcode":"01501",
    "sg:province":"MA",
    "sg:tags":[
        "used",
        "merchandise"
    ],
    "wof:name":"Auburn Antique Mall",
    "wof:placetype":"venue"
},
  "geometry": {"coordinates":[-71.841432,42.187007],"type":"Point"}
}