{
  "type": "Feature",
  "properties": {
    "addr:full": "175 Main St Spencer MA 01562",
    "addr:housenumber": "175",
    "addr:postcode": "01562",
    "addr:street": "Main St",
    "iso:country": "US",
    "sg:address": "175 Main St",
    "sg:city": "Spencer",
    "sg:classifiers": [
      {
        "category": "Organizations",
        "subcategory": "Community Association",
        "type": "Services"
      }
    ],
    "sg:phone": "+1 508 885 5930",
    "sg:postcode": "01562",
    "sg:province": "MA",
    "sg:tags": [
      "military"
    ],
    "wof:name": "American Legion",
    "wof:placetype": "venue"
  },
  "geometry": {"coordinates":[-71.992421,42.244068],"type":"Point"}
}
