{
  "type": "Feature",
  "properties": {
    "iso:country":"US",
    "sg:address":"27 Cedar Crest Rd",
    "sg:city":"Wayland",
    "sg:classifiers":[
        {
            "category":"Building & Trades",
            "subcategory":"Construction",
            "type":"Services"
        }
    ],
    "sg:phone":"+1 508 655 9665",
    "sg:postcode":"01778",
    "sg:province":"MA",
    "sg:tags":[
        "masonry",
        "contractor"
    ],
    "wof:name":"Cliff Construction Masonary",
    "wof:placetype":"venue"
},
  "geometry": {"coordinates":[-71.37179399999999,42.336308],"type":"Point"}
}