{
  "type": "Feature",
  "properties": {
    "iso:country":"US",
    "sg:address":"283 Boston Ave",
    "sg:city":"Medford",
    "sg:classifiers":[
        {
            "category":"Deli",
            "type":"Food & Drink"
        },
        {
            "category":"Cafe",
            "type":"Food & Drink"
        }
    ],
    "sg:menulink":"http://www.allmenus.com/ma/medford/17544-pasta-pisa---cafe-de-crepe/menu/",
    "sg:phone":"+1 781 391 2030",
    "sg:postcode":"02155",
    "sg:province":"MA",
    "sg:tags":[
        "sandwich",
        "crepe",
        "calzones",
        "american",
        "wrap",
        "pizza",
        "italian"
    ],
    "wof:name":"Pasta Pisa - Cafe De Crepe",
    "wof:placetype":"venue"
},
  "geometry": {"coordinates":[-71.11182100000001,42.400146],"type":"Point"}
}