{
  "type": "Feature",
  "properties": {
    "addr:full":"770 Main Rd Westport MA 02790",
    "addr:housenumber":"770",
    "addr:postcode":"02790",
    "addr:street":"Main Rd",
    "iso:country":"US",
    "sg:address":"770 Main Rd",
    "sg:city":"Westport",
    "sg:classifiers":[
        {
            "category":"Shopping",
            "subcategory":"Florist",
            "type":"Retail Goods"
        }
    ],
    "sg:phone":"+1 508 636 5535",
    "sg:postcode":"02790",
    "sg:province":"MA",
    "wof:name":"Brown Eyed Susan's Flower Shop",
    "wof:placetype":"venue"
},
  "geometry": {"coordinates":[-71.09043800000001,41.577181],"type":"Point"}
}