{
  "type": "Feature",
  "properties": {
    "iso:country":"US",
    "sg:address":"61 Pleasant St",
    "sg:city":"Spencer",
    "sg:classifiers":[
        {
            "category":"Bakery",
            "type":"Food & Drink"
        }
    ],
    "sg:phone":"+1 508 885 0266",
    "sg:postcode":"01562",
    "sg:province":"MA",
    "wof:name":"Koprowski's Bakery Distributors - CLOSED",
    "wof:placetype":"venue"
},
  "geometry": {"coordinates":[-71.996803,42.248001],"type":"Point"}
}