{
  "type": "Feature",
  "properties": {
    "addr:full":"1000 Bennington St Boston MA 02128",
    "addr:housenumber":"1000",
    "addr:postcode":"02128",
    "addr:street":"Bennington St",
    "iso:country":"US",
    "sg:address":"1000 Bennington St",
    "sg:city":"Boston",
    "sg:classifiers":[
        {
            "category":"Restaurant",
            "type":"Food & Drink"
        }
    ],
    "sg:phone":"+1 617 567 1346",
    "sg:postcode":"02128",
    "sg:province":"MA",
    "wof:name":"Cafe Orient Heights",
    "wof:placetype":"venue"
},
  "geometry": {"coordinates":[-71.0069,42.3869],"type":"Point"}
}