{
  "type": "Feature",
  "properties": {
    "iso:country":"US",
    "sg:address":"918 Cambridge St",
    "sg:city":"Cambridge",
    "sg:classifiers":[
        {
            "category":"Shopping",
            "subcategory":"Bicycles & Sporting Goods",
            "type":"Retail Goods"
        }
    ],
    "sg:phone":"+1 617 441 2500",
    "sg:postcode":"02141",
    "sg:province":"MA",
    "sg:tags":[
        "bike"
    ],
    "sg:website":"www.hubbicycle.com/",
    "wof:name":"Hub Bicycle Company",
    "wof:placetype":"venue"
},
  "geometry": {"coordinates":[-71.092026,42.372568],"type":"Point"}
}