{
  "type": "Feature",
  "properties": {
    "addr:full": "16 Linden St Whitinsville MA 01588",
    "addr:housenumber": "16",
    "addr:postcode": "01588",
    "addr:street": "Linden St",
    "iso:country": "US",
    "sg:address": "16 Linden St",
    "sg:city": "Whitinsville",
    "sg:classifiers": [
      {
        "category": "Health Services",
        "subcategory": "Health Practitioner",
        "type": "Services"
      }
    ],
    "sg:phone": "+1 508 234 6540",
    "sg:postcode": "01588",
    "sg:province": "MA",
    "sg:tags": [
      "psychotherapist"
    ],
    "wof:name": "Formation Consultation Svc",
    "wof:placetype": "venue"
  },
  "geometry": {"coordinates":[-71.672456,42.111791],"type":"Point"}
}
