{
  "type": "Feature",
  "properties": {
    "iso:country":"US",
    "sg:address":"1 Alewife Center",
    "sg:city":"Cambridge",
    "sg:classifiers":[
        {
            "category":"Manufacturing",
            "subcategory":"Printing",
            "type":"Manufacturing & Wholesale Goods"
        }
    ],
    "sg:phone":"+1 617 492 9668",
    "sg:postcode":"02140",
    "sg:province":"MA",
    "sg:tags":[
        "multimedia"
    ],
    "sg:website":"www.sixredmarbles.com",
    "wof:name":"Six Red Marbles",
    "wof:placetype":"venue"
},
  "geometry": {"coordinates":[-71.140472,42.398697],"type":"Point"}
}