{
  "type": "Feature",
  "properties": {
    "addr:full":"386 Arsenal St Watertown MA 02472",
    "addr:housenumber":"386",
    "addr:postcode":"02472",
    "addr:street":"Arsenal St",
    "iso:country":"US",
    "sg:address":"386 Arsenal St",
    "sg:city":"Watertown",
    "sg:classifiers":[
        {
            "category":"Retail",
            "subcategory":"Auto Repair",
            "type":"Services"
        }
    ],
    "sg:phone":"+1 617 924 1118",
    "sg:postcode":"02472",
    "sg:province":"MA",
    "sg:tags":[
        "body",
        "automobile",
        "painting"
    ],
    "wof:name":"European Auto Body Inc",
    "wof:placetype":"venue"
},
  "geometry": {"coordinates":[-71.16213399999999,42.363459],"type":"Point"}
}