{
  "type": "Feature",
  "properties": {
    "iso:country":"US",
    "sg:address":"26 Farragut St",
    "sg:city":"Lowell",
    "sg:classifiers":[
        {
            "category":"Building & Trades",
            "subcategory":"Electrical",
            "type":"Services"
        }
    ],
    "sg:phone":"+1 978 454 4453",
    "sg:postcode":"01854",
    "sg:province":"MA",
    "sg:tags":[
        "electric",
        "contractor"
    ],
    "wof:name":"Lowell Electrical Construction",
    "wof:placetype":"venue"
},
  "geometry": {"coordinates":[-71.32928,42.657833],"type":"Point"}
}