{
  "type": "Feature",
  "properties": {
    "addr:full":"293 Washington St Dorchester MA 02121",
    "addr:housenumber":"293",
    "addr:postcode":"02121",
    "addr:street":"Washington St",
    "iso:country":"US",
    "sg:address":"293 Washington St",
    "sg:city":"Dorchester",
    "sg:classifiers":[
        {
            "category":"Building & Trades",
            "subcategory":"Locksmith",
            "type":"Services"
        }
    ],
    "sg:phone":"+1 617 514 7064",
    "sg:postcode":"02121",
    "sg:province":"MA",
    "sg:tags":[
        "key"
    ],
    "wof:name":"Locksmith Service A",
    "wof:placetype":"venue"
},
  "geometry": {"coordinates":[-71.075396,42.300448],"type":"Point"}
}