{
  "type": "Feature",
  "properties": {
    "addr:full": "100 Locke Dr Marlborough MA 01752",
    "addr:housenumber": "100",
    "addr:postcode": "01752",
    "addr:street": "Locke Dr",
    "iso:country": "US",
    "sg:address": "100 Locke Dr",
    "sg:city": "Marlborough",
    "sg:classifiers": [
      {
        "category": "Shopping",
        "subcategory": "Computers \u0026 Home Electronics",
        "type": "Retail Goods"
      }
    ],
    "sg:phone": "+1 508 480 6990",
    "sg:postcode": "01752",
    "sg:province": "MA",
    "sg:tags": [
      "software"
    ],
    "sg:website": "www.adlex.com",
    "wof:name": "Adlex Corp",
    "wof:placetype": "venue"
  },
  "geometry": {"coordinates":[-71.579445,42.349274],"type":"Point"}
}
