{
  "type": "Feature",
  "properties": {
    "addr:full":"630 Commonwealth Ave Newton Center MA 02459",
    "addr:housenumber":"630",
    "addr:postcode":"02459",
    "addr:street":"Commonwealth Ave Newton Center",
    "iso:country":"US",
    "sg:address":"630 Commonwealth Ave",
    "sg:city":"Newton Center",
    "sg:classifiers":[
        {
            "category":"Personal",
            "subcategory":"Beauty Salon",
            "type":"Services"
        }
    ],
    "sg:phone":"+1 617 527 4181",
    "sg:postcode":"02459",
    "sg:province":"MA",
    "sg:tags":[
        "manicuring"
    ],
    "wof:name":"Way's Nail Salon",
    "wof:placetype":"venue"
},
  "geometry": {"coordinates":[-71.192144,42.336128],"type":"Point"}
}