{
  "type": "Feature",
  "properties": {
    "iso:country":"US",
    "sg:address":"314 Main St",
    "sg:city":"Wilmington",
    "sg:classifiers":[
        {
            "category":"Professional",
            "subcategory":"Lawyer & Legal Services",
            "type":"Services"
        }
    ],
    "sg:phone":"+1 978 658 5687",
    "sg:postcode":"01887",
    "sg:province":"MA",
    "wof:name":"Cutter Richard A Lwyr",
    "wof:placetype":"venue"
},
  "geometry": {"coordinates":[-71.177498,42.551102],"type":"Point"}
}