{
  "type": "Feature",
  "properties": {
    "iso:country":"US",
    "sg:address":"48 Willow Street",
    "sg:city":"Malden",
    "sg:classifiers":[
        {
            "category":"Personal",
            "subcategory":"Beauty Salon",
            "type":"Services"
        }
    ],
    "sg:phone":"+1 781 324 7333",
    "sg:postcode":"02148",
    "sg:province":"MA",
    "sg:tags":[
        "hair"
    ],
    "wof:name":"Curl Up & Dye",
    "wof:placetype":"venue"
},
  "geometry": {"coordinates":[-71.053532,42.426619],"type":"Point"}
}