{
  "type": "Feature",
  "properties": {
    "iso:country":"US",
    "sg:address":"10 Pole Plain Rd",
    "sg:city":"Sharon",
    "sg:classifiers":[
        {
            "category":"Real Estate",
            "subcategory":"Real Estate Services",
            "type":"Services"
        },
        {
            "category":"Real Estate",
            "subcategory":"Real Estate Agent",
            "type":"Services"
        }
    ],
    "sg:phone":"+1 781 784 9647",
    "sg:postcode":"02067",
    "sg:province":"MA",
    "sg:tags":[
        "management"
    ],
    "wof:name":"Aspis Inc",
    "wof:placetype":"venue"
},
  "geometry": {"coordinates":[-71.202265,42.107556],"type":"Point"}
}