{
  "type": "Feature",
  "properties": {
    "addr:full": "261 Locust St Springfield MA 01108",
    "addr:housenumber": "261",
    "addr:postcode": "01108",
    "addr:street": "Locust St",
    "iso:country": "US",
    "sg:address": "261 Locust St",
    "sg:city": "Springfield",
    "sg:classifiers": [
      {
        "category": "Manufacturing",
        "subcategory": "Motor Vehicles \u0026 Parts",
        "type": "Manufacturing \u0026 Wholesale Goods"
      }
    ],
    "sg:phone": "+1 413 739 9677",
    "sg:postcode": "01108",
    "sg:province": "MA",
    "sg:tags": [
      "automobile",
      "supply"
    ],
    "wof:name": "Enfield Auto Elec Sales Inc",
    "wof:placetype": "venue"
  },
  "geometry": {"coordinates":[-72.570678,42.092793],"type":"Point"}
}
