{
  "type": "Feature",
  "properties": {
    "addr:full":"8 Commerce Dr Orleans MA 02653",
    "addr:housenumber":"8",
    "addr:postcode":"02653",
    "addr:street":"Commerce Dr",
    "iso:country":"US",
    "sg:address":"8 Commerce Dr",
    "sg:city":"Orleans",
    "sg:classifiers":[
        {
            "category":"Shopping",
            "subcategory":"Used Merchandise",
            "type":"Retail Goods"
        }
    ],
    "sg:phone":"+1 508 255 2646",
    "sg:postcode":"02653",
    "sg:province":"MA",
    "sg:tags":[
        "antique"
    ],
    "wof:name":"Orleans Carpenters",
    "wof:placetype":"venue"
},
  "geometry": {"coordinates":[-69.99672700000001,41.776685],"type":"Point"}
}