{
  "type": "Feature",
  "properties": {
    "iso:country":"US",
    "sg:address":"62 Washington St",
    "sg:city":"Marblehead",
    "sg:classifiers":[
        {
            "category":"Manufacturing",
            "subcategory":"Printing",
            "type":"Manufacturing & Wholesale Goods"
        }
    ],
    "sg:phone":"+1   ",
    "sg:postcode":"01945",
    "sg:province":"MA",
    "sg:tags":[
        "book"
    ],
    "wof:name":"Dm Enterprises",
    "wof:placetype":"venue"
},
  "geometry": {"coordinates":[-70.84812700000001,42.506346],"type":"Point"}
}