{
  "type": "Feature",
  "properties": {
    "iso:country":"US",
    "sg:address":"50 Pine St",
    "sg:city":"Seekonk",
    "sg:classifiers":[
        {
            "category":"Travel",
            "subcategory":"Bed & Breakfast",
            "type":"Entertainment"
        }
    ],
    "sg:phone":"+1 508 761 7146",
    "sg:postcode":"02771",
    "sg:province":"MA",
    "sg:website":"www.nicholsguestrooms.com",
    "wof:name":"Nichol's Guestrooms",
    "wof:placetype":"venue"
},
  "geometry": {"coordinates":[-71.329599,41.888528],"type":"Point"}
}