{
  "type": "Feature",
  "properties": {
    "addr:full":"1849 Massachusetts Ave Lexington MA 02420",
    "addr:housenumber":"1849",
    "addr:postcode":"02420",
    "addr:street":"Massachusetts Ave",
    "iso:country":"US",
    "sg:address":"1849 Massachusetts Ave",
    "sg:city":"Lexington",
    "sg:classifiers":[
        {
            "category":"Shopping",
            "subcategory":"Mobile Phones",
            "type":"Retail Goods"
        }
    ],
    "sg:phone":"+1 781 861 7100",
    "sg:postcode":"02420",
    "sg:province":"MA",
    "sg:website":"www.verizonwireless.com",
    "wof:name":"Verizon Wireless",
    "wof:placetype":"venue"
},
  "geometry": {"coordinates":[-71.228858,42.448419],"type":"Point"}
}