{
  "type": "Feature",
  "properties": {
    "addr:full": "393 E Main St Southbridge MA 01550",
    "addr:housenumber": "393",
    "addr:postcode": "01550",
    "addr:street": "E Main St",
    "iso:country": "US",
    "sg:address": "393 E Main St",
    "sg:city": "Southbridge",
    "sg:classifiers": [
      {
        "category": "Autos \u0026 Motor Vehicles",
        "subcategory": "Auto Supplies",
        "type": "Retail Goods"
      }
    ],
    "sg:phone": "+1 508 909 0272",
    "sg:postcode": "01550",
    "sg:province": "MA",
    "sg:tags": [
      "automobile",
      "parts"
    ],
    "wof:name": "Benard Auto Parts",
    "wof:placetype": "venue"
  },
  "geometry": {"coordinates":[-72.015766,42.071032],"type":"Point"}
}
