{
  "type": "Feature",
  "properties": {
    "addr:full": "261 Milton St Dedham MA 02026",
    "addr:housenumber": "261",
    "addr:postcode": "02026",
    "addr:street": "Milton St",
    "iso:country": "US",
    "sg:address": "261 Milton St",
    "sg:city": "Dedham",
    "sg:classifiers": [
      {
        "category": "Retail",
        "subcategory": "Auto Repair",
        "type": "Services"
      }
    ],
    "sg:phone": "+1 781 329 9007",
    "sg:postcode": "02026",
    "sg:province": "MA",
    "sg:tags": [
      "repairing",
      "automobile"
    ],
    "wof:name": "Bert's Service Ctr",
    "wof:placetype": "venue"
  },
  "geometry": {"coordinates":[-71.145305,42.24138],"type":"Point"}
}
