{
  "type": "Feature",
  "properties": {
    "iso:country":"US",
    "sg:address":"261 Milton St",
    "sg:city":"Dedham",
    "sg:classifiers":[
        {
            "category":"Retail",
            "subcategory":"Auto Repair",
            "type":"Services"
        }
    ],
    "sg:phone":"+1 781 329 9007",
    "sg:postcode":"02026",
    "sg:province":"MA",
    "sg:tags":[
        "repairing",
        "automobile"
    ],
    "wof:name":"Bert's Service Ctr",
    "wof:placetype":"venue"
},
  "geometry": {"coordinates":[-71.14530499999999,42.24138],"type":"Point"}
}