{
  "type": "Feature",
  "properties": {
    "iso:country":"US",
    "sg:address":"386 Main St",
    "sg:city":"Southbridge",
    "sg:classifiers":[
        {
            "category":"Professional",
            "subcategory":"Accounting & Tax Preparation",
            "type":"Services"
        }
    ],
    "sg:phone":"+1 508 765 5484",
    "sg:postcode":"01550",
    "sg:province":"MA",
    "sg:tags":[
        "accountant"
    ],
    "wof:name":"Carlin Bruce M CPA",
    "wof:placetype":"venue"
},
  "geometry": {"coordinates":[-72.0373,42.077599],"type":"Point"}
}