{
  "type": "Feature",
  "properties": {
    "addr:full": "386 Main St Southbridge MA 01550",
    "addr:housenumber": "386",
    "addr:postcode": "01550",
    "addr:street": "Main St",
    "iso:country": "US",
    "sg:address": "386 Main St",
    "sg:city": "Southbridge",
    "sg:classifiers": [
      {
        "category": "Professional",
        "subcategory": "Accounting \u0026 Tax Preparation",
        "type": "Services"
      }
    ],
    "sg:phone": "+1 508 765 5484",
    "sg:postcode": "01550",
    "sg:province": "MA",
    "sg:tags": [
      "accountant"
    ],
    "wof:name": "Carlin Bruce M CPA",
    "wof:placetype": "venue"
  },
  "geometry": {"coordinates":[-72.0373,42.077599],"type":"Point"}
}
