{
  "type": "Feature",
  "properties": {
    "addr:full":"10 Rogers St Cambridge MA 02142",
    "addr:housenumber":"10",
    "addr:postcode":"02142",
    "addr:street":"Rogers St",
    "iso:country":"US",
    "sg:address":"10 Rogers St",
    "sg:city":"Cambridge",
    "sg:classifiers":[
        {
            "category":"Health Services",
            "subcategory":"Doctor",
            "type":"Services"
        },
        {
            "category":"Health Services",
            "subcategory":"Dentist",
            "type":"Services"
        }
    ],
    "sg:phone":"+1 617 497 6453",
    "sg:postcode":"02142",
    "sg:province":"MA",
    "sg:tags":[
        "dentists-oral",
        "physician",
        "maxillofacial",
        "surgeons",
        "surgery",
        "oral",
        "surgeon"
    ],
    "wof:name":"Gregory Kosmidis Dmd Pc",
    "wof:placetype":"venue"
},
  "geometry": {"coordinates":[-71.07685600000001,42.365703],"type":"Point"}
}