{
  "type": "Feature",
  "properties": {
    "addr:full":"175 Bodwell St Avon MA 02322",
    "addr:housenumber":"175",
    "addr:postcode":"02322",
    "addr:street":"Bodwell St",
    "iso:country":"US",
    "sg:address":"175 Bodwell St",
    "sg:city":"Avon",
    "sg:classifiers":[
        {
            "category":"Donuts",
            "subcategory":"None",
            "type":"Food & Drink"
        }
    ],
    "sg:phone":"+1 508 436 7777",
    "sg:postcode":"02322",
    "sg:province":"MA",
    "wof:name":"Donut Factory - CLOSED",
    "wof:placetype":"venue"
},
  "geometry": {"coordinates":[-71.046997,42.126598],"type":"Point"}
}