{
  "type": "Feature",
  "properties": {
    "addr:full": "1050 N Main St Randolph MA 02368",
    "addr:housenumber": "1050",
    "addr:postcode": "02368",
    "addr:street": "N Main St",
    "iso:country": "US",
    "sg:address": "1050 N Main St",
    "sg:city": "Randolph",
    "sg:classifiers": [
      {
        "category": "Restaurant",
        "type": "Food \u0026 Drink"
      }
    ],
    "sg:phone": "+1 781 986 9981",
    "sg:postcode": "02368",
    "sg:province": "MA",
    "wof:name": "Piccadilly Pub Restaurants",
    "wof:placetype": "venue"
  },
  "geometry": {"coordinates":[-71.059303,42.191799],"type":"Point"}
}
