{
  "type": "Feature",
  "properties": {
    "addr:full":"679 Mount Auburn St Cambridge MA 02138",
    "addr:housenumber":"679",
    "addr:postcode":"02138",
    "addr:street":"Mount Auburn St",
    "iso:country":"US",
    "sg:address":"679 Mount Auburn St",
    "sg:city":"Cambridge",
    "sg:classifiers":[
        {
            "category":"Building & Trades",
            "subcategory":"Locksmith",
            "type":"Services"
        }
    ],
    "sg:phone":"+1 617 299 2055",
    "sg:postcode":"02138",
    "sg:province":"MA",
    "sg:tags":[
        "key"
    ],
    "wof:name":"24 7 Available Emergency Locksmith",
    "wof:placetype":"venue"
},
  "geometry": {"coordinates":[-71.148157,42.375083],"type":"Point"}
}