{
  "type": "Feature",
  "properties": {
    "iso:country":"US",
    "sg:address":"41 Colchester Dr",
    "sg:city":"Plymouth",
    "sg:classifiers":[
        {
            "category":"Professional",
            "subcategory":"Business Services",
            "type":"Services"
        }
    ],
    "sg:phone":"+1 508 747 6388",
    "sg:postcode":"02360",
    "sg:province":"MA",
    "sg:tags":[
        "pool",
        "swimming"
    ],
    "wof:name":"Mazzilli Pool Svc",
    "wof:placetype":"venue"
},
  "geometry": {"coordinates":[-70.69440299999999,41.918803],"type":"Point"}
}