{
  "type": "Feature",
  "properties": {
    "addr:full":"766 Memorial Dr Chicopee MA 01020",
    "addr:housenumber":"766",
    "addr:postcode":"01020",
    "addr:street":"Memorial Dr",
    "iso:country":"US",
    "sg:address":"766 Memorial Dr",
    "sg:city":"Chicopee",
    "sg:classifiers":[
        {
            "category":"Personal",
            "subcategory":"Barber",
            "type":"Services"
        }
    ],
    "sg:phone":"+1 413 593 1330",
    "sg:postcode":"01020",
    "sg:province":"MA",
    "wof:name":"Natural Look",
    "wof:placetype":"venue"
},
  "geometry": {"coordinates":[-72.57705799999999,42.178077],"type":"Point"}
}