{
  "type": "Feature",
  "properties": {
    "addr:full": "8 Pilgrim Dr Westfield MA 01085",
    "addr:housenumber": "8",
    "addr:postcode": "01085",
    "addr:street": "Pilgrim Dr",
    "iso:country": "US",
    "sg:address": "8 Pilgrim Dr",
    "sg:city": "Westfield",
    "sg:classifiers": [
      {
        "category": "Professional",
        "subcategory": "Management \u0026 Consulting",
        "type": "Services"
      }
    ],
    "sg:phone": "+1   ",
    "sg:postcode": "01085",
    "sg:province": "MA",
    "sg:tags": [
      "consultant",
      "manufacturing",
      "quality",
      "assurance",
      "for"
    ],
    "wof:name": "Quality Consultant",
    "wof:placetype": "venue"
  },
  "geometry": {"coordinates":[-72.74597,42.096041],"type":"Point"}
}
