{
  "type": "Feature",
  "properties": {
    "addr:full": "7 Fire Rd 7 Lancaster MA 01523",
    "addr:housenumber": "7",
    "addr:postcode": "01523",
    "addr:street": "Fire Rd 7",
    "iso:country": "US",
    "sg:address": "7 Fire Rd 7",
    "sg:city": "Lancaster",
    "sg:classifiers": [
      {
        "category": "Retail",
        "subcategory": "Repair Shop",
        "type": "Services"
      }
    ],
    "sg:phone": "+1   ",
    "sg:postcode": "01523",
    "sg:province": "MA",
    "wof:name": "R L Culley Inc",
    "wof:placetype": "venue"
  },
  "geometry": {"coordinates":[-71.677935,42.515973],"type":"Point"}
}
