{
  "type": "Feature",
  "properties": {
    "iso:country":"US",
    "sg:address":"7 Fire Rd 7",
    "sg:city":"Lancaster",
    "sg:classifiers":[
        {
            "category":"Retail",
            "subcategory":"Repair Shop",
            "type":"Services"
        }
    ],
    "sg:phone":"+1   ",
    "sg:postcode":"01523",
    "sg:province":"MA",
    "wof:name":"R L Culley Inc",
    "wof:placetype":"venue"
},
  "geometry": {"coordinates":[-71.67793500000001,42.515973],"type":"Point"}
}