{
  "type": "Feature",
  "properties": {
    "iso:country":"US",
    "sg:address":"181 Essex St",
    "sg:city":"Salem",
    "sg:classifiers":[
        {
            "category":"Shopping",
            "type":"Retail Goods"
        }
    ],
    "sg:phone":"+1 978 745 1001",
    "sg:postcode":"01970",
    "sg:province":"MA",
    "sg:tags":[
        "picture",
        "frame"
    ],
    "wof:name":"Galant Gallery",
    "wof:placetype":"venue"
},
  "geometry": {"coordinates":[-70.892126,42.521896],"type":"Point"}
}