{
  "type": "Feature",
  "properties": {
    "addr:full": "78 Willow St South Hamilton MA 01982",
    "addr:housenumber": "78",
    "addr:postcode": "01982",
    "addr:street": "Willow St South",
    "iso:country": "US",
    "sg:address": "78 Willow St",
    "sg:city": "South Hamilton",
    "sg:classifiers": [
      {
        "category": "Health Services",
        "subcategory": "Podiatrist",
        "type": "Services"
      }
    ],
    "sg:phone": "+1 978 468 2232",
    "sg:postcode": "01982",
    "sg:province": "MA",
    "wof:name": "Hamilton Podiatry",
    "wof:placetype": "venue"
  },
  "geometry": {"coordinates":[-70.876598,42.611138],"type":"Point"}
}
