{
  "type": "Feature",
  "properties": {
    "iso:country":"US",
    "sg:address":"38-36 Mechanic St",
    "sg:city":"Foxboro",
    "sg:classifiers":[
        {
            "category":"Personal",
            "subcategory":"Beauty Salon",
            "type":"Services"
        },
        {
            "category":"Personal",
            "subcategory":"Day Spa",
            "type":"Services"
        }
    ],
    "sg:phone":"+1 508 543 2600",
    "sg:postcode":"02035",
    "sg:province":"MA",
    "sg:website":"http://www.tigerlillydayspa.com",
    "wof:name":"Tigerlilly Day Spa & Salon",
    "wof:placetype":"venue"
},
  "geometry": {"coordinates":[-71.24583199999999,42.06724],"type":"Point"}
}