{
  "type": "Feature",
  "properties": {
    "addr:full": "38-36 Mechanic St Foxboro MA 02035",
    "addr:housenumber": "38-36",
    "addr:postcode": "02035",
    "addr:street": "Mechanic St",
    "iso:country": "US",
    "sg:address": "38-36 Mechanic St",
    "sg:city": "Foxboro",
    "sg:classifiers": [
      {
        "category": "Personal",
        "subcategory": "Beauty Salon",
        "type": "Services"
      },
      {
        "category": "Personal",
        "subcategory": "Day Spa",
        "type": "Services"
      }
    ],
    "sg:phone": "+1 508 543 2600",
    "sg:postcode": "02035",
    "sg:province": "MA",
    "sg:website": "http://www.tigerlillydayspa.com",
    "wof:name": "Tigerlilly Day Spa \u0026 Salon",
    "wof:placetype": "venue"
  },
  "geometry": {"coordinates":[-71.245832,42.06724],"type":"Point"}
}
