{
  "type": "Feature",
  "properties": {
    "iso:country":"US",
    "sg:address":"10 Central St",
    "sg:city":"Manchester",
    "sg:classifiers":[
        {
            "category":"Banks & Credit Unions",
            "subcategory":"Bank",
            "type":"Services"
        }
    ],
    "sg:phone":"+1 978 526 7742",
    "sg:postcode":"01944",
    "sg:province":"MA",
    "wof:name":"Manchester Town Employees Cu",
    "wof:placetype":"venue"
},
  "geometry": {"coordinates":[-70.77240399999999,42.575177],"type":"Point"}
}