{
  "type": "Feature",
  "properties": {
    "addr:full":"90 Parkwood Dr Wareham MA 02571",
    "addr:housenumber":"90",
    "addr:postcode":"02571",
    "addr:street":"Parkwood Dr",
    "iso:country":"US",
    "sg:address":"90 Parkwood Dr",
    "sg:city":"Wareham",
    "sg:classifiers":[
        {
            "category":"Autos & Motor Vehicles",
            "subcategory":"Boat Sales",
            "type":"Retail Goods"
        }
    ],
    "sg:phone":"+1 508 291 3208",
    "sg:postcode":"02571",
    "sg:province":"MA",
    "sg:tags":[
        "top",
        "upholstery",
        "cover"
    ],
    "wof:name":"Paul's Canvas",
    "wof:placetype":"venue"
},
  "geometry": {"coordinates":[-70.703805,41.744448],"type":"Point"}
}