{
  "type": "Feature",
  "properties": {
    "addr:full": "62 Crystal St Lenox Dale MA 01242",
    "addr:housenumber": "62",
    "addr:postcode": "01242",
    "addr:street": "Crystal St",
    "iso:country": "US",
    "sg:address": "62 Crystal St",
    "sg:city": "Lenox Dale",
    "sg:classifiers": [
      {
        "category": "Real Estate",
        "subcategory": "Architect",
        "type": "Services"
      }
    ],
    "sg:phone": "+1 413 637 9996",
    "sg:postcode": "01242",
    "sg:province": "MA",
    "sg:tags": [
      "designer",
      "architectural"
    ],
    "wof:name": "Mark Smith Design",
    "wof:placetype": "venue"
  },
  "geometry": {"coordinates":[-73.245025,42.33735],"type":"Point"}
}
