{
  "type": "Feature",
  "properties": {
    "iso:country":"US",
    "sg:address":"34 Gee Ave Rear",
    "sg:city":"Gloucester",
    "sg:classifiers":[
        {
            "category":"Building & Trades",
            "subcategory":"Construction",
            "type":"Services"
        },
        {
            "category":"Military Area",
            "subcategory":"Armory",
            "type":"Public Place"
        }
    ],
    "sg:phone":"+1 978 283 8500",
    "sg:postcode":"01930",
    "sg:province":"MA",
    "sg:tags":[
        "repair",
        "fence-sales",
        "fence",
        "contractor"
    ],
    "wof:name":"David Linsky",
    "wof:placetype":"venue"
},
  "geometry": {"coordinates":[-70.66819,42.640783],"type":"Point"}
}