{
  "type": "Feature",
  "properties": {
    "addr:full": "25 Meadowlark Dr Wareham MA 02571",
    "addr:housenumber": "25",
    "addr:postcode": "02571",
    "addr:street": "Meadowlark Dr",
    "iso:country": "US",
    "sg:address": "25 Meadowlark Dr",
    "sg:city": "Wareham",
    "sg:classifiers": [
      {
        "category": "Organizations",
        "subcategory": "Religious Organization",
        "type": "Services"
      }
    ],
    "sg:phone": "+1   ",
    "sg:postcode": "02571",
    "sg:province": "MA",
    "wof:name": "C H C Assoc Inc",
    "wof:placetype": "venue"
  },
  "geometry": {"coordinates":[-70.699811,41.765604],"type":"Point"}
}
