{
  "type": "Feature",
  "properties": {
    "iso:country":"US",
    "sg:address":"131 Bradford St",
    "sg:city":"Pittsfield",
    "sg:classifiers":[
        {
            "category":"Organizations",
            "subcategory":"Non-profit Organization",
            "type":"Services"
        }
    ],
    "sg:phone":"+1 413 499 1000",
    "sg:postcode":"01201",
    "sg:province":"MA",
    "sg:tags":[
        "information",
        "alcoholism",
        "treatment"
    ],
    "sg:website":"www.briencenter.org",
    "wof:name":"Brien Center",
    "wof:placetype":"venue"
},
  "geometry": {"coordinates":[-73.255442,42.454644],"type":"Point"}
}