{
  "type": "Feature",
  "properties": {
    "addr:full":"446 Boston Rd Billerica MA 01821",
    "addr:housenumber":"446",
    "addr:postcode":"01821",
    "addr:street":"Boston Rd",
    "iso:country":"US",
    "sg:address":"446 Boston Rd",
    "sg:city":"Billerica",
    "sg:classifiers":[
        {
            "category":"Restaurant",
            "type":"Food & Drink"
        }
    ],
    "sg:phone":"+1   ",
    "sg:postcode":"01821",
    "sg:province":"MA",
    "sg:tags":[
        "eating"
    ],
    "wof:name":"Divito Bros Itln Specialities",
    "wof:placetype":"venue"
},
  "geometry": {"coordinates":[-71.26915,42.559577],"type":"Point"}
}