{
  "type": "Feature",
  "properties": {
    "addr:full": "25 Forest Cir Winchester MA 01890",
    "addr:housenumber": "25",
    "addr:postcode": "01890",
    "addr:street": "Forest Cir",
    "iso:country": "US",
    "sg:address": "25 Forest Cir",
    "sg:city": "Winchester",
    "sg:classifiers": [
      {
        "category": "Professional",
        "type": "Services"
      }
    ],
    "sg:phone": "+1 781 721 5229",
    "sg:postcode": "01890",
    "sg:province": "MA",
    "sg:tags": [
      "establishment"
    ],
    "wof:name": "Hinckley Kee",
    "wof:placetype": "venue"
  },
  "geometry": {"coordinates":[-71.114306,42.472315],"type":"Point"}
}
