{
  "type": "Feature",
  "properties": {
    "addr:full":"361 Somerville Ave Somerville MA 02143",
    "addr:housenumber":"361",
    "addr:postcode":"02143",
    "addr:street":"Somerville Ave",
    "iso:country":"US",
    "sg:address":"361 Somerville Ave",
    "sg:city":"Somerville",
    "sg:classifiers":[
        {
            "category":"Shopping",
            "subcategory":"Clothing, Apparel, & Fashions",
            "type":"Retail Goods"
        },
        {
            "category":"Professional",
            "subcategory":"Art Services",
            "type":"Services"
        }
    ],
    "sg:phone":"+1 617 591 9599",
    "sg:postcode":"02143",
    "sg:province":"MA",
    "sg:tags":[
        "apparel",
        "designer",
        "display",
        "producer",
        "women's"
    ],
    "wof:name":"Cirlene Starr Fashion Brazil",
    "wof:placetype":"venue"
},
  "geometry": {"coordinates":[-71.099182,42.381069],"type":"Point"}
}