{
  "type": "Feature",
  "properties": {
    "addr:full":"40 Court St Boston MA 02108",
    "addr:housenumber":"40",
    "addr:postcode":"02108",
    "addr:street":"Court St",
    "iso:country":"US",
    "sg:address":"40 Court St",
    "sg:city":"Boston",
    "sg:classifiers":[
        {
            "category":"Professional",
            "subcategory":"Lawyer & Legal Services",
            "type":"Services"
        }
    ],
    "sg:phone":"+1 617 556 9995",
    "sg:postcode":"02108",
    "sg:province":"MA",
    "sg:tags":[
        "attorney"
    ],
    "wof:name":"Scot Schneiderman Law Office",
    "wof:placetype":"venue"
},
  "geometry": {"coordinates":[-71.059774,42.359342],"type":"Point"}
}