{
  "type": "Feature",
  "properties": {
    "addr:full": "687 James St Chicopee MA 01020",
    "addr:housenumber": "687",
    "addr:postcode": "01020",
    "addr:street": "James St",
    "iso:country": "US",
    "sg:address": "687 James St",
    "sg:city": "Chicopee",
    "sg:classifiers": [
      {
        "category": "Shopping",
        "subcategory": "Hobbies, Toys, \u0026 Games",
        "type": "Retail Goods"
      }
    ],
    "sg:phone": "+1 413 532 3882",
    "sg:postcode": "01020",
    "sg:province": "MA",
    "sg:tags": [
      "model",
      "supply"
    ],
    "wof:name": "Dreams Hobby \u0026 Sports Cllctbls",
    "wof:placetype": "venue"
  },
  "geometry": {"coordinates":[-72.566402,42.199531],"type":"Point"}
}
