{
  "type": "Feature",
  "properties": {
    "iso:country":"US",
    "sg:address":"687 James St",
    "sg:city":"Chicopee",
    "sg:classifiers":[
        {
            "category":"Shopping",
            "subcategory":"Hobbies, Toys, & Games",
            "type":"Retail Goods"
        }
    ],
    "sg:phone":"+1 413 532 3882",
    "sg:postcode":"01020",
    "sg:province":"MA",
    "sg:tags":[
        "model",
        "supply"
    ],
    "wof:name":"Dreams Hobby & Sports Cllctbls",
    "wof:placetype":"venue"
},
  "geometry": {"coordinates":[-72.566402,42.199531],"type":"Point"}
}