{
  "type": "Feature",
  "properties": {
    "addr:full": "24 Thoreau Rd Lexington MA 02420",
    "addr:housenumber": "24",
    "addr:postcode": "02420",
    "addr:street": "Thoreau Rd",
    "iso:country": "US",
    "sg:address": "24 Thoreau Rd",
    "sg:city": "Lexington",
    "sg:classifiers": [
      {
        "category": "Professional",
        "subcategory": "Computer Services",
        "type": "Services"
      }
    ],
    "sg:phone": "+1   ",
    "sg:postcode": "02420",
    "sg:province": "MA",
    "sg:tags": [
      "related"
    ],
    "wof:name": "Bert K Collins",
    "wof:placetype": "venue"
  },
  "geometry": {"coordinates":[-71.206869,42.462834],"type":"Point"}
}
