{
  "type": "Feature",
  "properties": {
    "addr:full": "155 Village St Ste 1 Medway MA 02053",
    "addr:housenumber": "155",
    "addr:postcode": "02053",
    "addr:street": "Village St Ste 1",
    "iso:country": "US",
    "sg:address": "155 Village St Ste 1",
    "sg:city": "Medway",
    "sg:classifiers": [
      {
        "category": "Government",
        "subcategory": "City Hall",
        "type": "Public Place"
      },
      {
        "category": "Government",
        "subcategory": "Office",
        "type": "Public Place"
      }
    ],
    "sg:phone": "+1 508 533 3200",
    "sg:postcode": "02053",
    "sg:province": "MA",
    "sg:tags": [
      "town",
      "township",
      "planner",
      "government-city",
      "village"
    ],
    "sg:website": "http://www.medwayschools.org",
    "wof:name": "Town Of Medway",
    "wof:placetype": "venue"
  },
  "geometry": {"coordinates":[-71.398018,42.14027],"type":"Point"}
}
