{
  "type": "Feature",
  "properties": {
    "addr:full": "367 Moody St Waltham MA 02453",
    "addr:housenumber": "367",
    "addr:postcode": "02453",
    "addr:street": "Moody St",
    "iso:country": "US",
    "ovtr:label": "Lizzy's Homemade Ice Cream, 367 Moody St Waltham MA US",
    "ovtr:similarity": 2.399308919906616,
    "sg:address": "367 Moody St",
    "sg:city": "Waltham",
    "sg:classifiers": [
      {
        "category": "Restaurant",
        "type": "Food \u0026 Drink"
      }
    ],
    "sg:phone": "+1 781 893 6677",
    "sg:postcode": "02453",
    "sg:province": "MA",
    "sg:tags": [
      "parlor",
      "ice",
      "cream"
    ],
    "sg:website": "www.lizzysicecream.com",
    "wof:name": "Lizzy's Homemade Ice Cream",
    "wof:placetype": "venue"
  },
  "geometry": {"coordinates":[-71.237242,42.369838],"type":"Point"}
}
