{
  "type": "Feature",
  "properties": {
    "iso:country":"US",
    "sg:address":"367 Moody St",
    "sg:city":"Waltham",
    "sg:classifiers":[
        {
            "category":"Restaurant",
            "type":"Food & Drink"
        }
    ],
    "sg:phone":"+1 781 893 6677",
    "sg:postcode":"02453",
    "sg:province":"MA",
    "sg:tags":[
        "parlor",
        "ice",
        "cream"
    ],
    "sg:website":"www.lizzysicecream.com",
    "wof:name":"Lizzy's Homemade Ice Cream",
    "wof:placetype":"venue"
},
  "geometry": {"coordinates":[-71.23724199999999,42.369838],"type":"Point"}
}