{
  "type": "Feature",
  "properties": {
    "addr:full": "6 Gilbert Rd Gloucester MA 01930",
    "addr:housenumber": "6",
    "addr:postcode": "01930",
    "addr:street": "Gilbert Rd",
    "iso:country": "US",
    "sg:address": "6 Gilbert Rd",
    "sg:city": "Gloucester",
    "sg:classifiers": [
      {
        "category": "Building \u0026 Trades",
        "subcategory": "Plumbing",
        "type": "Services"
      }
    ],
    "sg:phone": "+1 978 283 8858",
    "sg:postcode": "01930",
    "sg:province": "MA",
    "sg:tags": [
      "plumbing",
      "contractor"
    ],
    "wof:name": "Mc Grath Plumbing \u0026 Heating",
    "wof:placetype": "venue"
  },
  "geometry": {"coordinates":[-70.648632,42.600156],"type":"Point"}
}
