{
  "type": "Feature",
  "properties": {
    "addr:full":"205 Newbury St Framingham MA 01701",
    "addr:housenumber":"205",
    "addr:postcode":"01701",
    "addr:street":"Newbury St",
    "iso:country":"US",
    "sg:address":"205 Newbury St",
    "sg:city":"Framingham",
    "sg:classifiers":[
        {
            "category":"Wholesale",
            "subcategory":"Drugs",
            "type":"Manufacturing & Wholesale Goods"
        }
    ],
    "sg:phone":"+1 508 620 1722",
    "sg:postcode":"01701",
    "sg:province":"MA",
    "sg:tags":[
        "pharmaceutical",
        "product"
    ],
    "wof:name":"Ariston Pharmaceutical",
    "wof:placetype":"venue"
},
  "geometry": {"coordinates":[-71.39230999999999,42.311027],"type":"Point"}
}