{
  "type": "Feature",
  "properties": {
    "iso:country":"US",
    "sg:address":"66 River Rd",
    "sg:city":"Agawam",
    "sg:classifiers":[
        {
            "category":"Professional",
            "type":"Services"
        }
    ],
    "sg:phone":"+1 413 789 4913",
    "sg:postcode":"01001",
    "sg:province":"MA",
    "sg:tags":[
        "establishment"
    ],
    "wof:name":"Inform Design",
    "wof:placetype":"venue"
},
  "geometry": {"coordinates":[-72.614414,42.047022],"type":"Point"}
}