{
  "type": "Feature",
  "properties": {
    "addr:full": "38 State Hwy 38 Lowell MA 01852",
    "addr:housenumber": "38",
    "addr:postcode": "01852",
    "addr:street": "State Hwy 38",
    "iso:country": "US",
    "sg:address": "38 State Hwy 38",
    "sg:city": "Lowell",
    "sg:classifiers": [
      {
        "category": "Real Estate",
        "subcategory": "Real Estate Agent",
        "type": "Services"
      }
    ],
    "sg:phone": "+1   ",
    "sg:postcode": "01852",
    "sg:province": "MA",
    "wof:name": "32 38 Branch Realty Trust",
    "wof:placetype": "venue"
  },
  "geometry": {"coordinates":[-71.299011,42.644073],"type":"Point"}
}
