{
  "type": "Feature",
  "properties": {
    "iso:country":"US",
    "sg:address":"88 Gordon St",
    "sg:city":"Brighton",
    "sg:classifiers":[
        {
            "category":"Professional",
            "subcategory":"Lawyer & Legal Services",
            "type":"Services"
        }
    ],
    "sg:phone":"+1 617 254 0380",
    "sg:postcode":"02135",
    "sg:province":"MA",
    "sg:tags":[
        "attorney"
    ],
    "wof:name":"Steve Reilly Attorney",
    "wof:placetype":"venue"
},
  "geometry": {"coordinates":[-71.13976700000001,42.349108],"type":"Point"}
}