{
  "type": "Feature",
  "properties": {
    "iso:country":"US",
    "sg:address":"163 Swan St",
    "sg:city":"Methuen",
    "sg:classifiers":[
        {
            "category":"Autos & Motor Vehicles",
            "subcategory":"Fuel & Gas Station",
            "type":"Retail Goods"
        }
    ],
    "sg:phone":"+1 978 687 1800",
    "sg:postcode":"01844",
    "sg:province":"MA",
    "sg:tags":[
        "oil"
    ],
    "wof:name":"Giordano's Gas & Foodmart",
    "wof:placetype":"venue"
},
  "geometry": {"coordinates":[-71.151976,42.725282],"type":"Point"}
}