{
  "type": "Feature",
  "properties": {
    "addr:full":"23 Arrow St Cambridge MA 02138",
    "addr:housenumber":"23",
    "addr:postcode":"02138",
    "addr:street":"Arrow St",
    "iso:country":"US",
    "sg:address":"23 Arrow St",
    "sg:city":"Cambridge",
    "sg:classifiers":[
        {
            "category":"Building & Trades",
            "subcategory":"Locksmith",
            "type":"Services"
        }
    ],
    "sg:phone":"+1 617 299 2080",
    "sg:postcode":"02138",
    "sg:province":"MA",
    "sg:tags":[
        "key"
    ],
    "wof:name":"24 Hour Locksmith Service",
    "wof:placetype":"venue"
},
  "geometry": {"coordinates":[-71.114386,42.371188],"type":"Point"}
}