{
  "type": "Feature",
  "properties": {
    "addr:full":"1339 Washington St Hanover MA 02339",
    "addr:housenumber":"1339",
    "addr:postcode":"02339",
    "addr:street":"Washington St",
    "iso:country":"US",
    "sg:address":"1339 Washington St",
    "sg:city":"Hanover",
    "sg:classifiers":[
        {
            "category":"Real Estate",
            "subcategory":"Real Estate Agent",
            "type":"Services"
        }
    ],
    "sg:phone":"+1 781 826 0684",
    "sg:postcode":"02339",
    "sg:province":"MA",
    "wof:name":"House Savvy Of Hanover",
    "wof:placetype":"venue"
},
  "geometry": {"coordinates":[-70.843675,42.142319],"type":"Point"}
}