{
  "type": "Feature",
  "properties": {
    "iso:country":"US",
    "sg:address":"28 Sheridan St",
    "sg:city":"Chicopee",
    "sg:classifiers":[
        {
            "category":"Shopping",
            "subcategory":"Discount & Variety Stores",
            "type":"Retail Goods"
        }
    ],
    "sg:phone":"+1   ",
    "sg:postcode":"01020",
    "sg:province":"MA",
    "wof:name":"Lichwan Variety",
    "wof:placetype":"venue"
},
  "geometry": {"coordinates":[-72.58104299999999,42.161424],"type":"Point"}
}