{
  "type": "Feature",
  "properties": {
    "addr:full":"14 Blueberry Cir Andover MA 01810",
    "addr:housenumber":"14",
    "addr:postcode":"01810",
    "addr:street":"Blueberry Cir",
    "iso:country":"US",
    "sg:address":"14 Blueberry Cir",
    "sg:city":"Andover",
    "sg:classifiers":[
        {
            "category":"Banks & Credit Unions",
            "subcategory":"Bank",
            "type":"Services"
        }
    ],
    "sg:phone":"+1 978 475 5129",
    "sg:postcode":"01810",
    "sg:province":"MA",
    "wof:name":"B.S.C. Universal Trade",
    "wof:placetype":"venue"
},
  "geometry": {"coordinates":[-71.119123,42.633103],"type":"Point"}
}