{
  "type": "Feature",
  "properties": {
    "iso:country":"US",
    "sg:address":"61 Valley Rd",
    "sg:city":"Lexington",
    "sg:classifiers":[
        {
            "category":"Building & Trades",
            "subcategory":"Construction",
            "type":"Services"
        }
    ],
    "sg:phone":"+1   ",
    "sg:postcode":"02421",
    "sg:province":"MA",
    "sg:tags":[
        "house"
    ],
    "wof:name":"Valley Contracting",
    "wof:placetype":"venue"
},
  "geometry": {"coordinates":[-71.24655199999999,42.46664],"type":"Point"}
}