{
  "type": "Feature",
  "properties": {
    "addr:full": "69 Arnold St Wrentham MA 02093",
    "addr:housenumber": "69",
    "addr:postcode": "02093",
    "addr:street": "Arnold St",
    "iso:country": "US",
    "sg:address": "69 Arnold St",
    "sg:city": "Wrentham",
    "sg:classifiers": [
      {
        "category": "Building \u0026 Trades",
        "subcategory": "Construction",
        "type": "Services"
      }
    ],
    "sg:phone": "+1 508 384 7657",
    "sg:postcode": "02093",
    "sg:province": "MA",
    "sg:tags": [
      "painter"
    ],
    "wof:name": "Class Painting",
    "wof:placetype": "venue"
  },
  "geometry": {"coordinates":[-71.395926,42.035204],"type":"Point"}
}
