{
  "type": "Feature",
  "properties": {
    "iso:country":"US",
    "sg:address":"100 Penn St",
    "sg:city":"Quincy",
    "sg:classifiers":[
        {
            "category":"Retail",
            "subcategory":"Auto Repair",
            "type":"Services"
        }
    ],
    "sg:phone":"+1 617 436 1075",
    "sg:postcode":"02169",
    "sg:province":"MA",
    "sg:tags":[
        "repairing",
        "automobile"
    ],
    "wof:name":"Unique Automotive",
    "wof:placetype":"venue"
},
  "geometry": {"coordinates":[-71.007712,42.234608],"type":"Point"}
}