{
  "type": "Feature",
  "properties": {
    "addr:full": "197 Pine St Attleboro MA 02703",
    "addr:housenumber": "197",
    "addr:postcode": "02703",
    "addr:street": "Pine St",
    "iso:country": "US",
    "sg:address": "197 Pine St",
    "sg:city": "Attleboro",
    "sg:classifiers": [
      {
        "category": "Health Services",
        "subcategory": "Health Practitioner",
        "type": "Services"
      }
    ],
    "sg:phone": "+1 508 223 2700",
    "sg:postcode": "02703",
    "sg:province": "MA",
    "sg:tags": [
      "nurse",
      "registry"
    ],
    "wof:name": "Culture Care",
    "wof:placetype": "venue"
  },
  "geometry": {"coordinates":[-71.282387,41.937076],"type":"Point"}
}
