{
  "type": "Feature",
  "properties": {
    "addr:full": "640 Auburn St Bridgewater MA 02324",
    "addr:housenumber": "640",
    "addr:postcode": "02324",
    "addr:street": "Auburn St",
    "iso:country": "US",
    "sg:address": "640 Auburn St",
    "sg:city": "Bridgewater",
    "sg:classifiers": [
      {
        "category": "Real Estate",
        "subcategory": "Real Estate Agent",
        "type": "Services"
      }
    ],
    "sg:phone": "+1 508 697 4346",
    "sg:postcode": "02324",
    "sg:province": "MA",
    "wof:name": "Lehtola Homes",
    "wof:placetype": "venue"
  },
  "geometry": {"coordinates":[-70.932341,41.973054],"type":"Point"}
}
