{
  "type": "Feature",
  "properties": {
    "iso:country":"US",
    "sg:address":"640 Auburn St",
    "sg:city":"Bridgewater",
    "sg:classifiers":[
        {
            "category":"Real Estate",
            "subcategory":"Real Estate Agent",
            "type":"Services"
        }
    ],
    "sg:phone":"+1 508 697 4346",
    "sg:postcode":"02324",
    "sg:province":"MA",
    "wof:name":"Lehtola Homes",
    "wof:placetype":"venue"
},
  "geometry": {"coordinates":[-70.93234099999999,41.973054],"type":"Point"}
}