{
  "type": "Feature",
  "properties": {
    "addr:full": "161 S Main St Middleton MA 01949",
    "addr:housenumber": "161",
    "addr:postcode": "01949",
    "addr:street": "S Main St",
    "iso:country": "US",
    "sg:address": "161 S Main St",
    "sg:city": "Middleton",
    "sg:classifiers": [
      {
        "category": "Professional",
        "subcategory": "Lawyer \u0026 Legal Services",
        "type": "Services"
      }
    ],
    "sg:phone": "+1 978 777 3588",
    "sg:postcode": "01949",
    "sg:province": "MA",
    "sg:tags": [
      "attorney"
    ],
    "wof:name": "Mark Caggiano",
    "wof:placetype": "venue"
  },
  "geometry": {"coordinates":[-71.005161,42.58281],"type":"Point"}
}
