{
  "type": "Feature",
  "properties": {
    "addr:full":"107 Laconia St Springfield MA 01129",
    "addr:housenumber":"107",
    "addr:postcode":"01129",
    "addr:street":"Laconia St",
    "iso:country":"US",
    "sg:address":"107 Laconia St",
    "sg:city":"Springfield",
    "sg:classifiers":[
        {
            "category":"Retail",
            "subcategory":"Auto Repair",
            "type":"Services"
        }
    ],
    "sg:phone":"+1 413 543 5055",
    "sg:postcode":"01129",
    "sg:province":"MA",
    "sg:tags":[
        "repairing",
        "automobile"
    ],
    "wof:name":"ESP Auto Engineering",
    "wof:placetype":"venue"
},
  "geometry": {"coordinates":[-72.48736100000001,42.146497],"type":"Point"}
}