{
  "type": "Feature",
  "properties": {
    "iso:country":"US",
    "sg:address":"460 County St",
    "sg:city":"New Bedford",
    "sg:classifiers":[
        {
            "category":"Professional",
            "subcategory":"Lawyer & Legal Services",
            "type":"Services"
        }
    ],
    "sg:phone":"+1 508 997 9393",
    "sg:postcode":"02740",
    "sg:province":"MA",
    "sg:tags":[
        "attorney"
    ],
    "wof:name":"Tynan Colleen Law Offices",
    "wof:placetype":"venue"
},
  "geometry": {"coordinates":[-70.930502,41.635179],"type":"Point"}
}