{
  "type": "Feature",
  "properties": {
    "iso:country":"US",
    "sg:address":"250 Milton St",
    "sg:city":"Dedham",
    "sg:classifiers":[
        {
            "category":"Education",
            "subcategory":"Special Training",
            "type":"Public Place"
        }
    ],
    "sg:phone":"+1 781 329 6656",
    "sg:postcode":"02026",
    "sg:province":"MA",
    "sg:tags":[
        "instruction",
        "driving"
    ],
    "wof:name":"Adaptive Driving Program Inc",
    "wof:placetype":"venue"
},
  "geometry": {"coordinates":[-71.147255,42.242119],"type":"Point"}
}