{
  "type": "Feature",
  "properties": {
    "iso:country":"US",
    "sg:address":"60 Exchange St",
    "sg:city":"Athol",
    "sg:classifiers":[
        {
            "category":"Personal",
            "subcategory":"Beauty Salon",
            "type":"Services"
        }
    ],
    "sg:phone":"+1 978 249 6591",
    "sg:postcode":"01331",
    "sg:province":"MA",
    "sg:tags":[
        "shop"
    ],
    "wof:name":"De Santis Beauty Salon",
    "wof:placetype":"venue"
},
  "geometry": {"coordinates":[-72.23128800000001,42.592969],"type":"Point"}
}