{
  "type": "Feature",
  "properties": {
    "iso:country":"US",
    "sg:address":"54 Langdon St",
    "sg:city":"Roxbury",
    "sg:classifiers":[
        {
            "category":"Building & Trades",
            "subcategory":"Construction",
            "type":"Services"
        }
    ],
    "sg:phone":"+1 617 293 0338",
    "sg:postcode":"02119",
    "sg:province":"MA",
    "sg:tags":[
        "contractor",
        "laying",
        "flooring",
        "floor"
    ],
    "wof:name":"Atwood Gleming Floors",
    "wof:placetype":"venue"
},
  "geometry": {"coordinates":[-71.070931,42.324922],"type":"Point"}
}