{
  "type": "Feature",
  "properties": {
    "addr:full": "341A Central St Saugus MA 01906",
    "addr:housenumber": "341a",
    "addr:postcode": "01906",
    "addr:street": "Central St",
    "iso:country": "US",
    "sg:address": "341A Central St",
    "sg:city": "Saugus",
    "sg:classifiers": [
      {
        "category": "Professional",
        "subcategory": "Advertising",
        "type": "Services"
      },
      {
        "category": "Professional",
        "subcategory": "Art Services",
        "type": "Services"
      },
      {
        "category": "Manufacturing",
        "subcategory": "Signs",
        "type": "Manufacturing \u0026 Wholesale Goods"
      }
    ],
    "sg:phone": "+1 781 231 2920",
    "sg:postcode": "01906",
    "sg:province": "MA",
    "sg:tags": [
      "graphic",
      "artist",
      "commercial",
      "specialty",
      "designer"
    ],
    "wof:name": "Grasso Graphics",
    "wof:placetype": "venue"
  },
  "geometry": {"coordinates":[-71.009407,42.461929],"type":"Point"}
}
