{
  "type": "Feature",
  "properties": {
    "addr:full":"25 Linnell Cir Billerica MA 01821",
    "addr:housenumber":"25",
    "addr:postcode":"01821",
    "addr:street":"Linnell Cir",
    "iso:country":"US",
    "sg:address":"25 Linnell Cir",
    "sg:city":"Billerica",
    "sg:classifiers":[
        {
            "category":"Organizations",
            "subcategory":"Professional Association",
            "type":"Services"
        }
    ],
    "sg:phone":"+1 978 663 6165",
    "sg:postcode":"01821",
    "sg:province":"MA",
    "wof:name":"National Association",
    "wof:placetype":"venue"
},
  "geometry": {"coordinates":[-71.250187,42.529432],"type":"Point"}
}