{
  "type": "Feature",
  "properties": {
    "iso:country":"US",
    "sg:address":"19 Central St",
    "sg:city":"Byfield",
    "sg:classifiers":[
        {
            "category":"Health Services",
            "subcategory":"Clinic",
            "type":"Services"
        }
    ],
    "sg:phone":"+1 978 463 0090",
    "sg:postcode":"01922",
    "sg:province":"MA",
    "sg:tags":[
        "counseling",
        "mental"
    ],
    "wof:name":"Byfield Family Therapy Associates",
    "wof:placetype":"venue"
},
  "geometry": {"coordinates":[-70.939796,42.755299],"type":"Point"}
}