{
  "type": "Feature",
  "properties": {
    "addr:full":"29 Pennybrook Rd Lynn MA 01905",
    "addr:housenumber":"29",
    "addr:postcode":"01905",
    "addr:street":"Pennybrook Rd",
    "iso:country":"US",
    "sg:address":"29 Pennybrook Rd",
    "sg:city":"Lynn",
    "sg:classifiers":[
        {
            "category":"Professional",
            "type":"Services"
        }
    ],
    "sg:phone":"+1 781 598 7114",
    "sg:postcode":"01905",
    "sg:province":"MA",
    "sg:tags":[
        "establishment"
    ],
    "wof:name":"O'Donnell M & E",
    "wof:placetype":"venue"
},
  "geometry": {"coordinates":[-70.98538499999999,42.47304],"type":"Point"}
}