{
  "type": "Feature",
  "properties": {
    "addr:full":"21 Westford Rd Ayer MA 01432",
    "addr:housenumber":"21",
    "addr:postcode":"01432",
    "addr:street":"Westford Rd",
    "iso:country":"US",
    "sg:address":"21 Westford Rd",
    "sg:city":"Ayer",
    "sg:classifiers":[
        {
            "category":"Transit Center",
            "subcategory":"Freight",
            "type":"Transportation"
        }
    ],
    "sg:phone":"+1 978 772 3113",
    "sg:postcode":"01432",
    "sg:province":"MA",
    "sg:tags":[
        "trucking-heavy",
        "hauling"
    ],
    "wof:name":"M W Leahy Co Inc",
    "wof:placetype":"venue"
},
  "geometry": {"coordinates":[-71.53716300000001,42.562481],"type":"Point"}
}