{
  "type": "Feature",
  "properties": {
    "iso:country":"US",
    "sg:address":"446 Boston Road",
    "sg:city":"Billerica",
    "sg:classifiers":[
        {
            "category":"Restaurant",
            "type":"Food & Drink"
        }
    ],
    "sg:phone":"+1 978 663 7353",
    "sg:postcode":"01821",
    "sg:province":"MA",
    "sg:tags":[
        "italian"
    ],
    "sg:website":"www.divitobrotherspizzeria.com",
    "wof:name":"DiVito Brothers Italian Specialities",
    "wof:placetype":"venue"
},
  "geometry": {"coordinates":[-71.2664,42.5589],"type":"Point"}
}