{
  "type": "Feature",
  "properties": {
    "addr:full": "446 Boston Road Billerica MA 01821",
    "addr:housenumber": "446",
    "addr:postcode": "01821",
    "addr:street": "Boston Road",
    "iso:country": "US",
    "sg:address": "446 Boston Road",
    "sg:city": "Billerica",
    "sg:classifiers": [
      {
        "category": "Restaurant",
        "type": "Food \u0026 Drink"
      }
    ],
    "sg:phone": "+1 978 663 7353",
    "sg:postcode": "01821",
    "sg:province": "MA",
    "sg:tags": [
      "italian"
    ],
    "sg:website": "www.divitobrotherspizzeria.com",
    "wof:name": "DiVito Brothers Italian Specialities",
    "wof:placetype": "venue"
  },
  "geometry": {"coordinates":[-71.2664,42.5589],"type":"Point"}
}
