{
  "type": "Feature",
  "properties": {
    "addr:full":"740 Chief Justice Cushing Hwy Scituate MA 02066",
    "addr:housenumber":"740",
    "addr:postcode":"02066",
    "addr:street":"Chief Justice Cushing Hwy",
    "iso:country":"US",
    "sg:address":"740 Chief Justice Cushing Hwy",
    "sg:city":"Scituate",
    "sg:classifiers":[
        {
            "category":"Recreation",
            "type":"Entertainment"
        }
    ],
    "sg:phone":"+1 781 545 1777",
    "sg:postcode":"02066",
    "sg:province":"MA",
    "sg:tags":[
        "safety",
        "instruction",
        "marksmanship",
        "gun"
    ],
    "wof:name":"Fox Distributers",
    "wof:placetype":"venue"
},
  "geometry": {"coordinates":[-70.77748099999999,42.204996],"type":"Point"}
}