{
  "type": "Feature",
  "properties": {
    "addr:full":"313 Plymouth St Halifax MA 02338",
    "addr:housenumber":"313",
    "addr:postcode":"02338",
    "addr:street":"Plymouth St",
    "iso:country":"US",
    "sg:address":"313 Plymouth St",
    "sg:city":"Halifax",
    "sg:classifiers":[
        {
            "category":"Social Services",
            "type":"Services"
        }
    ],
    "sg:phone":"+1 781 293 2328",
    "sg:postcode":"02338",
    "sg:province":"MA",
    "wof:name":"Journey Inward Counseling Inc",
    "wof:placetype":"venue"
},
  "geometry": {"coordinates":[-70.84657,41.99399],"type":"Point"}
}