{
  "type": "Feature",
  "properties": {
    "iso:country":"US",
    "sg:address":"566 Massachusetts Ave",
    "sg:city":"Acton",
    "sg:classifiers":[
        {
            "category":"Real Estate",
            "subcategory":"Real Estate Agent",
            "type":"Services"
        }
    ],
    "sg:phone":"+1 978 263 8887",
    "sg:postcode":"01720",
    "sg:province":"MA",
    "sg:website":"www.morrison-realestate.com",
    "wof:name":"Morrison Real Estate",
    "wof:placetype":"venue"
},
  "geometry": {"coordinates":[-71.473534,42.476115],"type":"Point"}
}