{
  "type": "Feature",
  "properties": {
    "iso:country":"US",
    "sg:address":"98 Main St",
    "sg:city":"Peabody",
    "sg:classifiers":[
        {
            "category":"Social Services",
            "type":"Services"
        }
    ],
    "sg:phone":"+1 978 531 0767",
    "sg:postcode":"01960",
    "sg:province":"MA",
    "sg:tags":[
        "organization",
        "welfare"
    ],
    "wof:name":"North Shore Community Action",
    "wof:placetype":"venue"
},
  "geometry": {"coordinates":[-70.92346000000001,42.52438],"type":"Point"}
}