{
  "type": "Feature",
  "properties": {
    "addr:full": "98 Main St Peabody MA 01960",
    "addr:housenumber": "98",
    "addr:postcode": "01960",
    "addr:street": "Main St",
    "iso:country": "US",
    "sg:address": "98 Main St",
    "sg:city": "Peabody",
    "sg:classifiers": [
      {
        "category": "Social Services",
        "type": "Services"
      }
    ],
    "sg:phone": "+1 978 531 0767",
    "sg:postcode": "01960",
    "sg:province": "MA",
    "sg:tags": [
      "organization",
      "welfare"
    ],
    "wof:name": "North Shore Community Action",
    "wof:placetype": "venue"
  },
  "geometry": {"coordinates":[-70.92346,42.52438],"type":"Point"}
}
