{
  "type": "Feature",
  "properties": {
    "iso:country":"US",
    "sg:address":"40 Macarthur Blvd",
    "sg:city":"Buzzards Bay",
    "sg:classifiers":[
        {
            "category":"Retail",
            "subcategory":"Funeral Services",
            "type":"Services"
        }
    ],
    "sg:phone":"+1 508 759 3511",
    "sg:postcode":"02532",
    "sg:province":"MA",
    "sg:tags":[
        "director"
    ],
    "wof:name":"Nickerson-Bourne Funeral Home",
    "wof:placetype":"venue"
},
  "geometry": {"coordinates":[-70.536328,41.800667],"type":"Point"}
}