{
  "type": "Feature",
  "properties": {
    "iso:country":"US",
    "sg:address":"15 Victory Rd",
    "sg:city":"Dorchester",
    "sg:classifiers":[
        {
            "category":"Real Estate",
            "subcategory":"Real Estate Agent",
            "type":"Services"
        }
    ],
    "sg:phone":"+1 617 287 0822",
    "sg:postcode":"02122",
    "sg:province":"MA",
    "sg:tags":[
        "management"
    ],
    "wof:name":"Mibo Investments",
    "wof:placetype":"venue"
},
  "geometry": {"coordinates":[-71.05443699999999,42.295922],"type":"Point"}
}