{
  "type": "Feature",
  "properties": {
    "addr:full": "15 Victory Rd Dorchester MA 02122",
    "addr:housenumber": "15",
    "addr:postcode": "02122",
    "addr:street": "Victory Rd",
    "iso:country": "US",
    "sg:address": "15 Victory Rd",
    "sg:city": "Dorchester",
    "sg:classifiers": [
      {
        "category": "Real Estate",
        "subcategory": "Real Estate Agent",
        "type": "Services"
      }
    ],
    "sg:phone": "+1 617 287 0822",
    "sg:postcode": "02122",
    "sg:province": "MA",
    "sg:tags": [
      "management"
    ],
    "wof:name": "Mibo Investments",
    "wof:placetype": "venue"
  },
  "geometry": {"coordinates":[-71.054437,42.295922],"type":"Point"}
}
