{
  "type": "Feature",
  "properties": {
    "addr:full":"56 Prospect St Wendell MA 01301",
    "addr:housenumber":"56",
    "addr:postcode":"01301",
    "addr:street":"Prospect St",
    "iso:country":"US",
    "sg:address":"56 Prospect St",
    "sg:city":"Wendell",
    "sg:classifiers":[
        {
            "category":"Personal",
            "subcategory":"Tattoo Parlor",
            "type":"Services"
        }
    ],
    "sg:phone":"+1 978 297 5109",
    "sg:postcode":"01301",
    "sg:province":"MA",
    "sg:tags":[
        "tattooing"
    ],
    "wof:name":"Dying Needle Tattoo Parlor",
    "wof:placetype":"venue"
},
  "geometry": {"coordinates":[-72.595029,42.584694],"type":"Point"}
}