{
  "type": "Feature",
  "properties": {
    "addr:full": "382 Commonwealth Ave Boston MA 02215",
    "addr:housenumber": "382",
    "addr:postcode": "02215",
    "addr:street": "Commonwealth Ave",
    "iso:country": "US",
    "sg:address": "382 Commonwealth Ave",
    "sg:city": "Boston",
    "sg:classifiers": [
      {
        "category": "Professional",
        "subcategory": "Art Services",
        "type": "Services"
      },
      {
        "category": "Professional",
        "subcategory": "Computer Services",
        "type": "Services"
      }
    ],
    "sg:phone": "+1 508 783 3214",
    "sg:postcode": "02215",
    "sg:province": "MA",
    "sg:tags": [
      "consultant",
      "graphic",
      "system",
      "designer"
    ],
    "wof:name": "Ilipsis Design",
    "wof:placetype": "venue"
  },
  "geometry": {"coordinates":[-71.089382,42.348875],"type":"Point"}
}
