{
  "type": "Feature",
  "properties": {
    "iso:country":"US",
    "sg:address":"441 N Main St",
    "sg:city":"Fall River",
    "sg:classifiers":[
        {
            "category":"Building & Trades",
            "subcategory":"Construction",
            "type":"Services"
        }
    ],
    "sg:phone":"+1   ",
    "sg:postcode":"02720",
    "sg:province":"MA",
    "sg:tags":[
        "house"
    ],
    "wof:name":"Webster Construction",
    "wof:placetype":"venue"
},
  "geometry": {"coordinates":[-71.15452399999999,41.707701],"type":"Point"}
}