{
  "type": "Feature",
  "properties": {
    "addr:full":"7 Morse Ct Manchester MA 01944",
    "addr:housenumber":"7",
    "addr:postcode":"01944",
    "addr:street":"Morse Ct",
    "iso:country":"US",
    "sg:address":"7 Morse Ct",
    "sg:city":"Manchester",
    "sg:classifiers":[
        {
            "category":"Building & Trades",
            "subcategory":"Construction",
            "type":"Services"
        }
    ],
    "sg:phone":"+1 978 526 4706",
    "sg:postcode":"01944",
    "sg:province":"MA",
    "sg:tags":[
        "woodworker"
    ],
    "wof:name":"Manchester Woodworking",
    "wof:placetype":"venue"
},
  "geometry": {"coordinates":[-70.774535,42.575774],"type":"Point"}
}