{
  "type": "Feature",
  "properties": {
    "addr:full": "84 Grape St New Bedford MA 02740",
    "addr:housenumber": "84",
    "addr:postcode": "02740",
    "addr:street": "Grape St",
    "iso:country": "US",
    "sg:address": "84 Grape St",
    "sg:city": "New Bedford",
    "sg:classifiers": [
      {
        "category": "Health Services",
        "subcategory": "Doctor",
        "type": "Services"
      }
    ],
    "sg:phone": "+1 508 992 1051",
    "sg:postcode": "02740",
    "sg:province": "MA",
    "sg:tags": [
      "physician",
      "surgeon"
    ],
    "wof:name": "Coastal Orthopaedics",
    "wof:placetype": "venue"
  },
  "geometry": {"coordinates":[-70.938462,41.624288],"type":"Point"}
}
