{
  "type": "Feature",
  "properties": {
    "iso:country":"US",
    "sg:address":"84 Grape St",
    "sg:city":"New Bedford",
    "sg:classifiers":[
        {
            "category":"Health Services",
            "subcategory":"Doctor",
            "type":"Services"
        }
    ],
    "sg:phone":"+1 508 992 1051",
    "sg:postcode":"02740",
    "sg:province":"MA",
    "sg:tags":[
        "physician",
        "surgeon"
    ],
    "wof:name":"Coastal Orthopaedics",
    "wof:placetype":"venue"
},
  "geometry": {"coordinates":[-70.938462,41.624288],"type":"Point"}
}