{
  "type": "Feature",
  "properties": {
    "iso:country":"US",
    "sg:address":"14 Pleasant St",
    "sg:city":"Gloucester",
    "sg:classifiers":[
        {
            "category":"Banks & Credit Unions",
            "subcategory":"Bank",
            "type":"Services"
        }
    ],
    "sg:phone":"+1   ",
    "sg:postcode":"01930",
    "sg:province":"MA",
    "sg:tags":[
        "mortgage"
    ],
    "wof:name":"1st New England Mortgage Corp",
    "wof:placetype":"venue"
},
  "geometry": {"coordinates":[-70.661855,42.612963],"type":"Point"}
}