{
  "type": "Feature",
  "properties": {
    "addr:full": "19 Spruce Tree Ln Norton MA 02766",
    "addr:housenumber": "19",
    "addr:postcode": "02766",
    "addr:street": "Spruce Tree Ln",
    "iso:country": "US",
    "sg:address": "19 Spruce Tree Ln",
    "sg:city": "Norton",
    "sg:classifiers": [
      {
        "category": "Food \u0026 Beverages",
        "subcategory": "Bakery",
        "type": "Retail Goods"
      }
    ],
    "sg:phone": "+1 508 406 0117",
    "sg:postcode": "02766",
    "sg:province": "MA",
    "sg:tags": [
      "cooky",
      "cracker"
    ],
    "wof:name": "Cookie Bouquets By Kim",
    "wof:placetype": "venue"
  },
  "geometry": {"coordinates":[-71.250274,41.972606],"type":"Point"}
}
