{
  "type": "Feature",
  "properties": {
    "iso:country":"US",
    "sg:address":"19 Spruce Tree Ln",
    "sg:city":"Norton",
    "sg:classifiers":[
        {
            "category":"Food & Beverages",
            "subcategory":"Bakery",
            "type":"Retail Goods"
        }
    ],
    "sg:phone":"+1 508 406 0117",
    "sg:postcode":"02766",
    "sg:province":"MA",
    "sg:tags":[
        "cooky",
        "cracker"
    ],
    "wof:name":"Cookie Bouquets By Kim",
    "wof:placetype":"venue"
},
  "geometry": {"coordinates":[-71.250274,41.972606],"type":"Point"}
}