{
  "type": "Feature",
  "properties": {
    "addr:full": "464 Quincy Ave Braintree MA 02184",
    "addr:housenumber": "464",
    "addr:postcode": "02184",
    "addr:street": "Quincy Ave",
    "iso:country": "US",
    "ovtr:label": "Castle Self Storage, 464 Quincy Ave Braintree MA US",
    "ovtr:similarity": 2.1427159309387207,
    "sg:address": "464 Quincy Ave",
    "sg:city": "Braintree",
    "sg:classifiers": [
      {
        "category": "Retail",
        "subcategory": "Storage",
        "type": "Services"
      }
    ],
    "sg:phone": "+1 781 318 3690",
    "sg:postcode": "02184",
    "sg:province": "MA",
    "sg:tags": [
      "automobile",
      "self",
      "commercial",
      "household"
    ],
    "sg:website": "http://www.storagefront.com",
    "wof:name": "Castle Self Storage",
    "wof:placetype": "venue"
  },
  "geometry": {"coordinates":[-70.978025,42.234726],"type":"Point"}
}
