{
  "type": "Feature",
  "properties": {
    "iso:country":"US",
    "sg:address":"464 Quincy Ave",
    "sg:city":"Braintree",
    "sg:classifiers":[
        {
            "category":"Retail",
            "subcategory":"Storage",
            "type":"Services"
        }
    ],
    "sg:phone":"+1 781 318 3690",
    "sg:postcode":"02184",
    "sg:province":"MA",
    "sg:tags":[
        "automobile",
        "self",
        "commercial",
        "household"
    ],
    "sg:website":"http://www.storagefront.com",
    "wof:name":"Castle Self Storage",
    "wof:placetype":"venue"
},
  "geometry": {"coordinates":[-70.978025,42.234726],"type":"Point"}
}