{
  "type": "Feature",
  "properties": {
    "addr:full":"33 Grove St South Yarmouth MA 02664",
    "addr:housenumber":"33",
    "addr:postcode":"02664",
    "addr:street":"Grove St",
    "iso:country":"US",
    "sg:address":"33 Grove St",
    "sg:city":"South Yarmouth",
    "sg:classifiers":[
        {
            "category":"Real Estate",
            "subcategory":"Real Estate Agent",
            "type":"Services"
        }
    ],
    "sg:phone":"+1   ",
    "sg:postcode":"02664",
    "sg:province":"MA",
    "wof:name":"Cape Winds Realty Corp",
    "wof:placetype":"venue"
},
  "geometry": {"coordinates":[-70.205403,41.653546],"type":"Point"}
}