{
  "type": "Feature",
  "properties": {
    "addr:full": "15 Birch Grove Hts Gloucester MA 01930",
    "addr:housenumber": "15",
    "addr:postcode": "01930",
    "addr:street": "Birch Grove",
    "iso:country": "US",
    "sg:address": "15 Birch Grove Hts",
    "sg:city": "Gloucester",
    "sg:classifiers": [
      {
        "category": "Building \u0026 Trades",
        "subcategory": "Construction",
        "type": "Services"
      }
    ],
    "sg:phone": "+1 978 283 1122",
    "sg:postcode": "01930",
    "sg:province": "MA",
    "sg:tags": [
      "general",
      "contractor"
    ],
    "wof:name": "Michael J Horgan",
    "wof:placetype": "venue"
  },
  "geometry": {"coordinates":[-70.690046,42.611236],"type":"Point"}
}
