{
  "type": "Feature",
  "properties": {
    "addr:full": "55 Otis St Medford MA 02155",
    "addr:housenumber": "55",
    "addr:postcode": "02155",
    "addr:street": "Otis St",
    "iso:country": "US",
    "ovtr:label": "First Community United Methodist Church of Medford, 55 Otis St Medford MA US",
    "ovtr:similarity": 3.2198750972747803,
    "sg:address": "55 Otis St",
    "sg:city": "Medford",
    "sg:classifiers": [
      {
        "category": "Place Of Worship",
        "subcategory": "Church",
        "type": "Public Place"
      },
      {
        "category": "Place Of Worship",
        "type": "Public Place"
      }
    ],
    "sg:phone": "+1 781 396 5436",
    "sg:postcode": "02155",
    "sg:province": "MA",
    "sg:tags": [
      "churches-methodist"
    ],
    "wof:name": "First Community United Methodist Church",
    "wof:placetype": "venue"
  },
  "geometry": {"coordinates":[-71.096573,42.418322],"type":"Point"}
}
