{
  "type": "Feature",
  "properties": {
    "iso:country":"US",
    "sg:address":"55 Otis St",
    "sg:city":"Medford",
    "sg:classifiers":[
        {
            "category":"Place Of Worship",
            "subcategory":"Church",
            "type":"Public Place"
        },
        {
            "category":"Place Of Worship",
            "type":"Public Place"
        }
    ],
    "sg:phone":"+1 781 396 5436",
    "sg:postcode":"02155",
    "sg:province":"MA",
    "sg:tags":[
        "churches-methodist"
    ],
    "wof:name":"First Community United Methodist Church",
    "wof:placetype":"venue"
},
  "geometry": {"coordinates":[-71.09657300000001,42.418322],"type":"Point"}
}