{
  "type": "Feature",
  "properties": {
    "addr:full": "26 West St Boston MA 02111",
    "addr:housenumber": "26",
    "addr:postcode": "02111",
    "addr:street": "West St",
    "iso:country": "US",
    "sg:address": "26 West St",
    "sg:city": "Boston",
    "sg:classifiers": [
      {
        "category": "Banks \u0026 Credit Unions",
        "subcategory": "Bank",
        "type": "Services"
      },
      {
        "category": "Shopping",
        "subcategory": "Used Merchandise",
        "type": "Retail Goods"
      }
    ],
    "sg:phone": "+1 617 695 0512",
    "sg:postcode": "02111",
    "sg:province": "MA",
    "sg:tags": [
      "shop",
      "second",
      "resale",
      "hand"
    ],
    "sg:website": "http://www.campneosa.com",
    "wof:name": "Salvation Army Fmly Thrift Str",
    "wof:placetype": "venue"
  },
  "geometry": {"coordinates":[-71.062448,42.354709],"type":"Point"}
}
