{
  "type": "Feature",
  "properties": {
    "addr:full":"39 Federal St Belchertown MA 01007",
    "addr:housenumber":"39",
    "addr:postcode":"01007",
    "addr:street":"Federal St",
    "iso:country":"US",
    "sg:address":"39 Federal St",
    "sg:city":"Belchertown",
    "sg:classifiers":[
        {
            "category":"Building & Trades",
            "subcategory":"Construction",
            "type":"Services"
        }
    ],
    "sg:phone":"+1 413 323 5634",
    "sg:postcode":"01007",
    "sg:province":"MA",
    "sg:tags":[
        "home",
        "builder"
    ],
    "wof:name":"Deer Hill Builders Inc",
    "wof:placetype":"venue"
},
  "geometry": {"coordinates":[-72.40883100000001,42.291028],"type":"Point"}
}