{
  "type": "Feature",
  "properties": {
    "iso:country":"US",
    "sg:address":"1205 Park St",
    "sg:city":"Attleboro",
    "sg:classifiers":[
        {
            "category":"Local Transit",
            "type":"Transportation"
        }
    ],
    "sg:phone":"+1 508 223 3133",
    "sg:postcode":"02703",
    "sg:province":"MA",
    "sg:tags":[
        "limousine"
    ],
    "wof:name":"Cricket Car Svc",
    "wof:placetype":"venue"
},
  "geometry": {"coordinates":[-71.25899099999999,41.922138],"type":"Point"}
}