{
  "type": "Feature",
  "properties": {
    "addr:full": "3 Center Plz Suite 430 Boston MA 02108",
    "addr:housenumber": "3",
    "addr:postcode": "02108",
    "addr:street": "Center Plz Suite 430",
    "iso:country": "US",
    "sg:address": "3 Center Plz Suite 430",
    "sg:city": "Boston",
    "sg:classifiers": [
      {
        "category": "Organizations",
        "subcategory": "Community Association",
        "type": "Services"
      }
    ],
    "sg:phone": "+1 617 227 7500",
    "sg:postcode": "02108",
    "sg:province": "MA",
    "wof:name": "Schneider Reilly LLP",
    "wof:placetype": "venue"
  },
  "geometry": {"coordinates":[-71.060934,42.359961],"type":"Point"}
}
