{
  "type": "Feature",
  "properties": {
    "iso:country":"US",
    "sg:address":"516 Lancaster Ave",
    "sg:city":"Lunenburg",
    "sg:classifiers":[
        {
            "category":"Professional",
            "subcategory":"Research",
            "type":"Services"
        }
    ],
    "sg:phone":"+1   ",
    "sg:postcode":"01462",
    "sg:province":"MA",
    "sg:tags":[
        "commercial",
        "physical"
    ],
    "wof:name":"Taylor Anderson",
    "wof:placetype":"venue"
},
  "geometry": {"coordinates":[-71.712783,42.575413],"type":"Point"}
}