{
  "type": "Feature",
  "properties": {
    "iso:country":"US",
    "sg:address":"464 Breckwood Blvd",
    "sg:city":"Springfield",
    "sg:classifiers":[
        {
            "category":"Bakery",
            "type":"Food & Drink"
        },
        {
            "category":"Coffee & Tea",
            "type":"Food & Drink"
        },
        {
            "category":"Bagels",
            "type":"Food & Drink"
        },
        {
            "category":"Donuts",
            "type":"Food & Drink"
        }
    ],
    "sg:menulink":"http://www.allmenus.com/ma/springfield/143412-dunkin-donuts/menu/",
    "sg:phone":"+1 413 783 2741",
    "sg:postcode":"01109",
    "sg:province":"MA",
    "sg:tags":[
        "american",
        "diner",
        "pastry"
    ],
    "wof:name":"Dunkin' Donuts",
    "wof:placetype":"venue"
},
  "geometry": {"coordinates":[-72.5243,42.117387],"type":"Point"}
}