{
  "type": "Feature",
  "properties": {
    "addr:full": "17 Cornell Rd Danvers MA 01923",
    "addr:housenumber": "17",
    "addr:postcode": "01923",
    "addr:street": "Cornell Rd",
    "iso:country": "US",
    "sg:address": "17 Cornell Rd",
    "sg:city": "Danvers",
    "sg:classifiers": [
      {
        "category": "Professional",
        "subcategory": "Management \u0026 Consulting",
        "type": "Services"
      }
    ],
    "sg:phone": "+1 978 774 1292",
    "sg:postcode": "01923",
    "sg:province": "MA",
    "sg:tags": [
      "consultant"
    ],
    "wof:name": "Materials Concepts",
    "wof:placetype": "venue"
  },
  "geometry": {"coordinates":[-70.921651,42.576641],"type":"Point"}
}
