{
  "type": "Feature",
  "properties": {
    "iso:country":"US",
    "sg:address":"14 Eliot St",
    "sg:city":"Cambridge",
    "sg:classifiers":[
        {
            "category":"Building & Trades",
            "subcategory":"Locksmith",
            "type":"Services"
        }
    ],
    "sg:phone":"+1 617 914 0088",
    "sg:postcode":"02138",
    "sg:province":"MA",
    "sg:tags":[
        "key"
    ],
    "wof:name":"Locksmith Service On Eliot All Emergencys",
    "wof:placetype":"venue"
},
  "geometry": {"coordinates":[-71.121617,42.372241],"type":"Point"}
}