{
  "type": "Feature",
  "properties": {
    "addr:full": "645 Washington St Stoughton MA 02072",
    "addr:housenumber": "645",
    "addr:postcode": "02072",
    "addr:street": "Washington St",
    "iso:country": "US",
    "sg:address": "645 Washington St",
    "sg:city": "Stoughton",
    "sg:classifiers": [
      {
        "category": "Food \u0026 Beverages",
        "subcategory": "Groceries \u0026 Convenience Stores",
        "type": "Retail Goods"
      }
    ],
    "sg:phone": "+1 781 297 0019",
    "sg:postcode": "02072",
    "sg:province": "MA",
    "wof:name": "Hawies Market Plus Valero",
    "wof:placetype": "venue"
  },
  "geometry": {"coordinates":[-71.102064,42.12879],"type":"Point"}
}
