{
  "type": "Feature",
  "properties": {
    "iso:country":"US",
    "sg:address":"645 Washington St",
    "sg:city":"Stoughton",
    "sg:classifiers":[
        {
            "category":"Food & Beverages",
            "subcategory":"Groceries & Convenience Stores",
            "type":"Retail Goods"
        }
    ],
    "sg:phone":"+1 781 297 0019",
    "sg:postcode":"02072",
    "sg:province":"MA",
    "wof:name":"Hawies Market Plus Valero",
    "wof:placetype":"venue"
},
  "geometry": {"coordinates":[-71.102064,42.12879],"type":"Point"}
}