{
  "type": "Feature",
  "properties": {
    "addr:full":"12 Federal St Newburyport MA 01950",
    "addr:housenumber":"12",
    "addr:postcode":"01950",
    "addr:street":"Federal St",
    "iso:country":"US",
    "sg:address":"12 Federal St",
    "sg:city":"Newburyport",
    "sg:classifiers":[
        {
            "category":"Shopping",
            "subcategory":"Bicycles & Sporting Goods",
            "type":"Retail Goods"
        },
        {
            "category":"Sports & Exercise",
            "subcategory":"Bicycle Rental",
            "type":"Entertainment"
        },
        {
            "category":"Parking",
            "subcategory":"Bicycle",
            "type":"Transportation"
        }
    ],
    "sg:phone":"+1 978 465 5566",
    "sg:postcode":"01950",
    "sg:province":"MA",
    "sg:tags":[
        "shop",
        "security",
        "system",
        "bicycles-renting",
        "rack"
    ],
    "sg:website":"http://www.riversidecycle.com",
    "wof:name":"Riverside Cycle",
    "wof:placetype":"venue"
},
  "geometry": {"coordinates":[-70.865262,42.809985],"type":"Point"}
}