{
  "type": "Feature",
  "properties": {
    "addr:full": "322 E Center St West Bridgewater MA 02379",
    "addr:housenumber": "322",
    "addr:postcode": "02379",
    "addr:street": "E Center St",
    "iso:country": "US",
    "sg:address": "322 E Center St",
    "sg:city": "West Bridgewater",
    "sg:classifiers": [
      {
        "category": "Health Services",
        "subcategory": "Doctor",
        "type": "Services"
      }
    ],
    "sg:phone": "+1 508 894 0400",
    "sg:postcode": "02379",
    "sg:province": "MA",
    "sg:tags": [
      "physician",
      "surgeon"
    ],
    "wof:name": "Bridgewater-Goddard Park Med",
    "wof:placetype": "venue"
  },
  "geometry": {"coordinates":[-70.989515,42.020216],"type":"Point"}
}
