{
  "type": "Feature",
  "properties": {
    "addr:full":"332 Newbury St Boston MA 02115",
    "addr:housenumber":"332",
    "addr:postcode":"02115",
    "addr:street":"Newbury St",
    "iso:country":"US",
    "sg:address":"332 Newbury St",
    "sg:city":"Boston",
    "sg:classifiers":[
        {
            "category":"Shopping",
            "subcategory":"Music",
            "type":"Retail Goods"
        }
    ],
    "sg:phone":"+1 617 236 4930",
    "sg:postcode":"02115",
    "sg:province":"MA",
    "sg:tags":[
        "compact",
        "record",
        "disc",
        "tape",
        "dvd's"
    ],
    "sg:website":"www.newbury.com",
    "wof:name":"Newbury Comics",
    "wof:placetype":"venue"
},
  "geometry": {"coordinates":[-71.086443,42.348519],"type":"Point"}
}