{
  "type": "Feature",
  "properties": {
    "addr:full":"27 Mount Auburn St Cambridge MA 02138",
    "addr:housenumber":"27",
    "addr:postcode":"02138",
    "addr:street":"Mount Auburn St",
    "iso:country":"US",
    "sg:address":"27 Mount Auburn St",
    "sg:city":"Cambridge",
    "sg:classifiers":[
        {
            "category":"Personal",
            "subcategory":"Beauty Salon",
            "type":"Services"
        }
    ],
    "sg:phone":"+1 617 868 7943",
    "sg:postcode":"02138",
    "sg:province":"MA",
    "wof:name":"Quetele's Place Of Beauty",
    "wof:placetype":"venue"
},
  "geometry": {"coordinates":[-71.1161,42.371085],"type":"Point"}
}