{
  "type": "Feature",
  "properties": {
    "addr:full":"816 Brayton Point Rd Somerset MA 02725",
    "addr:housenumber":"816",
    "addr:postcode":"02725",
    "addr:street":"Brayton Point Rd",
    "iso:country":"US",
    "sg:address":"816 Brayton Point Rd",
    "sg:city":"Somerset",
    "sg:classifiers":[
        {
            "category":"Education",
            "subcategory":"School",
            "type":"Public Place"
        }
    ],
    "sg:phone":"+1 508 324 3190",
    "sg:postcode":"02725",
    "sg:province":"MA",
    "sg:tags":[
        "elementary"
    ],
    "sg:website":"http://www.somerset.k12.ma.us/wilbur/",
    "wof:name":"Wilbur Elementary School",
    "wof:placetype":"venue"
},
  "geometry": {"coordinates":[-71.179411,41.722973],"type":"Point"}
}