{
  "type": "Feature",
  "properties": {
    "iso:country":"US",
    "sg:address":"57 Flint Locke Ln",
    "sg:city":"Medfield",
    "sg:classifiers":[
        {
            "category":"Personal",
            "type":"Services"
        }
    ],
    "sg:phone":"+1   ",
    "sg:postcode":"02052",
    "sg:province":"MA",
    "wof:name":"Jonathan Brill and Family",
    "wof:placetype":"venue"
},
  "geometry": {"coordinates":[-71.29764,42.20183],"type":"Point"}
}