{
  "type": "Feature",
  "properties": {
    "iso:country":"US",
    "sg:address":"80 Maple St",
    "sg:city":"Stoneham",
    "sg:classifiers":[
        {
            "category":"Insurance",
            "subcategory":"Hazard Insurance",
            "type":"Services"
        }
    ],
    "sg:phone":"+1 781 279 4343",
    "sg:postcode":"02180",
    "sg:province":"MA",
    "sg:tags":[
        "commercial",
        "business"
    ],
    "wof:name":"Donald J Bowers Insurance Agency",
    "wof:placetype":"venue"
},
  "geometry": {"coordinates":[-71.108976,42.478828],"type":"Point"}
}