{
  "type": "Feature",
  "properties": {
    "addr:full":"140 Pinehurst Rd Marshfield MA 02050",
    "addr:housenumber":"140",
    "addr:postcode":"02050",
    "addr:street":"Pinehurst Rd",
    "iso:country":"US",
    "sg:address":"140 Pinehurst Rd",
    "sg:city":"Marshfield",
    "sg:classifiers":[
        {
            "category":"Social Services",
            "type":"Services"
        }
    ],
    "sg:phone":"+1 781 834 5957",
    "sg:postcode":"02050",
    "sg:province":"MA",
    "sg:tags":[
        "counselor",
        "marriage",
        "family"
    ],
    "wof:name":"Allan T Griffin",
    "wof:placetype":"venue"
},
  "geometry": {"coordinates":[-70.715744,42.132423],"type":"Point"}
}