{
  "type": "Feature",
  "properties": {
    "iso:country":"US",
    "sg:address":"128 W Main St",
    "sg:city":"West Brookfield",
    "sg:classifiers":[
        {
            "category":"Banks & Credit Unions",
            "subcategory":"Bank",
            "type":"Services"
        }
    ],
    "sg:phone":"+1 508 867 5821",
    "sg:postcode":"01585",
    "sg:province":"MA",
    "wof:name":"North Brookfield Savings Bank",
    "wof:placetype":"venue"
},
  "geometry": {"coordinates":[-72.15693400000001,42.234013],"type":"Point"}
}