{
  "type": "Feature",
  "properties": {
    "addr:full": "128 W Main St West Brookfield MA 01585",
    "addr:housenumber": "128",
    "addr:postcode": "01585",
    "addr:street": "W Main St West",
    "iso:country": "US",
    "ovtr:label": "North Brookfield Savings Bank, 128 W Main St West Brookfield MA US",
    "ovtr:similarity": 3.893704891204834,
    "sg:address": "128 W Main St",
    "sg:city": "West Brookfield",
    "sg:classifiers": [
      {
        "category": "Banks \u0026 Credit Unions",
        "subcategory": "Bank",
        "type": "Services"
      }
    ],
    "sg:phone": "+1 508 867 5821",
    "sg:postcode": "01585",
    "sg:province": "MA",
    "wof:name": "North Brookfield Savings Bank",
    "wof:placetype": "venue"
  },
  "geometry": {"coordinates":[-72.156934,42.234013],"type":"Point"}
}
