{
  "type": "Feature",
  "properties": {
    "addr:full": "31 Forest St Worcester MA 01609",
    "addr:housenumber": "31",
    "addr:postcode": "01609",
    "addr:street": "Forest St",
    "iso:country": "US",
    "sg:address": "31 Forest St",
    "sg:city": "Worcester",
    "sg:classifiers": [
      {
        "category": "Social Services",
        "type": "Services"
      }
    ],
    "sg:phone": "+1 508 792 0441",
    "sg:postcode": "01609",
    "sg:province": "MA",
    "sg:tags": [
      "worker"
    ],
    "wof:name": "Rose Yapchian-Fourn",
    "wof:placetype": "venue"
  },
  "geometry": {"coordinates":[-71.815211,42.283694],"type":"Point"}
}
