{
  "type": "Feature",
  "properties": {
    "addr:full":"321 Hartford Ave Bellingham MA 02019",
    "addr:housenumber":"321",
    "addr:postcode":"02019",
    "addr:street":"Hartford Ave",
    "iso:country":"US",
    "sg:address":"321 Hartford Ave",
    "sg:city":"Bellingham",
    "sg:classifiers":[
        {
            "category":"Building & Trades",
            "subcategory":"Construction",
            "type":"Services"
        }
    ],
    "sg:phone":"+1 508 966 2573",
    "sg:postcode":"02019",
    "sg:province":"MA",
    "sg:tags":[
        "roofing",
        "contractor"
    ],
    "wof:name":"All American Roofing",
    "wof:placetype":"venue"
},
  "geometry": {"coordinates":[-71.460448,42.115407],"type":"Point"}
}