{
  "type": "Feature",
  "properties": {
    "addr:full": "42 Charles Dr Franklin MA 02038",
    "addr:housenumber": "42",
    "addr:postcode": "02038",
    "addr:street": "Charles Dr",
    "iso:country": "US",
    "sg:address": "42 Charles Dr",
    "sg:city": "Franklin",
    "sg:classifiers": [
      {
        "category": "Retail",
        "subcategory": "Laundry \u0026 Dry Cleaning",
        "type": "Services"
      }
    ],
    "sg:phone": "+1 508 520 3183",
    "sg:postcode": "02038",
    "sg:province": "MA",
    "sg:tags": [
      "cleaners",
      "rug",
      "carpet"
    ],
    "wof:name": "ATA Carpet Cleaning Corp",
    "wof:placetype": "venue"
  },
  "geometry": {"coordinates":[-71.393566,42.127436],"type":"Point"}
}
