{
  "type": "Feature",
  "properties": {
    "addr:full":"151 Mystic Ave Medford MA 02155",
    "addr:housenumber":"151",
    "addr:postcode":"02155",
    "addr:street":"Mystic Ave",
    "iso:country":"US",
    "sg:address":"151 Mystic Ave",
    "sg:city":"Medford",
    "sg:classifiers":[
        {
            "category":"Health Services",
            "subcategory":"Clinic",
            "type":"Services"
        }
    ],
    "sg:phone":"+1 781 395 1758",
    "sg:postcode":"02155",
    "sg:province":"MA",
    "sg:tags":[
        "therapy",
        "muscular"
    ],
    "wof:name":"Avatar Spa",
    "wof:placetype":"venue"
},
  "geometry": {"coordinates":[-71.105433,42.409747],"type":"Point"}
}