{
  "type": "Feature",
  "properties": {
    "addr:full": "835 Plain St Marshfield MA 02050",
    "addr:housenumber": "835",
    "addr:postcode": "02050",
    "addr:street": "Plain St",
    "iso:country": "US",
    "sg:address": "835 Plain St",
    "sg:city": "Marshfield",
    "sg:classifiers": [
      {
        "category": "Building \u0026 Trades",
        "subcategory": "Construction",
        "type": "Services"
      }
    ],
    "sg:phone": "+1 781 837 7199",
    "sg:postcode": "02050",
    "sg:province": "MA",
    "sg:tags": [
      "general",
      "contractor"
    ],
    "wof:name": "D Lorenzo Corp",
    "wof:placetype": "venue"
  },
  "geometry": {"coordinates":[-70.750866,42.106453],"type":"Point"}
}
