{
  "type": "Feature",
  "properties": {
    "addr:full": "100 Winthrop St Medford MA 02155",
    "addr:housenumber": "100",
    "addr:postcode": "02155",
    "addr:street": "Winthrop St",
    "iso:country": "US",
    "sg:address": "100 Winthrop St",
    "sg:city": "Medford",
    "sg:classifiers": [
      {
        "category": "Health Services",
        "subcategory": "Clinic",
        "type": "Services"
      }
    ],
    "sg:phone": "+1 781 391 2998",
    "sg:postcode": "02155",
    "sg:province": "MA",
    "sg:tags": [
      "home"
    ],
    "wof:name": "Additional Care",
    "wof:placetype": "venue"
  },
  "geometry": {"coordinates":[-71.120836,42.412987],"type":"Point"}
}
