{
  "type": "Feature",
  "properties": {
    "addr:full":"4 Johnson St Auburn MA 01527",
    "addr:housenumber":"4",
    "addr:postcode":"01527",
    "addr:street":"Johnson St",
    "iso:country":"US",
    "sg:address":"4 Johnson St",
    "sg:city":"Auburn",
    "sg:classifiers":[
        {
            "category":"Home & Garden",
            "subcategory":"Furniture",
            "type":"Retail Goods"
        }
    ],
    "sg:phone":"+1 508 832 0458",
    "sg:postcode":"01527",
    "sg:province":"MA",
    "sg:tags":[
        "mattress"
    ],
    "wof:name":"Mattress Giant",
    "wof:placetype":"venue"
},
  "geometry": {"coordinates":[-71.779815,42.215592],"type":"Point"}
}