{
  "type": "Feature",
  "properties": {
    "addr:full": "13 Stockton St Dorchester Ctr MA 02124",
    "addr:housenumber": "13",
    "addr:postcode": "02124",
    "addr:street": "Stockton St",
    "iso:country": "US",
    "sg:address": "13 Stockton St",
    "sg:city": "Dorchester Ctr",
    "sg:classifiers": [
      {
        "category": "Professional",
        "subcategory": "Accounting \u0026 Tax Preparation",
        "type": "Services"
      }
    ],
    "sg:phone": "+1 617 287 8430",
    "sg:postcode": "02124",
    "sg:province": "MA",
    "sg:tags": [
      "return",
      "filing"
    ],
    "wof:name": "Yancey Financial Svc",
    "wof:placetype": "venue"
  },
  "geometry": {"coordinates":[-71.075695,42.282387],"type":"Point"}
}
