{
  "type": "Feature",
  "properties": {
    "iso:country":"US",
    "sg:address":"13 Stockton St",
    "sg:city":"Dorchester Ctr",
    "sg:classifiers":[
        {
            "category":"Professional",
            "subcategory":"Accounting & Tax Preparation",
            "type":"Services"
        }
    ],
    "sg:phone":"+1 617 287 8430",
    "sg:postcode":"02124",
    "sg:province":"MA",
    "sg:tags":[
        "return",
        "filing"
    ],
    "wof:name":"Yancey Financial Svc",
    "wof:placetype":"venue"
},
  "geometry": {"coordinates":[-71.075695,42.282387],"type":"Point"}
}