{
  "type": "Feature",
  "properties": {
    "iso:country":"US",
    "sg:address":"557 SW Cutoff",
    "sg:city":"Worcester",
    "sg:classifiers":[
        {
            "category":"Wholesale",
            "subcategory":"Construction Materials",
            "type":"Manufacturing & Wholesale Goods"
        }
    ],
    "sg:phone":"+1 508 791 9343",
    "sg:postcode":"01607",
    "sg:province":"MA",
    "sg:tags":[
        "fence"
    ],
    "wof:name":"Joe Goodman Fencing",
    "wof:placetype":"venue"
},
  "geometry": {"coordinates":[-71.78473,42.212142],"type":"Point"}
}