{
  "type": "Feature",
  "properties": {
    "addr:full":"8 Museum Way Cambridge MA 02141",
    "addr:housenumber":"8",
    "addr:postcode":"02141",
    "addr:street":"Museum Way",
    "iso:country":"US",
    "sg:address":"8 Museum Way",
    "sg:city":"Cambridge",
    "sg:classifiers":[
        {
            "category":"Professional",
            "subcategory":"Computer Services",
            "type":"Services"
        }
    ],
    "sg:phone":"+1   ",
    "sg:postcode":"02141",
    "sg:province":"MA",
    "sg:tags":[
        "consulting",
        "it"
    ],
    "wof:name":"Edas Consulting Inc",
    "wof:placetype":"venue"
},
  "geometry": {"coordinates":[-71.072147,42.369001],"type":"Point"}
}