{
  "type": "Feature",
  "properties": {
    "addr:full":"6 Lincoln Ave Salisbury MA 01952",
    "addr:housenumber":"6",
    "addr:postcode":"01952",
    "addr:street":"Lincoln Ave",
    "iso:country":"US",
    "sg:address":"6 Lincoln Ave",
    "sg:city":"Salisbury",
    "sg:classifiers":[
        {
            "category":"Restaurant",
            "type":"Food & Drink"
        }
    ],
    "sg:phone":"+1   ",
    "sg:postcode":"01952",
    "sg:province":"MA",
    "sg:tags":[
        "eating"
    ],
    "wof:name":"Treats For Trotting",
    "wof:placetype":"venue"
},
  "geometry": {"coordinates":[-70.858679,42.843081],"type":"Point"}
}