{
  "type": "Feature",
  "properties": {
    "addr:full":"86 Summit Lock Rd Westfield MA 01085",
    "addr:housenumber":"86",
    "addr:postcode":"01085",
    "addr:street":"Summit Lock Rd",
    "iso:country":"US",
    "sg:address":"86 Summit Lock Rd",
    "sg:city":"Westfield",
    "sg:classifiers":[
        {
            "category":"Real Estate",
            "subcategory":"Real Estate Operator",
            "type":"Services"
        }
    ],
    "sg:phone":"+1 413 568 4447",
    "sg:postcode":"01085",
    "sg:province":"MA",
    "sg:tags":[
        "apartment"
    ],
    "wof:name":"Apartment Co",
    "wof:placetype":"venue"
},
  "geometry": {"coordinates":[-72.73048799999999,42.175906],"type":"Point"}
}