{
  "type": "Feature",
  "properties": {
    "addr:full": "207 Kendall St Walpole MA 02081",
    "addr:housenumber": "207",
    "addr:postcode": "02081",
    "addr:street": "Kendall St",
    "iso:country": "US",
    "sg:address": "207 Kendall St",
    "sg:city": "Walpole",
    "sg:classifiers": [
      {
        "category": "Professional",
        "subcategory": "Management \u0026 Consulting",
        "type": "Services"
      }
    ],
    "sg:phone": "+1 508 668 9210",
    "sg:postcode": "02081",
    "sg:province": "MA",
    "sg:tags": [
      "counselor",
      "relation",
      "public"
    ],
    "wof:name": "Yes Boston Inc",
    "wof:placetype": "venue"
  },
  "geometry": {"coordinates":[-71.247055,42.151215],"type":"Point"}
}
