{
  "type": "Feature",
  "properties": {
    "addr:full": "290 Main St Rutland MA 01543",
    "addr:housenumber": "290",
    "addr:postcode": "01543",
    "addr:street": "Main St",
    "iso:country": "US",
    "sg:address": "290 Main St",
    "sg:city": "Rutland",
    "sg:classifiers": [
      {
        "category": "Organizations",
        "subcategory": "Religious Organization",
        "type": "Services"
      }
    ],
    "sg:phone": "+1 508 886 4309",
    "sg:postcode": "01543",
    "sg:province": "MA",
    "sg:tags": [
      "church"
    ],
    "wof:name": "St Patricks Church Rectory",
    "wof:placetype": "venue"
  },
  "geometry": {"coordinates":[-71.96795,42.370906],"type":"Point"}
}
