{
  "type": "Feature",
  "properties": {
    "iso:country":"US",
    "sg:address":"36 N Bedford St",
    "sg:city":"East Bridgewater",
    "sg:classifiers":[
        {
            "category":"Professional",
            "subcategory":"Accounting & Tax Preparation",
            "type":"Services"
        }
    ],
    "sg:phone":"+1 508 378 8822",
    "sg:postcode":"02333",
    "sg:province":"MA",
    "sg:tags":[
        "accountant"
    ],
    "wof:name":"Victax Services",
    "wof:placetype":"venue"
},
  "geometry": {"coordinates":[-70.95831699999999,42.035025],"type":"Point"}
}