{
  "type": "Feature",
  "properties": {
    "iso:country":"US",
    "sg:address":"107 Squannacook Rd",
    "sg:city":"Shirley",
    "sg:classifiers":[
        {
            "category":"Building & Trades",
            "subcategory":"Construction",
            "type":"Services"
        }
    ],
    "sg:phone":"+1   ",
    "sg:postcode":"01464",
    "sg:province":"MA",
    "sg:tags":[
        "new",
        "home"
    ],
    "wof:name":"Franzek Construction",
    "wof:placetype":"venue"
},
  "geometry": {"coordinates":[-71.642967,42.611469],"type":"Point"}
}