{
  "type": "Feature",
  "properties": {
    "iso:country":"US",
    "sg:address":"691 Washington St",
    "sg:city":"South Easton",
    "sg:classifiers":[
        {
            "category":"Retail",
            "subcategory":"Animal Services",
            "type":"Services"
        }
    ],
    "sg:phone":"+1 508 574 8250",
    "sg:postcode":"02375",
    "sg:province":"MA",
    "sg:tags":[
        "pet"
    ],
    "wof:name":"Swept Away",
    "wof:placetype":"venue"
},
  "geometry": {"coordinates":[-71.07722699999999,42.041714],"type":"Point"}
}