{
  "type": "Feature",
  "properties": {
    "addr:full": "35 Columbus Ave Somerville MA 02143",
    "addr:housenumber": "35",
    "addr:postcode": "02143",
    "addr:street": "Columbus Ave",
    "iso:country": "US",
    "sg:address": "35 Columbus Ave",
    "sg:city": "Somerville",
    "sg:classifiers": [
      {
        "category": "Building \u0026 Trades",
        "subcategory": "Construction",
        "type": "Services"
      }
    ],
    "sg:phone": "+1 617 666 5665",
    "sg:postcode": "02143",
    "sg:province": "MA",
    "sg:tags": [
      "painter"
    ],
    "wof:name": "Evans Painting Co",
    "wof:placetype": "venue"
  },
  "geometry": {"coordinates":[-71.094149,42.381218],"type":"Point"}
}
