{
  "type": "Feature",
  "properties": {
    "addr:full": "1099 Main St Housatonic MA 01236",
    "addr:housenumber": "1099",
    "addr:postcode": "01236",
    "addr:street": "Main St",
    "iso:country": "US",
    "sg:address": "1099 Main St",
    "sg:city": "Housatonic",
    "sg:classifiers": [
      {
        "category": "Real Estate",
        "subcategory": "Real Estate Agent",
        "type": "Services"
      }
    ],
    "sg:phone": "+1 413 274 6224",
    "sg:postcode": "01236",
    "sg:province": "MA",
    "wof:name": "L J Stark Real Estate",
    "wof:placetype": "venue"
  },
  "geometry": {"coordinates":[-73.36332,42.257749],"type":"Point"}
}
