{
  "type": "Feature",
  "properties": {
    "iso:country":"US",
    "sg:address":"76 Elm St",
    "sg:city":"Jamaica Plain",
    "sg:classifiers":[
        {
            "category":"Real Estate",
            "subcategory":"Real Estate Operator",
            "type":"Services"
        }
    ],
    "sg:phone":"+1 617 524 5160",
    "sg:postcode":"02130",
    "sg:province":"MA",
    "sg:tags":[
        "apartment"
    ],
    "wof:name":"Sumner Hill House Apartments",
    "wof:placetype":"venue"
},
  "geometry": {"coordinates":[-71.11129800000001,42.309101],"type":"Point"}
}