{
  "type": "Feature",
  "properties": {
    "iso:country":"US",
    "sg:address":"1072 Massachusetts Ave",
    "sg:city":"Arlington",
    "sg:classifiers":[
        {
            "category":"Real Estate",
            "subcategory":"Surveying",
            "type":"Services"
        }
    ],
    "sg:phone":"+1 781 648 5533",
    "sg:postcode":"02476",
    "sg:province":"MA",
    "sg:tags":[
        "surveyor"
    ],
    "wof:name":"Rober Survey",
    "wof:placetype":"venue"
},
  "geometry": {"coordinates":[-71.171165,42.420915],"type":"Point"}
}