{
  "type": "Feature",
  "properties": {
    "addr:full":"102 Crane St Norton MA 02766",
    "addr:housenumber":"102",
    "addr:postcode":"02766",
    "addr:street":"Crane St",
    "iso:country":"US",
    "sg:address":"102 Crane St",
    "sg:city":"Norton",
    "sg:classifiers":[
        {
            "category":"Travel",
            "subcategory":"Hotels & Motels",
            "type":"Entertainment"
        }
    ],
    "sg:phone":"+1 508 285 2525",
    "sg:postcode":"02766",
    "sg:province":"MA",
    "wof:name":"National Cancer Society For Animals - CLOSED",
    "wof:placetype":"venue"
},
  "geometry": {"coordinates":[-71.15419799999999,41.952],"type":"Point"}
}