{
  "type": "Feature",
  "properties": {
    "iso:country":"US",
    "sg:address":"14 Hubbard Ave",
    "sg:city":"Springfield",
    "sg:classifiers":[
        {
            "category":"Professional",
            "subcategory":"Lawyer & Legal Services",
            "type":"Services"
        }
    ],
    "sg:phone":"+1 413 737 6001",
    "sg:postcode":"01105",
    "sg:province":"MA",
    "sg:tags":[
        "attorney"
    ],
    "wof:name":"Blackburn Law Office",
    "wof:placetype":"venue"
},
  "geometry": {"coordinates":[-72.583144,42.099215],"type":"Point"}
}