{
  "type": "Feature",
  "properties": {
    "iso:country":"US",
    "sg:address":"900 Main St",
    "sg:city":"Millis",
    "sg:classifiers":[
        {
            "category":"Government",
            "subcategory":"Office",
            "type":"Public Place"
        }
    ],
    "sg:phone":"+1 508 376 7051",
    "sg:postcode":"02054",
    "sg:province":"MA",
    "sg:tags":[
        "city",
        "resource",
        "human"
    ],
    "wof:name":"Millis Council On Aging",
    "wof:placetype":"venue"
},
  "geometry": {"coordinates":[-71.358082,42.166957],"type":"Point"}
}