{
  "type": "Feature",
  "properties": {
    "iso:country":"US",
    "sg:address":"43 Thackeray Rd",
    "sg:city":"Wellesley Hills",
    "sg:classifiers":[
        {
            "category":"Health Services",
            "subcategory":"Doctor",
            "type":"Services"
        }
    ],
    "sg:phone":"+1 781 235 8759",
    "sg:postcode":"02481",
    "sg:province":"MA",
    "sg:tags":[
        "physician",
        "surgeon"
    ],
    "wof:name":"William Dylewsky MD",
    "wof:placetype":"venue"
},
  "geometry": {"coordinates":[-71.255174,42.316299],"type":"Point"}
}