{
  "type": "Feature",
  "properties": {
    "iso:country":"US",
    "sg:address":"40 Grissom Rd",
    "sg:city":"Plymouth",
    "sg:classifiers":[
        {
            "category":"Home & Garden",
            "subcategory":"Household Appliances",
            "type":"Retail Goods"
        }
    ],
    "sg:phone":"+1 508 746 6106",
    "sg:postcode":"02360",
    "sg:province":"MA",
    "sg:tags":[
        "cleaners",
        "vacuum"
    ],
    "wof:name":"Edmar Corp",
    "wof:placetype":"venue"
},
  "geometry": {"coordinates":[-70.68911900000001,41.956409],"type":"Point"}
}