{
  "type": "Feature",
  "properties": {
    "iso:country":"US",
    "sg:address":"769 Iyannough Rd",
    "sg:city":"Hyannis",
    "sg:classifiers":[
        {
            "category":"Shopping",
            "subcategory":"Mobile Phones",
            "type":"Retail Goods"
        }
    ],
    "sg:phone":"+1 508 778 4313",
    "sg:postcode":"02601",
    "sg:province":"MA",
    "wof:name":"Radioshack",
    "wof:placetype":"venue"
},
  "geometry": {"coordinates":[-70.295334,41.668493],"type":"Point"}
}