{
  "type": "Feature",
  "properties": {
    "addr:full": "23 Boston St Somerville MA 02143",
    "addr:housenumber": "23",
    "addr:postcode": "02143",
    "addr:street": "Boston St",
    "iso:country": "US",
    "sg:address": "23 Boston St",
    "sg:city": "Somerville",
    "sg:classifiers": [
      {
        "category": "Shopping",
        "subcategory": "Hobbies, Toys, \u0026 Games",
        "type": "Retail Goods"
      },
      {
        "category": "Shopping",
        "subcategory": "Crafts \u0026 Fabrics",
        "type": "Retail Goods"
      }
    ],
    "sg:phone": "+1 617 833 9374",
    "sg:postcode": "02143",
    "sg:province": "MA",
    "sg:tags": [
      "shop",
      "model",
      "hobby",
      "supply"
    ],
    "wof:name": "Rimay S Craft",
    "wof:placetype": "venue"
  },
  "geometry": {"coordinates":[-71.090945,42.381046],"type":"Point"}
}
