{
  "type": "Feature",
  "properties": {
    "iso:country":"US",
    "sg:address":"892 Highland Ave",
    "sg:city":"Needham",
    "sg:classifiers":[
        {
            "category":"Restaurant",
            "type":"Food & Drink"
        }
    ],
    "sg:phone":"+1 781 444 4333",
    "sg:postcode":"02494",
    "sg:province":"MA",
    "wof:name":"Town House Pizza",
    "wof:placetype":"venue"
},
  "geometry": {"coordinates":[-71.235181,42.293374],"type":"Point"}
}