{
  "type": "Feature",
  "properties": {
    "addr:full": "23 State Hwy 8 Charlemont MA 01339",
    "addr:housenumber": "23",
    "addr:postcode": "01339",
    "addr:street": "State Hwy 8",
    "iso:country": "US",
    "sg:address": "23 State Hwy 8",
    "sg:city": "Charlemont",
    "sg:classifiers": [
      {
        "category": "Building \u0026 Trades",
        "subcategory": "Construction",
        "type": "Services"
      }
    ],
    "sg:phone": "+1 413 337 4426",
    "sg:postcode": "01339",
    "sg:province": "MA",
    "sg:tags": [
      "general",
      "contractor"
    ],
    "wof:name": "Homestyles",
    "wof:placetype": "venue"
  },
  "geometry": {"coordinates":[-72.876584,42.627693],"type":"Point"}
}
