{
  "type": "Feature",
  "properties": {
    "iso:country":"US",
    "sg:address":"23 State Hwy 8",
    "sg:city":"Charlemont",
    "sg:classifiers":[
        {
            "category":"Building & Trades",
            "subcategory":"Construction",
            "type":"Services"
        }
    ],
    "sg:phone":"+1 413 337 4426",
    "sg:postcode":"01339",
    "sg:province":"MA",
    "sg:tags":[
        "general",
        "contractor"
    ],
    "wof:name":"Homestyles",
    "wof:placetype":"venue"
},
  "geometry": {"coordinates":[-72.87658399999999,42.627693],"type":"Point"}
}