{
  "type": "Feature",
  "properties": {
    "iso:country":"US",
    "sg:address":"715 Crescent St",
    "sg:city":"Brockton",
    "sg:classifiers":[
        {
            "category":"Professional",
            "subcategory":"Management & Consulting",
            "type":"Services"
        }
    ],
    "sg:phone":"+1 508 583 1277",
    "sg:postcode":"02302",
    "sg:province":"MA",
    "sg:tags":[
        "marketing",
        "program"
    ],
    "wof:name":"Catalina Marketing Corp",
    "wof:placetype":"venue"
},
  "geometry": {"coordinates":[-70.988187,42.081402],"type":"Point"}
}