{
  "type": "Feature",
  "properties": {
    "addr:full": "21 Orchard St Taunton MA 02780",
    "addr:housenumber": "21",
    "addr:postcode": "02780",
    "addr:street": "Orchard St",
    "iso:country": "US",
    "sg:address": "21 Orchard St",
    "sg:city": "Taunton",
    "sg:classifiers": [
      {
        "category": "Building \u0026 Trades",
        "subcategory": "Electrical",
        "type": "Services"
      }
    ],
    "sg:phone": "+1   ",
    "sg:postcode": "02780",
    "sg:province": "MA",
    "sg:tags": [
      "electrical",
      "contractor"
    ],
    "wof:name": "Marshall Francis Electrician",
    "wof:placetype": "venue"
  },
  "geometry": {"coordinates":[-71.092894,41.892785],"type":"Point"}
}
