{
  "type": "Feature",
  "properties": {
    "iso:country":"US",
    "sg:address":"25 Grandview Ave",
    "sg:city":"Mattapoisett",
    "sg:classifiers":[
        {
            "category":"Building & Trades",
            "subcategory":"Construction",
            "type":"Services"
        }
    ],
    "sg:phone":"+1 508 758 9607",
    "sg:postcode":"02739",
    "sg:province":"MA",
    "sg:tags":[
        "wallpaper"
    ],
    "wof:name":"Peterson Painting & Paper",
    "wof:placetype":"venue"
},
  "geometry": {"coordinates":[-70.802987,41.638096],"type":"Point"}
}