{
  "type": "Feature",
  "properties": {
    "addr:full": "25 Grandview Ave Mattapoisett MA 02739",
    "addr:housenumber": "25",
    "addr:postcode": "02739",
    "addr:street": "Grandview Ave",
    "iso:country": "US",
    "sg:address": "25 Grandview Ave",
    "sg:city": "Mattapoisett",
    "sg:classifiers": [
      {
        "category": "Building \u0026 Trades",
        "subcategory": "Construction",
        "type": "Services"
      }
    ],
    "sg:phone": "+1 508 758 9607",
    "sg:postcode": "02739",
    "sg:province": "MA",
    "sg:tags": [
      "wallpaper"
    ],
    "wof:name": "Peterson Painting \u0026 Paper",
    "wof:placetype": "venue"
  },
  "geometry": {"coordinates":[-70.802987,41.638096],"type":"Point"}
}
