{
  "type": "Feature",
  "properties": {
    "iso:country":"US",
    "sg:address":"307 Grafton St",
    "sg:city":"Shrewsbury",
    "sg:classifiers":[
        {
            "category":"Personal",
            "subcategory":"Beauty Salon",
            "type":"Services"
        }
    ],
    "sg:phone":"+1 508 841 4121",
    "sg:postcode":"01545",
    "sg:province":"MA",
    "wof:name":"Salon Sogno",
    "wof:placetype":"venue"
},
  "geometry": {"coordinates":[-71.71180699999999,42.27599],"type":"Point"}
}