{
  "type": "Feature",
  "properties": {
    "addr:full": "90 E India Row Boston MA 02110",
    "addr:housenumber": "90",
    "addr:postcode": "02110",
    "addr:street": "E India Row",
    "iso:country": "US",
    "sg:address": "90 E India Row",
    "sg:city": "Boston",
    "sg:classifiers": [
      {
        "category": "Museum",
        "subcategory": "Aquarium",
        "type": "Entertainment"
      }
    ],
    "sg:phone": "+1 617 573 9352",
    "sg:postcode": "02110",
    "sg:province": "MA",
    "wof:name": "Aquarium New England",
    "wof:placetype": "venue"
  },
  "geometry": {"coordinates":[-71.050819,42.358921],"type":"Point"}
}
