{
  "type": "Feature",
  "properties": {
    "addr:full":"100 Bishop Dr Framingham MA 01702",
    "addr:housenumber":"100",
    "addr:postcode":"01702",
    "addr:street":"Bishop Dr",
    "iso:country":"US",
    "sg:address":"100 Bishop Dr",
    "sg:city":"Framingham",
    "sg:classifiers":[
        {
            "category":"Real Estate",
            "subcategory":"Real Estate Operator",
            "type":"Services"
        }
    ],
    "sg:phone":"+1 508 872 6115",
    "sg:postcode":"01702",
    "sg:province":"MA",
    "sg:tags":[
        "condominium"
    ],
    "wof:name":"Bishop Garden Condominiums",
    "wof:placetype":"venue"
},
  "geometry": {"coordinates":[-71.402749,42.284209],"type":"Point"}
}