{
  "type": "Feature",
  "properties": {
    "addr:full":"2 School St Marblehead MA 01945",
    "addr:housenumber":"2",
    "addr:postcode":"01945",
    "addr:street":"School St",
    "iso:country":"US",
    "sg:address":"2 School St",
    "sg:city":"Marblehead",
    "sg:classifiers":[
        {
            "category":"Food & Beverages",
            "subcategory":"Bakery",
            "type":"Retail Goods"
        }
    ],
    "sg:phone":"+1 781 631 2253",
    "sg:postcode":"01945",
    "sg:province":"MA",
    "sg:tags":[
        "baker"
    ],
    "wof:name":"Ladycakes",
    "wof:placetype":"venue"
},
  "geometry": {"coordinates":[-70.856635,42.501912],"type":"Point"}
}