{
  "type": "Feature",
  "properties": {
    "iso:country":"US",
    "sg:address":"7 Griffin Way",
    "sg:city":"Chelsea",
    "sg:classifiers":[
        {
            "category":"Autos & Motor Vehicles",
            "subcategory":"Auto Supplies",
            "type":"Retail Goods"
        },
        {
            "category":"Retail",
            "subcategory":"Auto Repair",
            "type":"Services"
        }
    ],
    "sg:phone":"+1 617 569 7450",
    "sg:postcode":"02150",
    "sg:province":"MA",
    "sg:tags":[
        "automobile",
        "accessory",
        "parts",
        "accessories-wholesale",
        "part",
        "manufacturer"
    ],
    "wof:name":"Gem Automobile Parts Co",
    "wof:placetype":"venue"
},
  "geometry": {"coordinates":[-71.024545,42.39155],"type":"Point"}
}