{
  "type": "Feature",
  "properties": {
    "addr:full": "129 South St Boston MA 02111",
    "addr:housenumber": "129",
    "addr:postcode": "02111",
    "addr:street": "South St",
    "iso:country": "US",
    "sg:address": "129 South St",
    "sg:city": "Boston",
    "sg:classifiers": [
      {
        "category": "Insurance",
        "subcategory": "Insurance Agent",
        "type": "Services"
      }
    ],
    "sg:phone": "+1 617 482 5554",
    "sg:postcode": "02111",
    "sg:province": "MA",
    "wof:name": "D I Ctr Of New England",
    "wof:placetype": "venue"
  },
  "geometry": {"coordinates":[-71.057417,42.350786],"type":"Point"}
}
