{
  "type": "Feature",
  "properties": {
    "iso:country":"US",
    "sg:address":"67 North St",
    "sg:city":"Medfield",
    "sg:classifiers":[
        {
            "category":"Shopping",
            "subcategory":"Crafts & Fabrics",
            "type":"Retail Goods"
        }
    ],
    "sg:phone":"+1   ",
    "sg:postcode":"02052",
    "sg:province":"MA",
    "sg:tags":[
        "sewing"
    ],
    "wof:name":"Wool Works",
    "wof:placetype":"venue"
},
  "geometry": {"coordinates":[-71.30744900000001,42.188919],"type":"Point"}
}