{
  "type": "Feature",
  "properties": {
    "addr:full": "67 North St Medfield MA 02052",
    "addr:housenumber": "67",
    "addr:postcode": "02052",
    "addr:street": "North St",
    "iso:country": "US",
    "sg:address": "67 North St",
    "sg:city": "Medfield",
    "sg:classifiers": [
      {
        "category": "Shopping",
        "subcategory": "Crafts \u0026 Fabrics",
        "type": "Retail Goods"
      }
    ],
    "sg:phone": "+1   ",
    "sg:postcode": "02052",
    "sg:province": "MA",
    "sg:tags": [
      "sewing"
    ],
    "wof:name": "Wool Works",
    "wof:placetype": "venue"
  },
  "geometry": {"coordinates":[-71.307449,42.188919],"type":"Point"}
}
