{
  "type": "Feature",
  "properties": {
    "addr:full": "29 Wallingford Rd Worcester MA 01607",
    "addr:housenumber": "29",
    "addr:postcode": "01607",
    "addr:street": "Wallingford Rd",
    "iso:country": "US",
    "sg:address": "29 Wallingford Rd",
    "sg:city": "Worcester",
    "sg:classifiers": [
      {
        "category": "Personal",
        "subcategory": "Beauty Salon",
        "type": "Services"
      }
    ],
    "sg:phone": "+1 508 755 1155",
    "sg:postcode": "01607",
    "sg:province": "MA",
    "wof:name": "Studio 28",
    "wof:placetype": "venue"
  },
  "geometry": {"coordinates":[-71.802393,42.218726],"type":"Point"}
}
