{
  "type": "Feature",
  "properties": {
    "iso:country":"US",
    "sg:address":"42 Silver Hill Ln",
    "sg:city":"Natick",
    "sg:classifiers":[
        {
            "category":"Food Court",
            "type":"Food & Drink"
        }
    ],
    "sg:phone":"+1 508 740 5594",
    "sg:postcode":"01760",
    "sg:province":"MA",
    "sg:tags":[
        "frozen",
        "locker",
        "plant"
    ],
    "wof:name":"Semsa",
    "wof:placetype":"venue"
},
  "geometry": {"coordinates":[-71.384822,42.278073],"type":"Point"}
}