{
  "type": "Feature",
  "properties": {
    "iso:country":"US",
    "sg:address":"305 Essex St",
    "sg:city":"Lawrence",
    "sg:classifiers":[
        {
            "category":"Organizations",
            "subcategory":"Non-profit Organization",
            "type":"Services"
        }
    ],
    "sg:phone":"+1 978 681 4900",
    "sg:postcode":"01840",
    "sg:province":"MA",
    "sg:website":"www.glcac.org",
    "wof:name":"Greater Lawrence Community Inc",
    "wof:placetype":"venue"
},
  "geometry": {"coordinates":[-71.162818,42.707114],"type":"Point"}
}