{
  "type": "Feature",
  "properties": {
    "addr:full":"184 Middleboro Rd East Freetown MA 02717",
    "addr:housenumber":"184",
    "addr:postcode":"02717",
    "addr:street":"Middleboro Rd",
    "iso:country":"US",
    "sg:address":"184 Middleboro Rd",
    "sg:city":"East Freetown",
    "sg:classifiers":[
        {
            "category":"Building & Trades",
            "subcategory":"Electrical",
            "type":"Services"
        }
    ],
    "sg:phone":"+1 508 763 4755",
    "sg:postcode":"02717",
    "sg:province":"MA",
    "sg:tags":[
        "installation"
    ],
    "wof:name":"Scb Installations",
    "wof:placetype":"venue"
},
  "geometry": {"coordinates":[-70.93055,41.778294],"type":"Point"}
}