{
  "type": "Feature",
  "properties": {
    "iso:country":"US",
    "sg:address":"398 Cedar Hill St",
    "sg:city":"Marlborough",
    "sg:classifiers":[
        {
            "category":"Professional",
            "subcategory":"Research",
            "type":"Services"
        }
    ],
    "sg:phone":"+1 508 481 5750",
    "sg:postcode":"01752",
    "sg:province":"MA",
    "sg:tags":[
        "environmental",
        "ecological"
    ],
    "wof:name":"Handex Of New England",
    "wof:placetype":"venue"
},
  "geometry": {"coordinates":[-71.592647,42.319105],"type":"Point"}
}