{
  "type": "Feature",
  "properties": {
    "iso:country":"US",
    "sg:address":"282 Park St",
    "sg:city":"Gardner",
    "sg:classifiers":[
        {
            "category":"Professional",
            "subcategory":"Management & Consulting",
            "type":"Services"
        }
    ],
    "sg:phone":"+1 978 632 6947",
    "sg:postcode":"01440",
    "sg:province":"MA",
    "sg:tags":[
        "consultant",
        "business"
    ],
    "wof:name":"Usana Business Consultant",
    "wof:placetype":"venue"
},
  "geometry": {"coordinates":[-71.99700799999999,42.584911],"type":"Point"}
}