{
  "type": "Feature",
  "properties": {
    "addr:full": "282 Park St Gardner MA 01440",
    "addr:housenumber": "282",
    "addr:postcode": "01440",
    "addr:street": "Park St",
    "iso:country": "US",
    "sg:address": "282 Park St",
    "sg:city": "Gardner",
    "sg:classifiers": [
      {
        "category": "Professional",
        "subcategory": "Management \u0026 Consulting",
        "type": "Services"
      }
    ],
    "sg:phone": "+1 978 632 6947",
    "sg:postcode": "01440",
    "sg:province": "MA",
    "sg:tags": [
      "consultant",
      "business"
    ],
    "wof:name": "Usana Business Consultant",
    "wof:placetype": "venue"
  },
  "geometry": {"coordinates":[-71.997008,42.584911],"type":"Point"}
}
