{
  "type": "Feature",
  "properties": {
    "addr:full":"12 Orange St Nantucket MA 02554",
    "addr:housenumber":"12",
    "addr:postcode":"02554",
    "addr:street":"Orange St",
    "iso:country":"US",
    "sg:address":"12 Orange St",
    "sg:city":"Nantucket",
    "sg:classifiers":[
        {
            "category":"Professional",
            "subcategory":"Engineering",
            "type":"Services"
        }
    ],
    "sg:phone":"+1 508 325 4414",
    "sg:postcode":"02554",
    "sg:province":"MA",
    "sg:tags":[
        "architect",
        "naval"
    ],
    "wof:name":"Nantucket Design & Marine",
    "wof:placetype":"venue"
},
  "geometry": {"coordinates":[-70.098821,41.282322],"type":"Point"}
}