{
  "type": "Feature",
  "properties": {
    "addr:full": "167 Corey Rd Brighton MA 02135",
    "addr:housenumber": "167",
    "addr:postcode": "02135",
    "addr:street": "Corey Rd",
    "iso:country": "US",
    "sg:address": "167 Corey Rd",
    "sg:city": "Brighton",
    "sg:classifiers": [
      {
        "category": "Food \u0026 Beverages",
        "subcategory": "Liquor \u0026 Beverages",
        "type": "Retail Goods"
      }
    ],
    "sg:phone": "+1 617 731 4845",
    "sg:postcode": "02135",
    "sg:province": "MA",
    "wof:name": "Bag Ladies Tea",
    "wof:placetype": "venue"
  },
  "geometry": {"coordinates":[-71.13936,42.343208],"type":"Point"}
}
