{
  "type": "Feature",
  "properties": {
    "iso:country":"US",
    "sg:address":"167 Corey Rd",
    "sg:city":"Brighton",
    "sg:classifiers":[
        {
            "category":"Food & Beverages",
            "subcategory":"Liquor & Beverages",
            "type":"Retail Goods"
        }
    ],
    "sg:phone":"+1 617 731 4845",
    "sg:postcode":"02135",
    "sg:province":"MA",
    "wof:name":"Bag Ladies Tea",
    "wof:placetype":"venue"
},
  "geometry": {"coordinates":[-71.13936,42.343208],"type":"Point"}
}