{
  "type": "Feature",
  "properties": {
    "iso:country":"US",
    "sg:address":"808 West St",
    "sg:city":"Stoughton",
    "sg:classifiers":[
        {
            "category":"Education",
            "subcategory":"Preschool",
            "type":"Public Place"
        },
        {
            "category":"Education",
            "subcategory":"School",
            "type":"Public Place"
        }
    ],
    "sg:phone":"+1 781 344 0200",
    "sg:postcode":"02072",
    "sg:province":"MA",
    "sg:tags":[
        "elementary"
    ],
    "wof:name":"Academy of Gymnastics",
    "wof:placetype":"venue"
},
  "geometry": {"coordinates":[-71.12370300000001,42.1105],"type":"Point"}
}