{
  "type": "Feature",
  "properties": {
    "iso:country":"US",
    "sg:address":"1 Kelleway Dr",
    "sg:city":"Randolph",
    "sg:classifiers":[
        {
            "category":"Professional",
            "subcategory":"Business Services",
            "type":"Services"
        },
        {
            "category":"Shopping",
            "subcategory":"Computers & Home Electronics",
            "type":"Retail Goods"
        }
    ],
    "sg:phone":"+1 781 961 1702",
    "sg:postcode":"02368",
    "sg:province":"MA",
    "sg:tags":[
        "software"
    ],
    "wof:name":"Bonaire Software Solutions LLC",
    "wof:placetype":"venue"
},
  "geometry": {"coordinates":[-71.018923,42.168245],"type":"Point"}
}