{
  "type": "Feature",
  "properties": {
    "addr:full": "271 Cady St Ludlow MA 01056",
    "addr:housenumber": "271",
    "addr:postcode": "01056",
    "addr:street": "Cady St",
    "iso:country": "US",
    "sg:address": "271 Cady St",
    "sg:city": "Ludlow",
    "sg:classifiers": [
      {
        "category": "Building \u0026 Trades",
        "subcategory": "Construction",
        "type": "Services"
      }
    ],
    "sg:phone": "+1 413 547 6200",
    "sg:postcode": "01056",
    "sg:province": "MA",
    "sg:tags": [
      "general",
      "contractor"
    ],
    "wof:name": "Caracas Construction Corp",
    "wof:placetype": "venue"
  },
  "geometry": {"coordinates":[-72.51677,42.168513],"type":"Point"}
}
