{
  "type": "Feature",
  "properties": {
    "iso:country":"US",
    "sg:address":"271 Cady St",
    "sg:city":"Ludlow",
    "sg:classifiers":[
        {
            "category":"Building & Trades",
            "subcategory":"Construction",
            "type":"Services"
        }
    ],
    "sg:phone":"+1 413 547 6200",
    "sg:postcode":"01056",
    "sg:province":"MA",
    "sg:tags":[
        "general",
        "contractor"
    ],
    "wof:name":"Caracas Construction Corp",
    "wof:placetype":"venue"
},
  "geometry": {"coordinates":[-72.51676999999999,42.168513],"type":"Point"}
}