{
  "type": "Feature",
  "properties": {
    "addr:full":"466 Rantoul St Beverly MA 01915",
    "addr:housenumber":"466",
    "addr:postcode":"01915",
    "addr:street":"Rantoul St",
    "iso:country":"US",
    "sg:address":"466 Rantoul St",
    "sg:city":"Beverly",
    "sg:classifiers":[
        {
            "category":"Personal",
            "subcategory":"Beauty Salon",
            "type":"Services"
        }
    ],
    "sg:phone":"+1 978 927 2222",
    "sg:postcode":"01915",
    "sg:province":"MA",
    "wof:name":"Shear Action",
    "wof:placetype":"venue"
},
  "geometry": {"coordinates":[-70.880832,42.556153],"type":"Point"}
}