{
  "type": "Feature",
  "properties": {
    "addr:full": "14 Deer Run Rd Littleton MA 01460",
    "addr:housenumber": "14",
    "addr:postcode": "01460",
    "addr:street": "Deer Run Rd",
    "iso:country": "US",
    "sg:address": "14 Deer Run Rd",
    "sg:city": "Littleton",
    "sg:classifiers": [
      {
        "category": "Home \u0026 Garden",
        "subcategory": "Furniture",
        "type": "Retail Goods"
      }
    ],
    "sg:phone": "+1   ",
    "sg:postcode": "01460",
    "sg:province": "MA",
    "wof:name": "S\u0026M Assoc",
    "wof:placetype": "venue"
  },
  "geometry": {"coordinates":[-71.488514,42.571656],"type":"Point"}
}
