{
  "type": "Feature",
  "properties": {
    "addr:full":"1334 Water St Fitchburg MA 01420",
    "addr:housenumber":"1334",
    "addr:postcode":"01420",
    "addr:street":"Water St",
    "iso:country":"US",
    "sg:address":"1334 Water St",
    "sg:city":"Fitchburg",
    "sg:classifiers":[
        {
            "category":"Food & Beverages",
            "subcategory":"Groceries & Convenience Stores",
            "type":"Retail Goods"
        }
    ],
    "sg:phone":"+1 978 343 6373",
    "sg:postcode":"01420",
    "sg:province":"MA",
    "sg:tags":[
        "market"
    ],
    "wof:name":"International Market",
    "wof:placetype":"venue"
},
  "geometry": {"coordinates":[-71.77562399999999,42.55957],"type":"Point"}
}