{
  "type": "Feature",
  "properties": {
    "iso:country":"US",
    "sg:address":"47 Desmoines Rd",
    "sg:city":"Quincy",
    "sg:classifiers":[
        {
            "category":"Building & Trades",
            "subcategory":"Pest Control",
            "type":"Services"
        }
    ],
    "sg:phone":"+1 781 329 4600",
    "sg:postcode":"02169",
    "sg:province":"MA",
    "sg:tags":[
        "mothproofing"
    ],
    "wof:name":"Brothers Pest Control",
    "wof:placetype":"venue"
},
  "geometry": {"coordinates":[-70.97938499999999,42.2421],"type":"Point"}
}