{
  "type": "Feature",
  "properties": {
    "addr:full": "47 Desmoines Rd Quincy MA 02169",
    "addr:housenumber": "47",
    "addr:postcode": "02169",
    "addr:street": "Desmoines Rd",
    "iso:country": "US",
    "sg:address": "47 Desmoines Rd",
    "sg:city": "Quincy",
    "sg:classifiers": [
      {
        "category": "Building \u0026 Trades",
        "subcategory": "Pest Control",
        "type": "Services"
      }
    ],
    "sg:phone": "+1 781 329 4600",
    "sg:postcode": "02169",
    "sg:province": "MA",
    "sg:tags": [
      "mothproofing"
    ],
    "wof:name": "Brothers Pest Control",
    "wof:placetype": "venue"
  },
  "geometry": {"coordinates":[-70.979385,42.2421],"type":"Point"}
}
