{
  "type": "Feature",
  "properties": {
    "iso:country":"US",
    "sg:address":"825 Washington St Ste 210",
    "sg:city":"Norwood",
    "sg:classifiers":[
        {
            "category":"Health Services",
            "subcategory":"Doctor",
            "type":"Services"
        }
    ],
    "sg:phone":"+1 781 769 6440",
    "sg:postcode":"02062",
    "sg:province":"MA",
    "sg:tags":[
        "physician",
        "surgeon",
        "radiology",
        "surgeons",
        "pediatrics-radiology"
    ],
    "wof:name":"Norwood Womens Imaging Center Inc",
    "wof:placetype":"venue"
},
  "geometry": {"coordinates":[-71.202713,42.189041],"type":"Point"}
}