{
  "type": "Feature",
  "properties": {
    "iso:country":"US",
    "sg:address":"150 Fisher Ave",
    "sg:city":"Brookline",
    "sg:classifiers":[
        {
            "category":"Shopping",
            "subcategory":"Books",
            "type":"Retail Goods"
        },
        {
            "category":"Wholesale",
            "subcategory":"Books, Periodicals, & Newspapers",
            "type":"Manufacturing & Wholesale Goods"
        }
    ],
    "sg:phone":"+1 617 734 3853",
    "sg:postcode":"02445",
    "sg:province":"MA",
    "sg:tags":[
        "books-wholesale",
        "store",
        "manufacturer"
    ],
    "wof:name":"Newbury Campus Shop",
    "wof:placetype":"venue"
},
  "geometry": {"coordinates":[-71.143615,42.331679],"type":"Point"}
}