{
  "type": "Feature",
  "properties": {
    "addr:full":"481 Purgatory Rd Whitinsville MA 01588",
    "addr:housenumber":"481",
    "addr:postcode":"01588",
    "addr:street":"Purgatory Rd",
    "iso:country":"US",
    "sg:address":"481 Purgatory Rd",
    "sg:city":"Whitinsville",
    "sg:classifiers":[
        {
            "category":"Ice Cream",
            "type":"Food & Drink"
        }
    ],
    "sg:menulink":"http://www.allmenus.com/ma/northbridge/224960-dels-frozen-lemonade/menu/",
    "sg:postcode":"01588",
    "sg:province":"MA",
    "sg:tags":[
        "smoothy",
        "juice",
        "american"
    ],
    "wof:name":"Del's Frozen Lemonade",
    "wof:placetype":"venue"
},
  "geometry": {"coordinates":[-71.69403699999999,42.124213],"type":"Point"}
}