{
  "type": "Feature",
  "properties": {
    "addr:full": "27 Monument Sq Leominster MA 01453",
    "addr:housenumber": "27",
    "addr:postcode": "01453",
    "addr:street": "Monument Sq",
    "iso:country": "US",
    "sg:address": "27 Monument Sq",
    "sg:city": "Leominster",
    "sg:classifiers": [
      {
        "category": "Professional",
        "subcategory": "Business Services",
        "type": "Services"
      }
    ],
    "sg:phone": "+1 978 534 1400",
    "sg:postcode": "01453",
    "sg:province": "MA",
    "sg:tags": [
      "painter",
      "sign"
    ],
    "sg:website": "www.blazingsignworks.com",
    "wof:name": "Blazing Signworks",
    "wof:placetype": "venue"
  },
  "geometry": {"coordinates":[-71.759576,42.525552],"type":"Point"}
}
