{
  "type": "Feature",
  "properties": {
    "addr:full":"277 Main St Wilmington MA 01887",
    "addr:housenumber":"277",
    "addr:postcode":"01887",
    "addr:street":"Main St",
    "iso:country":"US",
    "sg:address":"277 Main St",
    "sg:city":"Wilmington",
    "sg:classifiers":[
        {
            "category":"Retail",
            "subcategory":"Portrait Studio",
            "type":"Services"
        },
        {
            "category":"Shopping",
            "subcategory":"Pharmacy",
            "type":"Retail Goods"
        }
    ],
    "sg:phone":"+1 978 657 9401",
    "sg:postcode":"01887",
    "sg:province":"MA",
    "sg:tags":[
        "photography",
        "drugstore",
        "store"
    ],
    "sg:website":"www.walgreens.com",
    "wof:name":"Walgreen Drug Stores",
    "wof:placetype":"venue"
},
  "geometry": {"coordinates":[-71.1795,42.553338],"type":"Point"}
}