{
  "type": "Feature",
  "properties": {
    "addr:full": "831 Dorchester Ave Dorchester MA 02125",
    "addr:housenumber": "831",
    "addr:postcode": "02125",
    "addr:street": "Dorchester Ave",
    "iso:country": "US",
    "sg:address": "831 Dorchester Ave",
    "sg:city": "Dorchester",
    "sg:classifiers": [
      {
        "category": "Real Estate",
        "subcategory": "Real Estate Agent",
        "type": "Services"
      }
    ],
    "sg:phone": "+1 617 265 4080",
    "sg:postcode": "02125",
    "sg:province": "MA",
    "wof:name": "Bostonian Homes",
    "wof:placetype": "venue"
  },
  "geometry": {"coordinates":[-71.056855,42.321766],"type":"Point"}
}
