{
  "type": "Feature",
  "properties": {
    "addr:full":"128 Hazel St Uxbridge MA 01569",
    "addr:housenumber":"128",
    "addr:postcode":"01569",
    "addr:street":"Hazel St",
    "iso:country":"US",
    "sg:address":"128 Hazel St",
    "sg:city":"Uxbridge",
    "sg:classifiers":[
        {
            "category":"Professional",
            "subcategory":"Secretarial Services",
            "type":"Services"
        }
    ],
    "sg:phone":"+1 508 278 5602",
    "sg:postcode":"01569",
    "sg:province":"MA",
    "sg:tags":[
        "communication",
        "proofreading",
        "editing",
        "written",
        "writing"
    ],
    "wof:name":"Vfp Communications",
    "wof:placetype":"venue"
},
  "geometry": {"coordinates":[-71.644577,42.078831],"type":"Point"}
}