{
  "type": "Feature",
  "properties": {
    "addr:full":"35 Pine Ridge Rd Southbridge MA 01550",
    "addr:housenumber":"35",
    "addr:postcode":"01550",
    "addr:street":"Pine Ridge Rd",
    "iso:country":"US",
    "sg:address":"35 Pine Ridge Rd",
    "sg:city":"Southbridge",
    "sg:classifiers":[
        {
            "category":"Professional",
            "subcategory":"Business Services",
            "type":"Services"
        }
    ],
    "sg:phone":"+1   ",
    "sg:postcode":"01550",
    "sg:province":"MA",
    "wof:name":"Dennis J Martinek",
    "wof:placetype":"venue"
},
  "geometry": {"coordinates":[-72.056765,42.070398],"type":"Point"}
}