{
  "type": "Feature",
  "properties": {
    "addr:full": "41 Harrison St Taunton MA 02780",
    "addr:housenumber": "41",
    "addr:postcode": "02780",
    "addr:street": "Harrison St",
    "iso:country": "US",
    "sg:address": "41 Harrison St",
    "sg:city": "Taunton",
    "sg:classifiers": [
      {
        "category": "Professional",
        "subcategory": "Lawyer \u0026 Legal Services",
        "type": "Services"
      }
    ],
    "sg:phone": "+1 508 822 7777",
    "sg:postcode": "02780",
    "sg:province": "MA",
    "sg:tags": [
      "attorney"
    ],
    "wof:name": "Thomas E Workman Jr",
    "wof:placetype": "venue"
  },
  "geometry": {"coordinates":[-71.095887,41.897904],"type":"Point"}
}
