{
  "type": "Feature",
  "properties": {
    "addr:full":"313 North St Pittsfield MA 01201",
    "addr:housenumber":"313",
    "addr:postcode":"01201",
    "addr:street":"North St",
    "iso:country":"US",
    "sg:address":"313 North St",
    "sg:city":"Pittsfield",
    "sg:classifiers":[
        {
            "category":"Shopping",
            "subcategory":"Clothing, Apparel, & Fashions",
            "type":"Retail Goods"
        }
    ],
    "sg:phone":"+1 413 496 9665",
    "sg:postcode":"01201",
    "sg:province":"MA",
    "sg:tags":[
        "tuxedo"
    ],
    "wof:name":"Tux Express",
    "wof:placetype":"venue"
},
  "geometry": {"coordinates":[-73.25273900000001,42.453245],"type":"Point"}
}