{
  "type": "Feature",
  "properties": {
    "addr:full": "313 North St Pittsfield MA 01201",
    "addr:housenumber": "313",
    "addr:postcode": "01201",
    "addr:street": "North St",
    "iso:country": "US",
    "ovtr:label": "Tux Express, 313 North St Pittsfield MA US",
    "ovtr:similarity": 2.05794095993042,
    "sg:address": "313 North St",
    "sg:city": "Pittsfield",
    "sg:classifiers": [
      {
        "category": "Shopping",
        "subcategory": "Clothing, Apparel, \u0026 Fashions",
        "type": "Retail Goods"
      }
    ],
    "sg:phone": "+1 413 496 9665",
    "sg:postcode": "01201",
    "sg:province": "MA",
    "sg:tags": [
      "tuxedo"
    ],
    "wof:name": "Tux Express",
    "wof:placetype": "venue"
  },
  "geometry": {"coordinates":[-73.252739,42.453245],"type":"Point"}
}
