{
  "type": "Feature",
  "properties": {
    "addr:full":"16 Wildflower Ln Plymouth MA 02360",
    "addr:housenumber":"16",
    "addr:postcode":"02360",
    "addr:street":"Wildflower Ln",
    "iso:country":"US",
    "sg:address":"16 Wildflower Ln",
    "sg:city":"Plymouth",
    "sg:classifiers":[
        {
            "category":"Real Estate",
            "subcategory":"Real Estate Services",
            "type":"Services"
        },
        {
            "category":"Real Estate",
            "subcategory":"Real Estate Agent",
            "type":"Services"
        }
    ],
    "sg:phone":"+1 508 747 8360",
    "sg:postcode":"02360",
    "sg:province":"MA",
    "sg:tags":[
        "buyer",
        "broker"
    ],
    "wof:name":"Baldwin Realty Group Inc",
    "wof:placetype":"venue"
},
  "geometry": {"coordinates":[-70.608976,41.845099],"type":"Point"}
}