{
  "type": "Feature",
  "properties": {
    "iso:country":"US",
    "sg:address":"55 Commerce Way",
    "sg:city":"Dedham",
    "sg:classifiers":[
        {
            "category":"Wholesale",
            "subcategory":"Machinery & Supplies",
            "type":"Manufacturing & Wholesale Goods"
        }
    ],
    "sg:phone":"+1 781 251 9228",
    "sg:postcode":"02026",
    "sg:province":"MA",
    "sg:tags":[
        "equipment",
        "pneumatic",
        "component"
    ],
    "sg:website":"www.gocfa.com",
    "wof:name":"Controls For Automation Inc",
    "wof:placetype":"venue"
},
  "geometry": {"coordinates":[-71.152188,42.244158],"type":"Point"}
}