{
  "type": "Feature",
  "properties": {
    "addr:full": "87 Progress Ave Tyngsboro MA 01879",
    "addr:housenumber": "87",
    "addr:postcode": "01879",
    "addr:street": "Progress Ave",
    "iso:country": "US",
    "ovtr:label": "Absolute Gymnastics Academy, 87 Progress Ave Tyngsboro MA US",
    "ovtr:similarity": 2.2701640129089355,
    "sg:address": "87 Progress Ave",
    "sg:city": "Tyngsboro",
    "sg:classifiers": [
      {
        "category": "Recreation",
        "type": "Entertainment"
      }
    ],
    "sg:phone": "+1 978 649 7722",
    "sg:postcode": "01879",
    "sg:province": "MA",
    "sg:tags": [
      "instruction",
      "gymnastic"
    ],
    "sg:website": "www.absolutegymnastics.com",
    "wof:name": "Absolute Gymnastics Academy",
    "wof:placetype": "venue"
  },
  "geometry": {"coordinates":[-71.445617,42.673147],"type":"Point"}
}
