{
  "type": "Feature",
  "properties": {
    "addr:full": "9 Mear Rd Holbrook MA 02343",
    "addr:housenumber": "9",
    "addr:postcode": "02343",
    "addr:street": "Mear Rd",
    "iso:country": "US",
    "sg:address": "9 Mear Rd",
    "sg:city": "Holbrook",
    "sg:classifiers": [
      {
        "category": "Professional",
        "type": "Services"
      }
    ],
    "sg:phone": "+1 781 986 1056",
    "sg:postcode": "02343",
    "sg:province": "MA",
    "sg:tags": [
      "establishment"
    ],
    "wof:name": "Bruning International",
    "wof:placetype": "venue"
  },
  "geometry": {"coordinates":[-71.026831,42.153053],"type":"Point"}
}
