{
  "type": "Feature",
  "properties": {
    "addr:full": "55 Cape Rd Mendon MA 01756",
    "addr:housenumber": "55",
    "addr:postcode": "01756",
    "addr:street": "Cape Rd",
    "iso:country": "US",
    "sg:address": "55 Cape Rd",
    "sg:city": "Mendon",
    "sg:classifiers": [
      {
        "category": "Professional",
        "subcategory": "Management \u0026 Consulting",
        "type": "Services"
      }
    ],
    "sg:phone": "+1   ",
    "sg:postcode": "01756",
    "sg:province": "MA",
    "sg:tags": [
      "business"
    ],
    "wof:name": "Whitten Corp",
    "wof:placetype": "venue"
  },
  "geometry": {"coordinates":[-71.499327,42.090056],"type":"Point"}
}
