{
  "type": "Feature",
  "properties": {
    "iso:country":"US",
    "sg:address":"55 Cape Rd",
    "sg:city":"Mendon",
    "sg:classifiers":[
        {
            "category":"Professional",
            "subcategory":"Management & Consulting",
            "type":"Services"
        }
    ],
    "sg:phone":"+1   ",
    "sg:postcode":"01756",
    "sg:province":"MA",
    "sg:tags":[
        "business"
    ],
    "wof:name":"Whitten Corp",
    "wof:placetype":"venue"
},
  "geometry": {"coordinates":[-71.49932699999999,42.090056],"type":"Point"}
}