{
  "type": "Feature",
  "properties": {
    "iso:country":"US",
    "sg:address":"46 N Main St",
    "sg:city":"Bellingham",
    "sg:classifiers":[
        {
            "category":"Building & Trades",
            "subcategory":"Construction",
            "type":"Services"
        }
    ],
    "sg:phone":"+1 508 966 1003",
    "sg:postcode":"02019",
    "sg:province":"MA",
    "sg:tags":[
        "mason",
        "masonry",
        "industrial",
        "contractors-commercial",
        "contractor"
    ],
    "wof:name":"Jay Rowe Masonry",
    "wof:placetype":"venue"
},
  "geometry": {"coordinates":[-71.476555,42.092567],"type":"Point"}
}