{
  "type": "Feature",
  "properties": {
    "addr:full": "4 Mill St Bellingham MA 02019",
    "addr:housenumber": "4",
    "addr:postcode": "02019",
    "addr:street": "Mill St",
    "iso:country": "US",
    "sg:address": "4 Mill St",
    "sg:city": "Bellingham",
    "sg:classifiers": [
      {
        "category": "Professional",
        "subcategory": "Testing Lab",
        "type": "Services"
      }
    ],
    "sg:phone": "+1 508 966 1301",
    "sg:postcode": "02019",
    "sg:province": "MA",
    "sg:tags": [
      "laboratory"
    ],
    "sg:website": "www.jordiassoc.com",
    "wof:name": "Jordi Associates",
    "wof:placetype": "venue"
  },
  "geometry": {"coordinates":[-71.473268,42.089088],"type":"Point"}
}
