{
  "type": "Feature",
  "properties": {
    "addr:full": "1123 South St Fitchburg MA 01420",
    "addr:housenumber": "1123",
    "addr:postcode": "01420",
    "addr:street": "South St",
    "iso:country": "US",
    "sg:address": "1123 South St",
    "sg:city": "Fitchburg",
    "sg:classifiers": [
      {
        "category": "Personal",
        "subcategory": "Beauty Salon",
        "type": "Services"
      }
    ],
    "sg:phone": "+1 978 343 4307",
    "sg:postcode": "01420",
    "sg:province": "MA",
    "wof:name": "Keeping Ahead \u0026 Co",
    "wof:placetype": "venue"
  },
  "geometry": {"coordinates":[-71.784589,42.552859],"type":"Point"}
}
