{
  "type": "Feature",
  "properties": {
    "addr:full": "399 Chestnut St Needham MA 02492",
    "addr:housenumber": "399",
    "addr:postcode": "02492",
    "addr:street": "Chestnut St",
    "iso:country": "US",
    "sg:address": "399 Chestnut St",
    "sg:city": "Needham",
    "sg:classifiers": [
      {
        "category": "Shopping",
        "subcategory": "Clothing, Apparel, \u0026 Fashions",
        "type": "Retail Goods"
      }
    ],
    "sg:phone": "+1 781 455 8463",
    "sg:postcode": "02492",
    "sg:province": "MA",
    "sg:tags": [
      "tailor"
    ],
    "wof:name": "Hois Tailor Shop",
    "wof:placetype": "venue"
  },
  "geometry": {"coordinates":[-71.238143,42.272475],"type":"Point"}
}
