{
  "type": "Feature",
  "properties": {
    "iso:country":"US",
    "sg:address":"104 Bridge St",
    "sg:city":"North Weymouth",
    "sg:classifiers":[
        {
            "category":"Retail",
            "subcategory":"Repair Shop",
            "type":"Services"
        }
    ],
    "sg:phone":"+1 781 335 3412",
    "sg:postcode":"02191",
    "sg:province":"MA",
    "sg:tags":[
        "upholsterer"
    ],
    "wof:name":"Weymouth Upholstering Co",
    "wof:placetype":"venue"
},
  "geometry": {"coordinates":[-70.962661,42.243354],"type":"Point"}
}