{
  "type": "Feature",
  "properties": {
    "addr:full": "203 Carnegie Row Norwood MA 02062",
    "addr:housenumber": "203",
    "addr:postcode": "02062",
    "addr:street": "Carnegie Row",
    "iso:country": "US",
    "sg:address": "203 Carnegie Row",
    "sg:city": "Norwood",
    "sg:classifiers": [
      {
        "category": "Wholesale",
        "subcategory": "Machinery \u0026 Supplies",
        "type": "Manufacturing \u0026 Wholesale Goods"
      }
    ],
    "sg:phone": "+1 781 440 9993",
    "sg:postcode": "02062",
    "sg:province": "MA",
    "sg:tags": [
      "converting",
      "paper"
    ],
    "sg:website": "www.americanholt.com",
    "wof:name": "American Holt Corp",
    "wof:placetype": "venue"
  },
  "geometry": {"coordinates":[-71.193149,42.169036],"type":"Point"}
}
