{
  "type": "Feature",
  "properties": {
    "iso:country":"US",
    "sg:address":"203 Carnegie Row",
    "sg:city":"Norwood",
    "sg:classifiers":[
        {
            "category":"Wholesale",
            "subcategory":"Machinery & Supplies",
            "type":"Manufacturing & Wholesale Goods"
        }
    ],
    "sg:phone":"+1 781 440 9993",
    "sg:postcode":"02062",
    "sg:province":"MA",
    "sg:tags":[
        "converting",
        "paper"
    ],
    "sg:website":"www.americanholt.com",
    "wof:name":"American Holt Corp",
    "wof:placetype":"venue"
},
  "geometry": {"coordinates":[-71.19314900000001,42.169036],"type":"Point"}
}