{
  "type": "Feature",
  "properties": {
    "addr:full": "72 Jackson St Lawrence MA 01841",
    "addr:housenumber": "72",
    "addr:postcode": "01841",
    "addr:street": "Jackson St",
    "iso:country": "US",
    "sg:address": "72 Jackson St",
    "sg:city": "Lawrence",
    "sg:classifiers": [
      {
        "category": "Restaurant",
        "type": "Food \u0026 Drink"
      }
    ],
    "sg:phone": "+1 978 738 9566",
    "sg:postcode": "01841",
    "sg:province": "MA",
    "wof:name": "Casa De Sirena",
    "wof:placetype": "venue"
  },
  "geometry": {"coordinates":[-71.157871,42.71158],"type":"Point"}
}
