{
  "type": "Feature",
  "properties": {
    "addr:full": "85 Commercial Street Medford MA 02155",
    "addr:housenumber": "85",
    "addr:postcode": "02155",
    "addr:street": "Commercial Street",
    "iso:country": "US",
    "sg:address": "85 Commercial Street",
    "sg:city": "Medford",
    "sg:classifiers": [
      {
        "category": "Coffee \u0026 Tea",
        "type": "Food \u0026 Drink"
      }
    ],
    "sg:phone": "+1 781 396 2100",
    "sg:postcode": "02155",
    "sg:province": "MA",
    "sg:website": "www.espressoplus.com",
    "wof:name": "Espresso Plus",
    "wof:placetype": "venue"
  },
  "geometry": {"coordinates":[-71.08877,42.405152],"type":"Point"}
}
