{
  "type": "Feature",
  "properties": {
    "addr:full": "34 State St Newburyport MA 01950",
    "addr:housenumber": "34",
    "addr:postcode": "01950",
    "addr:street": "State St",
    "iso:country": "US",
    "sg:address": "34 State St",
    "sg:city": "Newburyport",
    "sg:classifiers": [
      {
        "category": "Shopping",
        "subcategory": "Books",
        "type": "Retail Goods"
      }
    ],
    "sg:phone": "+1 978 463 2226",
    "sg:postcode": "01950",
    "sg:province": "MA",
    "sg:tags": [
      "bookstore"
    ],
    "wof:name": "Enchanted Forest",
    "wof:placetype": "venue"
  },
  "geometry": {"coordinates":[-70.870106,42.810294],"type":"Point"}
}
