{
  "type": "Feature",
  "properties": {
    "addr:full": "317 Front St Ste C Marion MA 02738",
    "addr:housenumber": "317",
    "addr:postcode": "02738",
    "addr:street": "Front St Ste C",
    "iso:country": "US",
    "sg:address": "317 Front St Ste C",
    "sg:city": "Marion",
    "sg:classifiers": [
      {
        "category": "Travel",
        "subcategory": "Travel Agent",
        "type": "Entertainment"
      }
    ],
    "sg:phone": "+1 508 748 2220",
    "sg:postcode": "02738",
    "sg:province": "MA",
    "sg:tags": [
      "agency",
      "services-commercial"
    ],
    "wof:name": "Roehr Travel Inc",
    "wof:placetype": "venue"
  },
  "geometry": {"coordinates":[-70.767447,41.713366],"type":"Point"}
}
