{
  "type": "Feature",
  "properties": {
    "iso:country":"US",
    "sg:address":"52 Chapel Ln",
    "sg:city":"Brewster",
    "sg:classifiers":[
        {
            "category":"Retail",
            "subcategory":"Repair Shop",
            "type":"Services"
        }
    ],
    "sg:phone":"+1 508 896 8505",
    "sg:postcode":"02631",
    "sg:province":"MA",
    "sg:tags":[
        "machine",
        "electrical",
        "washing"
    ],
    "wof:name":"Appliance Plus Two",
    "wof:placetype":"venue"
},
  "geometry": {"coordinates":[-70.06855,41.769698],"type":"Point"}
}