{
  "type": "Feature",
  "properties": {
    "iso:country":"US",
    "sg:address":"375 Fortune Blvd",
    "sg:city":"Milford",
    "sg:classifiers":[
        {
            "category":"Social Services",
            "subcategory":"Child Care",
            "type":"Services"
        }
    ],
    "sg:phone":"+1 508 482 5939",
    "sg:postcode":"01757",
    "sg:province":"MA",
    "sg:tags":[
        "nursery",
        "day"
    ],
    "wof:name":"Healthy Families",
    "wof:placetype":"venue"
},
  "geometry": {"coordinates":[-71.49476300000001,42.158061],"type":"Point"}
}