{
  "type": "Feature",
  "properties": {
    "iso:country":"US",
    "sg:address":"86 Rossmore Rd",
    "sg:city":"Jamaica Plain",
    "sg:classifiers":[
        {
            "category":"Building & Trades",
            "subcategory":"Construction",
            "type":"Services"
        }
    ],
    "sg:phone":"+1 617 524 4372",
    "sg:postcode":"02130",
    "sg:province":"MA",
    "sg:tags":[
        "paving",
        "contractor"
    ],
    "wof:name":"Mathias Corp",
    "wof:placetype":"venue"
},
  "geometry": {"coordinates":[-71.10510499999999,42.303432],"type":"Point"}
}