{
  "type": "Feature",
  "properties": {
    "addr:full": "86 Rossmore Rd Jamaica Plain MA 02130",
    "addr:housenumber": "86",
    "addr:postcode": "02130",
    "addr:street": "Rossmore Rd",
    "iso:country": "US",
    "sg:address": "86 Rossmore Rd",
    "sg:city": "Jamaica Plain",
    "sg:classifiers": [
      {
        "category": "Building \u0026 Trades",
        "subcategory": "Construction",
        "type": "Services"
      }
    ],
    "sg:phone": "+1 617 524 4372",
    "sg:postcode": "02130",
    "sg:province": "MA",
    "sg:tags": [
      "paving",
      "contractor"
    ],
    "wof:name": "Mathias Corp",
    "wof:placetype": "venue"
  },
  "geometry": {"coordinates":[-71.105105,42.303432],"type":"Point"}
}
