{
  "type": "Feature",
  "properties": {
    "iso:country":"US",
    "sg:address":"25 Noble Ave",
    "sg:city":"Westfield",
    "sg:classifiers":[
        {
            "category":"Utilities",
            "subcategory":"Mobile Phone",
            "type":"Services"
        }
    ],
    "sg:phone":"+1 413 454 7308",
    "sg:postcode":"01085",
    "sg:province":"MA",
    "sg:tags":[
        "telephone",
        "cellular"
    ],
    "wof:name":"Blue Chip Constructn Cellular",
    "wof:placetype":"venue"
},
  "geometry": {"coordinates":[-72.754999,42.117321],"type":"Point"}
}