{
  "type": "Feature",
  "properties": {
    "addr:full":"932 Dorchester Ave Dorchester MA 02125",
    "addr:housenumber":"932",
    "addr:postcode":"02125",
    "addr:street":"Dorchester Ave",
    "iso:country":"US",
    "sg:address":"932 Dorchester Ave",
    "sg:city":"Dorchester",
    "sg:classifiers":[
        {
            "category":"Home & Garden",
            "subcategory":"Furniture",
            "type":"Retail Goods"
        }
    ],
    "sg:phone":"+1 617 288 5588",
    "sg:postcode":"02125",
    "sg:province":"MA",
    "wof:name":"French Furniture",
    "wof:placetype":"venue"
},
  "geometry": {"coordinates":[-71.056652,42.318844],"type":"Point"}
}