{
  "type": "Feature",
  "properties": {
    "iso:country":"US",
    "sg:address":"547 Washington St",
    "sg:city":"Boston",
    "sg:classifiers":[
        {
            "category":"Shopping",
            "subcategory":"Clothing, Apparel, & Fashions",
            "type":"Retail Goods"
        }
    ],
    "sg:phone":"+1 617 423 9026",
    "sg:postcode":"02111",
    "sg:province":"MA",
    "wof:name":"High Voltage Power",
    "wof:placetype":"venue"
},
  "geometry": {"coordinates":[-71.06210299999999,42.353802],"type":"Point"}
}