{
  "type": "Feature",
  "properties": {
    "addr:full": "922 Pleasant St Norwood MA 02062",
    "addr:housenumber": "922",
    "addr:postcode": "02062",
    "addr:street": "Pleasant St",
    "iso:country": "US",
    "sg:address": "922 Pleasant St",
    "sg:city": "Norwood",
    "sg:classifiers": [
      {
        "category": "Manufacturing",
        "subcategory": "Tools \u0026 Machinery",
        "type": "Manufacturing \u0026 Wholesale Goods"
      }
    ],
    "sg:phone": "+1 781 769 2400",
    "sg:postcode": "02062",
    "sg:province": "MA",
    "sg:tags": [
      "water",
      "equipment",
      "works",
      "supply"
    ],
    "sg:website": "www.stilesco.com",
    "wof:name": "Stiles Co Inc",
    "wof:placetype": "venue"
  },
  "geometry": {"coordinates":[-71.204392,42.169334],"type":"Point"}
}
