{
  "type": "Feature",
  "properties": {
    "iso:country":"US",
    "sg:address":"922 Pleasant St",
    "sg:city":"Norwood",
    "sg:classifiers":[
        {
            "category":"Manufacturing",
            "subcategory":"Tools & Machinery",
            "type":"Manufacturing & Wholesale Goods"
        }
    ],
    "sg:phone":"+1 781 769 2400",
    "sg:postcode":"02062",
    "sg:province":"MA",
    "sg:tags":[
        "water",
        "equipment",
        "works",
        "supply"
    ],
    "sg:website":"www.stilesco.com",
    "wof:name":"Stiles Co Inc",
    "wof:placetype":"venue"
},
  "geometry": {"coordinates":[-71.204392,42.169334],"type":"Point"}
}