{
  "type": "Feature",
  "properties": {
    "addr:full":"550 Lincoln Ave Saugus MA 01906",
    "addr:housenumber":"550",
    "addr:postcode":"01906",
    "addr:street":"Lincoln Ave",
    "iso:country":"US",
    "sg:address":"550 Lincoln Ave",
    "sg:city":"Saugus",
    "sg:classifiers":[
        {
            "category":"Retail",
            "subcategory":"Auto Repair",
            "type":"Services"
        }
    ],
    "sg:phone":"+1 781 233 7627",
    "sg:postcode":"01906",
    "sg:province":"MA",
    "sg:tags":[
        "body",
        "automobile",
        "painting"
    ],
    "sg:website":"www.amiconeautobody.com",
    "wof:name":"Amicone Auto Body",
    "wof:placetype":"venue"
},
  "geometry": {"coordinates":[-71.01039900000001,42.4478],"type":"Point"}
}