{
  "type": "Feature",
  "properties": {
    "addr:full":"36 Trapelo Rd Belmont MA 02478",
    "addr:housenumber":"36",
    "addr:postcode":"02478",
    "addr:street":"Trapelo Rd",
    "iso:country":"US",
    "sg:address":"36 Trapelo Rd",
    "sg:city":"Belmont",
    "sg:classifiers":[
        {
            "category":"Retail",
            "subcategory":"Funeral Services",
            "type":"Services"
        }
    ],
    "sg:phone":"+1 617 484 2534",
    "sg:postcode":"02478",
    "sg:province":"MA",
    "sg:tags":[
        "director"
    ],
    "wof:name":"Brown & Sons",
    "wof:placetype":"venue"
},
  "geometry": {"coordinates":[-71.171404,42.378701],"type":"Point"}
}