{
  "type": "Feature",
  "properties": {
    "addr:full": "55 Linden St Pittsfield MA 01201",
    "addr:housenumber": "55",
    "addr:postcode": "01201",
    "addr:street": "Linden St",
    "iso:country": "US",
    "sg:address": "55 Linden St",
    "sg:city": "Pittsfield",
    "sg:classifiers": [
      {
        "category": "Organizations",
        "subcategory": "Community Association",
        "type": "Services"
      }
    ],
    "sg:phone": "+1 413 447 9214",
    "sg:postcode": "01201",
    "sg:province": "MA",
    "sg:tags": [
      "club"
    ],
    "wof:name": "Polish Community Club",
    "wof:placetype": "venue"
  },
  "geometry": {"coordinates":[-73.255103,42.455883],"type":"Point"}
}
