{
  "type": "Feature",
  "properties": {
    "iso:country":"US",
    "sg:address":"55 Linden St",
    "sg:city":"Pittsfield",
    "sg:classifiers":[
        {
            "category":"Organizations",
            "subcategory":"Community Association",
            "type":"Services"
        }
    ],
    "sg:phone":"+1 413 447 9214",
    "sg:postcode":"01201",
    "sg:province":"MA",
    "sg:tags":[
        "club"
    ],
    "wof:name":"Polish Community Club",
    "wof:placetype":"venue"
},
  "geometry": {"coordinates":[-73.25510300000001,42.455883],"type":"Point"}
}