{
  "type": "Feature",
  "properties": {
    "addr:full": "200 N Cary St Brockton MA 02302",
    "addr:housenumber": "200",
    "addr:postcode": "02302",
    "addr:street": "N Cary St",
    "iso:country": "US",
    "sg:address": "200 N Cary St",
    "sg:city": "Brockton",
    "sg:classifiers": [
      {
        "category": "Wholesale",
        "subcategory": "Scrap",
        "type": "Manufacturing \u0026 Wholesale Goods"
      }
    ],
    "sg:phone": "+1 508 588 1620",
    "sg:postcode": "02302",
    "sg:province": "MA",
    "sg:tags": [
      "recycling",
      "center"
    ],
    "wof:name": "City Shredding Corp",
    "wof:placetype": "venue"
  },
  "geometry": {"coordinates":[-71.006868,42.093869],"type":"Point"}
}
