{
  "type": "Feature",
  "properties": {
    "addr:full": "100 Huntington Ave Boston MA 02116",
    "addr:housenumber": "100",
    "addr:postcode": "02116",
    "addr:street": "Huntington Ave",
    "iso:country": "US",
    "sg:address": "100 Huntington Ave",
    "sg:city": "Boston",
    "sg:classifiers": [
      {
        "category": "Real Estate",
        "subcategory": "Real Estate Services",
        "type": "Services"
      }
    ],
    "sg:phone": "+1 617 578 9800",
    "sg:postcode": "02116",
    "sg:province": "MA",
    "sg:tags": [
      "management",
      "property"
    ],
    "wof:name": "Bobson Realty Trust",
    "wof:placetype": "venue"
  },
  "geometry": {"coordinates":[-71.078905,42.347474],"type":"Point"}
}
