{
  "type": "Feature",
  "properties": {
    "iso:country":"US",
    "sg:address":"287 Feeding Hills Rd",
    "sg:city":"Southwick",
    "sg:classifiers":[
        {
            "category":"Wholesale",
            "subcategory":"Office Equipment",
            "type":"Manufacturing & Wholesale Goods"
        }
    ],
    "sg:phone":"+1   ",
    "sg:postcode":"01077",
    "sg:province":"MA",
    "wof:name":"A & L Distributing",
    "wof:placetype":"venue"
},
  "geometry": {"coordinates":[-72.719007,42.063615],"type":"Point"}
}