{
  "type": "Feature",
  "properties": {
    "iso:country":"US",
    "sg:address":"196 South St",
    "sg:city":"Foxboro",
    "sg:classifiers":[
        {
            "category":"Education",
            "subcategory":"School",
            "type":"Public Place"
        }
    ],
    "sg:phone":"+1 508 543 1607",
    "sg:postcode":"02035",
    "sg:province":"MA",
    "wof:name":"Charles G Taylor School",
    "wof:placetype":"venue"
},
  "geometry": {"coordinates":[-71.255561,42.049001],"type":"Point"}
}