{
  "type": "Feature",
  "properties": {
    "addr:full": "196 South St Foxboro MA 02035",
    "addr:housenumber": "196",
    "addr:postcode": "02035",
    "addr:street": "South St",
    "iso:country": "US",
    "sg:address": "196 South St",
    "sg:city": "Foxboro",
    "sg:classifiers": [
      {
        "category": "Education",
        "subcategory": "School",
        "type": "Public Place"
      }
    ],
    "sg:phone": "+1 508 543 1607",
    "sg:postcode": "02035",
    "sg:province": "MA",
    "wof:name": "Charles G Taylor School",
    "wof:placetype": "venue"
  },
  "geometry": {"coordinates":[-71.255561,42.049001],"type":"Point"}
}
