{
  "type": "Feature",
  "properties": {
    "iso:country":"US",
    "sg:address":"51 E Main St",
    "sg:city":"Milford",
    "sg:classifiers":[
        {
            "category":"Retail",
            "subcategory":"Auto Repair",
            "type":"Services"
        }
    ],
    "sg:phone":"+1 508 478 8400",
    "sg:postcode":"01757",
    "sg:province":"MA",
    "sg:tags":[
        "repairing",
        "automobile"
    ],
    "wof:name":"ALT Automotive",
    "wof:placetype":"venue"
},
  "geometry": {"coordinates":[-71.511955,42.145685],"type":"Point"}
}