{
  "type": "Feature",
  "properties": {
    "iso:country":"US",
    "sg:address":"448 Highland Ave",
    "sg:city":"Salem",
    "sg:classifiers":[
        {
            "category":"Shopping",
            "subcategory":"Shoes",
            "type":"Retail Goods"
        }
    ],
    "sg:phone":"+1 978 741 3444",
    "sg:postcode":"01970",
    "sg:province":"MA",
    "wof:name":"Mortt's Shoe Store",
    "wof:placetype":"venue"
},
  "geometry": {"coordinates":[-70.934602,42.492919],"type":"Point"}
}