{
  "type": "Feature",
  "properties": {
    "addr:full":"271 Mount Auburn St Watertown MA 02472",
    "addr:housenumber":"271",
    "addr:postcode":"02472",
    "addr:street":"Mount Auburn St",
    "iso:country":"US",
    "sg:address":"271 Mount Auburn St",
    "sg:city":"Watertown",
    "sg:classifiers":[
        {
            "category":"Arts & Performance",
            "subcategory":"Theater",
            "type":"Entertainment"
        }
    ],
    "sg:phone":"+1   ",
    "sg:postcode":"02472",
    "sg:province":"MA",
    "sg:tags":[
        "group"
    ],
    "wof:name":"Flying Monkey Entertainment",
    "wof:placetype":"venue"
},
  "geometry": {"coordinates":[-71.173242,42.36935],"type":"Point"}
}