{
  "type": "Feature",
  "properties": {
    "iso:country":"US",
    "sg:address":"25 Ferrecchia Dr",
    "sg:city":"Marlborough",
    "sg:classifiers":[
        {
            "category":"Building & Trades",
            "subcategory":"Pest Control",
            "type":"Services"
        }
    ],
    "sg:phone":"+1 508 485 3721",
    "sg:postcode":"01752",
    "sg:province":"MA",
    "wof:name":"Marlboro Pest Control Co",
    "wof:placetype":"venue"
},
  "geometry": {"coordinates":[-71.581256,42.345642],"type":"Point"}
}