{
  "type": "Feature",
  "properties": {
    "addr:full": "123 Hawley St Northampton MA 01060",
    "addr:housenumber": "123",
    "addr:postcode": "01060",
    "addr:street": "Hawley St",
    "iso:country": "US",
    "sg:address": "123 Hawley St",
    "sg:city": "Northampton",
    "sg:classifiers": [
      {
        "category": "Building \u0026 Trades",
        "subcategory": "Construction",
        "type": "Services"
      }
    ],
    "sg:phone": "+1 413 584 4087",
    "sg:postcode": "01060",
    "sg:province": "MA",
    "sg:tags": [
      "contractor"
    ],
    "wof:name": "Scott Houle Drywall \u0026 Plaster",
    "wof:placetype": "venue"
  },
  "geometry": {"coordinates":[-72.624562,42.31773],"type":"Point"}
}
