{
  "type": "Feature",
  "properties": {
    "addr:full": "60 Canterbury St Andover MA 01810",
    "addr:housenumber": "60",
    "addr:postcode": "01810",
    "addr:street": "Canterbury St",
    "iso:country": "US",
    "ovtr:label": "Andover Country Club, 60 Canterbury St Andover MA US",
    "ovtr:similarity": 3.0440030097961426,
    "sg:address": "60 Canterbury St",
    "sg:city": "Andover",
    "sg:classifiers": [
      {
        "category": "Recreation",
        "type": "Entertainment"
      }
    ],
    "sg:phone": "+1 978 475 1263",
    "sg:postcode": "01810",
    "sg:province": "MA",
    "sg:tags": [
      "course",
      "golf"
    ],
    "sg:website": "www.andovercountryclub.com",
    "wof:name": "Andover Country Club",
    "wof:placetype": "venue"
  },
  "geometry": {"coordinates":[-71.162494,42.67122],"type":"Point"}
}
