{
  "type": "Feature",
  "properties": {
    "addr:full": "21 Victoria Street Somerville MA 02144",
    "addr:housenumber": "21",
    "addr:postcode": "02144",
    "addr:street": "Victoria Street",
    "iso:country": "US",
    "sg:address": "21 Victoria Street",
    "sg:city": "Somerville",
    "sg:classifiers": [
      {
        "category": "Building \u0026 Trades",
        "subcategory": "Construction",
        "type": "Services"
      }
    ],
    "sg:phone": "+1 617 776 8870",
    "sg:postcode": "02144",
    "sg:province": "MA",
    "sg:tags": [
      "roofing"
    ],
    "wof:name": "Castle Slate Roofing Company",
    "wof:placetype": "venue"
  },
  "geometry": {"coordinates":[-71.131404,42.405088],"type":"Point"}
}
