{
  "type": "Feature",
  "properties": {
    "iso:country":"US",
    "sg:address":"71 Center St",
    "sg:city":"Fairhaven",
    "sg:classifiers":[
        {
            "category":"Social Services",
            "subcategory":"Job Training",
            "type":"Services"
        },
        {
            "category":"Health Services",
            "subcategory":"Health Practitioner",
            "type":"Services"
        }
    ],
    "sg:phone":"+1 508 999 4561",
    "sg:postcode":"02719",
    "sg:province":"MA",
    "sg:tags":[
        "nursing",
        "homes-skilled",
        "facility",
        "addiction-information",
        "treatment",
        "gambling"
    ],
    "wof:name":"Our Lady's Haven Of Fairhaven Inc",
    "wof:placetype":"venue"
},
  "geometry": {"coordinates":[-70.900632,41.636246],"type":"Point"}
}