{
  "type": "Feature",
  "properties": {
    "addr:full": "10 Commerce Way Norton MA 02766",
    "addr:housenumber": "10",
    "addr:postcode": "02766",
    "addr:street": "Commerce Way",
    "iso:country": "US",
    "ovtr:label": "Morton Buildings, Inc., 10 Commerce Way Norton MA US",
    "ovtr:similarity": 3.2198400497436523,
    "sg:address": "10 Commerce Way",
    "sg:city": "Norton",
    "sg:classifiers": [
      {
        "category": "Building \u0026 Trades",
        "subcategory": "Construction",
        "type": "Services"
      }
    ],
    "sg:phone": "+1 508 285 2718",
    "sg:postcode": "02766",
    "sg:province": "MA",
    "sg:tags": [
      "contractor"
    ],
    "sg:website": "www.mortonbuildings.com",
    "wof:name": "Morton Buildings Inc",
    "wof:placetype": "venue"
  },
  "geometry": {"coordinates":[-71.134903,41.960701],"type":"Point"}
}
