{
  "type": "Feature",
  "properties": {
    "addr:full":"46 Donelle Way Lancaster MA 01523",
    "addr:housenumber":"46",
    "addr:postcode":"01523",
    "addr:street":"Donelle Way",
    "iso:country":"US",
    "sg:address":"46 Donelle Way",
    "sg:city":"Lancaster",
    "sg:classifiers":[
        {
            "category":"Real Estate",
            "subcategory":"Real Estate Agent",
            "type":"Services"
        }
    ],
    "sg:phone":"+1 978 534 3352",
    "sg:postcode":"01523",
    "sg:province":"MA",
    "wof:name":"Home Connection",
    "wof:placetype":"venue"
},
  "geometry": {"coordinates":[-71.683701,42.529863],"type":"Point"}
}