{
  "type": "Feature",
  "properties": {
    "addr:full":"5 Old James St Chicopee MA 01020",
    "addr:housenumber":"5",
    "addr:postcode":"01020",
    "addr:street":"Old James St",
    "iso:country":"US",
    "sg:address":"5 Old James St",
    "sg:city":"Chicopee",
    "sg:classifiers":[
        {
            "category":"Shopping",
            "subcategory":"Pharmacy",
            "type":"Retail Goods"
        }
    ],
    "sg:phone":"+1 413 557 1547",
    "sg:postcode":"01020",
    "sg:province":"MA",
    "wof:name":"Brooks Pharmacy",
    "wof:placetype":"venue"
},
  "geometry": {"coordinates":[-72.58609199999999,42.206519],"type":"Point"}
}