{
  "type": "Feature",
  "properties": {
    "addr:full": "20 Waltham St Lexington MA 02420",
    "addr:housenumber": "20",
    "addr:postcode": "02420",
    "addr:street": "Waltham St",
    "iso:country": "US",
    "sg:address": "20 Waltham St",
    "sg:city": "Lexington",
    "sg:classifiers": [
      {
        "category": "Restaurant",
        "type": "Food \u0026 Drink"
      }
    ],
    "sg:phone": "+1 781 861 0162",
    "sg:postcode": "02420",
    "sg:province": "MA",
    "sg:tags": [
      "italian"
    ],
    "sg:website": "bucadibeppo.com",
    "wof:name": "Buca di Beppo",
    "wof:placetype": "venue"
  },
  "geometry": {"coordinates":[-71.22742,42.447024],"type":"Point"}
}
