{
  "type": "Feature",
  "properties": {
    "addr:full": "4 Fairhaven Rd Mattapoisett MA 02739",
    "addr:housenumber": "4",
    "addr:postcode": "02739",
    "addr:street": "Fairhaven Rd",
    "iso:country": "US",
    "sg:address": "4 Fairhaven Rd",
    "sg:city": "Mattapoisett",
    "sg:classifiers": [
      {
        "category": "Recreation",
        "subcategory": "Marina",
        "type": "Entertainment"
      }
    ],
    "sg:phone": "+1 508 758 4224",
    "sg:postcode": "02739",
    "sg:province": "MA",
    "sg:tags": [
      "repairing",
      "repair",
      "maintenance",
      "boat"
    ],
    "sg:website": "http://www.triadboat.com",
    "wof:name": "Triad Boatworks",
    "wof:placetype": "venue"
  },
  "geometry": {"coordinates":[-70.820129,41.66172],"type":"Point"}
}
