{
  "type": "Feature",
  "properties": {
    "iso:country":"US",
    "sg:address":"4 Fairhaven Rd",
    "sg:city":"Mattapoisett",
    "sg:classifiers":[
        {
            "category":"Recreation",
            "subcategory":"Marina",
            "type":"Entertainment"
        }
    ],
    "sg:phone":"+1 508 758 4224",
    "sg:postcode":"02739",
    "sg:province":"MA",
    "sg:tags":[
        "repairing",
        "repair",
        "maintenance",
        "boat"
    ],
    "sg:website":"http://www.triadboat.com",
    "wof:name":"Triad Boatworks",
    "wof:placetype":"venue"
},
  "geometry": {"coordinates":[-70.82012899999999,41.66172],"type":"Point"}
}