{
  "type": "Feature",
  "properties": {
    "addr:full":"241 Mansfield Ave Norton MA 02766",
    "addr:housenumber":"241",
    "addr:postcode":"02766",
    "addr:street":"Mansfield Ave",
    "iso:country":"US",
    "sg:address":"241 Mansfield Ave",
    "sg:city":"Norton",
    "sg:classifiers":[
        {
            "category":"Personal",
            "subcategory":"Beauty Salon",
            "type":"Services"
        }
    ],
    "sg:phone":"+1 508 285 7066",
    "sg:postcode":"02766",
    "sg:province":"MA",
    "wof:name":"Celebrations Hair Salon",
    "wof:placetype":"venue"
},
  "geometry": {"coordinates":[-71.210544,41.987321],"type":"Point"}
}