{
  "type": "Feature",
  "properties": {
    "addr:full": "100 Summer St Boston MA 02110",
    "addr:housenumber": "100",
    "addr:postcode": "02110",
    "addr:street": "Summer St",
    "iso:country": "US",
    "sg:address": "100 Summer St",
    "sg:city": "Boston",
    "sg:classifiers": [
      {
        "category": "Professional",
        "subcategory": "Lawyer \u0026 Legal Services",
        "type": "Services"
      }
    ],
    "sg:phone": "+1 617 426 5720",
    "sg:postcode": "02110",
    "sg:province": "MA",
    "wof:name": "Reed John M Lwyr",
    "wof:placetype": "venue"
  },
  "geometry": {"coordinates":[-71.057999,42.353802],"type":"Point"}
}
