{
  "type": "Feature",
  "properties": {
    "iso:country":"US",
    "sg:address":"2025 Roosevelt Ave",
    "sg:city":"Springfield",
    "sg:classifiers":[
        {
            "category":"Building & Trades",
            "subcategory":"Construction",
            "type":"Services"
        },
        {
            "category":"Utilities",
            "subcategory":"Natural Gas",
            "type":"Services"
        }
    ],
    "sg:phone":"+1 413 781 9200",
    "sg:postcode":"01104",
    "sg:province":"MA",
    "sg:tags":[
        "specialty",
        "system",
        "heating",
        "contractor",
        "air conditioning"
    ],
    "sg:website":"http://www.baystategas.com",
    "wof:name":"Bay State Gas Company",
    "wof:placetype":"venue"
},
  "geometry": {"coordinates":[-72.546763,42.136541],"type":"Point"}
}