{
  "type": "Feature",
  "properties": {
    "iso:country":"US",
    "sg:address":"143 Pratts Junction Rd",
    "sg:city":"Sterling",
    "sg:classifiers":[
        {
            "category":"Building & Trades",
            "subcategory":"Plumbing",
            "type":"Services"
        }
    ],
    "sg:phone":"+1 978 422 7474",
    "sg:postcode":"01564",
    "sg:province":"MA",
    "sg:tags":[
        "septic"
    ],
    "wof:name":"Best Sanitation Inc",
    "wof:placetype":"venue"
},
  "geometry": {"coordinates":[-71.737059,42.458913],"type":"Point"}
}