{
  "type": "Feature",
  "properties": {
    "addr:full": "219 New Boston St Woburn MA 01801",
    "addr:housenumber": "219",
    "addr:postcode": "01801",
    "addr:street": "New Boston St",
    "iso:country": "US",
    "sg:address": "219 New Boston St",
    "sg:city": "Woburn",
    "sg:classifiers": [
      {
        "category": "Building \u0026 Trades",
        "subcategory": "Locksmith",
        "type": "Services"
      }
    ],
    "sg:phone": "+1 781 904 0324",
    "sg:postcode": "01801",
    "sg:province": "MA",
    "sg:tags": [
      "key"
    ],
    "wof:name": "A 24 Hour Emergency Locksmith",
    "wof:placetype": "venue"
  },
  "geometry": {"coordinates":[-71.145562,42.517387],"type":"Point"}
}
