{
  "type": "Feature",
  "properties": {
    "iso:country":"US",
    "sg:address":"219 New Boston St",
    "sg:city":"Woburn",
    "sg:classifiers":[
        {
            "category":"Building & Trades",
            "subcategory":"Locksmith",
            "type":"Services"
        }
    ],
    "sg:phone":"+1 781 904 0324",
    "sg:postcode":"01801",
    "sg:province":"MA",
    "sg:tags":[
        "key"
    ],
    "wof:name":"A 24 Hour Emergency Locksmith",
    "wof:placetype":"venue"
},
  "geometry": {"coordinates":[-71.145562,42.517387],"type":"Point"}
}