{
  "type": "Feature",
  "properties": {
    "addr:full":"354 Washington St Stoughton MA 02072",
    "addr:housenumber":"354",
    "addr:postcode":"02072",
    "addr:street":"Washington St",
    "iso:country":"US",
    "sg:address":"354 Washington St",
    "sg:city":"Stoughton",
    "sg:classifiers":[
        {
            "category":"Wholesale",
            "subcategory":"Home Furnishings",
            "type":"Manufacturing & Wholesale Goods"
        }
    ],
    "sg:phone":"+1 781 344 1122",
    "sg:postcode":"02072",
    "sg:province":"MA",
    "sg:tags":[
        "blind",
        "shade"
    ],
    "wof:name":"Verticals Etc Factory Outlet",
    "wof:placetype":"venue"
},
  "geometry": {"coordinates":[-71.101997,42.136101],"type":"Point"}
}