{
  "type": "Feature",
  "properties": {
    "addr:full":"240 Onset Ave Onset MA 02558",
    "addr:housenumber":"240",
    "addr:postcode":"02558",
    "addr:street":"Onset Ave",
    "iso:country":"US",
    "sg:address":"240 Onset Ave",
    "sg:city":"Onset",
    "sg:classifiers":[
        {
            "category":"Government",
            "subcategory":"Fire Station",
            "type":"Public Place"
        }
    ],
    "sg:phone":"+1 508 295 6090",
    "sg:postcode":"02558",
    "sg:province":"MA",
    "sg:tags":[
        "department"
    ],
    "wof:name":"Onset Fire District",
    "wof:placetype":"venue"
},
  "geometry": {"coordinates":[-70.66091900000001,41.743253],"type":"Point"}
}