{
  "type": "Feature",
  "properties": {
    "addr:full":"700 Broadway St Lowell MA 01854",
    "addr:housenumber":"700",
    "addr:postcode":"01854",
    "addr:street":"Broadway St",
    "iso:country":"US",
    "sg:address":"700 Broadway St",
    "sg:city":"Lowell",
    "sg:classifiers":[
        {
            "category":"Wholesale",
            "subcategory":"Machinery & Supplies",
            "type":"Manufacturing & Wholesale Goods"
        }
    ],
    "sg:phone":"+1 978 454 7392",
    "sg:postcode":"01854",
    "sg:province":"MA",
    "sg:tags":[
        "equipment",
        "industrial"
    ],
    "wof:name":"Don Kennett Inc",
    "wof:placetype":"venue"
},
  "geometry": {"coordinates":[-71.328603,42.642768],"type":"Point"}
}