{
  "type": "Feature",
  "properties": {
    "addr:full":"75 North Dr Westborough MA 01581",
    "addr:housenumber":"75",
    "addr:postcode":"01581",
    "addr:street":"North Dr",
    "iso:country":"US",
    "sg:address":"75 North Dr",
    "sg:city":"Westborough",
    "sg:classifiers":[
        {
            "category":"Government",
            "subcategory":"Office",
            "type":"Public Place"
        }
    ],
    "sg:phone":"+1 508 792 7270",
    "sg:postcode":"01581",
    "sg:province":"MA",
    "sg:tags":[
        "state"
    ],
    "wof:name":"Fisheries & Game Div",
    "wof:placetype":"venue"
},
  "geometry": {"coordinates":[-71.631409,42.289401],"type":"Point"}
}