{
  "type": "Feature",
  "properties": {
    "iso:country":"US",
    "sg:address":"25 Oceanview Way",
    "sg:city":"Winthrop",
    "sg:classifiers":[
        {
            "category":"Personal",
            "type":"Services"
        }
    ],
    "sg:phone":"+1   ",
    "sg:postcode":"02152",
    "sg:province":"MA",
    "wof:name":"Anne C Zolla Electrologist",
    "wof:placetype":"venue"
},
  "geometry": {"coordinates":[-70.982449,42.378537],"type":"Point"}
}