{
  "type": "Feature",
  "properties": {
    "addr:full":"622 Carew St Springfield MA 01104",
    "addr:housenumber":"622",
    "addr:postcode":"01104",
    "addr:street":"Carew St",
    "iso:country":"US",
    "sg:address":"622 Carew St",
    "sg:city":"Springfield",
    "sg:classifiers":[
        {
            "category":"Restaurant",
            "type":"Food & Drink"
        }
    ],
    "sg:phone":"+1 413 732 8900",
    "sg:postcode":"01104",
    "sg:province":"MA",
    "wof:name":"El Pilon Restaurant",
    "wof:placetype":"venue"
},
  "geometry": {"coordinates":[-72.58797800000001,42.122525],"type":"Point"}
}