{
  "type": "Feature",
  "properties": {
    "addr:full": "845 Church St New Bedford MA 02745",
    "addr:housenumber": "845",
    "addr:postcode": "02745",
    "addr:street": "Church St",
    "iso:country": "US",
    "ovtr:label": "South Coast Towing, 847 Church St New Bedford MA US",
    "ovtr:similarity": 1.9608370065689087,
    "sg:address": "845 Church St",
    "sg:city": "New Bedford",
    "sg:classifiers": [
      {
        "category": "Retail",
        "subcategory": "Auto Repair",
        "type": "Services"
      }
    ],
    "sg:phone": "+1 508 995 9777",
    "sg:postcode": "02745",
    "sg:province": "MA",
    "sg:tags": [
      "road"
    ],
    "wof:name": "South Coast Towing",
    "wof:placetype": "venue"
  },
  "geometry": {"coordinates":[-70.941307,41.692419],"type":"Point"}
}
