{
  "type": "Feature",
  "properties": {
    "iso:country":"US",
    "sg:address":"4 Carroll Rd",
    "sg:city":"North Grafton",
    "sg:classifiers":[
        {
            "category":"Building & Trades",
            "subcategory":"Landscaping Services",
            "type":"Services"
        }
    ],
    "sg:phone":"+1 508 839 2929",
    "sg:postcode":"01536",
    "sg:province":"MA",
    "wof:name":"New England Design Group",
    "wof:placetype":"venue"
},
  "geometry": {"coordinates":[-71.69088000000001,42.213992],"type":"Point"}
}