{
  "type": "Feature",
  "properties": {
    "iso:country":"US",
    "sg:address":"18 Hancock St",
    "sg:city":"Salem",
    "sg:classifiers":[
        {
            "category":"Professional",
            "subcategory":"Business Services",
            "type":"Services"
        }
    ],
    "sg:phone":"+1   ",
    "sg:postcode":"01970",
    "sg:province":"MA",
    "wof:name":"Weinbaum Designs",
    "wof:placetype":"venue"
},
  "geometry": {"coordinates":[-70.89433,42.512805],"type":"Point"}
}