{
  "type": "Feature",
  "properties": {
    "addr:full":"2 Captain Harris Dr Assonet MA 02702",
    "addr:housenumber":"2",
    "addr:postcode":"02702",
    "addr:street":"Captain Harris Dr",
    "iso:country":"US",
    "sg:address":"2 Captain Harris Dr",
    "sg:city":"Assonet",
    "sg:classifiers":[
        {
            "category":"Professional",
            "subcategory":"Lawyer & Legal Services",
            "type":"Services"
        }
    ],
    "sg:phone":"+1 508 644 3003",
    "sg:postcode":"02702",
    "sg:province":"MA",
    "sg:tags":[
        "attorney"
    ],
    "wof:name":"John W Mac Sweeney Esq LLC",
    "wof:placetype":"venue"
},
  "geometry": {"coordinates":[-71.10122699999999,41.789297],"type":"Point"}
}