{
  "type": "Feature",
  "properties": {
    "addr:full": "446 Station Ave South Yarmouth MA 02664",
    "addr:housenumber": "446",
    "addr:postcode": "02664",
    "addr:street": "Station Ave",
    "iso:country": "US",
    "sg:address": "446 Station Ave",
    "sg:city": "South Yarmouth",
    "sg:classifiers": [
      {
        "category": "Autos \u0026 Motor Vehicles",
        "subcategory": "Fuel \u0026 Gas Station",
        "type": "Retail Goods"
      }
    ],
    "sg:phone": "+1 508 398 2337",
    "sg:postcode": "02664",
    "sg:province": "MA",
    "sg:tags": [
      "oil"
    ],
    "wof:name": "Station Avenue Shell",
    "wof:placetype": "venue"
  },
  "geometry": {"coordinates":[-70.207436,41.684669],"type":"Point"}
}
