{
  "type": "Feature",
  "properties": {
    "iso:country":"US",
    "sg:address":"446 Station Ave",
    "sg:city":"South Yarmouth",
    "sg:classifiers":[
        {
            "category":"Autos & Motor Vehicles",
            "subcategory":"Fuel & Gas Station",
            "type":"Retail Goods"
        }
    ],
    "sg:phone":"+1 508 398 2337",
    "sg:postcode":"02664",
    "sg:province":"MA",
    "sg:tags":[
        "oil"
    ],
    "wof:name":"Station Avenue Shell",
    "wof:placetype":"venue"
},
  "geometry": {"coordinates":[-70.207436,41.684669],"type":"Point"}
}