{
  "type": "Feature",
  "properties": {
    "addr:full": "3 Foundry Industrial Park Lowell MA 01852",
    "addr:housenumber": "3",
    "addr:postcode": "01852",
    "addr:street": "Foundry Industrial Park",
    "iso:country": "US",
    "sg:address": "3 Foundry Industrial Park",
    "sg:city": "Lowell",
    "sg:classifiers": [
      {
        "category": "Real Estate",
        "subcategory": "Real Estate Agent",
        "type": "Services"
      }
    ],
    "sg:phone": "+1 978 454 0785",
    "sg:postcode": "01852",
    "sg:province": "MA",
    "wof:name": "Frontier Development",
    "wof:placetype": "venue"
  },
  "geometry": {"coordinates":[-71.315408,42.623032],"type":"Point"}
}
