{
  "type": "Feature",
  "properties": {
    "iso:country":"US",
    "sg:address":"1 Porter Sq",
    "sg:city":"Cambridge",
    "sg:classifiers":[
        {
            "category":"Shopping",
            "subcategory":"Mobile Phones",
            "type":"Retail Goods"
        }
    ],
    "sg:phone":"+1 617 349 3555",
    "sg:postcode":"02140",
    "sg:province":"MA",
    "wof:name":"Cingular Wireless",
    "wof:placetype":"venue"
},
  "geometry": {"coordinates":[-71.11991399999999,42.389193],"type":"Point"}
}