{
  "type": "Feature",
  "properties": {
    "iso:country":"US",
    "sg:address":"532 Parker St",
    "sg:city":"Roxbury Crossing",
    "sg:classifiers":[
        {
            "category":"Building & Trades",
            "subcategory":"Locksmith",
            "type":"Services"
        }
    ],
    "sg:phone":"+1 617 652 9083",
    "sg:postcode":"02120",
    "sg:province":"MA",
    "sg:tags":[
        "key"
    ],
    "wof:name":"Locksmith On Parker 24 A Day 123 Emergency",
    "wof:placetype":"venue"
},
  "geometry": {"coordinates":[-71.09418100000001,42.335752],"type":"Point"}
}