{
  "type": "Feature",
  "properties": {
    "addr:full": "532 Parker St Roxbury Crossing MA 02120",
    "addr:housenumber": "532",
    "addr:postcode": "02120",
    "addr:street": "Parker St",
    "iso:country": "US",
    "sg:address": "532 Parker St",
    "sg:city": "Roxbury Crossing",
    "sg:classifiers": [
      {
        "category": "Building \u0026 Trades",
        "subcategory": "Locksmith",
        "type": "Services"
      }
    ],
    "sg:phone": "+1 617 652 9083",
    "sg:postcode": "02120",
    "sg:province": "MA",
    "sg:tags": [
      "key"
    ],
    "wof:name": "Locksmith On Parker 24 A Day 123 Emergency",
    "wof:placetype": "venue"
  },
  "geometry": {"coordinates":[-71.094181,42.335752],"type":"Point"}
}
