{
  "type": "Feature",
  "properties": {
    "addr:full":"375 S Ashburnham Rd Westminster MA 01473",
    "addr:housenumber":"375",
    "addr:postcode":"01473",
    "addr:street":"S Ashburnham Rd",
    "iso:country":"US",
    "sg:address":"375 S Ashburnham Rd",
    "sg:city":"Westminster",
    "sg:classifiers":[
        {
            "category":"Building & Trades",
            "subcategory":"Plumbing",
            "type":"Services"
        }
    ],
    "sg:phone":"+1 978 874 1750",
    "sg:postcode":"01473",
    "sg:province":"MA",
    "sg:tags":[
        "plumbing",
        "contractor"
    ],
    "wof:name":"Chevarie Plumbing & Heating",
    "wof:placetype":"venue"
},
  "geometry": {"coordinates":[-71.910106,42.597721],"type":"Point"}
}