{
  "type": "Feature",
  "properties": {
    "addr:full": "101 Mystic Ave Medford MA 02155",
    "addr:housenumber": "101",
    "addr:postcode": "02155",
    "addr:street": "Mystic Ave",
    "iso:country": "US",
    "sg:address": "101 Mystic Ave",
    "sg:city": "Medford",
    "sg:classifiers": [
      {
        "category": "Real Estate",
        "subcategory": "Real Estate Services",
        "type": "Services"
      }
    ],
    "sg:phone": "+1 339 221 5412",
    "sg:postcode": "02155",
    "sg:province": "MA",
    "sg:website": "www.cosmopolitanrealestate.net/",
    "wof:name": "Cosmopolitan Real Estate",
    "wof:placetype": "venue"
  },
  "geometry": {"coordinates":[-71.106661,42.411106],"type":"Point"}
}
