{
  "type": "Feature",
  "properties": {
    "iso:country":"US",
    "sg:address":"64 Willow Rd",
    "sg:city":"Littleton",
    "sg:classifiers":[
        {
            "category":"Professional",
            "subcategory":"Lawyer & Legal Services",
            "type":"Services"
        }
    ],
    "sg:phone":"+1 978 772 7888",
    "sg:postcode":"01432",
    "sg:province":"MA",
    "sg:tags":[
        "attorney"
    ],
    "wof:name":"Steven P Cormey",
    "wof:placetype":"venue"
},
  "geometry": {"coordinates":[-71.536293,42.551925],"type":"Point"}
}