{
  "type": "Feature",
  "properties": {
    "addr:full": "194 Rockdale Ave New Bedford MA 02740",
    "addr:housenumber": "194",
    "addr:postcode": "02740",
    "addr:street": "Rockdale Ave",
    "iso:country": "US",
    "ovtr:label": "Hawaiian Island Tanning, 194 Rockdale Ave New Bedford MA US",
    "ovtr:similarity": 1.848418951034546,
    "sg:address": "194 Rockdale Ave",
    "sg:city": "New Bedford",
    "sg:classifiers": [
      {
        "category": "Personal",
        "subcategory": "Piercing",
        "type": "Services"
      }
    ],
    "sg:phone": "+1 508 999 4468",
    "sg:postcode": "02740",
    "sg:province": "MA",
    "sg:tags": [
      "body"
    ],
    "wof:name": "Hawaiian Island Tanning",
    "wof:placetype": "venue"
  },
  "geometry": {"coordinates":[-70.938359,41.615525],"type":"Point"}
}
