{
  "type": "Feature",
  "properties": {
    "iso:country":"US",
    "sg:address":"194 Rockdale Ave",
    "sg:city":"New Bedford",
    "sg:classifiers":[
        {
            "category":"Personal",
            "subcategory":"Piercing",
            "type":"Services"
        }
    ],
    "sg:phone":"+1 508 999 4468",
    "sg:postcode":"02740",
    "sg:province":"MA",
    "sg:tags":[
        "body"
    ],
    "wof:name":"Hawaiian Island Tanning",
    "wof:placetype":"venue"
},
  "geometry": {"coordinates":[-70.93835900000001,41.615525],"type":"Point"}
}