{
  "type": "Feature",
  "properties": {
    "iso:country":"US",
    "sg:address":"1551 Russell Rd",
    "sg:city":"Montgomery",
    "sg:classifiers":[
        {
            "category":"Building & Trades",
            "subcategory":"Construction",
            "type":"Services"
        }
    ],
    "sg:phone":"+1 413 862 3645",
    "sg:postcode":"01085",
    "sg:province":"MA",
    "sg:tags":[
        "excavating",
        "contractor"
    ],
    "wof:name":"Bush Brothers Inc",
    "wof:placetype":"venue"
},
  "geometry": {"coordinates":[-72.816103,42.20353],"type":"Point"}
}