{
  "type": "Feature",
  "properties": {
    "addr:full":"322 Merrimack St Methuen MA 01844",
    "addr:housenumber":"322",
    "addr:postcode":"01844",
    "addr:street":"Merrimack St",
    "iso:country":"US",
    "sg:address":"322 Merrimack St",
    "sg:city":"Methuen",
    "sg:phone":"+1 978 687 2306",
    "sg:postcode":"01844",
    "sg:province":"MA",
    "sg:website":"http://www.borrellisdeli.com",
    "wof:name":"Borrelli's Italian Delicatessen",
    "wof:placetype":"venue"
},
  "geometry": {"coordinates":[-71.130882,42.743439],"type":"Point"}
}