{
  "type": "Feature",
  "properties": {
    "addr:full":"8 Burek's Cross Rd Sunderland MA 01375",
    "addr:housenumber":"8",
    "addr:postcode":"01375",
    "addr:street":"Burek'S Cross Rd",
    "iso:country":"US",
    "sg:address":"8 Burek's Cross Rd",
    "sg:city":"Sunderland",
    "sg:classifiers":[
        {
            "category":"Professional",
            "subcategory":"Business Services",
            "type":"Services"
        }
    ],
    "sg:phone":"+1 413 665 4773",
    "sg:postcode":"01375",
    "sg:province":"MA",
    "wof:name":"Fyden Home Inspections",
    "wof:placetype":"venue"
},
  "geometry": {"coordinates":[-72.57596700000001,42.433527],"type":"Point"}
}