{
  "type": "Feature",
  "properties": {
    "iso:country":"US",
    "sg:address":"62 Main St",
    "sg:city":"Harwich",
    "sg:classifiers":[
        {
            "category":"Freight",
            "type":"Transportation"
        }
    ],
    "sg:phone":"+1 508 430 4141",
    "sg:postcode":"02645",
    "sg:province":"MA",
    "sg:tags":[
        "trucking"
    ],
    "wof:name":"Tri-State Transportation Inc",
    "wof:placetype":"venue"
},
  "geometry": {"coordinates":[-70.128377,41.699554],"type":"Point"}
}