{
  "type": "Feature",
  "properties": {
    "iso:country":"US",
    "sg:address":"100 Hoods Lane",
    "sg:city":"Marblehead",
    "sg:classifiers":[
        {
            "category":"Professional",
            "subcategory":"Computer Services",
            "type":"Services"
        }
    ],
    "sg:phone":"+1 781 639 5155",
    "sg:postcode":"01945 ",
    "sg:province":"MA",
    "sg:website":"http://www.homelogic.com/",
    "wof:name":"HomeLogic",
    "wof:placetype":"venue"
},
  "geometry": {"coordinates":[-70.85554999999999,42.509101],"type":"Point"}
}