{
  "type": "Feature",
  "properties": {
    "iso:country":"US",
    "sg:address":"147 Hampshire St",
    "sg:city":"Cambridge",
    "sg:classifiers":[
        {
            "category":"Building & Trades",
            "subcategory":"Construction",
            "type":"Services"
        }
    ],
    "sg:phone":"+1 617 349 4806",
    "sg:postcode":"02139",
    "sg:province":"MA",
    "sg:tags":[
        "marking",
        "maintenance",
        "parking"
    ],
    "wof:name":"Public Works Commissioners Ofc",
    "wof:placetype":"venue"
},
  "geometry": {"coordinates":[-71.098112,42.371494],"type":"Point"}
}