{
  "type": "Feature",
  "properties": {
    "addr:full":"5 Park St North Reading MA 01864",
    "addr:housenumber":"5",
    "addr:postcode":"01864",
    "addr:street":"Park St",
    "iso:country":"US",
    "sg:address":"5 Park St",
    "sg:city":"North Reading",
    "sg:classifiers":[
        {
            "category":"Retail",
            "subcategory":"Repair Shop",
            "type":"Services"
        }
    ],
    "sg:phone":"+1 781 245 7576",
    "sg:postcode":"01864",
    "sg:province":"MA",
    "sg:tags":[
        "grease",
        "trap"
    ],
    "sg:website":"www.servicepumpingdrain.com",
    "wof:name":"Service Pumping & Drain Co Inc",
    "wof:placetype":"venue"
},
  "geometry": {"coordinates":[-71.06619600000001,42.565475],"type":"Point"}
}