{
  "type": "Feature",
  "properties": {
    "iso:country":"US",
    "sg:address":"44 Wycliffe Rd",
    "sg:city":"East Walpole",
    "sg:classifiers":[
        {
            "category":"Shopping",
            "subcategory":"Pets & Pet Supplies",
            "type":"Retail Goods"
        }
    ],
    "sg:phone":"+1 508 254 2085",
    "sg:postcode":"02032",
    "sg:province":"MA",
    "sg:tags":[
        "store"
    ],
    "sg:website":"www.theshooterdog.com",
    "wof:name":"The Shooter Dog",
    "wof:placetype":"venue"
},
  "geometry": {"coordinates":[-71.22315,42.150916],"type":"Point"}
}