{
  "type": "Feature",
  "properties": {
    "iso:country":"US",
    "sg:address":"146 Arnold Rd",
    "sg:city":"Newton",
    "sg:classifiers":[
        {
            "category":"Food & Beverages",
            "subcategory":"Bakery",
            "type":"Retail Goods"
        }
    ],
    "sg:phone":"+1 617 332 7444",
    "sg:postcode":"02459",
    "sg:province":"MA",
    "sg:tags":[
        "bagel"
    ],
    "wof:name":"Bagels Etc",
    "wof:placetype":"venue"
},
  "geometry": {"coordinates":[-71.191906,42.304963],"type":"Point"}
}