{
  "type": "Feature",
  "properties": {
    "iso:country":"US",
    "sg:address":"1735 Turnpike St",
    "sg:city":"Stoughton",
    "sg:classifiers":[
        {
            "category":"Manufacturing",
            "subcategory":"Printing",
            "type":"Manufacturing & Wholesale Goods"
        }
    ],
    "sg:phone":"+1 781 344 2650",
    "sg:postcode":"02072",
    "sg:province":"MA",
    "sg:tags":[
        "printer"
    ],
    "sg:website":"www.rivkind.com",
    "wof:name":"Rivkind Assoc",
    "wof:placetype":"venue"
},
  "geometry": {"coordinates":[-71.072615,42.158423],"type":"Point"}
}