{
  "type": "Feature",
  "properties": {
    "addr:full": "938 Regan Rd Somerset MA 02726",
    "addr:housenumber": "938",
    "addr:postcode": "02726",
    "addr:street": "Regan Rd",
    "iso:country": "US",
    "sg:address": "938 Regan Rd",
    "sg:city": "Somerset",
    "sg:classifiers": [
      {
        "category": "Building \u0026 Trades",
        "subcategory": "Construction",
        "type": "Services"
      }
    ],
    "sg:phone": "+1 508 673 3414",
    "sg:postcode": "02726",
    "sg:province": "MA",
    "sg:tags": [
      "resurfacing",
      "laying",
      "refinishing",
      "floor"
    ],
    "wof:name": "Vanguard Maintenance Svc",
    "wof:placetype": "venue"
  },
  "geometry": {"coordinates":[-71.148903,41.775078],"type":"Point"}
}
