{
  "type": "Feature",
  "properties": {
    "iso:country":"US",
    "sg:address":"938 Regan Rd",
    "sg:city":"Somerset",
    "sg:classifiers":[
        {
            "category":"Building & Trades",
            "subcategory":"Construction",
            "type":"Services"
        }
    ],
    "sg:phone":"+1 508 673 3414",
    "sg:postcode":"02726",
    "sg:province":"MA",
    "sg:tags":[
        "resurfacing",
        "laying",
        "refinishing",
        "floor"
    ],
    "wof:name":"Vanguard Maintenance Svc",
    "wof:placetype":"venue"
},
  "geometry": {"coordinates":[-71.148903,41.775078],"type":"Point"}
}