{
  "type": "Feature",
  "properties": {
    "iso:country":"US",
    "sg:address":"164 Waverley Ave",
    "sg:city":"Watertown",
    "sg:classifiers":[
        {
            "category":"Home & Garden",
            "subcategory":"Building Materials",
            "type":"Retail Goods"
        },
        {
            "category":"Building & Trades",
            "subcategory":"Construction",
            "type":"Services"
        }
    ],
    "sg:phone":"+1 617 926 0031",
    "sg:postcode":"02472",
    "sg:province":"MA",
    "sg:tags":[
        "chimneys-prefabricated",
        "chimney",
        "contractor"
    ],
    "wof:name":"De Felice Rocco",
    "wof:placetype":"venue"
},
  "geometry": {"coordinates":[-71.18876299999999,42.375733],"type":"Point"}
}