{
  "type": "Feature",
  "properties": {
    "iso:country":"US",
    "sg:address":"1371 Hanover St",
    "sg:city":"Hanover",
    "sg:classifiers":[
        {
            "category":"Food & Beverages",
            "subcategory":"Groceries & Convenience Stores",
            "type":"Retail Goods"
        }
    ],
    "sg:phone":"+1 781 871 2125",
    "sg:postcode":"02339",
    "sg:province":"MA",
    "wof:name":"Tedeschi Food Shops",
    "wof:placetype":"venue"
},
  "geometry": {"coordinates":[-70.88064799999999,42.118606],"type":"Point"}
}