{
  "type": "Feature",
  "properties": {
    "addr:full": "1371 Hanover St Hanover MA 02339",
    "addr:housenumber": "1371",
    "addr:postcode": "02339",
    "addr:street": "Hanover St",
    "iso:country": "US",
    "sg:address": "1371 Hanover St",
    "sg:city": "Hanover",
    "sg:classifiers": [
      {
        "category": "Food \u0026 Beverages",
        "subcategory": "Groceries \u0026 Convenience Stores",
        "type": "Retail Goods"
      }
    ],
    "sg:phone": "+1 781 871 2125",
    "sg:postcode": "02339",
    "sg:province": "MA",
    "wof:name": "Tedeschi Food Shops",
    "wof:placetype": "venue"
  },
  "geometry": {"coordinates":[-70.880648,42.118606],"type":"Point"}
}
