{
  "type": "Feature",
  "properties": {
    "iso:country":"US",
    "sg:address":"63 Bailey St",
    "sg:city":"Dorchester Ctr",
    "sg:classifiers":[
        {
            "category":"Organizations",
            "subcategory":"Community Association",
            "type":"Services"
        }
    ],
    "sg:phone":"+1 617 436 8939",
    "sg:postcode":"02124",
    "sg:province":"MA",
    "sg:tags":[
        "club"
    ],
    "wof:name":"Veterans Of Foreign Wars",
    "wof:placetype":"venue"
},
  "geometry": {"coordinates":[-71.064764,42.284742],"type":"Point"}
}