{
  "type": "Feature",
  "properties": {
    "addr:full":"394 Court St Plymouth MA 02360",
    "addr:housenumber":"394",
    "addr:postcode":"02360",
    "addr:street":"Court St",
    "iso:country":"US",
    "sg:address":"394 Court St",
    "sg:city":"Plymouth",
    "sg:classifiers":[
        {
            "category":"Shopping",
            "subcategory":"Clothing, Apparel, & Fashions",
            "type":"Retail Goods"
        }
    ],
    "sg:phone":"+1 508 746 8926",
    "sg:postcode":"02360",
    "sg:province":"MA",
    "sg:tags":[
        "theatrical",
        "costume"
    ],
    "wof:name":"Family Kloset Costume Shop",
    "wof:placetype":"venue"
},
  "geometry": {"coordinates":[-70.69215,41.979146],"type":"Point"}
}