{
  "type": "Feature",
  "properties": {
    "iso:country":"US",
    "sg:address":"955 Massachusetts Ave",
    "sg:city":"Cambridge",
    "sg:classifiers":[
        {
            "category":"Wholesale",
            "subcategory":"Durable Goods & Equipment",
            "type":"Manufacturing & Wholesale Goods"
        }
    ],
    "sg:phone":"+1 617 354 9600",
    "sg:postcode":"02139",
    "sg:province":"MA",
    "sg:tags":[
        "exporter"
    ],
    "sg:website":"www.sec-international.com",
    "wof:name":"SEC Intl",
    "wof:placetype":"venue"
},
  "geometry": {"coordinates":[-71.109539,42.368719],"type":"Point"}
}