{
  "type": "Feature",
  "properties": {
    "addr:full": "955 Massachusetts Ave Cambridge MA 02139",
    "addr:housenumber": "955",
    "addr:postcode": "02139",
    "addr:street": "Massachusetts Ave",
    "iso:country": "US",
    "sg:address": "955 Massachusetts Ave",
    "sg:city": "Cambridge",
    "sg:classifiers": [
      {
        "category": "Wholesale",
        "subcategory": "Durable Goods \u0026 Equipment",
        "type": "Manufacturing \u0026 Wholesale Goods"
      }
    ],
    "sg:phone": "+1 617 354 9600",
    "sg:postcode": "02139",
    "sg:province": "MA",
    "sg:tags": [
      "exporter"
    ],
    "sg:website": "www.sec-international.com",
    "wof:name": "SEC Intl",
    "wof:placetype": "venue"
  },
  "geometry": {"coordinates":[-71.109539,42.368719],"type":"Point"}
}
