{
  "type": "Feature",
  "properties": {
    "addr:full": "122 Teaticket Hwy Teaticket MA 02536",
    "addr:housenumber": "122",
    "addr:postcode": "02536",
    "addr:street": "Teaticket Hwy",
    "iso:country": "US",
    "sg:address": "122 Teaticket Hwy",
    "sg:city": "Teaticket",
    "sg:classifiers": [
      {
        "category": "Professional",
        "subcategory": "Lawyer \u0026 Legal Services",
        "type": "Services"
      }
    ],
    "sg:phone": "+1 508 540 7777",
    "sg:postcode": "02536",
    "sg:province": "MA",
    "sg:tags": [
      "attorney"
    ],
    "wof:name": "Glynn \u0026 Glynn",
    "wof:placetype": "venue"
  },
  "geometry": {"coordinates":[-70.596102,41.564459],"type":"Point"}
}
