{
  "type": "Feature",
  "properties": {
    "addr:full":"2 Main St Hopkinton MA 01748",
    "addr:housenumber":"2",
    "addr:postcode":"01748",
    "addr:street":"Main St",
    "iso:country":"US",
    "sg:address":"2 Main St",
    "sg:city":"Hopkinton",
    "sg:classifiers":[
        {
            "category":"Place Of Worship",
            "subcategory":"Church",
            "type":"Public Place"
        },
        {
            "category":"Place Of Worship",
            "type":"Public Place"
        }
    ],
    "sg:phone":"+1 508 435 4579",
    "sg:postcode":"01748",
    "sg:province":"MA",
    "sg:tags":[
        "churches-presbyterian-arp",
        "churches-presbyterian"
    ],
    "wof:name":"Korean Presbyterian Church In Greater Boston Inc",
    "wof:placetype":"venue"
},
  "geometry": {"coordinates":[-71.518547,42.229519],"type":"Point"}
}