{
  "type": "Feature",
  "properties": {
    "iso:country":"US",
    "sg:address":"59 Wood St",
    "sg:city":"Hopkinton",
    "sg:classifiers":[
        {
            "category":"Social Services",
            "subcategory":"Child Care",
            "type":"Services"
        }
    ],
    "sg:phone":"+1 508 497 0892",
    "sg:postcode":"01748",
    "sg:province":"MA",
    "wof:name":"Learning Center Of Hopkinton",
    "wof:placetype":"venue"
},
  "geometry": {"coordinates":[-71.53817600000001,42.226785],"type":"Point"}
}