{
  "type": "Feature",
  "properties": {
    "addr:full": "227 Fayette St Lowell MA 01852",
    "addr:housenumber": "227",
    "addr:postcode": "01852",
    "addr:street": "Fayette St",
    "iso:country": "US",
    "sg:address": "227 Fayette St",
    "sg:city": "Lowell",
    "sg:classifiers": [
      {
        "category": "Real Estate",
        "subcategory": "Real Estate Operator",
        "type": "Services"
      }
    ],
    "sg:phone": "+1   ",
    "sg:postcode": "01852",
    "sg:province": "MA",
    "sg:tags": [
      "building",
      "apartment"
    ],
    "wof:name": "Fayette St Management",
    "wof:placetype": "venue"
  },
  "geometry": {"coordinates":[-71.302104,42.642561],"type":"Point"}
}
