{
  "type": "Feature",
  "properties": {
    "iso:country":"US",
    "sg:address":"75 Francis St",
    "sg:city":"Boston",
    "sg:classifiers":[
        {
            "category":"Professional",
            "subcategory":"Business Services",
            "type":"Services"
        }
    ],
    "sg:phone":"+1   ",
    "sg:postcode":"02143",
    "sg:province":"MA",
    "wof:name":"Friends Brigham & Womens Hosp",
    "wof:placetype":"venue"
},
  "geometry": {"coordinates":[-71.11098,42.390645],"type":"Point"}
}