{
  "type": "Feature",
  "properties": {
    "iso:country":"US",
    "sg:address":"22 Pauline St",
    "sg:city":"Winthrop",
    "sg:classifiers":[
        {
            "category":"Professional",
            "subcategory":"Accounting & Tax Preparation",
            "type":"Services"
        }
    ],
    "sg:phone":"+1 617 846 0100",
    "sg:postcode":"02152",
    "sg:province":"MA",
    "sg:tags":[
        "billing"
    ],
    "wof:name":"Mikem Billing Svc",
    "wof:placetype":"venue"
},
  "geometry": {"coordinates":[-70.98459,42.376878],"type":"Point"}
}