{
  "type": "Feature",
  "properties": {
    "iso:country":"US",
    "sg:address":"9 Shipway Pl",
    "sg:city":"Charlestown",
    "sg:classifiers":[
        {
            "category":"Professional",
            "subcategory":"Research",
            "type":"Services"
        }
    ],
    "sg:phone":"+1 617 241 7600",
    "sg:postcode":"02129",
    "sg:province":"MA",
    "sg:tags":[
        "environmental",
        "ecological"
    ],
    "wof:name":"AAI Environmental",
    "wof:placetype":"venue"
},
  "geometry": {"coordinates":[-71.051507,42.379042],"type":"Point"}
}