{
  "type": "Feature",
  "properties": {
    "addr:full":"4 Jackson Ct Oxford MA 01540",
    "addr:housenumber":"4",
    "addr:postcode":"01540",
    "addr:street":"Jackson Ct",
    "iso:country":"US",
    "sg:address":"4 Jackson Ct",
    "sg:city":"Oxford",
    "sg:classifiers":[
        {
            "category":"Building & Trades",
            "subcategory":"Construction",
            "type":"Services"
        }
    ],
    "sg:phone":"+1 508 949 0202",
    "sg:postcode":"01540",
    "sg:province":"MA",
    "sg:tags":[
        "downspouts",
        "gutter"
    ],
    "wof:name":"D & M Seamless Gutters",
    "wof:placetype":"venue"
},
  "geometry": {"coordinates":[-71.867143,42.113964],"type":"Point"}
}