{
  "type": "Feature",
  "properties": {
    "iso:country":"US",
    "sg:address":"385 Southampton Rd",
    "sg:city":"Westfield",
    "sg:classifiers":[
        {
            "category":"Professional",
            "subcategory":"Lawyer & Legal Services",
            "type":"Services"
        }
    ],
    "sg:phone":"+1 413 562 6481",
    "sg:postcode":"01085",
    "sg:province":"MA",
    "sg:tags":[
        "attorney"
    ],
    "wof:name":"Patrick R Boland",
    "wof:placetype":"venue"
},
  "geometry": {"coordinates":[-72.72626700000001,42.151831],"type":"Point"}
}