{
  "type": "Feature",
  "properties": {
    "addr:full": "385 Southampton Rd Westfield MA 01085",
    "addr:housenumber": "385",
    "addr:postcode": "01085",
    "addr:street": "Southampton Rd",
    "iso:country": "US",
    "sg:address": "385 Southampton Rd",
    "sg:city": "Westfield",
    "sg:classifiers": [
      {
        "category": "Professional",
        "subcategory": "Lawyer \u0026 Legal Services",
        "type": "Services"
      }
    ],
    "sg:phone": "+1 413 562 6481",
    "sg:postcode": "01085",
    "sg:province": "MA",
    "sg:tags": [
      "attorney"
    ],
    "wof:name": "Patrick R Boland",
    "wof:placetype": "venue"
  },
  "geometry": {"coordinates":[-72.726267,42.151831],"type":"Point"}
}
