{
  "type": "Feature",
  "properties": {
    "iso:country":"US",
    "sg:address":"207 Middlesex Ave",
    "sg:city":"Medford",
    "sg:phone":"+1 781 393 9398",
    "sg:postcode":"02155",
    "sg:province":"MA",
    "wof:name":"Asian Taste",
    "wof:placetype":"venue"
},
  "geometry": {"coordinates":[-71.07988,42.409538],"type":"Point"}
}