{
  "type": "Feature",
  "properties": {
    "addr:full":"207 Middlesex Ave Medford MA 02155",
    "addr:housenumber":"207",
    "addr:postcode":"02155",
    "addr:street":"Middlesex Ave",
    "iso:country":"US",
    "sg:address":"207 Middlesex Ave",
    "sg:city":"Medford",
    "sg:phone":"+1 781 393 9398",
    "sg:postcode":"02155",
    "sg:province":"MA",
    "wof:name":"Asian Taste",
    "wof:placetype":"venue"
},
  "geometry": {"coordinates":[-71.07988,42.409538],"type":"Point"}
}