{
  "type": "Feature",
  "properties": {
    "addr:full":"89 S Main St Centerville MA 02632",
    "addr:housenumber":"89",
    "addr:postcode":"02632",
    "addr:street":"S Main St",
    "iso:country":"US",
    "sg:address":"89 S Main St",
    "sg:city":"Centerville",
    "sg:classifiers":[
        {
            "category":"Restaurant",
            "type":"Food & Drink"
        }
    ],
    "sg:phone":"+1 508 771 0347",
    "sg:postcode":"02632",
    "sg:province":"MA",
    "sg:tags":[
        "eating",
        "caterer"
    ],
    "wof:name":"Sandy's Gourmet Kitchen - CLOSED",
    "wof:placetype":"venue"
},
  "geometry": {"coordinates":[-70.3395,41.650002],"type":"Point"}
}