{
  "type": "Feature",
  "properties": {
    "iso:country":"US",
    "sg:address":"10 Emerson Pl",
    "sg:city":"Boston",
    "sg:classifiers":[
        {
            "category":"Professional",
            "subcategory":"Management & Consulting",
            "type":"Services"
        }
    ],
    "sg:phone":"+1 617 523 7277",
    "sg:postcode":"02114",
    "sg:province":"MA",
    "sg:tags":[
        "consultant",
        "training"
    ],
    "wof:name":"Grady Financial Seminars Inc",
    "wof:placetype":"venue"
},
  "geometry": {"coordinates":[-71.06855400000001,42.364903],"type":"Point"}
}