{
  "type": "Feature",
  "properties": {
    "iso:country":"US",
    "sg:address":"33 Cottage St",
    "sg:city":"Lexington",
    "sg:classifiers":[
        {
            "category":"Professional",
            "subcategory":"Research",
            "type":"Services"
        }
    ],
    "sg:phone":"+1 781 652 8385",
    "sg:postcode":"02420",
    "sg:province":"MA",
    "sg:tags":[
        "market",
        "analysis"
    ],
    "wof:name":"Bay State Market Research",
    "wof:placetype":"venue"
},
  "geometry": {"coordinates":[-71.21844299999999,42.446053],"type":"Point"}
}