{
  "type": "Feature",
  "properties": {
    "addr:full": "345 South St Foxboro MA 02035",
    "addr:housenumber": "345",
    "addr:postcode": "02035",
    "addr:street": "South St",
    "iso:country": "US",
    "sg:address": "345 South St",
    "sg:city": "Foxboro",
    "sg:classifiers": [
      {
        "category": "Professional",
        "type": "Services"
      }
    ],
    "sg:phone": "+1   ",
    "sg:postcode": "02035",
    "sg:province": "MA",
    "wof:name": "Christopher M Cunniff Inc",
    "wof:placetype": "venue"
  },
  "geometry": {"coordinates":[-71.267949,42.039685],"type":"Point"}
}
