{
  "type": "Feature",
  "properties": {
    "iso:country":"US",
    "sg:address":"12 Brodeur Ave",
    "sg:city":"Webster",
    "sg:classifiers":[
        {
            "category":"Retail",
            "subcategory":"Repair Shop",
            "type":"Services"
        }
    ],
    "sg:phone":"+1 508 756 9700",
    "sg:postcode":"01570",
    "sg:province":"MA",
    "sg:tags":[
        "upholsterer"
    ],
    "wof:name":"Furniture Plus",
    "wof:placetype":"venue"
},
  "geometry": {"coordinates":[-71.86959299999999,42.058494],"type":"Point"}
}