{
  "type": "Feature",
  "properties": {
    "addr:full":"11 Austin St Blackstone MA 01504",
    "addr:housenumber":"11",
    "addr:postcode":"01504",
    "addr:street":"Austin St",
    "iso:country":"US",
    "sg:address":"11 Austin St",
    "sg:city":"Blackstone",
    "sg:classifiers":[
        {
            "category":"Building & Trades",
            "subcategory":"Landscaping Services",
            "type":"Services"
        },
        {
            "category":"Manufacturing",
            "subcategory":"Buildings",
            "type":"Manufacturing & Wholesale Goods"
        },
        {
            "category":"Building & Trades",
            "subcategory":"Construction",
            "type":"Services"
        }
    ],
    "sg:phone":"+1 508 883 0860",
    "sg:postcode":"01504",
    "sg:province":"MA",
    "sg:tags":[
        "designer",
        "consultant",
        "builder",
        "snow",
        "removal",
        "home",
        "contractor",
        "landscape"
    ],
    "sg:website":"http://www.bandmlandscapema.com",
    "wof:name":"B & M Landscape Maintenance & Construction",
    "wof:placetype":"venue"
},
  "geometry": {"coordinates":[-71.537165,42.019404],"type":"Point"}
}