{
  "type": "Feature",
  "properties": {
    "iso:country":"US",
    "sg:address":"67 Mechanic St",
    "sg:city":"Attleboro",
    "sg:classifiers":[
        {
            "category":"Shopping",
            "type":"Retail Goods"
        }
    ],
    "sg:phone":"+1 508 223 9990",
    "sg:postcode":"02703",
    "sg:province":"MA",
    "sg:tags":[
        "trophy",
        "medal",
        "award"
    ],
    "wof:name":"Moore Awards",
    "wof:placetype":"venue"
},
  "geometry": {"coordinates":[-71.29285299999999,41.94395],"type":"Point"}
}