{
  "type": "Feature",
  "properties": {
    "addr:full": "1 Nemco Way Ayer MA 01432",
    "addr:housenumber": "1",
    "addr:postcode": "01432",
    "addr:street": "Nemco Way",
    "iso:country": "US",
    "sg:address": "1 Nemco Way",
    "sg:city": "Ayer",
    "sg:classifiers": [
      {
        "category": "Wholesale",
        "subcategory": "Durable Goods \u0026 Equipment",
        "type": "Manufacturing \u0026 Wholesale Goods"
      }
    ],
    "sg:phone": "+1 978 772 7900",
    "sg:postcode": "01432",
    "sg:province": "MA",
    "sg:tags": [
      "importer"
    ],
    "sg:website": "www.cataniausa.com",
    "wof:name": "Catania-Spagna Corp",
    "wof:placetype": "venue"
  },
  "geometry": {"coordinates":[-71.533296,42.565791],"type":"Point"}
}
