{
  "type": "Feature",
  "properties": {
    "iso:country":"US",
    "sg:address":"1 Nemco Way",
    "sg:city":"Ayer",
    "sg:classifiers":[
        {
            "category":"Wholesale",
            "subcategory":"Durable Goods & Equipment",
            "type":"Manufacturing & Wholesale Goods"
        }
    ],
    "sg:phone":"+1 978 772 7900",
    "sg:postcode":"01432",
    "sg:province":"MA",
    "sg:tags":[
        "importer"
    ],
    "sg:website":"www.cataniausa.com",
    "wof:name":"Catania-Spagna Corp",
    "wof:placetype":"venue"
},
  "geometry": {"coordinates":[-71.53329600000001,42.565791],"type":"Point"}
}