{
  "type": "Feature",
  "properties": {
    "addr:full":"28 State St Boston MA 02109",
    "addr:housenumber":"28",
    "addr:postcode":"02109",
    "addr:street":"State St",
    "iso:country":"US",
    "sg:address":"28 State St",
    "sg:city":"Boston",
    "sg:classifiers":[
        {
            "category":"Insurance",
            "subcategory":"Hazard Insurance",
            "type":"Services"
        }
    ],
    "sg:phone":"+1 617 345 0404",
    "sg:postcode":"02109",
    "sg:province":"MA",
    "sg:tags":[
        "profit",
        "sharing",
        "pension",
        "plan"
    ],
    "wof:name":"Tiaa-Cref",
    "wof:placetype":"venue"
},
  "geometry": {"coordinates":[-71.057805,42.358923],"type":"Point"}
}