{
  "type": "Feature",
  "properties": {
    "addr:full":"14 Pleasant St Cambridge MA 02139",
    "addr:housenumber":"14",
    "addr:postcode":"02139",
    "addr:street":"Pleasant St",
    "iso:country":"US",
    "sg:address":"14 Pleasant St",
    "sg:city":"Cambridge",
    "sg:classifiers":[
        {
            "category":"Health Services",
            "subcategory":"Health Practitioner",
            "type":"Services"
        }
    ],
    "sg:phone":"+1 617 491 5016",
    "sg:postcode":"02139",
    "sg:province":"MA",
    "wof:name":"Stephanie Roeder",
    "wof:placetype":"venue"
},
  "geometry": {"coordinates":[-71.106129,42.365705],"type":"Point"}
}