{
  "type": "Feature",
  "properties": {
    "iso:country":"US",
    "sg:address":"89 Leverett Ave",
    "sg:city":"Revere",
    "sg:classifiers":[
        {
            "category":"Building & Trades",
            "subcategory":"Plumbing",
            "type":"Services"
        }
    ],
    "sg:phone":"+1   ",
    "sg:postcode":"02151",
    "sg:province":"MA",
    "sg:tags":[
        "contractor"
    ],
    "wof:name":"Mc Hatton Plumbing & Heating",
    "wof:placetype":"venue"
},
  "geometry": {"coordinates":[-70.98402299999999,42.396879],"type":"Point"}
}