{
  "type": "Feature",
  "properties": {
    "addr:full": "24 Hollis Rd Lynn MA 01904",
    "addr:housenumber": "24",
    "addr:postcode": "01904",
    "addr:street": "Hollis Rd",
    "iso:country": "US",
    "sg:address": "24 Hollis Rd",
    "sg:city": "Lynn",
    "sg:classifiers": [
      {
        "category": "Building \u0026 Trades",
        "subcategory": "Plumbing",
        "type": "Services"
      }
    ],
    "sg:phone": "+1 781 592 2011",
    "sg:postcode": "01904",
    "sg:province": "MA",
    "sg:tags": [
      "plumbing",
      "contractor"
    ],
    "wof:name": "M Roberts Plumbing \u0026 Heating",
    "wof:placetype": "venue"
  },
  "geometry": {"coordinates":[-70.966448,42.493243],"type":"Point"}
}
