{
  "type": "Feature",
  "properties": {
    "iso:country":"US",
    "sg:address":"24 Hollis Rd",
    "sg:city":"Lynn",
    "sg:classifiers":[
        {
            "category":"Building & Trades",
            "subcategory":"Plumbing",
            "type":"Services"
        }
    ],
    "sg:phone":"+1 781 592 2011",
    "sg:postcode":"01904",
    "sg:province":"MA",
    "sg:tags":[
        "plumbing",
        "contractor"
    ],
    "wof:name":"M Roberts Plumbing & Heating",
    "wof:placetype":"venue"
},
  "geometry": {"coordinates":[-70.966448,42.493243],"type":"Point"}
}