{
  "type": "Feature",
  "properties": {
    "iso:country":"US",
    "sg:address":"100 Phillips St",
    "sg:city":"Fitchburg",
    "sg:classifiers":[
        {
            "category":"Building & Trades",
            "subcategory":"Construction",
            "type":"Services"
        }
    ],
    "sg:phone":"+1 978 343 3865",
    "sg:postcode":"01420",
    "sg:province":"MA",
    "sg:tags":[
        "home",
        "improvement"
    ],
    "wof:name":"Tri-City Home Improvements",
    "wof:placetype":"venue"
},
  "geometry": {"coordinates":[-71.84209300000001,42.576875],"type":"Point"}
}