{
  "type": "Feature",
  "properties": {
    "addr:full": "100 Phillips St Fitchburg MA 01420",
    "addr:housenumber": "100",
    "addr:postcode": "01420",
    "addr:street": "Phillips St",
    "iso:country": "US",
    "sg:address": "100 Phillips St",
    "sg:city": "Fitchburg",
    "sg:classifiers": [
      {
        "category": "Building \u0026 Trades",
        "subcategory": "Construction",
        "type": "Services"
      }
    ],
    "sg:phone": "+1 978 343 3865",
    "sg:postcode": "01420",
    "sg:province": "MA",
    "sg:tags": [
      "home",
      "improvement"
    ],
    "wof:name": "Tri-City Home Improvements",
    "wof:placetype": "venue"
  },
  "geometry": {"coordinates":[-71.842093,42.576875],"type":"Point"}
}
