{
  "type": "Feature",
  "properties": {
    "addr:full":"80 Galen St Waltham MA 02451",
    "addr:housenumber":"80",
    "addr:postcode":"02451",
    "addr:street":"Galen St",
    "iso:country":"US",
    "sg:address":"80 Galen St",
    "sg:city":"Waltham",
    "sg:classifiers":[
        {
            "category":"Retail",
            "subcategory":"Auto Repair",
            "type":"Services"
        }
    ],
    "sg:phone":"+1 617 923 4045",
    "sg:postcode":"02451",
    "sg:province":"MA",
    "sg:tags":[
        "automobile",
        "lubrication"
    ],
    "sg:website":"www.vioc.com",
    "wof:name":"Valvoline Instant Oil Change",
    "wof:placetype":"venue"
},
  "geometry": {"coordinates":[-71.24661399999999,42.386733],"type":"Point"}
}