{
  "type": "Feature",
  "properties": {
    "addr:full": "4 Gleason Way Leicester MA 01524",
    "addr:housenumber": "4",
    "addr:postcode": "01524",
    "addr:street": "Gleason Way",
    "iso:country": "US",
    "sg:address": "4 Gleason Way",
    "sg:city": "Leicester",
    "sg:classifiers": [
      {
        "category": "Home \u0026 Garden",
        "subcategory": "Household Appliances",
        "type": "Retail Goods"
      },
      {
        "category": "Building \u0026 Trades",
        "subcategory": "Construction",
        "type": "Services"
      }
    ],
    "sg:phone": "+1 508 757 1545",
    "sg:postcode": "01524",
    "sg:province": "MA",
    "sg:tags": [
      "dishwashing",
      "specialty",
      "heating",
      "system",
      "machine",
      "contractor",
      "air conditioning"
    ],
    "wof:name": "David's Heating \u0026 Air Conditioning \u0026 Refrigeration",
    "wof:placetype": "venue"
  },
  "geometry": {"coordinates":[-71.908965,42.247538],"type":"Point"}
}
