{
  "type": "Feature",
  "properties": {
    "addr:full":"4 Gleason Way Leicester MA 01524",
    "addr:housenumber":"4",
    "addr:postcode":"01524",
    "addr:street":"Gleason Way",
    "iso:country":"US",
    "sg:address":"4 Gleason Way",
    "sg:city":"Leicester",
    "sg:classifiers":[
        {
            "category":"Home & Garden",
            "subcategory":"Household Appliances",
            "type":"Retail Goods"
        },
        {
            "category":"Building & Trades",
            "subcategory":"Construction",
            "type":"Services"
        }
    ],
    "sg:phone":"+1 508 757 1545",
    "sg:postcode":"01524",
    "sg:province":"MA",
    "sg:tags":[
        "dishwashing",
        "specialty",
        "heating",
        "system",
        "machine",
        "contractor",
        "air conditioning"
    ],
    "wof:name":"David's Heating & Air Conditioning & Refrigeration",
    "wof:placetype":"venue"
},
  "geometry": {"coordinates":[-71.90896499999999,42.247538],"type":"Point"}
}