{
  "type": "Feature",
  "properties": {
    "addr:full": "807 Wilbraham Rd Springfield ME 01109",
    "addr:housenumber": "807",
    "addr:postcode": "01109",
    "addr:street": "Wilbraham Rd",
    "iso:country": "US",
    "sg:address": "807 Wilbraham Rd",
    "sg:city": "Springfield",
    "sg:classifiers": [
      {
        "category": "Professional",
        "type": "Services"
      }
    ],
    "sg:phone": "+1 413 783 1257",
    "sg:postcode": "01109",
    "sg:province": "ME",
    "sg:tags": [
      "establishment"
    ],
    "wof:name": "Care W Mass Life",
    "wof:placetype": "venue"
  },
  "geometry": {"coordinates":[-72.537684,42.113701],"type":"Point"}
}
