{
  "type": "Feature",
  "properties": {
    "addr:full":"65 Parker St Newburyport MA 01950",
    "addr:housenumber":"65",
    "addr:postcode":"01950",
    "addr:street":"Parker St",
    "iso:country":"US",
    "sg:address":"65 Parker St",
    "sg:city":"Newburyport",
    "sg:classifiers":[
        {
            "category":"Shopping",
            "subcategory":"Gifts & Souvenirs",
            "type":"Retail Goods"
        }
    ],
    "sg:phone":"+1 978 388 2505",
    "sg:postcode":"01950",
    "sg:province":"MA",
    "sg:tags":[
        "shop"
    ],
    "wof:name":"Fluns",
    "wof:placetype":"venue"
},
  "geometry": {"coordinates":[-70.88475099999999,42.800655],"type":"Point"}
}