{
  "type": "Feature",
  "properties": {
    "iso:country":"US",
    "sg:address":"14 Court Sq",
    "sg:city":"Greenfield",
    "sg:classifiers":[
        {
            "category":"Organizations",
            "subcategory":"Political Organization",
            "type":"Services"
        }
    ],
    "sg:phone":"+1   ",
    "sg:postcode":"01301",
    "sg:province":"MA",
    "wof:name":"Greenfield Town Council",
    "wof:placetype":"venue"
},
  "geometry": {"coordinates":[-72.60099,42.587553],"type":"Point"}
}