{
  "type": "Feature",
  "properties": {
    "addr:full": "45 Bromfield St Boston MA 02170",
    "addr:housenumber": "45",
    "addr:postcode": "02170",
    "addr:street": "Bromfield St",
    "iso:country": "US",
    "sg:address": "45 Bromfield St",
    "sg:city": "Boston",
    "sg:classifiers": [
      {
        "category": "Professional",
        "subcategory": "Lawyer \u0026 Legal Services",
        "type": "Services"
      }
    ],
    "sg:phone": "+1 617 259 1569",
    "sg:postcode": "02170",
    "sg:province": "MA",
    "sg:tags": [
      "attorney"
    ],
    "wof:name": "Walter H Porr Jr",
    "wof:placetype": "venue"
  },
  "geometry": {"coordinates":[-71.014215,42.27287],"type":"Point"}
}
