{
  "type": "Feature",
  "properties": {
    "iso:country":"US",
    "sg:address":"155 Seaport Blvd",
    "sg:city":"Boston",
    "sg:classifiers":[
        {
            "category":"Professional",
            "subcategory":"Lawyer & Legal Services",
            "type":"Services"
        }
    ],
    "sg:phone":"+1 617 832 1000",
    "sg:postcode":"02210",
    "sg:province":"MA",
    "sg:tags":[
        "litigation",
        "tort",
        "attorney"
    ],
    "wof:name":"White , Brandon F. - Foley Hoag Llp",
    "wof:placetype":"venue"
},
  "geometry": {"coordinates":[-71.04949999999999,42.353659],"type":"Point"}
}