{
  "type": "Feature",
  "properties": {
    "addr:full": "27 Great Neck Rd East Wareham MA 02538",
    "addr:housenumber": "27",
    "addr:postcode": "02538",
    "addr:street": "Great Neck Rd",
    "iso:country": "US",
    "sg:address": "27 Great Neck Rd",
    "sg:city": "East Wareham",
    "sg:classifiers": [
      {
        "category": "Home \u0026 Garden",
        "subcategory": "Garden Supply",
        "type": "Retail Goods"
      }
    ],
    "sg:phone": "+1 508 295 5378",
    "sg:postcode": "02538",
    "sg:province": "MA",
    "sg:tags": [
      "sprinkler"
    ],
    "wof:name": "John Avilla Irrigation",
    "wof:placetype": "venue"
  },
  "geometry": {"coordinates":[-70.678156,41.753283],"type":"Point"}
}
