{
  "type": "Feature",
  "properties": {
    "iso:country":"US",
    "sg:address":"27 Great Neck Rd",
    "sg:city":"East Wareham",
    "sg:classifiers":[
        {
            "category":"Home & Garden",
            "subcategory":"Garden Supply",
            "type":"Retail Goods"
        }
    ],
    "sg:phone":"+1 508 295 5378",
    "sg:postcode":"02538",
    "sg:province":"MA",
    "sg:tags":[
        "sprinkler"
    ],
    "wof:name":"John Avilla Irrigation",
    "wof:placetype":"venue"
},
  "geometry": {"coordinates":[-70.678156,41.753283],"type":"Point"}
}