{
  "type": "Feature",
  "properties": {
    "addr:full": "160 Gould St Needham Heights MA 02494",
    "addr:housenumber": "160",
    "addr:postcode": "02494",
    "addr:street": "Gould St",
    "iso:country": "US",
    "sg:address": "160 Gould St",
    "sg:city": "Needham Heights",
    "sg:classifiers": [
      {
        "category": "Professional",
        "type": "Services"
      }
    ],
    "sg:phone": "+1   ",
    "sg:postcode": "02494",
    "sg:province": "MA",
    "wof:name": "Ask Technical Svc",
    "wof:placetype": "venue"
  },
  "geometry": {"coordinates":[-71.229709,42.302932],"type":"Point"}
}
