{
  "type": "Feature",
  "properties": {
    "iso:country":"US",
    "sg:address":"49 Glen St",
    "sg:city":"Melrose",
    "sg:classifiers":[
        {
            "category":"Building & Trades",
            "subcategory":"Plumbing",
            "type":"Services"
        }
    ],
    "sg:phone":"+1 781 665 4349",
    "sg:postcode":"02176",
    "sg:province":"MA",
    "sg:tags":[
        "plumbing",
        "contractor"
    ],
    "wof:name":"Allphase Plumbing & Heating",
    "wof:placetype":"venue"
},
  "geometry": {"coordinates":[-71.079286,42.453035],"type":"Point"}
}