{
  "type": "Feature",
  "properties": {
    "addr:full":"170 N Main St South Yarmouth MA 02664",
    "addr:housenumber":"170",
    "addr:postcode":"02664",
    "addr:street":"N Main St",
    "iso:country":"US",
    "sg:address":"170 N Main St",
    "sg:city":"South Yarmouth",
    "sg:classifiers":[
        {
            "category":"Building & Trades",
            "subcategory":"Landscaping Services",
            "type":"Services"
        }
    ],
    "sg:phone":"+1 508 398 9558",
    "sg:postcode":"02664",
    "sg:province":"MA",
    "sg:tags":[
        "landscape",
        "contractor"
    ],
    "wof:name":"Star Landscaping & Design",
    "wof:placetype":"venue"
},
  "geometry": {"coordinates":[-70.18394499999999,41.67457],"type":"Point"}
}