{
  "type": "Feature",
  "properties": {
    "iso:country":"US",
    "sg:address":"157 Centre St",
    "sg:city":"Brockton",
    "sg:classifiers":[
        {
            "category":"Health Services",
            "subcategory":"Clinic",
            "type":"Services"
        }
    ],
    "sg:phone":"+1 508 941 0005",
    "sg:postcode":"02302",
    "sg:province":"MA",
    "sg:website":"www.lhi.org",
    "wof:name":"Latino Health Institute",
    "wof:placetype":"venue"
},
  "geometry": {"coordinates":[-71.013369,42.083927],"type":"Point"}
}