{
  "type": "Feature",
  "properties": {
    "iso:country":"US",
    "sg:address":"321 Elm St",
    "sg:city":"Pittsfield",
    "sg:classifiers":[
        {
            "category":"Real Estate",
            "subcategory":"Real Estate Agent",
            "type":"Services"
        }
    ],
    "sg:phone":"+1 413 443 6304",
    "sg:postcode":"01201",
    "sg:province":"MA",
    "wof:name":"Charlotte Mc Carthy Realty",
    "wof:placetype":"venue"
},
  "geometry": {"coordinates":[-73.230445,42.442537],"type":"Point"}
}