{
  "type": "Feature",
  "properties": {
    "addr:full":"230 Stuart St Boston MA 02116",
    "addr:housenumber":"230",
    "addr:postcode":"02116",
    "addr:street":"Stuart St",
    "iso:country":"US",
    "sg:address":"230 Stuart St",
    "sg:city":"Boston",
    "sg:classifiers":[
        {
            "category":"Personal",
            "subcategory":"Beauty Salon",
            "type":"Services"
        }
    ],
    "sg:phone":"+1 617 292 0202",
    "sg:postcode":"02116",
    "sg:province":"MA",
    "sg:tags":[
        "hair"
    ],
    "sg:website":"www.amacisalon.com",
    "wof:name":"Amaci Salon",
    "wof:placetype":"venue"
},
  "geometry": {"coordinates":[-71.068895,42.350314],"type":"Point"}
}