{
  "type": "Feature",
  "properties": {
    "addr:full": "124 Mount Auburn St Cambridge MA 02138",
    "addr:housenumber": "124",
    "addr:postcode": "02138",
    "addr:street": "Mount Auburn St",
    "iso:country": "US",
    "sg:address": "124 Mount Auburn St",
    "sg:city": "Cambridge",
    "sg:classifiers": [
      {
        "category": "Education",
        "subcategory": "College",
        "type": "Public Place"
      }
    ],
    "sg:phone": "+1 617 503 5000",
    "sg:postcode": "02138",
    "sg:province": "MA",
    "sg:tags": [
      "academic",
      "school"
    ],
    "wof:name": "Harvard University",
    "wof:placetype": "venue"
  },
  "geometry": {"coordinates":[-71.123446,42.373549],"type":"Point"}
}
