{
  "type": "Feature",
  "properties": {
    "iso:country":"US",
    "sg:address":"40 Lenox St",
    "sg:city":"Norwood",
    "sg:classifiers":[
        {
            "category":"Building & Trades",
            "subcategory":"Construction",
            "type":"Services"
        }
    ],
    "sg:phone":"+1 781 297 0115",
    "sg:postcode":"02062",
    "sg:province":"MA",
    "sg:tags":[
        "fence",
        "contractor"
    ],
    "wof:name":"KGJ Fence",
    "wof:placetype":"venue"
},
  "geometry": {"coordinates":[-71.196786,42.193923],"type":"Point"}
}