{
  "type": "Feature",
  "properties": {
    "iso:country":"US",
    "sg:address":"186 Parkerville Rd",
    "sg:city":"Southborough",
    "sg:classifiers":[
        {
            "category":"Professional",
            "type":"Services"
        }
    ],
    "sg:phone":"+1   ",
    "sg:postcode":"01772",
    "sg:province":"MA",
    "wof:name":"Nanis Room Inc",
    "wof:placetype":"venue"
},
  "geometry": {"coordinates":[-71.536405,42.278136],"type":"Point"}
}