{
  "type": "Feature",
  "properties": {
    "iso:country":"US",
    "sg:address":"16 Revere St",
    "sg:city":"Winthrop",
    "sg:classifiers":[
        {
            "category":"Building & Trades",
            "subcategory":"Landscaping Services",
            "type":"Services"
        }
    ],
    "sg:phone":"+1 617 846 7290",
    "sg:postcode":"02152",
    "sg:province":"MA",
    "sg:tags":[
        "landscape",
        "contractor"
    ],
    "wof:name":"Seacoast Contractors",
    "wof:placetype":"venue"
},
  "geometry": {"coordinates":[-70.981819,42.381802],"type":"Point"}
}