{
  "type": "Feature",
  "properties": {
    "iso:country":"US",
    "sg:address":"900 Cummings Center Suite 314-T",
    "sg:city":"Beverly",
    "sg:classifiers":[
        {
            "category":"Professional",
            "subcategory":"Computer Services",
            "type":"Services"
        }
    ],
    "sg:phone":"+1 978 816 1600",
    "sg:postcode":"01915",
    "sg:province":"MA",
    "sg:tags":[
        "xml",
        "uml",
        "databases",
        "web-services",
        "developer-tools"
    ],
    "sg:website":"http://www.altova.com",
    "wof:name":"Altova",
    "wof:placetype":"venue"
},
  "geometry": {"coordinates":[-70.92008199999999,42.528149],"type":"Point"}
}