{
  "type": "Feature",
  "properties": {
    "addr:full":"749 Maple Rd Longmeadow MA 01106",
    "addr:housenumber":"749",
    "addr:postcode":"01106",
    "addr:street":"Maple Rd",
    "iso:country":"US",
    "sg:address":"749 Maple Rd",
    "sg:city":"Longmeadow",
    "sg:classifiers":[
        {
            "category":"Shopping",
            "type":"Retail Goods"
        }
    ],
    "sg:phone":"+1 413 567 0040",
    "sg:postcode":"01106",
    "sg:province":"MA",
    "sg:tags":[
        "merchandise"
    ],
    "wof:name":"Totally Cellular",
    "wof:placetype":"venue"
},
  "geometry": {"coordinates":[-72.554247,42.032569],"type":"Point"}
}