{
  "type": "Feature",
  "properties": {
    "addr:full": "30 Boltwood Walk Amherst MA 01002",
    "addr:housenumber": "30",
    "addr:postcode": "01002",
    "addr:street": "Boltwood Walk",
    "iso:country": "US",
    "sg:address": "30 Boltwood Walk",
    "sg:city": "Amherst",
    "sg:classifiers": [
      {
        "category": "Building \u0026 Trades",
        "subcategory": "Construction",
        "type": "Services"
      }
    ],
    "sg:phone": "+1 413 256 8600",
    "sg:postcode": "01002",
    "sg:province": "MA",
    "sg:tags": [
      "contractor"
    ],
    "wof:name": "Levi-Nielsen Co Inc",
    "wof:placetype": "venue"
  },
  "geometry": {"coordinates":[-72.51888,42.376193],"type":"Point"}
}
