{
  "type": "Feature",
  "properties": {
    "addr:full":"2 Batterymarch Park Quincy MA 02169",
    "addr:housenumber":"2",
    "addr:postcode":"02169",
    "addr:street":"Park",
    "iso:country":"US",
    "sg:address":"2 Batterymarch Park",
    "sg:city":"Quincy",
    "sg:classifiers":[
        {
            "category":"Professional",
            "subcategory":"Advertising",
            "type":"Services"
        }
    ],
    "sg:phone":"+1 617 689 6900",
    "sg:postcode":"02169",
    "sg:province":"MA",
    "sg:tags":[
        "distribution"
    ],
    "wof:name":"Northeast Electrical Distr",
    "wof:placetype":"venue"
},
  "geometry": {"coordinates":[-71.02700900000001,42.23034],"type":"Point"}
}