{
  "type": "Feature",
  "properties": {
    "addr:full":"1852 Centre Street West Roxbury MA 02132",
    "addr:housenumber":"1852",
    "addr:postcode":"02132",
    "addr:street":"Centre Street",
    "iso:country":"US",
    "sg:address":"1852 Centre Street",
    "sg:city":"West Roxbury",
    "sg:classifiers":[
        {
            "category":"Health Services",
            "subcategory":"Dentist",
            "type":"Services"
        }
    ],
    "sg:phone":"+1 617 325 3700",
    "sg:postcode":"02132",
    "sg:province":"MA",
    "sg:website":"www.gentledental.com",
    "wof:name":"Gentle Dental",
    "wof:placetype":"venue"
},
  "geometry": {"coordinates":[-71.154639,42.286235],"type":"Point"}
}