{
  "type": "Feature",
  "properties": {
    "addr:full": "1534 Commonwealth Avenue # 1 Brighton MA 02135",
    "addr:housenumber": "1534",
    "addr:postcode": "02135",
    "addr:street": "Commonwealth Avenue # 1",
    "iso:country": "US",
    "sg:address": "1534 Commonwealth Avenue # 1",
    "sg:city": "Brighton",
    "sg:classifiers": [
      {
        "category": "Building \u0026 Trades",
        "subcategory": "Cleaning \u0026 Sanitation",
        "type": "Services"
      }
    ],
    "sg:phone": "+1 617 264 7535",
    "sg:postcode": "02135",
    "sg:province": "MA",
    "sg:tags": [
      "home"
    ],
    "wof:name": "Casa DO Zequita",
    "wof:placetype": "venue"
  },
  "geometry": {"coordinates":[-71.141791,42.345098],"type":"Point"}
}
