{
  "type": "Feature",
  "properties": {
    "iso:country":"US",
    "sg:address":"1534 Commonwealth Avenue # 1",
    "sg:city":"Brighton",
    "sg:classifiers":[
        {
            "category":"Building & Trades",
            "subcategory":"Cleaning & Sanitation",
            "type":"Services"
        }
    ],
    "sg:phone":"+1 617 264 7535",
    "sg:postcode":"02135",
    "sg:province":"MA",
    "sg:tags":[
        "home"
    ],
    "wof:name":"Casa DO Zequita",
    "wof:placetype":"venue"
},
  "geometry": {"coordinates":[-71.141791,42.345098],"type":"Point"}
}