{
  "type": "Feature",
  "properties": {
    "iso:country":"US",
    "sg:address":"334 Washington St",
    "sg:city":"Arlington",
    "sg:classifiers":[
        {
            "category":"Building & Trades",
            "subcategory":"Electrical",
            "type":"Services"
        }
    ],
    "sg:phone":"+1 781 643 5662",
    "sg:postcode":"02474",
    "sg:province":"MA",
    "sg:tags":[
        "electric",
        "contractor"
    ],
    "wof:name":"Jack Kelly Electric",
    "wof:placetype":"venue"
},
  "geometry": {"coordinates":[-71.173112,42.435033],"type":"Point"}
}