{
  "type": "Feature",
  "properties": {
    "addr:full":"35 Millbury St Auburn MA 01501",
    "addr:housenumber":"35",
    "addr:postcode":"01501",
    "addr:street":"Millbury St",
    "iso:country":"US",
    "sg:address":"35 Millbury St",
    "sg:city":"Auburn",
    "sg:classifiers":[
        {
            "category":"Health Services",
            "subcategory":"Doctor",
            "type":"Services"
        }
    ],
    "sg:phone":"+1 508 721 1195",
    "sg:postcode":"01501",
    "sg:province":"MA",
    "sg:tags":[
        "physician",
        "surgeon"
    ],
    "wof:name":"Fallon Medical Ctr",
    "wof:placetype":"venue"
},
  "geometry": {"coordinates":[-71.82895499999999,42.201355],"type":"Point"}
}