{
  "type": "Feature",
  "properties": {
    "iso:country":"US",
    "sg:address":"95 N Franklin St",
    "sg:city":"Holbrook",
    "sg:classifiers":[
        {
            "category":"Banks & Credit Unions",
            "subcategory":"Bank",
            "type":"Services"
        }
    ],
    "sg:phone":"+1 781 767 1888",
    "sg:postcode":"02343",
    "sg:province":"MA",
    "wof:name":"Holbrook Co-Operative Bank",
    "wof:placetype":"venue"
},
  "geometry": {"coordinates":[-71.00861,42.155982],"type":"Point"}
}