{
  "type": "Feature",
  "properties": {
    "addr:full":"124 2nd St Chelsea MA 02150",
    "addr:housenumber":"124",
    "addr:postcode":"02150",
    "addr:street":"2Nd St",
    "iso:country":"US",
    "sg:address":"124 2nd St",
    "sg:city":"Chelsea",
    "sg:classifiers":[
        {
            "category":"Professional",
            "subcategory":"Advertising",
            "type":"Services"
        }
    ],
    "sg:phone":"+1 617 889 2658",
    "sg:postcode":"02150",
    "sg:province":"MA",
    "sg:tags":[
        "mailing",
        "shipping"
    ],
    "wof:name":"Watson Mailing Svc",
    "wof:placetype":"venue"
},
  "geometry": {"coordinates":[-71.042771,42.393144],"type":"Point"}
}