{
  "type": "Feature",
  "properties": {
    "addr:full": "35 Hampden Rd Mansfield MA 02048",
    "addr:housenumber": "35",
    "addr:postcode": "02048",
    "addr:street": "Hampden Rd",
    "iso:country": "US",
    "sg:address": "35 Hampden Rd",
    "sg:city": "Mansfield",
    "sg:classifiers": [
      {
        "category": "Professional",
        "subcategory": "Management \u0026 Consulting",
        "type": "Services"
      }
    ],
    "sg:phone": "+1 508 261 7007",
    "sg:postcode": "02048",
    "sg:province": "MA",
    "sg:tags": [
      "communications",
      "consultant"
    ],
    "sg:website": "www.sbs.com",
    "wof:name": "SBS Technologies-Comms \u0026 Ents",
    "wof:placetype": "venue"
  },
  "geometry": {"coordinates":[-71.236584,42.019301],"type":"Point"}
}
