{
  "type": "Feature",
  "properties": {
    "addr:full": "40 Nagog Park Acton MA 01720",
    "addr:housenumber": "40",
    "addr:postcode": "01720",
    "addr:street": "Nagog Park",
    "iso:country": "US",
    "sg:address": "40 Nagog Park",
    "sg:city": "Acton",
    "sg:classifiers": [
      {
        "category": "Manufacturing",
        "subcategory": "Electronics",
        "type": "Manufacturing \u0026 Wholesale Goods"
      }
    ],
    "sg:phone": "+1 978 929 9889",
    "sg:postcode": "01720",
    "sg:province": "MA",
    "sg:tags": [
      "semiconductor",
      "devices"
    ],
    "wof:name": "Engim Inc",
    "wof:placetype": "venue"
  },
  "geometry": {"coordinates":[-71.431896,42.525096],"type":"Point"}
}
