{
  "type": "Feature",
  "properties": {
    "iso:country":"US",
    "sg:address":"40 Nagog Park",
    "sg:city":"Acton",
    "sg:classifiers":[
        {
            "category":"Manufacturing",
            "subcategory":"Electronics",
            "type":"Manufacturing & Wholesale Goods"
        }
    ],
    "sg:phone":"+1 978 929 9889",
    "sg:postcode":"01720",
    "sg:province":"MA",
    "sg:tags":[
        "semiconductor",
        "devices"
    ],
    "wof:name":"Engim Inc",
    "wof:placetype":"venue"
},
  "geometry": {"coordinates":[-71.43189599999999,42.525096],"type":"Point"}
}