{
  "type": "Feature",
  "properties": {
    "iso:country":"US",
    "sg:address":"87 Main St",
    "sg:city":"Rutland",
    "sg:classifiers":[
        {
            "category":"Wholesale",
            "subcategory":"Construction Materials",
            "type":"Manufacturing & Wholesale Goods"
        }
    ],
    "sg:phone":"+1 508 886 2921",
    "sg:postcode":"01543",
    "sg:province":"MA",
    "sg:tags":[
        "kitchen",
        "cabinet"
    ],
    "sg:website":"www.blairhomes.com",
    "wof:name":"Central New England Distribtng",
    "wof:placetype":"venue"
},
  "geometry": {"coordinates":[-71.93597699999999,42.377497],"type":"Point"}
}