{
  "type": "Feature",
  "properties": {
    "addr:full": "87 Main St Rutland MA 01543",
    "addr:housenumber": "87",
    "addr:postcode": "01543",
    "addr:street": "Main St",
    "iso:country": "US",
    "sg:address": "87 Main St",
    "sg:city": "Rutland",
    "sg:classifiers": [
      {
        "category": "Wholesale",
        "subcategory": "Construction Materials",
        "type": "Manufacturing \u0026 Wholesale Goods"
      }
    ],
    "sg:phone": "+1 508 886 2921",
    "sg:postcode": "01543",
    "sg:province": "MA",
    "sg:tags": [
      "kitchen",
      "cabinet"
    ],
    "sg:website": "www.blairhomes.com",
    "wof:name": "Central New England Distribtng",
    "wof:placetype": "venue"
  },
  "geometry": {"coordinates":[-71.935977,42.377497],"type":"Point"}
}
