{
  "type": "Feature",
  "properties": {
    "iso:country":"US",
    "sg:address":"303 Littleton Rd",
    "sg:city":"Chelmsford",
    "sg:classifiers":[
        {
            "category":"Professional",
            "subcategory":"Research",
            "type":"Services"
        }
    ],
    "sg:phone":"+1 978 250 8060",
    "sg:postcode":"01824",
    "sg:province":"MA",
    "sg:tags":[
        "development",
        "electronic"
    ],
    "sg:website":"www.assurtech.com",
    "wof:name":"Assurance Technology Corp",
    "wof:placetype":"venue"
},
  "geometry": {"coordinates":[-71.388724,42.582297],"type":"Point"}
}