{
  "type": "Feature",
  "properties": {
    "addr:full":"946 Great Plain Ave Needham MA 02492",
    "addr:housenumber":"946",
    "addr:postcode":"02492",
    "addr:street":"Great Plain Ave",
    "iso:country":"US",
    "sg:address":"946 Great Plain Ave",
    "sg:city":"Needham",
    "sg:classifiers":[
        {
            "category":"Communications",
            "subcategory":"News Services",
            "type":"Services"
        },
        {
            "category":"Transit Center",
            "subcategory":"Freight",
            "type":"Transportation"
        },
        {
            "category":"Professional",
            "subcategory":"Business Services",
            "type":"Services"
        },
        {
            "category":"Professional",
            "subcategory":"Printing & Photocopies",
            "type":"Services"
        },
        {
            "category":"Government",
            "subcategory":"Post Office",
            "type":"Public Place"
        }
    ],
    "sg:phone":"+1 781 433 2679",
    "sg:postcode":"02492",
    "sg:province":"MA",
    "sg:tags":[
        "cargo",
        "fax",
        "transparency",
        "package",
        "color",
        "express",
        "duplicating",
        "shipping",
        "mailbox-rental",
        "air",
        "copying",
        "mail",
        "print",
        "notary",
        "receiving",
        "photographic"
    ],
    "sg:website":"http://www.upsstore.com",
    "wof:name":"The UPS Store",
    "wof:placetype":"venue"
},
  "geometry": {"coordinates":[-71.235876,42.28027],"type":"Point"}
}