{
  "type": "Feature",
  "properties": {
    "addr:full": "406 S Huntington Ave Jamaica Plain MA 02130",
    "addr:housenumber": "406",
    "addr:postcode": "02130",
    "addr:street": "S Huntington Ave",
    "iso:country": "US",
    "sg:address": "406 S Huntington Ave",
    "sg:city": "Jamaica Plain",
    "sg:classifiers": [
      {
        "category": "Health Services",
        "subcategory": "Health Practitioner",
        "type": "Services"
      }
    ],
    "sg:phone": "+1 617 522 9100",
    "sg:postcode": "02130",
    "sg:province": "MA",
    "sg:tags": [
      "therapist",
      "physical"
    ],
    "wof:name": "South Huntington Physical Med",
    "wof:placetype": "venue"
  },
  "geometry": {"coordinates":[-71.111799,42.320709],"type":"Point"}
}
