{
  "type": "Feature",
  "properties": {
    "addr:full":"11 Jackson St Marshfield MA 02050",
    "addr:housenumber":"11",
    "addr:postcode":"02050",
    "addr:street":"Jackson St",
    "iso:country":"US",
    "sg:address":"11 Jackson St",
    "sg:city":"Marshfield",
    "sg:classifiers":[
        {
            "category":"Real Estate",
            "subcategory":"Real Estate Agent",
            "type":"Services"
        }
    ],
    "sg:phone":"+1   ",
    "sg:postcode":"02050",
    "sg:province":"MA",
    "wof:name":"Lorraine B Welch",
    "wof:placetype":"venue"
},
  "geometry": {"coordinates":[-70.673202,42.118428],"type":"Point"}
}