{
  "type": "Feature",
  "properties": {
    "addr:full": "98 Robinson Rd Acushnet MA 02743",
    "addr:housenumber": "98",
    "addr:postcode": "02743",
    "addr:street": "Robinson Rd",
    "iso:country": "US",
    "sg:address": "98 Robinson Rd",
    "sg:city": "Acushnet",
    "sg:classifiers": [
      {
        "category": "Manufacturing",
        "subcategory": "Tools \u0026 Machinery",
        "type": "Manufacturing \u0026 Wholesale Goods"
      }
    ],
    "sg:phone": "+1 508 763 4684",
    "sg:postcode": "02743",
    "sg:province": "MA",
    "sg:tags": [
      "equipment",
      "conveyor",
      "conveying"
    ],
    "wof:name": "RJP Freelance Fabricating",
    "wof:placetype": "venue"
  },
  "geometry": {"coordinates":[-70.89018,41.737984],"type":"Point"}
}
