{
  "type": "Feature",
  "properties": {
    "iso:country":"US",
    "sg:address":"69 North St",
    "sg:city":"Danvers",
    "sg:classifiers":[
        {
            "category":"Professional",
            "subcategory":"Business Services",
            "type":"Services"
        }
    ],
    "sg:phone":"+1 978 774 0003",
    "sg:postcode":"01923",
    "sg:province":"MA",
    "sg:tags":[
        "medical",
        "administration"
    ],
    "wof:name":"Dougald C Macgillivray Md",
    "wof:placetype":"venue"
},
  "geometry": {"coordinates":[-70.944149,42.590242],"type":"Point"}
}