{
  "type": "Feature",
  "properties": {
    "iso:country":"US",
    "sg:address":"21 Everett Ave",
    "sg:city":"Belchertown",
    "sg:classifiers":[
        {
            "category":"Professional",
            "subcategory":"Lawyer & Legal Services",
            "type":"Services"
        }
    ],
    "sg:phone":"+1 413 323 8800",
    "sg:postcode":"01007",
    "sg:province":"MA",
    "sg:tags":[
        "attorney"
    ],
    "wof:name":"Stoddard & Maynard",
    "wof:placetype":"venue"
},
  "geometry": {"coordinates":[-72.39741600000001,42.275663],"type":"Point"}
}