{
  "type": "Feature",
  "properties": {
    "addr:full": "21 Everett Ave Belchertown MA 01007",
    "addr:housenumber": "21",
    "addr:postcode": "01007",
    "addr:street": "Everett Ave",
    "iso:country": "US",
    "sg:address": "21 Everett Ave",
    "sg:city": "Belchertown",
    "sg:classifiers": [
      {
        "category": "Professional",
        "subcategory": "Lawyer \u0026 Legal Services",
        "type": "Services"
      }
    ],
    "sg:phone": "+1 413 323 8800",
    "sg:postcode": "01007",
    "sg:province": "MA",
    "sg:tags": [
      "attorney"
    ],
    "wof:name": "Stoddard \u0026 Maynard",
    "wof:placetype": "venue"
  },
  "geometry": {"coordinates":[-72.397416,42.275663],"type":"Point"}
}
