{
  "type": "Feature",
  "properties": {
    "iso:country":"US",
    "sg:address":"445 Concord Avenue",
    "sg:city":"Cambridge",
    "sg:classifiers":[
        {
            "category":"Shopping",
            "subcategory":"Antiques",
            "type":"Retail Goods"
        }
    ],
    "sg:phone":"+1 617 497 2204",
    "sg:postcode":"02138",
    "sg:province":"MA",
    "wof:name":"Show-Off Graphics & Display",
    "wof:placetype":"venue"
},
  "geometry": {"coordinates":[-71.139414,42.386072],"type":"Point"}
}