{
  "type": "Feature",
  "properties": {
    "addr:full": "26 Weston Ave Somerville MA 02144",
    "addr:housenumber": "26",
    "addr:postcode": "02144",
    "addr:street": "Weston Ave",
    "iso:country": "US",
    "sg:address": "26 Weston Ave",
    "sg:city": "Somerville",
    "sg:classifiers": [
      {
        "category": "Professional",
        "type": "Services"
      }
    ],
    "sg:phone": "+1 617 591 8266",
    "sg:postcode": "02144",
    "sg:province": "MA",
    "sg:tags": [
      "establishment"
    ],
    "wof:name": "Reune Inc",
    "wof:placetype": "venue"
  },
  "geometry": {"coordinates":[-71.128734,42.403058],"type":"Point"}
}
