{
  "type": "Feature",
  "properties": {
    "iso:country":"US",
    "sg:address":"12 Ericsson St",
    "sg:city":"Dorchester",
    "sg:classifiers":[
        {
            "category":"Building & Trades",
            "subcategory":"Electrical",
            "type":"Services"
        }
    ],
    "sg:phone":"+1 617 287 2464",
    "sg:postcode":"02122",
    "sg:province":"MA",
    "sg:tags":[
        "electric",
        "contractor"
    ],
    "wof:name":"City Lights Electrical",
    "wof:placetype":"venue"
},
  "geometry": {"coordinates":[-71.040724,42.291689],"type":"Point"}
}