{
  "type": "Feature",
  "properties": {
    "addr:full": "612 Middlesex Tpke Billerica MA 01821",
    "addr:housenumber": "612",
    "addr:postcode": "01821",
    "addr:street": "Middlesex Tpke",
    "iso:country": "US",
    "sg:address": "612 Middlesex Tpke",
    "sg:city": "Billerica",
    "sg:classifiers": [
      {
        "category": "Donuts",
        "subcategory": "None",
        "type": "Food \u0026 Drink"
      }
    ],
    "sg:phone": "+1 978 670 5482",
    "sg:postcode": "01821",
    "sg:province": "MA",
    "sg:website": "www.dunkindonuts.com",
    "wof:name": "Dunkin Donuts",
    "wof:placetype": "venue"
  },
  "geometry": {"coordinates":[-71.263159,42.533259],"type":"Point"}
}
