{
  "type": "Feature",
  "properties": {
    "addr:full":"2 Cable Hill Way Duxbury MA 02332",
    "addr:housenumber":"2",
    "addr:postcode":"02332",
    "addr:street":"Cable Hill Way",
    "iso:country":"US",
    "sg:address":"2 Cable Hill Way",
    "sg:city":"Duxbury",
    "sg:classifiers":[
        {
            "category":"Health Services",
            "subcategory":"Nursing And Care Facility",
            "type":"Services"
        }
    ],
    "sg:phone":"+1   ",
    "sg:postcode":"02332",
    "sg:province":"MA",
    "sg:tags":[
        "skilled"
    ],
    "wof:name":"Total Care Nursing Inc",
    "wof:placetype":"venue"
},
  "geometry": {"coordinates":[-70.64897999999999,42.064415],"type":"Point"}
}