{
  "type": "Feature",
  "properties": {
    "iso:country":"US",
    "sg:address":"31 Railroad St",
    "sg:city":"Great Barrington",
    "sg:classifiers":[
        {
            "category":"Home & Garden",
            "subcategory":"Home Furnishings",
            "type":"Retail Goods"
        }
    ],
    "sg:phone":"+1 413 528 0135",
    "sg:postcode":"01230",
    "sg:province":"MA",
    "sg:tags":[
        "utensil",
        "cooking"
    ],
    "wof:name":"Chef's Shop",
    "wof:placetype":"venue"
},
  "geometry": {"coordinates":[-73.363675,42.194894],"type":"Point"}
}