{
  "type": "Feature",
  "properties": {
    "addr:full": "16 Clarke St Lexington MA 02421",
    "addr:housenumber": "16",
    "addr:postcode": "02421",
    "addr:street": "Clarke St",
    "iso:country": "US",
    "sg:address": "16 Clarke St",
    "sg:city": "Lexington",
    "sg:classifiers": [
      {
        "category": "Health Services",
        "subcategory": "Optometrist",
        "type": "Services"
      }
    ],
    "sg:phone": "+1 781 676 2020",
    "sg:postcode": "02421",
    "sg:province": "MA",
    "wof:name": "Zhang Yi Lin",
    "wof:placetype": "venue"
  },
  "geometry": {"coordinates":[-71.230749,42.447404],"type":"Point"}
}
