{
  "type": "Feature",
  "properties": {
    "addr:full":"25 Franklin Ave Oak Bluffs MA 02557",
    "addr:housenumber":"25",
    "addr:postcode":"02557",
    "addr:street":"Franklin Ave",
    "iso:country":"US",
    "sg:address":"25 Franklin Ave",
    "sg:city":"Oak Bluffs",
    "sg:classifiers":[
        {
            "category":"Farming",
            "subcategory":"Vineyard",
            "type":"Manufacturing & Wholesale Goods"
        }
    ],
    "sg:phone":"+1 508 693 9590",
    "sg:postcode":"02557",
    "sg:province":"MA",
    "wof:name":"Martha's Vineyard Sound",
    "wof:placetype":"venue"
},
  "geometry": {"coordinates":[-70.56622900000001,41.450756],"type":"Point"}
}