{
  "type": "Feature",
  "properties": {
    "iso:country":"US",
    "sg:address":"580 Harrison Ave",
    "sg:city":"Boston",
    "sg:classifiers":[
        {
            "category":"Professional",
            "subcategory":"Management & Consulting",
            "type":"Services"
        }
    ],
    "sg:phone":"+1 617 357 6483",
    "sg:postcode":"02118",
    "sg:province":"MA",
    "sg:tags":[
        "marketing",
        "program"
    ],
    "wof:name":"Art Enterprise",
    "wof:placetype":"venue"
},
  "geometry": {"coordinates":[-71.067803,42.340755],"type":"Point"}
}