{
  "type": "Feature",
  "properties": {
    "addr:full": "1 Davis Sq Somerville MA 02144",
    "addr:housenumber": "1",
    "addr:postcode": "02144",
    "addr:street": "Davis Sq",
    "atp:label": "CVS, 1 Davis Sq Somerville MA US",
    "atp:similarity": 2.824728012084961,
    "iso:country": "US",
    "sg:address": "1 Davis Sq",
    "sg:city": "Somerville",
    "sg:classifiers": [
      {
        "category": "Shopping",
        "subcategory": "Pharmacy",
        "type": "Retail Goods"
      }
    ],
    "sg:phone": "+1 617 629 4156",
    "sg:postcode": "02144",
    "sg:province": "MA",
    "sg:tags": [
      "drugstore"
    ],
    "sg:website": "www.cvs.com",
    "wof:name": "CVS",
    "wof:placetype": "venue"
  },
  "geometry": {"coordinates":[-71.122316,42.396476],"type":"Point"}
}
