{
  "type": "Feature",
  "properties": {
    "addr:full": "242 Union St Rockland MA 02370",
    "addr:housenumber": "242",
    "addr:postcode": "02370",
    "addr:street": "Union St",
    "iso:country": "US",
    "sg:address": "242 Union St",
    "sg:city": "Rockland",
    "sg:classifiers": [
      {
        "category": "Government",
        "subcategory": "Office",
        "type": "Public Place"
      }
    ],
    "sg:phone": "+1 781 871 4183",
    "sg:postcode": "02370",
    "sg:province": "MA",
    "sg:tags": [
      "village"
    ],
    "wof:name": "Rockland Planning Dept",
    "wof:placetype": "venue"
  },
  "geometry": {"coordinates":[-70.915089,42.128461],"type":"Point"}
}
