{
  "type": "Feature",
  "properties": {
    "addr:full": "70 S Main St Fall River MA 02721",
    "addr:housenumber": "70",
    "addr:postcode": "02721",
    "addr:street": "S Main St",
    "iso:country": "US",
    "sg:address": "70 S Main St",
    "sg:city": "Fall River",
    "sg:classifiers": [
      {
        "category": "Professional",
        "subcategory": "Lawyer \u0026 Legal Services",
        "type": "Services"
      }
    ],
    "sg:phone": "+1 508 675 7896",
    "sg:postcode": "02721",
    "sg:province": "MA",
    "sg:tags": [
      "attorney"
    ],
    "wof:name": "Mcquire \u0026 Coughlin",
    "wof:placetype": "venue"
  },
  "geometry": {"coordinates":[-71.156163,41.700373],"type":"Point"}
}
