{
  "type": "Feature",
  "properties": {
    "iso:country":"US",
    "sg:address":"70 S Main St",
    "sg:city":"Fall River",
    "sg:classifiers":[
        {
            "category":"Professional",
            "subcategory":"Lawyer & Legal Services",
            "type":"Services"
        }
    ],
    "sg:phone":"+1 508 675 7896",
    "sg:postcode":"02721",
    "sg:province":"MA",
    "sg:tags":[
        "attorney"
    ],
    "wof:name":"Mcquire & Coughlin",
    "wof:placetype":"venue"
},
  "geometry": {"coordinates":[-71.15616300000001,41.700373],"type":"Point"}
}