{
  "type": "Feature",
  "properties": {
    "addr:full":"37 Davis Sq Somerville MA 02144",
    "addr:housenumber":"37",
    "addr:postcode":"02144",
    "addr:street":"Davis Sq",
    "iso:country":"US",
    "sg:address":"37 Davis Sq",
    "sg:city":"Somerville",
    "sg:classifiers":[
        {
            "category":"Restaurant",
            "type":"Food & Drink"
        }
    ],
    "sg:menulink":"http://www.allmenus.com/ma/somerville/282839-boston-burger-company/menu/",
    "sg:phone":"+1 617 440 7360",
    "sg:postcode":"02144",
    "sg:province":"MA",
    "sg:tags":[
        "burger",
        "american"
    ],
    "wof:name":"Boston Burger Company",
    "wof:placetype":"venue"
},
  "geometry": {"coordinates":[-71.122507,42.396503],"type":"Point"}
}