{
  "type": "Feature",
  "properties": {
    "addr:full":"380 School St Winchendon MA 01475",
    "addr:housenumber":"380",
    "addr:postcode":"01475",
    "addr:street":"School St",
    "iso:country":"US",
    "sg:address":"380 School St",
    "sg:city":"Winchendon",
    "sg:classifiers":[
        {
            "category":"Shopping",
            "type":"Retail Goods"
        }
    ],
    "sg:phone":"+1 978 297 2518",
    "sg:postcode":"01475",
    "sg:province":"MA",
    "sg:tags":[
        "pet",
        "food",
        "supply"
    ],
    "wof:name":"Horse & Buggy Feeds",
    "wof:placetype":"venue"
},
  "geometry": {"coordinates":[-72.060458,42.693738],"type":"Point"}
}