{
  "type": "Feature",
  "properties": {
    "addr:full": "20 Aegean Dr Methuen MA 01844",
    "addr:housenumber": "20",
    "addr:postcode": "01844",
    "addr:street": "Aegean Dr",
    "iso:country": "US",
    "sg:address": "20 Aegean Dr",
    "sg:city": "Methuen",
    "sg:classifiers": [
      {
        "category": "Building \u0026 Trades",
        "subcategory": "Plumbing",
        "type": "Services"
      }
    ],
    "sg:phone": "+1 978 685 6711",
    "sg:postcode": "01844",
    "sg:province": "MA",
    "sg:tags": [
      "heating",
      "contractor"
    ],
    "wof:name": "Process Piping Co",
    "wof:placetype": "venue"
  },
  "geometry": {"coordinates":[-71.214258,42.732106],"type":"Point"}
}
