{
  "type": "Feature",
  "properties": {
    "iso:country":"US",
    "sg:address":"384 Shoemaker Ln",
    "sg:city":"Agawam",
    "sg:classifiers":[
        {
            "category":"Bus Charters",
            "type":"Transportation"
        }
    ],
    "sg:phone":"+1 413 789 2039",
    "sg:postcode":"01001",
    "sg:province":"MA",
    "sg:tags":[
        "local",
        "except"
    ],
    "wof:name":"Five Star Tours",
    "wof:placetype":"venue"
},
  "geometry": {"coordinates":[-72.654703,42.048542],"type":"Point"}
}