{
  "type": "Feature",
  "properties": {
    "addr:full":"3920 Mystic Valley Parkway Ofc Medford MA 02155",
    "addr:housenumber":"3920",
    "addr:postcode":"02155",
    "addr:street":"Mystic Valley Parkway",
    "iso:country":"US",
    "sg:address":"3920 Mystic Valley Parkway Ofc",
    "sg:city":"Medford",
    "sg:classifiers":[
        {
            "category":"Building & Trades",
            "subcategory":"Pest Control",
            "type":"Services"
        }
    ],
    "sg:phone":"+1 781 396 6311",
    "sg:postcode":"02155",
    "sg:province":"MA",
    "wof:name":"Royal Pest Control",
    "wof:placetype":"venue"
},
  "geometry": {"coordinates":[-71.09083,42.404488],"type":"Point"}
}