{
  "type": "Feature",
  "properties": {
    "addr:full": "44 Winslow St Cambridge MA 02138",
    "addr:housenumber": "44",
    "addr:postcode": "02138",
    "addr:street": "Winslow St",
    "iso:country": "US",
    "sg:address": "44 Winslow St",
    "sg:city": "Cambridge",
    "sg:classifiers": [
      {
        "category": "Professional",
        "subcategory": "Management \u0026 Consulting",
        "type": "Services"
      }
    ],
    "sg:phone": "+1   ",
    "sg:postcode": "02138",
    "sg:province": "MA",
    "sg:tags": [
      "business"
    ],
    "wof:name": "Lynne Rosansky",
    "wof:placetype": "venue"
  },
  "geometry": {"coordinates":[-71.129068,42.384808],"type":"Point"}
}
