{
  "type": "Feature",
  "properties": {
    "iso:country":"US",
    "sg:address":"9 Fairview Rd",
    "sg:city":"Medfield",
    "sg:classifiers":[
        {
            "category":"Shopping",
            "subcategory":"Gifts & Souvenirs",
            "type":"Retail Goods"
        }
    ],
    "sg:phone":"+1 508 359 9010",
    "sg:postcode":"02052",
    "sg:province":"MA",
    "sg:tags":[
        "basket",
        "parcel"
    ],
    "wof:name":"Baskets & Beyond Inc",
    "wof:placetype":"venue"
},
  "geometry": {"coordinates":[-71.287004,42.183847],"type":"Point"}
}