{
  "type": "Feature",
  "properties": {
    "addr:full": "12 Blakeslee St Cambridge MA 02138",
    "addr:housenumber": "12",
    "addr:postcode": "02138",
    "addr:street": "Blakeslee St",
    "iso:country": "US",
    "sg:address": "12 Blakeslee St",
    "sg:city": "Cambridge",
    "sg:classifiers": [
      {
        "category": "Professional",
        "subcategory": "Engineering",
        "type": "Services"
      }
    ],
    "sg:phone": "+1 617 661 0011",
    "sg:postcode": "02138",
    "sg:province": "MA",
    "sg:tags": [
      "consulting",
      "engineer"
    ],
    "wof:name": "Blakeslee Engineering",
    "wof:placetype": "venue"
  },
  "geometry": {"coordinates":[-71.135931,42.38048],"type":"Point"}
}
