{
  "type": "Feature",
  "properties": {
    "iso:country":"US",
    "sg:address":"1038 Wilbraham Rd",
    "sg:city":"Springfield",
    "sg:classifiers":[
        {
            "category":"Food & Beverages",
            "subcategory":"Liquor & Beverages",
            "type":"Retail Goods"
        }
    ],
    "sg:phone":"+1 413 783 0761",
    "sg:postcode":"01109",
    "sg:province":"MA",
    "sg:tags":[
        "beer",
        "ale"
    ],
    "wof:name":"Winn Liquors",
    "wof:placetype":"venue"
},
  "geometry": {"coordinates":[-72.52597400000001,42.115701],"type":"Point"}
}