{
  "type": "Feature",
  "properties": {
    "addr:full": "1038 Wilbraham Rd Springfield MA 01109",
    "addr:housenumber": "1038",
    "addr:postcode": "01109",
    "addr:street": "Wilbraham Rd",
    "iso:country": "US",
    "sg:address": "1038 Wilbraham Rd",
    "sg:city": "Springfield",
    "sg:classifiers": [
      {
        "category": "Food \u0026 Beverages",
        "subcategory": "Liquor \u0026 Beverages",
        "type": "Retail Goods"
      }
    ],
    "sg:phone": "+1 413 783 0761",
    "sg:postcode": "01109",
    "sg:province": "MA",
    "sg:tags": [
      "beer",
      "ale"
    ],
    "wof:name": "Winn Liquors",
    "wof:placetype": "venue"
  },
  "geometry": {"coordinates":[-72.525974,42.115701],"type":"Point"}
}
