{
  "type": "Feature",
  "properties": {
    "addr:full": "111 State St Boston MA 02109",
    "addr:housenumber": "111",
    "addr:postcode": "02109",
    "addr:street": "State St",
    "iso:country": "US",
    "sg:address": "111 State St",
    "sg:city": "Boston",
    "sg:classifiers": [
      {
        "category": "Professional",
        "subcategory": "Accounting \u0026 Tax Preparation",
        "type": "Services"
      }
    ],
    "sg:phone": "+1 617 742 1188",
    "sg:postcode": "02109",
    "sg:province": "MA",
    "sg:tags": [
      "accountant"
    ],
    "wof:name": "Herscott Cooper \u0026 Co",
    "wof:placetype": "venue"
  },
  "geometry": {"coordinates":[-71.054826,42.359118],"type":"Point"}
}
