{
  "type": "Feature",
  "properties": {
    "addr:full": "211 S Main St Natick MA 01760",
    "addr:housenumber": "211",
    "addr:postcode": "01760",
    "addr:street": "S Main St",
    "iso:country": "US",
    "sg:address": "211 S Main St",
    "sg:city": "Natick",
    "sg:classifiers": [
      {
        "category": "Building \u0026 Trades",
        "subcategory": "Construction",
        "type": "Services"
      }
    ],
    "sg:phone": "+1 508 653 7800",
    "sg:postcode": "01760",
    "sg:province": "MA",
    "sg:tags": [
      "pavement",
      "marking"
    ],
    "wof:name": "Framingham Asphalt Maintenance",
    "wof:placetype": "venue"
  },
  "geometry": {"coordinates":[-71.355974,42.27054],"type":"Point"}
}
