{
  "type": "Feature",
  "properties": {
    "iso:country":"US",
    "sg:address":"211 S Main St",
    "sg:city":"Natick",
    "sg:classifiers":[
        {
            "category":"Building & Trades",
            "subcategory":"Construction",
            "type":"Services"
        }
    ],
    "sg:phone":"+1 508 653 7800",
    "sg:postcode":"01760",
    "sg:province":"MA",
    "sg:tags":[
        "pavement",
        "marking"
    ],
    "wof:name":"Framingham Asphalt Maintenance",
    "wof:placetype":"venue"
},
  "geometry": {"coordinates":[-71.355974,42.27054],"type":"Point"}
}