{
  "type": "Feature",
  "properties": {
    "addr:full":"97 Hamilton St Worcester MA 01604",
    "addr:housenumber":"97",
    "addr:postcode":"01604",
    "addr:street":"Hamilton St",
    "iso:country":"US",
    "sg:address":"97 Hamilton St",
    "sg:city":"Worcester",
    "sg:classifiers":[
        {
            "category":"Building & Trades",
            "subcategory":"Plumbing",
            "type":"Services"
        }
    ],
    "sg:phone":"+1 508 756 2862",
    "sg:postcode":"01604",
    "sg:province":"MA",
    "sg:tags":[
        "plumbing",
        "contractor"
    ],
    "wof:name":"George J Arraj",
    "wof:placetype":"venue"
},
  "geometry": {"coordinates":[-71.780021,42.256163],"type":"Point"}
}