{
  "type": "Feature",
  "properties": {
    "addr:full":"44 State St Lynn MA 01901",
    "addr:housenumber":"44",
    "addr:postcode":"01901",
    "addr:street":"State St",
    "iso:country":"US",
    "sg:address":"44 State St",
    "sg:city":"Lynn",
    "sg:classifiers":[
        {
            "category":"Food & Beverages",
            "subcategory":"Liquor & Beverages",
            "type":"Retail Goods"
        }
    ],
    "sg:phone":"+1 781 595 9780",
    "sg:postcode":"01901",
    "sg:province":"MA",
    "wof:name":"State Street Liquors",
    "wof:placetype":"venue"
},
  "geometry": {"coordinates":[-70.94896300000001,42.461718],"type":"Point"}
}