{
  "type": "Feature",
  "properties": {
    "addr:full": "122 S Broadway Lawrence MA 01843",
    "addr:housenumber": "122",
    "addr:postcode": "01843",
    "addr:street": "S Broadway",
    "iso:country": "US",
    "sg:address": "122 S Broadway",
    "sg:city": "Lawrence",
    "sg:classifiers": [
      {
        "category": "Personal",
        "subcategory": "Beauty Salon",
        "type": "Services"
      }
    ],
    "sg:phone": "+1 978 686 8887",
    "sg:postcode": "01843",
    "sg:province": "MA",
    "wof:name": "El Corte Magico",
    "wof:placetype": "venue"
  },
  "geometry": {"coordinates":[-71.163348,42.697043],"type":"Point"}
}
