{
  "type": "Feature",
  "properties": {
    "addr:full": "2 Brown Ave Winchendon MA 01475",
    "addr:housenumber": "2",
    "addr:postcode": "01475",
    "addr:street": "Brown Ave",
    "iso:country": "US",
    "sg:address": "2 Brown Ave",
    "sg:city": "Winchendon",
    "sg:classifiers": [
      {
        "category": "Wholesale",
        "subcategory": "Electrical",
        "type": "Manufacturing \u0026 Wholesale Goods"
      }
    ],
    "sg:phone": "+1 978 297 1713",
    "sg:postcode": "01475",
    "sg:province": "MA",
    "sg:tags": [
      "communication",
      "radio",
      "system"
    ],
    "wof:name": "Smith Electronics",
    "wof:placetype": "venue"
  },
  "geometry": {"coordinates":[-72.051099,42.696576],"type":"Point"}
}
