{
  "type": "Feature",
  "properties": {
    "iso:country":"US",
    "sg:address":"2 Brown Ave",
    "sg:city":"Winchendon",
    "sg:classifiers":[
        {
            "category":"Wholesale",
            "subcategory":"Electrical",
            "type":"Manufacturing & Wholesale Goods"
        }
    ],
    "sg:phone":"+1 978 297 1713",
    "sg:postcode":"01475",
    "sg:province":"MA",
    "sg:tags":[
        "communication",
        "radio",
        "system"
    ],
    "wof:name":"Smith Electronics",
    "wof:placetype":"venue"
},
  "geometry": {"coordinates":[-72.05109899999999,42.696576],"type":"Point"}
}