{
  "type": "Feature",
  "properties": {
    "addr:full":"80 Boylston St Jamaica Plain MA 02130",
    "addr:housenumber":"80",
    "addr:postcode":"02130",
    "addr:street":"Boylston St",
    "iso:country":"US",
    "sg:address":"80 Boylston St",
    "sg:city":"Jamaica Plain",
    "sg:classifiers":[
        {
            "category":"Food & Beverages",
            "subcategory":"Liquor & Beverages",
            "type":"Retail Goods"
        }
    ],
    "sg:phone":"+1 617 524 0740",
    "sg:postcode":"02130",
    "sg:province":"MA",
    "sg:tags":[
        "beer",
        "spirit",
        "wine"
    ],
    "wof:name":"Stonybrook Wine and Spirits",
    "wof:placetype":"venue"
},
  "geometry": {"coordinates":[-71.105279,42.316985],"type":"Point"}
}