{
  "type": "Feature",
  "properties": {
    "addr:full":"100 Searsville Rd South Dennis MA 02660",
    "addr:housenumber":"100",
    "addr:postcode":"02660",
    "addr:street":"Searsville Rd",
    "iso:country":"US",
    "sg:address":"100 Searsville Rd",
    "sg:city":"South Dennis",
    "sg:classifiers":[
        {
            "category":"Retail",
            "subcategory":"Repair Shop",
            "type":"Services"
        }
    ],
    "sg:phone":"+1 508 398 3810",
    "sg:postcode":"02660",
    "sg:province":"MA",
    "sg:tags":[
        "upholsterer"
    ],
    "wof:name":"Gramm's Workshop",
    "wof:placetype":"venue"
},
  "geometry": {"coordinates":[-70.142382,41.683189],"type":"Point"}
}