{
  "type": "Feature",
  "properties": {
    "addr:full":"200 Woodland Rd Southborough MA 01772",
    "addr:housenumber":"200",
    "addr:postcode":"01772",
    "addr:street":"Woodland Rd",
    "iso:country":"US",
    "sg:address":"200 Woodland Rd",
    "sg:city":"Southborough",
    "sg:classifiers":[
        {
            "category":"Professional",
            "subcategory":"Business Services",
            "type":"Services"
        }
    ],
    "sg:phone":"+1   ",
    "sg:postcode":"01772",
    "sg:province":"MA",
    "wof:name":"Gst Land Management Corp",
    "wof:placetype":"venue"
},
  "geometry": {"coordinates":[-71.522139,42.272395],"type":"Point"}
}