{
  "type": "Feature",
  "properties": {
    "addr:full":"1743 Washington St Canton MA 02021",
    "addr:housenumber":"1743",
    "addr:postcode":"02021",
    "addr:street":"Washington St",
    "iso:country":"US",
    "sg:address":"1743 Washington St",
    "sg:city":"Canton",
    "sg:classifiers":[
        {
            "category":"Professional",
            "subcategory":"Computer Services",
            "type":"Services"
        }
    ],
    "sg:phone":"+1 781 828 1208",
    "sg:postcode":"02021",
    "sg:province":"MA",
    "sg:tags":[
        "repair"
    ],
    "wof:name":"Vbrick Systems - CLOSED",
    "wof:placetype":"venue"
},
  "geometry": {"coordinates":[-71.12640399999999,42.182701],"type":"Point"}
}