{
  "type": "Feature",
  "properties": {
    "iso:country":"US",
    "sg:address":"2 Taggert Ct",
    "sg:city":"Ashland",
    "sg:classifiers":[
        {
            "category":"Professional",
            "subcategory":"Art Services",
            "type":"Services"
        }
    ],
    "sg:phone":"+1 508 881 5455",
    "sg:postcode":"01721",
    "sg:province":"MA",
    "sg:tags":[
        "calligrapher"
    ],
    "wof:name":"Social Scribe",
    "wof:placetype":"venue"
},
  "geometry": {"coordinates":[-71.494979,42.26809],"type":"Point"}
}