{
  "type": "Feature",
  "properties": {
    "addr:full":"4 Ferdie Rd Hubbardston MA 01452",
    "addr:housenumber":"4",
    "addr:postcode":"01452",
    "addr:street":"Ferdie Rd",
    "iso:country":"US",
    "sg:address":"4 Ferdie Rd",
    "sg:city":"Hubbardston",
    "sg:classifiers":[
        {
            "category":"Professional",
            "subcategory":"Management & Consulting",
            "type":"Services"
        }
    ],
    "sg:phone":"+1   ",
    "sg:postcode":"01452",
    "sg:province":"MA",
    "sg:tags":[
        "business"
    ],
    "wof:name":"Stillwater Consultants",
    "wof:placetype":"venue"
},
  "geometry": {"coordinates":[-72.037081,42.453281],"type":"Point"}
}