{
  "type": "Feature",
  "properties": {
    "addr:full": "17 Market St Northampton MA 01060",
    "addr:housenumber": "17",
    "addr:postcode": "01060",
    "addr:street": "Market St",
    "iso:country": "US",
    "ovtr:label": "Market Street Laundry, 17 Market St Northampton MA US",
    "ovtr:similarity": 2.8638079166412354,
    "sg:address": "17 Market St",
    "sg:city": "Northampton",
    "sg:classifiers": [
      {
        "category": "Retail",
        "subcategory": "Laundry \u0026 Dry Cleaning",
        "type": "Services"
      }
    ],
    "sg:phone": "+1 413 582 0433",
    "sg:postcode": "01060",
    "sg:province": "MA",
    "wof:name": "Market Street Laundry",
    "wof:placetype": "venue"
  },
  "geometry": {"coordinates":[-72.628621,42.321046],"type":"Point"}
}
