{
  "type": "Feature",
  "properties": {
    "addr:full": "727 Main St North Oxford MA 01537",
    "addr:housenumber": "727",
    "addr:postcode": "01537",
    "addr:street": "Main St",
    "iso:country": "US",
    "sg:address": "727 Main St",
    "sg:city": "North Oxford",
    "sg:classifiers": [
      {
        "category": "Retail",
        "subcategory": "Auto Repair",
        "type": "Services"
      }
    ],
    "sg:phone": "+1 508 987 7760",
    "sg:postcode": "01537",
    "sg:province": "MA",
    "sg:tags": [
      "recreational",
      "vehicle"
    ],
    "wof:name": "Rv's R Us Inc",
    "wof:placetype": "venue"
  },
  "geometry": {"coordinates":[-71.883317,42.16874],"type":"Point"}
}
