{
  "type": "Feature",
  "properties": {
    "iso:country":"US",
    "sg:address":"727 Main St",
    "sg:city":"North Oxford",
    "sg:classifiers":[
        {
            "category":"Retail",
            "subcategory":"Auto Repair",
            "type":"Services"
        }
    ],
    "sg:phone":"+1 508 987 7760",
    "sg:postcode":"01537",
    "sg:province":"MA",
    "sg:tags":[
        "recreational",
        "vehicle"
    ],
    "wof:name":"Rv's R Us Inc",
    "wof:placetype":"venue"
},
  "geometry": {"coordinates":[-71.88331700000001,42.16874],"type":"Point"}
}