{
  "type": "Feature",
  "properties": {
    "addr:full": "1357 Main St Acushnet MA 02743",
    "addr:housenumber": "1357",
    "addr:postcode": "02743",
    "addr:street": "Main St",
    "iso:country": "US",
    "sg:address": "1357 Main St",
    "sg:city": "Acushnet",
    "sg:classifiers": [
      {
        "category": "Freight",
        "type": "Transportation"
      }
    ],
    "sg:phone": "+1 508 763 4322",
    "sg:postcode": "02743",
    "sg:province": "MA",
    "sg:tags": [
      "trucking"
    ],
    "wof:name": "T D Transportation \u0026 Brokerage",
    "wof:placetype": "venue"
  },
  "geometry": {"coordinates":[-70.902659,41.750983],"type":"Point"}
}
