{
  "type": "Feature",
  "properties": {
    "iso:country":"US",
    "sg:address":"1357 Main St",
    "sg:city":"Acushnet",
    "sg:classifiers":[
        {
            "category":"Freight",
            "type":"Transportation"
        }
    ],
    "sg:phone":"+1 508 763 4322",
    "sg:postcode":"02743",
    "sg:province":"MA",
    "sg:tags":[
        "trucking"
    ],
    "wof:name":"T D Transportation & Brokerage",
    "wof:placetype":"venue"
},
  "geometry": {"coordinates":[-70.902659,41.750983],"type":"Point"}
}