{
  "type": "Feature",
  "properties": {
    "addr:full":"222 Forbes Rd Braintree MA 02184",
    "addr:housenumber":"222",
    "addr:postcode":"02184",
    "addr:street":"Forbes Rd",
    "iso:country":"US",
    "sg:address":"222 Forbes Rd",
    "sg:city":"Braintree",
    "sg:classifiers":[
        {
            "category":"Retail",
            "subcategory":"Laundry & Dry Cleaning",
            "type":"Services"
        }
    ],
    "sg:phone":"+1 781 849 7947",
    "sg:postcode":"02184",
    "sg:province":"MA",
    "sg:tags":[
        "uniform",
        "supply"
    ],
    "wof:name":"Cintas The Uniform People",
    "wof:placetype":"venue"
},
  "geometry": {"coordinates":[-71.034779,42.22027],"type":"Point"}
}