{
  "type": "Feature",
  "properties": {
    "iso:country":"US",
    "sg:address":"259 Great Western Rd",
    "sg:city":"South Dennis",
    "sg:classifiers":[
        {
            "category":"Retail",
            "subcategory":"Repair Shop",
            "type":"Services"
        }
    ],
    "sg:phone":"+1 508 760 5028",
    "sg:postcode":"02660",
    "sg:province":"MA",
    "wof:name":"Jorgensen Marine",
    "wof:placetype":"venue"
},
  "geometry": {"coordinates":[-70.131929,41.689555],"type":"Point"}
}