{
  "type": "Feature",
  "properties": {
    "addr:full": "15 Carson Ave Wilmington MA 01887",
    "addr:housenumber": "15",
    "addr:postcode": "01887",
    "addr:street": "Carson Ave",
    "iso:country": "US",
    "sg:address": "15 Carson Ave",
    "sg:city": "Wilmington",
    "sg:classifiers": [
      {
        "category": "Building \u0026 Trades",
        "subcategory": "Electrical",
        "type": "Services"
      }
    ],
    "sg:phone": "+1 978 658 2955",
    "sg:postcode": "01887",
    "sg:province": "MA",
    "sg:tags": [
      "electric",
      "contractor"
    ],
    "wof:name": "Eric P Sands Lic Electrician",
    "wof:placetype": "venue"
  },
  "geometry": {"coordinates":[-71.144205,42.576177],"type":"Point"}
}
