{
  "type": "Feature",
  "properties": {
    "iso:country":"US",
    "sg:address":"18 Arlington St",
    "sg:city":"Lawrence",
    "sg:classifiers":[
        {
            "category":"Restaurant",
            "type":"Food & Drink"
        }
    ],
    "sg:phone":"+1   ",
    "sg:postcode":"01841",
    "sg:province":"MA",
    "sg:tags":[
        "eating"
    ],
    "wof:name":"Playground Ice Cream Inc",
    "wof:placetype":"venue"
},
  "geometry": {"coordinates":[-71.16948499999999,42.721545],"type":"Point"}
}