{
  "type": "Feature",
  "properties": {
    "addr:full":"69 Newburyport Tpke Newbury MA 01951",
    "addr:housenumber":"69",
    "addr:postcode":"01951",
    "addr:street":"Newburyport Tpke",
    "iso:country":"US",
    "sg:address":"69 Newburyport Tpke",
    "sg:city":"Newbury",
    "sg:classifiers":[
        {
            "category":"Organizations",
            "subcategory":"Community Association",
            "type":"Services"
        }
    ],
    "sg:phone":"+1 978 462 2551",
    "sg:postcode":"01951",
    "sg:province":"MA",
    "sg:tags":[
        "environmental",
        "org"
    ],
    "wof:name":"Parker River Clean Water Assoc",
    "wof:placetype":"venue"
},
  "geometry": {"coordinates":[-70.881078,42.783191],"type":"Point"}
}