{
  "type": "Feature",
  "properties": {
    "iso:country":"US",
    "sg:address":"1114 Grand Army Hwy",
    "sg:city":"Somerset",
    "sg:classifiers":[
        {
            "category":"Autos & Motor Vehicles",
            "subcategory":"Automobile Sales",
            "type":"Retail Goods"
        }
    ],
    "sg:phone":"+1 508 677 9557",
    "sg:postcode":"02726",
    "sg:province":"MA",
    "sg:tags":[
        "car",
        "dealer"
    ],
    "wof:name":"Ed Holewiak's Auto Sales",
    "wof:placetype":"venue"
},
  "geometry": {"coordinates":[-71.174037,41.733027],"type":"Point"}
}