{
  "type": "Feature",
  "properties": {
    "iso:country":"US",
    "sg:address":"33 Jeanne Ave",
    "sg:city":"Brockton",
    "sg:classifiers":[
        {
            "category":"Retail",
            "subcategory":"Laundry & Dry Cleaning",
            "type":"Services"
        }
    ],
    "sg:phone":"+1 508 587 1588",
    "sg:postcode":"02301",
    "sg:province":"MA",
    "sg:tags":[
        "cleaners",
        "rug",
        "carpet"
    ],
    "wof:name":"Dan De Cleaning Co",
    "wof:placetype":"venue"
},
  "geometry": {"coordinates":[-71.03702699999999,42.063459],"type":"Point"}
}