{
  "type": "Feature",
  "properties": {
    "iso:country":"US",
    "sg:address":"295 Hartford Pike",
    "sg:city":"Shrewsbury",
    "sg:classifiers":[
        {
            "category":"Autos & Motor Vehicles",
            "subcategory":"Motorcycle Sales",
            "type":"Retail Goods"
        }
    ],
    "sg:phone":"+1 508 755 6979",
    "sg:postcode":"01545",
    "sg:province":"MA",
    "sg:tags":[
        "scooter"
    ],
    "wof:name":"Hogs & Rods Inc",
    "wof:placetype":"venue"
},
  "geometry": {"coordinates":[-71.71580899999999,42.249521],"type":"Point"}
}