{
  "type": "Feature",
  "properties": {
    "iso:country":"US",
    "sg:address":"2 Center Plaza",
    "sg:city":"Boston",
    "sg:classifiers":[
        {
            "category":"Retail",
            "subcategory":"Portrait Studio",
            "type":"Services"
        }
    ],
    "sg:phone":"+1 617 523 1105",
    "sg:postcode":"02108",
    "sg:province":"MA",
    "sg:tags":[
        "photography",
        "store"
    ],
    "sg:website":"www.cvs.com",
    "wof:name":"CVS Pharmacy",
    "wof:placetype":"venue"
},
  "geometry": {"coordinates":[-71.061499,42.35968],"type":"Point"}
}