{
  "type": "Feature",
  "properties": {
    "iso:country":"US",
    "sg:address":"3873 State Hwy 6 Alt",
    "sg:city":"Brewster",
    "sg:classifiers":[
        {
            "category":"Museum",
            "type":"Entertainment"
        }
    ],
    "sg:phone":"+1   ",
    "sg:postcode":"02631",
    "sg:province":"MA",
    "sg:tags":[
        "gallery"
    ],
    "wof:name":"Struna Gallery",
    "wof:placetype":"venue"
},
  "geometry": {"coordinates":[-70.020135,41.776061],"type":"Point"}
}