{
  "type": "Feature",
  "properties": {
    "addr:full":"262 Swansea Mall Dr Swansea MA 02777",
    "addr:housenumber":"262",
    "addr:postcode":"02777",
    "addr:street":"Swansea Mall Dr",
    "iso:country":"US",
    "sg:address":"262 Swansea Mall Dr",
    "sg:city":"Swansea",
    "sg:classifiers":[
        {
            "category":"Food & Beverages",
            "subcategory":"Specialty",
            "type":"Retail Goods"
        }
    ],
    "sg:phone":"+1 508 677 4687",
    "sg:postcode":"02777",
    "sg:province":"MA",
    "sg:tags":[
        "vitamin"
    ],
    "wof:name":"Vitamin World",
    "wof:placetype":"venue"
},
  "geometry": {"coordinates":[-71.220046,41.760038],"type":"Point"}
}