{
  "type": "Feature",
  "properties": {
    "addr:full":"131 Coolidge St Hudson MA 01749",
    "addr:housenumber":"131",
    "addr:postcode":"01749",
    "addr:street":"Coolidge St",
    "iso:country":"US",
    "sg:address":"131 Coolidge St",
    "sg:city":"Hudson",
    "sg:classifiers":[
        {
            "category":"Professional",
            "subcategory":"Research",
            "type":"Services"
        }
    ],
    "sg:phone":"+1 978 568 0041",
    "sg:postcode":"01749",
    "sg:province":"MA",
    "sg:tags":[
        "environmental",
        "ecological"
    ],
    "wof:name":"R I Analytical Lab Inc",
    "wof:placetype":"venue"
},
  "geometry": {"coordinates":[-71.60097500000001,42.39765],"type":"Point"}
}