{
  "type": "Feature",
  "properties": {
    "iso:country":"US",
    "sg:address":"2016 Ocean St",
    "sg:city":"Marshfield",
    "sg:classifiers":[
        {
            "category":"Professional",
            "subcategory":"Management & Consulting",
            "type":"Services"
        }
    ],
    "sg:phone":"+1   ",
    "sg:postcode":"02050",
    "sg:province":"MA",
    "wof:name":"Corrigan Mark D Associates",
    "wof:placetype":"venue"
},
  "geometry": {"coordinates":[-70.71182399999999,42.092405],"type":"Point"}
}