{
  "type": "Feature",
  "properties": {
    "addr:full": "2016 Ocean St Marshfield MA 02050",
    "addr:housenumber": "2016",
    "addr:postcode": "02050",
    "addr:street": "Ocean St",
    "iso:country": "US",
    "sg:address": "2016 Ocean St",
    "sg:city": "Marshfield",
    "sg:classifiers": [
      {
        "category": "Professional",
        "subcategory": "Management \u0026 Consulting",
        "type": "Services"
      }
    ],
    "sg:phone": "+1   ",
    "sg:postcode": "02050",
    "sg:province": "MA",
    "wof:name": "Corrigan Mark D Associates",
    "wof:placetype": "venue"
  },
  "geometry": {"coordinates":[-70.711824,42.092405],"type":"Point"}
}
