{
  "type": "Feature",
  "properties": {
    "addr:full": "125 County St Taunton MA 02780",
    "addr:housenumber": "125",
    "addr:postcode": "02780",
    "addr:street": "County St",
    "iso:country": "US",
    "sg:address": "125 County St",
    "sg:city": "Taunton",
    "sg:classifiers": [
      {
        "category": "Education",
        "subcategory": "School",
        "type": "Public Place"
      }
    ],
    "sg:phone": "+1 508 822 6175",
    "sg:postcode": "02780",
    "sg:province": "MA",
    "wof:name": "Borges Driving School",
    "wof:placetype": "venue"
  },
  "geometry": {"coordinates":[-71.076327,41.895594],"type":"Point"}
}
