{
  "type": "Feature",
  "properties": {
    "addr:full":"55 Cambridge Parkway Cambridge MA 02142",
    "addr:housenumber":"55",
    "addr:postcode":"02142",
    "addr:street":"Cambridge Parkway",
    "iso:country":"US",
    "sg:address":"55 Cambridge Parkway",
    "sg:city":"Cambridge",
    "sg:classifiers":[
        {
            "category":"Food & Beverages",
            "subcategory":"Candy",
            "type":"Retail Goods"
        }
    ],
    "sg:phone":"+1 617 499 2700",
    "sg:postcode":"02142",
    "sg:province":"MA",
    "sg:tags":[
        "store"
    ],
    "wof:name":"Theatre Merchandising",
    "wof:placetype":"venue"
},
  "geometry": {"coordinates":[-71.07507200000001,42.36618],"type":"Point"}
}