{
  "type": "Feature",
  "properties": {
    "addr:full": "100 Ferncroft Rd Danvers MA 01923",
    "addr:housenumber": "100",
    "addr:postcode": "01923",
    "addr:street": "Ferncroft Rd",
    "iso:country": "US",
    "sg:address": "100 Ferncroft Rd",
    "sg:city": "Danvers",
    "sg:classifiers": [
      {
        "category": "Local Transit",
        "type": "Transportation"
      }
    ],
    "sg:phone": "+1 978 283 6775",
    "sg:postcode": "01923",
    "sg:province": "MA",
    "sg:tags": [
      "limousine"
    ],
    "wof:name": "Ludwig's Limousine Svc",
    "wof:placetype": "venue"
  },
  "geometry": {"coordinates":[-70.969338,42.595479],"type":"Point"}
}
