{
  "type": "Feature",
  "properties": {
    "addr:full": "18 Washington St Canton MA 02021",
    "addr:housenumber": "18",
    "addr:postcode": "02021",
    "addr:street": "Washington St",
    "iso:country": "US",
    "sg:address": "18 Washington St",
    "sg:city": "Canton",
    "sg:classifiers": [
      {
        "category": "Banks \u0026 Credit Unions",
        "subcategory": "Bank",
        "type": "Services"
      }
    ],
    "sg:phone": "+1   ",
    "sg:postcode": "02021",
    "sg:province": "MA",
    "sg:tags": [
      "loan",
      "broker"
    ],
    "wof:name": "Northeast Corner",
    "wof:placetype": "venue"
  },
  "geometry": {"coordinates":[-71.148893,42.139454],"type":"Point"}
}
