{
  "type": "Feature",
  "properties": {
    "addr:full": "658 Washington St Boston MA 02111",
    "addr:housenumber": "658",
    "addr:postcode": "02111",
    "addr:street": "Washington St",
    "iso:country": "US",
    "sg:address": "658 Washington St",
    "sg:city": "Boston",
    "sg:classifiers": [
      {
        "category": "Parking",
        "type": "Transportation"
      }
    ],
    "sg:phone": "+1 617 423 1518",
    "sg:postcode": "02111",
    "sg:province": "MA",
    "sg:tags": [
      "garage"
    ],
    "wof:name": "Fitz Inn Auto Parks Inc",
    "wof:placetype": "venue"
  },
  "geometry": {"coordinates":[-71.062761,42.351507],"type":"Point"}
}
