{
  "type": "Feature",
  "properties": {
    "addr:full":"58 Summer St Ashland MA 01721",
    "addr:housenumber":"58",
    "addr:postcode":"01721",
    "addr:street":"Summer St",
    "iso:country":"US",
    "sg:address":"58 Summer St",
    "sg:city":"Ashland",
    "sg:classifiers":[
        {
            "category":"Building & Trades",
            "subcategory":"Pest Control",
            "type":"Services"
        }
    ],
    "sg:phone":"+1 508 872 8089",
    "sg:postcode":"01721",
    "sg:province":"MA",
    "sg:tags":[
        "trapper",
        "animal"
    ],
    "wof:name":"Integrated Pest Management Svc",
    "wof:placetype":"venue"
},
  "geometry": {"coordinates":[-71.46505999999999,42.258227],"type":"Point"}
}