{
  "type": "Feature",
  "properties": {
    "iso:country":"US",
    "sg:address":"11 Congress St",
    "sg:city":"Beverly",
    "sg:classifiers":[
        {
            "category":"Health Services",
            "subcategory":"Hospital",
            "type":"Services"
        }
    ],
    "sg:phone":"+1 978 922 6575",
    "sg:postcode":"01915",
    "sg:province":"MA",
    "sg:tags":[
        "mental"
    ],
    "wof:name":"NESR-Congress Street",
    "wof:placetype":"venue"
},
  "geometry": {"coordinates":[-70.888059,42.541111],"type":"Point"}
}