{
  "type": "Feature",
  "properties": {
    "addr:full": "22 Byland Ave Auburn MA 01501",
    "addr:housenumber": "22",
    "addr:postcode": "01501",
    "addr:street": "Byland Ave",
    "iso:country": "US",
    "sg:address": "22 Byland Ave",
    "sg:city": "Auburn",
    "sg:classifiers": [
      {
        "category": "Building \u0026 Trades",
        "subcategory": "Construction",
        "type": "Services"
      }
    ],
    "sg:phone": "+1 508 832 6380",
    "sg:postcode": "01501",
    "sg:province": "MA",
    "sg:tags": [
      "siding",
      "contractor"
    ],
    "wof:name": "Worcester Counting Siding Co",
    "wof:placetype": "venue"
  },
  "geometry": {"coordinates":[-71.854819,42.208638],"type":"Point"}
}
