{
  "type": "Feature",
  "properties": {
    "iso:country":"US",
    "sg:address":"22 Byland Ave",
    "sg:city":"Auburn",
    "sg:classifiers":[
        {
            "category":"Building & Trades",
            "subcategory":"Construction",
            "type":"Services"
        }
    ],
    "sg:phone":"+1 508 832 6380",
    "sg:postcode":"01501",
    "sg:province":"MA",
    "sg:tags":[
        "siding",
        "contractor"
    ],
    "wof:name":"Worcester Counting Siding Co",
    "wof:placetype":"venue"
},
  "geometry": {"coordinates":[-71.85481900000001,42.208638],"type":"Point"}
}