{
  "type": "Feature",
  "properties": {
    "addr:full": "74 Rabbit Rd Salisbury MA 01952",
    "addr:housenumber": "74",
    "addr:postcode": "01952",
    "addr:street": "Rabbit Rd",
    "iso:country": "US",
    "sg:address": "74 Rabbit Rd",
    "sg:city": "Salisbury",
    "sg:classifiers": [
      {
        "category": "Building \u0026 Trades",
        "subcategory": "Construction",
        "type": "Services"
      }
    ],
    "sg:phone": "+1 978 462 1165",
    "sg:postcode": "01952",
    "sg:province": "MA",
    "sg:tags": [
      "resurfacing",
      "laying",
      "refinishing",
      "floor"
    ],
    "wof:name": "New England Floor Coverings",
    "wof:placetype": "venue"
  },
  "geometry": {"coordinates":[-70.894582,42.855694],"type":"Point"}
}
