{
  "type": "Feature",
  "properties": {
    "addr:full": "768 Iyannough Rd Hyannis MA 02601",
    "addr:housenumber": "768",
    "addr:postcode": "02601",
    "addr:street": "Iyannough Rd",
    "iso:country": "US",
    "sg:address": "768 Iyannough Rd",
    "sg:city": "Hyannis",
    "sg:classifiers": [
      {
        "category": "Shopping",
        "subcategory": "Clothing, Apparel, \u0026 Fashions",
        "type": "Retail Goods"
      }
    ],
    "sg:phone": "+1 508 771 3608",
    "sg:postcode": "02601",
    "sg:province": "MA",
    "sg:tags": [
      "lingerie"
    ],
    "wof:name": "Lady Grace Stores Inc",
    "wof:placetype": "venue"
  },
  "geometry": {"coordinates":[-70.294221,41.668224],"type":"Point"}
}
