{
  "type": "Feature",
  "properties": {
    "addr:full": "31 Main St Belchertown MA 01007",
    "addr:housenumber": "31",
    "addr:postcode": "01007",
    "addr:street": "Main St",
    "iso:country": "US",
    "sg:address": "31 Main St",
    "sg:city": "Belchertown",
    "sg:classifiers": [
      {
        "category": "Social Services",
        "subcategory": "Child Care",
        "type": "Services"
      }
    ],
    "sg:phone": "+1 413 323 4795",
    "sg:postcode": "01007",
    "sg:province": "MA",
    "sg:tags": [
      "kindergarten",
      "academic",
      "school"
    ],
    "wof:name": "Belchertown Community Preschl",
    "wof:placetype": "venue"
  },
  "geometry": {"coordinates":[-72.40155,42.277751],"type":"Point"}
}
