{
  "type": "Feature",
  "properties": {
    "addr:full": "1456 N Shore Rd Revere MA 02151",
    "addr:housenumber": "1456",
    "addr:postcode": "02151",
    "addr:street": "N Shore Rd",
    "iso:country": "US",
    "sg:address": "1456 N Shore Rd",
    "sg:city": "Revere",
    "sg:classifiers": [
      {
        "category": "Retail",
        "subcategory": "Auto Repair",
        "type": "Services"
      }
    ],
    "sg:phone": "+1 781 284 9359",
    "sg:postcode": "02151",
    "sg:province": "MA",
    "sg:tags": [
      "repairing",
      "automobile"
    ],
    "wof:name": "Northgate Automotive Specs",
    "wof:placetype": "venue"
  },
  "geometry": {"coordinates":[-70.993089,42.411573],"type":"Point"}
}
