{
  "type": "Feature",
  "properties": {
    "iso:country":"US",
    "sg:address":"124 Calvary St",
    "sg:city":"Waltham",
    "sg:classifiers":[
        {
            "category":"Professional",
            "type":"Services"
        }
    ],
    "sg:phone":"+1 781 894 4100",
    "sg:postcode":"02453",
    "sg:province":"MA",
    "sg:tags":[
        "establishment"
    ],
    "wof:name":"Brokk Pros",
    "wof:placetype":"venue"
},
  "geometry": {"coordinates":[-71.224245,42.368082],"type":"Point"}
}