{
  "type": "Feature",
  "properties": {
    "addr:full":"1050 Kings Hwy New Bedford MA 02745",
    "addr:housenumber":"1050",
    "addr:postcode":"02745",
    "addr:street":"Kings Hwy",
    "iso:country":"US",
    "sg:address":"1050 Kings Hwy",
    "sg:city":"New Bedford",
    "sg:classifiers":[
        {
            "category":"Shopping",
            "subcategory":"Clothing, Apparel, & Fashions",
            "type":"Retail Goods"
        }
    ],
    "sg:phone":"+1 508 985 9010",
    "sg:postcode":"02745",
    "sg:province":"MA",
    "wof:name":"J Silver Clothing Inc",
    "wof:placetype":"venue"
},
  "geometry": {"coordinates":[-70.941137,41.678787],"type":"Point"}
}