{
  "type": "Feature",
  "properties": {
    "addr:full":"134 Kathleen Dr Plymouth MA 02360",
    "addr:housenumber":"134",
    "addr:postcode":"02360",
    "addr:street":"Kathleen Dr",
    "iso:country":"US",
    "sg:address":"134 Kathleen Dr",
    "sg:city":"Plymouth",
    "sg:classifiers":[
        {
            "category":"Professional",
            "subcategory":"Lawyer & Legal Services",
            "type":"Services"
        }
    ],
    "sg:phone":"+1   ",
    "sg:postcode":"02360",
    "sg:province":"MA",
    "wof:name":"Wanda J Warmack Pc",
    "wof:placetype":"venue"
},
  "geometry": {"coordinates":[-70.55578800000001,41.891261],"type":"Point"}
}