{
  "type": "Feature",
  "properties": {
    "addr:full":"43 Forest St Milford MA 01757",
    "addr:housenumber":"43",
    "addr:postcode":"01757",
    "addr:street":"Forest St",
    "iso:country":"US",
    "sg:address":"43 Forest St",
    "sg:city":"Milford",
    "sg:classifiers":[
        {
            "category":"Building & Trades",
            "subcategory":"Plumbing",
            "type":"Services"
        }
    ],
    "sg:phone":"+1 508 478 0777",
    "sg:postcode":"01757",
    "sg:province":"MA",
    "sg:tags":[
        "plumber",
        "industrial",
        "contractors-commercial"
    ],
    "wof:name":"J.A.Pighetti Plumbing And Heating",
    "wof:placetype":"venue"
},
  "geometry": {"coordinates":[-71.516862,42.134473],"type":"Point"}
}