{
  "type": "Feature",
  "properties": {
    "iso:country":"US",
    "sg:address":"275 North St",
    "sg:city":"Cheshire",
    "sg:classifiers":[
        {
            "category":"Freight",
            "type":"Transportation"
        }
    ],
    "sg:phone":"+1 413 743 5397",
    "sg:postcode":"01225",
    "sg:province":"MA",
    "sg:tags":[
        "trucking"
    ],
    "wof:name":"Delmolino & Sons Inc",
    "wof:placetype":"venue"
},
  "geometry": {"coordinates":[-73.165583,42.562271],"type":"Point"}
}