{
  "type": "Feature",
  "properties": {
    "iso:country":"US",
    "sg:address":"67 Salem St",
    "sg:city":"Boston",
    "sg:classifiers":[
        {
            "category":"Arts & Performance",
            "subcategory":"Art Gallery",
            "type":"Entertainment"
        }
    ],
    "sg:phone":"+1 617 742 0484",
    "sg:postcode":"02113",
    "sg:province":"MA",
    "sg:website":"www.shakethetreeboston.com",
    "wof:name":"Shake the Tree Gallery",
    "wof:placetype":"venue"
},
  "geometry": {"coordinates":[-71.05589999999999,42.3633],"type":"Point"}
}