{
  "type": "Feature",
  "properties": {
    "addr:full": "6 Lantern Ln Lexington MA 02421",
    "addr:housenumber": "6",
    "addr:postcode": "02421",
    "addr:street": "Lantern Ln",
    "iso:country": "US",
    "sg:address": "6 Lantern Ln",
    "sg:city": "Lexington",
    "sg:classifiers": [
      {
        "category": "Organizations",
        "subcategory": "Religious Organization",
        "type": "Services"
      }
    ],
    "sg:phone": "+1   ",
    "sg:postcode": "02421",
    "sg:province": "MA",
    "wof:name": "North ATL States Reg",
    "wof:placetype": "venue"
  },
  "geometry": {"coordinates":[-71.2153,42.426155],"type":"Point"}
}
