{
  "type": "Feature",
  "properties": {
    "addr:full": "321 Main St Great Barrington MA 01230",
    "addr:housenumber": "321",
    "addr:postcode": "01230",
    "addr:street": "Main St",
    "iso:country": "US",
    "sg:address": "321 Main St",
    "sg:city": "Great Barrington",
    "sg:classifiers": [
      {
        "category": "Manufacturing",
        "subcategory": "Printing",
        "type": "Manufacturing \u0026 Wholesale Goods"
      }
    ],
    "sg:phone": "+1 413 528 0034",
    "sg:postcode": "01230",
    "sg:province": "MA",
    "sg:tags": [
      "publisher"
    ],
    "sg:website": "www.northriverpress.com",
    "wof:name": "North River Press",
    "wof:placetype": "venue"
  },
  "geometry": {"coordinates":[-73.362879,42.193774],"type":"Point"}
}
