{
  "type": "Feature",
  "properties": {
    "iso:country":"US",
    "sg:address":"321 Main St",
    "sg:city":"Great Barrington",
    "sg:classifiers":[
        {
            "category":"Manufacturing",
            "subcategory":"Printing",
            "type":"Manufacturing & Wholesale Goods"
        }
    ],
    "sg:phone":"+1 413 528 0034",
    "sg:postcode":"01230",
    "sg:province":"MA",
    "sg:tags":[
        "publisher"
    ],
    "sg:website":"www.northriverpress.com",
    "wof:name":"North River Press",
    "wof:placetype":"venue"
},
  "geometry": {"coordinates":[-73.36287900000001,42.193774],"type":"Point"}
}