{
  "type": "Feature",
  "properties": {
    "addr:full":"805 Chief Justice Cushing Hwy Cohasset MA 02025",
    "addr:housenumber":"805",
    "addr:postcode":"02025",
    "addr:street":"Chief Justice Cushing Hwy",
    "iso:country":"US",
    "sg:address":"805 Chief Justice Cushing Hwy",
    "sg:city":"Cohasset",
    "sg:classifiers":[
        {
            "category":"Shopping",
            "subcategory":"Florist",
            "type":"Retail Goods"
        }
    ],
    "sg:phone":"+1 781 383 2333",
    "sg:postcode":"02025",
    "sg:province":"MA",
    "wof:name":"Cohasset Village Greenery",
    "wof:placetype":"venue"
},
  "geometry": {"coordinates":[-70.80281600000001,42.221584],"type":"Point"}
}