{
  "type": "Feature",
  "properties": {
    "addr:full":"8 North St Bridgewater MA 02324",
    "addr:housenumber":"8",
    "addr:postcode":"02324",
    "addr:street":"North St",
    "iso:country":"US",
    "sg:address":"8 North St",
    "sg:city":"Bridgewater",
    "sg:classifiers":[
        {
            "category":"Farming",
            "subcategory":"Farm",
            "type":"Manufacturing & Wholesale Goods"
        }
    ],
    "sg:phone":"+1 508 697 6500",
    "sg:postcode":"02324",
    "sg:province":"MA",
    "wof:name":"Den Beston Farm Inc",
    "wof:placetype":"venue"
},
  "geometry": {"coordinates":[-70.996285,41.978087],"type":"Point"}
}