{
  "type": "Feature",
  "properties": {
    "addr:full": "461 Longley Rd Groton MA 01450",
    "addr:housenumber": "461",
    "addr:postcode": "01450",
    "addr:street": "Longley Rd",
    "iso:country": "US",
    "sg:address": "461 Longley Rd",
    "sg:city": "Groton",
    "sg:classifiers": [
      {
        "category": "Restaurant",
        "type": "Food \u0026 Drink"
      }
    ],
    "sg:phone": "+1   ",
    "sg:postcode": "01450",
    "sg:province": "MA",
    "sg:tags": [
      "eating"
    ],
    "wof:name": "Johnsons Restaurant \u0026 Dar Bar",
    "wof:placetype": "venue"
  },
  "geometry": {"coordinates":[-71.568824,42.643767],"type":"Point"}
}
