{
  "type": "Feature",
  "properties": {
    "iso:country":"US",
    "sg:address":"62 Jefferson Ave",
    "sg:city":"Salem",
    "sg:classifiers":[
        {
            "category":"Autos & Motor Vehicles",
            "subcategory":"Automobile Sales",
            "type":"Retail Goods"
        }
    ],
    "sg:phone":"+1 978 825 0200",
    "sg:postcode":"01970",
    "sg:province":"MA",
    "sg:tags":[
        "car",
        "dealer"
    ],
    "wof:name":"Bob's Auto Sales",
    "wof:placetype":"venue"
},
  "geometry": {"coordinates":[-70.90114800000001,42.510729],"type":"Point"}
}