{
  "type": "Feature",
  "properties": {
    "iso:country":"US",
    "sg:address":"241 Groton Rd",
    "sg:city":"Westford",
    "sg:classifiers":[
        {
            "category":"Retail",
            "subcategory":"Laundry & Dry Cleaning",
            "type":"Services"
        }
    ],
    "sg:phone":"+1 978 692 0020",
    "sg:postcode":"01886",
    "sg:province":"MA",
    "sg:tags":[
        "operated",
        "equipment",
        "washer",
        "dryer",
        "coin"
    ],
    "wof:name":"Chelmsford Pressure Washing",
    "wof:placetype":"venue"
},
  "geometry": {"coordinates":[-71.455439,42.612728],"type":"Point"}
}