{
  "type": "Feature",
  "properties": {
    "addr:full": "311 Westford St Lowell MA 01851",
    "addr:housenumber": "311",
    "addr:postcode": "01851",
    "addr:street": "Westford St",
    "iso:country": "US",
    "sg:address": "311 Westford St",
    "sg:city": "Lowell",
    "sg:classifiers": [
      {
        "category": "Shopping",
        "subcategory": "Jewelry",
        "type": "Retail Goods"
      }
    ],
    "sg:phone": "+1 978 454 5278",
    "sg:postcode": "01851",
    "sg:province": "MA",
    "sg:tags": [
      "jeweler"
    ],
    "wof:name": "Bayou Jewelry",
    "wof:placetype": "venue"
  },
  "geometry": {"coordinates":[-71.327838,42.63499],"type":"Point"}
}
