{
  "type": "Feature",
  "properties": {
    "addr:full": "9 Charlton St Everett MA 02149",
    "addr:housenumber": "9",
    "addr:postcode": "02149",
    "addr:street": "Charlton St",
    "iso:country": "US",
    "sg:address": "9 Charlton St",
    "sg:city": "Everett",
    "sg:classifiers": [
      {
        "category": "Professional",
        "type": "Services"
      }
    ],
    "sg:phone": "+1 617 387 0690",
    "sg:postcode": "02149",
    "sg:province": "MA",
    "sg:tags": [
      "establishment"
    ],
    "wof:name": "Neb Burrcom Indl",
    "wof:placetype": "venue"
  },
  "geometry": {"coordinates":[-71.062649,42.400781],"type":"Point"}
}
