{
  "type": "Feature",
  "properties": {
    "iso:country":"US",
    "sg:address":"90 Birch St",
    "sg:city":"Roslindale",
    "sg:classifiers":[
        {
            "category":"Real Estate",
            "subcategory":"Real Estate Agent",
            "type":"Services"
        }
    ],
    "sg:phone":"+1 617 469 8161",
    "sg:postcode":"02131",
    "sg:province":"MA",
    "wof:name":"ABC Realty & Construction",
    "wof:placetype":"venue"
},
  "geometry": {"coordinates":[-71.132442,42.284783],"type":"Point"}
}