{
  "type": "Feature",
  "properties": {
    "addr:full": "17 Sterling Rd North Billerica MA 01862",
    "addr:housenumber": "17",
    "addr:postcode": "01862",
    "addr:street": "Sterling Rd",
    "iso:country": "US",
    "sg:address": "17 Sterling Rd",
    "sg:city": "North Billerica",
    "sg:classifiers": [
      {
        "category": "Manufacturing",
        "subcategory": "Tools \u0026 Machinery",
        "type": "Manufacturing \u0026 Wholesale Goods"
      }
    ],
    "sg:phone": "+1 978 439 9090",
    "sg:postcode": "01862",
    "sg:province": "MA",
    "sg:tags": [
      "filter"
    ],
    "wof:name": "Memtec New England",
    "wof:placetype": "venue"
  },
  "geometry": {"coordinates":[-71.308969,42.570036],"type":"Point"}
}
