{
  "type": "Feature",
  "properties": {
    "addr:full":"4 Fullers Ln Milton MA 02186",
    "addr:housenumber":"4",
    "addr:postcode":"02186",
    "addr:street":"Fullers Ln",
    "iso:country":"US",
    "sg:address":"4 Fullers Ln",
    "sg:city":"Milton",
    "sg:classifiers":[
        {
            "category":"Social Services",
            "type":"Services"
        }
    ],
    "sg:phone":"+1 617 698 3655",
    "sg:postcode":"02186",
    "sg:province":"MA",
    "sg:tags":[
        "youth",
        "organization",
        "center"
    ],
    "wof:name":"Girl Scouts House",
    "wof:placetype":"venue"
},
  "geometry": {"coordinates":[-71.052958,42.251676],"type":"Point"}
}