{
  "type": "Feature",
  "properties": {
    "addr:full": "6 Knox St Lawrence MA 01841",
    "addr:housenumber": "6",
    "addr:postcode": "01841",
    "addr:street": "Knox St",
    "iso:country": "US",
    "sg:address": "6 Knox St",
    "sg:city": "Lawrence",
    "sg:classifiers": [
      {
        "category": "Professional",
        "subcategory": "Business Services",
        "type": "Services"
      }
    ],
    "sg:phone": "+1 978 688 1321",
    "sg:postcode": "01841",
    "sg:province": "MA",
    "sg:tags": [
      "packaging"
    ],
    "wof:name": "Aldo \u0026 Yoki Construction",
    "wof:placetype": "venue"
  },
  "geometry": {"coordinates":[-71.157052,42.72145],"type":"Point"}
}
