{
  "type": "Feature",
  "properties": {
    "addr:full":"5 Toombs Ct Nantucket MA 02554",
    "addr:housenumber":"5",
    "addr:postcode":"02554",
    "addr:street":"Toombs Ct",
    "iso:country":"US",
    "sg:address":"5 Toombs Ct",
    "sg:city":"Nantucket",
    "sg:classifiers":[
        {
            "category":"Personal",
            "subcategory":"Beauty Salon",
            "type":"Services"
        },
        {
            "category":"Personal",
            "subcategory":"Tanning Parlor",
            "type":"Services"
        }
    ],
    "sg:phone":"+1 508 228 1099",
    "sg:postcode":"02554",
    "sg:province":"MA",
    "wof:name":"Kathleens Beauty Studio",
    "wof:placetype":"venue"
},
  "geometry": {"coordinates":[-70.082187,41.265384],"type":"Point"}
}