{
  "type": "Feature",
  "properties": {
    "iso:country":"US",
    "sg:address":"18 North St",
    "sg:city":"Hingham",
    "sg:classifiers":[
        {
            "category":"Organizations",
            "subcategory":"Membership Organization",
            "type":"Services"
        }
    ],
    "sg:phone":"+1 781 749 1946",
    "sg:postcode":"02043",
    "sg:province":"MA",
    "sg:tags":[
        "science",
        "reading",
        "christian",
        "rooms"
    ],
    "wof:name":"Christian Science Reading Room",
    "wof:placetype":"venue"
},
  "geometry": {"coordinates":[-70.884995,42.244421],"type":"Point"}
}