{
  "type": "Feature",
  "properties": {
    "addr:full":"121 Peck Brothers Rd Monson MA 01057",
    "addr:housenumber":"121",
    "addr:postcode":"01057",
    "addr:street":"Peck Brothers Rd",
    "iso:country":"US",
    "sg:address":"121 Peck Brothers Rd",
    "sg:city":"Monson",
    "sg:classifiers":[
        {
            "category":"Professional",
            "subcategory":"Employment Agencies",
            "type":"Services"
        }
    ],
    "sg:phone":"+1 413 267 4271",
    "sg:postcode":"01057",
    "sg:province":"MA",
    "sg:tags":[
        "opportunity"
    ],
    "wof:name":"Paul Shrenker Associates Inc",
    "wof:placetype":"venue"
},
  "geometry": {"coordinates":[-72.311987,42.049329],"type":"Point"}
}