{
  "type": "Feature",
  "properties": {
    "iso:country":"US",
    "sg:address":"613 Mount Auburn St",
    "sg:city":"Watertown",
    "sg:classifiers":[
        {
            "category":"Fast Food",
            "type":"Food & Drink"
        }
    ],
    "sg:phone":"+1 617 393 0333",
    "sg:postcode":"02472",
    "sg:province":"MA",
    "sg:tags":[
        "burger",
        "chicken",
        "wing"
    ],
    "sg:website":"www.eastsidewings.com/",
    "wof:name":"East Side Wings and Grill",
    "wof:placetype":"venue"
},
  "geometry": {"coordinates":[-71.158863,42.370613],"type":"Point"}
}