{
  "type": "Feature",
  "properties": {
    "iso:country":"US",
    "sg:address":"27 Langford Rd",
    "sg:city":"Plymouth",
    "sg:classifiers":[
        {
            "category":"Building & Trades",
            "subcategory":"Cleaning & Sanitation",
            "type":"Services"
        }
    ],
    "sg:phone":"+1   ",
    "sg:postcode":"02360",
    "sg:province":"MA",
    "sg:tags":[
        "maintenance"
    ],
    "wof:name":"Colligan Cleaning Co",
    "wof:placetype":"venue"
},
  "geometry": {"coordinates":[-70.620453,41.935542],"type":"Point"}
}