{
  "type": "Feature",
  "properties": {
    "addr:full": "27 Langford Rd Plymouth MA 02360",
    "addr:housenumber": "27",
    "addr:postcode": "02360",
    "addr:street": "Langford Rd",
    "iso:country": "US",
    "sg:address": "27 Langford Rd",
    "sg:city": "Plymouth",
    "sg:classifiers": [
      {
        "category": "Building \u0026 Trades",
        "subcategory": "Cleaning \u0026 Sanitation",
        "type": "Services"
      }
    ],
    "sg:phone": "+1   ",
    "sg:postcode": "02360",
    "sg:province": "MA",
    "sg:tags": [
      "maintenance"
    ],
    "wof:name": "Colligan Cleaning Co",
    "wof:placetype": "venue"
  },
  "geometry": {"coordinates":[-70.620453,41.935542],"type":"Point"}
}
