{
  "type": "Feature",
  "properties": {
    "iso:country":"US",
    "sg:address":"108 Trowbridge St",
    "sg:city":"Cambridge",
    "sg:classifiers":[
        {
            "category":"Professional",
            "subcategory":"Management & Consulting",
            "type":"Services"
        }
    ],
    "sg:phone":"+1   ",
    "sg:postcode":"02138",
    "sg:province":"MA",
    "sg:tags":[
        "business"
    ],
    "wof:name":"KB Consulting",
    "wof:placetype":"venue"
},
  "geometry": {"coordinates":[-71.10937,42.377569],"type":"Point"}
}