{
  "type": "Feature",
  "properties": {
    "iso:country":"US",
    "sg:address":"30 Beach St",
    "sg:city":"Wareham",
    "sg:classifiers":[
        {
            "category":"Professional",
            "subcategory":"Computer Services",
            "type":"Services"
        }
    ],
    "sg:phone":"+1 508 291 1774",
    "sg:postcode":"02571",
    "sg:province":"MA",
    "sg:tags":[
        "internet"
    ],
    "sg:website":"www.four.net",
    "wof:name":"Fournet",
    "wof:placetype":"venue"
},
  "geometry": {"coordinates":[-70.71627599999999,41.740376],"type":"Point"}
}