{
  "type": "Feature",
  "properties": {
    "addr:full": "314 Howard St Brockton MA 02302",
    "addr:housenumber": "314",
    "addr:postcode": "02302",
    "addr:street": "Howard St",
    "iso:country": "US",
    "sg:address": "314 Howard St",
    "sg:city": "Brockton",
    "sg:classifiers": [
      {
        "category": "Building \u0026 Trades",
        "subcategory": "Plumbing",
        "type": "Services"
      }
    ],
    "sg:phone": "+1 508 559 6744",
    "sg:postcode": "02302",
    "sg:province": "MA",
    "sg:tags": [
      "conditioning",
      "air",
      "system",
      "contractor"
    ],
    "wof:name": "Mc Claren Heating \u0026 Air Cond",
    "wof:placetype": "venue"
  },
  "geometry": {"coordinates":[-71.020918,42.115814],"type":"Point"}
}
