{
  "type": "Feature",
  "properties": {
    "iso:country":"US",
    "sg:address":"314 Howard St",
    "sg:city":"Brockton",
    "sg:classifiers":[
        {
            "category":"Building & Trades",
            "subcategory":"Plumbing",
            "type":"Services"
        }
    ],
    "sg:phone":"+1 508 559 6744",
    "sg:postcode":"02302",
    "sg:province":"MA",
    "sg:tags":[
        "conditioning",
        "air",
        "system",
        "contractor"
    ],
    "wof:name":"Mc Claren Heating & Air Cond",
    "wof:placetype":"venue"
},
  "geometry": {"coordinates":[-71.02091799999999,42.115814],"type":"Point"}
}