{
  "type": "Feature",
  "properties": {
    "addr:full":"15 Shaw St Fall River MA 02724",
    "addr:housenumber":"15",
    "addr:postcode":"02724",
    "addr:street":"Shaw St",
    "iso:country":"US",
    "sg:address":"15 Shaw St",
    "sg:city":"Fall River",
    "sg:classifiers":[
        {
            "category":"Shopping",
            "subcategory":"Clothing, Apparel, & Fashions",
            "type":"Retail Goods"
        }
    ],
    "sg:phone":"+1 508 672 9328",
    "sg:postcode":"02724",
    "sg:province":"MA",
    "sg:tags":[
        "designer"
    ],
    "wof:name":"American Power Source",
    "wof:placetype":"venue"
},
  "geometry": {"coordinates":[-71.178489,41.693903],"type":"Point"}
}