{
  "type": "Feature",
  "properties": {
    "addr:full": "310 Webster Ave Cambridge MA 02141",
    "addr:housenumber": "310",
    "addr:postcode": "02141",
    "addr:street": "Webster Ave",
    "iso:country": "US",
    "sg:address": "310 Webster Ave",
    "sg:city": "Cambridge",
    "sg:classifiers": [
      {
        "category": "Social Services",
        "type": "Services"
      }
    ],
    "sg:phone": "+1   ",
    "sg:postcode": "02141",
    "sg:province": "MA",
    "sg:tags": [
      "cultural",
      "center",
      "community"
    ],
    "wof:name": "Bccne",
    "wof:placetype": "venue"
  },
  "geometry": {"coordinates":[-71.09467,42.373657],"type":"Point"}
}
