{
  "type": "Feature",
  "properties": {
    "iso:country":"US",
    "sg:address":"310 Webster Ave",
    "sg:city":"Cambridge",
    "sg:classifiers":[
        {
            "category":"Social Services",
            "type":"Services"
        }
    ],
    "sg:phone":"+1   ",
    "sg:postcode":"02141",
    "sg:province":"MA",
    "sg:tags":[
        "cultural",
        "center",
        "community"
    ],
    "wof:name":"Bccne",
    "wof:placetype":"venue"
},
  "geometry": {"coordinates":[-71.09466999999999,42.373657],"type":"Point"}
}