{
  "type": "Feature",
  "properties": {
    "addr:full":"600 Atlantic Ave Boston MA 02210",
    "addr:housenumber":"600",
    "addr:postcode":"02210",
    "addr:street":"Atlantic Ave",
    "iso:country":"US",
    "sg:address":"600 Atlantic Ave",
    "sg:city":"Boston",
    "sg:classifiers":[
        {
            "category":"Real Estate",
            "subcategory":"Real Estate Agent",
            "type":"Services"
        }
    ],
    "sg:phone":"+1 617 912 7000",
    "sg:postcode":"02210",
    "sg:province":"MA",
    "wof:name":"C B Richard Ellis",
    "wof:placetype":"venue"
},
  "geometry": {"coordinates":[-71.05498,42.352869],"type":"Point"}
}