{
  "type": "Feature",
  "properties": {
    "addr:full":"15 Claremont St Worcester MA 01610",
    "addr:housenumber":"15",
    "addr:postcode":"01610",
    "addr:street":"Claremont St",
    "iso:country":"US",
    "sg:address":"15 Claremont St",
    "sg:city":"Worcester",
    "sg:classifiers":[
        {
            "category":"Recreation",
            "type":"Entertainment"
        }
    ],
    "sg:phone":"+1 508 755 8570",
    "sg:postcode":"01610",
    "sg:province":"MA",
    "sg:tags":[
        "amusement"
    ],
    "wof:name":"YMCA",
    "wof:placetype":"venue"
},
  "geometry": {"coordinates":[-71.818555,42.254714],"type":"Point"}
}