{
  "type": "Feature",
  "properties": {
    "iso:country":"US",
    "sg:address":"358 Ferry Street",
    "sg:city":"Everett",
    "sg:classifiers":[
        {
            "category":"Personal",
            "subcategory":"Tattoo Parlor",
            "type":"Services"
        }
    ],
    "sg:phone":"+1 617 394 0023",
    "sg:postcode":"02149",
    "sg:province":"MA",
    "sg:website":"mazelcustom.com/1.html",
    "wof:name":"Ma-Zel Tattoo",
    "wof:placetype":"venue"
},
  "geometry": {"coordinates":[-71.048592,42.415443],"type":"Point"}
}