{
  "type": "Feature",
  "properties": {
    "addr:full": "436 Still River Rd Bolton MA 01740",
    "addr:housenumber": "436",
    "addr:postcode": "01740",
    "addr:street": "Still River Rd",
    "iso:country": "US",
    "sg:address": "436 Still River Rd",
    "sg:city": "Bolton",
    "sg:classifiers": [
      {
        "category": "Professional",
        "subcategory": "Lawyer \u0026 Legal Services",
        "type": "Services"
      }
    ],
    "sg:phone": "+1 978 779 5255",
    "sg:postcode": "01740",
    "sg:province": "MA",
    "sg:tags": [
      "attorney"
    ],
    "wof:name": "Eric S Johnson",
    "wof:placetype": "venue"
  },
  "geometry": {"coordinates":[-71.626499,42.471368],"type":"Point"}
}
