{
  "type": "Feature",
  "properties": {
    "addr:full":"7 Main St Cummington MA 01026",
    "addr:housenumber":"7",
    "addr:postcode":"01026",
    "addr:street":"Main St",
    "iso:country":"US",
    "sg:address":"7 Main St",
    "sg:city":"Cummington",
    "sg:classifiers":[
        {
            "category":"Retail",
            "subcategory":"Auto Repair",
            "type":"Services"
        }
    ],
    "sg:phone":"+1 413 634 8889",
    "sg:postcode":"01026",
    "sg:province":"MA",
    "sg:tags":[
        "repairing",
        "automobile"
    ],
    "wof:name":"Cummington Garage",
    "wof:placetype":"venue"
},
  "geometry": {"coordinates":[-72.896764,42.462703],"type":"Point"}
}