{
  "type": "Feature",
  "properties": {
    "iso:country":"US",
    "sg:address":"8 S Main St",
    "sg:city":"Millbury",
    "sg:classifiers":[
        {
            "category":"Retail",
            "subcategory":"Auto Repair",
            "type":"Services"
        }
    ],
    "sg:phone":"+1 508 865 6004",
    "sg:postcode":"01527",
    "sg:province":"MA",
    "sg:tags":[
        "repairing",
        "automobile",
        "service-equipment",
        "supply"
    ],
    "wof:name":"Millbury Automobile Service",
    "wof:placetype":"venue"
},
  "geometry": {"coordinates":[-71.76030799999999,42.190198],"type":"Point"}
}