{
  "type": "Feature",
  "properties": {
    "iso:country":"US",
    "sg:address":"18 Rogers St",
    "sg:city":"Boston",
    "sg:classifiers":[
        {
            "category":"Building & Trades",
            "subcategory":"Construction",
            "type":"Services"
        }
    ],
    "sg:phone":"+1   ",
    "sg:postcode":"02127",
    "sg:province":"MA",
    "sg:tags":[
        "contractor"
    ],
    "wof:name":"Maksymilian Fence Company",
    "wof:placetype":"venue"
},
  "geometry": {"coordinates":[-71.05539,42.32972],"type":"Point"}
}