{
  "type": "Feature",
  "properties": {
    "addr:full": "628 Pleasant St New Bedford MA 02740",
    "addr:housenumber": "628",
    "addr:postcode": "02740",
    "addr:street": "Pleasant St",
    "iso:country": "US",
    "sg:address": "628 Pleasant St",
    "sg:city": "New Bedford",
    "sg:classifiers": [
      {
        "category": "Professional",
        "subcategory": "Lawyer \u0026 Legal Services",
        "type": "Services"
      }
    ],
    "sg:phone": "+1 508 994 7245",
    "sg:postcode": "02740",
    "sg:province": "MA",
    "sg:tags": [
      "attorney"
    ],
    "wof:name": "Guy Larock",
    "wof:placetype": "venue"
  },
  "geometry": {"coordinates":[-70.926965,41.635535],"type":"Point"}
}
