{
  "type": "Feature",
  "properties": {
    "addr:full": "12 Union St South Weymouth MA 02190",
    "addr:housenumber": "12",
    "addr:postcode": "02190",
    "addr:street": "Union St",
    "iso:country": "US",
    "sg:address": "12 Union St",
    "sg:city": "South Weymouth",
    "sg:classifiers": [
      {
        "category": "Recreation",
        "type": "Entertainment"
      }
    ],
    "sg:phone": "+1 781 337 9495",
    "sg:postcode": "02190",
    "sg:province": "MA",
    "sg:tags": [
      "instruction",
      "yoga"
    ],
    "wof:name": "Practice Studio Yoga",
    "wof:placetype": "venue"
  },
  "geometry": {"coordinates":[-70.950446,42.174153],"type":"Point"}
}
