{
  "type": "Feature",
  "properties": {
    "addr:full":"145 Sharon St Mobile Station Stoughton MA 02072",
    "addr:housenumber":"145",
    "addr:postcode":"02072",
    "addr:street":"Sharon St;Station",
    "iso:country":"US",
    "sg:address":"145 Sharon St Mobile Station",
    "sg:city":"Stoughton",
    "sg:classifiers":[
        {
            "category":"Donuts",
            "subcategory":"None",
            "type":"Food & Drink"
        }
    ],
    "sg:phone":"+1 781 297 7079",
    "sg:postcode":"02072",
    "sg:province":"MA",
    "sg:website":"www.dunkindonuts.com/",
    "wof:name":"Dunkin Donuts",
    "wof:placetype":"venue"
},
  "geometry": {"coordinates":[-71.14880700000001,42.138349],"type":"Point"}
}