{
  "type": "Feature",
  "properties": {
    "addr:full": "3 Paula Ln West Yarmouth MA 02673",
    "addr:housenumber": "3",
    "addr:postcode": "02673",
    "addr:street": "Paula Ln",
    "iso:country": "US",
    "sg:address": "3 Paula Ln",
    "sg:city": "West Yarmouth",
    "sg:classifiers": [
      {
        "category": "Arts \u0026 Performance",
        "subcategory": "Theater",
        "type": "Entertainment"
      }
    ],
    "sg:phone": "+1 508 790 3866",
    "sg:postcode": "02673",
    "sg:province": "MA",
    "sg:tags": [
      "live",
      "music"
    ],
    "wof:name": "Records On The Road",
    "wof:placetype": "venue"
  },
  "geometry": {"coordinates":[-70.233418,41.646218],"type":"Point"}
}
