{
  "type": "Feature",
  "properties": {
    "addr:full":"225 E Main St Milford MA 01757",
    "addr:housenumber":"225",
    "addr:postcode":"01757",
    "addr:street":"E Main St",
    "iso:country":"US",
    "sg:address":"225 E Main St",
    "sg:city":"Milford",
    "sg:classifiers":[
        {
            "category":"Autos & Motor Vehicles",
            "subcategory":"Automobile Sales",
            "type":"Retail Goods"
        }
    ],
    "sg:phone":"+1 508 478 8202",
    "sg:postcode":"01757",
    "sg:province":"MA",
    "sg:tags":[
        "car",
        "dealer"
    ],
    "sg:website":"www.rizoliauto.com",
    "wof:name":"Mark Rizoli Auto Village",
    "wof:placetype":"venue"
},
  "geometry": {"coordinates":[-71.500522,42.150788],"type":"Point"}
}