{
  "type": "Feature",
  "properties": {
    "iso:country":"US",
    "sg:address":"Woburn Mall",
    "sg:city":"Woburn",
    "sg:classifiers":[
        {
            "category":"Restaurant",
            "type":"Food & Drink"
        }
    ],
    "sg:phone":"+1 781 937 6016",
    "sg:postcode":"01801",
    "sg:province":"MA",
    "sg:tags":[
        "pizza"
    ],
    "wof:name":"Uno Chicago Grill",
    "wof:placetype":"venue"
},
  "geometry": {"coordinates":[-71.158997,42.484402],"type":"Point"}
}