{
  "type": "Feature",
  "properties": {
    "addr:full": "13 Kidder Rd Chelmsford MA 01824",
    "addr:housenumber": "13",
    "addr:postcode": "01824",
    "addr:street": "Kidder Rd",
    "iso:country": "US",
    "sg:address": "13 Kidder Rd",
    "sg:city": "Chelmsford",
    "sg:classifiers": [
      {
        "category": "Health Services",
        "subcategory": "Chiropractor",
        "type": "Services"
      }
    ],
    "sg:phone": "+1 800 522 2258",
    "sg:postcode": "01824",
    "sg:province": "MA",
    "wof:name": "Kennedy Chiropractic Supply",
    "wof:placetype": "venue"
  },
  "geometry": {"coordinates":[-71.389297,42.583],"type":"Point"}
}
