{
  "type": "Feature",
  "properties": {
    "addr:full": "6 Taylor Rd Lynn MA 01904",
    "addr:housenumber": "6",
    "addr:postcode": "01904",
    "addr:street": "Taylor Rd",
    "iso:country": "US",
    "sg:address": "6 Taylor Rd",
    "sg:city": "Lynn",
    "sg:classifiers": [
      {
        "category": "Building \u0026 Trades",
        "subcategory": "Cleaning \u0026 Sanitation",
        "type": "Services"
      }
    ],
    "sg:phone": "+1   ",
    "sg:postcode": "01904",
    "sg:province": "MA",
    "sg:tags": [
      "maintenance"
    ],
    "wof:name": "Lynns Cleaning Service",
    "wof:placetype": "venue"
  },
  "geometry": {"coordinates":[-70.968816,42.49437],"type":"Point"}
}
