{
  "type": "Feature",
  "properties": {
    "iso:country":"US",
    "sg:address":"6 Marie St",
    "sg:city":"Ludlow",
    "sg:classifiers":[
        {
            "category":"Building & Trades",
            "subcategory":"Construction",
            "type":"Services"
        }
    ],
    "sg:phone":"+1 413 589 7222",
    "sg:postcode":"01056",
    "sg:province":"MA",
    "sg:tags":[
        "fence",
        "contractor"
    ],
    "wof:name":"American Pride Fence",
    "wof:placetype":"venue"
},
  "geometry": {"coordinates":[-72.485737,42.163032],"type":"Point"}
}