{
  "type": "Feature",
  "properties": {
    "addr:full":"38 Main St West Dennis MA 02670",
    "addr:housenumber":"38",
    "addr:postcode":"02670",
    "addr:street":"Main St",
    "iso:country":"US",
    "sg:address":"38 Main St",
    "sg:city":"West Dennis",
    "sg:classifiers":[
        {
            "category":"Ferry",
            "type":"Transportation"
        }
    ],
    "sg:phone":"+1 508 362 5555",
    "sg:postcode":"02670",
    "sg:province":"MA",
    "sg:tags":[
        "boat"
    ],
    "wof:name":"Starfish Bass River Cruises",
    "wof:placetype":"venue"
},
  "geometry": {"coordinates":[-70.17865399999999,41.664718],"type":"Point"}
}