{
  "type": "Feature",
  "properties": {
    "iso:country":"US",
    "sg:address":"114 Gorham St",
    "sg:city":"Chelmsford",
    "sg:classifiers":[
        {
            "category":"Retail",
            "subcategory":"Auto Repair",
            "type":"Services"
        }
    ],
    "sg:phone":"+1 978 452 3938",
    "sg:postcode":"01824",
    "sg:province":"MA",
    "sg:tags":[
        "body",
        "automobile",
        "painting"
    ],
    "wof:name":"Al Gendron & Son Auto Body",
    "wof:placetype":"venue"
},
  "geometry": {"coordinates":[-71.301401,42.608827],"type":"Point"}
}