{
  "type": "Feature",
  "properties": {
    "addr:full":"37 North St Georgetown MA 01833",
    "addr:housenumber":"37",
    "addr:postcode":"01833",
    "addr:street":"North St",
    "iso:country":"US",
    "sg:address":"37 North St",
    "sg:city":"Georgetown",
    "sg:classifiers":[
        {
            "category":"Retail",
            "subcategory":"Portrait Studio",
            "type":"Services"
        }
    ],
    "sg:phone":"+1 978 352 7055",
    "sg:postcode":"01833",
    "sg:province":"MA",
    "sg:tags":[
        "photo",
        "photography"
    ],
    "wof:name":"Mackey Doc Photography",
    "wof:placetype":"venue"
},
  "geometry": {"coordinates":[-70.989609,42.726281],"type":"Point"}
}