{
  "type": "Feature",
  "properties": {
    "iso:country":"US",
    "sg:address":"10 Spring Ln",
    "sg:city":"Norton",
    "sg:classifiers":[
        {
            "category":"Professional",
            "subcategory":"Business Services",
            "type":"Services"
        }
    ],
    "sg:phone":"+1   ",
    "sg:postcode":"02766",
    "sg:province":"MA",
    "wof:name":"Tie Group",
    "wof:placetype":"venue"
},
  "geometry": {"coordinates":[-71.21641700000001,41.953648],"type":"Point"}
}