{
  "type": "Feature",
  "properties": {
    "iso:country":"US",
    "sg:address":"5 Paula Rd",
    "sg:city":"Milford",
    "sg:classifiers":[
        {
            "category":"Building & Trades",
            "subcategory":"Landscaping Services",
            "type":"Services"
        }
    ],
    "sg:phone":"+1 508 473 2129",
    "sg:postcode":"01757",
    "sg:province":"MA",
    "sg:tags":[
        "landscape",
        "contractor"
    ],
    "wof:name":"Giatas Landscaping",
    "wof:placetype":"venue"
},
  "geometry": {"coordinates":[-71.533123,42.15644],"type":"Point"}
}