{
  "type": "Feature",
  "properties": {
    "addr:full":"1670 Main St Agawam MA 01001",
    "addr:housenumber":"1670",
    "addr:postcode":"01001",
    "addr:street":"Main St",
    "iso:country":"US",
    "sg:address":"1670 Main St",
    "sg:city":"Agawam",
    "sg:classifiers":[
        {
            "category":"Freight",
            "type":"Transportation"
        }
    ],
    "sg:phone":"+1 413 786 1646",
    "sg:postcode":"01001",
    "sg:province":"MA",
    "sg:tags":[
        "commercial",
        "storage"
    ],
    "wof:name":"South Agawam Storage Facilties",
    "wof:placetype":"venue"
},
  "geometry": {"coordinates":[-72.616455,42.041464],"type":"Point"}
}