{
  "type": "Feature",
  "properties": {
    "iso:country":"US",
    "sg:address":"126 Burnside Dr",
    "sg:city":"Swansea",
    "sg:classifiers":[
        {
            "category":"Building & Trades",
            "subcategory":"Landscaping Services",
            "type":"Services"
        }
    ],
    "sg:phone":"+1 508 679 3600",
    "sg:postcode":"02777",
    "sg:province":"MA",
    "wof:name":"Nadeau Tree Svc",
    "wof:placetype":"venue"
},
  "geometry": {"coordinates":[-71.243183,41.74895],"type":"Point"}
}