{
  "type": "Feature",
  "properties": {
    "addr:full": "126 Burnside Dr Swansea MA 02777",
    "addr:housenumber": "126",
    "addr:postcode": "02777",
    "addr:street": "Burnside Dr",
    "iso:country": "US",
    "sg:address": "126 Burnside Dr",
    "sg:city": "Swansea",
    "sg:classifiers": [
      {
        "category": "Building \u0026 Trades",
        "subcategory": "Landscaping Services",
        "type": "Services"
      }
    ],
    "sg:phone": "+1 508 679 3600",
    "sg:postcode": "02777",
    "sg:province": "MA",
    "wof:name": "Nadeau Tree Svc",
    "wof:placetype": "venue"
  },
  "geometry": {"coordinates":[-71.243183,41.74895],"type":"Point"}
}
