{
  "type": "Feature",
  "properties": {
    "addr:full": "502 Boston Rd Billerica MA 01821",
    "addr:housenumber": "502",
    "addr:postcode": "01821",
    "addr:street": "Boston Rd",
    "iso:country": "US",
    "sg:address": "502 Boston Rd",
    "sg:city": "Billerica",
    "sg:classifiers": [
      {
        "category": "Restaurant",
        "type": "Food \u0026 Drink"
      }
    ],
    "sg:phone": "+1 978 670 7339",
    "sg:postcode": "01821",
    "sg:province": "MA",
    "sg:tags": [
      "chinese"
    ],
    "sg:website": "www.laosichuan.com/",
    "wof:name": "Sichuan Gourmet",
    "wof:placetype": "venue"
  },
  "geometry": {"coordinates":[-71.264198,42.552502],"type":"Point"}
}
