{
  "type": "Feature",
  "properties": {
    "addr:full": "434 Massachusetts Ave Ste 1 Boston MA 02118",
    "addr:housenumber": "434",
    "addr:postcode": "02118",
    "addr:street": "Massachusetts Ave Ste 1",
    "iso:country": "US",
    "sg:address": "434 Massachusetts Ave Ste 1",
    "sg:city": "Boston",
    "sg:classifiers": [
      {
        "category": "Professional",
        "subcategory": "Management \u0026 Consulting",
        "type": "Services"
      },
      {
        "category": "Education",
        "subcategory": "Special Training",
        "type": "Public Place"
      }
    ],
    "sg:phone": "+1 617 357 5717",
    "sg:postcode": "02118",
    "sg:province": "MA",
    "sg:tags": [
      "consultant",
      "educational"
    ],
    "wof:name": "Educational Development Group Inc",
    "wof:placetype": "venue"
  },
  "geometry": {"coordinates":[-71.082066,42.340808],"type":"Point"}
}
