{
  "type": "Feature",
  "properties": {
    "addr:full": "15 Shanpauly Dr Billerica MA 01821",
    "addr:housenumber": "15",
    "addr:postcode": "01821",
    "addr:street": "Shanpauly Dr",
    "iso:country": "US",
    "sg:address": "15 Shanpauly Dr",
    "sg:city": "Billerica",
    "sg:classifiers": [
      {
        "category": "Professional",
        "type": "Services"
      }
    ],
    "sg:phone": "+1   ",
    "sg:postcode": "01821",
    "sg:province": "MA",
    "wof:name": "Bayard R Lincoln",
    "wof:placetype": "venue"
  },
  "geometry": {"coordinates":[-71.230268,42.53787],"type":"Point"}
}
