{
  "type": "Feature",
  "properties": {
    "iso:country":"US",
    "sg:address":"33 Bradford St",
    "sg:city":"Concord",
    "sg:classifiers":[
        {
            "category":"Retail",
            "subcategory":"Portrait Studio",
            "type":"Services"
        }
    ],
    "sg:phone":"+1 978 287 5646",
    "sg:postcode":"01742",
    "sg:province":"MA",
    "sg:tags":[
        "photography"
    ],
    "wof:name":"John Earle Studio",
    "wof:placetype":"venue"
},
  "geometry": {"coordinates":[-71.396632,42.456771],"type":"Point"}
}