{
  "type": "Feature",
  "properties": {
    "iso:country":"US",
    "sg:address":"419 E River St",
    "sg:city":"Orange",
    "sg:classifiers":[
        {
            "category":"Real Estate",
            "subcategory":"Real Estate Operator",
            "type":"Services"
        }
    ],
    "sg:phone":"+1 978 544 7433",
    "sg:postcode":"01364",
    "sg:province":"MA",
    "sg:tags":[
        "apartment"
    ],
    "wof:name":"Pine Crest",
    "wof:placetype":"venue"
},
  "geometry": {"coordinates":[-72.29093,42.58322],"type":"Point"}
}