{
  "type": "Feature",
  "properties": {
    "iso:country":"US",
    "sg:address":"5 Watson Road",
    "sg:city":"Belmont",
    "sg:classifiers":[
        {
            "category":"Sports & Exercise",
            "subcategory":"Gym",
            "type":"Entertainment"
        }
    ],
    "sg:phone":"+1 617 489 1521",
    "sg:postcode":"02478",
    "sg:province":"MA",
    "sg:tags":[
        "trainer"
    ],
    "wof:name":"McDonnell Fredda Pschothrpst",
    "wof:placetype":"venue"
},
  "geometry": {"coordinates":[-71.161728,42.391611],"type":"Point"}
}