{
  "type": "Feature",
  "properties": {
    "addr:full":"216 Main St Wayland MA 01778",
    "addr:housenumber":"216",
    "addr:postcode":"01778",
    "addr:street":"Main St",
    "iso:country":"US",
    "sg:address":"216 Main St",
    "sg:city":"Wayland",
    "sg:classifiers":[
        {
            "category":"Building & Trades",
            "subcategory":"Locksmith",
            "type":"Services"
        }
    ],
    "sg:phone":"+1 508 655 4215",
    "sg:postcode":"01778",
    "sg:province":"MA",
    "sg:tags":[
        "lock",
        "industrial",
        "locksmiths-commercial"
    ],
    "wof:name":"Campana, R L Home Repair & Locksmith Service",
    "wof:placetype":"venue"
},
  "geometry": {"coordinates":[-71.364251,42.325911],"type":"Point"}
}