{
  "type": "Feature",
  "properties": {
    "addr:full": "11 State St Ludlow MA 01056",
    "addr:housenumber": "11",
    "addr:postcode": "01056",
    "addr:street": "State St",
    "iso:country": "US",
    "sg:address": "11 State St",
    "sg:city": "Ludlow",
    "sg:classifiers": [
      {
        "category": "Freight",
        "type": "Transportation"
      }
    ],
    "sg:phone": "+1 413 589 9223",
    "sg:postcode": "01056",
    "sg:province": "MA",
    "sg:tags": [
      "warehouse"
    ],
    "wof:name": "Waldman Publishing Corp",
    "wof:placetype": "venue"
  },
  "geometry": {"coordinates":[-72.479258,42.15658],"type":"Point"}
}
