{
  "type": "Feature",
  "properties": {
    "addr:full":"127 Eastern Ave Gloucester MA 01930",
    "addr:housenumber":"127",
    "addr:postcode":"01930",
    "addr:street":"Eastern Ave",
    "iso:country":"US",
    "sg:address":"127 Eastern Ave",
    "sg:city":"Gloucester",
    "sg:classifiers":[
        {
            "category":"Personal",
            "subcategory":"Beauty Salon",
            "type":"Services"
        }
    ],
    "sg:phone":"+1 978 282 4534",
    "sg:postcode":"01930",
    "sg:province":"MA",
    "wof:name":"Elegant Nails",
    "wof:placetype":"venue"
},
  "geometry": {"coordinates":[-70.640789,42.623734],"type":"Point"}
}