{
  "type": "Feature",
  "properties": {
    "addr:full": "875 Highland Ave Needham MA 02494",
    "addr:housenumber": "875",
    "addr:postcode": "02494",
    "addr:street": "Highland Ave",
    "iso:country": "US",
    "sg:address": "875 Highland Ave",
    "sg:city": "Needham",
    "sg:classifiers": [
      {
        "category": "Autos \u0026 Motor Vehicles",
        "subcategory": "Fuel \u0026 Gas Station",
        "type": "Retail Goods"
      }
    ],
    "sg:phone": "+1 781 444 9745",
    "sg:postcode": "02494",
    "sg:province": "MA",
    "sg:tags": [
      "oil"
    ],
    "wof:name": "Needham Heights Shell",
    "wof:placetype": "venue"
  },
  "geometry": {"coordinates":[-71.235348,42.29474],"type":"Point"}
}
