{
  "type": "Feature",
  "properties": {
    "iso:country":"US",
    "sg:address":"875 Highland Ave",
    "sg:city":"Needham",
    "sg:classifiers":[
        {
            "category":"Autos & Motor Vehicles",
            "subcategory":"Fuel & Gas Station",
            "type":"Retail Goods"
        }
    ],
    "sg:phone":"+1 781 444 9745",
    "sg:postcode":"02494",
    "sg:province":"MA",
    "sg:tags":[
        "oil"
    ],
    "wof:name":"Needham Heights Shell",
    "wof:placetype":"venue"
},
  "geometry": {"coordinates":[-71.235348,42.29474],"type":"Point"}
}