{
  "type": "Feature",
  "properties": {
    "addr:full": "775 Main St West Dennis MA 02670",
    "addr:housenumber": "775",
    "addr:postcode": "02670",
    "addr:street": "Main St",
    "iso:country": "US",
    "sg:address": "775 Main St",
    "sg:city": "West Dennis",
    "sg:classifiers": [
      {
        "category": "Shopping",
        "type": "Retail Goods"
      }
    ],
    "sg:phone": "+1 508 394 1001",
    "sg:postcode": "02670",
    "sg:province": "MA",
    "sg:tags": [
      "hearing",
      "equipment",
      "supply",
      "impaired"
    ],
    "wof:name": "Hogan's Hearing Aid Ctr",
    "wof:placetype": "venue"
  },
  "geometry": {"coordinates":[-70.154326,41.667612],"type":"Point"}
}
