{
  "type": "Feature",
  "properties": {
    "iso:country":"US",
    "sg:address":"6 Surrey Ln",
    "sg:city":"Wilbraham",
    "sg:classifiers":[
        {
            "category":"Building & Trades",
            "subcategory":"Construction",
            "type":"Services"
        }
    ],
    "sg:phone":"+1 413 596 2641",
    "sg:postcode":"01095",
    "sg:province":"MA",
    "sg:tags":[
        "siding",
        "contractor"
    ],
    "wof:name":"Julien Drapeau Home Imprvmnts",
    "wof:placetype":"venue"
},
  "geometry": {"coordinates":[-72.475109,42.134831],"type":"Point"}
}