{
  "type": "Feature",
  "properties": {
    "iso:country":"US",
    "sg:address":"15 Albany St",
    "sg:city":"Worcester",
    "sg:classifiers":[
        {
            "category":"Building & Trades",
            "subcategory":"Plumbing",
            "type":"Services"
        }
    ],
    "sg:phone":"+1 508 754 4300",
    "sg:postcode":"01604",
    "sg:province":"MA",
    "sg:tags":[
        "plumbing",
        "contractor"
    ],
    "wof:name":"Affilliated Plumbing & Htg Inc",
    "wof:placetype":"venue"
},
  "geometry": {"coordinates":[-71.785427,42.263787],"type":"Point"}
}