{
  "type": "Feature",
  "properties": {
    "addr:full": "15 Albany St Worcester MA 01604",
    "addr:housenumber": "15",
    "addr:postcode": "01604",
    "addr:street": "Albany St",
    "iso:country": "US",
    "sg:address": "15 Albany St",
    "sg:city": "Worcester",
    "sg:classifiers": [
      {
        "category": "Building \u0026 Trades",
        "subcategory": "Plumbing",
        "type": "Services"
      }
    ],
    "sg:phone": "+1 508 754 4300",
    "sg:postcode": "01604",
    "sg:province": "MA",
    "sg:tags": [
      "plumbing",
      "contractor"
    ],
    "wof:name": "Affilliated Plumbing \u0026 Htg Inc",
    "wof:placetype": "venue"
  },
  "geometry": {"coordinates":[-71.785427,42.263787],"type":"Point"}
}
