{
  "type": "Feature",
  "properties": {
    "iso:country":"US",
    "sg:address":"374 Salem St",
    "sg:city":"Malden",
    "sg:classifiers":[
        {
            "category":"Personal",
            "subcategory":"Beauty Salon",
            "type":"Services"
        }
    ],
    "sg:phone":"+1 781 397 0130",
    "sg:postcode":"02148",
    "sg:province":"MA",
    "wof:name":"Mickey's Hair Salon",
    "wof:placetype":"venue"
},
  "geometry": {"coordinates":[-71.05488200000001,42.431192],"type":"Point"}
}