{
  "type": "Feature",
  "properties": {
    "addr:full":"26 Memorial Ave Chicopee MA 01020",
    "addr:housenumber":"26",
    "addr:postcode":"01020",
    "addr:street":"Memorial Ave",
    "iso:country":"US",
    "sg:address":"26 Memorial Ave",
    "sg:city":"Chicopee",
    "sg:classifiers":[
        {
            "category":"Education",
            "subcategory":"School",
            "type":"Public Place"
        }
    ],
    "sg:phone":"+1 413 594 3501",
    "sg:postcode":"01020",
    "sg:province":"MA",
    "wof:name":"Fairview Veterans Memorial Mid",
    "wof:placetype":"venue"
},
  "geometry": {"coordinates":[-72.574804,42.208505],"type":"Point"}
}