{
  "type": "Feature",
  "properties": {
    "addr:full": "24 Mount Auburn St Cambridge MA 02138",
    "addr:housenumber": "24",
    "addr:postcode": "02138",
    "addr:street": "Mount Auburn St",
    "iso:country": "US",
    "sg:address": "24 Mount Auburn St",
    "sg:city": "Cambridge",
    "sg:classifiers": [
      {
        "category": "Organizations",
        "subcategory": "Community Association",
        "type": "Services"
      }
    ],
    "sg:phone": "+1 617 547 4100",
    "sg:postcode": "02138",
    "sg:province": "MA",
    "wof:name": "New England Complex Systems",
    "wof:placetype": "venue"
  },
  "geometry": {"coordinates":[-71.115173,42.37075],"type":"Point"}
}
