{
  "type": "Feature",
  "properties": {
    "iso:country":"US",
    "sg:address":"199 Mallory Rd",
    "sg:city":"New Ashford",
    "sg:classifiers":[
        {
            "category":"Government",
            "subcategory":"Office",
            "type":"Public Place"
        }
    ],
    "sg:phone":"+1 413 458 5461",
    "sg:postcode":"01237",
    "sg:province":"NY",
    "sg:tags":[
        "city"
    ],
    "wof:name":"New Ashford Town Hall",
    "wof:placetype":"venue"
},
  "geometry": {"coordinates":[-73.24574200000001,42.593741],"type":"Point"}
}