{
  "type": "Feature",
  "properties": {
    "addr:full":"219 Sandwich Rd Wareham MA 02571",
    "addr:housenumber":"219",
    "addr:postcode":"02571",
    "addr:street":"Sandwich Rd",
    "iso:country":"US",
    "sg:address":"219 Sandwich Rd",
    "sg:city":"Wareham",
    "sg:classifiers":[
        {
            "category":"Farming",
            "subcategory":"Berry Farm",
            "type":"Manufacturing & Wholesale Goods"
        }
    ],
    "sg:phone":"+1   ",
    "sg:postcode":"02571",
    "sg:province":"MA",
    "sg:tags":[
        "crop"
    ],
    "wof:name":"WD Ames Inc",
    "wof:placetype":"venue"
},
  "geometry": {"coordinates":[-70.68514399999999,41.763504],"type":"Point"}
}