{
  "type": "Feature",
  "properties": {
    "addr:full": "22 Rockdale St Worcester MA 01606",
    "addr:housenumber": "22",
    "addr:postcode": "01606",
    "addr:street": "Rockdale St",
    "iso:country": "US",
    "sg:address": "22 Rockdale St",
    "sg:city": "Worcester",
    "sg:classifiers": [
      {
        "category": "Professional",
        "subcategory": "Printing \u0026 Photocopies",
        "type": "Services"
      }
    ],
    "sg:phone": "+1 508 852 1195",
    "sg:postcode": "01606",
    "sg:province": "MA",
    "sg:tags": [
      "engraving"
    ],
    "wof:name": "Markonics",
    "wof:placetype": "venue"
  },
  "geometry": {"coordinates":[-71.799141,42.311008],"type":"Point"}
}
