{
  "type": "Feature",
  "properties": {
    "iso:country":"US",
    "sg:address":"22 Rockdale St",
    "sg:city":"Worcester",
    "sg:classifiers":[
        {
            "category":"Professional",
            "subcategory":"Printing & Photocopies",
            "type":"Services"
        }
    ],
    "sg:phone":"+1 508 852 1195",
    "sg:postcode":"01606",
    "sg:province":"MA",
    "sg:tags":[
        "engraving"
    ],
    "wof:name":"Markonics",
    "wof:placetype":"venue"
},
  "geometry": {"coordinates":[-71.79914100000001,42.311008],"type":"Point"}
}