{
  "type": "Feature",
  "properties": {
    "iso:country":"US",
    "sg:address":"176 Sheep Pond Cir",
    "sg:city":"Brewster",
    "sg:classifiers":[
        {
            "category":"Building & Trades",
            "subcategory":"Construction",
            "type":"Services"
        }
    ],
    "sg:phone":"+1 508 896 9274",
    "sg:postcode":"02631",
    "sg:province":"MA",
    "sg:tags":[
        "restoration",
        "cleaning",
        "patio",
        "deck"
    ],
    "wof:name":"Clean All Pressure Washing",
    "wof:placetype":"venue"
},
  "geometry": {"coordinates":[-70.064639,41.737084],"type":"Point"}
}