{
  "type": "Feature",
  "properties": {
    "iso:country":"US",
    "sg:address":"26 Adams St",
    "sg:city":"North Adams",
    "sg:classifiers":[
        {
            "category":"Bars & Pubs",
            "type":"Food & Drink"
        }
    ],
    "sg:phone":"+1 413 664 6087",
    "sg:postcode":"01247",
    "sg:province":"MA",
    "sg:tags":[
        "lounge",
        "cocktail"
    ],
    "wof:name":"Artery Lounge",
    "wof:placetype":"venue"
},
  "geometry": {"coordinates":[-73.123019,42.704164],"type":"Point"}
}