{
  "type": "Feature",
  "properties": {
    "addr:full":"1661 Washington St Holliston MA 01746",
    "addr:housenumber":"1661",
    "addr:postcode":"01746",
    "addr:street":"Washington St",
    "iso:country":"US",
    "sg:address":"1661 Washington St",
    "sg:city":"Holliston",
    "sg:classifiers":[
        {
            "category":"Government",
            "subcategory":"Post Office",
            "type":"Public Place"
        }
    ],
    "sg:phone":"+1 508 429 7479",
    "sg:postcode":"01746",
    "sg:province":"MA",
    "wof:name":"US Post Office",
    "wof:placetype":"venue"
},
  "geometry": {"coordinates":[-71.45081399999999,42.179724],"type":"Point"}
}