{
  "type": "Feature",
  "properties": {
    "addr:full":"50 Sutherland Rd Brighton MA 02135",
    "addr:housenumber":"50",
    "addr:postcode":"02135",
    "addr:street":"Sutherland Rd",
    "iso:country":"US",
    "sg:address":"50 Sutherland Rd",
    "sg:city":"Brighton",
    "sg:classifiers":[
        {
            "category":"Education",
            "subcategory":"Preschool",
            "type":"Public Place"
        },
        {
            "category":"Education",
            "subcategory":"School",
            "type":"Public Place"
        }
    ],
    "sg:phone":"+1 617 278 2950",
    "sg:postcode":"02135",
    "sg:province":"MA",
    "sg:tags":[
        "elementary"
    ],
    "wof:name":"Jewish Community Center Preschool-Brookline",
    "wof:placetype":"venue"
},
  "geometry": {"coordinates":[-71.153397,42.3493],"type":"Point"}
}