{
  "type": "Feature",
  "properties": {
    "iso:country":"US",
    "sg:address":"822 Boylston St",
    "sg:city":"Chestnut Hill",
    "sg:classifiers":[
        {
            "category":"Professional",
            "type":"Services"
        }
    ],
    "sg:phone":"+1 617 731 1239",
    "sg:postcode":"02467",
    "sg:province":"MA",
    "sg:tags":[
        "establishment"
    ],
    "wof:name":"Aesthetic Options",
    "wof:placetype":"venue"
},
  "geometry": {"coordinates":[-71.204914,42.319224],"type":"Point"}
}