{
  "type": "Feature",
  "properties": {
    "addr:full":"310 E Falmouth Hwy East Falmouth MA 02536",
    "addr:housenumber":"310",
    "addr:postcode":"02536",
    "addr:street":"E Falmouth Hwy",
    "iso:country":"US",
    "sg:address":"310 E Falmouth Hwy",
    "sg:city":"East Falmouth",
    "sg:classifiers":[
        {
            "category":"Education",
            "subcategory":"Library",
            "type":"Public Place"
        }
    ],
    "sg:phone":"+1 508 548 6340",
    "sg:postcode":"02536",
    "sg:province":"MA",
    "wof:name":"E Falmouth Public Library",
    "wof:placetype":"venue"
},
  "geometry": {"coordinates":[-70.562708,41.578835],"type":"Point"}
}