{
  "type": "Feature",
  "properties": {
    "iso:country":"US",
    "sg:address":"262 Barnstable Rd",
    "sg:city":"Hyannis",
    "sg:classifiers":[
        {
            "category":"Health Services",
            "subcategory":"Dentist",
            "type":"Services"
        }
    ],
    "sg:phone":"+1 508 778 1200",
    "sg:postcode":"02601",
    "sg:province":"MA",
    "wof:name":"Seidman Michael P DDS PC",
    "wof:placetype":"venue"
},
  "geometry": {"coordinates":[-70.28510300000001,41.660599],"type":"Point"}
}