{
  "type": "Feature",
  "properties": {
    "iso:country":"US",
    "sg:address":"132 Central St",
    "sg:city":"Foxboro",
    "sg:classifiers":[
        {
            "category":"Health Services",
            "subcategory":"Optometrist",
            "type":"Services"
        }
    ],
    "sg:phone":"+1 508 543 9215",
    "sg:postcode":"02035",
    "sg:province":"MA",
    "wof:name":"Foxboro Eye Care",
    "wof:placetype":"venue"
},
  "geometry": {"coordinates":[-71.24238099999999,42.056935],"type":"Point"}
}