{
  "type": "Feature",
  "properties": {
    "addr:full":"304 Belmont Ave Springfield MA 01108",
    "addr:housenumber":"304",
    "addr:postcode":"01108",
    "addr:street":"Belmont Ave",
    "iso:country":"US",
    "sg:address":"304 Belmont Ave",
    "sg:city":"Springfield",
    "sg:classifiers":[
        {
            "category":"Taxi",
            "type":"Transportation"
        }
    ],
    "sg:phone":"+1 413 731 8485",
    "sg:postcode":"01108",
    "sg:province":"MA",
    "sg:tags":[
        "taxicab"
    ],
    "wof:name":"Dial A Ride",
    "wof:placetype":"venue"
},
  "geometry": {"coordinates":[-72.56701700000001,42.087796],"type":"Point"}
}