{
  "type": "Feature",
  "properties": {
    "addr:full": "38 Edson Rd Oakham MA 01068",
    "addr:housenumber": "38",
    "addr:postcode": "01068",
    "addr:street": "Edson Rd",
    "iso:country": "US",
    "sg:address": "38 Edson Rd",
    "sg:city": "Oakham",
    "sg:classifiers": [
      {
        "category": "Shopping",
        "subcategory": "Pets \u0026 Pet Supplies",
        "type": "Retail Goods"
      },
      {
        "category": "Retail",
        "subcategory": "Veterinary Services",
        "type": "Services"
      }
    ],
    "sg:phone": "+1 508 882 3482",
    "sg:postcode": "01068",
    "sg:province": "MA",
    "sg:tags": [
      "specialty"
    ],
    "wof:name": "Grey Horse Farm",
    "wof:placetype": "venue"
  },
  "geometry": {"coordinates":[-72.070969,42.37542],"type":"Point"}
}
