{
  "type": "Feature",
  "properties": {
    "iso:country":"US",
    "sg:address":"161 E Main St",
    "sg:city":"Milford",
    "sg:classifiers":[
        {
            "category":"Home & Garden",
            "subcategory":"Furniture",
            "type":"Retail Goods"
        }
    ],
    "sg:phone":"+1 508 478 1882",
    "sg:postcode":"01757",
    "sg:province":"MA",
    "wof:name":"Milford's Furniture",
    "wof:placetype":"venue"
},
  "geometry": {"coordinates":[-71.505066,42.149866],"type":"Point"}
}