{
  "type": "Feature",
  "properties": {
    "addr:full": "175 New Boston St Woburn MA 01801",
    "addr:housenumber": "175",
    "addr:postcode": "01801",
    "addr:street": "New Boston St",
    "iso:country": "US",
    "sg:address": "175 New Boston St",
    "sg:city": "Woburn",
    "sg:classifiers": [
      {
        "category": "Wholesale",
        "subcategory": "Computers",
        "type": "Manufacturing \u0026 Wholesale Goods"
      }
    ],
    "sg:phone": "+1 781 939 5875",
    "sg:postcode": "01801",
    "sg:province": "MA",
    "wof:name": "Accutech Computer Company",
    "wof:placetype": "venue"
  },
  "geometry": {"coordinates":[-71.143288,42.511513],"type":"Point"}
}
