{
  "type": "Feature",
  "properties": {
    "iso:country":"US",
    "sg:address":"175 New Boston St",
    "sg:city":"Woburn",
    "sg:classifiers":[
        {
            "category":"Wholesale",
            "subcategory":"Computers",
            "type":"Manufacturing & Wholesale Goods"
        }
    ],
    "sg:phone":"+1 781 939 5875",
    "sg:postcode":"01801",
    "sg:province":"MA",
    "wof:name":"Accutech Computer Company",
    "wof:placetype":"venue"
},
  "geometry": {"coordinates":[-71.143288,42.511513],"type":"Point"}
}