{
  "type": "Feature",
  "properties": {
    "addr:full":"11 Main St Southborough MA 01772",
    "addr:housenumber":"11",
    "addr:postcode":"01772",
    "addr:street":"Main St",
    "iso:country":"US",
    "sg:address":"11 Main St",
    "sg:city":"Southborough",
    "sg:classifiers":[
        {
            "category":"Communications",
            "type":"Services"
        }
    ],
    "sg:phone":"+1 508 481 2950",
    "sg:postcode":"01772",
    "sg:province":"MA",
    "wof:name":"Communicatinos Unlimited",
    "wof:placetype":"venue"
},
  "geometry": {"coordinates":[-71.52552799999999,42.305582],"type":"Point"}
}