{
  "type": "Feature",
  "properties": {
    "addr:full":"3 Forbes Rd Lexington MA 02421",
    "addr:housenumber":"3",
    "addr:postcode":"02421",
    "addr:street":"Forbes Rd",
    "iso:country":"US",
    "sg:address":"3 Forbes Rd",
    "sg:city":"Lexington",
    "sg:classifiers":[
        {
            "category":"Building & Trades",
            "subcategory":"Locksmith",
            "type":"Services"
        }
    ],
    "sg:phone":"+1 781 301 6035",
    "sg:postcode":"02421",
    "sg:province":"MA",
    "sg:tags":[
        "key"
    ],
    "wof:name":"24 Emergency Locksmith",
    "wof:placetype":"venue"
},
  "geometry": {"coordinates":[-71.26177199999999,42.44456],"type":"Point"}
}