{
  "type": "Feature",
  "properties": {
    "iso:country":"US",
    "sg:address":"305 Newbury Street",
    "sg:city":"Boston",
    "sg:classifiers":[
        {
            "category":"Real Estate",
            "subcategory":"Architect",
            "type":"Services"
        }
    ],
    "sg:phone":"+1 617 247 7499",
    "sg:postcode":"02115",
    "sg:province":"MA",
    "wof:name":"Rosales Gottemoeller & Associates",
    "wof:placetype":"venue"
},
  "geometry": {"coordinates":[-71.085037,42.348953],"type":"Point"}
}