{
  "type": "Feature",
  "properties": {
    "addr:full":"702 Washington St Dorchester Ctr MA 02124",
    "addr:housenumber":"702",
    "addr:postcode":"02124",
    "addr:street":"Washington St",
    "iso:country":"US",
    "sg:address":"702 Washington St",
    "sg:city":"Dorchester Ctr",
    "sg:classifiers":[
        {
            "category":"Real Estate",
            "subcategory":"Real Estate Agent",
            "type":"Services"
        }
    ],
    "sg:phone":"+1 617 825 8888",
    "sg:postcode":"02124",
    "sg:province":"MA",
    "wof:name":"Codman Square Apartments",
    "wof:placetype":"venue"
},
  "geometry": {"coordinates":[-71.071095,42.286501],"type":"Point"}
}