{
  "type": "Feature",
  "properties": {
    "iso:country":"US",
    "sg:address":"600 Mount Pleasant St",
    "sg:city":"New Bedford",
    "sg:classifiers":[
        {
            "category":"Freight",
            "type":"Transportation"
        }
    ],
    "sg:phone":"+1 508 995 1844",
    "sg:postcode":"02745",
    "sg:province":"MA",
    "sg:tags":[
        "commercial",
        "storage"
    ],
    "wof:name":"Airport Mini Storage",
    "wof:placetype":"venue"
},
  "geometry": {"coordinates":[-70.943153,41.665966],"type":"Point"}
}