{
  "type": "Feature",
  "properties": {
    "addr:full": "600 Mount Pleasant St New Bedford MA 02745",
    "addr:housenumber": "600",
    "addr:postcode": "02745",
    "addr:street": "Mount Pleasant St",
    "iso:country": "US",
    "ovtr:label": "Airport Mini Storage, 600 Mt Pleasant St New Bedford MA US",
    "ovtr:similarity": 2.5680079460144043,
    "sg:address": "600 Mount Pleasant St",
    "sg:city": "New Bedford",
    "sg:classifiers": [
      {
        "category": "Freight",
        "type": "Transportation"
      }
    ],
    "sg:phone": "+1 508 995 1844",
    "sg:postcode": "02745",
    "sg:province": "MA",
    "sg:tags": [
      "commercial",
      "storage"
    ],
    "wof:name": "Airport Mini Storage",
    "wof:placetype": "venue"
  },
  "geometry": {"coordinates":[-70.943153,41.665966],"type":"Point"}
}
