{
  "type": "Feature",
  "properties": {
    "addr:full":"1688 Main St Springfield MA 01103",
    "addr:housenumber":"1688",
    "addr:postcode":"01103",
    "addr:street":"Main St",
    "iso:country":"US",
    "sg:address":"1688 Main St",
    "sg:city":"Springfield",
    "sg:classifiers":[
        {
            "category":"Restaurant",
            "type":"Food & Drink"
        }
    ],
    "sg:phone":"+1 413 732 8011",
    "sg:postcode":"01103",
    "sg:province":"MA",
    "wof:name":"Sitar Restaurant",
    "wof:placetype":"venue"
},
  "geometry": {"coordinates":[-72.594977,42.104704],"type":"Point"}
}