{
  "type": "Feature",
  "properties": {
    "addr:full":"1170 Beacon Street Brookline MA 02446",
    "addr:housenumber":"1170",
    "addr:postcode":"02446",
    "addr:street":"Beacon Street",
    "iso:country":"US",
    "sg:address":"1170 Beacon Street",
    "sg:city":"Brookline",
    "sg:classifiers":[
        {
            "category":"Sports & Exercise",
            "subcategory":"Gym",
            "type":"Entertainment"
        }
    ],
    "sg:phone":"+1 617 731 2707",
    "sg:postcode":"02446",
    "sg:province":"MA",
    "sg:tags":[
        "trainer"
    ],
    "wof:name":"Sandman Nancy Socl Worker",
    "wof:placetype":"venue"
},
  "geometry": {"coordinates":[-71.11429200000001,42.344185],"type":"Point"}
}