{
  "type": "Feature",
  "properties": {
    "iso:country":"US",
    "sg:address":"90 Conz St",
    "sg:city":"Northampton",
    "sg:classifiers":[
        {
            "category":"Health Services",
            "subcategory":"Health Practitioner",
            "type":"Services"
        }
    ],
    "sg:phone":"+1 413 586 8118",
    "sg:postcode":"01060",
    "sg:province":"MA",
    "sg:tags":[
        "psychologist"
    ],
    "wof:name":"Kara Kritis Harper PHD",
    "wof:placetype":"venue"
},
  "geometry": {"coordinates":[-72.626677,42.313228],"type":"Point"}
}