{
  "type": "Feature",
  "properties": {
    "addr:full":"121 Harvard Avenue Allston MA 02134",
    "addr:housenumber":"121",
    "addr:postcode":"02134",
    "addr:street":"Harvard Avenue",
    "iso:country":"US",
    "sg:address":"121 Harvard Avenue",
    "sg:city":"Allston",
    "sg:classifiers":[
        {
            "category":"Professional",
            "subcategory":"Lawyer & Legal Services",
            "type":"Services"
        }
    ],
    "sg:phone":"+1 617 782 8210",
    "sg:postcode":"02134",
    "sg:province":"MA",
    "wof:name":"Boone Jefferson W Atty",
    "wof:placetype":"venue"
},
  "geometry": {"coordinates":[-71.13172900000001,42.352267],"type":"Point"}
}