{
  "type": "Feature",
  "properties": {
    "addr:full":"29 Gilmore Dr Sutton MA 01590",
    "addr:housenumber":"29",
    "addr:postcode":"01590",
    "addr:street":"Gilmore Dr",
    "iso:country":"US",
    "sg:address":"29 Gilmore Dr",
    "sg:city":"Sutton",
    "sg:classifiers":[
        {
            "category":"Freight",
            "type":"Transportation"
        }
    ],
    "sg:phone":"+1   ",
    "sg:postcode":"01590",
    "sg:province":"MA",
    "sg:tags":[
        "operator",
        "local",
        "trucking"
    ],
    "wof:name":"Bay State Moving Systems Inc",
    "wof:placetype":"venue"
},
  "geometry": {"coordinates":[-71.70733300000001,42.10632],"type":"Point"}
}