{
  "type": "Feature",
  "properties": {
    "addr:full": "2 Brande Ct Reading MA 01867",
    "addr:housenumber": "2",
    "addr:postcode": "01867",
    "addr:street": "Brande Ct",
    "iso:country": "US",
    "ovtr:label": "Colombo's Pizza \u0026 Cafe, 2 Brande Ct Reading MA US",
    "ovtr:similarity": 3.1681571006774902,
    "sg:address": "2 Brande Ct",
    "sg:city": "Reading",
    "sg:classifiers": [
      {
        "category": "Restaurant",
        "type": "Food \u0026 Drink"
      }
    ],
    "sg:phone": "+1 781 944 1006",
    "sg:postcode": "01867",
    "sg:province": "MA",
    "sg:tags": [
      "pizza"
    ],
    "sg:website": "www.colombospizzacafe.com",
    "wof:name": "Colombo's Pizza and Cafe",
    "wof:placetype": "venue"
  },
  "geometry": {"coordinates":[-71.107479,42.522436],"type":"Point"}
}
