{
  "type": "Feature",
  "properties": {
    "iso:country":"US",
    "sg:address":"2 Brande Ct",
    "sg:city":"Reading",
    "sg:classifiers":[
        {
            "category":"Restaurant",
            "type":"Food & Drink"
        }
    ],
    "sg:phone":"+1 781 944 1006",
    "sg:postcode":"01867",
    "sg:province":"MA",
    "sg:tags":[
        "pizza"
    ],
    "sg:website":"www.colombospizzacafe.com",
    "wof:name":"Colombo's Pizza and Cafe",
    "wof:placetype":"venue"
},
  "geometry": {"coordinates":[-71.107479,42.522436],"type":"Point"}
}