{
  "type": "Feature",
  "properties": {
    "iso:country":"US",
    "sg:address":"36 Carmelinas Cir",
    "sg:city":"Ludlow",
    "sg:classifiers":[
        {
            "category":"Building & Trades",
            "subcategory":"Construction",
            "type":"Services"
        }
    ],
    "sg:phone":"+1 413 547 2767",
    "sg:postcode":"01056",
    "sg:province":"MA",
    "sg:tags":[
        "general",
        "contractor"
    ],
    "wof:name":"Freitas Construction Inc",
    "wof:placetype":"venue"
},
  "geometry": {"coordinates":[-72.445525,42.171158],"type":"Point"}
}