{
  "type": "Feature",
  "properties": {
    "iso:country":"US",
    "sg:address":"8 Spring St",
    "sg:city":"Wellesley",
    "sg:classifiers":[
        {
            "category":"Retail",
            "subcategory":"Auto Repair",
            "type":"Services"
        }
    ],
    "sg:phone":"+1 781 235 2886",
    "sg:postcode":"02482",
    "sg:province":"MA",
    "sg:tags":[
        "wheel",
        "axle",
        "alignment"
    ],
    "wof:name":"Auto Lab Alignment",
    "wof:placetype":"venue"
},
  "geometry": {"coordinates":[-71.291594,42.296414],"type":"Point"}
}