{
  "type": "Feature",
  "properties": {
    "addr:full":"92 Paxton Rd Spencer MA 01562",
    "addr:housenumber":"92",
    "addr:postcode":"01562",
    "addr:street":"Paxton Rd",
    "iso:country":"US",
    "sg:address":"92 Paxton Rd",
    "sg:city":"Spencer",
    "sg:classifiers":[
        {
            "category":"Building & Trades",
            "subcategory":"Construction",
            "type":"Services"
        }
    ],
    "sg:phone":"+1 508 885 5456",
    "sg:postcode":"01562",
    "sg:province":"MA",
    "sg:tags":[
        "general",
        "contractor"
    ],
    "wof:name":"J R Faucher Plastering",
    "wof:placetype":"venue"
},
  "geometry": {"coordinates":[-71.975661,42.269538],"type":"Point"}
}