{
  "type": "Feature",
  "properties": {
    "iso:country":"US",
    "sg:address":"2 Fairmount Ave",
    "sg:city":"Hyde Park",
    "sg:classifiers":[
        {
            "category":"Food & Beverages",
            "subcategory":"Groceries & Convenience Stores",
            "type":"Retail Goods"
        }
    ],
    "sg:phone":"+1 617 361 9631",
    "sg:postcode":"02136",
    "sg:province":"MA",
    "wof:name":"Fairmount Mini Mart",
    "wof:placetype":"venue"
},
  "geometry": {"coordinates":[-71.120277,42.255021],"type":"Point"}
}