{
  "type": "Feature",
  "properties": {
    "addr:full":"8 Union Sq Gardner MA 01440",
    "addr:housenumber":"8",
    "addr:postcode":"01440",
    "addr:street":"Union Sq",
    "iso:country":"US",
    "sg:address":"8 Union Sq",
    "sg:city":"Gardner",
    "sg:classifiers":[
        {
            "category":"Social Services",
            "type":"Services"
        }
    ],
    "sg:phone":"+1 978 632 9854",
    "sg:postcode":"01440",
    "sg:province":"MA",
    "sg:tags":[
        "organization",
        "welfare"
    ],
    "wof:name":"Salvation Army",
    "wof:placetype":"venue"
},
  "geometry": {"coordinates":[-71.98303900000001,42.567113],"type":"Point"}
}