{
  "type": "Feature",
  "properties": {
    "iso:country":"US",
    "sg:address":"10 Boxford Rd",
    "sg:city":"Rowley",
    "sg:classifiers":[
        {
            "category":"Building & Trades",
            "subcategory":"Landscaping Services",
            "type":"Services"
        }
    ],
    "sg:phone":"+1 978 948 3707",
    "sg:postcode":"01969",
    "sg:province":"MA",
    "sg:tags":[
        "landscape",
        "contractor"
    ],
    "wof:name":"Guisto Landscaping",
    "wof:placetype":"venue"
},
  "geometry": {"coordinates":[-70.944003,42.702787],"type":"Point"}
}