{
  "type": "Feature",
  "properties": {
    "addr:full":"43 Elm St Georgetown MA 01833",
    "addr:housenumber":"43",
    "addr:postcode":"01833",
    "addr:street":"Elm St",
    "iso:country":"US",
    "sg:address":"43 Elm St",
    "sg:city":"Georgetown",
    "sg:classifiers":[
        {
            "category":"Professional",
            "subcategory":"Business Services",
            "type":"Services"
        }
    ],
    "sg:phone":"+1   ",
    "sg:postcode":"01833",
    "sg:province":"MA",
    "wof:name":"Tom Rhinelander",
    "wof:placetype":"venue"
},
  "geometry": {"coordinates":[-70.986593,42.717524],"type":"Point"}
}