{
  "type": "Feature",
  "properties": {
    "iso:country":"US",
    "sg:address":"317 Chestnut St",
    "sg:city":"Needham",
    "sg:classifiers":[
        {
            "category":"Retail",
            "subcategory":"Laundry & Dry Cleaning",
            "type":"Services"
        }
    ],
    "sg:phone":"+1 781 449 8030",
    "sg:postcode":"02492",
    "sg:province":"MA",
    "sg:tags":[
        "cleaners"
    ],
    "wof:name":"Jaylin Cleaners",
    "wof:placetype":"venue"
},
  "geometry": {"coordinates":[-71.23795200000001,42.274355],"type":"Point"}
}