{
  "type": "Feature",
  "properties": {
    "addr:full":"6 Maxam Rd Colrain MA 01340",
    "addr:housenumber":"6",
    "addr:postcode":"01340",
    "addr:street":"Maxam Rd",
    "iso:country":"US",
    "sg:address":"6 Maxam Rd",
    "sg:city":"Colrain",
    "sg:classifiers":[
        {
            "category":"Wholesale",
            "subcategory":"Apparel",
            "type":"Manufacturing & Wholesale Goods"
        }
    ],
    "sg:phone":"+1 413 624 0262",
    "sg:postcode":"01340",
    "sg:province":"MA",
    "sg:website":"www.briteties.com",
    "wof:name":"Brite Ties",
    "wof:placetype":"venue"
},
  "geometry": {"coordinates":[-72.748092,42.679877],"type":"Point"}
}