{
  "type": "Feature",
  "properties": {
    "addr:full":"8 Porter Ave Somerville MA 02143",
    "addr:housenumber":"8",
    "addr:postcode":"02143",
    "addr:street":"Porter Ave",
    "iso:country":"US",
    "sg:address":"8 Porter Ave",
    "sg:city":"Somerville",
    "sg:classifiers":[
        {
            "category":"Professional",
            "subcategory":"Management & Consulting",
            "type":"Services"
        }
    ],
    "sg:phone":"+1   ",
    "sg:postcode":"02143",
    "sg:province":"MA",
    "wof:name":"David Humsey Assoc Inc",
    "wof:placetype":"venue"
},
  "geometry": {"coordinates":[-71.111991,42.389746],"type":"Point"}
}