{
  "type": "Feature",
  "properties": {
    "addr:full":"7 Kelsey Ln Shirley MA 01464",
    "addr:housenumber":"7",
    "addr:postcode":"01464",
    "addr:street":"Kelsey Ln",
    "iso:country":"US",
    "sg:address":"7 Kelsey Ln",
    "sg:city":"Shirley",
    "sg:classifiers":[
        {
            "category":"Professional",
            "subcategory":"Detective & Security Services",
            "type":"Services"
        }
    ],
    "sg:phone":"+1 978 425 2582",
    "sg:postcode":"01464",
    "sg:province":"MA",
    "sg:tags":[
        "information",
        "bureau"
    ],
    "wof:name":"Patriot Network Services",
    "wof:placetype":"venue"
},
  "geometry": {"coordinates":[-71.64151,42.549519],"type":"Point"}
}