{
  "type": "Feature",
  "properties": {
    "addr:full":"1127 Riverdale St West Springfield MA 01089",
    "addr:housenumber":"1127",
    "addr:postcode":"01089",
    "addr:street":"Riverdale St",
    "iso:country":"US",
    "sg:address":"1127 Riverdale St",
    "sg:city":"West Springfield",
    "sg:classifiers":[
        {
            "category":"Autos & Motor Vehicles",
            "subcategory":"Auto Supplies",
            "type":"Retail Goods"
        }
    ],
    "sg:phone":"+1 413 787 0701",
    "sg:postcode":"01089",
    "sg:province":"MA",
    "sg:tags":[
        "tire"
    ],
    "sg:website":"www.townfair.com",
    "wof:name":"Town Fair Tire",
    "wof:placetype":"venue"
},
  "geometry": {"coordinates":[-72.626121,42.138684],"type":"Point"}
}