{
  "type": "Feature",
  "properties": {
    "iso:country":"US",
    "sg:address":"15 Locust St",
    "sg:city":"Springfield",
    "sg:classifiers":[
        {
            "category":"Restaurant",
            "type":"Food & Drink"
        }
    ],
    "sg:phone":"+1 413 746 1100",
    "sg:postcode":"01108",
    "sg:province":"MA",
    "wof:name":"South End Deli & Pasta",
    "wof:placetype":"venue"
},
  "geometry": {"coordinates":[-72.57782400000001,42.090823],"type":"Point"}
}