{
  "type": "Feature",
  "properties": {
    "iso:country":"US",
    "sg:address":"73 Baker St",
    "sg:city":"Lynn",
    "sg:classifiers":[
        {
            "category":"Health Services",
            "subcategory":"Nursing And Care Facility",
            "type":"Services"
        }
    ],
    "sg:phone":"+1 781 595 8931",
    "sg:postcode":"01902",
    "sg:province":"MA",
    "sg:tags":[
        "home",
        "skilled",
        "convalescent"
    ],
    "wof:name":"Community Rest Home Inc",
    "wof:placetype":"venue"
},
  "geometry": {"coordinates":[-70.957886,42.465576],"type":"Point"}
}