{
  "type": "Feature",
  "properties": {
    "addr:full": "6 Dickinson St Cambridge MA 02139",
    "addr:housenumber": "6",
    "addr:postcode": "02139",
    "addr:street": "Dickinson St",
    "iso:country": "US",
    "sg:address": "6 Dickinson St",
    "sg:city": "Cambridge",
    "sg:classifiers": [
      {
        "category": "Communications",
        "type": "Services"
      }
    ],
    "sg:phone": "+1 617 447 6516",
    "sg:postcode": "02139",
    "sg:province": "MA",
    "wof:name": "Axis Global Communications",
    "wof:placetype": "venue"
  },
  "geometry": {"coordinates":[-71.094451,42.366304],"type":"Point"}
}
