{
  "type": "Feature",
  "properties": {
    "iso:country":"US",
    "sg:address":"6 Dickinson St",
    "sg:city":"Cambridge",
    "sg:classifiers":[
        {
            "category":"Communications",
            "type":"Services"
        }
    ],
    "sg:phone":"+1 617 447 6516",
    "sg:postcode":"02139",
    "sg:province":"MA",
    "wof:name":"Axis Global Communications",
    "wof:placetype":"venue"
},
  "geometry": {"coordinates":[-71.09445100000001,42.366304],"type":"Point"}
}