{
  "type": "Feature",
  "properties": {
    "addr:full":"1413 Rodman St Fall River MA 02721",
    "addr:housenumber":"1413",
    "addr:postcode":"02721",
    "addr:street":"Rodman St",
    "iso:country":"US",
    "sg:address":"1413 Rodman St",
    "sg:city":"Fall River",
    "sg:classifiers":[
        {
            "category":"Personal",
            "subcategory":"Beauty Salon",
            "type":"Services"
        }
    ],
    "sg:phone":"+1 508 678 9604",
    "sg:postcode":"02721",
    "sg:province":"MA",
    "wof:name":"Club Hair Design",
    "wof:placetype":"venue"
},
  "geometry": {"coordinates":[-71.15075400000001,41.68125],"type":"Point"}
}