{
  "type": "Feature",
  "properties": {
    "iso:country":"US",
    "sg:address":"84 Huntoon Memorial Hwy",
    "sg:city":"Rochdale",
    "sg:classifiers":[
        {
            "category":"Freight",
            "type":"Transportation"
        }
    ],
    "sg:phone":"+1 508 892 9501",
    "sg:postcode":"01542",
    "sg:province":"MA",
    "sg:tags":[
        "warehouse"
    ],
    "wof:name":"Minuteman Warehouse Inc",
    "wof:placetype":"venue"
},
  "geometry": {"coordinates":[-71.90563400000001,42.208398],"type":"Point"}
}