{
  "type": "Feature",
  "properties": {
    "addr:full": "226 Mystic Ave Medford MA 02155",
    "addr:housenumber": "226",
    "addr:postcode": "02155",
    "addr:street": "Mystic Ave",
    "iso:country": "US",
    "sg:address": "226 Mystic Ave",
    "sg:city": "Medford",
    "sg:classifiers": [
      {
        "category": "Professional",
        "type": "Services"
      }
    ],
    "sg:phone": "+1 781 395 0167",
    "sg:postcode": "02155",
    "sg:province": "MA",
    "sg:tags": [
      "establishment"
    ],
    "wof:name": "Before You Move Inc",
    "wof:placetype": "venue"
  },
  "geometry": {"coordinates":[-71.102163,42.406494],"type":"Point"}
}
