{
  "type": "Feature",
  "properties": {
    "iso:country":"US",
    "sg:address":"226 Mystic Ave",
    "sg:city":"Medford",
    "sg:classifiers":[
        {
            "category":"Professional",
            "type":"Services"
        }
    ],
    "sg:phone":"+1 781 395 0167",
    "sg:postcode":"02155",
    "sg:province":"MA",
    "sg:tags":[
        "establishment"
    ],
    "wof:name":"Before You Move Inc",
    "wof:placetype":"venue"
},
  "geometry": {"coordinates":[-71.102163,42.406494],"type":"Point"}
}