{
  "type": "Feature",
  "properties": {
    "addr:full": "220 Winter St Bridgewater MA 02324",
    "addr:housenumber": "220",
    "addr:postcode": "02324",
    "addr:street": "Winter St",
    "iso:country": "US",
    "sg:address": "220 Winter St",
    "sg:city": "Bridgewater",
    "sg:classifiers": [
      {
        "category": "Coffee \u0026 Tea",
        "type": "Food \u0026 Drink"
      },
      {
        "category": "Restaurant",
        "type": "Food \u0026 Drink"
      }
    ],
    "sg:phone": "+1 508 697 3077",
    "sg:postcode": "02324",
    "sg:province": "MA",
    "sg:tags": [
      "espresso",
      "pizza"
    ],
    "sg:website": "http://www.capecodcafepizza.com",
    "wof:name": "Cape Cod Cafe Bridgewater",
    "wof:placetype": "venue"
  },
  "geometry": {"coordinates":[-70.971917,41.969082],"type":"Point"}
}
