{
  "type": "Feature",
  "properties": {
    "iso:country":"US",
    "sg:address":"180 Linden St",
    "sg:city":"Wellesley",
    "sg:classifiers":[
        {
            "category":"Professional",
            "subcategory":"Employment Agencies",
            "type":"Services"
        }
    ],
    "sg:phone":"+1 781 237 1199",
    "sg:postcode":"02482",
    "sg:province":"MA",
    "sg:tags":[
        "consultant",
        "search",
        "executive"
    ],
    "wof:name":"Sink Walker Boltrus Group",
    "wof:placetype":"venue"
},
  "geometry": {"coordinates":[-71.291538,42.300259],"type":"Point"}
}