{
  "type": "Feature",
  "properties": {
    "iso:country":"US",
    "sg:address":"8 Spring St",
    "sg:city":"Marblehead",
    "sg:classifiers":[
        {
            "category":"Personal",
            "subcategory":"Beauty Salon",
            "type":"Services"
        }
    ],
    "sg:phone":"+1 781 639 9691",
    "sg:postcode":"01945",
    "sg:province":"MA",
    "sg:tags":[
        "spa",
        "day"
    ],
    "wof:name":"LA Belle Femme",
    "wof:placetype":"venue"
},
  "geometry": {"coordinates":[-70.855993,42.503149],"type":"Point"}
}