{
  "type": "Feature",
  "properties": {
    "addr:full": "1 County Rd Mattapoisett MA 02739",
    "addr:housenumber": "1",
    "addr:postcode": "02739",
    "addr:street": "County Rd",
    "iso:country": "US",
    "sg:address": "1 County Rd",
    "sg:city": "Mattapoisett",
    "sg:classifiers": [
      {
        "category": "Professional",
        "subcategory": "Engineering",
        "type": "Services"
      }
    ],
    "sg:phone": "+1 508 758 7866",
    "sg:postcode": "02739",
    "sg:province": "MA",
    "sg:tags": [
      "engineer"
    ],
    "wof:name": "N Douglas Schneider \u0026 Assoc",
    "wof:placetype": "venue"
  },
  "geometry": {"coordinates":[-70.816578,41.662718],"type":"Point"}
}
