{
  "type": "Feature",
  "properties": {
    "addr:full":"2153 Mystic Valley Pkwy Medford MA 02155",
    "addr:housenumber":"2153",
    "addr:postcode":"02155",
    "addr:street":"Mystic Valley Pkwy",
    "iso:country":"US",
    "sg:address":"2153 Mystic Valley Pkwy",
    "sg:city":"Medford",
    "sg:classifiers":[
        {
            "category":"Food & Beverages",
            "subcategory":"Liquor & Beverages",
            "type":"Retail Goods"
        }
    ],
    "sg:phone":"+1 781 395 6200",
    "sg:postcode":"02155",
    "sg:province":"MA",
    "sg:tags":[
        "beer",
        "spirit",
        "wine"
    ],
    "wof:name":"Sav-Mor Liquors",
    "wof:placetype":"venue"
},
  "geometry": {"coordinates":[-71.127602,42.4175],"type":"Point"}
}