{
  "type": "Feature",
  "properties": {
    "addr:full":"91 N Washington St North Attleboro MA 02760",
    "addr:housenumber":"91",
    "addr:postcode":"02760",
    "addr:street":"N Washington St",
    "iso:country":"US",
    "sg:address":"91 N Washington St",
    "sg:city":"North Attleboro",
    "sg:classifiers":[
        {
            "category":"Autos & Motor Vehicles",
            "subcategory":"Auto Supplies",
            "type":"Retail Goods"
        }
    ],
    "sg:phone":"+1 508 699 4661",
    "sg:postcode":"02760",
    "sg:province":"MA",
    "sg:tags":[
        "automobile",
        "parts"
    ],
    "wof:name":"Autozone",
    "wof:placetype":"venue"
},
  "geometry": {"coordinates":[-71.332109,41.984489],"type":"Point"}
}