{
  "type": "Feature",
  "properties": {
    "iso:country":"US",
    "sg:address":"511 River Rd",
    "sg:city":"Carlisle",
    "sg:classifiers":[
        {
            "category":"Professional",
            "subcategory":"Computer Services",
            "type":"Services"
        }
    ],
    "sg:phone":"+1 978 371 7422",
    "sg:postcode":"01741",
    "sg:province":"MA",
    "sg:tags":[
        "consultant",
        "designer"
    ],
    "wof:name":"Managing Technology",
    "wof:placetype":"venue"
},
  "geometry": {"coordinates":[-71.329728,42.504082],"type":"Point"}
}