{
  "type": "Feature",
  "properties": {
    "addr:full":"907 Sumner St Stoughton MA 02072",
    "addr:housenumber":"907",
    "addr:postcode":"02072",
    "addr:street":"Sumner St",
    "iso:country":"US",
    "sg:address":"907 Sumner St",
    "sg:city":"Stoughton",
    "sg:classifiers":[
        {
            "category":"Health Services",
            "subcategory":"Doctor",
            "type":"Services"
        }
    ],
    "sg:phone":"+1 781 297 8020",
    "sg:postcode":"02072",
    "sg:province":"MA",
    "sg:tags":[
        "physician",
        "surgeon"
    ],
    "wof:name":"Tzipora Wolff MD",
    "wof:placetype":"venue"
},
  "geometry": {"coordinates":[-71.081433,42.103635],"type":"Point"}
}