{
  "type": "Feature",
  "properties": {
    "iso:country":"US",
    "sg:address":"671 Adams St",
    "sg:city":"Dorchester",
    "sg:classifiers":[
        {
            "category":"Real Estate",
            "subcategory":"Real Estate Services",
            "type":"Services"
        },
        {
            "category":"Shopping",
            "subcategory":"Antiques",
            "type":"Retail Goods"
        },
        {
            "category":"Building & Trades",
            "subcategory":"Construction",
            "type":"Services"
        }
    ],
    "sg:phone":"+1 617 825 1210",
    "sg:postcode":"02122",
    "sg:province":"MA",
    "sg:tags":[
        "contractor"
    ],
    "wof:name":"Sweeney Associates Real Estate",
    "wof:placetype":"venue"
},
  "geometry": {"coordinates":[-71.05439800000001,42.287102],"type":"Point"}
}