{
  "type": "Feature",
  "properties": {
    "addr:full": "671 Adams St Dorchester MA 02122",
    "addr:housenumber": "671",
    "addr:postcode": "02122",
    "addr:street": "Adams St",
    "iso:country": "US",
    "sg:address": "671 Adams St",
    "sg:city": "Dorchester",
    "sg:classifiers": [
      {
        "category": "Real Estate",
        "subcategory": "Real Estate Services",
        "type": "Services"
      },
      {
        "category": "Shopping",
        "subcategory": "Antiques",
        "type": "Retail Goods"
      },
      {
        "category": "Building \u0026 Trades",
        "subcategory": "Construction",
        "type": "Services"
      }
    ],
    "sg:phone": "+1 617 825 1210",
    "sg:postcode": "02122",
    "sg:province": "MA",
    "sg:tags": [
      "contractor"
    ],
    "wof:name": "Sweeney Associates Real Estate",
    "wof:placetype": "venue"
  },
  "geometry": {"coordinates":[-71.054398,42.287102],"type":"Point"}
}
