{
  "type": "Feature",
  "properties": {
    "iso:country":"US",
    "sg:address":"736 Cambridge Street",
    "sg:city":"Boston",
    "sg:classifiers":[
        {
            "category":"Health Services",
            "subcategory":"Hospital",
            "type":"Services"
        }
    ],
    "sg:phone":"+1 617 789 4207",
    "sg:postcode":"02135",
    "sg:province":"MA",
    "wof:name":"St E's Hosp",
    "wof:placetype":"venue"
},
  "geometry": {"coordinates":[-71.147783,42.350027],"type":"Point"}
}