{
  "type": "Feature",
  "properties": {
    "addr:full": "315 Shawmut Ave Boston MA 02118",
    "addr:housenumber": "315",
    "addr:postcode": "02118",
    "addr:street": "Shawmut Ave",
    "iso:country": "US",
    "sg:address": "315 Shawmut Ave",
    "sg:city": "Boston",
    "sg:classifiers": [
      {
        "category": "Restaurant",
        "type": "Food \u0026 Drink"
      }
    ],
    "sg:menulink": "http://www.allmenus.com/ma/boston/740-joe-vs/menu/",
    "sg:phone": "+1 617 338 5638",
    "sg:postcode": "02118",
    "sg:province": "MA",
    "sg:tags": [
      "italian"
    ],
    "wof:name": "Joe V's",
    "wof:placetype": "venue"
  },
  "geometry": {"coordinates":[-71.070546,42.342147],"type":"Point"}
}
