{
  "type": "Feature",
  "properties": {
    "iso:country":"US",
    "sg:address":"315 Shawmut Ave",
    "sg:city":"Boston",
    "sg:classifiers":[
        {
            "category":"Restaurant",
            "type":"Food & Drink"
        }
    ],
    "sg:menulink":"http://www.allmenus.com/ma/boston/740-joe-vs/menu/",
    "sg:phone":"+1 617 338 5638",
    "sg:postcode":"02118",
    "sg:province":"MA",
    "sg:tags":[
        "italian"
    ],
    "wof:name":"Joe V's",
    "wof:placetype":"venue"
},
  "geometry": {"coordinates":[-71.07054599999999,42.342147],"type":"Point"}
}