{
  "type": "Feature",
  "properties": {
    "iso:country":"US",
    "sg:address":"985 Pleasant St",
    "sg:city":"Bridgewater",
    "sg:classifiers":[
        {
            "category":"Restaurant",
            "type":"Food & Drink"
        }
    ],
    "sg:phone":"+1 508 697 9332",
    "sg:postcode":"02324",
    "sg:province":"MA",
    "sg:tags":[
        "pizza"
    ],
    "wof:name":"Emma's Pub & Pizza",
    "wof:placetype":"venue"
},
  "geometry": {"coordinates":[-71.006742,41.971956],"type":"Point"}
}