{
  "type": "Feature",
  "properties": {
    "addr:full": "985 Pleasant St Bridgewater MA 02324",
    "addr:housenumber": "985",
    "addr:postcode": "02324",
    "addr:street": "Pleasant St",
    "iso:country": "US",
    "sg:address": "985 Pleasant St",
    "sg:city": "Bridgewater",
    "sg:classifiers": [
      {
        "category": "Restaurant",
        "type": "Food \u0026 Drink"
      }
    ],
    "sg:phone": "+1 508 697 9332",
    "sg:postcode": "02324",
    "sg:province": "MA",
    "sg:tags": [
      "pizza"
    ],
    "wof:name": "Emma's Pub \u0026 Pizza",
    "wof:placetype": "venue"
  },
  "geometry": {"coordinates":[-71.006742,41.971956],"type":"Point"}
}
