{
  "type": "Feature",
  "properties": {
    "iso:country":"US",
    "sg:address":"240 W Water St",
    "sg:city":"Rockland",
    "sg:classifiers":[
        {
            "category":"Wholesale",
            "subcategory":"Electrical",
            "type":"Manufacturing & Wholesale Goods"
        }
    ],
    "sg:phone":"+1 781 871 4404",
    "sg:postcode":"02370",
    "sg:province":"MA",
    "sg:tags":[
        "fire",
        "alarm",
        "system"
    ],
    "wof:name":"Applied American Technologies",
    "wof:placetype":"venue"
},
  "geometry": {"coordinates":[-70.919781,42.124057],"type":"Point"}
}