{
  "type": "Feature",
  "properties": {
    "addr:full": "247 Quincy Ave Quincy MA 02169",
    "addr:housenumber": "247",
    "addr:postcode": "02169",
    "addr:street": "Quincy Ave",
    "iso:country": "US",
    "sg:address": "247 Quincy Ave",
    "sg:city": "Quincy",
    "sg:classifiers": [
      {
        "category": "Personal",
        "type": "Services"
      }
    ],
    "sg:phone": "+1 617 984 1800",
    "sg:postcode": "02169",
    "sg:province": "MA",
    "sg:tags": [
      "wear",
      "formal"
    ],
    "wof:name": "Classic Tuxedo",
    "wof:placetype": "venue"
  },
  "geometry": {"coordinates":[-70.989279,42.240884],"type":"Point"}
}
