{
  "type": "Feature",
  "properties": {
    "addr:full": "71 Washington St Nantucket MA 02554",
    "addr:housenumber": "71",
    "addr:postcode": "02554",
    "addr:street": "Washington St",
    "iso:country": "US",
    "sg:address": "71 Washington St",
    "sg:city": "Nantucket",
    "sg:classifiers": [
      {
        "category": "Education",
        "subcategory": "Special Training",
        "type": "Public Place"
      }
    ],
    "sg:phone": "+1 508 325 7323",
    "sg:postcode": "02554",
    "sg:province": "MA",
    "sg:tags": [
      "reading",
      "instruction",
      "improvement"
    ],
    "wof:name": "Nantucket Literacy Program",
    "wof:placetype": "venue"
  },
  "geometry": {"coordinates":[-70.094352,41.280027],"type":"Point"}
}
