{
  "type": "Feature",
  "properties": {
    "iso:country":"US",
    "sg:address":"91 Franklin St",
    "sg:city":"Peabody",
    "sg:classifiers":[
        {
            "category":"Autos & Motor Vehicles",
            "subcategory":"Auto Supplies",
            "type":"Retail Goods"
        }
    ],
    "sg:phone":"+1 978 977 3544",
    "sg:postcode":"01960",
    "sg:province":"MA",
    "sg:tags":[
        "wheel"
    ],
    "wof:name":"World Of Wheels",
    "wof:placetype":"venue"
},
  "geometry": {"coordinates":[-70.93454699999999,42.528386],"type":"Point"}
}