{
  "type": "Feature",
  "properties": {
    "addr:full": "2264 Main St Jefferson MA 01522",
    "addr:housenumber": "2264",
    "addr:postcode": "01522",
    "addr:street": "Main St",
    "iso:country": "US",
    "sg:address": "2264 Main St",
    "sg:city": "Jefferson",
    "sg:classifiers": [
      {
        "category": "Retail",
        "subcategory": "Repair Shop",
        "type": "Services"
      }
    ],
    "sg:phone": "+1 508 829 9500",
    "sg:postcode": "01522",
    "sg:province": "MA",
    "sg:tags": [
      "welding"
    ],
    "wof:name": "G \u0026 L Welding Inc",
    "wof:placetype": "venue"
  },
  "geometry": {"coordinates":[-71.911999,42.370054],"type":"Point"}
}
