{
  "type": "Feature",
  "properties": {
    "iso:country":"US",
    "sg:address":"12 Crispus Attucks Pl",
    "sg:city":"Roxbury",
    "sg:classifiers":[
        {
            "category":"Retail",
            "subcategory":"Laundry & Dry Cleaning",
            "type":"Services"
        },
        {
            "category":"Building & Trades",
            "subcategory":"Cleaning & Sanitation",
            "type":"Services"
        }
    ],
    "sg:phone":"+1 617 442 3675",
    "sg:postcode":"02119",
    "sg:province":"MA",
    "sg:tags":[
        "house",
        "cleaner"
    ],
    "wof:name":"5 Star Cleaning Solutions",
    "wof:placetype":"venue"
},
  "geometry": {"coordinates":[-71.088053,42.325119],"type":"Point"}
}