{
  "type": "Feature",
  "properties": {
    "addr:full": "12 Crispus Attucks Pl Roxbury MA 02119",
    "addr:housenumber": "12",
    "addr:postcode": "02119",
    "addr:street": "Crispus Attucks Pl",
    "iso:country": "US",
    "sg:address": "12 Crispus Attucks Pl",
    "sg:city": "Roxbury",
    "sg:classifiers": [
      {
        "category": "Retail",
        "subcategory": "Laundry \u0026 Dry Cleaning",
        "type": "Services"
      },
      {
        "category": "Building \u0026 Trades",
        "subcategory": "Cleaning \u0026 Sanitation",
        "type": "Services"
      }
    ],
    "sg:phone": "+1 617 442 3675",
    "sg:postcode": "02119",
    "sg:province": "MA",
    "sg:tags": [
      "house",
      "cleaner"
    ],
    "wof:name": "5 Star Cleaning Solutions",
    "wof:placetype": "venue"
  },
  "geometry": {"coordinates":[-71.088053,42.325119],"type":"Point"}
}
