{
  "type": "Feature",
  "properties": {
    "iso:country":"US",
    "sg:address":"2256 Dorchester Ave",
    "sg:city":"Dorchester Ctr",
    "sg:classifiers":[
        {
            "category":"Personal",
            "subcategory":"Beauty Salon",
            "type":"Services"
        }
    ],
    "sg:phone":"+1 617 296 1172",
    "sg:postcode":"02124",
    "sg:province":"MA",
    "sg:tags":[
        "manicuring"
    ],
    "wof:name":"Daisy's Nail",
    "wof:placetype":"venue"
},
  "geometry": {"coordinates":[-71.067896,42.272603],"type":"Point"}
}