{
  "type": "Feature",
  "properties": {
    "addr:full":"20 Woodland Rd Wellesley MA 02481",
    "addr:housenumber":"20",
    "addr:postcode":"02481",
    "addr:street":"Woodland Rd",
    "iso:country":"US",
    "sg:address":"20 Woodland Rd",
    "sg:city":"Wellesley",
    "sg:classifiers":[
        {
            "category":"Professional",
            "subcategory":"Management & Consulting",
            "type":"Services"
        }
    ],
    "sg:phone":"+1   ",
    "sg:postcode":"02481",
    "sg:province":"MA",
    "sg:tags":[
        "business"
    ],
    "wof:name":"Thieme Consulting Inc",
    "wof:placetype":"venue"
},
  "geometry": {"coordinates":[-71.312241,42.311443],"type":"Point"}
}