{
  "type": "Feature",
  "properties": {
    "iso:country":"US",
    "sg:address":"340 Main Street",
    "sg:city":"Melrose",
    "sg:classifiers":[
        {
            "category":"Professional",
            "subcategory":"Lawyer & Legal Services",
            "type":"Services"
        }
    ],
    "sg:phone":"+1 781 662 8102",
    "sg:postcode":"02176",
    "sg:province":"MA",
    "wof:name":"Cefalo Frederick Law Office of",
    "wof:placetype":"venue"
},
  "geometry": {"coordinates":[-71.067161,42.452012],"type":"Point"}
}