{
  "type": "Feature",
  "properties": {
    "iso:country":"US",
    "sg:address":"25 Drydock Ave 5th Fl",
    "sg:city":"Boston",
    "sg:classifiers":[
        {
            "category":"Building & Trades",
            "subcategory":"Construction",
            "type":"Services"
        }
    ],
    "sg:phone":"+1 866 867 8729",
    "sg:postcode":"02210",
    "sg:province":"MA",
    "sg:tags":[
        "contractor"
    ],
    "sg:website":"nextsteplivinginc.com/",
    "wof:name":"Next Step Living, Inc",
    "wof:placetype":"venue"
},
  "geometry": {"coordinates":[-71.029934,42.344736],"type":"Point"}
}