{
  "type": "Feature",
  "properties": {
    "iso:country":"US",
    "sg:address":"1592 Hancock St",
    "sg:city":"Quincy",
    "sg:classifiers":[
        {
            "category":"Shopping",
            "type":"Retail Goods"
        }
    ],
    "sg:phone":"+1 617 479 4352",
    "sg:postcode":"02169",
    "sg:province":"MA",
    "sg:tags":[
        "picture",
        "frame"
    ],
    "wof:name":"Frantic Framers",
    "wof:placetype":"venue"
},
  "geometry": {"coordinates":[-71.000371,42.245957],"type":"Point"}
}