{
  "type": "Feature",
  "properties": {
    "iso:country":"US",
    "sg:address":"135 Cornet Stetson Rd",
    "sg:city":"Scituate",
    "sg:classifiers":[
        {
            "category":"Food & Beverages",
            "subcategory":"Fruits & Vegetables",
            "type":"Retail Goods"
        }
    ],
    "sg:phone":"+1 781 545 7750",
    "sg:postcode":"02066",
    "sg:province":"MA",
    "sg:tags":[
        "produce"
    ],
    "wof:name":"Tree Berry Farm",
    "wof:placetype":"venue"
},
  "geometry": {"coordinates":[-70.754266,42.174646],"type":"Point"}
}