{
  "type": "Feature",
  "properties": {
    "addr:full":"832 N Main St Leominster MA 01453",
    "addr:housenumber":"832",
    "addr:postcode":"01453",
    "addr:street":"N Main St",
    "iso:country":"US",
    "sg:address":"832 N Main St",
    "sg:city":"Leominster",
    "sg:classifiers":[
        {
            "category":"Autos & Motor Vehicles",
            "subcategory":"Automobile Sales",
            "type":"Retail Goods"
        }
    ],
    "sg:phone":"+1 978 537 8545",
    "sg:postcode":"01453",
    "sg:province":"MA",
    "sg:tags":[
        "new",
        "used",
        "truck",
        "car"
    ],
    "sg:website":"http://www.rickstarrford.com",
    "wof:name":"Rick Starr Ford",
    "wof:placetype":"venue"
},
  "geometry": {"coordinates":[-71.771855,42.557347],"type":"Point"}
}