{
  "type": "Feature",
  "properties": {
    "iso:country":"US",
    "sg:address":"643 River St",
    "sg:city":"Mattapan",
    "sg:classifiers":[
        {
            "category":"Restaurant",
            "type":"Food & Drink"
        }
    ],
    "sg:phone":"+1 617 298 9797",
    "sg:postcode":"02126",
    "sg:province":"MA",
    "wof:name":"Privileje Restaurant",
    "wof:placetype":"venue"
},
  "geometry": {"coordinates":[-71.099476,42.265077],"type":"Point"}
}