{
  "type": "Feature",
  "properties": {
    "addr:full": "4 Howard St Brookfield MA 01506",
    "addr:housenumber": "4",
    "addr:postcode": "01506",
    "addr:street": "Howard St",
    "iso:country": "US",
    "sg:address": "4 Howard St",
    "sg:city": "Brookfield",
    "sg:classifiers": [
      {
        "category": "Organizations",
        "subcategory": "Religious Organization",
        "type": "Services"
      }
    ],
    "sg:phone": "+1 508 867 3188",
    "sg:postcode": "01506",
    "sg:province": "MA",
    "sg:tags": [
      "church"
    ],
    "wof:name": "St Mary's Rectory",
    "wof:placetype": "venue"
  },
  "geometry": {"coordinates":[-72.10143,42.213334],"type":"Point"}
}
