{
  "type": "Feature",
  "properties": {
    "iso:country":"US",
    "sg:address":"548 Haydenville Rd",
    "sg:city":"Leeds",
    "sg:classifiers":[
        {
            "category":"Utilities",
            "subcategory":"Electric",
            "type":"Services"
        }
    ],
    "sg:phone":"+1 413 582 7200",
    "sg:postcode":"01053",
    "sg:province":"MA",
    "sg:tags":[
        "company"
    ],
    "wof:name":"Massachusetts Electric Co",
    "wof:placetype":"venue"
},
  "geometry": {"coordinates":[-72.69407699999999,42.364303],"type":"Point"}
}