{
  "type": "Feature",
  "properties": {
    "iso:country":"US",
    "sg:address":"36 Margaret St",
    "sg:city":"Springfield",
    "sg:classifiers":[
        {
            "category":"Education",
            "subcategory":"School",
            "type":"Public Place"
        }
    ],
    "sg:phone":"+1 413 739 3616",
    "sg:postcode":"01105",
    "sg:province":"MA",
    "wof:name":"Mt Carmel School",
    "wof:placetype":"venue"
},
  "geometry": {"coordinates":[-72.584169,42.096333],"type":"Point"}
}