{
  "type": "Feature",
  "properties": {
    "iso:country":"US",
    "sg:address":"38 Russell Rd",
    "sg:city":"Huntington",
    "sg:classifiers":[
        {
            "category":"Autos & Motor Vehicles",
            "subcategory":"Motorcycle Sales",
            "type":"Retail Goods"
        }
    ],
    "sg:phone":"+1 413 667 5575",
    "sg:postcode":"01050",
    "sg:province":"MA",
    "sg:tags":[
        "all",
        "terrain"
    ],
    "wof:name":"Smith's Sled Shop Inc",
    "wof:placetype":"venue"
},
  "geometry": {"coordinates":[-72.870734,42.224849],"type":"Point"}
}