{
  "type": "Feature",
  "properties": {
    "addr:full": "44 School St Boston MA 02108",
    "addr:housenumber": "44",
    "addr:postcode": "02108",
    "addr:street": "School St",
    "iso:country": "US",
    "sg:address": "44 School St",
    "sg:city": "Boston",
    "sg:classifiers": [
      {
        "category": "Real Estate",
        "subcategory": "Real Estate Agent",
        "type": "Services"
      }
    ],
    "sg:phone": "+1 617 367 0050",
    "sg:postcode": "02108",
    "sg:province": "MA",
    "wof:name": "Real Estate Boston",
    "wof:placetype": "venue"
  },
  "geometry": {"coordinates":[-71.059349,42.357689],"type":"Point"}
}
