{
  "type": "Feature",
  "properties": {
    "addr:full":"30 Hewlett St Roslindale MA 02131",
    "addr:housenumber":"30",
    "addr:postcode":"02131",
    "addr:street":"Hewlett St",
    "iso:country":"US",
    "sg:address":"30 Hewlett St",
    "sg:city":"Roslindale",
    "sg:classifiers":[
        {
            "category":"Shopping",
            "subcategory":"Jewelry",
            "type":"Retail Goods"
        }
    ],
    "sg:phone":"+1   ",
    "sg:postcode":"02131",
    "sg:province":"MA",
    "wof:name":"Purple Lightning Jewelry",
    "wof:placetype":"venue"
},
  "geometry": {"coordinates":[-71.13507300000001,42.289862],"type":"Point"}
}