{
  "type": "Feature",
  "properties": {
    "iso:country":"US",
    "sg:address":"178 North Ave",
    "sg:city":"Abington",
    "sg:classifiers":[
        {
            "category":"Building & Trades",
            "subcategory":"Construction",
            "type":"Services"
        }
    ],
    "sg:phone":"+1 781 871 5375",
    "sg:postcode":"02351",
    "sg:province":"MA",
    "sg:tags":[
        "handyman"
    ],
    "wof:name":"Acr Appliance Repair",
    "wof:placetype":"venue"
},
  "geometry": {"coordinates":[-70.94286,42.127998],"type":"Point"}
}