{
  "type": "Feature",
  "properties": {
    "addr:full": "349 Main St Winchendon MA 01475",
    "addr:housenumber": "349",
    "addr:postcode": "01475",
    "addr:street": "Main St",
    "iso:country": "US",
    "sg:address": "349 Main St",
    "sg:city": "Winchendon",
    "sg:classifiers": [
      {
        "category": "Personal",
        "subcategory": "Beauty Salon",
        "type": "Services"
      }
    ],
    "sg:phone": "+1 978 297 1171",
    "sg:postcode": "01475",
    "sg:province": "MA",
    "wof:name": "Back Street Salon",
    "wof:placetype": "venue"
  },
  "geometry": {"coordinates":[-72.085023,42.661329],"type":"Point"}
}
