{
  "type": "Feature",
  "properties": {
    "iso:country":"US",
    "sg:address":"182 Adams Rd",
    "sg:city":"Williamstown",
    "sg:classifiers":[
        {
            "category":"Health Services",
            "subcategory":"Doctor",
            "type":"Services"
        }
    ],
    "sg:phone":"+1 413 458 4238",
    "sg:postcode":"01267",
    "sg:province":"MA",
    "sg:tags":[
        "dentist"
    ],
    "wof:name":"Family & Prosthetic Dentistry",
    "wof:placetype":"venue"
},
  "geometry": {"coordinates":[-73.188734,42.703526],"type":"Point"}
}