{
  "type": "Feature",
  "properties": {
    "addr:full": "182 Adams Rd Williamstown MA 01267",
    "addr:housenumber": "182",
    "addr:postcode": "01267",
    "addr:street": "Adams Rd",
    "iso:country": "US",
    "sg:address": "182 Adams Rd",
    "sg:city": "Williamstown",
    "sg:classifiers": [
      {
        "category": "Health Services",
        "subcategory": "Doctor",
        "type": "Services"
      }
    ],
    "sg:phone": "+1 413 458 4238",
    "sg:postcode": "01267",
    "sg:province": "MA",
    "sg:tags": [
      "dentist"
    ],
    "wof:name": "Family \u0026 Prosthetic Dentistry",
    "wof:placetype": "venue"
  },
  "geometry": {"coordinates":[-73.188734,42.703526],"type":"Point"}
}
