{
  "type": "Feature",
  "properties": {
    "iso:country":"US",
    "sg:address":"250 Copeland St",
    "sg:city":"Quincy",
    "sg:classifiers":[
        {
            "category":"Health Services",
            "subcategory":"Chiropractor",
            "type":"Services"
        }
    ],
    "sg:phone":"+1 617 328 0839",
    "sg:postcode":"02169",
    "sg:province":"MA",
    "sg:tags":[
        "chiropractic"
    ],
    "wof:name":"Brown Family Chiropractic",
    "wof:placetype":"venue"
},
  "geometry": {"coordinates":[-71.025959,42.244755],"type":"Point"}
}