{
  "type": "Feature",
  "properties": {
    "iso:country":"US",
    "sg:address":"12 Sevinor Rd",
    "sg:city":"Marblehead",
    "sg:classifiers":[
        {
            "category":"Retail",
            "subcategory":"Repair Shop",
            "type":"Services"
        }
    ],
    "sg:phone":"+1 781 639 9090",
    "sg:postcode":"01945",
    "sg:province":"MA",
    "sg:tags":[
        "repairing",
        "piano",
        "refinishing"
    ],
    "wof:name":"Paul N Ouellette & Sons",
    "wof:placetype":"venue"
},
  "geometry": {"coordinates":[-70.876482,42.490087],"type":"Point"}
}