{
  "type": "Feature",
  "properties": {
    "addr:full":"390 Oak St East Bridgewater MA 02333",
    "addr:housenumber":"390",
    "addr:postcode":"02333",
    "addr:street":"Oak St",
    "iso:country":"US",
    "sg:address":"390 Oak St",
    "sg:city":"East Bridgewater",
    "sg:classifiers":[
        {
            "category":"Restaurant",
            "type":"Food & Drink"
        }
    ],
    "sg:phone":"+1 781 447 4032",
    "sg:postcode":"02333",
    "sg:province":"MA",
    "sg:tags":[
        "barbecue"
    ],
    "wof:name":"Leighton's Clambakes & Bbq",
    "wof:placetype":"venue"
},
  "geometry": {"coordinates":[-70.908907,42.05657],"type":"Point"}
}