{
  "type": "Feature",
  "properties": {
    "iso:country":"US",
    "sg:address":"50 Billerica Rd",
    "sg:city":"Chelmsford",
    "sg:classifiers":[
        {
            "category":"Government",
            "subcategory":"Office",
            "type":"Public Place"
        }
    ],
    "sg:phone":"+1 978 250 5280",
    "sg:postcode":"01824",
    "sg:province":"MA",
    "sg:tags":[
        "civil",
        "defense",
        "agency"
    ],
    "wof:name":"Chelmsford Civil Defense",
    "wof:placetype":"venue"
},
  "geometry": {"coordinates":[-71.346502,42.598373],"type":"Point"}
}