{
  "type": "Feature",
  "properties": {
    "iso:country":"US",
    "sg:address":"34 Glenview Dr",
    "sg:city":"Harvard",
    "sg:classifiers":[
        {
            "category":"Utilities",
            "subcategory":"Telephone",
            "type":"Services"
        },
        {
            "category":"Professional",
            "subcategory":"Business Services",
            "type":"Services"
        }
    ],
    "sg:phone":"+1 978 772 9600",
    "sg:postcode":"01451",
    "sg:province":"MA",
    "sg:tags":[
        "communications",
        "telemarketing"
    ],
    "sg:website":"www.itsyourcall.com",
    "wof:name":"It's Your Call",
    "wof:placetype":"venue"
},
  "geometry": {"coordinates":[-71.568922,42.533508],"type":"Point"}
}