{
  "type": "Feature",
  "properties": {
    "addr:full":"141 Village St Medway MA 02053",
    "addr:housenumber":"141",
    "addr:postcode":"02053",
    "addr:street":"Village St",
    "iso:country":"US",
    "sg:address":"141 Village St",
    "sg:city":"Medway",
    "sg:classifiers":[
        {
            "category":"Shopping",
            "subcategory":"Discount & Variety Stores",
            "type":"Retail Goods"
        }
    ],
    "sg:phone":"+1 508 533 4437",
    "sg:postcode":"02053",
    "sg:province":"MA",
    "wof:name":"Medway Mart",
    "wof:placetype":"venue"
},
  "geometry": {"coordinates":[-71.39650899999999,42.140119],"type":"Point"}
}