{
  "type": "Feature",
  "properties": {
    "addr:full": "983 Providence Highway Dedham MA 02026",
    "addr:housenumber": "983",
    "addr:postcode": "02026",
    "addr:street": "Providence Highway",
    "iso:country": "US",
    "sg:address": "983 Providence Highway",
    "sg:city": "Dedham",
    "sg:classifiers": [
      {
        "category": "Retail",
        "subcategory": "Portrait Studio",
        "type": "Services"
      },
      {
        "category": "Shopping",
        "subcategory": "Pharmacy",
        "type": "Retail Goods"
      }
    ],
    "sg:phone": "+1 781 251 0565",
    "sg:postcode": "02026",
    "sg:province": "MA",
    "sg:tags": [
      "photography",
      "drugstore",
      "store"
    ],
    "sg:website": "www.walgreens.com",
    "wof:name": "Walgreens",
    "wof:placetype": "venue"
  },
  "geometry": {"coordinates":[-71.180646,42.231634],"type":"Point"}
}
