{
  "type": "Feature",
  "properties": {
    "addr:full":"160 Beaver St Milford MA 01757",
    "addr:housenumber":"160",
    "addr:postcode":"01757",
    "addr:street":"Beaver St",
    "iso:country":"US",
    "sg:address":"160 Beaver St",
    "sg:city":"Milford",
    "sg:classifiers":[
        {
            "category":"Home & Garden",
            "subcategory":"Building Materials",
            "type":"Retail Goods"
        }
    ],
    "sg:phone":"+1 508 634 8588",
    "sg:postcode":"01757",
    "sg:province":"MA",
    "sg:tags":[
        "concrete",
        "reinforcement"
    ],
    "wof:name":"Precision Motor Sports",
    "wof:placetype":"venue"
},
  "geometry": {"coordinates":[-71.49400300000001,42.126403],"type":"Point"}
}