{
  "type": "Feature",
  "properties": {
    "iso:country":"US",
    "sg:address":"55 Spring St",
    "sg:city":"Williamstown",
    "sg:classifiers":[
        {
            "category":"Cinema",
            "subcategory":"Movie Theater",
            "type":"Entertainment"
        }
    ],
    "sg:phone":"+1 413 458 9700",
    "sg:postcode":"01267",
    "sg:province":"MA",
    "sg:website":"www.williamstownfilmfest.com",
    "wof:name":"Williamstown Film Festival",
    "wof:placetype":"venue"
},
  "geometry": {"coordinates":[-73.20426399999999,42.7106],"type":"Point"}
}