{
  "type": "Feature",
  "properties": {
    "addr:full": "1245 Commonwealth Avenue Boston MA 02134",
    "addr:housenumber": "1245",
    "addr:postcode": "02134",
    "addr:street": "Commonwealth Avenue",
    "iso:country": "US",
    "sg:address": "1245 Commonwealth Avenue",
    "sg:city": "Boston",
    "sg:classifiers": [
      {
        "category": "Restaurant",
        "type": "Food \u0026 Drink"
      }
    ],
    "sg:menulink": "http://www.allmenus.com/ma/boston/258951-1-sushi-express/menu/",
    "sg:phone": "+1 617 871 1144",
    "sg:postcode": "02134",
    "sg:province": "MA",
    "sg:tags": [
      "sushi",
      "japanese",
      "asian"
    ],
    "wof:name": "$1 Sushi Express",
    "wof:placetype": "venue"
  },
  "geometry": {"coordinates":[-71.131796,42.350154],"type":"Point"}
}
