{
  "type": "Feature",
  "properties": {
    "addr:full":"393 New Ludlow Rd Chicopee MA 01020",
    "addr:housenumber":"393",
    "addr:postcode":"01020",
    "addr:street":"New Ludlow Rd",
    "iso:country":"US",
    "sg:address":"393 New Ludlow Rd",
    "sg:city":"Chicopee",
    "sg:classifiers":[
        {
            "category":"Retail",
            "subcategory":"Auto Repair",
            "type":"Services"
        }
    ],
    "sg:phone":"+1 413 536 3906",
    "sg:postcode":"01020",
    "sg:province":"MA",
    "sg:tags":[
        "body",
        "automobile",
        "painting"
    ],
    "wof:name":"DMS Auto Body",
    "wof:placetype":"venue"
},
  "geometry": {"coordinates":[-72.56532799999999,42.212838],"type":"Point"}
}