{
  "type": "Feature",
  "properties": {
    "addr:full":"181 Park Ave West Springfield MA 01089",
    "addr:housenumber":"181",
    "addr:postcode":"01089",
    "addr:street":"Park Ave",
    "iso:country":"US",
    "sg:address":"181 Park Ave",
    "sg:city":"West Springfield",
    "sg:classifiers":[
        {
            "category":"Personal",
            "type":"Services"
        }
    ],
    "sg:phone":"+1 413 736 4257",
    "sg:postcode":"01089",
    "sg:province":"MA",
    "sg:tags":[
        "color",
        "consultant"
    ],
    "wof:name":"Coloright Doncaster By Corinne",
    "wof:placetype":"venue"
},
  "geometry": {"coordinates":[-72.62081999999999,42.104667],"type":"Point"}
}