{
  "type": "Feature",
  "properties": {
    "addr:full":"7 Hampton Ct East Walpole MA 02032",
    "addr:housenumber":"7",
    "addr:postcode":"02032",
    "addr:street":"Hampton Ct",
    "iso:country":"US",
    "sg:address":"7 Hampton Ct",
    "sg:city":"East Walpole",
    "sg:classifiers":[
        {
            "category":"Building & Trades",
            "subcategory":"Electrical",
            "type":"Services"
        }
    ],
    "sg:phone":"+1 508 660 2100",
    "sg:postcode":"02032",
    "sg:province":"MA",
    "wof:name":"New Boston Telephone Co",
    "wof:placetype":"venue"
},
  "geometry": {"coordinates":[-71.220429,42.149346],"type":"Point"}
}