{
  "type": "Feature",
  "properties": {
    "iso:country":"US",
    "sg:address":"278 S Broadway",
    "sg:city":"Lawrence",
    "sg:classifiers":[
        {
            "category":"Retail",
            "subcategory":"Auto Repair",
            "type":"Services"
        }
    ],
    "sg:phone":"+1 978 686 9156",
    "sg:postcode":"01843",
    "sg:province":"MA",
    "sg:tags":[
        "repairing",
        "automobile"
    ],
    "wof:name":"Ken's Auto Repair",
    "wof:placetype":"venue"
},
  "geometry": {"coordinates":[-71.160298,42.691806],"type":"Point"}
}