{
  "type": "Feature",
  "properties": {
    "addr:full": "72 Cambridge St Worcester MA 01603",
    "addr:housenumber": "72",
    "addr:postcode": "01603",
    "addr:street": "Cambridge St",
    "iso:country": "US",
    "ovtr:label": "The Salvation Army, 72 Cambridge St Worcester MA US",
    "ovtr:similarity": 3.6923201084136963,
    "sg:address": "72 Cambridge St",
    "sg:city": "Worcester",
    "sg:classifiers": [
      {
        "category": "Social Services",
        "type": "Services"
      }
    ],
    "sg:phone": "+1 508 799 0528",
    "sg:postcode": "01603",
    "sg:province": "MA",
    "sg:tags": [
      "organization",
      "welfare"
    ],
    "wof:name": "Salvation Army",
    "wof:placetype": "venue"
  },
  "geometry": {"coordinates":[-71.82733,42.243763],"type":"Point"}
}
