{
  "type": "Feature",
  "properties": {
    "addr:full": "60 Spring St Essex MA 01929",
    "addr:housenumber": "60",
    "addr:postcode": "01929",
    "addr:street": "Spring St",
    "iso:country": "US",
    "sg:address": "60 Spring St",
    "sg:city": "Essex",
    "sg:classifiers": [
      {
        "category": "Museum",
        "type": "Entertainment"
      }
    ],
    "sg:phone": "+1 978 768 3632",
    "sg:postcode": "01929",
    "sg:province": "MA",
    "wof:name": "Grant Cogwells",
    "wof:placetype": "venue"
  },
  "geometry": {"coordinates":[-70.775083,42.638637],"type":"Point"}
}
