{
  "type": "Feature",
  "properties": {
    "addr:full": "2 Executive Dr Chelmsford MA 01824",
    "addr:housenumber": "2",
    "addr:postcode": "01824",
    "addr:street": "Executive Dr",
    "iso:country": "US",
    "sg:address": "2 Executive Dr",
    "sg:city": "Chelmsford",
    "sg:classifiers": [
      {
        "category": "Professional",
        "subcategory": "Management \u0026 Consulting",
        "type": "Services"
      }
    ],
    "sg:phone": "+1 978 441 9500",
    "sg:postcode": "01824",
    "sg:province": "MA",
    "sg:tags": [
      "consultant",
      "automation"
    ],
    "sg:website": "www.rockwellautomation.com",
    "wof:name": "Rockwell Automation",
    "wof:placetype": "venue"
  },
  "geometry": {"coordinates":[-71.317869,42.610828],"type":"Point"}
}
