{
  "type": "Feature",
  "properties": {
    "addr:full":"210 Lincoln Street Ofc Boston MA 02111",
    "addr:housenumber":"210",
    "addr:postcode":"02111",
    "addr:street":"Lincoln Street",
    "iso:country":"US",
    "sg:address":"210 Lincoln Street Ofc",
    "sg:city":"Boston",
    "sg:classifiers":[
        {
            "category":"Professional",
            "subcategory":"Lawyer & Legal Services",
            "type":"Services"
        }
    ],
    "sg:phone":"+1 617 542 1787",
    "sg:postcode":"02111",
    "sg:province":"MA",
    "wof:name":"Swartz Mark A",
    "wof:placetype":"venue"
},
  "geometry": {"coordinates":[-71.058667,42.350575],"type":"Point"}
}