{
  "type": "Feature",
  "properties": {
    "addr:full": "651 Warren St Dorchester MA 02121",
    "addr:housenumber": "651",
    "addr:postcode": "02121",
    "addr:street": "Warren St",
    "iso:country": "US",
    "sg:address": "651 Warren St",
    "sg:city": "Dorchester",
    "sg:classifiers": [
      {
        "category": "Shopping",
        "subcategory": "Mobile Phones",
        "type": "Retail Goods"
      }
    ],
    "sg:phone": "+1 617 442 0021",
    "sg:postcode": "02121",
    "sg:province": "MA",
    "wof:name": "K \u0026 E Wireless",
    "wof:placetype": "venue"
  },
  "geometry": {"coordinates":[-71.083252,42.310207],"type":"Point"}
}
