{
  "type": "Feature",
  "properties": {
    "addr:full":"1736 Massachusetts Avenue Lexington MA 02420",
    "addr:housenumber":"1736",
    "addr:postcode":"02420",
    "addr:street":"Massachusetts Avenue",
    "iso:country":"US",
    "sg:address":"1736 Massachusetts Avenue",
    "sg:city":"Lexington",
    "sg:classifiers":[
        {
            "category":"Bakery",
            "type":"Food & Drink"
        }
    ],
    "sg:phone":"+1 781 861 9990",
    "sg:postcode":"02420",
    "sg:province":"MA",
    "wof:name":"Great Harvest Bread Company",
    "wof:placetype":"venue"
},
  "geometry": {"coordinates":[-71.226827,42.447326],"type":"Point"}
}