{
  "type": "Feature",
  "properties": {
    "iso:country":"US",
    "sg:address":"240 Pearl Street Ofc",
    "sg:city":"Somerville",
    "sg:classifiers":[
        {
            "category":"Real Estate",
            "subcategory":"Real Estate Operator",
            "type":"Services"
        }
    ],
    "sg:phone":"+1 617 625 8780",
    "sg:postcode":"02145",
    "sg:province":"MA",
    "sg:tags":[
        "apartment"
    ],
    "wof:name":"Pearl St Park",
    "wof:placetype":"venue"
},
  "geometry": {"coordinates":[-71.09476100000001,42.38782],"type":"Point"}
}