{
  "type": "Feature",
  "properties": {
    "addr:full":"38 E Main St Ayer MA 01432",
    "addr:housenumber":"38",
    "addr:postcode":"01432",
    "addr:street":"E Main St",
    "iso:country":"US",
    "sg:address":"38 E Main St",
    "sg:city":"Ayer",
    "sg:classifiers":[
        {
            "category":"Wholesale",
            "subcategory":"Computers",
            "type":"Manufacturing & Wholesale Goods"
        }
    ],
    "sg:phone":"+1 978 772 1000",
    "sg:postcode":"01432",
    "sg:province":"MA",
    "wof:name":"Computer Communications Group",
    "wof:placetype":"venue"
},
  "geometry": {"coordinates":[-71.58226500000001,42.557195],"type":"Point"}
}