{
  "type": "Feature",
  "properties": {
    "addr:full": "Eleven Beacon Street Suite 625 Boston MA 02108",
    "addr:postcode": "02108",
    "addr:street": "Beacon Street Suite 625",
    "iso:country": "US",
    "sg:address": "Eleven Beacon Street Suite 625",
    "sg:city": "Boston",
    "sg:classifiers": [
      {
        "category": "Professional",
        "subcategory": "Lawyer \u0026 Legal Services",
        "type": "Services"
      }
    ],
    "sg:phone": "+1 617 830 1389",
    "sg:postcode": "02108",
    "sg:province": "MA",
    "sg:tags": [
      "attorney",
      "law",
      "bankruptcy"
    ],
    "wof:name": "Law Offices of Richard N. Gottlieb",
    "wof:placetype": "venue"
  },
  "geometry": {"coordinates":[-71.061422,42.358226],"type":"Point"}
}
