{
  "type": "Feature",
  "properties": {
    "addr:full": "1325 Main St Tewksbury MA 01876",
    "addr:housenumber": "1325",
    "addr:postcode": "01876",
    "addr:street": "Main St",
    "iso:country": "US",
    "sg:address": "1325 Main St",
    "sg:city": "Tewksbury",
    "sg:classifiers": [
      {
        "category": "Wholesale",
        "subcategory": "Non-durable Goods",
        "type": "Manufacturing \u0026 Wholesale Goods"
      }
    ],
    "sg:phone": "+1 978 851 9900",
    "sg:postcode": "01876",
    "sg:province": "MA",
    "sg:tags": [
      "merchandise",
      "general"
    ],
    "wof:name": "Preferred Distributors",
    "wof:placetype": "venue"
  },
  "geometry": {"coordinates":[-71.222831,42.602253],"type":"Point"}
}
