{
  "type": "Feature",
  "properties": {
    "addr:full":"111 Magazine St Cambridge MA 02139",
    "addr:housenumber":"111",
    "addr:postcode":"02139",
    "addr:street":"Magazine St",
    "iso:country":"US",
    "sg:address":"111 Magazine St",
    "sg:city":"Cambridge",
    "sg:classifiers":[
        {
            "category":"Professional",
            "subcategory":"Art Services",
            "type":"Services"
        }
    ],
    "sg:phone":"+1   ",
    "sg:postcode":"02139",
    "sg:province":"MA",
    "sg:tags":[
        "commercial",
        "design"
    ],
    "wof:name":"Dennis Toohey Graphics",
    "wof:placetype":"venue"
},
  "geometry": {"coordinates":[-71.109816,42.360264],"type":"Point"}
}