{
  "type": "Feature",
  "properties": {
    "addr:full":"222 Vale St Fall River MA 02724",
    "addr:housenumber":"222",
    "addr:postcode":"02724",
    "addr:street":"Vale St",
    "iso:country":"US",
    "sg:address":"222 Vale St",
    "sg:city":"Fall River",
    "sg:classifiers":[
        {
            "category":"Building & Trades",
            "subcategory":"Construction",
            "type":"Services"
        }
    ],
    "sg:phone":"+1 508 674 8343",
    "sg:postcode":"02724",
    "sg:province":"MA",
    "sg:tags":[
        "roofing",
        "contractor"
    ],
    "wof:name":"Mc Nulty Home Improvement Inc",
    "wof:placetype":"venue"
},
  "geometry": {"coordinates":[-71.165587,41.684036],"type":"Point"}
}