{
  "type": "Feature",
  "properties": {
    "addr:full": "16 Forest Ave Plymouth MA 02360",
    "addr:housenumber": "16",
    "addr:postcode": "02360",
    "addr:street": "Forest Ave",
    "iso:country": "US",
    "sg:address": "16 Forest Ave",
    "sg:city": "Plymouth",
    "sg:classifiers": [
      {
        "category": "Social Services",
        "type": "Services"
      }
    ],
    "sg:phone": "+1 508 746 7992",
    "sg:postcode": "02360",
    "sg:province": "MA",
    "sg:tags": [
      "organization",
      "welfare"
    ],
    "wof:name": "Baird Center Group Home",
    "wof:placetype": "venue"
  },
  "geometry": {"coordinates":[-70.692398,41.978852],"type":"Point"}
}
