{
  "type": "Feature",
  "properties": {
    "addr:full": "206 Clarendon St Boston MA 02116",
    "addr:housenumber": "206",
    "addr:postcode": "02116",
    "addr:street": "Clarendon St",
    "iso:country": "US",
    "sg:address": "206 Clarendon St",
    "sg:city": "Boston",
    "sg:classifiers": [
      {
        "category": "Shopping",
        "subcategory": "Books",
        "type": "Retail Goods"
      }
    ],
    "sg:phone": "+1 617 927 0038",
    "sg:postcode": "02116",
    "sg:province": "MA",
    "sg:tags": [
      "religious"
    ],
    "sg:website": "www.trinitychurchboston.org",
    "wof:name": "Trinity Church Book Store",
    "wof:placetype": "venue"
  },
  "geometry": {"coordinates":[-71.075104,42.349998],"type":"Point"}
}
