{
  "type": "Feature",
  "properties": {
    "iso:country":"US",
    "sg:address":"32 Claflin St",
    "sg:city":"Milford",
    "sg:classifiers":[
        {
            "category":"Professional",
            "subcategory":"Business Services",
            "type":"Services"
        }
    ],
    "sg:phone":"+1   ",
    "sg:postcode":"01757",
    "sg:province":"MA",
    "wof:name":"Bjb Associates of Milford Inc",
    "wof:placetype":"venue"
},
  "geometry": {"coordinates":[-71.51745099999999,42.136857],"type":"Point"}
}