{
  "type": "Feature",
  "properties": {
    "addr:full": "150 State Hwy 28 West Dennis MA 02670",
    "addr:housenumber": "150",
    "addr:postcode": "02670",
    "addr:street": "State Hwy 28",
    "iso:country": "US",
    "sg:address": "150 State Hwy 28",
    "sg:city": "West Dennis",
    "sg:classifiers": [
      {
        "category": "Social Services",
        "type": "Services"
      }
    ],
    "sg:phone": "+1 508 394 5600",
    "sg:postcode": "02670",
    "sg:province": "MA",
    "sg:tags": [
      "organization",
      "welfare"
    ],
    "wof:name": "Cape Cod Property Owners",
    "wof:placetype": "venue"
  },
  "geometry": {"coordinates":[-70.175554,41.664478],"type":"Point"}
}
