{
  "type": "Feature",
  "properties": {
    "iso:country":"US",
    "sg:address":"150 State Hwy 28",
    "sg:city":"West Dennis",
    "sg:classifiers":[
        {
            "category":"Social Services",
            "type":"Services"
        }
    ],
    "sg:phone":"+1 508 394 5600",
    "sg:postcode":"02670",
    "sg:province":"MA",
    "sg:tags":[
        "organization",
        "welfare"
    ],
    "wof:name":"Cape Cod Property Owners",
    "wof:placetype":"venue"
},
  "geometry": {"coordinates":[-70.17555400000001,41.664478],"type":"Point"}
}