{
  "type": "Feature",
  "properties": {
    "iso:country":"US",
    "sg:address":"259 Main St",
    "sg:city":"Williamstown",
    "sg:classifiers":[
        {
            "category":"Banks & Credit Unions",
            "subcategory":"Bank",
            "type":"Services"
        }
    ],
    "sg:phone":"+1 413 458 9103",
    "sg:postcode":"01267",
    "sg:province":"MA",
    "sg:tags":[
        "cashing",
        "check"
    ],
    "wof:name":"Graham Check Cashing",
    "wof:placetype":"venue"
},
  "geometry": {"coordinates":[-73.18506499999999,42.702079],"type":"Point"}
}