{
  "type": "Feature",
  "properties": {
    "addr:full": "259 Main St Williamstown MA 01267",
    "addr:housenumber": "259",
    "addr:postcode": "01267",
    "addr:street": "Main St",
    "iso:country": "US",
    "sg:address": "259 Main St",
    "sg:city": "Williamstown",
    "sg:classifiers": [
      {
        "category": "Banks \u0026 Credit Unions",
        "subcategory": "Bank",
        "type": "Services"
      }
    ],
    "sg:phone": "+1 413 458 9103",
    "sg:postcode": "01267",
    "sg:province": "MA",
    "sg:tags": [
      "cashing",
      "check"
    ],
    "wof:name": "Graham Check Cashing",
    "wof:placetype": "venue"
  },
  "geometry": {"coordinates":[-73.185065,42.702079],"type":"Point"}
}
