{
  "type": "Feature",
  "properties": {
    "addr:full": "77 Powder Mill Rd Acton MA 01720",
    "addr:housenumber": "77",
    "addr:postcode": "01720",
    "addr:street": "Powder Mill Rd",
    "iso:country": "US",
    "sg:address": "77 Powder Mill Rd",
    "sg:city": "Acton",
    "sg:classifiers": [
      {
        "category": "Building \u0026 Trades",
        "subcategory": "Equipment Rental",
        "type": "Services"
      }
    ],
    "sg:phone": "+1 978 461 4774",
    "sg:postcode": "01720",
    "sg:province": "MA",
    "sg:tags": [
      "yard"
    ],
    "wof:name": "Concord Rental Ctr",
    "wof:placetype": "venue"
  },
  "geometry": {"coordinates":[-71.429374,42.440965],"type":"Point"}
}
