{
  "type": "Feature",
  "properties": {
    "iso:country":"US",
    "sg:address":"1 Memorial Dr",
    "sg:city":"Whitinsville",
    "sg:classifiers":[
        {
            "category":"Real Estate",
            "subcategory":"Surveying",
            "type":"Services"
        }
    ],
    "sg:phone":"+1 508 234 3493",
    "sg:postcode":"01545",
    "sg:province":"MA",
    "sg:tags":[
        "surveyor"
    ],
    "wof:name":"Tauper Land Survey",
    "wof:placetype":"venue"
},
  "geometry": {"coordinates":[-71.711043,42.274715],"type":"Point"}
}