{
  "type": "Feature",
  "properties": {
    "addr:full": "155 Castle St Great Barrington MA 01230",
    "addr:housenumber": "155",
    "addr:postcode": "01230",
    "addr:street": "Castle St",
    "iso:country": "US",
    "sg:address": "155 Castle St",
    "sg:city": "Great Barrington",
    "sg:classifiers": [
      {
        "category": "Recreation",
        "type": "Entertainment"
      }
    ],
    "sg:phone": "+1   ",
    "sg:postcode": "01230",
    "sg:province": "MA",
    "wof:name": "Janet Rickus Artist",
    "wof:placetype": "venue"
  },
  "geometry": {"coordinates":[-73.370443,42.195192],"type":"Point"}
}
