{
  "type": "Feature",
  "properties": {
    "addr:full":"51 Exchange St Athol MA 01331",
    "addr:housenumber":"51",
    "addr:postcode":"01331",
    "addr:street":"Exchange St",
    "iso:country":"US",
    "sg:address":"51 Exchange St",
    "sg:city":"Athol",
    "sg:classifiers":[
        {
            "category":"Professional",
            "type":"Services"
        }
    ],
    "sg:phone":"+1 978 249 6219",
    "sg:postcode":"01331",
    "sg:province":"MA",
    "sg:tags":[
        "establishment"
    ],
    "wof:name":"Teena's",
    "wof:placetype":"venue"
},
  "geometry": {"coordinates":[-72.231239,42.593189],"type":"Point"}
}