{
  "type": "Feature",
  "properties": {
    "iso:country":"US",
    "sg:address":"28 Draper Ln",
    "sg:city":"Canton",
    "sg:classifiers":[
        {
            "category":"Food & Beverages",
            "subcategory":"Candy",
            "type":"Retail Goods"
        }
    ],
    "sg:phone":"+1 781 828 4990",
    "sg:postcode":"02021",
    "sg:province":"MA",
    "sg:tags":[
        "store"
    ],
    "wof:name":"Rand Candy Co Inc",
    "wof:placetype":"venue"
},
  "geometry": {"coordinates":[-71.139252,42.173373],"type":"Point"}
}