{
  "type": "Feature",
  "properties": {
    "addr:full": "199 Auburn St Cambridge MA 02139",
    "addr:housenumber": "199",
    "addr:postcode": "02139",
    "addr:street": "Auburn St",
    "iso:country": "US",
    "sg:address": "199 Auburn St",
    "sg:city": "Cambridge",
    "sg:classifiers": [
      {
        "category": "Place Of Worship",
        "subcategory": "Temple",
        "type": "Public Place"
      }
    ],
    "sg:phone": "+1 617 576 3229",
    "sg:postcode": "02139",
    "sg:province": "MA",
    "sg:tags": [
      "buddhist"
    ],
    "wof:name": "Zen Center of Cambridge",
    "wof:placetype": "venue"
  },
  "geometry": {"coordinates":[-71.104401,42.364101],"type":"Point"}
}
