{
  "type": "Feature",
  "properties": {
    "iso:country":"US",
    "sg:address":"563 Columbus Avenue",
    "sg:city":"Roxbury",
    "sg:classifiers":[
        {
            "category":"Food & Beverages",
            "subcategory":"Groceries & Convenience Stores",
            "type":"Retail Goods"
        }
    ],
    "sg:phone":"+1 617 867 9094",
    "sg:postcode":"02118",
    "sg:province":"MA",
    "wof:name":"Food Basket",
    "wof:placetype":"venue"
},
  "geometry": {"coordinates":[-71.08116,42.340958],"type":"Point"}
}