{
  "type": "Feature",
  "properties": {
    "addr:full": "1125 County St New Bedford MA 02746",
    "addr:housenumber": "1125",
    "addr:postcode": "02746",
    "addr:street": "County St",
    "iso:country": "US",
    "sg:address": "1125 County St",
    "sg:city": "New Bedford",
    "sg:classifiers": [
      {
        "category": "Professional",
        "subcategory": "Accounting \u0026 Tax Preparation",
        "type": "Services"
      }
    ],
    "sg:phone": "+1 508 997 9434",
    "sg:postcode": "02746",
    "sg:province": "MA",
    "sg:tags": [
      "accountant"
    ],
    "wof:name": "Edwin J Haznar CPA",
    "wof:placetype": "venue"
  },
  "geometry": {"coordinates":[-70.933191,41.657373],"type":"Point"}
}
