{
  "type": "Feature",
  "properties": {
    "iso:country":"US",
    "sg:address":"1125 County St",
    "sg:city":"New Bedford",
    "sg:classifiers":[
        {
            "category":"Professional",
            "subcategory":"Accounting & Tax Preparation",
            "type":"Services"
        }
    ],
    "sg:phone":"+1 508 997 9434",
    "sg:postcode":"02746",
    "sg:province":"MA",
    "sg:tags":[
        "accountant"
    ],
    "wof:name":"Edwin J Haznar CPA",
    "wof:placetype":"venue"
},
  "geometry": {"coordinates":[-70.93319099999999,41.657373],"type":"Point"}
}