{
  "type": "Feature",
  "properties": {
    "addr:full":"84 E Falmouth Hwy East Falmouth MA 02536",
    "addr:housenumber":"84",
    "addr:postcode":"02536",
    "addr:street":"E Falmouth Hwy",
    "iso:country":"US",
    "sg:address":"84 E Falmouth Hwy",
    "sg:city":"East Falmouth",
    "sg:classifiers":[
        {
            "category":"Autos & Motor Vehicles",
            "subcategory":"Fuel & Gas Station",
            "type":"Retail Goods"
        }
    ],
    "sg:phone":"+1 508 548 9153",
    "sg:postcode":"02536",
    "sg:province":"MA",
    "sg:tags":[
        "oil"
    ],
    "wof:name":"East Falmouth BP",
    "wof:placetype":"venue"
},
  "geometry": {"coordinates":[-70.571012,41.578506],"type":"Point"}
}