{
  "type": "Feature",
  "properties": {
    "addr:full": "8 Worcester St Grafton MA 01519",
    "addr:housenumber": "8",
    "addr:postcode": "01519",
    "addr:street": "Worcester St",
    "iso:country": "US",
    "sg:address": "8 Worcester St",
    "sg:city": "Grafton",
    "sg:classifiers": [
      {
        "category": "Deli",
        "type": "Food \u0026 Drink"
      },
      {
        "category": "Restaurant",
        "type": "Food \u0026 Drink"
      }
    ],
    "sg:phone": "+1 508 839 9546",
    "sg:postcode": "01519",
    "sg:province": "MA",
    "sg:tags": [
      "delicatessen"
    ],
    "wof:name": "Branded Bear Deli",
    "wof:placetype": "venue"
  },
  "geometry": {"coordinates":[-71.685831,42.207856],"type":"Point"}
}
