{
  "type": "Feature",
  "properties": {
    "iso:country":"US",
    "sg:address":"8 Worcester St",
    "sg:city":"Grafton",
    "sg:classifiers":[
        {
            "category":"Deli",
            "type":"Food & Drink"
        },
        {
            "category":"Restaurant",
            "type":"Food & Drink"
        }
    ],
    "sg:phone":"+1 508 839 9546",
    "sg:postcode":"01519",
    "sg:province":"MA",
    "sg:tags":[
        "delicatessen"
    ],
    "wof:name":"Branded Bear Deli",
    "wof:placetype":"venue"
},
  "geometry": {"coordinates":[-71.68583099999999,42.207856],"type":"Point"}
}