{
  "type": "Feature",
  "properties": {
    "iso:country":"US",
    "sg:address":"8 Newcomb St",
    "sg:city":"Roxbury",
    "sg:classifiers":[
        {
            "category":"Real Estate",
            "subcategory":"Real Estate Agent",
            "type":"Services"
        }
    ],
    "sg:phone":"+1 617 445 1109",
    "sg:postcode":"02118",
    "sg:province":"MA",
    "wof:name":"8 Newcomb Street Realty Trust",
    "wof:placetype":"venue"
},
  "geometry": {"coordinates":[-71.078312,42.333838],"type":"Point"}
}