{
  "type": "Feature",
  "properties": {
    "iso:country":"US",
    "sg:address":"404 Middlesex Rd",
    "sg:city":"Tyngsboro",
    "sg:classifiers":[
        {
            "category":"Professional",
            "subcategory":"Accounting & Tax Preparation",
            "type":"Services"
        }
    ],
    "sg:phone":"+1 978 649 7818",
    "sg:postcode":"01879",
    "sg:province":"MA",
    "sg:tags":[
        "accountant"
    ],
    "wof:name":"Murphy & Co",
    "wof:placetype":"venue"
},
  "geometry": {"coordinates":[-71.435787,42.693741],"type":"Point"}
}