{
  "type": "Feature",
  "properties": {
    "addr:full": "404 Middlesex Rd Tyngsboro MA 01879",
    "addr:housenumber": "404",
    "addr:postcode": "01879",
    "addr:street": "Middlesex Rd",
    "iso:country": "US",
    "sg:address": "404 Middlesex Rd",
    "sg:city": "Tyngsboro",
    "sg:classifiers": [
      {
        "category": "Professional",
        "subcategory": "Accounting \u0026 Tax Preparation",
        "type": "Services"
      }
    ],
    "sg:phone": "+1 978 649 7818",
    "sg:postcode": "01879",
    "sg:province": "MA",
    "sg:tags": [
      "accountant"
    ],
    "wof:name": "Murphy \u0026 Co",
    "wof:placetype": "venue"
  },
  "geometry": {"coordinates":[-71.435787,42.693741],"type":"Point"}
}
