{
  "type": "Feature",
  "properties": {
    "iso:country":"US",
    "sg:address":"20 Sherman St",
    "sg:city":"Brockton",
    "sg:classifiers":[
        {
            "category":"Freight",
            "type":"Transportation"
        }
    ],
    "sg:phone":"+1   ",
    "sg:postcode":"02302",
    "sg:province":"MA",
    "sg:tags":[
        "courier"
    ],
    "wof:name":"Paxton Express",
    "wof:placetype":"venue"
},
  "geometry": {"coordinates":[-70.995535,42.087388],"type":"Point"}
}