{
  "type": "Feature",
  "properties": {
    "addr:full": "8 Baker Rd Nahant MA 01908",
    "addr:housenumber": "8",
    "addr:postcode": "01908",
    "addr:street": "Baker Rd",
    "iso:country": "US",
    "sg:address": "8 Baker Rd",
    "sg:city": "Nahant",
    "sg:classifiers": [
      {
        "category": "Building \u0026 Trades",
        "subcategory": "Construction",
        "type": "Services"
      }
    ],
    "sg:phone": "+1 781 581 3493",
    "sg:postcode": "01908",
    "sg:province": "MA",
    "sg:tags": [
      "wallcoverings-installation",
      "wallpaper",
      "painting",
      "contractor"
    ],
    "wof:name": "M Connelly Painting",
    "wof:placetype": "venue"
  },
  "geometry": {"coordinates":[-70.932983,42.43618],"type":"Point"}
}
