{
  "type": "Feature",
  "properties": {
    "addr:full": "18 Douglas St New Bedford MA 02744",
    "addr:housenumber": "18",
    "addr:postcode": "02744",
    "addr:street": "Douglas St",
    "iso:country": "US",
    "sg:address": "18 Douglas St",
    "sg:city": "New Bedford",
    "sg:classifiers": [
      {
        "category": "Shopping",
        "subcategory": "Computers \u0026 Home Electronics",
        "type": "Retail Goods"
      }
    ],
    "sg:phone": "+1 508 991 3330",
    "sg:postcode": "02744",
    "sg:province": "MA",
    "sg:tags": [
      "software"
    ],
    "wof:name": "Somtotal Systems Inc",
    "wof:placetype": "venue"
  },
  "geometry": {"coordinates":[-70.905698,41.601653],"type":"Point"}
}
