{
  "type": "Feature",
  "properties": {
    "iso:country":"US",
    "sg:address":"18 Douglas St",
    "sg:city":"New Bedford",
    "sg:classifiers":[
        {
            "category":"Shopping",
            "subcategory":"Computers & Home Electronics",
            "type":"Retail Goods"
        }
    ],
    "sg:phone":"+1 508 991 3330",
    "sg:postcode":"02744",
    "sg:province":"MA",
    "sg:tags":[
        "software"
    ],
    "wof:name":"Somtotal Systems Inc",
    "wof:placetype":"venue"
},
  "geometry": {"coordinates":[-70.905698,41.601653],"type":"Point"}
}