{
  "type": "Feature",
  "properties": {
    "addr:full": "24 Deerfield Rd Sherborn MA 01770",
    "addr:housenumber": "24",
    "addr:postcode": "01770",
    "addr:street": "Deerfield Rd",
    "iso:country": "US",
    "sg:address": "24 Deerfield Rd",
    "sg:city": "Sherborn",
    "sg:classifiers": [
      {
        "category": "Shopping",
        "subcategory": "Computers \u0026 Home Electronics",
        "type": "Retail Goods"
      }
    ],
    "sg:phone": "+1 978 663 7385",
    "sg:postcode": "01770",
    "sg:province": "MA",
    "sg:tags": [
      "audio"
    ],
    "wof:name": "Home Dynamic Systems",
    "wof:placetype": "venue"
  },
  "geometry": {"coordinates":[-71.37655,42.223284],"type":"Point"}
}
