{
  "type": "Feature",
  "properties": {
    "addr:full":"17 Old Farm Rd Orleans MA 02653",
    "addr:housenumber":"17",
    "addr:postcode":"02653",
    "addr:street":"Old Farm Rd",
    "iso:country":"US",
    "sg:address":"17 Old Farm Rd",
    "sg:city":"Orleans",
    "sg:classifiers":[
        {
            "category":"Professional",
            "subcategory":"Computer Services",
            "type":"Services"
        }
    ],
    "sg:phone":"+1 508 240 6543",
    "sg:postcode":"02653",
    "sg:province":"MA",
    "sg:tags":[
        "design",
        "system"
    ],
    "wof:name":"Pleasantbay Net",
    "wof:placetype":"venue"
},
  "geometry": {"coordinates":[-69.985083,41.781428],"type":"Point"}
}