{
  "type": "Feature",
  "properties": {
    "iso:country":"US",
    "sg:address":"383 Westhampton Rd",
    "sg:city":"Florence",
    "sg:classifiers":[
        {
            "category":"Home & Garden",
            "subcategory":"Garden Supply",
            "type":"Retail Goods"
        }
    ],
    "sg:phone":"+1 413 584 2813",
    "sg:postcode":"01062",
    "sg:province":"MA",
    "sg:tags":[
        "landscaping",
        "equipment"
    ],
    "sg:website":"www.sticks-n-stones.com",
    "wof:name":"Sticks N Stones",
    "wof:placetype":"venue"
},
  "geometry": {"coordinates":[-72.688873,42.302726],"type":"Point"}
}