{
  "type": "Feature",
  "properties": {
    "iso:country":"US",
    "sg:address":"48 Main St",
    "sg:city":"Ayer",
    "sg:classifiers":[
        {
            "category":"Real Estate",
            "subcategory":"Real Estate Agent",
            "type":"Services"
        }
    ],
    "sg:phone":"+1   ",
    "sg:postcode":"01432",
    "sg:province":"MA",
    "wof:name":"Berry Enterprises",
    "wof:placetype":"venue"
},
  "geometry": {"coordinates":[-71.588892,42.559726],"type":"Point"}
}