{
  "type": "Feature",
  "properties": {
    "iso:country":"US",
    "sg:address":"421 First Parish Rd",
    "sg:city":"Scituate",
    "sg:classifiers":[
        {
            "category":"Real Estate",
            "subcategory":"Real Estate Services",
            "type":"Services"
        },
        {
            "category":"Real Estate",
            "subcategory":"Real Estate Agent",
            "type":"Services"
        }
    ],
    "sg:phone":"+1 781 545 2805",
    "sg:postcode":"02066",
    "sg:province":"MA",
    "sg:tags":[
        "buyer",
        "broker"
    ],
    "wof:name":"Sm Roberts Realty Co",
    "wof:placetype":"venue"
},
  "geometry": {"coordinates":[-70.76462600000001,42.197352],"type":"Point"}
}