{
  "type": "Feature",
  "properties": {
    "iso:country":"US",
    "sg:address":"69 Napoleon St",
    "sg:city":"Fall River",
    "sg:classifiers":[
        {
            "category":"Retail",
            "subcategory":"Auto Repair",
            "type":"Services"
        }
    ],
    "sg:phone":"+1 508 675 0411",
    "sg:postcode":"02721",
    "sg:province":"MA",
    "sg:tags":[
        "wrecker"
    ],
    "wof:name":"A Towing Auto Repair",
    "wof:placetype":"venue"
},
  "geometry": {"coordinates":[-71.156547,41.667708],"type":"Point"}
}