{
  "type": "Feature",
  "properties": {
    "iso:country":"US",
    "sg:address":"217 Oneil Blvd",
    "sg:city":"Attleboro",
    "sg:classifiers":[
        {
            "category":"Retail",
            "subcategory":"Auto Repair",
            "type":"Services"
        }
    ],
    "sg:phone":"+1 508 222 9510",
    "sg:postcode":"02703",
    "sg:province":"MA",
    "wof:name":"Dave's Auto Repair",
    "wof:placetype":"venue"
},
  "geometry": {"coordinates":[-71.275803,41.937801],"type":"Point"}
}