{
  "type": "Feature",
  "properties": {
    "addr:full": "1239 Millbury St Worcester MA 01607",
    "addr:housenumber": "1239",
    "addr:postcode": "01607",
    "addr:street": "Millbury St",
    "iso:country": "US",
    "sg:address": "1239 Millbury St",
    "sg:city": "Worcester",
    "sg:classifiers": [
      {
        "category": "Autos \u0026 Motor Vehicles",
        "subcategory": "Automobile Sales",
        "type": "Retail Goods"
      }
    ],
    "sg:phone": "+1 508 793 8586",
    "sg:postcode": "01607",
    "sg:province": "MA",
    "sg:tags": [
      "car",
      "dealer"
    ],
    "wof:name": "Sonia's Used Cars",
    "wof:placetype": "venue"
  },
  "geometry": {"coordinates":[-71.783656,42.220246],"type":"Point"}
}
