{
  "type": "Feature",
  "properties": {
    "addr:full": "1445 Main St Tewksbury MA 01876",
    "addr:housenumber": "1445",
    "addr:postcode": "01876",
    "addr:street": "Main St",
    "iso:country": "US",
    "sg:address": "1445 Main St",
    "sg:city": "Tewksbury",
    "sg:classifiers": [
      {
        "category": "Shopping",
        "subcategory": "Gifts \u0026 Souvenirs",
        "type": "Retail Goods"
      }
    ],
    "sg:phone": "+1 978 851 3299",
    "sg:postcode": "01876",
    "sg:province": "MA",
    "sg:tags": [
      "party",
      "supply"
    ],
    "wof:name": "Perfect Party Boutique",
    "wof:placetype": "venue"
  },
  "geometry": {"coordinates":[-71.222628,42.601817],"type":"Point"}
}
