{
  "type": "Feature",
  "properties": {
    "addr:full":"47 Washington St North Easton MA 02356",
    "addr:housenumber":"47",
    "addr:postcode":"02356",
    "addr:street":"Washington St",
    "iso:country":"US",
    "sg:address":"47 Washington St",
    "sg:city":"North Easton",
    "sg:classifiers":[
        {
            "category":"Retail",
            "subcategory":"Repair Shop",
            "type":"Services"
        }
    ],
    "sg:phone":"+1 508 238 6456",
    "sg:postcode":"02356",
    "sg:province":"MA",
    "sg:tags":[
        "reupholstery",
        "furniture"
    ],
    "wof:name":"Lee Uphlstg - CLOSED",
    "wof:placetype":"venue"
},
  "geometry": {"coordinates":[-71.09200300000001,42.0877],"type":"Point"}
}