{
  "type": "Feature",
  "properties": {
    "iso:country":"US",
    "sg:address":"173 High St",
    "sg:city":"Holyoke",
    "sg:classifiers":[
        {
            "category":"Restaurant",
            "type":"Food & Drink"
        }
    ],
    "sg:phone":"+1 413 533 9893",
    "sg:postcode":"01040",
    "sg:province":"MA",
    "wof:name":"Nick O'Neill's Restaurant",
    "wof:placetype":"venue"
},
  "geometry": {"coordinates":[-72.60687900000001,42.207997],"type":"Point"}
}