{
  "type": "Feature",
  "properties": {
    "iso:country":"US",
    "sg:address":"328 Broad St",
    "sg:city":"Weymouth",
    "sg:classifiers":[
        {
            "category":"Local Transit",
            "type":"Transportation"
        }
    ],
    "sg:phone":"+1 617 689 0208",
    "sg:postcode":"02188",
    "sg:province":"MA",
    "sg:tags":[
        "airport"
    ],
    "wof:name":"Coach 128",
    "wof:placetype":"venue"
},
  "geometry": {"coordinates":[-70.949669,42.217673],"type":"Point"}
}