{
  "type": "Feature",
  "properties": {
    "addr:full":"22 Hyde Ave Newton MA 02458",
    "addr:housenumber":"22",
    "addr:postcode":"02458",
    "addr:street":"Hyde Ave",
    "iso:country":"US",
    "sg:address":"22 Hyde Ave",
    "sg:city":"Newton",
    "sg:classifiers":[
        {
            "category":"Building & Trades",
            "subcategory":"Construction",
            "type":"Services"
        }
    ],
    "sg:phone":"+1 617 527 0123",
    "sg:postcode":"02458",
    "sg:province":"MA",
    "sg:tags":[
        "estimate"
    ],
    "sg:website":"http://www.mchalfen.com",
    "wof:name":"Chalfen Melvin H Inc",
    "wof:placetype":"venue"
},
  "geometry": {"coordinates":[-71.185737,42.349182],"type":"Point"}
}