{
  "type": "Feature",
  "properties": {
    "addr:full": "199 Boylston St Brookline MA 02445",
    "addr:housenumber": "199",
    "addr:postcode": "02445",
    "addr:street": "Boylston St",
    "iso:country": "US",
    "sg:address": "199 Boylston St",
    "sg:city": "Brookline",
    "sg:classifiers": [
      {
        "category": "Building \u0026 Trades",
        "subcategory": "Locksmith",
        "type": "Services"
      }
    ],
    "sg:phone": "+1 617 622 3699",
    "sg:postcode": "02445",
    "sg:province": "MA",
    "sg:tags": [
      "key"
    ],
    "wof:name": "24 Hours A Locksmith",
    "wof:placetype": "venue"
  },
  "geometry": {"coordinates":[-71.122594,42.330863],"type":"Point"}
}
