{
  "type": "Feature",
  "properties": {
    "addr:full":"655 Iyannough Rd Hyannis MA 02601",
    "addr:housenumber":"655",
    "addr:postcode":"02601",
    "addr:street":"Iyannough Rd",
    "iso:country":"US",
    "sg:address":"655 Iyannough Rd",
    "sg:city":"Hyannis",
    "sg:classifiers":[
        {
            "category":"Food & Beverages",
            "subcategory":"Candy",
            "type":"Retail Goods"
        }
    ],
    "sg:phone":"+1 508 778 9294",
    "sg:postcode":"02601",
    "sg:province":"MA",
    "sg:tags":[
        "confectionery"
    ],
    "wof:name":"Candy Cafe",
    "wof:placetype":"venue"
},
  "geometry": {"coordinates":[-70.291274,41.666909],"type":"Point"}
}