{
  "type": "Feature",
  "properties": {
    "addr:full": "3 Wianno Avenue Osterville MA 02655",
    "addr:housenumber": "3",
    "addr:postcode": "02655",
    "addr:street": "Wianno Avenue",
    "iso:country": "US",
    "sg:address": "3 Wianno Avenue",
    "sg:city": "Osterville",
    "sg:classifiers": [
      {
        "category": "Restaurant",
        "type": "Food \u0026 Drink"
      }
    ],
    "sg:postcode": "02655",
    "sg:province": "MA",
    "wof:name": "Osterville Sundae News",
    "wof:placetype": "venue"
  },
  "geometry": {"coordinates":[-70.385157,41.628058],"type":"Point"}
}
