{
  "type": "Feature",
  "properties": {
    "iso:country":"US",
    "sg:address":"3 Wianno Avenue",
    "sg:city":"Osterville",
    "sg:classifiers":[
        {
            "category":"Restaurant",
            "type":"Food & Drink"
        }
    ],
    "sg:postcode":"02655",
    "sg:province":"MA",
    "wof:name":"Osterville Sundae News",
    "wof:placetype":"venue"
},
  "geometry": {"coordinates":[-70.38515700000001,41.628058],"type":"Point"}
}