{
  "type": "Feature",
  "properties": {
    "iso:country":"US",
    "sg:address":"434 Blue Hill Ave",
    "sg:city":"Dorchester",
    "sg:classifiers":[
        {
            "category":"Real Estate",
            "subcategory":"Real Estate Agent",
            "type":"Services"
        }
    ],
    "sg:phone":"+1 617 427 6663",
    "sg:postcode":"02121",
    "sg:province":"MA",
    "wof:name":"Champagne & Assoc Real Estate",
    "wof:placetype":"venue"
},
  "geometry": {"coordinates":[-71.082368,42.309753],"type":"Point"}
}