{
  "type": "Feature",
  "properties": {
    "addr:full": "434 Blue Hill Ave Dorchester MA 02121",
    "addr:housenumber": "434",
    "addr:postcode": "02121",
    "addr:street": "Blue Hill Ave",
    "iso:country": "US",
    "sg:address": "434 Blue Hill Ave",
    "sg:city": "Dorchester",
    "sg:classifiers": [
      {
        "category": "Real Estate",
        "subcategory": "Real Estate Agent",
        "type": "Services"
      }
    ],
    "sg:phone": "+1 617 427 6663",
    "sg:postcode": "02121",
    "sg:province": "MA",
    "wof:name": "Champagne \u0026 Assoc Real Estate",
    "wof:placetype": "venue"
  },
  "geometry": {"coordinates":[-71.082368,42.309753],"type":"Point"}
}
