{
  "type": "Feature",
  "properties": {
    "addr:full":"5 Rickard St Carver MA 02330",
    "addr:housenumber":"5",
    "addr:postcode":"02330",
    "addr:street":"Rickard St",
    "iso:country":"US",
    "sg:address":"5 Rickard St",
    "sg:city":"Carver",
    "sg:classifiers":[
        {
            "category":"Building & Trades",
            "subcategory":"Plumbing",
            "type":"Services"
        }
    ],
    "sg:phone":"+1   ",
    "sg:postcode":"02330",
    "sg:province":"MA",
    "sg:tags":[
        "contractor"
    ],
    "wof:name":"Patriot Plumbing Heating Inc",
    "wof:placetype":"venue"
},
  "geometry": {"coordinates":[-70.796441,41.902643],"type":"Point"}
}