{
  "type": "Feature",
  "properties": {
    "addr:full": "529 Nantasket Ave Hull MA 02045",
    "addr:housenumber": "529",
    "addr:postcode": "02045",
    "addr:street": "Nantasket Ave",
    "iso:country": "US",
    "sg:address": "529 Nantasket Ave",
    "sg:city": "Hull",
    "sg:classifiers": [
      {
        "category": "Health Services",
        "subcategory": "Doctor",
        "type": "Services"
      }
    ],
    "sg:phone": "+1 781 925 5100",
    "sg:postcode": "02045",
    "sg:province": "MA",
    "sg:tags": [
      "dentist"
    ],
    "wof:name": "Stephen A Locke DDS",
    "wof:placetype": "venue"
  },
  "geometry": {"coordinates":[-70.874,42.283109],"type":"Point"}
}
