{
  "type": "Feature",
  "properties": {
    "addr:full": "42 Harvard Ave Methuen MA 01844",
    "addr:housenumber": "42",
    "addr:postcode": "01844",
    "addr:street": "Harvard Ave",
    "iso:country": "US",
    "sg:address": "42 Harvard Ave",
    "sg:city": "Methuen",
    "sg:classifiers": [
      {
        "category": "Building \u0026 Trades",
        "subcategory": "Landscaping Services",
        "type": "Services"
      }
    ],
    "sg:phone": "+1 978 686 2635",
    "sg:postcode": "01844",
    "sg:province": "MA",
    "wof:name": "Woodland Landscaping",
    "wof:placetype": "venue"
  },
  "geometry": {"coordinates":[-71.223217,42.732684],"type":"Point"}
}
