{
  "type": "Feature",
  "properties": {
    "iso:country":"US",
    "sg:address":"42 Harvard Ave",
    "sg:city":"Methuen",
    "sg:classifiers":[
        {
            "category":"Building & Trades",
            "subcategory":"Landscaping Services",
            "type":"Services"
        }
    ],
    "sg:phone":"+1 978 686 2635",
    "sg:postcode":"01844",
    "sg:province":"MA",
    "wof:name":"Woodland Landscaping",
    "wof:placetype":"venue"
},
  "geometry": {"coordinates":[-71.22321700000001,42.732684],"type":"Point"}
}