{
  "type": "Feature",
  "properties": {
    "iso:country":"US",
    "sg:address":"416 Marlborough St",
    "sg:city":"Boston",
    "sg:classifiers":[
        {
            "category":"Professional",
            "subcategory":"Business Services",
            "type":"Services"
        }
    ],
    "sg:phone":"+1 617 504 1177",
    "sg:postcode":"02115",
    "sg:province":"MA",
    "sg:tags":[
        "management"
    ],
    "wof:name":"Trenriver",
    "wof:placetype":"venue"
},
  "geometry": {"coordinates":[-71.089111,42.35004],"type":"Point"}
}