{
  "type": "Feature",
  "properties": {
    "iso:country":"US",
    "sg:address":"100 Morse St",
    "sg:city":"Norwood",
    "sg:classifiers":[
        {
            "category":"Wholesale",
            "subcategory":"Groceries",
            "type":"Manufacturing & Wholesale Goods"
        }
    ],
    "sg:phone":"+1 781 278 5000",
    "sg:postcode":"02062",
    "sg:province":"MA",
    "sg:tags":[
        "food",
        "broker"
    ],
    "sg:website":"www.crossmark.com",
    "wof:name":"CROSSMARK",
    "wof:placetype":"venue"
},
  "geometry": {"coordinates":[-71.205618,42.17299],"type":"Point"}
}