{
  "type": "Feature",
  "properties": {
    "iso:country":"US",
    "sg:address":"312 Springfield St",
    "sg:city":"Agawam",
    "sg:classifiers":[
        {
            "category":"Retail",
            "subcategory":"Repair Shop",
            "type":"Services"
        }
    ],
    "sg:phone":"+1 413 786 9980",
    "sg:postcode":"01001",
    "sg:province":"MA",
    "sg:tags":[
        "electrical"
    ],
    "wof:name":"Easterntronics",
    "wof:placetype":"venue"
},
  "geometry": {"coordinates":[-72.63981800000001,42.088129],"type":"Point"}
}