{
  "type": "Feature",
  "properties": {
    "addr:full": "312 Springfield St Agawam MA 01001",
    "addr:housenumber": "312",
    "addr:postcode": "01001",
    "addr:street": "Springfield St",
    "iso:country": "US",
    "sg:address": "312 Springfield St",
    "sg:city": "Agawam",
    "sg:classifiers": [
      {
        "category": "Retail",
        "subcategory": "Repair Shop",
        "type": "Services"
      }
    ],
    "sg:phone": "+1 413 786 9980",
    "sg:postcode": "01001",
    "sg:province": "MA",
    "sg:tags": [
      "electrical"
    ],
    "wof:name": "Easterntronics",
    "wof:placetype": "venue"
  },
  "geometry": {"coordinates":[-72.639818,42.088129],"type":"Point"}
}
