{
  "type": "Feature",
  "properties": {
    "iso:country":"US",
    "sg:address":"184 Boston St",
    "sg:city":"Dorchester",
    "sg:classifiers":[
        {
            "category":"Building & Trades",
            "subcategory":"Construction",
            "type":"Services"
        }
    ],
    "sg:phone":"+1 800 675 7480",
    "sg:postcode":"02125",
    "sg:province":"MA",
    "sg:tags":[
        "board"
    ],
    "wof:name":"Boston Emergency Service Toll Free-Dial '1' & Then",
    "wof:placetype":"venue"
},
  "geometry": {"coordinates":[-71.060371,42.323384],"type":"Point"}
}