{
  "type": "Feature",
  "properties": {
    "addr:full": "184 Boston St Dorchester MA 02125",
    "addr:housenumber": "184",
    "addr:postcode": "02125",
    "addr:street": "Boston St",
    "iso:country": "US",
    "sg:address": "184 Boston St",
    "sg:city": "Dorchester",
    "sg:classifiers": [
      {
        "category": "Building \u0026 Trades",
        "subcategory": "Construction",
        "type": "Services"
      }
    ],
    "sg:phone": "+1 800 675 7480",
    "sg:postcode": "02125",
    "sg:province": "MA",
    "sg:tags": [
      "board"
    ],
    "wof:name": "Boston Emergency Service Toll Free-Dial '1' \u0026 Then",
    "wof:placetype": "venue"
  },
  "geometry": {"coordinates":[-71.060371,42.323384],"type":"Point"}
}
