{
  "type": "Feature",
  "properties": {
    "iso:country":"US",
    "sg:address":"61 Sanders Ln",
    "sg:city":"Waltham",
    "sg:classifiers":[
        {
            "category":"Real Estate",
            "subcategory":"Real Estate Agent",
            "type":"Services"
        }
    ],
    "sg:phone":"+1 781 894 6912",
    "sg:postcode":"02451",
    "sg:province":"MA",
    "sg:tags":[
        "management"
    ],
    "wof:name":"47 Bacon Street LLC",
    "wof:placetype":"venue"
},
  "geometry": {"coordinates":[-71.24384999999999,42.3891],"type":"Point"}
}