{
  "type": "Feature",
  "properties": {
    "addr:full": "61 Sanders Ln Waltham MA 02451",
    "addr:housenumber": "61",
    "addr:postcode": "02451",
    "addr:street": "Sanders Ln",
    "iso:country": "US",
    "sg:address": "61 Sanders Ln",
    "sg:city": "Waltham",
    "sg:classifiers": [
      {
        "category": "Real Estate",
        "subcategory": "Real Estate Agent",
        "type": "Services"
      }
    ],
    "sg:phone": "+1 781 894 6912",
    "sg:postcode": "02451",
    "sg:province": "MA",
    "sg:tags": [
      "management"
    ],
    "wof:name": "47 Bacon Street LLC",
    "wof:placetype": "venue"
  },
  "geometry": {"coordinates":[-71.24385,42.3891],"type":"Point"}
}
