{
  "type": "Feature",
  "properties": {
    "iso:country":"US",
    "sg:address":"2377 Boston Rd",
    "sg:city":"Wilbraham",
    "sg:classifiers":[
        {
            "category":"Personal",
            "type":"Services"
        }
    ],
    "sg:phone":"+1 413 596 4444",
    "sg:postcode":"01095",
    "sg:province":"MA",
    "sg:tags":[
        "credit",
        "debt",
        "counseling"
    ],
    "wof:name":"Pinnacle Financial Mgmt Corp",
    "wof:placetype":"venue"
},
  "geometry": {"coordinates":[-72.451654,42.149484],"type":"Point"}
}