{
  "type": "Feature",
  "properties": {
    "addr:full":"30 Washington St Monson MA 01057",
    "addr:housenumber":"30",
    "addr:postcode":"01057",
    "addr:street":"Washington St",
    "iso:country":"US",
    "sg:address":"30 Washington St",
    "sg:city":"Monson",
    "sg:classifiers":[
        {
            "category":"Manufacturing",
            "subcategory":"Metals",
            "type":"Manufacturing & Wholesale Goods"
        }
    ],
    "sg:phone":"+1 413 267 9300",
    "sg:postcode":"01057",
    "sg:province":"MA",
    "sg:tags":[
        "foundry"
    ],
    "wof:name":"Granite Wholesalers-New Eng",
    "wof:placetype":"venue"
},
  "geometry": {"coordinates":[-72.316452,42.102804],"type":"Point"}
}