{
  "type": "Feature",
  "properties": {
    "addr:full":"947 Washington St Attleboro MA 02703",
    "addr:housenumber":"947",
    "addr:postcode":"02703",
    "addr:street":"Washington St",
    "iso:country":"US",
    "sg:address":"947 Washington St",
    "sg:city":"Attleboro",
    "sg:classifiers":[
        {
            "category":"Professional",
            "subcategory":"Management & Consulting",
            "type":"Services"
        }
    ],
    "sg:phone":"+1 508 761 9222",
    "sg:postcode":"02703",
    "sg:province":"MA",
    "sg:tags":[
        "consultant",
        "business"
    ],
    "wof:name":"Canoe River Management Co",
    "wof:placetype":"venue"
},
  "geometry": {"coordinates":[-71.3682,41.900527],"type":"Point"}
}