{
  "type": "Feature",
  "properties": {
    "addr:full":"500 Boylston St Boston MA 02116",
    "addr:housenumber":"500",
    "addr:postcode":"02116",
    "addr:street":"Boylston St",
    "iso:country":"US",
    "sg:address":"500 Boylston St",
    "sg:city":"Boston",
    "sg:classifiers":[
        {
            "category":"Personal",
            "type":"Services"
        }
    ],
    "sg:phone":"+1 617 267 3888",
    "sg:postcode":"02116",
    "sg:province":"MA",
    "sg:tags":[
        "assistant"
    ],
    "wof:name":"Tea Court Copley Sq Bos",
    "wof:placetype":"venue"
},
  "geometry": {"coordinates":[-71.074471,42.350868],"type":"Point"}
}