{
  "type": "Feature",
  "properties": {
    "iso:country":"US",
    "sg:address":"160 Macarthur Blvd",
    "sg:city":"Buzzards Bay",
    "sg:classifiers":[
        {
            "category":"Real Estate",
            "subcategory":"Real Estate Agent",
            "type":"Services"
        }
    ],
    "sg:phone":"+1 508 759 6833",
    "sg:postcode":"02532",
    "sg:province":"MA",
    "wof:name":"Capeway Realty",
    "wof:placetype":"venue"
},
  "geometry": {"coordinates":[-70.536455,41.800271],"type":"Point"}
}