{
  "type": "Feature",
  "properties": {
    "addr:full":"256 Webster St Worcester MA 01603",
    "addr:housenumber":"256",
    "addr:postcode":"01603",
    "addr:street":"Webster St",
    "iso:country":"US",
    "sg:address":"256 Webster St",
    "sg:city":"Worcester",
    "sg:classifiers":[
        {
            "category":"Food & Beverages",
            "subcategory":"Meat & Fish",
            "type":"Retail Goods"
        }
    ],
    "sg:phone":"+1 508 754 0644",
    "sg:postcode":"01603",
    "sg:province":"MA",
    "sg:website":"www.hpmeat.com",
    "wof:name":"Hadwen Park Market",
    "wof:placetype":"venue"
},
  "geometry": {"coordinates":[-71.83389099999999,42.232339],"type":"Point"}
}