{
  "type": "Feature",
  "properties": {
    "iso:country":"US",
    "sg:address":"114 Southern Ave",
    "sg:city":"Dorchester Ctr",
    "sg:classifiers":[
        {
            "category":"Organizations",
            "subcategory":"Religious Organization",
            "type":"Services"
        }
    ],
    "sg:phone":"+1 617 287 9698",
    "sg:postcode":"02124",
    "sg:province":"MA",
    "sg:tags":[
        "church"
    ],
    "wof:name":"Prayer Room Pentecostal Church",
    "wof:placetype":"venue"
},
  "geometry": {"coordinates":[-71.077654,42.289567],"type":"Point"}
}