{
  "type": "Feature",
  "properties": {
    "addr:full": "404 Sumner St Boston MA 02128",
    "addr:housenumber": "404",
    "addr:postcode": "02128",
    "addr:street": "Sumner St",
    "iso:country": "US",
    "sg:address": "404 Sumner St",
    "sg:city": "Boston",
    "sg:classifiers": [
      {
        "category": "Organizations",
        "subcategory": "Religious Organization",
        "type": "Services"
      }
    ],
    "sg:phone": "+1 617 567 3227",
    "sg:postcode": "02128",
    "sg:province": "MA",
    "sg:tags": [
      "place",
      "worship",
      "church"
    ],
    "sg:website": "http://www.rosaryacademy.net",
    "wof:name": "Our Lady Of Assumption",
    "wof:placetype": "venue"
  },
  "geometry": {"coordinates":[-71.0336,42.366131],"type":"Point"}
}
