{
  "type": "Feature",
  "properties": {
    "iso:country":"US",
    "sg:address":"86 Billerica Mall",
    "sg:city":"Billerica",
    "sg:classifiers":[
        {
            "category":"Building & Trades",
            "subcategory":"Construction",
            "type":"Services"
        }
    ],
    "sg:phone":"+1 978 670 4747",
    "sg:postcode":"01821",
    "sg:province":"MA",
    "sg:tags":[
        "contractor"
    ],
    "sg:website":"www.morganconstruction.info",
    "wof:name":"Morgan Construction",
    "wof:placetype":"venue"
},
  "geometry": {"coordinates":[-71.283153,42.601257],"type":"Point"}
}