{
  "type": "Feature",
  "properties": {
    "addr:full": "86 Billerica Mall Billerica MA 01821",
    "addr:housenumber": "86",
    "addr:postcode": "01821",
    "addr:street": "Billerica Mall",
    "iso:country": "US",
    "sg:address": "86 Billerica Mall",
    "sg:city": "Billerica",
    "sg:classifiers": [
      {
        "category": "Building \u0026 Trades",
        "subcategory": "Construction",
        "type": "Services"
      }
    ],
    "sg:phone": "+1 978 670 4747",
    "sg:postcode": "01821",
    "sg:province": "MA",
    "sg:tags": [
      "contractor"
    ],
    "sg:website": "www.morganconstruction.info",
    "wof:name": "Morgan Construction",
    "wof:placetype": "venue"
  },
  "geometry": {"coordinates":[-71.283153,42.601257],"type":"Point"}
}
