{
  "type": "Feature",
  "properties": {
    "addr:full": "12 Welch Ave Ste 3 Stoughton MA 02072",
    "addr:housenumber": "12",
    "addr:postcode": "02072",
    "addr:street": "Welch Ave Ste 3",
    "iso:country": "US",
    "sg:address": "12 Welch Ave Ste 3",
    "sg:city": "Stoughton",
    "sg:classifiers": [
      {
        "category": "Wholesale",
        "subcategory": "Furniture",
        "type": "Manufacturing \u0026 Wholesale Goods"
      }
    ],
    "sg:phone": "+1 781 344 1970",
    "sg:postcode": "02072",
    "sg:province": "MA",
    "sg:tags": [
      "furniture-wholesale",
      "manufacturer"
    ],
    "sg:website": "http://www.highlandseating.com",
    "wof:name": "Highland Seating Inc",
    "wof:placetype": "venue"
  },
  "geometry": {"coordinates":[-71.102935,42.132731],"type":"Point"}
}
