{
  "type": "Feature",
  "properties": {
    "iso:country":"US",
    "sg:address":"29 Dock Ln",
    "sg:city":"Salisbury",
    "sg:classifiers":[
        {
            "category":"Building & Trades",
            "subcategory":"Construction",
            "type":"Services"
        }
    ],
    "sg:phone":"+1 978 462 6552",
    "sg:postcode":"01952",
    "sg:province":"MA",
    "sg:tags":[
        "contractor"
    ],
    "wof:name":"Johnson Building & Constr",
    "wof:placetype":"venue"
},
  "geometry": {"coordinates":[-70.83779800000001,42.835613],"type":"Point"}
}