{
  "type": "Feature",
  "properties": {
    "iso:country":"US",
    "sg:address":"868 Blue Hill Ave",
    "sg:city":"Dorchester Center",
    "sg:classifiers":[
        {
            "category":"Food & Beverages",
            "subcategory":"Groceries & Convenience Stores",
            "type":"Retail Goods"
        }
    ],
    "sg:phone":"+1 617 265 9359",
    "sg:postcode":"02124",
    "sg:province":"MA",
    "sg:tags":[
        "market"
    ],
    "wof:name":"Happy Supermarket",
    "wof:placetype":"venue"
},
  "geometry": {"coordinates":[-71.087898,42.2952],"type":"Point"}
}