{
  "type": "Feature",
  "properties": {
    "addr:full":"10 E Chestnut St Sharon MA 02067",
    "addr:housenumber":"10",
    "addr:postcode":"02067",
    "addr:street":"E Chestnut St",
    "iso:country":"US",
    "sg:address":"10 E Chestnut St",
    "sg:city":"Sharon",
    "sg:classifiers":[
        {
            "category":"Shopping",
            "subcategory":"Books",
            "type":"Retail Goods"
        }
    ],
    "sg:phone":"+1 781 784 0600",
    "sg:postcode":"02067",
    "sg:province":"MA",
    "sg:tags":[
        "dealer"
    ],
    "wof:name":"Book & Cup",
    "wof:placetype":"venue"
},
  "geometry": {"coordinates":[-71.179635,42.120891],"type":"Point"}
}