{
  "type": "Feature",
  "properties": {
    "iso:country":"US",
    "sg:address":"161 Kuniholm Dr",
    "sg:city":"Holliston",
    "sg:classifiers":[
        {
            "category":"Professional",
            "subcategory":"Business Services",
            "type":"Services"
        }
    ],
    "sg:phone":"+1 508 893 8025",
    "sg:postcode":"01746",
    "sg:province":"MA",
    "wof:name":"Asquith Corp",
    "wof:placetype":"venue"
},
  "geometry": {"coordinates":[-71.429371,42.230351],"type":"Point"}
}