{
  "type": "Feature",
  "properties": {
    "addr:full": "147 Northwest Rd Westhampton MA 01027",
    "addr:housenumber": "147",
    "addr:postcode": "01027",
    "addr:street": "Northwest Rd",
    "iso:country": "US",
    "sg:address": "147 Northwest Rd",
    "sg:city": "Westhampton",
    "sg:classifiers": [
      {
        "category": "Professional",
        "subcategory": "Business Services",
        "type": "Services"
      }
    ],
    "sg:phone": "+1 413 203 4222",
    "sg:postcode": "01027",
    "sg:province": "MA",
    "sg:tags": [
      "consultant",
      "coach"
    ],
    "wof:name": "Business Services",
    "wof:placetype": "venue"
  },
  "geometry": {"coordinates":[-72.786832,42.33722],"type":"Point"}
}
