{
  "type": "Feature",
  "properties": {
    "iso:country":"US",
    "sg:address":"1671 Worcester Rd Bsmt",
    "sg:city":"Framingham",
    "sg:classifiers":[
        {
            "category":"Real Estate",
            "subcategory":"Real Estate Agent",
            "type":"Services"
        }
    ],
    "sg:phone":"+1 508 879 4474",
    "sg:postcode":"01701",
    "sg:province":"MA",
    "sg:website":"http://www.jeanconsigli.com",
    "wof:name":"Era",
    "wof:placetype":"venue"
},
  "geometry": {"coordinates":[-71.483513,42.29705],"type":"Point"}
}