{
  "type": "Feature",
  "properties": {
    "iso:country":"US",
    "sg:address":"4 Moosehill Rd",
    "sg:city":"East Walpole",
    "sg:classifiers":[
        {
            "category":"Building & Trades",
            "subcategory":"Construction",
            "type":"Services"
        }
    ],
    "sg:phone":"+1   ",
    "sg:postcode":"02032",
    "sg:province":"MA",
    "sg:tags":[
        "contractor"
    ],
    "wof:name":"Budget Blinds Neponset Valley",
    "wof:placetype":"venue"
},
  "geometry": {"coordinates":[-71.214607,42.152846],"type":"Point"}
}