{
  "type": "Feature",
  "properties": {
    "iso:country":"US",
    "sg:address":"63 N Washington St",
    "sg:city":"North Attleboro",
    "sg:classifiers":[
        {
            "category":"Home & Garden",
            "subcategory":"Building Materials",
            "type":"Retail Goods"
        }
    ],
    "sg:phone":"+1 508 699 4019",
    "sg:postcode":"02760",
    "sg:province":"MA",
    "sg:tags":[
        "door",
        "gate",
        "operating",
        "devices"
    ],
    "wof:name":"J P Comp Overhead Doors",
    "wof:placetype":"venue"
},
  "geometry": {"coordinates":[-71.33225899999999,41.983756],"type":"Point"}
}