{
  "type": "Feature",
  "properties": {
    "addr:full": "22 Maple St Danvers MA 01923",
    "addr:housenumber": "22",
    "addr:postcode": "01923",
    "addr:street": "Maple St",
    "iso:country": "US",
    "ovtr:label": "Western Cycle, 89 Maple St Danvers MA US",
    "ovtr:similarity": 2.952078104019165,
    "sg:address": "22 Maple St",
    "sg:city": "Danvers",
    "sg:classifiers": [
      {
        "category": "Shopping",
        "subcategory": "Bicycles \u0026 Sporting Goods",
        "type": "Retail Goods"
      }
    ],
    "sg:phone": "+1 978 774 1685",
    "sg:postcode": "01923",
    "sg:province": "MA",
    "sg:website": "www.western-cycle.com",
    "wof:name": "Western Cycle",
    "wof:placetype": "venue"
  },
  "geometry": {"coordinates":[-70.935774,42.565472],"type":"Point"}
}
