{
  "type": "Feature",
  "properties": {
    "iso:country":"US",
    "sg:address":"22 Maple St",
    "sg:city":"Danvers",
    "sg:classifiers":[
        {
            "category":"Shopping",
            "subcategory":"Bicycles & Sporting Goods",
            "type":"Retail Goods"
        }
    ],
    "sg:phone":"+1 978 774 1685",
    "sg:postcode":"01923",
    "sg:province":"MA",
    "sg:website":"www.western-cycle.com",
    "wof:name":"Western Cycle",
    "wof:placetype":"venue"
},
  "geometry": {"coordinates":[-70.93577399999999,42.565472],"type":"Point"}
}