{
  "type": "Feature",
  "properties": {
    "iso:country":"US",
    "sg:address":"10 Phoenix Row",
    "sg:city":"Haverhill",
    "sg:classifiers":[
        {
            "category":"Social Services",
            "type":"Services"
        }
    ],
    "sg:phone":"+1 978 521 2503",
    "sg:postcode":"01832",
    "sg:province":"MA",
    "sg:tags":[
        "worker"
    ],
    "wof:name":"Teresa Restrepo Licsw",
    "wof:placetype":"venue"
},
  "geometry": {"coordinates":[-71.08316600000001,42.77316],"type":"Point"}
}