{
  "type": "Feature",
  "properties": {
    "addr:full": "177 Commercial St Provincetown MA 02657",
    "addr:housenumber": "177",
    "addr:postcode": "02657",
    "addr:street": "Commercial St",
    "iso:country": "US",
    "ovtr:label": "Bayside Betsy's, 177 Commercial St Provincetown MA US",
    "ovtr:similarity": 1.9546680450439453,
    "sg:address": "177 Commercial St",
    "sg:city": "Provincetown",
    "sg:classifiers": [
      {
        "category": "Restaurant",
        "type": "Food \u0026 Drink"
      }
    ],
    "sg:phone": "+1 508 487 6566",
    "sg:postcode": "02657",
    "sg:province": "MA",
    "sg:website": "www.baysidebetsys.com",
    "wof:name": "Bayside Betsy's",
    "wof:placetype": "venue"
  },
  "geometry": {"coordinates":[-70.189673,42.047955],"type":"Point"}
}
