{
  "type": "Feature",
  "properties": {
    "iso:country":"US",
    "sg:address":"177 Commercial St",
    "sg:city":"Provincetown",
    "sg:classifiers":[
        {
            "category":"Restaurant",
            "type":"Food & Drink"
        }
    ],
    "sg:phone":"+1 508 487 6566",
    "sg:postcode":"02657",
    "sg:province":"MA",
    "sg:website":"www.baysidebetsys.com",
    "wof:name":"Bayside Betsy's",
    "wof:placetype":"venue"
},
  "geometry": {"coordinates":[-70.189673,42.047955],"type":"Point"}
}