{
  "type": "Feature",
  "properties": {
    "addr:full":"26 School St Upton MA 01568",
    "addr:housenumber":"26",
    "addr:postcode":"01568",
    "addr:street":"School St",
    "iso:country":"US",
    "sg:address":"26 School St",
    "sg:city":"Upton",
    "sg:classifiers":[
        {
            "category":"Education",
            "subcategory":"Dance Studio",
            "type":"Public Place"
        }
    ],
    "sg:phone":"+1 508 529 3234",
    "sg:postcode":"01568",
    "sg:province":"MA",
    "sg:tags":[
        "instruction",
        "dancing"
    ],
    "wof:name":"Dance Works",
    "wof:placetype":"venue"
},
  "geometry": {"coordinates":[-71.605705,42.174419],"type":"Point"}
}