{
  "type": "Feature",
  "properties": {
    "addr:full":"236 Water St Pembroke MA 02359",
    "addr:housenumber":"236",
    "addr:postcode":"02359",
    "addr:street":"Water St",
    "iso:country":"US",
    "sg:address":"236 Water St",
    "sg:city":"Pembroke",
    "sg:classifiers":[
        {
            "category":"Shopping",
            "subcategory":"Used Merchandise",
            "type":"Retail Goods"
        }
    ],
    "sg:phone":"+1 781 826 3736",
    "sg:postcode":"02359",
    "sg:province":"MA",
    "wof:name":"Times Past",
    "wof:placetype":"venue"
},
  "geometry": {"coordinates":[-70.779515,42.108452],"type":"Point"}
}