{
  "type": "Feature",
  "properties": {
    "addr:full": "344 Bridge St Northampton MA 01060",
    "addr:housenumber": "344",
    "addr:postcode": "01060",
    "addr:street": "Bridge St",
    "iso:country": "US",
    "sg:address": "344 Bridge St",
    "sg:city": "Northampton",
    "sg:classifiers": [
      {
        "category": "Home \u0026 Garden",
        "subcategory": "Building Materials",
        "type": "Retail Goods"
      },
      {
        "category": "Building \u0026 Trades",
        "subcategory": "Construction",
        "type": "Services"
      }
    ],
    "sg:phone": "+1 413 584 3335",
    "sg:postcode": "01060",
    "sg:province": "MA",
    "sg:tags": [
      "fence-sales",
      "fence",
      "contractor"
    ],
    "wof:name": "Fitzgerald Fences",
    "wof:placetype": "venue"
  },
  "geometry": {"coordinates":[-72.623095,42.330836],"type":"Point"}
}
