{
  "type": "Feature",
  "properties": {
    "addr:full":"254 Dean St Norwood MA 02062",
    "addr:housenumber":"254",
    "addr:postcode":"02062",
    "addr:street":"Dean St",
    "iso:country":"US",
    "sg:address":"254 Dean St",
    "sg:city":"Norwood",
    "sg:classifiers":[
        {
            "category":"Restaurant",
            "type":"Food & Drink"
        }
    ],
    "sg:phone":"+1 781 501 5700",
    "sg:postcode":"02062",
    "sg:province":"MA",
    "sg:tags":[
        "pizza"
    ],
    "wof:name":"Stash's Pizza",
    "wof:placetype":"venue"
},
  "geometry": {"coordinates":[-71.18965900000001,42.178932],"type":"Point"}
}