{
  "type": "Feature",
  "properties": {
    "addr:full": "254 Dean St Norwood MA 02062",
    "addr:housenumber": "254",
    "addr:postcode": "02062",
    "addr:street": "Dean St",
    "iso:country": "US",
    "ovtr:label": "Stash's Pizza of Norwood, 254 Dean St Norwood MA US",
    "ovtr:similarity": 3.671375036239624,
    "sg:address": "254 Dean St",
    "sg:city": "Norwood",
    "sg:classifiers": [
      {
        "category": "Restaurant",
        "type": "Food \u0026 Drink"
      }
    ],
    "sg:phone": "+1 781 501 5700",
    "sg:postcode": "02062",
    "sg:province": "MA",
    "sg:tags": [
      "pizza"
    ],
    "wof:name": "Stash's Pizza",
    "wof:placetype": "venue"
  },
  "geometry": {"coordinates":[-71.189659,42.178932],"type":"Point"}
}
