{
  "type": "Feature",
  "properties": {
    "iso:country":"US",
    "sg:address":"147 Main St",
    "sg:city":"Foxboro",
    "sg:classifiers":[
        {
            "category":"Manufacturing",
            "subcategory":"Signs",
            "type":"Manufacturing & Wholesale Goods"
        }
    ],
    "sg:phone":"+1 508 543 5025",
    "sg:postcode":"02035",
    "sg:province":"MA",
    "wof:name":"Farmer Sign",
    "wof:placetype":"venue"
},
  "geometry": {"coordinates":[-71.261815,42.074955],"type":"Point"}
}