{
  "type": "Feature",
  "properties": {
    "addr:full":"70 Salem Tpke Saugus MA 01906",
    "addr:housenumber":"70",
    "addr:postcode":"01906",
    "addr:street":"Salem Tpke",
    "iso:country":"US",
    "sg:address":"70 Salem Tpke",
    "sg:city":"Saugus",
    "sg:classifiers":[
        {
            "category":"Communications",
            "subcategory":"Radio Station",
            "type":"Services"
        }
    ],
    "sg:phone":"+1 781 231 4927",
    "sg:postcode":"01906",
    "sg:province":"MA",
    "sg:tags":[
        "company",
        "broadcasting"
    ],
    "wof:name":"WROL",
    "wof:placetype":"venue"
},
  "geometry": {"coordinates":[-70.980165,42.449666],"type":"Point"}
}