{
  "type": "Feature",
  "properties": {
    "iso:country":"US",
    "sg:address":"301 Northern Ave",
    "sg:city":"Boston",
    "sg:classifiers":[
        {
            "category":"Professional",
            "subcategory":"Advertising",
            "type":"Services"
        }
    ],
    "sg:phone":"+1 617 542 1160",
    "sg:postcode":"02210",
    "sg:province":"MA",
    "sg:tags":[
        "distributing",
        "sample"
    ],
    "sg:website":"www.harpoonbrewery.com",
    "wof:name":"Harpoon Dist Co",
    "wof:placetype":"venue"
},
  "geometry": {"coordinates":[-71.03762399999999,42.348304],"type":"Point"}
}