{
  "type": "Feature",
  "properties": {
    "iso:country":"US",
    "sg:address":"137 Main St",
    "sg:city":"Ware",
    "sg:classifiers":[
        {
            "category":"Professional",
            "subcategory":"Business Services",
            "type":"Services"
        }
    ],
    "sg:phone":"+1 413 967 9941",
    "sg:postcode":"01082",
    "sg:province":"MA",
    "wof:name":"Deputy Tax Collectors",
    "wof:placetype":"venue"
},
  "geometry": {"coordinates":[-72.243088,42.260734],"type":"Point"}
}