{
  "type": "Feature",
  "properties": {
    "iso:country":"US",
    "sg:address":"120 Winter St",
    "sg:city":"Weymouth",
    "sg:classifiers":[
        {
            "category":"Government",
            "subcategory":"Office",
            "type":"Public Place"
        }
    ],
    "sg:phone":"+1 781 331 9460",
    "sg:postcode":"02188",
    "sg:province":"MA",
    "sg:tags":[
        "village"
    ],
    "sg:website":"www.weymouth.ma.us",
    "wof:name":"Weymouth DPW Administration",
    "wof:placetype":"venue"
},
  "geometry": {"coordinates":[-70.951886,42.200202],"type":"Point"}
}