{
  "type": "Feature",
  "properties": {
    "addr:full":"88 Broad St Lowr 1 Boston MA 02110",
    "addr:housenumber":"88;1",
    "addr:postcode":"02110",
    "addr:street":"Broad St Lowr",
    "iso:country":"US",
    "sg:address":"88 Broad St Lowr 1",
    "sg:city":"Boston",
    "sg:classifiers":[
        {
            "category":"Banks & Credit Unions",
            "subcategory":"Investment Brokerage",
            "type":"Services"
        },
        {
            "category":"Insurance",
            "subcategory":"Hazard Insurance",
            "type":"Services"
        },
        {
            "category":"Banks & Credit Unions",
            "subcategory":"Financial Services",
            "type":"Services"
        }
    ],
    "sg:phone":"+1 617 357 1996",
    "sg:postcode":"02110",
    "sg:province":"MA",
    "sg:tags":[
        "retirement",
        "business",
        "annuity",
        "commercial",
        "plan"
    ],
    "sg:website":"http://www.jarvisbrokerage.com",
    "wof:name":"Jarvis Insurance Brokerage Agency Of Mass. Inc",
    "wof:placetype":"venue"
},
  "geometry": {"coordinates":[-71.052696,42.35741],"type":"Point"}
}