{
  "type": "Feature",
  "properties": {
    "iso:country":"US",
    "sg:address":"231 Albany St",
    "sg:city":"Springfield",
    "sg:phone":"+1 413 746 1110",
    "sg:postcode":"01105",
    "sg:province":"MA",
    "sg:tags":[
        "oil"
    ],
    "wof:name":"U-Save Oil Delivery & Svc",
    "wof:placetype":"venue"
},
  "geometry": {"coordinates":[-72.57208900000001,42.120895],"type":"Point"}
}