{
  "type": "Feature",
  "properties": {
    "iso:country":"US",
    "sg:address":"593 High St",
    "sg:city":"Dedham",
    "sg:classifiers":[
        {
            "category":"Shopping",
            "subcategory":"Books",
            "type":"Retail Goods"
        }
    ],
    "sg:phone":"+1 781 493 6568",
    "sg:postcode":"02026",
    "sg:province":"MA",
    "sg:tags":[
        "dealer"
    ],
    "wof:name":"Blue Bunny",
    "wof:placetype":"venue"
},
  "geometry": {"coordinates":[-71.17403,42.24837],"type":"Point"}
}