{
  "type": "Feature",
  "properties": {
    "addr:full":"21 Forest Ave 2 Greenfield MA 01301",
    "addr:housenumber":"21;2",
    "addr:postcode":"01301",
    "addr:street":"Forest Ave",
    "iso:country":"US",
    "sg:address":"21 Forest Ave 2",
    "sg:city":"Greenfield",
    "sg:classifiers":[
        {
            "category":"Restaurant",
            "type":"Food & Drink"
        }
    ],
    "sg:phone":"+1 413 773 0238",
    "sg:postcode":"01301",
    "sg:province":"MA",
    "wof:name":"Shire Restaurant",
    "wof:placetype":"venue"
},
  "geometry": {"coordinates":[-72.59626799999999,42.599732],"type":"Point"}
}