{
  "type": "Feature",
  "properties": {
    "iso:country":"US",
    "sg:address":"166 East St",
    "sg:city":"Pittsfield",
    "sg:classifiers":[
        {
            "category":"Insurance",
            "subcategory":"Insurance Agent",
            "type":"Services"
        }
    ],
    "sg:phone":"+1 413 447 7376",
    "sg:postcode":"01201",
    "sg:province":"MA",
    "sg:website":"http://www.allianceberkshire.com",
    "wof:name":"Reynolds, Barnes & Hebb Inc",
    "wof:placetype":"venue"
},
  "geometry": {"coordinates":[-73.25,42.447861],"type":"Point"}
}