{
  "type": "Feature",
  "properties": {
    "iso:country":"US",
    "sg:address":"2 High St",
    "sg:city":"Danvers",
    "sg:classifiers":[
        {
            "category":"Real Estate",
            "subcategory":"Real Estate Agent",
            "type":"Services"
        }
    ],
    "sg:phone":"+1 978 777 1090",
    "sg:postcode":"01923",
    "sg:province":"MA",
    "wof:name":"Vernon A Martin Inc",
    "wof:placetype":"venue"
},
  "geometry": {"coordinates":[-70.93495,42.564553],"type":"Point"}
}