{
  "type": "Feature",
  "properties": {
    "iso:country":"US",
    "sg:address":"110 Griggs Rd",
    "sg:city":"Brookline",
    "sg:classifiers":[
        {
            "category":"Wholesale",
            "subcategory":"Non-durable Goods",
            "type":"Manufacturing & Wholesale Goods"
        }
    ],
    "sg:phone":"+1   ",
    "sg:postcode":"02446",
    "sg:province":"MA",
    "wof:name":"Pioneer Distribution Services",
    "wof:placetype":"venue"
},
  "geometry": {"coordinates":[-71.12809799999999,42.338925],"type":"Point"}
}