{
  "type": "Feature",
  "properties": {
    "iso:country":"US",
    "sg:address":"748 Main St",
    "sg:city":"Winchester",
    "sg:classifiers":[
        {
            "category":"Real Estate",
            "subcategory":"Real Estate Services",
            "type":"Services"
        },
        {
            "category":"Real Estate",
            "subcategory":"Real Estate Agent",
            "type":"Services"
        }
    ],
    "sg:phone":"+1 781 625 4249",
    "sg:postcode":"01890",
    "sg:province":"MA",
    "sg:website":"www.northofbostonrealestate.com",
    "wof:name":"Sven Andersen - RE/MAX Leading Edge Real Estate",
    "wof:placetype":"venue"
},
  "geometry": {"coordinates":[-71.139151,42.457899],"type":"Point"}
}