{
  "type": "Feature",
  "properties": {
    "addr:full": "8 Deeringer Rd Chelmsford MA 01824",
    "addr:housenumber": "8",
    "addr:postcode": "01824",
    "addr:street": "Deeringer Rd",
    "iso:country": "US",
    "sg:address": "8 Deeringer Rd",
    "sg:city": "Chelmsford",
    "sg:classifiers": [
      {
        "category": "Shopping",
        "subcategory": "Computers \u0026 Home Electronics",
        "type": "Retail Goods"
      }
    ],
    "sg:phone": "+1 978 244 1100",
    "sg:postcode": "01824",
    "sg:province": "MA",
    "sg:tags": [
      "software"
    ],
    "wof:name": "Solutions \u0026 Svc",
    "wof:placetype": "venue"
  },
  "geometry": {"coordinates":[-71.328148,42.587428],"type":"Point"}
}
