{
  "type": "Feature",
  "properties": {
    "addr:full": "25 Damon Rd Holden MA 01520",
    "addr:housenumber": "25",
    "addr:postcode": "01520",
    "addr:street": "Damon Rd",
    "iso:country": "US",
    "sg:address": "25 Damon Rd",
    "sg:city": "Holden",
    "sg:classifiers": [
      {
        "category": "Arena",
        "subcategory": "Sports Club",
        "type": "Entertainment"
      }
    ],
    "sg:phone": "+1 508 829 0487",
    "sg:postcode": "01520",
    "sg:province": "MA",
    "sg:tags": [
      "soccer"
    ],
    "wof:name": "Holden Youth Soccer Inc",
    "wof:placetype": "venue"
  },
  "geometry": {"coordinates":[-71.856749,42.355022],"type":"Point"}
}
