{
  "type": "Feature",
  "properties": {
    "iso:country":"US",
    "sg:address":"25 Damon Rd",
    "sg:city":"Holden",
    "sg:classifiers":[
        {
            "category":"Arena",
            "subcategory":"Sports Club",
            "type":"Entertainment"
        }
    ],
    "sg:phone":"+1 508 829 0487",
    "sg:postcode":"01520",
    "sg:province":"MA",
    "sg:tags":[
        "soccer"
    ],
    "wof:name":"Holden Youth Soccer Inc",
    "wof:placetype":"venue"
},
  "geometry": {"coordinates":[-71.85674899999999,42.355022],"type":"Point"}
}