{
  "type": "Feature",
  "properties": {
    "iso:country":"US",
    "sg:address":"1193 West Rd",
    "sg:city":"Ashby",
    "sg:classifiers":[
        {
            "category":"Building & Trades",
            "subcategory":"Landscaping Services",
            "type":"Services"
        }
    ],
    "sg:phone":"+1 978 386 7730",
    "sg:postcode":"01431",
    "sg:province":"MA",
    "sg:tags":[
        "snow",
        "removal"
    ],
    "wof:name":"Debettencourts Plowing Sa",
    "wof:placetype":"venue"
},
  "geometry": {"coordinates":[-71.859874,42.706014],"type":"Point"}
}