{
  "type": "Feature",
  "properties": {
    "addr:full": "1 Apple Hill Dr Natick MA 01760",
    "addr:housenumber": "1",
    "addr:postcode": "01760",
    "addr:street": "Apple Hill Dr",
    "iso:country": "US",
    "sg:address": "1 Apple Hill Dr",
    "sg:city": "Natick",
    "sg:classifiers": [
      {
        "category": "Professional",
        "subcategory": "Employment Agencies",
        "type": "Services"
      }
    ],
    "sg:phone": "+1 508 652 0202",
    "sg:postcode": "01760",
    "sg:province": "MA",
    "sg:tags": [
      "opportunity"
    ],
    "wof:name": "C T Browning Assoc Inc",
    "wof:placetype": "venue"
  },
  "geometry": {"coordinates":[-71.349554,42.300566],"type":"Point"}
}
