{
  "type": "Feature",
  "properties": {
    "iso:country":"US",
    "sg:address":"863 Mass Ave",
    "sg:city":"Cambridge",
    "sg:classifiers":[
        {
            "category":"Autos & Motor Vehicles",
            "subcategory":"Automobile Sales",
            "type":"Retail Goods"
        }
    ],
    "sg:phone":"+1 617 388 9914",
    "sg:postcode":"02238",
    "sg:province":"MA",
    "sg:tags":[
        "car"
    ],
    "sg:website":"www.sabalo-xalapa.com.mx",
    "wof:name":"Consuelo",
    "wof:placetype":"venue"
},
  "geometry": {"coordinates":[-71.107218,42.367551],"type":"Point"}
}