{
  "type": "Feature",
  "properties": {
    "addr:full": "449 Cambridge St Allston MA 02134",
    "addr:housenumber": "449",
    "addr:postcode": "02134",
    "addr:street": "Cambridge St",
    "iso:country": "US",
    "sg:address": "449 Cambridge St",
    "sg:city": "Allston",
    "sg:classifiers": [
      {
        "category": "Social Services",
        "type": "Services"
      },
      {
        "category": "Shopping",
        "subcategory": "Used Merchandise",
        "type": "Retail Goods"
      },
      {
        "category": "Banks \u0026 Credit Unions",
        "subcategory": "Bank",
        "type": "Services"
      },
      {
        "category": "Shopping",
        "subcategory": "Thrift Store",
        "type": "Retail Goods"
      },
      {
        "category": "Organizations",
        "subcategory": "Non-profit Organization",
        "type": "Services"
      }
    ],
    "sg:phone": "+1 617 782 2906",
    "sg:postcode": "02134",
    "sg:province": "MA",
    "sg:tags": [
      "shop",
      "foundations-educational",
      "philanthropic",
      "research",
      "resale",
      "second",
      "hand",
      "furniture",
      "charity"
    ],
    "sg:website": "http://www.goodwill.org",
    "wof:name": "Goodwill Stores",
    "wof:placetype": "venue"
  },
  "geometry": {"coordinates":[-71.135719,42.354279],"type":"Point"}
}
