{
  "type": "Feature",
  "properties": {
    "iso:country":"US",
    "sg:address":"449 Cambridge St",
    "sg:city":"Allston",
    "sg:classifiers":[
        {
            "category":"Social Services",
            "type":"Services"
        },
        {
            "category":"Shopping",
            "subcategory":"Used Merchandise",
            "type":"Retail Goods"
        },
        {
            "category":"Banks & Credit Unions",
            "subcategory":"Bank",
            "type":"Services"
        },
        {
            "category":"Shopping",
            "subcategory":"Thrift Store",
            "type":"Retail Goods"
        },
        {
            "category":"Organizations",
            "subcategory":"Non-profit Organization",
            "type":"Services"
        }
    ],
    "sg:phone":"+1 617 782 2906",
    "sg:postcode":"02134",
    "sg:province":"MA",
    "sg:tags":[
        "shop",
        "foundations-educational",
        "philanthropic",
        "research",
        "resale",
        "second",
        "hand",
        "furniture",
        "charity"
    ],
    "sg:website":"http://www.goodwill.org",
    "wof:name":"Goodwill Stores",
    "wof:placetype":"venue"
},
  "geometry": {"coordinates":[-71.13571899999999,42.354279],"type":"Point"}
}