{
  "type": "Feature",
  "properties": {
    "iso:country":"US",
    "sg:address":"227 Center St",
    "sg:city":"Ludlow",
    "sg:classifiers":[
        {
            "category":"Food & Beverages",
            "subcategory":"Groceries & Convenience Stores",
            "type":"Retail Goods"
        }
    ],
    "sg:phone":"+1 413 589 0434",
    "sg:postcode":"01056",
    "sg:province":"MA",
    "wof:name":"O'Connell Convenience & Oil",
    "wof:placetype":"venue"
},
  "geometry": {"coordinates":[-72.483557,42.163516],"type":"Point"}
}