{
  "type": "Feature",
  "properties": {
    "addr:full":"360 Revere Beach Pkwy Revere MA 02151",
    "addr:housenumber":"360",
    "addr:postcode":"02151",
    "addr:street":"Revere Beach Pkwy",
    "iso:country":"US",
    "sg:address":"360 Revere Beach Pkwy",
    "sg:city":"Revere",
    "sg:classifiers":[
        {
            "category":"Building & Trades",
            "subcategory":"Locksmith",
            "type":"Services"
        }
    ],
    "sg:phone":"+1 781 922 9083",
    "sg:postcode":"02151",
    "sg:province":"MA",
    "sg:tags":[
        "key"
    ],
    "wof:name":"A Emergency Locksmith",
    "wof:placetype":"venue"
},
  "geometry": {"coordinates":[-70.99979,42.401944],"type":"Point"}
}