{
  "type": "Feature",
  "properties": {
    "addr:full": "111 Adams Rd Clinton MA 01510",
    "addr:housenumber": "111",
    "addr:postcode": "01510",
    "addr:street": "Adams Rd",
    "iso:country": "US",
    "sg:address": "111 Adams Rd",
    "sg:city": "Clinton",
    "sg:classifiers": [
      {
        "category": "Professional",
        "subcategory": "Business Services",
        "type": "Services"
      }
    ],
    "sg:phone": "+1 978 368 0344",
    "sg:postcode": "01510",
    "sg:province": "MA",
    "sg:tags": [
      "packaging"
    ],
    "wof:name": "Holms Products Corp",
    "wof:placetype": "venue"
  },
  "geometry": {"coordinates":[-71.688777,42.425287],"type":"Point"}
}
