{
  "type": "Feature",
  "properties": {
    "addr:full": "32 Northampton Street Roxbury MA 02118",
    "addr:housenumber": "32",
    "addr:postcode": "02118",
    "addr:street": "Northampton Street",
    "iso:country": "US",
    "sg:address": "32 Northampton Street",
    "sg:city": "Roxbury",
    "sg:classifiers": [
      {
        "category": "Retail",
        "subcategory": "Auto Repair",
        "type": "Services"
      }
    ],
    "sg:phone": "+1 617 427 8585",
    "sg:postcode": "02118",
    "sg:province": "MA",
    "sg:tags": [
      "body",
      "painting",
      "repairing",
      "automobile"
    ],
    "wof:name": "V \u0026 N Autobody Repair",
    "wof:placetype": "venue"
  },
  "geometry": {"coordinates":[-71.075174,42.333445],"type":"Point"}
}
