{
  "type": "Feature",
  "properties": {
    "iso:country":"US",
    "sg:address":"505 Liberty St",
    "sg:city":"Hanson",
    "sg:classifiers":[
        {
            "category":"Government",
            "subcategory":"Fire Station",
            "type":"Public Place"
        }
    ],
    "sg:phone":"+1 781 293 9571",
    "sg:postcode":"02341",
    "sg:province":"MA",
    "sg:tags":[
        "department"
    ],
    "wof:name":"Hanson Fire Dept",
    "wof:placetype":"venue"
},
  "geometry": {"coordinates":[-70.86493400000001,42.065368],"type":"Point"}
}