{
  "type": "Feature",
  "properties": {
    "iso:country":"US",
    "sg:address":"70 Shawmut Rd",
    "sg:city":"Canton",
    "sg:classifiers":[
        {
            "category":"Professional",
            "subcategory":"Testing Lab",
            "type":"Services"
        }
    ],
    "sg:phone":"+1 781 401 9999",
    "sg:postcode":"02021",
    "sg:province":"MA",
    "sg:tags":[
        "laboratory"
    ],
    "sg:website":"www.rjhassociates.net",
    "wof:name":"Lapuck Labs Inc",
    "wof:placetype":"venue"
},
  "geometry": {"coordinates":[-71.151391,42.187353],"type":"Point"}
}