{
  "type": "Feature",
  "properties": {
    "addr:full":"60 Scenic Rd Westfield MA 01085",
    "addr:housenumber":"60",
    "addr:postcode":"01085",
    "addr:street":"Scenic Rd",
    "iso:country":"US",
    "sg:address":"60 Scenic Rd",
    "sg:city":"Westfield",
    "sg:classifiers":[
        {
            "category":"Building & Trades",
            "subcategory":"Construction",
            "type":"Services"
        }
    ],
    "sg:phone":"+1 413 562 4732",
    "sg:postcode":"01085",
    "sg:province":"MA",
    "sg:tags":[
        "general",
        "contractor"
    ],
    "wof:name":"Windows America",
    "wof:placetype":"venue"
},
  "geometry": {"coordinates":[-72.735404,42.184774],"type":"Point"}
}