{
  "type": "Feature",
  "properties": {
    "addr:full":"14 N Main St Middleton MA 01949",
    "addr:housenumber":"14",
    "addr:postcode":"01949",
    "addr:street":"N Main St",
    "iso:country":"US",
    "sg:address":"14 N Main St",
    "sg:city":"Middleton",
    "sg:classifiers":[
        {
            "category":"Government",
            "subcategory":"Office",
            "type":"Public Place"
        }
    ],
    "sg:phone":"+1 978 774 6372",
    "sg:postcode":"01949",
    "sg:province":"MA",
    "wof:name":"Correctional Office",
    "wof:placetype":"venue"
},
  "geometry": {"coordinates":[-71.01594,42.595326],"type":"Point"}
}