{
  "type": "Feature",
  "properties": {
    "iso:country":"US",
    "sg:address":"46 Elm St",
    "sg:city":"Pittsfield",
    "sg:classifiers":[
        {
            "category":"Retail",
            "subcategory":"Repair Shop",
            "type":"Services"
        }
    ],
    "sg:phone":"+1 413 499 7262",
    "sg:postcode":"01201",
    "sg:province":"MA",
    "sg:tags":[
        "lock",
        "locksmith"
    ],
    "wof:name":"O'Brien Locksmithing",
    "wof:placetype":"venue"
},
  "geometry": {"coordinates":[-73.243973,42.445124],"type":"Point"}
}