{
  "type": "Feature",
  "properties": {
    "addr:full":"79 Worcester St North Grafton MA 01536",
    "addr:housenumber":"79",
    "addr:postcode":"01536",
    "addr:street":"Worcester St",
    "iso:country":"US",
    "sg:address":"79 Worcester St",
    "sg:city":"North Grafton",
    "sg:classifiers":[
        {
            "category":"Personal",
            "subcategory":"Beauty Salon",
            "type":"Services"
        }
    ],
    "sg:phone":"+1 508 839 5958",
    "sg:postcode":"01536",
    "sg:province":"MA",
    "wof:name":"Studio 79",
    "wof:placetype":"venue"
},
  "geometry": {"coordinates":[-71.69177999999999,42.214825],"type":"Point"}
}