{
  "type": "Feature",
  "properties": {
    "iso:country":"US",
    "sg:address":"817 Gifford Rd",
    "sg:city":"Westport",
    "sg:classifiers":[
        {
            "category":"Local Transit",
            "type":"Transportation"
        }
    ],
    "sg:phone":"+1 508 636 8185",
    "sg:postcode":"02790",
    "sg:province":"MA",
    "sg:tags":[
        "airport"
    ],
    "wof:name":"Coastal Livery Of Westport",
    "wof:placetype":"venue"
},
  "geometry": {"coordinates":[-71.06071300000001,41.621498],"type":"Point"}
}