{
  "type": "Feature",
  "properties": {
    "iso:country":"US",
    "sg:address":"180 Blue Hill Ave",
    "sg:city":"Milton",
    "sg:classifiers":[
        {
            "category":"Organizations",
            "subcategory":"Religious Organization",
            "type":"Services"
        }
    ],
    "sg:phone":"+1 617 698 3394",
    "sg:postcode":"02186",
    "sg:province":"MA",
    "sg:tags":[
        "synagogue"
    ],
    "wof:name":"Temple Shalom Of Milton",
    "wof:placetype":"venue"
},
  "geometry": {"coordinates":[-71.097223,42.259637],"type":"Point"}
}