{
  "type": "Feature",
  "properties": {
    "iso:country":"US",
    "sg:address":"455 W Center St",
    "sg:city":"West Bridgewater",
    "sg:classifiers":[
        {
            "category":"Professional",
            "subcategory":"Lawyer & Legal Services",
            "type":"Services"
        }
    ],
    "sg:phone":"+1 508 584 2225",
    "sg:postcode":"02379",
    "sg:province":"MA",
    "sg:tags":[
        "attorney"
    ],
    "wof:name":"Michael S Cahill Law Offices",
    "wof:placetype":"venue"
},
  "geometry": {"coordinates":[-71.036624,42.015603],"type":"Point"}
}