{
  "type": "Feature",
  "properties": {
    "iso:country":"US",
    "sg:address":"32 Marlboro St",
    "sg:city":"Hudson",
    "sg:classifiers":[
        {
            "category":"Professional",
            "type":"Services"
        }
    ],
    "sg:phone":"+1 978 562 3666",
    "sg:postcode":"01749",
    "sg:province":"MA",
    "sg:tags":[
        "establishment"
    ],
    "wof:name":"Rykbost Corp",
    "wof:placetype":"venue"
},
  "geometry": {"coordinates":[-71.549184,42.383483],"type":"Point"}
}