{
  "type": "Feature",
  "properties": {
    "iso:country":"US",
    "sg:address":"180 Boston Post Rd",
    "sg:city":"Weston",
    "sg:classifiers":[
        {
            "category":"Government",
            "subcategory":"Police Station",
            "type":"Public Place"
        }
    ],
    "sg:phone":"+1 781 893 4803",
    "sg:postcode":"02493",
    "sg:province":"MA",
    "sg:tags":[
        "department"
    ],
    "sg:website":"www.weston.org",
    "wof:name":"Weston Police Dept",
    "wof:placetype":"venue"
},
  "geometry": {"coordinates":[-71.27671599999999,42.367357],"type":"Point"}
}