{
  "type": "Feature",
  "properties": {
    "addr:full": "68 Prescott St Worcester MA 01605",
    "addr:housenumber": "68",
    "addr:postcode": "01605",
    "addr:street": "Prescott St",
    "iso:country": "US",
    "sg:address": "68 Prescott St",
    "sg:city": "Worcester",
    "sg:classifiers": [
      {
        "category": "Building \u0026 Trades",
        "subcategory": "Construction",
        "type": "Services"
      }
    ],
    "sg:phone": "+1 508 755 1666",
    "sg:postcode": "01605",
    "sg:province": "MA",
    "sg:tags": [
      "general",
      "contractor"
    ],
    "wof:name": "Consigli Construction Co",
    "wof:placetype": "venue"
  },
  "geometry": {"coordinates":[-71.799518,42.276394],"type":"Point"}
}
