{
  "type": "Feature",
  "properties": {
    "iso:country":"US",
    "sg:address":"68 Prescott St",
    "sg:city":"Worcester",
    "sg:classifiers":[
        {
            "category":"Building & Trades",
            "subcategory":"Construction",
            "type":"Services"
        }
    ],
    "sg:phone":"+1 508 755 1666",
    "sg:postcode":"01605",
    "sg:province":"MA",
    "sg:tags":[
        "general",
        "contractor"
    ],
    "wof:name":"Consigli Construction Co",
    "wof:placetype":"venue"
},
  "geometry": {"coordinates":[-71.79951800000001,42.276394],"type":"Point"}
}