{
  "type": "Feature",
  "properties": {
    "addr:full": "64 Willard St Quincy MA 02169",
    "addr:housenumber": "64",
    "addr:postcode": "02169",
    "addr:street": "Willard St",
    "iso:country": "US",
    "sg:address": "64 Willard St",
    "sg:city": "Quincy",
    "sg:classifiers": [
      {
        "category": "Building \u0026 Trades",
        "subcategory": "Construction",
        "type": "Services"
      }
    ],
    "sg:phone": "+1   ",
    "sg:postcode": "02169",
    "sg:province": "MA",
    "sg:tags": [
      "contractor"
    ],
    "wof:name": "Delco Insulation Inc",
    "wof:placetype": "venue"
  },
  "geometry": {"coordinates":[-71.038068,42.253748],"type":"Point"}
}
