{
  "type": "Feature",
  "properties": {
    "addr:full":"327 Newbury St Boston MA 02115",
    "addr:housenumber":"327",
    "addr:postcode":"02115",
    "addr:street":"Newbury St",
    "iso:country":"US",
    "sg:address":"327 Newbury St",
    "sg:city":"Boston",
    "sg:classifiers":[
        {
            "category":"Retail",
            "subcategory":"Repair Shop",
            "type":"Services"
        }
    ],
    "sg:phone":"+1 617 208 1173",
    "sg:postcode":"02115",
    "sg:province":"MA",
    "sg:tags":[
        "lock",
        "locksmith"
    ],
    "wof:name":"1 Emerg 7 Day Locksmith",
    "wof:placetype":"venue"
},
  "geometry": {"coordinates":[-71.08787100000001,42.348297],"type":"Point"}
}