{
  "type": "Feature",
  "properties": {
    "iso:country":"US",
    "sg:address":"48 Cedar St",
    "sg:city":"Worcester",
    "sg:classifiers":[
        {
            "category":"Health Services",
            "subcategory":"Health Practitioner",
            "type":"Services"
        }
    ],
    "sg:phone":"+1 508 757 3292",
    "sg:postcode":"01609",
    "sg:province":"MA",
    "sg:tags":[
        "psychologist"
    ],
    "wof:name":"Paul Rosen",
    "wof:placetype":"venue"
},
  "geometry": {"coordinates":[-71.81155,42.266872],"type":"Point"}
}