{
  "type": "Feature",
  "properties": {
    "addr:full":"60 State Street Boston MA 02109",
    "addr:housenumber":"60",
    "addr:postcode":"02109",
    "addr:street":"State Street",
    "iso:country":"US",
    "sg:address":"60 State Street",
    "sg:city":"Boston",
    "sg:classifiers":[
        {
            "category":"Health Services",
            "subcategory":"Doctor",
            "type":"Services"
        },
        {
            "category":"Personal",
            "subcategory":"Tattoo Parlor",
            "type":"Services"
        },
        {
            "category":"Professional",
            "subcategory":"Lawyer & Legal Services",
            "type":"Services"
        }
    ],
    "sg:phone":"+1 617 526 6000",
    "sg:postcode":"02109",
    "sg:province":"MA",
    "sg:tags":[
        "practice",
        "family"
    ],
    "wof:name":"Rodenberger Timothy C Lwyr",
    "wof:placetype":"venue"
},
  "geometry": {"coordinates":[-71.056072,42.359011],"type":"Point"}
}