{
  "type": "Feature",
  "properties": {
    "addr:full": "66 Leonard St Ste 1F1 Belmont MA 02478",
    "addr:housenumber": "66",
    "addr:postcode": "02478",
    "addr:street": "Leonard St Ste 1F1",
    "iso:country": "US",
    "sg:address": "66 Leonard St Ste 1F1",
    "sg:city": "Belmont",
    "sg:classifiers": [
      {
        "category": "Farming",
        "subcategory": "Fish \u0026 Marine Products",
        "type": "Manufacturing \u0026 Wholesale Goods"
      },
      {
        "category": "Retail",
        "subcategory": "Repair Shop",
        "type": "Services"
      },
      {
        "category": "Professional",
        "subcategory": "Art Services",
        "type": "Services"
      }
    ],
    "sg:phone": "+1 617 484 4480",
    "sg:postcode": "02478",
    "sg:province": "MA",
    "sg:tags": [
      "picture",
      "frame",
      "restoration",
      "framing"
    ],
    "sg:website": "http://www.framehut.com",
    "wof:name": "The Frame Hut Inc",
    "wof:placetype": "venue"
  },
  "geometry": {"coordinates":[-71.175194,42.397701],"type":"Point"}
}
