{
  "type": "Feature",
  "properties": {
    "addr:full": "19 Heard St Waltham MA 02453",
    "addr:housenumber": "19",
    "addr:postcode": "02453",
    "addr:street": "Heard St",
    "iso:country": "US",
    "sg:address": "19 Heard St",
    "sg:city": "Waltham",
    "sg:classifiers": [
      {
        "category": "Retail",
        "subcategory": "Auto Repair",
        "type": "Services"
      }
    ],
    "sg:phone": "+1 781 893 9819",
    "sg:postcode": "02453",
    "sg:province": "MA",
    "sg:tags": [
      "repairing",
      "automobile"
    ],
    "wof:name": "Dons's Auto Repair",
    "wof:placetype": "venue"
  },
  "geometry": {"coordinates":[-71.230171,42.375852],"type":"Point"}
}
