{
  "type": "Feature",
  "properties": {
    "addr:full": "44 Mattakeesett St Pembroke MA 02359",
    "addr:housenumber": "44",
    "addr:postcode": "02359",
    "addr:street": "Mattakeesett St",
    "iso:country": "US",
    "sg:address": "44 Mattakeesett St",
    "sg:city": "Pembroke",
    "sg:classifiers": [
      {
        "category": "Home \u0026 Garden",
        "subcategory": "Hardware",
        "type": "Retail Goods"
      }
    ],
    "sg:phone": "+1 781 293 0560",
    "sg:postcode": "02359",
    "sg:province": "MA",
    "wof:name": "Rock's Ace Hardware",
    "wof:placetype": "venue"
  },
  "geometry": {"coordinates":[-70.81618,42.066949],"type":"Point"}
}
