{
  "type": "Feature",
  "properties": {
    "iso:country":"US",
    "sg:address":"134 Billerica Ave",
    "sg:city":"North Billerica",
    "sg:classifiers":[
        {
            "category":"Manufacturing",
            "subcategory":"Food",
            "type":"Manufacturing & Wholesale Goods"
        }
    ],
    "sg:phone":"+1 978 454 8811",
    "sg:postcode":"01862",
    "sg:province":"MA",
    "sg:tags":[
        "rendering",
        "company"
    ],
    "wof:name":"Baker Commodities Inc",
    "wof:placetype":"venue"
},
  "geometry": {"coordinates":[-71.28345299999999,42.602718],"type":"Point"}
}