{
  "type": "Feature",
  "properties": {
    "addr:full": "134 Billerica Ave North Billerica MA 01862",
    "addr:housenumber": "134",
    "addr:postcode": "01862",
    "addr:street": "Billerica Ave North",
    "iso:country": "US",
    "ovtr:label": "Baker Commodities Inc, 134 Billerica Ave North Billerica MA US",
    "ovtr:similarity": 2.040447950363159,
    "sg:address": "134 Billerica Ave",
    "sg:city": "North Billerica",
    "sg:classifiers": [
      {
        "category": "Manufacturing",
        "subcategory": "Food",
        "type": "Manufacturing \u0026 Wholesale Goods"
      }
    ],
    "sg:phone": "+1 978 454 8811",
    "sg:postcode": "01862",
    "sg:province": "MA",
    "sg:tags": [
      "rendering",
      "company"
    ],
    "wof:name": "Baker Commodities Inc",
    "wof:placetype": "venue"
  },
  "geometry": {"coordinates":[-71.283453,42.602718],"type":"Point"}
}
