{
  "type": "Feature",
  "properties": {
    "iso:country":"US",
    "sg:address":"130 Columbia St",
    "sg:city":"Adams",
    "sg:classifiers":[
        {
            "category":"Building & Trades",
            "subcategory":"Cleaning & Sanitation",
            "type":"Services"
        }
    ],
    "sg:phone":"+1 413 743 4726",
    "sg:postcode":"01220",
    "sg:province":"MA",
    "sg:tags":[
        "janitor"
    ],
    "wof:name":"Area Cleaning",
    "wof:placetype":"venue"
},
  "geometry": {"coordinates":[-73.114082,42.633197],"type":"Point"}
}