{
  "type": "Feature",
  "properties": {
    "addr:full":"9 Salros Rd Nantucket MA 02554",
    "addr:housenumber":"9",
    "addr:postcode":"02554",
    "addr:street":"Salros Rd",
    "iso:country":"US",
    "sg:address":"9 Salros Rd",
    "sg:city":"Nantucket",
    "sg:classifiers":[
        {
            "category":"Shopping",
            "subcategory":"Party Supplies",
            "type":"Retail Goods"
        },
        {
            "category":"Retail",
            "subcategory":"Auto Rental",
            "type":"Services"
        },
        {
            "category":"Taxi",
            "type":"Transportation"
        },
        {
            "category":"Airport",
            "type":"Transportation"
        }
    ],
    "sg:phone":"+1 508 825 9793",
    "sg:postcode":"02554",
    "sg:province":"MA",
    "sg:tags":[
        "limousine",
        "wedding"
    ],
    "sg:website":"http://www.cranberrytransportation.com",
    "wof:name":"Cranberry Transportation Services",
    "wof:placetype":"venue"
},
  "geometry": {"coordinates":[-70.106942,41.265112],"type":"Point"}
}