{
  "type": "Feature",
  "properties": {
    "iso:country":"US",
    "sg:address":"45 Crescent Dr",
    "sg:city":"Bridgewater",
    "sg:classifiers":[
        {
            "category":"Professional",
            "subcategory":"Management & Consulting",
            "type":"Services"
        }
    ],
    "sg:phone":"+1   ",
    "sg:postcode":"02324",
    "sg:province":"MA",
    "sg:tags":[
        "business"
    ],
    "wof:name":"Hewitson",
    "wof:placetype":"venue"
},
  "geometry": {"coordinates":[-70.983757,41.980775],"type":"Point"}
}