{
  "type": "Feature",
  "properties": {
    "iso:country":"US",
    "sg:address":"150B Main Street",
    "sg:city":"Spencer",
    "sg:classifiers":[
        {
            "category":"Bakery",
            "type":"Food & Drink"
        }
    ],
    "sg:phone":"+1 508 885 6030",
    "sg:postcode":"01562",
    "sg:province":"MA",
    "sg:website":"www.oomascookiejar.com",
    "wof:name":"Ooma's Cookie Jar",
    "wof:placetype":"venue"
},
  "geometry": {"coordinates":[-71.993672,42.2439],"type":"Point"}
}