{
  "type": "Feature",
  "properties": {
    "iso:country":"US",
    "sg:address":"1661 Worcester Rd",
    "sg:city":"Framingham",
    "sg:classifiers":[
        {
            "category":"Professional",
            "subcategory":"Employment Agencies",
            "type":"Services"
        }
    ],
    "sg:phone":"+1 508 620 1774",
    "sg:postcode":"01701",
    "sg:province":"MA",
    "sg:tags":[
        "nursing",
        "for",
        "contractor",
        "temp",
        "home",
        "help"
    ],
    "wof:name":"Temp Solutions of New England",
    "wof:placetype":"venue"
},
  "geometry": {"coordinates":[-71.47868699999999,42.296842],"type":"Point"}
}