{
  "type": "Feature",
  "properties": {
    "iso:country":"US",
    "sg:address":"226 Calvary St",
    "sg:city":"Waltham",
    "sg:classifiers":[
        {
            "category":"Building & Trades",
            "subcategory":"Equipment Rental",
            "type":"Services"
        }
    ],
    "sg:phone":"+1 781 891 9800",
    "sg:postcode":"02453",
    "sg:province":"MA",
    "sg:tags":[
        "audio",
        "leasing"
    ],
    "wof:name":"Computer & Image Magnification",
    "wof:placetype":"venue"
},
  "geometry": {"coordinates":[-71.220552,42.366973],"type":"Point"}
}