{
  "type": "Feature",
  "properties": {
    "iso:country":"US",
    "sg:address":"4 Sun Island Rd",
    "sg:city":"Nantucket",
    "sg:classifiers":[
        {
            "category":"Retail",
            "subcategory":"Auto Repair",
            "type":"Services"
        }
    ],
    "sg:phone":"+1 508 325 4255",
    "sg:postcode":"02554",
    "sg:province":"MA",
    "sg:tags":[
        "repairing",
        "automobile"
    ],
    "wof:name":"Jerry's Automotive Care",
    "wof:placetype":"venue"
},
  "geometry": {"coordinates":[-70.057778,41.26463],"type":"Point"}
}