{
  "type": "Feature",
  "properties": {
    "iso:country":"US",
    "sg:address":"448 Andover St",
    "sg:city":"Lawrence",
    "sg:classifiers":[
        {
            "category":"Home & Garden",
            "subcategory":"Furniture",
            "type":"Retail Goods"
        }
    ],
    "sg:phone":"+1 978 688 2225",
    "sg:postcode":"01843",
    "sg:province":"MA",
    "sg:tags":[
        "top",
        "counter"
    ],
    "sg:website":"www.napolitanogranite.com",
    "wof:name":"Napolitano Marble & Granite",
    "wof:placetype":"venue"
},
  "geometry": {"coordinates":[-71.16444799999999,42.692838],"type":"Point"}
}