{
  "type": "Feature",
  "properties": {
    "addr:full": "448 Andover St Lawrence MA 01843",
    "addr:housenumber": "448",
    "addr:postcode": "01843",
    "addr:street": "Andover St",
    "iso:country": "US",
    "sg:address": "448 Andover St",
    "sg:city": "Lawrence",
    "sg:classifiers": [
      {
        "category": "Home \u0026 Garden",
        "subcategory": "Furniture",
        "type": "Retail Goods"
      }
    ],
    "sg:phone": "+1 978 688 2225",
    "sg:postcode": "01843",
    "sg:province": "MA",
    "sg:tags": [
      "top",
      "counter"
    ],
    "sg:website": "www.napolitanogranite.com",
    "wof:name": "Napolitano Marble \u0026 Granite",
    "wof:placetype": "venue"
  },
  "geometry": {"coordinates":[-71.164448,42.692838],"type":"Point"}
}
