{
  "type": "Feature",
  "properties": {
    "iso:country":"US",
    "sg:address":"328 Sea St",
    "sg:city":"Hyannis",
    "sg:classifiers":[
        {
            "category":"Travel",
            "subcategory":"Bed & Breakfast",
            "type":"Entertainment"
        }
    ],
    "sg:phone":"+1 508 778 4278",
    "sg:postcode":"02601",
    "sg:province":"MA",
    "sg:website":"www.capecod-greenmtn-bb.com",
    "wof:name":"Green Mountain Inn Bed and Breakfast",
    "wof:placetype":"venue"
},
  "geometry": {"coordinates":[-70.290604,41.640202],"type":"Point"}
}