{
  "type": "Feature",
  "properties": {
    "addr:full": "328 Sea St Hyannis MA 02601",
    "addr:housenumber": "328",
    "addr:postcode": "02601",
    "addr:street": "Sea St",
    "iso:country": "US",
    "sg:address": "328 Sea St",
    "sg:city": "Hyannis",
    "sg:classifiers": [
      {
        "category": "Travel",
        "subcategory": "Bed \u0026 Breakfast",
        "type": "Entertainment"
      }
    ],
    "sg:phone": "+1 508 778 4278",
    "sg:postcode": "02601",
    "sg:province": "MA",
    "sg:website": "www.capecod-greenmtn-bb.com",
    "wof:name": "Green Mountain Inn Bed and Breakfast",
    "wof:placetype": "venue"
  },
  "geometry": {"coordinates":[-70.290604,41.640202],"type":"Point"}
}
