{
  "type": "Feature",
  "properties": {
    "iso:country":"US",
    "sg:address":"228 East St",
    "sg:city":"Easthampton",
    "sg:classifiers":[
        {
            "category":"Professional",
            "subcategory":"Research",
            "type":"Services"
        }
    ],
    "sg:phone":"+1 413 527 1928",
    "sg:postcode":"01027",
    "sg:province":"MA",
    "sg:tags":[
        "nonphysical",
        "commercial",
        "library"
    ],
    "wof:name":"Polidea Co",
    "wof:placetype":"venue"
},
  "geometry": {"coordinates":[-72.639679,42.276379],"type":"Point"}
}