{
  "type": "Feature",
  "properties": {
    "addr:full": "1 Lamplighter Ln Springfield MA 01119",
    "addr:housenumber": "1",
    "addr:postcode": "01119",
    "addr:street": "Lamplighter Ln",
    "iso:country": "US",
    "sg:address": "1 Lamplighter Ln",
    "sg:city": "Springfield",
    "sg:classifiers": [
      {
        "category": "Building \u0026 Trades",
        "subcategory": "Plumbing",
        "type": "Services"
      }
    ],
    "sg:phone": "+1   ",
    "sg:postcode": "01119",
    "sg:province": "MA",
    "sg:tags": [
      "contractor"
    ],
    "wof:name": "Bobs Plumbing Service",
    "wof:placetype": "venue"
  },
  "geometry": {"coordinates":[-72.509153,42.134615],"type":"Point"}
}
