{
  "type": "Feature",
  "properties": {
    "iso:country":"US",
    "sg:address":"1 Lamplighter Ln",
    "sg:city":"Springfield",
    "sg:classifiers":[
        {
            "category":"Building & Trades",
            "subcategory":"Plumbing",
            "type":"Services"
        }
    ],
    "sg:phone":"+1   ",
    "sg:postcode":"01119",
    "sg:province":"MA",
    "sg:tags":[
        "contractor"
    ],
    "wof:name":"Bobs Plumbing Service",
    "wof:placetype":"venue"
},
  "geometry": {"coordinates":[-72.509153,42.134615],"type":"Point"}
}