{
  "type": "Feature",
  "properties": {
    "addr:full":"185 Bedford St Lexington MA 02420",
    "addr:housenumber":"185",
    "addr:postcode":"02420",
    "addr:street":"Bedford St",
    "iso:country":"US",
    "sg:address":"185 Bedford St",
    "sg:city":"Lexington",
    "sg:classifiers":[
        {
            "category":"Building & Trades",
            "subcategory":"Locksmith",
            "type":"Services"
        }
    ],
    "sg:phone":"+1 781 515 1009",
    "sg:postcode":"02420",
    "sg:province":"MA",
    "sg:tags":[
        "key"
    ],
    "wof:name":"Emergency Locksmith",
    "wof:placetype":"venue"
},
  "geometry": {"coordinates":[-71.23792299999999,42.459274],"type":"Point"}
}