{
  "type": "Feature",
  "properties": {
    "iso:country":"US",
    "sg:address":"661 S Main St",
    "sg:city":"Webster",
    "sg:classifiers":[
        {
            "category":"Manufacturing",
            "subcategory":"Tools & Machinery",
            "type":"Manufacturing & Wholesale Goods"
        }
    ],
    "sg:phone":"+1 508 949 2968",
    "sg:postcode":"01570",
    "sg:province":"MA",
    "sg:tags":[
        "equipment",
        "woodworking",
        "supply"
    ],
    "sg:website":"www.inline.com",
    "wof:name":"In-Line Industries",
    "wof:placetype":"venue"
},
  "geometry": {"coordinates":[-71.87903900000001,42.052354],"type":"Point"}
}