{
  "type": "Feature",
  "properties": {
    "addr:full": "661 S Main St Webster MA 01570",
    "addr:housenumber": "661",
    "addr:postcode": "01570",
    "addr:street": "S Main St",
    "iso:country": "US",
    "sg:address": "661 S Main St",
    "sg:city": "Webster",
    "sg:classifiers": [
      {
        "category": "Manufacturing",
        "subcategory": "Tools \u0026 Machinery",
        "type": "Manufacturing \u0026 Wholesale Goods"
      }
    ],
    "sg:phone": "+1 508 949 2968",
    "sg:postcode": "01570",
    "sg:province": "MA",
    "sg:tags": [
      "equipment",
      "woodworking",
      "supply"
    ],
    "sg:website": "www.inline.com",
    "wof:name": "In-Line Industries",
    "wof:placetype": "venue"
  },
  "geometry": {"coordinates":[-71.879039,42.052354],"type":"Point"}
}
