{
  "type": "Feature",
  "properties": {
    "iso:country":"US",
    "sg:address":"277 Saint Georges St",
    "sg:city":"Duxbury",
    "sg:classifiers":[
        {
            "category":"Food & Beverages",
            "subcategory":"Groceries & Convenience Stores",
            "type":"Retail Goods"
        }
    ],
    "sg:phone":"+1 781 934 2921",
    "sg:postcode":"02332",
    "sg:province":"MA",
    "sg:tags":[
        "market"
    ],
    "wof:name":"Millbrook Market",
    "wof:placetype":"venue"
},
  "geometry": {"coordinates":[-70.68652899999999,42.048894],"type":"Point"}
}