{
  "type": "Feature",
  "properties": {
    "addr:full": "277 Saint Georges St Duxbury MA 02332",
    "addr:housenumber": "277",
    "addr:postcode": "02332",
    "addr:street": "Saint Georges St",
    "iso:country": "US",
    "sg:address": "277 Saint Georges St",
    "sg:city": "Duxbury",
    "sg:classifiers": [
      {
        "category": "Food \u0026 Beverages",
        "subcategory": "Groceries \u0026 Convenience Stores",
        "type": "Retail Goods"
      }
    ],
    "sg:phone": "+1 781 934 2921",
    "sg:postcode": "02332",
    "sg:province": "MA",
    "sg:tags": [
      "market"
    ],
    "wof:name": "Millbrook Market",
    "wof:placetype": "venue"
  },
  "geometry": {"coordinates":[-70.686529,42.048894],"type":"Point"}
}
