{
  "type": "Feature",
  "properties": {
    "addr:full": "34 Bow St 1st Fl Somerville MA 02143",
    "addr:housenumber": "34",
    "addr:postcode": "02143",
    "addr:street": "Bow St",
    "iso:country": "US",
    "sg:address": "34 Bow St 1st Fl",
    "sg:city": "Somerville",
    "sg:classifiers": [
      {
        "category": "Sports \u0026 Exercise",
        "subcategory": "Gym",
        "type": "Entertainment"
      }
    ],
    "sg:phone": "+1 617 440 5947",
    "sg:postcode": "02143",
    "sg:province": "MA",
    "sg:tags": [
      "yoga"
    ],
    "sg:website": "www.bowstreetyoga.com",
    "wof:name": "Bow Street Yoga",
    "wof:placetype": "venue"
  },
  "geometry": {"coordinates":[-71.097161,42.3809],"type":"Point"}
}
