{
  "type": "Feature",
  "properties": {
    "iso:country":"US",
    "sg:address":"908 Salem St",
    "sg:city":"Malden",
    "sg:classifiers":[
        {
            "category":"Insurance",
            "subcategory":"Insurance Agent",
            "type":"Services"
        }
    ],
    "sg:phone":"+1   ",
    "sg:postcode":"02148",
    "sg:province":"MA",
    "wof:name":"Trischitta Frank P Insur Agcy",
    "wof:placetype":"venue"
},
  "geometry": {"coordinates":[-71.039337,42.434169],"type":"Point"}
}