{
  "type": "Feature",
  "properties": {
    "iso:country":"US",
    "sg:address":"3 Maple St",
    "sg:city":"Natick",
    "sg:classifiers":[
        {
            "category":"Personal",
            "type":"Services"
        }
    ],
    "sg:phone":"+1 508 652 9988",
    "sg:postcode":"01760",
    "sg:province":"MA",
    "sg:tags":[
        "program",
        "physical",
        "exercise",
        "fitness"
    ],
    "wof:name":"Pro Active Fitness Personal",
    "wof:placetype":"venue"
},
  "geometry": {"coordinates":[-71.3522,42.281736],"type":"Point"}
}