{
  "type": "Feature",
  "properties": {
    "addr:full":"10 High Street Boston MA 02110",
    "addr:housenumber":"10",
    "addr:postcode":"02110",
    "addr:street":"High Street",
    "iso:country":"US",
    "sg:address":"10 High Street",
    "sg:city":"Boston",
    "sg:classifiers":[
        {
            "category":"Professional",
            "subcategory":"Lawyer & Legal Services",
            "type":"Services"
        }
    ],
    "sg:phone":"+1 617 556 9995",
    "sg:postcode":"02110",
    "sg:province":"MA",
    "wof:name":"Schneiderman Scot Lwyr",
    "wof:placetype":"venue"
},
  "geometry": {"coordinates":[-71.056797,42.353363],"type":"Point"}
}