{
  "type": "Feature",
  "properties": {
    "addr:full": "232 Atlantic St Gloucester MA 01930",
    "addr:housenumber": "232",
    "addr:postcode": "01930",
    "addr:street": "Atlantic St",
    "iso:country": "US",
    "sg:address": "232 Atlantic St",
    "sg:city": "Gloucester",
    "sg:classifiers": [
      {
        "category": "Recreation",
        "type": "Entertainment"
      }
    ],
    "sg:phone": "+1 978 282 1974",
    "sg:postcode": "01930",
    "sg:province": "MA",
    "sg:tags": [
      "concessionaire"
    ],
    "wof:name": "MNS Concession",
    "wof:placetype": "venue"
  },
  "geometry": {"coordinates":[-70.692004,42.651127],"type":"Point"}
}
