{
  "type": "Feature",
  "properties": {
    "addr:full":"27 Pine View Dr Scituate MA 02066",
    "addr:housenumber":"27",
    "addr:postcode":"02066",
    "addr:street":"Pine View Dr",
    "iso:country":"US",
    "sg:address":"27 Pine View Dr",
    "sg:city":"Scituate",
    "sg:classifiers":[
        {
            "category":"Education",
            "subcategory":"Special Training",
            "type":"Public Place"
        }
    ],
    "sg:phone":"+1 781 545 0140",
    "sg:postcode":"02066",
    "sg:province":"MA",
    "sg:tags":[
        "educational"
    ],
    "wof:name":"Joseph Devine",
    "wof:placetype":"venue"
},
  "geometry": {"coordinates":[-70.77263600000001,42.19451],"type":"Point"}
}