{
  "type": "Feature",
  "properties": {
    "addr:full":"801 Boylston St Boston MA 02116",
    "addr:housenumber":"801",
    "addr:postcode":"02116",
    "addr:street":"Boylston St",
    "iso:country":"US",
    "sg:address":"801 Boylston St",
    "sg:city":"Boston",
    "sg:classifiers":[
        {
            "category":"Banks & Credit Unions",
            "subcategory":"Investment Brokerage",
            "type":"Services"
        },
        {
            "category":"Banks & Credit Unions",
            "subcategory":"Bank",
            "type":"Services"
        },
        {
            "category":"Banks & Credit Unions",
            "subcategory":"Financial Services",
            "type":"Services"
        }
    ],
    "sg:phone":"+1 800 445 9448",
    "sg:postcode":"02116",
    "sg:province":"MA",
    "sg:tags":[
        "mutual",
        "retirement",
        "annuity",
        "broker",
        "fund",
        "planning",
        "plan",
        "consultant",
        "bond",
        "insurance",
        "stock"
    ],
    "sg:website":"http://www.fidelity.com",
    "wof:name":"Fidelity Investments",
    "wof:placetype":"venue"
},
  "geometry": {"coordinates":[-71.081772,42.348881],"type":"Point"}
}