{
  "type": "Feature",
  "properties": {
    "iso:country":"US",
    "sg:address":"184 State St",
    "sg:city":"Newburyport",
    "sg:classifiers":[
        {
            "category":"Social Services",
            "type":"Services"
        }
    ],
    "sg:phone":"+1 978 462 1888",
    "sg:postcode":"01950",
    "sg:province":"MA",
    "sg:tags":[
        "counselor",
        "marriage",
        "family"
    ],
    "wof:name":"Solutions",
    "wof:placetype":"venue"
},
  "geometry": {"coordinates":[-70.87473900000001,42.800095],"type":"Point"}
}