{
  "type": "Feature",
  "properties": {
    "iso:country":"US",
    "sg:address":"9 Grand Turk Way",
    "sg:city":"Salem",
    "sg:classifiers":[
        {
            "category":"Professional",
            "subcategory":"Engineering",
            "type":"Services"
        },
        {
            "category":"Professional",
            "subcategory":"Computer Services",
            "type":"Services"
        }
    ],
    "sg:phone":"+1 978 745 8507",
    "sg:postcode":"01970",
    "sg:province":"MA",
    "sg:tags":[
        "engineer",
        "consultant",
        "designer",
        "integration",
        "system"
    ],
    "wof:name":"Sims",
    "wof:placetype":"venue"
},
  "geometry": {"coordinates":[-70.919585,42.497172],"type":"Point"}
}