{
  "type": "Feature",
  "properties": {
    "iso:country":"US",
    "sg:address":"797 Mass Ave",
    "sg:city":"Arlington",
    "sg:classifiers":[
        {
            "category":"Restaurant",
            "type":"Food & Drink"
        }
    ],
    "sg:postcode":"02474",
    "sg:province":"MA",
    "sg:tags":[
        "pizza"
    ],
    "wof:name":"Arlington House of Pizza",
    "wof:placetype":"venue"
},
  "geometry": {"coordinates":[-71.158798,42.416698],"type":"Point"}
}