{
  "type": "Feature",
  "properties": {
    "iso:country":"US",
    "sg:address":"64 Brookside St",
    "sg:city":"Lowell",
    "sg:classifiers":[
        {
            "category":"Personal",
            "subcategory":"Beauty Salon",
            "type":"Services"
        }
    ],
    "sg:phone":"+1   ",
    "sg:postcode":"01854",
    "sg:province":"MA",
    "sg:tags":[
        "shop"
    ],
    "wof:name":"Mindys Nails",
    "wof:placetype":"venue"
},
  "geometry": {"coordinates":[-71.338358,42.647668],"type":"Point"}
}