{
  "type": "Feature",
  "properties": {
    "addr:full": "64 Brookside St Lowell MA 01854",
    "addr:housenumber": "64",
    "addr:postcode": "01854",
    "addr:street": "Brookside St",
    "iso:country": "US",
    "sg:address": "64 Brookside St",
    "sg:city": "Lowell",
    "sg:classifiers": [
      {
        "category": "Personal",
        "subcategory": "Beauty Salon",
        "type": "Services"
      }
    ],
    "sg:phone": "+1   ",
    "sg:postcode": "01854",
    "sg:province": "MA",
    "sg:tags": [
      "shop"
    ],
    "wof:name": "Mindys Nails",
    "wof:placetype": "venue"
  },
  "geometry": {"coordinates":[-71.338358,42.647668],"type":"Point"}
}
