{
  "type": "Feature",
  "properties": {
    "addr:full":"1 Bennett St Cambridge MA 02138",
    "addr:housenumber":"1",
    "addr:postcode":"02138",
    "addr:street":"Bennett St",
    "iso:country":"US",
    "sg:address":"1 Bennett St",
    "sg:city":"Cambridge",
    "sg:phone":"+1 617 765 4515",
    "sg:postcode":"02138",
    "sg:province":"MA",
    "sg:website":"http://boston.citysearch.com/profile/external/653752040/cambridge_ma/charles_hotel_in_harvard_square.html?publisher=yellowpages&reference_id=15&placement=ypwebsitemip",
    "wof:name":"Charles Hotel in Harvard Square",
    "wof:placetype":"venue"
},
  "geometry": {"coordinates":[-71.12181099999999,42.372261],"type":"Point"}
}