{
  "type": "Feature",
  "properties": {
    "iso:country":"US",
    "sg:address":"428 Merrill Rd",
    "sg:city":"Pittsfield",
    "sg:classifiers":[
        {
            "category":"Retail",
            "subcategory":"Auto Repair",
            "type":"Services"
        }
    ],
    "sg:phone":"+1 413 499 7283",
    "sg:postcode":"01201",
    "sg:province":"MA",
    "sg:tags":[
        "repairing",
        "automobile"
    ],
    "wof:name":"Mike Golin Automotive",
    "wof:placetype":"venue"
},
  "geometry": {"coordinates":[-73.208337,42.460801],"type":"Point"}
}