{
  "type": "Feature",
  "properties": {
    "addr:full": "29 Washington St Norwell MA 02061",
    "addr:housenumber": "29",
    "addr:postcode": "02061",
    "addr:street": "Washington St",
    "iso:country": "US",
    "sg:address": "29 Washington St",
    "sg:city": "Norwell",
    "sg:classifiers": [
      {
        "category": "Personal",
        "subcategory": "Beauty Salon",
        "type": "Services"
      }
    ],
    "sg:phone": "+1 781 878 7919",
    "sg:postcode": "02061",
    "sg:province": "MA",
    "sg:tags": [
      "manicuring"
    ],
    "wof:name": "Quality Nails",
    "wof:placetype": "venue"
  },
  "geometry": {"coordinates":[-70.88324,42.174135],"type":"Point"}
}
