{
  "type": "Feature",
  "properties": {
    "iso:country":"US",
    "sg:address":"29 Washington St",
    "sg:city":"Norwell",
    "sg:classifiers":[
        {
            "category":"Personal",
            "subcategory":"Beauty Salon",
            "type":"Services"
        }
    ],
    "sg:phone":"+1 781 878 7919",
    "sg:postcode":"02061",
    "sg:province":"MA",
    "sg:tags":[
        "manicuring"
    ],
    "wof:name":"Quality Nails",
    "wof:placetype":"venue"
},
  "geometry": {"coordinates":[-70.88324,42.174135],"type":"Point"}
}