{
  "type": "Feature",
  "properties": {
    "iso:country":"US",
    "sg:address":"70 Malden St",
    "sg:city":"West Boylston",
    "sg:classifiers":[
        {
            "category":"Real Estate",
            "subcategory":"Real Estate Agent",
            "type":"Services"
        }
    ],
    "sg:phone":"+1 508 835 4200",
    "sg:postcode":"01583",
    "sg:province":"MA",
    "wof:name":"Bradford Co",
    "wof:placetype":"venue"
},
  "geometry": {"coordinates":[-71.79177799999999,42.368621],"type":"Point"}
}