{
  "type": "Feature",
  "properties": {
    "iso:country":"US",
    "sg:address":"129 Florence St",
    "sg:city":"Springfield",
    "sg:classifiers":[
        {
            "category":"Building & Trades",
            "subcategory":"Construction",
            "type":"Services"
        }
    ],
    "sg:phone":"+1   ",
    "sg:postcode":"01105",
    "sg:province":"MA",
    "sg:tags":[
        "contractor"
    ],
    "wof:name":"Artisan Masonry",
    "wof:placetype":"venue"
},
  "geometry": {"coordinates":[-72.56807000000001,42.09991],"type":"Point"}
}