{
  "type": "Feature",
  "properties": {
    "addr:full": "515 Hanover St Hanover MA 02339",
    "addr:housenumber": "515",
    "addr:postcode": "02339",
    "addr:street": "Hanover St",
    "iso:country": "US",
    "sg:address": "515 Hanover St",
    "sg:city": "Hanover",
    "sg:classifiers": [
      {
        "category": "Social Services",
        "subcategory": "Child Care",
        "type": "Services"
      }
    ],
    "sg:phone": "+1 781 826 8604",
    "sg:postcode": "02339",
    "sg:province": "MA",
    "sg:tags": [
      "kindergarten",
      "academic",
      "school"
    ],
    "wof:name": "Hanover Nursery \u0026 Day Care Ctr",
    "wof:placetype": "venue"
  },
  "geometry": {"coordinates":[-70.842366,42.116762],"type":"Point"}
}
