{
  "type": "Feature",
  "properties": {
    "iso:country":"US",
    "sg:address":"515 Hanover St",
    "sg:city":"Hanover",
    "sg:classifiers":[
        {
            "category":"Social Services",
            "subcategory":"Child Care",
            "type":"Services"
        }
    ],
    "sg:phone":"+1 781 826 8604",
    "sg:postcode":"02339",
    "sg:province":"MA",
    "sg:tags":[
        "kindergarten",
        "academic",
        "school"
    ],
    "wof:name":"Hanover Nursery & Day Care Ctr",
    "wof:placetype":"venue"
},
  "geometry": {"coordinates":[-70.842366,42.116762],"type":"Point"}
}