{
  "type": "Feature",
  "properties": {
    "iso:country":"US",
    "sg:address":"4000 Mystic Valley Parkway",
    "sg:city":"Medford",
    "sg:classifiers":[
        {
            "category":"Home & Garden",
            "subcategory":"Furniture",
            "type":"Retail Goods"
        }
    ],
    "sg:phone":"+1 781 395 4131",
    "sg:postcode":"02155",
    "sg:province":"MA",
    "sg:tags":[
        "store"
    ],
    "wof:name":"Cks Interiors",
    "wof:placetype":"venue"
},
  "geometry": {"coordinates":[-71.088735,42.404004],"type":"Point"}
}