{
  "type": "Feature",
  "properties": {
    "iso:country":"US",
    "sg:address":"53 Court St",
    "sg:city":"Westfield",
    "sg:classifiers":[
        {
            "category":"Real Estate",
            "subcategory":"Real Estate Services",
            "type":"Services"
        },
        {
            "category":"Real Estate",
            "subcategory":"Real Estate Agent",
            "type":"Services"
        }
    ],
    "sg:phone":"+1 413 568 3536",
    "sg:postcode":"01085",
    "sg:province":"MA",
    "sg:tags":[
        "buyer",
        "management",
        "broker"
    ],
    "wof:name":"Show Case Realty Inc",
    "wof:placetype":"venue"
},
  "geometry": {"coordinates":[-72.754013,42.120232],"type":"Point"}
}