{
  "type": "Feature",
  "properties": {
    "addr:full":"166 Harvard Ave Allston MA 02134",
    "addr:housenumber":"166",
    "addr:postcode":"02134",
    "addr:street":"Harvard Ave",
    "iso:country":"US",
    "sg:address":"166 Harvard Ave",
    "sg:city":"Allston",
    "sg:classifiers":[
        {
            "category":"Restaurant",
            "type":"Food & Drink"
        }
    ],
    "sg:phone":"+1 617 787 5656",
    "sg:postcode":"02134",
    "sg:province":"MA",
    "sg:tags":[
        "korean"
    ],
    "wof:name":"Color Restaurant",
    "wof:placetype":"venue"
},
  "geometry": {"coordinates":[-71.131557,42.351356],"type":"Point"}
}