{
  "type": "Feature",
  "properties": {
    "addr:full":"1 Ekman St Worcester MA 01607",
    "addr:housenumber":"1",
    "addr:postcode":"01607",
    "addr:street":"Ekman St",
    "iso:country":"US",
    "sg:address":"1 Ekman St",
    "sg:city":"Worcester",
    "sg:classifiers":[
        {
            "category":"Shopping",
            "type":"Retail Goods"
        }
    ],
    "sg:phone":"+1 508 756 7200",
    "sg:postcode":"01607",
    "sg:province":"MA",
    "sg:tags":[
        "merchandise"
    ],
    "wof:name":"Village Art",
    "wof:placetype":"venue"
},
  "geometry": {"coordinates":[-71.79771100000001,42.230883],"type":"Point"}
}