{
  "type": "Feature",
  "properties": {
    "iso:country":"US",
    "sg:address":"251 Davis St",
    "sg:city":"Greenfield",
    "sg:classifiers":[
        {
            "category":"Home & Garden",
            "subcategory":"Building Materials",
            "type":"Retail Goods"
        }
    ],
    "sg:phone":"+1 413 774 4046",
    "sg:postcode":"01301",
    "sg:province":"MA",
    "sg:tags":[
        "paint"
    ],
    "sg:website":"www.dakorcenter.com",
    "wof:name":"Dakor Center",
    "wof:placetype":"venue"
},
  "geometry": {"coordinates":[-72.60039999999999,42.597753],"type":"Point"}
}