{
  "type": "Feature",
  "properties": {
    "addr:full": "251 Davis St Greenfield MA 01301",
    "addr:housenumber": "251",
    "addr:postcode": "01301",
    "addr:street": "Davis St",
    "iso:country": "US",
    "sg:address": "251 Davis St",
    "sg:city": "Greenfield",
    "sg:classifiers": [
      {
        "category": "Home \u0026 Garden",
        "subcategory": "Building Materials",
        "type": "Retail Goods"
      }
    ],
    "sg:phone": "+1 413 774 4046",
    "sg:postcode": "01301",
    "sg:province": "MA",
    "sg:tags": [
      "paint"
    ],
    "sg:website": "www.dakorcenter.com",
    "wof:name": "Dakor Center",
    "wof:placetype": "venue"
  },
  "geometry": {"coordinates":[-72.6004,42.597753],"type":"Point"}
}
