{
  "type": "Feature",
  "properties": {
    "iso:country":"US",
    "sg:address":"275 Grove St Ste 2-400",
    "sg:city":"Auburndale",
    "sg:classifiers":[
        {
            "category":"Professional",
            "subcategory":"Research",
            "type":"Services"
        }
    ],
    "sg:phone":"+1 617 663 5711",
    "sg:postcode":"02466",
    "sg:province":"MA",
    "sg:tags":[
        "information",
        "medical"
    ],
    "sg:website":"http://www.ctf.org",
    "wof:name":"New England Chapter",
    "wof:placetype":"venue"
},
  "geometry": {"coordinates":[-71.251648,42.337421],"type":"Point"}
}