{
  "type": "Feature",
  "properties": {
    "addr:full": "227 Washington St Marblehead MA 01945",
    "addr:housenumber": "227",
    "addr:postcode": "01945",
    "addr:street": "Washington St",
    "iso:country": "US",
    "sg:address": "227 Washington St",
    "sg:city": "Marblehead",
    "sg:classifiers": [
      {
        "category": "Personal",
        "type": "Services"
      }
    ],
    "sg:phone": "+1 781 639 3655",
    "sg:postcode": "01945",
    "sg:province": "MA",
    "sg:tags": [
      "electrolysis"
    ],
    "wof:name": "Irene-Dolly Doveas",
    "wof:placetype": "venue"
  },
  "geometry": {"coordinates":[-70.853368,42.502334],"type":"Point"}
}
