{
  "type": "Feature",
  "properties": {
    "iso:country":"US",
    "sg:address":"586 Main St",
    "sg:city":"Shrewsbury",
    "sg:classifiers":[
        {
            "category":"Professional",
            "subcategory":"Lawyer & Legal Services",
            "type":"Services"
        }
    ],
    "sg:phone":"+1 508 845 6766",
    "sg:postcode":"01545",
    "sg:province":"MA",
    "sg:tags":[
        "attorney"
    ],
    "wof:name":"Robert A Cole",
    "wof:placetype":"venue"
},
  "geometry": {"coordinates":[-71.714016,42.296521],"type":"Point"}
}