{
  "type": "Feature",
  "properties": {
    "addr:full": "442 Quaker Hwy Uxbridge MA 01569",
    "addr:housenumber": "442",
    "addr:postcode": "01569",
    "addr:street": "Quaker Hwy",
    "iso:country": "US",
    "sg:address": "442 Quaker Hwy",
    "sg:city": "Uxbridge",
    "sg:classifiers": [
      {
        "category": "Industrial Area",
        "type": "Public Place"
      }
    ],
    "sg:phone": "+1 508 278 2445",
    "sg:postcode": "01569",
    "sg:province": "MA",
    "sg:tags": [
      "development"
    ],
    "wof:name": "Quaker Industrial Park Inc",
    "wof:placetype": "venue"
  },
  "geometry": {"coordinates":[-71.621464,42.042391],"type":"Point"}
}
