{
  "type": "Feature",
  "properties": {
    "addr:full":"103 Vanderbilt Ave Norwood MA 02062",
    "addr:housenumber":"103",
    "addr:postcode":"02062",
    "addr:street":"Vanderbilt Ave",
    "iso:country":"US",
    "sg:address":"103 Vanderbilt Ave",
    "sg:city":"Norwood",
    "sg:classifiers":[
        {
            "category":"Health Services",
            "subcategory":"Health Practitioner",
            "type":"Services"
        },
        {
            "category":"Arena",
            "subcategory":"Sports Club",
            "type":"Entertainment"
        }
    ],
    "sg:phone":"+1 781 769 1258",
    "sg:postcode":"02062",
    "sg:province":"MA",
    "sg:tags":[
        "nutritionist"
    ],
    "wof:name":"Cathy Savage Fitness Center",
    "wof:placetype":"venue"
},
  "geometry": {"coordinates":[-71.191349,42.172397],"type":"Point"}
}