{
  "type": "Feature",
  "properties": {
    "addr:full":"830 Commonwealth Ave Boston MA 02215",
    "addr:housenumber":"830",
    "addr:postcode":"02215",
    "addr:street":"Commonwealth Ave",
    "iso:country":"US",
    "sg:address":"830 Commonwealth Ave",
    "sg:city":"Boston",
    "sg:classifiers":[
        {
            "category":"Personal",
            "subcategory":"Tanning Parlor",
            "type":"Services"
        }
    ],
    "sg:phone":"+1 617 738 1826",
    "sg:postcode":"02215",
    "sg:province":"MA",
    "sg:website":"www.darquetan.com",
    "wof:name":"Darque Tan",
    "wof:placetype":"venue"
},
  "geometry": {"coordinates":[-71.124358,42.351955],"type":"Point"}
}