{
  "type": "Feature",
  "properties": {
    "addr:full": "614 Blue Hill Ave Dorchester MA 02121",
    "addr:housenumber": "614",
    "addr:postcode": "02121",
    "addr:street": "Blue Hill Ave",
    "iso:country": "US",
    "sg:address": "614 Blue Hill Ave",
    "sg:city": "Dorchester",
    "sg:classifiers": [
      {
        "category": "Shopping",
        "subcategory": "Clothing, Apparel, \u0026 Fashions",
        "type": "Retail Goods"
      }
    ],
    "sg:phone": "+1 617 740 8460",
    "sg:postcode": "02121",
    "sg:province": "MA",
    "wof:name": "K Clothing",
    "wof:placetype": "venue"
  },
  "geometry": {"coordinates":[-71.084984,42.30338],"type":"Point"}
}
