{
  "type": "Feature",
  "properties": {
    "addr:full": "45 Oakland St Unit A Newburyport MA 01950",
    "addr:housenumber": "45",
    "addr:postcode": "01950",
    "addr:street": "Oakland St Unit A",
    "iso:country": "US",
    "sg:address": "45 Oakland St Unit A",
    "sg:city": "Newburyport",
    "sg:classifiers": [
      {
        "category": "Food \u0026 Beverages",
        "subcategory": "Groceries \u0026 Convenience Stores",
        "type": "Retail Goods"
      }
    ],
    "sg:phone": "+1 978 499 7745",
    "sg:postcode": "01950",
    "sg:province": "MA",
    "wof:name": "Novus Markets",
    "wof:placetype": "venue"
  },
  "geometry": {"coordinates":[-70.886147,42.816299],"type":"Point"}
}
