{
  "type": "Feature",
  "properties": {
    "iso:country":"US",
    "sg:address":"45 Oakland St Unit A",
    "sg:city":"Newburyport",
    "sg:classifiers":[
        {
            "category":"Food & Beverages",
            "subcategory":"Groceries & Convenience Stores",
            "type":"Retail Goods"
        }
    ],
    "sg:phone":"+1 978 499 7745",
    "sg:postcode":"01950",
    "sg:province":"MA",
    "wof:name":"Novus Markets",
    "wof:placetype":"venue"
},
  "geometry": {"coordinates":[-70.88614699999999,42.816299],"type":"Point"}
}