{
  "type": "Feature",
  "properties": {
    "addr:full":"329 Hovey St Lowell MA 01852",
    "addr:housenumber":"329",
    "addr:postcode":"01852",
    "addr:street":"Hovey St",
    "iso:country":"US",
    "sg:address":"329 Hovey St",
    "sg:city":"Lowell",
    "sg:classifiers":[
        {
            "category":"Building & Trades",
            "subcategory":"Cleaning & Sanitation",
            "type":"Services"
        }
    ],
    "sg:phone":"+1   ",
    "sg:postcode":"01852",
    "sg:province":"MA",
    "sg:tags":[
        "maintenance"
    ],
    "wof:name":"Expert Building Services Inc",
    "wof:placetype":"venue"
},
  "geometry": {"coordinates":[-71.27814100000001,42.639798],"type":"Point"}
}