{
  "type": "Feature",
  "properties": {
    "addr:full": "421 Princeton Blvd Lowell MA 01851",
    "addr:housenumber": "421",
    "addr:postcode": "01851",
    "addr:street": "Princeton Blvd",
    "iso:country": "US",
    "sg:address": "421 Princeton Blvd",
    "sg:city": "Lowell",
    "sg:classifiers": [
      {
        "category": "Organizations",
        "subcategory": "Religious Organization",
        "type": "Services"
      }
    ],
    "sg:phone": "+1 978 441 0998",
    "sg:postcode": "01851",
    "sg:province": "MA",
    "sg:tags": [
      "christ",
      "latter-day",
      "jesus",
      "churches-church",
      "saint",
      "church"
    ],
    "wof:name": "Church Of Jesus Christ",
    "wof:placetype": "venue"
  },
  "geometry": {"coordinates":[-71.347002,42.633594],"type":"Point"}
}
