{
  "type": "Feature",
  "properties": {
    "iso:country":"US",
    "sg:address":"374 Main St",
    "sg:city":"West Yarmouth",
    "sg:classifiers":[
        {
            "category":"Health Services",
            "subcategory":"Chiropractor",
            "type":"Services"
        }
    ],
    "sg:phone":"+1 508 775 1311",
    "sg:postcode":"02673",
    "sg:province":"MA",
    "wof:name":"Atlantic Chiropractic & Assoc",
    "wof:placetype":"venue"
},
  "geometry": {"coordinates":[-70.24643,41.651325],"type":"Point"}
}