{
  "type": "Feature",
  "properties": {
    "iso:country":"US",
    "sg:address":"56 Top Hill Ave",
    "sg:city":"Dedham",
    "sg:classifiers":[
        {
            "category":"Professional",
            "subcategory":"Art Services",
            "type":"Services"
        }
    ],
    "sg:phone":"+1 781 326 4086",
    "sg:postcode":"02026",
    "sg:province":"MA",
    "sg:tags":[
        "graphic",
        "designer"
    ],
    "wof:name":"Design Through Process",
    "wof:placetype":"venue"
},
  "geometry": {"coordinates":[-71.15962399999999,42.231359],"type":"Point"}
}