{
  "type": "Feature",
  "properties": {
    "addr:full":"7 Clifton Rd Newton MA 02459",
    "addr:housenumber":"7",
    "addr:postcode":"02459",
    "addr:street":"Clifton Rd",
    "iso:country":"US",
    "sg:address":"7 Clifton Rd",
    "sg:city":"Newton",
    "sg:classifiers":[
        {
            "category":"Wholesale",
            "subcategory":"Durable Goods & Equipment",
            "type":"Manufacturing & Wholesale Goods"
        }
    ],
    "sg:phone":"+1 617 964 8681",
    "sg:postcode":"02459",
    "sg:province":"MA",
    "wof:name":"Reliable Sales",
    "wof:placetype":"venue"
},
  "geometry": {"coordinates":[-71.17941500000001,42.302204],"type":"Point"}
}