{
  "type": "Feature",
  "properties": {
    "iso:country":"US",
    "sg:address":"3 Wallis Ct",
    "sg:city":"Lexington",
    "sg:classifiers":[
        {
            "category":"Social Services",
            "type":"Services"
        }
    ],
    "sg:phone":"+1 781 862 5215",
    "sg:postcode":"02421",
    "sg:province":"MA",
    "sg:tags":[
        "organization",
        "welfare"
    ],
    "sg:website":"www.helppro.com",
    "wof:name":"Helpnet Inc",
    "wof:placetype":"venue"
},
  "geometry": {"coordinates":[-71.22520900000001,42.445967],"type":"Point"}
}