{
  "type": "Feature",
  "properties": {
    "addr:full": "167 Corporation Rd Hyannis MA 02601",
    "addr:housenumber": "167",
    "addr:postcode": "02601",
    "addr:street": "Corporation Rd",
    "iso:country": "US",
    "ovtr:label": "Centerline Hobbies, 167 Corporation St Hyannis MA US",
    "ovtr:similarity": 2.336467981338501,
    "sg:address": "167 Corporation Rd",
    "sg:city": "Hyannis",
    "sg:classifiers": [
      {
        "category": "Shopping",
        "subcategory": "Hobbies, Toys, \u0026 Games",
        "type": "Retail Goods"
      }
    ],
    "sg:phone": "+1 508 771 1244",
    "sg:postcode": "02601",
    "sg:province": "MA",
    "sg:tags": [
      "model",
      "supply"
    ],
    "sg:website": "www.centerlinehobbies.com",
    "wof:name": "Centerline Hobbies",
    "wof:placetype": "venue"
  },
  "geometry": {"coordinates":[-70.300943,41.666846],"type":"Point"}
}
