{
  "type": "Feature",
  "properties": {
    "iso:country":"US",
    "sg:address":"167 Corporation Rd",
    "sg:city":"Hyannis",
    "sg:classifiers":[
        {
            "category":"Shopping",
            "subcategory":"Hobbies, Toys, & Games",
            "type":"Retail Goods"
        }
    ],
    "sg:phone":"+1 508 771 1244",
    "sg:postcode":"02601",
    "sg:province":"MA",
    "sg:tags":[
        "model",
        "supply"
    ],
    "sg:website":"www.centerlinehobbies.com",
    "wof:name":"Centerline Hobbies",
    "wof:placetype":"venue"
},
  "geometry": {"coordinates":[-70.300943,41.666846],"type":"Point"}
}