{
  "type": "Feature",
  "properties": {
    "addr:full":"29 Bennington Street Boston MA 02128",
    "addr:housenumber":"29",
    "addr:postcode":"02128",
    "addr:street":"Bennington Street",
    "iso:country":"US",
    "sg:address":"29 Bennington Street",
    "sg:city":"Boston",
    "sg:classifiers":[
        {
            "category":"Shopping",
            "subcategory":"Mobile Phones",
            "type":"Retail Goods"
        }
    ],
    "sg:phone":"+1 617 561 7004",
    "sg:postcode":"02128",
    "sg:province":"MA",
    "wof:name":"Telepaisa",
    "wof:placetype":"venue"
},
  "geometry": {"coordinates":[-71.037756,42.375302],"type":"Point"}
}