{
  "type": "Feature",
  "properties": {
    "addr:full": "12 Sagamore Rd Newton MA 02461",
    "addr:housenumber": "12",
    "addr:postcode": "02461",
    "addr:street": "Sagamore Rd",
    "iso:country": "US",
    "sg:address": "12 Sagamore Rd",
    "sg:city": "Newton",
    "sg:classifiers": [
      {
        "category": "Professional",
        "type": "Services"
      }
    ],
    "sg:phone": "+1   ",
    "sg:postcode": "02461",
    "sg:province": "MA",
    "sg:tags": [
      "artist"
    ],
    "wof:name": "Weiner Doris L Artist",
    "wof:placetype": "venue"
  },
  "geometry": {"coordinates":[-71.216322,42.326481],"type":"Point"}
}
