{
  "type": "Feature",
  "properties": {
    "addr:full": "119 W Boylston St West Boylston MA 01583",
    "addr:housenumber": "119",
    "addr:postcode": "01583",
    "addr:street": "W Boylston St",
    "iso:country": "US",
    "sg:address": "119 W Boylston St",
    "sg:city": "West Boylston",
    "sg:classifiers": [
      {
        "category": "Shopping",
        "subcategory": "Shoes",
        "type": "Retail Goods"
      }
    ],
    "sg:phone": "+1 508 835 4161",
    "sg:postcode": "01583",
    "sg:province": "MA",
    "wof:name": "Payless Shoe Source",
    "wof:placetype": "venue"
  },
  "geometry": {"coordinates":[-71.78465,42.353698],"type":"Point"}
}
