{
  "type": "Feature",
  "properties": {
    "addr:full":"75 Arlington Street Boston MA 02116",
    "addr:housenumber":"75",
    "addr:postcode":"02116",
    "addr:street":"Arlington Street",
    "iso:country":"US",
    "sg:address":"75 Arlington Street",
    "sg:city":"Boston",
    "sg:classifiers":[
        {
            "category":"Communications",
            "type":"Services"
        }
    ],
    "sg:phone":"+1 617 676 8109",
    "sg:postcode":"02116",
    "sg:province":"MA",
    "sg:tags":[
        "web",
        "design"
    ],
    "sg:website":"www.getfoundquick.com",
    "wof:name":"Boston Web Marketing",
    "wof:placetype":"venue"
},
  "geometry": {"coordinates":[-71.07020300000001,42.350379],"type":"Point"}
}