{
  "type": "Feature",
  "properties": {
    "iso:country":"US",
    "sg:address":"75 Meridian St",
    "sg:city":"Melrose",
    "sg:classifiers":[
        {
            "category":"Professional",
            "subcategory":"Computer Services",
            "type":"Services"
        }
    ],
    "sg:phone":"+1   ",
    "sg:postcode":"02176",
    "sg:province":"MA",
    "sg:tags":[
        "datum"
    ],
    "wof:name":"Eleanor Jefferson",
    "wof:placetype":"venue"
},
  "geometry": {"coordinates":[-71.055409,42.452273],"type":"Point"}
}