{
  "type": "Feature",
  "properties": {
    "iso:country":"US",
    "sg:address":"25 Adams St",
    "sg:city":"North Adams",
    "sg:phone":"+1 413 664 6906",
    "sg:postcode":"01247",
    "sg:province":"MA",
    "sg:tags":[
        "oil"
    ],
    "wof:name":"Preite Oil Co",
    "wof:placetype":"venue"
},
  "geometry": {"coordinates":[-73.122654,42.704222],"type":"Point"}
}