{
  "type": "Feature",
  "properties": {
    "iso:country":"US",
    "sg:address":"250 Jefferson Ave",
    "sg:city":"Salem",
    "sg:classifiers":[
        {
            "category":"Retail",
            "subcategory":"Auto Repair",
            "type":"Services"
        }
    ],
    "sg:phone":"+1 978 740 3172",
    "sg:postcode":"01970",
    "sg:province":"MA",
    "sg:tags":[
        "repairing",
        "automobile"
    ],
    "wof:name":"Superior Motors",
    "wof:placetype":"venue"
},
  "geometry": {"coordinates":[-70.90163699999999,42.506951],"type":"Point"}
}