{
  "type": "Feature",
  "properties": {
    "addr:full": "250 Jefferson Ave Salem MA 01970",
    "addr:housenumber": "250",
    "addr:postcode": "01970",
    "addr:street": "Jefferson Ave",
    "iso:country": "US",
    "sg:address": "250 Jefferson Ave",
    "sg:city": "Salem",
    "sg:classifiers": [
      {
        "category": "Retail",
        "subcategory": "Auto Repair",
        "type": "Services"
      }
    ],
    "sg:phone": "+1 978 740 3172",
    "sg:postcode": "01970",
    "sg:province": "MA",
    "sg:tags": [
      "repairing",
      "automobile"
    ],
    "wof:name": "Superior Motors",
    "wof:placetype": "venue"
  },
  "geometry": {"coordinates":[-70.901637,42.506951],"type":"Point"}
}
