{
  "type": "Feature",
  "properties": {
    "iso:country":"US",
    "sg:address":"250 Brookline St",
    "sg:city":"Newton",
    "sg:classifiers":[
        {
            "category":"Education",
            "subcategory":"School",
            "type":"Public Place"
        }
    ],
    "sg:phone":"+1   ",
    "sg:postcode":"02459",
    "sg:province":"MA",
    "sg:tags":[
        "elementary"
    ],
    "wof:name":"Memorl-Splding Elementary Schl",
    "wof:placetype":"venue"
},
  "geometry": {"coordinates":[-71.182232,42.301007],"type":"Point"}
}