{
  "type": "Feature",
  "properties": {
    "addr:full": "63 Main St Bridgewater MA 02324",
    "addr:housenumber": "63",
    "addr:postcode": "02324",
    "addr:street": "Main St",
    "iso:country": "US",
    "sg:address": "63 Main St",
    "sg:city": "Bridgewater",
    "sg:classifiers": [
      {
        "category": "Organizations",
        "subcategory": "Religious Organization",
        "type": "Services"
      }
    ],
    "sg:phone": "+1 508 279 4900",
    "sg:postcode": "02324",
    "sg:province": "MA",
    "sg:tags": [
      "church"
    ],
    "sg:website": "www.southshorecommunitychurch.com",
    "wof:name": "Southshore Community Church",
    "wof:placetype": "venue"
  },
  "geometry": {"coordinates":[-70.976665,41.991183],"type":"Point"}
}
