{
  "type": "Feature",
  "properties": {
    "iso:country":"US",
    "sg:address":"136 Weatherbee Dr",
    "sg:city":"Westwood",
    "sg:classifiers":[
        {
            "category":"Professional",
            "type":"Services"
        }
    ],
    "sg:phone":"+1   ",
    "sg:postcode":"02090",
    "sg:province":"MA",
    "wof:name":"Francesco Piazza",
    "wof:placetype":"venue"
},
  "geometry": {"coordinates":[-71.163517,42.217886],"type":"Point"}
}