{
  "type": "Feature",
  "properties": {
    "addr:full":"130 Newmarket Sq Roxbury MA 02118",
    "addr:housenumber":"130",
    "addr:postcode":"02118",
    "addr:street":"Newmarket Sq",
    "iso:country":"US",
    "sg:address":"130 Newmarket Sq",
    "sg:city":"Roxbury",
    "sg:classifiers":[
        {
            "category":"Restaurant",
            "type":"Food & Drink"
        }
    ],
    "sg:phone":"+1 617 445 7500",
    "sg:postcode":"02118",
    "sg:province":"MA",
    "wof:name":"Reza's Last Bite",
    "wof:placetype":"venue"
},
  "geometry": {"coordinates":[-71.068146,42.330269],"type":"Point"}
}