{
  "type": "Feature",
  "properties": {
    "addr:full":"20 Monument Hill Rd Chelmsford MA 01824",
    "addr:housenumber":"20",
    "addr:postcode":"01824",
    "addr:street":"Monument Hill Rd",
    "iso:country":"US",
    "sg:address":"20 Monument Hill Rd",
    "sg:city":"Chelmsford",
    "sg:classifiers":[
        {
            "category":"Professional",
            "subcategory":"Accounting & Tax Preparation",
            "type":"Services"
        }
    ],
    "sg:phone":"+1 978 256 5583",
    "sg:postcode":"01824",
    "sg:province":"MA",
    "wof:name":"Accounting Plus",
    "wof:placetype":"venue"
},
  "geometry": {"coordinates":[-71.39748400000001,42.608467],"type":"Point"}
}