{
  "type": "Feature",
  "properties": {
    "iso:country":"US",
    "sg:address":"89 Squantum St",
    "sg:city":"Milton",
    "sg:classifiers":[
        {
            "category":"Building & Trades",
            "subcategory":"Construction",
            "type":"Services"
        }
    ],
    "sg:phone":"+1 617 698 1309",
    "sg:postcode":"02186",
    "sg:province":"MA",
    "sg:tags":[
        "road",
        "contractor"
    ],
    "wof:name":"Karney Construction",
    "wof:placetype":"venue"
},
  "geometry": {"coordinates":[-71.042587,42.264671],"type":"Point"}
}