{
  "type": "Feature",
  "properties": {
    "addr:full": "98 Wannalancit St Lowell MA 01854",
    "addr:housenumber": "98",
    "addr:postcode": "01854",
    "addr:street": "Wannalancit St",
    "iso:country": "US",
    "sg:address": "98 Wannalancit St",
    "sg:city": "Lowell",
    "sg:classifiers": [
      {
        "category": "Real Estate",
        "subcategory": "Real Estate Agent",
        "type": "Services"
      }
    ],
    "sg:phone": "+1 978 453 0500",
    "sg:postcode": "01854",
    "sg:province": "MA",
    "sg:tags": [
      "consultant"
    ],
    "wof:name": "Mercantile Realty LLC",
    "wof:placetype": "venue"
  },
  "geometry": {"coordinates":[-71.328162,42.645359],"type":"Point"}
}
