{
  "type": "Feature",
  "properties": {
    "addr:full":"664 Nantasket Ave Hull MA 02045",
    "addr:housenumber":"664",
    "addr:postcode":"02045",
    "addr:street":"Nantasket Ave",
    "iso:country":"US",
    "sg:address":"664 Nantasket Ave",
    "sg:city":"Hull",
    "sg:classifiers":[
        {
            "category":"Education",
            "subcategory":"Dance Studio",
            "type":"Public Place"
        }
    ],
    "sg:phone":"+1 781 925 1743",
    "sg:postcode":"02045",
    "sg:province":"MA",
    "sg:tags":[
        "instruction",
        "dancing"
    ],
    "wof:name":"Coastal Academy Of Dance",
    "wof:placetype":"venue"
},
  "geometry": {"coordinates":[-70.879108,42.291551],"type":"Point"}
}