{
  "type": "Feature",
  "properties": {
    "addr:full": "119 High St Taunton MA 02780",
    "addr:housenumber": "119",
    "addr:postcode": "02780",
    "addr:street": "High St",
    "iso:country": "US",
    "sg:address": "119 High St",
    "sg:city": "Taunton",
    "sg:classifiers": [
      {
        "category": "Organizations",
        "subcategory": "Membership Organization",
        "type": "Services"
      }
    ],
    "sg:phone": "+1 508 824 7878",
    "sg:postcode": "02780",
    "sg:province": "MA",
    "sg:tags": [
      "fraternal"
    ],
    "wof:name": "Fraternal Benevaulent Order Of",
    "wof:placetype": "venue"
  },
  "geometry": {"coordinates":[-71.095791,41.899303],"type":"Point"}
}
