{
  "type": "Feature",
  "properties": {
    "iso:country":"US",
    "sg:address":"483 Elliott Rd",
    "sg:city":"Centerville",
    "sg:classifiers":[
        {
            "category":"Professional",
            "subcategory":"Accounting & Tax Preparation",
            "type":"Services"
        }
    ],
    "sg:phone":"+1 508 771 4485",
    "sg:postcode":"02632",
    "sg:province":"MA",
    "sg:tags":[
        "bookkeeping",
        "general"
    ],
    "wof:name":"Bookkeeping & Accounting",
    "wof:placetype":"venue"
},
  "geometry": {"coordinates":[-70.334005,41.645124],"type":"Point"}
}