{
  "type": "Feature",
  "properties": {
    "addr:full": "494 Washington St Wellesley MA 02482",
    "addr:housenumber": "494",
    "addr:postcode": "02482",
    "addr:street": "Washington St",
    "iso:country": "US",
    "sg:address": "494 Washington St",
    "sg:city": "Wellesley",
    "sg:classifiers": [
      {
        "category": "Building \u0026 Trades",
        "subcategory": "Construction",
        "type": "Services"
      }
    ],
    "sg:phone": "+1 781 431 1525",
    "sg:postcode": "02482",
    "sg:province": "MA",
    "sg:tags": [
      "general",
      "contractor"
    ],
    "wof:name": "Over C Properties",
    "wof:placetype": "venue"
  },
  "geometry": {"coordinates":[-71.288972,42.298605],"type":"Point"}
}
