{
  "type": "Feature",
  "properties": {
    "iso:country":"US",
    "sg:address":"125 Tolman Ave",
    "sg:city":"Leominster",
    "sg:classifiers":[
        {
            "category":"Wholesale",
            "subcategory":"Chemicals & Plastics",
            "type":"Manufacturing & Wholesale Goods"
        }
    ],
    "sg:phone":"+1 978 840 0113",
    "sg:postcode":"01453",
    "sg:province":"MA",
    "sg:tags":[
        "oxygen"
    ],
    "sg:website":"www.tolmanclinical.com",
    "wof:name":"North Atlantic Medical Svc",
    "wof:placetype":"venue"
},
  "geometry": {"coordinates":[-71.746364,42.549255],"type":"Point"}
}