{
  "type": "Feature",
  "properties": {
    "addr:full": "125 Tolman Ave Leominster MA 01453",
    "addr:housenumber": "125",
    "addr:postcode": "01453",
    "addr:street": "Tolman Ave",
    "iso:country": "US",
    "sg:address": "125 Tolman Ave",
    "sg:city": "Leominster",
    "sg:classifiers": [
      {
        "category": "Wholesale",
        "subcategory": "Chemicals \u0026 Plastics",
        "type": "Manufacturing \u0026 Wholesale Goods"
      }
    ],
    "sg:phone": "+1 978 840 0113",
    "sg:postcode": "01453",
    "sg:province": "MA",
    "sg:tags": [
      "oxygen"
    ],
    "sg:website": "www.tolmanclinical.com",
    "wof:name": "North Atlantic Medical Svc",
    "wof:placetype": "venue"
  },
  "geometry": {"coordinates":[-71.746364,42.549255],"type":"Point"}
}
