{
  "type": "Feature",
  "properties": {
    "iso:country":"US",
    "sg:address":"11 Miller Street",
    "sg:city":"Somerville",
    "sg:classifiers":[
        {
            "category":"Professional",
            "subcategory":"Lawyer & Legal Services",
            "type":"Services"
        }
    ],
    "sg:phone":"+1 617 868 2380",
    "sg:postcode":"02143",
    "sg:province":"MA",
    "wof:name":"Whalen Associates",
    "wof:placetype":"venue"
},
  "geometry": {"coordinates":[-71.112408,42.383977],"type":"Point"}
}