{
  "type": "Feature",
  "properties": {
    "addr:full":"153 Granite St Rockport MA 01966",
    "addr:housenumber":"153",
    "addr:postcode":"01966",
    "addr:street":"Granite St",
    "iso:country":"US",
    "sg:address":"153 Granite St",
    "sg:city":"Rockport",
    "sg:classifiers":[
        {
            "category":"Health Services",
            "subcategory":"Clinic",
            "type":"Services"
        }
    ],
    "sg:phone":"+1 978 546 3377",
    "sg:postcode":"01966",
    "sg:province":"MA",
    "sg:tags":[
        "welfare"
    ],
    "wof:name":"Cape Ann Health Professionals",
    "wof:placetype":"venue"
},
  "geometry": {"coordinates":[-70.62354999999999,42.674801],"type":"Point"}
}