{
  "type": "Feature",
  "properties": {
    "addr:full": "469 Stafford Rd Fall River MA 02721",
    "addr:housenumber": "469",
    "addr:postcode": "02721",
    "addr:street": "Stafford Rd",
    "iso:country": "US",
    "sg:address": "469 Stafford Rd",
    "sg:city": "Fall River",
    "sg:classifiers": [
      {
        "category": "Restaurant",
        "type": "Food \u0026 Drink"
      }
    ],
    "sg:phone": "+1 508 672 9840",
    "sg:postcode": "02721",
    "sg:province": "MA",
    "wof:name": "Papa Carls Pizza",
    "wof:placetype": "venue"
  },
  "geometry": {"coordinates":[-71.157275,41.682989],"type":"Point"}
}
