{
  "type": "Feature",
  "properties": {
    "iso:country":"US",
    "sg:address":"8 Henshaw St",
    "sg:city":"Woburn",
    "sg:classifiers":[
        {
            "category":"Wholesale",
            "subcategory":"Toys & Hobbies",
            "type":"Manufacturing & Wholesale Goods"
        }
    ],
    "sg:phone":"+1 781 935 1367",
    "sg:postcode":"01801",
    "sg:province":"MA",
    "sg:tags":[
        "model",
        "supply"
    ],
    "wof:name":"Reboxx",
    "wof:placetype":"venue"
},
  "geometry": {"coordinates":[-71.11944,42.477505],"type":"Point"}
}