{
  "type": "Feature",
  "properties": {
    "addr:full": "8 Henshaw St Woburn MA 01801",
    "addr:housenumber": "8",
    "addr:postcode": "01801",
    "addr:street": "Henshaw St",
    "iso:country": "US",
    "sg:address": "8 Henshaw St",
    "sg:city": "Woburn",
    "sg:classifiers": [
      {
        "category": "Wholesale",
        "subcategory": "Toys \u0026 Hobbies",
        "type": "Manufacturing \u0026 Wholesale Goods"
      }
    ],
    "sg:phone": "+1 781 935 1367",
    "sg:postcode": "01801",
    "sg:province": "MA",
    "sg:tags": [
      "model",
      "supply"
    ],
    "wof:name": "Reboxx",
    "wof:placetype": "venue"
  },
  "geometry": {"coordinates":[-71.11944,42.477505],"type":"Point"}
}
