{
  "type": "Feature",
  "properties": {
    "addr:full": "1 Dix St Worcester MA 01609",
    "addr:housenumber": "1",
    "addr:postcode": "01609",
    "addr:street": "Dix St",
    "iso:country": "US",
    "sg:address": "1 Dix St",
    "sg:city": "Worcester",
    "sg:classifiers": [
      {
        "category": "Professional",
        "subcategory": "Lawyer \u0026 Legal Services",
        "type": "Services"
      }
    ],
    "sg:phone": "+1 508 795 7544",
    "sg:postcode": "01609",
    "sg:province": "MA",
    "sg:tags": [
      "attorney"
    ],
    "wof:name": "Yancy L Garnett",
    "wof:placetype": "venue"
  },
  "geometry": {"coordinates":[-71.80323,42.269301],"type":"Point"}
}
