{
  "type": "Feature",
  "properties": {
    "addr:full":"15 Court St Plymouth MA 02360",
    "addr:housenumber":"15",
    "addr:postcode":"02360",
    "addr:street":"Court St",
    "iso:country":"US",
    "sg:address":"15 Court St",
    "sg:city":"Plymouth",
    "sg:classifiers":[
        {
            "category":"Personal",
            "subcategory":"Barber",
            "type":"Services"
        }
    ],
    "sg:phone":"+1 508 746 7331",
    "sg:postcode":"02360",
    "sg:province":"MA",
    "wof:name":"Plymouths Finest - CLOSED",
    "wof:placetype":"venue"
},
  "geometry": {"coordinates":[-70.665497,41.957199],"type":"Point"}
}