{
  "type": "Feature",
  "properties": {
    "addr:full":"85 North Ave Natick MA 01760",
    "addr:housenumber":"85",
    "addr:postcode":"01760",
    "addr:street":"North Ave",
    "iso:country":"US",
    "sg:address":"85 North Ave",
    "sg:city":"Natick",
    "sg:classifiers":[
        {
            "category":"Manufacturing",
            "subcategory":"Tools & Machinery",
            "type":"Manufacturing & Wholesale Goods"
        }
    ],
    "sg:phone":"+1 508 655 4469",
    "sg:postcode":"01760",
    "sg:province":"MA",
    "sg:tags":[
        "machine",
        "shop"
    ],
    "wof:name":"Debco Machine Co",
    "wof:placetype":"venue"
},
  "geometry": {"coordinates":[-71.343547,42.286538],"type":"Point"}
}