{
  "type": "Feature",
  "properties": {
    "iso:country":"US",
    "sg:address":"979 Main St",
    "sg:city":"Wakefield",
    "sg:classifiers":[
        {
            "category":"Restaurant",
            "type":"Food & Drink"
        }
    ],
    "sg:phone":"+1 781 224 9757",
    "sg:postcode":"01880",
    "sg:province":"MA",
    "wof:name":"Porto-Bello Restaurant",
    "wof:placetype":"venue"
},
  "geometry": {"coordinates":[-71.065269,42.481123],"type":"Point"}
}