{
  "type": "Feature",
  "properties": {
    "iso:country":"US",
    "sg:address":"21 Reynolds Ave",
    "sg:city":"Everett",
    "sg:classifiers":[
        {
            "category":"Wholesale",
            "subcategory":"Machinery & Supplies",
            "type":"Manufacturing & Wholesale Goods"
        }
    ],
    "sg:phone":"+1 617 387 7210",
    "sg:postcode":"02149",
    "sg:province":"MA",
    "sg:tags":[
        "instrument",
        "scientific",
        "apparatus"
    ],
    "wof:name":"Midgard",
    "wof:placetype":"venue"
},
  "geometry": {"coordinates":[-71.040527,42.403791],"type":"Point"}
}