{
  "type": "Feature",
  "properties": {
    "iso:country":"US",
    "sg:address":"18 Church St",
    "sg:city":"Hudson",
    "sg:classifiers":[
        {
            "category":"Organizations",
            "subcategory":"Professional Association",
            "type":"Services"
        }
    ],
    "sg:phone":"+1 978 568 0360",
    "sg:postcode":"01749",
    "sg:province":"MA",
    "sg:tags":[
        "chambers",
        "commerce"
    ],
    "sg:website":"www.assabetvalleychamber.org",
    "wof:name":"Assabet Valley Chamber-Commrc",
    "wof:placetype":"venue"
},
  "geometry": {"coordinates":[-71.56714599999999,42.39242],"type":"Point"}
}