{
  "type": "Feature",
  "properties": {
    "addr:full": "18 Church St Hudson MA 01749",
    "addr:housenumber": "18",
    "addr:postcode": "01749",
    "addr:street": "Church St",
    "iso:country": "US",
    "sg:address": "18 Church St",
    "sg:city": "Hudson",
    "sg:classifiers": [
      {
        "category": "Organizations",
        "subcategory": "Professional Association",
        "type": "Services"
      }
    ],
    "sg:phone": "+1 978 568 0360",
    "sg:postcode": "01749",
    "sg:province": "MA",
    "sg:tags": [
      "chambers",
      "commerce"
    ],
    "sg:website": "www.assabetvalleychamber.org",
    "wof:name": "Assabet Valley Chamber-Commrc",
    "wof:placetype": "venue"
  },
  "geometry": {"coordinates":[-71.567146,42.39242],"type":"Point"}
}
