{
  "type": "Feature",
  "properties": {
    "addr:full":"313 Washington St Newton MA 02458",
    "addr:housenumber":"313",
    "addr:postcode":"02458",
    "addr:street":"Washington St",
    "iso:country":"US",
    "sg:address":"313 Washington St",
    "sg:city":"Newton",
    "sg:classifiers":[
        {
            "category":"Personal",
            "type":"Services"
        }
    ],
    "sg:phone":"+1 617 332 2582",
    "sg:postcode":"02458",
    "sg:province":"MA",
    "sg:tags":[
        "dating"
    ],
    "sg:website":"www.postclub.com",
    "wof:name":"Post Club",
    "wof:placetype":"venue"
},
  "geometry": {"coordinates":[-71.18653,42.357029],"type":"Point"}
}