{
  "type": "Feature",
  "properties": {
    "iso:country":"US",
    "sg:address":"26 Dante Ave",
    "sg:city":"Belmont",
    "sg:classifiers":[
        {
            "category":"Manufacturing",
            "subcategory":"Buildings",
            "type":"Manufacturing & Wholesale Goods"
        },
        {
            "category":"Building & Trades",
            "subcategory":"Construction",
            "type":"Services"
        }
    ],
    "sg:phone":"+1 617 489 7055",
    "sg:postcode":"02478",
    "sg:province":"MA",
    "sg:tags":[
        "home",
        "builder",
        "contractor"
    ],
    "wof:name":"Peterson Davis Builders, Inc",
    "wof:placetype":"venue"
},
  "geometry": {"coordinates":[-71.186958,42.385093],"type":"Point"}
}