{
  "type": "Feature",
  "properties": {
    "addr:full":"352 Common St Lawrence MA 01840",
    "addr:housenumber":"352",
    "addr:postcode":"01840",
    "addr:street":"Common St",
    "iso:country":"US",
    "sg:address":"352 Common St",
    "sg:city":"Lawrence",
    "sg:classifiers":[
        {
            "category":"Organizations",
            "subcategory":"Religious Organization",
            "type":"Services"
        }
    ],
    "sg:phone":"+1   ",
    "sg:postcode":"01840",
    "sg:province":"MA",
    "wof:name":"Hands of Hope",
    "wof:placetype":"venue"
},
  "geometry": {"coordinates":[-71.164951,42.707043],"type":"Point"}
}