{
  "type": "Feature",
  "properties": {
    "addr:full": "97 High St Acton MA 01720",
    "addr:housenumber": "97",
    "addr:postcode": "01720",
    "addr:street": "High St",
    "iso:country": "US",
    "sg:address": "97 High St",
    "sg:city": "Acton",
    "sg:classifiers": [
      {
        "category": "Real Estate",
        "subcategory": "Architect",
        "type": "Services"
      }
    ],
    "sg:phone": "+1 978 263 6470",
    "sg:postcode": "01720",
    "sg:province": "MA",
    "wof:name": "Faber Design",
    "wof:placetype": "venue"
  },
  "geometry": {"coordinates":[-71.4487,42.4538],"type":"Point"}
}
