{
  "type": "Feature",
  "properties": {
    "addr:full": "150 Bolivar St Canton MA 02021",
    "addr:housenumber": "150",
    "addr:postcode": "02021",
    "addr:street": "Bolivar St",
    "iso:country": "US",
    "sg:address": "150 Bolivar St",
    "sg:city": "Canton",
    "sg:classifiers": [
      {
        "category": "Government",
        "subcategory": "Office",
        "type": "Public Place"
      }
    ],
    "sg:phone": "+1 781 821 5025",
    "sg:postcode": "02021",
    "sg:province": "MA",
    "sg:tags": [
      "village"
    ],
    "wof:name": "Canton Garage",
    "wof:placetype": "venue"
  },
  "geometry": {"coordinates":[-71.143101,42.152069],"type":"Point"}
}
