{
  "type": "Feature",
  "properties": {
    "addr:full": "59 Main St Spencer MA 01562",
    "addr:housenumber": "59",
    "addr:postcode": "01562",
    "addr:street": "Main St",
    "iso:country": "US",
    "sg:address": "59 Main St",
    "sg:city": "Spencer",
    "sg:classifiers": [
      {
        "category": "Health Services",
        "subcategory": "Clinic",
        "type": "Services"
      }
    ],
    "sg:phone": "+1 508 885 0323",
    "sg:postcode": "01562",
    "sg:province": "MA",
    "sg:tags": [
      "home"
    ],
    "sg:website": "www.pfhc.com",
    "wof:name": "Private Family Home Care Inc",
    "wof:placetype": "venue"
  },
  "geometry": {"coordinates":[-71.996055,42.243695],"type":"Point"}
}
