{
  "type": "Feature",
  "properties": {
    "iso:country":"US",
    "sg:address":"320 Washington Street Suite 4",
    "sg:city":"Brookline",
    "sg:classifiers":[
        {
            "category":"Education",
            "subcategory":"Special Training",
            "type":"Public Place"
        }
    ],
    "sg:phone":"+1 617 383 6058",
    "sg:postcode":"02445",
    "sg:province":"MA",
    "sg:tags":[
        "school",
        "specialty"
    ],
    "wof:name":"Boston Career Institute",
    "wof:placetype":"venue"
},
  "geometry": {"coordinates":[-71.126434,42.333436],"type":"Point"}
}