{
  "type": "Feature",
  "properties": {
    "iso:country":"US",
    "sg:address":"14 Mildred Cir",
    "sg:city":"Concord",
    "sg:classifiers":[
        {
            "category":"Manufacturing",
            "subcategory":"Printing",
            "type":"Manufacturing & Wholesale Goods"
        }
    ],
    "sg:phone":"+1   ",
    "sg:postcode":"01742",
    "sg:province":"MA",
    "sg:tags":[
        "book"
    ],
    "wof:name":"Pleasant Street Press",
    "wof:placetype":"venue"
},
  "geometry": {"coordinates":[-71.332519,42.450929],"type":"Point"}
}