{
  "type": "Feature",
  "properties": {
    "iso:country":"US",
    "sg:address":"450 Washington St",
    "sg:city":"Boston",
    "sg:classifiers":[
        {
            "category":"Personal",
            "subcategory":"Beauty Salon",
            "type":"Services"
        }
    ],
    "sg:phone":"+1 617 357 3205",
    "sg:postcode":"02111",
    "sg:province":"MA",
    "sg:website":"http://www.premiersalons.com",
    "wof:name":"Premier Salon 21680",
    "wof:placetype":"venue"
},
  "geometry": {"coordinates":[-71.060827,42.355083],"type":"Point"}
}