{
  "type": "Feature",
  "properties": {
    "iso:country":"US",
    "sg:address":"47 Trefton Dr",
    "sg:city":"Braintree",
    "sg:classifiers":[
        {
            "category":"Building & Trades",
            "subcategory":"Electrical",
            "type":"Services"
        }
    ],
    "sg:phone":"+1 781 848 1265",
    "sg:postcode":"02184",
    "sg:province":"MA",
    "sg:tags":[
        "electrician"
    ],
    "wof:name":"Robert Leahy Electric",
    "wof:placetype":"venue"
},
  "geometry": {"coordinates":[-70.969038,42.229906],"type":"Point"}
}