{
  "type": "Feature",
  "properties": {
    "addr:full": "942 Falmouth Rd Hyannis MA 02601",
    "addr:housenumber": "942",
    "addr:postcode": "02601",
    "addr:street": "Falmouth Rd",
    "iso:country": "US",
    "sg:address": "942 Falmouth Rd",
    "sg:city": "Hyannis",
    "sg:classifiers": [
      {
        "category": "Manufacturing",
        "subcategory": "Signs",
        "type": "Manufacturing \u0026 Wholesale Goods"
      }
    ],
    "sg:phone": "+1 508 775 1218",
    "sg:postcode": "02601",
    "sg:province": "MA",
    "sg:tags": [
      "advertising",
      "specialty"
    ],
    "wof:name": "John Carlson Signs",
    "wof:placetype": "venue"
  },
  "geometry": {"coordinates":[-70.322929,41.659818],"type":"Point"}
}
