{
  "type": "Feature",
  "properties": {
    "addr:full":"1587 Ware St Palmer MA 01069",
    "addr:housenumber":"1587",
    "addr:postcode":"01069",
    "addr:street":"Ware St",
    "iso:country":"US",
    "sg:address":"1587 Ware St",
    "sg:city":"Palmer",
    "sg:classifiers":[
        {
            "category":"Building & Trades",
            "subcategory":"Landscaping Services",
            "type":"Services"
        }
    ],
    "sg:phone":"+1 413 289 1909",
    "sg:postcode":"01069",
    "sg:province":"MA",
    "sg:tags":[
        "landscape",
        "contractor"
    ],
    "wof:name":"G A Hitchcock Inc",
    "wof:placetype":"venue"
},
  "geometry": {"coordinates":[-72.29559399999999,42.226574],"type":"Point"}
}