{
  "type": "Feature",
  "properties": {
    "iso:country":"US",
    "sg:address":"53 E Central St",
    "sg:city":"Natick",
    "sg:classifiers":[
        {
            "category":"Building & Trades",
            "subcategory":"Construction",
            "type":"Services"
        }
    ],
    "sg:phone":"+1 508 652 0999",
    "sg:postcode":"01760",
    "sg:province":"MA",
    "sg:tags":[
        "asbestos",
        "removal"
    ],
    "wof:name":"Environmental Abatement Tech",
    "wof:placetype":"venue"
},
  "geometry": {"coordinates":[-71.340825,42.284943],"type":"Point"}
}