{
  "type": "Feature",
  "properties": {
    "iso:country":"US",
    "sg:address":"985 Main St",
    "sg:city":"Holden",
    "sg:classifiers":[
        {
            "category":"Restaurant",
            "type":"Food & Drink"
        }
    ],
    "sg:phone":"+1 508 829 5030",
    "sg:postcode":"01520",
    "sg:province":"MA",
    "sg:tags":[
        "eating"
    ],
    "wof:name":"Orbit Pizza",
    "wof:placetype":"venue"
},
  "geometry": {"coordinates":[-71.85474000000001,42.345367],"type":"Point"}
}