{
  "type": "Feature",
  "properties": {
    "addr:full": "985 Main St Holden MA 01520",
    "addr:housenumber": "985",
    "addr:postcode": "01520",
    "addr:street": "Main St",
    "iso:country": "US",
    "ovtr:label": "Orbit Pizza, 985 Main St Holden MA US",
    "ovtr:similarity": 2.312498092651367,
    "sg:address": "985 Main St",
    "sg:city": "Holden",
    "sg:classifiers": [
      {
        "category": "Restaurant",
        "type": "Food \u0026 Drink"
      }
    ],
    "sg:phone": "+1 508 829 5030",
    "sg:postcode": "01520",
    "sg:province": "MA",
    "sg:tags": [
      "eating"
    ],
    "wof:name": "Orbit Pizza",
    "wof:placetype": "venue"
  },
  "geometry": {"coordinates":[-71.85474,42.345367],"type":"Point"}
}
