{
  "type": "Feature",
  "properties": {
    "addr:full": "30 Lowell St Cambridge MA 02138",
    "addr:housenumber": "30",
    "addr:postcode": "02138",
    "addr:street": "Lowell St",
    "iso:country": "US",
    "sg:address": "30 Lowell St",
    "sg:city": "Cambridge",
    "sg:classifiers": [
      {
        "category": "Travel",
        "subcategory": "Hotels \u0026 Motels",
        "type": "Entertainment"
      },
      {
        "category": "Real Estate",
        "subcategory": "Real Estate Operator",
        "type": "Services"
      }
    ],
    "sg:phone": "+1 617 354 3500",
    "sg:postcode": "02138",
    "sg:province": "MA",
    "sg:tags": [
      "apartment"
    ],
    "wof:name": "Harvard Sq Short \u0026 Long Term by Corporate Stay",
    "wof:placetype": "venue"
  },
  "geometry": {"coordinates":[-71.1334,42.375702],"type":"Point"}
}
