{
  "type": "Feature",
  "properties": {
    "addr:full":"30 Lowell St Cambridge MA 02138",
    "addr:housenumber":"30",
    "addr:postcode":"02138",
    "addr:street":"Lowell St",
    "iso:country":"US",
    "sg:address":"30 Lowell St",
    "sg:city":"Cambridge",
    "sg:classifiers":[
        {
            "category":"Travel",
            "subcategory":"Hotels & Motels",
            "type":"Entertainment"
        },
        {
            "category":"Real Estate",
            "subcategory":"Real Estate Operator",
            "type":"Services"
        }
    ],
    "sg:phone":"+1 617 354 3500",
    "sg:postcode":"02138",
    "sg:province":"MA",
    "sg:tags":[
        "apartment"
    ],
    "wof:name":"Harvard Sq Short & Long Term by Corporate Stay",
    "wof:placetype":"venue"
},
  "geometry": {"coordinates":[-71.13339999999999,42.375702],"type":"Point"}
}