{
  "type": "Feature",
  "properties": {
    "addr:full":"165 Hawthorne St Malden MA 02148",
    "addr:housenumber":"165",
    "addr:postcode":"02148",
    "addr:street":"Hawthorne St",
    "iso:country":"US",
    "sg:address":"165 Hawthorne St",
    "sg:city":"Malden",
    "sg:classifiers":[
        {
            "category":"Professional",
            "subcategory":"Management & Consulting",
            "type":"Services"
        }
    ],
    "sg:phone":"+1   ",
    "sg:postcode":"02148",
    "sg:province":"MA",
    "sg:tags":[
        "business"
    ],
    "wof:name":"Scad Inc",
    "wof:placetype":"venue"
},
  "geometry": {"coordinates":[-71.080895,42.432968],"type":"Point"}
}