{
  "type": "Feature",
  "properties": {
    "iso:country":"US",
    "sg:address":"1362 Beacon St",
    "sg:city":"Brookline",
    "sg:classifiers":[
        {
            "category":"Personal",
            "subcategory":"Day Spa",
            "type":"Services"
        },
        {
            "category":"Personal",
            "subcategory":"Skin Care",
            "type":"Services"
        }
    ],
    "sg:phone":"+1 617 264 7546",
    "sg:postcode":"02446",
    "sg:province":"MA",
    "sg:website":"www.violetskinboutique.com",
    "wof:name":"Violet Skin Boutique",
    "wof:placetype":"venue"
},
  "geometry": {"coordinates":[-71.122826,42.341951],"type":"Point"}
}