{
  "type": "Feature",
  "properties": {
    "addr:full": "185 Exchange St Chicopee MA 01013",
    "addr:housenumber": "185",
    "addr:postcode": "01013",
    "addr:street": "Exchange St",
    "iso:country": "US",
    "sg:address": "185 Exchange St",
    "sg:city": "Chicopee",
    "sg:classifiers": [
      {
        "category": "Building \u0026 Trades",
        "subcategory": "Equipment Rental",
        "type": "Services"
      }
    ],
    "sg:phone": "+1   ",
    "sg:postcode": "01013",
    "sg:province": "MA",
    "sg:tags": [
      "home",
      "furniture",
      "appliance",
      "entertainment"
    ],
    "wof:name": "Rainbow Rentals Inc",
    "wof:placetype": "venue"
  },
  "geometry": {"coordinates":[-72.608809,42.147957],"type":"Point"}
}
