{
  "type": "Feature",
  "properties": {
    "iso:country":"US",
    "sg:address":"6212 Arbor Dr",
    "sg:city":"Shrewsbury",
    "sg:classifiers":[
        {
            "category":"Retail",
            "subcategory":"Laundry & Dry Cleaning",
            "type":"Services"
        }
    ],
    "sg:phone":"+1 508 792 3988",
    "sg:postcode":"01545",
    "sg:province":"MA",
    "sg:tags":[
        "cleaners",
        "rug",
        "carpet"
    ],
    "wof:name":"Stanley Steemer Carpet Cleaner",
    "wof:placetype":"venue"
},
  "geometry": {"coordinates":[-71.68666399999999,42.280159],"type":"Point"}
}