{
  "type": "Feature",
  "properties": {
    "iso:country":"US",
    "sg:address":"24 Mulberry St",
    "sg:city":"Worcester",
    "sg:classifiers":[
        {
            "category":"Organizations",
            "subcategory":"Religious Organization",
            "type":"Services"
        }
    ],
    "sg:phone":"+1 508 752 2964",
    "sg:postcode":"01605",
    "sg:province":"MA",
    "wof:name":"Our Lady-Mount Carmel",
    "wof:placetype":"venue"
},
  "geometry": {"coordinates":[-71.79320199999999,42.263315],"type":"Point"}
}