{
  "type": "Feature",
  "properties": {
    "iso:country":"US",
    "sg:address":"34 Jackson St",
    "sg:city":"Lowell",
    "sg:classifiers":[
        {
            "category":"Bars & Pubs",
            "type":"Food & Drink"
        },
        {
            "category":"Restaurant",
            "type":"Food & Drink"
        },
        {
            "category":"Bars & Pubs",
            "subcategory":"Lounge",
            "type":"Food & Drink"
        }
    ],
    "sg:phone":"+1 978 458 9482",
    "sg:postcode":"01852",
    "sg:province":"MA",
    "sg:tags":[
        "cocktail"
    ],
    "wof:name":"Majors Inc",
    "wof:placetype":"venue"
},
  "geometry": {"coordinates":[-71.309692,42.642342],"type":"Point"}
}