{
  "type": "Feature",
  "properties": {
    "addr:full": "34 Jackson St Lowell MA 01852",
    "addr:housenumber": "34",
    "addr:postcode": "01852",
    "addr:street": "Jackson St",
    "iso:country": "US",
    "sg:address": "34 Jackson St",
    "sg:city": "Lowell",
    "sg:classifiers": [
      {
        "category": "Bars \u0026 Pubs",
        "type": "Food \u0026 Drink"
      },
      {
        "category": "Restaurant",
        "type": "Food \u0026 Drink"
      },
      {
        "category": "Bars \u0026 Pubs",
        "subcategory": "Lounge",
        "type": "Food \u0026 Drink"
      }
    ],
    "sg:phone": "+1 978 458 9482",
    "sg:postcode": "01852",
    "sg:province": "MA",
    "sg:tags": [
      "cocktail"
    ],
    "wof:name": "Majors Inc",
    "wof:placetype": "venue"
  },
  "geometry": {"coordinates":[-71.309692,42.642342],"type":"Point"}
}
