{
  "type": "Feature",
  "properties": {
    "iso:country":"US",
    "sg:address":"18 James St",
    "sg:city":"South Yarmouth",
    "sg:classifiers":[
        {
            "category":"Professional",
            "subcategory":"Accounting & Tax Preparation",
            "type":"Services"
        }
    ],
    "sg:phone":"+1 508 394 0341",
    "sg:postcode":"02664",
    "sg:province":"MA",
    "sg:tags":[
        "bookkeeping",
        "general"
    ],
    "wof:name":"Back On Track Bookkeeping Svc",
    "wof:placetype":"venue"
},
  "geometry": {"coordinates":[-70.19695900000001,41.673054],"type":"Point"}
}