{
  "type": "Feature",
  "properties": {
    "addr:full": "38 W Main St Apt 213 Merrimac MA 01860",
    "addr:housenumber": "38;213",
    "addr:postcode": "01860",
    "addr:street": "W Main St Apt",
    "iso:country": "US",
    "sg:address": "38 W Main St Apt 213",
    "sg:city": "Merrimac",
    "sg:classifiers": [
      {
        "category": "Real Estate",
        "subcategory": "Real Estate Operator",
        "type": "Services"
      }
    ],
    "sg:phone": "+1 978 346 8049",
    "sg:postcode": "01860",
    "sg:province": "MA",
    "sg:tags": [
      "apartment"
    ],
    "wof:name": "Carriage Square Apartments",
    "wof:placetype": "venue"
  },
  "geometry": {"coordinates":[-71.005211,42.83152],"type":"Point"}
}
