{
  "type": "Feature",
  "properties": {
    "addr:full": "85 Scott Dr Pittsfield MA 01201",
    "addr:housenumber": "85",
    "addr:postcode": "01201",
    "addr:street": "Scott Dr",
    "iso:country": "US",
    "sg:address": "85 Scott Dr",
    "sg:city": "Pittsfield",
    "sg:classifiers": [
      {
        "category": "Professional",
        "subcategory": "Lawyer \u0026 Legal Services",
        "type": "Services"
      }
    ],
    "sg:phone": "+1 413 443 4341",
    "sg:postcode": "01201",
    "sg:province": "MA",
    "sg:tags": [
      "attorney"
    ],
    "wof:name": "Philip A Vachon",
    "wof:placetype": "venue"
  },
  "geometry": {"coordinates":[-73.273054,42.437163],"type":"Point"}
}
