{
  "type": "Feature",
  "properties": {
    "iso:country":"US",
    "sg:address":"14 Clapp St",
    "sg:city":"Norton",
    "sg:classifiers":[
        {
            "category":"Building & Trades",
            "subcategory":"Construction",
            "type":"Services"
        }
    ],
    "sg:phone":"+1 508 285 5957",
    "sg:postcode":"02766",
    "sg:province":"MA",
    "sg:tags":[
        "altering",
        "remodeling",
        "operative",
        "contractor"
    ],
    "wof:name":"K & K Cnstr & Cstm Carpentry",
    "wof:placetype":"venue"
},
  "geometry": {"coordinates":[-71.18647300000001,41.962031],"type":"Point"}
}