{
  "type": "Feature",
  "properties": {
    "addr:full": "283 Broadway Cambridge MA 02139",
    "addr:housenumber": "283",
    "addr:postcode": "02139",
    "addr:street": "Broadway",
    "iso:country": "US",
    "ovtr:label": "Yayla Tribal Rugs, Inc., 283 Broadway Cambridge MA US",
    "ovtr:similarity": 3.962580919265747,
    "sg:address": "283 Broadway",
    "sg:city": "Cambridge",
    "sg:classifiers": [
      {
        "category": "Home \u0026 Garden",
        "subcategory": "Carpets \u0026 Floor Coverings",
        "type": "Retail Goods"
      }
    ],
    "sg:phone": "+1 617 576 3249",
    "sg:postcode": "02139",
    "sg:province": "MA",
    "sg:tags": [
      "rug",
      "carpeting"
    ],
    "sg:website": "http://www.yayla.com",
    "wof:name": "Yayla Tribal Rugs",
    "wof:placetype": "venue"
  },
  "geometry": {"coordinates":[-71.098503,42.368198],"type":"Point"}
}
