{
  "type": "Feature",
  "properties": {
    "iso:country":"US",
    "sg:address":"283 Broadway",
    "sg:city":"Cambridge",
    "sg:classifiers":[
        {
            "category":"Home & Garden",
            "subcategory":"Carpets & Floor Coverings",
            "type":"Retail Goods"
        }
    ],
    "sg:phone":"+1 617 576 3249",
    "sg:postcode":"02139",
    "sg:province":"MA",
    "sg:tags":[
        "rug",
        "carpeting"
    ],
    "sg:website":"http://www.yayla.com",
    "wof:name":"Yayla Tribal Rugs",
    "wof:placetype":"venue"
},
  "geometry": {"coordinates":[-71.09850299999999,42.368198],"type":"Point"}
}