{
  "type": "Feature",
  "properties": {
    "iso:country":"US",
    "sg:address":"324 Winton St",
    "sg:city":"Springfield",
    "sg:classifiers":[
        {
            "category":"Personal",
            "subcategory":"Beauty Salon",
            "type":"Services"
        }
    ],
    "sg:phone":"+1 413 796 9750",
    "sg:postcode":"01118",
    "sg:province":"MA",
    "sg:tags":[
        "shop"
    ],
    "wof:name":"Collette's Hair Care",
    "wof:placetype":"venue"
},
  "geometry": {"coordinates":[-72.53413999999999,42.103215],"type":"Point"}
}