{
  "type": "Feature",
  "properties": {
    "addr:full": "167 Maple St Danvers MA 01923",
    "addr:housenumber": "167",
    "addr:postcode": "01923",
    "addr:street": "Maple St",
    "iso:country": "US",
    "sg:address": "167 Maple St",
    "sg:city": "Danvers",
    "sg:classifiers": [
      {
        "category": "Retail",
        "subcategory": "Funeral Services",
        "type": "Services"
      }
    ],
    "sg:phone": "+1 978 774 6600",
    "sg:postcode": "01923",
    "sg:province": "MA",
    "sg:tags": [
      "director"
    ],
    "wof:name": "Peterson-O'Donnell Funeral Hm",
    "wof:placetype": "venue"
  },
  "geometry": {"coordinates":[-70.941859,42.570958],"type":"Point"}
}
