{
  "type": "Feature",
  "properties": {
    "addr:full": "136 Main St Brockton MA 02301",
    "addr:housenumber": "136",
    "addr:postcode": "02301",
    "addr:street": "Main St",
    "iso:country": "US",
    "sg:address": "136 Main St",
    "sg:city": "Brockton",
    "sg:classifiers": [
      {
        "category": "Real Estate",
        "subcategory": "Real Estate Agent",
        "type": "Services"
      }
    ],
    "sg:phone": "+1 508 583 6999",
    "sg:postcode": "02301",
    "sg:province": "MA",
    "wof:name": "South Shore Realty",
    "wof:placetype": "venue"
  },
  "geometry": {"coordinates":[-71.019884,42.082475],"type":"Point"}
}
