{
  "type": "Feature",
  "properties": {
    "iso:country":"US",
    "sg:address":"875 Main Street",
    "sg:city":"Malden",
    "sg:classifiers":[
        {
            "category":"Autos & Motor Vehicles",
            "subcategory":"Fuel & Gas Station",
            "type":"Retail Goods"
        }
    ],
    "sg:phone":"+1 781 324 9367",
    "sg:postcode":"02148",
    "sg:province":"MA",
    "wof:name":"World Gas",
    "wof:placetype":"venue"
},
  "geometry": {"coordinates":[-71.067868,42.435433],"type":"Point"}
}