{
  "type": "Feature",
  "properties": {
    "iso:country":"US",
    "sg:address":"857 Market St",
    "sg:city":"Rockland",
    "sg:classifiers":[
        {
            "category":"Home & Garden",
            "subcategory":"Furniture",
            "type":"Retail Goods"
        }
    ],
    "sg:phone":"+1 781 982 9105",
    "sg:postcode":"02370",
    "sg:province":"MA",
    "sg:tags":[
        "top",
        "counter"
    ],
    "wof:name":"Absolute Stone",
    "wof:placetype":"venue"
},
  "geometry": {"coordinates":[-70.891171,42.119777],"type":"Point"}
}