{
  "type": "Feature",
  "properties": {
    "addr:full":"100 Independence Way Danvers MA 01923",
    "addr:housenumber":"100",
    "addr:postcode":"01923",
    "addr:street":"Independence Way",
    "iso:country":"US",
    "sg:address":"100 Independence Way",
    "sg:city":"Danvers",
    "sg:classifiers":[
        {
            "category":"Home & Garden",
            "subcategory":"Furniture",
            "type":"Retail Goods"
        }
    ],
    "sg:phone":"+1 978 774 7260",
    "sg:postcode":"01923",
    "sg:province":"MA",
    "sg:website":"www.kempent.com",
    "wof:name":"Kemp Furniture",
    "wof:placetype":"venue"
},
  "geometry": {"coordinates":[-70.938069,42.550814],"type":"Point"}
}