{
  "type": "Feature",
  "properties": {
    "addr:full":"9 Amelia Dr Nantucket MA 02554",
    "addr:housenumber":"9",
    "addr:postcode":"02554",
    "addr:street":"Amelia Dr",
    "iso:country":"US",
    "sg:address":"9 Amelia Dr",
    "sg:city":"Nantucket",
    "sg:classifiers":[
        {
            "category":"Shopping",
            "subcategory":"Computers & Home Electronics",
            "type":"Retail Goods"
        }
    ],
    "sg:phone":"+1 508 228 8000",
    "sg:postcode":"02554",
    "sg:province":"MA",
    "sg:tags":[
        "television",
        "radio"
    ],
    "wof:name":"Plum TV",
    "wof:placetype":"venue"
},
  "geometry": {"coordinates":[-70.08453,41.267619],"type":"Point"}
}