{
  "type": "Feature",
  "properties": {
    "addr:full":"692 S. Franklin St. Rte. 37 Holbrook MA 02343",
    "addr:housenumber":"692",
    "addr:postcode":"02343",
    "addr:street":"S. Franklin St. Rte. 37",
    "iso:country":"US",
    "sg:address":"692 S. Franklin St. Rte. 37",
    "sg:city":"Holbrook",
    "sg:classifiers":[
        {
            "category":"Retail",
            "subcategory":"Storage",
            "type":"Services"
        }
    ],
    "sg:phone":"+1 781 767 7106",
    "sg:postcode":"02343",
    "sg:province":"MA",
    "sg:tags":[
        "self"
    ],
    "sg:website":"www.thestorageprosonline.com",
    "wof:name":"Storage Pros Self Storage",
    "wof:placetype":"venue"
},
  "geometry": {"coordinates":[-71.117659,42.310742],"type":"Point"}
}