{
  "type": "Feature",
  "properties": {
    "addr:full": "334 Main St Great Barrington MA 01230",
    "addr:housenumber": "334",
    "addr:postcode": "01230",
    "addr:street": "Main St",
    "iso:country": "US",
    "sg:address": "334 Main St",
    "sg:city": "Great Barrington",
    "sg:classifiers": [
      {
        "category": "Professional",
        "subcategory": "Business Services",
        "type": "Services"
      },
      {
        "category": "Government",
        "subcategory": "Office",
        "type": "Public Place"
      }
    ],
    "sg:phone": "+1 413 528 3032",
    "sg:postcode": "01230",
    "sg:province": "MA",
    "sg:tags": [
      "building",
      "inspector",
      "village"
    ],
    "wof:name": "Great Brrington Bldg Inspector",
    "wof:placetype": "venue"
  },
  "geometry": {"coordinates":[-73.363136,42.193503],"type":"Point"}
}
