{
  "type": "Feature",
  "properties": {
    "addr:full":"23 Centennial St Plymouth MA 02360",
    "addr:housenumber":"23",
    "addr:postcode":"02360",
    "addr:street":"Centennial St",
    "iso:country":"US",
    "sg:address":"23 Centennial St",
    "sg:city":"Plymouth",
    "sg:classifiers":[
        {
            "category":"Professional",
            "subcategory":"Business Services",
            "type":"Services"
        }
    ],
    "sg:phone":"+1 508 746 4030",
    "sg:postcode":"02360",
    "sg:province":"MA",
    "sg:tags":[
        "paging",
        "answering"
    ],
    "wof:name":"Avetel Computer & Answering",
    "wof:placetype":"venue"
},
  "geometry": {"coordinates":[-70.683932,41.969599],"type":"Point"}
}