{
  "type": "Feature",
  "properties": {
    "iso:country":"US",
    "sg:address":"272 Magnet Way",
    "sg:city":"Brewster",
    "sg:classifiers":[
        {
            "category":"Retail",
            "subcategory":"Repair Shop",
            "type":"Services"
        }
    ],
    "sg:phone":"+1 508 896 2999",
    "sg:postcode":"02631",
    "sg:province":"MA",
    "sg:tags":[
        "refinishing",
        "furniture"
    ],
    "wof:name":"Bayside Woodworks",
    "wof:placetype":"venue"
},
  "geometry": {"coordinates":[-70.03827099999999,41.747575],"type":"Point"}
}