{
  "type": "Feature",
  "properties": {
    "addr:full": "272 Magnet Way Brewster MA 02631",
    "addr:housenumber": "272",
    "addr:postcode": "02631",
    "addr:street": "Magnet Way",
    "iso:country": "US",
    "sg:address": "272 Magnet Way",
    "sg:city": "Brewster",
    "sg:classifiers": [
      {
        "category": "Retail",
        "subcategory": "Repair Shop",
        "type": "Services"
      }
    ],
    "sg:phone": "+1 508 896 2999",
    "sg:postcode": "02631",
    "sg:province": "MA",
    "sg:tags": [
      "refinishing",
      "furniture"
    ],
    "wof:name": "Bayside Woodworks",
    "wof:placetype": "venue"
  },
  "geometry": {"coordinates":[-70.038271,41.747575],"type":"Point"}
}
