{
  "type": "Feature",
  "properties": {
    "iso:country":"US",
    "sg:address":"155 Maple St Ste 206",
    "sg:city":"Springfield",
    "sg:classifiers":[
        {
            "category":"Health Services",
            "subcategory":"Doctor",
            "type":"Services"
        },
        {
            "category":"Health Services",
            "subcategory":"Podiatrist",
            "type":"Services"
        }
    ],
    "sg:phone":"+1 413 739 2931",
    "sg:postcode":"01105",
    "sg:province":"MA",
    "sg:tags":[
        "physician",
        "surgeon",
        "surgeons"
    ],
    "wof:name":"Marc A Fisher Md",
    "wof:placetype":"venue"
},
  "geometry": {"coordinates":[-72.579521,42.100014],"type":"Point"}
}