{
  "type": "Feature",
  "properties": {
    "iso:country":"US",
    "sg:address":"273 Cambridge Rd Apt 709",
    "sg:city":"Woburn",
    "sg:classifiers":[
        {
            "category":"Personal",
            "subcategory":"Beauty Salon",
            "type":"Services"
        }
    ],
    "sg:phone":"+1 781 938 8508",
    "sg:postcode":"01801",
    "sg:province":"MA",
    "wof:name":"Studio Six Group",
    "wof:placetype":"venue"
},
  "geometry": {"coordinates":[-71.16777,42.461281],"type":"Point"}
}