{
  "type": "Feature",
  "properties": {
    "addr:full":"233 Westford St Lowell MA 01851",
    "addr:housenumber":"233",
    "addr:postcode":"01851",
    "addr:street":"Westford St",
    "iso:country":"US",
    "sg:address":"233 Westford St",
    "sg:city":"Lowell",
    "sg:classifiers":[
        {
            "category":"Professional",
            "subcategory":"Employment Agencies",
            "type":"Services"
        }
    ],
    "sg:phone":"+1 978 452 0760",
    "sg:postcode":"01851",
    "sg:province":"MA",
    "sg:tags":[
        "help",
        "contractor"
    ],
    "wof:name":"Quality Temp Svc",
    "wof:placetype":"venue"
},
  "geometry": {"coordinates":[-71.32411,42.635739],"type":"Point"}
}