{
  "type": "Feature",
  "properties": {
    "iso:country":"US",
    "sg:address":"130 Liberty St",
    "sg:city":"Brockton",
    "sg:classifiers":[
        {
            "category":"Professional",
            "subcategory":"Accounting & Tax Preparation",
            "type":"Services"
        }
    ],
    "sg:phone":"+1 508 588 5960",
    "sg:postcode":"02301",
    "sg:province":"MA",
    "sg:tags":[
        "accountant"
    ],
    "wof:name":"Glen Ilacqua CPA",
    "wof:placetype":"venue"
},
  "geometry": {"coordinates":[-71.063059,42.057841],"type":"Point"}
}