{
  "type": "Feature",
  "properties": {
    "iso:country":"US",
    "sg:address":"853 Turnpike St",
    "sg:city":"North Andover",
    "sg:classifiers":[
        {
            "category":"Professional",
            "subcategory":"Employment Agencies",
            "type":"Services"
        }
    ],
    "sg:phone":"+1 978 687 1993",
    "sg:postcode":"01845",
    "sg:province":"MA",
    "sg:tags":[
        "consultant",
        "search",
        "executive"
    ],
    "sg:website":"www.straubeassociates.com",
    "wof:name":"Straube Associates",
    "wof:placetype":"venue"
},
  "geometry": {"coordinates":[-71.104146,42.657309],"type":"Point"}
}