{
  "type": "Feature",
  "properties": {
    "iso:country":"US",
    "sg:address":"70 Erin Rd",
    "sg:city":"Stoughton",
    "sg:classifiers":[
        {
            "category":"Real Estate",
            "subcategory":"Real Estate Operator",
            "type":"Services"
        }
    ],
    "sg:phone":"+1 781 344 1788",
    "sg:postcode":"02072",
    "sg:province":"MA",
    "sg:tags":[
        "condominium"
    ],
    "wof:name":"Knollsbrook Condominiums",
    "wof:placetype":"venue"
},
  "geometry": {"coordinates":[-71.137469,42.138787],"type":"Point"}
}