{
  "type": "Feature",
  "properties": {
    "addr:full":"3455 Main St Springfield MA 01107",
    "addr:housenumber":"3455",
    "addr:postcode":"01107",
    "addr:street":"Main St",
    "iso:country":"US",
    "sg:address":"3455 Main St",
    "sg:city":"Springfield",
    "sg:classifiers":[
        {
            "category":"Health Services",
            "subcategory":"Doctor",
            "type":"Services"
        }
    ],
    "sg:phone":"+1 413 746 9142",
    "sg:postcode":"01107",
    "sg:province":"MA",
    "sg:tags":[
        "physician",
        "surgeon"
    ],
    "wof:name":"Bay State Orthopedics Inc",
    "wof:placetype":"venue"
},
  "geometry": {"coordinates":[-72.610007,42.124192],"type":"Point"}
}