{
  "type": "Feature",
  "properties": {
    "iso:country":"US",
    "sg:address":"527 Dwight St",
    "sg:city":"Holyoke",
    "sg:classifiers":[
        {
            "category":"Organizations",
            "subcategory":"Religious Organization",
            "type":"Services"
        }
    ],
    "sg:phone":"+1 413 539 9952",
    "sg:postcode":"01040",
    "sg:province":"MA",
    "sg:tags":[
        "church"
    ],
    "wof:name":"True Deliverance Church Of God",
    "wof:placetype":"venue"
},
  "geometry": {"coordinates":[-72.606505,42.20652],"type":"Point"}
}