{
  "type": "Feature",
  "properties": {
    "iso:country":"US",
    "sg:address":"109 Keene Rd",
    "sg:city":"Acushnet",
    "sg:classifiers":[
        {
            "category":"Building & Trades",
            "subcategory":"Construction",
            "type":"Services"
        }
    ],
    "sg:phone":"+1   ",
    "sg:postcode":"02743",
    "sg:province":"MA",
    "sg:tags":[
        "house"
    ],
    "wof:name":"Don Sorelle Const",
    "wof:placetype":"venue"
},
  "geometry": {"coordinates":[-70.92187699999999,41.748494],"type":"Point"}
}