{
  "type": "Feature",
  "properties": {
    "iso:country":"US",
    "sg:address":"586 Abbott Ave",
    "sg:city":"Leominster",
    "sg:classifiers":[
        {
            "category":"Communications",
            "subcategory":"Film & Video Production",
            "type":"Services"
        }
    ],
    "sg:phone":"+1   ",
    "sg:postcode":"01453",
    "sg:province":"MA",
    "wof:name":"Moving Mment Video Photography",
    "wof:placetype":"venue"
},
  "geometry": {"coordinates":[-71.775677,42.553713],"type":"Point"}
}