{
  "type": "Feature",
  "properties": {
    "iso:country":"US",
    "sg:address":"4 New York Ave",
    "sg:city":"Framingham",
    "sg:classifiers":[
        {
            "category":"Professional",
            "subcategory":"Advertising",
            "type":"Services"
        }
    ],
    "sg:phone":"+1 508 628 9558",
    "sg:postcode":"01701",
    "sg:province":"MA",
    "sg:tags":[
        "mailing",
        "shipping"
    ],
    "wof:name":"Field Co",
    "wof:placetype":"venue"
},
  "geometry": {"coordinates":[-71.489052,42.299927],"type":"Point"}
}