{
  "type": "Feature",
  "properties": {
    "addr:full": "1276 Massachusetts Ave Cambridge MA 02138",
    "addr:housenumber": "1276",
    "addr:postcode": "02138",
    "addr:street": "Massachusetts Ave",
    "iso:country": "US",
    "sg:address": "1276 Massachusetts Ave",
    "sg:city": "Cambridge",
    "sg:classifiers": [
      {
        "category": "Shopping",
        "subcategory": "Optician",
        "type": "Retail Goods"
      }
    ],
    "sg:phone": "+1 617 868 1500",
    "sg:postcode": "02138",
    "sg:province": "MA",
    "sg:tags": [
      "eyewear"
    ],
    "sg:website": "www.seeeyewear.com",
    "wof:name": "See Eyewear",
    "wof:placetype": "venue"
  },
  "geometry": {"coordinates":[-71.116705,42.372752],"type":"Point"}
}
