{
  "type": "Feature",
  "properties": {
    "addr:full":"2032 Winthrop St North Dighton MA 02764",
    "addr:housenumber":"2032",
    "addr:postcode":"02764",
    "addr:street":"Winthrop St",
    "iso:country":"US",
    "sg:address":"2032 Winthrop St",
    "sg:city":"North Dighton",
    "sg:classifiers":[
        {
            "category":"Home & Garden",
            "subcategory":"Furniture",
            "type":"Retail Goods"
        },
        {
            "category":"Home & Garden",
            "subcategory":"Carpets & Floor Coverings",
            "type":"Retail Goods"
        }
    ],
    "sg:phone":"+1 508 252 6456",
    "sg:postcode":"02764",
    "sg:province":"MA",
    "sg:tags":[
        "store",
        "mattress"
    ],
    "wof:name":"Bilodeau's",
    "wof:placetype":"venue"
},
  "geometry": {"coordinates":[-71.184601,41.873299],"type":"Point"}
}