{
  "type": "Feature",
  "properties": {
    "addr:full": "471 Washington St Wellesley MA 02482",
    "addr:housenumber": "471",
    "addr:postcode": "02482",
    "addr:street": "Washington St",
    "iso:country": "US",
    "sg:address": "471 Washington St",
    "sg:city": "Wellesley",
    "sg:classifiers": [
      {
        "category": "Manufacturing",
        "subcategory": "Printing",
        "type": "Manufacturing \u0026 Wholesale Goods"
      }
    ],
    "sg:phone": "+1 781 235 1264",
    "sg:postcode": "02482",
    "sg:province": "MA",
    "sg:tags": [
      "publisher"
    ],
    "wof:name": "International Media",
    "wof:placetype": "venue"
  },
  "geometry": {"coordinates":[-71.287207,42.301446],"type":"Point"}
}
