{
  "type": "Feature",
  "properties": {
    "addr:full":"1500 Pine St Dighton MA 02715",
    "addr:housenumber":"1500",
    "addr:postcode":"02715",
    "addr:street":"Pine St",
    "iso:country":"US",
    "sg:address":"1500 Pine St",
    "sg:city":"Dighton",
    "sg:classifiers":[
        {
            "category":"Organizations",
            "subcategory":"Religious Organization",
            "type":"Services"
        }
    ],
    "sg:phone":"+1   ",
    "sg:postcode":"02715",
    "sg:province":"MA",
    "wof:name":"Kingdom Hall Jhovahs Witnesses",
    "wof:placetype":"venue"
},
  "geometry": {"coordinates":[-71.14369000000001,41.835412],"type":"Point"}
}