{
  "type": "Feature",
  "properties": {
    "iso:country":"US",
    "sg:address":"14 School St",
    "sg:city":"Woods Hole",
    "sg:classifiers":[
        {
            "category":"Shopping",
            "type":"Retail Goods"
        }
    ],
    "sg:phone":"+1 508 548 7594",
    "sg:postcode":"02543",
    "sg:province":"MA",
    "sg:tags":[
        "art",
        "gallery",
        "dealer"
    ],
    "wof:name":"Woods Hole Gallery",
    "wof:placetype":"venue"
},
  "geometry": {"coordinates":[-70.669192,41.52382],"type":"Point"}
}