{
  "type": "Feature",
  "properties": {
    "addr:full": "85 Robert St Roslindale MA 02131",
    "addr:housenumber": "85",
    "addr:postcode": "02131",
    "addr:street": "Robert St",
    "iso:country": "US",
    "sg:address": "85 Robert St",
    "sg:city": "Roslindale",
    "sg:classifiers": [
      {
        "category": "Professional",
        "subcategory": "Accounting \u0026 Tax Preparation",
        "type": "Services"
      }
    ],
    "sg:phone": "+1 617 327 3669",
    "sg:postcode": "02131",
    "sg:province": "MA",
    "sg:tags": [
      "consultant"
    ],
    "wof:name": "Corporate Tax Strategies",
    "wof:placetype": "venue"
  },
  "geometry": {"coordinates":[-71.134672,42.288301],"type":"Point"}
}
