{
  "type": "Feature",
  "properties": {
    "iso:country":"US",
    "sg:address":"85 Robert St",
    "sg:city":"Roslindale",
    "sg:classifiers":[
        {
            "category":"Professional",
            "subcategory":"Accounting & Tax Preparation",
            "type":"Services"
        }
    ],
    "sg:phone":"+1 617 327 3669",
    "sg:postcode":"02131",
    "sg:province":"MA",
    "sg:tags":[
        "consultant"
    ],
    "wof:name":"Corporate Tax Strategies",
    "wof:placetype":"venue"
},
  "geometry": {"coordinates":[-71.13467199999999,42.288301],"type":"Point"}
}