{
  "type": "Feature",
  "properties": {
    "iso:country":"US",
    "sg:address":"810 Memorial Dr",
    "sg:city":"Cambridge",
    "sg:classifiers":[
        {
            "category":"Manufacturing",
            "subcategory":"Tools & Machinery",
            "type":"Manufacturing & Wholesale Goods"
        },
        {
            "category":"Manufacturing",
            "subcategory":"Electronics",
            "type":"Manufacturing & Wholesale Goods"
        },
        {
            "category":"Shopping",
            "subcategory":"Computers & Home Electronics",
            "type":"Retail Goods"
        }
    ],
    "sg:phone":"+1 617 661 7500",
    "sg:postcode":"02139",
    "sg:province":"MA",
    "sg:tags":[
        "electric",
        "consumer",
        "equipment-testing",
        "equipment",
        "supplies-wholesale",
        "manufacturer"
    ],
    "wof:name":"Sonitrol Services Of Boston",
    "wof:placetype":"venue"
},
  "geometry": {"coordinates":[-71.115891,42.360867],"type":"Point"}
}