{
  "type": "Feature",
  "properties": {
    "iso:country":"US",
    "sg:address":"165 Lynn Fells Pkwy",
    "sg:city":"Melrose",
    "sg:classifiers":[
        {
            "category":"Education",
            "subcategory":"Dance Studio",
            "type":"Public Place"
        }
    ],
    "sg:phone":"+1 781 665 1855",
    "sg:postcode":"02176",
    "sg:province":"MA",
    "wof:name":"Lets Dance Inc",
    "wof:placetype":"venue"
},
  "geometry": {"coordinates":[-71.07401299999999,42.462839],"type":"Point"}
}