{
  "type": "Feature",
  "properties": {
    "iso:country":"US",
    "sg:address":"307 Revere St",
    "sg:city":"Revere",
    "sg:classifiers":[
        {
            "category":"Restaurant",
            "type":"Food & Drink"
        },
        {
            "category":"Bakery",
            "type":"Food & Drink"
        }
    ],
    "sg:phone":"+1 781 289 4500",
    "sg:postcode":"02151",
    "sg:province":"MA",
    "wof:name":"Vincenzo's Bakery",
    "wof:placetype":"venue"
},
  "geometry": {"coordinates":[-70.998863,42.418468],"type":"Point"}
}