{
  "type": "Feature",
  "properties": {
    "addr:full": "307 Revere St Revere MA 02151",
    "addr:housenumber": "307",
    "addr:postcode": "02151",
    "addr:street": "Revere St",
    "iso:country": "US",
    "sg:address": "307 Revere St",
    "sg:city": "Revere",
    "sg:classifiers": [
      {
        "category": "Restaurant",
        "type": "Food \u0026 Drink"
      },
      {
        "category": "Bakery",
        "type": "Food \u0026 Drink"
      }
    ],
    "sg:phone": "+1 781 289 4500",
    "sg:postcode": "02151",
    "sg:province": "MA",
    "wof:name": "Vincenzo's Bakery",
    "wof:placetype": "venue"
  },
  "geometry": {"coordinates":[-70.998863,42.418468],"type":"Point"}
}
