{
  "type": "Feature",
  "properties": {
    "iso:country":"US",
    "sg:address":"2696 Cranberry Hwy",
    "sg:city":"Wareham",
    "sg:classifiers":[
        {
            "category":"Building & Trades",
            "subcategory":"Construction",
            "type":"Services"
        }
    ],
    "sg:phone":"+1 508 295 9040",
    "sg:postcode":"02571",
    "sg:province":"MA",
    "sg:tags":[
        "well",
        "drilling"
    ],
    "sg:website":"www.dragindrilling.com",
    "wof:name":"Dragin Drilling Inc",
    "wof:placetype":"venue"
},
  "geometry": {"coordinates":[-70.699783,41.769613],"type":"Point"}
}