{
  "type": "Feature",
  "properties": {
    "iso:country":"US",
    "sg:address":"1 Eustis St",
    "sg:city":"Roxbury",
    "sg:classifiers":[
        {
            "category":"Social Services",
            "subcategory":"Adult Care",
            "type":"Services"
        }
    ],
    "sg:phone":"+1 617 445 7140",
    "sg:postcode":"02119",
    "sg:province":"MA",
    "sg:tags":[
        "home",
        "group"
    ],
    "wof:name":"Nueva Vida",
    "wof:placetype":"venue"
},
  "geometry": {"coordinates":[-71.08126300000001,42.331385],"type":"Point"}
}