{
  "type": "Feature",
  "properties": {
    "addr:full": "800 Boylston St Boston MA 02199",
    "addr:housenumber": "800",
    "addr:postcode": "02199",
    "addr:street": "Boylston St",
    "iso:country": "US",
    "sg:address": "800 Boylston St",
    "sg:city": "Boston",
    "sg:classifiers": [
      {
        "category": "Shopping",
        "subcategory": "Computers \u0026 Home Electronics",
        "type": "Retail Goods"
      }
    ],
    "sg:phone": "+1 617 236 4432",
    "sg:postcode": "02199",
    "sg:province": "MA",
    "sg:tags": [
      "software"
    ],
    "sg:website": "www.gamestop.com",
    "wof:name": "Babbage's Etc",
    "wof:placetype": "venue"
  },
  "geometry": {"coordinates":[-71.083462,42.348406],"type":"Point"}
}
