{
  "type": "Feature",
  "properties": {
    "addr:full": "32 Blaiswood Ave Marlborough MA 01752",
    "addr:housenumber": "32",
    "addr:postcode": "01752",
    "addr:street": "Blaiswood Ave",
    "iso:country": "US",
    "sg:address": "32 Blaiswood Ave",
    "sg:city": "Marlborough",
    "sg:classifiers": [
      {
        "category": "Education",
        "subcategory": "Special Training",
        "type": "Public Place"
      }
    ],
    "sg:phone": "+1   ",
    "sg:postcode": "01752",
    "sg:province": "MA",
    "wof:name": "R Eston",
    "wof:placetype": "venue"
  },
  "geometry": {"coordinates":[-71.560954,42.365551],"type":"Point"}
}
