{
  "type": "Feature",
  "properties": {
    "addr:full": "42 Church St Everett MA 02149",
    "addr:housenumber": "42",
    "addr:postcode": "02149",
    "addr:street": "Church St",
    "iso:country": "US",
    "sg:address": "42 Church St",
    "sg:city": "Everett",
    "sg:classifiers": [
      {
        "category": "Place Of Worship",
        "subcategory": "Church",
        "type": "Public Place"
      },
      {
        "category": "Place Of Worship",
        "type": "Public Place"
      },
      {
        "category": "Organizations",
        "subcategory": "Religious Organization",
        "type": "Services"
      }
    ],
    "sg:phone": "+1 617 387 1673",
    "sg:postcode": "02149",
    "sg:province": "MA",
    "sg:tags": [
      "god",
      "god-independent",
      "churches-assemblies"
    ],
    "wof:name": "Fellowship Assembly Of God",
    "wof:placetype": "venue"
  },
  "geometry": {"coordinates":[-71.055631,42.408857],"type":"Point"}
}
