{
  "type": "Feature",
  "properties": {
    "iso:country":"US",
    "sg:address":"42 Church St",
    "sg:city":"Everett",
    "sg:classifiers":[
        {
            "category":"Place Of Worship",
            "subcategory":"Church",
            "type":"Public Place"
        },
        {
            "category":"Place Of Worship",
            "type":"Public Place"
        },
        {
            "category":"Organizations",
            "subcategory":"Religious Organization",
            "type":"Services"
        }
    ],
    "sg:phone":"+1 617 387 1673",
    "sg:postcode":"02149",
    "sg:province":"MA",
    "sg:tags":[
        "god",
        "god-independent",
        "churches-assemblies"
    ],
    "wof:name":"Fellowship Assembly Of God",
    "wof:placetype":"venue"
},
  "geometry": {"coordinates":[-71.05563100000001,42.408857],"type":"Point"}
}