{
  "type": "Feature",
  "properties": {
    "iso:country":"US",
    "sg:address":"12 Janice Rd",
    "sg:city":"Lynn",
    "sg:classifiers":[
        {
            "category":"Building & Trades",
            "subcategory":"Construction",
            "type":"Services"
        }
    ],
    "sg:phone":"+1 781 771 5196",
    "sg:postcode":"01904",
    "sg:province":"MA",
    "sg:tags":[
        "home",
        "improvement"
    ],
    "wof:name":"Mg Home Improvements",
    "wof:placetype":"venue"
},
  "geometry": {"coordinates":[-70.976782,42.505241],"type":"Point"}
}