{
  "type": "Feature",
  "properties": {
    "iso:country":"US",
    "sg:address":"122 Fairhaven Rd",
    "sg:city":"Mattapoisett",
    "sg:classifiers":[
        {
            "category":"Professional",
            "subcategory":"Detective & Security Services",
            "type":"Services"
        }
    ],
    "sg:phone":"+1 508 758 3267",
    "sg:postcode":"02739",
    "sg:province":"MA",
    "sg:tags":[
        "investigator"
    ],
    "wof:name":"R D Assoc Private Invstgtrs",
    "wof:placetype":"venue"
},
  "geometry": {"coordinates":[-70.84387099999999,41.654419],"type":"Point"}
}