{
  "type": "Feature",
  "properties": {
    "addr:full": "122 Fairhaven Rd Mattapoisett MA 02739",
    "addr:housenumber": "122",
    "addr:postcode": "02739",
    "addr:street": "Fairhaven Rd",
    "iso:country": "US",
    "sg:address": "122 Fairhaven Rd",
    "sg:city": "Mattapoisett",
    "sg:classifiers": [
      {
        "category": "Professional",
        "subcategory": "Detective \u0026 Security Services",
        "type": "Services"
      }
    ],
    "sg:phone": "+1 508 758 3267",
    "sg:postcode": "02739",
    "sg:province": "MA",
    "sg:tags": [
      "investigator"
    ],
    "wof:name": "R D Assoc Private Invstgtrs",
    "wof:placetype": "venue"
  },
  "geometry": {"coordinates":[-70.843871,41.654419],"type":"Point"}
}
