{
  "type": "Feature",
  "properties": {
    "addr:full":"41 Lincoln St Newton MA 02461",
    "addr:housenumber":"41",
    "addr:postcode":"02461",
    "addr:street":"Lincoln St",
    "iso:country":"US",
    "sg:address":"41 Lincoln St",
    "sg:city":"Newton",
    "sg:classifiers":[
        {
            "category":"Shopping",
            "subcategory":"Clothing, Apparel, & Fashions",
            "type":"Retail Goods"
        }
    ],
    "sg:phone":"+1 617 964 4435",
    "sg:postcode":"02461",
    "sg:province":"MA",
    "sg:tags":[
        "ready",
        "accessory"
    ],
    "wof:name":"Staccato",
    "wof:placetype":"venue"
},
  "geometry": {"coordinates":[-71.20649,42.321769],"type":"Point"}
}