{
  "type": "Feature",
  "properties": {
    "addr:full":"43 Woodruff Rd Walpole MA 02081",
    "addr:housenumber":"43",
    "addr:postcode":"02081",
    "addr:street":"Woodruff Rd",
    "iso:country":"US",
    "sg:address":"43 Woodruff Rd",
    "sg:city":"Walpole",
    "sg:classifiers":[
        {
            "category":"Building & Trades",
            "subcategory":"Construction",
            "type":"Services"
        }
    ],
    "sg:phone":"+1 508 668 2689",
    "sg:postcode":"02081",
    "sg:province":"MA",
    "sg:tags":[
        "general",
        "contractor"
    ],
    "wof:name":"Raymond L Allison Construction",
    "wof:placetype":"venue"
},
  "geometry": {"coordinates":[-71.23804199999999,42.172658],"type":"Point"}
}