{
  "type": "Feature",
  "properties": {
    "addr:full": "26 Main St Orleans MA 02653",
    "addr:housenumber": "26",
    "addr:postcode": "02653",
    "addr:street": "Main St",
    "iso:country": "US",
    "ovtr:label": "Orleans Cycle, 26 Main St Orleans MA US",
    "ovtr:similarity": 3.0571699142456055,
    "sg:address": "26 Main St",
    "sg:city": "Orleans",
    "sg:classifiers": [
      {
        "category": "Shopping",
        "subcategory": "Bicycles \u0026 Sporting Goods",
        "type": "Retail Goods"
      }
    ],
    "sg:phone": "+1 508 255 9115",
    "sg:postcode": "02653",
    "sg:province": "MA",
    "wof:name": "Orleans Cycle",
    "wof:placetype": "venue"
  },
  "geometry": {"coordinates":[-69.992024,41.788386],"type":"Point"}
}
