{
  "type": "Feature",
  "properties": {
    "addr:full":"12 Mariners Way Edgartown MA 02539",
    "addr:housenumber":"12",
    "addr:postcode":"02539",
    "addr:street":"Mariners Way",
    "iso:country":"US",
    "sg:address":"12 Mariners Way",
    "sg:city":"Edgartown",
    "sg:classifiers":[
        {
            "category":"Real Estate",
            "subcategory":"Real Estate Agent",
            "type":"Services"
        }
    ],
    "sg:phone":"+1 508 627 3337",
    "sg:postcode":"02539",
    "sg:province":"MA",
    "sg:tags":[
        "management"
    ],
    "wof:name":"Harborside Management",
    "wof:placetype":"venue"
},
  "geometry": {"coordinates":[-70.530798,41.394616],"type":"Point"}
}