{
  "type": "Feature",
  "properties": {
    "iso:country":"US",
    "sg:address":"13 Court St",
    "sg:city":"Plymouth",
    "sg:classifiers":[
        {
            "category":"Shopping",
            "subcategory":"Clothing, Apparel, & Fashions",
            "type":"Retail Goods"
        }
    ],
    "sg:phone":"+1 508 746 6033",
    "sg:postcode":"02360",
    "sg:province":"MA",
    "sg:tags":[
        "clothing",
        "boys'"
    ],
    "sg:website":"http://www.pilgrimsprogressclothing.com",
    "wof:name":"Pilgrim's Progress",
    "wof:placetype":"venue"
},
  "geometry": {"coordinates":[-70.665859,41.957506],"type":"Point"}
}