{
  "type": "Feature",
  "properties": {
    "addr:full":"5 Heatherwood Cir Saugus MA 01906",
    "addr:housenumber":"5",
    "addr:postcode":"01906",
    "addr:street":"Heatherwood Cir",
    "iso:country":"US",
    "sg:address":"5 Heatherwood Cir",
    "sg:city":"Saugus",
    "sg:classifiers":[
        {
            "category":"Insurance",
            "subcategory":"Insurance Agent",
            "type":"Services"
        }
    ],
    "sg:phone":"+1 781 231 2380",
    "sg:postcode":"01906",
    "sg:province":"MA",
    "sg:tags":[
        "adjuster"
    ],
    "wof:name":"Ball Brothers Adjustment Company",
    "wof:placetype":"venue"
},
  "geometry": {"coordinates":[-71.039652,42.466139],"type":"Point"}
}