{
  "type": "Feature",
  "properties": {
    "iso:country":"US",
    "sg:address":"25 S Main St",
    "sg:city":"Sherborn",
    "sg:classifiers":[
        {
            "category":"Social Services",
            "subcategory":"Child Care",
            "type":"Services"
        }
    ],
    "sg:phone":"+1 508 655 1451",
    "sg:postcode":"01770",
    "sg:province":"MA",
    "sg:tags":[
        "kindergarten",
        "academic",
        "school"
    ],
    "wof:name":"Rocking Horse School",
    "wof:placetype":"venue"
},
  "geometry": {"coordinates":[-71.367386,42.235176],"type":"Point"}
}