{
  "type": "Feature",
  "properties": {
    "addr:full":"505 Middlesex Tpke Billerica MA 01821",
    "addr:housenumber":"505",
    "addr:postcode":"01821",
    "addr:street":"Middlesex Tpke",
    "iso:country":"US",
    "sg:address":"505 Middlesex Tpke",
    "sg:city":"Billerica",
    "sg:classifiers":[
        {
            "category":"Building & Trades",
            "subcategory":"Construction",
            "type":"Services"
        }
    ],
    "sg:phone":"+1   ",
    "sg:postcode":"01821",
    "sg:province":"MA",
    "sg:tags":[
        "home",
        "speculative",
        "builder"
    ],
    "wof:name":"North Middlesex Cnstr Co",
    "wof:placetype":"venue"
},
  "geometry": {"coordinates":[-71.269751,42.538524],"type":"Point"}
}