{
  "type": "Feature",
  "properties": {
    "addr:full":"2 Pine Glen Rd North Reading MA 01864",
    "addr:housenumber":"2",
    "addr:postcode":"01864",
    "addr:street":"Pine Glen Rd",
    "iso:country":"US",
    "sg:address":"2 Pine Glen Rd",
    "sg:city":"North Reading",
    "sg:classifiers":[
        {
            "category":"Health Services",
            "subcategory":"Medical Lab",
            "type":"Services"
        }
    ],
    "sg:phone":"+1   ",
    "sg:postcode":"01864",
    "sg:province":"MA",
    "sg:tags":[
        "laboratory",
        "dental"
    ],
    "wof:name":"Reading Dental Prosthetic",
    "wof:placetype":"venue"
},
  "geometry": {"coordinates":[-71.100544,42.583954],"type":"Point"}
}