{
  "type": "Feature",
  "properties": {
    "iso:country":"US",
    "sg:address":"10 Beach Ct",
    "sg:city":"Gloucester",
    "sg:classifiers":[
        {
            "category":"Professional",
            "subcategory":"Lawyer & Legal Services",
            "type":"Services"
        }
    ],
    "sg:phone":"+1 978 283 7088",
    "sg:postcode":"01930",
    "sg:province":"MA",
    "sg:tags":[
        "attorney"
    ],
    "wof:name":"Norman C Ross Law Office",
    "wof:placetype":"venue"
},
  "geometry": {"coordinates":[-70.666775,42.609747],"type":"Point"}
}