{
  "type": "Feature",
  "properties": {
    "iso:country":"US",
    "sg:address":"560 Harrison Ave",
    "sg:city":"Boston",
    "sg:classifiers":[
        {
            "category":"Government",
            "subcategory":"Office",
            "type":"Public Place"
        }
    ],
    "sg:phone":"+1 617 654 9800",
    "sg:postcode":"02118",
    "sg:province":"MA",
    "wof:name":"Medicine Board Of Registration",
    "wof:placetype":"venue"
},
  "geometry": {"coordinates":[-71.067615,42.341087],"type":"Point"}
}