{
  "type": "Feature",
  "properties": {
    "iso:country":"US",
    "sg:address":"56 Centre St",
    "sg:city":"Middleboro",
    "sg:classifiers":[
        {
            "category":"Retail",
            "subcategory":"Laundry & Dry Cleaning",
            "type":"Services"
        }
    ],
    "sg:phone":"+1 508 946 1530",
    "sg:postcode":"02346",
    "sg:province":"MA",
    "sg:tags":[
        "cleaners"
    ],
    "wof:name":"56 Center Dry Cleaners",
    "wof:placetype":"venue"
},
  "geometry": {"coordinates":[-70.910724,41.892886],"type":"Point"}
}