{
  "type": "Feature",
  "properties": {
    "addr:full":"507 Rantoul St Beverly MA 01915",
    "addr:housenumber":"507",
    "addr:postcode":"01915",
    "addr:street":"Rantoul St",
    "iso:country":"US",
    "sg:address":"507 Rantoul St",
    "sg:city":"Beverly",
    "sg:classifiers":[
        {
            "category":"Restaurant",
            "type":"Food & Drink"
        }
    ],
    "sg:phone":"+1 978 922 4492",
    "sg:postcode":"01915",
    "sg:province":"MA",
    "wof:name":"Joe's Pizza",
    "wof:placetype":"venue"
},
  "geometry": {"coordinates":[-70.879965,42.557579],"type":"Point"}
}