{
  "type": "Feature",
  "properties": {
    "addr:full":"43 Braintree Street Boston MA 02134",
    "addr:housenumber":"43",
    "addr:postcode":"02134",
    "addr:street":"Braintree Street",
    "iso:country":"US",
    "sg:address":"43 Braintree Street",
    "sg:city":"Boston",
    "sg:classifiers":[
        {
            "category":"Personal",
            "type":"Services"
        }
    ],
    "sg:phone":"+1 866 562 3663",
    "sg:postcode":"02134",
    "sg:province":"MA",
    "sg:tags":[
        "mover",
        "local"
    ],
    "sg:website":"www.michaelsmovers.com",
    "wof:name":"Michael's Movers",
    "wof:placetype":"venue"
},
  "geometry": {"coordinates":[-71.134743,42.356232],"type":"Point"}
}