{
  "type": "Feature",
  "properties": {
    "iso:country":"US",
    "sg:address":"227 Oneil Blvd",
    "sg:city":"Attleboro",
    "sg:classifiers":[
        {
            "category":"Manufacturing",
            "subcategory":"Metals",
            "type":"Manufacturing & Wholesale Goods"
        }
    ],
    "sg:phone":"+1 508 222 6810",
    "sg:postcode":"02703",
    "sg:province":"MA",
    "sg:tags":[
        "steel"
    ],
    "wof:name":"HMS Industries Inc",
    "wof:placetype":"venue"
},
  "geometry": {"coordinates":[-71.27546100000001,41.936092],"type":"Point"}
}