{
  "type": "Feature",
  "properties": {
    "addr:full": "227 Oneil Blvd Attleboro MA 02703",
    "addr:housenumber": "227",
    "addr:postcode": "02703",
    "addr:street": "Oneil Blvd",
    "iso:country": "US",
    "sg:address": "227 Oneil Blvd",
    "sg:city": "Attleboro",
    "sg:classifiers": [
      {
        "category": "Manufacturing",
        "subcategory": "Metals",
        "type": "Manufacturing \u0026 Wholesale Goods"
      }
    ],
    "sg:phone": "+1 508 222 6810",
    "sg:postcode": "02703",
    "sg:province": "MA",
    "sg:tags": [
      "steel"
    ],
    "wof:name": "HMS Industries Inc",
    "wof:placetype": "venue"
  },
  "geometry": {"coordinates":[-71.275461,41.936092],"type":"Point"}
}
