{
  "type": "Feature",
  "properties": {
    "iso:country":"US",
    "sg:address":"11 Miller View Rd",
    "sg:city":"Great Barrington",
    "sg:classifiers":[
        {
            "category":"Health Services",
            "subcategory":"Health Practitioner",
            "type":"Services"
        }
    ],
    "sg:phone":"+1 413 528 5055",
    "sg:postcode":"01230",
    "sg:province":"MA",
    "sg:tags":[
        "acupuncture"
    ],
    "wof:name":"Peter A Goldberg",
    "wof:placetype":"venue"
},
  "geometry": {"coordinates":[-73.425544,42.186287],"type":"Point"}
}