{
  "type": "Feature",
  "properties": {
    "addr:full": "11 Woodcrest Rd Westborough MA 01581",
    "addr:housenumber": "11",
    "addr:postcode": "01581",
    "addr:street": "Woodcrest Rd",
    "iso:country": "US",
    "sg:address": "11 Woodcrest Rd",
    "sg:city": "Westborough",
    "sg:classifiers": [
      {
        "category": "Professional",
        "type": "Services"
      }
    ],
    "sg:phone": "+1   ",
    "sg:postcode": "01581",
    "sg:province": "MA",
    "wof:name": "Coautomation Inc",
    "wof:placetype": "venue"
  },
  "geometry": {"coordinates":[-71.623393,42.240758],"type":"Point"}
}
