{
  "type": "Feature",
  "properties": {
    "iso:country":"US",
    "sg:address":"172 Willow St",
    "sg:city":"Acton",
    "sg:classifiers":[
        {
            "category":"Retail",
            "subcategory":"Repair Shop",
            "type":"Services"
        }
    ],
    "sg:phone":"+1 978 266 9766",
    "sg:postcode":"01720",
    "sg:province":"MA",
    "sg:tags":[
        "refinishing",
        "furniture"
    ],
    "wof:name":"Furniture Medic Inc",
    "wof:placetype":"venue"
},
  "geometry": {"coordinates":[-71.487808,42.459708],"type":"Point"}
}