{
  "type": "Feature",
  "properties": {
    "addr:full": "172 Willow St Acton MA 01720",
    "addr:housenumber": "172",
    "addr:postcode": "01720",
    "addr:street": "Willow St",
    "iso:country": "US",
    "sg:address": "172 Willow St",
    "sg:city": "Acton",
    "sg:classifiers": [
      {
        "category": "Retail",
        "subcategory": "Repair Shop",
        "type": "Services"
      }
    ],
    "sg:phone": "+1 978 266 9766",
    "sg:postcode": "01720",
    "sg:province": "MA",
    "sg:tags": [
      "refinishing",
      "furniture"
    ],
    "wof:name": "Furniture Medic Inc",
    "wof:placetype": "venue"
  },
  "geometry": {"coordinates":[-71.487808,42.459708],"type":"Point"}
}
