{
  "type": "Feature",
  "properties": {
    "iso:country":"US",
    "sg:address":"8 Jackson Ct",
    "sg:city":"Lawrence",
    "sg:classifiers":[
        {
            "category":"Professional",
            "subcategory":"Lawyer & Legal Services",
            "type":"Services"
        }
    ],
    "sg:phone":"+1 978 688 3521",
    "sg:postcode":"01840",
    "sg:province":"MA",
    "sg:tags":[
        "attorney",
        "practice",
        "plan"
    ],
    "wof:name":"Armand M Hyatt",
    "wof:placetype":"venue"
},
  "geometry": {"coordinates":[-71.157815,42.709862],"type":"Point"}
}