{
  "type": "Feature",
  "properties": {
    "iso:country":"US",
    "sg:address":"24 Park St",
    "sg:city":"Pittsfield",
    "sg:classifiers":[
        {
            "category":"Building & Trades",
            "subcategory":"Electrical",
            "type":"Services"
        }
    ],
    "sg:phone":"+1 413 442 6708",
    "sg:postcode":"01201",
    "sg:province":"MA",
    "sg:tags":[
        "electric",
        "contractor"
    ],
    "wof:name":"Comalli Electric Inc",
    "wof:placetype":"venue"
},
  "geometry": {"coordinates":[-73.25034599999999,42.458993],"type":"Point"}
}