{
  "type": "Feature",
  "properties": {
    "iso:country":"US",
    "sg:address":"86 Sherman St",
    "sg:city":"Cambridge",
    "sg:classifiers":[
        {
            "category":"Professional",
            "subcategory":"Lawyer & Legal Services",
            "type":"Services"
        }
    ],
    "sg:phone":"+1 617 497 6637",
    "sg:postcode":"02140",
    "sg:province":"MA",
    "sg:tags":[
        "attorney"
    ],
    "wof:name":"Margot Nash",
    "wof:placetype":"venue"
},
  "geometry": {"coordinates":[-71.13210599999999,42.387885],"type":"Point"}
}