{
  "type": "Feature",
  "properties": {
    "addr:full": "86 Sherman St Cambridge MA 02140",
    "addr:housenumber": "86",
    "addr:postcode": "02140",
    "addr:street": "Sherman St",
    "iso:country": "US",
    "sg:address": "86 Sherman St",
    "sg:city": "Cambridge",
    "sg:classifiers": [
      {
        "category": "Professional",
        "subcategory": "Lawyer \u0026 Legal Services",
        "type": "Services"
      }
    ],
    "sg:phone": "+1 617 497 6637",
    "sg:postcode": "02140",
    "sg:province": "MA",
    "sg:tags": [
      "attorney"
    ],
    "wof:name": "Margot Nash",
    "wof:placetype": "venue"
  },
  "geometry": {"coordinates":[-71.132106,42.387885],"type":"Point"}
}
