{
  "type": "Feature",
  "properties": {
    "addr:full":"154 Monument Rd Orleans MA 02653",
    "addr:housenumber":"154",
    "addr:postcode":"02653",
    "addr:street":"Monument Rd",
    "iso:country":"US",
    "sg:address":"154 Monument Rd",
    "sg:city":"Orleans",
    "sg:classifiers":[
        {
            "category":"Professional",
            "subcategory":"Business Services",
            "type":"Services"
        }
    ],
    "sg:phone":"+1   ",
    "sg:postcode":"02653",
    "sg:province":"MA",
    "wof:name":"Jim Spainhour",
    "wof:placetype":"venue"
},
  "geometry": {"coordinates":[-69.98142900000001,41.768052],"type":"Point"}
}