{
  "type": "Feature",
  "properties": {
    "iso:country":"US",
    "sg:address":"2141 Boston Rd",
    "sg:city":"Wilbraham",
    "sg:classifiers":[
        {
            "category":"Personal",
            "subcategory":"Beauty Salon",
            "type":"Services"
        }
    ],
    "sg:phone":"+1 413 543 1328",
    "sg:postcode":"01095",
    "sg:province":"MA",
    "wof:name":"Angelique Cosmetics",
    "wof:placetype":"venue"
},
  "geometry": {"coordinates":[-72.466966,42.150948],"type":"Point"}
}