{
  "type": "Feature",
  "properties": {
    "iso:country":"US",
    "sg:address":"56 Colpitts Rd",
    "sg:city":"Weston",
    "sg:classifiers":[
        {
            "category":"Building & Trades",
            "subcategory":"Construction",
            "type":"Services"
        }
    ],
    "sg:phone":"+1 781 891 0880",
    "sg:postcode":"02493",
    "sg:province":"MA",
    "sg:tags":[
        "home",
        "builder"
    ],
    "wof:name":"Pace Land Developement Inc",
    "wof:placetype":"venue"
},
  "geometry": {"coordinates":[-71.303803,42.36644],"type":"Point"}
}