{
  "type": "Feature",
  "properties": {
    "addr:full":"70 Princeton St North Chelmsford MA 01863",
    "addr:housenumber":"70",
    "addr:postcode":"01863",
    "addr:street":"Princeton St",
    "iso:country":"US",
    "sg:address":"70 Princeton St",
    "sg:city":"North Chelmsford",
    "sg:classifiers":[
        {
            "category":"Wholesale",
            "subcategory":"Computers",
            "type":"Manufacturing & Wholesale Goods"
        }
    ],
    "sg:phone":"+1 978 251 2800",
    "sg:postcode":"01863",
    "sg:province":"MA",
    "sg:tags":[
        "duplication"
    ],
    "sg:website":"www.nesw.com",
    "wof:name":"Northeast Software",
    "wof:placetype":"venue"
},
  "geometry": {"coordinates":[-71.379803,42.636303],"type":"Point"}
}