{
  "type": "Feature",
  "properties": {
    "iso:country":"US",
    "sg:address":"650 Memorial Dr",
    "sg:city":"Chicopee",
    "sg:classifiers":[
        {
            "category":"Autos & Motor Vehicles",
            "subcategory":"Automobile Sales",
            "type":"Retail Goods"
        },
        {
            "category":"Wholesale",
            "subcategory":"Electrical",
            "type":"Manufacturing & Wholesale Goods"
        }
    ],
    "sg:phone":"+1 413 594 4723",
    "sg:postcode":"01020",
    "sg:province":"MA",
    "sg:tags":[
        "car",
        "dealer",
        "electric"
    ],
    "wof:name":"Topor Motors Sales",
    "wof:placetype":"venue"
},
  "geometry": {"coordinates":[-72.57661899999999,42.175762],"type":"Point"}
}