{
  "type": "Feature",
  "properties": {
    "addr:full": "650 Memorial Dr Chicopee MA 01020",
    "addr:housenumber": "650",
    "addr:postcode": "01020",
    "addr:street": "Memorial Dr",
    "iso:country": "US",
    "sg:address": "650 Memorial Dr",
    "sg:city": "Chicopee",
    "sg:classifiers": [
      {
        "category": "Autos \u0026 Motor Vehicles",
        "subcategory": "Automobile Sales",
        "type": "Retail Goods"
      },
      {
        "category": "Wholesale",
        "subcategory": "Electrical",
        "type": "Manufacturing \u0026 Wholesale Goods"
      }
    ],
    "sg:phone": "+1 413 594 4723",
    "sg:postcode": "01020",
    "sg:province": "MA",
    "sg:tags": [
      "car",
      "dealer",
      "electric"
    ],
    "wof:name": "Topor Motors Sales",
    "wof:placetype": "venue"
  },
  "geometry": {"coordinates":[-72.576619,42.175762],"type":"Point"}
}
