{
  "type": "Feature",
  "properties": {
    "addr:full":"14 Michelle's Way Franklin MA 02038",
    "addr:housenumber":"14",
    "addr:postcode":"02038",
    "addr:street":"Michelle'S Way",
    "iso:country":"US",
    "sg:address":"14 Michelle's Way",
    "sg:city":"Franklin",
    "sg:classifiers":[
        {
            "category":"Professional",
            "subcategory":"Computer Services",
            "type":"Services"
        }
    ],
    "sg:phone":"+1   ",
    "sg:postcode":"02038",
    "sg:province":"MA",
    "sg:tags":[
        "programing",
        "custom"
    ],
    "wof:name":"K I F Consulting",
    "wof:placetype":"venue"
},
  "geometry": {"coordinates":[-71.39179,42.13486],"type":"Point"}
}