{
  "type": "Feature",
  "properties": {
    "addr:full":"1667 Central St Stoughton MA 02072",
    "addr:housenumber":"1667",
    "addr:postcode":"02072",
    "addr:street":"Central St",
    "iso:country":"US",
    "sg:address":"1667 Central St",
    "sg:city":"Stoughton",
    "sg:classifiers":[
        {
            "category":"Banks & Credit Unions",
            "subcategory":"Investment Brokerage",
            "type":"Services"
        }
    ],
    "sg:phone":"+1 781 341 6040",
    "sg:postcode":"02072",
    "sg:province":"MA",
    "sg:tags":[
        "advisory",
        "financial"
    ],
    "wof:name":"CGS Financial Technologies",
    "wof:placetype":"venue"
},
  "geometry": {"coordinates":[-71.12631,42.130916],"type":"Point"}
}