{
  "type": "Feature",
  "properties": {
    "iso:country":"US",
    "sg:address":"64 Enterprise Rd Ste 6",
    "sg:city":"Hyannis",
    "sg:classifiers":[
        {
            "category":"Shopping",
            "subcategory":"Mobile Phones",
            "type":"Retail Goods"
        }
    ],
    "sg:phone":"+1 508 771 2156",
    "sg:postcode":"02601",
    "sg:province":"MA",
    "sg:tags":[
        "equipment",
        "telephone",
        "cellular",
        "supply"
    ],
    "wof:name":"Southeastern Communications",
    "wof:placetype":"venue"
},
  "geometry": {"coordinates":[-70.302145,41.667495],"type":"Point"}
}