{
  "type": "Feature",
  "properties": {
    "addr:full": "727 Bennington St East Boston MA 02128",
    "addr:housenumber": "727",
    "addr:postcode": "02128",
    "addr:street": "Bennington St",
    "iso:country": "US",
    "sg:address": "727 Bennington St",
    "sg:city": "East Boston",
    "sg:classifiers": [
      {
        "category": "Building \u0026 Trades",
        "subcategory": "Construction",
        "type": "Services"
      }
    ],
    "sg:phone": "+1 617 568 9886",
    "sg:postcode": "02128",
    "sg:province": "MA",
    "sg:tags": [
      "resurfacing",
      "refinishing",
      "floor"
    ],
    "wof:name": "Sonny Professional Floor",
    "wof:placetype": "venue"
  },
  "geometry": {"coordinates":[-71.010442,42.385327],"type":"Point"}
}
