{
  "type": "Feature",
  "properties": {
    "addr:full":"66 Braley Rd East Freetown MA 02717",
    "addr:housenumber":"66",
    "addr:postcode":"02717",
    "addr:street":"Braley Rd",
    "iso:country":"US",
    "sg:address":"66 Braley Rd",
    "sg:city":"East Freetown",
    "sg:classifiers":[
        {
            "category":"Retail",
            "subcategory":"Auto Repair",
            "type":"Services"
        }
    ],
    "sg:phone":"+1 508 763 5957",
    "sg:postcode":"02717",
    "sg:province":"MA",
    "sg:tags":[
        "truck"
    ],
    "wof:name":"Gary's Repair",
    "wof:placetype":"venue"
},
  "geometry": {"coordinates":[-70.96801000000001,41.759596],"type":"Point"}
}