{
  "type": "Feature",
  "properties": {
    "addr:full": "15 Ward St Hingham MA 02043",
    "addr:housenumber": "15",
    "addr:postcode": "02043",
    "addr:street": "Ward St",
    "iso:country": "US",
    "sg:address": "15 Ward St",
    "sg:city": "Hingham",
    "sg:classifiers": [
      {
        "category": "Retail",
        "subcategory": "Auto Repair",
        "type": "Services"
      }
    ],
    "sg:phone": "+1 781 740 1749",
    "sg:postcode": "02043",
    "sg:province": "MA",
    "sg:tags": [
      "automobile",
      "lubrication"
    ],
    "wof:name": "Acculube Truck Oil \u0026 Lub Svc",
    "wof:placetype": "venue"
  },
  "geometry": {"coordinates":[-70.91179,42.211335],"type":"Point"}
}
