{
  "type": "Feature",
  "properties": {
    "addr:full": "1130 Grand Army Hwy Somerset MA 02726",
    "addr:housenumber": "1130",
    "addr:postcode": "02726",
    "addr:street": "Grand Army Hwy",
    "iso:country": "US",
    "sg:address": "1130 Grand Army Hwy",
    "sg:city": "Somerset",
    "sg:classifiers": [
      {
        "category": "Retail",
        "subcategory": "Auto Repair",
        "type": "Services"
      }
    ],
    "sg:phone": "+1 508 675 2592",
    "sg:postcode": "02726",
    "sg:province": "MA",
    "sg:tags": [
      "repairing",
      "automobile"
    ],
    "wof:name": "Viveiros Auto Repair Inc",
    "wof:placetype": "venue"
  },
  "geometry": {"coordinates":[-71.173936,41.73295],"type":"Point"}
}
