{
  "type": "Feature",
  "properties": {
    "addr:full":"651 Rogers St Lowell MA 01852",
    "addr:housenumber":"651",
    "addr:postcode":"01852",
    "addr:street":"Rogers St",
    "iso:country":"US",
    "sg:address":"651 Rogers St",
    "sg:city":"Lowell",
    "sg:classifiers":[
        {
            "category":"Bakery",
            "type":"Food & Drink"
        },
        {
            "category":"Coffee & Tea",
            "type":"Food & Drink"
        },
        {
            "category":"Bagels",
            "type":"Food & Drink"
        },
        {
            "category":"Donuts",
            "type":"Food & Drink"
        }
    ],
    "sg:menulink":"http://www.allmenus.com/ma/lowell/143044-dunkin-donuts/menu/",
    "sg:phone":"+1 978 452 8612",
    "sg:postcode":"01852",
    "sg:province":"MA",
    "sg:tags":[
        "american",
        "diner",
        "pastry"
    ],
    "wof:name":"Dunkin' Donuts",
    "wof:placetype":"venue"
},
  "geometry": {"coordinates":[-71.281587,42.630911],"type":"Point"}
}