{
  "type": "Feature",
  "properties": {
    "addr:full":"25 Granite St Milford MA 01757",
    "addr:housenumber":"25",
    "addr:postcode":"01757",
    "addr:street":"Granite St",
    "iso:country":"US",
    "sg:address":"25 Granite St",
    "sg:city":"Milford",
    "sg:classifiers":[
        {
            "category":"Shopping",
            "subcategory":"Discount & Variety Stores",
            "type":"Retail Goods"
        }
    ],
    "sg:phone":"+1 508 478 8270",
    "sg:postcode":"01757",
    "sg:province":"MA",
    "sg:tags":[
        "merchandise",
        "general"
    ],
    "wof:name":"Tempron Products Corp",
    "wof:placetype":"venue"
},
  "geometry": {"coordinates":[-71.516471,42.145266],"type":"Point"}
}