{
  "type": "Feature",
  "properties": {
    "iso:country":"US",
    "sg:address":"13 Groton-Harvard Rd",
    "sg:city":"Ayer",
    "sg:classifiers":[
        {
            "category":"Manufacturing",
            "subcategory":"Metals",
            "type":"Manufacturing & Wholesale Goods"
        }
    ],
    "sg:phone":"+1 978 772 3481",
    "sg:postcode":"01432",
    "sg:province":"MA",
    "sg:tags":[
        "cutlery"
    ],
    "sg:website":"www.rmurphyknives.com",
    "wof:name":"R Murphy Co",
    "wof:placetype":"venue"
},
  "geometry": {"coordinates":[-71.57804400000001,42.556322],"type":"Point"}
}