{
  "type": "Feature",
  "properties": {
    "addr:full": "277 Lowell St New Bedford MA 02745",
    "addr:housenumber": "277",
    "addr:postcode": "02745",
    "addr:street": "Lowell St",
    "iso:country": "US",
    "sg:address": "277 Lowell St",
    "sg:city": "New Bedford",
    "sg:classifiers": [
      {
        "category": "Personal",
        "subcategory": "Beauty Salon",
        "type": "Services"
      }
    ],
    "sg:phone": "+1 508 995 2551",
    "sg:postcode": "02745",
    "sg:province": "MA",
    "sg:tags": [
      "shop"
    ],
    "wof:name": "A-Plus Nails",
    "wof:placetype": "venue"
  },
  "geometry": {"coordinates":[-70.935978,41.686887],"type":"Point"}
}
