{
  "type": "Feature",
  "properties": {
    "iso:country":"US",
    "sg:address":"20 Eastbrook Rd",
    "sg:city":"Dedham",
    "sg:classifiers":[
        {
            "category":"Health Services",
            "subcategory":"Doctor",
            "type":"Services"
        }
    ],
    "sg:phone":"+1 781 326 8080",
    "sg:postcode":"02026",
    "sg:province":"MA",
    "sg:tags":[
        "dentist"
    ],
    "wof:name":"Oral Surgery Assoc",
    "wof:placetype":"venue"
},
  "geometry": {"coordinates":[-71.16510100000001,42.254954],"type":"Point"}
}