{
  "type": "Feature",
  "properties": {
    "iso:country":"US",
    "sg:address":"54 Front St",
    "sg:city":"Ashland",
    "sg:classifiers":[
        {
            "category":"Manufacturing",
            "subcategory":"Toys & Sporting Goods",
            "type":"Manufacturing & Wholesale Goods"
        }
    ],
    "sg:phone":"+1   ",
    "sg:postcode":"01721",
    "sg:province":"MA",
    "sg:tags":[
        "mfg"
    ],
    "wof:name":"Bear Hugs",
    "wof:placetype":"venue"
},
  "geometry": {"coordinates":[-71.457273,42.260113],"type":"Point"}
}