{
  "type": "Feature",
  "properties": {
    "addr:full": "75 Francis St Boston MA 02143",
    "addr:housenumber": "75",
    "addr:postcode": "02143",
    "addr:street": "Francis St",
    "iso:country": "US",
    "sg:address": "75 Francis St",
    "sg:city": "Boston",
    "sg:classifiers": [
      {
        "category": "Health Services",
        "subcategory": "Doctor",
        "type": "Services"
      }
    ],
    "sg:phone": "+1   ",
    "sg:postcode": "02143",
    "sg:province": "MA",
    "sg:tags": [
      "clinic",
      "medical"
    ],
    "wof:name": "David Soybel MD",
    "wof:placetype": "venue"
  },
  "geometry": {"coordinates":[-71.11098,42.390645],"type":"Point"}
}
