{
  "type": "Feature",
  "properties": {
    "addr:full":"243 Church St Pembroke MA 02359",
    "addr:housenumber":"243",
    "addr:postcode":"02359",
    "addr:street":"Church St",
    "iso:country":"US",
    "sg:address":"243 Church St",
    "sg:city":"Pembroke",
    "sg:classifiers":[
        {
            "category":"Professional",
            "subcategory":"Lawyer & Legal Services",
            "type":"Services"
        }
    ],
    "sg:phone":"+1 781 829 2003",
    "sg:postcode":"02359",
    "sg:province":"MA",
    "sg:tags":[
        "attorney"
    ],
    "wof:name":"Timothy J Vanderveen Law Ofc",
    "wof:placetype":"venue"
},
  "geometry": {"coordinates":[-70.760791,42.10728],"type":"Point"}
}