{
  "type": "Feature",
  "properties": {
    "iso:country":"US",
    "sg:address":"1525 Highland St",
    "sg:city":"Holliston",
    "sg:classifiers":[
        {
            "category":"Arts & Performance",
            "subcategory":"Theater",
            "type":"Entertainment"
        }
    ],
    "sg:phone":"+1 508 473 1816",
    "sg:postcode":"01746",
    "sg:province":"MA",
    "sg:tags":[
        "live",
        "music"
    ],
    "wof:name":"Ahronian Productions",
    "wof:placetype":"venue"
},
  "geometry": {"coordinates":[-71.43233600000001,42.184851],"type":"Point"}
}