{
  "type": "Feature",
  "properties": {
    "iso:country":"US",
    "sg:address":"205 Newbury St",
    "sg:city":"Boston",
    "sg:classifiers":[
        {
            "category":"Real Estate",
            "subcategory":"Real Estate Agent",
            "type":"Services"
        }
    ],
    "sg:phone":"+1 617 375 6780",
    "sg:postcode":"02116",
    "sg:province":"MA",
    "wof:name":"JFL Real Estate",
    "wof:placetype":"venue"
},
  "geometry": {"coordinates":[-71.081711,42.349918],"type":"Point"}
}