{
  "type": "Feature",
  "properties": {
    "iso:country":"US",
    "sg:address":"1074 Central St",
    "sg:city":"Leominster",
    "sg:classifiers":[
        {
            "category":"Autos & Motor Vehicles",
            "subcategory":"Automobile Sales",
            "type":"Retail Goods"
        }
    ],
    "sg:phone":"+1 978 534 4896",
    "sg:postcode":"01453",
    "sg:province":"MA",
    "sg:tags":[
        "car",
        "dealer"
    ],
    "wof:name":"Excellence Auto Sales Inc",
    "wof:placetype":"venue"
},
  "geometry": {"coordinates":[-71.74503199999999,42.496308],"type":"Point"}
}