{
  "type": "Feature",
  "properties": {
    "addr:full": "1074 Central St Leominster MA 01453",
    "addr:housenumber": "1074",
    "addr:postcode": "01453",
    "addr:street": "Central St",
    "iso:country": "US",
    "sg:address": "1074 Central St",
    "sg:city": "Leominster",
    "sg:classifiers": [
      {
        "category": "Autos \u0026 Motor Vehicles",
        "subcategory": "Automobile Sales",
        "type": "Retail Goods"
      }
    ],
    "sg:phone": "+1 978 534 4896",
    "sg:postcode": "01453",
    "sg:province": "MA",
    "sg:tags": [
      "car",
      "dealer"
    ],
    "wof:name": "Excellence Auto Sales Inc",
    "wof:placetype": "venue"
  },
  "geometry": {"coordinates":[-71.745032,42.496308],"type":"Point"}
}
