{
  "type": "Feature",
  "properties": {
    "addr:full": "345 Massasoit Rd Eastham MA 02642",
    "addr:housenumber": "345",
    "addr:postcode": "02642",
    "addr:street": "Massasoit Rd",
    "iso:country": "US",
    "ovtr:label": "Cape Associates, Inc., 345 Massasoit Rd Eastham MA US",
    "ovtr:similarity": 2.6224288940429688,
    "sg:address": "345 Massasoit Rd",
    "sg:city": "Eastham",
    "sg:classifiers": [
      {
        "category": "Building \u0026 Trades",
        "subcategory": "Construction",
        "type": "Services"
      }
    ],
    "sg:phone": "+1 508 255 1770",
    "sg:postcode": "02642",
    "sg:province": "MA",
    "sg:tags": [
      "painting",
      "contractor"
    ],
    "sg:website": "http://www.capeassociates.com",
    "wof:name": "Cape Associates Inc",
    "wof:placetype": "venue"
  },
  "geometry": {"coordinates":[-69.989369,41.853549],"type":"Point"}
}
