{
  "type": "Feature",
  "properties": {
    "iso:country":"US",
    "sg:address":"948 BROADWAY RT 1",
    "sg:city":"Saugus",
    "sg:classifiers":[
        {
            "category":"Restaurant",
            "type":"Food & Drink"
        }
    ],
    "sg:phone":"+1 781 233 0077",
    "sg:postcode":"01906",
    "sg:province":"MA",
    "sg:tags":[
        "asian",
        "pan"
    ],
    "sg:website":"http://www.kowloonrestaurant.com",
    "wof:name":"Kowloon",
    "wof:placetype":"venue"
},
  "geometry": {"coordinates":[-71.022419,42.457241],"type":"Point"}
}