{
  "type": "Feature",
  "properties": {
    "iso:country":"US",
    "sg:address":"36 Charles St",
    "sg:city":"Newburyport",
    "sg:classifiers":[
        {
            "category":"Arena",
            "subcategory":"Sports Club",
            "type":"Entertainment"
        }
    ],
    "sg:phone":"+1 978 462 7656",
    "sg:postcode":"01950",
    "sg:province":"MA",
    "sg:tags":[
        "soccer"
    ],
    "wof:name":"Newburyport Youth Soccer",
    "wof:placetype":"venue"
},
  "geometry": {"coordinates":[-70.86278900000001,42.808875],"type":"Point"}
}