{
  "type": "Feature",
  "properties": {
    "iso:country":"US",
    "sg:address":"45 Pearson Blvd",
    "sg:city":"Gardner",
    "sg:classifiers":[
        {
            "category":"Personal",
            "subcategory":"Beauty Salon",
            "type":"Services"
        }
    ],
    "sg:phone":"+1 978 630 1565",
    "sg:postcode":"01440",
    "sg:province":"MA",
    "sg:website":"www.robroy.com",
    "wof:name":"Rob Roy Hair Salon",
    "wof:placetype":"venue"
},
  "geometry": {"coordinates":[-71.978685,42.565547],"type":"Point"}
}