{
  "type": "Feature",
  "properties": {
    "addr:full": "45 Pearson Blvd Gardner MA 01440",
    "addr:housenumber": "45",
    "addr:postcode": "01440",
    "addr:street": "Pearson Blvd",
    "iso:country": "US",
    "ovtr:label": "Rob Roy Hair Salon, 45 Pearson Blvd Gardner MA US",
    "ovtr:similarity": 2.5297110080718994,
    "sg:address": "45 Pearson Blvd",
    "sg:city": "Gardner",
    "sg:classifiers": [
      {
        "category": "Personal",
        "subcategory": "Beauty Salon",
        "type": "Services"
      }
    ],
    "sg:phone": "+1 978 630 1565",
    "sg:postcode": "01440",
    "sg:province": "MA",
    "sg:website": "www.robroy.com",
    "wof:name": "Rob Roy Hair Salon",
    "wof:placetype": "venue"
  },
  "geometry": {"coordinates":[-71.978685,42.565547],"type":"Point"}
}
