{
  "type": "Feature",
  "properties": {
    "iso:country":"US",
    "sg:address":"55 Housatonic St",
    "sg:city":"Lee",
    "sg:classifiers":[
        {
            "category":"Autos & Motor Vehicles",
            "subcategory":"Fuel & Gas Station",
            "type":"Retail Goods"
        }
    ],
    "sg:phone":"+1 413 243 6443",
    "sg:postcode":"01238",
    "sg:province":"MA",
    "sg:tags":[
        "oil"
    ],
    "wof:name":"Lee Citgo Quick Mart LLC",
    "wof:placetype":"venue"
},
  "geometry": {"coordinates":[-73.24510100000001,42.303414],"type":"Point"}
}