{
  "type": "Feature",
  "properties": {
    "addr:full": "55 Housatonic St Lee MA 01238",
    "addr:housenumber": "55",
    "addr:postcode": "01238",
    "addr:street": "Housatonic St",
    "iso:country": "US",
    "sg:address": "55 Housatonic St",
    "sg:city": "Lee",
    "sg:classifiers": [
      {
        "category": "Autos \u0026 Motor Vehicles",
        "subcategory": "Fuel \u0026 Gas Station",
        "type": "Retail Goods"
      }
    ],
    "sg:phone": "+1 413 243 6443",
    "sg:postcode": "01238",
    "sg:province": "MA",
    "sg:tags": [
      "oil"
    ],
    "wof:name": "Lee Citgo Quick Mart LLC",
    "wof:placetype": "venue"
  },
  "geometry": {"coordinates":[-73.245101,42.303414],"type":"Point"}
}
