{
  "type": "Feature",
  "properties": {
    "iso:country":"US",
    "sg:address":"197 High St Ste 1B",
    "sg:city":"Ipswich",
    "sg:classifiers":[
        {
            "category":"Professional",
            "subcategory":"Computer Services",
            "type":"Services"
        }
    ],
    "sg:phone":"+1 978 356 0635",
    "sg:postcode":"01938",
    "sg:province":"MA",
    "sg:tags":[
        "repair"
    ],
    "sg:website":"www.scottnetworks.net",
    "wof:name":"Scott Networks",
    "wof:placetype":"venue"
},
  "geometry": {"coordinates":[-70.860664,42.694397],"type":"Point"}
}