{
  "type": "Feature",
  "properties": {
    "iso:country":"US",
    "sg:address":"6 Scotts Way",
    "sg:city":"Essex",
    "sg:classifiers":[
        {
            "category":"Building & Trades",
            "subcategory":"Landscaping Services",
            "type":"Services"
        }
    ],
    "sg:phone":"+1 978 768 6999",
    "sg:postcode":"01929",
    "sg:province":"MA",
    "sg:tags":[
        "tree"
    ],
    "wof:name":"Mayer Tree Svc",
    "wof:placetype":"venue"
},
  "geometry": {"coordinates":[-70.814241,42.623002],"type":"Point"}
}