{
  "type": "Feature",
  "properties": {
    "addr:full":"18 Broad St Nantucket MA 02554",
    "addr:housenumber":"18",
    "addr:postcode":"02554",
    "addr:street":"Broad St",
    "iso:country":"US",
    "sg:address":"18 Broad St",
    "sg:city":"Nantucket",
    "sg:classifiers":[
        {
            "category":"Government",
            "subcategory":"Office",
            "type":"Public Place"
        }
    ],
    "sg:phone":"+1 508 228 2559",
    "sg:postcode":"02554",
    "sg:province":"MA",
    "sg:tags":[
        "village"
    ],
    "wof:name":"Nantucket Passports",
    "wof:placetype":"venue"
},
  "geometry": {"coordinates":[-70.100078,41.284988],"type":"Point"}
}