{
  "type": "Feature",
  "properties": {
    "addr:full":"1678 Bridge St Dracut MA 01826",
    "addr:housenumber":"1678",
    "addr:postcode":"01826",
    "addr:street":"Bridge St",
    "iso:country":"US",
    "sg:address":"1678 Bridge St",
    "sg:city":"Dracut",
    "sg:classifiers":[
        {
            "category":"Personal",
            "subcategory":"Beauty Salon",
            "type":"Services"
        }
    ],
    "sg:phone":"+1 978 452 9565",
    "sg:postcode":"01826",
    "sg:province":"MA",
    "wof:name":"C'Est Chic Unisex Hairstyling",
    "wof:placetype":"venue"
},
  "geometry": {"coordinates":[-71.308446,42.679973],"type":"Point"}
}