{
  "type": "Feature",
  "properties": {
    "addr:full":"95 Eldredge Pkwy Orleans MA 02653",
    "addr:housenumber":"95",
    "addr:postcode":"02653",
    "addr:street":"Eldredge Pkwy",
    "iso:country":"US",
    "sg:address":"95 Eldredge Pkwy",
    "sg:city":"Orleans",
    "sg:classifiers":[
        {
            "category":"Real Estate",
            "subcategory":"Real Estate Agent",
            "type":"Services"
        }
    ],
    "sg:phone":"+1 508 255 1611",
    "sg:postcode":"02653",
    "sg:province":"MA",
    "sg:website":"www.wilkinsonre.com",
    "wof:name":"Wilkinson & Assocs",
    "wof:placetype":"venue"
},
  "geometry": {"coordinates":[-69.98875099999999,41.780842],"type":"Point"}
}