{
  "type": "Feature",
  "properties": {
    "addr:full": "31 Fulton St Woburn MA 01801",
    "addr:housenumber": "31",
    "addr:postcode": "01801",
    "addr:street": "Fulton St",
    "iso:country": "US",
    "sg:address": "31 Fulton St",
    "sg:city": "Woburn",
    "sg:classifiers": [
      {
        "category": "Professional",
        "subcategory": "Business Services",
        "type": "Services"
      }
    ],
    "sg:phone": "+1   ",
    "sg:postcode": "01801",
    "sg:province": "MA",
    "wof:name": "Phils Interiors",
    "wof:placetype": "venue"
  },
  "geometry": {"coordinates":[-71.139217,42.473867],"type":"Point"}
}
