{
  "type": "Feature",
  "properties": {
    "iso:country":"US",
    "sg:address":"268 Essex St",
    "sg:city":"Lynn",
    "sg:classifiers":[
        {
            "category":"Food & Beverages",
            "subcategory":"Groceries & Convenience Stores",
            "type":"Retail Goods"
        }
    ],
    "sg:phone":"+1 781 477 9996",
    "sg:postcode":"01902",
    "sg:province":"MA",
    "wof:name":"Soreno Market",
    "wof:placetype":"venue"
},
  "geometry": {"coordinates":[-70.937569,42.47045],"type":"Point"}
}