{
  "type": "Feature",
  "properties": {
    "iso:country":"US",
    "sg:address":"620 Main St",
    "sg:city":"Williamstown",
    "sg:classifiers":[
        {
            "category":"Travel",
            "subcategory":"Travel Agent",
            "type":"Entertainment"
        }
    ],
    "sg:phone":"+1 413 499 3770",
    "sg:postcode":"01267",
    "sg:province":"MA",
    "sg:tags":[
        "agency",
        "bureau"
    ],
    "wof:name":"Pittsfield Travel Store Inc",
    "wof:placetype":"venue"
},
  "geometry": {"coordinates":[-73.194275,42.709291],"type":"Point"}
}