{
  "type": "Feature",
  "properties": {
    "addr:full": "212 Upper Main St Edgartown MA 02539",
    "addr:housenumber": "212",
    "addr:postcode": "02539",
    "addr:street": "Upper Main St",
    "iso:country": "US",
    "ovtr:label": "Edgartown Bicycles, 212 Upper Main St Edgartown MA US",
    "ovtr:similarity": 2.5705249309539795,
    "sg:address": "212 Upper Main St",
    "sg:city": "Edgartown",
    "sg:classifiers": [
      {
        "category": "Shopping",
        "subcategory": "Bicycles \u0026 Sporting Goods",
        "type": "Retail Goods"
      }
    ],
    "sg:phone": "+1 508 627 9008",
    "sg:postcode": "02539",
    "sg:province": "MA",
    "wof:name": "Edgartown Bicycles",
    "wof:placetype": "venue"
  },
  "geometry": {"coordinates":[-70.526594,41.394211],"type":"Point"}
}
