{
  "type": "Feature",
  "properties": {
    "addr:full":"2249 Commonwealth Ave Auburndale MA 02466",
    "addr:housenumber":"2249",
    "addr:postcode":"02466",
    "addr:street":"Commonwealth Ave",
    "iso:country":"US",
    "sg:address":"2249 Commonwealth Ave",
    "sg:city":"Auburndale",
    "sg:classifiers":[
        {
            "category":"Professional",
            "subcategory":"Research",
            "type":"Services"
        }
    ],
    "sg:phone":"+1   ",
    "sg:postcode":"02466",
    "sg:province":"MA",
    "sg:tags":[
        "food",
        "development"
    ],
    "wof:name":"Fare & Fancy Inc",
    "wof:placetype":"venue"
},
  "geometry": {"coordinates":[-71.25498399999999,42.346768],"type":"Point"}
}