{
  "type": "Feature",
  "properties": {
    "addr:full":"44 Mechanic St Newton MA 02464",
    "addr:housenumber":"44",
    "addr:postcode":"02464",
    "addr:street":"Mechanic St",
    "iso:country":"US",
    "sg:address":"44 Mechanic St",
    "sg:city":"Newton",
    "sg:classifiers":[
        {
            "category":"Professional",
            "subcategory":"Management & Consulting",
            "type":"Services"
        }
    ],
    "sg:phone":"+1 617 964 3744",
    "sg:postcode":"02464",
    "sg:province":"MA",
    "sg:tags":[
        "personnel",
        "consultant"
    ],
    "wof:name":"JME Co",
    "wof:placetype":"venue"
},
  "geometry": {"coordinates":[-71.21790799999999,42.311246],"type":"Point"}
}