{
  "type": "Feature",
  "properties": {
    "addr:full": "1030 Main St Wakefield MA 01880",
    "addr:housenumber": "1030",
    "addr:postcode": "01880",
    "addr:street": "Main St",
    "iso:country": "US",
    "sg:address": "1030 Main St",
    "sg:city": "Wakefield",
    "sg:classifiers": [
      {
        "category": "Social Services",
        "subcategory": "Child Care",
        "type": "Services"
      }
    ],
    "sg:phone": "+1 781 213 9137",
    "sg:postcode": "01880",
    "sg:province": "MA",
    "wof:name": "Wakefield Extended Day",
    "wof:placetype": "venue"
  },
  "geometry": {"coordinates":[-71.066144,42.48232],"type":"Point"}
}
