{
  "type": "Feature",
  "properties": {
    "iso:country":"US",
    "sg:address":"108 Tower Rd",
    "sg:city":"Lincoln",
    "sg:classifiers":[
        {
            "category":"Professional",
            "subcategory":"Management & Consulting",
            "type":"Services"
        }
    ],
    "sg:phone":"+1   ",
    "sg:postcode":"01773",
    "sg:province":"MA",
    "sg:tags":[
        "consultant",
        "aerospace"
    ],
    "wof:name":"Jack L Kerrebrock",
    "wof:placetype":"venue"
},
  "geometry": {"coordinates":[-71.31087100000001,42.410046],"type":"Point"}
}