{
  "type": "Feature",
  "properties": {
    "addr:full": "108 Tower Rd Lincoln MA 01773",
    "addr:housenumber": "108",
    "addr:postcode": "01773",
    "addr:street": "Tower Rd",
    "iso:country": "US",
    "sg:address": "108 Tower Rd",
    "sg:city": "Lincoln",
    "sg:classifiers": [
      {
        "category": "Professional",
        "subcategory": "Management \u0026 Consulting",
        "type": "Services"
      }
    ],
    "sg:phone": "+1   ",
    "sg:postcode": "01773",
    "sg:province": "MA",
    "sg:tags": [
      "consultant",
      "aerospace"
    ],
    "wof:name": "Jack L Kerrebrock",
    "wof:placetype": "venue"
  },
  "geometry": {"coordinates":[-71.310871,42.410046],"type":"Point"}
}
