{
  "type": "Feature",
  "properties": {
    "addr:full":"179 River St Southbridge MA 01550",
    "addr:housenumber":"179",
    "addr:postcode":"01550",
    "addr:street":"River St",
    "iso:country":"US",
    "sg:address":"179 River St",
    "sg:city":"Southbridge",
    "sg:classifiers":[
        {
            "category":"Retail",
            "subcategory":"Auto Repair",
            "type":"Services"
        }
    ],
    "sg:phone":"+1 508 764 1466",
    "sg:postcode":"01550",
    "sg:province":"MA",
    "wof:name":"Auto Repair & Discount Tires of Southbridge",
    "wof:placetype":"venue"
},
  "geometry": {"coordinates":[-72.04409800000001,42.0839],"type":"Point"}
}