{
  "type": "Feature",
  "properties": {
    "addr:full": "206 Washington St Boston MA 02108",
    "addr:housenumber": "206",
    "addr:postcode": "02108",
    "addr:street": "Washington St",
    "iso:country": "US",
    "ovtr:label": "Old State House, 206 Washington St Boston MA US",
    "ovtr:similarity": 3.3168959617614746,
    "sg:address": "206 Washington St",
    "sg:city": "Boston",
    "sg:classifiers": [
      {
        "category": "Landmark",
        "subcategory": "Historic",
        "type": "Public Place"
      },
      {
        "category": "Museum",
        "type": "Entertainment"
      }
    ],
    "sg:phone": "+1 617 720 1713",
    "sg:postcode": "02108",
    "sg:province": "MA",
    "sg:tags": [
      "building",
      "historical"
    ],
    "sg:website": "www.bostonhistory.org/",
    "wof:name": "Old State House",
    "wof:placetype": "venue"
  },
  "geometry": {"coordinates":[-71.057814,42.358055],"type":"Point"}
}
