{
  "type": "Feature",
  "properties": {
    "addr:full": "200 Providence Hwy Dedham MA 02026",
    "addr:housenumber": "200",
    "addr:postcode": "02026",
    "addr:street": "Providence Hwy",
    "iso:country": "US",
    "sg:address": "200 Providence Hwy",
    "sg:city": "Dedham",
    "sg:classifiers": [
      {
        "category": "Health Services",
        "subcategory": "Chiropractor",
        "type": "Services"
      }
    ],
    "sg:phone": "+1 781 326 0904",
    "sg:postcode": "02026",
    "sg:province": "MA",
    "wof:name": "Patient First Chiropractic",
    "wof:placetype": "venue"
  },
  "geometry": {"coordinates":[-71.217193,42.143406],"type":"Point"}
}
