{
  "type": "Feature",
  "properties": {
    "addr:full":"78 Main St Hudson MA 01749",
    "addr:housenumber":"78",
    "addr:postcode":"01749",
    "addr:street":"Main St",
    "iso:country":"US",
    "sg:address":"78 Main St",
    "sg:city":"Hudson",
    "sg:classifiers":[
        {
            "category":"Government",
            "subcategory":"Office",
            "type":"Public Place"
        }
    ],
    "sg:phone":"+1 978 568 9620",
    "sg:postcode":"01749",
    "sg:province":"MA",
    "sg:tags":[
        "city",
        "taxation"
    ],
    "wof:name":"Hudson Assessor",
    "wof:placetype":"venue"
},
  "geometry": {"coordinates":[-71.568085,42.391162],"type":"Point"}
}