{
  "type": "Feature",
  "properties": {
    "addr:full": "25 Sylvan Rd Beverly MA 01915",
    "addr:housenumber": "25",
    "addr:postcode": "01915",
    "addr:street": "Sylvan Rd",
    "iso:country": "US",
    "sg:address": "25 Sylvan Rd",
    "sg:city": "Beverly",
    "sg:classifiers": [
      {
        "category": "Wholesale",
        "subcategory": "Non-durable Goods",
        "type": "Manufacturing \u0026 Wholesale Goods"
      }
    ],
    "sg:phone": "+1 978 922 1166",
    "sg:postcode": "01915",
    "sg:province": "MA",
    "sg:tags": [
      "advertising"
    ],
    "sg:website": "www.promografix.com",
    "wof:name": "Promografix",
    "wof:placetype": "venue"
  },
  "geometry": {"coordinates":[-70.863892,42.556367],"type":"Point"}
}
