{
  "type": "Feature",
  "properties": {
    "iso:country":"US",
    "sg:address":"25 Sylvan Rd",
    "sg:city":"Beverly",
    "sg:classifiers":[
        {
            "category":"Wholesale",
            "subcategory":"Non-durable Goods",
            "type":"Manufacturing & Wholesale Goods"
        }
    ],
    "sg:phone":"+1 978 922 1166",
    "sg:postcode":"01915",
    "sg:province":"MA",
    "sg:tags":[
        "advertising"
    ],
    "sg:website":"www.promografix.com",
    "wof:name":"Promografix",
    "wof:placetype":"venue"
},
  "geometry": {"coordinates":[-70.86389200000001,42.556367],"type":"Point"}
}