{
  "type": "Feature",
  "properties": {
    "addr:full": "15 Torrey St Brockton MA 02301",
    "addr:housenumber": "15",
    "addr:postcode": "02301",
    "addr:street": "Torrey St",
    "iso:country": "US",
    "sg:address": "15 Torrey St",
    "sg:city": "Brockton",
    "sg:classifiers": [
      {
        "category": "Real Estate",
        "subcategory": "Real Estate Agent",
        "type": "Services"
      }
    ],
    "sg:phone": "+1 508 580 8380",
    "sg:postcode": "02301",
    "sg:province": "MA",
    "wof:name": "M L Sullivan Real Estate",
    "wof:placetype": "venue"
  },
  "geometry": {"coordinates":[-71.041919,42.07471],"type":"Point"}
}
