{
  "type": "Feature",
  "properties": {
    "addr:full":"19 Fairway Dr Plymouth MA 02360",
    "addr:housenumber":"19",
    "addr:postcode":"02360",
    "addr:street":"Fairway Dr",
    "iso:country":"US",
    "sg:address":"19 Fairway Dr",
    "sg:city":"Plymouth",
    "sg:classifiers":[
        {
            "category":"Wholesale",
            "subcategory":"Durable Goods & Equipment",
            "type":"Manufacturing & Wholesale Goods"
        }
    ],
    "sg:phone":"+1 508 833 1515",
    "sg:postcode":"02360",
    "sg:province":"MA",
    "sg:tags":[
        "representative",
        "manufacturer"
    ],
    "wof:name":"Morton Industrial Sales",
    "wof:placetype":"venue"
},
  "geometry": {"coordinates":[-70.546048,41.816332],"type":"Point"}
}