{
  "type": "Feature",
  "properties": {
    "iso:country":"US",
    "sg:address":"148 Russell St",
    "sg:city":"Littleton",
    "sg:classifiers":[
        {
            "category":"Real Estate",
            "subcategory":"Real Estate Operator",
            "type":"Services"
        }
    ],
    "sg:phone":"+1   ",
    "sg:postcode":"01460",
    "sg:province":"MA",
    "sg:tags":[
        "building",
        "nonresidential"
    ],
    "wof:name":"KV Development Corp",
    "wof:placetype":"venue"
},
  "geometry": {"coordinates":[-71.48378,42.549596],"type":"Point"}
}