{
  "type": "Feature",
  "properties": {
    "addr:full":"87 W Union St Ashland MA 01721",
    "addr:housenumber":"87",
    "addr:postcode":"01721",
    "addr:street":"W Union St",
    "iso:country":"US",
    "sg:address":"87 W Union St",
    "sg:city":"Ashland",
    "sg:classifiers":[
        {
            "category":"Utilities",
            "subcategory":"Cable",
            "type":"Services"
        }
    ],
    "sg:phone":"+1 508 881 9222",
    "sg:postcode":"01721",
    "sg:province":"MA",
    "sg:tags":[
        "television"
    ],
    "wof:name":"Ashland Cable Access Corp",
    "wof:placetype":"venue"
},
  "geometry": {"coordinates":[-71.47128499999999,42.251903],"type":"Point"}
}