{
  "type": "Feature",
  "properties": {
    "iso:country":"US",
    "sg:address":"493 High St",
    "sg:city":"Dedham",
    "sg:classifiers":[
        {
            "category":"Personal",
            "subcategory":"Beauty Salon",
            "type":"Services"
        }
    ],
    "sg:phone":"+1 781 329 9338",
    "sg:postcode":"02026",
    "sg:province":"MA",
    "sg:tags":[
        "treatment",
        "skin"
    ],
    "wof:name":"Amer Skin Care By Catherine",
    "wof:placetype":"venue"
},
  "geometry": {"coordinates":[-71.17009299999999,42.24885],"type":"Point"}
}