{
  "type": "Feature",
  "properties": {
    "iso:country":"US",
    "sg:address":"164 S Main Rd",
    "sg:city":"Otis",
    "sg:classifiers":[
        {
            "category":"Real Estate",
            "subcategory":"Real Estate Agent",
            "type":"Services"
        }
    ],
    "sg:phone":"+1 413 269 6300",
    "sg:postcode":"01253",
    "sg:province":"MA",
    "wof:name":"Century 21 Franklin St Assoc",
    "wof:placetype":"venue"
},
  "geometry": {"coordinates":[-73.090442,42.189347],"type":"Point"}
}