{
  "type": "Feature",
  "properties": {
    "iso:country":"US",
    "sg:address":"697 State Rd",
    "sg:city":"West Tisbury",
    "sg:classifiers":[
        {
            "category":"Professional",
            "type":"Services"
        }
    ],
    "sg:phone":"+1 508 693 4484",
    "sg:postcode":"02575",
    "sg:province":"MA",
    "sg:tags":[
        "arts",
        "artist"
    ],
    "wof:name":"Clark Goffs' Print & Notes",
    "wof:placetype":"venue"
},
  "geometry": {"coordinates":[-70.67739899999999,41.402814],"type":"Point"}
}