{
  "type": "Feature",
  "properties": {
    "iso:country":"US",
    "sg:address":"PO Box 37",
    "sg:city":"Chartley",
    "sg:classifiers":[
        {
            "category":"Personal",
            "type":"Services"
        }
    ],
    "sg:phone":"+1 508 222 1800",
    "sg:postcode":"02712",
    "sg:province":"MA",
    "sg:tags":[
        "sewing",
        "alteration"
    ],
    "wof:name":"Personal Touch Monogramming - CLOSED",
    "wof:placetype":"venue"
},
  "geometry": {"coordinates":[-71.23519899999999,41.951302],"type":"Point"}
}