{
  "type": "Feature",
  "properties": {
    "addr:full": "PO Box 37 Chartley MA 02712",
    "addr:housenumber": "po box 37",
    "addr:postcode": "02712",
    "iso:country": "US",
    "sg:address": "PO Box 37",
    "sg:city": "Chartley",
    "sg:classifiers": [
      {
        "category": "Personal",
        "type": "Services"
      }
    ],
    "sg:phone": "+1 508 222 1800",
    "sg:postcode": "02712",
    "sg:province": "MA",
    "sg:tags": [
      "sewing",
      "alteration"
    ],
    "wof:name": "Personal Touch Monogramming - CLOSED",
    "wof:placetype": "venue"
  },
  "geometry": {"coordinates":[-71.235199,41.951302],"type":"Point"}
}
