{
  "type": "Feature",
  "properties": {
    "iso:country":"US",
    "sg:address":"214 Chapel St",
    "sg:city":"Gardner",
    "sg:classifiers":[
        {
            "category":"Professional",
            "subcategory":"Accounting & Tax Preparation",
            "type":"Services"
        }
    ],
    "sg:phone":"+1 978 632 2333",
    "sg:postcode":"01440",
    "sg:province":"MA",
    "sg:tags":[
        "return",
        "filing"
    ],
    "wof:name":"SEL Business Svc",
    "wof:placetype":"venue"
},
  "geometry": {"coordinates":[-71.9571,42.582433],"type":"Point"}
}