{
  "type": "Feature",
  "properties": {
    "iso:country":"US",
    "sg:address":"15 Park Ave",
    "sg:city":"Hull",
    "sg:classifiers":[
        {
            "category":"Autos & Motor Vehicles",
            "subcategory":"Boat Sales",
            "type":"Retail Goods"
        }
    ],
    "sg:phone":"+1 781 925 2300",
    "sg:postcode":"02045",
    "sg:province":"MA",
    "sg:tags":[
        "dealer",
        "sales"
    ],
    "wof:name":"Gould Boat Shop",
    "wof:placetype":"venue"
},
  "geometry": {"coordinates":[-70.853297,42.267674],"type":"Point"}
}