{
  "type": "Feature",
  "properties": {
    "addr:full":"346 West Ave Ludlow MA 01056",
    "addr:housenumber":"346",
    "addr:postcode":"01056",
    "addr:street":"West Ave",
    "iso:country":"US",
    "sg:address":"346 West Ave",
    "sg:city":"Ludlow",
    "sg:classifiers":[
        {
            "category":"Personal",
            "subcategory":"Beauty Salon",
            "type":"Services"
        }
    ],
    "sg:phone":"+1 413 547 2655",
    "sg:postcode":"01056",
    "sg:province":"MA",
    "sg:tags":[
        "manicuring"
    ],
    "wof:name":"Elegant Nails",
    "wof:placetype":"venue"
},
  "geometry": {"coordinates":[-72.48492299999999,42.164738],"type":"Point"}
}