{
  "type": "Feature",
  "properties": {
    "addr:full":"955 Massachusetts Ave # 340 Cambridge MA 02139",
    "addr:housenumber":"955",
    "addr:postcode":"02139",
    "addr:street":"Massachusetts Ave # 340",
    "iso:country":"US",
    "sg:address":"955 Massachusetts Ave # 340",
    "sg:city":"Cambridge",
    "sg:classifiers":[
        {
            "category":"Education",
            "subcategory":"University",
            "type":"Public Place"
        }
    ],
    "sg:phone":"+1 866 661 8447",
    "sg:postcode":"02139",
    "sg:province":"MA",
    "sg:tags":[
        "college"
    ],
    "wof:name":"College & University Advertising",
    "wof:placetype":"venue"
},
  "geometry": {"coordinates":[-71.10945,42.368679],"type":"Point"}
}