{
  "type": "Feature",
  "properties": {
    "iso:country":"US",
    "sg:address":"32 Corser Hill Rd",
    "sg:city":"Great Barrington",
    "sg:classifiers":[
        {
            "category":"Professional",
            "subcategory":"Lawyer & Legal Services",
            "type":"Services"
        }
    ],
    "sg:phone":"+1 413 229 7080",
    "sg:postcode":"01230",
    "sg:province":"MA",
    "sg:tags":[
        "attorney"
    ],
    "wof:name":"Susan M Smith Attorney",
    "wof:placetype":"venue"
},
  "geometry": {"coordinates":[-73.28615000000001,42.134473],"type":"Point"}
}