{
  "type": "Feature",
  "properties": {
    "addr:full":"124 Washinton St Boston MA 02121",
    "addr:housenumber":"124",
    "addr:postcode":"02121",
    "addr:street":"Washinton St",
    "iso:country":"US",
    "sg:address":"124 Washinton St",
    "sg:city":"Boston",
    "sg:classifiers":[
        {
            "category":"Personal",
            "subcategory":"Beauty Salon",
            "type":"Services"
        }
    ],
    "sg:phone":"+1 617 436 9977",
    "sg:postcode":"02121",
    "sg:province":"MA",
    "sg:tags":[
        "spa"
    ],
    "wof:name":"Amanda's Hair Salon",
    "wof:placetype":"venue"
},
  "geometry": {"coordinates":[-71.079911,42.305054],"type":"Point"}
}