{
  "type": "Feature",
  "properties": {
    "iso:country":"US",
    "sg:address":"180 Greenwood Ave",
    "sg:city":"Hyannis",
    "sg:classifiers":[
        {
            "category":"Local Transit",
            "type":"Transportation"
        }
    ],
    "sg:phone":"+1 508 778 0558",
    "sg:postcode":"02601",
    "sg:province":"MA",
    "sg:tags":[
        "passenger",
        "photo",
        "studio",
        "limo",
        "portrait",
        "limousine"
    ],
    "sg:website":"www.classiclimocapecod.com",
    "wof:name":"Classic Limousine Service",
    "wof:placetype":"venue"
},
  "geometry": {"coordinates":[-70.29920199999999,41.6404],"type":"Point"}
}