{
  "type": "Feature",
  "properties": {
    "iso:country":"US",
    "sg:address":"7 Pleasant St",
    "sg:city":"Rockport",
    "sg:classifiers":[
        {
            "category":"Professional",
            "subcategory":"Art Services",
            "type":"Services"
        }
    ],
    "sg:phone":"+1   ",
    "sg:postcode":"01966",
    "sg:province":"MA",
    "sg:tags":[
        "commercial",
        "design"
    ],
    "wof:name":"Lauterstien Graphic Design",
    "wof:placetype":"venue"
},
  "geometry": {"coordinates":[-70.61445399999999,42.656118],"type":"Point"}
}