{
  "type": "Feature",
  "properties": {
    "addr:full":"37 Jefferson Ave Cambridge MA 02129",
    "addr:housenumber":"37",
    "addr:postcode":"02129",
    "addr:street":"Jefferson Ave",
    "iso:country":"US",
    "sg:address":"37 Jefferson Ave",
    "sg:city":"Cambridge",
    "sg:classifiers":[
        {
            "category":"Government",
            "subcategory":"Office",
            "type":"Public Place"
        }
    ],
    "sg:phone":"+1 617 498 1119",
    "sg:postcode":"02129",
    "sg:province":"MA",
    "sg:tags":[
        "state",
        "program",
        "health"
    ],
    "wof:name":"Jefferson Park Health Ctr",
    "wof:placetype":"venue"
},
  "geometry": {"coordinates":[-71.061637,42.377341],"type":"Point"}
}