{
  "type": "Feature",
  "properties": {
    "addr:full": "241 Main St Northampton MA 01060",
    "addr:housenumber": "241",
    "addr:postcode": "01060",
    "addr:street": "Main St",
    "iso:country": "US",
    "sg:address": "241 Main St",
    "sg:city": "Northampton",
    "sg:classifiers": [
      {
        "category": "Restaurant",
        "type": "Food \u0026 Drink"
      }
    ],
    "sg:phone": "+1 413 587 3401",
    "sg:postcode": "01060",
    "sg:province": "MA",
    "sg:tags": [
      "cafe"
    ],
    "wof:name": "Java Net Cafe",
    "wof:placetype": "venue"
  },
  "geometry": {"coordinates":[-72.632489,42.31783],"type":"Point"}
}
