{
  "type": "Feature",
  "properties": {
    "iso:country":"US",
    "sg:address":"241 Main St",
    "sg:city":"Northampton",
    "sg:classifiers":[
        {
            "category":"Restaurant",
            "type":"Food & Drink"
        }
    ],
    "sg:phone":"+1 413 587 3401",
    "sg:postcode":"01060",
    "sg:province":"MA",
    "sg:tags":[
        "cafe"
    ],
    "wof:name":"Java Net Cafe",
    "wof:placetype":"venue"
},
  "geometry": {"coordinates":[-72.63248900000001,42.31783],"type":"Point"}
}