{
  "type": "Feature",
  "properties": {
    "iso:country":"US",
    "sg:address":"25 Mayflower St",
    "sg:city":"Plymouth",
    "sg:classifiers":[
        {
            "category":"Travel",
            "subcategory":"Hotels & Motels",
            "type":"Entertainment"
        }
    ],
    "sg:phone":"+1 508 732 0093",
    "sg:postcode":"02360",
    "sg:province":"MA",
    "sg:tags":[
        "breakfast",
        "accommodation",
        "bed"
    ],
    "wof:name":"Mayflower Bed & Breakfast",
    "wof:placetype":"venue"
},
  "geometry": {"coordinates":[-70.66202,41.951845],"type":"Point"}
}