{
  "type": "Feature",
  "properties": {
    "iso:country":"US",
    "sg:address":"2 Flagg St",
    "sg:city":"Bridgewater",
    "sg:classifiers":[
        {
            "category":"Professional",
            "type":"Services"
        }
    ],
    "sg:phone":"+1 508 697 5474",
    "sg:postcode":"02324",
    "sg:province":"MA",
    "sg:tags":[
        "establishment"
    ],
    "wof:name":"Bridgewater Youth Soccer Assn",
    "wof:placetype":"venue"
},
  "geometry": {"coordinates":[-70.9562,41.970568],"type":"Point"}
}