{
  "type": "Feature",
  "properties": {
    "addr:full":"21 Bellville Ln Millbury MA 01527",
    "addr:housenumber":"21",
    "addr:postcode":"01527",
    "addr:street":"Bellville Ln",
    "iso:country":"US",
    "sg:address":"21 Bellville Ln",
    "sg:city":"Millbury",
    "sg:classifiers":[
        {
            "category":"Retail",
            "subcategory":"Animal Services",
            "type":"Services"
        }
    ],
    "sg:phone":"+1 508 865 6180",
    "sg:postcode":"01527",
    "sg:province":"MA",
    "sg:tags":[
        "pet",
        "grooming",
        "washing"
    ],
    "wof:name":"Diamond In The Ruff",
    "wof:placetype":"venue"
},
  "geometry": {"coordinates":[-71.748345,42.195112],"type":"Point"}
}