{
  "type": "Feature",
  "properties": {
    "iso:country":"US",
    "sg:address":"3 Grove St",
    "sg:city":"Berkley",
    "sg:classifiers":[
        {
            "category":"Home & Garden",
            "subcategory":"Garden Supply",
            "type":"Retail Goods"
        }
    ],
    "sg:phone":"+1 508 822 6748",
    "sg:postcode":"02779",
    "sg:province":"MA",
    "sg:tags":[
        "landscaping",
        "equipment"
    ],
    "wof:name":"Stetson Agway",
    "wof:placetype":"venue"
},
  "geometry": {"coordinates":[-71.027434,41.830011],"type":"Point"}
}