{
  "type": "Feature",
  "properties": {
    "addr:full":"315 Andover St North Andover MA 01845",
    "addr:housenumber":"315",
    "addr:postcode":"01845",
    "addr:street":"Andover St",
    "iso:country":"US",
    "sg:address":"315 Andover St",
    "sg:city":"North Andover",
    "sg:classifiers":[
        {
            "category":"Farming",
            "subcategory":"Farm",
            "type":"Manufacturing & Wholesale Goods"
        }
    ],
    "sg:phone":"+1 978 688 8058",
    "sg:postcode":"01845",
    "sg:province":"MA",
    "wof:name":"Smolak Farms",
    "wof:placetype":"venue"
},
  "geometry": {"coordinates":[-71.12463,42.677285],"type":"Point"}
}