{
  "type": "Feature",
  "properties": {
    "iso:country":"US",
    "sg:address":"21 Canal St",
    "sg:city":"Lawrence",
    "sg:classifiers":[
        {
            "category":"Wholesale",
            "subcategory":"Medical Equipment & Supplies",
            "type":"Manufacturing & Wholesale Goods"
        }
    ],
    "sg:phone":"+1 978 688 5454",
    "sg:postcode":"01840",
    "sg:province":"MA",
    "sg:tags":[
        "physician",
        "surgeon"
    ],
    "wof:name":"Racine Medical Electronics Inc",
    "wof:placetype":"venue"
},
  "geometry": {"coordinates":[-71.152967,42.706556],"type":"Point"}
}