{
  "type": "Feature",
  "properties": {
    "addr:full": "21 Canal St Lawrence MA 01840",
    "addr:housenumber": "21",
    "addr:postcode": "01840",
    "addr:street": "Canal St",
    "iso:country": "US",
    "sg:address": "21 Canal St",
    "sg:city": "Lawrence",
    "sg:classifiers": [
      {
        "category": "Wholesale",
        "subcategory": "Medical Equipment \u0026 Supplies",
        "type": "Manufacturing \u0026 Wholesale Goods"
      }
    ],
    "sg:phone": "+1 978 688 5454",
    "sg:postcode": "01840",
    "sg:province": "MA",
    "sg:tags": [
      "physician",
      "surgeon"
    ],
    "wof:name": "Racine Medical Electronics Inc",
    "wof:placetype": "venue"
  },
  "geometry": {"coordinates":[-71.152967,42.706556],"type":"Point"}
}
