{
  "type": "Feature",
  "properties": {
    "addr:full": "128 Cedar St Milford MA 01757",
    "addr:housenumber": "128",
    "addr:postcode": "01757",
    "addr:street": "Cedar St",
    "iso:country": "US",
    "ovtr:label": "Wendy's, 128 Cedar St Milford MA US",
    "ovtr:similarity": 3.416424036026001,
    "sg:address": "128 Cedar St",
    "sg:city": "Milford",
    "sg:classifiers": [
      {
        "category": "Restaurant",
        "type": "Food \u0026 Drink"
      }
    ],
    "sg:menulink": "http://www.allmenus.com/ma/milford/173275-wendys/menu/",
    "sg:phone": "+1 508 478 5118",
    "sg:postcode": "01757",
    "sg:province": "MA",
    "sg:tags": [
      "burger",
      "american",
      "soup"
    ],
    "wof:name": "Wendy's",
    "wof:placetype": "venue"
  },
  "geometry": {"coordinates":[-71.505899,42.187382],"type":"Point"}
}
