{
  "type": "Feature",
  "properties": {
    "iso:country":"US",
    "sg:address":"146 Forest Hills St",
    "sg:city":"Jamaica Plain",
    "sg:classifiers":[
        {
            "category":"Organizations",
            "subcategory":"Religious Organization",
            "type":"Services"
        }
    ],
    "sg:phone":"+1   ",
    "sg:postcode":"02130",
    "sg:province":"MA",
    "wof:name":"Ukranian Chur Christ The King",
    "wof:placetype":"venue"
},
  "geometry": {"coordinates":[-71.105464,42.298978],"type":"Point"}
}