{
  "type": "Feature",
  "properties": {
    "iso:country":"US",
    "sg:address":"411 Main St",
    "sg:city":"Wakefield",
    "sg:classifiers":[
        {
            "category":"Restaurant",
            "type":"Food & Drink"
        }
    ],
    "sg:phone":"+1 781 245 9848",
    "sg:postcode":"01880",
    "sg:province":"MA",
    "sg:tags":[
        "parlor",
        "ice",
        "cream"
    ],
    "wof:name":"Brigham's Ice Cream",
    "wof:placetype":"venue"
},
  "geometry": {"coordinates":[-71.070448,42.503468],"type":"Point"}
}