{
  "type": "Feature",
  "properties": {
    "addr:full":"770 Boylston St Boston MA 02199",
    "addr:housenumber":"770",
    "addr:postcode":"02199",
    "addr:street":"Boylston St",
    "iso:country":"US",
    "sg:address":"770 Boylston St",
    "sg:city":"Boston",
    "sg:classifiers":[
        {
            "category":"Shopping",
            "subcategory":"Jewelry",
            "type":"Retail Goods"
        }
    ],
    "sg:phone":"+1 617 859 1200",
    "sg:postcode":"02199",
    "sg:province":"MA",
    "sg:tags":[
        "jeweler"
    ],
    "wof:name":"Eye For Style",
    "wof:placetype":"venue"
},
  "geometry": {"coordinates":[-71.081424,42.349018],"type":"Point"}
}