{
  "type": "Feature",
  "properties": {
    "iso:country":"US",
    "sg:address":"2 Constitution Rd",
    "sg:city":"Charlestown",
    "sg:classifiers":[
        {
            "category":"Building & Trades",
            "subcategory":"Construction",
            "type":"Services"
        }
    ],
    "sg:phone":"+1 617 567 0535",
    "sg:postcode":"02129",
    "sg:province":"MA",
    "sg:tags":[
        "company"
    ],
    "wof:name":"B & E Construction",
    "wof:placetype":"venue"
},
  "geometry": {"coordinates":[-71.06102799999999,42.370866],"type":"Point"}
}