{
  "type": "Feature",
  "properties": {
    "addr:full": "2 Constitution Rd Charlestown MA 02129",
    "addr:housenumber": "2",
    "addr:postcode": "02129",
    "addr:street": "Constitution Rd",
    "iso:country": "US",
    "sg:address": "2 Constitution Rd",
    "sg:city": "Charlestown",
    "sg:classifiers": [
      {
        "category": "Building \u0026 Trades",
        "subcategory": "Construction",
        "type": "Services"
      }
    ],
    "sg:phone": "+1 617 567 0535",
    "sg:postcode": "02129",
    "sg:province": "MA",
    "sg:tags": [
      "company"
    ],
    "wof:name": "B \u0026 E Construction",
    "wof:placetype": "venue"
  },
  "geometry": {"coordinates":[-71.061028,42.370866],"type":"Point"}
}
