{
  "type": "Feature",
  "properties": {
    "iso:country":"US",
    "sg:address":"649 N Main St",
    "sg:city":"Brockton",
    "sg:classifiers":[
        {
            "category":"Insurance",
            "subcategory":"Insurance Agent",
            "type":"Services"
        }
    ],
    "sg:phone":"+1 508 584 2343",
    "sg:postcode":"02301",
    "sg:province":"MA",
    "sg:tags":[
        "adjuster"
    ],
    "wof:name":"Eastern Adjustment & Appraisal",
    "wof:placetype":"venue"
},
  "geometry": {"coordinates":[-71.02103700000001,42.100578],"type":"Point"}
}