{
  "type": "Feature",
  "properties": {
    "iso:country":"US",
    "sg:address":"28 State St Ste 1100",
    "sg:city":"Boston",
    "sg:classifiers":[
        {
            "category":"Professional",
            "subcategory":"Management & Consulting",
            "type":"Services"
        },
        {
            "category":"Banks & Credit Unions",
            "subcategory":"Financial Services",
            "type":"Services"
        }
    ],
    "sg:phone":"+1 617 747 5800",
    "sg:postcode":"02109",
    "sg:province":"MA",
    "sg:tags":[
        "consultant",
        "financing",
        "planning"
    ],
    "wof:name":"High Rock Capital",
    "wof:placetype":"venue"
},
  "geometry": {"coordinates":[-71.057152,42.358799],"type":"Point"}
}