{
  "type": "Feature",
  "properties": {
    "addr:full": "470 Washington St Ste 2 Norwood MA 02062",
    "addr:housenumber": "470",
    "addr:postcode": "02062",
    "addr:street": "Washington St Ste 2",
    "iso:country": "US",
    "sg:address": "470 Washington St Ste 2",
    "sg:city": "Norwood",
    "sg:classifiers": [
      {
        "category": "Professional",
        "subcategory": "Lawyer \u0026 Legal Services",
        "type": "Services"
      }
    ],
    "sg:phone": "+1 781 762 4600",
    "sg:postcode": "02062",
    "sg:province": "MA",
    "wof:name": "Hern David Jr Atty",
    "wof:placetype": "venue"
  },
  "geometry": {"coordinates":[-71.198502,42.198101],"type":"Point"}
}
