{
  "type": "Feature",
  "properties": {
    "iso:country":"US",
    "sg:address":"113 Main St",
    "sg:city":"Sturbridge",
    "sg:classifiers":[
        {
            "category":"Education",
            "subcategory":"Kindergarten",
            "type":"Public Place"
        }
    ],
    "sg:phone":"+1 508 347 7211",
    "sg:postcode":"01566",
    "sg:province":"MA",
    "sg:tags":[
        "school",
        "driving"
    ],
    "wof:name":"Green Light Driving School",
    "wof:placetype":"venue"
},
  "geometry": {"coordinates":[-72.064475,42.088223],"type":"Point"}
}