{
  "type": "Feature",
  "properties": {
    "iso:country":"US",
    "sg:address":"515 Hyde Park Avenue",
    "sg:city":"Roslindale",
    "sg:classifiers":[
        {
            "category":"Education",
            "subcategory":"School",
            "type":"Public Place"
        }
    ],
    "sg:phone":"+1 617 635 8324",
    "sg:postcode":"02131",
    "sg:province":"MA",
    "sg:tags":[
        "high",
        "middle",
        "elementary"
    ],
    "wof:name":"Boston City of",
    "wof:placetype":"venue"
},
  "geometry": {"coordinates":[-71.11895699999999,42.282743],"type":"Point"}
}