{
  "type": "Feature",
  "properties": {
    "addr:full":"60 Prospect St Peabody MA 01960",
    "addr:housenumber":"60",
    "addr:postcode":"01960",
    "addr:street":"Prospect St",
    "iso:country":"US",
    "sg:address":"60 Prospect St",
    "sg:city":"Peabody",
    "sg:classifiers":[
        {
            "category":"Organizations",
            "subcategory":"Religious Organization",
            "type":"Services"
        }
    ],
    "sg:phone":"+1 978 531 1964",
    "sg:postcode":"01960",
    "sg:province":"MA",
    "sg:tags":[
        "church"
    ],
    "wof:name":"South Congregational Church",
    "wof:placetype":"venue"
},
  "geometry": {"coordinates":[-70.948193,42.542981],"type":"Point"}
}