{
  "type": "Feature",
  "properties": {
    "iso:country":"US",
    "sg:address":"1284 Memorial Dr",
    "sg:city":"Chicopee",
    "sg:classifiers":[
        {
            "category":"Restaurant",
            "type":"Food & Drink"
        }
    ],
    "sg:phone":"+1 413 593 1800",
    "sg:postcode":"01020",
    "sg:province":"MA",
    "wof:name":"D R's Pizza",
    "wof:placetype":"venue"
},
  "geometry": {"coordinates":[-72.57612,42.192839],"type":"Point"}
}