{
  "type": "Feature",
  "properties": {
    "addr:full": "35 W Main St Northborough MA 01532",
    "addr:housenumber": "35",
    "addr:postcode": "01532",
    "addr:street": "W Main St",
    "iso:country": "US",
    "sg:address": "35 W Main St",
    "sg:city": "Northborough",
    "sg:classifiers": [
      {
        "category": "Autos \u0026 Motor Vehicles",
        "subcategory": "Fuel \u0026 Gas Station",
        "type": "Retail Goods"
      }
    ],
    "sg:phone": "+1 508 393 3396",
    "sg:postcode": "01532",
    "sg:province": "MA",
    "sg:tags": [
      "oil"
    ],
    "wof:name": "Northborough Citgo",
    "wof:placetype": "venue"
  },
  "geometry": {"coordinates":[-71.64377,42.319919],"type":"Point"}
}
