{
  "type": "Feature",
  "properties": {
    "iso:country":"US",
    "sg:address":"35 W Main St",
    "sg:city":"Northborough",
    "sg:classifiers":[
        {
            "category":"Autos & Motor Vehicles",
            "subcategory":"Fuel & Gas Station",
            "type":"Retail Goods"
        }
    ],
    "sg:phone":"+1 508 393 3396",
    "sg:postcode":"01532",
    "sg:province":"MA",
    "sg:tags":[
        "oil"
    ],
    "wof:name":"Northborough Citgo",
    "wof:placetype":"venue"
},
  "geometry": {"coordinates":[-71.64377,42.319919],"type":"Point"}
}