{
  "type": "Feature",
  "properties": {
    "addr:full": "65 Walnut St Wellesley Hills MA 02481",
    "addr:housenumber": "65",
    "addr:postcode": "02481",
    "addr:street": "Walnut St",
    "iso:country": "US",
    "sg:address": "65 Walnut St",
    "sg:city": "Wellesley Hills",
    "sg:classifiers": [
      {
        "category": "Real Estate",
        "subcategory": "Real Estate Agent",
        "type": "Services"
      }
    ],
    "sg:phone": "+1 781 237 1100",
    "sg:postcode": "02481",
    "sg:province": "MA",
    "wof:name": "Simard Co LLC",
    "wof:placetype": "venue"
  },
  "geometry": {"coordinates":[-71.25333,42.324257],"type":"Point"}
}
