{
  "type": "Feature",
  "properties": {
    "iso:country":"US",
    "sg:address":"68 Dean St",
    "sg:city":"Everett",
    "sg:classifiers":[
        {
            "category":"Professional",
            "subcategory":"Computer Services",
            "type":"Services"
        }
    ],
    "sg:phone":"+1 617 387 9555",
    "sg:postcode":"02149",
    "sg:province":"MA",
    "sg:tags":[
        "equipment",
        "repair"
    ],
    "wof:name":"Red Devil Computer Services",
    "wof:placetype":"venue"
},
  "geometry": {"coordinates":[-71.05582,42.412309],"type":"Point"}
}