{
  "type": "Feature",
  "properties": {
    "addr:full": "422 Belchertown Rd Amherst MA 01002",
    "addr:housenumber": "422",
    "addr:postcode": "01002",
    "addr:street": "Belchertown Rd",
    "iso:country": "US",
    "sg:address": "422 Belchertown Rd",
    "sg:city": "Amherst",
    "sg:classifiers": [
      {
        "category": "Real Estate",
        "subcategory": "Real Estate Operator",
        "type": "Services"
      }
    ],
    "sg:phone": "+1 413 253 3000",
    "sg:postcode": "01002",
    "sg:province": "MA",
    "sg:tags": [
      "apartment"
    ],
    "wof:name": "Rolling Green Apartments",
    "wof:placetype": "venue"
  },
  "geometry": {"coordinates":[-72.488204,42.36229],"type":"Point"}
}
