{
  "type": "Feature",
  "properties": {
    "addr:full":"12 Oak St Shrewsbury MA 01545",
    "addr:housenumber":"12",
    "addr:postcode":"01545",
    "addr:street":"Oak St",
    "iso:country":"US",
    "sg:address":"12 Oak St",
    "sg:city":"Shrewsbury",
    "sg:classifiers":[
        {
            "category":"Health Services",
            "subcategory":"Medical Lab",
            "type":"Services"
        }
    ],
    "sg:phone":"+1 508 842 0402",
    "sg:postcode":"01545",
    "sg:province":"MA",
    "sg:tags":[
        "laboratory"
    ],
    "wof:name":"Sunrise Orthodontic Lab",
    "wof:placetype":"venue"
},
  "geometry": {"coordinates":[-71.728269,42.284629],"type":"Point"}
}