{
  "type": "Feature",
  "properties": {
    "iso:country":"US",
    "sg:address":"339 Main St",
    "sg:city":"Hingham",
    "sg:classifiers":[
        {
            "category":"Government",
            "subcategory":"Fire Station",
            "type":"Public Place"
        }
    ],
    "sg:phone":"+1 781 741 1480",
    "sg:postcode":"02043",
    "sg:province":"MA",
    "sg:tags":[
        "department"
    ],
    "wof:name":"Hingham Fire Dept",
    "wof:placetype":"venue"
},
  "geometry": {"coordinates":[-70.87999600000001,42.231271],"type":"Point"}
}