{
  "type": "Feature",
  "properties": {
    "addr:full": "339 Main St Hingham MA 02043",
    "addr:housenumber": "339",
    "addr:postcode": "02043",
    "addr:street": "Main St",
    "iso:country": "US",
    "ovtr:label": "Hingham Fire Department, 339 Main St Hingham MA US",
    "ovtr:similarity": 3.354227066040039,
    "sg:address": "339 Main St",
    "sg:city": "Hingham",
    "sg:classifiers": [
      {
        "category": "Government",
        "subcategory": "Fire Station",
        "type": "Public Place"
      }
    ],
    "sg:phone": "+1 781 741 1480",
    "sg:postcode": "02043",
    "sg:province": "MA",
    "sg:tags": [
      "department"
    ],
    "wof:name": "Hingham Fire Dept",
    "wof:placetype": "venue"
  },
  "geometry": {"coordinates":[-70.879996,42.231271],"type":"Point"}
}
