{
  "type": "Feature",
  "properties": {
    "addr:full":"665 Prospect St Ste 1 Chicopee MA 01020",
    "addr:housenumber":"665",
    "addr:postcode":"01020",
    "addr:street":"Prospect St Ste 1",
    "iso:country":"US",
    "sg:address":"665 Prospect St Ste 1",
    "sg:city":"Chicopee",
    "sg:classifiers":[
        {
            "category":"Manufacturing",
            "subcategory":"Buildings",
            "type":"Manufacturing & Wholesale Goods"
        },
        {
            "category":"Building & Trades",
            "subcategory":"Construction",
            "type":"Services"
        }
    ],
    "sg:phone":"+1 413 536 2060",
    "sg:postcode":"01020",
    "sg:province":"MA",
    "sg:tags":[
        "consultant",
        "metal",
        "contractor"
    ],
    "wof:name":"Berneche L N Inc",
    "wof:placetype":"venue"
},
  "geometry": {"coordinates":[-72.580929,42.201394],"type":"Point"}
}