{
  "type": "Feature",
  "properties": {
    "addr:full":"27 Damon Park Arlington MA 02474",
    "addr:housenumber":"27",
    "addr:postcode":"02474",
    "addr:street":"Damon Park",
    "iso:country":"US",
    "sg:address":"27 Damon Park",
    "sg:city":"Arlington",
    "sg:classifiers":[
        {
            "category":"Building & Trades",
            "subcategory":"Cleaning & Sanitation",
            "type":"Services"
        }
    ],
    "sg:phone":"+1 508 954 5506",
    "sg:postcode":"02474",
    "sg:province":"MA",
    "sg:tags":[
        "home"
    ],
    "sg:website":"www.housecleaningweston.com/",
    "wof:name":"Stella's House Cleaning Services",
    "wof:placetype":"venue"
},
  "geometry": {"coordinates":[-71.147841,42.414023],"type":"Point"}
}