{
  "type": "Feature",
  "properties": {
    "addr:full":"36 Philip Darch Rd Watertown MA 02472",
    "addr:housenumber":"36",
    "addr:postcode":"02472",
    "addr:street":"Philip Darch Rd",
    "iso:country":"US",
    "sg:address":"36 Philip Darch Rd",
    "sg:city":"Watertown",
    "sg:classifiers":[
        {
            "category":"Education",
            "subcategory":"School",
            "type":"Public Place"
        }
    ],
    "sg:phone":"+1 617 926 6119",
    "sg:postcode":"02472",
    "sg:province":"MA",
    "wof:name":"Watertown Housing Learning Ctr",
    "wof:placetype":"venue"
},
  "geometry": {"coordinates":[-71.19283,42.377396],"type":"Point"}
}