{
  "type": "Feature",
  "properties": {
    "addr:full": "431 Essex St Lawrence MA 01840",
    "addr:housenumber": "431",
    "addr:postcode": "01840",
    "addr:street": "Essex St",
    "iso:country": "US",
    "sg:address": "431 Essex St",
    "sg:city": "Lawrence",
    "sg:classifiers": [
      {
        "category": "Shopping",
        "subcategory": "Clothing, Apparel, \u0026 Fashions",
        "type": "Retail Goods"
      }
    ],
    "sg:phone": "+1 978 975 3957",
    "sg:postcode": "01840",
    "sg:province": "MA",
    "wof:name": "Allante Fashions",
    "wof:placetype": "venue"
  },
  "geometry": {"coordinates":[-71.163775,42.706946],"type":"Point"}
}
