{
  "type": "Feature",
  "properties": {
    "addr:full":"3 Valley View Rd Williamsburg MA 01096",
    "addr:housenumber":"3",
    "addr:postcode":"01096",
    "addr:street":"Valley View Rd",
    "iso:country":"US",
    "sg:address":"3 Valley View Rd",
    "sg:city":"Williamsburg",
    "sg:classifiers":[
        {
            "category":"Shopping",
            "subcategory":"Clothing, Apparel, & Fashions",
            "type":"Retail Goods"
        }
    ],
    "sg:phone":"+1 413 268 7747",
    "sg:postcode":"01096",
    "sg:province":"MA",
    "sg:tags":[
        "wig",
        "toupee",
        "hairpiece"
    ],
    "wof:name":"Smart Wig Salon",
    "wof:placetype":"venue"
},
  "geometry": {"coordinates":[-72.72453,42.39214],"type":"Point"}
}