{
  "type": "Feature",
  "properties": {
    "addr:full":"2 Peters Rd Middleton MA 01950",
    "addr:housenumber":"2",
    "addr:postcode":"01950",
    "addr:street":"Peters Rd",
    "iso:country":"US",
    "sg:address":"2 Peters Rd",
    "sg:city":"Middleton",
    "sg:classifiers":[
        {
            "category":"Building & Trades",
            "subcategory":"Plumbing",
            "type":"Services"
        }
    ],
    "sg:phone":"+1   ",
    "sg:postcode":"01950",
    "sg:province":"MA",
    "sg:tags":[
        "contractor"
    ],
    "wof:name":"McGrath Thomas F Plbg & Htg",
    "wof:placetype":"venue"
},
  "geometry": {"coordinates":[-70.925612,42.805853],"type":"Point"}
}