{
  "type": "Feature",
  "properties": {
    "addr:full":"10 E Main St West Yarmouth MA 02673",
    "addr:housenumber":"10",
    "addr:postcode":"02673",
    "addr:street":"E Main St",
    "iso:country":"US",
    "sg:address":"10 E Main St",
    "sg:city":"West Yarmouth",
    "sg:classifiers":[
        {
            "category":"Health Services",
            "subcategory":"Doctor",
            "type":"Services"
        }
    ],
    "sg:phone":"+1 508 790 7000",
    "sg:postcode":"02673",
    "sg:province":"MA",
    "wof:name":"Barna Steven MD",
    "wof:placetype":"venue"
},
  "geometry": {"coordinates":[-70.268327,41.657875],"type":"Point"}
}