{
  "type": "Feature",
  "properties": {
    "addr:full":"150 Baker Avenue Ext Concord MA 01742",
    "addr:housenumber":"150",
    "addr:postcode":"01742",
    "addr:street":"Baker Avenue Ext",
    "iso:country":"US",
    "sg:address":"150 Baker Avenue Ext",
    "sg:city":"Concord",
    "sg:classifiers":[
        {
            "category":"Communications",
            "subcategory":"Newspaper",
            "type":"Services"
        }
    ],
    "sg:phone":"+1 781 229 0918",
    "sg:postcode":"01742",
    "sg:province":"MA",
    "sg:tags":[
        "print",
        "medium"
    ],
    "wof:name":"Burlington Union",
    "wof:placetype":"venue"
},
  "geometry": {"coordinates":[-71.38720000000001,42.4626],"type":"Point"}
}