{
  "type": "Feature",
  "properties": {
    "addr:full": "680 Mechanic St Leominster MA 01453",
    "addr:housenumber": "680",
    "addr:postcode": "01453",
    "addr:street": "Mechanic St",
    "iso:country": "US",
    "ovtr:label": "Piccolo Mondo Child Care, 680 Mechanic St Leominster MA US",
    "ovtr:similarity": 2.0184121131896973,
    "sg:address": "680 Mechanic St",
    "sg:city": "Leominster",
    "sg:classifiers": [
      {
        "category": "Social Services",
        "subcategory": "Child Care",
        "type": "Services"
      }
    ],
    "sg:phone": "+1 978 537 2764",
    "sg:postcode": "01453",
    "sg:province": "MA",
    "wof:name": "Piccolo Mondo Child Care",
    "wof:placetype": "venue"
  },
  "geometry": {"coordinates":[-71.72846,42.519221],"type":"Point"}
}
