{
  "type": "Feature",
  "properties": {
    "addr:full":"50 Congress St Ste 925 Boston MA 02109",
    "addr:housenumber":"50",
    "addr:postcode":"02109",
    "addr:street":"Congress St Ste 925",
    "iso:country":"US",
    "sg:address":"50 Congress St Ste 925",
    "sg:city":"Boston",
    "sg:classifiers":[
        {
            "category":"Professional",
            "subcategory":"Lawyer & Legal Services",
            "type":"Services"
        }
    ],
    "sg:phone":"+1 617 227 3400",
    "sg:postcode":"02109",
    "sg:province":"MA",
    "wof:name":"Elfman Marc A",
    "wof:placetype":"venue"
},
  "geometry": {"coordinates":[-71.056504,42.357967],"type":"Point"}
}