{
  "type": "Feature",
  "properties": {
    "addr:full": "23 Blakeville Street Dorchester MA 02121",
    "addr:housenumber": "23",
    "addr:postcode": "02121",
    "addr:street": "Blakeville Street",
    "iso:country": "US",
    "sg:address": "23 Blakeville Street",
    "sg:city": "Dorchester",
    "sg:classifiers": [
      {
        "category": "Social Services",
        "subcategory": "Child Care",
        "type": "Services"
      },
      {
        "category": "Sports \u0026 Exercise",
        "subcategory": "Gym",
        "type": "Entertainment"
      }
    ],
    "sg:phone": "+1 617 288 5741",
    "sg:postcode": "02121",
    "sg:province": "MA",
    "sg:tags": [
      "trainer",
      "day"
    ],
    "wof:name": "Bev's Day Care",
    "wof:placetype": "venue"
  },
  "geometry": {"coordinates":[-71.071079,42.304742],"type":"Point"}
}
