{
  "type": "Feature",
  "properties": {
    "addr:full":"54 Devonshire Dr Cheshire MA 01225",
    "addr:housenumber":"54",
    "addr:postcode":"01225",
    "addr:street":"Devonshire Dr",
    "iso:country":"US",
    "sg:address":"54 Devonshire Dr",
    "sg:city":"Cheshire",
    "sg:classifiers":[
        {
            "category":"Building & Trades",
            "subcategory":"Cleaning & Sanitation",
            "type":"Services"
        }
    ],
    "sg:phone":"+1   ",
    "sg:postcode":"01225",
    "sg:province":"MA",
    "sg:tags":[
        "maintenance"
    ],
    "wof:name":"S & K Cleaning",
    "wof:placetype":"venue"
},
  "geometry": {"coordinates":[-73.183104,42.533073],"type":"Point"}
}