{
  "type": "Feature",
  "properties": {
    "addr:full": "611 High St Dedham MA 02026",
    "addr:housenumber": "611",
    "addr:postcode": "02026",
    "addr:street": "High St",
    "iso:country": "US",
    "sg:address": "611 High St",
    "sg:city": "Dedham",
    "sg:classifiers": [
      {
        "category": "Government",
        "subcategory": "Post Office",
        "type": "Public Place"
      }
    ],
    "sg:phone": "+1 781 000 1111",
    "sg:postcode": "02026",
    "sg:province": "MA",
    "wof:name": "US Post Office",
    "wof:placetype": "venue"
  },
  "geometry": {"coordinates":[-71.174324,42.248536],"type":"Point"}
}
