{
  "type": "Feature",
  "properties": {
    "iso:country":"US",
    "sg:address":"50 Main St",
    "sg:city":"Ashland",
    "sg:classifiers":[
        {
            "category":"Professional",
            "subcategory":"Management & Consulting",
            "type":"Services"
        },
        {
            "category":"Professional",
            "subcategory":"Advertising",
            "type":"Services"
        }
    ],
    "sg:phone":"+1 508 879 3009",
    "sg:postcode":"01721",
    "sg:province":"MA",
    "sg:tags":[
        "marketing",
        "program",
        "consultant"
    ],
    "sg:website":"http://www.goric.com",
    "wof:name":"The Bauman Group Inc",
    "wof:placetype":"venue"
},
  "geometry": {"coordinates":[-71.46659099999999,42.26207],"type":"Point"}
}