{
  "type": "Feature",
  "properties": {
    "addr:full": "50 Main St Ashland MA 01721",
    "addr:housenumber": "50",
    "addr:postcode": "01721",
    "addr:street": "Main St",
    "iso:country": "US",
    "sg:address": "50 Main St",
    "sg:city": "Ashland",
    "sg:classifiers": [
      {
        "category": "Professional",
        "subcategory": "Management \u0026 Consulting",
        "type": "Services"
      },
      {
        "category": "Professional",
        "subcategory": "Advertising",
        "type": "Services"
      }
    ],
    "sg:phone": "+1 508 879 3009",
    "sg:postcode": "01721",
    "sg:province": "MA",
    "sg:tags": [
      "marketing",
      "program",
      "consultant"
    ],
    "sg:website": "http://www.goric.com",
    "wof:name": "The Bauman Group Inc",
    "wof:placetype": "venue"
  },
  "geometry": {"coordinates":[-71.466591,42.26207],"type":"Point"}
}
