{
  "type": "Feature",
  "properties": {
    "iso:country":"US",
    "sg:address":"62 Marion Rd",
    "sg:city":"Mattapoisett",
    "sg:classifiers":[
        {
            "category":"Personal",
            "subcategory":"Beauty Salon",
            "type":"Services"
        }
    ],
    "sg:phone":"+1 508 758 9400",
    "sg:postcode":"02739",
    "sg:province":"MA",
    "wof:name":"Styles With Grace",
    "wof:placetype":"venue"
},
  "geometry": {"coordinates":[-70.785646,41.664263],"type":"Point"}
}