{
  "type": "Feature",
  "properties": {
    "addr:full": "1628 Main St Springfield MA 01103",
    "addr:housenumber": "1628",
    "addr:postcode": "01103",
    "addr:street": "Main St",
    "iso:country": "US",
    "sg:address": "1628 Main St",
    "sg:city": "Springfield",
    "sg:classifiers": [
      {
        "category": "Organizations",
        "subcategory": "Community Association",
        "type": "Services"
      }
    ],
    "sg:phone": "+1 413 272 2221",
    "sg:postcode": "01103",
    "sg:province": "MA",
    "sg:tags": [
      "chamber",
      "commerce"
    ],
    "wof:name": "Massachusetts Latino Chamber Of Commerce",
    "wof:placetype": "venue"
  },
  "geometry": {"coordinates":[-72.593714,42.104141],"type":"Point"}
}
