{
  "type": "Feature",
  "properties": {
    "iso:country":"US",
    "sg:address":"105 Bridge St",
    "sg:city":"Salem",
    "sg:classifiers":[
        {
            "category":"Building & Trades",
            "subcategory":"Construction",
            "type":"Services"
        }
    ],
    "sg:phone":"+1 978 745 3370",
    "sg:postcode":"01970",
    "sg:province":"MA",
    "sg:tags":[
        "resurfacing",
        "laying",
        "refinishing",
        "floor"
    ],
    "wof:name":"Flooring Discount",
    "wof:placetype":"venue"
},
  "geometry": {"coordinates":[-70.88974,42.52936],"type":"Point"}
}