{
  "type": "Feature",
  "properties": {
    "iso:country":"US",
    "sg:address":"12 Enterprise Rd",
    "sg:city":"Hyannis",
    "sg:classifiers":[
        {
            "category":"Building & Trades",
            "subcategory":"Plumbing",
            "type":"Services"
        }
    ],
    "sg:phone":"+1 508 775 5252",
    "sg:postcode":"02601",
    "sg:province":"MA",
    "sg:tags":[
        "conditioning",
        "air",
        "system",
        "contractor"
    ],
    "wof:name":"Preferred Heating & Cooling",
    "wof:placetype":"venue"
},
  "geometry": {"coordinates":[-70.302571,41.666731],"type":"Point"}
}