{
  "type": "Feature",
  "properties": {
    "iso:country":"US",
    "sg:address":"10 Carolina Way",
    "sg:city":"Boxford",
    "sg:classifiers":[
        {
            "category":"Real Estate",
            "subcategory":"Real Estate Services",
            "type":"Services"
        }
    ],
    "sg:phone":"+1 978 887 6568",
    "sg:postcode":"01921",
    "sg:province":"MA",
    "sg:tags":[
        "management"
    ],
    "wof:name":"North Shores Development",
    "wof:placetype":"venue"
},
  "geometry": {"coordinates":[-70.99034899999999,42.682571],"type":"Point"}
}