{
  "type": "Feature",
  "properties": {
    "addr:full": "94 Liberty St Quincy MA 02169",
    "addr:housenumber": "94",
    "addr:postcode": "02169",
    "addr:street": "Liberty St",
    "iso:country": "US",
    "sg:address": "94 Liberty St",
    "sg:city": "Quincy",
    "sg:classifiers": [
      {
        "category": "Wholesale",
        "subcategory": "Construction Materials",
        "type": "Manufacturing \u0026 Wholesale Goods"
      },
      {
        "category": "Home \u0026 Garden",
        "subcategory": "Building Materials",
        "type": "Retail Goods"
      },
      {
        "category": "Wholesale",
        "subcategory": "Home Furnishings",
        "type": "Manufacturing \u0026 Wholesale Goods"
      }
    ],
    "sg:phone": "+1 617 471 7003",
    "sg:postcode": "02169",
    "sg:province": "MA",
    "sg:tags": [
      "supply",
      "fixture",
      "heating",
      "system",
      "systems-wholesale",
      "equipment",
      "part",
      "plumbing",
      "fixtures",
      "supplies-wholesale",
      "manufacturer"
    ],
    "wof:name": "P V Sullivan Supply Co, Inc.",
    "wof:placetype": "venue"
  },
  "geometry": {"coordinates":[-71.008102,42.238689],"type":"Point"}
}
