{
  "type": "Feature",
  "properties": {
    "iso:country":"US",
    "sg:address":"94 Liberty St",
    "sg:city":"Quincy",
    "sg:classifiers":[
        {
            "category":"Wholesale",
            "subcategory":"Construction Materials",
            "type":"Manufacturing & Wholesale Goods"
        },
        {
            "category":"Home & Garden",
            "subcategory":"Building Materials",
            "type":"Retail Goods"
        },
        {
            "category":"Wholesale",
            "subcategory":"Home Furnishings",
            "type":"Manufacturing & Wholesale Goods"
        }
    ],
    "sg:phone":"+1 617 471 7003",
    "sg:postcode":"02169",
    "sg:province":"MA",
    "sg:tags":[
        "supply",
        "fixture",
        "heating",
        "system",
        "systems-wholesale",
        "equipment",
        "part",
        "plumbing",
        "fixtures",
        "supplies-wholesale",
        "manufacturer"
    ],
    "wof:name":"P V Sullivan Supply Co, Inc.",
    "wof:placetype":"venue"
},
  "geometry": {"coordinates":[-71.00810199999999,42.238689],"type":"Point"}
}