{
  "type": "Feature",
  "properties": {
    "addr:full": "25 Warren St Brighton MA 02135",
    "addr:housenumber": "25",
    "addr:postcode": "02135",
    "addr:street": "Warren St",
    "iso:country": "US",
    "sg:address": "25 Warren St",
    "sg:city": "Brighton",
    "sg:classifiers": [
      {
        "category": "Organizations",
        "subcategory": "Non-profit Organization",
        "type": "Services"
      }
    ],
    "sg:phone": "+1 617 254 8414",
    "sg:postcode": "02135",
    "sg:province": "MA",
    "wof:name": "Boston Private Industry Councl",
    "wof:placetype": "venue"
  },
  "geometry": {"coordinates":[-71.144379,42.349676],"type":"Point"}
}
