{
  "type": "Feature",
  "properties": {
    "iso:country":"US",
    "sg:address":"51 Washington St",
    "sg:city":"Wellesley",
    "sg:classifiers":[
        {
            "category":"Retail",
            "subcategory":"Laundry & Dry Cleaning",
            "type":"Services"
        }
    ],
    "sg:phone":"+1 781 235 0537",
    "sg:postcode":"02481",
    "sg:province":"MA",
    "sg:tags":[
        "cleaners"
    ],
    "wof:name":"Mayfair Cleaners Of Wellesley",
    "wof:placetype":"venue"
},
  "geometry": {"coordinates":[-71.26267,42.32325],"type":"Point"}
}