{
  "type": "Feature",
  "properties": {
    "addr:full": "51 Washington St Wellesley MA 02481",
    "addr:housenumber": "51",
    "addr:postcode": "02481",
    "addr:street": "Washington St",
    "iso:country": "US",
    "sg:address": "51 Washington St",
    "sg:city": "Wellesley",
    "sg:classifiers": [
      {
        "category": "Retail",
        "subcategory": "Laundry \u0026 Dry Cleaning",
        "type": "Services"
      }
    ],
    "sg:phone": "+1 781 235 0537",
    "sg:postcode": "02481",
    "sg:province": "MA",
    "sg:tags": [
      "cleaners"
    ],
    "wof:name": "Mayfair Cleaners Of Wellesley",
    "wof:placetype": "venue"
  },
  "geometry": {"coordinates":[-71.26267,42.32325],"type":"Point"}
}
