{
  "type": "Feature",
  "properties": {
    "addr:full": "8 Sapphire Rd Saugus MA 01906",
    "addr:housenumber": "8",
    "addr:postcode": "01906",
    "addr:street": "Sapphire Rd",
    "iso:country": "US",
    "sg:address": "8 Sapphire Rd",
    "sg:city": "Saugus",
    "sg:classifiers": [
      {
        "category": "Restaurant",
        "type": "Food \u0026 Drink"
      }
    ],
    "sg:phone": "+1 781 231 0247",
    "sg:postcode": "01906",
    "sg:province": "MA",
    "sg:tags": [
      "seafood"
    ],
    "wof:name": "Russo Jos",
    "wof:placetype": "venue"
  },
  "geometry": {"coordinates":[-71.003799,42.446701],"type":"Point"}
}
