{
  "type": "Feature",
  "properties": {
    "addr:full": "1612 Somerset Ave Dighton MA 02715",
    "addr:housenumber": "1612",
    "addr:postcode": "02715",
    "addr:street": "Somerset Ave",
    "iso:country": "US",
    "sg:address": "1612 Somerset Ave",
    "sg:city": "Dighton",
    "sg:classifiers": [
      {
        "category": "Utilities",
        "subcategory": "Natural Gas",
        "type": "Services"
      }
    ],
    "sg:phone": "+1 508 669 5471",
    "sg:postcode": "02715",
    "sg:province": "MA",
    "sg:tags": [
      "transmission"
    ],
    "wof:name": "Dukes Energy",
    "wof:placetype": "venue"
  },
  "geometry": {"coordinates":[-71.12109,41.825472],"type":"Point"}
}
