{
  "type": "Feature",
  "properties": {
    "addr:full": "5 Eastern Ave Beverly MA 01915",
    "addr:housenumber": "5",
    "addr:postcode": "01915",
    "addr:street": "Eastern Ave",
    "iso:country": "US",
    "sg:address": "5 Eastern Ave",
    "sg:city": "Beverly",
    "sg:classifiers": [
      {
        "category": "Real Estate",
        "subcategory": "Real Estate Agent",
        "type": "Services"
      }
    ],
    "sg:phone": "+1   ",
    "sg:postcode": "01915",
    "sg:province": "MA",
    "wof:name": "Parisella Realty",
    "wof:placetype": "venue"
  },
  "geometry": {"coordinates":[-70.896236,42.551604],"type":"Point"}
}
