{
  "type": "Feature",
  "properties": {
    "iso:country":"US",
    "sg:address":"100 Cambridgeside Place Ofc",
    "sg:city":"Cambridge",
    "sg:classifiers":[
        {
            "category":"Shopping",
            "subcategory":"Department Store",
            "type":"Retail Goods"
        }
    ],
    "sg:phone":"+1 617 225 9047",
    "sg:postcode":"02141",
    "sg:province":"MA",
    "wof:name":"Guess Accessories",
    "wof:placetype":"venue"
},
  "geometry": {"coordinates":[-71.076009,42.367055],"type":"Point"}
}