{
  "type": "Feature",
  "properties": {
    "addr:full": "234 Chestnut St Springfield MA 01103",
    "addr:housenumber": "234",
    "addr:postcode": "01103",
    "addr:street": "Chestnut St",
    "iso:country": "US",
    "sg:address": "234 Chestnut St",
    "sg:city": "Springfield",
    "sg:classifiers": [
      {
        "category": "Bars \u0026 Pubs",
        "type": "Food \u0026 Drink"
      },
      {
        "category": "Restaurant",
        "type": "Food \u0026 Drink"
      }
    ],
    "sg:phone": "+1 413 205 1483",
    "sg:postcode": "01103",
    "sg:province": "MA",
    "sg:tags": [
      "grill",
      "brew"
    ],
    "wof:name": "Pure",
    "wof:placetype": "venue"
  },
  "geometry": {"coordinates":[-72.59171,42.107857],"type":"Point"}
}
