{
  "type": "Feature",
  "properties": {
    "iso:country":"US",
    "sg:address":"234 Chestnut St",
    "sg:city":"Springfield",
    "sg:classifiers":[
        {
            "category":"Bars & Pubs",
            "type":"Food & Drink"
        },
        {
            "category":"Restaurant",
            "type":"Food & Drink"
        }
    ],
    "sg:phone":"+1 413 205 1483",
    "sg:postcode":"01103",
    "sg:province":"MA",
    "sg:tags":[
        "grill",
        "brew"
    ],
    "wof:name":"Pure",
    "wof:placetype":"venue"
},
  "geometry": {"coordinates":[-72.59171000000001,42.107857],"type":"Point"}
}