{
  "type": "Feature",
  "properties": {
    "addr:full": "653 Humphrey St Swampscott MA 01907",
    "addr:housenumber": "653",
    "addr:postcode": "01907",
    "addr:street": "Humphrey St",
    "iso:country": "US",
    "ovtr:label": "Cindy's Pizza and Subs, 653 Humphrey St Swampscott MA US",
    "ovtr:similarity": 2.688673973083496,
    "sg:address": "653 Humphrey St",
    "sg:city": "Swampscott",
    "sg:classifiers": [
      {
        "category": "Restaurant",
        "type": "Food \u0026 Drink"
      }
    ],
    "sg:phone": "+1 781 599 0358",
    "sg:postcode": "01907",
    "sg:province": "MA",
    "sg:tags": [
      "pizza"
    ],
    "sg:website": "http://www.cindyspizza.com",
    "wof:name": "Cindy's Pizza \u0026 Subs",
    "wof:placetype": "venue"
  },
  "geometry": {"coordinates":[-70.898883,42.468685],"type":"Point"}
}
