{
  "type": "Feature",
  "properties": {
    "addr:full":"140 Lee Burbank Hwy Revere MA 02151",
    "addr:housenumber":"140",
    "addr:postcode":"02151",
    "addr:street":"Lee Burbank Hwy",
    "iso:country":"US",
    "sg:address":"140 Lee Burbank Hwy",
    "sg:city":"Revere",
    "sg:phone":"+1 781 284 4500",
    "sg:postcode":"02151",
    "sg:province":"MA",
    "sg:tags":[
        "product",
        "petroleum"
    ],
    "wof:name":"Sun Co",
    "wof:placetype":"venue"
},
  "geometry": {"coordinates":[-71.005447,42.401096],"type":"Point"}
}