{
  "type": "Feature",
  "properties": {
    "addr:full": "10 Ridgewood Dr East Sandwich MA 02537",
    "addr:housenumber": "10",
    "addr:postcode": "02537",
    "addr:street": "Ridgewood Dr",
    "iso:country": "US",
    "sg:address": "10 Ridgewood Dr",
    "sg:city": "East Sandwich",
    "sg:classifiers": [
      {
        "category": "Building \u0026 Trades",
        "subcategory": "Landscaping Services",
        "type": "Services"
      }
    ],
    "sg:phone": "+1 508 833 2766",
    "sg:postcode": "02537",
    "sg:province": "MA",
    "sg:tags": [
      "designer",
      "landscape"
    ],
    "wof:name": "Burbank Group",
    "wof:placetype": "venue"
  },
  "geometry": {"coordinates":[-70.456794,41.714889],"type":"Point"}
}
