{
  "type": "Feature",
  "properties": {
    "addr:full":"459 Main St Amesbury MA 01913",
    "addr:housenumber":"459",
    "addr:postcode":"01913",
    "addr:street":"Main St",
    "iso:country":"US",
    "sg:address":"459 Main St",
    "sg:city":"Amesbury",
    "sg:classifiers":[
        {
            "category":"Manufacturing",
            "subcategory":"Watercraft",
            "type":"Manufacturing & Wholesale Goods"
        }
    ],
    "sg:phone":"+1 978 388 0162",
    "sg:postcode":"01913",
    "sg:province":"MA",
    "sg:tags":[
        "boat"
    ],
    "wof:name":"Lowell's Boat Shop Inc",
    "wof:placetype":"venue"
},
  "geometry": {"coordinates":[-70.912837,42.841458],"type":"Point"}
}