{
  "type": "Feature",
  "properties": {
    "addr:full": "929 Pine Hill Rd Westport MA 02790",
    "addr:housenumber": "929",
    "addr:postcode": "02790",
    "addr:street": "Pine Hill Rd",
    "iso:country": "US",
    "sg:address": "929 Pine Hill Rd",
    "sg:city": "Westport",
    "sg:classifiers": [
      {
        "category": "Retail",
        "subcategory": "Auto Repair",
        "type": "Services"
      }
    ],
    "sg:phone": "+1 508 636 8801",
    "sg:postcode": "02790",
    "sg:province": "MA",
    "sg:tags": [
      "repairing",
      "automobile"
    ],
    "wof:name": "Pine Hill Auto Svc",
    "wof:placetype": "venue"
  },
  "geometry": {"coordinates":[-71.058528,41.574182],"type":"Point"}
}
