{
  "type": "Feature",
  "properties": {
    "addr:full":"91 E Falmouth Hwy East Falmouth MA 02536",
    "addr:housenumber":"91",
    "addr:postcode":"02536",
    "addr:street":"E Falmouth Hwy",
    "iso:country":"US",
    "sg:address":"91 E Falmouth Hwy",
    "sg:city":"East Falmouth",
    "sg:classifiers":[
        {
            "category":"Professional",
            "subcategory":"Accounting & Tax Preparation",
            "type":"Services"
        }
    ],
    "sg:phone":"+1 508 540 3449",
    "sg:postcode":"02536",
    "sg:province":"MA",
    "sg:tags":[
        "bookkeeping",
        "return"
    ],
    "wof:name":"By The Book",
    "wof:placetype":"venue"
},
  "geometry": {"coordinates":[-70.569031,41.578663],"type":"Point"}
}