{
  "type": "Feature",
  "properties": {
    "iso:country":"US",
    "sg:address":"13 Highland Cir",
    "sg:city":"Needham Heights",
    "sg:classifiers":[
        {
            "category":"Professional",
            "subcategory":"Management & Consulting",
            "type":"Services"
        }
    ],
    "sg:phone":"+1 781 444 0311",
    "sg:postcode":"02494",
    "sg:province":"MA",
    "sg:tags":[
        "public",
        "relations"
    ],
    "wof:name":"Sunrise Public Relations",
    "wof:placetype":"venue"
},
  "geometry": {"coordinates":[-71.21786400000001,42.306302],"type":"Point"}
}