{
  "type": "Feature",
  "properties": {
    "addr:full": "30 Sylvan St Danvers MA 01923",
    "addr:housenumber": "30",
    "addr:postcode": "01923",
    "addr:street": "Sylvan St",
    "iso:country": "US",
    "sg:address": "30 Sylvan St",
    "sg:city": "Danvers",
    "sg:classifiers": [
      {
        "category": "Real Estate",
        "subcategory": "Developer",
        "type": "Services"
      }
    ],
    "sg:phone": "+1 978 774 1024",
    "sg:postcode": "01923",
    "sg:province": "MA",
    "sg:tags": [
      "cemetery"
    ],
    "wof:name": "Walnut Grove Cemetery Corp",
    "wof:placetype": "venue"
  },
  "geometry": {"coordinates":[-70.940782,42.560754],"type":"Point"}
}
