{
  "type": "Feature",
  "properties": {
    "addr:full":"221 Olde Derby Rd Norwood MA 02062",
    "addr:housenumber":"221",
    "addr:postcode":"02062",
    "addr:street":"Olde Derby Rd",
    "iso:country":"US",
    "sg:address":"221 Olde Derby Rd",
    "sg:city":"Norwood",
    "sg:classifiers":[
        {
            "category":"Professional",
            "subcategory":"Business Services",
            "type":"Services"
        }
    ],
    "sg:phone":"+1   ",
    "sg:postcode":"02062",
    "sg:province":"MA",
    "wof:name":"PCF Associates",
    "wof:placetype":"venue"
},
  "geometry": {"coordinates":[-71.223783,42.177935],"type":"Point"}
}