{
  "type": "Feature",
  "properties": {
    "addr:full":"43 Custer St Rockland MA 02370",
    "addr:housenumber":"43",
    "addr:postcode":"02370",
    "addr:street":"Custer St",
    "iso:country":"US",
    "sg:address":"43 Custer St",
    "sg:city":"Rockland",
    "sg:classifiers":[
        {
            "category":"Shopping",
            "subcategory":"Hobbies, Toys, & Games",
            "type":"Retail Goods"
        },
        {
            "category":"Shopping",
            "subcategory":"Crafts & Fabrics",
            "type":"Retail Goods"
        }
    ],
    "sg:phone":"+1 781 878 1444",
    "sg:postcode":"02370",
    "sg:province":"MA",
    "sg:tags":[
        "shop",
        "hobby",
        "model",
        "supply"
    ],
    "wof:name":"Wood Craft Frames",
    "wof:placetype":"venue"
},
  "geometry": {"coordinates":[-70.908585,42.128366],"type":"Point"}
}