{
  "type": "Feature",
  "properties": {
    "iso:country":"US",
    "sg:address":"516 Broadway",
    "sg:city":"Everett",
    "sg:classifiers":[
        {
            "category":"Personal",
            "subcategory":"Beauty Salon",
            "type":"Services"
        }
    ],
    "sg:phone":"+1 617 387 7350",
    "sg:postcode":"02149",
    "sg:province":"MA",
    "sg:tags":[
        "care",
        "treatment",
        "skin"
    ],
    "sg:website":"www.bellafacciacare.com/",
    "wof:name":"Bella Faccia",
    "wof:placetype":"venue"
},
  "geometry": {"coordinates":[-71.053675,42.4093],"type":"Point"}
}