{
  "type": "Feature",
  "properties": {
    "iso:country":"US",
    "sg:address":"820 N Main St",
    "sg:city":"Brockton",
    "sg:classifiers":[
        {
            "category":"Banks & Credit Unions",
            "subcategory":"Bank",
            "type":"Services"
        }
    ],
    "sg:phone":"+1 508 895 1430",
    "sg:postcode":"02301",
    "sg:province":"MA",
    "wof:name":"Harbor One Credit Union",
    "wof:placetype":"venue"
},
  "geometry": {"coordinates":[-71.025307,42.104882],"type":"Point"}
}