{
  "type": "Feature",
  "properties": {
    "iso:country":"US",
    "sg:address":"30 Sheffield Pl",
    "sg:city":"Mashpee",
    "sg:classifiers":[
        {
            "category":"Personal",
            "type":"Services"
        }
    ],
    "sg:phone":"+1 508 539 6699",
    "sg:postcode":"02649",
    "sg:province":"MA",
    "sg:tags":[
        "consultant",
        "wedding"
    ],
    "wof:name":"Signature Events",
    "wof:placetype":"venue"
},
  "geometry": {"coordinates":[-70.47147699999999,41.652315],"type":"Point"}
}