{
  "type": "Feature",
  "properties": {
    "addr:full":"24 Kings Row Ln Framingham MA 01701",
    "addr:housenumber":"24",
    "addr:postcode":"01701",
    "addr:street":"Kings Row Ln",
    "iso:country":"US",
    "sg:address":"24 Kings Row Ln",
    "sg:city":"Framingham",
    "sg:classifiers":[
        {
            "category":"Local Transit",
            "type":"Transportation"
        }
    ],
    "sg:phone":"+1 508 879 3808",
    "sg:postcode":"01701",
    "sg:province":"MA",
    "sg:tags":[
        "bus",
        "line"
    ],
    "wof:name":"Intercultural Bus Ctr Inc",
    "wof:placetype":"venue"
},
  "geometry": {"coordinates":[-71.46334899999999,42.302771],"type":"Point"}
}