{
  "type": "Feature",
  "properties": {
    "addr:full": "1 Charlesview Rd Hopedale MA 01747",
    "addr:housenumber": "1",
    "addr:postcode": "01747",
    "addr:street": "Charlesview Rd",
    "iso:country": "US",
    "sg:address": "1 Charlesview Rd",
    "sg:city": "Hopedale",
    "sg:classifiers": [
      {
        "category": "Insurance",
        "subcategory": "Insurance Agent",
        "type": "Services"
      }
    ],
    "sg:phone": "+1 508 634 0333",
    "sg:postcode": "01747",
    "sg:province": "MA",
    "wof:name": "Colonial Supplemental Ins",
    "wof:placetype": "venue"
  },
  "geometry": {"coordinates":[-71.502879,42.10485],"type":"Point"}
}
