{
  "type": "Feature",
  "properties": {
    "addr:full": "1794 Bridge St Dracut MA 01826",
    "addr:housenumber": "1794",
    "addr:postcode": "01826",
    "addr:street": "Bridge St",
    "iso:country": "US",
    "sg:address": "1794 Bridge St",
    "sg:city": "Dracut",
    "sg:classifiers": [
      {
        "category": "Retail",
        "subcategory": "Repair Shop",
        "type": "Services"
      }
    ],
    "sg:phone": "+1 978 656 9999",
    "sg:postcode": "01826",
    "sg:province": "MA",
    "sg:tags": [
      "cleaners",
      "parts",
      "vacuum"
    ],
    "wof:name": "Dracvax Vacuum Sales \u0026 Supply",
    "wof:placetype": "venue"
  },
  "geometry": {"coordinates":[-71.30994,42.683475],"type":"Point"}
}
