{
  "type": "Feature",
  "properties": {
    "addr:full": "7 Vernon St Norwood MA 02062",
    "addr:housenumber": "7",
    "addr:postcode": "02062",
    "addr:street": "Vernon St",
    "iso:country": "US",
    "sg:address": "7 Vernon St",
    "sg:city": "Norwood",
    "sg:classifiers": [
      {
        "category": "Banks \u0026 Credit Unions",
        "subcategory": "Financial Services",
        "type": "Services"
      }
    ],
    "sg:phone": "+1 781 762 2928",
    "sg:postcode": "02062",
    "sg:province": "MA",
    "sg:tags": [
      "broker",
      "mortgage"
    ],
    "wof:name": "Financial Omega",
    "wof:placetype": "venue"
  },
  "geometry": {"coordinates":[-71.201582,42.193134],"type":"Point"}
}
