{
  "type": "Feature",
  "properties": {
    "iso:country":"US",
    "sg:address":"156 Depot St",
    "sg:city":"Westford",
    "sg:classifiers":[
        {
            "category":"Transit Center",
            "subcategory":"Freight",
            "type":"Transportation"
        },
        {
            "category":"Freight",
            "type":"Transportation"
        }
    ],
    "sg:phone":"+1 978 392 9154",
    "sg:postcode":"01886",
    "sg:province":"MA",
    "sg:tags":[
        "local",
        "trucking-motor",
        "trucking"
    ],
    "wof:name":"J & M Dispatch",
    "wof:placetype":"venue"
},
  "geometry": {"coordinates":[-71.44550099999999,42.613292],"type":"Point"}
}