{
  "type": "Feature",
  "properties": {
    "addr:full":"55 Cottage St Hudson MA 01749",
    "addr:housenumber":"55",
    "addr:postcode":"01749",
    "addr:street":"Cottage St",
    "iso:country":"US",
    "sg:address":"55 Cottage St",
    "sg:city":"Hudson",
    "sg:classifiers":[
        {
            "category":"Shopping",
            "subcategory":"Hobbies, Toys, & Games",
            "type":"Retail Goods"
        },
        {
            "category":"Shopping",
            "subcategory":"Crafts & Fabrics",
            "type":"Retail Goods"
        }
    ],
    "sg:phone":"+1 978 562 5633",
    "sg:postcode":"01749",
    "sg:province":"MA",
    "sg:tags":[
        "shop",
        "hobby",
        "model",
        "supplies-wholesale",
        "manufacturer"
    ],
    "wof:name":"Warped Wits",
    "wof:placetype":"venue"
},
  "geometry": {"coordinates":[-71.574534,42.396535],"type":"Point"}
}