{
  "type": "Feature",
  "properties": {
    "addr:full": "36 Gloucester St Boston MA 02115",
    "addr:housenumber": "36",
    "addr:postcode": "02115",
    "addr:street": "Gloucester St",
    "iso:country": "US",
    "sg:address": "36 Gloucester St",
    "sg:city": "Boston",
    "sg:classifiers": [
      {
        "category": "Real Estate",
        "subcategory": "Real Estate Agent",
        "type": "Services"
      }
    ],
    "sg:phone": "+1 617 587 0100",
    "sg:postcode": "02115",
    "sg:province": "MA",
    "wof:name": "Charlesgate Realty Group",
    "wof:placetype": "venue"
  },
  "geometry": {"coordinates":[-71.084139,42.349174],"type":"Point"}
}
