{
  "type": "Feature",
  "properties": {
    "addr:full": "575 Pleasant St Framingham MA 01701",
    "addr:housenumber": "575",
    "addr:postcode": "01701",
    "addr:street": "Pleasant St",
    "iso:country": "US",
    "ovtr:label": "Brophy Elementary School, 575 Pleasant St Framingham MA US",
    "ovtr:similarity": 2.368375062942505,
    "sg:address": "575 Pleasant St",
    "sg:city": "Framingham",
    "sg:classifiers": [
      {
        "category": "Education",
        "subcategory": "School",
        "type": "Public Place"
      }
    ],
    "sg:phone": "+1 508 626 9159",
    "sg:postcode": "01701",
    "sg:province": "MA",
    "wof:name": "Brophy Elementary School",
    "wof:placetype": "venue"
  },
  "geometry": {"coordinates":[-71.46128,42.304102],"type":"Point"}
}
