{
  "type": "Feature",
  "properties": {
    "iso:country":"US",
    "sg:address":"155 Water St",
    "sg:city":"North Andover",
    "sg:classifiers":[
        {
            "category":"Shopping",
            "type":"Retail Goods"
        }
    ],
    "sg:phone":"+1   ",
    "sg:postcode":"01845",
    "sg:province":"MA",
    "sg:tags":[
        "merchandise"
    ],
    "wof:name":"J J Trophy",
    "wof:placetype":"venue"
},
  "geometry": {"coordinates":[-71.12278499999999,42.699761],"type":"Point"}
}