{
  "type": "Feature",
  "properties": {
    "addr:full": "1085 Main St Holden MA 01520",
    "addr:housenumber": "1085",
    "addr:postcode": "01520",
    "addr:street": "Main St",
    "iso:country": "US",
    "sg:address": "1085 Main St",
    "sg:city": "Holden",
    "sg:classifiers": [
      {
        "category": "Personal",
        "subcategory": "Beauty Salon",
        "type": "Services"
      }
    ],
    "sg:phone": "+1 508 829 3992",
    "sg:postcode": "01520",
    "sg:province": "MA",
    "wof:name": "Shear Creations",
    "wof:placetype": "venue"
  },
  "geometry": {"coordinates":[-71.85898,42.349407],"type":"Point"}
}
