{
  "type": "Feature",
  "properties": {
    "addr:full":"599 Boston Rd Billerica MA 01821",
    "addr:housenumber":"599",
    "addr:postcode":"01821",
    "addr:street":"Boston Rd",
    "iso:country":"US",
    "sg:address":"599 Boston Rd",
    "sg:city":"Billerica",
    "sg:classifiers":[
        {
            "category":"Ice Cream",
            "type":"Food & Drink"
        }
    ],
    "sg:phone":"+1 978 667 9661",
    "sg:postcode":"01821",
    "sg:province":"MA",
    "sg:tags":[
        "frozen",
        "yogurt"
    ],
    "sg:website":"www.orchardhillicecream.com/",
    "wof:name":"Orchard Hill Ice Cream",
    "wof:placetype":"venue"
},
  "geometry": {"coordinates":[-71.25250200000001,42.542999],"type":"Point"}
}