{
  "type": "Feature",
  "properties": {
    "addr:full": "599 Boston Rd Billerica MA 01821",
    "addr:housenumber": "599",
    "addr:postcode": "01821",
    "addr:street": "Boston Rd",
    "iso:country": "US",
    "ovtr:label": "Orchard Hill Ice Cream, 599 Boston Rd Billerica MA US",
    "ovtr:similarity": 2.0731539726257324,
    "sg:address": "599 Boston Rd",
    "sg:city": "Billerica",
    "sg:classifiers": [
      {
        "category": "Ice Cream",
        "type": "Food \u0026 Drink"
      }
    ],
    "sg:phone": "+1 978 667 9661",
    "sg:postcode": "01821",
    "sg:province": "MA",
    "sg:tags": [
      "frozen",
      "yogurt"
    ],
    "sg:website": "www.orchardhillicecream.com/",
    "wof:name": "Orchard Hill Ice Cream",
    "wof:placetype": "venue"
  },
  "geometry": {"coordinates":[-71.252502,42.542999],"type":"Point"}
}
