{
  "type": "Feature",
  "properties": {
    "iso:country":"US",
    "sg:address":"795 Turnpike St",
    "sg:city":"North Andover",
    "sg:classifiers":[
        {
            "category":"Health Services",
            "subcategory":"Doctor",
            "type":"Services"
        }
    ],
    "sg:phone":"+1 978 685 8313",
    "sg:postcode":"01845",
    "sg:province":"MA",
    "sg:tags":[
        "dentist"
    ],
    "wof:name":"Willows Dental Group",
    "wof:placetype":"venue"
},
  "geometry": {"coordinates":[-71.11002499999999,42.661615],"type":"Point"}
}