{
  "type": "Feature",
  "properties": {
    "addr:full": "795 Turnpike St North Andover MA 01845",
    "addr:housenumber": "795",
    "addr:postcode": "01845",
    "addr:street": "Turnpike St",
    "iso:country": "US",
    "sg:address": "795 Turnpike St",
    "sg:city": "North Andover",
    "sg:classifiers": [
      {
        "category": "Health Services",
        "subcategory": "Doctor",
        "type": "Services"
      }
    ],
    "sg:phone": "+1 978 685 8313",
    "sg:postcode": "01845",
    "sg:province": "MA",
    "sg:tags": [
      "dentist"
    ],
    "wof:name": "Willows Dental Group",
    "wof:placetype": "venue"
  },
  "geometry": {"coordinates":[-71.110025,42.661615],"type":"Point"}
}
