{
  "type": "Feature",
  "properties": {
    "iso:country":"US",
    "sg:address":"527 Gorwin Dr",
    "sg:city":"Hanson",
    "sg:classifiers":[
        {
            "category":"Manufacturing",
            "subcategory":"Buildings",
            "type":"Manufacturing & Wholesale Goods"
        },
        {
            "category":"Building & Trades",
            "subcategory":"Construction",
            "type":"Services"
        }
    ],
    "sg:phone":"+1 781 293 6452",
    "sg:postcode":"02341",
    "sg:province":"MA",
    "sg:tags":[
        "home",
        "builder",
        "industrial",
        "contractors-commercial",
        "contractor"
    ],
    "wof:name":"The Decoste Group Inc",
    "wof:placetype":"venue"
},
  "geometry": {"coordinates":[-70.85289,42.075848],"type":"Point"}
}