{
  "type": "Feature",
  "properties": {
    "iso:country":"US",
    "sg:address":"3 Pemberton Sq",
    "sg:city":"Boston",
    "sg:classifiers":[
        {
            "category":"Government",
            "subcategory":"Office",
            "type":"Public Place"
        }
    ],
    "sg:phone":"+1 617 788 8130",
    "sg:postcode":"02108",
    "sg:province":"MA",
    "wof:name":"Bail Administator's",
    "wof:placetype":"venue"
},
  "geometry": {"coordinates":[-71.060343,42.35875],"type":"Point"}
}