{
  "type": "Feature",
  "properties": {
    "iso:country":"US",
    "sg:address":"342-346 Commercial St, Unit C-1",
    "sg:city":"Boston",
    "sg:classifiers":[
        {
            "category":"Banks & Credit Unions",
            "subcategory":"Investment Brokerage",
            "type":"Services"
        },
        {
            "category":"Banks & Credit Unions",
            "subcategory":"Financial Services",
            "type":"Services"
        }
    ],
    "sg:phone":"+1 781 431 2466",
    "sg:postcode":"02109",
    "sg:province":"MA",
    "sg:tags":[
        "investing",
        "advising"
    ],
    "sg:website":"ameripriseadvisors.com",
    "wof:name":"Ameriprise Financial Advisors",
    "wof:placetype":"venue"
},
  "geometry": {"coordinates":[-71.051315,42.366115],"type":"Point"}
}