{
  "type": "Feature",
  "properties": {
    "addr:full":"50 Beharrell St Concord MA 01742",
    "addr:housenumber":"50",
    "addr:postcode":"01742",
    "addr:street":"Beharrell St",
    "iso:country":"US",
    "sg:address":"50 Beharrell St",
    "sg:city":"Concord",
    "sg:classifiers":[
        {
            "category":"Professional",
            "subcategory":"Research",
            "type":"Services"
        }
    ],
    "sg:phone":"+1 978 369 9440",
    "sg:postcode":"01742",
    "sg:province":"MA",
    "sg:tags":[
        "environmental",
        "ecological"
    ],
    "sg:website":"www.ecologicalengineering.com",
    "wof:name":"Sustainable Strategies",
    "wof:placetype":"venue"
},
  "geometry": {"coordinates":[-71.39485999999999,42.456946],"type":"Point"}
}