{
  "type": "Feature",
  "properties": {
    "addr:full": "7 Churchill St Salem MA 01970",
    "addr:housenumber": "7",
    "addr:postcode": "01970",
    "addr:street": "Churchill St",
    "iso:country": "US",
    "sg:address": "7 Churchill St",
    "sg:city": "Salem",
    "sg:classifiers": [
      {
        "category": "Real Estate",
        "subcategory": "Real Estate Services",
        "type": "Services"
      },
      {
        "category": "Real Estate",
        "subcategory": "Real Estate Agent",
        "type": "Services"
      }
    ],
    "sg:phone": "+1 978 745 6848",
    "sg:postcode": "01970",
    "sg:province": "MA",
    "sg:tags": [
      "buyer",
      "broker"
    ],
    "wof:name": "Americal Realty Trust",
    "wof:placetype": "venue"
  },
  "geometry": {"coordinates":[-70.906644,42.524831],"type":"Point"}
}
