{
  "type": "Feature",
  "properties": {
    "addr:full": "400 Franklin St Braintree MA 02184",
    "addr:housenumber": "400",
    "addr:postcode": "02184",
    "addr:street": "Franklin St",
    "iso:country": "US",
    "sg:address": "400 Franklin St",
    "sg:city": "Braintree",
    "sg:classifiers": [
      {
        "category": "Airline",
        "type": "Transportation"
      }
    ],
    "sg:phone": "+1 781 848 6671",
    "sg:postcode": "02184",
    "sg:province": "MA",
    "sg:tags": [
      "cargo",
      "air"
    ],
    "wof:name": "Express One",
    "wof:placetype": "venue"
  },
  "geometry": {"coordinates":[-71.019107,42.211581],"type":"Point"}
}
