{
  "type": "Feature",
  "properties": {
    "iso:country":"US",
    "sg:address":"200 Trafton Rd",
    "sg:city":"Springfield",
    "sg:classifiers":[
        {
            "category":"Recreation",
            "type":"Entertainment"
        }
    ],
    "sg:phone":"+1 413 787 6440",
    "sg:postcode":"01108",
    "sg:province":"MA",
    "sg:tags":[
        "parks"
    ],
    "sg:website":"www.springfieldparks.com",
    "wof:name":"Springfield Parks & Recreation",
    "wof:placetype":"venue"
},
  "geometry": {"coordinates":[-72.558717,42.08049],"type":"Point"}
}