{
  "type": "Feature",
  "properties": {
    "iso:country":"US",
    "sg:address":"1001 Commonwealth Ave",
    "sg:city":"Boston",
    "sg:classifiers":[
        {
            "category":"Education",
            "subcategory":"Vocational School",
            "type":"Public Place"
        },
        {
            "category":"Education",
            "subcategory":"School",
            "type":"Public Place"
        }
    ],
    "sg:phone":"+1 617 779 8390",
    "sg:postcode":"02215",
    "sg:province":"MA",
    "sg:tags":[
        "high",
        "middle",
        "private",
        "business",
        "k-"
    ],
    "wof:name":"Media and Technology Charter High School",
    "wof:placetype":"venue"
},
  "geometry": {"coordinates":[-71.12039900000001,42.3517],"type":"Point"}
}