{
  "type": "Feature",
  "properties": {
    "addr:full": "1001 Commonwealth Ave Boston MA 02215",
    "addr:housenumber": "1001",
    "addr:postcode": "02215",
    "addr:street": "Commonwealth Ave",
    "iso:country": "US",
    "sg:address": "1001 Commonwealth Ave",
    "sg:city": "Boston",
    "sg:classifiers": [
      {
        "category": "Education",
        "subcategory": "Vocational School",
        "type": "Public Place"
      },
      {
        "category": "Education",
        "subcategory": "School",
        "type": "Public Place"
      }
    ],
    "sg:phone": "+1 617 779 8390",
    "sg:postcode": "02215",
    "sg:province": "MA",
    "sg:tags": [
      "high",
      "middle",
      "private",
      "business",
      "k-"
    ],
    "wof:name": "Media and Technology Charter High School",
    "wof:placetype": "venue"
  },
  "geometry": {"coordinates":[-71.120399,42.3517],"type":"Point"}
}
