{
  "type": "Feature",
  "properties": {
    "iso:country":"US",
    "sg:address":"72 Norton Rd",
    "sg:city":"Quincy",
    "sg:classifiers":[
        {
            "category":"Health Services",
            "subcategory":"Doctor",
            "type":"Services"
        }
    ],
    "sg:phone":"+1 617 328 1364",
    "sg:postcode":"02169",
    "sg:province":"MA",
    "sg:tags":[
        "physician",
        "surgeon"
    ],
    "wof:name":"Boston Va Healthcare System",
    "wof:placetype":"venue"
},
  "geometry": {"coordinates":[-70.987073,42.263533],"type":"Point"}
}