{
  "type": "Feature",
  "properties": {
    "addr:full": "430 Crawford St Fitchburg MA 01420",
    "addr:housenumber": "430",
    "addr:postcode": "01420",
    "addr:street": "Crawford St",
    "iso:country": "US",
    "ovtr:label": "Steel-Fab Inc, 430 Crawford St Fitchburg MA US",
    "ovtr:similarity": 2.028956890106201,
    "sg:address": "430 Crawford St",
    "sg:city": "Fitchburg",
    "sg:classifiers": [
      {
        "category": "Manufacturing",
        "subcategory": "Metals",
        "type": "Manufacturing \u0026 Wholesale Goods"
      }
    ],
    "sg:phone": "+1 978 345 1112",
    "sg:postcode": "01420",
    "sg:province": "MA",
    "sg:tags": [
      "fabricated",
      "structural"
    ],
    "sg:website": "www.steel-fab-inc.com",
    "wof:name": "Steel-Fab Inc",
    "wof:placetype": "venue"
  },
  "geometry": {"coordinates":[-71.755214,42.559518],"type":"Point"}
}
