{
  "type": "Feature",
  "properties": {
    "iso:country":"US",
    "sg:address":"430 Crawford St",
    "sg:city":"Fitchburg",
    "sg:classifiers":[
        {
            "category":"Manufacturing",
            "subcategory":"Metals",
            "type":"Manufacturing & Wholesale Goods"
        }
    ],
    "sg:phone":"+1 978 345 1112",
    "sg:postcode":"01420",
    "sg:province":"MA",
    "sg:tags":[
        "fabricated",
        "structural"
    ],
    "sg:website":"www.steel-fab-inc.com",
    "wof:name":"Steel-Fab Inc",
    "wof:placetype":"venue"
},
  "geometry": {"coordinates":[-71.755214,42.559518],"type":"Point"}
}