{
  "type": "Feature",
  "properties": {
    "addr:full": "301 Highland St Weston MA 02493",
    "addr:housenumber": "301",
    "addr:postcode": "02493",
    "addr:street": "Highland St",
    "iso:country": "US",
    "sg:address": "301 Highland St",
    "sg:city": "Weston",
    "sg:classifiers": [
      {
        "category": "Professional",
        "subcategory": "Management \u0026 Consulting",
        "type": "Services"
      }
    ],
    "sg:phone": "+1   ",
    "sg:postcode": "02493",
    "sg:province": "MA",
    "sg:tags": [
      "advice",
      "research"
    ],
    "wof:name": "Chesbrough Consulting",
    "wof:placetype": "venue"
  },
  "geometry": {"coordinates":[-71.320349,42.343981],"type":"Point"}
}
