{
  "type": "Feature",
  "properties": {
    "addr:full":"10 Spencer Street Stoneham MA 02180",
    "addr:housenumber":"10",
    "addr:postcode":"02180",
    "addr:street":"Spencer Street",
    "iso:country":"US",
    "sg:address":"10 Spencer Street",
    "sg:city":"Stoneham",
    "sg:classifiers":[
        {
            "category":"Building & Trades",
            "subcategory":"Cleaning & Sanitation",
            "type":"Services"
        }
    ],
    "sg:phone":"+1 781 279 2900",
    "sg:postcode":"02180",
    "sg:province":"MA",
    "sg:tags":[
        "carpet"
    ],
    "sg:website":"www.breatheasier.com",
    "wof:name":"Envirotech Clean Air",
    "wof:placetype":"venue"
},
  "geometry": {"coordinates":[-71.099144,42.478505],"type":"Point"}
}