{
  "type": "Feature",
  "properties": {
    "iso:country":"US",
    "sg:address":"750 Lexington St",
    "sg:city":"Waltham",
    "sg:classifiers":[
        {
            "category":"Professional",
            "subcategory":"Business Services",
            "type":"Services"
        }
    ],
    "sg:phone":"+1 781 894 7907",
    "sg:postcode":"02452",
    "sg:province":"MA",
    "sg:tags":[
        "appraiser"
    ],
    "wof:name":"Metrowest Appraisals",
    "wof:placetype":"venue"
},
  "geometry": {"coordinates":[-71.234174,42.400661],"type":"Point"}
}