{
  "type": "Feature",
  "properties": {
    "iso:country":"US",
    "sg:address":"81 Edgewater Dr",
    "sg:city":"Quincy",
    "sg:classifiers":[
        {
            "category":"Professional",
            "subcategory":"Computer Services",
            "type":"Services"
        }
    ],
    "sg:phone":"+1 617 471 4301",
    "sg:postcode":"02169",
    "sg:province":"MA",
    "wof:name":"Phase III Corp",
    "wof:placetype":"venue"
},
  "geometry": {"coordinates":[-70.950863,42.266267],"type":"Point"}
}