{
  "type": "Feature",
  "properties": {
    "addr:full":"10 Essex St Andover MA 01810",
    "addr:housenumber":"10",
    "addr:postcode":"01810",
    "addr:street":"Essex St",
    "iso:country":"US",
    "sg:address":"10 Essex St",
    "sg:city":"Andover",
    "sg:classifiers":[
        {
            "category":"Insurance",
            "subcategory":"Insurance Agent",
            "type":"Services"
        }
    ],
    "sg:phone":"+1 978 475 9212",
    "sg:postcode":"01810",
    "sg:province":"MA",
    "wof:name":"Baystate Financial Svc",
    "wof:placetype":"venue"
},
  "geometry": {"coordinates":[-71.14403299999999,42.656658],"type":"Point"}
}