{
  "type": "Feature",
  "properties": {
    "addr:full": "453 High St Medford MA 02155",
    "addr:housenumber": "453",
    "addr:postcode": "02155",
    "addr:street": "High St",
    "iso:country": "US",
    "sg:address": "453 High St",
    "sg:city": "Medford",
    "sg:classifiers": [
      {
        "category": "Ice Cream",
        "type": "Food \u0026 Drink"
      }
    ],
    "sg:phone": "+1 781 393 5959",
    "sg:postcode": "02155",
    "sg:province": "MA",
    "sg:tags": [
      "frozen",
      "yogurt"
    ],
    "wof:name": "C.B. Scoops",
    "wof:placetype": "venue"
  },
  "geometry": {"coordinates":[-71.13182,42.421134],"type":"Point"}
}
