{
  "type": "Feature",
  "properties": {
    "addr:full": "6 Dun Cannon Ave Worcester MA 01604",
    "addr:housenumber": "6",
    "addr:postcode": "01604",
    "addr:street": "Dun Cannon Ave",
    "iso:country": "US",
    "sg:address": "6 Dun Cannon Ave",
    "sg:city": "Worcester",
    "sg:classifiers": [
      {
        "category": "Retail",
        "subcategory": "Auto Repair",
        "type": "Services"
      }
    ],
    "sg:phone": "+1 508 363 2565",
    "sg:postcode": "01604",
    "sg:province": "MA",
    "sg:tags": [
      "motorcycle"
    ],
    "wof:name": "Viking Choppers",
    "wof:placetype": "venue"
  },
  "geometry": {"coordinates":[-71.762029,42.244438],"type":"Point"}
}
