{
  "type": "Feature",
  "properties": {
    "iso:country":"US",
    "sg:address":"101 President Ave",
    "sg:city":"Fall River",
    "sg:classifiers":[
        {
            "category":"Bagels",
            "type":"Food & Drink"
        },
        {
            "category":"Coffee & Tea",
            "type":"Food & Drink"
        },
        {
            "category":"Food & Beverages",
            "subcategory":"Bakery",
            "type":"Retail Goods"
        },
        {
            "category":"Bakery",
            "type":"Food & Drink"
        },
        {
            "category":"Donuts",
            "type":"Food & Drink"
        }
    ],
    "sg:menulink":"http://www.allmenus.com/ma/fall-river/142889-dunkin-donuts/menu/",
    "sg:phone":"+1 508 677 0761",
    "sg:postcode":"02720",
    "sg:province":"MA",
    "sg:tags":[
        "coffee",
        "diner",
        "tea",
        "bakery",
        "bagel",
        "american",
        "pastry"
    ],
    "wof:name":"Dunkin' Donuts",
    "wof:placetype":"venue"
},
  "geometry": {"coordinates":[-71.155475,41.716669],"type":"Point"}
}