{
  "type": "Feature",
  "properties": {
    "addr:full": "101 President Ave Fall River MA 02720",
    "addr:housenumber": "101",
    "addr:postcode": "02720",
    "addr:street": "President Ave",
    "iso:country": "US",
    "sg:address": "101 President Ave",
    "sg:city": "Fall River",
    "sg:classifiers": [
      {
        "category": "Bagels",
        "type": "Food \u0026 Drink"
      },
      {
        "category": "Coffee \u0026 Tea",
        "type": "Food \u0026 Drink"
      },
      {
        "category": "Food \u0026 Beverages",
        "subcategory": "Bakery",
        "type": "Retail Goods"
      },
      {
        "category": "Bakery",
        "type": "Food \u0026 Drink"
      },
      {
        "category": "Donuts",
        "type": "Food \u0026 Drink"
      }
    ],
    "sg:menulink": "http://www.allmenus.com/ma/fall-river/142889-dunkin-donuts/menu/",
    "sg:phone": "+1 508 677 0761",
    "sg:postcode": "02720",
    "sg:province": "MA",
    "sg:tags": [
      "coffee",
      "diner",
      "tea",
      "bakery",
      "bagel",
      "american",
      "pastry"
    ],
    "wof:name": "Dunkin' Donuts",
    "wof:placetype": "venue"
  },
  "geometry": {"coordinates":[-71.155475,41.716669],"type":"Point"}
}
