{
  "type": "Feature",
  "properties": {
    "addr:full": "113 E Falmouth Hwy East Falmouth MA 02536",
    "addr:housenumber": "113",
    "addr:postcode": "02536",
    "addr:street": "E Falmouth Hwy",
    "iso:country": "US",
    "sg:address": "113 E Falmouth Hwy",
    "sg:city": "East Falmouth",
    "sg:classifiers": [
      {
        "category": "Building \u0026 Trades",
        "subcategory": "Construction",
        "type": "Services"
      }
    ],
    "sg:phone": "+1 508 540 9395",
    "sg:postcode": "02536",
    "sg:province": "MA",
    "sg:tags": [
      "painter"
    ],
    "wof:name": "Cape Way Painting",
    "wof:placetype": "venue"
  },
  "geometry": {"coordinates":[-70.569925,41.578483],"type":"Point"}
}
