{
  "type": "Feature",
  "properties": {
    "iso:country":"US",
    "sg:address":"22 Rockwood Heights Rd",
    "sg:city":"Manchester",
    "sg:classifiers":[
        {
            "category":"Health Services",
            "subcategory":"Doctor",
            "type":"Services"
        }
    ],
    "sg:phone":"+1   ",
    "sg:postcode":"01944",
    "sg:province":"MA",
    "sg:tags":[
        "medical"
    ],
    "wof:name":"Sports Medicine",
    "wof:placetype":"venue"
},
  "geometry": {"coordinates":[-70.78676900000001,42.587144],"type":"Point"}
}