{
  "type": "Feature",
  "properties": {
    "addr:full": "423 Concord Rd Weston MA 02493",
    "addr:housenumber": "423",
    "addr:postcode": "02493",
    "addr:street": "Concord Rd",
    "iso:country": "US",
    "sg:address": "423 Concord Rd",
    "sg:city": "Weston",
    "sg:classifiers": [
      {
        "category": "Health Services",
        "subcategory": "Doctor",
        "type": "Services"
      }
    ],
    "sg:phone": "+1 617 739 2525",
    "sg:postcode": "02493",
    "sg:province": "MA",
    "sg:tags": [
      "physician",
      "surgeon"
    ],
    "wof:name": "Boston Orthopedic Group",
    "wof:placetype": "venue"
  },
  "geometry": {"coordinates":[-71.322267,42.388024],"type":"Point"}
}
