{
  "type": "Feature",
  "properties": {
    "iso:country":"US",
    "sg:address":"40 Brattle St",
    "sg:city":"Cambridge",
    "sg:classifiers":[
        {
            "category":"Health Services",
            "subcategory":"Optometrist",
            "type":"Services"
        }
    ],
    "sg:phone":"+1 617 547 3310",
    "sg:postcode":"02138",
    "sg:province":"MA",
    "sg:website":"www.Brattlesquareoptical.com",
    "wof:name":"Brattle Square Optical",
    "wof:placetype":"venue"
},
  "geometry": {"coordinates":[-71.12133799999999,42.373799],"type":"Point"}
}