{
  "type": "Feature",
  "properties": {
    "addr:full": "350 Broadway Chelsea MA 02150",
    "addr:housenumber": "350",
    "addr:postcode": "02150",
    "addr:street": "Broadway",
    "iso:country": "US",
    "sg:address": "350 Broadway",
    "sg:city": "Chelsea",
    "sg:classifiers": [
      {
        "category": "Professional",
        "subcategory": "Lawyer \u0026 Legal Services",
        "type": "Services"
      }
    ],
    "sg:phone": "+1 617 884 7568",
    "sg:postcode": "02150",
    "sg:province": "MA",
    "wof:name": "Suffolk University Legal Svcs",
    "wof:placetype": "venue"
  },
  "geometry": {"coordinates":[-71.03597,42.39172],"type":"Point"}
}
