{
  "type": "Feature",
  "properties": {
    "iso:country":"US",
    "sg:address":"350 Broadway",
    "sg:city":"Chelsea",
    "sg:classifiers":[
        {
            "category":"Professional",
            "subcategory":"Lawyer & Legal Services",
            "type":"Services"
        }
    ],
    "sg:phone":"+1 617 884 7568",
    "sg:postcode":"02150",
    "sg:province":"MA",
    "wof:name":"Suffolk University Legal Svcs",
    "wof:placetype":"venue"
},
  "geometry": {"coordinates":[-71.03597000000001,42.39172],"type":"Point"}
}