{
  "type": "Feature",
  "properties": {
    "addr:full":"801 Boylston Street Chestnut Hill MA 02467",
    "addr:housenumber":"801",
    "addr:postcode":"02467",
    "addr:street":"Boylston Street",
    "iso:country":"US",
    "sg:address":"801 Boylston Street",
    "sg:city":"Chestnut Hill",
    "sg:classifiers":[
        {
            "category":"Home & Garden",
            "subcategory":"Home Furnishings",
            "type":"Retail Goods"
        },
        {
            "category":"Home & Garden",
            "subcategory":"Building Materials",
            "type":"Retail Goods"
        },
        {
            "category":"Shopping",
            "subcategory":"Antiques",
            "type":"Retail Goods"
        }
    ],
    "sg:phone":"+1 617 566 5322",
    "sg:postcode":"02467",
    "sg:province":"MA",
    "sg:tags":[
        "equipment",
        "decor",
        "lighting",
        "fixture"
    ],
    "sg:website":"www.appletonlighting.com",
    "wof:name":"Appleton Antique Lighting",
    "wof:placetype":"venue"
},
  "geometry": {"coordinates":[-71.14637,42.32649],"type":"Point"}
}