{
  "type": "Feature",
  "properties": {
    "iso:country":"US",
    "sg:address":"200 Friberg Pkwy",
    "sg:city":"Westborough",
    "sg:classifiers":[
        {
            "category":"Professional",
            "subcategory":"Engineering",
            "type":"Services"
        }
    ],
    "sg:phone":"+1 508 616 0412",
    "sg:postcode":"01581",
    "sg:province":"MA",
    "sg:tags":[
        "engineer"
    ],
    "wof:name":"KLA-Tencor Corp",
    "wof:placetype":"venue"
},
  "geometry": {"coordinates":[-71.580597,42.281882],"type":"Point"}
}