{
  "type": "Feature",
  "properties": {
    "iso:country":"US",
    "sg:address":"259 East St",
    "sg:city":"Ludlow",
    "sg:classifiers":[
        {
            "category":"Home & Garden",
            "subcategory":"Hardware",
            "type":"Retail Goods"
        }
    ],
    "sg:phone":"+1 413 583 6914",
    "sg:postcode":"01056",
    "sg:province":"MA",
    "wof:name":"Pope's Paint & Wallpaper Ctr",
    "wof:placetype":"venue"
},
  "geometry": {"coordinates":[-72.476591,42.158334],"type":"Point"}
}