{
  "type": "Feature",
  "properties": {
    "iso:country":"US",
    "sg:address":"5 Meadowbrook Ln",
    "sg:city":"Mattapoisett",
    "sg:classifiers":[
        {
            "category":"Farming",
            "subcategory":"Fish & Marine Products",
            "type":"Manufacturing & Wholesale Goods"
        }
    ],
    "sg:phone":"+1 508 758 6255",
    "sg:postcode":"02739",
    "sg:province":"MA",
    "sg:tags":[
        "fisherman"
    ],
    "wof:name":"Brandt Island Fishing Inc",
    "wof:placetype":"venue"
},
  "geometry": {"coordinates":[-70.829047,41.634753],"type":"Point"}
}