{
  "type": "Feature",
  "properties": {
    "addr:full": "5 Meadowbrook Ln Mattapoisett MA 02739",
    "addr:housenumber": "5",
    "addr:postcode": "02739",
    "addr:street": "Meadowbrook Ln",
    "iso:country": "US",
    "sg:address": "5 Meadowbrook Ln",
    "sg:city": "Mattapoisett",
    "sg:classifiers": [
      {
        "category": "Farming",
        "subcategory": "Fish \u0026 Marine Products",
        "type": "Manufacturing \u0026 Wholesale Goods"
      }
    ],
    "sg:phone": "+1 508 758 6255",
    "sg:postcode": "02739",
    "sg:province": "MA",
    "sg:tags": [
      "fisherman"
    ],
    "wof:name": "Brandt Island Fishing Inc",
    "wof:placetype": "venue"
  },
  "geometry": {"coordinates":[-70.829047,41.634753],"type":"Point"}
}
