{
  "type": "Feature",
  "properties": {
    "iso:country":"US",
    "sg:address":"58 Main St",
    "sg:city":"Franklin",
    "sg:classifiers":[
        {
            "category":"Banks & Credit Unions",
            "subcategory":"Financial Services",
            "type":"Services"
        },
        {
            "category":"Banks & Credit Unions",
            "subcategory":"Bank",
            "type":"Services"
        }
    ],
    "sg:phone":"+1 508 528 7000",
    "sg:postcode":"02038",
    "sg:province":"MA",
    "sg:tags":[
        "personal",
        "company",
        "institution",
        "holding"
    ],
    "wof:name":"Benjamin Franklin Bancorp Inc",
    "wof:placetype":"venue"
},
  "geometry": {"coordinates":[-71.39819799999999,42.08386],"type":"Point"}
}