{
  "type": "Feature",
  "properties": {
    "addr:full": "58 Main St Franklin MA 02038",
    "addr:housenumber": "58",
    "addr:postcode": "02038",
    "addr:street": "Main St",
    "iso:country": "US",
    "sg:address": "58 Main St",
    "sg:city": "Franklin",
    "sg:classifiers": [
      {
        "category": "Banks \u0026 Credit Unions",
        "subcategory": "Financial Services",
        "type": "Services"
      },
      {
        "category": "Banks \u0026 Credit Unions",
        "subcategory": "Bank",
        "type": "Services"
      }
    ],
    "sg:phone": "+1 508 528 7000",
    "sg:postcode": "02038",
    "sg:province": "MA",
    "sg:tags": [
      "personal",
      "company",
      "institution",
      "holding"
    ],
    "wof:name": "Benjamin Franklin Bancorp Inc",
    "wof:placetype": "venue"
  },
  "geometry": {"coordinates":[-71.398198,42.08386],"type":"Point"}
}
