{
  "type": "Feature",
  "properties": {
    "addr:full": "88 Franklin St Lawrence MA 01840",
    "addr:housenumber": "88",
    "addr:postcode": "01840",
    "addr:street": "Franklin St",
    "iso:country": "US",
    "sg:address": "88 Franklin St",
    "sg:city": "Lawrence",
    "sg:classifiers": [
      {
        "category": "Freight",
        "type": "Transportation"
      }
    ],
    "sg:phone": "+1 978 686 0009",
    "sg:postcode": "01840",
    "sg:province": "MA",
    "sg:tags": [
      "masters",
      "shipping"
    ],
    "wof:name": "Logico Express",
    "wof:placetype": "venue"
  },
  "geometry": {"coordinates":[-71.168548,42.707588],"type":"Point"}
}
