{
  "type": "Feature",
  "properties": {
    "addr:full": "15 Caswell Ln Plymouth MA 02360",
    "addr:housenumber": "15",
    "addr:postcode": "02360",
    "addr:street": "Caswell Ln",
    "iso:country": "US",
    "sg:address": "15 Caswell Ln",
    "sg:city": "Plymouth",
    "sg:classifiers": [
      {
        "category": "Professional",
        "subcategory": "Accounting \u0026 Tax Preparation",
        "type": "Services"
      }
    ],
    "sg:phone": "+1 508 746 7763",
    "sg:postcode": "02360",
    "sg:province": "MA",
    "sg:tags": [
      "accountant"
    ],
    "wof:name": "T L Condon \u0026 Co",
    "wof:placetype": "venue"
  },
  "geometry": {"coordinates":[-70.670905,41.966303],"type":"Point"}
}
