{
  "type": "Feature",
  "properties": {
    "iso:country":"US",
    "sg:address":"15 Caswell Ln",
    "sg:city":"Plymouth",
    "sg:classifiers":[
        {
            "category":"Professional",
            "subcategory":"Accounting & Tax Preparation",
            "type":"Services"
        }
    ],
    "sg:phone":"+1 508 746 7763",
    "sg:postcode":"02360",
    "sg:province":"MA",
    "sg:tags":[
        "accountant"
    ],
    "wof:name":"T L Condon & Co",
    "wof:placetype":"venue"
},
  "geometry": {"coordinates":[-70.670905,41.966303],"type":"Point"}
}