{
  "type": "Feature",
  "properties": {
    "addr:full":"81 Main St Canaan MA 06018",
    "addr:housenumber":"81",
    "addr:postcode":"06018",
    "addr:street":"Main St",
    "iso:country":"US",
    "sg:address":"81 Main St",
    "sg:city":"Canaan",
    "sg:classifiers":[
        {
            "category":"Restaurant",
            "type":"Food & Drink"
        }
    ],
    "sg:phone":"+1 860 824 8125",
    "sg:postcode":"06018",
    "sg:province":"MA",
    "sg:tags":[
        "eating"
    ],
    "wof:name":"Roma Pizzeria",
    "wof:placetype":"venue"
},
  "geometry": {"coordinates":[-73.32962000000001,42.026905],"type":"Point"}
}