{
  "type": "Feature",
  "properties": {
    "iso:country":"US",
    "sg:address":"100 Boylston St",
    "sg:city":"Boston",
    "sg:classifiers":[
        {
            "category":"Communications",
            "subcategory":"News Services",
            "type":"Services"
        }
    ],
    "sg:phone":"+1 617 482 9447",
    "sg:postcode":"02116",
    "sg:province":"MA",
    "wof:name":"Vnu Entertainment News Wire",
    "wof:placetype":"venue"
},
  "geometry": {"coordinates":[-71.065405,42.352339],"type":"Point"}
}