{
  "type": "Feature",
  "properties": {
    "addr:full": "14 Walker St Leominster MA 01453",
    "addr:housenumber": "14",
    "addr:postcode": "01453",
    "addr:street": "Walker St",
    "iso:country": "US",
    "sg:address": "14 Walker St",
    "sg:city": "Leominster",
    "sg:classifiers": [
      {
        "category": "Professional",
        "type": "Services"
      }
    ],
    "sg:phone": "+1   ",
    "sg:postcode": "01453",
    "sg:province": "MA",
    "wof:name": "E C B Incorporated",
    "wof:placetype": "venue"
  },
  "geometry": {"coordinates":[-71.75156,42.523537],"type":"Point"}
}
