{
  "type": "Feature",
  "properties": {
    "iso:country":"US",
    "sg:address":"14 Walker St",
    "sg:city":"Leominster",
    "sg:classifiers":[
        {
            "category":"Professional",
            "type":"Services"
        }
    ],
    "sg:phone":"+1   ",
    "sg:postcode":"01453",
    "sg:province":"MA",
    "wof:name":"E C B Incorporated",
    "wof:placetype":"venue"
},
  "geometry": {"coordinates":[-71.75156,42.523537],"type":"Point"}
}