{
  "type": "Feature",
  "properties": {
    "addr:full": "1 Market St Lynn MA 01901",
    "addr:housenumber": "1",
    "addr:postcode": "01901",
    "addr:street": "Market St",
    "iso:country": "US",
    "sg:address": "1 Market St",
    "sg:city": "Lynn",
    "sg:classifiers": [
      {
        "category": "Organizations",
        "subcategory": "Labor Organization",
        "type": "Services"
      }
    ],
    "sg:phone": "+1 781 598 3323",
    "sg:postcode": "01901",
    "sg:province": "MA",
    "wof:name": "Communications Workers-America",
    "wof:placetype": "venue"
  },
  "geometry": {"coordinates":[-70.949683,42.463356],"type":"Point"}
}
