{
  "type": "Feature",
  "properties": {
    "iso:country":"US",
    "sg:address":"50 Skyline Dr",
    "sg:city":"Worcester",
    "sg:classifiers":[
        {
            "category":"Organizations",
            "subcategory":"Membership Organization",
            "type":"Services"
        }
    ],
    "sg:phone":"+1 508 799 1042",
    "sg:postcode":"01605",
    "sg:province":"MA",
    "sg:tags":[
        "military",
        "veteran"
    ],
    "sg:website":"http://www.citychurchworc.org",
    "wof:name":"Veterans Services",
    "wof:placetype":"venue"
},
  "geometry": {"coordinates":[-71.77887,42.279301],"type":"Point"}
}