{
  "type": "Feature",
  "properties": {
    "addr:full": "600 Atlantic Ave Boston MA 02210",
    "addr:housenumber": "600",
    "addr:postcode": "02210",
    "addr:street": "Atlantic Ave",
    "iso:country": "US",
    "sg:address": "600 Atlantic Ave",
    "sg:city": "Boston",
    "sg:classifiers": [
      {
        "category": "Professional",
        "subcategory": "Lawyer \u0026 Legal Services",
        "type": "Services"
      }
    ],
    "sg:phone": "+1 617 482 7211",
    "sg:postcode": "02210",
    "sg:province": "MA",
    "sg:tags": [
      "attorney"
    ],
    "sg:website": "www.kb-law.com",
    "wof:name": "Krokidas \u0026 Bluestein",
    "wof:placetype": "venue"
  },
  "geometry": {"coordinates":[-71.05498,42.352869],"type":"Point"}
}
