{
  "type": "Feature",
  "properties": {
    "addr:full": "100 William St New Bedford MA 02740",
    "addr:housenumber": "100",
    "addr:postcode": "02740",
    "addr:street": "William St",
    "iso:country": "US",
    "sg:address": "100 William St",
    "sg:city": "New Bedford",
    "sg:classifiers": [
      {
        "category": "Shopping",
        "subcategory": "Gifts \u0026 Souvenirs",
        "type": "Retail Goods"
      }
    ],
    "sg:phone": "+1 508 992 8100",
    "sg:postcode": "02740",
    "sg:province": "MA",
    "sg:tags": [
      "shop"
    ],
    "wof:name": "White Knight Gallery",
    "wof:placetype": "venue"
  },
  "geometry": {"coordinates":[-70.926703,41.635241],"type":"Point"}
}
