{
  "type": "Feature",
  "properties": {
    "iso:country":"US",
    "sg:address":"133 Main Street",
    "sg:city":"Everett",
    "sg:classifiers":[
        {
            "category":"Personal",
            "subcategory":"Barber",
            "type":"Services"
        }
    ],
    "sg:phone":"+1 617 394 0818",
    "sg:postcode":"02149",
    "sg:province":"MA",
    "wof:name":"Larry's Barber Shop",
    "wof:placetype":"venue"
},
  "geometry": {"coordinates":[-71.061722,42.405315],"type":"Point"}
}