{
  "type": "Feature",
  "properties": {
    "addr:full":"386 South St Pittsfield MA 01201",
    "addr:housenumber":"386",
    "addr:postcode":"01201",
    "addr:street":"South St",
    "iso:country":"US",
    "sg:address":"386 South St",
    "sg:city":"Pittsfield",
    "sg:classifiers":[
        {
            "category":"Professional",
            "subcategory":"Accounting & Tax Preparation",
            "type":"Services"
        }
    ],
    "sg:phone":"+1 413 236 0950",
    "sg:postcode":"01201",
    "sg:province":"MA",
    "sg:tags":[
        "payroll"
    ],
    "wof:name":"Time Plus Payroll",
    "wof:placetype":"venue"
},
  "geometry": {"coordinates":[-73.256806,42.437848],"type":"Point"}
}