{
  "type": "Feature",
  "properties": {
    "addr:full": "459 Franklin St Worcester MA 01604",
    "addr:housenumber": "459",
    "addr:postcode": "01604",
    "addr:street": "Franklin St",
    "iso:country": "US",
    "sg:address": "459 Franklin St",
    "sg:city": "Worcester",
    "sg:classifiers": [
      {
        "category": "Freight",
        "type": "Transportation"
      }
    ],
    "sg:phone": "+1 508 753 0071",
    "sg:postcode": "01604",
    "sg:province": "MA",
    "sg:tags": [
      "trucking"
    ],
    "wof:name": "Delaware Express",
    "wof:placetype": "venue"
  },
  "geometry": {"coordinates":[-71.787558,42.260458],"type":"Point"}
}
