{
  "type": "Feature",
  "properties": {
    "iso:country":"US",
    "sg:address":"81 Main St",
    "sg:city":"Norfolk",
    "sg:classifiers":[
        {
            "category":"Personal",
            "type":"Services"
        }
    ],
    "sg:phone":"+1   ",
    "sg:postcode":"02056",
    "sg:province":"MA",
    "sg:tags":[
        "abstract",
        "title"
    ],
    "wof:name":"Arnold Title Inc",
    "wof:placetype":"venue"
},
  "geometry": {"coordinates":[-71.316923,42.120744],"type":"Point"}
}