{
  "type": "Feature",
  "properties": {
    "addr:full": "81 Main St Norfolk MA 02056",
    "addr:housenumber": "81",
    "addr:postcode": "02056",
    "addr:street": "Main St",
    "iso:country": "US",
    "sg:address": "81 Main St",
    "sg:city": "Norfolk",
    "sg:classifiers": [
      {
        "category": "Personal",
        "type": "Services"
      }
    ],
    "sg:phone": "+1   ",
    "sg:postcode": "02056",
    "sg:province": "MA",
    "sg:tags": [
      "abstract",
      "title"
    ],
    "wof:name": "Arnold Title Inc",
    "wof:placetype": "venue"
  },
  "geometry": {"coordinates":[-71.316923,42.120744],"type":"Point"}
}
