{
  "type": "Feature",
  "properties": {
    "addr:full":"24 Summit Dr East Bridgewater MA 02333",
    "addr:housenumber":"24",
    "addr:postcode":"02333",
    "addr:street":"Summit Dr",
    "iso:country":"US",
    "sg:address":"24 Summit Dr",
    "sg:city":"East Bridgewater",
    "sg:classifiers":[
        {
            "category":"Organizations",
            "subcategory":"Religious Organization",
            "type":"Services"
        }
    ],
    "sg:phone":"+1   ",
    "sg:postcode":"02333",
    "sg:province":"MA",
    "wof:name":"Full Gospel Businessmens",
    "wof:placetype":"venue"
},
  "geometry": {"coordinates":[-70.980597,42.030872],"type":"Point"}
}