{
  "type": "Feature",
  "properties": {
    "iso:country":"US",
    "sg:address":"2 2nd New Way",
    "sg:city":"Hyde Park",
    "sg:classifiers":[
        {
            "category":"Manufacturing",
            "subcategory":"Building Materials",
            "type":"Manufacturing & Wholesale Goods"
        }
    ],
    "sg:phone":"+1 617 361 5679",
    "sg:postcode":"02136",
    "sg:province":"MA",
    "sg:tags":[
        "mfg"
    ],
    "wof:name":"Gangemi Woodworking Inc",
    "wof:placetype":"venue"
},
  "geometry": {"coordinates":[-71.119699,42.254447],"type":"Point"}
}