{
  "type": "Feature",
  "properties": {
    "addr:full": "2 2nd New Way Hyde Park MA 02136",
    "addr:housenumber": "2",
    "addr:postcode": "02136",
    "addr:street": "2Nd New",
    "iso:country": "US",
    "sg:address": "2 2nd New Way",
    "sg:city": "Hyde Park",
    "sg:classifiers": [
      {
        "category": "Manufacturing",
        "subcategory": "Building Materials",
        "type": "Manufacturing \u0026 Wholesale Goods"
      }
    ],
    "sg:phone": "+1 617 361 5679",
    "sg:postcode": "02136",
    "sg:province": "MA",
    "sg:tags": [
      "mfg"
    ],
    "wof:name": "Gangemi Woodworking Inc",
    "wof:placetype": "venue"
  },
  "geometry": {"coordinates":[-71.119699,42.254447],"type":"Point"}
}
