{
  "type": "Feature",
  "properties": {
    "iso:country":"US",
    "sg:address":"788 Hale St",
    "sg:city":"Beverly",
    "sg:classifiers":[
        {
            "category":"Professional",
            "type":"Services"
        }
    ],
    "sg:phone":"+1 978 524 0174",
    "sg:postcode":"01915",
    "sg:province":"MA",
    "sg:tags":[
        "establishment"
    ],
    "wof:name":"Next Edge Solutions",
    "wof:placetype":"venue"
},
  "geometry": {"coordinates":[-70.812636,42.565661],"type":"Point"}
}