{
  "type": "Feature",
  "properties": {
    "addr:full": "387 Winthrop St Taunton MA 02780",
    "addr:housenumber": "387",
    "addr:postcode": "02780",
    "addr:street": "Winthrop St",
    "iso:country": "US",
    "sg:address": "387 Winthrop St",
    "sg:city": "Taunton",
    "sg:classifiers": [
      {
        "category": "Personal",
        "type": "Services"
      },
      {
        "category": "Retail",
        "subcategory": "Storage",
        "type": "Services"
      }
    ],
    "sg:phone": "+1 508 822 7717",
    "sg:postcode": "02780",
    "sg:province": "MA",
    "sg:tags": [
      "mover",
      "self"
    ],
    "wof:name": "Budget Rent A Car System Inc",
    "wof:placetype": "venue"
  },
  "geometry": {"coordinates":[-71.133499,41.886299],"type":"Point"}
}
