{
  "type": "Feature",
  "properties": {
    "addr:full":"21 Main St Natick MA 01760",
    "addr:housenumber":"21",
    "addr:postcode":"01760",
    "addr:street":"Main St",
    "iso:country":"US",
    "sg:address":"21 Main St",
    "sg:city":"Natick",
    "sg:classifiers":[
        {
            "category":"Professional",
            "subcategory":"Management & Consulting",
            "type":"Services"
        }
    ],
    "sg:phone":"+1 508 655 8978",
    "sg:postcode":"01760",
    "sg:province":"MA",
    "sg:tags":[
        "consultant"
    ],
    "wof:name":"Initial Design Group Cnsltng",
    "wof:placetype":"venue"
},
  "geometry": {"coordinates":[-71.34751300000001,42.284484],"type":"Point"}
}