{
  "type": "Feature",
  "properties": {
    "addr:full": "160 Lincoln Rd Lincoln MA 01773",
    "addr:housenumber": "160",
    "addr:postcode": "01773",
    "addr:street": "Lincoln Rd",
    "iso:country": "US",
    "sg:address": "160 Lincoln Rd",
    "sg:city": "Lincoln",
    "sg:classifiers": [
      {
        "category": "Professional",
        "type": "Services"
      }
    ],
    "sg:phone": "+1 781 259 4949",
    "sg:postcode": "01773",
    "sg:province": "MA",
    "sg:tags": [
      "establishment"
    ],
    "wof:name": "Pharmark Corp",
    "wof:placetype": "venue"
  },
  "geometry": {"coordinates":[-71.325375,42.414217],"type":"Point"}
}
