{
  "type": "Feature",
  "properties": {
    "addr:full":"387 Mattakeesett St Pembroke MA 02359",
    "addr:housenumber":"387",
    "addr:postcode":"02359",
    "addr:street":"Mattakeesett St",
    "iso:country":"US",
    "sg:address":"387 Mattakeesett St",
    "sg:city":"Pembroke",
    "sg:classifiers":[
        {
            "category":"Government",
            "subcategory":"Office",
            "type":"Public Place"
        }
    ],
    "sg:phone":"+1 781 293 6000",
    "sg:postcode":"02359",
    "sg:province":"MA",
    "sg:tags":[
        "village"
    ],
    "wof:name":"Pembroke Tree Dept",
    "wof:placetype":"venue"
},
  "geometry": {"coordinates":[-70.836049,42.056707],"type":"Point"}
}