{
  "type": "Feature",
  "properties": {
    "addr:full":"172 Summer St Andover MA 01810",
    "addr:housenumber":"172",
    "addr:postcode":"01810",
    "addr:street":"Summer St",
    "iso:country":"US",
    "sg:address":"172 Summer St",
    "sg:city":"Andover",
    "sg:classifiers":[
        {
            "category":"Health Services",
            "subcategory":"Health Practitioner",
            "type":"Services"
        }
    ],
    "sg:phone":"+1 978 475 2552",
    "sg:postcode":"01810",
    "sg:province":"MA",
    "sg:tags":[
        "nurse",
        "registry"
    ],
    "wof:name":"Private Nurses Inc",
    "wof:placetype":"venue"
},
  "geometry": {"coordinates":[-71.119714,42.660314],"type":"Point"}
}