{
  "type": "Feature",
  "properties": {
    "addr:full":"11 Old Lantern Ln Groton MA 01450",
    "addr:housenumber":"11",
    "addr:postcode":"01450",
    "addr:street":"Old Lantern Ln",
    "iso:country":"US",
    "sg:address":"11 Old Lantern Ln",
    "sg:city":"Groton",
    "sg:classifiers":[
        {
            "category":"Building & Trades",
            "subcategory":"Construction",
            "type":"Services"
        }
    ],
    "sg:phone":"+1   ",
    "sg:postcode":"01450",
    "sg:province":"MA",
    "sg:tags":[
        "hanging",
        "contractor"
    ],
    "wof:name":"Murchie Painting Corporation",
    "wof:placetype":"venue"
},
  "geometry": {"coordinates":[-71.530006,42.58603],"type":"Point"}
}