{
  "type": "Feature",
  "properties": {
    "addr:full": "139 Petersham Rd Hardwick MA 01037",
    "addr:housenumber": "139",
    "addr:postcode": "01037",
    "addr:street": "Petersham Rd",
    "iso:country": "US",
    "sg:address": "139 Petersham Rd",
    "sg:city": "Hardwick",
    "sg:classifiers": [
      {
        "category": "Retail",
        "subcategory": "Auto Repair",
        "type": "Services"
      }
    ],
    "sg:phone": "+1 413 477 8571",
    "sg:postcode": "01037",
    "sg:province": "MA",
    "sg:tags": [
      "repairing",
      "automobile"
    ],
    "wof:name": "Butler's Gas \u0026 Art's Auto Svc",
    "wof:placetype": "venue"
  },
  "geometry": {"coordinates":[-72.19971,42.356198],"type":"Point"}
}
