{
  "type": "Feature",
  "properties": {
    "addr:full":"35 Kneeland St Boston MA 02111",
    "addr:housenumber":"35",
    "addr:postcode":"02111",
    "addr:street":"Kneeland St",
    "iso:country":"US",
    "sg:address":"35 Kneeland St",
    "sg:city":"Boston",
    "sg:classifiers":[
        {
            "category":"Shopping",
            "subcategory":"Pharmacy",
            "type":"Retail Goods"
        }
    ],
    "sg:phone":"+1 617 542 1885",
    "sg:postcode":"02111",
    "sg:province":"MA",
    "sg:tags":[
        "drugstore"
    ],
    "wof:name":"Sdc",
    "wof:placetype":"venue"
},
  "geometry": {"coordinates":[-71.061826,42.350563],"type":"Point"}
}