{
  "type": "Feature",
  "properties": {
    "iso:country":"US",
    "sg:address":"18 E Worcester St",
    "sg:city":"Worcester",
    "sg:classifiers":[
        {
            "category":"Utilities",
            "subcategory":"Water",
            "type":"Services"
        }
    ],
    "sg:phone":"+1 508 799 1485",
    "sg:postcode":"01604",
    "sg:province":"MA",
    "sg:tags":[
        "company",
        "sewage"
    ],
    "wof:name":"Worcester Water Dept",
    "wof:placetype":"venue"
},
  "geometry": {"coordinates":[-71.78864900000001,42.263293],"type":"Point"}
}