{
  "type": "Feature",
  "properties": {
    "addr:full":"350 Cold Spring Rd Belchertown MA 01007",
    "addr:housenumber":"350",
    "addr:postcode":"01007",
    "addr:street":"Cold Spring Rd",
    "iso:country":"US",
    "sg:address":"350 Cold Spring Rd",
    "sg:city":"Belchertown",
    "sg:classifiers":[
        {
            "category":"Sports & Exercise",
            "subcategory":"Sports Center",
            "type":"Entertainment"
        }
    ],
    "sg:phone":"+1 413 323 9387",
    "sg:postcode":"01007",
    "sg:province":"MA",
    "wof:name":"Swift River Sportsman Club",
    "wof:placetype":"venue"
},
  "geometry": {"coordinates":[-72.347656,42.244141],"type":"Point"}
}