{
  "type": "Feature",
  "properties": {
    "iso:country":"US",
    "sg:address":"350 Cold Spring Rd",
    "sg:city":"Belchertown",
    "sg:classifiers":[
        {
            "category":"Sports & Exercise",
            "subcategory":"Sports Center",
            "type":"Entertainment"
        }
    ],
    "sg:phone":"+1 413 323 9387",
    "sg:postcode":"01007",
    "sg:province":"MA",
    "wof:name":"Swift River Sportsman Club",
    "wof:placetype":"venue"
},
  "geometry": {"coordinates":[-72.347656,42.244141],"type":"Point"}
}