{
  "type": "Feature",
  "properties": {
    "iso:country":"US",
    "sg:address":"1165R Massachusetts Ave",
    "sg:city":"Dorchester",
    "sg:classifiers":[
        {
            "category":"Building & Trades",
            "subcategory":"Construction",
            "type":"Services"
        }
    ],
    "sg:phone":"+1 781 646 1260",
    "sg:postcode":"02125",
    "sg:province":"MA",
    "sg:tags":[
        "interior",
        "design"
    ],
    "wof:name":"Reid Design Inc",
    "wof:placetype":"venue"
},
  "geometry": {"coordinates":[-71.065116,42.324461],"type":"Point"}
}