{
  "type": "Feature",
  "properties": {
    "iso:country":"US",
    "sg:address":"101 Ledgestone Rd",
    "sg:city":"Douglas",
    "sg:classifiers":[
        {
            "category":"Building & Trades",
            "subcategory":"Construction",
            "type":"Services"
        }
    ],
    "sg:phone":"+1 508 320 8976",
    "sg:postcode":"01516",
    "sg:province":"MA",
    "sg:tags":[
        "contractor",
        "mechanical"
    ],
    "wof:name":"D G Marshall Associates Inc",
    "wof:placetype":"venue"
},
  "geometry": {"coordinates":[-71.78016700000001,42.094021],"type":"Point"}
}