{
  "type": "Feature",
  "properties": {
    "addr:full": "52 Andover St North Andover MA 01845",
    "addr:housenumber": "52",
    "addr:postcode": "01845",
    "addr:street": "Andover St",
    "iso:country": "US",
    "sg:address": "52 Andover St",
    "sg:city": "North Andover",
    "sg:classifiers": [
      {
        "category": "Restaurant",
        "type": "Food \u0026 Drink"
      }
    ],
    "sg:phone": "+1   ",
    "sg:postcode": "01845",
    "sg:province": "MA",
    "sg:tags": [
      "eating"
    ],
    "wof:name": "Napoli Trk Co Inc",
    "wof:placetype": "venue"
  },
  "geometry": {"coordinates":[-71.115854,42.682911],"type":"Point"}
}
