{
  "type": "Feature",
  "properties": {
    "iso:country":"US",
    "sg:address":"52 Andover St",
    "sg:city":"North Andover",
    "sg:classifiers":[
        {
            "category":"Restaurant",
            "type":"Food & Drink"
        }
    ],
    "sg:phone":"+1   ",
    "sg:postcode":"01845",
    "sg:province":"MA",
    "sg:tags":[
        "eating"
    ],
    "wof:name":"Napoli Trk Co Inc",
    "wof:placetype":"venue"
},
  "geometry": {"coordinates":[-71.115854,42.682911],"type":"Point"}
}