{
  "type": "Feature",
  "properties": {
    "addr:full":"160 Boylston St Chestnut Hill MA 02467",
    "addr:housenumber":"160",
    "addr:postcode":"02467",
    "addr:street":"Boylston St",
    "iso:country":"US",
    "sg:address":"160 Boylston St",
    "sg:city":"Chestnut Hill",
    "sg:classifiers":[
        {
            "category":"Professional",
            "subcategory":"Computer Services",
            "type":"Services"
        }
    ],
    "sg:phone":"+1   ",
    "sg:postcode":"02467",
    "sg:province":"MA",
    "wof:name":"Thorne Computer Repair Inc",
    "wof:placetype":"venue"
},
  "geometry": {"coordinates":[-71.172338,42.321192],"type":"Point"}
}