{
  "type": "Feature",
  "properties": {
    "addr:full":"220 Packard Ave Medford MA 02155",
    "addr:housenumber":"220",
    "addr:postcode":"02155",
    "addr:street":"Packard Ave",
    "iso:country":"US",
    "sg:address":"220 Packard Ave",
    "sg:city":"Medford",
    "sg:classifiers":[
        {
            "category":"Organizations",
            "subcategory":"Membership Organization",
            "type":"Services"
        }
    ],
    "sg:phone":"+1 617 628 5000",
    "sg:postcode":"02155",
    "sg:province":"MA",
    "wof:name":"Hillel Foundation-Greater Bos",
    "wof:placetype":"venue"
},
  "geometry": {"coordinates":[-71.120445,42.409046],"type":"Point"}
}