{
  "type": "Feature",
  "properties": {
    "iso:country":"US",
    "sg:address":"32 School St",
    "sg:city":"Framingham",
    "sg:classifiers":[
        {
            "category":"Personal",
            "type":"Services"
        }
    ],
    "sg:phone":"+1 508 788 0906",
    "sg:postcode":"01701",
    "sg:province":"MA",
    "sg:tags":[
        "therapist",
        "massage"
    ],
    "wof:name":"Mare Tomaski Massage",
    "wof:placetype":"venue"
},
  "geometry": {"coordinates":[-71.396237,42.321443],"type":"Point"}
}