{
  "type": "Feature",
  "properties": {
    "addr:full": "100 Stonehedge Pl Boxborough MA 01719",
    "addr:housenumber": "100",
    "addr:postcode": "01719",
    "addr:street": "Stonehedge Pl",
    "iso:country": "US",
    "sg:address": "100 Stonehedge Pl",
    "sg:city": "Boxborough",
    "sg:classifiers": [
      {
        "category": "Building \u0026 Trades",
        "subcategory": "Electrical",
        "type": "Services"
      }
    ],
    "sg:phone": "+1 978 263 2996",
    "sg:postcode": "01719",
    "sg:province": "MA",
    "sg:tags": [
      "electric",
      "industrial",
      "contractors-commercial",
      "contractor"
    ],
    "wof:name": "Carbone Electric Inc",
    "wof:placetype": "venue"
  },
  "geometry": {"coordinates":[-71.498657,42.47459],"type":"Point"}
}
