{
  "type": "Feature",
  "properties": {
    "addr:full": "105 Ferry St Malden MA 02148",
    "addr:housenumber": "105",
    "addr:postcode": "02148",
    "addr:street": "Ferry St",
    "iso:country": "US",
    "sg:address": "105 Ferry St",
    "sg:city": "Malden",
    "sg:classifiers": [
      {
        "category": "Place Of Worship",
        "subcategory": "Church",
        "type": "Public Place"
      },
      {
        "category": "Place Of Worship",
        "type": "Public Place"
      },
      {
        "category": "Organizations",
        "subcategory": "Religious Organization",
        "type": "Services"
      }
    ],
    "sg:phone": "+1 781 324 4645",
    "sg:postcode": "02148",
    "sg:province": "MA",
    "sg:tags": [
      "god",
      "god-independent",
      "churches-assemblies"
    ],
    "wof:name": "Assembly Of God In Malden",
    "wof:placetype": "venue"
  },
  "geometry": {"coordinates":[-71.064933,42.424844],"type":"Point"}
}
