{
  "type": "Feature",
  "properties": {
    "addr:full": "100 Cambridge St Ste 900 Boston MA 02114",
    "addr:housenumber": "100",
    "addr:postcode": "02114",
    "addr:street": "Cambridge St Ste 900",
    "iso:country": "US",
    "sg:address": "100 Cambridge St Ste 900",
    "sg:city": "Boston",
    "sg:classifiers": [
      {
        "category": "Utilities",
        "subcategory": "Recycling",
        "type": "Services"
      }
    ],
    "sg:phone": "+1 617 626 1000",
    "sg:postcode": "02114",
    "sg:province": "MA",
    "sg:tags": [
      "disposal",
      "waste",
      "equipment"
    ],
    "wof:name": "Office Geographic Envmtl Info",
    "wof:placetype": "venue"
  },
  "geometry": {"coordinates":[-71.062543,42.361166],"type":"Point"}
}
