{
  "type": "Feature",
  "properties": {
    "addr:full": "844 Acushnet Ave New Bedford MA 02740",
    "addr:housenumber": "844",
    "addr:postcode": "02740",
    "addr:street": "Acushnet Ave",
    "iso:country": "US",
    "sg:address": "844 Acushnet Ave",
    "sg:city": "New Bedford",
    "sg:classifiers": [
      {
        "category": "Organizations",
        "subcategory": "Religious Organization",
        "type": "Services"
      }
    ],
    "sg:phone": "+1 508 993 8421",
    "sg:postcode": "02740",
    "sg:province": "MA",
    "wof:name": "Christian Revival Temple",
    "wof:placetype": "venue"
  },
  "geometry": {"coordinates":[-70.9277,41.651945],"type":"Point"}
}
