{
  "type": "Feature",
  "properties": {
    "addr:full":"190 Shepard St Lynn MA 01902",
    "addr:housenumber":"190",
    "addr:postcode":"01902",
    "addr:street":"Shepard St",
    "iso:country":"US",
    "sg:address":"190 Shepard St",
    "sg:city":"Lynn",
    "sg:classifiers":[
        {
            "category":"Government",
            "subcategory":"Office",
            "type":"Public Place"
        }
    ],
    "sg:phone":"+1 781 599 9474",
    "sg:postcode":"01902",
    "sg:province":"MA",
    "wof:name":"Connery Rink",
    "wof:placetype":"venue"
},
  "geometry": {"coordinates":[-70.95321199999999,42.456993],"type":"Point"}
}