{
  "type": "Feature",
  "properties": {
    "addr:full": "318 Manley St West Bridgewater MA 02379",
    "addr:housenumber": "318",
    "addr:postcode": "02379",
    "addr:street": "Manley St",
    "iso:country": "US",
    "sg:address": "318 Manley St",
    "sg:city": "West Bridgewater",
    "sg:classifiers": [
      {
        "category": "Building \u0026 Trades",
        "subcategory": "Construction",
        "type": "Services"
      }
    ],
    "sg:phone": "+1 508 588 5498",
    "sg:postcode": "02379",
    "sg:province": "MA",
    "sg:tags": [
      "maker",
      "cabinet"
    ],
    "wof:name": "Mediterranean Custom Cabinets",
    "wof:placetype": "venue"
  },
  "geometry": {"coordinates":[-71.056024,42.032716],"type":"Point"}
}
