{
  "type": "Feature",
  "properties": {
    "iso:country":"US",
    "sg:address":"318 Manley St",
    "sg:city":"West Bridgewater",
    "sg:classifiers":[
        {
            "category":"Building & Trades",
            "subcategory":"Construction",
            "type":"Services"
        }
    ],
    "sg:phone":"+1 508 588 5498",
    "sg:postcode":"02379",
    "sg:province":"MA",
    "sg:tags":[
        "maker",
        "cabinet"
    ],
    "wof:name":"Mediterranean Custom Cabinets",
    "wof:placetype":"venue"
},
  "geometry": {"coordinates":[-71.05602399999999,42.032716],"type":"Point"}
}