{
  "type": "Feature",
  "properties": {
    "iso:country":"US",
    "sg:address":"814 Route 28",
    "sg:city":"Harwich Port",
    "sg:classifiers":[
        {
            "category":"Building & Trades",
            "subcategory":"Plumbing",
            "type":"Services"
        }
    ],
    "sg:phone":"+1 508 432 2471",
    "sg:postcode":"02646",
    "sg:province":"MA",
    "wof:name":"Bell Plumbing Heating & Oil Burner Service - CLOSED",
    "wof:placetype":"venue"
},
  "geometry": {"coordinates":[-70.051498,41.673199],"type":"Point"}
}