{
  "type": "Feature",
  "properties": {
    "iso:country":"US",
    "sg:address":"987 Chestnut St",
    "sg:city":"Newton",
    "sg:classifiers":[
        {
            "category":"Shopping",
            "subcategory":"Hobbies, Toys, & Games",
            "type":"Retail Goods"
        }
    ],
    "sg:phone":"+1 781 449 3001",
    "sg:postcode":"02464",
    "sg:province":"MA",
    "sg:tags":[
        "equipment",
        "video",
        "rental"
    ],
    "wof:name":"Swank Audio Visual",
    "wof:placetype":"venue"
},
  "geometry": {"coordinates":[-71.225426,42.314953],"type":"Point"}
}