{
  "type": "Feature",
  "properties": {
    "iso:country":"US",
    "sg:address":"46 McLean St",
    "sg:city":"Wellesley",
    "sg:classifiers":[
        {
            "category":"Education",
            "subcategory":"Dance Studio",
            "type":"Public Place"
        }
    ],
    "sg:phone":"+1   ",
    "sg:postcode":"02481",
    "sg:province":"MA",
    "wof:name":"All That Jazz Dance Studio",
    "wof:placetype":"venue"
},
  "geometry": {"coordinates":[-71.241669,42.312922],"type":"Point"}
}