{
  "type": "Feature",
  "properties": {
    "iso:country":"US",
    "sg:address":"369 Main St",
    "sg:city":"Spencer",
    "sg:classifiers":[
        {
            "category":"Retail",
            "subcategory":"Veterinary Services",
            "type":"Services"
        }
    ],
    "sg:phone":"+1 508 885 4205",
    "sg:postcode":"01562",
    "sg:province":"MA",
    "sg:tags":[
        "veterinarian"
    ],
    "wof:name":"Buck Hill Veterinary Svc",
    "wof:placetype":"venue"
},
  "geometry": {"coordinates":[-71.971822,42.252458],"type":"Point"}
}