{
  "type": "Feature",
  "properties": {
    "addr:full": "173 Rt 6A Orleans MA 02653",
    "addr:housenumber": "173",
    "addr:postcode": "02653",
    "addr:street": "Rt 6A",
    "iso:country": "US",
    "sg:address": "173 Rt 6A",
    "sg:city": "Orleans",
    "sg:classifiers": [
      {
        "category": "Health Services",
        "subcategory": "Optometrist",
        "type": "Services"
      }
    ],
    "sg:phone": "+1 508 240 0898",
    "sg:postcode": "02653",
    "sg:province": "MA",
    "wof:name": "Bass River Optometrics Inc",
    "wof:placetype": "venue"
  },
  "geometry": {"coordinates":[-69.996654,41.782414],"type":"Point"}
}
