{
  "type": "Feature",
  "properties": {
    "iso:country":"US",
    "sg:address":"109 Mount Vernon St",
    "sg:city":"Boston",
    "sg:classifiers":[
        {
            "category":"Real Estate",
            "subcategory":"Real Estate Agent",
            "type":"Services"
        }
    ],
    "sg:phone":"+1 617 720 5066",
    "sg:postcode":"02108",
    "sg:province":"MA",
    "wof:name":"Historic Bostonian Properties",
    "wof:placetype":"venue"
},
  "geometry": {"coordinates":[-71.070173,42.357905],"type":"Point"}
}