{
  "type": "Feature",
  "properties": {
    "iso:country":"US",
    "sg:address":"13 Alexander Rd",
    "sg:city":"Billerica",
    "sg:classifiers":[
        {
            "category":"Manufacturing",
            "subcategory":"Tools & Machinery",
            "type":"Manufacturing & Wholesale Goods"
        }
    ],
    "sg:phone":"+1 978 663 3989",
    "sg:postcode":"01821",
    "sg:province":"MA",
    "sg:tags":[
        "machine",
        "shop"
    ],
    "sg:website":"www.crmach.com",
    "wof:name":"C R Machine Co",
    "wof:placetype":"venue"
},
  "geometry": {"coordinates":[-71.218484,42.551115],"type":"Point"}
}