{
  "type": "Feature",
  "properties": {
    "addr:full":"163 Tappan St Brookline MA 02445",
    "addr:housenumber":"163",
    "addr:postcode":"02445",
    "addr:street":"Tappan St",
    "iso:country":"US",
    "sg:address":"163 Tappan St",
    "sg:city":"Brookline",
    "sg:classifiers":[
        {
            "category":"Shopping",
            "subcategory":"Computers & Home Electronics",
            "type":"Retail Goods"
        },
        {
            "category":"Professional",
            "subcategory":"Computer Services",
            "type":"Services"
        }
    ],
    "sg:phone":"+1 617 277 0087",
    "sg:postcode":"02445",
    "sg:province":"MA",
    "sg:tags":[
        "software",
        "programing",
        "custom"
    ],
    "sg:website":"www.shiman.com",
    "wof:name":"Shiman Associates Inc",
    "wof:placetype":"venue"
},
  "geometry": {"coordinates":[-71.13194,42.33273],"type":"Point"}
}