{
  "type": "Feature",
  "properties": {
    "addr:full":"391 Main St Oxford MA 01540",
    "addr:housenumber":"391",
    "addr:postcode":"01540",
    "addr:street":"Main St",
    "iso:country":"US",
    "sg:address":"391 Main St",
    "sg:city":"Oxford",
    "sg:classifiers":[
        {
            "category":"Building & Trades",
            "subcategory":"Plumbing",
            "type":"Services"
        }
    ],
    "sg:phone":"+1   ",
    "sg:postcode":"01540",
    "sg:province":"MA",
    "sg:tags":[
        "contractor"
    ],
    "wof:name":"Bousquet Plumbing Heating",
    "wof:placetype":"venue"
},
  "geometry": {"coordinates":[-71.863833,42.124799],"type":"Point"}
}