{
  "type": "Feature",
  "properties": {
    "iso:country":"US",
    "sg:address":"1500 Riverdale St",
    "sg:city":"West Springfield",
    "sg:classifiers":[
        {
            "category":"Travel",
            "subcategory":"Hotels & Motels",
            "type":"Entertainment"
        }
    ],
    "sg:phone":"+1 413 736 8080",
    "sg:postcode":"01089",
    "sg:province":"MA",
    "sg:website":"www.super8.com",
    "wof:name":"Super 8 Motel",
    "wof:placetype":"venue"
},
  "geometry": {"coordinates":[-72.62914000000001,42.145044],"type":"Point"}
}