{
  "type": "Feature",
  "properties": {
    "addr:full": "1758 Boston Rd Springfield MA 01129",
    "addr:housenumber": "1758",
    "addr:postcode": "01129",
    "addr:street": "Boston Rd",
    "iso:country": "US",
    "ovtr:label": "Custom Car Sound Inc, 1758 Boston Rd Springfield MA US",
    "ovtr:similarity": 2.2267470359802246,
    "sg:address": "1758 Boston Rd",
    "sg:city": "Springfield",
    "sg:classifiers": [
      {
        "category": "Autos \u0026 Motor Vehicles",
        "subcategory": "Auto Supplies",
        "type": "Retail Goods"
      }
    ],
    "sg:phone": "+1 413 543 3713",
    "sg:postcode": "01129",
    "sg:province": "MA",
    "sg:tags": [
      "automobile",
      "stereo",
      "radio"
    ],
    "wof:name": "Custom Car Sound Inc",
    "wof:placetype": "venue"
  },
  "geometry": {"coordinates":[-72.484931,42.145022],"type":"Point"}
}
