{
  "type": "Feature",
  "properties": {
    "addr:full":"309 Hillside St Milton MA 02186",
    "addr:housenumber":"309",
    "addr:postcode":"02186",
    "addr:street":"Hillside St",
    "iso:country":"US",
    "sg:address":"309 Hillside St",
    "sg:city":"Milton",
    "sg:classifiers":[
        {
            "category":"Manufacturing",
            "subcategory":"Glass & Minerals",
            "type":"Manufacturing & Wholesale Goods"
        }
    ],
    "sg:phone":"+1 617 696 7335",
    "sg:postcode":"02186",
    "sg:province":"MA",
    "sg:tags":[
        "instrument",
        "scientific",
        "apparatus"
    ],
    "sg:website":"www.ionoptix.com",
    "wof:name":"Ion Optix Corp",
    "wof:placetype":"venue"
},
  "geometry": {"coordinates":[-71.084019,42.221046],"type":"Point"}
}