{
  "type": "Feature",
  "properties": {
    "iso:country":"US",
    "sg:address":"116 Old Wharf Rd",
    "sg:city":"North Chatham",
    "sg:classifiers":[
        {
            "category":"Professional",
            "subcategory":"Management & Consulting",
            "type":"Services"
        }
    ],
    "sg:phone":"+1 508 945 7012",
    "sg:postcode":"02650",
    "sg:province":"MA",
    "sg:tags":[
        "consultant",
        "business"
    ],
    "wof:name":"Gould Mc Coy & Chadick LTD",
    "wof:placetype":"venue"
},
  "geometry": {"coordinates":[-69.950587,41.703415],"type":"Point"}
}