{
  "type": "Feature",
  "properties": {
    "iso:country":"US",
    "sg:address":"268 Melrose St",
    "sg:city":"Auburndale",
    "sg:classifiers":[
        {
            "category":"Professional",
            "subcategory":"Management & Consulting",
            "type":"Services"
        }
    ],
    "sg:phone":"+1 617 969 3220",
    "sg:postcode":"02466",
    "sg:province":"MA",
    "wof:name":"Timefinder",
    "wof:placetype":"venue"
},
  "geometry": {"coordinates":[-71.248704,42.347578],"type":"Point"}
}