{
  "type": "Feature",
  "properties": {
    "addr:full":"1216 Main St Holden MA 01520",
    "addr:housenumber":"1216",
    "addr:postcode":"01520",
    "addr:street":"Main St",
    "iso:country":"US",
    "sg:address":"1216 Main St",
    "sg:city":"Holden",
    "sg:classifiers":[
        {
            "category":"Organizations",
            "subcategory":"Religious Organization",
            "type":"Services"
        }
    ],
    "sg:phone":"+1 508 829 4329",
    "sg:postcode":"01520",
    "sg:province":"MA",
    "sg:tags":[
        "church"
    ],
    "sg:website":"www.fbcholden.org",
    "wof:name":"First Baptist Church",
    "wof:placetype":"venue"
},
  "geometry": {"coordinates":[-71.864288,42.351266],"type":"Point"}
}