{
  "type": "Feature",
  "properties": {
    "addr:full": "17 South St Lowell MA 01852",
    "addr:housenumber": "17",
    "addr:postcode": "01852",
    "addr:street": "South St",
    "iso:country": "US",
    "sg:address": "17 South St",
    "sg:city": "Lowell",
    "sg:classifiers": [
      {
        "category": "Retail",
        "subcategory": "Auto Repair",
        "type": "Services"
      }
    ],
    "sg:phone": "+1 978 446 0070",
    "sg:postcode": "01852",
    "sg:province": "MA",
    "sg:tags": [
      "repairing",
      "automobile"
    ],
    "wof:name": "Christian Auto Repair",
    "wof:placetype": "venue"
  },
  "geometry": {"coordinates":[-71.311709,42.640882],"type":"Point"}
}
