{
  "type": "Feature",
  "properties": {
    "addr:full":"10 Parker St Gardner MA 01440",
    "addr:housenumber":"10",
    "addr:postcode":"01440",
    "addr:street":"Parker St",
    "iso:country":"US",
    "sg:address":"10 Parker St",
    "sg:city":"Gardner",
    "sg:classifiers":[
        {
            "category":"Professional",
            "subcategory":"Management & Consulting",
            "type":"Services"
        },
        {
            "category":"Social Services",
            "type":"Services"
        }
    ],
    "sg:phone":"+1 978 630 3316",
    "sg:postcode":"01440",
    "sg:province":"MA",
    "sg:tags":[
        "consultant",
        "organization",
        "resource",
        "human",
        "welfare"
    ],
    "wof:name":"HLWCC Case Management II",
    "wof:placetype":"venue"
},
  "geometry": {"coordinates":[-71.995273,42.575948],"type":"Point"}
}