{
  "type": "Feature",
  "properties": {
    "addr:full": "480 Hawes Hill Rd Barre MA 01005",
    "addr:housenumber": "480",
    "addr:postcode": "01005",
    "addr:street": "Hawes Hill Rd",
    "iso:country": "US",
    "sg:address": "480 Hawes Hill Rd",
    "sg:city": "Barre",
    "sg:classifiers": [
      {
        "category": "Retail",
        "subcategory": "Veterinary Services",
        "type": "Services"
      }
    ],
    "sg:phone": "+1   ",
    "sg:postcode": "01005",
    "sg:province": "MA",
    "wof:name": "L R Eiben Dvm",
    "wof:placetype": "venue"
  },
  "geometry": {"coordinates":[-72.121039,42.460272],"type":"Point"}
}
