{
  "type": "Feature",
  "properties": {
    "addr:full":"40 Hudson St Woburn MA 01801",
    "addr:housenumber":"40",
    "addr:postcode":"01801",
    "addr:street":"Hudson St",
    "iso:country":"US",
    "sg:address":"40 Hudson St",
    "sg:city":"Woburn",
    "sg:classifiers":[
        {
            "category":"Education",
            "subcategory":"School",
            "type":"Public Place"
        }
    ],
    "sg:phone":"+1 781 937 8236",
    "sg:postcode":"01801",
    "sg:province":"MA",
    "sg:tags":[
        "high",
        "middle",
        "elementary"
    ],
    "wof:name":"Woburn School District",
    "wof:placetype":"venue"
},
  "geometry": {"coordinates":[-71.15285799999999,42.470853],"type":"Point"}
}