{
  "type": "Feature",
  "properties": {
    "addr:full": "369 Congress Street 7th Floor Boston MA 02210",
    "addr:housenumber": "369;7th floor",
    "addr:postcode": "02210",
    "addr:street": "Congress Street",
    "iso:country": "US",
    "ovtr:label": "Innovative Collaborations, Inc., 369 Congress St Boston MA US",
    "ovtr:similarity": 3.591204881668091,
    "sg:address": "369 Congress Street 7th Floor",
    "sg:city": "Boston",
    "sg:classifiers": [
      {
        "category": "Real Estate",
        "subcategory": "Architect",
        "type": "Services"
      }
    ],
    "sg:phone": "+1 617 695 3777",
    "sg:postcode": "02210",
    "sg:province": "MA",
    "sg:website": "www.innovative-c.com",
    "wof:name": "Innovative Collaborations, Inc.",
    "wof:placetype": "venue"
  },
  "geometry": {"coordinates":[-71.0481,42.3498],"type":"Point"}
}
