{
  "type": "Feature",
  "properties": {
    "iso:country":"US",
    "sg:address":"369 Congress Street 7th Floor",
    "sg:city":"Boston",
    "sg:classifiers":[
        {
            "category":"Real Estate",
            "subcategory":"Architect",
            "type":"Services"
        }
    ],
    "sg:phone":"+1 617 695 3777",
    "sg:postcode":"02210",
    "sg:province":"MA",
    "sg:website":"www.innovative-c.com",
    "wof:name":"Innovative Collaborations, Inc.",
    "wof:placetype":"venue"
},
  "geometry": {"coordinates":[-71.04810000000001,42.3498],"type":"Point"}
}