{
  "type": "Feature",
  "properties": {
    "iso:country":"US",
    "sg:address":"61 Endicott St",
    "sg:city":"Norwood",
    "sg:classifiers":[
        {
            "category":"Building & Trades",
            "subcategory":"Cleaning & Sanitation",
            "type":"Services"
        }
    ],
    "sg:phone":"+1 781 255 9000",
    "sg:postcode":"02062",
    "sg:province":"MA",
    "sg:tags":[
        "janitor",
        "maintenance"
    ],
    "wof:name":"Sal & Sons Sunshine Cleaning",
    "wof:placetype":"venue"
},
  "geometry": {"coordinates":[-71.217218,42.178643],"type":"Point"}
}