{
  "type": "Feature",
  "properties": {
    "addr:full": "31 Glenwood Rd Andover MA 01810",
    "addr:housenumber": "31",
    "addr:postcode": "01810",
    "addr:street": "Glenwood Rd",
    "iso:country": "US",
    "sg:address": "31 Glenwood Rd",
    "sg:city": "Andover",
    "sg:classifiers": [
      {
        "category": "Real Estate",
        "subcategory": "Architect",
        "type": "Services"
      }
    ],
    "sg:phone": "+1 978 470 0454",
    "sg:postcode": "01810",
    "sg:province": "MA",
    "sg:tags": [
      "home",
      "planning",
      "design"
    ],
    "wof:name": "Homeworks Residential Design",
    "wof:placetype": "venue"
  },
  "geometry": {"coordinates":[-71.134944,42.612336],"type":"Point"}
}
