{
  "type": "Feature",
  "properties": {
    "addr:full": "2 Linden Ave Swampscott MA 01907",
    "addr:housenumber": "2",
    "addr:postcode": "01907",
    "addr:street": "Linden Ave",
    "iso:country": "US",
    "sg:address": "2 Linden Ave",
    "sg:city": "Swampscott",
    "sg:classifiers": [
      {
        "category": "Real Estate",
        "subcategory": "Architect",
        "type": "Services"
      }
    ],
    "sg:phone": "+1 781 596 1910",
    "sg:postcode": "01907",
    "sg:province": "MA",
    "wof:name": "William Hall Architects",
    "wof:placetype": "venue"
  },
  "geometry": {"coordinates":[-70.892821,42.481338],"type":"Point"}
}
