{
  "type": "Feature",
  "properties": {
    "addr:full":"420 Belmont St Worcester MA 01604",
    "addr:housenumber":"420",
    "addr:postcode":"01604",
    "addr:street":"Belmont St",
    "iso:country":"US",
    "sg:address":"420 Belmont St",
    "sg:city":"Worcester",
    "sg:classifiers":[
        {
            "category":"Autos & Motor Vehicles",
            "subcategory":"Auto Supplies",
            "type":"Retail Goods"
        },
        {
            "category":"Retail",
            "subcategory":"Auto Repair",
            "type":"Services"
        }
    ],
    "sg:phone":"+1 508 755 9387",
    "sg:postcode":"01604",
    "sg:province":"MA",
    "sg:tags":[
        "exhaust",
        "oil",
        "tire",
        "automobile",
        "system",
        "lube",
        "part",
        "brake",
        "muffler"
    ],
    "sg:website":"http://www.monro.com",
    "wof:name":"Monro Muffler Brake & Service",
    "wof:placetype":"venue"
},
  "geometry": {"coordinates":[-71.760035,42.273962],"type":"Point"}
}