{
  "type": "Feature",
  "properties": {
    "addr:full":"113 Commonwealth Ave Concord MA 01742",
    "addr:housenumber":"113",
    "addr:postcode":"01742",
    "addr:street":"Commonwealth Ave",
    "iso:country":"US",
    "sg:address":"113 Commonwealth Ave",
    "sg:city":"Concord",
    "sg:classifiers":[
        {
            "category":"Personal",
            "subcategory":"Beauty Salon",
            "type":"Services"
        }
    ],
    "sg:phone":"+1 978 371 1699",
    "sg:postcode":"01742",
    "sg:province":"MA",
    "sg:tags":[
        "nail",
        "manicuring"
    ],
    "wof:name":"Concord Nails",
    "wof:placetype":"venue"
},
  "geometry": {"coordinates":[-71.395798,42.457401],"type":"Point"}
}