{
  "type": "Feature",
  "properties": {
    "addr:full": "89 Evergreen Dr East Longmeadow MA 01028",
    "addr:housenumber": "89",
    "addr:postcode": "01028",
    "addr:street": "Evergreen Dr",
    "iso:country": "US",
    "sg:address": "89 Evergreen Dr",
    "sg:city": "East Longmeadow",
    "sg:classifiers": [
      {
        "category": "Professional",
        "subcategory": "Computer Services",
        "type": "Services"
      }
    ],
    "sg:phone": "+1   ",
    "sg:postcode": "01028",
    "sg:province": "MA",
    "sg:tags": [
      "datum"
    ],
    "wof:name": "Edr Associates",
    "wof:placetype": "venue"
  },
  "geometry": {"coordinates":[-72.470594,42.082825],"type":"Point"}
}
