{
  "type": "Feature",
  "properties": {
    "addr:full":"24 Grafton Ave Milton MA 02186",
    "addr:housenumber":"24",
    "addr:postcode":"02186",
    "addr:street":"Grafton Ave",
    "iso:country":"US",
    "sg:address":"24 Grafton Ave",
    "sg:city":"Milton",
    "sg:classifiers":[
        {
            "category":"Building & Trades",
            "subcategory":"Landscaping Services",
            "type":"Services"
        }
    ],
    "sg:phone":"+1 617 696 1244",
    "sg:postcode":"02186",
    "sg:province":"MA",
    "sg:tags":[
        "gardener"
    ],
    "wof:name":"Creative Garden Services",
    "wof:placetype":"venue"
},
  "geometry": {"coordinates":[-71.042119,42.25642],"type":"Point"}
}