{
  "type": "Feature",
  "properties": {
    "addr:full": "23 Norfolk Boston MA 02121",
    "addr:housenumber": "23",
    "addr:postcode": "02121",
    "addr:street": "Norfolk",
    "iso:country": "US",
    "sg:address": "23 Norfolk",
    "sg:city": "Boston",
    "sg:classifiers": [
      {
        "category": "Shopping",
        "subcategory": "Music",
        "type": "Retail Goods"
      }
    ],
    "sg:phone": "+1 617 265 6246",
    "sg:postcode": "02121",
    "sg:province": "MA",
    "sg:tags": [
      "dvd's"
    ],
    "wof:name": "Amical Records",
    "wof:placetype": "venue"
  },
  "geometry": {"coordinates":[-71.080997,42.309681],"type":"Point"}
}
