{
  "type": "Feature",
  "properties": {
    "addr:full": "4 Lascala Ave Plymouth MA 02360",
    "addr:housenumber": "4",
    "addr:postcode": "02360",
    "addr:street": "Lascala Ave",
    "iso:country": "US",
    "sg:address": "4 Lascala Ave",
    "sg:city": "Plymouth",
    "sg:classifiers": [
      {
        "category": "Retail",
        "subcategory": "Animal Services",
        "type": "Services"
      }
    ],
    "sg:phone": "+1 508 746 3144",
    "sg:postcode": "02360",
    "sg:province": "MA",
    "sg:tags": [
      "pet",
      "grooming",
      "washing"
    ],
    "wof:name": "Jo's Grooming Shop",
    "wof:placetype": "venue"
  },
  "geometry": {"coordinates":[-70.732377,41.934757],"type":"Point"}
}
