{
  "type": "Feature",
  "properties": {
    "iso:country":"US",
    "sg:address":"214 York St",
    "sg:city":"Canton",
    "sg:classifiers":[
        {
            "category":"Building & Trades",
            "subcategory":"Locksmith",
            "type":"Services"
        }
    ],
    "sg:phone":"+1 339 237 3693",
    "sg:postcode":"02021",
    "sg:province":"MA",
    "sg:tags":[
        "key"
    ],
    "wof:name":"Days A Emergency 24 Hr Locksmith 7",
    "wof:placetype":"venue"
},
  "geometry": {"coordinates":[-71.09457999999999,42.17613],"type":"Point"}
}