{
  "type": "Feature",
  "properties": {
    "addr:full": "421 Baker St West Roxbury MA 02132",
    "addr:housenumber": "421",
    "addr:postcode": "02132",
    "addr:street": "Baker St",
    "iso:country": "US",
    "sg:address": "421 Baker St",
    "sg:city": "West Roxbury",
    "sg:classifiers": [
      {
        "category": "Personal",
        "subcategory": "Beauty Salon",
        "type": "Services"
      }
    ],
    "sg:phone": "+1 617 323 8031",
    "sg:postcode": "02132",
    "sg:province": "MA",
    "wof:name": "Evian Nails",
    "wof:placetype": "venue"
  },
  "geometry": {"coordinates":[-71.169653,42.284101],"type":"Point"}
}
