{
  "type": "Feature",
  "properties": {
    "addr:full": "73 E Falmouth Hwy East Falmouth MA 02536",
    "addr:housenumber": "73",
    "addr:postcode": "02536",
    "addr:street": "E Falmouth Hwy",
    "iso:country": "US",
    "sg:address": "73 E Falmouth Hwy",
    "sg:city": "East Falmouth",
    "sg:classifiers": [
      {
        "category": "Organizations",
        "subcategory": "Professional Association",
        "type": "Services"
      }
    ],
    "sg:phone": "+1 508 540 9991",
    "sg:postcode": "02536",
    "sg:province": "MA",
    "sg:website": "www.tmane.org",
    "wof:name": "Treasury Management Assn Neng",
    "wof:placetype": "venue"
  },
  "geometry": {"coordinates":[-70.570635,41.57841],"type":"Point"}
}
