{
  "type": "Feature",
  "properties": {
    "iso:country":"US",
    "sg:address":"971 Commonwealth Ave",
    "sg:city":"Boston",
    "sg:classifiers":[
        {
            "category":"Education",
            "subcategory":"Music School",
            "type":"Public Place"
        }
    ],
    "sg:phone":"+1 617 782 1452",
    "sg:postcode":"02215",
    "sg:province":"MA",
    "sg:tags":[
        "instrument",
        "teacher",
        "musical"
    ],
    "wof:name":"Mtlc Music Software & Hardware",
    "wof:placetype":"venue"
},
  "geometry": {"coordinates":[-71.119338,42.351766],"type":"Point"}
}