{
  "type": "Feature",
  "properties": {
    "iso:country":"US",
    "sg:address":"25 Riverview St",
    "sg:city":"Brockton",
    "sg:classifiers":[
        {
            "category":"Manufacturing",
            "subcategory":"Signs",
            "type":"Manufacturing & Wholesale Goods"
        }
    ],
    "sg:phone":"+1 508 559 9393",
    "sg:postcode":"02302",
    "sg:province":"MA",
    "wof:name":"DMS Signs",
    "wof:placetype":"venue"
},
  "geometry": {"coordinates":[-71.008685,42.064558],"type":"Point"}
}