{
  "type": "Feature",
  "properties": {
    "addr:full": "25 Riverview St Brockton MA 02302",
    "addr:housenumber": "25",
    "addr:postcode": "02302",
    "addr:street": "Riverview St",
    "iso:country": "US",
    "sg:address": "25 Riverview St",
    "sg:city": "Brockton",
    "sg:classifiers": [
      {
        "category": "Manufacturing",
        "subcategory": "Signs",
        "type": "Manufacturing \u0026 Wholesale Goods"
      }
    ],
    "sg:phone": "+1 508 559 9393",
    "sg:postcode": "02302",
    "sg:province": "MA",
    "wof:name": "DMS Signs",
    "wof:placetype": "venue"
  },
  "geometry": {"coordinates":[-71.008685,42.064558],"type":"Point"}
}
