{
  "type": "Feature",
  "properties": {
    "addr:full":"504 Union Wharf Boston MA 02109",
    "addr:housenumber":"504",
    "addr:postcode":"02109",
    "addr:street":"Union",
    "iso:country":"US",
    "sg:address":"504 Union Wharf",
    "sg:city":"Boston",
    "sg:classifiers":[
        {
            "category":"Banks & Credit Unions",
            "subcategory":"Financial Services",
            "type":"Services"
        }
    ],
    "sg:phone":"+1   ",
    "sg:postcode":"02109",
    "sg:province":"MA",
    "sg:tags":[
        "trust",
        "realty"
    ],
    "wof:name":"244 Realty Trust",
    "wof:placetype":"venue"
},
  "geometry": {"coordinates":[-71.049378,42.365166],"type":"Point"}
}