{
  "type": "Feature",
  "properties": {
    "iso:country":"US",
    "sg:address":"109 Bridge St",
    "sg:city":"Northampton",
    "sg:classifiers":[
        {
            "category":"Personal",
            "subcategory":"Beauty Salon",
            "type":"Services"
        }
    ],
    "sg:phone":"+1 413 587 3993",
    "sg:postcode":"01060",
    "sg:province":"MA",
    "wof:name":"Diane Todrin Hair Repair",
    "wof:placetype":"venue"
},
  "geometry": {"coordinates":[-72.625103,42.324177],"type":"Point"}
}