{
  "type": "Feature",
  "properties": {
    "addr:full":"15 Lyman St Waltham MA 02452",
    "addr:housenumber":"15",
    "addr:postcode":"02452",
    "addr:street":"Lyman St",
    "iso:country":"US",
    "sg:address":"15 Lyman St",
    "sg:city":"Waltham",
    "sg:classifiers":[
        {
            "category":"Building & Trades",
            "subcategory":"Cleaning & Sanitation",
            "type":"Services"
        }
    ],
    "sg:phone":"+1 781 894 6646",
    "sg:postcode":"02452",
    "sg:province":"MA",
    "sg:tags":[
        "window"
    ],
    "wof:name":"Royal Window Cleaning Co",
    "wof:placetype":"venue"
},
  "geometry": {"coordinates":[-71.23041000000001,42.377535],"type":"Point"}
}