{
  "type": "Feature",
  "properties": {
    "addr:full": "785 Main St Holden MA 01520",
    "addr:housenumber": "785",
    "addr:postcode": "01520",
    "addr:street": "Main St",
    "iso:country": "US",
    "sg:address": "785 Main St",
    "sg:city": "Holden",
    "sg:classifiers": [
      {
        "category": "Shopping",
        "subcategory": "Gifts \u0026 Souvenirs",
        "type": "Retail Goods"
      }
    ],
    "sg:phone": "+1 508 829 6161",
    "sg:postcode": "01520",
    "sg:province": "MA",
    "sg:tags": [
      "shop"
    ],
    "wof:name": "Jr's Crafts \u0026 Gifts",
    "wof:placetype": "venue"
  },
  "geometry": {"coordinates":[-71.843928,42.341785],"type":"Point"}
}
