{
  "type": "Feature",
  "properties": {
    "addr:full": "84 Gifford St New Bedford MA 02744",
    "addr:housenumber": "84",
    "addr:postcode": "02744",
    "addr:street": "Gifford St",
    "iso:country": "US",
    "sg:address": "84 Gifford St",
    "sg:city": "New Bedford",
    "sg:classifiers": [
      {
        "category": "Autos \u0026 Motor Vehicles",
        "subcategory": "Auto Supplies",
        "type": "Retail Goods"
      }
    ],
    "sg:phone": "+1 508 984 0005",
    "sg:postcode": "02744",
    "sg:province": "MA",
    "sg:tags": [
      "automobile",
      "parts"
    ],
    "wof:name": "American Discount Supply",
    "wof:placetype": "venue"
  },
  "geometry": {"coordinates":[-70.915638,41.618964],"type":"Point"}
}
