{
  "type": "Feature",
  "properties": {
    "addr:full": "205 Broadway Lawrence MA 01840",
    "addr:housenumber": "205",
    "addr:postcode": "01840",
    "addr:street": "Broadway",
    "iso:country": "US",
    "sg:address": "205 Broadway",
    "sg:city": "Lawrence",
    "sg:classifiers": [
      {
        "category": "Autos \u0026 Motor Vehicles",
        "subcategory": "Auto Supplies",
        "type": "Retail Goods"
      }
    ],
    "sg:phone": "+1   ",
    "sg:postcode": "01840",
    "sg:province": "MA",
    "sg:tags": [
      "home"
    ],
    "wof:name": "Auto Plaza",
    "wof:placetype": "venue"
  },
  "geometry": {"coordinates":[-71.170458,42.707728],"type":"Point"}
}
