{
  "type": "Feature",
  "properties": {
    "addr:full": "27 Front St Weymouth MA 02188",
    "addr:housenumber": "27",
    "addr:postcode": "02188",
    "addr:street": "Front St",
    "iso:country": "US",
    "sg:address": "27 Front St",
    "sg:city": "Weymouth",
    "sg:classifiers": [
      {
        "category": "Social Services",
        "type": "Services"
      }
    ],
    "sg:phone": "+1 781 337 0772",
    "sg:postcode": "02188",
    "sg:province": "MA",
    "sg:tags": [
      "instruction",
      "health",
      "care"
    ],
    "wof:name": "Professional Medical Mgmt Inc",
    "wof:placetype": "venue"
  },
  "geometry": {"coordinates":[-70.968485,42.21862],"type":"Point"}
}
