{
  "type": "Feature",
  "properties": {
    "iso:country":"US",
    "sg:address":"21 Lakeside Ave",
    "sg:city":"Quincy",
    "sg:classifiers":[
        {
            "category":"Building & Trades",
            "subcategory":"Cleaning & Sanitation",
            "type":"Services"
        }
    ],
    "sg:phone":"+1 617 471 7077",
    "sg:postcode":"02169",
    "sg:province":"MA",
    "sg:tags":[
        "janitor"
    ],
    "wof:name":"Underground Technologies",
    "wof:placetype":"venue"
},
  "geometry": {"coordinates":[-70.958872,42.26873],"type":"Point"}
}