{
  "type": "Feature",
  "properties": {
    "iso:country":"US",
    "sg:address":"8 Jan Sebastian Dr",
    "sg:city":"Sandwich",
    "sg:classifiers":[
        {
            "category":"Food & Beverages",
            "subcategory":"Groceries & Convenience Stores",
            "type":"Retail Goods"
        }
    ],
    "sg:phone":"+1 508 833 8894",
    "sg:postcode":"02563",
    "sg:province":"MA",
    "sg:website":"www.wallacemv.com",
    "wof:name":"Wallace Co",
    "wof:placetype":"venue"
},
  "geometry": {"coordinates":[-70.48720400000001,41.717924],"type":"Point"}
}