{
  "type": "Feature",
  "properties": {
    "iso:country":"US",
    "sg:address":"30A Mitchell Rd",
    "sg:city":"Ipswich",
    "sg:classifiers":[
        {
            "category":"Recreation",
            "subcategory":"Boat Charter",
            "type":"Entertainment"
        }
    ],
    "sg:phone":"+1 978 356 1764",
    "sg:postcode":"01938",
    "sg:province":"MA",
    "sg:tags":[
        "boating"
    ],
    "sg:website":"www.transfusionboats.com",
    "wof:name":"Transfusion Boat Works Inc",
    "wof:placetype":"venue"
},
  "geometry": {"coordinates":[-70.85212,42.695576],"type":"Point"}
}