{
  "type": "Feature",
  "properties": {
    "addr:full":"1352 West St Amherst MA 01002",
    "addr:housenumber":"1352",
    "addr:postcode":"01002",
    "addr:street":"West St",
    "iso:country":"US",
    "sg:address":"1352 West St",
    "sg:city":"Amherst",
    "sg:classifiers":[
        {
            "category":"Organizations",
            "subcategory":"Community Association",
            "type":"Services"
        }
    ],
    "sg:phone":"+1 413 253 2080",
    "sg:postcode":"01002",
    "sg:province":"MA",
    "wof:name":"Norwottuck Fish & Game Association, Inc.",
    "wof:placetype":"venue"
},
  "geometry": {"coordinates":[-72.529532,42.308979],"type":"Point"}
}