{
  "type": "Feature",
  "properties": {
    "addr:full": "371 Commonwealth Ave Boston MA 02115",
    "addr:housenumber": "371",
    "addr:postcode": "02115",
    "addr:street": "Commonwealth Ave",
    "iso:country": "US",
    "ovtr:label": "Deuxave, 371 Commonwealth Ave Boston MA US",
    "ovtr:similarity": 1.9226230382919312,
    "sg:address": "371 Commonwealth Ave",
    "sg:city": "Boston",
    "sg:classifiers": [
      {
        "category": "Restaurant",
        "type": "Food \u0026 Drink"
      }
    ],
    "sg:phone": "+1 617 517 5915",
    "sg:postcode": "02115",
    "sg:province": "MA",
    "sg:tags": [
      "new",
      "american"
    ],
    "sg:website": "deuxave.com/",
    "wof:name": "Deuxave",
    "wof:placetype": "venue"
  },
  "geometry": {"coordinates":[-71.089078,42.34927],"type":"Point"}
}
