{
  "type": "Feature",
  "properties": {
    "addr:full": "147 Auburn St New Bedford MA 02740",
    "addr:housenumber": "147",
    "addr:postcode": "02740",
    "addr:street": "Auburn St",
    "iso:country": "US",
    "sg:address": "147 Auburn St",
    "sg:city": "New Bedford",
    "sg:classifiers": [
      {
        "category": "Manufacturing",
        "subcategory": "Printing",
        "type": "Manufacturing \u0026 Wholesale Goods"
      }
    ],
    "sg:phone": "+1 508 997 2300",
    "sg:postcode": "02740",
    "sg:province": "MA",
    "sg:tags": [
      "newspaper"
    ],
    "wof:name": "CVN News \u0026 Business Ctr",
    "wof:placetype": "venue"
  },
  "geometry": {"coordinates":[-70.951931,41.645417],"type":"Point"}
}
