{
  "type": "Feature",
  "properties": {
    "iso:country":"US",
    "sg:address":"147 Auburn St",
    "sg:city":"New Bedford",
    "sg:classifiers":[
        {
            "category":"Manufacturing",
            "subcategory":"Printing",
            "type":"Manufacturing & Wholesale Goods"
        }
    ],
    "sg:phone":"+1 508 997 2300",
    "sg:postcode":"02740",
    "sg:province":"MA",
    "sg:tags":[
        "newspaper"
    ],
    "wof:name":"CVN News & Business Ctr",
    "wof:placetype":"venue"
},
  "geometry": {"coordinates":[-70.951931,41.645417],"type":"Point"}
}