{
  "type": "Feature",
  "properties": {
    "addr:full": "85 Eastern Ave Gloucester MA 01930",
    "addr:housenumber": "85",
    "addr:postcode": "01930",
    "addr:street": "Eastern Ave",
    "iso:country": "US",
    "sg:address": "85 Eastern Ave",
    "sg:city": "Gloucester",
    "sg:classifiers": [
      {
        "category": "Health Services",
        "subcategory": "Doctor",
        "type": "Services"
      }
    ],
    "sg:phone": "+1 978 281 6890",
    "sg:postcode": "01930",
    "sg:province": "MA",
    "sg:tags": [
      "physician",
      "surgeon"
    ],
    "wof:name": "Neil Kobrosky MD",
    "wof:placetype": "venue"
  },
  "geometry": {"coordinates":[-70.645414,42.620954],"type":"Point"}
}
