{
  "type": "Feature",
  "properties": {
    "iso:country":"US",
    "sg:address":"625 Adams St",
    "sg:city":"Dorchester",
    "sg:classifiers":[
        {
            "category":"Wholesale",
            "subcategory":"Machinery & Supplies",
            "type":"Manufacturing & Wholesale Goods"
        }
    ],
    "sg:phone":"+1 617 265 8500",
    "sg:postcode":"02122",
    "sg:province":"MA",
    "sg:tags":[
        "tailor"
    ],
    "wof:name":"Pam Tailor Supply",
    "wof:placetype":"venue"
},
  "geometry": {"coordinates":[-71.055393,42.288293],"type":"Point"}
}