{
  "type": "Feature",
  "properties": {
    "addr:full":"20 Brastow Ave Somerville MA 02143",
    "addr:housenumber":"20",
    "addr:postcode":"02143",
    "addr:street":"Brastow Ave",
    "iso:country":"US",
    "sg:address":"20 Brastow Ave",
    "sg:city":"Somerville",
    "sg:classifiers":[
        {
            "category":"Professional",
            "subcategory":"Business Services",
            "type":"Services"
        }
    ],
    "sg:phone":"+1 617 623 2988",
    "sg:postcode":"02143",
    "sg:province":"MA",
    "sg:tags":[
        "financial"
    ],
    "wof:name":"Chilmark Advisors Inc",
    "wof:placetype":"venue"
},
  "geometry": {"coordinates":[-71.11096499999999,42.389363],"type":"Point"}
}