{
  "type": "Feature",
  "properties": {
    "addr:full":"277 Lafayette St Salem MA 01970",
    "addr:housenumber":"277",
    "addr:postcode":"01970",
    "addr:street":"Lafayette St",
    "iso:country":"US",
    "sg:address":"277 Lafayette St",
    "sg:city":"Salem",
    "sg:classifiers":[
        {
            "category":"Shopping",
            "subcategory":"Computers & Home Electronics",
            "type":"Retail Goods"
        }
    ],
    "sg:phone":"+1 978 745 0863",
    "sg:postcode":"01970",
    "sg:province":"MA",
    "sg:tags":[
        "software"
    ],
    "wof:name":"Whitebirch Software Inc",
    "wof:placetype":"venue"
},
  "geometry": {"coordinates":[-70.891353,42.509131],"type":"Point"}
}