{
  "type": "Feature",
  "properties": {
    "addr:full": "26 Eliot St Sherborn MA 01770",
    "addr:housenumber": "26",
    "addr:postcode": "01770",
    "addr:street": "Eliot St",
    "iso:country": "US",
    "sg:address": "26 Eliot St",
    "sg:city": "Sherborn",
    "sg:classifiers": [
      {
        "category": "Wholesale",
        "subcategory": "Apparel",
        "type": "Manufacturing \u0026 Wholesale Goods"
      }
    ],
    "sg:phone": "+1 508 655 1988",
    "sg:postcode": "01770",
    "sg:province": "MA",
    "sg:tags": [
      "scissors"
    ],
    "wof:name": "Lawrence Rubin Resources",
    "wof:placetype": "venue"
  },
  "geometry": {"coordinates":[-71.368449,42.248329],"type":"Point"}
}
