{
  "type": "Feature",
  "properties": {
    "iso:country":"US",
    "sg:address":"26 Eliot St",
    "sg:city":"Sherborn",
    "sg:classifiers":[
        {
            "category":"Wholesale",
            "subcategory":"Apparel",
            "type":"Manufacturing & Wholesale Goods"
        }
    ],
    "sg:phone":"+1 508 655 1988",
    "sg:postcode":"01770",
    "sg:province":"MA",
    "sg:tags":[
        "scissors"
    ],
    "wof:name":"Lawrence Rubin Resources",
    "wof:placetype":"venue"
},
  "geometry": {"coordinates":[-71.368449,42.248329],"type":"Point"}
}