{
  "type": "Feature",
  "properties": {
    "iso:country":"US",
    "sg:address":"9 Short St",
    "sg:city":"Worcester",
    "sg:classifiers":[
        {
            "category":"Manufacturing",
            "subcategory":"Chemicals & Compounds",
            "type":"Manufacturing & Wholesale Goods"
        }
    ],
    "sg:phone":"+1 508 756 6677",
    "sg:postcode":"01604",
    "sg:province":"MA",
    "sg:tags":[
        "biological",
        "product"
    ],
    "wof:name":"Boston Bio Products",
    "wof:placetype":"venue"
},
  "geometry": {"coordinates":[-71.77273700000001,42.246357],"type":"Point"}
}