{
  "type": "Feature",
  "properties": {
    "addr:full":"958 Main St Woburn MA 01801",
    "addr:housenumber":"958",
    "addr:postcode":"01801",
    "addr:street":"Main St",
    "iso:country":"US",
    "sg:address":"958 Main St",
    "sg:city":"Woburn",
    "sg:classifiers":[
        {
            "category":"Building & Trades",
            "subcategory":"Construction",
            "type":"Services"
        }
    ],
    "sg:phone":"+1   ",
    "sg:postcode":"01801",
    "sg:province":"MA",
    "wof:name":"Koster & Sons Construction",
    "wof:placetype":"venue"
},
  "geometry": {"coordinates":[-71.161552,42.510619],"type":"Point"}
}