{
  "type": "Feature",
  "properties": {
    "addr:full": "116 Foundry St Wakefield MA 01880",
    "addr:housenumber": "116",
    "addr:postcode": "01880",
    "addr:street": "Foundry St",
    "iso:country": "US",
    "sg:address": "116 Foundry St",
    "sg:city": "Wakefield",
    "sg:classifiers": [
      {
        "category": "Wholesale",
        "subcategory": "Stationery",
        "type": "Manufacturing \u0026 Wholesale Goods"
      }
    ],
    "sg:phone": "+1 781 246 4450",
    "sg:postcode": "01880",
    "sg:province": "MA",
    "sg:tags": [
      "packaging",
      "material"
    ],
    "sg:website": "www.millerservice.com",
    "wof:name": "Miller Service Co Inc",
    "wof:placetype": "venue"
  },
  "geometry": {"coordinates":[-71.073914,42.499073],"type":"Point"}
}
