{
  "type": "Feature",
  "properties": {
    "addr:full": "3698 Washington St. Jamaica Plain MA 02130",
    "addr:housenumber": "3698",
    "addr:postcode": "02130",
    "addr:street": "Washington St.",
    "iso:country": "US",
    "sg:address": "3698 Washington St.",
    "sg:city": "Jamaica Plain",
    "sg:classifiers": [
      {
        "category": "Bars \u0026 Pubs",
        "subcategory": "Dive Bar",
        "type": "Food \u0026 Drink"
      }
    ],
    "sg:postcode": "02130",
    "sg:province": "MA",
    "wof:name": "Griffin's Cafe",
    "wof:placetype": "venue"
  },
  "geometry": {"coordinates":[-71.112757,42.300583],"type":"Point"}
}
