{
  "type": "Feature",
  "properties": {
    "iso:country":"US",
    "sg:address":"580 Meadow St",
    "sg:city":"Chicopee",
    "sg:classifiers":[
        {
            "category":"Social Services",
            "type":"Services"
        }
    ],
    "sg:phone":"+1 413 592 4373",
    "sg:postcode":"01013",
    "sg:province":"MA",
    "sg:tags":[
        "government"
    ],
    "wof:name":"Youth Services Dept",
    "wof:placetype":"venue"
},
  "geometry": {"coordinates":[-72.614611,42.171192],"type":"Point"}
}