{
  "type": "Feature",
  "properties": {
    "addr:full":"290 Baker Ave Ste N228 Concord MA 01742",
    "addr:housenumber":"290",
    "addr:postcode":"01742",
    "addr:street":"Baker Ave Ste N228",
    "iso:country":"US",
    "sg:address":"290 Baker Ave Ste N228",
    "sg:city":"Concord",
    "sg:classifiers":[
        {
            "category":"Health Services",
            "subcategory":"Dentist",
            "type":"Services"
        }
    ],
    "sg:phone":"+1 978 369 7771",
    "sg:postcode":"01742",
    "sg:province":"MA",
    "sg:tags":[
        "pediatric"
    ],
    "sg:website":"www.pediatricdentistcm.com",
    "wof:name":"Pediatric Dentistry",
    "wof:placetype":"venue"
},
  "geometry": {"coordinates":[-71.383797,42.460602],"type":"Point"}
}