{
  "type": "Feature",
  "properties": {
    "addr:full": "21 B St Grafton MA 01501",
    "addr:housenumber": "21",
    "addr:postcode": "01501",
    "addr:street": "B St",
    "iso:country": "US",
    "sg:address": "21 B St",
    "sg:city": "Grafton",
    "sg:classifiers": [
      {
        "category": "Building \u0026 Trades",
        "subcategory": "Construction",
        "type": "Services"
      }
    ],
    "sg:phone": "+1   ",
    "sg:postcode": "01501",
    "sg:province": "MA",
    "sg:tags": [
      "carpentry",
      "contractor"
    ],
    "wof:name": "Sneade Bros Windows \u0026 Siding",
    "wof:placetype": "venue"
  },
  "geometry": {"coordinates":[-71.831193,42.221347],"type":"Point"}
}
