{
  "type": "Feature",
  "properties": {
    "addr:full": "19 Circuit Ave Oak Bluffs MA 02557",
    "addr:housenumber": "19",
    "addr:postcode": "02557",
    "addr:street": "Circuit Ave",
    "iso:country": "US",
    "sg:address": "19 Circuit Ave",
    "sg:city": "Oak Bluffs",
    "sg:classifiers": [
      {
        "category": "Bars \u0026 Pubs",
        "type": "Food \u0026 Drink"
      }
    ],
    "sg:phone": "+1 508 693 7129",
    "sg:postcode": "02557",
    "sg:province": "MA",
    "sg:tags": [
      "club",
      "night"
    ],
    "sg:website": "www.atlanticconnection.com",
    "wof:name": "Atlantic Connection Caterers",
    "wof:placetype": "venue"
  },
  "geometry": {"coordinates":[-70.557876,41.456741],"type":"Point"}
}
