{
  "type": "Feature",
  "properties": {
    "iso:country":"US",
    "sg:address":"19 Circuit Ave",
    "sg:city":"Oak Bluffs",
    "sg:classifiers":[
        {
            "category":"Bars & Pubs",
            "type":"Food & Drink"
        }
    ],
    "sg:phone":"+1 508 693 7129",
    "sg:postcode":"02557",
    "sg:province":"MA",
    "sg:tags":[
        "club",
        "night"
    ],
    "sg:website":"www.atlanticconnection.com",
    "wof:name":"Atlantic Connection Caterers",
    "wof:placetype":"venue"
},
  "geometry": {"coordinates":[-70.55787599999999,41.456741],"type":"Point"}
}