{
  "type": "Feature",
  "properties": {
    "addr:full": "2 Freedom Farme Rd Acton MA 01720",
    "addr:housenumber": "2",
    "addr:postcode": "01720",
    "addr:street": "Freedom Farme Rd",
    "iso:country": "US",
    "sg:address": "2 Freedom Farme Rd",
    "sg:city": "Acton",
    "sg:classifiers": [
      {
        "category": "Professional",
        "subcategory": "Management \u0026 Consulting",
        "type": "Services"
      },
      {
        "category": "Banks \u0026 Credit Unions",
        "subcategory": "Financial Services",
        "type": "Services"
      }
    ],
    "sg:phone": "+1 978 263 8718",
    "sg:postcode": "01720",
    "sg:province": "MA",
    "sg:tags": [
      "consultant",
      "financing",
      "planning"
    ],
    "wof:name": "The Majors Group",
    "wof:placetype": "venue"
  },
  "geometry": {"coordinates":[-71.460632,42.489349],"type":"Point"}
}
