{
  "type": "Feature",
  "properties": {
    "iso:country":"US",
    "sg:address":"2 Freedom Farme Rd",
    "sg:city":"Acton",
    "sg:classifiers":[
        {
            "category":"Professional",
            "subcategory":"Management & Consulting",
            "type":"Services"
        },
        {
            "category":"Banks & Credit Unions",
            "subcategory":"Financial Services",
            "type":"Services"
        }
    ],
    "sg:phone":"+1 978 263 8718",
    "sg:postcode":"01720",
    "sg:province":"MA",
    "sg:tags":[
        "consultant",
        "financing",
        "planning"
    ],
    "wof:name":"The Majors Group",
    "wof:placetype":"venue"
},
  "geometry": {"coordinates":[-71.460632,42.489349],"type":"Point"}
}