{
  "type": "Feature",
  "properties": {
    "addr:full":"54 Winthrop Ave Lawrence MA 01843",
    "addr:housenumber":"54",
    "addr:postcode":"01843",
    "addr:street":"Winthrop Ave",
    "iso:country":"US",
    "sg:address":"54 Winthrop Ave",
    "sg:city":"Lawrence",
    "sg:classifiers":[
        {
            "category":"Autos & Motor Vehicles",
            "subcategory":"Automobile Sales",
            "type":"Retail Goods"
        },
        {
            "category":"Retail",
            "subcategory":"Auto Repair",
            "type":"Services"
        }
    ],
    "sg:phone":"+1 978 682 2642",
    "sg:postcode":"01843",
    "sg:province":"MA",
    "sg:tags":[
        "body",
        "repairing",
        "used",
        "car",
        "painting",
        "dealers-used",
        "cars-wholesale"
    ],
    "sg:website":"http://www.michaelsmotors.com",
    "wof:name":"Michael's Motor Sales Inc",
    "wof:placetype":"venue"
},
  "geometry": {"coordinates":[-71.153032,42.69224],"type":"Point"}
}