{
  "type": "Feature",
  "properties": {
    "addr:full": "1409 Hanover St Hanover MA 02339",
    "addr:housenumber": "1409",
    "addr:postcode": "02339",
    "addr:street": "Hanover St",
    "iso:country": "US",
    "sg:address": "1409 Hanover St",
    "sg:city": "Hanover",
    "sg:classifiers": [
      {
        "category": "Retail",
        "subcategory": "Repair Shop",
        "type": "Services"
      }
    ],
    "sg:phone": "+1 781 413 0225",
    "sg:postcode": "02339",
    "sg:province": "MA",
    "sg:tags": [
      "lock",
      "locksmith"
    ],
    "wof:name": "A Emergency 24 7 Locksmith",
    "wof:placetype": "venue"
  },
  "geometry": {"coordinates":[-70.882177,42.11906],"type":"Point"}
}
