{
  "type": "Feature",
  "properties": {
    "iso:country":"US",
    "sg:address":"229 Lexington St",
    "sg:city":"Woburn",
    "sg:classifiers":[
        {
            "category":"Autos & Motor Vehicles",
            "subcategory":"Fuel & Gas Station",
            "type":"Retail Goods"
        }
    ],
    "sg:phone":"+1 781 933 9861",
    "sg:postcode":"01801",
    "sg:province":"MA",
    "wof:name":"McDermottroe Getty of Woburn Inc",
    "wof:placetype":"venue"
},
  "geometry": {"coordinates":[-71.177696,42.466702],"type":"Point"}
}