{
  "type": "Feature",
  "properties": {
    "addr:full": "1 Design Center Pl Ste 236 Boston MA 02210",
    "addr:postcode": "02210",
    "addr:street": "Center Pl Ste 236",
    "iso:country": "US",
    "sg:address": "1 Design Center Pl Ste 236",
    "sg:city": "Boston",
    "sg:classifiers": [
      {
        "category": "Wholesale",
        "subcategory": "Home Furnishings",
        "type": "Manufacturing \u0026 Wholesale Goods"
      }
    ],
    "sg:phone": "+1 617 439 9492",
    "sg:postcode": "02210",
    "sg:province": "MA",
    "sg:tags": [
      "blind",
      "shade"
    ],
    "wof:name": "Window Treats",
    "wof:placetype": "venue"
  },
  "geometry": {"coordinates":[-71.046188,42.345746],"type":"Point"}
}
