{
  "type": "Feature",
  "properties": {
    "addr:full": "167 Georgetown Rd Boxford MA 01921",
    "addr:housenumber": "167",
    "addr:postcode": "01921",
    "addr:street": "Georgetown Rd",
    "iso:country": "US",
    "sg:address": "167 Georgetown Rd",
    "sg:city": "Boxford",
    "sg:classifiers": [
      {
        "category": "Professional",
        "subcategory": "Management \u0026 Consulting",
        "type": "Services"
      }
    ],
    "sg:phone": "+1 978 887 2133",
    "sg:postcode": "01921",
    "sg:province": "MA",
    "sg:tags": [
      "marketing",
      "consultant"
    ],
    "sg:website": "www.hydrohandle.com",
    "wof:name": "Criston Corp",
    "wof:placetype": "venue"
  },
  "geometry": {"coordinates":[-70.994669,42.682634],"type":"Point"}
}
