{
  "type": "Feature",
  "properties": {
    "iso:country":"US",
    "sg:address":"487 Adams St",
    "sg:city":"Milton",
    "sg:classifiers":[
        {
            "category":"Professional",
            "subcategory":"Lawyer & Legal Services",
            "type":"Services"
        }
    ],
    "sg:phone":"+1 617 698 4100",
    "sg:postcode":"02186",
    "sg:province":"MA",
    "wof:name":"Thomas Guiney",
    "wof:placetype":"venue"
},
  "geometry": {"coordinates":[-71.042689,42.2587],"type":"Point"}
}