{
  "type": "Feature",
  "properties": {
    "iso:country":"US",
    "sg:address":"5 E Main St",
    "sg:city":"Westborough",
    "sg:classifiers":[
        {
            "category":"Banks & Credit Unions",
            "subcategory":"Investment Brokerage",
            "type":"Services"
        }
    ],
    "sg:phone":"+1 508 366 8802",
    "sg:postcode":"01581",
    "sg:province":"MA",
    "sg:tags":[
        "security"
    ],
    "wof:name":"RSI Asset Management",
    "wof:placetype":"venue"
},
  "geometry": {"coordinates":[-71.61294700000001,42.269825],"type":"Point"}
}