{
  "type": "Feature",
  "properties": {
    "addr:full": "136 Main St Watertown MA 02472",
    "addr:housenumber": "136",
    "addr:postcode": "02472",
    "addr:street": "Main St",
    "iso:country": "US",
    "ovtr:label": "Town Hall Shoe Repair, 136 Main St Watertown MA US",
    "ovtr:similarity": 1.898717999458313,
    "sg:address": "136 Main St",
    "sg:city": "Watertown",
    "sg:classifiers": [
      {
        "category": "Personal",
        "subcategory": "Shoe Repair \u0026 Shine",
        "type": "Services"
      }
    ],
    "sg:phone": "+1 617 923 4555",
    "sg:postcode": "02472",
    "sg:province": "MA",
    "sg:tags": [
      "parlor"
    ],
    "wof:name": "Town Hall Shoe Repair",
    "wof:placetype": "venue"
  },
  "geometry": {"coordinates":[-71.187709,42.367418],"type":"Point"}
}
