{
  "type": "Feature",
  "properties": {
    "addr:full":"14 E Plain St Wayland MA 01778",
    "addr:housenumber":"14",
    "addr:postcode":"01778",
    "addr:street":"E Plain St",
    "iso:country":"US",
    "sg:address":"14 E Plain St",
    "sg:city":"Wayland",
    "sg:classifiers":[
        {
            "category":"Shopping",
            "type":"Retail Goods"
        }
    ],
    "sg:phone":"+1 508 653 8251",
    "sg:postcode":"01778",
    "sg:province":"MA",
    "sg:tags":[
        "art",
        "gallery",
        "dealer"
    ],
    "wof:name":"Wayland Art Ctr",
    "wof:placetype":"venue"
},
  "geometry": {"coordinates":[-71.363992,42.321498],"type":"Point"}
}