{
  "type": "Feature",
  "properties": {
    "iso:country":"US",
    "sg:address":"Riverview II 18th Floor",
    "sg:city":"Cambridge",
    "sg:classifiers":[
        {
            "category":"Professional",
            "subcategory":"Computer Services",
            "type":"Services"
        }
    ],
    "sg:postcode":"02142",
    "sg:province":"MA",
    "sg:tags":[
        "deduplication-software",
        "data-matching-software",
        "dedupe-software",
        "data-deduplication",
        "merge-purge",
        "merge-database",
        "purge-database",
        "merge-purge-software",
        "data-deduplication-software",
        "dediplication"
    ],
    "sg:website":"http://www.dataladder.com/",
    "wof:name":"Data Ladder",
    "wof:placetype":"venue"
},
  "geometry": {"coordinates":[-70.93325900000001,42.25615],"type":"Point"}
}