{
  "type": "Feature",
  "properties": {
    "addr:full": "Riverview II 18th Floor Cambridge MA 02142",
    "addr:housenumber": "18th",
    "addr:postcode": "02142",
    "addr:street": "Floor",
    "iso:country": "US",
    "sg:address": "Riverview II 18th Floor",
    "sg:city": "Cambridge",
    "sg:classifiers": [
      {
        "category": "Professional",
        "subcategory": "Computer Services",
        "type": "Services"
      }
    ],
    "sg:postcode": "02142",
    "sg:province": "MA",
    "sg:tags": [
      "deduplication-software",
      "data-matching-software",
      "dedupe-software",
      "data-deduplication",
      "merge-purge",
      "merge-database",
      "purge-database",
      "merge-purge-software",
      "data-deduplication-software",
      "dediplication"
    ],
    "sg:website": "http://www.dataladder.com/",
    "wof:name": "Data Ladder",
    "wof:placetype": "venue"
  },
  "geometry": {"coordinates":[-70.933259,42.25615],"type":"Point"}
}
