{
  "type": "Feature",
  "properties": {
    "iso:country":"US",
    "sg:address":"919 Winthrop Ave",
    "sg:city":"Revere",
    "sg:classifiers":[
        {
            "category":"Manufacturing",
            "subcategory":"Printing",
            "type":"Manufacturing & Wholesale Goods"
        }
    ],
    "sg:phone":"+1 781 289 9242",
    "sg:postcode":"02151",
    "sg:province":"MA",
    "sg:tags":[
        "printer"
    ],
    "sg:website":"www.northrupprinting.com",
    "wof:name":"Northrup Printing",
    "wof:placetype":"venue"
},
  "geometry": {"coordinates":[-70.9854,42.394459],"type":"Point"}
}