{
  "type": "Feature",
  "properties": {
    "addr:full": "276 W Main St Northborough MA 01532",
    "addr:housenumber": "276",
    "addr:postcode": "01532",
    "addr:street": "W Main St",
    "iso:country": "US",
    "sg:address": "276 W Main St",
    "sg:city": "Northborough",
    "sg:classifiers": [
      {
        "category": "Personal",
        "subcategory": "Beauty Salon",
        "type": "Services"
      }
    ],
    "sg:phone": "+1 508 393 9242",
    "sg:postcode": "01532",
    "sg:province": "MA",
    "wof:name": "Studio West Hair Design",
    "wof:placetype": "venue"
  },
  "geometry": {"coordinates":[-71.65648,42.308785],"type":"Point"}
}
