{
  "type": "Feature",
  "properties": {
    "addr:full": "519 Foundry St North Easton MA 02356",
    "addr:housenumber": "519",
    "addr:postcode": "02356",
    "addr:street": "Foundry St",
    "iso:country": "US",
    "sg:address": "519 Foundry St",
    "sg:city": "North Easton",
    "sg:classifiers": [
      {
        "category": "Sports \u0026 Exercise",
        "subcategory": "Gym",
        "type": "Entertainment"
      }
    ],
    "sg:phone": "+1 508 219 4033",
    "sg:postcode": "02356",
    "sg:province": "MA",
    "sg:tags": [
      "trainer"
    ],
    "sg:website": "www.one2onebodyscapes.com/easton/",
    "wof:name": "One2One Bodyscapes",
    "wof:placetype": "venue"
  },
  "geometry": {"coordinates":[-71.125061,42.024281],"type":"Point"}
}
