{
  "type": "Feature",
  "properties": {
    "iso:country":"US",
    "sg:address":"5 Academy Hill Rd",
    "sg:city":"Conway",
    "sg:classifiers":[
        {
            "category":"Government",
            "subcategory":"Office",
            "type":"Public Place"
        }
    ],
    "sg:phone":"+1 413 369 4773",
    "sg:postcode":"01341",
    "sg:province":"MA",
    "sg:tags":[
        "city",
        "program",
        "health"
    ],
    "wof:name":"Conway Board Of Health",
    "wof:placetype":"venue"
},
  "geometry": {"coordinates":[-72.69616499999999,42.50806],"type":"Point"}
}