{
  "type": "Feature",
  "properties": {
    "addr:full": "20 Kersey Rd Foxboro MA 02035",
    "addr:housenumber": "20",
    "addr:postcode": "02035",
    "addr:street": "Kersey Rd",
    "iso:country": "US",
    "sg:address": "20 Kersey Rd",
    "sg:city": "Foxboro",
    "sg:classifiers": [
      {
        "category": "Shopping",
        "type": "Retail Goods"
      }
    ],
    "sg:phone": "+1 508 543 1562",
    "sg:postcode": "02035",
    "sg:province": "MA",
    "sg:tags": [
      "awning",
      "canopy"
    ],
    "wof:name": "Boston Awning Co",
    "wof:placetype": "venue"
  },
  "geometry": {"coordinates":[-71.247696,42.078502],"type":"Point"}
}
