{
  "type": "Feature",
  "properties": {
    "addr:full":"126 South St Hingham MA 02043",
    "addr:housenumber":"126",
    "addr:postcode":"02043",
    "addr:street":"South St",
    "iso:country":"US",
    "sg:address":"126 South St",
    "sg:city":"Hingham",
    "sg:classifiers":[
        {
            "category":"Professional",
            "subcategory":"Lawyer & Legal Services",
            "type":"Services"
        }
    ],
    "sg:phone":"+1 781 749 6512",
    "sg:postcode":"02043",
    "sg:province":"MA",
    "sg:tags":[
        "attorney"
    ],
    "wof:name":"Kathryn Connolly-Chase Lwyr",
    "wof:placetype":"venue"
},
  "geometry": {"coordinates":[-70.89241,42.240898],"type":"Point"}
}