{
  "type": "Feature",
  "properties": {
    "iso:country":"US",
    "sg:address":"210 W Main St",
    "sg:city":"Dudley",
    "sg:classifiers":[
        {
            "category":"Food & Beverages",
            "subcategory":"Groceries & Convenience Stores",
            "type":"Retail Goods"
        }
    ],
    "sg:phone":"+1 508 671 9003",
    "sg:postcode":"01571",
    "sg:province":"MA",
    "sg:tags":[
        "grocer"
    ],
    "wof:name":"Park 'n Shop Office",
    "wof:placetype":"venue"
},
  "geometry": {"coordinates":[-71.916003,42.038543],"type":"Point"}
}