{
  "type": "Feature",
  "properties": {
    "iso:country":"US",
    "sg:address":"73 Tremont St Ste 600",
    "sg:city":"Boston",
    "sg:classifiers":[
        {
            "category":"Real Estate",
            "subcategory":"Real Estate Services",
            "type":"Services"
        },
        {
            "category":"Real Estate",
            "subcategory":"Real Estate Agent",
            "type":"Services"
        }
    ],
    "sg:phone":"+1 617 742 3379",
    "sg:postcode":"02108",
    "sg:province":"MA",
    "sg:tags":[
        "buyer",
        "broker"
    ],
    "wof:name":"Tremont Realty Development",
    "wof:placetype":"venue"
},
  "geometry": {"coordinates":[-71.060463,42.35799],"type":"Point"}
}