{
  "type": "Feature",
  "properties": {
    "iso:country":"US",
    "sg:address":"55 Hunnewell St",
    "sg:city":"Wellesley",
    "sg:classifiers":[
        {
            "category":"Building & Trades",
            "subcategory":"Construction",
            "type":"Services"
        }
    ],
    "sg:phone":"+1 781 235 0345",
    "sg:postcode":"02481",
    "sg:province":"MA",
    "sg:tags":[
        "painter"
    ],
    "wof:name":"Donahue Brothers",
    "wof:placetype":"venue"
},
  "geometry": {"coordinates":[-71.245468,42.308972],"type":"Point"}
}