{
  "type": "Feature",
  "properties": {
    "addr:full": "400 Washington St Ste Ll9 Braintree MA 02184",
    "addr:housenumber": "400",
    "addr:postcode": "02184",
    "addr:street": "Washington St Ste Ll9",
    "iso:country": "US",
    "sg:address": "400 Washington St Ste Ll9",
    "sg:city": "Braintree",
    "sg:classifiers": [
      {
        "category": "Real Estate",
        "subcategory": "Surveying",
        "type": "Services"
      }
    ],
    "sg:phone": "+1 781 794 6800",
    "sg:postcode": "02184",
    "sg:province": "MA",
    "sg:tags": [
      "surveyor",
      "land",
      "engineer"
    ],
    "wof:name": "Decelle Engineering \u0026 Survey Co Inc",
    "wof:placetype": "venue"
  },
  "geometry": {"coordinates":[-71.0034,42.219018],"type":"Point"}
}
