{
  "type": "Feature",
  "properties": {
    "iso:country":"US",
    "sg:address":"309 Cambridge St",
    "sg:city":"Worcester",
    "sg:classifiers":[
        {
            "category":"Organizations",
            "subcategory":"Professional Association",
            "type":"Services"
        }
    ],
    "sg:phone":"+1 508 754 6012",
    "sg:postcode":"01603",
    "sg:province":"MA",
    "wof:name":"Us Cross Cultural Assn Inc",
    "wof:placetype":"venue"
},
  "geometry": {"coordinates":[-71.817905,42.243658],"type":"Point"}
}