{
  "type": "Feature",
  "properties": {
    "addr:full": "247 Mill St Leominster MA 01453",
    "addr:housenumber": "247",
    "addr:postcode": "01453",
    "addr:street": "Mill St",
    "iso:country": "US",
    "ovtr:label": "McDonald's, 247 Mill St Leominster MA US",
    "ovtr:similarity": 3.0937650203704834,
    "sg:address": "247 Mill St",
    "sg:city": "Leominster",
    "sg:classifiers": [
      {
        "category": "Restaurant",
        "type": "Food \u0026 Drink"
      }
    ],
    "sg:phone": "+1   ",
    "sg:postcode": "01453",
    "sg:province": "MA",
    "sg:tags": [
      "eating"
    ],
    "wof:name": "McDonalds",
    "wof:placetype": "venue"
  },
  "geometry": {"coordinates":[-71.745846,42.532972],"type":"Point"}
}
