{
  "type": "Feature",
  "properties": {
    "iso:country":"US",
    "sg:address":"37 Main St",
    "sg:city":"Kingston",
    "sg:classifiers":[
        {
            "category":"Autos & Motor Vehicles",
            "subcategory":"Fuel & Gas Station",
            "type":"Retail Goods"
        }
    ],
    "sg:phone":"+1 508 746 9815",
    "sg:postcode":"02364",
    "sg:province":"MA",
    "sg:tags":[
        "oil"
    ],
    "wof:name":"Fred's Kingston Texaco",
    "wof:placetype":"venue"
},
  "geometry": {"coordinates":[-70.701413,41.98401],"type":"Point"}
}