{
  "type": "Feature",
  "properties": {
    "iso:country":"US",
    "sg:address":"5 Masonic Pl",
    "sg:city":"Provincetown",
    "sg:classifiers":[
        {
            "category":"Restaurant",
            "type":"Food & Drink"
        }
    ],
    "sg:phone":"+1 508 487 7599",
    "sg:postcode":"02657",
    "sg:province":"MA",
    "sg:tags":[
        "eating"
    ],
    "wof:name":"Grand Central Cafe",
    "wof:placetype":"venue"
},
  "geometry": {"coordinates":[-70.188428,42.049808],"type":"Point"}
}