{
  "type": "Feature",
  "properties": {
    "addr:full":"101 Lindberg Ave Methuen MA 01844",
    "addr:housenumber":"101",
    "addr:postcode":"01844",
    "addr:street":"Lindberg Ave",
    "iso:country":"US",
    "sg:address":"101 Lindberg Ave",
    "sg:city":"Methuen",
    "sg:classifiers":[
        {
            "category":"Building & Trades",
            "subcategory":"Construction",
            "type":"Services"
        }
    ],
    "sg:phone":"+1 978 686 4500",
    "sg:postcode":"01844",
    "sg:province":"MA",
    "sg:tags":[
        "pavement",
        "marking"
    ],
    "sg:website":"www.ejpaving.com",
    "wof:name":"E J Paving Co",
    "wof:placetype":"venue"
},
  "geometry": {"coordinates":[-71.208067,42.718878],"type":"Point"}
}