{
  "type": "Feature",
  "properties": {
    "addr:full": "2 Kenasaoome Way Chilmark MA 02535",
    "addr:housenumber": "2",
    "addr:postcode": "02535",
    "addr:street": "Kenasaoome Way",
    "iso:country": "US",
    "sg:address": "2 Kenasaoome Way",
    "sg:city": "Chilmark",
    "sg:classifiers": [
      {
        "category": "Manufacturing",
        "subcategory": "Printing",
        "type": "Manufacturing \u0026 Wholesale Goods"
      }
    ],
    "sg:phone": "+1 508 645 3700",
    "sg:postcode": "02535",
    "sg:province": "MA",
    "sg:tags": [
      "publisher"
    ],
    "wof:name": "Three Ring Info",
    "wof:placetype": "venue"
  },
  "geometry": {"coordinates":[-70.68085,41.3679],"type":"Point"}
}
