{
  "type": "Feature",
  "properties": {
    "iso:country":"US",
    "sg:address":"2 Kenasaoome Way",
    "sg:city":"Chilmark",
    "sg:classifiers":[
        {
            "category":"Manufacturing",
            "subcategory":"Printing",
            "type":"Manufacturing & Wholesale Goods"
        }
    ],
    "sg:phone":"+1 508 645 3700",
    "sg:postcode":"02535",
    "sg:province":"MA",
    "sg:tags":[
        "publisher"
    ],
    "wof:name":"Three Ring Info",
    "wof:placetype":"venue"
},
  "geometry": {"coordinates":[-70.68085000000001,41.3679],"type":"Point"}
}