{
  "type": "Feature",
  "properties": {
    "iso:country":"US",
    "sg:address":"249 Vanderbilt Ave",
    "sg:city":"Norwood",
    "sg:classifiers":[
        {
            "category":"Manufacturing",
            "subcategory":"Tools & Machinery",
            "type":"Manufacturing & Wholesale Goods"
        }
    ],
    "sg:phone":"+1 781 461 9700",
    "sg:postcode":"02062",
    "sg:province":"MA",
    "sg:tags":[
        "surgical",
        "appliance"
    ],
    "wof:name":"Mitek Worldwide",
    "wof:placetype":"venue"
},
  "geometry": {"coordinates":[-71.186837,42.169692],"type":"Point"}
}