{
  "type": "Feature",
  "properties": {
    "iso:country":"US",
    "sg:address":"37 Meadowbrook Ln",
    "sg:city":"Hampden",
    "sg:classifiers":[
        {
            "category":"Building & Trades",
            "subcategory":"Construction",
            "type":"Services"
        }
    ],
    "sg:phone":"+1 413 566 3000",
    "sg:postcode":"01036",
    "sg:province":"MA",
    "sg:tags":[
        "painter"
    ],
    "wof:name":"Timothy Bresnahan Painting",
    "wof:placetype":"venue"
},
  "geometry": {"coordinates":[-72.440893,42.056193],"type":"Point"}
}