{
  "type": "Feature",
  "properties": {
    "iso:country":"US",
    "sg:address":"126 Elm St",
    "sg:city":"Methuen",
    "sg:classifiers":[
        {
            "category":"Building & Trades",
            "subcategory":"Construction",
            "type":"Services"
        }
    ],
    "sg:phone":"+1 978 682 2779",
    "sg:postcode":"01844",
    "sg:province":"MA",
    "sg:tags":[
        "roofing",
        "contractor"
    ],
    "wof:name":"John Jennings Co Inc",
    "wof:placetype":"venue"
},
  "geometry": {"coordinates":[-71.19694,42.713939],"type":"Point"}
}