{
  "type": "Feature",
  "properties": {
    "addr:full":"67 Belmont St Ste 302 Worcester MA 01605",
    "addr:housenumber":"67",
    "addr:postcode":"01605",
    "addr:street":"Belmont St Ste 302",
    "iso:country":"US",
    "sg:address":"67 Belmont St Ste 302",
    "sg:city":"Worcester",
    "sg:classifiers":[
        {
            "category":"Health Services",
            "subcategory":"Doctor",
            "type":"Services"
        },
        {
            "category":"Health Services",
            "subcategory":"Health Practitioner",
            "type":"Services"
        }
    ],
    "sg:phone":"+1 508 752 1155",
    "sg:postcode":"01605",
    "sg:province":"MA",
    "sg:tags":[
        "physician",
        "laser",
        "surgeons",
        "ophthalmology",
        "surgeon",
        "surgery",
        "surgery-general"
    ],
    "wof:name":"Vitreo Retinal Associates of Worcester PC",
    "wof:placetype":"venue"
},
  "geometry": {"coordinates":[-71.796947,42.271608],"type":"Point"}
}