{
  "type": "Feature",
  "properties": {
    "addr:full": "99 St Botolph St Boston MA 02116",
    "addr:housenumber": "99",
    "addr:postcode": "02116",
    "addr:street": "St Botolph St",
    "iso:country": "US",
    "sg:address": "99 St Botolph St",
    "sg:city": "Boston",
    "sg:classifiers": [
      {
        "category": "Travel",
        "subcategory": "Hotels \u0026 Motels",
        "type": "Entertainment"
      }
    ],
    "sg:phone": "+1 617 236 8099",
    "sg:postcode": "02116",
    "sg:province": "MA",
    "sg:website": "www.innatstbotolph.com",
    "wof:name": "Inn @ St. Botolph",
    "wof:placetype": "venue"
  },
  "geometry": {"coordinates":[-71.080826,42.34501],"type":"Point"}
}
