{
  "type": "Feature",
  "properties": {
    "iso:country":"US",
    "sg:address":"99 St Botolph St",
    "sg:city":"Boston",
    "sg:classifiers":[
        {
            "category":"Travel",
            "subcategory":"Hotels & Motels",
            "type":"Entertainment"
        }
    ],
    "sg:phone":"+1 617 236 8099",
    "sg:postcode":"02116",
    "sg:province":"MA",
    "sg:website":"www.innatstbotolph.com",
    "wof:name":"Inn @ St. Botolph",
    "wof:placetype":"venue"
},
  "geometry": {"coordinates":[-71.080826,42.34501],"type":"Point"}
}