{
  "type": "Feature",
  "properties": {
    "iso:country":"US",
    "sg:address":"115 Mount Auburn St",
    "sg:city":"Watertown",
    "sg:classifiers":[
        {
            "category":"Professional",
            "subcategory":"Computer Services",
            "type":"Services"
        }
    ],
    "sg:phone":"+1 617 923 6020",
    "sg:postcode":"02472",
    "sg:province":"MA",
    "sg:tags":[
        "repair"
    ],
    "wof:name":"Boston Computer Connection",
    "wof:placetype":"venue"
},
  "geometry": {"coordinates":[-71.179078,42.367753],"type":"Point"}
}