{
  "type": "Feature",
  "properties": {
    "addr:full": "54 Barton Ave Belchertown MA 01007",
    "addr:housenumber": "54",
    "addr:postcode": "01007",
    "addr:street": "Barton Ave",
    "iso:country": "US",
    "sg:address": "54 Barton Ave",
    "sg:city": "Belchertown",
    "sg:classifiers": [
      {
        "category": "Health Services",
        "subcategory": "Clinic",
        "type": "Services"
      }
    ],
    "sg:phone": "+1 413 323 9700",
    "sg:postcode": "01007",
    "sg:province": "MA",
    "sg:tags": [
      "home"
    ],
    "wof:name": "Home Helpers Direct Link",
    "wof:placetype": "venue"
  },
  "geometry": {"coordinates":[-72.444799,42.264555],"type":"Point"}
}
