{
  "type": "Feature",
  "properties": {
    "iso:country":"US",
    "sg:address":"228 Billerica Rd",
    "sg:city":"Chelmsford",
    "sg:classifiers":[
        {
            "category":"Health Services",
            "subcategory":"Doctor",
            "type":"Services"
        }
    ],
    "sg:phone":"+1 978 250 6100",
    "sg:postcode":"01824",
    "sg:province":"MA",
    "wof:name":"Larson Lucia MD",
    "wof:placetype":"venue"
},
  "geometry": {"coordinates":[-71.332802,42.597801],"type":"Point"}
}