{
  "type": "Feature",
  "properties": {
    "addr:full": "14 Juniper St Wenham MA 01984",
    "addr:housenumber": "14",
    "addr:postcode": "01984",
    "addr:street": "Juniper St",
    "iso:country": "US",
    "sg:address": "14 Juniper St",
    "sg:city": "Wenham",
    "sg:classifiers": [
      {
        "category": "Professional",
        "subcategory": "Management \u0026 Consulting",
        "type": "Services"
      }
    ],
    "sg:phone": "+1   ",
    "sg:postcode": "01984",
    "sg:province": "MA",
    "sg:tags": [
      "business"
    ],
    "wof:name": "Pgm Consulting Inc",
    "wof:placetype": "venue"
  },
  "geometry": {"coordinates":[-70.8887,42.611574],"type":"Point"}
}
