{
  "type": "Feature",
  "properties": {
    "addr:full":"694 County St Attleboro MA 02703",
    "addr:housenumber":"694",
    "addr:postcode":"02703",
    "addr:street":"County St",
    "iso:country":"US",
    "sg:address":"694 County St",
    "sg:city":"Attleboro",
    "sg:classifiers":[
        {
            "category":"Building & Trades",
            "subcategory":"Construction",
            "type":"Services"
        }
    ],
    "sg:phone":"+1 508 222 6706",
    "sg:postcode":"02703",
    "sg:province":"MA",
    "sg:tags":[
        "contractor",
        "painting",
        "hanging"
    ],
    "wof:name":"Laviolette Painting",
    "wof:placetype":"venue"
},
  "geometry": {"coordinates":[-71.301231,41.931721],"type":"Point"}
}