{
  "type": "Feature",
  "properties": {
    "addr:full": "5 Post Office Sq Ste 5 Sharon MA 02067",
    "addr:housenumber": "5",
    "addr:postcode": "02067",
    "addr:street": "Post Office Sq Ste 5",
    "iso:country": "US",
    "sg:address": "5 Post Office Sq Ste 5",
    "sg:city": "Sharon",
    "sg:classifiers": [
      {
        "category": "Professional",
        "subcategory": "Lawyer \u0026 Legal Services",
        "type": "Services"
      }
    ],
    "sg:phone": "+1 781 784 0014",
    "sg:postcode": "02067",
    "sg:province": "MA",
    "wof:name": "Watstein Law Offices",
    "wof:placetype": "venue"
  },
  "geometry": {"coordinates":[-71.178959,42.123532],"type":"Point"}
}
