{
  "type": "Feature",
  "properties": {
    "iso:country":"US",
    "sg:address":"5 Post Office Sq Ste 5",
    "sg:city":"Sharon",
    "sg:classifiers":[
        {
            "category":"Professional",
            "subcategory":"Lawyer & Legal Services",
            "type":"Services"
        }
    ],
    "sg:phone":"+1 781 784 0014",
    "sg:postcode":"02067",
    "sg:province":"MA",
    "wof:name":"Watstein Law Offices",
    "wof:placetype":"venue"
},
  "geometry": {"coordinates":[-71.17895900000001,42.123532],"type":"Point"}
}