{
  "type": "Feature",
  "properties": {
    "addr:full":"46 Main St Maynard MA 01754",
    "addr:housenumber":"46",
    "addr:postcode":"01754",
    "addr:street":"Main St",
    "iso:country":"US",
    "sg:address":"46 Main St",
    "sg:city":"Maynard",
    "sg:classifiers":[
        {
            "category":"Restaurant",
            "type":"Food & Drink"
        }
    ],
    "sg:phone":"+1 978 897 8995",
    "sg:postcode":"01754",
    "sg:province":"MA",
    "wof:name":"Mc Donald's",
    "wof:placetype":"venue"
},
  "geometry": {"coordinates":[-71.45194600000001,42.432462],"type":"Point"}
}