{
  "type": "Feature",
  "properties": {
    "iso:country":"US",
    "sg:address":"1101 Beacon St",
    "sg:city":"Brookline",
    "sg:classifiers":[
        {
            "category":"Health Services",
            "subcategory":"Doctor",
            "type":"Services"
        }
    ],
    "sg:phone":"+1 617 731 2220",
    "sg:postcode":"02446",
    "sg:province":"MA",
    "sg:tags":[
        "physician",
        "surgeons",
        "psychologist",
        "psychiatry",
        "surgeon"
    ],
    "wof:name":"Dr Alexandra Psych Beckett",
    "wof:placetype":"venue"
},
  "geometry": {"coordinates":[-71.11084700000001,42.344872],"type":"Point"}
}