{
  "type": "Feature",
  "properties": {
    "iso:country":"US",
    "sg:address":"311 Old Meeting House Rd",
    "sg:city":"East Falmouth",
    "sg:classifiers":[
        {
            "category":"Building & Trades",
            "subcategory":"Plumbing",
            "type":"Services"
        }
    ],
    "sg:phone":"+1 508 548 4582",
    "sg:postcode":"02536",
    "sg:province":"MA",
    "wof:name":"Johnson Del Plumbing & Heating",
    "wof:placetype":"venue"
},
  "geometry": {"coordinates":[-70.56424,41.593155],"type":"Point"}
}