{
  "type": "Feature",
  "properties": {
    "addr:full": "311 Old Meeting House Rd East Falmouth MA 02536",
    "addr:housenumber": "311",
    "addr:postcode": "02536",
    "addr:street": "Old Meeting House Rd",
    "iso:country": "US",
    "sg:address": "311 Old Meeting House Rd",
    "sg:city": "East Falmouth",
    "sg:classifiers": [
      {
        "category": "Building \u0026 Trades",
        "subcategory": "Plumbing",
        "type": "Services"
      }
    ],
    "sg:phone": "+1 508 548 4582",
    "sg:postcode": "02536",
    "sg:province": "MA",
    "wof:name": "Johnson Del Plumbing \u0026 Heating",
    "wof:placetype": "venue"
  },
  "geometry": {"coordinates":[-70.56424,41.593155],"type":"Point"}
}
