{
  "type": "Feature",
  "properties": {
    "addr:full": "605 Dorchester Ave Boston MA 02127",
    "addr:housenumber": "605",
    "addr:postcode": "02127",
    "addr:street": "Dorchester Ave",
    "iso:country": "US",
    "ovtr:label": "Andrew Square Liquors, 605 Dorchester Ave Boston MA US",
    "ovtr:similarity": 2.0250179767608643,
    "sg:address": "605 Dorchester Ave",
    "sg:city": "Boston",
    "sg:classifiers": [
      {
        "category": "Food \u0026 Beverages",
        "subcategory": "Liquor \u0026 Beverages",
        "type": "Retail Goods"
      }
    ],
    "sg:phone": "+1 617 269 0705",
    "sg:postcode": "02127",
    "sg:province": "MA",
    "wof:name": "Andrew Square Liquors",
    "wof:placetype": "venue"
  },
  "geometry": {"coordinates":[-71.057015,42.329028],"type":"Point"}
}
