{
  "type": "Feature",
  "properties": {
    "addr:full":"605 Dorchester Ave Boston MA 02127",
    "addr:housenumber":"605",
    "addr:postcode":"02127",
    "addr:street":"Dorchester Ave",
    "iso:country":"US",
    "sg:address":"605 Dorchester Ave",
    "sg:city":"Boston",
    "sg:classifiers":[
        {
            "category":"Food & Beverages",
            "subcategory":"Liquor & Beverages",
            "type":"Retail Goods"
        }
    ],
    "sg:phone":"+1 617 269 0705",
    "sg:postcode":"02127",
    "sg:province":"MA",
    "wof:name":"Andrew Square Liquors",
    "wof:placetype":"venue"
},
  "geometry": {"coordinates":[-71.05701500000001,42.329028],"type":"Point"}
}