{
  "type": "Feature",
  "properties": {
    "iso:country":"US",
    "sg:address":"14 S Deerfield Byp",
    "sg:city":"South Deerfield",
    "sg:classifiers":[
        {
            "category":"Insurance",
            "subcategory":"Insurance Agent",
            "type":"Services"
        }
    ],
    "sg:phone":"+1 413 665 4097",
    "sg:postcode":"01373",
    "sg:province":"MA",
    "wof:name":"New York Life Insurance Co",
    "wof:placetype":"venue"
},
  "geometry": {"coordinates":[-72.61461,42.471157],"type":"Point"}
}