{
  "type": "Feature",
  "properties": {
    "iso:country":"US",
    "sg:address":"1106 Blue Hill Ave",
    "sg:city":"Dorchester Ctr",
    "sg:classifiers":[
        {
            "category":"Retail",
            "subcategory":"Auto Repair",
            "type":"Services"
        }
    ],
    "sg:phone":"+1 617 265 1613",
    "sg:postcode":"02124",
    "sg:province":"MA",
    "sg:tags":[
        "repairing",
        "automobile"
    ],
    "wof:name":"M & J Auto Repair",
    "wof:placetype":"venue"
},
  "geometry": {"coordinates":[-71.09057799999999,42.286553],"type":"Point"}
}