{
  "type": "Feature",
  "properties": {
    "iso:country":"US",
    "sg:address":"345 Bone Hill Rd",
    "sg:city":"Barnstable",
    "sg:classifiers":[
        {
            "category":"Professional",
            "type":"Services"
        }
    ],
    "sg:phone":"+1 508 362 7475",
    "sg:postcode":"02637",
    "sg:province":"MA",
    "sg:tags":[
        "establishment"
    ],
    "wof:name":"Ma Audubon Coastal Waterbird",
    "wof:placetype":"venue"
},
  "geometry": {"coordinates":[-70.27516300000001,41.709428],"type":"Point"}
}