{
  "type": "Feature",
  "properties": {
    "addr:full": "15 Bay Ter Plymouth MA 02360",
    "addr:housenumber": "15",
    "addr:postcode": "02360",
    "addr:street": "Bay Ter",
    "iso:country": "US",
    "sg:address": "15 Bay Ter",
    "sg:city": "Plymouth",
    "sg:classifiers": [
      {
        "category": "Taxi",
        "type": "Transportation"
      }
    ],
    "sg:phone": "+1 508 224 7107",
    "sg:postcode": "02360",
    "sg:province": "MA",
    "sg:tags": [
      "taxicab"
    ],
    "wof:name": "Manomet Taxi",
    "wof:placetype": "venue"
  },
  "geometry": {"coordinates":[-70.538104,41.890447],"type":"Point"}
}
