{
  "type": "Feature",
  "properties": {
    "iso:country":"US",
    "sg:address":"80 Lowell St",
    "sg:city":"Peabody",
    "sg:classifiers":[
        {
            "category":"Professional",
            "subcategory":"Lawyer & Legal Services",
            "type":"Services"
        }
    ],
    "sg:phone":"+1 978 531 6363",
    "sg:postcode":"01960",
    "sg:province":"MA",
    "sg:tags":[
        "attorney"
    ],
    "wof:name":"Mary-Ellen Manning",
    "wof:placetype":"venue"
},
  "geometry": {"coordinates":[-70.93153100000001,42.527198],"type":"Point"}
}