{
  "type": "Feature",
  "properties": {
    "addr:full": "80 Lowell St Peabody MA 01960",
    "addr:housenumber": "80",
    "addr:postcode": "01960",
    "addr:street": "Lowell St",
    "iso:country": "US",
    "sg:address": "80 Lowell St",
    "sg:city": "Peabody",
    "sg:classifiers": [
      {
        "category": "Professional",
        "subcategory": "Lawyer \u0026 Legal Services",
        "type": "Services"
      }
    ],
    "sg:phone": "+1 978 531 6363",
    "sg:postcode": "01960",
    "sg:province": "MA",
    "sg:tags": [
      "attorney"
    ],
    "wof:name": "Mary-Ellen Manning",
    "wof:placetype": "venue"
  },
  "geometry": {"coordinates":[-70.931531,42.527198],"type":"Point"}
}
