{
  "type": "Feature",
  "properties": {
    "iso:country":"US",
    "sg:address":"90 Rte 6a",
    "sg:city":"Sandwich",
    "sg:classifiers":[
        {
            "category":"Social Services",
            "subcategory":"Adult Care",
            "type":"Services"
        }
    ],
    "sg:phone":"+1 508 888 7138",
    "sg:postcode":"02563",
    "sg:province":"MA",
    "sg:tags":[
        "organization",
        "senior",
        "citizen"
    ],
    "wof:name":"Case Management Professionals",
    "wof:placetype":"venue"
},
  "geometry": {"coordinates":[-70.50099299999999,41.764925],"type":"Point"}
}