{
  "type": "Feature",
  "properties": {
    "addr:full":"21 Bow St Union Square Acupuncture 21 Bow Street Somerville MA 02143",
    "addr:housenumber":"21;21",
    "addr:postcode":"02143",
    "addr:street":"Bow St;Bow Street",
    "iso:country":"US",
    "sg:address":"21 Bow St Union Square Acupuncture 21 Bow Street",
    "sg:city":"Somerville",
    "sg:classifiers":[
        {
            "category":"Personal",
            "subcategory":"Massage",
            "type":"Services"
        },
        {
            "category":"Health Services",
            "subcategory":"Clinic",
            "type":"Services"
        }
    ],
    "sg:phone":"+1 617 680 7597",
    "sg:postcode":"02143",
    "sg:province":"MA",
    "sg:tags":[
        "medical"
    ],
    "sg:website":"www.deftherapeuticbodywork.com",
    "wof:name":"DEFTherapeutic Bodywork & Massage",
    "wof:placetype":"venue"
},
  "geometry": {"coordinates":[-71.097207,42.381444],"type":"Point"}
}