{
  "type": "Feature",
  "properties": {
    "iso:country":"US",
    "sg:address":"449 Marlborough St",
    "sg:city":"Boston",
    "sg:classifiers":[
        {
            "category":"Professional",
            "subcategory":"Computer Services",
            "type":"Services"
        }
    ],
    "sg:phone":"+1 617 266 9613",
    "sg:postcode":"02115",
    "sg:province":"MA",
    "sg:tags":[
        "web",
        "design",
        "site",
        "software"
    ],
    "sg:website":"http://www.arpados.com",
    "wof:name":"Arpados Inc",
    "wof:placetype":"venue"
},
  "geometry": {"coordinates":[-71.090952,42.349712],"type":"Point"}
}