{
  "type": "Feature",
  "properties": {
    "addr:full":"1454 Main St Walpole MA 02081",
    "addr:housenumber":"1454",
    "addr:postcode":"02081",
    "addr:street":"Main St",
    "iso:country":"US",
    "sg:address":"1454 Main St",
    "sg:city":"Walpole",
    "sg:classifiers":[
        {
            "category":"Building & Trades",
            "subcategory":"Landscaping Services",
            "type":"Services"
        }
    ],
    "sg:phone":"+1 508 668 5296",
    "sg:postcode":"02081",
    "sg:province":"MA",
    "sg:tags":[
        "landscape",
        "contractor"
    ],
    "wof:name":"Matz Landscape Co",
    "wof:placetype":"venue"
},
  "geometry": {"coordinates":[-71.26315200000001,42.131392],"type":"Point"}
}