{
  "type": "Feature",
  "properties": {
    "addr:full":"545 Lampblack Rd Greenfield MA 01301",
    "addr:housenumber":"545",
    "addr:postcode":"01301",
    "addr:street":"Lampblack Rd",
    "iso:country":"US",
    "sg:address":"545 Lampblack Rd",
    "sg:city":"Greenfield",
    "sg:classifiers":[
        {
            "category":"Building & Trades",
            "subcategory":"Construction",
            "type":"Services"
        }
    ],
    "sg:phone":"+1 413 774 7648",
    "sg:postcode":"01301",
    "sg:province":"MA",
    "sg:tags":[
        "general",
        "contractor"
    ],
    "wof:name":"Peter A Burakiewicz",
    "wof:placetype":"venue"
},
  "geometry": {"coordinates":[-72.550388,42.642571],"type":"Point"}
}