{
  "type": "Feature",
  "properties": {
    "iso:country":"US",
    "sg:address":"1252 Springfield St",
    "sg:city":"Feeding Hills",
    "sg:classifiers":[
        {
            "category":"Food & Beverages",
            "subcategory":"Fruits & Vegetables",
            "type":"Retail Goods"
        }
    ],
    "sg:phone":"+1 413 786 2188",
    "sg:postcode":"01030",
    "sg:province":"MA",
    "sg:tags":[
        "produce"
    ],
    "wof:name":"Cincotta Farms",
    "wof:placetype":"venue"
},
  "geometry": {"coordinates":[-72.67025,42.068415],"type":"Point"}
}