{
  "type": "Feature",
  "properties": {
    "iso:country":"US",
    "sg:address":"10 Balsam Dr",
    "sg:city":"Bedford",
    "sg:classifiers":[
        {
            "category":"Building & Trades",
            "subcategory":"Locksmith",
            "type":"Services"
        }
    ],
    "sg:phone":"+1 781 301 6021",
    "sg:postcode":"01730",
    "sg:province":"MA",
    "sg:tags":[
        "key"
    ],
    "wof:name":"24 Hour Bedford Available Locksmith",
    "wof:placetype":"venue"
},
  "geometry": {"coordinates":[-71.26034199999999,42.517519],"type":"Point"}
}