{
  "type": "Feature",
  "properties": {
    "addr:full": "10 Balsam Dr Bedford MA 01730",
    "addr:housenumber": "10",
    "addr:postcode": "01730",
    "addr:street": "Balsam Dr",
    "iso:country": "US",
    "sg:address": "10 Balsam Dr",
    "sg:city": "Bedford",
    "sg:classifiers": [
      {
        "category": "Building \u0026 Trades",
        "subcategory": "Locksmith",
        "type": "Services"
      }
    ],
    "sg:phone": "+1 781 301 6021",
    "sg:postcode": "01730",
    "sg:province": "MA",
    "sg:tags": [
      "key"
    ],
    "wof:name": "24 Hour Bedford Available Locksmith",
    "wof:placetype": "venue"
  },
  "geometry": {"coordinates":[-71.260342,42.517519],"type":"Point"}
}
