{
  "type": "Feature",
  "properties": {
    "addr:full": "300 Longwood Ave Boston MA 02115",
    "addr:housenumber": "300",
    "addr:postcode": "02115",
    "addr:street": "Longwood Ave",
    "iso:country": "US",
    "sg:address": "300 Longwood Ave",
    "sg:city": "Boston",
    "sg:classifiers": [
      {
        "category": "Wholesale",
        "subcategory": "Medical Equipment \u0026 Supplies",
        "type": "Manufacturing \u0026 Wholesale Goods"
      }
    ],
    "sg:phone": "+1 617 355 6887",
    "sg:postcode": "02115",
    "sg:province": "MA",
    "sg:tags": [
      "device",
      "prosthetic"
    ],
    "wof:name": "National Orthotics Prosthetics Co",
    "wof:placetype": "venue"
  },
  "geometry": {"coordinates":[-71.105288,42.337813],"type":"Point"}
}
