{
  "type": "Feature",
  "properties": {
    "iso:country":"US",
    "sg:address":"300 Longwood Ave",
    "sg:city":"Boston",
    "sg:classifiers":[
        {
            "category":"Wholesale",
            "subcategory":"Medical Equipment & Supplies",
            "type":"Manufacturing & Wholesale Goods"
        }
    ],
    "sg:phone":"+1 617 355 6887",
    "sg:postcode":"02115",
    "sg:province":"MA",
    "sg:tags":[
        "device",
        "prosthetic"
    ],
    "wof:name":"National Orthotics Prosthetics Co",
    "wof:placetype":"venue"
},
  "geometry": {"coordinates":[-71.105288,42.337813],"type":"Point"}
}