{
  "type": "Feature",
  "properties": {
    "addr:full":"3 Van de Graaff Drive Burlington MA 01803",
    "addr:housenumber":"3",
    "addr:postcode":"01803",
    "addr:street":"Van;Graaff Drive",
    "iso:country":"US",
    "sg:address":"3 Van de Graaff Drive",
    "sg:city":"Burlington",
    "sg:classifiers":[
        {
            "category":"Professional",
            "subcategory":"Computer Services",
            "type":"Services"
        }
    ],
    "sg:phone":"+1 781 761 6600",
    "sg:postcode":"01803",
    "sg:province":"MA",
    "sg:website":"http://www.streamserve.com/",
    "wof:name":"StreamServe",
    "wof:placetype":"venue"
},
  "geometry": {"coordinates":[-71.201222,42.482166],"type":"Point"}
}