{
  "type": "Feature",
  "properties": {
    "addr:full":"4 New St Worcester MA 01605",
    "addr:housenumber":"4",
    "addr:postcode":"01605",
    "addr:street":"New St",
    "iso:country":"US",
    "sg:address":"4 New St",
    "sg:city":"Worcester",
    "sg:classifiers":[
        {
            "category":"Wholesale",
            "subcategory":"Durable Goods & Equipment",
            "type":"Manufacturing & Wholesale Goods"
        }
    ],
    "sg:phone":"+1 508 755 5860",
    "sg:postcode":"01605",
    "sg:province":"MA",
    "sg:tags":[
        "importer"
    ],
    "wof:name":"Crossings",
    "wof:placetype":"venue"
},
  "geometry": {"coordinates":[-71.79469,42.284626],"type":"Point"}
}