{
  "type": "Feature",
  "properties": {
    "addr:full": "1383 Boylston St Boston MA 02215",
    "addr:housenumber": "1383",
    "addr:postcode": "02215",
    "addr:street": "Boylston St",
    "iso:country": "US",
    "sg:address": "1383 Boylston St",
    "sg:city": "Boston",
    "sg:classifiers": [
      {
        "category": "Professional",
        "type": "Services"
      }
    ],
    "sg:phone": "+1 617 536 4278",
    "sg:postcode": "02215",
    "sg:province": "MA",
    "sg:tags": [
      "establishment"
    ],
    "wof:name": "Lasting Impressions",
    "wof:placetype": "venue"
  },
  "geometry": {"coordinates":[-71.101346,42.343717],"type":"Point"}
}
