{
  "type": "Feature",
  "properties": {
    "iso:country":"US",
    "sg:address":"145 Globe St",
    "sg:city":"Fall River",
    "sg:classifiers":[
        {
            "category":"Real Estate",
            "subcategory":"Real Estate Agent",
            "type":"Services"
        }
    ],
    "sg:phone":"+1 508 646 0193",
    "sg:postcode":"02724",
    "sg:province":"MA",
    "wof:name":"Duckwillan",
    "wof:placetype":"venue"
},
  "geometry": {"coordinates":[-71.178665,41.689326],"type":"Point"}
}