{
  "type": "Feature",
  "properties": {
    "addr:full": "232 North Rd Bedford MA 01730",
    "addr:housenumber": "232",
    "addr:postcode": "01730",
    "addr:street": "North Rd",
    "iso:country": "US",
    "sg:address": "232 North Rd",
    "sg:city": "Bedford",
    "sg:classifiers": [
      {
        "category": "Professional",
        "subcategory": "Art Services",
        "type": "Services"
      }
    ],
    "sg:phone": "+1 781 687 9076",
    "sg:postcode": "01730",
    "sg:province": "MA",
    "sg:tags": [
      "graphic",
      "designer"
    ],
    "wof:name": "Lanna Ng Designs",
    "wof:placetype": "venue"
  },
  "geometry": {"coordinates":[-71.285153,42.508465],"type":"Point"}
}
