{
  "type": "Feature",
  "properties": {
    "iso:country":"US",
    "sg:address":"1062 Taunton Ave",
    "sg:city":"Seekonk",
    "sg:classifiers":[
        {
            "category":"Retail",
            "subcategory":"Photofinishing",
            "type":"Services"
        },
        {
            "category":"Retail",
            "subcategory":"Portrait Studio",
            "type":"Services"
        },
        {
            "category":"Professional",
            "subcategory":"Art Services",
            "type":"Services"
        }
    ],
    "sg:phone":"+1 508 336 4777",
    "sg:postcode":"02771",
    "sg:province":"MA",
    "sg:tags":[
        "rental",
        "photographers-portrait",
        "darkroom",
        "photo",
        "photography",
        "retouching",
        "restoration",
        "photographer",
        "photographic",
        "store"
    ],
    "sg:website":"www.chestnuthillstudios.com",
    "wof:name":"Chestnut Hill Studios Ltd",
    "wof:placetype":"venue"
},
  "geometry": {"coordinates":[-71.301903,41.8321],"type":"Point"}
}