{
  "type": "Feature",
  "properties": {
    "iso:country":"US",
    "sg:address":"6 Adamsville Rd",
    "sg:city":"Westport",
    "sg:classifiers":[
        {
            "category":"Shopping",
            "subcategory":"Clothing, Apparel, & Fashions",
            "type":"Retail Goods"
        }
    ],
    "sg:phone":"+1 508 636 3198",
    "sg:postcode":"02790",
    "sg:province":"MA",
    "sg:tags":[
        "tailor"
    ],
    "wof:name":"Tripp Tailoring",
    "wof:placetype":"venue"
},
  "geometry": {"coordinates":[-71.091663,41.573698],"type":"Point"}
}