{
  "type": "Feature",
  "properties": {
    "addr:full":"82 Hillside Ave 3 Rehoboth MA 02769",
    "addr:housenumber":"82;3",
    "addr:postcode":"02769",
    "addr:street":"Hillside Ave",
    "iso:country":"US",
    "sg:address":"82 Hillside Ave 3",
    "sg:city":"Rehoboth",
    "sg:classifiers":[
        {
            "category":"Transit Center",
            "subcategory":"Freight",
            "type":"Transportation"
        },
        {
            "category":"Freight",
            "type":"Transportation"
        }
    ],
    "sg:phone":"+1 508 252 1007",
    "sg:postcode":"02769",
    "sg:province":"MA",
    "sg:tags":[
        "trucking-motor",
        "trucking"
    ],
    "wof:name":"R. Carrier's, Inc.",
    "wof:placetype":"venue"
},
  "geometry": {"coordinates":[-71.27993499999999,41.85155],"type":"Point"}
}