{
  "type": "Feature",
  "properties": {
    "addr:full":"53 Gladstone St Quincy MA 02171",
    "addr:housenumber":"53",
    "addr:postcode":"02171",
    "addr:street":"Gladstone St",
    "iso:country":"US",
    "sg:address":"53 Gladstone St",
    "sg:city":"Quincy",
    "sg:classifiers":[
        {
            "category":"Professional",
            "subcategory":"Lawyer & Legal Services",
            "type":"Services"
        }
    ],
    "sg:phone":"+1 617 479 0676",
    "sg:postcode":"02171",
    "sg:province":"MA",
    "sg:tags":[
        "convention",
        "reporters-court"
    ],
    "wof:name":"Mennitto, John",
    "wof:placetype":"venue"
},
  "geometry": {"coordinates":[-71.00727500000001,42.299146],"type":"Point"}
}