{
  "type": "Feature",
  "properties": {
    "addr:full":"336 Poole St Ludlow MA 01056",
    "addr:housenumber":"336",
    "addr:postcode":"01056",
    "addr:street":"Poole St",
    "iso:country":"US",
    "sg:address":"336 Poole St",
    "sg:city":"Ludlow",
    "sg:classifiers":[
        {
            "category":"Home & Garden",
            "subcategory":"Garden Supply",
            "type":"Retail Goods"
        }
    ],
    "sg:phone":"+1 413 589 9112",
    "sg:postcode":"01056",
    "sg:province":"MA",
    "sg:tags":[
        "nurseryman"
    ],
    "wof:name":"De Ponte's Farm Inc",
    "wof:placetype":"venue"
},
  "geometry": {"coordinates":[-72.415768,42.17959],"type":"Point"}
}