{
  "type": "Feature",
  "properties": {
    "addr:full": "23 Brigantine Cir Plymouth MA 02360",
    "addr:housenumber": "23",
    "addr:postcode": "02360",
    "addr:street": "Brigantine Cir",
    "iso:country": "US",
    "sg:address": "23 Brigantine Cir",
    "sg:city": "Plymouth",
    "sg:classifiers": [
      {
        "category": "Shopping",
        "subcategory": "Bicycles \u0026 Sporting Goods",
        "type": "Retail Goods"
      }
    ],
    "sg:phone": "+1   ",
    "sg:postcode": "02360",
    "sg:province": "MA",
    "wof:name": "Pfluger Enterprise",
    "wof:placetype": "venue"
  },
  "geometry": {"coordinates":[-70.538975,41.880412],"type":"Point"}
}
