{
  "type": "Feature",
  "properties": {
    "addr:full":"77 Princeton St New Bedford MA 02745",
    "addr:housenumber":"77",
    "addr:postcode":"02745",
    "addr:street":"Princeton St",
    "iso:country":"US",
    "sg:address":"77 Princeton St",
    "sg:city":"New Bedford",
    "sg:classifiers":[
        {
            "category":"Personal",
            "subcategory":"Beauty Salon",
            "type":"Services"
        }
    ],
    "sg:phone":"+1 508 995 7077",
    "sg:postcode":"02745",
    "sg:province":"MA",
    "wof:name":"Pat's Beauty Salon",
    "wof:placetype":"venue"
},
  "geometry": {"coordinates":[-70.93003400000001,41.672611],"type":"Point"}
}