{
  "type": "Feature",
  "properties": {
    "addr:full": "30 Dane St Beverly MA 01915",
    "addr:housenumber": "30",
    "addr:postcode": "01915",
    "addr:street": "Dane St",
    "iso:country": "US",
    "sg:address": "30 Dane St",
    "sg:city": "Beverly",
    "sg:classifiers": [
      {
        "category": "Professional",
        "subcategory": "Art Services",
        "type": "Services"
      }
    ],
    "sg:phone": "+1   ",
    "sg:postcode": "01915",
    "sg:province": "MA",
    "sg:tags": [
      "commercial",
      "design"
    ],
    "wof:name": "Thomas Torri Illustration",
    "wof:placetype": "venue"
  },
  "geometry": {"coordinates":[-70.87481,42.550516],"type":"Point"}
}
