{
  "type": "Feature",
  "properties": {
    "addr:full": "2 Prospect St Natick MA 01760",
    "addr:housenumber": "2",
    "addr:postcode": "01760",
    "addr:street": "Prospect St",
    "iso:country": "US",
    "sg:address": "2 Prospect St",
    "sg:city": "Natick",
    "sg:classifiers": [
      {
        "category": "Wholesale",
        "subcategory": "Durable Goods \u0026 Equipment",
        "type": "Manufacturing \u0026 Wholesale Goods"
      }
    ],
    "sg:phone": "+1 508 655 8483",
    "sg:postcode": "01760",
    "sg:province": "MA",
    "sg:tags": [
      "automobile",
      "part",
      "exporter",
      "supply"
    ],
    "wof:name": "American European Product Exchange",
    "wof:placetype": "venue"
  },
  "geometry": {"coordinates":[-71.385349,42.280594],"type":"Point"}
}
