{
  "type": "Feature",
  "properties": {
    "iso:country":"US",
    "sg:address":"2 Prospect St",
    "sg:city":"Natick",
    "sg:classifiers":[
        {
            "category":"Wholesale",
            "subcategory":"Durable Goods & Equipment",
            "type":"Manufacturing & Wholesale Goods"
        }
    ],
    "sg:phone":"+1 508 655 8483",
    "sg:postcode":"01760",
    "sg:province":"MA",
    "sg:tags":[
        "automobile",
        "part",
        "exporter",
        "supply"
    ],
    "wof:name":"American European Product Exchange",
    "wof:placetype":"venue"
},
  "geometry": {"coordinates":[-71.38534900000001,42.280594],"type":"Point"}
}