{
  "type": "Feature",
  "properties": {
    "addr:full": "1950 Massachusetts Avenue Cambridge MA 02140",
    "addr:housenumber": "1950",
    "addr:postcode": "02140",
    "addr:street": "Massachusetts Avenue",
    "iso:country": "US",
    "sg:address": "1950 Massachusetts Avenue",
    "sg:city": "Cambridge",
    "sg:classifiers": [
      {
        "category": "Building \u0026 Trades",
        "subcategory": "Construction",
        "type": "Services"
      }
    ],
    "sg:phone": "+1 617 868 7336",
    "sg:postcode": "02140",
    "sg:province": "MA",
    "sg:tags": [
      "interior",
      "design"
    ],
    "sg:website": "www.susanreddickdesign.com",
    "wof:name": "Reddick Design",
    "wof:placetype": "venue"
  },
  "geometry": {"coordinates":[-71.120193,42.389697],"type":"Point"}
}
