{
  "type": "Feature",
  "properties": {
    "addr:full":"1840 Ocean St Marshfield MA 02050",
    "addr:housenumber":"1840",
    "addr:postcode":"02050",
    "addr:street":"Ocean St",
    "iso:country":"US",
    "sg:address":"1840 Ocean St",
    "sg:city":"Marshfield",
    "sg:classifiers":[
        {
            "category":"Restaurant",
            "type":"Food & Drink"
        }
    ],
    "sg:phone":"+1 781 834 0050",
    "sg:postcode":"02050",
    "sg:province":"MA",
    "wof:name":"Hide Out Grill",
    "wof:placetype":"venue"
},
  "geometry": {"coordinates":[-70.70273400000001,42.092504],"type":"Point"}
}