{
  "type": "Feature",
  "properties": {
    "addr:full": "14 Lincoln Cir Swampscott MA 01907",
    "addr:housenumber": "14",
    "addr:postcode": "01907",
    "addr:street": "Lincoln Cir",
    "iso:country": "US",
    "sg:address": "14 Lincoln Cir",
    "sg:city": "Swampscott",
    "sg:classifiers": [
      {
        "category": "Manufacturing",
        "subcategory": "Food",
        "type": "Manufacturing \u0026 Wholesale Goods"
      }
    ],
    "sg:phone": "+1 781 595 8140",
    "sg:postcode": "01907",
    "sg:province": "MA",
    "sg:tags": [
      "confectionery",
      "candy"
    ],
    "sg:website": "www.chocolatebydesign.com",
    "wof:name": "Chocolate By Design",
    "wof:placetype": "venue"
  },
  "geometry": {"coordinates":[-70.885215,42.476923],"type":"Point"}
}
