{
  "type": "Feature",
  "properties": {
    "iso:country":"US",
    "sg:address":"294 Varnum Ave",
    "sg:city":"Lowell",
    "sg:classifiers":[
        {
            "category":"Health Services",
            "subcategory":"Doctor",
            "type":"Services"
        }
    ],
    "sg:phone":"+1 978 937 6460",
    "sg:postcode":"01854",
    "sg:province":"MA",
    "sg:tags":[
        "physician",
        "surgeon"
    ],
    "wof:name":"New England Neurological Assoc",
    "wof:placetype":"venue"
},
  "geometry": {"coordinates":[-71.341167,42.646271],"type":"Point"}
}