{
  "type": "Feature",
  "properties": {
    "addr:full":"189 Alden St Duxbury MA 02332",
    "addr:housenumber":"189",
    "addr:postcode":"02332",
    "addr:street":"Alden St",
    "iso:country":"US",
    "sg:address":"189 Alden St",
    "sg:city":"Duxbury",
    "sg:classifiers":[
        {
            "category":"Museum",
            "type":"Entertainment"
        }
    ],
    "sg:phone":"+1 781 934 6634",
    "sg:postcode":"02332",
    "sg:province":"MA",
    "wof:name":"Art Complex Inc At Duxbury",
    "wof:placetype":"venue"
},
  "geometry": {"coordinates":[-70.688726,42.043832],"type":"Point"}
}