{
  "type": "Feature",
  "properties": {
    "addr:city": "Duxbury",
    "addr:full": "189 Alden St Duxbury, Ma 02332",
    "addr:house_number": "189",
    "addr:housenumber": "189",
    "addr:phone": "+1 781-934-6634",
    "addr:postcode": "02332",
    "addr:road": "Alden St",
    "addr:state": "MA",
    "addr:street": "Alden St",
    "ilms:label": "ART COMPLEX AT DUXBURY, 189 ALDEN ST DUXBURY MA 02332",
    "ilms:similarity": 1.3957279920578003,
    "iso:country": "US",
    "sg:address": "189 Alden St",
    "sg:city": "Duxbury",
    "sg:classifiers": [
      {
        "category": "Museum",
        "type": "Entertainment"
      }
    ],
    "sg:phone": "+1 781 934 6634",
    "sg:postcode": "02332",
    "sg:province": "MA",
    "wof:name": "Art Complex At Duxbury",
    "wof:placetype": "venue"
  },
  "geometry": {"coordinates":[-70.68901,42.04329],"type":"Point"}
}
