{
  "type": "Feature",
  "properties": {
    "iso:country":"US",
    "sg:address":"260 Franklin St",
    "sg:city":"Boston",
    "sg:classifiers":[
        {
            "category":"Food & Beverages",
            "subcategory":"Bakery",
            "type":"Retail Goods"
        }
    ],
    "sg:phone":"+1 617 204 9993",
    "sg:postcode":"02110",
    "sg:province":"MA",
    "sg:tags":[
        "sandwich"
    ],
    "wof:name":"Boston Tea Party the",
    "wof:placetype":"venue"
},
  "geometry": {"coordinates":[-71.053802,42.356602],"type":"Point"}
}