{
  "type": "Feature",
  "properties": {
    "addr:full":"240 S Main St Middleton MA 01949",
    "addr:housenumber":"240",
    "addr:postcode":"01949",
    "addr:street":"S Main St",
    "iso:country":"US",
    "sg:address":"240 S Main St",
    "sg:city":"Middleton",
    "sg:classifiers":[
        {
            "category":"Shopping",
            "subcategory":"Shoes",
            "type":"Retail Goods"
        }
    ],
    "sg:phone":"+1 978 774 2480",
    "sg:postcode":"01949",
    "sg:province":"MA",
    "wof:name":"Red Wing Shoe Store",
    "wof:placetype":"venue"
},
  "geometry": {"coordinates":[-70.99800999999999,42.577574],"type":"Point"}
}