{
  "type": "Feature",
  "properties": {
    "iso:country":"US",
    "sg:address":"3 Warfield Pl",
    "sg:city":"Northampton",
    "sg:classifiers":[
        {
            "category":"Professional",
            "subcategory":"Management & Consulting",
            "type":"Services"
        }
    ],
    "sg:phone":"+1   ",
    "sg:postcode":"01060",
    "sg:province":"MA",
    "sg:tags":[
        "business"
    ],
    "wof:name":"Paradise City Accounting",
    "wof:placetype":"venue"
},
  "geometry": {"coordinates":[-72.63731199999999,42.326051],"type":"Point"}
}