{
  "type": "Feature",
  "properties": {
    "addr:full": "3 Warfield Pl Northampton MA 01060",
    "addr:housenumber": "3",
    "addr:postcode": "01060",
    "addr:street": "Warfield Pl",
    "iso:country": "US",
    "sg:address": "3 Warfield Pl",
    "sg:city": "Northampton",
    "sg:classifiers": [
      {
        "category": "Professional",
        "subcategory": "Management \u0026 Consulting",
        "type": "Services"
      }
    ],
    "sg:phone": "+1   ",
    "sg:postcode": "01060",
    "sg:province": "MA",
    "sg:tags": [
      "business"
    ],
    "wof:name": "Paradise City Accounting",
    "wof:placetype": "venue"
  },
  "geometry": {"coordinates":[-72.637312,42.326051],"type":"Point"}
}
