{
  "type": "Feature",
  "properties": {
    "addr:full": "30 Erica Cir Hampden MA 01036",
    "addr:housenumber": "30",
    "addr:postcode": "01036",
    "addr:street": "Erica Cir",
    "iso:country": "US",
    "sg:address": "30 Erica Cir",
    "sg:city": "Hampden",
    "sg:classifiers": [
      {
        "category": "Building \u0026 Trades",
        "subcategory": "Plumbing",
        "type": "Services"
      }
    ],
    "sg:phone": "+1 413 566 3191",
    "sg:postcode": "01036",
    "sg:province": "MA",
    "sg:tags": [
      "plumbing",
      "contractor"
    ],
    "wof:name": "Thomas Mc Laughlin Plumbing",
    "wof:placetype": "venue"
  },
  "geometry": {"coordinates":[-72.450158,42.047044],"type":"Point"}
}
