{
  "type": "Feature",
  "properties": {
    "addr:full": "16 Groton St Pepperell MA 01463",
    "addr:housenumber": "16",
    "addr:postcode": "01463",
    "addr:street": "Groton St",
    "iso:country": "US",
    "sg:address": "16 Groton St",
    "sg:city": "Pepperell",
    "sg:classifiers": [
      {
        "category": "Utilities",
        "subcategory": "Fuel Oil \u0026 Lpg",
        "type": "Services"
      },
      {
        "category": "Building \u0026 Trades",
        "subcategory": "Construction",
        "type": "Services"
      }
    ],
    "sg:phone": "+1 978 433 6701",
    "sg:postcode": "01463",
    "sg:province": "MA",
    "sg:tags": [
      "system",
      "specialty",
      "burner",
      "heating",
      "contractor",
      "oils-fuel",
      "air conditioning"
    ],
    "wof:name": "Shattuck Oil CO Inc",
    "wof:placetype": "venue"
  },
  "geometry": {"coordinates":[-71.577171,42.671268],"type":"Point"}
}
