{
  "type": "Feature",
  "properties": {
    "addr:full":"8 Park St Fitchburg MA 01420",
    "addr:housenumber":"8",
    "addr:postcode":"01420",
    "addr:street":"Park St",
    "iso:country":"US",
    "sg:address":"8 Park St",
    "sg:city":"Fitchburg",
    "sg:classifiers":[
        {
            "category":"Professional",
            "subcategory":"Business Services",
            "type":"Services"
        }
    ],
    "sg:phone":"+1 978 343 9814",
    "sg:postcode":"01420",
    "sg:province":"MA",
    "sg:tags":[
        "broker"
    ],
    "wof:name":"Sunbelt Business Advisors",
    "wof:placetype":"venue"
},
  "geometry": {"coordinates":[-71.807438,42.586994],"type":"Point"}
}