{
  "type": "Feature",
  "properties": {
    "addr:full":"440 Somerville Avenue Somerville MA 02143",
    "addr:housenumber":"440",
    "addr:postcode":"02143",
    "addr:street":"Somerville Avenue",
    "iso:country":"US",
    "sg:address":"440 Somerville Avenue",
    "sg:city":"Somerville",
    "sg:classifiers":[
        {
            "category":"Real Estate",
            "subcategory":"Architect",
            "type":"Services"
        }
    ],
    "sg:phone":"+1 617 776 0007",
    "sg:postcode":"02143",
    "sg:province":"MA",
    "wof:name":"Kao Design Group",
    "wof:placetype":"venue"
},
  "geometry": {"coordinates":[-71.102205,42.38215],"type":"Point"}
}