{
  "type": "Feature",
  "properties": {
    "iso:country":"US",
    "sg:address":"66 Richardson Rd",
    "sg:city":"Melrose",
    "sg:classifiers":[
        {
            "category":"Professional",
            "subcategory":"Art Services",
            "type":"Services"
        }
    ],
    "sg:phone":"+1   ",
    "sg:postcode":"02176",
    "sg:province":"MA",
    "sg:tags":[
        "commercial",
        "design"
    ],
    "wof:name":"Baker Designs",
    "wof:placetype":"venue"
},
  "geometry": {"coordinates":[-71.06535100000001,42.470969],"type":"Point"}
}