{
  "type": "Feature",
  "properties": {
    "addr:full":"21 N Dartmouth Mall North Dartmouth MA 02747",
    "addr:housenumber":"21",
    "addr:postcode":"02747",
    "addr:street":"N Dartmouth Mall",
    "iso:country":"US",
    "sg:address":"21 N Dartmouth Mall",
    "sg:city":"North Dartmouth",
    "sg:classifiers":[
        {
            "category":"Building & Trades",
            "subcategory":"Construction",
            "type":"Services"
        }
    ],
    "sg:phone":"+1   ",
    "sg:postcode":"02747",
    "sg:province":"MA",
    "sg:tags":[
        "contractor"
    ],
    "wof:name":"Plaster Craftsmen",
    "wof:placetype":"venue"
},
  "geometry": {"coordinates":[-70.99428,41.641581],"type":"Point"}
}