{
  "type": "Feature",
  "properties": {
    "iso:country":"US",
    "sg:address":"25 Manomet St",
    "sg:city":"Brockton",
    "sg:classifiers":[
        {
            "category":"Education",
            "subcategory":"School",
            "type":"Public Place"
        }
    ],
    "sg:phone":"+1 508 580 7266",
    "sg:postcode":"02301",
    "sg:province":"MA",
    "wof:name":"Whitman Elementary School",
    "wof:placetype":"venue"
},
  "geometry": {"coordinates":[-71.03204599999999,42.077781],"type":"Point"}
}