{
  "type": "Feature",
  "properties": {
    "addr:full": "155 Summer St Somerville MA 02143",
    "addr:housenumber": "155",
    "addr:postcode": "02143",
    "addr:street": "Summer St",
    "iso:country": "US",
    "sg:address": "155 Summer St",
    "sg:city": "Somerville",
    "sg:classifiers": [
      {
        "category": "Professional",
        "subcategory": "Computer Services",
        "type": "Services"
      }
    ],
    "sg:phone": "+1   ",
    "sg:postcode": "02143",
    "sg:province": "MA",
    "sg:tags": [
      "related"
    ],
    "wof:name": "Dan Hull/Software Methods",
    "wof:placetype": "venue"
  },
  "geometry": {"coordinates":[-71.10642,42.386514],"type":"Point"}
}
