{
  "type": "Feature",
  "properties": {
    "addr:full": "68 Appleton Rd Auburn MA 01501",
    "addr:housenumber": "68",
    "addr:postcode": "01501",
    "addr:street": "Appleton Rd",
    "iso:country": "US",
    "sg:address": "68 Appleton Rd",
    "sg:city": "Auburn",
    "sg:classifiers": [
      {
        "category": "Shopping",
        "subcategory": "Gifts \u0026 Souvenirs",
        "type": "Retail Goods"
      }
    ],
    "sg:phone": "+1   ",
    "sg:postcode": "01501",
    "sg:province": "MA",
    "wof:name": "Cricket Crafts",
    "wof:placetype": "venue"
  },
  "geometry": {"coordinates":[-71.865641,42.178799],"type":"Point"}
}
