{
  "type": "Feature",
  "properties": {
    "addr:full":"271 Newbury St Boston MA 02116",
    "addr:housenumber":"271",
    "addr:postcode":"02116",
    "addr:street":"Newbury St",
    "iso:country":"US",
    "sg:address":"271 Newbury St",
    "sg:city":"Boston",
    "sg:classifiers":[
        {
            "category":"Restaurant",
            "type":"Food & Drink"
        }
    ],
    "sg:menulink":"http://www.allmenus.com/ma/boston/423-croma/menu/",
    "sg:phone":"+1 617 247 3200",
    "sg:postcode":"02116",
    "sg:province":"MA",
    "sg:tags":[
        "pasta",
        "american",
        "italian",
        "pizza"
    ],
    "wof:name":"Croma",
    "wof:placetype":"venue"
},
  "geometry": {"coordinates":[-71.083671,42.349424],"type":"Point"}
}