{
  "type": "Feature",
  "properties": {
    "iso:country":"US",
    "sg:address":"490 W Main St",
    "sg:city":"Avon",
    "sg:classifiers":[
        {
            "category":"Personal",
            "subcategory":"Beauty Salon",
            "type":"Services"
        }
    ],
    "sg:phone":"+1 508 583 0036",
    "sg:postcode":"02322",
    "sg:province":"MA",
    "sg:tags":[
        "manicuring"
    ],
    "wof:name":"Avon Nail",
    "wof:placetype":"venue"
},
  "geometry": {"coordinates":[-71.04107399999999,42.122828],"type":"Point"}
}