{
  "type": "Feature",
  "properties": {
    "addr:full": "15 Biskie Head Pt Gloucester MA 01930",
    "addr:housenumber": "15",
    "addr:postcode": "01930",
    "addr:street": "Biskie Head Pt",
    "iso:country": "US",
    "ovtr:label": "Heron Way Marina, 15 Biskie Head Pt Gloucester MA US",
    "ovtr:similarity": 2.909558057785034,
    "sg:address": "15 Biskie Head Pt",
    "sg:city": "Gloucester",
    "sg:classifiers": [
      {
        "category": "Recreation",
        "subcategory": "Marina",
        "type": "Entertainment"
      }
    ],
    "sg:phone": "+1 978 283 0767",
    "sg:postcode": "01930",
    "sg:province": "MA",
    "wof:name": "Heron Way Marina",
    "wof:placetype": "venue"
  },
  "geometry": {"coordinates":[-70.693677,42.625167],"type":"Point"}
}
