{
  "type": "Feature",
  "properties": {
    "iso:country":"US",
    "sg:address":"15 Biskie Head Pt",
    "sg:city":"Gloucester",
    "sg:classifiers":[
        {
            "category":"Recreation",
            "subcategory":"Marina",
            "type":"Entertainment"
        }
    ],
    "sg:phone":"+1 978 283 0767",
    "sg:postcode":"01930",
    "sg:province":"MA",
    "wof:name":"Heron Way Marina",
    "wof:placetype":"venue"
},
  "geometry": {"coordinates":[-70.69367699999999,42.625167],"type":"Point"}
}