{
  "type": "Feature",
  "properties": {
    "addr:full": "132 Main Rd Williamsburg MA 01096",
    "addr:housenumber": "132",
    "addr:postcode": "01096",
    "addr:street": "Main Rd",
    "iso:country": "US",
    "sg:address": "132 Main Rd",
    "sg:city": "Williamsburg",
    "sg:classifiers": [
      {
        "category": "Organizations",
        "subcategory": "Non-profit Organization",
        "type": "Services"
      }
    ],
    "sg:phone": "+1 413 268 7637",
    "sg:postcode": "01096",
    "sg:province": "MA",
    "sg:tags": [
      "charity",
      "foundations-educational",
      "philanthropic",
      "research"
    ],
    "sg:website": "http://www.macular.org",
    "wof:name": "American Macular Degeneration Foundation Inc",
    "wof:placetype": "venue"
  },
  "geometry": {"coordinates":[-72.798745,42.383707],"type":"Point"}
}
