{
  "type": "Feature",
  "properties": {
    "addr:full": "28 Church St Winchester MA 01890",
    "addr:housenumber": "28",
    "addr:postcode": "01890",
    "addr:street": "Church St",
    "iso:country": "US",
    "sg:address": "28 Church St",
    "sg:city": "Winchester",
    "sg:classifiers": [
      {
        "category": "Personal",
        "type": "Services"
      }
    ],
    "sg:phone": "+1 781 729 7112",
    "sg:postcode": "01890",
    "sg:province": "MA",
    "sg:tags": [
      "therapist",
      "massage"
    ],
    "wof:name": "Tranquility Therapeutic Mssg",
    "wof:placetype": "venue"
  },
  "geometry": {"coordinates":[-71.138923,42.451447],"type":"Point"}
}
