{
  "type": "Feature",
  "properties": {
    "addr:full": "4 Broadway Salisbury Beach MA 01952",
    "addr:housenumber": "4",
    "addr:postcode": "01952",
    "addr:street": "Broadway",
    "iso:country": "US",
    "sg:address": "4 Broadway",
    "sg:city": "Salisbury Beach",
    "sg:classifiers": [
      {
        "category": "Food \u0026 Beverages",
        "subcategory": "Candy",
        "type": "Retail Goods"
      }
    ],
    "sg:phone": "+1 978 465 5541",
    "sg:postcode": "01952",
    "sg:province": "MA",
    "sg:tags": [
      "confectionery"
    ],
    "wof:name": "Willey's Candy Shop",
    "wof:placetype": "venue"
  },
  "geometry": {"coordinates":[-70.817246,42.842583],"type":"Point"}
}
