{
  "type": "Feature",
  "properties": {
    "addr:full": "211 Congress St Boston MA 02110",
    "addr:housenumber": "211",
    "addr:postcode": "02110",
    "addr:street": "Congress St",
    "iso:country": "US",
    "sg:address": "211 Congress St",
    "sg:city": "Boston",
    "sg:classifiers": [
      {
        "category": "Bagels",
        "subcategory": "None",
        "type": "Food \u0026 Drink"
      }
    ],
    "sg:phone": "+1 617 423 7105",
    "sg:postcode": "02110",
    "sg:province": "MA",
    "wof:name": "Bruegger's Bagel Bakery",
    "wof:placetype": "venue"
  },
  "geometry": {"coordinates":[-71.054756,42.354679],"type":"Point"}
}
