{
  "type": "Feature",
  "properties": {
    "addr:full": "117 Summer St Stoneham MA 02180",
    "addr:housenumber": "117",
    "addr:postcode": "02180",
    "addr:street": "Summer St",
    "iso:country": "US",
    "sg:address": "117 Summer St",
    "sg:city": "Stoneham",
    "sg:classifiers": [
      {
        "category": "Building \u0026 Trades",
        "subcategory": "Construction",
        "type": "Services"
      }
    ],
    "sg:phone": "+1 781 861 9521",
    "sg:postcode": "02180",
    "sg:province": "MA",
    "sg:tags": [
      "downspouts",
      "gutter"
    ],
    "wof:name": "Richfield Aluminum Products Co",
    "wof:placetype": "venue"
  },
  "geometry": {"coordinates":[-71.094014,42.477312],"type":"Point"}
}
