{
  "type": "Feature",
  "properties": {
    "addr:full":"1 Foundry St Lowell MA 01880",
    "addr:housenumber":"1",
    "addr:postcode":"01880",
    "addr:street":"Foundry St",
    "iso:country":"US",
    "sg:address":"1 Foundry St",
    "sg:city":"Lowell",
    "sg:classifiers":[
        {
            "category":"Autos & Motor Vehicles",
            "subcategory":"Auto Supplies",
            "type":"Retail Goods"
        }
    ],
    "sg:phone":"+1 978 275 9930",
    "sg:postcode":"01880",
    "sg:province":"MA",
    "sg:tags":[
        "automobile",
        "parts"
    ],
    "wof:name":"Foreign Autopart",
    "wof:placetype":"venue"
},
  "geometry": {"coordinates":[-71.074789,42.500006],"type":"Point"}
}