{
  "type": "Feature",
  "properties": {
    "addr:full": "62 Main St Upton MA 01568",
    "addr:housenumber": "62",
    "addr:postcode": "01568",
    "addr:street": "Main St",
    "iso:country": "US",
    "sg:address": "62 Main St",
    "sg:city": "Upton",
    "sg:classifiers": [
      {
        "category": "Health Services",
        "subcategory": "Doctor",
        "type": "Services"
      }
    ],
    "sg:phone": "+1 508 529 4325",
    "sg:postcode": "01568",
    "sg:province": "MA",
    "sg:tags": [
      "physician",
      "surgeon"
    ],
    "wof:name": "Healthy By Nature Dr Theolinda",
    "wof:placetype": "venue"
  },
  "geometry": {"coordinates":[-71.610882,42.169719],"type":"Point"}
}
