{
  "type": "Feature",
  "properties": {
    "iso:country":"US",
    "sg:address":"8 Tremont St",
    "sg:city":"Brighton",
    "sg:classifiers":[
        {
            "category":"Personal",
            "subcategory":"Beauty Salon",
            "type":"Services"
        }
    ],
    "sg:phone":"+1 617 782 6160",
    "sg:postcode":"02135",
    "sg:province":"MA",
    "sg:tags":[
        "manicuring"
    ],
    "wof:name":"Brighton Nails",
    "wof:placetype":"venue"
},
  "geometry": {"coordinates":[-71.17046499999999,42.35006],"type":"Point"}
}