{
  "type": "Feature",
  "properties": {
    "addr:full": "8 Tremont St Brighton MA 02135",
    "addr:housenumber": "8",
    "addr:postcode": "02135",
    "addr:street": "Tremont St",
    "iso:country": "US",
    "ovtr:label": "Brighton Nails, 8 Tremont St Brighton MA US",
    "ovtr:similarity": 2.815103054046631,
    "sg:address": "8 Tremont St",
    "sg:city": "Brighton",
    "sg:classifiers": [
      {
        "category": "Personal",
        "subcategory": "Beauty Salon",
        "type": "Services"
      }
    ],
    "sg:phone": "+1 617 782 6160",
    "sg:postcode": "02135",
    "sg:province": "MA",
    "sg:tags": [
      "manicuring"
    ],
    "wof:name": "Brighton Nails",
    "wof:placetype": "venue"
  },
  "geometry": {"coordinates":[-71.170465,42.35006],"type":"Point"}
}
