{
  "type": "Feature",
  "properties": {
    "addr:full": "683 S Main St Attleboro MA 02703",
    "addr:housenumber": "683",
    "addr:postcode": "02703",
    "addr:street": "S Main St",
    "iso:country": "US",
    "sg:address": "683 S Main St",
    "sg:city": "Attleboro",
    "sg:classifiers": [
      {
        "category": "Organizations",
        "subcategory": "Religious Organization",
        "type": "Services"
      }
    ],
    "sg:phone": "+1 508 222 0641",
    "sg:postcode": "02703",
    "sg:province": "MA",
    "sg:tags": [
      "church"
    ],
    "wof:name": "St Stephen's Rectory",
    "wof:placetype": "venue"
  },
  "geometry": {"coordinates":[-71.307026,41.914254],"type":"Point"}
}
