{
  "type": "Feature",
  "properties": {
    "iso:country":"US",
    "sg:address":"683 S Main St",
    "sg:city":"Attleboro",
    "sg:classifiers":[
        {
            "category":"Organizations",
            "subcategory":"Religious Organization",
            "type":"Services"
        }
    ],
    "sg:phone":"+1 508 222 0641",
    "sg:postcode":"02703",
    "sg:province":"MA",
    "sg:tags":[
        "church"
    ],
    "wof:name":"St Stephen's Rectory",
    "wof:placetype":"venue"
},
  "geometry": {"coordinates":[-71.30702599999999,41.914254],"type":"Point"}
}