{
  "type": "Feature",
  "properties": {
    "addr:full":"7 Badger Ave Natick MA 01760",
    "addr:housenumber":"7",
    "addr:postcode":"01760",
    "addr:street":"Badger Ave",
    "iso:country":"US",
    "sg:address":"7 Badger Ave",
    "sg:city":"Natick",
    "sg:classifiers":[
        {
            "category":"Manufacturing",
            "subcategory":"Metals",
            "type":"Manufacturing & Wholesale Goods"
        }
    ],
    "sg:phone":"+1 508 650 1120",
    "sg:postcode":"01760",
    "sg:province":"MA",
    "sg:tags":[
        "tank"
    ],
    "sg:website":"www.hodinc.com",
    "wof:name":"HOD Inc",
    "wof:placetype":"venue"
},
  "geometry": {"coordinates":[-71.31914399999999,42.272341],"type":"Point"}
}