{
  "type": "Feature",
  "properties": {
    "iso:country":"US",
    "sg:address":"447 Washington St",
    "sg:city":"Duxbury",
    "sg:classifiers":[
        {
            "category":"Shopping",
            "subcategory":"Used Merchandise",
            "type":"Retail Goods"
        }
    ],
    "sg:phone":"+1 781 934 7132",
    "sg:postcode":"02332",
    "sg:province":"MA",
    "sg:tags":[
        "antique"
    ],
    "wof:name":"Folk Art Antiques",
    "wof:placetype":"venue"
},
  "geometry": {"coordinates":[-70.671567,42.038954],"type":"Point"}
}