{
  "type": "Feature",
  "properties": {
    "addr:full": "447 Washington St Duxbury MA 02332",
    "addr:housenumber": "447",
    "addr:postcode": "02332",
    "addr:street": "Washington St",
    "iso:country": "US",
    "sg:address": "447 Washington St",
    "sg:city": "Duxbury",
    "sg:classifiers": [
      {
        "category": "Shopping",
        "subcategory": "Used Merchandise",
        "type": "Retail Goods"
      }
    ],
    "sg:phone": "+1 781 934 7132",
    "sg:postcode": "02332",
    "sg:province": "MA",
    "sg:tags": [
      "antique"
    ],
    "wof:name": "Folk Art Antiques",
    "wof:placetype": "venue"
  },
  "geometry": {"coordinates":[-70.671567,42.038954],"type":"Point"}
}
