{
  "type": "Feature",
  "properties": {
    "addr:full": "685 Main St Walpole MA 02081",
    "addr:housenumber": "685",
    "addr:postcode": "02081",
    "addr:street": "Main St",
    "iso:country": "US",
    "sg:address": "685 Main St",
    "sg:city": "Walpole",
    "sg:classifiers": [
      {
        "category": "Real Estate",
        "subcategory": "Real Estate Agent",
        "type": "Services"
      }
    ],
    "sg:phone": "+1 508 668 4634",
    "sg:postcode": "02081",
    "sg:province": "MA",
    "sg:website": "www.remaxrealestatecenter.com",
    "wof:name": "Re/Max Real Estate Ctr",
    "wof:placetype": "venue"
  },
  "geometry": {"coordinates":[-71.246276,42.154181],"type":"Point"}
}
