{
  "type": "Feature",
  "properties": {
    "iso:country":"US",
    "sg:address":"91 Yoke Rd",
    "sg:city":"Bridgewater",
    "sg:classifiers":[
        {
            "category":"Real Estate",
            "subcategory":"Real Estate Agent",
            "type":"Services"
        }
    ],
    "sg:phone":"+1 508 279 0353",
    "sg:postcode":"02324",
    "sg:province":"MA",
    "wof:name":"Bridgewater Tree Farm Inc",
    "wof:placetype":"venue"
},
  "geometry": {"coordinates":[-70.95456,42.00246],"type":"Point"}
}