{
  "type": "Feature",
  "properties": {
    "iso:country":"US",
    "sg:address":"53 Cole Pkwy",
    "sg:city":"Scituate",
    "sg:classifiers":[
        {
            "category":"Travel",
            "subcategory":"Travel Agent",
            "type":"Entertainment"
        }
    ],
    "sg:phone":"+1 781 545 4281",
    "sg:postcode":"02066",
    "sg:province":"MA",
    "sg:tags":[
        "agency",
        "bureau"
    ],
    "wof:name":"Scituate Harbor Travel",
    "wof:placetype":"venue"
},
  "geometry": {"coordinates":[-70.72551900000001,42.193417],"type":"Point"}
}