{
  "type": "Feature",
  "properties": {
    "iso:country":"US",
    "sg:address":"6 Oakwood Rd",
    "sg:city":"Wilmington",
    "sg:classifiers":[
        {
            "category":"Professional",
            "subcategory":"Business Services",
            "type":"Services"
        },
        {
            "category":"Professional",
            "subcategory":"Printing & Photocopies",
            "type":"Services"
        }
    ],
    "sg:phone":"+1 978 988 7944",
    "sg:postcode":"01887",
    "sg:province":"MA",
    "sg:tags":[
        "system",
        "form",
        "printers-business"
    ],
    "wof:name":"Mackenzie Forms Inc",
    "wof:placetype":"venue"
},
  "geometry": {"coordinates":[-71.185013,42.568539],"type":"Point"}
}