{
  "type": "Feature",
  "properties": {
    "addr:full":"69 Bayview Ave Berkley MA 02779",
    "addr:housenumber":"69",
    "addr:postcode":"02779",
    "addr:street":"Bayview Ave",
    "iso:country":"US",
    "sg:address":"69 Bayview Ave",
    "sg:city":"Berkley",
    "sg:classifiers":[
        {
            "category":"Shopping",
            "subcategory":"Catalog Store",
            "type":"Retail Goods"
        }
    ],
    "sg:phone":"+1   ",
    "sg:postcode":"02779",
    "sg:province":"MA",
    "sg:tags":[
        "collectible",
        "sales",
        "plush"
    ],
    "wof:name":"Elyssas Treasures",
    "wof:placetype":"venue"
},
  "geometry": {"coordinates":[-71.09623000000001,41.815315],"type":"Point"}
}