{
  "type": "Feature",
  "properties": {
    "iso:country":"US",
    "sg:address":"48 Bank St",
    "sg:city":"Attleboro",
    "sg:classifiers":[
        {
            "category":"Building & Trades",
            "subcategory":"Cleaning & Sanitation",
            "type":"Services"
        }
    ],
    "sg:phone":"+1 508 223 4545",
    "sg:postcode":"02703",
    "sg:province":"MA",
    "sg:tags":[
        "janitor"
    ],
    "wof:name":"Fabulous Cleaning",
    "wof:placetype":"venue"
},
  "geometry": {"coordinates":[-71.283749,41.946325],"type":"Point"}
}