{
  "type": "Feature",
  "properties": {
    "addr:full": "60 Washington St Brighton MA 02135",
    "addr:housenumber": "60",
    "addr:postcode": "02135",
    "addr:street": "Washington St",
    "iso:country": "US",
    "sg:address": "60 Washington St",
    "sg:city": "Brighton",
    "sg:classifiers": [
      {
        "category": "Restaurant",
        "type": "Food \u0026 Drink"
      }
    ],
    "sg:phone": "+1 617 277 8277",
    "sg:postcode": "02135",
    "sg:province": "MA",
    "sg:tags": [
      "pizza"
    ],
    "sg:website": "www.pizzaninionline.com/",
    "wof:name": "Pizzanini",
    "wof:placetype": "venue"
  },
  "geometry": {"coordinates":[-71.142303,42.343601],"type":"Point"}
}
