{
  "type": "Feature",
  "properties": {
    "iso:country":"US",
    "sg:address":"1581 Beacon Street",
    "sg:city":"Brookline",
    "sg:classifiers":[
        {
            "category":"Sports & Exercise",
            "subcategory":"Gym",
            "type":"Entertainment"
        }
    ],
    "sg:phone":"+1 617 277 3910",
    "sg:postcode":"02446",
    "sg:province":"MA",
    "sg:tags":[
        "trainer"
    ],
    "wof:name":"The Therapy Center",
    "wof:placetype":"venue"
},
  "geometry": {"coordinates":[-71.13323800000001,42.33937],"type":"Point"}
}