{
  "type": "Feature",
  "properties": {
    "addr:full": "Boston Center for the Arts 539 Tremont St Boston MA 02116",
    "addr:housenumber": "539",
    "addr:postcode": "02116",
    "addr:street": "Tremont St",
    "iso:country": "US",
    "sg:address": "Boston Center for the Arts 539 Tremont St",
    "sg:city": "Boston",
    "sg:classifiers": [
      {
        "category": "Shopping",
        "subcategory": "Clothing, Apparel, \u0026 Fashions",
        "type": "Retail Goods"
      }
    ],
    "sg:postcode": "02116",
    "sg:province": "MA",
    "sg:website": "www.StyleFixx.com",
    "wof:name": "StyleFixx Girl's Night Out",
    "wof:placetype": "venue"
  },
  "geometry": {"coordinates":[-71.070168,42.34493],"type":"Point"}
}
