{
  "type": "Feature",
  "properties": {
    "iso:country":"US",
    "sg:address":"61 Pine Ln",
    "sg:city":"Barnstable",
    "sg:classifiers":[
        {
            "category":"Building & Trades",
            "subcategory":"Pest Control",
            "type":"Services"
        }
    ],
    "sg:phone":"+1 508 375 9009",
    "sg:postcode":"02630",
    "sg:province":"MA",
    "sg:website":"www.pestinvestigators.com",
    "wof:name":"P.I. Pest Investigators Llc",
    "wof:placetype":"venue"
},
  "geometry": {"coordinates":[-70.307762,41.700278],"type":"Point"}
}