{
  "type": "Feature",
  "properties": {
    "addr:full":"14 Knollwood Dr Charlton MA 01507",
    "addr:housenumber":"14",
    "addr:postcode":"01507",
    "addr:street":"Knollwood Dr",
    "iso:country":"US",
    "sg:address":"14 Knollwood Dr",
    "sg:city":"Charlton",
    "sg:classifiers":[
        {
            "category":"Building & Trades",
            "subcategory":"Construction",
            "type":"Services"
        }
    ],
    "sg:phone":"+1 508 248 4490",
    "sg:postcode":"01507",
    "sg:province":"MA",
    "sg:tags":[
        "contractor"
    ],
    "wof:name":"K & M Designs",
    "wof:placetype":"venue"
},
  "geometry": {"coordinates":[-71.97020000000001,42.180801],"type":"Point"}
}