{
  "type": "Feature",
  "properties": {
    "addr:full": "161 Jones Rd Falmouth MA 02540",
    "addr:housenumber": "161",
    "addr:postcode": "02540",
    "addr:street": "Jones Rd",
    "iso:country": "US",
    "sg:address": "161 Jones Rd",
    "sg:city": "Falmouth",
    "sg:classifiers": [
      {
        "category": "Government",
        "subcategory": "Office",
        "type": "Public Place"
      }
    ],
    "sg:phone": "+1 508 457 6534",
    "sg:postcode": "02540",
    "sg:province": "MA",
    "sg:tags": [
      "federal",
      "security"
    ],
    "wof:name": "US Army National Guard",
    "wof:placetype": "venue"
  },
  "geometry": {"coordinates":[-70.613525,41.562004],"type":"Point"}
}
