{
  "type": "Feature",
  "properties": {
    "iso:country":"US",
    "sg:address":"2979 County St",
    "sg:city":"Somerset",
    "sg:classifiers":[
        {
            "category":"Restaurant",
            "type":"Food & Drink"
        }
    ],
    "sg:phone":"+1 508 673 3340",
    "sg:postcode":"02726",
    "sg:province":"MA",
    "sg:tags":[
        "pizza"
    ],
    "wof:name":"Savas Pizza",
    "wof:placetype":"venue"
},
  "geometry": {"coordinates":[-71.138195,41.771231],"type":"Point"}
}