{
  "type": "Feature",
  "properties": {
    "addr:full": "2979 County St Somerset MA 02726",
    "addr:housenumber": "2979",
    "addr:postcode": "02726",
    "addr:street": "County St",
    "iso:country": "US",
    "ovtr:label": "Savas Pizza, 2979 County St Somerset MA US",
    "ovtr:similarity": 2.144045114517212,
    "sg:address": "2979 County St",
    "sg:city": "Somerset",
    "sg:classifiers": [
      {
        "category": "Restaurant",
        "type": "Food \u0026 Drink"
      }
    ],
    "sg:phone": "+1 508 673 3340",
    "sg:postcode": "02726",
    "sg:province": "MA",
    "sg:tags": [
      "pizza"
    ],
    "wof:name": "Savas Pizza",
    "wof:placetype": "venue"
  },
  "geometry": {"coordinates":[-71.138195,41.771231],"type":"Point"}
}
