{
  "type": "Feature",
  "properties": {
    "addr:full":"500 Boston Post Rd E # 3 Marlborough MA 01752",
    "addr:housenumber":"500",
    "addr:postcode":"01752",
    "addr:street":"Boston Post Rd E # 3",
    "iso:country":"US",
    "sg:address":"500 Boston Post Rd E # 3",
    "sg:city":"Marlborough",
    "sg:classifiers":[
        {
            "category":"Restaurant",
            "type":"Food & Drink"
        }
    ],
    "sg:phone":"+1 508 281 6555",
    "sg:postcode":"01752",
    "sg:province":"MA",
    "sg:tags":[
        "house",
        "steak"
    ],
    "wof:name":"Vitoria",
    "wof:placetype":"venue"
},
  "geometry": {"coordinates":[-71.51128799999999,42.347458],"type":"Point"}
}