{
  "type": "Feature",
  "properties": {
    "addr:full": "147 Main Rd Williamsburg MA 01096",
    "addr:housenumber": "147",
    "addr:postcode": "01096",
    "addr:street": "Main Rd",
    "iso:country": "US",
    "sg:address": "147 Main Rd",
    "sg:city": "Williamsburg",
    "sg:classifiers": [
      {
        "category": "Arts \u0026 Performance",
        "subcategory": "Art Gallery",
        "type": "Entertainment"
      }
    ],
    "sg:phone": "+1 413 268 9215",
    "sg:postcode": "01096",
    "sg:province": "MA",
    "sg:tags": [
      "fine",
      "artist"
    ],
    "wof:name": "Funny Face Productions",
    "wof:placetype": "venue"
  },
  "geometry": {"coordinates":[-72.800018,42.384232],"type":"Point"}
}
