{
  "type": "Feature",
  "properties": {
    "iso:country":"US",
    "sg:address":"147 Main Rd",
    "sg:city":"Williamsburg",
    "sg:classifiers":[
        {
            "category":"Arts & Performance",
            "subcategory":"Art Gallery",
            "type":"Entertainment"
        }
    ],
    "sg:phone":"+1 413 268 9215",
    "sg:postcode":"01096",
    "sg:province":"MA",
    "sg:tags":[
        "fine",
        "artist"
    ],
    "wof:name":"Funny Face Productions",
    "wof:placetype":"venue"
},
  "geometry": {"coordinates":[-72.80001799999999,42.384232],"type":"Point"}
}