{
  "type": "Feature",
  "properties": {
    "iso:country":"US",
    "sg:address":"341 South St",
    "sg:city":"Northborough",
    "sg:classifiers":[
        {
            "category":"Restaurant",
            "type":"Food & Drink"
        }
    ],
    "sg:phone":"+1 508 393 5782",
    "sg:postcode":"01532",
    "sg:province":"MA",
    "sg:tags":[
        "cafe"
    ],
    "wof:name":"NYSA Cafe",
    "wof:placetype":"venue"
},
  "geometry": {"coordinates":[-71.63845499999999,42.297125],"type":"Point"}
}