{
  "type": "Feature",
  "properties": {
    "iso:country":"US",
    "sg:address":"601 Washington St",
    "sg:city":"Boston",
    "sg:classifiers":[
        {
            "category":"Home & Garden",
            "subcategory":"Furniture",
            "type":"Retail Goods"
        }
    ],
    "sg:phone":"+1 617 457 7905",
    "sg:postcode":"02111",
    "sg:province":"MA",
    "sg:tags":[
        "store"
    ],
    "wof:name":"Roche Bobois",
    "wof:placetype":"venue"
},
  "geometry": {"coordinates":[-71.062735,42.352944],"type":"Point"}
}