{
  "type": "Feature",
  "properties": {
    "iso:country":"US",
    "sg:address":"61 Trahan Ave",
    "sg:city":"Worcester",
    "sg:classifiers":[
        {
            "category":"Personal",
            "type":"Services"
        }
    ],
    "sg:phone":"+1 508 752 9990",
    "sg:postcode":"01604",
    "sg:province":"MA",
    "sg:tags":[
        "therapist",
        "massage"
    ],
    "wof:name":"Above It All Massage Therapy",
    "wof:placetype":"venue"
},
  "geometry": {"coordinates":[-71.76941100000001,42.251667],"type":"Point"}
}