{
  "type": "Feature",
  "properties": {
    "iso:country":"US",
    "sg:address":"13 Atwood St",
    "sg:city":"Carver",
    "sg:classifiers":[
        {
            "category":"Building & Trades",
            "subcategory":"Electrical",
            "type":"Services"
        }
    ],
    "sg:phone":"+1 508 866 3870",
    "sg:postcode":"02330",
    "sg:province":"MA",
    "sg:tags":[
        "electric",
        "contractor"
    ],
    "wof:name":"D & S Electrical Contracting",
    "wof:placetype":"venue"
},
  "geometry": {"coordinates":[-70.793747,41.897566],"type":"Point"}
}