{
  "type": "Feature",
  "properties": {
    "iso:country":"US",
    "sg:address":"93 Burrell St",
    "sg:city":"Roxbury",
    "sg:classifiers":[
        {
            "category":"Food & Beverages",
            "subcategory":"Groceries & Convenience Stores",
            "type":"Retail Goods"
        }
    ],
    "sg:phone":"+1 617 442 7686",
    "sg:postcode":"02119",
    "sg:province":"MA",
    "wof:name":"Boutwell Corner Store",
    "wof:placetype":"venue"
},
  "geometry": {"coordinates":[-71.068167,42.323714],"type":"Point"}
}