{
  "type": "Feature",
  "properties": {
    "addr:full": "93 Burrell St Roxbury MA 02119",
    "addr:housenumber": "93",
    "addr:postcode": "02119",
    "addr:street": "Burrell St",
    "iso:country": "US",
    "sg:address": "93 Burrell St",
    "sg:city": "Roxbury",
    "sg:classifiers": [
      {
        "category": "Food \u0026 Beverages",
        "subcategory": "Groceries \u0026 Convenience Stores",
        "type": "Retail Goods"
      }
    ],
    "sg:phone": "+1 617 442 7686",
    "sg:postcode": "02119",
    "sg:province": "MA",
    "wof:name": "Boutwell Corner Store",
    "wof:placetype": "venue"
  },
  "geometry": {"coordinates":[-71.068167,42.323714],"type":"Point"}
}
