{
  "type": "Feature",
  "properties": {
    "addr:full": "146 Dorchester St Boston MA 02127",
    "addr:housenumber": "146",
    "addr:postcode": "02127",
    "addr:street": "Dorchester St",
    "iso:country": "US",
    "sg:address": "146 Dorchester St",
    "sg:city": "Boston",
    "sg:classifiers": [
      {
        "category": "Retail",
        "subcategory": "Funeral Services",
        "type": "Services"
      }
    ],
    "sg:phone": "+1 617 269 2390",
    "sg:postcode": "02127",
    "sg:province": "MA",
    "sg:tags": [
      "director",
      "cemetery",
      "supply"
    ],
    "wof:name": "J F O'brien Funeral Home",
    "wof:placetype": "venue"
  },
  "geometry": {"coordinates":[-71.047897,42.334599],"type":"Point"}
}
