{
  "type": "Feature",
  "properties": {
    "iso:country":"US",
    "sg:address":"256 Maple St",
    "sg:city":"Marlborough",
    "sg:classifiers":[
        {
            "category":"Banks & Credit Unions",
            "subcategory":"Bank",
            "type":"Services"
        }
    ],
    "sg:phone":"+1 508 303 0330",
    "sg:postcode":"01752",
    "sg:province":"MA",
    "sg:tags":[
        "savings"
    ],
    "wof:name":"Hudson Savings Bank",
    "wof:placetype":"venue"
},
  "geometry": {"coordinates":[-71.542131,42.33875],"type":"Point"}
}