{
  "type": "Feature",
  "properties": {
    "addr:full": "20 Sea St Exd Hyannis MA 02601",
    "addr:housenumber": "20",
    "addr:postcode": "02601",
    "addr:street": "Sea St Exd",
    "iso:country": "US",
    "sg:address": "20 Sea St Exd",
    "sg:city": "Hyannis",
    "sg:classifiers": [
      {
        "category": "Personal",
        "subcategory": "Beauty Salon",
        "type": "Services"
      }
    ],
    "sg:phone": "+1 508 790 9210",
    "sg:postcode": "02601",
    "sg:province": "MA",
    "wof:name": "Bersal Skin \u0026 Nail Care Studio",
    "wof:placetype": "venue"
  },
  "geometry": {"coordinates":[-70.292237,41.650682],"type":"Point"}
}
