{
  "type": "Feature",
  "properties": {
    "iso:country":"US",
    "sg:address":"20 Sea St Exd",
    "sg:city":"Hyannis",
    "sg:classifiers":[
        {
            "category":"Personal",
            "subcategory":"Beauty Salon",
            "type":"Services"
        }
    ],
    "sg:phone":"+1 508 790 9210",
    "sg:postcode":"02601",
    "sg:province":"MA",
    "wof:name":"Bersal Skin & Nail Care Studio",
    "wof:placetype":"venue"
},
  "geometry": {"coordinates":[-70.292237,41.650682],"type":"Point"}
}