{
  "type": "Feature",
  "properties": {
    "addr:full":"49 McGrath Rd Dracut MA 01826",
    "addr:housenumber":"49",
    "addr:postcode":"01826",
    "addr:street":"Mcgrath Rd",
    "iso:country":"US",
    "sg:address":"49 McGrath Rd",
    "sg:city":"Dracut",
    "sg:classifiers":[
        {
            "category":"Freight",
            "type":"Transportation"
        }
    ],
    "sg:phone":"+1   ",
    "sg:postcode":"01826",
    "sg:province":"MA",
    "sg:tags":[
        "operator",
        "local",
        "trucking"
    ],
    "wof:name":"Saverance Trucking",
    "wof:placetype":"venue"
},
  "geometry": {"coordinates":[-71.250939,42.705526],"type":"Point"}
}