{
  "type": "Feature",
  "properties": {
    "addr:full":"95 Howlett St Topsfield MA 01983",
    "addr:housenumber":"95",
    "addr:postcode":"01983",
    "addr:street":"Howlett St",
    "iso:country":"US",
    "sg:address":"95 Howlett St",
    "sg:city":"Topsfield",
    "sg:classifiers":[
        {
            "category":"Professional",
            "subcategory":"Business Services",
            "type":"Services"
        }
    ],
    "sg:phone":"+1 978 887 0627",
    "sg:postcode":"01983",
    "sg:province":"MA",
    "wof:name":"APS Computer Solutions",
    "wof:placetype":"venue"
},
  "geometry": {"coordinates":[-70.93846499999999,42.642365],"type":"Point"}
}