{
  "type": "Feature",
  "properties": {
    "iso:country":"US",
    "sg:address":"409 Main St",
    "sg:city":"Worcester",
    "sg:classifiers":[
        {
            "category":"Real Estate",
            "subcategory":"Real Estate Agent",
            "type":"Services"
        }
    ],
    "sg:phone":"+1 508 797 6009",
    "sg:postcode":"01608",
    "sg:province":"MA",
    "wof:name":"Homeland Realty",
    "wof:placetype":"venue"
},
  "geometry": {"coordinates":[-71.801771,42.264254],"type":"Point"}
}