{
  "type": "Feature",
  "properties": {
    "iso:country":"US",
    "sg:address":"484 Lowell St Ste A6",
    "sg:city":"Peabody",
    "sg:classifiers":[
        {
            "category":"Airline",
            "type":"Transportation"
        },
        {
            "category":"Travel",
            "subcategory":"Travel Agent",
            "type":"Entertainment"
        }
    ],
    "sg:phone":"+1 978 535 6175",
    "sg:postcode":"01960",
    "sg:province":"MA",
    "sg:tags":[
        "ticket",
        "agency"
    ],
    "wof:name":"Casino Representive Intl",
    "wof:placetype":"venue"
},
  "geometry": {"coordinates":[-70.97396999999999,42.541638],"type":"Point"}
}