{
  "type": "Feature",
  "properties": {
    "addr:full": "2559 Baptist Corner Rd Shelburne Falls MA 01370",
    "addr:housenumber": "2559",
    "addr:postcode": "01370",
    "addr:street": "Baptist Corner Rd",
    "iso:country": "US",
    "sg:address": "2559 Baptist Corner Rd",
    "sg:city": "Shelburne Falls",
    "sg:classifiers": [
      {
        "category": "Home \u0026 Garden",
        "subcategory": "Building Materials",
        "type": "Retail Goods"
      }
    ],
    "sg:phone": "+1 413 625 2400",
    "sg:postcode": "01370",
    "sg:province": "MA",
    "sg:tags": [
      "door"
    ],
    "wof:name": "A 1 Overhead Door Inc",
    "wof:placetype": "venue"
  },
  "geometry": {"coordinates":[-72.737729,42.558888],"type":"Point"}
}
