{
  "type": "Feature",
  "properties": {
    "addr:full":"8 Harrison Ave Boston MA 02111",
    "addr:housenumber":"8",
    "addr:postcode":"02111",
    "addr:street":"Harrison Ave",
    "iso:country":"US",
    "sg:address":"8 Harrison Ave",
    "sg:city":"Boston",
    "sg:classifiers":[
        {
            "category":"Retail",
            "subcategory":"Funeral Services",
            "type":"Services"
        }
    ],
    "sg:phone":"+1 617 695 6820",
    "sg:postcode":"02111",
    "sg:province":"MA",
    "sg:tags":[
        "embalmer",
        "director"
    ],
    "wof:name":"Wing Fook Funeral Home",
    "wof:placetype":"venue"
},
  "geometry": {"coordinates":[-71.06120300000001,42.352139],"type":"Point"}
}