{
  "type": "Feature",
  "properties": {
    "iso:country":"US",
    "sg:address":"524 Commonwealth Ave (Hotel Commonwealth)",
    "sg:city":"Boston",
    "sg:phone":"+1 617 266 6555",
    "sg:postcode":"02215",
    "sg:province":"MA",
    "sg:website":"http://www.jean-therapy.com",
    "wof:name":"Jean Therapy",
    "wof:placetype":"venue"
},
  "geometry": {"coordinates":[-71.095833,42.348789],"type":"Point"}
}