{
  "type": "Feature",
  "properties": {
    "addr:full":"133 Fort Meadow Dr Hudson MA 01749",
    "addr:housenumber":"133",
    "addr:postcode":"01749",
    "addr:street":"Fort Meadow Dr",
    "iso:country":"US",
    "sg:address":"133 Fort Meadow Dr",
    "sg:city":"Hudson",
    "sg:classifiers":[
        {
            "category":"Professional",
            "subcategory":"Art Services",
            "type":"Services"
        }
    ],
    "sg:phone":"+1 978 568 8675",
    "sg:postcode":"01749",
    "sg:province":"MA",
    "sg:tags":[
        "design",
        "screen",
        "printing",
        "commercial"
    ],
    "wof:name":"Black Eagle Silkscreening",
    "wof:placetype":"venue"
},
  "geometry": {"coordinates":[-71.53600299999999,42.379117],"type":"Point"}
}