{
  "type": "Feature",
  "properties": {
    "iso:country":"US",
    "sg:address":"961 Somerset Ave",
    "sg:city":"Taunton",
    "sg:classifiers":[
        {
            "category":"Building & Trades",
            "subcategory":"Cleaning & Sanitation",
            "type":"Services"
        }
    ],
    "sg:phone":"+1 508 821 9499",
    "sg:postcode":"02780",
    "sg:province":"MA",
    "sg:tags":[
        "janitor"
    ],
    "wof:name":"Atalaia Cleaning Co",
    "wof:placetype":"venue"
},
  "geometry": {"coordinates":[-71.106328,41.874313],"type":"Point"}
}