{
  "type": "Feature",
  "properties": {
    "iso:country":"US",
    "sg:address":"300 Congress St",
    "sg:city":"Quincy",
    "sg:classifiers":[
        {
            "category":"Professional",
            "subcategory":"Lawyer & Legal Services",
            "type":"Services"
        }
    ],
    "sg:phone":"+1 617 984 0616",
    "sg:postcode":"02169",
    "sg:province":"MA",
    "sg:tags":[
        "attorney"
    ],
    "sg:website":"www.medlencarroll.com",
    "wof:name":"Medlen & Carroll LLP",
    "wof:placetype":"venue"
},
  "geometry": {"coordinates":[-71.014287,42.232697],"type":"Point"}
}