{
  "type": "Feature",
  "properties": {
    "iso:country":"US",
    "sg:address":"2218 Massachusetts Ave",
    "sg:city":"Cambridge",
    "sg:classifiers":[
        {
            "category":"Travel",
            "subcategory":"Hotels & Motels",
            "type":"Entertainment"
        }
    ],
    "sg:phone":"+1 617 491 6300",
    "sg:postcode":"02140",
    "sg:province":"MA",
    "sg:tags":[
        "breakfast",
        "accommodation",
        "bed"
    ],
    "sg:website":"www.acambridgehouse.com/",
    "wof:name":"A Cambridge House Inn",
    "wof:placetype":"venue"
},
  "geometry": {"coordinates":[-71.126161,42.393233],"type":"Point"}
}