{
  "type": "Feature",
  "properties": {
    "addr:full":"95 Washington St Canton MA 02021",
    "addr:housenumber":"95",
    "addr:postcode":"02021",
    "addr:street":"Washington St",
    "iso:country":"US",
    "sg:address":"95 Washington St",
    "sg:city":"Canton",
    "sg:classifiers":[
        {
            "category":"Home & Garden",
            "subcategory":"Carpets & Floor Coverings",
            "type":"Retail Goods"
        }
    ],
    "sg:phone":"+1 781 821 2825",
    "sg:postcode":"02021",
    "sg:province":"MA",
    "sg:tags":[
        "mattress"
    ],
    "sg:website":"www.sleepys.com/",
    "wof:name":"Sleepy's, The Mattress Professionals",
    "wof:placetype":"venue"
},
  "geometry": {"coordinates":[-71.147719,42.140564],"type":"Point"}
}