{
  "type": "Feature",
  "properties": {
    "addr:full": "267 Boston Rd Chelmsford MA 01824",
    "addr:housenumber": "267",
    "addr:postcode": "01824",
    "addr:street": "Boston Rd",
    "iso:country": "US",
    "sg:address": "267 Boston Rd",
    "sg:city": "Chelmsford",
    "sg:classifiers": [
      {
        "category": "Health Services",
        "subcategory": "Doctor",
        "type": "Services"
      }
    ],
    "sg:phone": "+1 978 663 6666",
    "sg:postcode": "01824",
    "sg:province": "MA",
    "wof:name": "John Berkoben MD",
    "wof:placetype": "venue"
  },
  "geometry": {"coordinates":[-71.334702,42.575298],"type":"Point"}
}
