{
  "type": "Feature",
  "properties": {
    "addr:full":"54 Clevelandtown Rd Edgartown MA 02539",
    "addr:housenumber":"54",
    "addr:postcode":"02539",
    "addr:street":"Clevelandtown Rd",
    "iso:country":"US",
    "sg:address":"54 Clevelandtown Rd",
    "sg:city":"Edgartown",
    "sg:classifiers":[
        {
            "category":"Building & Trades",
            "subcategory":"Electrical",
            "type":"Services"
        }
    ],
    "sg:phone":"+1 508 627 7255",
    "sg:postcode":"02539",
    "sg:province":"MA",
    "sg:tags":[
        "industrial",
        "electrician",
        "contractors-commercial",
        "electric"
    ],
    "wof:name":"Mark A Forbus Electrn",
    "wof:placetype":"venue"
},
  "geometry": {"coordinates":[-70.522598,41.382111],"type":"Point"}
}