{
  "type": "Feature",
  "properties": {
    "addr:full":"1297 Beacon Street Brookline MA 02446",
    "addr:housenumber":"1297",
    "addr:postcode":"02446",
    "addr:street":"Beacon Street",
    "iso:country":"US",
    "sg:address":"1297 Beacon Street",
    "sg:city":"Brookline",
    "sg:classifiers":[
        {
            "category":"Sports & Exercise",
            "subcategory":"Gym",
            "type":"Entertainment"
        }
    ],
    "sg:phone":"+1 617 731 0060",
    "sg:postcode":"02446",
    "sg:province":"MA",
    "sg:tags":[
        "trainer"
    ],
    "wof:name":"Repro Associates",
    "wof:placetype":"venue"
},
  "geometry": {"coordinates":[-71.119989,42.342235],"type":"Point"}
}