{
  "type": "Feature",
  "properties": {
    "addr:full":"454 Lincoln St Franklin MA 02038",
    "addr:housenumber":"454",
    "addr:postcode":"02038",
    "addr:street":"Lincoln St",
    "iso:country":"US",
    "sg:address":"454 Lincoln St",
    "sg:city":"Franklin",
    "sg:classifiers":[
        {
            "category":"Personal",
            "subcategory":"Beauty Salon",
            "type":"Services"
        }
    ],
    "sg:phone":"+1 508 528 9883",
    "sg:postcode":"02038",
    "sg:province":"MA",
    "sg:tags":[
        "shop"
    ],
    "wof:name":"Cut N Curl",
    "wof:placetype":"venue"
},
  "geometry": {"coordinates":[-71.39502899999999,42.106328],"type":"Point"}
}