{
  "type": "Feature",
  "properties": {
    "iso:country":"US",
    "sg:address":"1207 Commercial St",
    "sg:city":"Weymouth",
    "sg:classifiers":[
        {
            "category":"Professional",
            "subcategory":"Secretarial Services",
            "type":"Services"
        }
    ],
    "sg:phone":"+1 781 335 6791",
    "sg:postcode":"02189",
    "sg:province":"MA",
    "sg:tags":[
        "convention",
        "court",
        "reporter"
    ],
    "wof:name":"Leavitt Reporting Svc Inc",
    "wof:placetype":"venue"
},
  "geometry": {"coordinates":[-70.92676,42.21736],"type":"Point"}
}