{
  "type": "Feature",
  "properties": {
    "addr:full":"147 South Rd Pepperell MA 01463",
    "addr:housenumber":"147",
    "addr:postcode":"01463",
    "addr:street":"South Rd",
    "iso:country":"US",
    "sg:address":"147 South Rd",
    "sg:city":"Pepperell",
    "sg:classifiers":[
        {
            "category":"Shopping",
            "subcategory":"Gifts & Souvenirs",
            "type":"Retail Goods"
        }
    ],
    "sg:phone":"+1 978 433 9702",
    "sg:postcode":"01463",
    "sg:province":"MA",
    "sg:tags":[
        "indian"
    ],
    "wof:name":"Buck Skin Gallery",
    "wof:placetype":"venue"
},
  "geometry": {"coordinates":[-71.63420000000001,42.645773],"type":"Point"}
}