{
  "type": "Feature",
  "properties": {
    "addr:full": "926 Norwest Dr Norwood MA 02062",
    "addr:housenumber": "926",
    "addr:postcode": "02062",
    "addr:street": "Norwest Dr",
    "iso:country": "US",
    "sg:address": "926 Norwest Dr",
    "sg:city": "Norwood",
    "sg:classifiers": [
      {
        "category": "Building \u0026 Trades",
        "subcategory": "Locksmith",
        "type": "Services"
      }
    ],
    "sg:phone": "+1 781 269 7096",
    "sg:postcode": "02062",
    "sg:province": "MA",
    "sg:tags": [
      "key"
    ],
    "wof:name": "Emergency Locksmith",
    "wof:placetype": "venue"
  },
  "geometry": {"coordinates":[-71.211248,42.206034],"type":"Point"}
}
