{
  "type": "Feature",
  "properties": {
    "iso:country":"US",
    "sg:address":"20 Genest St",
    "sg:city":"Dracut",
    "sg:classifiers":[
        {
            "category":"Building & Trades",
            "subcategory":"Construction",
            "type":"Services"
        }
    ],
    "sg:phone":"+1   ",
    "sg:postcode":"01826",
    "sg:province":"MA",
    "sg:tags":[
        "house"
    ],
    "wof:name":"S D Construction",
    "wof:placetype":"venue"
},
  "geometry": {"coordinates":[-71.311877,42.668203],"type":"Point"}
}