{
  "type": "Feature",
  "properties": {
    "iso:country":"US",
    "sg:address":"19 Seaverns Ave",
    "sg:city":"Jamaica Plain",
    "sg:classifiers":[
        {
            "category":"Retail",
            "subcategory":"Repair Shop",
            "type":"Services"
        }
    ],
    "sg:phone":"+1   ",
    "sg:postcode":"02130",
    "sg:province":"MA",
    "wof:name":"Nicholas Bundy Woodwind Repair",
    "wof:placetype":"venue"
},
  "geometry": {"coordinates":[-71.112672,42.31196],"type":"Point"}
}