{
  "type": "Feature",
  "properties": {
    "addr:full":"32 Pleasant St Wenham MA 01984",
    "addr:housenumber":"32",
    "addr:postcode":"01984",
    "addr:street":"Pleasant St",
    "iso:country":"US",
    "sg:address":"32 Pleasant St",
    "sg:city":"Wenham",
    "sg:classifiers":[
        {
            "category":"Retail",
            "subcategory":"Repair Shop",
            "type":"Services"
        }
    ],
    "sg:phone":"+1 978 468 7157",
    "sg:postcode":"01984",
    "sg:province":"MA",
    "sg:tags":[
        "equipment",
        "telephone",
        "system"
    ],
    "wof:name":"C Duffy Communications",
    "wof:placetype":"venue"
},
  "geometry": {"coordinates":[-70.895994,42.605488],"type":"Point"}
}