{
  "type": "Feature",
  "properties": {
    "iso:country":"US",
    "sg:address":"315 Mishawum Rd",
    "sg:city":"Woburn",
    "sg:classifiers":[
        {
            "category":"Communications",
            "type":"Services"
        }
    ],
    "sg:phone":"+1 781 503 0481",
    "sg:postcode":"01801",
    "sg:province":"MA",
    "wof:name":"Golden Tree Communications",
    "wof:placetype":"venue"
},
  "geometry": {"coordinates":[-71.131317,42.503979],"type":"Point"}
}