{
  "type": "Feature",
  "properties": {
    "addr:full": "115 Richards Ave Paxton MA 01612",
    "addr:housenumber": "115",
    "addr:postcode": "01612",
    "addr:street": "Richards Ave",
    "iso:country": "US",
    "sg:address": "115 Richards Ave",
    "sg:city": "Paxton",
    "sg:classifiers": [
      {
        "category": "Professional",
        "subcategory": "Lawyer \u0026 Legal Services",
        "type": "Services"
      }
    ],
    "sg:phone": "+1 508 753 3309",
    "sg:postcode": "01612",
    "sg:province": "MA",
    "sg:tags": [
      "plan"
    ],
    "wof:name": "Thos J Aitken",
    "wof:placetype": "venue"
  },
  "geometry": {"coordinates":[-71.927213,42.318916],"type":"Point"}
}
