{
  "type": "Feature",
  "properties": {
    "iso:country":"US",
    "sg:address":"115 Richards Ave",
    "sg:city":"Paxton",
    "sg:classifiers":[
        {
            "category":"Professional",
            "subcategory":"Lawyer & Legal Services",
            "type":"Services"
        }
    ],
    "sg:phone":"+1 508 753 3309",
    "sg:postcode":"01612",
    "sg:province":"MA",
    "sg:tags":[
        "plan"
    ],
    "wof:name":"Thos J Aitken",
    "wof:placetype":"venue"
},
  "geometry": {"coordinates":[-71.92721299999999,42.318916],"type":"Point"}
}