{
  "type": "Feature",
  "properties": {
    "addr:full": "1 Court St Boston MA 02108",
    "addr:housenumber": "1",
    "addr:postcode": "02108",
    "addr:street": "Court St",
    "iso:country": "US",
    "sg:address": "1 Court St",
    "sg:city": "Boston",
    "sg:classifiers": [
      {
        "category": "Banks \u0026 Credit Unions",
        "subcategory": "Investment Brokerage",
        "type": "Services"
      }
    ],
    "sg:phone": "+1 617 248 0202",
    "sg:postcode": "02108",
    "sg:province": "MA",
    "wof:name": "Congress Street Investment",
    "wof:placetype": "venue"
  },
  "geometry": {"coordinates":[-71.058216,42.358951],"type":"Point"}
}
