{
  "type": "Feature",
  "properties": {
    "iso:country":"US",
    "sg:address":"1554 Riverdale St",
    "sg:city":"West Springfield",
    "sg:classifiers":[
        {
            "category":"Restaurant",
            "type":"Food & Drink"
        }
    ],
    "sg:phone":"+1 413 736 9587",
    "sg:postcode":"01089",
    "sg:province":"MA",
    "wof:name":"Galley",
    "wof:placetype":"venue"
},
  "geometry": {"coordinates":[-72.62987099999999,42.14647],"type":"Point"}
}