{
  "type": "Feature",
  "properties": {
    "addr:full": "5 Park St Hopedale MA 01747",
    "addr:housenumber": "5",
    "addr:postcode": "01747",
    "addr:street": "Park St",
    "iso:country": "US",
    "sg:address": "5 Park St",
    "sg:city": "Hopedale",
    "sg:classifiers": [
      {
        "category": "Health Services",
        "subcategory": "Medical Lab",
        "type": "Services"
      }
    ],
    "sg:phone": "+1 508 422 9700",
    "sg:postcode": "01747",
    "sg:province": "MA",
    "sg:tags": [
      "laboratory",
      "testing"
    ],
    "sg:website": "http://www.lotusdental.com",
    "wof:name": "Lotus Dental Lab Corp",
    "wof:placetype": "venue"
  },
  "geometry": {"coordinates":[-71.543085,42.136492],"type":"Point"}
}
