{
  "type": "Feature",
  "properties": {
    "addr:full":"121 Crosby St Lowell MA 01852",
    "addr:housenumber":"121",
    "addr:postcode":"01852",
    "addr:street":"Crosby St",
    "iso:country":"US",
    "sg:address":"121 Crosby St",
    "sg:city":"Lowell",
    "sg:classifiers":[
        {
            "category":"Shopping",
            "type":"Retail Goods"
        }
    ],
    "sg:phone":"+1 978 937 5520",
    "sg:postcode":"01852",
    "sg:province":"MA",
    "sg:tags":[
        "pet",
        "shop"
    ],
    "wof:name":"Emerald City Cattery",
    "wof:placetype":"venue"
},
  "geometry": {"coordinates":[-71.30609699999999,42.633068],"type":"Point"}
}