{
  "type": "Feature",
  "properties": {
    "iso:country":"US",
    "sg:address":"41 Judy Dr",
    "sg:city":"Leominster",
    "sg:classifiers":[
        {
            "category":"Professional",
            "subcategory":"Management & Consulting",
            "type":"Services"
        }
    ],
    "sg:phone":"+1   ",
    "sg:postcode":"01453",
    "sg:province":"MA",
    "sg:tags":[
        "business"
    ],
    "wof:name":"Gwl Consulting",
    "wof:placetype":"venue"
},
  "geometry": {"coordinates":[-71.730047,42.556316],"type":"Point"}
}