{
  "type": "Feature",
  "properties": {
    "addr:full":"1158 Main St Holden MA 01520",
    "addr:housenumber":"1158",
    "addr:postcode":"01520",
    "addr:street":"Main St",
    "iso:country":"US",
    "sg:address":"1158 Main St",
    "sg:city":"Holden",
    "sg:classifiers":[
        {
            "category":"Retail",
            "subcategory":"Funeral Services",
            "type":"Services"
        }
    ],
    "sg:phone":"+1 508 829 4434",
    "sg:postcode":"01520",
    "sg:province":"MA",
    "sg:tags":[
        "director"
    ],
    "wof:name":"Miles Funeral Home",
    "wof:placetype":"venue"
},
  "geometry": {"coordinates":[-71.86197799999999,42.350544],"type":"Point"}
}