{
  "type": "Feature",
  "properties": {
    "addr:full": "33 South St Westborough MA 01581",
    "addr:housenumber": "33",
    "addr:postcode": "01581",
    "addr:street": "South St",
    "iso:country": "US",
    "sg:address": "33 South St",
    "sg:city": "Westborough",
    "sg:classifiers": [
      {
        "category": "Personal",
        "subcategory": "Beauty Salon",
        "type": "Services"
      }
    ],
    "sg:phone": "+1 508 870 1544",
    "sg:postcode": "01581",
    "sg:province": "MA",
    "wof:name": "Studio 21",
    "wof:placetype": "venue"
  },
  "geometry": {"coordinates":[-71.612712,42.268874],"type":"Point"}
}
