{
  "type": "Feature",
  "properties": {
    "addr:full": "193 Quarry St Quincy MA 02169",
    "addr:housenumber": "193",
    "addr:postcode": "02169",
    "addr:street": "Quarry St",
    "iso:country": "US",
    "sg:address": "193 Quarry St",
    "sg:city": "Quincy",
    "sg:classifiers": [
      {
        "category": "Government",
        "subcategory": "Office",
        "type": "Public Place"
      }
    ],
    "sg:phone": "+1 617 472 2707",
    "sg:postcode": "02169",
    "sg:province": "MA",
    "wof:name": "Congress Group",
    "wof:placetype": "venue"
  },
  "geometry": {"coordinates":[-71.01363,42.245253],"type":"Point"}
}
