{
  "type": "Feature",
  "properties": {
    "iso:country":"US",
    "sg:address":"425 Pleasant St",
    "sg:city":"Fall River",
    "sg:classifiers":[
        {
            "category":"Professional",
            "subcategory":"Research",
            "type":"Services"
        }
    ],
    "sg:phone":"+1 508 677 9748",
    "sg:postcode":"02721",
    "sg:province":"MA",
    "sg:tags":[
        "market",
        "analysis"
    ],
    "wof:name":"Customer Retention Systems",
    "wof:placetype":"venue"
},
  "geometry": {"coordinates":[-71.147824,41.698959],"type":"Point"}
}