{
  "type": "Feature",
  "properties": {
    "addr:full":"310 King St Littleton MA 01460",
    "addr:housenumber":"310",
    "addr:postcode":"01460",
    "addr:street":"King St",
    "iso:country":"US",
    "sg:address":"310 King St",
    "sg:city":"Littleton",
    "sg:classifiers":[
        {
            "category":"Organizations",
            "subcategory":"Community Association",
            "type":"Services"
        }
    ],
    "sg:phone":"+1 978 486 3198",
    "sg:postcode":"01460",
    "sg:province":"MA",
    "sg:tags":[
        "fraternal"
    ],
    "wof:name":"Tahattawan Lodge",
    "wof:placetype":"venue"
},
  "geometry": {"coordinates":[-71.483093,42.539242],"type":"Point"}
}