{
  "type": "Feature",
  "properties": {
    "addr:full": "39 Emerson Rd Ste 201 Waltham MA 02451",
    "addr:housenumber": "39",
    "addr:postcode": "02451",
    "addr:street": "Emerson Rd Ste 201",
    "iso:country": "US",
    "sg:address": "39 Emerson Rd Ste 201",
    "sg:city": "Waltham",
    "sg:classifiers": [
      {
        "category": "Real Estate",
        "subcategory": "Real Estate Services",
        "type": "Services"
      },
      {
        "category": "Real Estate",
        "subcategory": "Surveying",
        "type": "Services"
      },
      {
        "category": "Real Estate",
        "subcategory": "Real Estate Agent",
        "type": "Services"
      }
    ],
    "sg:phone": "+1 781 894 0507",
    "sg:postcode": "02451",
    "sg:province": "MA",
    "sg:tags": [
      "buyer",
      "industrial",
      "appraisers-commercial",
      "broker",
      "appraiser"
    ],
    "wof:name": "Commonwealth East Appraisal",
    "wof:placetype": "venue"
  },
  "geometry": {"coordinates":[-71.238585,42.381401],"type":"Point"}
}
