{
  "type": "Feature",
  "properties": {
    "iso:country":"US",
    "sg:address":"474 Dorchester Ave",
    "sg:city":"Boston",
    "sg:classifiers":[
        {
            "category":"Manufacturing",
            "subcategory":"Tools & Machinery",
            "type":"Manufacturing & Wholesale Goods"
        },
        {
            "category":"Wholesale",
            "subcategory":"Electrical",
            "type":"Manufacturing & Wholesale Goods"
        },
        {
            "category":"Shopping",
            "subcategory":"Computers & Home Electronics",
            "type":"Retail Goods"
        }
    ],
    "sg:phone":"+1 617 464 5790",
    "sg:postcode":"02127",
    "sg:province":"MA",
    "sg:tags":[
        "electric",
        "supply",
        "supplies-wholesale",
        "equipment",
        "consumer",
        "manufacturer"
    ],
    "sg:website":"http://www.columbiaelectricsupply.com",
    "wof:name":"Allen Supply Inc.",
    "wof:placetype":"venue"
},
  "geometry": {"coordinates":[-71.057007,42.33284],"type":"Point"}
}