{
  "type": "Feature",
  "properties": {
    "iso:country":"US",
    "sg:address":"14 Union Point Rd",
    "sg:city":"Webster",
    "sg:classifiers":[
        {
            "category":"Home & Garden",
            "subcategory":"Furniture",
            "type":"Retail Goods"
        }
    ],
    "sg:phone":"+1 508 450 9472",
    "sg:postcode":"01570",
    "sg:province":"MA",
    "sg:tags":[
        "store"
    ],
    "wof:name":"Parkers Collection",
    "wof:placetype":"venue"
},
  "geometry": {"coordinates":[-71.856919,42.039642],"type":"Point"}
}