{
  "type": "Feature",
  "properties": {
    "addr:full":"54 JFK St Cambridge MA 02138",
    "addr:housenumber":"54",
    "addr:postcode":"02138",
    "addr:street":"Jfk St",
    "iso:country":"US",
    "sg:address":"54 JFK St",
    "sg:city":"Cambridge",
    "sg:classifiers":[
        {
            "category":"Juice Bar",
            "subcategory":"None",
            "type":"Food & Drink"
        },
        {
            "category":"Coffee & Tea",
            "type":"Food & Drink"
        }
    ],
    "sg:phone":"+1 617 945 0017",
    "sg:postcode":"02138",
    "sg:province":"MA",
    "sg:tags":[
        "smoothy"
    ],
    "wof:name":"Boston Tea Stop",
    "wof:placetype":"venue"
},
  "geometry": {"coordinates":[-71.120639,42.37183],"type":"Point"}
}