{
  "type": "Feature",
  "properties": {
    "iso:country":"US",
    "sg:address":"5 Masonic Home Rd",
    "sg:city":"Charlton",
    "sg:classifiers":[
        {
            "category":"Insurance",
            "subcategory":"Hazard Insurance",
            "type":"Services"
        }
    ],
    "sg:phone":"+1 508 248 7400",
    "sg:postcode":"01507",
    "sg:province":"MA",
    "sg:tags":[
        "commercial",
        "business"
    ],
    "sg:website":"http://www.oxfordinsurance.com",
    "wof:name":"Oxford Insurance Agency Inc",
    "wof:placetype":"venue"
},
  "geometry": {"coordinates":[-71.986053,42.145439],"type":"Point"}
}