{
  "type": "Feature",
  "properties": {
    "addr:full": "81 Holland St Saugus MA 01906",
    "addr:housenumber": "81",
    "addr:postcode": "01906",
    "addr:street": "Holland St",
    "iso:country": "US",
    "sg:address": "81 Holland St",
    "sg:city": "Saugus",
    "sg:classifiers": [
      {
        "category": "Building \u0026 Trades",
        "subcategory": "Construction",
        "type": "Services"
      }
    ],
    "sg:phone": "+1 781 231 7931",
    "sg:postcode": "01906",
    "sg:province": "MA",
    "sg:tags": [
      "woodworker"
    ],
    "wof:name": "Northeast Machinery Svc",
    "wof:placetype": "venue"
  },
  "geometry": {"coordinates":[-71.005976,42.471882],"type":"Point"}
}
