{
  "type": "Feature",
  "properties": {
    "iso:country":"US",
    "sg:address":"1 Lowell Research Center Dr",
    "sg:city":"Lowell",
    "sg:classifiers":[
        {
            "category":"Manufacturing",
            "subcategory":"Tools & Machinery",
            "type":"Manufacturing & Wholesale Goods"
        }
    ],
    "sg:phone":"+1 978 275 0800",
    "sg:postcode":"01852",
    "sg:province":"MA",
    "sg:tags":[
        "devices"
    ],
    "wof:name":"Thermo Electron Corp",
    "wof:placetype":"venue"
},
  "geometry": {"coordinates":[-71.277451,42.627089],"type":"Point"}
}