{
  "type": "Feature",
  "properties": {
    "addr:full": "873 Millbury St Worcester MA 01607",
    "addr:housenumber": "873",
    "addr:postcode": "01607",
    "addr:street": "Millbury St",
    "iso:country": "US",
    "sg:address": "873 Millbury St",
    "sg:city": "Worcester",
    "sg:classifiers": [
      {
        "category": "Restaurant",
        "type": "Food \u0026 Drink"
      }
    ],
    "sg:phone": "+1 508 757 8040",
    "sg:postcode": "01607",
    "sg:province": "MA",
    "sg:tags": [
      "eating"
    ],
    "wof:name": "Vinny's Fish \u0026 Chips \u0026 More",
    "wof:placetype": "venue"
  },
  "geometry": {"coordinates":[-71.794443,42.232327],"type":"Point"}
}
