{
  "type": "Feature",
  "properties": {
    "addr:full": "320 Elm St Marlborough MA 01752",
    "addr:housenumber": "320",
    "addr:postcode": "01752",
    "addr:street": "Elm St",
    "iso:country": "US",
    "sg:address": "320 Elm St",
    "sg:city": "Marlborough",
    "sg:classifiers": [
      {
        "category": "Manufacturing",
        "subcategory": "Tools \u0026 Machinery",
        "type": "Manufacturing \u0026 Wholesale Goods"
      }
    ],
    "sg:phone": "+1 508 481 7495",
    "sg:postcode": "01752",
    "sg:province": "MA",
    "sg:tags": [
      "equipment",
      "photographic"
    ],
    "sg:website": "www.intl-polarizer.com",
    "wof:name": "International Polarizer Inc",
    "wof:placetype": "venue"
  },
  "geometry": {"coordinates":[-71.571934,42.347441],"type":"Point"}
}
