{
  "type": "Feature",
  "properties": {
    "iso:country":"US",
    "sg:address":"320 Elm St",
    "sg:city":"Marlborough",
    "sg:classifiers":[
        {
            "category":"Manufacturing",
            "subcategory":"Tools & Machinery",
            "type":"Manufacturing & Wholesale Goods"
        }
    ],
    "sg:phone":"+1 508 481 7495",
    "sg:postcode":"01752",
    "sg:province":"MA",
    "sg:tags":[
        "equipment",
        "photographic"
    ],
    "sg:website":"www.intl-polarizer.com",
    "wof:name":"International Polarizer Inc",
    "wof:placetype":"venue"
},
  "geometry": {"coordinates":[-71.571934,42.347441],"type":"Point"}
}