{
  "type": "Feature",
  "properties": {
    "addr:full": "464 Commonwealth Ave Boston MA 02215",
    "addr:housenumber": "464",
    "addr:postcode": "02215",
    "addr:street": "Commonwealth Ave",
    "iso:country": "US",
    "sg:address": "464 Commonwealth Ave",
    "sg:city": "Boston",
    "sg:classifiers": [
      {
        "category": "Professional",
        "subcategory": "Accounting \u0026 Tax Preparation",
        "type": "Services"
      }
    ],
    "sg:phone": "+1 617 266 5100",
    "sg:postcode": "02215",
    "sg:province": "MA",
    "sg:tags": [
      "accountant"
    ],
    "wof:name": "Rivet Robert P CPA",
    "wof:placetype": "venue"
  },
  "geometry": {"coordinates":[-71.093002,42.348801],"type":"Point"}
}
