{
  "type": "Feature",
  "properties": {
    "iso:country":"US",
    "sg:address":"464 Commonwealth Ave",
    "sg:city":"Boston",
    "sg:classifiers":[
        {
            "category":"Professional",
            "subcategory":"Accounting & Tax Preparation",
            "type":"Services"
        }
    ],
    "sg:phone":"+1 617 266 5100",
    "sg:postcode":"02215",
    "sg:province":"MA",
    "sg:tags":[
        "accountant"
    ],
    "wof:name":"Rivet Robert P CPA",
    "wof:placetype":"venue"
},
  "geometry": {"coordinates":[-71.093002,42.348801],"type":"Point"}
}