{
  "type": "Feature",
  "properties": {
    "addr:full":"13 Bartlet St Andover MA 01810",
    "addr:housenumber":"13",
    "addr:postcode":"01810",
    "addr:street":"Bartlet St",
    "iso:country":"US",
    "sg:address":"13 Bartlet St",
    "sg:city":"Andover",
    "sg:classifiers":[
        {
            "category":"Real Estate",
            "subcategory":"Real Estate Agent",
            "type":"Services"
        }
    ],
    "sg:phone":"+1 978 475 1121",
    "sg:postcode":"01810",
    "sg:province":"MA",
    "wof:name":"Harkins Real Estate & Auction",
    "wof:placetype":"venue"
},
  "geometry": {"coordinates":[-71.138199,42.655901],"type":"Point"}
}