{
  "type": "Feature",
  "properties": {
    "addr:full": "12 Sandy Ave Canton MA 02021",
    "addr:housenumber": "12",
    "addr:postcode": "02021",
    "addr:street": "Sandy Ave",
    "iso:country": "US",
    "sg:address": "12 Sandy Ave",
    "sg:city": "Canton",
    "sg:classifiers": [
      {
        "category": "Professional",
        "subcategory": "Lawyer \u0026 Legal Services",
        "type": "Services"
      }
    ],
    "sg:phone": "+1 781 575 0037",
    "sg:postcode": "02021",
    "sg:province": "MA",
    "sg:tags": [
      "attorney"
    ],
    "sg:website": "http://www.rogerlevine.com",
    "wof:name": "Roger Levine",
    "wof:placetype": "venue"
  },
  "geometry": {"coordinates":[-71.114689,42.174833],"type":"Point"}
}
