{
  "type": "Feature",
  "properties": {
    "addr:full": "70 Summer St Malden MA 02148",
    "addr:housenumber": "70",
    "addr:postcode": "02148",
    "addr:street": "Summer St",
    "iso:country": "US",
    "sg:address": "70 Summer St",
    "sg:city": "Malden",
    "sg:classifiers": [
      {
        "category": "Building \u0026 Trades",
        "subcategory": "Construction",
        "type": "Services"
      }
    ],
    "sg:phone": "+1 781 322 9313",
    "sg:postcode": "02148",
    "sg:province": "MA",
    "sg:tags": [
      "glass"
    ],
    "wof:name": "Window Remedies",
    "wof:placetype": "venue"
  },
  "geometry": {"coordinates":[-71.074017,42.428633],"type":"Point"}
}
