{
  "type": "Feature",
  "properties": {
    "iso:country":"US",
    "sg:address":"24 Reservoir St",
    "sg:city":"Milford",
    "sg:classifiers":[
        {
            "category":"Professional",
            "type":"Services"
        }
    ],
    "sg:phone":"+1   ",
    "sg:postcode":"01757",
    "sg:province":"MA",
    "wof:name":"Ecreativa",
    "wof:placetype":"venue"
},
  "geometry": {"coordinates":[-71.55108,42.172188],"type":"Point"}
}