{
  "type": "Feature",
  "properties": {
    "addr:full":"3 Beacon St Somerville MA 02143",
    "addr:housenumber":"3",
    "addr:postcode":"02143",
    "addr:street":"Beacon St",
    "iso:country":"US",
    "sg:address":"3 Beacon St",
    "sg:city":"Somerville",
    "sg:classifiers":[
        {
            "category":"Bars & Pubs",
            "subcategory":"Lounge",
            "type":"Food & Drink"
        },
        {
            "category":"Restaurant",
            "type":"Food & Drink"
        }
    ],
    "sg:phone":"+1 617 576 0006",
    "sg:postcode":"02143",
    "sg:province":"MA",
    "sg:tags":[
        "traditional",
        "american"
    ],
    "sg:website":"trinastarlitelounge.com",
    "wof:name":"Trina's Starlite Lounge",
    "wof:placetype":"venue"
},
  "geometry": {"coordinates":[-71.101648,42.37443],"type":"Point"}
}