{
  "type": "Feature",
  "properties": {
    "addr:full": "3 Beacon St Somerville MA 02143",
    "addr:housenumber": "3",
    "addr:postcode": "02143",
    "addr:street": "Beacon St",
    "iso:country": "US",
    "ovtr:label": "Trina's Starlite Lounge, 3 Beacon St Somerville MA US",
    "ovtr:similarity": 2.8372719287872314,
    "sg:address": "3 Beacon St",
    "sg:city": "Somerville",
    "sg:classifiers": [
      {
        "category": "Bars \u0026 Pubs",
        "subcategory": "Lounge",
        "type": "Food \u0026 Drink"
      },
      {
        "category": "Restaurant",
        "type": "Food \u0026 Drink"
      }
    ],
    "sg:phone": "+1 617 576 0006",
    "sg:postcode": "02143",
    "sg:province": "MA",
    "sg:tags": [
      "traditional",
      "american"
    ],
    "sg:website": "trinastarlitelounge.com",
    "wof:name": "Trina's Starlite Lounge",
    "wof:placetype": "venue"
  },
  "geometry": {"coordinates":[-71.101648,42.37443],"type":"Point"}
}
