{
  "type": "Feature",
  "properties": {
    "iso:country":"US",
    "sg:address":"64 Brighton Ave Ste B",
    "sg:city":"Allston",
    "sg:classifiers":[
        {
            "category":"Professional",
            "subcategory":"Advertising",
            "type":"Services"
        },
        {
            "category":"Manufacturing",
            "subcategory":"Signs",
            "type":"Manufacturing & Wholesale Goods"
        }
    ],
    "sg:phone":"+1 617 536 5792",
    "sg:postcode":"02134",
    "sg:province":"MA",
    "sg:tags":[
        "specialty"
    ],
    "wof:name":"Ardon Vinyl Graphics",
    "wof:placetype":"venue"
},
  "geometry": {"coordinates":[-71.12835699999999,42.352551],"type":"Point"}
}