{
  "type": "Feature",
  "properties": {
    "addr:full": "3920 Mystic Valley Pkwy Medford MA 02155",
    "addr:housenumber": "3920",
    "addr:postcode": "02155",
    "addr:street": "Mystic Valley Pkwy",
    "iso:country": "US",
    "sg:address": "3920 Mystic Valley Pkwy",
    "sg:city": "Medford",
    "sg:classifiers": [
      {
        "category": "Building \u0026 Trades",
        "subcategory": "Electrical",
        "type": "Services"
      }
    ],
    "sg:phone": "+1 781 391 1773",
    "sg:postcode": "02155",
    "sg:province": "MA",
    "sg:tags": [
      "electric",
      "contractor"
    ],
    "wof:name": "Souza Electric",
    "wof:placetype": "venue"
  },
  "geometry": {"coordinates":[-71.088726,42.404049],"type":"Point"}
}
