{
  "type": "Feature",
  "properties": {
    "iso:country":"US",
    "sg:address":"263 Carpenter Hill Rd",
    "sg:city":"Charlton",
    "sg:classifiers":[
        {
            "category":"Building & Trades",
            "subcategory":"Construction",
            "type":"Services"
        }
    ],
    "sg:phone":"+1   ",
    "sg:postcode":"01507",
    "sg:province":"MA",
    "sg:tags":[
        "contractor",
        "carpentry"
    ],
    "wof:name":"David Barbale",
    "wof:placetype":"venue"
},
  "geometry": {"coordinates":[-72.011556,42.116206],"type":"Point"}
}