{
  "type": "Feature",
  "properties": {
    "iso:country":"US",
    "sg:address":"24 Center St",
    "sg:city":"Newburyport",
    "sg:classifiers":[
        {
            "category":"Professional",
            "subcategory":"Lawyer & Legal Services",
            "type":"Services"
        }
    ],
    "sg:phone":"+1 978 465 5022",
    "sg:postcode":"01950",
    "sg:province":"MA",
    "wof:name":"Rogal James L Atty",
    "wof:placetype":"venue"
},
  "geometry": {"coordinates":[-70.86889600000001,42.810501],"type":"Point"}
}