{
  "type": "Feature",
  "properties": {
    "iso:country":"US",
    "sg:address":"26 White Oak Trl",
    "sg:city":"Centerville",
    "sg:classifiers":[
        {
            "category":"Home & Garden",
            "subcategory":"Garden Supply",
            "type":"Retail Goods"
        }
    ],
    "sg:phone":"+1 508 771 2219",
    "sg:postcode":"02632",
    "sg:province":"MA",
    "sg:tags":[
        "sprinkler"
    ],
    "wof:name":"Grass Roots Irrigation",
    "wof:placetype":"venue"
},
  "geometry": {"coordinates":[-70.35584299999999,41.668218],"type":"Point"}
}