{
  "type": "Feature",
  "properties": {
    "iso:country":"US",
    "sg:address":"1514 Allen St",
    "sg:city":"Springfield",
    "sg:classifiers":[
        {
            "category":"Real Estate",
            "subcategory":"Real Estate Agent",
            "type":"Services"
        }
    ],
    "sg:phone":"+1 413 426 9529",
    "sg:postcode":"01118",
    "sg:province":"MA",
    "wof:name":"Century 21 Hometown",
    "wof:placetype":"venue"
},
  "geometry": {"coordinates":[-72.507701,42.094108],"type":"Point"}
}