{
  "type": "Feature",
  "properties": {
    "iso:country":"US",
    "sg:address":"802 State Rd",
    "sg:city":"Richmond",
    "sg:classifiers":[
        {
            "category":"Travel",
            "subcategory":"Hotels & Motels",
            "type":"Entertainment"
        }
    ],
    "sg:phone":"+1 413 698 2566",
    "sg:postcode":"01254",
    "sg:province":"MA",
    "sg:tags":[
        "breakfast",
        "accommodation",
        "bed"
    ],
    "sg:website":"www.innatrichmond.com",
    "wof:name":"Inn At Richmond",
    "wof:placetype":"venue"
},
  "geometry": {"coordinates":[-73.366754,42.400079],"type":"Point"}
}