{
  "type": "Feature",
  "properties": {
    "addr:full": "802 State Rd Richmond MA 01254",
    "addr:housenumber": "802",
    "addr:postcode": "01254",
    "addr:street": "State Rd",
    "iso:country": "US",
    "ovtr:label": "Inn At Richmond, 802 State Rd Richmond MA US",
    "ovtr:similarity": 3.974392890930176,
    "sg:address": "802 State Rd",
    "sg:city": "Richmond",
    "sg:classifiers": [
      {
        "category": "Travel",
        "subcategory": "Hotels \u0026 Motels",
        "type": "Entertainment"
      }
    ],
    "sg:phone": "+1 413 698 2566",
    "sg:postcode": "01254",
    "sg:province": "MA",
    "sg:tags": [
      "breakfast",
      "accommodation",
      "bed"
    ],
    "sg:website": "www.innatrichmond.com",
    "wof:name": "Inn At Richmond",
    "wof:placetype": "venue"
  },
  "geometry": {"coordinates":[-73.366754,42.400079],"type":"Point"}
}
