{
  "type": "Feature",
  "properties": {
    "addr:full": "19 Homer St Worcester MA 01602",
    "addr:housenumber": "19",
    "addr:postcode": "01602",
    "addr:street": "Homer St",
    "iso:country": "US",
    "sg:address": "19 Homer St",
    "sg:city": "Worcester",
    "sg:classifiers": [
      {
        "category": "Professional",
        "subcategory": "Computer Services",
        "type": "Services"
      }
    ],
    "sg:phone": "+1 508 853 1215",
    "sg:postcode": "01602",
    "sg:province": "MA",
    "sg:tags": [
      "consultant",
      "designer"
    ],
    "wof:name": "Alternatives Corp",
    "wof:placetype": "venue"
  },
  "geometry": {"coordinates":[-71.813738,42.273909],"type":"Point"}
}
