{
  "type": "Feature",
  "properties": {
    "addr:full":"57 Bedford Street Lexington MA 02420",
    "addr:housenumber":"57",
    "addr:postcode":"02420",
    "addr:street":"Bedford Street",
    "iso:country":"US",
    "sg:address":"57 Bedford Street",
    "sg:city":"Lexington",
    "sg:classifiers":[
        {
            "category":"Real Estate",
            "subcategory":"Architect",
            "type":"Services"
        }
    ],
    "sg:phone":"+1 781 674 2290",
    "sg:postcode":"02420",
    "sg:province":"MA",
    "wof:name":"D PA Architects",
    "wof:placetype":"venue"
},
  "geometry": {"coordinates":[-71.23293200000001,42.453449],"type":"Point"}
}