{
  "type": "Feature",
  "properties": {
    "addr:full":"16-18 North Street Boston MA 02109",
    "addr:housenumber":"16-18",
    "addr:postcode":"02109",
    "addr:street":"North Street",
    "iso:country":"US",
    "sg:address":"16-18 North Street",
    "sg:city":"Boston",
    "sg:classifiers":[
        {
            "category":"Bars & Pubs",
            "type":"Food & Drink"
        }
    ],
    "sg:postcode":"02109",
    "sg:province":"MA",
    "wof:name":"The Red Bar",
    "wof:placetype":"venue"
},
  "geometry": {"coordinates":[-71.056,42.3606],"type":"Point"}
}