{
  "type": "Feature",
  "properties": {
    "iso:country":"US",
    "sg:address":"1104 Pleasant St",
    "sg:city":"Worcester",
    "sg:classifiers":[
        {
            "category":"Personal",
            "subcategory":"Barber",
            "type":"Services"
        }
    ],
    "sg:phone":"+1 508 753 5006",
    "sg:postcode":"01602",
    "sg:province":"MA",
    "wof:name":"Bob's Barber Shop",
    "wof:placetype":"venue"
},
  "geometry": {"coordinates":[-71.85292699999999,42.278224],"type":"Point"}
}