{
  "type": "Feature",
  "properties": {
    "addr:full": "95 Glenville Ave Allston MA 02134",
    "addr:housenumber": "95",
    "addr:postcode": "02134",
    "addr:street": "Glenville Ave",
    "iso:country": "US",
    "sg:address": "95 Glenville Ave",
    "sg:city": "Allston",
    "sg:classifiers": [
      {
        "category": "Building \u0026 Trades",
        "subcategory": "Locksmith",
        "type": "Services"
      }
    ],
    "sg:phone": "+1 617 206 2473",
    "sg:postcode": "02134",
    "sg:province": "MA",
    "sg:tags": [
      "key"
    ],
    "wof:name": "24 Hour A Locksmith",
    "wof:placetype": "venue"
  },
  "geometry": {"coordinates":[-71.135219,42.349408],"type":"Point"}
}
