{
  "type": "Feature",
  "properties": {
    "iso:country":"US",
    "sg:address":"541 South St",
    "sg:city":"Wrentham",
    "sg:classifiers":[
        {
            "category":"Retail",
            "subcategory":"Repair Shop",
            "type":"Services"
        }
    ],
    "sg:phone":"+1 508 384 0300",
    "sg:postcode":"02093",
    "sg:province":"MA",
    "sg:tags":[
        "lock",
        "locksmith"
    ],
    "wof:name":"Franklin Lock & Safe",
    "wof:placetype":"venue"
},
  "geometry": {"coordinates":[-71.34591,42.0507],"type":"Point"}
}