{
  "type": "Feature",
  "properties": {
    "iso:country":"US",
    "sg:address":"93 Longmeadow Ave",
    "sg:city":"Worcester",
    "sg:classifiers":[
        {
            "category":"Manufacturing",
            "subcategory":"Printing",
            "type":"Manufacturing & Wholesale Goods"
        }
    ],
    "sg:phone":"+1 508 853 0781",
    "sg:postcode":"01606",
    "sg:province":"MA",
    "sg:tags":[
        "printer"
    ],
    "wof:name":"Guiding Channels",
    "wof:placetype":"venue"
},
  "geometry": {"coordinates":[-71.78447799999999,42.303478],"type":"Point"}
}