{
  "type": "Feature",
  "properties": {
    "iso:country":"US",
    "sg:address":"40 South St",
    "sg:city":"Foxboro",
    "sg:classifiers":[
        {
            "category":"Government",
            "subcategory":"Office",
            "type":"Public Place"
        }
    ],
    "sg:phone":"+1   ",
    "sg:postcode":"02035",
    "sg:province":"MA",
    "sg:tags":[
        "executive"
    ],
    "wof:name":"Neponset Reservoir Restoration",
    "wof:placetype":"venue"
},
  "geometry": {"coordinates":[-71.250175,42.063692],"type":"Point"}
}