{
  "type": "Feature",
  "properties": {
    "addr:full":"57 Cannon Rock Rd Lynn MA 01904",
    "addr:housenumber":"57",
    "addr:postcode":"01904",
    "addr:street":"Cannon Rock Rd",
    "iso:country":"US",
    "sg:address":"57 Cannon Rock Rd",
    "sg:city":"Lynn",
    "sg:classifiers":[
        {
            "category":"Home & Garden",
            "subcategory":"Carpets & Floor Coverings",
            "type":"Retail Goods"
        }
    ],
    "sg:phone":"+1 781 592 4642",
    "sg:postcode":"01904",
    "sg:province":"MA",
    "sg:tags":[
        "material"
    ],
    "wof:name":"Kenney Floors",
    "wof:placetype":"venue"
},
  "geometry": {"coordinates":[-70.967338,42.500492],"type":"Point"}
}