{
  "type": "Feature",
  "properties": {
    "iso:country":"US",
    "sg:address":"36 Dean St",
    "sg:city":"Norton",
    "sg:classifiers":[
        {
            "category":"Wholesale",
            "subcategory":"Auto Parts",
            "type":"Manufacturing & Wholesale Goods"
        }
    ],
    "sg:phone":"+1 508 285 7301",
    "sg:postcode":"02766",
    "sg:province":"MA",
    "sg:tags":[
        "automobile",
        "rebuilt"
    ],
    "wof:name":"Goosebrook Garage",
    "wof:placetype":"venue"
},
  "geometry": {"coordinates":[-71.201784,41.938689],"type":"Point"}
}