{
  "type": "Feature",
  "properties": {
    "addr:full": "617 Lexington St Waltham MA 02452",
    "addr:housenumber": "617",
    "addr:postcode": "02452",
    "addr:street": "Lexington St",
    "iso:country": "US",
    "sg:address": "617 Lexington St",
    "sg:city": "Waltham",
    "sg:classifiers": [
      {
        "category": "Education",
        "subcategory": "School",
        "type": "Public Place"
      }
    ],
    "sg:phone": "+1 781 893 8050",
    "sg:postcode": "02452",
    "sg:province": "MA",
    "wof:name": "Public Schl Admin Offc",
    "wof:placetype": "venue"
  },
  "geometry": {"coordinates":[-71.235585,42.396725],"type":"Point"}
}
