{
  "type": "Feature",
  "properties": {
    "addr:full": "3 Amboy Ct Springfield MA 01105",
    "addr:housenumber": "3",
    "addr:postcode": "01105",
    "addr:street": "Amboy Ct",
    "iso:country": "US",
    "sg:address": "3 Amboy Ct",
    "sg:city": "Springfield",
    "sg:classifiers": [
      {
        "category": "Retail",
        "subcategory": "Auto Repair",
        "type": "Services"
      }
    ],
    "sg:phone": "+1 413 785 1357",
    "sg:postcode": "01105",
    "sg:province": "MA",
    "sg:tags": [
      "spring"
    ],
    "wof:name": "Frank L Ferrara Spring Works",
    "wof:placetype": "venue"
  },
  "geometry": {"coordinates":[-72.578245,42.114579],"type":"Point"}
}
