{
  "type": "Feature",
  "properties": {
    "iso:country":"US",
    "sg:address":"362 Lowell St",
    "sg:city":"Andover",
    "sg:classifiers":[
        {
            "category":"Professional",
            "subcategory":"Business Services",
            "type":"Services"
        }
    ],
    "sg:phone":"+1 978 858 5000",
    "sg:postcode":"01810",
    "sg:province":"MA",
    "sg:tags":[
        "inspection"
    ],
    "sg:website":"http://www.raytheon.com",
    "wof:name":"Rsic",
    "wof:placetype":"venue"
},
  "geometry": {"coordinates":[-71.191475,42.643689],"type":"Point"}
}