{
  "type": "Feature",
  "properties": {
    "iso:country":"US",
    "sg:address":"60 Broad St",
    "sg:city":"Westfield",
    "sg:classifiers":[
        {
            "category":"Organizations",
            "subcategory":"Religious Organization",
            "type":"Services"
        }
    ],
    "sg:phone":"+1 413 568 1417",
    "sg:postcode":"01085",
    "sg:province":"MA",
    "sg:tags":[
        "church"
    ],
    "wof:name":"St John's Lutheran Church",
    "wof:placetype":"venue"
},
  "geometry": {"coordinates":[-72.74813399999999,42.117665],"type":"Point"}
}