{
  "type": "Feature",
  "properties": {
    "addr:full": "60 Broad St Westfield MA 01085",
    "addr:housenumber": "60",
    "addr:postcode": "01085",
    "addr:street": "Broad St",
    "iso:country": "US",
    "ovtr:label": "St. John's Lutheran Church, 60 Broad St Westfield MA US",
    "ovtr:similarity": 3.4785330295562744,
    "sg:address": "60 Broad St",
    "sg:city": "Westfield",
    "sg:classifiers": [
      {
        "category": "Organizations",
        "subcategory": "Religious Organization",
        "type": "Services"
      }
    ],
    "sg:phone": "+1 413 568 1417",
    "sg:postcode": "01085",
    "sg:province": "MA",
    "sg:tags": [
      "church"
    ],
    "wof:name": "St John's Lutheran Church",
    "wof:placetype": "venue"
  },
  "geometry": {"coordinates":[-72.748134,42.117665],"type":"Point"}
}
