{
  "type": "Feature",
  "properties": {
    "iso:country":"US",
    "sg:address":"38 Main St",
    "sg:city":"Northampton",
    "sg:classifiers":[
        {
            "category":"Health Services",
            "subcategory":"Doctor",
            "type":"Services"
        }
    ],
    "sg:phone":"+1 413 586 1146",
    "sg:postcode":"01060",
    "sg:province":"MA",
    "sg:tags":[
        "physician",
        "surgeon"
    ],
    "wof:name":"William B White MD",
    "wof:placetype":"venue"
},
  "geometry": {"coordinates":[-72.629699,42.319523],"type":"Point"}
}