{
  "type": "Feature",
  "properties": {
    "addr:full":"431 Main St Amesbury MA 01913",
    "addr:housenumber":"431",
    "addr:postcode":"01913",
    "addr:street":"Main St",
    "iso:country":"US",
    "sg:address":"431 Main St",
    "sg:city":"Amesbury",
    "sg:classifiers":[
        {
            "category":"Professional",
            "subcategory":"Computer Services",
            "type":"Services"
        }
    ],
    "sg:phone":"+1 978 388 5666",
    "sg:postcode":"01913",
    "sg:province":"MA",
    "sg:tags":[
        "consultant"
    ],
    "wof:name":"Interspeed Computer Svc",
    "wof:placetype":"venue"
},
  "geometry": {"coordinates":[-70.917267,42.843401],"type":"Point"}
}