{
  "type": "Feature",
  "properties": {
    "addr:full": "3 Mill Ln Scituate MA 02025",
    "addr:housenumber": "3",
    "addr:postcode": "02025",
    "addr:street": "Mill Ln",
    "iso:country": "US",
    "sg:address": "3 Mill Ln",
    "sg:city": "Scituate",
    "sg:classifiers": [
      {
        "category": "Sports \u0026 Exercise",
        "subcategory": "Gym",
        "type": "Entertainment"
      }
    ],
    "sg:phone": "+1 781 544 0988",
    "sg:postcode": "02025",
    "sg:province": "MA",
    "sg:tags": [
      "spa",
      "health"
    ],
    "wof:name": "Beauty Therapies",
    "wof:placetype": "venue"
  },
  "geometry": {"coordinates":[-70.809193,42.215937],"type":"Point"}
}
