{
  "type": "Feature",
  "properties": {
    "iso:country":"US",
    "sg:address":"100 Cambridgeside Pl",
    "sg:city":"Cambridge",
    "sg:phone":"+1 617 494 1338",
    "sg:postcode":"02141",
    "sg:province":"MA",
    "sg:website":"http://www.abercrombiekids.com",
    "wof:name":"abercrombie",
    "wof:placetype":"venue"
},
  "geometry": {"coordinates":[-71.07567,42.36694],"type":"Point"}
}