{
  "type": "Feature",
  "properties": {
    "addr:full":"400 Washington St Braintree MA 02184",
    "addr:housenumber":"400",
    "addr:postcode":"02184",
    "addr:street":"Washington St",
    "iso:country":"US",
    "sg:address":"400 Washington St",
    "sg:city":"Braintree",
    "sg:classifiers":[
        {
            "category":"Manufacturing",
            "subcategory":"Retail Goods",
            "type":"Manufacturing & Wholesale Goods"
        }
    ],
    "sg:phone":"+1 781 849 0882",
    "sg:postcode":"02184",
    "sg:province":"MA",
    "sg:tags":[
        "manufacturer"
    ],
    "wof:name":"ZBS Industries",
    "wof:placetype":"venue"
},
  "geometry": {"coordinates":[-71.00354900000001,42.219469],"type":"Point"}
}