{
  "type": "Feature",
  "properties": {
    "addr:full": "295 Plymouth St Halifax MA 02338",
    "addr:housenumber": "295",
    "addr:postcode": "02338",
    "addr:street": "Plymouth St",
    "iso:country": "US",
    "sg:address": "295 Plymouth St",
    "sg:city": "Halifax",
    "sg:classifiers": [
      {
        "category": "Utilities",
        "subcategory": "Mobile Phone",
        "type": "Services"
      },
      {
        "category": "Shopping",
        "subcategory": "Mobile Phones",
        "type": "Retail Goods"
      },
      {
        "category": "Utilities",
        "subcategory": "Telephone",
        "type": "Services"
      },
      {
        "category": "Professional",
        "subcategory": "Computer Services",
        "type": "Services"
      }
    ],
    "sg:postcode": "02338",
    "sg:province": "MA",
    "sg:tags": [
      "telecommunication",
      "supply",
      "communication",
      "system",
      "wireless",
      "equipment",
      "cellular"
    ],
    "sg:website": "http://clickserve.dartsearch.net/link/click?lid=43000000308049899",
    "wof:name": "T-Mobile",
    "wof:placetype": "venue"
  },
  "geometry": {"coordinates":[-70.844589,41.99564],"type":"Point"}
}
