{
  "type": "Feature",
  "properties": {
    "iso:country":"US",
    "sg:address":"30 Abbott St",
    "sg:city":"Newton",
    "sg:classifiers":[
        {
            "category":"Professional",
            "subcategory":"Business Services",
            "type":"Services"
        }
    ],
    "sg:phone":"+1   ",
    "sg:postcode":"02464",
    "sg:province":"MA",
    "wof:name":"Nelson Foundation Corp",
    "wof:placetype":"venue"
},
  "geometry": {"coordinates":[-71.218658,42.307293],"type":"Point"}
}