{
  "type": "Feature",
  "properties": {
    "iso:country":"US",
    "sg:address":"234 Quincy Ave",
    "sg:city":"Quincy",
    "sg:classifiers":[
        {
            "category":"Home & Garden",
            "subcategory":"Furniture",
            "type":"Retail Goods"
        },
        {
            "category":"Manufacturing",
            "subcategory":"Furniture",
            "type":"Manufacturing & Wholesale Goods"
        },
        {
            "category":"Wholesale",
            "subcategory":"Home Furnishings",
            "type":"Manufacturing & Wholesale Goods"
        }
    ],
    "sg:phone":"+1 617 328 6488",
    "sg:postcode":"02169",
    "sg:province":"MA",
    "sg:tags":[
        "custom",
        "designer",
        "equipment-wholesale",
        "builder",
        "kitchen",
        "equipment-household",
        "cabinet",
        "manufacturer"
    ],
    "wof:name":"A & C Cabinet Countertop, Inc.",
    "wof:placetype":"venue"
},
  "geometry": {"coordinates":[-70.99102499999999,42.241291],"type":"Point"}
}