{
  "type": "Feature",
  "properties": {
    "iso:country":"US",
    "sg:address":"70 Commercial St",
    "sg:city":"Lynn",
    "sg:classifiers":[
        {
            "category":"Food & Beverages",
            "subcategory":"Groceries & Convenience Stores",
            "type":"Retail Goods"
        }
    ],
    "sg:phone":"+1 781 595 4333",
    "sg:postcode":"01905",
    "sg:province":"MA",
    "wof:name":"As Food Mart",
    "wof:placetype":"venue"
},
  "geometry": {"coordinates":[-70.960921,42.460854],"type":"Point"}
}