{
  "type": "Feature",
  "properties": {
    "addr:full":"60 Sibley Dr West Yarmouth MA 02673",
    "addr:housenumber":"60",
    "addr:postcode":"02673",
    "addr:street":"Sibley Dr",
    "iso:country":"US",
    "sg:address":"60 Sibley Dr",
    "sg:city":"West Yarmouth",
    "sg:classifiers":[
        {
            "category":"Shopping",
            "type":"Retail Goods"
        },
        {
            "category":"Shopping",
            "subcategory":"Beauty & Cosmetics",
            "type":"Retail Goods"
        }
    ],
    "sg:phone":"+1 508 775 7861",
    "sg:postcode":"02673",
    "sg:province":"MA",
    "sg:tags":[
        "merchandise",
        "perfume"
    ],
    "wof:name":"Mary Kay Cosmetics",
    "wof:placetype":"venue"
},
  "geometry": {"coordinates":[-70.24227399999999,41.648704],"type":"Point"}
}