{
  "type": "Feature",
  "properties": {
    "addr:full":"71 Circuit St Melrose MA 02176",
    "addr:housenumber":"71",
    "addr:postcode":"02176",
    "addr:street":"Circuit St",
    "iso:country":"US",
    "sg:address":"71 Circuit St",
    "sg:city":"Melrose",
    "sg:classifiers":[
        {
            "category":"Real Estate",
            "subcategory":"Real Estate Services",
            "type":"Services"
        },
        {
            "category":"Building & Trades",
            "subcategory":"Cleaning & Sanitation",
            "type":"Services"
        }
    ],
    "sg:phone":"+1 781 662 1477",
    "sg:postcode":"02176",
    "sg:province":"MA",
    "sg:tags":[
        "maintenance",
        "cleaners-interior"
    ],
    "wof:name":"Jerusa G Nascimento",
    "wof:placetype":"venue"
},
  "geometry": {"coordinates":[-71.070379,42.453757],"type":"Point"}
}