{
  "type": "Feature",
  "properties": {
    "addr:full": "87 Fresh Pond Pkwy Cambridge MA 02138",
    "addr:housenumber": "87",
    "addr:postcode": "02138",
    "addr:street": "Fresh Pond Pkwy",
    "iso:country": "US",
    "sg:address": "87 Fresh Pond Pkwy",
    "sg:city": "Cambridge",
    "sg:classifiers": [
      {
        "category": "Professional",
        "subcategory": "Computer Services",
        "type": "Services"
      }
    ],
    "sg:phone": "+1 617 868 1111",
    "sg:postcode": "02138",
    "sg:province": "MA",
    "sg:tags": [
      "consultant",
      "designer",
      "datum",
      "system"
    ],
    "sg:website": "www.camb.com",
    "wof:name": "Cambridge Computer Assoc Inc",
    "wof:placetype": "venue"
  },
  "geometry": {"coordinates":[-71.143295,42.377923],"type":"Point"}
}
