{
  "type": "Feature",
  "properties": {
    "iso:country":"US",
    "sg:address":"55 Pond Avenue",
    "sg:city":"Brookline",
    "sg:classifiers":[
        {
            "category":"Personal",
            "subcategory":"Barber",
            "type":"Services"
        }
    ],
    "sg:phone":"+1 617 731 3250",
    "sg:postcode":"02445",
    "sg:province":"MA",
    "wof:name":"Brook House Men's Salon",
    "wof:placetype":"venue"
},
  "geometry": {"coordinates":[-71.11426400000001,42.330796],"type":"Point"}
}