{
  "type": "Feature",
  "properties": {
    "iso:country":"US",
    "sg:address":"201 Main St",
    "sg:city":"Webster",
    "sg:classifiers":[
        {
            "category":"Shopping",
            "subcategory":"Discount & Variety Stores",
            "type":"Retail Goods"
        }
    ],
    "sg:phone":"+1 508 943 0663",
    "sg:postcode":"01570",
    "sg:province":"MA",
    "wof:name":"G 1 Variety",
    "wof:placetype":"venue"
},
  "geometry": {"coordinates":[-71.88269099999999,42.049313],"type":"Point"}
}