{
  "type": "Feature",
  "properties": {
    "iso:country":"US",
    "sg:address":"17 Otis Street",
    "sg:city":"Cambridge",
    "sg:classifiers":[
        {
            "category":"Professional",
            "subcategory":"Art Services",
            "type":"Services"
        }
    ],
    "sg:phone":"+1 617 308 7740",
    "sg:postcode":"02141",
    "sg:province":"MA",
    "sg:tags":[
        "photographer"
    ],
    "wof:name":"Veracious Productions",
    "wof:placetype":"venue"
},
  "geometry": {"coordinates":[-71.077581,42.370002],"type":"Point"}
}