{
  "type": "Feature",
  "properties": {
    "addr:full": "130 Rockland St Hanover MA 02339",
    "addr:housenumber": "130",
    "addr:postcode": "02339",
    "addr:street": "Rockland St",
    "iso:country": "US",
    "sg:address": "130 Rockland St",
    "sg:city": "Hanover",
    "sg:classifiers": [
      {
        "category": "Wholesale",
        "subcategory": "Machinery \u0026 Supplies",
        "type": "Manufacturing \u0026 Wholesale Goods"
      }
    ],
    "sg:phone": "+1 781 826 1149",
    "sg:postcode": "02339",
    "sg:province": "MA",
    "sg:tags": [
      "stencil"
    ],
    "wof:name": "Hanvoer Tole \u0026 Stencil Shop",
    "wof:placetype": "venue"
  },
  "geometry": {"coordinates":[-70.823583,42.114528],"type":"Point"}
}
