{
  "type": "Feature",
  "properties": {
    "iso:country":"US",
    "sg:address":"130 Rockland St",
    "sg:city":"Hanover",
    "sg:classifiers":[
        {
            "category":"Wholesale",
            "subcategory":"Machinery & Supplies",
            "type":"Manufacturing & Wholesale Goods"
        }
    ],
    "sg:phone":"+1 781 826 1149",
    "sg:postcode":"02339",
    "sg:province":"MA",
    "sg:tags":[
        "stencil"
    ],
    "wof:name":"Hanvoer Tole & Stencil Shop",
    "wof:placetype":"venue"
},
  "geometry": {"coordinates":[-70.823583,42.114528],"type":"Point"}
}