{
  "type": "Feature",
  "properties": {
    "iso:country":"US",
    "sg:address":"11 Alden Ave W",
    "sg:city":"Randolph",
    "sg:classifiers":[
        {
            "category":"Real Estate",
            "subcategory":"Real Estate Agent",
            "type":"Services"
        }
    ],
    "sg:phone":"+1 781 961 8500",
    "sg:postcode":"02368",
    "sg:province":"MA",
    "wof:name":"Freedom Realty",
    "wof:placetype":"venue"
},
  "geometry": {"coordinates":[-71.034565,42.150891],"type":"Point"}
}