{
  "type": "Feature",
  "properties": {
    "addr:full":"309 Silver St Monson MA 01057",
    "addr:housenumber":"309",
    "addr:postcode":"01057",
    "addr:street":"Silver St",
    "iso:country":"US",
    "sg:address":"309 Silver St",
    "sg:city":"Monson",
    "sg:classifiers":[
        {
            "category":"Building & Trades",
            "subcategory":"Construction",
            "type":"Services"
        }
    ],
    "sg:phone":"+1 413 596 4370",
    "sg:postcode":"01057",
    "sg:province":"MA",
    "sg:tags":[
        "excavating",
        "contractor"
    ],
    "wof:name":"Moore Contractors Inc",
    "wof:placetype":"venue"
},
  "geometry": {"coordinates":[-72.38153,42.138728],"type":"Point"}
}