{
  "type": "Feature",
  "properties": {
    "iso:country":"US",
    "sg:address":"420 Washington St",
    "sg:city":"Braintree",
    "sg:classifiers":[
        {
            "category":"Health Services",
            "subcategory":"Health Practitioner",
            "type":"Services"
        }
    ],
    "sg:phone":"+1 781 848 2273",
    "sg:postcode":"02184",
    "sg:province":"MA",
    "sg:tags":[
        "addiction",
        "abuse",
        "drug"
    ],
    "wof:name":"Murray, John",
    "wof:placetype":"venue"
},
  "geometry": {"coordinates":[-71.00314899999999,42.218239],"type":"Point"}
}