{
  "type": "Feature",
  "properties": {
    "iso:country":"US",
    "sg:address":"15 Hampden St",
    "sg:city":"Springfield",
    "sg:classifiers":[
        {
            "category":"Professional",
            "subcategory":"Advertising",
            "type":"Services"
        }
    ],
    "sg:phone":"+1 413 731 0750",
    "sg:postcode":"01103",
    "sg:province":"MA",
    "sg:tags":[
        "counselor"
    ],
    "wof:name":"Paulson & Michaels Advertising",
    "wof:placetype":"venue"
},
  "geometry": {"coordinates":[-72.59499,42.10326],"type":"Point"}
}