{
  "type": "Feature",
  "properties": {
    "addr:full":"74 Ames St Brockton MA 02302",
    "addr:housenumber":"74",
    "addr:postcode":"02302",
    "addr:street":"Ames St",
    "iso:country":"US",
    "sg:address":"74 Ames St",
    "sg:city":"Brockton",
    "sg:classifiers":[
        {
            "category":"Building & Trades",
            "subcategory":"Plumbing",
            "type":"Services"
        }
    ],
    "sg:phone":"+1 508 580 2400",
    "sg:postcode":"02302",
    "sg:province":"MA",
    "sg:tags":[
        "conditioning",
        "air",
        "system",
        "contractor"
    ],
    "wof:name":"Island Heating & AC INC",
    "wof:placetype":"venue"
},
  "geometry": {"coordinates":[-71.01786300000001,42.102271],"type":"Point"}
}