{
  "type": "Feature",
  "properties": {
    "iso:country":"US",
    "sg:address":"90 Orchard St",
    "sg:city":"Jamaica Plain",
    "sg:classifiers":[
        {
            "category":"Professional",
            "subcategory":"Business Services",
            "type":"Services"
        }
    ],
    "sg:phone":"+1   ",
    "sg:postcode":"02130",
    "sg:province":"MA",
    "wof:name":"Diverse Net Ventures",
    "wof:placetype":"venue"
},
  "geometry": {"coordinates":[-71.12020200000001,42.309099],"type":"Point"}
}