{
  "type": "Feature",
  "properties": {
    "addr:full": "280 Providence St Worcester MA 01607",
    "addr:housenumber": "280",
    "addr:postcode": "01607",
    "addr:street": "Providence St",
    "iso:country": "US",
    "sg:address": "280 Providence St",
    "sg:city": "Worcester",
    "sg:classifiers": [
      {
        "category": "Restaurant",
        "type": "Food \u0026 Drink"
      }
    ],
    "sg:menulink": "http://www.allmenus.com/ma/worcester/131833-subway/menu/",
    "sg:phone": "+1 508 459 5799",
    "sg:postcode": "01607",
    "sg:province": "MA",
    "sg:tags": [
      "american",
      "sandwich"
    ],
    "wof:name": "Subway",
    "wof:placetype": "venue"
  },
  "geometry": {"coordinates":[-71.792088,42.238233],"type":"Point"}
}
