{
  "type": "Feature",
  "properties": {
    "addr:full": "111 Narragansett St Springfield MA 01107",
    "addr:housenumber": "111",
    "addr:postcode": "01107",
    "addr:street": "Narragansett St",
    "iso:country": "US",
    "sg:address": "111 Narragansett St",
    "sg:city": "Springfield",
    "sg:classifiers": [
      {
        "category": "Retail",
        "subcategory": "Photofinishing",
        "type": "Services"
      }
    ],
    "sg:phone": "+1   ",
    "sg:postcode": "01107",
    "sg:province": "MA",
    "sg:tags": [
      "laboratory"
    ],
    "wof:name": "Springfield Custom Color",
    "wof:placetype": "venue"
  },
  "geometry": {"coordinates":[-72.600015,42.119416],"type":"Point"}
}
