{
  "type": "Feature",
  "properties": {
    "addr:full":"149 Pond St Stoneham MA 02180",
    "addr:housenumber":"149",
    "addr:postcode":"02180",
    "addr:street":"Pond St",
    "iso:country":"US",
    "sg:address":"149 Pond St",
    "sg:city":"Stoneham",
    "sg:classifiers":[
        {
            "category":"Museum",
            "subcategory":"Zoo",
            "type":"Entertainment"
        }
    ],
    "sg:phone":"+1 781 438 5100",
    "sg:postcode":"02180",
    "sg:province":"MA",
    "sg:website":"www.stonezoo.org",
    "wof:name":"Stone Zoo",
    "wof:placetype":"venue"
},
  "geometry": {"coordinates":[-71.09514299999999,42.464716],"type":"Point"}
}