{
  "type": "Feature",
  "properties": {
    "addr:full": "E Main Southbridge MA 01550",
    "addr:postcode": "01550",
    "addr:street": "E Main",
    "iso:country": "US",
    "sg:address": "E Main",
    "sg:city": "Southbridge",
    "sg:classifiers": [
      {
        "category": "Restaurant",
        "type": "Food \u0026 Drink"
      }
    ],
    "sg:phone": "+1 508 764 2196",
    "sg:postcode": "01550",
    "sg:province": "MA",
    "wof:name": "McDonald's",
    "wof:placetype": "venue"
  },
  "geometry": {"coordinates":[-72.0326,42.074501],"type":"Point"}
}
