{
  "type": "Feature",
  "properties": {
    "addr:full":"25 Middle Rd Amesbury MA 01913",
    "addr:housenumber":"25",
    "addr:postcode":"01913",
    "addr:street":"Middle Rd",
    "iso:country":"US",
    "sg:address":"25 Middle Rd",
    "sg:city":"Amesbury",
    "sg:classifiers":[
        {
            "category":"Food & Beverages",
            "subcategory":"Fruits & Vegetables",
            "type":"Retail Goods"
        }
    ],
    "sg:phone":"+1 603 944 0395",
    "sg:postcode":"01913",
    "sg:province":"MA",
    "wof:name":"Heritage Farm",
    "wof:placetype":"venue"
},
  "geometry": {"coordinates":[-70.953225,42.839335],"type":"Point"}
}