{
  "type": "Feature",
  "properties": {
    "addr:full":"362 Highland Ave Somerville MA 02144",
    "addr:housenumber":"362",
    "addr:postcode":"02144",
    "addr:street":"Highland Ave",
    "iso:country":"US",
    "sg:address":"362 Highland Ave",
    "sg:city":"Somerville",
    "sg:classifiers":[
        {
            "category":"Professional",
            "subcategory":"Business Services",
            "type":"Services"
        }
    ],
    "sg:phone":"+1   ",
    "sg:postcode":"02144",
    "sg:province":"MA",
    "wof:name":"GP Enterprises",
    "wof:placetype":"venue"
},
  "geometry": {"coordinates":[-71.11843500000001,42.394708],"type":"Point"}
}