{
  "type": "Feature",
  "properties": {
    "addr:full": "60 J St Turners Falls MA 01376",
    "addr:housenumber": "60",
    "addr:postcode": "01376",
    "addr:street": "J St",
    "iso:country": "US",
    "sg:address": "60 J St",
    "sg:city": "Turners Falls",
    "sg:classifiers": [
      {
        "category": "Organizations",
        "subcategory": "Non-profit Organization",
        "type": "Services"
      }
    ],
    "sg:phone": "+1 413 863 3525",
    "sg:postcode": "01376",
    "sg:province": "MA",
    "wof:name": "Winslow Wentworth House",
    "wof:placetype": "venue"
  },
  "geometry": {"coordinates":[-72.560887,42.60627],"type":"Point"}
}
