{
  "type": "Feature",
  "properties": {
    "addr:full":"177 Stockton St Fall River MA 02721",
    "addr:housenumber":"177",
    "addr:postcode":"02721",
    "addr:street":"Stockton St",
    "iso:country":"US",
    "sg:address":"177 Stockton St",
    "sg:city":"Fall River",
    "sg:classifiers":[
        {
            "category":"Personal",
            "subcategory":"Shoe Repair & Shine",
            "type":"Services"
        }
    ],
    "sg:phone":"+1 508 996 2800",
    "sg:postcode":"02721",
    "sg:province":"MA",
    "sg:tags":[
        "repairing",
        "boot"
    ],
    "wof:name":"Lincoln Shoe Repair",
    "wof:placetype":"venue"
},
  "geometry": {"coordinates":[-71.151759,41.674592],"type":"Point"}
}