{
  "type": "Feature",
  "properties": {
    "addr:full": "52 Waltham St Lexington MA 02421",
    "addr:housenumber": "52",
    "addr:postcode": "02421",
    "addr:street": "Waltham St",
    "iso:country": "US",
    "sg:address": "52 Waltham St",
    "sg:city": "Lexington",
    "sg:classifiers": [
      {
        "category": "Real Estate",
        "subcategory": "Real Estate Agent",
        "type": "Services"
      }
    ],
    "sg:phone": "+1 781 862 3636",
    "sg:postcode": "02421",
    "sg:province": "MA",
    "sg:website": "www.grantcole.com",
    "wof:name": "Grant Cole Realtors",
    "wof:placetype": "venue"
  },
  "geometry": {"coordinates":[-71.22715,42.44735],"type":"Point"}
}
