{
  "type": "Feature",
  "properties": {
    "addr:full": "1544 Somerset Ave Dighton MA 02715",
    "addr:housenumber": "1544",
    "addr:postcode": "02715",
    "addr:street": "Somerset Ave",
    "iso:country": "US",
    "sg:address": "1544 Somerset Ave",
    "sg:city": "Dighton",
    "sg:classifiers": [
      {
        "category": "Insurance",
        "subcategory": "Insurance Agent",
        "type": "Services"
      }
    ],
    "sg:phone": "+1 508 669 6762",
    "sg:postcode": "02715",
    "sg:province": "MA",
    "wof:name": "F J Torres Real Estate \u0026 Ins",
    "wof:placetype": "venue"
  },
  "geometry": {"coordinates":[-71.121022,41.828669],"type":"Point"}
}
