{
  "type": "Feature",
  "properties": {
    "addr:full": "51 Kimball Ave Apt 2 Revere MA 02151",
    "addr:housenumber": "51;2",
    "addr:postcode": "02151",
    "addr:street": "Kimball Ave Apt",
    "iso:country": "US",
    "sg:address": "51 Kimball Ave Apt 2",
    "sg:city": "Revere",
    "sg:classifiers": [
      {
        "category": "Building \u0026 Trades",
        "subcategory": "Electrical",
        "type": "Services"
      }
    ],
    "sg:phone": "+1 781 289 8004",
    "sg:postcode": "02151",
    "sg:province": "MA",
    "sg:tags": [
      "electrician"
    ],
    "wof:name": "Ceruolo Electric",
    "wof:placetype": "venue"
  },
  "geometry": {"coordinates":[-70.996951,42.410085],"type":"Point"}
}
