{
  "type": "Feature",
  "properties": {
    "addr:full":"28 State St Boston MA 02109",
    "addr:housenumber":"28",
    "addr:postcode":"02109",
    "addr:street":"State St",
    "iso:country":"US",
    "sg:address":"28 State St",
    "sg:city":"Boston",
    "sg:classifiers":[
        {
            "category":"Real Estate",
            "subcategory":"Real Estate Agent",
            "type":"Services"
        }
    ],
    "sg:phone":"+1 617 573 5035",
    "sg:postcode":"02109",
    "sg:province":"MA",
    "wof:name":"H Q Global State Street",
    "wof:placetype":"venue"
},
  "geometry": {"coordinates":[-71.057805,42.358923],"type":"Point"}
}