{
  "type": "Feature",
  "properties": {
    "addr:full": "241 King St Northampton MA 01060",
    "addr:housenumber": "241",
    "addr:postcode": "01060",
    "addr:street": "King St",
    "iso:country": "US",
    "sg:address": "241 King St",
    "sg:city": "Northampton",
    "sg:classifiers": [
      {
        "category": "Banks \u0026 Credit Unions",
        "subcategory": "Bank",
        "type": "Services"
      }
    ],
    "sg:phone": "+1 413 586 2689",
    "sg:postcode": "01060",
    "sg:province": "MA",
    "sg:tags": [
      "loan",
      "real estate"
    ],
    "wof:name": "Countrywide Home Loans",
    "wof:placetype": "venue"
  },
  "geometry": {"coordinates":[-72.633922,42.32973],"type":"Point"}
}
