{
  "type": "Feature",
  "properties": {
    "iso:country":"US",
    "sg:address":"241 King St",
    "sg:city":"Northampton",
    "sg:classifiers":[
        {
            "category":"Banks & Credit Unions",
            "subcategory":"Bank",
            "type":"Services"
        }
    ],
    "sg:phone":"+1 413 586 2689",
    "sg:postcode":"01060",
    "sg:province":"MA",
    "sg:tags":[
        "loan",
        "real estate"
    ],
    "wof:name":"Countrywide Home Loans",
    "wof:placetype":"venue"
},
  "geometry": {"coordinates":[-72.633922,42.32973],"type":"Point"}
}