{
  "type": "Feature",
  "properties": {
    "addr:full": "909 Washington St Stoughton MA 02072",
    "addr:housenumber": "909",
    "addr:postcode": "02072",
    "addr:street": "Washington St",
    "iso:country": "US",
    "sg:address": "909 Washington St",
    "sg:city": "Stoughton",
    "sg:classifiers": [
      {
        "category": "Building \u0026 Trades",
        "subcategory": "Construction",
        "type": "Services"
      }
    ],
    "sg:phone": "+1 781 341 2196",
    "sg:postcode": "02072",
    "sg:province": "MA",
    "sg:tags": [
      "contractor"
    ],
    "wof:name": "Sun Construction Custom Homes Inc",
    "wof:placetype": "venue"
  },
  "geometry": {"coordinates":[-71.1017,42.121],"type":"Point"}
}
