{
  "type": "Feature",
  "properties": {
    "iso:country":"US",
    "sg:address":"105 Windsor St",
    "sg:city":"Cambridge",
    "sg:classifiers":[
        {
            "category":"Education",
            "subcategory":"Special Training",
            "type":"Public Place"
        }
    ],
    "sg:phone":"+1 617 354 5968",
    "sg:postcode":"02139",
    "sg:province":"MA",
    "sg:tags":[
        "tutoring",
        "center"
    ],
    "sg:website":"www.tutoringplus.org",
    "wof:name":"Tutoring Plus of Cambridge",
    "wof:placetype":"venue"
},
  "geometry": {"coordinates":[-71.09670300000001,42.364101],"type":"Point"}
}