{
  "type": "Feature",
  "properties": {
    "addr:full":"353 Highland Ave Seekonk MA 02771",
    "addr:housenumber":"353",
    "addr:postcode":"02771",
    "addr:street":"Highland Ave",
    "iso:country":"US",
    "sg:address":"353 Highland Ave",
    "sg:city":"Seekonk",
    "sg:classifiers":[
        {
            "category":"Restaurant",
            "type":"Food & Drink"
        }
    ],
    "sg:menulink":"http://www.allmenus.com/ma/seekonk/239266-vinny-ts-of-boston/menu/",
    "sg:phone":"+1 508 336 8488",
    "sg:postcode":"02771",
    "sg:province":"MA",
    "sg:tags":[
        "italian"
    ],
    "wof:name":"Vinny T's of Boston",
    "wof:placetype":"venue"
},
  "geometry": {"coordinates":[-71.33069,41.795264],"type":"Point"}
}