{
  "type": "Feature",
  "properties": {
    "addr:full":"182 N Elm St Westfield MA 01085",
    "addr:housenumber":"182",
    "addr:postcode":"01085",
    "addr:street":"N Elm St",
    "iso:country":"US",
    "sg:address":"182 N Elm St",
    "sg:city":"Westfield",
    "sg:classifiers":[
        {
            "category":"Restaurant",
            "type":"Food & Drink"
        }
    ],
    "sg:menulink":"http://www.allmenus.com/ma/westfield/188759-mcdonalds/menu/",
    "sg:postcode":"01085",
    "sg:province":"MA",
    "sg:tags":[
        "burger",
        "american"
    ],
    "wof:name":"McDonald's",
    "wof:placetype":"venue"
},
  "geometry": {"coordinates":[-72.739187,42.136663],"type":"Point"}
}