{
  "type": "Feature",
  "properties": {
    "iso:country":"US",
    "sg:address":"123 Cambridge St",
    "sg:city":"Burlington",
    "sg:classifiers":[
        {
            "category":"Utilities",
            "subcategory":"Cable",
            "type":"Services"
        }
    ],
    "sg:phone":"+1 781 273 5922",
    "sg:postcode":"01803",
    "sg:province":"MA",
    "sg:tags":[
        "television"
    ],
    "sg:website":"www.sallywillardproductions.com",
    "wof:name":"Burlington Cable Access Television",
    "wof:placetype":"venue"
},
  "geometry": {"coordinates":[-71.19470200000001,42.500801],"type":"Point"}
}