{
  "type": "Feature",
  "properties": {
    "iso:country":"US",
    "sg:address":"28 State St",
    "sg:city":"Boston",
    "sg:classifiers":[
        {
            "category":"Professional",
            "type":"Services"
        }
    ],
    "sg:phone":"+1 617 619 3680",
    "sg:postcode":"02109",
    "sg:province":"MA",
    "sg:tags":[
        "establishment"
    ],
    "wof:name":"Congruent International Inc",
    "wof:placetype":"venue"
},
  "geometry": {"coordinates":[-71.057805,42.358923],"type":"Point"}
}