{
  "type": "Feature",
  "properties": {
    "iso:country":"US",
    "sg:address":"92 Groton St",
    "sg:city":"Pepperell",
    "sg:classifiers":[
        {
            "category":"Building & Trades",
            "subcategory":"Landscaping Services",
            "type":"Services"
        }
    ],
    "sg:phone":"+1 978 433 3268",
    "sg:postcode":"01463",
    "sg:province":"MA",
    "sg:tags":[
        "landscape",
        "contractor"
    ],
    "wof:name":"Landscapes Unlimited",
    "wof:placetype":"venue"
},
  "geometry": {"coordinates":[-71.572334,42.659985],"type":"Point"}
}