{
  "type": "Feature",
  "properties": {
    "iso:country":"US",
    "sg:address":"317 SW Cutoff",
    "sg:city":"Worcester",
    "sg:classifiers":[
        {
            "category":"Recreation",
            "type":"Entertainment"
        }
    ],
    "sg:phone":"+1 508 755 9955",
    "sg:postcode":"01604",
    "sg:province":"MA",
    "sg:tags":[
        "safety",
        "instruction",
        "marksmanship",
        "gun"
    ],
    "sg:website":"www.bostongunrange.com",
    "wof:name":"Boston Gun Range",
    "wof:placetype":"venue"
},
  "geometry": {"coordinates":[-71.76321299999999,42.225783],"type":"Point"}
}