{
  "type": "Feature",
  "properties": {
    "iso:country":"US",
    "sg:address":"24 Putting Green Cir",
    "sg:city":"East Sandwich",
    "sg:classifiers":[
        {
            "category":"Professional",
            "subcategory":"Business Services",
            "type":"Services"
        }
    ],
    "sg:phone":"+1   ",
    "sg:postcode":"02537",
    "sg:province":"MA",
    "wof:name":"Translation",
    "wof:placetype":"venue"
},
  "geometry": {"coordinates":[-70.39358,41.732582],"type":"Point"}
}