{
  "type": "Feature",
  "properties": {
    "iso:country":"US",
    "sg:address":"128 West St",
    "sg:city":"Wilmington",
    "sg:classifiers":[
        {
            "category":"Utilities",
            "subcategory":"Fuel Oil & Lpg",
            "type":"Services"
        }
    ],
    "sg:phone":"+1 978 988 8060",
    "sg:postcode":"01887",
    "sg:province":"MA",
    "sg:tags":[
        "firewood"
    ],
    "wof:name":"Birchwood Development",
    "wof:placetype":"venue"
},
  "geometry": {"coordinates":[-71.1361,42.533674],"type":"Point"}
}