{
  "type": "Feature",
  "properties": {
    "addr:full": "128 West St Wilmington MA 01887",
    "addr:housenumber": "128",
    "addr:postcode": "01887",
    "addr:street": "West St",
    "iso:country": "US",
    "sg:address": "128 West St",
    "sg:city": "Wilmington",
    "sg:classifiers": [
      {
        "category": "Utilities",
        "subcategory": "Fuel Oil \u0026 Lpg",
        "type": "Services"
      }
    ],
    "sg:phone": "+1 978 988 8060",
    "sg:postcode": "01887",
    "sg:province": "MA",
    "sg:tags": [
      "firewood"
    ],
    "wof:name": "Birchwood Development",
    "wof:placetype": "venue"
  },
  "geometry": {"coordinates":[-71.1361,42.533674],"type":"Point"}
}
