{
  "type": "Feature",
  "properties": {
    "iso:country":"US",
    "sg:address":"8 Esther Dr",
    "sg:city":"Milford",
    "sg:classifiers":[
        {
            "category":"Professional",
            "subcategory":"Advertising",
            "type":"Services"
        }
    ],
    "sg:phone":"+1 508 473 8643",
    "sg:postcode":"01757",
    "sg:province":"MA",
    "sg:tags":[
        "agency",
        "specialty"
    ],
    "sg:website":"http://www.mccarthyandking.com",
    "wof:name":"Mccarthy & King Marketing Inc",
    "wof:placetype":"venue"
},
  "geometry": {"coordinates":[-71.53973000000001,42.180009],"type":"Point"}
}