{
  "type": "Feature",
  "properties": {
    "addr:full": "15 Rantoul St Beverly MA 01915",
    "addr:housenumber": "15",
    "addr:postcode": "01915",
    "addr:street": "Rantoul St",
    "iso:country": "US",
    "sg:address": "15 Rantoul St",
    "sg:city": "Beverly",
    "sg:classifiers": [
      {
        "category": "Autos \u0026 Motor Vehicles",
        "subcategory": "Boat Sales",
        "type": "Retail Goods"
      }
    ],
    "sg:phone": "+1 978 921 6600",
    "sg:postcode": "01915",
    "sg:province": "MA",
    "sg:tags": [
      "yacht",
      "broker"
    ],
    "wof:name": "Northrop \u0026 Johnson",
    "wof:placetype": "venue"
  },
  "geometry": {"coordinates":[-70.884942,42.543056],"type":"Point"}
}
