{
  "type": "Feature",
  "properties": {
    "addr:full":"5 Sophie Cir Southampton MA 01073",
    "addr:housenumber":"5",
    "addr:postcode":"01073",
    "addr:street":"Sophie Cir",
    "iso:country":"US",
    "sg:address":"5 Sophie Cir",
    "sg:city":"Southampton",
    "sg:classifiers":[
        {
            "category":"Professional",
            "subcategory":"Advertising",
            "type":"Services"
        }
    ],
    "sg:phone":"+1   ",
    "sg:postcode":"01073",
    "sg:province":"MA",
    "sg:tags":[
        "mail",
        "computer",
        "direct",
        "related"
    ],
    "wof:name":"Event Mailing Services",
    "wof:placetype":"venue"
},
  "geometry": {"coordinates":[-72.71508900000001,42.223128],"type":"Point"}
}