{
  "type": "Feature",
  "properties": {
    "iso:country":"US",
    "sg:address":"44 Sand Trap Way",
    "sg:city":"Chicopee",
    "sg:classifiers":[
        {
            "category":"Building & Trades",
            "subcategory":"Construction",
            "type":"Services"
        }
    ],
    "sg:phone":"+1 413 594 2450",
    "sg:postcode":"01020",
    "sg:province":"MA",
    "sg:tags":[
        "general",
        "contractor"
    ],
    "wof:name":"A-Crane Construction Co",
    "wof:placetype":"venue"
},
  "geometry": {"coordinates":[-72.521238,42.179099],"type":"Point"}
}