{
  "type": "Feature",
  "properties": {
    "addr:full": "94 Pleasant St Arlington MA 02476",
    "addr:housenumber": "94",
    "addr:postcode": "02476",
    "addr:street": "Pleasant St",
    "iso:country": "US",
    "sg:address": "94 Pleasant St",
    "sg:city": "Arlington",
    "sg:classifiers": [
      {
        "category": "Health Services",
        "subcategory": "Doctor",
        "type": "Services"
      }
    ],
    "sg:phone": "+1 781 641 0700",
    "sg:postcode": "02476",
    "sg:province": "MA",
    "wof:name": "Speller Jeffrey",
    "wof:placetype": "venue"
  },
  "geometry": {"coordinates":[-71.155572,42.413384],"type":"Point"}
}
