{
  "type": "Feature",
  "properties": {
    "iso:country":"US",
    "sg:address":"596 S Bridge St",
    "sg:city":"Holyoke",
    "sg:classifiers":[
        {
            "category":"Education",
            "subcategory":"School",
            "type":"Public Place"
        }
    ],
    "sg:phone":"+1 413 534 2083",
    "sg:postcode":"01040",
    "sg:province":"MA",
    "wof:name":"Morgan Elementary School",
    "wof:placetype":"venue"
},
  "geometry": {"coordinates":[-72.60830799999999,42.196273],"type":"Point"}
}