{
  "type": "Feature",
  "properties": {
    "addr:full":"110 W Adams St Somerville MA 02144",
    "addr:housenumber":"110",
    "addr:postcode":"02144",
    "addr:street":"W Adams St",
    "iso:country":"US",
    "sg:address":"110 W Adams St",
    "sg:city":"Somerville",
    "sg:classifiers":[
        {
            "category":"Retail",
            "subcategory":"Laundry & Dry Cleaning",
            "type":"Services"
        }
    ],
    "sg:phone":"+1 617 666 3500",
    "sg:postcode":"02144",
    "sg:province":"MA",
    "sg:tags":[
        "cleaners",
        "rug",
        "carpet"
    ],
    "wof:name":"Embassy Rug & Upholstery Co",
    "wof:placetype":"venue"
},
  "geometry": {"coordinates":[-71.127269,42.409045],"type":"Point"}
}