{
  "type": "Feature",
  "properties": {
    "addr:full": "83 Concord St Framingham MA 01702",
    "addr:housenumber": "83",
    "addr:postcode": "01702",
    "addr:street": "Concord St",
    "iso:country": "US",
    "ovtr:label": "Party Flowers, 83 Concord St Framingham MA US",
    "ovtr:similarity": 2.297003984451294,
    "sg:address": "83 Concord St",
    "sg:city": "Framingham",
    "sg:classifiers": [
      {
        "category": "Shopping",
        "subcategory": "Florist",
        "type": "Retail Goods"
      }
    ],
    "sg:phone": "+1 508 879 3000",
    "sg:postcode": "01702",
    "sg:province": "MA",
    "wof:name": "Party Flowers",
    "wof:placetype": "venue"
  },
  "geometry": {"coordinates":[-71.416695,42.278257],"type":"Point"}
}
