{
  "type": "Feature",
  "properties": {
    "iso:country":"US",
    "sg:address":"17 Lombard St",
    "sg:city":"Springfield",
    "sg:classifiers":[
        {
            "category":"Personal",
            "subcategory":"Beauty Salon",
            "type":"Services"
        }
    ],
    "sg:phone":"+1 413 734 8749",
    "sg:postcode":"01105",
    "sg:province":"MA",
    "wof:name":"Jean Sylvia's Hair Salon",
    "wof:placetype":"venue"
},
  "geometry": {"coordinates":[-72.58304200000001,42.094427],"type":"Point"}
}