{
  "type": "Feature",
  "properties": {
    "addr:full": "96 Hartford Pike Shrewsbury MA 01545",
    "addr:housenumber": "96",
    "addr:postcode": "01545",
    "addr:street": "Hartford Pike",
    "iso:country": "US",
    "sg:address": "96 Hartford Pike",
    "sg:city": "Shrewsbury",
    "sg:classifiers": [
      {
        "category": "Retail",
        "subcategory": "Repair Shop",
        "type": "Services"
      }
    ],
    "sg:phone": "+1 508 791 1975",
    "sg:postcode": "01545",
    "sg:province": "MA",
    "sg:tags": [
      "welding"
    ],
    "wof:name": "J M Welding",
    "wof:placetype": "venue"
  },
  "geometry": {"coordinates":[-71.733205,42.246027],"type":"Point"}
}
