{
  "type": "Feature",
  "properties": {
    "iso:country":"US",
    "sg:address":"75 County Rd",
    "sg:city":"North Falmouth",
    "sg:classifiers":[
        {
            "category":"Farming",
            "subcategory":"Farm",
            "type":"Manufacturing & Wholesale Goods"
        }
    ],
    "sg:phone":"+1 508 564 6977",
    "sg:postcode":"02556",
    "sg:province":"MA",
    "wof:name":"Village Farm Stand",
    "wof:placetype":"venue"
},
  "geometry": {"coordinates":[-70.61904699999999,41.650348],"type":"Point"}
}