{
  "type": "Feature",
  "properties": {
    "iso:country":"US",
    "sg:address":"1244 Boylston St",
    "sg:city":"Boston",
    "sg:classifiers":[
        {
            "category":"Health Services",
            "subcategory":"Health Practitioner",
            "type":"Services"
        }
    ],
    "sg:phone":"+1 617 264 9155",
    "sg:postcode":"02215",
    "sg:province":"MA",
    "sg:tags":[
        "acupuncture"
    ],
    "wof:name":"Wenfei Xie",
    "wof:placetype":"venue"
},
  "geometry": {"coordinates":[-71.09433799999999,42.345481],"type":"Point"}
}