{
  "type": "Feature",
  "properties": {
    "addr:full": "1244 Boylston St Boston MA 02215",
    "addr:housenumber": "1244",
    "addr:postcode": "02215",
    "addr:street": "Boylston St",
    "iso:country": "US",
    "sg:address": "1244 Boylston St",
    "sg:city": "Boston",
    "sg:classifiers": [
      {
        "category": "Health Services",
        "subcategory": "Health Practitioner",
        "type": "Services"
      }
    ],
    "sg:phone": "+1 617 264 9155",
    "sg:postcode": "02215",
    "sg:province": "MA",
    "sg:tags": [
      "acupuncture"
    ],
    "wof:name": "Wenfei Xie",
    "wof:placetype": "venue"
  },
  "geometry": {"coordinates":[-71.094338,42.345481],"type":"Point"}
}
