{
  "type": "Feature",
  "properties": {
    "addr:full":"130 Rte 6a Sandwich MA 02563",
    "addr:housenumber":"130",
    "addr:postcode":"02563",
    "addr:street":"Rte 6A",
    "iso:country":"US",
    "sg:address":"130 Rte 6a",
    "sg:city":"Sandwich",
    "sg:classifiers":[
        {
            "category":"Shopping",
            "subcategory":"Jewelry",
            "type":"Retail Goods"
        }
    ],
    "sg:phone":"+1 508 833 8500",
    "sg:postcode":"02563",
    "sg:province":"MA",
    "sg:tags":[
        "jeweler"
    ],
    "wof:name":"Heart Of Stone",
    "wof:placetype":"venue"
},
  "geometry": {"coordinates":[-70.493779,41.759187],"type":"Point"}
}