{
  "type": "Feature",
  "properties": {
    "iso:country":"US",
    "sg:address":"769 Plain St",
    "sg:city":"Marshfield",
    "sg:classifiers":[
        {
            "category":"Professional",
            "subcategory":"Lawyer & Legal Services",
            "type":"Services"
        }
    ],
    "sg:phone":"+1 781 837 4310",
    "sg:postcode":"02050",
    "sg:province":"MA",
    "sg:tags":[
        "attorney"
    ],
    "wof:name":"Hoag & Sullivan",
    "wof:placetype":"venue"
},
  "geometry": {"coordinates":[-70.74822399999999,42.106224],"type":"Point"}
}