{
  "type": "Feature",
  "properties": {
    "addr:full": "769 Plain St Marshfield MA 02050",
    "addr:housenumber": "769",
    "addr:postcode": "02050",
    "addr:street": "Plain St",
    "iso:country": "US",
    "sg:address": "769 Plain St",
    "sg:city": "Marshfield",
    "sg:classifiers": [
      {
        "category": "Professional",
        "subcategory": "Lawyer \u0026 Legal Services",
        "type": "Services"
      }
    ],
    "sg:phone": "+1 781 837 4310",
    "sg:postcode": "02050",
    "sg:province": "MA",
    "sg:tags": [
      "attorney"
    ],
    "wof:name": "Hoag \u0026 Sullivan",
    "wof:placetype": "venue"
  },
  "geometry": {"coordinates":[-70.748224,42.106224],"type":"Point"}
}
