{
  "type": "Feature",
  "properties": {
    "iso:country":"US",
    "sg:address":"220 Russell St",
    "sg:city":"Hadley",
    "sg:classifiers":[
        {
            "category":"Retail",
            "subcategory":"Auto Repair",
            "type":"Services"
        }
    ],
    "sg:phone":"+1 413 586 9336",
    "sg:postcode":"01035",
    "sg:province":"MA",
    "sg:tags":[
        "repairing",
        "automobile"
    ],
    "wof:name":"Kevin's Auto Repair",
    "wof:placetype":"venue"
},
  "geometry": {"coordinates":[-72.581923,42.342923],"type":"Point"}
}