{
  "type": "Feature",
  "properties": {
    "addr:full":"441 Marshall St Leicester MA 01524",
    "addr:housenumber":"441",
    "addr:postcode":"01524",
    "addr:street":"Marshall St",
    "iso:country":"US",
    "sg:address":"441 Marshall St",
    "sg:city":"Leicester",
    "sg:classifiers":[
        {
            "category":"Building & Trades",
            "subcategory":"Cleaning & Sanitation",
            "type":"Services"
        },
        {
            "category":"Utilities",
            "subcategory":"Fuel Oil & Lpg",
            "type":"Services"
        },
        {
            "category":"Building & Trades",
            "subcategory":"Construction",
            "type":"Services"
        }
    ],
    "sg:phone":"+1 508 892 9436",
    "sg:postcode":"01524",
    "sg:province":"MA",
    "sg:tags":[
        "duct",
        "burner",
        "system",
        "specialty",
        "heating",
        "ventilating",
        "contractor",
        "air conditioning"
    ],
    "sg:website":"http://WWW.MCDONALDHVAC.com",
    "wof:name":"McDonald Heating & Air Conditioning",
    "wof:placetype":"venue"
},
  "geometry": {"coordinates":[-71.920597,42.280052],"type":"Point"}
}