{
  "type": "Feature",
  "properties": {
    "iso:country":"US",
    "sg:address":"600 Main St",
    "sg:city":"Winchester",
    "sg:classifiers":[
        {
            "category":"Food & Beverages",
            "subcategory":"Specialty",
            "type":"Retail Goods"
        },
        {
            "category":"Food & Beverages",
            "subcategory":"Liquor & Beverages",
            "type":"Retail Goods"
        }
    ],
    "sg:phone":"+1 781 721 9463",
    "sg:postcode":"01890",
    "sg:province":"MA",
    "sg:tags":[
        "beer",
        "spirit",
        "wine"
    ],
    "sg:website":"www.pairingswineandfood.com",
    "wof:name":"Pairings Wine and Food",
    "wof:placetype":"venue"
},
  "geometry": {"coordinates":[-71.137469,42.453642],"type":"Point"}
}