{
  "type": "Feature",
  "properties": {
    "addr:full":"33 Old Colony Dr Weymouth MA 02188",
    "addr:housenumber":"33",
    "addr:postcode":"02188",
    "addr:street":"Old Colony Dr",
    "iso:country":"US",
    "sg:address":"33 Old Colony Dr",
    "sg:city":"Weymouth",
    "sg:classifiers":[
        {
            "category":"Retail",
            "subcategory":"Portrait Studio",
            "type":"Services"
        }
    ],
    "sg:phone":"+1 781 337 8238",
    "sg:postcode":"02188",
    "sg:province":"MA",
    "sg:tags":[
        "photo"
    ],
    "wof:name":"Robert R Photography",
    "wof:placetype":"venue"
},
  "geometry": {"coordinates":[-70.96386699999999,42.192341],"type":"Point"}
}