{
  "type": "Feature",
  "properties": {
    "iso:country":"US",
    "sg:address":"17 West St",
    "sg:city":"Mansfield",
    "sg:classifiers":[
        {
            "category":"Social Services",
            "type":"Services"
        }
    ],
    "sg:phone":"+1 508 339 9331",
    "sg:postcode":"02048",
    "sg:province":"MA",
    "sg:tags":[
        "youth",
        "organization",
        "center"
    ],
    "wof:name":"YMCA",
    "wof:placetype":"venue"
},
  "geometry": {"coordinates":[-71.21725000000001,42.02456],"type":"Point"}
}