{
  "type": "Feature",
  "properties": {
    "addr:full": "2 Cabot Pl Ste 1A Stoughton MA 02072",
    "addr:housenumber": "2",
    "addr:postcode": "02072",
    "addr:street": "Cabot Pl Ste 1A",
    "iso:country": "US",
    "sg:address": "2 Cabot Pl Ste 1A",
    "sg:city": "Stoughton",
    "sg:classifiers": [
      {
        "category": "Health Services",
        "subcategory": "Medical Lab",
        "type": "Services"
      },
      {
        "category": "Community Center",
        "type": "Public Place"
      }
    ],
    "sg:phone": "+1 781 341 4041",
    "sg:postcode": "02072",
    "sg:province": "MA",
    "sg:tags": [
      "examination",
      "insurance"
    ],
    "wof:name": "Mass Medical Services",
    "wof:placetype": "venue"
  },
  "geometry": {"coordinates":[-71.075709,42.153275],"type":"Point"}
}
