{
  "type": "Feature",
  "properties": {
    "iso:country":"US",
    "sg:address":"40 Eastern Avenue",
    "sg:city":"Malden",
    "sg:classifiers":[
        {
            "category":"Sports & Exercise",
            "subcategory":"Gym",
            "type":"Entertainment"
        }
    ],
    "sg:phone":"+1 781 338 1100",
    "sg:postcode":"02148",
    "sg:province":"MA",
    "sg:tags":[
        "trainer"
    ],
    "wof:name":"Travcorps",
    "wof:placetype":"venue"
},
  "geometry": {"coordinates":[-71.06611700000001,42.42365],"type":"Point"}
}