{
  "type": "Feature",
  "properties": {
    "addr:full":"201 Chelsea St Everett MA 02149",
    "addr:housenumber":"201",
    "addr:postcode":"02149",
    "addr:street":"Chelsea St",
    "iso:country":"US",
    "sg:address":"201 Chelsea St",
    "sg:city":"Everett",
    "sg:classifiers":[
        {
            "category":"Real Estate",
            "subcategory":"Real Estate Operator",
            "type":"Services"
        }
    ],
    "sg:phone":"+1 617 381 9700",
    "sg:postcode":"02149",
    "sg:province":"MA",
    "sg:tags":[
        "apartment"
    ],
    "wof:name":"Parkway Heights",
    "wof:placetype":"venue"
},
  "geometry": {"coordinates":[-71.047828,42.403433],"type":"Point"}
}