{
  "type": "Feature",
  "properties": {
    "addr:full":"43 Oak Hill Rd Harvard MA 01451",
    "addr:housenumber":"43",
    "addr:postcode":"01451",
    "addr:street":"Oak Hill Rd",
    "iso:country":"US",
    "sg:address":"43 Oak Hill Rd",
    "sg:city":"Harvard",
    "sg:classifiers":[
        {
            "category":"Professional",
            "subcategory":"Computer Services",
            "type":"Services"
        }
    ],
    "sg:phone":"+1   ",
    "sg:postcode":"01451",
    "sg:province":"MA",
    "sg:tags":[
        "related"
    ],
    "wof:name":"Robert Voelk",
    "wof:placetype":"venue"
},
  "geometry": {"coordinates":[-71.576531,42.4984],"type":"Point"}
}