{
  "type": "Feature",
  "properties": {
    "iso:country":"US",
    "sg:address":"83 Hollis St",
    "sg:city":"Pepperell",
    "sg:classifiers":[
        {
            "category":"Education",
            "subcategory":"School",
            "type":"Public Place"
        }
    ],
    "sg:phone":"+1 978 433 5695",
    "sg:postcode":"01463",
    "sg:province":"MA",
    "sg:website":"www.mapledene.org",
    "wof:name":"Maple Dene Elementary School",
    "wof:placetype":"venue"
},
  "geometry": {"coordinates":[-71.581678,42.680898],"type":"Point"}
}