{
  "type": "Feature",
  "properties": {
    "iso:country":"US",
    "sg:address":"8 Oliver Rd",
    "sg:city":"Watertown",
    "sg:classifiers":[
        {
            "category":"Manufacturing",
            "subcategory":"Signs",
            "type":"Manufacturing & Wholesale Goods"
        }
    ],
    "sg:phone":"+1 781 443 7042",
    "sg:postcode":"02472",
    "sg:province":"MA",
    "sg:tags":[
        "signs-erectors",
        "hanger"
    ],
    "wof:name":"New Impact Graphics",
    "wof:placetype":"venue"
},
  "geometry": {"coordinates":[-71.16176400000001,42.369693],"type":"Point"}
}