{
  "type": "Feature",
  "properties": {
    "iso:country":"US",
    "sg:address":"214 Broadway",
    "sg:city":"Saugus",
    "sg:classifiers":[
        {
            "category":"Real Estate",
            "subcategory":"Real Estate Agent",
            "type":"Services"
        }
    ],
    "sg:phone":"+1 781 231 2767",
    "sg:postcode":"01906",
    "sg:province":"MA",
    "wof:name":"Castlegate Real Estate",
    "wof:placetype":"venue"
},
  "geometry": {"coordinates":[-71.01760400000001,42.487353],"type":"Point"}
}