{
  "type": "Feature",
  "properties": {
    "iso:country":"US",
    "sg:address":"140 Newbury St",
    "sg:city":"Boston",
    "sg:classifiers":[
        {
            "category":"Building & Trades",
            "subcategory":"Locksmith",
            "type":"Services"
        }
    ],
    "sg:phone":"+1 617 535 8927",
    "sg:postcode":"02116",
    "sg:province":"MA",
    "sg:tags":[
        "key"
    ],
    "wof:name":"Locksmith On Beacon 123 Always 24 Hour Emergen",
    "wof:placetype":"venue"
},
  "geometry": {"coordinates":[-71.077271,42.350871],"type":"Point"}
}