{
  "type": "Feature",
  "properties": {
    "iso:country":"US",
    "sg:address":"24 Elm St",
    "sg:city":"Westfield",
    "sg:classifiers":[
        {
            "category":"Professional",
            "subcategory":"Computer Services",
            "type":"Services"
        }
    ],
    "sg:phone":"+1 413 562 3202",
    "sg:postcode":"01085",
    "sg:province":"MA",
    "sg:tags":[
        "consultant",
        "designer"
    ],
    "wof:name":"Darling Associates",
    "wof:placetype":"venue"
},
  "geometry": {"coordinates":[-72.74891599999999,42.121746],"type":"Point"}
}