{
  "type": "Feature",
  "properties": {
    "iso:country":"US",
    "sg:address":"558 S Main St",
    "sg:city":"Raynham",
    "sg:classifiers":[
        {
            "category":"Education",
            "subcategory":"School",
            "type":"Public Place"
        }
    ],
    "sg:phone":"+1 508 824 2733",
    "sg:postcode":"02767",
    "sg:province":"MA",
    "sg:tags":[
        "elementary"
    ],
    "wof:name":"William J Sullivan Elementary School",
    "wof:placetype":"venue"
},
  "geometry": {"coordinates":[-71.05682400000001,41.918743],"type":"Point"}
}