{
  "type": "Feature",
  "properties": {
    "addr:full": "24 Liverpool Dr Yarmouth Port MA 02675",
    "addr:housenumber": "24",
    "addr:postcode": "02675",
    "addr:street": "Liverpool Dr",
    "iso:country": "US",
    "sg:address": "24 Liverpool Dr",
    "sg:city": "Yarmouth Port",
    "sg:classifiers": [
      {
        "category": "Professional",
        "subcategory": "Management \u0026 Consulting",
        "type": "Services"
      }
    ],
    "sg:phone": "+1 508 375 0067",
    "sg:postcode": "02675",
    "sg:province": "MA",
    "sg:tags": [
      "consultant",
      "business"
    ],
    "wof:name": "Acorn Business Svc",
    "wof:placetype": "venue"
  },
  "geometry": {"coordinates":[-70.206187,41.71782],"type":"Point"}
}
