{
  "type": "Feature",
  "properties": {
    "iso:country":"US",
    "sg:address":"24 Liverpool Dr",
    "sg:city":"Yarmouth Port",
    "sg:classifiers":[
        {
            "category":"Professional",
            "subcategory":"Management & Consulting",
            "type":"Services"
        }
    ],
    "sg:phone":"+1 508 375 0067",
    "sg:postcode":"02675",
    "sg:province":"MA",
    "sg:tags":[
        "consultant",
        "business"
    ],
    "wof:name":"Acorn Business Svc",
    "wof:placetype":"venue"
},
  "geometry": {"coordinates":[-70.206187,41.71782],"type":"Point"}
}