{
  "type": "Feature",
  "properties": {
    "addr:full":"72 Taunton St Plainville MA 02762",
    "addr:housenumber":"72",
    "addr:postcode":"02762",
    "addr:street":"Taunton St",
    "iso:country":"US",
    "sg:address":"72 Taunton St",
    "sg:city":"Plainville",
    "sg:classifiers":[
        {
            "category":"Banks & Credit Unions",
            "subcategory":"Investment Brokerage",
            "type":"Services"
        }
    ],
    "sg:phone":"+1 508 643 3050",
    "sg:postcode":"02762",
    "sg:province":"MA",
    "sg:tags":[
        "advisory",
        "financial"
    ],
    "wof:name":"PPM Consulting Svc",
    "wof:placetype":"venue"
},
  "geometry": {"coordinates":[-71.31043,42.029219],"type":"Point"}
}