{
  "type": "Feature",
  "properties": {
    "addr:full": "115 Lewis Wharf Boston MA 02110",
    "addr:housenumber": "115",
    "addr:postcode": "02110",
    "addr:street": "Lewis Wharf",
    "iso:country": "US",
    "sg:address": "115 Lewis Wharf",
    "sg:city": "Boston",
    "sg:classifiers": [
      {
        "category": "Personal",
        "subcategory": "Beauty Salon",
        "type": "Services"
      },
      {
        "category": "Personal",
        "subcategory": "Day Spa",
        "type": "Services"
      },
      {
        "category": "Personal",
        "subcategory": "Nail Salon",
        "type": "Services"
      }
    ],
    "sg:phone": "+1 617 227 5499",
    "sg:postcode": "02110",
    "sg:province": "MA",
    "sg:website": "www.adaraspaboston.com",
    "wof:name": "Adara Spa",
    "wof:placetype": "venue"
  },
  "geometry": {"coordinates":[-71.050923,42.363645],"type":"Point"}
}
