{
  "type": "Feature",
  "properties": {
    "addr:full":"450 William F McClellan Hwy East Boston MA 02128",
    "addr:housenumber":"450",
    "addr:postcode":"02128",
    "addr:street":"William F Mcclellan Hwy",
    "iso:country":"US",
    "sg:address":"450 William F McClellan Hwy",
    "sg:city":"East Boston",
    "sg:classifiers":[
        {
            "category":"Retail",
            "subcategory":"Auto Rental",
            "type":"Services"
        }
    ],
    "sg:phone":"+1 617 561 3000",
    "sg:postcode":"02128",
    "sg:province":"MA",
    "sg:tags":[
        "renting",
        "automobile"
    ],
    "wof:name":"Hertz Rent A Car",
    "wof:placetype":"venue"
},
  "geometry": {"coordinates":[-71.012191,42.392769],"type":"Point"}
}