{
  "type": "Feature",
  "properties": {
    "addr:full": "134 Summer St Medway MA 02053",
    "addr:housenumber": "134",
    "addr:postcode": "02053",
    "addr:street": "Summer St",
    "iso:country": "US",
    "sg:address": "134 Summer St",
    "sg:city": "Medway",
    "sg:classifiers": [
      {
        "category": "Home \u0026 Garden",
        "subcategory": "Garden Supply",
        "type": "Retail Goods"
      }
    ],
    "sg:phone": "+1 508 533 9555",
    "sg:postcode": "02053",
    "sg:province": "MA",
    "sg:tags": [
      "sprinkler"
    ],
    "wof:name": "Rain By Design",
    "wof:placetype": "venue"
  },
  "geometry": {"coordinates":[-71.443625,42.165535],"type":"Point"}
}
