{
  "type": "Feature",
  "properties": {
    "iso:country":"US",
    "sg:address":"134 Summer St",
    "sg:city":"Medway",
    "sg:classifiers":[
        {
            "category":"Home & Garden",
            "subcategory":"Garden Supply",
            "type":"Retail Goods"
        }
    ],
    "sg:phone":"+1 508 533 9555",
    "sg:postcode":"02053",
    "sg:province":"MA",
    "sg:tags":[
        "sprinkler"
    ],
    "wof:name":"Rain By Design",
    "wof:placetype":"venue"
},
  "geometry": {"coordinates":[-71.443625,42.165535],"type":"Point"}
}