{
  "type": "Feature",
  "properties": {
    "iso:country":"US",
    "sg:address":"9 Salros Rd",
    "sg:city":"Nantucket",
    "sg:classifiers":[
        {
            "category":"Professional",
            "type":"Services"
        },
        {
            "category":"Taxi",
            "type":"Transportation"
        },
        {
            "category":"Retail",
            "subcategory":"Auto Rental",
            "type":"Services"
        }
    ],
    "sg:phone":"+1 508 228 5779",
    "sg:postcode":"02554",
    "sg:province":"MA",
    "sg:tags":[
        "limousine"
    ],
    "sg:website":"http://www.cranberrytransportation.com",
    "wof:name":"All Point Taxi & Tours",
    "wof:placetype":"venue"
},
  "geometry": {"coordinates":[-70.106942,41.265112],"type":"Point"}
}