{
  "type": "Feature",
  "properties": {
    "addr:full":"370 Washington St Gloucester MA 01930",
    "addr:housenumber":"370",
    "addr:postcode":"01930",
    "addr:street":"Washington St",
    "iso:country":"US",
    "sg:address":"370 Washington St",
    "sg:city":"Gloucester",
    "sg:classifiers":[
        {
            "category":"Building & Trades",
            "subcategory":"Construction",
            "type":"Services"
        }
    ],
    "sg:phone":"+1   ",
    "sg:postcode":"01930",
    "sg:province":"MA",
    "sg:tags":[
        "hanging",
        "contractor"
    ],
    "wof:name":"Custom Pntg Co Marc Beauregard",
    "wof:placetype":"venue"
},
  "geometry": {"coordinates":[-70.678659,42.63203],"type":"Point"}
}