{
  "type": "Feature",
  "properties": {
    "addr:full":"217 Oneil Blvd Attleboro MA 02703",
    "addr:housenumber":"217",
    "addr:postcode":"02703",
    "addr:street":"Oneil Blvd",
    "iso:country":"US",
    "sg:address":"217 Oneil Blvd",
    "sg:city":"Attleboro",
    "sg:classifiers":[
        {
            "category":"Wholesale",
            "subcategory":"Machinery & Supplies",
            "type":"Manufacturing & Wholesale Goods"
        }
    ],
    "sg:phone":"+1 508 222 5700",
    "sg:postcode":"02703",
    "sg:province":"MA",
    "sg:tags":[
        "equipment",
        "industrial"
    ],
    "wof:name":"Brask Enterprises Inc",
    "wof:placetype":"venue"
},
  "geometry": {"coordinates":[-71.27544399999999,41.936021],"type":"Point"}
}