{
  "type": "Feature",
  "properties": {
    "addr:full": "274 Newburyport Tpke Rowley MA 01969",
    "addr:housenumber": "274",
    "addr:postcode": "01969",
    "addr:street": "Newburyport Tpke",
    "iso:country": "US",
    "ovtr:label": "Family Auto Clinic, 274 Newburyport Tpke Rowley MA US",
    "ovtr:similarity": 2.613676071166992,
    "sg:address": "274 Newburyport Tpke",
    "sg:city": "Rowley",
    "sg:classifiers": [
      {
        "category": "Retail",
        "subcategory": "Auto Repair",
        "type": "Services"
      }
    ],
    "sg:phone": "+1 978 948 0800",
    "sg:postcode": "01969",
    "sg:province": "MA",
    "wof:name": "Family Auto Clinic",
    "wof:placetype": "venue"
  },
  "geometry": {"coordinates":[-70.907799,42.709599],"type":"Point"}
}
