{
  "type": "Feature",
  "properties": {
    "iso:country":"US",
    "sg:address":"274 Newburyport Tpke",
    "sg:city":"Rowley",
    "sg:classifiers":[
        {
            "category":"Retail",
            "subcategory":"Auto Repair",
            "type":"Services"
        }
    ],
    "sg:phone":"+1 978 948 0800",
    "sg:postcode":"01969",
    "sg:province":"MA",
    "wof:name":"Family Auto Clinic",
    "wof:placetype":"venue"
},
  "geometry": {"coordinates":[-70.907799,42.709599],"type":"Point"}
}