{
  "type": "Feature",
  "properties": {
    "addr:full":"706 Washington Street Brookline MA 02446",
    "addr:housenumber":"706",
    "addr:postcode":"02446",
    "addr:street":"Washington Street",
    "iso:country":"US",
    "sg:address":"706 Washington Street",
    "sg:city":"Brookline",
    "sg:classifiers":[
        {
            "category":"Home & Garden",
            "subcategory":"Hardware",
            "type":"Retail Goods"
        }
    ],
    "sg:phone":"+1 617 277 7349",
    "sg:postcode":"02446",
    "sg:province":"MA",
    "sg:tags":[
        "store"
    ],
    "wof:name":"Connelly Hardware",
    "wof:placetype":"venue"
},
  "geometry": {"coordinates":[-71.135159,42.339185],"type":"Point"}
}