{
  "type": "Feature",
  "properties": {
    "addr:full": "706 Washington Street Brookline MA 02446",
    "addr:housenumber": "706",
    "addr:postcode": "02446",
    "addr:street": "Washington Street",
    "iso:country": "US",
    "ovtr:label": "Connelly Hardware Co, 706 Washington St Brookline MA US",
    "ovtr:similarity": 3.4815149307250977,
    "sg:address": "706 Washington Street",
    "sg:city": "Brookline",
    "sg:classifiers": [
      {
        "category": "Home \u0026 Garden",
        "subcategory": "Hardware",
        "type": "Retail Goods"
      }
    ],
    "sg:phone": "+1 617 277 7349",
    "sg:postcode": "02446",
    "sg:province": "MA",
    "sg:tags": [
      "store"
    ],
    "wof:name": "Connelly Hardware",
    "wof:placetype": "venue"
  },
  "geometry": {"coordinates":[-71.135159,42.339185],"type":"Point"}
}
