{
  "type": "Feature",
  "properties": {
    "addr:full":"20 S Main St Topsfield MA 01983",
    "addr:housenumber":"20",
    "addr:postcode":"01983",
    "addr:street":"S Main St",
    "iso:country":"US",
    "sg:address":"20 S Main St",
    "sg:city":"Topsfield",
    "sg:classifiers":[
        {
            "category":"Retail",
            "subcategory":"Laundry & Dry Cleaning",
            "type":"Services"
        }
    ],
    "sg:phone":"+1 978 887 8431",
    "sg:postcode":"01983",
    "sg:province":"MA",
    "sg:tags":[
        "cleaners"
    ],
    "wof:name":"VIP Cleaners",
    "wof:placetype":"venue"
},
  "geometry": {"coordinates":[-70.95027899999999,42.636064],"type":"Point"}
}