{
  "type": "Feature",
  "properties": {
    "addr:full":"621 Grattan St Chicopee MA 01020",
    "addr:housenumber":"621",
    "addr:postcode":"01020",
    "addr:street":"Grattan St",
    "iso:country":"US",
    "sg:address":"621 Grattan St",
    "sg:city":"Chicopee",
    "sg:classifiers":[
        {
            "category":"Building & Trades",
            "subcategory":"Cleaning & Sanitation",
            "type":"Services"
        }
    ],
    "sg:phone":"+1 413 593 9916",
    "sg:postcode":"01020",
    "sg:province":"MA",
    "sg:tags":[
        "janitor"
    ],
    "wof:name":"Rusin Janitorial Inc",
    "wof:placetype":"venue"
},
  "geometry": {"coordinates":[-72.598247,42.171988],"type":"Point"}
}