{
  "type": "Feature",
  "properties": {
    "iso:country":"US",
    "sg:address":"8 Speranza Dr",
    "sg:city":"Buzzards Bay",
    "sg:classifiers":[
        {
            "category":"Professional",
            "type":"Services"
        }
    ],
    "sg:phone":"+1 508 759 3455",
    "sg:postcode":"02532",
    "sg:province":"MA",
    "sg:tags":[
        "establishment"
    ],
    "wof:name":"Cubellis & Cubellis",
    "wof:placetype":"venue"
},
  "geometry": {"coordinates":[-70.60294399999999,41.750339],"type":"Point"}
}