{
  "type": "Feature",
  "properties": {
    "addr:full": "8 Speranza Dr Buzzards Bay MA 02532",
    "addr:housenumber": "8",
    "addr:postcode": "02532",
    "addr:street": "Speranza Dr",
    "iso:country": "US",
    "sg:address": "8 Speranza Dr",
    "sg:city": "Buzzards Bay",
    "sg:classifiers": [
      {
        "category": "Professional",
        "type": "Services"
      }
    ],
    "sg:phone": "+1 508 759 3455",
    "sg:postcode": "02532",
    "sg:province": "MA",
    "sg:tags": [
      "establishment"
    ],
    "wof:name": "Cubellis \u0026 Cubellis",
    "wof:placetype": "venue"
  },
  "geometry": {"coordinates":[-70.602944,41.750339],"type":"Point"}
}
