{
  "type": "Feature",
  "properties": {
    "addr:full":"35 Old Colony Dr Westborough MA 01581",
    "addr:housenumber":"35",
    "addr:postcode":"01581",
    "addr:street":"Old Colony Dr",
    "iso:country":"US",
    "sg:address":"35 Old Colony Dr",
    "sg:city":"Westborough",
    "sg:classifiers":[
        {
            "category":"Shopping",
            "subcategory":"Computers & Home Electronics",
            "type":"Retail Goods"
        }
    ],
    "sg:phone":"+1   ",
    "sg:postcode":"01581",
    "sg:province":"MA",
    "sg:tags":[
        "equipment"
    ],
    "wof:name":"Global Technologies Entps",
    "wof:placetype":"venue"
},
  "geometry": {"coordinates":[-71.627455,42.254878],"type":"Point"}
}