{
  "type": "Feature",
  "properties": {
    "addr:full": "39 Olean St Worcester MA 01602",
    "addr:housenumber": "39",
    "addr:postcode": "01602",
    "addr:street": "Olean St",
    "iso:country": "US",
    "sg:address": "39 Olean St",
    "sg:city": "Worcester",
    "sg:classifiers": [
      {
        "category": "Arts \u0026 Performance",
        "subcategory": "Theater",
        "type": "Entertainment"
      }
    ],
    "sg:phone": "+1 508 831 0444",
    "sg:postcode": "01602",
    "sg:province": "MA",
    "sg:tags": [
      "bureau"
    ],
    "wof:name": "All Access Events Inc",
    "wof:placetype": "venue"
  },
  "geometry": {"coordinates":[-71.856724,42.280097],"type":"Point"}
}
