{
  "type": "Feature",
  "properties": {
    "addr:full":"33 Wales Ave Unit D Avon MA 02322",
    "addr:housenumber":"33",
    "addr:postcode":"02322",
    "addr:street":"Wales Ave Unit D",
    "iso:country":"US",
    "sg:address":"33 Wales Ave Unit D",
    "sg:city":"Avon",
    "sg:classifiers":[
        {
            "category":"Real Estate",
            "subcategory":"Real Estate Services",
            "type":"Services"
        },
        {
            "category":"Personal",
            "type":"Services"
        }
    ],
    "sg:phone":"+1 617 524 4052",
    "sg:postcode":"02322",
    "sg:province":"MA",
    "sg:tags":[
        "home",
        "mover",
        "staging"
    ],
    "sg:website":"www.brilliantmove.net",
    "wof:name":"Brilliant Move, LLC",
    "wof:placetype":"venue"
},
  "geometry": {"coordinates":[-71.057762,42.141397],"type":"Point"}
}