{
  "type": "Feature",
  "properties": {
    "addr:full": "60 State St Boston MA 02109",
    "addr:housenumber": "60",
    "addr:postcode": "02109",
    "addr:street": "State St",
    "iso:country": "US",
    "sg:address": "60 State St",
    "sg:city": "Boston",
    "sg:classifiers": [
      {
        "category": "Insurance",
        "subcategory": "Hazard Insurance",
        "type": "Services"
      }
    ],
    "sg:phone": "+1 617 227 8227",
    "sg:postcode": "02109",
    "sg:province": "MA",
    "sg:tags": [
      "employee",
      "benefit",
      "compensation",
      "plan"
    ],
    "wof:name": "CTG Clontigora Inc",
    "wof:placetype": "venue"
  },
  "geometry": {"coordinates":[-71.055927,42.359114],"type":"Point"}
}
