{
  "type": "Feature",
  "properties": {
    "addr:full": "21 Washington St Ayer MA 01432",
    "addr:housenumber": "21",
    "addr:postcode": "01432",
    "addr:street": "Washington St",
    "iso:country": "US",
    "sg:address": "21 Washington St",
    "sg:city": "Ayer",
    "sg:classifiers": [
      {
        "category": "Building \u0026 Trades",
        "subcategory": "Construction",
        "type": "Services"
      }
    ],
    "sg:phone": "+1 978 425 4882",
    "sg:postcode": "01432",
    "sg:province": "MA",
    "sg:tags": [
      "contractor"
    ],
    "wof:name": "Peter Ryan Contractor Inc",
    "wof:placetype": "venue"
  },
  "geometry": {"coordinates":[-71.587094,42.56169],"type":"Point"}
}
