{
  "type": "Feature",
  "properties": {
    "iso:country":"US",
    "sg:address":"21 Washington St",
    "sg:city":"Ayer",
    "sg:classifiers":[
        {
            "category":"Building & Trades",
            "subcategory":"Construction",
            "type":"Services"
        }
    ],
    "sg:phone":"+1 978 425 4882",
    "sg:postcode":"01432",
    "sg:province":"MA",
    "sg:tags":[
        "contractor"
    ],
    "wof:name":"Peter Ryan Contractor Inc",
    "wof:placetype":"venue"
},
  "geometry": {"coordinates":[-71.58709399999999,42.56169],"type":"Point"}
}