{
  "type": "Feature",
  "properties": {
    "iso:country":"US",
    "sg:address":"59 Beecher St",
    "sg:city":"Southbridge",
    "sg:classifiers":[
        {
            "category":"Retail",
            "subcategory":"Laundry & Dry Cleaning",
            "type":"Services"
        }
    ],
    "sg:phone":"+1 508 765 0229",
    "sg:postcode":"01550",
    "sg:province":"MA",
    "sg:tags":[
        "cleaner",
        "rug",
        "carpet"
    ],
    "wof:name":"Marinelli Cleaning Service",
    "wof:placetype":"venue"
},
  "geometry": {"coordinates":[-72.03510300000001,42.068699],"type":"Point"}
}