{
  "type": "Feature",
  "properties": {
    "addr:full": "72 Church St Lenox MA 01240",
    "addr:housenumber": "72",
    "addr:postcode": "01240",
    "addr:street": "Church St",
    "iso:country": "US",
    "sg:address": "72 Church St",
    "sg:city": "Lenox",
    "sg:classifiers": [
      {
        "category": "Shopping",
        "subcategory": "Clothing, Apparel, \u0026 Fashions",
        "type": "Retail Goods"
      }
    ],
    "sg:phone": "+1 413 637 1191",
    "sg:postcode": "01240",
    "sg:province": "MA",
    "sg:tags": [
      "children's",
      "infant",
      "wear"
    ],
    "wof:name": "Gifted Child",
    "wof:placetype": "venue"
  },
  "geometry": {"coordinates":[-73.282771,42.357983],"type":"Point"}
}
