{
  "type": "Feature",
  "properties": {
    "addr:full": "273 Cedar Swamp Rd Monson MA 01057",
    "addr:housenumber": "273",
    "addr:postcode": "01057",
    "addr:street": "Cedar Swamp Rd",
    "iso:country": "US",
    "sg:address": "273 Cedar Swamp Rd",
    "sg:city": "Monson",
    "sg:classifiers": [
      {
        "category": "Autos \u0026 Motor Vehicles",
        "subcategory": "Auto Supplies",
        "type": "Retail Goods"
      }
    ],
    "sg:phone": "+1 413 267 5167",
    "sg:postcode": "01057",
    "sg:province": "MA",
    "sg:tags": [
      "automobile",
      "us"
    ],
    "wof:name": "P \u0026 F Auto Parts",
    "wof:placetype": "venue"
  },
  "geometry": {"coordinates":[-72.301593,42.046122],"type":"Point"}
}
