{
  "type": "Feature",
  "properties": {
    "iso:country":"US",
    "sg:address":"273 Cedar Swamp Rd",
    "sg:city":"Monson",
    "sg:classifiers":[
        {
            "category":"Autos & Motor Vehicles",
            "subcategory":"Auto Supplies",
            "type":"Retail Goods"
        }
    ],
    "sg:phone":"+1 413 267 5167",
    "sg:postcode":"01057",
    "sg:province":"MA",
    "sg:tags":[
        "automobile",
        "us"
    ],
    "wof:name":"P & F Auto Parts",
    "wof:placetype":"venue"
},
  "geometry": {"coordinates":[-72.301593,42.046122],"type":"Point"}
}