{
  "type": "Feature",
  "properties": {
    "addr:full": "435 Main St Athol MA 01331",
    "addr:housenumber": "435",
    "addr:postcode": "01331",
    "addr:street": "Main St",
    "iso:country": "US",
    "ovtr:label": "Athol-Orange Auto School, 435 Main St Athol MA US",
    "ovtr:similarity": 3.005156993865967,
    "sg:address": "435 Main St",
    "sg:city": "Athol",
    "sg:classifiers": [
      {
        "category": "Education",
        "subcategory": "Special Training",
        "type": "Public Place"
      }
    ],
    "sg:phone": "+1 978 249 9388",
    "sg:postcode": "01331",
    "sg:province": "MA",
    "sg:tags": [
      "instruction",
      "driving"
    ],
    "wof:name": "Athol-Orange Auto School",
    "wof:placetype": "venue"
  },
  "geometry": {"coordinates":[-72.231686,42.594014],"type":"Point"}
}
