{
  "type": "Feature",
  "properties": {
    "iso:country":"US",
    "sg:address":"435 Main St",
    "sg:city":"Athol",
    "sg:classifiers":[
        {
            "category":"Education",
            "subcategory":"Special Training",
            "type":"Public Place"
        }
    ],
    "sg:phone":"+1 978 249 9388",
    "sg:postcode":"01331",
    "sg:province":"MA",
    "sg:tags":[
        "instruction",
        "driving"
    ],
    "wof:name":"Athol-Orange Auto School",
    "wof:placetype":"venue"
},
  "geometry": {"coordinates":[-72.231686,42.594014],"type":"Point"}
}