{
  "type": "Feature",
  "properties": {
    "iso:country":"US",
    "sg:address":"294 Pleasant St Ste 204",
    "sg:city":"Stoughton",
    "sg:classifiers":[
        {
            "category":"Professional",
            "subcategory":"Lawyer & Legal Services",
            "type":"Services"
        }
    ],
    "sg:phone":"+1 781 297 7427",
    "sg:postcode":"02072",
    "sg:province":"MA",
    "wof:name":"Bierhans Bruce A Atty - CLOSED",
    "wof:placetype":"venue"
},
  "geometry": {"coordinates":[-71.094002,42.1297],"type":"Point"}
}