{
  "type": "Feature",
  "properties": {
    "iso:country":"US",
    "sg:address":"230 3rd Ave",
    "sg:city":"Waltham",
    "sg:classifiers":[
        {
            "category":"Banks & Credit Unions",
            "subcategory":"Investment Brokerage",
            "type":"Services"
        }
    ],
    "sg:phone":"+1 781 895 1776",
    "sg:postcode":"02451",
    "sg:province":"MA",
    "sg:tags":[
        "advisory",
        "financial"
    ],
    "wof:name":"Meehan Financial Svc",
    "wof:placetype":"venue"
},
  "geometry": {"coordinates":[-71.261427,42.390611],"type":"Point"}
}