{
  "type": "Feature",
  "properties": {
    "addr:full": "84 Auburn Park Cambridge MA 02139",
    "addr:housenumber": "84",
    "addr:postcode": "02139",
    "addr:street": "Auburn Park",
    "iso:country": "US",
    "sg:address": "84 Auburn Park",
    "sg:city": "Cambridge",
    "sg:classifiers": [
      {
        "category": "Professional",
        "subcategory": "Advertising",
        "type": "Services"
      }
    ],
    "sg:phone": "+1 617 876 0910",
    "sg:postcode": "02139",
    "sg:province": "MA",
    "sg:tags": [
      "mail"
    ],
    "wof:name": "Source Communications LLC",
    "wof:placetype": "venue"
  },
  "geometry": {"coordinates":[-71.102762,42.362388],"type":"Point"}
}
