{
  "type": "Feature",
  "properties": {
    "addr:full":"37 Waverly St Framingham MA 01702",
    "addr:housenumber":"37",
    "addr:postcode":"01702",
    "addr:street":"Waverly St",
    "iso:country":"US",
    "sg:address":"37 Waverly St",
    "sg:city":"Framingham",
    "sg:classifiers":[
        {
            "category":"Retail",
            "subcategory":"Auto Repair",
            "type":"Services"
        }
    ],
    "sg:phone":"+1 508 626 3655",
    "sg:postcode":"01702",
    "sg:province":"MA",
    "sg:tags":[
        "muffler",
        "exhaust",
        "system"
    ],
    "wof:name":"Meineke Car Care Ctr",
    "wof:placetype":"venue"
},
  "geometry": {"coordinates":[-71.40022,42.280509],"type":"Point"}
}