{
  "type": "Feature",
  "properties": {
    "iso:country":"US",
    "sg:address":"Main Rd",
    "sg:city":"North Falmouth",
    "sg:classifiers":[
        {
            "category":"Food & Beverages",
            "subcategory":"Groceries & Convenience Stores",
            "type":"Retail Goods"
        }
    ],
    "sg:phone":"+1 508 563 3713",
    "sg:postcode":"02556",
    "sg:province":"MA",
    "sg:website":"www.tedeschifoodshops.com",
    "wof:name":"Tedeschi Food Shops",
    "wof:placetype":"venue"
},
  "geometry": {"coordinates":[-70.631798,41.636501],"type":"Point"}
}