{
  "type": "Feature",
  "properties": {
    "addr:full":"373 Highland Ave Somerville MA 02144",
    "addr:housenumber":"373",
    "addr:postcode":"02144",
    "addr:street":"Highland Ave",
    "iso:country":"US",
    "sg:address":"373 Highland Ave",
    "sg:city":"Somerville",
    "sg:classifiers":[
        {
            "category":"Wholesale",
            "subcategory":"Durable Goods & Equipment",
            "type":"Manufacturing & Wholesale Goods"
        },
        {
            "category":"Mining & Drilling",
            "type":"Manufacturing & Wholesale Goods"
        }
    ],
    "sg:phone":"+1 617 628 3100",
    "sg:postcode":"02144",
    "sg:province":"MA",
    "sg:tags":[
        "diamond",
        "powder",
        "representative",
        "manufacturer"
    ],
    "sg:website":"www.ultradiamondtech.com",
    "wof:name":"Ultradiamond Technologies Inc",
    "wof:placetype":"venue"
},
  "geometry": {"coordinates":[-71.119236,42.395215],"type":"Point"}
}