{
  "type": "Feature",
  "properties": {
    "addr:full":"845 Woburn St Wilmington MA 01887",
    "addr:housenumber":"845",
    "addr:postcode":"01887",
    "addr:street":"Woburn St",
    "iso:country":"US",
    "sg:address":"845 Woburn St",
    "sg:city":"Wilmington",
    "sg:classifiers":[
        {
            "category":"Professional",
            "subcategory":"Business Services",
            "type":"Services"
        }
    ],
    "sg:phone":"+1 978 658 6377",
    "sg:postcode":"01887",
    "sg:province":"MA",
    "sg:tags":[
        "delivery",
        "courier"
    ],
    "wof:name":"Hub Delivery",
    "wof:placetype":"venue"
},
  "geometry": {"coordinates":[-71.149002,42.527901],"type":"Point"}
}