{
  "type": "Feature",
  "properties": {
    "addr:full":"22 Jan Marie Dr Plymouth MA 02360",
    "addr:housenumber":"22",
    "addr:postcode":"02360",
    "addr:street":"Jan Marie Dr",
    "iso:country":"US",
    "sg:address":"22 Jan Marie Dr",
    "sg:city":"Plymouth",
    "sg:classifiers":[
        {
            "category":"Education",
            "subcategory":"School",
            "type":"Public Place"
        }
    ],
    "sg:phone":"+1 508 746 3698",
    "sg:postcode":"02360",
    "sg:province":"MA",
    "sg:tags":[
        "consultant",
        "management"
    ],
    "wof:name":"Massachusettes Astronomy",
    "wof:placetype":"venue"
},
  "geometry": {"coordinates":[-70.705673,41.940048],"type":"Point"}
}