{
  "type": "Feature",
  "properties": {
    "addr:full": "90 Lincoln St Lowell MA 01851",
    "addr:housenumber": "90",
    "addr:postcode": "01851",
    "addr:street": "Lincoln St",
    "iso:country": "US",
    "ovtr:label": "City Mirror And Glass Co. Inc., 90 Lincoln St Lowell MA US",
    "ovtr:similarity": 2.7634050846099854,
    "sg:address": "90 Lincoln St",
    "sg:city": "Lowell",
    "sg:classifiers": [
      {
        "category": "Home \u0026 Garden",
        "subcategory": "Building Materials",
        "type": "Retail Goods"
      }
    ],
    "sg:phone": "+1 978 452 5976",
    "sg:postcode": "01851",
    "sg:province": "MA",
    "sg:tags": [
      "glass",
      "window",
      "plate"
    ],
    "wof:name": "City Mirror \u0026 Glass Co Inc",
    "wof:placetype": "venue"
  },
  "geometry": {"coordinates":[-71.31868,42.629646],"type":"Point"}
}
