{
  "type": "Feature",
  "properties": {
    "addr:full":"2068 Main St Tewksbury MA 01876",
    "addr:housenumber":"2068",
    "addr:postcode":"01876",
    "addr:street":"Main St",
    "iso:country":"US",
    "sg:address":"2068 Main St",
    "sg:city":"Tewksbury",
    "sg:classifiers":[
        {
            "category":"Organizations",
            "subcategory":"Community Association",
            "type":"Services"
        }
    ],
    "sg:phone":"+1 978 658 6342",
    "sg:postcode":"01876",
    "sg:province":"MA",
    "sg:tags":[
        "fraternal"
    ],
    "wof:name":"Knights Of Columbus",
    "wof:placetype":"venue"
},
  "geometry": {"coordinates":[-71.199921,42.587201],"type":"Point"}
}