{
  "type": "Feature",
  "properties": {
    "addr:full": "54 Whately Rd South Deerfield MA 01373",
    "addr:housenumber": "54",
    "addr:postcode": "01373",
    "addr:street": "Whately Rd",
    "iso:country": "US",
    "sg:address": "54 Whately Rd",
    "sg:city": "South Deerfield",
    "sg:classifiers": [
      {
        "category": "Social Services",
        "type": "Services"
      }
    ],
    "sg:phone": "+1 413 665 0062",
    "sg:postcode": "01373",
    "sg:province": "MA",
    "sg:tags": [
      "organization",
      "welfare"
    ],
    "wof:name": "Valley Educational Assoc",
    "wof:placetype": "venue"
  },
  "geometry": {"coordinates":[-72.619659,42.477013],"type":"Point"}
}
