{
  "type": "Feature",
  "properties": {
    "iso:country":"US",
    "sg:address":"1277 Broadway",
    "sg:city":"Saugus",
    "sg:classifiers":[
        {
            "category":"Shopping",
            "type":"Retail Goods"
        }
    ],
    "sg:phone":"+1 781 941 2207",
    "sg:postcode":"01906",
    "sg:province":"MA",
    "sg:tags":[
        "incense"
    ],
    "wof:name":"Mystique Place",
    "wof:placetype":"venue"
},
  "geometry": {"coordinates":[-71.024711,42.462458],"type":"Point"}
}