{
  "type": "Feature",
  "properties": {
    "addr:full": "354 White Oak Trl Centerville MA 02632",
    "addr:housenumber": "354",
    "addr:postcode": "02632",
    "addr:street": "White Oak Trl",
    "iso:country": "US",
    "sg:address": "354 White Oak Trl",
    "sg:city": "Centerville",
    "sg:classifiers": [
      {
        "category": "Building \u0026 Trades",
        "subcategory": "Plumbing",
        "type": "Services"
      }
    ],
    "sg:phone": "+1 508 775 1129",
    "sg:postcode": "02632",
    "sg:province": "MA",
    "sg:tags": [
      "heating",
      "contractor"
    ],
    "wof:name": "Gregoire \u0026 Jones Heating Contr",
    "wof:placetype": "venue"
  },
  "geometry": {"coordinates":[-70.354492,41.672424],"type":"Point"}
}
