{
  "type": "Feature",
  "properties": {
    "iso:country":"US",
    "sg:address":"354 White Oak Trl",
    "sg:city":"Centerville",
    "sg:classifiers":[
        {
            "category":"Building & Trades",
            "subcategory":"Plumbing",
            "type":"Services"
        }
    ],
    "sg:phone":"+1 508 775 1129",
    "sg:postcode":"02632",
    "sg:province":"MA",
    "sg:tags":[
        "heating",
        "contractor"
    ],
    "wof:name":"Gregoire & Jones Heating Contr",
    "wof:placetype":"venue"
},
  "geometry": {"coordinates":[-70.35449199999999,41.672424],"type":"Point"}
}