{
  "type": "Feature",
  "properties": {
    "addr:full":"235 Hubbard St Ludlow MA 01056",
    "addr:housenumber":"235",
    "addr:postcode":"01056",
    "addr:street":"Hubbard St",
    "iso:country":"US",
    "sg:address":"235 Hubbard St",
    "sg:city":"Ludlow",
    "sg:classifiers":[
        {
            "category":"Building & Trades",
            "subcategory":"Landscaping Services",
            "type":"Services"
        }
    ],
    "sg:phone":"+1   ",
    "sg:postcode":"01056",
    "sg:province":"MA",
    "wof:name":"Leal Lawncare & Snow Service",
    "wof:placetype":"venue"
},
  "geometry": {"coordinates":[-72.476219,42.15947],"type":"Point"}
}