{
  "type": "Feature",
  "properties": {
    "iso:country":"US",
    "sg:address":"635 Broadway",
    "sg:city":"Saugus",
    "sg:classifiers":[
        {
            "category":"Shopping",
            "subcategory":"Clothing, Apparel, & Fashions",
            "type":"Retail Goods"
        }
    ],
    "sg:phone":"+1 781 233 5029",
    "sg:postcode":"01906",
    "sg:province":"MA",
    "wof:name":"Priceless Kids",
    "wof:placetype":"venue"
},
  "geometry": {"coordinates":[-71.022357,42.478994],"type":"Point"}
}