{
  "type": "Feature",
  "properties": {
    "addr:full": "276 Lunenburg St Fitchburg MA 01420",
    "addr:housenumber": "276",
    "addr:postcode": "01420",
    "addr:street": "Lunenburg St",
    "iso:country": "US",
    "sg:address": "276 Lunenburg St",
    "sg:city": "Fitchburg",
    "sg:classifiers": [
      {
        "category": "Restaurant",
        "type": "Food \u0026 Drink"
      }
    ],
    "sg:phone": "+1   ",
    "sg:postcode": "01420",
    "sg:province": "MA",
    "sg:tags": [
      "eating"
    ],
    "wof:name": "Mill Street Cafe",
    "wof:placetype": "venue"
  },
  "geometry": {"coordinates":[-71.774076,42.586095],"type":"Point"}
}
