{
  "type": "Feature",
  "properties": {
    "iso:country":"US",
    "sg:address":"276 Lunenburg St",
    "sg:city":"Fitchburg",
    "sg:classifiers":[
        {
            "category":"Restaurant",
            "type":"Food & Drink"
        }
    ],
    "sg:phone":"+1   ",
    "sg:postcode":"01420",
    "sg:province":"MA",
    "sg:tags":[
        "eating"
    ],
    "wof:name":"Mill Street Cafe",
    "wof:placetype":"venue"
},
  "geometry": {"coordinates":[-71.77407599999999,42.586095],"type":"Point"}
}