{
  "type": "Feature",
  "properties": {
    "addr:full":"400 S Undermountain Rd Sheffield MA 01257",
    "addr:housenumber":"400",
    "addr:postcode":"01257",
    "addr:street":"S Undermountain Rd",
    "iso:country":"US",
    "sg:address":"400 S Undermountain Rd",
    "sg:city":"Sheffield",
    "sg:classifiers":[
        {
            "category":"Travel",
            "subcategory":"Hotels & Motels",
            "type":"Entertainment"
        }
    ],
    "sg:phone":"+1 413 229 3363",
    "sg:postcode":"01257",
    "sg:province":"MA",
    "sg:tags":[
        "breakfast",
        "accommodation",
        "bed"
    ],
    "sg:website":"www.ramblewoodinn.com",
    "wof:name":"Ramblewood Inn",
    "wof:placetype":"venue"
},
  "geometry": {"coordinates":[-73.409504,42.098068],"type":"Point"}
}