{
  "type": "Feature",
  "properties": {
    "addr:full": "10 Peabody St Haverhill MA 01835",
    "addr:housenumber": "10",
    "addr:postcode": "01835",
    "addr:street": "Peabody St",
    "iso:country": "US",
    "sg:address": "10 Peabody St",
    "sg:city": "Haverhill",
    "sg:phone": "+1 978 521 7095",
    "sg:postcode": "01835",
    "sg:province": "MA",
    "sg:tags": [
      "scale"
    ],
    "wof:name": "Precision Weighing Balances",
    "wof:placetype": "venue"
  },
  "geometry": {"coordinates":[-71.067211,42.764685],"type":"Point"}
}
