{
  "type": "Feature",
  "properties": {
    "addr:full":"210 Highland Ave Needham MA 02494",
    "addr:housenumber":"210",
    "addr:postcode":"02494",
    "addr:street":"Highland Ave",
    "iso:country":"US",
    "sg:address":"210 Highland Ave",
    "sg:city":"Needham",
    "sg:classifiers":[
        {
            "category":"Wholesale",
            "subcategory":"Durable Goods & Equipment",
            "type":"Manufacturing & Wholesale Goods"
        }
    ],
    "sg:phone":"+1 781 449 8024",
    "sg:postcode":"02494",
    "sg:province":"MA",
    "sg:tags":[
        "representative",
        "manufacturer"
    ],
    "sg:website":"www.madlar.com",
    "wof:name":"Madlar Marketing Inc",
    "wof:placetype":"venue"
},
  "geometry": {"coordinates":[-71.22004200000001,42.304533],"type":"Point"}
}