{
  "type": "Feature",
  "properties": {
    "iso:country":"US",
    "sg:address":"975 N Main St",
    "sg:city":"Randolph",
    "sg:classifiers":[
        {
            "category":"Social Services",
            "subcategory":"Job Training",
            "type":"Services"
        }
    ],
    "sg:phone":"+1 781 963 6326",
    "sg:postcode":"02368",
    "sg:province":"MA",
    "sg:tags":[
        "rehabilitation"
    ],
    "wof:name":"Paragon Rehabilitation Inc",
    "wof:placetype":"venue"
},
  "geometry": {"coordinates":[-71.057738,42.189322],"type":"Point"}
}