{
  "type": "Feature",
  "properties": {
    "iso:country":"US",
    "sg:address":"341 Russell St",
    "sg:city":"Hadley",
    "sg:classifiers":[
        {
            "category":"Shopping",
            "type":"Retail Goods"
        }
    ],
    "sg:phone":"+1 413 582 9089",
    "sg:postcode":"01035",
    "sg:province":"MA",
    "sg:tags":[
        "cosmetic",
        "perfume"
    ],
    "wof:name":"Bath & Body Works Inc",
    "wof:placetype":"venue"
},
  "geometry": {"coordinates":[-72.55144199999999,42.357291],"type":"Point"}
}