{
  "type": "Feature",
  "properties": {
    "addr:full": "32 Central Ave Needham MA 02494",
    "addr:housenumber": "32",
    "addr:postcode": "02494",
    "addr:street": "Central Ave",
    "iso:country": "US",
    "sg:address": "32 Central Ave",
    "sg:city": "Needham",
    "sg:classifiers": [
      {
        "category": "Wholesale",
        "subcategory": "Durable Goods \u0026 Equipment",
        "type": "Manufacturing \u0026 Wholesale Goods"
      }
    ],
    "sg:phone": "+1 781 444 1880",
    "sg:postcode": "02494",
    "sg:province": "MA",
    "sg:tags": [
      "representative",
      "manufacturer"
    ],
    "wof:name": "B Samuels Assoc Inc",
    "wof:placetype": "venue"
  },
  "geometry": {"coordinates":[-71.227865,42.312024],"type":"Point"}
}
