{
  "type": "Feature",
  "properties": {
    "iso:country":"US",
    "sg:address":"32 Central Ave",
    "sg:city":"Needham",
    "sg:classifiers":[
        {
            "category":"Wholesale",
            "subcategory":"Durable Goods & Equipment",
            "type":"Manufacturing & Wholesale Goods"
        }
    ],
    "sg:phone":"+1 781 444 1880",
    "sg:postcode":"02494",
    "sg:province":"MA",
    "sg:tags":[
        "representative",
        "manufacturer"
    ],
    "wof:name":"B Samuels Assoc Inc",
    "wof:placetype":"venue"
},
  "geometry": {"coordinates":[-71.22786499999999,42.312024],"type":"Point"}
}