{
  "type": "Feature",
  "properties": {
    "addr:full":"610 Shawmut Ave Roxbury MA 02118",
    "addr:housenumber":"610",
    "addr:postcode":"02118",
    "addr:street":"Shawmut Ave",
    "iso:country":"US",
    "sg:address":"610 Shawmut Ave",
    "sg:city":"Roxbury",
    "sg:classifiers":[
        {
            "category":"Organizations",
            "subcategory":"Community Association",
            "type":"Services"
        }
    ],
    "sg:phone":"+1 617 427 7297",
    "sg:postcode":"02118",
    "sg:province":"MA",
    "sg:tags":[
        "club"
    ],
    "wof:name":"Roxbury Mens Club",
    "wof:placetype":"venue"
},
  "geometry": {"coordinates":[-71.080597,42.335583],"type":"Point"}
}