{
  "type": "Feature",
  "properties": {
    "iso:country":"US",
    "sg:address":"794 S Main St",
    "sg:city":"Bellingham",
    "sg:classifiers":[
        {
            "category":"Retail",
            "subcategory":"Auto Repair",
            "type":"Services"
        }
    ],
    "sg:phone":"+1 508 883 1978",
    "sg:postcode":"02019",
    "sg:province":"MA",
    "sg:tags":[
        "repairing",
        "automobile"
    ],
    "wof:name":"Bellingham Parts Plus",
    "wof:placetype":"venue"
},
  "geometry": {"coordinates":[-71.484731,42.052305],"type":"Point"}
}