{
  "type": "Feature",
  "properties": {
    "addr:full": "2 Ellis Dr Harwich MA 02645",
    "addr:housenumber": "2",
    "addr:postcode": "02645",
    "addr:street": "Ellis Dr",
    "iso:country": "US",
    "sg:address": "2 Ellis Dr",
    "sg:city": "Harwich",
    "sg:classifiers": [
      {
        "category": "Wholesale",
        "subcategory": "Construction Materials",
        "type": "Manufacturing \u0026 Wholesale Goods"
      }
    ],
    "sg:phone": "+1 508 432 7877",
    "sg:postcode": "02645",
    "sg:province": "MA",
    "sg:tags": [
      "granite"
    ],
    "wof:name": "Victoria Granite Inc",
    "wof:placetype": "venue"
  },
  "geometry": {"coordinates":[-70.018755,41.700714],"type":"Point"}
}
