{
  "type": "Feature",
  "properties": {
    "iso:country":"US",
    "sg:address":"2 Technology Dr",
    "sg:city":"Westborough",
    "sg:classifiers":[
        {
            "category":"Manufacturing",
            "subcategory":"Tools & Machinery",
            "type":"Manufacturing & Wholesale Goods"
        }
    ],
    "sg:phone":"+1 508 836 4200",
    "sg:postcode":"01581",
    "sg:province":"MA",
    "sg:tags":[
        "product",
        "electrical"
    ],
    "wof:name":"American Superconductor Corp",
    "wof:placetype":"venue"
},
  "geometry": {"coordinates":[-71.573021,42.288965],"type":"Point"}
}