{
  "type": "Feature",
  "properties": {
    "iso:country":"US",
    "sg:address":"153 Washington St",
    "sg:city":"Boston",
    "sg:classifiers":[
        {
            "category":"Organizations",
            "subcategory":"Religious Organization",
            "type":"Services"
        }
    ],
    "sg:phone":"+1 617 740 7131",
    "sg:postcode":"02121",
    "sg:province":"MA",
    "sg:tags":[
        "church"
    ],
    "wof:name":"New Bethel Apostolic Church",
    "wof:placetype":"venue"
},
  "geometry": {"coordinates":[-71.07894,42.303937],"type":"Point"}
}