{
  "type": "Feature",
  "properties": {
    "iso:country":"US",
    "sg:address":"471 Hanover St",
    "sg:city":"Boston",
    "sg:classifiers":[
        {
            "category":"Restaurant",
            "type":"Food & Drink"
        }
    ],
    "sg:phone":"+1 617 742 7172",
    "sg:postcode":"02113",
    "sg:province":"MA",
    "sg:tags":[
        "pizza"
    ],
    "wof:name":"Grill 417",
    "wof:placetype":"venue"
},
  "geometry": {"coordinates":[-71.05259700000001,42.367199],"type":"Point"}
}