{
  "type": "Feature",
  "properties": {
    "addr:full": "1008 East St Walpole MA 02081",
    "addr:housenumber": "1008",
    "addr:postcode": "02081",
    "addr:street": "East St",
    "iso:country": "US",
    "sg:address": "1008 East St",
    "sg:city": "Walpole",
    "sg:classifiers": [
      {
        "category": "Health Services",
        "subcategory": "Doctor",
        "type": "Services"
      }
    ],
    "sg:phone": "+1 508 668 6060",
    "sg:postcode": "02081",
    "sg:province": "MA",
    "wof:name": "Walpole Internal Medicine MD",
    "wof:placetype": "venue"
  },
  "geometry": {"coordinates":[-71.232399,42.151798],"type":"Point"}
}
