{
  "type": "Feature",
  "properties": {
    "addr:full": "352 Albany St Springfield MA 01105",
    "addr:housenumber": "352",
    "addr:postcode": "01105",
    "addr:street": "Albany St",
    "iso:country": "US",
    "ovtr:label": "Associated Building Wreckers, Inc., 352 Albany St Springfield MA US",
    "ovtr:similarity": 3.9825220108032227,
    "sg:address": "352 Albany St",
    "sg:city": "Springfield",
    "sg:classifiers": [
      {
        "category": "Building \u0026 Trades",
        "subcategory": "Construction",
        "type": "Services"
      }
    ],
    "sg:phone": "+1 413 732 3179",
    "sg:postcode": "01105",
    "sg:province": "MA",
    "sg:tags": [
      "demolition",
      "contractor"
    ],
    "wof:name": "Associated Building Wreckers",
    "wof:placetype": "venue"
  },
  "geometry": {"coordinates":[-72.57024,42.122147],"type":"Point"}
}
