{
  "type": "Feature",
  "properties": {
    "iso:country":"US",
    "sg:address":"352 Albany St",
    "sg:city":"Springfield",
    "sg:classifiers":[
        {
            "category":"Building & Trades",
            "subcategory":"Construction",
            "type":"Services"
        }
    ],
    "sg:phone":"+1 413 732 3179",
    "sg:postcode":"01105",
    "sg:province":"MA",
    "sg:tags":[
        "demolition",
        "contractor"
    ],
    "wof:name":"Associated Building Wreckers",
    "wof:placetype":"venue"
},
  "geometry": {"coordinates":[-72.57024,42.122147],"type":"Point"}
}