{
  "type": "Feature",
  "properties": {
    "iso:country":"US",
    "sg:address":"80 Landsdowne St",
    "sg:city":"Cambridge",
    "sg:classifiers":[
        {
            "category":"Real Estate",
            "subcategory":"Architect",
            "type":"Services"
        }
    ],
    "sg:phone":"+1 617 876 6580",
    "sg:postcode":"02139",
    "sg:province":"MA",
    "sg:tags":[
        "building",
        "construction"
    ],
    "wof:name":"William A Berry & Son",
    "wof:placetype":"venue"
},
  "geometry": {"coordinates":[-71.10142399999999,42.359995],"type":"Point"}
}