{
  "type": "Feature",
  "properties": {
    "addr:full": "131 Main St Carver MA 02330",
    "addr:housenumber": "131",
    "addr:postcode": "02330",
    "addr:street": "Main St",
    "iso:country": "US",
    "sg:address": "131 Main St",
    "sg:city": "Carver",
    "sg:classifiers": [
      {
        "category": "Autos \u0026 Motor Vehicles",
        "subcategory": "Fuel \u0026 Gas Station",
        "type": "Retail Goods"
      }
    ],
    "sg:phone": "+1 508 866 9098",
    "sg:postcode": "02330",
    "sg:province": "MA",
    "wof:name": "Eagle Gas Inc",
    "wof:placetype": "venue"
  },
  "geometry": {"coordinates":[-70.7665,41.8848],"type":"Point"}
}
