{
  "type": "Feature",
  "properties": {
    "iso:country":"US",
    "sg:address":"131 Main St",
    "sg:city":"Carver",
    "sg:classifiers":[
        {
            "category":"Autos & Motor Vehicles",
            "subcategory":"Fuel & Gas Station",
            "type":"Retail Goods"
        }
    ],
    "sg:phone":"+1 508 866 9098",
    "sg:postcode":"02330",
    "sg:province":"MA",
    "wof:name":"Eagle Gas Inc",
    "wof:placetype":"venue"
},
  "geometry": {"coordinates":[-70.76649999999999,41.8848],"type":"Point"}
}