{
  "type": "Feature",
  "properties": {
    "iso:country":"US",
    "sg:address":"877 Main St",
    "sg:city":"Osterville",
    "sg:classifiers":[
        {
            "category":"Real Estate",
            "subcategory":"Real Estate Services",
            "type":"Services"
        }
    ],
    "sg:phone":"+1 508 428 0401",
    "sg:postcode":"02655",
    "sg:province":"MA",
    "wof:name":"Schulze Donna Realtor - CLOSED",
    "wof:placetype":"venue"
},
  "geometry": {"coordinates":[-70.387001,41.628899],"type":"Point"}
}