{
  "type": "Feature",
  "properties": {
    "addr:full": "46 South St Rockport MA 01966",
    "addr:housenumber": "46",
    "addr:postcode": "01966",
    "addr:street": "South St",
    "iso:country": "US",
    "sg:address": "46 South St",
    "sg:city": "Rockport",
    "sg:classifiers": [
      {
        "category": "Shopping",
        "subcategory": "Jewelry",
        "type": "Retail Goods"
      }
    ],
    "sg:phone": "+1 978 546 5922",
    "sg:postcode": "01966",
    "sg:province": "MA",
    "sg:tags": [
      "jeweler"
    ],
    "wof:name": "Earth's Treasures",
    "wof:placetype": "venue"
  },
  "geometry": {"coordinates":[-70.604726,42.654162],"type":"Point"}
}
