{
  "type": "Feature",
  "properties": {
    "addr:full":"262 Summer St Lunenburg MA 01462",
    "addr:housenumber":"262",
    "addr:postcode":"01462",
    "addr:street":"Summer St",
    "iso:country":"US",
    "sg:address":"262 Summer St",
    "sg:city":"Lunenburg",
    "sg:classifiers":[
        {
            "category":"Building & Trades",
            "subcategory":"Construction",
            "type":"Services"
        }
    ],
    "sg:phone":"+1 978 343 2323",
    "sg:postcode":"01462",
    "sg:province":"MA",
    "sg:tags":[
        "utility",
        "contractor"
    ],
    "wof:name":"Paolini Corp",
    "wof:placetype":"venue"
},
  "geometry": {"coordinates":[-71.762033,42.566685],"type":"Point"}
}