{
  "type": "Feature",
  "properties": {
    "iso:country":"US",
    "sg:address":"806 Tremont St",
    "sg:city":"Boston",
    "sg:classifiers":[
        {
            "category":"Personal",
            "subcategory":"Adult",
            "type":"Services"
        }
    ],
    "sg:phone":"+1 617 254 0660",
    "sg:postcode":"02118",
    "sg:province":"MA",
    "sg:tags":[
        "escort"
    ],
    "wof:name":"Park Avenue",
    "wof:placetype":"venue"
},
  "geometry": {"coordinates":[-71.081602,42.338609],"type":"Point"}
}