{
  "type": "Feature",
  "properties": {
    "iso:country":"US",
    "sg:address":"215 Quincy Ave",
    "sg:city":"Quincy",
    "sg:classifiers":[
        {
            "category":"Building & Trades",
            "subcategory":"Equipment Rental",
            "type":"Services"
        }
    ],
    "sg:phone":"+1 617 786 7772",
    "sg:postcode":"02169",
    "sg:province":"MA",
    "sg:tags":[
        "leasing",
        "furniture"
    ],
    "wof:name":"Aaron's Rental Purchase",
    "wof:placetype":"venue"
},
  "geometry": {"coordinates":[-70.990143,42.241081],"type":"Point"}
}