{
  "type": "Feature",
  "properties": {
    "addr:full": "33 Rock Meadow Dr Brockton MA 02301",
    "addr:housenumber": "33",
    "addr:postcode": "02301",
    "addr:street": "Rock Meadow Dr",
    "iso:country": "US",
    "sg:address": "33 Rock Meadow Dr",
    "sg:city": "Brockton",
    "sg:classifiers": [
      {
        "category": "Professional",
        "subcategory": "Lawyer \u0026 Legal Services",
        "type": "Services"
      }
    ],
    "sg:phone": "+1 508 588 3607",
    "sg:postcode": "02301",
    "sg:province": "MA",
    "sg:tags": [
      "attorney"
    ],
    "wof:name": "Ona G Wainwright",
    "wof:placetype": "venue"
  },
  "geometry": {"coordinates":[-71.058814,42.075488],"type":"Point"}
}
