{
  "type": "Feature",
  "properties": {
    "addr:full":"180 Bunker Hill St Charlestown MA 02129",
    "addr:housenumber":"180",
    "addr:postcode":"02129",
    "addr:street":"Bunker Hill St",
    "iso:country":"US",
    "sg:address":"180 Bunker Hill St",
    "sg:city":"Charlestown",
    "sg:classifiers":[
        {
            "category":"Shopping",
            "type":"Retail Goods"
        }
    ],
    "sg:phone":"+1 617 734 2232",
    "sg:postcode":"02129",
    "sg:province":"MA",
    "sg:tags":[
        "merchandise"
    ],
    "wof:name":"Martin Beepers Repair Shop",
    "wof:placetype":"venue"
},
  "geometry": {"coordinates":[-71.061577,42.378639],"type":"Point"}
}