{
  "type": "Feature",
  "properties": {
    "addr:full": "32 Sherborne Cir Ashland MA 01721",
    "addr:housenumber": "32",
    "addr:postcode": "01721",
    "addr:street": "Sherborne Cir",
    "iso:country": "US",
    "sg:address": "32 Sherborne Cir",
    "sg:city": "Ashland",
    "sg:classifiers": [
      {
        "category": "Professional",
        "subcategory": "Business Services",
        "type": "Services"
      }
    ],
    "sg:phone": "+1   ",
    "sg:postcode": "01721",
    "sg:province": "MA",
    "wof:name": "Boccuzzi Solutions",
    "wof:placetype": "venue"
  },
  "geometry": {"coordinates":[-71.425957,42.240827],"type":"Point"}
}
