{
  "type": "Feature",
  "properties": {
    "iso:country":"US",
    "sg:address":"46 Main St",
    "sg:city":"Conway",
    "sg:classifiers":[
        {
            "category":"Building & Trades",
            "subcategory":"Plumbing",
            "type":"Services"
        }
    ],
    "sg:phone":"+1 413 369 4081",
    "sg:postcode":"01341",
    "sg:province":"MA",
    "sg:tags":[
        "plumbing",
        "contractor"
    ],
    "wof:name":"Ouimette Plumbing & Heating",
    "wof:placetype":"venue"
},
  "geometry": {"coordinates":[-72.697163,42.508724],"type":"Point"}
}