{
  "type": "Feature",
  "properties": {
    "addr:full": "46 Main St Conway MA 01341",
    "addr:housenumber": "46",
    "addr:postcode": "01341",
    "addr:street": "Main St",
    "iso:country": "US",
    "sg:address": "46 Main St",
    "sg:city": "Conway",
    "sg:classifiers": [
      {
        "category": "Building \u0026 Trades",
        "subcategory": "Plumbing",
        "type": "Services"
      }
    ],
    "sg:phone": "+1 413 369 4081",
    "sg:postcode": "01341",
    "sg:province": "MA",
    "sg:tags": [
      "plumbing",
      "contractor"
    ],
    "wof:name": "Ouimette Plumbing \u0026 Heating",
    "wof:placetype": "venue"
  },
  "geometry": {"coordinates":[-72.697163,42.508724],"type":"Point"}
}
