{
  "type": "Feature",
  "properties": {
    "iso:country":"US",
    "sg:address":"1 Market St",
    "sg:city":"Lynn",
    "sg:classifiers":[
        {
            "category":"Health Services",
            "subcategory":"Chiropractor",
            "type":"Services"
        }
    ],
    "sg:phone":"+1 781 593 4144",
    "sg:postcode":"01901",
    "sg:province":"MA",
    "wof:name":"Northshore Chiropractic Ofcs",
    "wof:placetype":"venue"
},
  "geometry": {"coordinates":[-70.94968299999999,42.463356],"type":"Point"}
}