{
  "type": "Feature",
  "properties": {
    "addr:full":"1 Design Center Pl # 643 Boston MA 02210",
    "addr:postcode":"02210",
    "addr:street":"Center Pl # 643",
    "iso:country":"US",
    "sg:address":"1 Design Center Pl # 643",
    "sg:city":"Boston",
    "sg:classifiers":[
        {
            "category":"Home & Garden",
            "subcategory":"Household Appliances",
            "type":"Retail Goods"
        },
        {
            "category":"Home & Garden",
            "subcategory":"Furniture",
            "type":"Retail Goods"
        },
        {
            "category":"Wholesale",
            "subcategory":"Home Furnishings",
            "type":"Manufacturing & Wholesale Goods"
        }
    ],
    "sg:phone":"+1 617 482 2566",
    "sg:postcode":"02210",
    "sg:province":"MA",
    "sg:tags":[
        "major",
        "equipment-wholesale",
        "kitchen",
        "equipment-household",
        "cabinet",
        "manufacturer"
    ],
    "sg:website":"http://www.daliakitchens.com",
    "wof:name":"Alno Boston",
    "wof:placetype":"venue"
},
  "geometry": {"coordinates":[-71.034317,42.343929],"type":"Point"}
}