{
  "type": "Feature",
  "properties": {
    "addr:full": "50 Croydon Rd Worcester MA 01606",
    "addr:housenumber": "50",
    "addr:postcode": "01606",
    "addr:street": "Croydon Rd",
    "iso:country": "US",
    "sg:address": "50 Croydon Rd",
    "sg:city": "Worcester",
    "sg:classifiers": [
      {
        "category": "Social Services",
        "subcategory": "Child Care",
        "type": "Services"
      }
    ],
    "sg:phone": "+1 508 852 4754",
    "sg:postcode": "01606",
    "sg:province": "MA",
    "wof:name": "Explorer's Clubhouse",
    "wof:placetype": "venue"
  },
  "geometry": {"coordinates":[-71.791747,42.319111],"type":"Point"}
}
