{
  "type": "Feature",
  "properties": {
    "addr:full":"65 Fall River Ave Rehoboth MA 02769",
    "addr:housenumber":"65",
    "addr:postcode":"02769",
    "addr:street":"Fall River Ave",
    "iso:country":"US",
    "sg:address":"65 Fall River Ave",
    "sg:city":"Rehoboth",
    "sg:classifiers":[
        {
            "category":"Insurance",
            "subcategory":"Hazard Insurance",
            "type":"Services"
        }
    ],
    "sg:phone":"+1 508 336 3900",
    "sg:postcode":"02769",
    "sg:province":"MA",
    "sg:tags":[
        "commercial",
        "business"
    ],
    "wof:name":"Rodrigues Dennis Insurance Agency",
    "wof:placetype":"venue"
},
  "geometry": {"coordinates":[-71.292526,41.778576],"type":"Point"}
}