{
  "type": "Feature",
  "properties": {
    "addr:full":"75 Dutcher St Hopedale MA 01747",
    "addr:housenumber":"75",
    "addr:postcode":"01747",
    "addr:street":"Dutcher St",
    "iso:country":"US",
    "sg:address":"75 Dutcher St",
    "sg:city":"Hopedale",
    "sg:classifiers":[
        {
            "category":"Education",
            "subcategory":"Special Training",
            "type":"Public Place"
        }
    ],
    "sg:phone":"+1 508 473 1032",
    "sg:postcode":"01747",
    "sg:province":"MA",
    "sg:tags":[
        "tutoring"
    ],
    "wof:name":"Reid Tutoring Svc",
    "wof:placetype":"venue"
},
  "geometry": {"coordinates":[-71.543744,42.135713],"type":"Point"}
}