{
  "type": "Feature",
  "properties": {
    "addr:full":"27 S Bolton St Marlborough MA 01752",
    "addr:housenumber":"27",
    "addr:postcode":"01752",
    "addr:street":"S Bolton St",
    "iso:country":"US",
    "sg:address":"27 S Bolton St",
    "sg:city":"Marlborough",
    "sg:classifiers":[
        {
            "category":"Winery",
            "type":"Food & Drink"
        },
        {
            "category":"Food & Beverages",
            "subcategory":"Specialty",
            "type":"Retail Goods"
        },
        {
            "category":"Food & Beverages",
            "subcategory":"Liquor & Beverages",
            "type":"Retail Goods"
        },
        {
            "category":"Wholesale",
            "subcategory":"Wine & Distilled Alcoholic Beverages",
            "type":"Manufacturing & Wholesale Goods"
        }
    ],
    "sg:phone":"+1 508 480 9463",
    "sg:postcode":"01752",
    "sg:province":"MA",
    "sg:tags":[
        "shop",
        "gourmet",
        "broker",
        "store"
    ],
    "wof:name":"Vin Bin",
    "wof:placetype":"venue"
},
  "geometry": {"coordinates":[-71.545884,42.346373],"type":"Point"}
}