{
  "type": "Feature",
  "properties": {
    "addr:full": "2 Frontage Rd Boston MA 02118",
    "addr:housenumber": "2",
    "addr:postcode": "02118",
    "addr:street": "Frontage Rd",
    "iso:country": "US",
    "sg:address": "2 Frontage Rd",
    "sg:city": "Boston",
    "sg:classifiers": [
      {
        "category": "Professional",
        "type": "Services"
      }
    ],
    "sg:phone": "+1   ",
    "sg:postcode": "02118",
    "sg:province": "MA",
    "wof:name": "Lastom Transportation",
    "wof:placetype": "venue"
  },
  "geometry": {"coordinates":[-71.060229,42.330186],"type":"Point"}
}
