{
  "type": "Feature",
  "properties": {
    "iso:country":"US",
    "sg:address":"2 Frontage Rd",
    "sg:city":"Boston",
    "sg:classifiers":[
        {
            "category":"Professional",
            "type":"Services"
        }
    ],
    "sg:phone":"+1   ",
    "sg:postcode":"02118",
    "sg:province":"MA",
    "wof:name":"Lastom Transportation",
    "wof:placetype":"venue"
},
  "geometry": {"coordinates":[-71.06022900000001,42.330186],"type":"Point"}
}