{
  "type": "Feature",
  "properties": {
    "iso:country":"US",
    "sg:address":"4 Downing St",
    "sg:city":"Fall River",
    "sg:classifiers":[
        {
            "category":"Professional",
            "subcategory":"Computer Services",
            "type":"Services"
        }
    ],
    "sg:phone":"+1 508 324 0961",
    "sg:postcode":"02723",
    "sg:province":"MA",
    "sg:tags":[
        "repair"
    ],
    "wof:name":"Printer Pros",
    "wof:placetype":"venue"
},
  "geometry": {"coordinates":[-71.133037,41.695651],"type":"Point"}
}