{
  "type": "Feature",
  "properties": {
    "addr:full":"1199 Sumner Ave Springfield MA 01118",
    "addr:housenumber":"1199",
    "addr:postcode":"01118",
    "addr:street":"Sumner Ave",
    "iso:country":"US",
    "sg:address":"1199 Sumner Ave",
    "sg:city":"Springfield",
    "sg:classifiers":[
        {
            "category":"Food & Beverages",
            "subcategory":"Specialty",
            "type":"Retail Goods"
        }
    ],
    "sg:phone":"+1 413 782 4296",
    "sg:postcode":"01118",
    "sg:province":"MA",
    "sg:tags":[
        "gourmet",
        "shop"
    ],
    "wof:name":"Gordie's Gourmet",
    "wof:placetype":"venue"
},
  "geometry": {"coordinates":[-72.53367299999999,42.090832],"type":"Point"}
}