{
  "type": "Feature",
  "properties": {
    "addr:full": "1570 Boston-Providence Tpke Norwood MA 02062",
    "addr:housenumber": "1570",
    "addr:postcode": "02062",
    "addr:street": "Boston-Providence Tpke",
    "iso:country": "US",
    "sg:address": "1570 Boston-Providence Tpke",
    "sg:city": "Norwood",
    "sg:classifiers": [
      {
        "category": "Home \u0026 Garden",
        "subcategory": "Furniture",
        "type": "Retail Goods"
      }
    ],
    "sg:phone": "+1 781 255 2020",
    "sg:postcode": "02062",
    "sg:province": "MA",
    "sg:tags": [
      "mattress"
    ],
    "wof:name": "Sleep Easy",
    "wof:placetype": "venue"
  },
  "geometry": {"coordinates":[-71.200451,42.159666],"type":"Point"}
}
