{
  "type": "Feature",
  "properties": {
    "iso:country":"US",
    "sg:address":"397 Main St",
    "sg:city":"Spencer",
    "sg:classifiers":[
        {
            "category":"Banks & Credit Unions",
            "subcategory":"Bank",
            "type":"Services"
        }
    ],
    "sg:phone":"+1 508 885 8100",
    "sg:postcode":"01562",
    "sg:province":"MA",
    "sg:tags":[
        "loan",
        "real estate"
    ],
    "wof:name":"Country Mortgage Corp",
    "wof:placetype":"venue"
},
  "geometry": {"coordinates":[-71.95513699999999,42.256011],"type":"Point"}
}