{
  "type": "Feature",
  "properties": {
    "addr:full": "397 Main St Spencer MA 01562",
    "addr:housenumber": "397",
    "addr:postcode": "01562",
    "addr:street": "Main St",
    "iso:country": "US",
    "sg:address": "397 Main St",
    "sg:city": "Spencer",
    "sg:classifiers": [
      {
        "category": "Banks \u0026 Credit Unions",
        "subcategory": "Bank",
        "type": "Services"
      }
    ],
    "sg:phone": "+1 508 885 8100",
    "sg:postcode": "01562",
    "sg:province": "MA",
    "sg:tags": [
      "loan",
      "real estate"
    ],
    "wof:name": "Country Mortgage Corp",
    "wof:placetype": "venue"
  },
  "geometry": {"coordinates":[-71.955137,42.256011],"type":"Point"}
}
