{
  "type": "Feature",
  "properties": {
    "addr:full": "54 S Williams St Haverhill MA 01835",
    "addr:housenumber": "54",
    "addr:postcode": "01835",
    "addr:street": "S Williams St",
    "iso:country": "US",
    "sg:address": "54 S Williams St",
    "sg:city": "Haverhill",
    "sg:classifiers": [
      {
        "category": "Shopping",
        "subcategory": "Stationery \u0026 Office Supplies",
        "type": "Retail Goods"
      }
    ],
    "sg:phone": "+1   ",
    "sg:postcode": "01835",
    "sg:province": "MA",
    "wof:name": "Laurie W Perkins",
    "wof:placetype": "venue"
  },
  "geometry": {"coordinates":[-71.075181,42.762329],"type":"Point"}
}
