{
  "type": "Feature",
  "properties": {
    "addr:full": "241 John Wise Ave Essex MA 01929",
    "addr:housenumber": "241",
    "addr:postcode": "01929",
    "addr:street": "John Wise Ave",
    "iso:country": "US",
    "sg:address": "241 John Wise Ave",
    "sg:city": "Essex",
    "sg:classifiers": [
      {
        "category": "Food \u0026 Beverages",
        "subcategory": "Meat \u0026 Fish",
        "type": "Retail Goods"
      }
    ],
    "sg:phone": "+1 978 768 6371",
    "sg:postcode": "01929",
    "sg:province": "MA",
    "sg:tags": [
      "lobster"
    ],
    "wof:name": "Essex Lobster Co",
    "wof:placetype": "venue"
  },
  "geometry": {"coordinates":[-70.806325,42.653895],"type":"Point"}
}
