{
  "type": "Feature",
  "properties": {
    "iso:country":"US",
    "sg:address":"241 John Wise Ave",
    "sg:city":"Essex",
    "sg:classifiers":[
        {
            "category":"Food & Beverages",
            "subcategory":"Meat & Fish",
            "type":"Retail Goods"
        }
    ],
    "sg:phone":"+1 978 768 6371",
    "sg:postcode":"01929",
    "sg:province":"MA",
    "sg:tags":[
        "lobster"
    ],
    "wof:name":"Essex Lobster Co",
    "wof:placetype":"venue"
},
  "geometry": {"coordinates":[-70.806325,42.653895],"type":"Point"}
}