{
  "type": "Feature",
  "properties": {
    "addr:full": "138 Lowell St Lexington MA 02420",
    "addr:housenumber": "138",
    "addr:postcode": "02420",
    "addr:street": "Lowell St",
    "iso:country": "US",
    "sg:address": "138 Lowell St",
    "sg:city": "Lexington",
    "sg:classifiers": [
      {
        "category": "Personal",
        "type": "Services"
      }
    ],
    "sg:phone": "+1 781 861 9847",
    "sg:postcode": "02420",
    "sg:province": "MA",
    "sg:tags": [
      "counseling"
    ],
    "wof:name": "Noation Collaborative, The",
    "wof:placetype": "venue"
  },
  "geometry": {"coordinates":[-71.19063,42.437662],"type":"Point"}
}
