{
  "type": "Feature",
  "properties": {
    "addr:full":"69 Kittredge St Roslindale MA 02131",
    "addr:housenumber":"69",
    "addr:postcode":"02131",
    "addr:street":"Kittredge St",
    "iso:country":"US",
    "sg:address":"69 Kittredge St",
    "sg:city":"Roslindale",
    "sg:classifiers":[
        {
            "category":"Wholesale",
            "subcategory":"Electrical",
            "type":"Manufacturing & Wholesale Goods"
        }
    ],
    "sg:phone":"+1 617 783 0328",
    "sg:postcode":"02131",
    "sg:province":"MA",
    "sg:tags":[
        "video",
        "disc",
        "tape"
    ],
    "wof:name":"Championship Technique Videos",
    "wof:placetype":"venue"
},
  "geometry": {"coordinates":[-71.129192,42.283634],"type":"Point"}
}