{
  "type": "Feature",
  "properties": {
    "addr:full":"418 Rantoul St Beverly MA 01915",
    "addr:housenumber":"418",
    "addr:postcode":"01915",
    "addr:street":"Rantoul St",
    "iso:country":"US",
    "sg:address":"418 Rantoul St",
    "sg:city":"Beverly",
    "sg:classifiers":[
        {
            "category":"Home & Garden",
            "subcategory":"Household Appliances",
            "type":"Retail Goods"
        }
    ],
    "sg:phone":"+1 978 927 8003",
    "sg:postcode":"01915",
    "sg:province":"MA",
    "sg:tags":[
        "cleaners",
        "vacuum"
    ],
    "sg:website":"www.beverlyvac.com",
    "wof:name":"Beverly Vac",
    "wof:placetype":"venue"
},
  "geometry": {"coordinates":[-70.881997,42.554028],"type":"Point"}
}