{
  "type": "Feature",
  "properties": {
    "addr:full":"61 Worcester St Natick MA 01760",
    "addr:housenumber":"61",
    "addr:postcode":"01760",
    "addr:street":"Worcester St",
    "iso:country":"US",
    "sg:address":"61 Worcester St",
    "sg:city":"Natick",
    "sg:classifiers":[
        {
            "category":"Restaurant",
            "type":"Food & Drink"
        }
    ],
    "sg:menulink":"http://www.allmenus.com/ma/natick/131518-quiznos-sub/menu/",
    "sg:phone":"+1 508 655 5865",
    "sg:postcode":"01760",
    "sg:province":"MA",
    "sg:tags":[
        "wrap",
        "american",
        "sandwich"
    ],
    "wof:name":"Quiznos Sub",
    "wof:placetype":"venue"
},
  "geometry": {"coordinates":[-71.32914100000001,42.304681],"type":"Point"}
}