{
  "type": "Feature",
  "properties": {
    "addr:full": "49 Emerson Rd Lexington MA 02420",
    "addr:housenumber": "49",
    "addr:postcode": "02420",
    "addr:street": "Emerson Rd",
    "iso:country": "US",
    "sg:address": "49 Emerson Rd",
    "sg:city": "Lexington",
    "sg:classifiers": [
      {
        "category": "Professional",
        "subcategory": "Management \u0026 Consulting",
        "type": "Services"
      }
    ],
    "sg:phone": "+1   ",
    "sg:postcode": "02420",
    "sg:province": "MA",
    "wof:name": "Chris Ketcios",
    "wof:placetype": "venue"
  },
  "geometry": {"coordinates":[-71.213024,42.460269],"type":"Point"}
}
