{
  "type": "Feature",
  "properties": {
    "iso:country":"US",
    "sg:address":"49 Emerson Rd",
    "sg:city":"Lexington",
    "sg:classifiers":[
        {
            "category":"Professional",
            "subcategory":"Management & Consulting",
            "type":"Services"
        }
    ],
    "sg:phone":"+1   ",
    "sg:postcode":"02420",
    "sg:province":"MA",
    "wof:name":"Chris Ketcios",
    "wof:placetype":"venue"
},
  "geometry": {"coordinates":[-71.213024,42.460269],"type":"Point"}
}