{
  "type": "Feature",
  "properties": {
    "iso:country":"US",
    "sg:address":"676 State Hwy 28",
    "sg:city":"Dennis Port",
    "sg:classifiers":[
        {
            "category":"Shopping",
            "subcategory":"Used Merchandise",
            "type":"Retail Goods"
        }
    ],
    "sg:phone":"+1 508 394 6181",
    "sg:postcode":"02639",
    "sg:province":"MA",
    "sg:tags":[
        "antique"
    ],
    "wof:name":"Howard & Howard Fine Antiques",
    "wof:placetype":"venue"
},
  "geometry": {"coordinates":[-70.12366299999999,41.668064],"type":"Point"}
}