{
  "type": "Feature",
  "properties": {
    "addr:full": "676 State Hwy 28 Dennis Port MA 02639",
    "addr:housenumber": "676",
    "addr:postcode": "02639",
    "addr:street": "State Hwy 28",
    "iso:country": "US",
    "sg:address": "676 State Hwy 28",
    "sg:city": "Dennis Port",
    "sg:classifiers": [
      {
        "category": "Shopping",
        "subcategory": "Used Merchandise",
        "type": "Retail Goods"
      }
    ],
    "sg:phone": "+1 508 394 6181",
    "sg:postcode": "02639",
    "sg:province": "MA",
    "sg:tags": [
      "antique"
    ],
    "wof:name": "Howard \u0026 Howard Fine Antiques",
    "wof:placetype": "venue"
  },
  "geometry": {"coordinates":[-70.123663,41.668064],"type":"Point"}
}
