{
  "type": "Feature",
  "properties": {
    "addr:full": "291 Commercial St Provincetown MA 02657",
    "addr:housenumber": "291",
    "addr:postcode": "02657",
    "addr:street": "Commercial St",
    "iso:country": "US",
    "sg:address": "291 Commercial St",
    "sg:city": "Provincetown",
    "sg:classifiers": [
      {
        "category": "Restaurant",
        "type": "Food \u0026 Drink"
      }
    ],
    "sg:phone": "+1 508 487 2890",
    "sg:postcode": "02657",
    "sg:province": "MA",
    "wof:name": "Alibi",
    "wof:placetype": "venue"
  },
  "geometry": {"coordinates":[-70.185806,42.051691],"type":"Point"}
}
