{
  "type": "Feature",
  "properties": {
    "iso:country":"US",
    "sg:address":"24 Hancock St",
    "sg:city":"Shrewsbury",
    "sg:classifiers":[
        {
            "category":"Shopping",
            "subcategory":"Books",
            "type":"Retail Goods"
        }
    ],
    "sg:phone":"+1   ",
    "sg:postcode":"01545",
    "sg:province":"MA",
    "wof:name":"Goodnews Bookstore Co",
    "wof:placetype":"venue"
},
  "geometry": {"coordinates":[-71.744379,42.271219],"type":"Point"}
}