{
  "type": "Feature",
  "properties": {
    "addr:full": "24 Hancock St Shrewsbury MA 01545",
    "addr:housenumber": "24",
    "addr:postcode": "01545",
    "addr:street": "Hancock St",
    "iso:country": "US",
    "sg:address": "24 Hancock St",
    "sg:city": "Shrewsbury",
    "sg:classifiers": [
      {
        "category": "Shopping",
        "subcategory": "Books",
        "type": "Retail Goods"
      }
    ],
    "sg:phone": "+1   ",
    "sg:postcode": "01545",
    "sg:province": "MA",
    "wof:name": "Goodnews Bookstore Co",
    "wof:placetype": "venue"
  },
  "geometry": {"coordinates":[-71.744379,42.271219],"type":"Point"}
}
