{
  "type": "Feature",
  "properties": {
    "addr:full": "111 Hawthorne St Chelsea MA 02150",
    "addr:housenumber": "111",
    "addr:postcode": "02150",
    "addr:street": "Hawthorne St",
    "iso:country": "US",
    "ovtr:label": "Seventh day Adventist Church, 111 Hawthorne St Chelsea MA US",
    "ovtr:similarity": 3.831089973449707,
    "sg:address": "111 Hawthorne St",
    "sg:city": "Chelsea",
    "sg:classifiers": [
      {
        "category": "Place Of Worship",
        "subcategory": "Church",
        "type": "Public Place"
      },
      {
        "category": "Place Of Worship",
        "type": "Public Place"
      }
    ],
    "sg:phone": "+1 617 884 0121",
    "sg:postcode": "02150",
    "sg:province": "MA",
    "sg:tags": [
      "churches-seventh-day",
      "adventist",
      "christian",
      "churches-advent"
    ],
    "wof:name": "Seventh Day Adventist Church Of Chelsea",
    "wof:placetype": "venue"
  },
  "geometry": {"coordinates":[-71.035208,42.390725],"type":"Point"}
}
