{
  "type": "Feature",
  "properties": {
    "iso:country":"US",
    "sg:address":"111 Hawthorne St",
    "sg:city":"Chelsea",
    "sg:classifiers":[
        {
            "category":"Place Of Worship",
            "subcategory":"Church",
            "type":"Public Place"
        },
        {
            "category":"Place Of Worship",
            "type":"Public Place"
        }
    ],
    "sg:phone":"+1 617 884 0121",
    "sg:postcode":"02150",
    "sg:province":"MA",
    "sg:tags":[
        "churches-seventh-day",
        "adventist",
        "christian",
        "churches-advent"
    ],
    "wof:name":"Seventh Day Adventist Church Of Chelsea",
    "wof:placetype":"venue"
},
  "geometry": {"coordinates":[-71.035208,42.390725],"type":"Point"}
}