{
  "type": "Feature",
  "properties": {
    "addr:full": "118 Waterhouse Rd Ste C Buzzards Bay MA 02532",
    "addr:housenumber": "118",
    "addr:postcode": "02532",
    "addr:street": "Waterhouse Rd Ste C",
    "iso:country": "US",
    "sg:address": "118 Waterhouse Rd Ste C",
    "sg:city": "Buzzards Bay",
    "sg:classifiers": [
      {
        "category": "Health Services",
        "subcategory": "Doctor",
        "type": "Services"
      }
    ],
    "sg:phone": "+1 508 743 0899",
    "sg:postcode": "02532",
    "sg:province": "MA",
    "sg:tags": [
      "practice",
      "family"
    ],
    "wof:name": "Bourne Family Medicine",
    "wof:placetype": "venue"
  },
  "geometry": {"coordinates":[-70.592697,41.736801],"type":"Point"}
}
