{
  "type": "Feature",
  "properties": {
    "addr:full": "8 Merchant's Way Middleboro MA 02346",
    "addr:housenumber": "8",
    "addr:postcode": "02346",
    "addr:street": "Merchant'S Way",
    "iso:country": "US",
    "sg:address": "8 Merchant's Way",
    "sg:city": "Middleboro",
    "sg:classifiers": [
      {
        "category": "Food \u0026 Beverages",
        "subcategory": "Groceries \u0026 Convenience Stores",
        "type": "Retail Goods"
      }
    ],
    "sg:phone": "+1 508 947 4787",
    "sg:postcode": "02346",
    "sg:province": "MA",
    "sg:tags": [
      "grocer"
    ],
    "sg:website": "www.victorysupermarkets.com",
    "wof:name": "Victory Hannaford",
    "wof:placetype": "venue"
  },
  "geometry": {"coordinates":[-70.909065,41.882897],"type":"Point"}
}
