{
  "type": "Feature",
  "properties": {
    "iso:country":"US",
    "sg:address":"155 Gore St",
    "sg:city":"Cambridge",
    "sg:classifiers":[
        {
            "category":"Shopping",
            "subcategory":"Bicycles & Sporting Goods",
            "type":"Retail Goods"
        }
    ],
    "sg:phone":"+1 617 797 8328",
    "sg:postcode":"02141",
    "sg:province":"MA",
    "wof:name":"Skaters Edge",
    "wof:placetype":"venue"
},
  "geometry": {"coordinates":[-71.085505,42.372699],"type":"Point"}
}