{
  "type": "Feature",
  "properties": {
    "iso:country":"US",
    "sg:address":"157 Grove St Ste 90",
    "sg:city":"Franklin",
    "sg:classifiers":[
        {
            "category":"Home & Garden",
            "subcategory":"Hardware",
            "type":"Retail Goods"
        }
    ],
    "sg:phone":"+1 508 528 3166",
    "sg:postcode":"02038",
    "sg:province":"MA",
    "sg:tags":[
        "wire",
        "cable-electric"
    ],
    "sg:website":"http://www.precisionconverting.com",
    "wof:name":"Hisco",
    "wof:placetype":"venue"
},
  "geometry": {"coordinates":[-71.4235,42.072189],"type":"Point"}
}