{
  "type": "Feature",
  "properties": {
    "iso:country":"US",
    "sg:address":"969 Ocean St",
    "sg:city":"Marshfield",
    "sg:classifiers":[
        {
            "category":"Autos & Motor Vehicles",
            "subcategory":"Fuel & Gas Station",
            "type":"Retail Goods"
        }
    ],
    "sg:phone":"+1 781 837 2981",
    "sg:postcode":"02050",
    "sg:province":"MA",
    "sg:tags":[
        "oil"
    ],
    "wof:name":"Marshfield Coastal Inc",
    "wof:placetype":"venue"
},
  "geometry": {"coordinates":[-70.668564,42.105979],"type":"Point"}
}