{
  "type": "Feature",
  "properties": {
    "addr:full": "3 Traffic Cir Newburyport MA 01950",
    "addr:housenumber": "3",
    "addr:postcode": "01950",
    "addr:street": "Traffic Cir",
    "iso:country": "US",
    "sg:address": "3 Traffic Cir",
    "sg:city": "Newburyport",
    "sg:classifiers": [
      {
        "category": "Restaurant",
        "type": "Food \u0026 Drink"
      },
      {
        "category": "Food \u0026 Beverages",
        "subcategory": "Bakery",
        "type": "Retail Goods"
      }
    ],
    "sg:phone": "+1 978 462 1221",
    "sg:postcode": "01950",
    "sg:province": "MA",
    "sg:tags": [
      "sandwich",
      "pizza"
    ],
    "wof:name": "Leo's House of Pizza",
    "wof:placetype": "venue"
  },
  "geometry": {"coordinates":[-70.875099,42.806198],"type":"Point"}
}
