{
  "type": "Feature",
  "properties": {
    "addr:full": "42 Mattakeesett St Pembroke MA 02359",
    "addr:housenumber": "42",
    "addr:postcode": "02359",
    "addr:street": "Mattakeesett St",
    "iso:country": "US",
    "sg:address": "42 Mattakeesett St",
    "sg:city": "Pembroke",
    "sg:classifiers": [
      {
        "category": "Social Services",
        "subcategory": "Child Care",
        "type": "Services"
      }
    ],
    "sg:phone": "+1 781 293 9794",
    "sg:postcode": "02359",
    "sg:province": "MA",
    "wof:name": "Learning Circle",
    "wof:placetype": "venue"
  },
  "geometry": {"coordinates":[-70.816357,42.066956],"type":"Point"}
}
