{
  "type": "Feature",
  "properties": {
    "iso:country":"US",
    "sg:address":"1844 Commonwealth Ave",
    "sg:city":"Auburndale",
    "sg:classifiers":[
        {
            "category":"Education",
            "subcategory":"College",
            "type":"Public Place"
        }
    ],
    "sg:phone":"+1 617 243 2000",
    "sg:postcode":"02466",
    "sg:province":"MA",
    "sg:tags":[
        "academic",
        "school"
    ],
    "wof:name":"Lasell College",
    "wof:placetype":"venue"
},
  "geometry": {"coordinates":[-71.24113699999999,42.344752],"type":"Point"}
}