{
  "type": "Feature",
  "properties": {
    "iso:country":"US",
    "sg:address":"106 N Dartmouth Mall",
    "sg:city":"North Dartmouth",
    "sg:classifiers":[
        {
            "category":"Real Estate",
            "subcategory":"Real Estate Agent",
            "type":"Services"
        }
    ],
    "sg:phone":"+1   ",
    "sg:postcode":"02747",
    "sg:province":"MA",
    "wof:name":"Ronnie Glassman Real Estate",
    "wof:placetype":"venue"
},
  "geometry": {"coordinates":[-70.993314,41.642928],"type":"Point"}
}