{
  "type": "Feature",
  "properties": {
    "addr:full": "19 Fort Hill St Hingham MA 02043",
    "addr:housenumber": "19",
    "addr:postcode": "02043",
    "addr:street": "Fort Hill St",
    "iso:country": "US",
    "sg:address": "19 Fort Hill St",
    "sg:city": "Hingham",
    "sg:classifiers": [
      {
        "category": "Banks \u0026 Credit Unions",
        "subcategory": "Bank",
        "type": "Services"
      }
    ],
    "sg:phone": "+1 781 749 2026",
    "sg:postcode": "02043",
    "sg:province": "MA",
    "sg:website": "www.hinghamfcu.org",
    "wof:name": "Hingham Federal Credit Union",
    "wof:placetype": "venue"
  },
  "geometry": {"coordinates":[-70.903437,42.236592],"type":"Point"}
}
