{
  "type": "Feature",
  "properties": {
    "iso:country":"US",
    "sg:address":"662 Boston Post Rd",
    "sg:city":"Sudbury",
    "sg:classifiers":[
        {
            "category":"Retail",
            "subcategory":"Veterinary Services",
            "type":"Services"
        }
    ],
    "sg:phone":"+1 978 443 2839",
    "sg:postcode":"01776",
    "sg:province":"MA",
    "sg:tags":[
        "clinic",
        "hospital",
        "veterinarian",
        "specialty"
    ],
    "wof:name":"Sudbury Animal Hospital",
    "wof:placetype":"venue"
},
  "geometry": {"coordinates":[-71.4426,42.360603],"type":"Point"}
}