{
  "type": "Feature",
  "properties": {
    "addr:full": "39 State St Newburyport MA 01950",
    "addr:housenumber": "39",
    "addr:postcode": "01950",
    "addr:street": "State St",
    "iso:country": "US",
    "sg:address": "39 State St",
    "sg:city": "Newburyport",
    "sg:classifiers": [
      {
        "category": "Education",
        "subcategory": "Special Training",
        "type": "Public Place"
      }
    ],
    "sg:phone": "+1 978 499 9811",
    "sg:postcode": "01950",
    "sg:province": "MA",
    "sg:tags": [
      "center"
    ],
    "wof:name": "Learning Challenge Inc",
    "wof:placetype": "venue"
  },
  "geometry": {"coordinates":[-70.870029,42.810251],"type":"Point"}
}
