{
  "type": "Feature",
  "properties": {
    "addr:full": "7 Peninsula Place Dorchester MA 02125",
    "addr:housenumber": "7",
    "addr:postcode": "02125",
    "addr:street": "Peninsula Place",
    "iso:country": "US",
    "sg:address": "7 Peninsula Place",
    "sg:city": "Dorchester",
    "sg:classifiers": [
      {
        "category": "Real Estate",
        "subcategory": "Real Estate Operator",
        "type": "Services"
      }
    ],
    "sg:phone": "+1 617 929 1928",
    "sg:postcode": "02125",
    "sg:province": "MA",
    "sg:tags": [
      "apartment"
    ],
    "wof:name": "Harbor Point Apartments",
    "wof:placetype": "venue"
  },
  "geometry": {"coordinates":[-71.044099,42.32079],"type":"Point"}
}
