{
  "type": "Feature",
  "properties": {
    "addr:full": "575 Union St Springfield ME 01109",
    "addr:housenumber": "575",
    "addr:postcode": "01109",
    "addr:street": "Union St",
    "iso:country": "US",
    "sg:address": "575 Union St",
    "sg:city": "Springfield",
    "sg:classifiers": [
      {
        "category": "Building \u0026 Trades",
        "subcategory": "Cleaning \u0026 Sanitation",
        "type": "Services"
      }
    ],
    "sg:phone": "+1 413 563 4644",
    "sg:postcode": "01109",
    "sg:province": "ME",
    "sg:tags": [
      "ventilating",
      "system"
    ],
    "wof:name": "Duct \u0026 Vent Cleaning-America",
    "wof:placetype": "venue"
  },
  "geometry": {"coordinates":[-72.569507,42.107929],"type":"Point"}
}
