{
  "type": "Feature",
  "properties": {
    "iso:country":"US",
    "sg:address":"575 Union St",
    "sg:city":"Springfield",
    "sg:classifiers":[
        {
            "category":"Building & Trades",
            "subcategory":"Cleaning & Sanitation",
            "type":"Services"
        }
    ],
    "sg:phone":"+1 413 563 4644",
    "sg:postcode":"01109",
    "sg:province":"ME",
    "sg:tags":[
        "ventilating",
        "system"
    ],
    "wof:name":"Duct & Vent Cleaning-America",
    "wof:placetype":"venue"
},
  "geometry": {"coordinates":[-72.569507,42.107929],"type":"Point"}
}