{
  "type": "Feature",
  "properties": {
    "iso:country":"US",
    "sg:address":"9 Longfellow Rd",
    "sg:city":"Wayland",
    "sg:classifiers":[
        {
            "category":"Professional",
            "subcategory":"Management & Consulting",
            "type":"Services"
        }
    ],
    "sg:phone":"+1 508 358 5640",
    "sg:postcode":"01778",
    "sg:province":"MA",
    "sg:tags":[
        "business"
    ],
    "wof:name":"Novotny Consulting",
    "wof:placetype":"venue"
},
  "geometry": {"coordinates":[-71.353864,42.369073],"type":"Point"}
}