{
  "type": "Feature",
  "properties": {
    "iso:country":"US",
    "sg:address":"169 Munsell St",
    "sg:city":"Belchertown",
    "sg:classifiers":[
        {
            "category":"Retail",
            "subcategory":"Auto Repair",
            "type":"Services"
        }
    ],
    "sg:phone":"+1 413 323 6362",
    "sg:postcode":"01007",
    "sg:province":"MA",
    "sg:tags":[
        "repairing",
        "automobile",
        "general"
    ],
    "wof:name":"Martin's Auto Repair",
    "wof:placetype":"venue"
},
  "geometry": {"coordinates":[-72.427578,42.338733],"type":"Point"}
}