{
  "type": "Feature",
  "properties": {
    "addr:full": "20 Central St South Easton MA 02375",
    "addr:housenumber": "20",
    "addr:postcode": "02375",
    "addr:street": "Central St",
    "iso:country": "US",
    "sg:address": "20 Central St",
    "sg:city": "South Easton",
    "sg:classifiers": [
      {
        "category": "Manufacturing",
        "subcategory": "Metals",
        "type": "Manufacturing \u0026 Wholesale Goods"
      }
    ],
    "sg:phone": "+1 508 230 2890",
    "sg:postcode": "02375",
    "sg:province": "MA",
    "sg:tags": [
      "fabricator",
      "sheet"
    ],
    "wof:name": "Easton Sheet Metal Co",
    "wof:placetype": "venue"
  },
  "geometry": {"coordinates":[-71.082612,42.046493],"type":"Point"}
}
