{
  "type": "Feature",
  "properties": {
    "iso:country":"US",
    "sg:address":"315 E Haverhill St",
    "sg:city":"Lawrence",
    "sg:classifiers":[
        {
            "category":"Personal",
            "subcategory":"Beauty Salon",
            "type":"Services"
        }
    ],
    "sg:phone":"+1 978 688 1133",
    "sg:postcode":"01841",
    "sg:province":"MA",
    "sg:tags":[
        "school"
    ],
    "wof:name":"Merrimack Valley School-Hair",
    "wof:placetype":"venue"
},
  "geometry": {"coordinates":[-71.142253,42.720516],"type":"Point"}
}