{
  "type": "Feature",
  "properties": {
    "addr:full":"22 Union St West Bridgewater MA 02379",
    "addr:housenumber":"22",
    "addr:postcode":"02379",
    "addr:street":"Union St",
    "iso:country":"US",
    "sg:address":"22 Union St",
    "sg:city":"West Bridgewater",
    "sg:classifiers":[
        {
            "category":"Professional",
            "subcategory":"Business Services",
            "type":"Services"
        }
    ],
    "sg:phone":"+1   ",
    "sg:postcode":"02379",
    "sg:province":"MA",
    "wof:name":"Trustees of Howard Funds",
    "wof:placetype":"venue"
},
  "geometry": {"coordinates":[-70.987859,42.02779],"type":"Point"}
}