{
  "type": "Feature",
  "properties": {
    "addr:full": "136 Elm St North Easton MA 02356",
    "addr:housenumber": "136",
    "addr:postcode": "02356",
    "addr:street": "Elm St",
    "iso:country": "US",
    "sg:address": "136 Elm St",
    "sg:city": "North Easton",
    "sg:classifiers": [
      {
        "category": "Government",
        "subcategory": "Office",
        "type": "Public Place"
      }
    ],
    "sg:phone": "+1 508 230 3305",
    "sg:postcode": "02356",
    "sg:province": "MA",
    "sg:tags": [
      "city",
      "resource",
      "human"
    ],
    "wof:name": "Council On Aging",
    "wof:placetype": "venue"
  },
  "geometry": {"coordinates":[-71.095557,42.074149],"type":"Point"}
}
