{
  "type": "Feature",
  "properties": {
    "iso:country":"US",
    "sg:address":"39 Court St",
    "sg:city":"Groton",
    "sg:classifiers":[
        {
            "category":"Organizations",
            "subcategory":"Membership Organization",
            "type":"Services"
        }
    ],
    "sg:phone":"+1 978 448 4357",
    "sg:postcode":"01450",
    "sg:province":"MA",
    "wof:name":"Fatherhood Coalition Merrimack",
    "wof:placetype":"venue"
},
  "geometry": {"coordinates":[-71.573497,42.608305],"type":"Point"}
}