{
  "type": "Feature",
  "properties": {
    "iso:country":"US",
    "sg:address":"38 Gleason St",
    "sg:city":"Dorchester",
    "sg:classifiers":[
        {
            "category":"Professional",
            "subcategory":"Detective & Security Services",
            "type":"Services"
        }
    ],
    "sg:phone":"+1 617 825 2685",
    "sg:postcode":"02121",
    "sg:province":"MA",
    "sg:tags":[
        "car",
        "private",
        "investigator"
    ],
    "wof:name":"Tyrone Foster",
    "wof:placetype":"venue"
},
  "geometry": {"coordinates":[-71.08171299999999,42.29727],"type":"Point"}
}