{
  "type": "Feature",
  "properties": {
    "addr:full": "38 Gleason St Dorchester MA 02121",
    "addr:housenumber": "38",
    "addr:postcode": "02121",
    "addr:street": "Gleason St",
    "iso:country": "US",
    "sg:address": "38 Gleason St",
    "sg:city": "Dorchester",
    "sg:classifiers": [
      {
        "category": "Professional",
        "subcategory": "Detective \u0026 Security Services",
        "type": "Services"
      }
    ],
    "sg:phone": "+1 617 825 2685",
    "sg:postcode": "02121",
    "sg:province": "MA",
    "sg:tags": [
      "car",
      "private",
      "investigator"
    ],
    "wof:name": "Tyrone Foster",
    "wof:placetype": "venue"
  },
  "geometry": {"coordinates":[-71.081713,42.29727],"type":"Point"}
}
