{
  "type": "Feature",
  "properties": {
    "addr:full":"96 Chestnut St Wakefield MA 01880",
    "addr:housenumber":"96",
    "addr:postcode":"01880",
    "addr:street":"Chestnut St",
    "iso:country":"US",
    "sg:address":"96 Chestnut St",
    "sg:city":"Wakefield",
    "sg:classifiers":[
        {
            "category":"Wholesale",
            "subcategory":"Electrical",
            "type":"Manufacturing & Wholesale Goods"
        }
    ],
    "sg:phone":"+1 781 246 0331",
    "sg:postcode":"01880",
    "sg:province":"MA",
    "sg:tags":[
        "signal",
        "traffic",
        "sign"
    ],
    "wof:name":"USA Wiring",
    "wof:placetype":"venue"
},
  "geometry": {"coordinates":[-71.083393,42.501506],"type":"Point"}
}