{
  "type": "Feature",
  "properties": {
    "iso:country":"US",
    "sg:address":"34 Rogers Rd",
    "sg:city":"Haverhill",
    "sg:classifiers":[
        {
            "category":"Wholesale",
            "subcategory":"Medical Equipment & Supplies",
            "type":"Manufacturing & Wholesale Goods"
        }
    ],
    "sg:phone":"+1 978 372 2290",
    "sg:postcode":"01835",
    "sg:province":"MA",
    "sg:tags":[
        "physician",
        "surgeon"
    ],
    "wof:name":"Inspire Medical Eqpt & Svc",
    "wof:placetype":"venue"
},
  "geometry": {"coordinates":[-71.11252500000001,42.760895],"type":"Point"}
}