{
  "type": "Feature",
  "properties": {
    "addr:full": "34 Rogers Rd Haverhill MA 01835",
    "addr:housenumber": "34",
    "addr:postcode": "01835",
    "addr:street": "Rogers Rd",
    "iso:country": "US",
    "sg:address": "34 Rogers Rd",
    "sg:city": "Haverhill",
    "sg:classifiers": [
      {
        "category": "Wholesale",
        "subcategory": "Medical Equipment \u0026 Supplies",
        "type": "Manufacturing \u0026 Wholesale Goods"
      }
    ],
    "sg:phone": "+1 978 372 2290",
    "sg:postcode": "01835",
    "sg:province": "MA",
    "sg:tags": [
      "physician",
      "surgeon"
    ],
    "wof:name": "Inspire Medical Eqpt \u0026 Svc",
    "wof:placetype": "venue"
  },
  "geometry": {"coordinates":[-71.112525,42.760895],"type":"Point"}
}
