{
  "type": "Feature",
  "properties": {
    "addr:full": "309 Boston Post Rd Wayland MA 01778",
    "addr:housenumber": "309",
    "addr:postcode": "01778",
    "addr:street": "Boston Post Rd",
    "iso:country": "US",
    "sg:address": "309 Boston Post Rd",
    "sg:city": "Wayland",
    "sg:phone": "+1 508 358 2288",
    "sg:postcode": "01778",
    "sg:province": "MA",
    "wof:name": "Water Lily",
    "wof:placetype": "venue"
  },
  "geometry": {"coordinates":[-71.367249,42.363178],"type":"Point"}
}
