{
  "type": "Feature",
  "properties": {
    "addr:full": "128 Washington St Haverhill MA 01832",
    "addr:housenumber": "128",
    "addr:postcode": "01832",
    "addr:street": "Washington St",
    "iso:country": "US",
    "sg:address": "128 Washington St",
    "sg:city": "Haverhill",
    "sg:classifiers": [
      {
        "category": "Restaurant",
        "type": "Food \u0026 Drink"
      }
    ],
    "sg:phone": "+1 978 372 3148",
    "sg:postcode": "01832",
    "sg:province": "MA",
    "sg:tags": [
      "grill",
      "bar"
    ],
    "sg:website": "http://www.bluefinngrille.com",
    "wof:name": "Grille Blue Finn",
    "wof:placetype": "venue"
  },
  "geometry": {"coordinates":[-71.085876,42.772678],"type":"Point"}
}
