{
  "type": "Feature",
  "properties": {
    "iso:country":"US",
    "sg:address":"6 Acton St",
    "sg:city":"Watertown",
    "sg:classifiers":[
        {
            "category":"Restaurant",
            "type":"Food & Drink"
        }
    ],
    "sg:phone":"+1   ",
    "sg:postcode":"02472",
    "sg:province":"MA",
    "sg:tags":[
        "eating"
    ],
    "wof:name":"Javas Brewin",
    "wof:placetype":"venue"
},
  "geometry": {"coordinates":[-71.195779,42.369462],"type":"Point"}
}