{
  "type": "Feature",
  "properties": {
    "addr:full": "129 Fisher Ave Brookline MA 02445",
    "addr:housenumber": "129",
    "addr:postcode": "02445",
    "addr:street": "Fisher Ave",
    "iso:country": "US",
    "sg:address": "129 Fisher Ave",
    "sg:city": "Brookline",
    "sg:classifiers": [
      {
        "category": "Education",
        "subcategory": "University",
        "type": "Public Place"
      }
    ],
    "sg:phone": "+1 781 245 8297",
    "sg:postcode": "02445",
    "sg:province": "MA",
    "sg:tags": [
      "college"
    ],
    "wof:name": "Newbury College",
    "wof:placetype": "venue"
  },
  "geometry": {"coordinates":[-71.141197,42.327801],"type":"Point"}
}
