{
  "type": "Feature",
  "properties": {
    "addr:full":"1 Prescott St Groton MA 01450",
    "addr:housenumber":"1",
    "addr:postcode":"01450",
    "addr:street":"Prescott St",
    "iso:country":"US",
    "sg:address":"1 Prescott St",
    "sg:city":"Groton",
    "sg:classifiers":[
        {
            "category":"Building & Trades",
            "subcategory":"Construction",
            "type":"Services"
        }
    ],
    "sg:phone":"+1   ",
    "sg:postcode":"01450",
    "sg:province":"MA",
    "sg:tags":[
        "contractor"
    ],
    "wof:name":"Tims Hydroseeding",
    "wof:placetype":"venue"
},
  "geometry": {"coordinates":[-71.54003899999999,42.594736],"type":"Point"}
}