{
  "type": "Feature",
  "properties": {
    "addr:full":"667 Boylston St Fl 5 Boston MA 02116",
    "addr:housenumber":"667;5",
    "addr:postcode":"02116",
    "addr:street":"Boylston St",
    "iso:country":"US",
    "sg:address":"667 Boylston St Fl 5",
    "sg:city":"Boston",
    "sg:classifiers":[
        {
            "category":"Professional",
            "subcategory":"Research",
            "type":"Services"
        }
    ],
    "sg:phone":"+1 617 266 1000",
    "sg:postcode":"02116",
    "sg:province":"MA",
    "sg:tags":[
        "analysis",
        "market"
    ],
    "wof:name":"Kiley & Company",
    "wof:placetype":"venue"
},
  "geometry": {"coordinates":[-71.078734,42.349702],"type":"Point"}
}