{
  "type": "Feature",
  "properties": {
    "addr:full":"1 Sajo Dr Attleboro MA 02703",
    "addr:housenumber":"1",
    "addr:postcode":"02703",
    "addr:street":"Sajo Dr",
    "iso:country":"US",
    "sg:address":"1 Sajo Dr",
    "sg:city":"Attleboro",
    "sg:classifiers":[
        {
            "category":"Arts & Performance",
            "subcategory":"Theater",
            "type":"Entertainment"
        }
    ],
    "sg:phone":"+1   ",
    "sg:postcode":"02703",
    "sg:province":"MA",
    "sg:tags":[
        "group"
    ],
    "wof:name":"Genesis Disc Jockey",
    "wof:placetype":"venue"
},
  "geometry": {"coordinates":[-71.28973499999999,41.910202],"type":"Point"}
}