{
  "type": "Feature",
  "properties": {
    "iso:country":"US",
    "sg:address":"36 Slocum St",
    "sg:city":"Acushnet",
    "sg:classifiers":[
        {
            "category":"Retail",
            "subcategory":"Auto Repair",
            "type":"Services"
        }
    ],
    "sg:phone":"+1 508 995 5375",
    "sg:postcode":"02743",
    "sg:province":"MA",
    "sg:tags":[
        "body",
        "automobile",
        "painting"
    ],
    "wof:name":"Fred's Collision Ctr",
    "wof:placetype":"venue"
},
  "geometry": {"coordinates":[-70.911659,41.679284],"type":"Point"}
}