{
  "type": "Feature",
  "properties": {
    "addr:full":"1430 Massachusetts Ave Cambridge MA 02138",
    "addr:housenumber":"1430",
    "addr:postcode":"02138",
    "addr:street":"Massachusetts Ave",
    "iso:country":"US",
    "sg:address":"1430 Massachusetts Ave",
    "sg:city":"Cambridge",
    "sg:classifiers":[
        {
            "category":"Real Estate",
            "subcategory":"Architect",
            "type":"Services"
        }
    ],
    "sg:phone":"+1 617 868 8999",
    "sg:postcode":"02138",
    "sg:province":"MA",
    "sg:website":"www.fmarchitects.com",
    "wof:name":"Fondren McGrath Architects",
    "wof:placetype":"venue"
},
  "geometry": {"coordinates":[-71.11889600000001,42.374199],"type":"Point"}
}