{
  "type": "Feature",
  "properties": {
    "addr:full":"322 Centre St Brockton MA 02302",
    "addr:housenumber":"322",
    "addr:postcode":"02302",
    "addr:street":"Centre St",
    "iso:country":"US",
    "sg:address":"322 Centre St",
    "sg:city":"Brockton",
    "sg:classifiers":[
        {
            "category":"Home & Garden",
            "subcategory":"Building Materials",
            "type":"Retail Goods"
        }
    ],
    "sg:phone":"+1 508 583 3030",
    "sg:postcode":"02302",
    "sg:province":"MA",
    "sg:tags":[
        "glass",
        "window",
        "plate"
    ],
    "wof:name":"City Glass Co",
    "wof:placetype":"venue"
},
  "geometry": {"coordinates":[-71.006221,42.083935],"type":"Point"}
}