{
  "type": "Feature",
  "properties": {
    "addr:full": "49 Bearskin Neck Rockport MA 01966",
    "addr:housenumber": "49",
    "addr:postcode": "01966",
    "addr:street": "Bearskin Neck",
    "iso:country": "US",
    "sg:address": "49 Bearskin Neck",
    "sg:city": "Rockport",
    "sg:classifiers": [
      {
        "category": "Shopping",
        "subcategory": "Jewelry",
        "type": "Retail Goods"
      }
    ],
    "sg:phone": "+1 978 546 2003",
    "sg:postcode": "01966",
    "sg:province": "MA",
    "sg:tags": [
      "jeweler"
    ],
    "wof:name": "Crown Jewels Assoc Inc",
    "wof:placetype": "venue"
  },
  "geometry": {"coordinates":[-70.614121,42.660935],"type":"Point"}
}
