{
  "type": "Feature",
  "properties": {
    "addr:full": "1796 Massachusetts Ave Cambridge MA 02140",
    "addr:housenumber": "1796",
    "addr:postcode": "02140",
    "addr:street": "Massachusetts Ave",
    "iso:country": "US",
    "sg:address": "1796 Massachusetts Ave",
    "sg:city": "Cambridge",
    "sg:classifiers": [
      {
        "category": "Restaurant",
        "type": "Food \u0026 Drink"
      }
    ],
    "sg:phone": "+1 617 868 1899",
    "sg:postcode": "02140",
    "sg:province": "MA",
    "sg:tags": [
      "cafe"
    ],
    "wof:name": "Sweetea Cafe",
    "wof:placetype": "venue"
  },
  "geometry": {"coordinates":[-71.119463,42.38559],"type":"Point"}
}
