{
  "type": "Feature",
  "properties": {
    "addr:full": "134 Hartsville New Marlboro Rd New Marlborough MA 01230",
    "addr:housenumber": "134",
    "addr:postcode": "01230",
    "addr:street": "Hartsville New Marlboro Rd",
    "iso:country": "US",
    "sg:address": "134 Hartsville New Marlboro Rd",
    "sg:city": "New Marlborough",
    "sg:classifiers": [
      {
        "category": "Restaurant",
        "type": "Food \u0026 Drink"
      }
    ],
    "sg:menulink": "http://www.allmenus.com/ma/new-marlborough/269608-the-old-inn-on-the-green/menu/",
    "sg:phone": "+1 413 229 7924",
    "sg:postcode": "01230",
    "sg:province": "MA",
    "wof:name": "The Old Inn On The Green",
    "wof:placetype": "venue"
  },
  "geometry": {"coordinates":[-73.261253,42.165028],"type":"Point"}
}
