{
  "type": "Feature",
  "properties": {
    "addr:full": "22 Wood Ave Mattapan MA 02126",
    "addr:housenumber": "22",
    "addr:postcode": "02126",
    "addr:street": "Wood Ave",
    "iso:country": "US",
    "sg:address": "22 Wood Ave",
    "sg:city": "Mattapan",
    "sg:classifiers": [
      {
        "category": "Arts \u0026 Performance",
        "subcategory": "Theater",
        "type": "Entertainment"
      }
    ],
    "sg:phone": "+1   ",
    "sg:postcode": "02126",
    "sg:province": "MA",
    "sg:tags": [
      "group"
    ],
    "wof:name": "TMJ Productions",
    "wof:placetype": "venue"
  },
  "geometry": {"coordinates":[-71.110039,42.272759],"type":"Point"}
}
