{
  "type": "Feature",
  "properties": {
    "addr:full":"55 State St Springfield MA 01103",
    "addr:housenumber":"55",
    "addr:postcode":"01103",
    "addr:street":"State St",
    "iso:country":"US",
    "sg:address":"55 State St",
    "sg:city":"Springfield",
    "sg:classifiers":[
        {
            "category":"Professional",
            "subcategory":"Lawyer & Legal Services",
            "type":"Services"
        }
    ],
    "sg:phone":"+1 413 781 4566",
    "sg:postcode":"01103",
    "sg:province":"MA",
    "sg:tags":[
        "attorney"
    ],
    "wof:name":"Ryan E Alekman Law Office",
    "wof:placetype":"venue"
},
  "geometry": {"coordinates":[-72.58815199999999,42.099808],"type":"Point"}
}