{
  "type": "Feature",
  "properties": {
    "addr:full":"2 Atlantic Avenue Boston MA 02110",
    "addr:housenumber":"2",
    "addr:postcode":"02110",
    "addr:street":"Atlantic Avenue",
    "iso:country":"US",
    "sg:address":"2 Atlantic Avenue",
    "sg:city":"Boston",
    "sg:classifiers":[
        {
            "category":"Communications",
            "subcategory":"Television Station",
            "type":"Services"
        }
    ],
    "sg:phone":"+1 617 742 9500",
    "sg:postcode":"02110",
    "sg:province":"MA",
    "wof:name":"Pilot House Associates",
    "wof:placetype":"venue"
},
  "geometry": {"coordinates":[-71.051074,42.363889],"type":"Point"}
}