{
  "type": "Feature",
  "properties": {
    "iso:country":"US",
    "sg:address":"354 Cambridge St",
    "sg:city":"Allston",
    "sg:classifiers":[
        {
            "category":"Autos & Motor Vehicles",
            "subcategory":"Auto Supplies",
            "type":"Retail Goods"
        }
    ],
    "sg:phone":"+1 617 782 1251",
    "sg:postcode":"02134",
    "sg:province":"MA",
    "sg:tags":[
        "automobile",
        "parts"
    ],
    "sg:website":"www.jackyoungco.com",
    "wof:name":"Young's Auto Supplies",
    "wof:placetype":"venue"
},
  "geometry": {"coordinates":[-71.131777,42.355931],"type":"Point"}
}