{
  "type": "Feature",
  "properties": {
    "addr:full":"5 Evelyn Way Vineyard Haven MA 02568",
    "addr:housenumber":"5",
    "addr:postcode":"02568",
    "addr:street":"Evelyn Way",
    "iso:country":"US",
    "sg:address":"5 Evelyn Way",
    "sg:city":"Vineyard Haven",
    "sg:classifiers":[
        {
            "category":"Health Services",
            "subcategory":"Hospital",
            "type":"Services"
        }
    ],
    "sg:phone":"+1 508 696 7563",
    "sg:postcode":"02568",
    "sg:province":"MA",
    "sg:tags":[
        "mental"
    ],
    "wof:name":"Daybreak Clubhouse",
    "wof:placetype":"venue"
},
  "geometry": {"coordinates":[-70.61221999999999,41.447714],"type":"Point"}
}