{
  "type": "Feature",
  "properties": {
    "addr:full":"186 Union Ave Framingham MA 01702",
    "addr:housenumber":"186",
    "addr:postcode":"01702",
    "addr:street":"Union Ave",
    "iso:country":"US",
    "sg:address":"186 Union Ave",
    "sg:city":"Framingham",
    "sg:classifiers":[
        {
            "category":"Home & Garden",
            "subcategory":"Building Materials",
            "type":"Retail Goods"
        }
    ],
    "sg:phone":"+1 508 620 6737",
    "sg:postcode":"01702",
    "sg:province":"MA",
    "sg:tags":[
        "roofing"
    ],
    "wof:name":"Weather Reps",
    "wof:placetype":"venue"
},
  "geometry": {"coordinates":[-71.41970600000001,42.282475],"type":"Point"}
}