{
  "type": "Feature",
  "properties": {
    "iso:country":"US",
    "sg:address":"55 Holman Rd",
    "sg:city":"Plymouth",
    "sg:classifiers":[
        {
            "category":"Personal",
            "type":"Services"
        },
        {
            "category":"Retail",
            "subcategory":"Storage",
            "type":"Services"
        }
    ],
    "sg:phone":"+1 866 320 6309",
    "sg:postcode":"02360",
    "sg:province":"MA",
    "sg:tags":[
        "self",
        "full",
        "commercial",
        "mover",
        "household"
    ],
    "sg:website":"http://www.unclebobs.com/stores/UB240/?source=Yellowpages.com&howheard=ISM",
    "wof:name":"Uncle Bob's Self Storage",
    "wof:placetype":"venue"
},
  "geometry": {"coordinates":[-70.661621,41.929722],"type":"Point"}
}