{
  "type": "Feature",
  "properties": {
    "iso:country":"US",
    "sg:address":"27 1st St",
    "sg:city":"Salem",
    "sg:classifiers":[
        {
            "category":"Professional",
            "subcategory":"Lawyer & Legal Services",
            "type":"Services"
        }
    ],
    "sg:phone":"+1 978 745 2565",
    "sg:postcode":"01970",
    "sg:province":"MA",
    "sg:tags":[
        "attorney"
    ],
    "wof:name":"Carmichael & Del Valle",
    "wof:placetype":"venue"
},
  "geometry": {"coordinates":[-70.91805600000001,42.501002],"type":"Point"}
}