{
  "type": "Feature",
  "properties": {
    "addr:full": "27 1st St Salem MA 01970",
    "addr:housenumber": "27",
    "addr:postcode": "01970",
    "addr:street": "1St St",
    "iso:country": "US",
    "sg:address": "27 1st St",
    "sg:city": "Salem",
    "sg:classifiers": [
      {
        "category": "Professional",
        "subcategory": "Lawyer \u0026 Legal Services",
        "type": "Services"
      }
    ],
    "sg:phone": "+1 978 745 2565",
    "sg:postcode": "01970",
    "sg:province": "MA",
    "sg:tags": [
      "attorney"
    ],
    "wof:name": "Carmichael \u0026 Del Valle",
    "wof:placetype": "venue"
  },
  "geometry": {"coordinates":[-70.918056,42.501002],"type":"Point"}
}
