{
  "type": "Feature",
  "properties": {
    "addr:full": "1 Isaac Sprague Dr Hingham MA 02043",
    "addr:housenumber": "1",
    "addr:postcode": "02043",
    "addr:street": "Isaac Sprague Dr",
    "iso:country": "US",
    "sg:address": "1 Isaac Sprague Dr",
    "sg:city": "Hingham",
    "sg:classifiers": [
      {
        "category": "Professional",
        "subcategory": "Management \u0026 Consulting",
        "type": "Services"
      }
    ],
    "sg:phone": "+1   ",
    "sg:postcode": "02043",
    "sg:province": "MA",
    "sg:tags": [
      "business"
    ],
    "wof:name": "Lgb Consulting Inc",
    "wof:placetype": "venue"
  },
  "geometry": {"coordinates":[-70.91135,42.230368],"type":"Point"}
}
