{
  "type": "Feature",
  "properties": {
    "iso:country":"US",
    "sg:address":"266 Main St",
    "sg:city":"Medfield",
    "sg:classifiers":[
        {
            "category":"Travel",
            "subcategory":"Travel Agent",
            "type":"Entertainment"
        }
    ],
    "sg:phone":"+1 508 359 4181",
    "sg:postcode":"02052",
    "sg:province":"MA",
    "sg:tags":[
        "agency",
        "bureau"
    ],
    "wof:name":"Jean's Travel Agency",
    "wof:placetype":"venue"
},
  "geometry": {"coordinates":[-71.29174,42.192657],"type":"Point"}
}