{
  "type": "Feature",
  "properties": {
    "addr:full":"10 Canal Park Cambridge MA 02141",
    "addr:housenumber":"10",
    "addr:postcode":"02141",
    "addr:street":"Canal Park",
    "iso:country":"US",
    "sg:address":"10 Canal Park",
    "sg:city":"Cambridge",
    "sg:classifiers":[
        {
            "category":"Banks & Credit Unions",
            "subcategory":"Investment Brokerage",
            "type":"Services"
        }
    ],
    "sg:phone":"+1 617 494 0421",
    "sg:postcode":"02141",
    "sg:province":"MA",
    "sg:tags":[
        "advisory",
        "financial"
    ],
    "wof:name":"Ten Canal Park",
    "wof:placetype":"venue"
},
  "geometry": {"coordinates":[-71.07489099999999,42.369783],"type":"Point"}
}