{
  "type": "Feature",
  "properties": {
    "iso:country":"US",
    "sg:address":"255 S Royalston Rd",
    "sg:city":"Royalston",
    "sg:classifiers":[
        {
            "category":"Real Estate",
            "subcategory":"Real Estate Agent",
            "type":"Services"
        }
    ],
    "sg:phone":"+1 978 249 4725",
    "sg:postcode":"01368",
    "sg:province":"MA",
    "sg:tags":[
        "cooperative"
    ],
    "wof:name":"Millers River Ed Co-Op",
    "wof:placetype":"venue"
},
  "geometry": {"coordinates":[-72.15458700000001,42.64042],"type":"Point"}
}