{
  "type": "Feature",
  "properties": {
    "iso:country":"US",
    "sg:address":"162 Booth St",
    "sg:city":"Ludlow",
    "sg:classifiers":[
        {
            "category":"Retail",
            "subcategory":"Auto Repair",
            "type":"Services"
        }
    ],
    "sg:phone":"+1 413 583 5126",
    "sg:postcode":"01056",
    "sg:province":"MA",
    "sg:tags":[
        "body",
        "automobile",
        "painting"
    ],
    "wof:name":"Austin Auto Body",
    "wof:placetype":"venue"
},
  "geometry": {"coordinates":[-72.458663,42.193259],"type":"Point"}
}