{
  "type": "Feature",
  "properties": {
    "addr:full": "15 Washington Ave Waltham MA 02453",
    "addr:housenumber": "15",
    "addr:postcode": "02453",
    "addr:street": "Washington Ave",
    "iso:country": "US",
    "sg:address": "15 Washington Ave",
    "sg:city": "Waltham",
    "sg:classifiers": [
      {
        "category": "Building \u0026 Trades",
        "subcategory": "Construction",
        "type": "Services"
      }
    ],
    "sg:phone": "+1   ",
    "sg:postcode": "02453",
    "sg:province": "MA",
    "sg:tags": [
      "house"
    ],
    "wof:name": "N Leblanc Construction",
    "wof:placetype": "venue"
  },
  "geometry": {"coordinates":[-71.237659,42.362759],"type":"Point"}
}
