{
  "type": "Feature",
  "properties": {
    "addr:full":"193 Salem St Boston MA 02113",
    "addr:housenumber":"193",
    "addr:postcode":"02113",
    "addr:street":"Salem St",
    "iso:country":"US",
    "sg:address":"193 Salem St",
    "sg:city":"Boston",
    "sg:classifiers":[
        {
            "category":"Organizations",
            "subcategory":"Religious Organization",
            "type":"Services"
        }
    ],
    "sg:phone":"+1 617 523 6676",
    "sg:postcode":"02113",
    "sg:province":"MA",
    "sg:tags":[
        "landmark",
        "building",
        "historical",
        "church"
    ],
    "sg:website":"www.oldnorth.com",
    "wof:name":"Old North Church",
    "wof:placetype":"venue"
},
  "geometry": {"coordinates":[-71.054604,42.366901],"type":"Point"}
}