{
  "type": "Feature",
  "properties": {
    "addr:city": "Boston",
    "addr:full": "193 Salem Street Boston, Ma 02113",
    "addr:house_number": "193",
    "addr:housenumber": "193",
    "addr:phone": "+1 617-523-6676",
    "addr:postcode": "02113",
    "addr:road": "Salem Street",
    "addr:state": "MA",
    "addr:street": "Salem St",
    "iso:country": "US",
    "sg:address": "193 Salem St",
    "sg:city": "Boston",
    "sg:classifiers": [
      {
        "category": "Organizations",
        "subcategory": "Religious Organization",
        "type": "Services"
      }
    ],
    "sg:phone": "+1 617 523 6676",
    "sg:postcode": "02113",
    "sg:province": "MA",
    "sg:tags": [
      "landmark",
      "building",
      "historical",
      "church"
    ],
    "sg:website": "www.oldnorth.com",
    "wof:airports": [
      102530741
    ],
    "wof:name": "Old North Church Museum",
    "wof:placetype": "venue"
  },
  "geometry": {"coordinates":[-71.05451,42.36649],"type":"Point"}
}
