{
  "type": "Feature",
  "properties": {
    "iso:country":"US",
    "sg:address":"32 Oxford St",
    "sg:city":"Boston",
    "sg:classifiers":[
        {
            "category":"Manufacturing",
            "subcategory":"Printing",
            "type":"Manufacturing & Wholesale Goods"
        }
    ],
    "sg:phone":"+1 617 968 8019",
    "sg:postcode":"02111",
    "sg:province":"MA",
    "sg:tags":[
        "newspaper"
    ],
    "sg:website":"www.epochtimes.com",
    "wof:name":"Epoch Times Boston-Chinese",
    "wof:placetype":"venue"
},
  "geometry": {"coordinates":[-71.06062900000001,42.352456],"type":"Point"}
}