{
  "type": "Feature",
  "properties": {
    "addr:full": "32 Oxford St Boston MA 02111",
    "addr:housenumber": "32",
    "addr:postcode": "02111",
    "addr:street": "Oxford St",
    "iso:country": "US",
    "sg:address": "32 Oxford St",
    "sg:city": "Boston",
    "sg:classifiers": [
      {
        "category": "Manufacturing",
        "subcategory": "Printing",
        "type": "Manufacturing \u0026 Wholesale Goods"
      }
    ],
    "sg:phone": "+1 617 968 8019",
    "sg:postcode": "02111",
    "sg:province": "MA",
    "sg:tags": [
      "newspaper"
    ],
    "sg:website": "www.epochtimes.com",
    "wof:name": "Epoch Times Boston-Chinese",
    "wof:placetype": "venue"
  },
  "geometry": {"coordinates":[-71.060629,42.352456],"type":"Point"}
}
