{
  "type": "Feature",
  "properties": {
    "addr:full": "85 Copeland Dr Mansfield MA 02048",
    "addr:housenumber": "85",
    "addr:postcode": "02048",
    "addr:street": "Copeland Dr",
    "iso:country": "US",
    "sg:address": "85 Copeland Dr",
    "sg:city": "Mansfield",
    "sg:classifiers": [
      {
        "category": "Real Estate",
        "subcategory": "Real Estate Agent",
        "type": "Services"
      }
    ],
    "sg:phone": "+1 508 339 3654",
    "sg:postcode": "02048",
    "sg:province": "MA",
    "wof:name": "Brugliera Real Estate",
    "wof:placetype": "venue"
  },
  "geometry": {"coordinates":[-71.228573,42.029566],"type":"Point"}
}
