{
  "type": "Feature",
  "properties": {
    "addr:full": "14 Strong Ave Northampton MA 01060",
    "addr:housenumber": "14",
    "addr:postcode": "01060",
    "addr:street": "Strong Ave",
    "iso:country": "US",
    "sg:address": "14 Strong Ave",
    "sg:city": "Northampton",
    "sg:classifiers": [
      {
        "category": "Structure",
        "subcategory": "Office Building",
        "type": "Public Place"
      }
    ],
    "sg:phone": "+1 413 584 1885",
    "sg:postcode": "01060",
    "sg:province": "MA",
    "sg:tags": [
      "park"
    ],
    "wof:name": "Pedal To Properties",
    "wof:placetype": "venue"
  },
  "geometry": {"coordinates":[-72.628386,42.319895],"type":"Point"}
}
