{
  "type": "Feature",
  "properties": {
    "iso:country":"US",
    "sg:address":"181 Great Rd",
    "sg:city":"Bedford",
    "sg:classifiers":[
        {
            "category":"Retail",
            "subcategory":"Auto Repair",
            "type":"Services"
        }
    ],
    "sg:phone":"+1 781 275 8484",
    "sg:postcode":"01730",
    "sg:province":"MA",
    "sg:tags":[
        "repairing",
        "automobile"
    ],
    "wof:name":"Bedford Auto Repair",
    "wof:placetype":"venue"
},
  "geometry": {"coordinates":[-71.27139099999999,42.489049],"type":"Point"}
}