{
  "type": "Feature",
  "properties": {
    "addr:full": "32 Bank St Pittsfield MA 01267",
    "addr:housenumber": "32",
    "addr:postcode": "01267",
    "addr:street": "Bank St",
    "iso:country": "US",
    "sg:address": "32 Bank St",
    "sg:city": "Pittsfield",
    "sg:classifiers": [
      {
        "category": "Home \u0026 Garden",
        "subcategory": "Carpets \u0026 Floor Coverings",
        "type": "Retail Goods"
      }
    ],
    "sg:phone": "+1 413 443 4747",
    "sg:postcode": "01267",
    "sg:province": "MA",
    "sg:tags": [
      "dealer",
      "rug"
    ],
    "wof:name": "Haddad's Rug Co",
    "wof:placetype": "venue"
  },
  "geometry": {"coordinates":[-73.205181,42.710867],"type":"Point"}
}
