{
  "type": "Feature",
  "properties": {
    "iso:country":"US",
    "sg:address":"32 Bank St",
    "sg:city":"Pittsfield",
    "sg:classifiers":[
        {
            "category":"Home & Garden",
            "subcategory":"Carpets & Floor Coverings",
            "type":"Retail Goods"
        }
    ],
    "sg:phone":"+1 413 443 4747",
    "sg:postcode":"01267",
    "sg:province":"MA",
    "sg:tags":[
        "dealer",
        "rug"
    ],
    "wof:name":"Haddad's Rug Co",
    "wof:placetype":"venue"
},
  "geometry": {"coordinates":[-73.205181,42.710867],"type":"Point"}
}