{
  "type": "Feature",
  "properties": {
    "iso:country":"US",
    "sg:address":"10 Springdale Ave",
    "sg:city":"Dover",
    "sg:classifiers":[
        {
            "category":"Professional",
            "subcategory":"Lawyer & Legal Services",
            "type":"Services"
        }
    ],
    "sg:phone":"+1 508 785 1303",
    "sg:postcode":"02030",
    "sg:province":"MA",
    "sg:tags":[
        "attorney"
    ],
    "wof:name":"Jack Donoghue",
    "wof:placetype":"venue"
},
  "geometry": {"coordinates":[-71.28111,42.24463],"type":"Point"}
}