{
  "type": "Feature",
  "properties": {
    "addr:full": "10 Springdale Ave Dover MA 02030",
    "addr:housenumber": "10",
    "addr:postcode": "02030",
    "addr:street": "Springdale Ave",
    "iso:country": "US",
    "sg:address": "10 Springdale Ave",
    "sg:city": "Dover",
    "sg:classifiers": [
      {
        "category": "Professional",
        "subcategory": "Lawyer \u0026 Legal Services",
        "type": "Services"
      }
    ],
    "sg:phone": "+1 508 785 1303",
    "sg:postcode": "02030",
    "sg:province": "MA",
    "sg:tags": [
      "attorney"
    ],
    "wof:name": "Jack Donoghue",
    "wof:placetype": "venue"
  },
  "geometry": {"coordinates":[-71.28111,42.24463],"type":"Point"}
}
