{
  "type": "Feature",
  "properties": {
    "addr:full":"190 Littleton Rd Westford MA 01886",
    "addr:housenumber":"190",
    "addr:postcode":"01886",
    "addr:street":"Littleton Rd",
    "iso:country":"US",
    "sg:address":"190 Littleton Rd",
    "sg:city":"Westford",
    "sg:classifiers":[
        {
            "category":"Personal",
            "subcategory":"Nail Salon",
            "type":"Services"
        }
    ],
    "sg:phone":"+1 978 692 1291",
    "sg:postcode":"01886",
    "sg:province":"MA",
    "wof:name":"Tropical Tanning & Nails",
    "wof:placetype":"venue"
},
  "geometry": {"coordinates":[-71.42483,42.564864],"type":"Point"}
}