{
  "type": "Feature",
  "properties": {
    "addr:full": "270 Border Rd Concord MA 01742",
    "addr:housenumber": "270",
    "addr:postcode": "01742",
    "addr:street": "Border Rd",
    "iso:country": "US",
    "sg:address": "270 Border Rd",
    "sg:city": "Concord",
    "sg:classifiers": [
      {
        "category": "Education",
        "subcategory": "School",
        "type": "Public Place"
      }
    ],
    "sg:phone": "+1   ",
    "sg:postcode": "01742",
    "sg:province": "MA",
    "wof:name": "Retirees School Volunteer",
    "wof:placetype": "venue"
  },
  "geometry": {"coordinates":[-71.420618,42.434956],"type":"Point"}
}
