{
  "type": "Feature",
  "properties": {
    "iso:country":"US",
    "sg:address":"19 Grove St",
    "sg:city":"Methuen",
    "sg:classifiers":[
        {
            "category":"Professional",
            "type":"Services"
        }
    ],
    "sg:phone":"+1 978 975 3405",
    "sg:postcode":"01844",
    "sg:province":"MA",
    "sg:tags":[
        "establishment"
    ],
    "wof:name":"World Class",
    "wof:placetype":"venue"
},
  "geometry": {"coordinates":[-71.189094,42.723827],"type":"Point"}
}