{
  "type": "Feature",
  "properties": {
    "iso:country":"US",
    "sg:address":"262 Swansea Mall Dr",
    "sg:city":"Swansea",
    "sg:classifiers":[
        {
            "category":"Shopping",
            "subcategory":"Music",
            "type":"Retail Goods"
        }
    ],
    "sg:phone":"+1 508 673 2616",
    "sg:postcode":"02777",
    "sg:province":"MA",
    "sg:tags":[
        "compact",
        "record",
        "disc",
        "tape"
    ],
    "wof:name":"Fye",
    "wof:placetype":"venue"
},
  "geometry": {"coordinates":[-71.220046,41.760038],"type":"Point"}
}