{
  "type": "Feature",
  "properties": {
    "iso:country":"US",
    "sg:address":"1390 Tucker Rd",
    "sg:city":"North Dartmouth",
    "sg:classifiers":[
        {
            "category":"Education",
            "subcategory":"School",
            "type":"Public Place"
        }
    ],
    "sg:phone":"+1 508 999 3146",
    "sg:postcode":"02747",
    "sg:province":"MA",
    "wof:name":"Gidley Elementary School",
    "wof:placetype":"venue"
},
  "geometry": {"coordinates":[-70.982635,41.637621],"type":"Point"}
}