{
  "type": "Feature",
  "properties": {
    "addr:full": "17 Long Leaf Rd Boylston MA 01505",
    "addr:housenumber": "17",
    "addr:postcode": "01505",
    "addr:street": "Long Leaf Rd",
    "iso:country": "US",
    "sg:address": "17 Long Leaf Rd",
    "sg:city": "Boylston",
    "sg:classifiers": [
      {
        "category": "Professional",
        "subcategory": "Business Services",
        "type": "Services"
      }
    ],
    "sg:phone": "+1 508 869 6622",
    "sg:postcode": "01505",
    "sg:province": "MA",
    "sg:website": "www.neetevents.com",
    "wof:name": "Neet Events By Anita Thomas",
    "wof:placetype": "venue"
  },
  "geometry": {"coordinates":[-71.740052,42.321785],"type":"Point"}
}
