{
  "type": "Feature",
  "properties": {
    "addr:full": "8 Mount Auburn St Watertown MA 02472",
    "addr:housenumber": "8",
    "addr:postcode": "02472",
    "addr:street": "Mount Auburn St",
    "iso:country": "US",
    "sg:address": "8 Mount Auburn St",
    "sg:city": "Watertown",
    "sg:classifiers": [
      {
        "category": "Shopping",
        "subcategory": "Clothing, Apparel, \u0026 Fashions",
        "type": "Retail Goods"
      }
    ],
    "sg:phone": "+1 617 924 6194",
    "sg:postcode": "02472",
    "sg:province": "MA",
    "sg:tags": [
      "dressmaker"
    ],
    "wof:name": "House Of Fashion Irine Mischko",
    "wof:placetype": "venue"
  },
  "geometry": {"coordinates":[-71.184338,42.365224],"type":"Point"}
}
