{
  "type": "Feature",
  "properties": {
    "iso:country":"US",
    "sg:address":"8 Mount Auburn St",
    "sg:city":"Watertown",
    "sg:classifiers":[
        {
            "category":"Shopping",
            "subcategory":"Clothing, Apparel, & Fashions",
            "type":"Retail Goods"
        }
    ],
    "sg:phone":"+1 617 924 6194",
    "sg:postcode":"02472",
    "sg:province":"MA",
    "sg:tags":[
        "dressmaker"
    ],
    "wof:name":"House Of Fashion Irine Mischko",
    "wof:placetype":"venue"
},
  "geometry": {"coordinates":[-71.184338,42.365224],"type":"Point"}
}