{
  "type": "Feature",
  "properties": {
    "addr:full":"49 Symphony Rd Boston MA 02115",
    "addr:housenumber":"49",
    "addr:postcode":"02115",
    "addr:street":"Symphony Rd",
    "iso:country":"US",
    "sg:address":"49 Symphony Rd",
    "sg:city":"Boston",
    "sg:classifiers":[
        {
            "category":"Professional",
            "subcategory":"Management & Consulting",
            "type":"Services"
        }
    ],
    "sg:phone":"+1   ",
    "sg:postcode":"02115",
    "sg:province":"MA",
    "sg:tags":[
        "business"
    ],
    "wof:name":"Devine Trudell Consulting LLC",
    "wof:placetype":"venue"
},
  "geometry": {"coordinates":[-71.088612,42.342993],"type":"Point"}
}