{
  "type": "Feature",
  "properties": {
    "addr:full":"226 Essex St Lawrence MA 01840",
    "addr:housenumber":"226",
    "addr:postcode":"01840",
    "addr:street":"Essex St",
    "iso:country":"US",
    "sg:address":"226 Essex St",
    "sg:city":"Lawrence",
    "sg:classifiers":[
        {
            "category":"Shopping",
            "subcategory":"Shoes",
            "type":"Retail Goods"
        }
    ],
    "sg:phone":"+1 978 681 7641",
    "sg:postcode":"01840",
    "sg:province":"MA",
    "wof:name":"Kenner Shoe Store Major League",
    "wof:placetype":"venue"
},
  "geometry": {"coordinates":[-71.15858299999999,42.70766],"type":"Point"}
}