{
  "type": "Feature",
  "properties": {
    "iso:country":"US",
    "sg:address":"51 Florence St",
    "sg:city":"Franklin",
    "sg:classifiers":[
        {
            "category":"Organizations",
            "subcategory":"Community Association",
            "type":"Services"
        }
    ],
    "sg:phone":"+1 508 528 2573",
    "sg:postcode":"02038",
    "sg:province":"MA",
    "sg:tags":[
        "club"
    ],
    "wof:name":"Franklin Rod & Gun Club Inc",
    "wof:placetype":"venue"
},
  "geometry": {"coordinates":[-71.379409,42.061668],"type":"Point"}
}