{
  "type": "Feature",
  "properties": {
    "addr:full":"529 Park Ave Worcester MA 01603",
    "addr:housenumber":"529",
    "addr:postcode":"01603",
    "addr:street":"Park Ave",
    "iso:country":"US",
    "sg:address":"529 Park Ave",
    "sg:city":"Worcester",
    "sg:classifiers":[
        {
            "category":"Home & Garden",
            "subcategory":"Home Furnishings",
            "type":"Retail Goods"
        }
    ],
    "sg:phone":"+1 508 799 7533",
    "sg:postcode":"01603",
    "sg:province":"MA",
    "sg:tags":[
        "curtain",
        "made",
        "drapery"
    ],
    "wof:name":"Anderson's Window Fashions",
    "wof:placetype":"venue"
},
  "geometry": {"coordinates":[-71.82793100000001,42.252826],"type":"Point"}
}