{
  "type": "Feature",
  "properties": {
    "addr:full":"7 Elkins Street Boston MA 02127",
    "addr:housenumber":"7",
    "addr:postcode":"02127",
    "addr:street":"Elkins Street",
    "iso:country":"US",
    "sg:address":"7 Elkins Street",
    "sg:city":"Boston",
    "sg:classifiers":[
        {
            "category":"Education",
            "subcategory":"School",
            "type":"Public Place"
        }
    ],
    "sg:phone":"+1 617 268 4695",
    "sg:postcode":"02127",
    "sg:province":"MA",
    "wof:name":"Uphams Corner Charter School",
    "wof:placetype":"venue"
},
  "geometry": {"coordinates":[-71.0369,42.33931],"type":"Point"}
}