{
  "type": "Feature",
  "properties": {
    "addr:full": "21 Mc Grath Hwy Quincy MA 02169",
    "addr:housenumber": "21",
    "addr:postcode": "02169",
    "addr:street": "Mc Grath Hwy",
    "iso:country": "US",
    "sg:address": "21 Mc Grath Hwy",
    "sg:city": "Quincy",
    "sg:classifiers": [
      {
        "category": "Professional",
        "subcategory": "Lawyer \u0026 Legal Services",
        "type": "Services"
      }
    ],
    "sg:phone": "+1 617 479 5200",
    "sg:postcode": "02169",
    "sg:province": "MA",
    "sg:tags": [
      "attorney"
    ],
    "wof:name": "Tracy \u0026 Doocey",
    "wof:placetype": "venue"
  },
  "geometry": {"coordinates":[-70.9981,42.250743],"type":"Point"}
}
