{
  "type": "Feature",
  "properties": {
    "addr:full":"198 Andover St North Andover MA 01845",
    "addr:housenumber":"198",
    "addr:postcode":"01845",
    "addr:street":"Andover St",
    "iso:country":"US",
    "sg:address":"198 Andover St",
    "sg:city":"North Andover",
    "sg:classifiers":[
        {
            "category":"Professional",
            "subcategory":"Accounting & Tax Preparation",
            "type":"Services"
        }
    ],
    "sg:phone":"+1 978 686 7651",
    "sg:postcode":"01845",
    "sg:province":"MA",
    "sg:tags":[
        "accountant"
    ],
    "wof:name":"Henry & Co",
    "wof:placetype":"venue"
},
  "geometry": {"coordinates":[-71.119499,42.680216],"type":"Point"}
}