{
  "type": "Feature",
  "properties": {
    "addr:full":"22 Preston St Worcester MA 01610",
    "addr:housenumber":"22",
    "addr:postcode":"01610",
    "addr:street":"Preston St",
    "iso:country":"US",
    "sg:address":"22 Preston St",
    "sg:city":"Worcester",
    "sg:classifiers":[
        {
            "category":"Building & Trades",
            "subcategory":"Landscaping Services",
            "type":"Services"
        }
    ],
    "sg:phone":"+1   ",
    "sg:postcode":"01610",
    "sg:province":"MA",
    "wof:name":"R & J Landscape Construction",
    "wof:placetype":"venue"
},
  "geometry": {"coordinates":[-71.811313,42.258466],"type":"Point"}
}