{
  "type": "Feature",
  "properties": {
    "addr:full": "16 Sunset Rd Norton MA 02766",
    "addr:housenumber": "16",
    "addr:postcode": "02766",
    "addr:street": "Sunset Rd",
    "iso:country": "US",
    "sg:address": "16 Sunset Rd",
    "sg:city": "Norton",
    "sg:classifiers": [
      {
        "category": "Building \u0026 Trades",
        "subcategory": "Construction",
        "type": "Services"
      }
    ],
    "sg:phone": "+1 508 285 7377",
    "sg:postcode": "02766",
    "sg:province": "MA",
    "sg:tags": [
      "resurfacing",
      "floor",
      "laying",
      "refinishing",
      "contractor"
    ],
    "wof:name": "North Brook Flooring Service",
    "wof:placetype": "venue"
  },
  "geometry": {"coordinates":[-71.192926,41.986802],"type":"Point"}
}
