{
  "type": "Feature",
  "properties": {
    "iso:country":"US",
    "sg:address":"16 Sunset Rd",
    "sg:city":"Norton",
    "sg:classifiers":[
        {
            "category":"Building & Trades",
            "subcategory":"Construction",
            "type":"Services"
        }
    ],
    "sg:phone":"+1 508 285 7377",
    "sg:postcode":"02766",
    "sg:province":"MA",
    "sg:tags":[
        "resurfacing",
        "floor",
        "laying",
        "refinishing",
        "contractor"
    ],
    "wof:name":"North Brook Flooring Service",
    "wof:placetype":"venue"
},
  "geometry": {"coordinates":[-71.192926,41.986802],"type":"Point"}
}