{
  "type": "Feature",
  "properties": {
    "iso:country":"US",
    "sg:address":"500 Pleasant St",
    "sg:city":"Canton",
    "sg:classifiers":[
        {
            "category":"Organizations",
            "subcategory":"Community Association",
            "type":"Services"
        }
    ],
    "sg:phone":"+1 781 828 9730",
    "sg:postcode":"02021",
    "sg:province":"MA",
    "sg:tags":[
        "fraternal"
    ],
    "wof:name":"Knights Of Columbus",
    "wof:placetype":"venue"
},
  "geometry": {"coordinates":[-71.131331,42.160185],"type":"Point"}
}