{
  "type": "Feature",
  "properties": {
    "iso:country":"US",
    "sg:address":"71 1st Ave",
    "sg:city":"Charlestown",
    "sg:classifiers":[
        {
            "category":"Wholesale",
            "subcategory":"Vending Machines",
            "type":"Manufacturing & Wholesale Goods"
        }
    ],
    "sg:phone":"+1   ",
    "sg:postcode":"02129",
    "sg:province":"MA",
    "sg:tags":[
        "operator"
    ],
    "wof:name":"Canteen Food & Vending",
    "wof:placetype":"venue"
},
  "geometry": {"coordinates":[-71.054221,42.374885],"type":"Point"}
}