{
  "type": "Feature",
  "properties": {
    "iso:country":"US",
    "sg:address":"252 Bridge St",
    "sg:city":"Northampton",
    "sg:classifiers":[
        {
            "category":"Autos & Motor Vehicles",
            "subcategory":"Auto Supplies",
            "type":"Retail Goods"
        }
    ],
    "sg:phone":"+1 413 584 9244",
    "sg:postcode":"01060",
    "sg:province":"MA",
    "sg:tags":[
        "tire"
    ],
    "wof:name":"Duffy Tire Svc",
    "wof:placetype":"venue"
},
  "geometry": {"coordinates":[-72.62451799999999,42.328457],"type":"Point"}
}