{
  "type": "Feature",
  "properties": {
    "addr:full": "252 Bridge St Northampton MA 01060",
    "addr:housenumber": "252",
    "addr:postcode": "01060",
    "addr:street": "Bridge St",
    "iso:country": "US",
    "sg:address": "252 Bridge St",
    "sg:city": "Northampton",
    "sg:classifiers": [
      {
        "category": "Autos \u0026 Motor Vehicles",
        "subcategory": "Auto Supplies",
        "type": "Retail Goods"
      }
    ],
    "sg:phone": "+1 413 584 9244",
    "sg:postcode": "01060",
    "sg:province": "MA",
    "sg:tags": [
      "tire"
    ],
    "wof:name": "Duffy Tire Svc",
    "wof:placetype": "venue"
  },
  "geometry": {"coordinates":[-72.624518,42.328457],"type":"Point"}
}
