{
  "type": "Feature",
  "properties": {
    "addr:full":"383 Main St Woburn MA 01801",
    "addr:housenumber":"383",
    "addr:postcode":"01801",
    "addr:street":"Main St",
    "iso:country":"US",
    "sg:address":"383 Main St",
    "sg:city":"Woburn",
    "sg:classifiers":[
        {
            "category":"Restaurant",
            "type":"Food & Drink"
        }
    ],
    "sg:phone":"+1 781 933 9888",
    "sg:postcode":"01801",
    "sg:province":"MA",
    "sg:tags":[
        "thai",
        "vietnamese"
    ],
    "sg:website":"www.greenbasilwoburn.com",
    "wof:name":"Green Basil",
    "wof:placetype":"venue"
},
  "geometry": {"coordinates":[-71.15191299999999,42.479813],"type":"Point"}
}