{
  "type": "Feature",
  "properties": {
    "iso:country":"US",
    "sg:address":"578 Tremont St",
    "sg:city":"Boston",
    "sg:classifiers":[
        {
            "category":"Restaurant",
            "type":"Food & Drink"
        }
    ],
    "sg:phone":"+1 617 859 4805",
    "sg:postcode":"02118",
    "sg:province":"MA",
    "sg:tags":[
        "indian"
    ],
    "sg:website":"www.melaboston.com",
    "wof:name":"Mela",
    "wof:placetype":"venue"
},
  "geometry": {"coordinates":[-71.07266799999999,42.343417],"type":"Point"}
}