{
  "type": "Feature",
  "properties": {
    "addr:full": "578 Tremont St Boston MA 02118",
    "addr:housenumber": "578",
    "addr:postcode": "02118",
    "addr:street": "Tremont St",
    "iso:country": "US",
    "sg:address": "578 Tremont St",
    "sg:city": "Boston",
    "sg:classifiers": [
      {
        "category": "Restaurant",
        "type": "Food \u0026 Drink"
      }
    ],
    "sg:phone": "+1 617 859 4805",
    "sg:postcode": "02118",
    "sg:province": "MA",
    "sg:tags": [
      "indian"
    ],
    "sg:website": "www.melaboston.com",
    "wof:name": "Mela",
    "wof:placetype": "venue"
  },
  "geometry": {"coordinates":[-71.072668,42.343417],"type":"Point"}
}
