{
  "type": "Feature",
  "properties": {
    "addr:full":"104 McCarthy Rd Granville MA 01034",
    "addr:housenumber":"104",
    "addr:postcode":"01034",
    "addr:street":"Mccarthy Rd",
    "iso:country":"US",
    "sg:address":"104 McCarthy Rd",
    "sg:city":"Granville",
    "sg:classifiers":[
        {
            "category":"Farming",
            "subcategory":"Farm",
            "type":"Manufacturing & Wholesale Goods"
        }
    ],
    "sg:phone":"+1   ",
    "sg:postcode":"01034",
    "sg:province":"MA",
    "sg:tags":[
        "crop",
        "general"
    ],
    "wof:name":"Equine Farm and Garden Pdts",
    "wof:placetype":"venue"
},
  "geometry": {"coordinates":[-72.895233,42.041337],"type":"Point"}
}