{
  "type": "Feature",
  "properties": {
    "iso:country":"US",
    "sg:address":"437 Whittenton St",
    "sg:city":"Taunton",
    "sg:classifiers":[
        {
            "category":"Building & Trades",
            "subcategory":"Electrical",
            "type":"Services"
        }
    ],
    "sg:phone":"+1 508 821 5574",
    "sg:postcode":"02780",
    "sg:province":"MA",
    "sg:tags":[
        "electrician"
    ],
    "wof:name":"Easton Group Inc",
    "wof:placetype":"venue"
},
  "geometry": {"coordinates":[-71.10508900000001,41.923249],"type":"Point"}
}