{
  "type": "Feature",
  "properties": {
    "addr:full": "437 Whittenton St Taunton MA 02780",
    "addr:housenumber": "437",
    "addr:postcode": "02780",
    "addr:street": "Whittenton St",
    "iso:country": "US",
    "sg:address": "437 Whittenton St",
    "sg:city": "Taunton",
    "sg:classifiers": [
      {
        "category": "Building \u0026 Trades",
        "subcategory": "Electrical",
        "type": "Services"
      }
    ],
    "sg:phone": "+1 508 821 5574",
    "sg:postcode": "02780",
    "sg:province": "MA",
    "sg:tags": [
      "electrician"
    ],
    "wof:name": "Easton Group Inc",
    "wof:placetype": "venue"
  },
  "geometry": {"coordinates":[-71.105089,41.923249],"type":"Point"}
}
