{
  "type": "Feature",
  "properties": {
    "addr:full":"32 Astor St Lynn MA 01905",
    "addr:housenumber":"32",
    "addr:postcode":"01905",
    "addr:street":"Astor St",
    "iso:country":"US",
    "sg:address":"32 Astor St",
    "sg:city":"Lynn",
    "sg:classifiers":[
        {
            "category":"Building & Trades",
            "subcategory":"Plumbing",
            "type":"Services"
        }
    ],
    "sg:phone":"+1 781 593 1100",
    "sg:postcode":"01905",
    "sg:province":"MA",
    "sg:tags":[
        "conditioning",
        "air",
        "system",
        "contractor"
    ],
    "wof:name":"Tab Engineering",
    "wof:placetype":"venue"
},
  "geometry": {"coordinates":[-70.961378,42.459673],"type":"Point"}
}