{
  "type": "Feature",
  "properties": {
    "addr:full":"4 Brookside Cir Mashpee MA 02649",
    "addr:housenumber":"4",
    "addr:postcode":"02649",
    "addr:street":"Brookside Cir",
    "iso:country":"US",
    "sg:address":"4 Brookside Cir",
    "sg:city":"Mashpee",
    "sg:classifiers":[
        {
            "category":"Building & Trades",
            "subcategory":"Construction",
            "type":"Services"
        }
    ],
    "sg:phone":"+1   ",
    "sg:postcode":"02649",
    "sg:province":"MA",
    "sg:tags":[
        "hanging",
        "contractor"
    ],
    "wof:name":"Cofran Painting Co",
    "wof:placetype":"venue"
},
  "geometry": {"coordinates":[-70.503063,41.581916],"type":"Point"}
}