{
  "type": "Feature",
  "properties": {
    "iso:country":"US",
    "sg:address":"374 Congress St",
    "sg:city":"Boston",
    "sg:classifiers":[
        {
            "category":"Real Estate",
            "subcategory":"Architect",
            "type":"Services"
        }
    ],
    "sg:phone":"+1 617 670 0265",
    "sg:postcode":"02210",
    "sg:province":"MA",
    "wof:name":"Elizabeth Whittaker Archtctr",
    "wof:placetype":"venue"
},
  "geometry": {"coordinates":[-71.04715299999999,42.349554],"type":"Point"}
}