{
  "type": "Feature",
  "properties": {
    "addr:full": "69 Lafayette St Salem MA 01970",
    "addr:housenumber": "69",
    "addr:postcode": "01970",
    "addr:street": "Lafayette St",
    "iso:country": "US",
    "sg:address": "69 Lafayette St",
    "sg:city": "Salem",
    "sg:classifiers": [
      {
        "category": "Real Estate",
        "subcategory": "Architect",
        "type": "Services"
      }
    ],
    "sg:phone": "+1 978 744 5354",
    "sg:postcode": "01970",
    "sg:province": "MA",
    "wof:name": "H H Morant \u0026 Co",
    "wof:placetype": "venue"
  },
  "geometry": {"coordinates":[-70.893416,42.519526],"type":"Point"}
}
