{
  "type": "Feature",
  "properties": {
    "addr:full":"28 South St Hingham MA 02043",
    "addr:housenumber":"28",
    "addr:postcode":"02043",
    "addr:street":"South St",
    "iso:country":"US",
    "sg:address":"28 South St",
    "sg:city":"Hingham",
    "sg:classifiers":[
        {
            "category":"Shopping",
            "subcategory":"Gifts & Souvenirs",
            "type":"Retail Goods"
        }
    ],
    "sg:phone":"+1 781 749 6437",
    "sg:postcode":"02043",
    "sg:province":"MA",
    "sg:tags":[
        "shop"
    ],
    "wof:name":"Treasures In The Square",
    "wof:placetype":"venue"
},
  "geometry": {"coordinates":[-70.889167,42.242084],"type":"Point"}
}