{
  "type": "Feature",
  "properties": {
    "iso:country":"US",
    "sg:address":"29 Duggan Dr",
    "sg:city":"Framingham",
    "sg:classifiers":[
        {
            "category":"Wholesale",
            "subcategory":"Computers",
            "type":"Manufacturing & Wholesale Goods"
        }
    ],
    "sg:phone":"+1   ",
    "sg:postcode":"01702",
    "sg:province":"MA",
    "wof:name":"Orion DSA Group",
    "wof:placetype":"venue"
},
  "geometry": {"coordinates":[-71.45013,42.275714],"type":"Point"}
}