{
  "type": "Feature",
  "properties": {
    "addr:full": "308 Tosca Dr Stoughton MA 02072",
    "addr:housenumber": "308",
    "addr:postcode": "02072",
    "addr:street": "Tosca Dr",
    "iso:country": "US",
    "sg:address": "308 Tosca Dr",
    "sg:city": "Stoughton",
    "sg:classifiers": [
      {
        "category": "Wholesale",
        "subcategory": "Computers",
        "type": "Manufacturing \u0026 Wholesale Goods"
      }
    ],
    "sg:phone": "+1 781 297 3552",
    "sg:postcode": "02072",
    "sg:province": "MA",
    "wof:name": "S Pk Group Inc - CLOSED",
    "wof:placetype": "venue"
  },
  "geometry": {"coordinates":[-71.124199,42.137501],"type":"Point"}
}
