{
  "type": "Feature",
  "properties": {
    "iso:country":"US",
    "sg:address":"94 Pleasant St",
    "sg:city":"Arlington",
    "sg:classifiers":[
        {
            "category":"Arts & Performance",
            "subcategory":"Theater",
            "type":"Entertainment"
        }
    ],
    "sg:phone":"+1 781 646 0770",
    "sg:postcode":"02476",
    "sg:province":"MA",
    "sg:tags":[
        "musician"
    ],
    "wof:name":"Kelly Sylvia",
    "wof:placetype":"venue"
},
  "geometry": {"coordinates":[-71.156105,42.413162],"type":"Point"}
}