{
  "type": "Feature",
  "properties": {
    "addr:full": "1 Design Center Pl Boston MA 02210",
    "addr:postcode": "02210",
    "addr:street": "Center Pl",
    "iso:country": "US",
    "sg:address": "1 Design Center Pl",
    "sg:city": "Boston",
    "sg:classifiers": [
      {
        "category": "Wholesale",
        "subcategory": "Home Furnishings",
        "type": "Manufacturing \u0026 Wholesale Goods"
      },
      {
        "category": "Home \u0026 Garden",
        "subcategory": "Building Materials",
        "type": "Retail Goods"
      },
      {
        "category": "Home \u0026 Garden",
        "subcategory": "Furniture",
        "type": "Retail Goods"
      }
    ],
    "sg:phone": "+1 617 451 1412",
    "sg:postcode": "02210",
    "sg:province": "MA",
    "sg:tags": [
      "blind",
      "fixture",
      "equipment",
      "lighting",
      "shade",
      "store"
    ],
    "wof:name": "McGuire Company the",
    "wof:placetype": "venue"
  },
  "geometry": {"coordinates":[-71.042503,42.345901],"type":"Point"}
}
