{
  "type": "Feature",
  "properties": {
    "addr:full":"636 State Rd Westport MA 02790",
    "addr:housenumber":"636",
    "addr:postcode":"02790",
    "addr:street":"State Rd",
    "iso:country":"US",
    "sg:address":"636 State Rd",
    "sg:city":"Westport",
    "sg:classifiers":[
        {
            "category":"Home & Garden",
            "subcategory":"Furniture",
            "type":"Retail Goods"
        }
    ],
    "sg:phone":"+1 508 678 7070",
    "sg:postcode":"02790",
    "sg:province":"MA",
    "sg:tags":[
        "equipment",
        "kitchen",
        "cabinet"
    ],
    "wof:name":"Affordable Kitchens",
    "wof:placetype":"venue"
},
  "geometry": {"coordinates":[-71.08147,41.659554],"type":"Point"}
}