{
  "type": "Feature",
  "properties": {
    "iso:country":"US",
    "sg:address":"20 Madison Ave",
    "sg:city":"Winthrop",
    "sg:classifiers":[
        {
            "category":"Manufacturing",
            "subcategory":"Tools & Machinery",
            "type":"Manufacturing & Wholesale Goods"
        }
    ],
    "sg:phone":"+1 617 846 4423",
    "sg:postcode":"02152",
    "sg:province":"MA",
    "sg:tags":[
        "model",
        "maker",
        "sculptor"
    ],
    "wof:name":"Curci Models",
    "wof:placetype":"venue"
},
  "geometry": {"coordinates":[-70.98332000000001,42.376195],"type":"Point"}
}