{
  "type": "Feature",
  "properties": {
    "iso:country":"US",
    "sg:address":"6 Bowdoin St",
    "sg:city":"Boston",
    "sg:classifiers":[
        {
            "category":"Real Estate",
            "subcategory":"Real Estate Agent",
            "type":"Services"
        }
    ],
    "sg:phone":"+1 617 716 0240",
    "sg:postcode":"02108",
    "sg:province":"MA",
    "wof:name":"Marsh Properties",
    "wof:placetype":"venue"
},
  "geometry": {"coordinates":[-71.062797,42.359634],"type":"Point"}
}