{
  "type": "Feature",
  "properties": {
    "addr:full": "1176 Granby Rd Chicopee MA 01020",
    "addr:housenumber": "1176",
    "addr:postcode": "01020",
    "addr:street": "Granby Rd",
    "iso:country": "US",
    "ovtr:label": "CVS, 1176 Granby Rd Chicopee MA US",
    "ovtr:similarity": 1.9855400323867798,
    "sg:address": "1176 Granby Rd",
    "sg:city": "Chicopee",
    "sg:classifiers": [
      {
        "category": "Shopping",
        "subcategory": "Pharmacy",
        "type": "Retail Goods"
      }
    ],
    "sg:phone": "+1   ",
    "sg:postcode": "01020",
    "sg:province": "MA",
    "wof:name": "CVS",
    "wof:placetype": "venue"
  },
  "geometry": {"coordinates":[-72.587816,42.17376],"type":"Point"}
}
