{
  "type": "Feature",
  "properties": {
    "addr:full": "112 Water Street Lbby Boston MA 02109",
    "addr:housenumber": "112",
    "addr:postcode": "02109",
    "addr:street": "Water Street",
    "iso:country": "US",
    "sg:address": "112 Water Street Lbby",
    "sg:city": "Boston",
    "sg:classifiers": [
      {
        "category": "Professional",
        "subcategory": "Lawyer \u0026 Legal Services",
        "type": "Services"
      }
    ],
    "sg:phone": "+1 617 523 1750",
    "sg:postcode": "02109",
    "sg:province": "MA",
    "wof:name": "Powell Michael J Atty",
    "wof:placetype": "venue"
  },
  "geometry": {"coordinates":[-71.054728,42.35815],"type":"Point"}
}
