{
  "type": "Feature",
  "properties": {
    "addr:full": "6 Falmouth Rd Mashpee MA 02649",
    "addr:housenumber": "6",
    "addr:postcode": "02649",
    "addr:street": "Falmouth Rd",
    "iso:country": "US",
    "sg:address": "6 Falmouth Rd",
    "sg:city": "Mashpee",
    "sg:classifiers": [
      {
        "category": "Travel",
        "subcategory": "Hotels \u0026 Motels",
        "type": "Entertainment"
      }
    ],
    "sg:phone": "+1 508 428 6433",
    "sg:postcode": "02649",
    "sg:province": "MA",
    "wof:name": "Santuit Inn",
    "wof:placetype": "venue"
  },
  "geometry": {"coordinates":[-70.456629,41.634865],"type":"Point"}
}
