{
  "type": "Feature",
  "properties": {
    "iso:country":"US",
    "sg:address":"6 Falmouth Rd",
    "sg:city":"Mashpee",
    "sg:classifiers":[
        {
            "category":"Travel",
            "subcategory":"Hotels & Motels",
            "type":"Entertainment"
        }
    ],
    "sg:phone":"+1 508 428 6433",
    "sg:postcode":"02649",
    "sg:province":"MA",
    "wof:name":"Santuit Inn",
    "wof:placetype":"venue"
},
  "geometry": {"coordinates":[-70.45662900000001,41.634865],"type":"Point"}
}