{
  "type": "Feature",
  "properties": {
    "iso:country":"US",
    "sg:address":"70 Andover St",
    "sg:city":"Peabody",
    "sg:classifiers":[
        {
            "category":"Personal",
            "subcategory":"Beauty Salon",
            "type":"Services"
        }
    ],
    "sg:phone":"+1   ",
    "sg:postcode":"01960",
    "sg:province":"MA",
    "sg:tags":[
        "shop"
    ],
    "wof:name":"Beauty Corner",
    "wof:placetype":"venue"
},
  "geometry": {"coordinates":[-70.934836,42.5373],"type":"Point"}
}