{
  "type": "Feature",
  "properties": {
    "iso:country":"US",
    "sg:address":"13 Mount Vernon Ave",
    "sg:city":"Braintree",
    "sg:classifiers":[
        {
            "category":"Building & Trades",
            "subcategory":"Equipment Rental",
            "type":"Services"
        }
    ],
    "sg:phone":"+1 781 843 7327",
    "sg:postcode":"02184",
    "sg:province":"MA",
    "sg:tags":[
        "wheel",
        "chair"
    ],
    "wof:name":"Apex Medical Products",
    "wof:placetype":"venue"
},
  "geometry": {"coordinates":[-71.00792199999999,42.213112],"type":"Point"}
}