{
  "type": "Feature",
  "properties": {
    "addr:full": "13 Mount Vernon Ave Braintree MA 02184",
    "addr:housenumber": "13",
    "addr:postcode": "02184",
    "addr:street": "Mount Vernon Ave",
    "iso:country": "US",
    "sg:address": "13 Mount Vernon Ave",
    "sg:city": "Braintree",
    "sg:classifiers": [
      {
        "category": "Building \u0026 Trades",
        "subcategory": "Equipment Rental",
        "type": "Services"
      }
    ],
    "sg:phone": "+1 781 843 7327",
    "sg:postcode": "02184",
    "sg:province": "MA",
    "sg:tags": [
      "wheel",
      "chair"
    ],
    "wof:name": "Apex Medical Products",
    "wof:placetype": "venue"
  },
  "geometry": {"coordinates":[-71.007922,42.213112],"type":"Point"}
}
