{
  "type": "Feature",
  "properties": {
    "iso:country":"US",
    "sg:address":"25 Bridge St",
    "sg:city":"Lowell",
    "sg:classifiers":[
        {
            "category":"Restaurant",
            "type":"Food & Drink"
        }
    ],
    "sg:phone":"+1 978 453 9499",
    "sg:postcode":"01852",
    "sg:province":"MA",
    "sg:tags":[
        "caterer"
    ],
    "wof:name":"Lenzi's Catering Svc",
    "wof:placetype":"venue"
},
  "geometry": {"coordinates":[-71.306793,42.646257],"type":"Point"}
}