{
  "type": "Feature",
  "properties": {
    "iso:country":"US",
    "sg:address":"85 Broad St",
    "sg:city":"Bridgewater",
    "sg:classifiers":[
        {
            "category":"Personal",
            "type":"Services"
        }
    ],
    "sg:phone":"+1 508 697 4180",
    "sg:postcode":"02324",
    "sg:province":"MA",
    "sg:tags":[
        "electrolysis"
    ],
    "wof:name":"Beverly Ensher",
    "wof:placetype":"venue"
},
  "geometry": {"coordinates":[-70.97449400000001,41.992649],"type":"Point"}
}