{
  "type": "Feature",
  "properties": {
    "addr:full": "8 Partridge Hill Rd Weston MA 02493",
    "addr:housenumber": "8",
    "addr:postcode": "02493",
    "addr:street": "Partridge Hill Rd",
    "iso:country": "US",
    "sg:address": "8 Partridge Hill Rd",
    "sg:city": "Weston",
    "sg:classifiers": [
      {
        "category": "Building \u0026 Trades",
        "subcategory": "Construction",
        "type": "Services"
      }
    ],
    "sg:phone": "+1   ",
    "sg:postcode": "02493",
    "sg:province": "MA",
    "sg:tags": [
      "carpentry",
      "contractor"
    ],
    "wof:name": "Kest Inc",
    "wof:placetype": "venue"
  },
  "geometry": {"coordinates":[-71.301155,42.382559],"type":"Point"}
}
