{
  "type": "Feature",
  "properties": {
    "iso:country":"US",
    "sg:address":"8 Partridge Hill Rd",
    "sg:city":"Weston",
    "sg:classifiers":[
        {
            "category":"Building & Trades",
            "subcategory":"Construction",
            "type":"Services"
        }
    ],
    "sg:phone":"+1   ",
    "sg:postcode":"02493",
    "sg:province":"MA",
    "sg:tags":[
        "carpentry",
        "contractor"
    ],
    "wof:name":"Kest Inc",
    "wof:placetype":"venue"
},
  "geometry": {"coordinates":[-71.30115499999999,42.382559],"type":"Point"}
}