{
  "type": "Feature",
  "properties": {
    "addr:full":"1401 Gorham St Lowell MA 01852",
    "addr:housenumber":"1401",
    "addr:postcode":"01852",
    "addr:street":"Gorham St",
    "iso:country":"US",
    "sg:address":"1401 Gorham St",
    "sg:city":"Lowell",
    "sg:classifiers":[
        {
            "category":"Autos & Motor Vehicles",
            "subcategory":"Fuel & Gas Station",
            "type":"Retail Goods"
        }
    ],
    "sg:phone":"+1 978 937 8186",
    "sg:postcode":"01852",
    "sg:province":"MA",
    "sg:tags":[
        "oil"
    ],
    "wof:name":"Gasoline Merchants Inc",
    "wof:placetype":"venue"
},
  "geometry": {"coordinates":[-71.303811,42.616167],"type":"Point"}
}