{
  "type": "Feature",
  "properties": {
    "addr:full":"300 Jubilee Dr Peabody MA 01960",
    "addr:housenumber":"300",
    "addr:postcode":"01960",
    "addr:street":"Jubilee Dr",
    "iso:country":"US",
    "sg:address":"300 Jubilee Dr",
    "sg:city":"Peabody",
    "sg:classifiers":[
        {
            "category":"Manufacturing",
            "subcategory":"Electronics",
            "type":"Manufacturing & Wholesale Goods"
        }
    ],
    "sg:phone":"+1 978 538 5000",
    "sg:postcode":"01960",
    "sg:province":"MA",
    "sg:tags":[
        "high",
        "fidelity",
        "stereophonic"
    ],
    "sg:website":"www.bostonacoustics.com",
    "wof:name":"Boston Acoustics Inc",
    "wof:placetype":"venue"
},
  "geometry": {"coordinates":[-70.975988,42.521195],"type":"Point"}
}