{
  "type": "Feature",
  "properties": {
    "iso:country":"US",
    "sg:address":"141 Washington St",
    "sg:city":"Canton",
    "sg:classifiers":[
        {
            "category":"Wholesale",
            "subcategory":"Medical Equipment & Supplies",
            "type":"Manufacturing & Wholesale Goods"
        }
    ],
    "sg:phone":"+1 508 660 3907",
    "sg:postcode":"02021",
    "sg:province":"MA",
    "sg:tags":[
        "hospital"
    ],
    "wof:name":"Langford IC Systems Inc",
    "wof:placetype":"venue"
},
  "geometry": {"coordinates":[-71.148696,42.141272],"type":"Point"}
}