{
  "type": "Feature",
  "properties": {
    "addr:full": "141 Washington St Canton MA 02021",
    "addr:housenumber": "141",
    "addr:postcode": "02021",
    "addr:street": "Washington St",
    "iso:country": "US",
    "sg:address": "141 Washington St",
    "sg:city": "Canton",
    "sg:classifiers": [
      {
        "category": "Wholesale",
        "subcategory": "Medical Equipment \u0026 Supplies",
        "type": "Manufacturing \u0026 Wholesale Goods"
      }
    ],
    "sg:phone": "+1 508 660 3907",
    "sg:postcode": "02021",
    "sg:province": "MA",
    "sg:tags": [
      "hospital"
    ],
    "wof:name": "Langford IC Systems Inc",
    "wof:placetype": "venue"
  },
  "geometry": {"coordinates":[-71.148696,42.141272],"type":"Point"}
}
