{
  "type": "Feature",
  "properties": {
    "iso:country":"US",
    "sg:address":"1645 Blue Hill Ave",
    "sg:city":"Mattapan",
    "sg:classifiers":[
        {
            "category":"Shopping",
            "subcategory":"Music",
            "type":"Retail Goods"
        }
    ],
    "sg:phone":"+1 617 296 3345",
    "sg:postcode":"02126",
    "sg:province":"MA",
    "sg:tags":[
        "compact",
        "record",
        "disc",
        "tape"
    ],
    "wof:name":"Mattapan Music",
    "wof:placetype":"venue"
},
  "geometry": {"coordinates":[-71.093951,42.267957],"type":"Point"}
}