{
  "type": "Feature",
  "properties": {
    "addr:full":"185 Squire Rd Ste 1 Revere MA 02151",
    "addr:housenumber":"185",
    "addr:postcode":"02151",
    "addr:street":"Squire Rd Ste 1",
    "iso:country":"US",
    "sg:address":"185 Squire Rd Ste 1",
    "sg:city":"Revere",
    "sg:classifiers":[
        {
            "category":"Professional",
            "subcategory":"Business Services",
            "type":"Services"
        },
        {
            "category":"Government",
            "subcategory":"Post Office",
            "type":"Public Place"
        }
    ],
    "sg:phone":"+1 781 284 2928",
    "sg:postcode":"02151",
    "sg:province":"MA",
    "sg:tags":[
        "delivery",
        "messenger",
        "courier"
    ],
    "wof:name":"Harbor Express Inc",
    "wof:placetype":"venue"
},
  "geometry": {"coordinates":[-71.01028599999999,42.42429],"type":"Point"}
}