{
  "type": "Feature",
  "properties": {
    "addr:full":"184 W Main St Norton MA 02766",
    "addr:housenumber":"184",
    "addr:postcode":"02766",
    "addr:street":"W Main St",
    "iso:country":"US",
    "sg:address":"184 W Main St",
    "sg:city":"Norton",
    "sg:classifiers":[
        {
            "category":"Bars & Pubs",
            "type":"Food & Drink"
        },
        {
            "category":"Food & Beverages",
            "subcategory":"Liquor & Beverages",
            "type":"Retail Goods"
        }
    ],
    "sg:phone":"+1 774 430 3424",
    "sg:postcode":"02766",
    "sg:province":"MA",
    "sg:tags":[
        "beer",
        "spirit",
        "wine"
    ],
    "sg:website":"www.trinitynorton.com",
    "wof:name":"Trinity Bar & Restaurant",
    "wof:placetype":"venue"
},
  "geometry": {"coordinates":[-71.207493,41.957787],"type":"Point"}
}