{
  "type": "Feature",
  "properties": {
    "iso:country":"US",
    "sg:address":"584 Columbia Rd",
    "sg:city":"Dorchester",
    "sg:classifiers":[
        {
            "category":"Organizations",
            "subcategory":"Religious Organization",
            "type":"Services"
        }
    ],
    "sg:phone":"+1 617 436 8051",
    "sg:postcode":"02125",
    "sg:province":"MA",
    "sg:tags":[
        "church"
    ],
    "wof:name":"Life Changing Evangelistic",
    "wof:placetype":"venue"
},
  "geometry": {"coordinates":[-71.065578,42.316818],"type":"Point"}
}