{
  "type": "Feature",
  "properties": {
    "iso:country":"US",
    "sg:address":"635 Washington St",
    "sg:city":"Canton",
    "sg:classifiers":[
        {
            "category":"Food & Beverages",
            "subcategory":"Bakery",
            "type":"Retail Goods"
        }
    ],
    "sg:phone":"+1 781 828 6420",
    "sg:postcode":"02021",
    "sg:province":"MA",
    "sg:tags":[
        "baker"
    ],
    "wof:name":"Sunrise Bakery & Cafe",
    "wof:placetype":"venue"
},
  "geometry": {"coordinates":[-71.14591900000001,42.153949],"type":"Point"}
}