{
  "type": "Feature",
  "properties": {
    "addr:full": "635 Washington St Canton MA 02021",
    "addr:housenumber": "635",
    "addr:postcode": "02021",
    "addr:street": "Washington St",
    "iso:country": "US",
    "sg:address": "635 Washington St",
    "sg:city": "Canton",
    "sg:classifiers": [
      {
        "category": "Food \u0026 Beverages",
        "subcategory": "Bakery",
        "type": "Retail Goods"
      }
    ],
    "sg:phone": "+1 781 828 6420",
    "sg:postcode": "02021",
    "sg:province": "MA",
    "sg:tags": [
      "baker"
    ],
    "wof:name": "Sunrise Bakery \u0026 Cafe",
    "wof:placetype": "venue"
  },
  "geometry": {"coordinates":[-71.145919,42.153949],"type":"Point"}
}
