{
  "type": "Feature",
  "properties": {
    "addr:full": "1035 Main St Housatonic MA 01236",
    "addr:housenumber": "1035",
    "addr:postcode": "01236",
    "addr:street": "Main St",
    "iso:country": "US",
    "sg:address": "1035 Main St",
    "sg:city": "Housatonic",
    "sg:classifiers": [
      {
        "category": "Retail",
        "subcategory": "Auto Repair",
        "type": "Services"
      }
    ],
    "sg:phone": "+1 413 274 6078",
    "sg:postcode": "01236",
    "sg:province": "MA",
    "sg:tags": [
      "body",
      "automobile",
      "painting",
      "repairing"
    ],
    "wof:name": "Johns Body Shop",
    "wof:placetype": "venue"
  },
  "geometry": {"coordinates":[-73.371434,42.253512],"type":"Point"}
}
