{
  "type": "Feature",
  "properties": {
    "iso:country":"US",
    "sg:address":"16 East Main St",
    "sg:city":"West Yarmouth",
    "sg:classifiers":[
        {
            "category":"Donuts",
            "subcategory":"None",
            "type":"Food & Drink"
        }
    ],
    "sg:phone":"+1 508 862 0124",
    "sg:postcode":"02673",
    "sg:province":"MA",
    "sg:website":"www.dunkindonuts.com",
    "wof:name":"Dunkin Donuts",
    "wof:placetype":"venue"
},
  "geometry": {"coordinates":[-70.26951,41.657443],"type":"Point"}
}