{
  "type": "Feature",
  "properties": {
    "iso:country":"US",
    "sg:address":"553 Cross St",
    "sg:city":"Malden",
    "sg:classifiers":[
        {
            "category":"Professional",
            "subcategory":"Computer Services",
            "type":"Services"
        }
    ],
    "sg:phone":"+1   ",
    "sg:postcode":"02148",
    "sg:province":"MA",
    "sg:tags":[
        "datum"
    ],
    "wof:name":"Sheppard & Company",
    "wof:placetype":"venue"
},
  "geometry": {"coordinates":[-71.055137,42.428098],"type":"Point"}
}