{
  "type": "Feature",
  "properties": {
    "iso:country":"US",
    "sg:address":"60 Magazine St",
    "sg:city":"Cambridge",
    "sg:classifiers":[
        {
            "category":"Professional",
            "type":"Services"
        }
    ],
    "sg:phone":"+1 617 661 1914",
    "sg:postcode":"02139",
    "sg:province":"MA",
    "sg:tags":[
        "establishment"
    ],
    "wof:name":"AAAA B & B Boston & Cambridge",
    "wof:placetype":"venue"
},
  "geometry": {"coordinates":[-71.10796499999999,42.361937],"type":"Point"}
}