{
  "type": "Feature",
  "properties": {
    "addr:full": "60 Magazine St Cambridge MA 02139",
    "addr:housenumber": "60",
    "addr:postcode": "02139",
    "addr:street": "Magazine St",
    "iso:country": "US",
    "sg:address": "60 Magazine St",
    "sg:city": "Cambridge",
    "sg:classifiers": [
      {
        "category": "Professional",
        "type": "Services"
      }
    ],
    "sg:phone": "+1 617 661 1914",
    "sg:postcode": "02139",
    "sg:province": "MA",
    "sg:tags": [
      "establishment"
    ],
    "wof:name": "AAAA B \u0026 B Boston \u0026 Cambridge",
    "wof:placetype": "venue"
  },
  "geometry": {"coordinates":[-71.107965,42.361937],"type":"Point"}
}
