{
  "type": "Feature",
  "properties": {
    "addr:full":"429 Brookline Ave Boston MA 02215",
    "addr:housenumber":"429",
    "addr:postcode":"02215",
    "addr:street":"Brookline Ave",
    "iso:country":"US",
    "sg:address":"429 Brookline Ave",
    "sg:city":"Boston",
    "sg:classifiers":[
        {
            "category":"Shopping",
            "subcategory":"Pharmacy",
            "type":"Retail Goods"
        }
    ],
    "sg:phone":"+1 617 232 7506",
    "sg:postcode":"02215",
    "sg:province":"MA",
    "sg:tags":[
        "drugstore"
    ],
    "sg:website":"www.walgreens.com",
    "wof:name":"Walgreen Drug Stores",
    "wof:placetype":"venue"
},
  "geometry": {"coordinates":[-71.107975,42.338449],"type":"Point"}
}