{
  "type": "Feature",
  "properties": {
    "addr:full": "441 E Main St Westfield MA 01085",
    "addr:housenumber": "441",
    "addr:postcode": "01085",
    "addr:street": "E Main St",
    "iso:country": "US",
    "sg:address": "441 E Main St",
    "sg:city": "Westfield",
    "sg:classifiers": [
      {
        "category": "Restaurant",
        "type": "Food \u0026 Drink"
      }
    ],
    "sg:menulink": "http://www.allmenus.com/ma/westfield/84789-applebees/menu/",
    "sg:phone": "+1 413 564 0343",
    "sg:postcode": "01085",
    "sg:province": "MA",
    "sg:tags": [
      "burger",
      "american",
      "sandwich",
      "soup"
    ],
    "wof:name": "Applebee's",
    "wof:placetype": "venue"
  },
  "geometry": {"coordinates":[-72.721672,42.112847],"type":"Point"}
}
