{
  "type": "Feature",
  "properties": {
    "iso:country":"US",
    "sg:address":"30 N Hadley Rd",
    "sg:city":"Amherst",
    "sg:classifiers":[
        {
            "category":"Professional",
            "subcategory":"Management & Consulting",
            "type":"Services"
        }
    ],
    "sg:phone":"+1 413 549 4803",
    "sg:postcode":"01002",
    "sg:province":"MA",
    "sg:tags":[
        "consultant",
        "financing"
    ],
    "wof:name":"Levi Gots Inc",
    "wof:placetype":"venue"
},
  "geometry": {"coordinates":[-72.52763400000001,42.38393],"type":"Point"}
}