{
  "type": "Feature",
  "properties": {
    "addr:full": "30 N Hadley Rd Amherst MA 01002",
    "addr:housenumber": "30",
    "addr:postcode": "01002",
    "addr:street": "N Hadley Rd",
    "iso:country": "US",
    "sg:address": "30 N Hadley Rd",
    "sg:city": "Amherst",
    "sg:classifiers": [
      {
        "category": "Professional",
        "subcategory": "Management \u0026 Consulting",
        "type": "Services"
      }
    ],
    "sg:phone": "+1 413 549 4803",
    "sg:postcode": "01002",
    "sg:province": "MA",
    "sg:tags": [
      "consultant",
      "financing"
    ],
    "wof:name": "Levi Gots Inc",
    "wof:placetype": "venue"
  },
  "geometry": {"coordinates":[-72.527634,42.38393],"type":"Point"}
}
