{
  "type": "Feature",
  "properties": {
    "addr:full": "6 New England Executive Park Burlington MA 01803",
    "addr:housenumber": "6",
    "addr:postcode": "01803",
    "addr:street": "New England Executive Park",
    "iso:country": "US",
    "sg:address": "6 New England Executive Park",
    "sg:city": "Burlington",
    "sg:classifiers": [
      {
        "category": "Manufacturing",
        "subcategory": "Electronics",
        "type": "Manufacturing \u0026 Wholesale Goods"
      }
    ],
    "sg:phone": "+1 781 272 4263",
    "sg:postcode": "01803",
    "sg:province": "MA",
    "sg:tags": [
      "equipment",
      "electronic",
      "supply"
    ],
    "wof:name": "Western Digital Corp",
    "wof:placetype": "venue"
  },
  "geometry": {"coordinates":[-71.211683,42.485483],"type":"Point"}
}
