{
  "type": "Feature",
  "properties": {
    "addr:full":"66 Jefferson St North Attleboro MA 02760",
    "addr:housenumber":"66",
    "addr:postcode":"02760",
    "addr:street":"Jefferson St",
    "iso:country":"US",
    "sg:address":"66 Jefferson St",
    "sg:city":"North Attleboro",
    "sg:classifiers":[
        {
            "category":"Building & Trades",
            "subcategory":"Construction",
            "type":"Services"
        }
    ],
    "sg:phone":"+1   ",
    "sg:postcode":"02760",
    "sg:province":"MA",
    "sg:tags":[
        "contractor"
    ],
    "wof:name":"Black Diamond Contractors",
    "wof:placetype":"venue"
},
  "geometry": {"coordinates":[-71.329424,41.972504],"type":"Point"}
}