{
  "type": "Feature",
  "properties": {
    "iso:country":"US",
    "sg:address":"94 Bow Street",
    "sg:city":"Lexington",
    "sg:classifiers":[
        {
            "category":"Building & Trades",
            "subcategory":"Plumbing",
            "type":"Services"
        }
    ],
    "sg:phone":"+1 781 861 6085",
    "sg:postcode":"02420",
    "sg:province":"MA",
    "wof:name":"Pierro Wm G Plumbing & Heating",
    "wof:placetype":"venue"
},
  "geometry": {"coordinates":[-71.192346,42.43066],"type":"Point"}
}