{
  "type": "Feature",
  "properties": {
    "addr:full": "423 Coggeshall St New Bedford MA 02746",
    "addr:housenumber": "423",
    "addr:postcode": "02746",
    "addr:street": "Coggeshall St",
    "iso:country": "US",
    "sg:address": "423 Coggeshall St",
    "sg:city": "New Bedford",
    "sg:classifiers": [
      {
        "category": "Building \u0026 Trades",
        "subcategory": "Construction",
        "type": "Services"
      }
    ],
    "sg:phone": "+1 508 997 3771",
    "sg:postcode": "02746",
    "sg:province": "MA",
    "sg:tags": [
      "roofing",
      "contractor"
    ],
    "wof:name": "Loader Home Improvements",
    "wof:placetype": "venue"
  },
  "geometry": {"coordinates":[-70.930351,41.655895],"type":"Point"}
}
