{
  "type": "Feature",
  "properties": {
    "iso:country":"US",
    "sg:address":"205 Worcester Ct",
    "sg:city":"Falmouth",
    "sg:classifiers":[
        {
            "category":"Restaurant",
            "type":"Food & Drink"
        }
    ],
    "sg:phone":"+1 508 540 7136",
    "sg:postcode":"02540",
    "sg:province":"MA",
    "wof:name":"Conference Table",
    "wof:placetype":"venue"
},
  "geometry": {"coordinates":[-70.597432,41.559015],"type":"Point"}
}