{
  "type": "Feature",
  "properties": {
    "addr:full": "205 Worcester Ct Falmouth MA 02540",
    "addr:housenumber": "205",
    "addr:postcode": "02540",
    "addr:street": "Worcester Ct",
    "iso:country": "US",
    "ovtr:label": "Conference Table, 205 Worcester Ct Falmouth MA US",
    "ovtr:similarity": 2.2540900707244873,
    "sg:address": "205 Worcester Ct",
    "sg:city": "Falmouth",
    "sg:classifiers": [
      {
        "category": "Restaurant",
        "type": "Food \u0026 Drink"
      }
    ],
    "sg:phone": "+1 508 540 7136",
    "sg:postcode": "02540",
    "sg:province": "MA",
    "wof:name": "Conference Table",
    "wof:placetype": "venue"
  },
  "geometry": {"coordinates":[-70.597432,41.559015],"type":"Point"}
}
