{
  "type": "Feature",
  "properties": {
    "addr:full":"76 Annawan Rd Waban MA 02468",
    "addr:housenumber":"76",
    "addr:postcode":"02468",
    "addr:street":"Annawan Rd",
    "iso:country":"US",
    "sg:address":"76 Annawan Rd",
    "sg:city":"Waban",
    "sg:classifiers":[
        {
            "category":"Health Services",
            "subcategory":"Doctor",
            "type":"Services"
        }
    ],
    "sg:phone":"+1 617 965 2779",
    "sg:postcode":"02468",
    "sg:province":"MA",
    "sg:tags":[
        "physician",
        "surgeon"
    ],
    "wof:name":"Joseph E Schwartz MD",
    "wof:placetype":"venue"
},
  "geometry": {"coordinates":[-71.23484999999999,42.323081],"type":"Point"}
}