{
  "type": "Feature",
  "properties": {
    "addr:full": "110 Taunton Ave Seekonk MA 02771",
    "addr:housenumber": "110",
    "addr:postcode": "02771",
    "addr:street": "Taunton Ave",
    "iso:country": "US",
    "sg:address": "110 Taunton Ave",
    "sg:city": "Seekonk",
    "sg:classifiers": [
      {
        "category": "Autos \u0026 Motor Vehicles",
        "subcategory": "Automobile Sales",
        "type": "Retail Goods"
      }
    ],
    "sg:phone": "+1 508 336 5258",
    "sg:postcode": "02771",
    "sg:province": "MA",
    "sg:tags": [
      "dealers-used",
      "car",
      "cars-wholesale"
    ],
    "wof:name": "Friendship Auto Sales",
    "wof:placetype": "venue"
  },
  "geometry": {"coordinates":[-71.342419,41.824062],"type":"Point"}
}
