{
  "type": "Feature",
  "properties": {
    "iso:country":"US",
    "sg:address":"110 Taunton Ave",
    "sg:city":"Seekonk",
    "sg:classifiers":[
        {
            "category":"Autos & Motor Vehicles",
            "subcategory":"Automobile Sales",
            "type":"Retail Goods"
        }
    ],
    "sg:phone":"+1 508 336 5258",
    "sg:postcode":"02771",
    "sg:province":"MA",
    "sg:tags":[
        "dealers-used",
        "car",
        "cars-wholesale"
    ],
    "wof:name":"Friendship Auto Sales",
    "wof:placetype":"venue"
},
  "geometry": {"coordinates":[-71.34241900000001,41.824062],"type":"Point"}
}