{
  "type": "Feature",
  "properties": {
    "addr:full": "422 Main St Falmouth MA 02540",
    "addr:housenumber": "422",
    "addr:postcode": "02540",
    "addr:street": "Main St",
    "iso:country": "US",
    "sg:address": "422 Main St",
    "sg:city": "Falmouth",
    "sg:classifiers": [
      {
        "category": "Retail",
        "subcategory": "Repair Shop",
        "type": "Services"
      }
    ],
    "sg:phone": "+1 508 548 4565",
    "sg:postcode": "02540",
    "sg:province": "MA",
    "sg:tags": [
      "lock",
      "locksmith"
    ],
    "wof:name": "Ace Locksmithing Inc",
    "wof:placetype": "venue"
  },
  "geometry": {"coordinates":[-70.60754,41.552388],"type":"Point"}
}
