{
  "type": "Feature",
  "properties": {
    "iso:country":"US",
    "sg:address":"11 Republic Rd",
    "sg:city":"North Billerica",
    "sg:classifiers":[
        {
            "category":"Wholesale",
            "subcategory":"Construction Materials",
            "type":"Manufacturing & Wholesale Goods"
        }
    ],
    "sg:phone":"+1 978 663 0035",
    "sg:postcode":"01862",
    "sg:province":"MA",
    "sg:tags":[
        "sand",
        "gravel"
    ],
    "wof:name":"Pitcherville Sand & Gravel",
    "wof:placetype":"venue"
},
  "geometry": {"coordinates":[-71.29982,42.558305],"type":"Point"}
}