{
  "type": "Feature",
  "properties": {
    "addr:full": "11 Republic Rd North Billerica MA 01862",
    "addr:housenumber": "11",
    "addr:postcode": "01862",
    "addr:street": "Republic Rd",
    "iso:country": "US",
    "sg:address": "11 Republic Rd",
    "sg:city": "North Billerica",
    "sg:classifiers": [
      {
        "category": "Wholesale",
        "subcategory": "Construction Materials",
        "type": "Manufacturing \u0026 Wholesale Goods"
      }
    ],
    "sg:phone": "+1 978 663 0035",
    "sg:postcode": "01862",
    "sg:province": "MA",
    "sg:tags": [
      "sand",
      "gravel"
    ],
    "wof:name": "Pitcherville Sand \u0026 Gravel",
    "wof:placetype": "venue"
  },
  "geometry": {"coordinates":[-71.29982,42.558305],"type":"Point"}
}
