{
  "type": "Feature",
  "properties": {
    "addr:full": "100 Cambridge St Boston MA 02114",
    "addr:housenumber": "100",
    "addr:postcode": "02114",
    "addr:street": "Cambridge St",
    "iso:country": "US",
    "sg:address": "100 Cambridge St",
    "sg:city": "Boston",
    "sg:classifiers": [
      {
        "category": "Insurance",
        "subcategory": "Hazard Insurance",
        "type": "Services"
      },
      {
        "category": "Insurance",
        "subcategory": "Life Insurance",
        "type": "Services"
      }
    ],
    "sg:phone": "+1 617 722 4314",
    "sg:postcode": "02114",
    "sg:province": "MA",
    "sg:tags": [
      "commercial",
      "business"
    ],
    "sg:website": "http://www.pennmutual.com",
    "wof:name": "Penn Mutual Ins",
    "wof:placetype": "venue"
  },
  "geometry": {"coordinates":[-71.061816,42.360892],"type":"Point"}
}
