{
  "type": "Feature",
  "properties": {
    "addr:full": "23 Oxford St Worcester MA 01609",
    "addr:housenumber": "23",
    "addr:postcode": "01609",
    "addr:street": "Oxford St",
    "iso:country": "US",
    "sg:address": "23 Oxford St",
    "sg:city": "Worcester",
    "sg:classifiers": [
      {
        "category": "Professional",
        "subcategory": "Management \u0026 Consulting",
        "type": "Services"
      }
    ],
    "sg:phone": "+1   ",
    "sg:postcode": "01609",
    "sg:province": "MA",
    "sg:tags": [
      "business"
    ],
    "wof:name": "Janice Weekes",
    "wof:placetype": "venue"
  },
  "geometry": {"coordinates":[-71.80747,42.26311],"type":"Point"}
}
