{
  "type": "Feature",
  "properties": {
    "addr:full": "957 W Broadway Gardner MA 01440",
    "addr:housenumber": "957",
    "addr:postcode": "01440",
    "addr:street": "W Broadway",
    "iso:country": "US",
    "sg:address": "957 W Broadway",
    "sg:city": "Gardner",
    "sg:classifiers": [
      {
        "category": "Home \u0026 Garden",
        "subcategory": "Building Materials",
        "type": "Retail Goods"
      }
    ],
    "sg:phone": "+1 978 630 1311",
    "sg:postcode": "01440",
    "sg:province": "MA",
    "sg:tags": [
      "modular"
    ],
    "wof:name": "American Dream Inc",
    "wof:placetype": "venue"
  },
  "geometry": {"coordinates":[-72.021263,42.564812],"type":"Point"}
}
