{
  "type": "Feature",
  "properties": {
    "addr:full": "32 Downs Rd Douglas MA 01516",
    "addr:housenumber": "32",
    "addr:postcode": "01516",
    "addr:street": "Downs Rd",
    "iso:country": "US",
    "sg:address": "32 Downs Rd",
    "sg:city": "Douglas",
    "sg:classifiers": [
      {
        "category": "Freight",
        "type": "Transportation"
      }
    ],
    "sg:phone": "+1 508 476 9240",
    "sg:postcode": "01516",
    "sg:province": "MA",
    "sg:tags": [
      "trucking"
    ],
    "wof:name": "AAT Co",
    "wof:placetype": "venue"
  },
  "geometry": {"coordinates":[-71.730795,42.04465],"type":"Point"}
}
