{
  "type": "Feature",
  "properties": {
    "iso:country":"US",
    "sg:address":"60 Bedford St",
    "sg:city":"Middleboro",
    "sg:classifiers":[
        {
            "category":"Manufacturing",
            "subcategory":"Tools & Machinery",
            "type":"Manufacturing & Wholesale Goods"
        }
    ],
    "sg:phone":"+1 508 946 1195",
    "sg:postcode":"02346",
    "sg:province":"MA",
    "sg:tags":[
        "machine",
        "shop"
    ],
    "wof:name":"BSM Engineering Co",
    "wof:placetype":"venue"
},
  "geometry": {"coordinates":[-70.960075,41.906268],"type":"Point"}
}