{
  "type": "Feature",
  "properties": {
    "addr:full": "36 Worcester Rd Charlton MA 01507",
    "addr:housenumber": "36",
    "addr:postcode": "01507",
    "addr:street": "Worcester Rd",
    "iso:country": "US",
    "sg:address": "36 Worcester Rd",
    "sg:city": "Charlton",
    "sg:classifiers": [
      {
        "category": "Autos \u0026 Motor Vehicles",
        "subcategory": "Fuel \u0026 Gas Station",
        "type": "Retail Goods"
      },
      {
        "category": "Food \u0026 Beverages",
        "subcategory": "Groceries \u0026 Convenience Stores",
        "type": "Retail Goods"
      }
    ],
    "sg:phone": "+1 508 248 4864",
    "sg:postcode": "01507",
    "sg:province": "MA",
    "wof:name": "Honey Farms",
    "wof:placetype": "venue"
  },
  "geometry": {"coordinates":[-71.987851,42.145388],"type":"Point"}
}
