{
  "type": "Feature",
  "properties": {
    "iso:country":"US",
    "sg:address":"36 Worcester Rd",
    "sg:city":"Charlton",
    "sg:classifiers":[
        {
            "category":"Autos & Motor Vehicles",
            "subcategory":"Fuel & Gas Station",
            "type":"Retail Goods"
        },
        {
            "category":"Food & Beverages",
            "subcategory":"Groceries & Convenience Stores",
            "type":"Retail Goods"
        }
    ],
    "sg:phone":"+1 508 248 4864",
    "sg:postcode":"01507",
    "sg:province":"MA",
    "wof:name":"Honey Farms",
    "wof:placetype":"venue"
},
  "geometry": {"coordinates":[-71.98785100000001,42.145388],"type":"Point"}
}