{
  "type": "Feature",
  "properties": {
    "iso:country":"US",
    "sg:address":"104 Summer St",
    "sg:city":"Watertown",
    "sg:classifiers":[
        {
            "category":"Professional",
            "subcategory":"Computer Services",
            "type":"Services"
        },
        {
            "category":"Internet Cafe",
            "subcategory":"None",
            "type":"Food & Drink"
        }
    ],
    "sg:phone":"+1 617 744 1091",
    "sg:postcode":"02472",
    "sg:province":"MA",
    "sg:tags":[
        "product",
        "software"
    ],
    "sg:website":"http://www.intdatsys.com",
    "wof:name":"Interval Data Systems Inc",
    "wof:placetype":"venue"
},
  "geometry": {"coordinates":[-71.185418,42.368716],"type":"Point"}
}