{
  "type": "Feature",
  "properties": {
    "addr:full": "37 Castleton St Jamaica Plain MA 02130",
    "addr:housenumber": "37",
    "addr:postcode": "02130",
    "addr:street": "Castleton St",
    "iso:country": "US",
    "sg:address": "37 Castleton St",
    "sg:city": "Jamaica Plain",
    "sg:classifiers": [
      {
        "category": "Organizations",
        "subcategory": "Religious Organization",
        "type": "Services"
      }
    ],
    "sg:phone": "+1 617 522 6909",
    "sg:postcode": "02130",
    "sg:province": "MA",
    "wof:name": "Sisters of Notre Dame",
    "wof:placetype": "venue"
  },
  "geometry": {"coordinates":[-71.114899,42.323399],"type":"Point"}
}
