{
  "type": "Feature",
  "properties": {
    "iso:country":"US",
    "sg:address":"903 Main St",
    "sg:city":"West Springfield",
    "sg:classifiers":[
        {
            "category":"Restaurant",
            "type":"Food & Drink"
        }
    ],
    "sg:phone":"+1 413 750 3444",
    "sg:postcode":"01089",
    "sg:province":"MA",
    "wof:name":"Angara Restaurant",
    "wof:placetype":"venue"
},
  "geometry": {"coordinates":[-72.603319,42.098808],"type":"Point"}
}