{
  "type": "Feature",
  "properties": {
    "addr:full":"8 River Dr Hadley MA 01035",
    "addr:housenumber":"8",
    "addr:postcode":"01035",
    "addr:street":"River Dr",
    "iso:country":"US",
    "sg:address":"8 River Dr",
    "sg:city":"Hadley",
    "sg:classifiers":[
        {
            "category":"Personal",
            "subcategory":"Beauty Salon",
            "type":"Services"
        }
    ],
    "sg:phone":"+1 413 584 6343",
    "sg:postcode":"01035",
    "sg:province":"MA",
    "wof:name":"Hair Shop",
    "wof:placetype":"venue"
},
  "geometry": {"coordinates":[-72.58977,42.350684],"type":"Point"}
}