{
  "type": "Feature",
  "properties": {
    "addr:full": "238 Millbury St Worcester MA 01610",
    "addr:housenumber": "238",
    "addr:postcode": "01610",
    "addr:street": "Millbury St",
    "iso:country": "US",
    "sg:address": "238 Millbury St",
    "sg:city": "Worcester",
    "sg:classifiers": [
      {
        "category": "Retail",
        "subcategory": "Auto Repair",
        "type": "Services"
      }
    ],
    "sg:phone": "+1 508 754 0882",
    "sg:postcode": "01610",
    "sg:province": "MA",
    "sg:tags": [
      "repairing",
      "automobile"
    ],
    "wof:name": "Trust Auto Sales",
    "wof:placetype": "venue"
  },
  "geometry": {"coordinates":[-71.800489,42.250267],"type":"Point"}
}
