{
  "type": "Feature",
  "properties": {
    "iso:country":"US",
    "sg:address":"1019 Crescent St",
    "sg:city":"Brockton",
    "sg:classifiers":[
        {
            "category":"Social Services",
            "type":"Services"
        }
    ],
    "sg:phone":"+1 508 584 6627",
    "sg:postcode":"02302",
    "sg:province":"MA",
    "sg:tags":[
        "employee",
        "assistance",
        "program"
    ],
    "wof:name":"Employee Assistance Program",
    "wof:placetype":"venue"
},
  "geometry": {"coordinates":[-70.97611000000001,42.081273],"type":"Point"}
}