{
  "type": "Feature",
  "properties": {
    "iso:country":"US",
    "sg:address":"98 Church St",
    "sg:city":"Whitinsville",
    "sg:classifiers":[
        {
            "category":"Shopping",
            "subcategory":"Books",
            "type":"Retail Goods"
        }
    ],
    "sg:phone":"+1 508 234 1988",
    "sg:postcode":"01588",
    "sg:province":"MA",
    "sg:tags":[
        "dealer",
        "gift"
    ],
    "wof:name":"Blackstone's Books & Gifts",
    "wof:placetype":"venue"
},
  "geometry": {"coordinates":[-71.660661,42.111967],"type":"Point"}
}