{
  "type": "Feature",
  "properties": {
    "iso:country":"US",
    "sg:address":"73 Pelham Island Rd",
    "sg:city":"Wayland",
    "sg:classifiers":[
        {
            "category":"Real Estate",
            "subcategory":"Architect",
            "type":"Services"
        }
    ],
    "sg:phone":"+1 508 358 6298",
    "sg:postcode":"01778",
    "sg:province":"MA",
    "sg:tags":[
        "home",
        "planning",
        "design"
    ],
    "wof:name":"Chadwick Properties Inc",
    "wof:placetype":"venue"
},
  "geometry": {"coordinates":[-71.364952,42.361724],"type":"Point"}
}