{
  "type": "Feature",
  "properties": {
    "addr:full": "25 Spring Garden St Boston MA 02125",
    "addr:housenumber": "25",
    "addr:postcode": "02125",
    "addr:street": "Spring Garden St",
    "iso:country": "US",
    "sg:address": "25 Spring Garden St",
    "sg:city": "Boston",
    "sg:classifiers": [
      {
        "category": "Retail",
        "subcategory": "Repair Shop",
        "type": "Services"
      }
    ],
    "sg:phone": "+1   ",
    "sg:postcode": "02125",
    "sg:province": "MA",
    "wof:name": "Deane Locksmith Service",
    "wof:placetype": "venue"
  },
  "geometry": {"coordinates":[-71.053372,42.31749],"type":"Point"}
}
