{
  "type": "Feature",
  "properties": {
    "addr:full": "294 Washington St Boston MA 02108",
    "addr:housenumber": "294",
    "addr:postcode": "02108",
    "addr:street": "Washington St",
    "iso:country": "US",
    "sg:address": "294 Washington St",
    "sg:city": "Boston",
    "sg:classifiers": [
      {
        "category": "Recreation",
        "type": "Entertainment"
      }
    ],
    "sg:phone": "+1 617 988 0613",
    "sg:postcode": "02108",
    "sg:province": "MA",
    "sg:tags": [
      "inspection",
      "carnival"
    ],
    "wof:name": "Fair Housing Testing Project",
    "wof:placetype": "venue"
  },
  "geometry": {"coordinates":[-71.05861,42.357216],"type":"Point"}
}
