{
  "type": "Feature",
  "properties": {
    "addr:full": "60 Washington St Lowell MA 01851",
    "addr:housenumber": "60",
    "addr:postcode": "01851",
    "addr:street": "Washington St",
    "iso:country": "US",
    "sg:address": "60 Washington St",
    "sg:city": "Lowell",
    "sg:classifiers": [
      {
        "category": "Professional",
        "subcategory": "Detective \u0026 Security Services",
        "type": "Services"
      }
    ],
    "sg:phone": "+1 978 710 6720",
    "sg:postcode": "01851",
    "sg:province": "MA",
    "sg:tags": [
      "information",
      "bureau"
    ],
    "wof:name": "Goodwill Support Services",
    "wof:placetype": "venue"
  },
  "geometry": {"coordinates":[-71.317803,42.630059],"type":"Point"}
}
