{
  "type": "Feature",
  "properties": {
    "addr:full": "70 Coolidge Cir Northborough MA 01532",
    "addr:housenumber": "70",
    "addr:postcode": "01532",
    "addr:street": "Coolidge Cir",
    "iso:country": "US",
    "sg:address": "70 Coolidge Cir",
    "sg:city": "Northborough",
    "sg:classifiers": [
      {
        "category": "Professional",
        "subcategory": "Accounting \u0026 Tax Preparation",
        "type": "Services"
      }
    ],
    "sg:phone": "+1 508 393 3384",
    "sg:postcode": "01532",
    "sg:province": "MA",
    "wof:name": "James Casella CPA",
    "wof:placetype": "venue"
  },
  "geometry": {"coordinates":[-71.638479,42.356001],"type":"Point"}
}
