{
  "type": "Feature",
  "properties": {
    "iso:country":"US",
    "sg:address":"399 Common St",
    "sg:city":"Belmont",
    "sg:classifiers":[
        {
            "category":"Health Services",
            "subcategory":"Doctor",
            "type":"Services"
        }
    ],
    "sg:phone":"+1 617 484 7496",
    "sg:postcode":"02478",
    "sg:province":"MA",
    "sg:tags":[
        "dentist"
    ],
    "wof:name":"Gregory N Connolly DDS",
    "wof:placetype":"venue"
},
  "geometry": {"coordinates":[-71.175252,42.38259],"type":"Point"}
}