{
  "type": "Feature",
  "properties": {
    "addr:full":"122 Brookfield Rd Fiskdale MA 01518",
    "addr:housenumber":"122",
    "addr:postcode":"01518",
    "addr:street":"Brookfield Rd",
    "iso:country":"US",
    "sg:address":"122 Brookfield Rd",
    "sg:city":"Fiskdale",
    "sg:classifiers":[
        {
            "category":"Real Estate",
            "subcategory":"Real Estate Agent",
            "type":"Services"
        }
    ],
    "sg:phone":"+1 508 347 7050",
    "sg:postcode":"01518",
    "sg:province":"MA",
    "sg:tags":[
        "inspection"
    ],
    "wof:name":"Leblanc Septic Inspections Lsi",
    "wof:placetype":"venue"
},
  "geometry": {"coordinates":[-72.123544,42.130573],"type":"Point"}
}