{
  "type": "Feature",
  "properties": {
    "iso:country":"US",
    "sg:address":"243 Pleasant St",
    "sg:city":"Northampton",
    "sg:classifiers":[
        {
            "category":"Food & Beverages",
            "subcategory":"Liquor & Beverages",
            "type":"Retail Goods"
        }
    ],
    "sg:phone":"+1 413 584 5145",
    "sg:postcode":"01060",
    "sg:province":"MA",
    "wof:name":"Millennium Package Store",
    "wof:placetype":"venue"
},
  "geometry": {"coordinates":[-72.626718,42.317403],"type":"Point"}
}