{
  "type": "Feature",
  "properties": {
    "addr:full": "243 Pleasant St Northampton MA 01060",
    "addr:housenumber": "243",
    "addr:postcode": "01060",
    "addr:street": "Pleasant St",
    "iso:country": "US",
    "ovtr:label": "Millennium Package Store, 243 Pleasant St Northampton MA US",
    "ovtr:similarity": 2.374650001525879,
    "sg:address": "243 Pleasant St",
    "sg:city": "Northampton",
    "sg:classifiers": [
      {
        "category": "Food \u0026 Beverages",
        "subcategory": "Liquor \u0026 Beverages",
        "type": "Retail Goods"
      }
    ],
    "sg:phone": "+1 413 584 5145",
    "sg:postcode": "01060",
    "sg:province": "MA",
    "wof:name": "Millennium Package Store",
    "wof:placetype": "venue"
  },
  "geometry": {"coordinates":[-72.626718,42.317403],"type":"Point"}
}
