{
  "type": "Feature",
  "properties": {
    "addr:full":"64 Argilla Rd Andover MA 01810",
    "addr:housenumber":"64",
    "addr:postcode":"01810",
    "addr:street":"Argilla Rd",
    "iso:country":"US",
    "sg:address":"64 Argilla Rd",
    "sg:city":"Andover",
    "sg:classifiers":[
        {
            "category":"Building & Trades",
            "subcategory":"Construction",
            "type":"Services"
        }
    ],
    "sg:phone":"+1 978 470 8366",
    "sg:postcode":"01810",
    "sg:province":"MA",
    "sg:tags":[
        "hanging",
        "contractor"
    ],
    "wof:name":"Custom Interior Decorating",
    "wof:placetype":"venue"
},
  "geometry": {"coordinates":[-71.162318,42.644761],"type":"Point"}
}