{
  "type": "Feature",
  "properties": {
    "addr:full":"43 Winnetuxet Rd Plympton MA 02367",
    "addr:housenumber":"43",
    "addr:postcode":"02367",
    "addr:street":"Winnetuxet Rd",
    "iso:country":"US",
    "sg:address":"43 Winnetuxet Rd",
    "sg:city":"Plympton",
    "sg:classifiers":[
        {
            "category":"Retail",
            "subcategory":"Pet Boarding",
            "type":"Services"
        }
    ],
    "sg:phone":"+1 781 585 2150",
    "sg:postcode":"02367",
    "sg:province":"MA",
    "sg:tags":[
        "boarding/pet",
        "sitting"
    ],
    "wof:name":"Cat's Cradle Inc",
    "wof:placetype":"venue"
},
  "geometry": {"coordinates":[-70.81619999999999,41.943001],"type":"Point"}
}