{
  "type": "Feature",
  "properties": {
    "addr:full": "790 Boylston St Apt 14H Boston MA 02199",
    "addr:housenumber": "790;14h",
    "addr:postcode": "02199",
    "addr:street": "Boylston St Apt",
    "iso:country": "US",
    "sg:address": "790 Boylston St Apt 14H",
    "sg:city": "Boston",
    "sg:classifiers": [
      {
        "category": "Manufacturing",
        "subcategory": "Metals",
        "type": "Manufacturing \u0026 Wholesale Goods"
      },
      {
        "category": "Wholesale",
        "subcategory": "Jewelry",
        "type": "Manufacturing \u0026 Wholesale Goods"
      },
      {
        "category": "Manufacturing",
        "subcategory": "Jewelry",
        "type": "Manufacturing \u0026 Wholesale Goods"
      }
    ],
    "sg:phone": "+1 617 267 9239",
    "sg:postcode": "02199",
    "sg:province": "MA",
    "sg:tags": [
      "jewelers-wholesale",
      "supply",
      "metals-precious",
      "jeweler",
      "finding",
      "manufacturer"
    ],
    "wof:name": "Shapes By Andrea Chapin",
    "wof:placetype": "venue"
  },
  "geometry": {"coordinates":[-71.08168,42.3489],"type":"Point"}
}
