{
  "type": "Feature",
  "properties": {
    "iso:country":"US",
    "sg:address":"790 Boylston St Apt 14H",
    "sg:city":"Boston",
    "sg:classifiers":[
        {
            "category":"Manufacturing",
            "subcategory":"Metals",
            "type":"Manufacturing & Wholesale Goods"
        },
        {
            "category":"Wholesale",
            "subcategory":"Jewelry",
            "type":"Manufacturing & Wholesale Goods"
        },
        {
            "category":"Manufacturing",
            "subcategory":"Jewelry",
            "type":"Manufacturing & Wholesale Goods"
        }
    ],
    "sg:phone":"+1 617 267 9239",
    "sg:postcode":"02199",
    "sg:province":"MA",
    "sg:tags":[
        "jewelers-wholesale",
        "supply",
        "metals-precious",
        "jeweler",
        "finding",
        "manufacturer"
    ],
    "wof:name":"Shapes By Andrea Chapin",
    "wof:placetype":"venue"
},
  "geometry": {"coordinates":[-71.08168000000001,42.3489],"type":"Point"}
}