{
  "type": "Feature",
  "properties": {
    "addr:full":"27 S Pond St Newbury MA 01951",
    "addr:housenumber":"27",
    "addr:postcode":"01951",
    "addr:street":"S Pond St",
    "iso:country":"US",
    "sg:address":"27 S Pond St",
    "sg:city":"Newbury",
    "sg:classifiers":[
        {
            "category":"Retail",
            "subcategory":"Portrait Studio",
            "type":"Services"
        }
    ],
    "sg:phone":"+1   ",
    "sg:postcode":"01951",
    "sg:province":"MA",
    "sg:tags":[
        "photo"
    ],
    "wof:name":"Rakaplan Photography",
    "wof:placetype":"venue"
},
  "geometry": {"coordinates":[-70.859189,42.79933],"type":"Point"}
}