{
  "type": "Feature",
  "properties": {
    "addr:full":"84 Bess Rd Weston MA 02492",
    "addr:housenumber":"84",
    "addr:postcode":"02492",
    "addr:street":"Bess Rd",
    "iso:country":"US",
    "sg:address":"84 Bess Rd",
    "sg:city":"Weston",
    "sg:classifiers":[
        {
            "category":"Health Services",
            "subcategory":"Doctor",
            "type":"Services"
        }
    ],
    "sg:phone":"+1   ",
    "sg:postcode":"02492",
    "sg:province":"MA",
    "sg:tags":[
        "physician"
    ],
    "wof:name":"Douglas Dalh",
    "wof:placetype":"venue"
},
  "geometry": {"coordinates":[-71.249669,42.289558],"type":"Point"}
}