{
  "type": "Feature",
  "properties": {
    "addr:full": "191 Stafford Rd Fall River MA 02721",
    "addr:housenumber": "191",
    "addr:postcode": "02721",
    "addr:street": "Stafford Rd",
    "iso:country": "US",
    "sg:address": "191 Stafford Rd",
    "sg:city": "Fall River",
    "sg:classifiers": [
      {
        "category": "Shopping",
        "subcategory": "Bicycles \u0026 Sporting Goods",
        "type": "Retail Goods"
      }
    ],
    "sg:phone": "+1 508 674 7900",
    "sg:postcode": "02721",
    "sg:province": "MA",
    "sg:tags": [
      "tackle",
      "parts",
      "fishing"
    ],
    "wof:name": "Bucko's Part \u0026 Tackle Svc",
    "wof:placetype": "venue"
  },
  "geometry": {"coordinates":[-71.15906,41.686795],"type":"Point"}
}
