{
  "type": "Feature",
  "properties": {
    "iso:country":"US",
    "sg:address":"145 Oak St",
    "sg:city":"Ashland",
    "sg:classifiers":[
        {
            "category":"Building & Trades",
            "subcategory":"Landscaping Services",
            "type":"Services"
        }
    ],
    "sg:phone":"+1 508 620 1234",
    "sg:postcode":"01721",
    "sg:province":"MA",
    "sg:tags":[
        "landscape",
        "contractor"
    ],
    "wof:name":"Centre Landscape",
    "wof:placetype":"venue"
},
  "geometry": {"coordinates":[-71.493669,42.274384],"type":"Point"}
}