{
  "type": "Feature",
  "properties": {
    "iso:country":"US",
    "sg:address":"10 Winthrop Sq",
    "sg:city":"Boston",
    "sg:classifiers":[
        {
            "category":"Personal",
            "type":"Services"
        }
    ],
    "sg:phone":"+1 617 338 2254",
    "sg:postcode":"02110",
    "sg:province":"MA",
    "sg:tags":[
        "sewing",
        "alteration"
    ],
    "wof:name":"Tony Tong the Tailor",
    "wof:placetype":"venue"
},
  "geometry": {"coordinates":[-71.058098,42.353802],"type":"Point"}
}