{
  "type": "Feature",
  "properties": {
    "iso:country":"US",
    "sg:address":"812 Liberty St",
    "sg:city":"Braintree",
    "sg:classifiers":[
        {
            "category":"Professional",
            "subcategory":"Business Services",
            "type":"Services"
        }
    ],
    "sg:phone":"+1   ",
    "sg:postcode":"02184",
    "sg:province":"MA",
    "sg:tags":[
        "landscape"
    ],
    "wof:name":"Hal Enterprises",
    "wof:placetype":"venue"
},
  "geometry": {"coordinates":[-70.98477699999999,42.193767],"type":"Point"}
}