{
  "type": "Feature",
  "properties": {
    "addr:full": "812 Liberty St Braintree MA 02184",
    "addr:housenumber": "812",
    "addr:postcode": "02184",
    "addr:street": "Liberty St",
    "iso:country": "US",
    "sg:address": "812 Liberty St",
    "sg:city": "Braintree",
    "sg:classifiers": [
      {
        "category": "Professional",
        "subcategory": "Business Services",
        "type": "Services"
      }
    ],
    "sg:phone": "+1   ",
    "sg:postcode": "02184",
    "sg:province": "MA",
    "sg:tags": [
      "landscape"
    ],
    "wof:name": "Hal Enterprises",
    "wof:placetype": "venue"
  },
  "geometry": {"coordinates":[-70.984777,42.193767],"type":"Point"}
}
