{
  "type": "Feature",
  "properties": {
    "addr:full": "894 Main St Waltham MA 02451",
    "addr:housenumber": "894",
    "addr:postcode": "02451",
    "addr:street": "Main St",
    "iso:country": "US",
    "sg:address": "894 Main St",
    "sg:city": "Waltham",
    "sg:classifiers": [
      {
        "category": "Food \u0026 Beverages",
        "subcategory": "Liquor \u0026 Beverages",
        "type": "Retail Goods"
      }
    ],
    "sg:phone": "+1 781 893 1900",
    "sg:postcode": "02451",
    "sg:province": "MA",
    "sg:website": "www.gordonsthewinesource.com",
    "wof:name": "Gordon's Liquor Store Inc",
    "wof:placetype": "venue"
  },
  "geometry": {"coordinates":[-71.246756,42.376211],"type":"Point"}
}
