{
  "type": "Feature",
  "properties": {
    "addr:full":"478 Broadway Chelsea MA 02150",
    "addr:housenumber":"478",
    "addr:postcode":"02150",
    "addr:street":"Broadway",
    "iso:country":"US",
    "sg:address":"478 Broadway",
    "sg:city":"Chelsea",
    "sg:classifiers":[
        {
            "category":"Bakery",
            "type":"Food & Drink"
        },
        {
            "category":"Coffee & Tea",
            "type":"Food & Drink"
        },
        {
            "category":"Bagels",
            "type":"Food & Drink"
        },
        {
            "category":"Donuts",
            "type":"Food & Drink"
        }
    ],
    "sg:menulink":"http://www.allmenus.com/ma/chelsea/142811-dunkin-donuts/menu/",
    "sg:phone":"+1 617 884 9453",
    "sg:postcode":"02150",
    "sg:province":"MA",
    "sg:tags":[
        "american",
        "diner",
        "pastry"
    ],
    "wof:name":"Dunkin' Donuts",
    "wof:placetype":"venue"
},
  "geometry": {"coordinates":[-71.034296,42.393084],"type":"Point"}
}