{
  "type": "Feature",
  "properties": {
    "addr:full":"20 Park Plz Ste 610 Boston MA 02116",
    "addr:housenumber":"20",
    "addr:postcode":"02116",
    "addr:street":"Park Plz Ste 610",
    "iso:country":"US",
    "sg:address":"20 Park Plz Ste 610",
    "sg:city":"Boston",
    "sg:classifiers":[
        {
            "category":"Landmark",
            "subcategory":"Tourist Information",
            "type":"Public Place"
        }
    ],
    "sg:phone":"+1 617 338 5050",
    "sg:postcode":"02116",
    "sg:province":"MA",
    "sg:tags":[
        "tour"
    ],
    "sg:website":"www.millrun.com",
    "wof:name":"Mill-Run Tours of Mass",
    "wof:placetype":"venue"
},
  "geometry": {"coordinates":[-71.069716,42.351392],"type":"Point"}
}