{
  "type": "Feature",
  "properties": {
    "addr:full":"418 Macarthur Blvd Buzzards Bay MA 02532",
    "addr:housenumber":"418",
    "addr:postcode":"02532",
    "addr:street":"Macarthur Blvd",
    "iso:country":"US",
    "sg:address":"418 Macarthur Blvd",
    "sg:city":"Buzzards Bay",
    "sg:classifiers":[
        {
            "category":"Autos & Motor Vehicles",
            "subcategory":"Automobile Sales",
            "type":"Retail Goods"
        }
    ],
    "sg:phone":"+1 508 759 2900",
    "sg:postcode":"02532",
    "sg:province":"MA",
    "sg:tags":[
        "car",
        "dealer"
    ],
    "sg:website":"www.showcaseisuzu.com",
    "wof:name":"Showcase Isuzu",
    "wof:placetype":"venue"
},
  "geometry": {"coordinates":[-70.536455,41.799407],"type":"Point"}
}