{
  "type": "Feature",
  "properties": {
    "iso:country":"US",
    "sg:address":"360 South St",
    "sg:city":"Marlborough",
    "sg:classifiers":[
        {
            "category":"Shopping",
            "subcategory":"Discount & Variety Stores",
            "type":"Retail Goods"
        }
    ],
    "sg:phone":"+1 508 485 7489",
    "sg:postcode":"01752",
    "sg:province":"MA",
    "sg:tags":[
        "merchandise",
        "general"
    ],
    "wof:name":"Brazilian Products Dstrbtn",
    "wof:placetype":"venue"
},
  "geometry": {"coordinates":[-71.545579,42.334783],"type":"Point"}
}