{
  "type": "Feature",
  "properties": {
    "addr:full":"85 Devonshire St Boston MA 02109",
    "addr:housenumber":"85",
    "addr:postcode":"02109",
    "addr:street":"Devonshire St",
    "iso:country":"US",
    "sg:address":"85 Devonshire St",
    "sg:city":"Boston",
    "sg:classifiers":[
        {
            "category":"Real Estate",
            "subcategory":"Developer",
            "type":"Services"
        }
    ],
    "sg:phone":"+1 617 742 6000",
    "sg:postcode":"02109",
    "sg:province":"MA",
    "sg:website":"www.cathartes.com",
    "wof:name":"Cathartes Group",
    "wof:placetype":"venue"
},
  "geometry": {"coordinates":[-71.05727400000001,42.358321],"type":"Point"}
}