{
  "type": "Feature",
  "properties": {
    "addr:full": "115 Clemente St Holyoke MA 01040",
    "addr:housenumber": "115",
    "addr:postcode": "01040",
    "addr:street": "Clemente St",
    "iso:country": "US",
    "sg:address": "115 Clemente St",
    "sg:city": "Holyoke",
    "sg:classifiers": [
      {
        "category": "Manufacturing",
        "subcategory": "Tools \u0026 Machinery",
        "type": "Manufacturing \u0026 Wholesale Goods"
      }
    ],
    "sg:phone": "+1 413 532 4551",
    "sg:postcode": "01040",
    "sg:province": "MA",
    "sg:tags": [
      "equipment",
      "hospital",
      "supply"
    ],
    "sg:website": "www.atsurgical.com",
    "wof:name": "A-T Surgical Mfg Co",
    "wof:placetype": "venue"
  },
  "geometry": {"coordinates":[-72.607111,42.198839],"type":"Point"}
}
