{
  "type": "Feature",
  "properties": {
    "addr:full": "216 Willow St West Roxbury MA 02132",
    "addr:housenumber": "216",
    "addr:postcode": "02132",
    "addr:street": "Willow St",
    "iso:country": "US",
    "sg:address": "216 Willow St",
    "sg:city": "West Roxbury",
    "sg:classifiers": [
      {
        "category": "Building \u0026 Trades",
        "subcategory": "Construction",
        "type": "Services"
      }
    ],
    "sg:phone": "+1 617 327 3267",
    "sg:postcode": "02132",
    "sg:province": "MA",
    "sg:tags": [
      "home",
      "improvement"
    ],
    "wof:name": "Fleming Builders Inc",
    "wof:placetype": "venue"
  },
  "geometry": {"coordinates":[-71.157759,42.293913],"type":"Point"}
}
