{
  "type": "Feature",
  "properties": {
    "iso:country":"US",
    "sg:address":"216 Willow St",
    "sg:city":"West Roxbury",
    "sg:classifiers":[
        {
            "category":"Building & Trades",
            "subcategory":"Construction",
            "type":"Services"
        }
    ],
    "sg:phone":"+1 617 327 3267",
    "sg:postcode":"02132",
    "sg:province":"MA",
    "sg:tags":[
        "home",
        "improvement"
    ],
    "wof:name":"Fleming Builders Inc",
    "wof:placetype":"venue"
},
  "geometry": {"coordinates":[-71.157759,42.293913],"type":"Point"}
}