{
  "type": "Feature",
  "properties": {
    "iso:country":"US",
    "sg:address":"10 Oolah Ave",
    "sg:city":"Norwood",
    "sg:classifiers":[
        {
            "category":"Professional",
            "subcategory":"Computer Services",
            "type":"Services"
        }
    ],
    "sg:phone":"+1   ",
    "sg:postcode":"02062",
    "sg:province":"MA",
    "sg:tags":[
        "related"
    ],
    "wof:name":"Puterwiz",
    "wof:placetype":"venue"
},
  "geometry": {"coordinates":[-71.205726,42.179424],"type":"Point"}
}