{
  "type": "Feature",
  "properties": {
    "addr:full":"1568 Broadway St Raynham MA 02767",
    "addr:housenumber":"1568",
    "addr:postcode":"02767",
    "addr:street":"Broadway St",
    "iso:country":"US",
    "sg:address":"1568 Broadway St",
    "sg:city":"Raynham",
    "sg:classifiers":[
        {
            "category":"Recreation",
            "type":"Entertainment"
        }
    ],
    "sg:phone":"+1 508 880 3311",
    "sg:postcode":"02767",
    "sg:province":"MA",
    "sg:tags":[
        "skating",
        "rink"
    ],
    "sg:website":"www.cdlarena.com",
    "wof:name":"CDL Arena",
    "wof:placetype":"venue"
},
  "geometry": {"coordinates":[-71.06814199999999,41.974544],"type":"Point"}
}