{
  "type": "Feature",
  "properties": {
    "addr:full": "142 Marginal St East Boston MA 02128",
    "addr:housenumber": "142",
    "addr:postcode": "02128",
    "addr:street": "Marginal St",
    "iso:country": "US",
    "sg:address": "142 Marginal St",
    "sg:city": "East Boston",
    "sg:classifiers": [
      {
        "category": "Real Estate",
        "subcategory": "Real Estate Agent",
        "type": "Services"
      }
    ],
    "sg:phone": "+1 617 561 3131",
    "sg:postcode": "02128",
    "sg:province": "MA",
    "wof:name": "Independent Realty Management",
    "wof:placetype": "venue"
  },
  "geometry": {"coordinates":[-71.033575,42.364372],"type":"Point"}
}
