{
  "type": "Feature",
  "properties": {
    "iso:country":"US",
    "sg:address":"45 Newbury Street",
    "sg:city":"Boston",
    "sg:classifiers":[
        {
            "category":"Retail",
            "subcategory":"Portrait Studio",
            "type":"Services"
        },
        {
            "category":"Professional",
            "subcategory":"Art Services",
            "type":"Services"
        }
    ],
    "sg:phone":"+1 617 247 0733",
    "sg:postcode":"02116",
    "sg:province":"MA",
    "sg:tags":[
        "photographer",
        "photography",
        "store"
    ],
    "wof:name":"Lampert Margaret Photog",
    "wof:placetype":"venue"
},
  "geometry": {"coordinates":[-71.072721,42.352263],"type":"Point"}
}