{
  "type": "Feature",
  "properties": {
    "iso:country":"US",
    "sg:address":"86 Old Sudbury Rd",
    "sg:city":"Wayland",
    "sg:classifiers":[
        {
            "category":"Health Services",
            "subcategory":"Doctor",
            "type":"Services"
        }
    ],
    "sg:phone":"+1 508 358 0246",
    "sg:postcode":"01778",
    "sg:province":"MA",
    "sg:tags":[
        "physician",
        "surgeon"
    ],
    "wof:name":"Pinnamaneni, Sita",
    "wof:placetype":"venue"
},
  "geometry": {"coordinates":[-71.372039,42.373085],"type":"Point"}
}