{
  "type": "Feature",
  "properties": {
    "addr:full":"400 S Elm St Holyoke MA 01040",
    "addr:housenumber":"400",
    "addr:postcode":"01040",
    "addr:street":"S Elm St",
    "iso:country":"US",
    "sg:address":"400 S Elm St",
    "sg:city":"Holyoke",
    "sg:classifiers":[
        {
            "category":"Education",
            "subcategory":"Special Training",
            "type":"Public Place"
        }
    ],
    "sg:phone":"+1 413 532 0465",
    "sg:postcode":"01040",
    "sg:province":"MA",
    "sg:tags":[
        "craft"
    ],
    "wof:name":"Holyoke Creative Arts Ctr",
    "wof:placetype":"venue"
},
  "geometry": {"coordinates":[-72.62122599999999,42.197441],"type":"Point"}
}