{
  "type": "Feature",
  "properties": {
    "iso:country":"US",
    "sg:address":"64 Chestnut St",
    "sg:city":"North Attleboro",
    "sg:classifiers":[
        {
            "category":"Building & Trades",
            "subcategory":"Construction",
            "type":"Services"
        }
    ],
    "sg:phone":"+1 508 699 4966",
    "sg:postcode":"02760",
    "sg:province":"MA",
    "sg:tags":[
        "excavation",
        "contractor"
    ],
    "wof:name":"Finn Excavating",
    "wof:placetype":"venue"
},
  "geometry": {"coordinates":[-71.332262,41.978363],"type":"Point"}
}