{
  "type": "Feature",
  "properties": {
    "iso:country":"US",
    "sg:address":"33 Cambridge St",
    "sg:city":"Burlington",
    "sg:classifiers":[
        {
            "category":"Building & Trades",
            "subcategory":"Locksmith",
            "type":"Services"
        }
    ],
    "sg:phone":"+1 781 203 6138",
    "sg:postcode":"01803",
    "sg:province":"MA",
    "sg:tags":[
        "key"
    ],
    "wof:name":"Locksmith Service ABC Emergency",
    "wof:placetype":"venue"
},
  "geometry": {"coordinates":[-71.188317,42.482623],"type":"Point"}
}