{
  "type": "Feature",
  "properties": {
    "addr:full":"36 1st Ave Charlestown MA 02129",
    "addr:housenumber":"36",
    "addr:postcode":"02129",
    "addr:street":"1St Ave",
    "iso:country":"US",
    "sg:address":"36 1st Ave",
    "sg:city":"Charlestown",
    "sg:classifiers":[
        {
            "category":"Education",
            "subcategory":"Junior College",
            "type":"Public Place"
        }
    ],
    "sg:phone":"+1 617 726 8002",
    "sg:postcode":"02129",
    "sg:province":"MA",
    "sg:tags":[
        "technical",
        "institute"
    ],
    "sg:website":"www.mghihp.edu",
    "wof:name":"MGH Institute-Health Profsns",
    "wof:placetype":"venue"
},
  "geometry": {"coordinates":[-71.05421200000001,42.375089],"type":"Point"}
}