{
  "type": "Feature",
  "properties": {
    "addr:full":"84 Shirley Ave Revere MA 02151",
    "addr:housenumber":"84",
    "addr:postcode":"02151",
    "addr:street":"Shirley Ave",
    "iso:country":"US",
    "sg:address":"84 Shirley Ave",
    "sg:city":"Revere",
    "sg:classifiers":[
        {
            "category":"Personal",
            "subcategory":"Beauty Salon",
            "type":"Services"
        }
    ],
    "sg:phone":"+1 781 289 3834",
    "sg:postcode":"02151",
    "sg:province":"MA",
    "wof:name":"Kelly's Hair Salon",
    "wof:placetype":"venue"
},
  "geometry": {"coordinates":[-70.997311,42.408127],"type":"Point"}
}