{
  "type": "Feature",
  "properties": {
    "iso:country":"US",
    "sg:address":"10 Tremont St",
    "sg:city":"Braintree",
    "sg:classifiers":[
        {
            "category":"Government",
            "subcategory":"Office",
            "type":"Public Place"
        }
    ],
    "sg:phone":"+1 781 849 7808",
    "sg:postcode":"02184",
    "sg:province":"MA",
    "sg:tags":[
        "government-state",
        "government-united",
        "state"
    ],
    "wof:name":"Massachusetts Department Of Highway",
    "wof:placetype":"venue"
},
  "geometry": {"coordinates":[-71.00654299999999,42.202255],"type":"Point"}
}