{
  "type": "Feature",
  "properties": {
    "addr:full":"9 Prescott Street Brookline MA 02446",
    "addr:housenumber":"9",
    "addr:postcode":"02446",
    "addr:street":"Prescott Street",
    "iso:country":"US",
    "sg:address":"9 Prescott Street",
    "sg:city":"Brookline",
    "sg:classifiers":[
        {
            "category":"Education",
            "subcategory":"School",
            "type":"Public Place"
        }
    ],
    "sg:phone":"+1 617 731 5330",
    "sg:postcode":"02446",
    "sg:province":"MA",
    "sg:tags":[
        "high",
        "middle",
        "elementary"
    ],
    "wof:name":"New England Hebrew Academy",
    "wof:placetype":"venue"
},
  "geometry": {"coordinates":[-71.110107,42.348811],"type":"Point"}
}