{
  "type": "Feature",
  "properties": {
    "iso:country":"US",
    "sg:address":"920 Plymouth Ave",
    "sg:city":"Fall River",
    "sg:classifiers":[
        {
            "category":"Health Services",
            "subcategory":"Doctor",
            "type":"Services"
        }
    ],
    "sg:phone":"+1 508 672 6471",
    "sg:postcode":"02721",
    "sg:province":"MA",
    "sg:tags":[
        "dentist"
    ],
    "wof:name":"Dentistry With A Smile",
    "wof:placetype":"venue"
},
  "geometry": {"coordinates":[-71.158582,41.690591],"type":"Point"}
}