{
  "type": "Feature",
  "properties": {
    "iso:country":"US",
    "sg:address":"26 Everton St",
    "sg:city":"Boston",
    "sg:classifiers":[
        {
            "category":"Utilities",
            "type":"Services"
        }
    ],
    "sg:phone":"+1   ",
    "sg:postcode":"02121",
    "sg:province":"MA",
    "sg:tags":[
        "sanitary"
    ],
    "wof:name":"Msm Snow Plowing",
    "wof:placetype":"venue"
},
  "geometry": {"coordinates":[-71.07171099999999,42.304451],"type":"Point"}
}