{
  "type": "Feature",
  "properties": {
    "addr:full": "26 Everton St Boston MA 02121",
    "addr:housenumber": "26",
    "addr:postcode": "02121",
    "addr:street": "Everton St",
    "iso:country": "US",
    "sg:address": "26 Everton St",
    "sg:city": "Boston",
    "sg:classifiers": [
      {
        "category": "Utilities",
        "type": "Services"
      }
    ],
    "sg:phone": "+1   ",
    "sg:postcode": "02121",
    "sg:province": "MA",
    "sg:tags": [
      "sanitary"
    ],
    "wof:name": "Msm Snow Plowing",
    "wof:placetype": "venue"
  },
  "geometry": {"coordinates":[-71.071711,42.304451],"type":"Point"}
}
