{
  "type": "Feature",
  "properties": {
    "iso:country":"US",
    "sg:address":"30 Fairway Dr",
    "sg:city":"Longmeadow",
    "sg:classifiers":[
        {
            "category":"Arts & Performance",
            "subcategory":"Dance",
            "type":"Entertainment"
        }
    ],
    "sg:phone":"+1 413 567 7289",
    "sg:postcode":"01106",
    "sg:province":"MA",
    "sg:tags":[
        "instruction",
        "dancing"
    ],
    "wof:name":"New England Dance Promotions Inc",
    "wof:placetype":"venue"
},
  "geometry": {"coordinates":[-72.565403,42.035711],"type":"Point"}
}