{
  "type": "Feature",
  "properties": {
    "addr:full": "1696 Massachusetts Ave Cambridge MA 02138",
    "addr:housenumber": "1696",
    "addr:postcode": "02138",
    "addr:street": "Massachusetts Ave",
    "iso:country": "US",
    "sg:address": "1696 Massachusetts Ave",
    "sg:city": "Cambridge",
    "sg:classifiers": [
      {
        "category": "Real Estate",
        "subcategory": "Real Estate Agent",
        "type": "Services"
      }
    ],
    "sg:phone": "+1 617 497 8900",
    "sg:postcode": "02138",
    "sg:province": "MA",
    "wof:name": "Joe Kobialka Real Estate",
    "wof:placetype": "venue"
  },
  "geometry": {"coordinates":[-71.119739,42.382222],"type":"Point"}
}
