{
  "type": "Feature",
  "properties": {
    "addr:full": "13 Greenwood St Worcester MA 01607",
    "addr:housenumber": "13",
    "addr:postcode": "01607",
    "addr:street": "Greenwood St",
    "iso:country": "US",
    "sg:address": "13 Greenwood St",
    "sg:city": "Worcester",
    "sg:classifiers": [
      {
        "category": "Professional",
        "subcategory": "Art Services",
        "type": "Services"
      }
    ],
    "sg:phone": "+1 508 831 7744",
    "sg:postcode": "01607",
    "sg:province": "MA",
    "sg:tags": [
      "graphic",
      "designer"
    ],
    "wof:name": "Willie Rivers",
    "wof:placetype": "venue"
  },
  "geometry": {"coordinates":[-71.793732,42.23153],"type":"Point"}
}
