{
  "type": "Feature",
  "properties": {
    "iso:country":"US",
    "sg:address":"307 Westford St",
    "sg:city":"Lowell",
    "sg:classifiers":[
        {
            "category":"Travel",
            "subcategory":"Travel Agent",
            "type":"Entertainment"
        }
    ],
    "sg:phone":"+1 978 275 2809",
    "sg:postcode":"01851",
    "sg:province":"MA",
    "sg:tags":[
        "agency",
        "bureau"
    ],
    "wof:name":"Khmer Travel",
    "wof:placetype":"venue"
},
  "geometry": {"coordinates":[-71.327899,42.634981],"type":"Point"}
}