{
  "type": "Feature",
  "properties": {
    "iso:country":"US",
    "sg:address":"56 N County Rd",
    "sg:city":"Florida",
    "sg:classifiers":[
        {
            "category":"Education",
            "subcategory":"Library",
            "type":"Public Place"
        }
    ],
    "sg:phone":"+1 413 664 0153",
    "sg:postcode":"01247",
    "sg:province":"MA",
    "wof:name":"Florida Free Library",
    "wof:placetype":"venue"
},
  "geometry": {"coordinates":[-73.03248499999999,42.693064],"type":"Point"}
}