{
  "type": "Feature",
  "properties": {
    "addr:full": "594 Blue Hill Ave Dorchester MA 02121",
    "addr:housenumber": "594",
    "addr:postcode": "02121",
    "addr:street": "Blue Hill Ave",
    "iso:country": "US",
    "sg:address": "594 Blue Hill Ave",
    "sg:city": "Dorchester",
    "sg:classifiers": [
      {
        "category": "Shopping",
        "subcategory": "Clothing, Apparel, \u0026 Fashions",
        "type": "Retail Goods"
      }
    ],
    "sg:phone": "+1 617 427 8930",
    "sg:postcode": "02121",
    "sg:province": "MA",
    "sg:tags": [
      "tuxedo"
    ],
    "wof:name": "Allen Tuxedo",
    "wof:placetype": "venue"
  },
  "geometry": {"coordinates":[-71.084794,42.303948],"type":"Point"}
}
