{
  "type": "Feature",
  "properties": {
    "addr:full": "73 Barrett St Northampton MA 01060",
    "addr:housenumber": "73",
    "addr:postcode": "01060",
    "addr:street": "Barrett St",
    "iso:country": "US",
    "sg:address": "73 Barrett St",
    "sg:city": "Northampton",
    "sg:classifiers": [
      {
        "category": "Banks \u0026 Credit Unions",
        "subcategory": "Investment Brokerage",
        "type": "Services"
      }
    ],
    "sg:phone": "+1 413 586 1405",
    "sg:postcode": "01060",
    "sg:province": "MA",
    "sg:tags": [
      "trust"
    ],
    "wof:name": "Affordable Trust Fund",
    "wof:placetype": "venue"
  },
  "geometry": {"coordinates":[-72.640099,42.333771],"type":"Point"}
}
