{
  "type": "Feature",
  "properties": {
    "iso:country":"US",
    "sg:address":"85 Harvard St",
    "sg:city":"Boston",
    "sg:classifiers":[
        {
            "category":"Retail",
            "subcategory":"Laundry & Dry Cleaning",
            "type":"Services"
        }
    ],
    "sg:phone":"+1 617 232 1711",
    "sg:postcode":"02111",
    "sg:province":"MA",
    "sg:tags":[
        "garment",
        "commercial",
        "agent"
    ],
    "wof:name":"Sunflower Cleaners & Tailors",
    "wof:placetype":"venue"
},
  "geometry": {"coordinates":[-71.060807,42.349271],"type":"Point"}
}