{
  "type": "Feature",
  "properties": {
    "addr:full":"160 E Berkeley St Roxbury MA 02118",
    "addr:housenumber":"160",
    "addr:postcode":"02118",
    "addr:street":"E Berkeley St",
    "iso:country":"US",
    "sg:address":"160 E Berkeley St",
    "sg:city":"Roxbury",
    "sg:classifiers":[
        {
            "category":"Social Services",
            "subcategory":"Child Care",
            "type":"Services"
        },
        {
            "category":"Education",
            "subcategory":"Preschool",
            "type":"Public Place"
        },
        {
            "category":"Education",
            "subcategory":"School",
            "type":"Public Place"
        }
    ],
    "sg:phone":"+1 508 393 9496",
    "sg:postcode":"02118",
    "sg:province":"MA",
    "sg:tags":[
        "elementary",
        "day"
    ],
    "wof:name":"Kids Palace Day Care",
    "wof:placetype":"venue"
},
  "geometry": {"coordinates":[-71.06500200000001,42.3437],"type":"Point"}
}