{
  "type": "Feature",
  "properties": {
    "iso:country":"US",
    "sg:address":"405 Main St",
    "sg:city":"Indian Orchard",
    "sg:classifiers":[
        {
            "category":"Building & Trades",
            "subcategory":"Construction",
            "type":"Services"
        }
    ],
    "sg:phone":"+1   ",
    "sg:postcode":"01151",
    "sg:province":"MA",
    "sg:tags":[
        "excavation",
        "contractor"
    ],
    "wof:name":"Raymond P Desautels Excavating",
    "wof:placetype":"venue"
},
  "geometry": {"coordinates":[-72.489372,42.156609],"type":"Point"}
}