{
  "type": "Feature",
  "properties": {
    "iso:country":"US",
    "sg:address":"479 Broadway",
    "sg:city":"Chelsea",
    "sg:classifiers":[
        {
            "category":"Shopping",
            "subcategory":"Department Store",
            "type":"Retail Goods"
        }
    ],
    "sg:phone":"+1 617 884 7047",
    "sg:postcode":"02150",
    "sg:province":"MA",
    "wof:name":"Tienda Lolita Dollar Yma",
    "wof:placetype":"venue"
},
  "geometry": {"coordinates":[-71.03343599999999,42.392993],"type":"Point"}
}