{
  "type": "Feature",
  "properties": {
    "iso:country":"US",
    "sg:address":"67 Hunt St",
    "sg:city":"Agawam",
    "sg:classifiers":[
        {
            "category":"Social Services",
            "subcategory":"Job Training",
            "type":"Services"
        }
    ],
    "sg:phone":"+1 413 789 6400",
    "sg:postcode":"01001",
    "sg:province":"MA",
    "sg:tags":[
        "employment"
    ],
    "sg:website":"www.eane.org",
    "wof:name":"Employers Assn Of Ne",
    "wof:placetype":"venue"
},
  "geometry": {"coordinates":[-72.59304,42.082185],"type":"Point"}
}