{
  "type": "Feature",
  "properties": {
    "addr:full": "47 Fairgrounds Rd Nantucket MA 02554",
    "addr:housenumber": "47",
    "addr:postcode": "02554",
    "addr:street": "Fairgrounds Rd",
    "iso:country": "US",
    "sg:address": "47 Fairgrounds Rd",
    "sg:city": "Nantucket",
    "sg:classifiers": [
      {
        "category": "Building \u0026 Trades",
        "subcategory": "Construction",
        "type": "Services"
      }
    ],
    "sg:phone": "+1 508 228 4614",
    "sg:postcode": "02554",
    "sg:province": "MA",
    "sg:tags": [
      "wallpaper"
    ],
    "wof:name": "Elwell Ellen J Wallpapering",
    "wof:placetype": "venue"
  },
  "geometry": {"coordinates":[-70.092256,41.264227],"type":"Point"}
}
