{
  "type": "Feature",
  "properties": {
    "iso:country":"US",
    "sg:address":"50 Northridge Dr",
    "sg:city":"East Bridgewater",
    "sg:classifiers":[
        {
            "category":"Building & Trades",
            "subcategory":"Electrical",
            "type":"Services"
        }
    ],
    "sg:phone":"+1   ",
    "sg:postcode":"02333",
    "sg:province":"MA",
    "sg:tags":[
        "electrical",
        "contractor"
    ],
    "wof:name":"Marc Shirey Electric",
    "wof:placetype":"venue"
},
  "geometry": {"coordinates":[-70.965947,42.052703],"type":"Point"}
}