{
  "type": "Feature",
  "properties": {
    "addr:full": "50 Northridge Dr East Bridgewater MA 02333",
    "addr:housenumber": "50",
    "addr:postcode": "02333",
    "addr:street": "Northridge Dr",
    "iso:country": "US",
    "sg:address": "50 Northridge Dr",
    "sg:city": "East Bridgewater",
    "sg:classifiers": [
      {
        "category": "Building \u0026 Trades",
        "subcategory": "Electrical",
        "type": "Services"
      }
    ],
    "sg:phone": "+1   ",
    "sg:postcode": "02333",
    "sg:province": "MA",
    "sg:tags": [
      "electrical",
      "contractor"
    ],
    "wof:name": "Marc Shirey Electric",
    "wof:placetype": "venue"
  },
  "geometry": {"coordinates":[-70.965947,42.052703],"type":"Point"}
}
