{
  "type": "Feature",
  "properties": {
    "iso:country":"US",
    "sg:address":"425 Washington Street",
    "sg:city":"Brighton",
    "sg:classifiers":[
        {
            "category":"Shopping",
            "subcategory":"Florist",
            "type":"Retail Goods"
        }
    ],
    "sg:phone":"+1 617 254 1130",
    "sg:postcode":"02135",
    "sg:province":"MA",
    "wof:name":"Minihane's Flower & Garden Shop",
    "wof:placetype":"venue"
},
  "geometry": {"coordinates":[-71.149697,42.34644],"type":"Point"}
}