{
  "type": "Feature",
  "properties": {
    "iso:country":"US",
    "sg:address":"118 Southfield Dr",
    "sg:city":"Brockton",
    "sg:classifiers":[
        {
            "category":"Shopping",
            "subcategory":"Gifts & Souvenirs",
            "type":"Retail Goods"
        }
    ],
    "sg:phone":"+1 508 583 4635",
    "sg:postcode":"02302",
    "sg:province":"MA",
    "sg:tags":[
        "shop"
    ],
    "wof:name":"Alkebulan Associates Inc",
    "wof:placetype":"venue"
},
  "geometry": {"coordinates":[-70.991608,42.060223],"type":"Point"}
}