{
  "type": "Feature",
  "properties": {
    "addr:full": "10 Lee St Lancaster MA 01523",
    "addr:housenumber": "10",
    "addr:postcode": "01523",
    "addr:street": "Lee St",
    "iso:country": "US",
    "sg:address": "10 Lee St",
    "sg:city": "Lancaster",
    "sg:classifiers": [
      {
        "category": "Shopping",
        "subcategory": "Department Store",
        "type": "Retail Goods"
      }
    ],
    "sg:phone": "+1   ",
    "sg:postcode": "01523",
    "sg:province": "MA",
    "wof:name": "Pinnacle Marketing Group New E",
    "wof:placetype": "venue"
  },
  "geometry": {"coordinates":[-71.674714,42.436997],"type":"Point"}
}
