{
  "type": "Feature",
  "properties": {
    "iso:country":"US",
    "sg:address":"10 Lee St",
    "sg:city":"Lancaster",
    "sg:classifiers":[
        {
            "category":"Shopping",
            "subcategory":"Department Store",
            "type":"Retail Goods"
        }
    ],
    "sg:phone":"+1   ",
    "sg:postcode":"01523",
    "sg:province":"MA",
    "wof:name":"Pinnacle Marketing Group New E",
    "wof:placetype":"venue"
},
  "geometry": {"coordinates":[-71.67471399999999,42.436997],"type":"Point"}
}