{
  "type": "Feature",
  "properties": {
    "iso:country":"US",
    "sg:address":"602 State Hwy 6 Alt",
    "sg:city":"East Sandwich",
    "sg:classifiers":[
        {
            "category":"Shopping",
            "subcategory":"Crafts & Fabrics",
            "type":"Retail Goods"
        }
    ],
    "sg:phone":"+1 508 888 2195",
    "sg:postcode":"02537",
    "sg:province":"MA",
    "sg:tags":[
        "yarn"
    ],
    "wof:name":"Yarn Barn",
    "wof:placetype":"venue"
},
  "geometry": {"coordinates":[-70.48978099999999,41.739174],"type":"Point"}
}