{
  "type": "Feature",
  "properties": {
    "addr:full": "248 Old Windsor Rd Dalton MA 01226",
    "addr:housenumber": "248",
    "addr:postcode": "01226",
    "addr:street": "Old Windsor Rd",
    "iso:country": "US",
    "sg:address": "248 Old Windsor Rd",
    "sg:city": "Dalton",
    "sg:classifiers": [
      {
        "category": "Professional",
        "type": "Services"
      }
    ],
    "sg:phone": "+1   ",
    "sg:postcode": "01226",
    "sg:province": "MA",
    "wof:name": "Airwolf Homepage",
    "wof:placetype": "venue"
  },
  "geometry": {"coordinates":[-73.13769,42.474369],"type":"Point"}
}
