{
  "type": "Feature",
  "properties": {
    "iso:country":"US",
    "sg:address":"248 Old Windsor Rd",
    "sg:city":"Dalton",
    "sg:classifiers":[
        {
            "category":"Professional",
            "type":"Services"
        }
    ],
    "sg:phone":"+1   ",
    "sg:postcode":"01226",
    "sg:province":"MA",
    "wof:name":"Airwolf Homepage",
    "wof:placetype":"venue"
},
  "geometry": {"coordinates":[-73.13769000000001,42.474369],"type":"Point"}
}