{
  "type": "Feature",
  "properties": {
    "addr:full": "330 Whitney Ave Holyoke MA 01040",
    "addr:housenumber": "330",
    "addr:postcode": "01040",
    "addr:street": "Whitney Ave",
    "iso:country": "US",
    "sg:address": "330 Whitney Ave",
    "sg:city": "Holyoke",
    "sg:classifiers": [
      {
        "category": "Insurance",
        "subcategory": "Insurance Agent",
        "type": "Services"
      }
    ],
    "sg:phone": "+1 413 532 8400",
    "sg:postcode": "01040",
    "sg:province": "MA",
    "wof:name": "Woodbrook Insurance",
    "wof:placetype": "venue"
  },
  "geometry": {"coordinates":[-72.642676,42.164144],"type":"Point"}
}
