{
  "type": "Feature",
  "properties": {
    "iso:country":"US",
    "sg:address":"330 Whitney Ave",
    "sg:city":"Holyoke",
    "sg:classifiers":[
        {
            "category":"Insurance",
            "subcategory":"Insurance Agent",
            "type":"Services"
        }
    ],
    "sg:phone":"+1 413 532 8400",
    "sg:postcode":"01040",
    "sg:province":"MA",
    "wof:name":"Woodbrook Insurance",
    "wof:placetype":"venue"
},
  "geometry": {"coordinates":[-72.64267599999999,42.164144],"type":"Point"}
}