{
  "type": "Feature",
  "properties": {
    "addr:full": "423 Lewis Wharf Boston MA 02110",
    "addr:housenumber": "423",
    "addr:postcode": "02110",
    "addr:street": "Lewis Wharf",
    "iso:country": "US",
    "sg:address": "423 Lewis Wharf",
    "sg:city": "Boston",
    "sg:classifiers": [
      {
        "category": "Professional",
        "type": "Services"
      }
    ],
    "sg:phone": "+1 617 227 2480",
    "sg:postcode": "02110",
    "sg:province": "MA",
    "sg:tags": [
      "chemical",
      "equipment",
      "plant",
      "supply"
    ],
    "sg:website": "http://www.chargedinjection.com",
    "wof:name": "Charge Injection Technologies, Inc.",
    "wof:placetype": "venue"
  },
  "geometry": {"coordinates":[-71.050542,42.363548],"type":"Point"}
}
