{
  "type": "Feature",
  "properties": {
    "iso:country":"US",
    "sg:address":"222 3rd St",
    "sg:city":"Cambridge",
    "sg:classifiers":[
        {
            "category":"Professional",
            "subcategory":"Management & Consulting",
            "type":"Services"
        }
    ],
    "sg:phone":"+1 617 871 6396",
    "sg:postcode":"02141",
    "sg:province":"MA",
    "sg:tags":[
        "consultant",
        "publishing"
    ],
    "sg:website":"www.octavodesign.com",
    "wof:name":"Octavo",
    "wof:placetype":"venue"
},
  "geometry": {"coordinates":[-71.081109,42.367675],"type":"Point"}
}