{
  "type": "Feature",
  "properties": {
    "addr:full":"1568 Shawmut Ave New Bedford MA 02746",
    "addr:housenumber":"1568",
    "addr:postcode":"02746",
    "addr:street":"Shawmut Ave",
    "iso:country":"US",
    "sg:address":"1568 Shawmut Ave",
    "sg:city":"New Bedford",
    "sg:classifiers":[
        {
            "category":"Utilities",
            "subcategory":"Fuel Oil & Lpg",
            "type":"Services"
        }
    ],
    "sg:phone":"+1 508 994 5261",
    "sg:postcode":"02746",
    "sg:province":"MA",
    "sg:tags":[
        "propane",
        "gas"
    ],
    "wof:name":"Ameri Gas Propane LP",
    "wof:placetype":"venue"
},
  "geometry": {"coordinates":[-70.959003,41.672776],"type":"Point"}
}