{
  "type": "Feature",
  "properties": {
    "addr:full": "22 Oak St Hyde Park MA 02136",
    "addr:housenumber": "22",
    "addr:postcode": "02136",
    "addr:street": "Oak St",
    "iso:country": "US",
    "ovtr:label": "Carroll-Thomas Funeral Home, 22 Oak St Hyde Park MA US",
    "ovtr:similarity": 2.7523770332336426,
    "sg:address": "22 Oak St",
    "sg:city": "Hyde Park",
    "sg:classifiers": [
      {
        "category": "Retail",
        "subcategory": "Funeral Services",
        "type": "Services"
      }
    ],
    "sg:phone": "+1 617 361 0380",
    "sg:postcode": "02136",
    "sg:province": "MA",
    "sg:tags": [
      "director"
    ],
    "wof:name": "Carroll-Thomas Funeral Home",
    "wof:placetype": "venue"
  },
  "geometry": {"coordinates":[-71.123909,42.255183],"type":"Point"}
}
