{
  "type": "Feature",
  "properties": {
    "iso:country":"US",
    "sg:address":"22 Oak St",
    "sg:city":"Hyde Park",
    "sg:classifiers":[
        {
            "category":"Retail",
            "subcategory":"Funeral Services",
            "type":"Services"
        }
    ],
    "sg:phone":"+1 617 361 0380",
    "sg:postcode":"02136",
    "sg:province":"MA",
    "sg:tags":[
        "director"
    ],
    "wof:name":"Carroll-Thomas Funeral Home",
    "wof:placetype":"venue"
},
  "geometry": {"coordinates":[-71.123909,42.255183],"type":"Point"}
}