{
  "type": "Feature",
  "properties": {
    "iso:country":"US",
    "sg:address":"10 Quarry St",
    "sg:city":"Great Barrington",
    "sg:classifiers":[
        {
            "category":"Shopping",
            "type":"Retail Goods"
        }
    ],
    "sg:phone":"+1 413 528 0859",
    "sg:postcode":"01230",
    "sg:province":"MA",
    "sg:tags":[
        "monument"
    ],
    "wof:name":"Arienti Monument Co",
    "wof:placetype":"venue"
},
  "geometry": {"coordinates":[-73.355886,42.195405],"type":"Point"}
}