{
  "type": "Feature",
  "properties": {
    "iso:country":"US",
    "sg:address":"170 Middlesex St",
    "sg:city":"North Chelmsford",
    "sg:classifiers":[
        {
            "category":"Autos & Motor Vehicles",
            "subcategory":"Automobile Sales",
            "type":"Retail Goods"
        }
    ],
    "sg:phone":"+1 978 251 8182",
    "sg:postcode":"01863",
    "sg:province":"MA",
    "wof:name":"Ntc Automotive",
    "wof:placetype":"venue"
},
  "geometry": {"coordinates":[-71.365481,42.635556],"type":"Point"}
}