{
  "type": "Feature",
  "properties": {
    "iso:country":"US",
    "sg:address":"30 Gardner St",
    "sg:city":"Salem",
    "sg:classifiers":[
        {
            "category":"Building & Trades",
            "subcategory":"Plumbing",
            "type":"Services"
        }
    ],
    "sg:phone":"+1 978 744 4149",
    "sg:postcode":"01970",
    "sg:province":"MA",
    "sg:tags":[
        "plumber",
        "industrial",
        "contractors-commercial"
    ],
    "wof:name":"Thomas Gagnon",
    "wof:placetype":"venue"
},
  "geometry": {"coordinates":[-70.894837,42.513495],"type":"Point"}
}