{
  "type": "Feature",
  "properties": {
    "addr:full": "20 Wiltshire Rd Brighton MA 02135",
    "addr:housenumber": "20",
    "addr:postcode": "02135",
    "addr:street": "Wiltshire Rd",
    "iso:country": "US",
    "sg:address": "20 Wiltshire Rd",
    "sg:city": "Brighton",
    "sg:classifiers": [
      {
        "category": "Travel",
        "subcategory": "Travel Agent",
        "type": "Entertainment"
      }
    ],
    "sg:phone": "+1 617 782 0033",
    "sg:postcode": "02135",
    "sg:province": "MA",
    "sg:tags": [
      "agency",
      "bureau"
    ],
    "wof:name": "Travel Dynamics",
    "wof:placetype": "venue"
  },
  "geometry": {"coordinates":[-71.154557,42.343466],"type":"Point"}
}
