{
  "type": "Feature",
  "properties": {
    "iso:country":"US",
    "sg:address":"11 Lincoln St",
    "sg:city":"Plymouth",
    "sg:classifiers":[
        {
            "category":"Government",
            "subcategory":"Office",
            "type":"Public Place"
        }
    ],
    "sg:phone":"+1   ",
    "sg:postcode":"02360",
    "sg:province":"MA",
    "sg:tags":[
        "department",
        "veteran"
    ],
    "wof:name":"Plymouth Veterans Department",
    "wof:placetype":"venue"
},
  "geometry": {"coordinates":[-70.65877399999999,41.953934],"type":"Point"}
}