{
  "type": "Feature",
  "properties": {
    "addr:full":"89 Hartford Ave E Mendon MA 01756",
    "addr:housenumber":"89",
    "addr:postcode":"01756",
    "addr:street":"Hartford Ave E",
    "iso:country":"US",
    "sg:address":"89 Hartford Ave E",
    "sg:city":"Mendon",
    "sg:classifiers":[
        {
            "category":"Home & Garden",
            "subcategory":"Furniture",
            "type":"Retail Goods"
        }
    ],
    "sg:phone":"+1 508 634 2004",
    "sg:postcode":"01756",
    "sg:province":"MA",
    "sg:tags":[
        "cabinet"
    ],
    "wof:name":"Heartwood Cabinet Makers LLC",
    "wof:placetype":"venue"
},
  "geometry": {"coordinates":[-71.517235,42.09934],"type":"Point"}
}