{
  "type": "Feature",
  "properties": {
    "addr:full": "210 Linden St Holyoke MA 01040",
    "addr:housenumber": "210",
    "addr:postcode": "01040",
    "addr:street": "Linden St",
    "iso:country": "US",
    "ovtr:label": "Sanctuary Animal Clinic, 210 Linden St Holyoke MA US",
    "ovtr:similarity": 2.0916759967803955,
    "sg:address": "210 Linden St",
    "sg:city": "Holyoke",
    "sg:classifiers": [
      {
        "category": "Retail",
        "subcategory": "Veterinary Services",
        "type": "Services"
      }
    ],
    "sg:phone": "+1 413 532 2175",
    "sg:postcode": "01040",
    "sg:province": "MA",
    "sg:tags": [
      "veterinarian"
    ],
    "wof:name": "Sanctuary Animal Clinic",
    "wof:placetype": "venue"
  },
  "geometry": {"coordinates":[-72.61805,42.207498],"type":"Point"}
}
