{
  "type": "Feature",
  "properties": {
    "iso:country":"US",
    "sg:address":"210 Linden St",
    "sg:city":"Holyoke",
    "sg:classifiers":[
        {
            "category":"Retail",
            "subcategory":"Veterinary Services",
            "type":"Services"
        }
    ],
    "sg:phone":"+1 413 532 2175",
    "sg:postcode":"01040",
    "sg:province":"MA",
    "sg:tags":[
        "veterinarian"
    ],
    "wof:name":"Sanctuary Animal Clinic",
    "wof:placetype":"venue"
},
  "geometry": {"coordinates":[-72.61805,42.207498],"type":"Point"}
}