{
  "type": "Feature",
  "properties": {
    "addr:full": "505 East St Ste 1 Pittsfield MA 01201",
    "addr:housenumber": "505",
    "addr:postcode": "01201",
    "addr:street": "East St Ste 1",
    "iso:country": "US",
    "sg:address": "505 East St Ste 1",
    "sg:city": "Pittsfield",
    "sg:classifiers": [
      {
        "category": "Restaurant",
        "type": "Food \u0026 Drink"
      }
    ],
    "sg:phone": "+1 413 499 1180",
    "sg:postcode": "01201",
    "sg:province": "MA",
    "wof:name": "Daddyos Diner",
    "wof:placetype": "venue"
  },
  "geometry": {"coordinates":[-73.245209,42.44702],"type":"Point"}
}
