{
  "type": "Feature",
  "properties": {
    "iso:country":"US",
    "sg:address":"505 East St Ste 1",
    "sg:city":"Pittsfield",
    "sg:classifiers":[
        {
            "category":"Restaurant",
            "type":"Food & Drink"
        }
    ],
    "sg:phone":"+1 413 499 1180",
    "sg:postcode":"01201",
    "sg:province":"MA",
    "wof:name":"Daddyos Diner",
    "wof:placetype":"venue"
},
  "geometry": {"coordinates":[-73.245209,42.44702],"type":"Point"}
}