{
  "type": "Feature",
  "properties": {
    "iso:country":"US",
    "sg:address":"182 N Main St",
    "sg:city":"Brockton",
    "sg:classifiers":[
        {
            "category":"Professional",
            "subcategory":"Business Services",
            "type":"Services"
        }
    ],
    "sg:phone":"+1 508 580 2811",
    "sg:postcode":"02301",
    "sg:province":"MA",
    "sg:tags":[
        "notary"
    ],
    "wof:name":"Victor Rosario",
    "wof:placetype":"venue"
},
  "geometry": {"coordinates":[-71.0194,42.089767],"type":"Point"}
}