{
  "type": "Feature",
  "properties": {
    "addr:full": "9 Somerset Ave Winthrop MA 02152",
    "addr:housenumber": "9",
    "addr:postcode": "02152",
    "addr:street": "Somerset Ave",
    "iso:country": "US",
    "sg:address": "9 Somerset Ave",
    "sg:city": "Winthrop",
    "sg:classifiers": [
      {
        "category": "Personal",
        "subcategory": "Beauty Salon",
        "type": "Services"
      }
    ],
    "sg:phone": "+1 617 846 1232",
    "sg:postcode": "02152",
    "sg:province": "MA",
    "wof:name": "Special F/X",
    "wof:placetype": "venue"
  },
  "geometry": {"coordinates":[-70.987087,42.374792],"type":"Point"}
}
