{
  "type": "Feature",
  "properties": {
    "addr:full": "93 E Haverhill St Lawrence MA 01841",
    "addr:housenumber": "93",
    "addr:postcode": "01841",
    "addr:street": "E Haverhill St",
    "iso:country": "US",
    "sg:address": "93 E Haverhill St",
    "sg:city": "Lawrence",
    "sg:classifiers": [
      {
        "category": "Organizations",
        "subcategory": "Religious Organization",
        "type": "Services"
      }
    ],
    "sg:phone": "+1 978 683 4869",
    "sg:postcode": "01841",
    "sg:province": "MA",
    "sg:tags": [
      "church"
    ],
    "wof:name": "Christian Fellowship Chr",
    "wof:placetype": "venue"
  },
  "geometry": {"coordinates":[-71.155628,42.716364],"type":"Point"}
}
