{
  "type": "Feature",
  "properties": {
    "iso:country":"US",
    "sg:address":"50 Weir St",
    "sg:city":"Taunton",
    "sg:classifiers":[
        {
            "category":"Shopping",
            "subcategory":"Clothing, Apparel, & Fashions",
            "type":"Retail Goods"
        }
    ],
    "sg:phone":"+1 508 824 9521",
    "sg:postcode":"02780",
    "sg:province":"MA",
    "wof:name":"Jackie's Fashions",
    "wof:placetype":"venue"
},
  "geometry": {"coordinates":[-71.092456,41.901066],"type":"Point"}
}