{
  "type": "Feature",
  "properties": {
    "addr:full":"8 Baron Park Ln Burlington MA 01803",
    "addr:housenumber":"8",
    "addr:postcode":"01803",
    "addr:street":"Baron Park Ln",
    "iso:country":"US",
    "sg:address":"8 Baron Park Ln",
    "sg:city":"Burlington",
    "sg:classifiers":[
        {
            "category":"Real Estate",
            "subcategory":"Real Estate Operator",
            "type":"Services"
        }
    ],
    "sg:phone":"+1 781 272 5037",
    "sg:postcode":"01803",
    "sg:province":"MA",
    "sg:tags":[
        "apartment"
    ],
    "wof:name":"Kosow Management Co",
    "wof:placetype":"venue"
},
  "geometry": {"coordinates":[-71.223838,42.499377],"type":"Point"}
}