{
  "type": "Feature",
  "properties": {
    "iso:country":"US",
    "sg:address":"457 Worcester St",
    "sg:city":"Wellesley",
    "sg:classifiers":[
        {
            "category":"Government",
            "subcategory":"Fire Station",
            "type":"Public Place"
        }
    ],
    "sg:phone":"+1 781 235 1300",
    "sg:postcode":"02481",
    "sg:province":"MA",
    "sg:tags":[
        "department"
    ],
    "wof:name":"Wellesley Fire Dept",
    "wof:placetype":"venue"
},
  "geometry": {"coordinates":[-71.272352,42.314324],"type":"Point"}
}