{
  "type": "Feature",
  "properties": {
    "addr:full": "243 Charles St Boston MA 02114",
    "addr:housenumber": "243",
    "addr:postcode": "02114",
    "addr:street": "Charles St",
    "iso:country": "US",
    "sg:address": "243 Charles St",
    "sg:city": "Boston",
    "sg:classifiers": [
      {
        "category": "Health Services",
        "subcategory": "Doctor",
        "type": "Services"
      },
      {
        "category": "Health Services",
        "subcategory": "Health Practitioner",
        "type": "Services"
      }
    ],
    "sg:phone": "+1 617 573 3124",
    "sg:postcode": "02114",
    "sg:province": "MA",
    "sg:tags": [
      "physician",
      "surgeon",
      "surgeons",
      "ophthalmology"
    ],
    "wof:name": "Thaddeus P Dryja",
    "wof:placetype": "venue"
  },
  "geometry": {"coordinates":[-71.070807,42.362145],"type":"Point"}
}
