{
  "type": "Feature",
  "properties": {
    "iso:country":"US",
    "sg:address":"110 Lake Shore Dr",
    "sg:city":"Chatham",
    "sg:classifiers":[
        {
            "category":"Health Services",
            "subcategory":"Health Practitioner",
            "type":"Services"
        }
    ],
    "sg:phone":"+1   ",
    "sg:postcode":"02633",
    "sg:province":"MA",
    "sg:tags":[
        "personal"
    ],
    "wof:name":"Jensen Marilyn B Rd",
    "wof:placetype":"venue"
},
  "geometry": {"coordinates":[-69.984189,41.69674],"type":"Point"}
}