{
  "type": "Feature",
  "properties": {
    "iso:country":"US",
    "sg:address":"138 Donald Ave",
    "sg:city":"Somerset",
    "sg:classifiers":[
        {
            "category":"Marine",
            "type":"Transportation"
        }
    ],
    "sg:phone":"+1 508 673 3380",
    "sg:postcode":"02726",
    "sg:province":"MA",
    "sg:tags":[
        "towing"
    ],
    "wof:name":"Marine Dynamics Inc",
    "wof:placetype":"venue"
},
  "geometry": {"coordinates":[-71.136653,41.757508],"type":"Point"}
}