{
  "type": "Feature",
  "properties": {
    "iso:country":"US",
    "sg:address":"18 Main St",
    "sg:city":"Hatfield",
    "sg:classifiers":[
        {
            "category":"Professional",
            "subcategory":"Art Services",
            "type":"Services"
        }
    ],
    "sg:phone":"+1 413 247 3023",
    "sg:postcode":"01038",
    "sg:province":"MA",
    "sg:tags":[
        "designer",
        "display",
        "producer"
    ],
    "wof:name":"Susannah Auferoth Design",
    "wof:placetype":"venue"
},
  "geometry": {"coordinates":[-72.597084,42.367671],"type":"Point"}
}