{
  "type": "Feature",
  "properties": {
    "iso:country":"US",
    "sg:address":"511 Main Street",
    "sg:city":"Medfield",
    "sg:classifiers":[
        {
            "category":"Building & Trades",
            "subcategory":"Construction",
            "type":"Services"
        }
    ],
    "sg:phone":"+1 508 359 7904",
    "sg:postcode":"02052",
    "sg:province":"MA",
    "sg:tags":[
        "restoration",
        "preservation"
    ],
    "wof:name":"Mitchell Construction Group",
    "wof:placetype":"venue"
},
  "geometry": {"coordinates":[-71.30703699999999,42.186081],"type":"Point"}
}