{
  "type": "Feature",
  "properties": {
    "addr:full": "511 Main Street Medfield MA 02052",
    "addr:housenumber": "511",
    "addr:postcode": "02052",
    "addr:street": "Main Street",
    "iso:country": "US",
    "ovtr:label": "Mitchell Construction Group, 511 Main St Medfield MA US",
    "ovtr:similarity": 3.3202099800109863,
    "sg:address": "511 Main Street",
    "sg:city": "Medfield",
    "sg:classifiers": [
      {
        "category": "Building \u0026 Trades",
        "subcategory": "Construction",
        "type": "Services"
      }
    ],
    "sg:phone": "+1 508 359 7904",
    "sg:postcode": "02052",
    "sg:province": "MA",
    "sg:tags": [
      "restoration",
      "preservation"
    ],
    "wof:name": "Mitchell Construction Group",
    "wof:placetype": "venue"
  },
  "geometry": {"coordinates":[-71.307037,42.186081],"type":"Point"}
}
