{
  "type": "Feature",
  "properties": {
    "addr:full": "400 Atlantic Ave Boston MA 02110",
    "addr:housenumber": "400",
    "addr:postcode": "02110",
    "addr:street": "Atlantic Ave",
    "iso:country": "US",
    "sg:address": "400 Atlantic Ave",
    "sg:city": "Boston",
    "sg:classifiers": [
      {
        "category": "Professional",
        "subcategory": "Lawyer \u0026 Legal Services",
        "type": "Services"
      }
    ],
    "sg:phone": "+1   ",
    "sg:postcode": "02110",
    "sg:province": "MA",
    "wof:name": "Robert P Goldman",
    "wof:placetype": "venue"
  },
  "geometry": {"coordinates":[-71.050684,42.35603],"type":"Point"}
}
