{
  "type": "Feature",
  "properties": {
    "iso:country":"US",
    "sg:address":"525 Broadway",
    "sg:city":"Lawrence",
    "sg:classifiers":[
        {
            "category":"Personal",
            "subcategory":"Beauty Salon",
            "type":"Services"
        }
    ],
    "sg:phone":"+1 978 975 8750",
    "sg:postcode":"01841",
    "sg:province":"MA",
    "sg:tags":[
        "shop"
    ],
    "wof:name":"Corte Tropical Beauty Salon",
    "wof:placetype":"venue"
},
  "geometry": {"coordinates":[-71.176237,42.714591],"type":"Point"}
}