{
  "type": "Feature",
  "properties": {
    "addr:full": "273 Hayden Rowe St Hopkinton MA 01748",
    "addr:housenumber": "273",
    "addr:postcode": "01748",
    "addr:street": "Hayden Rowe St",
    "iso:country": "US",
    "sg:address": "273 Hayden Rowe St",
    "sg:city": "Hopkinton",
    "sg:classifiers": [
      {
        "category": "Building \u0026 Trades",
        "subcategory": "Construction",
        "type": "Services"
      }
    ],
    "sg:phone": "+1 508 435 0205",
    "sg:postcode": "01748",
    "sg:province": "MA",
    "sg:tags": [
      "project"
    ],
    "wof:name": "Gateway Homes LTD",
    "wof:placetype": "venue"
  },
  "geometry": {"coordinates":[-71.504495,42.195949],"type":"Point"}
}
