{
  "type": "Feature",
  "properties": {
    "iso:country":"US",
    "sg:address":"273 Hayden Rowe St",
    "sg:city":"Hopkinton",
    "sg:classifiers":[
        {
            "category":"Building & Trades",
            "subcategory":"Construction",
            "type":"Services"
        }
    ],
    "sg:phone":"+1 508 435 0205",
    "sg:postcode":"01748",
    "sg:province":"MA",
    "sg:tags":[
        "project"
    ],
    "wof:name":"Gateway Homes LTD",
    "wof:placetype":"venue"
},
  "geometry": {"coordinates":[-71.50449500000001,42.195949],"type":"Point"}
}