{
  "type": "Feature",
  "properties": {
    "addr:full": "4 Bennett St Woburn MA 01801",
    "addr:housenumber": "4",
    "addr:postcode": "01801",
    "addr:street": "Bennett St",
    "iso:country": "US",
    "sg:address": "4 Bennett St",
    "sg:city": "Woburn",
    "sg:classifiers": [
      {
        "category": "Professional",
        "subcategory": "Lawyer \u0026 Legal Services",
        "type": "Services"
      }
    ],
    "sg:phone": "+1 781 933 5070",
    "sg:postcode": "01801",
    "sg:province": "MA",
    "sg:tags": [
      "attorney"
    ],
    "wof:name": "Lawton \u0026 Lawton Attys",
    "wof:placetype": "venue"
  },
  "geometry": {"coordinates":[-71.1539,42.478401],"type":"Point"}
}
