{
  "type": "Feature",
  "properties": {
    "iso:country":"US",
    "sg:address":"200 Research Dr",
    "sg:city":"Wilmington",
    "sg:classifiers":[
        {
            "category":"Shopping",
            "subcategory":"Computers & Home Electronics",
            "type":"Retail Goods"
        }
    ],
    "sg:phone":"+1 978 657 5170",
    "sg:postcode":"01887",
    "sg:province":"MA",
    "sg:tags":[
        "equipment",
        "electronic",
        "supply"
    ],
    "wof:name":"Anthem Electronics",
    "wof:placetype":"venue"
},
  "geometry": {"coordinates":[-71.15631399999999,42.604065],"type":"Point"}
}