{
  "type": "Feature",
  "properties": {
    "addr:full":"249 Main St Townsend MA 01469",
    "addr:housenumber":"249",
    "addr:postcode":"01469",
    "addr:street":"Main St",
    "iso:country":"US",
    "sg:address":"249 Main St",
    "sg:city":"Townsend",
    "sg:classifiers":[
        {
            "category":"Personal",
            "type":"Services"
        },
        {
            "category":"Shopping",
            "subcategory":"Clothing, Apparel, & Fashions",
            "type":"Retail Goods"
        }
    ],
    "sg:phone":"+1 978 597 6102",
    "sg:postcode":"01469",
    "sg:province":"MA",
    "sg:tags":[
        "theatrical",
        "used",
        "costume",
        "merchandise"
    ],
    "wof:name":"Uncommon Costume & Vintage Wr",
    "wof:placetype":"venue"
},
  "geometry": {"coordinates":[-71.704728,42.666413],"type":"Point"}
}