{
  "type": "Feature",
  "properties": {
    "iso:country":"US",
    "sg:address":"96 Court St",
    "sg:city":"Plymouth",
    "sg:classifiers":[
        {
            "category":"Professional",
            "subcategory":"Lawyer & Legal Services",
            "type":"Services"
        }
    ],
    "sg:phone":"+1 508 746 0481",
    "sg:postcode":"02360",
    "sg:province":"MA",
    "sg:tags":[
        "attorney"
    ],
    "wof:name":"Michael P Vidette Jr",
    "wof:placetype":"venue"
},
  "geometry": {"coordinates":[-70.669507,41.959658],"type":"Point"}
}