{
  "type": "Feature",
  "properties": {
    "iso:country":"US",
    "sg:address":"702 Broadway",
    "sg:city":"Everett",
    "sg:classifiers":[
        {
            "category":"Restaurant",
            "type":"Food & Drink"
        }
    ],
    "sg:phone":"+1 617 387 1581",
    "sg:postcode":"02149",
    "sg:province":"MA",
    "sg:tags":[
        "american",
        "latin"
    ],
    "wof:name":"Carnival Latino Restaurant",
    "wof:placetype":"venue"
},
  "geometry": {"coordinates":[-71.048883,42.414578],"type":"Point"}
}