{
  "type": "Feature",
  "properties": {
    "iso:country":"US",
    "sg:address":"19 Cheney Pond Rd",
    "sg:city":"Medfield",
    "sg:classifiers":[
        {
            "category":"Professional",
            "subcategory":"Management & Consulting",
            "type":"Services"
        }
    ],
    "sg:phone":"+1   ",
    "sg:postcode":"02052",
    "sg:province":"MA",
    "wof:name":"Pendleton Associates Inc",
    "wof:placetype":"venue"
},
  "geometry": {"coordinates":[-71.29042200000001,42.195753],"type":"Point"}
}