{
  "type": "Feature",
  "properties": {
    "addr:full": "1376 Bridge St South Yarmouth MA 02664",
    "addr:housenumber": "1376",
    "addr:postcode": "02664",
    "addr:street": "Bridge St",
    "iso:country": "US",
    "sg:address": "1376 Bridge St",
    "sg:city": "South Yarmouth",
    "sg:classifiers": [
      {
        "category": "Travel",
        "subcategory": "Hotels \u0026 Motels",
        "type": "Entertainment"
      }
    ],
    "sg:phone": "+1 508 398 2253",
    "sg:postcode": "02664",
    "sg:province": "MA",
    "wof:name": "Bass River Jolly Captain Condo",
    "wof:placetype": "venue"
  },
  "geometry": {"coordinates":[-70.183319,41.666272],"type":"Point"}
}
