{
  "type": "Feature",
  "properties": {
    "iso:country":"US",
    "sg:address":"1376 Bridge St",
    "sg:city":"South Yarmouth",
    "sg:classifiers":[
        {
            "category":"Travel",
            "subcategory":"Hotels & Motels",
            "type":"Entertainment"
        }
    ],
    "sg:phone":"+1 508 398 2253",
    "sg:postcode":"02664",
    "sg:province":"MA",
    "wof:name":"Bass River Jolly Captain Condo",
    "wof:placetype":"venue"
},
  "geometry": {"coordinates":[-70.183319,41.666272],"type":"Point"}
}