{
  "type": "Feature",
  "properties": {
    "iso:country":"US",
    "sg:address":"39 N Dartmouth Mall",
    "sg:city":"North Dartmouth",
    "sg:classifiers":[
        {
            "category":"Shopping",
            "subcategory":"Shoes",
            "type":"Retail Goods"
        }
    ],
    "sg:phone":"+1 508 990 3616",
    "sg:postcode":"02747",
    "sg:province":"MA",
    "wof:name":"Red Wing Shoe Store",
    "wof:placetype":"venue"
},
  "geometry": {"coordinates":[-70.99424500000001,41.641954],"type":"Point"}
}