{
  "type": "Feature",
  "properties": {
    "addr:full":"196 Nashua Rd Pepperell MA 01463",
    "addr:housenumber":"196",
    "addr:postcode":"01463",
    "addr:street":"Nashua Rd",
    "iso:country":"US",
    "sg:address":"196 Nashua Rd",
    "sg:city":"Pepperell",
    "sg:classifiers":[
        {
            "category":"Building & Trades",
            "subcategory":"Construction",
            "type":"Services"
        }
    ],
    "sg:phone":"+1 978 433 5243",
    "sg:postcode":"01463",
    "sg:province":"MA",
    "sg:tags":[
        "general",
        "contractor"
    ],
    "wof:name":"DMA Building Corp",
    "wof:placetype":"venue"
},
  "geometry": {"coordinates":[-71.552672,42.70214],"type":"Point"}
}