{
  "type": "Feature",
  "properties": {
    "addr:full": "179 Broad St Bridgewater MA 02324",
    "addr:housenumber": "179",
    "addr:postcode": "02324",
    "addr:street": "Broad St",
    "iso:country": "US",
    "sg:address": "179 Broad St",
    "sg:city": "Bridgewater",
    "sg:classifiers": [
      {
        "category": "Real Estate",
        "subcategory": "Real Estate Services",
        "type": "Services"
      },
      {
        "category": "Real Estate",
        "subcategory": "Real Estate Agent",
        "type": "Services"
      }
    ],
    "sg:phone": "+1 508 279 1547",
    "sg:postcode": "02324",
    "sg:province": "MA",
    "sg:tags": [
      "buyer",
      "broker"
    ],
    "wof:name": "Federal Realty Investment Trust",
    "wof:placetype": "venue"
  },
  "geometry": {"coordinates":[-70.974001,41.994109],"type":"Point"}
}
