{
  "type": "Feature",
  "properties": {
    "addr:full":"59 Union Sq Somerville MA 02143",
    "addr:housenumber":"59",
    "addr:postcode":"02143",
    "addr:street":"Union Sq",
    "iso:country":"US",
    "sg:address":"59 Union Sq",
    "sg:city":"Somerville",
    "sg:classifiers":[
        {
            "category":"Professional",
            "subcategory":"Management & Consulting",
            "type":"Services"
        }
    ],
    "sg:phone":"+1 617 666 9400",
    "sg:postcode":"02143",
    "sg:province":"MA",
    "sg:tags":[
        "consultant",
        "business"
    ],
    "wof:name":"Henry B WYNN & Assoc",
    "wof:placetype":"venue"
},
  "geometry": {"coordinates":[-71.09629700000001,42.379726],"type":"Point"}
}