{
  "type": "Feature",
  "properties": {
    "iso:country":"US",
    "sg:address":"7 Main St",
    "sg:city":"Rockport",
    "sg:classifiers":[
        {
            "category":"Organizations",
            "subcategory":"Religious Organization",
            "type":"Services"
        }
    ],
    "sg:phone":"+1 978 546 2392",
    "sg:postcode":"01966",
    "sg:province":"MA",
    "sg:tags":[
        "church"
    ],
    "wof:name":"Christian Science Reading Room",
    "wof:placetype":"venue"
},
  "geometry": {"coordinates":[-70.61869900000001,42.658361],"type":"Point"}
}