{
  "type": "Feature",
  "properties": {
    "addr:full":"246 Flat Hill Rd Lunenburg MA 01462",
    "addr:housenumber":"246",
    "addr:postcode":"01462",
    "addr:street":"Flat Hill Rd",
    "iso:country":"US",
    "sg:address":"246 Flat Hill Rd",
    "sg:city":"Lunenburg",
    "sg:classifiers":[
        {
            "category":"Real Estate",
            "subcategory":"Real Estate Agent",
            "type":"Services"
        }
    ],
    "sg:phone":"+1 978 582 6949",
    "sg:postcode":"01462",
    "sg:province":"MA",
    "wof:name":"Christopher A St Hilaire",
    "wof:placetype":"venue"
},
  "geometry": {"coordinates":[-71.67917300000001,42.584756],"type":"Point"}
}