{
  "type": "Feature",
  "properties": {
    "iso:country":"US",
    "sg:address":"100 Technology Center Dr",
    "sg:city":"Stoughton",
    "sg:classifiers":[
        {
            "category":"Banks & Credit Unions",
            "subcategory":"Financial Services",
            "type":"Services"
        }
    ],
    "sg:phone":"+1   ",
    "sg:postcode":"02072",
    "sg:province":"MA",
    "sg:tags":[
        "company",
        "holding"
    ],
    "wof:name":"Reebok Chc Inc",
    "wof:placetype":"venue"
},
  "geometry": {"coordinates":[-71.0638,42.160579],"type":"Point"}
}