{
  "type": "Feature",
  "properties": {
    "addr:full": "100 Technology Center Dr Stoughton MA 02072",
    "addr:housenumber": "100",
    "addr:postcode": "02072",
    "addr:street": "Center Dr",
    "iso:country": "US",
    "sg:address": "100 Technology Center Dr",
    "sg:city": "Stoughton",
    "sg:classifiers": [
      {
        "category": "Banks \u0026 Credit Unions",
        "subcategory": "Financial Services",
        "type": "Services"
      }
    ],
    "sg:phone": "+1   ",
    "sg:postcode": "02072",
    "sg:province": "MA",
    "sg:tags": [
      "company",
      "holding"
    ],
    "wof:name": "Reebok Chc Inc",
    "wof:placetype": "venue"
  },
  "geometry": {"coordinates":[-71.0638,42.160579],"type":"Point"}
}
