{
  "type": "Feature",
  "properties": {
    "addr:full":"17 Middle St South Dartmouth MA 02748",
    "addr:housenumber":"17",
    "addr:postcode":"02748",
    "addr:street":"Middle St",
    "iso:country":"US",
    "sg:address":"17 Middle St",
    "sg:city":"South Dartmouth",
    "sg:classifiers":[
        {
            "category":"Organizations",
            "subcategory":"Religious Organization",
            "type":"Services"
        }
    ],
    "sg:phone":"+1 508 993 6676",
    "sg:postcode":"02748",
    "sg:province":"MA",
    "sg:tags":[
        "church"
    ],
    "wof:name":"Congregational Church",
    "wof:placetype":"venue"
},
  "geometry": {"coordinates":[-70.940618,41.588725],"type":"Point"}
}