{
  "type": "Feature",
  "properties": {
    "iso:country":"US",
    "sg:address":"156 State St",
    "sg:city":"Boston",
    "sg:classifiers":[
        {
            "category":"Real Estate",
            "subcategory":"Real Estate Agent",
            "type":"Services"
        }
    ],
    "sg:phone":"+1 617 262 4383",
    "sg:postcode":"02109",
    "sg:province":"MA",
    "wof:name":"Greenspan Realty",
    "wof:placetype":"venue"
},
  "geometry": {"coordinates":[-71.054068,42.359357],"type":"Point"}
}