{
  "type": "Feature",
  "properties": {
    "iso:country":"US",
    "sg:address":"12 Turner St",
    "sg:city":"Norfolk",
    "sg:classifiers":[
        {
            "category":"Sports & Exercise",
            "subcategory":"Race Track",
            "type":"Entertainment"
        }
    ],
    "sg:phone":"+1   ",
    "sg:postcode":"02056",
    "sg:province":"MA",
    "sg:tags":[
        "operation",
        "racing",
        "or"
    ],
    "wof:name":"Griffin Racing",
    "wof:placetype":"venue"
},
  "geometry": {"coordinates":[-71.32986,42.137742],"type":"Point"}
}