{
  "type": "Feature",
  "properties": {
    "addr:full": "12 Turner St Norfolk MA 02056",
    "addr:housenumber": "12",
    "addr:postcode": "02056",
    "addr:street": "Turner St",
    "iso:country": "US",
    "sg:address": "12 Turner St",
    "sg:city": "Norfolk",
    "sg:classifiers": [
      {
        "category": "Sports \u0026 Exercise",
        "subcategory": "Race Track",
        "type": "Entertainment"
      }
    ],
    "sg:phone": "+1   ",
    "sg:postcode": "02056",
    "sg:province": "MA",
    "sg:tags": [
      "operation",
      "racing",
      "or"
    ],
    "wof:name": "Griffin Racing",
    "wof:placetype": "venue"
  },
  "geometry": {"coordinates":[-71.32986,42.137742],"type":"Point"}
}
