{
  "type": "Feature",
  "properties": {
    "iso:country":"US",
    "sg:address":"30 Industrial Dr E",
    "sg:city":"Northampton",
    "sg:classifiers":[
        {
            "category":"Professional",
            "subcategory":"Engineering",
            "type":"Services"
        }
    ],
    "sg:phone":"+1 413 584 7444",
    "sg:postcode":"01060",
    "sg:province":"MA",
    "sg:tags":[
        "engineer"
    ],
    "wof:name":"Huntley Associates PC",
    "wof:placetype":"venue"
},
  "geometry": {"coordinates":[-72.62982700000001,42.335431],"type":"Point"}
}