{
  "type": "Feature",
  "properties": {
    "addr:full": "637 South St Walpole MA 02081",
    "addr:housenumber": "637",
    "addr:postcode": "02081",
    "addr:street": "South St",
    "iso:country": "US",
    "sg:address": "637 South St",
    "sg:city": "Walpole",
    "sg:classifiers": [
      {
        "category": "Building \u0026 Trades",
        "subcategory": "Cleaning \u0026 Sanitation",
        "type": "Services"
      }
    ],
    "sg:phone": "+1 508 668 4411",
    "sg:postcode": "02081",
    "sg:province": "MA",
    "sg:tags": [
      "house"
    ],
    "wof:name": "Chandler's Cleaning Svc",
    "wof:placetype": "venue"
  },
  "geometry": {"coordinates":[-71.248978,42.122563],"type":"Point"}
}
