{
  "type": "Feature",
  "properties": {
    "addr:full": "41 Foster St Arlington MA 02474",
    "addr:housenumber": "41",
    "addr:postcode": "02474",
    "addr:street": "Foster St",
    "iso:country": "US",
    "sg:address": "41 Foster St",
    "sg:city": "Arlington",
    "sg:classifiers": [
      {
        "category": "Professional",
        "type": "Services"
      }
    ],
    "sg:phone": "+1 781 648 0962",
    "sg:postcode": "02474",
    "sg:province": "MA",
    "sg:tags": [
      "arts",
      "artist"
    ],
    "wof:name": "Nadia Mahfuz",
    "wof:placetype": "venue"
  },
  "geometry": {"coordinates":[-71.146725,42.409697],"type":"Point"}
}
