{
  "type": "Feature",
  "properties": {
    "addr:full": "100 Milk St Methuen MA 01844",
    "addr:housenumber": "100",
    "addr:postcode": "01844",
    "addr:street": "Milk St",
    "iso:country": "US",
    "sg:address": "100 Milk St",
    "sg:city": "Methuen",
    "sg:classifiers": [
      {
        "category": "Health Services",
        "subcategory": "Doctor",
        "type": "Services"
      }
    ],
    "sg:phone": "+1 978 685 7115",
    "sg:postcode": "01844",
    "sg:province": "MA",
    "sg:tags": [
      "dentist"
    ],
    "wof:name": "Modern Dentistry",
    "wof:placetype": "venue"
  },
  "geometry": {"coordinates":[-71.155042,42.738203],"type":"Point"}
}
