{
  "type": "Feature",
  "properties": {
    "addr:full": "81 Eber Taft Rd Uxbridge MA 01569",
    "addr:housenumber": "81",
    "addr:postcode": "01569",
    "addr:street": "Eber Taft Rd",
    "iso:country": "US",
    "sg:address": "81 Eber Taft Rd",
    "sg:city": "Uxbridge",
    "sg:classifiers": [
      {
        "category": "Building \u0026 Trades",
        "subcategory": "Construction",
        "type": "Services"
      }
    ],
    "sg:phone": "+1 508 278 4528",
    "sg:postcode": "01569",
    "sg:province": "MA",
    "sg:tags": [
      "excavating",
      "contractor"
    ],
    "wof:name": "Kennedy Land Clearing Inc",
    "wof:placetype": "venue"
  },
  "geometry": {"coordinates":[-71.650843,42.057214],"type":"Point"}
}
