{
  "type": "Feature",
  "properties": {
    "addr:full": "153 Central St Lowell MA 01852",
    "addr:housenumber": "153",
    "addr:postcode": "01852",
    "addr:street": "Central St",
    "iso:country": "US",
    "sg:address": "153 Central St",
    "sg:city": "Lowell",
    "sg:classifiers": [
      {
        "category": "Shopping",
        "subcategory": "Music",
        "type": "Retail Goods"
      }
    ],
    "sg:phone": "+1 978 934 9339",
    "sg:postcode": "01852",
    "sg:province": "MA",
    "sg:tags": [
      "compact",
      "record",
      "disc",
      "tape"
    ],
    "wof:name": "Bananas Music Store",
    "wof:placetype": "venue"
  },
  "geometry": {"coordinates":[-71.308562,42.64365],"type":"Point"}
}
