{
  "type": "Feature",
  "properties": {
    "addr:full":"54 Village Brook Ln Natick MA 01760",
    "addr:housenumber":"54",
    "addr:postcode":"01760",
    "addr:street":"Village Brook Ln",
    "iso:country":"US",
    "sg:address":"54 Village Brook Ln",
    "sg:city":"Natick",
    "sg:classifiers":[
        {
            "category":"Professional",
            "subcategory":"Art Services",
            "type":"Services"
        }
    ],
    "sg:phone":"+1   ",
    "sg:postcode":"01760",
    "sg:province":"MA",
    "sg:tags":[
        "photography",
        "commercial"
    ],
    "wof:name":"Barry Photography",
    "wof:placetype":"venue"
},
  "geometry": {"coordinates":[-71.393248,42.277677],"type":"Point"}
}