{
  "type": "Feature",
  "properties": {
    "iso:country":"US",
    "sg:address":"865 Merriam Ave",
    "sg:city":"Leominster",
    "sg:classifiers":[
        {
            "category":"Utilities",
            "subcategory":"Mobile Phone",
            "type":"Services"
        }
    ],
    "sg:phone":"+1 978 466 9120",
    "sg:postcode":"01453",
    "sg:province":"MA",
    "sg:tags":[
        "telephone",
        "cellular"
    ],
    "wof:name":"Cingular Wireless",
    "wof:placetype":"venue"
},
  "geometry": {"coordinates":[-71.782905,42.551995],"type":"Point"}
}