{
  "type": "Feature",
  "properties": {
    "iso:country":"US",
    "sg:address":"168 Eastern Ave",
    "sg:city":"Lynn",
    "sg:classifiers":[
        {
            "category":"Wholesale",
            "subcategory":"Non-durable Goods",
            "type":"Manufacturing & Wholesale Goods"
        }
    ],
    "sg:phone":"+1 781 592 4622",
    "sg:postcode":"01902",
    "sg:province":"MA",
    "sg:tags":[
        "ice"
    ],
    "wof:name":"Patten Ice",
    "wof:placetype":"venue"
},
  "geometry": {"coordinates":[-70.92671,42.472824],"type":"Point"}
}