{
  "type": "Feature",
  "properties": {
    "addr:full": "62 Broadway Somerville MA 02143",
    "addr:housenumber": "62",
    "addr:postcode": "02143",
    "addr:street": "Broadway",
    "iso:country": "US",
    "sg:address": "62 Broadway",
    "sg:city": "Somerville",
    "sg:classifiers": [
      {
        "category": "Restaurant",
        "type": "Food \u0026 Drink"
      }
    ],
    "sg:phone": "+1 617 629 3502",
    "sg:postcode": "02143",
    "sg:province": "MA",
    "wof:name": "Los Paisanos",
    "wof:placetype": "venue"
  },
  "geometry": {"coordinates":[-71.080803,42.3866],"type":"Point"}
}
