{
  "type": "Feature",
  "properties": {
    "addr:full": "26 George Ryder Rd S Chatham MA 02633",
    "addr:housenumber": "26",
    "addr:postcode": "02633",
    "addr:street": "George Ryder Rd S",
    "iso:country": "US",
    "sg:address": "26 George Ryder Rd S",
    "sg:city": "Chatham",
    "sg:classifiers": [
      {
        "category": "Banks \u0026 Credit Unions",
        "subcategory": "Bank",
        "type": "Services"
      }
    ],
    "sg:phone": "+1 508 945 0460",
    "sg:postcode": "02633",
    "sg:province": "MA",
    "sg:tags": [
      "loan",
      "real estate"
    ],
    "wof:name": "Light Speed Mortgage",
    "wof:placetype": "venue"
  },
  "geometry": {"coordinates":[-69.996696,41.682582],"type":"Point"}
}
