{
  "type": "Feature",
  "properties": {
    "addr:full": "149 Townsend St Pepperell MA 01463",
    "addr:housenumber": "149",
    "addr:postcode": "01463",
    "addr:street": "Townsend St",
    "iso:country": "US",
    "sg:address": "149 Townsend St",
    "sg:city": "Pepperell",
    "sg:classifiers": [
      {
        "category": "Shopping",
        "subcategory": "Used Merchandise",
        "type": "Retail Goods"
      }
    ],
    "sg:phone": "+1   ",
    "sg:postcode": "01463",
    "sg:province": "MA",
    "wof:name": "The Silver Lining",
    "wof:placetype": "venue"
  },
  "geometry": {"coordinates":[-71.631972,42.650246],"type":"Point"}
}
