{
  "type": "Feature",
  "properties": {
    "iso:country":"US",
    "sg:address":"14 Bedford Rd",
    "sg:city":"Lincoln",
    "sg:classifiers":[
        {
            "category":"Organizations",
            "subcategory":"Religious Organization",
            "type":"Services"
        }
    ],
    "sg:phone":"+1 781 259 8118",
    "sg:postcode":"01773",
    "sg:province":"MA",
    "sg:tags":[
        "church"
    ],
    "sg:website":"www.firstparishinlincoln.org",
    "wof:name":"First Parish In Lincoln",
    "wof:placetype":"venue"
},
  "geometry": {"coordinates":[-71.303645,42.426071],"type":"Point"}
}