{
  "type": "Feature",
  "properties": {
    "addr:full": "14 Bedford Rd Lincoln MA 01773",
    "addr:housenumber": "14",
    "addr:postcode": "01773",
    "addr:street": "Bedford Rd",
    "iso:country": "US",
    "ovtr:label": "First Parish In Lincoln, 14 Bedford Rd Lincoln MA US",
    "ovtr:similarity": 2.810029983520508,
    "sg:address": "14 Bedford Rd",
    "sg:city": "Lincoln",
    "sg:classifiers": [
      {
        "category": "Organizations",
        "subcategory": "Religious Organization",
        "type": "Services"
      }
    ],
    "sg:phone": "+1 781 259 8118",
    "sg:postcode": "01773",
    "sg:province": "MA",
    "sg:tags": [
      "church"
    ],
    "sg:website": "www.firstparishinlincoln.org",
    "wof:name": "First Parish In Lincoln",
    "wof:placetype": "venue"
  },
  "geometry": {"coordinates":[-71.303645,42.426071],"type":"Point"}
}
