{
  "type": "Feature",
  "properties": {
    "addr:full":"273 Salem St Reading MA 01867",
    "addr:housenumber":"273",
    "addr:postcode":"01867",
    "addr:street":"Salem St",
    "iso:country":"US",
    "sg:address":"273 Salem St",
    "sg:city":"Reading",
    "sg:classifiers":[
        {
            "category":"Arts & Performance",
            "subcategory":"Theater",
            "type":"Entertainment"
        }
    ],
    "sg:phone":"+1 781 944 5065",
    "sg:postcode":"01867",
    "sg:province":"MA",
    "sg:tags":[
        "dance",
        "company"
    ],
    "wof:name":"Dancepiration",
    "wof:placetype":"venue"
},
  "geometry": {"coordinates":[-71.085402,42.525758],"type":"Point"}
}