{
  "type": "Feature",
  "properties": {
    "iso:country":"US",
    "sg:address":"22 Bennett Rd",
    "sg:city":"Boxford",
    "sg:classifiers":[
        {
            "category":"Real Estate",
            "subcategory":"Real Estate Services",
            "type":"Services"
        },
        {
            "category":"Real Estate",
            "subcategory":"Real Estate Agent",
            "type":"Services"
        }
    ],
    "sg:phone":"+1 781 910 5033",
    "sg:postcode":"01921",
    "sg:province":"MA",
    "sg:tags":[
        "management"
    ],
    "wof:name":"Distinctive Properties Neng",
    "wof:placetype":"venue"
},
  "geometry": {"coordinates":[-71.040806,42.675363],"type":"Point"}
}