{
  "type": "Feature",
  "properties": {
    "addr:full": "233 Harvard St Brookline MA 02446",
    "addr:housenumber": "233",
    "addr:postcode": "02446",
    "addr:street": "Harvard St",
    "iso:country": "US",
    "sg:address": "233 Harvard St",
    "sg:city": "Brookline",
    "sg:classifiers": [
      {
        "category": "Personal",
        "subcategory": "Day Spa",
        "type": "Services"
      }
    ],
    "sg:phone": "+1 617 277 3339",
    "sg:postcode": "02446",
    "sg:province": "MA",
    "sg:website": "www.EdenBoston.com",
    "wof:name": "Eden Spa",
    "wof:placetype": "venue"
  },
  "geometry": {"coordinates":[-71.120809,42.340702],"type":"Point"}
}
