{
  "type": "Feature",
  "properties": {
    "iso:country":"US",
    "sg:address":"233 Harvard St",
    "sg:city":"Brookline",
    "sg:classifiers":[
        {
            "category":"Personal",
            "subcategory":"Day Spa",
            "type":"Services"
        }
    ],
    "sg:phone":"+1 617 277 3339",
    "sg:postcode":"02446",
    "sg:province":"MA",
    "sg:website":"www.EdenBoston.com",
    "wof:name":"Eden Spa",
    "wof:placetype":"venue"
},
  "geometry": {"coordinates":[-71.12080899999999,42.340702],"type":"Point"}
}