{
  "type": "Feature",
  "properties": {
    "addr:full": "54 Middlesex Turnpike Building C Bedford MA 01730",
    "addr:housenumber": "54",
    "addr:postcode": "01730",
    "addr:street": "Middlesex Turnpike;C",
    "iso:country": "US",
    "sg:address": "54 Middlesex Turnpike Building C",
    "sg:city": "Bedford",
    "sg:classifiers": [
      {
        "category": "Personal",
        "subcategory": "Massage",
        "type": "Services"
      }
    ],
    "sg:phone": "+1 617 763 4117",
    "sg:postcode": "01730",
    "sg:province": "MA",
    "sg:website": "www.touchbodyandsoul.com",
    "wof:name": "Body \u0026 Soul Massage",
    "wof:placetype": "venue"
  },
  "geometry": {"coordinates":[-71.239345,42.511956],"type":"Point"}
}
