{
  "type": "Feature",
  "properties": {
    "iso:country":"US",
    "sg:address":"54 Middlesex Turnpike Building C",
    "sg:city":"Bedford",
    "sg:classifiers":[
        {
            "category":"Personal",
            "subcategory":"Massage",
            "type":"Services"
        }
    ],
    "sg:phone":"+1 617 763 4117",
    "sg:postcode":"01730",
    "sg:province":"MA",
    "sg:website":"www.touchbodyandsoul.com",
    "wof:name":"Body & Soul Massage",
    "wof:placetype":"venue"
},
  "geometry": {"coordinates":[-71.239345,42.511956],"type":"Point"}
}