{
  "type": "Feature",
  "properties": {
    "iso:country":"US",
    "sg:address":"2 E Main St",
    "sg:city":"Avon",
    "sg:classifiers":[
        {
            "category":"Home & Garden",
            "subcategory":"Home Furnishings",
            "type":"Retail Goods"
        }
    ],
    "sg:phone":"+1 508 588 0864",
    "sg:postcode":"02322",
    "sg:province":"MA",
    "sg:tags":[
        "curtain",
        "made",
        "drapery"
    ],
    "wof:name":"Linen Chest Unlimited",
    "wof:placetype":"venue"
},
  "geometry": {"coordinates":[-71.04012,42.13163],"type":"Point"}
}