{
  "type": "Feature",
  "properties": {
    "addr:full":"811 Boylston St. Units 1 & 2 Boston MA 02116",
    "addr:housenumber":"811;1 & 2",
    "addr:postcode":"02116",
    "addr:street":"Boylston St.",
    "iso:country":"US",
    "sg:address":"811 Boylston St. Units 1 & 2",
    "sg:city":"Boston",
    "sg:classifiers":[
        {
            "category":"Home & Garden",
            "subcategory":"Carpets & Floor Coverings",
            "type":"Retail Goods"
        }
    ],
    "sg:phone":"+1 617 456 1694",
    "sg:postcode":"02116",
    "sg:province":"MA",
    "sg:tags":[
        "mattress"
    ],
    "sg:website":"www.sleepys.com/",
    "wof:name":"Sleepy's, The Mattress Professionals",
    "wof:placetype":"venue"
},
  "geometry": {"coordinates":[-71.082172,42.348812],"type":"Point"}
}