{
  "type": "Feature",
  "properties": {
    "addr:full": "12 Kenwood St Greenfield MA 01301",
    "addr:housenumber": "12",
    "addr:postcode": "01301",
    "addr:street": "Kenwood St",
    "iso:country": "US",
    "sg:address": "12 Kenwood St",
    "sg:city": "Greenfield",
    "sg:classifiers": [
      {
        "category": "Wholesale",
        "subcategory": "Hardware",
        "type": "Manufacturing \u0026 Wholesale Goods"
      }
    ],
    "sg:phone": "+1 413 774 6002",
    "sg:postcode": "01301",
    "sg:province": "MA",
    "sg:tags": [
      "plumbing",
      "fixture",
      "supply"
    ],
    "wof:name": "Franklin County Plumbing Sply",
    "wof:placetype": "venue"
  },
  "geometry": {"coordinates":[-72.599294,42.601249],"type":"Point"}
}
