{
  "type": "Feature",
  "properties": {
    "addr:full":"44 Binney St Boston MA 02115",
    "addr:housenumber":"44",
    "addr:postcode":"02115",
    "addr:street":"Binney St",
    "iso:country":"US",
    "sg:address":"44 Binney St",
    "sg:city":"Boston",
    "sg:classifiers":[
        {
            "category":"Health Services",
            "subcategory":"Doctor",
            "type":"Services"
        }
    ],
    "sg:phone":"+1 617 732 7176",
    "sg:postcode":"02115",
    "sg:province":"MA",
    "sg:tags":[
        "physician",
        "oncology",
        "surgeons",
        "surgeon",
        "gynecologic"
    ],
    "wof:name":"Bwh Radiation Oncology Research And Education Foun",
    "wof:placetype":"venue"
},
  "geometry": {"coordinates":[-71.10713199999999,42.337299],"type":"Point"}
}