{
  "type": "Feature",
  "properties": {
    "addr:full": "703 Hyde Park Ave Roslindale MA 02131",
    "addr:housenumber": "703",
    "addr:postcode": "02131",
    "addr:street": "Hyde Park Ave",
    "iso:country": "US",
    "sg:address": "703 Hyde Park Ave",
    "sg:city": "Roslindale",
    "sg:classifiers": [
      {
        "category": "Building \u0026 Trades",
        "subcategory": "Construction",
        "type": "Services"
      }
    ],
    "sg:phone": "+1 617 323 2029",
    "sg:postcode": "02131",
    "sg:province": "MA",
    "sg:tags": [
      "wallpaper"
    ],
    "wof:name": "Marco A Acosta Quality Paint",
    "wof:placetype": "venue"
  },
  "geometry": {"coordinates":[-71.120155,42.272589],"type":"Point"}
}
