{
  "type": "Feature",
  "properties": {
    "iso:country":"US",
    "sg:address":"26 Crestway Rd",
    "sg:city":"Boston",
    "sg:classifiers":[
        {
            "category":"Manufacturing",
            "subcategory":"Buildings",
            "type":"Manufacturing & Wholesale Goods"
        },
        {
            "category":"Building & Trades",
            "subcategory":"Construction",
            "type":"Services"
        }
    ],
    "sg:phone":"+1 978 973 9247",
    "sg:postcode":"02128",
    "sg:province":"MA",
    "sg:tags":[
        "home",
        "builder",
        "contractor"
    ],
    "wof:name":"Mpc",
    "wof:placetype":"venue"
},
  "geometry": {"coordinates":[-71.004829,42.392218],"type":"Point"}
}