{
  "type": "Feature",
  "properties": {
    "addr:full": "240 Ivory St Braintree MA 02184",
    "addr:housenumber": "240",
    "addr:postcode": "02184",
    "addr:street": "Ivory St",
    "iso:country": "US",
    "sg:address": "240 Ivory St",
    "sg:city": "Braintree",
    "sg:classifiers": [
      {
        "category": "Bakery",
        "type": "Food \u0026 Drink"
      },
      {
        "category": "Coffee \u0026 Tea",
        "type": "Food \u0026 Drink"
      },
      {
        "category": "Bagels",
        "type": "Food \u0026 Drink"
      },
      {
        "category": "Donuts",
        "type": "Food \u0026 Drink"
      }
    ],
    "sg:menulink": "http://www.allmenus.com/ma/braintree/142737-dunkin-donuts/menu/",
    "sg:phone": "+1 781 843 6503",
    "sg:postcode": "02184",
    "sg:province": "MA",
    "sg:tags": [
      "american",
      "diner",
      "pastry"
    ],
    "wof:name": "Dunkin' Donuts",
    "wof:placetype": "venue"
  },
  "geometry": {"coordinates":[-71.000846,42.205277],"type":"Point"}
}
