{
  "type": "Feature",
  "properties": {
    "addr:full": "419 Maple Ave Sheffield MA 01257",
    "addr:housenumber": "419",
    "addr:postcode": "01257",
    "addr:street": "Maple Ave",
    "iso:country": "US",
    "sg:address": "419 Maple Ave",
    "sg:city": "Sheffield",
    "sg:classifiers": [
      {
        "category": "Building \u0026 Trades",
        "subcategory": "Electrical",
        "type": "Services"
      }
    ],
    "sg:phone": "+1   ",
    "sg:postcode": "01257",
    "sg:province": "MA",
    "sg:tags": [
      "electrical",
      "contractor"
    ],
    "wof:name": "Richard J Cappadona",
    "wof:placetype": "venue"
  },
  "geometry": {"coordinates":[-73.335987,42.108198],"type":"Point"}
}
