{
  "type": "Feature",
  "properties": {
    "iso:country":"US",
    "sg:address":"419 Maple Ave",
    "sg:city":"Sheffield",
    "sg:classifiers":[
        {
            "category":"Building & Trades",
            "subcategory":"Electrical",
            "type":"Services"
        }
    ],
    "sg:phone":"+1   ",
    "sg:postcode":"01257",
    "sg:province":"MA",
    "sg:tags":[
        "electrical",
        "contractor"
    ],
    "wof:name":"Richard J Cappadona",
    "wof:placetype":"venue"
},
  "geometry": {"coordinates":[-73.335987,42.108198],"type":"Point"}
}