{
  "type": "Feature",
  "properties": {
    "addr:full": "811 Washington St Stoughton MA 02072",
    "addr:housenumber": "811",
    "addr:postcode": "02072",
    "addr:street": "Washington St",
    "iso:country": "US",
    "sg:address": "811 Washington St",
    "sg:city": "Stoughton",
    "sg:classifiers": [
      {
        "category": "Restaurant",
        "type": "Food \u0026 Drink"
      }
    ],
    "sg:phone": "+1 781 344 3008",
    "sg:postcode": "02072",
    "sg:province": "MA",
    "wof:name": "Wilson Brazilian Food - CLOSED",
    "wof:placetype": "venue"
  },
  "geometry": {"coordinates":[-71.101402,42.123901],"type":"Point"}
}
