{
  "type": "Feature",
  "properties": {
    "addr:full": "1540 Bedford St Abington MA 02351",
    "addr:housenumber": "1540",
    "addr:postcode": "02351",
    "addr:street": "Bedford St",
    "iso:country": "US",
    "sg:address": "1540 Bedford St",
    "sg:city": "Abington",
    "sg:classifiers": [
      {
        "category": "Building \u0026 Trades",
        "subcategory": "Construction",
        "type": "Services"
      }
    ],
    "sg:phone": "+1 781 871 0585",
    "sg:postcode": "02351",
    "sg:province": "MA",
    "sg:tags": [
      "contractor"
    ],
    "wof:name": "Boxberry Builders \u0026 Management",
    "wof:placetype": "venue"
  },
  "geometry": {"coordinates":[-70.95314,42.142584],"type":"Point"}
}
