{
  "type": "Feature",
  "properties": {
    "addr:full": "560 Loring Ave Salem MA 01970",
    "addr:housenumber": "560",
    "addr:postcode": "01970",
    "addr:street": "Loring Ave",
    "iso:country": "US",
    "sg:address": "560 Loring Ave",
    "sg:city": "Salem",
    "sg:classifiers": [
      {
        "category": "Banks \u0026 Credit Unions",
        "subcategory": "Investment Brokerage",
        "type": "Services"
      }
    ],
    "sg:phone": "+1 978 740 9360",
    "sg:postcode": "01970",
    "sg:province": "MA",
    "sg:tags": [
      "consultant",
      "planning",
      "financial"
    ],
    "wof:name": "Financial Planning Strategies",
    "wof:placetype": "venue"
  },
  "geometry": {"coordinates":[-70.903526,42.485206],"type":"Point"}
}
