{
  "type": "Feature",
  "properties": {
    "iso:country":"US",
    "sg:address":"45 Sandwich Rd",
    "sg:city":"Wareham",
    "sg:classifiers":[
        {
            "category":"Home & Garden",
            "subcategory":"Household Appliances",
            "type":"Retail Goods"
        }
    ],
    "sg:phone":"+1 508 295 1045",
    "sg:postcode":"02571",
    "sg:province":"MA",
    "sg:tags":[
        "repair"
    ],
    "wof:name":"Hilltop Tv & Appliances",
    "wof:placetype":"venue"
},
  "geometry": {"coordinates":[-70.708603,41.757801],"type":"Point"}
}