{
  "type": "Feature",
  "properties": {
    "addr:full": "45 Sandwich Rd Wareham MA 02571",
    "addr:housenumber": "45",
    "addr:postcode": "02571",
    "addr:street": "Sandwich Rd",
    "iso:country": "US",
    "sg:address": "45 Sandwich Rd",
    "sg:city": "Wareham",
    "sg:classifiers": [
      {
        "category": "Home \u0026 Garden",
        "subcategory": "Household Appliances",
        "type": "Retail Goods"
      }
    ],
    "sg:phone": "+1 508 295 1045",
    "sg:postcode": "02571",
    "sg:province": "MA",
    "sg:tags": [
      "repair"
    ],
    "wof:name": "Hilltop Tv \u0026 Appliances",
    "wof:placetype": "venue"
  },
  "geometry": {"coordinates":[-70.708603,41.757801],"type":"Point"}
}
