{
  "type": "Feature",
  "properties": {
    "addr:full": "360 Riverway Boston MA 02115",
    "addr:housenumber": "360",
    "addr:postcode": "02115",
    "addr:street": "Riverway",
    "iso:country": "US",
    "sg:address": "360 Riverway",
    "sg:city": "Boston",
    "sg:classifiers": [
      {
        "category": "Professional",
        "subcategory": "Advertising",
        "type": "Services"
      }
    ],
    "sg:phone": "+1   ",
    "sg:postcode": "02115",
    "sg:province": "MA",
    "wof:name": "Urban Exchange Magazine Inc",
    "wof:placetype": "venue"
  },
  "geometry": {"coordinates":[-71.110176,42.334728],"type":"Point"}
}
