{
  "type": "Feature",
  "properties": {
    "addr:full": "22 Water St Holyoke MA 01040",
    "addr:housenumber": "22",
    "addr:postcode": "01040",
    "addr:street": "Water St",
    "iso:country": "US",
    "sg:address": "22 Water St",
    "sg:city": "Holyoke",
    "sg:classifiers": [
      {
        "category": "Building \u0026 Trades",
        "subcategory": "Construction",
        "type": "Services"
      }
    ],
    "sg:phone": "+1 413 534 2229",
    "sg:postcode": "01040",
    "sg:province": "MA",
    "sg:tags": [
      "marking",
      "maintenance",
      "parking"
    ],
    "wof:name": "Holyoke City Public Works",
    "wof:placetype": "venue"
  },
  "geometry": {"coordinates":[-72.595835,42.208894],"type":"Point"}
}
