{
  "type": "Feature",
  "properties": {
    "iso:country":"US",
    "sg:address":"22 Water St",
    "sg:city":"Holyoke",
    "sg:classifiers":[
        {
            "category":"Building & Trades",
            "subcategory":"Construction",
            "type":"Services"
        }
    ],
    "sg:phone":"+1 413 534 2229",
    "sg:postcode":"01040",
    "sg:province":"MA",
    "sg:tags":[
        "marking",
        "maintenance",
        "parking"
    ],
    "wof:name":"Holyoke City Public Works",
    "wof:placetype":"venue"
},
  "geometry": {"coordinates":[-72.59583499999999,42.208894],"type":"Point"}
}