{
  "type": "Feature",
  "properties": {
    "iso:country":"US",
    "sg:address":"55 Birchland Ave",
    "sg:city":"Springfield",
    "sg:classifiers":[
        {
            "category":"Building & Trades",
            "subcategory":"Landscaping Services",
            "type":"Services"
        }
    ],
    "sg:phone":"+1   ",
    "sg:postcode":"01119",
    "sg:province":"MA",
    "wof:name":"Martel Tree & Landscape",
    "wof:placetype":"venue"
},
  "geometry": {"coordinates":[-72.509772,42.115753],"type":"Point"}
}