{
  "type": "Feature",
  "properties": {
    "addr:full": "55 Birchland Ave Springfield MA 01119",
    "addr:housenumber": "55",
    "addr:postcode": "01119",
    "addr:street": "Birchland Ave",
    "iso:country": "US",
    "sg:address": "55 Birchland Ave",
    "sg:city": "Springfield",
    "sg:classifiers": [
      {
        "category": "Building \u0026 Trades",
        "subcategory": "Landscaping Services",
        "type": "Services"
      }
    ],
    "sg:phone": "+1   ",
    "sg:postcode": "01119",
    "sg:province": "MA",
    "wof:name": "Martel Tree \u0026 Landscape",
    "wof:placetype": "venue"
  },
  "geometry": {"coordinates":[-72.509772,42.115753],"type":"Point"}
}
