{
  "type": "Feature",
  "properties": {
    "addr:full":"493 Essex St Lawrence MA 01840",
    "addr:housenumber":"493",
    "addr:postcode":"01840",
    "addr:street":"Essex St",
    "iso:country":"US",
    "sg:address":"493 Essex St",
    "sg:city":"Lawrence",
    "sg:classifiers":[
        {
            "category":"Professional",
            "type":"Services"
        }
    ],
    "sg:phone":"+1 978 725 3670",
    "sg:postcode":"01840",
    "sg:province":"MA",
    "sg:tags":[
        "establishment"
    ],
    "wof:name":"Pac Trading",
    "wof:placetype":"venue"
},
  "geometry": {"coordinates":[-71.166124,42.705882],"type":"Point"}
}