{
  "type": "Feature",
  "properties": {
    "iso:country":"US",
    "sg:address":"940 Winter Street",
    "sg:city":"Waltham",
    "sg:classifiers":[
        {
            "category":"Professional",
            "subcategory":"Computer Services",
            "type":"Services"
        }
    ],
    "sg:phone":"+1 203 925 4602",
    "sg:postcode":"02451",
    "sg:province":"MA",
    "sg:website":"http://www.perkinelmer.com",
    "wof:name":"PerkinElmer",
    "wof:placetype":"venue"
},
  "geometry": {"coordinates":[-71.275195,42.399335],"type":"Point"}
}