{
  "type": "Feature",
  "properties": {
    "iso:country":"US",
    "sg:address":"50 Washington St",
    "sg:city":"Worcester",
    "sg:classifiers":[
        {
            "category":"Building & Trades",
            "subcategory":"Construction",
            "type":"Services"
        }
    ],
    "sg:phone":"+1 508 798 5124",
    "sg:postcode":"01610",
    "sg:province":"MA",
    "sg:tags":[
        "demolition",
        "contractor"
    ],
    "wof:name":"Amc Co",
    "wof:placetype":"venue"
},
  "geometry": {"coordinates":[-71.79946099999999,42.258678],"type":"Point"}
}