{
  "type": "Feature",
  "properties": {
    "addr:full": "50 Washington St Worcester MA 01610",
    "addr:housenumber": "50",
    "addr:postcode": "01610",
    "addr:street": "Washington St",
    "iso:country": "US",
    "sg:address": "50 Washington St",
    "sg:city": "Worcester",
    "sg:classifiers": [
      {
        "category": "Building \u0026 Trades",
        "subcategory": "Construction",
        "type": "Services"
      }
    ],
    "sg:phone": "+1 508 798 5124",
    "sg:postcode": "01610",
    "sg:province": "MA",
    "sg:tags": [
      "demolition",
      "contractor"
    ],
    "wof:name": "Amc Co",
    "wof:placetype": "venue"
  },
  "geometry": {"coordinates":[-71.799461,42.258678],"type":"Point"}
}
