{
  "type": "Feature",
  "properties": {
    "addr:full":"43 Bethel St New Bedford MA 02740",
    "addr:housenumber":"43",
    "addr:postcode":"02740",
    "addr:street":"Bethel St",
    "iso:country":"US",
    "sg:address":"43 Bethel St",
    "sg:city":"New Bedford",
    "sg:classifiers":[
        {
            "category":"Wholesale",
            "subcategory":"Medical Equipment & Supplies",
            "type":"Manufacturing & Wholesale Goods"
        }
    ],
    "sg:phone":"+1 508 992 2146",
    "sg:postcode":"02740",
    "sg:province":"MA",
    "sg:tags":[
        "hospital"
    ],
    "wof:name":"Enos Home Oxygen Therapy Co",
    "wof:placetype":"venue"
},
  "geometry": {"coordinates":[-70.923244,41.635839],"type":"Point"}
}