{
  "type": "Feature",
  "properties": {
    "iso:country":"US",
    "sg:address":"63 Exchange St",
    "sg:city":"Malden",
    "sg:classifiers":[
        {
            "category":"Personal",
            "subcategory":"Tanning Parlor",
            "type":"Services"
        }
    ],
    "sg:phone":"+1 781 388 9573",
    "sg:postcode":"02148",
    "sg:province":"MA",
    "sg:tags":[
        "salon",
        "massage"
    ],
    "sg:website":"www.islandbreezesalon.net",
    "wof:name":"Island Breeze Tan & Spa",
    "wof:placetype":"venue"
},
  "geometry": {"coordinates":[-71.069728,42.426439],"type":"Point"}
}