{
  "type": "Feature",
  "properties": {
    "addr:full":"1 Exeter St Lawrence MA 01843",
    "addr:housenumber":"1",
    "addr:postcode":"01843",
    "addr:street":"Exeter St",
    "iso:country":"US",
    "sg:address":"1 Exeter St",
    "sg:city":"Lawrence",
    "sg:classifiers":[
        {
            "category":"Professional",
            "subcategory":"Business Services",
            "type":"Services"
        }
    ],
    "sg:phone":"+1   ",
    "sg:postcode":"01843",
    "sg:province":"MA",
    "sg:tags":[
        "document",
        "confidential",
        "destroyer"
    ],
    "wof:name":"Jose Gonzalez",
    "wof:placetype":"venue"
},
  "geometry": {"coordinates":[-71.1473,42.693095],"type":"Point"}
}