{
  "type": "Feature",
  "properties": {
    "addr:full":"244 Teaticket Hwy Teaticket MA 02536",
    "addr:housenumber":"244",
    "addr:postcode":"02536",
    "addr:street":"Teaticket Hwy",
    "iso:country":"US",
    "sg:address":"244 Teaticket Hwy",
    "sg:city":"Teaticket",
    "sg:classifiers":[
        {
            "category":"Retail",
            "subcategory":"Auto Repair",
            "type":"Services"
        }
    ],
    "sg:phone":"+1 508 540 4290",
    "sg:postcode":"02536",
    "sg:province":"MA",
    "sg:tags":[
        "muffler",
        "exhaust",
        "system"
    ],
    "wof:name":"Midas Auto Svc Experts",
    "wof:placetype":"venue"
},
  "geometry": {"coordinates":[-70.595326,41.566949],"type":"Point"}
}