{
  "type": "Feature",
  "properties": {
    "addr:full": "125 Washington St Salem MA 01970",
    "addr:housenumber": "125",
    "addr:postcode": "01970",
    "addr:street": "Washington St",
    "iso:country": "US",
    "sg:address": "125 Washington St",
    "sg:city": "Salem",
    "sg:classifiers": [
      {
        "category": "Education",
        "subcategory": "School",
        "type": "Public Place"
      }
    ],
    "sg:phone": "+1 978 744 2105",
    "sg:postcode": "01970",
    "sg:province": "MA",
    "wof:name": "Salem Academy Charter School",
    "wof:placetype": "venue"
  },
  "geometry": {"coordinates":[-70.895463,42.520936],"type":"Point"}
}
