{
  "type": "Feature",
  "properties": {
    "addr:full":"12 Thomas St Middleboro MA 02346",
    "addr:housenumber":"12",
    "addr:postcode":"02346",
    "addr:street":"Thomas St",
    "iso:country":"US",
    "sg:address":"12 Thomas St",
    "sg:city":"Middleboro",
    "sg:classifiers":[
        {
            "category":"Building & Trades",
            "subcategory":"Construction",
            "type":"Services"
        }
    ],
    "sg:phone":"+1 508 947 3226",
    "sg:postcode":"02346",
    "sg:province":"MA",
    "sg:tags":[
        "contractor"
    ],
    "wof:name":"Falconeiri Construction Co",
    "wof:placetype":"venue"
},
  "geometry": {"coordinates":[-70.880437,41.880362],"type":"Point"}
}