{
  "type": "Feature",
  "properties": {
    "addr:full": "8 Bill Graham Ln Millbury MA 01527",
    "addr:housenumber": "8",
    "addr:postcode": "01527",
    "addr:street": "Bill Graham Ln",
    "iso:country": "US",
    "sg:address": "8 Bill Graham Ln",
    "sg:city": "Millbury",
    "sg:classifiers": [
      {
        "category": "Autos \u0026 Motor Vehicles",
        "subcategory": "Fuel \u0026 Gas Station",
        "type": "Retail Goods"
      }
    ],
    "sg:phone": "+1   ",
    "sg:postcode": "01527",
    "sg:province": "MA",
    "sg:tags": [
      "station"
    ],
    "wof:name": "Dudley Getty",
    "wof:placetype": "venue"
  },
  "geometry": {"coordinates":[-71.744166,42.21748],"type":"Point"}
}
