{
  "type": "Feature",
  "properties": {
    "iso:country":"US",
    "sg:address":"8 Bill Graham Ln",
    "sg:city":"Millbury",
    "sg:classifiers":[
        {
            "category":"Autos & Motor Vehicles",
            "subcategory":"Fuel & Gas Station",
            "type":"Retail Goods"
        }
    ],
    "sg:phone":"+1   ",
    "sg:postcode":"01527",
    "sg:province":"MA",
    "sg:tags":[
        "station"
    ],
    "wof:name":"Dudley Getty",
    "wof:placetype":"venue"
},
  "geometry": {"coordinates":[-71.74416600000001,42.21748],"type":"Point"}
}