{
  "type": "Feature",
  "properties": {
    "iso:country":"US",
    "sg:address":"One Exeter Plaza 699 Boylston at Exeter",
    "sg:city":"Boston",
    "sg:classifiers":[
        {
            "category":"Restaurant",
            "type":"Food & Drink"
        }
    ],
    "sg:phone":"+1 617 266 5858",
    "sg:postcode":"02116",
    "sg:province":"MA",
    "sg:tags":[
        "steakhouse"
    ],
    "sg:website":"www.mortons.com",
    "wof:name":"Morton's",
    "wof:placetype":"venue"
},
  "geometry": {"coordinates":[-71.081228,42.352985],"type":"Point"}
}