{
  "type": "Feature",
  "properties": {
    "addr:full": "35 Willie St Lowell MA 01854",
    "addr:housenumber": "35",
    "addr:postcode": "01854",
    "addr:street": "Willie St",
    "iso:country": "US",
    "sg:address": "35 Willie St",
    "sg:city": "Lowell",
    "sg:classifiers": [
      {
        "category": "Health Services",
        "subcategory": "Chiropractor",
        "type": "Services"
      }
    ],
    "sg:phone": "+1 978 452 4220",
    "sg:postcode": "01854",
    "sg:province": "MA",
    "sg:tags": [
      "chiropractic"
    ],
    "wof:name": "Pine St Chiropractic \u0026 Rehab",
    "wof:placetype": "venue"
  },
  "geometry": {"coordinates":[-71.321567,42.643965],"type":"Point"}
}
