{
  "type": "Feature",
  "properties": {
    "addr:full":"171 Milk St. 33 Boston MA 02109",
    "addr:housenumber":"171;33",
    "addr:postcode":"02109",
    "addr:street":"Milk St.",
    "iso:country":"US",
    "sg:address":"171 Milk St. 33",
    "sg:city":"Boston",
    "sg:classifiers":[
        {
            "category":"Sports & Exercise",
            "subcategory":"Sports Center",
            "type":"Entertainment"
        },
        {
            "category":"Recreation",
            "type":"Entertainment"
        }
    ],
    "sg:phone":"+1 617 542 2453",
    "sg:postcode":"02109",
    "sg:province":"MA",
    "sg:tags":[
        "active",
        "life"
    ],
    "sg:website":"www.massbike.org/",
    "wof:name":"Massachusetts Bicycle Coalition aka MassBike",
    "wof:placetype":"venue"
},
  "geometry": {"coordinates":[-71.053304,42.358271],"type":"Point"}
}