{
  "type": "Feature",
  "properties": {
    "addr:full": "500 W Boylston St Worcester MA 01606",
    "addr:housenumber": "500",
    "addr:postcode": "01606",
    "addr:street": "W Boylston St",
    "iso:country": "US",
    "sg:address": "500 W Boylston St",
    "sg:city": "Worcester",
    "sg:classifiers": [
      {
        "category": "Health Services",
        "subcategory": "Podiatrist",
        "type": "Services"
      }
    ],
    "sg:phone": "+1 508 853 4114",
    "sg:postcode": "01606",
    "sg:province": "MA",
    "wof:name": "Family Foot Care Center",
    "wof:placetype": "venue"
  },
  "geometry": {"coordinates":[-71.798875,42.308543],"type":"Point"}
}
