{
  "type": "Feature",
  "properties": {
    "addr:full":"95 Shannon St Brighton MA 02135",
    "addr:housenumber":"95",
    "addr:postcode":"02135",
    "addr:street":"Shannon St",
    "iso:country":"US",
    "sg:address":"95 Shannon St",
    "sg:city":"Brighton",
    "sg:classifiers":[
        {
            "category":"Building & Trades",
            "subcategory":"Locksmith",
            "type":"Services"
        }
    ],
    "sg:phone":"+1 617 415 9167",
    "sg:postcode":"02135",
    "sg:province":"MA",
    "sg:tags":[
        "key"
    ],
    "wof:name":"Service On Nantasket 123 Emergency Locksmith",
    "wof:placetype":"venue"
},
  "geometry": {"coordinates":[-71.15034,42.3457],"type":"Point"}
}