{
  "type": "Feature",
  "properties": {
    "addr:full": "262 Mapleshade Ave East Longmeadow MA 01028",
    "addr:housenumber": "262",
    "addr:postcode": "01028",
    "addr:street": "Mapleshade Ave",
    "iso:country": "US",
    "sg:address": "262 Mapleshade Ave",
    "sg:city": "East Longmeadow",
    "sg:classifiers": [
      {
        "category": "Building \u0026 Trades",
        "subcategory": "Construction",
        "type": "Services"
      }
    ],
    "sg:phone": "+1 413 525 8441",
    "sg:postcode": "01028",
    "sg:province": "MA",
    "sg:tags": [
      "hanging",
      "contractor"
    ],
    "wof:name": "Alternative Painting Co",
    "wof:placetype": "venue"
  },
  "geometry": {"coordinates":[-72.501573,42.073287],"type":"Point"}
}
