{
  "type": "Feature",
  "properties": {
    "iso:country":"US",
    "sg:address":"60 Court St",
    "sg:city":"Taunton",
    "sg:classifiers":[
        {
            "category":"Professional",
            "subcategory":"Engineering",
            "type":"Services"
        }
    ],
    "sg:phone":"+1 508 822 9870",
    "sg:postcode":"02780",
    "sg:province":"MA",
    "sg:tags":[
        "engineer"
    ],
    "wof:name":"Hayward-Boynton & Williams Inc",
    "wof:placetype":"venue"
},
  "geometry": {"coordinates":[-71.096193,41.902859],"type":"Point"}
}