{
  "type": "Feature",
  "properties": {
    "addr:full":"235 Woodland St Holliston MA 01746",
    "addr:housenumber":"235",
    "addr:postcode":"01746",
    "addr:street":"Woodland St",
    "iso:country":"US",
    "sg:address":"235 Woodland St",
    "sg:city":"Holliston",
    "sg:classifiers":[
        {
            "category":"Education",
            "subcategory":"School",
            "type":"Public Place"
        }
    ],
    "sg:phone":"+1 508 429 0667",
    "sg:postcode":"01746",
    "sg:province":"MA",
    "wof:name":"Holliston Miller School",
    "wof:placetype":"venue"
},
  "geometry": {"coordinates":[-71.42110700000001,42.205472],"type":"Point"}
}