{
  "type": "Feature",
  "properties": {
    "iso:country":"US",
    "sg:address":"631 Main St",
    "sg:city":"Walpole",
    "sg:classifiers":[
        {
            "category":"Shopping",
            "subcategory":"Jewelry",
            "type":"Retail Goods"
        }
    ],
    "sg:phone":"+1 508 660 6600",
    "sg:postcode":"02081",
    "sg:province":"MA",
    "sg:tags":[
        "jeweler"
    ],
    "wof:name":"Crown Jewelers Inc",
    "wof:placetype":"venue"
},
  "geometry": {"coordinates":[-71.24561,42.154802],"type":"Point"}
}