{
  "type": "Feature",
  "properties": {
    "addr:full": "1 Ranger Rd Methuen MA 01844",
    "addr:housenumber": "1",
    "addr:postcode": "01844",
    "addr:street": "Ranger Rd",
    "iso:country": "US",
    "sg:address": "1 Ranger Rd",
    "sg:city": "Methuen",
    "sg:classifiers": [
      {
        "category": "Education",
        "subcategory": "School",
        "type": "Public Place"
      }
    ],
    "sg:phone": "+1 978 681 1393",
    "sg:postcode": "01844",
    "sg:province": "MA",
    "wof:name": "Kitchen",
    "wof:placetype": "venue"
  },
  "geometry": {"coordinates":[-71.169547,42.733145],"type":"Point"}
}
