{
  "type": "Feature",
  "properties": {
    "addr:full": "214 Lincoln St Allston MA 02134",
    "addr:housenumber": "214",
    "addr:postcode": "02134",
    "addr:street": "Lincoln St",
    "iso:country": "US",
    "sg:address": "214 Lincoln St",
    "sg:city": "Allston",
    "sg:classifiers": [
      {
        "category": "Building \u0026 Trades",
        "subcategory": "Construction",
        "type": "Services"
      }
    ],
    "sg:phone": "+1 617 787 5400",
    "sg:postcode": "02134",
    "sg:province": "MA",
    "sg:tags": [
      "general",
      "contractor"
    ],
    "sg:website": "www.wtrich.com",
    "wof:name": "W T Rich Co",
    "wof:placetype": "venue"
  },
  "geometry": {"coordinates":[-71.136782,42.357518],"type":"Point"}
}
