{
  "type": "Feature",
  "properties": {
    "addr:full": "50 Resnik Rd # 103 Plymouth MA 02360",
    "addr:housenumber": "50",
    "addr:postcode": "02360",
    "addr:street": "Resnik Rd # 103",
    "iso:country": "US",
    "sg:address": "50 Resnik Rd # 103",
    "sg:city": "Plymouth",
    "sg:classifiers": [
      {
        "category": "Banks \u0026 Credit Unions",
        "subcategory": "Financial Services",
        "type": "Services"
      }
    ],
    "sg:phone": "+1 508 732 8940",
    "sg:postcode": "02360",
    "sg:province": "MA",
    "sg:tags": [
      "broker",
      "mortgage"
    ],
    "wof:name": "Allied Home Mortgage Capital Corporation - CLOSED",
    "wof:placetype": "venue"
  },
  "geometry": {"coordinates":[-70.708702,41.949902],"type":"Point"}
}
