{
  "type": "Feature",
  "properties": {
    "addr:full": "116 Stevens St Hyannis MA 02601",
    "addr:housenumber": "116",
    "addr:postcode": "02601",
    "addr:street": "Stevens St",
    "iso:country": "US",
    "sg:address": "116 Stevens St",
    "sg:city": "Hyannis",
    "sg:classifiers": [
      {
        "category": "Social Services",
        "subcategory": "Child Care",
        "type": "Services"
      }
    ],
    "sg:phone": "+1 508 778 6818",
    "sg:postcode": "02601",
    "sg:province": "MA",
    "sg:tags": [
      "day"
    ],
    "wof:name": "Ahanecqa Collins Childrens Center - CLOSED",
    "wof:placetype": "venue"
  },
  "geometry": {"coordinates":[-70.289597,41.6539],"type":"Point"}
}
