{
  "type": "Feature",
  "properties": {
    "addr:full":"27 Melcher St Boston MA 02210",
    "addr:housenumber":"27",
    "addr:postcode":"02210",
    "addr:street":"Melcher St",
    "iso:country":"US",
    "sg:address":"27 Melcher St",
    "sg:city":"Boston",
    "sg:classifiers":[
        {
            "category":"Banks & Credit Unions",
            "subcategory":"Investment Brokerage",
            "type":"Services"
        }
    ],
    "sg:phone":"+1 617 292 3900",
    "sg:postcode":"02210",
    "sg:province":"MA",
    "sg:tags":[
        "advisory",
        "financial"
    ],
    "wof:name":"DST Belvedere Financial Syst",
    "wof:placetype":"venue"
},
  "geometry": {"coordinates":[-71.05107,42.350202],"type":"Point"}
}