{
  "type": "Feature",
  "properties": {
    "iso:country":"US",
    "sg:address":"76 Wapping Rd",
    "sg:city":"Kingston",
    "sg:classifiers":[
        {
            "category":"Building & Trades",
            "subcategory":"Construction",
            "type":"Services"
        }
    ],
    "sg:phone":"+1 781 585 5600",
    "sg:postcode":"02364",
    "sg:province":"MA",
    "sg:tags":[
        "driveway"
    ],
    "wof:name":"Puma Paving",
    "wof:placetype":"venue"
},
  "geometry": {"coordinates":[-70.770072,41.990058],"type":"Point"}
}