{
  "type": "Feature",
  "properties": {
    "iso:country":"US",
    "sg:address":"201 Manning St",
    "sg:city":"Hudson",
    "sg:classifiers":[
        {
            "category":"Education",
            "subcategory":"School",
            "type":"Public Place"
        }
    ],
    "sg:phone":"+1 978 567 6210",
    "sg:postcode":"01749",
    "sg:province":"MA",
    "sg:tags":[
        "middle"
    ],
    "sg:website":"http://www.hudsonlight.com",
    "wof:name":"John F Kennedy Middle School",
    "wof:placetype":"venue"
},
  "geometry": {"coordinates":[-71.564763,42.403537],"type":"Point"}
}