{
  "type": "Feature",
  "properties": {
    "iso:country":"US",
    "sg:address":"1288 Dorchester Ave",
    "sg:city":"Dorchester",
    "sg:classifiers":[
        {
            "category":"Building & Trades",
            "subcategory":"Construction",
            "type":"Services"
        }
    ],
    "sg:phone":"+1 617 265 2128",
    "sg:postcode":"02122",
    "sg:province":"MA",
    "sg:tags":[
        "roofing",
        "industrial",
        "contractors-commercial",
        "contractor"
    ],
    "sg:website":"http://www.thomasroofingdorchester.com",
    "wof:name":"Thomas Roofing Co",
    "wof:placetype":"venue"
},
  "geometry": {"coordinates":[-71.05864800000001,42.306657],"type":"Point"}
}