{
  "type": "Feature",
  "properties": {
    "addr:full":"25 Waban St Natick MA 01760",
    "addr:housenumber":"25",
    "addr:postcode":"01760",
    "addr:street":"Waban St",
    "iso:country":"US",
    "sg:address":"25 Waban St",
    "sg:city":"Natick",
    "sg:classifiers":[
        {
            "category":"Manufacturing",
            "subcategory":"Buildings",
            "type":"Manufacturing & Wholesale Goods"
        },
        {
            "category":"Building & Trades",
            "subcategory":"Construction",
            "type":"Services"
        }
    ],
    "sg:phone":"+1 508 653 0033",
    "sg:postcode":"01760",
    "sg:province":"MA",
    "sg:tags":[
        "home",
        "builder",
        "contractor"
    ],
    "wof:name":"Daniel F Langan Ii",
    "wof:placetype":"venue"
},
  "geometry": {"coordinates":[-71.35204299999999,42.27927],"type":"Point"}
}