{
  "type": "Feature",
  "properties": {
    "addr:full":"1129 Main St Dennis MA 02638",
    "addr:housenumber":"1129",
    "addr:postcode":"02638",
    "addr:street":"Main St",
    "iso:country":"US",
    "sg:address":"1129 Main St",
    "sg:city":"Dennis",
    "sg:classifiers":[
        {
            "category":"Professional",
            "subcategory":"Lawyer & Legal Services",
            "type":"Services"
        }
    ],
    "sg:phone":"+1 508 385 3216",
    "sg:postcode":"02638",
    "sg:province":"MA",
    "sg:tags":[
        "attorney"
    ],
    "wof:name":"Crowell & Crowell",
    "wof:placetype":"venue"
},
  "geometry": {"coordinates":[-70.17649299999999,41.74628],"type":"Point"}
}