{
  "type": "Feature",
  "properties": {
    "addr:full":"1 State St Boston MA 02109",
    "addr:housenumber":"1",
    "addr:postcode":"02109",
    "addr:street":"State St",
    "iso:country":"US",
    "sg:address":"1 State St",
    "sg:city":"Boston",
    "sg:classifiers":[
        {
            "category":"Banks & Credit Unions",
            "subcategory":"Investment Brokerage",
            "type":"Services"
        }
    ],
    "sg:phone":"+1 617 720 1444",
    "sg:postcode":"02109",
    "sg:province":"MA",
    "sg:tags":[
        "advisory",
        "financial"
    ],
    "wof:name":"Axiom Capital Group Inc",
    "wof:placetype":"venue"
},
  "geometry": {"coordinates":[-71.05725700000001,42.358888],"type":"Point"}
}