{
  "type": "Feature",
  "properties": {
    "addr:full":"265 Cabot St Beverly MA 01915",
    "addr:housenumber":"265",
    "addr:postcode":"01915",
    "addr:street":"Cabot St",
    "iso:country":"US",
    "sg:address":"265 Cabot St",
    "sg:city":"Beverly",
    "sg:classifiers":[
        {
            "category":"Restaurant",
            "type":"Food & Drink"
        }
    ],
    "sg:phone":"+1 978 922 0042",
    "sg:postcode":"01915",
    "sg:province":"MA",
    "sg:tags":[
        "cafe"
    ],
    "sg:website":"www.atomicafe.com",
    "wof:name":"Atomic Cafe",
    "wof:placetype":"venue"
},
  "geometry": {"coordinates":[-70.877973,42.54924],"type":"Point"}
}