{
  "type": "Feature",
  "properties": {
    "addr:full": "4 Edmund Brigham Way Westborough MA 01581",
    "addr:housenumber": "4",
    "addr:postcode": "01581",
    "addr:street": "Edmund Brigham Way",
    "iso:country": "US",
    "sg:address": "4 Edmund Brigham Way",
    "sg:city": "Westborough",
    "sg:classifiers": [
      {
        "category": "Shopping",
        "subcategory": "Hobbies, Toys, \u0026 Games",
        "type": "Retail Goods"
      }
    ],
    "sg:phone": "+1 508 366 7738",
    "sg:postcode": "01581",
    "sg:province": "MA",
    "wof:name": "Arsta Toys",
    "wof:placetype": "venue"
  },
  "geometry": {"coordinates":[-71.612671,42.253488],"type":"Point"}
}
