{
  "type": "Feature",
  "properties": {
    "iso:country":"US",
    "sg:address":"340 W Brookfield Rd",
    "sg:city":"New Braintree",
    "sg:classifiers":[
        {
            "category":"Government",
            "subcategory":"Police Station",
            "type":"Public Place"
        }
    ],
    "sg:phone":"+1 508 867 1000",
    "sg:postcode":"01531",
    "sg:province":"MA",
    "sg:tags":[
        "department"
    ],
    "wof:name":"State Police",
    "wof:placetype":"venue"
},
  "geometry": {"coordinates":[-72.132013,42.308816],"type":"Point"}
}