{
  "type": "Feature",
  "properties": {
    "iso:country":"US",
    "sg:address":"15 Kimball Rd",
    "sg:city":"Boxford",
    "sg:classifiers":[
        {
            "category":"Professional",
            "subcategory":"Art Services",
            "type":"Services"
        }
    ],
    "sg:phone":"+1   ",
    "sg:postcode":"01921",
    "sg:province":"MA",
    "sg:tags":[
        "commercial",
        "design"
    ],
    "wof:name":"Blue Sky Ltd",
    "wof:placetype":"venue"
},
  "geometry": {"coordinates":[-71.060638,42.705557],"type":"Point"}
}