{
  "type": "Feature",
  "properties": {
    "addr:full":"114 Alden St Duxbury MA 02332",
    "addr:housenumber":"114",
    "addr:postcode":"02332",
    "addr:street":"Alden St",
    "iso:country":"US",
    "sg:address":"114 Alden St",
    "sg:city":"Duxbury",
    "sg:classifiers":[
        {
            "category":"Real Estate",
            "subcategory":"Architect",
            "type":"Services"
        }
    ],
    "sg:phone":"+1 781 934 2150",
    "sg:postcode":"02332",
    "sg:province":"MA",
    "sg:tags":[
        "designer",
        "architectural"
    ],
    "wof:name":"Williams Design Studio",
    "wof:placetype":"venue"
},
  "geometry": {"coordinates":[-70.68635999999999,42.046217],"type":"Point"}
}