{
  "type": "Feature",
  "properties": {
    "iso:country":"US",
    "sg:address":"27 Chandler St",
    "sg:city":"Worcester",
    "sg:classifiers":[
        {
            "category":"Freight",
            "type":"Transportation"
        }
    ],
    "sg:phone":"+1 508 752 5581",
    "sg:postcode":"01609",
    "sg:province":"MA",
    "sg:tags":[
        "mover"
    ],
    "wof:name":"O'Connell Movers",
    "wof:placetype":"venue"
},
  "geometry": {"coordinates":[-71.80626700000001,42.260109],"type":"Point"}
}