{
  "type": "Feature",
  "properties": {
    "iso:country":"US",
    "sg:address":"3 Collins St",
    "sg:city":"Danvers",
    "sg:classifiers":[
        {
            "category":"Shopping",
            "subcategory":"Discount & Variety Stores",
            "type":"Retail Goods"
        }
    ],
    "sg:phone":"+1 978 774 9502",
    "sg:postcode":"01923",
    "sg:province":"MA",
    "wof:name":"Highland Variety",
    "wof:placetype":"venue"
},
  "geometry": {"coordinates":[-70.958572,42.560478],"type":"Point"}
}