{
  "type": "Feature",
  "properties": {
    "iso:country":"US",
    "sg:address":"475 Moody St",
    "sg:city":"Waltham",
    "sg:classifiers":[
        {
            "category":"Restaurant",
            "type":"Food & Drink"
        }
    ],
    "sg:menulink":"http://www.allmenus.com/ma/waltham/171558-little-india/menu/",
    "sg:phone":"+1 781 894 8755",
    "sg:postcode":"02453",
    "sg:province":"MA",
    "sg:tags":[
        "indian",
        "asian"
    ],
    "wof:name":"Little India",
    "wof:placetype":"venue"
},
  "geometry": {"coordinates":[-71.23746800000001,42.367939],"type":"Point"}
}