{
  "type": "Feature",
  "properties": {
    "addr:full": "295 Webster St Hanover MA 02339",
    "addr:housenumber": "295",
    "addr:postcode": "02339",
    "addr:street": "Webster St",
    "iso:country": "US",
    "sg:address": "295 Webster St",
    "sg:city": "Hanover",
    "sg:classifiers": [
      {
        "category": "Retail",
        "subcategory": "Auto Repair",
        "type": "Services"
      }
    ],
    "sg:phone": "+1   ",
    "sg:postcode": "02339",
    "sg:province": "MA",
    "sg:tags": [
      "automotive"
    ],
    "wof:name": "Karls Radiator",
    "wof:placetype": "venue"
  },
  "geometry": {"coordinates":[-70.858576,42.153145],"type":"Point"}
}
