{
  "type": "Feature",
  "properties": {
    "iso:country":"US",
    "sg:address":"295 Webster St",
    "sg:city":"Hanover",
    "sg:classifiers":[
        {
            "category":"Retail",
            "subcategory":"Auto Repair",
            "type":"Services"
        }
    ],
    "sg:phone":"+1   ",
    "sg:postcode":"02339",
    "sg:province":"MA",
    "sg:tags":[
        "automotive"
    ],
    "wof:name":"Karls Radiator",
    "wof:placetype":"venue"
},
  "geometry": {"coordinates":[-70.858576,42.153145],"type":"Point"}
}