{
  "type": "Feature",
  "properties": {
    "iso:country":"US",
    "sg:address":"24 Wachusett Dr",
    "sg:city":"Lexington",
    "sg:classifiers":[
        {
            "category":"Professional",
            "subcategory":"Computer Services",
            "type":"Services"
        }
    ],
    "sg:phone":"+1   ",
    "sg:postcode":"02421",
    "sg:province":"MA",
    "sg:tags":[
        "consulting",
        "software"
    ],
    "wof:name":"Metaglue Corparation",
    "wof:placetype":"venue"
},
  "geometry": {"coordinates":[-71.23978,42.437411],"type":"Point"}
}