{
  "type": "Feature",
  "properties": {
    "addr:full":"8 McGrath Hwy Somerville MA 02143",
    "addr:housenumber":"8",
    "addr:postcode":"02143",
    "addr:street":"Mcgrath Hwy",
    "iso:country":"US",
    "sg:address":"8 McGrath Hwy",
    "sg:city":"Somerville",
    "sg:classifiers":[
        {
            "category":"Shopping",
            "subcategory":"Pharmacy",
            "type":"Retail Goods"
        }
    ],
    "sg:phone":"+1 617 628 2870",
    "sg:postcode":"02143",
    "sg:province":"MA",
    "wof:name":"Osco Drug",
    "wof:placetype":"venue"
},
  "geometry": {"coordinates":[-71.085477,42.375302],"type":"Point"}
}