{
  "type": "Feature",
  "properties": {
    "addr:full":"114 Emerson Rd Longmeadow MA 01106",
    "addr:housenumber":"114",
    "addr:postcode":"01106",
    "addr:street":"Emerson Rd",
    "iso:country":"US",
    "sg:address":"114 Emerson Rd",
    "sg:city":"Longmeadow",
    "sg:classifiers":[
        {
            "category":"Real Estate",
            "subcategory":"Real Estate Operator",
            "type":"Services"
        }
    ],
    "sg:phone":"+1 413 567 0601",
    "sg:postcode":"01106",
    "sg:province":"MA",
    "sg:tags":[
        "apartment"
    ],
    "wof:name":"Emerson Manor",
    "wof:placetype":"venue"
},
  "geometry": {"coordinates":[-72.588975,42.057812],"type":"Point"}
}