{
  "type": "Feature",
  "properties": {
    "iso:country":"US",
    "sg:address":"157 Pawtucket Blvd",
    "sg:city":"Lowell",
    "sg:classifiers":[
        {
            "category":"Retail",
            "subcategory":"Auto Repair",
            "type":"Services"
        }
    ],
    "sg:phone":"+1 978 458 8888",
    "sg:postcode":"01854",
    "sg:province":"MA",
    "sg:tags":[
        "body",
        "automobile",
        "removal",
        "dent",
        "windshield",
        "painting",
        "repairing"
    ],
    "sg:website":"http://www.hamelbros.com",
    "wof:name":"Hamel Bros Service Inc",
    "wof:placetype":"venue"
},
  "geometry": {"coordinates":[-71.340729,42.643261],"type":"Point"}
}