{
  "type": "Feature",
  "properties": {
    "addr:full": "157 Pawtucket Blvd Lowell MA 01854",
    "addr:housenumber": "157",
    "addr:postcode": "01854",
    "addr:street": "Pawtucket Blvd",
    "iso:country": "US",
    "ovtr:label": "Hamel Bros Service Inc, 157 Pawtucket Blvd Lowell MA US",
    "ovtr:similarity": 1.9518380165100098,
    "sg:address": "157 Pawtucket Blvd",
    "sg:city": "Lowell",
    "sg:classifiers": [
      {
        "category": "Retail",
        "subcategory": "Auto Repair",
        "type": "Services"
      }
    ],
    "sg:phone": "+1 978 458 8888",
    "sg:postcode": "01854",
    "sg:province": "MA",
    "sg:tags": [
      "body",
      "automobile",
      "removal",
      "dent",
      "windshield",
      "painting",
      "repairing"
    ],
    "sg:website": "http://www.hamelbros.com",
    "wof:name": "Hamel Bros Service Inc",
    "wof:placetype": "venue"
  },
  "geometry": {"coordinates":[-71.340729,42.643261],"type":"Point"}
}
