{
  "type": "Feature",
  "properties": {
    "iso:country":"US",
    "sg:address":"295 Old Littleton Rd",
    "sg:city":"Harvard",
    "sg:classifiers":[
        {
            "category":"Home & Garden",
            "subcategory":"Home Furnishings",
            "type":"Retail Goods"
        }
    ],
    "sg:phone":"+1 978 456 1258",
    "sg:postcode":"01451",
    "sg:province":"MA",
    "sg:tags":[
        "utensil",
        "cooking"
    ],
    "wof:name":"Apple Of Your Pie",
    "wof:placetype":"venue"
},
  "geometry": {"coordinates":[-71.546072,42.517549],"type":"Point"}
}