{
  "type": "Feature",
  "properties": {
    "addr:full":"1502 Providence Hwy Norwood MA 02062",
    "addr:housenumber":"1502",
    "addr:postcode":"02062",
    "addr:street":"Providence Hwy",
    "iso:country":"US",
    "sg:address":"1502 Providence Hwy",
    "sg:city":"Norwood",
    "sg:classifiers":[
        {
            "category":"Building & Trades",
            "subcategory":"Construction",
            "type":"Services"
        }
    ],
    "sg:phone":"+1 781 899 6616",
    "sg:postcode":"02062",
    "sg:province":"MA",
    "sg:tags":[
        "insulation",
        "heat",
        "contractor"
    ],
    "wof:name":"Rogers Insulation Specialists",
    "wof:placetype":"venue"
},
  "geometry": {"coordinates":[-71.200266,42.160342],"type":"Point"}
}