{
  "type": "Feature",
  "properties": {
    "iso:country":"US",
    "sg:address":"50 University Ave",
    "sg:city":"Westwood",
    "sg:classifiers":[
        {
            "category":"Parking",
            "subcategory":"Garage",
            "type":"Transportation"
        }
    ],
    "sg:phone":"+1 781 320 0019",
    "sg:postcode":"02090",
    "sg:province":"MA",
    "sg:tags":[
        "lot"
    ],
    "wof:name":"Route 128 Mbta Parking",
    "wof:placetype":"venue"
},
  "geometry": {"coordinates":[-71.150452,42.209982],"type":"Point"}
}