{
  "type": "Feature",
  "properties": {
    "iso:country":"US",
    "sg:address":"140 Dudley St",
    "sg:city":"Roxbury",
    "sg:classifiers":[
        {
            "category":"Restaurant",
            "type":"Food & Drink"
        }
    ],
    "sg:phone":"+1 617 442 8824",
    "sg:postcode":"02119",
    "sg:province":"MA",
    "sg:tags":[
        "deli",
        "pizza"
    ],
    "wof:name":"Joe's Sub Shop",
    "wof:placetype":"venue"
},
  "geometry": {"coordinates":[-71.08390900000001,42.32876],"type":"Point"}
}