{
  "type": "Feature",
  "properties": {
    "addr:full": "140 Dudley St Roxbury MA 02119",
    "addr:housenumber": "140",
    "addr:postcode": "02119",
    "addr:street": "Dudley St",
    "iso:country": "US",
    "sg:address": "140 Dudley St",
    "sg:city": "Roxbury",
    "sg:classifiers": [
      {
        "category": "Restaurant",
        "type": "Food \u0026 Drink"
      }
    ],
    "sg:phone": "+1 617 442 8824",
    "sg:postcode": "02119",
    "sg:province": "MA",
    "sg:tags": [
      "deli",
      "pizza"
    ],
    "wof:name": "Joe's Sub Shop",
    "wof:placetype": "venue"
  },
  "geometry": {"coordinates":[-71.083909,42.32876],"type":"Point"}
}
