{
  "type": "Feature",
  "properties": {
    "addr:full":"99 Oak Ave Lunenburg MA 01462",
    "addr:housenumber":"99",
    "addr:postcode":"01462",
    "addr:street":"Oak Ave",
    "iso:country":"US",
    "sg:address":"99 Oak Ave",
    "sg:city":"Lunenburg",
    "sg:classifiers":[
        {
            "category":"Professional",
            "subcategory":"Business Services",
            "type":"Services"
        }
    ],
    "sg:phone":"+1   ",
    "sg:postcode":"01462",
    "sg:province":"MA",
    "wof:name":"Lora Enterprise Inc",
    "wof:placetype":"venue"
},
  "geometry": {"coordinates":[-71.72171299999999,42.600548],"type":"Point"}
}