{
  "type": "Feature",
  "properties": {
    "addr:full":"358 W Main St Hyannis MA 02601",
    "addr:housenumber":"358",
    "addr:postcode":"02601",
    "addr:street":"W Main St",
    "iso:country":"US",
    "sg:address":"358 W Main St",
    "sg:city":"Hyannis",
    "sg:classifiers":[
        {
            "category":"Building & Trades",
            "subcategory":"Pest Control",
            "type":"Services"
        }
    ],
    "sg:phone":"+1 508 771 2847",
    "sg:postcode":"02601",
    "sg:province":"MA",
    "sg:website":"www.fowlerandsonsinc.com",
    "wof:name":"James A Fowler & Sons Inc",
    "wof:placetype":"venue"
},
  "geometry": {"coordinates":[-70.31050500000001,41.648981],"type":"Point"}
}