{
  "type": "Feature",
  "properties": {
    "addr:full": "3 Gill St Woburn MA 01801",
    "addr:housenumber": "3",
    "addr:postcode": "01801",
    "addr:street": "Gill St",
    "iso:country": "US",
    "sg:address": "3 Gill St",
    "sg:city": "Woburn",
    "sg:classifiers": [
      {
        "category": "Real Estate",
        "subcategory": "Real Estate Agent",
        "type": "Services"
      }
    ],
    "sg:phone": "+1 781 935 8002",
    "sg:postcode": "01801",
    "sg:province": "MA",
    "wof:name": "Flexplay Technologies Inc",
    "wof:placetype": "venue"
  },
  "geometry": {"coordinates":[-71.146938,42.509792],"type":"Point"}
}
