{
  "type": "Feature",
  "properties": {
    "addr:full": "21 Ironstone St Millville MA 01529",
    "addr:housenumber": "21",
    "addr:postcode": "01529",
    "addr:street": "Ironstone St",
    "iso:country": "US",
    "sg:address": "21 Ironstone St",
    "sg:city": "Millville",
    "sg:classifiers": [
      {
        "category": "Organizations",
        "subcategory": "Community Association",
        "type": "Services"
      }
    ],
    "sg:phone": "+1 508 883 9510",
    "sg:postcode": "01529",
    "sg:province": "MA",
    "sg:tags": [
      "club"
    ],
    "wof:name": "Polish American Citizens Club Inc",
    "wof:placetype": "venue"
  },
  "geometry": {"coordinates":[-71.583615,42.026307],"type":"Point"}
}
