{
  "type": "Feature",
  "properties": {
    "addr:full":"384 School St Webster MA 01570",
    "addr:housenumber":"384",
    "addr:postcode":"01570",
    "addr:street":"School St",
    "iso:country":"US",
    "sg:address":"384 School St",
    "sg:city":"Webster",
    "sg:classifiers":[
        {
            "category":"Retail",
            "subcategory":"Portrait Studio",
            "type":"Services"
        },
        {
            "category":"Professional",
            "subcategory":"Art Services",
            "type":"Services"
        }
    ],
    "sg:phone":"+1 508 943 1176",
    "sg:postcode":"01570",
    "sg:province":"MA",
    "sg:tags":[
        "photo",
        "photography",
        "commercial"
    ],
    "sg:website":"www.curtiscleaves.com",
    "wof:name":"Curtis Cleaves Photographers",
    "wof:placetype":"venue"
},
  "geometry": {"coordinates":[-71.883549,42.04506],"type":"Point"}
}