{
  "type": "Feature",
  "properties": {
    "iso:country":"US",
    "sg:address":"18 Bellevue Ave",
    "sg:city":"Cambridge",
    "sg:classifiers":[
        {
            "category":"Health Services",
            "subcategory":"Health Practitioner",
            "type":"Services"
        }
    ],
    "sg:phone":"+1 617 547 6542",
    "sg:postcode":"02140",
    "sg:province":"MA",
    "sg:tags":[
        "psychotherapist"
    ],
    "wof:name":"Linda Miller",
    "wof:placetype":"venue"
},
  "geometry": {"coordinates":[-71.12589699999999,42.385953],"type":"Point"}
}