{
  "type": "Feature",
  "properties": {
    "addr:full": "18 Bellevue Ave Cambridge MA 02140",
    "addr:housenumber": "18",
    "addr:postcode": "02140",
    "addr:street": "Bellevue Ave",
    "iso:country": "US",
    "sg:address": "18 Bellevue Ave",
    "sg:city": "Cambridge",
    "sg:classifiers": [
      {
        "category": "Health Services",
        "subcategory": "Health Practitioner",
        "type": "Services"
      }
    ],
    "sg:phone": "+1 617 547 6542",
    "sg:postcode": "02140",
    "sg:province": "MA",
    "sg:tags": [
      "psychotherapist"
    ],
    "wof:name": "Linda Miller",
    "wof:placetype": "venue"
  },
  "geometry": {"coordinates":[-71.125897,42.385953],"type":"Point"}
}
