{
  "type": "Feature",
  "properties": {
    "addr:full": "282 Bussey St Dedham MA 02026",
    "addr:housenumber": "282",
    "addr:postcode": "02026",
    "addr:street": "Bussey St",
    "iso:country": "US",
    "sg:address": "282 Bussey St",
    "sg:city": "Dedham",
    "sg:classifiers": [
      {
        "category": "Food \u0026 Beverages",
        "subcategory": "Liquor \u0026 Beverages",
        "type": "Retail Goods"
      }
    ],
    "sg:phone": "+1 781 329 8800",
    "sg:postcode": "02026",
    "sg:province": "MA",
    "wof:name": "Best Friends Cocoa",
    "wof:placetype": "venue"
  },
  "geometry": {"coordinates":[-71.154417,42.247777],"type":"Point"}
}
