{
  "type": "Feature",
  "properties": {
    "iso:country":"US",
    "sg:address":"117 Kendall St",
    "sg:city":"Framingham",
    "sg:classifiers":[
        {
            "category":"Organizations",
            "subcategory":"Religious Organization",
            "type":"Services"
        }
    ],
    "sg:phone":"+1 508 628 3875",
    "sg:postcode":"01702",
    "sg:province":"MA",
    "wof:name":"International Minister New",
    "wof:placetype":"venue"
},
  "geometry": {"coordinates":[-71.41525900000001,42.27834],"type":"Point"}
}