{
  "type": "Feature",
  "properties": {
    "addr:full": "117 Kendall St Framingham MA 01702",
    "addr:housenumber": "117",
    "addr:postcode": "01702",
    "addr:street": "Kendall St",
    "iso:country": "US",
    "sg:address": "117 Kendall St",
    "sg:city": "Framingham",
    "sg:classifiers": [
      {
        "category": "Organizations",
        "subcategory": "Religious Organization",
        "type": "Services"
      }
    ],
    "sg:phone": "+1 508 628 3875",
    "sg:postcode": "01702",
    "sg:province": "MA",
    "wof:name": "International Minister New",
    "wof:placetype": "venue"
  },
  "geometry": {"coordinates":[-71.415259,42.27834],"type":"Point"}
}
