{
  "type": "Feature",
  "properties": {
    "addr:full": "36 Border St West Newton MA 02465",
    "addr:housenumber": "36",
    "addr:postcode": "02465",
    "addr:street": "Border St",
    "iso:country": "US",
    "sg:address": "36 Border St",
    "sg:city": "West Newton",
    "sg:classifiers": [
      {
        "category": "Building \u0026 Trades",
        "subcategory": "Construction",
        "type": "Services"
      }
    ],
    "sg:phone": "+1 617 969 1418",
    "sg:postcode": "02465",
    "sg:province": "MA",
    "sg:tags": [
      "general",
      "contractor"
    ],
    "wof:name": "Rosebud Construction Rmdlng",
    "wof:placetype": "venue"
  },
  "geometry": {"coordinates":[-71.231557,42.348355],"type":"Point"}
}
