{
  "type": "Feature",
  "properties": {
    "iso:country":"US",
    "sg:address":"37 Harrison Ave",
    "sg:city":"Gloucester",
    "sg:classifiers":[
        {
            "category":"Building & Trades",
            "subcategory":"Cleaning & Sanitation",
            "type":"Services"
        }
    ],
    "sg:phone":"+1 978 282 1414",
    "sg:postcode":"01930",
    "sg:province":"MA",
    "sg:tags":[
        "house"
    ],
    "wof:name":"Monarch Cleaning",
    "wof:placetype":"venue"
},
  "geometry": {"coordinates":[-70.649625,42.623722],"type":"Point"}
}