{
  "type": "Feature",
  "properties": {
    "iso:country":"US",
    "sg:address":"512 North Rd",
    "sg:city":"Chilmark",
    "sg:classifiers":[
        {
            "category":"Restaurant",
            "type":"Food & Drink"
        }
    ],
    "sg:phone":"+1 508 645 2679",
    "sg:postcode":"02535",
    "sg:province":"MA",
    "wof:name":"Home Port Restaurant",
    "wof:placetype":"venue"
},
  "geometry": {"coordinates":[-70.76369800000001,41.351357],"type":"Point"}
}