{
  "type": "Feature",
  "properties": {
    "addr:full": "512 North Rd Chilmark MA 02535",
    "addr:housenumber": "512",
    "addr:postcode": "02535",
    "addr:street": "North Rd",
    "iso:country": "US",
    "sg:address": "512 North Rd",
    "sg:city": "Chilmark",
    "sg:classifiers": [
      {
        "category": "Restaurant",
        "type": "Food \u0026 Drink"
      }
    ],
    "sg:phone": "+1 508 645 2679",
    "sg:postcode": "02535",
    "sg:province": "MA",
    "wof:name": "Home Port Restaurant",
    "wof:placetype": "venue"
  },
  "geometry": {"coordinates":[-70.763698,41.351357],"type":"Point"}
}
