{
  "type": "Feature",
  "properties": {
    "iso:country":"US",
    "sg:address":"1064 S Main St",
    "sg:city":"Bellingham",
    "sg:classifiers":[
        {
            "category":"Building & Trades",
            "subcategory":"Electrical",
            "type":"Services"
        }
    ],
    "sg:phone":"+1 508 883 6445",
    "sg:postcode":"02019",
    "sg:province":"MA",
    "sg:tags":[
        "electric",
        "contractor"
    ],
    "wof:name":"Energy Electric Co",
    "wof:placetype":"venue"
},
  "geometry": {"coordinates":[-71.47624399999999,42.07533],"type":"Point"}
}