{
  "type": "Feature",
  "properties": {
    "addr:full": "1064 S Main St Bellingham MA 02019",
    "addr:housenumber": "1064",
    "addr:postcode": "02019",
    "addr:street": "S Main St",
    "iso:country": "US",
    "sg:address": "1064 S Main St",
    "sg:city": "Bellingham",
    "sg:classifiers": [
      {
        "category": "Building \u0026 Trades",
        "subcategory": "Electrical",
        "type": "Services"
      }
    ],
    "sg:phone": "+1 508 883 6445",
    "sg:postcode": "02019",
    "sg:province": "MA",
    "sg:tags": [
      "electric",
      "contractor"
    ],
    "wof:name": "Energy Electric Co",
    "wof:placetype": "venue"
  },
  "geometry": {"coordinates":[-71.476244,42.07533],"type":"Point"}
}
