{
  "type": "Feature",
  "properties": {
    "iso:country":"US",
    "sg:address":"214 S Meadow Rd Rear S",
    "sg:city":"Plymouth",
    "sg:classifiers":[
        {
            "category":"Manufacturing",
            "subcategory":"Tools & Machinery",
            "type":"Manufacturing & Wholesale Goods"
        },
        {
            "category":"Wholesale",
            "subcategory":"Machinery & Supplies",
            "type":"Manufacturing & Wholesale Goods"
        }
    ],
    "sg:phone":"+1 508 747 1490",
    "sg:postcode":"02360",
    "sg:province":"MA",
    "sg:tags":[
        "building",
        "equipment",
        "construction",
        "industrial"
    ],
    "sg:website":"http://www.praziusa.com",
    "wof:name":"Prazi, U.S.A., Inc.",
    "wof:placetype":"venue"
},
  "geometry": {"coordinates":[-70.73,41.914958],"type":"Point"}
}