{
  "type": "Feature",
  "properties": {
    "addr:full": "214 S Meadow Rd Rear S Plymouth MA 02360",
    "addr:housenumber": "214",
    "addr:postcode": "02360",
    "addr:street": "S Meadow Rd Rear S",
    "iso:country": "US",
    "sg:address": "214 S Meadow Rd Rear S",
    "sg:city": "Plymouth",
    "sg:classifiers": [
      {
        "category": "Manufacturing",
        "subcategory": "Tools \u0026 Machinery",
        "type": "Manufacturing \u0026 Wholesale Goods"
      },
      {
        "category": "Wholesale",
        "subcategory": "Machinery \u0026 Supplies",
        "type": "Manufacturing \u0026 Wholesale Goods"
      }
    ],
    "sg:phone": "+1 508 747 1490",
    "sg:postcode": "02360",
    "sg:province": "MA",
    "sg:tags": [
      "building",
      "equipment",
      "construction",
      "industrial"
    ],
    "sg:website": "http://www.praziusa.com",
    "wof:name": "Prazi, U.S.A., Inc.",
    "wof:placetype": "venue"
  },
  "geometry": {"coordinates":[-70.73,41.914958],"type":"Point"}
}
