{
  "type": "Feature",
  "properties": {
    "addr:full":"164 Leeward Rd Buzzards Bay MA 02532",
    "addr:housenumber":"164",
    "addr:postcode":"02532",
    "addr:street":"Leeward Rd",
    "iso:country":"US",
    "sg:address":"164 Leeward Rd",
    "sg:city":"Buzzards Bay",
    "sg:classifiers":[
        {
            "category":"Restaurant",
            "type":"Food & Drink"
        }
    ],
    "sg:phone":"+1 508 759 9390",
    "sg:postcode":"02532",
    "sg:province":"MA",
    "wof:name":"Mashnee Island Grill & Beach Bar",
    "wof:placetype":"venue"
},
  "geometry": {"coordinates":[-70.63462699999999,41.715776],"type":"Point"}
}