{
  "type": "Feature",
  "properties": {
    "iso:country":"US",
    "sg:address":"55 Fruit St",
    "sg:city":"Boston",
    "sg:classifiers":[
        {
            "category":"Health Services",
            "subcategory":"Doctor",
            "type":"Services"
        }
    ],
    "sg:phone":"+1 617 724 0365",
    "sg:postcode":"02114",
    "sg:province":"MA",
    "sg:tags":[
        "physician",
        "surgeon"
    ],
    "wof:name":"Shellito Paul C MD",
    "wof:placetype":"venue"
},
  "geometry": {"coordinates":[-71.069801,42.3624],"type":"Point"}
}