{
  "type": "Feature",
  "properties": {
    "addr:full": "125 Nagog Park Acton MA 01720",
    "addr:housenumber": "125",
    "addr:postcode": "01720",
    "addr:street": "Nagog Park",
    "iso:country": "US",
    "sg:address": "125 Nagog Park",
    "sg:city": "Acton",
    "sg:classifiers": [
      {
        "category": "Manufacturing",
        "subcategory": "Printing",
        "type": "Manufacturing \u0026 Wholesale Goods"
      }
    ],
    "sg:phone": "+1 978 263 1212",
    "sg:postcode": "01720",
    "sg:province": "MA",
    "sg:tags": [
      "manifold",
      "business",
      "form"
    ],
    "wof:name": "Uniform Printing \u0026 Supply",
    "wof:placetype": "venue"
  },
  "geometry": {"coordinates":[-71.422031,42.522321],"type":"Point"}
}
