{
  "type": "Feature",
  "properties": {
    "iso:country":"US",
    "sg:address":"125 Nagog Park",
    "sg:city":"Acton",
    "sg:classifiers":[
        {
            "category":"Manufacturing",
            "subcategory":"Printing",
            "type":"Manufacturing & Wholesale Goods"
        }
    ],
    "sg:phone":"+1 978 263 1212",
    "sg:postcode":"01720",
    "sg:province":"MA",
    "sg:tags":[
        "manifold",
        "business",
        "form"
    ],
    "wof:name":"Uniform Printing & Supply",
    "wof:placetype":"venue"
},
  "geometry": {"coordinates":[-71.422031,42.522321],"type":"Point"}
}