{
  "type": "Feature",
  "properties": {
    "addr:full": "75 Central St Wellesley MA 02482",
    "addr:housenumber": "75",
    "addr:postcode": "02482",
    "addr:street": "Central St",
    "iso:country": "US",
    "sg:address": "75 Central St",
    "sg:city": "Wellesley",
    "sg:classifiers": [
      {
        "category": "Communications",
        "type": "Services"
      }
    ],
    "sg:phone": "+1   ",
    "sg:postcode": "02482",
    "sg:province": "MA",
    "sg:tags": [
      "development",
      "tower",
      "leasing",
      "antenna"
    ],
    "wof:name": "Evergreen Wireless Group  LLC",
    "wof:placetype": "venue"
  },
  "geometry": {"coordinates":[-71.298904,42.296007],"type":"Point"}
}
