{
  "type": "Feature",
  "properties": {
    "iso:country":"US",
    "sg:address":"109 Page Rd",
    "sg:city":"Lincoln",
    "sg:classifiers":[
        {
            "category":"Building & Trades",
            "subcategory":"Construction",
            "type":"Services"
        }
    ],
    "sg:phone":"+1 781 259 1800",
    "sg:postcode":"01773",
    "sg:province":"MA",
    "sg:tags":[
        "contractor"
    ],
    "wof:name":"Panetta Construction Co Inc",
    "wof:placetype":"venue"
},
  "geometry": {"coordinates":[-71.277199,42.430801],"type":"Point"}
}