{
  "type": "Feature",
  "properties": {
    "iso:country":"US",
    "sg:address":"197 Nantasket Ave",
    "sg:city":"Hull",
    "sg:classifiers":[
        {
            "category":"Recreation",
            "subcategory":"Picnic Area",
            "type":"Entertainment"
        }
    ],
    "sg:phone":"+1 781 925 0011",
    "sg:postcode":"02045",
    "sg:province":"MA",
    "sg:tags":[
        "place",
        "arcade",
        "amusement"
    ],
    "sg:website":"http://www.dreammachine.com",
    "wof:name":"Dream Machine Of Nantasket",
    "wof:placetype":"venue"
},
  "geometry": {"coordinates":[-70.855019,42.269547],"type":"Point"}
}