{
  "type": "Feature",
  "properties": {
    "addr:full": "40 Dunster Rd Sudbury MA 01776",
    "addr:housenumber": "40",
    "addr:postcode": "01776",
    "addr:street": "Dunster Rd",
    "iso:country": "US",
    "sg:address": "40 Dunster Rd",
    "sg:city": "Sudbury",
    "sg:classifiers": [
      {
        "category": "Communications",
        "subcategory": "Film \u0026 Video Production",
        "type": "Services"
      }
    ],
    "sg:phone": "+1 978 443 0450",
    "sg:postcode": "01776",
    "sg:province": "MA",
    "sg:tags": [
      "motion",
      "taping"
    ],
    "wof:name": "Waking State Film Productions",
    "wof:placetype": "venue"
  },
  "geometry": {"coordinates":[-71.411692,42.414082],"type":"Point"}
}
