{
  "type": "Feature",
  "properties": {
    "addr:full":"35 Torrey St Brockton MA 02301",
    "addr:housenumber":"35",
    "addr:postcode":"02301",
    "addr:street":"Torrey St",
    "iso:country":"US",
    "sg:address":"35 Torrey St",
    "sg:city":"Brockton",
    "sg:classifiers":[
        {
            "category":"Restaurant",
            "type":"Food & Drink"
        }
    ],
    "sg:phone":"+1 508 588 1331",
    "sg:postcode":"02301",
    "sg:province":"MA",
    "sg:tags":[
        "pizza"
    ],
    "wof:name":"West Side Pizza & Sub Shop",
    "wof:placetype":"venue"
},
  "geometry": {"coordinates":[-71.04273499999999,42.074456],"type":"Point"}
}