{
  "type": "Feature",
  "properties": {
    "iso:country":"US",
    "sg:address":"124 Jewett St",
    "sg:city":"Georgetown",
    "sg:classifiers":[
        {
            "category":"Building & Trades",
            "subcategory":"Landscaping Services",
            "type":"Services"
        }
    ],
    "sg:phone":"+1 978 352 5559",
    "sg:postcode":"01833",
    "sg:province":"MA",
    "sg:tags":[
        "landscape",
        "contractor"
    ],
    "wof:name":"Prime Landscape Contractors",
    "wof:placetype":"venue"
},
  "geometry": {"coordinates":[-70.94819699999999,42.73236],"type":"Point"}
}