{
  "type": "Feature",
  "properties": {
    "addr:full": "124 Jewett St Georgetown MA 01833",
    "addr:housenumber": "124",
    "addr:postcode": "01833",
    "addr:street": "Jewett St",
    "iso:country": "US",
    "sg:address": "124 Jewett St",
    "sg:city": "Georgetown",
    "sg:classifiers": [
      {
        "category": "Building \u0026 Trades",
        "subcategory": "Landscaping Services",
        "type": "Services"
      }
    ],
    "sg:phone": "+1 978 352 5559",
    "sg:postcode": "01833",
    "sg:province": "MA",
    "sg:tags": [
      "landscape",
      "contractor"
    ],
    "wof:name": "Prime Landscape Contractors",
    "wof:placetype": "venue"
  },
  "geometry": {"coordinates":[-70.948197,42.73236],"type":"Point"}
}
