{
  "type": "Feature",
  "properties": {
    "iso:country":"US",
    "sg:address":"3928 Washington St",
    "sg:city":"Roslindale",
    "sg:classifiers":[
        {
            "category":"Building & Trades",
            "subcategory":"Cleaning & Sanitation",
            "type":"Services"
        }
    ],
    "sg:phone":"+1   ",
    "sg:postcode":"02131",
    "sg:province":"MA",
    "sg:tags":[
        "maintenance"
    ],
    "wof:name":"Tapias Cleaning Services",
    "wof:placetype":"venue"
},
  "geometry": {"coordinates":[-71.119653,42.294331],"type":"Point"}
}