{
  "type": "Feature",
  "properties": {
    "addr:full": "3928 Washington St Roslindale MA 02131",
    "addr:housenumber": "3928",
    "addr:postcode": "02131",
    "addr:street": "Washington St",
    "iso:country": "US",
    "sg:address": "3928 Washington St",
    "sg:city": "Roslindale",
    "sg:classifiers": [
      {
        "category": "Building \u0026 Trades",
        "subcategory": "Cleaning \u0026 Sanitation",
        "type": "Services"
      }
    ],
    "sg:phone": "+1   ",
    "sg:postcode": "02131",
    "sg:province": "MA",
    "sg:tags": [
      "maintenance"
    ],
    "wof:name": "Tapias Cleaning Services",
    "wof:placetype": "venue"
  },
  "geometry": {"coordinates":[-71.119653,42.294331],"type":"Point"}
}
