{
  "type": "Feature",
  "properties": {
    "iso:country":"US",
    "sg:address":"183 Eldridge St",
    "sg:city":"Taunton",
    "sg:classifiers":[
        {
            "category":"Professional",
            "subcategory":"Accounting & Tax Preparation",
            "type":"Services"
        }
    ],
    "sg:phone":"+1   ",
    "sg:postcode":"02780",
    "sg:province":"MA",
    "wof:name":"Patricia Gove Ea",
    "wof:placetype":"venue"
},
  "geometry": {"coordinates":[-71.107731,41.914374],"type":"Point"}
}