{
  "type": "Feature",
  "properties": {
    "iso:country":"US",
    "sg:address":"1701 Worcester Rd",
    "sg:city":"Framingham",
    "sg:classifiers":[
        {
            "category":"Health Services",
            "subcategory":"Doctor",
            "type":"Services"
        },
        {
            "category":"Health Services",
            "subcategory":"Clinic",
            "type":"Services"
        }
    ],
    "sg:phone":"+1 508 879 5885",
    "sg:postcode":"01701",
    "sg:province":"MA",
    "sg:tags":[
        "psychological",
        "psychologist"
    ],
    "wof:name":"Lmd Psychological Association",
    "wof:placetype":"venue"
},
  "geometry": {"coordinates":[-71.483535,42.297052],"type":"Point"}
}