{
  "type": "Feature",
  "properties": {
    "iso:country":"US",
    "sg:address":"46 Main St",
    "sg:city":"Orleans",
    "sg:classifiers":[
        {
            "category":"Education",
            "subcategory":"Special Training",
            "type":"Public Place"
        }
    ],
    "sg:phone":"+1 508 255 0076",
    "sg:postcode":"02653",
    "sg:province":"MA",
    "sg:tags":[
        "tutoring"
    ],
    "wof:name":"Cape Cod Speech & Language",
    "wof:placetype":"venue"
},
  "geometry": {"coordinates":[-69.990253,41.786772],"type":"Point"}
}