{
  "type": "Feature",
  "properties": {
    "addr:full":"120 Washington St Dorchester MA 02121",
    "addr:housenumber":"120",
    "addr:postcode":"02121",
    "addr:street":"Washington St",
    "iso:country":"US",
    "sg:address":"120 Washington St",
    "sg:city":"Dorchester",
    "sg:classifiers":[
        {
            "category":"Building & Trades",
            "subcategory":"Locksmith",
            "type":"Services"
        }
    ],
    "sg:phone":"+1 617 514 9524",
    "sg:postcode":"02121",
    "sg:province":"MA",
    "sg:tags":[
        "key"
    ],
    "wof:name":"AAA 24 Hour Locksmith Services",
    "wof:placetype":"venue"
},
  "geometry": {"coordinates":[-71.07991699999999,42.30511],"type":"Point"}
}