{
  "type": "Feature",
  "properties": {
    "iso:country":"US",
    "sg:address":"5 Cardinal Dr",
    "sg:city":"Franklin",
    "sg:classifiers":[
        {
            "category":"Professional",
            "subcategory":"Computer Services",
            "type":"Services"
        }
    ],
    "sg:phone":"+1   ",
    "sg:postcode":"02038",
    "sg:province":"MA",
    "sg:tags":[
        "programing",
        "custom"
    ],
    "wof:name":"Levin Assoc",
    "wof:placetype":"venue"
},
  "geometry": {"coordinates":[-71.37165299999999,42.098008],"type":"Point"}
}