{
  "type": "Feature",
  "properties": {
    "addr:full": "1090 Commonwealth Ave Newton MA 02459",
    "addr:housenumber": "1090",
    "addr:postcode": "02459",
    "addr:street": "Commonwealth Ave",
    "iso:country": "US",
    "sg:address": "1090 Commonwealth Ave",
    "sg:city": "Newton",
    "sg:classifiers": [
      {
        "category": "Food \u0026 Beverages",
        "subcategory": "Groceries \u0026 Convenience Stores",
        "type": "Retail Goods"
      }
    ],
    "sg:phone": "+1 617 738 9138",
    "sg:postcode": "02459",
    "sg:province": "MA",
    "sg:tags": [
      "grocer"
    ],
    "wof:name": "Commonwealth Market Inc",
    "wof:placetype": "venue"
  },
  "geometry": {"coordinates":[-71.21016,42.337818],"type":"Point"}
}
