{
  "type": "Feature",
  "properties": {
    "addr:full":"20 W Yarmouth Rd West Yarmouth MA 02673",
    "addr:housenumber":"20",
    "addr:postcode":"02673",
    "addr:street":"W Yarmouth Rd",
    "iso:country":"US",
    "sg:address":"20 W Yarmouth Rd",
    "sg:city":"West Yarmouth",
    "sg:classifiers":[
        {
            "category":"Wholesale",
            "subcategory":"Durable Goods & Equipment",
            "type":"Manufacturing & Wholesale Goods"
        }
    ],
    "sg:phone":"+1   ",
    "sg:postcode":"02673",
    "sg:province":"MA",
    "wof:name":"Karting Equipment Supply",
    "wof:placetype":"venue"
},
  "geometry": {"coordinates":[-70.233054,41.651638],"type":"Point"}
}