{
  "type": "Feature",
  "properties": {
    "iso:country":"US",
    "sg:address":"25 Sawyer Passway",
    "sg:city":"Fitchburg",
    "sg:classifiers":[
        {
            "category":"Shopping",
            "subcategory":"Computers & Home Electronics",
            "type":"Retail Goods"
        }
    ],
    "sg:phone":"+1 978 345 5000",
    "sg:postcode":"01420",
    "sg:province":"MA",
    "sg:tags":[
        "medical",
        "software"
    ],
    "wof:name":"Arrhythmia Research Technology",
    "wof:placetype":"venue"
},
  "geometry": {"coordinates":[-71.791399,42.581645],"type":"Point"}
}