{
  "type": "Feature",
  "properties": {
    "iso:country":"US",
    "sg:address":"765 Broadway Rd",
    "sg:city":"Dracut",
    "sg:classifiers":[
        {
            "category":"Professional",
            "subcategory":"Business Services",
            "type":"Services"
        }
    ],
    "sg:phone":"+1   ",
    "sg:postcode":"01826",
    "sg:province":"MA",
    "wof:name":"JD Leasing Group Corp",
    "wof:placetype":"venue"
},
  "geometry": {"coordinates":[-71.275318,42.685403],"type":"Point"}
}