{
  "type": "Feature",
  "properties": {
    "addr:full":"44 Brooks St Brighton MA 02135",
    "addr:housenumber":"44",
    "addr:postcode":"02135",
    "addr:street":"Brooks St",
    "iso:country":"US",
    "sg:address":"44 Brooks St",
    "sg:city":"Brighton",
    "sg:classifiers":[
        {
            "category":"Real Estate",
            "subcategory":"Real Estate Agent",
            "type":"Services"
        }
    ],
    "sg:phone":"+1 617 787 2860",
    "sg:postcode":"02135",
    "sg:province":"MA",
    "wof:name":"Newbridge Realty Group",
    "wof:placetype":"venue"
},
  "geometry": {"coordinates":[-71.162305,42.356218],"type":"Point"}
}