{
  "type": "Feature",
  "properties": {
    "iso:country":"US",
    "sg:address":"392 S Main St",
    "sg:city":"Haverhill",
    "sg:classifiers":[
        {
            "category":"Personal",
            "subcategory":"Tanning Parlor",
            "type":"Services"
        }
    ],
    "sg:phone":"+1 978 374 3131",
    "sg:postcode":"01835",
    "sg:province":"MA",
    "sg:tags":[
        "salon"
    ],
    "wof:name":"Beyond The Beach Tanning",
    "wof:placetype":"venue"
},
  "geometry": {"coordinates":[-71.082975,42.765062],"type":"Point"}
}