{
  "type": "Feature",
  "properties": {
    "iso:country":"US",
    "sg:address":"320 Centre Ave",
    "sg:city":"Rockland",
    "sg:classifiers":[
        {
            "category":"Retail",
            "subcategory":"Car Wash",
            "type":"Services"
        }
    ],
    "sg:phone":"+1 781 878 9019",
    "sg:postcode":"02370",
    "sg:province":"MA",
    "sg:tags":[
        "polishing",
        "washing"
    ],
    "wof:name":"Nice N Clean Car Wash",
    "wof:placetype":"venue"
},
  "geometry": {"coordinates":[-70.92692599999999,42.112802],"type":"Point"}
}