{
  "type": "Feature",
  "properties": {
    "iso:country":"US",
    "sg:address":"15 Ararat St",
    "sg:city":"Worcester",
    "sg:classifiers":[
        {
            "category":"Insurance",
            "subcategory":"Insurance Agent",
            "type":"Services"
        }
    ],
    "sg:phone":"+1 508 852 4726",
    "sg:postcode":"01606",
    "sg:province":"MA",
    "sg:tags":[
        "adjuster"
    ],
    "wof:name":"Vaida Adjustment Svc Inc",
    "wof:placetype":"venue"
},
  "geometry": {"coordinates":[-71.80628299999999,42.314437],"type":"Point"}
}