{
  "type": "Feature",
  "properties": {
    "addr:full": "15 Ararat St Worcester MA 01606",
    "addr:housenumber": "15",
    "addr:postcode": "01606",
    "addr:street": "Ararat St",
    "iso:country": "US",
    "sg:address": "15 Ararat St",
    "sg:city": "Worcester",
    "sg:classifiers": [
      {
        "category": "Insurance",
        "subcategory": "Insurance Agent",
        "type": "Services"
      }
    ],
    "sg:phone": "+1 508 852 4726",
    "sg:postcode": "01606",
    "sg:province": "MA",
    "sg:tags": [
      "adjuster"
    ],
    "wof:name": "Vaida Adjustment Svc Inc",
    "wof:placetype": "venue"
  },
  "geometry": {"coordinates":[-71.806283,42.314437],"type":"Point"}
}
