{
  "type": "Feature",
  "properties": {
    "addr:full":"235 Albany Street Cambridge MA 02139",
    "addr:housenumber":"235",
    "addr:postcode":"02139",
    "addr:street":"Albany Street",
    "iso:country":"US",
    "sg:address":"235 Albany Street",
    "sg:city":"Cambridge",
    "sg:classifiers":[
        {
            "category":"Bars & Pubs",
            "subcategory":"Nightclub",
            "type":"Food & Drink"
        }
    ],
    "sg:phone":"+1 617 258 9754",
    "sg:postcode":"02139",
    "sg:province":"MA",
    "sg:tags":[
        "nightlife"
    ],
    "sg:website":"thirsty-ear.mit.edu",
    "wof:name":"The Thirsty Ear Pub",
    "wof:placetype":"venue"
},
  "geometry": {"coordinates":[-71.10089499999999,42.358607],"type":"Point"}
}