{
  "type": "Feature",
  "properties": {
    "addr:full":"6 Heritage Dr Whitinsville MA 01588",
    "addr:housenumber":"6",
    "addr:postcode":"01588",
    "addr:street":"Heritage Dr",
    "iso:country":"US",
    "sg:address":"6 Heritage Dr",
    "sg:city":"Whitinsville",
    "sg:classifiers":[
        {
            "category":"Professional",
            "type":"Services"
        }
    ],
    "sg:phone":"+1 508 234 6100",
    "sg:postcode":"01588",
    "sg:province":"MA",
    "sg:tags":[
        "establishment"
    ],
    "wof:name":"Dayton Technologies",
    "wof:placetype":"venue"
},
  "geometry": {"coordinates":[-71.648278,42.10254],"type":"Point"}
}