{
  "type": "Feature",
  "properties": {
    "addr:full":"266 Brookline St Cambridge MA 02139",
    "addr:housenumber":"266",
    "addr:postcode":"02139",
    "addr:street":"Brookline St",
    "iso:country":"US",
    "sg:address":"266 Brookline St",
    "sg:city":"Cambridge",
    "sg:classifiers":[
        {
            "category":"Retail",
            "subcategory":"Self-service Laundry",
            "type":"Services"
        }
    ],
    "sg:phone":"+1   ",
    "sg:postcode":"02139",
    "sg:province":"MA",
    "sg:tags":[
        "coin"
    ],
    "wof:name":"R & D Laundry",
    "wof:placetype":"venue"
},
  "geometry": {"coordinates":[-71.107428,42.357895],"type":"Point"}
}