{
  "type": "Feature",
  "properties": {
    "iso:country":"US",
    "sg:address":"558 Washington St",
    "sg:city":"Dorchester Ctr",
    "sg:classifiers":[
        {
            "category":"Food & Beverages",
            "subcategory":"Groceries & Convenience Stores",
            "type":"Retail Goods"
        }
    ],
    "sg:phone":"+1 617 825 7601",
    "sg:postcode":"02124",
    "sg:province":"MA",
    "sg:tags":[
        "market"
    ],
    "wof:name":"Carribean Market",
    "wof:placetype":"venue"
},
  "geometry": {"coordinates":[-71.07168299999999,42.292204],"type":"Point"}
}