{
  "type": "Feature",
  "properties": {
    "addr:full": "558 Washington St Dorchester Ctr MA 02124",
    "addr:housenumber": "558",
    "addr:postcode": "02124",
    "addr:street": "Washington St",
    "iso:country": "US",
    "sg:address": "558 Washington St",
    "sg:city": "Dorchester Ctr",
    "sg:classifiers": [
      {
        "category": "Food \u0026 Beverages",
        "subcategory": "Groceries \u0026 Convenience Stores",
        "type": "Retail Goods"
      }
    ],
    "sg:phone": "+1 617 825 7601",
    "sg:postcode": "02124",
    "sg:province": "MA",
    "sg:tags": [
      "market"
    ],
    "wof:name": "Carribean Market",
    "wof:placetype": "venue"
  },
  "geometry": {"coordinates":[-71.071683,42.292204],"type":"Point"}
}
