{
  "type": "Feature",
  "properties": {
    "addr:full": "35 Adin St Hopedale MA 01747",
    "addr:housenumber": "35",
    "addr:postcode": "01747",
    "addr:street": "Adin St",
    "iso:country": "US",
    "sg:address": "35 Adin St",
    "sg:city": "Hopedale",
    "sg:classifiers": [
      {
        "category": "Recreation",
        "type": "Entertainment"
      }
    ],
    "sg:phone": "+1 508 634 6884",
    "sg:postcode": "01747",
    "sg:province": "MA",
    "sg:tags": [
      "concessionaire"
    ],
    "wof:name": "D A Hodgens \u0026 Co",
    "wof:placetype": "venue"
  },
  "geometry": {"coordinates":[-71.534695,42.130141],"type":"Point"}
}
