{
  "type": "Feature",
  "properties": {
    "addr:full":"1376 Concord St Framingham MA 01701",
    "addr:housenumber":"1376",
    "addr:postcode":"01701",
    "addr:street":"Concord St",
    "iso:country":"US",
    "sg:address":"1376 Concord St",
    "sg:city":"Framingham",
    "sg:classifiers":[
        {
            "category":"Personal",
            "type":"Services"
        }
    ],
    "sg:phone":"+1 508 788 0009",
    "sg:postcode":"01701",
    "sg:province":"MA",
    "sg:tags":[
        "electrolysis"
    ],
    "wof:name":"Mary Colvin Electrolysis",
    "wof:placetype":"venue"
},
  "geometry": {"coordinates":[-71.398516,42.317703],"type":"Point"}
}