{
  "type": "Feature",
  "properties": {
    "addr:full":"2235 State Rd Plymouth MA 02360",
    "addr:housenumber":"2235",
    "addr:postcode":"02360",
    "addr:street":"State Rd",
    "iso:country":"US",
    "sg:address":"2235 State Rd",
    "sg:city":"Plymouth",
    "sg:classifiers":[
        {
            "category":"Bakery",
            "type":"Food & Drink"
        },
        {
            "category":"Coffee & Tea",
            "type":"Food & Drink"
        },
        {
            "category":"Bagels",
            "type":"Food & Drink"
        },
        {
            "category":"Donuts",
            "type":"Food & Drink"
        }
    ],
    "sg:menulink":"http://www.allmenus.com/ma/plymouth/142799-dunkin-donuts/menu/",
    "sg:phone":"+1 508 888 7022",
    "sg:postcode":"02360",
    "sg:province":"MA",
    "sg:tags":[
        "american",
        "diner",
        "pastry"
    ],
    "wof:name":"Dunkin' Donuts",
    "wof:placetype":"venue"
},
  "geometry": {"coordinates":[-70.55134,41.822149],"type":"Point"}
}