{
  "type": "Feature",
  "properties": {
    "iso:country":"US",
    "sg:address":"100 University Dr",
    "sg:city":"Amherst",
    "sg:classifiers":[
        {
            "category":"Shopping",
            "subcategory":"Computers & Home Electronics",
            "type":"Retail Goods"
        }
    ],
    "sg:phone":"+1 413 549 0203",
    "sg:postcode":"01002",
    "sg:province":"MA",
    "sg:tags":[
        "software"
    ],
    "sg:website":"www.appecon.com",
    "wof:name":"Applied Econometrics",
    "wof:placetype":"venue"
},
  "geometry": {"coordinates":[-72.53218099999999,42.378881],"type":"Point"}
}