{
  "type": "Feature",
  "properties": {
    "addr:full": "149 Asbury St South Hamilton MA 01982",
    "addr:housenumber": "149",
    "addr:postcode": "01982",
    "addr:street": "Asbury St South",
    "iso:country": "US",
    "sg:address": "149 Asbury St",
    "sg:city": "South Hamilton",
    "sg:classifiers": [
      {
        "category": "Organizations",
        "subcategory": "Religious Organization",
        "type": "Services"
      }
    ],
    "sg:phone": "+1 978 468 4461",
    "sg:postcode": "01982",
    "sg:province": "MA",
    "sg:tags": [
      "church"
    ],
    "sg:website": "www.christchurchhw.org",
    "wof:name": "Christ Church",
    "wof:placetype": "venue"
  },
  "geometry": {"coordinates":[-70.87653,42.616311],"type":"Point"}
}
