{
  "type": "Feature",
  "properties": {
    "iso:country":"US",
    "sg:address":"15 Boston Ave",
    "sg:city":"Somerville",
    "sg:classifiers":[
        {
            "category":"Personal",
            "type":"Services"
        }
    ],
    "sg:phone":"+1 617 628 8272",
    "sg:postcode":"02144",
    "sg:province":"MA",
    "wof:name":"Oriental & Sports Massage",
    "wof:placetype":"venue"
},
  "geometry": {"coordinates":[-71.110452,42.395742],"type":"Point"}
}