{
  "type": "Feature",
  "properties": {
    "addr:full": "8 Fredrickson Rd Billerica MA 01821",
    "addr:housenumber": "8",
    "addr:postcode": "01821",
    "addr:street": "Fredrickson Rd",
    "iso:country": "US",
    "sg:address": "8 Fredrickson Rd",
    "sg:city": "Billerica",
    "sg:classifiers": [
      {
        "category": "Building \u0026 Trades",
        "subcategory": "Construction",
        "type": "Services"
      }
    ],
    "sg:phone": "+1   ",
    "sg:postcode": "01821",
    "sg:province": "MA",
    "sg:tags": [
      "house"
    ],
    "wof:name": "D B Edmonds Inc",
    "wof:placetype": "venue"
  },
  "geometry": {"coordinates":[-71.247374,42.534777],"type":"Point"}
}
