{
  "type": "Feature",
  "properties": {
    "addr:full":"104 Shirley Ave Revere MA 02151",
    "addr:housenumber":"104",
    "addr:postcode":"02151",
    "addr:street":"Shirley Ave",
    "iso:country":"US",
    "sg:address":"104 Shirley Ave",
    "sg:city":"Revere",
    "sg:classifiers":[
        {
            "category":"Building & Trades",
            "subcategory":"Locksmith",
            "type":"Services"
        }
    ],
    "sg:phone":"+1 781 922 9094",
    "sg:postcode":"02151",
    "sg:province":"MA",
    "sg:tags":[
        "key"
    ],
    "wof:name":"24 Hour Emergency Locksmith",
    "wof:placetype":"venue"
},
  "geometry": {"coordinates":[-70.996774,42.408089],"type":"Point"}
}