{
  "type": "Feature",
  "properties": {
    "addr:full":"237 Franklin St Cambridge MA 02139",
    "addr:housenumber":"237",
    "addr:postcode":"02139",
    "addr:street":"Franklin St",
    "iso:country":"US",
    "sg:address":"237 Franklin St",
    "sg:city":"Cambridge",
    "sg:classifiers":[
        {
            "category":"Professional",
            "subcategory":"Management & Consulting",
            "type":"Services"
        }
    ],
    "sg:phone":"+1 617 661 0259",
    "sg:postcode":"02139",
    "sg:province":"MA",
    "sg:tags":[
        "science",
        "consultant",
        "academic"
    ],
    "wof:name":"Solar Environmental Works",
    "wof:placetype":"venue"
},
  "geometry": {"coordinates":[-71.104568,42.364155],"type":"Point"}
}