{
  "type": "Feature",
  "properties": {
    "addr:full": "54 Main St Topsfield MA 01983",
    "addr:housenumber": "54",
    "addr:postcode": "01983",
    "addr:street": "Main St",
    "iso:country": "US",
    "sg:address": "54 Main St",
    "sg:city": "Topsfield",
    "sg:classifiers": [
      {
        "category": "Travel",
        "subcategory": "Travel Agent",
        "type": "Entertainment"
      }
    ],
    "sg:phone": "+1 978 887 6577",
    "sg:postcode": "01983",
    "sg:province": "MA",
    "sg:tags": [
      "agency",
      "bureau"
    ],
    "sg:website": "www.winntravel.com",
    "wof:name": "Winn Travel Svc",
    "wof:placetype": "venue"
  },
  "geometry": {"coordinates":[-70.950253,42.64053],"type":"Point"}
}
