{
  "type": "Feature",
  "properties": {
    "addr:full": "248 Haverhill St Methuen MA 01844",
    "addr:housenumber": "248",
    "addr:postcode": "01844",
    "addr:street": "Haverhill St",
    "iso:country": "US",
    "ovtr:label": "Burger King, 248 Haverhill St Methuen MA US",
    "ovtr:similarity": 3.346407890319824,
    "sg:address": "248 Haverhill St",
    "sg:city": "Methuen",
    "sg:classifiers": [
      {
        "category": "Restaurant",
        "type": "Food \u0026 Drink"
      }
    ],
    "sg:menulink": "http://www.allmenus.com/ma/methuen/197612-burger-king/menu/",
    "sg:phone": "+1 978 688 7846",
    "sg:postcode": "01844",
    "sg:province": "MA",
    "sg:tags": [
      "burger",
      "american"
    ],
    "wof:name": "Burger King",
    "wof:placetype": "venue"
  },
  "geometry": {"coordinates":[-71.204659,42.706546],"type":"Point"}
}
