{
  "type": "Feature",
  "properties": {
    "addr:full":"248 Haverhill St Methuen MA 01844",
    "addr:housenumber":"248",
    "addr:postcode":"01844",
    "addr:street":"Haverhill St",
    "iso:country":"US",
    "sg:address":"248 Haverhill St",
    "sg:city":"Methuen",
    "sg:classifiers":[
        {
            "category":"Restaurant",
            "type":"Food & Drink"
        }
    ],
    "sg:menulink":"http://www.allmenus.com/ma/methuen/197612-burger-king/menu/",
    "sg:phone":"+1 978 688 7846",
    "sg:postcode":"01844",
    "sg:province":"MA",
    "sg:tags":[
        "burger",
        "american"
    ],
    "wof:name":"Burger King",
    "wof:placetype":"venue"
},
  "geometry": {"coordinates":[-71.20465900000001,42.706546],"type":"Point"}
}