{
  "type": "Feature",
  "properties": {
    "addr:full": "28 Talbot Ave Dorchester Ctr MA 02124",
    "addr:housenumber": "28",
    "addr:postcode": "02124",
    "addr:street": "Talbot Ave Dorchester Ctr",
    "iso:country": "US",
    "sg:address": "28 Talbot Ave",
    "sg:city": "Dorchester Ctr",
    "sg:classifiers": [
      {
        "category": "Home \u0026 Garden",
        "subcategory": "Building Materials",
        "type": "Retail Goods"
      }
    ],
    "sg:phone": "+1 617 282 1740",
    "sg:postcode": "02124",
    "sg:province": "MA",
    "wof:name": "Franklin Field Lumber Co",
    "wof:placetype": "venue"
  },
  "geometry": {"coordinates":[-71.086573,42.294639],"type":"Point"}
}
