{
  "type": "Feature",
  "properties": {
    "iso:country":"US",
    "sg:address":"6 Hancock St",
    "sg:city":"Boston",
    "sg:classifiers":[
        {
            "category":"Restaurant",
            "type":"Food & Drink"
        }
    ],
    "sg:phone":"+1 617 288 3825",
    "sg:postcode":"02125",
    "sg:province":"MA",
    "sg:tags":[
        "chinese"
    ],
    "wof:name":"Canton House Restaurant",
    "wof:placetype":"venue"
},
  "geometry": {"coordinates":[-71.06606499999999,42.315586],"type":"Point"}
}