{
  "type": "Feature",
  "properties": {
    "addr:full": "6 Hancock St Boston MA 02125",
    "addr:housenumber": "6",
    "addr:postcode": "02125",
    "addr:street": "Hancock St",
    "iso:country": "US",
    "sg:address": "6 Hancock St",
    "sg:city": "Boston",
    "sg:classifiers": [
      {
        "category": "Restaurant",
        "type": "Food \u0026 Drink"
      }
    ],
    "sg:phone": "+1 617 288 3825",
    "sg:postcode": "02125",
    "sg:province": "MA",
    "sg:tags": [
      "chinese"
    ],
    "wof:name": "Canton House Restaurant",
    "wof:placetype": "venue"
  },
  "geometry": {"coordinates":[-71.066065,42.315586],"type":"Point"}
}
