{
  "type": "Feature",
  "properties": {
    "addr:full": "20 County St Walpole MA 02081",
    "addr:housenumber": "20",
    "addr:postcode": "02081",
    "addr:street": "County St",
    "iso:country": "US",
    "sg:address": "20 County St",
    "sg:city": "Walpole",
    "sg:classifiers": [
      {
        "category": "Shopping",
        "subcategory": "Bicycles \u0026 Sporting Goods",
        "type": "Retail Goods"
      }
    ],
    "sg:phone": "+1   ",
    "sg:postcode": "02081",
    "sg:province": "MA",
    "wof:name": "Wimbldon 109",
    "wof:placetype": "venue"
  },
  "geometry": {"coordinates":[-71.255612,42.20323],"type":"Point"}
}
