{
  "type": "Feature",
  "properties": {
    "iso:country":"US",
    "sg:address":"25 Wildwood Ave",
    "sg:city":"Arlington",
    "sg:classifiers":[
        {
            "category":"Building & Trades",
            "subcategory":"Locksmith",
            "type":"Services"
        }
    ],
    "sg:phone":"+1 617 714 1101",
    "sg:postcode":"02476",
    "sg:province":"MA",
    "sg:tags":[
        "key"
    ],
    "wof:name":"Gilbert Locksmith",
    "wof:placetype":"venue"
},
  "geometry": {"coordinates":[-71.161907,42.415519],"type":"Point"}
}