{
  "type": "Feature",
  "properties": {
    "addr:full": "25 Wildwood Ave Arlington MA 02476",
    "addr:housenumber": "25",
    "addr:postcode": "02476",
    "addr:street": "Wildwood Ave",
    "iso:country": "US",
    "sg:address": "25 Wildwood Ave",
    "sg:city": "Arlington",
    "sg:classifiers": [
      {
        "category": "Building \u0026 Trades",
        "subcategory": "Locksmith",
        "type": "Services"
      }
    ],
    "sg:phone": "+1 617 714 1101",
    "sg:postcode": "02476",
    "sg:province": "MA",
    "sg:tags": [
      "key"
    ],
    "wof:name": "Gilbert Locksmith",
    "wof:placetype": "venue"
  },
  "geometry": {"coordinates":[-71.161907,42.415519],"type":"Point"}
}
