{
  "type": "Feature",
  "properties": {
    "addr:full":"Harvard Square 49a Brattle St Cambridge MA 02138",
    "addr:housenumber":"49a",
    "addr:postcode":"02138",
    "addr:street":"St",
    "iso:country":"US",
    "sg:address":"Harvard Square 49a Brattle St",
    "sg:city":"Cambridge",
    "sg:classifiers":[
        {
            "category":"Personal",
            "type":"Services"
        },
        {
            "category":"Retail",
            "subcategory":"Laundry & Dry Cleaning",
            "type":"Services"
        }
    ],
    "sg:phone":"+1 617 354 1872",
    "sg:postcode":"02138",
    "sg:province":"MA",
    "sg:tags":[
        "sewing",
        "alteration"
    ],
    "wof:name":"Hillside Cleaners",
    "wof:placetype":"venue"
},
  "geometry": {"coordinates":[-71.12160900000001,42.374242],"type":"Point"}
}