{
  "type": "Feature",
  "properties": {
    "addr:full":"53 Main St North Adams MA 01247",
    "addr:housenumber":"53",
    "addr:postcode":"01247",
    "addr:street":"Main St",
    "iso:country":"US",
    "sg:address":"53 Main St",
    "sg:city":"North Adams",
    "sg:classifiers":[
        {
            "category":"Manufacturing",
            "subcategory":"Printing",
            "type":"Manufacturing & Wholesale Goods"
        }
    ],
    "sg:phone":"+1 413 663 3414",
    "sg:postcode":"01247",
    "sg:province":"MA",
    "sg:tags":[
        "commercial",
        "bo",
        "lithographic"
    ],
    "wof:name":"PIP Printing",
    "wof:placetype":"venue"
},
  "geometry": {"coordinates":[-73.113524,42.699458],"type":"Point"}
}