{
  "type": "Feature",
  "properties": {
    "iso:country":"US",
    "sg:address":"41 Park St",
    "sg:city":"Adams",
    "sg:classifiers":[
        {
            "category":"Real Estate",
            "subcategory":"Developer",
            "type":"Services"
        }
    ],
    "sg:phone":"+1 413 743 2400",
    "sg:postcode":"01220",
    "sg:province":"MA",
    "sg:website":"www.stonybrookland.com",
    "wof:name":"Stonybrook Properties Inc",
    "wof:placetype":"venue"
},
  "geometry": {"coordinates":[-73.12011099999999,42.622765],"type":"Point"}
}