{
  "type": "Feature",
  "properties": {
    "addr:full": "41 Park St Adams MA 01220",
    "addr:housenumber": "41",
    "addr:postcode": "01220",
    "addr:street": "Park St",
    "iso:country": "US",
    "sg:address": "41 Park St",
    "sg:city": "Adams",
    "sg:classifiers": [
      {
        "category": "Real Estate",
        "subcategory": "Developer",
        "type": "Services"
      }
    ],
    "sg:phone": "+1 413 743 2400",
    "sg:postcode": "01220",
    "sg:province": "MA",
    "sg:website": "www.stonybrookland.com",
    "wof:name": "Stonybrook Properties Inc",
    "wof:placetype": "venue"
  },
  "geometry": {"coordinates":[-73.120111,42.622765],"type":"Point"}
}
