{
  "type": "Feature",
  "properties": {
    "addr:full": "155 Division St Chelsea MA 02150",
    "addr:housenumber": "155",
    "addr:postcode": "02150",
    "addr:street": "Division St",
    "iso:country": "US",
    "sg:address": "155 Division St",
    "sg:city": "Chelsea",
    "sg:classifiers": [
      {
        "category": "Building \u0026 Trades",
        "subcategory": "Construction",
        "type": "Services"
      }
    ],
    "sg:phone": "+1 617 889 3261",
    "sg:postcode": "02150",
    "sg:province": "MA",
    "sg:tags": [
      "repairing",
      "remodeling",
      "contractor"
    ],
    "wof:name": "ABC Bathroom Remodeling Co",
    "wof:placetype": "venue"
  },
  "geometry": {"coordinates":[-71.036518,42.390562],"type":"Point"}
}
