{
  "type": "Feature",
  "properties": {
    "addr:full": "74 W Central St Natick MA 01760",
    "addr:housenumber": "74",
    "addr:postcode": "01760",
    "addr:street": "W Central St",
    "iso:country": "US",
    "sg:address": "74 W Central St",
    "sg:city": "Natick",
    "sg:classifiers": [
      {
        "category": "Professional",
        "subcategory": "Lawyer \u0026 Legal Services",
        "type": "Services"
      }
    ],
    "sg:phone": "+1 508 655 1960",
    "sg:postcode": "01760",
    "sg:province": "MA",
    "sg:tags": [
      "attorney"
    ],
    "wof:name": "Zaltas Medoff \u0026 Raider",
    "wof:placetype": "venue"
  },
  "geometry": {"coordinates":[-71.356634,42.282577],"type":"Point"}
}
