{
  "type": "Feature",
  "properties": {
    "iso:country":"US",
    "sg:address":"74 W Central St",
    "sg:city":"Natick",
    "sg:classifiers":[
        {
            "category":"Professional",
            "subcategory":"Lawyer & Legal Services",
            "type":"Services"
        }
    ],
    "sg:phone":"+1 508 655 1960",
    "sg:postcode":"01760",
    "sg:province":"MA",
    "sg:tags":[
        "attorney"
    ],
    "wof:name":"Zaltas Medoff & Raider",
    "wof:placetype":"venue"
},
  "geometry": {"coordinates":[-71.356634,42.282577],"type":"Point"}
}