{
  "type": "Feature",
  "properties": {
    "addr:full": "500 E Broadway Boston MA 02127",
    "addr:housenumber": "500",
    "addr:postcode": "02127",
    "addr:street": "E Broadway",
    "iso:country": "US",
    "sg:address": "500 E Broadway",
    "sg:city": "Boston",
    "sg:classifiers": [
      {
        "category": "Health Services",
        "subcategory": "Dentist",
        "type": "Services"
      }
    ],
    "sg:phone": "+1 617 268 2333",
    "sg:postcode": "02127",
    "sg:province": "MA",
    "wof:name": "Sameka Dental Management",
    "wof:placetype": "venue"
  },
  "geometry": {"coordinates":[-71.044622,42.335591],"type":"Point"}
}
