{
  "type": "Feature",
  "properties": {
    "iso:country":"US",
    "sg:address":"450 Cambridge St",
    "sg:city":"Allston",
    "sg:classifiers":[
        {
            "category":"Shopping",
            "type":"Retail Goods"
        }
    ],
    "sg:phone":"+1 617 787 2055",
    "sg:postcode":"02134",
    "sg:province":"MA",
    "wof:name":"Paperworks",
    "wof:placetype":"venue"
},
  "geometry": {"coordinates":[-71.135803,42.354198],"type":"Point"}
}