{
  "type": "Feature",
  "properties": {
    "addr:full":"99 A Eastman Easton MA 02334",
    "addr:housenumber":"99 a",
    "addr:postcode":"02334",
    "iso:country":"US",
    "sg:address":"99 A Eastman",
    "sg:city":"Easton",
    "sg:classifiers":[
        {
            "category":"Education",
            "subcategory":"Dance Studio",
            "type":"Public Place"
        }
    ],
    "sg:phone":"+1 508 238 6101",
    "sg:postcode":"02334",
    "sg:province":"MA",
    "sg:website":"www.danceexpresseaston.com",
    "wof:name":"Dance Express",
    "wof:placetype":"venue"
},
  "geometry": {"coordinates":[-71.15431599999999,42.024958],"type":"Point"}
}