{
  "type": "Feature",
  "properties": {
    "addr:full": "65 W Water St Taunton MA 02780",
    "addr:housenumber": "65",
    "addr:postcode": "02780",
    "addr:street": "W Water St",
    "iso:country": "US",
    "sg:address": "65 W Water St",
    "sg:city": "Taunton",
    "sg:classifiers": [
      {
        "category": "Restaurant",
        "type": "Food \u0026 Drink"
      }
    ],
    "sg:phone": "+1 508 884 8994",
    "sg:postcode": "02780",
    "sg:province": "MA",
    "sg:tags": [
      "sandwich",
      "eating"
    ],
    "wof:name": "Frank's Dogs \u0026 More",
    "wof:placetype": "venue"
  },
  "geometry": {"coordinates":[-71.089803,41.885953],"type":"Point"}
}
