{
  "type": "Feature",
  "properties": {
    "iso:country":"US",
    "sg:address":"65 W Water St",
    "sg:city":"Taunton",
    "sg:classifiers":[
        {
            "category":"Restaurant",
            "type":"Food & Drink"
        }
    ],
    "sg:phone":"+1 508 884 8994",
    "sg:postcode":"02780",
    "sg:province":"MA",
    "sg:tags":[
        "sandwich",
        "eating"
    ],
    "wof:name":"Frank's Dogs & More",
    "wof:placetype":"venue"
},
  "geometry": {"coordinates":[-71.089803,41.885953],"type":"Point"}
}