{
  "type": "Feature",
  "properties": {
    "addr:full": "30 Appleton Rd Nantucket MA 02554",
    "addr:housenumber": "30",
    "addr:postcode": "02554",
    "addr:street": "Appleton Rd",
    "iso:country": "US",
    "sg:address": "30 Appleton Rd",
    "sg:city": "Nantucket",
    "sg:classifiers": [
      {
        "category": "Building \u0026 Trades",
        "subcategory": "Construction",
        "type": "Services"
      }
    ],
    "sg:phone": "+1 508 228 0984",
    "sg:postcode": "02554",
    "sg:province": "MA",
    "sg:tags": [
      "general",
      "contractor"
    ],
    "wof:name": "R J Kalman \u0026 Sons Inc",
    "wof:placetype": "venue"
  },
  "geometry": {"coordinates":[-70.108216,41.263386],"type":"Point"}
}
