{
  "type": "Feature",
  "properties": {
    "addr:full": "158 Porter St Stoughton MA 02072",
    "addr:housenumber": "158",
    "addr:postcode": "02072",
    "addr:street": "Porter St",
    "iso:country": "US",
    "sg:address": "158 Porter St",
    "sg:city": "Stoughton",
    "sg:classifiers": [
      {
        "category": "Building \u0026 Trades",
        "subcategory": "Locksmith",
        "type": "Services"
      }
    ],
    "sg:phone": "+1 781 318 9428",
    "sg:postcode": "02072",
    "sg:province": "MA",
    "sg:tags": [
      "key"
    ],
    "wof:name": "Service Porter ABC Emergency Locksmith",
    "wof:placetype": "venue"
  },
  "geometry": {"coordinates":[-71.099261,42.127249],"type":"Point"}
}
