{
  "type": "Feature",
  "properties": {
    "addr:full": "45 Lemoyne St Braintree MA 02184",
    "addr:housenumber": "45",
    "addr:postcode": "02184",
    "addr:street": "Lemoyne St",
    "iso:country": "US",
    "sg:address": "45 Lemoyne St",
    "sg:city": "Braintree",
    "sg:classifiers": [
      {
        "category": "Professional",
        "subcategory": "Computer Services",
        "type": "Services"
      }
    ],
    "sg:phone": "+1 781 843 5788",
    "sg:postcode": "02184",
    "sg:province": "MA",
    "sg:tags": [
      "consultant",
      "designer"
    ],
    "wof:name": "E Datamate",
    "wof:placetype": "venue"
  },
  "geometry": {"coordinates":[-70.993769,42.221315],"type":"Point"}
}
