{
  "type": "Feature",
  "properties": {
    "addr:full":"30 Smith Rd Chesterfield MA 01050",
    "addr:housenumber":"30",
    "addr:postcode":"01050",
    "addr:street":"Smith Rd",
    "iso:country":"US",
    "sg:address":"30 Smith Rd",
    "sg:city":"Chesterfield",
    "sg:classifiers":[
        {
            "category":"Social Services",
            "subcategory":"Child Care",
            "type":"Services"
        }
    ],
    "sg:phone":"+1 413 296 0182",
    "sg:postcode":"01050",
    "sg:province":"MA",
    "wof:name":"Bonnie's Place",
    "wof:placetype":"venue"
},
  "geometry": {"coordinates":[-72.86037,42.397332],"type":"Point"}
}