{
  "type": "Feature",
  "properties": {
    "addr:full": "71 Cedar St Hopkinton MA 01748",
    "addr:housenumber": "71",
    "addr:postcode": "01748",
    "addr:street": "Cedar St",
    "iso:country": "US",
    "sg:address": "71 Cedar St",
    "sg:city": "Hopkinton",
    "sg:classifiers": [
      {
        "category": "Government",
        "subcategory": "Office",
        "type": "Public Place"
      }
    ],
    "sg:phone": "+1   ",
    "sg:postcode": "01748",
    "sg:province": "MA",
    "sg:tags": [
      "conservation"
    ],
    "wof:name": "Hopkinton State Park",
    "wof:placetype": "venue"
  },
  "geometry": {"coordinates":[-71.525478,42.243168],"type":"Point"}
}
