{
  "type": "Feature",
  "properties": {
    "iso:country":"US",
    "sg:address":"71 Cedar St",
    "sg:city":"Hopkinton",
    "sg:classifiers":[
        {
            "category":"Government",
            "subcategory":"Office",
            "type":"Public Place"
        }
    ],
    "sg:phone":"+1   ",
    "sg:postcode":"01748",
    "sg:province":"MA",
    "sg:tags":[
        "conservation"
    ],
    "wof:name":"Hopkinton State Park",
    "wof:placetype":"venue"
},
  "geometry": {"coordinates":[-71.52547800000001,42.243168],"type":"Point"}
}