{
  "type": "Feature",
  "properties": {
    "addr:full": "450 Southern Artery Quincy MA 02169",
    "addr:housenumber": "450",
    "addr:postcode": "02169",
    "addr:street": "Southern Artery",
    "iso:country": "US",
    "sg:address": "450 Southern Artery",
    "sg:city": "Quincy",
    "sg:classifiers": [
      {
        "category": "Autos \u0026 Motor Vehicles",
        "subcategory": "Fuel \u0026 Gas Station",
        "type": "Retail Goods"
      }
    ],
    "sg:phone": "+1 617 471 9872",
    "sg:postcode": "02169",
    "sg:province": "MA",
    "sg:tags": [
      "oil"
    ],
    "wof:name": "Space Age Svc Mobil",
    "wof:placetype": "venue"
  },
  "geometry": {"coordinates":[-71.002777,42.259597],"type":"Point"}
}
