{
  "type": "Feature",
  "properties": {
    "addr:full": "324 Grove St Ste 4 Worcester MA 01605",
    "addr:housenumber": "324",
    "addr:postcode": "01605",
    "addr:street": "Grove St Ste 4",
    "iso:country": "US",
    "sg:address": "324 Grove St Ste 4",
    "sg:city": "Worcester",
    "sg:classifiers": [
      {
        "category": "Banks \u0026 Credit Unions",
        "subcategory": "Bank",
        "type": "Services"
      },
      {
        "category": "Banks \u0026 Credit Unions",
        "subcategory": "Financial Services",
        "type": "Services"
      }
    ],
    "sg:phone": "+1 508 831 7728",
    "sg:postcode": "01605",
    "sg:province": "MA",
    "sg:tags": [
      "saving",
      "loan",
      "commercial"
    ],
    "sg:website": "http://www.wellsfargo.com",
    "wof:name": "Wells Fargo Bank",
    "wof:placetype": "venue"
  },
  "geometry": {"coordinates":[-71.807068,42.283661],"type":"Point"}
}
