{
  "type": "Feature",
  "properties": {
    "iso:country":"US",
    "sg:address":"10 Bellevue Ave",
    "sg:city":"Dracut",
    "sg:classifiers":[
        {
            "category":"Building & Trades",
            "subcategory":"Construction",
            "type":"Services"
        }
    ],
    "sg:phone":"+1 978 815 8078",
    "sg:postcode":"01826",
    "sg:province":"MA",
    "sg:tags":[
        "plastering",
        "contractor"
    ],
    "wof:name":"Mark Jussaume",
    "wof:placetype":"venue"
},
  "geometry": {"coordinates":[-71.25672900000001,42.658497],"type":"Point"}
}