{
  "type": "Feature",
  "properties": {
    "addr:full": "10 Bellevue Ave Dracut MA 01826",
    "addr:housenumber": "10",
    "addr:postcode": "01826",
    "addr:street": "Bellevue Ave",
    "iso:country": "US",
    "sg:address": "10 Bellevue Ave",
    "sg:city": "Dracut",
    "sg:classifiers": [
      {
        "category": "Building \u0026 Trades",
        "subcategory": "Construction",
        "type": "Services"
      }
    ],
    "sg:phone": "+1 978 815 8078",
    "sg:postcode": "01826",
    "sg:province": "MA",
    "sg:tags": [
      "plastering",
      "contractor"
    ],
    "wof:name": "Mark Jussaume",
    "wof:placetype": "venue"
  },
  "geometry": {"coordinates":[-71.256729,42.658497],"type":"Point"}
}
