{
  "type": "Feature",
  "properties": {
    "addr:full": "372 Washington St Somerville MA 02143",
    "addr:housenumber": "372",
    "addr:postcode": "02143",
    "addr:street": "Washington St",
    "iso:country": "US",
    "ovtr:label": "Sweet Laundry, 372 Washington St Somerville MA US",
    "ovtr:similarity": 2.188278913497925,
    "sg:address": "372 Washington St",
    "sg:city": "Somerville",
    "sg:classifiers": [
      {
        "category": "Retail",
        "subcategory": "Laundry \u0026 Dry Cleaning",
        "type": "Services"
      }
    ],
    "sg:phone": "+1 617 628 7206",
    "sg:postcode": "02143",
    "sg:province": "MA",
    "wof:name": "Sweet Laundry",
    "wof:placetype": "venue"
  },
  "geometry": {"coordinates":[-71.103969,42.378847],"type":"Point"}
}
