{
  "type": "Feature",
  "properties": {
    "iso:country":"US",
    "sg:address":"372 Washington St",
    "sg:city":"Somerville",
    "sg:classifiers":[
        {
            "category":"Retail",
            "subcategory":"Laundry & Dry Cleaning",
            "type":"Services"
        }
    ],
    "sg:phone":"+1 617 628 7206",
    "sg:postcode":"02143",
    "sg:province":"MA",
    "wof:name":"Sweet Laundry",
    "wof:placetype":"venue"
},
  "geometry": {"coordinates":[-71.10396900000001,42.378847],"type":"Point"}
}