{
  "type": "Feature",
  "properties": {
    "iso:country":"US",
    "sg:address":"87 County Rd",
    "sg:city":"Plympton",
    "sg:classifiers":[
        {
            "category":"Retail",
            "subcategory":"Auto Repair",
            "type":"Services"
        }
    ],
    "sg:phone":"+1 781 582 2355",
    "sg:postcode":"02367",
    "sg:province":"MA",
    "sg:tags":[
        "repairing",
        "automobile"
    ],
    "wof:name":"Scott's Classic Imports LTD",
    "wof:placetype":"venue"
},
  "geometry": {"coordinates":[-70.80301799999999,41.988143],"type":"Point"}
}