{
  "type": "Feature",
  "properties": {
    "addr:full": "34 Cummington St Boston MA 02215",
    "addr:housenumber": "34",
    "addr:postcode": "02215",
    "addr:street": "Cummington St",
    "iso:country": "US",
    "sg:address": "34 Cummington St",
    "sg:city": "Boston",
    "sg:classifiers": [
      {
        "category": "Cinema",
        "subcategory": "Movie Theater",
        "type": "Entertainment"
      }
    ],
    "sg:phone": "+1 617 424 1500",
    "sg:postcode": "02215",
    "sg:province": "MA",
    "wof:name": "Sony/Loews Theatres",
    "wof:placetype": "venue"
  },
  "geometry": {"coordinates":[-71.101498,42.348351],"type":"Point"}
}
