{
  "type": "Feature",
  "properties": {
    "addr:full": "125 Pleasant St Lynn MA 01901",
    "addr:housenumber": "125",
    "addr:postcode": "01901",
    "addr:street": "Pleasant St",
    "iso:country": "US",
    "sg:address": "125 Pleasant St",
    "sg:city": "Lynn",
    "sg:classifiers": [
      {
        "category": "Professional",
        "type": "Services"
      }
    ],
    "sg:phone": "+1   ",
    "sg:postcode": "01901",
    "sg:province": "MA",
    "wof:name": "Mariner Fuel Service Inc",
    "wof:placetype": "venue"
  },
  "geometry": {"coordinates":[-70.94931,42.460404],"type":"Point"}
}
