{
  "type": "Feature",
  "properties": {
    "iso:country":"US",
    "sg:address":"875 Main St Ste 5",
    "sg:city":"Cambridge",
    "sg:classifiers":[
        {
            "category":"Building & Trades",
            "subcategory":"Landscaping Services",
            "type":"Services"
        }
    ],
    "sg:phone":"+1 617 354 0643",
    "sg:postcode":"02139",
    "sg:province":"MA",
    "sg:tags":[
        "consultant",
        "designer",
        "landscape"
    ],
    "sg:website":"http://www.jeanbrookslandscapes.com",
    "wof:name":"Jean Brooks Landscape",
    "wof:placetype":"venue"
},
  "geometry": {"coordinates":[-71.098871,42.363379],"type":"Point"}
}