{
  "type": "Feature",
  "properties": {
    "addr:full":"1232 Pleasant St Athol MA 01331",
    "addr:housenumber":"1232",
    "addr:postcode":"01331",
    "addr:street":"Pleasant St",
    "iso:country":"US",
    "sg:address":"1232 Pleasant St",
    "sg:city":"Athol",
    "sg:classifiers":[
        {
            "category":"Professional",
            "subcategory":"Business Services",
            "type":"Services"
        }
    ],
    "sg:phone":"+1 978 249 4304",
    "sg:postcode":"01331",
    "sg:province":"MA",
    "sg:tags":[
        "water",
        "treatment"
    ],
    "wof:name":"Clear Choice Pure Water System",
    "wof:placetype":"venue"
},
  "geometry": {"coordinates":[-72.219013,42.571925],"type":"Point"}
}