{
  "type": "Feature",
  "properties": {
    "addr:full": "354 Beacon St Boston MA 02116",
    "addr:housenumber": "354",
    "addr:postcode": "02116",
    "addr:street": "Beacon St",
    "iso:country": "US",
    "sg:address": "354 Beacon St",
    "sg:city": "Boston",
    "sg:classifiers": [
      {
        "category": "Shopping",
        "subcategory": "Used Merchandise",
        "type": "Retail Goods"
      }
    ],
    "sg:phone": "+1   ",
    "sg:postcode": "02116",
    "sg:province": "MA",
    "wof:name": "Jorgensen Sb Antiques",
    "wof:placetype": "venue"
  },
  "geometry": {"coordinates":[-71.085077,42.352142],"type":"Point"}
}
