{
  "type": "Feature",
  "properties": {
    "iso:country":"US",
    "sg:address":"1016 Boston Rd",
    "sg:city":"Haverhill",
    "sg:classifiers":[
        {
            "category":"Education",
            "subcategory":"College",
            "type":"Public Place"
        }
    ],
    "sg:phone":"+1 978 373 8073",
    "sg:postcode":"01835",
    "sg:province":"MA",
    "sg:tags":[
        "academic",
        "school"
    ],
    "wof:name":"Boston Tooling & Machining",
    "wof:placetype":"venue"
},
  "geometry": {"coordinates":[-71.10374899999999,42.748881],"type":"Point"}
}