{
  "type": "Feature",
  "properties": {
    "iso:country":"US",
    "sg:address":"18 Worthington St",
    "sg:city":"Dedham",
    "sg:classifiers":[
        {
            "category":"Banks & Credit Unions",
            "subcategory":"Investment Brokerage",
            "type":"Services"
        },
        {
            "category":"Banks & Credit Unions",
            "subcategory":"Financial Services",
            "type":"Services"
        }
    ],
    "sg:phone":"+1 781 329 8044",
    "sg:postcode":"02026",
    "sg:province":"MA",
    "sg:tags":[
        "advisory",
        "planner"
    ],
    "wof:name":"Financial Associates, Inc.",
    "wof:placetype":"venue"
},
  "geometry": {"coordinates":[-71.17542899999999,42.245574],"type":"Point"}
}