{
  "type": "Feature",
  "properties": {
    "iso:country":"US",
    "sg:address":"160 Ocean St",
    "sg:city":"Marshfield",
    "sg:classifiers":[
        {
            "category":"Real Estate",
            "subcategory":"Real Estate Agent",
            "type":"Services"
        }
    ],
    "sg:phone":"+1 781 834 4032",
    "sg:postcode":"02050",
    "sg:province":"MA",
    "wof:name":"Hunt Real Estate",
    "wof:placetype":"venue"
},
  "geometry": {"coordinates":[-70.642607,42.090345],"type":"Point"}
}