{
  "type": "Feature",
  "properties": {
    "addr:full": "61 South St Easthampton MA 01027",
    "addr:housenumber": "61",
    "addr:postcode": "01027",
    "addr:street": "South St",
    "iso:country": "US",
    "sg:address": "61 South St",
    "sg:city": "Easthampton",
    "sg:classifiers": [
      {
        "category": "Retail",
        "subcategory": "Auto Repair",
        "type": "Services"
      }
    ],
    "sg:phone": "+1 413 527 1840",
    "sg:postcode": "01027",
    "sg:province": "MA",
    "sg:tags": [
      "automotive"
    ],
    "wof:name": "Lynn Transportation Inc",
    "wof:placetype": "venue"
  },
  "geometry": {"coordinates":[-72.685272,42.259845],"type":"Point"}
}
