{
  "type": "Feature",
  "properties": {
    "addr:full":"23 Mordecai Lincoln Rd Scituate MA 02066",
    "addr:housenumber":"23",
    "addr:postcode":"02066",
    "addr:street":"Mordecai Lincoln Rd",
    "iso:country":"US",
    "sg:address":"23 Mordecai Lincoln Rd",
    "sg:city":"Scituate",
    "sg:classifiers":[
        {
            "category":"Retail",
            "subcategory":"Repair Shop",
            "type":"Services"
        }
    ],
    "sg:phone":"+1   ",
    "sg:postcode":"02066",
    "sg:province":"MA",
    "wof:name":"Diane Cochran",
    "wof:placetype":"venue"
},
  "geometry": {"coordinates":[-70.786231,42.221091],"type":"Point"}
}