{
  "type": "Feature",
  "properties": {
    "addr:full": "730 Williamsville Rd Barre MA 01005",
    "addr:housenumber": "730",
    "addr:postcode": "01005",
    "addr:street": "Williamsville Rd",
    "iso:country": "US",
    "sg:address": "730 Williamsville Rd",
    "sg:city": "Barre",
    "sg:classifiers": [
      {
        "category": "Autos \u0026 Motor Vehicles",
        "subcategory": "Automobile Sales",
        "type": "Retail Goods"
      }
    ],
    "sg:phone": "+1 978 355 2897",
    "sg:postcode": "01005",
    "sg:province": "MA",
    "sg:tags": [
      "trucks-industrial"
    ],
    "wof:name": "P \u0026 P Trucking",
    "wof:placetype": "venue"
  },
  "geometry": {"coordinates":[-72.091469,42.450327],"type":"Point"}
}
