{
  "type": "Feature",
  "properties": {
    "addr:full": "190 Russell St Hadley MA 01035",
    "addr:housenumber": "190",
    "addr:postcode": "01035",
    "addr:street": "Russell St",
    "iso:country": "US",
    "ovtr:label": "Western Mass Endodontics in Hadley, MA, 190 Russell St Hadley MA US",
    "ovtr:similarity": 3.6930510997772217,
    "sg:address": "190 Russell St",
    "sg:city": "Hadley",
    "sg:classifiers": [
      {
        "category": "Health Services",
        "subcategory": "Doctor",
        "type": "Services"
      },
      {
        "category": "Health Services",
        "subcategory": "Dentist",
        "type": "Services"
      }
    ],
    "sg:phone": "+1 413 582 0700",
    "sg:postcode": "01035",
    "sg:province": "MA",
    "sg:tags": [
      "dentists-oral",
      "physician",
      "maxillofacial",
      "surgeons",
      "dentists-endodontists",
      "surgery",
      "oral"
    ],
    "sg:website": "http://wmendo.com",
    "wof:name": "Western Mass Endodontics",
    "wof:placetype": "venue"
  },
  "geometry": {"coordinates":[-72.581837,42.342921],"type":"Point"}
}
