{
  "type": "Feature",
  "properties": {
    "iso:country":"US",
    "sg:address":"190 Russell St",
    "sg:city":"Hadley",
    "sg:classifiers":[
        {
            "category":"Health Services",
            "subcategory":"Doctor",
            "type":"Services"
        },
        {
            "category":"Health Services",
            "subcategory":"Dentist",
            "type":"Services"
        }
    ],
    "sg:phone":"+1 413 582 0700",
    "sg:postcode":"01035",
    "sg:province":"MA",
    "sg:tags":[
        "dentists-oral",
        "physician",
        "maxillofacial",
        "surgeons",
        "dentists-endodontists",
        "surgery",
        "oral"
    ],
    "sg:website":"http://wmendo.com",
    "wof:name":"Western Mass Endodontics",
    "wof:placetype":"venue"
},
  "geometry": {"coordinates":[-72.58183699999999,42.342921],"type":"Point"}
}