{
  "type": "Feature",
  "properties": {
    "addr:full":"385 Pleasant St Watertown MA 02472",
    "addr:housenumber":"385",
    "addr:postcode":"02472",
    "addr:street":"Pleasant St",
    "iso:country":"US",
    "sg:address":"385 Pleasant St",
    "sg:city":"Watertown",
    "sg:classifiers":[
        {
            "category":"Professional",
            "subcategory":"Advertising",
            "type":"Services"
        }
    ],
    "sg:phone":"+1 617 926 5550",
    "sg:postcode":"02472",
    "sg:province":"MA",
    "sg:tags":[
        "mail",
        "direct"
    ],
    "sg:website":"http://www.fieldcompanies.com",
    "wof:name":"The Field Companies Inc",
    "wof:placetype":"venue"
},
  "geometry": {"coordinates":[-71.202046,42.367176],"type":"Point"}
}