{
  "type": "Feature",
  "properties": {
    "iso:country":"US",
    "sg:address":"145 S Main St",
    "sg:city":"Carver",
    "sg:classifiers":[
        {
            "category":"Insurance",
            "subcategory":"Insurance Agent",
            "type":"Services"
        }
    ],
    "sg:phone":"+1 508 866 9150",
    "sg:postcode":"02330",
    "sg:province":"MA",
    "wof:name":"Farm Family Insurance Co",
    "wof:placetype":"venue"
},
  "geometry": {"coordinates":[-70.74927700000001,41.8373],"type":"Point"}
}