{
  "type": "Feature",
  "properties": {
    "addr:full": "145 S Main St Carver MA 02330",
    "addr:housenumber": "145",
    "addr:postcode": "02330",
    "addr:street": "S Main St",
    "iso:country": "US",
    "sg:address": "145 S Main St",
    "sg:city": "Carver",
    "sg:classifiers": [
      {
        "category": "Insurance",
        "subcategory": "Insurance Agent",
        "type": "Services"
      }
    ],
    "sg:phone": "+1 508 866 9150",
    "sg:postcode": "02330",
    "sg:province": "MA",
    "wof:name": "Farm Family Insurance Co",
    "wof:placetype": "venue"
  },
  "geometry": {"coordinates":[-70.749277,41.8373],"type":"Point"}
}
