{
  "type": "Feature",
  "properties": {
    "addr:full":"20 Driftwood Dr Holden MA 01520",
    "addr:housenumber":"20",
    "addr:postcode":"01520",
    "addr:street":"Driftwood Dr",
    "iso:country":"US",
    "sg:address":"20 Driftwood Dr",
    "sg:city":"Holden",
    "sg:classifiers":[
        {
            "category":"Building & Trades",
            "subcategory":"Construction",
            "type":"Services"
        }
    ],
    "sg:phone":"+1   ",
    "sg:postcode":"01520",
    "sg:province":"MA",
    "sg:tags":[
        "heavy"
    ],
    "wof:name":"Alcott and Brice Inc",
    "wof:placetype":"venue"
},
  "geometry": {"coordinates":[-71.84291399999999,42.3496],"type":"Point"}
}