{
  "type": "Feature",
  "properties": {
    "addr:full": "10 Bowdoin St Unit 204 Boston MA 02114",
    "addr:housenumber": "10;204",
    "addr:postcode": "02114",
    "addr:street": "Bowdoin St Unit",
    "iso:country": "US",
    "sg:address": "10 Bowdoin St Unit 204",
    "sg:city": "Boston",
    "sg:classifiers": [
      {
        "category": "Building \u0026 Trades",
        "subcategory": "Construction",
        "type": "Services"
      }
    ],
    "sg:phone": "+1 617 823 0322",
    "sg:postcode": "02114",
    "sg:province": "MA",
    "sg:tags": [
      "carpenter"
    ],
    "wof:name": "Don Scott Fine Custom Carpentry",
    "wof:placetype": "venue"
  },
  "geometry": {"coordinates":[-71.062929,42.361002],"type":"Point"}
}
