{
  "type": "Feature",
  "properties": {
    "iso:country":"US",
    "sg:address":"109 Magnolia Ave",
    "sg:city":"Gloucester",
    "sg:classifiers":[
        {
            "category":"Building & Trades",
            "subcategory":"Construction",
            "type":"Services"
        }
    ],
    "sg:phone":"+1 978 525 3980",
    "sg:postcode":"01930",
    "sg:province":"MA",
    "sg:tags":[
        "concrete",
        "contractor"
    ],
    "wof:name":"Sullivan Construction Co",
    "wof:placetype":"venue"
},
  "geometry": {"coordinates":[-70.718671,42.587242],"type":"Point"}
}