{
  "type": "Feature",
  "properties": {
    "addr:full": "106 Thornberry Rd Winchester MA 01890",
    "addr:housenumber": "106",
    "addr:postcode": "01890",
    "addr:street": "Thornberry Rd",
    "iso:country": "US",
    "sg:address": "106 Thornberry Rd",
    "sg:city": "Winchester",
    "sg:classifiers": [
      {
        "category": "Building \u0026 Trades",
        "subcategory": "Construction",
        "type": "Services"
      }
    ],
    "sg:phone": "+1   ",
    "sg:postcode": "01890",
    "sg:province": "MA",
    "sg:tags": [
      "house"
    ],
    "wof:name": "Management Construction Inc",
    "wof:placetype": "venue"
  },
  "geometry": {"coordinates":[-71.179298,42.448327],"type":"Point"}
}
