{
  "type": "Feature",
  "properties": {
    "addr:full": "37 Main St Concord MA 01742",
    "addr:housenumber": "37",
    "addr:postcode": "01742",
    "addr:street": "Main St",
    "iso:country": "US",
    "sg:address": "37 Main St",
    "sg:city": "Concord",
    "sg:classifiers": [
      {
        "category": "Professional",
        "subcategory": "Lawyer \u0026 Legal Services",
        "type": "Services"
      }
    ],
    "sg:phone": "+1 978 369 8333",
    "sg:postcode": "01742",
    "sg:province": "MA",
    "sg:tags": [
      "attorney"
    ],
    "wof:name": "Dane Brady \u0026 Haydon Llp",
    "wof:placetype": "venue"
  },
  "geometry": {"coordinates":[-71.350197,42.4599],"type":"Point"}
}
