{
  "type": "Feature",
  "properties": {
    "iso:country":"US",
    "sg:address":"37 Main St",
    "sg:city":"Concord",
    "sg:classifiers":[
        {
            "category":"Professional",
            "subcategory":"Lawyer & Legal Services",
            "type":"Services"
        }
    ],
    "sg:phone":"+1 978 369 8333",
    "sg:postcode":"01742",
    "sg:province":"MA",
    "sg:tags":[
        "attorney"
    ],
    "wof:name":"Dane Brady & Haydon Llp",
    "wof:placetype":"venue"
},
  "geometry": {"coordinates":[-71.35019699999999,42.4599],"type":"Point"}
}