{
  "type": "Feature",
  "properties": {
    "addr:full": "1221 Main St Holyoke MA 01040",
    "addr:housenumber": "1221",
    "addr:postcode": "01040",
    "addr:street": "Main St",
    "iso:country": "US",
    "sg:address": "1221 Main St",
    "sg:city": "Holyoke",
    "sg:classifiers": [
      {
        "category": "Professional",
        "subcategory": "Accounting \u0026 Tax Preparation",
        "type": "Services"
      }
    ],
    "sg:phone": "+1 413 493 3850",
    "sg:postcode": "01040",
    "sg:province": "MA",
    "sg:tags": [
      "billing"
    ],
    "wof:name": "Numeric Inc",
    "wof:placetype": "venue"
  },
  "geometry": {"coordinates":[-72.632943,42.164215],"type":"Point"}
}
