{
  "type": "Feature",
  "properties": {
    "addr:full":"32 Alexander Rd Hopkinton MA 01748",
    "addr:housenumber":"32",
    "addr:postcode":"01748",
    "addr:street":"Alexander Rd",
    "iso:country":"US",
    "sg:address":"32 Alexander Rd",
    "sg:city":"Hopkinton",
    "sg:classifiers":[
        {
            "category":"Professional",
            "subcategory":"Management & Consulting",
            "type":"Services"
        }
    ],
    "sg:phone":"+1 508 435 0400",
    "sg:postcode":"01748",
    "sg:province":"MA",
    "sg:tags":[
        "consultant",
        "energy",
        "conservation"
    ],
    "wof:name":"Energy Market Decisions Inc",
    "wof:placetype":"venue"
},
  "geometry": {"coordinates":[-71.524081,42.204224],"type":"Point"}
}