{
  "type": "Feature",
  "properties": {
    "iso:country":"US",
    "sg:address":"2 Shaker Rd",
    "sg:city":"Shirley",
    "sg:classifiers":[
        {
            "category":"Building & Trades",
            "subcategory":"Construction",
            "type":"Services"
        }
    ],
    "sg:phone":"+1 978 425 9802",
    "sg:postcode":"01464",
    "sg:province":"MA",
    "sg:tags":[
        "general",
        "contractor"
    ],
    "sg:website":"www.senateconstruction.com",
    "wof:name":"Senate Construction Corp",
    "wof:placetype":"venue"
},
  "geometry": {"coordinates":[-71.64772000000001,42.541711],"type":"Point"}
}