{
  "type": "Feature",
  "properties": {
    "addr:full": "101 Arch Street Ste 300 Boston MA 02110",
    "addr:housenumber": "101",
    "addr:postcode": "02110",
    "addr:street": "Arch Street Ste 300",
    "iso:country": "US",
    "sg:address": "101 Arch Street Ste 300",
    "sg:city": "Boston",
    "sg:classifiers": [
      {
        "category": "Professional",
        "subcategory": "Accounting \u0026 Tax Preparation",
        "type": "Services"
      }
    ],
    "sg:phone": "+1 617 482 5511",
    "sg:postcode": "02110",
    "sg:province": "MA",
    "sg:tags": [
      "accountant"
    ],
    "wof:name": "Ercolini \u0026 Co Llp",
    "wof:placetype": "venue"
  },
  "geometry": {"coordinates":[-71.058746,42.354871],"type":"Point"}
}
