{
  "type": "Feature",
  "properties": {
    "iso:country":"US",
    "sg:address":"101 Arch Street Ste 300",
    "sg:city":"Boston",
    "sg:classifiers":[
        {
            "category":"Professional",
            "subcategory":"Accounting & Tax Preparation",
            "type":"Services"
        }
    ],
    "sg:phone":"+1 617 482 5511",
    "sg:postcode":"02110",
    "sg:province":"MA",
    "sg:tags":[
        "accountant"
    ],
    "wof:name":"Ercolini & Co Llp",
    "wof:placetype":"venue"
},
  "geometry": {"coordinates":[-71.058746,42.354871],"type":"Point"}
}