{
  "type": "Feature",
  "properties": {
    "iso:country":"US",
    "sg:address":"16 Echo Rd",
    "sg:city":"Mashpee",
    "sg:classifiers":[
        {
            "category":"Wholesale",
            "subcategory":"Scrap",
            "type":"Manufacturing & Wholesale Goods"
        }
    ],
    "sg:phone":"+1 508 477 3675",
    "sg:postcode":"02649",
    "sg:province":"MA",
    "sg:tags":[
        "recycling",
        "center"
    ],
    "wof:name":"Mashpee Wine & Spirits",
    "wof:placetype":"venue"
},
  "geometry": {"coordinates":[-70.494817,41.657686],"type":"Point"}
}