{
  "type": "Feature",
  "properties": {
    "iso:country":"US",
    "sg:address":"8 2nd New Way",
    "sg:city":"Hyde Park",
    "sg:classifiers":[
        {
            "category":"Retail",
            "subcategory":"Auto Repair",
            "type":"Services"
        }
    ],
    "sg:phone":"+1 617 364 6470",
    "sg:postcode":"02136",
    "sg:province":"MA",
    "sg:tags":[
        "wrecker"
    ],
    "wof:name":"Glaser's Towing Svc",
    "wof:placetype":"venue"
},
  "geometry": {"coordinates":[-71.11961700000001,42.254437],"type":"Point"}
}