{
  "type": "Feature",
  "properties": {
    "addr:full": "8 2nd New Way Hyde Park MA 02136",
    "addr:housenumber": "8",
    "addr:postcode": "02136",
    "addr:street": "2Nd New",
    "iso:country": "US",
    "sg:address": "8 2nd New Way",
    "sg:city": "Hyde Park",
    "sg:classifiers": [
      {
        "category": "Retail",
        "subcategory": "Auto Repair",
        "type": "Services"
      }
    ],
    "sg:phone": "+1 617 364 6470",
    "sg:postcode": "02136",
    "sg:province": "MA",
    "sg:tags": [
      "wrecker"
    ],
    "wof:name": "Glaser's Towing Svc",
    "wof:placetype": "venue"
  },
  "geometry": {"coordinates":[-71.119617,42.254437],"type":"Point"}
}
