{
  "type": "Feature",
  "properties": {
    "iso:country":"US",
    "sg:address":"705 Gallivan Blvd",
    "sg:city":"Dorchester Ctr",
    "sg:classifiers":[
        {
            "category":"Home & Garden",
            "subcategory":"Building Materials",
            "type":"Retail Goods"
        }
    ],
    "sg:phone":"+1 617 436 1268",
    "sg:postcode":"02124",
    "sg:province":"MA",
    "sg:tags":[
        "paint"
    ],
    "sg:website":"www.driveinpaintmart.com",
    "wof:name":"Drive In Paint Mart",
    "wof:placetype":"venue"
},
  "geometry": {"coordinates":[-71.047713,42.283608],"type":"Point"}
}