{
  "type": "Feature",
  "properties": {
    "iso:country":"US",
    "sg:address":"1533 Main St",
    "sg:city":"Springfield",
    "sg:classifiers":[
        {
            "category":"Manufacturing",
            "subcategory":"Printing",
            "type":"Manufacturing & Wholesale Goods"
        }
    ],
    "sg:phone":"+1 413 543 6001",
    "sg:postcode":"01103",
    "sg:province":"MA",
    "sg:tags":[
        "printer"
    ],
    "wof:name":"PIP Printing",
    "wof:placetype":"venue"
},
  "geometry": {"coordinates":[-72.592235,42.103461],"type":"Point"}
}