{
  "type": "Feature",
  "properties": {
    "addr:full":"374 Salem St Andover MA 01810",
    "addr:housenumber":"374",
    "addr:postcode":"01810",
    "addr:street":"Salem St",
    "iso:country":"US",
    "sg:address":"374 Salem St",
    "sg:city":"Andover",
    "sg:classifiers":[
        {
            "category":"Autos & Motor Vehicles",
            "subcategory":"Automobile Sales",
            "type":"Retail Goods"
        }
    ],
    "sg:phone":"+1   ",
    "sg:postcode":"01810",
    "sg:province":"MA",
    "sg:tags":[
        "used"
    ],
    "wof:name":"Classic Marque Ltd",
    "wof:placetype":"venue"
},
  "geometry": {"coordinates":[-71.091139,42.622664],"type":"Point"}
}