{
  "type": "Feature",
  "properties": {
    "iso:country":"US",
    "sg:address":"4 Bay Rd",
    "sg:city":"Norton",
    "sg:classifiers":[
        {
            "category":"Restaurant",
            "type":"Food & Drink"
        }
    ],
    "sg:phone":"+1 508 285 7481",
    "sg:postcode":"02766",
    "sg:province":"MA",
    "wof:name":"A Nossa Casa Restaurant",
    "wof:placetype":"venue"
},
  "geometry": {"coordinates":[-71.12614600000001,41.966847],"type":"Point"}
}