{
  "type": "Feature",
  "properties": {
    "addr:full": "4 Bay Rd Norton MA 02766",
    "addr:housenumber": "4",
    "addr:postcode": "02766",
    "addr:street": "Bay Rd",
    "iso:country": "US",
    "sg:address": "4 Bay Rd",
    "sg:city": "Norton",
    "sg:classifiers": [
      {
        "category": "Restaurant",
        "type": "Food \u0026 Drink"
      }
    ],
    "sg:phone": "+1 508 285 7481",
    "sg:postcode": "02766",
    "sg:province": "MA",
    "wof:name": "A Nossa Casa Restaurant",
    "wof:placetype": "venue"
  },
  "geometry": {"coordinates":[-71.126146,41.966847],"type":"Point"}
}
