{
  "type": "Feature",
  "properties": {
    "addr:full": "36 S Main St Sharon MA 02067",
    "addr:housenumber": "36",
    "addr:postcode": "02067",
    "addr:street": "S Main St",
    "iso:country": "US",
    "sg:address": "36 S Main St",
    "sg:city": "Sharon",
    "sg:classifiers": [
      {
        "category": "Building \u0026 Trades",
        "subcategory": "Construction",
        "type": "Services"
      }
    ],
    "sg:phone": "+1 781 784 2731",
    "sg:postcode": "02067",
    "sg:province": "MA",
    "sg:tags": [
      "front",
      "store"
    ],
    "wof:name": "Advance Equipment Inc",
    "wof:placetype": "venue"
  },
  "geometry": {"coordinates":[-71.17971,42.12242],"type":"Point"}
}
