{
  "type": "Feature",
  "properties": {
    "addr:full":"165 Prospect St Marshfield MA 02050",
    "addr:housenumber":"165",
    "addr:postcode":"02050",
    "addr:street":"Prospect St",
    "iso:country":"US",
    "sg:address":"165 Prospect St",
    "sg:city":"Marshfield",
    "sg:classifiers":[
        {
            "category":"Shopping",
            "subcategory":"Discount & Variety Stores",
            "type":"Retail Goods"
        }
    ],
    "sg:phone":"+1 781 834 8443",
    "sg:postcode":"02050",
    "sg:province":"MA",
    "sg:tags":[
        "merchandise",
        "general"
    ],
    "wof:name":"Marshfield Hills General Store",
    "wof:placetype":"venue"
},
  "geometry": {"coordinates":[-70.73839,42.145775],"type":"Point"}
}