{
  "type": "Feature",
  "properties": {
    "addr:full":"38 Montvale Avenue Stoneham MA 02180",
    "addr:housenumber":"38",
    "addr:postcode":"02180",
    "addr:street":"Montvale Avenue",
    "iso:country":"US",
    "sg:address":"38 Montvale Avenue",
    "sg:city":"Stoneham",
    "sg:classifiers":[
        {
            "category":"Food & Beverages",
            "subcategory":"Groceries & Convenience Stores",
            "type":"Retail Goods"
        }
    ],
    "sg:phone":"+1 781 279 9943",
    "sg:postcode":"02180",
    "sg:province":"MA",
    "wof:name":"Laverde's",
    "wof:placetype":"venue"
},
  "geometry": {"coordinates":[-71.103741,42.482082],"type":"Point"}
}