{
  "type": "Feature",
  "properties": {
    "iso:country":"US",
    "sg:address":"13 This Way",
    "sg:city":"Osterville",
    "sg:classifiers":[
        {
            "category":"Building & Trades",
            "subcategory":"Construction",
            "type":"Services"
        }
    ],
    "sg:phone":"+1 508 428 4828",
    "sg:postcode":"02655",
    "sg:province":"MA",
    "sg:tags":[
        "general",
        "contractor"
    ],
    "wof:name":"M K Nickerson Residential",
    "wof:placetype":"venue"
},
  "geometry": {"coordinates":[-70.39062199999999,41.646615],"type":"Point"}
}