{
  "type": "Feature",
  "properties": {
    "addr:full":"13 Springs Rd Billerica MA 01821",
    "addr:housenumber":"13",
    "addr:postcode":"01821",
    "addr:street":"Springs Rd",
    "iso:country":"US",
    "sg:address":"13 Springs Rd",
    "sg:city":"Billerica",
    "sg:classifiers":[
        {
            "category":"Education",
            "subcategory":"Dance Studio",
            "type":"Public Place"
        }
    ],
    "sg:phone":"+1 978 670 9333",
    "sg:postcode":"01821",
    "sg:province":"MA",
    "sg:tags":[
        "square",
        "caller"
    ],
    "wof:name":"Parkes & Parkes",
    "wof:placetype":"venue"
},
  "geometry": {"coordinates":[-71.280923,42.526437],"type":"Point"}
}