{
  "type": "Feature",
  "properties": {
    "addr:full": "75 Riverside Avenue Medford MA 02155",
    "addr:housenumber": "75",
    "addr:postcode": "02155",
    "addr:street": "Riverside Avenue",
    "iso:country": "US",
    "sg:address": "75 Riverside Avenue",
    "sg:city": "Medford",
    "sg:classifiers": [
      {
        "category": "Health Services",
        "subcategory": "Doctor",
        "type": "Services"
      },
      {
        "category": "Sports \u0026 Exercise",
        "subcategory": "Gym",
        "type": "Entertainment"
      }
    ],
    "sg:phone": "+1 781 391 8821",
    "sg:postcode": "02155",
    "sg:province": "MA",
    "sg:tags": [
      "trainer",
      "pediatrician"
    ],
    "wof:name": "Mystic Valley Pediatrics",
    "wof:placetype": "venue"
  },
  "geometry": {"coordinates":[-71.105564,42.416871],"type":"Point"}
}
