{
  "type": "Feature",
  "properties": {
    "iso:country":"US",
    "sg:address":"128 Memorial Dr",
    "sg:city":"Shrewsbury",
    "sg:classifiers":[
        {
            "category":"Professional",
            "subcategory":"Management & Consulting",
            "type":"Services"
        }
    ],
    "sg:phone":"+1 508 845 5400",
    "sg:postcode":"01545",
    "sg:province":"MA",
    "sg:tags":[
        "consultant",
        "business"
    ],
    "wof:name":"Mercator Advisory Group",
    "wof:placetype":"venue"
},
  "geometry": {"coordinates":[-71.71071000000001,42.266834],"type":"Point"}
}