{
  "type": "Feature",
  "properties": {
    "addr:full": "128 Memorial Dr Shrewsbury MA 01545",
    "addr:housenumber": "128",
    "addr:postcode": "01545",
    "addr:street": "Memorial Dr",
    "iso:country": "US",
    "sg:address": "128 Memorial Dr",
    "sg:city": "Shrewsbury",
    "sg:classifiers": [
      {
        "category": "Professional",
        "subcategory": "Management \u0026 Consulting",
        "type": "Services"
      }
    ],
    "sg:phone": "+1 508 845 5400",
    "sg:postcode": "01545",
    "sg:province": "MA",
    "sg:tags": [
      "consultant",
      "business"
    ],
    "wof:name": "Mercator Advisory Group",
    "wof:placetype": "venue"
  },
  "geometry": {"coordinates":[-71.71071,42.266834],"type":"Point"}
}
