{
  "type": "Feature",
  "properties": {
    "addr:full": "1877 Washington St Hanover MA 02339",
    "addr:housenumber": "1877",
    "addr:postcode": "02339",
    "addr:street": "Washington St",
    "iso:country": "US",
    "sg:address": "1877 Washington St",
    "sg:city": "Hanover",
    "sg:classifiers": [
      {
        "category": "Autos \u0026 Motor Vehicles",
        "subcategory": "Automobile Sales",
        "type": "Retail Goods"
      }
    ],
    "sg:phone": "+1 781 826 8300",
    "sg:postcode": "02339",
    "sg:province": "MA",
    "sg:tags": [
      "car",
      "dealer"
    ],
    "sg:website": "www.columbiamotors.com",
    "wof:name": "Columbia Buick Pontiac GMC",
    "wof:placetype": "venue"
  },
  "geometry": {"coordinates":[-70.845379,42.149595],"type":"Point"}
}
