{
  "type": "Feature",
  "properties": {
    "iso:country":"US",
    "sg:address":"1877 Washington St",
    "sg:city":"Hanover",
    "sg:classifiers":[
        {
            "category":"Autos & Motor Vehicles",
            "subcategory":"Automobile Sales",
            "type":"Retail Goods"
        }
    ],
    "sg:phone":"+1 781 826 8300",
    "sg:postcode":"02339",
    "sg:province":"MA",
    "sg:tags":[
        "car",
        "dealer"
    ],
    "sg:website":"www.columbiamotors.com",
    "wof:name":"Columbia Buick Pontiac GMC",
    "wof:placetype":"venue"
},
  "geometry": {"coordinates":[-70.84537899999999,42.149595],"type":"Point"}
}