{
  "type": "Feature",
  "properties": {
    "addr:full": "158 Captain Pierce Rd Scituate MA 02066",
    "addr:housenumber": "158",
    "addr:postcode": "02066",
    "addr:street": "Captain Pierce Rd",
    "iso:country": "US",
    "sg:address": "158 Captain Pierce Rd",
    "sg:city": "Scituate",
    "sg:classifiers": [
      {
        "category": "Restaurant",
        "type": "Food \u0026 Drink"
      }
    ],
    "sg:phone": "+1 781 545 7091",
    "sg:postcode": "02066",
    "sg:province": "MA",
    "sg:tags": [
      "style",
      "family"
    ],
    "wof:name": "Denny Kerns \u0026 Associates",
    "wof:placetype": "venue"
  },
  "geometry": {"coordinates":[-70.769208,42.210473],"type":"Point"}
}
