{
  "type": "Feature",
  "properties": {
    "addr:full": "3 Williams Rd Sterling MA 01564",
    "addr:housenumber": "3",
    "addr:postcode": "01564",
    "addr:street": "Williams Rd",
    "iso:country": "US",
    "sg:address": "3 Williams Rd",
    "sg:city": "Sterling",
    "sg:classifiers": [
      {
        "category": "Retail",
        "subcategory": "Auto Repair",
        "type": "Services"
      }
    ],
    "sg:phone": "+1 978 422 6567",
    "sg:postcode": "01564",
    "sg:province": "MA",
    "sg:tags": [
      "repairing",
      "automobile"
    ],
    "wof:name": "Rick's Auto Repair",
    "wof:placetype": "venue"
  },
  "geometry": {"coordinates":[-71.763721,42.479034],"type":"Point"}
}
