{
  "type": "Feature",
  "properties": {
    "addr:full": "5 Merchants Dr Ste 1 Walpole MA 02081",
    "addr:housenumber": "5",
    "addr:postcode": "02081",
    "addr:street": "Merchants Dr Ste 1",
    "iso:country": "US",
    "sg:address": "5 Merchants Dr Ste 1",
    "sg:city": "Walpole",
    "sg:phone": "+1 508 668 4900",
    "sg:postcode": "02081",
    "sg:province": "MA",
    "sg:website": "http://www.acmeglass.net",
    "wof:name": "Acme Glass Co",
    "wof:placetype": "venue"
  },
  "geometry": {"coordinates":[-71.269634,42.136757],"type":"Point"}
}
