{
  "type": "Feature",
  "properties": {
    "addr:full":"9 Riverside Ave Danvers MA 01923",
    "addr:housenumber":"9",
    "addr:postcode":"01923",
    "addr:street":"Riverside Ave",
    "iso:country":"US",
    "sg:address":"9 Riverside Ave",
    "sg:city":"Danvers",
    "sg:classifiers":[
        {
            "category":"Manufacturing",
            "subcategory":"Tools & Machinery",
            "type":"Manufacturing & Wholesale Goods"
        }
    ],
    "sg:phone":"+1 978 777 3772",
    "sg:postcode":"01923",
    "sg:province":"MA",
    "sg:tags":[
        "machine",
        "shop"
    ],
    "wof:name":"Auto Industrial Machine Inc",
    "wof:placetype":"venue"
},
  "geometry": {"coordinates":[-70.930497,42.561419],"type":"Point"}
}