{
  "type": "Feature",
  "properties": {
    "addr:full":"192 Main St Kingston MA 02364",
    "addr:housenumber":"192",
    "addr:postcode":"02364",
    "addr:street":"Main St",
    "iso:country":"US",
    "sg:address":"192 Main St",
    "sg:city":"Kingston",
    "sg:classifiers":[
        {
            "category":"Retail",
            "subcategory":"Veterinary Services",
            "type":"Services"
        }
    ],
    "sg:phone":"+1 781 585 6525",
    "sg:postcode":"02364",
    "sg:province":"MA",
    "sg:tags":[
        "veterinarian"
    ],
    "wof:name":"Kingston Animal Hospital",
    "wof:placetype":"venue"
},
  "geometry": {"coordinates":[-70.72613699999999,41.991966],"type":"Point"}
}