{
  "type": "Feature",
  "properties": {
    "addr:full":"106 Inverness Ln Longmeadow MA 01106",
    "addr:housenumber":"106",
    "addr:postcode":"01106",
    "addr:street":"Inverness Ln",
    "iso:country":"US",
    "sg:address":"106 Inverness Ln",
    "sg:city":"Longmeadow",
    "sg:classifiers":[
        {
            "category":"Professional",
            "subcategory":"Accounting & Tax Preparation",
            "type":"Services"
        }
    ],
    "sg:phone":"+1 413 565 2100",
    "sg:postcode":"01106",
    "sg:province":"MA",
    "sg:tags":[
        "return",
        "accountants-certified",
        "preparation-business",
        "taxes-consultants",
        "representative",
        "public"
    ],
    "sg:website":"http://www.jahpccpa.com",
    "wof:name":"Jeffrey A. Hirsch, PC",
    "wof:placetype":"venue"
},
  "geometry": {"coordinates":[-72.552063,42.041359],"type":"Point"}
}