{
  "type": "Feature",
  "properties": {
    "addr:full": "503 Hosmer St Marlborough MA 01752",
    "addr:housenumber": "503",
    "addr:postcode": "01752",
    "addr:street": "Hosmer St",
    "iso:country": "US",
    "sg:address": "503 Hosmer St",
    "sg:city": "Marlborough",
    "sg:classifiers": [
      {
        "category": "Building \u0026 Trades",
        "subcategory": "Landscaping Services",
        "type": "Services"
      }
    ],
    "sg:phone": "+1 508 481 2255",
    "sg:postcode": "01752",
    "sg:province": "MA",
    "sg:tags": [
      "landscape",
      "contractor"
    ],
    "wof:name": "Andy Craig Lawn \u0026 Landscape",
    "wof:placetype": "venue"
  },
  "geometry": {"coordinates":[-71.531471,42.367641],"type":"Point"}
}
