{
  "type": "Feature",
  "properties": {
    "iso:country":"US",
    "sg:address":"503 Hosmer St",
    "sg:city":"Marlborough",
    "sg:classifiers":[
        {
            "category":"Building & Trades",
            "subcategory":"Landscaping Services",
            "type":"Services"
        }
    ],
    "sg:phone":"+1 508 481 2255",
    "sg:postcode":"01752",
    "sg:province":"MA",
    "sg:tags":[
        "landscape",
        "contractor"
    ],
    "wof:name":"Andy Craig Lawn & Landscape",
    "wof:placetype":"venue"
},
  "geometry": {"coordinates":[-71.531471,42.367641],"type":"Point"}
}