{
  "type": "Feature",
  "properties": {
    "iso:country":"US",
    "sg:address":"20 Franklin St 1st Fl",
    "sg:city":"Allston",
    "sg:classifiers":[
        {
            "category":"Health Services",
            "subcategory":"Health Practitioner",
            "type":"Services"
        },
        {
            "category":"Health Services",
            "subcategory":"Chiropractor",
            "type":"Services"
        }
    ],
    "sg:phone":"+1 617 787 8700",
    "sg:postcode":"02134",
    "sg:province":"MA",
    "sg:tags":[
        "therapy",
        "physical"
    ],
    "sg:website":"www.bostonsportsmed.com",
    "wof:name":"Boston Sports Medicine",
    "wof:placetype":"venue"
},
  "geometry": {"coordinates":[-71.132886,42.356212],"type":"Point"}
}