{
  "type": "Feature",
  "properties": {
    "iso:country":"US",
    "sg:address":"1690 Hyde Park Ave",
    "sg:city":"Hyde Park",
    "sg:classifiers":[
        {
            "category":"Retail",
            "subcategory":"Repair Shop",
            "type":"Services"
        }
    ],
    "sg:phone":"+1 617 333 0535",
    "sg:postcode":"02136",
    "sg:province":"MA",
    "sg:tags":[
        "welding"
    ],
    "wof:name":"Henry's Railings",
    "wof:placetype":"venue"
},
  "geometry": {"coordinates":[-71.12989399999999,42.243647],"type":"Point"}
}