{
  "type": "Feature",
  "properties": {
    "iso:country":"US",
    "sg:address":"830 Oak St",
    "sg:city":"Brockton",
    "sg:classifiers":[
        {
            "category":"Health Services",
            "subcategory":"Doctor",
            "type":"Services"
        }
    ],
    "sg:phone":"+1 508 897 4723",
    "sg:postcode":"02301",
    "sg:province":"MA",
    "sg:tags":[
        "physician",
        "surgeon"
    ],
    "wof:name":"Youssef Anid MD",
    "wof:placetype":"venue"
},
  "geometry": {"coordinates":[-71.06127600000001,42.100351],"type":"Point"}
}