{
  "type": "Feature",
  "properties": {
    "addr:full":"66 Old Bolton Rd Stow MA 01775",
    "addr:housenumber":"66",
    "addr:postcode":"01775",
    "addr:street":"Old Bolton Rd",
    "iso:country":"US",
    "sg:address":"66 Old Bolton Rd",
    "sg:city":"Stow",
    "sg:classifiers":[
        {
            "category":"Real Estate",
            "subcategory":"Real Estate Agent",
            "type":"Services"
        }
    ],
    "sg:phone":"+1 978 897 7130",
    "sg:postcode":"01775",
    "sg:province":"MA",
    "sg:tags":[
        "inspection"
    ],
    "wof:name":"Allstate Home Inspection",
    "wof:placetype":"venue"
},
  "geometry": {"coordinates":[-71.54501500000001,42.43445],"type":"Point"}
}