{
  "type": "Feature",
  "properties": {
    "iso:country":"US",
    "sg:address":"408 Atlantic Ave",
    "sg:city":"Boston",
    "sg:classifiers":[
        {
            "category":"Professional",
            "type":"Services"
        }
    ],
    "sg:phone":"+1 617 223 8015",
    "sg:postcode":"02110",
    "sg:province":"MA",
    "sg:tags":[
        "government",
        "agency",
        "services-information",
        "program",
        "social",
        "referral"
    ],
    "wof:name":"National Oceanic & Atmospheric",
    "wof:placetype":"venue"
},
  "geometry": {"coordinates":[-71.051041,42.355202],"type":"Point"}
}