{
  "type": "Feature",
  "properties": {
    "iso:country":"US",
    "sg:address":"71 Whittemore St",
    "sg:city":"Leicester",
    "sg:classifiers":[
        {
            "category":"Farming",
            "subcategory":"Nursery",
            "type":"Manufacturing & Wholesale Goods"
        }
    ],
    "sg:phone":"+1 508 892 4184",
    "sg:postcode":"01524",
    "sg:province":"MA",
    "sg:tags":[
        "tree",
        "grower",
        "nursery-wholesale",
        "nurseries-plants"
    ],
    "wof:name":"Johnson's Greenhouse",
    "wof:placetype":"venue"
},
  "geometry": {"coordinates":[-71.910951,42.25722],"type":"Point"}
}