{
  "type": "Feature",
  "properties": {
    "addr:full": "35 Corporate Dr Burlington MA 01803",
    "addr:housenumber": "35",
    "addr:postcode": "01803",
    "addr:street": "Corporate Dr",
    "iso:country": "US",
    "sg:address": "35 Corporate Dr",
    "sg:city": "Burlington",
    "sg:classifiers": [
      {
        "category": "Retail",
        "subcategory": "Portrait Studio",
        "type": "Services"
      },
      {
        "category": "Banks \u0026 Credit Unions",
        "subcategory": "Bank",
        "type": "Services"
      }
    ],
    "sg:phone": "+1 781 505 9820",
    "sg:postcode": "01803",
    "sg:province": "MA",
    "sg:tags": [
      "photography",
      "store"
    ],
    "wof:name": "Eastern Corporate Federal Credit Union",
    "wof:placetype": "venue"
  },
  "geometry": {"coordinates":[-71.189812,42.494764],"type":"Point"}
}
