{
  "type": "Feature",
  "properties": {
    "iso:country":"US",
    "sg:address":"65 Mount Auburn St",
    "sg:city":"Cambridge",
    "sg:classifiers":[
        {
            "category":"Health Services",
            "subcategory":"Optometrist",
            "type":"Services"
        }
    ],
    "sg:phone":"+1 617 547 8165",
    "sg:postcode":"02138",
    "sg:province":"MA",
    "wof:name":"D'ambrosio Louis F At Harvard Sq Optics Optmrst",
    "wof:placetype":"venue"
},
  "geometry": {"coordinates":[-71.1185,42.372002],"type":"Point"}
}