{
  "type": "Feature",
  "properties": {
    "iso:country":"US",
    "sg:address":"791 South St E",
    "sg:city":"Raynham",
    "sg:classifiers":[
        {
            "category":"Freight",
            "type":"Transportation"
        }
    ],
    "sg:phone":"+1 508 880 7116",
    "sg:postcode":"02767",
    "sg:province":"MA",
    "sg:tags":[
        "hauling",
        "trucking"
    ],
    "wof:name":"J Rego Trucking Inc",
    "wof:placetype":"venue"
},
  "geometry": {"coordinates":[-71.043851,41.902509],"type":"Point"}
}