{
  "type": "Feature",
  "properties": {
    "addr:full": "466 Talbot Ave Dorchester Ctr MA 02124",
    "addr:housenumber": "466",
    "addr:postcode": "02124",
    "addr:street": "Talbot Ave Dorchester Ctr",
    "iso:country": "US",
    "sg:address": "466 Talbot Ave",
    "sg:city": "Dorchester Ctr",
    "sg:classifiers": [
      {
        "category": "Shopping",
        "subcategory": "Discount \u0026 Variety Stores",
        "type": "Retail Goods"
      }
    ],
    "sg:phone": "+1 617 288 9646",
    "sg:postcode": "02124",
    "sg:province": "MA",
    "wof:name": "Mini Rossi",
    "wof:placetype": "venue"
  },
  "geometry": {"coordinates":[-71.065684,42.288274],"type":"Point"}
}
