{
  "type": "Feature",
  "properties": {
    "iso:country":"US",
    "sg:address":"466 Talbot Ave",
    "sg:city":"Dorchester Ctr",
    "sg:classifiers":[
        {
            "category":"Shopping",
            "subcategory":"Discount & Variety Stores",
            "type":"Retail Goods"
        }
    ],
    "sg:phone":"+1 617 288 9646",
    "sg:postcode":"02124",
    "sg:province":"MA",
    "wof:name":"Mini Rossi",
    "wof:placetype":"venue"
},
  "geometry": {"coordinates":[-71.065684,42.288274],"type":"Point"}
}