{
  "type": "Feature",
  "properties": {
    "iso:country":"US",
    "sg:address":"30 Grant Ave",
    "sg:city":"Burlington",
    "sg:classifiers":[
        {
            "category":"Building & Trades",
            "subcategory":"Locksmith",
            "type":"Services"
        }
    ],
    "sg:phone":"+1 781 425 2122",
    "sg:postcode":"01803",
    "sg:province":"MA",
    "sg:tags":[
        "key"
    ],
    "wof:name":"Top Rate Locksmith",
    "wof:placetype":"venue"
},
  "geometry": {"coordinates":[-71.20001999999999,42.512616],"type":"Point"}
}