{
  "type": "Feature",
  "properties": {
    "addr:full":"34 Myrtle Ave Winthrop MA 02152",
    "addr:housenumber":"34",
    "addr:postcode":"02152",
    "addr:street":"Myrtle Ave",
    "iso:country":"US",
    "sg:address":"34 Myrtle Ave",
    "sg:city":"Winthrop",
    "sg:classifiers":[
        {
            "category":"Home & Garden",
            "subcategory":"Household Appliances",
            "type":"Retail Goods"
        }
    ],
    "sg:phone":"+1 617 846 1471",
    "sg:postcode":"02152",
    "sg:province":"MA",
    "sg:tags":[
        "small",
        "repair"
    ],
    "wof:name":"Winthrop Appliance Service",
    "wof:placetype":"venue"
},
  "geometry": {"coordinates":[-70.973282,42.38176],"type":"Point"}
}