{
  "type": "Feature",
  "properties": {
    "addr:full":"7 Charlton St Everett MA 02149",
    "addr:housenumber":"7",
    "addr:postcode":"02149",
    "addr:street":"Charlton St",
    "iso:country":"US",
    "sg:address":"7 Charlton St",
    "sg:city":"Everett",
    "sg:classifiers":[
        {
            "category":"Real Estate",
            "subcategory":"Real Estate Agent",
            "type":"Services"
        }
    ],
    "sg:phone":"+1 617 389 0650",
    "sg:postcode":"02149",
    "sg:province":"MA",
    "sg:tags":[
        "investment"
    ],
    "wof:name":"Pinnacle Properties II",
    "wof:placetype":"venue"
},
  "geometry": {"coordinates":[-71.06265500000001,42.400773],"type":"Point"}
}