{
  "type": "Feature",
  "properties": {
    "addr:full": "452 Great Rd Acton MA 01720",
    "addr:housenumber": "452",
    "addr:postcode": "01720",
    "addr:street": "Great Rd",
    "iso:country": "US",
    "sg:address": "452 Great Rd",
    "sg:city": "Acton",
    "sg:classifiers": [
      {
        "category": "Shopping",
        "subcategory": "Used Merchandise",
        "type": "Retail Goods"
      }
    ],
    "sg:phone": "+1 978 266 1115",
    "sg:postcode": "01720",
    "sg:province": "MA",
    "sg:tags": [
      "shop",
      "consignment"
    ],
    "sg:website": "www.tablestoteapots.com",
    "wof:name": "Tables To Teapots Distinctive",
    "wof:placetype": "venue"
  },
  "geometry": {"coordinates":[-71.424615,42.513244],"type":"Point"}
}
