{
  "type": "Feature",
  "properties": {
    "addr:full":"11 Rockmere St Dorchester MA 02125",
    "addr:housenumber":"11",
    "addr:postcode":"02125",
    "addr:street":"Rockmere St",
    "iso:country":"US",
    "sg:address":"11 Rockmere St",
    "sg:city":"Dorchester",
    "sg:classifiers":[
        {
            "category":"Professional",
            "subcategory":"Management & Consulting",
            "type":"Services"
        }
    ],
    "sg:phone":"+1 617 436 9024",
    "sg:postcode":"02125",
    "sg:province":"MA",
    "sg:tags":[
        "consultant"
    ],
    "wof:name":"Schardt Media",
    "wof:placetype":"venue"
},
  "geometry": {"coordinates":[-71.050282,42.310727],"type":"Point"}
}