{
  "type": "Feature",
  "properties": {
    "addr:full":"218 Willard St Leominster MA 01453",
    "addr:housenumber":"218",
    "addr:postcode":"01453",
    "addr:street":"Willard St",
    "iso:country":"US",
    "sg:address":"218 Willard St",
    "sg:city":"Leominster",
    "sg:classifiers":[
        {
            "category":"Shopping",
            "type":"Retail Goods"
        }
    ],
    "sg:phone":"+1 978 537 3824",
    "sg:postcode":"01453",
    "sg:province":"MA",
    "sg:tags":[
        "plastic"
    ],
    "wof:name":"A & R Plastics Moldg",
    "wof:placetype":"venue"
},
  "geometry": {"coordinates":[-71.734949,42.496953],"type":"Point"}
}