{
  "type": "Feature",
  "properties": {
    "addr:full": "50 Pleasant St Holyoke MA 01040",
    "addr:housenumber": "50",
    "addr:postcode": "01040",
    "addr:street": "Pleasant St",
    "iso:country": "US",
    "sg:address": "50 Pleasant St",
    "sg:city": "Holyoke",
    "sg:classifiers": [
      {
        "category": "Real Estate",
        "subcategory": "Real Estate Agent",
        "type": "Services"
      }
    ],
    "sg:phone": "+1 413 539 6637",
    "sg:postcode": "01040",
    "sg:province": "MA",
    "wof:name": "John H Woods \u0026 Co",
    "wof:placetype": "venue"
  },
  "geometry": {"coordinates":[-72.623002,42.227439],"type":"Point"}
}
