{
  "type": "Feature",
  "properties": {
    "addr:full": "91 Felton St Waltham MA 02453",
    "addr:housenumber": "91",
    "addr:postcode": "02453",
    "addr:street": "Felton St",
    "iso:country": "US",
    "sg:address": "91 Felton St",
    "sg:city": "Waltham",
    "sg:classifiers": [
      {
        "category": "Building \u0026 Trades",
        "subcategory": "Construction",
        "type": "Services"
      }
    ],
    "sg:phone": "+1 781 899 1900",
    "sg:postcode": "02453",
    "sg:province": "MA",
    "sg:tags": [
      "home",
      "builder"
    ],
    "wof:name": "Kenneth Vona Construction",
    "wof:placetype": "venue"
  },
  "geometry": {"coordinates":[-71.241716,42.373511],"type":"Point"}
}
