{
  "type": "Feature",
  "properties": {
    "iso:country":"US",
    "sg:address":"52 Holden St",
    "sg:city":"Worcester",
    "sg:classifiers":[
        {
            "category":"Health Services",
            "subcategory":"Nursing And Care Facility",
            "type":"Services"
        }
    ],
    "sg:phone":"+1 508 854 0431",
    "sg:postcode":"01605",
    "sg:province":"MA",
    "sg:tags":[
        "home",
        "retirement",
        "community"
    ],
    "wof:name":"Bringing Elder Care Home",
    "wof:placetype":"venue"
},
  "geometry": {"coordinates":[-71.817699,42.301669],"type":"Point"}
}