{
  "type": "Feature",
  "properties": {
    "iso:country":"US",
    "sg:address":"23 West St",
    "sg:city":"Lunenburg",
    "sg:classifiers":[
        {
            "category":"Recreation",
            "type":"Entertainment"
        }
    ],
    "sg:phone":"+1 978 582 4165",
    "sg:postcode":"01462",
    "sg:province":"MA",
    "sg:tags":[
        "parks"
    ],
    "wof:name":"Park Dept",
    "wof:placetype":"venue"
},
  "geometry": {"coordinates":[-71.733062,42.589712],"type":"Point"}
}