{
  "type": "Feature",
  "properties": {
    "iso:country":"US",
    "sg:address":"41 Aurora Ln",
    "sg:city":"South Yarmouth",
    "sg:classifiers":[
        {
            "category":"Building & Trades",
            "subcategory":"Landscaping Services",
            "type":"Services"
        }
    ],
    "sg:phone":"+1   ",
    "sg:postcode":"02664",
    "sg:province":"MA",
    "sg:tags":[
        "landscape"
    ],
    "wof:name":"Anthonys Tree Service",
    "wof:placetype":"venue"
},
  "geometry": {"coordinates":[-70.209526,41.682153],"type":"Point"}
}