{
  "type": "Feature",
  "properties": {
    "iso:country":"US",
    "sg:address":"6 Allison Cir",
    "sg:city":"Worcester",
    "sg:classifiers":[
        {
            "category":"Banks & Credit Unions",
            "subcategory":"Bank",
            "type":"Services"
        }
    ],
    "sg:phone":"+1 508 852 4178",
    "sg:postcode":"01606",
    "sg:province":"MA",
    "sg:tags":[
        "broker",
        "mortgage"
    ],
    "wof:name":"Mortgage Concepts Inc",
    "wof:placetype":"venue"
},
  "geometry": {"coordinates":[-71.784058,42.329819],"type":"Point"}
}