{
  "type": "Feature",
  "properties": {
    "addr:full":"152 Court St Plymouth MA 02360",
    "addr:housenumber":"152",
    "addr:postcode":"02360",
    "addr:street":"Court St",
    "iso:country":"US",
    "sg:address":"152 Court St",
    "sg:city":"Plymouth",
    "sg:classifiers":[
        {
            "category":"Personal",
            "subcategory":"Beauty Salon",
            "type":"Services"
        }
    ],
    "sg:phone":"+1 508 746 4884",
    "sg:postcode":"02360",
    "sg:province":"MA",
    "wof:name":"A Second Look",
    "wof:placetype":"venue"
},
  "geometry": {"coordinates":[-70.67429199999999,41.962531],"type":"Point"}
}