{
  "type": "Feature",
  "properties": {
    "iso:country":"US",
    "sg:address":"5 Broadway",
    "sg:city":"Gloucester",
    "sg:classifiers":[
        {
            "category":"Insurance",
            "subcategory":"Insurance Agent",
            "type":"Services"
        }
    ],
    "sg:phone":"+1 978 231 6888",
    "sg:postcode":"01915",
    "sg:province":"MA",
    "sg:tags":[
        "adjuster"
    ],
    "wof:name":"Depiano & Todisco",
    "wof:placetype":"venue"
},
  "geometry": {"coordinates":[-70.88003999999999,42.547815],"type":"Point"}
}