{
  "type": "Feature",
  "properties": {
    "addr:full": "5 Broadway Gloucester MA 01915",
    "addr:housenumber": "5",
    "addr:postcode": "01915",
    "addr:street": "Broadway",
    "iso:country": "US",
    "sg:address": "5 Broadway",
    "sg:city": "Gloucester",
    "sg:classifiers": [
      {
        "category": "Insurance",
        "subcategory": "Insurance Agent",
        "type": "Services"
      }
    ],
    "sg:phone": "+1 978 231 6888",
    "sg:postcode": "01915",
    "sg:province": "MA",
    "sg:tags": [
      "adjuster"
    ],
    "wof:name": "Depiano \u0026 Todisco",
    "wof:placetype": "venue"
  },
  "geometry": {"coordinates":[-70.88004,42.547815],"type":"Point"}
}
