{
  "type": "Feature",
  "properties": {
    "iso:country":"US",
    "sg:address":"18 Spruce St",
    "sg:city":"Greenfield",
    "sg:classifiers":[
        {
            "category":"Building & Trades",
            "subcategory":"Electrical",
            "type":"Services"
        }
    ],
    "sg:phone":"+1 413 772 5737",
    "sg:postcode":"01301",
    "sg:province":"MA",
    "sg:tags":[
        "electric",
        "contractor"
    ],
    "wof:name":"Sean Murphy Electric",
    "wof:placetype":"venue"
},
  "geometry": {"coordinates":[-72.609415,42.601273],"type":"Point"}
}