{
  "type": "Feature",
  "properties": {
    "iso:country":"US",
    "sg:address":"29 Rio Vista St",
    "sg:city":"North Billerica",
    "sg:classifiers":[
        {
            "category":"Professional",
            "subcategory":"Computer Services",
            "type":"Services"
        }
    ],
    "sg:phone":"+1   ",
    "sg:postcode":"01862",
    "sg:province":"MA",
    "sg:tags":[
        "related"
    ],
    "wof:name":"Distinctid",
    "wof:placetype":"venue"
},
  "geometry": {"coordinates":[-71.30279899999999,42.54552],"type":"Point"}
}