{
  "type": "Feature",
  "properties": {
    "iso:country":"US",
    "sg:address":"19 Sears Ave",
    "sg:city":"Melrose",
    "sg:classifiers":[
        {
            "category":"Professional",
            "subcategory":"Detective & Security Services",
            "type":"Services"
        }
    ],
    "sg:phone":"+1 781 640 1484",
    "sg:postcode":"02176",
    "sg:province":"MA",
    "sg:tags":[
        "information",
        "bureau"
    ],
    "wof:name":"Andrew Drgan Mem Golf Trnament",
    "wof:placetype":"venue"
},
  "geometry": {"coordinates":[-71.07538599999999,42.466561],"type":"Point"}
}