{
  "type": "Feature",
  "properties": {
    "addr:full": "19 Sears Ave Melrose MA 02176",
    "addr:housenumber": "19",
    "addr:postcode": "02176",
    "addr:street": "Sears Ave",
    "iso:country": "US",
    "sg:address": "19 Sears Ave",
    "sg:city": "Melrose",
    "sg:classifiers": [
      {
        "category": "Professional",
        "subcategory": "Detective \u0026 Security Services",
        "type": "Services"
      }
    ],
    "sg:phone": "+1 781 640 1484",
    "sg:postcode": "02176",
    "sg:province": "MA",
    "sg:tags": [
      "information",
      "bureau"
    ],
    "wof:name": "Andrew Drgan Mem Golf Trnament",
    "wof:placetype": "venue"
  },
  "geometry": {"coordinates":[-71.075386,42.466561],"type":"Point"}
}
