{
  "type": "Feature",
  "properties": {
    "addr:full": "206 Metcalf St Winchendon MA 01475",
    "addr:housenumber": "206",
    "addr:postcode": "01475",
    "addr:street": "Metcalf St",
    "iso:country": "US",
    "sg:address": "206 Metcalf St",
    "sg:city": "Winchendon",
    "sg:phone": "+1 978 297 1311",
    "sg:postcode": "01475",
    "sg:province": "MA",
    "wof:name": "Winchendon Taxi",
    "wof:placetype": "venue"
  },
  "geometry": {"coordinates":[-72.087044,42.669986],"type":"Point"}
}
