{
  "type": "Feature",
  "properties": {
    "addr:full": "254 Bay Rd South Hamilton MA 01982",
    "addr:housenumber": "254",
    "addr:postcode": "01982",
    "addr:street": "Bay Rd South",
    "iso:country": "US",
    "sg:address": "254 Bay Rd",
    "sg:city": "South Hamilton",
    "sg:classifiers": [
      {
        "category": "Professional",
        "subcategory": "Lawyer \u0026 Legal Services",
        "type": "Services"
      }
    ],
    "sg:phone": "+1 978 468 7200",
    "sg:postcode": "01982",
    "sg:province": "MA",
    "sg:tags": [
      "attorney"
    ],
    "wof:name": "Douglas Fecteau Law Offices",
    "wof:placetype": "venue"
  },
  "geometry": {"coordinates":[-70.872699,42.612528],"type":"Point"}
}
