{
  "type": "Feature",
  "properties": {
    "iso:country":"US",
    "sg:address":"85 Warren Street Apt 2",
    "sg:city":"Charlestown",
    "sg:classifiers":[
        {
            "category":"Professional",
            "subcategory":"Advertising",
            "type":"Services"
        }
    ],
    "sg:phone":"+1 888 460 9513",
    "sg:postcode":"02129",
    "sg:province":"MA",
    "sg:website":"http://www.collective.com",
    "wof:name":"Collective ",
    "wof:placetype":"venue"
},
  "geometry": {"coordinates":[-71.06250799999999,42.374325],"type":"Point"}
}