{
  "type": "Feature",
  "properties": {
    "iso:country":"US",
    "sg:address":"700 Oak St",
    "sg:city":"Brockton",
    "sg:classifiers":[
        {
            "category":"Restaurant",
            "type":"Food & Drink"
        }
    ],
    "sg:menulink":"http://www.allmenus.com/ma/brockton/131949-subway/menu/",
    "sg:phone":"+1 508 427 5464",
    "sg:postcode":"02301",
    "sg:province":"MA",
    "sg:tags":[
        "american",
        "sandwich"
    ],
    "wof:name":"Subway",
    "wof:placetype":"venue"
},
  "geometry": {"coordinates":[-71.057652,42.101159],"type":"Point"}
}