{
  "type": "Feature",
  "properties": {
    "addr:full": "700 Oak St Brockton MA 02301",
    "addr:housenumber": "700",
    "addr:postcode": "02301",
    "addr:street": "Oak St",
    "iso:country": "US",
    "ovtr:label": "Subway, 666 Oak St Brockton MA US",
    "ovtr:similarity": 3.155090093612671,
    "sg:address": "700 Oak St",
    "sg:city": "Brockton",
    "sg:classifiers": [
      {
        "category": "Restaurant",
        "type": "Food \u0026 Drink"
      }
    ],
    "sg:menulink": "http://www.allmenus.com/ma/brockton/131949-subway/menu/",
    "sg:phone": "+1 508 427 5464",
    "sg:postcode": "02301",
    "sg:province": "MA",
    "sg:tags": [
      "american",
      "sandwich"
    ],
    "wof:name": "Subway",
    "wof:placetype": "venue"
  },
  "geometry": {"coordinates":[-71.057652,42.101159],"type":"Point"}
}
