{
  "type": "Feature",
  "properties": {
    "addr:full": "278 Beacon St Boston MA 02116",
    "addr:housenumber": "278",
    "addr:postcode": "02116",
    "addr:street": "Beacon St",
    "iso:country": "US",
    "sg:address": "278 Beacon St",
    "sg:city": "Boston",
    "sg:classifiers": [
      {
        "category": "Building \u0026 Trades",
        "subcategory": "Locksmith",
        "type": "Services"
      }
    ],
    "sg:phone": "+1 617 303 2614",
    "sg:postcode": "02116",
    "sg:province": "MA",
    "sg:tags": [
      "key"
    ],
    "wof:name": "Your Local Locksmith",
    "wof:placetype": "venue"
  },
  "geometry": {"coordinates":[-71.081185,42.35321],"type":"Point"}
}
