{
  "type": "Feature",
  "properties": {
    "addr:full": "78 Donna Dr Hanson MA 02341",
    "addr:housenumber": "78",
    "addr:postcode": "02341",
    "addr:street": "Donna Dr",
    "iso:country": "US",
    "sg:address": "78 Donna Dr",
    "sg:city": "Hanson",
    "sg:classifiers": [
      {
        "category": "Freight",
        "type": "Transportation"
      }
    ],
    "sg:phone": "+1 781 767 5566",
    "sg:postcode": "02341",
    "sg:province": "MA",
    "sg:tags": [
      "trucking"
    ],
    "wof:name": "Coburn's Motor Express",
    "wof:placetype": "venue"
  },
  "geometry": {"coordinates":[-70.857442,42.045275],"type":"Point"}
}
