{
  "type": "Feature",
  "properties": {
    "iso:country":"US",
    "sg:address":"43 Deacon St",
    "sg:city":"Northborough",
    "sg:classifiers":[
        {
            "category":"Banks & Credit Unions",
            "subcategory":"Bank",
            "type":"Services"
        }
    ],
    "sg:phone":"+1 508 393 1263",
    "sg:postcode":"01532",
    "sg:province":"MA",
    "sg:tags":[
        "company",
        "trust"
    ],
    "wof:name":"Birchwood Condominium Trust",
    "wof:placetype":"venue"
},
  "geometry": {"coordinates":[-71.623931,42.33124],"type":"Point"}
}