{
  "type": "Feature",
  "properties": {
    "addr:full":"7 Wright Ave Medford MA 02155",
    "addr:housenumber":"7",
    "addr:postcode":"02155",
    "addr:street":"Wright Ave",
    "iso:country":"US",
    "sg:address":"7 Wright Ave",
    "sg:city":"Medford",
    "sg:classifiers":[
        {
            "category":"Building & Trades",
            "subcategory":"Construction",
            "type":"Services"
        }
    ],
    "sg:phone":"+1 781 395 3948",
    "sg:postcode":"02155",
    "sg:province":"MA",
    "sg:tags":[
        "industrial",
        "contractors-commercial",
        "contractor"
    ],
    "wof:name":"J P Pino General Contracting",
    "wof:placetype":"venue"
},
  "geometry": {"coordinates":[-71.10802700000001,42.40574],"type":"Point"}
}