{
  "type": "Feature",
  "properties": {
    "iso:country":"US",
    "sg:address":"270 Talbot Ave",
    "sg:city":"Dorchester Center",
    "sg:classifiers":[
        {
            "category":"Retail",
            "subcategory":"Auto Repair",
            "type":"Services"
        }
    ],
    "sg:phone":"+1 617 287 9443",
    "sg:postcode":"02124",
    "sg:province":"MA",
    "sg:tags":[
        "repairing",
        "automobile"
    ],
    "wof:name":"Roper's Auto Repair",
    "wof:placetype":"venue"
},
  "geometry": {"coordinates":[-71.07579800000001,42.291199],"type":"Point"}
}