{
  "type": "Feature",
  "properties": {
    "addr:full": "270 Talbot Ave Dorchester Center MA 02124",
    "addr:housenumber": "270",
    "addr:postcode": "02124",
    "addr:street": "Talbot Ave",
    "iso:country": "US",
    "sg:address": "270 Talbot Ave",
    "sg:city": "Dorchester Center",
    "sg:classifiers": [
      {
        "category": "Retail",
        "subcategory": "Auto Repair",
        "type": "Services"
      }
    ],
    "sg:phone": "+1 617 287 9443",
    "sg:postcode": "02124",
    "sg:province": "MA",
    "sg:tags": [
      "repairing",
      "automobile"
    ],
    "wof:name": "Roper's Auto Repair",
    "wof:placetype": "venue"
  },
  "geometry": {"coordinates":[-71.075798,42.291199],"type":"Point"}
}
