{
  "type": "Feature",
  "properties": {
    "addr:full": "259 Maple St Holyoke MA 01040",
    "addr:housenumber": "259",
    "addr:postcode": "01040",
    "addr:street": "Maple St",
    "iso:country": "US",
    "sg:address": "259 Maple St",
    "sg:city": "Holyoke",
    "sg:classifiers": [
      {
        "category": "Home \u0026 Garden",
        "subcategory": "Household Appliances",
        "type": "Retail Goods"
      }
    ],
    "sg:phone": "+1 413 532 9040",
    "sg:postcode": "01040",
    "sg:province": "MA",
    "wof:name": "Phil's Used Appliances \u0026 Furn",
    "wof:placetype": "venue"
  },
  "geometry": {"coordinates":[-72.608413,42.207553],"type":"Point"}
}
