{
  "type": "Feature",
  "properties": {
    "iso:country":"US",
    "sg:address":"23 Spring St",
    "sg:city":"West Roxbury",
    "sg:classifiers":[
        {
            "category":"Real Estate",
            "subcategory":"Real Estate Agent",
            "type":"Services"
        }
    ],
    "sg:phone":"+1 617 988 5116",
    "sg:postcode":"02132",
    "sg:province":"MA",
    "sg:tags":[
        "authorities",
        "housing"
    ],
    "wof:name":"Boston Housing Authority",
    "wof:placetype":"venue"
},
  "geometry": {"coordinates":[-71.16188699999999,42.27789],"type":"Point"}
}