{
  "type": "Feature",
  "properties": {
    "iso:country":"US",
    "sg:address":"1145 Main St",
    "sg:city":"Springfield",
    "sg:classifiers":[
        {
            "category":"Professional",
            "subcategory":"Lawyer & Legal Services",
            "type":"Services"
        }
    ],
    "sg:phone":"+1 413 731 7300",
    "sg:postcode":"01103",
    "sg:province":"MA",
    "sg:tags":[
        "attorney"
    ],
    "wof:name":"Stephen P Maidman",
    "wof:placetype":"venue"
},
  "geometry": {"coordinates":[-72.58617099999999,42.100437],"type":"Point"}
}