{
  "type": "Feature",
  "properties": {
    "addr:full": "11 Highwood Rd Manchester MA 01944",
    "addr:housenumber": "11",
    "addr:postcode": "01944",
    "addr:street": "Highwood Rd",
    "iso:country": "US",
    "sg:address": "11 Highwood Rd",
    "sg:city": "Manchester",
    "sg:classifiers": [
      {
        "category": "Professional",
        "subcategory": "Business Services",
        "type": "Services"
      }
    ],
    "sg:phone": "+1   ",
    "sg:postcode": "01944",
    "sg:province": "MA",
    "wof:name": "New England Power Technologies",
    "wof:placetype": "venue"
  },
  "geometry": {"coordinates":[-70.785446,42.578957],"type":"Point"}
}
