{
  "type": "Feature",
  "properties": {
    "addr:full":"55 W Prescott St Westford MA 01886",
    "addr:housenumber":"55",
    "addr:postcode":"01886",
    "addr:street":"W Prescott St",
    "iso:country":"US",
    "sg:address":"55 W Prescott St",
    "sg:city":"Westford",
    "sg:classifiers":[
        {
            "category":"Restaurant",
            "type":"Food & Drink"
        }
    ],
    "sg:phone":"+1 978 692 7013",
    "sg:postcode":"01886",
    "sg:province":"MA",
    "sg:tags":[
        "banquet",
        "rooms"
    ],
    "wof:name":"Franco American Club",
    "wof:placetype":"venue"
},
  "geometry": {"coordinates":[-71.48779399999999,42.580441],"type":"Point"}
}