{
  "type": "Feature",
  "properties": {
    "addr:full":"468 Canal St Lawrence MA 01840",
    "addr:housenumber":"468",
    "addr:postcode":"01840",
    "addr:street":"Canal St",
    "iso:country":"US",
    "sg:address":"468 Canal St",
    "sg:city":"Lawrence",
    "sg:classifiers":[
        {
            "category":"Home & Garden",
            "subcategory":"Furniture",
            "type":"Retail Goods"
        }
    ],
    "sg:phone":"+1 978 738 5063",
    "sg:postcode":"01840",
    "sg:province":"MA",
    "wof:name":"Kelly's Furniture",
    "wof:placetype":"venue"
},
  "geometry": {"coordinates":[-71.166624,42.703058],"type":"Point"}
}