{
  "type": "Feature",
  "properties": {
    "iso:country":"US",
    "sg:address":"20 Aegean Dr Ste 14",
    "sg:city":"Methuen",
    "sg:classifiers":[
        {
            "category":"Recreation",
            "subcategory":"Amusement Park",
            "type":"Entertainment"
        }
    ],
    "sg:phone":"+1 978 688 7576",
    "sg:postcode":"01844",
    "sg:province":"MA",
    "sg:tags":[
        "device"
    ],
    "wof:name":"Hot Shots Inc",
    "wof:placetype":"venue"
},
  "geometry": {"coordinates":[-71.21241999999999,42.72954],"type":"Point"}
}