{
  "type": "Feature",
  "properties": {
    "addr:full":"1734 Lakeview Ave Dracut MA 01826",
    "addr:housenumber":"1734",
    "addr:postcode":"01826",
    "addr:street":"Lakeview Ave",
    "iso:country":"US",
    "sg:address":"1734 Lakeview Ave",
    "sg:city":"Dracut",
    "sg:classifiers":[
        {
            "category":"Personal",
            "subcategory":"Beauty Salon",
            "type":"Services"
        }
    ],
    "sg:phone":"+1   ",
    "sg:postcode":"01826",
    "sg:province":"MA",
    "sg:tags":[
        "shop"
    ],
    "wof:name":"Threes Company",
    "wof:placetype":"venue"
},
  "geometry": {"coordinates":[-71.34269500000001,42.67962],"type":"Point"}
}