{
  "type": "Feature",
  "properties": {
    "iso:country":"US",
    "sg:address":"26 Middle Rd",
    "sg:city":"Newbury",
    "sg:classifiers":[
        {
            "category":"Retail",
            "subcategory":"Car Wash",
            "type":"Services"
        }
    ],
    "sg:phone":"+1 978 465 4640",
    "sg:postcode":"01951",
    "sg:province":"MA",
    "sg:tags":[
        "automobile",
        "detail",
        "clean"
    ],
    "wof:name":"Detailz Unlimited",
    "wof:placetype":"venue"
},
  "geometry": {"coordinates":[-70.883321,42.786602],"type":"Point"}
}