{
  "type": "Feature",
  "properties": {
    "addr:full": "798 Winter St East Bridgewater MA 02333",
    "addr:housenumber": "798",
    "addr:postcode": "02333",
    "addr:street": "Winter St",
    "iso:country": "US",
    "sg:address": "798 Winter St",
    "sg:city": "East Bridgewater",
    "sg:classifiers": [
      {
        "category": "Retail",
        "subcategory": "Laundry \u0026 Dry Cleaning",
        "type": "Services"
      }
    ],
    "sg:phone": "+1 508 427 6200",
    "sg:postcode": "02333",
    "sg:province": "MA",
    "sg:tags": [
      "cleaners",
      "rug",
      "carpet"
    ],
    "wof:name": "Hometown Carpet Cleaning Co",
    "wof:placetype": "venue"
  },
  "geometry": {"coordinates":[-70.963717,42.061831],"type":"Point"}
}
