{
  "type": "Feature",
  "properties": {
    "iso:country":"US",
    "sg:address":"73 River St",
    "sg:city":"Marlborough",
    "sg:classifiers":[
        {
            "category":"Home & Garden",
            "subcategory":"Building Materials",
            "type":"Retail Goods"
        }
    ],
    "sg:phone":"+1 508 485 8078",
    "sg:postcode":"01752",
    "sg:province":"MA",
    "sg:tags":[
        "concrete",
        "shape",
        "block"
    ],
    "wof:name":"Union Concrete Construction Corporation",
    "wof:placetype":"venue"
},
  "geometry": {"coordinates":[-71.54017399999999,42.333333],"type":"Point"}
}