{
  "type": "Feature",
  "properties": {
    "addr:full": "73 River St Marlborough MA 01752",
    "addr:housenumber": "73",
    "addr:postcode": "01752",
    "addr:street": "River St",
    "iso:country": "US",
    "sg:address": "73 River St",
    "sg:city": "Marlborough",
    "sg:classifiers": [
      {
        "category": "Home \u0026 Garden",
        "subcategory": "Building Materials",
        "type": "Retail Goods"
      }
    ],
    "sg:phone": "+1 508 485 8078",
    "sg:postcode": "01752",
    "sg:province": "MA",
    "sg:tags": [
      "concrete",
      "shape",
      "block"
    ],
    "wof:name": "Union Concrete Construction Corporation",
    "wof:placetype": "venue"
  },
  "geometry": {"coordinates":[-71.540174,42.333333],"type":"Point"}
}
