{
  "type": "Feature",
  "properties": {
    "iso:country":"US",
    "sg:address":"31 Melvin Rd",
    "sg:city":"Arlington",
    "sg:classifiers":[
        {
            "category":"Building & Trades",
            "subcategory":"Plumbing",
            "type":"Services"
        }
    ],
    "sg:phone":"+1   ",
    "sg:postcode":"02474",
    "sg:province":"MA",
    "sg:tags":[
        "engineering",
        "contractor"
    ],
    "wof:name":"System Engineering and Dev",
    "wof:placetype":"venue"
},
  "geometry": {"coordinates":[-71.161573,42.43009],"type":"Point"}
}