{
  "type": "Feature",
  "properties": {
    "addr:full": "31 Melvin Rd Arlington MA 02474",
    "addr:housenumber": "31",
    "addr:postcode": "02474",
    "addr:street": "Melvin Rd",
    "iso:country": "US",
    "sg:address": "31 Melvin Rd",
    "sg:city": "Arlington",
    "sg:classifiers": [
      {
        "category": "Building \u0026 Trades",
        "subcategory": "Plumbing",
        "type": "Services"
      }
    ],
    "sg:phone": "+1   ",
    "sg:postcode": "02474",
    "sg:province": "MA",
    "sg:tags": [
      "engineering",
      "contractor"
    ],
    "wof:name": "System Engineering and Dev",
    "wof:placetype": "venue"
  },
  "geometry": {"coordinates":[-71.161573,42.43009],"type":"Point"}
}
