{
  "type": "Feature",
  "properties": {
    "addr:full":"575 South St W Raynham MA 02767",
    "addr:housenumber":"575",
    "addr:postcode":"02767",
    "addr:street":"South St W",
    "iso:country":"US",
    "sg:address":"575 South St W",
    "sg:city":"Raynham",
    "sg:classifiers":[
        {
            "category":"Home & Garden",
            "subcategory":"Household Appliances",
            "type":"Retail Goods"
        }
    ],
    "sg:phone":"+1 508 824 7755",
    "sg:postcode":"02767",
    "sg:province":"MA",
    "sg:tags":[
        "machine",
        "sewing"
    ],
    "wof:name":"Able Sewing Machine & Vac Sls",
    "wof:placetype":"venue"
},
  "geometry": {"coordinates":[-71.044971,41.903183],"type":"Point"}
}