{
  "type": "Feature",
  "properties": {
    "addr:full": "101 University Dr Amherst MA 01002",
    "addr:housenumber": "101",
    "addr:postcode": "01002",
    "addr:street": "University Dr",
    "iso:country": "US",
    "sg:address": "101 University Dr",
    "sg:city": "Amherst",
    "sg:classifiers": [
      {
        "category": "Manufacturing",
        "subcategory": "Printing",
        "type": "Manufacturing \u0026 Wholesale Goods"
      }
    ],
    "sg:phone": "+1   ",
    "sg:postcode": "01002",
    "sg:province": "MA",
    "sg:tags": [
      "commercial",
      "lithographic"
    ],
    "wof:name": "Marcus Company Inc",
    "wof:placetype": "venue"
  },
  "geometry": {"coordinates":[-72.532031,42.378867],"type":"Point"}
}
