{
  "type": "Feature",
  "properties": {
    "iso:country":"US",
    "sg:address":"101 University Dr",
    "sg:city":"Amherst",
    "sg:classifiers":[
        {
            "category":"Manufacturing",
            "subcategory":"Printing",
            "type":"Manufacturing & Wholesale Goods"
        }
    ],
    "sg:phone":"+1   ",
    "sg:postcode":"01002",
    "sg:province":"MA",
    "sg:tags":[
        "commercial",
        "lithographic"
    ],
    "wof:name":"Marcus Company Inc",
    "wof:placetype":"venue"
},
  "geometry": {"coordinates":[-72.532031,42.378867],"type":"Point"}
}