{
  "type": "Feature",
  "properties": {
    "addr:full":"154 N Dartmouth Mall North Dartmouth MA 02747",
    "addr:housenumber":"154",
    "addr:postcode":"02747",
    "addr:street":"N Dartmouth Mall",
    "iso:country":"US",
    "sg:address":"154 N Dartmouth Mall",
    "sg:city":"North Dartmouth",
    "sg:classifiers":[
        {
            "category":"Home & Garden",
            "subcategory":"Home Furnishings",
            "type":"Retail Goods"
        }
    ],
    "sg:phone":"+1 508 995 3299",
    "sg:postcode":"02747",
    "sg:province":"MA",
    "sg:tags":[
        "venetian",
        "blind"
    ],
    "wof:name":"Blinds & Designs",
    "wof:placetype":"venue"
},
  "geometry": {"coordinates":[-70.99213,41.642642],"type":"Point"}
}