{
  "type": "Feature",
  "properties": {
    "addr:full": "54 Bolton St Exd Marlborough MA 01752",
    "addr:housenumber": "54",
    "addr:postcode": "01752",
    "addr:street": "Bolton St Exd",
    "iso:country": "US",
    "sg:address": "54 Bolton St Exd",
    "sg:city": "Marlborough",
    "sg:classifiers": [
      {
        "category": "Shopping",
        "type": "Retail Goods"
      }
    ],
    "sg:phone": "+1 508 460 9006",
    "sg:postcode": "01752",
    "sg:province": "MA",
    "sg:tags": [
      "factory",
      "outlet"
    ],
    "wof:name": "Reebok-Rockport Factory Direct",
    "wof:placetype": "venue"
  },
  "geometry": {"coordinates":[-71.546099,42.346181],"type":"Point"}
}
