{
  "type": "Feature",
  "properties": {
    "addr:full": "120 Lincoln St Boston MA 02111",
    "addr:housenumber": "120",
    "addr:postcode": "02111",
    "addr:street": "Lincoln St",
    "iso:country": "US",
    "sg:address": "120 Lincoln St",
    "sg:city": "Boston",
    "sg:classifiers": [
      {
        "category": "Health Services",
        "subcategory": "Doctor",
        "type": "Services"
      }
    ],
    "sg:phone": "+1 617 451 2111",
    "sg:postcode": "02111",
    "sg:province": "MA",
    "sg:tags": [
      "surgeon",
      "oral"
    ],
    "wof:name": "Boston Oral \u0026 Facial Surgery",
    "wof:placetype": "venue"
  },
  "geometry": {"coordinates":[-71.05815,42.351363],"type":"Point"}
}
