{
  "type": "Feature",
  "properties": {
    "iso:country":"US",
    "sg:address":"120 Lincoln St",
    "sg:city":"Boston",
    "sg:classifiers":[
        {
            "category":"Health Services",
            "subcategory":"Doctor",
            "type":"Services"
        }
    ],
    "sg:phone":"+1 617 451 2111",
    "sg:postcode":"02111",
    "sg:province":"MA",
    "sg:tags":[
        "surgeon",
        "oral"
    ],
    "wof:name":"Boston Oral & Facial Surgery",
    "wof:placetype":"venue"
},
  "geometry": {"coordinates":[-71.05815,42.351363],"type":"Point"}
}