{
  "type": "Feature",
  "properties": {
    "iso:country":"US",
    "sg:address":"11 Waltham Street",
    "sg:city":"Lexington",
    "sg:classifiers":[
        {
            "category":"Personal",
            "subcategory":"Beauty Salon",
            "type":"Services"
        }
    ],
    "sg:phone":"+1 781 862 2277",
    "sg:postcode":"02421",
    "sg:province":"MA",
    "sg:tags":[
        "hair"
    ],
    "wof:name":"Copoli Salon",
    "wof:placetype":"venue"
},
  "geometry": {"coordinates":[-71.22732999999999,42.447186],"type":"Point"}
}