{
  "type": "Feature",
  "properties": {
    "addr:full": "11 Waltham Street Lexington MA 02421",
    "addr:housenumber": "11",
    "addr:postcode": "02421",
    "addr:street": "Waltham Street",
    "iso:country": "US",
    "ovtr:label": "Copoli Salon, 11 Waltham St Lexington MA US",
    "ovtr:similarity": 2.6674280166625977,
    "sg:address": "11 Waltham Street",
    "sg:city": "Lexington",
    "sg:classifiers": [
      {
        "category": "Personal",
        "subcategory": "Beauty Salon",
        "type": "Services"
      }
    ],
    "sg:phone": "+1 781 862 2277",
    "sg:postcode": "02421",
    "sg:province": "MA",
    "sg:tags": [
      "hair"
    ],
    "wof:name": "Copoli Salon",
    "wof:placetype": "venue"
  },
  "geometry": {"coordinates":[-71.22733,42.447186],"type":"Point"}
}
