{
  "type": "Feature",
  "properties": {
    "addr:full": "14 Park Ave Arlington MA 02474",
    "addr:housenumber": "14",
    "addr:postcode": "02474",
    "addr:street": "Park Ave",
    "iso:country": "US",
    "sg:address": "14 Park Ave",
    "sg:city": "Arlington",
    "sg:classifiers": [
      {
        "category": "Food \u0026 Beverages",
        "subcategory": "Specialty",
        "type": "Retail Goods"
      }
    ],
    "sg:phone": "+1 781 643 6600",
    "sg:postcode": "02474",
    "sg:province": "MA",
    "sg:tags": [
      "vitamin"
    ],
    "wof:name": "Arlington Health Foods",
    "wof:placetype": "venue"
  },
  "geometry": {"coordinates":[-71.181851,42.426055],"type":"Point"}
}
