{
  "type": "Feature",
  "properties": {
    "iso:country":"US",
    "sg:address":"10 Crow Ln",
    "sg:city":"Newburyport",
    "sg:classifiers":[
        {
            "category":"Freight",
            "type":"Transportation"
        }
    ],
    "sg:phone":"+1 978 463 4300",
    "sg:postcode":"01950",
    "sg:province":"MA",
    "sg:tags":[
        "commercial",
        "storage"
    ],
    "wof:name":"Crow Lane Storage",
    "wof:placetype":"venue"
},
  "geometry": {"coordinates":[-70.89788900000001,42.815705],"type":"Point"}
}