{
  "type": "Feature",
  "properties": {
    "addr:full":"65 Winston Rd Dorchester Center MA 02124",
    "addr:housenumber":"65",
    "addr:postcode":"02124",
    "addr:street":"Winston Rd",
    "iso:country":"US",
    "sg:address":"65 Winston Rd",
    "sg:city":"Dorchester Center",
    "sg:classifiers":[
        {
            "category":"Real Estate",
            "subcategory":"Real Estate Agent",
            "type":"Services"
        }
    ],
    "sg:phone":"+1 617 288 7857",
    "sg:postcode":"02124",
    "sg:province":"MA",
    "sg:tags":[
        "management",
        "property"
    ],
    "wof:name":"Lucerne Gardens",
    "wof:placetype":"venue"
},
  "geometry": {"coordinates":[-71.088898,42.2845],"type":"Point"}
}