{
  "type": "Feature",
  "properties": {
    "addr:full": "34 McNamara St Stoughton MA 02072",
    "addr:housenumber": "34",
    "addr:postcode": "02072",
    "addr:street": "Mcnamara St",
    "iso:country": "US",
    "sg:address": "34 McNamara St",
    "sg:city": "Stoughton",
    "sg:classifiers": [
      {
        "category": "Professional",
        "subcategory": "Management \u0026 Consulting",
        "type": "Services"
      }
    ],
    "sg:phone": "+1   ",
    "sg:postcode": "02072",
    "sg:province": "MA",
    "wof:name": "P W Resources Inc",
    "wof:placetype": "venue"
  },
  "geometry": {"coordinates":[-71.11608,42.11743],"type":"Point"}
}
