{
  "type": "Feature",
  "properties": {
    "iso:country":"US",
    "sg:address":"18 Searls St",
    "sg:city":"Easthampton",
    "sg:classifiers":[
        {
            "category":"Retail",
            "subcategory":"Animal Services",
            "type":"Services"
        }
    ],
    "sg:phone":"+1   ",
    "sg:postcode":"01027",
    "sg:province":"MA",
    "wof:name":"All About Dogs Training Center",
    "wof:placetype":"venue"
},
  "geometry": {"coordinates":[-72.685406,42.274032],"type":"Point"}
}