{
  "type": "Feature",
  "properties": {
    "iso:country":"US",
    "sg:address":"34 E Main St",
    "sg:city":"Webster",
    "sg:classifiers":[
        {
            "category":"Building & Trades",
            "subcategory":"Construction",
            "type":"Services"
        }
    ],
    "sg:phone":"+1   ",
    "sg:postcode":"01570",
    "sg:province":"MA",
    "sg:tags":[
        "floor",
        "laying",
        "contractor"
    ],
    "wof:name":"Cournoyer Floor Sanding",
    "wof:placetype":"venue"
},
  "geometry": {"coordinates":[-71.87457499999999,42.05551],"type":"Point"}
}