{
  "type": "Feature",
  "properties": {
    "iso:country":"US",
    "sg:address":"2 Copley Place",
    "sg:city":"Boston",
    "sg:classifiers":[
        {
            "category":"Building & Trades",
            "subcategory":"Cleaning & Sanitation",
            "type":"Services"
        }
    ],
    "sg:phone":"+1 617 580 3189",
    "sg:postcode":"02116",
    "sg:province":"MA",
    "sg:tags":[
        "duct",
        "vent",
        "dryer"
    ],
    "sg:website":"http://MA.Boston.dryerventcleaning2u.com/index.html",
    "wof:name":"Dryer Vent Cleaning Boston",
    "wof:placetype":"venue"
},
  "geometry": {"coordinates":[-71.077568,42.34811],"type":"Point"}
}