{
  "type": "Feature",
  "properties": {
    "iso:country":"US",
    "sg:address":"2 Seaport Ln",
    "sg:city":"Boston",
    "sg:classifiers":[
        {
            "category":"Professional",
            "subcategory":"Lawyer & Legal Services",
            "type":"Services"
        }
    ],
    "sg:phone":"+1 617 946 4800",
    "sg:postcode":"02210",
    "sg:province":"MA",
    "wof:name":"Quill John Atty",
    "wof:placetype":"venue"
},
  "geometry": {"coordinates":[-71.041496,42.348598],"type":"Point"}
}