{
  "type": "Feature",
  "properties": {
    "iso:country":"US",
    "sg:address":"255 Park Ave",
    "sg:city":"Worcester",
    "sg:classifiers":[
        {
            "category":"Professional",
            "subcategory":"Management & Consulting",
            "type":"Services"
        }
    ],
    "sg:phone":"+1 508 791 1701",
    "sg:postcode":"01609",
    "sg:province":"MA",
    "sg:tags":[
        "consultant",
        "business"
    ],
    "wof:name":"Quinlivan Benefit Consultants",
    "wof:placetype":"venue"
},
  "geometry": {"coordinates":[-71.81870000000001,42.265516],"type":"Point"}
}