{
  "type": "Feature",
  "properties": {
    "iso:country":"US",
    "sg:address":"10 Independence Ln",
    "sg:city":"Millis",
    "sg:classifiers":[
        {
            "category":"Building & Trades",
            "subcategory":"Landscaping Services",
            "type":"Services"
        }
    ],
    "sg:phone":"+1   ",
    "sg:postcode":"02054",
    "sg:province":"MA",
    "wof:name":"Harrington Tree Service",
    "wof:placetype":"venue"
},
  "geometry": {"coordinates":[-71.375489,42.14249],"type":"Point"}
}