{
  "type": "Feature",
  "properties": {
    "addr:full": "1054 Main St Brockton MA 02301",
    "addr:housenumber": "1054",
    "addr:postcode": "02301",
    "addr:street": "Main St",
    "iso:country": "US",
    "sg:address": "1054 Main St",
    "sg:city": "Brockton",
    "sg:classifiers": [
      {
        "category": "Retail",
        "subcategory": "Laundry \u0026 Dry Cleaning",
        "type": "Services"
      }
    ],
    "sg:phone": "+1 508 583 7181",
    "sg:postcode": "02301",
    "sg:province": "MA",
    "wof:name": "Laundry Masters",
    "wof:placetype": "venue"
  },
  "geometry": {"coordinates":[-71.015911,42.064806],"type":"Point"}
}
