{
  "type": "Feature",
  "properties": {
    "iso:country":"US",
    "sg:address":"1054 Main St",
    "sg:city":"Brockton",
    "sg:classifiers":[
        {
            "category":"Retail",
            "subcategory":"Laundry & Dry Cleaning",
            "type":"Services"
        }
    ],
    "sg:phone":"+1 508 583 7181",
    "sg:postcode":"02301",
    "sg:province":"MA",
    "wof:name":"Laundry Masters",
    "wof:placetype":"venue"
},
  "geometry": {"coordinates":[-71.015911,42.064806],"type":"Point"}
}