{
  "type": "Feature",
  "properties": {
    "addr:full":"7 Sandwich Rd Plymouth MA 02360",
    "addr:housenumber":"7",
    "addr:postcode":"02360",
    "addr:street":"Sandwich Rd",
    "iso:country":"US",
    "sg:address":"7 Sandwich Rd",
    "sg:city":"Plymouth",
    "sg:classifiers":[
        {
            "category":"Professional",
            "type":"Services"
        }
    ],
    "sg:phone":"+1   ",
    "sg:postcode":"02360",
    "sg:province":"MA",
    "sg:tags":[
        "studio",
        "artist"
    ],
    "wof:name":"Naomi Just Artist",
    "wof:placetype":"venue"
},
  "geometry": {"coordinates":[-70.62969099999999,41.935414],"type":"Point"}
}