{
  "type": "Feature",
  "properties": {
    "addr:full": "34 Old Stage Rd Montague MA 01351",
    "addr:housenumber": "34",
    "addr:postcode": "01351",
    "addr:street": "Old Stage Rd",
    "iso:country": "US",
    "sg:address": "34 Old Stage Rd",
    "sg:city": "Montague",
    "sg:classifiers": [
      {
        "category": "Social Services",
        "type": "Services"
      }
    ],
    "sg:phone": "+1   ",
    "sg:postcode": "01351",
    "sg:province": "MA",
    "wof:name": "U IL Liaison Service",
    "wof:placetype": "venue"
  },
  "geometry": {"coordinates":[-72.535043,42.522583],"type":"Point"}
}
