{
  "type": "Feature",
  "properties": {
    "addr:full": "55 I St South Boston MA 02127",
    "addr:housenumber": "55",
    "addr:postcode": "02127",
    "addr:street": "I St",
    "iso:country": "US",
    "sg:address": "55 I St",
    "sg:city": "South Boston",
    "sg:classifiers": [
      {
        "category": "Professional",
        "type": "Services"
      }
    ],
    "sg:phone": "+1 617 268 7423",
    "sg:postcode": "02127",
    "sg:province": "MA",
    "sg:tags": [
      "establishment"
    ],
    "wof:name": "Fifty Five I Street",
    "wof:placetype": "venue"
  },
  "geometry": {"coordinates":[-71.040031,42.335922],"type":"Point"}
}
