{
  "type": "Feature",
  "properties": {
    "addr:full":"32 Dix Rd Maynard MA 01754",
    "addr:housenumber":"32",
    "addr:postcode":"01754",
    "addr:street":"Dix Rd",
    "iso:country":"US",
    "sg:address":"32 Dix Rd",
    "sg:city":"Maynard",
    "sg:classifiers":[
        {
            "category":"Wholesale",
            "subcategory":"Electrical",
            "type":"Manufacturing & Wholesale Goods"
        }
    ],
    "sg:phone":"+1 978 461 0091",
    "sg:postcode":"01754",
    "sg:province":"MA",
    "sg:tags":[
        "alarm",
        "burglar",
        "system"
    ],
    "wof:name":"Alarm Contracting",
    "wof:placetype":"venue"
},
  "geometry": {"coordinates":[-71.465701,42.441264],"type":"Point"}
}