{
  "type": "Feature",
  "properties": {
    "iso:country":"US",
    "sg:address":"435 Newbury St",
    "sg:city":"Danvers",
    "sg:classifiers":[
        {
            "category":"Professional",
            "subcategory":"Lawyer & Legal Services",
            "type":"Services"
        }
    ],
    "sg:phone":"+1 978 739 8484",
    "sg:postcode":"01923",
    "sg:province":"MA",
    "sg:tags":[
        "attorney"
    ],
    "wof:name":"Mc Cann & Mc Cann",
    "wof:placetype":"venue"
},
  "geometry": {"coordinates":[-70.96050700000001,42.598532],"type":"Point"}
}