{
  "type": "Feature",
  "properties": {
    "addr:full": "435 Newbury St Danvers MA 01923",
    "addr:housenumber": "435",
    "addr:postcode": "01923",
    "addr:street": "Newbury St",
    "iso:country": "US",
    "sg:address": "435 Newbury St",
    "sg:city": "Danvers",
    "sg:classifiers": [
      {
        "category": "Professional",
        "subcategory": "Lawyer \u0026 Legal Services",
        "type": "Services"
      }
    ],
    "sg:phone": "+1 978 739 8484",
    "sg:postcode": "01923",
    "sg:province": "MA",
    "sg:tags": [
      "attorney"
    ],
    "wof:name": "Mc Cann \u0026 Mc Cann",
    "wof:placetype": "venue"
  },
  "geometry": {"coordinates":[-70.960507,42.598532],"type":"Point"}
}
