{
  "type": "Feature",
  "properties": {
    "iso:country":"US",
    "sg:address":"1 International Place",
    "sg:city":"Boston",
    "sg:classifiers":[
        {
            "category":"Professional",
            "subcategory":"Lawyer & Legal Services",
            "type":"Services"
        }
    ],
    "sg:phone":"+1 617 598 3120",
    "sg:postcode":"02110",
    "sg:province":"MA",
    "wof:name":"Fitzpatrick Anthony J Atty",
    "wof:placetype":"venue"
},
  "geometry": {"coordinates":[-71.05258000000001,42.35628],"type":"Point"}
}