{
  "type": "Feature",
  "properties": {
    "addr:full":"25 Prescott St Woburn MA 01801",
    "addr:housenumber":"25",
    "addr:postcode":"01801",
    "addr:street":"Prescott St",
    "iso:country":"US",
    "sg:address":"25 Prescott St",
    "sg:city":"Woburn",
    "sg:classifiers":[
        {
            "category":"Banks & Credit Unions",
            "subcategory":"Investment Brokerage",
            "type":"Services"
        }
    ],
    "sg:phone":"+1 781 938 9383",
    "sg:postcode":"01801",
    "sg:province":"MA",
    "sg:tags":[
        "consultant",
        "planning",
        "financial"
    ],
    "wof:name":"Financial Planning Solutions",
    "wof:placetype":"venue"
},
  "geometry": {"coordinates":[-71.15574100000001,42.513721],"type":"Point"}
}