{
  "type": "Feature",
  "properties": {
    "addr:full": "171 Associates Rd Falmouth MA 02540",
    "addr:housenumber": "171",
    "addr:postcode": "02540",
    "addr:street": "Associates Rd",
    "iso:country": "US",
    "sg:address": "171 Associates Rd",
    "sg:city": "Falmouth",
    "sg:classifiers": [
      {
        "category": "Recreation",
        "subcategory": "Marina",
        "type": "Entertainment"
      }
    ],
    "sg:phone": "+1 508 548 0681",
    "sg:postcode": "02540",
    "sg:province": "MA",
    "sg:tags": [
      "club",
      "boat"
    ],
    "wof:name": "Chapoquiot Yacht Club",
    "wof:placetype": "venue"
  },
  "geometry": {"coordinates":[-70.647988,41.602923],"type":"Point"}
}
