{
  "type": "Feature",
  "properties": {
    "addr:full":"13 Emerson Ave Brockton MA 02301",
    "addr:housenumber":"13",
    "addr:postcode":"02301",
    "addr:street":"Emerson Ave",
    "iso:country":"US",
    "sg:address":"13 Emerson Ave",
    "sg:city":"Brockton",
    "sg:classifiers":[
        {
            "category":"Wholesale",
            "subcategory":"Machinery & Supplies",
            "type":"Manufacturing & Wholesale Goods"
        }
    ],
    "sg:phone":"+1 508 580 2658",
    "sg:postcode":"02301",
    "sg:province":"MA",
    "sg:tags":[
        "shoe",
        "findings"
    ],
    "wof:name":"Colt Heel",
    "wof:placetype":"venue"
},
  "geometry": {"coordinates":[-71.022594,42.103598],"type":"Point"}
}