{
  "type": "Feature",
  "properties": {
    "addr:full":"10 Magazine St Cambridge MA 02139",
    "addr:housenumber":"10",
    "addr:postcode":"02139",
    "addr:street":"Magazine St",
    "iso:country":"US",
    "sg:address":"10 Magazine St",
    "sg:city":"Cambridge",
    "sg:classifiers":[
        {
            "category":"Real Estate",
            "subcategory":"Real Estate Agent",
            "type":"Services"
        }
    ],
    "sg:phone":"+1 617 547 8700",
    "sg:postcode":"02139",
    "sg:province":"MA",
    "sg:website":"www.skylinerealty.com",
    "wof:name":"Skyline Realty",
    "wof:placetype":"venue"
},
  "geometry": {"coordinates":[-71.10471699999999,42.364601],"type":"Point"}
}