{
  "type": "Feature",
  "properties": {
    "addr:full":"60 Canal Street Boston MA 02114",
    "addr:housenumber":"60",
    "addr:postcode":"02114",
    "addr:street":"Canal Street",
    "iso:country":"US",
    "sg:address":"60 Canal Street",
    "sg:city":"Boston",
    "sg:classifiers":[
        {
            "category":"Professional",
            "type":"Services"
        }
    ],
    "sg:phone":"+1 617 557 0066",
    "sg:postcode":"02114",
    "sg:province":"MA",
    "wof:name":"Insight Direct",
    "wof:placetype":"venue"
},
  "geometry": {"coordinates":[-71.05943600000001,42.363774],"type":"Point"}
}