{
  "type": "Feature",
  "properties": {
    "addr:full":"17 Centennial Dr Peabody MA 01960",
    "addr:housenumber":"17",
    "addr:postcode":"01960",
    "addr:street":"Centennial Dr",
    "iso:country":"US",
    "sg:address":"17 Centennial Dr",
    "sg:city":"Peabody",
    "sg:classifiers":[
        {
            "category":"Health Services",
            "subcategory":"Doctor",
            "type":"Services"
        }
    ],
    "sg:phone":"+1 978 977 3434",
    "sg:postcode":"01960",
    "sg:province":"MA",
    "sg:tags":[
        "physician",
        "surgeon"
    ],
    "wof:name":"North Shore Cancer Ctr",
    "wof:placetype":"venue"
},
  "geometry": {"coordinates":[-70.96917500000001,42.521941],"type":"Point"}
}