{
  "type": "Feature",
  "properties": {
    "iso:country":"US",
    "sg:address":"Copley Mall 100 Huntington Avenue",
    "sg:city":"Boston",
    "sg:classifiers":[
        {
            "category":"Shopping",
            "subcategory":"Shoes",
            "type":"Retail Goods"
        }
    ],
    "sg:phone":"+1 617 266 1202",
    "sg:postcode":"02116",
    "sg:province":"MA",
    "sg:tags":[
        "store"
    ],
    "sg:website":"www.bandolino.com",
    "wof:name":"Bandolino",
    "wof:placetype":"venue"
},
  "geometry": {"coordinates":[-71.0774,42.348099],"type":"Point"}
}