{
  "type": "Feature",
  "properties": {
    "iso:country":"US",
    "sg:address":"107 Flanders Rd",
    "sg:city":"Westborough",
    "sg:classifiers":[
        {
            "category":"Building & Trades",
            "subcategory":"Construction",
            "type":"Services"
        }
    ],
    "sg:phone":"+1 508 366 9006",
    "sg:postcode":"01581",
    "sg:province":"MA",
    "sg:tags":[
        "designer",
        "dealer",
        "pool",
        "swimming"
    ],
    "sg:website":"www.aquascapepooldesigns.com",
    "wof:name":"Aquascape Pool Design Inc",
    "wof:placetype":"venue"
},
  "geometry": {"coordinates":[-71.578176,42.275731],"type":"Point"}
}