{
  "type": "Feature",
  "properties": {
    "addr:full": "11 W Knoll Rd Andover MA 01810",
    "addr:housenumber": "11",
    "addr:postcode": "01810",
    "addr:street": "W Knoll Rd",
    "iso:country": "US",
    "sg:address": "11 W Knoll Rd",
    "sg:city": "Andover",
    "sg:classifiers": [
      {
        "category": "Manufacturing",
        "subcategory": "Paper Products",
        "type": "Manufacturing \u0026 Wholesale Goods"
      }
    ],
    "sg:phone": "+1 978 474 5018",
    "sg:postcode": "01810",
    "sg:province": "MA",
    "sg:tags": [
      "bag"
    ],
    "wof:name": "Pakpro Inc",
    "wof:placetype": "venue"
  },
  "geometry": {"coordinates":[-71.12546,42.633667],"type":"Point"}
}
