{
  "type": "Feature",
  "properties": {
    "iso:country":"US",
    "sg:address":"11 W Knoll Rd",
    "sg:city":"Andover",
    "sg:classifiers":[
        {
            "category":"Manufacturing",
            "subcategory":"Paper Products",
            "type":"Manufacturing & Wholesale Goods"
        }
    ],
    "sg:phone":"+1 978 474 5018",
    "sg:postcode":"01810",
    "sg:province":"MA",
    "sg:tags":[
        "bag"
    ],
    "wof:name":"Pakpro Inc",
    "wof:placetype":"venue"
},
  "geometry": {"coordinates":[-71.12546,42.633667],"type":"Point"}
}