{
  "type": "Feature",
  "properties": {
    "addr:full":"20 Edith Rd Weymouth MA 02189",
    "addr:housenumber":"20",
    "addr:postcode":"02189",
    "addr:street":"Edith Rd",
    "iso:country":"US",
    "sg:address":"20 Edith Rd",
    "sg:city":"Weymouth",
    "sg:classifiers":[
        {
            "category":"Freight",
            "type":"Transportation"
        }
    ],
    "sg:phone":"+1 781 340 5222",
    "sg:postcode":"02189",
    "sg:province":"MA",
    "sg:tags":[
        "trucking"
    ],
    "wof:name":"Metropolitan Trucking Co",
    "wof:placetype":"venue"
},
  "geometry": {"coordinates":[-70.93220700000001,42.229857],"type":"Point"}
}