{
  "type": "Feature",
  "properties": {
    "addr:full":"284 Bunker Hill St Charlestown MA 02129",
    "addr:housenumber":"284",
    "addr:postcode":"02129",
    "addr:street":"Bunker Hill St",
    "iso:country":"US",
    "sg:address":"284 Bunker Hill St",
    "sg:city":"Charlestown",
    "sg:classifiers":[
        {
            "category":"Professional",
            "type":"Services"
        }
    ],
    "sg:phone":"+1 617 242 7280",
    "sg:postcode":"02129",
    "sg:province":"MA",
    "sg:tags":[
        "establishment"
    ],
    "wof:name":"Isocor Inc",
    "wof:placetype":"venue"
},
  "geometry": {"coordinates":[-71.06575599999999,42.380394],"type":"Point"}
}