{
  "type": "Feature",
  "properties": {
    "addr:full":"185 Simonds St Athol MA 01331",
    "addr:housenumber":"185",
    "addr:postcode":"01331",
    "addr:street":"Simonds St",
    "iso:country":"US",
    "sg:address":"185 Simonds St",
    "sg:city":"Athol",
    "sg:classifiers":[
        {
            "category":"Professional",
            "subcategory":"Art Services",
            "type":"Services"
        }
    ],
    "sg:phone":"+1   ",
    "sg:postcode":"01331",
    "sg:province":"MA",
    "sg:tags":[
        "graphic",
        "design"
    ],
    "wof:name":"Enders Graphic Design",
    "wof:placetype":"venue"
},
  "geometry": {"coordinates":[-72.21548799999999,42.582271],"type":"Point"}
}