{
  "type": "Feature",
  "properties": {
    "addr:full": "200 Portland St Boston MA 02114",
    "addr:housenumber": "200",
    "addr:postcode": "02114",
    "addr:street": "Portland St",
    "iso:country": "US",
    "sg:address": "200 Portland St",
    "sg:city": "Boston",
    "sg:classifiers": [
      {
        "category": "Banks \u0026 Credit Unions",
        "subcategory": "Financial Services",
        "type": "Services"
      },
      {
        "category": "Banks \u0026 Credit Unions",
        "subcategory": "Bank",
        "type": "Services"
      },
      {
        "category": "Banks \u0026 Credit Unions",
        "subcategory": "Atm",
        "type": "Services"
      }
    ],
    "sg:phone": "+1 800 432 1000",
    "sg:postcode": "02114",
    "sg:province": "MA",
    "sg:tags": [
      "saving",
      "commercial",
      "location"
    ],
    "sg:website": "http://locators.bankofamerica.com/a/BC-14316",
    "wof:name": "Bank of America ATM",
    "wof:placetype": "venue"
  },
  "geometry": {"coordinates":[-71.061528,42.364155],"type":"Point"}
}
