{
  "type": "Feature",
  "properties": {
    "iso:country":"US",
    "sg:address":"134 Boston St",
    "sg:city":"Salem",
    "sg:classifiers":[
        {
            "category":"Shopping",
            "subcategory":"Clothing, Apparel, & Fashions",
            "type":"Retail Goods"
        }
    ],
    "sg:phone":"+1 978 745 7303",
    "sg:postcode":"01970",
    "sg:province":"MA",
    "wof:name":"Boston Street Children's",
    "wof:placetype":"venue"
},
  "geometry": {"coordinates":[-70.911858,42.520472],"type":"Point"}
}