{
  "type": "Feature",
  "properties": {
    "addr:full": "134 Boston St Salem MA 01970",
    "addr:housenumber": "134",
    "addr:postcode": "01970",
    "addr:street": "Boston St",
    "iso:country": "US",
    "ovtr:label": "Boston Street Children's, 134 Boston St Salem MA US",
    "ovtr:similarity": 2.849745988845825,
    "sg:address": "134 Boston St",
    "sg:city": "Salem",
    "sg:classifiers": [
      {
        "category": "Shopping",
        "subcategory": "Clothing, Apparel, \u0026 Fashions",
        "type": "Retail Goods"
      }
    ],
    "sg:phone": "+1 978 745 7303",
    "sg:postcode": "01970",
    "sg:province": "MA",
    "wof:name": "Boston Street Children's",
    "wof:placetype": "venue"
  },
  "geometry": {"coordinates":[-70.911858,42.520472],"type":"Point"}
}
