{
  "type": "Feature",
  "properties": {
    "addr:full": "712 Summer St Arlington MA 02474",
    "addr:housenumber": "712",
    "addr:postcode": "02474",
    "addr:street": "Summer St",
    "iso:country": "US",
    "sg:address": "712 Summer St",
    "sg:city": "Arlington",
    "sg:classifiers": [
      {
        "category": "Retail",
        "subcategory": "Auto Repair",
        "type": "Services"
      }
    ],
    "sg:phone": "+1 781 646 1990",
    "sg:postcode": "02474",
    "sg:province": "MA",
    "sg:tags": [
      "body",
      "automobile",
      "painting"
    ],
    "wof:name": "Palmer's Auto Body",
    "wof:placetype": "venue"
  },
  "geometry": {"coordinates":[-71.183826,42.432524],"type":"Point"}
}
