{
  "type": "Feature",
  "properties": {
    "addr:full": "105 Weaver St Fall River MA 02720",
    "addr:housenumber": "105",
    "addr:postcode": "02720",
    "addr:street": "Weaver St",
    "iso:country": "US",
    "sg:address": "105 Weaver St",
    "sg:city": "Fall River",
    "sg:classifiers": [
      {
        "category": "Freight",
        "type": "Transportation"
      }
    ],
    "sg:phone": "+1 508 672 4424",
    "sg:postcode": "02720",
    "sg:province": "MA",
    "sg:tags": [
      "mover"
    ],
    "wof:name": "Bristol Plymouth Moving",
    "wof:placetype": "venue"
  },
  "geometry": {"coordinates":[-71.141771,41.727739],"type":"Point"}
}
