{
  "type": "Feature",
  "properties": {
    "addr:full": "41 Clifford St Melrose MA 02176",
    "addr:housenumber": "41",
    "addr:postcode": "02176",
    "addr:street": "Clifford St",
    "iso:country": "US",
    "sg:address": "41 Clifford St",
    "sg:city": "Melrose",
    "sg:classifiers": [
      {
        "category": "Manufacturing",
        "subcategory": "Signs",
        "type": "Manufacturing \u0026 Wholesale Goods"
      }
    ],
    "sg:phone": "+1 781 979 9048",
    "sg:postcode": "02176",
    "sg:province": "MA",
    "wof:name": "Bnckley Heller Rama",
    "wof:placetype": "venue"
  },
  "geometry": {"coordinates":[-71.056596,42.466339],"type":"Point"}
}
