{
  "type": "Feature",
  "properties": {
    "iso:country":"US",
    "sg:address":"17 Luke Rd",
    "sg:city":"Everett",
    "sg:classifiers":[
        {
            "category":"Professional",
            "type":"Services"
        }
    ],
    "sg:phone":"+1 781 308 8771",
    "sg:postcode":"02149",
    "sg:province":"MA",
    "sg:tags":[
        "transportation"
    ],
    "wof:name":"Horizons Moving Company",
    "wof:placetype":"venue"
},
  "geometry": {"coordinates":[-71.04391200000001,42.403213],"type":"Point"}
}