{
  "type": "Feature",
  "properties": {
    "iso:country":"US",
    "sg:address":"607 Commercial St",
    "sg:city":"Provincetown",
    "sg:classifiers":[
        {
            "category":"Professional",
            "subcategory":"Business Services",
            "type":"Services"
        }
    ],
    "sg:phone":"+1 508 487 0049",
    "sg:postcode":"02657",
    "sg:province":"MA",
    "sg:tags":[
        "interior",
        "consultant",
        "design",
        "decorator"
    ],
    "wof:name":"Noble-Lawton Interior Designer",
    "wof:placetype":"venue"
},
  "geometry": {"coordinates":[-70.168048,42.060316],"type":"Point"}
}