{
  "type": "Feature",
  "properties": {
    "addr:full":"8 Kendrick Rd Wareham MA 02571",
    "addr:housenumber":"8",
    "addr:postcode":"02571",
    "addr:street":"Kendrick Rd",
    "iso:country":"US",
    "sg:address":"8 Kendrick Rd",
    "sg:city":"Wareham",
    "sg:classifiers":[
        {
            "category":"Professional",
            "subcategory":"Engineering",
            "type":"Services"
        }
    ],
    "sg:phone":"+1 508 273 0300",
    "sg:postcode":"02571",
    "sg:province":"MA",
    "sg:tags":[
        "engineer"
    ],
    "wof:name":"Paquette & Assoc",
    "wof:placetype":"venue"
},
  "geometry": {"coordinates":[-70.741215,41.779326],"type":"Point"}
}