{
  "type": "Feature",
  "properties": {
    "addr:full": "37 Mechanic St Ste 1 Worcester MA 01608",
    "addr:housenumber": "37",
    "addr:postcode": "01608",
    "addr:street": "Mechanic St Ste 1",
    "iso:country": "US",
    "sg:address": "37 Mechanic St Ste 1",
    "sg:city": "Worcester",
    "sg:classifiers": [
      {
        "category": "Insurance",
        "subcategory": "Hazard Insurance",
        "type": "Services"
      }
    ],
    "sg:phone": "+1 508 791 5566",
    "sg:postcode": "01608",
    "sg:province": "MA",
    "sg:tags": [
      "commercial",
      "business"
    ],
    "sg:website": "http://www.midstins.com",
    "wof:name": "Mid-State Insurance Agency",
    "wof:placetype": "venue"
  },
  "geometry": {"coordinates":[-71.800725,42.263772],"type":"Point"}
}
