{
  "type": "Feature",
  "properties": {
    "iso:country":"US",
    "sg:address":"74 South St",
    "sg:city":"Shrewsbury",
    "sg:classifiers":[
        {
            "category":"Building & Trades",
            "subcategory":"Plumbing",
            "type":"Services"
        }
    ],
    "sg:phone":"+1 508 845 1924",
    "sg:postcode":"01545",
    "sg:province":"MA",
    "sg:tags":[
        "plumbing",
        "contractor"
    ],
    "wof:name":"Lyons Plumbing & Heating Inc",
    "wof:placetype":"venue"
},
  "geometry": {"coordinates":[-71.70104000000001,42.290443],"type":"Point"}
}