{
  "type": "Feature",
  "properties": {
    "addr:full": "74 South St Shrewsbury MA 01545",
    "addr:housenumber": "74",
    "addr:postcode": "01545",
    "addr:street": "South St",
    "iso:country": "US",
    "sg:address": "74 South St",
    "sg:city": "Shrewsbury",
    "sg:classifiers": [
      {
        "category": "Building \u0026 Trades",
        "subcategory": "Plumbing",
        "type": "Services"
      }
    ],
    "sg:phone": "+1 508 845 1924",
    "sg:postcode": "01545",
    "sg:province": "MA",
    "sg:tags": [
      "plumbing",
      "contractor"
    ],
    "wof:name": "Lyons Plumbing \u0026 Heating Inc",
    "wof:placetype": "venue"
  },
  "geometry": {"coordinates":[-71.70104,42.290443],"type":"Point"}
}
