{
  "type": "Feature",
  "properties": {
    "addr:full":"7 Bengal Ln Salem MA 01970",
    "addr:housenumber":"7",
    "addr:postcode":"01970",
    "addr:street":"Bengal Ln",
    "iso:country":"US",
    "sg:address":"7 Bengal Ln",
    "sg:city":"Salem",
    "sg:classifiers":[
        {
            "category":"Professional",
            "subcategory":"Management & Consulting",
            "type":"Services"
        }
    ],
    "sg:phone":"+1   ",
    "sg:postcode":"01970",
    "sg:province":"MA",
    "sg:tags":[
        "transportation"
    ],
    "wof:name":"Fjp Freight Systems",
    "wof:placetype":"venue"
},
  "geometry": {"coordinates":[-70.917554,42.499276],"type":"Point"}
}