{
  "type": "Feature",
  "properties": {
    "iso:country":"US",
    "sg:address":"122 Summit St",
    "sg:city":"Rockland",
    "sg:classifiers":[
        {
            "category":"Home & Garden",
            "subcategory":"Hardware",
            "type":"Retail Goods"
        }
    ],
    "sg:phone":"+1 781 982 0565",
    "sg:postcode":"02370",
    "sg:province":"MA",
    "sg:tags":[
        "water",
        "equipment",
        "filtration",
        "purification"
    ],
    "wof:name":"The Water Guys",
    "wof:placetype":"venue"
},
  "geometry": {"coordinates":[-70.915263,42.14041],"type":"Point"}
}