{
  "type": "Feature",
  "properties": {
    "iso:country":"US",
    "sg:address":"10 Old Mine Rock Way",
    "sg:city":"Hingham",
    "sg:classifiers":[
        {
            "category":"Shopping",
            "subcategory":"Computers & Home Electronics",
            "type":"Retail Goods"
        }
    ],
    "sg:phone":"+1 781 749 5092",
    "sg:postcode":"02043",
    "sg:province":"MA",
    "sg:tags":[
        "equipment",
        "dealer"
    ],
    "wof:name":"Aurum Computer Corp",
    "wof:placetype":"venue"
},
  "geometry": {"coordinates":[-70.91889500000001,42.174023],"type":"Point"}
}