{
  "type": "Feature",
  "properties": {
    "addr:full": "10 Old Mine Rock Way Hingham MA 02043",
    "addr:housenumber": "10",
    "addr:postcode": "02043",
    "addr:street": "Old Mine Rock Way",
    "iso:country": "US",
    "sg:address": "10 Old Mine Rock Way",
    "sg:city": "Hingham",
    "sg:classifiers": [
      {
        "category": "Shopping",
        "subcategory": "Computers \u0026 Home Electronics",
        "type": "Retail Goods"
      }
    ],
    "sg:phone": "+1 781 749 5092",
    "sg:postcode": "02043",
    "sg:province": "MA",
    "sg:tags": [
      "equipment",
      "dealer"
    ],
    "wof:name": "Aurum Computer Corp",
    "wof:placetype": "venue"
  },
  "geometry": {"coordinates":[-70.918895,42.174023],"type":"Point"}
}
