{
  "type": "Feature",
  "properties": {
    "iso:country":"US",
    "sg:address":"105 W 4th St",
    "sg:city":"Boston",
    "sg:classifiers":[
        {
            "category":"Professional",
            "subcategory":"Business Services",
            "type":"Services"
        }
    ],
    "sg:phone":"+1   ",
    "sg:postcode":"02127",
    "sg:province":"MA",
    "wof:name":"Newbury Design Lab",
    "wof:placetype":"venue"
},
  "geometry": {"coordinates":[-71.056798,42.341341],"type":"Point"}
}