{
  "type": "Feature",
  "properties": {
    "addr:full": "73 Greenleaf Cir Framingham MA 01701",
    "addr:housenumber": "73",
    "addr:postcode": "01701",
    "addr:street": "Greenleaf Cir",
    "iso:country": "US",
    "sg:address": "73 Greenleaf Cir",
    "sg:city": "Framingham",
    "sg:classifiers": [
      {
        "category": "Professional",
        "subcategory": "Employment Agencies",
        "type": "Services"
      }
    ],
    "sg:phone": "+1 508 628 0111",
    "sg:postcode": "01701",
    "sg:province": "MA",
    "sg:tags": [
      "opportunity"
    ],
    "wof:name": "H R I Executive Search Inc",
    "wof:placetype": "venue"
  },
  "geometry": {"coordinates":[-71.39638,42.309242],"type":"Point"}
}
