{
  "type": "Feature",
  "properties": {
    "addr:full": "205 Conway St Greenfield MA 01301",
    "addr:housenumber": "205",
    "addr:postcode": "01301",
    "addr:street": "Conway St",
    "iso:country": "US",
    "sg:address": "205 Conway St",
    "sg:city": "Greenfield",
    "sg:classifiers": [
      {
        "category": "Building \u0026 Trades",
        "subcategory": "Construction",
        "type": "Services"
      }
    ],
    "sg:phone": "+1   ",
    "sg:postcode": "01301",
    "sg:province": "MA",
    "sg:tags": [
      "house"
    ],
    "wof:name": "Hobbs Handyman Services",
    "wof:placetype": "venue"
  },
  "geometry": {"coordinates":[-72.608078,42.594084],"type":"Point"}
}
