{
  "type": "Feature",
  "properties": {
    "iso:country":"US",
    "sg:address":"205 Conway St",
    "sg:city":"Greenfield",
    "sg:classifiers":[
        {
            "category":"Building & Trades",
            "subcategory":"Construction",
            "type":"Services"
        }
    ],
    "sg:phone":"+1   ",
    "sg:postcode":"01301",
    "sg:province":"MA",
    "sg:tags":[
        "house"
    ],
    "wof:name":"Hobbs Handyman Services",
    "wof:placetype":"venue"
},
  "geometry": {"coordinates":[-72.60807800000001,42.594084],"type":"Point"}
}