{
  "type": "Feature",
  "properties": {
    "iso:country":"US",
    "sg:address":"72 Central St",
    "sg:city":"Wellesley",
    "sg:classifiers":[
        {
            "category":"Personal",
            "subcategory":"Beauty Salon",
            "type":"Services"
        },
        {
            "category":"Personal",
            "subcategory":"Hair Removal",
            "type":"Services"
        },
        {
            "category":"Personal",
            "subcategory":"Day Spa",
            "type":"Services"
        },
        {
            "category":"Personal",
            "subcategory":"Skin Care",
            "type":"Services"
        }
    ],
    "sg:phone":"+1 857 366 5341",
    "sg:postcode":"02482",
    "sg:province":"MA",
    "sg:tags":[
        "stylist"
    ],
    "sg:website":"http://www.ardanspa.com",
    "wof:name":"Ardan MedSpa & Salon",
    "wof:placetype":"venue"
},
  "geometry": {"coordinates":[-71.297714,42.295965],"type":"Point"}
}