{
  "type": "Feature",
  "properties": {
    "addr:full": "25 Endicott St Lawrence MA 01841",
    "addr:housenumber": "25",
    "addr:postcode": "01841",
    "addr:street": "Endicott St",
    "iso:country": "US",
    "sg:address": "25 Endicott St",
    "sg:city": "Lawrence",
    "sg:classifiers": [
      {
        "category": "Professional",
        "type": "Services"
      }
    ],
    "sg:phone": "+1 978 794 9195",
    "sg:postcode": "01841",
    "sg:province": "MA",
    "sg:tags": [
      "establishment"
    ],
    "wof:name": "Mesa Technology Corp",
    "wof:placetype": "venue"
  },
  "geometry": {"coordinates":[-71.187518,42.702608],"type":"Point"}
}
