{
  "type": "Feature",
  "properties": {
    "addr:full":"125 Varnum Rd Dracut MA 01826",
    "addr:housenumber":"125",
    "addr:postcode":"01826",
    "addr:street":"Varnum Rd",
    "iso:country":"US",
    "sg:address":"125 Varnum Rd",
    "sg:city":"Dracut",
    "sg:classifiers":[
        {
            "category":"Building & Trades",
            "subcategory":"Construction",
            "type":"Services"
        }
    ],
    "sg:phone":"+1 978 957 9200",
    "sg:postcode":"01826",
    "sg:province":"MA",
    "sg:tags":[
        "concrete",
        "contractor"
    ],
    "wof:name":"Northeast Concrete Foundations",
    "wof:placetype":"venue"
},
  "geometry": {"coordinates":[-71.360119,42.683775],"type":"Point"}
}