{
  "type": "Feature",
  "properties": {
    "iso:country":"US",
    "sg:address":"12 Dexter Rd",
    "sg:city":"Newtonville",
    "sg:classifiers":[
        {
            "category":"Health Services",
            "subcategory":"Doctor",
            "type":"Services"
        }
    ],
    "sg:phone":"+1 617 244 1824",
    "sg:postcode":"02460",
    "sg:province":"MA",
    "sg:tags":[
        "physician",
        "surgeon"
    ],
    "wof:name":"Vales Vassilios",
    "wof:placetype":"venue"
},
  "geometry": {"coordinates":[-71.20715300000001,42.342784],"type":"Point"}
}