{
  "type": "Feature",
  "properties": {
    "addr:full":"136 Nahatan St Norwood MA 02062",
    "addr:housenumber":"136",
    "addr:postcode":"02062",
    "addr:street":"Nahatan St",
    "iso:country":"US",
    "sg:address":"136 Nahatan St",
    "sg:city":"Norwood",
    "sg:classifiers":[
        {
            "category":"Retail",
            "subcategory":"Portrait Studio",
            "type":"Services"
        },
        {
            "category":"Shopping",
            "subcategory":"Pharmacy",
            "type":"Retail Goods"
        }
    ],
    "sg:phone":"+1 781 769 8336",
    "sg:postcode":"02062",
    "sg:province":"MA",
    "sg:tags":[
        "photography",
        "drugstore",
        "store"
    ],
    "sg:website":"www.cvs.com",
    "wof:name":"Cvs/Pharmacy",
    "wof:placetype":"venue"
},
  "geometry": {"coordinates":[-71.200401,42.195],"type":"Point"}
}