{
  "type": "Feature",
  "properties": {
    "addr:full": "1047 Washington St East Weymouth MA 02189",
    "addr:housenumber": "1047",
    "addr:postcode": "02189",
    "addr:street": "Washington St",
    "iso:country": "US",
    "sg:address": "1047 Washington St",
    "sg:city": "East Weymouth",
    "sg:classifiers": [
      {
        "category": "Retail",
        "subcategory": "Repair Shop",
        "type": "Services"
      }
    ],
    "sg:phone": "+1 781 331 1009",
    "sg:postcode": "02189",
    "sg:province": "MA",
    "sg:tags": [
      "refrigerating"
    ],
    "wof:name": "Atlantic Refrigeration",
    "wof:placetype": "venue"
  },
  "geometry": {"coordinates":[-70.934236,42.198743],"type":"Point"}
}
