{
  "type": "Feature",
  "properties": {
    "addr:full": "678 Brookline Ave Brookline MA 02445",
    "addr:housenumber": "678",
    "addr:postcode": "02445",
    "addr:street": "Brookline Ave",
    "iso:country": "US",
    "sg:address": "678 Brookline Ave",
    "sg:city": "Brookline",
    "sg:classifiers": [
      {
        "category": "Retail",
        "subcategory": "Repair Shop",
        "type": "Services"
      }
    ],
    "sg:phone": "+1 617 477 0254",
    "sg:postcode": "02445",
    "sg:province": "MA",
    "sg:tags": [
      "lock",
      "locksmith"
    ],
    "wof:name": "1 Hour 7 Day Emerge Locksmith",
    "wof:placetype": "venue"
  },
  "geometry": {"coordinates":[-71.113915,42.332626],"type":"Point"}
}
