{
  "type": "Feature",
  "properties": {
    "iso:country":"US",
    "sg:address":"3 Pevey St",
    "sg:city":"Lowell",
    "sg:classifiers":[
        {
            "category":"Freight",
            "type":"Transportation"
        }
    ],
    "sg:phone":"+1   ",
    "sg:postcode":"01851",
    "sg:province":"MA",
    "sg:tags":[
        "operator",
        "local",
        "trucking"
    ],
    "wof:name":"Troys Moving & Storage",
    "wof:placetype":"venue"
},
  "geometry": {"coordinates":[-71.326609,42.639686],"type":"Point"}
}