{
  "type": "Feature",
  "properties": {
    "addr:full":"9 Peacevale Rd Dorchester Ctr MA 02124",
    "addr:housenumber":"9",
    "addr:postcode":"02124",
    "addr:street":"Peacevale Rd",
    "iso:country":"US",
    "sg:address":"9 Peacevale Rd",
    "sg:city":"Dorchester Ctr",
    "sg:classifiers":[
        {
            "category":"Professional",
            "type":"Services"
        }
    ],
    "sg:phone":"+1 617 282 8503",
    "sg:postcode":"02124",
    "sg:province":"MA",
    "sg:tags":[
        "establishment"
    ],
    "wof:name":"Institute For Student Achvmnt",
    "wof:placetype":"venue"
},
  "geometry": {"coordinates":[-71.07598299999999,42.286218],"type":"Point"}
}