{
  "type": "Feature",
  "properties": {
    "addr:full": "88 Montvale Avenue Stoneham MA 02180",
    "addr:housenumber": "88",
    "addr:postcode": "02180",
    "addr:street": "Montvale Avenue",
    "iso:country": "US",
    "sg:address": "88 Montvale Avenue",
    "sg:city": "Stoneham",
    "sg:classifiers": [
      {
        "category": "Sports \u0026 Exercise",
        "subcategory": "Gym",
        "type": "Entertainment"
      },
      {
        "category": "Health Services",
        "subcategory": "Dentist",
        "type": "Services"
      }
    ],
    "sg:phone": "+1 781 438 7206",
    "sg:postcode": "02180",
    "sg:province": "MA",
    "sg:tags": [
      "trainer"
    ],
    "wof:name": "Tarro Allen W DMD",
    "wof:placetype": "venue"
  },
  "geometry": {"coordinates":[-71.110855,42.480676],"type":"Point"}
}
