{
  "type": "Feature",
  "properties": {
    "addr:full":"28 Hayden Rowe St Hopkinton MA 01748",
    "addr:housenumber":"28",
    "addr:postcode":"01748",
    "addr:street":"Hayden Rowe St",
    "iso:country":"US",
    "sg:address":"28 Hayden Rowe St",
    "sg:city":"Hopkinton",
    "sg:classifiers":[
        {
            "category":"Health Services",
            "subcategory":"Doctor",
            "type":"Services"
        }
    ],
    "sg:phone":"+1 508 435 4033",
    "sg:postcode":"01748",
    "sg:province":"MA",
    "sg:tags":[
        "physician",
        "surgeon"
    ],
    "wof:name":"Charles River Medical Assoc",
    "wof:placetype":"venue"
},
  "geometry": {"coordinates":[-71.51777300000001,42.226628],"type":"Point"}
}