{
  "type": "Feature",
  "properties": {
    "addr:full":"Fruit Boston MA 02108",
    "addr:postcode":"02108",
    "iso:country":"US",
    "sg:address":"Fruit",
    "sg:city":"Boston",
    "sg:classifiers":[
        {
            "category":"Health Services",
            "subcategory":"Doctor",
            "type":"Services"
        },
        {
            "category":"Sports & Exercise",
            "subcategory":"Gym",
            "type":"Entertainment"
        }
    ],
    "sg:phone":"+1 617 726 3896",
    "sg:postcode":"02108",
    "sg:province":"MA",
    "sg:tags":[
        "trainer"
    ],
    "wof:name":"Poskanzer David C Phys",
    "wof:placetype":"venue"
},
  "geometry": {"coordinates":[-71.06511399999999,42.357724],"type":"Point"}
}