{
  "type": "Feature",
  "properties": {
    "addr:full":"145 Malden St Malden MA 02148",
    "addr:housenumber":"145",
    "addr:postcode":"02148",
    "addr:street":"Malden St",
    "iso:country":"US",
    "sg:address":"145 Malden St",
    "sg:city":"Malden",
    "sg:classifiers":[
        {
            "category":"Building & Trades",
            "subcategory":"Construction",
            "type":"Services"
        }
    ],
    "sg:phone":"+1 781 321 5282",
    "sg:postcode":"02148",
    "sg:province":"MA",
    "sg:tags":[
        "plastering",
        "contractor"
    ],
    "wof:name":"Skips Plastering",
    "wof:placetype":"venue"
},
  "geometry": {"coordinates":[-71.08302399999999,42.419552],"type":"Point"}
}