{
  "type": "Feature",
  "properties": {
    "addr:full": "28 Caswell St East Taunton MA 02718",
    "addr:housenumber": "28",
    "addr:postcode": "02718",
    "addr:street": "Caswell St",
    "iso:country": "US",
    "sg:address": "28 Caswell St",
    "sg:city": "East Taunton",
    "sg:classifiers": [
      {
        "category": "Building \u0026 Trades",
        "subcategory": "Construction",
        "type": "Services"
      }
    ],
    "sg:phone": "+1 508 823 2481",
    "sg:postcode": "02718",
    "sg:province": "MA",
    "sg:tags": [
      "painter"
    ],
    "wof:name": "Stevenson Painting Co Inc",
    "wof:placetype": "venue"
  },
  "geometry": {"coordinates":[-71.039539,41.879629],"type":"Point"}
}
