{
  "type": "Feature",
  "properties": {
    "iso:country":"US",
    "sg:address":"602 Main St",
    "sg:city":"Haverhill",
    "sg:classifiers":[
        {
            "category":"Banks & Credit Unions",
            "subcategory":"Investment Brokerage",
            "type":"Services"
        }
    ],
    "sg:phone":"+1   ",
    "sg:postcode":"01830",
    "sg:province":"MA",
    "sg:tags":[
        "company"
    ],
    "wof:name":"Pentoliros Enterprises",
    "wof:placetype":"venue"
},
  "geometry": {"coordinates":[-71.082555,42.791458],"type":"Point"}
}