{
  "type": "Feature",
  "properties": {
    "addr:full":"148 Washington St Salem MA 01970",
    "addr:housenumber":"148",
    "addr:postcode":"01970",
    "addr:street":"Washington St",
    "iso:country":"US",
    "sg:address":"148 Washington St",
    "sg:city":"Salem",
    "sg:classifiers":[
        {
            "category":"Real Estate",
            "subcategory":"Real Estate Services",
            "type":"Services"
        },
        {
            "category":"Real Estate",
            "subcategory":"Real Estate Agent",
            "type":"Services"
        }
    ],
    "sg:phone":"+1 978 741 0500",
    "sg:postcode":"01970",
    "sg:province":"MA",
    "sg:tags":[
        "management"
    ],
    "wof:name":"Carlson Executive Account Inc",
    "wof:placetype":"venue"
},
  "geometry": {"coordinates":[-70.895506,42.520534],"type":"Point"}
}