{
  "type": "Feature",
  "properties": {
    "addr:full":"15 Pleasant Street Malden MA 02148",
    "addr:housenumber":"15",
    "addr:postcode":"02148",
    "addr:street":"Pleasant Street",
    "iso:country":"US",
    "sg:address":"15 Pleasant Street",
    "sg:city":"Malden",
    "sg:classifiers":[
        {
            "category":"Personal",
            "subcategory":"Nail Salon",
            "type":"Services"
        }
    ],
    "sg:phone":"+1 781 321 2111",
    "sg:postcode":"02148",
    "sg:province":"MA",
    "wof:name":"Natural Nails",
    "wof:placetype":"venue"
},
  "geometry": {"coordinates":[-71.06791800000001,42.426431],"type":"Point"}
}