{
  "type": "Feature",
  "properties": {
    "addr:full":"347 Pratt St Mansfield MA 02048",
    "addr:housenumber":"347",
    "addr:postcode":"02048",
    "addr:street":"Pratt St",
    "iso:country":"US",
    "sg:address":"347 Pratt St",
    "sg:city":"Mansfield",
    "sg:classifiers":[
        {
            "category":"Home & Garden",
            "subcategory":"Garden Supply",
            "type":"Retail Goods"
        },
        {
            "category":"Shopping",
            "subcategory":"Gifts & Souvenirs",
            "type":"Retail Goods"
        },
        {
            "category":"Shopping",
            "subcategory":"Crafts & Fabrics",
            "type":"Retail Goods"
        },
        {
            "category":"Shopping",
            "subcategory":"Florist",
            "type":"Retail Goods"
        }
    ],
    "sg:phone":"+1 508 339 3076",
    "sg:postcode":"02048",
    "sg:province":"MA",
    "sg:tags":[
        "plant",
        "etc-retail",
        "dried",
        "basket",
        "trees-silk",
        "flowers"
    ],
    "sg:website":"http://www.mansfieldflorist.net",
    "wof:name":"Mansfield Florist",
    "wof:placetype":"venue"
},
  "geometry": {"coordinates":[-71.20177099999999,42.033539],"type":"Point"}
}