{
  "type": "Feature",
  "properties": {
    "addr:full":"137 Fellsway W Medford MA 02155",
    "addr:housenumber":"137",
    "addr:postcode":"02155",
    "addr:street":"Fellsway W",
    "iso:country":"US",
    "sg:address":"137 Fellsway W",
    "sg:city":"Medford",
    "sg:classifiers":[
        {
            "category":"Banks & Credit Unions",
            "subcategory":"Bank",
            "type":"Services"
        }
    ],
    "sg:phone":"+1   ",
    "sg:postcode":"02155",
    "sg:province":"MA",
    "sg:tags":[
        "national",
        "commercial"
    ],
    "wof:name":"Fleet",
    "wof:placetype":"venue"
},
  "geometry": {"coordinates":[-71.09141,42.424526],"type":"Point"}
}