{
  "type": "Feature",
  "properties": {
    "addr:full": "739 Ashley Blvd New Bedford MA 02745",
    "addr:housenumber": "739",
    "addr:postcode": "02745",
    "addr:street": "Ashley Blvd",
    "iso:country": "US",
    "sg:address": "739 Ashley Blvd",
    "sg:city": "New Bedford",
    "sg:classifiers": [
      {
        "category": "Personal",
        "type": "Services"
      }
    ],
    "sg:phone": "+1 508 998 9999",
    "sg:postcode": "02745",
    "sg:province": "MA",
    "sg:tags": [
      "electrolysis"
    ],
    "wof:name": "Andrea Andrews Professional",
    "wof:placetype": "venue"
  },
  "geometry": {"coordinates":[-70.933816,41.680598],"type":"Point"}
}
