{
  "type": "Feature",
  "properties": {
    "iso:country":"US",
    "sg:address":"162 E Main St",
    "sg:city":"Avon",
    "sg:classifiers":[
        {
            "category":"Professional",
            "subcategory":"Lawyer & Legal Services",
            "type":"Services"
        }
    ],
    "sg:phone":"+1 508 584 8930",
    "sg:postcode":"02322",
    "sg:province":"MA",
    "wof:name":"David I Brenner",
    "wof:placetype":"venue"
},
  "geometry": {"coordinates":[-71.037081,42.126848],"type":"Point"}
}