{
  "type": "Feature",
  "properties": {
    "addr:full": "46 Route 6a Sandwich MA 02563",
    "addr:housenumber": "46",
    "addr:postcode": "02563",
    "addr:street": "Route 6A",
    "iso:country": "US",
    "sg:address": "46 Route 6a",
    "sg:city": "Sandwich",
    "sg:classifiers": [
      {
        "category": "Restaurant",
        "type": "Food \u0026 Drink"
      }
    ],
    "sg:menulink": "http://www.allmenus.com/ma/sandwich/25701-british-beer-company/menu/",
    "sg:phone": "+1 508 833 9590",
    "sg:postcode": "02563",
    "sg:province": "MA",
    "sg:tags": [
      "food",
      "american",
      "pub"
    ],
    "wof:name": "British Beer Company",
    "wof:placetype": "venue"
  },
  "geometry": {"coordinates":[-70.512357,41.76551],"type":"Point"}
}
