{
  "type": "Feature",
  "properties": {
    "addr:full":"175 Elm St Somerville MA 02144",
    "addr:housenumber":"175",
    "addr:postcode":"02144",
    "addr:street":"Elm St",
    "iso:country":"US",
    "sg:address":"175 Elm St",
    "sg:city":"Somerville",
    "sg:classifiers":[
        {
            "category":"Sports & Exercise",
            "subcategory":"Gym",
            "type":"Entertainment"
        }
    ],
    "sg:phone":"+1 617 591 9655",
    "sg:postcode":"02144",
    "sg:province":"MA",
    "sg:tags":[
        "technique",
        "alexander"
    ],
    "wof:name":"Alexander Technique Harvard",
    "wof:placetype":"venue"
},
  "geometry": {"coordinates":[-71.120014,42.392616],"type":"Point"}
}