{
  "type": "Feature",
  "properties": {
    "addr:full":"1100 Lexington St Waltham MA 02452",
    "addr:housenumber":"1100",
    "addr:postcode":"02452",
    "addr:street":"Lexington St",
    "iso:country":"US",
    "sg:address":"1100 Lexington St",
    "sg:city":"Waltham",
    "sg:phone":"+1 781 547 5655",
    "sg:postcode":"02452",
    "sg:province":"MA",
    "sg:website":"http://www.panerabread.com",
    "wof:name":"Panera Bread",
    "wof:placetype":"venue"
},
  "geometry": {"coordinates":[-71.23362899999999,42.411363],"type":"Point"}
}