{
  "type": "Feature",
  "properties": {
    "addr:full": "171 Harrison Avenue Boston MA 02111",
    "addr:housenumber": "171",
    "addr:postcode": "02111",
    "addr:street": "Harrison Avenue",
    "iso:country": "US",
    "sg:address": "171 Harrison Avenue",
    "sg:city": "Boston",
    "sg:classifiers": [
      {
        "category": "Health Services",
        "subcategory": "Doctor",
        "type": "Services"
      },
      {
        "category": "Sports \u0026 Exercise",
        "subcategory": "Gym",
        "type": "Entertainment"
      }
    ],
    "sg:phone": "+1 617 956 5879",
    "sg:postcode": "02111",
    "sg:province": "MA",
    "sg:tags": [
      "trainer"
    ],
    "wof:name": "Donowitz Mark MD",
    "wof:placetype": "venue"
  },
  "geometry": {"coordinates":[-71.06187,42.34973],"type":"Point"}
}
