{
  "type": "Feature",
  "properties": {
    "iso:country":"US",
    "sg:address":"450 Lexington St",
    "sg:city":"Auburndale",
    "sg:classifiers":[
        {
            "category":"Banks & Credit Unions",
            "subcategory":"Bank",
            "type":"Services"
        }
    ],
    "sg:phone":"+1 617 964 5254",
    "sg:postcode":"02466",
    "sg:province":"MA",
    "sg:tags":[
        "loan",
        "real estate"
    ],
    "wof:name":"Preferred Mortgage Group",
    "wof:placetype":"venue"
},
  "geometry": {"coordinates":[-71.246931,42.346754],"type":"Point"}
}