{
  "type": "Feature",
  "properties": {
    "iso:country":"US",
    "sg:address":"198 Ash St",
    "sg:city":"Reading",
    "sg:classifiers":[
        {
            "category":"Health Services",
            "subcategory":"Doctor",
            "type":"Services"
        }
    ],
    "sg:phone":"+1 781 944 6761",
    "sg:postcode":"01867",
    "sg:province":"MA",
    "sg:tags":[
        "surgeon",
        "oral"
    ],
    "wof:name":"Associates In Family Dentistry DDS",
    "wof:placetype":"venue"
},
  "geometry": {"coordinates":[-71.101601,42.517899],"type":"Point"}
}