{
  "type": "Feature",
  "properties": {
    "iso:country":"US",
    "sg:address":"59 Bigelow Ave",
    "sg:city":"Watertown",
    "sg:classifiers":[
        {
            "category":"Building & Trades",
            "subcategory":"Construction",
            "type":"Services"
        }
    ],
    "sg:phone":"+1 617 926 0949",
    "sg:postcode":"02472",
    "sg:province":"MA",
    "sg:tags":[
        "hanging",
        "contractor"
    ],
    "sg:website":"www.painterlycraft.com",
    "wof:name":"Painterly Craft Inc",
    "wof:placetype":"venue"
},
  "geometry": {"coordinates":[-71.15752000000001,42.368056],"type":"Point"}
}