{
  "type": "Feature",
  "properties": {
    "addr:full": "32 Billings Ave Medford MA 02155",
    "addr:housenumber": "32",
    "addr:postcode": "02155",
    "addr:street": "Billings Ave",
    "iso:country": "US",
    "sg:address": "32 Billings Ave",
    "sg:city": "Medford",
    "sg:classifiers": [
      {
        "category": "Professional",
        "subcategory": "Accounting \u0026 Tax Preparation",
        "type": "Services"
      }
    ],
    "sg:phone": "+1 781 396 3303",
    "sg:postcode": "02155",
    "sg:province": "MA",
    "sg:tags": [
      "return"
    ],
    "wof:name": "John M Power Ea",
    "wof:placetype": "venue"
  },
  "geometry": {"coordinates":[-71.107527,42.407787],"type":"Point"}
}
