{
  "type": "Feature",
  "properties": {
    "addr:full":"1640 Massachusetts Ave Cambridge MA 02138",
    "addr:housenumber":"1640",
    "addr:postcode":"02138",
    "addr:street":"Massachusetts Ave",
    "iso:country":"US",
    "sg:address":"1640 Massachusetts Ave",
    "sg:city":"Cambridge",
    "sg:classifiers":[
        {
            "category":"Shopping",
            "subcategory":"Books",
            "type":"Retail Goods"
        }
    ],
    "sg:phone":"+1 617 576 3634",
    "sg:postcode":"02138",
    "sg:province":"MA",
    "sg:tags":[
        "bookstore"
    ],
    "sg:website":"www.bledsoebooks.com",
    "wof:name":"Robin Bledsoe, Bookseller",
    "wof:placetype":"venue"
},
  "geometry": {"coordinates":[-71.12029,42.381226],"type":"Point"}
}