{
  "type": "Feature",
  "properties": {
    "addr:full":"1330 Broadway Revere MA 02151",
    "addr:housenumber":"1330",
    "addr:postcode":"02151",
    "addr:street":"Broadway",
    "iso:country":"US",
    "sg:address":"1330 Broadway",
    "sg:city":"Revere",
    "sg:classifiers":[
        {
            "category":"Building & Trades",
            "subcategory":"Plumbing",
            "type":"Services"
        }
    ],
    "sg:phone":"+1 781 592 3355",
    "sg:postcode":"02151",
    "sg:province":"MA",
    "sg:tags":[
        "plumbing",
        "contractor"
    ],
    "wof:name":"James N Roche Co Inc",
    "wof:placetype":"venue"
},
  "geometry": {"coordinates":[-70.99879,42.428885],"type":"Point"}
}