{
  "type": "Feature",
  "properties": {
    "addr:full":"140 Eastern Ave Ste 5 Chelsea MA 02150",
    "addr:housenumber":"140",
    "addr:postcode":"02150",
    "addr:street":"Eastern Ave Ste 5",
    "iso:country":"US",
    "sg:address":"140 Eastern Ave Ste 5",
    "sg:city":"Chelsea",
    "sg:classifiers":[
        {
            "category":"Professional",
            "subcategory":"Employment Agencies",
            "type":"Services"
        },
        {
            "category":"Professional",
            "subcategory":"Business Services",
            "type":"Services"
        }
    ],
    "sg:phone":"+1 617 887 0803",
    "sg:postcode":"02150",
    "sg:province":"MA",
    "sg:tags":[
        "consultant",
        "broker",
        "custom"
    ],
    "wof:name":"Albatrans Inc",
    "wof:placetype":"venue"
},
  "geometry": {"coordinates":[-71.022463,42.391388],"type":"Point"}
}