{
  "type": "Feature",
  "properties": {
    "addr:full": "14 Bray Ct Amherst MA 01002",
    "addr:housenumber": "14",
    "addr:postcode": "01002",
    "addr:street": "Bray Ct",
    "iso:country": "US",
    "sg:address": "14 Bray Ct",
    "sg:city": "Amherst",
    "sg:classifiers": [
      {
        "category": "Retail",
        "subcategory": "Portrait Studio",
        "type": "Services"
      }
    ],
    "sg:phone": "+1   ",
    "sg:postcode": "01002",
    "sg:province": "MA",
    "sg:tags": [
      "photo"
    ],
    "wof:name": "Jon Crispin Photography",
    "wof:placetype": "venue"
  },
  "geometry": {"coordinates":[-72.432938,42.380178],"type":"Point"}
}
