{
  "type": "Feature",
  "properties": {
    "addr:full":"95 Pine St Natick MA 01760",
    "addr:housenumber":"95",
    "addr:postcode":"01760",
    "addr:street":"Pine St",
    "iso:country":"US",
    "sg:address":"95 Pine St",
    "sg:city":"Natick",
    "sg:classifiers":[
        {
            "category":"Organizations",
            "subcategory":"Professional Association",
            "type":"Services"
        }
    ],
    "sg:phone":"+1   ",
    "sg:postcode":"01760",
    "sg:province":"MA",
    "sg:tags":[
        "contracting",
        "general"
    ],
    "wof:name":"Martyn ARI",
    "wof:placetype":"venue"
},
  "geometry": {"coordinates":[-71.344723,42.314936],"type":"Point"}
}