{
  "type": "Feature",
  "properties": {
    "addr:full": "11 Ryders Ln Marshfield MA 02050",
    "addr:housenumber": "11",
    "addr:postcode": "02050",
    "addr:street": "Ryders Ln",
    "iso:country": "US",
    "sg:address": "11 Ryders Ln",
    "sg:city": "Marshfield",
    "sg:classifiers": [
      {
        "category": "Home \u0026 Garden",
        "subcategory": "Building Materials",
        "type": "Retail Goods"
      }
    ],
    "sg:phone": "+1   ",
    "sg:postcode": "02050",
    "sg:province": "MA",
    "wof:name": "All Star Auto Glass Co Inc",
    "wof:placetype": "venue"
  },
  "geometry": {"coordinates":[-70.730021,42.098774],"type":"Point"}
}
