{
  "type": "Feature",
  "properties": {
    "addr:full":"10 Presidents Lndg Medford MA 02155",
    "addr:housenumber":"10",
    "addr:postcode":"02155",
    "addr:street":"Presidents Lndg",
    "iso:country":"US",
    "sg:address":"10 Presidents Lndg",
    "sg:city":"Medford",
    "sg:classifiers":[
        {
            "category":"Professional",
            "type":"Services"
        }
    ],
    "sg:phone":"+1 781 396 4095",
    "sg:postcode":"02155",
    "sg:province":"MA",
    "sg:tags":[
        "management",
        "property"
    ],
    "wof:name":"National Development",
    "wof:placetype":"venue"
},
  "geometry": {"coordinates":[-71.082179,42.402207],"type":"Point"}
}