{
  "type": "Feature",
  "properties": {
    "addr:full":"25 Boston St Boston MA 02127",
    "addr:housenumber":"25",
    "addr:postcode":"02127",
    "addr:street":"Boston St",
    "iso:country":"US",
    "sg:address":"25 Boston St",
    "sg:city":"Boston",
    "sg:classifiers":[
        {
            "category":"Real Estate",
            "subcategory":"Real Estate Agent",
            "type":"Services"
        }
    ],
    "sg:phone":"+1 617 268 5300",
    "sg:postcode":"02127",
    "sg:province":"MA",
    "sg:tags":[
        "apartment"
    ],
    "sg:website":"www.gentlemovers.com",
    "wof:name":"Gentle Movers Moving & Storage Company",
    "wof:placetype":"venue"
},
  "geometry": {"coordinates":[-71.05740400000001,42.328701],"type":"Point"}
}