{
  "type": "Feature",
  "properties": {
    "iso:country":"US",
    "sg:address":"22 Lyman St",
    "sg:city":"Waltham",
    "sg:classifiers":[
        {
            "category":"Social Services",
            "subcategory":"Child Care",
            "type":"Services"
        }
    ],
    "sg:phone":"+1 781 893 5880",
    "sg:postcode":"02452",
    "sg:province":"MA",
    "wof:name":"Little Souls Ctr",
    "wof:placetype":"venue"
},
  "geometry": {"coordinates":[-71.230535,42.377334],"type":"Point"}
}