{
  "type": "Feature",
  "properties": {
    "addr:full":"84 Bowers St Newtonville MA 02460",
    "addr:housenumber":"84",
    "addr:postcode":"02460",
    "addr:street":"Bowers St",
    "iso:country":"US",
    "sg:address":"84 Bowers St",
    "sg:city":"Newtonville",
    "sg:classifiers":[
        {
            "category":"Manufacturing",
            "subcategory":"Printing",
            "type":"Manufacturing & Wholesale Goods"
        }
    ],
    "sg:phone":"+1 617 527 9777",
    "sg:postcode":"02460",
    "sg:province":"MA",
    "sg:tags":[
        "multimedia"
    ],
    "wof:name":"Lawtek Media Group LLC",
    "wof:placetype":"venue"
},
  "geometry": {"coordinates":[-71.202793,42.351615],"type":"Point"}
}