{
  "type": "Feature",
  "properties": {
    "iso:country":"US",
    "sg:address":"504 Pleasant St",
    "sg:city":"Attleboro",
    "sg:classifiers":[
        {
            "category":"Personal",
            "subcategory":"Nail Salon",
            "type":"Services"
        }
    ],
    "sg:phone":"+1 508 226 7090",
    "sg:postcode":"02703",
    "sg:province":"MA",
    "wof:name":"Top Nails",
    "wof:placetype":"venue"
},
  "geometry": {"coordinates":[-71.2715,41.951698],"type":"Point"}
}