{
  "type": "Feature",
  "properties": {
    "iso:country":"US",
    "sg:address":"529 Ashland Ave",
    "sg:city":"Southbridge",
    "sg:classifiers":[
        {
            "category":"Wholesale",
            "subcategory":"Metals & Minerals",
            "type":"Manufacturing & Wholesale Goods"
        }
    ],
    "sg:phone":"+1 508 765 4929",
    "sg:postcode":"01550",
    "sg:province":"MA",
    "sg:tags":[
        "steel",
        "warehouse"
    ],
    "wof:name":"Accurate Metal Sales",
    "wof:placetype":"venue"
},
  "geometry": {"coordinates":[-71.996402,42.058489],"type":"Point"}
}