{
  "type": "Feature",
  "properties": {
    "iso:country":"US",
    "sg:address":"106 Robert St",
    "sg:city":"Attleboro",
    "sg:classifiers":[
        {
            "category":"Arts & Performance",
            "subcategory":"Theater",
            "type":"Entertainment"
        }
    ],
    "sg:phone":"+1 508 222 6624",
    "sg:postcode":"02703",
    "sg:province":"MA",
    "sg:tags":[
        "performing"
    ],
    "wof:name":"Triboro Youth Theatre",
    "wof:placetype":"venue"
},
  "geometry": {"coordinates":[-71.295998,41.935398],"type":"Point"}
}