{
  "type": "Feature",
  "properties": {
    "iso:country":"US",
    "sg:address":"996 E Falmouth Hwy",
    "sg:city":"East Falmouth",
    "sg:classifiers":[
        {
            "category":"Building & Trades",
            "subcategory":"Landscaping Services",
            "type":"Services"
        }
    ],
    "sg:phone":"+1 508 548 2662",
    "sg:postcode":"02536",
    "sg:province":"MA",
    "sg:tags":[
        "landscape",
        "contractor"
    ],
    "sg:website":"www.davey.com",
    "wof:name":"Davey Tree Expert Co",
    "wof:placetype":"venue"
},
  "geometry": {"coordinates":[-70.539824,41.579622],"type":"Point"}
}