{
  "type": "Feature",
  "properties": {
    "addr:full": "485 Arsenal St Watertown MA 02472",
    "addr:housenumber": "485",
    "addr:postcode": "02472",
    "addr:street": "Arsenal St",
    "iso:country": "US",
    "sg:address": "485 Arsenal St",
    "sg:city": "Watertown",
    "sg:classifiers": [
      {
        "category": "Personal",
        "subcategory": "Piercing",
        "type": "Services"
      }
    ],
    "sg:phone": "+1 617 924 3337",
    "sg:postcode": "02472",
    "sg:province": "MA",
    "wof:name": "Almoda",
    "wof:placetype": "venue"
  },
  "geometry": {"coordinates":[-71.15865,42.362769],"type":"Point"}
}
