{
  "type": "Feature",
  "properties": {
    "iso:country":"US",
    "sg:address":"485 Arsenal St",
    "sg:city":"Watertown",
    "sg:classifiers":[
        {
            "category":"Personal",
            "subcategory":"Piercing",
            "type":"Services"
        }
    ],
    "sg:phone":"+1 617 924 3337",
    "sg:postcode":"02472",
    "sg:province":"MA",
    "wof:name":"Almoda",
    "wof:placetype":"venue"
},
  "geometry": {"coordinates":[-71.15864999999999,42.362769],"type":"Point"}
}