{
  "type": "Feature",
  "properties": {
    "iso:country":"US",
    "sg:address":"420 Medford St",
    "sg:city":"Somerville",
    "sg:classifiers":[
        {
            "category":"Shopping",
            "subcategory":"Discount & Variety Stores",
            "type":"Retail Goods"
        }
    ],
    "sg:phone":"+1 617 718 0830",
    "sg:postcode":"02145",
    "sg:province":"MA",
    "wof:name":"Hispana American",
    "wof:placetype":"venue"
},
  "geometry": {"coordinates":[-71.09940400000001,42.391321],"type":"Point"}
}