{
  "type": "Feature",
  "properties": {
    "addr:full": "449 Cambridge St Allston MA 02134",
    "addr:housenumber": "449",
    "addr:postcode": "02134",
    "addr:street": "Cambridge St",
    "iso:country": "US",
    "sg:address": "449 Cambridge St",
    "sg:city": "Allston",
    "sg:classifiers": [
      {
        "category": "Wholesale",
        "subcategory": "Furniture",
        "type": "Manufacturing \u0026 Wholesale Goods"
      },
      {
        "category": "Home \u0026 Garden",
        "subcategory": "Furniture",
        "type": "Retail Goods"
      }
    ],
    "sg:phone": "+1 617 562 0388",
    "sg:postcode": "02134",
    "sg:province": "MA",
    "sg:tags": [
      "store",
      "furniture-wholesale",
      "manufacturer"
    ],
    "wof:name": "Century Furniture, Inc.",
    "wof:placetype": "venue"
  },
  "geometry": {"coordinates":[-71.135719,42.354279],"type":"Point"}
}
