{
  "type": "Feature",
  "properties": {
    "iso:country":"US",
    "sg:address":"449 Cambridge St",
    "sg:city":"Allston",
    "sg:classifiers":[
        {
            "category":"Wholesale",
            "subcategory":"Furniture",
            "type":"Manufacturing & Wholesale Goods"
        },
        {
            "category":"Home & Garden",
            "subcategory":"Furniture",
            "type":"Retail Goods"
        }
    ],
    "sg:phone":"+1 617 562 0388",
    "sg:postcode":"02134",
    "sg:province":"MA",
    "sg:tags":[
        "store",
        "furniture-wholesale",
        "manufacturer"
    ],
    "wof:name":"Century Furniture, Inc.",
    "wof:placetype":"venue"
},
  "geometry": {"coordinates":[-71.13571899999999,42.354279],"type":"Point"}
}