{
  "type": "Feature",
  "properties": {
    "iso:country":"US",
    "sg:address":"51 S Main St",
    "sg:city":"New Salem",
    "sg:classifiers":[
        {
            "category":"Professional",
            "type":"Services"
        }
    ],
    "sg:phone":"+1   ",
    "sg:postcode":"01355",
    "sg:province":"MA",
    "wof:name":"Veterans Guild Inc",
    "wof:placetype":"venue"
},
  "geometry": {"coordinates":[-72.33096500000001,42.495357],"type":"Point"}
}