{
  "type": "Feature",
  "properties": {
    "addr:full":"203 Adams St Newton MA 02458",
    "addr:housenumber":"203",
    "addr:postcode":"02458",
    "addr:street":"Adams St",
    "iso:country":"US",
    "sg:address":"203 Adams St",
    "sg:city":"Newton",
    "sg:classifiers":[
        {
            "category":"Restaurant",
            "type":"Food & Drink"
        }
    ],
    "sg:phone":"+1 617 244 8314",
    "sg:postcode":"02458",
    "sg:province":"MA",
    "wof:name":"Francesca Pizzeria Inc",
    "wof:placetype":"venue"
},
  "geometry": {"coordinates":[-71.199997,42.358149],"type":"Point"}
}