{
  "type": "Feature",
  "properties": {
    "addr:full": "71 Dodge St Beverly MA 01915",
    "addr:housenumber": "71",
    "addr:postcode": "01915",
    "addr:street": "Dodge St",
    "iso:country": "US",
    "ovtr:label": "Shaw's Supermarket, 71 Dodge St Beverly MA US",
    "ovtr:similarity": 3.0659708976745605,
    "sg:address": "71 Dodge St",
    "sg:city": "Beverly",
    "sg:classifiers": [
      {
        "category": "Food \u0026 Beverages",
        "subcategory": "Groceries \u0026 Convenience Stores",
        "type": "Retail Goods"
      }
    ],
    "sg:phone": "+1 978 927 4202",
    "sg:postcode": "01915",
    "sg:province": "MA",
    "sg:tags": [
      "grocer"
    ],
    "sg:website": "www.shaws.com",
    "wof:name": "Shaw's Supermarket",
    "wof:placetype": "venue"
  },
  "geometry": {"coordinates":[-70.890402,42.577181],"type":"Point"}
}
