{
  "type": "Feature",
  "properties": {
    "iso:country":"US",
    "sg:address":"325 W Center St",
    "sg:city":"West Bridgewater",
    "sg:classifiers":[
        {
            "category":"Autos & Motor Vehicles",
            "subcategory":"Recreational Vehicle Sales",
            "type":"Retail Goods"
        }
    ],
    "sg:phone":"+1 508 580 5156",
    "sg:postcode":"02379",
    "sg:province":"MA",
    "sg:tags":[
        "canopy",
        "shell",
        "truck",
        "cap"
    ],
    "wof:name":"Line-X Of West Bridgewater",
    "wof:placetype":"venue"
},
  "geometry": {"coordinates":[-71.023985,42.016743],"type":"Point"}
}