{
  "type": "Feature",
  "properties": {
    "iso:country":"US",
    "sg:address":"34 Summer St",
    "sg:city":"Boston",
    "sg:classifiers":[
        {
            "category":"Bars & Pubs",
            "type":"Food & Drink"
        }
    ],
    "sg:phone":"+1 781 444 7771",
    "sg:postcode":"02110",
    "sg:province":"MA",
    "wof:name":"Spring Wine Fest",
    "wof:placetype":"venue"
},
  "geometry": {"coordinates":[-71.059489,42.354713],"type":"Point"}
}