{
  "type": "Feature",
  "properties": {
    "addr:full": "34 Summer St Boston MA 02110",
    "addr:housenumber": "34",
    "addr:postcode": "02110",
    "addr:street": "Summer St",
    "iso:country": "US",
    "sg:address": "34 Summer St",
    "sg:city": "Boston",
    "sg:classifiers": [
      {
        "category": "Bars \u0026 Pubs",
        "type": "Food \u0026 Drink"
      }
    ],
    "sg:phone": "+1 781 444 7771",
    "sg:postcode": "02110",
    "sg:province": "MA",
    "wof:name": "Spring Wine Fest",
    "wof:placetype": "venue"
  },
  "geometry": {"coordinates":[-71.059489,42.354713],"type":"Point"}
}
