{
  "type": "Feature",
  "properties": {
    "addr:full":"724 Main St Hyannis MA 02601",
    "addr:housenumber":"724",
    "addr:postcode":"02601",
    "addr:street":"Main St",
    "iso:country":"US",
    "sg:address":"724 Main St",
    "sg:city":"Hyannis",
    "sg:classifiers":[
        {
            "category":"Professional",
            "subcategory":"Computer Services",
            "type":"Services"
        }
    ],
    "sg:phone":"+1 508 771 2929",
    "sg:postcode":"02601",
    "sg:province":"MA",
    "sg:tags":[
        "repair"
    ],
    "wof:name":"Centerline Computer Service",
    "wof:placetype":"venue"
},
  "geometry": {"coordinates":[-70.29209899999999,41.648701],"type":"Point"}
}