{
  "type": "Feature",
  "properties": {
    "addr:full": "6 Lincoln St Brookfield MA 01506",
    "addr:housenumber": "6",
    "addr:postcode": "01506",
    "addr:street": "Lincoln St",
    "iso:country": "US",
    "sg:address": "6 Lincoln St",
    "sg:city": "Brookfield",
    "sg:classifiers": [
      {
        "category": "Retail",
        "subcategory": "Auto Repair",
        "type": "Services"
      }
    ],
    "sg:phone": "+1 508 867 4800",
    "sg:postcode": "01506",
    "sg:province": "MA",
    "sg:tags": [
      "repairing",
      "automobile"
    ],
    "wof:name": "Inside \u0026 Out Auto",
    "wof:placetype": "venue"
  },
  "geometry": {"coordinates":[-72.10228,42.213591],"type":"Point"}
}
