{
  "type": "Feature",
  "properties": {
    "iso:country":"US",
    "sg:address":"6 Lincoln St",
    "sg:city":"Brookfield",
    "sg:classifiers":[
        {
            "category":"Retail",
            "subcategory":"Auto Repair",
            "type":"Services"
        }
    ],
    "sg:phone":"+1 508 867 4800",
    "sg:postcode":"01506",
    "sg:province":"MA",
    "sg:tags":[
        "repairing",
        "automobile"
    ],
    "wof:name":"Inside & Out Auto",
    "wof:placetype":"venue"
},
  "geometry": {"coordinates":[-72.10227999999999,42.213591],"type":"Point"}
}