{
  "type": "Feature",
  "properties": {
    "iso:country":"US",
    "sg:address":"21 Merchants Row",
    "sg:city":"Boston",
    "sg:classifiers":[
        {
            "category":"Professional",
            "subcategory":"Lawyer & Legal Services",
            "type":"Services"
        }
    ],
    "sg:phone":"+1 617 742 4481",
    "sg:postcode":"02109",
    "sg:province":"MA",
    "sg:tags":[
        "attorney"
    ],
    "wof:name":"Economic Development Assstnc",
    "wof:placetype":"venue"
},
  "geometry": {"coordinates":[-71.055306,42.359141],"type":"Point"}
}