{
  "type": "Feature",
  "properties": {
    "iso:country":"US",
    "sg:address":"376 Highland Ave",
    "sg:city":"Salem",
    "sg:classifiers":[
        {
            "category":"Restaurant",
            "type":"Food & Drink"
        }
    ],
    "sg:phone":"+1 978 741 3883",
    "sg:postcode":"01970",
    "sg:province":"MA",
    "wof:name":"Brother George Place",
    "wof:placetype":"venue"
},
  "geometry": {"coordinates":[-70.93100699999999,42.497599],"type":"Point"}
}