{
  "type": "Feature",
  "properties": {
    "addr:full": "144 Summer St Waltham MA 02452",
    "addr:housenumber": "144",
    "addr:postcode": "02452",
    "addr:street": "Summer St",
    "iso:country": "US",
    "sg:address": "144 Summer St",
    "sg:city": "Waltham",
    "sg:classifiers": [
      {
        "category": "Building \u0026 Trades",
        "subcategory": "Electrical",
        "type": "Services"
      }
    ],
    "sg:phone": "+1 781 893 5379",
    "sg:postcode": "02452",
    "sg:province": "MA",
    "sg:tags": [
      "electric",
      "contractor"
    ],
    "wof:name": "Thomas Le Blanc \u0026 Sons LLP",
    "wof:placetype": "venue"
  },
  "geometry": {"coordinates":[-71.236064,42.380054],"type":"Point"}
}
