{
  "type": "Feature",
  "properties": {
    "addr:full": "133 Littleton Rd Ste 205 Westford MA 01886",
    "addr:housenumber": "133",
    "addr:postcode": "01886",
    "addr:street": "Littleton Rd Ste 205",
    "iso:country": "US",
    "ovtr:label": "Adult \u0026 Pediatric Dermatology, PC, 133 Littleton Rd Westford MA US",
    "ovtr:similarity": 3.3119161128997803,
    "sg:address": "133 Littleton Rd Ste 205",
    "sg:city": "Westford",
    "sg:classifiers": [
      {
        "category": "Health Services",
        "subcategory": "Doctor",
        "type": "Services"
      },
      {
        "category": "Personal",
        "subcategory": "Hair Removal",
        "type": "Services"
      }
    ],
    "sg:phone": "+1 978 692 9978",
    "sg:postcode": "01886",
    "sg:province": "MA",
    "sg:tags": [
      "dermatologist"
    ],
    "sg:website": "www.apderm.com",
    "wof:name": "Adult \u0026 Pediatric Dermatology PC",
    "wof:placetype": "venue"
  },
  "geometry": {"coordinates":[-71.4123,42.570999],"type":"Point"}
}
