{
  "type": "Feature",
  "properties": {
    "iso:country":"US",
    "sg:address":"133 Littleton Rd Ste 205",
    "sg:city":"Westford",
    "sg:classifiers":[
        {
            "category":"Health Services",
            "subcategory":"Doctor",
            "type":"Services"
        },
        {
            "category":"Personal",
            "subcategory":"Hair Removal",
            "type":"Services"
        }
    ],
    "sg:phone":"+1 978 692 9978",
    "sg:postcode":"01886",
    "sg:province":"MA",
    "sg:tags":[
        "dermatologist"
    ],
    "sg:website":"www.apderm.com",
    "wof:name":"Adult & Pediatric Dermatology PC",
    "wof:placetype":"venue"
},
  "geometry": {"coordinates":[-71.4123,42.570999],"type":"Point"}
}