{
  "type": "Feature",
  "properties": {
    "iso:country":"US",
    "sg:address":"67 Broad St Ste 4",
    "sg:city":"Boston",
    "sg:classifiers":[
        {
            "category":"Organizations",
            "subcategory":"Professional Association",
            "type":"Services"
        }
    ],
    "sg:phone":"+1 617 261 4222",
    "sg:postcode":"02109",
    "sg:province":"MA",
    "sg:tags":[
        "business",
        "trade"
    ],
    "wof:name":"Hispanic American Commerce",
    "wof:placetype":"venue"
},
  "geometry": {"coordinates":[-71.053708,42.35784],"type":"Point"}
}