{
  "type": "Feature",
  "properties": {
    "addr:full": "67 Broad St Ste 4 Boston MA 02109",
    "addr:housenumber": "67",
    "addr:postcode": "02109",
    "addr:street": "Broad St Ste 4",
    "iso:country": "US",
    "sg:address": "67 Broad St Ste 4",
    "sg:city": "Boston",
    "sg:classifiers": [
      {
        "category": "Organizations",
        "subcategory": "Professional Association",
        "type": "Services"
      }
    ],
    "sg:phone": "+1 617 261 4222",
    "sg:postcode": "02109",
    "sg:province": "MA",
    "sg:tags": [
      "business",
      "trade"
    ],
    "wof:name": "Hispanic American Commerce",
    "wof:placetype": "venue"
  },
  "geometry": {"coordinates":[-71.053708,42.35784],"type":"Point"}
}
