{
  "type": "Feature",
  "properties": {
    "addr:full":"1156 Massachusetts Ave Cambridge MA 02138",
    "addr:housenumber":"1156",
    "addr:postcode":"02138",
    "addr:street":"Massachusetts Ave",
    "iso:country":"US",
    "sg:address":"1156 Massachusetts Ave",
    "sg:city":"Cambridge",
    "sg:classifiers":[
        {
            "category":"Shopping",
            "subcategory":"Jewelry",
            "type":"Retail Goods"
        }
    ],
    "sg:phone":"+1 617 661 4267",
    "sg:postcode":"02138",
    "sg:province":"MA",
    "sg:website":"www.tayrona1156.com",
    "wof:name":"Tayrona",
    "wof:placetype":"venue"
},
  "geometry": {"coordinates":[-71.114278,42.371124],"type":"Point"}
}