{
  "type": "Feature",
  "properties": {
    "addr:full":"236 Plymouth St Holbrook MA 02343",
    "addr:housenumber":"236",
    "addr:postcode":"02343",
    "addr:street":"Plymouth St",
    "iso:country":"US",
    "sg:address":"236 Plymouth St",
    "sg:city":"Holbrook",
    "sg:classifiers":[
        {
            "category":"Autos & Motor Vehicles",
            "subcategory":"Automobile Sales",
            "type":"Retail Goods"
        }
    ],
    "sg:phone":"+1 781 767 9699",
    "sg:postcode":"02343",
    "sg:province":"MA",
    "sg:tags":[
        "car",
        "dealer"
    ],
    "wof:name":"Stars Auto Sales",
    "wof:placetype":"venue"
},
  "geometry": {"coordinates":[-70.99793200000001,42.152492],"type":"Point"}
}