{
  "type": "Feature",
  "properties": {
    "iso:country":"US",
    "sg:address":"218 Washington St",
    "sg:city":"Brookline",
    "sg:classifiers":[
        {
            "category":"Real Estate",
            "subcategory":"Real Estate Agent",
            "type":"Services"
        }
    ],
    "sg:phone":"+1 617 232 1049",
    "sg:postcode":"02445",
    "sg:province":"MA",
    "wof:name":"Ford Realty",
    "wof:placetype":"venue"
},
  "geometry": {"coordinates":[-71.11819,42.332049],"type":"Point"}
}