{
  "type": "Feature",
  "properties": {
    "addr:full": "100 North St Ste 322 Pittsfield MA 01201",
    "addr:housenumber": "100",
    "addr:postcode": "01201",
    "addr:street": "North St Ste 322",
    "iso:country": "US",
    "sg:address": "100 North St Ste 322",
    "sg:city": "Pittsfield",
    "sg:classifiers": [
      {
        "category": "Health Services",
        "subcategory": "Nursing And Care Facility",
        "type": "Services"
      },
      {
        "category": "Health Services",
        "subcategory": "Health Practitioner",
        "type": "Services"
      }
    ],
    "sg:phone": "+1 413 443 4780",
    "sg:postcode": "01201",
    "sg:province": "MA",
    "sg:tags": [
      "home",
      "eldercare-home"
    ],
    "wof:name": "Specialized Home Care",
    "wof:placetype": "venue"
  },
  "geometry": {"coordinates":[-73.253548,42.449841],"type":"Point"}
}
