{
  "type": "Feature",
  "properties": {
    "iso:country":"US",
    "sg:address":"9 Western Ave",
    "sg:city":"Milford",
    "sg:classifiers":[
        {
            "category":"Personal",
            "type":"Services"
        }
    ],
    "sg:phone":"+1 508 478 0954",
    "sg:postcode":"01757",
    "sg:province":"MA",
    "sg:tags":[
        "electrolysis"
    ],
    "wof:name":"Body Essentials",
    "wof:placetype":"venue"
},
  "geometry": {"coordinates":[-71.54225700000001,42.141875],"type":"Point"}
}