{
  "type": "Feature",
  "properties": {
    "addr:full":"18 Hulbert St Roxbury MA 02119",
    "addr:housenumber":"18",
    "addr:postcode":"02119",
    "addr:street":"Hulbert St",
    "iso:country":"US",
    "sg:address":"18 Hulbert St",
    "sg:city":"Roxbury",
    "sg:classifiers":[
        {
            "category":"Education",
            "subcategory":"School",
            "type":"Public Place"
        }
    ],
    "sg:phone":"+1 617 442 3554",
    "sg:postcode":"02119",
    "sg:province":"MA",
    "wof:name":"Roxbury Charter Hs Student Services Dept",
    "wof:placetype":"venue"
},
  "geometry": {"coordinates":[-71.087898,42.3232],"type":"Point"}
}