{
  "type": "Feature",
  "properties": {
    "addr:full":"101 Mystic Avenue Medford MA 02155",
    "addr:housenumber":"101",
    "addr:postcode":"02155",
    "addr:street":"Mystic Avenue",
    "iso:country":"US",
    "sg:address":"101 Mystic Avenue",
    "sg:city":"Medford",
    "sg:classifiers":[
        {
            "category":"Wholesale",
            "subcategory":"Computers",
            "type":"Manufacturing & Wholesale Goods"
        }
    ],
    "sg:phone":"+1 781 393 9915",
    "sg:postcode":"02155",
    "sg:province":"MA",
    "wof:name":"Axis Microsystems",
    "wof:placetype":"venue"
},
  "geometry": {"coordinates":[-71.10869599999999,42.413495],"type":"Point"}
}