{
  "type": "Feature",
  "properties": {
    "addr:full":"25 Mill St Burlington MA 01803",
    "addr:housenumber":"25",
    "addr:postcode":"01803",
    "addr:street":"Mill St",
    "iso:country":"US",
    "sg:address":"25 Mill St",
    "sg:city":"Burlington",
    "sg:classifiers":[
        {
            "category":"Banks & Credit Unions",
            "subcategory":"Bank",
            "type":"Services"
        }
    ],
    "sg:phone":"+1 781 505 2000",
    "sg:postcode":"01803",
    "sg:province":"MA",
    "sg:tags":[
        "loan",
        "real estate"
    ],
    "wof:name":"Full Spectrum Lending",
    "wof:placetype":"venue"
},
  "geometry": {"coordinates":[-71.192009,42.512123],"type":"Point"}
}