{
  "type": "Feature",
  "properties": {
    "iso:country":"US",
    "sg:address":"967 Patriots Rd",
    "sg:city":"Templeton",
    "sg:classifiers":[
        {
            "category":"Travel",
            "subcategory":"Travel Agent",
            "type":"Entertainment"
        }
    ],
    "sg:phone":"+1 978 939 7777",
    "sg:postcode":"01468",
    "sg:province":"MA",
    "sg:tags":[
        "agency",
        "bureau"
    ],
    "wof:name":"Country Tree Travel",
    "wof:placetype":"venue"
},
  "geometry": {"coordinates":[-72.104204,42.570014],"type":"Point"}
}