{
  "type": "Feature",
  "properties": {
    "addr:full":"1876 Massachusetts Ave Cambridge MA 02140",
    "addr:housenumber":"1876",
    "addr:postcode":"02140",
    "addr:street":"Massachusetts Ave",
    "iso:country":"US",
    "sg:address":"1876 Massachusetts Ave",
    "sg:city":"Cambridge",
    "sg:classifiers":[
        {
            "category":"Food & Beverages",
            "subcategory":"Bakery",
            "type":"Retail Goods"
        }
    ],
    "sg:phone":"+1 617 576 6163",
    "sg:postcode":"02140",
    "sg:province":"MA",
    "sg:tags":[
        "bagel"
    ],
    "sg:website":"www.brueggers.com",
    "wof:name":"Bruegger's Bagel Bakery",
    "wof:placetype":"venue"
},
  "geometry": {"coordinates":[-71.119738,42.388247],"type":"Point"}
}