{
  "type": "Feature",
  "properties": {
    "addr:full": "2000 Main St Brockton MA 02301",
    "addr:housenumber": "2000",
    "addr:postcode": "02301",
    "addr:street": "Main St",
    "iso:country": "US",
    "sg:address": "2000 Main St",
    "sg:city": "Brockton",
    "sg:classifiers": [
      {
        "category": "Autos \u0026 Motor Vehicles",
        "subcategory": "Automobile Sales",
        "type": "Retail Goods"
      }
    ],
    "sg:phone": "+1 508 587 9040",
    "sg:postcode": "02301",
    "sg:province": "MA",
    "sg:tags": [
      "car",
      "dealer"
    ],
    "sg:website": "www.paulclarkcars.com",
    "wof:name": "Paul Clark Inc",
    "wof:placetype": "venue"
  },
  "geometry": {"coordinates":[-71.010851,42.049112],"type":"Point"}
}
