{
  "type": "Feature",
  "properties": {
    "iso:country":"US",
    "sg:address":"42 Hudson St",
    "sg:city":"Quincy",
    "sg:classifiers":[
        {
            "category":"Building & Trades",
            "subcategory":"Construction",
            "type":"Services"
        }
    ],
    "sg:phone":"+1   ",
    "sg:postcode":"02169",
    "sg:province":"MA",
    "sg:tags":[
        "hanging",
        "contractor"
    ],
    "wof:name":"Grant Ward Painting & Wallcove",
    "wof:placetype":"venue"
},
  "geometry": {"coordinates":[-71.006203,42.258655],"type":"Point"}
}