{
  "type": "Feature",
  "properties": {
    "addr:full":"4 Ingraham Ter Swampscott MA 01907",
    "addr:housenumber":"4",
    "addr:postcode":"01907",
    "addr:street":"Ingraham Ter",
    "iso:country":"US",
    "sg:address":"4 Ingraham Ter",
    "sg:city":"Swampscott",
    "sg:classifiers":[
        {
            "category":"Real Estate",
            "subcategory":"Real Estate Agent",
            "type":"Services"
        }
    ],
    "sg:phone":"+1   ",
    "sg:postcode":"01907",
    "sg:province":"MA",
    "wof:name":"Pj Realty Trust",
    "wof:placetype":"venue"
},
  "geometry": {"coordinates":[-70.88774100000001,42.478722],"type":"Point"}
}