{
  "type": "Feature",
  "properties": {
    "iso:country":"US",
    "sg:address":"85 E Main St",
    "sg:city":"West Brookfield",
    "sg:classifiers":[
        {
            "category":"Real Estate",
            "subcategory":"Real Estate Agent",
            "type":"Services"
        }
    ],
    "sg:phone":"+1 508 867 7064",
    "sg:postcode":"01585",
    "sg:province":"MA",
    "sg:website":"www.khosley.com",
    "wof:name":"Toomey-Lovett Inc",
    "wof:placetype":"venue"
},
  "geometry": {"coordinates":[-72.14003,42.235372],"type":"Point"}
}