{
  "type": "Feature",
  "properties": {
    "addr:full":"56 Southwick Rd Westfield MA 01085",
    "addr:housenumber":"56",
    "addr:postcode":"01085",
    "addr:street":"Southwick Rd",
    "iso:country":"US",
    "sg:address":"56 Southwick Rd",
    "sg:city":"Westfield",
    "sg:classifiers":[
        {
            "category":"Personal",
            "subcategory":"Massage",
            "type":"Services"
        },
        {
            "category":"Personal",
            "subcategory":"Beauty Salon",
            "type":"Services"
        },
        {
            "category":"Personal",
            "subcategory":"Barber",
            "type":"Services"
        },
        {
            "category":"Personal",
            "subcategory":"Day Spa",
            "type":"Services"
        },
        {
            "category":"Personal",
            "subcategory":"Tanning Parlor",
            "type":"Services"
        }
    ],
    "sg:phone":"+1 413 568 9000",
    "sg:postcode":"01085",
    "sg:province":"MA",
    "sg:tags":[
        "therapist"
    ],
    "sg:website":"http://www.pufferdayspa.com",
    "wof:name":"Puffer's Salon & Day Spa",
    "wof:placetype":"venue"
},
  "geometry": {"coordinates":[-72.764635,42.109123],"type":"Point"}
}