{
  "type": "Feature",
  "properties": {
    "addr:full": "108 Tanner St Lowell MA 01852",
    "addr:housenumber": "108",
    "addr:postcode": "01852",
    "addr:street": "Tanner St",
    "iso:country": "US",
    "sg:address": "108 Tanner St",
    "sg:city": "Lowell",
    "sg:classifiers": [
      {
        "category": "Wholesale",
        "subcategory": "Auto Parts",
        "type": "Manufacturing \u0026 Wholesale Goods"
      }
    ],
    "sg:phone": "+1 978 454 4444",
    "sg:postcode": "01852",
    "sg:province": "MA",
    "sg:tags": [
      "automobile",
      "rebuilt"
    ],
    "wof:name": "Lowell Used Auto Parts",
    "wof:placetype": "venue"
  },
  "geometry": {"coordinates":[-71.315109,42.629545],"type":"Point"}
}
