{
  "type": "Feature",
  "properties": {
    "iso:country":"US",
    "sg:address":"108 Tanner St",
    "sg:city":"Lowell",
    "sg:classifiers":[
        {
            "category":"Wholesale",
            "subcategory":"Auto Parts",
            "type":"Manufacturing & Wholesale Goods"
        }
    ],
    "sg:phone":"+1 978 454 4444",
    "sg:postcode":"01852",
    "sg:province":"MA",
    "sg:tags":[
        "automobile",
        "rebuilt"
    ],
    "wof:name":"Lowell Used Auto Parts",
    "wof:placetype":"venue"
},
  "geometry": {"coordinates":[-71.31510900000001,42.629545],"type":"Point"}
}