{
  "type": "Feature",
  "properties": {
    "iso:country":"US",
    "sg:address":"30 Sunny Wood Dr",
    "sg:city":"Centerville",
    "sg:classifiers":[
        {
            "category":"Social Services",
            "type":"Services"
        }
    ],
    "sg:phone":"+1   ",
    "sg:postcode":"02632",
    "sg:province":"MA",
    "sg:tags":[
        "individual",
        "family"
    ],
    "wof:name":"Aidan J Walsh",
    "wof:placetype":"venue"
},
  "geometry": {"coordinates":[-70.31564899999999,41.669751],"type":"Point"}
}