{
  "type": "Feature",
  "properties": {
    "iso:country":"US",
    "sg:address":"35 Beach Bluff Ave",
    "sg:city":"Swampscott",
    "sg:classifiers":[
        {
            "category":"Wholesale",
            "subcategory":"Stationery",
            "type":"Manufacturing & Wholesale Goods"
        },
        {
            "category":"Professional",
            "subcategory":"Business Services",
            "type":"Services"
        }
    ],
    "sg:phone":"+1 781 598 4256",
    "sg:postcode":"01907",
    "sg:province":"MA",
    "sg:tags":[
        "system",
        "form"
    ],
    "wof:name":"Belkin Business Systems",
    "wof:placetype":"venue"
},
  "geometry": {"coordinates":[-70.88748200000001,42.479531],"type":"Point"}
}