{
  "type": "Feature",
  "properties": {
    "addr:full": "31 West Ave Kingston MA 02364",
    "addr:housenumber": "31",
    "addr:postcode": "02364",
    "addr:street": "West Ave",
    "iso:country": "US",
    "sg:address": "31 West Ave",
    "sg:city": "Kingston",
    "sg:classifiers": [
      {
        "category": "Building \u0026 Trades",
        "subcategory": "Construction",
        "type": "Services"
      }
    ],
    "sg:phone": "+1 781 878 2312",
    "sg:postcode": "02364",
    "sg:province": "MA",
    "sg:tags": [
      "hanging",
      "contractor"
    ],
    "wof:name": "Decorative Interiors",
    "wof:placetype": "venue"
  },
  "geometry": {"coordinates":[-70.702585,41.993373],"type":"Point"}
}
