{
  "type": "Feature",
  "properties": {
    "addr:full":"11 Long Meadow Rd Westford MA 01886",
    "addr:housenumber":"11",
    "addr:postcode":"01886",
    "addr:street":"Long Meadow Rd",
    "iso:country":"US",
    "sg:address":"11 Long Meadow Rd",
    "sg:city":"Westford",
    "sg:classifiers":[
        {
            "category":"Professional",
            "subcategory":"Management & Consulting",
            "type":"Services"
        }
    ],
    "sg:phone":"+1 978 392 1121",
    "sg:postcode":"01886",
    "sg:province":"MA",
    "sg:tags":[
        "consultant",
        "business"
    ],
    "wof:name":"National Loan Consultants",
    "wof:placetype":"venue"
},
  "geometry": {"coordinates":[-71.458658,42.58732],"type":"Point"}
}