{
  "type": "Feature",
  "properties": {
    "addr:full":"756 Adams St Dorchester MA 02122",
    "addr:housenumber":"756",
    "addr:postcode":"02122",
    "addr:street":"Adams St",
    "iso:country":"US",
    "sg:address":"756 Adams St",
    "sg:city":"Dorchester",
    "sg:classifiers":[
        {
            "category":"Personal",
            "subcategory":"Beauty Salon",
            "type":"Services"
        }
    ],
    "sg:phone":"+1 617 265 3521",
    "sg:postcode":"02122",
    "sg:province":"MA",
    "wof:name":"Village Touch",
    "wof:placetype":"venue"
},
  "geometry": {"coordinates":[-71.05552400000001,42.283876],"type":"Point"}
}