{
  "type": "Feature",
  "properties": {
    "iso:country":"US",
    "sg:address":"69 King St",
    "sg:city":"Hanover",
    "sg:classifiers":[
        {
            "category":"Building & Trades",
            "subcategory":"Construction",
            "type":"Services"
        }
    ],
    "sg:phone":"+1 781 878 8200",
    "sg:postcode":"02339",
    "sg:province":"MA",
    "sg:tags":[
        "excavating",
        "contractor"
    ],
    "wof:name":"Humarock Realty Trust",
    "wof:placetype":"venue"
},
  "geometry": {"coordinates":[-70.877067,42.108584],"type":"Point"}
}