{
  "type": "Feature",
  "properties": {
    "iso:country":"US",
    "sg:address":"356 Central St",
    "sg:city":"Saugus",
    "sg:classifiers":[
        {
            "category":"Education",
            "subcategory":"Special Training",
            "type":"Public Place"
        }
    ],
    "sg:phone":"+1 781 662 6101",
    "sg:postcode":"01906",
    "sg:province":"MA",
    "sg:tags":[
        "instruction",
        "music",
        "instruction-instrumental"
    ],
    "wof:name":"Music 101",
    "wof:placetype":"venue"
},
  "geometry": {"coordinates":[-71.009393,42.461579],"type":"Point"}
}