{
  "type": "Feature",
  "properties": {
    "addr:full":"494 Chestnut St Springfield MA 01107",
    "addr:housenumber":"494",
    "addr:postcode":"01107",
    "addr:street":"Chestnut St",
    "iso:country":"US",
    "sg:address":"494 Chestnut St",
    "sg:city":"Springfield",
    "sg:classifiers":[
        {
            "category":"Retail",
            "subcategory":"Funeral Services",
            "type":"Services"
        }
    ],
    "sg:phone":"+1 413 732 1816",
    "sg:postcode":"01107",
    "sg:province":"MA",
    "sg:tags":[
        "director"
    ],
    "wof:name":"O'Donnell Funeral Home",
    "wof:placetype":"venue"
},
  "geometry": {"coordinates":[-72.598955,42.114573],"type":"Point"}
}