{
  "type": "Feature",
  "properties": {
    "addr:full": "15 Francis Street 1st floor Peter Brent Building, overlooking HMS Bldg. A Boston MA 02115",
    "addr:housenumber": "15;floor",
    "addr:postcode": "02115",
    "addr:street": "Francis Street 1St;Peter",
    "iso:country": "US",
    "sg:address": "15 Francis Street 1st floor Peter Brent Building, overlooking HMS Bldg. A",
    "sg:city": "Boston",
    "sg:classifiers": [
      {
        "category": "Fast Food",
        "type": "Food \u0026 Drink"
      },
      {
        "category": "Restaurant",
        "type": "Food \u0026 Drink"
      },
      {
        "category": "Food \u0026 Beverages",
        "subcategory": "Bakery",
        "type": "Retail Goods"
      }
    ],
    "sg:phone": "+1 617 732 4088",
    "sg:postcode": "02115",
    "sg:province": "MA",
    "sg:tags": [
      "burger",
      "sandwich",
      "diner"
    ],
    "wof:name": "Pat's Place",
    "wof:placetype": "venue"
  },
  "geometry": {"coordinates":[-71.105171,42.334572],"type":"Point"}
}
