{
  "type": "Feature",
  "properties": {
    "addr:full": "160 Marstons Ave Hyannis Port MA 02647",
    "addr:housenumber": "160",
    "addr:postcode": "02647",
    "addr:street": "Marstons Ave",
    "iso:country": "US",
    "ovtr:label": "Harbor Village Cottages, 160 Marston Ave Hyannis MA US",
    "ovtr:similarity": 3.4755449295043945,
    "sg:address": "160 Marstons Ave",
    "sg:city": "Hyannis Port",
    "sg:classifiers": [
      {
        "category": "Travel",
        "subcategory": "Hotels \u0026 Motels",
        "type": "Entertainment"
      }
    ],
    "sg:phone": "+1 508 775 7581",
    "sg:postcode": "02647",
    "sg:province": "MA",
    "wof:name": "Harbor Village Cottages",
    "wof:placetype": "venue"
  },
  "geometry": {"coordinates":[-70.303001,41.632301],"type":"Point"}
}
