{
  "type": "Feature",
  "properties": {
    "iso:country":"US",
    "sg:address":"160 Marstons Ave",
    "sg:city":"Hyannis Port",
    "sg:classifiers":[
        {
            "category":"Travel",
            "subcategory":"Hotels & Motels",
            "type":"Entertainment"
        }
    ],
    "sg:phone":"+1 508 775 7581",
    "sg:postcode":"02647",
    "sg:province":"MA",
    "wof:name":"Harbor Village Cottages",
    "wof:placetype":"venue"
},
  "geometry": {"coordinates":[-70.30300099999999,41.632301],"type":"Point"}
}