{
  "type": "Feature",
  "properties": {
    "addr:full":"230 Hathaway Blvd New Bedford MA 02740",
    "addr:housenumber":"230",
    "addr:postcode":"02740",
    "addr:street":"Hathaway Blvd",
    "iso:country":"US",
    "sg:address":"230 Hathaway Blvd",
    "sg:city":"New Bedford",
    "sg:classifiers":[
        {
            "category":"Government",
            "subcategory":"Office",
            "type":"Public Place"
        }
    ],
    "sg:phone":"+1 508 996 5094",
    "sg:postcode":"02740",
    "sg:province":"MA",
    "sg:tags":[
        "federal",
        "security"
    ],
    "wof:name":"Us Army Junior Rotc",
    "wof:placetype":"venue"
},
  "geometry": {"coordinates":[-70.948797,41.646106],"type":"Point"}
}