{
  "type": "Feature",
  "properties": {
    "iso:country":"US",
    "sg:address":"537 Main St",
    "sg:city":"Indian Orchard",
    "sg:classifiers":[
        {
            "category":"Restaurant",
            "type":"Food & Drink"
        }
    ],
    "sg:phone":"+1 413 543 3225",
    "sg:postcode":"01151",
    "sg:province":"MA",
    "wof:name":"Johnson's Sports Cafe",
    "wof:placetype":"venue"
},
  "geometry": {"coordinates":[-72.48656200000001,42.155575],"type":"Point"}
}