{
  "type": "Feature",
  "properties": {
    "iso:country":"US",
    "sg:address":"82 Winchester St",
    "sg:city":"Newton",
    "sg:classifiers":[
        {
            "category":"Real Estate",
            "subcategory":"Real Estate Agent",
            "type":"Services"
        }
    ],
    "sg:phone":"+1 617 965 4200",
    "sg:postcode":"02461",
    "sg:province":"MA",
    "sg:tags":[
        "management"
    ],
    "sg:website":"www.godinoco.com",
    "wof:name":"Godino & Co",
    "wof:placetype":"venue"
},
  "geometry": {"coordinates":[-71.208743,42.316848],"type":"Point"}
}