{
  "type": "Feature",
  "properties": {
    "addr:full": "30 Bedford St Bridgewater MA 02324",
    "addr:housenumber": "30",
    "addr:postcode": "02324",
    "addr:street": "Bedford St",
    "iso:country": "US",
    "sg:address": "30 Bedford St",
    "sg:city": "Bridgewater",
    "sg:classifiers": [
      {
        "category": "Wholesale",
        "subcategory": "Motor Vehicles",
        "type": "Manufacturing \u0026 Wholesale Goods"
      }
    ],
    "sg:phone": "+1 508 697 5893",
    "sg:postcode": "02324",
    "sg:province": "MA",
    "sg:tags": [
      "body",
      "equipment",
      "truck"
    ],
    "wof:name": "Cotta Truck Equipment",
    "wof:placetype": "venue"
  },
  "geometry": {"coordinates":[-70.976418,41.987951],"type":"Point"}
}
