{
  "type": "Feature",
  "properties": {
    "addr:full": "1269 Massachusetts Ave Dorchester MA 02125",
    "addr:housenumber": "1269",
    "addr:postcode": "02125",
    "addr:street": "Massachusetts Ave",
    "iso:country": "US",
    "sg:address": "1269 Massachusetts Ave",
    "sg:city": "Dorchester",
    "sg:classifiers": [
      {
        "category": "Restaurant",
        "type": "Food \u0026 Drink"
      },
      {
        "category": "Food \u0026 Beverages",
        "subcategory": "Groceries \u0026 Convenience Stores",
        "type": "Retail Goods"
      }
    ],
    "sg:phone": "+1 617 288 9262",
    "sg:postcode": "02125",
    "sg:province": "MA",
    "sg:tags": [
      "shop",
      "sandwich",
      "american",
      "health",
      "italian"
    ],
    "wof:name": "Venetian Garden",
    "wof:placetype": "venue"
  },
  "geometry": {"coordinates":[-71.062596,42.321528],"type":"Point"}
}
