{
  "type": "Feature",
  "properties": {
    "addr:full":"74 Elm St Danvers MA 01923",
    "addr:housenumber":"74",
    "addr:postcode":"01923",
    "addr:street":"Elm St",
    "iso:country":"US",
    "sg:address":"74 Elm St",
    "sg:city":"Danvers",
    "sg:classifiers":[
        {
            "category":"Real Estate",
            "subcategory":"Real Estate Agent",
            "type":"Services"
        }
    ],
    "sg:phone":"+1 978 777 5510",
    "sg:postcode":"01923",
    "sg:province":"MA",
    "wof:name":"Russell Palmer Co Realtors",
    "wof:placetype":"venue"
},
  "geometry": {"coordinates":[-70.936956,42.564291],"type":"Point"}
}