{
  "type": "Feature",
  "properties": {
    "addr:full":"7 Broadway Ave Lawrence MA 01841",
    "addr:housenumber":"7",
    "addr:postcode":"01841",
    "addr:street":"Broadway Ave",
    "iso:country":"US",
    "sg:address":"7 Broadway Ave",
    "sg:city":"Lawrence",
    "sg:classifiers":[
        {
            "category":"Freight",
            "type":"Transportation"
        }
    ],
    "sg:phone":"+1 978 682 4944",
    "sg:postcode":"01841",
    "sg:province":"MA",
    "wof:name":"Mega Transportation",
    "wof:placetype":"venue"
},
  "geometry": {"coordinates":[-71.17524400000001,42.711743],"type":"Point"}
}