{
  "type": "Feature",
  "properties": {
    "iso:country":"US",
    "sg:address":"10 Mansfield Rd",
    "sg:city":"Middleton",
    "sg:classifiers":[
        {
            "category":"Health Services",
            "subcategory":"Nursing And Care Facility",
            "type":"Services"
        }
    ],
    "sg:phone":"+1 978 750 0386",
    "sg:postcode":"01949",
    "sg:province":"MA",
    "sg:tags":[
        "home",
        "rest"
    ],
    "wof:name":"Parentcare USA",
    "wof:placetype":"venue"
},
  "geometry": {"coordinates":[-70.97566999999999,42.599212],"type":"Point"}
}