{
  "type": "Feature",
  "properties": {
    "iso:country":"US",
    "sg:address":"34 Riverside Ave",
    "sg:city":"Somerset",
    "sg:classifiers":[
        {
            "category":"Manufacturing",
            "subcategory":"Watercraft",
            "type":"Manufacturing & Wholesale Goods"
        }
    ],
    "sg:phone":"+1 508 673 5253",
    "sg:postcode":"02725",
    "sg:province":"MA",
    "sg:tags":[
        "boat"
    ],
    "sg:website":"www.fortierboats.com",
    "wof:name":"Fortier Boats",
    "wof:placetype":"venue"
},
  "geometry": {"coordinates":[-71.16115499999999,41.72207],"type":"Point"}
}