{
  "type": "Feature",
  "properties": {
    "addr:full": "34 Riverside Ave Somerset MA 02725",
    "addr:housenumber": "34",
    "addr:postcode": "02725",
    "addr:street": "Riverside Ave",
    "iso:country": "US",
    "sg:address": "34 Riverside Ave",
    "sg:city": "Somerset",
    "sg:classifiers": [
      {
        "category": "Manufacturing",
        "subcategory": "Watercraft",
        "type": "Manufacturing \u0026 Wholesale Goods"
      }
    ],
    "sg:phone": "+1 508 673 5253",
    "sg:postcode": "02725",
    "sg:province": "MA",
    "sg:tags": [
      "boat"
    ],
    "sg:website": "www.fortierboats.com",
    "wof:name": "Fortier Boats",
    "wof:placetype": "venue"
  },
  "geometry": {"coordinates":[-71.161155,41.72207],"type":"Point"}
}
