{
  "type": "Feature",
  "properties": {
    "addr:full": "40 Old Pleasant St Lee MA 01238",
    "addr:housenumber": "40",
    "addr:postcode": "01238",
    "addr:street": "Old Pleasant St",
    "iso:country": "US",
    "sg:address": "40 Old Pleasant St",
    "sg:city": "Lee",
    "sg:classifiers": [
      {
        "category": "Building \u0026 Trades",
        "subcategory": "Construction",
        "type": "Services"
      }
    ],
    "sg:phone": "+1   ",
    "sg:postcode": "01238",
    "sg:province": "MA",
    "sg:tags": [
      "carpentry",
      "contractor"
    ],
    "wof:name": "Stephen Fradley",
    "wof:placetype": "venue"
  },
  "geometry": {"coordinates":[-73.240885,42.294],"type":"Point"}
}
