{
  "type": "Feature",
  "properties": {
    "addr:full":"19 Back River Rd Amesbury MA 01913",
    "addr:housenumber":"19",
    "addr:postcode":"01913",
    "addr:street":"Back River Rd",
    "iso:country":"US",
    "sg:address":"19 Back River Rd",
    "sg:city":"Amesbury",
    "sg:classifiers":[
        {
            "category":"Education",
            "subcategory":"Special Training",
            "type":"Public Place"
        }
    ],
    "sg:phone":"+1 978 388 6995",
    "sg:postcode":"01913",
    "sg:province":"MA",
    "sg:tags":[
        "tutoring"
    ],
    "wof:name":"Kumon Math & Reading Ctr",
    "wof:placetype":"venue"
},
  "geometry": {"coordinates":[-70.91488099999999,42.876262],"type":"Point"}
}