{
  "type": "Feature",
  "properties": {
    "iso:country":"US",
    "sg:address":"45 Schuyler Dr",
    "sg:city":"East Longmeadow",
    "sg:classifiers":[
        {
            "category":"Retail",
            "subcategory":"Repair Shop",
            "type":"Services"
        }
    ],
    "sg:phone":"+1 413 525 0610",
    "sg:postcode":"01028",
    "sg:province":"MA",
    "sg:tags":[
        "related"
    ],
    "wof:name":"Snowboard Factory Inc",
    "wof:placetype":"venue"
},
  "geometry": {"coordinates":[-72.533851,42.052042],"type":"Point"}
}