{
  "type": "Feature",
  "properties": {
    "iso:country":"US",
    "sg:address":"30 Warren St",
    "sg:city":"Brighton",
    "sg:classifiers":[
        {
            "category":"Health Services",
            "subcategory":"Doctor",
            "type":"Services"
        }
    ],
    "sg:phone":"+1   ",
    "sg:postcode":"02135",
    "sg:province":"MA",
    "sg:tags":[
        "medical"
    ],
    "wof:name":"Dr Ronald Rbin Surgeical Assoc",
    "wof:placetype":"venue"
},
  "geometry": {"coordinates":[-71.14456800000001,42.349865],"type":"Point"}
}