{
  "type": "Feature",
  "properties": {
    "addr:full": "20 Overland St Boston MA 02215",
    "addr:housenumber": "20",
    "addr:postcode": "02215",
    "addr:street": "Overland St",
    "iso:country": "US",
    "sg:address": "20 Overland St",
    "sg:city": "Boston",
    "sg:classifiers": [
      {
        "category": "Shopping",
        "subcategory": "Computers \u0026 Home Electronics",
        "type": "Retail Goods"
      }
    ],
    "sg:phone": "+1 617 267 8600",
    "sg:postcode": "02215",
    "sg:province": "MA",
    "sg:tags": [
      "equipment",
      "dealer"
    ],
    "wof:name": "Equipment Remarketing Co",
    "wof:placetype": "venue"
  },
  "geometry": {"coordinates":[-71.100823,42.346572],"type":"Point"}
}
