{
  "type": "Feature",
  "properties": {
    "iso:country":"US",
    "sg:address":"20 Overland St",
    "sg:city":"Boston",
    "sg:classifiers":[
        {
            "category":"Shopping",
            "subcategory":"Computers & Home Electronics",
            "type":"Retail Goods"
        }
    ],
    "sg:phone":"+1 617 267 8600",
    "sg:postcode":"02215",
    "sg:province":"MA",
    "sg:tags":[
        "equipment",
        "dealer"
    ],
    "wof:name":"Equipment Remarketing Co",
    "wof:placetype":"venue"
},
  "geometry": {"coordinates":[-71.10082300000001,42.346572],"type":"Point"}
}