{
  "type": "Feature",
  "properties": {
    "addr:full": "11 Beverly Dr Sterling MA 01564",
    "addr:housenumber": "11",
    "addr:postcode": "01564",
    "addr:street": "Beverly Dr",
    "iso:country": "US",
    "sg:address": "11 Beverly Dr",
    "sg:city": "Sterling",
    "sg:classifiers": [
      {
        "category": "Building \u0026 Trades",
        "subcategory": "Landscaping Services",
        "type": "Services"
      }
    ],
    "sg:phone": "+1 978 422 0002",
    "sg:postcode": "01564",
    "sg:province": "MA",
    "sg:tags": [
      "landscape",
      "contractor"
    ],
    "wof:name": "Pine Fall Landscape",
    "wof:placetype": "venue"
  },
  "geometry": {"coordinates":[-71.74838,42.475506],"type":"Point"}
}
