{
  "type": "Feature",
  "properties": {
    "addr:full": "30 Farnham Rd Rowley MA 01969",
    "addr:housenumber": "30",
    "addr:postcode": "01969",
    "addr:street": "Farnham Rd",
    "iso:country": "US",
    "sg:address": "30 Farnham Rd",
    "sg:city": "Rowley",
    "sg:classifiers": [
      {
        "category": "Home \u0026 Garden",
        "subcategory": "Home Furnishings",
        "type": "Retail Goods"
      }
    ],
    "sg:phone": "+1   ",
    "sg:postcode": "01969",
    "sg:province": "MA",
    "wof:name": "Chef Pampered The",
    "wof:placetype": "venue"
  },
  "geometry": {"coordinates":[-70.935739,42.727252],"type":"Point"}
}
