{
  "type": "Feature",
  "properties": {
    "iso:country":"US",
    "sg:address":"265 Essex St",
    "sg:city":"Salem",
    "sg:classifiers":[
        {
            "category":"Professional",
            "subcategory":"Lawyer & Legal Services",
            "type":"Services"
        }
    ],
    "sg:phone":"+1 978 744 2555",
    "sg:postcode":"01970",
    "sg:province":"MA",
    "sg:tags":[
        "attorney"
    ],
    "wof:name":"Christopher Plunkett PC",
    "wof:placetype":"venue"
},
  "geometry": {"coordinates":[-70.897522,42.521365],"type":"Point"}
}