{
  "type": "Feature",
  "properties": {
    "iso:country":"US",
    "sg:address":"405 Devon Rd",
    "sg:city":"Lee",
    "sg:classifiers":[
        {
            "category":"Government",
            "subcategory":"Office",
            "type":"Public Place"
        }
    ],
    "sg:phone":"+1 413 243 2641",
    "sg:postcode":"01238",
    "sg:province":"MA",
    "sg:tags":[
        "village"
    ],
    "wof:name":"Tyringham Town Office",
    "wof:placetype":"venue"
},
  "geometry": {"coordinates":[-73.27636800000001,42.303741],"type":"Point"}
}