{
  "type": "Feature",
  "properties": {
    "iso:country":"US",
    "sg:address":"711 Atlantic Ave",
    "sg:city":"Boston",
    "sg:classifiers":[
        {
            "category":"Social Services",
            "type":"Services"
        }
    ],
    "sg:phone":"+1 617 424 6616",
    "sg:postcode":"02111",
    "sg:province":"MA",
    "sg:tags":[
        "organization",
        "welfare"
    ],
    "wof:name":"Career Connections",
    "wof:placetype":"venue"
},
  "geometry": {"coordinates":[-71.05646400000001,42.351049],"type":"Point"}
}