{
  "type": "Feature",
  "properties": {
    "iso:country":"US",
    "sg:address":"188 Main St",
    "sg:city":"Wilmington",
    "sg:classifiers":[
        {
            "category":"Professional",
            "subcategory":"Engineering",
            "type":"Services"
        }
    ],
    "sg:phone":"+1 978 657 0555",
    "sg:postcode":"01887",
    "sg:province":"MA",
    "sg:tags":[
        "engineer"
    ],
    "wof:name":"Woodard & Curran Inc",
    "wof:placetype":"venue"
},
  "geometry": {"coordinates":[-71.182181,42.558966],"type":"Point"}
}