{
  "type": "Feature",
  "properties": {
    "addr:full":"246 Providence St Uxbridge MA 01569",
    "addr:housenumber":"246",
    "addr:postcode":"01569",
    "addr:street":"Providence St",
    "iso:country":"US",
    "sg:address":"246 Providence St",
    "sg:city":"Uxbridge",
    "sg:classifiers":[
        {
            "category":"Autos & Motor Vehicles",
            "subcategory":"Auto Supplies",
            "type":"Retail Goods"
        },
        {
            "category":"Retail",
            "subcategory":"Auto Repair",
            "type":"Services"
        }
    ],
    "sg:phone":"+1 508 278 0920",
    "sg:postcode":"01569",
    "sg:province":"MA",
    "sg:tags":[
        "body",
        "repairing",
        "oil",
        "automobile",
        "lube",
        "painting"
    ],
    "wof:name":"Jeff Automotive",
    "wof:placetype":"venue"
},
  "geometry": {"coordinates":[-71.603748,42.025524],"type":"Point"}
}