{
  "type": "Feature",
  "properties": {
    "addr:full":"4 Richmond Ave Worcester MA 01602",
    "addr:housenumber":"4",
    "addr:postcode":"01602",
    "addr:street":"Richmond Ave",
    "iso:country":"US",
    "sg:address":"4 Richmond Ave",
    "sg:city":"Worcester",
    "sg:classifiers":[
        {
            "category":"Retail",
            "subcategory":"Animal Services",
            "type":"Services"
        }
    ],
    "sg:phone":"+1   ",
    "sg:postcode":"01602",
    "sg:province":"MA",
    "wof:name":"Poochies Grooming Salon",
    "wof:placetype":"venue"
},
  "geometry": {"coordinates":[-71.831059,42.275188],"type":"Point"}
}