{
  "type": "Feature",
  "properties": {
    "iso:country":"US",
    "sg:address":"159 Camelot Dr",
    "sg:city":"Plymouth",
    "sg:classifiers":[
        {
            "category":"Government",
            "subcategory":"Office",
            "type":"Public Place"
        }
    ],
    "sg:phone":"+1 508 830 4160",
    "sg:postcode":"02360",
    "sg:province":"MA",
    "sg:tags":[
        "village"
    ],
    "wof:name":"Plymouth Recycling Dept",
    "wof:placetype":"venue"
},
  "geometry": {"coordinates":[-70.64659399999999,41.930431],"type":"Point"}
}