{
  "type": "Feature",
  "properties": {
    "iso:country":"US",
    "sg:address":"24 Braemoor Rd",
    "sg:city":"Brockton",
    "sg:classifiers":[
        {
            "category":"Arts & Performance",
            "subcategory":"Theater",
            "type":"Entertainment"
        }
    ],
    "sg:phone":"+1   ",
    "sg:postcode":"02301",
    "sg:province":"MA",
    "sg:tags":[
        "group"
    ],
    "wof:name":"Kovner Bob Orchestra",
    "wof:placetype":"venue"
},
  "geometry": {"coordinates":[-71.053735,42.073508],"type":"Point"}
}