{
  "type": "Feature",
  "properties": {
    "iso:country":"US",
    "sg:address":"145 Simpson St",
    "sg:city":"Stoughton",
    "sg:classifiers":[
        {
            "category":"Building & Trades",
            "subcategory":"Plumbing",
            "type":"Services"
        }
    ],
    "sg:phone":"+1 781 344 3800",
    "sg:postcode":"02072",
    "sg:province":"MA",
    "wof:name":"Lindelof Plumbing and Heating Inc - CLOSED",
    "wof:placetype":"venue"
},
  "geometry": {"coordinates":[-71.115196,42.128399],"type":"Point"}
}