{
  "type": "Feature",
  "properties": {
    "iso:country":"US",
    "sg:address":"73 Lynn St",
    "sg:city":"Peabody",
    "sg:classifiers":[
        {
            "category":"Retail",
            "subcategory":"Auto Repair",
            "type":"Services"
        }
    ],
    "sg:phone":"+1 978 531 9652",
    "sg:postcode":"01960",
    "sg:province":"MA",
    "sg:tags":[
        "repairing",
        "automobile"
    ],
    "wof:name":"Lynn St Auto Svc",
    "wof:placetype":"venue"
},
  "geometry": {"coordinates":[-70.946882,42.512788],"type":"Point"}
}