{
  "type": "Feature",
  "properties": {
    "addr:full":"1 Grafton Cir Grafton MA 01545",
    "addr:housenumber":"1",
    "addr:postcode":"01545",
    "addr:street":"Grafton Cir",
    "iso:country":"US",
    "sg:address":"1 Grafton Cir",
    "sg:city":"Grafton",
    "sg:classifiers":[
        {
            "category":"Restaurant",
            "type":"Food & Drink"
        }
    ],
    "sg:phone":"+1 508 839 7447",
    "sg:postcode":"01545",
    "sg:province":"MA",
    "sg:tags":[
        "tea",
        "rooms"
    ],
    "wof:name":"Cafe On The Common",
    "wof:placetype":"venue"
},
  "geometry": {"coordinates":[-71.711597,42.279897],"type":"Point"}
}