{
  "type": "Feature",
  "properties": {
    "addr:full":"3 Edgewater Dr, Ste 101 Norwood MA 02062",
    "addr:housenumber":"3",
    "addr:postcode":"02062",
    "addr:street":"Edgewater Dr Ste 101",
    "iso:country":"US",
    "sg:address":"3 Edgewater Dr, Ste 101",
    "sg:city":"Norwood",
    "sg:classifiers":[
        {
            "category":"Banks & Credit Unions",
            "subcategory":"Investment Brokerage",
            "type":"Services"
        },
        {
            "category":"Banks & Credit Unions",
            "subcategory":"Financial Services",
            "type":"Services"
        }
    ],
    "sg:phone":"+1 781 762 6717",
    "sg:postcode":"02062",
    "sg:province":"MA",
    "sg:tags":[
        "investing",
        "advising"
    ],
    "sg:website":"ameripriseadvisors.com",
    "wof:name":"Ameriprise Financial Advisors",
    "wof:placetype":"venue"
},
  "geometry": {"coordinates":[-71.200349,42.160894],"type":"Point"}
}