{
  "type": "Feature",
  "properties": {
    "addr:full":"2556 Main St Brewster MA 02631",
    "addr:housenumber":"2556",
    "addr:postcode":"02631",
    "addr:street":"Main St",
    "iso:country":"US",
    "sg:address":"2556 Main St",
    "sg:city":"Brewster",
    "sg:classifiers":[
        {
            "category":"Freight",
            "type":"Transportation"
        }
    ],
    "sg:phone":"+1 508 430 1402",
    "sg:postcode":"02631",
    "sg:province":"MA",
    "sg:tags":[
        "courier"
    ],
    "wof:name":"Overton Express Courier Svc",
    "wof:placetype":"venue"
},
  "geometry": {"coordinates":[-70.062117,41.765969],"type":"Point"}
}