{
  "type": "Feature",
  "properties": {
    "addr:full":"1207 Salem St Groveland MA 01834",
    "addr:housenumber":"1207",
    "addr:postcode":"01834",
    "addr:street":"Salem St",
    "iso:country":"US",
    "sg:address":"1207 Salem St",
    "sg:city":"Groveland",
    "sg:classifiers":[
        {
            "category":"Restaurant",
            "type":"Food & Drink"
        }
    ],
    "sg:phone":"+1 978 374 8793",
    "sg:postcode":"01834",
    "sg:province":"MA",
    "wof:name":"Bobby's Barn",
    "wof:placetype":"venue"
},
  "geometry": {"coordinates":[-71.01599,42.735745],"type":"Point"}
}