{
  "type": "Feature",
  "properties": {
    "addr:full":"18 Powder House Ter Medford MA 02155",
    "addr:housenumber":"18",
    "addr:postcode":"02155",
    "addr:street":"Powder;Ter",
    "iso:country":"US",
    "sg:address":"18 Powder House Ter",
    "sg:city":"Medford",
    "sg:classifiers":[
        {
            "category":"Professional",
            "subcategory":"Business Services",
            "type":"Services"
        }
    ],
    "sg:phone":"+1   ",
    "sg:postcode":"02155",
    "sg:province":"MA",
    "wof:name":"King & Assoc Inc",
    "wof:placetype":"venue"
},
  "geometry": {"coordinates":[-71.113703,42.422796],"type":"Point"}
}