{
  "type": "Feature",
  "properties": {
    "iso:country":"US",
    "sg:address":"48 Federal St",
    "sg:city":"Belchertown",
    "sg:classifiers":[
        {
            "category":"Food & Beverages",
            "subcategory":"Groceries & Convenience Stores",
            "type":"Retail Goods"
        }
    ],
    "sg:phone":"+1 413 323 9344",
    "sg:postcode":"01007",
    "sg:province":"MA",
    "wof:name":"Country Crossroads Convenience",
    "wof:placetype":"venue"
},
  "geometry": {"coordinates":[-72.409398,42.29167],"type":"Point"}
}