{
  "type": "Feature",
  "properties": {
    "addr:full": "48 Federal St Belchertown MA 01007",
    "addr:housenumber": "48",
    "addr:postcode": "01007",
    "addr:street": "Federal St",
    "iso:country": "US",
    "sg:address": "48 Federal St",
    "sg:city": "Belchertown",
    "sg:classifiers": [
      {
        "category": "Food \u0026 Beverages",
        "subcategory": "Groceries \u0026 Convenience Stores",
        "type": "Retail Goods"
      }
    ],
    "sg:phone": "+1 413 323 9344",
    "sg:postcode": "01007",
    "sg:province": "MA",
    "wof:name": "Country Crossroads Convenience",
    "wof:placetype": "venue"
  },
  "geometry": {"coordinates":[-72.409398,42.29167],"type":"Point"}
}
