{
  "type": "Feature",
  "properties": {
    "iso:country":"US",
    "sg:address":"155 New Boston St",
    "sg:city":"Woburn",
    "sg:classifiers":[
        {
            "category":"Manufacturing",
            "subcategory":"Metals",
            "type":"Manufacturing & Wholesale Goods"
        }
    ],
    "sg:phone":"+1 781 932 9520",
    "sg:postcode":"01801",
    "sg:province":"MA",
    "sg:tags":[
        "fabricator",
        "sheet"
    ],
    "wof:name":"Bellingham Sheet Metal",
    "wof:placetype":"venue"
},
  "geometry": {"coordinates":[-71.143877,42.509411],"type":"Point"}
}