{
  "type": "Feature",
  "properties": {
    "iso:country":"US",
    "sg:address":"835 Temple St",
    "sg:city":"Whitman",
    "sg:classifiers":[
        {
            "category":"Freight",
            "type":"Transportation"
        }
    ],
    "sg:phone":"+1 781 447 3440",
    "sg:postcode":"02382",
    "sg:province":"MA",
    "sg:tags":[
        "commercial",
        "storage"
    ],
    "wof:name":"Route 27 Discount Storage",
    "wof:placetype":"venue"
},
  "geometry": {"coordinates":[-70.967534,42.081983],"type":"Point"}
}