{
  "type": "Feature",
  "properties": {
    "addr:full": "7 Riverview Ave Maynard MA 01754",
    "addr:housenumber": "7",
    "addr:postcode": "01754",
    "addr:street": "Riverview Ave",
    "iso:country": "US",
    "sg:address": "7 Riverview Ave",
    "sg:city": "Maynard",
    "sg:classifiers": [
      {
        "category": "Personal",
        "type": "Services"
      }
    ],
    "sg:phone": "+1 978 263 3254",
    "sg:postcode": "01754",
    "sg:province": "MA",
    "sg:tags": [
      "assistant"
    ],
    "sg:website": "http://www.voicesofmen.org",
    "wof:name": "Ben Atherton-Zeman",
    "wof:placetype": "venue"
  },
  "geometry": {"coordinates":[-71.473761,42.426919],"type":"Point"}
}
