{
  "type": "Feature",
  "properties": {
    "iso:country":"US",
    "sg:address":"120 Patch Hill Rd",
    "sg:city":"Acton",
    "sg:classifiers":[
        {
            "category":"Professional",
            "subcategory":"Management & Consulting",
            "type":"Services"
        }
    ],
    "sg:phone":"+1   ",
    "sg:postcode":"01719",
    "sg:province":"MA",
    "wof:name":"Sordill Consulting",
    "wof:placetype":"venue"
},
  "geometry": {"coordinates":[-71.504761,42.493924],"type":"Point"}
}