{
  "type": "Feature",
  "properties": {
    "addr:full": "87 Lafayette Rd Salisbury MA 01952",
    "addr:housenumber": "87",
    "addr:postcode": "01952",
    "iso:country": "US",
    "sg:address": "87 Lafayette Rd",
    "sg:city": "Salisbury",
    "sg:classifiers": [
      {
        "category": "Retail",
        "subcategory": "Portrait Studio",
        "type": "Services"
      },
      {
        "category": "Professional",
        "subcategory": "Art Services",
        "type": "Services"
      }
    ],
    "sg:phone": "+1 978 465 6296",
    "sg:postcode": "01952",
    "sg:province": "MA",
    "sg:tags": [
      "rental",
      "photographers-portrait",
      "photographic",
      "darkroom"
    ],
    "wof:name": "Sullivan Studio",
    "wof:placetype": "venue"
  },
  "geometry": {"coordinates":[-70.868217,42.852203],"type":"Point"}
}
