{
  "type": "Feature",
  "properties": {
    "iso:country":"US",
    "sg:address":"365 Lowell Ave",
    "sg:city":"Haverhill",
    "sg:classifiers":[
        {
            "category":"Wholesale",
            "subcategory":"Machinery & Supplies",
            "type":"Manufacturing & Wholesale Goods"
        }
    ],
    "sg:phone":"+1 978 374 0141",
    "sg:postcode":"01832",
    "sg:province":"MA",
    "sg:tags":[
        "equipment",
        "welding"
    ],
    "sg:website":"www.middlesexgases.com",
    "wof:name":"Middlesex Gases & Technologies",
    "wof:placetype":"venue"
},
  "geometry": {"coordinates":[-71.11696499999999,42.775692],"type":"Point"}
}