{
  "type": "Feature",
  "properties": {
    "iso:country":"US",
    "sg:address":"128 Meadow St",
    "sg:city":"Westfield",
    "sg:classifiers":[
        {
            "category":"Retail",
            "subcategory":"Auto Repair",
            "type":"Services"
        }
    ],
    "sg:phone":"+1 413 568 0151",
    "sg:postcode":"01085",
    "sg:province":"MA",
    "sg:tags":[
        "repairing",
        "automobile"
    ],
    "wof:name":"Ken Fife's Westfield Svc Ctr",
    "wof:placetype":"venue"
},
  "geometry": {"coordinates":[-72.740826,42.123112],"type":"Point"}
}