{
  "type": "Feature",
  "properties": {
    "iso:country":"US",
    "sg:address":"19 Belmont St",
    "sg:city":"South Easton",
    "sg:classifiers":[
        {
            "category":"Insurance",
            "subcategory":"Insurance Agent",
            "type":"Services"
        }
    ],
    "sg:phone":"+1 508 238 0181",
    "sg:postcode":"02375",
    "sg:province":"MA",
    "wof:name":"Hackwell-Boone Insurance",
    "wof:placetype":"venue"
},
  "geometry": {"coordinates":[-71.082932,42.049875],"type":"Point"}
}