{
  "type": "Feature",
  "properties": {
    "iso:country":"US",
    "sg:address":"400 High Street",
    "sg:city":"Medford",
    "sg:classifiers":[
        {
            "category":"Social Services",
            "subcategory":"Child Care",
            "type":"Services"
        },
        {
            "category":"Sports & Exercise",
            "subcategory":"Gym",
            "type":"Entertainment"
        }
    ],
    "sg:phone":"+1 781 395 5320",
    "sg:postcode":"02155",
    "sg:province":"MA",
    "sg:tags":[
        "trainer",
        "day"
    ],
    "wof:name":"Bright Stars Afterschool Program",
    "wof:placetype":"venue"
},
  "geometry": {"coordinates":[-71.129727,42.421426],"type":"Point"}
}