{
  "type": "Feature",
  "properties": {
    "iso:country":"US",
    "sg:address":"85 Central St",
    "sg:city":"Waltham",
    "sg:classifiers":[
        {
            "category":"Insurance",
            "subcategory":"Insurance Agent",
            "type":"Services"
        }
    ],
    "sg:phone":"+1 781 647 3790",
    "sg:postcode":"02453",
    "sg:province":"MA",
    "sg:tags":[
        "processing"
    ],
    "wof:name":"Professional Office Management",
    "wof:placetype":"venue"
},
  "geometry": {"coordinates":[-71.233808,42.375226],"type":"Point"}
}