{
  "type": "Feature",
  "properties": {
    "addr:full": "235 W Boylston St West Boylston MA 01583",
    "addr:housenumber": "235",
    "addr:postcode": "01583",
    "addr:street": "W Boylston St",
    "iso:country": "US",
    "sg:address": "235 W Boylston St",
    "sg:city": "West Boylston",
    "sg:classifiers": [
      {
        "category": "Building \u0026 Trades",
        "subcategory": "Plumbing",
        "type": "Services"
      }
    ],
    "sg:phone": "+1 508 835 1676",
    "sg:postcode": "01583",
    "sg:province": "MA",
    "sg:tags": [
      "heating",
      "contractor",
      "air",
      "system",
      "conditioning"
    ],
    "wof:name": "Complete Heating \u0026 AC SYST",
    "wof:placetype": "venue"
  },
  "geometry": {"coordinates":[-71.78683,42.345589],"type":"Point"}
}
