{
  "type": "Feature",
  "properties": {
    "iso:country":"US",
    "sg:address":"235 W Boylston St",
    "sg:city":"West Boylston",
    "sg:classifiers":[
        {
            "category":"Building & Trades",
            "subcategory":"Plumbing",
            "type":"Services"
        }
    ],
    "sg:phone":"+1 508 835 1676",
    "sg:postcode":"01583",
    "sg:province":"MA",
    "sg:tags":[
        "heating",
        "contractor",
        "air",
        "system",
        "conditioning"
    ],
    "wof:name":"Complete Heating & AC SYST",
    "wof:placetype":"venue"
},
  "geometry": {"coordinates":[-71.78682999999999,42.345589],"type":"Point"}
}