{
  "type": "Feature",
  "properties": {
    "iso:country":"US",
    "sg:address":"627 N Westfield St",
    "sg:city":"Feeding Hills",
    "sg:classifiers":[
        {
            "category":"Retail",
            "subcategory":"Animal Services",
            "type":"Services"
        }
    ],
    "sg:phone":"+1 413 786 5633",
    "sg:postcode":"01030",
    "sg:province":"MA",
    "sg:tags":[
        "pet",
        "boarding",
        "sitting"
    ],
    "wof:name":"Berlyd Acres Boarding Kennels",
    "wof:placetype":"venue"
},
  "geometry": {"coordinates":[-72.683125,42.088285],"type":"Point"}
}