{
  "type": "Feature",
  "properties": {
    "addr:full":"365 Concord St Rockland MA 02370",
    "addr:housenumber":"365",
    "addr:postcode":"02370",
    "addr:street":"Concord St",
    "iso:country":"US",
    "sg:address":"365 Concord St",
    "sg:city":"Rockland",
    "sg:classifiers":[
        {
            "category":"Real Estate",
            "subcategory":"Architect",
            "type":"Services"
        }
    ],
    "sg:phone":"+1 781 871 7816",
    "sg:postcode":"02370",
    "sg:province":"MA",
    "sg:tags":[
        "estimate",
        "construction"
    ],
    "wof:name":"Dandel Construction",
    "wof:placetype":"venue"
},
  "geometry": {"coordinates":[-70.90463099999999,42.11373],"type":"Point"}
}