{
  "type": "Feature",
  "properties": {
    "iso:country":"US",
    "sg:address":"12 Clarendon St",
    "sg:city":"Boston",
    "sg:classifiers":[
        {
            "category":"Personal",
            "subcategory":"Massage",
            "type":"Services"
        },
        {
            "category":"Health Services",
            "subcategory":"Health Practitioner",
            "type":"Services"
        }
    ],
    "sg:phone":"+1 617 290 1490",
    "sg:postcode":"02116",
    "sg:province":"MA",
    "sg:tags":[
        "therapy",
        "physical"
    ],
    "sg:website":"www.craigfauchermassage.com",
    "wof:name":"CDF Therapeutic Bodywork",
    "wof:placetype":"venue"
},
  "geometry": {"coordinates":[-71.07235,42.344679],"type":"Point"}
}