{
  "type": "Feature",
  "properties": {
    "addr:full": "60 Nowell Rd Melrose MA 02176",
    "addr:housenumber": "60",
    "addr:postcode": "02176",
    "addr:street": "Nowell Rd",
    "iso:country": "US",
    "sg:address": "60 Nowell Rd",
    "sg:city": "Melrose",
    "sg:classifiers": [
      {
        "category": "Building \u0026 Trades",
        "subcategory": "Landscaping Services",
        "type": "Services"
      }
    ],
    "sg:phone": "+1   ",
    "sg:postcode": "02176",
    "sg:province": "MA",
    "wof:name": "Holmen Landscaping",
    "wof:placetype": "venue"
  },
  "geometry": {"coordinates":[-71.064246,42.471263],"type":"Point"}
}
