{
  "type": "Feature",
  "properties": {
    "iso:country":"US",
    "sg:address":"60 Nowell Rd",
    "sg:city":"Melrose",
    "sg:classifiers":[
        {
            "category":"Building & Trades",
            "subcategory":"Landscaping Services",
            "type":"Services"
        }
    ],
    "sg:phone":"+1   ",
    "sg:postcode":"02176",
    "sg:province":"MA",
    "wof:name":"Holmen Landscaping",
    "wof:placetype":"venue"
},
  "geometry": {"coordinates":[-71.064246,42.471263],"type":"Point"}
}