{
  "type": "Feature",
  "properties": {
    "iso:country":"US",
    "sg:address":"151 Country Dr",
    "sg:city":"Weston",
    "sg:classifiers":[
        {
            "category":"Restaurant",
            "type":"Food & Drink"
        }
    ],
    "sg:phone":"+1 781 893 3718",
    "sg:postcode":"02493",
    "sg:province":"MA",
    "wof:name":"Flying Star Inc",
    "wof:placetype":"venue"
},
  "geometry": {"coordinates":[-71.327941,42.337143],"type":"Point"}
}