{
  "type": "Feature",
  "properties": {
    "iso:country":"US",
    "sg:address":"121 Main St",
    "sg:city":"South Grafton",
    "sg:classifiers":[
        {
            "category":"Building & Trades",
            "subcategory":"Construction",
            "type":"Services"
        }
    ],
    "sg:phone":"+1 508 839 0610",
    "sg:postcode":"01560",
    "sg:province":"MA",
    "sg:tags":[
        "excavating",
        "contractor"
    ],
    "wof:name":"Seaver Brothers Construction",
    "wof:placetype":"venue"
},
  "geometry": {"coordinates":[-71.70032399999999,42.178163],"type":"Point"}
}