{
  "type": "Feature",
  "properties": {
    "addr:full": "121 Main St South Grafton MA 01560",
    "addr:housenumber": "121",
    "addr:postcode": "01560",
    "addr:street": "Main St",
    "iso:country": "US",
    "sg:address": "121 Main St",
    "sg:city": "South Grafton",
    "sg:classifiers": [
      {
        "category": "Building \u0026 Trades",
        "subcategory": "Construction",
        "type": "Services"
      }
    ],
    "sg:phone": "+1 508 839 0610",
    "sg:postcode": "01560",
    "sg:province": "MA",
    "sg:tags": [
      "excavating",
      "contractor"
    ],
    "wof:name": "Seaver Brothers Construction",
    "wof:placetype": "venue"
  },
  "geometry": {"coordinates":[-71.700324,42.178163],"type":"Point"}
}
