{
  "type": "Feature",
  "properties": {
    "addr:full":"685 Beaver St Waltham MA 02452",
    "addr:housenumber":"685",
    "addr:postcode":"02452",
    "addr:street":"Beaver St",
    "iso:country":"US",
    "sg:address":"685 Beaver St",
    "sg:city":"Waltham",
    "sg:classifiers":[
        {
            "category":"Professional",
            "subcategory":"Secretarial Services",
            "type":"Services"
        }
    ],
    "sg:phone":"+1 781 647 5517",
    "sg:postcode":"02452",
    "sg:province":"MA",
    "sg:tags":[
        "reporting",
        "word",
        "processing"
    ],
    "wof:name":"ASAP Transcription Services",
    "wof:placetype":"venue"
},
  "geometry": {"coordinates":[-71.23168800000001,42.384749],"type":"Point"}
}