{
  "type": "Feature",
  "properties": {
    "addr:full": "77 Linwood St Malden MA 02148",
    "addr:housenumber": "77",
    "addr:postcode": "02148",
    "addr:street": "Linwood St",
    "iso:country": "US",
    "sg:address": "77 Linwood St",
    "sg:city": "Malden",
    "sg:classifiers": [
      {
        "category": "Building \u0026 Trades",
        "subcategory": "Cleaning \u0026 Sanitation",
        "type": "Services"
      }
    ],
    "sg:phone": "+1 781 322 7517",
    "sg:postcode": "02148",
    "sg:province": "MA",
    "sg:tags": [
      "house"
    ],
    "wof:name": "M D Cleaning Svc",
    "wof:placetype": "venue"
  },
  "geometry": {"coordinates":[-71.058881,42.424894],"type":"Point"}
}
