{
  "type": "Feature",
  "properties": {
    "addr:full":"21 Taylor St Quincy MA 02170",
    "addr:housenumber":"21",
    "addr:postcode":"02170",
    "addr:street":"Taylor St",
    "iso:country":"US",
    "sg:address":"21 Taylor St",
    "sg:city":"Quincy",
    "sg:classifiers":[
        {
            "category":"Professional",
            "type":"Services"
        }
    ],
    "sg:phone":"+1   ",
    "sg:postcode":"02170",
    "sg:province":"MA",
    "wof:name":"Paul Panarelli",
    "wof:placetype":"venue"
},
  "geometry": {"coordinates":[-71.028065,42.268136],"type":"Point"}
}