{
  "type": "Feature",
  "properties": {
    "iso:country":"US",
    "sg:address":"197 Plainfield St",
    "sg:city":"Springfield",
    "sg:classifiers":[
        {
            "category":"Retail",
            "subcategory":"Car Wash",
            "type":"Services"
        }
    ],
    "sg:phone":"+1 413 732 6661",
    "sg:postcode":"01107",
    "sg:province":"MA",
    "sg:tags":[
        "automobile",
        "detail",
        "clean"
    ],
    "wof:name":"A G Auto Detailing",
    "wof:placetype":"venue"
},
  "geometry": {"coordinates":[-72.610033,42.112431],"type":"Point"}
}