{
  "type": "Feature",
  "properties": {
    "addr:full":"1245 Bernardston Rd Greenfield MA 01301",
    "addr:housenumber":"1245",
    "addr:postcode":"01301",
    "addr:street":"Bernardston Rd",
    "iso:country":"US",
    "sg:address":"1245 Bernardston Rd",
    "sg:city":"Greenfield",
    "sg:classifiers":[
        {
            "category":"Shopping",
            "subcategory":"Gifts & Souvenirs",
            "type":"Retail Goods"
        }
    ],
    "sg:phone":"+1   ",
    "sg:postcode":"01301",
    "sg:province":"MA",
    "sg:tags":[
        "sewing",
        "hob"
    ],
    "wof:name":"Bears Paw Quilts Cntry Crafts",
    "wof:placetype":"venue"
},
  "geometry": {"coordinates":[-72.564131,42.643758],"type":"Point"}
}