{
  "type": "Feature",
  "properties": {
    "addr:full": "88 Central St Rockland MA 02370",
    "addr:housenumber": "88",
    "addr:postcode": "02370",
    "addr:street": "Central St",
    "iso:country": "US",
    "sg:address": "88 Central St",
    "sg:city": "Rockland",
    "sg:classifiers": [
      {
        "category": "Wholesale",
        "subcategory": "Medical Equipment \u0026 Supplies",
        "type": "Manufacturing \u0026 Wholesale Goods"
      }
    ],
    "sg:phone": "+1 781 982 1415",
    "sg:postcode": "02370",
    "sg:province": "MA",
    "sg:tags": [
      "optical"
    ],
    "wof:name": "Massachusetts Ophthalmics Inc",
    "wof:placetype": "venue"
  },
  "geometry": {"coordinates":[-70.926989,42.11595],"type":"Point"}
}
