{
  "type": "Feature",
  "properties": {
    "iso:country":"US",
    "sg:address":"88 Central St",
    "sg:city":"Rockland",
    "sg:classifiers":[
        {
            "category":"Wholesale",
            "subcategory":"Medical Equipment & Supplies",
            "type":"Manufacturing & Wholesale Goods"
        }
    ],
    "sg:phone":"+1 781 982 1415",
    "sg:postcode":"02370",
    "sg:province":"MA",
    "sg:tags":[
        "optical"
    ],
    "wof:name":"Massachusetts Ophthalmics Inc",
    "wof:placetype":"venue"
},
  "geometry": {"coordinates":[-70.92698900000001,42.11595],"type":"Point"}
}