{
  "type": "Feature",
  "properties": {
    "addr:full": "115 W Boylston St West Boylston MA 01583",
    "addr:housenumber": "115",
    "addr:postcode": "01583",
    "addr:street": "W Boylston St",
    "iso:country": "US",
    "sg:address": "115 W Boylston St",
    "sg:city": "West Boylston",
    "sg:classifiers": [
      {
        "category": "Shopping",
        "subcategory": "Hobbies, Toys, \u0026 Games",
        "type": "Retail Goods"
      }
    ],
    "sg:phone": "+1 508 835 4229",
    "sg:postcode": "01583",
    "sg:province": "MA",
    "sg:tags": [
      "supply"
    ],
    "wof:name": "EB Games",
    "wof:placetype": "venue"
  },
  "geometry": {"coordinates":[-71.784731,42.353603],"type":"Point"}
}
