{
  "type": "Feature",
  "properties": {
    "addr:full":"560 Riverglade Dr Apt K Amherst MA 01002",
    "addr:housenumber":"560",
    "addr:postcode":"01002",
    "addr:street":"Riverglade Dr Apt K",
    "iso:country":"US",
    "sg:address":"560 Riverglade Dr Apt K",
    "sg:city":"Amherst",
    "sg:classifiers":[
        {
            "category":"Wholesale",
            "subcategory":"Machinery & Supplies",
            "type":"Manufacturing & Wholesale Goods"
        }
    ],
    "sg:phone":"+1 413 896 7495",
    "sg:postcode":"01002",
    "sg:province":"MA",
    "sg:tags":[
        "equipment",
        "irrigation",
        "system"
    ],
    "wof:name":"Redmond Irrigation And Bu",
    "wof:placetype":"venue"
},
  "geometry": {"coordinates":[-72.527058,42.346883],"type":"Point"}
}