{
  "type": "Feature",
  "properties": {
    "iso:country":"US",
    "sg:address":"11 Robbie Rd",
    "sg:city":"Avon",
    "sg:classifiers":[
        {
            "category":"Wholesale",
            "subcategory":"Electrical",
            "type":"Manufacturing & Wholesale Goods"
        }
    ],
    "sg:phone":"+1 508 584 9010",
    "sg:postcode":"02322",
    "sg:province":"MA",
    "sg:tags":[
        "equipment",
        "electric",
        "supply"
    ],
    "sg:website":"www.controllerservice.com",
    "wof:name":"Controller Service & Sales Inc",
    "wof:placetype":"venue"
},
  "geometry": {"coordinates":[-71.060787,42.130656],"type":"Point"}
}