{
  "type": "Feature",
  "properties": {
    "addr:full": "11 Robbie Rd Avon MA 02322",
    "addr:housenumber": "11",
    "addr:postcode": "02322",
    "addr:street": "Robbie Rd",
    "iso:country": "US",
    "sg:address": "11 Robbie Rd",
    "sg:city": "Avon",
    "sg:classifiers": [
      {
        "category": "Wholesale",
        "subcategory": "Electrical",
        "type": "Manufacturing \u0026 Wholesale Goods"
      }
    ],
    "sg:phone": "+1 508 584 9010",
    "sg:postcode": "02322",
    "sg:province": "MA",
    "sg:tags": [
      "equipment",
      "electric",
      "supply"
    ],
    "sg:website": "www.controllerservice.com",
    "wof:name": "Controller Service \u0026 Sales Inc",
    "wof:placetype": "venue"
  },
  "geometry": {"coordinates":[-71.060787,42.130656],"type":"Point"}
}
