{
  "type": "Feature",
  "properties": {
    "addr:full":"17 Newcastle Rd Ashland MA 01721",
    "addr:housenumber":"17",
    "addr:postcode":"01721",
    "addr:street":"Newcastle Rd",
    "iso:country":"US",
    "sg:address":"17 Newcastle Rd",
    "sg:city":"Ashland",
    "sg:classifiers":[
        {
            "category":"Communications",
            "subcategory":"Film & Video Production",
            "type":"Services"
        }
    ],
    "sg:phone":"+1 508 881 4211",
    "sg:postcode":"01721",
    "sg:province":"MA",
    "sg:tags":[
        "television",
        "producer"
    ],
    "wof:name":"MJN Productions Inc",
    "wof:placetype":"venue"
},
  "geometry": {"coordinates":[-71.452277,42.243989],"type":"Point"}
}