{
  "type": "Feature",
  "properties": {
    "addr:full":"148 Harvard Rd Bolton MA 01740",
    "addr:housenumber":"148",
    "addr:postcode":"01740",
    "addr:street":"Harvard Rd",
    "iso:country":"US",
    "sg:address":"148 Harvard Rd",
    "sg:city":"Bolton",
    "sg:classifiers":[
        {
            "category":"Utilities",
            "subcategory":"Telephone",
            "type":"Services"
        }
    ],
    "sg:phone":"+1   ",
    "sg:postcode":"01740",
    "sg:province":"MA",
    "sg:tags":[
        "communications"
    ],
    "wof:name":"Bob Plaskon",
    "wof:placetype":"venue"
},
  "geometry": {"coordinates":[-71.614339,42.438229],"type":"Point"}
}