{
  "type": "Feature",
  "properties": {
    "iso:country":"US",
    "sg:address":"66 Church Green",
    "sg:city":"Taunton",
    "sg:classifiers":[
        {
            "category":"Museum",
            "type":"Entertainment"
        }
    ],
    "sg:phone":"+1 508 822 1622",
    "sg:postcode":"02780",
    "sg:province":"MA",
    "wof:name":"Old Colony Historical Society",
    "wof:placetype":"venue"
},
  "geometry": {"coordinates":[-71.087042,41.901517],"type":"Point"}
}