{
  "type": "Feature",
  "properties": {
    "addr:city": "Taunton",
    "addr:full": "66 Church Grn Taunton, Ma 02780-3445",
    "addr:house_number": "66",
    "addr:housenumber": "66",
    "addr:phone": "+1 508-822-1622",
    "addr:postcode": "02780-3445",
    "addr:road": "Church Grn",
    "addr:state": "MA",
    "addr:street": "Church Green",
    "ilms:label": "OLD COLONY HISTORICAL SOCIETY, 66 CHURCH GRN TAUNTON MA 02780-3445",
    "ilms:similarity": 1.0391390323638916,
    "iso:country": "US",
    "sg:address": "66 Church Green",
    "sg:city": "Taunton",
    "sg:classifiers": [
      {
        "category": "Museum",
        "type": "Entertainment"
      }
    ],
    "sg:phone": "+1 508 822 1622",
    "sg:postcode": "02780",
    "sg:province": "MA",
    "wof:name": "Old Colony Historical Society",
    "wof:placetype": "venue"
  },
  "geometry": {"coordinates":[-71.08715,41.90158],"type":"Point"}
}
