{
  "type": "Feature",
  "properties": {
    "iso:country":"US",
    "sg:address":"306 Dartmouth St Ste 5",
    "sg:city":"Boston",
    "sg:classifiers":[
        {
            "category":"Real Estate",
            "subcategory":"Real Estate Services",
            "type":"Services"
        },
        {
            "category":"Real Estate",
            "subcategory":"Real Estate Agent",
            "type":"Services"
        }
    ],
    "sg:phone":"+1 617 292 0899",
    "sg:postcode":"02116",
    "sg:province":"MA",
    "sg:tags":[
        "management"
    ],
    "wof:name":"Leon Limited Inc",
    "wof:placetype":"venue"
},
  "geometry": {"coordinates":[-71.078491,42.352459],"type":"Point"}
}