{
  "type": "Feature",
  "properties": {
    "addr:full":"55 Main St Medfield MA 02052",
    "addr:housenumber":"55",
    "addr:postcode":"02052",
    "addr:street":"Main St",
    "iso:country":"US",
    "sg:address":"55 Main St",
    "sg:city":"Medfield",
    "sg:classifiers":[
        {
            "category":"Shopping",
            "subcategory":"Pharmacy",
            "type":"Retail Goods"
        }
    ],
    "sg:phone":"+1 508 359 7995",
    "sg:postcode":"02052",
    "sg:province":"MA",
    "wof:name":"CVS Pharmacy",
    "wof:placetype":"venue"
},
  "geometry": {"coordinates":[-71.274124,42.199251],"type":"Point"}
}