{
  "type": "Feature",
  "properties": {
    "addr:full": "22 Paris St East Boston MA 02128",
    "addr:housenumber": "22",
    "addr:postcode": "02128",
    "addr:street": "Paris St",
    "iso:country": "US",
    "sg:address": "22 Paris St",
    "sg:city": "East Boston",
    "sg:classifiers": [
      {
        "category": "Social Services",
        "type": "Services"
      }
    ],
    "sg:phone": "+1 617 567 5882",
    "sg:postcode": "02128",
    "sg:province": "MA",
    "sg:tags": [
      "organization",
      "welfare"
    ],
    "sg:website": "www.noahcdc.org",
    "wof:name": "Noah Neighborhood-Affordable",
    "wof:placetype": "venue"
  },
  "geometry": {"coordinates":[-71.040121,42.369867],"type":"Point"}
}
