{
  "type": "Feature",
  "properties": {
    "iso:country":"US",
    "sg:address":"85 Federal Ave",
    "sg:city":"Quincy",
    "sg:classifiers":[
        {
            "category":"Freight",
            "type":"Transportation"
        }
    ],
    "sg:phone":"+1 617 770 3210",
    "sg:postcode":"02169",
    "sg:province":"MA",
    "sg:tags":[
        "commercial",
        "storage"
    ],
    "wof:name":"Granite City Self Storage",
    "wof:placetype":"venue"
},
  "geometry": {"coordinates":[-71.004728,42.240547],"type":"Point"}
}