{
  "type": "Feature",
  "properties": {
    "addr:full": "41 Amory St Roxbury MA 02119",
    "addr:housenumber": "41",
    "addr:postcode": "02119",
    "addr:street": "Amory St",
    "iso:country": "US",
    "sg:address": "41 Amory St",
    "sg:city": "Roxbury",
    "sg:classifiers": [
      {
        "category": "Shopping",
        "subcategory": "Used Merchandise",
        "type": "Retail Goods"
      }
    ],
    "sg:phone": "+1 617 445 0139",
    "sg:postcode": "02119",
    "sg:province": "MA",
    "sg:tags": [
      "junk"
    ],
    "wof:name": "Boston Auto Salvage",
    "wof:placetype": "venue"
  },
  "geometry": {"coordinates":[-71.099328,42.321254],"type":"Point"}
}
