{
  "type": "Feature",
  "properties": {
    "addr:full":"7 Rice Dr Wilbraham MA 01095",
    "addr:housenumber":"7",
    "addr:postcode":"01095",
    "addr:street":"Rice Dr",
    "iso:country":"US",
    "sg:address":"7 Rice Dr",
    "sg:city":"Wilbraham",
    "sg:classifiers":[
        {
            "category":"Real Estate",
            "subcategory":"Architect",
            "type":"Services"
        }
    ],
    "sg:phone":"+1 413 599 0079",
    "sg:postcode":"01095",
    "sg:province":"MA",
    "sg:tags":[
        "architects'",
        "specification",
        "construction",
        "builders'",
        "architectural"
    ],
    "wof:name":"Jls Architects Inc",
    "wof:placetype":"venue"
},
  "geometry": {"coordinates":[-72.435733,42.10302],"type":"Point"}
}