{
  "type": "Feature",
  "properties": {
    "addr:full":"8 Pioneer Cir Salem MA 01970",
    "addr:housenumber":"8",
    "addr:postcode":"01970",
    "addr:street":"Pioneer Cir",
    "iso:country":"US",
    "sg:address":"8 Pioneer Cir",
    "sg:city":"Salem",
    "sg:classifiers":[
        {
            "category":"Building & Trades",
            "subcategory":"Construction",
            "type":"Services"
        }
    ],
    "sg:phone":"+1   ",
    "sg:postcode":"01970",
    "sg:province":"MA",
    "sg:tags":[
        "contractor"
    ],
    "wof:name":"Rons Sun",
    "wof:placetype":"venue"
},
  "geometry": {"coordinates":[-70.91828,42.517768],"type":"Point"}
}