{
  "type": "Feature",
  "properties": {
    "addr:full": "46 Chatham Rd Billerica MA 01821",
    "addr:housenumber": "46",
    "addr:postcode": "01821",
    "addr:street": "Chatham Rd",
    "iso:country": "US",
    "sg:address": "46 Chatham Rd",
    "sg:city": "Billerica",
    "sg:classifiers": [
      {
        "category": "Insurance",
        "subcategory": "Insurance Agent",
        "type": "Services"
      }
    ],
    "sg:phone": "+1 978 667 5230",
    "sg:postcode": "01821",
    "sg:province": "MA",
    "sg:tags": [
      "processing"
    ],
    "wof:name": "Medical Billing Svc",
    "wof:placetype": "venue"
  },
  "geometry": {"coordinates":[-71.223689,42.56322],"type":"Point"}
}
