{
  "type": "Feature",
  "properties": {
    "iso:country":"US",
    "sg:address":"8 Bay View Ave",
    "sg:city":"Plymouth",
    "sg:classifiers":[
        {
            "category":"Professional",
            "subcategory":"Management & Consulting",
            "type":"Services"
        }
    ],
    "sg:phone":"+1 508 830 0900",
    "sg:postcode":"02360",
    "sg:province":"MA",
    "sg:tags":[
        "consultant",
        "rate",
        "electric"
    ],
    "sg:website":"www.cci-energy.com",
    "wof:name":"Cost Containment",
    "wof:placetype":"venue"
},
  "geometry": {"coordinates":[-70.65427200000001,41.949581],"type":"Point"}
}