{
  "type": "Feature",
  "properties": {
    "addr:full": "8 Bay View Ave Plymouth MA 02360",
    "addr:housenumber": "8",
    "addr:postcode": "02360",
    "addr:street": "Bay View Ave",
    "iso:country": "US",
    "sg:address": "8 Bay View Ave",
    "sg:city": "Plymouth",
    "sg:classifiers": [
      {
        "category": "Professional",
        "subcategory": "Management \u0026 Consulting",
        "type": "Services"
      }
    ],
    "sg:phone": "+1 508 830 0900",
    "sg:postcode": "02360",
    "sg:province": "MA",
    "sg:tags": [
      "consultant",
      "rate",
      "electric"
    ],
    "sg:website": "www.cci-energy.com",
    "wof:name": "Cost Containment",
    "wof:placetype": "venue"
  },
  "geometry": {"coordinates":[-70.654272,41.949581],"type":"Point"}
}
