{
  "type": "Feature",
  "properties": {
    "addr:full":"34 Tyler Rd Lexington MA 02420",
    "addr:housenumber":"34",
    "addr:postcode":"02420",
    "addr:street":"Tyler Rd",
    "iso:country":"US",
    "sg:address":"34 Tyler Rd",
    "sg:city":"Lexington",
    "sg:classifiers":[
        {
            "category":"Professional",
            "subcategory":"Computer Services",
            "type":"Services"
        }
    ],
    "sg:phone":"+1 781 863 8025",
    "sg:postcode":"02420",
    "sg:province":"MA",
    "sg:tags":[
        "consultant",
        "designer"
    ],
    "wof:name":"Advanced Technologies Engnrng",
    "wof:placetype":"venue"
},
  "geometry": {"coordinates":[-71.18698500000001,42.444826],"type":"Point"}
}