{
  "type": "Feature",
  "properties": {
    "addr:full":"90 Sandisfield Rd Sandisfield MA 01255",
    "addr:housenumber":"90",
    "addr:postcode":"01255",
    "addr:street":"Sandisfield Rd",
    "iso:country":"US",
    "sg:address":"90 Sandisfield Rd",
    "sg:city":"Sandisfield",
    "sg:classifiers":[
        {
            "category":"Building & Trades",
            "subcategory":"Construction",
            "type":"Services"
        }
    ],
    "sg:phone":"+1 413 258 4958",
    "sg:postcode":"01255",
    "sg:province":"MA",
    "sg:tags":[
        "carpenter"
    ],
    "wof:name":"Dana Beardsley Carpentry",
    "wof:placetype":"venue"
},
  "geometry": {"coordinates":[-73.115532,42.110329],"type":"Point"}
}