{
  "type": "Feature",
  "properties": {
    "addr:full": "129 Reservation Rd Andover MA 01810",
    "addr:housenumber": "129",
    "addr:postcode": "01810",
    "addr:street": "Reservation Rd",
    "iso:country": "US",
    "ovtr:label": "Discover Preschool, 129 Reservation Rd Andover MA US",
    "ovtr:similarity": 2.144521951675415,
    "sg:address": "129 Reservation Rd",
    "sg:city": "Andover",
    "sg:classifiers": [
      {
        "category": "Organizations",
        "subcategory": "Religious Organization",
        "type": "Services"
      }
    ],
    "sg:phone": "+1 978 475 9706",
    "sg:postcode": "01810",
    "sg:province": "MA",
    "wof:name": "Discover Preschool",
    "wof:placetype": "venue"
  },
  "geometry": {"coordinates":[-71.165616,42.659559],"type":"Point"}
}
