{
  "type": "Feature",
  "properties": {
    "iso:country":"US",
    "sg:address":"353 W Grove St",
    "sg:city":"Middleboro",
    "sg:classifiers":[
        {
            "category":"Building & Trades",
            "subcategory":"Construction",
            "type":"Services"
        }
    ],
    "sg:phone":"+1 508 947 8646",
    "sg:postcode":"02346",
    "sg:province":"MA",
    "sg:tags":[
        "paving",
        "contractor"
    ],
    "wof:name":"Cacciatore Brothers Inc",
    "wof:placetype":"venue"
},
  "geometry": {"coordinates":[-70.94448800000001,41.894931],"type":"Point"}
}