{
  "type": "Feature",
  "properties": {
    "iso:country":"US",
    "sg:address":"68 Reservoir St",
    "sg:city":"Holden",
    "sg:classifiers":[
        {
            "category":"Health Services",
            "subcategory":"Nursing And Care Facility",
            "type":"Services"
        }
    ],
    "sg:phone":"+1 508 829 4300",
    "sg:postcode":"01520",
    "sg:province":"MA",
    "sg:tags":[
        "home",
        "retirement",
        "community"
    ],
    "wof:name":"Colony Retirement Homes-Holden",
    "wof:placetype":"venue"
},
  "geometry": {"coordinates":[-71.86461199999999,42.348416],"type":"Point"}
}