{
  "type": "Feature",
  "properties": {
    "addr:full": "68 Reservoir St Holden MA 01520",
    "addr:housenumber": "68",
    "addr:postcode": "01520",
    "addr:street": "Reservoir St",
    "iso:country": "US",
    "sg:address": "68 Reservoir St",
    "sg:city": "Holden",
    "sg:classifiers": [
      {
        "category": "Health Services",
        "subcategory": "Nursing And Care Facility",
        "type": "Services"
      }
    ],
    "sg:phone": "+1 508 829 4300",
    "sg:postcode": "01520",
    "sg:province": "MA",
    "sg:tags": [
      "home",
      "retirement",
      "community"
    ],
    "wof:name": "Colony Retirement Homes-Holden",
    "wof:placetype": "venue"
  },
  "geometry": {"coordinates":[-71.864612,42.348416],"type":"Point"}
}
