{
  "type": "Feature",
  "properties": {
    "addr:full":"25 Seagirt Ave Saugus MA 01906",
    "addr:housenumber":"25",
    "addr:postcode":"01906",
    "addr:street":"Seagirt Ave",
    "iso:country":"US",
    "sg:address":"25 Seagirt Ave",
    "sg:city":"Saugus",
    "sg:classifiers":[
        {
            "category":"Building & Trades",
            "subcategory":"Cleaning & Sanitation",
            "type":"Services"
        },
        {
            "category":"Professional",
            "subcategory":"Employment Agencies",
            "type":"Services"
        }
    ],
    "sg:phone":"+1 781 231 7308",
    "sg:postcode":"01906",
    "sg:province":"MA",
    "sg:tags":[
        "home",
        "contractor"
    ],
    "wof:name":"Heavanly Homes Cleaning Svcs - CLOSED",
    "wof:placetype":"venue"
},
  "geometry": {"coordinates":[-70.99539900000001,42.448299],"type":"Point"}
}