{
  "type": "Feature",
  "properties": {
    "iso:country":"US",
    "sg:address":"1691 Revere Beach Pkwy",
    "sg:city":"Everett",
    "sg:classifiers":[
        {
            "category":"Autos & Motor Vehicles",
            "subcategory":"Auto Supplies",
            "type":"Retail Goods"
        }
    ],
    "sg:phone":"+1 617 389 6080",
    "sg:postcode":"02149",
    "sg:province":"MA",
    "sg:tags":[
        "automobile",
        "parts"
    ],
    "sg:website":"www.autozone.com",
    "wof:name":"Autozone",
    "wof:placetype":"venue"
},
  "geometry": {"coordinates":[-71.042653,42.401779],"type":"Point"}
}