{
  "type": "Feature",
  "properties": {
    "addr:full": "17 Forty Steps Ln Nahant MA 01908",
    "addr:housenumber": "17",
    "addr:postcode": "01908",
    "addr:street": "Forty Steps Ln",
    "iso:country": "US",
    "sg:address": "17 Forty Steps Ln",
    "sg:city": "Nahant",
    "sg:classifiers": [
      {
        "category": "Building \u0026 Trades",
        "subcategory": "Construction",
        "type": "Services"
      }
    ],
    "sg:phone": "+1 781 581 0289",
    "sg:postcode": "01908",
    "sg:province": "MA",
    "sg:tags": [
      "general",
      "contractor"
    ],
    "wof:name": "Donald Savino \u0026 Sons",
    "wof:placetype": "venue"
  },
  "geometry": {"coordinates":[-70.911221,42.422454],"type":"Point"}
}
