{
  "type": "Feature",
  "properties": {
    "iso:country":"US",
    "sg:address":"17 Forty Steps Ln",
    "sg:city":"Nahant",
    "sg:classifiers":[
        {
            "category":"Building & Trades",
            "subcategory":"Construction",
            "type":"Services"
        }
    ],
    "sg:phone":"+1 781 581 0289",
    "sg:postcode":"01908",
    "sg:province":"MA",
    "sg:tags":[
        "general",
        "contractor"
    ],
    "wof:name":"Donald Savino & Sons",
    "wof:placetype":"venue"
},
  "geometry": {"coordinates":[-70.911221,42.422454],"type":"Point"}
}