{
  "type": "Feature",
  "properties": {
    "addr:full": "1 Sewall St Salem MA 01970",
    "addr:housenumber": "1",
    "addr:postcode": "01970",
    "addr:street": "Sewall St",
    "iso:country": "US",
    "ovtr:label": "Salem YMCA, 1 Sewall St Salem MA US",
    "ovtr:similarity": 3.8971869945526123,
    "sg:address": "1 Sewall St",
    "sg:city": "Salem",
    "sg:classifiers": [
      {
        "category": "Social Services",
        "subcategory": "Child Care",
        "type": "Services"
      }
    ],
    "sg:phone": "+1 978 744 0351",
    "sg:postcode": "01970",
    "sg:province": "MA",
    "wof:name": "YMCA",
    "wof:placetype": "venue"
  },
  "geometry": {"coordinates":[-70.897498,42.522428],"type":"Point"}
}
