{
  "type": "Feature",
  "properties": {
    "iso:country":"US",
    "sg:address":"1 Sewall St",
    "sg:city":"Salem",
    "sg:classifiers":[
        {
            "category":"Social Services",
            "subcategory":"Child Care",
            "type":"Services"
        }
    ],
    "sg:phone":"+1 978 744 0351",
    "sg:postcode":"01970",
    "sg:province":"MA",
    "wof:name":"YMCA",
    "wof:placetype":"venue"
},
  "geometry": {"coordinates":[-70.897498,42.522428],"type":"Point"}
}