{
  "type": "Feature",
  "properties": {
    "iso:country":"US",
    "sg:address":"46 Medford St",
    "sg:city":"Somerville",
    "sg:classifiers":[
        {
            "category":"Restaurant",
            "type":"Food & Drink"
        }
    ],
    "sg:phone":"+1 617 864 2553",
    "sg:postcode":"02143",
    "sg:province":"MA",
    "sg:tags":[
        "pizza"
    ],
    "sg:website":"www.lahaciendasomerville.com/",
    "wof:name":"La Hacienda",
    "wof:placetype":"venue"
},
  "geometry": {"coordinates":[-71.088331,42.374783],"type":"Point"}
}