{
  "type": "Feature",
  "properties": {
    "addr:full":"4 Canal Park Cambridge MA 02141",
    "addr:housenumber":"4",
    "addr:postcode":"02141",
    "addr:street":"Park",
    "iso:country":"US",
    "sg:address":"4 Canal Park",
    "sg:city":"Cambridge",
    "sg:classifiers":[
        {
            "category":"Real Estate",
            "subcategory":"Real Estate Operator",
            "type":"Services"
        }
    ],
    "sg:phone":"+1 617 225 0743",
    "sg:postcode":"02141",
    "sg:province":"MA",
    "sg:tags":[
        "condominium"
    ],
    "wof:name":"Thomas Graves Landing Condo",
    "wof:placetype":"venue"
},
  "geometry": {"coordinates":[-71.07708100000001,42.369941],"type":"Point"}
}