{
  "type": "Feature",
  "properties": {
    "iso:country":"US",
    "sg:address":"443 Shaker Rd",
    "sg:city":"East Longmeadow",
    "sg:classifiers":[
        {
            "category":"Manufacturing",
            "subcategory":"Toys & Sporting Goods",
            "type":"Manufacturing & Wholesale Goods"
        }
    ],
    "sg:phone":"+1 413 525 6411",
    "sg:postcode":"01028",
    "sg:province":"MA",
    "sg:tags":[
        "game",
        "vehicle"
    ],
    "sg:website":"www.hasbro.com",
    "wof:name":"Hasbro Games",
    "wof:placetype":"venue"
},
  "geometry": {"coordinates":[-72.51917899999999,42.047214],"type":"Point"}
}