{
  "type": "Feature",
  "properties": {
    "addr:full": "443 Shaker Rd East Longmeadow MA 01028",
    "addr:housenumber": "443",
    "addr:postcode": "01028",
    "addr:street": "Shaker Rd",
    "iso:country": "US",
    "sg:address": "443 Shaker Rd",
    "sg:city": "East Longmeadow",
    "sg:classifiers": [
      {
        "category": "Manufacturing",
        "subcategory": "Toys \u0026 Sporting Goods",
        "type": "Manufacturing \u0026 Wholesale Goods"
      }
    ],
    "sg:phone": "+1 413 525 6411",
    "sg:postcode": "01028",
    "sg:province": "MA",
    "sg:tags": [
      "game",
      "vehicle"
    ],
    "sg:website": "www.hasbro.com",
    "wof:name": "Hasbro Games",
    "wof:placetype": "venue"
  },
  "geometry": {"coordinates":[-72.519179,42.047214],"type":"Point"}
}
