{
  "type": "Feature",
  "properties": {
    "iso:country":"US",
    "sg:address":"15 Northern Ave",
    "sg:city":"Boston",
    "sg:classifiers":[
        {
            "category":"Restaurant",
            "type":"Food & Drink"
        },
        {
            "category":"Food & Beverages",
            "subcategory":"Meat & Fish",
            "type":"Retail Goods"
        }
    ],
    "sg:phone":"+1 617 423 5500",
    "sg:postcode":"02210",
    "sg:province":"MA",
    "sg:tags":[
        "seafood",
        "market"
    ],
    "sg:website":"www.jameshooklobster.com",
    "wof:name":"Hook Jas & Co Shell Fish",
    "wof:placetype":"venue"
},
  "geometry": {"coordinates":[-71.04769899999999,42.353901],"type":"Point"}
}