{
  "type": "Feature",
  "properties": {
    "addr:full": "15 Northern Ave Boston MA 02210",
    "addr:housenumber": "15",
    "addr:postcode": "02210",
    "addr:street": "Northern Ave",
    "iso:country": "US",
    "sg:address": "15 Northern Ave",
    "sg:city": "Boston",
    "sg:classifiers": [
      {
        "category": "Restaurant",
        "type": "Food \u0026 Drink"
      },
      {
        "category": "Food \u0026 Beverages",
        "subcategory": "Meat \u0026 Fish",
        "type": "Retail Goods"
      }
    ],
    "sg:phone": "+1 617 423 5500",
    "sg:postcode": "02210",
    "sg:province": "MA",
    "sg:tags": [
      "seafood",
      "market"
    ],
    "sg:website": "www.jameshooklobster.com",
    "wof:name": "Hook Jas \u0026 Co Shell Fish",
    "wof:placetype": "venue"
  },
  "geometry": {"coordinates":[-71.047699,42.353901],"type":"Point"}
}
