{
  "type": "Feature",
  "properties": {
    "iso:country":"US",
    "sg:address":"435 Faneuil St",
    "sg:city":"Brighton",
    "sg:classifiers":[
        {
            "category":"Restaurant",
            "type":"Food & Drink"
        }
    ],
    "sg:phone":"+1 617 254 5055",
    "sg:postcode":"02135",
    "sg:province":"MA",
    "sg:tags":[
        "box",
        "lunch"
    ],
    "wof:name":"Royal Catering Inc",
    "wof:placetype":"venue"
},
  "geometry": {"coordinates":[-71.167933,42.351212],"type":"Point"}
}