{
  "type": "Feature",
  "properties": {
    "addr:full": "435 Faneuil St Brighton MA 02135",
    "addr:housenumber": "435",
    "addr:postcode": "02135",
    "addr:street": "Faneuil St",
    "iso:country": "US",
    "sg:address": "435 Faneuil St",
    "sg:city": "Brighton",
    "sg:classifiers": [
      {
        "category": "Restaurant",
        "type": "Food \u0026 Drink"
      }
    ],
    "sg:phone": "+1 617 254 5055",
    "sg:postcode": "02135",
    "sg:province": "MA",
    "sg:tags": [
      "box",
      "lunch"
    ],
    "wof:name": "Royal Catering Inc",
    "wof:placetype": "venue"
  },
  "geometry": {"coordinates":[-71.167933,42.351212],"type":"Point"}
}
