{
  "type": "Feature",
  "properties": {
    "addr:full": "22 Cooney Rd Spencer MA 01562",
    "addr:housenumber": "22",
    "addr:postcode": "01562",
    "addr:street": "Cooney Rd",
    "iso:country": "US",
    "sg:address": "22 Cooney Rd",
    "sg:city": "Spencer",
    "sg:classifiers": [
      {
        "category": "Retail",
        "subcategory": "Auto Repair",
        "type": "Services"
      }
    ],
    "sg:phone": "+1 508 885 7774",
    "sg:postcode": "01562",
    "sg:province": "MA",
    "sg:tags": [
      "automobile",
      "inspection"
    ],
    "wof:name": "Autocomm Inc",
    "wof:placetype": "venue"
  },
  "geometry": {"coordinates":[-72.004128,42.264548],"type":"Point"}
}
