{
  "type": "Feature",
  "properties": {
    "addr:full":"120 Quarry Dr Milford MA 01757",
    "addr:housenumber":"120",
    "addr:postcode":"01757",
    "addr:street":"Quarry Dr",
    "iso:country":"US",
    "sg:address":"120 Quarry Dr",
    "sg:city":"Milford",
    "sg:classifiers":[
        {
            "category":"Professional",
            "type":"Services"
        }
    ],
    "sg:phone":"+1 508 478 5808",
    "sg:postcode":"01757",
    "sg:province":"MA",
    "sg:tags":[
        "establishment"
    ],
    "wof:name":"E D & E",
    "wof:placetype":"venue"
},
  "geometry": {"coordinates":[-71.49847699999999,42.152788],"type":"Point"}
}