{
  "type": "Feature",
  "properties": {
    "iso:country":"US",
    "sg:address":"174 Shaker Rd",
    "sg:city":"East Longmeadow",
    "sg:classifiers":[
        {
            "category":"Retail",
            "subcategory":"Auto Repair",
            "type":"Services"
        }
    ],
    "sg:phone":"+1 413 525 7309",
    "sg:postcode":"01028",
    "sg:province":"MA",
    "sg:tags":[
        "repairing",
        "automobile"
    ],
    "wof:name":"Redstone Automotive",
    "wof:placetype":"venue"
},
  "geometry": {"coordinates":[-72.517821,42.056367],"type":"Point"}
}