{
  "type": "Feature",
  "properties": {
    "iso:country":"US",
    "sg:address":"420 Main Street",
    "sg:city":"Malden",
    "sg:classifiers":[
        {
            "category":"Shopping",
            "subcategory":"Mobile Phones",
            "type":"Retail Goods"
        }
    ],
    "sg:phone":"+1 781 324 2232",
    "sg:postcode":"02148",
    "sg:province":"MA",
    "wof:name":"Cellular Supply",
    "wof:placetype":"venue"
},
  "geometry": {"coordinates":[-71.06699500000001,42.426597],"type":"Point"}
}