{
  "type": "Feature",
  "properties": {
    "iso:country":"US",
    "sg:address":"163 N Worcester St",
    "sg:city":"Norton",
    "sg:classifiers":[
        {
            "category":"Manufacturing",
            "subcategory":"Printing",
            "type":"Manufacturing & Wholesale Goods"
        }
    ],
    "sg:phone":"+1 508 226 5558",
    "sg:postcode":"02766",
    "sg:province":"MA",
    "sg:tags":[
        "multimedia"
    ],
    "wof:name":"Green Media Solutions",
    "wof:placetype":"venue"
},
  "geometry": {"coordinates":[-71.240554,41.966637],"type":"Point"}
}