{
  "type": "Feature",
  "properties": {
    "addr:full":"893 Grafton St Worcester MA 01604",
    "addr:housenumber":"893",
    "addr:postcode":"01604",
    "addr:street":"Grafton St",
    "iso:country":"US",
    "sg:address":"893 Grafton St",
    "sg:city":"Worcester",
    "sg:classifiers":[
        {
            "category":"Professional",
            "subcategory":"Accounting & Tax Preparation",
            "type":"Services"
        }
    ],
    "sg:phone":"+1 508 754 5917",
    "sg:postcode":"01604",
    "sg:province":"MA",
    "sg:tags":[
        "return",
        "filing"
    ],
    "sg:website":"www.hrblock.com",
    "wof:name":"H & R Block Tax Svc",
    "wof:placetype":"venue"
},
  "geometry": {"coordinates":[-71.761589,42.248127],"type":"Point"}
}