{
  "type": "Feature",
  "properties": {
    "addr:full":"1 Van de Graaff Dr Burlington MA 01803",
    "addr:housenumber":"1",
    "addr:postcode":"01803",
    "addr:street":"Van;Graaff Dr",
    "iso:country":"US",
    "sg:address":"1 Van de Graaff Dr",
    "sg:city":"Burlington",
    "sg:classifiers":[
        {
            "category":"Wholesale",
            "subcategory":"Electrical",
            "type":"Manufacturing & Wholesale Goods"
        }
    ],
    "sg:phone":"+1 781 270 6500",
    "sg:postcode":"01803",
    "sg:province":"MA",
    "sg:tags":[
        "equipment",
        "telephone",
        "system"
    ],
    "sg:website":"www.adc-oss.com",
    "wof:name":"ADC",
    "wof:placetype":"venue"
},
  "geometry": {"coordinates":[-71.195521,42.483601],"type":"Point"}
}