{
  "type": "Feature",
  "properties": {
    "iso:country":"US",
    "sg:address":"2071 Purchase St",
    "sg:city":"New Bedford",
    "sg:phone":"+1 508 994 1762",
    "sg:postcode":"02746",
    "sg:province":"MA",
    "sg:tags":[
        "oil"
    ],
    "wof:name":"Bancroft Oil Co",
    "wof:placetype":"venue"
},
  "geometry": {"coordinates":[-70.93150300000001,41.655533],"type":"Point"}
}