{
  "type": "Feature",
  "properties": {
    "addr:full": "45 Storey Ave Ste 19 Newburyport MA 01950",
    "addr:housenumber": "45",
    "addr:postcode": "01950",
    "addr:street": "Storey Ave Ste 19",
    "iso:country": "US",
    "sg:address": "45 Storey Ave Ste 19",
    "sg:city": "Newburyport",
    "sg:classifiers": [
      {
        "category": "Shopping",
        "subcategory": "Pharmacy",
        "type": "Retail Goods"
      }
    ],
    "sg:phone": "+1 978 462 8530",
    "sg:postcode": "01950",
    "sg:province": "MA",
    "sg:tags": [
      "drugstore"
    ],
    "sg:website": "www.riteaid.com",
    "wof:name": "Rite Aid Pharmacies",
    "wof:placetype": "venue"
  },
  "geometry": {"coordinates":[-70.906663,42.820872],"type":"Point"}
}
