{
  "type": "Feature",
  "properties": {
    "iso:country":"US",
    "sg:address":"250 Waltham St",
    "sg:city":"Newton",
    "sg:classifiers":[
        {
            "category":"Retail",
            "subcategory":"Repair Shop",
            "type":"Services"
        }
    ],
    "sg:phone":"+1 617 630 1617",
    "sg:postcode":"02465",
    "sg:province":"MA",
    "sg:tags":[
        "sharpening",
        "skate"
    ],
    "wof:name":"Gary Lubin Skating Accessories",
    "wof:placetype":"venue"
},
  "geometry": {"coordinates":[-71.222758,42.358342],"type":"Point"}
}