{
  "type": "Feature",
  "properties": {
    "addr:full": "188 Main St Wilmington MA 01887",
    "addr:housenumber": "188",
    "addr:postcode": "01887",
    "addr:street": "Main St",
    "iso:country": "US",
    "sg:address": "188 Main St",
    "sg:city": "Wilmington",
    "sg:classifiers": [
      {
        "category": "Home \u0026 Garden",
        "subcategory": "Building Materials",
        "type": "Retail Goods"
      }
    ],
    "sg:phone": "+1 978 658 3411",
    "sg:postcode": "01887",
    "sg:province": "MA",
    "sg:tags": [
      "paint"
    ],
    "wof:name": "Sherwin-Williams Paints",
    "wof:placetype": "venue"
  },
  "geometry": {"coordinates":[-71.182181,42.558966],"type":"Point"}
}
