{
  "type": "Feature",
  "properties": {
    "iso:country":"US",
    "sg:address":"1201 Fall River Ave",
    "sg:city":"Seekonk",
    "sg:classifiers":[
        {
            "category":"Shopping",
            "subcategory":"Bicycles & Sporting Goods",
            "type":"Retail Goods"
        }
    ],
    "sg:phone":"+1 508 336 2788",
    "sg:postcode":"02771",
    "sg:province":"MA",
    "sg:website":"www.soccergear4u.com",
    "wof:name":"Soccer World",
    "wof:placetype":"venue"
},
  "geometry": {"coordinates":[-71.325777,41.792759],"type":"Point"}
}