{
  "type": "Feature",
  "properties": {
    "addr:full":"491 High St # 497 Medford MA 02155",
    "addr:housenumber":"491",
    "addr:postcode":"02155",
    "addr:street":"High St # 497",
    "iso:country":"US",
    "sg:address":"491 High St # 497",
    "sg:city":"Medford",
    "sg:classifiers":[
        {
            "category":"Shopping",
            "subcategory":"Pharmacy",
            "type":"Retail Goods"
        }
    ],
    "sg:phone":"+1 781 646 9622",
    "sg:postcode":"02155",
    "sg:province":"MA",
    "sg:tags":[
        "drugstore"
    ],
    "wof:name":"Rite Aid Pharmacies",
    "wof:placetype":"venue"
},
  "geometry": {"coordinates":[-71.13335499999999,42.421431],"type":"Point"}
}