{
  "type": "Feature",
  "properties": {
    "iso:country":"US",
    "sg:address":"1 Independence Way",
    "sg:city":"Brewster",
    "sg:classifiers":[
        {
            "category":"Health Services",
            "subcategory":"Doctor",
            "type":"Services"
        }
    ],
    "sg:phone":"+1 508 896 0050",
    "sg:postcode":"02631",
    "sg:province":"MA",
    "sg:tags":[
        "physician",
        "surgeon"
    ],
    "wof:name":"Theodor T Herwig MD",
    "wof:placetype":"venue"
},
  "geometry": {"coordinates":[-70.065349,41.757808],"type":"Point"}
}