{
  "type": "Feature",
  "properties": {
    "iso:country":"US",
    "sg:address":"615 Washington St",
    "sg:city":"Pembroke",
    "sg:classifiers":[
        {
            "category":"Bars & Pubs",
            "subcategory":"Lounge",
            "type":"Food & Drink"
        },
        {
            "category":"Restaurant",
            "type":"Food & Drink"
        }
    ],
    "sg:phone":"+1 781 826 3161",
    "sg:postcode":"02359",
    "sg:province":"MA",
    "sg:tags":[
        "seafood",
        "cocktail"
    ],
    "wof:name":"Bobby Hackett's Restaurant Inc",
    "wof:placetype":"venue"
},
  "geometry": {"coordinates":[-70.781184,42.07461],"type":"Point"}
}