{
  "type": "Feature",
  "properties": {
    "addr:full": "615 Washington St Pembroke MA 02359",
    "addr:housenumber": "615",
    "addr:postcode": "02359",
    "addr:street": "Washington St",
    "iso:country": "US",
    "sg:address": "615 Washington St",
    "sg:city": "Pembroke",
    "sg:classifiers": [
      {
        "category": "Bars \u0026 Pubs",
        "subcategory": "Lounge",
        "type": "Food \u0026 Drink"
      },
      {
        "category": "Restaurant",
        "type": "Food \u0026 Drink"
      }
    ],
    "sg:phone": "+1 781 826 3161",
    "sg:postcode": "02359",
    "sg:province": "MA",
    "sg:tags": [
      "seafood",
      "cocktail"
    ],
    "wof:name": "Bobby Hackett's Restaurant Inc",
    "wof:placetype": "venue"
  },
  "geometry": {"coordinates":[-70.781184,42.07461],"type":"Point"}
}
