{
  "type": "Feature",
  "properties": {
    "iso:country":"US",
    "sg:address":"775 Quaker Hwy",
    "sg:city":"Uxbridge",
    "sg:classifiers":[
        {
            "category":"Professional",
            "subcategory":"Computer Services",
            "type":"Services"
        }
    ],
    "sg:phone":"+1 508 278 7839",
    "sg:postcode":"01569",
    "sg:province":"MA",
    "sg:tags":[
        "consultant",
        "designer"
    ],
    "wof:name":"Designer Systems",
    "wof:placetype":"venue"
},
  "geometry": {"coordinates":[-71.60648,42.027917],"type":"Point"}
}