{
  "type": "Feature",
  "properties": {
    "iso:country":"US",
    "sg:address":"515 Berkeley St",
    "sg:city":"Boston",
    "sg:classifiers":[
        {
            "category":"Building & Trades",
            "subcategory":"Locksmith",
            "type":"Services"
        }
    ],
    "sg:phone":"+1 617 692 2892",
    "sg:postcode":"02116",
    "sg:province":"MA",
    "sg:tags":[
        "lock"
    ],
    "sg:website":"http://www.boston-locksmiths.us/",
    "wof:name":"Locksmith Boston 365",
    "wof:placetype":"venue"
},
  "geometry": {"coordinates":[-71.07391,42.352964],"type":"Point"}
}