{
  "type": "Feature",
  "properties": {
    "addr:full": "515 Berkeley St Boston MA 02116",
    "addr:housenumber": "515",
    "addr:postcode": "02116",
    "addr:street": "Berkeley St",
    "iso:country": "US",
    "sg:address": "515 Berkeley St",
    "sg:city": "Boston",
    "sg:classifiers": [
      {
        "category": "Building \u0026 Trades",
        "subcategory": "Locksmith",
        "type": "Services"
      }
    ],
    "sg:phone": "+1 617 692 2892",
    "sg:postcode": "02116",
    "sg:province": "MA",
    "sg:tags": [
      "lock"
    ],
    "sg:website": "http://www.boston-locksmiths.us/",
    "wof:name": "Locksmith Boston 365",
    "wof:placetype": "venue"
  },
  "geometry": {"coordinates":[-71.07391,42.352964],"type":"Point"}
}
