{
  "type": "Feature",
  "properties": {
    "addr:full": "14 Federal St Greenfield MA 01301",
    "addr:housenumber": "14",
    "addr:postcode": "01301",
    "addr:street": "Federal St",
    "iso:country": "US",
    "ovtr:label": "Chet's Barber Shop, 14 Federal St Greenfield MA US",
    "ovtr:similarity": 2.420320987701416,
    "sg:address": "14 Federal St",
    "sg:city": "Greenfield",
    "sg:classifiers": [
      {
        "category": "Personal",
        "subcategory": "Barber",
        "type": "Services"
      }
    ],
    "sg:phone": "+1 413 774 7488",
    "sg:postcode": "01301",
    "sg:province": "MA",
    "wof:name": "Chet's Barber Shop",
    "wof:placetype": "venue"
  },
  "geometry": {"coordinates":[-72.600058,42.588337],"type":"Point"}
}
