{
  "type": "Feature",
  "properties": {
    "iso:country":"US",
    "sg:address":"1277 Broadway",
    "sg:city":"Saugus",
    "sg:classifiers":[
        {
            "category":"Professional",
            "subcategory":"Art Services",
            "type":"Services"
        }
    ],
    "sg:phone":"+1 781 231 7537",
    "sg:postcode":"01906",
    "sg:province":"MA",
    "sg:tags":[
        "photographer"
    ],
    "wof:name":"Photo Promotions Inc",
    "wof:placetype":"venue"
},
  "geometry": {"coordinates":[-71.024711,42.462458],"type":"Point"}
}