{
  "type": "Feature",
  "properties": {
    "iso:country":"US",
    "sg:address":"333 Washington St Ste 714",
    "sg:city":"Boston",
    "sg:classifiers":[
        {
            "category":"Real Estate",
            "subcategory":"Architect",
            "type":"Services"
        }
    ],
    "sg:phone":"+1 617 426 3770",
    "sg:postcode":"02108",
    "sg:province":"MA",
    "wof:name":"Stewart Sean T Architects",
    "wof:placetype":"venue"
},
  "geometry": {"coordinates":[-71.058981,42.356793],"type":"Point"}
}