{
  "type": "Feature",
  "properties": {
    "addr:full":"66 Wendell Ave Pittsfield MA 01201",
    "addr:housenumber":"66",
    "addr:postcode":"01201",
    "addr:street":"Wendell Ave",
    "iso:country":"US",
    "sg:address":"66 Wendell Ave",
    "sg:city":"Pittsfield",
    "sg:classifiers":[
        {
            "category":"Health Services",
            "subcategory":"Nursing And Care Facility",
            "type":"Services"
        }
    ],
    "sg:phone":"+1 413 499 0524",
    "sg:postcode":"01201",
    "sg:province":"MA",
    "sg:tags":[
        "home",
        "retirement",
        "community"
    ],
    "sg:website":"www.esbci.org",
    "wof:name":"Area Agency On Aging",
    "wof:placetype":"venue"
},
  "geometry": {"coordinates":[-73.252207,42.4475],"type":"Point"}
}