{
  "type": "Feature",
  "properties": {
    "addr:full": "138 Powder House Blvd Somerville MA 02144",
    "addr:housenumber": "138",
    "addr:postcode": "02144",
    "addr:street": "Powder House Blvd",
    "iso:country": "US",
    "sg:address": "138 Powder House Blvd",
    "sg:city": "Somerville",
    "sg:classifiers": [
      {
        "category": "Building \u0026 Trades",
        "subcategory": "Plumbing",
        "type": "Services"
      }
    ],
    "sg:phone": "+1 617 776 8704",
    "sg:postcode": "02144",
    "sg:province": "MA",
    "sg:tags": [
      "plumber",
      "contractor"
    ],
    "wof:name": "Petersen Plumbing \u0026 Heating Co Inc.",
    "wof:placetype": "venue"
  },
  "geometry": {"coordinates":[-71.124619,42.40493],"type":"Point"}
}
