{
  "type": "Feature",
  "properties": {
    "addr:full": "360 Mast Rd Manomet MA 02360",
    "addr:housenumber": "360",
    "addr:postcode": "02360",
    "addr:street": "Mast Rd",
    "iso:country": "US",
    "sg:address": "360 Mast Rd",
    "sg:city": "Manomet",
    "sg:classifiers": [
      {
        "category": "Social Services",
        "type": "Services"
      }
    ],
    "sg:phone": "+1 508 224 6039",
    "sg:postcode": "02360",
    "sg:province": "MA",
    "sg:tags": [
      "youth",
      "organization",
      "center"
    ],
    "wof:name": "Wind In The Pines Girl Scout",
    "wof:placetype": "venue"
  },
  "geometry": {"coordinates":[-70.623028,41.861996],"type":"Point"}
}
