{
  "type": "Feature",
  "properties": {
    "addr:full": "23 Stratford Rd Seekonk MA 02771",
    "addr:housenumber": "23",
    "addr:postcode": "02771",
    "addr:street": "Stratford Rd",
    "iso:country": "US",
    "sg:address": "23 Stratford Rd",
    "sg:city": "Seekonk",
    "sg:classifiers": [
      {
        "category": "Professional",
        "subcategory": "Business Services",
        "type": "Services"
      }
    ],
    "sg:phone": "+1   ",
    "sg:postcode": "02771",
    "sg:province": "MA",
    "wof:name": "Howell Estimating Systems",
    "wof:placetype": "venue"
  },
  "geometry": {"coordinates":[-71.315695,41.801969],"type":"Point"}
}
