{
  "type": "Feature",
  "properties": {
    "iso:country":"US",
    "sg:address":"23 Stratford Rd",
    "sg:city":"Seekonk",
    "sg:classifiers":[
        {
            "category":"Professional",
            "subcategory":"Business Services",
            "type":"Services"
        }
    ],
    "sg:phone":"+1   ",
    "sg:postcode":"02771",
    "sg:province":"MA",
    "wof:name":"Howell Estimating Systems",
    "wof:placetype":"venue"
},
  "geometry": {"coordinates":[-71.31569500000001,41.801969],"type":"Point"}
}