{
  "type": "Feature",
  "properties": {
    "iso:country":"US",
    "sg:address":"395 North St",
    "sg:city":"Pittsfield",
    "sg:classifiers":[
        {
            "category":"Education",
            "subcategory":"Dance Studio",
            "type":"Public Place"
        }
    ],
    "sg:phone":"+1 413 443 5392",
    "sg:postcode":"01201",
    "sg:province":"MA",
    "sg:tags":[
        "instruction",
        "dancing"
    ],
    "wof:name":"Terpsichore Dance Ctr",
    "wof:placetype":"venue"
},
  "geometry": {"coordinates":[-73.251909,42.455281],"type":"Point"}
}