{
  "type": "Feature",
  "properties": {
    "addr:full": "38 Nathan Ellis Hwy Mashpee MA 02649",
    "addr:housenumber": "38",
    "addr:postcode": "02649",
    "addr:street": "Nathan Ellis Hwy",
    "iso:country": "US",
    "sg:address": "38 Nathan Ellis Hwy",
    "sg:city": "Mashpee",
    "sg:classifiers": [
      {
        "category": "Utilities",
        "subcategory": "Mobile Phone",
        "type": "Services"
      },
      {
        "category": "Shopping",
        "subcategory": "Gifts \u0026 Souvenirs",
        "type": "Retail Goods"
      }
    ],
    "sg:phone": "+1 508 477 2368",
    "sg:postcode": "02649",
    "sg:province": "MA",
    "sg:tags": [
      "shop",
      "wi-fi",
      "hotspot"
    ],
    "wof:name": "Lili Pad",
    "wof:placetype": "venue"
  },
  "geometry": {"coordinates":[-70.491478,41.618191],"type":"Point"}
}
