{
  "type": "Feature",
  "properties": {
    "iso:country":"US",
    "sg:address":"97 Main St",
    "sg:city":"Malden",
    "sg:classifiers":[
        {
            "category":"Retail",
            "subcategory":"Repair Shop",
            "type":"Services"
        }
    ],
    "sg:phone":"+1   ",
    "sg:postcode":"02148",
    "sg:province":"MA",
    "wof:name":"Everette Upholstery Company",
    "wof:placetype":"venue"
},
  "geometry": {"coordinates":[-71.06547399999999,42.418161],"type":"Point"}
}