{
  "type": "Feature",
  "properties": {
    "addr:full": "132 Brookline Ave Boston MA 02215",
    "addr:housenumber": "132",
    "addr:postcode": "02215",
    "addr:street": "Brookline Ave",
    "iso:country": "US",
    "sg:address": "132 Brookline Ave",
    "sg:city": "Boston",
    "sg:classifiers": [
      {
        "category": "Manufacturing",
        "subcategory": "Printing",
        "type": "Manufacturing \u0026 Wholesale Goods"
      }
    ],
    "sg:phone": "+1 617 731 7900",
    "sg:postcode": "02215",
    "sg:province": "MA",
    "sg:tags": [
      "printer"
    ],
    "sg:website": "www.mmpbrookline.com",
    "wof:name": "Minuteman Press",
    "wof:placetype": "venue"
  },
  "geometry": {"coordinates":[-71.100435,42.345299],"type":"Point"}
}
