{
  "type": "Feature",
  "properties": {
    "addr:full":"334 Lunenburg St Fitchburg MA 01420",
    "addr:housenumber":"334",
    "addr:postcode":"01420",
    "addr:street":"Lunenburg St",
    "iso:country":"US",
    "sg:address":"334 Lunenburg St",
    "sg:city":"Fitchburg",
    "sg:classifiers":[
        {
            "category":"Real Estate",
            "subcategory":"Real Estate Agent",
            "type":"Services"
        }
    ],
    "sg:phone":"+1 978 342 6300",
    "sg:postcode":"01420",
    "sg:province":"MA",
    "sg:website":"www.alpharealestate.net",
    "wof:name":"Alpha Real Estate",
    "wof:placetype":"venue"
},
  "geometry": {"coordinates":[-71.77378400000001,42.586047],"type":"Point"}
}