{
  "type": "Feature",
  "properties": {
    "addr:full":"276 Highland Ave Salem MA 01970",
    "addr:housenumber":"276",
    "addr:postcode":"01970",
    "addr:street":"Highland Ave",
    "iso:country":"US",
    "sg:address":"276 Highland Ave",
    "sg:city":"Salem",
    "sg:classifiers":[
        {
            "category":"Personal",
            "subcategory":"Beauty Salon",
            "type":"Services"
        },
        {
            "category":"Personal",
            "subcategory":"Barber",
            "type":"Services"
        }
    ],
    "sg:phone":"+1 978 744 5480",
    "sg:postcode":"01970",
    "sg:province":"MA",
    "sg:tags":[
        "hair",
        "accessory",
        "stylist",
        "supply"
    ],
    "sg:website":"http://www.supercuts.com/",
    "wof:name":"Supercuts",
    "wof:placetype":"venue"
},
  "geometry": {"coordinates":[-70.924212,42.50284],"type":"Point"}
}