{
  "type": "Feature",
  "properties": {
    "addr:full": "3 Owl Dr Sharon MA 02067",
    "addr:housenumber": "3",
    "addr:postcode": "02067",
    "addr:street": "Owl Dr",
    "iso:country": "US",
    "sg:address": "3 Owl Dr",
    "sg:city": "Sharon",
    "sg:classifiers": [
      {
        "category": "Organizations",
        "subcategory": "Professional Association",
        "type": "Services"
      }
    ],
    "sg:phone": "+1   ",
    "sg:postcode": "02067",
    "sg:province": "MA",
    "sg:tags": [
      "trade"
    ],
    "wof:name": "New England Chapter Archtctrl",
    "wof:placetype": "venue"
  },
  "geometry": {"coordinates":[-71.184712,42.089914],"type":"Point"}
}
