{
  "type": "Feature",
  "properties": {
    "addr:full": "48 Garden St West Springfield MA 01089",
    "addr:housenumber": "48",
    "addr:postcode": "01089",
    "addr:street": "Garden St",
    "iso:country": "US",
    "sg:address": "48 Garden St",
    "sg:city": "West Springfield",
    "sg:classifiers": [
      {
        "category": "Organizations",
        "subcategory": "Religious Organization",
        "type": "Services"
      }
    ],
    "sg:phone": "+1 413 737 6056",
    "sg:postcode": "01089",
    "sg:province": "MA",
    "sg:tags": [
      "church"
    ],
    "wof:name": "Gospel Hall",
    "wof:placetype": "venue"
  },
  "geometry": {"coordinates":[-72.619898,42.109995],"type":"Point"}
}
