{
  "type": "Feature",
  "properties": {
    "addr:full": "21 Washington St Newburyport MA 01950",
    "addr:housenumber": "21",
    "addr:postcode": "01950",
    "addr:street": "Washington St",
    "iso:country": "US",
    "sg:address": "21 Washington St",
    "sg:city": "Newburyport",
    "sg:classifiers": [
      {
        "category": "Professional",
        "subcategory": "Lawyer \u0026 Legal Services",
        "type": "Services"
      }
    ],
    "sg:phone": "+1 978 476 9896",
    "sg:postcode": "01950",
    "sg:province": "MA",
    "sg:tags": [
      "plan"
    ],
    "wof:name": "Nathan M Cenower",
    "wof:placetype": "venue"
  },
  "geometry": {"coordinates":[-70.875397,42.810631],"type":"Point"}
}
