{
  "type": "Feature",
  "properties": {
    "iso:country":"US",
    "sg:address":"21 Washington St",
    "sg:city":"Newburyport",
    "sg:classifiers":[
        {
            "category":"Professional",
            "subcategory":"Lawyer & Legal Services",
            "type":"Services"
        }
    ],
    "sg:phone":"+1 978 476 9896",
    "sg:postcode":"01950",
    "sg:province":"MA",
    "sg:tags":[
        "plan"
    ],
    "wof:name":"Nathan M Cenower",
    "wof:placetype":"venue"
},
  "geometry": {"coordinates":[-70.87539700000001,42.810631],"type":"Point"}
}