{
  "type": "Feature",
  "properties": {
    "addr:full": "122 Princeton Blvd Lowell MA 01851",
    "addr:housenumber": "122",
    "addr:postcode": "01851",
    "addr:street": "Princeton Blvd",
    "iso:country": "US",
    "ovtr:label": "Morse-Bayliss Funeral Home, 122 Princeton Blvd Lowell MA US",
    "ovtr:similarity": 2.945033073425293,
    "sg:address": "122 Princeton Blvd",
    "sg:city": "Lowell",
    "sg:classifiers": [
      {
        "category": "Retail",
        "subcategory": "Funeral Services",
        "type": "Services"
      }
    ],
    "sg:phone": "+1 978 458 6841",
    "sg:postcode": "01851",
    "sg:province": "MA",
    "wof:name": "Morse Bayliss Funeral Home",
    "wof:placetype": "venue"
  },
  "geometry": {"coordinates":[-71.335917,42.635096],"type":"Point"}
}
