{
  "type": "Feature",
  "properties": {
    "iso:country":"US",
    "sg:address":"122 Princeton Blvd",
    "sg:city":"Lowell",
    "sg:classifiers":[
        {
            "category":"Retail",
            "subcategory":"Funeral Services",
            "type":"Services"
        }
    ],
    "sg:phone":"+1 978 458 6841",
    "sg:postcode":"01851",
    "sg:province":"MA",
    "wof:name":"Morse Bayliss Funeral Home",
    "wof:placetype":"venue"
},
  "geometry": {"coordinates":[-71.33591699999999,42.635096],"type":"Point"}
}