{
  "type": "Feature",
  "properties": {
    "addr:full": "11 Fairmount Ave Hyde Park MA 02136",
    "addr:housenumber": "11",
    "addr:postcode": "02136",
    "addr:street": "Fairmount Ave",
    "iso:country": "US",
    "sg:address": "11 Fairmount Ave",
    "sg:city": "Hyde Park",
    "sg:classifiers": [
      {
        "category": "Professional",
        "subcategory": "Lawyer \u0026 Legal Services",
        "type": "Services"
      }
    ],
    "sg:phone": "+1 617 364 5577",
    "sg:postcode": "02136",
    "sg:province": "MA",
    "sg:tags": [
      "attorney"
    ],
    "wof:name": "John C Mc Donald Attorney",
    "wof:placetype": "venue"
  },
  "geometry": {"coordinates":[-71.120541,42.255207],"type":"Point"}
}
