{
  "type": "Feature",
  "properties": {
    "iso:country":"US",
    "sg:address":"209 Green St",
    "sg:city":"Jamaica Plain",
    "sg:classifiers":[
        {
            "category":"Education",
            "subcategory":"College",
            "type":"Public Place"
        }
    ],
    "sg:phone":"+1 617 522 8567",
    "sg:postcode":"02130",
    "sg:province":"MA",
    "sg:tags":[
        "academic",
        "school"
    ],
    "sg:website":"www.umass.edu",
    "wof:name":"UMASS Extension Nutrition",
    "wof:placetype":"venue"
},
  "geometry": {"coordinates":[-71.105408,42.309787],"type":"Point"}
}