{
  "type": "Feature",
  "properties": {
    "addr:full": "7 Bushnell Dr Lexington MA 02421",
    "addr:housenumber": "7",
    "addr:postcode": "02421",
    "addr:street": "Bushnell Dr",
    "iso:country": "US",
    "sg:address": "7 Bushnell Dr",
    "sg:city": "Lexington",
    "sg:classifiers": [
      {
        "category": "Arts \u0026 Performance",
        "subcategory": "Theater",
        "type": "Entertainment"
      }
    ],
    "sg:phone": "+1   ",
    "sg:postcode": "02421",
    "sg:province": "MA",
    "sg:tags": [
      "group"
    ],
    "wof:name": "Vocal Parts",
    "wof:placetype": "venue"
  },
  "geometry": {"coordinates":[-71.233903,42.440594],"type":"Point"}
}
