{
  "type": "Feature",
  "properties": {
    "addr:full": "32 Central St Millville MA 01529",
    "addr:housenumber": "32",
    "addr:postcode": "01529",
    "addr:street": "Central St",
    "iso:country": "US",
    "sg:address": "32 Central St",
    "sg:city": "Millville",
    "sg:classifiers": [
      {
        "category": "Restaurant",
        "type": "Food \u0026 Drink"
      }
    ],
    "sg:phone": "+1 508 883 7100",
    "sg:postcode": "01529",
    "sg:province": "MA",
    "sg:tags": [
      "pizza"
    ],
    "wof:name": "Onnies \u0026 Nonnies Inc",
    "wof:placetype": "venue"
  },
  "geometry": {"coordinates":[-71.582043,42.025514],"type":"Point"}
}
