{
  "type": "Feature",
  "properties": {
    "iso:country":"US",
    "sg:address":"32 Central St",
    "sg:city":"Millville",
    "sg:classifiers":[
        {
            "category":"Restaurant",
            "type":"Food & Drink"
        }
    ],
    "sg:phone":"+1 508 883 7100",
    "sg:postcode":"01529",
    "sg:province":"MA",
    "sg:tags":[
        "pizza"
    ],
    "wof:name":"Onnies & Nonnies Inc",
    "wof:placetype":"venue"
},
  "geometry": {"coordinates":[-71.582043,42.025514],"type":"Point"}
}