{
  "type": "Feature",
  "properties": {
    "addr:full":"70 Billings Rd North Quincy MA 02171",
    "addr:housenumber":"70",
    "addr:postcode":"02171",
    "addr:street":"Billings Rd",
    "iso:country":"US",
    "sg:address":"70 Billings Rd",
    "sg:city":"North Quincy",
    "sg:classifiers":[
        {
            "category":"Retail",
            "subcategory":"Repair Shop",
            "type":"Services"
        }
    ],
    "sg:phone":"+1 617 328 5228",
    "sg:postcode":"02171",
    "sg:province":"MA",
    "sg:tags":[
        "upholsterer"
    ],
    "wof:name":"Accent Upholstery",
    "wof:placetype":"venue"
},
  "geometry": {"coordinates":[-71.02394,42.27429],"type":"Point"}
}