{
  "type": "Feature",
  "properties": {
    "iso:country":"US",
    "sg:address":"15 Town Forest Rd",
    "sg:city":"Webster",
    "sg:classifiers":[
        {
            "category":"Manufacturing",
            "subcategory":"Tools & Machinery",
            "type":"Manufacturing & Wholesale Goods"
        }
    ],
    "sg:phone":"+1 508 949 1105",
    "sg:postcode":"01570",
    "sg:province":"MA",
    "sg:tags":[
        "machine",
        "shop"
    ],
    "sg:website":"www.htmachine.com",
    "wof:name":"H T Machine Co",
    "wof:placetype":"venue"
},
  "geometry": {"coordinates":[-71.863681,42.081193],"type":"Point"}
}