{
  "type": "Feature",
  "properties": {
    "addr:full": "39 Adams St Braintree MA 02184",
    "addr:housenumber": "39",
    "addr:postcode": "02184",
    "addr:street": "Adams St",
    "iso:country": "US",
    "sg:address": "39 Adams St",
    "sg:city": "Braintree",
    "sg:classifiers": [
      {
        "category": "Freight",
        "type": "Transportation"
      }
    ],
    "sg:phone": "+1 781 380 0728",
    "sg:postcode": "02184",
    "sg:province": "MA",
    "wof:name": "Braintree Public Schools",
    "wof:placetype": "venue"
  },
  "geometry": {"coordinates":[-70.99659,42.22462],"type":"Point"}
}
