{
  "type": "Feature",
  "properties": {
    "addr:full":"4 West St Reading MA 01867",
    "addr:housenumber":"4",
    "addr:postcode":"01867",
    "addr:street":"West St",
    "iso:country":"US",
    "sg:address":"4 West St",
    "sg:city":"Reading",
    "sg:classifiers":[
        {
            "category":"Food & Beverages",
            "subcategory":"Bakery",
            "type":"Retail Goods"
        }
    ],
    "sg:phone":"+1 781 944 3744",
    "sg:postcode":"01867",
    "sg:province":"MA",
    "sg:tags":[
        "donut",
        "doughnut"
    ],
    "sg:website":"www.dunkindonuts.com",
    "wof:name":"Dunkin Donuts",
    "wof:placetype":"venue"
},
  "geometry": {"coordinates":[-71.124064,42.508498],"type":"Point"}
}