{
  "type": "Feature",
  "properties": {
    "iso:country":"US",
    "sg:address":"3131 Cranberry Hwy",
    "sg:city":"East Wareham",
    "sg:classifiers":[
        {
            "category":"Autos & Motor Vehicles",
            "subcategory":"Automobile Sales",
            "type":"Retail Goods"
        }
    ],
    "sg:phone":"+1 508 759 9888",
    "sg:postcode":"02538",
    "sg:province":"MA",
    "sg:tags":[
        "car"
    ],
    "wof:name":"Cranberry Chevrolet Olds Inc",
    "wof:placetype":"venue"
},
  "geometry": {"coordinates":[-70.65589900000001,41.757301],"type":"Point"}
}