{
  "type": "Feature",
  "properties": {
    "addr:full": "23 Randolph Pl Northampton MA 01060",
    "addr:housenumber": "23",
    "addr:postcode": "01060",
    "addr:street": "Randolph Pl",
    "iso:country": "US",
    "sg:address": "23 Randolph Pl",
    "sg:city": "Northampton",
    "sg:classifiers": [
      {
        "category": "Social Services",
        "type": "Services"
      }
    ],
    "sg:phone": "+1 413 585 0957",
    "sg:postcode": "01060",
    "sg:province": "MA",
    "sg:tags": [
      "worker"
    ],
    "wof:name": "Rose Maloof",
    "wof:placetype": "venue"
  },
  "geometry": {"coordinates":[-72.626967,42.317419],"type":"Point"}
}
