{
  "type": "Feature",
  "properties": {
    "addr:full":"10 Ferry Wharf Newburyport MA 01950",
    "addr:housenumber":"10",
    "addr:postcode":"01950",
    "addr:street":"Ferry Wharf",
    "iso:country":"US",
    "sg:address":"10 Ferry Wharf",
    "sg:city":"Newburyport",
    "sg:classifiers":[
        {
            "category":"Shopping",
            "subcategory":"Computers & Home Electronics",
            "type":"Retail Goods"
        }
    ],
    "sg:phone":"+1 978 462 3329",
    "sg:postcode":"01950",
    "sg:province":"MA",
    "sg:tags":[
        "equipment",
        "dealer"
    ],
    "wof:name":"Michaura Systems Corp",
    "wof:placetype":"venue"
},
  "geometry": {"coordinates":[-70.868748,42.811849],"type":"Point"}
}