{
  "type": "Feature",
  "properties": {
    "addr:full":"1019 Iyannough Rd Hyannis MA 02601",
    "addr:housenumber":"1019",
    "addr:postcode":"02601",
    "addr:street":"Iyannough Rd",
    "iso:country":"US",
    "sg:address":"1019 Iyannough Rd",
    "sg:city":"Hyannis",
    "sg:classifiers":[
        {
            "category":"Real Estate",
            "subcategory":"Architect",
            "type":"Services"
        }
    ],
    "sg:phone":"+1 508 771 9933",
    "sg:postcode":"02601",
    "sg:province":"MA",
    "wof:name":"Deacon Associates",
    "wof:placetype":"venue"
},
  "geometry": {"coordinates":[-70.30374399999999,41.672436],"type":"Point"}
}