{
  "type": "Feature",
  "properties": {
    "addr:full":"1 Farnham St Lowell MA 01854",
    "addr:housenumber":"1",
    "addr:postcode":"01854",
    "addr:street":"Farnham St",
    "iso:country":"US",
    "sg:address":"1 Farnham St",
    "sg:city":"Lowell",
    "sg:classifiers":[
        {
            "category":"Restaurant",
            "type":"Food & Drink"
        }
    ],
    "sg:menulink":"http://www.allmenus.com/ma/lowell/188626-mcdonalds/menu/",
    "sg:postcode":"01854",
    "sg:province":"MA",
    "sg:tags":[
        "burger",
        "american"
    ],
    "wof:name":"McDonald's",
    "wof:placetype":"venue"
},
  "geometry": {"coordinates":[-71.321726,42.643037],"type":"Point"}
}