{
  "type": "Feature",
  "properties": {
    "addr:full": "2685 Nauset Rd Eastham MA 02642",
    "addr:housenumber": "2685",
    "addr:postcode": "02642",
    "addr:street": "Nauset Rd",
    "iso:country": "US",
    "sg:address": "2685 Nauset Rd",
    "sg:city": "Eastham",
    "sg:classifiers": [
      {
        "category": "Retail",
        "subcategory": "Animal Services",
        "type": "Services"
      }
    ],
    "sg:phone": "+1 508 255 0081",
    "sg:postcode": "02642",
    "sg:province": "MA",
    "sg:tags": [
      "pet",
      "boarding",
      "sitting"
    ],
    "wof:name": "Nauset Kennels",
    "wof:placetype": "venue"
  },
  "geometry": {"coordinates":[-69.982597,41.864531],"type":"Point"}
}
