{
  "type": "Feature",
  "properties": {
    "iso:country":"US",
    "sg:address":"85 Federal St",
    "sg:city":"Salem",
    "sg:classifiers":[
        {
            "category":"Retail",
            "subcategory":"Funeral Services",
            "type":"Services"
        }
    ],
    "sg:phone":"+1 978 744 0497",
    "sg:postcode":"01970",
    "sg:province":"MA",
    "sg:tags":[
        "director"
    ],
    "sg:website":"www.murphyfuneralhome.com",
    "wof:name":"Murphy Funeral Home",
    "wof:placetype":"venue"
},
  "geometry": {"coordinates":[-70.899494,42.522571],"type":"Point"}
}