{
  "type": "Feature",
  "properties": {
    "addr:full": "21 Turnpike Rd Southborough MA 01772",
    "addr:housenumber": "21",
    "addr:postcode": "01772",
    "addr:street": "Turnpike Rd",
    "iso:country": "US",
    "ovtr:label": "Subway, 21 Turnpike Rd Southborough MA US",
    "ovtr:similarity": 2.6636900901794434,
    "sg:address": "21 Turnpike Rd",
    "sg:city": "Southborough",
    "sg:classifiers": [
      {
        "category": "Fast Food",
        "type": "Food \u0026 Drink"
      },
      {
        "category": "Restaurant",
        "type": "Food \u0026 Drink"
      },
      {
        "category": "Food \u0026 Beverages",
        "subcategory": "Groceries \u0026 Convenience Stores",
        "type": "Retail Goods"
      }
    ],
    "sg:phone": "+1 508 460 8488",
    "sg:postcode": "01772",
    "sg:province": "MA",
    "sg:tags": [
      "shop",
      "american",
      "sandwich",
      "take"
    ],
    "sg:website": "http://www.subway.com",
    "wof:name": "Subway",
    "wof:placetype": "venue"
  },
  "geometry": {"coordinates":[-71.496223,42.296459],"type":"Point"}
}
