{
  "type": "Feature",
  "properties": {
    "iso:country":"US",
    "sg:address":"1000 Technology Park Dr",
    "sg:city":"Billerica",
    "sg:classifiers":[
        {
            "category":"Wholesale",
            "subcategory":"Durable Goods & Equipment",
            "type":"Manufacturing & Wholesale Goods"
        }
    ],
    "sg:phone":"+1 978 663 3933",
    "sg:postcode":"01821",
    "sg:province":"MA",
    "sg:tags":[
        "representative",
        "manufacturer"
    ],
    "wof:name":"Jaybe El Assoc",
    "wof:placetype":"venue"
},
  "geometry": {"coordinates":[-71.274552,42.528653],"type":"Point"}
}