{
  "type": "Feature",
  "properties": {
    "addr:full": "1000 Technology Park Dr Billerica MA 01821",
    "addr:housenumber": "1000",
    "addr:postcode": "01821",
    "addr:street": "Technology Park Dr",
    "iso:country": "US",
    "sg:address": "1000 Technology Park Dr",
    "sg:city": "Billerica",
    "sg:classifiers": [
      {
        "category": "Wholesale",
        "subcategory": "Durable Goods \u0026 Equipment",
        "type": "Manufacturing \u0026 Wholesale Goods"
      }
    ],
    "sg:phone": "+1 978 663 3933",
    "sg:postcode": "01821",
    "sg:province": "MA",
    "sg:tags": [
      "representative",
      "manufacturer"
    ],
    "wof:name": "Jaybe El Assoc",
    "wof:placetype": "venue"
  },
  "geometry": {"coordinates":[-71.274552,42.528653],"type":"Point"}
}
