{
  "type": "Feature",
  "properties": {
    "addr:full": "139 Central Ave Lynn MA 01901",
    "addr:housenumber": "139",
    "addr:postcode": "01901",
    "addr:street": "Central Ave",
    "iso:country": "US",
    "ovtr:label": "Juvenile Court, 139 Central Ave Lynn MA US",
    "ovtr:similarity": 2.1856350898742676,
    "sg:address": "139 Central Ave",
    "sg:city": "Lynn",
    "sg:classifiers": [
      {
        "category": "Government",
        "subcategory": "Jail",
        "type": "Public Place"
      }
    ],
    "sg:phone": "+1 781 586 0415",
    "sg:postcode": "01901",
    "sg:province": "MA",
    "sg:tags": [
      "govt",
      "state",
      "institution"
    ],
    "wof:name": "Juvenile Court",
    "wof:placetype": "venue"
  },
  "geometry": {"coordinates":[-70.951107,42.464315],"type":"Point"}
}
