{
  "type": "Feature",
  "properties": {
    "iso:country":"US",
    "sg:address":"139 Central Ave",
    "sg:city":"Lynn",
    "sg:classifiers":[
        {
            "category":"Government",
            "subcategory":"Jail",
            "type":"Public Place"
        }
    ],
    "sg:phone":"+1 781 586 0415",
    "sg:postcode":"01901",
    "sg:province":"MA",
    "sg:tags":[
        "govt",
        "state",
        "institution"
    ],
    "wof:name":"Juvenile Court",
    "wof:placetype":"venue"
},
  "geometry": {"coordinates":[-70.95110699999999,42.464315],"type":"Point"}
}