{
  "type": "Feature",
  "properties": {
    "addr:full":"24 Longview Dr Centerville MA 02632",
    "addr:housenumber":"24",
    "addr:postcode":"02632",
    "addr:street":"Longview Dr",
    "iso:country":"US",
    "sg:address":"24 Longview Dr",
    "sg:city":"Centerville",
    "sg:classifiers":[
        {
            "category":"Building & Trades",
            "subcategory":"Landscaping Services",
            "type":"Services"
        }
    ],
    "sg:phone":"+1 508 771 1331",
    "sg:postcode":"02632",
    "sg:province":"MA",
    "sg:tags":[
        "consultant",
        "lawn",
        "designer",
        "landscape"
    ],
    "wof:name":"Kmk Landscape Design & Installation",
    "wof:placetype":"venue"
},
  "geometry": {"coordinates":[-70.319947,41.670089],"type":"Point"}
}