{
  "type": "Feature",
  "properties": {
    "iso:country":"US",
    "sg:address":"725 Summer St",
    "sg:city":"Lynn",
    "sg:classifiers":[
        {
            "category":"Retail",
            "subcategory":"Auto Repair",
            "type":"Services"
        }
    ],
    "sg:phone":"+1 781 598 0848",
    "sg:postcode":"01905",
    "sg:province":"MA",
    "sg:tags":[
        "repairing",
        "automotive",
        "automobile"
    ],
    "wof:name":"R D Automotive Inc",
    "wof:placetype":"venue"
},
  "geometry": {"coordinates":[-70.97721799999999,42.458911],"type":"Point"}
}