{
  "type": "Feature",
  "properties": {
    "iso:country":"US",
    "sg:address":"7 Elm Cir",
    "sg:city":"Townsend",
    "sg:classifiers":[
        {
            "category":"Education",
            "subcategory":"School",
            "type":"Public Place"
        }
    ],
    "sg:phone":"+1 978 597 6772",
    "sg:postcode":"01469",
    "sg:province":"MA",
    "wof:name":"Michelle Goodwin School-Dance",
    "wof:placetype":"venue"
},
  "geometry": {"coordinates":[-71.70932500000001,42.66166],"type":"Point"}
}