{
  "type": "Feature",
  "properties": {
    "addr:full": "7 Elm Cir Townsend MA 01469",
    "addr:housenumber": "7",
    "addr:postcode": "01469",
    "addr:street": "Elm Cir",
    "iso:country": "US",
    "sg:address": "7 Elm Cir",
    "sg:city": "Townsend",
    "sg:classifiers": [
      {
        "category": "Education",
        "subcategory": "School",
        "type": "Public Place"
      }
    ],
    "sg:phone": "+1 978 597 6772",
    "sg:postcode": "01469",
    "sg:province": "MA",
    "wof:name": "Michelle Goodwin School-Dance",
    "wof:placetype": "venue"
  },
  "geometry": {"coordinates":[-71.709325,42.66166],"type":"Point"}
}
