{
  "type": "Feature",
  "properties": {
    "addr:full": "10 Mazzeo Dr Randolph MA 02368",
    "addr:housenumber": "10",
    "addr:postcode": "02368",
    "addr:street": "Mazzeo Dr",
    "iso:country": "US",
    "sg:address": "10 Mazzeo Dr",
    "sg:city": "Randolph",
    "sg:classifiers": [
      {
        "category": "Health Services",
        "subcategory": "Health Practitioner",
        "type": "Services"
      }
    ],
    "sg:phone": "+1 781 986 4753",
    "sg:postcode": "02368",
    "sg:province": "MA",
    "sg:tags": [
      "psychologist"
    ],
    "wof:name": "Stephen R Blumberg",
    "wof:placetype": "venue"
  },
  "geometry": {"coordinates":[-71.056275,42.165397],"type":"Point"}
}
