{
  "type": "Feature",
  "properties": {
    "addr:full":"74 Elm St Worcester MA 01609",
    "addr:housenumber":"74",
    "addr:postcode":"01609",
    "addr:street":"Elm St",
    "iso:country":"US",
    "sg:address":"74 Elm St",
    "sg:city":"Worcester",
    "sg:classifiers":[
        {
            "category":"Real Estate",
            "subcategory":"Real Estate Agent",
            "type":"Services"
        }
    ],
    "sg:phone":"+1 508 753 9479",
    "sg:postcode":"01609",
    "sg:province":"MA",
    "wof:name":"Kevin La Hair",
    "wof:placetype":"venue"
},
  "geometry": {"coordinates":[-71.81014999999999,42.265526],"type":"Point"}
}