{
  "type": "Feature",
  "properties": {
    "iso:country":"US",
    "sg:address":"100 N Prospect St",
    "sg:city":"Amherst",
    "sg:classifiers":[
        {
            "category":"Shopping",
            "subcategory":"Jewelry",
            "type":"Retail Goods"
        },
        {
            "category":"Manufacturing",
            "subcategory":"Jewelry",
            "type":"Manufacturing & Wholesale Goods"
        }
    ],
    "sg:phone":"+1 413 253 1721",
    "sg:postcode":"01002",
    "sg:province":"MA",
    "sg:tags":[
        "manufacturer",
        "jewelers-wholesale",
        "jeweler"
    ],
    "wof:name":"S E C Designs",
    "wof:placetype":"venue"
},
  "geometry": {"coordinates":[-72.521585,42.376352],"type":"Point"}
}