{
  "type": "Feature",
  "properties": {
    "addr:full":"200 Great Rd Ste 8A-B Bedford MA 01730",
    "addr:housenumber":"200",
    "addr:postcode":"01730",
    "addr:street":"Great Rd Ste 8A-B",
    "iso:country":"US",
    "sg:address":"200 Great Rd Ste 8A-B",
    "sg:city":"Bedford",
    "sg:classifiers":[
        {
            "category":"Professional",
            "subcategory":"Accounting & Tax Preparation",
            "type":"Services"
        },
        {
            "category":"Banks & Credit Unions",
            "subcategory":"Financial Services",
            "type":"Services"
        }
    ],
    "sg:phone":"+1 781 275 1155",
    "sg:postcode":"01730",
    "sg:province":"MA",
    "sg:tags":[
        "return",
        "preparation-business",
        "taxes-consultants",
        "loan",
        "reporting",
        "representative",
        "alternative",
        "bookkeeping"
    ],
    "sg:website":"http://www.hrblock.com",
    "wof:name":"H&R Block",
    "wof:placetype":"venue"
},
  "geometry": {"coordinates":[-71.271145,42.488972],"type":"Point"}
}