{
  "type": "Feature",
  "properties": {
    "addr:full":"98 Tenean St Dorchester MA 02122",
    "addr:housenumber":"98",
    "addr:postcode":"02122",
    "addr:street":"Tenean St",
    "iso:country":"US",
    "sg:address":"98 Tenean St",
    "sg:city":"Dorchester",
    "sg:classifiers":[
        {
            "category":"Building & Trades",
            "subcategory":"Construction",
            "type":"Services"
        }
    ],
    "sg:phone":"+1 617 451 9802",
    "sg:postcode":"02122",
    "sg:province":"MA",
    "sg:tags":[
        "demolition",
        "contractor"
    ],
    "wof:name":"Emergency Demolition Co",
    "wof:placetype":"venue"
},
  "geometry": {"coordinates":[-71.04494099999999,42.292192],"type":"Point"}
}