{
  "type": "Feature",
  "properties": {
    "iso:country":"US",
    "sg:address":"8 Meadow Dr",
    "sg:city":"Lowell",
    "sg:classifiers":[
        {
            "category":"Freight",
            "type":"Transportation"
        }
    ],
    "sg:phone":"+1 978 275 2800",
    "sg:postcode":"01854",
    "sg:province":"MA",
    "sg:tags":[
        "operator",
        "local",
        "trucking"
    ],
    "wof:name":"Falardeau & Sons Movers",
    "wof:placetype":"venue"
},
  "geometry": {"coordinates":[-71.354057,42.646983],"type":"Point"}
}