{
  "type": "Feature",
  "properties": {
    "iso:country":"US",
    "sg:address":"320 Washington St",
    "sg:city":"Newton",
    "sg:classifiers":[
        {
            "category":"Travel",
            "subcategory":"Hotels & Motels",
            "type":"Entertainment"
        },
        {
            "category":"Retail",
            "subcategory":"Event Space",
            "type":"Services"
        },
        {
            "category":"Travel",
            "subcategory":"Resort",
            "type":"Entertainment"
        }
    ],
    "sg:phone":"+1 877 270 1412",
    "sg:postcode":"02458",
    "sg:province":"MA",
    "sg:tags":[
        "hall",
        "lodging",
        "banquet",
        "reception",
        "facility"
    ],
    "sg:website":"http://ad.doubleclick.net/clk;222817048;46581824;l?http://www.crowneplaza.com/redirect?path=hd&brandCode=cp&hotelCode=bosaa&_PMID=99601036&cm_mmc=mdpr-_-yellowpages-_-cp-_-bosaa",
    "wof:name":"Crowne Plaza Hotel Boston - Newton",
    "wof:placetype":"venue"
},
  "geometry": {"coordinates":[-71.186752,42.356861],"type":"Point"}
}