{
  "type": "Feature",
  "properties": {
    "addr:full": "88 King St Dorchester MA 02122",
    "addr:housenumber": "88",
    "addr:postcode": "02122",
    "addr:street": "King St",
    "iso:country": "US",
    "sg:address": "88 King St",
    "sg:city": "Dorchester",
    "sg:classifiers": [
      {
        "category": "Building \u0026 Trades",
        "subcategory": "Cleaning \u0026 Sanitation",
        "type": "Services"
      }
    ],
    "sg:phone": "+1 617 288 0699",
    "sg:postcode": "02122",
    "sg:province": "MA",
    "sg:tags": [
      "janitor"
    ],
    "wof:name": "C \u0026 G Svc",
    "wof:placetype": "venue"
  },
  "geometry": {"coordinates":[-71.053396,42.294192],"type":"Point"}
}
