{
  "type": "Feature",
  "properties": {
    "iso:country":"US",
    "sg:address":"88 King St",
    "sg:city":"Dorchester",
    "sg:classifiers":[
        {
            "category":"Building & Trades",
            "subcategory":"Cleaning & Sanitation",
            "type":"Services"
        }
    ],
    "sg:phone":"+1 617 288 0699",
    "sg:postcode":"02122",
    "sg:province":"MA",
    "sg:tags":[
        "janitor"
    ],
    "wof:name":"C & G Svc",
    "wof:placetype":"venue"
},
  "geometry": {"coordinates":[-71.05339600000001,42.294192],"type":"Point"}
}