{
  "type": "Feature",
  "properties": {
    "iso:country":"US",
    "sg:address":"60 Dunham Rd",
    "sg:city":"Beverly",
    "sg:classifiers":[
        {
            "category":"Manufacturing",
            "subcategory":"Rubber & Plastics",
            "type":"Manufacturing & Wholesale Goods"
        }
    ],
    "sg:phone":"+1 978 922 5634",
    "sg:postcode":"01915",
    "sg:province":"MA",
    "sg:website":"www.nauglermold.com",
    "wof:name":"Naugler Mold & Engineering Inc",
    "wof:placetype":"venue"
},
  "geometry": {"coordinates":[-70.87027,42.57501],"type":"Point"}
}