{
  "type": "Feature",
  "properties": {
    "addr:full":"140 S Main St Milford MA 01757",
    "addr:housenumber":"140",
    "addr:postcode":"01757",
    "addr:street":"S Main St",
    "iso:country":"US",
    "sg:address":"140 S Main St",
    "sg:city":"Milford",
    "sg:classifiers":[
        {
            "category":"Banks & Credit Unions",
            "subcategory":"Bank",
            "type":"Services"
        }
    ],
    "sg:phone":"+1 508 478 8484",
    "sg:postcode":"01757",
    "sg:province":"MA",
    "wof:name":"Strata Bank",
    "wof:placetype":"venue"
},
  "geometry": {"coordinates":[-71.517246,42.12579],"type":"Point"}
}