{
  "type": "Feature",
  "properties": {
    "iso:country":"US",
    "sg:address":"615 Hartford Pike",
    "sg:city":"Shrewsbury",
    "sg:classifiers":[
        {
            "category":"Freight",
            "type":"Transportation"
        }
    ],
    "sg:phone":"+1 508 845 6731",
    "sg:postcode":"01545",
    "sg:province":"MA",
    "sg:tags":[
        "trucking"
    ],
    "wof:name":"Mc Lean Trucking Co",
    "wof:placetype":"venue"
},
  "geometry": {"coordinates":[-71.693202,42.263379],"type":"Point"}
}