{
  "type": "Feature",
  "properties": {
    "addr:full": "1487 Main St Chatham MA 02633",
    "addr:housenumber": "1487",
    "addr:postcode": "02633",
    "addr:street": "Main St",
    "iso:country": "US",
    "ovtr:label": "The Chatham Motel, 1487 Main St Chatham MA US",
    "ovtr:similarity": 3.635814905166626,
    "sg:address": "1487 Main St",
    "sg:city": "Chatham",
    "sg:classifiers": [
      {
        "category": "Travel",
        "subcategory": "Hotels \u0026 Motels",
        "type": "Entertainment"
      }
    ],
    "sg:phone": "+1 508 945 2630",
    "sg:postcode": "02633",
    "sg:province": "MA",
    "sg:website": "www.chathammotel.com",
    "wof:name": "Chatham Motel the",
    "wof:placetype": "venue"
  },
  "geometry": {"coordinates":[-69.9888,41.682701],"type":"Point"}
}
