{
  "type": "Feature",
  "properties": {
    "iso:country":"US",
    "sg:address":"8 Foxhill Rd",
    "sg:city":"Andover",
    "sg:classifiers":[
        {
            "category":"Building & Trades",
            "subcategory":"Plumbing",
            "type":"Services"
        }
    ],
    "sg:phone":"+1 978 866 1559",
    "sg:postcode":"01810",
    "sg:province":"MA",
    "sg:tags":[
        "plumber",
        "industrial",
        "contractors-commercial"
    ],
    "wof:name":"Rivers Plumbing And Heating, Inc.",
    "wof:placetype":"venue"
},
  "geometry": {"coordinates":[-71.12749700000001,42.667873],"type":"Point"}
}