{
  "type": "Feature",
  "properties": {
    "iso:country":"US",
    "sg:address":"28 State Street",
    "sg:city":"Boston",
    "sg:classifiers":[
        {
            "category":"Professional",
            "subcategory":"Lawyer & Legal Services",
            "type":"Services"
        }
    ],
    "sg:phone":"+1 617 720 9600",
    "sg:postcode":"02109",
    "sg:province":"MA",
    "sg:tags":[
        "litigation",
        "attorney",
        "tort"
    ],
    "wof:name":"Banner Witcoff",
    "wof:placetype":"venue"
},
  "geometry": {"coordinates":[-71.05709400000001,42.358901],"type":"Point"}
}