{
  "type": "Feature",
  "properties": {
    "addr:full": "28 State Street Boston MA 02109",
    "addr:housenumber": "28",
    "addr:postcode": "02109",
    "addr:street": "State Street",
    "iso:country": "US",
    "sg:address": "28 State Street",
    "sg:city": "Boston",
    "sg:classifiers": [
      {
        "category": "Professional",
        "subcategory": "Lawyer \u0026 Legal Services",
        "type": "Services"
      }
    ],
    "sg:phone": "+1 617 720 9600",
    "sg:postcode": "02109",
    "sg:province": "MA",
    "sg:tags": [
      "litigation",
      "attorney",
      "tort"
    ],
    "wof:name": "Banner Witcoff",
    "wof:placetype": "venue"
  },
  "geometry": {"coordinates":[-71.057094,42.358901],"type":"Point"}
}
