{
  "type": "Feature",
  "properties": {
    "addr:full": "45 Broadway Somerville MA 02145",
    "addr:housenumber": "45",
    "addr:postcode": "02145",
    "addr:street": "Broadway",
    "iso:country": "US",
    "sg:address": "45 Broadway",
    "sg:city": "Somerville",
    "sg:classifiers": [
      {
        "category": "Freight",
        "type": "Transportation"
      }
    ],
    "sg:phone": "+1 617 666 1100",
    "sg:postcode": "02145",
    "sg:province": "MA",
    "sg:tags": [
      "trucking"
    ],
    "wof:name": "Broadway Brake Corp",
    "wof:placetype": "venue"
  },
  "geometry": {"coordinates":[-71.079037,42.386302],"type":"Point"}
}
