{
  "type": "Feature",
  "properties": {
    "addr:full": "63 Concord Avenue Belmont MA 02478",
    "addr:housenumber": "63",
    "addr:postcode": "02478",
    "addr:street": "Concord Avenue",
    "iso:country": "US",
    "sg:address": "63 Concord Avenue",
    "sg:city": "Belmont",
    "sg:classifiers": [
      {
        "category": "Restaurant",
        "type": "Food \u0026 Drink"
      }
    ],
    "sg:phone": "+1 617 489 4408",
    "sg:postcode": "02478",
    "sg:province": "MA",
    "wof:name": "Chilin",
    "wof:placetype": "venue"
  },
  "geometry": {"coordinates":[-71.160405,42.391419],"type":"Point"}
}
