{
  "type": "Feature",
  "properties": {
    "iso:country":"US",
    "sg:address":"355 Broadway",
    "sg:city":"Saugus",
    "sg:classifiers":[
        {
            "category":"Shopping",
            "subcategory":"Gifts & Souvenirs",
            "type":"Retail Goods"
        }
    ],
    "sg:phone":"+1 781 233 8881",
    "sg:postcode":"01906",
    "sg:province":"MA",
    "sg:tags":[
        "shop"
    ],
    "wof:name":"Cardsmart",
    "wof:placetype":"venue"
},
  "geometry": {"coordinates":[-71.01774,42.488029],"type":"Point"}
}