{
  "type": "Feature",
  "properties": {
    "iso:country":"US",
    "sg:address":"1 Boston Pl Ste 3700",
    "sg:city":"Boston",
    "sg:classifiers":[
        {
            "category":"Professional",
            "subcategory":"Lawyer & Legal Services",
            "type":"Services"
        }
    ],
    "sg:phone":"+1 617 367 2500",
    "sg:postcode":"02108",
    "sg:province":"MA",
    "sg:website":"www.davismalm.com",
    "wof:name":"Davis Malm D'agostine",
    "wof:placetype":"venue"
},
  "geometry": {"coordinates":[-71.058098,42.359001],"type":"Point"}
}