{
  "type": "Feature",
  "properties": {
    "iso:country":"US",
    "sg:address":"590 Washington St",
    "sg:city":"Canton",
    "sg:classifiers":[
        {
            "category":"Banks & Credit Unions",
            "subcategory":"Financial Services",
            "type":"Services"
        }
    ],
    "sg:phone":"+1 781 575 6360",
    "sg:postcode":"02021",
    "sg:province":"MA",
    "sg:tags":[
        "broker",
        "mortgage"
    ],
    "wof:name":"Acela Financial",
    "wof:placetype":"venue"
},
  "geometry": {"coordinates":[-71.146514,42.153701],"type":"Point"}
}