{
  "type": "Feature",
  "properties": {
    "addr:full":"595 Washington St Canton MA 02021",
    "addr:housenumber":"595",
    "addr:postcode":"02021",
    "addr:street":"Washington St",
    "iso:country":"US",
    "sg:address":"595 Washington St",
    "sg:city":"Canton",
    "sg:classifiers":[
        {
            "category":"Wholesale",
            "subcategory":"Medical Equipment & Supplies",
            "type":"Manufacturing & Wholesale Goods"
        },
        {
            "category":"Shopping",
            "subcategory":"Pharmacy",
            "type":"Retail Goods"
        }
    ],
    "sg:phone":"+1 781 828 2375",
    "sg:postcode":"02021",
    "sg:province":"MA",
    "sg:tags":[
        "health",
        "aid",
        "home",
        "first",
        "drugstore",
        "care"
    ],
    "sg:website":"www.walgreens.com",
    "wof:name":"Walgreen Drug Stores",
    "wof:placetype":"venue"
},
  "geometry": {"coordinates":[-71.1465,42.153702],"type":"Point"}
}