{
  "type": "Feature",
  "properties": {
    "addr:full": "3 Genoa Ave Saugus MA 01906",
    "addr:housenumber": "3",
    "addr:postcode": "01906",
    "addr:street": "Genoa Ave",
    "iso:country": "US",
    "sg:address": "3 Genoa Ave",
    "sg:city": "Saugus",
    "sg:classifiers": [
      {
        "category": "Wholesale",
        "subcategory": "Electrical",
        "type": "Manufacturing \u0026 Wholesale Goods"
      }
    ],
    "sg:phone": "+1 781 231 0392",
    "sg:postcode": "01906",
    "sg:province": "MA",
    "sg:tags": [
      "alarm",
      "burglar",
      "system"
    ],
    "wof:name": "Alarm Controls Systems Inc",
    "wof:placetype": "venue"
  },
  "geometry": {"coordinates":[-70.995631,42.44759],"type":"Point"}
}
