{
  "type": "Feature",
  "properties": {
    "iso:country":"US",
    "sg:address":"100 Union St",
    "sg:city":"Attleboro",
    "sg:classifiers":[
        {
            "category":"Government",
            "subcategory":"Office",
            "type":"Public Place"
        }
    ],
    "sg:phone":"+1 508 223 2200",
    "sg:postcode":"02703",
    "sg:province":"MA",
    "sg:tags":[
        "civil",
        "defense",
        "agency"
    ],
    "wof:name":"Attleboro Emergency Management",
    "wof:placetype":"venue"
},
  "geometry": {"coordinates":[-71.282624,41.942139],"type":"Point"}
}