{
  "type": "Feature",
  "properties": {
    "iso:country":"US",
    "sg:address":"881 Liberty St",
    "sg:city":"Springfield",
    "sg:classifiers":[
        {
            "category":"Personal",
            "subcategory":"Barber",
            "type":"Services"
        }
    ],
    "sg:phone":"+1 413 732 8415",
    "sg:postcode":"01104",
    "sg:province":"MA",
    "wof:name":"Casey's Barber Shop",
    "wof:placetype":"venue"
},
  "geometry": {"coordinates":[-72.58440299999999,42.127874],"type":"Point"}
}