{
  "type": "Feature",
  "properties": {
    "addr:full":"Today's Fitness Center 35 Industrial Parkway Woburn MA 01801",
    "addr:housenumber":"35",
    "addr:postcode":"01801",
    "addr:street":"Fitness;Industrial Parkway",
    "iso:country":"US",
    "sg:address":"Today's Fitness Center 35 Industrial Parkway",
    "sg:city":"Woburn",
    "sg:classifiers":[
        {
            "category":"Sports & Exercise",
            "subcategory":"Gym",
            "type":"Entertainment"
        }
    ],
    "sg:phone":"+1 617 834 4776",
    "sg:postcode":"01801",
    "sg:province":"MA",
    "sg:tags":[
        "trainer"
    ],
    "sg:website":"www.fitzroy-bramble.com/fitness",
    "wof:name":"Personal Fitness Training with Fitzroy Bramble",
    "wof:placetype":"venue"
},
  "geometry": {"coordinates":[-71.14131500000001,42.506629],"type":"Point"}
}