{
  "type": "Feature",
  "properties": {
    "addr:full":"484 W Main St Hyannis MA 02601",
    "addr:housenumber":"484",
    "addr:postcode":"02601",
    "addr:street":"W Main St",
    "iso:country":"US",
    "sg:address":"484 W Main St",
    "sg:city":"Hyannis",
    "sg:classifiers":[
        {
            "category":"Shopping",
            "subcategory":"Florist",
            "type":"Retail Goods"
        }
    ],
    "sg:phone":"+1 508 775 0095",
    "sg:postcode":"02601",
    "sg:province":"MA",
    "wof:name":"Bassett's Flower Shop",
    "wof:placetype":"venue"
},
  "geometry": {"coordinates":[-70.313103,41.650002],"type":"Point"}
}