{
  "type": "Feature",
  "properties": {
    "iso:country":"US",
    "sg:address":"8 Hancock St",
    "sg:city":"Braintree",
    "sg:classifiers":[
        {
            "category":"Shopping",
            "subcategory":"Pharmacy",
            "type":"Retail Goods"
        }
    ],
    "sg:phone":"+1 781 380 0906",
    "sg:postcode":"02184",
    "sg:province":"MA",
    "wof:name":"Medicine Shoppe Pharmacy",
    "wof:placetype":"venue"
},
  "geometry": {"coordinates":[-71.005015,42.201598],"type":"Point"}
}