{
  "type": "Feature",
  "properties": {
    "addr:full":"101 Cranberry Hwy Sagamore MA 02561",
    "addr:housenumber":"101",
    "addr:postcode":"02561",
    "addr:street":"Cranberry Hwy",
    "iso:country":"US",
    "sg:address":"101 Cranberry Hwy",
    "sg:city":"Sagamore",
    "sg:classifiers":[
        {
            "category":"Shopping",
            "subcategory":"Bicycles & Sporting Goods",
            "type":"Retail Goods"
        }
    ],
    "sg:phone":"+1 508 833 2996",
    "sg:postcode":"02561",
    "sg:province":"MA",
    "sg:tags":[
        "tackle",
        "fishing"
    ],
    "wof:name":"Canal Bait & Tackle",
    "wof:placetype":"venue"
},
  "geometry": {"coordinates":[-70.529352,41.77001],"type":"Point"}
}