{
  "type": "Feature",
  "properties": {
    "iso:country":"US",
    "sg:address":"80 Atlantic Avenue",
    "sg:city":"Boston",
    "sg:classifiers":[
        {
            "category":"Bars & Pubs",
            "type":"Food & Drink"
        },
        {
            "category":"Restaurant",
            "type":"Food & Drink"
        }
    ],
    "sg:phone":"+1 617 227 7280",
    "sg:postcode":"02110",
    "sg:province":"MA",
    "sg:tags":[
        "traditional",
        "american",
        "style",
        "seafood",
        "family"
    ],
    "wof:name":"The Boston Sail Loft",
    "wof:placetype":"venue"
},
  "geometry": {"coordinates":[-71.051029,42.362906],"type":"Point"}
}