{
  "type": "Feature",
  "properties": {
    "addr:full": "80 Atlantic Avenue Boston MA 02110",
    "addr:housenumber": "80",
    "addr:postcode": "02110",
    "addr:street": "Atlantic Avenue",
    "iso:country": "US",
    "ovtr:label": "Boston Sail Loft, 80 Atlantic Ave Boston MA US",
    "ovtr:similarity": 3.5172760486602783,
    "sg:address": "80 Atlantic Avenue",
    "sg:city": "Boston",
    "sg:classifiers": [
      {
        "category": "Bars \u0026 Pubs",
        "type": "Food \u0026 Drink"
      },
      {
        "category": "Restaurant",
        "type": "Food \u0026 Drink"
      }
    ],
    "sg:phone": "+1 617 227 7280",
    "sg:postcode": "02110",
    "sg:province": "MA",
    "sg:tags": [
      "traditional",
      "american",
      "style",
      "seafood",
      "family"
    ],
    "wof:name": "The Boston Sail Loft",
    "wof:placetype": "venue"
  },
  "geometry": {"coordinates":[-71.051029,42.362906],"type":"Point"}
}
