{
  "type": "Feature",
  "properties": {
    "iso:country":"US",
    "sg:address":"22 Mill St Ste 306",
    "sg:city":"Arlington",
    "sg:classifiers":[
        {
            "category":"Health Services",
            "subcategory":"Doctor",
            "type":"Services"
        }
    ],
    "sg:phone":"+1 781 643 0610",
    "sg:postcode":"02476",
    "sg:province":"MA",
    "sg:tags":[
        "medicine",
        "physician",
        "surgeon",
        "forensic",
        "surgeons"
    ],
    "sg:website":"http://www.nemanet.org",
    "wof:name":"Ball, Carol J",
    "wof:placetype":"venue"
},
  "geometry": {"coordinates":[-71.15781200000001,42.41725],"type":"Point"}
}