{
  "type": "Feature",
  "properties": {
    "addr:full": "22 Mill St Ste 306 Arlington MA 02476",
    "addr:housenumber": "22",
    "addr:postcode": "02476",
    "addr:street": "Mill St Ste 306",
    "iso:country": "US",
    "sg:address": "22 Mill St Ste 306",
    "sg:city": "Arlington",
    "sg:classifiers": [
      {
        "category": "Health Services",
        "subcategory": "Doctor",
        "type": "Services"
      }
    ],
    "sg:phone": "+1 781 643 0610",
    "sg:postcode": "02476",
    "sg:province": "MA",
    "sg:tags": [
      "medicine",
      "physician",
      "surgeon",
      "forensic",
      "surgeons"
    ],
    "sg:website": "http://www.nemanet.org",
    "wof:name": "Ball, Carol J",
    "wof:placetype": "venue"
  },
  "geometry": {"coordinates":[-71.157812,42.41725],"type":"Point"}
}
