{
  "type": "Feature",
  "properties": {
    "iso:country":"US",
    "sg:address":"19 Central St",
    "sg:city":"Berlin",
    "sg:classifiers":[
        {
            "category":"Shopping",
            "subcategory":"Discount & Variety Stores",
            "type":"Retail Goods"
        }
    ],
    "sg:phone":"+1 978 838 2459",
    "sg:postcode":"01503",
    "sg:province":"MA",
    "sg:tags":[
        "merchandise",
        "general"
    ],
    "wof:name":"Berlin General Store",
    "wof:placetype":"venue"
},
  "geometry": {"coordinates":[-71.634596,42.38132],"type":"Point"}
}