{
  "type": "Feature",
  "properties": {
    "addr:full":"2480 Green River Rd Williamstown MA 01267",
    "addr:housenumber":"2480",
    "addr:postcode":"01267",
    "addr:street":"Green River Rd",
    "iso:country":"US",
    "sg:address":"2480 Green River Rd",
    "sg:city":"Williamstown",
    "sg:classifiers":[
        {
            "category":"Farming",
            "subcategory":"Farm",
            "type":"Manufacturing & Wholesale Goods"
        }
    ],
    "sg:phone":"+1 413 458 1831",
    "sg:postcode":"01267",
    "sg:province":"MA",
    "wof:name":"Green River Farms",
    "wof:placetype":"venue"
},
  "geometry": {"coordinates":[-73.24083400000001,42.660882],"type":"Point"}
}