{
  "type": "Feature",
  "properties": {
    "addr:full":"26 Linda Rd Wakefield MA 01880",
    "addr:housenumber":"26",
    "addr:postcode":"01880",
    "addr:street":"Linda Rd",
    "iso:country":"US",
    "sg:address":"26 Linda Rd",
    "sg:city":"Wakefield",
    "sg:classifiers":[
        {
            "category":"Organizations",
            "subcategory":"Community Association",
            "type":"Services"
        }
    ],
    "sg:phone":"+1 781 245 9518",
    "sg:postcode":"01880",
    "sg:province":"MA",
    "sg:tags":[
        "club"
    ],
    "wof:name":"Quannapowitt Yacht Club",
    "wof:placetype":"venue"
},
  "geometry": {"coordinates":[-71.08452200000001,42.512643],"type":"Point"}
}