{
  "type": "Feature",
  "properties": {
    "iso:country":"US",
    "sg:address":"2000 Massachusetts Ave",
    "sg:city":"Cambridge",
    "sg:classifiers":[
        {
            "category":"Professional",
            "subcategory":"Business Services",
            "type":"Services"
        }
    ],
    "sg:phone":"+1 617 491 2106",
    "sg:postcode":"02140",
    "sg:province":"MA",
    "sg:tags":[
        "recording",
        "studio"
    ],
    "wof:name":"Moontower Recording",
    "wof:placetype":"venue"
},
  "geometry": {"coordinates":[-71.121538,42.390524],"type":"Point"}
}