{
  "type": "Feature",
  "properties": {
    "iso:country":"US",
    "sg:address":"17 Greenough Ln",
    "sg:city":"Boston",
    "sg:classifiers":[
        {
            "category":"Professional",
            "subcategory":"Computer Services",
            "type":"Services"
        }
    ],
    "sg:phone":"+1   ",
    "sg:postcode":"02113",
    "sg:province":"MA",
    "sg:tags":[
        "datum"
    ],
    "wof:name":"Data Processing Odds & En",
    "wof:placetype":"venue"
},
  "geometry": {"coordinates":[-71.053045,42.367285],"type":"Point"}
}