{
  "type": "Feature",
  "properties": {
    "iso:country":"US",
    "sg:address":"15 Court Sq",
    "sg:city":"Boston",
    "sg:classifiers":[
        {
            "category":"Professional",
            "subcategory":"Lawyer & Legal Services",
            "type":"Services"
        }
    ],
    "sg:phone":"+1 617 523 5100",
    "sg:postcode":"02108",
    "sg:province":"MA",
    "wof:name":"Shuman Harry M Atty",
    "wof:placetype":"venue"
},
  "geometry": {"coordinates":[-71.06511399999999,42.357724],"type":"Point"}
}