{
  "type": "Feature",
  "properties": {
    "iso:country":"US",
    "sg:address":"65 Church St",
    "sg:city":"Lenox",
    "sg:classifiers":[
        {
            "category":"Shopping",
            "subcategory":"Clothing, Apparel, & Fashions",
            "type":"Retail Goods"
        }
    ],
    "sg:phone":"+1 413 637 2013",
    "sg:postcode":"01240",
    "sg:province":"MA",
    "sg:tags":[
        "cloth",
        "weaved"
    ],
    "wof:name":"Weaver's Fancy",
    "wof:placetype":"venue"
},
  "geometry": {"coordinates":[-73.28227699999999,42.359143],"type":"Point"}
}