{
  "type": "Feature",
  "properties": {
    "addr:full": "65 Church St Lenox MA 01240",
    "addr:housenumber": "65",
    "addr:postcode": "01240",
    "addr:street": "Church St",
    "iso:country": "US",
    "sg:address": "65 Church St",
    "sg:city": "Lenox",
    "sg:classifiers": [
      {
        "category": "Shopping",
        "subcategory": "Clothing, Apparel, \u0026 Fashions",
        "type": "Retail Goods"
      }
    ],
    "sg:phone": "+1 413 637 2013",
    "sg:postcode": "01240",
    "sg:province": "MA",
    "sg:tags": [
      "cloth",
      "weaved"
    ],
    "wof:name": "Weaver's Fancy",
    "wof:placetype": "venue"
  },
  "geometry": {"coordinates":[-73.282277,42.359143],"type":"Point"}
}
