{
  "type": "Feature",
  "properties": {
    "iso:country":"US",
    "sg:address":"54 Suffolk St",
    "sg:city":"Worcester",
    "sg:classifiers":[
        {
            "category":"Shopping",
            "subcategory":"Used Merchandise",
            "type":"Retail Goods"
        }
    ],
    "sg:phone":"+1 508 752 5200",
    "sg:postcode":"01604",
    "sg:province":"MA",
    "sg:tags":[
        "antique"
    ],
    "wof:name":"Olde Tyme Stuffe",
    "wof:placetype":"venue"
},
  "geometry": {"coordinates":[-71.78749500000001,42.258299],"type":"Point"}
}