{
  "type": "Feature",
  "properties": {
    "addr:full": "54 Suffolk St Worcester MA 01604",
    "addr:housenumber": "54",
    "addr:postcode": "01604",
    "addr:street": "Suffolk St",
    "iso:country": "US",
    "sg:address": "54 Suffolk St",
    "sg:city": "Worcester",
    "sg:classifiers": [
      {
        "category": "Shopping",
        "subcategory": "Used Merchandise",
        "type": "Retail Goods"
      }
    ],
    "sg:phone": "+1 508 752 5200",
    "sg:postcode": "01604",
    "sg:province": "MA",
    "sg:tags": [
      "antique"
    ],
    "wof:name": "Olde Tyme Stuffe",
    "wof:placetype": "venue"
  },
  "geometry": {"coordinates":[-71.787495,42.258299],"type":"Point"}
}
