{
  "type": "Feature",
  "properties": {
    "addr:full": "733 Chapin St Ludlow MA 01056",
    "addr:housenumber": "733",
    "addr:postcode": "01056",
    "addr:street": "Chapin St",
    "iso:country": "US",
    "sg:address": "733 Chapin St",
    "sg:city": "Ludlow",
    "sg:classifiers": [
      {
        "category": "Professional",
        "subcategory": "Accounting \u0026 Tax Preparation",
        "type": "Services"
      }
    ],
    "sg:phone": "+1 413 589 0988",
    "sg:postcode": "01056",
    "sg:province": "MA",
    "sg:tags": [
      "accountant"
    ],
    "wof:name": "Gariepy \u0026 Sherman",
    "wof:placetype": "venue"
  },
  "geometry": {"coordinates":[-72.485227,42.175331],"type":"Point"}
}
