{
  "type": "Feature",
  "properties": {
    "iso:country":"US",
    "sg:address":"733 Chapin St",
    "sg:city":"Ludlow",
    "sg:classifiers":[
        {
            "category":"Professional",
            "subcategory":"Accounting & Tax Preparation",
            "type":"Services"
        }
    ],
    "sg:phone":"+1 413 589 0988",
    "sg:postcode":"01056",
    "sg:province":"MA",
    "sg:tags":[
        "accountant"
    ],
    "wof:name":"Gariepy & Sherman",
    "wof:placetype":"venue"
},
  "geometry": {"coordinates":[-72.48522699999999,42.175331],"type":"Point"}
}