{
  "type": "Feature",
  "properties": {
    "addr:full": "236 Commercial St Provincetown MA 02657",
    "addr:housenumber": "236",
    "addr:postcode": "02657",
    "addr:street": "Commercial St",
    "iso:country": "US",
    "sg:address": "236 Commercial St",
    "sg:city": "Provincetown",
    "sg:classifiers": [
      {
        "category": "Organizations",
        "subcategory": "Religious Organization",
        "type": "Services"
      }
    ],
    "sg:phone": "+1 508 487 9344",
    "sg:postcode": "02657",
    "sg:province": "MA",
    "sg:tags": [
      "church"
    ],
    "sg:website": "www.uumh.org",
    "wof:name": "Unitarian-Universalist Meeting",
    "wof:placetype": "venue"
  },
  "geometry": {"coordinates":[-70.187734,42.050651],"type":"Point"}
}
