{
  "type": "Feature",
  "properties": {
    "addr:full":"37 Harris St Webster MA 01570",
    "addr:housenumber":"37",
    "addr:postcode":"01570",
    "addr:street":"Harris St",
    "iso:country":"US",
    "sg:address":"37 Harris St",
    "sg:city":"Webster",
    "sg:classifiers":[
        {
            "category":"Organizations",
            "subcategory":"Community Association",
            "type":"Services"
        }
    ],
    "sg:phone":"+1 508 943 9716",
    "sg:postcode":"01570",
    "sg:province":"MA",
    "sg:tags":[
        "club"
    ],
    "wof:name":"Polish American Citizens Club",
    "wof:placetype":"venue"
},
  "geometry": {"coordinates":[-71.87626899999999,42.047221],"type":"Point"}
}