{
  "type": "Feature",
  "properties": {
    "iso:country":"US",
    "sg:address":"628 Somerville Ave",
    "sg:city":"Somerville",
    "sg:classifiers":[
        {
            "category":"Health Services",
            "subcategory":"Clinic",
            "type":"Services"
        },
        {
            "category":"Health Services",
            "subcategory":"Health Practitioner",
            "type":"Services"
        }
    ],
    "sg:phone":"+1 617 623 2943",
    "sg:postcode":"02143",
    "sg:province":"MA",
    "sg:tags":[
        "therapist",
        "therapy",
        "physical"
    ],
    "wof:name":"Neighborhood Physical Therapy",
    "wof:placetype":"venue"
},
  "geometry": {"coordinates":[-71.110615,42.384163],"type":"Point"}
}