{
  "type": "Feature",
  "properties": {
    "iso:country":"US",
    "sg:address":"229 Quequechan St",
    "sg:city":"Fall River",
    "sg:classifiers":[
        {
            "category":"Shopping",
            "subcategory":"Discount & Variety Stores",
            "type":"Retail Goods"
        }
    ],
    "sg:phone":"+1   ",
    "sg:postcode":"02723",
    "sg:province":"MA",
    "wof:name":"Joe S Variety",
    "wof:placetype":"venue"
},
  "geometry": {"coordinates":[-71.137413,41.692369],"type":"Point"}
}