{
  "type": "Feature",
  "properties": {
    "addr:full": "10 Eliot St Cambridge MA 02138",
    "addr:housenumber": "10",
    "addr:postcode": "02138",
    "addr:street": "Eliot St",
    "iso:country": "US",
    "sg:address": "10 Eliot St",
    "sg:city": "Cambridge",
    "sg:classifiers": [
      {
        "category": "Restaurant",
        "type": "Food \u0026 Drink"
      }
    ],
    "sg:phone": "+1 617 661 0733",
    "sg:postcode": "02138",
    "sg:province": "MA",
    "wof:name": "Ristorante Giannino",
    "wof:placetype": "venue"
  },
  "geometry": {"coordinates":[-71.121803,42.372601],"type":"Point"}
}
