{
  "type": "Feature",
  "properties": {
    "iso:country":"US",
    "sg:address":"10 Eliot St",
    "sg:city":"Cambridge",
    "sg:classifiers":[
        {
            "category":"Restaurant",
            "type":"Food & Drink"
        }
    ],
    "sg:phone":"+1 617 661 0733",
    "sg:postcode":"02138",
    "sg:province":"MA",
    "wof:name":"Ristorante Giannino",
    "wof:placetype":"venue"
},
  "geometry": {"coordinates":[-71.121803,42.372601],"type":"Point"}
}