{
  "type": "Feature",
  "properties": {
    "addr:full": "106 Main St Stoneham MA 02180",
    "addr:housenumber": "106",
    "addr:postcode": "02180",
    "addr:street": "Main St",
    "iso:country": "US",
    "sg:address": "106 Main St",
    "sg:city": "Stoneham",
    "sg:classifiers": [
      {
        "category": "Building \u0026 Trades",
        "subcategory": "Construction",
        "type": "Services"
      }
    ],
    "sg:phone": "+1 781 279 7010",
    "sg:postcode": "02180",
    "sg:province": "MA",
    "sg:tags": [
      "masonry",
      "contractor"
    ],
    "wof:name": "Zeraschi \u0026 Son",
    "wof:placetype": "venue"
  },
  "geometry": {"coordinates":[-71.10052,42.495083],"type":"Point"}
}
