{
  "type": "Feature",
  "properties": {
    "iso:country":"US",
    "sg:address":"106 Main St",
    "sg:city":"Stoneham",
    "sg:classifiers":[
        {
            "category":"Building & Trades",
            "subcategory":"Construction",
            "type":"Services"
        }
    ],
    "sg:phone":"+1 781 279 7010",
    "sg:postcode":"02180",
    "sg:province":"MA",
    "sg:tags":[
        "masonry",
        "contractor"
    ],
    "wof:name":"Zeraschi & Son",
    "wof:placetype":"venue"
},
  "geometry": {"coordinates":[-71.10052,42.495083],"type":"Point"}
}