{
  "type": "Feature",
  "properties": {
    "addr:full":"222 North St Hingham MA 02043",
    "addr:housenumber":"222",
    "addr:postcode":"02043",
    "addr:street":"North St",
    "iso:country":"US",
    "sg:address":"222 North St",
    "sg:city":"Hingham",
    "sg:classifiers":[
        {
            "category":"Food & Beverages",
            "subcategory":"Candy",
            "type":"Retail Goods"
        }
    ],
    "sg:phone":"+1 781 749 6638",
    "sg:postcode":"02043",
    "sg:province":"MA",
    "sg:tags":[
        "confectionery"
    ],
    "wof:name":"Puopolo Candies",
    "wof:placetype":"venue"
},
  "geometry": {"coordinates":[-70.89550199999999,42.242113],"type":"Point"}
}