{
  "type": "Feature",
  "properties": {
    "iso:country":"US",
    "sg:address":"126 Vale St",
    "sg:city":"Fall River",
    "sg:classifiers":[
        {
            "category":"Manufacturing",
            "subcategory":"Tools & Machinery",
            "type":"Manufacturing & Wholesale Goods"
        }
    ],
    "sg:phone":"+1 508 646 1134",
    "sg:postcode":"02724",
    "sg:province":"MA",
    "sg:tags":[
        "relay"
    ],
    "wof:name":"Meder Electronic Inc",
    "wof:placetype":"venue"
},
  "geometry": {"coordinates":[-71.16508,41.685758],"type":"Point"}
}