{
  "type": "Feature",
  "properties": {
    "iso:country":"US",
    "sg:address":"86 Marion Rd",
    "sg:city":"Mattapoisett",
    "sg:classifiers":[
        {
            "category":"Government",
            "subcategory":"Office",
            "type":"Public Place"
        }
    ],
    "sg:phone":"+1   ",
    "sg:postcode":"02739",
    "sg:province":"MA",
    "wof:name":"Sharon A Moniz",
    "wof:placetype":"venue"
},
  "geometry": {"coordinates":[-70.78475899999999,41.664571],"type":"Point"}
}