{
  "type": "Feature",
  "properties": {
    "iso:country":"US",
    "sg:address":"14 Marmion St",
    "sg:city":"Jamaica Plain",
    "sg:classifiers":[
        {
            "category":"Professional",
            "subcategory":"Business Services",
            "type":"Services"
        }
    ],
    "sg:phone":"+1   ",
    "sg:postcode":"02130",
    "sg:province":"MA",
    "wof:name":"Gourmet Goodies Inc",
    "wof:placetype":"venue"
},
  "geometry": {"coordinates":[-71.103157,42.312719],"type":"Point"}
}