{
  "type": "Feature",
  "properties": {
    "addr:full":"18 Green St Reading MA 01867",
    "addr:housenumber":"18",
    "addr:postcode":"01867",
    "addr:street":"Green St",
    "iso:country":"US",
    "sg:address":"18 Green St",
    "sg:city":"Reading",
    "sg:classifiers":[
        {
            "category":"Real Estate",
            "subcategory":"Real Estate Agent",
            "type":"Services"
        }
    ],
    "sg:phone":"+1 781 944 0314",
    "sg:postcode":"01867",
    "sg:province":"MA",
    "sg:tags":[
        "inspection"
    ],
    "wof:name":"Alternative One Hm Inspctn Svc",
    "wof:placetype":"venue"
},
  "geometry": {"coordinates":[-71.104929,42.521988],"type":"Point"}
}