{
  "type": "Feature",
  "properties": {
    "iso:country":"US",
    "sg:address":"285 Circuit St",
    "sg:city":"Hanover",
    "sg:classifiers":[
        {
            "category":"Wholesale",
            "subcategory":"Durable Goods & Equipment",
            "type":"Manufacturing & Wholesale Goods"
        }
    ],
    "sg:phone":"+1 781 871 8868",
    "sg:postcode":"02339",
    "sg:province":"MA",
    "sg:tags":[
        "instrument",
        "scientific",
        "apparatus"
    ],
    "wof:name":"BMI Electronic Brokerage",
    "wof:placetype":"venue"
},
  "geometry": {"coordinates":[-70.86689699999999,42.111287],"type":"Point"}
}