{
  "type": "Feature",
  "properties": {
    "addr:full": "285 Circuit St Hanover MA 02339",
    "addr:housenumber": "285",
    "addr:postcode": "02339",
    "addr:street": "Circuit",
    "iso:country": "US",
    "sg:address": "285 Circuit St",
    "sg:city": "Hanover",
    "sg:classifiers": [
      {
        "category": "Wholesale",
        "subcategory": "Durable Goods \u0026 Equipment",
        "type": "Manufacturing \u0026 Wholesale Goods"
      }
    ],
    "sg:phone": "+1 781 871 8868",
    "sg:postcode": "02339",
    "sg:province": "MA",
    "sg:tags": [
      "instrument",
      "scientific",
      "apparatus"
    ],
    "wof:name": "BMI Electronic Brokerage",
    "wof:placetype": "venue"
  },
  "geometry": {"coordinates":[-70.866897,42.111287],"type":"Point"}
}
