{
  "type": "Feature",
  "properties": {
    "iso:country":"US",
    "sg:address":"60 Prescott St",
    "sg:city":"Worcester",
    "sg:classifiers":[
        {
            "category":"Professional",
            "subcategory":"Engineering",
            "type":"Services"
        }
    ],
    "sg:phone":"+1 508 799 6601",
    "sg:postcode":"01605",
    "sg:province":"MA",
    "sg:tags":[
        "engineer"
    ],
    "wof:name":"Altshuller Institute",
    "wof:placetype":"venue"
},
  "geometry": {"coordinates":[-71.799367,42.275199],"type":"Point"}
}