{
  "type": "Feature",
  "properties": {
    "addr:full":"95 Topeka St Boston MA 02118",
    "addr:housenumber":"95",
    "addr:postcode":"02118",
    "addr:street":"Topeka St",
    "iso:country":"US",
    "sg:address":"95 Topeka St",
    "sg:city":"Boston",
    "sg:classifiers":[
        {
            "category":"Freight",
            "type":"Transportation"
        }
    ],
    "sg:phone":"+1 617 427 4401",
    "sg:postcode":"02118",
    "sg:province":"MA",
    "sg:tags":[
        "warehouse",
        "storage"
    ],
    "sg:website":"www.peninsulaofboston.com",
    "wof:name":"Penninsula Of Boston Inc",
    "wof:placetype":"venue"
},
  "geometry": {"coordinates":[-71.067086,42.332846],"type":"Point"}
}