{
  "type": "Feature",
  "properties": {
    "addr:full": "129 Pearl St Somerville MA 02145",
    "addr:housenumber": "129",
    "addr:postcode": "02145",
    "addr:street": "Pearl St",
    "iso:country": "US",
    "sg:address": "129 Pearl St",
    "sg:city": "Somerville",
    "sg:classifiers": [
      {
        "category": "Social Services",
        "type": "Services"
      }
    ],
    "sg:phone": "+1 617 628 5800",
    "sg:postcode": "02145",
    "sg:province": "MA",
    "sg:tags": [
      "organization",
      "welfare"
    ],
    "wof:name": "Ethnic Arts Ctr Of Somerville",
    "wof:placetype": "venue"
  },
  "geometry": {"coordinates":[-71.088827,42.386071],"type":"Point"}
}
