{
  "type": "Feature",
  "properties": {
    "addr:full":"235 Aspen Cir Lincoln MA 01773",
    "addr:housenumber":"235",
    "addr:postcode":"01773",
    "addr:street":"Aspen Cir",
    "iso:country":"US",
    "sg:address":"235 Aspen Cir",
    "sg:city":"Lincoln",
    "sg:classifiers":[
        {
            "category":"Education",
            "subcategory":"Special Training",
            "type":"Public Place"
        }
    ],
    "sg:phone":"+1   ",
    "sg:postcode":"01773",
    "sg:province":"MA",
    "wof:name":"Successfulife Coaching Inc",
    "wof:placetype":"venue"
},
  "geometry": {"coordinates":[-71.35545,42.411044],"type":"Point"}
}