{
  "type": "Feature",
  "properties": {
    "iso:country":"US",
    "sg:address":"2 Mortimer Rd",
    "sg:city":"Sterling",
    "sg:classifiers":[
        {
            "category":"Building & Trades",
            "subcategory":"Construction",
            "type":"Services"
        }
    ],
    "sg:phone":"+1 508 752 4157",
    "sg:postcode":"01564",
    "sg:province":"MA",
    "sg:tags":[
        "carpenter"
    ],
    "wof:name":"Belanger Woodworking",
    "wof:placetype":"venue"
},
  "geometry": {"coordinates":[-71.769886,42.40537],"type":"Point"}
}