{
  "type": "Feature",
  "properties": {
    "addr:full": "674 Brush Hill Rd Milton MA 02186",
    "addr:housenumber": "674",
    "addr:postcode": "02186",
    "addr:street": "Brush Hill Rd",
    "iso:country": "US",
    "sg:address": "674 Brush Hill Rd",
    "sg:city": "Milton",
    "sg:classifiers": [
      {
        "category": "Professional",
        "type": "Services"
      }
    ],
    "sg:phone": "+1   ",
    "sg:postcode": "02186",
    "sg:province": "MA",
    "wof:name": "Taber Keally Inc",
    "wof:placetype": "venue"
  },
  "geometry": {"coordinates":[-71.107959,42.246181],"type":"Point"}
}
