{
  "type": "Feature",
  "properties": {
    "iso:country":"US",
    "sg:address":"50 Walnut St",
    "sg:city":"Lynnfield",
    "sg:classifiers":[
        {
            "category":"Shopping",
            "subcategory":"Catalog Store",
            "type":"Retail Goods"
        }
    ],
    "sg:phone":"+1 781 233 3010",
    "sg:postcode":"01940",
    "sg:province":"MA",
    "sg:tags":[
        "mail",
        "order"
    ],
    "wof:name":"Decadent Details",
    "wof:placetype":"venue"
},
  "geometry": {"coordinates":[-71.035279,42.528428],"type":"Point"}
}