{
  "type": "Feature",
  "properties": {
    "addr:full": "50 Walnut St Lynnfield MA 01940",
    "addr:housenumber": "50",
    "addr:postcode": "01940",
    "addr:street": "Walnut St",
    "iso:country": "US",
    "sg:address": "50 Walnut St",
    "sg:city": "Lynnfield",
    "sg:classifiers": [
      {
        "category": "Shopping",
        "subcategory": "Catalog Store",
        "type": "Retail Goods"
      }
    ],
    "sg:phone": "+1 781 233 3010",
    "sg:postcode": "01940",
    "sg:province": "MA",
    "sg:tags": [
      "mail",
      "order"
    ],
    "wof:name": "Decadent Details",
    "wof:placetype": "venue"
  },
  "geometry": {"coordinates":[-71.035279,42.528428],"type":"Point"}
}
