{
  "type": "Feature",
  "properties": {
    "addr:full": "1098 Massachusetts Ave Arlington MA 02476",
    "addr:housenumber": "1098",
    "addr:postcode": "02476",
    "addr:street": "Massachusetts Ave",
    "iso:country": "US",
    "sg:address": "1098 Massachusetts Ave",
    "sg:city": "Arlington",
    "sg:classifiers": [
      {
        "category": "Retail",
        "subcategory": "Driving School",
        "type": "Services"
      },
      {
        "category": "Autos \u0026 Motor Vehicles",
        "subcategory": "Motorcycle Sales",
        "type": "Retail Goods"
      }
    ],
    "sg:phone": "+1 781 641 3768",
    "sg:postcode": "02476",
    "sg:province": "MA",
    "sg:tags": [
      "instruction"
    ],
    "wof:name": "Cycles Associated Companies",
    "wof:placetype": "venue"
  },
  "geometry": {"coordinates":[-71.172047,42.421607],"type":"Point"}
}
