{
  "type": "Feature",
  "properties": {
    "iso:country":"US",
    "sg:address":"1098 Massachusetts Ave",
    "sg:city":"Arlington",
    "sg:classifiers":[
        {
            "category":"Retail",
            "subcategory":"Driving School",
            "type":"Services"
        },
        {
            "category":"Autos & Motor Vehicles",
            "subcategory":"Motorcycle Sales",
            "type":"Retail Goods"
        }
    ],
    "sg:phone":"+1 781 641 3768",
    "sg:postcode":"02476",
    "sg:province":"MA",
    "sg:tags":[
        "instruction"
    ],
    "wof:name":"Cycles Associated Companies",
    "wof:placetype":"venue"
},
  "geometry": {"coordinates":[-71.17204700000001,42.421607],"type":"Point"}
}