{
  "type": "Feature",
  "properties": {
    "addr:full":"172 Summer St Rehoboth MA 02769",
    "addr:housenumber":"172",
    "addr:postcode":"02769",
    "addr:street":"Summer St",
    "iso:country":"US",
    "sg:address":"172 Summer St",
    "sg:city":"Rehoboth",
    "sg:classifiers":[
        {
            "category":"Home & Garden",
            "subcategory":"Building Materials",
            "type":"Retail Goods"
        }
    ],
    "sg:phone":"+1 508 252 5557",
    "sg:postcode":"02769",
    "sg:province":"MA",
    "sg:tags":[
        "glass",
        "leaded"
    ],
    "wof:name":"Stain Glass Artistry",
    "wof:placetype":"venue"
},
  "geometry": {"coordinates":[-71.27148699999999,41.82922],"type":"Point"}
}