{
  "type": "Feature",
  "properties": {
    "addr:full": "38 Old Tyng Rd Tyngsboro MA 01879",
    "addr:housenumber": "38",
    "addr:postcode": "01879",
    "addr:street": "Old Tyng Rd",
    "iso:country": "US",
    "sg:address": "38 Old Tyng Rd",
    "sg:city": "Tyngsboro",
    "sg:classifiers": [
      {
        "category": "Building \u0026 Trades",
        "subcategory": "Landscaping Services",
        "type": "Services"
      }
    ],
    "sg:phone": "+1 978 649 2669",
    "sg:postcode": "01879",
    "sg:province": "MA",
    "sg:tags": [
      "landscape",
      "contractor"
    ],
    "wof:name": "Environmental Gardens Inc",
    "wof:placetype": "venue"
  },
  "geometry": {"coordinates":[-71.413255,42.665813],"type":"Point"}
}
