{
  "type": "Feature",
  "properties": {
    "iso:country":"US",
    "sg:address":"38 Old Tyng Rd",
    "sg:city":"Tyngsboro",
    "sg:classifiers":[
        {
            "category":"Building & Trades",
            "subcategory":"Landscaping Services",
            "type":"Services"
        }
    ],
    "sg:phone":"+1 978 649 2669",
    "sg:postcode":"01879",
    "sg:province":"MA",
    "sg:tags":[
        "landscape",
        "contractor"
    ],
    "wof:name":"Environmental Gardens Inc",
    "wof:placetype":"venue"
},
  "geometry": {"coordinates":[-71.41325500000001,42.665813],"type":"Point"}
}