{
  "type": "Feature",
  "properties": {
    "addr:full": "338 Main St Wakefield MA 01880",
    "addr:housenumber": "338",
    "addr:postcode": "01880",
    "addr:street": "Main St",
    "iso:country": "US",
    "sg:address": "338 Main St",
    "sg:city": "Wakefield",
    "sg:classifiers": [
      {
        "category": "Professional",
        "subcategory": "Business Services",
        "type": "Services"
      },
      {
        "category": "Building \u0026 Trades",
        "subcategory": "Construction",
        "type": "Services"
      }
    ],
    "sg:phone": "+1 781 245 6550",
    "sg:postcode": "01880",
    "sg:province": "MA",
    "sg:tags": [
      "designer"
    ],
    "wof:name": "Edmund Britt \u0026 Co",
    "wof:placetype": "venue"
  },
  "geometry": {"coordinates":[-71.071546,42.505213],"type":"Point"}
}
