{
  "type": "Feature",
  "properties": {
    "iso:country":"US",
    "sg:address":"8 Vincent St",
    "sg:city":"North Dartmouth",
    "sg:classifiers":[
        {
            "category":"Home & Garden",
            "subcategory":"Furniture",
            "type":"Retail Goods"
        }
    ],
    "sg:phone":"+1 508 646 0557",
    "sg:postcode":"02747",
    "sg:province":"MA",
    "wof:name":"Garden Woodworks",
    "wof:placetype":"venue"
},
  "geometry": {"coordinates":[-71.008573,41.643199],"type":"Point"}
}