{
  "type": "Feature",
  "properties": {
    "addr:full":"21 Custom House St Suite 500 Boston MA 02110",
    "addr:housenumber":"21",
    "addr:postcode":"02110",
    "addr:street":"Custom House St Suite 500",
    "iso:country":"US",
    "sg:address":"21 Custom House St Suite 500",
    "sg:city":"Boston",
    "sg:classifiers":[
        {
            "category":"Professional",
            "subcategory":"Lawyer & Legal Services",
            "type":"Services"
        }
    ],
    "sg:phone":"+1 617 482 8300",
    "sg:postcode":"02110",
    "sg:province":"MA",
    "sg:tags":[
        "litigation",
        "tort",
        "attorney"
    ],
    "wof:name":"Theise, Jay F. - Jay F. Theise & Associates",
    "wof:placetype":"venue"
},
  "geometry": {"coordinates":[-71.053009,42.357971],"type":"Point"}
}