{
  "type": "Feature",
  "properties": {
    "iso:country":"US",
    "sg:address":"1 Central Ave",
    "sg:city":"Wareham",
    "sg:classifiers":[
        {
            "category":"Personal",
            "subcategory":"Nail Salon",
            "type":"Services"
        }
    ],
    "sg:phone":"+1 508 273 2355",
    "sg:postcode":"02571",
    "sg:province":"MA",
    "wof:name":"Onset Finest Nails Beauty Supply",
    "wof:placetype":"venue"
},
  "geometry": {"coordinates":[-70.675157,41.741882],"type":"Point"}
}