{
  "type": "Feature",
  "properties": {
    "addr:full":"38 Narrows Rd Assonet MA 02702",
    "addr:housenumber":"38",
    "addr:postcode":"02702",
    "addr:street":"Narrows Rd",
    "iso:country":"US",
    "sg:address":"38 Narrows Rd",
    "sg:city":"Assonet",
    "sg:classifiers":[
        {
            "category":"Education",
            "subcategory":"School",
            "type":"Public Place"
        }
    ],
    "sg:phone":"+1 508 644 3101",
    "sg:postcode":"02702",
    "sg:province":"MA",
    "wof:name":"Crystal Springs School",
    "wof:placetype":"venue"
},
  "geometry": {"coordinates":[-71.08962099999999,41.785948],"type":"Point"}
}