{
  "type": "Feature",
  "properties": {
    "addr:full":"717 Main St Worcester MA 01610",
    "addr:housenumber":"717",
    "addr:postcode":"01610",
    "addr:street":"Main St",
    "iso:country":"US",
    "sg:address":"717 Main St",
    "sg:city":"Worcester",
    "sg:classifiers":[
        {
            "category":"Organizations",
            "subcategory":"Religious Organization",
            "type":"Services"
        }
    ],
    "sg:phone":"+1 508 756 0009",
    "sg:postcode":"01610",
    "sg:province":"MA",
    "wof:name":"Emmanuel Baptist Church",
    "wof:placetype":"venue"
},
  "geometry": {"coordinates":[-71.80771300000001,42.25798],"type":"Point"}
}