{
  "type": "Feature",
  "properties": {
    "addr:full": "577 Main St Hyannis MA 02601",
    "addr:housenumber": "577",
    "addr:postcode": "02601",
    "addr:street": "Main St",
    "iso:country": "US",
    "sg:address": "577 Main St",
    "sg:city": "Hyannis",
    "sg:classifiers": [
      {
        "category": "Real Estate",
        "subcategory": "Real Estate Services",
        "type": "Services"
      }
    ],
    "sg:phone": "+1 508 775 9119",
    "sg:postcode": "02601",
    "sg:province": "MA",
    "wof:name": "Carey Real Estate - CLOSED",
    "wof:placetype": "venue"
  },
  "geometry": {"coordinates":[-70.2882,41.650501],"type":"Point"}
}
