{
  "type": "Feature",
  "properties": {
    "iso:country":"US",
    "sg:address":"183 State St",
    "sg:city":"Boston",
    "sg:classifiers":[
        {
            "category":"Government",
            "subcategory":"City Hall",
            "type":"Public Place"
        }
    ],
    "sg:postcode":"02109",
    "sg:province":"MA",
    "sg:website":"www.mbta.com/schedules_and_maps/...",
    "wof:name":"Aquarium Station",
    "wof:placetype":"venue"
},
  "geometry": {"coordinates":[-71.05298000000001,42.359412],"type":"Point"}
}