{
  "type": "Feature",
  "properties": {
    "addr:full":"14 Phoenix St Shirley MA 01464",
    "addr:housenumber":"14",
    "addr:postcode":"01464",
    "addr:street":"Phoenix St",
    "iso:country":"US",
    "sg:address":"14 Phoenix St",
    "sg:city":"Shirley",
    "sg:classifiers":[
        {
            "category":"Organizations",
            "subcategory":"Religious Organization",
            "type":"Services"
        }
    ],
    "sg:phone":"+1 978 425 0980",
    "sg:postcode":"01464",
    "sg:province":"MA",
    "sg:tags":[
        "church"
    ],
    "wof:name":"St Anthony Of Padua Church",
    "wof:placetype":"venue"
},
  "geometry": {"coordinates":[-71.648009,42.544047],"type":"Point"}
}