{
  "type": "Feature",
  "properties": {
    "addr:full": "80 Newbury St Boston MA 02116",
    "addr:housenumber": "80",
    "addr:postcode": "02116",
    "addr:street": "Newbury St",
    "iso:country": "US",
    "sg:address": "80 Newbury St",
    "sg:city": "Boston",
    "sg:classifiers": [
      {
        "category": "Shopping",
        "subcategory": "Clothing, Apparel, \u0026 Fashions",
        "type": "Retail Goods"
      }
    ],
    "sg:phone": "+1 617 236 4147",
    "sg:postcode": "02116",
    "sg:province": "MA",
    "sg:tags": [
      "accessory",
      "clothing",
      "women's"
    ],
    "wof:name": "Guess",
    "wof:placetype": "venue"
  },
  "geometry": {"coordinates":[-71.074501,42.351898],"type":"Point"}
}
