{
  "type": "Feature",
  "properties": {
    "addr:full":"55 Union St Methuen MA 01844",
    "addr:housenumber":"55",
    "addr:postcode":"01844",
    "addr:street":"Union St",
    "iso:country":"US",
    "sg:address":"55 Union St",
    "sg:city":"Methuen",
    "sg:classifiers":[
        {
            "category":"Organizations",
            "subcategory":"Labor Organization",
            "type":"Services"
        }
    ],
    "sg:phone":"+1 978 687 7200",
    "sg:postcode":"01844",
    "sg:province":"MA",
    "wof:name":"Laborers International Union",
    "wof:placetype":"venue"
},
  "geometry": {"coordinates":[-71.18651699999999,42.723771],"type":"Point"}
}