{
  "type": "Feature",
  "properties": {
    "iso:country":"US",
    "sg:address":"108 Clematis Ave",
    "sg:city":"Waltham",
    "sg:classifiers":[
        {
            "category":"Wholesale",
            "subcategory":"Groceries",
            "type":"Manufacturing & Wholesale Goods"
        }
    ],
    "sg:phone":"+1 781 642 8999",
    "sg:postcode":"02453",
    "sg:province":"MA",
    "sg:tags":[
        "food",
        "product",
        "health"
    ],
    "wof:name":"Health Soy",
    "wof:placetype":"venue"
},
  "geometry": {"coordinates":[-71.205348,42.382853],"type":"Point"}
}