{
  "type": "Feature",
  "properties": {
    "addr:full":"222 W Squantum St Quincy MA 02171",
    "addr:housenumber":"222",
    "addr:postcode":"02171",
    "addr:street":"W Squantum St",
    "iso:country":"US",
    "sg:address":"222 W Squantum St",
    "sg:city":"Quincy",
    "sg:classifiers":[
        {
            "category":"Personal",
            "subcategory":"Beauty Salon",
            "type":"Services"
        }
    ],
    "sg:phone":"+1 617 769 0044",
    "sg:postcode":"02171",
    "sg:province":"MA",
    "wof:name":"Salon Gabbana",
    "wof:placetype":"venue"
},
  "geometry": {"coordinates":[-71.034187,42.269859],"type":"Point"}
}