{
  "type": "Feature",
  "properties": {
    "addr:full": "95 Beaver St Waltham MA 02453",
    "addr:housenumber": "95",
    "addr:postcode": "02453",
    "addr:street": "Beaver St",
    "iso:country": "US",
    "sg:address": "95 Beaver St",
    "sg:city": "Waltham",
    "sg:classifiers": [
      {
        "category": "Professional",
        "subcategory": "Testing Lab",
        "type": "Services"
      }
    ],
    "sg:phone": "+1 781 891 4750",
    "sg:postcode": "02453",
    "sg:province": "MA",
    "sg:tags": [
      "analytical",
      "laboratory"
    ],
    "wof:name": "Hub Testing Laboratory",
    "wof:placetype": "venue"
  },
  "geometry": {"coordinates":[-71.206959,42.382593],"type":"Point"}
}
