{
  "type": "Feature",
  "properties": {
    "iso:country":"US",
    "sg:address":"95 Beaver St",
    "sg:city":"Waltham",
    "sg:classifiers":[
        {
            "category":"Professional",
            "subcategory":"Testing Lab",
            "type":"Services"
        }
    ],
    "sg:phone":"+1 781 891 4750",
    "sg:postcode":"02453",
    "sg:province":"MA",
    "sg:tags":[
        "analytical",
        "laboratory"
    ],
    "wof:name":"Hub Testing Laboratory",
    "wof:placetype":"venue"
},
  "geometry": {"coordinates":[-71.206959,42.382593],"type":"Point"}
}