{
  "type": "Feature",
  "properties": {
    "iso:country":"US",
    "sg:address":"228 County St",
    "sg:city":"Attleboro",
    "sg:classifiers":[
        {
            "category":"Professional",
            "subcategory":"Lawyer & Legal Services",
            "type":"Services"
        }
    ],
    "sg:phone":"+1 508 226 8300",
    "sg:postcode":"02703",
    "sg:province":"MA",
    "wof:name":"Dalrymple Stephen P Atty",
    "wof:placetype":"venue"
},
  "geometry": {"coordinates":[-71.29630299999999,41.936298],"type":"Point"}
}