{
  "type": "Feature",
  "properties": {
    "addr:full":"60 Orchard St Greenfield MA 01301",
    "addr:housenumber":"60",
    "addr:postcode":"01301",
    "addr:street":"Orchard St",
    "iso:country":"US",
    "sg:address":"60 Orchard St",
    "sg:city":"Greenfield",
    "sg:classifiers":[
        {
            "category":"Health Services",
            "subcategory":"Health Practitioner",
            "type":"Services"
        }
    ],
    "sg:phone":"+1 413 772 0010",
    "sg:postcode":"01301",
    "sg:province":"MA",
    "sg:tags":[
        "psychologist"
    ],
    "wof:name":"Francis D Kelly",
    "wof:placetype":"venue"
},
  "geometry": {"coordinates":[-72.59269399999999,42.589736],"type":"Point"}
}