{
  "type": "Feature",
  "properties": {
    "addr:full":"90 Oak St Newton Upper Fls MA 02464",
    "addr:housenumber":"90",
    "addr:postcode":"02464",
    "addr:street":"Oak St",
    "iso:country":"US",
    "sg:address":"90 Oak St",
    "sg:city":"Newton Upper Fls",
    "sg:classifiers":[
        {
            "category":"Professional",
            "type":"Services"
        }
    ],
    "sg:phone":"+1 617 630 9010",
    "sg:postcode":"02464",
    "sg:province":"MA",
    "sg:tags":[
        "establishment"
    ],
    "wof:name":"Etgar L'Noar",
    "wof:placetype":"venue"
},
  "geometry": {"coordinates":[-71.220597,42.310179],"type":"Point"}
}