{
  "type": "Feature",
  "properties": {
    "iso:country":"US",
    "sg:address":"990 Chandler St",
    "sg:city":"Tewksbury",
    "sg:classifiers":[
        {
            "category":"Health Services",
            "subcategory":"Hospital",
            "type":"Services"
        }
    ],
    "sg:phone":"+1 978 851 7205",
    "sg:postcode":"01876",
    "sg:province":"MA",
    "sg:tags":[
        "mental"
    ],
    "wof:name":"Greater Lynn Mental Health",
    "wof:placetype":"venue"
},
  "geometry": {"coordinates":[-71.239018,42.588341],"type":"Point"}
}