{
  "type": "Feature",
  "properties": {
    "addr:full": "3 Crane St Danvers MA 01923",
    "addr:housenumber": "3",
    "addr:postcode": "01923",
    "addr:street": "Crane St",
    "iso:country": "US",
    "sg:address": "3 Crane St",
    "sg:city": "Danvers",
    "sg:classifiers": [
      {
        "category": "Building \u0026 Trades",
        "subcategory": "Construction",
        "type": "Services"
      }
    ],
    "sg:phone": "+1   ",
    "sg:postcode": "01923",
    "sg:province": "MA",
    "sg:tags": [
      "house"
    ],
    "wof:name": "United Construction Co",
    "wof:placetype": "venue"
  },
  "geometry": {"coordinates":[-70.934115,42.557769],"type":"Point"}
}
