{
  "type": "Feature",
  "properties": {
    "iso:country":"US",
    "sg:address":"3 Crane St",
    "sg:city":"Danvers",
    "sg:classifiers":[
        {
            "category":"Building & Trades",
            "subcategory":"Construction",
            "type":"Services"
        }
    ],
    "sg:phone":"+1   ",
    "sg:postcode":"01923",
    "sg:province":"MA",
    "sg:tags":[
        "house"
    ],
    "wof:name":"United Construction Co",
    "wof:placetype":"venue"
},
  "geometry": {"coordinates":[-70.93411500000001,42.557769],"type":"Point"}
}