{
  "type": "Feature",
  "properties": {
    "iso:country":"US",
    "sg:address":"2875 Cranberry Hwy",
    "sg:city":"East Wareham",
    "sg:classifiers":[
        {
            "category":"Social Services",
            "type":"Services"
        }
    ],
    "sg:phone":"+1 508 291 6244",
    "sg:postcode":"02538",
    "sg:province":"MA",
    "sg:tags":[
        "organization",
        "welfare"
    ],
    "wof:name":"Evergreen House Inc",
    "wof:placetype":"venue"
},
  "geometry": {"coordinates":[-70.672662,41.760042],"type":"Point"}
}