{
  "type": "Feature",
  "properties": {
    "addr:full":"184 Cambridge St Burlington MA 01803",
    "addr:housenumber":"184",
    "addr:postcode":"01803",
    "addr:street":"Cambridge St",
    "iso:country":"US",
    "sg:address":"184 Cambridge St",
    "sg:city":"Burlington",
    "sg:classifiers":[
        {
            "category":"Health Services",
            "subcategory":"Dentist",
            "type":"Services"
        }
    ],
    "sg:phone":"+1 781 221 0072",
    "sg:postcode":"01803",
    "sg:province":"MA",
    "sg:website":"www.gentledental.com",
    "wof:name":"Gentle Dental",
    "wof:placetype":"venue"
},
  "geometry": {"coordinates":[-71.198607,42.509679],"type":"Point"}
}