{
  "type": "Feature",
  "properties": {
    "addr:full": "100 Patterson Rd Worthington MA 01098",
    "addr:housenumber": "100",
    "addr:postcode": "01098",
    "addr:street": "Patterson Rd",
    "iso:country": "US",
    "sg:address": "100 Patterson Rd",
    "sg:city": "Worthington",
    "sg:classifiers": [
      {
        "category": "Professional",
        "subcategory": "Management \u0026 Consulting",
        "type": "Services"
      }
    ],
    "sg:phone": "+1   ",
    "sg:postcode": "01098",
    "sg:province": "MA",
    "wof:name": "Judymoves Dance \u0026 Fitness",
    "wof:placetype": "venue"
  },
  "geometry": {"coordinates":[-72.930923,42.356506],"type":"Point"}
}
