{
  "type": "Feature",
  "properties": {
    "iso:country":"US",
    "sg:address":"100 Patterson Rd",
    "sg:city":"Worthington",
    "sg:classifiers":[
        {
            "category":"Professional",
            "subcategory":"Management & Consulting",
            "type":"Services"
        }
    ],
    "sg:phone":"+1   ",
    "sg:postcode":"01098",
    "sg:province":"MA",
    "wof:name":"Judymoves Dance & Fitness",
    "wof:placetype":"venue"
},
  "geometry": {"coordinates":[-72.93092300000001,42.356506],"type":"Point"}
}