{
  "type": "Feature",
  "properties": {
    "iso:country":"US",
    "sg:address":"3 Ash Ln",
    "sg:city":"Millville",
    "sg:classifiers":[
        {
            "category":"Building & Trades",
            "subcategory":"Cleaning & Sanitation",
            "type":"Services"
        }
    ],
    "sg:phone":"+1 508 473 4063",
    "sg:postcode":"01529",
    "sg:province":"MA",
    "sg:tags":[
        "supply",
        "septic",
        "tanks-treatment"
    ],
    "wof:name":"Gibson Cesspool Services",
    "wof:placetype":"venue"
},
  "geometry": {"coordinates":[-71.569745,42.054292],"type":"Point"}
}