{
  "type": "Feature",
  "properties": {
    "addr:full": "3 Ash Ln Millville MA 01529",
    "addr:housenumber": "3",
    "addr:postcode": "01529",
    "addr:street": "Ash Ln",
    "iso:country": "US",
    "sg:address": "3 Ash Ln",
    "sg:city": "Millville",
    "sg:classifiers": [
      {
        "category": "Building \u0026 Trades",
        "subcategory": "Cleaning \u0026 Sanitation",
        "type": "Services"
      }
    ],
    "sg:phone": "+1 508 473 4063",
    "sg:postcode": "01529",
    "sg:province": "MA",
    "sg:tags": [
      "supply",
      "septic",
      "tanks-treatment"
    ],
    "wof:name": "Gibson Cesspool Services",
    "wof:placetype": "venue"
  },
  "geometry": {"coordinates":[-71.569745,42.054292],"type":"Point"}
}
