{
  "type": "Feature",
  "properties": {
    "iso:country":"US",
    "sg:address":"292 Main St",
    "sg:city":"Northborough",
    "sg:classifiers":[
        {
            "category":"Personal",
            "type":"Services"
        }
    ],
    "sg:phone":"+1 508 393 2131",
    "sg:postcode":"01532",
    "sg:province":"MA",
    "sg:tags":[
        "consultant",
        "planning",
        "wedding"
    ],
    "wof:name":"Alankar Event Planners & Decorators",
    "wof:placetype":"venue"
},
  "geometry": {"coordinates":[-71.619919,42.32803],"type":"Point"}
}