{
  "type": "Feature",
  "properties": {
    "addr:full":"1 Fenway Plz Boston MA 02215",
    "addr:housenumber":"1",
    "addr:postcode":"02215",
    "addr:street":"Fenway Plz",
    "iso:country":"US",
    "sg:address":"1 Fenway Plz",
    "sg:city":"Boston",
    "sg:classifiers":[
        {
            "category":"Health Services",
            "subcategory":"Doctor",
            "type":"Services"
        }
    ],
    "sg:phone":"+1 617 421 1122",
    "sg:postcode":"02215",
    "sg:province":"MA",
    "sg:tags":[
        "dentist"
    ],
    "wof:name":"James Campbell DDS",
    "wof:placetype":"venue"
},
  "geometry": {"coordinates":[-71.100291,42.346979],"type":"Point"}
}