{
  "type": "Feature",
  "properties": {
    "addr:full":"204 Derby St Salem MA 01970",
    "addr:housenumber":"204",
    "addr:postcode":"01970",
    "addr:street":"Derby St",
    "iso:country":"US",
    "sg:address":"204 Derby St",
    "sg:city":"Salem",
    "sg:classifiers":[
        {
            "category":"Food & Beverages",
            "subcategory":"Liquor & Beverages",
            "type":"Retail Goods"
        }
    ],
    "sg:phone":"+1 978 744 2251",
    "sg:postcode":"01970",
    "sg:province":"MA",
    "sg:website":"www.thebunghole.com",
    "wof:name":"Bung Hole Liquor Store",
    "wof:placetype":"venue"
},
  "geometry": {"coordinates":[-70.888668,42.520843],"type":"Point"}
}