{
  "type": "Feature",
  "properties": {
    "addr:full":"400 Centre St Newton MA 02458",
    "addr:housenumber":"400",
    "addr:postcode":"02458",
    "addr:street":"Centre St",
    "iso:country":"US",
    "sg:address":"400 Centre St",
    "sg:city":"Newton",
    "sg:classifiers":[
        {
            "category":"Banks & Credit Unions",
            "subcategory":"Investment Brokerage",
            "type":"Services"
        },
        {
            "category":"Real Estate",
            "subcategory":"Developer",
            "type":"Services"
        }
    ],
    "sg:phone":"+1 617 928 1300",
    "sg:postcode":"02458",
    "sg:province":"MA",
    "sg:tags":[
        "investing"
    ],
    "wof:name":"Gov Grand Oak Properties Trust",
    "wof:placetype":"venue"
},
  "geometry": {"coordinates":[-71.18619,42.355489],"type":"Point"}
}