{
  "type": "Feature",
  "properties": {
    "addr:full": "1100 Riverside Ave Somerset MA 02726",
    "addr:housenumber": "1100",
    "addr:postcode": "02726",
    "addr:street": "Riverside Ave",
    "iso:country": "US",
    "sg:address": "1100 Riverside Ave",
    "sg:city": "Somerset",
    "sg:classifiers": [
      {
        "category": "Professional",
        "subcategory": "Management \u0026 Consulting",
        "type": "Services"
      }
    ],
    "sg:phone": "+1 508 646 9399",
    "sg:postcode": "02726",
    "sg:province": "MA",
    "sg:tags": [
      "consultant",
      "safety"
    ],
    "wof:name": "Safety Concepts Inc",
    "wof:placetype": "venue"
  },
  "geometry": {"coordinates":[-71.154342,41.730728],"type":"Point"}
}
