{
  "type": "Feature",
  "properties": {
    "iso:country":"US",
    "sg:address":"40 Arborough Rd",
    "sg:city":"Roslindale",
    "sg:classifiers":[
        {
            "category":"Manufacturing",
            "subcategory":"Tools & Machinery",
            "type":"Manufacturing & Wholesale Goods"
        }
    ],
    "sg:phone":"+1   ",
    "sg:postcode":"02131",
    "sg:province":"MA",
    "sg:tags":[
        "equipment",
        "lighting",
        "mfg"
    ],
    "wof:name":"Speed of Earth Inc",
    "wof:placetype":"venue"
},
  "geometry": {"coordinates":[-71.12782199999999,42.290068],"type":"Point"}
}