{
  "type": "Feature",
  "properties": {
    "iso:country":"US",
    "sg:address":"110 Commonwealth Ave",
    "sg:city":"Boston",
    "sg:classifiers":[
        {
            "category":"Place Of Worship",
            "subcategory":"Church",
            "type":"Public Place"
        }
    ],
    "sg:phone":"+1 617 267 3148",
    "sg:postcode":"02116",
    "sg:province":"MA",
    "sg:website":"firstbaptistchurchofboston.org/",
    "wof:name":"First Baptist Church of Boston",
    "wof:placetype":"venue"
},
  "geometry": {"coordinates":[-71.07620199999999,42.352299],"type":"Point"}
}