{
  "type": "Feature",
  "properties": {
    "iso:country":"US",
    "sg:address":"150 Presidential Way",
    "sg:city":"Woburn",
    "sg:classifiers":[
        {
            "category":"Health Services",
            "subcategory":"Doctor",
            "type":"Services"
        }
    ],
    "sg:phone":"+1 781 782 1300",
    "sg:postcode":"01801",
    "sg:province":"MA",
    "sg:tags":[
        "orthopedist"
    ],
    "wof:name":"Excel Orthopedics",
    "wof:placetype":"venue"
},
  "geometry": {"coordinates":[-71.1437,42.525299],"type":"Point"}
}