{
  "type": "Feature",
  "properties": {
    "iso:country":"US",
    "sg:address":"77 Alexander Rd",
    "sg:city":"Billerica",
    "sg:classifiers":[
        {
            "category":"Manufacturing",
            "subcategory":"Metals",
            "type":"Manufacturing & Wholesale Goods"
        }
    ],
    "sg:phone":"+1 978 663 7781",
    "sg:postcode":"01821",
    "sg:province":"MA",
    "sg:tags":[
        "fabricator",
        "sheet"
    ],
    "wof:name":"Sheetmetal Systems & Design",
    "wof:placetype":"venue"
},
  "geometry": {"coordinates":[-71.21243699999999,42.555931],"type":"Point"}
}