{
  "type": "Feature",
  "properties": {
    "addr:full":"29 Market St Swansea MA 02777",
    "addr:housenumber":"29",
    "addr:postcode":"02777",
    "addr:street":"Market St",
    "iso:country":"US",
    "sg:address":"29 Market St",
    "sg:city":"Swansea",
    "sg:classifiers":[
        {
            "category":"Food & Beverages",
            "subcategory":"Candy",
            "type":"Retail Goods"
        }
    ],
    "sg:phone":"+1   ",
    "sg:postcode":"02777",
    "sg:province":"MA",
    "wof:name":"Nut House",
    "wof:placetype":"venue"
},
  "geometry": {"coordinates":[-71.265066,41.769347],"type":"Point"}
}