{
  "type": "Feature",
  "properties": {
    "addr:full": "145 Powder Mill Rd Acton MA 01720",
    "addr:housenumber": "145",
    "addr:postcode": "01720",
    "addr:street": "Powder Mill Rd",
    "iso:country": "US",
    "sg:address": "145 Powder Mill Rd",
    "sg:city": "Acton",
    "sg:classifiers": [
      {
        "category": "Home \u0026 Garden",
        "subcategory": "Home Furnishings",
        "type": "Retail Goods"
      }
    ],
    "sg:phone": "+1 978 897 9901",
    "sg:postcode": "01720",
    "sg:province": "MA",
    "sg:tags": [
      "lighting",
      "fixture"
    ],
    "wof:name": "Lighting Center",
    "wof:placetype": "venue"
  },
  "geometry": {"coordinates":[-71.435345,42.43873],"type":"Point"}
}
