{
  "type": "Feature",
  "properties": {
    "iso:country":"US",
    "sg:address":"357 Cottage St",
    "sg:city":"Springfield",
    "sg:classifiers":[
        {
            "category":"Shopping",
            "subcategory":"Computers & Home Electronics",
            "type":"Retail Goods"
        }
    ],
    "sg:phone":"+1 781 871 4757",
    "sg:postcode":"01104",
    "sg:province":"MA",
    "sg:tags":[
        "equipment",
        "electronic",
        "supply"
    ],
    "wof:name":"Electronics Systems Inc",
    "wof:placetype":"venue"
},
  "geometry": {"coordinates":[-72.542922,42.144108],"type":"Point"}
}