{
  "type": "Feature",
  "properties": {
    "iso:country":"US",
    "sg:address":"58 Dunham Rd",
    "sg:city":"Beverly",
    "sg:classifiers":[
        {
            "category":"Building & Trades",
            "subcategory":"Landscaping Services",
            "type":"Services"
        },
        {
            "category":"Home & Garden",
            "subcategory":"Garden Supply",
            "type":"Retail Goods"
        },
        {
            "category":"Retail",
            "subcategory":"Repair Shop",
            "type":"Services"
        }
    ],
    "sg:phone":"+1 978 338 4530",
    "sg:postcode":"01915",
    "sg:province":"MA",
    "sg:tags":[
        "lawn",
        "outdoor",
        "power",
        "equipment-sales",
        "snow",
        "removal",
        "mower"
    ],
    "sg:website":"http://www.maestranzi.com",
    "wof:name":"Maestranzi Bros Inc",
    "wof:placetype":"venue"
},
  "geometry": {"coordinates":[-70.872255,42.575377],"type":"Point"}
}