{
  "type": "Feature",
  "properties": {
    "iso:country":"US",
    "sg:address":"962 Washington St",
    "sg:city":"Hanover",
    "sg:classifiers":[
        {
            "category":"Manufacturing",
            "subcategory":"Buildings",
            "type":"Manufacturing & Wholesale Goods"
        }
    ],
    "sg:phone":"+1 781 826 4132",
    "sg:postcode":"02339",
    "sg:province":"MA",
    "sg:tags":[
        "prefab"
    ],
    "wof:name":"Sustainable Design",
    "wof:placetype":"venue"
},
  "geometry": {"coordinates":[-70.835148,42.130375],"type":"Point"}
}