{
  "type": "Feature",
  "properties": {
    "iso:country":"US",
    "sg:address":"179 Summer St",
    "sg:city":"Kingston",
    "sg:classifiers":[
        {
            "category":"Shopping",
            "type":"Retail Goods"
        }
    ],
    "sg:phone":"+1 781 582 8004",
    "sg:postcode":"02364",
    "sg:province":"MA",
    "sg:tags":[
        "candle"
    ],
    "wof:name":"Country Scents Candles",
    "wof:placetype":"venue"
},
  "geometry": {"coordinates":[-70.731004,42.008522],"type":"Point"}
}