{
  "type": "Feature",
  "properties": {
    "addr:full": "289 Court St Plymouth MA 02360",
    "addr:housenumber": "289",
    "addr:postcode": "02360",
    "addr:street": "Court St",
    "iso:country": "US",
    "sg:address": "289 Court St",
    "sg:city": "Plymouth",
    "sg:classifiers": [
      {
        "category": "Shopping",
        "subcategory": "Pharmacy",
        "type": "Retail Goods"
      }
    ],
    "sg:phone": "+1 508 746 1251",
    "sg:postcode": "02360",
    "sg:province": "MA",
    "wof:name": "Balboni's Drug Store Inc",
    "wof:placetype": "venue"
  },
  "geometry": {"coordinates":[-70.682771,41.972204],"type":"Point"}
}
