{
  "type": "Feature",
  "properties": {
    "addr:full": "50 Maple St Mansfield MA 02048",
    "addr:housenumber": "50",
    "addr:postcode": "02048",
    "addr:street": "Maple St",
    "iso:country": "US",
    "sg:address": "50 Maple St",
    "sg:city": "Mansfield",
    "sg:classifiers": [
      {
        "category": "Wholesale",
        "subcategory": "Machinery \u0026 Supplies",
        "type": "Manufacturing \u0026 Wholesale Goods"
      }
    ],
    "sg:phone": "+1 508 285 9559",
    "sg:postcode": "02048",
    "sg:province": "MA",
    "sg:tags": [
      "glass",
      "beads"
    ],
    "wof:name": "Mansfield Glass",
    "wof:placetype": "venue"
  },
  "geometry": {"coordinates":[-71.210736,42.042287],"type":"Point"}
}
