{
  "type": "Feature",
  "properties": {
    "iso:country":"US",
    "sg:address":"50 Maple St",
    "sg:city":"Mansfield",
    "sg:classifiers":[
        {
            "category":"Wholesale",
            "subcategory":"Machinery & Supplies",
            "type":"Manufacturing & Wholesale Goods"
        }
    ],
    "sg:phone":"+1 508 285 9559",
    "sg:postcode":"02048",
    "sg:province":"MA",
    "sg:tags":[
        "glass",
        "beads"
    ],
    "wof:name":"Mansfield Glass",
    "wof:placetype":"venue"
},
  "geometry": {"coordinates":[-71.210736,42.042287],"type":"Point"}
}