{
  "type": "Feature",
  "properties": {
    "addr:full": "60 Lewis St Lynn MA 01902",
    "addr:housenumber": "60",
    "addr:postcode": "01902",
    "addr:street": "Lewis St",
    "iso:country": "US",
    "sg:address": "60 Lewis St",
    "sg:city": "Lynn",
    "sg:classifiers": [
      {
        "category": "Professional",
        "subcategory": "Lawyer \u0026 Legal Services",
        "type": "Services"
      }
    ],
    "sg:phone": "+1 781 593 6800",
    "sg:postcode": "01902",
    "sg:province": "MA",
    "sg:tags": [
      "attorney"
    ],
    "wof:name": "Loring P Fluke",
    "wof:placetype": "venue"
  },
  "geometry": {"coordinates":[-70.927557,42.466514],"type":"Point"}
}
