{
  "type": "Feature",
  "properties": {
    "addr:full": "100 Sturbridge Rd Charlton MA 01507",
    "addr:housenumber": "100",
    "addr:postcode": "01507",
    "addr:street": "Sturbridge Rd",
    "iso:country": "US",
    "sg:address": "100 Sturbridge Rd",
    "sg:city": "Charlton",
    "sg:classifiers": [
      {
        "category": "Utilities",
        "subcategory": "Fuel Oil \u0026 Lpg",
        "type": "Services"
      }
    ],
    "sg:phone": "+1 508 248 9797",
    "sg:postcode": "01507",
    "sg:province": "MA",
    "sg:tags": [
      "oils-fuel"
    ],
    "wof:name": "Charlton Oil",
    "wof:placetype": "venue"
  },
  "geometry": {"coordinates":[-72.012677,42.141241],"type":"Point"}
}
