{
  "type": "Feature",
  "properties": {
    "iso:country":"US",
    "sg:address":"1 Beacon St",
    "sg:city":"Boston",
    "sg:classifiers":[
        {
            "category":"Health Services",
            "subcategory":"Doctor",
            "type":"Services"
        },
        {
            "category":"Insurance",
            "subcategory":"Hazard Insurance",
            "type":"Services"
        }
    ],
    "sg:phone":"+1 617 742 6200",
    "sg:postcode":"02108",
    "sg:province":"MA",
    "sg:tags":[
        "physician",
        "surgeon"
    ],
    "wof:name":"Mara John",
    "wof:placetype":"venue"
},
  "geometry": {"coordinates":[-71.061029,42.358195],"type":"Point"}
}