{
  "type": "Feature",
  "properties": {
    "iso:country":"US",
    "sg:address":"165 Tor Ct",
    "sg:city":"Pittsfield",
    "sg:classifiers":[
        {
            "category":"Health Services",
            "subcategory":"Nursing And Care Facility",
            "type":"Services"
        }
    ],
    "sg:phone":"+1 413 447 9047",
    "sg:postcode":"01201",
    "sg:province":"MA",
    "sg:tags":[
        "home",
        "retirement",
        "community"
    ],
    "wof:name":"Salisbury Estates Inc",
    "wof:placetype":"venue"
},
  "geometry": {"coordinates":[-73.284159,42.453159],"type":"Point"}
}