{
  "type": "Feature",
  "properties": {
    "addr:full": "51 Middlesex Tpke Burlington MA 01803",
    "addr:housenumber": "51",
    "addr:postcode": "01803",
    "addr:street": "Middlesex Tpke",
    "iso:country": "US",
    "sg:address": "51 Middlesex Tpke",
    "sg:city": "Burlington",
    "sg:classifiers": [
      {
        "category": "Food \u0026 Beverages",
        "subcategory": "Groceries \u0026 Convenience Stores",
        "type": "Retail Goods"
      }
    ],
    "sg:phone": "+1 781 273 2310",
    "sg:postcode": "01803",
    "sg:province": "MA",
    "sg:website": "www.traderjoes.com",
    "wof:name": "Trader Joe's",
    "wof:placetype": "venue"
  },
  "geometry": {"coordinates":[-71.211233,42.473236],"type":"Point"}
}
