{
  "type": "Feature",
  "properties": {
    "iso:country":"US",
    "sg:address":"51 Middlesex Tpke",
    "sg:city":"Burlington",
    "sg:classifiers":[
        {
            "category":"Food & Beverages",
            "subcategory":"Groceries & Convenience Stores",
            "type":"Retail Goods"
        }
    ],
    "sg:phone":"+1 781 273 2310",
    "sg:postcode":"01803",
    "sg:province":"MA",
    "sg:website":"www.traderjoes.com",
    "wof:name":"Trader Joe's",
    "wof:placetype":"venue"
},
  "geometry": {"coordinates":[-71.21123299999999,42.473236],"type":"Point"}
}