{
  "type": "Feature",
  "properties": {
    "addr:full":"50 Congress Street Boston MA 02109",
    "addr:housenumber":"50",
    "addr:postcode":"02109",
    "addr:street":"Congress Street",
    "iso:country":"US",
    "sg:address":"50 Congress Street",
    "sg:city":"Boston",
    "sg:classifiers":[
        {
            "category":"Professional",
            "subcategory":"Employment Agencies",
            "type":"Services"
        }
    ],
    "sg:phone":"+1 617 523 7779",
    "sg:postcode":"02109",
    "sg:province":"MA",
    "sg:website":"www.aceboston.net",
    "wof:name":"Ace Employment Agency",
    "wof:placetype":"venue"
},
  "geometry": {"coordinates":[-71.05669899999999,42.358144],"type":"Point"}
}