{
  "type": "Feature",
  "properties": {
    "addr:full": "2 Surrey Dr Lakeville MA 02347",
    "addr:housenumber": "2",
    "addr:postcode": "02347",
    "addr:street": "Surrey Dr",
    "iso:country": "US",
    "sg:address": "2 Surrey Dr",
    "sg:city": "Lakeville",
    "sg:classifiers": [
      {
        "category": "Restaurant",
        "type": "Food \u0026 Drink"
      }
    ],
    "sg:phone": "+1   ",
    "sg:postcode": "02347",
    "sg:province": "MA",
    "sg:tags": [
      "eating"
    ],
    "wof:name": "Surrey Drive Corp",
    "wof:placetype": "venue"
  },
  "geometry": {"coordinates":[-70.949001,41.881931],"type":"Point"}
}
