{
  "type": "Feature",
  "properties": {
    "addr:full":"235 Sawmill Dr Dracut MA 01826",
    "addr:housenumber":"235",
    "addr:postcode":"01826",
    "addr:street":"Sawmill Dr",
    "iso:country":"US",
    "sg:address":"235 Sawmill Dr",
    "sg:city":"Dracut",
    "sg:classifiers":[
        {
            "category":"Building & Trades",
            "subcategory":"Electrical",
            "type":"Services"
        }
    ],
    "sg:phone":"+1   ",
    "sg:postcode":"01826",
    "sg:province":"MA",
    "sg:tags":[
        "electrical",
        "contractor"
    ],
    "wof:name":"A&S Electric",
    "wof:placetype":"venue"
},
  "geometry": {"coordinates":[-71.267123,42.712408],"type":"Point"}
}