{
  "type": "Feature",
  "properties": {
    "addr:full":"337 Hanover St Fall River MA 02720",
    "addr:housenumber":"337",
    "addr:postcode":"02720",
    "addr:street":"Hanover St",
    "iso:country":"US",
    "sg:address":"337 Hanover St",
    "sg:city":"Fall River",
    "sg:classifiers":[
        {
            "category":"Social Services",
            "type":"Services"
        }
    ],
    "sg:phone":"+1 508 679 0198",
    "sg:postcode":"02720",
    "sg:province":"MA",
    "sg:tags":[
        "information",
        "planning",
        "center",
        "family"
    ],
    "wof:name":"Family Planning",
    "wof:placetype":"venue"
},
  "geometry": {"coordinates":[-71.144041,41.710066],"type":"Point"}
}