{
  "type": "Feature",
  "properties": {
    "addr:full": "325 Worcester Rd Charlton MA 01507",
    "addr:housenumber": "325",
    "addr:postcode": "01507",
    "addr:street": "Worcester Rd",
    "iso:country": "US",
    "sg:address": "325 Worcester Rd",
    "sg:city": "Charlton",
    "sg:classifiers": [
      {
        "category": "Manufacturing",
        "subcategory": "Lumber",
        "type": "Manufacturing \u0026 Wholesale Goods"
      }
    ],
    "sg:phone": "+1 508 248 6384",
    "sg:postcode": "01507",
    "sg:province": "MA",
    "wof:name": "Native American Hardwood Corp",
    "wof:placetype": "venue"
  },
  "geometry": {"coordinates":[-71.935527,42.147051],"type":"Point"}
}
