{
  "type": "Feature",
  "properties": {
    "iso:country":"US",
    "sg:address":"325 Worcester Rd",
    "sg:city":"Charlton",
    "sg:classifiers":[
        {
            "category":"Manufacturing",
            "subcategory":"Lumber",
            "type":"Manufacturing & Wholesale Goods"
        }
    ],
    "sg:phone":"+1 508 248 6384",
    "sg:postcode":"01507",
    "sg:province":"MA",
    "wof:name":"Native American Hardwood Corp",
    "wof:placetype":"venue"
},
  "geometry": {"coordinates":[-71.93552699999999,42.147051],"type":"Point"}
}