{
  "type": "Feature",
  "properties": {
    "addr:full": "8 Carriage Ln Maynard MA 01754",
    "addr:housenumber": "8",
    "addr:postcode": "01754",
    "addr:street": "Carriage Ln",
    "iso:country": "US",
    "sg:address": "8 Carriage Ln",
    "sg:city": "Maynard",
    "sg:classifiers": [
      {
        "category": "Professional",
        "subcategory": "Management \u0026 Consulting",
        "type": "Services"
      }
    ],
    "sg:phone": "+1 978 897 9221",
    "sg:postcode": "01754",
    "sg:province": "MA",
    "sg:tags": [
      "consultant",
      "business"
    ],
    "wof:name": "Pilgrim Landing LLC",
    "wof:placetype": "venue"
  },
  "geometry": {"coordinates":[-71.444885,42.408702],"type":"Point"}
}
