{
  "type": "Feature",
  "properties": {
    "iso:country":"US",
    "sg:address":"4437 Washington St",
    "sg:city":"Roslindale",
    "sg:classifiers":[
        {
            "category":"Manufacturing",
            "subcategory":"Chemicals & Compounds",
            "type":"Manufacturing & Wholesale Goods"
        },
        {
            "category":"Shopping",
            "subcategory":"Gifts & Souvenirs",
            "type":"Retail Goods"
        }
    ],
    "sg:phone":"+1 617 323 2599",
    "sg:postcode":"02131",
    "sg:province":"MA",
    "sg:tags":[
        "shop",
        "toilet",
        "cosmetics-wholesale",
        "mfg",
        "preparation",
        "manufacturer"
    ],
    "wof:name":"Botanica Parton Santiago",
    "wof:placetype":"venue"
},
  "geometry": {"coordinates":[-71.134247,42.28074],"type":"Point"}
}