{
  "type": "Feature",
  "properties": {
    "addr:full":"23 Central Ave Lynn MA 01901",
    "addr:housenumber":"23",
    "addr:postcode":"01901",
    "addr:street":"Central Ave",
    "iso:country":"US",
    "sg:address":"23 Central Ave",
    "sg:city":"Lynn",
    "sg:classifiers":[
        {
            "category":"Health Services",
            "subcategory":"Clinic",
            "type":"Services"
        }
    ],
    "sg:phone":"+1 781 592 3822",
    "sg:postcode":"01901",
    "sg:province":"MA",
    "sg:tags":[
        "medical",
        "examiner"
    ],
    "wof:name":"Quality Medical Evalutations",
    "wof:placetype":"venue"
},
  "geometry": {"coordinates":[-70.945708,42.464144],"type":"Point"}
}