{
  "type": "Feature",
  "properties": {
    "iso:country":"US",
    "sg:address":"238 Hancock St",
    "sg:city":"Quincy",
    "sg:classifiers":[
        {
            "category":"Autos & Motor Vehicles",
            "subcategory":"Fuel & Gas Station",
            "type":"Retail Goods"
        }
    ],
    "sg:phone":"+1 617 328 5742",
    "sg:postcode":"02171",
    "sg:province":"MA",
    "sg:tags":[
        "oil"
    ],
    "wof:name":"Hess",
    "wof:placetype":"venue"
},
  "geometry": {"coordinates":[-71.03089199999999,42.277947],"type":"Point"}
}