{
  "type": "Feature",
  "properties": {
    "addr:full":"7 Wedge St Lowell MA 01851",
    "addr:housenumber":"7",
    "addr:postcode":"01851",
    "addr:street":"Wedge St",
    "iso:country":"US",
    "sg:address":"7 Wedge St",
    "sg:city":"Lowell",
    "sg:classifiers":[
        {
            "category":"Retail",
            "subcategory":"Repair Shop",
            "type":"Services"
        }
    ],
    "sg:phone":"+1 978 458 7862",
    "sg:postcode":"01851",
    "sg:province":"MA",
    "sg:tags":[
        "upholsterer"
    ],
    "wof:name":"Garcia Upholstery",
    "wof:placetype":"venue"
},
  "geometry": {"coordinates":[-71.33220300000001,42.627342],"type":"Point"}
}