{
  "type": "Feature",
  "properties": {
    "addr:full": "234 Farmers Row Groton MA 01450",
    "addr:housenumber": "234",
    "addr:postcode": "01450",
    "addr:street": "Farmers Row",
    "iso:country": "US",
    "sg:address": "234 Farmers Row",
    "sg:city": "Groton",
    "sg:classifiers": [
      {
        "category": "Shopping",
        "subcategory": "Crafts \u0026 Fabrics",
        "type": "Retail Goods"
      }
    ],
    "sg:phone": "+1 978 448 9279",
    "sg:postcode": "01450",
    "sg:province": "MA",
    "sg:tags": [
      "embroidery"
    ],
    "wof:name": "Kim Niles Originals",
    "wof:placetype": "venue"
  },
  "geometry": {"coordinates":[-71.581711,42.597133],"type":"Point"}
}
