{
  "type": "Feature",
  "properties": {
    "addr:full": "882 Massachusetts Avenue Arlington MA 02476",
    "addr:housenumber": "882",
    "addr:postcode": "02476",
    "addr:street": "Massachusetts Avenue",
    "iso:country": "US",
    "sg:address": "882 Massachusetts Avenue",
    "sg:city": "Arlington",
    "sg:classifiers": [
      {
        "category": "Restaurant",
        "type": "Food \u0026 Drink"
      }
    ],
    "sg:phone": "+1 781 316 1662",
    "sg:postcode": "02476",
    "sg:province": "MA",
    "wof:name": "Buddy's Ice Cream",
    "wof:placetype": "venue"
  },
  "geometry": {"coordinates":[-71.164788,42.417942],"type":"Point"}
}
