{
  "type": "Feature",
  "properties": {
    "addr:full": "66 Main St Carver MA 02330",
    "addr:housenumber": "66",
    "addr:postcode": "02330",
    "addr:street": "Main St",
    "iso:country": "US",
    "sg:address": "66 Main St",
    "sg:city": "Carver",
    "sg:classifiers": [
      {
        "category": "Arts \u0026 Performance",
        "subcategory": "Arts Center",
        "type": "Entertainment"
      }
    ],
    "sg:phone": "+1 508 746 7377",
    "sg:postcode": "02330",
    "sg:province": "MA",
    "sg:tags": [
      "performing"
    ],
    "wof:name": "Carver Dance Center Inc",
    "wof:placetype": "venue"
  },
  "geometry": {"coordinates":[-70.761002,41.874001],"type":"Point"}
}
