{
  "type": "Feature",
  "properties": {
    "iso:country":"US",
    "sg:address":"254 Locust St",
    "sg:city":"Danvers",
    "sg:classifiers":[
        {
            "category":"Home & Garden",
            "subcategory":"Household Appliances",
            "type":"Retail Goods"
        },
        {
            "category":"Retail",
            "subcategory":"Laundry & Dry Cleaning",
            "type":"Services"
        },
        {
            "category":"Building & Trades",
            "subcategory":"Cleaning & Sanitation",
            "type":"Services"
        }
    ],
    "sg:phone":"+1 978 777 2669",
    "sg:postcode":"01923",
    "sg:province":"MA",
    "sg:tags":[
        "cleaner",
        "upholstery",
        "duct",
        "house",
        "rug",
        "air",
        "ventilation",
        "cleaning-industrial",
        "vacuum",
        "curtain",
        "drapery",
        "carpet"
    ],
    "sg:website":"http://www.servicemasterclean.com/reslf/smclean_leadform.asp?url=http://www.servicemasterclean.com/reslf/smclean_leadform.asp&partnerName=YellowPages.com&adName=yptl&HGProp=SMClean",
    "wof:name":"ServiceMaster Clean",
    "wof:placetype":"venue"
},
  "geometry": {"coordinates":[-70.93910200000001,42.58979],"type":"Point"}
}