{
  "type": "Feature",
  "properties": {
    "addr:full":"115 Brewster Ave Braintree MA 02184",
    "addr:housenumber":"115",
    "addr:postcode":"02184",
    "addr:street":"Brewster Ave",
    "iso:country":"US",
    "sg:address":"115 Brewster Ave",
    "sg:city":"Braintree",
    "sg:classifiers":[
        {
            "category":"Professional",
            "subcategory":"Detective & Security Services",
            "type":"Services"
        }
    ],
    "sg:phone":"+1 781 356 5384",
    "sg:postcode":"02184",
    "sg:province":"MA",
    "sg:tags":[
        "private",
        "investigator"
    ],
    "wof:name":"Bbd Investigative Services",
    "wof:placetype":"venue"
},
  "geometry": {"coordinates":[-71.009438,42.178714],"type":"Point"}
}