{
  "type": "Feature",
  "properties": {
    "iso:country":"US",
    "sg:address":"810 Main St.",
    "sg:city":"Winchester",
    "sg:classifiers":[
        {
            "category":"Education",
            "subcategory":"Music School",
            "type":"Public Place"
        },
        {
            "category":"Personal",
            "type":"Services"
        }
    ],
    "sg:phone":"+1 781 756 4877",
    "sg:postcode":"01890",
    "sg:province":"MA",
    "sg:tags":[
        "instrument",
        "local",
        "musical",
        "teacher"
    ],
    "sg:website":"mouradianguitar.com",
    "wof:name":"Mouradian Guitar Co.",
    "wof:placetype":"venue"
},
  "geometry": {"coordinates":[-71.140269,42.459642],"type":"Point"}
}