{
  "type": "Feature",
  "properties": {
    "iso:country":"US",
    "sg:address":"32 Fairgrounds Rd",
    "sg:city":"Nantucket",
    "sg:classifiers":[
        {
            "category":"Building & Trades",
            "subcategory":"Landscaping Services",
            "type":"Services"
        }
    ],
    "sg:phone":"+1 508 228 5217",
    "sg:postcode":"02554",
    "sg:province":"MA",
    "sg:tags":[
        "landscape",
        "contractor"
    ],
    "wof:name":"Michael Flanagan Landscaping",
    "wof:placetype":"venue"
},
  "geometry": {"coordinates":[-70.091218,41.265063],"type":"Point"}
}