{
  "type": "Feature",
  "properties": {
    "iso:country":"US",
    "sg:address":"164 Old Bay Rd",
    "sg:city":"Belchertown",
    "sg:classifiers":[
        {
            "category":"Manufacturing",
            "subcategory":"Glass & Minerals",
            "type":"Manufacturing & Wholesale Goods"
        }
    ],
    "sg:phone":"+1   ",
    "sg:postcode":"01007",
    "sg:province":"MA",
    "sg:tags":[
        "product",
        "nonmetallic",
        "mfg"
    ],
    "wof:name":"Black Bird Studios",
    "wof:placetype":"venue"
},
  "geometry": {"coordinates":[-72.453074,42.308525],"type":"Point"}
}