{
  "type": "Feature",
  "properties": {
    "addr:full":"11 Piccadilly Way Westborough MA 01581",
    "addr:housenumber":"11",
    "addr:postcode":"01581",
    "addr:street":"Piccadilly Way",
    "iso:country":"US",
    "sg:address":"11 Piccadilly Way",
    "sg:city":"Westborough",
    "sg:classifiers":[
        {
            "category":"Professional",
            "subcategory":"Computer Services",
            "type":"Services"
        }
    ],
    "sg:phone":"+1 508 870 0240",
    "sg:postcode":"01581",
    "sg:province":"MA",
    "sg:tags":[
        "internet"
    ],
    "sg:website":"www.coolingzone.com",
    "wof:name":"Coolingzone",
    "wof:placetype":"venue"
},
  "geometry": {"coordinates":[-71.60158699999999,42.254594],"type":"Point"}
}