{
  "type": "Feature",
  "properties": {
    "iso:country":"US",
    "sg:address":"1128 Main St",
    "sg:city":"Holden",
    "sg:classifiers":[
        {
            "category":"Organizations",
            "subcategory":"Membership Organization",
            "type":"Services"
        }
    ],
    "sg:phone":"+1 508 829 7768",
    "sg:postcode":"01520",
    "sg:province":"MA",
    "wof:name":"Friends Of Holden Council",
    "wof:placetype":"venue"
},
  "geometry": {"coordinates":[-71.86009199999999,42.349935],"type":"Point"}
}