{
  "type": "Feature",
  "properties": {
    "addr:full": "6 Main St Lakeville MA 02347",
    "addr:housenumber": "6",
    "addr:postcode": "02347",
    "addr:street": "Main St",
    "iso:country": "US",
    "sg:address": "6 Main St",
    "sg:city": "Lakeville",
    "sg:classifiers": [
      {
        "category": "Banks \u0026 Credit Unions",
        "subcategory": "Bank",
        "type": "Services"
      }
    ],
    "sg:phone": "+1 508 946 5050",
    "sg:postcode": "02347",
    "sg:province": "MA",
    "wof:name": "Bridgewater Savings Bank",
    "wof:placetype": "venue"
  },
  "geometry": {"coordinates":[-70.923531,41.879104],"type":"Point"}
}
