{
  "type": "Feature",
  "properties": {
    "addr:full":"18 Old Farm Way Newbury MA 01951",
    "addr:housenumber":"18",
    "addr:postcode":"01951",
    "addr:street":"Old Farm Way",
    "iso:country":"US",
    "sg:address":"18 Old Farm Way",
    "sg:city":"Newbury",
    "sg:classifiers":[
        {
            "category":"Professional",
            "subcategory":"Research",
            "type":"Services"
        }
    ],
    "sg:phone":"+1 978 465 1100",
    "sg:postcode":"01951",
    "sg:province":"MA",
    "sg:tags":[
        "market",
        "analysis"
    ],
    "sg:website":"www.marketaccess-intl.com",
    "wof:name":"Market Access Intl",
    "wof:placetype":"venue"
},
  "geometry": {"coordinates":[-70.857485,42.786297],"type":"Point"}
}