{
  "type": "Feature",
  "properties": {
    "addr:full": "230 Bridge St Weymouth MA 02191",
    "addr:housenumber": "230",
    "addr:postcode": "02191",
    "addr:street": "Bridge St",
    "iso:country": "US",
    "sg:address": "230 Bridge St",
    "sg:city": "Weymouth",
    "sg:classifiers": [
      {
        "category": "Home \u0026 Garden",
        "subcategory": "Building Materials",
        "type": "Retail Goods"
      }
    ],
    "sg:phone": "+1 781 331 4811",
    "sg:postcode": "02191",
    "sg:province": "MA",
    "sg:tags": [
      "plumbing",
      "fixture",
      "supply"
    ],
    "sg:website": "www.republicsupplyco.com",
    "wof:name": "Republic Bath Showplace",
    "wof:placetype": "venue"
  },
  "geometry": {"coordinates":[-70.955958,42.242733],"type":"Point"}
}
