{
  "type": "Feature",
  "properties": {
    "addr:full":"9 Main St Watertown MA 02472",
    "addr:housenumber":"9",
    "addr:postcode":"02472",
    "addr:street":"Main St",
    "iso:country":"US",
    "sg:address":"9 Main St",
    "sg:city":"Watertown",
    "sg:classifiers":[
        {
            "category":"Retail",
            "subcategory":"Repair Shop",
            "type":"Services"
        }
    ],
    "sg:phone":"+1 617 477 0304",
    "sg:postcode":"02472",
    "sg:province":"MA",
    "sg:tags":[
        "lock",
        "locksmith"
    ],
    "wof:name":"24 Hour A Day Locksmith",
    "wof:placetype":"venue"
},
  "geometry": {"coordinates":[-71.184338,42.365224],"type":"Point"}
}