{
  "type": "Feature",
  "properties": {
    "addr:full": "205 Ferry Street Malden MA 02148",
    "addr:housenumber": "205",
    "addr:postcode": "02148",
    "addr:street": "Ferry Street",
    "iso:country": "US",
    "sg:address": "205 Ferry Street",
    "sg:city": "Malden",
    "sg:classifiers": [
      {
        "category": "Personal",
        "subcategory": "Barber",
        "type": "Services"
      }
    ],
    "sg:phone": "+1 781 324 3377",
    "sg:postcode": "02148",
    "sg:province": "MA",
    "wof:name": "Hair We Are",
    "wof:placetype": "venue"
  },
  "geometry": {"coordinates":[-71.063065,42.423437],"type":"Point"}
}
