{
  "type": "Feature",
  "properties": {
    "iso:country":"US",
    "sg:address":"1101 Worcester Rd",
    "sg:city":"Framingham",
    "sg:classifiers":[
        {
            "category":"Building & Trades",
            "subcategory":"Construction",
            "type":"Services"
        }
    ],
    "sg:phone":"+1 508 879 7064",
    "sg:postcode":"01701",
    "sg:province":"MA",
    "sg:tags":[
        "contractor"
    ],
    "wof:name":"Sun Valley Homes",
    "wof:placetype":"venue"
},
  "geometry": {"coordinates":[-71.442786,42.299206],"type":"Point"}
}