{
  "type": "Feature",
  "properties": {
    "addr:full": "850 Boylston Street Suite 317 Chestnut Hill MA 02467",
    "addr:housenumber": "850",
    "addr:postcode": "02467",
    "addr:street": "Boylston Street Suite 317;Hill",
    "iso:country": "US",
    "sg:address": "850 Boylston Street Suite 317",
    "sg:city": "Chestnut Hill",
    "sg:classifiers": [
      {
        "category": "Sports \u0026 Exercise",
        "subcategory": "Gym",
        "type": "Entertainment"
      }
    ],
    "sg:phone": "+1 617 732 5282",
    "sg:postcode": "02467",
    "sg:province": "MA",
    "sg:tags": [
      "trainer"
    ],
    "wof:name": "Brigham Dental Group",
    "wof:placetype": "venue"
  },
  "geometry": {"coordinates":[-71.150699,42.326645],"type":"Point"}
}
