{
  "type": "Feature",
  "properties": {
    "iso:country":"US",
    "sg:address":"38 Turnpike St",
    "sg:city":"West Bridgewater",
    "sg:classifiers":[
        {
            "category":"Retail",
            "subcategory":"Auto Repair",
            "type":"Services"
        }
    ],
    "sg:phone":"+1 508 587 6500",
    "sg:postcode":"02379",
    "sg:province":"MA",
    "sg:tags":[
        "repairing",
        "automobile"
    ],
    "wof:name":"Advanced Imported Auto Repair",
    "wof:placetype":"venue"
},
  "geometry": {"coordinates":[-71.067892,42.04297],"type":"Point"}
}