{
  "type": "Feature",
  "properties": {
    "iso:country":"US",
    "sg:address":"521 Mount Auburn Street",
    "sg:city":"Watertown",
    "sg:classifiers":[
        {
            "category":"Health Services",
            "subcategory":"Doctor",
            "type":"Services"
        },
        {
            "category":"Sports & Exercise",
            "subcategory":"Gym",
            "type":"Entertainment"
        }
    ],
    "sg:phone":"+1 617 926 2414",
    "sg:postcode":"02472",
    "sg:province":"MA",
    "sg:tags":[
        "trainer"
    ],
    "wof:name":"Boulanger Christine Phys",
    "wof:placetype":"venue"
},
  "geometry": {"coordinates":[-71.161818,42.370504],"type":"Point"}
}