{
  "type": "Feature",
  "properties": {
    "addr:full": "950 Mason Rd Ashby MA 01431",
    "addr:housenumber": "950",
    "addr:postcode": "01431",
    "addr:street": "Mason Rd",
    "iso:country": "US",
    "sg:address": "950 Mason Rd",
    "sg:city": "Ashby",
    "sg:classifiers": [
      {
        "category": "Professional",
        "subcategory": "Lawyer \u0026 Legal Services",
        "type": "Services"
      }
    ],
    "sg:phone": "+1 978 386 7292",
    "sg:postcode": "01431",
    "sg:province": "MA",
    "wof:name": "Susan J Mahan",
    "wof:placetype": "venue"
  },
  "geometry": {"coordinates":[-71.797757,42.700227],"type":"Point"}
}
