{
  "type": "Feature",
  "properties": {
    "addr:full":"1441 Main St Springfield MA 01103",
    "addr:housenumber":"1441",
    "addr:postcode":"01103",
    "addr:street":"Main St",
    "iso:country":"US",
    "sg:address":"1441 Main St",
    "sg:city":"Springfield",
    "sg:classifiers":[
        {
            "category":"Government",
            "subcategory":"Office",
            "type":"Public Place"
        }
    ],
    "sg:phone":"+1 413 746 2445",
    "sg:postcode":"01103",
    "sg:province":"MA",
    "sg:tags":[
        "federal",
        "human"
    ],
    "wof:name":"US Social Security Adm",
    "wof:placetype":"venue"
},
  "geometry": {"coordinates":[-72.59098299999999,42.1029],"type":"Point"}
}