{
  "type": "Feature",
  "properties": {
    "addr:full":"50 Rowe St Ste 700 Melrose MA 02176",
    "addr:housenumber":"50",
    "addr:postcode":"02176",
    "addr:street":"Rowe St Ste 700",
    "iso:country":"US",
    "sg:address":"50 Rowe St Ste 700",
    "sg:city":"Melrose",
    "sg:classifiers":[
        {
            "category":"Health Services",
            "subcategory":"Doctor",
            "type":"Services"
        }
    ],
    "sg:phone":"+1 781 662 6010",
    "sg:postcode":"02176",
    "sg:province":"MA",
    "sg:tags":[
        "physician",
        "family",
        "practice",
        "surgeons",
        "medicine",
        "surgeon"
    ],
    "wof:name":"Maury A Goldman Md",
    "wof:placetype":"venue"
},
  "geometry": {"coordinates":[-71.06051600000001,42.459267],"type":"Point"}
}