{
  "type": "Feature",
  "properties": {
    "addr:full": "95 Pine St Attleboro MA 02703",
    "addr:housenumber": "95",
    "addr:postcode": "02703",
    "addr:street": "Pine St",
    "iso:country": "US",
    "sg:address": "95 Pine St",
    "sg:city": "Attleboro",
    "sg:classifiers": [
      {
        "category": "Social Services",
        "type": "Services"
      }
    ],
    "sg:phone": "+1 508 226 4543",
    "sg:postcode": "02703",
    "sg:province": "MA",
    "sg:tags": [
      "organization",
      "welfare"
    ],
    "wof:name": "WIC Program",
    "wof:placetype": "venue"
  },
  "geometry": {"coordinates":[-71.281119,41.941764],"type":"Point"}
}
