{
  "type": "Feature",
  "properties": {
    "addr:full":"80 Front St Scituate MA 02066",
    "addr:housenumber":"80",
    "addr:postcode":"02066",
    "addr:street":"Front St",
    "iso:country":"US",
    "sg:address":"80 Front St",
    "sg:city":"Scituate",
    "sg:classifiers":[
        {
            "category":"Professional",
            "subcategory":"Lawyer & Legal Services",
            "type":"Services"
        }
    ],
    "sg:phone":"+1 781 545 6620",
    "sg:postcode":"02066",
    "sg:province":"MA",
    "sg:tags":[
        "attorney"
    ],
    "wof:name":"Benway & Harrington",
    "wof:placetype":"venue"
},
  "geometry": {"coordinates":[-70.72519200000001,42.194086],"type":"Point"}
}