{
  "type": "Feature",
  "properties": {
    "addr:full": "49 Kestrel Ln Amherst MA 01002",
    "addr:housenumber": "49",
    "addr:postcode": "01002",
    "addr:street": "Kestrel Ln",
    "iso:country": "US",
    "sg:address": "49 Kestrel Ln",
    "sg:city": "Amherst",
    "sg:classifiers": [
      {
        "category": "Professional",
        "subcategory": "Management \u0026 Consulting",
        "type": "Services"
      }
    ],
    "sg:phone": "+1   ",
    "sg:postcode": "01002",
    "sg:province": "MA",
    "wof:name": "Top Management Inc",
    "wof:placetype": "venue"
  },
  "geometry": {"coordinates":[-72.496485,42.356801],"type":"Point"}
}
