{
  "type": "Feature",
  "properties": {
    "addr:full": "399 Concord St Carlisle MA 01741",
    "addr:housenumber": "399",
    "addr:postcode": "01741",
    "addr:street": "Concord St",
    "iso:country": "US",
    "sg:address": "399 Concord St",
    "sg:city": "Carlisle",
    "sg:classifiers": [
      {
        "category": "Manufacturing",
        "subcategory": "Metals",
        "type": "Manufacturing \u0026 Wholesale Goods"
      }
    ],
    "sg:phone": "+1 978 369 4727",
    "sg:postcode": "01741",
    "sg:province": "MA",
    "sg:tags": [
      "coating"
    ],
    "sg:website": "www.surfacesolutionslabs.com",
    "wof:name": "Surface Solutions Laboratories",
    "wof:placetype": "venue"
  },
  "geometry": {"coordinates":[-71.358986,42.523512],"type":"Point"}
}
