{
  "type": "Feature",
  "properties": {
    "addr:full": "1 Beacon St Boston MA 02108",
    "addr:housenumber": "1",
    "addr:postcode": "02108",
    "addr:street": "Beacon St",
    "iso:country": "US",
    "sg:address": "1 Beacon St",
    "sg:city": "Boston",
    "sg:classifiers": [
      {
        "category": "Professional",
        "subcategory": "Lawyer \u0026 Legal Services",
        "type": "Services"
      }
    ],
    "sg:phone": "+1 617 523 0002",
    "sg:postcode": "02108",
    "sg:province": "MA",
    "wof:name": "Goodman Louis A Atty",
    "wof:placetype": "venue"
  },
  "geometry": {"coordinates":[-71.061235,42.358403],"type":"Point"}
}
