{
  "type": "Feature",
  "properties": {
    "addr:full":"220 Main St Falmouth MA 02540",
    "addr:housenumber":"220",
    "addr:postcode":"02540",
    "addr:street":"Main St",
    "iso:country":"US",
    "sg:address":"220 Main St",
    "sg:city":"Falmouth",
    "sg:classifiers":[
        {
            "category":"Professional",
            "subcategory":"Lawyer & Legal Services",
            "type":"Services"
        }
    ],
    "sg:phone":"+1 508 548 1155",
    "sg:postcode":"02540",
    "sg:province":"MA",
    "sg:tags":[
        "attorney"
    ],
    "wof:name":"Mackey & Foster",
    "wof:placetype":"venue"
},
  "geometry": {"coordinates":[-70.616015,41.552237],"type":"Point"}
}