{
  "type": "Feature",
  "properties": {
    "iso:country":"US",
    "sg:address":"46 Daniel Shays Hwy",
    "sg:city":"Orange",
    "sg:classifiers":[
        {
            "category":"Retail",
            "subcategory":"Auto Repair",
            "type":"Services"
        }
    ],
    "sg:phone":"+1 978 544 2600",
    "sg:postcode":"01364",
    "sg:province":"MA",
    "sg:tags":[
        "body",
        "automobile",
        "painting"
    ],
    "wof:name":"Quality Auto Body",
    "wof:placetype":"venue"
},
  "geometry": {"coordinates":[-72.279938,42.563569],"type":"Point"}
}