{
  "type": "Feature",
  "properties": {
    "iso:country":"US",
    "sg:address":"1170 Soldiers Field Road",
    "sg:city":"Allston",
    "sg:classifiers":[
        {
            "category":"Communications",
            "subcategory":"Radio Station",
            "type":"Services"
        },
        {
            "category":"Shopping",
            "type":"Retail Goods"
        }
    ],
    "sg:phone":"+1 617 787 7181",
    "sg:postcode":"02134",
    "sg:province":"MA",
    "wof:name":"Wbz-Am Sales",
    "wof:placetype":"venue"
},
  "geometry": {"coordinates":[-71.129373,42.363215],"type":"Point"}
}