{
  "type": "Feature",
  "properties": {
    "iso:country":"US",
    "sg:address":"120 Banks St",
    "sg:city":"Winthrop",
    "sg:classifiers":[
        {
            "category":"Freight",
            "type":"Transportation"
        }
    ],
    "sg:phone":"+1 617 539 0986",
    "sg:postcode":"02152",
    "sg:province":"MA",
    "wof:name":"Vessel Operation Of Ne Inc",
    "wof:placetype":"venue"
},
  "geometry": {"coordinates":[-70.984167,42.384161],"type":"Point"}
}