{
  "type": "Feature",
  "properties": {
    "iso:country":"US",
    "sg:address":"3 White Ter",
    "sg:city":"Auburn",
    "sg:classifiers":[
        {
            "category":"Building & Trades",
            "subcategory":"Landscaping Services",
            "type":"Services"
        }
    ],
    "sg:phone":"+1 508 756 6685",
    "sg:postcode":"01501",
    "sg:province":"MA",
    "sg:tags":[
        "landscape",
        "contractor"
    ],
    "wof:name":"Bells Lawn & Irrigation Svc",
    "wof:placetype":"venue"
},
  "geometry": {"coordinates":[-71.83976199999999,42.225833],"type":"Point"}
}