{
  "type": "Feature",
  "properties": {
    "addr:full": "3 White Ter Auburn MA 01501",
    "addr:housenumber": "3",
    "addr:postcode": "01501",
    "addr:street": "White Ter",
    "iso:country": "US",
    "sg:address": "3 White Ter",
    "sg:city": "Auburn",
    "sg:classifiers": [
      {
        "category": "Building \u0026 Trades",
        "subcategory": "Landscaping Services",
        "type": "Services"
      }
    ],
    "sg:phone": "+1 508 756 6685",
    "sg:postcode": "01501",
    "sg:province": "MA",
    "sg:tags": [
      "landscape",
      "contractor"
    ],
    "wof:name": "Bells Lawn \u0026 Irrigation Svc",
    "wof:placetype": "venue"
  },
  "geometry": {"coordinates":[-71.839762,42.225833],"type":"Point"}
}
