{
  "type": "Feature",
  "properties": {
    "iso:country":"US",
    "sg:address":"101 Bradford Rd",
    "sg:city":"Hanover",
    "sg:classifiers":[
        {
            "category":"Wholesale",
            "subcategory":"Home Furnishings",
            "type":"Manufacturing & Wholesale Goods"
        }
    ],
    "sg:phone":"+1 781 924 1149",
    "sg:postcode":"02339",
    "sg:province":"MA",
    "sg:tags":[
        "draperies",
        "shades-wholesale",
        "curtain",
        "manufacturer"
    ],
    "wof:name":"Richard P Cooke Sales Inc",
    "wof:placetype":"venue"
},
  "geometry": {"coordinates":[-70.849456,42.10556],"type":"Point"}
}