{
  "type": "Feature",
  "properties": {
    "addr:full": "101 Bradford Rd Hanover MA 02339",
    "addr:housenumber": "101",
    "addr:postcode": "02339",
    "addr:street": "Bradford Rd",
    "iso:country": "US",
    "sg:address": "101 Bradford Rd",
    "sg:city": "Hanover",
    "sg:classifiers": [
      {
        "category": "Wholesale",
        "subcategory": "Home Furnishings",
        "type": "Manufacturing \u0026 Wholesale Goods"
      }
    ],
    "sg:phone": "+1 781 924 1149",
    "sg:postcode": "02339",
    "sg:province": "MA",
    "sg:tags": [
      "draperies",
      "shades-wholesale",
      "curtain",
      "manufacturer"
    ],
    "wof:name": "Richard P Cooke Sales Inc",
    "wof:placetype": "venue"
  },
  "geometry": {"coordinates":[-70.849456,42.10556],"type":"Point"}
}
