{
  "type": "Feature",
  "properties": {
    "iso:country":"US",
    "sg:address":"59 Minott Rd",
    "sg:city":"Westminster",
    "sg:classifiers":[
        {
            "category":"Building & Trades",
            "subcategory":"Construction",
            "type":"Services"
        }
    ],
    "sg:phone":"+1 978 874 2119",
    "sg:postcode":"01473",
    "sg:province":"MA",
    "sg:tags":[
        "general",
        "contractor"
    ],
    "wof:name":"Westminster Post & Beam",
    "wof:placetype":"venue"
},
  "geometry": {"coordinates":[-71.934237,42.526579],"type":"Point"}
}