{
  "type": "Feature",
  "properties": {
    "iso:country":"US",
    "sg:address":"95 Rayber Rd",
    "sg:city":"Orleans",
    "sg:classifiers":[
        {
            "category":"Real Estate",
            "subcategory":"Real Estate Agent",
            "type":"Services"
        }
    ],
    "sg:phone":"+1 508 833 2224",
    "sg:postcode":"02653",
    "sg:province":"MA",
    "sg:tags":[
        "appraiser"
    ],
    "sg:website":"www.capecodappraisal.com",
    "wof:name":"Cape Cod & Island Appraisal",
    "wof:placetype":"venue"
},
  "geometry": {"coordinates":[-69.992042,41.776206],"type":"Point"}
}