{
  "type": "Feature",
  "properties": {
    "iso:country":"US",
    "sg:address":"92 Tupper Rd",
    "sg:city":"Sandwich",
    "sg:classifiers":[
        {
            "category":"Insurance",
            "subcategory":"Insurance Agent",
            "type":"Services"
        }
    ],
    "sg:phone":"+1 508 888 0207",
    "sg:postcode":"02563",
    "sg:province":"MA",
    "sg:website":"www.almeidacarlson.com",
    "wof:name":"Almeida & Carlson Insurance",
    "wof:placetype":"venue"
},
  "geometry": {"coordinates":[-70.498559,41.764226],"type":"Point"}
}