{
  "type": "Feature",
  "properties": {
    "addr:full": "92 Tupper Rd Sandwich MA 02563",
    "addr:housenumber": "92",
    "addr:postcode": "02563",
    "addr:street": "Tupper Rd",
    "iso:country": "US",
    "ovtr:label": "Almeida \u0026 Carlson Insurance Agency, 92 Tupper Rd Sandwich MA US",
    "ovtr:similarity": 3.6490681171417236,
    "sg:address": "92 Tupper Rd",
    "sg:city": "Sandwich",
    "sg:classifiers": [
      {
        "category": "Insurance",
        "subcategory": "Insurance Agent",
        "type": "Services"
      }
    ],
    "sg:phone": "+1 508 888 0207",
    "sg:postcode": "02563",
    "sg:province": "MA",
    "sg:website": "www.almeidacarlson.com",
    "wof:name": "Almeida \u0026 Carlson Insurance",
    "wof:placetype": "venue"
  },
  "geometry": {"coordinates":[-70.498559,41.764226],"type":"Point"}
}
