{
  "type": "Feature",
  "properties": {
    "addr:full": "132 Bowden St Lowell MA 01852",
    "addr:housenumber": "132",
    "addr:postcode": "01852",
    "addr:street": "Bowden St",
    "iso:country": "US",
    "sg:address": "132 Bowden St",
    "sg:city": "Lowell",
    "sg:classifiers": [
      {
        "category": "Manufacturing",
        "subcategory": "Printing",
        "type": "Manufacturing \u0026 Wholesale Goods"
      }
    ],
    "sg:phone": "+1 978 902 5290",
    "sg:postcode": "01852",
    "sg:province": "MA",
    "sg:tags": [
      "newspaper",
      "publishing"
    ],
    "wof:name": "India Newsweek Inc",
    "wof:placetype": "venue"
  },
  "geometry": {"coordinates":[-71.299865,42.619901],"type":"Point"}
}
