{
  "type": "Feature",
  "properties": {
    "iso:country":"US",
    "sg:address":"132 Bowden St",
    "sg:city":"Lowell",
    "sg:classifiers":[
        {
            "category":"Manufacturing",
            "subcategory":"Printing",
            "type":"Manufacturing & Wholesale Goods"
        }
    ],
    "sg:phone":"+1 978 902 5290",
    "sg:postcode":"01852",
    "sg:province":"MA",
    "sg:tags":[
        "newspaper",
        "publishing"
    ],
    "wof:name":"India Newsweek Inc",
    "wof:placetype":"venue"
},
  "geometry": {"coordinates":[-71.299865,42.619901],"type":"Point"}
}