{
  "type": "Feature",
  "properties": {
    "addr:full":"280 N Main St East Longmeadow MA 01028",
    "addr:housenumber":"280",
    "addr:postcode":"01028",
    "addr:street":"N Main St",
    "iso:country":"US",
    "sg:address":"280 N Main St",
    "sg:city":"East Longmeadow",
    "sg:classifiers":[
        {
            "category":"Health Services",
            "subcategory":"Clinic",
            "type":"Services"
        }
    ],
    "sg:phone":"+1 413 525 7500",
    "sg:postcode":"01028",
    "sg:province":"MA",
    "wof:name":"A & L Holistic Health Spa",
    "wof:placetype":"venue"
},
  "geometry": {"coordinates":[-72.521049,42.075052],"type":"Point"}
}