{
  "type": "Feature",
  "properties": {
    "iso:country":"US",
    "sg:address":"84 Mill St",
    "sg:city":"Lincoln",
    "sg:classifiers":[
        {
            "category":"Professional",
            "subcategory":"Research",
            "type":"Services"
        }
    ],
    "sg:phone":"+1   ",
    "sg:postcode":"01773",
    "sg:province":"MA",
    "sg:tags":[
        "commercial",
        "physical"
    ],
    "wof:name":"Social Science Res Evaluation",
    "wof:placetype":"venue"
},
  "geometry": {"coordinates":[-71.273927,42.442706],"type":"Point"}
}