{
  "type": "Feature",
  "properties": {
    "iso:country":"US",
    "sg:address":"28 Central St",
    "sg:city":"Foxboro",
    "sg:phone":"+1 508 543 7644",
    "sg:postcode":"02035",
    "sg:province":"MA",
    "wof:name":"Xpressions",
    "wof:placetype":"venue"
},
  "geometry": {"coordinates":[-71.24921000000001,42.06356],"type":"Point"}
}