{
  "type": "Feature",
  "properties": {
    "addr:full": "28 Central St Foxboro MA 02035",
    "addr:housenumber": "28",
    "addr:postcode": "02035",
    "addr:street": "Central St",
    "iso:country": "US",
    "sg:address": "28 Central St",
    "sg:city": "Foxboro",
    "sg:phone": "+1 508 543 7644",
    "sg:postcode": "02035",
    "sg:province": "MA",
    "wof:name": "Xpressions",
    "wof:placetype": "venue"
  },
  "geometry": {"coordinates":[-71.24921,42.06356],"type":"Point"}
}
