{
  "type": "Feature",
  "properties": {
    "addr:full": "67 Merriam Ave Leominster MA 01453",
    "addr:housenumber": "67",
    "addr:postcode": "01453",
    "addr:street": "Merriam Ave",
    "iso:country": "US",
    "sg:address": "67 Merriam Ave",
    "sg:city": "Leominster",
    "sg:classifiers": [
      {
        "category": "Professional",
        "subcategory": "Accounting \u0026 Tax Preparation",
        "type": "Services"
      }
    ],
    "sg:phone": "+1 978 534 4095",
    "sg:postcode": "01453",
    "sg:province": "MA",
    "sg:tags": [
      "return",
      "accountants-certified",
      "preparation-business",
      "public"
    ],
    "wof:name": "Janet S. Chambers, P.C.",
    "wof:placetype": "venue"
  },
  "geometry": {"coordinates":[-71.760391,42.528296],"type":"Point"}
}
