{
  "type": "Feature",
  "properties": {
    "addr:full":"2 Galleria Mall Dr Taunton MA 02780",
    "addr:housenumber":"2",
    "addr:postcode":"02780",
    "addr:street":"Galleria Mall Dr",
    "iso:country":"US",
    "sg:address":"2 Galleria Mall Dr",
    "sg:city":"Taunton",
    "sg:classifiers":[
        {
            "category":"Shopping",
            "subcategory":"Clothing, Apparel, & Fashions",
            "type":"Retail Goods"
        }
    ],
    "sg:phone":"+1 508 822 7370",
    "sg:postcode":"02780",
    "sg:province":"MA",
    "sg:tags":[
        "sportswear"
    ],
    "sg:website":"www.pacsun.com",
    "wof:name":"Pacific Sunwear",
    "wof:placetype":"venue"
},
  "geometry": {"coordinates":[-71.05463,41.864481],"type":"Point"}
}