{
  "type": "Feature",
  "properties": {
    "addr:full":"9 Scroxton Dr Billerica MA 01821",
    "addr:housenumber":"9",
    "addr:postcode":"01821",
    "addr:street":"Scroxton Dr",
    "iso:country":"US",
    "sg:address":"9 Scroxton Dr",
    "sg:city":"Billerica",
    "sg:classifiers":[
        {
            "category":"Professional",
            "subcategory":"Management & Consulting",
            "type":"Services"
        }
    ],
    "sg:phone":"+1   ",
    "sg:postcode":"01821",
    "sg:province":"MA",
    "wof:name":"Lmk Enterprises Inc",
    "wof:placetype":"venue"
},
  "geometry": {"coordinates":[-71.238895,42.536766],"type":"Point"}
}