{
  "type": "Feature",
  "properties": {
    "addr:full":"8 Park Dr Westford MA 01886",
    "addr:housenumber":"8",
    "addr:postcode":"01886",
    "addr:street":"Park Dr",
    "iso:country":"US",
    "sg:address":"8 Park Dr",
    "sg:city":"Westford",
    "sg:classifiers":[
        {
            "category":"Wholesale",
            "subcategory":"Non-durable Goods",
            "type":"Manufacturing & Wholesale Goods"
        }
    ],
    "sg:phone":"+1 978 692 0393",
    "sg:postcode":"01886",
    "sg:province":"MA",
    "wof:name":"Westford China",
    "wof:placetype":"venue"
},
  "geometry": {"coordinates":[-71.43532,42.557315],"type":"Point"}
}