{
  "type": "Feature",
  "properties": {
    "addr:full": "11 Ardmore Rd Worcester MA 01609",
    "addr:housenumber": "11",
    "addr:postcode": "01609",
    "addr:street": "Ardmore Rd",
    "iso:country": "US",
    "sg:address": "11 Ardmore Rd",
    "sg:city": "Worcester",
    "sg:classifiers": [
      {
        "category": "Manufacturing",
        "subcategory": "Paper Products",
        "type": "Manufacturing \u0026 Wholesale Goods"
      },
      {
        "category": "Manufacturing",
        "subcategory": "Printing",
        "type": "Manufacturing \u0026 Wholesale Goods"
      }
    ],
    "sg:phone": "+1 508 755 9982",
    "sg:postcode": "01609",
    "sg:province": "MA",
    "sg:tags": [
      "converted",
      "label",
      "mfg"
    ],
    "wof:name": "Hammer Lithograph Corp",
    "wof:placetype": "venue"
  },
  "geometry": {"coordinates":[-71.818723,42.289136],"type":"Point"}
}
