{
  "type": "Feature",
  "properties": {
    "iso:country":"US",
    "sg:address":"11 Ardmore Rd",
    "sg:city":"Worcester",
    "sg:classifiers":[
        {
            "category":"Manufacturing",
            "subcategory":"Paper Products",
            "type":"Manufacturing & Wholesale Goods"
        },
        {
            "category":"Manufacturing",
            "subcategory":"Printing",
            "type":"Manufacturing & Wholesale Goods"
        }
    ],
    "sg:phone":"+1 508 755 9982",
    "sg:postcode":"01609",
    "sg:province":"MA",
    "sg:tags":[
        "converted",
        "label",
        "mfg"
    ],
    "wof:name":"Hammer Lithograph Corp",
    "wof:placetype":"venue"
},
  "geometry": {"coordinates":[-71.81872300000001,42.289136],"type":"Point"}
}