{
  "type": "Feature",
  "properties": {
    "iso:country":"US",
    "sg:address":"7 Jeanne Marie Dr",
    "sg:city":"Westfield",
    "sg:classifiers":[
        {
            "category":"Real Estate",
            "subcategory":"Real Estate Agent",
            "type":"Services"
        }
    ],
    "sg:phone":"+1 413 568 4163",
    "sg:postcode":"01085",
    "sg:province":"MA",
    "wof:name":"Berltrandi & Co Realtors",
    "wof:placetype":"venue"
},
  "geometry": {"coordinates":[-72.707328,42.087013],"type":"Point"}
}