{
  "type": "Feature",
  "properties": {
    "addr:full": "8 10th Ave Scituate MA 02066",
    "addr:housenumber": "8",
    "addr:postcode": "02066",
    "addr:street": "10Th Ave",
    "iso:country": "US",
    "sg:address": "8 10th Ave",
    "sg:city": "Scituate",
    "sg:classifiers": [
      {
        "category": "Social Services",
        "type": "Services"
      },
      {
        "category": "Organizations",
        "subcategory": "Community Association",
        "type": "Services"
      }
    ],
    "sg:phone": "+1 781 659 4453",
    "sg:postcode": "02066",
    "sg:province": "MA",
    "wof:name": "Marshfield Lions Club",
    "wof:placetype": "venue"
  },
  "geometry": {"coordinates":[-70.734927,42.209528],"type":"Point"}
}
