{
  "type": "Feature",
  "properties": {
    "iso:country":"US",
    "sg:address":"129 Gray St",
    "sg:city":"Amherst",
    "sg:classifiers":[
        {
            "category":"Health Services",
            "subcategory":"Health Practitioner",
            "type":"Services"
        }
    ],
    "sg:phone":"+1 413 253 4994",
    "sg:postcode":"01002",
    "sg:province":"MA",
    "sg:tags":[
        "psychotherapist"
    ],
    "wof:name":"Virginia Lewis",
    "wof:placetype":"venue"
},
  "geometry": {"coordinates":[-72.51052900000001,42.381178],"type":"Point"}
}