{
  "type": "Feature",
  "properties": {
    "addr:full": "624 Washington St Newton MA 02458",
    "addr:housenumber": "624",
    "addr:postcode": "02458",
    "addr:street": "Washington St",
    "iso:country": "US",
    "sg:address": "624 Washington St",
    "sg:city": "Newton",
    "sg:classifiers": [
      {
        "category": "Autos \u0026 Motor Vehicles",
        "subcategory": "Automobile Sales",
        "type": "Retail Goods"
      }
    ],
    "sg:phone": "+1 617 332 7800",
    "sg:postcode": "02458",
    "sg:province": "MA",
    "sg:tags": [
      "car",
      "dealer"
    ],
    "sg:website": "www.frostnissan.com",
    "wof:name": "Frost Motors Used Car Warehse",
    "wof:placetype": "venue"
  },
  "geometry": {"coordinates":[-71.201002,42.353021],"type":"Point"}
}
