{
  "type": "Feature",
  "properties": {
    "addr:full":"50 Allen St Braintree MA 02184",
    "addr:housenumber":"50",
    "addr:postcode":"02184",
    "addr:street":"Allen St",
    "iso:country":"US",
    "sg:address":"50 Allen St",
    "sg:city":"Braintree",
    "sg:classifiers":[
        {
            "category":"Shopping",
            "subcategory":"Jewelry",
            "type":"Retail Goods"
        }
    ],
    "sg:phone":"+1 781 843 6427",
    "sg:postcode":"02184",
    "sg:province":"MA",
    "sg:tags":[
        "clocks"
    ],
    "wof:name":"Starling Furniture",
    "wof:placetype":"venue"
},
  "geometry": {"coordinates":[-70.97184900000001,42.222881],"type":"Point"}
}