{
  "type": "Feature",
  "properties": {
    "iso:country":"US",
    "sg:address":"281 Winter St",
    "sg:city":"Waltham",
    "sg:classifiers":[
        {
            "category":"Real Estate",
            "subcategory":"Real Estate Agent",
            "type":"Services"
        }
    ],
    "sg:phone":"+1   ",
    "sg:postcode":"02451",
    "sg:province":"MA",
    "sg:tags":[
        "property",
        "management"
    ],
    "wof:name":"Summerset Court",
    "wof:placetype":"venue"
},
  "geometry": {"coordinates":[-71.255072,42.398737],"type":"Point"}
}