{
  "type": "Feature",
  "properties": {
    "iso:country":"US",
    "sg:address":"2 Connector Rd",
    "sg:city":"Andover",
    "sg:classifiers":[
        {
            "category":"Wholesale",
            "subcategory":"Hardware",
            "type":"Manufacturing & Wholesale Goods"
        }
    ],
    "sg:phone":"+1 978 475 2909",
    "sg:postcode":"01810",
    "sg:province":"MA",
    "sg:tags":[
        "fastener"
    ],
    "wof:name":"Celus Fasteners",
    "wof:placetype":"venue"
},
  "geometry": {"coordinates":[-71.159187,42.613946],"type":"Point"}
}