{
  "type": "Feature",
  "properties": {
    "addr:full": "2 Connector Rd Andover MA 01810",
    "addr:housenumber": "2",
    "addr:postcode": "01810",
    "addr:street": "Connector Rd",
    "iso:country": "US",
    "sg:address": "2 Connector Rd",
    "sg:city": "Andover",
    "sg:classifiers": [
      {
        "category": "Wholesale",
        "subcategory": "Hardware",
        "type": "Manufacturing \u0026 Wholesale Goods"
      }
    ],
    "sg:phone": "+1 978 475 2909",
    "sg:postcode": "01810",
    "sg:province": "MA",
    "sg:tags": [
      "fastener"
    ],
    "wof:name": "Celus Fasteners",
    "wof:placetype": "venue"
  },
  "geometry": {"coordinates":[-71.159187,42.613946],"type":"Point"}
}
