{
  "type": "Feature",
  "properties": {
    "iso:country":"US",
    "sg:address":"141 Spring St",
    "sg:city":"Hyannis",
    "sg:classifiers":[
        {
            "category":"Building & Trades",
            "subcategory":"Plumbing",
            "type":"Services"
        }
    ],
    "sg:phone":"+1 508 771 1077",
    "sg:postcode":"02601",
    "sg:province":"MA",
    "sg:tags":[
        "plumbing",
        "contractor"
    ],
    "wof:name":"Raymond Soares Plumbing & Htg",
    "wof:placetype":"venue"
},
  "geometry": {"coordinates":[-70.281435,41.661842],"type":"Point"}
}