{
  "type": "Feature",
  "properties": {
    "iso:country":"US",
    "sg:address":"20 Springdale Ave",
    "sg:city":"Canton",
    "sg:classifiers":[
        {
            "category":"Building & Trades",
            "subcategory":"Electrical",
            "type":"Services"
        }
    ],
    "sg:phone":"+1 781 828 9375",
    "sg:postcode":"02021",
    "sg:province":"MA",
    "sg:tags":[
        "electrician"
    ],
    "wof:name":"Seaver Electric Corp - CLOSED",
    "wof:placetype":"venue"
},
  "geometry": {"coordinates":[-71.127899,42.145802],"type":"Point"}
}