{
  "type": "Feature",
  "properties": {
    "addr:full": "105 Pomeroy Meadow Rd Southampton MA 01073",
    "addr:housenumber": "105",
    "addr:postcode": "01073",
    "addr:street": "Pomeroy Meadow Rd",
    "iso:country": "US",
    "sg:address": "105 Pomeroy Meadow Rd",
    "sg:city": "Southampton",
    "sg:classifiers": [
      {
        "category": "Building \u0026 Trades",
        "subcategory": "Landscaping Services",
        "type": "Services"
      }
    ],
    "sg:phone": "+1 413 527 2370",
    "sg:postcode": "01073",
    "sg:province": "MA",
    "sg:tags": [
      "tree"
    ],
    "wof:name": "Larkin Tree Svc",
    "wof:placetype": "venue"
  },
  "geometry": {"coordinates":[-72.720981,42.251948],"type":"Point"}
}
