{
  "type": "Feature",
  "properties": {
    "iso:country":"US",
    "sg:address":"105 Pomeroy Meadow Rd",
    "sg:city":"Southampton",
    "sg:classifiers":[
        {
            "category":"Building & Trades",
            "subcategory":"Landscaping Services",
            "type":"Services"
        }
    ],
    "sg:phone":"+1 413 527 2370",
    "sg:postcode":"01073",
    "sg:province":"MA",
    "sg:tags":[
        "tree"
    ],
    "wof:name":"Larkin Tree Svc",
    "wof:placetype":"venue"
},
  "geometry": {"coordinates":[-72.72098099999999,42.251948],"type":"Point"}
}