{
  "type": "Feature",
  "properties": {
    "iso:country":"US",
    "sg:address":"85 Cedar Street",
    "sg:city":"Stoneham",
    "sg:classifiers":[
        {
            "category":"Shopping",
            "subcategory":"Discount & Variety Stores",
            "type":"Retail Goods"
        }
    ],
    "sg:phone":"+1 781 279 1499",
    "sg:postcode":"02180",
    "sg:province":"MA",
    "sg:tags":[
        "wholesale"
    ],
    "wof:name":"B J's Wholesale Club #50",
    "wof:placetype":"venue"
},
  "geometry": {"coordinates":[-71.12047099999999,42.499993],"type":"Point"}
}