{
  "type": "Feature",
  "properties": {
    "iso:country":"US",
    "sg:address":"26 Warren St",
    "sg:city":"Randolph",
    "sg:classifiers":[
        {
            "category":"Retail",
            "subcategory":"Auto Repair",
            "type":"Services"
        }
    ],
    "sg:phone":"+1 781 963 5869",
    "sg:postcode":"02368",
    "sg:province":"MA",
    "sg:tags":[
        "automobile",
        "lubrication"
    ],
    "wof:name":"Jiffy Lube",
    "wof:placetype":"venue"
},
  "geometry": {"coordinates":[-71.04441,42.165392],"type":"Point"}
}