{
  "type": "Feature",
  "properties": {
    "addr:full": "177 A Massachusetts Ave Boston MA 02115",
    "addr:housenumber": "177",
    "addr:postcode": "02115",
    "addr:street": "A Massachusetts Ave",
    "iso:country": "US",
    "ovtr:label": "Pho Basil, 177 Massachusetts Ave Boston MA US",
    "ovtr:similarity": 2.573828935623169,
    "sg:address": "177 A Massachusetts Ave",
    "sg:city": "Boston",
    "sg:classifiers": [
      {
        "category": "Restaurant",
        "type": "Food \u0026 Drink"
      }
    ],
    "sg:phone": "+1 617 262 5377",
    "sg:postcode": "02115",
    "sg:province": "MA",
    "sg:tags": [
      "thai",
      "vietnamese"
    ],
    "sg:website": "www.phobasil.com/",
    "wof:name": "Pho Basil",
    "wof:placetype": "venue"
  },
  "geometry": {"coordinates":[-71.087222,42.345845],"type":"Point"}
}
