{
  "type": "Feature",
  "properties": {
    "iso:country":"US",
    "sg:address":"7 Davis Square Suite 3",
    "sg:city":"Somerville",
    "sg:classifiers":[
        {
            "category":"Health Services",
            "subcategory":"Health Practitioner",
            "type":"Services"
        }
    ],
    "sg:phone":"+1 781 697 5858",
    "sg:postcode":"02144",
    "sg:province":"MA",
    "sg:tags":[
        "acupuncture",
        "traditional",
        "medicine",
        "chinese"
    ],
    "sg:website":"www.clinic-eight.com",
    "wof:name":"Clinic Eight - Traditional Chinese Medicine",
    "wof:placetype":"venue"
},
  "geometry": {"coordinates":[-71.122651,42.396697],"type":"Point"}
}