{
  "type": "Feature",
  "properties": {
    "iso:country":"US",
    "sg:address":"36 Highland St",
    "sg:city":"Berlin",
    "sg:classifiers":[
        {
            "category":"Professional",
            "subcategory":"Engineering",
            "type":"Services"
        }
    ],
    "sg:phone":"+1 978 838 2240",
    "sg:postcode":"01503",
    "sg:province":"MA",
    "sg:tags":[
        "engineer"
    ],
    "wof:name":"Rexxon Engineering Corp",
    "wof:placetype":"venue"
},
  "geometry": {"coordinates":[-71.630882,42.396108],"type":"Point"}
}