{
  "type": "Feature",
  "properties": {
    "addr:full":"1 Cudworth Rd Webster MA 01570",
    "addr:housenumber":"1",
    "addr:postcode":"01570",
    "addr:street":"Cudworth Rd",
    "iso:country":"US",
    "sg:address":"1 Cudworth Rd",
    "sg:city":"Webster",
    "sg:classifiers":[
        {
            "category":"Wholesale",
            "subcategory":"Stationery",
            "type":"Manufacturing & Wholesale Goods"
        }
    ],
    "sg:phone":"+1 508 987 2637",
    "sg:postcode":"01570",
    "sg:province":"MA",
    "sg:tags":[
        "packaging",
        "material"
    ],
    "wof:name":"Lelanite Corp",
    "wof:placetype":"venue"
},
  "geometry": {"coordinates":[-71.85695200000001,42.066725],"type":"Point"}
}