{
  "type": "Feature",
  "properties": {
    "iso:country":"US",
    "sg:address":"599 Hildreth St",
    "sg:city":"Dracut",
    "sg:classifiers":[
        {
            "category":"Building & Trades",
            "subcategory":"Construction",
            "type":"Services"
        }
    ],
    "sg:phone":"+1   ",
    "sg:postcode":"01826",
    "sg:province":"MA",
    "sg:tags":[
        "contractor"
    ],
    "wof:name":"Bob St Hilaire Plastering Co",
    "wof:placetype":"venue"
},
  "geometry": {"coordinates":[-71.314305,42.668351],"type":"Point"}
}