{
  "type": "Feature",
  "properties": {
    "addr:full":"143 Providence St Hyde Park MA 02136",
    "addr:housenumber":"143",
    "addr:postcode":"02136",
    "addr:street":"Providence St",
    "iso:country":"US",
    "sg:address":"143 Providence St",
    "sg:city":"Hyde Park",
    "sg:classifiers":[
        {
            "category":"Farming",
            "subcategory":"Farm",
            "type":"Manufacturing & Wholesale Goods"
        }
    ],
    "sg:phone":"+1 617 364 9890",
    "sg:postcode":"02136",
    "sg:province":"MA",
    "wof:name":"City Farm Inc",
    "wof:placetype":"venue"
},
  "geometry": {"coordinates":[-71.122135,42.267438],"type":"Point"}
}