{
  "type": "Feature",
  "properties": {
    "addr:full": "195 Washington St Brookline MA 02445",
    "addr:housenumber": "195",
    "addr:postcode": "02445",
    "addr:street": "Washington St",
    "iso:country": "US",
    "sg:address": "195 Washington St",
    "sg:city": "Brookline",
    "sg:classifiers": [
      {
        "category": "Food \u0026 Beverages",
        "subcategory": "Bakery",
        "type": "Retail Goods"
      }
    ],
    "sg:phone": "+1 617 232 8182",
    "sg:postcode": "02445",
    "sg:province": "MA",
    "sg:tags": [
      "sandwich"
    ],
    "wof:name": "Sandwich Works",
    "wof:placetype": "venue"
  },
  "geometry": {"coordinates":[-71.118096,42.332132],"type":"Point"}
}
