{
  "type": "Feature",
  "properties": {
    "addr:full": "136 Oakland St Springfield MA 01108",
    "addr:housenumber": "136",
    "addr:postcode": "01108",
    "addr:street": "Oakland St",
    "iso:country": "US",
    "sg:address": "136 Oakland St",
    "sg:city": "Springfield",
    "sg:classifiers": [
      {
        "category": "Recreation",
        "type": "Entertainment"
      }
    ],
    "sg:phone": "+1 413 737 5734",
    "sg:postcode": "01108",
    "sg:province": "MA",
    "sg:tags": [
      "martial",
      "arts",
      "instruction",
      "amusement"
    ],
    "wof:name": "Griffins Judo \u0026 Karate Studios",
    "wof:placetype": "venue"
  },
  "geometry": {"coordinates":[-72.563968,42.088218],"type":"Point"}
}
