{
  "type": "Feature",
  "properties": {
    "iso:country":"US",
    "sg:address":"136 Oakland St",
    "sg:city":"Springfield",
    "sg:classifiers":[
        {
            "category":"Recreation",
            "type":"Entertainment"
        }
    ],
    "sg:phone":"+1 413 737 5734",
    "sg:postcode":"01108",
    "sg:province":"MA",
    "sg:tags":[
        "martial",
        "arts",
        "instruction",
        "amusement"
    ],
    "wof:name":"Griffins Judo & Karate Studios",
    "wof:placetype":"venue"
},
  "geometry": {"coordinates":[-72.563968,42.088218],"type":"Point"}
}