{
  "type": "Feature",
  "properties": {
    "addr:full":"1731 Centre St West Roxbury MA 02132",
    "addr:housenumber":"1731",
    "addr:postcode":"02132",
    "addr:street":"Centre St",
    "iso:country":"US",
    "sg:address":"1731 Centre St",
    "sg:city":"West Roxbury",
    "sg:classifiers":[
        {
            "category":"Shopping",
            "subcategory":"Clothing, Apparel, & Fashions",
            "type":"Retail Goods"
        }
    ],
    "sg:phone":"+1 617 323 9374",
    "sg:postcode":"02132",
    "sg:province":"MA",
    "sg:tags":[
        "t"
    ],
    "wof:name":"Super Flash T-Shirts",
    "wof:placetype":"venue"
},
  "geometry": {"coordinates":[-71.14940900000001,42.287277],"type":"Point"}
}