{
  "type": "Feature",
  "properties": {
    "addr:full":"7 Kendall Dr Northborough MA 01532",
    "addr:housenumber":"7",
    "addr:postcode":"01532",
    "addr:street":"Kendall Dr",
    "iso:country":"US",
    "sg:address":"7 Kendall Dr",
    "sg:city":"Northborough",
    "sg:classifiers":[
        {
            "category":"Professional",
            "subcategory":"Detective & Security Services",
            "type":"Services"
        }
    ],
    "sg:phone":"+1 508 393 4639",
    "sg:postcode":"01532",
    "sg:province":"MA",
    "sg:tags":[
        "information",
        "bureau"
    ],
    "wof:name":"Carelink Services Inc",
    "wof:placetype":"venue"
},
  "geometry": {"coordinates":[-71.64178200000001,42.30478],"type":"Point"}
}