{
  "type": "Feature",
  "properties": {
    "addr:full":"600 Unicorn Park Dr Woburn MA 01801",
    "addr:housenumber":"600",
    "addr:postcode":"01801",
    "addr:street":"Unicorn Park Dr",
    "iso:country":"US",
    "sg:address":"600 Unicorn Park Dr",
    "sg:city":"Woburn",
    "sg:classifiers":[
        {
            "category":"Professional",
            "subcategory":"Engineering",
            "type":"Services"
        }
    ],
    "sg:phone":"+1 781 932 3201",
    "sg:postcode":"01801",
    "sg:province":"MA",
    "sg:tags":[
        "civil",
        "consulting",
        "structural",
        "engineer"
    ],
    "sg:website":"http://www.baysideengineering.com",
    "wof:name":"Bayside Engineering Inc",
    "wof:placetype":"venue"
},
  "geometry": {"coordinates":[-71.114907,42.48557],"type":"Point"}
}