{
  "type": "Feature",
  "properties": {
    "addr:full": "348 Cooley St Springfield MA 01128",
    "addr:housenumber": "348",
    "addr:postcode": "01128",
    "addr:street": "Cooley St",
    "iso:country": "US",
    "sg:address": "348 Cooley St",
    "sg:city": "Springfield",
    "sg:classifiers": [
      {
        "category": "Shopping",
        "subcategory": "Shoes",
        "type": "Retail Goods"
      }
    ],
    "sg:phone": "+1 413 783 7004",
    "sg:postcode": "01128",
    "sg:province": "MA",
    "wof:name": "Payless Shoe Source",
    "wof:placetype": "venue"
  },
  "geometry": {"coordinates":[-72.498368,42.095402],"type":"Point"}
}
