{
  "type": "Feature",
  "properties": {
    "addr:full": "55 Lake St Gardner MA 01440",
    "addr:housenumber": "55",
    "addr:postcode": "01440",
    "addr:street": "Lake St",
    "iso:country": "US",
    "sg:address": "55 Lake St",
    "sg:city": "Gardner",
    "sg:classifiers": [
      {
        "category": "Government",
        "subcategory": "Office",
        "type": "Public Place"
      }
    ],
    "sg:phone": "+1 978 632 1004",
    "sg:postcode": "01440",
    "sg:province": "MA",
    "sg:tags": [
      "federal",
      "human"
    ],
    "wof:name": "US Social Security Adm",
    "wof:placetype": "venue"
  },
  "geometry": {"coordinates":[-71.993932,42.578336],"type":"Point"}
}
