{
  "type": "Feature",
  "properties": {
    "addr:full":"343 Commercial St Boston MA 02109",
    "addr:housenumber":"343",
    "addr:postcode":"02109",
    "addr:street":"Commercial St",
    "iso:country":"US",
    "sg:address":"343 Commercial St",
    "sg:city":"Boston",
    "sg:classifiers":[
        {
            "category":"Real Estate",
            "subcategory":"Real Estate Operator",
            "type":"Services"
        }
    ],
    "sg:phone":"+1 617 742 1647",
    "sg:postcode":"02109",
    "sg:province":"MA",
    "sg:tags":[
        "condominium"
    ],
    "wof:name":"Union Wharf Condominium Trust",
    "wof:placetype":"venue"
},
  "geometry": {"coordinates":[-71.051247,42.366119],"type":"Point"}
}