{
  "type": "Feature",
  "properties": {
    "addr:full": "55 Avocado St Springfield MA 01104",
    "addr:housenumber": "55",
    "addr:postcode": "01104",
    "addr:street": "Avocado St",
    "iso:country": "US",
    "sg:address": "55 Avocado St",
    "sg:city": "Springfield",
    "sg:classifiers": [
      {
        "category": "Wholesale",
        "subcategory": "Meat",
        "type": "Manufacturing \u0026 Wholesale Goods"
      }
    ],
    "sg:phone": "+1 413 737 8392",
    "sg:postcode": "01104",
    "sg:province": "MA",
    "sg:tags": [
      "poultry",
      "plant",
      "processing"
    ],
    "wof:name": "Royal Harvest Foods",
    "wof:placetype": "venue"
  },
  "geometry": {"coordinates":[-72.608515,42.109726],"type":"Point"}
}
