{
  "type": "Feature",
  "properties": {
    "iso:country":"US",
    "sg:address":"55 Avocado St",
    "sg:city":"Springfield",
    "sg:classifiers":[
        {
            "category":"Wholesale",
            "subcategory":"Meat",
            "type":"Manufacturing & Wholesale Goods"
        }
    ],
    "sg:phone":"+1 413 737 8392",
    "sg:postcode":"01104",
    "sg:province":"MA",
    "sg:tags":[
        "poultry",
        "plant",
        "processing"
    ],
    "wof:name":"Royal Harvest Foods",
    "wof:placetype":"venue"
},
  "geometry": {"coordinates":[-72.608515,42.109726],"type":"Point"}
}