{
  "type": "Feature",
  "properties": {
    "iso:country":"US",
    "sg:address":"14 Silver Lake Dr",
    "sg:city":"Kingston",
    "sg:classifiers":[
        {
            "category":"Building & Trades",
            "subcategory":"Construction",
            "type":"Services"
        }
    ],
    "sg:phone":"+1   ",
    "sg:postcode":"02364",
    "sg:province":"MA",
    "sg:tags":[
        "residential",
        "remodeling"
    ],
    "wof:name":"Kernozicky Roger Bldg Rmdlg Co",
    "wof:placetype":"venue"
},
  "geometry": {"coordinates":[-70.752287,41.974198],"type":"Point"}
}