{
  "type": "Feature",
  "properties": {
    "addr:full": "44 Salem St Wakefield MA 01880",
    "addr:housenumber": "44",
    "addr:postcode": "01880",
    "addr:street": "Salem St",
    "iso:country": "US",
    "sg:address": "44 Salem St",
    "sg:city": "Wakefield",
    "sg:classifiers": [
      {
        "category": "Manufacturing",
        "subcategory": "Printing",
        "type": "Manufacturing \u0026 Wholesale Goods"
      }
    ],
    "sg:phone": "+1 781 246 5320",
    "sg:postcode": "01880",
    "sg:province": "MA",
    "sg:tags": [
      "publisher"
    ],
    "wof:name": "Quannapowitt Publishers Inc",
    "wof:placetype": "venue"
  },
  "geometry": {"coordinates":[-71.068063,42.508857],"type":"Point"}
}
