{
  "type": "Feature",
  "properties": {
    "iso:country":"US",
    "sg:address":"597 Pleasant St",
    "sg:city":"Fall River",
    "sg:classifiers":[
        {
            "category":"Retail",
            "subcategory":"Auto Rental",
            "type":"Services"
        }
    ],
    "sg:phone":"+1 508 673 6522",
    "sg:postcode":"02721",
    "sg:province":"MA",
    "sg:tags":[
        "renting",
        "automobile"
    ],
    "wof:name":"Johnny's Auto Rental Agency",
    "wof:placetype":"venue"
},
  "geometry": {"coordinates":[-71.14516500000001,41.697972],"type":"Point"}
}