{
  "type": "Feature",
  "properties": {
    "iso:country":"US",
    "sg:address":"265 Broadway",
    "sg:city":"Methuen",
    "sg:classifiers":[
        {
            "category":"Wholesale",
            "subcategory":"Sporting Goods",
            "type":"Manufacturing & Wholesale Goods"
        }
    ],
    "sg:phone":"+1 978 683 6446",
    "sg:postcode":"01844",
    "sg:province":"MA",
    "wof:name":"Pendergast Sports",
    "wof:placetype":"venue"
},
  "geometry": {"coordinates":[-71.18708700000001,42.727238],"type":"Point"}
}