{
  "type": "Feature",
  "properties": {
    "iso:country":"US",
    "sg:address":"263 Copeland St",
    "sg:city":"Quincy",
    "sg:classifiers":[
        {
            "category":"Personal",
            "subcategory":"Beauty Salon",
            "type":"Services"
        }
    ],
    "sg:phone":"+1 617 328 8318",
    "sg:postcode":"02169",
    "sg:province":"MA",
    "sg:tags":[
        "manicuring"
    ],
    "wof:name":"Lily Nails",
    "wof:placetype":"venue"
},
  "geometry": {"coordinates":[-71.025036,42.244496],"type":"Point"}
}