{
  "type": "Feature",
  "properties": {
    "iso:country":"US",
    "sg:address":"32 Elderberry Dr",
    "sg:city":"Plymouth",
    "sg:classifiers":[
        {
            "category":"Sports & Exercise",
            "subcategory":"Golf",
            "type":"Entertainment"
        }
    ],
    "sg:phone":"+1 508 746 5001",
    "sg:postcode":"02360",
    "sg:province":"MA",
    "sg:website":"www.squirrelrungolf.com",
    "wof:name":"Squirrel Run Country Club",
    "wof:placetype":"venue"
},
  "geometry": {"coordinates":[-70.722801,41.932499],"type":"Point"}
}