{
  "type": "Feature",
  "properties": {
    "addr:full": "32 Elderberry Dr Plymouth MA 02360",
    "addr:housenumber": "32",
    "addr:postcode": "02360",
    "addr:street": "Elderberry Dr",
    "iso:country": "US",
    "ovtr:label": "Squirrel Run Country Club, 32 Elderberry Dr Plymouth MA US",
    "ovtr:similarity": 2.4278900623321533,
    "sg:address": "32 Elderberry Dr",
    "sg:city": "Plymouth",
    "sg:classifiers": [
      {
        "category": "Sports \u0026 Exercise",
        "subcategory": "Golf",
        "type": "Entertainment"
      }
    ],
    "sg:phone": "+1 508 746 5001",
    "sg:postcode": "02360",
    "sg:province": "MA",
    "sg:website": "www.squirrelrungolf.com",
    "wof:name": "Squirrel Run Country Club",
    "wof:placetype": "venue"
  },
  "geometry": {"coordinates":[-70.722801,41.932499],"type":"Point"}
}
