{
  "type": "Feature",
  "properties": {
    "addr:full": "56 Roland St Charlestown MA 02129",
    "addr:housenumber": "56",
    "addr:postcode": "02129",
    "addr:street": "Roland St",
    "iso:country": "US",
    "sg:address": "56 Roland St",
    "sg:city": "Charlestown",
    "sg:classifiers": [
      {
        "category": "Professional",
        "subcategory": "Management \u0026 Consulting",
        "type": "Services"
      }
    ],
    "sg:phone": "+1 617 625 0024",
    "sg:postcode": "02129",
    "sg:province": "MA",
    "sg:tags": [
      "consultant",
      "training"
    ],
    "wof:name": "Tata Interactive Systems",
    "wof:placetype": "venue"
  },
  "geometry": {"coordinates":[-71.079382,42.381653],"type":"Point"}
}
