{
  "type": "Feature",
  "properties": {
    "iso:country":"US",
    "sg:address":"56 Roland St",
    "sg:city":"Charlestown",
    "sg:classifiers":[
        {
            "category":"Professional",
            "subcategory":"Management & Consulting",
            "type":"Services"
        }
    ],
    "sg:phone":"+1 617 625 0024",
    "sg:postcode":"02129",
    "sg:province":"MA",
    "sg:tags":[
        "consultant",
        "training"
    ],
    "wof:name":"Tata Interactive Systems",
    "wof:placetype":"venue"
},
  "geometry": {"coordinates":[-71.079382,42.381653],"type":"Point"}
}