{
  "type": "Feature",
  "properties": {
    "addr:full": "248 Main St Acushnet MA 02743",
    "addr:housenumber": "248",
    "addr:postcode": "02743",
    "addr:street": "Main St",
    "iso:country": "US",
    "sg:address": "248 Main St",
    "sg:city": "Acushnet",
    "sg:classifiers": [
      {
        "category": "Wholesale",
        "subcategory": "Auto Parts",
        "type": "Manufacturing \u0026 Wholesale Goods"
      }
    ],
    "sg:phone": "+1 508 995 7200",
    "sg:postcode": "02743",
    "sg:province": "MA",
    "sg:tags": [
      "tire"
    ],
    "wof:name": "M \u0026 M Scrap Tire Removal",
    "wof:placetype": "venue"
  },
  "geometry": {"coordinates":[-70.905036,41.688897],"type":"Point"}
}
