{
  "type": "Feature",
  "properties": {
    "iso:country":"US",
    "sg:address":"93 Grand St",
    "sg:city":"Worcester",
    "sg:classifiers":[
        {
            "category":"Wholesale",
            "subcategory":"Apparel",
            "type":"Manufacturing & Wholesale Goods"
        },
        {
            "category":"Manufacturing",
            "subcategory":"Textiles",
            "type":"Manufacturing & Wholesale Goods"
        }
    ],
    "sg:phone":"+1 508 757 7468",
    "sg:postcode":"01610",
    "sg:province":"MA",
    "sg:tags":[
        "thread"
    ],
    "sg:website":"www.eddingtonthread.com",
    "wof:name":"Eddington Thread Mfg Co",
    "wof:placetype":"venue"
},
  "geometry": {"coordinates":[-71.818425,42.248784],"type":"Point"}
}