{
  "type": "Feature",
  "properties": {
    "iso:country":"US",
    "sg:address":"745 Main St",
    "sg:city":"South Weymouth",
    "sg:classifiers":[
        {
            "category":"Real Estate",
            "subcategory":"Real Estate Agent",
            "type":"Services"
        }
    ],
    "sg:phone":"+1 781 337 1894",
    "sg:postcode":"02190",
    "sg:province":"MA",
    "wof:name":"Herbert W Raymond & Son",
    "wof:placetype":"venue"
},
  "geometry": {"coordinates":[-70.95519299999999,42.181152],"type":"Point"}
}