{
  "type": "Feature",
  "properties": {
    "addr:full": "745 Main St South Weymouth MA 02190",
    "addr:housenumber": "745",
    "addr:postcode": "02190",
    "addr:street": "Main St",
    "iso:country": "US",
    "sg:address": "745 Main St",
    "sg:city": "South Weymouth",
    "sg:classifiers": [
      {
        "category": "Real Estate",
        "subcategory": "Real Estate Agent",
        "type": "Services"
      }
    ],
    "sg:phone": "+1 781 337 1894",
    "sg:postcode": "02190",
    "sg:province": "MA",
    "wof:name": "Herbert W Raymond \u0026 Son",
    "wof:placetype": "venue"
  },
  "geometry": {"coordinates":[-70.955193,42.181152],"type":"Point"}
}
