{
  "type": "Feature",
  "properties": {
    "addr:full": "64 Lamphor St Fall River MA 02721",
    "addr:housenumber": "64",
    "addr:postcode": "02721",
    "addr:street": "Lamphor St",
    "iso:country": "US",
    "ovtr:label": "Holy Trinity School, 64 Lamphor St Fall River MA US",
    "ovtr:similarity": 2.6805200576782227,
    "sg:address": "64 Lamphor St",
    "sg:city": "Fall River",
    "sg:classifiers": [
      {
        "category": "Education",
        "subcategory": "School",
        "type": "Public Place"
      }
    ],
    "sg:phone": "+1 508 673 6772",
    "sg:postcode": "02721",
    "sg:province": "MA",
    "wof:name": "Holy Trinity School",
    "wof:placetype": "venue"
  },
  "geometry": {"coordinates":[-71.156268,41.6761],"type":"Point"}
}
