{
  "type": "Feature",
  "properties": {
    "iso:country":"US",
    "sg:address":"64 Lamphor St",
    "sg:city":"Fall River",
    "sg:classifiers":[
        {
            "category":"Education",
            "subcategory":"School",
            "type":"Public Place"
        }
    ],
    "sg:phone":"+1 508 673 6772",
    "sg:postcode":"02721",
    "sg:province":"MA",
    "wof:name":"Holy Trinity School",
    "wof:placetype":"venue"
},
  "geometry": {"coordinates":[-71.156268,41.6761],"type":"Point"}
}