{
  "type": "Feature",
  "properties": {
    "addr:full":"38 11th Ave Haverhill MA 01830",
    "addr:housenumber":"38",
    "addr:postcode":"01830",
    "addr:street":"11Th Ave",
    "iso:country":"US",
    "sg:address":"38 11th Ave",
    "sg:city":"Haverhill",
    "sg:classifiers":[
        {
            "category":"Education",
            "subcategory":"Junior College",
            "type":"Public Place"
        }
    ],
    "sg:phone":"+1 978 374 3163",
    "sg:postcode":"01830",
    "sg:province":"MA",
    "sg:tags":[
        "technical",
        "institute"
    ],
    "wof:name":"Allied Health Training Inst",
    "wof:placetype":"venue"
},
  "geometry": {"coordinates":[-71.08604,42.787082],"type":"Point"}
}