{
  "type": "Feature",
  "properties": {
    "iso:country":"US",
    "sg:address":"372 Broadway",
    "sg:city":"Lawrence",
    "sg:classifiers":[
        {
            "category":"Retail",
            "subcategory":"Auto Repair",
            "type":"Services"
        }
    ],
    "sg:phone":"+1 978 683 6633",
    "sg:postcode":"01841",
    "sg:province":"MA",
    "sg:tags":[
        "body",
        "automobile",
        "painting"
    ],
    "wof:name":"O F Auto Body",
    "wof:placetype":"venue"
},
  "geometry": {"coordinates":[-71.17397200000001,42.711645],"type":"Point"}
}