{
  "type": "Feature",
  "properties": {
    "iso:country":"US",
    "sg:address":"34 Chestnut St",
    "sg:city":"Wakefield",
    "sg:classifiers":[
        {
            "category":"Personal",
            "type":"Services"
        }
    ],
    "sg:phone":"+1 781 246 9711",
    "sg:postcode":"01880",
    "sg:province":"MA",
    "sg:tags":[
        "therapist",
        "massage"
    ],
    "wof:name":"Nancy Lally",
    "wof:placetype":"venue"
},
  "geometry": {"coordinates":[-71.076014,42.502944],"type":"Point"}
}