{
  "type": "Feature",
  "properties": {
    "addr:full":"25 N Hancock St Lexington MA 02420",
    "addr:housenumber":"25",
    "addr:postcode":"02420",
    "addr:street":"N Hancock St",
    "iso:country":"US",
    "sg:address":"25 N Hancock St",
    "sg:city":"Lexington",
    "sg:classifiers":[
        {
            "category":"Health Services",
            "subcategory":"Health Practitioner",
            "type":"Services"
        }
    ],
    "sg:phone":"+1   ",
    "sg:postcode":"02420",
    "sg:province":"MA",
    "sg:tags":[
        "psychologist"
    ],
    "wof:name":"Roberta Caplan",
    "wof:placetype":"venue"
},
  "geometry": {"coordinates":[-71.238271,42.463156],"type":"Point"}
}