{
  "type": "Feature",
  "properties": {
    "addr:full":"72 North St Hyannis MA 02601",
    "addr:housenumber":"72",
    "addr:postcode":"02601",
    "addr:street":"North St",
    "iso:country":"US",
    "sg:address":"72 North St",
    "sg:city":"Hyannis",
    "sg:classifiers":[
        {
            "category":"Bars & Pubs",
            "type":"Food & Drink"
        },
        {
            "category":"Restaurant",
            "type":"Food & Drink"
        },
        {
            "category":"Bars & Pubs",
            "subcategory":"Sports Bar",
            "type":"Food & Drink"
        }
    ],
    "sg:phone":"+1 508 775 7100",
    "sg:postcode":"02601",
    "sg:province":"MA",
    "sg:tags":[
        "brew",
        "house",
        "steak",
        "steakhouse"
    ],
    "wof:name":"Steak House and Sports Bar",
    "wof:placetype":"venue"
},
  "geometry": {"coordinates":[-70.2855,41.6538],"type":"Point"}
}