{
  "type": "Feature",
  "properties": {
    "iso:country":"US",
    "sg:address":"60 School St",
    "sg:city":"Brockton",
    "sg:classifiers":[
        {
            "category":"Organizations",
            "subcategory":"Professional Association",
            "type":"Services"
        }
    ],
    "sg:phone":"+1 508 586 0500",
    "sg:postcode":"02301",
    "sg:province":"MA",
    "sg:tags":[
        "chambers",
        "commerce"
    ],
    "sg:website":"www.metrosouthchamber.com",
    "wof:name":"Metro South Chamber-Commerce",
    "wof:placetype":"venue"
},
  "geometry": {"coordinates":[-71.01777199999999,42.082611],"type":"Point"}
}