{
  "type": "Feature",
  "properties": {
    "addr:full": "60 School St Brockton MA 02301",
    "addr:housenumber": "60",
    "addr:postcode": "02301",
    "addr:street": "School St",
    "iso:country": "US",
    "ovtr:label": "Metro South Chamber of Commerce, 60 School St Brockton MA US",
    "ovtr:similarity": 3.2434329986572266,
    "sg:address": "60 School St",
    "sg:city": "Brockton",
    "sg:classifiers": [
      {
        "category": "Organizations",
        "subcategory": "Professional Association",
        "type": "Services"
      }
    ],
    "sg:phone": "+1 508 586 0500",
    "sg:postcode": "02301",
    "sg:province": "MA",
    "sg:tags": [
      "chambers",
      "commerce"
    ],
    "sg:website": "www.metrosouthchamber.com",
    "wof:name": "Metro South Chamber-Commerce",
    "wof:placetype": "venue"
  },
  "geometry": {"coordinates":[-71.017772,42.082611],"type":"Point"}
}
