{
  "type": "Feature",
  "properties": {
    "iso:country":"US",
    "sg:address":"39 Hamilton St",
    "sg:city":"Southbridge",
    "sg:classifiers":[
        {
            "category":"Restaurant",
            "type":"Food & Drink"
        }
    ],
    "sg:phone":"+1 508 765 2793",
    "sg:postcode":"01550",
    "sg:province":"MA",
    "wof:name":"Spanky's Roadhouse",
    "wof:placetype":"venue"
},
  "geometry": {"coordinates":[-72.03442800000001,42.07663],"type":"Point"}
}