{
  "type": "Feature",
  "properties": {
    "addr:full": "39 Hamilton St Southbridge MA 01550",
    "addr:housenumber": "39",
    "addr:postcode": "01550",
    "addr:street": "Hamilton St",
    "iso:country": "US",
    "sg:address": "39 Hamilton St",
    "sg:city": "Southbridge",
    "sg:classifiers": [
      {
        "category": "Restaurant",
        "type": "Food \u0026 Drink"
      }
    ],
    "sg:phone": "+1 508 765 2793",
    "sg:postcode": "01550",
    "sg:province": "MA",
    "wof:name": "Spanky's Roadhouse",
    "wof:placetype": "venue"
  },
  "geometry": {"coordinates":[-72.034428,42.07663],"type":"Point"}
}
