{
  "type": "Feature",
  "properties": {
    "addr:full": "Massachusetts General Hospital 55 Fruit St Boston MA 02114",
    "addr:housenumber": "55",
    "addr:postcode": "02114",
    "addr:street": "Fruit St",
    "iso:country": "US",
    "sg:address": "Massachusetts General Hospital 55 Fruit St",
    "sg:city": "Boston",
    "sg:classifiers": [
      {
        "category": "Restaurant",
        "type": "Food \u0026 Drink"
      }
    ],
    "sg:postcode": "02114",
    "sg:province": "MA",
    "sg:website": "www.massgeneral.org",
    "wof:name": "MGH Canteen",
    "wof:placetype": "venue"
  },
  "geometry": {"coordinates":[-71.069779,42.362429],"type":"Point"}
}
