{
  "type": "Feature",
  "properties": {
    "addr:full":"746 Massachusetts Ave Cambridge MA 02139",
    "addr:housenumber":"746",
    "addr:postcode":"02139",
    "addr:street":"Massachusetts Ave",
    "iso:country":"US",
    "sg:address":"746 Massachusetts Ave",
    "sg:city":"Cambridge",
    "sg:classifiers":[
        {
            "category":"Retail",
            "subcategory":"Laundry & Dry Cleaning",
            "type":"Services"
        }
    ],
    "sg:phone":"+1 617 354 8808",
    "sg:postcode":"02139",
    "sg:province":"MA",
    "sg:tags":[
        "cleaner"
    ],
    "wof:name":"Coolidge Looking Good",
    "wof:placetype":"venue"
},
  "geometry": {"coordinates":[-71.105305,42.366332],"type":"Point"}
}