{
  "type": "Feature",
  "properties": {
    "iso:country":"US",
    "sg:address":"28 Sunset Rd",
    "sg:city":"Wellesley",
    "sg:classifiers":[
        {
            "category":"Banks & Credit Unions",
            "subcategory":"Financial Services",
            "type":"Services"
        }
    ],
    "sg:phone":"+1 781 431 7676",
    "sg:postcode":"02482",
    "sg:province":"MA",
    "sg:tags":[
        "sharing",
        "profit",
        "annuity",
        "retirement",
        "planning",
        "plan",
        "insurance",
        "pension"
    ],
    "wof:name":"Whitney Pension Associates Inc",
    "wof:placetype":"venue"
},
  "geometry": {"coordinates":[-71.302071,42.300968],"type":"Point"}
}