{
  "type": "Feature",
  "properties": {
    "addr:full": "309 Shawmut Avenue Boston MA 02118",
    "addr:housenumber": "309",
    "addr:postcode": "02118",
    "addr:street": "Shawmut Avenue",
    "iso:country": "US",
    "ovtr:label": "B Cummings Hair Salon, 309 Shawmut Ave Boston MA US",
    "ovtr:similarity": 2.7268619537353516,
    "sg:address": "309 Shawmut Avenue",
    "sg:city": "Boston",
    "sg:classifiers": [
      {
        "category": "Personal",
        "subcategory": "Beauty Salon",
        "type": "Services"
      }
    ],
    "sg:phone": "+1 617 338 5356",
    "sg:postcode": "02118",
    "sg:province": "MA",
    "sg:tags": [
      "hair"
    ],
    "wof:name": "B Cummings Hair Salon",
    "wof:placetype": "venue"
  },
  "geometry": {"coordinates":[-71.070145,42.34225],"type":"Point"}
}
