{
  "type": "Feature",
  "properties": {
    "addr:full":"750 Webster St Marshfield MA 02050",
    "addr:housenumber":"750",
    "addr:postcode":"02050",
    "addr:street":"Webster St",
    "iso:country":"US",
    "sg:address":"750 Webster St",
    "sg:city":"Marshfield",
    "sg:classifiers":[
        {
            "category":"Building & Trades",
            "subcategory":"Landscaping Services",
            "type":"Services"
        }
    ],
    "sg:phone":"+1 781 826 1441",
    "sg:postcode":"02050",
    "sg:province":"MA",
    "sg:tags":[
        "landscape",
        "contractor"
    ],
    "wof:name":"Edward's Escavating",
    "wof:placetype":"venue"
},
  "geometry": {"coordinates":[-70.697782,42.086386],"type":"Point"}
}