{
  "type": "Feature",
  "properties": {
    "iso:country":"US",
    "sg:address":"59 Crescent Street",
    "sg:city":"Winthrop",
    "sg:classifiers":[
        {
            "category":"Real Estate",
            "subcategory":"Real Estate Services",
            "type":"Services"
        }
    ],
    "sg:phone":"+1 617 846 8328",
    "sg:postcode":"02152",
    "sg:province":"MA",
    "sg:tags":[
        "home",
        "inspector",
        "inspection"
    ],
    "sg:website":"www.rechomeinspections.com/",
    "wof:name":"Rec Consultants",
    "wof:placetype":"venue"
},
  "geometry": {"coordinates":[-70.976263,42.380923],"type":"Point"}
}