{
  "type": "Feature",
  "properties": {
    "addr:full": "187 Neck Rd Haverhill MA 01835",
    "addr:housenumber": "187",
    "addr:postcode": "01835",
    "addr:street": "Neck Rd",
    "iso:country": "US",
    "sg:address": "187 Neck Rd",
    "sg:city": "Haverhill",
    "sg:classifiers": [
      {
        "category": "Home \u0026 Garden",
        "subcategory": "Household Appliances",
        "type": "Retail Goods"
      },
      {
        "category": "Wholesale",
        "subcategory": "Construction Materials",
        "type": "Manufacturing \u0026 Wholesale Goods"
      },
      {
        "category": "Home \u0026 Garden",
        "subcategory": "Building Materials",
        "type": "Retail Goods"
      },
      {
        "category": "Building \u0026 Trades",
        "subcategory": "Construction",
        "type": "Services"
      },
      {
        "category": "Utilities",
        "type": "Services"
      }
    ],
    "sg:phone": "+1 978 373 1666",
    "sg:postcode": "01835",
    "sg:province": "MA",
    "sg:tags": [
      "systems-wholesale",
      "units-manufacturers",
      "dishwashing",
      "specialty",
      "system",
      "machine",
      "equipment",
      "heating",
      "distributor",
      "contractor",
      "air conditioning"
    ],
    "sg:website": "http://www.runtalnorthamerica.com",
    "wof:name": "Runtal North America, Inc.",
    "wof:placetype": "venue"
  },
  "geometry": {"coordinates":[-71.118379,42.754521],"type":"Point"}
}
