{
  "type": "Feature",
  "properties": {
    "iso:country":"US",
    "sg:address":"3 Condlin Dr",
    "sg:city":"Randolph",
    "sg:classifiers":[
        {
            "category":"Retail",
            "subcategory":"Laundry & Dry Cleaning",
            "type":"Services"
        }
    ],
    "sg:phone":"+1 781 963 7980",
    "sg:postcode":"02368",
    "sg:province":"MA",
    "wof:name":"Laundry Room Plus",
    "wof:placetype":"venue"
},
  "geometry": {"coordinates":[-71.045733,42.166646],"type":"Point"}
}