{
  "type": "Feature",
  "properties": {
    "addr:full": "3 Condlin Dr Randolph MA 02368",
    "addr:housenumber": "3",
    "addr:postcode": "02368",
    "addr:street": "Condlin Dr",
    "iso:country": "US",
    "sg:address": "3 Condlin Dr",
    "sg:city": "Randolph",
    "sg:classifiers": [
      {
        "category": "Retail",
        "subcategory": "Laundry \u0026 Dry Cleaning",
        "type": "Services"
      }
    ],
    "sg:phone": "+1 781 963 7980",
    "sg:postcode": "02368",
    "sg:province": "MA",
    "wof:name": "Laundry Room Plus",
    "wof:placetype": "venue"
  },
  "geometry": {"coordinates":[-71.045733,42.166646],"type":"Point"}
}
