{
  "type": "Feature",
  "properties": {
    "addr:full":"166 Central Ave Seekonk MA 02771",
    "addr:housenumber":"166",
    "addr:postcode":"02771",
    "addr:street":"Central Ave",
    "iso:country":"US",
    "sg:address":"166 Central Ave",
    "sg:city":"Seekonk",
    "sg:classifiers":[
        {
            "category":"Autos & Motor Vehicles",
            "subcategory":"Automobile Sales",
            "type":"Retail Goods"
        }
    ],
    "sg:phone":"+1 508 761 9680",
    "sg:postcode":"02771",
    "sg:province":"MA",
    "sg:tags":[
        "used"
    ],
    "wof:name":"Countryside Motors Inc",
    "wof:placetype":"venue"
},
  "geometry": {"coordinates":[-71.332241,41.889055],"type":"Point"}
}