{
  "type": "Feature",
  "properties": {
    "addr:full": "Independence Mall Kingston MA 02364",
    "addr:postcode": "02364",
    "iso:country": "US",
    "sg:address": "Independence Mall",
    "sg:city": "Kingston",
    "sg:classifiers": [
      {
        "category": "Restaurant",
        "type": "Food \u0026 Drink"
      }
    ],
    "sg:menulink": "http://www.allmenus.com/ma/kingston/68220-uno-chicago-grill/menu/",
    "sg:phone": "+1 781 582 2482",
    "sg:postcode": "02364",
    "sg:province": "MA",
    "sg:tags": [
      "american",
      "italian",
      "pizza"
    ],
    "wof:name": "Uno Chicago Grill",
    "wof:placetype": "venue"
  },
  "geometry": {"coordinates":[-70.712088,41.973794],"type":"Point"}
}
