{
  "type": "Feature",
  "properties": {
    "addr:full":"1 William C Gould Jr Way Kingston MA 02364",
    "addr:housenumber":"1",
    "addr:postcode":"02364",
    "addr:street":"William C Gould Jr Way",
    "iso:country":"US",
    "sg:address":"1 William C Gould Jr Way",
    "sg:city":"Kingston",
    "sg:classifiers":[
        {
            "category":"Autos & Motor Vehicles",
            "subcategory":"Automobile Sales",
            "type":"Retail Goods"
        }
    ],
    "sg:phone":"+1 781 582 0163",
    "sg:postcode":"02364",
    "sg:province":"MA",
    "sg:tags":[
        "car",
        "dealer"
    ],
    "wof:name":"Sullivan Brothers Mitsubishi",
    "wof:placetype":"venue"
},
  "geometry": {"coordinates":[-70.704965,41.971962],"type":"Point"}
}