{
  "type": "Feature",
  "properties": {
    "addr:full":"36 Market St Ipswich MA 01938",
    "addr:housenumber":"36",
    "addr:postcode":"01938",
    "addr:street":"Market St",
    "iso:country":"US",
    "sg:address":"36 Market St",
    "sg:city":"Ipswich",
    "sg:classifiers":[
        {
            "category":"Personal",
            "subcategory":"Beauty Salon",
            "type":"Services"
        }
    ],
    "sg:phone":"+1 978 922 4675",
    "sg:postcode":"01938",
    "sg:province":"MA",
    "wof:name":"Reflections",
    "wof:placetype":"venue"
},
  "geometry": {"coordinates":[-70.838179,42.679569],"type":"Point"}
}