{
  "type": "Feature",
  "properties": {
    "iso:country":"US",
    "sg:address":"165 East St",
    "sg:city":"Ludlow",
    "sg:classifiers":[
        {
            "category":"Personal",
            "subcategory":"Shoe Repair & Shine",
            "type":"Services"
        }
    ],
    "sg:phone":"+1 413 589 7706",
    "sg:postcode":"01056",
    "sg:province":"MA",
    "sg:tags":[
        "repairing",
        "parlor",
        "boot"
    ],
    "wof:name":"Tony's Shoe Repair",
    "wof:placetype":"venue"
},
  "geometry": {"coordinates":[-72.47731899999999,42.158123],"type":"Point"}
}