{
  "type": "Feature",
  "properties": {
    "iso:country":"US",
    "sg:address":"16 Appleton St",
    "sg:city":"Everett",
    "sg:classifiers":[
        {
            "category":"Building & Trades",
            "subcategory":"Cleaning & Sanitation",
            "type":"Services"
        }
    ],
    "sg:phone":"+1 781 324 1200",
    "sg:postcode":"02149",
    "sg:province":"MA",
    "sg:tags":[
        "house"
    ],
    "wof:name":"A & C Cleaning Svc",
    "wof:placetype":"venue"
},
  "geometry": {"coordinates":[-71.062432,42.407181],"type":"Point"}
}