{
  "type": "Feature",
  "properties": {
    "addr:full": "16 Appleton St Everett MA 02149",
    "addr:housenumber": "16",
    "addr:postcode": "02149",
    "addr:street": "Appleton St",
    "iso:country": "US",
    "sg:address": "16 Appleton St",
    "sg:city": "Everett",
    "sg:classifiers": [
      {
        "category": "Building \u0026 Trades",
        "subcategory": "Cleaning \u0026 Sanitation",
        "type": "Services"
      }
    ],
    "sg:phone": "+1 781 324 1200",
    "sg:postcode": "02149",
    "sg:province": "MA",
    "sg:tags": [
      "house"
    ],
    "wof:name": "A \u0026 C Cleaning Svc",
    "wof:placetype": "venue"
  },
  "geometry": {"coordinates":[-71.062432,42.407181],"type":"Point"}
}
