{
  "type": "Feature",
  "properties": {
    "addr:full": "705 High St Westwood MA 02090",
    "addr:housenumber": "705",
    "addr:postcode": "02090",
    "addr:street": "High St",
    "iso:country": "US",
    "sg:address": "705 High St",
    "sg:city": "Westwood",
    "sg:classifiers": [
      {
        "category": "Banks \u0026 Credit Unions",
        "subcategory": "Bank",
        "type": "Services"
      },
      {
        "category": "Banks \u0026 Credit Unions",
        "subcategory": "Financial Services",
        "type": "Services"
      }
    ],
    "sg:phone": "+1 781 326 6400",
    "sg:postcode": "02090",
    "sg:province": "MA",
    "sg:tags": [
      "broker",
      "mortgage"
    ],
    "wof:name": "Bay State Federal Bank",
    "wof:placetype": "venue"
  },
  "geometry": {"coordinates":[-71.222603,42.2253],"type":"Point"}
}
