{
  "type": "Feature",
  "properties": {
    "iso:country":"US",
    "sg:address":"705 High St",
    "sg:city":"Westwood",
    "sg:classifiers":[
        {
            "category":"Banks & Credit Unions",
            "subcategory":"Bank",
            "type":"Services"
        },
        {
            "category":"Banks & Credit Unions",
            "subcategory":"Financial Services",
            "type":"Services"
        }
    ],
    "sg:phone":"+1 781 326 6400",
    "sg:postcode":"02090",
    "sg:province":"MA",
    "sg:tags":[
        "broker",
        "mortgage"
    ],
    "wof:name":"Bay State Federal Bank",
    "wof:placetype":"venue"
},
  "geometry": {"coordinates":[-71.22260300000001,42.2253],"type":"Point"}
}