{
  "type": "Feature",
  "properties": {
    "iso:country":"US",
    "sg:address":"17 Oak St",
    "sg:city":"Needham",
    "sg:classifiers":[
        {
            "category":"Health Services",
            "subcategory":"Doctor",
            "type":"Services"
        }
    ],
    "sg:phone":"+1 781 455 6200",
    "sg:postcode":"02492",
    "sg:province":"MA",
    "sg:tags":[
        "physician",
        "surgeon"
    ],
    "wof:name":"Cohen, Steven B, Md - Oak Street Medical Assoc",
    "wof:placetype":"venue"
},
  "geometry": {"coordinates":[-71.238293,42.276931],"type":"Point"}
}