{
  "type": "Feature",
  "properties": {
    "addr:full":"147 Holliston St Medway MA 02053",
    "addr:housenumber":"147",
    "addr:postcode":"02053",
    "addr:street":"Holliston St",
    "iso:country":"US",
    "sg:address":"147 Holliston St",
    "sg:city":"Medway",
    "sg:classifiers":[
        {
            "category":"Building & Trades",
            "subcategory":"Construction",
            "type":"Services"
        }
    ],
    "sg:phone":"+1 508 877 1911",
    "sg:postcode":"02053",
    "sg:province":"MA",
    "sg:tags":[
        "general",
        "contractor"
    ],
    "wof:name":"Cantin Construction Co",
    "wof:placetype":"venue"
},
  "geometry": {"coordinates":[-71.41002,42.16684],"type":"Point"}
}