{
  "type": "Feature",
  "properties": {
    "iso:country":"US",
    "sg:address":"587 Albany St",
    "sg:city":"Roxbury",
    "sg:classifiers":[
        {
            "category":"Bars & Pubs",
            "subcategory":"Nightclub",
            "type":"Food & Drink"
        }
    ],
    "sg:phone":"+1 617 338 7453",
    "sg:postcode":"02118",
    "sg:province":"MA",
    "sg:tags":[
        "nightlife"
    ],
    "wof:name":"Pontian Soc Panagia Soumela",
    "wof:placetype":"venue"
},
  "geometry": {"coordinates":[-71.06770299999999,42.337502],"type":"Point"}
}