{
  "type": "Feature",
  "properties": {
    "addr:full":"39 Norfolk Rd Millis MA 02054",
    "addr:housenumber":"39",
    "addr:postcode":"02054",
    "addr:street":"Norfolk Rd",
    "iso:country":"US",
    "sg:address":"39 Norfolk Rd",
    "sg:city":"Millis",
    "sg:classifiers":[
        {
            "category":"Professional",
            "subcategory":"Engineering",
            "type":"Services"
        },
        {
            "category":"Home & Garden",
            "subcategory":"Building Materials",
            "type":"Retail Goods"
        },
        {
            "category":"Building & Trades",
            "subcategory":"Construction",
            "type":"Services"
        }
    ],
    "sg:phone":"+1 508 376 5545",
    "sg:postcode":"02054",
    "sg:province":"MA",
    "sg:tags":[
        "system",
        "specialty",
        "heating",
        "contractor",
        "equipment",
        "air conditioning"
    ],
    "sg:website":"http://find.trane.com/tcs-dealer-412764?utm_source=YP&utm_medium=banner&utm_campaign=TL",
    "wof:name":"Kermit Schulz",
    "wof:placetype":"venue"
},
  "geometry": {"coordinates":[-71.34993,42.144611],"type":"Point"}
}