{
  "type": "Feature",
  "properties": {
    "iso:country":"US",
    "sg:address":"15 Marlboro St",
    "sg:city":"Belmont",
    "sg:classifiers":[
        {
            "category":"Professional",
            "subcategory":"Management & Consulting",
            "type":"Services"
        }
    ],
    "sg:phone":"+1   ",
    "sg:postcode":"02478",
    "sg:province":"MA",
    "sg:tags":[
        "datum",
        "business"
    ],
    "wof:name":"Reverb45 Co Inc",
    "wof:placetype":"venue"
},
  "geometry": {"coordinates":[-71.15678,42.376965],"type":"Point"}
}