{
  "type": "Feature",
  "properties": {
    "addr:full": "555 Merrimack St Lowell MA 01854",
    "addr:housenumber": "555",
    "addr:postcode": "01854",
    "addr:street": "Merrimack St",
    "iso:country": "US",
    "sg:address": "555 Merrimack St",
    "sg:city": "Lowell",
    "sg:classifiers": [
      {
        "category": "Shopping",
        "subcategory": "Jewelry",
        "type": "Retail Goods"
      }
    ],
    "sg:phone": "+1 978 458 1061",
    "sg:postcode": "01854",
    "sg:province": "MA",
    "sg:tags": [
      "jeweler"
    ],
    "wof:name": "Schiller Jewelers",
    "wof:placetype": "venue"
  },
  "geometry": {"coordinates":[-71.317064,42.647335],"type":"Point"}
}
