{
  "type": "Feature",
  "properties": {
    "addr:full":"80 Sumner Ave Springfield MA 01108",
    "addr:housenumber":"80",
    "addr:postcode":"01108",
    "addr:street":"Sumner Ave",
    "iso:country":"US",
    "sg:address":"80 Sumner Ave",
    "sg:city":"Springfield",
    "sg:classifiers":[
        {
            "category":"Health Services",
            "subcategory":"Chiropractor",
            "type":"Services"
        }
    ],
    "sg:phone":"+1 413 733 0404",
    "sg:postcode":"01108",
    "sg:province":"MA",
    "sg:website":"www.physiciansplus.net",
    "wof:name":"Therapeutic Touch",
    "wof:placetype":"venue"
},
  "geometry": {"coordinates":[-72.573701,42.083109],"type":"Point"}
}