{
  "type": "Feature",
  "properties": {
    "addr:full": "374 Merrimac St Newburyport MA 01950",
    "addr:housenumber": "374",
    "addr:postcode": "01950",
    "addr:street": "Merrimac St",
    "iso:country": "US",
    "sg:address": "374 Merrimac St",
    "sg:city": "Newburyport",
    "sg:classifiers": [
      {
        "category": "Manufacturing",
        "subcategory": "Electronics",
        "type": "Manufacturing \u0026 Wholesale Goods"
      }
    ],
    "sg:phone": "+1 978 462 6662",
    "sg:postcode": "01950",
    "sg:province": "MA",
    "sg:tags": [
      "equipment",
      "electronic",
      "supply"
    ],
    "sg:website": "www.ferrazshawmut.com",
    "wof:name": "Ferraz Shawmut Inc",
    "wof:placetype": "venue"
  },
  "geometry": {"coordinates":[-70.887412,42.82266],"type":"Point"}
}
