{
  "type": "Feature",
  "properties": {
    "addr:full":"93 Main St Andover MA 01810",
    "addr:housenumber":"93",
    "addr:postcode":"01810",
    "addr:street":"Main St",
    "iso:country":"US",
    "sg:address":"93 Main St",
    "sg:city":"Andover",
    "sg:classifiers":[
        {
            "category":"Shopping",
            "subcategory":"Clothing, Apparel, & Fashions",
            "type":"Retail Goods"
        }
    ],
    "sg:phone":"+1 978 470 0632",
    "sg:postcode":"01810",
    "sg:province":"MA",
    "wof:name":"Vena Coco Collection",
    "wof:placetype":"venue"
},
  "geometry": {"coordinates":[-71.138391,42.653224],"type":"Point"}
}