{
  "type": "Feature",
  "properties": {
    "iso:country":"US",
    "sg:address":"54 Old Garrison Rd",
    "sg:city":"Sudbury",
    "sg:classifiers":[
        {
            "category":"Shopping",
            "subcategory":"Gifts & Souvenirs",
            "type":"Retail Goods"
        }
    ],
    "sg:phone":"+1   ",
    "sg:postcode":"01776",
    "sg:province":"MA",
    "sg:tags":[
        "novelty"
    ],
    "wof:name":"Berks Vintage Militaria LLC",
    "wof:placetype":"venue"
},
  "geometry": {"coordinates":[-71.457048,42.36829],"type":"Point"}
}