{
  "type": "Feature",
  "properties": {
    "addr:full":"600 Main St Williamstown MA 01267",
    "addr:housenumber":"600",
    "addr:postcode":"01267",
    "addr:street":"Main St",
    "iso:country":"US",
    "sg:address":"600 Main St",
    "sg:city":"Williamstown",
    "sg:phone":"+1 413 458 5904",
    "sg:postcode":"01267",
    "sg:province":"MA",
    "sg:tags":[
        "gas"
    ],
    "wof:name":"Ameri Gas Propane LP",
    "wof:placetype":"venue"
},
  "geometry": {"coordinates":[-73.19369,42.708815],"type":"Point"}
}