{
  "type": "Feature",
  "properties": {
    "addr:full": "85 Sexton Ave Westwood MA 02090",
    "addr:housenumber": "85",
    "addr:postcode": "02090",
    "addr:street": "Sexton Ave",
    "iso:country": "US",
    "sg:address": "85 Sexton Ave",
    "sg:city": "Westwood",
    "sg:classifiers": [
      {
        "category": "Shopping",
        "subcategory": "Gifts \u0026 Souvenirs",
        "type": "Retail Goods"
      }
    ],
    "sg:phone": "+1 781 251 9441",
    "sg:postcode": "02090",
    "sg:province": "MA",
    "sg:tags": [
      "shop"
    ],
    "wof:name": "Alisha's Gallery Inc",
    "wof:placetype": "venue"
  },
  "geometry": {"coordinates":[-71.225914,42.212673],"type":"Point"}
}
