{
  "type": "Feature",
  "properties": {
    "addr:full": "48 Main St Nantucket MA 02554",
    "addr:housenumber": "48",
    "addr:postcode": "02554",
    "addr:street": "Main St",
    "iso:country": "US",
    "sg:address": "48 Main St",
    "sg:city": "Nantucket",
    "sg:classifiers": [
      {
        "category": "Shopping",
        "subcategory": "Clothing, Apparel, \u0026 Fashions",
        "type": "Retail Goods"
      }
    ],
    "sg:phone": "+1 508 325 4622",
    "sg:postcode": "02554",
    "sg:province": "MA",
    "wof:name": "Island Breeze",
    "wof:placetype": "venue"
  },
  "geometry": {"coordinates":[-70.099015,41.283187],"type":"Point"}
}
