{
  "type": "Feature",
  "properties": {
    "iso:country":"US",
    "sg:address":"53 West St",
    "sg:city":"Boston",
    "sg:classifiers":[
        {
            "category":"Professional",
            "subcategory":"Lawyer & Legal Services",
            "type":"Services"
        }
    ],
    "sg:phone":"+1 617 570 1067",
    "sg:postcode":"02111",
    "sg:province":"MA",
    "wof:name":"Arel Joyce M Lwyr",
    "wof:placetype":"venue"
},
  "geometry": {"coordinates":[-71.063067,42.355083],"type":"Point"}
}