{
  "type": "Feature",
  "properties": {
    "addr:full":"95 E Falmouth Hwy East Falmouth MA 02536",
    "addr:housenumber":"95",
    "addr:postcode":"02536",
    "addr:street":"E Falmouth Hwy",
    "iso:country":"US",
    "sg:address":"95 E Falmouth Hwy",
    "sg:city":"East Falmouth",
    "sg:classifiers":[
        {
            "category":"Professional",
            "subcategory":"Management & Consulting",
            "type":"Services"
        }
    ],
    "sg:phone":"+1   ",
    "sg:postcode":"02536",
    "sg:province":"MA",
    "sg:tags":[
        "retail",
        "direct",
        "sales"
    ],
    "wof:name":"Gregory A Carey",
    "wof:placetype":"venue"
},
  "geometry": {"coordinates":[-70.56918899999999,41.578582],"type":"Point"}
}