{
  "type": "Feature",
  "properties": {
    "iso:country":"US",
    "sg:address":"29 Sawyer Rd",
    "sg:city":"Waltham",
    "sg:classifiers":[
        {
            "category":"Communications",
            "type":"Services"
        }
    ],
    "sg:phone":"+1 781 736 1200",
    "sg:postcode":"02453",
    "sg:province":"MA",
    "wof:name":"Starbak Communications",
    "wof:placetype":"venue"
},
  "geometry": {"coordinates":[-71.2597,42.361667],"type":"Point"}
}