{
  "type": "Feature",
  "properties": {
    "addr:full": "29 Sawyer Rd Waltham MA 02453",
    "addr:housenumber": "29",
    "addr:postcode": "02453",
    "addr:street": "Sawyer Rd",
    "iso:country": "US",
    "sg:address": "29 Sawyer Rd",
    "sg:city": "Waltham",
    "sg:classifiers": [
      {
        "category": "Communications",
        "type": "Services"
      }
    ],
    "sg:phone": "+1 781 736 1200",
    "sg:postcode": "02453",
    "sg:province": "MA",
    "wof:name": "Starbak Communications",
    "wof:placetype": "venue"
  },
  "geometry": {"coordinates":[-71.2597,42.361667],"type":"Point"}
}
