{
  "type": "Feature",
  "properties": {
    "addr:full":"868 S Franklin St Holbrook MA 02343",
    "addr:housenumber":"868",
    "addr:postcode":"02343",
    "addr:street":"S Franklin St",
    "iso:country":"US",
    "sg:address":"868 S Franklin St",
    "sg:city":"Holbrook",
    "sg:classifiers":[
        {
            "category":"Personal",
            "subcategory":"Beauty Salon",
            "type":"Services"
        }
    ],
    "sg:phone":"+1 781 767 5454",
    "sg:postcode":"02343",
    "sg:province":"MA",
    "wof:name":"Signature Cuts",
    "wof:placetype":"venue"
},
  "geometry": {"coordinates":[-71.010555,42.126881],"type":"Point"}
}