{
  "type": "Feature",
  "properties": {
    "iso:country":"US",
    "sg:address":"8 Woodfin Ter",
    "sg:city":"Marblehead",
    "sg:classifiers":[
        {
            "category":"Retail",
            "subcategory":"Auto Repair",
            "type":"Services"
        }
    ],
    "sg:phone":"+1 781 476 5319",
    "sg:postcode":"01945",
    "sg:province":"MA",
    "sg:tags":[
        "body",
        "repairing",
        "automobile",
        "dent",
        "removal",
        "painting"
    ],
    "sg:website":"http://www.stingraycollision.com",
    "wof:name":"The Stingray Collision Center, Inc.",
    "wof:placetype":"venue"
},
  "geometry": {"coordinates":[-70.858313,42.513946],"type":"Point"}
}