{
  "type": "Feature",
  "properties": {
    "iso:country":"US",
    "sg:address":"11 Turnpike Rd",
    "sg:city":"Southborough",
    "sg:classifiers":[
        {
            "category":"Retail",
            "subcategory":"Auto Repair",
            "type":"Services"
        }
    ],
    "sg:phone":"+1 508 303 6699",
    "sg:postcode":"01772",
    "sg:province":"MA",
    "sg:tags":[
        "wrecker"
    ],
    "wof:name":"Statewide Towing Assn",
    "wof:placetype":"venue"
},
  "geometry": {"coordinates":[-71.49562299999999,42.296541],"type":"Point"}
}