{
  "type": "Feature",
  "properties": {
    "addr:full":"184 High St Boston MA 02110",
    "addr:housenumber":"184",
    "addr:postcode":"02110",
    "addr:street":"High St",
    "iso:country":"US",
    "sg:address":"184 High St",
    "sg:city":"Boston",
    "sg:classifiers":[
        {
            "category":"Retail",
            "subcategory":"Repair Shop",
            "type":"Services"
        }
    ],
    "sg:phone":"+1 617 208 1104",
    "sg:postcode":"02110",
    "sg:province":"MA",
    "sg:tags":[
        "lock",
        "locksmith"
    ],
    "wof:name":"24 All Day Emergency Locksmith",
    "wof:placetype":"venue"
},
  "geometry": {"coordinates":[-71.052468,42.356572],"type":"Point"}
}