{
  "type": "Feature",
  "properties": {
    "addr:full": "145 W River St Upton MA 01568",
    "addr:housenumber": "145",
    "addr:postcode": "01568",
    "addr:street": "W River St",
    "iso:country": "US",
    "sg:address": "145 W River St",
    "sg:city": "Upton",
    "sg:classifiers": [
      {
        "category": "Retail",
        "subcategory": "Animal Services",
        "type": "Services"
      }
    ],
    "sg:phone": "+1 508 529 3095",
    "sg:postcode": "01568",
    "sg:province": "MA",
    "sg:tags": [
      "pet",
      "boarding",
      "sitting"
    ],
    "wof:name": "Kobblestone Kennels",
    "wof:placetype": "venue"
  },
  "geometry": {"coordinates":[-71.617055,42.14257],"type":"Point"}
}
