{
  "type": "Feature",
  "properties": {
    "iso:country":"US",
    "sg:address":"145 W River St",
    "sg:city":"Upton",
    "sg:classifiers":[
        {
            "category":"Retail",
            "subcategory":"Animal Services",
            "type":"Services"
        }
    ],
    "sg:phone":"+1 508 529 3095",
    "sg:postcode":"01568",
    "sg:province":"MA",
    "sg:tags":[
        "pet",
        "boarding",
        "sitting"
    ],
    "wof:name":"Kobblestone Kennels",
    "wof:placetype":"venue"
},
  "geometry": {"coordinates":[-71.61705499999999,42.14257],"type":"Point"}
}