{
  "type": "Feature",
  "properties": {
    "addr:full":"52 Boylston Street Brookline MA 02445",
    "addr:housenumber":"52",
    "addr:postcode":"02445",
    "addr:street":"Boylston Street",
    "iso:country":"US",
    "sg:address":"52 Boylston Street",
    "sg:city":"Brookline",
    "sg:classifiers":[
        {
            "category":"Personal",
            "subcategory":"Nail Salon",
            "type":"Services"
        }
    ],
    "sg:phone":"+1 617 734 6693",
    "sg:postcode":"02445",
    "sg:province":"MA",
    "wof:name":"Brookline Nail Design",
    "wof:placetype":"venue"
},
  "geometry": {"coordinates":[-71.11852399999999,42.331507],"type":"Point"}
}