{
  "type": "Feature",
  "properties": {
    "iso:country":"US",
    "sg:address":"94 Meadow Vw",
    "sg:city":"Wellfleet",
    "sg:classifiers":[
        {
            "category":"Education",
            "subcategory":"Vocational School",
            "type":"Public Place"
        }
    ],
    "sg:phone":"+1 508 349 1975",
    "sg:postcode":"02667",
    "sg:province":"MA",
    "sg:tags":[
        "training",
        "computer"
    ],
    "wof:name":"Computer Wise",
    "wof:placetype":"venue"
},
  "geometry": {"coordinates":[-70.033221,41.956264],"type":"Point"}
}