{
  "type": "Feature",
  "properties": {
    "addr:full": "876 E Falmouth Hwy East Falmouth MA 02536",
    "addr:housenumber": "876",
    "addr:postcode": "02536",
    "addr:street": "E Falmouth Hwy",
    "iso:country": "US",
    "sg:address": "876 E Falmouth Hwy",
    "sg:city": "East Falmouth",
    "sg:classifiers": [
      {
        "category": "Wholesale",
        "subcategory": "Seafood",
        "type": "Manufacturing \u0026 Wholesale Goods"
      }
    ],
    "sg:phone": "+1 508 540 4699",
    "sg:postcode": "02536",
    "sg:province": "MA",
    "wof:name": "Captain Leo's",
    "wof:placetype": "venue"
  },
  "geometry": {"coordinates":[-70.543737,41.578641],"type":"Point"}
}
