{
  "type": "Feature",
  "properties": {
    "iso:country":"US",
    "sg:address":"876 E Falmouth Hwy",
    "sg:city":"East Falmouth",
    "sg:classifiers":[
        {
            "category":"Wholesale",
            "subcategory":"Seafood",
            "type":"Manufacturing & Wholesale Goods"
        }
    ],
    "sg:phone":"+1 508 540 4699",
    "sg:postcode":"02536",
    "sg:province":"MA",
    "wof:name":"Captain Leo's",
    "wof:placetype":"venue"
},
  "geometry": {"coordinates":[-70.54373699999999,41.578641],"type":"Point"}
}