{
  "type": "Feature",
  "properties": {
    "addr:full":"41 Walnut Park Roxbury MA 02119",
    "addr:housenumber":"41",
    "addr:postcode":"02119",
    "addr:street":"Walnut Park",
    "iso:country":"US",
    "sg:address":"41 Walnut Park",
    "sg:city":"Roxbury",
    "sg:classifiers":[
        {
            "category":"Building & Trades",
            "subcategory":"Construction",
            "type":"Services"
        }
    ],
    "sg:phone":"+1 617 442 6378",
    "sg:postcode":"02119",
    "sg:province":"MA",
    "sg:tags":[
        "carpenter"
    ],
    "wof:name":"Handy Hands Co",
    "wof:placetype":"venue"
},
  "geometry": {"coordinates":[-71.095624,42.315114],"type":"Point"}
}