{
  "type": "Feature",
  "properties": {
    "addr:full":"27 Jefferson St Taunton MA 02780",
    "addr:housenumber":"27",
    "addr:postcode":"02780",
    "addr:street":"Jefferson St",
    "iso:country":"US",
    "sg:address":"27 Jefferson St",
    "sg:city":"Taunton",
    "sg:classifiers":[
        {
            "category":"Real Estate",
            "subcategory":"Surveying",
            "type":"Services"
        }
    ],
    "sg:phone":"+1 508 824 6609",
    "sg:postcode":"02780",
    "sg:province":"MA",
    "sg:tags":[
        "surveyor"
    ],
    "wof:name":"John W De Lano & Assoc",
    "wof:placetype":"venue"
},
  "geometry": {"coordinates":[-71.091871,41.916758],"type":"Point"}
}