{
  "type": "Feature",
  "properties": {
    "iso:country":"US",
    "sg:address":"194 Congress Ave",
    "sg:city":"Chelsea",
    "sg:classifiers":[
        {
            "category":"Building & Trades",
            "subcategory":"Locksmith",
            "type":"Services"
        }
    ],
    "sg:phone":"+1 617 819 3276",
    "sg:postcode":"02150",
    "sg:province":"MA",
    "sg:tags":[
        "key"
    ],
    "wof:name":"Locksmith ABC 24 A Day Emergency",
    "wof:placetype":"venue"
},
  "geometry": {"coordinates":[-71.031142,42.387996],"type":"Point"}
}