{
  "type": "Feature",
  "properties": {
    "addr:full":"99 Church St Northbridge MA 01570",
    "addr:housenumber":"99",
    "addr:postcode":"01570",
    "addr:street":"Church St",
    "iso:country":"US",
    "sg:address":"99 Church St",
    "sg:city":"Northbridge",
    "sg:classifiers":[
        {
            "category":"Shopping",
            "subcategory":"Computers & Home Electronics",
            "type":"Retail Goods"
        }
    ],
    "sg:phone":"+1 508 234 9499",
    "sg:postcode":"01570",
    "sg:province":"MA",
    "sg:tags":[
        "equipment",
        "dealer"
    ],
    "wof:name":"Business Service Group",
    "wof:placetype":"venue"
},
  "geometry": {"coordinates":[-71.881367,42.049596],"type":"Point"}
}