{
  "type": "Feature",
  "properties": {
    "iso:country":"US",
    "sg:address":"215 Columbia St",
    "sg:city":"Fall River",
    "sg:classifiers":[
        {
            "category":"Retail",
            "subcategory":"Funeral Services",
            "type":"Services"
        }
    ],
    "sg:phone":"+1 508 672 4768",
    "sg:postcode":"02721",
    "sg:province":"MA",
    "sg:tags":[
        "director"
    ],
    "sg:website":"www.oliveirafuneralhomes.com",
    "wof:name":"Oliveira Funeral Homes",
    "wof:placetype":"venue"
},
  "geometry": {"coordinates":[-71.16364799999999,41.69915],"type":"Point"}
}