{
  "type": "Feature",
  "properties": {
    "addr:full": "215 Columbia St Fall River MA 02721",
    "addr:housenumber": "215",
    "addr:postcode": "02721",
    "addr:street": "Columbia St",
    "iso:country": "US",
    "sg:address": "215 Columbia St",
    "sg:city": "Fall River",
    "sg:classifiers": [
      {
        "category": "Retail",
        "subcategory": "Funeral Services",
        "type": "Services"
      }
    ],
    "sg:phone": "+1 508 672 4768",
    "sg:postcode": "02721",
    "sg:province": "MA",
    "sg:tags": [
      "director"
    ],
    "sg:website": "www.oliveirafuneralhomes.com",
    "wof:name": "Oliveira Funeral Homes",
    "wof:placetype": "venue"
  },
  "geometry": {"coordinates":[-71.163648,41.69915],"type":"Point"}
}
