{
  "type": "Feature",
  "properties": {
    "addr:full":"8 Fairway Dr Bellingham MA 02019",
    "addr:housenumber":"8",
    "addr:postcode":"02019",
    "addr:street":"Fairway Dr",
    "iso:country":"US",
    "sg:address":"8 Fairway Dr",
    "sg:city":"Bellingham",
    "sg:classifiers":[
        {
            "category":"Recreation",
            "type":"Entertainment"
        }
    ],
    "sg:phone":"+1   ",
    "sg:postcode":"02019",
    "sg:province":"MA",
    "wof:name":"Busy Line Charters Inc",
    "wof:placetype":"venue"
},
  "geometry": {"coordinates":[-71.487189,42.018685],"type":"Point"}
}