{
  "type": "Feature",
  "properties": {
    "addr:full":"79 Rindone St Holbrook MA 02343",
    "addr:housenumber":"79",
    "addr:postcode":"02343",
    "addr:street":"Rindone St",
    "iso:country":"US",
    "sg:address":"79 Rindone St",
    "sg:city":"Holbrook",
    "sg:classifiers":[
        {
            "category":"Social Services",
            "subcategory":"Child Care",
            "type":"Services"
        }
    ],
    "sg:phone":"+1   ",
    "sg:postcode":"02343",
    "sg:province":"MA",
    "sg:tags":[
        "day"
    ],
    "wof:name":"Mary Sica Country Day Care Ctr",
    "wof:placetype":"venue"
},
  "geometry": {"coordinates":[-71.002011,42.140431],"type":"Point"}
}