{
  "type": "Feature",
  "properties": {
    "addr:full": "776 Washington St Dorchester MA 02124",
    "addr:housenumber": "776",
    "addr:postcode": "02124",
    "addr:street": "Washington St",
    "iso:country": "US",
    "sg:address": "776 Washington St",
    "sg:city": "Dorchester",
    "sg:classifiers": [
      {
        "category": "Social Services",
        "subcategory": "Child Care",
        "type": "Services"
      },
      {
        "category": "Recreation",
        "subcategory": "Water Park",
        "type": "Entertainment"
      },
      {
        "category": "Sports \u0026 Exercise",
        "subcategory": "Gym",
        "type": "Entertainment"
      },
      {
        "category": "Education",
        "subcategory": "Preschool",
        "type": "Public Place"
      },
      {
        "category": "Sports \u0026 Exercise",
        "subcategory": "Swimming Pool",
        "type": "Entertainment"
      }
    ],
    "sg:phone": "+1 617 436 7750",
    "sg:postcode": "02124",
    "sg:province": "MA",
    "sg:tags": [
      "trainer",
      "beach",
      "day"
    ],
    "sg:website": "www.ymcaboston.org",
    "wof:name": "Dorchester Family YMCA",
    "wof:placetype": "venue"
  },
  "geometry": {"coordinates":[-71.071582,42.284232],"type":"Point"}
}
