{
  "type": "Feature",
  "properties": {
    "addr:full":"21 Cummings Park Woburn MA 01801",
    "addr:housenumber":"21",
    "addr:postcode":"01801",
    "addr:street":"Cummings Park",
    "iso:country":"US",
    "sg:address":"21 Cummings Park",
    "sg:city":"Woburn",
    "sg:classifiers":[
        {
            "category":"Health Services",
            "subcategory":"Doctor",
            "type":"Services"
        }
    ],
    "sg:phone":"+1 781 935 7555",
    "sg:postcode":"01801",
    "sg:province":"MA",
    "sg:tags":[
        "physician",
        "surgeon"
    ],
    "wof:name":"Richard D Siegel MD",
    "wof:placetype":"venue"
},
  "geometry": {"coordinates":[-71.124398,42.49744],"type":"Point"}
}