{
  "type": "Feature",
  "properties": {
    "addr:full":"10 Corey St Melrose MA 02176",
    "addr:housenumber":"10",
    "addr:postcode":"02176",
    "addr:street":"Corey St",
    "iso:country":"US",
    "sg:address":"10 Corey St",
    "sg:city":"Melrose",
    "sg:classifiers":[
        {
            "category":"Shopping",
            "subcategory":"Florist",
            "type":"Retail Goods"
        }
    ],
    "sg:phone":"+1 781 391 8700",
    "sg:postcode":"02176",
    "sg:province":"MA",
    "wof:name":"Solomon Jeri",
    "wof:placetype":"venue"
},
  "geometry": {"coordinates":[-71.06813699999999,42.451828],"type":"Point"}
}