{
  "type": "Feature",
  "properties": {
    "addr:full": "1164 Worcester Rd Framingham MA 01702",
    "addr:housenumber": "1164",
    "addr:postcode": "01702",
    "addr:street": "Worcester Rd",
    "iso:country": "US",
    "sg:address": "1164 Worcester Rd",
    "sg:city": "Framingham",
    "sg:classifiers": [
      {
        "category": "Shopping",
        "type": "Retail Goods"
      }
    ],
    "sg:phone": "+1 508 820 8899",
    "sg:postcode": "01702",
    "sg:province": "MA",
    "sg:tags": [
      "picture",
      "frame"
    ],
    "wof:name": "Frame Center",
    "wof:placetype": "venue"
  },
  "geometry": {"coordinates":[-71.444761,42.298843],"type":"Point"}
}
