{
  "type": "Feature",
  "properties": {
    "iso:country":"US",
    "sg:address":"5 Victoria Cir",
    "sg:city":"Sharon",
    "sg:classifiers":[
        {
            "category":"Real Estate",
            "subcategory":"Real Estate Agent",
            "type":"Services"
        }
    ],
    "sg:phone":"+1 781 793 0393",
    "sg:postcode":"02067",
    "sg:province":"MA",
    "wof:name":"Victoria Realty Corp",
    "wof:placetype":"venue"
},
  "geometry": {"coordinates":[-71.175239,42.072599],"type":"Point"}
}