{
  "type": "Feature",
  "properties": {
    "iso:country":"US",
    "sg:address":"386 Langley Rd",
    "sg:city":"Newton",
    "sg:classifiers":[
        {
            "category":"Shopping",
            "subcategory":"Discount & Variety Stores",
            "type":"Retail Goods"
        }
    ],
    "sg:phone":"+1 617 964 1445",
    "sg:postcode":"02459",
    "sg:province":"MA",
    "wof:name":"Langley Variety",
    "wof:placetype":"venue"
},
  "geometry": {"coordinates":[-71.18332700000001,42.319782],"type":"Point"}
}