{
  "type": "Feature",
  "properties": {
    "addr:full": "386 Langley Rd Newton MA 02459",
    "addr:housenumber": "386",
    "addr:postcode": "02459",
    "addr:street": "Langley Rd",
    "iso:country": "US",
    "sg:address": "386 Langley Rd",
    "sg:city": "Newton",
    "sg:classifiers": [
      {
        "category": "Shopping",
        "subcategory": "Discount \u0026 Variety Stores",
        "type": "Retail Goods"
      }
    ],
    "sg:phone": "+1 617 964 1445",
    "sg:postcode": "02459",
    "sg:province": "MA",
    "wof:name": "Langley Variety",
    "wof:placetype": "venue"
  },
  "geometry": {"coordinates":[-71.183327,42.319782],"type":"Point"}
}
