{
  "type": "Feature",
  "properties": {
    "addr:full": "33 Rainbow Dr Centerville MA 02632",
    "addr:housenumber": "33",
    "addr:postcode": "02632",
    "addr:street": "Rainbow Dr",
    "iso:country": "US",
    "sg:address": "33 Rainbow Dr",
    "sg:city": "Centerville",
    "sg:classifiers": [
      {
        "category": "Professional",
        "subcategory": "Accounting \u0026 Tax Preparation",
        "type": "Services"
      }
    ],
    "sg:phone": "+1   ",
    "sg:postcode": "02632",
    "sg:province": "MA",
    "wof:name": "Peck Marketing Services Inc",
    "wof:placetype": "venue"
  },
  "geometry": {"coordinates":[-70.35953,41.65053],"type":"Point"}
}
