{
  "type": "Feature",
  "properties": {
    "addr:full": "1401 Highland Ave Needham MA 02492",
    "addr:housenumber": "1401",
    "addr:postcode": "02492",
    "addr:street": "Highland Ave",
    "iso:country": "US",
    "sg:address": "1401 Highland Ave",
    "sg:city": "Needham",
    "sg:classifiers": [
      {
        "category": "Autos \u0026 Motor Vehicles",
        "subcategory": "Fuel \u0026 Gas Station",
        "type": "Retail Goods"
      }
    ],
    "sg:phone": "+1 781 444 5100",
    "sg:postcode": "02492",
    "sg:province": "MA",
    "sg:tags": [
      "oil"
    ],
    "wof:name": "Needham Service Ctr",
    "wof:placetype": "venue"
  },
  "geometry": {"coordinates":[-71.236096,42.281712],"type":"Point"}
}
