{
  "type": "Feature",
  "properties": {
    "iso:country":"US",
    "sg:address":"17 Tudor St",
    "sg:city":"Cambridge",
    "sg:classifiers":[
        {
            "category":"Wholesale",
            "subcategory":"Electrical",
            "type":"Manufacturing & Wholesale Goods"
        }
    ],
    "sg:phone":"+1 617 497 4163",
    "sg:postcode":"02139",
    "sg:province":"MA",
    "sg:tags":[
        "recording",
        "studio"
    ],
    "wof:name":"Tudor Studios",
    "wof:placetype":"venue"
},
  "geometry": {"coordinates":[-71.10438499999999,42.360501],"type":"Point"}
}