{
  "type": "Feature",
  "properties": {
    "addr:full":"239 Commercial Street Malden MA 02148",
    "addr:housenumber":"239",
    "addr:postcode":"02148",
    "addr:street":"Commercial Street",
    "iso:country":"US",
    "sg:address":"239 Commercial Street",
    "sg:city":"Malden",
    "sg:classifiers":[
        {
            "category":"Sports & Exercise",
            "subcategory":"Gym",
            "type":"Entertainment"
        }
    ],
    "sg:phone":"+1 781 388 3330",
    "sg:postcode":"02148",
    "sg:province":"MA",
    "sg:tags":[
        "trainer"
    ],
    "sg:website":"www.curves.com",
    "wof:name":"Curves For Women",
    "wof:placetype":"venue"
},
  "geometry": {"coordinates":[-71.07543800000001,42.420242],"type":"Point"}
}