{
  "type": "Feature",
  "properties": {
    "iso:country":"US",
    "sg:address":"178 Bradford St",
    "sg:city":"Provincetown",
    "sg:classifiers":[
        {
            "category":"Travel",
            "subcategory":"Hotels & Motels",
            "type":"Entertainment"
        }
    ],
    "sg:phone":"+1 508 487 1616",
    "sg:postcode":"02657",
    "sg:province":"MA",
    "sg:tags":[
        "breakfast",
        "accommodation",
        "bed"
    ],
    "sg:website":"www.snugcottage.com",
    "wof:name":"Snug Cottage",
    "wof:placetype":"venue"
},
  "geometry": {"coordinates":[-70.18145699999999,42.056284],"type":"Point"}
}