{
  "type": "Feature",
  "properties": {
    "addr:full": "178 Bradford St Provincetown MA 02657",
    "addr:housenumber": "178",
    "addr:postcode": "02657",
    "addr:street": "Bradford St",
    "iso:country": "US",
    "ovtr:label": "Snug Cottage, 178 Bradford St Provincetown MA US",
    "ovtr:similarity": 2.133162021636963,
    "sg:address": "178 Bradford St",
    "sg:city": "Provincetown",
    "sg:classifiers": [
      {
        "category": "Travel",
        "subcategory": "Hotels \u0026 Motels",
        "type": "Entertainment"
      }
    ],
    "sg:phone": "+1 508 487 1616",
    "sg:postcode": "02657",
    "sg:province": "MA",
    "sg:tags": [
      "breakfast",
      "accommodation",
      "bed"
    ],
    "sg:website": "www.snugcottage.com",
    "wof:name": "Snug Cottage",
    "wof:placetype": "venue"
  },
  "geometry": {"coordinates":[-70.181457,42.056284],"type":"Point"}
}
