{
  "type": "Feature",
  "properties": {
    "iso:country":"US",
    "sg:address":"272 Bridge St",
    "sg:city":"North Weymouth",
    "sg:classifiers":[
        {
            "category":"Retail",
            "subcategory":"Repair Shop",
            "type":"Services"
        }
    ],
    "sg:phone":"+1 781 337 3942",
    "sg:postcode":"02191",
    "sg:province":"MA",
    "sg:tags":[
        "scooter",
        "motorcycle",
        "motor"
    ],
    "wof:name":"New England V-Twin Inc",
    "wof:placetype":"venue"
},
  "geometry": {"coordinates":[-70.95421899999999,42.24276],"type":"Point"}
}