{
  "type": "Feature",
  "properties": {
    "addr:full": "272 Bridge St North Weymouth MA 02191",
    "addr:housenumber": "272",
    "addr:postcode": "02191",
    "addr:street": "Bridge St",
    "iso:country": "US",
    "sg:address": "272 Bridge St",
    "sg:city": "North Weymouth",
    "sg:classifiers": [
      {
        "category": "Retail",
        "subcategory": "Repair Shop",
        "type": "Services"
      }
    ],
    "sg:phone": "+1 781 337 3942",
    "sg:postcode": "02191",
    "sg:province": "MA",
    "sg:tags": [
      "scooter",
      "motorcycle",
      "motor"
    ],
    "wof:name": "New England V-Twin Inc",
    "wof:placetype": "venue"
  },
  "geometry": {"coordinates":[-70.954219,42.24276],"type":"Point"}
}
