{
  "type": "Feature",
  "properties": {
    "addr:full":"1441 North St Walpole MA 02081",
    "addr:housenumber":"1441",
    "addr:postcode":"02081",
    "addr:street":"North St",
    "iso:country":"US",
    "sg:address":"1441 North St",
    "sg:city":"Walpole",
    "sg:classifiers":[
        {
            "category":"Building & Trades",
            "subcategory":"Construction",
            "type":"Services"
        }
    ],
    "sg:phone":"+1 508 668 2425",
    "sg:postcode":"02081",
    "sg:province":"MA",
    "sg:tags":[
        "general",
        "contractor"
    ],
    "wof:name":"Steven G Murray Contracting",
    "wof:placetype":"venue"
},
  "geometry": {"coordinates":[-71.249489,42.20106],"type":"Point"}
}