{
  "type": "Feature",
  "properties": {
    "iso:country":"US",
    "sg:address":"1 River St",
    "sg:city":"Norwell",
    "sg:classifiers":[
        {
            "category":"Banks & Credit Unions",
            "subcategory":"Bank",
            "type":"Services"
        }
    ],
    "sg:phone":"+1 781 659 0088",
    "sg:postcode":"02061",
    "sg:province":"MA",
    "sg:tags":[
        "federal",
        "savings",
        "institution"
    ],
    "wof:name":"Scituate Federal Savings Bank",
    "wof:placetype":"venue"
},
  "geometry": {"coordinates":[-70.793279,42.160692],"type":"Point"}
}