{
  "type": "Feature",
  "properties": {
    "addr:full":"1655 Beacon St Brookline MA 02445",
    "addr:housenumber":"1655",
    "addr:postcode":"02445",
    "addr:street":"Beacon St",
    "iso:country":"US",
    "sg:address":"1655 Beacon St",
    "sg:city":"Brookline",
    "sg:classifiers":[
        {
            "category":"Building & Trades",
            "subcategory":"Locksmith",
            "type":"Services"
        }
    ],
    "sg:phone":"+1 617 517 9056",
    "sg:postcode":"02445",
    "sg:province":"MA",
    "sg:tags":[
        "key"
    ],
    "wof:name":"Emergency A Locksmith",
    "wof:placetype":"venue"
},
  "geometry": {"coordinates":[-71.136731,42.338721],"type":"Point"}
}