{
  "type": "Feature",
  "properties": {
    "iso:country":"US",
    "sg:address":"2 Golen Dr",
    "sg:city":"North Dartmouth",
    "sg:classifiers":[
        {
            "category":"Manufacturing",
            "subcategory":"Printing",
            "type":"Manufacturing & Wholesale Goods"
        }
    ],
    "sg:phone":"+1 508 991 4540",
    "sg:postcode":"02747",
    "sg:province":"MA",
    "sg:tags":[
        "label"
    ],
    "wof:name":"Advantage Label",
    "wof:placetype":"venue"
},
  "geometry": {"coordinates":[-71.00006999999999,41.608098],"type":"Point"}
}