{
  "type": "Feature",
  "properties": {
    "addr:full": "11 Walpole St Norwood MA 02062",
    "addr:housenumber": "11",
    "addr:postcode": "02062",
    "addr:street": "Walpole St",
    "iso:country": "US",
    "sg:address": "11 Walpole St",
    "sg:city": "Norwood",
    "sg:classifiers": [
      {
        "category": "Wholesale",
        "subcategory": "Electrical",
        "type": "Manufacturing \u0026 Wholesale Goods"
      }
    ],
    "sg:phone": "+1 617 623 8200",
    "sg:postcode": "02062",
    "sg:province": "MA",
    "sg:tags": [
      "light",
      "tube",
      "bulb"
    ],
    "wof:name": "Peerless",
    "wof:placetype": "venue"
  },
  "geometry": {"coordinates":[-71.203123,42.191407],"type":"Point"}
}
