{
  "type": "Feature",
  "properties": {
    "iso:country":"US",
    "sg:address":"11 Walpole St",
    "sg:city":"Norwood",
    "sg:classifiers":[
        {
            "category":"Wholesale",
            "subcategory":"Electrical",
            "type":"Manufacturing & Wholesale Goods"
        }
    ],
    "sg:phone":"+1 617 623 8200",
    "sg:postcode":"02062",
    "sg:province":"MA",
    "sg:tags":[
        "light",
        "tube",
        "bulb"
    ],
    "wof:name":"Peerless",
    "wof:placetype":"venue"
},
  "geometry": {"coordinates":[-71.20312300000001,42.191407],"type":"Point"}
}