{
  "type": "Feature",
  "properties": {
    "addr:full": "11 Austin Rd Sudbury MA 01776",
    "addr:housenumber": "11",
    "addr:postcode": "01776",
    "addr:street": "Austin Rd",
    "iso:country": "US",
    "sg:address": "11 Austin Rd",
    "sg:city": "Sudbury",
    "sg:classifiers": [
      {
        "category": "Professional",
        "subcategory": "Computer Services",
        "type": "Services"
      }
    ],
    "sg:phone": "+1   ",
    "sg:postcode": "01776",
    "sg:province": "MA",
    "sg:tags": [
      "related"
    ],
    "wof:name": "Lavari Consulting",
    "wof:placetype": "venue"
  },
  "geometry": {"coordinates":[-71.450708,42.378487],"type":"Point"}
}
