{
  "type": "Feature",
  "properties": {
    "iso:country":"US",
    "sg:address":"11 Austin Rd",
    "sg:city":"Sudbury",
    "sg:classifiers":[
        {
            "category":"Professional",
            "subcategory":"Computer Services",
            "type":"Services"
        }
    ],
    "sg:phone":"+1   ",
    "sg:postcode":"01776",
    "sg:province":"MA",
    "sg:tags":[
        "related"
    ],
    "wof:name":"Lavari Consulting",
    "wof:placetype":"venue"
},
  "geometry": {"coordinates":[-71.45070800000001,42.378487],"type":"Point"}
}