{
  "type": "Feature",
  "properties": {
    "addr:full":"248 Main St Reading MA 01867",
    "addr:housenumber":"248",
    "addr:postcode":"01867",
    "addr:street":"Main St",
    "iso:country":"US",
    "sg:address":"248 Main St",
    "sg:city":"Reading",
    "sg:classifiers":[
        {
            "category":"Real Estate",
            "subcategory":"Real Estate Agent",
            "type":"Services"
        }
    ],
    "sg:phone":"+1 781 944 6060",
    "sg:postcode":"01867",
    "sg:province":"MA",
    "wof:name":"Lynne Scouten",
    "wof:placetype":"venue"
},
  "geometry": {"coordinates":[-71.103837,42.513608],"type":"Point"}
}