{
  "type": "Feature",
  "properties": {
    "iso:country":"US",
    "sg:address":"17 Waters Rd",
    "sg:city":"Sutton",
    "sg:classifiers":[
        {
            "category":"Professional",
            "subcategory":"Business Services",
            "type":"Services"
        }
    ],
    "sg:phone":"+1   ",
    "sg:postcode":"01590",
    "sg:province":"MA",
    "wof:name":"SCR Enterprises Inc",
    "wof:placetype":"venue"
},
  "geometry": {"coordinates":[-71.79261200000001,42.108685],"type":"Point"}
}