{
  "type": "Feature",
  "properties": {
    "iso:country":"US",
    "sg:address":"16 Winter St",
    "sg:city":"Taunton",
    "sg:classifiers":[
        {
            "category":"Shopping",
            "type":"Retail Goods"
        }
    ],
    "sg:phone":"+1 508 822 4944",
    "sg:postcode":"02780",
    "sg:province":"MA",
    "sg:tags":[
        "awning",
        "canopy"
    ],
    "wof:name":"D A Costa Awning Co",
    "wof:placetype":"venue"
},
  "geometry": {"coordinates":[-71.088329,41.916845],"type":"Point"}
}