{
  "type": "Feature",
  "properties": {
    "iso:country":"US",
    "sg:address":"52 Kennebec St",
    "sg:city":"Oak Bluffs",
    "sg:classifiers":[
        {
            "category":"Shopping",
            "subcategory":"Used Merchandise",
            "type":"Retail Goods"
        }
    ],
    "sg:phone":"+1 508 693 9313",
    "sg:postcode":"02557",
    "sg:province":"MA",
    "sg:tags":[
        "antique"
    ],
    "wof:name":"Never Say Goodbye Inc",
    "wof:placetype":"venue"
},
  "geometry": {"coordinates":[-70.55803299999999,41.454955],"type":"Point"}
}