{
  "type": "Feature",
  "properties": {
    "iso:country":"US",
    "sg:address":"50 Worcester Rd",
    "sg:city":"Framingham",
    "sg:classifiers":[
        {
            "category":"Shopping",
            "subcategory":"Music",
            "type":"Retail Goods"
        }
    ],
    "sg:phone":"+1 508 879 7310",
    "sg:postcode":"01702",
    "sg:province":"MA",
    "sg:tags":[
        "compact",
        "record",
        "disc",
        "tape"
    ],
    "wof:name":"Strawberries",
    "wof:placetype":"venue"
},
  "geometry": {"coordinates":[-71.398112,42.298655],"type":"Point"}
}