{
  "type": "Feature",
  "properties": {
    "addr:full": "50 Worcester Rd Framingham MA 01702",
    "addr:housenumber": "50",
    "addr:postcode": "01702",
    "addr:street": "Worcester Rd",
    "iso:country": "US",
    "sg:address": "50 Worcester Rd",
    "sg:city": "Framingham",
    "sg:classifiers": [
      {
        "category": "Shopping",
        "subcategory": "Music",
        "type": "Retail Goods"
      }
    ],
    "sg:phone": "+1 508 879 7310",
    "sg:postcode": "01702",
    "sg:province": "MA",
    "sg:tags": [
      "compact",
      "record",
      "disc",
      "tape"
    ],
    "wof:name": "Strawberries",
    "wof:placetype": "venue"
  },
  "geometry": {"coordinates":[-71.398112,42.298655],"type":"Point"}
}
