{
  "type": "Feature",
  "properties": {
    "addr:full":"201 Forest St Saugus MA 01906",
    "addr:housenumber":"201",
    "addr:postcode":"01906",
    "addr:street":"Forest St",
    "iso:country":"US",
    "sg:address":"201 Forest St",
    "sg:city":"Saugus",
    "sg:classifiers":[
        {
            "category":"Shopping",
            "subcategory":"Bicycles & Sporting Goods",
            "type":"Retail Goods"
        }
    ],
    "sg:phone":"+1 781 231 7079",
    "sg:postcode":"01906",
    "sg:province":"MA",
    "sg:tags":[
        "equipment",
        "hockey"
    ],
    "wof:name":"Tropeano's Hockey Shop",
    "wof:placetype":"venue"
},
  "geometry": {"coordinates":[-71.027625,42.483502],"type":"Point"}
}