{
  "type": "Feature",
  "properties": {
    "addr:full": "271 Great Rd Acton MA 01720",
    "addr:housenumber": "271",
    "addr:postcode": "01720",
    "addr:street": "Great Rd",
    "iso:country": "US",
    "sg:address": "271 Great Rd",
    "sg:city": "Acton",
    "sg:classifiers": [
      {
        "category": "Wholesale",
        "subcategory": "Durable Goods \u0026 Equipment",
        "type": "Manufacturing \u0026 Wholesale Goods"
      }
    ],
    "sg:phone": "+1 978 264 3999",
    "sg:postcode": "01720",
    "sg:province": "MA",
    "sg:tags": [
      "representative",
      "manufacturer"
    ],
    "wof:name": "TR2 Corp",
    "wof:placetype": "venue"
  },
  "geometry": {"coordinates":[-71.416367,42.494405],"type":"Point"}
}
