{
  "type": "Feature",
  "properties": {
    "addr:full":"6 Simpson Rd Marlborough MA 01752",
    "addr:housenumber":"6",
    "addr:postcode":"01752",
    "addr:street":"Simpson Rd",
    "iso:country":"US",
    "sg:address":"6 Simpson Rd",
    "sg:city":"Marlborough",
    "sg:classifiers":[
        {
            "category":"Professional",
            "subcategory":"Accounting & Tax Preparation",
            "type":"Services"
        }
    ],
    "sg:phone":"+1 508 485 3811",
    "sg:postcode":"01752",
    "sg:province":"MA",
    "sg:tags":[
        "accountant"
    ],
    "sg:website":"www.cataldocpa.com",
    "wof:name":"Denise Cataldo CPA",
    "wof:placetype":"venue"
},
  "geometry": {"coordinates":[-71.522875,42.37535],"type":"Point"}
}