{
  "type": "Feature",
  "properties": {
    "addr:full": "809 Boston Rd Springfield MA 01119",
    "addr:housenumber": "809",
    "addr:postcode": "01119",
    "addr:street": "Boston Rd",
    "iso:country": "US",
    "ovtr:label": "McDonald's, 809 Boston Rd Springfield MA US",
    "ovtr:similarity": 3.155724048614502,
    "sg:address": "809 Boston Rd",
    "sg:city": "Springfield",
    "sg:classifiers": [
      {
        "category": "Fast Food",
        "type": "Food \u0026 Drink"
      },
      {
        "category": "Restaurant",
        "type": "Food \u0026 Drink"
      }
    ],
    "sg:phone": "+1 413 783 2328",
    "sg:postcode": "01119",
    "sg:province": "MA",
    "sg:tags": [
      "hamburger",
      "hot",
      "dog",
      "american",
      "take",
      "chicken"
    ],
    "sg:website": "http://www.mcdonalds.com",
    "wof:name": "McDonald's",
    "wof:placetype": "venue"
  },
  "geometry": {"coordinates":[-72.517722,42.13713],"type":"Point"}
}
