{
  "type": "Feature",
  "properties": {
    "addr:full":"2345 Cranberry Hwy West Wareham MA 02576",
    "addr:housenumber":"2345",
    "addr:postcode":"02576",
    "addr:street":"Cranberry Hwy West",
    "iso:country":"US",
    "sg:address":"2345 Cranberry Hwy",
    "sg:city":"West Wareham",
    "sg:classifiers":[
        {
            "category":"Professional",
            "type":"Services"
        }
    ],
    "sg:phone":"+1 508 291 6024",
    "sg:postcode":"02576",
    "sg:province":"MA",
    "sg:tags":[
        "establishment"
    ],
    "wof:name":"Knotty Pine",
    "wof:placetype":"venue"
},
  "geometry": {"coordinates":[-70.751302,41.789241],"type":"Point"}
}