{
  "type": "Feature",
  "properties": {
    "addr:full":"25 Perry Ave Buzzards Bay MA 02532",
    "addr:housenumber":"25",
    "addr:postcode":"02532",
    "addr:street":"Perry Ave",
    "iso:country":"US",
    "sg:address":"25 Perry Ave",
    "sg:city":"Buzzards Bay",
    "sg:classifiers":[
        {
            "category":"Personal",
            "type":"Services"
        },
        {
            "category":"Retail",
            "subcategory":"Auto Repair",
            "type":"Services"
        }
    ],
    "sg:phone":"+1 508 759 1410",
    "sg:postcode":"02532",
    "sg:province":"MA",
    "sg:tags":[
        "towing"
    ],
    "wof:name":"Cubellis 24 Hour Towing - CLOSED",
    "wof:placetype":"venue"
},
  "geometry": {"coordinates":[-70.60230300000001,41.748001],"type":"Point"}
}