{
  "type": "Feature",
  "properties": {
    "iso:country":"US",
    "sg:address":"39 Church Street",
    "sg:city":"Boston",
    "sg:classifiers":[
        {
            "category":"Arts & Performance",
            "subcategory":"Arts Center",
            "type":"Entertainment"
        }
    ],
    "sg:phone":"+1 617 426 2274",
    "sg:postcode":"02116",
    "sg:province":"MA",
    "sg:tags":[
        "performing"
    ],
    "wof:name":"Cinema Booking Service of New England",
    "wof:placetype":"venue"
},
  "geometry": {"coordinates":[-71.06819,42.34908],"type":"Point"}
}