{
  "type": "Feature",
  "properties": {
    "addr:full": "750 Washington St Boston MA 02111",
    "addr:housenumber": "750",
    "addr:postcode": "02111",
    "addr:street": "Washington St",
    "iso:country": "US",
    "sg:address": "750 Washington St",
    "sg:city": "Boston",
    "sg:classifiers": [
      {
        "category": "Health Services",
        "subcategory": "Doctor",
        "type": "Services"
      }
    ],
    "sg:phone": "+1 617 956 5732",
    "sg:postcode": "02111",
    "sg:province": "MA",
    "sg:tags": [
      "practice",
      "family"
    ],
    "wof:name": "Taylor Yvonne S MD",
    "wof:placetype": "venue"
  },
  "geometry": {"coordinates":[-71.0634,42.350201],"type":"Point"}
}
