{
  "type": "Feature",
  "properties": {
    "iso:country":"US",
    "sg:address":"120 Boston Tpke",
    "sg:city":"Shrewsbury",
    "sg:classifiers":[
        {
            "category":"Restaurant",
            "type":"Food & Drink"
        }
    ],
    "sg:menulink":"http://www.allmenus.com/ma/shrewsbury/42506-white-city-pizza/menu/",
    "sg:phone":"+1 508 757 1022",
    "sg:postcode":"01545",
    "sg:province":"MA",
    "sg:tags":[
        "american",
        "pizza"
    ],
    "wof:name":"White City Pizza",
    "wof:placetype":"venue"
},
  "geometry": {"coordinates":[-71.749287,42.27473],"type":"Point"}
}