{
  "type": "Feature",
  "properties": {
    "iso:country":"US",
    "sg:address":"200 E Main St",
    "sg:city":"Milford",
    "sg:classifiers":[
        {
            "category":"Government",
            "subcategory":"Office",
            "type":"Public Place"
        }
    ],
    "sg:phone":"+1 508 634 1877",
    "sg:postcode":"01757",
    "sg:province":"MA",
    "sg:tags":[
        "state",
        "program",
        "health"
    ],
    "wof:name":"Spectrum Health Systems",
    "wof:placetype":"venue"
},
  "geometry": {"coordinates":[-71.500063,42.150915],"type":"Point"}
}