{
  "type": "Feature",
  "properties": {
    "addr:full": "37 Delmont Ave Lowell MA 01852",
    "addr:housenumber": "37",
    "addr:postcode": "01852",
    "addr:street": "Delmont Ave",
    "iso:country": "US",
    "sg:address": "37 Delmont Ave",
    "sg:city": "Lowell",
    "sg:classifiers": [
      {
        "category": "Manufacturing",
        "subcategory": "Retail Goods",
        "type": "Manufacturing \u0026 Wholesale Goods"
      }
    ],
    "sg:phone": "+1 978 459 3061",
    "sg:postcode": "01852",
    "sg:province": "MA",
    "sg:tags": [
      "assembly",
      "fabricating"
    ],
    "wof:name": "Appleton Industries Inc",
    "wof:placetype": "venue"
  },
  "geometry": {"coordinates":[-71.287023,42.615792],"type":"Point"}
}
