{
  "type": "Feature",
  "properties": {
    "addr:full": "95 Commonwealth Ave Concord MA 01742",
    "addr:housenumber": "95",
    "addr:postcode": "01742",
    "addr:street": "Commonwealth Ave",
    "iso:country": "US",
    "sg:address": "95 Commonwealth Ave",
    "sg:city": "Concord",
    "sg:classifiers": [
      {
        "category": "Building \u0026 Trades",
        "subcategory": "Construction",
        "type": "Services"
      }
    ],
    "sg:phone": "+1 978 369 3606",
    "sg:postcode": "01742",
    "sg:province": "MA",
    "sg:tags": [
      "interior",
      "design"
    ],
    "wof:name": "Phillips Fine Paint \u0026 Wallcoverings",
    "wof:placetype": "venue"
  },
  "geometry": {"coordinates":[-71.394897,42.456799],"type":"Point"}
}
