{
  "type": "Feature",
  "properties": {
    "iso:country":"US",
    "sg:address":"95 Commonwealth Ave",
    "sg:city":"Concord",
    "sg:classifiers":[
        {
            "category":"Building & Trades",
            "subcategory":"Construction",
            "type":"Services"
        }
    ],
    "sg:phone":"+1 978 369 3606",
    "sg:postcode":"01742",
    "sg:province":"MA",
    "sg:tags":[
        "interior",
        "design"
    ],
    "wof:name":"Phillips Fine Paint & Wallcoverings",
    "wof:placetype":"venue"
},
  "geometry": {"coordinates":[-71.394897,42.456799],"type":"Point"}
}