{
  "type": "Feature",
  "properties": {
    "addr:full": "1512 Memorial Dr Chicopee MA 01020",
    "addr:housenumber": "1512",
    "addr:postcode": "01020",
    "addr:street": "Memorial Dr",
    "iso:country": "US",
    "ovtr:label": "Cyber Surf Shop, 1512 Memorial Dr Chicopee MA US",
    "ovtr:similarity": 1.6684099435806274,
    "sg:address": "1512 Memorial Dr",
    "sg:city": "Chicopee",
    "sg:classifiers": [
      {
        "category": "Professional",
        "subcategory": "Computer Services",
        "type": "Services"
      }
    ],
    "sg:phone": "+1 413 552 0081",
    "sg:postcode": "01020",
    "sg:province": "MA",
    "sg:tags": [
      "repair"
    ],
    "wof:name": "Cyber Surf Shop",
    "wof:placetype": "venue"
  },
  "geometry": {"coordinates":[-72.573899,42.19779],"type":"Point"}
}
