{
  "type": "Feature",
  "properties": {
    "iso:country":"US",
    "sg:address":"1512 Memorial Dr",
    "sg:city":"Chicopee",
    "sg:classifiers":[
        {
            "category":"Professional",
            "subcategory":"Computer Services",
            "type":"Services"
        }
    ],
    "sg:phone":"+1 413 552 0081",
    "sg:postcode":"01020",
    "sg:province":"MA",
    "sg:tags":[
        "repair"
    ],
    "wof:name":"Cyber Surf Shop",
    "wof:placetype":"venue"
},
  "geometry": {"coordinates":[-72.573899,42.19779],"type":"Point"}
}