{
  "type": "Feature",
  "properties": {
    "addr:full": "10 Doty Ave Danvers MA 01923",
    "addr:housenumber": "10",
    "addr:postcode": "01923",
    "addr:street": "Doty Ave",
    "iso:country": "US",
    "sg:address": "10 Doty Ave",
    "sg:city": "Danvers",
    "sg:classifiers": [
      {
        "category": "Building \u0026 Trades",
        "subcategory": "Construction",
        "type": "Services"
      }
    ],
    "sg:phone": "+1 978 774 6156",
    "sg:postcode": "01923",
    "sg:province": "MA",
    "sg:tags": [
      "general",
      "contractor"
    ],
    "wof:name": "Norden Co Builders",
    "wof:placetype": "venue"
  },
  "geometry": {"coordinates":[-70.914278,42.551269],"type":"Point"}
}
