{
  "type": "Feature",
  "properties": {
    "addr:full":"783 Washington St Holliston MA 01746",
    "addr:housenumber":"783",
    "addr:postcode":"01746",
    "addr:street":"Washington St",
    "iso:country":"US",
    "sg:address":"783 Washington St",
    "sg:city":"Holliston",
    "sg:classifiers":[
        {
            "category":"Retail",
            "subcategory":"Portrait Studio",
            "type":"Services"
        }
    ],
    "sg:phone":"+1 508 429 2120",
    "sg:postcode":"01746",
    "sg:province":"MA",
    "sg:tags":[
        "photography"
    ],
    "sg:website":"www.thehenrystudio.com",
    "wof:name":"Henry Studio",
    "wof:placetype":"venue"
},
  "geometry": {"coordinates":[-71.429602,42.200635],"type":"Point"}
}