{
  "type": "Feature",
  "properties": {
    "iso:country":"US",
    "sg:address":"693 Cochituate Rd",
    "sg:city":"Framingham",
    "sg:classifiers":[
        {
            "category":"Manufacturing",
            "subcategory":"Signs",
            "type":"Manufacturing & Wholesale Goods"
        }
    ],
    "sg:phone":"+1 508 820 8335",
    "sg:postcode":"01701",
    "sg:province":"MA",
    "wof:name":"Fastsigns",
    "wof:placetype":"venue"
},
  "geometry": {"coordinates":[-71.384871,42.308013],"type":"Point"}
}