{
  "type": "Feature",
  "properties": {
    "iso:country":"US",
    "sg:address":"5 Cottage St",
    "sg:city":"East Weymouth",
    "sg:classifiers":[
        {
            "category":"Professional",
            "subcategory":"Lawyer & Legal Services",
            "type":"Services"
        }
    ],
    "sg:phone":"+1 781 337 1400",
    "sg:postcode":"02189",
    "sg:province":"MA",
    "sg:tags":[
        "attorney"
    ],
    "wof:name":"Patrick J Fitzgerald",
    "wof:placetype":"venue"
},
  "geometry": {"coordinates":[-70.92675300000001,42.217269],"type":"Point"}
}