{
  "type": "Feature",
  "properties": {
    "addr:full":"2 Willow St Fayville MA 01745",
    "addr:housenumber":"2",
    "addr:postcode":"01745",
    "addr:street":"Willow St",
    "iso:country":"US",
    "sg:address":"2 Willow St",
    "sg:city":"Fayville",
    "sg:classifiers":[
        {
            "category":"Professional",
            "subcategory":"Management & Consulting",
            "type":"Services"
        }
    ],
    "sg:phone":"+1 508 460 3800",
    "sg:postcode":"01745",
    "sg:province":"MA",
    "sg:tags":[
        "consultant",
        "business"
    ],
    "wof:name":"Iquantic Inc",
    "wof:placetype":"venue"
},
  "geometry": {"coordinates":[-71.49704,42.297723],"type":"Point"}
}