{
  "type": "Feature",
  "properties": {
    "iso:country":"US",
    "sg:address":"1 Cabot Road",
    "sg:city":"Medford",
    "sg:classifiers":[
        {
            "category":"Real Estate",
            "subcategory":"Real Estate Services",
            "type":"Services"
        }
    ],
    "sg:phone":"+1 781 396 3122",
    "sg:postcode":"02155",
    "sg:province":"MA",
    "sg:tags":[
        "management",
        "property"
    ],
    "wof:name":"Cabot Road Partners",
    "wof:placetype":"venue"
},
  "geometry": {"coordinates":[-71.105062,42.416711],"type":"Point"}
}