{
  "type": "Feature",
  "properties": {
    "iso:country":"US",
    "sg:address":"107 Otis St",
    "sg:city":"Northborough",
    "sg:classifiers":[
        {
            "category":"Professional",
            "subcategory":"Employment Agencies",
            "type":"Services"
        }
    ],
    "sg:phone":"+1 508 393 0800",
    "sg:postcode":"01532",
    "sg:province":"MA",
    "sg:tags":[
        "opportunity"
    ],
    "sg:website":"www.greysmith.com",
    "wof:name":"Account Search & Greysmith",
    "wof:placetype":"venue"
},
  "geometry": {"coordinates":[-71.657203,42.291557],"type":"Point"}
}