{
  "type": "Feature",
  "properties": {
    "addr:full":"425 Cambridge Street Cambridge MA 02141",
    "addr:housenumber":"425",
    "addr:postcode":"02141",
    "addr:street":"Cambridge Street",
    "iso:country":"US",
    "sg:address":"425 Cambridge Street",
    "sg:city":"Cambridge",
    "sg:classifiers":[
        {
            "category":"Sports & Exercise",
            "subcategory":"Gym",
            "type":"Entertainment"
        },
        {
            "category":"Shopping",
            "subcategory":"Pharmacy",
            "type":"Retail Goods"
        }
    ],
    "sg:phone":"+1 617 547 0325",
    "sg:postcode":"02141",
    "sg:province":"MA",
    "sg:tags":[
        "trainer",
        "drugstore"
    ],
    "wof:name":"Ciampa Medical Supply",
    "wof:placetype":"venue"
},
  "geometry": {"coordinates":[-71.08328899999999,42.37135],"type":"Point"}
}