{
  "type": "Feature",
  "properties": {
    "addr:full": "583 Washington St Brighton MA 02135",
    "addr:housenumber": "583",
    "addr:postcode": "02135",
    "addr:street": "Washington St",
    "iso:country": "US",
    "sg:address": "583 Washington St",
    "sg:city": "Brighton",
    "sg:classifiers": [
      {
        "category": "Deli",
        "type": "Food \u0026 Drink"
      },
      {
        "category": "Restaurant",
        "type": "Food \u0026 Drink"
      }
    ],
    "sg:menulink": "http://www.allmenus.com/ma/boston/952-oak-square-pizza/menu/",
    "sg:phone": "+1 617 254 4514",
    "sg:postcode": "02135",
    "sg:province": "MA",
    "sg:tags": [
      "sandwich",
      "deli",
      "mediterranean",
      "american",
      "wrap",
      "pizza",
      "italian"
    ],
    "wof:name": "Oak Square Pizza",
    "wof:placetype": "venue"
  },
  "geometry": {"coordinates":[-71.165546,42.350293],"type":"Point"}
}
