{
  "type": "Feature",
  "properties": {
    "addr:full": "58 Hayward St Braintree MA 02184",
    "addr:housenumber": "58",
    "addr:postcode": "02184",
    "addr:street": "Hayward St",
    "iso:country": "US",
    "sg:address": "58 Hayward St",
    "sg:city": "Braintree",
    "sg:classifiers": [
      {
        "category": "Professional",
        "subcategory": "Management \u0026 Consulting",
        "type": "Services"
      }
    ],
    "sg:phone": "+1   ",
    "sg:postcode": "02184",
    "sg:province": "MA",
    "wof:name": "Duquette Consulting LLC",
    "wof:placetype": "venue"
  },
  "geometry": {"coordinates":[-70.987077,42.228321],"type":"Point"}
}
