{
  "type": "Feature",
  "properties": {
    "iso:country":"US",
    "sg:address":"11 Algonquin Rd",
    "sg:city":"Canton",
    "sg:classifiers":[
        {
            "category":"Wholesale",
            "subcategory":"Meat",
            "type":"Manufacturing & Wholesale Goods"
        }
    ],
    "sg:phone":"+1   ",
    "sg:postcode":"02021",
    "sg:province":"MA",
    "sg:tags":[
        "product"
    ],
    "wof:name":"Sheldon Forwarding",
    "wof:placetype":"venue"
},
  "geometry": {"coordinates":[-71.135989,42.193439],"type":"Point"}
}