{
  "type": "Feature",
  "properties": {
    "addr:full": "11 Algonquin Rd Canton MA 02021",
    "addr:housenumber": "11",
    "addr:postcode": "02021",
    "addr:street": "Algonquin Rd",
    "iso:country": "US",
    "sg:address": "11 Algonquin Rd",
    "sg:city": "Canton",
    "sg:classifiers": [
      {
        "category": "Wholesale",
        "subcategory": "Meat",
        "type": "Manufacturing \u0026 Wholesale Goods"
      }
    ],
    "sg:phone": "+1   ",
    "sg:postcode": "02021",
    "sg:province": "MA",
    "sg:tags": [
      "product"
    ],
    "wof:name": "Sheldon Forwarding",
    "wof:placetype": "venue"
  },
  "geometry": {"coordinates":[-71.135989,42.193439],"type":"Point"}
}
