{
  "type": "Feature",
  "properties": {
    "iso:country":"US",
    "sg:address":"109 Candlewood Ln",
    "sg:city":"Hanover",
    "sg:classifiers":[
        {
            "category":"Building & Trades",
            "subcategory":"Construction",
            "type":"Services"
        }
    ],
    "sg:phone":"+1 781 826 7973",
    "sg:postcode":"02339",
    "sg:province":"MA",
    "sg:tags":[
        "general",
        "contractor"
    ],
    "wof:name":"J F Esposito & Sons Inc",
    "wof:placetype":"venue"
},
  "geometry": {"coordinates":[-70.841573,42.112933],"type":"Point"}
}