{
  "type": "Feature",
  "properties": {
    "addr:full": "109 Candlewood Ln Hanover MA 02339",
    "addr:housenumber": "109",
    "addr:postcode": "02339",
    "addr:street": "Candlewood Ln",
    "iso:country": "US",
    "sg:address": "109 Candlewood Ln",
    "sg:city": "Hanover",
    "sg:classifiers": [
      {
        "category": "Building \u0026 Trades",
        "subcategory": "Construction",
        "type": "Services"
      }
    ],
    "sg:phone": "+1 781 826 7973",
    "sg:postcode": "02339",
    "sg:province": "MA",
    "sg:tags": [
      "general",
      "contractor"
    ],
    "wof:name": "J F Esposito \u0026 Sons Inc",
    "wof:placetype": "venue"
  },
  "geometry": {"coordinates":[-70.841573,42.112933],"type":"Point"}
}
