{
  "type": "Feature",
  "properties": {
    "iso:country":"US",
    "sg:address":"20 Locust St",
    "sg:city":"Medford",
    "sg:classifiers":[
        {
            "category":"Retail",
            "subcategory":"Auto Repair",
            "type":"Services"
        }
    ],
    "sg:phone":"+1 781 391 2269",
    "sg:postcode":"02155",
    "sg:province":"MA",
    "sg:tags":[
        "wrecker"
    ],
    "wof:name":"Mc Govern's Towing",
    "wof:placetype":"venue"
},
  "geometry": {"coordinates":[-71.093791,42.407226],"type":"Point"}
}