{
  "type": "Feature",
  "properties": {
    "iso:country":"US",
    "sg:address":"340 Burncoat St",
    "sg:city":"Worcester",
    "sg:classifiers":[
        {
            "category":"Social Services",
            "subcategory":"Child Care",
            "type":"Services"
        }
    ],
    "sg:phone":"+1 508 853 1096",
    "sg:postcode":"01606",
    "sg:province":"MA",
    "wof:name":"Magic Years Preschool",
    "wof:placetype":"venue"
},
  "geometry": {"coordinates":[-71.78910500000001,42.310853],"type":"Point"}
}