{
  "type": "Feature",
  "properties": {
    "iso:country":"US",
    "sg:address":"143 Spring St",
    "sg:city":"Hanover",
    "sg:classifiers":[
        {
            "category":"Building & Trades",
            "subcategory":"Electrical",
            "type":"Services"
        }
    ],
    "sg:phone":"+1   ",
    "sg:postcode":"02339",
    "sg:province":"MA",
    "sg:tags":[
        "electrical",
        "contractor"
    ],
    "wof:name":"OHara Elc Fithful SEC Systems",
    "wof:placetype":"venue"
},
  "geometry": {"coordinates":[-70.839383,42.111862],"type":"Point"}
}