{
  "type": "Feature",
  "properties": {
    "iso:country":"US",
    "sg:address":"8 Gates St",
    "sg:city":"Lowell",
    "sg:classifiers":[
        {
            "category":"Building & Trades",
            "subcategory":"Cleaning & Sanitation",
            "type":"Services"
        }
    ],
    "sg:phone":"+1 978 459 0701",
    "sg:postcode":"01851",
    "sg:province":"MA",
    "sg:tags":[
        "janitor"
    ],
    "wof:name":"E S Cleaning Svc",
    "wof:placetype":"venue"
},
  "geometry": {"coordinates":[-71.32037699999999,42.637332],"type":"Point"}
}