{
  "type": "Feature",
  "properties": {
    "addr:full": "10 Sandy Ln Salisbury MA 01952",
    "addr:housenumber": "10",
    "addr:postcode": "01952",
    "addr:street": "Sandy Ln",
    "iso:country": "US",
    "sg:address": "10 Sandy Ln",
    "sg:city": "Salisbury",
    "sg:classifiers": [
      {
        "category": "Building \u0026 Trades",
        "subcategory": "Construction",
        "type": "Services"
      }
    ],
    "sg:phone": "+1 978 462 2195",
    "sg:postcode": "01952",
    "sg:province": "MA",
    "sg:tags": [
      "general",
      "contractor"
    ],
    "wof:name": "Stevens Construction Assoc",
    "wof:placetype": "venue"
  },
  "geometry": {"coordinates":[-70.851419,42.840462],"type":"Point"}
}
