{
  "type": "Feature",
  "properties": {
    "iso:country":"US",
    "sg:address":"10 Sandy Ln",
    "sg:city":"Salisbury",
    "sg:classifiers":[
        {
            "category":"Building & Trades",
            "subcategory":"Construction",
            "type":"Services"
        }
    ],
    "sg:phone":"+1 978 462 2195",
    "sg:postcode":"01952",
    "sg:province":"MA",
    "sg:tags":[
        "general",
        "contractor"
    ],
    "wof:name":"Stevens Construction Assoc",
    "wof:placetype":"venue"
},
  "geometry": {"coordinates":[-70.85141900000001,42.840462],"type":"Point"}
}