{
  "type": "Feature",
  "properties": {
    "addr:full": "880 W Main St Hyannis MA 02601",
    "addr:housenumber": "880",
    "addr:postcode": "02601",
    "addr:street": "W Main St",
    "iso:country": "US",
    "sg:address": "880 W Main St",
    "sg:city": "Hyannis",
    "sg:classifiers": [
      {
        "category": "Professional",
        "type": "Services"
      }
    ],
    "sg:phone": "+1 508 790 7857",
    "sg:postcode": "02601",
    "sg:province": "MA",
    "sg:tags": [
      "establishment"
    ],
    "wof:name": "Xiphias Enterprises Inc",
    "wof:placetype": "venue"
  },
  "geometry": {"coordinates":[-70.325674,41.655431],"type":"Point"}
}
