{
  "type": "Feature",
  "properties": {
    "addr:full": "241 Wildwood Ave Braintree MA 02184",
    "addr:housenumber": "241",
    "addr:postcode": "02184",
    "addr:street": "Wildwood Ave",
    "iso:country": "US",
    "sg:address": "241 Wildwood Ave",
    "sg:city": "Braintree",
    "sg:classifiers": [
      {
        "category": "Building \u0026 Trades",
        "subcategory": "Construction",
        "type": "Services"
      }
    ],
    "sg:phone": "+1   ",
    "sg:postcode": "02184",
    "sg:province": "MA",
    "sg:tags": [
      "contractor"
    ],
    "wof:name": "Cedrone \u0026 Son",
    "wof:placetype": "venue"
  },
  "geometry": {"coordinates":[-70.999593,42.176046],"type":"Point"}
}
