{
  "type": "Feature",
  "properties": {
    "iso:country":"US",
    "sg:address":"241 Wildwood Ave",
    "sg:city":"Braintree",
    "sg:classifiers":[
        {
            "category":"Building & Trades",
            "subcategory":"Construction",
            "type":"Services"
        }
    ],
    "sg:phone":"+1   ",
    "sg:postcode":"02184",
    "sg:province":"MA",
    "sg:tags":[
        "contractor"
    ],
    "wof:name":"Cedrone & Son",
    "wof:placetype":"venue"
},
  "geometry": {"coordinates":[-70.999593,42.176046],"type":"Point"}
}