{
  "type": "Feature",
  "properties": {
    "addr:full": "58 Sagamore Ave Medford MA 02155",
    "addr:housenumber": "58",
    "addr:postcode": "02155",
    "addr:street": "Sagamore Ave",
    "iso:country": "US",
    "sg:address": "58 Sagamore Ave",
    "sg:city": "Medford",
    "sg:classifiers": [
      {
        "category": "Professional",
        "subcategory": "Management \u0026 Consulting",
        "type": "Services"
      }
    ],
    "sg:phone": "+1   ",
    "sg:postcode": "02155",
    "sg:province": "MA",
    "wof:name": "Russell P Boisjoly",
    "wof:placetype": "venue"
  },
  "geometry": {"coordinates":[-71.14092,42.423575],"type":"Point"}
}
