{
  "type": "Feature",
  "properties": {
    "iso:country":"US",
    "sg:address":"58 Sagamore Ave",
    "sg:city":"Medford",
    "sg:classifiers":[
        {
            "category":"Professional",
            "subcategory":"Management & Consulting",
            "type":"Services"
        }
    ],
    "sg:phone":"+1   ",
    "sg:postcode":"02155",
    "sg:province":"MA",
    "wof:name":"Russell P Boisjoly",
    "wof:placetype":"venue"
},
  "geometry": {"coordinates":[-71.14091999999999,42.423575],"type":"Point"}
}