{
  "type": "Feature",
  "properties": {
    "iso:country":"US",
    "sg:address":"8 Thorndike St",
    "sg:city":"Everett",
    "sg:classifiers":[
        {
            "category":"Retail",
            "subcategory":"Auto Repair",
            "type":"Services"
        }
    ],
    "sg:phone":"+1 617 387 2100",
    "sg:postcode":"02149",
    "sg:province":"MA",
    "sg:tags":[
        "repairing",
        "automobile"
    ],
    "wof:name":"Finish Line Automotive",
    "wof:placetype":"venue"
},
  "geometry": {"coordinates":[-71.062712,42.395717],"type":"Point"}
}