{
  "type": "Feature",
  "properties": {
    "iso:country":"US",
    "sg:address":"1019 State Hwy 132",
    "sg:city":"Hyannis",
    "sg:classifiers":[
        {
            "category":"Health Services",
            "subcategory":"Hospital",
            "type":"Services"
        }
    ],
    "sg:phone":"+1 508 778 1839",
    "sg:postcode":"02601",
    "sg:province":"MA",
    "sg:tags":[
        "mental"
    ],
    "wof:name":"Child & Family Svc Of Cape Cod",
    "wof:placetype":"venue"
},
  "geometry": {"coordinates":[-70.30374399999999,41.672436],"type":"Point"}
}