{
  "type": "Feature",
  "properties": {
    "addr:full": "782 Main St Chatham MA 02633",
    "addr:housenumber": "782",
    "addr:postcode": "02633",
    "addr:street": "Main St",
    "iso:country": "US",
    "sg:address": "782 Main St",
    "sg:city": "Chatham",
    "sg:classifiers": [
      {
        "category": "Real Estate",
        "subcategory": "Real Estate Agent",
        "type": "Services"
      }
    ],
    "sg:phone": "+1 508 945 5350",
    "sg:postcode": "02633",
    "sg:province": "MA",
    "sg:tags": [
      "apartment",
      "management"
    ],
    "wof:name": "Lighthouse Realty",
    "wof:placetype": "venue"
  },
  "geometry": {"coordinates":[-69.965103,41.684399],"type":"Point"}
}
