{
  "type": "Feature",
  "properties": {
    "iso:country":"US",
    "sg:address":"20 Brush Hill Ter",
    "sg:city":"Hyde Park",
    "sg:classifiers":[
        {
            "category":"Wholesale",
            "subcategory":"Drugs",
            "type":"Manufacturing & Wholesale Goods"
        }
    ],
    "sg:phone":"+1 617 364 9116",
    "sg:postcode":"02136",
    "sg:province":"MA",
    "sg:tags":[
        "cosmetic"
    ],
    "wof:name":"IBC Industries & Healthcare",
    "wof:placetype":"venue"
},
  "geometry": {"coordinates":[-71.115819,42.245233],"type":"Point"}
}