{
  "type": "Feature",
  "properties": {
    "iso:country":"US",
    "sg:address":"140 Humphrey St",
    "sg:city":"Swampscott",
    "sg:classifiers":[
        {
            "category":"Insurance",
            "subcategory":"Hazard Insurance",
            "type":"Services"
        }
    ],
    "sg:phone":"+1 781 593 1417",
    "sg:postcode":"01907",
    "sg:province":"MA",
    "sg:tags":[
        "commercial",
        "business"
    ],
    "wof:name":"C Guy Insurance Agency",
    "wof:placetype":"venue"
},
  "geometry": {"coordinates":[-70.91693100000001,42.468048],"type":"Point"}
}