{
  "type": "Feature",
  "properties": {
    "iso:country":"US",
    "sg:address":"110 Webster St",
    "sg:city":"Newton",
    "sg:classifiers":[
        {
            "category":"Professional",
            "type":"Services"
        }
    ],
    "sg:phone":"+1   ",
    "sg:postcode":"02465",
    "sg:province":"MA",
    "wof:name":"Slavin Jh PHD PC",
    "wof:placetype":"venue"
},
  "geometry": {"coordinates":[-71.22987500000001,42.349869],"type":"Point"}
}