{
  "type": "Feature",
  "properties": {
    "iso:country":"US",
    "sg:address":"52 Grove St",
    "sg:city":"North Dartmouth",
    "sg:classifiers":[
        {
            "category":"Retail",
            "subcategory":"Repair Shop",
            "type":"Services"
        }
    ],
    "sg:phone":"+1   ",
    "sg:postcode":"02747",
    "sg:province":"MA",
    "sg:tags":[
        "electrical"
    ],
    "wof:name":"Sanitary Laundry",
    "wof:placetype":"venue"
},
  "geometry": {"coordinates":[-71.035175,41.65557],"type":"Point"}
}