{
  "type": "Feature",
  "properties": {
    "addr:full": "800 Boylston St Boston MA 02199",
    "addr:housenumber": "800",
    "addr:postcode": "02199",
    "addr:street": "Boylston St",
    "iso:country": "US",
    "sg:address": "800 Boylston St",
    "sg:city": "Boston",
    "sg:classifiers": [
      {
        "category": "Shopping",
        "subcategory": "Jewelry",
        "type": "Retail Goods"
      }
    ],
    "sg:phone": "+1 617 236 0601",
    "sg:postcode": "02199",
    "sg:province": "MA",
    "sg:tags": [
      "watch"
    ],
    "wof:name": "Ocean Time",
    "wof:placetype": "venue"
  },
  "geometry": {"coordinates":[-71.083099,42.348296],"type":"Point"}
}
