{
  "type": "Feature",
  "properties": {
    "addr:full": "1221 Ocean St Marshfield MA 02050",
    "addr:housenumber": "1221",
    "addr:postcode": "02050",
    "addr:street": "Ocean St",
    "iso:country": "US",
    "sg:address": "1221 Ocean St",
    "sg:city": "Marshfield",
    "sg:classifiers": [
      {
        "category": "Shopping",
        "type": "Retail Goods"
      }
    ],
    "sg:phone": "+1 781 319 0048",
    "sg:postcode": "02050",
    "sg:province": "MA",
    "sg:tags": [
      "candle"
    ],
    "wof:name": "Fergie's Candles \u0026 Access",
    "wof:placetype": "venue"
  },
  "geometry": {"coordinates":[-70.67833,42.100439],"type":"Point"}
}
