{
  "type": "Feature",
  "properties": {
    "addr:full":"21 Commerce Rd Rockland MA 02370",
    "addr:housenumber":"21",
    "addr:postcode":"02370",
    "addr:street":"Commerce Rd",
    "iso:country":"US",
    "sg:address":"21 Commerce Rd",
    "sg:city":"Rockland",
    "sg:classifiers":[
        {
            "category":"Manufacturing",
            "subcategory":"Printing",
            "type":"Manufacturing & Wholesale Goods"
        }
    ],
    "sg:phone":"+1 781 871 1645",
    "sg:postcode":"02370",
    "sg:province":"MA",
    "sg:tags":[
        "printer"
    ],
    "wof:name":"Peacock Press Inc",
    "wof:placetype":"venue"
},
  "geometry": {"coordinates":[-70.900536,42.163423],"type":"Point"}
}