{
  "type": "Feature",
  "properties": {
    "addr:full":"363 Liberty St Rockland MA 02370",
    "addr:housenumber":"363",
    "addr:postcode":"02370",
    "addr:street":"Liberty St",
    "iso:country":"US",
    "sg:address":"363 Liberty St",
    "sg:city":"Rockland",
    "sg:classifiers":[
        {
            "category":"Building & Trades",
            "subcategory":"Construction",
            "type":"Services"
        }
    ],
    "sg:phone":"+1 781 871 8333",
    "sg:postcode":"02370",
    "sg:province":"MA",
    "sg:tags":[
        "general",
        "contractor"
    ],
    "wof:name":"FDW Construction",
    "wof:placetype":"venue"
},
  "geometry": {"coordinates":[-70.90783399999999,42.132555],"type":"Point"}
}