{
  "type": "Feature",
  "properties": {
    "addr:full": "122 Lafayette Rd Salisbury MA 01952",
    "addr:housenumber": "122",
    "addr:postcode": "01952",
    "iso:country": "US",
    "sg:address": "122 Lafayette Rd",
    "sg:city": "Salisbury",
    "sg:classifiers": [
      {
        "category": "Home \u0026 Garden",
        "subcategory": "Furniture",
        "type": "Retail Goods"
      }
    ],
    "sg:phone": "+1 978 465 5830",
    "sg:postcode": "01952",
    "sg:province": "MA",
    "wof:name": "Mattress Depot Inc",
    "wof:placetype": "venue"
  },
  "geometry": {"coordinates":[-70.872813,42.85891],"type":"Point"}
}
