{
  "type": "Feature",
  "properties": {
    "addr:full": "265 Main St Cambridge MA 02142",
    "addr:housenumber": "265",
    "addr:postcode": "02142",
    "addr:street": "Main St",
    "iso:country": "US",
    "sg:address": "265 Main St",
    "sg:city": "Cambridge",
    "sg:classifiers": [
      {
        "category": "Building \u0026 Trades",
        "subcategory": "Locksmith",
        "type": "Services"
      }
    ],
    "sg:phone": "+1 617 914 0031",
    "sg:postcode": "02142",
    "sg:province": "MA",
    "sg:tags": [
      "key"
    ],
    "wof:name": "A S A P Twenty Four Emergency Locksmith Cam",
    "wof:placetype": "venue"
  },
  "geometry": {"coordinates":[-71.085738,42.362566],"type":"Point"}
}
