{
  "type": "Feature",
  "properties": {
    "addr:full":"43 Kirk Cir Plymouth MA 02360",
    "addr:housenumber":"43",
    "addr:postcode":"02360",
    "addr:street":"Kirk Cir",
    "iso:country":"US",
    "sg:address":"43 Kirk Cir",
    "sg:city":"Plymouth",
    "sg:classifiers":[
        {
            "category":"Building & Trades",
            "subcategory":"Plumbing",
            "type":"Services"
        }
    ],
    "sg:phone":"+1   ",
    "sg:postcode":"02360",
    "sg:province":"MA",
    "sg:tags":[
        "contractor"
    ],
    "wof:name":"Frugal Air",
    "wof:placetype":"venue"
},
  "geometry": {"coordinates":[-70.594449,41.800227],"type":"Point"}
}