{
  "type": "Feature",
  "properties": {
    "iso:country":"US",
    "sg:address":"337 North Ave",
    "sg:city":"Wakefield",
    "sg:classifiers":[
        {
            "category":"Building & Trades",
            "subcategory":"Equipment Rental",
            "type":"Services"
        }
    ],
    "sg:phone":"+1 781 246 4424",
    "sg:postcode":"01880",
    "sg:province":"MA",
    "sg:tags":[
        "instrument",
        "musical"
    ],
    "wof:name":"Timeline Music",
    "wof:placetype":"venue"
},
  "geometry": {"coordinates":[-71.077907,42.505179],"type":"Point"}
}