{
  "type": "Feature",
  "properties": {
    "addr:full": "75 Southwood Dr Ludlow MA 01056",
    "addr:housenumber": "75",
    "addr:postcode": "01056",
    "addr:street": "Southwood Dr",
    "iso:country": "US",
    "sg:address": "75 Southwood Dr",
    "sg:city": "Ludlow",
    "sg:classifiers": [
      {
        "category": "Building \u0026 Trades",
        "subcategory": "Construction",
        "type": "Services"
      }
    ],
    "sg:phone": "+1 413 583 3070",
    "sg:postcode": "01056",
    "sg:province": "MA",
    "sg:tags": [
      "general",
      "contractor"
    ],
    "wof:name": "Celebrity Builders Inc",
    "wof:placetype": "venue"
  },
  "geometry": {"coordinates":[-72.413947,42.192602],"type":"Point"}
}
