{
  "type": "Feature",
  "properties": {
    "iso:country":"US",
    "sg:address":"75 Southwood Dr",
    "sg:city":"Ludlow",
    "sg:classifiers":[
        {
            "category":"Building & Trades",
            "subcategory":"Construction",
            "type":"Services"
        }
    ],
    "sg:phone":"+1 413 583 3070",
    "sg:postcode":"01056",
    "sg:province":"MA",
    "sg:tags":[
        "general",
        "contractor"
    ],
    "wof:name":"Celebrity Builders Inc",
    "wof:placetype":"venue"
},
  "geometry": {"coordinates":[-72.41394699999999,42.192602],"type":"Point"}
}