{
  "type": "Feature",
  "properties": {
    "iso:country":"US",
    "sg:address":"400 Commonwealth Ave",
    "sg:city":"Boston",
    "sg:classifiers":[
        {
            "category":"Health Services",
            "subcategory":"Doctor",
            "type":"Services"
        }
    ],
    "sg:phone":"+1 617 247 2600",
    "sg:postcode":"02215",
    "sg:province":"MA",
    "sg:tags":[
        "dentist"
    ],
    "sg:website":"www.o-works.com",
    "wof:name":"Roy Daniel Rinkle DDS",
    "wof:placetype":"venue"
},
  "geometry": {"coordinates":[-71.088566,42.348962],"type":"Point"}
}