{
  "type": "Feature",
  "properties": {
    "iso:country":"US",
    "sg:address":"53 Highland Ave",
    "sg:city":"Haverhill",
    "sg:classifiers":[
        {
            "category":"Social Services",
            "subcategory":"Child Care",
            "type":"Services"
        }
    ],
    "sg:phone":"+1   ",
    "sg:postcode":"01830",
    "sg:province":"MA",
    "sg:tags":[
        "day"
    ],
    "wof:name":"Fullerton Family Day Care",
    "wof:placetype":"venue"
},
  "geometry": {"coordinates":[-71.07283,42.783904],"type":"Point"}
}