{
  "type": "Feature",
  "properties": {
    "addr:full": "97 Webster St Worcester MA 01603",
    "addr:housenumber": "97",
    "addr:postcode": "01603",
    "addr:street": "Webster St",
    "iso:country": "US",
    "sg:address": "97 Webster St",
    "sg:city": "Worcester",
    "sg:classifiers": [
      {
        "category": "Shopping",
        "subcategory": "Florist",
        "type": "Retail Goods"
      }
    ],
    "sg:phone": "+1 508 756 9624",
    "sg:postcode": "01603",
    "sg:province": "MA",
    "wof:name": "Teleflora Stems \u0026 Bunches",
    "wof:placetype": "venue"
  },
  "geometry": {"coordinates":[-71.832634,42.240772],"type":"Point"}
}
