{
  "type": "Feature",
  "properties": {
    "addr:full": "81 Granger Blvd Marlborough MA 01752",
    "addr:housenumber": "81",
    "addr:postcode": "01752",
    "addr:street": "Granger Blvd",
    "iso:country": "US",
    "sg:address": "81 Granger Blvd",
    "sg:city": "Marlborough",
    "sg:classifiers": [
      {
        "category": "Autos \u0026 Motor Vehicles",
        "subcategory": "Automobile Sales",
        "type": "Retail Goods"
      }
    ],
    "sg:phone": "+1 508 490 8100",
    "sg:postcode": "01752",
    "sg:province": "MA",
    "sg:tags": [
      "car",
      "dealer"
    ],
    "wof:name": "Express Auto Ctr",
    "wof:placetype": "venue"
  },
  "geometry": {"coordinates":[-71.549805,42.345314],"type":"Point"}
}
