{
  "type": "Feature",
  "properties": {
    "iso:country":"US",
    "sg:address":"81 Granger Blvd",
    "sg:city":"Marlborough",
    "sg:classifiers":[
        {
            "category":"Autos & Motor Vehicles",
            "subcategory":"Automobile Sales",
            "type":"Retail Goods"
        }
    ],
    "sg:phone":"+1 508 490 8100",
    "sg:postcode":"01752",
    "sg:province":"MA",
    "sg:tags":[
        "car",
        "dealer"
    ],
    "wof:name":"Express Auto Ctr",
    "wof:placetype":"venue"
},
  "geometry": {"coordinates":[-71.54980500000001,42.345314],"type":"Point"}
}