{
  "type": "Feature",
  "properties": {
    "iso:country":"US",
    "sg:address":"137 Andover St",
    "sg:city":"Lowell",
    "sg:classifiers":[
        {
            "category":"Autos & Motor Vehicles",
            "subcategory":"Fuel & Gas Station",
            "type":"Retail Goods"
        }
    ],
    "sg:phone":"+1 978 459 8625",
    "sg:postcode":"01852",
    "sg:province":"MA",
    "sg:tags":[
        "oil"
    ],
    "wof:name":"Lowell Getty Mart",
    "wof:placetype":"venue"
},
  "geometry": {"coordinates":[-71.29952900000001,42.641921],"type":"Point"}
}