{
  "type": "Feature",
  "properties": {
    "iso:country":"US",
    "sg:address":"231 Union St",
    "sg:city":"New Bedford",
    "sg:classifiers":[
        {
            "category":"Bagels",
            "type":"Food & Drink"
        },
        {
            "category":"Coffee & Tea",
            "type":"Food & Drink"
        },
        {
            "category":"Food & Beverages",
            "subcategory":"Bakery",
            "type":"Retail Goods"
        },
        {
            "category":"Bakery",
            "type":"Food & Drink"
        },
        {
            "category":"Donuts",
            "type":"Food & Drink"
        }
    ],
    "sg:menulink":"http://www.allmenus.com/ma/new-bedford/143151-dunkin-donuts/menu/",
    "sg:phone":"+1 508 997 3047",
    "sg:postcode":"02740",
    "sg:province":"MA",
    "sg:tags":[
        "coffee",
        "diner",
        "tea",
        "bakery",
        "bagel",
        "american",
        "pastry"
    ],
    "wof:name":"Dunkin' Donuts",
    "wof:placetype":"venue"
},
  "geometry": {"coordinates":[-70.92728700000001,41.634085],"type":"Point"}
}