{
  "type": "Feature",
  "properties": {
    "addr:full": "231 Union St New Bedford MA 02740",
    "addr:housenumber": "231",
    "addr:postcode": "02740",
    "addr:street": "Union St",
    "iso:country": "US",
    "sg:address": "231 Union St",
    "sg:city": "New Bedford",
    "sg:classifiers": [
      {
        "category": "Bagels",
        "type": "Food \u0026 Drink"
      },
      {
        "category": "Coffee \u0026 Tea",
        "type": "Food \u0026 Drink"
      },
      {
        "category": "Food \u0026 Beverages",
        "subcategory": "Bakery",
        "type": "Retail Goods"
      },
      {
        "category": "Bakery",
        "type": "Food \u0026 Drink"
      },
      {
        "category": "Donuts",
        "type": "Food \u0026 Drink"
      }
    ],
    "sg:menulink": "http://www.allmenus.com/ma/new-bedford/143151-dunkin-donuts/menu/",
    "sg:phone": "+1 508 997 3047",
    "sg:postcode": "02740",
    "sg:province": "MA",
    "sg:tags": [
      "coffee",
      "diner",
      "tea",
      "bakery",
      "bagel",
      "american",
      "pastry"
    ],
    "wof:name": "Dunkin' Donuts",
    "wof:placetype": "venue"
  },
  "geometry": {"coordinates":[-70.927287,41.634085],"type":"Point"}
}
