{
  "type": "Feature",
  "properties": {
    "iso:country":"US",
    "sg:address":"35 Airport Rd",
    "sg:city":"Fitchburg",
    "sg:classifiers":[
        {
            "category":"Health Services",
            "subcategory":"Chiropractor",
            "type":"Services"
        }
    ],
    "sg:phone":"+1   ",
    "sg:postcode":"01420",
    "sg:province":"MA",
    "wof:name":"Congram Herb",
    "wof:placetype":"venue"
},
  "geometry": {"coordinates":[-71.778623,42.567167],"type":"Point"}
}