{
  "type": "Feature",
  "properties": {
    "addr:full": "1101 Beacon St Ste 1W Brookline MA 02446",
    "addr:housenumber": "1101",
    "addr:postcode": "02446",
    "addr:street": "Beacon St Ste 1W",
    "iso:country": "US",
    "sg:address": "1101 Beacon St Ste 1W",
    "sg:city": "Brookline",
    "sg:classifiers": [
      {
        "category": "Health Services",
        "subcategory": "Doctor",
        "type": "Services"
      }
    ],
    "sg:phone": "+1 617 731 8334",
    "sg:postcode": "02446",
    "sg:province": "MA",
    "sg:tags": [
      "physician",
      "surgeon",
      "neurology",
      "surgeons"
    ],
    "wof:name": "Jacob Rachlin",
    "wof:placetype": "venue"
  },
  "geometry": {"coordinates":[-71.110847,42.344872],"type":"Point"}
}
