{
  "type": "Feature",
  "properties": {
    "iso:country":"US",
    "sg:address":"95 Furrowtown Rd",
    "sg:city":"Westfield",
    "sg:classifiers":[
        {
            "category":"Organizations",
            "subcategory":"Community Association",
            "type":"Services"
        }
    ],
    "sg:phone":"+1 413 562 0771",
    "sg:postcode":"01085",
    "sg:province":"MA",
    "sg:tags":[
        "club"
    ],
    "wof:name":"Westfield Sportsmans Club",
    "wof:placetype":"venue"
},
  "geometry": {"coordinates":[-72.76076399999999,42.147472],"type":"Point"}
}