{
  "type": "Feature",
  "properties": {
    "addr:full": "53 Hundreds Cir Wellesley Hills MA 02481",
    "addr:housenumber": "53",
    "addr:postcode": "02481",
    "addr:street": "Hundreds Cir",
    "iso:country": "US",
    "sg:address": "53 Hundreds Cir",
    "sg:city": "Wellesley Hills",
    "sg:classifiers": [
      {
        "category": "Health Services",
        "subcategory": "Doctor",
        "type": "Services"
      }
    ],
    "sg:phone": "+1 781 235 4477",
    "sg:postcode": "02481",
    "sg:province": "MA",
    "sg:tags": [
      "physician",
      "surgeon"
    ],
    "wof:name": "David Hughes MD",
    "wof:placetype": "venue"
  },
  "geometry": {"coordinates":[-71.280316,42.318569],"type":"Point"}
}
