{
  "type": "Feature",
  "properties": {
    "iso:country":"US",
    "sg:address":"7 Orchard Xing",
    "sg:city":"Andover",
    "sg:classifiers":[
        {
            "category":"Real Estate",
            "subcategory":"Real Estate Agent",
            "type":"Services"
        }
    ],
    "sg:phone":"+1 978 475 3141",
    "sg:postcode":"01810",
    "sg:province":"MA",
    "wof:name":"Advance Realty",
    "wof:placetype":"venue"
},
  "geometry": {"coordinates":[-71.129356,42.629847],"type":"Point"}
}