{
  "type": "Feature",
  "properties": {
    "iso:country":"US",
    "sg:address":"279 Cambridge St",
    "sg:city":"Burlington",
    "sg:classifiers":[
        {
            "category":"Personal",
            "subcategory":"Beauty Salon",
            "type":"Services"
        }
    ],
    "sg:phone":"+1 781 272 4770",
    "sg:postcode":"01803",
    "sg:province":"MA",
    "wof:name":"Leone's Hair Design Inc",
    "wof:placetype":"venue"
},
  "geometry": {"coordinates":[-71.20635900000001,42.515517],"type":"Point"}
}