{
  "type": "Feature",
  "properties": {
    "addr:full": "279 Cambridge St Burlington MA 01803",
    "addr:housenumber": "279",
    "addr:postcode": "01803",
    "addr:street": "Cambridge St",
    "iso:country": "US",
    "ovtr:label": "Leone's Hair Design Inc, 279 Cambridge St Burlington MA US",
    "ovtr:similarity": 2.5340800285339355,
    "sg:address": "279 Cambridge St",
    "sg:city": "Burlington",
    "sg:classifiers": [
      {
        "category": "Personal",
        "subcategory": "Beauty Salon",
        "type": "Services"
      }
    ],
    "sg:phone": "+1 781 272 4770",
    "sg:postcode": "01803",
    "sg:province": "MA",
    "wof:name": "Leone's Hair Design Inc",
    "wof:placetype": "venue"
  },
  "geometry": {"coordinates":[-71.206359,42.515517],"type":"Point"}
}
