{
  "type": "Feature",
  "properties": {
    "iso:country":"US",
    "sg:address":"15 Chester Ave",
    "sg:city":"Medford",
    "sg:classifiers":[
        {
            "category":"Professional",
            "subcategory":"Management & Consulting",
            "type":"Services"
        }
    ],
    "sg:phone":"+1 781 306 1173",
    "sg:postcode":"02155",
    "sg:province":"MA",
    "sg:website":"www.yourstrategies.com",
    "wof:name":"Workplace Strategies",
    "wof:placetype":"venue"
},
  "geometry": {"coordinates":[-71.118804,42.41294],"type":"Point"}
}