{
  "type": "Feature",
  "properties": {
    "iso:country":"US",
    "sg:address":"228 Brooks St",
    "sg:city":"Worcester",
    "sg:classifiers":[
        {
            "category":"Real Estate",
            "subcategory":"Real Estate Agent",
            "type":"Services"
        }
    ],
    "sg:phone":"+1 617 853 2622",
    "sg:postcode":"01606",
    "sg:province":"MA",
    "sg:tags":[
        "agency",
        "rental"
    ],
    "wof:name":"Nci Scale Rentals",
    "wof:placetype":"venue"
},
  "geometry": {"coordinates":[-71.798134,42.324969],"type":"Point"}
}