{
  "type": "Feature",
  "properties": {
    "iso:country":"US",
    "sg:address":"9 Ridgeway St",
    "sg:city":"Quincy",
    "sg:classifiers":[
        {
            "category":"Building & Trades",
            "subcategory":"Construction",
            "type":"Services"
        }
    ],
    "sg:phone":"+1 617 479 2918",
    "sg:postcode":"02170",
    "sg:province":"MA",
    "sg:tags":[
        "general",
        "contractor"
    ],
    "wof:name":"Chris-Ryan Construction",
    "wof:placetype":"venue"
},
  "geometry": {"coordinates":[-71.007181,42.272338],"type":"Point"}
}