{
  "type": "Feature",
  "properties": {
    "addr:full":"290 Leadmine Rd Fiskdale MA 01518",
    "addr:housenumber":"290",
    "addr:postcode":"01518",
    "addr:street":"Leadmine Rd",
    "iso:country":"US",
    "sg:address":"290 Leadmine Rd",
    "sg:city":"Fiskdale",
    "sg:classifiers":[
        {
            "category":"Manufacturing",
            "subcategory":"Printing",
            "type":"Manufacturing & Wholesale Goods"
        }
    ],
    "sg:phone":"+1 508 347 5574",
    "sg:postcode":"01518",
    "sg:province":"MA",
    "sg:tags":[
        "publisher"
    ],
    "sg:website":"www.monogramaviation.com",
    "wof:name":"Monogram Aviation Publications",
    "wof:placetype":"venue"
},
  "geometry": {"coordinates":[-72.11904,42.0839],"type":"Point"}
}