{
  "type": "Feature",
  "properties": {
    "addr:full": "342 Main St Groton MA 01450",
    "addr:housenumber": "342",
    "addr:postcode": "01450",
    "addr:street": "Main St",
    "iso:country": "US",
    "ovtr:label": "Florence Roche Elementary School, 342 Main St Groton MA US",
    "ovtr:similarity": 3.889180898666382,
    "sg:address": "342 Main St",
    "sg:city": "Groton",
    "sg:classifiers": [
      {
        "category": "Education",
        "subcategory": "School",
        "type": "Public Place"
      }
    ],
    "sg:phone": "+1 978 448 6665",
    "sg:postcode": "01450",
    "sg:province": "MA",
    "sg:website": "www.gdrsd.org",
    "wof:name": "Florence Roche School",
    "wof:placetype": "venue"
  },
  "geometry": {"coordinates":[-71.583974,42.618482],"type":"Point"}
}
