{
  "type": "Feature",
  "properties": {
    "iso:country":"US",
    "sg:address":"67 S Bedford St Ste 101E",
    "sg:city":"Burlington",
    "sg:classifiers":[
        {
            "category":"Social Services",
            "subcategory":"Job Training",
            "type":"Services"
        }
    ],
    "sg:phone":"+1 781 238 1800",
    "sg:postcode":"01803",
    "sg:province":"MA",
    "sg:tags":[
        "career",
        "counseling"
    ],
    "sg:website":"www.keystoneassociates.com",
    "wof:name":"Keystone Associates",
    "wof:placetype":"venue"
},
  "geometry": {"coordinates":[-71.20059999999999,42.4842],"type":"Point"}
}