{
  "type": "Feature",
  "properties": {
    "iso:country":"US",
    "sg:address":"100 Commercial Rd",
    "sg:city":"Leominster",
    "sg:classifiers":[
        {
            "category":"Shopping",
            "subcategory":"Clothing, Apparel, & Fashions",
            "type":"Retail Goods"
        }
    ],
    "sg:phone":"+1 978 466 6889",
    "sg:postcode":"01453",
    "sg:province":"MA",
    "sg:tags":[
        "sale",
        "rental",
        "wear",
        "formal"
    ],
    "wof:name":"Gingiss Formalwear",
    "wof:placetype":"venue"
},
  "geometry": {"coordinates":[-71.74039500000001,42.530605],"type":"Point"}
}