{
  "type": "Feature",
  "properties": {
    "iso:country":"US",
    "sg:address":"451 Lincoln St",
    "sg:city":"Worcester",
    "sg:classifiers":[
        {
            "category":"Restaurant",
            "type":"Food & Drink"
        },
        {
            "category":"Ice Cream",
            "type":"Food & Drink"
        }
    ],
    "sg:menulink":"http://www.allmenus.com/ma/worcester/99185-friendlys/menu/",
    "sg:phone":"+1 508 852 1470",
    "sg:postcode":"01605",
    "sg:province":"MA",
    "sg:tags":[
        "burger",
        "american",
        "ice",
        "cream"
    ],
    "wof:name":"Friendly's",
    "wof:placetype":"venue"
},
  "geometry": {"coordinates":[-71.77959199999999,42.292067],"type":"Point"}
}