{
  "type": "Feature",
  "properties": {
    "addr:full": "451 Lincoln St Worcester MA 01605",
    "addr:housenumber": "451",
    "addr:postcode": "01605",
    "addr:street": "Lincoln St",
    "iso:country": "US",
    "sg:address": "451 Lincoln St",
    "sg:city": "Worcester",
    "sg:classifiers": [
      {
        "category": "Restaurant",
        "type": "Food \u0026 Drink"
      },
      {
        "category": "Ice Cream",
        "type": "Food \u0026 Drink"
      }
    ],
    "sg:menulink": "http://www.allmenus.com/ma/worcester/99185-friendlys/menu/",
    "sg:phone": "+1 508 852 1470",
    "sg:postcode": "01605",
    "sg:province": "MA",
    "sg:tags": [
      "burger",
      "american",
      "ice",
      "cream"
    ],
    "wof:name": "Friendly's",
    "wof:placetype": "venue"
  },
  "geometry": {"coordinates":[-71.779592,42.292067],"type":"Point"}
}
