{
  "type": "Feature",
  "properties": {
    "addr:full": "188 Oak St Methuen MA 01844",
    "addr:housenumber": "188",
    "addr:postcode": "01844",
    "addr:street": "Oak St",
    "iso:country": "US",
    "sg:address": "188 Oak St",
    "sg:city": "Methuen",
    "sg:classifiers": [
      {
        "category": "Manufacturing",
        "subcategory": "Lumber",
        "type": "Manufacturing \u0026 Wholesale Goods"
      }
    ],
    "sg:phone": "+1   ",
    "sg:postcode": "01844",
    "sg:province": "MA",
    "sg:tags": [
      "wood",
      "carving"
    ],
    "wof:name": "Urban Woods",
    "wof:placetype": "venue"
  },
  "geometry": {"coordinates":[-71.144439,42.735238],"type":"Point"}
}
