{
  "type": "Feature",
  "properties": {
    "iso:country":"US",
    "sg:address":"188 Oak St",
    "sg:city":"Methuen",
    "sg:classifiers":[
        {
            "category":"Manufacturing",
            "subcategory":"Lumber",
            "type":"Manufacturing & Wholesale Goods"
        }
    ],
    "sg:phone":"+1   ",
    "sg:postcode":"01844",
    "sg:province":"MA",
    "sg:tags":[
        "wood",
        "carving"
    ],
    "wof:name":"Urban Woods",
    "wof:placetype":"venue"
},
  "geometry": {"coordinates":[-71.14443900000001,42.735238],"type":"Point"}
}