{
  "type": "Feature",
  "properties": {
    "iso:country":"US",
    "sg:address":"154 Center Depot Rd",
    "sg:city":"Charlton",
    "sg:classifiers":[
        {
            "category":"Building & Trades",
            "subcategory":"Construction",
            "type":"Services"
        }
    ],
    "sg:phone":"+1 508 248 2788",
    "sg:postcode":"01507",
    "sg:province":"MA",
    "sg:tags":[
        "contractor"
    ],
    "wof:name":"Kevlar Construction",
    "wof:placetype":"venue"
},
  "geometry": {"coordinates":[-71.97682,42.164297],"type":"Point"}
}