{
  "type": "Feature",
  "properties": {
    "iso:country":"US",
    "sg:address":"401 Otter River Rd",
    "sg:city":"Templeton",
    "sg:classifiers":[
        {
            "category":"Building & Trades",
            "subcategory":"Construction",
            "type":"Services"
        }
    ],
    "sg:phone":"+1   ",
    "sg:postcode":"01468",
    "sg:province":"MA",
    "sg:tags":[
        "carpentry",
        "contractor"
    ],
    "wof:name":"Rios Armando",
    "wof:placetype":"venue"
},
  "geometry": {"coordinates":[-72.05318699999999,42.577859],"type":"Point"}
}