{
  "type": "Feature",
  "properties": {
    "addr:full": "401 Otter River Rd Templeton MA 01468",
    "addr:housenumber": "401",
    "addr:postcode": "01468",
    "addr:street": "Otter River Rd",
    "iso:country": "US",
    "sg:address": "401 Otter River Rd",
    "sg:city": "Templeton",
    "sg:classifiers": [
      {
        "category": "Building \u0026 Trades",
        "subcategory": "Construction",
        "type": "Services"
      }
    ],
    "sg:phone": "+1   ",
    "sg:postcode": "01468",
    "sg:province": "MA",
    "sg:tags": [
      "carpentry",
      "contractor"
    ],
    "wof:name": "Rios Armando",
    "wof:placetype": "venue"
  },
  "geometry": {"coordinates":[-72.053187,42.577859],"type":"Point"}
}
