{
  "type": "Feature",
  "properties": {
    "iso:country":"US",
    "sg:address":"27 N Dartmouth Mall",
    "sg:city":"North Dartmouth",
    "sg:classifiers":[
        {
            "category":"Home & Garden",
            "subcategory":"Furniture",
            "type":"Retail Goods"
        }
    ],
    "sg:phone":"+1 508 995 7725",
    "sg:postcode":"02747",
    "sg:province":"MA",
    "sg:tags":[
        "builder",
        "custom"
    ],
    "wof:name":"Robbie Staples",
    "wof:placetype":"venue"
},
  "geometry": {"coordinates":[-70.99426800000001,41.641705],"type":"Point"}
}