{
  "type": "Feature",
  "properties": {
    "iso:country":"US",
    "sg:address":"7 Johnson Rd",
    "sg:city":"Chelmsford",
    "sg:classifiers":[
        {
            "category":"Personal",
            "subcategory":"Beauty Salon",
            "type":"Services"
        }
    ],
    "sg:phone":"+1   ",
    "sg:postcode":"01824",
    "sg:province":"MA",
    "sg:tags":[
        "shop"
    ],
    "wof:name":"Contemporary Hair Co",
    "wof:placetype":"venue"
},
  "geometry": {"coordinates":[-71.386028,42.579954],"type":"Point"}
}