{
  "type": "Feature",
  "properties": {
    "iso:country":"US",
    "sg:address":"165 Wood Rd",
    "sg:city":"Braintree",
    "sg:classifiers":[
        {
            "category":"Manufacturing",
            "subcategory":"Metals",
            "type":"Manufacturing & Wholesale Goods"
        }
    ],
    "sg:phone":"+1 781 848 9940",
    "sg:postcode":"02184",
    "sg:province":"MA",
    "sg:tags":[
        "fabricator",
        "sheet"
    ],
    "wof:name":"North East Air Solutions Inc",
    "wof:placetype":"venue"
},
  "geometry": {"coordinates":[-71.035906,42.223156],"type":"Point"}
}