{
  "type": "Feature",
  "properties": {
    "addr:full": "165 Wood Rd Braintree MA 02184",
    "addr:housenumber": "165",
    "addr:postcode": "02184",
    "addr:street": "Wood Rd",
    "iso:country": "US",
    "sg:address": "165 Wood Rd",
    "sg:city": "Braintree",
    "sg:classifiers": [
      {
        "category": "Manufacturing",
        "subcategory": "Metals",
        "type": "Manufacturing \u0026 Wholesale Goods"
      }
    ],
    "sg:phone": "+1 781 848 9940",
    "sg:postcode": "02184",
    "sg:province": "MA",
    "sg:tags": [
      "fabricator",
      "sheet"
    ],
    "wof:name": "North East Air Solutions Inc",
    "wof:placetype": "venue"
  },
  "geometry": {"coordinates":[-71.035906,42.223156],"type":"Point"}
}
