{
  "type": "Feature",
  "properties": {
    "iso:country":"US",
    "sg:address":"460 Wildwood Ave",
    "sg:city":"Woburn",
    "sg:classifiers":[
        {
            "category":"Shopping",
            "type":"Retail Goods"
        }
    ],
    "sg:phone":"+1 781 938 8777",
    "sg:postcode":"01801",
    "sg:province":"MA",
    "sg:tags":[
        "factory",
        "outlet"
    ],
    "sg:website":"www.crateandbarrel.com",
    "wof:name":"Crate & Barrel Outlet",
    "wof:placetype":"venue"
},
  "geometry": {"coordinates":[-71.140226,42.496309],"type":"Point"}
}