{
  "type": "Feature",
  "properties": {
    "addr:full": "460 Wildwood Ave Woburn MA 01801",
    "addr:housenumber": "460",
    "addr:postcode": "01801",
    "addr:street": "Wildwood Ave",
    "iso:country": "US",
    "sg:address": "460 Wildwood Ave",
    "sg:city": "Woburn",
    "sg:classifiers": [
      {
        "category": "Shopping",
        "type": "Retail Goods"
      }
    ],
    "sg:phone": "+1 781 938 8777",
    "sg:postcode": "01801",
    "sg:province": "MA",
    "sg:tags": [
      "factory",
      "outlet"
    ],
    "sg:website": "www.crateandbarrel.com",
    "wof:name": "Crate \u0026 Barrel Outlet",
    "wof:placetype": "venue"
  },
  "geometry": {"coordinates":[-71.140226,42.496309],"type":"Point"}
}
