{
  "type": "Feature",
  "properties": {
    "addr:full": "44 North St Hingham MA 02043",
    "addr:housenumber": "44",
    "addr:postcode": "02043",
    "addr:street": "North St",
    "iso:country": "US",
    "sg:address": "44 North St",
    "sg:city": "Hingham",
    "sg:classifiers": [
      {
        "category": "Shopping",
        "subcategory": "Clothing, Apparel, \u0026 Fashions",
        "type": "Retail Goods"
      }
    ],
    "sg:phone": "+1 781 740 9666",
    "sg:postcode": "02043",
    "sg:province": "MA",
    "sg:tags": [
      "alteration"
    ],
    "wof:name": "A Loving Stitch Alterations",
    "wof:placetype": "venue"
  },
  "geometry": {"coordinates":[-70.886512,42.243361],"type":"Point"}
}
