{
  "type": "Feature",
  "properties": {
    "iso:country":"US",
    "sg:address":"796 Boston Post Rd E",
    "sg:city":"Marlborough",
    "sg:classifiers":[
        {
            "category":"Freight",
            "type":"Transportation"
        }
    ],
    "sg:phone":"+1 508 303 8996",
    "sg:postcode":"01752",
    "sg:province":"MA",
    "sg:tags":[
        "commercial",
        "storage"
    ],
    "wof:name":"Paper Safe",
    "wof:placetype":"venue"
},
  "geometry": {"coordinates":[-71.498544,42.350805],"type":"Point"}
}