{
  "type": "Feature",
  "properties": {
    "addr:full":"29 Bedford St East Bridgewater MA 02333",
    "addr:housenumber":"29",
    "addr:postcode":"02333",
    "addr:street":"Bedford St",
    "iso:country":"US",
    "sg:address":"29 Bedford St",
    "sg:city":"East Bridgewater",
    "sg:classifiers":[
        {
            "category":"Banks & Credit Unions",
            "subcategory":"Bank",
            "type":"Services"
        }
    ],
    "sg:phone":"+1 508 378 8400",
    "sg:postcode":"02333",
    "sg:province":"MA",
    "wof:name":"East Bridgewater Savings Bank",
    "wof:placetype":"venue"
},
  "geometry": {"coordinates":[-70.958673,42.032964],"type":"Point"}
}