{
  "type": "Feature",
  "properties": {
    "iso:country":"US",
    "sg:address":"99 Cedar St",
    "sg:city":"Waltham",
    "sg:classifiers":[
        {
            "category":"Organizations",
            "subcategory":"Community Association",
            "type":"Services"
        }
    ],
    "sg:phone":"+1 781 893 8838",
    "sg:postcode":"02453",
    "sg:province":"MA",
    "wof:name":"Sons Of Italy",
    "wof:placetype":"venue"
},
  "geometry": {"coordinates":[-71.228639,42.365718],"type":"Point"}
}