{
  "type": "Feature",
  "properties": {
    "addr:full": "154 S Mountain Rd Northfield MA 01360",
    "addr:housenumber": "154",
    "addr:postcode": "01360",
    "addr:street": "S Mountain Rd",
    "iso:country": "US",
    "sg:address": "154 S Mountain Rd",
    "sg:city": "Northfield",
    "sg:classifiers": [
      {
        "category": "Education",
        "subcategory": "School",
        "type": "Public Place"
      }
    ],
    "sg:phone": "+1 413 498 2906",
    "sg:postcode": "01360",
    "sg:province": "MA",
    "sg:website": "www.lindenhs.org",
    "wof:name": "Linden Hill School",
    "wof:placetype": "venue"
  },
  "geometry": {"coordinates":[-72.454828,42.649748],"type":"Point"}
}
