{
  "type": "Feature",
  "properties": {
    "iso:country":"US",
    "sg:address":"154 S Mountain Rd",
    "sg:city":"Northfield",
    "sg:classifiers":[
        {
            "category":"Education",
            "subcategory":"School",
            "type":"Public Place"
        }
    ],
    "sg:phone":"+1 413 498 2906",
    "sg:postcode":"01360",
    "sg:province":"MA",
    "sg:website":"www.lindenhs.org",
    "wof:name":"Linden Hill School",
    "wof:placetype":"venue"
},
  "geometry": {"coordinates":[-72.45482800000001,42.649748],"type":"Point"}
}