{
  "type": "Feature",
  "properties": {
    "addr:full":"68 Smith Rd Milton MA 02186",
    "addr:housenumber":"68",
    "addr:postcode":"02186",
    "addr:street":"Smith Rd",
    "iso:country":"US",
    "sg:address":"68 Smith Rd",
    "sg:city":"Milton",
    "sg:classifiers":[
        {
            "category":"Organizations",
            "subcategory":"Religious Organization",
            "type":"Services"
        }
    ],
    "sg:phone":"+1 617 287 2144",
    "sg:postcode":"02186",
    "sg:province":"MA",
    "sg:tags":[
        "church"
    ],
    "wof:name":"Greater Annoiting Harvest Chr",
    "wof:placetype":"venue"
},
  "geometry": {"coordinates":[-71.10596200000001,42.255189],"type":"Point"}
}