{
  "type": "Feature",
  "properties": {
    "addr:full": "618 Shawmut Ave Boston MA 02118",
    "addr:housenumber": "618",
    "addr:postcode": "02118",
    "addr:street": "Shawmut Ave",
    "iso:country": "US",
    "sg:address": "618 Shawmut Ave",
    "sg:city": "Boston",
    "sg:classifiers": [
      {
        "category": "Restaurant",
        "type": "Food \u0026 Drink"
      }
    ],
    "sg:phone": "+1   ",
    "sg:postcode": "02118",
    "sg:province": "MA",
    "sg:tags": [
      "eating"
    ],
    "wof:name": "Mastro Pizza",
    "wof:placetype": "venue"
  },
  "geometry": {"coordinates":[-71.081435,42.335052],"type":"Point"}
}
