{
  "type": "Feature",
  "properties": {
    "iso:country":"US",
    "sg:address":"618 Shawmut Ave",
    "sg:city":"Boston",
    "sg:classifiers":[
        {
            "category":"Restaurant",
            "type":"Food & Drink"
        }
    ],
    "sg:phone":"+1   ",
    "sg:postcode":"02118",
    "sg:province":"MA",
    "sg:tags":[
        "eating"
    ],
    "wof:name":"Mastro Pizza",
    "wof:placetype":"venue"
},
  "geometry": {"coordinates":[-71.081435,42.335052],"type":"Point"}
}