{
  "type": "Feature",
  "properties": {
    "iso:country":"US",
    "sg:address":"118 Carew St",
    "sg:city":"Springfield",
    "sg:classifiers":[
        {
            "category":"Organizations",
            "subcategory":"Religious Organization",
            "type":"Services"
        }
    ],
    "sg:phone":"+1 413 734 8472",
    "sg:postcode":"01104",
    "sg:province":"MA",
    "sg:tags":[
        "church"
    ],
    "sg:website":"www.stspp.org",
    "wof:name":"St Peter & St Paul Russian Chr",
    "wof:placetype":"venue"
},
  "geometry": {"coordinates":[-72.597764,42.112856],"type":"Point"}
}