{
  "type": "Feature",
  "properties": {
    "iso:country":"US",
    "sg:address":"309 Main Street",
    "sg:city":"Winthrop",
    "sg:classifiers":[
        {
            "category":"Sports & Exercise",
            "subcategory":"Gym",
            "type":"Entertainment"
        },
        {
            "category":"Health Services",
            "subcategory":"Dentist",
            "type":"Services"
        }
    ],
    "sg:phone":"+1 617 846 1200",
    "sg:postcode":"02152",
    "sg:province":"MA",
    "sg:tags":[
        "trainer",
        "orthodontist"
    ],
    "wof:name":"Arrigo Michael P Orthdont",
    "wof:placetype":"venue"
},
  "geometry": {"coordinates":[-70.98386000000001,42.381865],"type":"Point"}
}