{
  "type": "Feature",
  "properties": {
    "addr:full": "1 Beacon St Boston MA 02108",
    "addr:housenumber": "1",
    "addr:postcode": "02108",
    "addr:street": "Beacon St",
    "iso:country": "US",
    "sg:address": "1 Beacon St",
    "sg:city": "Boston",
    "sg:classifiers": [
      {
        "category": "Banks \u0026 Credit Unions",
        "subcategory": "Bank",
        "type": "Services"
      }
    ],
    "sg:phone": "+1 617 523 0066",
    "sg:postcode": "02108",
    "sg:province": "MA",
    "sg:tags": [
      "saving",
      "commercial"
    ],
    "wof:name": "Deutsche Bank Trust Company Americas",
    "wof:placetype": "venue"
  },
  "geometry": {"coordinates":[-71.060562,42.358021],"type":"Point"}
}
