{
  "type": "Feature",
  "properties": {
    "addr:full": "8 Highland Road Somerville MA 02144",
    "addr:housenumber": "8",
    "addr:postcode": "02144",
    "addr:street": "Highland Road",
    "iso:country": "US",
    "sg:address": "8 Highland Road",
    "sg:city": "Somerville",
    "sg:classifiers": [
      {
        "category": "Sports \u0026 Exercise",
        "subcategory": "Gym",
        "type": "Entertainment"
      }
    ],
    "sg:phone": "+1 617 623 8014",
    "sg:postcode": "02144",
    "sg:province": "MA",
    "sg:tags": [
      "trainer"
    ],
    "wof:name": "Caley \u0026 Whitmore Corporation",
    "wof:placetype": "venue"
  },
  "geometry": {"coordinates":[-71.113409,42.394976],"type":"Point"}
}
