{
  "type": "Feature",
  "properties": {
    "iso:country":"US",
    "sg:address":"8 Highland Road",
    "sg:city":"Somerville",
    "sg:classifiers":[
        {
            "category":"Sports & Exercise",
            "subcategory":"Gym",
            "type":"Entertainment"
        }
    ],
    "sg:phone":"+1 617 623 8014",
    "sg:postcode":"02144",
    "sg:province":"MA",
    "sg:tags":[
        "trainer"
    ],
    "wof:name":"Caley & Whitmore Corporation",
    "wof:placetype":"venue"
},
  "geometry": {"coordinates":[-71.113409,42.394976],"type":"Point"}
}