{
  "type": "Feature",
  "properties": {
    "addr:full": "37 Providence Rd Westford MA 01886",
    "addr:housenumber": "37",
    "addr:postcode": "01886",
    "addr:street": "Providence Rd",
    "iso:country": "US",
    "sg:address": "37 Providence Rd",
    "sg:city": "Westford",
    "sg:classifiers": [
      {
        "category": "Professional",
        "subcategory": "Art Services",
        "type": "Services"
      }
    ],
    "sg:phone": "+1 978 692 5657",
    "sg:postcode": "01886",
    "sg:province": "MA",
    "sg:tags": [
      "designer",
      "display",
      "producer"
    ],
    "wof:name": "Page Of Wisnowski Design",
    "wof:placetype": "venue"
  },
  "geometry": {"coordinates":[-71.425282,42.586663],"type":"Point"}
}
