{
  "type": "Feature",
  "properties": {
    "iso:country":"US",
    "sg:address":"1 Arsenal Court Dr",
    "sg:city":"Watertown",
    "sg:classifiers":[
        {
            "category":"Professional",
            "type":"Services"
        }
    ],
    "sg:phone":"+1 617 926 5244",
    "sg:postcode":"02472",
    "sg:province":"MA",
    "sg:tags":[
        "establishment"
    ],
    "wof:name":"Thinkingbytes",
    "wof:placetype":"venue"
},
  "geometry": {"coordinates":[-71.16046799999999,42.362977],"type":"Point"}
}