{
  "type": "Feature",
  "properties": {
    "addr:full":"31 Noel St South Hadley MA 01075",
    "addr:housenumber":"31",
    "addr:postcode":"01075",
    "addr:street":"Noel St",
    "iso:country":"US",
    "sg:address":"31 Noel St",
    "sg:city":"South Hadley",
    "sg:classifiers":[
        {
            "category":"Social Services",
            "subcategory":"Child Care",
            "type":"Services"
        }
    ],
    "sg:phone":"+1   ",
    "sg:postcode":"01075",
    "sg:province":"MA",
    "sg:tags":[
        "day"
    ],
    "wof:name":"Your Special Day",
    "wof:placetype":"venue"
},
  "geometry": {"coordinates":[-72.57772,42.231719],"type":"Point"}
}