{
  "type": "Feature",
  "properties": {
    "addr:full": "233 Broad St Bridgewater MA 02324",
    "addr:housenumber": "233",
    "addr:postcode": "02324",
    "addr:street": "Broad St",
    "iso:country": "US",
    "sg:address": "233 Broad St",
    "sg:city": "Bridgewater",
    "sg:classifiers": [
      {
        "category": "Wholesale",
        "subcategory": "Medical Equipment \u0026 Supplies",
        "type": "Manufacturing \u0026 Wholesale Goods"
      },
      {
        "category": "Shopping",
        "subcategory": "Beauty \u0026 Cosmetics",
        "type": "Retail Goods"
      },
      {
        "category": "Food \u0026 Beverages",
        "subcategory": "Specialty",
        "type": "Retail Goods"
      },
      {
        "category": "Shopping",
        "subcategory": "Gifts \u0026 Souvenirs",
        "type": "Retail Goods"
      },
      {
        "category": "Retail",
        "subcategory": "Photofinishing",
        "type": "Services"
      },
      {
        "category": "Shopping",
        "subcategory": "Pharmacy",
        "type": "Retail Goods"
      }
    ],
    "sg:phone": "+1 508 697 2564",
    "sg:postcode": "02324",
    "sg:province": "MA",
    "sg:tags": [
      "product",
      "photo",
      "vitamin",
      "perfume",
      "supplement",
      "health",
      "wellness",
      "aid",
      "finishing",
      "first",
      "card",
      "greeting"
    ],
    "sg:website": "http://www.riteaid.com",
    "wof:name": "Rite Aid",
    "wof:placetype": "venue"
  },
  "geometry": {"coordinates":[-70.973292,41.995667],"type":"Point"}
}
