{
  "type": "Feature",
  "properties": {
    "addr:full":"10 Hospital Rd Baldwinville MA 01436",
    "addr:housenumber":"10",
    "addr:postcode":"01436",
    "addr:street":"Hospital Rd",
    "iso:country":"US",
    "sg:address":"10 Hospital Rd",
    "sg:city":"Baldwinville",
    "sg:classifiers":[
        {
            "category":"Building & Trades",
            "subcategory":"Construction",
            "type":"Services"
        }
    ],
    "sg:phone":"+1 978 939 2036",
    "sg:postcode":"01436",
    "sg:province":"MA",
    "sg:tags":[
        "hanging",
        "contractor"
    ],
    "wof:name":"Hamel & Son",
    "wof:placetype":"venue"
},
  "geometry": {"coordinates":[-72.061607,42.609996],"type":"Point"}
}