{
  "type": "Feature",
  "properties": {
    "addr:full":"1 Huntington Ave South Yarmouth MA 02664",
    "addr:housenumber":"1",
    "addr:postcode":"02664",
    "addr:street":"Huntington Ave",
    "iso:country":"US",
    "sg:address":"1 Huntington Ave",
    "sg:city":"South Yarmouth",
    "sg:classifiers":[
        {
            "category":"Home & Garden",
            "subcategory":"Building Materials",
            "type":"Retail Goods"
        }
    ],
    "sg:phone":"+1 508 398 2757",
    "sg:postcode":"02664",
    "sg:province":"MA",
    "sg:tags":[
        "door"
    ],
    "wof:name":"All Cape Garage Door",
    "wof:placetype":"venue"
},
  "geometry": {"coordinates":[-70.205563,41.687138],"type":"Point"}
}