{
  "type": "Feature",
  "properties": {
    "iso:country":"US",
    "sg:address":"90 Boston St",
    "sg:city":"Lynn",
    "sg:classifiers":[
        {
            "category":"Food & Beverages",
            "subcategory":"Liquor & Beverages",
            "type":"Retail Goods"
        }
    ],
    "sg:phone":"+1 781 595 3736",
    "sg:postcode":"01904",
    "sg:province":"MA",
    "wof:name":"Audet's Wine & Spirits",
    "wof:placetype":"venue"
},
  "geometry": {"coordinates":[-70.958365,42.473957],"type":"Point"}
}