{
  "type": "Feature",
  "properties": {
    "addr:full": "90 Boston St Lynn MA 01904",
    "addr:housenumber": "90",
    "addr:postcode": "01904",
    "addr:street": "Boston St",
    "iso:country": "US",
    "ovtr:label": "Audet's Wine \u0026 Spirits,, 90 Boston St Lynn MA US",
    "ovtr:similarity": 2.6958670616149902,
    "sg:address": "90 Boston St",
    "sg:city": "Lynn",
    "sg:classifiers": [
      {
        "category": "Food \u0026 Beverages",
        "subcategory": "Liquor \u0026 Beverages",
        "type": "Retail Goods"
      }
    ],
    "sg:phone": "+1 781 595 3736",
    "sg:postcode": "01904",
    "sg:province": "MA",
    "wof:name": "Audet's Wine \u0026 Spirits",
    "wof:placetype": "venue"
  },
  "geometry": {"coordinates":[-70.958365,42.473957],"type":"Point"}
}
