{
  "type": "Feature",
  "properties": {
    "iso:country":"US",
    "sg:address":"292 Bridge St",
    "sg:city":"South Hamilton",
    "sg:classifiers":[
        {
            "category":"Recreation",
            "type":"Entertainment"
        }
    ],
    "sg:phone":"+1 978 468 5162",
    "sg:postcode":"01982",
    "sg:province":"MA",
    "sg:tags":[
        "stable"
    ],
    "wof:name":"Gathering Farm",
    "wof:placetype":"venue"
},
  "geometry": {"coordinates":[-70.837057,42.615321],"type":"Point"}
}