{
  "type": "Feature",
  "properties": {
    "addr:full": "292 Bridge St South Hamilton MA 01982",
    "addr:housenumber": "292",
    "addr:postcode": "01982",
    "addr:street": "Bridge St South",
    "iso:country": "US",
    "sg:address": "292 Bridge St",
    "sg:city": "South Hamilton",
    "sg:classifiers": [
      {
        "category": "Recreation",
        "type": "Entertainment"
      }
    ],
    "sg:phone": "+1 978 468 5162",
    "sg:postcode": "01982",
    "sg:province": "MA",
    "sg:tags": [
      "stable"
    ],
    "wof:name": "Gathering Farm",
    "wof:placetype": "venue"
  },
  "geometry": {"coordinates":[-70.837057,42.615321],"type":"Point"}
}
