{
  "type": "Feature",
  "properties": {
    "iso:country":"US",
    "sg:address":"157 Saundersdale Rd",
    "sg:city":"Charlton",
    "sg:classifiers":[
        {
            "category":"Building & Trades",
            "subcategory":"Construction",
            "type":"Services"
        }
    ],
    "sg:phone":"+1   ",
    "sg:postcode":"01507",
    "sg:province":"MA",
    "sg:tags":[
        "house"
    ],
    "wof:name":"Reilly Construction & Rmdlg",
    "wof:placetype":"venue"
},
  "geometry": {"coordinates":[-71.991658,42.081019],"type":"Point"}
}