{
  "type": "Feature",
  "properties": {
    "addr:full": "639 Douglas St Uxbridge MA 01569",
    "addr:housenumber": "639",
    "addr:postcode": "01569",
    "addr:street": "Douglas St",
    "iso:country": "US",
    "ovtr:label": "Faith Fellowship Church, 647 Douglas St Uxbridge MA US",
    "ovtr:similarity": 3.089643955230713,
    "sg:address": "639 Douglas St",
    "sg:city": "Uxbridge",
    "sg:classifiers": [
      {
        "category": "Organizations",
        "subcategory": "Religious Organization",
        "type": "Services"
      }
    ],
    "sg:phone": "+1 508 278 0300",
    "sg:postcode": "01569",
    "sg:province": "MA",
    "sg:tags": [
      "church"
    ],
    "wof:name": "Faith Fellowship Church",
    "wof:placetype": "venue"
  },
  "geometry": {"coordinates":[-71.667414,42.065632],"type":"Point"}
}
