{
  "type": "Feature",
  "properties": {
    "addr:full":"22 Elizabeth St Northampton MA 01060",
    "addr:housenumber":"22",
    "addr:postcode":"01060",
    "addr:street":"Elizabeth St",
    "iso:country":"US",
    "sg:address":"22 Elizabeth St",
    "sg:city":"Northampton",
    "sg:classifiers":[
        {
            "category":"Building & Trades",
            "subcategory":"Landscaping Services",
            "type":"Services"
        }
    ],
    "sg:phone":"+1 413 584 4077",
    "sg:postcode":"01060",
    "sg:province":"MA",
    "wof:name":"Valley Stump Grinding",
    "wof:placetype":"venue"
},
  "geometry": {"coordinates":[-72.62750200000001,42.328373],"type":"Point"}
}