{
  "type": "Feature",
  "properties": {
    "addr:full": "39 Boulder Brook Rd East Sandwich MA 02537",
    "addr:housenumber": "39",
    "addr:postcode": "02537",
    "addr:street": "Boulder Brook Rd",
    "iso:country": "US",
    "sg:address": "39 Boulder Brook Rd",
    "sg:city": "East Sandwich",
    "sg:classifiers": [
      {
        "category": "Professional",
        "subcategory": "Lawyer \u0026 Legal Services",
        "type": "Services"
      }
    ],
    "sg:phone": "+1 508 888 5392",
    "sg:postcode": "02537",
    "sg:province": "MA",
    "sg:tags": [
      "attorney"
    ],
    "wof:name": "Anna T Merrill Esq",
    "wof:placetype": "venue"
  },
  "geometry": {"coordinates":[-70.457699,41.754715],"type":"Point"}
}
