{
  "type": "Feature",
  "properties": {
    "iso:country":"US",
    "sg:address":"39 Boulder Brook Rd",
    "sg:city":"East Sandwich",
    "sg:classifiers":[
        {
            "category":"Professional",
            "subcategory":"Lawyer & Legal Services",
            "type":"Services"
        }
    ],
    "sg:phone":"+1 508 888 5392",
    "sg:postcode":"02537",
    "sg:province":"MA",
    "sg:tags":[
        "attorney"
    ],
    "wof:name":"Anna T Merrill Esq",
    "wof:placetype":"venue"
},
  "geometry": {"coordinates":[-70.45769900000001,41.754715],"type":"Point"}
}