{
  "type": "Feature",
  "properties": {
    "addr:full": "101 Broadway Rd Dracut MA 01826",
    "addr:housenumber": "101",
    "addr:postcode": "01826",
    "addr:street": "Broadway Rd",
    "iso:country": "US",
    "sg:address": "101 Broadway Rd",
    "sg:city": "Dracut",
    "sg:classifiers": [
      {
        "category": "Wholesale",
        "subcategory": "Books, Periodicals, \u0026 Newspapers",
        "type": "Manufacturing \u0026 Wholesale Goods"
      }
    ],
    "sg:phone": "+1 978 458 8572",
    "sg:postcode": "01826",
    "sg:province": "MA",
    "sg:tags": [
      "dealer"
    ],
    "wof:name": "Book Vendor",
    "wof:placetype": "venue"
  },
  "geometry": {"coordinates":[-71.294739,42.674384],"type":"Point"}
}
