{
  "type": "Feature",
  "properties": {
    "iso:country":"US",
    "sg:address":"101 Broadway Rd",
    "sg:city":"Dracut",
    "sg:classifiers":[
        {
            "category":"Wholesale",
            "subcategory":"Books, Periodicals, & Newspapers",
            "type":"Manufacturing & Wholesale Goods"
        }
    ],
    "sg:phone":"+1 978 458 8572",
    "sg:postcode":"01826",
    "sg:province":"MA",
    "sg:tags":[
        "dealer"
    ],
    "wof:name":"Book Vendor",
    "wof:placetype":"venue"
},
  "geometry": {"coordinates":[-71.29473900000001,42.674384],"type":"Point"}
}