{
  "type": "Feature",
  "properties": {
    "iso:country":"US",
    "sg:address":"64 W Main St",
    "sg:city":"Norton",
    "sg:classifiers":[
        {
            "category":"Education",
            "subcategory":"School",
            "type":"Public Place"
        }
    ],
    "sg:phone":"+1 508 285 0100",
    "sg:postcode":"02766",
    "sg:province":"MA",
    "sg:tags":[
        "high",
        "middle",
        "elementary"
    ],
    "wof:name":"Norton Town of",
    "wof:placetype":"venue"
},
  "geometry": {"coordinates":[-71.191597,41.964199],"type":"Point"}
}