{
  "type": "Feature",
  "properties": {
    "addr:full": "40 Richdale Rd Needham MA 02494",
    "addr:housenumber": "40",
    "addr:postcode": "02494",
    "addr:street": "Richdale Rd",
    "iso:country": "US",
    "sg:address": "40 Richdale Rd",
    "sg:city": "Needham",
    "sg:classifiers": [
      {
        "category": "Social Services",
        "subcategory": "Job Training",
        "type": "Services"
      }
    ],
    "sg:phone": "+1 781 449 6435",
    "sg:postcode": "02494",
    "sg:province": "MA",
    "sg:tags": [
      "rehabilitation"
    ],
    "wof:name": "Professional Rehab Network Inc",
    "wof:placetype": "venue"
  },
  "geometry": {"coordinates":[-71.220701,42.291277],"type":"Point"}
}
