{
  "type": "Feature",
  "properties": {
    "iso:country":"US",
    "sg:address":"242 Neck Rd",
    "sg:city":"Haverhill",
    "sg:classifiers":[
        {
            "category":"Manufacturing",
            "subcategory":"Tools & Machinery",
            "type":"Manufacturing & Wholesale Goods"
        }
    ],
    "sg:phone":"+1   ",
    "sg:postcode":"01835",
    "sg:province":"MA",
    "sg:tags":[
        "mfg",
        "industrial",
        "general"
    ],
    "wof:name":"Balston Filter Products",
    "wof:placetype":"venue"
},
  "geometry": {"coordinates":[-71.12204800000001,42.756166],"type":"Point"}
}