{
  "type": "Feature",
  "properties": {
    "iso:country":"US",
    "sg:address":"313 State Rd",
    "sg:city":"North Dartmouth",
    "sg:classifiers":[
        {
            "category":"Shopping",
            "subcategory":"Computers & Home Electronics",
            "type":"Retail Goods"
        },
        {
            "category":"Professional",
            "subcategory":"Computer Services",
            "type":"Services"
        }
    ],
    "sg:phone":"+1 508 992 0333",
    "sg:postcode":"02747",
    "sg:province":"MA",
    "sg:tags":[
        "hardware",
        "repair"
    ],
    "wof:name":"Compu Buy",
    "wof:placetype":"venue"
},
  "geometry": {"coordinates":[-70.98564399999999,41.639367],"type":"Point"}
}