{
  "type": "Feature",
  "properties": {
    "addr:full": "InterContinental Hotel 510 Atlantic Avenue Boston MA 02210",
    "addr:housenumber": "510",
    "addr:postcode": "02210",
    "addr:street": "Atlantic Avenue",
    "iso:country": "US",
    "sg:address": "InterContinental Hotel 510 Atlantic Avenue",
    "sg:city": "Boston",
    "sg:classifiers": [
      {
        "category": "Personal",
        "subcategory": "Massage",
        "type": "Services"
      },
      {
        "category": "Personal",
        "subcategory": "Skin Care",
        "type": "Services"
      }
    ],
    "sg:phone": "+1 617 217 5090",
    "sg:postcode": "02210",
    "sg:province": "MA",
    "sg:website": "www.intercontinentalboston.com",
    "wof:name": "SPA InterContinental",
    "wof:placetype": "venue"
  },
  "geometry": {"coordinates":[-71.052984,42.353941],"type":"Point"}
}
