{
  "type": "Feature",
  "properties": {
    "addr:full":"100 Ducharme Ave Chicopee MA 01013",
    "addr:housenumber":"100",
    "addr:postcode":"01013",
    "addr:street":"Ducharme Ave",
    "iso:country":"US",
    "sg:address":"100 Ducharme Ave",
    "sg:city":"Chicopee",
    "sg:classifiers":[
        {
            "category":"Building & Trades",
            "subcategory":"Construction",
            "type":"Services"
        }
    ],
    "sg:phone":"+1   ",
    "sg:postcode":"01013",
    "sg:province":"MA",
    "sg:tags":[
        "hanging",
        "contractor"
    ],
    "wof:name":"Gerard Lachance Painting",
    "wof:placetype":"venue"
},
  "geometry": {"coordinates":[-72.615239,42.179028],"type":"Point"}
}