{
  "type": "Feature",
  "properties": {
    "iso:country":"US",
    "sg:address":"11 Bowdoin Ave",
    "sg:city":"Dorchester",
    "sg:classifiers":[
        {
            "category":"Education",
            "subcategory":"School",
            "type":"Public Place"
        }
    ],
    "sg:phone":"+1 617 892 3017",
    "sg:postcode":"02121",
    "sg:province":"MA",
    "wof:name":"Junior Enterprise",
    "wof:placetype":"venue"
},
  "geometry": {"coordinates":[-71.07650599999999,42.3025],"type":"Point"}
}