{
  "type": "Feature",
  "properties": {
    "addr:full": "11 Bowdoin Ave Dorchester MA 02121",
    "addr:housenumber": "11",
    "addr:postcode": "02121",
    "addr:street": "Bowdoin Ave",
    "iso:country": "US",
    "sg:address": "11 Bowdoin Ave",
    "sg:city": "Dorchester",
    "sg:classifiers": [
      {
        "category": "Education",
        "subcategory": "School",
        "type": "Public Place"
      }
    ],
    "sg:phone": "+1 617 892 3017",
    "sg:postcode": "02121",
    "sg:province": "MA",
    "wof:name": "Junior Enterprise",
    "wof:placetype": "venue"
  },
  "geometry": {"coordinates":[-71.076506,42.3025],"type":"Point"}
}
