{
  "type": "Feature",
  "properties": {
    "addr:full":"24 Warwick St Quincy MA 02170",
    "addr:housenumber":"24",
    "addr:postcode":"02170",
    "addr:street":"Warwick St",
    "iso:country":"US",
    "sg:address":"24 Warwick St",
    "sg:city":"Quincy",
    "sg:classifiers":[
        {
            "category":"Restaurant",
            "type":"Food & Drink"
        }
    ],
    "sg:phone":"+1   ",
    "sg:postcode":"02170",
    "sg:province":"MA",
    "sg:tags":[
        "eating"
    ],
    "wof:name":"Liao Restaurant Corp",
    "wof:placetype":"venue"
},
  "geometry": {"coordinates":[-71.019228,42.277794],"type":"Point"}
}