{
  "type": "Feature",
  "properties": {
    "addr:full": "502 Washington St Auburn MA 01501",
    "addr:housenumber": "502",
    "addr:postcode": "01501",
    "addr:street": "Washington St",
    "atp:label": "Cumberland Farms, 502 WASHINGTON ST AUBURN MA US",
    "atp:similarity": 2.4896230697631836,
    "iso:country": "US",
    "sg:address": "502 Washington St",
    "sg:city": "Auburn",
    "sg:classifiers": [
      {
        "category": "Food \u0026 Beverages",
        "subcategory": "Groceries \u0026 Convenience Stores",
        "type": "Retail Goods"
      }
    ],
    "sg:phone": "+1 508 721 9560",
    "sg:postcode": "01501",
    "sg:province": "MA",
    "wof:name": "Cumberland Farms",
    "wof:placetype": "venue"
  },
  "geometry": {"coordinates":[-71.837069,42.18645],"type":"Point"}
}
