{
  "type": "Feature",
  "properties": {
    "addr:full": "103 Alley Rd Rochester MA 02770",
    "addr:housenumber": "103",
    "addr:postcode": "02770",
    "addr:street": "Alley Rd",
    "iso:country": "US",
    "sg:address": "103 Alley Rd",
    "sg:city": "Rochester",
    "sg:classifiers": [
      {
        "category": "Real Estate",
        "subcategory": "Real Estate Agent",
        "type": "Services"
      }
    ],
    "sg:phone": "+1 508 763 4639",
    "sg:postcode": "02770",
    "sg:province": "MA",
    "wof:name": "Mark Wellington Real Estate",
    "wof:placetype": "venue"
  },
  "geometry": {"coordinates":[-70.829862,41.760934],"type":"Point"}
}
