{
  "type": "Feature",
  "properties": {
    "iso:country":"US",
    "sg:address":"133 Milk St",
    "sg:city":"Westborough",
    "sg:classifiers":[
        {
            "category":"Building & Trades",
            "subcategory":"Construction",
            "type":"Services"
        }
    ],
    "sg:phone":"+1   ",
    "sg:postcode":"01581",
    "sg:province":"MA",
    "sg:tags":[
        "department",
        "house",
        "store"
    ],
    "wof:name":"Uhlman Construction",
    "wof:placetype":"venue"
},
  "geometry": {"coordinates":[-71.627415,42.277439],"type":"Point"}
}