{
  "type": "Feature",
  "properties": {
    "addr:full":"839 Beacon St Ste 2 Boston MA 02215",
    "addr:housenumber":"839",
    "addr:postcode":"02215",
    "addr:street":"Beacon St Ste 2",
    "iso:country":"US",
    "sg:address":"839 Beacon St Ste 2",
    "sg:city":"Boston",
    "sg:classifiers":[
        {
            "category":"Real Estate",
            "subcategory":"Real Estate Operator",
            "type":"Services"
        },
        {
            "category":"Travel",
            "subcategory":"Hotels & Motels",
            "type":"Entertainment"
        }
    ],
    "sg:phone":"+1 617 267 7424",
    "sg:postcode":"02215",
    "sg:province":"MA",
    "sg:tags":[
        "apartment"
    ],
    "wof:name":"Hotel & Inn Citywide Reservation Services",
    "wof:placetype":"venue"
},
  "geometry": {"coordinates":[-71.102997,42.347099],"type":"Point"}
}