{
  "type": "Feature",
  "properties": {
    "iso:country":"US",
    "sg:address":"374 Farm St",
    "sg:city":"New Bedford",
    "sg:classifiers":[
        {
            "category":"Recreation",
            "type":"Entertainment"
        }
    ],
    "sg:phone":"+1 508 984 1676",
    "sg:postcode":"02740",
    "sg:province":"MA",
    "sg:tags":[
        "instruction",
        "swimming"
    ],
    "sg:website":"www.swimdsa.com",
    "wof:name":"Southcoast Aquatics",
    "wof:placetype":"venue"
},
  "geometry": {"coordinates":[-70.94293,41.625611],"type":"Point"}
}