{
  "type": "Feature",
  "properties": {
    "addr:full": "324 Electric Ave Lunenburg MA 01462",
    "addr:housenumber": "324",
    "addr:postcode": "01462",
    "addr:street": "Electric Ave",
    "iso:country": "US",
    "sg:address": "324 Electric Ave",
    "sg:city": "Lunenburg",
    "sg:classifiers": [
      {
        "category": "Shopping",
        "subcategory": "Used Merchandise",
        "type": "Retail Goods"
      }
    ],
    "sg:phone": "+1   ",
    "sg:postcode": "01462",
    "sg:province": "MA",
    "wof:name": "Sunshines Flea Market",
    "wof:placetype": "venue"
  },
  "geometry": {"coordinates":[-71.748424,42.576278],"type":"Point"}
}
