{
  "type": "Feature",
  "properties": {
    "iso:country":"US",
    "sg:address":"324 Electric Ave",
    "sg:city":"Lunenburg",
    "sg:classifiers":[
        {
            "category":"Shopping",
            "subcategory":"Used Merchandise",
            "type":"Retail Goods"
        }
    ],
    "sg:phone":"+1   ",
    "sg:postcode":"01462",
    "sg:province":"MA",
    "wof:name":"Sunshines Flea Market",
    "wof:placetype":"venue"
},
  "geometry": {"coordinates":[-71.748424,42.576278],"type":"Point"}
}