{
  "type": "Feature",
  "properties": {
    "addr:full": "36 Loring St Springfield MA 01105",
    "addr:housenumber": "36",
    "addr:postcode": "01105",
    "addr:street": "Loring St",
    "iso:country": "US",
    "sg:address": "36 Loring St",
    "sg:city": "Springfield",
    "sg:classifiers": [
      {
        "category": "Professional",
        "subcategory": "Art Services",
        "type": "Services"
      }
    ],
    "sg:phone": "+1 413 732 1174",
    "sg:postcode": "01105",
    "sg:province": "MA",
    "sg:tags": [
      "photographer"
    ],
    "wof:name": "James A Langone Photo Inc",
    "wof:placetype": "venue"
  },
  "geometry": {"coordinates":[-72.58337,42.095321],"type":"Point"}
}
