{
  "type": "Feature",
  "properties": {
    "iso:country":"US",
    "sg:address":"4 Boston St",
    "sg:city":"Salem",
    "sg:classifiers":[
        {
            "category":"Restaurant",
            "type":"Food & Drink"
        }
    ],
    "sg:phone":"+1 978 745 2348",
    "sg:postcode":"01970",
    "sg:province":"MA",
    "wof:name":"Deb's Diner",
    "wof:placetype":"venue"
},
  "geometry": {"coordinates":[-70.90527899999999,42.517879],"type":"Point"}
}