{
  "type": "Feature",
  "properties": {
    "addr:full": "4 Boston St Salem MA 01970",
    "addr:housenumber": "4",
    "addr:postcode": "01970",
    "addr:street": "Boston St",
    "iso:country": "US",
    "ovtr:label": "Deb's Diner, 4 Boston St Salem MA US",
    "ovtr:similarity": 2.9633209705352783,
    "sg:address": "4 Boston St",
    "sg:city": "Salem",
    "sg:classifiers": [
      {
        "category": "Restaurant",
        "type": "Food \u0026 Drink"
      }
    ],
    "sg:phone": "+1 978 745 2348",
    "sg:postcode": "01970",
    "sg:province": "MA",
    "wof:name": "Deb's Diner",
    "wof:placetype": "venue"
  },
  "geometry": {"coordinates":[-70.905279,42.517879],"type":"Point"}
}
