{
  "type": "Feature",
  "properties": {
    "iso:country":"US",
    "sg:address":"2 Crawford St",
    "sg:city":"Randolph",
    "sg:phone":"+1 781 961 4272",
    "sg:postcode":"02368",
    "sg:province":"MA",
    "sg:tags":[
        "oil"
    ],
    "wof:name":"EMH Oil & Chemical",
    "wof:placetype":"venue"
},
  "geometry": {"coordinates":[-71.07835,42.18734],"type":"Point"}
}