{
  "type": "Feature",
  "properties": {
    "iso:country":"US",
    "sg:address":"85 Parkhurst Rd",
    "sg:city":"Chelmsford",
    "sg:classifiers":[
        {
            "category":"Health Services",
            "subcategory":"Doctor",
            "type":"Services"
        }
    ],
    "sg:phone":"+1 978 458 6868",
    "sg:postcode":"01824",
    "sg:province":"MA",
    "sg:tags":[
        "physician",
        "surgeon"
    ],
    "wof:name":"Chelmsford Walk-In Medical Ctr",
    "wof:placetype":"venue"
},
  "geometry": {"coordinates":[-71.360029,42.624013],"type":"Point"}
}