{
  "type": "Feature",
  "properties": {
    "iso:country":"US",
    "sg:address":"1275 Pawtucket Blvd",
    "sg:city":"Lowell",
    "sg:classifiers":[
        {
            "category":"Personal",
            "subcategory":"Beauty Salon",
            "type":"Services"
        },
        {
            "category":"Personal",
            "subcategory":"Day Spa",
            "type":"Services"
        }
    ],
    "sg:phone":"+1 978 631 0137",
    "sg:postcode":"01854",
    "sg:province":"MA",
    "sg:tags":[
        "hair",
        "stylist"
    ],
    "wof:name":"Unique You Salon",
    "wof:placetype":"venue"
},
  "geometry": {"coordinates":[-71.376417,42.644673],"type":"Point"}
}