{
  "type": "Feature",
  "properties": {
    "iso:country":"US",
    "sg:address":"15 Chippy Ln",
    "sg:city":"Methuen",
    "sg:classifiers":[
        {
            "category":"Shopping",
            "subcategory":"Gifts & Souvenirs",
            "type":"Retail Goods"
        }
    ],
    "sg:phone":"+1 978 794 0829",
    "sg:postcode":"01844",
    "sg:province":"MA",
    "sg:tags":[
        "basket",
        "parcel"
    ],
    "wof:name":"Bayberry Gift & Baskets",
    "wof:placetype":"venue"
},
  "geometry": {"coordinates":[-71.147678,42.741704],"type":"Point"}
}