{
  "type": "Feature",
  "properties": {
    "iso:country":"US",
    "sg:address":"766 Falmouth Rd",
    "sg:city":"Mashpee",
    "sg:classifiers":[
        {
            "category":"Professional",
            "subcategory":"Engineering",
            "type":"Services"
        }
    ],
    "sg:phone":"+1 508 539 3737",
    "sg:postcode":"02649",
    "sg:province":"MA",
    "sg:tags":[
        "engineer"
    ],
    "sg:website":"www.appliedcoastal.com",
    "wof:name":"Applied Coastal Research",
    "wof:placetype":"venue"
},
  "geometry": {"coordinates":[-70.496837,41.604044],"type":"Point"}
}