{
  "type": "Feature",
  "properties": {
    "addr:full": "108 Northfield Rd Bernardston MA 01337",
    "addr:housenumber": "108",
    "addr:postcode": "01337",
    "addr:street": "Northfield Rd",
    "iso:country": "US",
    "sg:address": "108 Northfield Rd",
    "sg:city": "Bernardston",
    "sg:classifiers": [
      {
        "category": "Health Services",
        "subcategory": "Chiropractor",
        "type": "Services"
      }
    ],
    "sg:phone": "+1 413 648 0006",
    "sg:postcode": "01337",
    "sg:province": "MA",
    "wof:name": "Zuttermeister Chiropractic",
    "wof:placetype": "venue"
  },
  "geometry": {"coordinates":[-72.535846,42.669962],"type":"Point"}
}
