{
  "type": "Feature",
  "properties": {
    "addr:full": "Quincy Market Boston MA 02109",
    "addr:postcode": "02109",
    "iso:country": "US",
    "sg:address": "Quincy Market",
    "sg:city": "Boston",
    "sg:classifiers": [
      {
        "category": "Restaurant",
        "type": "Food \u0026 Drink"
      }
    ],
    "sg:menulink": "http://www.allmenus.com/ma/boston/258543-wagamama---faneuil-hall/menu/",
    "sg:phone": "+1 617 742 9242",
    "sg:postcode": "02109",
    "sg:province": "MA",
    "sg:tags": [
      "japanese",
      "asian"
    ],
    "wof:name": "Wagamama - Faneuil Hall",
    "wof:placetype": "venue"
  },
  "geometry": {"coordinates":[-71.055634,42.360274],"type":"Point"}
}
