{
  "type": "Feature",
  "properties": {
    "addr:full": "3120 Shelburne Falls Rd Conway MA 01341",
    "addr:housenumber": "3120",
    "addr:postcode": "01341",
    "addr:street": "Shelburne Falls Rd",
    "iso:country": "US",
    "sg:address": "3120 Shelburne Falls Rd",
    "sg:city": "Conway",
    "sg:classifiers": [
      {
        "category": "Farming",
        "subcategory": "Farm \u0026 Veterinary Services",
        "type": "Manufacturing \u0026 Wholesale Goods"
      }
    ],
    "sg:phone": "+1 413 773 3706",
    "sg:postcode": "01341",
    "sg:province": "MA",
    "sg:tags": [
      "insemination"
    ],
    "wof:name": "American Breeders Svc",
    "wof:placetype": "venue"
  },
  "geometry": {"coordinates":[-72.719242,42.570465],"type":"Point"}
}
