{
  "type": "Feature",
  "properties": {
    "iso:country":"US",
    "sg:address":"3120 Shelburne Falls Rd",
    "sg:city":"Conway",
    "sg:classifiers":[
        {
            "category":"Farming",
            "subcategory":"Farm & Veterinary Services",
            "type":"Manufacturing & Wholesale Goods"
        }
    ],
    "sg:phone":"+1 413 773 3706",
    "sg:postcode":"01341",
    "sg:province":"MA",
    "sg:tags":[
        "insemination"
    ],
    "wof:name":"American Breeders Svc",
    "wof:placetype":"venue"
},
  "geometry": {"coordinates":[-72.71924199999999,42.570465],"type":"Point"}
}