{
  "type": "Feature",
  "properties": {
    "addr:full":"233 Andover St Andover MA 01810",
    "addr:housenumber":"233",
    "addr:postcode":"01810",
    "addr:street":"Andover St",
    "iso:country":"US",
    "sg:address":"233 Andover St",
    "sg:city":"Andover",
    "sg:classifiers":[
        {
            "category":"Manufacturing",
            "subcategory":"Jewelry",
            "type":"Manufacturing & Wholesale Goods"
        }
    ],
    "sg:phone":"+1 978 475 1906",
    "sg:postcode":"01810",
    "sg:province":"MA",
    "sg:tags":[
        "precious",
        "metal",
        "mfg"
    ],
    "wof:name":"Glass Rabbit",
    "wof:placetype":"venue"
},
  "geometry": {"coordinates":[-71.152811,42.627733],"type":"Point"}
}