{
  "type": "Feature",
  "properties": {
    "addr:full": "100 Terminal St Boston MA 02129",
    "addr:housenumber": "100",
    "addr:postcode": "02129",
    "addr:street": "Terminal St",
    "iso:country": "US",
    "sg:address": "100 Terminal St",
    "sg:city": "Boston",
    "sg:classifiers": [
      {
        "category": "Landmark",
        "subcategory": "Tourist Information",
        "type": "Public Place"
      }
    ],
    "sg:phone": "+1 877 343 8257",
    "sg:postcode": "02129",
    "sg:province": "MA",
    "sg:tags": [
      "tour"
    ],
    "sg:website": "www.superducktours.com",
    "wof:name": "Super Duck Tours",
    "wof:placetype": "venue"
  },
  "geometry": {"coordinates":[-71.052023,42.381091],"type":"Point"}
}
