{
  "type": "Feature",
  "properties": {
    "addr:full": "1535 Bay St Springfield MA 01109",
    "addr:housenumber": "1535",
    "addr:postcode": "01109",
    "addr:street": "Bay St",
    "iso:country": "US",
    "sg:address": "1535 Bay St",
    "sg:city": "Springfield",
    "sg:classifiers": [
      {
        "category": "Autos \u0026 Motor Vehicles",
        "subcategory": "Automobile Sales",
        "type": "Retail Goods"
      }
    ],
    "sg:phone": "+1 413 783 1211",
    "sg:postcode": "01109",
    "sg:province": "MA",
    "sg:tags": [
      "car",
      "dealer"
    ],
    "wof:name": "Springfield Lincoln Mercury",
    "wof:placetype": "venue"
  },
  "geometry": {"coordinates":[-72.533096,42.129972],"type":"Point"}
}
