{
  "type": "Feature",
  "properties": {
    "iso:country":"US",
    "sg:address":"110 Union St",
    "sg:city":"Westfield",
    "sg:classifiers":[
        {
            "category":"Health Services",
            "subcategory":"Clinic",
            "type":"Services"
        }
    ],
    "sg:phone":"+1 413 562 9802",
    "sg:postcode":"01085",
    "sg:province":"MA",
    "sg:tags":[
        "home"
    ],
    "wof:name":"International Health Svc",
    "wof:placetype":"venue"
},
  "geometry": {"coordinates":[-72.734483,42.130706],"type":"Point"}
}