{
  "type": "Feature",
  "properties": {
    "iso:country":"US",
    "sg:address":"375 Boston St",
    "sg:city":"Topsfield",
    "sg:classifiers":[
        {
            "category":"Insurance",
            "subcategory":"Insurance Agent",
            "type":"Services"
        }
    ],
    "sg:phone":"+1 978 983 6990",
    "sg:postcode":"01983",
    "sg:province":"MA",
    "sg:tags":[
        "commercial",
        "saving",
        "bank"
    ],
    "wof:name":"Bank North Insurance",
    "wof:placetype":"venue"
},
  "geometry": {"coordinates":[-70.93489099999999,42.651749],"type":"Point"}
}