{
  "type": "Feature",
  "properties": {
    "addr:full":"231 Forest Street Suite 2278 Wellesley MA 02457",
    "addr:housenumber":"231",
    "addr:postcode":"02457",
    "addr:street":"Forest Street Suite 2278",
    "iso:country":"US",
    "sg:address":"231 Forest Street Suite 2278",
    "sg:city":"Wellesley",
    "sg:classifiers":[
        {
            "category":"Professional",
            "subcategory":"Computer Services",
            "type":"Services"
        }
    ],
    "sg:phone":"+1 917 617 4253",
    "sg:postcode":"02457",
    "sg:province":"MA",
    "sg:tags":[
        "mass-customization",
        "apparel",
        "self-design",
        "fashion",
        "dress-shirts",
        "menswear",
        "clothes",
        "ecommerce",
        "online-retail",
        "shopping"
    ],
    "sg:website":"http://www.blank-label.com",
    "wof:name":"Blank Label - Custom Men's Dress Shirts",
    "wof:placetype":"venue"
},
  "geometry": {"coordinates":[-71.17598599999999,42.432196],"type":"Point"}
}