{
  "type": "Feature",
  "properties": {
    "addr:full":"8 Pearl St Boston MA 02110",
    "addr:housenumber":"8",
    "addr:postcode":"02110",
    "addr:street":"Pearl St",
    "iso:country":"US",
    "sg:address":"8 Pearl St",
    "sg:city":"Boston",
    "sg:classifiers":[
        {
            "category":"Building & Trades",
            "subcategory":"Locksmith",
            "type":"Services"
        }
    ],
    "sg:phone":"+1 617 303 2780",
    "sg:postcode":"02110",
    "sg:province":"MA",
    "sg:tags":[
        "key"
    ],
    "wof:name":"USA Locksmith",
    "wof:placetype":"venue"
},
  "geometry": {"coordinates":[-71.05546099999999,42.356865],"type":"Point"}
}