{
  "type": "Feature",
  "properties": {
    "addr:full":"42 Essex St Boston MA 02111",
    "addr:housenumber":"42",
    "addr:postcode":"02111",
    "addr:street":"Essex St",
    "iso:country":"US",
    "sg:address":"42 Essex St",
    "sg:city":"Boston",
    "sg:classifiers":[
        {
            "category":"Personal",
            "subcategory":"Beauty Salon",
            "type":"Services"
        }
    ],
    "sg:phone":"+1 617 338 9338",
    "sg:postcode":"02111",
    "sg:province":"MA",
    "sg:tags":[
        "hair"
    ],
    "sg:website":"www.hairadventure.com",
    "wof:name":"Hair Adventure Beauty Salon",
    "wof:placetype":"venue"
},
  "geometry": {"coordinates":[-71.061593,42.352566],"type":"Point"}
}