{
  "type": "Feature",
  "properties": {
    "addr:full":"218 Elm St South Dartmouth MA 02748",
    "addr:housenumber":"218",
    "addr:postcode":"02748",
    "addr:street":"Elm St",
    "iso:country":"US",
    "sg:address":"218 Elm St",
    "sg:city":"South Dartmouth",
    "sg:classifiers":[
        {
            "category":"Recreation",
            "subcategory":"Marina",
            "type":"Entertainment"
        }
    ],
    "sg:phone":"+1 508 999 1381",
    "sg:postcode":"02748",
    "sg:province":"MA",
    "sg:tags":[
        "repairing",
        "boat"
    ],
    "sg:website":"www.concordiaboats.com",
    "wof:name":"Concordia Co",
    "wof:placetype":"venue"
},
  "geometry": {"coordinates":[-70.942868,41.585848],"type":"Point"}
}