{
  "type": "Feature",
  "properties": {
    "iso:country":"US",
    "sg:address":"16 Meadowview Rd",
    "sg:city":"Foxboro",
    "sg:classifiers":[
        {
            "category":"Building & Trades",
            "subcategory":"Electrical",
            "type":"Services"
        }
    ],
    "sg:phone":"+1   ",
    "sg:postcode":"02035",
    "sg:province":"MA",
    "sg:tags":[
        "electrical",
        "contractor"
    ],
    "wof:name":"James Rehill Elec",
    "wof:placetype":"venue"
},
  "geometry": {"coordinates":[-71.25403799999999,42.100843],"type":"Point"}
}