{
  "type": "Feature",
  "properties": {
    "addr:full": "106 4th St Chelsea MA 02150",
    "addr:housenumber": "106",
    "addr:postcode": "02150",
    "addr:street": "4Th St",
    "iso:country": "US",
    "ovtr:label": "Buccieri's Pizzeria, 106 4th St Chelsea MA US",
    "ovtr:similarity": 2.70330810546875,
    "sg:address": "106 4th St",
    "sg:city": "Chelsea",
    "sg:classifiers": [
      {
        "category": "Deli",
        "type": "Food \u0026 Drink"
      },
      {
        "category": "Restaurant",
        "type": "Food \u0026 Drink"
      }
    ],
    "sg:phone": "+1 617 889 0001",
    "sg:postcode": "02150",
    "sg:province": "MA",
    "sg:tags": [
      "pizza",
      "italian"
    ],
    "sg:website": "Buccierispizza.com",
    "wof:name": "Buccieri's Pizzeria",
    "wof:placetype": "venue"
  },
  "geometry": {"coordinates":[-71.038244,42.393948],"type":"Point"}
}
