{
  "type": "Feature",
  "properties": {
    "iso:country":"US",
    "sg:address":"106 4th St",
    "sg:city":"Chelsea",
    "sg:classifiers":[
        {
            "category":"Deli",
            "type":"Food & Drink"
        },
        {
            "category":"Restaurant",
            "type":"Food & Drink"
        }
    ],
    "sg:phone":"+1 617 889 0001",
    "sg:postcode":"02150",
    "sg:province":"MA",
    "sg:tags":[
        "pizza",
        "italian"
    ],
    "sg:website":"Buccierispizza.com",
    "wof:name":"Buccieri's Pizzeria",
    "wof:placetype":"venue"
},
  "geometry": {"coordinates":[-71.03824400000001,42.393948],"type":"Point"}
}