{
  "type": "Feature",
  "properties": {
    "addr:full": "90 Commerce Way Woburn MA 01801",
    "addr:housenumber": "90",
    "addr:postcode": "01801",
    "addr:street": "Commerce Way",
    "iso:country": "US",
    "sg:address": "90 Commerce Way",
    "sg:city": "Woburn",
    "sg:classifiers": [
      {
        "category": "Home \u0026 Garden",
        "subcategory": "Carpets \u0026 Floor Coverings",
        "type": "Retail Goods"
      }
    ],
    "sg:phone": "+1 781 933 8500",
    "sg:postcode": "01801",
    "sg:province": "MA",
    "sg:tags": [
      "material"
    ],
    "wof:name": "Pavillion Flooring",
    "wof:placetype": "venue"
  },
  "geometry": {"coordinates":[-71.133536,42.510973],"type":"Point"}
}
