{
  "type": "Feature",
  "properties": {
    "addr:full":"21 Spring Valley Rd Hull MA 02045",
    "addr:housenumber":"21",
    "addr:postcode":"02045",
    "addr:street":"Spring Valley Rd",
    "iso:country":"US",
    "sg:address":"21 Spring Valley Rd",
    "sg:city":"Hull",
    "sg:classifiers":[
        {
            "category":"Farming",
            "subcategory":"Fish & Marine Products",
            "type":"Manufacturing & Wholesale Goods"
        }
    ],
    "sg:phone":"+1 781 925 1885",
    "sg:postcode":"02045",
    "sg:province":"MA",
    "sg:tags":[
        "actuary"
    ],
    "wof:name":"Arthur W Anderson Group",
    "wof:placetype":"venue"
},
  "geometry": {"coordinates":[-70.84669100000001,42.264535],"type":"Point"}
}