{
  "type": "Feature",
  "properties": {
    "iso:country":"US",
    "sg:address":"42 North St",
    "sg:city":"Hingham",
    "sg:classifiers":[
        {
            "category":"Wholesale",
            "subcategory":"Groceries",
            "type":"Manufacturing & Wholesale Goods"
        }
    ],
    "sg:phone":"+1 781 741 5299",
    "sg:postcode":"02043",
    "sg:province":"MA",
    "sg:tags":[
        "food",
        "broker"
    ],
    "wof:name":"ICI Marketing Group",
    "wof:placetype":"venue"
},
  "geometry": {"coordinates":[-70.886242,42.243367],"type":"Point"}
}