{
  "type": "Feature",
  "properties": {
    "iso:country":"US",
    "sg:address":"60 Rock Glen Rd",
    "sg:city":"Medford",
    "sg:classifiers":[
        {
            "category":"Professional",
            "subcategory":"Computer Services",
            "type":"Services"
        }
    ],
    "sg:phone":"+1   ",
    "sg:postcode":"02155",
    "sg:province":"MA",
    "sg:tags":[
        "added",
        "value"
    ],
    "wof:name":"Electronic Repair",
    "wof:placetype":"venue"
},
  "geometry": {"coordinates":[-71.09266599999999,42.426922],"type":"Point"}
}