{
  "type": "Feature",
  "properties": {
    "addr:full": "40 Spring St Watertown MA 02472",
    "addr:housenumber": "40",
    "addr:postcode": "02472",
    "addr:street": "Spring St",
    "iso:country": "US",
    "sg:address": "40 Spring St",
    "sg:city": "Watertown",
    "sg:classifiers": [
      {
        "category": "Health Services",
        "subcategory": "Medical Lab",
        "type": "Services"
      }
    ],
    "sg:phone": "+1 617 924 2317",
    "sg:postcode": "02472",
    "sg:province": "MA",
    "sg:tags": [
      "laboratory"
    ],
    "wof:name": "Excell Clinical Laboratories",
    "wof:placetype": "venue"
  },
  "geometry": {"coordinates":[-71.183122,42.367043],"type":"Point"}
}
