{
  "type": "Feature",
  "properties": {
    "iso:country":"US",
    "sg:address":"21 Union Wharf",
    "sg:city":"Boston",
    "sg:classifiers":[
        {
            "category":"Professional",
            "type":"Services"
        },
        {
            "category":"Professional",
            "subcategory":"Management & Consulting",
            "type":"Services"
        }
    ],
    "sg:phone":"+1 617 723 8889",
    "sg:postcode":"02109",
    "sg:province":"MA",
    "sg:tags":[
        "consultant",
        "speaker",
        "public",
        "business",
        "author"
    ],
    "sg:website":"www.whiteleygroup.com",
    "wof:name":"Whiteley Group Inc",
    "wof:placetype":"venue"
},
  "geometry": {"coordinates":[-71.050893,42.365424],"type":"Point"}
}