{
  "type": "Feature",
  "properties": {
    "addr:full": "18 Lowell St Peabody MA 01960",
    "addr:housenumber": "18",
    "addr:postcode": "01960",
    "addr:street": "Lowell St",
    "iso:country": "US",
    "sg:address": "18 Lowell St",
    "sg:city": "Peabody",
    "sg:classifiers": [
      {
        "category": "Personal",
        "subcategory": "Beauty Salon",
        "type": "Services"
      }
    ],
    "sg:phone": "+1 978 531 7960",
    "sg:postcode": "01960",
    "sg:province": "MA",
    "wof:name": "Dottie's",
    "wof:placetype": "venue"
  },
  "geometry": {"coordinates":[-70.927696,42.52606],"type":"Point"}
}
