{
  "type": "Feature",
  "properties": {
    "iso:country":"US",
    "sg:address":"48 Brundrett Ave",
    "sg:city":"Andover",
    "sg:classifiers":[
        {
            "category":"Professional",
            "subcategory":"Management & Consulting",
            "type":"Services"
        }
    ],
    "sg:phone":"+1 978 683 0692",
    "sg:postcode":"01810",
    "sg:province":"MA",
    "sg:tags":[
        "agricultural",
        "consultant"
    ],
    "wof:name":"Konjoans Flrclture Edcatn Svcs",
    "wof:placetype":"venue"
},
  "geometry": {"coordinates":[-71.215991,42.685721],"type":"Point"}
}