{
  "type": "Feature",
  "properties": {
    "addr:full":"191 Burley St Danvers MA 01923",
    "addr:housenumber":"191",
    "addr:postcode":"01923",
    "addr:street":"Burley St",
    "iso:country":"US",
    "sg:address":"191 Burley St",
    "sg:city":"Danvers",
    "sg:classifiers":[
        {
            "category":"Autos & Motor Vehicles",
            "subcategory":"Automobile Sales",
            "type":"Retail Goods"
        }
    ],
    "sg:phone":"+1 978 774 2070",
    "sg:postcode":"01923",
    "sg:province":"MA",
    "sg:tags":[
        "aircraft"
    ],
    "wof:name":"North Atlantic Air Inc",
    "wof:placetype":"venue"
},
  "geometry": {"coordinates":[-70.92608,42.583718],"type":"Point"}
}