{
  "type": "Feature",
  "properties": {
    "addr:full": "33 Tozer Rd Beverly MA 01915",
    "addr:housenumber": "33",
    "addr:postcode": "01915",
    "addr:street": "Tozer Rd",
    "iso:country": "US",
    "sg:address": "33 Tozer Rd",
    "sg:city": "Beverly",
    "sg:classifiers": [
      {
        "category": "Manufacturing",
        "subcategory": "Signs",
        "type": "Manufacturing \u0026 Wholesale Goods"
      }
    ],
    "sg:phone": "+1 978 927 9346",
    "sg:postcode": "01915",
    "sg:province": "MA",
    "wof:name": "United Sign Co Inc",
    "wof:placetype": "venue"
  },
  "geometry": {"coordinates":[-70.884912,42.57539],"type":"Point"}
}
