{
  "type": "Feature",
  "properties": {
    "addr:full": "433 West St Amherst MA 01002",
    "addr:housenumber": "433",
    "addr:postcode": "01002",
    "addr:street": "West St",
    "iso:country": "US",
    "sg:address": "433 West St",
    "sg:city": "Amherst",
    "sg:classifiers": [
      {
        "category": "Health Services",
        "subcategory": "Health Practitioner",
        "type": "Services"
      }
    ],
    "sg:phone": "+1 413 256 3393",
    "sg:postcode": "01002",
    "sg:province": "MA",
    "sg:tags": [
      "psychologist"
    ],
    "wof:name": "Nancy Haffey",
    "wof:placetype": "venue"
  },
  "geometry": {"coordinates":[-72.520293,42.34332],"type":"Point"}
}
