{
  "type": "Feature",
  "properties": {
    "addr:full": "25 Thorndike St Everett MA 02149",
    "addr:housenumber": "25",
    "addr:postcode": "02149",
    "addr:street": "Thorndike St",
    "iso:country": "US",
    "sg:address": "25 Thorndike St",
    "sg:city": "Everett",
    "sg:classifiers": [
      {
        "category": "Retail",
        "subcategory": "Laundry \u0026 Dry Cleaning",
        "type": "Services"
      },
      {
        "category": "Retail",
        "subcategory": "Repair Shop",
        "type": "Services"
      },
      {
        "category": "Building \u0026 Trades",
        "subcategory": "Cleaning \u0026 Sanitation",
        "type": "Services"
      }
    ],
    "sg:phone": "+1 617 381 0856",
    "sg:postcode": "02149",
    "sg:province": "MA",
    "sg:tags": [
      "cleaner",
      "upholstery",
      "rug",
      "upholsterer",
      "carpet"
    ],
    "wof:name": "Mr Orange Carpet Cleaning",
    "wof:placetype": "venue"
  },
  "geometry": {"coordinates":[-71.064098,42.396398],"type":"Point"}
}
