{
  "type": "Feature",
  "properties": {
    "iso:country":"US",
    "sg:address":"880 Winter St Bldg 4",
    "sg:city":"Waltham",
    "sg:classifiers":[
        {
            "category":"Wholesale",
            "subcategory":"Computers",
            "type":"Manufacturing & Wholesale Goods"
        },
        {
            "category":"Professional",
            "subcategory":"Computer Services",
            "type":"Services"
        }
    ],
    "sg:phone":"+1 781 487 3300",
    "sg:postcode":"02451",
    "sg:province":"MA",
    "sg:tags":[
        "publisher",
        "network",
        "system",
        "equipment",
        "design",
        "developer",
        "software"
    ],
    "sg:website":"http://www.on.com",
    "wof:name":"On Technology Corp",
    "wof:placetype":"venue"
},
  "geometry": {"coordinates":[-71.271883,42.407615],"type":"Point"}
}