{
  "type": "Feature",
  "properties": {
    "addr:full":"15 E Silver St Westfield MA 01085",
    "addr:housenumber":"15",
    "addr:postcode":"01085",
    "addr:street":"E Silver St",
    "iso:country":"US",
    "sg:address":"15 E Silver St",
    "sg:city":"Westfield",
    "sg:classifiers":[
        {
            "category":"Professional",
            "subcategory":"Business Services",
            "type":"Services"
        }
    ],
    "sg:phone":"+1 413 562 8800",
    "sg:postcode":"01085",
    "sg:province":"MA",
    "sg:tags":[
        "consultant",
        "coach"
    ],
    "sg:website":"http://www.jeromespartyplus.com",
    "wof:name":"Compuset Inc",
    "wof:placetype":"venue"
},
  "geometry": {"coordinates":[-72.74483499999999,42.114271],"type":"Point"}
}