{
  "type": "Feature",
  "properties": {
    "addr:full":"272 N Falmouth Hwy North Falmouth MA 02556",
    "addr:housenumber":"272",
    "addr:postcode":"02556",
    "addr:street":"N Falmouth Hwy North",
    "iso:country":"US",
    "sg:address":"272 N Falmouth Hwy",
    "sg:city":"North Falmouth",
    "sg:classifiers":[
        {
            "category":"Building & Trades",
            "subcategory":"Construction",
            "type":"Services"
        }
    ],
    "sg:phone":"+1 508 457 1693",
    "sg:postcode":"02556",
    "sg:province":"MA",
    "sg:tags":[
        "contractor"
    ],
    "wof:name":"Caron Robt Bldrs - CLOSED",
    "wof:placetype":"venue"
},
  "geometry": {"coordinates":[-70.61840100000001,41.631401],"type":"Point"}
}