{
  "type": "Feature",
  "properties": {
    "iso:country":"US",
    "sg:address":"1355 East St",
    "sg:city":"Pittsfield",
    "sg:classifiers":[
        {
            "category":"Railroad",
            "type":"Transportation"
        }
    ],
    "sg:phone":"+1 413 499 9700",
    "sg:postcode":"01201",
    "sg:province":"MA",
    "wof:name":"CSX",
    "wof:placetype":"venue"
},
  "geometry": {"coordinates":[-73.219257,42.45409],"type":"Point"}
}