{
  "type": "Feature",
  "properties": {
    "addr:full":"50 Industrial Ct Seekonk MA 02771",
    "addr:housenumber":"50",
    "addr:postcode":"02771",
    "addr:street":"Industrial Ct",
    "iso:country":"US",
    "sg:address":"50 Industrial Ct",
    "sg:city":"Seekonk",
    "sg:classifiers":[
        {
            "category":"Autos & Motor Vehicles",
            "subcategory":"Automobile Sales",
            "type":"Retail Goods"
        }
    ],
    "sg:phone":"+1 508 336 2579",
    "sg:postcode":"02771",
    "sg:province":"MA",
    "sg:tags":[
        "performance",
        "race",
        "dealer"
    ],
    "wof:name":"Mc Kenna Performance Products",
    "wof:placetype":"venue"
},
  "geometry": {"coordinates":[-71.30627,41.780304],"type":"Point"}
}