{
  "type": "Feature",
  "properties": {
    "addr:full":"60 Adams St Braintree MA 02184",
    "addr:housenumber":"60",
    "addr:postcode":"02184",
    "addr:street":"Adams St",
    "iso:country":"US",
    "sg:address":"60 Adams St",
    "sg:city":"Braintree",
    "sg:classifiers":[
        {
            "category":"Health Services",
            "subcategory":"Dentist",
            "type":"Services"
        }
    ],
    "sg:phone":"+1 781 843 0660",
    "sg:postcode":"02184",
    "sg:province":"MA",
    "sg:tags":[
        "dentists-cosmetic",
        "denture",
        "dentists-prosthodontists",
        "dentists-periodontists",
        "dentistry",
        "dentists-orthodontists"
    ],
    "sg:website":"http://www.drgeorgesalem.com",
    "wof:name":"Salem George DMD & Associates PC",
    "wof:placetype":"venue"
},
  "geometry": {"coordinates":[-70.99329400000001,42.22459],"type":"Point"}
}