{
  "type": "Feature",
  "properties": {
    "addr:full": "137 Lexington St Woburn MA 01801",
    "addr:housenumber": "137",
    "addr:postcode": "01801",
    "addr:street": "Lexington St",
    "iso:country": "US",
    "sg:address": "137 Lexington St",
    "sg:city": "Woburn",
    "sg:classifiers": [
      {
        "category": "Social Services",
        "subcategory": "Child Care",
        "type": "Services"
      },
      {
        "category": "Education",
        "subcategory": "Preschool",
        "type": "Public Place"
      },
      {
        "category": "Education",
        "subcategory": "School",
        "type": "Public Place"
      }
    ],
    "sg:phone": "+1 781 938 1025",
    "sg:postcode": "01801",
    "sg:province": "MA",
    "sg:tags": [
      "elementary",
      "day"
    ],
    "wof:name": "YMCA of Greater Boston",
    "wof:placetype": "venue"
  },
  "geometry": {"coordinates":[-71.173302,42.472698],"type":"Point"}
}
