{
  "type": "Feature",
  "properties": {
    "iso:country":"US",
    "sg:address":"125 Cambridgepark Dr",
    "sg:city":"Cambridge",
    "sg:classifiers":[
        {
            "category":"Food & Beverages",
            "subcategory":"Specialty",
            "type":"Retail Goods"
        },
        {
            "category":"Food & Beverages",
            "subcategory":"Farmers Market",
            "type":"Retail Goods"
        },
        {
            "category":"Food & Beverages",
            "subcategory":"Groceries & Convenience Stores",
            "type":"Retail Goods"
        }
    ],
    "sg:phone":"+1 617 492 5500",
    "sg:postcode":"02140",
    "sg:province":"MA",
    "sg:tags":[
        "product",
        "natural",
        "diet",
        "fruit",
        "health",
        "vegetable"
    ],
    "sg:website":"http://www.wholefoodsmarket.com",
    "wof:name":"Whole Foods Market",
    "wof:placetype":"venue"
},
  "geometry": {"coordinates":[-71.144884,42.394683],"type":"Point"}
}