{
  "type": "Feature",
  "properties": {
    "iso:country":"US",
    "sg:address":"58 Sandwich Rd",
    "sg:city":"Wareham",
    "sg:classifiers":[
        {
            "category":"Autos & Motor Vehicles",
            "subcategory":"Automobile Sales",
            "type":"Retail Goods"
        }
    ],
    "sg:phone":"+1 508 295 0751",
    "sg:postcode":"02571",
    "sg:province":"MA",
    "sg:tags":[
        "car",
        "dealer"
    ],
    "wof:name":"Al's Used Cars",
    "wof:placetype":"venue"
},
  "geometry": {"coordinates":[-70.703507,41.758987],"type":"Point"}
}