{
  "type": "Feature",
  "properties": {
    "iso:country":"US",
    "sg:address":"15 Oak Hill Dr",
    "sg:city":"Canton",
    "sg:classifiers":[
        {
            "category":"Building & Trades",
            "subcategory":"Construction",
            "type":"Services"
        }
    ],
    "sg:phone":"+1   ",
    "sg:postcode":"02021",
    "sg:province":"MA",
    "sg:tags":[
        "house"
    ],
    "wof:name":"Home Repair Carpentry",
    "wof:placetype":"venue"
},
  "geometry": {"coordinates":[-71.13506700000001,42.154752],"type":"Point"}
}