{
  "type": "Feature",
  "properties": {
    "iso:country":"US",
    "sg:address":"205 Lexington St",
    "sg:city":"Waltham",
    "sg:classifiers":[
        {
            "category":"Shopping",
            "subcategory":"Clothing, Apparel, & Fashions",
            "type":"Retail Goods"
        }
    ],
    "sg:phone":"+1 781 894 5750",
    "sg:postcode":"02452",
    "sg:province":"MA",
    "sg:tags":[
        "tailor"
    ],
    "wof:name":"Leon Chez Tailoring",
    "wof:placetype":"venue"
},
  "geometry": {"coordinates":[-71.236949,42.383463],"type":"Point"}
}