{
  "type": "Feature",
  "properties": {
    "addr:full": "205 Lexington St Waltham MA 02452",
    "addr:housenumber": "205",
    "addr:postcode": "02452",
    "addr:street": "Lexington St",
    "iso:country": "US",
    "ovtr:label": "Chez Leon Tailoring, 205 Lexington St Waltham MA US",
    "ovtr:similarity": 3.7081000804901123,
    "sg:address": "205 Lexington St",
    "sg:city": "Waltham",
    "sg:classifiers": [
      {
        "category": "Shopping",
        "subcategory": "Clothing, Apparel, \u0026 Fashions",
        "type": "Retail Goods"
      }
    ],
    "sg:phone": "+1 781 894 5750",
    "sg:postcode": "02452",
    "sg:province": "MA",
    "sg:tags": [
      "tailor"
    ],
    "wof:name": "Leon Chez Tailoring",
    "wof:placetype": "venue"
  },
  "geometry": {"coordinates":[-71.236949,42.383463],"type":"Point"}
}
