{
  "type": "Feature",
  "properties": {
    "addr:full": "10 Church St Boylston MA 01505",
    "addr:housenumber": "10",
    "addr:postcode": "01505",
    "addr:street": "Church St",
    "iso:country": "US",
    "ovtr:label": "First Congregational Church, 10 Church St Boylston MA US",
    "ovtr:similarity": 3.0620710849761963,
    "sg:address": "10 Church St",
    "sg:city": "Boylston",
    "sg:classifiers": [
      {
        "category": "Organizations",
        "subcategory": "Religious Organization",
        "type": "Services"
      }
    ],
    "sg:phone": "+1 508 869 2027",
    "sg:postcode": "01505",
    "sg:province": "MA",
    "sg:tags": [
      "church"
    ],
    "sg:website": "www.fcc-boylston.org",
    "wof:name": "First Congregational Church",
    "wof:placetype": "venue"
  },
  "geometry": {"coordinates":[-71.734254,42.352878],"type":"Point"}
}
