{
  "type": "Feature",
  "properties": {
    "iso:country":"US",
    "sg:address":"10 Church St",
    "sg:city":"Boylston",
    "sg:classifiers":[
        {
            "category":"Organizations",
            "subcategory":"Religious Organization",
            "type":"Services"
        }
    ],
    "sg:phone":"+1 508 869 2027",
    "sg:postcode":"01505",
    "sg:province":"MA",
    "sg:tags":[
        "church"
    ],
    "sg:website":"www.fcc-boylston.org",
    "wof:name":"First Congregational Church",
    "wof:placetype":"venue"
},
  "geometry": {"coordinates":[-71.73425400000001,42.352878],"type":"Point"}
}