{
  "type": "Feature",
  "properties": {
    "addr:full":"78 Main St Gloucester MA 01930",
    "addr:housenumber":"78",
    "addr:postcode":"01930",
    "addr:street":"Main St",
    "iso:country":"US",
    "sg:address":"78 Main St",
    "sg:city":"Gloucester",
    "sg:classifiers":[
        {
            "category":"Shopping",
            "subcategory":"Used Merchandise",
            "type":"Retail Goods"
        }
    ],
    "sg:phone":"+1 978 283 8806",
    "sg:postcode":"01930",
    "sg:province":"MA",
    "sg:tags":[
        "clothing"
    ],
    "wof:name":"Bananas",
    "wof:placetype":"venue"
},
  "geometry": {"coordinates":[-70.664709,42.612469],"type":"Point"}
}