{
  "type": "Feature",
  "properties": {
    "iso:country":"US",
    "sg:address":"400 Chestnut St",
    "sg:city":"Wilmington",
    "sg:classifiers":[
        {
            "category":"Building & Trades",
            "subcategory":"Construction",
            "type":"Services"
        }
    ],
    "sg:phone":"+1   ",
    "sg:postcode":"01887",
    "sg:province":"MA",
    "sg:tags":[
        "carpentry",
        "contractor"
    ],
    "wof:name":"Magee Thomas",
    "wof:placetype":"venue"
},
  "geometry": {"coordinates":[-71.16848400000001,42.518943],"type":"Point"}
}