{
  "type": "Feature",
  "properties": {
    "addr:full": "400 Chestnut St Wilmington MA 01887",
    "addr:housenumber": "400",
    "addr:postcode": "01887",
    "addr:street": "Chestnut St",
    "iso:country": "US",
    "sg:address": "400 Chestnut St",
    "sg:city": "Wilmington",
    "sg:classifiers": [
      {
        "category": "Building \u0026 Trades",
        "subcategory": "Construction",
        "type": "Services"
      }
    ],
    "sg:phone": "+1   ",
    "sg:postcode": "01887",
    "sg:province": "MA",
    "sg:tags": [
      "carpentry",
      "contractor"
    ],
    "wof:name": "Magee Thomas",
    "wof:placetype": "venue"
  },
  "geometry": {"coordinates":[-71.168484,42.518943],"type":"Point"}
}
