{
  "type": "Feature",
  "properties": {
    "iso:country":"US",
    "sg:address":"8 Lakeview Rd",
    "sg:city":"Millbury",
    "sg:classifiers":[
        {
            "category":"Manufacturing",
            "subcategory":"Tools & Machinery",
            "type":"Manufacturing & Wholesale Goods"
        }
    ],
    "sg:phone":"+1   ",
    "sg:postcode":"01527",
    "sg:province":"MA",
    "sg:tags":[
        "machining"
    ],
    "wof:name":"R & D Precision Machine Co",
    "wof:placetype":"venue"
},
  "geometry": {"coordinates":[-71.749988,42.218706],"type":"Point"}
}