{
  "type": "Feature",
  "properties": {
    "addr:full": "8 Lakeview Rd Millbury MA 01527",
    "addr:housenumber": "8",
    "addr:postcode": "01527",
    "addr:street": "Lakeview Rd",
    "iso:country": "US",
    "sg:address": "8 Lakeview Rd",
    "sg:city": "Millbury",
    "sg:classifiers": [
      {
        "category": "Manufacturing",
        "subcategory": "Tools \u0026 Machinery",
        "type": "Manufacturing \u0026 Wholesale Goods"
      }
    ],
    "sg:phone": "+1   ",
    "sg:postcode": "01527",
    "sg:province": "MA",
    "sg:tags": [
      "machining"
    ],
    "wof:name": "R \u0026 D Precision Machine Co",
    "wof:placetype": "venue"
  },
  "geometry": {"coordinates":[-71.749988,42.218706],"type":"Point"}
}
