{
  "type": "Feature",
  "properties": {
    "iso:country":"US",
    "sg:address":"21 Chestnut Hill Rd",
    "sg:city":"Chelmsford",
    "sg:classifiers":[
        {
            "category":"Shopping",
            "subcategory":"Gifts & Souvenirs",
            "type":"Retail Goods"
        }
    ],
    "sg:phone":"+1 978 256 9914",
    "sg:postcode":"01824",
    "sg:province":"MA",
    "sg:tags":[
        "announcement",
        "invitation"
    ],
    "wof:name":"Take It Personally",
    "wof:placetype":"venue"
},
  "geometry": {"coordinates":[-71.394454,42.592017],"type":"Point"}
}