{
  "type": "Feature",
  "properties": {
    "addr:full": "305 Walnut St Newtonville MA 02460",
    "addr:housenumber": "305",
    "addr:postcode": "02460",
    "addr:street": "Walnut St",
    "iso:country": "US",
    "sg:address": "305 Walnut St",
    "sg:city": "Newtonville",
    "sg:classifiers": [
      {
        "category": "Banks \u0026 Credit Unions",
        "subcategory": "Bank",
        "type": "Services"
      }
    ],
    "sg:phone": "+1 617 641 2022",
    "sg:postcode": "02460",
    "sg:province": "MA",
    "wof:name": "Citizens Bank",
    "wof:placetype": "venue"
  },
  "geometry": {"coordinates":[-71.207,42.350129],"type":"Point"}
}
