{
  "type": "Feature",
  "properties": {
    "iso:country":"US",
    "sg:address":"305 Walnut St",
    "sg:city":"Newtonville",
    "sg:classifiers":[
        {
            "category":"Banks & Credit Unions",
            "subcategory":"Bank",
            "type":"Services"
        }
    ],
    "sg:phone":"+1 617 641 2022",
    "sg:postcode":"02460",
    "sg:province":"MA",
    "wof:name":"Citizens Bank",
    "wof:placetype":"venue"
},
  "geometry": {"coordinates":[-71.20699999999999,42.350129],"type":"Point"}
}