{
  "type": "Feature",
  "properties": {
    "iso:country":"US",
    "sg:address":"476 Appleton St Ste 1",
    "sg:city":"Holyoke",
    "sg:classifiers":[
        {
            "category":"Building & Trades",
            "subcategory":"Pest Control",
            "type":"Services"
        }
    ],
    "sg:phone":"+1 413 538 9717",
    "sg:postcode":"01040",
    "sg:province":"MA",
    "sg:website":"http://www.womanshelter.org",
    "wof:name":"Womanshelter/Companeras, Inc.",
    "wof:placetype":"venue"
},
  "geometry": {"coordinates":[-72.617268,42.20892],"type":"Point"}
}