{
  "type": "Feature",
  "properties": {
    "iso:country":"US",
    "sg:address":"39 Pleasant St",
    "sg:city":"Waltham",
    "sg:classifiers":[
        {
            "category":"Professional",
            "subcategory":"Lawyer & Legal Services",
            "type":"Services"
        }
    ],
    "sg:phone":"+1 781 891 7014",
    "sg:postcode":"02452",
    "sg:province":"MA",
    "sg:tags":[
        "attorney",
        "practice"
    ],
    "wof:name":"Brian O'brien Pe",
    "wof:placetype":"venue"
},
  "geometry": {"coordinates":[-71.22774,42.378435],"type":"Point"}
}