{
  "type": "Feature",
  "properties": {
    "iso:country":"US",
    "sg:address":"16 Richardson Corner Rd",
    "sg:city":"Charlton",
    "sg:classifiers":[
        {
            "category":"Building & Trades",
            "subcategory":"Construction",
            "type":"Services"
        }
    ],
    "sg:phone":"+1 508 248 9885",
    "sg:postcode":"01507",
    "sg:province":"MA",
    "sg:tags":[
        "painter"
    ],
    "wof:name":"Superior House Painting",
    "wof:placetype":"venue"
},
  "geometry": {"coordinates":[-71.923103,42.138401],"type":"Point"}
}