{
  "type": "Feature",
  "properties": {
    "iso:country":"US",
    "sg:address":"1 Boston Pl",
    "sg:city":"Boston",
    "sg:classifiers":[
        {
            "category":"Professional",
            "type":"Services"
        }
    ],
    "sg:phone":"+1 617 619 3770",
    "sg:postcode":"02108",
    "sg:province":"MA",
    "sg:tags":[
        "establishment"
    ],
    "wof:name":"Challenger Systems",
    "wof:placetype":"venue"
},
  "geometry": {"coordinates":[-71.058386,42.358668],"type":"Point"}
}