{
  "type": "Feature",
  "properties": {
    "iso:country":"US",
    "sg:address":"24 Water St",
    "sg:city":"Holliston",
    "sg:classifiers":[
        {
            "category":"Building & Trades",
            "subcategory":"Landscaping Services",
            "type":"Services"
        }
    ],
    "sg:phone":"+1 508 893 6232",
    "sg:postcode":"01746",
    "sg:province":"MA",
    "sg:tags":[
        "designer",
        "landscape"
    ],
    "wof:name":"Kattman Corp",
    "wof:placetype":"venue"
},
  "geometry": {"coordinates":[-71.426546,42.19719],"type":"Point"}
}