{
  "type": "Feature",
  "properties": {
    "iso:country":"US",
    "sg:address":"401 River Rd",
    "sg:city":"Hudson",
    "sg:classifiers":[
        {
            "category":"Retail",
            "subcategory":"Auto Repair",
            "type":"Services"
        }
    ],
    "sg:phone":"+1 978 568 8864",
    "sg:postcode":"01749",
    "sg:province":"MA",
    "sg:tags":[
        "body",
        "automobile",
        "painting"
    ],
    "wof:name":"KAS Auto Body",
    "wof:placetype":"venue"
},
  "geometry": {"coordinates":[-71.595613,42.372063],"type":"Point"}
}