{
  "type": "Feature",
  "properties": {
    "addr:full": "792 Main St Cambridge MA 02139",
    "addr:housenumber": "792",
    "addr:postcode": "02139",
    "addr:street": "Main St",
    "iso:country": "US",
    "sg:address": "792 Main St",
    "sg:city": "Cambridge",
    "sg:classifiers": [
      {
        "category": "Restaurant",
        "type": "Food \u0026 Drink"
      }
    ],
    "sg:menulink": "http://www.allmenus.com/ma/cambridge/17787-royal-east/menu/",
    "sg:phone": "+1 617 661 1660",
    "sg:postcode": "02139",
    "sg:province": "MA",
    "sg:tags": [
      "asian",
      "chinese"
    ],
    "wof:name": "Royal East",
    "wof:placetype": "venue"
  },
  "geometry": {"coordinates":[-71.096934,42.363268],"type":"Point"}
}
