{
  "type": "Feature",
  "properties": {
    "iso:country":"US",
    "sg:address":"27 Industrial Ave",
    "sg:city":"Chelmsford",
    "sg:classifiers":[
        {
            "category":"Wholesale",
            "subcategory":"Office Equipment",
            "type":"Manufacturing & Wholesale Goods"
        }
    ],
    "sg:phone":"+1 978 256 6444",
    "sg:postcode":"01824",
    "sg:province":"MA",
    "sg:tags":[
        "machine",
        "mailing"
    ],
    "wof:name":"Rormscan",
    "wof:placetype":"venue"
},
  "geometry": {"coordinates":[-71.332911,42.596316],"type":"Point"}
}