{
  "type": "Feature",
  "properties": {
    "iso:country":"US",
    "sg:address":"27 Black Flats Rd",
    "sg:city":"Dennis",
    "sg:classifiers":[
        {
            "category":"Restaurant",
            "type":"Food & Drink"
        }
    ],
    "sg:phone":"+1 508 385 3003",
    "sg:postcode":"02638",
    "sg:province":"MA",
    "sg:tags":[
        "italian"
    ],
    "wof:name":"Rose's",
    "wof:placetype":"venue"
},
  "geometry": {"coordinates":[-70.214776,41.737609],"type":"Point"}
}