{
  "type": "Feature",
  "properties": {
    "addr:full": "100 Oak St Harwich MA 02645",
    "addr:housenumber": "100",
    "addr:postcode": "02645",
    "addr:street": "Oak St",
    "iso:country": "US",
    "sg:address": "100 Oak St",
    "sg:city": "Harwich",
    "sg:classifiers": [
      {
        "category": "Social Services",
        "type": "Services"
      }
    ],
    "sg:phone": "+1 508 430 7550",
    "sg:postcode": "02645",
    "sg:province": "MA",
    "sg:tags": [
      "on",
      "council",
      "aging"
    ],
    "wof:name": "Harwich Council On Aging",
    "wof:placetype": "venue"
  },
  "geometry": {"coordinates":[-70.069838,41.692013],"type":"Point"}
}
