{
  "type": "Feature",
  "properties": {
    "addr:full": "685 N Main St West Bridgewater MA 02379",
    "addr:housenumber": "685",
    "addr:postcode": "02379",
    "addr:street": "N Main St",
    "iso:country": "US",
    "sg:address": "685 N Main St",
    "sg:city": "West Bridgewater",
    "sg:classifiers": [
      {
        "category": "Professional",
        "subcategory": "Research",
        "type": "Services"
      }
    ],
    "sg:phone": "+1 508 580 3400",
    "sg:postcode": "02379",
    "sg:province": "MA",
    "sg:tags": [
      "environmental",
      "ecological"
    ],
    "wof:name": "Ramco Survey Stakes",
    "wof:placetype": "venue"
  },
  "geometry": {"coordinates":[-71.008845,42.03509],"type":"Point"}
}
