{
  "type": "Feature",
  "properties": {
    "iso:country":"US",
    "sg:address":"150 Main St",
    "sg:city":"Peabody",
    "sg:classifiers":[
        {
            "category":"Cinema",
            "subcategory":"Movie Rental",
            "type":"Entertainment"
        }
    ],
    "sg:phone":"+1 978 531 2921",
    "sg:postcode":"01960",
    "sg:province":"MA",
    "sg:tags":[
        "leasing",
        "video",
        "disc",
        "tape"
    ],
    "wof:name":"West Coast Video",
    "wof:placetype":"venue"
},
  "geometry": {"coordinates":[-70.920391,42.523121],"type":"Point"}
}