{
  "type": "Feature",
  "properties": {
    "addr:full": "114 Broadway Saugus MA 01906",
    "addr:housenumber": "114",
    "addr:postcode": "01906",
    "addr:street": "Broadway",
    "iso:country": "US",
    "sg:address": "114 Broadway",
    "sg:city": "Saugus",
    "sg:classifiers": [
      {
        "category": "Utilities",
        "subcategory": "Mobile Phone",
        "type": "Services"
      }
    ],
    "sg:phone": "+1 781 233 7676",
    "sg:postcode": "01906",
    "sg:province": "MA",
    "sg:tags": [
      "telephone",
      "cellular"
    ],
    "wof:name": "Sprint PCS",
    "wof:placetype": "venue"
  },
  "geometry": {"coordinates":[-71.016097,42.493835],"type":"Point"}
}
