{
  "type": "Feature",
  "properties": {
    "addr:full": "933 Pleasant St Somerset MA 02726",
    "addr:housenumber": "933",
    "addr:postcode": "02726",
    "addr:street": "Pleasant St",
    "iso:country": "US",
    "sg:address": "933 Pleasant St",
    "sg:city": "Somerset",
    "sg:classifiers": [
      {
        "category": "Utilities",
        "subcategory": "Telephone",
        "type": "Services"
      },
      {
        "category": "Shopping",
        "subcategory": "Mobile Phones",
        "type": "Retail Goods"
      },
      {
        "category": "Manufacturing",
        "subcategory": "Electronics",
        "type": "Manufacturing \u0026 Wholesale Goods"
      },
      {
        "category": "Shopping",
        "subcategory": "Computers \u0026 Home Electronics",
        "type": "Retail Goods"
      },
      {
        "category": "Communications",
        "type": "Services"
      }
    ],
    "sg:phone": "+1 508 674 3002",
    "sg:postcode": "02726",
    "sg:province": "MA",
    "sg:tags": [
      "sound",
      "television",
      "theater",
      "supply",
      "system",
      "equipment",
      "radio",
      "cellular",
      "telecommunications-equipment",
      "consumer",
      "store"
    ],
    "sg:website": "http://www.radioshack.com",
    "wof:name": "RadioShack",
    "wof:placetype": "venue"
  },
  "geometry": {"coordinates":[-71.125467,41.786211],"type":"Point"}
}
