{
  "type": "Feature",
  "properties": {
    "iso:country":"US",
    "sg:address":"214 Harvard St",
    "sg:city":"Brookline",
    "sg:classifiers":[
        {
            "category":"Education",
            "subcategory":"Dance Studio",
            "type":"Public Place"
        }
    ],
    "sg:phone":"+1 617 562 0550",
    "sg:postcode":"02446",
    "sg:province":"MA",
    "sg:tags":[
        "instruction",
        "dancing"
    ],
    "wof:name":"Mass Motion Dance Academy",
    "wof:placetype":"venue"
},
  "geometry": {"coordinates":[-71.12093,42.339729],"type":"Point"}
}