{
  "type": "Feature",
  "properties": {
    "addr:full": "91 Betts Rd Belmont MA 02478",
    "addr:housenumber": "91",
    "addr:postcode": "02478",
    "addr:street": "Betts Rd",
    "iso:country": "US",
    "sg:address": "91 Betts Rd",
    "sg:city": "Belmont",
    "sg:classifiers": [
      {
        "category": "Building \u0026 Trades",
        "subcategory": "Locksmith",
        "type": "Services"
      }
    ],
    "sg:phone": "+1 617 826 6132",
    "sg:postcode": "02478",
    "sg:province": "MA",
    "sg:tags": [
      "key"
    ],
    "wof:name": "Service All Emergencies Locksmith",
    "wof:placetype": "venue"
  },
  "geometry": {"coordinates":[-71.163519,42.383955],"type":"Point"}
}
