{
  "type": "Feature",
  "properties": {
    "iso:country":"US",
    "sg:address":"91 Betts Rd",
    "sg:city":"Belmont",
    "sg:classifiers":[
        {
            "category":"Building & Trades",
            "subcategory":"Locksmith",
            "type":"Services"
        }
    ],
    "sg:phone":"+1 617 826 6132",
    "sg:postcode":"02478",
    "sg:province":"MA",
    "sg:tags":[
        "key"
    ],
    "wof:name":"Service All Emergencies Locksmith",
    "wof:placetype":"venue"
},
  "geometry": {"coordinates":[-71.16351899999999,42.383955],"type":"Point"}
}