{
  "type": "Feature",
  "properties": {
    "iso:country":"US",
    "sg:address":"122 Sharon St",
    "sg:city":"Medford",
    "sg:classifiers":[
        {
            "category":"Building & Trades",
            "subcategory":"Locksmith",
            "type":"Services"
        }
    ],
    "sg:phone":"+1 781 443 7135",
    "sg:postcode":"02155",
    "sg:province":"MA",
    "sg:tags":[
        "key"
    ],
    "wof:name":"Fast Locksmith Service",
    "wof:placetype":"venue"
},
  "geometry": {"coordinates":[-71.134261,42.41761],"type":"Point"}
}