{
  "type": "Feature",
  "properties": {
    "addr:full": "73 Nicholas Rd Framingham MA 01701",
    "addr:housenumber": "73",
    "addr:postcode": "01701",
    "addr:street": "Nicholas Rd",
    "iso:country": "US",
    "sg:address": "73 Nicholas Rd",
    "sg:city": "Framingham",
    "sg:classifiers": [
      {
        "category": "Wholesale",
        "subcategory": "Vending Machines",
        "type": "Manufacturing \u0026 Wholesale Goods"
      }
    ],
    "sg:phone": "+1   ",
    "sg:postcode": "01701",
    "sg:province": "MA",
    "sg:tags": [
      "operator"
    ],
    "wof:name": "Metro West Vending",
    "wof:placetype": "venue"
  },
  "geometry": {"coordinates":[-71.405064,42.328376],"type":"Point"}
}
