{
  "type": "Feature",
  "properties": {
    "addr:full":"6 Lexington Ave Gloucester MA 01930",
    "addr:housenumber":"6",
    "addr:postcode":"01930",
    "addr:street":"Lexington Ave",
    "iso:country":"US",
    "sg:address":"6 Lexington Ave",
    "sg:city":"Gloucester",
    "sg:classifiers":[
        {
            "category":"Government",
            "subcategory":"Post Office",
            "type":"Public Place"
        }
    ],
    "sg:phone":"+1 978 000 1111",
    "sg:postcode":"01930",
    "sg:province":"MA",
    "sg:tags":[
        "postal",
        "us"
    ],
    "wof:name":"US Post Office",
    "wof:placetype":"venue"
},
  "geometry": {"coordinates":[-70.712074,42.576222],"type":"Point"}
}