{
  "type": "Feature",
  "properties": {
    "addr:full":"624 Gallivan Blvd Dorchester Center MA 02124",
    "addr:housenumber":"624",
    "addr:postcode":"02124",
    "addr:street":"Gallivan Blvd",
    "iso:country":"US",
    "sg:address":"624 Gallivan Blvd",
    "sg:city":"Dorchester Center",
    "sg:classifiers":[
        {
            "category":"Building & Trades",
            "subcategory":"Locksmith",
            "type":"Services"
        }
    ],
    "sg:phone":"+1 617 615 3240",
    "sg:postcode":"02124",
    "sg:province":"MA",
    "sg:tags":[
        "key"
    ],
    "wof:name":"A 24 Hour Emergency Locksmith",
    "wof:placetype":"venue"
},
  "geometry": {"coordinates":[-71.05043999999999,42.283493],"type":"Point"}
}