{
  "type": "Feature",
  "properties": {
    "addr:full":"5 Overdale Pkwy Hopedale MA 01747",
    "addr:housenumber":"5",
    "addr:postcode":"01747",
    "addr:street":"Overdale Pkwy",
    "iso:country":"US",
    "sg:address":"5 Overdale Pkwy",
    "sg:city":"Hopedale",
    "sg:classifiers":[
        {
            "category":"Real Estate",
            "subcategory":"Real Estate Agent",
            "type":"Services"
        }
    ],
    "sg:phone":"+1 508 478 9725",
    "sg:postcode":"01747",
    "sg:province":"MA",
    "wof:name":"Douglas Moore",
    "wof:placetype":"venue"
},
  "geometry": {"coordinates":[-71.560738,42.1343],"type":"Point"}
}