{
  "type": "Feature",
  "properties": {
    "iso:country":"US",
    "sg:address":"414 Park St",
    "sg:city":"West Springfield",
    "sg:classifiers":[
        {
            "category":"Wholesale",
            "subcategory":"Auto Parts",
            "type":"Manufacturing & Wholesale Goods"
        }
    ],
    "sg:phone":"+1 413 736 9881",
    "sg:postcode":"01089",
    "sg:province":"MA",
    "sg:tags":[
        "equipment",
        "towing"
    ],
    "wof:name":"All Star Towing",
    "wof:placetype":"venue"
},
  "geometry": {"coordinates":[-72.627084,42.101418],"type":"Point"}
}