{
  "type": "Feature",
  "properties": {
    "addr:full":"4 Man-Mar Dr Plainville MA 02762",
    "addr:housenumber":"4",
    "addr:postcode":"02762",
    "addr:street":"Man-Mar Dr",
    "iso:country":"US",
    "sg:address":"4 Man-Mar Dr",
    "sg:city":"Plainville",
    "sg:classifiers":[
        {
            "category":"Insurance",
            "subcategory":"Insurance Agent",
            "type":"Services"
        }
    ],
    "sg:phone":"+1 508 699 7634",
    "sg:postcode":"02762",
    "sg:province":"MA",
    "wof:name":"Capital Choice Financial Svc",
    "wof:placetype":"venue"
},
  "geometry": {"coordinates":[-71.308532,42.007664],"type":"Point"}
}