{
  "type": "Feature",
  "properties": {
    "addr:full":"21 Bancroft St Auburn MA 01501",
    "addr:housenumber":"21",
    "addr:postcode":"01501",
    "addr:street":"Bancroft St",
    "iso:country":"US",
    "sg:address":"21 Bancroft St",
    "sg:city":"Auburn",
    "sg:classifiers":[
        {
            "category":"Professional",
            "type":"Services"
        }
    ],
    "sg:phone":"+1   ",
    "sg:postcode":"01501",
    "sg:province":"MA",
    "wof:name":"Terrasphere Inc",
    "wof:placetype":"venue"
},
  "geometry": {"coordinates":[-71.82387,42.206964],"type":"Point"}
}