{
  "type": "Feature",
  "properties": {
    "iso:country":"US",
    "sg:address":"1 Park St",
    "sg:city":"Sterling",
    "sg:classifiers":[
        {
            "category":"Government",
            "subcategory":"Office",
            "type":"Public Place"
        }
    ],
    "sg:phone":"+1 978 422 3025",
    "sg:postcode":"01564",
    "sg:province":"MA",
    "sg:tags":[
        "city",
        "program",
        "health"
    ],
    "wof:name":"Sterling Town Board Of Health",
    "wof:placetype":"venue"
},
  "geometry": {"coordinates":[-71.742442,42.416937],"type":"Point"}
}