{
  "type": "Feature",
  "properties": {
    "addr:full":"18 Grove St Upton MA 01568",
    "addr:housenumber":"18",
    "addr:postcode":"01568",
    "addr:street":"Grove St",
    "iso:country":"US",
    "sg:address":"18 Grove St",
    "sg:city":"Upton",
    "sg:classifiers":[
        {
            "category":"Professional",
            "subcategory":"Business Services",
            "type":"Services"
        }
    ],
    "sg:phone":"+1   ",
    "sg:postcode":"01568",
    "sg:province":"MA",
    "wof:name":"Dutchman Enterprises Inc",
    "wof:placetype":"venue"
},
  "geometry": {"coordinates":[-71.602631,42.172536],"type":"Point"}
}