{
  "type": "Feature",
  "properties": {
    "iso:country":"US",
    "sg:address":"348 Park St Ste 101",
    "sg:city":"North Reading",
    "sg:classifiers":[
        {
            "category":"Professional",
            "subcategory":"Accounting & Tax Preparation",
            "type":"Services"
        }
    ],
    "sg:phone":"+1 978 664 3331",
    "sg:postcode":"01864",
    "sg:province":"MA",
    "sg:tags":[
        "accountant"
    ],
    "wof:name":"Deluca Joanne M CPA",
    "wof:placetype":"venue"
},
  "geometry": {"coordinates":[-71.108299,42.565201],"type":"Point"}
}