{
  "type": "Feature",
  "properties": {
    "addr:full": "44 Virginia Rd Needham Heights MA 02494",
    "addr:housenumber": "44",
    "addr:postcode": "02494",
    "addr:street": "Virginia Rd",
    "iso:country": "US",
    "sg:address": "44 Virginia Rd",
    "sg:city": "Needham Heights",
    "sg:classifiers": [
      {
        "category": "Shopping",
        "subcategory": "Clothing, Apparel, \u0026 Fashions",
        "type": "Retail Goods"
      }
    ],
    "sg:phone": "+1   ",
    "sg:postcode": "02494",
    "sg:province": "MA",
    "sg:tags": [
      "painted",
      "ready",
      "clo",
      "hand"
    ],
    "wof:name": "Prototype",
    "wof:placetype": "venue"
  },
  "geometry": {"coordinates":[-71.22312,42.294891],"type":"Point"}
}
