{
  "type": "Feature",
  "properties": {
    "addr:full": "250 Essex St Beverly MA 01915",
    "addr:housenumber": "250",
    "addr:postcode": "01915",
    "addr:street": "Essex St",
    "iso:country": "US",
    "sg:address": "250 Essex St",
    "sg:city": "Beverly",
    "sg:classifiers": [
      {
        "category": "Building \u0026 Trades",
        "subcategory": "Construction",
        "type": "Services"
      }
    ],
    "sg:phone": "+1   ",
    "sg:postcode": "01915",
    "sg:province": "MA",
    "sg:tags": [
      "house"
    ],
    "wof:name": "Marshall Const Co",
    "wof:placetype": "venue"
  },
  "geometry": {"coordinates":[-70.862766,42.566115],"type":"Point"}
}
