{
  "type": "Feature",
  "properties": {
    "addr:full": "26 Dean St Taunton MA 02780",
    "addr:housenumber": "26",
    "addr:postcode": "02780",
    "addr:street": "Dean St",
    "iso:country": "US",
    "sg:address": "26 Dean St",
    "sg:city": "Taunton",
    "sg:classifiers": [
      {
        "category": "Professional",
        "subcategory": "Lawyer \u0026 Legal Services",
        "type": "Services"
      }
    ],
    "sg:phone": "+1 508 824 7000",
    "sg:postcode": "02780",
    "sg:province": "MA",
    "sg:tags": [
      "attorney"
    ],
    "wof:name": "Fagan \u0026 Goldrick",
    "wof:placetype": "venue"
  },
  "geometry": {"coordinates":[-71.081953,41.903813],"type":"Point"}
}
