{
  "type": "Feature",
  "properties": {
    "addr:full":"1 Deaconess Rd Boston MA 02215",
    "addr:housenumber":"1",
    "addr:postcode":"02215",
    "addr:street":"Deaconess Rd",
    "iso:country":"US",
    "sg:address":"1 Deaconess Rd",
    "sg:city":"Boston",
    "sg:classifiers":[
        {
            "category":"Health Services",
            "subcategory":"Hospital",
            "type":"Services"
        }
    ],
    "sg:phone":"+1 617 632 0991",
    "sg:postcode":"02215",
    "sg:province":"MA",
    "wof:name":"Deaconess Hospital",
    "wof:placetype":"venue"
},
  "geometry": {"coordinates":[-71.108704,42.3381],"type":"Point"}
}