{
  "type": "Feature",
  "properties": {
    "addr:full": "271 West St Uxbridge MA 01569",
    "addr:housenumber": "271",
    "addr:postcode": "01569",
    "addr:street": "West St",
    "iso:country": "US",
    "sg:address": "271 West St",
    "sg:city": "Uxbridge",
    "sg:classifiers": [
      {
        "category": "Manufacturing",
        "subcategory": "Wood Products",
        "type": "Manufacturing \u0026 Wholesale Goods"
      }
    ],
    "sg:phone": "+1 508 278 5687",
    "sg:postcode": "01569",
    "sg:province": "MA",
    "sg:tags": [
      "millwork-wholesale",
      "millwork",
      "manufacturer"
    ],
    "wof:name": "Mechanically Designed Wood",
    "wof:placetype": "venue"
  },
  "geometry": {"coordinates":[-71.671658,42.062401],"type":"Point"}
}
