{
  "type": "Feature",
  "properties": {
    "addr:full": "9 Jewel Rd Holbrook MA 02343",
    "addr:housenumber": "9",
    "addr:postcode": "02343",
    "addr:street": "Jewel Rd",
    "iso:country": "US",
    "sg:address": "9 Jewel Rd",
    "sg:city": "Holbrook",
    "sg:classifiers": [
      {
        "category": "Government",
        "subcategory": "Office",
        "type": "Public Place"
      }
    ],
    "sg:phone": "+1 781 767 4617",
    "sg:postcode": "02343",
    "sg:province": "MA",
    "sg:tags": [
      "city",
      "resource",
      "human"
    ],
    "wof:name": "Council On Aging",
    "wof:placetype": "venue"
  },
  "geometry": {"coordinates":[-71.00673,42.155702],"type":"Point"}
}
