{
  "type": "Feature",
  "properties": {
    "addr:full":"113 Macarthur Dr New Bedford MA 02740",
    "addr:housenumber":"113",
    "addr:postcode":"02740",
    "addr:street":"Macarthur Dr",
    "iso:country":"US",
    "sg:address":"113 Macarthur Dr",
    "sg:city":"New Bedford",
    "sg:classifiers":[
        {
            "category":"Professional",
            "type":"Services"
        }
    ],
    "sg:phone":"+1   ",
    "sg:postcode":"02740",
    "sg:province":"MA",
    "wof:name":"Arnies Fisheries Inc",
    "wof:placetype":"venue"
},
  "geometry": {"coordinates":[-70.92146200000001,41.628327],"type":"Point"}
}