{
  "type": "Feature",
  "properties": {
    "iso:country":"US",
    "sg:address":"11 Ray Ave",
    "sg:city":"Burlington",
    "sg:classifiers":[
        {
            "category":"Building & Trades",
            "subcategory":"Plumbing",
            "type":"Services"
        }
    ],
    "sg:phone":"+1 781 273 1835",
    "sg:postcode":"01803",
    "sg:province":"MA",
    "sg:tags":[
        "conditioning",
        "air",
        "system",
        "contractor"
    ],
    "sg:website":"www.grinnellmech.com",
    "wof:name":"Grinnell Mechanical Inc",
    "wof:placetype":"venue"
},
  "geometry": {"coordinates":[-71.184495,42.482602],"type":"Point"}
}