{
  "type": "Feature",
  "properties": {
    "addr:full":"15 Marthas Way Franklin MA 02038",
    "addr:housenumber":"15",
    "addr:postcode":"02038",
    "addr:street":"Marthas Way",
    "iso:country":"US",
    "sg:address":"15 Marthas Way",
    "sg:city":"Franklin",
    "sg:classifiers":[
        {
            "category":"Professional",
            "subcategory":"Engineering",
            "type":"Services"
        }
    ],
    "sg:phone":"+1 508 541 8410",
    "sg:postcode":"02038",
    "sg:province":"MA",
    "sg:tags":[
        "consulting",
        "engineer"
    ],
    "wof:name":"A & A Engineering Inc",
    "wof:placetype":"venue"
},
  "geometry": {"coordinates":[-71.37676,42.094971],"type":"Point"}
}