{
  "type": "Feature",
  "properties": {
    "addr:full":"22 Truman Ct Carver MA 02330",
    "addr:housenumber":"22",
    "addr:postcode":"02330",
    "addr:street":"Truman Ct",
    "iso:country":"US",
    "sg:address":"22 Truman Ct",
    "sg:city":"Carver",
    "sg:classifiers":[
        {
            "category":"Professional",
            "subcategory":"Business Services",
            "type":"Services"
        }
    ],
    "sg:phone":"+1   ",
    "sg:postcode":"02330",
    "sg:province":"MA",
    "wof:name":"F1rst Computer Sales",
    "wof:placetype":"venue"
},
  "geometry": {"coordinates":[-70.73150699999999,41.833556],"type":"Point"}
}