{
  "type": "Feature",
  "properties": {
    "iso:country":"US",
    "sg:address":"23 Walkers Brook Dr",
    "sg:city":"Reading",
    "sg:classifiers":[
        {
            "category":"Professional",
            "subcategory":"Computer Services",
            "type":"Services"
        }
    ],
    "sg:phone":"+1 781 944 0870",
    "sg:postcode":"01867",
    "sg:province":"MA",
    "sg:tags":[
        "consultant",
        "designer"
    ],
    "wof:name":"RSD Assoc Inc",
    "wof:placetype":"venue"
},
  "geometry": {"coordinates":[-71.094887,42.519564],"type":"Point"}
}