{
  "type": "Feature",
  "properties": {
    "addr:full": "131 Washington St Auburn MA 01501",
    "addr:housenumber": "131",
    "addr:postcode": "01501",
    "addr:street": "Washington St",
    "iso:country": "US",
    "sg:address": "131 Washington St",
    "sg:city": "Auburn",
    "sg:classifiers": [
      {
        "category": "Shopping",
        "subcategory": "Used Merchandise",
        "type": "Retail Goods"
      },
      {
        "category": "Home \u0026 Garden",
        "subcategory": "Home Furnishings",
        "type": "Retail Goods"
      }
    ],
    "sg:phone": "+1 508 753 4935",
    "sg:postcode": "01501",
    "sg:province": "MA",
    "sg:tags": [
      "stove",
      "wood",
      "burning"
    ],
    "wof:name": "Ye Olde Stove Shoppe \u0026 Antq",
    "wof:placetype": "venue"
  },
  "geometry": {"coordinates":[-71.805537,42.212407],"type":"Point"}
}
