{
  "type": "Feature",
  "properties": {
    "addr:full":"1000 Cambridge St Cambridge MA 02141",
    "addr:housenumber":"1000",
    "addr:postcode":"02141",
    "addr:street":"Cambridge St",
    "iso:country":"US",
    "sg:address":"1000 Cambridge St",
    "sg:city":"Cambridge",
    "sg:classifiers":[
        {
            "category":"Professional",
            "subcategory":"Lawyer & Legal Services",
            "type":"Services"
        }
    ],
    "sg:phone":"+1 617 868 7005",
    "sg:postcode":"02141",
    "sg:province":"MA",
    "wof:name":"Crovo M Delacy Attorney",
    "wof:placetype":"venue"
},
  "geometry": {"coordinates":[-71.093739,42.372796],"type":"Point"}
}