{
  "type": "Feature",
  "properties": {
    "iso:country":"US",
    "sg:address":"27 Chestnut St",
    "sg:city":"North Reading",
    "sg:classifiers":[
        {
            "category":"Building & Trades",
            "subcategory":"Construction",
            "type":"Services"
        }
    ],
    "sg:phone":"+1 978 664 9255",
    "sg:postcode":"01864",
    "sg:province":"MA",
    "sg:tags":[
        "general",
        "contractor"
    ],
    "wof:name":"J J Gallant Inc",
    "wof:placetype":"venue"
},
  "geometry": {"coordinates":[-71.069711,42.56359],"type":"Point"}
}