{
  "type": "Feature",
  "properties": {
    "addr:full":"69 Haverhill Rd Amesbury MA 01913",
    "addr:housenumber":"69",
    "addr:postcode":"01913",
    "addr:street":"Haverhill Rd",
    "iso:country":"US",
    "sg:address":"69 Haverhill Rd",
    "sg:city":"Amesbury",
    "sg:classifiers":[
        {
            "category":"Personal",
            "type":"Services"
        },
        {
            "category":"Arena",
            "subcategory":"Sports Club",
            "type":"Entertainment"
        }
    ],
    "sg:phone":"+1 978 388 4636",
    "sg:postcode":"01913",
    "sg:province":"MA",
    "sg:tags":[
        "trainer",
        "consultant",
        "physical",
        "health",
        "fitness"
    ],
    "sg:website":"http://www.pfgym.com",
    "wof:name":"Planet Fitness",
    "wof:placetype":"venue"
},
  "geometry": {"coordinates":[-70.948227,42.841881],"type":"Point"}
}