{
  "type": "Feature",
  "properties": {
    "addr:full":"419 Main St Sturbridge MA 01566",
    "addr:housenumber":"419",
    "addr:postcode":"01566",
    "addr:street":"Main St",
    "iso:country":"US",
    "sg:address":"419 Main St",
    "sg:city":"Sturbridge",
    "sg:classifiers":[
        {
            "category":"Shopping",
            "subcategory":"Gifts & Souvenirs",
            "type":"Retail Goods"
        }
    ],
    "sg:phone":"+1 508 347 3493",
    "sg:postcode":"01566",
    "sg:province":"MA",
    "sg:tags":[
        "shop"
    ],
    "sg:website":"www.basketville.com",
    "wof:name":"Basketville Of Sturbridge",
    "wof:placetype":"venue"
},
  "geometry": {"coordinates":[-72.097723,42.112378],"type":"Point"}
}