{
  "type": "Feature",
  "properties": {
    "iso:country":"US",
    "sg:address":"692 Quincy Shore Dr",
    "sg:city":"Quincy",
    "sg:classifiers":[
        {
            "category":"Organizations",
            "subcategory":"Community Association",
            "type":"Services"
        }
    ],
    "sg:phone":"+1 617 472 9796",
    "sg:postcode":"02170",
    "sg:province":"MA",
    "sg:tags":[
        "marina",
        "club"
    ],
    "wof:name":"Wollaston Yacht Club",
    "wof:placetype":"venue"
},
  "geometry": {"coordinates":[-71.013018,42.277927],"type":"Point"}
}