{
  "type": "Feature",
  "properties": {
    "addr:full": "276 Nantasket Ave Hull MA 02045",
    "addr:housenumber": "276",
    "addr:postcode": "02045",
    "addr:street": "Nantasket Ave",
    "iso:country": "US",
    "sg:address": "276 Nantasket Ave",
    "sg:city": "Hull",
    "sg:classifiers": [
      {
        "category": "Restaurant",
        "type": "Food \u0026 Drink"
      }
    ],
    "sg:phone": "+1 781 925 2007",
    "sg:postcode": "02045",
    "sg:province": "MA",
    "sg:tags": [
      "grill",
      "american",
      "bar"
    ],
    "wof:name": "Barefoot Bob's",
    "wof:placetype": "venue"
  },
  "geometry": {"coordinates":[-70.860704,42.273668],"type":"Point"}
}
