{
  "type": "Feature",
  "properties": {
    "iso:country":"US",
    "sg:address":"276 Nantasket Ave",
    "sg:city":"Hull",
    "sg:classifiers":[
        {
            "category":"Restaurant",
            "type":"Food & Drink"
        }
    ],
    "sg:phone":"+1 781 925 2007",
    "sg:postcode":"02045",
    "sg:province":"MA",
    "sg:tags":[
        "grill",
        "american",
        "bar"
    ],
    "wof:name":"Barefoot Bob's",
    "wof:placetype":"venue"
},
  "geometry": {"coordinates":[-70.860704,42.273668],"type":"Point"}
}