{
  "type": "Feature",
  "properties": {
    "iso:country":"US",
    "sg:address":"222 Cedar St",
    "sg:city":"Somerville",
    "sg:classifiers":[
        {
            "category":"Professional",
            "subcategory":"Art Services",
            "type":"Services"
        }
    ],
    "sg:phone":"+1 617 628 9122",
    "sg:postcode":"02145",
    "sg:province":"MA",
    "sg:tags":[
        "commercial",
        "graphic",
        "design",
        "designer"
    ],
    "wof:name":"Filosi Design Inc",
    "wof:placetype":"venue"
},
  "geometry": {"coordinates":[-71.109493,42.396349],"type":"Point"}
}