{
  "type": "Feature",
  "properties": {
    "addr:full": "7 Plenty St Billerica MA 01821",
    "addr:housenumber": "7",
    "addr:postcode": "01821",
    "addr:street": "Plenty St",
    "iso:country": "US",
    "sg:address": "7 Plenty St",
    "sg:city": "Billerica",
    "sg:classifiers": [
      {
        "category": "Communications",
        "subcategory": "Film \u0026 Video Production",
        "type": "Services"
      },
      {
        "category": "Communications",
        "subcategory": "Television Station",
        "type": "Services"
      }
    ],
    "sg:phone": "+1 978 663 7825",
    "sg:postcode": "01821",
    "sg:province": "MA",
    "sg:tags": [
      "companies-film",
      "producer",
      "tv",
      "program",
      "radio",
      "distributor"
    ],
    "wof:name": "Plenty Street Productions",
    "wof:placetype": "venue"
  },
  "geometry": {"coordinates":[-71.270233,42.540031],"type":"Point"}
}
