{
  "type": "Feature",
  "properties": {
    "addr:full":"126 Princeton St Boston MA 02128",
    "addr:housenumber":"126",
    "addr:postcode":"02128",
    "addr:street":"Princeton St",
    "iso:country":"US",
    "sg:address":"126 Princeton St",
    "sg:city":"Boston",
    "sg:classifiers":[
        {
            "category":"Professional",
            "subcategory":"Business Services",
            "type":"Services"
        }
    ],
    "sg:phone":"+1 617 569 9885",
    "sg:postcode":"02128",
    "sg:province":"MA",
    "sg:tags":[
        "consultant",
        "publishing"
    ],
    "wof:name":"Princeton Press",
    "wof:placetype":"venue"
},
  "geometry": {"coordinates":[-71.03484,42.378024],"type":"Point"}
}