{
  "type": "Feature",
  "properties": {
    "iso:country":"US",
    "sg:address":"140 Clarendon St Ste 304",
    "sg:city":"Boston",
    "sg:classifiers":[
        {
            "category":"Professional",
            "subcategory":"Business Services",
            "type":"Services"
        }
    ],
    "sg:phone":"+1 617 585 5730",
    "sg:postcode":"02116",
    "sg:province":"MA",
    "sg:tags":[
        "organizing",
        "services-household"
    ],
    "sg:website":"http://www.apmsolutions.com",
    "wof:name":"Asset Performance Management, Inc.",
    "wof:placetype":"venue"
},
  "geometry": {"coordinates":[-71.074364,42.34893],"type":"Point"}
}