{
  "type": "Feature",
  "properties": {
    "iso:country":"US",
    "sg:address":"14 Oak Ridge Dr W",
    "sg:city":"Brockton",
    "sg:classifiers":[
        {
            "category":"Insurance",
            "subcategory":"Hazard Insurance",
            "type":"Services"
        }
    ],
    "sg:phone":"+1 508 583 7750",
    "sg:postcode":"02301",
    "sg:province":"MA",
    "sg:tags":[
        "commercial",
        "business"
    ],
    "wof:name":"Insurance Telemarketing Service",
    "wof:placetype":"venue"
},
  "geometry": {"coordinates":[-71.037261,42.098142],"type":"Point"}
}