{
  "type": "Feature",
  "properties": {
    "addr:full": "102 Center St Hyannis MA 02601",
    "addr:housenumber": "102",
    "addr:postcode": "02601",
    "addr:street": "Center St",
    "iso:country": "US",
    "sg:address": "102 Center St",
    "sg:city": "Hyannis",
    "sg:classifiers": [
      {
        "category": "Personal",
        "subcategory": "Beauty Salon",
        "type": "Services"
      }
    ],
    "sg:phone": "+1 508 778 6979",
    "sg:postcode": "02601",
    "sg:province": "MA",
    "wof:name": "Family Fun Cuts Ii",
    "wof:placetype": "venue"
  },
  "geometry": {"coordinates":[-70.282822,41.656658],"type":"Point"}
}
