{
  "type": "Feature",
  "properties": {
    "addr:full":"336 Stockbridge Rd Great Barrington MA 01230",
    "addr:housenumber":"336",
    "addr:postcode":"01230",
    "addr:street":"Stockbridge Rd",
    "iso:country":"US",
    "sg:address":"336 Stockbridge Rd",
    "sg:city":"Great Barrington",
    "sg:classifiers":[
        {
            "category":"Home & Garden",
            "subcategory":"Furniture",
            "type":"Retail Goods"
        }
    ],
    "sg:phone":"+1 413 644 9094",
    "sg:postcode":"01230",
    "sg:province":"MA",
    "sg:tags":[
        "mattress"
    ],
    "wof:name":"Sleepy's",
    "wof:placetype":"venue"
},
  "geometry": {"coordinates":[-73.3458,42.209732],"type":"Point"}
}