{
  "type": "Feature",
  "properties": {
    "addr:full":"283 Commercial St Provincetown MA 02657",
    "addr:housenumber":"283",
    "addr:postcode":"02657",
    "addr:street":"Commercial St",
    "iso:country":"US",
    "sg:address":"283 Commercial St",
    "sg:city":"Provincetown",
    "sg:classifiers":[
        {
            "category":"Shopping",
            "type":"Retail Goods"
        }
    ],
    "sg:phone":"+1 508 487 4200",
    "sg:postcode":"02657",
    "sg:province":"MA",
    "sg:tags":[
        "art",
        "gallery",
        "dealer"
    ],
    "wof:name":"Joey Mars Gallery",
    "wof:placetype":"venue"
},
  "geometry": {"coordinates":[-70.186567,42.05131],"type":"Point"}
}