{
  "type": "Feature",
  "properties": {
    "addr:full": "430 Broadway Revere MA 02151",
    "addr:housenumber": "430",
    "addr:postcode": "02151",
    "addr:street": "Broadway",
    "atp:label": "WALGREENS #10824, 430 Broadway Revere MA US",
    "atp:similarity": 3.9818339347839355,
    "iso:country": "US",
    "ovtr:label": "Walgreens, 430 Broadway Revere MA US",
    "ovtr:similarity": 2.982422113418579,
    "sg:address": "430 Broadway",
    "sg:city": "Revere",
    "sg:classifiers": [
      {
        "category": "Shopping",
        "subcategory": "Pharmacy",
        "type": "Retail Goods"
      }
    ],
    "sg:phone": "+1 781 289 3607",
    "sg:postcode": "02151",
    "sg:province": "MA",
    "sg:tags": [
      "drugstore"
    ],
    "sg:website": "walgreens.com",
    "wof:name": "Walgreens",
    "wof:placetype": "venue"
  },
  "geometry": {"coordinates":[-71.012576,42.411071],"type":"Point"}
}
