{
  "type": "Feature",
  "properties": {
    "addr:full":"7 Abenaki St Hubbardston MA 01452",
    "addr:housenumber":"7",
    "addr:postcode":"01452",
    "addr:street":"Abenaki St",
    "iso:country":"US",
    "sg:address":"7 Abenaki St",
    "sg:city":"Hubbardston",
    "sg:classifiers":[
        {
            "category":"Building & Trades",
            "subcategory":"Construction",
            "type":"Services"
        }
    ],
    "sg:phone":"+1 978 928 4795",
    "sg:postcode":"01452",
    "sg:province":"MA",
    "sg:tags":[
        "restoration",
        "cleaning",
        "patio",
        "deck"
    ],
    "wof:name":"Rainbow Floor Maintenance",
    "wof:placetype":"venue"
},
  "geometry": {"coordinates":[-71.947574,42.475812],"type":"Point"}
}