{
  "type": "Feature",
  "properties": {
    "addr:full": "990 Pleasant St Brockton MA 02301",
    "addr:housenumber": "990",
    "addr:postcode": "02301",
    "addr:street": "Pleasant St",
    "iso:country": "US",
    "ovtr:label": "Perron Family Chiropractic, 990 Pleasant St Brockton MA US",
    "ovtr:similarity": 1.8274149894714355,
    "sg:address": "990 Pleasant St",
    "sg:city": "Brockton",
    "sg:classifiers": [
      {
        "category": "Health Services",
        "subcategory": "Chiropractor",
        "type": "Services"
      }
    ],
    "sg:phone": "+1 508 588 1300",
    "sg:postcode": "02301",
    "sg:province": "MA",
    "sg:website": "www.perronchiropractic.com",
    "wof:name": "Perron Family Chiropractic",
    "wof:placetype": "venue"
  },
  "geometry": {"coordinates":[-71.059842,42.08806],"type":"Point"}
}
