{
  "type": "Feature",
  "properties": {
    "addr:full":"139 Winthrop Rd Brookline MA 02445",
    "addr:housenumber":"139",
    "addr:postcode":"02445",
    "addr:street":"Winthrop Rd",
    "iso:country":"US",
    "sg:address":"139 Winthrop Rd",
    "sg:city":"Brookline",
    "sg:classifiers":[
        {
            "category":"Building & Trades",
            "subcategory":"Plumbing",
            "type":"Services"
        }
    ],
    "sg:phone":"+1   ",
    "sg:postcode":"02445",
    "sg:province":"MA",
    "sg:tags":[
        "contractor"
    ],
    "wof:name":"Zack AA Plumbing",
    "wof:placetype":"venue"
},
  "geometry": {"coordinates":[-71.13297,42.33712],"type":"Point"}
}