{
  "type": "Feature",
  "properties": {
    "addr:full":"262 Kenrick St Newton MA 02458",
    "addr:housenumber":"262",
    "addr:postcode":"02458",
    "addr:street":"Kenrick St",
    "iso:country":"US",
    "sg:address":"262 Kenrick St",
    "sg:city":"Newton",
    "sg:classifiers":[
        {
            "category":"Professional",
            "subcategory":"Business Services",
            "type":"Services"
        }
    ],
    "sg:phone":"+1 617 527 3152",
    "sg:postcode":"02458",
    "sg:province":"MA",
    "wof:name":"Lynn K Cooper",
    "wof:placetype":"venue"
},
  "geometry": {"coordinates":[-71.17245699999999,42.346543],"type":"Point"}
}