{
  "type": "Feature",
  "properties": {
    "iso:country":"US",
    "sg:address":"224 Dedham St",
    "sg:city":"Norfolk",
    "sg:classifiers":[
        {
            "category":"Shopping",
            "subcategory":"Clothing, Apparel, & Fashions",
            "type":"Retail Goods"
        }
    ],
    "sg:phone":"+1 508 384 2200",
    "sg:postcode":"02056",
    "sg:province":"MA",
    "wof:name":"Kaleidoscope Kids",
    "wof:placetype":"venue"
},
  "geometry": {"coordinates":[-71.296036,42.093413],"type":"Point"}
}