{
  "type": "Feature",
  "properties": {
    "addr:full": "15 Leonard St Belmont MA 02478",
    "addr:housenumber": "15",
    "addr:postcode": "02478",
    "addr:street": "Leonard St",
    "iso:country": "US",
    "sg:address": "15 Leonard St",
    "sg:city": "Belmont",
    "sg:classifiers": [
      {
        "category": "Real Estate",
        "subcategory": "Real Estate Agent",
        "type": "Services"
      }
    ],
    "sg:phone": "+1 617 484 1043",
    "sg:postcode": "02478",
    "sg:province": "MA",
    "wof:name": "Ingram Realty Co",
    "wof:placetype": "venue"
  },
  "geometry": {"coordinates":[-71.175596,42.396613],"type":"Point"}
}
