{
  "type": "Feature",
  "properties": {
    "addr:full":"34 Davenport Rd Plymouth MA 02360",
    "addr:housenumber":"34",
    "addr:postcode":"02360",
    "addr:street":"Davenport Rd",
    "iso:country":"US",
    "sg:address":"34 Davenport Rd",
    "sg:city":"Plymouth",
    "sg:classifiers":[
        {
            "category":"Building & Trades",
            "subcategory":"Construction",
            "type":"Services"
        }
    ],
    "sg:phone":"+1   ",
    "sg:postcode":"02360",
    "sg:province":"MA",
    "sg:tags":[
        "contractor"
    ],
    "wof:name":"Pros Masonary",
    "wof:placetype":"venue"
},
  "geometry": {"coordinates":[-70.56583500000001,41.897721],"type":"Point"}
}