{
  "type": "Feature",
  "properties": {
    "addr:full": "20 Shedd Ln Chelmsford MA 01824",
    "addr:housenumber": "20",
    "addr:postcode": "01824",
    "addr:street": "Shedd Ln",
    "iso:country": "US",
    "sg:address": "20 Shedd Ln",
    "sg:city": "Chelmsford",
    "sg:classifiers": [
      {
        "category": "Health Services",
        "subcategory": "Doctor",
        "type": "Services"
      },
      {
        "category": "Health Services",
        "subcategory": "Hospital",
        "type": "Services"
      }
    ],
    "sg:phone": "+1 978 452 7202",
    "sg:postcode": "01824",
    "sg:province": "MA",
    "sg:tags": [
      "consultant",
      "medical",
      "practice",
      "nursing",
      "home"
    ],
    "wof:name": "Medpharm Consulting Solutions",
    "wof:placetype": "venue"
  },
  "geometry": {"coordinates":[-71.305134,42.604971],"type":"Point"}
}
