{
  "type": "Feature",
  "properties": {
    "iso:country":"US",
    "sg:address":"481 Wilbur Ave",
    "sg:city":"Somerset",
    "sg:classifiers":[
        {
            "category":"Wholesale",
            "subcategory":"Machinery & Supplies",
            "type":"Manufacturing & Wholesale Goods"
        }
    ],
    "sg:phone":"+1 508 730 2342",
    "sg:postcode":"02725",
    "sg:province":"MA",
    "sg:tags":[
        "equipment",
        "material",
        "handling"
    ],
    "wof:name":"Industrial Fleet Svc",
    "wof:placetype":"venue"
},
  "geometry": {"coordinates":[-71.16744300000001,41.720115],"type":"Point"}
}