{
  "type": "Feature",
  "properties": {
    "addr:full": "116 Beech St Belmont MA 02478",
    "addr:housenumber": "116",
    "addr:postcode": "02478",
    "addr:street": "Beech St",
    "iso:country": "US",
    "sg:address": "116 Beech St",
    "sg:city": "Belmont",
    "sg:classifiers": [
      {
        "category": "Professional",
        "subcategory": "Lawyer \u0026 Legal Services",
        "type": "Services"
      }
    ],
    "sg:phone": "+1 617 484 0007",
    "sg:postcode": "02478",
    "sg:province": "MA",
    "sg:tags": [
      "attorney"
    ],
    "wof:name": "Ananian \u0026 Rodibaugh",
    "wof:placetype": "venue"
  },
  "geometry": {"coordinates":[-71.184945,42.385267],"type":"Point"}
}
