{
  "type": "Feature",
  "properties": {
    "iso:country":"US",
    "sg:address":"116 Beech St",
    "sg:city":"Belmont",
    "sg:classifiers":[
        {
            "category":"Professional",
            "subcategory":"Lawyer & Legal Services",
            "type":"Services"
        }
    ],
    "sg:phone":"+1 617 484 0007",
    "sg:postcode":"02478",
    "sg:province":"MA",
    "sg:tags":[
        "attorney"
    ],
    "wof:name":"Ananian & Rodibaugh",
    "wof:placetype":"venue"
},
  "geometry": {"coordinates":[-71.184945,42.385267],"type":"Point"}
}