{
  "type": "Feature",
  "properties": {
    "addr:full": "41 Montvale Ave Ste 550 Stoneham MA 02180",
    "addr:housenumber": "41",
    "addr:postcode": "02180",
    "addr:street": "Montvale Ave Ste 550",
    "iso:country": "US",
    "sg:address": "41 Montvale Ave Ste 550",
    "sg:city": "Stoneham",
    "sg:classifiers": [
      {
        "category": "Health Services",
        "subcategory": "Doctor",
        "type": "Services"
      }
    ],
    "sg:phone": "+1 781 224 5800",
    "sg:postcode": "02180",
    "sg:province": "MA",
    "wof:name": "Hallmark Health Cancer Ctr",
    "wof:placetype": "venue"
  },
  "geometry": {"coordinates":[-71.103772,42.482235],"type":"Point"}
}
