{
  "type": "Feature",
  "properties": {
    "iso:country":"US",
    "sg:address":"475 Washington St",
    "sg:city":"Wellesley",
    "sg:classifiers":[
        {
            "category":"Shopping",
            "subcategory":"Bicycles & Sporting Goods",
            "type":"Retail Goods"
        }
    ],
    "sg:phone":"+1 781 235 6669",
    "sg:postcode":"02482",
    "sg:province":"MA",
    "sg:tags":[
        "equipment",
        "tennis",
        "supply"
    ],
    "wof:name":"St Moritz Sports",
    "wof:placetype":"venue"
},
  "geometry": {"coordinates":[-71.287059,42.301554],"type":"Point"}
}