{
  "type": "Feature",
  "properties": {
    "iso:country":"US",
    "sg:address":"112 Main St",
    "sg:city":"Wareham",
    "sg:classifiers":[
        {
            "category":"Health Services",
            "subcategory":"Doctor",
            "type":"Services"
        }
    ],
    "sg:phone":"+1 508 291 1300",
    "sg:postcode":"02571",
    "sg:province":"MA",
    "sg:tags":[
        "throat",
        "physician",
        "surgeon",
        "ear",
        "nose"
    ],
    "wof:name":"Northeast Ear Nose & Throat",
    "wof:placetype":"venue"
},
  "geometry": {"coordinates":[-70.7136,41.756901],"type":"Point"}
}