{
  "type": "Feature",
  "properties": {
    "iso:country":"US",
    "sg:address":"150 High St",
    "sg:city":"Bridgewater",
    "sg:classifiers":[
        {
            "category":"Organizations",
            "subcategory":"Community Association",
            "type":"Services"
        }
    ],
    "sg:phone":"+1 508 697 9872",
    "sg:postcode":"02324",
    "sg:province":"MA",
    "sg:tags":[
        "club"
    ],
    "wof:name":"Lincoln Athletic Assn",
    "wof:placetype":"venue"
},
  "geometry": {"coordinates":[-70.98112399999999,42.003174],"type":"Point"}
}