{
  "type": "Feature",
  "properties": {
    "iso:country":"US",
    "sg:address":"10 Thistle Ln",
    "sg:city":"Westford",
    "sg:classifiers":[
        {
            "category":"Communications",
            "type":"Services"
        }
    ],
    "sg:phone":"+1 978 392 9628",
    "sg:postcode":"01886",
    "sg:province":"MA",
    "wof:name":"Esi Media",
    "wof:placetype":"venue"
},
  "geometry": {"coordinates":[-71.463014,42.558661],"type":"Point"}
}