{
  "type": "Feature",
  "properties": {
    "addr:full":"11 Porter St Boston MA 02128",
    "addr:housenumber":"11",
    "addr:postcode":"02128",
    "addr:street":"Porter St",
    "iso:country":"US",
    "sg:address":"11 Porter St",
    "sg:city":"Boston",
    "sg:classifiers":[
        {
            "category":"Insurance",
            "subcategory":"Hazard Insurance",
            "type":"Services"
        }
    ],
    "sg:phone":"+1 617 561 3191",
    "sg:postcode":"02128",
    "sg:province":"MA",
    "sg:tags":[
        "commercial",
        "business"
    ],
    "wof:name":"Metro Boston Ins Agency",
    "wof:placetype":"venue"
},
  "geometry": {"coordinates":[-71.038101,42.374699],"type":"Point"}
}