{
  "type": "Feature",
  "properties": {
    "addr:full": "208 Homer St Newton MA 02459",
    "addr:housenumber": "208",
    "addr:postcode": "02459",
    "addr:street": "Homer St",
    "iso:country": "US",
    "sg:address": "208 Homer St",
    "sg:city": "Newton",
    "sg:classifiers": [
      {
        "category": "Professional",
        "subcategory": "Business Services",
        "type": "Services"
      }
    ],
    "sg:phone": "+1   ",
    "sg:postcode": "02459",
    "sg:province": "MA",
    "wof:name": "Snap Design Inc",
    "wof:placetype": "venue"
  },
  "geometry": {"coordinates":[-71.202099,42.334918],"type":"Point"}
}
