{
  "type": "Feature",
  "properties": {
    "iso:country":"US",
    "sg:address":"139 Coolidge Rd",
    "sg:city":"Berlin",
    "sg:classifiers":[
        {
            "category":"Autos & Motor Vehicles",
            "subcategory":"Fuel & Gas Station",
            "type":"Retail Goods"
        }
    ],
    "sg:phone":"+1 978 568 0401",
    "sg:postcode":"01503",
    "sg:province":"MA",
    "sg:tags":[
        "oil"
    ],
    "wof:name":"Verc Berlin Exxon",
    "wof:placetype":"venue"
},
  "geometry": {"coordinates":[-71.60436,42.395887],"type":"Point"}
}