{
  "type": "Feature",
  "properties": {
    "iso:country":"US",
    "sg:address":"8 Farrington St",
    "sg:city":"Arlington",
    "sg:classifiers":[
        {
            "category":"Professional",
            "subcategory":"Business Services",
            "type":"Services"
        }
    ],
    "sg:phone":"+1 781 646 1730",
    "sg:postcode":"02474",
    "sg:province":"MA",
    "sg:tags":[
        "transcribing",
        "disc"
    ],
    "wof:name":"ATM Arlington Typing Mailing",
    "wof:placetype":"venue"
},
  "geometry": {"coordinates":[-71.152598,42.421468],"type":"Point"}
}