{
  "type": "Feature",
  "properties": {
    "iso:country":"US",
    "sg:address":"742 Washington St",
    "sg:city":"Canton",
    "sg:classifiers":[
        {
            "category":"Building & Trades",
            "subcategory":"Construction",
            "type":"Services"
        }
    ],
    "sg:phone":"+1 781 828 6359",
    "sg:postcode":"02021",
    "sg:province":"MA",
    "sg:tags":[
        "pile",
        "driving"
    ],
    "wof:name":"Allied Pile Driving Inc",
    "wof:placetype":"venue"
},
  "geometry": {"coordinates":[-71.14563699999999,42.157498],"type":"Point"}
}