{
  "type": "Feature",
  "properties": {
    "addr:full":"194 Callender Street Dorchester Center MA 02124",
    "addr:housenumber":"194",
    "addr:postcode":"02124",
    "addr:street":"Callender Street Dorchester Center",
    "iso:country":"US",
    "sg:address":"194 Callender Street",
    "sg:city":"Dorchester Center",
    "sg:classifiers":[
        {
            "category":"Travel",
            "subcategory":"Hotels & Motels",
            "type":"Entertainment"
        }
    ],
    "sg:phone":"+1 617 436 9776",
    "sg:postcode":"02124",
    "sg:province":"MA",
    "wof:name":"Mac's Guest House",
    "wof:placetype":"venue"
},
  "geometry": {"coordinates":[-71.087898,42.288306],"type":"Point"}
}