{
  "type": "Feature",
  "properties": {
    "addr:full": "22 Green St Monson MA 01057",
    "addr:housenumber": "22",
    "addr:postcode": "01057",
    "addr:street": "Green St",
    "iso:country": "US",
    "sg:address": "22 Green St",
    "sg:city": "Monson",
    "sg:classifiers": [
      {
        "category": "Organizations",
        "subcategory": "Religious Organization",
        "type": "Services"
      }
    ],
    "sg:phone": "+1 413 267 3622",
    "sg:postcode": "01057",
    "sg:province": "MA",
    "sg:tags": [
      "church"
    ],
    "sg:website": "www.stpatrickmonson.org",
    "wof:name": "St Patricks Church",
    "wof:placetype": "venue"
  },
  "geometry": {"coordinates":[-72.313311,42.094835],"type":"Point"}
}
