{
  "type": "Feature",
  "properties": {
    "addr:full": "1895 Centre Street West Roxbury MA 02132",
    "addr:housenumber": "1895",
    "addr:postcode": "02132",
    "addr:street": "Centre Street",
    "iso:country": "US",
    "sg:address": "1895 Centre Street",
    "sg:city": "West Roxbury",
    "sg:classifiers": [
      {
        "category": "Professional",
        "subcategory": "Lawyer \u0026 Legal Services",
        "type": "Services"
      }
    ],
    "sg:phone": "+1 617 323 3845",
    "sg:postcode": "02132",
    "sg:province": "MA",
    "wof:name": "Fishbon Mark E Atty",
    "wof:placetype": "venue"
  },
  "geometry": {"coordinates":[-71.156213,42.285459],"type":"Point"}
}
