{
  "type": "Feature",
  "properties": {
    "addr:full": "131 Warren St Revere MA 02151",
    "addr:housenumber": "131",
    "addr:postcode": "02151",
    "addr:street": "Warren St",
    "iso:country": "US",
    "sg:address": "131 Warren St",
    "sg:city": "Revere",
    "sg:classifiers": [
      {
        "category": "Professional",
        "subcategory": "Computer Services",
        "type": "Services"
      }
    ],
    "sg:phone": "+1 781 808 4263",
    "sg:postcode": "02151",
    "sg:province": "MA",
    "sg:tags": [
      "repair"
    ],
    "sg:website": "eapcrepair.com",
    "wof:name": "EA Pc-Repair",
    "wof:placetype": "venue"
  },
  "geometry": {"coordinates":[-71.019683,42.411266],"type":"Point"}
}
