{
  "type": "Feature",
  "properties": {
    "addr:full":"301 Littleton Rd Westford MA 01886",
    "addr:housenumber":"301",
    "addr:postcode":"01886",
    "addr:street":"Littleton Rd",
    "iso:country":"US",
    "sg:address":"301 Littleton Rd",
    "sg:city":"Westford",
    "sg:classifiers":[
        {
            "category":"Building & Trades",
            "subcategory":"Construction",
            "type":"Services"
        }
    ],
    "sg:phone":"+1 978 692 3703",
    "sg:postcode":"01886",
    "sg:province":"MA",
    "sg:tags":[
        "interior",
        "design",
        "painter"
    ],
    "wof:name":"Lynch W J Paint Ctr Inc",
    "wof:placetype":"venue"
},
  "geometry": {"coordinates":[-71.437798,42.557701],"type":"Point"}
}