{
  "type": "Feature",
  "properties": {
    "iso:country":"US",
    "sg:address":"7 Tozer Rd",
    "sg:city":"Beverly",
    "sg:classifiers":[
        {
            "category":"Wholesale",
            "subcategory":"Vending Machines",
            "type":"Manufacturing & Wholesale Goods"
        }
    ],
    "sg:phone":"+1 978 232 1218",
    "sg:postcode":"01915",
    "sg:province":"MA",
    "wof:name":"Hospitality Vending Inc",
    "wof:placetype":"venue"
},
  "geometry": {"coordinates":[-70.885587,42.578913],"type":"Point"}
}