{
  "type": "Feature",
  "properties": {
    "addr:full":"25 South St Mansfield MA 02048",
    "addr:housenumber":"25",
    "addr:postcode":"02048",
    "addr:street":"South St",
    "iso:country":"US",
    "sg:address":"25 South St",
    "sg:city":"Mansfield",
    "sg:classifiers":[
        {
            "category":"Professional",
            "subcategory":"Management & Consulting",
            "type":"Services"
        }
    ],
    "sg:phone":"+1   ",
    "sg:postcode":"02048",
    "sg:province":"MA",
    "sg:tags":[
        "business"
    ],
    "wof:name":"Gazzola Realty Trust",
    "wof:placetype":"venue"
},
  "geometry": {"coordinates":[-71.263908,42.022942],"type":"Point"}
}