{
  "type": "Feature",
  "properties": {
    "iso:country":"US",
    "sg:address":"146 Tremont St",
    "sg:city":"Boston",
    "sg:classifiers":[
        {
            "category":"Building & Trades",
            "subcategory":"Locksmith",
            "type":"Services"
        }
    ],
    "sg:phone":"+1 617 272 4353",
    "sg:postcode":"02111",
    "sg:province":"MA",
    "sg:tags":[
        "key"
    ],
    "wof:name":"Locksmith 24 Hours",
    "wof:placetype":"venue"
},
  "geometry": {"coordinates":[-71.063016,42.355244],"type":"Point"}
}