{
  "type": "Feature",
  "properties": {
    "addr:full": "5 Linden Place Brookline MA 02445",
    "addr:housenumber": "5",
    "addr:postcode": "02445",
    "addr:street": "Linden Place",
    "iso:country": "US",
    "sg:address": "5 Linden Place",
    "sg:city": "Brookline",
    "sg:classifiers": [
      {
        "category": "Place Of Worship",
        "subcategory": "Church",
        "type": "Public Place"
      },
      {
        "category": "Place Of Worship",
        "type": "Public Place"
      },
      {
        "category": "Organizations",
        "subcategory": "Religious Organization",
        "type": "Services"
      }
    ],
    "sg:phone": "+1 617 734 0444",
    "sg:postcode": "02445",
    "sg:province": "MA",
    "sg:tags": [
      "churches-catholic-traditional",
      "churches-catholic"
    ],
    "wof:name": "St Mary of the Assumption Rectory",
    "wof:placetype": "venue"
  },
  "geometry": {"coordinates":[-71.11932,42.33484],"type":"Point"}
}
