{
  "type": "Feature",
  "properties": {
    "addr:full": "127 South St Boston MA 02111",
    "addr:housenumber": "127",
    "addr:postcode": "02111",
    "addr:street": "South St",
    "iso:country": "US",
    "sg:address": "127 South St",
    "sg:city": "Boston",
    "sg:classifiers": [
      {
        "category": "Professional",
        "subcategory": "Art Services",
        "type": "Services"
      }
    ],
    "sg:phone": "+1 617 314 6286",
    "sg:postcode": "02111",
    "sg:province": "MA",
    "sg:tags": [
      "graphic",
      "design"
    ],
    "sg:website": "www.brunellocreative.com",
    "wof:name": "Brunello Creative",
    "wof:placetype": "venue"
  },
  "geometry": {"coordinates":[-71.05736,42.351161],"type":"Point"}
}
