{
  "type": "Feature",
  "properties": {
    "addr:full": "95 Frank B Murray St Springfield MA 01103",
    "addr:housenumber": "95",
    "addr:postcode": "01103",
    "addr:street": "Frank B Murray St",
    "iso:country": "US",
    "sg:address": "95 Frank B Murray St",
    "sg:city": "Springfield",
    "sg:classifiers": [
      {
        "category": "Building \u0026 Trades",
        "subcategory": "Electrical",
        "type": "Services"
      }
    ],
    "sg:phone": "+1 413 747 1700",
    "sg:postcode": "01103",
    "sg:province": "MA",
    "sg:tags": [
      "electric",
      "contractor"
    ],
    "wof:name": "Turcotte Electric",
    "wof:placetype": "venue"
  },
  "geometry": {"coordinates":[-72.592455,42.10795],"type":"Point"}
}
