{
  "type": "Feature",
  "properties": {
    "addr:full":"283 Cox St Hudson MA 01749",
    "addr:housenumber":"283",
    "addr:postcode":"01749",
    "addr:street":"Cox St",
    "iso:country":"US",
    "sg:address":"283 Cox St",
    "sg:city":"Hudson",
    "sg:classifiers":[
        {
            "category":"Building & Trades",
            "subcategory":"Construction",
            "type":"Services"
        }
    ],
    "sg:phone":"+1 978 568 8801",
    "sg:postcode":"01749",
    "sg:province":"MA",
    "sg:tags":[
        "sealcoating",
        "asphalt",
        "paving"
    ],
    "wof:name":"J D Deangelis Inc",
    "wof:placetype":"venue"
},
  "geometry": {"coordinates":[-71.549408,42.402458],"type":"Point"}
}