{
  "type": "Feature",
  "properties": {
    "iso:country":"US",
    "sg:address":"180 Milton St",
    "sg:city":"Dedham",
    "sg:classifiers":[
        {
            "category":"Home & Garden",
            "subcategory":"Building Materials",
            "type":"Retail Goods"
        },
        {
            "category":"Building & Trades",
            "subcategory":"Construction",
            "type":"Services"
        }
    ],
    "sg:phone":"+1 781 329 3542",
    "sg:postcode":"02026",
    "sg:province":"MA",
    "sg:tags":[
        "concrete",
        "staining",
        "contractor"
    ],
    "wof:name":"Gallagher Concrete Constructio",
    "wof:placetype":"venue"
},
  "geometry": {"coordinates":[-71.14701100000001,42.241972],"type":"Point"}
}