{
  "type": "Feature",
  "properties": {
    "addr:full": "180 Milton St Dedham MA 02026",
    "addr:housenumber": "180",
    "addr:postcode": "02026",
    "addr:street": "Milton St",
    "iso:country": "US",
    "sg:address": "180 Milton St",
    "sg:city": "Dedham",
    "sg:classifiers": [
      {
        "category": "Home \u0026 Garden",
        "subcategory": "Building Materials",
        "type": "Retail Goods"
      },
      {
        "category": "Building \u0026 Trades",
        "subcategory": "Construction",
        "type": "Services"
      }
    ],
    "sg:phone": "+1 781 329 3542",
    "sg:postcode": "02026",
    "sg:province": "MA",
    "sg:tags": [
      "concrete",
      "staining",
      "contractor"
    ],
    "wof:name": "Gallagher Concrete Constructio",
    "wof:placetype": "venue"
  },
  "geometry": {"coordinates":[-71.147011,42.241972],"type":"Point"}
}
