{
  "type": "Feature",
  "properties": {
    "addr:full":"7 Dale St Medfield MA 02052",
    "addr:housenumber":"7",
    "addr:postcode":"02052",
    "addr:street":"Dale St",
    "iso:country":"US",
    "sg:address":"7 Dale St",
    "sg:city":"Medfield",
    "sg:classifiers":[
        {
            "category":"Education",
            "subcategory":"School",
            "type":"Public Place"
        }
    ],
    "sg:phone":"+1 508 359 6055",
    "sg:postcode":"02052",
    "sg:province":"MA",
    "wof:name":"Wheelock School",
    "wof:placetype":"venue"
},
  "geometry": {"coordinates":[-71.31143899999999,42.191241],"type":"Point"}
}