{
  "type": "Feature",
  "properties": {
    "addr:full":"201 Vale St Fall River MA 02724",
    "addr:housenumber":"201",
    "addr:postcode":"02724",
    "addr:street":"Vale St",
    "iso:country":"US",
    "sg:address":"201 Vale St",
    "sg:city":"Fall River",
    "sg:classifiers":[
        {
            "category":"Retail",
            "subcategory":"Auto Repair",
            "type":"Services"
        }
    ],
    "sg:phone":"+1 508 672 5821",
    "sg:postcode":"02724",
    "sg:province":"MA",
    "sg:tags":[
        "general"
    ],
    "wof:name":"J & D Auto Repair",
    "wof:placetype":"venue"
},
  "geometry": {"coordinates":[-71.164973,41.686545],"type":"Point"}
}