{
  "type": "Feature",
  "properties": {
    "addr:full": "455 Main St Stoneham MA 02180",
    "addr:housenumber": "455",
    "addr:postcode": "02180",
    "addr:street": "Main St",
    "iso:country": "US",
    "sg:address": "455 Main St",
    "sg:city": "Stoneham",
    "sg:classifiers": [
      {
        "category": "Personal",
        "subcategory": "Beauty Salon",
        "type": "Services"
      }
    ],
    "sg:phone": "+1 781 438 0263",
    "sg:postcode": "02180",
    "sg:province": "MA",
    "wof:name": "Marie Helaine Color FX",
    "wof:placetype": "venue"
  },
  "geometry": {"coordinates":[-71.10043,42.477822],"type":"Point"}
}
