{
  "type": "Feature",
  "properties": {
    "iso:country":"US",
    "sg:address":"22 Railroad Ave",
    "sg:city":"Andover",
    "sg:classifiers":[
        {
            "category":"Organizations",
            "subcategory":"Non-profit Organization",
            "type":"Services"
        }
    ],
    "sg:phone":"+1 978 749 9428",
    "sg:postcode":"01810",
    "sg:province":"MA",
    "sg:tags":[
        "disability"
    ],
    "wof:name":"What's New",
    "wof:placetype":"venue"
},
  "geometry": {"coordinates":[-71.144266,42.661442],"type":"Point"}
}