{
  "type": "Feature",
  "properties": {
    "addr:full":"266 Cabot St Beverly MA 01915",
    "addr:housenumber":"266",
    "addr:postcode":"01915",
    "addr:street":"Cabot St",
    "iso:country":"US",
    "sg:address":"266 Cabot St",
    "sg:city":"Beverly",
    "sg:classifiers":[
        {
            "category":"Personal",
            "type":"Services"
        }
    ],
    "sg:phone":"+1 508 783 9451",
    "sg:postcode":"01915",
    "sg:province":"MA",
    "sg:tags":[
        "therapist",
        "massage"
    ],
    "wof:name":"Ocean Wave Muscular Therapy",
    "wof:placetype":"venue"
},
  "geometry": {"coordinates":[-70.87801399999999,42.549461],"type":"Point"}
}