{
  "type": "Feature",
  "properties": {
    "iso:country":"US",
    "sg:address":"80 Audrey's Ln",
    "sg:city":"Marstons Mills",
    "sg:classifiers":[
        {
            "category":"Professional",
            "subcategory":"Business Services",
            "type":"Services"
        }
    ],
    "sg:phone":"+1   ",
    "sg:postcode":"02648",
    "sg:province":"MA",
    "sg:tags":[
        "development",
        "software"
    ],
    "wof:name":"Etherdyne",
    "wof:placetype":"venue"
},
  "geometry": {"coordinates":[-70.44669399999999,41.66062],"type":"Point"}
}