{
  "type": "Feature",
  "properties": {
    "iso:country":"US",
    "sg:address":"459 Washington St",
    "sg:city":"Duxbury",
    "sg:classifiers":[
        {
            "category":"Shopping",
            "subcategory":"Discount & Variety Stores",
            "type":"Retail Goods"
        }
    ],
    "sg:phone":"+1 781 934 6000",
    "sg:postcode":"02332",
    "sg:province":"MA",
    "sg:tags":[
        "merchandise",
        "general"
    ],
    "wof:name":"Sweetsers Properties",
    "wof:placetype":"venue"
},
  "geometry": {"coordinates":[-70.671555,42.038839],"type":"Point"}
}