{
  "type": "Feature",
  "properties": {
    "iso:country":"US",
    "sg:address":"199 Essex St",
    "sg:city":"Saugus",
    "sg:classifiers":[
        {
            "category":"Home & Garden",
            "subcategory":"Garden Supply",
            "type":"Retail Goods"
        }
    ],
    "sg:phone":"+1 781 233 2307",
    "sg:postcode":"01906",
    "sg:province":"MA",
    "sg:tags":[
        "center"
    ],
    "wof:name":"Kreations By Karlene",
    "wof:placetype":"venue"
},
  "geometry": {"coordinates":[-71.01992,42.454473],"type":"Point"}
}