{
  "type": "Feature",
  "properties": {
    "addr:full":"118 Sandwich St Plymouth MA 02360",
    "addr:housenumber":"118",
    "addr:postcode":"02360",
    "addr:street":"Sandwich St",
    "iso:country":"US",
    "sg:address":"118 Sandwich St",
    "sg:city":"Plymouth",
    "sg:classifiers":[
        {
            "category":"Retail",
            "subcategory":"Auto Repair",
            "type":"Services"
        }
    ],
    "sg:phone":"+1 508 746 7206",
    "sg:postcode":"02360",
    "sg:province":"MA",
    "sg:tags":[
        "repairing",
        "automobile"
    ],
    "wof:name":"Reimels Automotive Specialists",
    "wof:placetype":"venue"
},
  "geometry": {"coordinates":[-70.656812,41.952047],"type":"Point"}
}