{
  "type": "Feature",
  "properties": {
    "addr:full": "1201 Walnut St Newton MA 02461",
    "addr:housenumber": "1201",
    "addr:postcode": "02461",
    "addr:street": "Walnut St",
    "iso:country": "US",
    "sg:address": "1201 Walnut St",
    "sg:city": "Newton",
    "sg:classifiers": [
      {
        "category": "Retail",
        "subcategory": "Repair Shop",
        "type": "Services"
      }
    ],
    "sg:phone": "+1 617 527 3224",
    "sg:postcode": "02461",
    "sg:province": "MA",
    "sg:tags": [
      "cleaners",
      "parts",
      "vacuum"
    ],
    "wof:name": "Electrolux",
    "wof:placetype": "venue"
  },
  "geometry": {"coordinates":[-71.20548,42.320898],"type":"Point"}
}
