{
  "type": "Feature",
  "properties": {
    "addr:full": "125 Kingston St Fl 2 Boston MA 02111",
    "addr:housenumber": "125;2",
    "addr:postcode": "02111",
    "addr:street": "Kingston St",
    "iso:country": "US",
    "sg:address": "125 Kingston St Fl 2",
    "sg:city": "Boston",
    "sg:classifiers": [
      {
        "category": "Real Estate",
        "subcategory": "Real Estate Services",
        "type": "Services"
      }
    ],
    "sg:phone": "+1 617 542 1935",
    "sg:postcode": "02111",
    "sg:province": "MA",
    "sg:tags": [
      "apartment",
      "vacancy",
      "listing",
      "rental",
      "finder"
    ],
    "wof:name": "Behnisch Studio East Llp",
    "wof:placetype": "venue"
  },
  "geometry": {"coordinates":[-71.059347,42.3519],"type":"Point"}
}
