{
  "type": "Feature",
  "properties": {
    "iso:country":"US",
    "sg:address":"18 Dale St",
    "sg:city":"Needham Heights",
    "sg:classifiers":[
        {
            "category":"Professional",
            "type":"Services"
        }
    ],
    "sg:phone":"+1   ",
    "sg:postcode":"02494",
    "sg:province":"MA",
    "wof:name":"Taytslin Art Studio",
    "wof:placetype":"venue"
},
  "geometry": {"coordinates":[-71.237799,42.292012],"type":"Point"}
}