{
  "type": "Feature",
  "properties": {
    "addr:full": "369 Codman Hill Rd Boxborough MA 01719",
    "addr:housenumber": "369",
    "addr:postcode": "01719",
    "addr:street": "Codman Hill Rd",
    "iso:country": "US",
    "sg:address": "369 Codman Hill Rd",
    "sg:city": "Boxborough",
    "sg:classifiers": [
      {
        "category": "Building \u0026 Trades",
        "subcategory": "Construction",
        "type": "Services"
      }
    ],
    "sg:phone": "+1 978 263 3377",
    "sg:postcode": "01719",
    "sg:province": "MA",
    "sg:tags": [
      "excavating",
      "contractor"
    ],
    "wof:name": "J P Crory Co",
    "wof:placetype": "venue"
  },
  "geometry": {"coordinates":[-71.554257,42.481142],"type":"Point"}
}
