{
  "type": "Feature",
  "properties": {
    "iso:country":"US",
    "sg:address":"369 Codman Hill Rd",
    "sg:city":"Boxborough",
    "sg:classifiers":[
        {
            "category":"Building & Trades",
            "subcategory":"Construction",
            "type":"Services"
        }
    ],
    "sg:phone":"+1 978 263 3377",
    "sg:postcode":"01719",
    "sg:province":"MA",
    "sg:tags":[
        "excavating",
        "contractor"
    ],
    "wof:name":"J P Crory Co",
    "wof:placetype":"venue"
},
  "geometry": {"coordinates":[-71.55425700000001,42.481142],"type":"Point"}
}