{
  "type": "Feature",
  "properties": {
    "iso:country":"US",
    "sg:address":"60 Plymouth St",
    "sg:city":"Holbrook",
    "sg:classifiers":[
        {
            "category":"Organizations",
            "subcategory":"Religious Organization",
            "type":"Services"
        }
    ],
    "sg:phone":"+1 781 767 3639",
    "sg:postcode":"02343",
    "sg:province":"MA",
    "sg:tags":[
        "church"
    ],
    "wof:name":"Methodist Church Of Holbrook",
    "wof:placetype":"venue"
},
  "geometry": {"coordinates":[-71.00475,42.154779],"type":"Point"}
}