{
  "type": "Feature",
  "properties": {
    "iso:country":"US",
    "sg:address":"218 S Main St",
    "sg:city":"Fall River",
    "sg:classifiers":[
        {
            "category":"Professional",
            "subcategory":"Management & Consulting",
            "type":"Services"
        }
    ],
    "sg:phone":"+1 508 674 2636",
    "sg:postcode":"02721",
    "sg:province":"MA",
    "sg:tags":[
        "counselor",
        "public",
        "relations"
    ],
    "wof:name":"Admark",
    "wof:placetype":"venue"
},
  "geometry": {"coordinates":[-71.156727,41.700083],"type":"Point"}
}