{
  "type": "Feature",
  "properties": {
    "addr:full": "218 S Main St Fall River MA 02721",
    "addr:housenumber": "218",
    "addr:postcode": "02721",
    "addr:street": "S Main St",
    "iso:country": "US",
    "sg:address": "218 S Main St",
    "sg:city": "Fall River",
    "sg:classifiers": [
      {
        "category": "Professional",
        "subcategory": "Management \u0026 Consulting",
        "type": "Services"
      }
    ],
    "sg:phone": "+1 508 674 2636",
    "sg:postcode": "02721",
    "sg:province": "MA",
    "sg:tags": [
      "counselor",
      "public",
      "relations"
    ],
    "wof:name": "Admark",
    "wof:placetype": "venue"
  },
  "geometry": {"coordinates":[-71.156727,41.700083],"type":"Point"}
}
