{
  "type": "Feature",
  "properties": {
    "addr:full":"7 Brentwood Way Ipswich MA 01938",
    "addr:housenumber":"7",
    "addr:postcode":"01938",
    "addr:street":"Brentwood Way",
    "iso:country":"US",
    "sg:address":"7 Brentwood Way",
    "sg:city":"Ipswich",
    "sg:classifiers":[
        {
            "category":"Bars & Pubs",
            "type":"Food & Drink"
        },
        {
            "category":"Restaurant",
            "type":"Food & Drink"
        }
    ],
    "sg:phone":"+1 978 546 0055",
    "sg:postcode":"01938",
    "sg:province":"MA",
    "sg:tags":[
        "tavern"
    ],
    "wof:name":"Nate S At Front Beach",
    "wof:placetype":"venue"
},
  "geometry": {"coordinates":[-70.871066,42.666894],"type":"Point"}
}