{
  "type": "Feature",
  "properties": {
    "iso:country":"US",
    "sg:address":"45 Central Sq",
    "sg:city":"Lynn",
    "sg:classifiers":[
        {
            "category":"Social Services",
            "subcategory":"Job Training",
            "type":"Services"
        }
    ],
    "sg:phone":"+1   ",
    "sg:postcode":"01901",
    "sg:province":"MA",
    "sg:tags":[
        "executive"
    ],
    "wof:name":"Northshore Employment Training",
    "wof:placetype":"venue"
},
  "geometry": {"coordinates":[-70.945061,42.464081],"type":"Point"}
}