{
  "type": "Feature",
  "properties": {
    "addr:full":"50 Village Post Rd Danvers MA 01923",
    "addr:housenumber":"50",
    "addr:postcode":"01923",
    "addr:street":"Village Post Rd",
    "iso:country":"US",
    "sg:address":"50 Village Post Rd",
    "sg:city":"Danvers",
    "sg:classifiers":[
        {
            "category":"Professional",
            "subcategory":"Management & Consulting",
            "type":"Services"
        }
    ],
    "sg:phone":"+1   ",
    "sg:postcode":"01923",
    "sg:province":"MA",
    "sg:tags":[
        "manufacture",
        "for",
        "rep",
        "instrument",
        "electrical",
        "imaging"
    ],
    "wof:name":"Cats",
    "wof:placetype":"venue"
},
  "geometry": {"coordinates":[-70.957382,42.555938],"type":"Point"}
}