{
  "type": "Feature",
  "properties": {
    "iso:country":"US",
    "sg:address":"8 Wayne Rd",
    "sg:city":"Westford",
    "sg:classifiers":[
        {
            "category":"Manufacturing",
            "subcategory":"Rubber & Plastics",
            "type":"Manufacturing & Wholesale Goods"
        }
    ],
    "sg:phone":"+1 978 692 7939",
    "sg:postcode":"01886",
    "sg:province":"MA",
    "sg:tags":[
        "product"
    ],
    "wof:name":"Advanced Technical Marketing",
    "wof:placetype":"venue"
},
  "geometry": {"coordinates":[-71.412775,42.553902],"type":"Point"}
}