{
  "type": "Feature",
  "properties": {
    "addr:full": "8 Wayne Rd Westford MA 01886",
    "addr:housenumber": "8",
    "addr:postcode": "01886",
    "addr:street": "Wayne Rd",
    "iso:country": "US",
    "sg:address": "8 Wayne Rd",
    "sg:city": "Westford",
    "sg:classifiers": [
      {
        "category": "Manufacturing",
        "subcategory": "Rubber \u0026 Plastics",
        "type": "Manufacturing \u0026 Wholesale Goods"
      }
    ],
    "sg:phone": "+1 978 692 7939",
    "sg:postcode": "01886",
    "sg:province": "MA",
    "sg:tags": [
      "product"
    ],
    "wof:name": "Advanced Technical Marketing",
    "wof:placetype": "venue"
  },
  "geometry": {"coordinates":[-71.412775,42.553902],"type":"Point"}
}
