{
  "type": "Feature",
  "properties": {
    "addr:full": "235 Shaw Farm Rd Holliston MA 01746",
    "addr:housenumber": "235",
    "addr:postcode": "01746",
    "addr:street": "Shaw Farm Rd",
    "iso:country": "US",
    "sg:address": "235 Shaw Farm Rd",
    "sg:city": "Holliston",
    "sg:classifiers": [
      {
        "category": "Autos \u0026 Motor Vehicles",
        "subcategory": "Auto Supplies",
        "type": "Retail Goods"
      }
    ],
    "sg:phone": "+1   ",
    "sg:postcode": "01746",
    "sg:province": "MA",
    "wof:name": "Carsons Antique Auto Part",
    "wof:placetype": "venue"
  },
  "geometry": {"coordinates":[-71.411164,42.188472],"type":"Point"}
}
