{
  "type": "Feature",
  "properties": {
    "iso:country":"US",
    "sg:address":"521 Loop Rd",
    "sg:city":"Savoy",
    "sg:classifiers":[
        {
            "category":"Personal",
            "subcategory":"Beauty Salon",
            "type":"Services"
        }
    ],
    "sg:phone":"+1 413 743 1283",
    "sg:postcode":"01256",
    "sg:province":"MA",
    "wof:name":"You'Ve Got Nails",
    "wof:placetype":"venue"
},
  "geometry": {"coordinates":[-72.98643800000001,42.550329],"type":"Point"}
}