{
  "type": "Feature",
  "properties": {
    "iso:country":"US",
    "sg:address":"104 Federal St",
    "sg:city":"Salem",
    "sg:classifiers":[
        {
            "category":"Real Estate",
            "subcategory":"Architect",
            "type":"Services"
        }
    ],
    "sg:phone":"+1 978 744 8202",
    "sg:postcode":"01970",
    "sg:province":"MA",
    "sg:tags":[
        "architecture"
    ],
    "wof:name":"David M. Hart Enterprises",
    "wof:placetype":"venue"
},
  "geometry": {"coordinates":[-70.901132,42.521908],"type":"Point"}
}