{
  "type": "Feature",
  "properties": {
    "addr:full":"493 Pleasant St Watertown MA 02472",
    "addr:housenumber":"493",
    "addr:postcode":"02472",
    "addr:street":"Pleasant St",
    "iso:country":"US",
    "sg:address":"493 Pleasant St",
    "sg:city":"Watertown",
    "sg:classifiers":[
        {
            "category":"Autos & Motor Vehicles",
            "subcategory":"Fuel & Gas Station",
            "type":"Retail Goods"
        }
    ],
    "sg:phone":"+1 617 924 9800",
    "sg:postcode":"02472",
    "sg:province":"MA",
    "sg:tags":[
        "oil"
    ],
    "wof:name":"Perfection Plus LLC",
    "wof:placetype":"venue"
},
  "geometry": {"coordinates":[-71.209377,42.366232],"type":"Point"}
}