{
  "type": "Feature",
  "properties": {
    "addr:full": "493 Pleasant St Watertown MA 02472",
    "addr:housenumber": "493",
    "addr:postcode": "02472",
    "addr:street": "Pleasant St",
    "iso:country": "US",
    "ovtr:label": "Perfection Plus LLC, 483 Pleasant St Watertown MA US",
    "ovtr:similarity": 2.4360170364379883,
    "sg:address": "493 Pleasant St",
    "sg:city": "Watertown",
    "sg:classifiers": [
      {
        "category": "Autos \u0026 Motor Vehicles",
        "subcategory": "Fuel \u0026 Gas Station",
        "type": "Retail Goods"
      }
    ],
    "sg:phone": "+1 617 924 9800",
    "sg:postcode": "02472",
    "sg:province": "MA",
    "sg:tags": [
      "oil"
    ],
    "wof:name": "Perfection Plus LLC",
    "wof:placetype": "venue"
  },
  "geometry": {"coordinates":[-71.209377,42.366232],"type":"Point"}
}
