{
  "type": "Feature",
  "properties": {
    "addr:full":"17 Ellen Rd Taunton MA 02780",
    "addr:housenumber":"17",
    "addr:postcode":"02780",
    "addr:street":"Ellen Rd",
    "iso:country":"US",
    "sg:address":"17 Ellen Rd",
    "sg:city":"Taunton",
    "sg:classifiers":[
        {
            "category":"Building & Trades",
            "subcategory":"Plumbing",
            "type":"Services"
        }
    ],
    "sg:phone":"+1 508 821 7626",
    "sg:postcode":"02780",
    "sg:province":"MA",
    "sg:tags":[
        "septic"
    ],
    "wof:name":"Anytime Septic Svc",
    "wof:placetype":"venue"
},
  "geometry": {"coordinates":[-71.06188299999999,41.898793],"type":"Point"}
}