{
  "type": "Feature",
  "properties": {
    "addr:full": "755 Crescent St Brockton MA 02302",
    "addr:housenumber": "755",
    "addr:postcode": "02302",
    "addr:street": "Crescent St",
    "iso:country": "US",
    "sg:address": "755 Crescent St",
    "sg:city": "Brockton",
    "sg:classifiers": [
      {
        "category": "Social Services",
        "type": "Services"
      }
    ],
    "sg:phone": "+1 508 583 7048",
    "sg:postcode": "02302",
    "sg:province": "MA",
    "sg:tags": [
      "organization",
      "welfare"
    ],
    "wof:name": "RSVP Volunteer Program",
    "wof:placetype": "venue"
  },
  "geometry": {"coordinates":[-70.990723,42.08106],"type":"Point"}
}
