{
  "type": "Feature",
  "properties": {
    "iso:country":"US",
    "sg:address":"620 Washington St",
    "sg:city":"South Easton",
    "sg:classifiers":[
        {
            "category":"Restaurant",
            "type":"Food & Drink"
        }
    ],
    "sg:phone":"+1 508 238 5311",
    "sg:postcode":"02375",
    "sg:province":"MA",
    "wof:name":"Peri's Restaurant",
    "wof:placetype":"venue"
},
  "geometry": {"coordinates":[-71.07941,42.044942],"type":"Point"}
}