{
  "type": "Feature",
  "properties": {
    "addr:full": "620 Washington St South Easton MA 02375",
    "addr:housenumber": "620",
    "addr:postcode": "02375",
    "addr:street": "Washington St",
    "iso:country": "US",
    "sg:address": "620 Washington St",
    "sg:city": "South Easton",
    "sg:classifiers": [
      {
        "category": "Restaurant",
        "type": "Food \u0026 Drink"
      }
    ],
    "sg:phone": "+1 508 238 5311",
    "sg:postcode": "02375",
    "sg:province": "MA",
    "wof:name": "Peri's Restaurant",
    "wof:placetype": "venue"
  },
  "geometry": {"coordinates":[-71.07941,42.044942],"type":"Point"}
}
