{
  "type": "Feature",
  "properties": {
    "addr:full": "163 Lake St Wilmington MA 01887",
    "addr:housenumber": "163",
    "addr:postcode": "01887",
    "addr:street": "Lake St",
    "iso:country": "US",
    "sg:address": "163 Lake St",
    "sg:city": "Wilmington",
    "sg:classifiers": [
      {
        "category": "Freight",
        "type": "Transportation"
      }
    ],
    "sg:phone": "+1   ",
    "sg:postcode": "01887",
    "sg:province": "MA",
    "sg:tags": [
      "operator",
      "local",
      "trucking"
    ],
    "wof:name": "Tri FI Enterprises Inc",
    "wof:placetype": "venue"
  },
  "geometry": {"coordinates":[-71.202655,42.561612],"type":"Point"}
}
