{
  "type": "Feature",
  "properties": {
    "iso:country":"US",
    "sg:address":"163 Lake St",
    "sg:city":"Wilmington",
    "sg:classifiers":[
        {
            "category":"Freight",
            "type":"Transportation"
        }
    ],
    "sg:phone":"+1   ",
    "sg:postcode":"01887",
    "sg:province":"MA",
    "sg:tags":[
        "operator",
        "local",
        "trucking"
    ],
    "wof:name":"Tri FI Enterprises Inc",
    "wof:placetype":"venue"
},
  "geometry": {"coordinates":[-71.20265499999999,42.561612],"type":"Point"}
}