{
  "type": "Feature",
  "properties": {
    "addr:full":"202 Main St Milford MA 01757",
    "addr:housenumber":"202",
    "addr:postcode":"01757",
    "addr:street":"Main St",
    "iso:country":"US",
    "sg:address":"202 Main St",
    "sg:city":"Milford",
    "sg:classifiers":[
        {
            "category":"Professional",
            "subcategory":"Business Services",
            "type":"Services"
        }
    ],
    "sg:phone":"+1 508 634 8008",
    "sg:postcode":"01757",
    "sg:province":"MA",
    "sg:tags":[
        "translator",
        "interpreter"
    ],
    "wof:name":"Santos Translation Etc",
    "wof:placetype":"venue"
},
  "geometry": {"coordinates":[-71.52086799999999,42.139503],"type":"Point"}
}