{
  "type": "Feature",
  "properties": {
    "iso:country":"US",
    "sg:address":"500 Rutherford Avenue",
    "sg:city":"Charlestown",
    "sg:classifiers":[
        {
            "category":"Shopping",
            "subcategory":"Mobile Phones",
            "type":"Retail Goods"
        }
    ],
    "sg:phone":"+1 617 241 4000",
    "sg:postcode":"02129",
    "sg:province":"MA",
    "sg:website":"www.sprint.com",
    "wof:name":"Nextel Communications",
    "wof:placetype":"venue"
},
  "geometry": {"coordinates":[-71.071871,42.38074],"type":"Point"}
}