{
  "type": "Feature",
  "properties": {
    "addr:full": "130 Lincoln St Brighton MA 02135",
    "addr:housenumber": "130",
    "addr:postcode": "02135",
    "addr:street": "Lincoln St",
    "iso:country": "US",
    "sg:address": "130 Lincoln St",
    "sg:city": "Brighton",
    "sg:classifiers": [
      {
        "category": "Retail",
        "subcategory": "Storage",
        "type": "Services"
      }
    ],
    "sg:phone": "+1 617 787 4325",
    "sg:postcode": "02135",
    "sg:province": "MA",
    "sg:tags": [
      "self"
    ],
    "sg:website": "www.simplyss.com/",
    "wof:name": "Simply Self Storage",
    "wof:placetype": "venue"
  },
  "geometry": {"coordinates":[-71.1411,42.3584],"type":"Point"}
}
