{
  "type": "Feature",
  "properties": {
    "iso:country":"US",
    "sg:address":"130 Lincoln St",
    "sg:city":"Brighton",
    "sg:classifiers":[
        {
            "category":"Retail",
            "subcategory":"Storage",
            "type":"Services"
        }
    ],
    "sg:phone":"+1 617 787 4325",
    "sg:postcode":"02135",
    "sg:province":"MA",
    "sg:tags":[
        "self"
    ],
    "sg:website":"www.simplyss.com/",
    "wof:name":"Simply Self Storage",
    "wof:placetype":"venue"
},
  "geometry": {"coordinates":[-71.14109999999999,42.3584],"type":"Point"}
}