{
  "type": "Feature",
  "properties": {
    "addr:full": "151 Bow St Everett MA 02149",
    "addr:housenumber": "151",
    "addr:postcode": "02149",
    "addr:street": "Bow St",
    "iso:country": "US",
    "sg:address": "151 Bow St",
    "sg:city": "Everett",
    "sg:classifiers": [
      {
        "category": "Professional",
        "type": "Services"
      },
      {
        "category": "Personal",
        "type": "Services"
      },
      {
        "category": "Structure",
        "subcategory": "Warehouse",
        "type": "Public Place"
      },
      {
        "category": "Retail",
        "subcategory": "Storage",
        "type": "Services"
      }
    ],
    "sg:phone": "+1 617 389 2343",
    "sg:postcode": "02149",
    "sg:province": "MA",
    "sg:tags": [
      "warehouses-merchandise",
      "self",
      "material",
      "moving",
      "services-labor",
      "mover"
    ],
    "wof:name": "Warehouse Services Inc",
    "wof:placetype": "venue"
  },
  "geometry": {"coordinates":[-71.062019,42.398472],"type":"Point"}
}
