{
  "type": "Feature",
  "properties": {
    "addr:full": "231 Rosemont St Haverhill MA 01832",
    "addr:housenumber": "231",
    "addr:postcode": "01832",
    "addr:street": "Rosemont St",
    "iso:country": "US",
    "sg:address": "231 Rosemont St",
    "sg:city": "Haverhill",
    "sg:classifiers": [
      {
        "category": "Building \u0026 Trades",
        "subcategory": "Landscaping Services",
        "type": "Services"
      }
    ],
    "sg:phone": "+1 978 521 9534",
    "sg:postcode": "01832",
    "sg:province": "MA",
    "sg:tags": [
      "landscape",
      "contractor"
    ],
    "wof:name": "A Z Landscaping \u0026 Ground Mntnc",
    "wof:placetype": "venue"
  },
  "geometry": {"coordinates":[-71.1118,42.802447],"type":"Point"}
}
