{
  "type": "Feature",
  "properties": {
    "addr:full": "18 Court St Plymouth MA 02360",
    "addr:housenumber": "18",
    "addr:postcode": "02360",
    "addr:street": "Court St",
    "iso:country": "US",
    "sg:address": "18 Court St",
    "sg:city": "Plymouth",
    "sg:classifiers": [
      {
        "category": "Shopping",
        "subcategory": "Jewelry",
        "type": "Retail Goods"
      }
    ],
    "sg:phone": "+1 508 747 0007",
    "sg:postcode": "02360",
    "sg:province": "MA",
    "sg:tags": [
      "jeweler"
    ],
    "wof:name": "Craig Jewelry Inc",
    "wof:placetype": "venue"
  },
  "geometry": {"coordinates":[-70.666129,41.957626],"type":"Point"}
}
