{
  "type": "Feature",
  "properties": {
    "iso:country":"US",
    "sg:address":"94 Marion St",
    "sg:city":"Chicopee",
    "sg:classifiers":[
        {
            "category":"Real Estate",
            "subcategory":"Real Estate Agent",
            "type":"Services"
        }
    ],
    "sg:phone":"+1   ",
    "sg:postcode":"01013",
    "sg:province":"MA",
    "wof:name":"Lorenko Home",
    "wof:placetype":"venue"
},
  "geometry": {"coordinates":[-72.60442500000001,42.137763],"type":"Point"}
}