{
  "type": "Feature",
  "properties": {
    "iso:country":"US",
    "sg:address":"1 Charles St",
    "sg:city":"Boston",
    "sg:classifiers":[
        {
            "category":"Coffee & Tea",
            "type":"Food & Drink"
        }
    ],
    "sg:phone":"+1 617 742 2664",
    "sg:postcode":"02114",
    "sg:province":"MA",
    "sg:website":"www.starbucks.com",
    "wof:name":"Starbucks",
    "wof:placetype":"venue"
},
  "geometry": {"coordinates":[-71.067188,42.351456],"type":"Point"}
}