{
  "type": "Feature",
  "properties": {
    "addr:full": "435 Winthrop Ave Lawrence MA 01843",
    "addr:housenumber": "435",
    "addr:postcode": "01843",
    "addr:street": "Winthrop Ave",
    "iso:country": "US",
    "sg:address": "435 Winthrop Ave",
    "sg:city": "Lawrence",
    "sg:classifiers": [
      {
        "category": "Shopping",
        "subcategory": "Florist",
        "type": "Retail Goods"
      }
    ],
    "sg:phone": "+1 978 685 1513",
    "sg:postcode": "01843",
    "sg:province": "MA",
    "wof:name": "Riverside At The Den",
    "wof:placetype": "venue"
  },
  "geometry": {"coordinates":[-71.135817,42.681279],"type":"Point"}
}
