{
  "type": "Feature",
  "properties": {
    "addr:full": "25 S Main St Attleboro MA 02703",
    "addr:housenumber": "25",
    "addr:postcode": "02703",
    "addr:street": "S Main St",
    "iso:country": "US",
    "sg:address": "25 S Main St",
    "sg:city": "Attleboro",
    "sg:classifiers": [
      {
        "category": "Arena",
        "subcategory": "Sports Club",
        "type": "Entertainment"
      }
    ],
    "sg:phone": "+1 508 266 0707",
    "sg:postcode": "02703",
    "sg:province": "MA",
    "sg:tags": [
      "martial art"
    ],
    "wof:name": "Mu Han Martial Arts",
    "wof:placetype": "venue"
  },
  "geometry": {"coordinates":[-71.283997,41.944302],"type":"Point"}
}
