{
  "type": "Feature",
  "properties": {
    "iso:country":"US",
    "sg:address":"770 Boylston St",
    "sg:city":"Boston",
    "sg:classifiers":[
        {
            "category":"Health Services",
            "subcategory":"Nursing And Care Facility",
            "type":"Services"
        }
    ],
    "sg:phone":"+1 617 232 6702",
    "sg:postcode":"02199",
    "sg:province":"MA",
    "sg:tags":[
        "adult"
    ],
    "wof:name":"Longwood Senior Living Inc",
    "wof:placetype":"venue"
},
  "geometry": {"coordinates":[-71.081424,42.349018],"type":"Point"}
}