{
  "type": "Feature",
  "properties": {
    "addr:full":"622 Somerville Ave Somerville MA 02143",
    "addr:housenumber":"622",
    "addr:postcode":"02143",
    "addr:street":"Somerville Ave",
    "iso:country":"US",
    "sg:address":"622 Somerville Ave",
    "sg:city":"Somerville",
    "sg:classifiers":[
        {
            "category":"Retail",
            "subcategory":"Repair Shop",
            "type":"Services"
        }
    ],
    "sg:phone":"+1 617 453 5180",
    "sg:postcode":"02143",
    "sg:province":"MA",
    "sg:tags":[
        "lock",
        "locksmith"
    ],
    "wof:name":"Emergency 7 Day Locksmith",
    "wof:placetype":"venue"
},
  "geometry": {"coordinates":[-71.11021599999999,42.383949],"type":"Point"}
}