{
  "type": "Feature",
  "properties": {
    "iso:country":"US",
    "sg:address":"97 Jewell St",
    "sg:city":"Mansfield",
    "sg:classifiers":[
        {
            "category":"Freight",
            "type":"Transportation"
        }
    ],
    "sg:phone":"+1   ",
    "sg:postcode":"02048",
    "sg:province":"MA",
    "sg:tags":[
        "fixed",
        "motor",
        "facility"
    ],
    "wof:name":"Bob Servais Inspection Svcs",
    "wof:placetype":"venue"
},
  "geometry": {"coordinates":[-71.25809700000001,42.006739],"type":"Point"}
}