{
  "type": "Feature",
  "properties": {
    "addr:full": "300 Oak St Ste 120 Pembroke MA 02359",
    "addr:housenumber": "300",
    "addr:postcode": "02359",
    "addr:street": "Oak St Ste 120",
    "iso:country": "US",
    "sg:address": "300 Oak St Ste 120",
    "sg:city": "Pembroke",
    "sg:classifiers": [
      {
        "category": "Farming",
        "subcategory": "Nursery",
        "type": "Manufacturing \u0026 Wholesale Goods"
      },
      {
        "category": "Shopping",
        "subcategory": "Crafts \u0026 Fabrics",
        "type": "Retail Goods"
      }
    ],
    "sg:phone": "+1 781 826 3656",
    "sg:postcode": "02359",
    "sg:province": "MA",
    "sg:tags": [
      "florists'",
      "supply",
      "nursery-wholesale",
      "florist",
      "supplies-wholesale",
      "grower",
      "manufacturer"
    ],
    "sg:website": "http://www.recarr.com",
    "wof:name": "Robert Carr Wholesale",
    "wof:placetype": "venue"
  },
  "geometry": {"coordinates":[-70.763988,42.104854],"type":"Point"}
}
