{
  "type": "Feature",
  "properties": {
    "iso:country":"US",
    "sg:address":"65 Franklin St",
    "sg:city":"Boston",
    "sg:classifiers":[
        {
            "category":"Travel",
            "subcategory":"Travel Agent",
            "type":"Entertainment"
        }
    ],
    "sg:phone":"+1   ",
    "sg:postcode":"02110",
    "sg:province":"MA",
    "sg:tags":[
        "agency"
    ],
    "wof:name":"Travizon Inc",
    "wof:placetype":"venue"
},
  "geometry": {"coordinates":[-71.058716,42.355587],"type":"Point"}
}