{
  "type": "Feature",
  "properties": {
    "iso:country":"US",
    "sg:address":"1500 Soldiers Field Rd",
    "sg:city":"Brighton",
    "sg:classifiers":[
        {
            "category":"Banks & Credit Unions",
            "subcategory":"Financial Services",
            "type":"Services"
        }
    ],
    "sg:phone":"+1 617 254 5001",
    "sg:postcode":"02135",
    "sg:province":"MA",
    "sg:tags":[
        "broker",
        "mortgage"
    ],
    "wof:name":"Referral Financial",
    "wof:placetype":"venue"
},
  "geometry": {"coordinates":[-71.14967300000001,42.360127],"type":"Point"}
}