{
  "type": "Feature",
  "properties": {
    "addr:full": "1500 Soldiers Field Rd Brighton MA 02135",
    "addr:housenumber": "1500",
    "addr:postcode": "02135",
    "addr:street": "Soldiers Field Rd",
    "iso:country": "US",
    "sg:address": "1500 Soldiers Field Rd",
    "sg:city": "Brighton",
    "sg:classifiers": [
      {
        "category": "Banks \u0026 Credit Unions",
        "subcategory": "Financial Services",
        "type": "Services"
      }
    ],
    "sg:phone": "+1 617 254 5001",
    "sg:postcode": "02135",
    "sg:province": "MA",
    "sg:tags": [
      "broker",
      "mortgage"
    ],
    "wof:name": "Referral Financial",
    "wof:placetype": "venue"
  },
  "geometry": {"coordinates":[-71.149673,42.360127],"type":"Point"}
}
