{
  "type": "Feature",
  "properties": {
    "iso:country":"US",
    "sg:address":"273 Winter St",
    "sg:city":"Hanover",
    "sg:classifiers":[
        {
            "category":"Taxi",
            "type":"Transportation"
        }
    ],
    "sg:phone":"+1 781 826 7888",
    "sg:postcode":"02339",
    "sg:province":"MA",
    "wof:name":"Hanover Town Taxi",
    "wof:placetype":"venue"
},
  "geometry": {"coordinates":[-70.868545,42.097482],"type":"Point"}
}