{
  "type": "Feature",
  "properties": {
    "addr:full": "129 Boston Ave Medford MA 02155",
    "addr:housenumber": "129",
    "addr:postcode": "02155",
    "addr:street": "Boston Ave",
    "iso:country": "US",
    "sg:address": "129 Boston Ave",
    "sg:city": "Medford",
    "sg:classifiers": [
      {
        "category": "Personal",
        "subcategory": "Beauty Salon",
        "type": "Services"
      }
    ],
    "sg:phone": "+1 781 483 3099",
    "sg:postcode": "02155",
    "sg:province": "MA",
    "wof:name": "Hairs 2 Creativity Inc",
    "wof:placetype": "venue"
  },
  "geometry": {"coordinates":[-71.130985,42.417597],"type":"Point"}
}
