{
  "type": "Feature",
  "properties": {
    "iso:country":"US",
    "sg:address":"16 Park Ave",
    "sg:city":"Worcester",
    "sg:classifiers":[
        {
            "category":"Health Services",
            "subcategory":"Dentist",
            "type":"Services"
        }
    ],
    "sg:phone":"+1 508 471 3264",
    "sg:postcode":"01605",
    "sg:province":"MA",
    "sg:tags":[
        "dentists-cosmetic",
        "denture",
        "dental",
        "dentists-pediatric",
        "clinic",
        "dentistry",
        "dentists-prosthodontists"
    ],
    "sg:website":"http://www.gracefamilydental.com",
    "wof:name":"Grace Family Dental",
    "wof:placetype":"venue"
},
  "geometry": {"coordinates":[-71.808589,42.282949],"type":"Point"}
}