{
  "type": "Feature",
  "properties": {
    "addr:full":"831 Pleasant St Brockton MA 02301",
    "addr:housenumber":"831",
    "addr:postcode":"02301",
    "addr:street":"Pleasant St",
    "iso:country":"US",
    "sg:address":"831 Pleasant St",
    "sg:city":"Brockton",
    "sg:phone":"+1 508 586 8459",
    "sg:postcode":"02301",
    "sg:province":"MA",
    "sg:tags":[
        "oil"
    ],
    "wof:name":"Waverly Oil Co",
    "wof:placetype":"venue"
},
  "geometry": {"coordinates":[-71.053777,42.087834],"type":"Point"}
}