{
  "type": "Feature",
  "properties": {
    "addr:full":"38 Oxford St Springfield MA 01108",
    "addr:housenumber":"38",
    "addr:postcode":"01108",
    "addr:street":"Oxford St",
    "iso:country":"US",
    "sg:address":"38 Oxford St",
    "sg:city":"Springfield",
    "sg:classifiers":[
        {
            "category":"Real Estate",
            "subcategory":"Real Estate Operator",
            "type":"Services"
        }
    ],
    "sg:phone":"+1   ",
    "sg:postcode":"01108",
    "sg:province":"MA",
    "sg:tags":[
        "bu",
        "apartment",
        "nonresidential"
    ],
    "wof:name":"145 Sumner Avenue",
    "wof:placetype":"venue"
},
  "geometry": {"coordinates":[-72.57145,42.086174],"type":"Point"}
}