{
  "type": "Feature",
  "properties": {
    "iso:country":"US",
    "sg:address":"683 Bridge St",
    "sg:city":"East Bridgewater",
    "sg:classifiers":[
        {
            "category":"Retail",
            "subcategory":"Repair Shop",
            "type":"Services"
        }
    ],
    "sg:phone":"+1   ",
    "sg:postcode":"02333",
    "sg:province":"MA",
    "sg:tags":[
        "electrical"
    ],
    "wof:name":"A B W Appliance By Whiting",
    "wof:placetype":"venue"
},
  "geometry": {"coordinates":[-70.933184,42.016067],"type":"Point"}
}