{
  "type": "Feature",
  "properties": {
    "iso:country":"US",
    "sg:address":"168 North St",
    "sg:city":"Northampton",
    "sg:classifiers":[
        {
            "category":"Utilities",
            "subcategory":"Telephone",
            "type":"Services"
        }
    ],
    "sg:phone":"+1   ",
    "sg:postcode":"01060",
    "sg:province":"MA",
    "sg:tags":[
        "communications"
    ],
    "wof:name":"Blue Sky Communications",
    "wof:placetype":"venue"
},
  "geometry": {"coordinates":[-72.62842499999999,42.328455],"type":"Point"}
}