{
  "type": "Feature",
  "properties": {
    "iso:country":"US",
    "sg:address":"1068 Washington St",
    "sg:city":"Weymouth",
    "sg:classifiers":[
        {
            "category":"Recreation",
            "type":"Entertainment"
        }
    ],
    "sg:phone":"+1 781 331 6669",
    "sg:postcode":"02189",
    "sg:province":"MA",
    "sg:tags":[
        "psychic",
        "medium"
    ],
    "wof:name":"Middle Earth South",
    "wof:placetype":"venue"
},
  "geometry": {"coordinates":[-70.930122,42.197436],"type":"Point"}
}