{
  "type": "Feature",
  "properties": {
    "addr:full":"370 N Plain Rd Housatonic MA 01236",
    "addr:housenumber":"370",
    "addr:postcode":"01236",
    "addr:street":"N Plain Rd",
    "iso:country":"US",
    "sg:address":"370 N Plain Rd",
    "sg:city":"Housatonic",
    "sg:classifiers":[
        {
            "category":"Building & Trades",
            "subcategory":"Landscaping Services",
            "type":"Services"
        }
    ],
    "sg:phone":"+1   ",
    "sg:postcode":"01236",
    "sg:province":"MA",
    "wof:name":"Johns Organic Garden",
    "wof:placetype":"venue"
},
  "geometry": {"coordinates":[-73.374748,42.249758],"type":"Point"}
}