{
  "type": "Feature",
  "properties": {
    "addr:full":"285 Salem St Malden MA 02148",
    "addr:housenumber":"285",
    "addr:postcode":"02148",
    "addr:street":"Salem St",
    "iso:country":"US",
    "sg:address":"285 Salem St",
    "sg:city":"Malden",
    "sg:classifiers":[
        {
            "category":"Personal",
            "subcategory":"Beauty Salon",
            "type":"Services"
        }
    ],
    "sg:phone":"+1   ",
    "sg:postcode":"02148",
    "sg:province":"MA",
    "sg:tags":[
        "shop"
    ],
    "wof:name":"Bel Bebe",
    "wof:placetype":"venue"
},
  "geometry": {"coordinates":[-71.057166,42.431051],"type":"Point"}
}