{
  "type": "Feature",
  "properties": {
    "iso:country":"US",
    "sg:address":"65 Beacon St",
    "sg:city":"Somerville",
    "sg:classifiers":[
        {
            "category":"Health Services",
            "subcategory":"Doctor",
            "type":"Services"
        }
    ],
    "sg:phone":"+1 617 491 0590",
    "sg:postcode":"02143",
    "sg:province":"MA",
    "sg:tags":[
        "physician",
        "surgeon"
    ],
    "wof:name":"Cambridge Health Alliance Eye",
    "wof:placetype":"venue"
},
  "geometry": {"coordinates":[-71.10252699999999,42.37511],"type":"Point"}
}