{
  "type": "Feature",
  "properties": {
    "addr:full":"185 College Hwy Southwick MA 01077",
    "addr:housenumber":"185",
    "addr:postcode":"01077",
    "addr:street":"College Hwy",
    "iso:country":"US",
    "sg:address":"185 College Hwy",
    "sg:city":"Southwick",
    "sg:classifiers":[
        {
            "category":"Banks & Credit Unions",
            "subcategory":"Bank",
            "type":"Services"
        }
    ],
    "sg:phone":"+1 413 568 9141",
    "sg:postcode":"01077",
    "sg:province":"MA",
    "wof:name":"Woronoco Savings Bank",
    "wof:placetype":"venue"
},
  "geometry": {"coordinates":[-72.789779,42.020092],"type":"Point"}
}