{
  "type": "Feature",
  "properties": {
    "iso:country":"US",
    "sg:address":"45 Lewis St",
    "sg:city":"Lynn",
    "sg:classifiers":[
        {
            "category":"Personal",
            "subcategory":"Beauty Salon",
            "type":"Services"
        }
    ],
    "sg:phone":"+1 781 598 9168",
    "sg:postcode":"01902",
    "sg:province":"MA",
    "wof:name":"Le Masquerade Hair & Tanning",
    "wof:placetype":"venue"
},
  "geometry": {"coordinates":[-70.92750700000001,42.466607],"type":"Point"}
}