{
  "type": "Feature",
  "properties": {
    "addr:full":"50 Concord Sq Roxbury MA 02118",
    "addr:housenumber":"50",
    "addr:postcode":"02118",
    "addr:street":"Concord Sq",
    "iso:country":"US",
    "sg:address":"50 Concord Sq",
    "sg:city":"Roxbury",
    "sg:classifiers":[
        {
            "category":"Personal",
            "subcategory":"Massage",
            "type":"Services"
        },
        {
            "category":"Sports & Exercise",
            "subcategory":"Gym",
            "type":"Entertainment"
        }
    ],
    "sg:phone":"+1 617 421 0825",
    "sg:postcode":"02118",
    "sg:province":"MA",
    "sg:tags":[
        "trainer"
    ],
    "sg:website":"www.southendhealth.com",
    "wof:name":"South End Health Associates",
    "wof:placetype":"venue"
},
  "geometry": {"coordinates":[-71.079234,42.341892],"type":"Point"}
}