{
  "type": "Feature",
  "properties": {
    "iso:country":"US",
    "sg:address":"18 Maine Ave",
    "sg:city":"Easthampton",
    "sg:classifiers":[
        {
            "category":"Bars & Pubs",
            "type":"Food & Drink"
        }
    ],
    "sg:phone":"+1 413 527 9507",
    "sg:postcode":"01027",
    "sg:province":"MA",
    "sg:tags":[
        "lounge",
        "cocktail"
    ],
    "wof:name":"Remember When Lounge",
    "wof:placetype":"venue"
},
  "geometry": {"coordinates":[-72.65351200000001,42.272517],"type":"Point"}
}