{
  "type": "Feature",
  "properties": {
    "iso:country":"US",
    "sg:address":"11 Hall St",
    "sg:city":"Feeding Hills",
    "sg:classifiers":[
        {
            "category":"Autos & Motor Vehicles",
            "subcategory":"Auto Supplies",
            "type":"Retail Goods"
        },
        {
            "category":"Retail",
            "subcategory":"Auto Repair",
            "type":"Services"
        }
    ],
    "sg:phone":"+1 413 786 8100",
    "sg:postcode":"01030",
    "sg:province":"MA",
    "sg:tags":[
        "automobile",
        "top",
        "upholstery"
    ],
    "wof:name":"Vinnies Auto Appearance & Acc",
    "wof:placetype":"venue"
},
  "geometry": {"coordinates":[-72.654776,42.08105],"type":"Point"}
}