{
  "type": "Feature",
  "properties": {
    "iso:country":"US",
    "sg:address":"180 North St",
    "sg:city":"Tewksbury",
    "sg:classifiers":[
        {
            "category":"Building & Trades",
            "subcategory":"Construction",
            "type":"Services"
        }
    ],
    "sg:phone":"+1   ",
    "sg:postcode":"01876",
    "sg:province":"MA",
    "sg:tags":[
        "hanging",
        "contractor"
    ],
    "wof:name":"Final Touch Painting Company",
    "wof:placetype":"venue"
},
  "geometry": {"coordinates":[-71.231307,42.616288],"type":"Point"}
}