{
  "type": "Feature",
  "properties": {
    "addr:full": "180 North St Tewksbury MA 01876",
    "addr:housenumber": "180",
    "addr:postcode": "01876",
    "addr:street": "North St",
    "iso:country": "US",
    "sg:address": "180 North St",
    "sg:city": "Tewksbury",
    "sg:classifiers": [
      {
        "category": "Building \u0026 Trades",
        "subcategory": "Construction",
        "type": "Services"
      }
    ],
    "sg:phone": "+1   ",
    "sg:postcode": "01876",
    "sg:province": "MA",
    "sg:tags": [
      "hanging",
      "contractor"
    ],
    "wof:name": "Final Touch Painting Company",
    "wof:placetype": "venue"
  },
  "geometry": {"coordinates":[-71.231307,42.616288],"type":"Point"}
}
