{
  "type": "Feature",
  "properties": {
    "iso:country":"US",
    "sg:address":"17 Samoset Rd",
    "sg:city":"Peabody",
    "sg:classifiers":[
        {
            "category":"Retail",
            "subcategory":"Laundry & Dry Cleaning",
            "type":"Services"
        }
    ],
    "sg:phone":"+1 978 535 4543",
    "sg:postcode":"01960",
    "sg:province":"MA",
    "sg:tags":[
        "cleaners",
        "rug",
        "carpet"
    ],
    "wof:name":"Richard's Cleaning Svc",
    "wof:placetype":"venue"
},
  "geometry": {"coordinates":[-71.015654,42.544923],"type":"Point"}
}