{
  "type": "Feature",
  "properties": {
    "addr:full": "750 Podunk Rd East Brookfield MA 01515",
    "addr:housenumber": "750",
    "addr:postcode": "01515",
    "addr:street": "Podunk Rd",
    "iso:country": "US",
    "sg:address": "750 Podunk Rd",
    "sg:city": "East Brookfield",
    "sg:classifiers": [
      {
        "category": "Organizations",
        "subcategory": "Community Association",
        "type": "Services"
      }
    ],
    "sg:phone": "+1 508 867 5660",
    "sg:postcode": "01515",
    "sg:province": "MA",
    "sg:tags": [
      "fraternal"
    ],
    "wof:name": "Hayden Lodge AF \u0026 AM",
    "wof:placetype": "venue"
  },
  "geometry": {"coordinates":[-72.033127,42.183558],"type":"Point"}
}
