{
  "type": "Feature",
  "properties": {
    "iso:country":"US",
    "sg:address":"50 Union Ave",
    "sg:city":"Sudbury",
    "sg:classifiers":[
        {
            "category":"Building & Trades",
            "subcategory":"Construction",
            "type":"Services"
        }
    ],
    "sg:phone":"+1 978 443 4955",
    "sg:postcode":"01776",
    "sg:province":"MA",
    "sg:tags":[
        "paving",
        "contractor"
    ],
    "wof:name":"Johnston Paving Co",
    "wof:placetype":"venue"
},
  "geometry": {"coordinates":[-71.421722,42.363617],"type":"Point"}
}