{
  "type": "Feature",
  "properties": {
    "iso:country":"US",
    "sg:address":"270 Huttleston Ave Ste 9",
    "sg:city":"Fairhaven",
    "sg:classifiers":[
        {
            "category":"Shopping",
            "subcategory":"Gifts & Souvenirs",
            "type":"Retail Goods"
        }
    ],
    "sg:phone":"+1 508 984 4930",
    "sg:postcode":"02719",
    "sg:province":"MA",
    "sg:tags":[
        "shop"
    ],
    "wof:name":"Periwinkles",
    "wof:placetype":"venue"
},
  "geometry": {"coordinates":[-70.87130000000001,41.643009],"type":"Point"}
}