{
  "type": "Feature",
  "properties": {
    "addr:full": "270 Huttleston Ave Ste 9 Fairhaven MA 02719",
    "addr:housenumber": "270",
    "addr:postcode": "02719",
    "addr:street": "Huttleston Ave Ste 9",
    "iso:country": "US",
    "ovtr:label": "Periwinkles, 270 Huttleston Ave Fairhaven MA US",
    "ovtr:similarity": 2.8813788890838623,
    "sg:address": "270 Huttleston Ave Ste 9",
    "sg:city": "Fairhaven",
    "sg:classifiers": [
      {
        "category": "Shopping",
        "subcategory": "Gifts \u0026 Souvenirs",
        "type": "Retail Goods"
      }
    ],
    "sg:phone": "+1 508 984 4930",
    "sg:postcode": "02719",
    "sg:province": "MA",
    "sg:tags": [
      "shop"
    ],
    "wof:name": "Periwinkles",
    "wof:placetype": "venue"
  },
  "geometry": {"coordinates":[-70.8713,41.643009],"type":"Point"}
}
