{
  "type": "Feature",
  "properties": {
    "addr:full": "297 Weston Rd Wellesley MA 02482",
    "addr:housenumber": "297",
    "addr:postcode": "02482",
    "addr:street": "Weston Rd",
    "iso:country": "US",
    "sg:address": "297 Weston Rd",
    "sg:city": "Wellesley",
    "sg:classifiers": [
      {
        "category": "Professional",
        "subcategory": "Lawyer \u0026 Legal Services",
        "type": "Services"
      }
    ],
    "sg:phone": "+1 781 407 9001",
    "sg:postcode": "02482",
    "sg:province": "MA",
    "sg:tags": [
      "divorce",
      "attorney",
      "law",
      "family"
    ],
    "wof:name": "Massachusetts Family Law Group",
    "wof:placetype": "venue"
  },
  "geometry": {"coordinates":[-71.311623,42.304272],"type":"Point"}
}
