{
  "type": "Feature",
  "properties": {
    "iso:country":"US",
    "sg:address":"297 Weston Rd",
    "sg:city":"Wellesley",
    "sg:classifiers":[
        {
            "category":"Professional",
            "subcategory":"Lawyer & Legal Services",
            "type":"Services"
        }
    ],
    "sg:phone":"+1 781 407 9001",
    "sg:postcode":"02482",
    "sg:province":"MA",
    "sg:tags":[
        "divorce",
        "attorney",
        "law",
        "family"
    ],
    "wof:name":"Massachusetts Family Law Group",
    "wof:placetype":"venue"
},
  "geometry": {"coordinates":[-71.311623,42.304272],"type":"Point"}
}