{
  "type": "Feature",
  "properties": {
    "addr:full":"17 Shad Hole Rd Dennis Port MA 02639",
    "addr:housenumber":"17",
    "addr:postcode":"02639",
    "addr:street":"Shad Hole Rd",
    "iso:country":"US",
    "sg:address":"17 Shad Hole Rd",
    "sg:city":"Dennis Port",
    "sg:classifiers":[
        {
            "category":"Manufacturing",
            "subcategory":"Printing",
            "type":"Manufacturing & Wholesale Goods"
        }
    ],
    "sg:phone":"+1 508 760 1601",
    "sg:postcode":"02639",
    "sg:province":"MA",
    "sg:tags":[
        "printer"
    ],
    "sg:website":"www.craneduplicating.com",
    "wof:name":"Crane Duplicating Svc",
    "wof:placetype":"venue"
},
  "geometry": {"coordinates":[-70.14364500000001,41.666113],"type":"Point"}
}