{
  "type": "Feature",
  "properties": {
    "iso:country":"US",
    "sg:address":"5 Man Mar Dr Unit 4",
    "sg:city":"Plainville",
    "sg:classifiers":[
        {
            "category":"Home & Garden",
            "subcategory":"Carpets & Floor Coverings",
            "type":"Retail Goods"
        }
    ],
    "sg:phone":"+1 508 643 0710",
    "sg:postcode":"02762",
    "sg:province":"MA",
    "sg:tags":[
        "carpeting"
    ],
    "wof:name":"Cannata Tile & Carpet Inc - CLOSED",
    "wof:placetype":"venue"
},
  "geometry": {"coordinates":[-71.306297,42.0093],"type":"Point"}
}