{
  "type": "Feature",
  "properties": {
    "addr:full": "5 Man Mar Dr Unit 4 Plainville MA 02762",
    "addr:housenumber": "5;4",
    "addr:postcode": "02762",
    "addr:street": "Man Mar Dr Unit",
    "iso:country": "US",
    "sg:address": "5 Man Mar Dr Unit 4",
    "sg:city": "Plainville",
    "sg:classifiers": [
      {
        "category": "Home \u0026 Garden",
        "subcategory": "Carpets \u0026 Floor Coverings",
        "type": "Retail Goods"
      }
    ],
    "sg:phone": "+1 508 643 0710",
    "sg:postcode": "02762",
    "sg:province": "MA",
    "sg:tags": [
      "carpeting"
    ],
    "wof:name": "Cannata Tile \u0026 Carpet Inc - CLOSED",
    "wof:placetype": "venue"
  },
  "geometry": {"coordinates":[-71.306297,42.0093],"type":"Point"}
}
