{
  "type": "Feature",
  "properties": {
    "addr:full": "739 College Hwy Southwick MA 01077",
    "addr:housenumber": "739",
    "addr:postcode": "01077",
    "addr:street": "College Hwy",
    "iso:country": "US",
    "sg:address": "739 College Hwy",
    "sg:city": "Southwick",
    "sg:classifiers": [
      {
        "category": "Professional",
        "subcategory": "Lawyer \u0026 Legal Services",
        "type": "Services"
      }
    ],
    "sg:phone": "+1   ",
    "sg:postcode": "01077",
    "sg:province": "MA",
    "wof:name": "William J Nejam Jr",
    "wof:placetype": "venue"
  },
  "geometry": {"coordinates":[-72.768593,42.078084],"type":"Point"}
}
