{
  "type": "Feature",
  "properties": {
    "addr:full":"2041 Boston Rd Wilbraham MA 01095",
    "addr:housenumber":"2041",
    "addr:postcode":"01095",
    "addr:street":"Boston Rd",
    "iso:country":"US",
    "sg:address":"2041 Boston Rd",
    "sg:city":"Wilbraham",
    "sg:classifiers":[
        {
            "category":"Shopping",
            "subcategory":"Bicycles & Sporting Goods",
            "type":"Retail Goods"
        }
    ],
    "sg:phone":"+1 413 543 1499",
    "sg:postcode":"01095",
    "sg:province":"MA",
    "sg:tags":[
        "skating",
        "equipment",
        "supply"
    ],
    "wof:name":"On Ramp Skate Shop",
    "wof:placetype":"venue"
},
  "geometry": {"coordinates":[-72.47513600000001,42.149282],"type":"Point"}
}