{
  "type": "Feature",
  "properties": {
    "iso:country":"US",
    "sg:address":"1147 Mohawk Trl",
    "sg:city":"Shelburne Falls",
    "sg:classifiers":[
        {
            "category":"Manufacturing",
            "subcategory":"Wood Products",
            "type":"Manufacturing & Wholesale Goods"
        }
    ],
    "sg:phone":"+1 413 625 9226",
    "sg:postcode":"01370",
    "sg:province":"MA",
    "sg:tags":[
        "container",
        "mfg"
    ],
    "wof:name":"Woven Wood Baskets",
    "wof:placetype":"venue"
},
  "geometry": {"coordinates":[-72.671122,42.610123],"type":"Point"}
}