{
  "type": "Feature",
  "properties": {
    "addr:full": "34 School St Foxboro MA 02035",
    "addr:housenumber": "34",
    "addr:postcode": "02035",
    "addr:street": "School St",
    "iso:country": "US",
    "sg:address": "34 School St",
    "sg:city": "Foxboro",
    "sg:classifiers": [
      {
        "category": "Manufacturing",
        "subcategory": "Tools \u0026 Machinery",
        "type": "Manufacturing \u0026 Wholesale Goods"
      }
    ],
    "sg:phone": "+1 508 698 3611",
    "sg:postcode": "02035",
    "sg:province": "MA",
    "sg:tags": [
      "peripheral",
      "computer"
    ],
    "wof:name": "Nematron Corp",
    "wof:placetype": "venue"
  },
  "geometry": {"coordinates":[-71.250605,42.064319],"type":"Point"}
}
