{
  "type": "Feature",
  "properties": {
    "iso:country":"US",
    "sg:address":"7 Billings St",
    "sg:city":"Acton",
    "sg:classifiers":[
        {
            "category":"Arts & Performance",
            "subcategory":"Theater",
            "type":"Entertainment"
        }
    ],
    "sg:phone":"+1 978 263 7523",
    "sg:postcode":"01720",
    "sg:province":"MA",
    "sg:tags":[
        "live",
        "music"
    ],
    "wof:name":"Dave Young Country",
    "wof:placetype":"venue"
},
  "geometry": {"coordinates":[-71.471716,42.458774],"type":"Point"}
}