{
  "type": "Feature",
  "properties": {
    "iso:country":"US",
    "sg:address":"169 Cummins Hwy",
    "sg:city":"Roslindale",
    "sg:classifiers":[
        {
            "category":"Organizations",
            "subcategory":"Religious Organization",
            "type":"Services"
        }
    ],
    "sg:phone":"+1 617 325 3322",
    "sg:postcode":"02131",
    "sg:province":"MA",
    "sg:tags":[
        "church"
    ],
    "sg:website":"www.sh-roslindale.org",
    "wof:name":"Sacred Heart Rectory",
    "wof:placetype":"venue"
},
  "geometry": {"coordinates":[-71.12310100000001,42.282182],"type":"Point"}
}