{
  "type": "Feature",
  "properties": {
    "addr:full": "169 Cummins Hwy Roslindale MA 02131",
    "addr:housenumber": "169",
    "addr:postcode": "02131",
    "addr:street": "Cummins Hwy",
    "iso:country": "US",
    "sg:address": "169 Cummins Hwy",
    "sg:city": "Roslindale",
    "sg:classifiers": [
      {
        "category": "Organizations",
        "subcategory": "Religious Organization",
        "type": "Services"
      }
    ],
    "sg:phone": "+1 617 325 3322",
    "sg:postcode": "02131",
    "sg:province": "MA",
    "sg:tags": [
      "church"
    ],
    "sg:website": "www.sh-roslindale.org",
    "wof:name": "Sacred Heart Rectory",
    "wof:placetype": "venue"
  },
  "geometry": {"coordinates":[-71.123101,42.282182],"type":"Point"}
}
