{
  "type": "Feature",
  "properties": {
    "addr:full": "44 Country Corners Rd Amherst MA 01002",
    "addr:housenumber": "44",
    "addr:postcode": "01002",
    "addr:street": "Country Corners Rd",
    "iso:country": "US",
    "sg:address": "44 Country Corners Rd",
    "sg:city": "Amherst",
    "sg:classifiers": [
      {
        "category": "Professional",
        "type": "Services"
      }
    ],
    "sg:phone": "+1   ",
    "sg:postcode": "01002",
    "sg:province": "MA",
    "wof:name": "Hampshire Village Cmnty Corp",
    "wof:placetype": "venue"
  },
  "geometry": {"coordinates":[-72.535203,42.314667],"type":"Point"}
}
