{
  "type": "Feature",
  "properties": {
    "iso:country":"US",
    "sg:address":"26 Concord Rd",
    "sg:city":"Sudbury",
    "sg:classifiers":[
        {
            "category":"Organizations",
            "subcategory":"Religious Organization",
            "type":"Services"
        }
    ],
    "sg:phone":"+1 978 443 3885",
    "sg:postcode":"01776",
    "sg:province":"MA",
    "sg:tags":[
        "church"
    ],
    "wof:name":"Memorial Congregational Church",
    "wof:placetype":"venue"
},
  "geometry": {"coordinates":[-71.415938,42.363413],"type":"Point"}
}