{
  "type": "Feature",
  "properties": {
    "addr:full": "26 Concord Rd Sudbury MA 01776",
    "addr:housenumber": "26",
    "addr:postcode": "01776",
    "addr:street": "Concord Rd",
    "iso:country": "US",
    "ovtr:label": "Memorial Congregational Church, 26 Concord Rd Sudbury MA US",
    "ovtr:similarity": 3.2339839935302734,
    "sg:address": "26 Concord Rd",
    "sg:city": "Sudbury",
    "sg:classifiers": [
      {
        "category": "Organizations",
        "subcategory": "Religious Organization",
        "type": "Services"
      }
    ],
    "sg:phone": "+1 978 443 3885",
    "sg:postcode": "01776",
    "sg:province": "MA",
    "sg:tags": [
      "church"
    ],
    "wof:name": "Memorial Congregational Church",
    "wof:placetype": "venue"
  },
  "geometry": {"coordinates":[-71.415938,42.363413],"type":"Point"}
}
