{
  "type": "Feature",
  "properties": {
    "iso:country":"US",
    "sg:address":"213 N Main St",
    "sg:city":"North Brookfield",
    "sg:classifiers":[
        {
            "category":"Food & Beverages",
            "subcategory":"Liquor & Beverages",
            "type":"Retail Goods"
        }
    ],
    "sg:phone":"+1 508 867 6677",
    "sg:postcode":"01535",
    "sg:province":"MA",
    "wof:name":"Colonial Spirit Inc",
    "wof:placetype":"venue"
},
  "geometry": {"coordinates":[-72.08564,42.270166],"type":"Point"}
}