{
  "type": "Feature",
  "properties": {
    "addr:full":"1 South St Bernardston MA 01337",
    "addr:housenumber":"1",
    "addr:postcode":"01337",
    "addr:street":"South St",
    "iso:country":"US",
    "sg:address":"1 South St",
    "sg:city":"Bernardston",
    "sg:classifiers":[
        {
            "category":"Restaurant",
            "type":"Food & Drink"
        }
    ],
    "sg:phone":"+1 413 648 9800",
    "sg:postcode":"01337",
    "sg:province":"MA",
    "wof:name":"Red House Pizzeria",
    "wof:placetype":"venue"
},
  "geometry": {"coordinates":[-72.55699199999999,42.663972],"type":"Point"}
}