{
  "type": "Feature",
  "properties": {
    "iso:country":"US",
    "sg:address":"4 Southern Ave",
    "sg:city":"Essex",
    "sg:classifiers":[
        {
            "category":"Shopping",
            "subcategory":"Used Merchandise",
            "type":"Retail Goods"
        }
    ],
    "sg:phone":"+1 978 768 7716",
    "sg:postcode":"01929",
    "sg:province":"MA",
    "sg:tags":[
        "antique"
    ],
    "wof:name":"Joshua's Corner Antiques",
    "wof:placetype":"venue"
},
  "geometry": {"coordinates":[-70.77116700000001,42.628435],"type":"Point"}
}