{
  "type": "Feature",
  "properties": {
    "addr:full": "4 Southern Ave Essex MA 01929",
    "addr:housenumber": "4",
    "addr:postcode": "01929",
    "addr:street": "Southern Ave",
    "iso:country": "US",
    "sg:address": "4 Southern Ave",
    "sg:city": "Essex",
    "sg:classifiers": [
      {
        "category": "Shopping",
        "subcategory": "Used Merchandise",
        "type": "Retail Goods"
      }
    ],
    "sg:phone": "+1 978 768 7716",
    "sg:postcode": "01929",
    "sg:province": "MA",
    "sg:tags": [
      "antique"
    ],
    "wof:name": "Joshua's Corner Antiques",
    "wof:placetype": "venue"
  },
  "geometry": {"coordinates":[-70.771167,42.628435],"type":"Point"}
}
