{
  "type": "Feature",
  "properties": {
    "addr:full": "17 Walnut St Danvers MA 01923",
    "addr:housenumber": "17",
    "addr:postcode": "01923",
    "addr:street": "Walnut St",
    "iso:country": "US",
    "sg:address": "17 Walnut St",
    "sg:city": "Danvers",
    "sg:classifiers": [
      {
        "category": "Social Services",
        "type": "Services"
      }
    ],
    "sg:phone": "+1 978 524 5314",
    "sg:postcode": "01923",
    "sg:province": "MA",
    "sg:tags": [
      "counselor",
      "marriage",
      "family"
    ],
    "wof:name": "Shelly Powell",
    "wof:placetype": "venue"
  },
  "geometry": {"coordinates":[-70.961774,42.561299],"type":"Point"}
}
