{
  "type": "Feature",
  "properties": {
    "addr:full": "30 Ridlon Rd Mattapan MA 02126",
    "addr:housenumber": "30",
    "addr:postcode": "02126",
    "addr:street": "Ridlon Rd",
    "iso:country": "US",
    "sg:address": "30 Ridlon Rd",
    "sg:city": "Mattapan",
    "sg:classifiers": [
      {
        "category": "Communications",
        "subcategory": "Film \u0026 Video Production",
        "type": "Services"
      }
    ],
    "sg:phone": "+1 617 276 3340",
    "sg:postcode": "02126",
    "sg:province": "MA",
    "sg:tags": [
      "audio"
    ],
    "wof:name": "Extreme Productions",
    "wof:placetype": "venue"
  },
  "geometry": {"coordinates":[-71.105966,42.270176],"type":"Point"}
}
