{
  "type": "Feature",
  "properties": {
    "iso:country":"US",
    "sg:address":"30 Ridlon Rd",
    "sg:city":"Mattapan",
    "sg:classifiers":[
        {
            "category":"Communications",
            "subcategory":"Film & Video Production",
            "type":"Services"
        }
    ],
    "sg:phone":"+1 617 276 3340",
    "sg:postcode":"02126",
    "sg:province":"MA",
    "sg:tags":[
        "audio"
    ],
    "wof:name":"Extreme Productions",
    "wof:placetype":"venue"
},
  "geometry": {"coordinates":[-71.105966,42.270176],"type":"Point"}
}