{
  "type": "Feature",
  "properties": {
    "iso:country":"US",
    "sg:address":"275 Main St",
    "sg:city":"Rowley",
    "sg:classifiers":[
        {
            "category":"Shopping",
            "subcategory":"Used Merchandise",
            "type":"Retail Goods"
        }
    ],
    "sg:phone":"+1 978 948 2217",
    "sg:postcode":"01969",
    "sg:province":"MA",
    "sg:tags":[
        "antique"
    ],
    "wof:name":"Todd Farm Antiques",
    "wof:placetype":"venue"
},
  "geometry": {"coordinates":[-70.872229,42.720365],"type":"Point"}
}