{
  "type": "Feature",
  "properties": {
    "addr:full": "293 Littleton Rd Chelmsford MA 01824",
    "addr:housenumber": "293",
    "addr:postcode": "01824",
    "addr:street": "Littleton Rd",
    "iso:country": "US",
    "sg:address": "293 Littleton Rd",
    "sg:city": "Chelmsford",
    "sg:classifiers": [
      {
        "category": "Retail",
        "subcategory": "Auto Repair",
        "type": "Services"
      }
    ],
    "sg:phone": "+1 978 399 0008",
    "sg:postcode": "01824",
    "sg:province": "MA",
    "sg:tags": [
      "towing",
      "wrecker"
    ],
    "wof:name": "Halpin's Towing",
    "wof:placetype": "venue"
  },
  "geometry": {"coordinates":[-71.386398,42.583099],"type":"Point"}
}
