{
  "type": "Feature",
  "properties": {
    "addr:full":"29 N Sullivan Rd Charlton MA 01507",
    "addr:housenumber":"29",
    "addr:postcode":"01507",
    "addr:street":"N Sullivan Rd",
    "iso:country":"US",
    "sg:address":"29 N Sullivan Rd",
    "sg:city":"Charlton",
    "sg:classifiers":[
        {
            "category":"Retail",
            "subcategory":"Pet Boarding",
            "type":"Services"
        }
    ],
    "sg:phone":"+1 508 248 9993",
    "sg:postcode":"01507",
    "sg:province":"MA",
    "sg:tags":[
        "boarding/pet",
        "sitting"
    ],
    "sg:website":"www.tallpinefarm.net",
    "wof:name":"Tall Pine Farm and Kennel",
    "wof:placetype":"venue"
},
  "geometry": {"coordinates":[-72.008117,42.15638],"type":"Point"}
}