{
  "type": "Feature",
  "properties": {
    "addr:full":"91 Manville St Leicester MA 01524",
    "addr:housenumber":"91",
    "addr:postcode":"01524",
    "addr:street":"Manville St",
    "iso:country":"US",
    "sg:address":"91 Manville St",
    "sg:city":"Leicester",
    "sg:classifiers":[
        {
            "category":"Organizations",
            "subcategory":"Community Association",
            "type":"Services"
        }
    ],
    "sg:phone":"+1 508 892 4528",
    "sg:postcode":"01524",
    "sg:province":"MA",
    "sg:tags":[
        "fraternal"
    ],
    "wof:name":"Knights Of Columbus",
    "wof:placetype":"venue"
},
  "geometry": {"coordinates":[-71.893823,42.251357],"type":"Point"}
}