{
  "type": "Feature",
  "properties": {
    "iso:country":"US",
    "sg:address":"31 Union Ave",
    "sg:city":"Sudbury",
    "sg:classifiers":[
        {
            "category":"Building & Trades",
            "subcategory":"Construction",
            "type":"Services"
        }
    ],
    "sg:phone":"+1 978 440 8111",
    "sg:postcode":"01776",
    "sg:province":"MA",
    "sg:tags":[
        "general",
        "contractor"
    ],
    "wof:name":"Osvold Construction",
    "wof:placetype":"venue"
},
  "geometry": {"coordinates":[-71.42227200000001,42.362943],"type":"Point"}
}