{
  "type": "Feature",
  "properties": {
    "addr:full":"249 Vanderbilt Ave Norwood MA 02062",
    "addr:housenumber":"249",
    "addr:postcode":"02062",
    "addr:street":"Vanderbilt Ave",
    "iso:country":"US",
    "sg:address":"249 Vanderbilt Ave",
    "sg:city":"Norwood",
    "sg:classifiers":[
        {
            "category":"Communications",
            "subcategory":"Newspaper",
            "type":"Services"
        }
    ],
    "sg:phone":"+1 781 501 7000",
    "sg:postcode":"02062",
    "sg:province":"MA",
    "sg:tags":[
        "magazine"
    ],
    "wof:name":"Ebsco Industires",
    "wof:placetype":"venue"
},
  "geometry": {"coordinates":[-71.189637,42.172025],"type":"Point"}
}