{
  "type": "Feature",
  "properties": {
    "iso:country":"US",
    "sg:address":"114 Briarcliff Ln",
    "sg:city":"Holliston",
    "sg:classifiers":[
        {
            "category":"Professional",
            "subcategory":"Secretarial Services",
            "type":"Services"
        }
    ],
    "sg:phone":"+1 508 429 2787",
    "sg:postcode":"01746",
    "sg:province":"MA",
    "sg:tags":[
        "processing",
        "word"
    ],
    "wof:name":"Accu Writers",
    "wof:placetype":"venue"
},
  "geometry": {"coordinates":[-71.468296,42.210019],"type":"Point"}
}