{
  "type": "Feature",
  "properties": {
    "iso:country":"US",
    "sg:address":"845 S Franklin St",
    "sg:city":"Holbrook",
    "sg:classifiers":[
        {
            "category":"Manufacturing",
            "subcategory":"Petroleum Products",
            "type":"Manufacturing & Wholesale Goods"
        }
    ],
    "sg:phone":"+1 781 767 9400",
    "sg:postcode":"02343",
    "sg:province":"MA",
    "wof:name":"Super Petroleum Inc",
    "wof:placetype":"venue"
},
  "geometry": {"coordinates":[-71.009711,42.127182],"type":"Point"}
}