{
  "type": "Feature",
  "properties": {
    "addr:full": "438 W Central St Franklin MA 02038",
    "addr:housenumber": "438",
    "addr:postcode": "02038",
    "addr:street": "W Central St",
    "iso:country": "US",
    "sg:address": "438 W Central St",
    "sg:city": "Franklin",
    "sg:classifiers": [
      {
        "category": "Professional",
        "subcategory": "Accounting \u0026 Tax Preparation",
        "type": "Services"
      }
    ],
    "sg:phone": "+1 508 528 0930",
    "sg:postcode": "02038",
    "sg:province": "MA",
    "sg:tags": [
      "bookkeeping",
      "billing"
    ],
    "wof:name": "Ranieri Management Inc",
    "wof:placetype": "venue"
  },
  "geometry": {"coordinates":[-71.416955,42.08874],"type":"Point"}
}
