{
  "type": "Feature",
  "properties": {
    "iso:country":"US",
    "sg:address":"29 S Mill St",
    "sg:city":"Hopkinton",
    "sg:classifiers":[
        {
            "category":"Wholesale",
            "subcategory":"Furniture",
            "type":"Manufacturing & Wholesale Goods"
        }
    ],
    "sg:phone":"+1 508 435 5779",
    "sg:postcode":"01748",
    "sg:province":"MA",
    "sg:tags":[
        "equipment",
        "library",
        "supply"
    ],
    "wof:name":"Tucker Library Interiors LLC",
    "wof:placetype":"venue"
},
  "geometry": {"coordinates":[-71.485355,42.214396],"type":"Point"}
}