{
  "type": "Feature",
  "properties": {
    "addr:full": "29 S Mill St Hopkinton MA 01748",
    "addr:housenumber": "29",
    "addr:postcode": "01748",
    "addr:street": "S Mill St",
    "iso:country": "US",
    "sg:address": "29 S Mill St",
    "sg:city": "Hopkinton",
    "sg:classifiers": [
      {
        "category": "Wholesale",
        "subcategory": "Furniture",
        "type": "Manufacturing \u0026 Wholesale Goods"
      }
    ],
    "sg:phone": "+1 508 435 5779",
    "sg:postcode": "01748",
    "sg:province": "MA",
    "sg:tags": [
      "equipment",
      "library",
      "supply"
    ],
    "wof:name": "Tucker Library Interiors LLC",
    "wof:placetype": "venue"
  },
  "geometry": {"coordinates":[-71.485355,42.214396],"type":"Point"}
}
