{
  "type": "Feature",
  "properties": {
    "iso:country":"US",
    "sg:address":"971 Park St",
    "sg:city":"Stoughton",
    "sg:classifiers":[
        {
            "category":"Professional",
            "subcategory":"Accounting & Tax Preparation",
            "type":"Services"
        }
    ],
    "sg:phone":"+1 781 436 3434",
    "sg:postcode":"02072",
    "sg:province":"MA",
    "sg:tags":[
        "return",
        "preparation-business"
    ],
    "wof:name":"Tailored Tax Centers",
    "wof:placetype":"venue"
},
  "geometry": {"coordinates":[-71.072502,42.111041],"type":"Point"}
}