{
  "type": "Feature",
  "properties": {
    "addr:full":"15 Cross St Stoughton MA 02072",
    "addr:housenumber":"15",
    "addr:postcode":"02072",
    "addr:street":"Cross St",
    "iso:country":"US",
    "sg:address":"15 Cross St",
    "sg:city":"Stoughton",
    "sg:classifiers":[
        {
            "category":"Shopping",
            "subcategory":"Hobbies, Toys, & Games",
            "type":"Retail Goods"
        }
    ],
    "sg:phone":"+1 781 344 6272",
    "sg:postcode":"02072",
    "sg:province":"MA",
    "sg:tags":[
        "supply"
    ],
    "wof:name":"Art's Automobilia",
    "wof:placetype":"venue"
},
  "geometry": {"coordinates":[-71.116254,42.134927],"type":"Point"}
}