{
  "type": "Feature",
  "properties": {
    "iso:country":"US",
    "sg:address":"80 Maple Ave",
    "sg:city":"Great Barrington",
    "sg:classifiers":[
        {
            "category":"Professional",
            "subcategory":"Accounting & Tax Preparation",
            "type":"Services"
        }
    ],
    "sg:phone":"+1 413 528 3880",
    "sg:postcode":"01230",
    "sg:province":"MA",
    "sg:tags":[
        "accountant"
    ],
    "wof:name":"Thomas J Major CPA",
    "wof:placetype":"venue"
},
  "geometry": {"coordinates":[-73.367306,42.186826],"type":"Point"}
}