{
  "type": "Feature",
  "properties": {
    "iso:country":"US",
    "sg:address":"3 Wallis Court",
    "sg:city":"Lexington",
    "sg:classifiers":[
        {
            "category":"Sports & Exercise",
            "subcategory":"Gym",
            "type":"Entertainment"
        }
    ],
    "sg:phone":"+1 781 861 8077",
    "sg:postcode":"02421",
    "sg:province":"MA",
    "sg:tags":[
        "trainer"
    ],
    "wof:name":"Schlein Stephen Dr",
    "wof:placetype":"venue"
},
  "geometry": {"coordinates":[-71.224819,42.446539],"type":"Point"}
}