{
  "type": "Feature",
  "properties": {
    "addr:full":"717 Beaver St Waltham MA 02452",
    "addr:housenumber":"717",
    "addr:postcode":"02452",
    "addr:street":"Beaver St",
    "iso:country":"US",
    "sg:address":"717 Beaver St",
    "sg:city":"Waltham",
    "sg:classifiers":[
        {
            "category":"Professional",
            "subcategory":"Art Services",
            "type":"Services"
        }
    ],
    "sg:phone":"+1   ",
    "sg:postcode":"02452",
    "sg:province":"MA",
    "sg:tags":[
        "commercial",
        "design"
    ],
    "wof:name":"Digital Graphics Co",
    "wof:placetype":"venue"
},
  "geometry": {"coordinates":[-71.23319600000001,42.385734],"type":"Point"}
}