{
  "type": "Feature",
  "properties": {
    "addr:full": "30 Kneeland Street Ofc Boston MA 02111",
    "addr:housenumber": "30",
    "addr:postcode": "02111",
    "addr:street": "Kneeland Street",
    "iso:country": "US",
    "sg:address": "30 Kneeland Street Ofc",
    "sg:city": "Boston",
    "sg:classifiers": [
      {
        "category": "Professional",
        "subcategory": "Accounting \u0026 Tax Preparation",
        "type": "Services"
      },
      {
        "category": "Professional",
        "subcategory": "Lawyer \u0026 Legal Services",
        "type": "Services"
      }
    ],
    "sg:phone": "+1 617 482 6865",
    "sg:postcode": "02111",
    "sg:province": "MA",
    "sg:tags": [
      "accountant"
    ],
    "wof:name": "Yee Kenneth M P Lwyr",
    "wof:placetype": "venue"
  },
  "geometry": {"coordinates":[-71.062008,42.350792],"type":"Point"}
}
