{
  "type": "Feature",
  "properties": {
    "addr:full":"11 Sylvan St Danvers MA 01923",
    "addr:housenumber":"11",
    "addr:postcode":"01923",
    "addr:street":"Sylvan St",
    "iso:country":"US",
    "sg:address":"11 Sylvan St",
    "sg:city":"Danvers",
    "sg:classifiers":[
        {
            "category":"Real Estate",
            "subcategory":"Real Estate Agent",
            "type":"Services"
        }
    ],
    "sg:phone":"+1 978 777 3003",
    "sg:postcode":"01923",
    "sg:province":"MA",
    "wof:name":"Kilborn Property Consultants",
    "wof:placetype":"venue"
},
  "geometry": {"coordinates":[-70.939278,42.562432],"type":"Point"}
}