{
  "type": "Feature",
  "properties": {
    "iso:country":"US",
    "sg:address":"528 American Legion Highway",
    "sg:city":"Boston",
    "sg:classifiers":[
        {
            "category":"Ice Cream",
            "type":"Food & Drink"
        }
    ],
    "sg:postcode":"02131",
    "sg:province":"MA",
    "sg:tags":[
        "frozen",
        "yogurt"
    ],
    "wof:name":"Frosty Freeze",
    "wof:placetype":"venue"
},
  "geometry": {"coordinates":[-71.10691,42.287507],"type":"Point"}
}