{
  "type": "Feature",
  "properties": {
    "iso:country":"US",
    "sg:address":"999 N Main St",
    "sg:city":"Randolph",
    "sg:classifiers":[
        {
            "category":"Health Services",
            "subcategory":"Doctor",
            "type":"Services"
        }
    ],
    "sg:phone":"+1 781 961 1330",
    "sg:postcode":"02368",
    "sg:province":"MA",
    "sg:tags":[
        "medicine",
        "internal"
    ],
    "wof:name":"Glasman Ann",
    "wof:placetype":"venue"
},
  "geometry": {"coordinates":[-71.05799399999999,42.189984],"type":"Point"}
}