{
  "type": "Feature",
  "properties": {
    "addr:full": "30 Church St Belmont MA 02478",
    "addr:housenumber": "30",
    "addr:postcode": "02478",
    "addr:street": "Church St",
    "iso:country": "US",
    "sg:address": "30 Church St",
    "sg:city": "Belmont",
    "sg:classifiers": [
      {
        "category": "Professional",
        "subcategory": "Accounting \u0026 Tax Preparation",
        "type": "Services"
      }
    ],
    "sg:phone": "+1 617 489 7554",
    "sg:postcode": "02478",
    "sg:province": "MA",
    "sg:tags": [
      "transmission",
      "return"
    ],
    "wof:name": "Noreen M Millane Acctg \u0026 Tax",
    "wof:placetype": "venue"
  },
  "geometry": {"coordinates":[-71.190786,42.38706],"type":"Point"}
}
