{
  "type": "Feature",
  "properties": {
    "iso:country":"US",
    "sg:address":"114 North St",
    "sg:city":"Middleboro",
    "sg:classifiers":[
        {
            "category":"Retail",
            "subcategory":"Auto Repair",
            "type":"Services"
        }
    ],
    "sg:phone":"+1 508 947 2857",
    "sg:postcode":"02346",
    "sg:province":"MA",
    "sg:tags":[
        "wheel",
        "axle",
        "alignment"
    ],
    "wof:name":"Herb's Front End Shop",
    "wof:placetype":"venue"
},
  "geometry": {"coordinates":[-70.91615299999999,41.905267],"type":"Point"}
}