{
  "type": "Feature",
  "properties": {
    "addr:full": "5 Central St Stoneham MA 02180",
    "addr:housenumber": "5",
    "addr:postcode": "02180",
    "addr:street": "Central St",
    "iso:country": "US",
    "sg:address": "5 Central St",
    "sg:city": "Stoneham",
    "sg:classifiers": [
      {
        "category": "Building \u0026 Trades",
        "subcategory": "Landscaping Services",
        "type": "Services"
      }
    ],
    "sg:phone": "+1 781 438 3088",
    "sg:postcode": "02180",
    "sg:province": "MA",
    "sg:tags": [
      "designer",
      "landscape"
    ],
    "sg:website": "www.williamfleming.com",
    "wof:name": "William Fleming Assoc",
    "wof:placetype": "venue"
  },
  "geometry": {"coordinates":[-71.099257,42.480209],"type":"Point"}
}
