{
  "type": "Feature",
  "properties": {
    "iso:country":"US",
    "sg:address":"25 Kingston St Ste B1",
    "sg:city":"Boston",
    "sg:classifiers":[
        {
            "category":"Sports & Exercise",
            "subcategory":"Bicycle Rental",
            "type":"Entertainment"
        }
    ],
    "sg:phone":"+1 617 426 7181",
    "sg:postcode":"02111",
    "sg:province":"MA",
    "sg:tags":[
        "wear"
    ],
    "sg:website":"www.westoncentreboston.com",
    "wof:name":"Boston Skyline",
    "wof:placetype":"venue"
},
  "geometry": {"coordinates":[-71.058899,42.353802],"type":"Point"}
}