{
  "type": "Feature",
  "properties": {
    "addr:full": "1109 Whipple Rd Tewksbury MA 01876",
    "addr:housenumber": "1109",
    "addr:postcode": "01876",
    "addr:street": "Whipple Rd",
    "iso:country": "US",
    "sg:address": "1109 Whipple Rd",
    "sg:city": "Tewksbury",
    "sg:classifiers": [
      {
        "category": "Professional",
        "subcategory": "Business Services",
        "type": "Services"
      }
    ],
    "sg:phone": "+1   ",
    "sg:postcode": "01876",
    "sg:province": "MA",
    "wof:name": "Boss Express Incorporated",
    "wof:placetype": "venue"
  },
  "geometry": {"coordinates":[-71.24225,42.592268],"type":"Point"}
}
