{
  "type": "Feature",
  "properties": {
    "addr:full":"23 Marion Dr Tewksbury MA 01876",
    "addr:housenumber":"23",
    "addr:postcode":"01876",
    "addr:street":"Marion Dr",
    "iso:country":"US",
    "sg:address":"23 Marion Dr",
    "sg:city":"Tewksbury",
    "sg:classifiers":[
        {
            "category":"Professional",
            "type":"Services"
        }
    ],
    "sg:phone":"+1   ",
    "sg:postcode":"01876",
    "sg:province":"MA",
    "wof:name":"Kaufman Mico Sculpture Inc",
    "wof:placetype":"venue"
},
  "geometry": {"coordinates":[-71.234408,42.632127],"type":"Point"}
}