{
  "type": "Feature",
  "properties": {
    "addr:full": "152 Hampden Street Roxbury MA 02119",
    "addr:housenumber": "152",
    "addr:postcode": "02119",
    "addr:street": "Hampden Street",
    "iso:country": "US",
    "sg:address": "152 Hampden Street",
    "sg:city": "Roxbury",
    "sg:classifiers": [
      {
        "category": "Building \u0026 Trades",
        "subcategory": "Construction",
        "type": "Services"
      }
    ],
    "sg:phone": "+1 617 541 8999",
    "sg:postcode": "02119",
    "sg:province": "MA",
    "sg:tags": [
      "contractor"
    ],
    "wof:name": "Giugliano Construction Company",
    "wof:placetype": "venue"
  },
  "geometry": {"coordinates":[-71.075275,42.327852],"type":"Point"}
}
