{
  "type": "Feature",
  "properties": {
    "iso:country":"US",
    "sg:address":"215 Boston Post Rd",
    "sg:city":"Weston",
    "sg:classifiers":[
        {
            "category":"Professional",
            "subcategory":"Business Services",
            "type":"Services"
        }
    ],
    "sg:phone":"+1 781 647 8585",
    "sg:postcode":"02493",
    "sg:province":"MA",
    "sg:tags":[
        "interior",
        "consultant",
        "design",
        "decorator"
    ],
    "wof:name":"Anamika Design",
    "wof:placetype":"venue"
},
  "geometry": {"coordinates":[-71.28174799999999,42.367433],"type":"Point"}
}