{
  "type": "Feature",
  "properties": {
    "addr:full":"1 Cambridge Ctr Ste 11 Cambridge MA 02142",
    "addr:housenumber":"1;11",
    "addr:postcode":"02142",
    "addr:street":"Cambridge Ctr Ste",
    "iso:country":"US",
    "sg:address":"1 Cambridge Ctr Ste 11",
    "sg:city":"Cambridge",
    "sg:classifiers":[
        {
            "category":"Home & Garden",
            "subcategory":"Hardware",
            "type":"Retail Goods"
        }
    ],
    "sg:phone":"+1 617 499 4090",
    "sg:postcode":"02142",
    "sg:province":"MA",
    "sg:tags":[
        "measuring",
        "device"
    ],
    "sg:website":"http://www.thingmagic.com",
    "wof:name":"Thingmagic Inc.",
    "wof:placetype":"venue"
},
  "geometry": {"coordinates":[-71.07402,42.367531],"type":"Point"}
}