{
  "type": "Feature",
  "properties": {
    "addr:full": "40 Central St Winchendon MA 01475",
    "addr:housenumber": "40",
    "addr:postcode": "01475",
    "addr:street": "Central St",
    "iso:country": "US",
    "sg:address": "40 Central St",
    "sg:city": "Winchendon",
    "sg:classifiers": [
      {
        "category": "Real Estate",
        "subcategory": "Real Estate Agent",
        "type": "Services"
      }
    ],
    "sg:phone": "+1 978 297 5254",
    "sg:postcode": "01475",
    "sg:province": "MA",
    "wof:name": "Mercury Real Estate",
    "wof:placetype": "venue"
  },
  "geometry": {"coordinates":[-72.047997,42.681957],"type":"Point"}
}
