{
  "type": "Feature",
  "properties": {
    "addr:full": "374 William S Canning Blvd Fall River MA 02721",
    "addr:housenumber": "374",
    "addr:postcode": "02721",
    "addr:street": "William S Canning Blvd",
    "atp:label": "Burger King, 374 William S. Canning Blvd. Fall River MA US",
    "atp:similarity": 3.4837870597839355,
    "iso:country": "US",
    "ovtr:label": "Burger King, 374 William S Canning Blvd Fall River MA US",
    "ovtr:similarity": 2.2336769104003906,
    "sg:address": "374 William S Canning Blvd",
    "sg:city": "Fall River",
    "sg:classifiers": [
      {
        "category": "Restaurant",
        "type": "Food \u0026 Drink"
      }
    ],
    "sg:menulink": "http://www.allmenus.com/ma/fall-river/197012-burger-king/menu/",
    "sg:phone": "+1 508 678 9400",
    "sg:postcode": "02721",
    "sg:province": "MA",
    "sg:tags": [
      "burger",
      "american"
    ],
    "wof:name": "Burger King",
    "wof:placetype": "venue"
  },
  "geometry": {"coordinates":[-71.161058,41.672638],"type":"Point"}
}
