{
  "type": "Feature",
  "properties": {
    "iso:country":"US",
    "sg:address":"141 Ballard St",
    "sg:city":"Worcester",
    "sg:classifiers":[
        {
            "category":"Wholesale",
            "subcategory":"Construction Materials",
            "type":"Manufacturing & Wholesale Goods"
        }
    ],
    "sg:phone":"+1 508 791 3344",
    "sg:postcode":"01607",
    "sg:province":"MA",
    "sg:tags":[
        "concrete",
        "product"
    ],
    "wof:name":"Dan Wilga Inc",
    "wof:placetype":"venue"
},
  "geometry": {"coordinates":[-71.785799,42.22801],"type":"Point"}
}