{
  "type": "Feature",
  "properties": {
    "addr:full":"103 South St Hingham MA 02043",
    "addr:housenumber":"103",
    "addr:postcode":"02043",
    "addr:street":"South St",
    "iso:country":"US",
    "sg:address":"103 South St",
    "sg:city":"Hingham",
    "sg:classifiers":[
        {
            "category":"Personal",
            "subcategory":"Beauty Salon",
            "type":"Services"
        }
    ],
    "sg:phone":"+1 781 749 2448",
    "sg:postcode":"02043",
    "sg:province":"MA",
    "wof:name":"Salon Nouveau",
    "wof:placetype":"venue"
},
  "geometry": {"coordinates":[-70.89102099999999,42.241386],"type":"Point"}
}