{
  "type": "Feature",
  "properties": {
    "addr:full":"41 Foster St Arlington MA 02474",
    "addr:housenumber":"41",
    "addr:postcode":"02474",
    "addr:street":"Foster St",
    "iso:country":"US",
    "sg:address":"41 Foster St",
    "sg:city":"Arlington",
    "sg:classifiers":[
        {
            "category":"Arts & Performance",
            "subcategory":"Arts Center",
            "type":"Entertainment"
        },
        {
            "category":"Education",
            "subcategory":"Special Training",
            "type":"Public Place"
        }
    ],
    "sg:phone":"+1 781 721 0490",
    "sg:postcode":"02474",
    "sg:province":"MA",
    "sg:tags":[
        "school",
        "performing",
        "specialty"
    ],
    "sg:website":"gilgraham.com",
    "wof:name":"Drumming Preparatory School",
    "wof:placetype":"venue"
},
  "geometry": {"coordinates":[-71.14581,42.410578],"type":"Point"}
}