{
  "type": "Feature",
  "properties": {
    "addr:full":"4 Brattle St Cambridge MA 02138",
    "addr:housenumber":"4",
    "addr:postcode":"02138",
    "addr:street":"Brattle St",
    "iso:country":"US",
    "sg:address":"4 Brattle St",
    "sg:city":"Cambridge",
    "sg:classifiers":[
        {
            "category":"Shopping",
            "subcategory":"Computers & Home Electronics",
            "type":"Retail Goods"
        }
    ],
    "sg:phone":"+1 617 492 3673",
    "sg:postcode":"02138",
    "sg:province":"MA",
    "sg:tags":[
        "software"
    ],
    "wof:name":"Asafo Media",
    "wof:placetype":"venue"
},
  "geometry": {"coordinates":[-71.119812,42.373309],"type":"Point"}
}