{
  "type": "Feature",
  "properties": {
    "addr:full": "3 Whiting Rd Dover MA 02030",
    "addr:housenumber": "3",
    "addr:postcode": "02030",
    "addr:street": "Whiting Rd",
    "iso:country": "US",
    "sg:address": "3 Whiting Rd",
    "sg:city": "Dover",
    "sg:classifiers": [
      {
        "category": "Banks \u0026 Credit Unions",
        "subcategory": "Bank",
        "type": "Services"
      }
    ],
    "sg:phone": "+1 508 279 2457",
    "sg:postcode": "02030",
    "sg:province": "MA",
    "sg:tags": [
      "commercial",
      "saving"
    ],
    "wof:name": "Bridgewater Credit Union",
    "wof:placetype": "venue"
  },
  "geometry": {"coordinates":[-71.281908,42.244335],"type":"Point"}
}
