{
  "type": "Feature",
  "properties": {
    "addr:full": "363 Highland Ave Somerville MA 02144",
    "addr:housenumber": "363",
    "addr:postcode": "02144",
    "addr:street": "Highland Ave",
    "iso:country": "US",
    "sg:address": "363 Highland Ave",
    "sg:city": "Somerville",
    "sg:classifiers": [
      {
        "category": "Professional",
        "subcategory": "Management \u0026 Consulting",
        "type": "Services"
      }
    ],
    "sg:phone": "+1 617 623 7600",
    "sg:postcode": "02144",
    "sg:province": "MA",
    "sg:tags": [
      "consultant",
      "product"
    ],
    "wof:name": "Altitude Inc",
    "wof:placetype": "venue"
  },
  "geometry": {"coordinates":[-71.117077,42.394257],"type":"Point"}
}
