{
  "type": "Feature",
  "properties": {
    "iso:country":"US",
    "sg:address":"31 Sturgis St",
    "sg:city":"Winthrop",
    "sg:classifiers":[
        {
            "category":"Building & Trades",
            "subcategory":"Construction",
            "type":"Services"
        }
    ],
    "sg:phone":"+1   ",
    "sg:postcode":"02152",
    "sg:province":"MA",
    "sg:tags":[
        "house"
    ],
    "wof:name":"H & A Remodeling",
    "wof:placetype":"venue"
},
  "geometry": {"coordinates":[-70.96950699999999,42.372819],"type":"Point"}
}