{
  "type": "Feature",
  "properties": {
    "addr:full":"116 Belmont St Rm 42 Worcester MA 01605",
    "addr:housenumber":"116;42",
    "addr:postcode":"01605",
    "addr:street":"Belmont St Rm",
    "iso:country":"US",
    "sg:address":"116 Belmont St Rm 42",
    "sg:city":"Worcester",
    "sg:classifiers":[
        {
            "category":"Health Services",
            "subcategory":"Doctor",
            "type":"Services"
        }
    ],
    "sg:phone":"+1 508 792 5800",
    "sg:postcode":"01605",
    "sg:province":"MA",
    "sg:tags":[
        "gynecology",
        "physician",
        "surgeon",
        "surgeons",
        "obstetrics"
    ],
    "wof:name":"Alan J Albert Md",
    "wof:placetype":"venue"
},
  "geometry": {"coordinates":[-71.792236,42.272091],"type":"Point"}
}