{
  "type": "Feature",
  "properties": {
    "iso:country":"US",
    "sg:address":"58 Wedgewood Rd",
    "sg:city":"Stow",
    "sg:classifiers":[
        {
            "category":"Building & Trades",
            "subcategory":"Construction",
            "type":"Services"
        }
    ],
    "sg:phone":"+1 978 897 9977",
    "sg:postcode":"01775",
    "sg:province":"MA",
    "sg:tags":[
        "excavating",
        "contractor"
    ],
    "wof:name":"Chris Merrill Excavating",
    "wof:placetype":"venue"
},
  "geometry": {"coordinates":[-71.530905,42.441747],"type":"Point"}
}