{
  "type": "Feature",
  "properties": {
    "addr:full": "58 Wedgewood Rd Stow MA 01775",
    "addr:housenumber": "58",
    "addr:postcode": "01775",
    "addr:street": "Wedgewood Rd",
    "iso:country": "US",
    "sg:address": "58 Wedgewood Rd",
    "sg:city": "Stow",
    "sg:classifiers": [
      {
        "category": "Building \u0026 Trades",
        "subcategory": "Construction",
        "type": "Services"
      }
    ],
    "sg:phone": "+1 978 897 9977",
    "sg:postcode": "01775",
    "sg:province": "MA",
    "sg:tags": [
      "excavating",
      "contractor"
    ],
    "wof:name": "Chris Merrill Excavating",
    "wof:placetype": "venue"
  },
  "geometry": {"coordinates":[-71.530905,42.441747],"type":"Point"}
}
