{
  "type": "Feature",
  "properties": {
    "iso:country":"US",
    "sg:address":"376 Boylston St",
    "sg:city":"Boston",
    "sg:classifiers":[
        {
            "category":"Real Estate",
            "subcategory":"Real Estate Agent",
            "type":"Services"
        }
    ],
    "sg:phone":"+1 617 266 6343",
    "sg:postcode":"02116",
    "sg:province":"MA",
    "wof:name":"Eldridge Realty",
    "wof:placetype":"venue"
},
  "geometry": {"coordinates":[-71.07254500000001,42.351358],"type":"Point"}
}