{
  "type": "Feature",
  "properties": {
    "addr:full": "376 Boylston St Boston MA 02116",
    "addr:housenumber": "376",
    "addr:postcode": "02116",
    "addr:street": "Boylston St",
    "iso:country": "US",
    "sg:address": "376 Boylston St",
    "sg:city": "Boston",
    "sg:classifiers": [
      {
        "category": "Real Estate",
        "subcategory": "Real Estate Agent",
        "type": "Services"
      }
    ],
    "sg:phone": "+1 617 266 6343",
    "sg:postcode": "02116",
    "sg:province": "MA",
    "wof:name": "Eldridge Realty",
    "wof:placetype": "venue"
  },
  "geometry": {"coordinates":[-71.072545,42.351358],"type":"Point"}
}
