{
  "type": "Feature",
  "properties": {
    "iso:country":"US",
    "sg:address":"400 Franklin St",
    "sg:city":"Braintree",
    "sg:classifiers":[
        {
            "category":"Travel",
            "subcategory":"Travel Agent",
            "type":"Entertainment"
        }
    ],
    "sg:phone":"+1 781 849 9166",
    "sg:postcode":"02184",
    "sg:province":"MA",
    "sg:tags":[
        "cruise"
    ],
    "wof:name":"Alan's Cruise Corner",
    "wof:placetype":"venue"
},
  "geometry": {"coordinates":[-71.01910700000001,42.211581],"type":"Point"}
}