{
  "type": "Feature",
  "properties": {
    "addr:full": "11 Mcbride Rd Wales MA 01081",
    "addr:housenumber": "11",
    "addr:postcode": "01081",
    "addr:street": "Mcbride Rd",
    "iso:country": "US",
    "sg:address": "11 Mcbride Rd",
    "sg:city": "Wales",
    "sg:classifiers": [
      {
        "category": "Place Of Worship",
        "subcategory": "Church",
        "type": "Public Place"
      },
      {
        "category": "Place Of Worship",
        "type": "Public Place"
      }
    ],
    "sg:phone": "+1 413 245 3066",
    "sg:postcode": "01081",
    "sg:province": "MA",
    "sg:tags": [
      "churches-jehovah's",
      "witness"
    ],
    "sg:website": "http://www.watchtower.org",
    "wof:name": "Jehovah S Witnesses Palme",
    "wof:placetype": "venue"
  },
  "geometry": {"coordinates":[-72.239448,42.068111],"type":"Point"}
}
