{
  "type": "Feature",
  "properties": {
    "iso:country":"US",
    "sg:address":"59 Church St",
    "sg:city":"Winchester",
    "sg:classifiers":[
        {
            "category":"Professional",
            "type":"Services"
        }
    ],
    "sg:phone":"+1   ",
    "sg:postcode":"01890",
    "sg:province":"MA",
    "wof:name":"Marc Iovine",
    "wof:placetype":"venue"
},
  "geometry": {"coordinates":[-71.143765,42.450443],"type":"Point"}
}