{
  "type": "Feature",
  "properties": {
    "addr:full": "43 Avery St Ipswich MA 01938",
    "addr:housenumber": "43",
    "addr:postcode": "01938",
    "addr:street": "Avery St",
    "iso:country": "US",
    "sg:address": "43 Avery St",
    "sg:city": "Ipswich",
    "sg:classifiers": [
      {
        "category": "Restaurant",
        "type": "Food \u0026 Drink"
      }
    ],
    "sg:phone": "+1 978 356 3337",
    "sg:postcode": "01938",
    "sg:province": "MA",
    "sg:tags": [
      "seafood"
    ],
    "wof:name": "Sea Best Inc - CLOSED",
    "wof:placetype": "venue"
  },
  "geometry": {"coordinates":[-70.850403,42.692001],"type":"Point"}
}
