{
  "type": "Feature",
  "properties": {
    "addr:full":"70 Munroe St Lynn MA 01901",
    "addr:housenumber":"70",
    "addr:postcode":"01901",
    "addr:street":"Munroe St",
    "iso:country":"US",
    "sg:address":"70 Munroe St",
    "sg:city":"Lynn",
    "sg:classifiers":[
        {
            "category":"Professional",
            "subcategory":"Business Services",
            "type":"Services"
        }
    ],
    "sg:phone":"+1 781 598 9960",
    "sg:postcode":"01901",
    "sg:province":"MA",
    "sg:tags":[
        "development",
        "plan"
    ],
    "wof:name":"American Resources",
    "wof:placetype":"venue"
},
  "geometry": {"coordinates":[-70.947131,42.462584],"type":"Point"}
}