{
  "type": "Feature",
  "properties": {
    "addr:full":"270 Communication Way Hyannis MA 02601",
    "addr:housenumber":"270",
    "addr:postcode":"02601",
    "addr:street":"Communication Way",
    "iso:country":"US",
    "sg:address":"270 Communication Way",
    "sg:city":"Hyannis",
    "sg:classifiers":[
        {
            "category":"Shopping",
            "subcategory":"Bicycles & Sporting Goods",
            "type":"Retail Goods"
        }
    ],
    "sg:phone":"+1 508 778 1667",
    "sg:postcode":"02601",
    "sg:province":"MA",
    "sg:tags":[
        "equipment",
        "exercise"
    ],
    "wof:name":"Linray Fitness Superstore",
    "wof:placetype":"venue"
},
  "geometry": {"coordinates":[-70.293595,41.683189],"type":"Point"}
}