{
  "type": "Feature",
  "properties": {
    "iso:country":"US",
    "sg:address":"388 Pleasant Street Suite 204",
    "sg:city":"Malden",
    "sg:classifiers":[
        {
            "category":"Sports & Exercise",
            "subcategory":"Gym",
            "type":"Entertainment"
        }
    ],
    "sg:phone":"+1 781 388 9400",
    "sg:postcode":"02148",
    "sg:province":"MA",
    "sg:tags":[
        "trainer"
    ],
    "wof:name":"Tenzer Craig S PC",
    "wof:placetype":"venue"
},
  "geometry": {"coordinates":[-71.078563,42.426846],"type":"Point"}
}