{
  "type": "Feature",
  "properties": {
    "addr:full": "388 Pleasant Street Suite 204 Malden MA 02148",
    "addr:housenumber": "388",
    "addr:postcode": "02148",
    "addr:street": "Pleasant Street Suite 204",
    "iso:country": "US",
    "sg:address": "388 Pleasant Street Suite 204",
    "sg:city": "Malden",
    "sg:classifiers": [
      {
        "category": "Sports \u0026 Exercise",
        "subcategory": "Gym",
        "type": "Entertainment"
      }
    ],
    "sg:phone": "+1 781 388 9400",
    "sg:postcode": "02148",
    "sg:province": "MA",
    "sg:tags": [
      "trainer"
    ],
    "wof:name": "Tenzer Craig S PC",
    "wof:placetype": "venue"
  },
  "geometry": {"coordinates":[-71.078563,42.426846],"type":"Point"}
}
