{
  "type": "Feature",
  "properties": {
    "addr:full": "48 Antonio Costa Ave New Bedford MA 02740",
    "addr:housenumber": "48",
    "addr:postcode": "02740",
    "addr:street": "Antonio Costa Ave",
    "iso:country": "US",
    "sg:address": "48 Antonio Costa Ave",
    "sg:city": "New Bedford",
    "sg:classifiers": [
      {
        "category": "Retail",
        "subcategory": "Repair Shop",
        "type": "Services"
      }
    ],
    "sg:phone": "+1 508 999 5920",
    "sg:postcode": "02740",
    "sg:province": "MA",
    "sg:tags": [
      "welding"
    ],
    "wof:name": "Luzo Welding",
    "wof:placetype": "venue"
  },
  "geometry": {"coordinates":[-70.924067,41.642934],"type":"Point"}
}
