{
  "type": "Feature",
  "properties": {
    "addr:full":"171 Washington St Winchester MA 01890",
    "addr:housenumber":"171",
    "addr:postcode":"01890",
    "addr:street":"Washington St",
    "iso:country":"US",
    "sg:address":"171 Washington St",
    "sg:city":"Winchester",
    "sg:classifiers":[
        {
            "category":"Building & Trades",
            "subcategory":"Locksmith",
            "type":"Services"
        }
    ],
    "sg:phone":"+1 781 977 9115",
    "sg:postcode":"01890",
    "sg:province":"MA",
    "sg:tags":[
        "key"
    ],
    "wof:name":"24 Hour 7 Day Emergency Locksmith",
    "wof:placetype":"venue"
},
  "geometry": {"coordinates":[-71.131626,42.454844],"type":"Point"}
}