{
  "type": "Feature",
  "properties": {
    "iso:country":"US",
    "sg:address":"40 Commercial St",
    "sg:city":"Weymouth",
    "sg:classifiers":[
        {
            "category":"Education",
            "subcategory":"Special Training",
            "type":"Public Place"
        }
    ],
    "sg:phone":"+1 781 337 1003",
    "sg:postcode":"02188",
    "sg:province":"MA",
    "sg:tags":[
        "instruction",
        "driving"
    ],
    "wof:name":"New England Driving School",
    "wof:placetype":"venue"
},
  "geometry": {"coordinates":[-70.967952,42.219604],"type":"Point"}
}