{
  "type": "Feature",
  "properties": {
    "iso:country":"US",
    "sg:address":"10 Huron Dr",
    "sg:city":"Hopedale",
    "sg:classifiers":[
        {
            "category":"Professional",
            "subcategory":"Secretarial Services",
            "type":"Services"
        }
    ],
    "sg:phone":"+1 508 478 9795",
    "sg:postcode":"01749",
    "sg:province":"MA",
    "sg:tags":[
        "convention",
        "court",
        "reporter"
    ],
    "wof:name":"Eppley Court Reporting",
    "wof:placetype":"venue"
},
  "geometry": {"coordinates":[-71.545993,42.381177],"type":"Point"}
}