{
  "type": "Feature",
  "properties": {
    "iso:country":"US",
    "sg:address":"725 Main St",
    "sg:city":"Wakefield",
    "sg:classifiers":[
        {
            "category":"Health Services",
            "subcategory":"Doctor",
            "type":"Services"
        }
    ],
    "sg:phone":"+1 781 245 6966",
    "sg:postcode":"01880",
    "sg:province":"MA",
    "sg:tags":[
        "dentist"
    ],
    "wof:name":"Richard A Nutil INC",
    "wof:placetype":"venue"
},
  "geometry": {"coordinates":[-71.06899799999999,42.490517],"type":"Point"}
}