{
  "type": "Feature",
  "properties": {
    "addr:full": "2 New England Way Ayer MA 01432",
    "addr:housenumber": "2",
    "addr:postcode": "01432",
    "addr:street": "New England Way",
    "iso:country": "US",
    "sg:address": "2 New England Way",
    "sg:city": "Ayer",
    "sg:classifiers": [
      {
        "category": "Manufacturing",
        "subcategory": "Tools \u0026 Machinery",
        "type": "Manufacturing \u0026 Wholesale Goods"
      }
    ],
    "sg:phone": "+1 978 772 4444",
    "sg:postcode": "01432",
    "sg:province": "MA",
    "sg:tags": [
      "hand"
    ],
    "wof:name": "Silpro",
    "wof:placetype": "venue"
  },
  "geometry": {"coordinates":[-71.536958,42.562155],"type":"Point"}
}
