{
  "type": "Feature",
  "properties": {
    "addr:full": "450 Harrison Ave Boston MA 02118",
    "addr:housenumber": "450",
    "addr:postcode": "02118",
    "addr:street": "Harrison Ave",
    "iso:country": "US",
    "sg:address": "450 Harrison Ave",
    "sg:city": "Boston",
    "sg:classifiers": [
      {
        "category": "Shopping",
        "type": "Retail Goods"
      }
    ],
    "sg:phone": "+1 617 482 7778",
    "sg:postcode": "02118",
    "sg:province": "MA",
    "sg:tags": [
      "art",
      "gallery",
      "dealer"
    ],
    "wof:name": "Maysnow Gallery",
    "wof:placetype": "venue"
  },
  "geometry": {"coordinates":[-71.064809,42.34314],"type":"Point"}
}
