{
  "type": "Feature",
  "properties": {
    "addr:full": "1425 Centre St West Roxbury MA 02132",
    "addr:housenumber": "1425",
    "addr:postcode": "02132",
    "addr:street": "Centre St",
    "iso:country": "US",
    "sg:address": "1425 Centre St",
    "sg:city": "West Roxbury",
    "sg:classifiers": [
      {
        "category": "Building \u0026 Trades",
        "subcategory": "Locksmith",
        "type": "Services"
      }
    ],
    "sg:phone": "+1 617 942 4092",
    "sg:postcode": "02132",
    "sg:province": "MA",
    "sg:tags": [
      "key"
    ],
    "wof:name": "A 1 West Roxbury Emerency Locksmith",
    "wof:placetype": "venue"
  },
  "geometry": {"coordinates":[-71.136971,42.293789],"type":"Point"}
}
