{
  "type": "Feature",
  "properties": {
    "addr:full": "287 Arbor St Lunenburg MA 01462",
    "addr:housenumber": "287",
    "addr:postcode": "01462",
    "addr:street": "Arbor St",
    "iso:country": "US",
    "sg:address": "287 Arbor St",
    "sg:city": "Lunenburg",
    "sg:classifiers": [
      {
        "category": "Wholesale",
        "subcategory": "Electrical",
        "type": "Manufacturing \u0026 Wholesale Goods"
      }
    ],
    "sg:phone": "+1 978 632 8232",
    "sg:postcode": "01462",
    "sg:province": "MA",
    "sg:tags": [
      "alarm",
      "burglar",
      "system"
    ],
    "wof:name": "Security Burgler Alarm",
    "wof:placetype": "venue"
  },
  "geometry": {"coordinates":[-71.696183,42.588551],"type":"Point"}
}
