{
  "type": "Feature",
  "properties": {
    "addr:full": "51 Coventry Ln West Barnstable MA 02668",
    "addr:housenumber": "51",
    "addr:postcode": "02668",
    "addr:street": "Coventry Ln",
    "iso:country": "US",
    "sg:address": "51 Coventry Ln",
    "sg:city": "West Barnstable",
    "sg:classifiers": [
      {
        "category": "Professional",
        "type": "Services"
      }
    ],
    "sg:phone": "+1   ",
    "sg:postcode": "02668",
    "sg:province": "MA",
    "wof:name": "Curley \u0026 Stewart",
    "wof:placetype": "venue"
  },
  "geometry": {"coordinates":[-70.395366,41.716922],"type":"Point"}
}
