{
  "type": "Feature",
  "properties": {
    "iso:country":"US",
    "sg:address":"51 Coventry Ln",
    "sg:city":"West Barnstable",
    "sg:classifiers":[
        {
            "category":"Professional",
            "type":"Services"
        }
    ],
    "sg:phone":"+1   ",
    "sg:postcode":"02668",
    "sg:province":"MA",
    "wof:name":"Curley & Stewart",
    "wof:placetype":"venue"
},
  "geometry": {"coordinates":[-70.395366,41.716922],"type":"Point"}
}