{
  "type": "Feature",
  "properties": {
    "addr:full":"6 Blake St Leicester MA 01532",
    "addr:housenumber":"6",
    "addr:postcode":"01532",
    "addr:street":"Blake St",
    "iso:country":"US",
    "sg:address":"6 Blake St",
    "sg:city":"Leicester",
    "sg:classifiers":[
        {
            "category":"Retail",
            "subcategory":"Repair Shop",
            "type":"Services"
        }
    ],
    "sg:phone":"+1 508 612 6659",
    "sg:postcode":"01532",
    "sg:province":"MA",
    "sg:tags":[
        "equipment",
        "telephone",
        "system"
    ],
    "wof:name":"Elite Communications",
    "wof:placetype":"venue"
},
  "geometry": {"coordinates":[-71.641977,42.319815],"type":"Point"}
}