{
  "type": "Feature",
  "properties": {
    "iso:country":"US",
    "sg:address":"357 Summer St",
    "sg:city":"Lynnfield",
    "sg:classifiers":[
        {
            "category":"Professional",
            "subcategory":"Art Services",
            "type":"Services"
        }
    ],
    "sg:phone":"+1 781 334 4000",
    "sg:postcode":"01940",
    "sg:province":"MA",
    "sg:tags":[
        "photographer"
    ],
    "wof:name":"Onsite Cards & Design",
    "wof:placetype":"venue"
},
  "geometry": {"coordinates":[-71.039998,42.532008],"type":"Point"}
}