{
  "type": "Feature",
  "properties": {
    "iso:country":"US",
    "sg:address":"44 S Maple St",
    "sg:city":"Westfield",
    "sg:classifiers":[
        {
            "category":"Professional",
            "subcategory":"Business Services",
            "type":"Services"
        }
    ],
    "sg:phone":"+1   ",
    "sg:postcode":"01085",
    "sg:province":"MA",
    "wof:name":"DK Multimedia Design",
    "wof:placetype":"venue"
},
  "geometry": {"coordinates":[-72.756091,42.112635],"type":"Point"}
}