{
  "type": "Feature",
  "properties": {
    "addr:full": "42 Thorny Lea Ter Brockton MA 02301",
    "addr:housenumber": "42",
    "addr:postcode": "02301",
    "addr:street": "Thorny Lea Ter",
    "iso:country": "US",
    "sg:address": "42 Thorny Lea Ter",
    "sg:city": "Brockton",
    "sg:classifiers": [
      {
        "category": "Professional",
        "subcategory": "Lawyer \u0026 Legal Services",
        "type": "Services"
      }
    ],
    "sg:phone": "+1 508 583 9216",
    "sg:postcode": "02301",
    "sg:province": "MA",
    "wof:name": "Frenette Henry N Jr Lwyr - CLOSED",
    "wof:placetype": "venue"
  },
  "geometry": {"coordinates":[-71.0467,42.0835],"type":"Point"}
}
