{
  "type": "Feature",
  "properties": {
    "iso:country":"US",
    "sg:address":"72 Tanglewood Dr",
    "sg:city":"East Longmeadow",
    "sg:classifiers":[
        {
            "category":"Utilities",
            "subcategory":"Refuse",
            "type":"Services"
        }
    ],
    "sg:phone":"+1 413 525 2892",
    "sg:postcode":"01028",
    "sg:province":"MA",
    "sg:tags":[
        "disposal",
        "waste"
    ],
    "wof:name":"Phil's Dump Runs",
    "wof:placetype":"venue"
},
  "geometry": {"coordinates":[-72.475587,42.074397],"type":"Point"}
}