{
  "type": "Feature",
  "properties": {
    "addr:full":"21 Wyeth St Malden MA 02148",
    "addr:housenumber":"21",
    "addr:postcode":"02148",
    "addr:street":"Wyeth St",
    "iso:country":"US",
    "sg:address":"21 Wyeth St",
    "sg:city":"Malden",
    "sg:classifiers":[
        {
            "category":"Wholesale",
            "subcategory":"Non-durable Goods",
            "type":"Manufacturing & Wholesale Goods"
        }
    ],
    "sg:phone":"+1   ",
    "sg:postcode":"02148",
    "sg:province":"MA",
    "wof:name":"Fabulous Concepts",
    "wof:placetype":"venue"
},
  "geometry": {"coordinates":[-71.06213,42.424549],"type":"Point"}
}