{
  "type": "Feature",
  "properties": {
    "iso:country":"US",
    "sg:address":"214 Lunenburg St",
    "sg:city":"Fitchburg",
    "sg:classifiers":[
        {
            "category":"Retail",
            "subcategory":"Repair Shop",
            "type":"Services"
        }
    ],
    "sg:phone":"+1 978 345 1951",
    "sg:postcode":"01420",
    "sg:province":"MA",
    "sg:tags":[
        "energy",
        "system",
        "solar"
    ],
    "wof:name":"Woodland Energy Retail",
    "wof:placetype":"venue"
},
  "geometry": {"coordinates":[-71.779188,42.585627],"type":"Point"}
}