{
  "type": "Feature",
  "properties": {
    "addr:full":"1 Patriot Pl Foxboro MA 02035",
    "addr:housenumber":"1",
    "addr:postcode":"02035",
    "addr:street":"Patriot Pl",
    "iso:country":"US",
    "sg:address":"1 Patriot Pl",
    "sg:city":"Foxboro",
    "sg:classifiers":[
        {
            "category":"Coffee & Tea",
            "type":"Food & Drink"
        },
        {
            "category":"Bakery",
            "type":"Food & Drink"
        },
        {
            "category":"Bagels",
            "subcategory":"None",
            "type":"Food & Drink"
        },
        {
            "category":"Donuts",
            "subcategory":"None",
            "type":"Food & Drink"
        }
    ],
    "sg:phone":"+1 508 203 9037",
    "sg:postcode":"02035",
    "sg:province":"MA",
    "sg:tags":[
        "shop",
        "espresso",
        "restaurant"
    ],
    "sg:website":"http://boston.citysearch.com/profile/external/615137410/foxborough_ma/dunkin_donuts.html?publisher=yellowpages&reference_id=1&placement=ypwebsitemip",
    "wof:name":"Dunkin Donuts",
    "wof:placetype":"venue"
},
  "geometry": {"coordinates":[-71.266479,42.094849],"type":"Point"}
}