{
  "type": "Feature",
  "properties": {
    "addr:full":"91 Summer St Lunenburg MA 01462",
    "addr:housenumber":"91",
    "addr:postcode":"01462",
    "addr:street":"Summer St",
    "iso:country":"US",
    "sg:address":"91 Summer St",
    "sg:city":"Lunenburg",
    "sg:classifiers":[
        {
            "category":"Shopping",
            "subcategory":"Gifts & Souvenirs",
            "type":"Retail Goods"
        }
    ],
    "sg:phone":"+1 978 342 5100",
    "sg:postcode":"01462",
    "sg:province":"MA",
    "sg:tags":[
        "shop"
    ],
    "wof:name":"Horsefeathers",
    "wof:placetype":"venue"
},
  "geometry": {"coordinates":[-71.766076,42.568245],"type":"Point"}
}