{
  "type": "Feature",
  "properties": {
    "addr:full":"1266 Bay Rd Stoughton MA 02072",
    "addr:housenumber":"1266",
    "addr:postcode":"02072",
    "addr:street":"Bay Rd",
    "iso:country":"US",
    "sg:address":"1266 Bay Rd",
    "sg:city":"Stoughton",
    "sg:classifiers":[
        {
            "category":"Retail",
            "subcategory":"Auto Repair",
            "type":"Services"
        }
    ],
    "sg:phone":"+1 781 344 8619",
    "sg:postcode":"02072",
    "sg:province":"MA",
    "sg:tags":[
        "repairing",
        "automobile"
    ],
    "wof:name":"S & L Pump & Well Repair",
    "wof:placetype":"venue"
},
  "geometry": {"coordinates":[-71.13244899999999,42.108374],"type":"Point"}
}