{
  "type": "Feature",
  "properties": {
    "iso:country":"US",
    "sg:address":"137 Washington St",
    "sg:city":"Norwell",
    "sg:classifiers":[
        {
            "category":"Banks & Credit Unions",
            "subcategory":"Bank",
            "type":"Services"
        }
    ],
    "sg:phone":"+1 781 681 9400",
    "sg:postcode":"02061",
    "sg:province":"MA",
    "sg:tags":[
        "loan",
        "real estate"
    ],
    "sg:website":"www.conwayfinancial.com",
    "wof:name":"Conway Financial Svc",
    "wof:placetype":"venue"
},
  "geometry": {"coordinates":[-70.876728,42.170579],"type":"Point"}
}