{
  "type": "Feature",
  "properties": {
    "addr:full":"46 Stevens St Andover MA 01810",
    "addr:housenumber":"46",
    "addr:postcode":"01810",
    "addr:street":"Stevens St",
    "iso:country":"US",
    "sg:address":"46 Stevens St",
    "sg:city":"Andover",
    "sg:classifiers":[
        {
            "category":"Professional",
            "subcategory":"Computer Services",
            "type":"Services"
        }
    ],
    "sg:phone":"+1 978 470 1780",
    "sg:postcode":"01810",
    "sg:province":"MA",
    "sg:tags":[
        "web",
        "design",
        "site"
    ],
    "sg:website":"http://www.e-brainstormtech.com",
    "wof:name":"E-Brainstorm Technology Inc",
    "wof:placetype":"venue"
},
  "geometry": {"coordinates":[-71.14770300000001,42.661747],"type":"Point"}
}