{
  "type": "Feature",
  "properties": {
    "addr:full":"144 Sherman St Canton MA 02021",
    "addr:housenumber":"144",
    "addr:postcode":"02021",
    "addr:street":"Sherman St",
    "iso:country":"US",
    "sg:address":"144 Sherman St",
    "sg:city":"Canton",
    "sg:classifiers":[
        {
            "category":"Insurance",
            "subcategory":"Insurance Agent",
            "type":"Services"
        }
    ],
    "sg:phone":"+1 781 821 5760",
    "sg:postcode":"02021",
    "sg:province":"MA",
    "sg:tags":[
        "processing"
    ],
    "wof:name":"Coppermill Claim Svc",
    "wof:placetype":"venue"
},
  "geometry": {"coordinates":[-71.136358,42.157847],"type":"Point"}
}