{
  "type": "Feature",
  "properties": {
    "iso:country":"US",
    "sg:address":"1306 Boylston St",
    "sg:city":"Boston",
    "sg:classifiers":[
        {
            "category":"Restaurant",
            "type":"Food & Drink"
        }
    ],
    "sg:menulink":"http://www.allmenus.com/ma/boston/1120-restaurant-at-baseball-tavern/menu/",
    "sg:phone":"+1 617 456 0363",
    "sg:postcode":"02215",
    "sg:province":"MA",
    "sg:tags":[
        "american"
    ],
    "wof:name":"Restaurant at Baseball Tavern",
    "wof:placetype":"venue"
},
  "geometry": {"coordinates":[-71.098134,42.344486],"type":"Point"}
}