{
  "type": "Feature",
  "properties": {
    "addr:full":"115 Wayside Ave West Springfield MA 01089",
    "addr:housenumber":"115",
    "addr:postcode":"01089",
    "addr:street":"Wayside Ave",
    "iso:country":"US",
    "sg:address":"115 Wayside Ave",
    "sg:city":"West Springfield",
    "sg:classifiers":[
        {
            "category":"Professional",
            "type":"Services"
        }
    ],
    "sg:phone":"+1 413 731 0000",
    "sg:postcode":"01089",
    "sg:province":"MA",
    "sg:tags":[
        "establishment"
    ],
    "wof:name":"Baroco Habilitation Ctr",
    "wof:placetype":"venue"
},
  "geometry": {"coordinates":[-72.62244,42.143299],"type":"Point"}
}