{
  "type": "Feature",
  "properties": {
    "iso:country":"US",
    "sg:address":"339 Grafton St",
    "sg:city":"Shrewsbury",
    "sg:classifiers":[
        {
            "category":"Building & Trades",
            "subcategory":"Construction",
            "type":"Services"
        }
    ],
    "sg:phone":"+1   ",
    "sg:postcode":"01545",
    "sg:province":"MA",
    "sg:tags":[
        "house"
    ],
    "wof:name":"Gaudette Pj Const",
    "wof:placetype":"venue"
},
  "geometry": {"coordinates":[-71.712541,42.273764],"type":"Point"}
}