{
  "type": "Feature",
  "properties": {
    "addr:full": "966A Park St Stoughton MA 02072",
    "addr:housenumber": "966a",
    "addr:postcode": "02072",
    "addr:street": "Park St",
    "iso:country": "US",
    "sg:address": "966A Park St",
    "sg:city": "Stoughton",
    "sg:classifiers": [
      {
        "category": "Social Services",
        "type": "Services"
      },
      {
        "category": "Health Services",
        "subcategory": "Clinic",
        "type": "Services"
      },
      {
        "category": "Professional",
        "type": "Services"
      },
      {
        "category": "Professional",
        "subcategory": "Lawyer \u0026 Legal Services",
        "type": "Services"
      },
      {
        "category": "Health Services",
        "subcategory": "Doctor",
        "type": "Services"
      },
      {
        "category": "Personal",
        "type": "Services"
      }
    ],
    "sg:phone": "+1 781 341 0923",
    "sg:postcode": "02072",
    "sg:province": "MA",
    "sg:tags": [
      "mental",
      "family",
      "divorce",
      "assistance",
      "mediation",
      "psychologist",
      "therapist",
      "marriage",
      "counseling"
    ],
    "sg:website": "www.adultchildcounseling.com",
    "wof:name": "Adult \u0026 Child Counseling Associates",
    "wof:placetype": "venue"
  },
  "geometry": {"coordinates":[-71.072854,42.111332],"type":"Point"}
}
