{
  "type": "Feature",
  "properties": {
    "addr:full": "90 Chandler St Somerville MA 02144",
    "addr:housenumber": "90",
    "addr:postcode": "02144",
    "addr:street": "Chandler St",
    "iso:country": "US",
    "sg:address": "90 Chandler St",
    "sg:city": "Somerville",
    "sg:classifiers": [
      {
        "category": "Professional",
        "subcategory": "Computer Services",
        "type": "Services"
      }
    ],
    "sg:phone": "+1 617 628 2919",
    "sg:postcode": "02144",
    "sg:province": "MA",
    "sg:tags": [
      "publisher",
      "software",
      "developer",
      "services-wholesale"
    ],
    "wof:name": "Henkels \u0026 Co",
    "wof:placetype": "venue"
  },
  "geometry": {"coordinates":[-71.120175,42.400631],"type":"Point"}
}
