{
  "type": "Feature",
  "properties": {
    "iso:country":"US",
    "sg:address":"251 Crescent St",
    "sg:city":"Brockton",
    "sg:classifiers":[
        {
            "category":"Education",
            "subcategory":"Special Training",
            "type":"Public Place"
        }
    ],
    "sg:phone":"+1 508 587 5787",
    "sg:postcode":"02302",
    "sg:province":"MA",
    "sg:tags":[
        "educational"
    ],
    "wof:name":"Brazuca Learning Ctr",
    "wof:placetype":"venue"
},
  "geometry": {"coordinates":[-71.011692,42.080199],"type":"Point"}
}