{
  "type": "Feature",
  "properties": {
    "iso:country":"US",
    "sg:address":"360 High St",
    "sg:city":"Clinton",
    "sg:classifiers":[
        {
            "category":"Home & Garden",
            "subcategory":"Building Materials",
            "type":"Retail Goods"
        }
    ],
    "sg:phone":"+1 978 368 1520",
    "sg:postcode":"01510",
    "sg:province":"MA",
    "sg:tags":[
        "glass",
        "window",
        "plate"
    ],
    "wof:name":"AGM Glass & Mirror Co",
    "wof:placetype":"venue"
},
  "geometry": {"coordinates":[-71.68355,42.423247],"type":"Point"}
}