{
  "type": "Feature",
  "properties": {
    "iso:country":"US",
    "sg:address":"80 Depot St",
    "sg:city":"Westford",
    "sg:classifiers":[
        {
            "category":"Restaurant",
            "type":"Food & Drink"
        }
    ],
    "sg:phone":"+1 978 692 0689",
    "sg:postcode":"01886",
    "sg:province":"MA",
    "wof:name":"Crystal Soup",
    "wof:placetype":"venue"
},
  "geometry": {"coordinates":[-71.437618,42.600747],"type":"Point"}
}