{
  "type": "Feature",
  "properties": {
    "addr:full": "80 Depot St Westford MA 01886",
    "addr:housenumber": "80",
    "addr:postcode": "01886",
    "addr:street": "Depot St",
    "iso:country": "US",
    "sg:address": "80 Depot St",
    "sg:city": "Westford",
    "sg:classifiers": [
      {
        "category": "Restaurant",
        "type": "Food \u0026 Drink"
      }
    ],
    "sg:phone": "+1 978 692 0689",
    "sg:postcode": "01886",
    "sg:province": "MA",
    "wof:name": "Crystal Soup",
    "wof:placetype": "venue"
  },
  "geometry": {"coordinates":[-71.437618,42.600747],"type":"Point"}
}
