{
  "type": "Feature",
  "properties": {
    "addr:full":"1423 Ocean St Marshfield MA 02050",
    "addr:housenumber":"1423",
    "addr:postcode":"02050",
    "addr:street":"Ocean St",
    "iso:country":"US",
    "sg:address":"1423 Ocean St",
    "sg:city":"Marshfield",
    "sg:classifiers":[
        {
            "category":"Real Estate",
            "subcategory":"Real Estate Agent",
            "type":"Services"
        }
    ],
    "sg:phone":"+1 781 834 8651",
    "sg:postcode":"02050",
    "sg:province":"MA",
    "sg:website":"www.mass-bay.com",
    "wof:name":"Massachusetts Bay Assoc Rltrs",
    "wof:placetype":"venue"
},
  "geometry": {"coordinates":[-70.686347,42.09569],"type":"Point"}
}