{
  "type": "Feature",
  "properties": {
    "addr:full":"33 Hamilton Ave South Hamilton MA 01982",
    "addr:housenumber":"33",
    "addr:postcode":"01982",
    "addr:street":"Hamilton Ave South",
    "iso:country":"US",
    "sg:address":"33 Hamilton Ave",
    "sg:city":"South Hamilton",
    "sg:classifiers":[
        {
            "category":"Shopping",
            "subcategory":"Bicycles & Sporting Goods",
            "type":"Retail Goods"
        }
    ],
    "sg:phone":"+1 978 468 6363",
    "sg:postcode":"01982",
    "sg:province":"MA",
    "sg:tags":[
        "horse",
        "furnishing"
    ],
    "wof:name":"Round The Bend",
    "wof:placetype":"venue"
},
  "geometry": {"coordinates":[-70.876395,42.613508],"type":"Point"}
}