{
  "type": "Feature",
  "properties": {
    "iso:country":"US",
    "sg:address":"49 Worcester Providence Tpke",
    "sg:city":"Sutton",
    "sg:classifiers":[
        {
            "category":"Autos & Motor Vehicles",
            "subcategory":"Automobile Sales",
            "type":"Retail Goods"
        }
    ],
    "sg:phone":"+1 508 753 6800",
    "sg:postcode":"01590",
    "sg:province":"MA",
    "sg:tags":[
        "dealers-used",
        "car",
        "used",
        "cars-wholesale",
        "new"
    ],
    "sg:website":"http://www.soniasautosales.com",
    "wof:name":"Sonia's Auto Sales",
    "wof:placetype":"venue"
},
  "geometry": {"coordinates":[-71.74957000000001,42.169814],"type":"Point"}
}