{
  "type": "Feature",
  "properties": {
    "iso:country":"US",
    "sg:address":"1734 Lakeview Ave Ste 29",
    "sg:city":"Dracut",
    "sg:classifiers":[
        {
            "category":"Sports & Exercise",
            "subcategory":"Ice Rink",
            "type":"Entertainment"
        }
    ],
    "sg:phone":"+1 978 957 9037",
    "sg:postcode":"01826",
    "sg:province":"MA",
    "sg:tags":[
        "skating"
    ],
    "wof:name":"Ice Huts",
    "wof:placetype":"venue"
},
  "geometry": {"coordinates":[-71.34187300000001,42.679489],"type":"Point"}
}