{
  "type": "Feature",
  "properties": {
    "iso:country":"US",
    "sg:address":"40 Broadway",
    "sg:city":"Salisbury Beach",
    "sg:classifiers":[
        {
            "category":"Restaurant",
            "type":"Food & Drink"
        }
    ],
    "sg:phone":"+1 978 465 3846",
    "sg:postcode":"01952",
    "sg:province":"MA",
    "wof:name":"Tripoli Pizza",
    "wof:placetype":"venue"
},
  "geometry": {"coordinates":[-70.81676400000001,42.842524],"type":"Point"}
}