{
  "type": "Feature",
  "properties": {
    "addr:full": "40 Broadway Salisbury Beach MA 01952",
    "addr:housenumber": "40",
    "addr:postcode": "01952",
    "addr:street": "Broadway",
    "iso:country": "US",
    "sg:address": "40 Broadway",
    "sg:city": "Salisbury Beach",
    "sg:classifiers": [
      {
        "category": "Restaurant",
        "type": "Food \u0026 Drink"
      }
    ],
    "sg:phone": "+1 978 465 3846",
    "sg:postcode": "01952",
    "sg:province": "MA",
    "wof:name": "Tripoli Pizza",
    "wof:placetype": "venue"
  },
  "geometry": {"coordinates":[-70.816764,42.842524],"type":"Point"}
}
