{
  "type": "Feature",
  "properties": {
    "addr:full":"113 Townsend Harbor Rd Lunenburg MA 01462",
    "addr:housenumber":"113",
    "addr:postcode":"01462",
    "addr:street":"Townsend Harbor Rd",
    "iso:country":"US",
    "sg:address":"113 Townsend Harbor Rd",
    "sg:city":"Lunenburg",
    "sg:classifiers":[
        {
            "category":"Manufacturing",
            "subcategory":"Apparel",
            "type":"Manufacturing & Wholesale Goods"
        }
    ],
    "sg:phone":"+1   ",
    "sg:postcode":"01462",
    "sg:province":"MA",
    "sg:tags":[
        "costume",
        "custom"
    ],
    "wof:name":"By J",
    "wof:placetype":"venue"
},
  "geometry": {"coordinates":[-71.707483,42.600793],"type":"Point"}
}