{
  "type": "Feature",
  "properties": {
    "addr:full": "1173 Stafford Rd Fall River MA 02721",
    "addr:housenumber": "1173",
    "addr:postcode": "02721",
    "addr:street": "Stafford Rd",
    "iso:country": "US",
    "ovtr:label": "United Liberty Bakery, 1173 Stafford Rd Fall River MA US",
    "ovtr:similarity": 2.0906620025634766,
    "sg:address": "1173 Stafford Rd",
    "sg:city": "Fall River",
    "sg:classifiers": [
      {
        "category": "Manufacturing",
        "subcategory": "Food",
        "type": "Manufacturing \u0026 Wholesale Goods"
      }
    ],
    "sg:phone": "+1 508 674 8706",
    "sg:postcode": "02721",
    "sg:province": "MA",
    "sg:tags": [
      "bakery",
      "prod",
      "cookie"
    ],
    "wof:name": "United Liberty Bakery",
    "wof:placetype": "venue"
  },
  "geometry": {"coordinates":[-71.153631,41.672696],"type":"Point"}
}
