{
  "type": "Feature",
  "properties": {
    "iso:country":"US",
    "sg:address":"1173 Stafford Rd",
    "sg:city":"Fall River",
    "sg:classifiers":[
        {
            "category":"Manufacturing",
            "subcategory":"Food",
            "type":"Manufacturing & Wholesale Goods"
        }
    ],
    "sg:phone":"+1 508 674 8706",
    "sg:postcode":"02721",
    "sg:province":"MA",
    "sg:tags":[
        "bakery",
        "prod",
        "cookie"
    ],
    "wof:name":"United Liberty Bakery",
    "wof:placetype":"venue"
},
  "geometry": {"coordinates":[-71.153631,41.672696],"type":"Point"}
}