{
  "type": "Feature",
  "properties": {
    "iso:country":"US",
    "sg:address":"26 Elm St",
    "sg:city":"Cohasset",
    "sg:classifiers":[
        {
            "category":"Health Services",
            "subcategory":"Clinic",
            "type":"Services"
        }
    ],
    "sg:phone":"+1 781 383 8444",
    "sg:postcode":"02025",
    "sg:province":"MA",
    "sg:tags":[
        "home"
    ],
    "wof:name":"Fidelity Home Health Care",
    "wof:placetype":"venue"
},
  "geometry": {"coordinates":[-70.80206,42.24077],"type":"Point"}
}