{
  "type": "Feature",
  "properties": {
    "iso:country":"US",
    "sg:address":"980 S Rodney French Blvd",
    "sg:city":"New Bedford",
    "sg:classifiers":[
        {
            "category":"Recreation",
            "type":"Entertainment"
        }
    ],
    "sg:phone":"+1 508 996 4230",
    "sg:postcode":"02744",
    "sg:province":"MA",
    "sg:tags":[
        "boating",
        "instruction"
    ],
    "wof:name":"Fort Rodman Marine Educational",
    "wof:placetype":"venue"
},
  "geometry": {"coordinates":[-70.904461,41.596921],"type":"Point"}
}