{
  "type": "Feature",
  "properties": {
    "iso:country":"US",
    "sg:address":"372 Washington St",
    "sg:city":"Brighton",
    "sg:classifiers":[
        {
            "category":"Health Services",
            "subcategory":"Optometrist",
            "type":"Services"
        },
        {
            "category":"Shopping",
            "subcategory":"Optician",
            "type":"Retail Goods"
        }
    ],
    "sg:phone":"+1 617 782 6650",
    "sg:postcode":"02135",
    "sg:province":"MA",
    "sg:tags":[
        "eyewear"
    ],
    "sg:website":"www.brightoneyecare.com",
    "wof:name":"Brighton Eye Associates",
    "wof:placetype":"venue"
},
  "geometry": {"coordinates":[-71.153887,42.349139],"type":"Point"}
}