{
  "type": "Feature",
  "properties": {
    "addr:full":"10 Union Wharf Fairhaven MA 02719",
    "addr:housenumber":"10",
    "addr:postcode":"02719",
    "iso:country":"US",
    "sg:address":"10 Union Wharf",
    "sg:city":"Fairhaven",
    "sg:classifiers":[
        {
            "category":"Professional",
            "subcategory":"Art Services",
            "type":"Services"
        }
    ],
    "sg:phone":"+1 508 990 1333",
    "sg:postcode":"02719",
    "sg:province":"MA",
    "sg:tags":[
        "graphic",
        "designer"
    ],
    "wof:name":"Blue Ocean",
    "wof:placetype":"venue"
},
  "geometry": {"coordinates":[-70.906234,41.634871],"type":"Point"}
}