{
  "type": "Feature",
  "properties": {
    "iso:country":"US",
    "sg:address":"3 Smallwood Cir",
    "sg:city":"Boylston",
    "sg:classifiers":[
        {
            "category":"Building & Trades",
            "subcategory":"Plumbing",
            "type":"Services"
        }
    ],
    "sg:phone":"+1 508 869 6986",
    "sg:postcode":"01505",
    "sg:province":"MA",
    "sg:tags":[
        "plumbing",
        "contractor"
    ],
    "wof:name":"Dick Lapan Jr & Son",
    "wof:placetype":"venue"
},
  "geometry": {"coordinates":[-71.737438,42.324433],"type":"Point"}
}