{
  "type": "Feature",
  "properties": {
    "addr:full": "3 Smallwood Cir Boylston MA 01505",
    "addr:housenumber": "3",
    "addr:postcode": "01505",
    "addr:street": "Smallwood Cir",
    "iso:country": "US",
    "sg:address": "3 Smallwood Cir",
    "sg:city": "Boylston",
    "sg:classifiers": [
      {
        "category": "Building \u0026 Trades",
        "subcategory": "Plumbing",
        "type": "Services"
      }
    ],
    "sg:phone": "+1 508 869 6986",
    "sg:postcode": "01505",
    "sg:province": "MA",
    "sg:tags": [
      "plumbing",
      "contractor"
    ],
    "wof:name": "Dick Lapan Jr \u0026 Son",
    "wof:placetype": "venue"
  },
  "geometry": {"coordinates":[-71.737438,42.324433],"type":"Point"}
}
