{
  "type": "Feature",
  "properties": {
    "addr:full":"207 Main St Wareham MA 02571",
    "addr:housenumber":"207",
    "addr:postcode":"02571",
    "addr:street":"Main St",
    "iso:country":"US",
    "sg:address":"207 Main St",
    "sg:city":"Wareham",
    "sg:classifiers":[
        {
            "category":"Restaurant",
            "type":"Food & Drink"
        }
    ],
    "sg:phone":"+1 508 295 3356",
    "sg:postcode":"02571",
    "sg:province":"MA",
    "sg:tags":[
        "seafood"
    ],
    "wof:name":"Piper Beau's",
    "wof:placetype":"venue"
},
  "geometry": {"coordinates":[-70.7152,41.7583],"type":"Point"}
}