{
  "type": "Feature",
  "properties": {
    "addr:full":"1019 Iyannough Rd Hyannis MA 02601",
    "addr:housenumber":"1019",
    "addr:postcode":"02601",
    "addr:street":"Iyannough Rd",
    "iso:country":"US",
    "sg:address":"1019 Iyannough Rd",
    "sg:city":"Hyannis",
    "sg:classifiers":[
        {
            "category":"Government",
            "subcategory":"Office",
            "type":"Public Place"
        }
    ],
    "sg:phone":"+1 508 771 2414",
    "sg:postcode":"02601",
    "sg:province":"MA",
    "sg:tags":[
        "state",
        "taxation"
    ],
    "wof:name":"Revenue Dept",
    "wof:placetype":"venue"
},
  "geometry": {"coordinates":[-70.30374399999999,41.672436],"type":"Point"}
}