{
  "type": "Feature",
  "properties": {
    "addr:full": "21 Wood Rd Sherborn MA 01770",
    "addr:housenumber": "21",
    "addr:postcode": "01770",
    "addr:street": "Wood Rd",
    "iso:country": "US",
    "sg:address": "21 Wood Rd",
    "sg:city": "Sherborn",
    "sg:classifiers": [
      {
        "category": "Professional",
        "type": "Services"
      }
    ],
    "sg:phone": "+1 508 651 3027",
    "sg:postcode": "01770",
    "sg:province": "MA",
    "sg:tags": [
      "establishment"
    ],
    "wof:name": "Layer Eight Systems",
    "wof:placetype": "venue"
  },
  "geometry": {"coordinates":[-71.384571,42.234447],"type":"Point"}
}
