{
  "type": "Feature",
  "properties": {
    "iso:country":"US",
    "sg:address":"54 Capitol St",
    "sg:city":"Watertown",
    "sg:classifiers":[
        {
            "category":"Professional",
            "type":"Services"
        }
    ],
    "sg:phone":"+1   ",
    "sg:postcode":"02472",
    "sg:province":"MA",
    "sg:tags":[
        "consulting"
    ],
    "wof:name":"L Morton Schagrin",
    "wof:placetype":"venue"
},
  "geometry": {"coordinates":[-71.18777799999999,42.361333],"type":"Point"}
}