{
  "type": "Feature",
  "properties": {
    "addr:full": "54 Capitol St Watertown MA 02472",
    "addr:housenumber": "54",
    "addr:postcode": "02472",
    "addr:street": "Capitol St",
    "iso:country": "US",
    "sg:address": "54 Capitol St",
    "sg:city": "Watertown",
    "sg:classifiers": [
      {
        "category": "Professional",
        "type": "Services"
      }
    ],
    "sg:phone": "+1   ",
    "sg:postcode": "02472",
    "sg:province": "MA",
    "sg:tags": [
      "consulting"
    ],
    "wof:name": "L Morton Schagrin",
    "wof:placetype": "venue"
  },
  "geometry": {"coordinates":[-71.187778,42.361333],"type":"Point"}
}
