{
  "type": "Feature",
  "properties": {
    "addr:full": "290 Chestnut St Needham MA 02492",
    "addr:housenumber": "290",
    "addr:postcode": "02492",
    "addr:street": "Chestnut St",
    "iso:country": "US",
    "sg:address": "290 Chestnut St",
    "sg:city": "Needham",
    "sg:classifiers": [
      {
        "category": "Personal",
        "subcategory": "Beauty Salon",
        "type": "Services"
      }
    ],
    "sg:phone": "+1 781 444 6330",
    "sg:postcode": "02492",
    "sg:province": "MA",
    "wof:name": "Hairdressers",
    "wof:placetype": "venue"
  },
  "geometry": {"coordinates":[-71.23758,42.275832],"type":"Point"}
}
