{
  "type": "Feature",
  "properties": {
    "addr:full": "94 Old Westboro Rd North Grafton MA 01536",
    "addr:housenumber": "94",
    "addr:postcode": "01536",
    "addr:street": "Old Westboro Rd",
    "iso:country": "US",
    "sg:address": "94 Old Westboro Rd",
    "sg:city": "North Grafton",
    "sg:classifiers": [
      {
        "category": "Recreation",
        "type": "Entertainment"
      }
    ],
    "sg:phone": "+1 508 839 7370",
    "sg:postcode": "01536",
    "sg:province": "MA",
    "wof:name": "Quarter Ridge Farm",
    "wof:placetype": "venue"
  },
  "geometry": {"coordinates":[-71.667026,42.230083],"type":"Point"}
}
