{
  "type": "Feature",
  "properties": {
    "addr:full":"157 Prospect St Hatfield MA 01038",
    "addr:housenumber":"157",
    "addr:postcode":"01038",
    "addr:street":"Prospect St",
    "iso:country":"US",
    "sg:address":"157 Prospect St",
    "sg:city":"Hatfield",
    "sg:classifiers":[
        {
            "category":"Wholesale",
            "subcategory":"Scrap",
            "type":"Manufacturing & Wholesale Goods"
        }
    ],
    "sg:phone":"+1 413 247 9231",
    "sg:postcode":"01038",
    "sg:province":"MA",
    "sg:tags":[
        "recycling",
        "center"
    ],
    "wof:name":"Dave E Wickles Trucking",
    "wof:placetype":"venue"
},
  "geometry": {"coordinates":[-72.610724,42.384045],"type":"Point"}
}