{
  "type": "Feature",
  "properties": {
    "addr:full": "488 Hadley St South Hadley MA 01075",
    "addr:housenumber": "488",
    "addr:postcode": "01075",
    "addr:street": "Hadley St",
    "iso:country": "US",
    "sg:address": "488 Hadley St",
    "sg:city": "South Hadley",
    "sg:classifiers": [
      {
        "category": "Health Services",
        "subcategory": "Doctor",
        "type": "Services"
      }
    ],
    "sg:phone": "+1 413 532 9092",
    "sg:postcode": "01075",
    "sg:province": "MA",
    "sg:tags": [
      "physician",
      "surgeon"
    ],
    "wof:name": "South Hadley Wellness Ctr",
    "wof:placetype": "venue"
  },
  "geometry": {"coordinates":[-72.601199,42.284674],"type":"Point"}
}
