{
  "type": "Feature",
  "properties": {
    "addr:full": "2000 Boston Rd Wilbraham MA 01095",
    "addr:housenumber": "2000",
    "addr:postcode": "01095",
    "addr:street": "Boston Rd",
    "iso:country": "US",
    "sg:address": "2000 Boston Rd",
    "sg:city": "Wilbraham",
    "sg:classifiers": [
      {
        "category": "Restaurant",
        "type": "Food \u0026 Drink"
      }
    ],
    "sg:phone": "+1 413 543 2326",
    "sg:postcode": "01095",
    "sg:province": "MA",
    "wof:name": "Upper Crust Pizza II",
    "wof:placetype": "venue"
  },
  "geometry": {"coordinates":[-72.462662,42.151695],"type":"Point"}
}
