{
  "type": "Feature",
  "properties": {
    "iso:country":"US",
    "sg:address":"10 Taunton Ave",
    "sg:city":"Norton",
    "sg:classifiers":[
        {
            "category":"Retail",
            "subcategory":"Portrait Studio",
            "type":"Services"
        }
    ],
    "sg:phone":"+1 508 285 6941",
    "sg:postcode":"02766",
    "sg:province":"MA",
    "sg:tags":[
        "photography",
        "store"
    ],
    "wof:name":"Bookstore At Wheaton College",
    "wof:placetype":"venue"
},
  "geometry": {"coordinates":[-71.187302,41.9659],"type":"Point"}
}