{
  "type": "Feature",
  "properties": {
    "addr:full": "628 Main St Hyannis MA 02601",
    "addr:housenumber": "628",
    "addr:postcode": "02601",
    "addr:street": "Main St",
    "iso:country": "US",
    "sg:address": "628 Main St",
    "sg:city": "Hyannis",
    "sg:classifiers": [
      {
        "category": "Shopping",
        "subcategory": "Clothing, Apparel, \u0026 Fashions",
        "type": "Retail Goods"
      }
    ],
    "sg:phone": "+1 508 790 2786",
    "sg:postcode": "02601",
    "sg:province": "MA",
    "wof:name": "Del Sol Color Change Products",
    "wof:placetype": "venue"
  },
  "geometry": {"coordinates":[-70.291148,41.64902],"type":"Point"}
}
