{
  "type": "Feature",
  "properties": {
    "iso:country":"US",
    "sg:address":"628 Main St",
    "sg:city":"Hyannis",
    "sg:classifiers":[
        {
            "category":"Shopping",
            "subcategory":"Clothing, Apparel, & Fashions",
            "type":"Retail Goods"
        }
    ],
    "sg:phone":"+1 508 790 2786",
    "sg:postcode":"02601",
    "sg:province":"MA",
    "wof:name":"Del Sol Color Change Products",
    "wof:placetype":"venue"
},
  "geometry": {"coordinates":[-70.29114800000001,41.64902],"type":"Point"}
}