{
  "type": "Feature",
  "properties": {
    "addr:full":"25 N Dartmouth Mall North Dartmouth MA 02747",
    "addr:housenumber":"25",
    "addr:postcode":"02747",
    "addr:street":"N Dartmouth Mall",
    "iso:country":"US",
    "sg:address":"25 N Dartmouth Mall",
    "sg:city":"North Dartmouth",
    "sg:classifiers":[
        {
            "category":"Banks & Credit Unions",
            "subcategory":"Bank",
            "type":"Services"
        }
    ],
    "sg:phone":"+1 508 999 0032",
    "sg:postcode":"02747",
    "sg:province":"MA",
    "wof:name":"Citizens Bank",
    "wof:placetype":"venue"
},
  "geometry": {"coordinates":[-70.994272,41.641664],"type":"Point"}
}