{
  "type": "Feature",
  "properties": {
    "addr:full": "1 Congress Street Boston MA 02114",
    "addr:housenumber": "1",
    "addr:postcode": "02114",
    "addr:street": "Congress Street",
    "iso:country": "US",
    "sg:address": "1 Congress Street",
    "sg:city": "Boston",
    "sg:classifiers": [
      {
        "category": "Building \u0026 Trades",
        "subcategory": "Construction",
        "type": "Services"
      }
    ],
    "sg:phone": "+1 617 720 4296",
    "sg:postcode": "02114",
    "sg:province": "MA",
    "sg:tags": [
      "contractor"
    ],
    "wof:name": "Rubin Gary K \u0026 Assoc",
    "wof:placetype": "venue"
  },
  "geometry": {"coordinates":[-71.058367,42.362203],"type":"Point"}
}
