{
  "type": "Feature",
  "properties": {
    "addr:full": "201 3rd St Cambridge MA 02141",
    "addr:housenumber": "201",
    "addr:postcode": "02141",
    "addr:street": "3Rd St",
    "iso:country": "US",
    "sg:address": "201 3rd St",
    "sg:city": "Cambridge",
    "sg:classifiers": [
      {
        "category": "Building \u0026 Trades",
        "subcategory": "Locksmith",
        "type": "Services"
      }
    ],
    "sg:phone": "+1 617 299 2084",
    "sg:postcode": "02141",
    "sg:province": "MA",
    "sg:tags": [
      "key"
    ],
    "wof:name": "3rd St Available Locksmith",
    "wof:placetype": "venue"
  },
  "geometry": {"coordinates":[-71.081234,42.367765],"type":"Point"}
}
