{
  "type": "Feature",
  "properties": {
    "iso:country":"US",
    "sg:address":"84 Washington St",
    "sg:city":"Woburn",
    "sg:classifiers":[
        {
            "category":"Personal",
            "subcategory":"Beauty Salon",
            "type":"Services"
        }
    ],
    "sg:phone":"+1 781 939 9959",
    "sg:postcode":"01801",
    "sg:province":"MA",
    "wof:name":"Fantastic Sam's",
    "wof:placetype":"venue"
},
  "geometry": {"coordinates":[-71.12111,42.480413],"type":"Point"}
}