{
  "type": "Feature",
  "properties": {
    "iso:country":"US",
    "sg:address":"9 West Rd",
    "sg:city":"Orleans",
    "sg:classifiers":[
        {
            "category":"Personal",
            "subcategory":"Beauty Salon",
            "type":"Services"
        },
        {
            "category":"Shopping",
            "subcategory":"Beauty & Cosmetics",
            "type":"Retail Goods"
        },
        {
            "category":"Personal",
            "subcategory":"Nail Salon",
            "type":"Services"
        }
    ],
    "sg:phone":"+1 508 255 1900",
    "sg:postcode":"02653",
    "sg:province":"MA",
    "sg:tags":[
        "perfume",
        "salons-equipment",
        "supply"
    ],
    "wof:name":"Heavenly Nails",
    "wof:placetype":"venue"
},
  "geometry": {"coordinates":[-70.000269,41.780739],"type":"Point"}
}