{
  "type": "Feature",
  "properties": {
    "iso:country":"US",
    "sg:address":"16 Woodchester Dr",
    "sg:city":"Acton",
    "sg:classifiers":[
        {
            "category":"Professional",
            "subcategory":"Management & Consulting",
            "type":"Services"
        }
    ],
    "sg:phone":"+1   ",
    "sg:postcode":"01720",
    "sg:province":"MA",
    "wof:name":"Ianelli Assoc",
    "wof:placetype":"venue"
},
  "geometry": {"coordinates":[-71.493319,42.462446],"type":"Point"}
}