{
  "type": "Feature",
  "properties": {
    "addr:full": "16 Woodchester Dr Acton MA 01720",
    "addr:housenumber": "16",
    "addr:postcode": "01720",
    "addr:street": "Woodchester Dr",
    "iso:country": "US",
    "sg:address": "16 Woodchester Dr",
    "sg:city": "Acton",
    "sg:classifiers": [
      {
        "category": "Professional",
        "subcategory": "Management \u0026 Consulting",
        "type": "Services"
      }
    ],
    "sg:phone": "+1   ",
    "sg:postcode": "01720",
    "sg:province": "MA",
    "wof:name": "Ianelli Assoc",
    "wof:placetype": "venue"
  },
  "geometry": {"coordinates":[-71.493319,42.462446],"type":"Point"}
}
