{
  "type": "Feature",
  "properties": {
    "iso:country":"US",
    "sg:address":"1927 Beacon St",
    "sg:city":"Brighton",
    "sg:classifiers":[
        {
            "category":"Retail",
            "subcategory":"Portrait Studio",
            "type":"Services"
        },
        {
            "category":"Shopping",
            "subcategory":"Pharmacy",
            "type":"Retail Goods"
        }
    ],
    "sg:phone":"+1 617 738 6820",
    "sg:postcode":"02146",
    "sg:province":"MA",
    "sg:tags":[
        "photography",
        "drugstore",
        "store"
    ],
    "sg:website":"cvs.com",
    "wof:name":"CVS Pharmacy",
    "wof:placetype":"venue"
},
  "geometry": {"coordinates":[-71.148796,42.335885],"type":"Point"}
}