{
  "type": "Feature",
  "properties": {
    "addr:full": "1927 Beacon St Brighton MA 02146",
    "addr:housenumber": "1927",
    "addr:postcode": "02146",
    "addr:street": "Beacon St",
    "atp:label": "CVS Pharmacy, 1927 Beacon St. Brighton Brighton MA US",
    "atp:similarity": 3.916735887527466,
    "iso:country": "US",
    "ovtr:label": "CVS Pharmacy, 1927 Beacon St Brighton MA US",
    "ovtr:similarity": 2.8690030574798584,
    "sg:address": "1927 Beacon St",
    "sg:city": "Brighton",
    "sg:classifiers": [
      {
        "category": "Retail",
        "subcategory": "Portrait Studio",
        "type": "Services"
      },
      {
        "category": "Shopping",
        "subcategory": "Pharmacy",
        "type": "Retail Goods"
      }
    ],
    "sg:phone": "+1 617 738 6820",
    "sg:postcode": "02146",
    "sg:province": "MA",
    "sg:tags": [
      "photography",
      "drugstore",
      "store"
    ],
    "sg:website": "cvs.com",
    "wof:name": "CVS Pharmacy",
    "wof:placetype": "venue"
  },
  "geometry": {"coordinates":[-71.148796,42.335885],"type":"Point"}
}
