{
  "type": "Feature",
  "properties": {
    "addr:full": "820 Washington St South Easton MA 02375",
    "addr:housenumber": "820",
    "addr:postcode": "02375",
    "addr:street": "Washington St",
    "iso:country": "US",
    "sg:address": "820 Washington St",
    "sg:city": "South Easton",
    "sg:classifiers": [
      {
        "category": "Real Estate",
        "subcategory": "Real Estate Operator",
        "type": "Services"
      }
    ],
    "sg:phone": "+1 508 238 5715",
    "sg:postcode": "02375",
    "sg:province": "MA",
    "sg:tags": [
      "building",
      "parks"
    ],
    "wof:name": "Workteq Inc",
    "wof:placetype": "venue"
  },
  "geometry": {"coordinates":[-71.072966,42.034514],"type":"Point"}
}
