{
  "type": "Feature",
  "properties": {
    "addr:full": "546 South St Fitchburg MA 01420",
    "addr:housenumber": "546",
    "addr:postcode": "01420",
    "addr:street": "South St",
    "iso:country": "US",
    "sg:address": "546 South St",
    "sg:city": "Fitchburg",
    "sg:classifiers": [
      {
        "category": "Retail",
        "subcategory": "Auto Repair",
        "type": "Services"
      }
    ],
    "sg:phone": "+1 978 343 0821",
    "sg:postcode": "01420",
    "sg:province": "MA",
    "sg:tags": [
      "repairing",
      "automobile"
    ],
    "wof:name": "K D Automotive",
    "wof:placetype": "venue"
  },
  "geometry": {"coordinates":[-71.795266,42.56759],"type":"Point"}
}
