{
  "type": "Feature",
  "properties": {
    "addr:full": "5 Raymond St Lexington MA 02421",
    "addr:housenumber": "5",
    "addr:postcode": "02421",
    "addr:street": "Raymond St",
    "iso:country": "US",
    "sg:address": "5 Raymond St",
    "sg:city": "Lexington",
    "sg:classifiers": [
      {
        "category": "Professional",
        "subcategory": "Management \u0026 Consulting",
        "type": "Services"
      }
    ],
    "sg:phone": "+1   ",
    "sg:postcode": "02421",
    "sg:province": "MA",
    "wof:name": "Blake Melville Maywood Advisor",
    "wof:placetype": "venue"
  },
  "geometry": {"coordinates":[-71.230976,42.447374],"type":"Point"}
}
