{
  "type": "Feature",
  "properties": {
    "addr:full": "56 Allen Crest St Hampden MA 01036",
    "addr:housenumber": "56",
    "addr:postcode": "01036",
    "addr:street": "Allen Crest St",
    "iso:country": "US",
    "sg:address": "56 Allen Crest St",
    "sg:city": "Hampden",
    "sg:classifiers": [
      {
        "category": "Personal",
        "subcategory": "Tanning Parlor",
        "type": "Services"
      }
    ],
    "sg:phone": "+1 413 566 3222",
    "sg:postcode": "01036",
    "sg:province": "MA",
    "sg:tags": [
      "salon"
    ],
    "wof:name": "Total Transformation",
    "wof:placetype": "venue"
  },
  "geometry": {"coordinates":[-72.46777,42.077898],"type":"Point"}
}
