{
  "type": "Feature",
  "properties": {
    "iso:country":"US",
    "sg:address":"693 N Montello St",
    "sg:city":"Brockton",
    "sg:classifiers":[
        {
            "category":"Autos & Motor Vehicles",
            "subcategory":"Automobile Sales",
            "type":"Retail Goods"
        },
        {
            "category":"Retail",
            "subcategory":"Auto Repair",
            "type":"Services"
        }
    ],
    "sg:phone":"+1 508 584 3201",
    "sg:postcode":"02301",
    "sg:province":"MA",
    "sg:tags":[
        "body",
        "used",
        "car",
        "diagnostic",
        "painting",
        "repairing"
    ],
    "wof:name":"B A R Automotive",
    "wof:placetype":"venue"
},
  "geometry": {"coordinates":[-71.019447,42.10183],"type":"Point"}
}