{
  "type": "Feature",
  "properties": {
    "iso:country":"US",
    "sg:address":"245 Winter St",
    "sg:city":"Waltham",
    "sg:classifiers":[
        {
            "category":"Professional",
            "type":"Services"
        }
    ],
    "sg:phone":"+1 781 890 0535",
    "sg:postcode":"02451",
    "sg:province":"MA",
    "sg:tags":[
        "establishment"
    ],
    "wof:name":"Banking Decision Systems",
    "wof:placetype":"venue"
},
  "geometry": {"coordinates":[-71.252421,42.398403],"type":"Point"}
}