{
  "type": "Feature",
  "properties": {
    "addr:full": "100 Tower Office Park Woburn MA 01801",
    "addr:housenumber": "100",
    "addr:postcode": "01801",
    "addr:street": "Office Park",
    "iso:country": "US",
    "sg:address": "100 Tower Office Park",
    "sg:city": "Woburn",
    "sg:classifiers": [
      {
        "category": "Communications",
        "subcategory": "Film \u0026 Video Production",
        "type": "Services"
      }
    ],
    "sg:phone": "+1 781 937 0225",
    "sg:postcode": "01801",
    "sg:province": "MA",
    "sg:tags": [
      "consultant",
      "audio"
    ],
    "sg:website": "www.multimediatechnologies.com",
    "wof:name": "Multi Media Technologies",
    "wof:placetype": "venue"
  },
  "geometry": {"coordinates":[-71.123653,42.497697],"type":"Point"}
}
