{
  "type": "Feature",
  "properties": {
    "addr:full":"172 Lynn Fells Pkwy Saugus MA 01906",
    "addr:housenumber":"172",
    "addr:postcode":"01906",
    "addr:street":"Lynn Fells Pkwy",
    "iso:country":"US",
    "sg:address":"172 Lynn Fells Pkwy",
    "sg:city":"Saugus",
    "sg:classifiers":[
        {
            "category":"Autos & Motor Vehicles",
            "subcategory":"Fuel & Gas Station",
            "type":"Retail Goods"
        }
    ],
    "sg:phone":"+1 781 231 0907",
    "sg:postcode":"01906",
    "sg:province":"MA",
    "sg:tags":[
        "oil"
    ],
    "wof:name":"Fellsway Exxon",
    "wof:placetype":"venue"
},
  "geometry": {"coordinates":[-71.035375,42.472071],"type":"Point"}
}