{
  "type": "Feature",
  "properties": {
    "addr:full": "57 Edgartown Meadows Rd Edgartown MA 02539",
    "addr:housenumber": "57",
    "addr:postcode": "02539",
    "addr:street": "Edgartown Meadows Rd",
    "iso:country": "US",
    "sg:address": "57 Edgartown Meadows Rd",
    "sg:city": "Edgartown",
    "sg:classifiers": [
      {
        "category": "Manufacturing",
        "subcategory": "Wood Products",
        "type": "Manufacturing \u0026 Wholesale Goods"
      },
      {
        "category": "Building \u0026 Trades",
        "subcategory": "Construction",
        "type": "Services"
      }
    ],
    "sg:phone": "+1 508 627 9738",
    "sg:postcode": "02539",
    "sg:province": "MA",
    "sg:tags": [
      "mfg",
      "general",
      "contractor"
    ],
    "wof:name": "Zadeh \u0026 Brothers",
    "wof:placetype": "venue"
  },
  "geometry": {"coordinates":[-70.556994,41.388287],"type":"Point"}
}
