{
  "type": "Feature",
  "properties": {
    "iso:country":"US",
    "sg:address":"57 Edgartown Meadows Rd",
    "sg:city":"Edgartown",
    "sg:classifiers":[
        {
            "category":"Manufacturing",
            "subcategory":"Wood Products",
            "type":"Manufacturing & Wholesale Goods"
        },
        {
            "category":"Building & Trades",
            "subcategory":"Construction",
            "type":"Services"
        }
    ],
    "sg:phone":"+1 508 627 9738",
    "sg:postcode":"02539",
    "sg:province":"MA",
    "sg:tags":[
        "mfg",
        "general",
        "contractor"
    ],
    "wof:name":"Zadeh & Brothers",
    "wof:placetype":"venue"
},
  "geometry": {"coordinates":[-70.556994,41.388287],"type":"Point"}
}