{
  "type": "Feature",
  "properties": {
    "addr:full": "3 Railroad St Great Barrington MA 01230",
    "addr:housenumber": "3",
    "addr:postcode": "01230",
    "addr:street": "Railroad St",
    "iso:country": "US",
    "sg:address": "3 Railroad St",
    "sg:city": "Great Barrington",
    "sg:classifiers": [
      {
        "category": "Shopping",
        "subcategory": "Gifts \u0026 Souvenirs",
        "type": "Retail Goods"
      }
    ],
    "sg:phone": "+1 413 528 1899",
    "sg:postcode": "01230",
    "sg:province": "MA",
    "sg:tags": [
      "shop"
    ],
    "wof:name": "Red Door",
    "wof:placetype": "venue"
  },
  "geometry": {"coordinates":[-73.363367,42.195649],"type":"Point"}
}
