{
  "type": "Feature",
  "properties": {
    "addr:full":"15 Ward St Carver MA 02330",
    "addr:housenumber":"15",
    "addr:postcode":"02330",
    "addr:street":"Ward St",
    "iso:country":"US",
    "sg:address":"15 Ward St",
    "sg:city":"Carver",
    "sg:classifiers":[
        {
            "category":"Building & Trades",
            "subcategory":"Landscaping Services",
            "type":"Services"
        }
    ],
    "sg:phone":"+1 508 866 7775",
    "sg:postcode":"02330",
    "sg:province":"MA",
    "wof:name":"Yard Wizard",
    "wof:placetype":"venue"
},
  "geometry": {"coordinates":[-70.741317,41.894911],"type":"Point"}
}