{
  "type": "Feature",
  "properties": {
    "iso:country":"US",
    "sg:address":"20 Sequoia Ln",
    "sg:city":"Hanover",
    "sg:classifiers":[
        {
            "category":"Manufacturing",
            "subcategory":"Metals",
            "type":"Manufacturing & Wholesale Goods"
        }
    ],
    "sg:phone":"+1 781 826 8141",
    "sg:postcode":"02339",
    "sg:province":"MA",
    "sg:tags":[
        "hardware"
    ],
    "wof:name":"Crawford Products Inc",
    "wof:placetype":"venue"
},
  "geometry": {"coordinates":[-70.864784,42.10344],"type":"Point"}
}