{
  "type": "Feature",
  "properties": {
    "iso:country":"US",
    "sg:address":"258 W Main St",
    "sg:city":"Northborough",
    "sg:classifiers":[
        {
            "category":"Retail",
            "subcategory":"Auto Repair",
            "type":"Services"
        }
    ],
    "sg:phone":"+1 508 393 7777",
    "sg:postcode":"01532",
    "sg:province":"MA",
    "sg:tags":[
        "repairing",
        "automobile"
    ],
    "wof:name":"European Car Svc Inc",
    "wof:placetype":"venue"
},
  "geometry": {"coordinates":[-71.655845,42.309698],"type":"Point"}
}