{
  "type": "Feature",
  "properties": {
    "iso:country":"US",
    "sg:address":"65 Burlington St",
    "sg:city":"Woburn",
    "sg:classifiers":[
        {
            "category":"Building & Trades",
            "subcategory":"Landscaping Services",
            "type":"Services"
        }
    ],
    "sg:phone":"+1 781 938 8988",
    "sg:postcode":"01801",
    "sg:province":"MA",
    "sg:tags":[
        "landscape",
        "contractor"
    ],
    "wof:name":"Heimlich Landscaping & Constr",
    "wof:placetype":"venue"
},
  "geometry": {"coordinates":[-71.168808,42.478008],"type":"Point"}
}