{
  "type": "Feature",
  "properties": {
    "addr:full":"943 Great Plain Ave Needham MA 02492",
    "addr:housenumber":"943",
    "addr:postcode":"02492",
    "addr:street":"Great Plain Ave",
    "iso:country":"US",
    "sg:address":"943 Great Plain Ave",
    "sg:city":"Needham",
    "sg:classifiers":[
        {
            "category":"Shopping",
            "subcategory":"Jewelry",
            "type":"Retail Goods"
        }
    ],
    "sg:phone":"+1 781 444 0230",
    "sg:postcode":"02492",
    "sg:province":"MA",
    "sg:tags":[
        "jeweler"
    ],
    "wof:name":"Three Crown Jewelry",
    "wof:placetype":"venue"
},
  "geometry": {"coordinates":[-71.235282,42.28035],"type":"Point"}
}