{
  "type": "Feature",
  "properties": {
    "addr:full":"419 Washington St Brighton MA 02135",
    "addr:housenumber":"419",
    "addr:postcode":"02135",
    "addr:street":"Washington St",
    "iso:country":"US",
    "sg:address":"419 Washington St",
    "sg:city":"Brighton",
    "sg:classifiers":[
        {
            "category":"Retail",
            "subcategory":"Repair Shop",
            "type":"Services"
        }
    ],
    "sg:phone":"+1 617 370 0392",
    "sg:postcode":"02135",
    "sg:province":"MA",
    "sg:tags":[
        "lock",
        "locksmith"
    ],
    "wof:name":"24 Hour 7 Day Emergency",
    "wof:placetype":"venue"
},
  "geometry": {"coordinates":[-71.154715,42.349129],"type":"Point"}
}