{
  "type": "Feature",
  "properties": {
    "iso:country":"US",
    "sg:address":"19 Main St",
    "sg:city":"Edgartown",
    "sg:classifiers":[
        {
            "category":"Banks & Credit Unions",
            "subcategory":"Bank",
            "type":"Services"
        },
        {
            "category":"Banks & Credit Unions",
            "subcategory":"Financial Services",
            "type":"Services"
        }
    ],
    "sg:phone":"+1 508 627 9400",
    "sg:postcode":"02539",
    "sg:province":"MA",
    "sg:tags":[
        "saving",
        "loan",
        "commercial"
    ],
    "sg:website":"http://www.sovereignbank.com",
    "wof:name":"Sovereign Bank",
    "wof:placetype":"venue"
},
  "geometry": {"coordinates":[-70.513008,41.3894],"type":"Point"}
}