{
  "type": "Feature",
  "properties": {
    "addr:full":"202 Moulton St Rehoboth MA 02769",
    "addr:housenumber":"202",
    "addr:postcode":"02769",
    "addr:street":"Moulton St",
    "iso:country":"US",
    "sg:address":"202 Moulton St",
    "sg:city":"Rehoboth",
    "sg:classifiers":[
        {
            "category":"Shopping",
            "subcategory":"Used Merchandise",
            "type":"Retail Goods"
        }
    ],
    "sg:phone":"+1 508 252 3171",
    "sg:postcode":"02769",
    "sg:province":"MA",
    "sg:tags":[
        "antique"
    ],
    "wof:name":"North Star Antique Refinishing",
    "wof:placetype":"venue"
},
  "geometry": {"coordinates":[-71.233152,41.821181],"type":"Point"}
}