{
  "type": "Feature",
  "properties": {
    "iso:country":"US",
    "sg:address":"47 Industrial Dr",
    "sg:city":"Uxbridge",
    "sg:classifiers":[
        {
            "category":"Building & Trades",
            "subcategory":"Construction",
            "type":"Services"
        }
    ],
    "sg:phone":"+1 508 278 8055",
    "sg:postcode":"01569",
    "sg:province":"MA",
    "sg:tags":[
        "roofing",
        "contractor"
    ],
    "wof:name":"Windows Plus",
    "wof:placetype":"venue"
},
  "geometry": {"coordinates":[-71.613404,42.038774],"type":"Point"}
}