{
  "type": "Feature",
  "properties": {
    "addr:full": "210 Stedman St Lowell MA 01851",
    "addr:housenumber": "210",
    "addr:postcode": "01851",
    "addr:street": "Stedman St",
    "iso:country": "US",
    "sg:address": "210 Stedman St",
    "sg:city": "Lowell",
    "sg:classifiers": [
      {
        "category": "Wholesale",
        "subcategory": "Chemicals \u0026 Plastics",
        "type": "Manufacturing \u0026 Wholesale Goods"
      }
    ],
    "sg:phone": "+1 978 425 2000",
    "sg:postcode": "01851",
    "sg:province": "MA",
    "sg:tags": [
      "adhesive",
      "glue"
    ],
    "wof:name": "Norpak Adhesives",
    "wof:placetype": "venue"
  },
  "geometry": {"coordinates":[-71.351103,42.625323],"type":"Point"}
}
