{
  "type": "Feature",
  "properties": {
    "iso:country":"US",
    "sg:address":"210 Stedman St",
    "sg:city":"Lowell",
    "sg:classifiers":[
        {
            "category":"Wholesale",
            "subcategory":"Chemicals & Plastics",
            "type":"Manufacturing & Wholesale Goods"
        }
    ],
    "sg:phone":"+1 978 425 2000",
    "sg:postcode":"01851",
    "sg:province":"MA",
    "sg:tags":[
        "adhesive",
        "glue"
    ],
    "wof:name":"Norpak Adhesives",
    "wof:placetype":"venue"
},
  "geometry": {"coordinates":[-71.35110299999999,42.625323],"type":"Point"}
}