{
  "type": "Feature",
  "properties": {
    "addr:full":"201 Middle Rd Chilmark MA 02535",
    "addr:housenumber":"201",
    "addr:postcode":"02535",
    "addr:street":"Middle Rd",
    "iso:country":"US",
    "sg:address":"201 Middle Rd",
    "sg:city":"Chilmark",
    "sg:classifiers":[
        {
            "category":"Home & Garden",
            "subcategory":"Building Materials",
            "type":"Retail Goods"
        }
    ],
    "sg:phone":"+1 508 645 2202",
    "sg:postcode":"02535",
    "sg:province":"MA",
    "sg:tags":[
        "window",
        "wood"
    ],
    "wof:name":"Parry, William Mill Work",
    "wof:placetype":"venue"
},
  "geometry": {"coordinates":[-70.71751500000001,41.3624],"type":"Point"}
}