{
  "type": "Feature",
  "properties": {
    "addr:full": "202 Pond St Ashland MA 01721",
    "addr:housenumber": "202",
    "addr:postcode": "01721",
    "addr:street": "Pond St",
    "iso:country": "US",
    "ovtr:label": "Camp Canine, 202 Pond St Ashland MA US",
    "ovtr:similarity": 2.2915139198303223,
    "sg:address": "202 Pond St",
    "sg:city": "Ashland",
    "sg:phone": "+1 508 881 7364",
    "sg:postcode": "01721",
    "sg:province": "MA",
    "sg:website": "http://www.campcaninedogspa.com",
    "wof:name": "Camp Canine",
    "wof:placetype": "venue"
  },
  "geometry": {"coordinates":[-71.430337,42.247265],"type":"Point"}
}
