{
  "type": "Feature",
  "properties": {
    "iso:country":"US",
    "sg:address":"202 Pond St",
    "sg:city":"Ashland",
    "sg:phone":"+1 508 881 7364",
    "sg:postcode":"01721",
    "sg:province":"MA",
    "sg:website":"http://www.campcaninedogspa.com",
    "wof:name":"Camp Canine",
    "wof:placetype":"venue"
},
  "geometry": {"coordinates":[-71.43033699999999,42.247265],"type":"Point"}
}