{
  "type": "Feature",
  "properties": {
    "iso:country":"US",
    "sg:address":"129 Munroe St",
    "sg:city":"Lynn",
    "sg:classifiers":[
        {
            "category":"Restaurant",
            "type":"Food & Drink"
        }
    ],
    "sg:phone":"+1 781 586 0444",
    "sg:postcode":"01901",
    "sg:province":"MA",
    "wof:name":"Victorima Fried Chicken",
    "wof:placetype":"venue"
},
  "geometry": {"coordinates":[-70.94532100000001,42.464048],"type":"Point"}
}