{
  "type": "Feature",
  "properties": {
    "addr:full":"74 Mill Rd East Sandwich MA 02537",
    "addr:housenumber":"74",
    "addr:postcode":"02537",
    "addr:street":"Mill Rd",
    "iso:country":"US",
    "sg:address":"74 Mill Rd",
    "sg:city":"East Sandwich",
    "sg:classifiers":[
        {
            "category":"Personal",
            "type":"Services"
        }
    ],
    "sg:phone":"+1 508 833 8200",
    "sg:postcode":"02537",
    "sg:province":"MA",
    "sg:tags":[
        "electrolysis"
    ],
    "wof:name":"A Perfect Solution",
    "wof:placetype":"venue"
},
  "geometry": {"coordinates":[-70.457138,41.714332],"type":"Point"}
}