{
  "type": "Feature",
  "properties": {
    "iso:country":"US",
    "sg:address":"398 Commonwealth Ave",
    "sg:city":"Boston",
    "sg:classifiers":[
        {
            "category":"Health Services",
            "subcategory":"Dentist",
            "type":"Services"
        }
    ],
    "sg:phone":"+1 617 262 3737",
    "sg:postcode":"02215",
    "sg:province":"MA",
    "wof:name":"Welz Valdemar Dent",
    "wof:placetype":"venue"
},
  "geometry": {"coordinates":[-71.08869900000001,42.3489],"type":"Point"}
}