{
  "type": "Feature",
  "properties": {
    "addr:full": "251 Waltham Street Lexington MA 02421",
    "addr:housenumber": "251",
    "addr:postcode": "02421",
    "addr:street": "Waltham Street",
    "iso:country": "US",
    "sg:address": "251 Waltham Street",
    "sg:city": "Lexington",
    "sg:classifiers": [
      {
        "category": "Education",
        "subcategory": "School",
        "type": "Public Place"
      }
    ],
    "sg:phone": "+1 781 861 2499",
    "sg:postcode": "02421",
    "sg:province": "MA",
    "sg:tags": [
      "high",
      "middle",
      "elementary"
    ],
    "sg:website": "lps.lexingtonma.org",
    "wof:name": "Lexington Town of",
    "wof:placetype": "venue"
  },
  "geometry": {"coordinates":[-71.231151,42.441783],"type":"Point"}
}
