{
  "type": "Feature",
  "properties": {
    "addr:full":"74 Arlington Ave Dracut MA 01826",
    "addr:housenumber":"74",
    "addr:postcode":"01826",
    "addr:street":"Arlington Ave",
    "iso:country":"US",
    "sg:address":"74 Arlington Ave",
    "sg:city":"Dracut",
    "sg:classifiers":[
        {
            "category":"Wholesale",
            "subcategory":"Construction Materials",
            "type":"Manufacturing & Wholesale Goods"
        }
    ],
    "sg:phone":"+1 978 454 3574",
    "sg:postcode":"01826",
    "sg:province":"MA",
    "sg:tags":[
        "concrete",
        "form"
    ],
    "wof:name":"Jeff St George",
    "wof:placetype":"venue"
},
  "geometry": {"coordinates":[-71.299915,42.667519],"type":"Point"}
}