{
  "type": "Feature",
  "properties": {
    "iso:country":"US",
    "sg:address":"45 Grand St",
    "sg:city":"Worcester",
    "sg:classifiers":[
        {
            "category":"Wholesale",
            "subcategory":"Apparel",
            "type":"Manufacturing & Wholesale Goods"
        }
    ],
    "sg:phone":"+1 508 798 8731",
    "sg:postcode":"01610",
    "sg:province":"MA",
    "sg:tags":[
        "clothing"
    ],
    "wof:name":"Best Value Sportswear",
    "wof:placetype":"venue"
},
  "geometry": {"coordinates":[-71.81874500000001,42.248776],"type":"Point"}
}