{
  "type": "Feature",
  "properties": {
    "addr:full": "38 Rosary Ln Hyannis MA 02601",
    "addr:housenumber": "38",
    "addr:postcode": "02601",
    "addr:street": "Rosary Ln",
    "iso:country": "US",
    "sg:address": "38 Rosary Ln",
    "sg:city": "Hyannis",
    "sg:classifiers": [
      {
        "category": "Building \u0026 Trades",
        "subcategory": "Construction",
        "type": "Services"
      }
    ],
    "sg:phone": "+1 508 771 4128",
    "sg:postcode": "02601",
    "sg:province": "MA",
    "sg:tags": [
      "excavating",
      "contractor"
    ],
    "wof:name": "Hickey Construction Inc",
    "wof:placetype": "venue"
  },
  "geometry": {"coordinates":[-70.26815,41.668614],"type":"Point"}
}
