{
  "type": "Feature",
  "properties": {
    "iso:country":"US",
    "sg:address":"1 Recovery Rd",
    "sg:city":"Wareham",
    "sg:classifiers":[
        {
            "category":"Health Services",
            "subcategory":"Doctor",
            "type":"Services"
        }
    ],
    "sg:phone":"+1 508 295 3306",
    "sg:postcode":"02571",
    "sg:province":"MA",
    "sg:tags":[
        "medicine",
        "physician",
        "surgeon",
        "sport",
        "surgeons"
    ],
    "wof:name":"Sports Medicine Center",
    "wof:placetype":"venue"
},
  "geometry": {"coordinates":[-70.741928,41.778961],"type":"Point"}
}