{
  "type": "Feature",
  "properties": {
    "addr:full": "51 Boston Hill Rd Fairhaven MA 02719",
    "addr:housenumber": "51",
    "addr:postcode": "02719",
    "addr:street": "Boston Hill Rd",
    "iso:country": "US",
    "sg:address": "51 Boston Hill Rd",
    "sg:city": "Fairhaven",
    "sg:classifiers": [
      {
        "category": "Social Services",
        "subcategory": "Child Care",
        "type": "Services"
      }
    ],
    "sg:phone": "+1 508 979 4967",
    "sg:postcode": "02719",
    "sg:province": "MA",
    "wof:name": "Rock-A-Bye Kids",
    "wof:placetype": "venue"
  },
  "geometry": {"coordinates":[-70.889426,41.655399],"type":"Point"}
}
