{
  "type": "Feature",
  "properties": {
    "iso:country":"US",
    "sg:address":"262 E Eagle St",
    "sg:city":"East Boston",
    "sg:classifiers":[
        {
            "category":"Professional",
            "subcategory":"Detective & Security Services",
            "type":"Services"
        }
    ],
    "sg:phone":"+1 617 567 7448",
    "sg:postcode":"02128",
    "sg:province":"MA",
    "sg:tags":[
        "constable"
    ],
    "wof:name":"John G Consolo & Assoc",
    "wof:placetype":"venue"
},
  "geometry": {"coordinates":[-71.030689,42.381414],"type":"Point"}
}