{
  "type": "Feature",
  "properties": {
    "iso:country":"US",
    "sg:address":"54 Middle St",
    "sg:city":"Leominster",
    "sg:classifiers":[
        {
            "category":"Wholesale",
            "subcategory":"Vending Machines",
            "type":"Manufacturing & Wholesale Goods"
        }
    ],
    "sg:phone":"+1 978 466 1811",
    "sg:postcode":"01453",
    "sg:province":"MA",
    "wof:name":"P & P Vending",
    "wof:placetype":"venue"
},
  "geometry": {"coordinates":[-71.753535,42.522702],"type":"Point"}
}