{
  "type": "Feature",
  "properties": {
    "addr:full": "54 Middle St Leominster MA 01453",
    "addr:housenumber": "54",
    "addr:postcode": "01453",
    "addr:street": "Middle St",
    "iso:country": "US",
    "sg:address": "54 Middle St",
    "sg:city": "Leominster",
    "sg:classifiers": [
      {
        "category": "Wholesale",
        "subcategory": "Vending Machines",
        "type": "Manufacturing \u0026 Wholesale Goods"
      }
    ],
    "sg:phone": "+1 978 466 1811",
    "sg:postcode": "01453",
    "sg:province": "MA",
    "wof:name": "P \u0026 P Vending",
    "wof:placetype": "venue"
  },
  "geometry": {"coordinates":[-71.753535,42.522702],"type":"Point"}
}
