{
  "type": "Feature",
  "properties": {
    "iso:country":"US",
    "sg:address":"862 Washington St",
    "sg:city":"Gloucester",
    "sg:classifiers":[
        {
            "category":"Manufacturing",
            "subcategory":"Building Materials",
            "type":"Manufacturing & Wholesale Goods"
        }
    ],
    "sg:phone":"+1   ",
    "sg:postcode":"01930",
    "sg:province":"MA",
    "sg:tags":[
        "mfg",
        "wood",
        "kitchen",
        "cabinet"
    ],
    "wof:name":"Hurd J S Kit & Bath Design",
    "wof:placetype":"venue"
},
  "geometry": {"coordinates":[-70.669922,42.663079],"type":"Point"}
}