{
  "type": "Feature",
  "properties": {
    "addr:full":"990 Main St Holyoke MA 01040",
    "addr:housenumber":"990",
    "addr:postcode":"01040",
    "addr:street":"Main St",
    "iso:country":"US",
    "sg:address":"990 Main St",
    "sg:city":"Holyoke",
    "sg:classifiers":[
        {
            "category":"Retail",
            "subcategory":"Car Wash",
            "type":"Services"
        }
    ],
    "sg:phone":"+1 413 532 2378",
    "sg:postcode":"01040",
    "sg:province":"MA",
    "sg:tags":[
        "polishing",
        "washing"
    ],
    "wof:name":"Bradley Auto Wash",
    "wof:placetype":"venue"
},
  "geometry": {"coordinates":[-72.629199,42.179757],"type":"Point"}
}