{
  "type": "Feature",
  "properties": {
    "iso:country":"US",
    "sg:address":"120 Parker St",
    "sg:city":"Lawrence",
    "sg:classifiers":[
        {
            "category":"Health Services",
            "subcategory":"Doctor",
            "type":"Services"
        }
    ],
    "sg:phone":"+1 978 682 8285",
    "sg:postcode":"01843",
    "sg:province":"MA",
    "sg:tags":[
        "dentist"
    ],
    "wof:name":"Paul A De Marco DDS",
    "wof:placetype":"venue"
},
  "geometry": {"coordinates":[-71.158586,42.697731],"type":"Point"}
}