{
  "type": "Feature",
  "properties": {
    "addr:full":"93 Como Rd Hyde Park MA 02136",
    "addr:housenumber":"93",
    "addr:postcode":"02136",
    "addr:street":"Como Rd",
    "iso:country":"US",
    "sg:address":"93 Como Rd",
    "sg:city":"Hyde Park",
    "sg:classifiers":[
        {
            "category":"Real Estate",
            "subcategory":"Real Estate Agent",
            "type":"Services"
        }
    ],
    "sg:phone":"+1 617 361 0805",
    "sg:postcode":"02136",
    "sg:province":"MA",
    "sg:tags":[
        "inspection"
    ],
    "wof:name":"Commonwealth Inspection Svc",
    "wof:placetype":"venue"
},
  "geometry": {"coordinates":[-71.142923,42.241667],"type":"Point"}
}