{
  "type": "Feature",
  "properties": {
    "iso:country":"US",
    "sg:address":"41 Alexander Rd",
    "sg:city":"Billerica",
    "sg:classifiers":[
        {
            "category":"Professional",
            "type":"Services"
        }
    ],
    "sg:phone":"+1 978 663 2391",
    "sg:postcode":"01821",
    "sg:province":"MA",
    "sg:tags":[
        "establishment"
    ],
    "wof:name":"Accavia",
    "wof:placetype":"venue"
},
  "geometry": {"coordinates":[-71.217457,42.552986],"type":"Point"}
}