{
  "type": "Feature",
  "properties": {
    "iso:country":"US",
    "sg:address":"185 Devonshire St",
    "sg:city":"Boston",
    "sg:classifiers":[
        {
            "category":"Professional",
            "subcategory":"Lawyer & Legal Services",
            "type":"Services"
        }
    ],
    "sg:phone":"+1 617 542 7486",
    "sg:postcode":"02110",
    "sg:province":"MA",
    "wof:name":"Berman Leihu Atty",
    "wof:placetype":"venue"
},
  "geometry": {"coordinates":[-71.05740400000001,42.355999],"type":"Point"}
}