{
  "type": "Feature",
  "properties": {
    "iso:country":"US",
    "sg:address":"2450 Main St",
    "sg:city":"Brewster",
    "sg:classifiers":[
        {
            "category":"Insurance",
            "subcategory":"Insurance Agent",
            "type":"Services"
        }
    ],
    "sg:phone":"+1 508 896 3771",
    "sg:postcode":"02631",
    "sg:province":"MA",
    "wof:name":"Callahan Insurance Inc",
    "wof:placetype":"venue"
},
  "geometry": {"coordinates":[-70.06500200000001,41.765542],"type":"Point"}
}