{
  "type": "Feature",
  "properties": {
    "addr:full":"140 Elliott St Beverly MA 01915",
    "addr:housenumber":"140",
    "addr:postcode":"01915",
    "addr:street":"Elliott St",
    "iso:country":"US",
    "sg:address":"140 Elliott St",
    "sg:city":"Beverly",
    "sg:classifiers":[
        {
            "category":"Manufacturing",
            "subcategory":"Tools & Machinery",
            "type":"Manufacturing & Wholesale Goods"
        }
    ],
    "sg:phone":"+1 978 524 0022",
    "sg:postcode":"01915",
    "sg:province":"MA",
    "sg:tags":[
        "machine",
        "shop"
    ],
    "wof:name":"Micronics",
    "wof:placetype":"venue"
},
  "geometry": {"coordinates":[-70.885243,42.55571],"type":"Point"}
}