{
  "type": "Feature",
  "properties": {
    "addr:full":"97 Webster St Shrewsbury MA 01516",
    "addr:housenumber":"97",
    "addr:postcode":"01516",
    "addr:street":"Webster St",
    "iso:country":"US",
    "sg:address":"97 Webster St",
    "sg:city":"Shrewsbury",
    "sg:classifiers":[
        {
            "category":"Education",
            "subcategory":"Dance Studio",
            "type":"Public Place"
        }
    ],
    "sg:phone":"+1 508 752 4910",
    "sg:postcode":"01516",
    "sg:province":"MA",
    "sg:tags":[
        "instruction",
        "dancing"
    ],
    "wof:name":"Poise Style & Motion Ballroom",
    "wof:placetype":"venue"
},
  "geometry": {"coordinates":[-71.76601700000001,42.055549],"type":"Point"}
}