{
  "type": "Feature",
  "properties": {
    "addr:full":"123 Main St Pepperell MA 01463",
    "addr:housenumber":"123",
    "addr:postcode":"01463",
    "addr:street":"Main St",
    "iso:country":"US",
    "sg:address":"123 Main St",
    "sg:city":"Pepperell",
    "sg:classifiers":[
        {
            "category":"Shopping",
            "type":"Retail Goods"
        }
    ],
    "sg:phone":"+1 978 433 3323",
    "sg:postcode":"01463",
    "sg:province":"MA",
    "sg:tags":[
        "wheel",
        "chair",
        "scooter"
    ],
    "wof:name":"Mc Nabb General Store",
    "wof:placetype":"venue"
},
  "geometry": {"coordinates":[-71.57916299999999,42.665042],"type":"Point"}
}