{
  "type": "Feature",
  "properties": {
    "iso:country":"US",
    "sg:address":"19 Jacob Rd",
    "sg:city":"Belmont",
    "sg:classifiers":[
        {
            "category":"Home & Garden",
            "subcategory":"Building Materials",
            "type":"Retail Goods"
        }
    ],
    "sg:phone":"+1   ",
    "sg:postcode":"02478",
    "sg:province":"MA",
    "wof:name":"Martin Sherwin",
    "wof:placetype":"venue"
},
  "geometry": {"coordinates":[-71.165418,42.381998],"type":"Point"}
}