{
  "type": "Feature",
  "properties": {
    "addr:full": "19 Jacob Rd Belmont MA 02478",
    "addr:housenumber": "19",
    "addr:postcode": "02478",
    "addr:street": "Jacob Rd",
    "iso:country": "US",
    "sg:address": "19 Jacob Rd",
    "sg:city": "Belmont",
    "sg:classifiers": [
      {
        "category": "Home \u0026 Garden",
        "subcategory": "Building Materials",
        "type": "Retail Goods"
      }
    ],
    "sg:phone": "+1   ",
    "sg:postcode": "02478",
    "sg:province": "MA",
    "wof:name": "Martin Sherwin",
    "wof:placetype": "venue"
  },
  "geometry": {"coordinates":[-71.165418,42.381998],"type":"Point"}
}
