{
  "type": "Feature",
  "properties": {
    "addr:full": "6 North Ave Attleboro Falls MA 02763",
    "addr:housenumber": "6",
    "addr:postcode": "02763",
    "addr:street": "North Ave",
    "iso:country": "US",
    "sg:address": "6 North Ave",
    "sg:city": "Attleboro Falls",
    "sg:classifiers": [
      {
        "category": "Shopping",
        "subcategory": "Jewelry",
        "type": "Retail Goods"
      }
    ],
    "sg:phone": "+1   ",
    "sg:postcode": "02763",
    "sg:province": "MA",
    "wof:name": "Eastern Mass Clock Service",
    "wof:placetype": "venue"
  },
  "geometry": {"coordinates":[-71.303628,41.967555],"type":"Point"}
}
