{
  "type": "Feature",
  "properties": {
    "iso:country":"US",
    "sg:address":"178 Granite St",
    "sg:city":"Rockport",
    "sg:classifiers":[
        {
            "category":"Professional",
            "subcategory":"Research",
            "type":"Services"
        }
    ],
    "sg:phone":"+1 978 546 7414",
    "sg:postcode":"01966",
    "sg:province":"MA",
    "sg:tags":[
        "development",
        "laboratory"
    ],
    "wof:name":"Advanced Protein Technologies",
    "wof:placetype":"venue"
},
  "geometry": {"coordinates":[-70.624583,42.677469],"type":"Point"}
}