{
  "type": "Feature",
  "properties": {
    "addr:full":"56 Bennett Street Brighton MA 02135",
    "addr:housenumber":"56",
    "addr:postcode":"02135",
    "addr:street":"Bennett Street",
    "iso:country":"US",
    "sg:address":"56 Bennett Street",
    "sg:city":"Brighton",
    "sg:classifiers":[
        {
            "category":"Health Services",
            "subcategory":"Health Practitioner",
            "type":"Services"
        }
    ],
    "sg:phone":"+1 617 789 4141",
    "sg:postcode":"02135",
    "sg:province":"MA",
    "sg:tags":[
        "acupuncture"
    ],
    "wof:name":"Strauss Adele Acupuncture & Oriental Body Work Therapies",
    "wof:placetype":"venue"
},
  "geometry": {"coordinates":[-71.15596499999999,42.351912],"type":"Point"}
}