{
  "type": "Feature",
  "properties": {
    "iso:country":"US",
    "sg:address":"3 Windsor Ave",
    "sg:city":"Acton",
    "sg:classifiers":[
        {
            "category":"Professional",
            "subcategory":"Computer Services",
            "type":"Services"
        }
    ],
    "sg:phone":"+1 978 841 9581",
    "sg:postcode":"01720",
    "sg:province":"MA",
    "sg:website":"http://www.tripleseat.com",
    "wof:name":"Tripleseat",
    "wof:placetype":"venue"
},
  "geometry": {"coordinates":[-71.47365000000001,42.475341],"type":"Point"}
}