{
  "type": "Feature",
  "properties": {
    "iso:country":"US",
    "sg:address":"109 Main St",
    "sg:city":"North Andover",
    "sg:classifiers":[
        {
            "category":"Food & Beverages",
            "subcategory":"Groceries & Convenience Stores",
            "type":"Retail Goods"
        }
    ],
    "sg:phone":"+1 978 683 8330",
    "sg:postcode":"01845",
    "sg:province":"MA",
    "sg:tags":[
        "grocer"
    ],
    "wof:name":"Star Market",
    "wof:placetype":"venue"
},
  "geometry": {"coordinates":[-71.131264,42.70298],"type":"Point"}
}