{
  "type": "Feature",
  "properties": {
    "addr:full":"590 Dartmouth St South Dartmouth MA 02748",
    "addr:housenumber":"590",
    "addr:postcode":"02748",
    "addr:street":"Dartmouth St",
    "iso:country":"US",
    "sg:address":"590 Dartmouth St",
    "sg:city":"South Dartmouth",
    "sg:classifiers":[
        {
            "category":"Autos & Motor Vehicles",
            "subcategory":"Automobile Sales",
            "type":"Retail Goods"
        }
    ],
    "sg:phone":"+1 508 991 8050",
    "sg:postcode":"02748",
    "sg:province":"MA",
    "sg:tags":[
        "car",
        "dealer"
    ],
    "wof:name":"Bliss Corner Auto Sales",
    "wof:placetype":"venue"
},
  "geometry": {"coordinates":[-70.94032300000001,41.608192],"type":"Point"}
}