{
  "type": "Feature",
  "properties": {
    "addr:full": "28 Winn St Burlington MA 01803",
    "addr:housenumber": "28",
    "addr:postcode": "01803",
    "addr:street": "Winn St",
    "iso:country": "US",
    "sg:address": "28 Winn St",
    "sg:city": "Burlington",
    "sg:classifiers": [
      {
        "category": "Donuts",
        "subcategory": "None",
        "type": "Food \u0026 Drink"
      }
    ],
    "sg:phone": "+1 781 273 1889",
    "sg:postcode": "01803",
    "sg:province": "MA",
    "sg:website": "www.dunkindonuts.com",
    "wof:name": "Dunkin Donuts",
    "wof:placetype": "venue"
  },
  "geometry": {"coordinates":[-71.173584,42.490924],"type":"Point"}
}
