{
  "type": "Feature",
  "properties": {
    "iso:country":"US",
    "sg:address":"1442 Main St",
    "sg:city":"Brockton",
    "sg:classifiers":[
        {
            "category":"Local Transit",
            "type":"Transportation"
        }
    ],
    "sg:phone":"+1 508 584 5530",
    "sg:postcode":"02301",
    "sg:province":"MA",
    "sg:tags":[
        "bus",
        "line"
    ],
    "wof:name":"Dial-A-Bat",
    "wof:placetype":"venue"
},
  "geometry": {"coordinates":[-71.01302200000001,42.056706],"type":"Point"}
}