{
  "type": "Feature",
  "properties": {
    "addr:full": "29 Tara Ln North Falmouth MA 02556",
    "addr:housenumber": "29",
    "addr:postcode": "02556",
    "addr:street": "Tara Ln North",
    "iso:country": "US",
    "sg:address": "29 Tara Ln",
    "sg:city": "North Falmouth",
    "sg:classifiers": [
      {
        "category": "Travel",
        "subcategory": "Travel Agent",
        "type": "Entertainment"
      }
    ],
    "sg:phone": "+1   ",
    "sg:postcode": "02556",
    "sg:province": "MA",
    "sg:tags": [
      "agency"
    ],
    "wof:name": "Ocean Breeze Vacations",
    "wof:placetype": "venue"
  },
  "geometry": {"coordinates":[-70.607979,41.650722],"type":"Point"}
}
