{
  "type": "Feature",
  "properties": {
    "addr:full": "250 Green St Gardner MA 01440",
    "addr:housenumber": "250",
    "addr:postcode": "01440",
    "addr:street": "Green St",
    "iso:country": "US",
    "ovtr:label": "Chair City Family Medicine, 250 Green St Gardner MA US",
    "ovtr:similarity": 2.101457118988037,
    "sg:address": "250 Green St",
    "sg:city": "Gardner",
    "sg:classifiers": [
      {
        "category": "Health Services",
        "subcategory": "Doctor",
        "type": "Services"
      }
    ],
    "sg:phone": "+1 978 630 4455",
    "sg:postcode": "01440",
    "sg:province": "MA",
    "sg:tags": [
      "physician",
      "surgeon"
    ],
    "wof:name": "Chair City Family Medicine",
    "wof:placetype": "venue"
  },
  "geometry": {"coordinates":[-71.986496,42.587128],"type":"Point"}
}
