{
  "type": "Feature",
  "properties": {
    "addr:full": "315 Broadway Arlington MA 02474",
    "addr:housenumber": "315",
    "addr:postcode": "02474",
    "addr:street": "Broadway",
    "iso:country": "US",
    "sg:address": "315 Broadway",
    "sg:city": "Arlington",
    "sg:classifiers": [
      {
        "category": "Restaurant",
        "type": "Food \u0026 Drink"
      }
    ],
    "sg:menulink": "http://www.allmenus.com/ma/arlington/610-gemma/menu/",
    "sg:phone": "+1 781 648 8884",
    "sg:postcode": "02474",
    "sg:province": "MA",
    "sg:tags": [
      "sandwich",
      "burger",
      "american",
      "wrap",
      "italian",
      "pizza"
    ],
    "wof:name": "Gemma",
    "wof:placetype": "venue"
  },
  "geometry": {"coordinates":[-71.150225,42.41429],"type":"Point"}
}
