{
  "type": "Feature",
  "properties": {
    "iso:country":"US",
    "sg:address":"315 Broadway",
    "sg:city":"Arlington",
    "sg:classifiers":[
        {
            "category":"Restaurant",
            "type":"Food & Drink"
        }
    ],
    "sg:menulink":"http://www.allmenus.com/ma/arlington/610-gemma/menu/",
    "sg:phone":"+1 781 648 8884",
    "sg:postcode":"02474",
    "sg:province":"MA",
    "sg:tags":[
        "sandwich",
        "burger",
        "american",
        "wrap",
        "italian",
        "pizza"
    ],
    "wof:name":"Gemma",
    "wof:placetype":"venue"
},
  "geometry": {"coordinates":[-71.15022500000001,42.41429],"type":"Point"}
}