{
  "type": "Feature",
  "properties": {
    "iso:country":"US",
    "sg:address":"14 Sconticut Neck Rd",
    "sg:city":"Fairhaven",
    "sg:classifiers":[
        {
            "category":"Personal",
            "subcategory":"Tanning Parlor",
            "type":"Services"
        }
    ],
    "sg:phone":"+1 508 992 7247",
    "sg:postcode":"02719",
    "sg:province":"MA",
    "sg:tags":[
        "salon"
    ],
    "wof:name":"Caribbean Sun Tanning",
    "wof:placetype":"venue"
},
  "geometry": {"coordinates":[-70.881333,41.639446],"type":"Point"}
}