{
  "type": "Feature",
  "properties": {
    "iso:country":"US",
    "sg:address":"24 Ireland Rd",
    "sg:city":"Newton",
    "sg:classifiers":[
        {
            "category":"Health Services",
            "subcategory":"Health Practitioner",
            "type":"Services"
        }
    ],
    "sg:phone":"+1 617 244 8389",
    "sg:postcode":"02459",
    "sg:province":"MA",
    "sg:tags":[
        "psychotherapist"
    ],
    "wof:name":"Karen Binder",
    "wof:placetype":"venue"
},
  "geometry": {"coordinates":[-71.186356,42.339763],"type":"Point"}
}