{
  "type": "Feature",
  "properties": {
    "addr:full":"27 Jackson Ter Newton MA 02458",
    "addr:housenumber":"27",
    "addr:postcode":"02458",
    "addr:street":"Jackson Ter",
    "iso:country":"US",
    "sg:address":"27 Jackson Ter",
    "sg:city":"Newton",
    "sg:classifiers":[
        {
            "category":"Building & Trades",
            "subcategory":"Landscaping Services",
            "type":"Services"
        }
    ],
    "sg:phone":"+1 617 527 4969",
    "sg:postcode":"02458",
    "sg:province":"MA",
    "wof:name":"Uberti Landscaping",
    "wof:placetype":"venue"
},
  "geometry": {"coordinates":[-71.19587199999999,42.356136],"type":"Point"}
}