{
  "type": "Feature",
  "properties": {
    "addr:full":"269 N Main St West Bridgewater MA 02379",
    "addr:housenumber":"269",
    "addr:postcode":"02379",
    "addr:street":"N Main St",
    "iso:country":"US",
    "sg:address":"269 N Main St",
    "sg:city":"West Bridgewater",
    "sg:classifiers":[
        {
            "category":"Restaurant",
            "type":"Food & Drink"
        }
    ],
    "sg:phone":"+1 508 580 0255",
    "sg:postcode":"02379",
    "sg:province":"MA",
    "wof:name":"Town Line Cafe",
    "wof:placetype":"venue"
},
  "geometry": {"coordinates":[-71.008488,42.030127],"type":"Point"}
}