{
  "type": "Feature",
  "properties": {
    "iso:country":"US",
    "sg:address":"9 Quail Run",
    "sg:city":"Wakefield",
    "sg:classifiers":[
        {
            "category":"Retail",
            "subcategory":"Repair Shop",
            "type":"Services"
        }
    ],
    "sg:phone":"+1   ",
    "sg:postcode":"01880",
    "sg:province":"MA",
    "wof:name":"Extreme Cleaning",
    "wof:placetype":"venue"
},
  "geometry": {"coordinates":[-71.05345699999999,42.494465],"type":"Point"}
}