{
  "type": "Feature",
  "properties": {
    "addr:full": "101 Ames St Lawrence MA 01841",
    "addr:housenumber": "101",
    "addr:postcode": "01841",
    "addr:street": "Ames St",
    "iso:country": "US",
    "sg:address": "101 Ames St",
    "sg:city": "Lawrence",
    "sg:classifiers": [
      {
        "category": "Shopping",
        "subcategory": "Discount \u0026 Variety Stores",
        "type": "Retail Goods"
      }
    ],
    "sg:phone": "+1 978 682 7222",
    "sg:postcode": "01841",
    "sg:province": "MA",
    "wof:name": "Tower Hill Variety",
    "wof:placetype": "venue"
  },
  "geometry": {"coordinates":[-71.182079,42.701002],"type":"Point"}
}
