{
  "type": "Feature",
  "properties": {
    "addr:full": "1518 N Main St Fall River MA 02720",
    "addr:housenumber": "1518",
    "addr:postcode": "02720",
    "addr:street": "N Main St",
    "iso:country": "US",
    "ovtr:label": "Roger's Coney Island Hot Dogs, 1518 N Main St Fall River MA US",
    "ovtr:similarity": 1.8004740476608276,
    "sg:address": "1518 N Main St",
    "sg:city": "Fall River",
    "sg:classifiers": [
      {
        "category": "Restaurant",
        "type": "Food \u0026 Drink"
      }
    ],
    "sg:phone": "+1 508 678 9889",
    "sg:postcode": "02720",
    "sg:province": "MA",
    "wof:name": "Roger's Coney Island Hot Dogs",
    "wof:placetype": "venue"
  },
  "geometry": {"coordinates":[-71.145904,41.721107],"type":"Point"}
}
