{
  "type": "Feature",
  "properties": {
    "addr:full":"Quaker Rd North Falmouth MA 02556",
    "addr:postcode":"02556",
    "addr:street":"Quaker Rd North",
    "iso:country":"US",
    "sg:address":"Quaker Rd",
    "sg:city":"North Falmouth",
    "sg:classifiers":[
        {
            "category":"Recreation",
            "subcategory":"Water Park",
            "type":"Entertainment"
        }
    ],
    "sg:postcode":"02556",
    "sg:province":"MA",
    "sg:tags":[
        "beach"
    ],
    "wof:name":"Old Silver Beach",
    "wof:placetype":"venue"
},
  "geometry": {"coordinates":[-70.63223000000001,41.63374],"type":"Point"}
}