{
  "type": "Feature",
  "properties": {
    "addr:full":"719 S Franklin St Holbrook MA 02343",
    "addr:housenumber":"719",
    "addr:postcode":"02343",
    "addr:street":"S Franklin St",
    "iso:country":"US",
    "sg:address":"719 S Franklin St",
    "sg:city":"Holbrook",
    "sg:classifiers":[
        {
            "category":"Education",
            "subcategory":"School",
            "type":"Public Place"
        }
    ],
    "sg:phone":"+1 781 767 0211",
    "sg:postcode":"02343",
    "sg:province":"MA",
    "sg:website":"www.holbrook.k12.ma.us",
    "wof:name":"South Elementary School",
    "wof:placetype":"venue"
},
  "geometry": {"coordinates":[-71.008788,42.129387],"type":"Point"}
}