{
  "type": "Feature",
  "properties": {
    "addr:full":"23 Grove St Kingston MA 02364",
    "addr:housenumber":"23",
    "addr:postcode":"02364",
    "addr:street":"Grove St",
    "iso:country":"US",
    "sg:address":"23 Grove St",
    "sg:city":"Kingston",
    "sg:classifiers":[
        {
            "category":"Building & Trades",
            "subcategory":"Construction",
            "type":"Services"
        }
    ],
    "sg:phone":"+1   ",
    "sg:postcode":"02364",
    "sg:province":"MA",
    "sg:tags":[
        "hanging",
        "contractor"
    ],
    "wof:name":"Cjc Professional Painting",
    "wof:placetype":"venue"
},
  "geometry": {"coordinates":[-70.75379100000001,42.000401],"type":"Point"}
}