{
  "type": "Feature",
  "properties": {
    "addr:full":"1834 Centre St West Roxbury MA 02132",
    "addr:housenumber":"1834",
    "addr:postcode":"02132",
    "addr:street":"Centre St",
    "iso:country":"US",
    "sg:address":"1834 Centre St",
    "sg:city":"West Roxbury",
    "sg:classifiers":[
        {
            "category":"Sports & Exercise",
            "subcategory":"Bowling",
            "type":"Entertainment"
        }
    ],
    "sg:phone":"+1 617 323 7291",
    "sg:postcode":"02132",
    "sg:province":"MA",
    "sg:tags":[
        "alley"
    ],
    "wof:name":"Big League Bowling",
    "wof:placetype":"venue"
},
  "geometry": {"coordinates":[-71.154572,42.286203],"type":"Point"}
}