{
  "type": "Feature",
  "properties": {
    "addr:full":"625 Bedford St East Bridgewater MA 02333",
    "addr:housenumber":"625",
    "addr:postcode":"02333",
    "addr:street":"Bedford St",
    "iso:country":"US",
    "sg:address":"625 Bedford St",
    "sg:city":"East Bridgewater",
    "sg:classifiers":[
        {
            "category":"Home & Garden",
            "subcategory":"Building Materials",
            "type":"Retail Goods"
        }
    ],
    "sg:phone":"+1   ",
    "sg:postcode":"02333",
    "sg:province":"MA",
    "sg:tags":[
        "windows"
    ],
    "wof:name":"Evergreen Window Company The",
    "wof:placetype":"venue"
},
  "geometry": {"coordinates":[-70.961174,42.015498],"type":"Point"}
}