{
  "type": "Feature",
  "properties": {
    "addr:full":"221 Boston Post Rd W Marlborough MA 01752",
    "addr:housenumber":"221",
    "addr:postcode":"01752",
    "addr:street":"Boston Post Rd W",
    "iso:country":"US",
    "sg:address":"221 Boston Post Rd W",
    "sg:city":"Marlborough",
    "sg:classifiers":[
        {
            "category":"Health Services",
            "subcategory":"Health Practitioner",
            "type":"Services"
        }
    ],
    "sg:phone":"+1 508 460 9633",
    "sg:postcode":"01752",
    "sg:province":"MA",
    "sg:tags":[
        "psychotherapist"
    ],
    "wof:name":"Mental Health Affiliates",
    "wof:placetype":"venue"
},
  "geometry": {"coordinates":[-71.59123599999999,42.33844],"type":"Point"}
}