{
  "type": "Feature",
  "properties": {
    "iso:country":"US",
    "sg:address":"181 Canal St",
    "sg:city":"Lawrence",
    "sg:classifiers":[
        {
            "category":"Wholesale",
            "subcategory":"Groceries",
            "type":"Manufacturing & Wholesale Goods"
        }
    ],
    "sg:phone":"+1 978 683 2873",
    "sg:postcode":"01840",
    "sg:province":"MA",
    "sg:tags":[
        "confectionery",
        "candy"
    ],
    "wof:name":"Metropolis Fine Confections",
    "wof:placetype":"venue"
},
  "geometry": {"coordinates":[-71.154697,42.70655],"type":"Point"}
}