{
  "type": "Feature",
  "properties": {
    "addr:full":"Children's Museum 300 Congress Street Boston MA 02210",
    "addr:housenumber":"300",
    "addr:postcode":"02210",
    "addr:street":"Congress Street",
    "iso:country":"US",
    "sg:address":"Children's Museum 300 Congress Street",
    "sg:city":"Boston",
    "sg:classifiers":[
        {
            "category":"Fast Food",
            "type":"Food & Drink"
        },
        {
            "category":"Coffee & Tea",
            "type":"Food & Drink"
        },
        {
            "category":"Restaurant",
            "type":"Food & Drink"
        },
        {
            "category":"Bakery",
            "type":"Food & Drink"
        },
        {
            "category":"Food & Beverages",
            "subcategory":"Groceries & Convenience Stores",
            "type":"Retail Goods"
        }
    ],
    "sg:phone":"+1 617 542 0412",
    "sg:postcode":"02210",
    "sg:province":"MA",
    "sg:tags":[
        "shop",
        "american",
        "sandwich",
        "espresso",
        "take"
    ],
    "sg:website":"www.aubonpain.com/",
    "wof:name":"Au Bon Pain",
    "wof:placetype":"venue"
},
  "geometry": {"coordinates":[-71.050032,42.351591],"type":"Point"}
}