{
  "type": "Feature",
  "properties": {
    "addr:full": "Children's Museum 300 Congress Street Boston MA 02210",
    "addr:housenumber": "300",
    "addr:postcode": "02210",
    "addr:street": "Congress Street",
    "iso:country": "US",
    "sg:address": "Children's Museum 300 Congress Street",
    "sg:city": "Boston",
    "sg:classifiers": [
      {
        "category": "Fast Food",
        "type": "Food \u0026 Drink"
      },
      {
        "category": "Coffee \u0026 Tea",
        "type": "Food \u0026 Drink"
      },
      {
        "category": "Restaurant",
        "type": "Food \u0026 Drink"
      },
      {
        "category": "Bakery",
        "type": "Food \u0026 Drink"
      },
      {
        "category": "Food \u0026 Beverages",
        "subcategory": "Groceries \u0026 Convenience Stores",
        "type": "Retail Goods"
      }
    ],
    "sg:phone": "+1 617 542 0412",
    "sg:postcode": "02210",
    "sg:province": "MA",
    "sg:tags": [
      "shop",
      "american",
      "sandwich",
      "espresso",
      "take"
    ],
    "sg:website": "www.aubonpain.com/",
    "wof:name": "Au Bon Pain",
    "wof:placetype": "venue"
  },
  "geometry": {"coordinates":[-71.050032,42.351591],"type":"Point"}
}
