{
  "type": "Feature",
  "properties": {
    "iso:country":"US",
    "sg:address":"734 Adams St",
    "sg:city":"Holliston",
    "sg:classifiers":[
        {
            "category":"Recreation",
            "type":"Entertainment"
        }
    ],
    "sg:phone":"+1 508 429 7154",
    "sg:postcode":"01746",
    "sg:province":"MA",
    "sg:tags":[
        "riding",
        "academy"
    ],
    "wof:name":"Beaver Brook Farm",
    "wof:placetype":"venue"
},
  "geometry": {"coordinates":[-71.490793,42.188651],"type":"Point"}
}