{
  "type": "Feature",
  "properties": {
    "addr:full":"1866 Somerset Ave Dighton MA 02715",
    "addr:housenumber":"1866",
    "addr:postcode":"02715",
    "addr:street":"Somerset Ave",
    "iso:country":"US",
    "sg:address":"1866 Somerset Ave",
    "sg:city":"Dighton",
    "sg:classifiers":[
        {
            "category":"Autos & Motor Vehicles",
            "subcategory":"Fuel & Gas Station",
            "type":"Retail Goods"
        }
    ],
    "sg:phone":"+1 508 669 6512",
    "sg:postcode":"02715",
    "sg:province":"MA",
    "sg:tags":[
        "oil"
    ],
    "wof:name":"Value Gas Co Inc",
    "wof:placetype":"venue"
},
  "geometry": {"coordinates":[-71.119658,41.816245],"type":"Point"}
}