{
  "type": "Feature",
  "properties": {
    "iso:country":"US",
    "sg:address":"121 South St",
    "sg:city":"Plainville",
    "sg:classifiers":[
        {
            "category":"Restaurant",
            "type":"Food & Drink"
        }
    ],
    "sg:phone":"+1 508 695 7036",
    "sg:postcode":"02762",
    "sg:province":"MA",
    "wof:name":"Don's Diner Inc",
    "wof:placetype":"venue"
},
  "geometry": {"coordinates":[-71.33591300000001,42.00498],"type":"Point"}
}