{
  "type": "Feature",
  "properties": {
    "addr:full": "121 South St Plainville MA 02762",
    "addr:housenumber": "121",
    "addr:postcode": "02762",
    "addr:street": "South St",
    "iso:country": "US",
    "ovtr:label": "Don's Diner Inc, 121 South St Plainville MA US",
    "ovtr:similarity": 2.2119429111480713,
    "sg:address": "121 South St",
    "sg:city": "Plainville",
    "sg:classifiers": [
      {
        "category": "Restaurant",
        "type": "Food \u0026 Drink"
      }
    ],
    "sg:phone": "+1 508 695 7036",
    "sg:postcode": "02762",
    "sg:province": "MA",
    "wof:name": "Don's Diner Inc",
    "wof:placetype": "venue"
  },
  "geometry": {"coordinates":[-71.335913,42.00498],"type":"Point"}
}
