{
  "type": "Feature",
  "properties": {
    "iso:country":"US",
    "sg:address":"16 Herrick Dr",
    "sg:city":"Ipswich",
    "sg:classifiers":[
        {
            "category":"Professional",
            "subcategory":"Management & Consulting",
            "type":"Services"
        }
    ],
    "sg:phone":"+1   ",
    "sg:postcode":"01938",
    "sg:province":"MA",
    "sg:tags":[
        "retail",
        "direct",
        "sales"
    ],
    "wof:name":"Sandra J Hanwell Avon Rep",
    "wof:placetype":"venue"
},
  "geometry": {"coordinates":[-70.935918,42.679324],"type":"Point"}
}