{
  "type": "Feature",
  "properties": {
    "addr:full": "8 Linden St Hopkinton MA 01748",
    "addr:housenumber": "8",
    "addr:postcode": "01748",
    "addr:street": "Linden St",
    "iso:country": "US",
    "sg:address": "8 Linden St",
    "sg:city": "Hopkinton",
    "sg:classifiers": [
      {
        "category": "Building \u0026 Trades",
        "subcategory": "Electrical",
        "type": "Services"
      }
    ],
    "sg:phone": "+1   ",
    "sg:postcode": "01748",
    "sg:province": "MA",
    "sg:tags": [
      "electrical",
      "contractor"
    ],
    "wof:name": "DC Electric",
    "wof:placetype": "venue"
  },
  "geometry": {"coordinates":[-71.498611,42.234414],"type":"Point"}
}
