{
  "type": "Feature",
  "properties": {
    "iso:country":"US",
    "sg:address":"50 Catherine St",
    "sg:city":"Dracut",
    "sg:classifiers":[
        {
            "category":"Building & Trades",
            "subcategory":"Construction",
            "type":"Services"
        }
    ],
    "sg:phone":"+1 978 674 0266",
    "sg:postcode":"01826",
    "sg:province":"MA",
    "sg:tags":[
        "roofing",
        "contractor"
    ],
    "wof:name":"Reliable Roofing",
    "wof:placetype":"venue"
},
  "geometry": {"coordinates":[-71.352306,42.684536],"type":"Point"}
}