{
  "type": "Feature",
  "properties": {
    "addr:full": "723 Blue Hill Ave Milton MA 02186",
    "addr:housenumber": "723",
    "addr:postcode": "02186",
    "addr:street": "Blue Hill Ave",
    "iso:country": "US",
    "sg:address": "723 Blue Hill Ave",
    "sg:city": "Milton",
    "sg:classifiers": [
      {
        "category": "Professional",
        "subcategory": "Management \u0026 Consulting",
        "type": "Services"
      }
    ],
    "sg:phone": "+1   ",
    "sg:postcode": "02186",
    "sg:province": "MA",
    "sg:tags": [
      "business"
    ],
    "wof:name": "Orasis Consulting Inc",
    "wof:placetype": "venue"
  },
  "geometry": {"coordinates":[-71.108447,42.239426],"type":"Point"}
}
