{
  "type": "Feature",
  "properties": {
    "iso:country":"US",
    "sg:address":"723 Blue Hill Ave",
    "sg:city":"Milton",
    "sg:classifiers":[
        {
            "category":"Professional",
            "subcategory":"Management & Consulting",
            "type":"Services"
        }
    ],
    "sg:phone":"+1   ",
    "sg:postcode":"02186",
    "sg:province":"MA",
    "sg:tags":[
        "business"
    ],
    "wof:name":"Orasis Consulting Inc",
    "wof:placetype":"venue"
},
  "geometry": {"coordinates":[-71.108447,42.239426],"type":"Point"}
}