{
  "type": "Feature",
  "properties": {
    "iso:country":"US",
    "sg:address":"106 Nauset St",
    "sg:city":"New Bedford",
    "sg:classifiers":[
        {
            "category":"Organizations",
            "subcategory":"Religious Organization",
            "type":"Services"
        }
    ],
    "sg:phone":"+1 508 992 2745",
    "sg:postcode":"02746",
    "sg:province":"MA",
    "sg:tags":[
        "church"
    ],
    "wof:name":"Greater New Bedford Baseball",
    "wof:placetype":"venue"
},
  "geometry": {"coordinates":[-70.9432,41.661671],"type":"Point"}
}