{
  "type": "Feature",
  "properties": {
    "addr:full":"353 Chestnut St Lynnfield MA 01940",
    "addr:housenumber":"353",
    "addr:postcode":"01940",
    "addr:street":"Chestnut St",
    "iso:country":"US",
    "sg:address":"353 Chestnut St",
    "sg:city":"Lynnfield",
    "sg:classifiers":[
        {
            "category":"Building & Trades",
            "subcategory":"Construction",
            "type":"Services"
        }
    ],
    "sg:phone":"+1 781 334 6232",
    "sg:postcode":"01940",
    "sg:province":"MA",
    "sg:tags":[
        "painter"
    ],
    "wof:name":"RLS Painting Co",
    "wof:placetype":"venue"
},
  "geometry": {"coordinates":[-71.062737,42.547305],"type":"Point"}
}