{
  "type": "Feature",
  "properties": {
    "addr:full": "42 Oakland St Newburyport MA 01950",
    "addr:housenumber": "42",
    "addr:postcode": "01950",
    "addr:street": "Oakland St",
    "iso:country": "US",
    "sg:address": "42 Oakland St",
    "sg:city": "Newburyport",
    "sg:classifiers": [
      {
        "category": "Professional",
        "subcategory": "Management \u0026 Consulting",
        "type": "Services"
      }
    ],
    "sg:phone": "+1   ",
    "sg:postcode": "01950",
    "sg:province": "MA",
    "sg:tags": [
      "business"
    ],
    "wof:name": "Ask On Consulting",
    "wof:placetype": "venue"
  },
  "geometry": {"coordinates":[-70.886187,42.816291],"type":"Point"}
}
