{
  "type": "Feature",
  "properties": {
    "iso:country":"US",
    "sg:address":"42 Oakland St",
    "sg:city":"Newburyport",
    "sg:classifiers":[
        {
            "category":"Professional",
            "subcategory":"Management & Consulting",
            "type":"Services"
        }
    ],
    "sg:phone":"+1   ",
    "sg:postcode":"01950",
    "sg:province":"MA",
    "sg:tags":[
        "business"
    ],
    "wof:name":"Ask On Consulting",
    "wof:placetype":"venue"
},
  "geometry": {"coordinates":[-70.88618700000001,42.816291],"type":"Point"}
}