{
  "type": "Feature",
  "properties": {
    "addr:full": "301 N Elm St Westfield MA 01085",
    "addr:housenumber": "301",
    "addr:postcode": "01085",
    "addr:street": "N Elm St",
    "iso:country": "US",
    "ovtr:label": "Greg's Auto Repair, 301 N Elm St Westfield MA US",
    "ovtr:similarity": 2.134061098098755,
    "sg:address": "301 N Elm St",
    "sg:city": "Westfield",
    "sg:classifiers": [
      {
        "category": "Retail",
        "subcategory": "Auto Repair",
        "type": "Services"
      }
    ],
    "sg:phone": "+1 413 562 9725",
    "sg:postcode": "01085",
    "sg:province": "MA",
    "sg:tags": [
      "repairing",
      "automobile"
    ],
    "wof:name": "Greg's Auto Repair",
    "wof:placetype": "venue"
  },
  "geometry": {"coordinates":[-72.736181,42.139117],"type":"Point"}
}
