{
  "type": "Feature",
  "properties": {
    "iso:country":"US",
    "sg:address":"46 Cedar St",
    "sg:city":"Taunton",
    "sg:classifiers":[
        {
            "category":"Sports & Exercise",
            "subcategory":"Sports Center",
            "type":"Entertainment"
        }
    ],
    "sg:phone":"+1 508 880 7833",
    "sg:postcode":"02780",
    "sg:province":"MA",
    "wof:name":"Cedar Swim Club Inc",
    "wof:placetype":"venue"
},
  "geometry": {"coordinates":[-71.08949699999999,41.905275],"type":"Point"}
}