{
  "type": "Feature",
  "properties": {
    "iso:country":"US",
    "sg:address":"1 Cutty Hunk Ave",
    "sg:city":"Vineyard Haven",
    "sg:classifiers":[
        {
            "category":"Professional",
            "type":"Services"
        }
    ],
    "sg:phone":"+1 508 696 8699",
    "sg:postcode":"02568",
    "sg:province":"MA",
    "wof:name":"Associated Preservation Svc",
    "wof:placetype":"venue"
},
  "geometry": {"coordinates":[-70.65257,41.46012],"type":"Point"}
}