{
  "type": "Feature",
  "properties": {
    "addr:full": "167 South St W Raynham MA 02767",
    "addr:housenumber": "167",
    "addr:postcode": "02767",
    "addr:street": "South St W",
    "iso:country": "US",
    "sg:address": "167 South St W",
    "sg:city": "Raynham",
    "sg:classifiers": [
      {
        "category": "Retail",
        "subcategory": "Auto Repair",
        "type": "Services"
      }
    ],
    "sg:phone": "+1   ",
    "sg:postcode": "02767",
    "sg:province": "MA",
    "sg:tags": [
      "automotive",
      "general"
    ],
    "wof:name": "Heberts Auto Service",
    "wof:placetype": "venue"
  },
  "geometry": {"coordinates":[-71.0622,41.906806],"type":"Point"}
}
