{
  "type": "Feature",
  "properties": {
    "iso:country":"US",
    "sg:address":"42 Middleboro Rd",
    "sg:city":"East Freetown",
    "sg:classifiers":[
        {
            "category":"Building & Trades",
            "subcategory":"Landscaping Services",
            "type":"Services"
        }
    ],
    "sg:phone":"+1 508 763 0255",
    "sg:postcode":"02717",
    "sg:province":"MA",
    "sg:tags":[
        "landscape",
        "contractor"
    ],
    "wof:name":"Stix N'Stones Landscape Svc",
    "wof:placetype":"venue"
},
  "geometry": {"coordinates":[-70.943609,41.75559],"type":"Point"}
}