{
  "type": "Feature",
  "properties": {
    "iso:country":"US",
    "sg:address":"84 Myrtle St",
    "sg:city":"Ashland",
    "sg:classifiers":[
        {
            "category":"Health Services",
            "subcategory":"Nursing And Care Facility",
            "type":"Services"
        }
    ],
    "sg:phone":"+1 508 881 1360",
    "sg:postcode":"01721",
    "sg:province":"MA",
    "sg:tags":[
        "home",
        "convalescent"
    ],
    "wof:name":"Mill Pond Rest Home",
    "wof:placetype":"venue"
},
  "geometry": {"coordinates":[-71.464198,42.266979],"type":"Point"}
}