{
  "type": "Feature",
  "properties": {
    "addr:full": "84 Myrtle St Ashland MA 01721",
    "addr:housenumber": "84",
    "addr:postcode": "01721",
    "addr:street": "Myrtle St",
    "iso:country": "US",
    "ovtr:label": "Mill Pond Rest Home, 84 Myrtle St Ashland MA US",
    "ovtr:similarity": 2.564229965209961,
    "sg:address": "84 Myrtle St",
    "sg:city": "Ashland",
    "sg:classifiers": [
      {
        "category": "Health Services",
        "subcategory": "Nursing And Care Facility",
        "type": "Services"
      }
    ],
    "sg:phone": "+1 508 881 1360",
    "sg:postcode": "01721",
    "sg:province": "MA",
    "sg:tags": [
      "home",
      "convalescent"
    ],
    "wof:name": "Mill Pond Rest Home",
    "wof:placetype": "venue"
  },
  "geometry": {"coordinates":[-71.464198,42.266979],"type":"Point"}
}
