{
  "type": "Feature",
  "properties": {
    "addr:full":"14 Pleasant St Gloucester MA 01930",
    "addr:housenumber":"14",
    "addr:postcode":"01930",
    "addr:street":"Pleasant St",
    "iso:country":"US",
    "sg:address":"14 Pleasant St",
    "sg:city":"Gloucester",
    "sg:classifiers":[
        {
            "category":"Professional",
            "subcategory":"Lawyer & Legal Services",
            "type":"Services"
        }
    ],
    "sg:phone":"+1 978 283 2850",
    "sg:postcode":"01930",
    "sg:province":"MA",
    "sg:tags":[
        "attorney"
    ],
    "wof:name":"Frontiero Law Office PC",
    "wof:placetype":"venue"
},
  "geometry": {"coordinates":[-70.661855,42.612963],"type":"Point"}
}