{
  "type": "Feature",
  "properties": {
    "addr:full": "124 Bowdoin St Boston MA 02108",
    "addr:housenumber": "124",
    "addr:postcode": "02108",
    "addr:street": "Bowdoin St",
    "iso:country": "US",
    "sg:address": "124 Bowdoin St",
    "sg:city": "Boston",
    "sg:classifiers": [
      {
        "category": "Personal",
        "subcategory": "Barber",
        "type": "Services"
      }
    ],
    "sg:phone": "+1 617 530 0404",
    "sg:postcode": "02108",
    "sg:province": "MA",
    "wof:name": "Capitol Barber Shop",
    "wof:placetype": "venue"
  },
  "geometry": {"coordinates":[-71.062855,42.358974],"type":"Point"}
}
