{
  "type": "Feature",
  "properties": {
    "iso:country":"US",
    "sg:address":"34 Sullivan Rd Ste 34",
    "sg:city":"North Billerica",
    "sg:classifiers":[
        {
            "category":"Building & Trades",
            "subcategory":"Construction",
            "type":"Services"
        }
    ],
    "sg:phone":"+1 978 667 4644",
    "sg:postcode":"01862",
    "sg:province":"MA",
    "sg:tags":[
        "contractor"
    ],
    "wof:name":"B & B Mechanical Service",
    "wof:placetype":"venue"
},
  "geometry": {"coordinates":[-71.32060199999999,42.563184],"type":"Point"}
}