{
  "type": "Feature",
  "properties": {
    "addr:full": "34 Sullivan Rd Ste 34 North Billerica MA 01862",
    "addr:housenumber": "34",
    "addr:postcode": "01862",
    "addr:street": "Sullivan Rd Ste 34 North",
    "iso:country": "US",
    "sg:address": "34 Sullivan Rd Ste 34",
    "sg:city": "North Billerica",
    "sg:classifiers": [
      {
        "category": "Building \u0026 Trades",
        "subcategory": "Construction",
        "type": "Services"
      }
    ],
    "sg:phone": "+1 978 667 4644",
    "sg:postcode": "01862",
    "sg:province": "MA",
    "sg:tags": [
      "contractor"
    ],
    "wof:name": "B \u0026 B Mechanical Service",
    "wof:placetype": "venue"
  },
  "geometry": {"coordinates":[-71.320602,42.563184],"type":"Point"}
}
