{
  "type": "Feature",
  "properties": {
    "iso:country":"US",
    "sg:address":"29 Wendell Ave",
    "sg:city":"Pittsfield",
    "sg:classifiers":[
        {
            "category":"Banks & Credit Unions",
            "subcategory":"Investment Brokerage",
            "type":"Services"
        }
    ],
    "sg:phone":"+1   ",
    "sg:postcode":"01201",
    "sg:province":"MA",
    "sg:tags":[
        "security",
        "dealer"
    ],
    "wof:name":"First Montauk",
    "wof:placetype":"venue"
},
  "geometry": {"coordinates":[-73.252484,42.445992],"type":"Point"}
}