{
  "type": "Feature",
  "properties": {
    "iso:country":"US",
    "sg:address":"119 Braintree St",
    "sg:city":"Allston",
    "sg:classifiers":[
        {
            "category":"Professional",
            "subcategory":"Business Services",
            "type":"Services"
        }
    ],
    "sg:phone":"+1 617 782 8100",
    "sg:postcode":"02134",
    "sg:province":"MA",
    "sg:tags":[
        "cinema"
    ],
    "wof:name":"Boston Comedy & Movie Festival",
    "wof:placetype":"venue"
},
  "geometry": {"coordinates":[-71.136703,42.356499],"type":"Point"}
}