{
  "type": "Feature",
  "properties": {
    "addr:full": "119 Braintree St Allston MA 02134",
    "addr:housenumber": "119",
    "addr:postcode": "02134",
    "addr:street": "Braintree St",
    "iso:country": "US",
    "sg:address": "119 Braintree St",
    "sg:city": "Allston",
    "sg:classifiers": [
      {
        "category": "Professional",
        "subcategory": "Business Services",
        "type": "Services"
      }
    ],
    "sg:phone": "+1 617 782 8100",
    "sg:postcode": "02134",
    "sg:province": "MA",
    "sg:tags": [
      "cinema"
    ],
    "wof:name": "Boston Comedy \u0026 Movie Festival",
    "wof:placetype": "venue"
  },
  "geometry": {"coordinates":[-71.136703,42.356499],"type":"Point"}
}
