{
  "type": "Feature",
  "properties": {
    "iso:country":"US",
    "sg:address":"12 Thornton St",
    "sg:city":"Attleboro",
    "sg:classifiers":[
        {
            "category":"Building & Trades",
            "subcategory":"Construction",
            "type":"Services"
        }
    ],
    "sg:phone":"+1 508 222 0055",
    "sg:postcode":"02703",
    "sg:province":"MA",
    "sg:tags":[
        "contractor"
    ],
    "wof:name":"Highview Realty Trust - CLOSED",
    "wof:placetype":"venue"
},
  "geometry": {"coordinates":[-71.28679700000001,41.922901],"type":"Point"}
}