{
  "type": "Feature",
  "properties": {
    "addr:full": "25 Elm St New Bedford MA 02740",
    "addr:housenumber": "25",
    "addr:postcode": "02740",
    "addr:street": "Elm St",
    "iso:country": "US",
    "sg:address": "25 Elm St",
    "sg:city": "New Bedford",
    "sg:classifiers": [
      {
        "category": "Manufacturing",
        "subcategory": "Printing",
        "type": "Manufacturing \u0026 Wholesale Goods"
      }
    ],
    "sg:phone": "+1 508 997 7411",
    "sg:postcode": "02740",
    "sg:province": "MA",
    "sg:tags": [
      "newspaper"
    ],
    "sg:website": "www.s-t.com",
    "wof:name": "Standard-Times",
    "wof:placetype": "venue"
  },
  "geometry": {"coordinates":[-70.923631,41.636635],"type":"Point"}
}
