{
  "type": "Feature",
  "properties": {
    "addr:full": "62 Woodside Ave Winthrop MA 02152",
    "addr:housenumber": "62",
    "addr:postcode": "02152",
    "addr:street": "Woodside Ave",
    "iso:country": "US",
    "ovtr:label": "Tokyo Hair \u0026 Nails, 62 Woodside Ave Winthrop MA US",
    "ovtr:similarity": 2.8391189575195312,
    "sg:address": "62 Woodside Ave",
    "sg:city": "Winthrop",
    "sg:classifiers": [
      {
        "category": "Personal",
        "subcategory": "Nail Salon",
        "type": "Services"
      }
    ],
    "sg:phone": "+1 617 846 6529",
    "sg:postcode": "02152",
    "sg:province": "MA",
    "wof:name": "Tokyo Hair and Nails",
    "wof:placetype": "venue"
  },
  "geometry": {"coordinates":[-70.986501,42.374431],"type":"Point"}
}
