{
  "type": "Feature",
  "properties": {
    "iso:country":"US",
    "sg:address":"62 Woodside Ave",
    "sg:city":"Winthrop",
    "sg:classifiers":[
        {
            "category":"Personal",
            "subcategory":"Nail Salon",
            "type":"Services"
        }
    ],
    "sg:phone":"+1 617 846 6529",
    "sg:postcode":"02152",
    "sg:province":"MA",
    "wof:name":"Tokyo Hair and Nails",
    "wof:placetype":"venue"
},
  "geometry": {"coordinates":[-70.986501,42.374431],"type":"Point"}
}