{
  "type": "Feature",
  "properties": {
    "addr:full":"452 High St Medford MA 02155",
    "addr:housenumber":"452",
    "addr:postcode":"02155",
    "addr:street":"High St",
    "iso:country":"US",
    "sg:address":"452 High St",
    "sg:city":"Medford",
    "sg:classifiers":[
        {
            "category":"Wholesale",
            "subcategory":"Machinery & Supplies",
            "type":"Manufacturing & Wholesale Goods"
        }
    ],
    "sg:phone":"+1 781 395 2211",
    "sg:postcode":"02155",
    "sg:province":"MA",
    "sg:tags":[
        "pottery",
        "equipment"
    ],
    "wof:name":"Barn Studio Pottery",
    "wof:placetype":"venue"
},
  "geometry": {"coordinates":[-71.13217299999999,42.421067],"type":"Point"}
}