{
  "type": "Feature",
  "properties": {
    "iso:country":"US",
    "sg:address":"3 Bedford Rd",
    "sg:city":"Lincoln",
    "sg:classifiers":[
        {
            "category":"Education",
            "subcategory":"Library",
            "type":"Public Place"
        }
    ],
    "sg:phone":"+1 781 259 8465",
    "sg:postcode":"01773",
    "sg:province":"MA",
    "sg:website":"www.lincolnpl.org",
    "wof:name":"Lincoln Public Library",
    "wof:placetype":"venue"
},
  "geometry": {"coordinates":[-71.303229,42.426369],"type":"Point"}
}