{
  "type": "Feature",
  "properties": {
    "iso:country":"US",
    "sg:address":"119 Ministerial Dr",
    "sg:city":"Concord",
    "sg:classifiers":[
        {
            "category":"Professional",
            "subcategory":"Computer Services",
            "type":"Services"
        }
    ],
    "sg:phone":"+1   ",
    "sg:postcode":"01742",
    "sg:province":"MA",
    "sg:tags":[
        "related"
    ],
    "wof:name":"Demo Ware Assoc",
    "wof:placetype":"venue"
},
  "geometry": {"coordinates":[-71.40105800000001,42.448048],"type":"Point"}
}