{
  "type": "Feature",
  "properties": {
    "addr:full": "119 Ministerial Dr Concord MA 01742",
    "addr:housenumber": "119",
    "addr:postcode": "01742",
    "addr:street": "Ministerial Dr",
    "iso:country": "US",
    "sg:address": "119 Ministerial Dr",
    "sg:city": "Concord",
    "sg:classifiers": [
      {
        "category": "Professional",
        "subcategory": "Computer Services",
        "type": "Services"
      }
    ],
    "sg:phone": "+1   ",
    "sg:postcode": "01742",
    "sg:province": "MA",
    "sg:tags": [
      "related"
    ],
    "wof:name": "Demo Ware Assoc",
    "wof:placetype": "venue"
  },
  "geometry": {"coordinates":[-71.401058,42.448048],"type":"Point"}
}
