{
  "type": "Feature",
  "properties": {
    "addr:full": "80 Harvard Way Boston MA 02163",
    "addr:housenumber": "80",
    "addr:postcode": "02163",
    "addr:street": "Harvard Way",
    "iso:country": "US",
    "sg:address": "80 Harvard Way",
    "sg:city": "Boston",
    "sg:classifiers": [
      {
        "category": "Professional",
        "type": "Services"
      }
    ],
    "sg:phone": "+1 617 864 1865",
    "sg:postcode": "02163",
    "sg:province": "MA",
    "sg:tags": [
      "establishment"
    ],
    "wof:name": "Mc Cusker Gill Inc",
    "wof:placetype": "venue"
  },
  "geometry": {"coordinates":[-71.125122,42.366237],"type":"Point"}
}
