{
  "type": "Feature",
  "properties": {
    "iso:country":"US",
    "sg:address":"1714 Granville Rd",
    "sg:city":"Westfield",
    "sg:classifiers":[
        {
            "category":"Building & Trades",
            "subcategory":"Landscaping Services",
            "type":"Services"
        }
    ],
    "sg:phone":"+1 413 568 3340",
    "sg:postcode":"01085",
    "sg:province":"MA",
    "sg:tags":[
        "landscape",
        "contractor"
    ],
    "wof:name":"Cobble Mountain Landscaping",
    "wof:placetype":"venue"
},
  "geometry": {"coordinates":[-72.841195,42.115226],"type":"Point"}
}