{
  "type": "Feature",
  "properties": {
    "addr:full":"1361 Memorial Dr Chicopee MA 01020",
    "addr:housenumber":"1361",
    "addr:postcode":"01020",
    "addr:street":"Memorial Dr",
    "iso:country":"US",
    "sg:address":"1361 Memorial Dr",
    "sg:city":"Chicopee",
    "sg:classifiers":[
        {
            "category":"Retail",
            "subcategory":"Veterinary Services",
            "type":"Services"
        }
    ],
    "sg:phone":"+1 413 535 1777",
    "sg:postcode":"01020",
    "sg:province":"MA",
    "sg:tags":[
        "veterinarian"
    ],
    "wof:name":"Westover Animal Clinic",
    "wof:placetype":"venue"
},
  "geometry": {"coordinates":[-72.574082,42.19638],"type":"Point"}
}