{
  "type": "Feature",
  "properties": {
    "addr:full": "1 E Emerson St Melrose MA 02176",
    "addr:housenumber": "1",
    "addr:postcode": "02176",
    "addr:street": "E Emerson St",
    "iso:country": "US",
    "sg:address": "1 E Emerson St",
    "sg:city": "Melrose",
    "sg:classifiers": [
      {
        "category": "Health Services",
        "subcategory": "Doctor",
        "type": "Services"
      }
    ],
    "sg:phone": "+1 781 665 6102",
    "sg:postcode": "02176",
    "sg:province": "MA",
    "sg:tags": [
      "physician",
      "surgeon"
    ],
    "wof:name": "American Society-Abdmnl Srgns",
    "wof:placetype": "venue"
  },
  "geometry": {"coordinates":[-71.06172,42.458684],"type":"Point"}
}
