{
  "type": "Feature",
  "properties": {
    "addr:full": "32 Lyman St Westborough MA 01581",
    "addr:housenumber": "32",
    "addr:postcode": "01581",
    "addr:street": "Lyman St",
    "iso:country": "US",
    "sg:address": "32 Lyman St",
    "sg:city": "Westborough",
    "sg:classifiers": [
      {
        "category": "Banks \u0026 Credit Unions",
        "subcategory": "Bank",
        "type": "Services"
      }
    ],
    "sg:phone": "+1 508 366 0762",
    "sg:postcode": "01581",
    "sg:province": "MA",
    "wof:name": "Citizens Bank",
    "wof:placetype": "venue"
  },
  "geometry": {"coordinates":[-71.607077,42.282283],"type":"Point"}
}
