{
  "type": "Feature",
  "properties": {
    "addr:full":"260 Arlington St Acton MA 01720",
    "addr:housenumber":"260",
    "addr:postcode":"01720",
    "addr:street":"Arlington St",
    "iso:country":"US",
    "sg:address":"260 Arlington St",
    "sg:city":"Acton",
    "sg:classifiers":[
        {
            "category":"Professional",
            "subcategory":"Business Services",
            "type":"Services"
        }
    ],
    "sg:phone":"+1   ",
    "sg:postcode":"01720",
    "sg:province":"MA",
    "sg:tags":[
        "datum"
    ],
    "wof:name":"C S I",
    "wof:placetype":"venue"
},
  "geometry": {"coordinates":[-71.473822,42.476814],"type":"Point"}
}