{
  "type": "Feature",
  "properties": {
    "addr:full":"42 Carey Ave Watertown MA 02472",
    "addr:housenumber":"42",
    "addr:postcode":"02472",
    "addr:street":"Carey Ave",
    "iso:country":"US",
    "sg:address":"42 Carey Ave",
    "sg:city":"Watertown",
    "sg:classifiers":[
        {
            "category":"Home & Garden",
            "subcategory":"Garden Supply",
            "type":"Retail Goods"
        }
    ],
    "sg:phone":"+1 781 862 5161",
    "sg:postcode":"02472",
    "sg:province":"MA",
    "sg:tags":[
        "equipment",
        "snow",
        "removal"
    ],
    "wof:name":"Bob's Power Equipment",
    "wof:placetype":"venue"
},
  "geometry": {"coordinates":[-71.194552,42.376279],"type":"Point"}
}