{
  "type": "Feature",
  "properties": {
    "addr:full": "73 Main St Charlestown MA 02129",
    "addr:housenumber": "73",
    "addr:postcode": "02129",
    "addr:street": "Main St",
    "iso:country": "US",
    "sg:address": "73 Main St",
    "sg:city": "Charlestown",
    "sg:classifiers": [
      {
        "category": "Bars \u0026 Pubs",
        "subcategory": "Lounge",
        "type": "Food \u0026 Drink"
      },
      {
        "category": "Bars \u0026 Pubs",
        "subcategory": "Hookah Bar",
        "type": "Food \u0026 Drink"
      },
      {
        "category": "Retail",
        "subcategory": "Event Space",
        "type": "Services"
      }
    ],
    "sg:phone": "+1 617 242 6010",
    "sg:postcode": "02129",
    "sg:province": "MA",
    "sg:tags": [
      "venue"
    ],
    "wof:name": "Koullshi",
    "wof:placetype": "venue"
  },
  "geometry": {"coordinates":[-71.062767,42.373827],"type":"Point"}
}
