{
  "type": "Feature",
  "properties": {
    "iso:country":"US",
    "sg:address":"73 Main St",
    "sg:city":"Charlestown",
    "sg:classifiers":[
        {
            "category":"Bars & Pubs",
            "subcategory":"Lounge",
            "type":"Food & Drink"
        },
        {
            "category":"Bars & Pubs",
            "subcategory":"Hookah Bar",
            "type":"Food & Drink"
        },
        {
            "category":"Retail",
            "subcategory":"Event Space",
            "type":"Services"
        }
    ],
    "sg:phone":"+1 617 242 6010",
    "sg:postcode":"02129",
    "sg:province":"MA",
    "sg:tags":[
        "venue"
    ],
    "wof:name":"Koullshi",
    "wof:placetype":"venue"
},
  "geometry": {"coordinates":[-71.06276699999999,42.373827],"type":"Point"}
}