{
  "type": "Feature",
  "properties": {
    "addr:full": "114 Pleasant St Marblehead MA 01945",
    "addr:housenumber": "114",
    "addr:postcode": "01945",
    "addr:street": "Pleasant St",
    "iso:country": "US",
    "sg:address": "114 Pleasant St",
    "sg:city": "Marblehead",
    "sg:classifiers": [
      {
        "category": "Restaurant",
        "type": "Food \u0026 Drink"
      }
    ],
    "sg:phone": "+1 781 631 8200",
    "sg:postcode": "01945",
    "sg:province": "MA",
    "sg:tags": [
      "grill",
      "bar"
    ],
    "wof:name": "Hooked Seafood \u0026 Grill",
    "wof:placetype": "venue"
  },
  "geometry": {"coordinates":[-70.856901,42.501688],"type":"Point"}
}
