{
  "type": "Feature",
  "properties": {
    "addr:full":"27 Colchester St Brookline MA 02446",
    "addr:housenumber":"27",
    "addr:postcode":"02446",
    "addr:street":"Colchester St",
    "iso:country":"US",
    "sg:address":"27 Colchester St",
    "sg:city":"Brookline",
    "sg:classifiers":[
        {
            "category":"Professional",
            "subcategory":"Research",
            "type":"Services"
        }
    ],
    "sg:phone":"+1 617 277 1900",
    "sg:postcode":"02446",
    "sg:province":"MA",
    "sg:tags":[
        "foundation",
        "philanthropic"
    ],
    "sg:website":"www.vinstitute.org",
    "wof:name":"Visionary Institute",
    "wof:placetype":"venue"
},
  "geometry": {"coordinates":[-71.108566,42.343221],"type":"Point"}
}