{
  "type": "Feature",
  "properties": {
    "addr:full":"40 Lake St Somerville MA 02143",
    "addr:housenumber":"40",
    "addr:postcode":"02143",
    "addr:street":"Lake St",
    "iso:country":"US",
    "sg:address":"40 Lake St",
    "sg:city":"Somerville",
    "sg:classifiers":[
        {
            "category":"Wholesale",
            "subcategory":"Machinery & Supplies",
            "type":"Manufacturing & Wholesale Goods"
        }
    ],
    "sg:phone":"+1 617 666 9090",
    "sg:postcode":"02143",
    "sg:province":"MA",
    "sg:tags":[
        "equipment",
        "industrial"
    ],
    "sg:website":"www.hdchasen.com",
    "wof:name":"H D Chasen & Co",
    "wof:placetype":"venue"
},
  "geometry": {"coordinates":[-71.099243,42.380057],"type":"Point"}
}