{
  "type": "Feature",
  "properties": {
    "addr:full": "Online Commerce Group  MS 740 Framingham MA 01701-8863",
    "addr:housenumber": "740",
    "addr:postcode": "01701-8863",
    "iso:country": "US",
    "sg:address": "Online Commerce Group  MS 740",
    "sg:city": "Framingham",
    "sg:classifiers": [
      {
        "category": "Professional",
        "subcategory": "Computer Services",
        "type": "Services"
      }
    ],
    "sg:phone": "+1 508 879 7330",
    "sg:postcode": "01701-8863",
    "sg:province": "MA",
    "sg:website": "http://global.bose.com/index.html",
    "wof:name": "Bose",
    "wof:placetype": "venue"
  },
  "geometry": {"coordinates":[-71.480026,42.149308],"type":"Point"}
}
