{
  "type": "Feature",
  "properties": {
    "iso:country":"US",
    "sg:address":"12 Irish Ln",
    "sg:city":"Rutland",
    "sg:classifiers":[
        {
            "category":"Professional",
            "type":"Services"
        }
    ],
    "sg:phone":"+1 508 886 4790",
    "sg:postcode":"01543",
    "sg:province":"MA",
    "sg:tags":[
        "establishment"
    ],
    "wof:name":"Northern Estates",
    "wof:placetype":"venue"
},
  "geometry": {"coordinates":[-71.97304,42.342017],"type":"Point"}
}