{
  "type": "Feature",
  "properties": {
    "addr:full": "366 King St Northampton MA 01060",
    "addr:housenumber": "366",
    "addr:postcode": "01060",
    "addr:street": "King St",
    "iso:country": "US",
    "ovtr:label": "CVS Pharmacy, 366 King St Northampton MA US",
    "ovtr:similarity": 3.9372520446777344,
    "sg:address": "366 King St",
    "sg:city": "Northampton",
    "sg:classifiers": [
      {
        "category": "Shopping",
        "subcategory": "Pharmacy",
        "type": "Retail Goods"
      }
    ],
    "sg:phone": "+1 413 586 8315",
    "sg:postcode": "01060",
    "sg:province": "MA",
    "sg:tags": [
      "aid",
      "supply",
      "first"
    ],
    "sg:website": "http://www.cvs.com",
    "wof:name": "CVS/pharmacy",
    "wof:placetype": "venue"
  },
  "geometry": {"coordinates":[-72.636551,42.335953],"type":"Point"}
}
