{
  "type": "Feature",
  "properties": {
    "addr:full": "839 Albany St Roxbury MA 02119",
    "addr:housenumber": "839",
    "addr:postcode": "02119",
    "addr:street": "Albany St",
    "iso:country": "US",
    "sg:address": "839 Albany St",
    "sg:city": "Roxbury",
    "sg:classifiers": [
      {
        "category": "Shopping",
        "subcategory": "Florist",
        "type": "Retail Goods"
      }
    ],
    "sg:phone": "+1 617 442 0900",
    "sg:postcode": "02119",
    "sg:province": "MA",
    "wof:name": "Blueguava Design Group",
    "wof:placetype": "venue"
  },
  "geometry": {"coordinates":[-71.075761,42.3321],"type":"Point"}
}
