{
  "type": "Feature",
  "properties": {
    "addr:full": "75 Oxford Ave Haverhill MA 01835",
    "addr:housenumber": "75",
    "addr:postcode": "01835",
    "addr:street": "Oxford Ave",
    "iso:country": "US",
    "sg:address": "75 Oxford Ave",
    "sg:city": "Haverhill",
    "sg:classifiers": [
      {
        "category": "Building \u0026 Trades",
        "subcategory": "Construction",
        "type": "Services"
      }
    ],
    "sg:phone": "+1 978 374 8313",
    "sg:postcode": "01835",
    "sg:province": "MA",
    "sg:tags": [
      "general",
      "contractor"
    ],
    "wof:name": "M \u0026 M Construction Co",
    "wof:placetype": "venue"
  },
  "geometry": {"coordinates":[-71.106577,42.748505],"type":"Point"}
}
