{
  "type": "Feature",
  "properties": {
    "addr:full": "800 Broadway Ste 13 Haverhill MA 01832",
    "addr:housenumber": "800;13",
    "addr:postcode": "01832",
    "addr:street": "Broadway Ste",
    "iso:country": "US",
    "sg:address": "800 Broadway Ste 13",
    "sg:city": "Haverhill",
    "sg:classifiers": [
      {
        "category": "Shopping",
        "subcategory": "Jewelry",
        "type": "Retail Goods"
      },
      {
        "category": "Manufacturing",
        "subcategory": "Jewelry",
        "type": "Manufacturing \u0026 Wholesale Goods"
      }
    ],
    "sg:phone": "+1 978 374 8675",
    "sg:postcode": "01832",
    "sg:province": "MA",
    "sg:tags": [
      "stone",
      "designer",
      "semi-precious",
      "precious",
      "jeweler"
    ],
    "wof:name": "Gold Leaf",
    "wof:placetype": "venue"
  },
  "geometry": {"coordinates":[-71.13372,42.78706],"type":"Point"}
}
