{
  "type": "Feature",
  "properties": {
    "addr:full": "53 Freeport St Dorchester MA 02122",
    "addr:housenumber": "53",
    "addr:postcode": "02122",
    "addr:street": "Freeport St",
    "iso:country": "US",
    "sg:address": "53 Freeport St",
    "sg:city": "Dorchester",
    "sg:classifiers": [
      {
        "category": "Building \u0026 Trades",
        "subcategory": "Construction",
        "type": "Services"
      }
    ],
    "sg:phone": "+1 508 495 5558",
    "sg:postcode": "02122",
    "sg:province": "MA",
    "sg:tags": [
      "industrial",
      "contractors-commercial",
      "contractor"
    ],
    "wof:name": "Christy Place",
    "wof:placetype": "venue"
  },
  "geometry": {"coordinates":[-71.057602,42.305939],"type":"Point"}
}
