{
  "type": "Feature",
  "properties": {
    "addr:full": "740 Main St Winchester MA 01890",
    "addr:housenumber": "740",
    "addr:postcode": "01890",
    "addr:street": "Main St",
    "iso:country": "US",
    "sg:address": "740 Main St",
    "sg:city": "Winchester",
    "sg:classifiers": [
      {
        "category": "Restaurant",
        "type": "Food \u0026 Drink"
      }
    ],
    "sg:phone": "+1 781 729 6700",
    "sg:postcode": "01890",
    "sg:province": "MA",
    "sg:tags": [
      "italian"
    ],
    "wof:name": "Toscano's Italian Kitchen",
    "wof:placetype": "venue"
  },
  "geometry": {"coordinates":[-71.132497,42.436027],"type":"Point"}
}
