{
  "type": "Feature",
  "properties": {
    "iso:country":"US",
    "sg:address":"740 Main St",
    "sg:city":"Winchester",
    "sg:classifiers":[
        {
            "category":"Restaurant",
            "type":"Food & Drink"
        }
    ],
    "sg:phone":"+1 781 729 6700",
    "sg:postcode":"01890",
    "sg:province":"MA",
    "sg:tags":[
        "italian"
    ],
    "wof:name":"Toscano's Italian Kitchen",
    "wof:placetype":"venue"
},
  "geometry": {"coordinates":[-71.132497,42.436027],"type":"Point"}
}