{
  "type": "Feature",
  "properties": {
    "iso:country":"US",
    "sg:address":"14 Decatur Street",
    "sg:city":"Cambridge",
    "sg:classifiers":[
        {
            "category":"Retail",
            "subcategory":"Auto Repair",
            "type":"Services"
        }
    ],
    "sg:phone":"+1 617 864 1555",
    "sg:postcode":"02139",
    "sg:province":"MA",
    "wof:name":"Auto Bon Imports",
    "wof:placetype":"venue"
},
  "geometry": {"coordinates":[-71.105166,42.361037],"type":"Point"}
}