{
  "type": "Feature",
  "properties": {
    "addr:full": "9 Liberty St Plymouth MA 02360",
    "addr:housenumber": "9",
    "addr:postcode": "02360",
    "addr:street": "Liberty St",
    "iso:country": "US",
    "sg:address": "9 Liberty St",
    "sg:city": "Plymouth",
    "sg:classifiers": [
      {
        "category": "Building \u0026 Trades",
        "subcategory": "Construction",
        "type": "Services"
      }
    ],
    "sg:phone": "+1   ",
    "sg:postcode": "02360",
    "sg:province": "MA",
    "sg:tags": [
      "real estate",
      "rental",
      "contractor"
    ],
    "wof:name": "John S Cavacco",
    "wof:placetype": "venue"
  },
  "geometry": {"coordinates":[-70.684247,41.966801],"type":"Point"}
}
