{
  "type": "Feature",
  "properties": {
    "iso:country":"US",
    "sg:address":"210 Queen Anne Rd",
    "sg:city":"Harwich",
    "sg:classifiers":[
        {
            "category":"Retail",
            "subcategory":"Auto Repair",
            "type":"Services"
        }
    ],
    "sg:phone":"+1   ",
    "sg:postcode":"02645",
    "sg:province":"MA",
    "sg:tags":[
        "body",
        "shop",
        "automotive"
    ],
    "wof:name":"Ryders",
    "wof:placetype":"venue"
},
  "geometry": {"coordinates":[-70.09648,41.698455],"type":"Point"}
}