{
  "type": "Feature",
  "properties": {
    "iso:country":"US",
    "sg:address":"644 Hemenway St",
    "sg:city":"Marlborough",
    "sg:classifiers":[
        {
            "category":"Wholesale",
            "subcategory":"Groceries",
            "type":"Manufacturing & Wholesale Goods"
        }
    ],
    "sg:phone":"+1   ",
    "sg:postcode":"01752",
    "sg:province":"MA",
    "sg:tags":[
        "general"
    ],
    "wof:name":"Tolman Associates",
    "wof:placetype":"venue"
},
  "geometry": {"coordinates":[-71.49807199999999,42.366536],"type":"Point"}
}