{
  "type": "Feature",
  "properties": {
    "addr:full": "81 East St Ludlow MA 01056",
    "addr:housenumber": "81",
    "addr:postcode": "01056",
    "addr:street": "East St",
    "iso:country": "US",
    "sg:address": "81 East St",
    "sg:city": "Ludlow",
    "sg:classifiers": [
      {
        "category": "Shopping",
        "subcategory": "Computers \u0026 Home Electronics",
        "type": "Retail Goods"
      }
    ],
    "sg:phone": "+1 413 583 6398",
    "sg:postcode": "01056",
    "sg:province": "MA",
    "sg:tags": [
      "software"
    ],
    "wof:name": "NMI Software",
    "wof:placetype": "venue"
  },
  "geometry": {"coordinates":[-72.479674,42.157189],"type":"Point"}
}
