{
  "type": "Feature",
  "properties": {
    "addr:full": "10 Federal St Nantucket MA 02554",
    "addr:housenumber": "10",
    "addr:postcode": "02554",
    "addr:street": "Federal St",
    "iso:country": "US",
    "sg:address": "10 Federal St",
    "sg:city": "Nantucket",
    "sg:classifiers": [
      {
        "category": "Shopping",
        "type": "Retail Goods"
      }
    ],
    "sg:phone": "+1 508 228 9314",
    "sg:postcode": "02554",
    "sg:province": "MA",
    "sg:tags": [
      "art",
      "gallery",
      "dealer"
    ],
    "wof:name": "Hoorn-Ashby Gallery",
    "wof:placetype": "venue"
  },
  "geometry": {"coordinates":[-70.098816,41.283823],"type":"Point"}
}
