{
  "type": "Feature",
  "properties": {
    "iso:country":"US",
    "sg:address":"523 Great Rd",
    "sg:city":"Littleton",
    "sg:classifiers":[
        {
            "category":"Building & Trades",
            "subcategory":"Construction",
            "type":"Services"
        }
    ],
    "sg:phone":"+1 978 952 0052",
    "sg:postcode":"01460",
    "sg:province":"MA",
    "sg:tags":[
        "contractor",
        "mechanical"
    ],
    "wof:name":"Mechanical Alliance Svc",
    "wof:placetype":"venue"
},
  "geometry": {"coordinates":[-71.484855,42.555242],"type":"Point"}
}