{
  "type": "Feature",
  "properties": {
    "addr:full": "210 Main St Gloucester MA 01930",
    "addr:housenumber": "210",
    "addr:postcode": "01930",
    "addr:street": "Main St",
    "iso:country": "US",
    "sg:address": "210 Main St",
    "sg:city": "Gloucester",
    "sg:classifiers": [
      {
        "category": "Shopping",
        "subcategory": "Music",
        "type": "Retail Goods"
      }
    ],
    "sg:phone": "+1 978 281 4874",
    "sg:postcode": "01930",
    "sg:province": "MA",
    "sg:tags": [
      "compact",
      "record",
      "disc",
      "tape"
    ],
    "wof:name": "Gloucester Music",
    "wof:placetype": "venue"
  },
  "geometry": {"coordinates":[-70.660694,42.613266],"type":"Point"}
}
