{
  "type": "Feature",
  "properties": {
    "iso:country":"US",
    "sg:address":"210 Main St",
    "sg:city":"Gloucester",
    "sg:classifiers":[
        {
            "category":"Shopping",
            "subcategory":"Music",
            "type":"Retail Goods"
        }
    ],
    "sg:phone":"+1 978 281 4874",
    "sg:postcode":"01930",
    "sg:province":"MA",
    "sg:tags":[
        "compact",
        "record",
        "disc",
        "tape"
    ],
    "wof:name":"Gloucester Music",
    "wof:placetype":"venue"
},
  "geometry": {"coordinates":[-70.66069400000001,42.613266],"type":"Point"}
}