{
  "type": "Feature",
  "properties": {
    "addr:full": "50 Meadowbrook Rd Brockton MA 02301",
    "addr:housenumber": "50",
    "addr:postcode": "02301",
    "addr:street": "Meadowbrook Rd",
    "iso:country": "US",
    "sg:address": "50 Meadowbrook Rd",
    "sg:city": "Brockton",
    "sg:classifiers": [
      {
        "category": "Home \u0026 Garden",
        "subcategory": "Hardware",
        "type": "Retail Goods"
      }
    ],
    "sg:phone": "+1 508 587 1224",
    "sg:postcode": "02301",
    "sg:province": "MA",
    "wof:name": "Sargent Supply Corp",
    "wof:placetype": "venue"
  },
  "geometry": {"coordinates":[-71.009193,42.056686],"type":"Point"}
}
