{
  "type": "Feature",
  "properties": {
    "iso:country":"US",
    "sg:address":"30 Main St",
    "sg:city":"Topsfield",
    "sg:classifiers":[
        {
            "category":"Shopping",
            "subcategory":"Pharmacy",
            "type":"Retail Goods"
        }
    ],
    "sg:phone":"+1 978 887 5003",
    "sg:postcode":"01983",
    "sg:province":"MA",
    "wof:name":"Eaton Apothecary",
    "wof:placetype":"venue"
},
  "geometry": {"coordinates":[-70.950751,42.639458],"type":"Point"}
}