{
  "type": "Feature",
  "properties": {
    "iso:country":"US",
    "sg:address":"1 Waterhouse St",
    "sg:city":"Cambridge",
    "sg:classifiers":[
        {
            "category":"Real Estate",
            "subcategory":"Real Estate Agent",
            "type":"Services"
        }
    ],
    "sg:phone":"+1   ",
    "sg:postcode":"02138",
    "sg:province":"MA",
    "wof:name":"George Bissell Rpo",
    "wof:placetype":"venue"
},
  "geometry": {"coordinates":[-71.122137,42.377503],"type":"Point"}
}