{
  "type": "Feature",
  "properties": {
    "iso:country":"US",
    "sg:address":"735 Providence Hwy",
    "sg:city":"Walpole",
    "sg:classifiers":[
        {
            "category":"Autos & Motor Vehicles",
            "subcategory":"Automobile Sales",
            "type":"Retail Goods"
        },
        {
            "category":"Retail",
            "subcategory":"Auto Repair",
            "type":"Services"
        }
    ],
    "sg:phone":"+1 781 762 4200",
    "sg:postcode":"02081",
    "sg:province":"MA",
    "sg:tags":[
        "car"
    ],
    "wof:name":"Jack Madden Ford",
    "wof:placetype":"venue"
},
  "geometry": {"coordinates":[-71.227097,42.128399],"type":"Point"}
}