{
  "type": "Feature",
  "properties": {
    "addr:full": "1 W Church St Mansfield MA 02048",
    "addr:housenumber": "1",
    "addr:postcode": "02048",
    "addr:street": "W Church St",
    "iso:country": "US",
    "sg:address": "1 W Church St",
    "sg:city": "Mansfield",
    "sg:classifiers": [
      {
        "category": "Personal",
        "type": "Services"
      }
    ],
    "sg:phone": "+1 508 337 9800",
    "sg:postcode": "02048",
    "sg:province": "MA",
    "sg:tags": [
      "consultant",
      "program",
      "health",
      "fitness"
    ],
    "wof:name": "Results Unlimited",
    "wof:placetype": "venue"
  },
  "geometry": {"coordinates":[-71.218612,42.029475],"type":"Point"}
}
