{
  "type": "Feature",
  "properties": {
    "addr:full":"1637 N Main St Fall River MA 02720",
    "addr:housenumber":"1637",
    "addr:postcode":"02720",
    "addr:street":"N Main St",
    "iso:country":"US",
    "sg:address":"1637 N Main St",
    "sg:city":"Fall River",
    "sg:classifiers":[
        {
            "category":"Manufacturing",
            "subcategory":"Apparel",
            "type":"Manufacturing & Wholesale Goods"
        }
    ],
    "sg:phone":"+1 508 673 3212",
    "sg:postcode":"02720",
    "sg:province":"MA",
    "sg:tags":[
        "outerwear",
        "waterproof"
    ],
    "sg:website":"www.idealbibs.com",
    "wof:name":"Ideal Bias Binding Corp",
    "wof:placetype":"venue"
},
  "geometry": {"coordinates":[-71.14475899999999,41.722336],"type":"Point"}
}