{
  "type": "Feature",
  "properties": {
    "addr:full": "649 S Main St Sheffield MA 01257",
    "addr:housenumber": "649",
    "addr:postcode": "01257",
    "addr:street": "S Main St",
    "iso:country": "US",
    "sg:address": "649 S Main St",
    "sg:city": "Sheffield",
    "sg:classifiers": [
      {
        "category": "Shopping",
        "subcategory": "Used Merchandise",
        "type": "Retail Goods"
      }
    ],
    "sg:phone": "+1 413 229 8382",
    "sg:postcode": "01257",
    "sg:province": "MA",
    "sg:tags": [
      "antique"
    ],
    "wof:name": "Ole T J's Antique Barn",
    "wof:placetype": "venue"
  },
  "geometry": {"coordinates":[-73.347357,42.093067],"type":"Point"}
}
