{
  "type": "Feature",
  "properties": {
    "addr:full": "249 Highland Ave Malden MA 02148",
    "addr:housenumber": "249",
    "addr:postcode": "02148",
    "addr:street": "Highland Ave",
    "iso:country": "US",
    "sg:address": "249 Highland Ave",
    "sg:city": "Malden",
    "sg:classifiers": [
      {
        "category": "Restaurant",
        "type": "Food \u0026 Drink"
      }
    ],
    "sg:phone": "+1 781 321 5322",
    "sg:postcode": "02148",
    "sg:province": "MA",
    "sg:tags": [
      "chinese"
    ],
    "wof:name": "Real Lucky",
    "wof:placetype": "venue"
  },
  "geometry": {"coordinates":[-71.079982,42.421993],"type":"Point"}
}
