{
  "type": "Feature",
  "properties": {
    "iso:country":"US",
    "sg:address":"249 Highland Ave",
    "sg:city":"Malden",
    "sg:classifiers":[
        {
            "category":"Restaurant",
            "type":"Food & Drink"
        }
    ],
    "sg:phone":"+1 781 321 5322",
    "sg:postcode":"02148",
    "sg:province":"MA",
    "sg:tags":[
        "chinese"
    ],
    "wof:name":"Real Lucky",
    "wof:placetype":"venue"
},
  "geometry": {"coordinates":[-71.079982,42.421993],"type":"Point"}
}