{
  "type": "Feature",
  "properties": {
    "addr:full":"60 Pinehurst Ave Auburn MA 01501",
    "addr:housenumber":"60",
    "addr:postcode":"01501",
    "addr:street":"Pinehurst Ave",
    "iso:country":"US",
    "sg:address":"60 Pinehurst Ave",
    "sg:city":"Auburn",
    "sg:classifiers":[
        {
            "category":"Taxi",
            "type":"Transportation"
        }
    ],
    "sg:phone":"+1 508 832 8412",
    "sg:postcode":"01501",
    "sg:province":"MA",
    "wof:name":"Precious Cargo Trnsprtn Inc",
    "wof:placetype":"venue"
},
  "geometry": {"coordinates":[-71.846667,42.221988],"type":"Point"}
}