{
  "type": "Feature",
  "properties": {
    "addr:full":"802 Bay Rd Taunton MA 02780",
    "addr:housenumber":"802",
    "addr:postcode":"02780",
    "addr:street":"Bay Rd",
    "iso:country":"US",
    "sg:address":"802 Bay Rd",
    "sg:city":"Taunton",
    "sg:classifiers":[
        {
            "category":"Food & Beverages",
            "subcategory":"Groceries & Convenience Stores",
            "type":"Retail Goods"
        }
    ],
    "sg:phone":"+1 508 822 1246",
    "sg:postcode":"02780",
    "sg:province":"MA",
    "sg:tags":[
        "market"
    ],
    "wof:name":"Andy's Super Market",
    "wof:placetype":"venue"
},
  "geometry": {"coordinates":[-71.103413,41.93214],"type":"Point"}
}