{
  "type": "Feature",
  "properties": {
    "iso:country":"US",
    "sg:address":"808 Main St",
    "sg:city":"Fitchburg",
    "sg:classifiers":[
        {
            "category":"Manufacturing",
            "subcategory":"Printing",
            "type":"Manufacturing & Wholesale Goods"
        }
    ],
    "sg:phone":"+1 978 343 6911",
    "sg:postcode":"01420",
    "sg:province":"MA",
    "sg:tags":[
        "newspaper"
    ],
    "sg:website":"www.sentinelandenterprise.com",
    "wof:name":"Fitchburg Publishing Co",
    "wof:placetype":"venue"
},
  "geometry": {"coordinates":[-71.80456,42.584907],"type":"Point"}
}