{
  "type": "Feature",
  "properties": {
    "addr:full": "316 Plain St Hanover MA 02339",
    "addr:housenumber": "316",
    "addr:postcode": "02339",
    "addr:street": "Plain St",
    "iso:country": "US",
    "sg:address": "316 Plain St",
    "sg:city": "Hanover",
    "sg:classifiers": [
      {
        "category": "Retail",
        "subcategory": "Laundry \u0026 Dry Cleaning",
        "type": "Services"
      },
      {
        "category": "Building \u0026 Trades",
        "subcategory": "Cleaning \u0026 Sanitation",
        "type": "Services"
      }
    ],
    "sg:phone": "+1 781 706 3581",
    "sg:postcode": "02339",
    "sg:province": "MA",
    "sg:tags": [
      "cleaner",
      "house"
    ],
    "wof:name": "Sure Kleen",
    "wof:placetype": "venue"
  },
  "geometry": {"coordinates":[-70.861516,42.12222],"type":"Point"}
}
