{
  "type": "Feature",
  "properties": {
    "iso:country":"US",
    "sg:address":"316 Plain St",
    "sg:city":"Hanover",
    "sg:classifiers":[
        {
            "category":"Retail",
            "subcategory":"Laundry & Dry Cleaning",
            "type":"Services"
        },
        {
            "category":"Building & Trades",
            "subcategory":"Cleaning & Sanitation",
            "type":"Services"
        }
    ],
    "sg:phone":"+1 781 706 3581",
    "sg:postcode":"02339",
    "sg:province":"MA",
    "sg:tags":[
        "cleaner",
        "house"
    ],
    "wof:name":"Sure Kleen",
    "wof:placetype":"venue"
},
  "geometry": {"coordinates":[-70.86151599999999,42.12222],"type":"Point"}
}