{
  "type": "Feature",
  "properties": {
    "addr:full":"215 Griffith Rd Chicopee MA 01022",
    "addr:housenumber":"215",
    "addr:postcode":"01022",
    "addr:street":"Griffith Rd",
    "iso:country":"US",
    "sg:address":"215 Griffith Rd",
    "sg:city":"Chicopee",
    "sg:classifiers":[
        {
            "category":"Wholesale",
            "subcategory":"Wine & Distilled Alcoholic Beverages",
            "type":"Manufacturing & Wholesale Goods"
        }
    ],
    "sg:phone":"+1 413 592 8178",
    "sg:postcode":"01022",
    "sg:province":"MA",
    "sg:tags":[
        "liquors-wholesale"
    ],
    "wof:name":"Specialized Carriers, Inc.",
    "wof:placetype":"venue"
},
  "geometry": {"coordinates":[-72.56146099999999,42.199242],"type":"Point"}
}