{
  "type": "Feature",
  "properties": {
    "addr:full": "498 E 3rd St South Boston MA 02127",
    "addr:housenumber": "498",
    "addr:postcode": "02127",
    "addr:street": "E 3Rd St",
    "iso:country": "US",
    "sg:address": "498 E 3rd St",
    "sg:city": "South Boston",
    "sg:classifiers": [
      {
        "category": "Retail",
        "subcategory": "Laundry \u0026 Dry Cleaning",
        "type": "Services"
      }
    ],
    "sg:phone": "+1 617 269 6110",
    "sg:postcode": "02127",
    "sg:province": "MA",
    "wof:name": "Suds N Bubbles",
    "wof:placetype": "venue"
  },
  "geometry": {"coordinates":[-71.040714,42.336408],"type":"Point"}
}
