{
  "type": "Feature",
  "properties": {
    "iso:country":"US",
    "sg:address":"498 E 3rd St",
    "sg:city":"South Boston",
    "sg:classifiers":[
        {
            "category":"Retail",
            "subcategory":"Laundry & Dry Cleaning",
            "type":"Services"
        }
    ],
    "sg:phone":"+1 617 269 6110",
    "sg:postcode":"02127",
    "sg:province":"MA",
    "wof:name":"Suds N Bubbles",
    "wof:placetype":"venue"
},
  "geometry": {"coordinates":[-71.04071399999999,42.336408],"type":"Point"}
}