{
  "type": "Feature",
  "properties": {
    "iso:country":"US",
    "sg:address":"191 Sherman St",
    "sg:city":"Cambridge",
    "sg:classifiers":[
        {
            "category":"Building & Trades",
            "subcategory":"Construction",
            "type":"Services"
        }
    ],
    "sg:phone":"+1   ",
    "sg:postcode":"02140",
    "sg:province":"MA",
    "sg:tags":[
        "carpentry",
        "contractor"
    ],
    "wof:name":"M S White Construction",
    "wof:placetype":"venue"
},
  "geometry": {"coordinates":[-71.132909,42.392877],"type":"Point"}
}