{
  "type": "Feature",
  "properties": {
    "addr:full": "489 Washington St Auburn MA 01501",
    "addr:housenumber": "489",
    "addr:postcode": "01501",
    "addr:street": "Washington St",
    "iso:country": "US",
    "sg:address": "489 Washington St",
    "sg:city": "Auburn",
    "sg:classifiers": [
      {
        "category": "Personal",
        "subcategory": "Tanning Parlor",
        "type": "Services"
      }
    ],
    "sg:phone": "+1 508 832 9821",
    "sg:postcode": "01501",
    "sg:province": "MA",
    "sg:tags": [
      "salon"
    ],
    "wof:name": "Tropic Sun Tanning Salon",
    "wof:placetype": "venue"
  },
  "geometry": {"coordinates":[-71.834068,42.187109],"type":"Point"}
}
