{
  "type": "Feature",
  "properties": {
    "addr:full": "1 Maple St Taunton MA 02780",
    "addr:housenumber": "1",
    "addr:postcode": "02780",
    "addr:street": "Maple St",
    "iso:country": "US",
    "sg:address": "1 Maple St",
    "sg:city": "Taunton",
    "sg:classifiers": [
      {
        "category": "Social Services",
        "type": "Services"
      }
    ],
    "sg:phone": "+1 508 977 9920",
    "sg:postcode": "02780",
    "sg:province": "MA",
    "sg:tags": [
      "organization",
      "welfare"
    ],
    "wof:name": "Childrens Study Home",
    "wof:placetype": "venue"
  },
  "geometry": {"coordinates":[-71.106343,41.904275],"type":"Point"}
}
