{
  "type": "Feature",
  "properties": {
    "iso:country":"US",
    "sg:address":"83 Bennington St",
    "sg:city":"Revere",
    "sg:classifiers":[
        {
            "category":"Retail",
            "subcategory":"Auto Repair",
            "type":"Services"
        }
    ],
    "sg:phone":"+1 781 284 9365",
    "sg:postcode":"02151",
    "sg:province":"MA",
    "sg:tags":[
        "repairing",
        "automobile"
    ],
    "wof:name":"Len's Auto Body",
    "wof:placetype":"venue"
},
  "geometry": {"coordinates":[-70.994272,42.393872],"type":"Point"}
}