{
  "type": "Feature",
  "properties": {
    "addr:full": "226 Page St Avon MA 02322",
    "addr:housenumber": "226",
    "addr:postcode": "02322",
    "addr:street": "Page St",
    "iso:country": "US",
    "sg:address": "226 Page St",
    "sg:city": "Avon",
    "sg:classifiers": [
      {
        "category": "Retail",
        "subcategory": "Veterinary Services",
        "type": "Services"
      }
    ],
    "sg:phone": "+1   ",
    "sg:postcode": "02322",
    "sg:province": "MA",
    "wof:name": "Norwood Animal Hospital",
    "wof:placetype": "venue"
  },
  "geometry": {"coordinates":[-71.050079,42.133126],"type":"Point"}
}
