{
  "type": "Feature",
  "properties": {
    "iso:country":"US",
    "sg:address":"396 Old Colony Rd",
    "sg:city":"Norton",
    "sg:classifiers":[
        {
            "category":"Professional",
            "subcategory":"Lawyer & Legal Services",
            "type":"Services"
        }
    ],
    "sg:phone":"+1 508 222 1234",
    "sg:postcode":"02766",
    "sg:province":"MA",
    "wof:name":"Skurchak John W Jr Lwyr",
    "wof:placetype":"venue"
},
  "geometry": {"coordinates":[-71.236397,41.951801],"type":"Point"}
}