{
  "type": "Feature",
  "properties": {
    "iso:country":"US",
    "sg:address":"133 Church St",
    "sg:city":"West Roxbury",
    "sg:classifiers":[
        {
            "category":"Professional",
            "type":"Services"
        }
    ],
    "sg:phone":"+1 617 327 6600",
    "sg:postcode":"02132",
    "sg:province":"MA",
    "sg:tags":[
        "establishment"
    ],
    "wof:name":"Addex Inc",
    "wof:placetype":"venue"
},
  "geometry": {"coordinates":[-71.14889700000001,42.292433],"type":"Point"}
}