{
  "type": "Feature",
  "properties": {
    "iso:country":"US",
    "sg:address":"40 Westech Dr",
    "sg:city":"Tyngsboro",
    "sg:classifiers":[
        {
            "category":"Professional",
            "subcategory":"Engineering",
            "type":"Services"
        },
        {
            "category":"Home & Garden",
            "subcategory":"Building Materials",
            "type":"Retail Goods"
        }
    ],
    "sg:phone":"+1 978 649 1128",
    "sg:postcode":"01879",
    "sg:province":"MA",
    "sg:tags":[
        "system",
        "equipment",
        "heating",
        "air conditioning"
    ],
    "wof:name":"Mass Control Center Inc",
    "wof:placetype":"venue"
},
  "geometry": {"coordinates":[-71.423849,42.655877],"type":"Point"}
}