{
  "type": "Feature",
  "properties": {
    "addr:full": "868 S Franklin St Holbrook MA 02343",
    "addr:housenumber": "868",
    "addr:postcode": "02343",
    "addr:street": "S Franklin St",
    "iso:country": "US",
    "sg:address": "868 S Franklin St",
    "sg:city": "Holbrook",
    "sg:classifiers": [
      {
        "category": "Restaurant",
        "type": "Food \u0026 Drink"
      }
    ],
    "sg:phone": "+1 781 961 4118",
    "sg:postcode": "02343",
    "sg:province": "MA",
    "sg:tags": [
      "shop",
      "coffee"
    ],
    "wof:name": "Boop's Coffee Shop",
    "wof:placetype": "venue"
  },
  "geometry": {"coordinates":[-71.010555,42.126881],"type":"Point"}
}
