{
  "type": "Feature",
  "properties": {
    "iso:country":"US",
    "sg:address":"1380 Soldiers Field Road",
    "sg:city":"Boston",
    "sg:classifiers":[
        {
            "category":"Professional",
            "subcategory":"Research",
            "type":"Services"
        }
    ],
    "sg:province":"MA",
    "sg:tags":[
        "renewable-energy"
    ],
    "sg:website":"http://www.ze-gen.com/",
    "wof:name":"Ze-Gen",
    "wof:placetype":"venue"
},
  "geometry": {"coordinates":[-71.117941,42.364194],"type":"Point"}
}