{
  "type": "Feature",
  "properties": {
    "iso:country":"US",
    "sg:address":"5 Pond Park Rd",
    "sg:city":"Hingham",
    "sg:classifiers":[
        {
            "category":"Professional",
            "subcategory":"Management & Consulting",
            "type":"Services"
        }
    ],
    "sg:phone":"+1 781 741 8622",
    "sg:postcode":"02043",
    "sg:province":"MA",
    "sg:tags":[
        "consultant",
        "business"
    ],
    "sg:website":"www.myersnissi.com",
    "wof:name":"Nissi Myers & Co Inc",
    "wof:placetype":"venue"
},
  "geometry": {"coordinates":[-70.91824699999999,42.17606],"type":"Point"}
}