{
  "type": "Feature",
  "properties": {
    "addr:full": "5 Pond Park Rd Hingham MA 02043",
    "addr:housenumber": "5",
    "addr:postcode": "02043",
    "addr:street": "Pond Park Rd",
    "iso:country": "US",
    "sg:address": "5 Pond Park Rd",
    "sg:city": "Hingham",
    "sg:classifiers": [
      {
        "category": "Professional",
        "subcategory": "Management \u0026 Consulting",
        "type": "Services"
      }
    ],
    "sg:phone": "+1 781 741 8622",
    "sg:postcode": "02043",
    "sg:province": "MA",
    "sg:tags": [
      "consultant",
      "business"
    ],
    "sg:website": "www.myersnissi.com",
    "wof:name": "Nissi Myers \u0026 Co Inc",
    "wof:placetype": "venue"
  },
  "geometry": {"coordinates":[-70.918247,42.17606],"type":"Point"}
}
