{
  "type": "Feature",
  "properties": {
    "addr:full": "1140 Washington St Roxbury MA 02118",
    "addr:housenumber": "1140",
    "addr:postcode": "02118",
    "addr:street": "Washington St",
    "iso:country": "US",
    "sg:address": "1140 Washington St",
    "sg:city": "Roxbury",
    "sg:classifiers": [
      {
        "category": "Retail",
        "subcategory": "Funeral Services",
        "type": "Services"
      }
    ],
    "sg:phone": "+1 617 298 8011",
    "sg:postcode": "02118",
    "sg:province": "MA",
    "sg:tags": [
      "cemetery"
    ],
    "wof:name": "Dolan Jas W Inc Funrl Serv",
    "wof:placetype": "venue"
  },
  "geometry": {"coordinates":[-71.066002,42.3438],"type":"Point"}
}
