{
  "type": "Feature",
  "properties": {
    "addr:full": "2226 Massachusetts Ave Cambridge MA 02140",
    "addr:housenumber": "2226",
    "addr:postcode": "02140",
    "addr:street": "Massachusetts Ave",
    "iso:country": "US",
    "sg:address": "2226 Massachusetts Ave",
    "sg:city": "Cambridge",
    "sg:classifiers": [
      {
        "category": "Shopping",
        "subcategory": "Antiques",
        "type": "Retail Goods"
      }
    ],
    "sg:phone": "+1 617 547 1490",
    "sg:postcode": "02140",
    "sg:province": "MA",
    "sg:website": "www.citylights.nu",
    "wof:name": "City Lights",
    "wof:placetype": "venue"
  },
  "geometry": {"coordinates":[-71.126003,42.39356],"type":"Point"}
}
