{
  "type": "Feature",
  "properties": {
    "iso:country":"US",
    "sg:address":"400 Minuteman Rd",
    "sg:city":"Andover",
    "sg:classifiers":[
        {
            "category":"Communications",
            "subcategory":"News Services",
            "type":"Services"
        }
    ],
    "sg:phone":"+1 978 983 6300",
    "sg:postcode":"01810",
    "sg:province":"MA",
    "sg:tags":[
        "information",
        "weather"
    ],
    "sg:website":"http://www.wsi.com",
    "wof:name":"Wsi Corporation",
    "wof:placetype":"venue"
},
  "geometry": {"coordinates":[-71.211708,42.69389],"type":"Point"}
}