{
  "type": "Feature",
  "properties": {
    "iso:country":"US",
    "sg:address":"73 Walnut St",
    "sg:city":"Oxford",
    "sg:classifiers":[
        {
            "category":"Professional",
            "subcategory":"Business Services",
            "type":"Services"
        }
    ],
    "sg:phone":"+1   ",
    "sg:postcode":"01540",
    "sg:province":"MA",
    "wof:name":"Ace Enterprises Inc",
    "wof:placetype":"venue"
},
  "geometry": {"coordinates":[-71.87815000000001,42.108918],"type":"Point"}
}