{
  "type": "Feature",
  "properties": {
    "addr:full": "1 University Park Waltham MA 02453",
    "addr:housenumber": "1",
    "addr:postcode": "02453",
    "addr:street": "University Park",
    "iso:country": "US",
    "sg:address": "1 University Park",
    "sg:city": "Waltham",
    "sg:classifiers": [
      {
        "category": "Building \u0026 Trades",
        "subcategory": "Construction",
        "type": "Services"
      }
    ],
    "sg:phone": "+1 781 647 1255",
    "sg:postcode": "02453",
    "sg:province": "MA",
    "sg:tags": [
      "equipment",
      "computer",
      "rooms"
    ],
    "wof:name": "Microclean Inc",
    "wof:placetype": "venue"
  },
  "geometry": {"coordinates":[-71.260215,42.370183],"type":"Point"}
}
