{
  "type": "Feature",
  "properties": {
    "iso:country":"US",
    "sg:address":"108 Degrass Rd",
    "sg:city":"Mashpee",
    "sg:classifiers":[
        {
            "category":"Mining & Drilling",
            "type":"Manufacturing & Wholesale Goods"
        },
        {
            "category":"Utilities",
            "subcategory":"Water",
            "type":"Services"
        }
    ],
    "sg:phone":"+1 508 477 1142",
    "sg:postcode":"02649",
    "sg:province":"MA",
    "sg:tags":[
        "boring",
        "pump",
        "well",
        "contractor"
    ],
    "wof:name":"Diversified Drilling Co",
    "wof:placetype":"venue"
},
  "geometry": {"coordinates":[-70.484869,41.586277],"type":"Point"}
}