{
  "type": "Feature",
  "properties": {
    "addr:full":"26 Pleasant St Uxbridge MA 01569",
    "addr:housenumber":"26",
    "addr:postcode":"01569",
    "addr:street":"Pleasant St",
    "iso:country":"US",
    "sg:address":"26 Pleasant St",
    "sg:city":"Uxbridge",
    "sg:classifiers":[
        {
            "category":"Building & Trades",
            "subcategory":"Electrical",
            "type":"Services"
        }
    ],
    "sg:phone":"+1 508 278 3288",
    "sg:postcode":"01569",
    "sg:province":"MA",
    "sg:tags":[
        "electrician"
    ],
    "wof:name":"Thiebault Electric Inc",
    "wof:placetype":"venue"
},
  "geometry": {"coordinates":[-71.629372,42.074291],"type":"Point"}
}