{
  "type": "Feature",
  "properties": {
    "iso:country":"US",
    "sg:address":"100 Widett Cir",
    "sg:city":"Roxbury",
    "sg:classifiers":[
        {
            "category":"Wholesale",
            "subcategory":"Seafood",
            "type":"Manufacturing & Wholesale Goods"
        }
    ],
    "sg:phone":"+1 617 269 3100",
    "sg:postcode":"02118",
    "sg:province":"MA",
    "sg:tags":[
        "fish",
        "seafood-wholesale"
    ],
    "sg:website":"http://www.crockerwinsor.com",
    "wof:name":"Crocker and Winsor Seafoods",
    "wof:placetype":"venue"
},
  "geometry": {"coordinates":[-71.06183,42.337911],"type":"Point"}
}