{
  "type": "Feature",
  "properties": {
    "addr:full":"408 Sodom Rd Westport MA 02790",
    "addr:housenumber":"408",
    "addr:postcode":"02790",
    "addr:street":"Sodom Rd",
    "iso:country":"US",
    "sg:address":"408 Sodom Rd",
    "sg:city":"Westport",
    "sg:classifiers":[
        {
            "category":"Freight",
            "type":"Transportation"
        }
    ],
    "sg:phone":"+1 508 636 8052",
    "sg:postcode":"02790",
    "sg:province":"MA",
    "sg:tags":[
        "trucking"
    ],
    "wof:name":"Ivy Meadows Farms",
    "wof:placetype":"venue"
},
  "geometry": {"coordinates":[-71.111717,41.606459],"type":"Point"}
}