{
  "type": "Feature",
  "properties": {
    "iso:country":"US",
    "sg:address":"6 Colonial Dr",
    "sg:city":"Westborough",
    "sg:classifiers":[
        {
            "category":"Social Services",
            "type":"Services"
        }
    ],
    "sg:phone":"+1 508 366 7557",
    "sg:postcode":"01581",
    "sg:province":"MA",
    "sg:tags":[
        "counselor",
        "marriage",
        "family"
    ],
    "wof:name":"Parenting That Works",
    "wof:placetype":"venue"
},
  "geometry": {"coordinates":[-71.609236,42.272408],"type":"Point"}
}