{
  "type": "Feature",
  "properties": {
    "iso:country":"US",
    "sg:address":"71 Bond St",
    "sg:city":"Norwood",
    "sg:phone":"+1 781 762 1633",
    "sg:postcode":"02062",
    "sg:province":"MA",
    "wof:name":"First Baptist Church Of Norwood",
    "wof:placetype":"venue"
},
  "geometry": {"coordinates":[-71.206667,42.190537],"type":"Point"}
}