{
  "type": "Feature",
  "properties": {
    "addr:full":"14 Sandra Rd Peabody MA 01960",
    "addr:housenumber":"14",
    "addr:postcode":"01960",
    "addr:street":"Sandra Rd",
    "iso:country":"US",
    "sg:address":"14 Sandra Rd",
    "sg:city":"Peabody",
    "sg:classifiers":[
        {
            "category":"Building & Trades",
            "subcategory":"Construction",
            "type":"Services"
        }
    ],
    "sg:phone":"+1   ",
    "sg:postcode":"01960",
    "sg:province":"MA",
    "sg:tags":[
        "residential"
    ],
    "wof:name":"J Karamas Co",
    "wof:placetype":"venue"
},
  "geometry": {"coordinates":[-70.963252,42.513023],"type":"Point"}
}