{
  "type": "Feature",
  "properties": {
    "addr:full": "115 Day St West Springfield MA 01089",
    "addr:housenumber": "115",
    "addr:postcode": "01089",
    "addr:street": "Day St",
    "iso:country": "US",
    "sg:address": "115 Day St",
    "sg:city": "West Springfield",
    "sg:classifiers": [
      {
        "category": "Professional",
        "subcategory": "Business Services",
        "type": "Services"
      }
    ],
    "sg:phone": "+1 413 734 7800",
    "sg:postcode": "01089",
    "sg:province": "MA",
    "sg:tags": [
      "water",
      "treatment"
    ],
    "wof:name": "Form Cell",
    "wof:placetype": "venue"
  },
  "geometry": {"coordinates":[-72.613568,42.100234],"type":"Point"}
}
