{
  "type": "Feature",
  "properties": {
    "iso:country":"US",
    "sg:address":"265 Sisson Rd",
    "sg:city":"Harwich",
    "sg:classifiers":[
        {
            "category":"Recreation",
            "type":"Entertainment"
        }
    ],
    "sg:phone":"+1 508 430 7553",
    "sg:postcode":"02645",
    "sg:province":"MA",
    "sg:tags":[
        "parks"
    ],
    "wof:name":"Harwich Recreation & Youth",
    "wof:placetype":"venue"
},
  "geometry": {"coordinates":[-70.076776,41.684835],"type":"Point"}
}