{
  "type": "Feature",
  "properties": {
    "addr:full": "265 Sisson Rd Harwich MA 02645",
    "addr:housenumber": "265",
    "addr:postcode": "02645",
    "addr:street": "Sisson Rd",
    "iso:country": "US",
    "sg:address": "265 Sisson Rd",
    "sg:city": "Harwich",
    "sg:classifiers": [
      {
        "category": "Recreation",
        "type": "Entertainment"
      }
    ],
    "sg:phone": "+1 508 430 7553",
    "sg:postcode": "02645",
    "sg:province": "MA",
    "sg:tags": [
      "parks"
    ],
    "wof:name": "Harwich Recreation \u0026 Youth",
    "wof:placetype": "venue"
  },
  "geometry": {"coordinates":[-70.076776,41.684835],"type":"Point"}
}
