{
  "type": "Feature",
  "properties": {
    "iso:country":"US",
    "sg:address":"114 Douglas St",
    "sg:city":"Uxbridge",
    "sg:phone":"+1 508 278 5895",
    "sg:postcode":"01569",
    "sg:province":"MA",
    "sg:tags":[
        "gas"
    ],
    "wof:name":"Martin's Oil & Gas",
    "wof:placetype":"venue"
},
  "geometry": {"coordinates":[-71.63838,42.078078],"type":"Point"}
}