{
  "type": "Feature",
  "properties": {
    "addr:full": "114 Douglas St Uxbridge MA 01569",
    "addr:housenumber": "114",
    "addr:postcode": "01569",
    "addr:street": "Douglas St",
    "iso:country": "US",
    "sg:address": "114 Douglas St",
    "sg:city": "Uxbridge",
    "sg:phone": "+1 508 278 5895",
    "sg:postcode": "01569",
    "sg:province": "MA",
    "sg:tags": [
      "gas"
    ],
    "wof:name": "Martin's Oil \u0026 Gas",
    "wof:placetype": "venue"
  },
  "geometry": {"coordinates":[-71.63838,42.078078],"type":"Point"}
}
