{
  "type": "Feature",
  "properties": {
    "iso:country":"US",
    "sg:address":"16 River Rd",
    "sg:city":"Orleans",
    "sg:classifiers":[
        {
            "category":"Building & Trades",
            "subcategory":"Landscaping Services",
            "type":"Services"
        }
    ],
    "sg:phone":"+1 508 255 8288",
    "sg:postcode":"02653",
    "sg:province":"MA",
    "sg:tags":[
        "landscape",
        "contractor"
    ],
    "wof:name":"Sea Gardens Fine Landscaping",
    "wof:placetype":"venue"
},
  "geometry": {"coordinates":[-69.974857,41.78291],"type":"Point"}
}