{
  "type": "Feature",
  "properties": {
    "iso:country":"US",
    "sg:address":"151 Essex St",
    "sg:city":"Haverhill",
    "sg:classifiers":[
        {
            "category":"Manufacturing",
            "subcategory":"Apparel",
            "type":"Manufacturing & Wholesale Goods"
        }
    ],
    "sg:phone":"+1 978 373 1566",
    "sg:postcode":"01832",
    "sg:province":"MA",
    "wof:name":"Chaucer Leather Corp",
    "wof:placetype":"venue"
},
  "geometry": {"coordinates":[-71.086457,42.775331],"type":"Point"}
}