{
  "type": "Feature",
  "properties": {
    "addr:full":"30 Pleasant Ave Leominster MA 01453",
    "addr:housenumber":"30",
    "addr:postcode":"01453",
    "addr:street":"Pleasant Ave",
    "iso:country":"US",
    "sg:address":"30 Pleasant Ave",
    "sg:city":"Leominster",
    "sg:classifiers":[
        {
            "category":"Food & Beverages",
            "subcategory":"Liquor & Beverages",
            "type":"Retail Goods"
        }
    ],
    "sg:phone":"+1 978 537 5537",
    "sg:postcode":"01453",
    "sg:province":"MA",
    "wof:name":"Wyman's Liquor Mart Inc",
    "wof:placetype":"venue"
},
  "geometry": {"coordinates":[-71.74503900000001,42.571265],"type":"Point"}
}