{
  "type": "Feature",
  "properties": {
    "addr:full": "38 Duxbury Rd Newton MA 02459",
    "addr:housenumber": "38",
    "addr:postcode": "02459",
    "addr:street": "Duxbury Rd",
    "iso:country": "US",
    "sg:address": "38 Duxbury Rd",
    "sg:city": "Newton",
    "sg:classifiers": [
      {
        "category": "Professional",
        "subcategory": "Management \u0026 Consulting",
        "type": "Services"
      }
    ],
    "sg:phone": "+1 617 244 0553",
    "sg:postcode": "02459",
    "sg:province": "MA",
    "sg:tags": [
      "consultant",
      "business"
    ],
    "wof:name": "Ford-Stuck Organization",
    "wof:placetype": "venue"
  },
  "geometry": {"coordinates":[-71.190247,42.319027],"type":"Point"}
}
