{
  "type": "Feature",
  "properties": {
    "iso:country":"US",
    "sg:address":"38 Duxbury Rd",
    "sg:city":"Newton",
    "sg:classifiers":[
        {
            "category":"Professional",
            "subcategory":"Management & Consulting",
            "type":"Services"
        }
    ],
    "sg:phone":"+1 617 244 0553",
    "sg:postcode":"02459",
    "sg:province":"MA",
    "sg:tags":[
        "consultant",
        "business"
    ],
    "wof:name":"Ford-Stuck Organization",
    "wof:placetype":"venue"
},
  "geometry": {"coordinates":[-71.190247,42.319027],"type":"Point"}
}