{
  "type": "Feature",
  "properties": {
    "addr:full": "44 Main St Nantucket MA 02554",
    "addr:housenumber": "44",
    "addr:postcode": "02554",
    "addr:street": "Main St",
    "iso:country": "US",
    "sg:address": "44 Main St",
    "sg:city": "Nantucket",
    "sg:classifiers": [
      {
        "category": "Shopping",
        "type": "Retail Goods"
      }
    ],
    "sg:phone": "+1 508 228 0110",
    "sg:postcode": "02554",
    "sg:province": "MA",
    "sg:tags": [
      "art",
      "gallery",
      "dealer"
    ],
    "sg:website": "www.madeonnantucket.com",
    "wof:name": "Made On Nantucket",
    "wof:placetype": "venue"
  },
  "geometry": {"coordinates":[-70.098654,41.283302],"type":"Point"}
}
