{
  "type": "Feature",
  "properties": {
    "iso:country":"US",
    "sg:address":"197 Main St",
    "sg:city":"North Reading",
    "sg:classifiers":[
        {
            "category":"Personal",
            "subcategory":"Beauty Salon",
            "type":"Services"
        }
    ],
    "sg:phone":"+1 978 664 4496",
    "sg:postcode":"01864",
    "sg:province":"MA",
    "sg:tags":[
        "treatment",
        "skin"
    ],
    "sg:website":"www.essentialsbysheila.com",
    "wof:name":"Essentials By Sheila",
    "wof:placetype":"venue"
},
  "geometry": {"coordinates":[-71.11443,42.585516],"type":"Point"}
}