{
  "type": "Feature",
  "properties": {
    "addr:full": "969 Main St Millis MA 02054",
    "addr:housenumber": "969",
    "addr:postcode": "02054",
    "addr:street": "Main St",
    "iso:country": "US",
    "sg:address": "969 Main St",
    "sg:city": "Millis",
    "sg:classifiers": [
      {
        "category": "Banks \u0026 Credit Unions",
        "subcategory": "Bank",
        "type": "Services"
      }
    ],
    "sg:phone": "+1 508 376 8484",
    "sg:postcode": "02054",
    "sg:province": "MA",
    "sg:tags": [
      "loan",
      "real estate"
    ],
    "wof:name": "New England Schooner Mortgage",
    "wof:placetype": "venue"
  },
  "geometry": {"coordinates":[-71.361917,42.165653],"type":"Point"}
}
