{
  "type": "Feature",
  "properties": {
    "iso:country":"US",
    "sg:address":"60 Gore St",
    "sg:city":"Cambridge",
    "sg:classifiers":[
        {
            "category":"Arts & Performance",
            "subcategory":"Theater",
            "type":"Entertainment"
        }
    ],
    "sg:phone":"+1 617 349 0086",
    "sg:postcode":"02141",
    "sg:province":"MA",
    "sg:tags":[
        "band",
        "orchestra"
    ],
    "sg:website":"www.bostonchambermusic.org",
    "wof:name":"Boston Chamber Music Society",
    "wof:placetype":"venue"
},
  "geometry": {"coordinates":[-71.07998600000001,42.371676],"type":"Point"}
}