{
  "type": "Feature",
  "properties": {
    "iso:country":"US",
    "sg:address":"7 Hathorn St",
    "sg:city":"Somerville",
    "sg:classifiers":[
        {
            "category":"Health Services",
            "subcategory":"Doctor",
            "type":"Services"
        },
        {
            "category":"Health Services",
            "subcategory":"Chiropractor",
            "type":"Services"
        }
    ],
    "sg:phone":"+1 617 666 1289",
    "sg:postcode":"02145",
    "sg:province":"MA",
    "sg:tags":[
        "physician",
        "surgeon",
        "chiropractic"
    ],
    "wof:name":"Jacob George",
    "wof:placetype":"venue"
},
  "geometry": {"coordinates":[-71.08175799999999,42.38695],"type":"Point"}
}