{
  "type": "Feature",
  "properties": {
    "addr:full":"638 Chandler St Worcester MA 01602",
    "addr:housenumber":"638",
    "addr:postcode":"01602",
    "addr:street":"Chandler St",
    "iso:country":"US",
    "sg:address":"638 Chandler St",
    "sg:city":"Worcester",
    "sg:classifiers":[
        {
            "category":"Home & Garden",
            "subcategory":"Hardware",
            "type":"Retail Goods"
        }
    ],
    "sg:phone":"+1 508 363 4680",
    "sg:postcode":"01602",
    "sg:province":"MA",
    "sg:website":"www.rockys.com",
    "wof:name":"Rocky's Ace Hardware",
    "wof:placetype":"venue"
},
  "geometry": {"coordinates":[-71.85359,42.277602],"type":"Point"}
}