{
  "type": "Feature",
  "properties": {
    "addr:full":"219 Washington St Woburn MA 01801",
    "addr:housenumber":"219",
    "addr:postcode":"01801",
    "addr:street":"Washington St",
    "iso:country":"US",
    "sg:address":"219 Washington St",
    "sg:city":"Woburn",
    "sg:classifiers":[
        {
            "category":"Personal",
            "type":"Services"
        }
    ],
    "sg:phone":"+1   ",
    "sg:postcode":"01801",
    "sg:province":"MA",
    "wof:name":"Safe Skin Sunless Tanning",
    "wof:placetype":"venue"
},
  "geometry": {"coordinates":[-71.12035,42.486202],"type":"Point"}
}