{
  "type": "Feature",
  "properties": {
    "addr:full": "40 Spring Garden Street Dorchester MA 02125",
    "addr:housenumber": "40",
    "addr:postcode": "02125",
    "addr:street": "Spring Garden Street",
    "iso:country": "US",
    "sg:address": "40 Spring Garden Street",
    "sg:city": "Dorchester",
    "sg:classifiers": [
      {
        "category": "Building \u0026 Trades",
        "subcategory": "Construction",
        "type": "Services"
      }
    ],
    "sg:phone": "+1 617 825 9363",
    "sg:postcode": "02125",
    "sg:province": "MA",
    "sg:tags": [
      "contractor"
    ],
    "wof:name": "Manganese Emilio M Home Improvement",
    "wof:placetype": "venue"
  },
  "geometry": {"coordinates":[-71.053486,42.317063],"type":"Point"}
}
