{
  "type": "Feature",
  "properties": {
    "iso:country":"US",
    "sg:address":"40 Spring Garden Street",
    "sg:city":"Dorchester",
    "sg:classifiers":[
        {
            "category":"Building & Trades",
            "subcategory":"Construction",
            "type":"Services"
        }
    ],
    "sg:phone":"+1 617 825 9363",
    "sg:postcode":"02125",
    "sg:province":"MA",
    "sg:tags":[
        "contractor"
    ],
    "wof:name":"Manganese Emilio M Home Improvement",
    "wof:placetype":"venue"
},
  "geometry": {"coordinates":[-71.05348600000001,42.317063],"type":"Point"}
}