{
  "type": "Feature",
  "properties": {
    "addr:full":"1 Partridge Ln Winchester MA 01890",
    "addr:housenumber":"1",
    "addr:postcode":"01890",
    "addr:street":"Partridge Ln",
    "iso:country":"US",
    "sg:address":"1 Partridge Ln",
    "sg:city":"Winchester",
    "sg:classifiers":[
        {
            "category":"Insurance",
            "subcategory":"Hazard Insurance",
            "type":"Services"
        }
    ],
    "sg:phone":"+1 781 439 8507",
    "sg:postcode":"01890",
    "sg:province":"MA",
    "sg:tags":[
        "commercial",
        "business"
    ],
    "wof:name":"Shannon Quinn Insur",
    "wof:placetype":"venue"
},
  "geometry": {"coordinates":[-71.182343,42.446869],"type":"Point"}
}