{
  "type": "Feature",
  "properties": {
    "iso:country":"US",
    "sg:address":"10 Moulton St",
    "sg:city":"Georgetown",
    "sg:classifiers":[
        {
            "category":"Building & Trades",
            "subcategory":"Construction",
            "type":"Services"
        }
    ],
    "sg:phone":"+1 978 352 2641",
    "sg:postcode":"01833",
    "sg:province":"MA",
    "sg:tags":[
        "contractor"
    ],
    "wof:name":"Moretti & Sons Inc",
    "wof:placetype":"venue"
},
  "geometry": {"coordinates":[-70.996906,42.725401],"type":"Point"}
}