{
  "type": "Feature",
  "properties": {
    "addr:full":"34 Merriam Ln Sutton MA 01590",
    "addr:housenumber":"34",
    "addr:postcode":"01590",
    "addr:street":"Merriam Ln",
    "iso:country":"US",
    "sg:address":"34 Merriam Ln",
    "sg:city":"Sutton",
    "sg:classifiers":[
        {
            "category":"Manufacturing",
            "subcategory":"Tools & Machinery",
            "type":"Manufacturing & Wholesale Goods"
        }
    ],
    "sg:phone":"+1 508 865 7848",
    "sg:postcode":"01590",
    "sg:province":"MA",
    "sg:tags":[
        "equipment",
        "tree",
        "supply"
    ],
    "wof:name":"Just Stumps",
    "wof:placetype":"venue"
},
  "geometry": {"coordinates":[-71.77831399999999,42.151263],"type":"Point"}
}