{
  "type": "Feature",
  "properties": {
    "addr:full": "158 Main St Northampton MA 01060",
    "addr:housenumber": "158",
    "addr:postcode": "01060",
    "addr:street": "Main St",
    "iso:country": "US",
    "sg:address": "158 Main St",
    "sg:city": "Northampton",
    "sg:classifiers": [
      {
        "category": "Shopping",
        "subcategory": "Shoes",
        "type": "Retail Goods"
      }
    ],
    "sg:phone": "+1 413 586 1074",
    "sg:postcode": "01060",
    "sg:province": "MA",
    "wof:name": "Ted's Boot Shop",
    "wof:placetype": "venue"
  },
  "geometry": {"coordinates":[-72.630813,42.318815],"type":"Point"}
}
