{
  "type": "Feature",
  "properties": {
    "iso:country":"US",
    "sg:address":"20 William St",
    "sg:city":"Wellesley",
    "sg:classifiers":[
        {
            "category":"Professional",
            "subcategory":"Employment Agencies",
            "type":"Services"
        }
    ],
    "sg:phone":"+1 781 237 9880",
    "sg:postcode":"02481",
    "sg:province":"MA",
    "sg:tags":[
        "opportunity"
    ],
    "sg:website":"www.wilmark.com",
    "wof:name":"Winstaff",
    "wof:placetype":"venue"
},
  "geometry": {"coordinates":[-71.23035900000001,42.318276],"type":"Point"}
}