{
  "type": "Feature",
  "properties": {
    "iso:country":"US",
    "sg:address":"1195 Centre St",
    "sg:city":"Roslindale",
    "sg:classifiers":[
        {
            "category":"Organizations",
            "subcategory":"Religious Organization",
            "type":"Services"
        }
    ],
    "sg:phone":"+1 617 323 6220",
    "sg:postcode":"02130",
    "sg:province":"MA",
    "sg:tags":[
        "church"
    ],
    "wof:name":"Highland Congregational Church",
    "wof:placetype":"venue"
},
  "geometry": {"coordinates":[-71.13006799999999,42.298183],"type":"Point"}
}