{
  "type": "Feature",
  "properties": {
    "iso:country":"US",
    "sg:address":"1355 Washington St",
    "sg:city":"West Newton",
    "sg:classifiers":[
        {
            "category":"Retail",
            "subcategory":"Portrait Studio",
            "type":"Services"
        }
    ],
    "sg:phone":"+1 617 558 5552",
    "sg:postcode":"02465",
    "sg:province":"MA",
    "sg:tags":[
        "photographer"
    ],
    "wof:name":"Bachrach Photographers",
    "wof:placetype":"venue"
},
  "geometry": {"coordinates":[-71.22878799999999,42.348801],"type":"Point"}
}