{
  "type": "Feature",
  "properties": {
    "addr:full": "1355 Washington St West Newton MA 02465",
    "addr:housenumber": "1355",
    "addr:postcode": "02465",
    "addr:street": "Washington St",
    "iso:country": "US",
    "sg:address": "1355 Washington St",
    "sg:city": "West Newton",
    "sg:classifiers": [
      {
        "category": "Retail",
        "subcategory": "Portrait Studio",
        "type": "Services"
      }
    ],
    "sg:phone": "+1 617 558 5552",
    "sg:postcode": "02465",
    "sg:province": "MA",
    "sg:tags": [
      "photographer"
    ],
    "wof:name": "Bachrach Photographers",
    "wof:placetype": "venue"
  },
  "geometry": {"coordinates":[-71.228788,42.348801],"type":"Point"}
}
