{
  "type": "Feature",
  "properties": {
    "addr:full":"18 Millbury St Worcester MA 01610",
    "addr:housenumber":"18",
    "addr:postcode":"01610",
    "addr:street":"Millbury St",
    "iso:country":"US",
    "sg:address":"18 Millbury St",
    "sg:city":"Worcester",
    "sg:classifiers":[
        {
            "category":"Professional",
            "subcategory":"Employment Agencies",
            "type":"Services"
        }
    ],
    "sg:phone":"+1 508 757 8668",
    "sg:postcode":"01610",
    "sg:province":"MA",
    "sg:tags":[
        "opportunity"
    ],
    "wof:name":"Bestway Temporary Agency Inc",
    "wof:placetype":"venue"
},
  "geometry": {"coordinates":[-71.798068,42.254459],"type":"Point"}
}