{
  "type": "Feature",
  "properties": {
    "iso:country":"US",
    "sg:address":"769 Worcester St Ste 4",
    "sg:city":"Southbridge",
    "sg:classifiers":[
        {
            "category":"Food & Beverages",
            "subcategory":"Groceries & Convenience Stores",
            "type":"Retail Goods"
        }
    ],
    "sg:phone":"+1 508 764 8900",
    "sg:postcode":"01550",
    "sg:province":"MA",
    "wof:name":"One Stop Convenience Store",
    "wof:placetype":"venue"
},
  "geometry": {"coordinates":[-72.019114,42.099385],"type":"Point"}
}