{
  "type": "Feature",
  "properties": {
    "addr:full": "736 High St Westwood MA 02090",
    "addr:housenumber": "736",
    "addr:postcode": "02090",
    "addr:street": "High St",
    "iso:country": "US",
    "sg:address": "736 High St",
    "sg:city": "Westwood",
    "sg:classifiers": [
      {
        "category": "Coffee \u0026 Tea",
        "type": "Food \u0026 Drink"
      }
    ],
    "sg:menulink": "http://www.allmenus.com/ma/westwood/125552-starbucks-coffee/menu/",
    "sg:phone": "+1 781 329 5421",
    "sg:postcode": "02090",
    "sg:province": "MA",
    "sg:tags": [
      "american"
    ],
    "wof:name": "Starbucks Coffee",
    "wof:placetype": "venue"
  },
  "geometry": {"coordinates":[-71.222667,42.223196],"type":"Point"}
}
