{
  "type": "Feature",
  "properties": {
    "addr:full":"15 Stacy Dr North Andover MA 01845",
    "addr:housenumber":"15",
    "addr:postcode":"01845",
    "addr:street":"Stacy Dr",
    "iso:country":"US",
    "sg:address":"15 Stacy Dr",
    "sg:city":"North Andover",
    "sg:classifiers":[
        {
            "category":"Wholesale",
            "subcategory":"Stationery",
            "type":"Manufacturing & Wholesale Goods"
        }
    ],
    "sg:phone":"+1 978 794 3344",
    "sg:postcode":"01845",
    "sg:province":"MA",
    "sg:tags":[
        "packaging",
        "material"
    ],
    "wof:name":"Packaging Products Trading",
    "wof:placetype":"venue"
},
  "geometry": {"coordinates":[-71.12012,42.705526],"type":"Point"}
}