{
  "type": "Feature",
  "properties": {
    "iso:country":"US",
    "sg:address":"17 Sellers St",
    "sg:city":"Cambridge",
    "sg:classifiers":[
        {
            "category":"Social Services",
            "type":"Services"
        }
    ],
    "sg:phone":"+1   ",
    "sg:postcode":"02139",
    "sg:province":"MA",
    "sg:tags":[
        "aids",
        "related"
    ],
    "wof:name":"Ccaa",
    "wof:placetype":"venue"
},
  "geometry": {"coordinates":[-71.107259,42.366767],"type":"Point"}
}