{
  "type": "Feature",
  "properties": {
    "iso:country":"US",
    "sg:address":"63 Main St",
    "sg:city":"Winthrop",
    "sg:classifiers":[
        {
            "category":"Restaurant",
            "type":"Food & Drink"
        }
    ],
    "sg:phone":"+1 617 846 7200",
    "sg:postcode":"02152",
    "sg:province":"MA",
    "sg:tags":[
        "eating",
        "italian"
    ],
    "wof:name":"Odyssey Grill",
    "wof:placetype":"venue"
},
  "geometry": {"coordinates":[-70.992075,42.38245],"type":"Point"}
}