{
  "type": "Feature",
  "properties": {
    "iso:country":"US",
    "sg:address":"47 Arlington Rd",
    "sg:city":"Wareham",
    "sg:classifiers":[
        {
            "category":"Building & Trades",
            "subcategory":"Landscaping Services",
            "type":"Services"
        }
    ],
    "sg:phone":"+1 508 291 4234",
    "sg:postcode":"02571",
    "sg:province":"MA",
    "sg:tags":[
        "landscape",
        "contractor"
    ],
    "wof:name":"Landside Services",
    "wof:placetype":"venue"
},
  "geometry": {"coordinates":[-70.674581,41.741772],"type":"Point"}
}