{
  "type": "Feature",
  "properties": {
    "iso:country":"US",
    "sg:address":"18 Bridge St",
    "sg:city":"Salem",
    "sg:classifiers":[
        {
            "category":"Real Estate",
            "subcategory":"Real Estate Agent",
            "type":"Services"
        }
    ],
    "sg:phone":"+1 978 741 0765",
    "sg:postcode":"01970",
    "sg:province":"MA",
    "sg:tags":[
        "cooperative"
    ],
    "wof:name":"Salem Bodywork Cooperative",
    "wof:placetype":"venue"
},
  "geometry": {"coordinates":[-70.886957,42.53582],"type":"Point"}
}