{
  "type": "Feature",
  "properties": {
    "addr:full": "50 Cole Pkwy Scituate MA 02066",
    "addr:housenumber": "50",
    "addr:postcode": "02066",
    "addr:street": "Cole Pkwy",
    "iso:country": "US",
    "sg:address": "50 Cole Pkwy",
    "sg:city": "Scituate",
    "sg:classifiers": [
      {
        "category": "Professional",
        "subcategory": "Lawyer \u0026 Legal Services",
        "type": "Services"
      }
    ],
    "sg:phone": "+1 781 545 2600",
    "sg:postcode": "02066",
    "sg:province": "MA",
    "sg:tags": [
      "attorney"
    ],
    "wof:name": "Loring \u0026 Robinson",
    "wof:placetype": "venue"
  },
  "geometry": {"coordinates":[-70.725487,42.193255],"type":"Point"}
}
