{
  "type": "Feature",
  "properties": {
    "addr:full":"245 N Broadway Haverhill MA 01832",
    "addr:housenumber":"245",
    "addr:postcode":"01832",
    "addr:street":"N Broadway",
    "iso:country":"US",
    "sg:address":"245 N Broadway",
    "sg:city":"Haverhill",
    "sg:classifiers":[
        {
            "category":"Building & Trades",
            "subcategory":"Construction",
            "type":"Services"
        }
    ],
    "sg:phone":"+1 978 372 1902",
    "sg:postcode":"01832",
    "sg:province":"MA",
    "sg:tags":[
        "siding",
        "contractor"
    ],
    "wof:name":"Waddingtons Window & Siding",
    "wof:placetype":"venue"
},
  "geometry": {"coordinates":[-71.11466299999999,42.790288],"type":"Point"}
}