{
  "type": "Feature",
  "properties": {
    "addr:full": "61 Billings Rd North Quincy MA 02171",
    "addr:housenumber": "61",
    "addr:postcode": "02171",
    "addr:street": "Billings Rd",
    "iso:country": "US",
    "sg:address": "61 Billings Rd",
    "sg:city": "North Quincy",
    "sg:classifiers": [
      {
        "category": "Food \u0026 Beverages",
        "subcategory": "Meat \u0026 Fish",
        "type": "Retail Goods"
      }
    ],
    "sg:phone": "+1 617 479 1540",
    "sg:postcode": "02171",
    "sg:province": "MA",
    "sg:tags": [
      "seafood"
    ],
    "wof:name": "Burke's Seafood",
    "wof:placetype": "venue"
  },
  "geometry": {"coordinates":[-71.024994,42.273502],"type":"Point"}
}
