{
  "type": "Feature",
  "properties": {
    "iso:country":"US",
    "sg:address":"61 Billings Rd",
    "sg:city":"North Quincy",
    "sg:classifiers":[
        {
            "category":"Food & Beverages",
            "subcategory":"Meat & Fish",
            "type":"Retail Goods"
        }
    ],
    "sg:phone":"+1 617 479 1540",
    "sg:postcode":"02171",
    "sg:province":"MA",
    "sg:tags":[
        "seafood"
    ],
    "wof:name":"Burke's Seafood",
    "wof:placetype":"venue"
},
  "geometry": {"coordinates":[-71.02499400000001,42.273502],"type":"Point"}
}