{
  "type": "Feature",
  "properties": {
    "addr:full": "99 Rice St Cambridge MA 02140",
    "addr:housenumber": "99",
    "addr:postcode": "02140",
    "addr:street": "Rice St",
    "iso:country": "US",
    "sg:address": "99 Rice St",
    "sg:city": "Cambridge",
    "sg:classifiers": [
      {
        "category": "Health Services",
        "subcategory": "Doctor",
        "type": "Services"
      }
    ],
    "sg:phone": "+1 617 732 5500",
    "sg:postcode": "02140",
    "sg:province": "MA",
    "wof:name": "Brigham and Women's Hospital",
    "wof:placetype": "venue"
  },
  "geometry": {"coordinates":[-71.130622,42.393706],"type":"Point"}
}
