{
  "type": "Feature",
  "properties": {
    "iso:country":"US",
    "sg:address":"8 Church St",
    "sg:city":"Westborough",
    "sg:classifiers":[
        {
            "category":"Museum",
            "type":"Entertainment"
        }
    ],
    "sg:phone":"+1 508 870 0468",
    "sg:postcode":"01581",
    "sg:province":"MA",
    "sg:tags":[
        "organization",
        "arts",
        "information"
    ],
    "wof:name":"Weaver's Guild Of Boston",
    "wof:placetype":"venue"
},
  "geometry": {"coordinates":[-71.616162,42.267373],"type":"Point"}
}