{
  "type": "Feature",
  "properties": {
    "addr:full": "16 Temple Pl Boston MA 02111",
    "addr:housenumber": "16",
    "addr:postcode": "02111",
    "addr:street": "Temple Pl",
    "iso:country": "US",
    "sg:address": "16 Temple Pl",
    "sg:city": "Boston",
    "sg:classifiers": [
      {
        "category": "Building \u0026 Trades",
        "subcategory": "Locksmith",
        "type": "Services"
      }
    ],
    "sg:phone": "+1 617 449 9818",
    "sg:postcode": "02111",
    "sg:province": "MA",
    "sg:tags": [
      "key"
    ],
    "wof:name": "Locksmith Service A",
    "wof:placetype": "venue"
  },
  "geometry": {"coordinates":[-71.062551,42.355608],"type":"Point"}
}
