{
  "type": "Feature",
  "properties": {
    "iso:country":"US",
    "sg:address":"16 Temple Pl",
    "sg:city":"Boston",
    "sg:classifiers":[
        {
            "category":"Building & Trades",
            "subcategory":"Locksmith",
            "type":"Services"
        }
    ],
    "sg:phone":"+1 617 449 9818",
    "sg:postcode":"02111",
    "sg:province":"MA",
    "sg:tags":[
        "key"
    ],
    "wof:name":"Locksmith Service A",
    "wof:placetype":"venue"
},
  "geometry": {"coordinates":[-71.062551,42.355608],"type":"Point"}
}