{
  "type": "Feature",
  "properties": {
    "addr:full": "269 Main St Woburn MA 01801",
    "addr:housenumber": "269",
    "addr:postcode": "01801",
    "addr:street": "Main St",
    "iso:country": "US",
    "sg:address": "269 Main St",
    "sg:city": "Woburn",
    "sg:classifiers": [
      {
        "category": "Professional",
        "subcategory": "Lawyer \u0026 Legal Services",
        "type": "Services"
      }
    ],
    "sg:phone": "+1 781 935 7100",
    "sg:postcode": "01801",
    "sg:province": "MA",
    "wof:name": "Tourkantonis Arthur C Atty",
    "wof:placetype": "venue"
  },
  "geometry": {"coordinates":[-71.150902,42.477001],"type":"Point"}
}
