{
  "type": "Feature",
  "properties": {
    "iso:country":"US",
    "sg:address":"465 Main St",
    "sg:city":"Rowley",
    "sg:classifiers":[
        {
            "category":"Health Services",
            "subcategory":"Health Practitioner",
            "type":"Services"
        }
    ],
    "sg:phone":"+1 978 948 5015",
    "sg:postcode":"01969",
    "sg:province":"MA",
    "sg:tags":[
        "psychologist"
    ],
    "wof:name":"Port Psychological Assoc",
    "wof:placetype":"venue"
},
  "geometry": {"coordinates":[-70.862235,42.735167],"type":"Point"}
}