{
  "type": "Feature",
  "properties": {
    "addr:full":"15 Newport Ave Exd North Quincy MA 02171",
    "addr:housenumber":"15",
    "addr:postcode":"02171",
    "addr:street":"Newport Ave Exd North",
    "iso:country":"US",
    "sg:address":"15 Newport Ave Exd",
    "sg:city":"North Quincy",
    "sg:classifiers":[
        {
            "category":"Retail",
            "subcategory":"Auto Repair",
            "type":"Services"
        }
    ],
    "sg:phone":"+1 617 472 8006",
    "sg:postcode":"02171",
    "sg:province":"MA",
    "sg:tags":[
        "automobile",
        "electric"
    ],
    "wof:name":"Mr Wires Auto Electric",
    "wof:placetype":"venue"
},
  "geometry": {"coordinates":[-71.02999699999999,42.274798],"type":"Point"}
}