{
  "type": "Feature",
  "properties": {
    "addr:full": "8 Mountain Rd Charlemont MA 01339",
    "addr:housenumber": "8",
    "addr:postcode": "01339",
    "addr:street": "Mountain Rd",
    "iso:country": "US",
    "sg:address": "8 Mountain Rd",
    "sg:city": "Charlemont",
    "sg:classifiers": [
      {
        "category": "Food \u0026 Beverages",
        "subcategory": "Cheese",
        "type": "Retail Goods"
      }
    ],
    "sg:phone": "+1 413 339 8500",
    "sg:postcode": "01339",
    "sg:province": "MA",
    "sg:website": "http://www.goatrising.com",
    "wof:name": "Goat Rising",
    "wof:placetype": "venue"
  },
  "geometry": {"coordinates":[-72.885279,42.608604],"type":"Point"}
}
