{
  "type": "Feature",
  "properties": {
    "addr:full": "64 Harvard St Brookline MA 02445",
    "addr:housenumber": "64",
    "addr:postcode": "02445",
    "addr:street": "Harvard St",
    "iso:country": "US",
    "sg:address": "64 Harvard St",
    "sg:city": "Brookline",
    "sg:classifiers": [
      {
        "category": "Professional",
        "subcategory": "Business Services",
        "type": "Services"
      }
    ],
    "sg:phone": "+1 617 734 6150",
    "sg:postcode": "02445",
    "sg:province": "MA",
    "sg:tags": [
      "interior",
      "consultant",
      "design",
      "decorator"
    ],
    "wof:name": "Interiors By The Inch",
    "wof:placetype": "venue"
  },
  "geometry": {"coordinates":[-71.119561,42.335021],"type":"Point"}
}
