{
  "type": "Feature",
  "properties": {
    "iso:country":"US",
    "sg:address":"112 State St",
    "sg:city":"Shelburne Falls",
    "sg:classifiers":[
        {
            "category":"Retail",
            "subcategory":"Animal Services",
            "type":"Services"
        }
    ],
    "sg:phone":"+1 413 625 6163",
    "sg:postcode":"01370",
    "sg:province":"MA",
    "sg:tags":[
        "pet",
        "grooming",
        "washing"
    ],
    "wof:name":"K 9 Hairfairy Pet Grooming",
    "wof:placetype":"venue"
},
  "geometry": {"coordinates":[-72.73884,42.612588],"type":"Point"}
}