{
  "type": "Feature",
  "properties": {
    "iso:country":"US",
    "sg:address":"190 American Legion Hwy",
    "sg:city":"Revere",
    "sg:classifiers":[
        {
            "category":"Professional",
            "type":"Services"
        },
        {
            "category":"Personal",
            "type":"Services"
        }
    ],
    "sg:phone":"+1 781 284 6751",
    "sg:postcode":"02151",
    "sg:province":"MA",
    "sg:tags":[
        "mover",
        "material",
        "moving",
        "services-labor"
    ],
    "wof:name":"All About Moving",
    "wof:placetype":"venue"
},
  "geometry": {"coordinates":[-71.00383100000001,42.414649],"type":"Point"}
}