{
  "type": "Feature",
  "properties": {
    "addr:full":"10 Hitchcock Rd Wilbraham MA 01095",
    "addr:housenumber":"10",
    "addr:postcode":"01095",
    "addr:street":"Hitchcock Rd",
    "iso:country":"US",
    "sg:address":"10 Hitchcock Rd",
    "sg:city":"Wilbraham",
    "sg:classifiers":[
        {
            "category":"Retail",
            "subcategory":"Repair Shop",
            "type":"Services"
        }
    ],
    "sg:phone":"+1 413 596 2394",
    "sg:postcode":"01095",
    "sg:province":"MA",
    "sg:tags":[
        "welding"
    ],
    "wof:name":"SWS/Springfield Welding Svc",
    "wof:placetype":"venue"
},
  "geometry": {"coordinates":[-72.457427,42.126991],"type":"Point"}
}