{
  "type": "Feature",
  "properties": {
    "addr:full": "Copley Pl Boston MA 02116",
    "addr:postcode": "02116",
    "addr:street": "Copley Pl",
    "iso:country": "US",
    "sg:address": "Copley Pl",
    "sg:city": "Boston",
    "sg:classifiers": [
      {
        "category": "Shopping",
        "subcategory": "Clothing, Apparel, \u0026 Fashions",
        "type": "Retail Goods"
      },
      {
        "category": "Shopping",
        "subcategory": "Luggage \u0026 Leather Goods",
        "type": "Retail Goods"
      }
    ],
    "sg:phone": "+1 617 437 6519",
    "sg:postcode": "02116",
    "sg:province": "MA",
    "wof:name": "Louis Vuitton",
    "wof:placetype": "venue"
  },
  "geometry": {"coordinates":[-71.076611,42.346756],"type":"Point"}
}
