{
  "type": "Feature",
  "properties": {
    "addr:full":"150 Middle Water St Holyoke MA 01040",
    "addr:housenumber":"150",
    "addr:postcode":"01040",
    "addr:street":"Middle Water St",
    "iso:country":"US",
    "sg:address":"150 Middle Water St",
    "sg:city":"Holyoke",
    "sg:classifiers":[
        {
            "category":"Manufacturing",
            "subcategory":"Paper Products",
            "type":"Manufacturing & Wholesale Goods"
        }
    ],
    "sg:phone":"+1 413 534 5284",
    "sg:postcode":"01040",
    "sg:province":"MA",
    "sg:tags":[
        "box"
    ],
    "sg:website":"www.uni-pac.com",
    "wof:name":"United Paper Box Co",
    "wof:placetype":"venue"
},
  "geometry": {"coordinates":[-72.60217,42.206521],"type":"Point"}
}