{
  "type": "Feature",
  "properties": {
    "addr:full": "1594 Main St Weymouth MA 02190",
    "addr:housenumber": "1594",
    "addr:postcode": "02190",
    "addr:street": "Main St",
    "iso:country": "US",
    "sg:address": "1594 Main St",
    "sg:city": "Weymouth",
    "sg:classifiers": [
      {
        "category": "Real Estate",
        "subcategory": "Real Estate Agent",
        "type": "Services"
      }
    ],
    "sg:phone": "+1 781 337 3900",
    "sg:postcode": "02190",
    "sg:province": "MA",
    "sg:tags": [
      "appraiser"
    ],
    "wof:name": "Mc Carthy Appraisal Svc",
    "wof:placetype": "venue"
  },
  "geometry": {"coordinates":[-70.955059,42.149766],"type":"Point"}
}
