{
  "type": "Feature",
  "properties": {
    "addr:full":"95 Commercial Wharf Boston MA 02110",
    "addr:housenumber":"95",
    "addr:postcode":"02110",
    "addr:street":"Commercial Wharf",
    "iso:country":"US",
    "sg:address":"95 Commercial Wharf",
    "sg:city":"Boston",
    "sg:classifiers":[
        {
            "category":"Professional",
            "subcategory":"Lawyer & Legal Services",
            "type":"Services"
        }
    ],
    "sg:phone":"+1 617 227 0146",
    "sg:postcode":"02110",
    "sg:province":"MA",
    "wof:name":"Bowser Charles",
    "wof:placetype":"venue"
},
  "geometry": {"coordinates":[-71.050422,42.361935],"type":"Point"}
}