{
  "type": "Feature",
  "properties": {
    "addr:full": "15 Hammatt St Ipswich MA 01938",
    "addr:housenumber": "15",
    "addr:postcode": "01938",
    "addr:street": "Hammatt St",
    "iso:country": "US",
    "sg:address": "15 Hammatt St",
    "sg:city": "Ipswich",
    "sg:classifiers": [
      {
        "category": "Home \u0026 Garden",
        "subcategory": "Hardware",
        "type": "Retail Goods"
      }
    ],
    "sg:phone": "+1 978 356 4304",
    "sg:postcode": "01938",
    "sg:province": "MA",
    "wof:name": "Agawam Hardware Svc",
    "wof:placetype": "venue"
  },
  "geometry": {"coordinates":[-70.840093,42.680082],"type":"Point"}
}
