{
  "type": "Feature",
  "properties": {
    "iso:country":"US",
    "sg:address":"350 Ashmont St",
    "sg:city":"Dorchester Ctr",
    "sg:classifiers":[
        {
            "category":"Real Estate",
            "subcategory":"Real Estate Agent",
            "type":"Services"
        }
    ],
    "sg:phone":"+1 617 988 5231",
    "sg:postcode":"02124",
    "sg:province":"MA",
    "sg:tags":[
        "authorities",
        "housing"
    ],
    "wof:name":"Boston Housing Authority",
    "wof:placetype":"venue"
},
  "geometry": {"coordinates":[-71.05776,42.28753],"type":"Point"}
}