{
  "type": "Feature",
  "properties": {
    "addr:full":"19 Pleasant St Second Floor Gloucester MA 01930",
    "addr:housenumber":"19",
    "addr:postcode":"01930",
    "addr:street":"Pleasant St Second Floor",
    "iso:country":"US",
    "sg:address":"19 Pleasant St Second Floor",
    "sg:city":"Gloucester",
    "sg:classifiers":[
        {
            "category":"Health Services",
            "subcategory":"Health Practitioner",
            "type":"Services"
        }
    ],
    "sg:phone":"+1 978 412 5162",
    "sg:postcode":"01930",
    "sg:province":"MA",
    "sg:tags":[
        "nutritionist",
        "dietitian"
    ],
    "wof:name":"Art of Healing",
    "wof:placetype":"venue"
},
  "geometry": {"coordinates":[-70.66185,42.613461],"type":"Point"}
}