{
  "type": "Feature",
  "properties": {
    "addr:full":"486 Chandler St Tewksbury MA 01876",
    "addr:housenumber":"486",
    "addr:postcode":"01876",
    "addr:street":"Chandler St",
    "iso:country":"US",
    "sg:address":"486 Chandler St",
    "sg:city":"Tewksbury",
    "sg:classifiers":[
        {
            "category":"Organizations",
            "subcategory":"Religious Organization",
            "type":"Services"
        }
    ],
    "sg:phone":"+1 978 851 2462",
    "sg:postcode":"01876",
    "sg:province":"MA",
    "sg:tags":[
        "monastery",
        "convent"
    ],
    "wof:name":"Little Sisters-The Holy Family",
    "wof:placetype":"venue"
},
  "geometry": {"coordinates":[-71.227608,42.604203],"type":"Point"}
}