{
  "type": "Feature",
  "properties": {
    "iso:country":"US",
    "sg:address":"255 Lincoln Ave",
    "sg:city":"Haverhill",
    "sg:classifiers":[
        {
            "category":"Shopping",
            "subcategory":"Mobile Phones",
            "type":"Retail Goods"
        }
    ],
    "sg:phone":"+1 978 372 3003",
    "sg:postcode":"01830",
    "sg:province":"MA",
    "sg:website":"www.radioshack.com",
    "wof:name":"Radioshack",
    "wof:placetype":"venue"
},
  "geometry": {"coordinates":[-71.038251,42.764284],"type":"Point"}
}