{
  "type": "Feature",
  "properties": {
    "addr:full":"1426 Main St Palmer MA 01069",
    "addr:housenumber":"1426",
    "addr:postcode":"01069",
    "addr:street":"Main St",
    "iso:country":"US",
    "sg:address":"1426 Main St",
    "sg:city":"Palmer",
    "sg:classifiers":[
        {
            "category":"Shopping",
            "subcategory":"Clothing, Apparel, & Fashions",
            "type":"Retail Goods"
        }
    ],
    "sg:phone":"+1 413 283 6300",
    "sg:postcode":"01069",
    "sg:province":"MA",
    "sg:tags":[
        "shop",
        "bridal"
    ],
    "wof:name":"Belchertown Bridal",
    "wof:placetype":"venue"
},
  "geometry": {"coordinates":[-72.329837,42.157237],"type":"Point"}
}