{
  "type": "Feature",
  "properties": {
    "addr:full":"5 Norcross St Worcester MA 01602",
    "addr:housenumber":"5",
    "addr:postcode":"01602",
    "addr:street":"Norcross St",
    "iso:country":"US",
    "sg:address":"5 Norcross St",
    "sg:city":"Worcester",
    "sg:classifiers":[
        {
            "category":"Professional",
            "subcategory":"Art Services",
            "type":"Services"
        },
        {
            "category":"Professional",
            "subcategory":"Business Services",
            "type":"Services"
        }
    ],
    "sg:phone":"+1 508 831 1170",
    "sg:postcode":"01602",
    "sg:province":"MA",
    "sg:tags":[
        "development",
        "product",
        "graphic",
        "designers-industrial",
        "marketing",
        "commercial",
        "designer",
        "design"
    ],
    "wof:name":"Miglionico Design",
    "wof:placetype":"venue"
},
  "geometry": {"coordinates":[-71.832588,42.262275],"type":"Point"}
}