{
  "type": "Feature",
  "properties": {
    "iso:country":"US",
    "sg:address":"95 Walkers Brook Dr",
    "sg:city":"Reading",
    "sg:classifiers":[
        {
            "category":"Professional",
            "subcategory":"Management & Consulting",
            "type":"Services"
        }
    ],
    "sg:phone":"+1 781 942 0600",
    "sg:postcode":"01867",
    "sg:province":"MA",
    "sg:tags":[
        "consultant",
        "business"
    ],
    "wof:name":"Aristonics",
    "wof:placetype":"venue"
},
  "geometry": {"coordinates":[-71.091532,42.517679],"type":"Point"}
}