{
  "type": "Feature",
  "properties": {
    "iso:country":"US",
    "sg:address":"85 Hudson Rd",
    "sg:city":"Stow",
    "sg:classifiers":[
        {
            "category":"Manufacturing",
            "subcategory":"Tools & Machinery",
            "type":"Manufacturing & Wholesale Goods"
        }
    ],
    "sg:phone":"+1 978 897 4647",
    "sg:postcode":"01775",
    "sg:province":"MA",
    "sg:tags":[
        "ind",
        "general"
    ],
    "sg:website":"www.hydro-test.com",
    "wof:name":"Hydro-Test Products Inc",
    "wof:placetype":"venue"
},
  "geometry": {"coordinates":[-71.536224,42.424516],"type":"Point"}
}