{
  "type": "Feature",
  "properties": {
    "addr:full": "85 Hudson Rd Stow MA 01775",
    "addr:housenumber": "85",
    "addr:postcode": "01775",
    "addr:street": "Hudson Rd",
    "iso:country": "US",
    "ovtr:label": "Hydro-Test Products, 85 Hudson Rd Stow MA US",
    "ovtr:similarity": 3.292973041534424,
    "sg:address": "85 Hudson Rd",
    "sg:city": "Stow",
    "sg:classifiers": [
      {
        "category": "Manufacturing",
        "subcategory": "Tools \u0026 Machinery",
        "type": "Manufacturing \u0026 Wholesale Goods"
      }
    ],
    "sg:phone": "+1 978 897 4647",
    "sg:postcode": "01775",
    "sg:province": "MA",
    "sg:tags": [
      "ind",
      "general"
    ],
    "sg:website": "www.hydro-test.com",
    "wof:name": "Hydro-Test Products Inc",
    "wof:placetype": "venue"
  },
  "geometry": {"coordinates":[-71.536224,42.424516],"type":"Point"}
}
