{
  "type": "Feature",
  "properties": {
    "iso:country":"US",
    "sg:address":"126 County Rd",
    "sg:city":"Ipswich",
    "sg:classifiers":[
        {
            "category":"Social Services",
            "subcategory":"Child Care",
            "type":"Services"
        }
    ],
    "sg:phone":"+1 978 356 6464",
    "sg:postcode":"01938",
    "sg:province":"MA",
    "wof:name":"Run A Muck",
    "wof:placetype":"venue"
},
  "geometry": {"coordinates":[-70.838718,42.666709],"type":"Point"}
}