{
  "type": "Feature",
  "properties": {
    "addr:full": "293 Montvale Ave Woburn MA 01801",
    "addr:housenumber": "293",
    "addr:postcode": "01801",
    "addr:street": "Montvale Ave",
    "iso:country": "US",
    "sg:address": "293 Montvale Ave",
    "sg:city": "Woburn",
    "sg:classifiers": [
      {
        "category": "Autos \u0026 Motor Vehicles",
        "subcategory": "Fuel \u0026 Gas Station",
        "type": "Retail Goods"
      }
    ],
    "sg:phone": "+1 781 932 8954",
    "sg:postcode": "01801",
    "sg:province": "MA",
    "sg:tags": [
      "oil"
    ],
    "wof:name": "Joes Auto Servis Ctr",
    "wof:placetype": "venue"
  },
  "geometry": {"coordinates":[-71.122876,42.479743],"type":"Point"}
}
