{
  "type": "Feature",
  "properties": {
    "iso:country":"US",
    "sg:address":"1 Hill St",
    "sg:city":"Lexington",
    "sg:classifiers":[
        {
            "category":"Professional",
            "subcategory":"Accounting & Tax Preparation",
            "type":"Services"
        }
    ],
    "sg:phone":"+1 781 861 7294",
    "sg:postcode":"02421",
    "sg:province":"MA",
    "sg:tags":[
        "accountant"
    ],
    "wof:name":"Sagan & Sagan",
    "wof:placetype":"venue"
},
  "geometry": {"coordinates":[-71.236485,42.455608],"type":"Point"}
}