{
  "type": "Feature",
  "properties": {
    "addr:full": "177 Lewis St Lynn MA 01902",
    "addr:housenumber": "177",
    "addr:postcode": "01902",
    "addr:street": "Lewis St",
    "iso:country": "US",
    "sg:address": "177 Lewis St",
    "sg:city": "Lynn",
    "sg:classifiers": [
      {
        "category": "Insurance",
        "subcategory": "Hazard Insurance",
        "type": "Services"
      }
    ],
    "sg:phone": "+1 781 558 3281",
    "sg:postcode": "01902",
    "sg:province": "MA",
    "sg:tags": [
      "commercial",
      "business"
    ],
    "sg:website": "http://www.goldeninsuranceinc.com",
    "wof:name": "Golden Insurance Inc.",
    "wof:placetype": "venue"
  },
  "geometry": {"coordinates":[-70.93293,42.465359],"type":"Point"}
}
