{
  "type": "Feature",
  "properties": {
    "addr:full":"9 Esther Dr Milford MA 01757",
    "addr:housenumber":"9",
    "addr:postcode":"01757",
    "addr:street":"Esther Dr",
    "iso:country":"US",
    "sg:address":"9 Esther Dr",
    "sg:city":"Milford",
    "sg:classifiers":[
        {
            "category":"Building & Trades",
            "subcategory":"Construction",
            "type":"Services"
        }
    ],
    "sg:phone":"+1 508 473 6563",
    "sg:postcode":"01757",
    "sg:province":"MA",
    "sg:tags":[
        "plastering",
        "contractor"
    ],
    "wof:name":"Harris Construction Corp",
    "wof:placetype":"venue"
},
  "geometry": {"coordinates":[-71.539751,42.180052],"type":"Point"}
}