{
  "type": "Feature",
  "properties": {
    "iso:country":"US",
    "sg:address":"40 W Chester St",
    "sg:city":"Nantucket",
    "sg:classifiers":[
        {
            "category":"Travel",
            "subcategory":"Hotels & Motels",
            "type":"Entertainment"
        }
    ],
    "sg:phone":"+1 508 228 2740",
    "sg:postcode":"02554",
    "sg:province":"MA",
    "sg:tags":[
        "operation"
    ],
    "wof:name":"40 West Chester",
    "wof:placetype":"venue"
},
  "geometry": {"coordinates":[-70.108103,41.286716],"type":"Point"}
}