{
  "type": "Feature",
  "properties": {
    "iso:country":"US",
    "sg:address":"153 Chandler Rd",
    "sg:city":"Andover",
    "sg:classifiers":[
        {
            "category":"Recreation",
            "type":"Entertainment"
        }
    ],
    "sg:phone":"+1 978 688 5522",
    "sg:postcode":"01810",
    "sg:province":"MA",
    "sg:tags":[
        "range",
        "practice",
        "golf"
    ],
    "wof:name":"Sarkisian Farms & Driving Rnge",
    "wof:placetype":"venue"
},
  "geometry": {"coordinates":[-71.200158,42.677248],"type":"Point"}
}