{
  "type": "Feature",
  "properties": {
    "iso:country":"US",
    "sg:address":"3 Oak St",
    "sg:city":"Shrewsbury",
    "sg:classifiers":[
        {
            "category":"Health Services",
            "subcategory":"Doctor",
            "type":"Services"
        }
    ],
    "sg:phone":"+1 508 842 8908",
    "sg:postcode":"01545",
    "sg:province":"MA",
    "sg:tags":[
        "dentist"
    ],
    "wof:name":"Peter J Alizzeo DDS",
    "wof:placetype":"venue"
},
  "geometry": {"coordinates":[-71.72801699999999,42.285633],"type":"Point"}
}