{
  "type": "Feature",
  "properties": {
    "addr:full":"1355 Central St Leominster MA 01453",
    "addr:housenumber":"1355",
    "addr:postcode":"01453",
    "addr:street":"Central St",
    "iso:country":"US",
    "sg:address":"1355 Central St",
    "sg:city":"Leominster",
    "sg:classifiers":[
        {
            "category":"Personal",
            "subcategory":"Beauty Salon",
            "type":"Services"
        }
    ],
    "sg:phone":"+1 978 537 7077",
    "sg:postcode":"01453",
    "sg:province":"MA",
    "sg:tags":[
        "shop"
    ],
    "wof:name":"All About Nails",
    "wof:placetype":"venue"
},
  "geometry": {"coordinates":[-71.747728,42.487146],"type":"Point"}
}