{
  "type": "Feature",
  "properties": {
    "iso:country":"US",
    "sg:address":"1001 S Main St",
    "sg:city":"Bellingham",
    "sg:classifiers":[
        {
            "category":"Bus Charters",
            "type":"Transportation"
        }
    ],
    "sg:phone":"+1 508 883 6180",
    "sg:postcode":"02019",
    "sg:province":"MA",
    "sg:tags":[
        "rental"
    ],
    "wof:name":"Vendetti Buses",
    "wof:placetype":"venue"
},
  "geometry": {"coordinates":[-71.47523,42.068799],"type":"Point"}
}