{
  "type": "Feature",
  "properties": {
    "addr:full": "489 Washington St Boston MA 02111",
    "addr:housenumber": "489",
    "addr:postcode": "02111",
    "addr:street": "Washington St",
    "iso:country": "US",
    "sg:address": "489 Washington St",
    "sg:city": "Boston",
    "sg:classifiers": [
      {
        "category": "Shopping",
        "subcategory": "Shoes",
        "type": "Retail Goods"
      }
    ],
    "sg:phone": "+1 617 338 6008",
    "sg:postcode": "02111",
    "sg:province": "MA",
    "sg:tags": [
      "store"
    ],
    "sg:website": "footpathsshoes.com",
    "wof:name": "Foot Paths",
    "wof:placetype": "venue"
  },
  "geometry": {"coordinates":[-71.061355,42.354723],"type":"Point"}
}
