{
  "type": "Feature",
  "properties": {
    "iso:country":"US",
    "sg:address":"489 Washington St",
    "sg:city":"Boston",
    "sg:classifiers":[
        {
            "category":"Shopping",
            "subcategory":"Shoes",
            "type":"Retail Goods"
        }
    ],
    "sg:phone":"+1 617 338 6008",
    "sg:postcode":"02111",
    "sg:province":"MA",
    "sg:tags":[
        "store"
    ],
    "sg:website":"footpathsshoes.com",
    "wof:name":"Foot Paths",
    "wof:placetype":"venue"
},
  "geometry": {"coordinates":[-71.06135500000001,42.354723],"type":"Point"}
}