{
  "type": "Feature",
  "properties": {
    "addr:full":"380 Forest St West Bridgewater MA 02379",
    "addr:housenumber":"380",
    "addr:postcode":"02379",
    "addr:street":"Forest St",
    "iso:country":"US",
    "sg:address":"380 Forest St",
    "sg:city":"West Bridgewater",
    "sg:classifiers":[
        {
            "category":"Building & Trades",
            "subcategory":"Construction",
            "type":"Services"
        }
    ],
    "sg:phone":"+1 508 269 9287",
    "sg:postcode":"02379",
    "sg:province":"MA",
    "sg:tags":[
        "masonry",
        "contractor"
    ],
    "wof:name":"Deluca Masonry",
    "wof:placetype":"venue"
},
  "geometry": {"coordinates":[-71.01197000000001,42.006658],"type":"Point"}
}