{
  "type": "Feature",
  "properties": {
    "addr:full": "80 Yorktown St Somerville MA 02144",
    "addr:housenumber": "80",
    "addr:postcode": "02144",
    "addr:street": "Yorktown St",
    "iso:country": "US",
    "sg:address": "80 Yorktown St",
    "sg:city": "Somerville",
    "sg:classifiers": [
      {
        "category": "Professional",
        "subcategory": "Business Services",
        "type": "Services"
      }
    ],
    "sg:phone": "+1   ",
    "sg:postcode": "02144",
    "sg:province": "MA",
    "wof:name": "Spectre Design Solutions Inc",
    "wof:placetype": "venue"
  },
  "geometry": {"coordinates":[-71.129585,42.39983],"type":"Point"}
}
