{
  "type": "Feature",
  "properties": {
    "addr:full": "111 Huntington Avenue Fl 6 Boston MA 02199",
    "addr:housenumber": "111;6",
    "addr:postcode": "02199",
    "addr:street": "Huntington Avenue Fl",
    "iso:country": "US",
    "sg:address": "111 Huntington Avenue Fl 6",
    "sg:city": "Boston",
    "sg:classifiers": [
      {
        "category": "Professional",
        "subcategory": "Lawyer \u0026 Legal Services",
        "type": "Services"
      }
    ],
    "sg:phone": "+1 617 239 0250",
    "sg:postcode": "02199",
    "sg:province": "MA",
    "wof:name": "D'antuono Karen Atty",
    "wof:placetype": "venue"
  },
  "geometry": {"coordinates":[-71.081631,42.34893],"type":"Point"}
}
