{
  "type": "Feature",
  "properties": {
    "addr:full":"1429 Hilldale Ave Haverhill MA 01832",
    "addr:housenumber":"1429",
    "addr:postcode":"01832",
    "addr:street":"Hilldale Ave",
    "iso:country":"US",
    "sg:address":"1429 Hilldale Ave",
    "sg:city":"Haverhill",
    "sg:classifiers":[
        {
            "category":"Manufacturing",
            "subcategory":"Chemicals & Compounds",
            "type":"Manufacturing & Wholesale Goods"
        },
        {
            "category":"Shopping",
            "subcategory":"Pharmacy",
            "type":"Retail Goods"
        }
    ],
    "sg:phone":"+1 978 374 5200",
    "sg:postcode":"01832",
    "sg:province":"MA",
    "sg:tags":[
        "medicines-patent",
        "manufacturer",
        "proprietary",
        "chemicals-wholesale"
    ],
    "wof:name":"Safc Hitech, Inc.",
    "wof:placetype":"venue"
},
  "geometry": {"coordinates":[-71.116665,42.816685],"type":"Point"}
}