{
  "type": "Feature",
  "properties": {
    "iso:country":"US",
    "sg:address":"342 Pearl St",
    "sg:city":"Malden",
    "sg:classifiers":[
        {
            "category":"Bakery",
            "type":"Food & Drink"
        }
    ],
    "sg:phone":"+1 781 288 0291",
    "sg:postcode":"02148",
    "sg:province":"MA",
    "wof:name":"Late Night Cookies",
    "wof:placetype":"venue"
},
  "geometry": {"coordinates":[-71.07766700000001,42.417915],"type":"Point"}
}