{
  "type": "Feature",
  "properties": {
    "addr:full":"14 Lakeview Cir Sutton MA 01590",
    "addr:housenumber":"14",
    "addr:postcode":"01590",
    "addr:street":"Lakeview Cir",
    "iso:country":"US",
    "sg:address":"14 Lakeview Cir",
    "sg:city":"Sutton",
    "sg:classifiers":[
        {
            "category":"Wholesale",
            "subcategory":"Machinery & Supplies",
            "type":"Manufacturing & Wholesale Goods"
        }
    ],
    "sg:phone":"+1 508 234 8888",
    "sg:postcode":"01590",
    "sg:province":"MA",
    "sg:tags":[
        "tool"
    ],
    "wof:name":"Fitta Hendricks Assoc",
    "wof:placetype":"venue"
},
  "geometry": {"coordinates":[-71.68696199999999,42.101861],"type":"Point"}
}