{
  "type": "Feature",
  "properties": {
    "addr:full": "14 Lakeview Cir Sutton MA 01590",
    "addr:housenumber": "14",
    "addr:postcode": "01590",
    "addr:street": "Lakeview Cir",
    "iso:country": "US",
    "sg:address": "14 Lakeview Cir",
    "sg:city": "Sutton",
    "sg:classifiers": [
      {
        "category": "Wholesale",
        "subcategory": "Machinery \u0026 Supplies",
        "type": "Manufacturing \u0026 Wholesale Goods"
      }
    ],
    "sg:phone": "+1 508 234 8888",
    "sg:postcode": "01590",
    "sg:province": "MA",
    "sg:tags": [
      "tool"
    ],
    "wof:name": "Fitta Hendricks Assoc",
    "wof:placetype": "venue"
  },
  "geometry": {"coordinates":[-71.686962,42.101861],"type":"Point"}
}
