{
  "type": "Feature",
  "properties": {
    "addr:full": "414 Ashley Blvd New Bedford MA 02745",
    "addr:housenumber": "414",
    "addr:postcode": "02745",
    "addr:street": "Ashley Blvd",
    "iso:country": "US",
    "sg:address": "414 Ashley Blvd",
    "sg:city": "New Bedford",
    "sg:classifiers": [
      {
        "category": "Shopping",
        "subcategory": "Computers \u0026 Home Electronics",
        "type": "Retail Goods"
      }
    ],
    "sg:phone": "+1 508 996 5820",
    "sg:postcode": "02745",
    "sg:province": "MA",
    "sg:tags": [
      "audio"
    ],
    "wof:name": "Image Audio",
    "wof:placetype": "venue"
  },
  "geometry": {"coordinates":[-70.931193,41.66782],"type":"Point"}
}
