{
  "type": "Feature",
  "properties": {
    "iso:country":"US",
    "sg:address":"50 Dalton St",
    "sg:city":"Boston",
    "sg:classifiers":[
        {
            "category":"Cinema",
            "subcategory":"Movie Theater",
            "type":"Entertainment"
        }
    ],
    "sg:phone":"+1 617 536 2870",
    "sg:postcode":"02115",
    "sg:province":"MA",
    "wof:name":"Sony/Loews Theatres",
    "wof:placetype":"venue"
},
  "geometry": {"coordinates":[-71.08503,42.346737],"type":"Point"}
}