{
  "type": "Feature",
  "properties": {
    "addr:full":"7 Fieldstone Ln Milton MA 02186",
    "addr:housenumber":"7",
    "addr:postcode":"02186",
    "addr:street":"Fieldstone Ln",
    "iso:country":"US",
    "sg:address":"7 Fieldstone Ln",
    "sg:city":"Milton",
    "sg:classifiers":[
        {
            "category":"Professional",
            "subcategory":"Management & Consulting",
            "type":"Services"
        }
    ],
    "sg:phone":"+1 617 698 1242",
    "sg:postcode":"02186",
    "sg:province":"MA",
    "sg:tags":[
        "personnel",
        "consultant"
    ],
    "wof:name":"Astrue Coakley & Garloo Inc",
    "wof:placetype":"venue"
},
  "geometry": {"coordinates":[-71.085139,42.262491],"type":"Point"}
}