{
  "type": "Feature",
  "properties": {
    "iso:country":"US",
    "sg:address":"22 Hilliard St",
    "sg:city":"Cambridge",
    "sg:classifiers":[
        {
            "category":"Personal",
            "subcategory":"Massage",
            "type":"Services"
        }
    ],
    "sg:phone":"+1 617 876 0196",
    "sg:postcode":"02138",
    "sg:province":"MA",
    "wof:name":"Sandra N Daitch, Lic Massage",
    "wof:placetype":"venue"
},
  "geometry": {"coordinates":[-71.123878,42.373976],"type":"Point"}
}