{
  "type": "Feature",
  "properties": {
    "addr:full":"6 Stoneybrook Cir Andover MA 01810",
    "addr:housenumber":"6",
    "addr:postcode":"01810",
    "addr:street":"Stoneybrook Cir",
    "iso:country":"US",
    "sg:address":"6 Stoneybrook Cir",
    "sg:city":"Andover",
    "sg:classifiers":[
        {
            "category":"Shopping",
            "type":"Retail Goods"
        }
    ],
    "sg:phone":"+1 978 689 4041",
    "sg:postcode":"01810",
    "sg:province":"MA",
    "sg:tags":[
        "product",
        "wood"
    ],
    "wof:name":"Wood Carver Inc",
    "wof:placetype":"venue"
},
  "geometry": {"coordinates":[-71.235738,42.660581],"type":"Point"}
}