{
  "type": "Feature",
  "properties": {
    "iso:country":"US",
    "sg:address":"23 Davedon Dr",
    "sg:city":"East Falmouth",
    "sg:classifiers":[
        {
            "category":"Professional",
            "subcategory":"Computer Services",
            "type":"Services"
        }
    ],
    "sg:phone":"+1   ",
    "sg:postcode":"02536",
    "sg:province":"MA",
    "sg:tags":[
        "engineering",
        "consulting",
        "software"
    ],
    "wof:name":"Christine D Scott",
    "wof:placetype":"venue"
},
  "geometry": {"coordinates":[-70.59715,41.585487],"type":"Point"}
}