{
  "type": "Feature",
  "properties": {
    "iso:country":"US",
    "sg:address":"1875 Commonwealth Ave",
    "sg:city":"Auburndale",
    "sg:classifiers":[
        {
            "category":"Health Services",
            "subcategory":"Health Practitioner",
            "type":"Services"
        }
    ],
    "sg:phone":"+1 617 527 7034",
    "sg:postcode":"02466",
    "sg:province":"MA",
    "sg:tags":[
        "massage"
    ],
    "wof:name":"Stockton Dbrah J Msclar Thrapy",
    "wof:placetype":"venue"
},
  "geometry": {"coordinates":[-71.24117200000001,42.343874],"type":"Point"}
}