{
  "type": "Feature",
  "properties": {
    "iso:country":"US",
    "sg:address":"146 Main St",
    "sg:city":"Saugus",
    "sg:classifiers":[
        {
            "category":"Building & Trades",
            "subcategory":"Construction",
            "type":"Services"
        }
    ],
    "sg:phone":"+1 781 231 2053",
    "sg:postcode":"01906",
    "sg:province":"MA",
    "sg:tags":[
        "masonry",
        "contractor"
    ],
    "wof:name":"J G Masonry Inc",
    "wof:placetype":"venue"
},
  "geometry": {"coordinates":[-71.022211,42.464664],"type":"Point"}
}