{
  "type": "Feature",
  "properties": {
    "addr:full": "146 Main St Saugus MA 01906",
    "addr:housenumber": "146",
    "addr:postcode": "01906",
    "addr:street": "Main St",
    "iso:country": "US",
    "sg:address": "146 Main St",
    "sg:city": "Saugus",
    "sg:classifiers": [
      {
        "category": "Building \u0026 Trades",
        "subcategory": "Construction",
        "type": "Services"
      }
    ],
    "sg:phone": "+1 781 231 2053",
    "sg:postcode": "01906",
    "sg:province": "MA",
    "sg:tags": [
      "masonry",
      "contractor"
    ],
    "wof:name": "J G Masonry Inc",
    "wof:placetype": "venue"
  },
  "geometry": {"coordinates":[-71.022211,42.464664],"type":"Point"}
}
