{
  "type": "Feature",
  "properties": {
    "addr:full": "21 Blandin Ave Framingham MA 01702",
    "addr:housenumber": "21",
    "addr:postcode": "01702",
    "addr:street": "Blandin Ave",
    "iso:country": "US",
    "sg:address": "21 Blandin Ave",
    "sg:city": "Framingham",
    "sg:classifiers": [
      {
        "category": "Professional",
        "subcategory": "Advertising",
        "type": "Services"
      }
    ],
    "sg:phone": "+1 508 626 0700",
    "sg:postcode": "01702",
    "sg:province": "MA",
    "sg:tags": [
      "display",
      "convention"
    ],
    "wof:name": "Tigermark",
    "wof:placetype": "venue"
  },
  "geometry": {"coordinates":[-71.409211,42.277651],"type":"Point"}
}
