{
  "type": "Feature",
  "properties": {
    "addr:full":"39 Salisbury St Ste 3 Worcester MA 01609",
    "addr:housenumber":"39",
    "addr:postcode":"01609",
    "addr:street":"Salisbury St Ste 3",
    "iso:country":"US",
    "sg:address":"39 Salisbury St Ste 3",
    "sg:city":"Worcester",
    "sg:classifiers":[
        {
            "category":"Health Services",
            "subcategory":"Hospital",
            "type":"Services"
        },
        {
            "category":"Health Services",
            "subcategory":"Nursing And Care Facility",
            "type":"Services"
        },
        {
            "category":"Health Services",
            "subcategory":"Health Practitioner",
            "type":"Services"
        }
    ],
    "sg:phone":"+1 508 755 1133",
    "sg:postcode":"01609",
    "sg:province":"MA",
    "sg:tags":[
        "physician",
        "assistant",
        "registry",
        "home",
        "nurse",
        "eldercare-home"
    ],
    "wof:name":"Diversified Staffing Group Inc",
    "wof:placetype":"venue"
},
  "geometry": {"coordinates":[-71.800331,42.273331],"type":"Point"}
}