{
  "type": "Feature",
  "properties": {
    "addr:full": "7 S Main St Uxbridge MA 01569",
    "addr:housenumber": "7",
    "addr:postcode": "01569",
    "addr:street": "S Main St",
    "iso:country": "US",
    "ovtr:label": "Harry's Famous Pizza, 6 S Main St Uxbridge MA US",
    "ovtr:similarity": 3.5651869773864746,
    "sg:address": "7 S Main St",
    "sg:city": "Uxbridge",
    "sg:classifiers": [
      {
        "category": "Restaurant",
        "type": "Food \u0026 Drink"
      }
    ],
    "sg:phone": "+1 508 278 2114",
    "sg:postcode": "01569",
    "sg:province": "MA",
    "wof:name": "Harry's Famous Pizza",
    "wof:placetype": "venue"
  },
  "geometry": {"coordinates":[-71.629423,42.076307],"type":"Point"}
}
