{
  "type": "Feature",
  "properties": {
    "iso:country":"US",
    "sg:address":"7 S Main St",
    "sg:city":"Uxbridge",
    "sg:classifiers":[
        {
            "category":"Restaurant",
            "type":"Food & Drink"
        }
    ],
    "sg:phone":"+1 508 278 2114",
    "sg:postcode":"01569",
    "sg:province":"MA",
    "wof:name":"Harry's Famous Pizza",
    "wof:placetype":"venue"
},
  "geometry": {"coordinates":[-71.629423,42.076307],"type":"Point"}
}