{
  "type": "Feature",
  "properties": {
    "iso:country":"US",
    "sg:address":"106 Mount Auburn St",
    "sg:city":"Watertown",
    "sg:classifiers":[
        {
            "category":"Health Services",
            "subcategory":"Doctor",
            "type":"Services"
        }
    ],
    "sg:phone":"+1 617 926 1013",
    "sg:postcode":"02472",
    "sg:province":"MA",
    "sg:tags":[
        "dentist"
    ],
    "wof:name":"Serge Dibart DDS",
    "wof:placetype":"venue"
},
  "geometry": {"coordinates":[-71.179366,42.367695],"type":"Point"}
}