{
  "type": "Feature",
  "properties": {
    "iso:country":"US",
    "sg:address":"372 Vale St",
    "sg:city":"Fall River",
    "sg:classifiers":[
        {
            "category":"Manufacturing",
            "subcategory":"Apparel",
            "type":"Manufacturing & Wholesale Goods"
        }
    ],
    "sg:phone":"+1 508 679 2213",
    "sg:postcode":"02724",
    "sg:province":"MA",
    "sg:tags":[
        "sewing",
        "contractor"
    ],
    "wof:name":"S & S Accessories Mfg",
    "wof:placetype":"venue"
},
  "geometry": {"coordinates":[-71.165767,41.683633],"type":"Point"}
}