{
  "type": "Feature",
  "properties": {
    "addr:full": "372 Vale St Fall River MA 02724",
    "addr:housenumber": "372",
    "addr:postcode": "02724",
    "addr:street": "Vale St",
    "iso:country": "US",
    "sg:address": "372 Vale St",
    "sg:city": "Fall River",
    "sg:classifiers": [
      {
        "category": "Manufacturing",
        "subcategory": "Apparel",
        "type": "Manufacturing \u0026 Wholesale Goods"
      }
    ],
    "sg:phone": "+1 508 679 2213",
    "sg:postcode": "02724",
    "sg:province": "MA",
    "sg:tags": [
      "sewing",
      "contractor"
    ],
    "wof:name": "S \u0026 S Accessories Mfg",
    "wof:placetype": "venue"
  },
  "geometry": {"coordinates":[-71.165767,41.683633],"type":"Point"}
}
