{
  "type": "Feature",
  "properties": {
    "addr:full":"585 E Washington St Unit 4 North Attleboro MA 02760",
    "addr:housenumber":"585",
    "addr:postcode":"02760",
    "addr:street":"E Washington St Unit 4",
    "iso:country":"US",
    "sg:address":"585 E Washington St Unit 4",
    "sg:city":"North Attleboro",
    "sg:classifiers":[
        {
            "category":"Shopping",
            "subcategory":"Bicycles & Sporting Goods",
            "type":"Retail Goods"
        }
    ],
    "sg:phone":"+1 508 699 2220",
    "sg:postcode":"02760",
    "sg:province":"MA",
    "wof:name":"Strike Zone Sports",
    "wof:placetype":"venue"
},
  "geometry": {"coordinates":[-71.328039,41.983569],"type":"Point"}
}