{
  "type": "Feature",
  "properties": {
    "iso:country":"US",
    "sg:address":"281 Hartford Ave W",
    "sg:city":"Uxbridge",
    "sg:classifiers":[
        {
            "category":"Health Services",
            "subcategory":"Doctor",
            "type":"Services"
        }
    ],
    "sg:phone":"+1 508 334 1000",
    "sg:postcode":"01569",
    "sg:province":"MA",
    "sg:tags":[
        "physician",
        "surgeon"
    ],
    "wof:name":"Hayley M Drohan DO",
    "wof:placetype":"venue"
},
  "geometry": {"coordinates":[-71.652778,42.089216],"type":"Point"}
}