{
  "type": "Feature",
  "properties": {
    "addr:full": "59 Temple St Whitman MA 02382",
    "addr:housenumber": "59",
    "addr:postcode": "02382",
    "addr:street": "Temple St",
    "iso:country": "US",
    "sg:address": "59 Temple St",
    "sg:city": "Whitman",
    "sg:classifiers": [
      {
        "category": "Building \u0026 Trades",
        "subcategory": "Construction",
        "type": "Services"
      }
    ],
    "sg:phone": "+1   ",
    "sg:postcode": "02382",
    "sg:province": "MA",
    "sg:tags": [
      "contractor"
    ],
    "wof:name": "Stone Design Inc",
    "wof:placetype": "venue"
  },
  "geometry": {"coordinates":[-70.939572,42.080483],"type":"Point"}
}
