{
  "type": "Feature",
  "properties": {
    "addr:full":"292 Main St Ste I Northborough MA 01532",
    "addr:housenumber":"292",
    "addr:postcode":"01532",
    "addr:street":"Main St Ste I",
    "iso:country":"US",
    "sg:address":"292 Main St Ste I",
    "sg:city":"Northborough",
    "sg:classifiers":[
        {
            "category":"Professional",
            "subcategory":"Computer Services",
            "type":"Services"
        }
    ],
    "sg:phone":"+1 617 921 0100",
    "sg:postcode":"01532",
    "sg:province":"MA",
    "sg:tags":[
        "consultant",
        "designer",
        "system"
    ],
    "wof:name":"Gopi Bala",
    "wof:placetype":"venue"
},
  "geometry": {"coordinates":[-71.619919,42.32803],"type":"Point"}
}