{
  "type": "Feature",
  "properties": {
    "iso:country":"US",
    "sg:address":"134 3rd St",
    "sg:city":"Leominster",
    "sg:classifiers":[
        {
            "category":"Personal",
            "subcategory":"Beauty Salon",
            "type":"Services"
        }
    ],
    "sg:phone":"+1 978 537 5538",
    "sg:postcode":"01453",
    "sg:province":"MA",
    "wof:name":"New Beginnings Beauty Salon",
    "wof:placetype":"venue"
},
  "geometry": {"coordinates":[-71.751367,42.523711],"type":"Point"}
}